{
  "type": "Feature",
  "properties": {
    "iso:country":"US",
    "sg:address":"1725 I St",
    "sg:city":"Sacramento",
    "sg:classifiers":[
        {
            "category":"Restaurant",
            "type":"Food & Drink"
        }
    ],
    "sg:phone":"+1 916 446 5012",
    "sg:postcode":"95814",
    "sg:province":"CA",
    "sg:tags":[
        "italian"
    ],
    "wof:name":"Michelangelo's",
    "wof:placetype":"venue"
},
  "geometry": {"coordinates":[-121.483045,38.578783],"type":"Point"}
}