{
  "type": "Feature",
  "properties": {
    "addr:full":"8611 Carlisle Ave Sacramento CA 95828",
    "addr:housenumber":"8611",
    "addr:postcode":"95828",
    "addr:street":"Carlisle Ave",
    "iso:country":"US",
    "sg:address":"8611 Carlisle Ave",
    "sg:city":"Sacramento",
    "sg:classifiers":[
        {
            "category":"Professional",
            "type":"Services"
        }
    ],
    "sg:phone":"+1 916 423 1302",
    "sg:postcode":"95828",
    "sg:province":"CA",
    "sg:tags":[
        "animal"
    ],
    "wof:name":"Ducks On The Green Kennels",
    "wof:placetype":"venue"
},
  "geometry": {"coordinates":[-121.386315,38.469058],"type":"Point"}
}