{
  "type": "Feature",
  "properties": {
    "addr:full":"8641 Wilshire Blvd Beverly Hills CA 90211",
    "addr:housenumber":"8641",
    "addr:postcode":"90211",
    "addr:street":"Wilshire Blvd",
    "iso:country":"US",
    "sg:address":"8641 Wilshire Blvd",
    "sg:city":"Beverly Hills",
    "sg:classifiers":[
        {
            "category":"Health Services",
            "subcategory":"Optometrist",
            "type":"Services"
        }
    ],
    "sg:phone":"+1 310 854 6201",
    "sg:postcode":"90211",
    "sg:province":"CA",
    "sg:tags":[
        "ophthalmologist"
    ],
    "sg:website":"www.laretina.com",
    "wof:name":"Retina-Vitreous Associates Medical Group",
    "wof:placetype":"venue"
},
  "geometry": {"coordinates":[-118.379516,34.066071],"type":"Point"}
}