{
  "type": "Feature",
  "properties": {
    "iso:country":"US",
    "sg:address":"321 2nd St",
    "sg:city":"Livingston",
    "sg:classifiers":[
        {
            "category":"Home & Garden",
            "subcategory":"Hardware",
            "type":"Retail Goods"
        }
    ],
    "sg:phone":"+1 209 394 7949",
    "sg:postcode":"95334",
    "sg:province":"CA",
    "sg:tags":[
        "store"
    ],
    "sg:website":"http://www.ltvhdw.com",
    "wof:name":"Livingston True Value Hardware",
    "wof:placetype":"venue"
},
  "geometry": {"coordinates":[-120.724334,37.38737],"type":"Point"}
}