{
  "type": "Feature",
  "properties": {
    "iso:country":"US",
    "sg:address":"2492 Walnut Ave",
    "sg:city":"Tustin",
    "sg:classifiers":[
        {
            "category":"Manufacturing",
            "subcategory":"Tools & Machinery",
            "type":"Manufacturing & Wholesale Goods"
        }
    ],
    "sg:phone":"+1 714 505 4460",
    "sg:postcode":"92780",
    "sg:province":"CA",
    "sg:tags":[
        "devices",
        "mfg"
    ],
    "wof:name":"Amdl Inc",
    "wof:placetype":"venue"
},
  "geometry": {"coordinates":[-117.80871,33.717389],"type":"Point"}
}