{
  "type": "Feature",
  "properties": {
    "iso:country":"US",
    "sg:address":"Sobrato Center for Nonprofits 568 Valley Way",
    "sg:city":"Milpitas",
    "sg:classifiers":[
        {
            "category":"Government",
            "subcategory":"City Hall",
            "type":"Public Place"
        },
        {
            "category":"Education",
            "subcategory":"School",
            "type":"Public Place"
        }
    ],
    "sg:phone":"+1 408 263 2630",
    "sg:postcode":"95035",
    "sg:province":"CA",
    "sg:website":"www.flyprogram.org",
    "wof:name":"Fresh Lifelines for Youth aka FLY Program",
    "wof:placetype":"venue"
},
  "geometry": {"coordinates":[-121.914225,37.427569],"type":"Point"}
}