{
  "type": "Feature",
  "properties": {
    "iso:country":"US",
    "sg:address":"6767 W Sunset Blvd",
    "sg:city":"Los Angeles",
    "sg:classifiers":[
        {
            "category":"Arts & Performance",
            "subcategory":"Dance",
            "type":"Entertainment"
        }
    ],
    "sg:phone":"+1 323 466 1307",
    "sg:postcode":"90028",
    "sg:province":"CA",
    "sg:tags":[
        "school"
    ],
    "sg:website":"www.blackbirddance.com",
    "wof:name":"Blackbird Dance Company",
    "wof:placetype":"venue"
},
  "geometry": {"coordinates":[-118.33845,34.098097],"type":"Point"}
}