{
  "type": "Feature",
  "properties": {
    "addr:full":"4570 E Pine Ave Fresno CA 93703",
    "addr:housenumber":"4570",
    "addr:postcode":"93703",
    "addr:street":"E Pine Ave",
    "iso:country":"US",
    "sg:address":"4570 E Pine Ave",
    "sg:city":"Fresno",
    "sg:classifiers":[
        {
            "category":"Utilities",
            "subcategory":"Telephone",
            "type":"Services"
        }
    ],
    "sg:phone":"+1 559 252 0347",
    "sg:postcode":"93703",
    "sg:province":"CA",
    "sg:tags":[
        "company"
    ],
    "wof:name":"Prince Telecom Fresno",
    "wof:placetype":"venue"
},
  "geometry": {"coordinates":[-119.746261,36.762217],"type":"Point"}
}