{
  "type": "Feature",
  "properties": {
    "addr:full":"1801 N Kingsley Dr Los Angeles CA 90027",
    "addr:housenumber":"1801",
    "addr:postcode":"90027",
    "addr:street":"N Kingsley Dr",
    "iso:country":"US",
    "sg:address":"1801 N Kingsley Dr",
    "sg:city":"Los Angeles",
    "sg:classifiers":[
        {
            "category":"Communications",
            "subcategory":"Film & Video Production",
            "type":"Services"
        }
    ],
    "sg:phone":"+1 323 765 9038",
    "sg:postcode":"90027",
    "sg:province":"CA",
    "sg:tags":[
        "audio"
    ],
    "wof:name":"THW Productions",
    "wof:placetype":"venue"
},
  "geometry": {"coordinates":[-118.30358099999999,34.103554],"type":"Point"}
}