{
  "type": "Feature",
  "properties": {
    "addr:full":"735 W Duarte Rd Ste 200 Arcadia CA 91007",
    "addr:housenumber":"735",
    "addr:postcode":"91007",
    "addr:street":"W Duarte Rd Ste 200",
    "iso:country":"US",
    "sg:address":"735 W Duarte Rd Ste 200",
    "sg:city":"Arcadia",
    "sg:classifiers":[
        {
            "category":"Real Estate",
            "subcategory":"Real Estate Services",
            "type":"Services"
        }
    ],
    "sg:phone":"+1 626 821 0218",
    "sg:postcode":"91007",
    "sg:province":"CA",
    "sg:website":"www.jennysuen.com",
    "wof:name":"Jenny Suen Realtor",
    "wof:placetype":"venue"
},
  "geometry": {"coordinates":[-118.056,34.125999],"type":"Point"}
}