{
  "type": "Feature",
  "properties": {
    "addr:full":"107 N Maple Ave Manteca CA 95336",
    "addr:housenumber":"107",
    "addr:postcode":"95336",
    "addr:street":"N Maple Ave",
    "iso:country":"US",
    "sg:address":"107 N Maple Ave",
    "sg:city":"Manteca",
    "sg:classifiers":[
        {
            "category":"Personal",
            "subcategory":"Beauty Salon",
            "type":"Services"
        }
    ],
    "sg:phone":"+1 209 239 3990",
    "sg:postcode":"95336",
    "sg:province":"CA",
    "wof:name":"Secrets & Salon",
    "wof:placetype":"venue"
},
  "geometry": {"coordinates":[-121.217828,37.797449],"type":"Point"}
}