{
  "type": "Feature",
  "properties": {
    "iso:country":"US",
    "sg:address":"11450 Lampson Ave",
    "sg:city":"Garden Grove",
    "sg:classifiers":[
        {
            "category":"Real Estate",
            "subcategory":"Real Estate Operator",
            "type":"Services"
        }
    ],
    "sg:phone":"+1 714 537 7927",
    "sg:postcode":"92840",
    "sg:province":"CA",
    "sg:tags":[
        "apartment"
    ],
    "wof:name":"Lampson Village Apartments",
    "wof:placetype":"venue"
},
  "geometry": {"coordinates":[-117.933998,33.781502],"type":"Point"}
}