{
  "type": "Feature",
  "properties": {
    "addr:full":"1018 S Pacific Ave San Pedro CA 90731",
    "addr:housenumber":"1018",
    "addr:postcode":"90731",
    "addr:street":"S Pacific Ave",
    "iso:country":"US",
    "sg:address":"1018 S Pacific Ave",
    "sg:city":"San Pedro",
    "sg:classifiers":[
        {
            "category":"Retail",
            "subcategory":"Repair Shop",
            "type":"Services"
        }
    ],
    "sg:phone":"+1 310 548 1949",
    "sg:postcode":"90731",
    "sg:province":"CA",
    "sg:tags":[
        "appliance"
    ],
    "wof:name":"King Appliance",
    "wof:placetype":"venue"
},
  "geometry": {"coordinates":[-118.28784899999999,33.734334],"type":"Point"}
}