{
  "type": "Feature",
  "properties": {
    "iso:country":"US",
    "sg:address":"30827 Mainmast Dr",
    "sg:city":"Agoura Hills",
    "sg:classifiers":[
        {
            "category":"Professional",
            "subcategory":"Employment Agencies",
            "type":"Services"
        }
    ],
    "sg:phone":"+1 818 706 2635",
    "sg:postcode":"91301",
    "sg:province":"CA",
    "sg:tags":[
        "consultant",
        "search",
        "executive"
    ],
    "wof:name":"International Search Cons",
    "wof:placetype":"venue"
},
  "geometry": {"coordinates":[-118.791115,34.151131],"type":"Point"}
}