{
  "type": "Feature",
  "properties": {
    "addr:full":"3601 E Ventura Ave Fresno CA 93702",
    "addr:housenumber":"3601",
    "addr:postcode":"93702",
    "addr:street":"E Ventura Ave",
    "iso:country":"US",
    "sg:address":"3601 E Ventura Ave",
    "sg:city":"Fresno",
    "sg:classifiers":[
        {
            "category":"Shopping",
            "subcategory":"Music",
            "type":"Retail Goods"
        }
    ],
    "sg:phone":"+1 559 237 9301",
    "sg:postcode":"93702",
    "sg:province":"CA",
    "sg:tags":[
        "video",
        "sale",
        "dvds-rental",
        "disc",
        "tape",
        "cassette"
    ],
    "wof:name":"Fresno Video Exchange",
    "wof:placetype":"venue"
},
  "geometry": {"coordinates":[-119.764374,36.73595],"type":"Point"}
}