{
  "type": "Feature",
  "properties": {
    "addr:full":"1930 Truxtun Ave Bakersfield CA 93301",
    "addr:housenumber":"1930",
    "addr:postcode":"93301",
    "addr:street":"Truxtun Ave",
    "iso:country":"US",
    "sg:address":"1930 Truxtun Ave",
    "sg:city":"Bakersfield",
    "sg:classifiers":[
        {
            "category":"Professional",
            "subcategory":"Management & Consulting",
            "type":"Services"
        }
    ],
    "sg:phone":"+1 661 323 5289",
    "sg:postcode":"93301",
    "sg:province":"CA",
    "sg:tags":[
        "counselor",
        "public",
        "relations"
    ],
    "sg:website":"www.griffincommunications.com",
    "wof:name":"Griffin Communications",
    "wof:placetype":"venue"
},
  "geometry": {"coordinates":[-119.024407,35.373431],"type":"Point"}
}