{
  "type": "Feature",
  "properties": {
    "addr:full":"36238 Plaza Dr Cathedral City CA 92234",
    "addr:housenumber":"36238",
    "addr:postcode":"92234",
    "addr:street":"Plaza Dr",
    "iso:country":"US",
    "sg:address":"36238 Plaza Dr",
    "sg:city":"Cathedral City",
    "sg:classifiers":[
        {
            "category":"Home & Garden",
            "subcategory":"Carpets & Floor Coverings",
            "type":"Retail Goods"
        }
    ],
    "sg:phone":"+1 760 324 3977",
    "sg:postcode":"92234",
    "sg:province":"CA",
    "sg:tags":[
        "material"
    ],
    "wof:name":"David C Greenbaum Co",
    "wof:placetype":"venue"
},
  "geometry": {"coordinates":[-116.463472,33.78549],"type":"Point"}
}