{
  "type": "Feature",
  "properties": {
    "iso:country":"US",
    "sg:address":"156 Walnut Ave",
    "sg:city":"Santa Cruz",
    "sg:classifiers":[
        {
            "category":"Personal",
            "subcategory":"Beauty Salon",
            "type":"Services"
        }
    ],
    "sg:phone":"+1 831 426 3363",
    "sg:postcode":"95060",
    "sg:province":"CA",
    "wof:name":"Hair & Nail Design By Kye",
    "wof:placetype":"venue"
},
  "geometry": {"coordinates":[-122.027907,36.973243],"type":"Point"}
}