{
  "type": "Feature",
  "properties": {
    "addr:full":"2400 Traffic Way Atascadero CA 93422",
    "addr:housenumber":"2400",
    "addr:postcode":"93422",
    "addr:street":"Traffic Way",
    "iso:country":"US",
    "sg:address":"2400 Traffic Way",
    "sg:city":"Atascadero",
    "sg:classifiers":[
        {
            "category":"Education",
            "subcategory":"Preschool",
            "type":"Public Place"
        }
    ],
    "sg:phone":"+1 805 466 1133",
    "sg:postcode":"93422",
    "sg:province":"CA",
    "sg:tags":[
        "kindergarten"
    ],
    "wof:name":"Learning Tree-Pre-School Ctr",
    "wof:placetype":"venue"
},
  "geometry": {"coordinates":[-120.686272,35.518532],"type":"Point"}
}