{
  "type": "Feature",
  "properties": {
    "iso:country":"US",
    "sg:address":"5130 Schaefer Ave",
    "sg:city":"Chino",
    "sg:classifiers":[
        {
            "category":"Professional",
            "subcategory":"Art Services",
            "type":"Services"
        }
    ],
    "sg:phone":"+1 909 591 0021",
    "sg:postcode":"91710",
    "sg:province":"CA",
    "sg:tags":[
        "graphic",
        "designer"
    ],
    "wof:name":"Illgrfx Graphics & Printing",
    "wof:placetype":"venue"
},
  "geometry": {"coordinates":[-117.6898,34.004626],"type":"Point"}
}