{
  "type": "Feature",
  "properties": {
    "iso:country":"US",
    "sg:address":"225 Alameda Del Prado",
    "sg:city":"Novato",
    "sg:classifiers":[
        {
            "category":"Restaurant",
            "type":"Food & Drink"
        }
    ],
    "sg:menulink":"http://www.allmenus.com/ca/northeast-marin/22056-wildfox/menu/",
    "sg:phone":"+1 415 883 9125",
    "sg:postcode":"94949",
    "sg:province":"CA",
    "sg:tags":[
        "american",
        "californian"
    ],
    "wof:name":"Wildfox",
    "wof:placetype":"venue"
},
  "geometry": {"coordinates":[-122.531755,38.058687],"type":"Point"}
}