{
  "type": "Feature",
  "properties": {
    "iso:country":"US",
    "sg:address":"1818 S State College Blvd",
    "sg:city":"Anaheim",
    "sg:classifiers":[
        {
            "category":"Professional",
            "type":"Services"
        }
    ],
    "sg:phone":"+1 888 778 2979",
    "sg:postcode":"92806",
    "sg:province":"CA",
    "sg:website":"www.houseofdesigners.com",
    "wof:name":"House of Designers",
    "wof:placetype":"venue"
},
  "geometry": {"coordinates":[-117.889079,33.802648],"type":"Point"}
}