{
  "type": "Feature",
  "properties": {
    "addr:full":"1154 N Chestnut Ave Rialto CA 92376",
    "addr:housenumber":"1154",
    "addr:postcode":"92376",
    "addr:street":"N Chestnut Ave",
    "iso:country":"US",
    "sg:address":"1154 N Chestnut Ave",
    "sg:city":"Rialto",
    "sg:classifiers":[
        {
            "category":"Shopping",
            "type":"Retail Goods"
        }
    ],
    "sg:phone":"+1 909 820 0796",
    "sg:postcode":"92376",
    "sg:province":"CA",
    "sg:tags":[
        "merchandise"
    ],
    "wof:name":"Dandridge Fine Art",
    "wof:placetype":"venue"
},
  "geometry": {"coordinates":[-117.355974,34.12015],"type":"Point"}
}