{
  "type": "Feature",
  "properties": {
    "addr:full":"4053 Lincoln Blvd Marina Del Rey CA 90292",
    "addr:housenumber":"4053",
    "addr:postcode":"90292",
    "addr:street":"Lincoln Blvd",
    "iso:country":"US",
    "sg:address":"4053 Lincoln Blvd",
    "sg:city":"Marina Del Rey",
    "sg:classifiers":[
        {
            "category":"Retail",
            "subcategory":"Veterinary Services",
            "type":"Services"
        }
    ],
    "sg:phone":"+1 310 448 8080",
    "sg:postcode":"90292",
    "sg:province":"CA",
    "sg:tags":[
        "veterinarian"
    ],
    "wof:name":"Anchor Veterinary Group",
    "wof:placetype":"venue"
},
  "geometry": {"coordinates":[-118.44525400000001,33.987814],"type":"Point"}
}