{
  "type": "Feature",
  "properties": {
    "addr:full":"7552 Reynolds Cir Huntington Beach CA 92647",
    "addr:housenumber":"7552",
    "addr:postcode":"92647",
    "addr:street":"Reynolds Cir",
    "iso:country":"US",
    "sg:address":"7552 Reynolds Cir",
    "sg:city":"Huntington Beach",
    "sg:classifiers":[
        {
            "category":"Wholesale",
            "subcategory":"Machinery & Supplies",
            "type":"Manufacturing & Wholesale Goods"
        }
    ],
    "sg:phone":"+1 714 375 6211",
    "sg:postcode":"92647",
    "sg:province":"CA",
    "sg:tags":[
        "equipment",
        "industrial",
        "l"
    ],
    "wof:name":"Advanced Gas Pdts Wldg Sups",
    "wof:placetype":"venue"
},
  "geometry": {"coordinates":[-117.99632200000001,33.706155],"type":"Point"}
}