{
  "type": "Feature",
  "properties": {
    "iso:country":"US",
    "sg:address":"7900 Loyola Blvd",
    "sg:city":"Los Angeles",
    "sg:classifiers":[
        {
            "category":"Health Services",
            "subcategory":"Doctor",
            "type":"Services"
        }
    ],
    "sg:phone":"+1 310 338 2993",
    "sg:postcode":"90045",
    "sg:province":"CA",
    "sg:tags":[
        "physician",
        "surgeon"
    ],
    "wof:name":"John Flynn MD",
    "wof:placetype":"venue"
},
  "geometry": {"coordinates":[-118.416697,33.965886],"type":"Point"}
}