{
  "type": "Feature",
  "properties": {
    "iso:country":"US",
    "sg:address":"9719 Lincoln Village Dr",
    "sg:city":"Sacramento",
    "sg:classifiers":[
        {
            "category":"Education",
            "subcategory":"Library",
            "type":"Public Place"
        }
    ],
    "sg:phone":"+1 916 366 6713",
    "sg:postcode":"95827",
    "sg:province":"CA",
    "sg:tags":[
        "reading",
        "instruction"
    ],
    "sg:website":"http://www.kumon.com",
    "wof:name":"Kumon Math & Reading Center Of Sacramento",
    "wof:placetype":"venue"
},
  "geometry": {"coordinates":[-121.33361499999999,38.562053],"type":"Point"}
}