{
  "type": "Feature",
  "properties": {
    "addr:full":"2244 S Garey Ave Pomona CA 91766",
    "addr:housenumber":"2244",
    "addr:postcode":"91766",
    "addr:street":"S Garey Ave",
    "iso:country":"US",
    "sg:address":"2244 S Garey Ave",
    "sg:city":"Pomona",
    "sg:classifiers":[
        {
            "category":"Banks & Credit Unions",
            "subcategory":"Bank",
            "type":"Services"
        }
    ],
    "sg:phone":"+1 909 517 1540",
    "sg:postcode":"91766",
    "sg:province":"CA",
    "sg:tags":[
        "depository",
        "banking"
    ],
    "wof:name":"A & A Check Cashing",
    "wof:placetype":"venue"
},
  "geometry": {"coordinates":[-117.74912,34.032317],"type":"Point"}
}