{
  "type": "Feature",
  "properties": {
    "iso:country":"US",
    "sg:address":"1485 Enea Cir",
    "sg:city":"Concord",
    "sg:classifiers":[
        {
            "category":"Manufacturing",
            "subcategory":"Printing",
            "type":"Manufacturing & Wholesale Goods"
        }
    ],
    "sg:phone":"+1 925 680 6712",
    "sg:postcode":"94520",
    "sg:province":"CA",
    "sg:tags":[
        "printer"
    ],
    "wof:name":"American WEBB",
    "wof:placetype":"venue"
},
  "geometry": {"coordinates":[-122.051802,37.971239],"type":"Point"}
}