{
  "type": "Feature",
  "properties": {
    "iso:country":"US",
    "sg:address":"840 S Maple Ave",
    "sg:city":"Montebello",
    "sg:classifiers":[
        {
            "category":"Retail",
            "subcategory":"Auto Rental",
            "type":"Services"
        }
    ],
    "sg:phone":"+1 323 726 2116",
    "sg:postcode":"90640",
    "sg:province":"CA",
    "sg:tags":[
        "renting",
        "truck",
        "leasing"
    ],
    "sg:website":"www.ryder.com",
    "wof:name":"Budget Truck Rental",
    "wof:placetype":"venue"
},
  "geometry": {"coordinates":[-118.121727,34.000272],"type":"Point"}
}