{
  "type": "Feature",
  "properties": {
    "iso:country":"US",
    "sg:address":"17157 Bellflower Blvd",
    "sg:city":"Bellflower",
    "sg:classifiers":[
        {
            "category":"Personal",
            "subcategory":"Barber",
            "type":"Services"
        }
    ],
    "sg:phone":"+1 562 925 0076",
    "sg:postcode":"90706",
    "sg:province":"CA",
    "wof:name":"Style Masters",
    "wof:placetype":"venue"
},
  "geometry": {"coordinates":[-118.125271,33.876944],"type":"Point"}
}