{
  "type": "Feature",
  "properties": {
    "addr:full":"2034 Woodard Rd San Jose CA 95124",
    "addr:housenumber":"2034",
    "addr:postcode":"95124",
    "addr:street":"Woodard Rd",
    "iso:country":"US",
    "sg:address":"2034 Woodard Rd",
    "sg:city":"San Jose",
    "sg:classifiers":[
        {
            "category":"Real Estate",
            "subcategory":"Real Estate Services",
            "type":"Services"
        }
    ],
    "sg:phone":"+1 408 377 8887",
    "sg:postcode":"95124",
    "sg:province":"CA",
    "wof:name":"Guercio Jack Realtor",
    "wof:placetype":"venue"
},
  "geometry": {"coordinates":[-121.931719,37.260139],"type":"Point"}
}