{
  "type": "Feature",
  "properties": {
    "addr:full":"626 State Rte 66 Glendora CA 91740",
    "addr:housenumber":"626",
    "addr:postcode":"91740",
    "addr:street":"State Rte 66",
    "iso:country":"US",
    "sg:address":"626 State Rte 66",
    "sg:city":"Glendora",
    "sg:classifiers":[
        {
            "category":"Insurance",
            "subcategory":"Insurance Agent",
            "type":"Services"
        }
    ],
    "sg:phone":"+1 626 914 7694",
    "sg:postcode":"91740",
    "sg:province":"CA",
    "wof:name":"Mosso Insurance Srv",
    "wof:placetype":"venue"
},
  "geometry": {"coordinates":[-117.85552800000001,34.128593],"type":"Point"}
}