{
  "type": "Feature",
  "properties": {
    "iso:country":"US",
    "sg:address":"6719 Alvarado Rd",
    "sg:city":"San Diego",
    "sg:classifiers":[
        {
            "category":"Health Services",
            "subcategory":"Medical Lab",
            "type":"Services"
        }
    ],
    "sg:phone":"+1 619 583 5731",
    "sg:postcode":"92120",
    "sg:province":"CA",
    "sg:tags":[
        "laboratory"
    ],
    "wof:name":"Ivf Laboratory of San Diego",
    "wof:placetype":"venue"
},
  "geometry": {"coordinates":[-117.049907,32.775501],"type":"Point"}
}