{
  "type": "Feature",
  "properties": {
    "addr:full":"6613 Magnolia Ave Riverside CA 92506",
    "addr:housenumber":"6613",
    "addr:postcode":"92506",
    "addr:street":"Magnolia Ave",
    "iso:country":"US",
    "sg:address":"6613 Magnolia Ave",
    "sg:city":"Riverside",
    "sg:classifiers":[
        {
            "category":"Personal",
            "subcategory":"Barber",
            "type":"Services"
        }
    ],
    "sg:phone":"+1 951 369 1295",
    "sg:postcode":"92506",
    "sg:province":"CA",
    "wof:name":"Low Cost Barber Shop",
    "wof:placetype":"venue"
},
  "geometry": {"coordinates":[-117.396742,33.953202],"type":"Point"}
}