{
  "type": "Feature",
  "properties": {
    "addr:full":"2440 16th St San Francisco CA 94103",
    "addr:housenumber":"2440",
    "addr:postcode":"94103",
    "addr:street":"16Th St",
    "iso:country":"US",
    "sg:address":"2440 16th St",
    "sg:city":"San Francisco",
    "sg:classifiers":[
        {
            "category":"Freight",
            "type":"Transportation"
        }
    ],
    "sg:phone":"+1 415 626 0800",
    "sg:postcode":"94103",
    "sg:province":"CA",
    "sg:tags":[
        "warehouse",
        "self",
        "storage"
    ],
    "sg:website":"www.atticselfstorageca.com",
    "wof:name":"Attic Self Storage",
    "wof:placetype":"venue"
},
  "geometry": {"coordinates":[-122.410886,37.765601],"type":"Point"}
}