{
  "type": "Feature",
  "properties": {
    "iso:country":"US",
    "sg:address":"3207 Giovanetti Ave",
    "sg:city":"Bakersfield",
    "sg:classifiers":[
        {
            "category":"Building & Trades",
            "subcategory":"Equipment Rental",
            "type":"Services"
        }
    ],
    "sg:phone":"+1 661 398 9640",
    "sg:postcode":"93313",
    "sg:province":"CA",
    "sg:tags":[
        "yard",
        "leasing",
        "store"
    ],
    "wof:name":"Regassa Gent Rental",
    "wof:placetype":"venue"
},
  "geometry": {"coordinates":[-119.037881,35.275601],"type":"Point"}
}