{
  "type": "Feature",
  "properties": {
    "addr:full":"11007 Victory Blvd North Hollywood CA 91606",
    "addr:housenumber":"11007",
    "addr:postcode":"91606",
    "addr:street":"Victory Blvd",
    "iso:country":"US",
    "sg:address":"11007 Victory Blvd",
    "sg:city":"North Hollywood",
    "sg:classifiers":[
        {
            "category":"Restaurant",
            "type":"Food & Drink"
        }
    ],
    "sg:phone":"+1 818 753 0648",
    "sg:postcode":"91606",
    "sg:province":"CA",
    "sg:tags":[
        "mexican"
    ],
    "wof:name":"El Trebol",
    "wof:placetype":"venue"
},
  "geometry": {"coordinates":[-118.370423,34.186825],"type":"Point"}
}