{
  "type": "Feature",
  "properties": {
    "addr:full":"280 Caldecott Ln Oakland CA 94618",
    "addr:housenumber":"280",
    "addr:postcode":"94618",
    "addr:street":"Caldecott Ln",
    "iso:country":"US",
    "sg:address":"280 Caldecott Ln",
    "sg:city":"Oakland",
    "sg:classifiers":[
        {
            "category":"Recreation",
            "type":"Entertainment"
        }
    ],
    "sg:phone":"+1 510 647 3779",
    "sg:postcode":"94618",
    "sg:province":"CA",
    "sg:tags":[
        "amusement"
    ],
    "wof:name":"Grow Forward",
    "wof:placetype":"venue"
},
  "geometry": {"coordinates":[-122.220564,37.854824],"type":"Point"}
}