{
  "type": "Feature",
  "properties": {
    "addr:full":"1130 W 6th St Corona CA 92882",
    "addr:housenumber":"1130",
    "addr:postcode":"92882",
    "addr:street":"W 6Th St",
    "iso:country":"US",
    "sg:address":"1130 W 6th St",
    "sg:city":"Corona",
    "sg:classifiers":[
        {
            "category":"Food & Beverages",
            "subcategory":"Specialty",
            "type":"Retail Goods"
        },
        {
            "category":"Food & Beverages",
            "subcategory":"Groceries & Convenience Stores",
            "type":"Retail Goods"
        }
    ],
    "sg:phone":"+1 951 372 9485",
    "sg:postcode":"92882",
    "sg:province":"CA",
    "sg:tags":[
        "grocers-specialty"
    ],
    "wof:name":"Superior Grocers",
    "wof:placetype":"venue"
},
  "geometry": {"coordinates":[-117.584132,33.877286],"type":"Point"}
}