{
  "type": "Feature",
  "properties": {
    "addr:full":"8400 Church St Gilroy CA 95020",
    "addr:housenumber":"8400",
    "addr:postcode":"95020",
    "addr:street":"Church St",
    "iso:country":"US",
    "sg:address":"8400 Church St",
    "sg:city":"Gilroy",
    "sg:classifiers":[
        {
            "category":"Food & Beverages",
            "subcategory":"Groceries & Convenience Stores",
            "type":"Retail Goods"
        }
    ],
    "sg:phone":"+1 408 842 9096",
    "sg:postcode":"95020",
    "sg:province":"CA",
    "wof:name":"Quik Stop Market 93",
    "wof:placetype":"venue"
},
  "geometry": {"coordinates":[-121.57635399999999,37.017603],"type":"Point"}
}