{
  "type": "Feature",
  "properties": {
    "addr:full":"1524 W Sunset Blvd Los Angeles CA 90026",
    "addr:housenumber":"1524",
    "addr:postcode":"90026",
    "addr:street":"W Sunset Blvd",
    "iso:country":"US",
    "sg:address":"1524 W Sunset Blvd",
    "sg:city":"Los Angeles",
    "sg:classifiers":[
        {
            "category":"Fast Food",
            "type":"Food & Drink"
        }
    ],
    "sg:phone":"+1 213 250 0301",
    "sg:postcode":"90026",
    "sg:province":"CA",
    "sg:tags":[
        "burger"
    ],
    "wof:name":"Patra Burgers On Sunset",
    "wof:placetype":"venue"
},
  "geometry": {"coordinates":[-118.25599699999999,34.076302],"type":"Point"}
}