{
  "type": "Feature",
  "properties": {
    "iso:country":"US",
    "sg:address":"3002 Midvale Ave",
    "sg:city":"Los Angeles",
    "sg:classifiers":[
        {
            "category":"Travel",
            "subcategory":"Travel Agent",
            "type":"Entertainment"
        }
    ],
    "sg:phone":"+1 310 234 9577",
    "sg:postcode":"90034",
    "sg:province":"CA",
    "sg:tags":[
        "passenger",
        "transportation",
        "arrangement"
    ],
    "wof:name":"Cruise Lady",
    "wof:placetype":"venue"
},
  "geometry": {"coordinates":[-118.41984100000001,34.027733],"type":"Point"}
}