{
  "type": "Feature",
  "properties": {
    "addr:full":"735 Montgomery St San Francisco CA 94111",
    "addr:housenumber":"735",
    "addr:postcode":"94111",
    "addr:street":"Montgomery St",
    "iso:country":"US",
    "sg:address":"735 Montgomery St",
    "sg:city":"San Francisco",
    "sg:classifiers":[
        {
            "category":"Manufacturing",
            "subcategory":"Printing",
            "type":"Manufacturing & Wholesale Goods"
        }
    ],
    "sg:phone":"+1 415 402 0222",
    "sg:postcode":"94111",
    "sg:province":"CA",
    "sg:tags":[
        "publisher",
        "software"
    ],
    "sg:website":"www.ipro.com",
    "wof:name":"I-Pro",
    "wof:placetype":"venue"
},
  "geometry": {"coordinates":[-122.403522,37.796098],"type":"Point"}
}