{
  "type": "Feature",
  "properties": {
    "iso:country":"US",
    "sg:address":"721 E Main St",
    "sg:city":"Alhambra",
    "sg:classifiers":[
        {
            "category":"Restaurant",
            "type":"Food & Drink"
        }
    ],
    "sg:menulink":"http://www.allmenus.com/ca/southwest-san-gabriel-valley/123873-quiznos-sub/menu/",
    "sg:phone":"+1 626 289 6654",
    "sg:postcode":"91801",
    "sg:province":"CA",
    "sg:tags":[
        "wrap",
        "american",
        "sandwich"
    ],
    "wof:name":"Quiznos Sub",
    "wof:placetype":"venue"
},
  "geometry": {"coordinates":[-118.119208,34.098814],"type":"Point"}
}