{
  "type": "Feature",
  "properties": {
    "addr:full":"28042 N Ave Stanford Ste E Santa Clarita CA 91355",
    "addr:housenumber":"28042",
    "addr:postcode":"91355",
    "addr:street":"N Ave;Ste E",
    "iso:country":"US",
    "sg:address":"28042 N Ave Stanford Ste E",
    "sg:city":"Santa Clarita",
    "sg:classifiers":[
        {
            "category":"Social Services",
            "subcategory":"Job Training",
            "type":"Services"
        }
    ],
    "sg:phone":"+1 661 251 0484",
    "sg:postcode":"91355",
    "sg:province":"CA",
    "sg:tags":[
        "career",
        "counseling"
    ],
    "sg:website":"www.scc-co.com",
    "wof:name":"Santa Clarita Consultants",
    "wof:placetype":"venue"
},
  "geometry": {"coordinates":[-118.58771299999999,34.433956],"type":"Point"}
}