{
  "type": "Feature",
  "properties": {
    "iso:country":"US",
    "sg:address":"530 S Lake Ave",
    "sg:city":"Pasadena",
    "sg:classifiers":[
        {
            "category":"Professional",
            "subcategory":"Business Services",
            "type":"Services"
        },
        {
            "category":"Government",
            "subcategory":"Post Office",
            "type":"Public Place"
        }
    ],
    "sg:phone":"+1 626 744 0420",
    "sg:postcode":"91101",
    "sg:province":"CA",
    "sg:tags":[
        "mailbox-rental",
        "shipping",
        "notary",
        "mail",
        "receiving"
    ],
    "sg:website":"http://www.mailboxplanet.net",
    "wof:name":"Mail Box Planet",
    "wof:placetype":"venue"
},
  "geometry": {"coordinates":[-118.13228599999999,34.136721],"type":"Point"}
}