{
  "type": "Feature",
  "properties": {
    "iso:country":"US",
    "sg:address":"21700 Moneta Ave",
    "sg:city":"Carson",
    "sg:classifiers":[
        {
            "category":"Professional",
            "subcategory":"Detective & Security Services",
            "type":"Services"
        }
    ],
    "sg:phone":"+1 310 409 2977",
    "sg:postcode":"90745",
    "sg:province":"CA",
    "sg:tags":[
        "system"
    ],
    "sg:website":"www.watch-security-cameras.com",
    "wof:name":"Watch Security Cameras",
    "wof:placetype":"venue"
},
  "geometry": {"coordinates":[-118.281676,33.831158],"type":"Point"}
}