{
  "type": "Feature",
  "properties": {
    "iso:country":"US",
    "sg:address":"3098-B Winkle Ave",
    "sg:city":"Santa Cruz",
    "sg:classifiers":[
        {
            "category":"Retail",
            "subcategory":"Auto Repair",
            "type":"Services"
        }
    ],
    "sg:phone":"+1 831 464 8726",
    "sg:postcode":"95065",
    "sg:province":"CA",
    "wof:name":"Auto-Motives",
    "wof:placetype":"venue"
},
  "geometry": {"coordinates":[-121.974018,36.989114],"type":"Point"}
}