{
  "type": "Feature",
  "properties": {
    "addr:full":"1868 Gallop Ct Simi Valley CA 93065",
    "addr:housenumber":"1868",
    "addr:postcode":"93065",
    "addr:street":"Gallop Ct",
    "iso:country":"US",
    "sg:address":"1868 Gallop Ct",
    "sg:city":"Simi Valley",
    "sg:classifiers":[
        {
            "category":"Building & Trades",
            "subcategory":"Electrical",
            "type":"Services"
        }
    ],
    "sg:phone":"+1 805 520 4898",
    "sg:postcode":"93065",
    "sg:province":"CA",
    "sg:tags":[
        "electrical",
        "contractor"
    ],
    "wof:name":"Parker McKee Corporation",
    "wof:placetype":"venue"
},
  "geometry": {"coordinates":[-118.763727,34.248781],"type":"Point"}
}