{
  "type": "Feature",
  "properties": {
    "iso:country":"US",
    "sg:address":"6511 Lexington Ave",
    "sg:city":"Los Angeles",
    "sg:classifiers":[
        {
            "category":"Manufacturing",
            "subcategory":"Signs",
            "type":"Manufacturing & Wholesale Goods"
        }
    ],
    "sg:phone":"+1 323 469 5217",
    "sg:postcode":"90038",
    "sg:province":"CA",
    "sg:tags":[
        "advertising",
        "specialty"
    ],
    "wof:name":"Sign Express",
    "wof:placetype":"venue"
},
  "geometry": {"coordinates":[-118.33213600000001,34.092617],"type":"Point"}
}