{
  "type": "Feature",
  "properties": {
    "addr:full":"6395 Winona Ave San Diego CA 92120",
    "addr:housenumber":"6395",
    "addr:postcode":"92120",
    "addr:street":"Winona Ave",
    "iso:country":"US",
    "sg:address":"6395 Winona Ave",
    "sg:city":"San Diego",
    "sg:classifiers":[
        {
            "category":"Retail",
            "subcategory":"Laundry & Dry Cleaning",
            "type":"Services"
        }
    ],
    "sg:phone":"+1 619 296 0569",
    "sg:postcode":"92120",
    "sg:province":"CA",
    "sg:tags":[
        "cleaners",
        "rug",
        "carpet"
    ],
    "wof:name":"Pro Steam",
    "wof:placetype":"venue"
},
  "geometry": {"coordinates":[-117.08715599999999,32.788097],"type":"Point"}
}