{
  "type": "Feature",
  "properties": {
    "iso:country":"US",
    "sg:address":"15 Viejo",
    "sg:city":"Irvine",
    "sg:classifiers":[
        {
            "category":"Manufacturing",
            "subcategory":"Printing",
            "type":"Manufacturing & Wholesale Goods"
        }
    ],
    "sg:phone":"+1 949 515 1454",
    "sg:postcode":"92612",
    "sg:province":"CA",
    "sg:tags":[
        "lithographic",
        "commercial"
    ],
    "wof:name":"Copy Rite",
    "wof:placetype":"venue"
},
  "geometry": {"coordinates":[-117.834039,33.659475],"type":"Point"}
}