{
  "type": "Feature",
  "properties": {
    "iso:country":"US",
    "sg:address":"4780 Mission Gorge Pl",
    "sg:city":"San Diego",
    "sg:classifiers":[
        {
            "category":"Home & Garden",
            "subcategory":"Carpets & Floor Coverings",
            "type":"Retail Goods"
        }
    ],
    "sg:phone":"+1 619 582 3900",
    "sg:postcode":"92120",
    "sg:province":"CA",
    "sg:tags":[
        "dealer",
        "rug"
    ],
    "wof:name":"Charlie's Carpets",
    "wof:placetype":"venue"
},
  "geometry": {"coordinates":[-117.09791300000001,32.78306],"type":"Point"}
}