{
  "type": "Feature",
  "properties": {
    "iso:country":"US",
    "sg:address":"14670 Hwy 9",
    "sg:city":"Boulder Creek",
    "sg:classifiers":[
        {
            "category":"Professional",
            "subcategory":"Engineering",
            "type":"Services"
        }
    ],
    "sg:phone":"+1 831 338 1800",
    "sg:postcode":"95006",
    "sg:province":"CA",
    "sg:tags":[
        "engineer"
    ],
    "wof:name":"EMF Systems",
    "wof:placetype":"venue"
},
  "geometry": {"coordinates":[-122.133149,37.146267],"type":"Point"}
}