{
  "type": "Feature",
  "properties": {
    "iso:country":"US",
    "sg:address":"25334 Poderio Dr",
    "sg:city":"Ramona",
    "sg:classifiers":[
        {
            "category":"Shopping",
            "subcategory":"Used Merchandise",
            "type":"Retail Goods"
        }
    ],
    "sg:phone":"+1 760 789 3415",
    "sg:postcode":"92065",
    "sg:province":"CA",
    "sg:tags":[
        "resells",
        "software"
    ],
    "wof:name":"Red FM Software",
    "wof:placetype":"venue"
},
  "geometry": {"coordinates":[-116.778516,33.005773],"type":"Point"}
}