{
  "type": "Feature",
  "properties": {
    "addr:full":"10129 N Ponderosa Way Rough And Ready CA 95975",
    "addr:housenumber":"10129",
    "addr:postcode":"95975",
    "addr:street":"N Ponderosa Way",
    "iso:country":"US",
    "sg:address":"10129 N Ponderosa Way",
    "sg:city":"Rough And Ready",
    "sg:classifiers":[
        {
            "category":"Building & Trades",
            "subcategory":"Construction",
            "type":"Services"
        }
    ],
    "sg:phone":"+1 530 272 6179",
    "sg:postcode":"95975",
    "sg:province":"CA",
    "sg:tags":[
        "excavation",
        "contractor"
    ],
    "wof:name":"Holub Backhoe",
    "wof:placetype":"venue"
},
  "geometry": {"coordinates":[-121.129408,39.234794],"type":"Point"}
}