{
  "type": "Feature",
  "properties": {
    "addr:full":"10638 Ranchito St El Monte CA 91731",
    "addr:housenumber":"10638",
    "addr:postcode":"91731",
    "addr:street":"Ranchito St",
    "iso:country":"US",
    "sg:address":"10638 Ranchito St",
    "sg:city":"El Monte",
    "sg:classifiers":[
        {
            "category":"Manufacturing",
            "subcategory":"Building Materials",
            "type":"Manufacturing & Wholesale Goods"
        }
    ],
    "sg:phone":"+1 626 442 6213",
    "sg:postcode":"91731",
    "sg:province":"CA",
    "sg:tags":[
        "mfg",
        "wood",
        "kitchen",
        "cabinet"
    ],
    "wof:name":"Morse Cabinets",
    "wof:placetype":"venue"
},
  "geometry": {"coordinates":[-118.037008,34.090633],"type":"Point"}
}