{
  "type": "Feature",
  "properties": {
    "addr:full":"4387 Lucy Way Soquel CA 95073",
    "addr:housenumber":"4387",
    "addr:postcode":"95073",
    "addr:street":"Lucy Way",
    "iso:country":"US",
    "sg:address":"4387 Lucy Way",
    "sg:city":"Soquel",
    "sg:classifiers":[
        {
            "category":"Professional",
            "subcategory":"Management & Consulting",
            "type":"Services"
        }
    ],
    "sg:phone":"+1 831 475 3235",
    "sg:postcode":"95073",
    "sg:province":"CA",
    "sg:tags":[
        "marketing",
        "consultant"
    ],
    "wof:name":"Kar Lar Ltd",
    "wof:placetype":"venue"
},
  "geometry": {"coordinates":[-121.958887,36.99943],"type":"Point"}
}