{
  "type": "Feature",
  "properties": {
    "addr:full":"26615 Tampico Pl Mission Viejo CA 92691",
    "addr:housenumber":"26615",
    "addr:postcode":"92691",
    "addr:street":"Tampico Pl",
    "iso:country":"US",
    "sg:address":"26615 Tampico Pl",
    "sg:city":"Mission Viejo",
    "sg:classifiers":[
        {
            "category":"Shopping",
            "subcategory":"Used Merchandise",
            "type":"Retail Goods"
        }
    ],
    "sg:phone":"+1 949 707 0055",
    "sg:postcode":"92691",
    "sg:province":"CA",
    "wof:name":"Tortuga Imports",
    "wof:placetype":"venue"
},
  "geometry": {"coordinates":[-117.666945,33.61941],"type":"Point"}
}