{
  "type": "Feature",
  "properties": {
    "addr:full":"3192 16th St San Francisco CA 94103",
    "addr:housenumber":"3192",
    "addr:postcode":"94103",
    "addr:street":"16Th St",
    "iso:country":"US",
    "sg:address":"3192 16th St",
    "sg:city":"San Francisco",
    "sg:classifiers":[
        {
            "category":"Bars & Pubs",
            "type":"Food & Drink"
        }
    ],
    "sg:phone":"+1 415 373 1042",
    "sg:postcode":"94103",
    "sg:province":"CA",
    "sg:website":"www.thedoubledutch.com",
    "wof:name":"Double Dutch",
    "wof:placetype":"venue"
},
  "geometry": {"coordinates":[-122.423858,37.764817],"type":"Point"}
}