{
  "type": "Feature",
  "properties": {
    "iso:country":"US",
    "sg:address":"4601 Orwood Rd",
    "sg:city":"Brentwood",
    "sg:classifiers":[
        {
            "category":"Shopping",
            "subcategory":"Florist",
            "type":"Retail Goods"
        }
    ],
    "sg:phone":"+1 925 634 1593",
    "sg:postcode":"94513",
    "sg:province":"CA",
    "sg:website":"www.flowersbygerry.com",
    "wof:name":"Flowers by Gerry",
    "wof:placetype":"venue"
},
  "geometry": {"coordinates":[-121.609256,37.938813],"type":"Point"}
}