{
  "type": "Feature",
  "properties": {
    "addr:full":"2732 el Portal Dr San Pablo CA 94806",
    "addr:housenumber":"2732",
    "addr:postcode":"94806",
    "addr:street":"El Portal Dr",
    "iso:country":"US",
    "sg:address":"2732 el Portal Dr",
    "sg:city":"San Pablo",
    "sg:classifiers":[
        {
            "category":"Building & Trades",
            "subcategory":"Construction",
            "type":"Services"
        }
    ],
    "sg:phone":"+1 510 235 2698",
    "sg:postcode":"94806",
    "sg:province":"CA",
    "sg:tags":[
        "fence",
        "contractor"
    ],
    "sg:website":"www.justfencing.com",
    "wof:name":"Just Fencing Inc",
    "wof:placetype":"venue"
},
  "geometry": {"coordinates":[-122.333372,37.963014],"type":"Point"}
}