{
  "type": "Feature",
  "properties": {
    "addr:full":"235 N Sepulveda Blvd Manhattan Beach CA 90266",
    "addr:housenumber":"235",
    "addr:postcode":"90266",
    "addr:street":"N Sepulveda Blvd",
    "iso:country":"US",
    "sg:address":"235 N Sepulveda Blvd",
    "sg:city":"Manhattan Beach",
    "sg:classifiers":[
        {
            "category":"Restaurant",
            "type":"Food & Drink"
        }
    ],
    "sg:phone":"+1 310 372 4504",
    "sg:postcode":"90266",
    "sg:province":"CA",
    "wof:name":"Sion's Mexican Restaurant",
    "wof:placetype":"venue"
},
  "geometry": {"coordinates":[-118.39604,33.880371],"type":"Point"}
}