{
  "type": "Feature",
  "properties": {
    "iso:country":"US",
    "sg:address":"1116 E Broadway",
    "sg:city":"Glendale",
    "sg:classifiers":[
        {
            "category":"Professional",
            "subcategory":"Computer Services",
            "type":"Services"
        }
    ],
    "sg:phone":"+1 818 243 4812",
    "sg:postcode":"91205",
    "sg:province":"CA",
    "sg:tags":[
        "communications",
        "telephone",
        "internet"
    ],
    "wof:name":"I P C Zone Internet Cafe",
    "wof:placetype":"venue"
},
  "geometry": {"coordinates":[-118.24146399999999,34.146178],"type":"Point"}
}