{
  "type": "Feature",
  "properties": {
    "addr:full":"2130 E 2nd St Long Beach CA 90803",
    "addr:housenumber":"2130",
    "addr:postcode":"90803",
    "addr:street":"E 2Nd St",
    "iso:country":"US",
    "sg:address":"2130 E 2nd St",
    "sg:city":"Long Beach",
    "sg:classifiers":[
        {
            "category":"Wholesale",
            "subcategory":"Metals & Minerals",
            "type":"Manufacturing & Wholesale Goods"
        }
    ],
    "sg:phone":"+1 562 439 5333",
    "sg:postcode":"90803",
    "sg:province":"CA",
    "sg:tags":[
        "pipe",
        "center"
    ],
    "wof:name":"Car Ber Holdings Inc",
    "wof:placetype":"venue"
},
  "geometry": {"coordinates":[-118.16447599999999,33.765946],"type":"Point"}
}