{
  "type": "Feature",
  "properties": {
    "iso:country":"US",
    "sg:address":"9641 Tujunga Canyon Blvd",
    "sg:city":"Tujunga",
    "sg:classifiers":[
        {
            "category":"Place Of Worship",
            "subcategory":"Church",
            "type":"Public Place"
        },
        {
            "category":"Place Of Worship",
            "type":"Public Place"
        },
        {
            "category":"Organizations",
            "subcategory":"Religious Organization",
            "type":"Services"
        }
    ],
    "sg:phone":"+1 818 353 1138",
    "sg:postcode":"91042",
    "sg:province":"CA",
    "sg:tags":[
        "churches-interdenominational",
        "churches-various",
        "denomination"
    ],
    "sg:website":"http://www.buildingleaders.net",
    "wof:name":"Church Of The Open Bible",
    "wof:placetype":"venue"
},
  "geometry": {"coordinates":[-118.273798,34.242681],"type":"Point"}
}