{
  "type": "Feature",
  "properties": {
    "addr:full":"47840 Bougainvillea St La Quinta CA 92253",
    "addr:postcode":"47840;92253",
    "addr:street":"Bougainvillea St",
    "iso:country":"US",
    "sg:address":"47840 Bougainvillea St",
    "sg:city":"La Quinta",
    "sg:classifiers":[
        {
            "category":"Professional",
            "type":"Services"
        }
    ],
    "sg:phone":"+1 760 564 1497",
    "sg:postcode":"92253",
    "sg:province":"CA",
    "sg:tags":[
        "establishment"
    ],
    "wof:name":"DCTC Joint Venture",
    "wof:placetype":"venue"
},
  "geometry": {"coordinates":[-116.271581,33.700997],"type":"Point"}
}