{
  "type": "Feature",
  "properties": {
    "iso:country":"US",
    "sg:address":"72333 Hwy 111",
    "sg:city":"Palm Desert",
    "sg:classifiers":[
        {
            "category":"Professional",
            "subcategory":"Management & Consulting",
            "type":"Services"
        }
    ],
    "sg:phone":"+1 760 328 3287",
    "sg:postcode":"92260",
    "sg:province":"CA",
    "sg:tags":[
        "consultant",
        "business"
    ],
    "wof:name":"Kantor Management",
    "wof:placetype":"venue"
},
  "geometry": {"coordinates":[-116.402131,33.727632],"type":"Point"}
}