{
  "type": "Feature",
  "properties": {
    "iso:country":"US",
    "sg:address":"2245 Nice Ave",
    "sg:city":"Mentone",
    "sg:classifiers":[
        {
            "category":"Arts & Performance",
            "subcategory":"Theater",
            "type":"Entertainment"
        }
    ],
    "sg:phone":"+1 909 844 7439",
    "sg:postcode":"92359",
    "sg:province":"CA",
    "sg:tags":[
        "live",
        "music"
    ],
    "wof:name":"Props Productions DJ & Ent",
    "wof:placetype":"venue"
},
  "geometry": {"coordinates":[-117.108379,34.066114],"type":"Point"}
}