{
  "type": "Feature",
  "properties": {
    "addr:full":"5454 Central Ave Newark CA 94560",
    "addr:housenumber":"5454",
    "addr:postcode":"94560",
    "addr:street":"Central Ave",
    "iso:country":"US",
    "sg:address":"5454 Central Ave",
    "sg:city":"Newark",
    "sg:classifiers":[
        {
            "category":"Personal",
            "subcategory":"Beauty Salon",
            "type":"Services"
        }
    ],
    "sg:phone":"+1 510 795 2866",
    "sg:postcode":"94560",
    "sg:province":"CA",
    "wof:name":"Studio 54 Salon",
    "wof:placetype":"venue"
},
  "geometry": {"coordinates":[-122.017565,37.538817],"type":"Point"}
}