{
  "type": "Feature",
  "properties": {
    "iso:country":"US",
    "sg:address":"1235 Broadway St",
    "sg:city":"Chico",
    "sg:classifiers":[
        {
            "category":"Shopping",
            "subcategory":"Used Merchandise",
            "type":"Retail Goods"
        }
    ],
    "sg:phone":"+1 530 343 6285",
    "sg:postcode":"95928",
    "sg:province":"CA",
    "sg:tags":[
        "sector",
        "regulation",
        "commercial"
    ],
    "wof:name":"Corinthian Antiques",
    "wof:placetype":"venue"
},
  "geometry": {"coordinates":[-121.832537,39.722159],"type":"Point"}
}