{
  "type": "Feature",
  "properties": {
    "iso:country":"US",
    "sg:address":"8155 Arroyo Cir",
    "sg:city":"Gilroy",
    "sg:classifiers":[
        {
            "category":"Shopping",
            "type":"Retail Goods"
        }
    ],
    "sg:phone":"+1 408 848 5769",
    "sg:postcode":"95020",
    "sg:province":"CA",
    "sg:tags":[
        "perfume"
    ],
    "wof:name":"Designer Fragrance",
    "wof:placetype":"venue"
},
  "geometry": {"coordinates":[-121.55681,37.01173],"type":"Point"}
}