{
  "type": "Feature",
  "properties": {
    "iso:country":"US",
    "sg:address":"22240 Avalon Blvd",
    "sg:city":"Carson",
    "sg:classifiers":[
        {
            "category":"Autos & Motor Vehicles",
            "subcategory":"Fuel & Gas Station",
            "type":"Retail Goods"
        },
        {
            "category":"Personal",
            "type":"Services"
        },
        {
            "category":"Retail",
            "subcategory":"Auto Repair",
            "type":"Services"
        }
    ],
    "sg:phone":"+1 310 835 9140",
    "sg:postcode":"90745",
    "sg:province":"CA",
    "sg:tags":[
        "towing"
    ],
    "wof:name":"Hasty Mobil Service",
    "wof:placetype":"venue"
},
  "geometry": {"coordinates":[-118.264,33.824699],"type":"Point"}
}