{
  "type": "Feature",
  "properties": {
    "addr:full":"123 S Linden Ave S San Francisco CA 94080",
    "addr:housenumber":"123",
    "addr:postcode":"94080",
    "addr:street":"S Linden Ave S",
    "iso:country":"US",
    "sg:address":"123 S Linden Ave",
    "sg:city":"S San Francisco",
    "sg:classifiers":[
        {
            "category":"Wholesale",
            "subcategory":"Apparel",
            "type":"Manufacturing & Wholesale Goods"
        }
    ],
    "sg:phone":"+1 650 225 9968",
    "sg:postcode":"94080",
    "sg:province":"CA",
    "sg:tags":[
        "sportswear"
    ],
    "wof:name":"Ameritex Souvenir Corp",
    "wof:placetype":"venue"
},
  "geometry": {"coordinates":[-122.414132,37.643198],"type":"Point"}
}