{
  "type": "Feature",
  "properties": {
    "iso:country":"US",
    "sg:address":"3420 W Jefferson Blvd",
    "sg:city":"Los Angeles",
    "sg:classifiers":[
        {
            "category":"Education",
            "subcategory":"School",
            "type":"Public Place"
        }
    ],
    "sg:phone":"+1 323 731 2581",
    "sg:postcode":"90018",
    "sg:province":"CA",
    "wof:name":"Institute Of Islamic Studies",
    "wof:placetype":"venue"
},
  "geometry": {"coordinates":[-118.333614,34.025513],"type":"Point"}
}