{
  "type": "Feature",
  "properties": {
    "iso:country":"US",
    "sg:address":"135 Keyes St",
    "sg:city":"San Jose",
    "sg:classifiers":[
        {
            "category":"Retail",
            "subcategory":"Auto Repair",
            "type":"Services"
        }
    ],
    "sg:phone":"+1 408 297 7455",
    "sg:postcode":"95112",
    "sg:province":"CA",
    "wof:name":"Yip's Auto Center",
    "wof:placetype":"venue"
},
  "geometry": {"coordinates":[-121.87599899999999,37.3209],"type":"Point"}
}