{
  "type": "Feature",
  "properties": {
    "addr:full":"21609 Marilla St Chatsworth CA 91311",
    "addr:housenumber":"21609",
    "addr:postcode":"91311",
    "addr:street":"Marilla St",
    "iso:country":"US",
    "sg:address":"21609 Marilla St",
    "sg:city":"Chatsworth",
    "sg:classifiers":[
        {
            "category":"Building & Trades",
            "subcategory":"Pest Control",
            "type":"Services"
        }
    ],
    "sg:phone":"+1 818 407 1836",
    "sg:postcode":"91311",
    "sg:province":"CA",
    "wof:name":"A Ace Pest & Termite Control",
    "wof:placetype":"venue"
},
  "geometry": {"coordinates":[-118.600847,34.247677],"type":"Point"}
}