{
  "type": "Feature",
  "properties": {
    "iso:country":"US",
    "sg:address":"26277 Mirada St",
    "sg:city":"Highland",
    "sg:classifiers":[
        {
            "category":"Arts & Performance",
            "subcategory":"Theater",
            "type":"Entertainment"
        }
    ],
    "sg:phone":"+1 909 425 5007",
    "sg:postcode":"92346",
    "sg:province":"CA",
    "sg:tags":[
        "bureau"
    ],
    "wof:name":"Big Time Sport & Entertainment",
    "wof:placetype":"venue"
},
  "geometry": {"coordinates":[-117.231246,34.142693],"type":"Point"}
}