{
  "type": "Feature",
  "properties": {
    "addr:full":"4212 167th St Lawndale CA 90260",
    "addr:housenumber":"4212",
    "addr:postcode":"ca 90260",
    "addr:street":"167Th St",
    "iso:country":"US",
    "sg:address":"4212 167th St",
    "sg:city":"Lawndale",
    "sg:classifiers":[
        {
            "category":"Building & Trades",
            "subcategory":"Plumbing",
            "type":"Services"
        }
    ],
    "sg:phone":"+1 310 370 8307",
    "sg:postcode":"90260",
    "sg:province":"CA",
    "sg:tags":[
        "plumbing",
        "contractor"
    ],
    "wof:name":"Vinnie's Plumbing",
    "wof:placetype":"venue"
},
  "geometry": {"coordinates":[-118.351625,33.879332],"type":"Point"}
}