{
  "type": "Feature",
  "properties": {
    "iso:country":"US",
    "sg:address":"3201 Crest Dr",
    "sg:city":"Bakersfield",
    "sg:classifiers":[
        {
            "category":"Health Services",
            "subcategory":"Optometrist",
            "type":"Services"
        }
    ],
    "sg:phone":"+1 661 322 2847",
    "sg:postcode":"93306",
    "sg:province":"CA",
    "wof:name":"Peter C Mitchell OD",
    "wof:placetype":"venue"
},
  "geometry": {"coordinates":[-118.956593,35.410187],"type":"Point"}
}