{
  "type": "Feature",
  "properties": {
    "addr:full":"110 N Rose St Anaheim CA 92805",
    "addr:housenumber":"110",
    "addr:postcode":"92805",
    "addr:street":"N Rose St",
    "iso:country":"US",
    "sg:address":"110 N Rose St",
    "sg:city":"Anaheim",
    "sg:classifiers":[
        {
            "category":"Real Estate",
            "subcategory":"Real Estate Agent",
            "type":"Services"
        }
    ],
    "sg:phone":"+1 714 590 1263",
    "sg:postcode":"92805",
    "sg:province":"CA",
    "sg:website":"www.aopenhouse.com",
    "wof:name":"AOPENHOUSE.COM",
    "wof:placetype":"venue"
},
  "geometry": {"coordinates":[-117.904045,33.838165],"type":"Point"}
}