{
  "type": "Feature",
  "properties": {
    "iso:country":"US",
    "sg:address":"1307 S Mary Avenue",
    "sg:city":"Sunnyvale",
    "sg:classifiers":[
        {
            "category":"Building & Trades",
            "subcategory":"Construction",
            "type":"Services"
        }
    ],
    "sg:phone":"+1 408 733 9693",
    "sg:postcode":"94087",
    "sg:province":"CA",
    "sg:tags":[
        "contractor"
    ],
    "wof:name":"Landmark Development Corporation",
    "wof:placetype":"venue"
},
  "geometry": {"coordinates":[-122.050532,37.35067],"type":"Point"}
}