{
  "type": "Feature",
  "properties": {
    "iso:country":"US",
    "sg:address":"1515 E Shaw Ave",
    "sg:city":"Fresno",
    "sg:classifiers":[
        {
            "category":"Banks & Credit Unions",
            "subcategory":"Bank",
            "type":"Services"
        }
    ],
    "sg:phone":"+1 559 225 7228",
    "sg:postcode":"93710",
    "sg:province":"CA",
    "sg:tags":[
        "commercial",
        "saving"
    ],
    "sg:website":"http://www.statecentercu.com",
    "wof:name":"State Center Credit Union",
    "wof:placetype":"venue"
},
  "geometry": {"coordinates":[-119.760817,36.808285],"type":"Point"}
}