{
  "type": "Feature",
  "properties": {
    "iso:country":"US",
    "sg:address":"301 W Esplanade Dr",
    "sg:city":"Oxnard",
    "sg:classifiers":[
        {
            "category":"Shopping",
            "subcategory":"Department Store",
            "type":"Retail Goods"
        }
    ],
    "sg:phone":"+1 805 485 8731",
    "sg:postcode":"93036",
    "sg:province":"CA",
    "sg:tags":[
        "catalog",
        "center"
    ],
    "wof:name":"Sears",
    "wof:placetype":"venue"
},
  "geometry": {"coordinates":[-119.17527699999999,34.231305],"type":"Point"}
}