{
  "type": "Feature",
  "properties": {
    "iso:country":"US",
    "sg:address":"9021 Las Tunas Dr",
    "sg:city":"Temple City",
    "sg:classifiers":[
        {
            "category":"Cinema",
            "subcategory":"Movie Theater",
            "type":"Entertainment"
        }
    ],
    "sg:phone":"+1 626 309 9525",
    "sg:postcode":"91780",
    "sg:province":"CA",
    "wof:name":"Golin Theaters",
    "wof:placetype":"venue"
},
  "geometry": {"coordinates":[-118.07223999999999,34.103984],"type":"Point"}
}