{
  "type": "Feature",
  "properties": {
    "iso:country":"US",
    "sg:address":"9025 Wilshire Blvd",
    "sg:city":"Beverly Hills",
    "sg:classifiers":[
        {
            "category":"Professional",
            "subcategory":"Business Services",
            "type":"Services"
        }
    ],
    "sg:phone":"+1 310 271 3183",
    "sg:postcode":"90211",
    "sg:province":"CA",
    "sg:tags":[
        "paralegal"
    ],
    "wof:name":"Immigration Collection Prlgls",
    "wof:placetype":"venue"
},
  "geometry": {"coordinates":[-118.387811,34.067121],"type":"Point"}
}