{
  "type": "Feature",
  "properties": {
    "iso:country":"US",
    "sg:address":"534 S Mountain Ave",
    "sg:city":"Ontario",
    "sg:classifiers":[
        {
            "category":"Building & Trades",
            "subcategory":"Construction",
            "type":"Services"
        }
    ],
    "sg:phone":"+1 909 984 6430",
    "sg:postcode":"91762",
    "sg:province":"CA",
    "sg:tags":[
        "fabricator",
        "metal"
    ],
    "wof:name":"Engage Off Road",
    "wof:placetype":"venue"
},
  "geometry": {"coordinates":[-117.669876,34.059315],"type":"Point"}
}