{
  "type": "Feature",
  "properties": {
    "addr:full":"858 G St Arcata CA 95521",
    "addr:housenumber":"858",
    "addr:postcode":"95521",
    "addr:street":"G St",
    "iso:country":"US",
    "sg:address":"858 G St",
    "sg:city":"Arcata",
    "sg:classifiers":[
        {
            "category":"Shopping",
            "subcategory":"Music",
            "type":"Retail Goods"
        }
    ],
    "sg:phone":"+1 707 822 9015",
    "sg:postcode":"95521",
    "sg:province":"CA",
    "sg:tags":[
        "compact",
        "record",
        "disc",
        "tape"
    ],
    "wof:name":"Metro C D's & Tapes",
    "wof:placetype":"venue"
},
  "geometry": {"coordinates":[-124.08582699999999,40.868307],"type":"Point"}
}