{
  "type": "Feature",
  "properties": {
    "iso:country":"US",
    "sg:address":"6930 65th St #117",
    "sg:city":"Sacramento",
    "sg:classifiers":[
        {
            "category":"Restaurant",
            "type":"Food & Drink"
        }
    ],
    "sg:phone":"+1 916 428 8886",
    "sg:postcode":"95823",
    "sg:province":"CA",
    "sg:tags":[
        "sushi",
        "bar",
        "japanese",
        "buffet"
    ],
    "wof:name":"Kawa Sushi Buffet",
    "wof:placetype":"venue"
},
  "geometry": {"coordinates":[-121.433571,38.501225],"type":"Point"}
}