{
  "type": "Feature",
  "properties": {
    "addr:full":"418 6th St Eureka CA 95501",
    "addr:housenumber":"418",
    "addr:postcode":"95501",
    "addr:street":"6Th St",
    "iso:country":"US",
    "sg:address":"418 6th St",
    "sg:city":"Eureka",
    "sg:classifiers":[
        {
            "category":"Personal",
            "subcategory":"Beauty Salon",
            "type":"Services"
        }
    ],
    "sg:phone":"+1 707 445 4856",
    "sg:postcode":"95501",
    "sg:province":"CA",
    "wof:name":"Ann Pfeifer Skin Care",
    "wof:placetype":"venue"
},
  "geometry": {"coordinates":[-124.165882,40.800964],"type":"Point"}
}