{
  "type": "Feature",
  "properties": {
    "iso:country":"US",
    "sg:address":"6929 Sunrise Blvd",
    "sg:city":"Citrus Heights",
    "sg:classifiers":[
        {
            "category":"Real Estate",
            "subcategory":"Real Estate Agent",
            "type":"Services"
        }
    ],
    "sg:phone":"+1 916 652 5854",
    "sg:postcode":"95610",
    "sg:province":"CA",
    "sg:tags":[
        "management"
    ],
    "wof:name":"Adventure West Property Mgmt",
    "wof:placetype":"venue"
},
  "geometry": {"coordinates":[-121.271787,38.694984],"type":"Point"}
}