{
  "type": "Feature",
  "properties": {
    "addr:full":"213 N Evergreen St Anaheim CA 92805",
    "addr:housenumber":"213",
    "addr:postcode":"92805",
    "addr:street":"N Evergreen St",
    "iso:country":"US",
    "sg:address":"213 N Evergreen St",
    "sg:city":"Anaheim",
    "sg:classifiers":[
        {
            "category":"Communications",
            "type":"Services"
        }
    ],
    "sg:phone":"+1 714 776 8419",
    "sg:postcode":"92805",
    "sg:province":"CA",
    "wof:name":"Big Dawg Communication",
    "wof:placetype":"venue"
},
  "geometry": {"coordinates":[-117.89529899999999,33.843212],"type":"Point"}
}