{
  "type": "Feature",
  "properties": {
    "iso:country":"US",
    "sg:address":"213 N Evergreen St",
    "sg:city":"Anaheim",
    "sg:classifiers":[
        {
            "category":"Communications",
            "type":"Services"
        }
    ],
    "sg:phone":"+1 714 776 8419",
    "sg:postcode":"92805",
    "sg:province":"CA",
    "wof:name":"Big Dawg Communication",
    "wof:placetype":"venue"
},
  "geometry": {"coordinates":[-117.895299,33.843212],"type":"Point"}
}