{
  "type": "Feature",
  "properties": {
    "iso:country":"US",
    "sg:address":"5188 Etiwanda Ave",
    "sg:city":"Mira Loma",
    "sg:classifiers":[
        {
            "category":"Shopping",
            "type":"Retail Goods"
        }
    ],
    "sg:phone":"+1 909 361 3674",
    "sg:postcode":"91752",
    "sg:province":"CA",
    "sg:tags":[
        "merchandise"
    ],
    "wof:name":"Zefati Cellular & Music",
    "wof:placetype":"venue"
},
  "geometry": {"coordinates":[-117.523275,33.996166],"type":"Point"}
}