{
  "type": "Feature",
  "properties": {
    "iso:country":"US",
    "sg:address":"816 McMinn Ave",
    "sg:city":"Santa Rosa",
    "sg:classifiers":[
        {
            "category":"Food & Beverages",
            "subcategory":"Groceries & Convenience Stores",
            "type":"Retail Goods"
        }
    ],
    "sg:phone":"+1 707 528 2382",
    "sg:postcode":"95407",
    "sg:province":"CA",
    "wof:name":"Quik Stop",
    "wof:placetype":"venue"
},
  "geometry": {"coordinates":[-122.732357,38.428942],"type":"Point"}
}