{
  "type": "Feature",
  "properties": {
    "addr:full":"15739 Via Nueva San Lorenzo CA 94580",
    "addr:housenumber":"15739",
    "addr:postcode":"94580",
    "addr:street":"Via Nueva San Lorenzo",
    "iso:country":"US",
    "sg:address":"15739 Via Nueva",
    "sg:city":"San Lorenzo",
    "sg:classifiers":[
        {
            "category":"Wholesale",
            "subcategory":"Plants",
            "type":"Manufacturing & Wholesale Goods"
        }
    ],
    "sg:phone":"+1 510 278 4177",
    "sg:postcode":"94580",
    "sg:province":"CA",
    "sg:tags":[
        "supply"
    ],
    "wof:name":"Flowers By Negrette",
    "wof:placetype":"venue"
},
  "geometry": {"coordinates":[-122.148335,37.67586],"type":"Point"}
}