{
  "type": "Feature",
  "properties": {
    "addr:full":"4400 W Tulare Ave Visalia CA 93277",
    "addr:housenumber":"4400",
    "addr:postcode":"93277",
    "addr:street":"W Tulare Ave",
    "iso:country":"US",
    "sg:address":"4400 W Tulare Ave",
    "sg:city":"Visalia",
    "sg:classifiers":[
        {
            "category":"Organizations",
            "subcategory":"Religious Organization",
            "type":"Services"
        }
    ],
    "sg:phone":"+1 559 733 7859",
    "sg:postcode":"93277",
    "sg:province":"CA",
    "sg:tags":[
        "church"
    ],
    "sg:website":"www.heartofthevalley.org",
    "wof:name":"Heart Of The Valley Christian",
    "wof:placetype":"venue"
},
  "geometry": {"coordinates":[-119.33778599999999,36.32013],"type":"Point"}
}