{
  "type": "Feature",
  "properties": {
    "iso:country":"US",
    "sg:address":"2014 Capitol Ave",
    "sg:city":"Sacramento",
    "sg:classifiers":[
        {
            "category":"Organizations",
            "subcategory":"Religious Organization",
            "type":"Services"
        },
        {
            "category":"Organizations",
            "subcategory":"Non-profit Organization",
            "type":"Services"
        }
    ],
    "sg:phone":"+1 916 486 0906",
    "sg:postcode":"95811",
    "sg:province":"CA",
    "sg:tags":[
        "service/non-profit",
        "community"
    ],
    "sg:website":"www.jewishsac.org",
    "wof:name":"The Jewish Federation of the Sacramento Region",
    "wof:placetype":"venue"
},
  "geometry": {"coordinates":[-121.481016,38.572903],"type":"Point"}
}