{
  "type": "Feature",
  "properties": {
    "iso:country":"US",
    "sg:address":"Sak's Fifth Avenue 9600 Wilshire Blvd",
    "sg:city":"Beverly Hills",
    "sg:phone":"+1 310 275 4211",
    "sg:postcode":"90212",
    "sg:province":"CA",
    "wof:name":"SnAKS",
    "wof:placetype":"venue"
},
  "geometry": {"coordinates":[-118.40372,34.066723],"type":"Point"}
}