{
  "type": "Feature",
  "properties": {
    "iso:country":"US",
    "sg:address":"3526 Stockton Pl",
    "sg:city":"Carlsbad",
    "sg:classifiers":[
        {
            "category":"Banks & Credit Unions",
            "subcategory":"Financial Services",
            "type":"Services"
        }
    ],
    "sg:phone":"+1 760 720 1934",
    "sg:postcode":"92010",
    "sg:province":"CA",
    "sg:tags":[
        "consultant",
        "real estate"
    ],
    "wof:name":"Thompson & Associates",
    "wof:placetype":"venue"
},
  "geometry": {"coordinates":[-117.30027,33.17556],"type":"Point"}
}