{
  "type": "Feature",
  "properties": {
    "iso:country":"US",
    "sg:address":"572 W Sierra Ave",
    "sg:city":"Clovis",
    "sg:classifiers":[
        {
            "category":"Farming",
            "subcategory":"Orchard",
            "type":"Manufacturing & Wholesale Goods"
        }
    ],
    "sg:phone":"+1 559 299 8390",
    "sg:postcode":"93612",
    "sg:province":"CA",
    "sg:tags":[
        "fruit",
        "tree"
    ],
    "wof:name":"Arakelian Aram",
    "wof:placetype":"venue"
},
  "geometry": {"coordinates":[-119.721644,36.830194],"type":"Point"}
}