{
  "type": "Feature",
  "properties": {
    "iso:country":"US",
    "sg:address":"2930 Summit St",
    "sg:city":"Oakland",
    "sg:classifiers":[
        {
            "category":"Health Services",
            "subcategory":"Dentist",
            "type":"Services"
        }
    ],
    "sg:phone":"+1 510 839 9480",
    "sg:postcode":"94609",
    "sg:province":"CA",
    "sg:tags":[
        "dentists-endodontists",
        "endodontist"
    ],
    "sg:website":"www.oaklandalamedaendo.com",
    "wof:name":"Oakland-Alameda Endodontics",
    "wof:placetype":"venue"
},
  "geometry": {"coordinates":[-122.26445699999999,37.818225],"type":"Point"}
}