{
  "type": "Feature",
  "properties": {
    "addr:full":"5331 Mount Alifan Dr San Diego CA 92111",
    "addr:housenumber":"5331",
    "addr:postcode":"92111",
    "addr:street":"Mount Alifan Dr",
    "iso:country":"US",
    "sg:address":"5331 Mount Alifan Dr",
    "sg:city":"San Diego",
    "sg:classifiers":[
        {
            "category":"Place Of Worship",
            "subcategory":"Church",
            "type":"Public Place"
        },
        {
            "category":"Education",
            "subcategory":"School",
            "type":"Public Place"
        }
    ],
    "sg:phone":"+1 858 277 4991",
    "sg:postcode":"92111",
    "sg:province":"CA",
    "sg:tags":[
        "high",
        "middle",
        "elementary"
    ],
    "sg:website":"www.horizonsd.org",
    "wof:name":"Horizon Christian Fellowship",
    "wof:placetype":"venue"
},
  "geometry": {"coordinates":[-117.182175,32.81675],"type":"Point"}
}