{
  "type": "Feature",
  "properties": {
    "addr:full":"24730 Avenue Tibbitts #160 Valencia CA 91355",
    "addr:housenumber":"24730",
    "addr:postcode":"91355",
    "addr:street":"Avenue Tibbitts # 160",
    "iso:country":"US",
    "sg:address":"24730 Avenue Tibbitts #160",
    "sg:city":"Valencia",
    "sg:classifiers":[
        {
            "category":"Building & Trades",
            "subcategory":"Construction",
            "type":"Services"
        }
    ],
    "sg:phone":"+1 661 775 7430",
    "sg:postcode":"91355",
    "sg:province":"CA",
    "sg:tags":[
        "interior",
        "design",
        "contractor"
    ],
    "sg:website":"www.dannickdesign.com",
    "wof:name":"Dannick Design",
    "wof:placetype":"venue"
},
  "geometry": {"coordinates":[-118.565105,34.435273],"type":"Point"}
}