{
  "type": "Feature",
  "properties": {
    "addr:full":"575 E Main St El Cajon CA 92020",
    "addr:housenumber":"575",
    "addr:postcode":"92020",
    "addr:street":"E Main St",
    "iso:country":"US",
    "sg:address":"575 E Main St",
    "sg:city":"El Cajon",
    "sg:classifiers":[
        {
            "category":"Shopping",
            "subcategory":"Clothing, Apparel, & Fashions",
            "type":"Retail Goods"
        }
    ],
    "sg:phone":"+1 619 444 1200",
    "sg:postcode":"92020",
    "sg:province":"CA",
    "sg:tags":[
        "shop",
        "bridal"
    ],
    "wof:name":"Sara's Fashion",
    "wof:placetype":"venue"
},
  "geometry": {"coordinates":[-116.955607,32.794852],"type":"Point"}
}