{
  "type": "Feature",
  "properties": {
    "addr:full":"17091 Newland St Huntington Beach CA 92647",
    "addr:housenumber":"17091",
    "addr:postcode":"92647",
    "addr:street":"Newland St",
    "iso:country":"US",
    "sg:address":"17091 Newland St",
    "sg:city":"Huntington Beach",
    "sg:classifiers":[
        {
            "category":"Fast Food",
            "type":"Food & Drink"
        },
        {
            "category":"Restaurant",
            "type":"Food & Drink"
        }
    ],
    "sg:phone":"+1 714 848 9406",
    "sg:postcode":"92647",
    "sg:province":"CA",
    "sg:tags":[
        "traditional",
        "burger",
        "american",
        "mexican"
    ],
    "wof:name":"Bun & Burger",
    "wof:placetype":"venue"
},
  "geometry": {"coordinates":[-117.98053400000001,33.714379],"type":"Point"}
}