{
  "type": "Feature",
  "properties": {
    "addr:full":"225 N Rancho Santa Fe Rd San Marcos CA 92069",
    "addr:housenumber":"225",
    "addr:postcode":"92069",
    "addr:street":"N Rancho Santa Fe Rd",
    "iso:country":"US",
    "sg:address":"225 N Rancho Santa Fe Rd",
    "sg:city":"San Marcos",
    "sg:classifiers":[
        {
            "category":"Restaurant",
            "type":"Food & Drink"
        }
    ],
    "sg:phone":"+1 760 510 9940",
    "sg:postcode":"92069",
    "sg:province":"CA",
    "wof:name":"Europian Market",
    "wof:placetype":"venue"
},
  "geometry": {"coordinates":[-117.19592299999999,33.152719],"type":"Point"}
}