{
  "type": "Feature",
  "properties": {
    "addr:full":"2148 Glendale Galleria Glendale CA 91210",
    "addr:housenumber":"2148",
    "addr:postcode":"91210",
    "addr:street":"Glendale Galleria",
    "iso:country":"US",
    "sg:address":"2148 Glendale Galleria",
    "sg:city":"Glendale",
    "sg:classifiers":[
        {
            "category":"Shopping",
            "subcategory":"Jewelry",
            "type":"Retail Goods"
        }
    ],
    "sg:phone":"+1 818 549 0856",
    "sg:postcode":"91210",
    "sg:province":"CA",
    "sg:website":"www.kevinjewelers.com",
    "wof:name":"Kevin Jewelers",
    "wof:placetype":"venue"
},
  "geometry": {"coordinates":[-118.25954900000001,34.144816],"type":"Point"}
}