{
  "type": "Feature",
  "properties": {
    "addr:full":"4638 Meridian Ave San Jose CA 95124",
    "addr:housenumber":"4638",
    "addr:postcode":"95124",
    "addr:street":"Meridian Ave",
    "iso:country":"US",
    "sg:address":"4638 Meridian Ave",
    "sg:city":"San Jose",
    "sg:classifiers":[
        {
            "category":"Shopping",
            "subcategory":"Florist",
            "type":"Retail Goods"
        }
    ],
    "sg:phone":"+1 408 267 7300",
    "sg:postcode":"95124",
    "sg:province":"CA",
    "sg:website":"www.annies-florist.com",
    "wof:name":"Annie's Florist",
    "wof:placetype":"venue"
},
  "geometry": {"coordinates":[-121.898329,37.25546],"type":"Point"}
}