{
  "type": "Feature",
  "properties": {
    "iso:country":"US",
    "sg:address":"55 Mitchell Blvd",
    "sg:city":"San Rafael",
    "sg:classifiers":[
        {
            "category":"Shopping",
            "subcategory":"Hobbies, Toys, & Games",
            "type":"Retail Goods"
        }
    ],
    "sg:phone":"+1 415 499 0664",
    "sg:postcode":"94903",
    "sg:province":"CA",
    "sg:tags":[
        "model",
        "supply"
    ],
    "wof:name":"Feather River Train Shop",
    "wof:placetype":"venue"
},
  "geometry": {"coordinates":[-122.539309,38.017223],"type":"Point"}
}