{
  "type": "Feature",
  "properties": {
    "addr:full":"1105 Airport Rd Monterey CA 93940",
    "addr:housenumber":"1105",
    "addr:postcode":"93940",
    "addr:street":"Airport Rd",
    "iso:country":"US",
    "sg:address":"1105 Airport Rd",
    "sg:city":"Monterey",
    "sg:classifiers":[
        {
            "category":"Building & Trades",
            "subcategory":"Construction",
            "type":"Services"
        }
    ],
    "sg:phone":"+1 831 656 9500",
    "sg:postcode":"93940",
    "sg:province":"CA",
    "sg:tags":[
        "maker",
        "cabinet"
    ],
    "wof:name":"Martin C Dehmler Fine Cabinet",
    "wof:placetype":"venue"
},
  "geometry": {"coordinates":[-121.851546,36.592517],"type":"Point"}
}