{
  "type": "Feature",
  "properties": {
    "addr:full":"8505 Saran Dr Playa Del Rey CA 90293",
    "addr:housenumber":"8505",
    "addr:postcode":"90293",
    "addr:street":"Saran Dr",
    "iso:country":"US",
    "sg:address":"8505 Saran Dr",
    "sg:city":"Playa Del Rey",
    "sg:classifiers":[
        {
            "category":"Social Services",
            "subcategory":"Child Care",
            "type":"Services"
        },
        {
            "category":"Education",
            "subcategory":"Preschool",
            "type":"Public Place"
        },
        {
            "category":"Education",
            "subcategory":"School",
            "type":"Public Place"
        }
    ],
    "sg:phone":"+1 310 823 0844",
    "sg:postcode":"90293",
    "sg:province":"CA",
    "sg:tags":[
        "elementary",
        "day"
    ],
    "wof:name":"Del Rey Christian Children's Center",
    "wof:placetype":"venue"
},
  "geometry": {"coordinates":[-118.431999,33.960499],"type":"Point"}
}