{
  "type": "Feature",
  "properties": {
    "iso:country":"US",
    "sg:address":"1041 U St",
    "sg:city":"Rio Linda",
    "sg:classifiers":[
        {
            "category":"Building & Trades",
            "subcategory":"Construction",
            "type":"Services"
        }
    ],
    "sg:phone":"+1 916 991 6740",
    "sg:postcode":"95673",
    "sg:province":"CA",
    "sg:tags":[
        "coping",
        "plastering",
        "tiling",
        "pool",
        "swimming"
    ],
    "wof:name":"Nelson & Nelson Pool Care",
    "wof:placetype":"venue"
},
  "geometry": {"coordinates":[-121.43368599999999,38.70484],"type":"Point"}
}