{
  "type": "Feature",
  "properties": {
    "iso:country":"US",
    "sg:address":"2405 Forest Ave",
    "sg:city":"San Jose",
    "sg:classifiers":[
        {
            "category":"Health Services",
            "subcategory":"Doctor",
            "type":"Services"
        }
    ],
    "sg:phone":"+1 408 258 0777",
    "sg:postcode":"95128",
    "sg:province":"CA",
    "sg:tags":[
        "physician",
        "surgeon"
    ],
    "wof:name":"Park Hyun K MD Facog",
    "wof:placetype":"venue"
},
  "geometry": {"coordinates":[-121.946793,37.327043],"type":"Point"}
}