{
  "type": "Feature",
  "properties": {
    "iso:country":"US",
    "sg:address":"711 Fair Oaks Ave Ste M",
    "sg:city":"South Pasadena",
    "sg:classifiers":[
        {
            "category":"Restaurant",
            "type":"Food & Drink"
        }
    ],
    "sg:phone":"+1 626 441 2489",
    "sg:postcode":"91030",
    "sg:province":"CA",
    "sg:tags":[
        "thai"
    ],
    "wof:name":"Patakan Thai Restaurant",
    "wof:placetype":"venue"
},
  "geometry": {"coordinates":[-118.15047,34.117537],"type":"Point"}
}