{
  "type": "Feature",
  "properties": {
    "addr:full":"701 N Stockton St Lodi CA 95240",
    "addr:housenumber":"701",
    "addr:postcode":"95240",
    "addr:street":"N Stockton St",
    "iso:country":"US",
    "sg:address":"701 N Stockton St",
    "sg:city":"Lodi",
    "sg:classifiers":[
        {
            "category":"Organizations",
            "subcategory":"Religious Organization",
            "type":"Services"
        }
    ],
    "sg:phone":"+1 209 333 2526",
    "sg:postcode":"95240",
    "sg:province":"CA",
    "sg:tags":[
        "church"
    ],
    "wof:name":"Cornerstone Evangelical Free",
    "wof:placetype":"venue"
},
  "geometry": {"coordinates":[-121.268947,38.14167],"type":"Point"}
}