{
  "type": "Feature",
  "properties": {
    "iso:country":"US",
    "sg:address":"6951 World Way W",
    "sg:city":"Los Angeles",
    "sg:classifiers":[
        {
            "category":"Airline",
            "type":"Transportation"
        }
    ],
    "sg:phone":"+1 310 646 3747",
    "sg:postcode":"90045",
    "sg:province":"CA",
    "sg:tags":[
        "airport"
    ],
    "wof:name":"Menzies Aviation Group",
    "wof:placetype":"venue"
},
  "geometry": {"coordinates":[-118.419855,33.941939],"type":"Point"}
}