{
  "type": "Feature",
  "properties": {
    "addr:full":"825 Park Way S San Francisco CA 94080",
    "addr:housenumber":"825",
    "addr:postcode":"94080",
    "addr:street":"Park Way S",
    "iso:country":"US",
    "sg:address":"825 Park Way",
    "sg:city":"S San Francisco",
    "sg:classifiers":[
        {
            "category":"Social Services",
            "type":"Services"
        }
    ],
    "sg:phone":"+1 650 583 0392",
    "sg:postcode":"94080",
    "sg:province":"CA",
    "sg:tags":[
        "organization",
        "welfare"
    ],
    "sg:website":"www.familiesontrack.org",
    "wof:name":"Families On Track",
    "wof:placetype":"venue"
},
  "geometry": {"coordinates":[-122.41920500000001,37.661292],"type":"Point"}
}