{
  "type": "Feature",
  "properties": {
    "addr:full":"1073 W Terrace Dr Hanford CA 93230",
    "addr:housenumber":"1073",
    "addr:postcode":"ca 93230",
    "addr:street":"W Terrace Dr",
    "iso:country":"US",
    "sg:address":"1073 W Terrace Dr",
    "sg:city":"Hanford",
    "sg:classifiers":[
        {
            "category":"Professional",
            "type":"Services"
        }
    ],
    "sg:phone":"+1 559 583 7802",
    "sg:postcode":"93230",
    "sg:province":"CA",
    "sg:tags":[
        "establishment"
    ],
    "wof:name":"Smith Residential Care",
    "wof:placetype":"venue"
},
  "geometry": {"coordinates":[-119.660218,36.345721],"type":"Point"}
}