{
  "type": "Feature",
  "properties": {
    "iso:country":"US",
    "sg:address":"1827 State St",
    "sg:city":"Santa Barbara",
    "sg:classifiers":[
        {
            "category":"Retail",
            "subcategory":"Laundry & Dry Cleaning",
            "type":"Services"
        },
        {
            "category":"Shopping",
            "subcategory":"Clothing, Apparel, & Fashions",
            "type":"Retail Goods"
        }
    ],
    "sg:phone":"+1 805 569 6969",
    "sg:postcode":"93101",
    "sg:province":"CA",
    "sg:tags":[
        "tailor"
    ],
    "wof:name":"Adam's Tailor",
    "wof:placetype":"venue"
},
  "geometry": {"coordinates":[-119.713176,34.429599],"type":"Point"}
}