{
  "type": "Feature",
  "properties": {
    "addr:full":"1492 McAllister Street San Francisco CA 94115",
    "addr:housenumber":"1492",
    "addr:postcode":"94115",
    "addr:street":"Mcallister Street",
    "iso:country":"US",
    "sg:address":"1492 McAllister Street",
    "sg:city":"San Francisco",
    "sg:classifiers":[
        {
            "category":"Personal",
            "subcategory":"Nail Salon",
            "type":"Services"
        }
    ],
    "sg:phone":"+1 415 346 1909",
    "sg:postcode":"94115",
    "sg:province":"CA",
    "wof:name":"Ivory-Moi",
    "wof:placetype":"venue"
},
  "geometry": {"coordinates":[-122.435997,37.778198],"type":"Point"}
}