{
  "type": "Feature",
  "properties": {
    "iso:country":"US",
    "sg:address":"351 N Walnut Rd",
    "sg:city":"Turlock",
    "sg:classifiers":[
        {
            "category":"Manufacturing",
            "subcategory":"Tools & Machinery",
            "type":"Manufacturing & Wholesale Goods"
        }
    ],
    "sg:phone":"+1 209 669 1064",
    "sg:postcode":"95380",
    "sg:province":"CA",
    "sg:tags":[
        "machine",
        "shop",
        "industrial",
        "mfg"
    ],
    "wof:name":"Jon's Precision Machining",
    "wof:placetype":"venue"
},
  "geometry": {"coordinates":[-120.87231,37.495889],"type":"Point"}
}