{
  "type": "Feature",
  "properties": {
    "addr:full":"8616 Lodestone Cir Elk Grove CA 95624",
    "addr:housenumber":"8616",
    "addr:postcode":"95624",
    "addr:street":"Lodestone Cir",
    "iso:country":"US",
    "sg:address":"8616 Lodestone Cir",
    "sg:city":"Elk Grove",
    "sg:classifiers":[
        {
            "category":"Professional",
            "subcategory":"Business Services",
            "type":"Services"
        }
    ],
    "sg:phone":"+1 916 685 7623",
    "sg:postcode":"95624",
    "sg:province":"CA",
    "sg:tags":[
        "recording",
        "studio"
    ],
    "wof:name":"Real Beal Records",
    "wof:placetype":"venue"
},
  "geometry": {"coordinates":[-121.378597,38.403172],"type":"Point"}
}