{
  "type": "Feature",
  "properties": {
    "iso:country":"US",
    "sg:address":"29 Catalpa Ave",
    "sg:city":"Mill Valley",
    "sg:classifiers":[
        {
            "category":"Professional",
            "type":"Services"
        }
    ],
    "sg:phone":"+1 415 383 1881",
    "sg:postcode":"94941",
    "sg:province":"CA",
    "wof:name":"Lucebet LLC",
    "wof:placetype":"venue"
},
  "geometry": {"coordinates":[-122.537321,37.902068],"type":"Point"}
}