{
  "type": "Feature",
  "properties": {
    "addr:full":"2298 E 14th St San Leandro CA 94577",
    "addr:housenumber":"2298",
    "addr:postcode":"94577",
    "addr:street":"E 14Th St",
    "iso:country":"US",
    "sg:address":"2298 E 14th St",
    "sg:city":"San Leandro",
    "sg:classifiers":[
        {
            "category":"Cinema",
            "subcategory":"Movie Rental",
            "type":"Entertainment"
        }
    ],
    "sg:phone":"+1 510 483 7733",
    "sg:postcode":"94577",
    "sg:province":"CA",
    "sg:tags":[
        "game",
        "video"
    ],
    "wof:name":"Video Experience",
    "wof:placetype":"venue"
},
  "geometry": {"coordinates":[-122.146384,37.718123],"type":"Point"}
}