{
  "type": "Feature",
  "properties": {
    "iso:country":"US",
    "sg:address":"3606 Mountain Shadows Ct",
    "sg:city":"Palmdale",
    "sg:classifiers":[
        {
            "category":"Real Estate",
            "subcategory":"Real Estate Services",
            "type":"Services"
        },
        {
            "category":"Building & Trades",
            "subcategory":"Cleaning & Sanitation",
            "type":"Services"
        }
    ],
    "sg:phone":"+1 661 266 1063",
    "sg:postcode":"93551",
    "sg:province":"CA",
    "sg:tags":[
        "maintenance",
        "cleaners-interior"
    ],
    "wof:name":"Sunrise Maintenance Corporation",
    "wof:placetype":"venue"
},
  "geometry": {"coordinates":[-118.194738,34.620774],"type":"Point"}
}