{
  "type": "Feature",
  "properties": {
    "addr:full":"3992 Douglas Blvd Roseville CA 95678",
    "addr:housenumber":"3992",
    "addr:postcode":"95678",
    "addr:street":"Douglas Blvd",
    "iso:country":"US",
    "sg:address":"3992 Douglas Blvd",
    "sg:city":"Roseville",
    "sg:classifiers":[
        {
            "category":"Food & Beverages",
            "subcategory":"Bakery",
            "type":"Retail Goods"
        }
    ],
    "sg:phone":"+1 916 789 7737",
    "sg:postcode":"95678",
    "sg:province":"CA",
    "sg:tags":[
        "cookie",
        "cracker"
    ],
    "wof:name":"Cookie Connection",
    "wof:placetype":"venue"
},
  "geometry": {"coordinates":[-121.226443,38.743786],"type":"Point"}
}