{
  "type": "Feature",
  "properties": {
    "addr:full":"1830 E Washington Blvd Pasadena CA 91104",
    "addr:housenumber":"1830",
    "addr:postcode":"91104",
    "addr:street":"E Washington Blvd",
    "iso:country":"US",
    "sg:address":"1830 E Washington Blvd",
    "sg:city":"Pasadena",
    "sg:classifiers":[
        {
            "category":"Coffee & Tea",
            "type":"Food & Drink"
        }
    ],
    "sg:menulink":"http://www.allmenus.com/ca/pasadena/108103-starbucks-coffee/menu/",
    "sg:phone":"+1 626 296 1248",
    "sg:postcode":"91104",
    "sg:province":"CA",
    "sg:tags":[
        "american"
    ],
    "wof:name":"Starbucks Coffee",
    "wof:placetype":"venue"
},
  "geometry": {"coordinates":[-118.11274,34.168873],"type":"Point"}
}