{
  "type": "Feature",
  "properties": {
    "addr:full":"139 S Market St Inglewood CA 90301",
    "addr:housenumber":"139",
    "addr:postcode":"90301",
    "addr:street":"S Market St",
    "iso:country":"US",
    "sg:address":"139 S Market St",
    "sg:city":"Inglewood",
    "sg:classifiers":[
        {
            "category":"Shopping",
            "subcategory":"Department Store",
            "type":"Retail Goods"
        }
    ],
    "sg:phone":"+1 310 673 3175",
    "sg:postcode":"90301",
    "sg:province":"CA",
    "wof:name":"J Fashion",
    "wof:placetype":"venue"
},
  "geometry": {"coordinates":[-118.351997,33.9622],"type":"Point"}
}