{
  "type": "Feature",
  "properties": {
    "addr:full":"6455 Mesquite Ave Twentynine Palms CA 92277",
    "addr:housenumber":"6455",
    "addr:postcode":"92277",
    "addr:street":"Mesquite Ave",
    "iso:country":"US",
    "sg:address":"6455 Mesquite Ave",
    "sg:city":"Twentynine Palms",
    "sg:classifiers":[
        {
            "category":"Organizations",
            "subcategory":"Professional Association",
            "type":"Services"
        }
    ],
    "sg:phone":"+1 760 367 3445",
    "sg:postcode":"92277",
    "sg:province":"CA",
    "sg:tags":[
        "chambers",
        "commerce"
    ],
    "wof:name":"Twentynine Palms Chamber-Cmrc",
    "wof:placetype":"venue"
},
  "geometry": {"coordinates":[-116.051408,34.13666],"type":"Point"}
}