{
  "type": "Feature",
  "properties": {
    "iso:country":"US",
    "sg:address":"234 E Foothill Blvd",
    "sg:city":"Azusa",
    "sg:classifiers":[
        {
            "category":"Health Services",
            "subcategory":"Doctor",
            "type":"Services"
        }
    ],
    "sg:phone":"+1 626 812 6131",
    "sg:postcode":"91702",
    "sg:province":"CA",
    "sg:tags":[
        "clinic"
    ],
    "wof:name":"Clinica Medica Latino Amrcn",
    "wof:placetype":"venue"
},
  "geometry": {"coordinates":[-117.905947,34.133385],"type":"Point"}
}