{
  "type": "Feature",
  "properties": {
    "iso:country":"US",
    "sg:address":"3301 Barham Boulevard",
    "sg:city":"Los Angeles",
    "sg:classifiers":[
        {
            "category":"Communications",
            "subcategory":"Radio Station",
            "type":"Services"
        }
    ],
    "sg:phone":"+1 323 512 2225",
    "sg:postcode":"90068",
    "sg:province":"CA",
    "wof:name":"Lotus Communications Corporation",
    "wof:placetype":"venue"
},
  "geometry": {"coordinates":[-118.345207,34.130912],"type":"Point"}
}