{
  "type": "Feature",
  "properties": {
    "addr:full":"3016 W Pontiac Way Fresno CA 93722",
    "addr:housenumber":"3016",
    "addr:postcode":"93722",
    "addr:street":"W Pontiac Way",
    "iso:country":"US",
    "sg:address":"3016 W Pontiac Way",
    "sg:city":"Fresno",
    "sg:classifiers":[
        {
            "category":"Wholesale",
            "subcategory":"Groceries",
            "type":"Manufacturing & Wholesale Goods"
        }
    ],
    "sg:phone":"+1 559 225 7221",
    "sg:postcode":"93722",
    "sg:province":"CA",
    "wof:name":"Western Brokerage Co",
    "wof:placetype":"venue"
},
  "geometry": {"coordinates":[-119.845063,36.789687],"type":"Point"}
}