{
  "type": "Feature",
  "properties": {
    "addr:full":"1525 S Escondido Blvd Escondido CA 92025",
    "addr:housenumber":"1525",
    "addr:postcode":"92025",
    "addr:street":"S Escondido Blvd",
    "iso:country":"US",
    "sg:address":"1525 S Escondido Blvd",
    "sg:city":"Escondido",
    "sg:classifiers":[
        {
            "category":"Professional",
            "subcategory":"Accounting & Tax Preparation",
            "type":"Services"
        }
    ],
    "sg:phone":"+1 760 737 2900",
    "sg:postcode":"92025",
    "sg:province":"CA",
    "sg:tags":[
        "return",
        "filing"
    ],
    "wof:name":"Liroje Notary & Tax Svc",
    "wof:placetype":"venue"
},
  "geometry": {"coordinates":[-117.074917,33.107103],"type":"Point"}
}