{
  "type": "Feature",
  "properties": {
    "addr:full":"5690 Dehesa Rd El Cajon CA 92019",
    "addr:housenumber":"5690",
    "addr:postcode":"92019",
    "addr:street":"Dehesa Rd",
    "iso:country":"US",
    "sg:address":"5690 Dehesa Rd",
    "sg:city":"El Cajon",
    "sg:classifiers":[
        {
            "category":"Shopping",
            "type":"Retail Goods"
        }
    ],
    "sg:phone":"+1 619 445 4800",
    "sg:postcode":"92019",
    "sg:province":"CA",
    "sg:tags":[
        "merchandise",
        "animal"
    ],
    "wof:name":"B I S Summerwinds Inc",
    "wof:placetype":"venue"
},
  "geometry": {"coordinates":[-116.82887700000001,32.797104],"type":"Point"}
}