{
  "type": "Feature",
  "properties": {
    "addr:full":"496 Redwing Rd Chula Vista CA 91911",
    "addr:housenumber":"496",
    "addr:postcode":"91911",
    "addr:street":"Redwing Rd",
    "iso:country":"US",
    "sg:address":"496 Redwing Rd",
    "sg:city":"Chula Vista",
    "sg:classifiers":[
        {
            "category":"Shopping",
            "subcategory":"Gifts & Souvenirs",
            "type":"Retail Goods"
        }
    ],
    "sg:phone":"+1 619 421 2059",
    "sg:postcode":"91911",
    "sg:province":"CA",
    "sg:tags":[
        "announcement",
        "invitation"
    ],
    "wof:name":"Januine Creations",
    "wof:placetype":"venue"
},
  "geometry": {"coordinates":[-117.034733,32.616035],"type":"Point"}
}