{
  "type": "Feature",
  "properties": {
    "addr:full":"1606 W Magnolia Blvd Burbank CA 91506",
    "addr:housenumber":"1606",
    "addr:postcode":"91506",
    "addr:street":"W Magnolia Blvd",
    "iso:country":"US",
    "sg:address":"1606 W Magnolia Blvd",
    "sg:city":"Burbank",
    "sg:classifiers":[
        {
            "category":"Home & Garden",
            "subcategory":"Building Materials",
            "type":"Retail Goods"
        }
    ],
    "sg:phone":"+1 818 841 0621",
    "sg:postcode":"91506",
    "sg:province":"CA",
    "sg:tags":[
        "shower",
        "door",
        "enclosure"
    ],
    "wof:name":"Crestview Glass Co",
    "wof:placetype":"venue"
},
  "geometry": {"coordinates":[-118.326477,34.174633],"type":"Point"}
}