{
  "type": "Feature",
  "properties": {
    "addr:full":"108 Kentucky St Petaluma CA 94952",
    "addr:housenumber":"108",
    "addr:postcode":"94952",
    "addr:street":"Kentucky St",
    "iso:country":"US",
    "sg:address":"108 Kentucky St",
    "sg:city":"Petaluma",
    "sg:classifiers":[
        {
            "category":"Shopping",
            "subcategory":"Clothing, Apparel, & Fashions",
            "type":"Retail Goods"
        }
    ],
    "sg:phone":"+1 707 775 3239",
    "sg:postcode":"94952",
    "sg:province":"CA",
    "sg:tags":[
        "infant",
        "wear"
    ],
    "wof:name":"Kid Exchange & Zoe Women's",
    "wof:placetype":"venue"
},
  "geometry": {"coordinates":[-122.64116799999999,38.233917],"type":"Point"}
}