{
  "type": "Feature",
  "properties": {
    "iso:country":"US",
    "sg:address":"491 Seaport Ct",
    "sg:city":"Redwood City",
    "sg:classifiers":[
        {
            "category":"Professional",
            "subcategory":"Lawyer & Legal Services",
            "type":"Services"
        }
    ],
    "sg:phone":"+1 650 363 8621",
    "sg:postcode":"94063",
    "sg:province":"CA",
    "sg:tags":[
        "attorney"
    ],
    "wof:name":"Sam J Smith",
    "wof:placetype":"venue"
},
  "geometry": {"coordinates":[-122.21129999999999,37.503142],"type":"Point"}
}