{
  "type": "Feature",
  "properties": {
    "iso:country":"US",
    "sg:address":"5100 E La Palma Ave Ste 119",
    "sg:city":"Anaheim",
    "sg:classifiers":[
        {
            "category":"Place Of Worship",
            "subcategory":"Church",
            "type":"Public Place"
        }
    ],
    "sg:phone":"+1 714 777 6850",
    "sg:postcode":"92807",
    "sg:province":"CA",
    "wof:name":"Community Christian Church",
    "wof:placetype":"venue"
},
  "geometry": {"coordinates":[-117.80663300000001,33.858442],"type":"Point"}
}