{
  "type": "Feature",
  "properties": {
    "addr:full":"43233 7th St E Lancaster CA 93535",
    "addr:housenumber":"43233",
    "addr:postcode":"93535",
    "addr:street":"7Th St E",
    "iso:country":"US",
    "sg:address":"43233 7th St E",
    "sg:city":"Lancaster",
    "sg:classifiers":[
        {
            "category":"Organizations",
            "subcategory":"Religious Organization",
            "type":"Services"
        }
    ],
    "sg:phone":"+1 661 949 0011",
    "sg:postcode":"93535",
    "sg:province":"CA",
    "sg:tags":[
        "church"
    ],
    "wof:name":"Apostolic New Life Ministry",
    "wof:placetype":"venue"
},
  "geometry": {"coordinates":[-118.117968,34.668297],"type":"Point"}
}