{
  "type": "Feature",
  "properties": {
    "addr:full":"8225 S Normandie Ave Los Angeles CA 90044",
    "addr:housenumber":"8225",
    "addr:postcode":"90044",
    "addr:street":"S Normandie Ave",
    "iso:country":"US",
    "sg:address":"8225 S Normandie Ave",
    "sg:city":"Los Angeles",
    "sg:classifiers":[
        {
            "category":"Retail",
            "subcategory":"Laundry & Dry Cleaning",
            "type":"Services"
        }
    ],
    "sg:phone":"+1 323 778 8997",
    "sg:postcode":"90044",
    "sg:province":"CA",
    "wof:name":"Plus Cleaners",
    "wof:placetype":"venue"
},
  "geometry": {"coordinates":[-118.30039499999999,33.964359],"type":"Point"}
}