{
  "type": "Feature",
  "properties": {
    "iso:country":"US",
    "sg:address":"441 Merritt Ave",
    "sg:city":"Oakland",
    "sg:classifiers":[
        {
            "category":"Travel",
            "subcategory":"Hotels & Motels",
            "type":"Entertainment"
        }
    ],
    "sg:phone":"+1 510 763 3140",
    "sg:postcode":"94610",
    "sg:province":"CA",
    "wof:name":"Alta Vista",
    "wof:placetype":"venue"
},
  "geometry": {"coordinates":[-122.248411,37.807089],"type":"Point"}
}