{
  "type": "Feature",
  "properties": {
    "addr:full":"622 N Gilbert St Anaheim CA 92801",
    "addr:housenumber":"622",
    "addr:postcode":"92801",
    "addr:street":"N Gilbert St",
    "iso:country":"US",
    "sg:address":"622 N Gilbert St",
    "sg:city":"Anaheim",
    "sg:classifiers":[
        {
            "category":"Organizations",
            "subcategory":"Religious Organization",
            "type":"Services"
        }
    ],
    "sg:phone":"+1 714 535 1313",
    "sg:postcode":"92801",
    "sg:province":"CA",
    "sg:tags":[
        "church"
    ],
    "sg:website":"www.crescentbaptist.org",
    "wof:name":"Crescent Southern Baptist Chr",
    "wof:placetype":"venue"
},
  "geometry": {"coordinates":[-117.967691,33.841381],"type":"Point"}
}