{
  "type": "Feature",
  "properties": {
    "iso:country":"US",
    "sg:address":"17720 Studebaker Rd",
    "sg:city":"Cerritos",
    "sg:classifiers":[
        {
            "category":"Manufacturing",
            "subcategory":"Food",
            "type":"Manufacturing & Wholesale Goods"
        }
    ],
    "sg:phone":"+1 562 924 8855",
    "sg:postcode":"90703",
    "sg:province":"CA",
    "sg:tags":[
        "mfg",
        "milk",
        "fluid"
    ],
    "wof:name":"Dannon Company Inc",
    "wof:placetype":"venue"
},
  "geometry": {"coordinates":[-118.099333,33.870948],"type":"Point"}
}