{
  "type": "Feature",
  "properties": {
    "addr:full":"13 Main St Belvedere Tibrn CA 94920",
    "addr:housenumber":"13",
    "addr:postcode":"94920",
    "addr:street":"Main St",
    "iso:country":"US",
    "sg:address":"13 Main St",
    "sg:city":"Belvedere Tibrn",
    "sg:classifiers":[
        {
            "category":"Shopping",
            "subcategory":"Gifts & Souvenirs",
            "type":"Retail Goods"
        }
    ],
    "sg:phone":"+1 415 435 1321",
    "sg:postcode":"94920",
    "sg:province":"CA",
    "sg:tags":[
        "shop"
    ],
    "wof:name":"Citrus",
    "wof:placetype":"venue"
},
  "geometry": {"coordinates":[-122.456676,37.873087],"type":"Point"}
}