{
  "type": "Feature",
  "properties": {
    "iso:country":"US",
    "sg:address":"2316 S Elm Ave",
    "sg:city":"Fresno",
    "sg:classifiers":[
        {
            "category":"Wholesale",
            "subcategory":"Meat",
            "type":"Manufacturing & Wholesale Goods"
        }
    ],
    "sg:phone":"+1 559 233 5841",
    "sg:postcode":"93706",
    "sg:province":"CA",
    "sg:tags":[
        "packer"
    ],
    "wof:name":"Farmer John Meat Co",
    "wof:placetype":"venue"
},
  "geometry": {"coordinates":[-119.790791,36.71658],"type":"Point"}
}