{
  "type": "Feature",
  "properties": {
    "iso:country":"US",
    "sg:address":"2103 N Broadway",
    "sg:city":"Santa Ana",
    "sg:classifiers":[
        {
            "category":"Health Services",
            "subcategory":"Chiropractor",
            "type":"Services"
        }
    ],
    "sg:phone":"+1 714 550 7701",
    "sg:postcode":"92706",
    "sg:province":"CA",
    "wof:name":"Garcia Carlos T DC",
    "wof:placetype":"venue"
},
  "geometry": {"coordinates":[-117.870003,33.763901],"type":"Point"}
}