{
  "type": "Feature",
  "properties": {
    "addr:full":"21541 Bonita Ter Monte Rio CA 95462",
    "addr:housenumber":"21541",
    "addr:postcode":"95462",
    "addr:street":"Bonita Ter;Rio",
    "iso:country":"US",
    "sg:address":"21541 Bonita Ter",
    "sg:city":"Monte Rio",
    "sg:classifiers":[
        {
            "category":"Building & Trades",
            "subcategory":"Plumbing",
            "type":"Services"
        }
    ],
    "sg:phone":"+1 707 865 1779",
    "sg:postcode":"95462",
    "sg:province":"CA",
    "sg:tags":[
        "plumbing",
        "contractor"
    ],
    "wof:name":"O'Malley Plumbing",
    "wof:placetype":"venue"
},
  "geometry": {"coordinates":[-123.01428,38.463628],"type":"Point"}
}