{
  "type": "Feature",
  "properties": {
    "addr:full":"3785 Wilshire Blvd Ste 22 Los Angeles CA 90010",
    "addr:housenumber":"3785",
    "addr:postcode":"90010",
    "addr:street":"Wilshire Blvd Ste 22",
    "iso:country":"US",
    "sg:address":"3785 Wilshire Blvd Ste 22",
    "sg:city":"Los Angeles",
    "sg:classifiers":[
        {
            "category":"Professional",
            "subcategory":"Business Services",
            "type":"Services"
        },
        {
            "category":"Wholesale",
            "subcategory":"Fruits & Vegetables",
            "type":"Manufacturing & Wholesale Goods"
        }
    ],
    "sg:phone":"+1 213 365 8080",
    "sg:postcode":"90010",
    "sg:province":"CA",
    "sg:tags":[
        "food",
        "delivery",
        "veggie"
    ],
    "sg:website":"dofruit.com",
    "wof:name":"Edible Arrangements",
    "wof:placetype":"venue"
},
  "geometry": {"coordinates":[-118.30866899999999,34.061706],"type":"Point"}
}