{
  "type": "Feature",
  "properties": {
    "addr:full":"3367 Woodland Dr Mariposa CA 95338",
    "addr:housenumber":"3367",
    "addr:postcode":"95338",
    "addr:street":"Woodland Dr",
    "iso:country":"US",
    "sg:address":"3367 Woodland Dr",
    "sg:city":"Mariposa",
    "sg:classifiers":[
        {
            "category":"Organizations",
            "subcategory":"Religious Organization",
            "type":"Services"
        }
    ],
    "sg:phone":"+1 209 742 6136",
    "sg:postcode":"95338",
    "sg:province":"CA",
    "sg:tags":[
        "church"
    ],
    "wof:name":"Grace Community Church",
    "wof:placetype":"venue"
},
  "geometry": {"coordinates":[-119.847313,37.449823],"type":"Point"}
}