{
  "type": "Feature",
  "properties": {
    "addr:full":"1327 W Glenmere St West Covina CA 91790",
    "addr:housenumber":"1327",
    "addr:postcode":"91790",
    "addr:street":"W Glenmere St",
    "iso:country":"US",
    "sg:address":"1327 W Glenmere St",
    "sg:city":"West Covina",
    "sg:classifiers":[
        {
            "category":"Food & Beverages",
            "subcategory":"Specialty",
            "type":"Retail Goods"
        }
    ],
    "sg:phone":"+1 626 916 2050",
    "sg:postcode":"91790",
    "sg:province":"CA",
    "sg:tags":[
        "health",
        "diet"
    ],
    "wof:name":"Megumi Propolis",
    "wof:placetype":"venue"
},
  "geometry": {"coordinates":[-117.950958,34.054887],"type":"Point"}
}