{
  "type": "Feature",
  "properties": {
    "iso:country":"US",
    "sg:address":"3410 Logan Ct",
    "sg:city":"Burbank",
    "sg:classifiers":[
        {
            "category":"Professional",
            "type":"Services"
        }
    ],
    "sg:phone":"+1 818 845 6563",
    "sg:postcode":"91504",
    "sg:province":"CA",
    "sg:tags":[
        "arranger",
        "music",
        "composer"
    ],
    "wof:name":"Ron Jones Productions Inc",
    "wof:placetype":"venue"
},
  "geometry": {"coordinates":[-118.334339,34.216581],"type":"Point"}
}