{
  "type": "Feature",
  "properties": {
    "addr:full":"24398 Rd 148 Tulare CA 93274",
    "addr:postcode":"24398;93274",
    "addr:street":"Rd 148",
    "iso:country":"US",
    "sg:address":"24398 Rd 148",
    "sg:city":"Tulare",
    "sg:classifiers":[
        {
            "category":"Farming",
            "subcategory":"Crops",
            "type":"Manufacturing & Wholesale Goods"
        }
    ],
    "sg:phone":"+1 559 686 7576",
    "sg:postcode":"93274",
    "sg:province":"CA",
    "sg:tags":[
        "grove",
        "nut",
        "tree"
    ],
    "wof:name":"Hughan Farm",
    "wof:placetype":"venue"
},
  "geometry": {"coordinates":[-119.242362,36.237226],"type":"Point"}
}