{
  "type": "Feature",
  "properties": {
    "iso:country":"US",
    "sg:address":"4273 Valley View Rd",
    "sg:city":"El Sobrante",
    "sg:classifiers":[
        {
            "category":"Professional",
            "type":"Services"
        }
    ],
    "sg:phone":"+1 510 223 4348",
    "sg:postcode":"94803",
    "sg:province":"CA",
    "wof:name":"Curves",
    "wof:placetype":"venue"
},
  "geometry": {"coordinates":[-122.29341599999999,37.977948],"type":"Point"}
}