{
  "type": "Feature",
  "properties": {
    "addr:full":"12653 Harbor Blvd Garden Grove CA 92840",
    "addr:housenumber":"12653",
    "addr:postcode":"92840",
    "addr:street":"Harbor Blvd",
    "iso:country":"US",
    "sg:address":"12653 Harbor Blvd",
    "sg:city":"Garden Grove",
    "sg:classifiers":[
        {
            "category":"Restaurant",
            "type":"Food & Drink"
        }
    ],
    "sg:phone":"+1 714 638 8896",
    "sg:postcode":"92840",
    "sg:province":"CA",
    "sg:tags":[
        "peruvian"
    ],
    "wof:name":"Mr Pollo Peruvian Cuisine",
    "wof:placetype":"venue"
},
  "geometry": {"coordinates":[-117.914953,33.779735],"type":"Point"}
}