{
  "type": "Feature",
  "properties": {
    "iso:country":"US",
    "sg:address":"3315 State St",
    "sg:city":"Santa Barbara",
    "sg:classifiers":[
        {
            "category":"Wholesale",
            "subcategory":"Groceries",
            "type":"Manufacturing & Wholesale Goods"
        }
    ],
    "sg:phone":"+1 805 569 2023",
    "sg:postcode":"93105",
    "sg:province":"CA",
    "sg:tags":[
        "baker"
    ],
    "wof:name":"Italian Bakery",
    "wof:placetype":"venue"
},
  "geometry": {"coordinates":[-119.73627500000001,34.440322],"type":"Point"}
}