{
  "type": "Feature",
  "properties": {
    "addr:full":"933 Niles St Bakersfield CA 93305",
    "addr:housenumber":"933",
    "addr:postcode":"93305",
    "addr:street":"Niles St",
    "iso:country":"US",
    "sg:address":"933 Niles St",
    "sg:city":"Bakersfield",
    "sg:classifiers":[
        {
            "category":"Professional",
            "subcategory":"Management & Consulting",
            "type":"Services"
        }
    ],
    "sg:phone":"+1 661 321 0100",
    "sg:postcode":"93305",
    "sg:province":"CA",
    "sg:tags":[
        "consultant",
        "business"
    ],
    "wof:name":"American Grant Writing",
    "wof:placetype":"venue"
},
  "geometry": {"coordinates":[-118.98684,35.380959],"type":"Point"}
}