{
  "type": "Feature",
  "properties": {
    "addr:full":"5375 Manila Ave Oakland CA 94618",
    "addr:housenumber":"5375",
    "addr:postcode":"94618",
    "addr:street":"Manila Ave",
    "iso:country":"US",
    "sg:address":"5375 Manila Ave",
    "sg:city":"Oakland",
    "sg:classifiers":[
        {
            "category":"Community Center",
            "subcategory":"Senior",
            "type":"Public Place"
        },
        {
            "category":"Social Services",
            "subcategory":"Adult Care",
            "type":"Services"
        }
    ],
    "sg:phone":"+1 510 653 0256",
    "sg:postcode":"94618",
    "sg:province":"CA",
    "sg:tags":[
        "counseling",
        "citizen"
    ],
    "wof:name":"Satellite Senior Homes",
    "wof:placetype":"venue"
},
  "geometry": {"coordinates":[-122.25176500000001,37.839561],"type":"Point"}
}