{
  "type": "Feature",
  "properties": {
    "addr:full":"4656 Park Hill Dr Placerville CA 95667",
    "addr:housenumber":"4656",
    "addr:postcode":"95667",
    "addr:street":"Park Hill Dr",
    "iso:country":"US",
    "sg:address":"4656 Park Hill Dr",
    "sg:city":"Placerville",
    "sg:classifiers":[
        {
            "category":"Manufacturing",
            "subcategory":"Metals",
            "type":"Manufacturing & Wholesale Goods"
        },
        {
            "category":"Building & Trades",
            "subcategory":"Construction",
            "type":"Services"
        }
    ],
    "sg:phone":"+1 530 644 2107",
    "sg:postcode":"95667",
    "sg:province":"CA",
    "sg:tags":[
        "steel",
        "contractor"
    ],
    "wof:name":"Phillips Medical Systems",
    "wof:placetype":"venue"
},
  "geometry": {"coordinates":[-120.64787,38.686771],"type":"Point"}
}