{
  "type": "Feature",
  "properties": {
    "addr:full":"1616 Culpepper Ave Modesto CA 95351",
    "addr:housenumber":"1616",
    "addr:postcode":"ca 95351",
    "addr:street":"Culpepper Ave",
    "iso:country":"US",
    "sg:address":"1616 Culpepper Ave",
    "sg:city":"Modesto",
    "sg:classifiers":[
        {
            "category":"Wholesale",
            "subcategory":"Jewelry",
            "type":"Manufacturing & Wholesale Goods"
        }
    ],
    "sg:phone":"+1 209 578 0172",
    "sg:postcode":"95351",
    "sg:province":"CA",
    "sg:tags":[
        "jeweler",
        "supply"
    ],
    "wof:name":"Valley Findings & Tools",
    "wof:placetype":"venue"
},
  "geometry": {"coordinates":[-121.027564,37.660436],"type":"Point"}
}