{
  "type": "Feature",
  "properties": {
    "iso:country":"US",
    "sg:address":"1297 B St",
    "sg:city":"Hayward",
    "sg:classifiers":[
        {
            "category":"Professional",
            "subcategory":"Lawyer & Legal Services",
            "type":"Services"
        }
    ],
    "sg:phone":"+1 510 583 1155",
    "sg:postcode":"94541",
    "sg:province":"CA",
    "sg:tags":[
        "attorney",
        "partnership",
        "business",
        "corporation",
        "practice",
        "tax",
        "plan",
        "real estate",
        "law"
    ],
    "sg:website":"http://www.mossandmurphy.com",
    "wof:name":"Moss & Murphy",
    "wof:placetype":"venue"
},
  "geometry": {"coordinates":[-122.078003,37.676399],"type":"Point"}
}