{
  "type": "Feature",
  "properties": {
    "addr:full":"865 W El Camino Real Sunnyvale CA 94087",
    "addr:housenumber":"865",
    "addr:postcode":"94087",
    "addr:street":"W El Camino Real",
    "iso:country":"US",
    "sg:address":"865 W El Camino Real",
    "sg:city":"Sunnyvale",
    "sg:classifiers":[
        {
            "category":"Professional",
            "subcategory":"Lawyer & Legal Services",
            "type":"Services"
        }
    ],
    "sg:phone":"+1 650 924 9755",
    "sg:postcode":"94087",
    "sg:province":"CA",
    "sg:tags":[
        "litigation"
    ],
    "sg:website":"www.varinsky.com",
    "wof:name":"Varinsky Associates",
    "wof:placetype":"venue"
},
  "geometry": {"coordinates":[-122.04336600000001,37.370823],"type":"Point"}
}