{
  "type": "Feature",
  "properties": {
    "addr:full":"10045 Cristobal Dr Spring Valley CA 91977",
    "addr:housenumber":"10045",
    "addr:postcode":"91977",
    "addr:street":"Cristobal Dr",
    "iso:country":"US",
    "sg:address":"10045 Cristobal Dr",
    "sg:city":"Spring Valley",
    "sg:classifiers":[
        {
            "category":"Manufacturing",
            "subcategory":"Tools & Machinery",
            "type":"Manufacturing & Wholesale Goods"
        }
    ],
    "sg:phone":"+1 619 464 1568",
    "sg:postcode":"91977",
    "sg:province":"CA",
    "sg:tags":[
        "carpet",
        "cleaning",
        "rug"
    ],
    "sg:website":"www.carpetcleaningsandiego.com/",
    "wof:name":"AYC Carpet & Upholstery Cleaning",
    "wof:placetype":"venue"
},
  "geometry": {"coordinates":[-116.977048,32.740695],"type":"Point"}
}