{
  "type": "Feature",
  "properties": {
    "addr:full":"17751 Douglas Rd Nevada City CA 95959",
    "addr:housenumber":"17751",
    "addr:postcode":"95959",
    "addr:street":"Douglas Rd",
    "iso:country":"US",
    "sg:address":"17751 Douglas Rd",
    "sg:city":"Nevada City",
    "sg:classifiers":[
        {
            "category":"Wholesale",
            "subcategory":"Furniture",
            "type":"Manufacturing & Wholesale Goods"
        }
    ],
    "sg:phone":"+1 530 470 0382",
    "sg:postcode":"95959",
    "sg:province":"CA",
    "sg:tags":[
        "modular",
        "dealership"
    ],
    "wof:name":"Agile Office Systems",
    "wof:placetype":"venue"
},
  "geometry": {"coordinates":[-120.98383,39.306704],"type":"Point"}
}