{
  "type": "Feature",
  "properties": {
    "iso:country":"US",
    "sg:address":"1141 Foothill Blvd",
    "sg:city":"La Verne",
    "sg:classifiers":[
        {
            "category":"Insurance",
            "subcategory":"Insurance Agent",
            "type":"Services"
        }
    ],
    "sg:phone":"+1 909 593 4533",
    "sg:postcode":"91750",
    "sg:province":"CA",
    "wof:name":"State Farm Insurance",
    "wof:placetype":"venue"
},
  "geometry": {"coordinates":[-117.782116,34.11909],"type":"Point"}
}