{
  "type": "Feature",
  "properties": {
    "addr:full":"565 Middlefield Road Suite 100 Menlo Park CA 94025",
    "addr:housenumber":"565",
    "addr:postcode":"94025",
    "addr:street":"Middlefield Road Suite 100",
    "iso:country":"US",
    "sg:address":"565 Middlefield Road Suite 100",
    "sg:city":"Menlo Park",
    "sg:classifiers":[
        {
            "category":"Professional",
            "subcategory":"Computer Services",
            "type":"Services"
        }
    ],
    "sg:phone":"+1 650 859 6051",
    "sg:postcode":"94025",
    "sg:province":"CA",
    "wof:name":"KonaWare",
    "wof:placetype":"venue"
},
  "geometry": {"coordinates":[-122.168599,37.456831],"type":"Point"}
}