{
  "type": "Feature",
  "properties": {
    "addr:full":"392 A St Hayward CA 94541",
    "addr:housenumber":"392",
    "addr:postcode":"94541",
    "addr:street":"A St",
    "iso:country":"US",
    "sg:address":"392 A St",
    "sg:city":"Hayward",
    "sg:classifiers":[
        {
            "category":"Restaurant",
            "type":"Food & Drink"
        }
    ],
    "sg:menulink":"http://www.allmenus.com/ca/hayward/91373-tien-giang/menu/",
    "sg:phone":"+1 510 582 0684",
    "sg:postcode":"94541",
    "sg:province":"CA",
    "sg:tags":[
        "asian",
        "vietnamese"
    ],
    "wof:name":"Tien Giang",
    "wof:placetype":"venue"
},
  "geometry": {"coordinates":[-122.094386,37.669166],"type":"Point"}
}