{
  "type": "Feature",
  "properties": {
    "iso:country":"US",
    "sg:address":"1509 N Sepulveda Boulevard",
    "sg:city":"Manhattan Beach",
    "sg:classifiers":[
        {
            "category":"Professional",
            "subcategory":"Lawyer & Legal Services",
            "type":"Services"
        }
    ],
    "sg:phone":"+1 310 545 3331",
    "sg:postcode":"90266",
    "sg:province":"CA",
    "wof:name":"Glover Carol",
    "wof:placetype":"venue"
},
  "geometry": {"coordinates":[-118.396219,33.889703],"type":"Point"}
}