{
  "type": "Feature",
  "properties": {
    "iso:country":"US",
    "sg:address":"160 Old Adobe Rd",
    "sg:city":"Watsonville",
    "sg:classifiers":[
        {
            "category":"Building & Trades",
            "subcategory":"Plumbing",
            "type":"Services"
        }
    ],
    "sg:phone":"+1 831 763 9050",
    "sg:postcode":"95076",
    "sg:province":"CA",
    "sg:tags":[
        "sheet",
        "work",
        "metal",
        "contractor"
    ],
    "wof:name":"Ronzano Sheet Metal",
    "wof:placetype":"venue"
},
  "geometry": {"coordinates":[-121.812743,36.946194],"type":"Point"}
}