{
  "type": "Feature",
  "properties": {
    "iso:country":"US",
    "sg:address":"167 Canyon Highlands Dr",
    "sg:city":"Oroville",
    "sg:classifiers":[
        {
            "category":"Wholesale",
            "subcategory":"Vending Machines",
            "type":"Manufacturing & Wholesale Goods"
        }
    ],
    "sg:phone":"+1 530 534 3536",
    "sg:postcode":"95966",
    "sg:province":"CA",
    "sg:tags":[
        "operator"
    ],
    "wof:name":"Jim Williams Vending",
    "wof:placetype":"venue"
},
  "geometry": {"coordinates":[-121.527098,39.517309],"type":"Point"}
}