{
  "type": "Feature",
  "properties": {
    "iso:country":"US",
    "sg:address":"1460 Washington Blvd",
    "sg:city":"Concord",
    "sg:classifiers":[
        {
            "category":"Building & Trades",
            "subcategory":"Construction",
            "type":"Services"
        }
    ],
    "sg:phone":"+1 925 672 8895",
    "sg:postcode":"94521",
    "sg:province":"CA",
    "sg:tags":[
        "contractor"
    ],
    "wof:name":"Lemke Construction",
    "wof:placetype":"venue"
},
  "geometry": {"coordinates":[-121.95635299999999,37.951101],"type":"Point"}
}