{
  "type": "Feature",
  "properties": {
    "iso:country":"US",
    "sg:address":"6779 Sandylee Way",
    "sg:city":"Sacramento",
    "sg:classifiers":[
        {
            "category":"Retail",
            "subcategory":"Repair Shop",
            "type":"Services"
        }
    ],
    "sg:phone":"+1 916 427 3232",
    "sg:postcode":"95828",
    "sg:province":"CA",
    "sg:tags":[
        "plumbing",
        "drain",
        "cleaning",
        "sewer"
    ],
    "wof:name":"Cunningham's Plumbing & Rooter",
    "wof:placetype":"venue"
},
  "geometry": {"coordinates":[-121.422598,38.489249],"type":"Point"}
}