{
  "type": "Feature",
  "properties": {
    "addr:full":"4640 Lankershim Blvd Ste 105 North Hollywood CA 91602",
    "addr:postcode":"4640;91602",
    "addr:street":"Lankershim Blvd Ste 105",
    "iso:country":"US",
    "sg:address":"4640 Lankershim Blvd Ste 105",
    "sg:city":"North Hollywood",
    "sg:classifiers":[
        {
            "category":"Coffee & Tea",
            "type":"Food & Drink"
        },
        {
            "category":"Restaurant",
            "type":"Food & Drink"
        },
        {
            "category":"Bagels",
            "subcategory":"None",
            "type":"Food & Drink"
        }
    ],
    "sg:phone":"+1 818 487 9293",
    "sg:postcode":"91602",
    "sg:province":"CA",
    "sg:tags":[
        "traditional",
        "american"
    ],
    "wof:name":"California Sub",
    "wof:placetype":"venue"
},
  "geometry": {"coordinates":[-118.36852,34.154801],"type":"Point"}
}