{
  "type": "Feature",
  "properties": {
    "addr:full":"2001 N Evergreen St Burbank CA 91505",
    "addr:housenumber":"2001",
    "addr:postcode":"91505",
    "addr:street":"N Evergreen St",
    "iso:country":"US",
    "sg:address":"2001 N Evergreen St",
    "sg:city":"Burbank",
    "sg:classifiers":[
        {
            "category":"Personal",
            "subcategory":"Hair Removal",
            "type":"Services"
        }
    ],
    "sg:phone":"+1 818 652 9410",
    "sg:postcode":"91505",
    "sg:province":"CA",
    "wof:name":"Aire-Lite Electrolysis",
    "wof:placetype":"venue"
},
  "geometry": {"coordinates":[-118.35580899999999,34.185062],"type":"Point"}
}