{
  "type": "Feature",
  "properties": {
    "iso:country":"US",
    "sg:address":"2207 Country Club Blvd",
    "sg:city":"Stockton",
    "sg:phone":"+1 209 463 1669",
    "sg:postcode":"95204",
    "sg:province":"CA",
    "sg:website":"http://www.slograd.com",
    "wof:name":"Graduate Restaurant",
    "wof:placetype":"venue"
},
  "geometry": {"coordinates":[-121.329866,37.965754],"type":"Point"}
}