{
  "type": "Feature",
  "properties": {
    "addr:full":"10 Rio Camino Sacramento CA 95834",
    "addr:housenumber":"10",
    "addr:postcode":"95834",
    "addr:street":"Rio Camino Sacramento",
    "iso:country":"US",
    "sg:address":"10 Rio Camino",
    "sg:city":"Sacramento",
    "sg:classifiers":[
        {
            "category":"Building & Trades",
            "subcategory":"Construction",
            "type":"Services"
        }
    ],
    "sg:phone":"+1 916 924 3702",
    "sg:postcode":"95834",
    "sg:province":"CA",
    "sg:tags":[
        "contractor"
    ],
    "sg:website":"www.garagedsolutions.com",
    "wof:name":"Garage Door Solutions",
    "wof:placetype":"venue"
},
  "geometry": {"coordinates":[-121.49256099999999,38.634522],"type":"Point"}
}