{
  "type": "Feature",
  "properties": {
    "iso:country":"US",
    "sg:address":"8327 Reseda Blvd",
    "sg:city":"Northridge",
    "sg:classifiers":[
        {
            "category":"Health Services",
            "subcategory":"Doctor",
            "type":"Services"
        }
    ],
    "sg:phone":"+1 818 718 8450",
    "sg:postcode":"91324",
    "sg:province":"CA",
    "sg:tags":[
        "physician",
        "surgeon"
    ],
    "wof:name":"Hallmark Surgical Ctr",
    "wof:placetype":"venue"
},
  "geometry": {"coordinates":[-118.53615499999999,34.224098],"type":"Point"}
}