{
  "type": "Feature",
  "properties": {
    "iso:country":"US",
    "sg:address":"3 Lagoon Dr",
    "sg:city":"Redwood City",
    "sg:classifiers":[
        {
            "category":"Professional",
            "subcategory":"Computer Services",
            "type":"Services"
        }
    ],
    "sg:phone":"+1 650 801 7400",
    "sg:postcode":"94065",
    "sg:province":"CA",
    "sg:tags":[
        "marketing",
        "email",
        "internet"
    ],
    "wof:name":"Responsyscom",
    "wof:placetype":"venue"
},
  "geometry": {"coordinates":[-122.263566,37.526228],"type":"Point"}
}