{
  "type": "Feature",
  "properties": {
    "addr:full":"1840 Gateway Dr San Mateo CA 94404",
    "addr:housenumber":"1840",
    "addr:postcode":"94404",
    "addr:street":"Gateway Dr",
    "iso:country":"US",
    "sg:address":"1840 Gateway Dr",
    "sg:city":"San Mateo",
    "sg:classifiers":[
        {
            "category":"Professional",
            "type":"Services"
        }
    ],
    "sg:phone":"+1 650 592 1862",
    "sg:postcode":"94404",
    "sg:province":"CA",
    "wof:name":"Menicon America Inc",
    "wof:placetype":"venue"
},
  "geometry": {"coordinates":[-122.281769,37.556424],"type":"Point"}
}