{
  "type": "Feature",
  "properties": {
    "iso:country":"US",
    "sg:address":"43430 Monroe St",
    "sg:city":"Indio",
    "sg:classifiers":[
        {
            "category":"Food & Beverages",
            "subcategory":"Groceries & Convenience Stores",
            "type":"Retail Goods"
        }
    ],
    "sg:phone":"+1 760 775 2011",
    "sg:postcode":"92201",
    "sg:province":"CA",
    "sg:tags":[
        "market"
    ],
    "wof:name":"Valley Market",
    "wof:placetype":"venue"
},
  "geometry": {"coordinates":[-116.233828,33.735002],"type":"Point"}
}