{
  "type": "Feature",
  "properties": {
    "addr:full":"22372 Thunderbird Pl Hayward CA 94545",
    "addr:housenumber":"22372",
    "addr:postcode":"94545",
    "addr:street":"Thunderbird Pl",
    "iso:country":"US",
    "sg:address":"22372 Thunderbird Pl",
    "sg:city":"Hayward",
    "sg:classifiers":[
        {
            "category":"Retail",
            "subcategory":"Laundry & Dry Cleaning",
            "type":"Services"
        }
    ],
    "sg:phone":"+1 510 783 0700",
    "sg:postcode":"94545",
    "sg:province":"CA",
    "wof:name":"Crow Canyon Laundry",
    "wof:placetype":"venue"
},
  "geometry": {"coordinates":[-122.122574,37.651707],"type":"Point"}
}