{
  "type": "Feature",
  "properties": {
    "addr:full":"25212 Marguerite Pkwy Mission Viejo CA 92692",
    "addr:housenumber":"25212",
    "addr:postcode":"92692",
    "addr:street":"Marguerite Pkwy",
    "iso:country":"US",
    "sg:address":"25212 Marguerite Pkwy",
    "sg:city":"Mission Viejo",
    "sg:classifiers":[
        {
            "category":"Banks & Credit Unions",
            "subcategory":"Bank",
            "type":"Services"
        }
    ],
    "sg:phone":"+1 949 830 1101",
    "sg:postcode":"92692",
    "sg:province":"CA",
    "sg:tags":[
        "escrow"
    ],
    "wof:name":"Coast Cities Escrow",
    "wof:placetype":"venue"
},
  "geometry": {"coordinates":[-117.65846999999999,33.596214],"type":"Point"}
}