{
  "type": "Feature",
  "properties": {
    "iso:country":"US",
    "sg:address":"605 Divisadero St",
    "sg:city":"San Francisco",
    "sg:classifiers":[
        {
            "category":"Personal",
            "subcategory":"Beauty Salon",
            "type":"Services"
        }
    ],
    "sg:phone":"+1 415 923 9509",
    "sg:postcode":"94117",
    "sg:province":"CA",
    "sg:tags":[
        "manicuring"
    ],
    "wof:name":"Leslie's Nail",
    "wof:placetype":"venue"
},
  "geometry": {"coordinates":[-122.438074,37.775915],"type":"Point"}
}