{
  "type": "Feature",
  "properties": {
    "iso:country":"US",
    "sg:address":"7217 Bernadine Ave",
    "sg:city":"Canoga Park",
    "sg:classifiers":[
        {
            "category":"Wholesale",
            "subcategory":"Chemicals & Plastics",
            "type":"Manufacturing & Wholesale Goods"
        }
    ],
    "sg:phone":"+1 818 999 2834",
    "sg:postcode":"91307",
    "sg:province":"CA",
    "sg:tags":[
        "establishment"
    ],
    "wof:name":"Amway Home Pdts Distrs Blechma",
    "wof:placetype":"venue"
},
  "geometry": {"coordinates":[-118.63876999999999,34.201481],"type":"Point"}
}