{
  "type": "Feature",
  "properties": {
    "addr:full":"2170 Evergreen St Sacramento CA 95815",
    "addr:housenumber":"2170",
    "addr:postcode":"95815",
    "addr:street":"Evergreen St",
    "iso:country":"US",
    "sg:address":"2170 Evergreen St",
    "sg:city":"Sacramento",
    "sg:classifiers":[
        {
            "category":"Shopping",
            "subcategory":"Party Supplies",
            "type":"Retail Goods"
        }
    ],
    "sg:phone":"+1 916 925 5866",
    "sg:postcode":"95815",
    "sg:province":"CA",
    "sg:website":"www.rentritethepartypeople.com",
    "wof:name":"Rent-Rite the Party People",
    "wof:placetype":"venue"
},
  "geometry": {"coordinates":[-121.444,38.6063],"type":"Point"}
}