{
  "type": "Feature",
  "properties": {
    "addr:full":"259 10th St Oakland CA 94607",
    "addr:housenumber":"259",
    "addr:postcode":"94607",
    "addr:street":"10Th St",
    "iso:country":"US",
    "sg:address":"259 10th St",
    "sg:city":"Oakland",
    "sg:classifiers":[
        {
            "category":"Utilities",
            "subcategory":"Mobile Phone",
            "type":"Services"
        }
    ],
    "sg:phone":"+1 510 834 8889",
    "sg:postcode":"94607",
    "sg:province":"CA",
    "sg:tags":[
        "telephone",
        "cellular"
    ],
    "wof:name":"Mobile Phone",
    "wof:placetype":"venue"
},
  "geometry": {"coordinates":[-122.269232,37.800024],"type":"Point"}
}