{
  "type": "Feature",
  "properties": {
    "iso:country":"US",
    "sg:address":"4751 Holt Blvd",
    "sg:city":"Montclair",
    "sg:classifiers":[
        {
            "category":"Wholesale",
            "subcategory":"Medical Equipment & Supplies",
            "type":"Manufacturing & Wholesale Goods"
        }
    ],
    "sg:phone":"+1 909 621 5901",
    "sg:postcode":"91763",
    "sg:province":"CA",
    "wof:name":"Action Homehealth Supplies",
    "wof:placetype":"venue"
},
  "geometry": {"coordinates":[-117.7055,34.063101],"type":"Point"}
}