{
  "type": "Feature",
  "properties": {
    "iso:country":"US",
    "sg:address":"117 W 9th St",
    "sg:city":"Los Angeles",
    "sg:classifiers":[
        {
            "category":"Shopping",
            "subcategory":"Clothing, Apparel, & Fashions",
            "type":"Retail Goods"
        }
    ],
    "sg:phone":"+1 213 629 1545",
    "sg:postcode":"90015",
    "sg:province":"CA",
    "wof:name":"Gal Pal",
    "wof:placetype":"venue"
},
  "geometry": {"coordinates":[-118.255214,34.041843],"type":"Point"}
}