{
  "type": "Feature",
  "properties": {
    "addr:full":"5221 Coast Rd Santa Cruz CA 95060",
    "addr:housenumber":"5221",
    "addr:postcode":"95060",
    "addr:street":"Coast Rd",
    "iso:country":"US",
    "sg:address":"5221 Coast Rd",
    "sg:city":"Santa Cruz",
    "sg:classifiers":[
        {
            "category":"Farming",
            "subcategory":"Farm",
            "type":"Manufacturing & Wholesale Goods"
        }
    ],
    "sg:phone":"+1 831 426 6515",
    "sg:postcode":"95060",
    "sg:province":"CA",
    "sg:tags":[
        "crop",
        "general"
    ],
    "wof:name":"Free Wheelin Farm",
    "wof:placetype":"venue"
},
  "geometry": {"coordinates":[-122.143461,36.982337],"type":"Point"}
}