{
  "type": "Feature",
  "properties": {
    "iso:country":"US",
    "sg:address":"3433 Arden Way",
    "sg:city":"Sacramento",
    "sg:classifiers":[
        {
            "category":"Health Services",
            "subcategory":"Dentist",
            "type":"Services"
        }
    ],
    "sg:phone":"+1 916 482 0288",
    "sg:postcode":"95825",
    "sg:province":"CA",
    "sg:tags":[
        "pediatric"
    ],
    "sg:website":"www.kiddentists.com",
    "wof:name":"Childrens Dental Care",
    "wof:placetype":"venue"
},
  "geometry": {"coordinates":[-121.384253,38.596152],"type":"Point"}
}