{
  "type": "Feature",
  "properties": {
    "addr:full":"2563 Manchester Ave Cardiff By Sea CA 92007",
    "addr:housenumber":"2563",
    "addr:postcode":"92007",
    "addr:street":"Manchester Ave",
    "iso:country":"US",
    "sg:address":"2563 Manchester Ave",
    "sg:city":"Cardiff By Sea",
    "sg:classifiers":[
        {
            "category":"Education",
            "subcategory":"Special Training",
            "type":"Public Place"
        }
    ],
    "sg:phone":"+1 760 943 1852",
    "sg:postcode":"92007",
    "sg:province":"CA",
    "sg:tags":[
        "instruction",
        "music"
    ],
    "wof:name":"Piano Studio Of Chutaphin",
    "wof:placetype":"venue"
},
  "geometry": {"coordinates":[-117.27591200000001,33.015412],"type":"Point"}
}