{
  "type": "Feature",
  "properties": {
    "addr:full":"5614 Geary Blvd San Francisco CA 94121",
    "addr:housenumber":"5614",
    "addr:postcode":"94121",
    "addr:street":"Geary Blvd",
    "iso:country":"US",
    "sg:address":"5614 Geary Blvd",
    "sg:city":"San Francisco",
    "sg:classifiers":[
        {
            "category":"Shopping",
            "subcategory":"Pharmacy",
            "type":"Retail Goods"
        }
    ],
    "sg:phone":"+1 415 752 3737",
    "sg:postcode":"94121",
    "sg:province":"CA",
    "wof:name":"Torgsyn Discount Pharmacy Inc",
    "wof:placetype":"venue"
},
  "geometry": {"coordinates":[-122.480403,37.780421],"type":"Point"}
}