{
  "type": "Feature",
  "properties": {
    "addr:full":"1590 Allen Rae Pl South Lake Tahoe CA 89449",
    "addr:housenumber":"1590",
    "addr:postcode":"89449",
    "addr:street":"Allen Rae Pl",
    "iso:country":"US",
    "sg:address":"1590 Allen Rae Pl",
    "sg:city":"South Lake Tahoe",
    "sg:classifiers":[
        {
            "category":"Shopping",
            "subcategory":"Clothing, Apparel, & Fashions",
            "type":"Retail Goods"
        }
    ],
    "sg:phone":"+1 209 962 0887",
    "sg:postcode":"89449",
    "sg:province":"CA",
    "sg:tags":[
        "infant",
        "wear"
    ],
    "wof:name":"Cookie Baby Inc",
    "wof:placetype":"venue"
},
  "geometry": {"coordinates":[-119.95792899999999,38.928554],"type":"Point"}
}