{
  "type": "Feature",
  "properties": {
    "iso:country":"US",
    "sg:address":"3540 E 4th St",
    "sg:city":"Long Beach",
    "sg:classifiers":[
        {
            "category":"Government",
            "subcategory":"Post Office",
            "type":"Public Place"
        }
    ],
    "sg:phone":"+1 562 000 1111",
    "sg:postcode":"90814",
    "sg:province":"CA",
    "wof:name":"US Post Office",
    "wof:placetype":"venue"
},
  "geometry": {"coordinates":[-118.1506,33.771629],"type":"Point"}
}