{
  "type": "Feature",
  "properties": {
    "iso:country":"US",
    "sg:address":"2121 Blumenfeld Dr",
    "sg:city":"Sacramento",
    "sg:classifiers":[
        {
            "category":"Utilities",
            "subcategory":"Water",
            "type":"Services"
        },
        {
            "category":"Wholesale",
            "subcategory":"Beer",
            "type":"Manufacturing & Wholesale Goods"
        },
        {
            "category":"Food & Beverages",
            "subcategory":"Liquor & Beverages",
            "type":"Retail Goods"
        },
        {
            "category":"Home & Garden",
            "subcategory":"Hardware",
            "type":"Retail Goods"
        }
    ],
    "sg:phone":"+1 916 921 4428",
    "sg:postcode":"95815",
    "sg:province":"CA",
    "sg:tags":[
        "filtration",
        "bottler",
        "softening",
        "companies-bottled",
        "purification",
        "bulk",
        "equipment",
        "conditioning"
    ],
    "sg:website":"http://www.culliganwatersystems.com",
    "wof:name":"Culligan Water Systems",
    "wof:placetype":"venue"
},
  "geometry": {"coordinates":[-121.43817300000001,38.605049],"type":"Point"}
}