{
  "type": "Feature",
  "properties": {
    "addr:full":"649 Speers Rd Santa Rosa CA 95409",
    "addr:housenumber":"649",
    "addr:postcode":"95409",
    "addr:street":"Speers Rd",
    "iso:country":"US",
    "sg:address":"649 Speers Rd",
    "sg:city":"Santa Rosa",
    "sg:classifiers":[
        {
            "category":"Building & Trades",
            "subcategory":"Construction",
            "type":"Services"
        }
    ],
    "sg:phone":"+1 707 539 3543",
    "sg:postcode":"95409",
    "sg:province":"CA",
    "sg:tags":[
        "excavation",
        "excavating",
        "contractor"
    ],
    "wof:name":"Sichels Backhoe & Excavating",
    "wof:placetype":"venue"
},
  "geometry": {"coordinates":[-122.668121,38.472816],"type":"Point"}
}