{
  "type": "Feature",
  "properties": {
    "addr:full":"8 Bridge Ct Vallejo CA 94591",
    "addr:housenumber":"8",
    "addr:postcode":"94591",
    "addr:street":"Bridge Ct",
    "iso:country":"US",
    "sg:address":"8 Bridge Ct",
    "sg:city":"Vallejo",
    "sg:classifiers":[
        {
            "category":"Professional",
            "subcategory":"Art Services",
            "type":"Services"
        }
    ],
    "sg:phone":"+1 707 649 8877",
    "sg:postcode":"94591",
    "sg:province":"CA",
    "sg:tags":[
        "photographer"
    ],
    "wof:name":"Alan Arqueza Photography",
    "wof:placetype":"venue"
},
  "geometry": {"coordinates":[-122.217562,38.110503],"type":"Point"}
}