{
  "type": "Feature",
  "properties": {
    "addr:full":"1405 N H St Lompoc CA 93436",
    "addr:housenumber":"1405",
    "addr:postcode":"93436",
    "addr:street":"N H St",
    "iso:country":"US",
    "sg:address":"1405 N H St",
    "sg:city":"Lompoc",
    "sg:classifiers":[
        {
            "category":"Restaurant",
            "type":"Food & Drink"
        }
    ],
    "sg:phone":"+1 805 735 5560",
    "sg:postcode":"93436",
    "sg:province":"CA",
    "sg:website":"www.dennys.com",
    "wof:name":"Denny's",
    "wof:placetype":"venue"
},
  "geometry": {"coordinates":[-120.457875,34.664163],"type":"Point"}
}