{
  "type": "Feature",
  "properties": {
    "addr:full":"365 Hallsons Ln Ben Lomond CA 95005",
    "addr:housenumber":"365",
    "addr:postcode":"95005",
    "addr:street":"Hallsons Ln",
    "iso:country":"US",
    "sg:address":"365 Hallsons Ln",
    "sg:city":"Ben Lomond",
    "sg:classifiers":[
        {
            "category":"Real Estate",
            "subcategory":"Real Estate Agent",
            "type":"Services"
        }
    ],
    "sg:phone":"+1 831 336 9805",
    "sg:postcode":"95005",
    "sg:province":"CA",
    "sg:tags":[
        "inspection"
    ],
    "wof:name":"Home Inspector Of America",
    "wof:placetype":"venue"
},
  "geometry": {"coordinates":[-122.075487,37.089556],"type":"Point"}
}