{
  "type": "Feature",
  "properties": {
    "addr:full":"1111 Las Tablas Rd Templeton CA 93465",
    "addr:housenumber":"1111",
    "addr:postcode":"93465",
    "addr:street":"Las Tablas Rd",
    "iso:country":"US",
    "sg:address":"1111 Las Tablas Rd",
    "sg:city":"Templeton",
    "sg:classifiers":[
        {
            "category":"Health Services",
            "subcategory":"Doctor",
            "type":"Services"
        }
    ],
    "sg:phone":"+1 805 434 1511",
    "sg:postcode":"93465",
    "sg:province":"CA",
    "sg:tags":[
        "physician",
        "surgeon"
    ],
    "wof:name":"Elena Martinho MD",
    "wof:placetype":"venue"
},
  "geometry": {"coordinates":[-120.720681,35.554308],"type":"Point"}
}