{
  "type": "Feature",
  "properties": {
    "addr:full":"169 N McDowell Blvd Petaluma CA 94954",
    "addr:housenumber":"169",
    "addr:postcode":"94954",
    "addr:street":"N Mcdowell Blvd",
    "iso:country":"US",
    "sg:address":"169 N McDowell Blvd",
    "sg:city":"Petaluma",
    "sg:classifiers":[
        {
            "category":"Food & Beverages",
            "subcategory":"Groceries & Convenience Stores",
            "type":"Retail Goods"
        }
    ],
    "sg:phone":"+1 707 763 1993",
    "sg:postcode":"94954",
    "sg:province":"CA",
    "wof:name":"Crown Grocers Inc",
    "wof:placetype":"venue"
},
  "geometry": {"coordinates":[-122.627242,38.249923],"type":"Point"}
}