{
  "type": "Feature",
  "properties": {
    "addr:full":"1122 Western St Fairfield CA 94533",
    "addr:housenumber":"1122",
    "addr:postcode":"94533",
    "addr:street":"Western St",
    "iso:country":"US",
    "sg:address":"1122 Western St",
    "sg:city":"Fairfield",
    "sg:classifiers":[
        {
            "category":"Manufacturing",
            "subcategory":"Electronics",
            "type":"Manufacturing & Wholesale Goods"
        }
    ],
    "sg:phone":"+1 707 426 4788",
    "sg:postcode":"94533",
    "sg:province":"CA",
    "sg:tags":[
        "equipment",
        "mfg",
        "communication"
    ],
    "wof:name":"Motorola",
    "wof:placetype":"venue"
},
  "geometry": {"coordinates":[-122.01079,38.274393],"type":"Point"}
}