{
  "type": "Feature",
  "properties": {
    "addr:full":"4611 Teller Ave Newport Beach CA 92660",
    "addr:housenumber":"4611",
    "addr:postcode":"92660",
    "addr:street":"Teller Ave",
    "iso:country":"US",
    "sg:address":"4611 Teller Ave",
    "sg:city":"Newport Beach",
    "sg:classifiers":[
        {
            "category":"Professional",
            "type":"Services"
        }
    ],
    "sg:phone":"+1 949 474 7959",
    "sg:postcode":"92660",
    "sg:province":"CA",
    "sg:tags":[
        "establishment"
    ],
    "wof:name":"Brooklyn & Assoc",
    "wof:placetype":"venue"
},
  "geometry": {"coordinates":[-117.856121,33.667295],"type":"Point"}
}