{
  "type": "Feature",
  "properties": {
    "addr:full":"4815 State Hwy 16 Guinda CA 95637",
    "addr:housenumber":"4815",
    "addr:postcode":"95637",
    "addr:street":"State Hwy 16",
    "iso:country":"US",
    "sg:address":"4815 State Hwy 16",
    "sg:city":"Guinda",
    "sg:classifiers":[
        {
            "category":"Farming",
            "subcategory":"Crops",
            "type":"Manufacturing & Wholesale Goods"
        }
    ],
    "sg:phone":"+1 530 796 3835",
    "sg:postcode":"95637",
    "sg:province":"CA",
    "sg:tags":[
        "grove",
        "nut",
        "tree"
    ],
    "wof:name":"Facciunto Vine",
    "wof:placetype":"venue"
},
  "geometry": {"coordinates":[-122.223007,38.86818],"type":"Point"}
}