{
  "type": "Feature",
  "properties": {
    "addr:full":"2475 Corinth Ave Los Angeles CA 90064",
    "addr:housenumber":"2475",
    "addr:postcode":"90064",
    "addr:street":"Corinth Ave",
    "iso:country":"US",
    "sg:address":"2475 Corinth Ave",
    "sg:city":"Los Angeles",
    "sg:classifiers":[
        {
            "category":"Real Estate",
            "subcategory":"Real Estate Operator",
            "type":"Services"
        }
    ],
    "sg:phone":"+1 310 478 5614",
    "sg:postcode":"90064",
    "sg:province":"CA",
    "sg:tags":[
        "building",
        "apartment"
    ],
    "wof:name":"2475 Corinth Apartments",
    "wof:placetype":"venue"
},
  "geometry": {"coordinates":[-118.438682,34.033719],"type":"Point"}
}