{
  "type": "Feature",
  "properties": {
    "iso:country":"US",
    "sg:address":"151 Ash St",
    "sg:city":"Susanville",
    "sg:classifiers":[
        {
            "category":"Health Services",
            "subcategory":"Doctor",
            "type":"Services"
        }
    ],
    "sg:phone":"+1 530 257 2828",
    "sg:postcode":"96130",
    "sg:province":"CA",
    "sg:tags":[
        "dentist"
    ],
    "wof:name":"Robert W Kohrt DDS",
    "wof:placetype":"venue"
},
  "geometry": {"coordinates":[-120.648257,40.416854],"type":"Point"}
}