{
  "type": "Feature",
  "properties": {
    "iso:country":"US",
    "sg:address":"3400 Orange Ave",
    "sg:city":"Long Beach",
    "sg:classifiers":[
        {
            "category":"Food & Beverages",
            "subcategory":"Liquor & Beverages",
            "type":"Retail Goods"
        }
    ],
    "sg:phone":"+1 562 988 7786",
    "sg:postcode":"90807",
    "sg:province":"CA",
    "wof:name":"Eddie's Liquor & Jr Market",
    "wof:placetype":"venue"
},
  "geometry": {"coordinates":[-118.176318,33.822143],"type":"Point"}
}