{
  "type": "Feature",
  "properties": {
    "addr:full":"9323 Chesapeake Dr San Diego CA 92123",
    "addr:housenumber":"9323",
    "addr:postcode":"92123",
    "addr:street":"Chesapeake Dr",
    "iso:country":"US",
    "sg:address":"9323 Chesapeake Dr",
    "sg:city":"San Diego",
    "sg:classifiers":[
        {
            "category":"Manufacturing",
            "subcategory":"Tools & Machinery",
            "type":"Manufacturing & Wholesale Goods"
        }
    ],
    "sg:phone":"+1 858 576 3550",
    "sg:postcode":"92123",
    "sg:province":"CA",
    "sg:tags":[
        "physician",
        "surgeon"
    ],
    "sg:website":"www.circaid.com",
    "wof:name":"Circ Aid Medical Products Inc",
    "wof:placetype":"venue"
},
  "geometry": {"coordinates":[-117.128601,32.837518],"type":"Point"}
}