{
  "type": "Feature",
  "properties": {
    "iso:country":"US",
    "sg:address":"1243 Transit Ave",
    "sg:city":"Pomona",
    "sg:classifiers":[
        {
            "category":"Food & Beverages",
            "subcategory":"Fruits & Vegetables",
            "type":"Retail Goods"
        }
    ],
    "sg:phone":"+1 909 622 5663",
    "sg:postcode":"91766",
    "sg:province":"CA",
    "sg:tags":[
        "juice"
    ],
    "wof:name":"Soon Food Corp",
    "wof:placetype":"venue"
},
  "geometry": {"coordinates":[-117.731687,34.050581],"type":"Point"}
}