{
  "type": "Feature",
  "properties": {
    "iso:country":"US",
    "sg:address":"1000 S Fresno St",
    "sg:city":"Los Angeles",
    "sg:classifiers":[
        {
            "category":"Government",
            "subcategory":"Police Station",
            "type":"Public Place"
        }
    ],
    "sg:phone":"+1 213 300 3042",
    "sg:postcode":"90023",
    "sg:province":"CA",
    "sg:tags":[
        "protection"
    ],
    "wof:name":"Los Angeles County Sheriff",
    "wof:placetype":"venue"
},
  "geometry": {"coordinates":[-118.207522,34.026742],"type":"Point"}
}