{
  "type": "Feature",
  "properties": {
    "addr:full":"1560 Yosemite Pkwy Merced CA 95341",
    "addr:housenumber":"1560",
    "addr:postcode":"95341",
    "addr:street":"Yosemite Pkwy",
    "iso:country":"US",
    "sg:address":"1560 Yosemite Pkwy",
    "sg:city":"Merced",
    "sg:classifiers":[
        {
            "category":"Shopping",
            "subcategory":"Music",
            "type":"Retail Goods"
        }
    ],
    "sg:phone":"+1 209 384 0678",
    "sg:postcode":"95341",
    "sg:province":"CA",
    "sg:tags":[
        "video",
        "disc",
        "tape",
        "cassette"
    ],
    "wof:name":"JMS Thai Video Sales",
    "wof:placetype":"venue"
},
  "geometry": {"coordinates":[-120.457189,37.295115],"type":"Point"}
}