{
  "type": "Feature",
  "properties": {
    "iso:country":"US",
    "sg:address":"1571 Laurelwood Rd",
    "sg:city":"Santa Clara",
    "sg:classifiers":[
        {
            "category":"Building & Trades",
            "subcategory":"Construction",
            "type":"Services"
        }
    ],
    "sg:phone":"+1 408 844 9608",
    "sg:postcode":"95054",
    "sg:province":"CA",
    "sg:tags":[
        "spray",
        "hanging",
        "painting",
        "finishing",
        "contractor"
    ],
    "wof:name":"J & E Refinishing",
    "wof:placetype":"venue"
},
  "geometry": {"coordinates":[-121.95756299999999,37.380551],"type":"Point"}
}