{
  "type": "Feature",
  "properties": {
    "iso:country":"US",
    "sg:address":"1 Via Las Encinas",
    "sg:city":"Carmel Valley",
    "sg:classifiers":[
        {
            "category":"Building & Trades",
            "subcategory":"Construction",
            "type":"Services"
        }
    ],
    "sg:phone":"+1 831 659 4827",
    "sg:postcode":"93924",
    "sg:province":"CA",
    "sg:tags":[
        "contractor"
    ],
    "wof:name":"Warmington Construction",
    "wof:placetype":"venue"
},
  "geometry": {"coordinates":[-121.753868,36.493942],"type":"Point"}
}