{
  "type": "Feature",
  "properties": {
    "addr:full":"1050 Marina Village Pkwy Ste 104 Alameda CA 94501",
    "addr:housenumber":"1050",
    "addr:postcode":"94501",
    "addr:street":"Marina Village Pkwy Ste 104",
    "iso:country":"US",
    "sg:address":"1050 Marina Village Pkwy Ste 104",
    "sg:city":"Alameda",
    "sg:classifiers":[
        {
            "category":"Health Services",
            "subcategory":"Health Practitioner",
            "type":"Services"
        }
    ],
    "sg:phone":"+1 510 995 8933",
    "sg:postcode":"94501",
    "sg:province":"CA",
    "sg:tags":[
        "acupuncture",
        "traditional",
        "medicine",
        "chinese"
    ],
    "wof:name":"Tokubo Acupuncture",
    "wof:placetype":"venue"
},
  "geometry": {"coordinates":[-122.26979900000001,37.785258],"type":"Point"}
}