{
  "type": "Feature",
  "properties": {
    "addr:full":"1100 N Poinsettia Ave Manhattan Beach CA 90266",
    "addr:housenumber":"1100",
    "addr:postcode":"90266",
    "addr:street":"N Poinsettia Ave",
    "iso:country":"US",
    "sg:address":"1100 N Poinsettia Ave",
    "sg:city":"Manhattan Beach",
    "sg:classifiers":[
        {
            "category":"Education",
            "subcategory":"Preschool",
            "type":"Public Place"
        },
        {
            "category":"Education",
            "subcategory":"School",
            "type":"Public Place"
        }
    ],
    "sg:phone":"+1 310 545 5653",
    "sg:postcode":"90266",
    "sg:province":"CA",
    "sg:tags":[
        "elementary"
    ],
    "wof:name":"First Lutheran Church of Manhattan Beach",
    "wof:placetype":"venue"
},
  "geometry": {"coordinates":[-118.400002,33.8867],"type":"Point"}
}