{
  "type": "Feature",
  "properties": {
    "addr:full":"1811 21st Ave San Francisco CA 94122",
    "addr:housenumber":"1811",
    "addr:postcode":"94122",
    "addr:street":"21St Ave",
    "iso:country":"US",
    "sg:address":"1811 21st Ave",
    "sg:city":"San Francisco",
    "sg:classifiers":[
        {
            "category":"Real Estate",
            "subcategory":"Real Estate Agent",
            "type":"Services"
        }
    ],
    "sg:phone":"+1 415 665 6291",
    "sg:postcode":"94122",
    "sg:province":"CA",
    "wof:name":"Richland Properties",
    "wof:placetype":"venue"
},
  "geometry": {"coordinates":[-122.478571,37.752468],"type":"Point"}
}