{
  "type": "Feature",
  "properties": {
    "addr:full":"6628 Fiesta Ln Orangevale CA 95662",
    "addr:housenumber":"6628",
    "addr:postcode":"95662",
    "addr:street":"Fiesta Ln",
    "iso:country":"US",
    "sg:address":"6628 Fiesta Ln",
    "sg:city":"Orangevale",
    "sg:classifiers":[
        {
            "category":"Wholesale",
            "subcategory":"Groceries",
            "type":"Manufacturing & Wholesale Goods"
        }
    ],
    "sg:phone":"+1 916 988 1030",
    "sg:postcode":"95662",
    "sg:province":"CA",
    "sg:tags":[
        "general"
    ],
    "wof:name":"Brooks Dwayne Keith Company",
    "wof:placetype":"venue"
},
  "geometry": {"coordinates":[-121.208895,38.686809],"type":"Point"}
}