{
  "type": "Feature",
  "properties": {
    "addr:full":"870 Bayberry Dr Corona CA 92882",
    "addr:housenumber":"870",
    "addr:postcode":"92882",
    "addr:street":"Bayberry Dr",
    "iso:country":"US",
    "sg:address":"870 Bayberry Dr",
    "sg:city":"Corona",
    "sg:classifiers":[
        {
            "category":"Building & Trades",
            "subcategory":"Construction",
            "type":"Services"
        }
    ],
    "sg:phone":"+1 951 737 0244",
    "sg:postcode":"92882",
    "sg:province":"CA",
    "sg:tags":[
        "tile",
        "dealer"
    ],
    "wof:name":"Tile By Wayne",
    "wof:placetype":"venue"
},
  "geometry": {"coordinates":[-117.629971,33.87868],"type":"Point"}
}