{
  "type": "Feature",
  "properties": {
    "iso:country":"US",
    "sg:address":"1852 Buenaventura Blvd",
    "sg:city":"Redding",
    "sg:classifiers":[
        {
            "category":"Real Estate",
            "subcategory":"Real Estate Agent",
            "type":"Services"
        }
    ],
    "sg:phone":"+1 530 245 5950",
    "sg:postcode":"96001",
    "sg:province":"CA",
    "wof:name":"Real Estate 1",
    "wof:placetype":"venue"
},
  "geometry": {"coordinates":[-122.421941,40.575614],"type":"Point"}
}