{
  "type": "Feature",
  "properties": {
    "addr:full":"1330 Jackson Gate Rd Jackson CA 95642",
    "addr:housenumber":"1330",
    "addr:postcode":"95642",
    "addr:street":"Jackson Gate Rd",
    "iso:country":"US",
    "sg:address":"1330 Jackson Gate Rd",
    "sg:city":"Jackson",
    "sg:classifiers":[
        {
            "category":"Travel",
            "subcategory":"Hotels & Motels",
            "type":"Entertainment"
        }
    ],
    "sg:phone":"+1 209 223 3500",
    "sg:postcode":"95642",
    "sg:province":"CA",
    "sg:tags":[
        "breakfast",
        "accommodation",
        "bed"
    ],
    "sg:website":"www.gatehouseinn.com",
    "wof:name":"Gate House Inn",
    "wof:placetype":"venue"
},
  "geometry": {"coordinates":[-120.77532100000001,38.367909],"type":"Point"}
}