{
  "type": "Feature",
  "properties": {
    "iso:country":"US",
    "sg:address":"380 Whippet-Run",
    "sg:city":"Corralitos",
    "sg:classifiers":[
        {
            "category":"Building & Trades",
            "subcategory":"Plumbing",
            "type":"Services"
        }
    ],
    "sg:phone":"+1 831 761 0644",
    "sg:postcode":"95076",
    "sg:province":"CA",
    "sg:tags":[
        "plumbing",
        "contractor"
    ],
    "sg:website":"www.preferredplumbing.com",
    "wof:name":"Preferred Plumbing",
    "wof:placetype":"venue"
},
  "geometry": {"coordinates":[-121.789467,36.997671],"type":"Point"}
}