{
  "type": "Feature",
  "properties": {
    "iso:country":"US",
    "sg:address":"5757 Greenback Ln",
    "sg:city":"Sacramento",
    "sg:classifiers":[
        {
            "category":"Retail",
            "subcategory":"Funeral Services",
            "type":"Services"
        }
    ],
    "sg:phone":"+1 916 961 1915",
    "sg:postcode":"95841",
    "sg:province":"CA",
    "sg:tags":[
        "cemetery"
    ],
    "wof:name":"East Lawn Mortuary & Sierra Hills Memorial Park",
    "wof:placetype":"venue"
},
  "geometry": {"coordinates":[-121.33200100000001,38.681099],"type":"Point"}
}