{
  "type": "Feature",
  "properties": {
    "addr:full":"2535 B St Selma CA 93662",
    "addr:housenumber":"2535",
    "addr:postcode":"93662",
    "addr:street":"B St",
    "iso:country":"US",
    "sg:address":"2535 B St",
    "sg:city":"Selma",
    "sg:classifiers":[
        {
            "category":"Education",
            "subcategory":"School",
            "type":"Public Place"
        }
    ],
    "sg:phone":"+1 559 898 6740",
    "sg:postcode":"93662",
    "sg:province":"CA",
    "sg:tags":[
        "elementary"
    ],
    "sg:website":"http://www.selma.k12.ca.us",
    "wof:name":"Garfield james Elementary School",
    "wof:placetype":"venue"
},
  "geometry": {"coordinates":[-119.60856099999999,36.571042],"type":"Point"}
}