{
  "type": "Feature",
  "properties": {
    "iso:country":"US",
    "sg:address":"1030 Piedmont Rd",
    "sg:city":"San Jose",
    "sg:classifiers":[
        {
            "category":"Real Estate",
            "subcategory":"Real Estate Agent",
            "type":"Services"
        }
    ],
    "sg:phone":"+1 408 926 3900",
    "sg:postcode":"95132",
    "sg:province":"CA",
    "wof:name":"Creekside Realty",
    "wof:placetype":"venue"
},
  "geometry": {"coordinates":[-121.843305,37.392465],"type":"Point"}
}