{
  "type": "Feature",
  "properties": {
    "iso:country":"US",
    "sg:address":"6133 Camino Verde Dr",
    "sg:city":"San Jose",
    "sg:classifiers":[
        {
            "category":"Retail",
            "subcategory":"Laundry & Dry Cleaning",
            "type":"Services"
        }
    ],
    "sg:phone":"+1 408 227 5820",
    "sg:postcode":"95119",
    "sg:province":"CA",
    "wof:name":"Bona's Cleaners",
    "wof:placetype":"venue"
},
  "geometry": {"coordinates":[-121.801196,37.236055],"type":"Point"}
}