{
  "type": "Feature",
  "properties": {
    "iso:country":"US",
    "sg:address":"3033 Cleveland Ave",
    "sg:city":"Santa Rosa",
    "sg:classifiers":[
        {
            "category":"Health Services",
            "subcategory":"Chiropractor",
            "type":"Services"
        }
    ],
    "sg:phone":"+1 707 575 8604",
    "sg:postcode":"95403",
    "sg:province":"CA",
    "wof:name":"Duff Chiropractic",
    "wof:placetype":"venue"
},
  "geometry": {"coordinates":[-122.72936,38.469187],"type":"Point"}
}