{
  "type": "Feature",
  "properties": {
    "iso:country":"US",
    "sg:address":"11011 Crenshaw Blvd Ste 202",
    "sg:city":"Inglewood",
    "sg:classifiers":[
        {
            "category":"Professional",
            "subcategory":"Accounting & Tax Preparation",
            "type":"Services"
        }
    ],
    "sg:phone":"+1 310 672 1415",
    "sg:postcode":"90303",
    "sg:province":"CA",
    "sg:tags":[
        "accountant"
    ],
    "wof:name":"Wilak Services",
    "wof:placetype":"venue"
},
  "geometry": {"coordinates":[-118.327003,33.935699],"type":"Point"}
}