{
  "type": "Feature",
  "properties": {
    "addr:full":"162 Cross St San Luis Obispo CA 93401",
    "addr:housenumber":"162",
    "addr:postcode":"93401",
    "addr:street":"Cross St",
    "iso:country":"US",
    "sg:address":"162 Cross St",
    "sg:city":"San Luis Obispo",
    "sg:classifiers":[
        {
            "category":"Retail",
            "subcategory":"Veterinary Services",
            "type":"Services"
        }
    ],
    "sg:phone":"+1 805 545 8212",
    "sg:postcode":"93401",
    "sg:province":"CA",
    "wof:name":"Animal Care Clinic",
    "wof:placetype":"venue"
},
  "geometry": {"coordinates":[-120.671869,35.245964],"type":"Point"}
}