{
  "type": "Feature",
  "properties": {
    "iso:country":"US",
    "sg:address":"1800 S Robertson Blvd",
    "sg:city":"Los Angeles",
    "sg:classifiers":[
        {
            "category":"Health Services",
            "subcategory":"Health Practitioner",
            "type":"Services"
        }
    ],
    "sg:phone":"+1 310 204 4484",
    "sg:postcode":"90035",
    "sg:province":"CA",
    "sg:tags":[
        "medicine",
        "alternative"
    ],
    "wof:name":"Body Pure",
    "wof:placetype":"venue"
},
  "geometry": {"coordinates":[-118.386334,34.045812],"type":"Point"}
}