{
  "type": "Feature",
  "properties": {
    "iso:country":"US",
    "sg:address":"348 6th Ave",
    "sg:city":"Oakland",
    "sg:classifiers":[
        {
            "category":"Professional",
            "type":"Services"
        }
    ],
    "sg:phone":"+1 510 436 7263",
    "sg:postcode":"94606",
    "sg:province":"CA",
    "sg:tags":[
        "establishment"
    ],
    "wof:name":"Technical Instrument Sn",
    "wof:placetype":"venue"
},
  "geometry": {"coordinates":[-122.259397,37.78965],"type":"Point"}
}