{
  "type": "Feature",
  "properties": {
    "addr:full":"348 6th Ave Oakland CA 94606",
    "addr:housenumber":"348",
    "addr:postcode":"94606",
    "addr:street":"6Th Ave",
    "iso:country":"US",
    "sg:address":"348 6th Ave",
    "sg:city":"Oakland",
    "sg:classifiers":[
        {
            "category":"Professional",
            "type":"Services"
        }
    ],
    "sg:phone":"+1 510 436 7263",
    "sg:postcode":"94606",
    "sg:province":"CA",
    "sg:tags":[
        "establishment"
    ],
    "wof:name":"Technical Instrument Sn",
    "wof:placetype":"venue"
},
  "geometry": {"coordinates":[-122.25939700000001,37.78965],"type":"Point"}
}