{
  "type": "Feature",
  "properties": {
    "iso:country":"US",
    "sg:address":"4782 Marlborough Way",
    "sg:city":"Carmichael",
    "sg:classifiers":[
        {
            "category":"Health Services",
            "subcategory":"Doctor",
            "type":"Services"
        }
    ],
    "sg:phone":"+1 916 488 3433",
    "sg:postcode":"95608",
    "sg:province":"CA",
    "sg:tags":[
        "medicine",
        "physician",
        "practice",
        "surgeons",
        "family"
    ],
    "wof:name":"Duc M Vuong Md",
    "wof:placetype":"venue"
},
  "geometry": {"coordinates":[-121.350059,38.582921],"type":"Point"}
}