{
  "type": "Feature",
  "properties": {
    "addr:full":"250 N Robertson Blvd Suite 606 Beverly Hills CA 90211",
    "addr:housenumber":"250",
    "addr:postcode":"90211",
    "addr:street":"N Robertson Blvd Suite 606;Hills Ca",
    "iso:country":"US",
    "sg:address":"250 N Robertson Blvd Suite 606",
    "sg:city":"Beverly Hills",
    "sg:classifiers":[
        {
            "category":"Health Services",
            "subcategory":"Doctor",
            "type":"Services"
        }
    ],
    "sg:phone":"+1 310 385 2940",
    "sg:postcode":"90211",
    "sg:province":"CA",
    "wof:name":"Warren Roston, MD",
    "wof:placetype":"venue"
},
  "geometry": {"coordinates":[-118.383501,34.069636],"type":"Point"}
}