{
  "type": "Feature",
  "properties": {
    "iso:country":"US",
    "sg:address":"3425 Tanya Ave",
    "sg:city":"Hemet",
    "sg:classifiers":[
        {
            "category":"Wholesale",
            "subcategory":"Non-durable Goods",
            "type":"Manufacturing & Wholesale Goods"
        }
    ],
    "sg:phone":"+1 951 765 0303",
    "sg:postcode":"92545",
    "sg:province":"CA",
    "wof:name":"Jimenez Export Services",
    "wof:placetype":"venue"
},
  "geometry": {"coordinates":[-117.008925,33.732343],"type":"Point"}
}