{
  "type": "Feature",
  "properties": {
    "iso:country":"US",
    "sg:address":"2420 del Paso Rd Ste 255",
    "sg:city":"Sacramento",
    "sg:classifiers":[
        {
            "category":"Health Services",
            "subcategory":"Optometrist",
            "type":"Services"
        }
    ],
    "sg:phone":"+1 916 575 7170",
    "sg:postcode":"95834",
    "sg:province":"CA",
    "wof:name":"Board Of Optometry",
    "wof:placetype":"venue"
},
  "geometry": {"coordinates":[-121.51891000000001,38.65585],"type":"Point"}
}