{
  "type": "Feature",
  "properties": {
    "addr:full":"6988 Gullstrand Street San Diego CA 92122",
    "addr:housenumber":"6988",
    "addr:postcode":"92122",
    "addr:street":"Gullstrand Street",
    "iso:country":"US",
    "sg:address":"6988 Gullstrand Street",
    "sg:city":"San Diego",
    "sg:classifiers":[
        {
            "category":"Professional",
            "subcategory":"Employment Agencies",
            "type":"Services"
        }
    ],
    "sg:phone":"+1 858 414 9603",
    "sg:postcode":"92122",
    "sg:province":"CA",
    "sg:website":"www.sdresumes.com",
    "wof:name":"Competitive Edge Resume Service",
    "wof:placetype":"venue"
},
  "geometry": {"coordinates":[-117.191226,32.856961],"type":"Point"}
}