{
  "type": "Feature",
  "properties": {
    "addr:full":"23072 Lake Center Dr Lake Forest CA 92630",
    "addr:housenumber":"23072",
    "addr:postcode":"92630",
    "addr:street":"Lake Center Dr",
    "iso:country":"US",
    "sg:address":"23072 Lake Center Dr",
    "sg:city":"Lake Forest",
    "sg:classifiers":[
        {
            "category":"Professional",
            "subcategory":"Employment Agencies",
            "type":"Services"
        }
    ],
    "sg:phone":"+1 949 458 6623",
    "sg:postcode":"92630",
    "sg:province":"CA",
    "sg:tags":[
        "opportunity"
    ],
    "wof:name":"Market Wise Staffing & Consult",
    "wof:placetype":"venue"
},
  "geometry": {"coordinates":[-117.71681100000001,33.627381],"type":"Point"}
}