{
  "type": "Feature",
  "properties": {
    "addr:full":"945 Turquoise St San Diego CA 92109",
    "addr:housenumber":"945",
    "addr:postcode":"92109",
    "addr:street":"Turquoise St",
    "iso:country":"US",
    "sg:address":"945 Turquoise St",
    "sg:city":"San Diego",
    "sg:classifiers":[
        {
            "category":"Banks & Credit Unions",
            "subcategory":"Bank",
            "type":"Services"
        }
    ],
    "sg:phone":"+1 858 945 5500",
    "sg:postcode":"92109",
    "sg:province":"CA",
    "sg:tags":[
        "loan",
        "real estate"
    ],
    "sg:website":"www.724mortgage.com",
    "wof:name":"724MORTGAGE.COM",
    "wof:placetype":"venue"
},
  "geometry": {"coordinates":[-117.25606999999999,32.809216],"type":"Point"}
}