{
  "type": "Feature",
  "properties": {
    "iso:country":"US",
    "sg:address":"8880 Rio San Diego Drive Suite 1070",
    "sg:city":"San Diego",
    "sg:classifiers":[
        {
            "category":"Professional",
            "subcategory":"Accounting & Tax Preparation",
            "type":"Services"
        },
        {
            "category":"Professional",
            "subcategory":"Employment Agencies",
            "type":"Services"
        }
    ],
    "sg:phone":"+1 619 295 6161",
    "sg:postcode":"92108",
    "sg:province":"CA",
    "sg:tags":[
        "accountant"
    ],
    "wof:name":"Accountants",
    "wof:placetype":"venue"
},
  "geometry": {"coordinates":[-117.13869800000001,32.776183],"type":"Point"}
}