{
  "type": "Feature",
  "properties": {
    "iso:country":"US",
    "sg:address":"15576 Graham Rd",
    "sg:city":"Middletown",
    "sg:classifiers":[
        {
            "category":"Organizations",
            "subcategory":"Religious Organization",
            "type":"Services"
        }
    ],
    "sg:phone":"+1 707 987 2802",
    "sg:postcode":"95461",
    "sg:province":"CA",
    "sg:tags":[
        "church"
    ],
    "wof:name":"First Baptist Church",
    "wof:placetype":"venue"
},
  "geometry": {"coordinates":[-122.619586,38.752362],"type":"Point"}
}