{
  "type": "Feature",
  "properties": {
    "addr:full":"3775 Pacheco Blvd Martinez CA 94553",
    "addr:housenumber":"3775",
    "addr:postcode":"94553",
    "addr:street":"Pacheco Blvd",
    "iso:country":"US",
    "sg:address":"3775 Pacheco Blvd",
    "sg:city":"Martinez",
    "sg:classifiers":[
        {
            "category":"Building & Trades",
            "subcategory":"Electrical",
            "type":"Services"
        }
    ],
    "sg:phone":"+1 925 686 3535",
    "sg:postcode":"94553",
    "sg:province":"CA",
    "sg:tags":[
        "electric",
        "contractor"
    ],
    "sg:website":"www.dawsonelectric.com",
    "wof:name":"Dawson Electric",
    "wof:placetype":"venue"
},
  "geometry": {"coordinates":[-122.099862,38.010038],"type":"Point"}
}