{
  "type": "Feature",
  "properties": {
    "iso:country":"US",
    "sg:address":"68250 Tortuga Rd",
    "sg:city":"Cathedral City",
    "sg:classifiers":[
        {
            "category":"Building & Trades",
            "subcategory":"Cleaning & Sanitation",
            "type":"Services"
        }
    ],
    "sg:phone":"+1 760 322 3049",
    "sg:postcode":"92234",
    "sg:province":"CA",
    "sg:tags":[
        "window"
    ],
    "wof:name":"Ruben's Window Cleaning",
    "wof:placetype":"venue"
},
  "geometry": {"coordinates":[-116.470022,33.835256],"type":"Point"}
}