{
  "type": "Feature",
  "properties": {
    "iso:country":"US",
    "sg:address":"3553 W 3rd St",
    "sg:city":"Los Angeles",
    "sg:classifiers":[
        {
            "category":"Restaurant",
            "type":"Food & Drink"
        }
    ],
    "sg:phone":"+1 213 387 7172",
    "sg:postcode":"90020",
    "sg:province":"CA",
    "wof:name":"El Pollo Bailador",
    "wof:placetype":"venue"
},
  "geometry": {"coordinates":[-118.293301,34.069256],"type":"Point"}
}