{
  "type": "Feature",
  "properties": {
    "addr:full":"1325 Chorro St San Luis Obispo CA 93401",
    "addr:housenumber":"1325",
    "addr:postcode":"93401",
    "addr:street":"Chorro St",
    "iso:country":"US",
    "sg:address":"1325 Chorro St",
    "sg:city":"San Luis Obispo",
    "sg:classifiers":[
        {
            "category":"Insurance",
            "subcategory":"Insurance Agent",
            "type":"Services"
        }
    ],
    "sg:phone":"+1 805 543 3051",
    "sg:postcode":"93401",
    "sg:province":"CA",
    "wof:name":"Frank Sheahan Insurance",
    "wof:placetype":"venue"
},
  "geometry": {"coordinates":[-120.661435,35.278131],"type":"Point"}
}