{
  "type": "Feature",
  "properties": {
    "addr:full":"145 W San Carlos St San Jose CA 95110",
    "addr:housenumber":"145",
    "addr:postcode":"95110",
    "addr:street":"W San Carlos St",
    "iso:country":"US",
    "sg:address":"145 W San Carlos St",
    "sg:city":"San Jose",
    "sg:classifiers":[
        {
            "category":"Government",
            "subcategory":"Office",
            "type":"Public Place"
        }
    ],
    "sg:phone":"+1 408 277 5277",
    "sg:postcode":"95110",
    "sg:province":"CA",
    "sg:tags":[
        "village"
    ],
    "wof:name":"San Jose Civic Auditorium",
    "wof:placetype":"venue"
},
  "geometry": {"coordinates":[-121.890641,37.329875],"type":"Point"}
}