{
  "type": "Feature",
  "properties": {
    "addr:full":"4324 26th St San Francisco CA 94131",
    "addr:housenumber":"4324",
    "addr:postcode":"94131",
    "addr:street":"26Th St",
    "iso:country":"US",
    "sg:address":"4324 26th St",
    "sg:city":"San Francisco",
    "sg:classifiers":[
        {
            "category":"Professional",
            "subcategory":"Art Services",
            "type":"Services"
        }
    ],
    "sg:phone":"+1 415 794 9683",
    "sg:postcode":"94131",
    "sg:province":"CA",
    "sg:tags":[
        "photographer"
    ],
    "sg:website":"www.soniasavio.com",
    "wof:name":"Sonia Savio Photography",
    "wof:placetype":"venue"
},
  "geometry": {"coordinates":[-122.43666,37.748167],"type":"Point"}
}