{
  "type": "Feature",
  "properties": {
    "iso:country":"US",
    "sg:address":"2128 North St",
    "sg:city":"Selma",
    "sg:classifiers":[
        {
            "category":"Real Estate",
            "subcategory":"Real Estate Agent",
            "type":"Services"
        }
    ],
    "sg:phone":"+1 559 896 4777",
    "sg:postcode":"93662",
    "sg:province":"CA",
    "wof:name":"Bill Tucker & Assocs Real Est",
    "wof:placetype":"venue"
},
  "geometry": {"coordinates":[-119.61242900000001,36.570217],"type":"Point"}
}