{
  "type": "Feature",
  "properties": {
    "iso:country":"US",
    "sg:address":"1204 Wallin Way",
    "sg:city":"Modesto",
    "sg:classifiers":[
        {
            "category":"Professional",
            "subcategory":"Accounting & Tax Preparation",
            "type":"Services"
        }
    ],
    "sg:phone":"+1 209 538 0845",
    "sg:postcode":"95351",
    "sg:province":"CA",
    "sg:tags":[
        "return",
        "filing"
    ],
    "wof:name":"Donald J Cowper Business Svc",
    "wof:placetype":"venue"
},
  "geometry": {"coordinates":[-120.952974,37.611996],"type":"Point"}
}