{
  "type": "Feature",
  "properties": {
    "iso:country":"US",
    "sg:address":"154 W Tulare Ave",
    "sg:city":"Shafter",
    "sg:classifiers":[
        {
            "category":"Organizations",
            "subcategory":"Religious Organization",
            "type":"Services"
        }
    ],
    "sg:phone":"+1 661 746 6543",
    "sg:postcode":"93263",
    "sg:province":"CA",
    "sg:tags":[
        "church"
    ],
    "wof:name":"Spanish Assembly Of God",
    "wof:placetype":"venue"
},
  "geometry": {"coordinates":[-119.279774,35.507177],"type":"Point"}
}