{
  "type": "Feature",
  "properties": {
    "addr:full":"317 Isis Ave Inglewood CA 90301",
    "addr:housenumber":"317",
    "addr:postcode":"90301",
    "addr:street":"Isis Ave",
    "iso:country":"US",
    "sg:address":"317 Isis Ave",
    "sg:city":"Inglewood",
    "sg:classifiers":[
        {
            "category":"Freight",
            "type":"Transportation"
        }
    ],
    "sg:phone":"+1 310 536 9095",
    "sg:postcode":"90301",
    "sg:province":"CA",
    "wof:name":"Allisped",
    "wof:placetype":"venue"
},
  "geometry": {"coordinates":[-118.375348,33.956476],"type":"Point"}
}