{
  "type": "Feature",
  "properties": {
    "addr:full":"155 Park St Lakeport CA 95453",
    "addr:housenumber":"155",
    "addr:postcode":"95453",
    "addr:street":"Park St",
    "iso:country":"US",
    "sg:address":"155 Park St",
    "sg:city":"Lakeport",
    "sg:classifiers":[
        {
            "category":"Restaurant",
            "type":"Food & Drink"
        }
    ],
    "sg:phone":"+1 707 263 7995",
    "sg:postcode":"95453",
    "sg:province":"CA",
    "wof:name":"Yuppy Puppy Hot Dogs",
    "wof:placetype":"venue"
},
  "geometry": {"coordinates":[-122.91419999999999,39.042662],"type":"Point"}
}