{
  "type": "Feature",
  "properties": {
    "addr:full":"1548 W Winton Ave Hayward CA 94545",
    "addr:housenumber":"1548",
    "addr:postcode":"94545",
    "addr:street":"W Winton Ave",
    "iso:country":"US",
    "sg:address":"1548 W Winton Ave",
    "sg:city":"Hayward",
    "sg:classifiers":[
        {
            "category":"Building & Trades",
            "subcategory":"Equipment Rental",
            "type":"Services"
        }
    ],
    "sg:phone":"+1 510 887 0727",
    "sg:postcode":"94545",
    "sg:province":"CA",
    "sg:tags":[
        "yard"
    ],
    "wof:name":"Celebration Party Rentals",
    "wof:placetype":"venue"
},
  "geometry": {"coordinates":[-122.121574,37.653088],"type":"Point"}
}