{
  "type": "Feature",
  "properties": {
    "iso:country":"US",
    "sg:address":"41853 Humber Dr",
    "sg:city":"Temecula",
    "sg:classifiers":[
        {
            "category":"Professional",
            "subcategory":"Art Services",
            "type":"Services"
        }
    ],
    "sg:phone":"+1 951 694 4191",
    "sg:postcode":"92591",
    "sg:province":"CA",
    "sg:tags":[
        "photographer"
    ],
    "wof:name":"Aglow Photography",
    "wof:placetype":"venue"
},
  "geometry": {"coordinates":[-117.13103700000001,33.514823],"type":"Point"}
}