{
  "type": "Feature",
  "properties": {
    "iso:country":"US",
    "sg:address":"21382 Dockside Cir",
    "sg:city":"Huntington Beach",
    "sg:classifiers":[
        {
            "category":"Building & Trades",
            "subcategory":"Construction",
            "type":"Services"
        }
    ],
    "sg:phone":"+1 714 965 0245",
    "sg:postcode":"92646",
    "sg:province":"CA",
    "sg:tags":[
        "roofing",
        "contractor"
    ],
    "wof:name":"Adams Roofing",
    "wof:placetype":"venue"
},
  "geometry": {"coordinates":[-117.964724,33.651328],"type":"Point"}
}