{
  "type": "Feature",
  "properties": {
    "iso:country":"US",
    "sg:address":"3116 W Sunset Blvd",
    "sg:city":"Los Angeles",
    "sg:classifiers":[
        {
            "category":"Manufacturing",
            "subcategory":"Jewelry",
            "type":"Manufacturing & Wholesale Goods"
        },
        {
            "category":"Shopping",
            "subcategory":"Jewelry",
            "type":"Retail Goods"
        }
    ],
    "sg:phone":"+1 323 661 9805",
    "sg:postcode":"90026",
    "sg:province":"CA",
    "sg:tags":[
        "precious",
        "designer",
        "metal",
        "mfg"
    ],
    "wof:name":"Leon Jewelry and Diamonds",
    "wof:placetype":"venue"
},
  "geometry": {"coordinates":[-118.27441,34.084302],"type":"Point"}
}