{
  "type": "Feature",
  "properties": {
    "iso:country":"US",
    "sg:address":"3827 Whiteside St",
    "sg:city":"Los Angeles",
    "sg:classifiers":[
        {
            "category":"Freight",
            "type":"Transportation"
        }
    ],
    "sg:phone":"+1 323 261 0768",
    "sg:postcode":"90063",
    "sg:province":"CA",
    "wof:name":"A G Express",
    "wof:placetype":"venue"
},
  "geometry": {"coordinates":[-118.182271,34.057811],"type":"Point"}
}