{
  "type": "Feature",
  "properties": {
    "addr:full":"333 S Beverly Dr Beverly Hills CA 90212",
    "addr:housenumber":"333",
    "addr:postcode":"90212",
    "addr:street":"S Beverly Dr",
    "iso:country":"US",
    "sg:address":"333 S Beverly Dr",
    "sg:city":"Beverly Hills",
    "sg:classifiers":[
        {
            "category":"Professional",
            "subcategory":"Lawyer & Legal Services",
            "type":"Services"
        }
    ],
    "sg:phone":"+1 310 551 0881",
    "sg:postcode":"90212",
    "sg:province":"CA",
    "sg:tags":[
        "attorney"
    ],
    "wof:name":"Jeffrey A Cohen",
    "wof:placetype":"venue"
},
  "geometry": {"coordinates":[-118.399154,34.061559],"type":"Point"}
}