{
  "type": "Feature",
  "properties": {
    "iso:country":"US",
    "sg:address":"465 Coloma St",
    "sg:city":"Sausalito",
    "sg:classifiers":[
        {
            "category":"Wholesale",
            "subcategory":"Furniture",
            "type":"Manufacturing & Wholesale Goods"
        }
    ],
    "sg:phone":"+1 415 332 6719",
    "sg:postcode":"94965",
    "sg:province":"CA",
    "sg:website":"www.susangoldstick.com",
    "wof:name":"Susan Goldstick Inc",
    "wof:placetype":"venue"
},
  "geometry": {"coordinates":[-122.503209,37.867819],"type":"Point"}
}