{
  "type": "Feature",
  "properties": {
    "iso:country":"US",
    "sg:address":"12801 Lopez Canyon Rd",
    "sg:city":"Sylmar",
    "sg:classifiers":[
        {
            "category":"Bars & Pubs",
            "type":"Food & Drink"
        }
    ],
    "sg:phone":"+1 818 899 1470",
    "sg:postcode":"91342",
    "sg:province":"CA",
    "sg:tags":[
        "drinking",
        "timber",
        "operation",
        "animal",
        "tract"
    ],
    "wof:name":"Rancho Vista De Solana",
    "wof:placetype":"venue"
},
  "geometry": {"coordinates":[-118.382811,34.314675],"type":"Point"}
}