{
  "type": "Feature",
  "properties": {
    "addr:full":"3305 W Magnolia Blvd Burbank CA 91505",
    "addr:housenumber":"3305",
    "addr:postcode":"91505",
    "addr:street":"W Magnolia Blvd",
    "iso:country":"US",
    "sg:address":"3305 W Magnolia Blvd",
    "sg:city":"Burbank",
    "sg:classifiers":[
        {
            "category":"Retail",
            "subcategory":"Laundry & Dry Cleaning",
            "type":"Services"
        }
    ],
    "sg:phone":"+1 818 843 3925",
    "sg:postcode":"91505",
    "sg:province":"CA",
    "wof:name":"California Cleaners",
    "wof:placetype":"venue"
},
  "geometry": {"coordinates":[-118.343002,34.168999],"type":"Point"}
}