{
  "type": "Feature",
  "properties": {
    "addr:full":"2275 S Main St Corona CA 92882",
    "addr:housenumber":"2275",
    "addr:postcode":"92882",
    "addr:street":"S Main St",
    "iso:country":"US",
    "sg:address":"2275 S Main St",
    "sg:city":"Corona",
    "sg:classifiers":[
        {
            "category":"Health Services",
            "subcategory":"Optometrist",
            "type":"Services"
        }
    ],
    "sg:phone":"+1 951 736 8751",
    "sg:postcode":"92882",
    "sg:province":"CA",
    "wof:name":"Clear Vision Property",
    "wof:placetype":"venue"
},
  "geometry": {"coordinates":[-117.569766,33.853293],"type":"Point"}
}