{
  "type": "Feature",
  "properties": {
    "addr:full":"9453 Taft Hwy Bakersfield CA 93311",
    "addr:housenumber":"9453",
    "addr:postcode":"93311",
    "addr:street":"Taft Hwy",
    "iso:country":"US",
    "sg:address":"9453 Taft Hwy",
    "sg:city":"Bakersfield",
    "sg:classifiers":[
        {
            "category":"Wholesale",
            "subcategory":"Machinery & Supplies",
            "type":"Manufacturing & Wholesale Goods"
        }
    ],
    "sg:phone":"+1 661 834 4489",
    "sg:postcode":"93311",
    "sg:province":"CA",
    "sg:tags":[
        "equipment",
        "dairy"
    ],
    "wof:name":"Southwest Dairy Equipment Inc",
    "wof:placetype":"venue"
},
  "geometry": {"coordinates":[-119.104928,35.26709],"type":"Point"}
}