{
  "type": "Feature",
  "properties": {
    "iso:country":"US",
    "sg:address":"1812 Golf Rd",
    "sg:city":"Turlock",
    "sg:classifiers":[
        {
            "category":"Building & Trades",
            "subcategory":"Landscaping Services",
            "type":"Services"
        }
    ],
    "sg:phone":"+1 209 668 9457",
    "sg:postcode":"95380",
    "sg:province":"CA",
    "wof:name":"Ochoa Gardening Service",
    "wof:placetype":"venue"
},
  "geometry": {"coordinates":[-120.830601,37.475123],"type":"Point"}
}