{
  "type": "Feature",
  "properties": {
    "addr:full":"1451 River Park Dr Ste 285 Sacramento CA 95815",
    "addr:housenumber":"1451",
    "addr:postcode":"95815",
    "addr:street":"River Park Dr Ste 285",
    "iso:country":"US",
    "sg:address":"1451 River Park Dr Ste 285",
    "sg:city":"Sacramento",
    "sg:classifiers":[
        {
            "category":"Professional",
            "subcategory":"Lawyer & Legal Services",
            "type":"Services"
        }
    ],
    "sg:phone":"+1 916 567 1400",
    "sg:postcode":"95815",
    "sg:province":"CA",
    "wof:name":"Epstein Bradley J",
    "wof:placetype":"venue"
},
  "geometry": {"coordinates":[-121.439289,38.598519],"type":"Point"}
}