{
  "type": "Feature",
  "properties": {
    "iso:country":"US",
    "sg:address":"27502 Vantage Cir",
    "sg:city":"San Juan Capistrano",
    "sg:classifiers":[
        {
            "category":"Professional",
            "type":"Services"
        }
    ],
    "sg:phone":"+1 949 493 6063",
    "sg:postcode":"92675",
    "sg:province":"CA",
    "wof:name":"Michael H Voss A California Co",
    "wof:placetype":"venue"
},
  "geometry": {"coordinates":[-117.65065800000001,33.526403],"type":"Point"}
}