{
  "type": "Feature",
  "properties": {
    "addr:full":"25202 Crenshaw Blvd Ste 205 Torrance CA 90505",
    "addr:housenumber":"25202",
    "addr:postcode":"90505",
    "addr:street":"Crenshaw Blvd Ste 205",
    "iso:country":"US",
    "sg:address":"25202 Crenshaw Blvd Ste 205",
    "sg:city":"Torrance",
    "sg:classifiers":[
        {
            "category":"Professional",
            "subcategory":"Lawyer & Legal Services",
            "type":"Services"
        }
    ],
    "sg:phone":"+1 310 891 2875",
    "sg:postcode":"90505",
    "sg:province":"CA",
    "wof:name":"Mazorow Marc A Law Office of",
    "wof:placetype":"venue"
},
  "geometry": {"coordinates":[-118.329002,33.795399],"type":"Point"}
}