{
  "type": "Feature",
  "properties": {
    "iso:country":"US",
    "sg:address":"670 Coleman Ave",
    "sg:city":"San Jose",
    "sg:classifiers":[
        {
            "category":"Utilities",
            "type":"Services"
        }
    ],
    "sg:phone":"+1 408 295 4223",
    "sg:postcode":"95110",
    "sg:province":"CA",
    "sg:tags":[
        "locating"
    ],
    "wof:name":"Lewis & Tibbetts",
    "wof:placetype":"venue"
},
  "geometry": {"coordinates":[-121.910436,37.341987],"type":"Point"}
}