{
  "type": "Feature",
  "properties": {
    "addr:full":"612 S Flower St Los Angeles CA 90017",
    "addr:housenumber":"612",
    "addr:postcode":"90017",
    "addr:street":"S Flower St",
    "iso:country":"US",
    "sg:address":"612 S Flower St",
    "sg:city":"Los Angeles",
    "sg:classifiers":[
        {
            "category":"Real Estate",
            "subcategory":"Real Estate Operator",
            "type":"Services"
        }
    ],
    "sg:phone":"+1 213 430 9112",
    "sg:postcode":"90017",
    "sg:province":"CA",
    "sg:tags":[
        "apartment"
    ],
    "sg:website":"www.pegasusapartments.com/",
    "wof:name":"Pegasus Apartment Homes",
    "wof:placetype":"venue"
},
  "geometry": {"coordinates":[-118.257453,34.049543],"type":"Point"}
}