{
  "type": "Feature",
  "properties": {
    "iso:country":"US",
    "sg:address":"1557 165th Ave",
    "sg:city":"San Leandro",
    "sg:classifiers":[
        {
            "category":"Taxi",
            "type":"Transportation"
        }
    ],
    "sg:phone":"+1 510 278 5919",
    "sg:postcode":"94578",
    "sg:province":"CA",
    "sg:tags":[
        "taxicab"
    ],
    "wof:name":"Ram Singh Matharu",
    "wof:placetype":"venue"
},
  "geometry": {"coordinates":[-122.108527,37.696103],"type":"Point"}
}