{
  "type": "Feature",
  "properties": {
    "iso:country":"US",
    "sg:address":"2445 N Texas St",
    "sg:city":"Fairfield",
    "sg:classifiers":[
        {
            "category":"Shopping",
            "type":"Retail Goods"
        }
    ],
    "sg:phone":"+1 707 422 0114",
    "sg:postcode":"94533",
    "sg:province":"CA",
    "sg:tags":[
        "telephone",
        "cellular"
    ],
    "wof:name":"Radio Shack",
    "wof:placetype":"venue"
},
  "geometry": {"coordinates":[-122.03426899999999,38.275668],"type":"Point"}
}