{
  "type": "Feature",
  "properties": {
    "iso:country":"US",
    "sg:address":"2460 N 1st St",
    "sg:city":"San Jose",
    "sg:classifiers":[
        {
            "category":"Utilities",
            "subcategory":"Telephone",
            "type":"Services"
        }
    ],
    "sg:phone":"+1 408 232 4858",
    "sg:postcode":"95131",
    "sg:province":"CA",
    "sg:tags":[
        "communications"
    ],
    "wof:name":"Ul On Co Inc",
    "wof:placetype":"venue"
},
  "geometry": {"coordinates":[-121.923537,37.380379],"type":"Point"}
}