{
  "type": "Feature",
  "properties": {
    "addr:full":"Golden West St Huntington Beach CA 92648",
    "addr:postcode":"92648",
    "addr:street":"West",
    "iso:country":"US",
    "sg:address":"Golden West St",
    "sg:city":"Huntington Beach",
    "sg:classifiers":[
        {
            "category":"Sports & Exercise",
            "subcategory":"Golf",
            "type":"Entertainment"
        }
    ],
    "sg:phone":"+1 714 425 9931",
    "sg:postcode":"92648",
    "sg:province":"CA",
    "sg:website":"www.stockteam.com/frisbee.html",
    "wof:name":"Huntington Beach Central Park Disc Golf",
    "wof:placetype":"venue"
},
  "geometry": {"coordinates":[-118.00655399999999,33.703599],"type":"Point"}
}