{
  "type": "Feature",
  "properties": {
    "addr:full":"8608 Garden Grove Blvd Garden Grove CA 92844",
    "addr:housenumber":"8608",
    "addr:postcode":"92844",
    "addr:street":"Garden Grove Blvd",
    "iso:country":"US",
    "sg:address":"8608 Garden Grove Blvd",
    "sg:city":"Garden Grove",
    "sg:classifiers":[
        {
            "category":"Shopping",
            "subcategory":"Stationery & Office Supplies",
            "type":"Retail Goods"
        }
    ],
    "sg:phone":"+1 714 539 9808",
    "sg:postcode":"92844",
    "sg:province":"CA",
    "sg:tags":[
        "equipment"
    ],
    "wof:name":"Jump Q Educational Books & Supplies",
    "wof:placetype":"venue"
},
  "geometry": {"coordinates":[-117.98200199999999,33.773701],"type":"Point"}
}