{
  "type": "Feature",
  "properties": {
    "addr:full":"500 Sansome Street 7th Flr San Francisco CA 94111",
    "addr:housenumber":"500",
    "addr:postcode":"flr;94111",
    "addr:street":"Sansome Street",
    "iso:country":"US",
    "sg:address":"500 Sansome Street 7th Flr",
    "sg:city":"San Francisco",
    "sg:classifiers":[
        {
            "category":"Communications",
            "subcategory":"Film & Video Production",
            "type":"Services"
        }
    ],
    "sg:phone":"+1 415 394 2400",
    "sg:postcode":"94111",
    "sg:province":"CA",
    "sg:tags":[
        "video/film"
    ],
    "sg:website":"www.filmcore.net/",
    "wof:name":"Filmcore Distribution",
    "wof:placetype":"venue"
},
  "geometry": {"coordinates":[-122.401214,37.795135],"type":"Point"}
}