{
  "type": "Feature",
  "properties": {
    "iso:country":"US",
    "sg:address":"25395 Pineview Dr",
    "sg:city":"Colfax",
    "sg:classifiers":[
        {
            "category":"Manufacturing",
            "subcategory":"Buildings",
            "type":"Manufacturing & Wholesale Goods"
        },
        {
            "category":"Building & Trades",
            "subcategory":"Construction",
            "type":"Services"
        }
    ],
    "sg:phone":"+1 530 346 7692",
    "sg:postcode":"95713",
    "sg:province":"CA",
    "sg:tags":[
        "home",
        "builder",
        "contractor"
    ],
    "wof:name":"H&H Construction",
    "wof:placetype":"venue"
},
  "geometry": {"coordinates":[-120.96472900000001,39.113958],"type":"Point"}
}