{
  "type": "Feature",
  "properties": {
    "iso:country":"US",
    "sg:address":"23542 Lyons Ave",
    "sg:city":"Newhall",
    "sg:classifiers":[
        {
            "category":"Professional",
            "subcategory":"Lawyer & Legal Services",
            "type":"Services"
        }
    ],
    "sg:phone":"+1 661 287 9728",
    "sg:postcode":"91321",
    "sg:province":"CA",
    "wof:name":"Patnoi Stanley G Atty",
    "wof:placetype":"venue"
},
  "geometry": {"coordinates":[-118.54499800000001,34.379501],"type":"Point"}
}