{
  "type": "Feature",
  "properties": {
    "addr:full":"1955 Monument Blvd Concord CA 94520",
    "addr:housenumber":"1955",
    "addr:postcode":"94520",
    "addr:street":"Monument Blvd",
    "iso:country":"US",
    "sg:address":"1955 Monument Blvd",
    "sg:city":"Concord",
    "sg:classifiers":[
        {
            "category":"Retail",
            "subcategory":"Repair Shop",
            "type":"Services"
        }
    ],
    "sg:phone":"+1 925 246 8682",
    "sg:postcode":"94520",
    "sg:province":"CA",
    "sg:tags":[
        "watch"
    ],
    "wof:name":"Watch Zone",
    "wof:placetype":"venue"
},
  "geometry": {"coordinates":[-122.04109,37.954955],"type":"Point"}
}