{
  "type": "Feature",
  "properties": {
    "iso:country":"US",
    "sg:address":"800 Playa Ave",
    "sg:city":"Seaside",
    "sg:classifiers":[
        {
            "category":"Home & Garden",
            "subcategory":"Hardware",
            "type":"Retail Goods"
        }
    ],
    "sg:phone":"+1 831 899 5144",
    "sg:postcode":"93955",
    "sg:province":"CA",
    "wof:name":"Osh",
    "wof:placetype":"venue"
},
  "geometry": {"coordinates":[-121.845895,36.619993],"type":"Point"}
}