{
  "type": "Feature",
  "properties": {
    "addr:full":"9286 Madison Ave Orangevale CA 95662",
    "addr:housenumber":"9286",
    "addr:postcode":"95662",
    "addr:street":"Madison Ave",
    "iso:country":"US",
    "sg:address":"9286 Madison Ave",
    "sg:city":"Orangevale",
    "sg:classifiers":[
        {
            "category":"Personal",
            "type":"Services"
        }
    ],
    "sg:phone":"+1 916 600 6044",
    "sg:postcode":"95662",
    "sg:province":"CA",
    "sg:tags":[
        "therapist",
        "massage"
    ],
    "wof:name":"Laura Nelson Cmt",
    "wof:placetype":"venue"
},
  "geometry": {"coordinates":[-121.20773699999999,38.66982],"type":"Point"}
}