{
  "type": "Feature",
  "properties": {
    "iso:country":"US",
    "sg:address":"1695 Market St",
    "sg:city":"San Francisco",
    "sg:classifiers":[
        {
            "category":"Professional",
            "type":"Services"
        }
    ],
    "sg:phone":"+1 415 487 8662",
    "sg:postcode":"94103",
    "sg:province":"CA",
    "sg:tags":[
        "establishment"
    ],
    "wof:name":"Center For Young Womens Dev",
    "wof:placetype":"venue"
},
  "geometry": {"coordinates":[-122.421895,37.772929],"type":"Point"}
}