{
  "type": "Feature",
  "properties": {
    "iso:country":"US",
    "sg:address":"24377 Newhall Ave Apt 110",
    "sg:city":"Newhall",
    "sg:classifiers":[
        {
            "category":"Real Estate",
            "subcategory":"Real Estate Operator",
            "type":"Services"
        }
    ],
    "sg:phone":"+1 661 254 9325",
    "sg:postcode":"91321",
    "sg:province":"CA",
    "sg:tags":[
        "apartment"
    ],
    "wof:name":"Newhall Terrace Apartments",
    "wof:placetype":"venue"
},
  "geometry": {"coordinates":[-118.531998,34.3787],"type":"Point"}
}