{
  "type": "Feature",
  "properties": {
    "addr:full":"950 S Bascom Ave Ste 3114 San Jose CA 95128",
    "addr:housenumber":"950",
    "addr:postcode":"95128",
    "addr:street":"S Bascom Ave Ste 3114",
    "iso:country":"US",
    "sg:address":"950 S Bascom Ave Ste 3114",
    "sg:city":"San Jose",
    "sg:classifiers":[
        {
            "category":"Professional",
            "subcategory":"Accounting & Tax Preparation",
            "type":"Services"
        }
    ],
    "sg:phone":"+1 408 295 0724",
    "sg:postcode":"95128",
    "sg:province":"CA",
    "sg:tags":[
        "accountant"
    ],
    "wof:name":"Conte Joseph A Dr",
    "wof:placetype":"venue"
},
  "geometry": {"coordinates":[-121.931999,37.3088],"type":"Point"}
}