{
  "type": "Feature",
  "properties": {
    "iso:country":"US",
    "sg:address":"8630 Balboa Blvd",
    "sg:city":"Northridge",
    "sg:classifiers":[
        {
            "category":"Personal",
            "subcategory":"Barber",
            "type":"Services"
        }
    ],
    "sg:phone":"+1 818 895 5500",
    "sg:postcode":"91325",
    "sg:province":"CA",
    "wof:name":"Reggie's Barber Shop",
    "wof:placetype":"venue"
},
  "geometry": {"coordinates":[-118.502529,34.227944],"type":"Point"}
}