{
  "type": "Feature",
  "properties": {
    "iso:country":"US",
    "sg:address":"3162 Potrero Way",
    "sg:city":"Fairfield",
    "sg:classifiers":[
        {
            "category":"Utilities",
            "subcategory":"Refuse",
            "type":"Services"
        }
    ],
    "sg:phone":"+1 707 421 8997",
    "sg:postcode":"94534",
    "sg:province":"CA",
    "sg:tags":[
        "system"
    ],
    "wof:name":"Waste Recovery West Inc",
    "wof:placetype":"venue"
},
  "geometry": {"coordinates":[-122.071081,38.262793],"type":"Point"}
}