{
  "type": "Feature",
  "properties": {
    "iso:country":"US",
    "sg:address":"1601 McCarthy Boulevard",
    "sg:city":"Milpitas",
    "sg:classifiers":[
        {
            "category":"Shopping",
            "subcategory":"Mobile Phones",
            "type":"Retail Goods"
        }
    ],
    "sg:phone":"+1 408 232 0100",
    "sg:postcode":"95035",
    "sg:province":"CA",
    "wof:name":"Kineto Wireless",
    "wof:placetype":"venue"
},
  "geometry": {"coordinates":[-121.91797800000001,37.405814],"type":"Point"}
}