{
  "type": "Feature",
  "properties": {
    "addr:full":"15424 Haas Ave Gardena CA 90249",
    "addr:housenumber":"15424",
    "addr:postcode":"90249",
    "addr:street":"Haas Ave",
    "iso:country":"US",
    "sg:address":"15424 Haas Ave",
    "sg:city":"Gardena",
    "sg:classifiers":[
        {
            "category":"Building & Trades",
            "subcategory":"Construction",
            "type":"Services"
        }
    ],
    "sg:phone":"+1 310 532 7855",
    "sg:postcode":"90249",
    "sg:province":"CA",
    "sg:tags":[
        "contractor",
        "specialty",
        "grading"
    ],
    "wof:name":"Anthony Sena",
    "wof:placetype":"venue"
},
  "geometry": {"coordinates":[-118.31688699999999,33.890808],"type":"Point"}
}