{
  "type": "Feature",
  "properties": {
    "iso:country":"US",
    "sg:address":"2200 Powell St Ste 430",
    "sg:city":"Emeryville",
    "sg:classifiers":[
        {
            "category":"Professional",
            "subcategory":"Research",
            "type":"Services"
        }
    ],
    "sg:phone":"+1 510 923 0623",
    "sg:postcode":"94608",
    "sg:province":"CA",
    "sg:tags":[
        "economic",
        "analysis"
    ],
    "sg:website":"http://www.oskr.com",
    "wof:name":"Oskr",
    "wof:placetype":"venue"
},
  "geometry": {"coordinates":[-122.30236499999999,37.83717],"type":"Point"}
}