{
  "type": "Feature",
  "properties": {
    "addr:full":"12007 Los Nietos Rd Santa Fe Springs CA 90670",
    "addr:housenumber":"12007",
    "addr:postcode":"90670",
    "addr:street":"Los Nietos Rd",
    "iso:country":"US",
    "sg:address":"12007 Los Nietos Rd",
    "sg:city":"Santa Fe Springs",
    "sg:classifiers":[
        {
            "category":"Banks & Credit Unions",
            "subcategory":"Bank",
            "type":"Services"
        }
    ],
    "sg:phone":"+1 562 777 9977",
    "sg:postcode":"90670",
    "sg:province":"CA",
    "sg:tags":[
        "lender",
        "independent",
        "finance"
    ],
    "wof:name":"Earl Investment Corporation",
    "wof:placetype":"venue"
},
  "geometry": {"coordinates":[-118.06753399999999,33.955016],"type":"Point"}
}