{
  "type": "Feature",
  "properties": {
    "iso:country":"US",
    "sg:address":"399 Haight St",
    "sg:city":"San Francisco",
    "sg:classifiers":[
        {
            "category":"Food & Beverages",
            "subcategory":"Groceries & Convenience Stores",
            "type":"Retail Goods"
        }
    ],
    "sg:phone":"+1 415 255 4583",
    "sg:postcode":"94102",
    "sg:province":"CA",
    "wof:name":"S & W Market",
    "wof:placetype":"venue"
},
  "geometry": {"coordinates":[-122.429001,37.772202],"type":"Point"}
}