{
  "type": "Feature",
  "properties": {
    "iso:country":"US",
    "sg:address":"21494 Victory Blvd",
    "sg:city":"Woodland Hills",
    "sg:classifiers":[
        {
            "category":"Recreation",
            "subcategory":"Amusement Park",
            "type":"Entertainment"
        }
    ],
    "sg:phone":"+1 818 386 0643",
    "sg:postcode":"91367",
    "sg:province":"CA",
    "wof:name":"Golftec",
    "wof:placetype":"venue"
},
  "geometry": {"coordinates":[-118.59899900000001,34.1884],"type":"Point"}
}