{
  "type": "Feature",
  "properties": {
    "addr:full":"12943 1st Ave Victorville CA 92395",
    "addr:housenumber":"12943",
    "addr:postcode":"92395",
    "addr:street":"1St Ave",
    "iso:country":"US",
    "sg:address":"12943 1st Ave",
    "sg:city":"Victorville",
    "sg:classifiers":[
        {
            "category":"Manufacturing",
            "subcategory":"Glass & Minerals",
            "type":"Manufacturing & Wholesale Goods"
        }
    ],
    "sg:phone":"+1 760 951 7365",
    "sg:postcode":"92395",
    "sg:province":"CA",
    "sg:tags":[
        "plate",
        "shape",
        "glass-wholesale",
        "window",
        "special",
        "circle",
        "glass-auto",
        "manufacturer"
    ],
    "wof:name":"Golden State Autoglass",
    "wof:placetype":"venue"
},
  "geometry": {"coordinates":[-117.295816,34.486162],"type":"Point"}
}