{
  "type": "Feature",
  "properties": {
    "iso:country":"US",
    "sg:address":"12269 Oak Knoll Rd",
    "sg:city":"Poway",
    "sg:classifiers":[
        {
            "category":"Organizations",
            "subcategory":"Religious Organization",
            "type":"Services"
        }
    ],
    "sg:phone":"+1 858 486 1231",
    "sg:postcode":"92064",
    "sg:province":"CA",
    "wof:name":"San Diego Sikh Gurudwara",
    "wof:placetype":"venue"
},
  "geometry": {"coordinates":[-117.0642,32.949844],"type":"Point"}
}