{
  "type": "Feature",
  "properties": {
    "addr:full":"29885 2nd St Lake Elsinore CA 92532",
    "addr:housenumber":"29885",
    "addr:postcode":"92532",
    "addr:street":"2Nd St",
    "iso:country":"US",
    "sg:address":"29885 2nd St",
    "sg:city":"Lake Elsinore",
    "sg:classifiers":[
        {
            "category":"Wholesale",
            "subcategory":"Non-durable Goods",
            "type":"Manufacturing & Wholesale Goods"
        }
    ],
    "sg:phone":"+1 951 674 7074",
    "sg:postcode":"92532",
    "sg:province":"CA",
    "sg:tags":[
        "advertising"
    ],
    "wof:name":"Xtreme Advertising",
    "wof:placetype":"venue"
},
  "geometry": {"coordinates":[-117.330623,33.68627],"type":"Point"}
}