{
  "type": "Feature",
  "properties": {
    "addr:full":"10524 La Morada Drive San Diego CA 92124",
    "addr:housenumber":"10524",
    "addr:postcode":"92124",
    "addr:street":"La Morada Drive",
    "iso:country":"US",
    "sg:address":"10524 La Morada Drive",
    "sg:city":"San Diego",
    "sg:classifiers":[
        {
            "category":"Retail",
            "subcategory":"Laundry & Dry Cleaning",
            "type":"Services"
        }
    ],
    "sg:phone":"+1 858 268 8827",
    "sg:postcode":"92124",
    "sg:province":"CA",
    "wof:name":"Dry Cleaning Laundry Mechanical Services",
    "wof:placetype":"venue"
},
  "geometry": {"coordinates":[-117.09929200000001,32.83872],"type":"Point"}
}