{
  "type": "Feature",
  "properties": {
    "iso:country":"US",
    "sg:address":"415 Jackson St",
    "sg:city":"San Francisco",
    "sg:classifiers":[
        {
            "category":"Communications",
            "subcategory":"Film & Video Production",
            "type":"Services"
        }
    ],
    "sg:phone":"+1 415 781 2603",
    "sg:postcode":"94111",
    "sg:province":"CA",
    "sg:tags":[
        "taping"
    ],
    "wof:name":"AVR Gold",
    "wof:placetype":"venue"
},
  "geometry": {"coordinates":[-122.40223,37.796507],"type":"Point"}
}