{
  "type": "Feature",
  "properties": {
    "iso:country":"US",
    "sg:address":"11915 Lakewood Boulevard",
    "sg:city":"Downey",
    "sg:classifiers":[
        {
            "category":"Retail",
            "subcategory":"Laundry & Dry Cleaning",
            "type":"Services"
        }
    ],
    "sg:phone":"+1 562 622 3739",
    "sg:postcode":"90241",
    "sg:province":"CA",
    "sg:website":"www.joycleaners.com",
    "wof:name":"Joy Cleaners",
    "wof:placetype":"venue"
},
  "geometry": {"coordinates":[-118.125432,33.929623],"type":"Point"}
}