{
  "type": "Feature",
  "properties": {
    "addr:full":"3246 Folsom St San Francisco CA 94110",
    "addr:housenumber":"3246",
    "addr:postcode":"94110",
    "addr:street":"Folsom St",
    "iso:country":"US",
    "sg:address":"3246 Folsom St",
    "sg:city":"San Francisco",
    "sg:classifiers":[
        {
            "category":"Shopping",
            "type":"Retail Goods"
        }
    ],
    "sg:phone":"+1 415 824 0201",
    "sg:postcode":"94110",
    "sg:province":"CA",
    "sg:tags":[
        "merchandise"
    ],
    "wof:name":"Devoted Pet Sitters",
    "wof:placetype":"venue"
},
  "geometry": {"coordinates":[-122.41348499999999,37.745592],"type":"Point"}
}