{
  "type": "Feature",
  "properties": {
    "iso:country":"US",
    "sg:address":"4201 Long Beach Blvd Ste 404",
    "sg:city":"Long Beach",
    "sg:classifiers":[
        {
            "category":"Communications",
            "subcategory":"Newspaper",
            "type":"Services"
        }
    ],
    "sg:phone":"+1 562 283 0600",
    "sg:postcode":"90807",
    "sg:province":"CA",
    "sg:tags":[
        "print",
        "medium"
    ],
    "wof:name":"Carson Courier the",
    "wof:placetype":"venue"
},
  "geometry": {"coordinates":[-118.189003,33.834499],"type":"Point"}
}