{
  "type": "Feature",
  "properties": {
    "addr:full":"4909 Stonehedge Dr Santa Rosa CA 95405",
    "addr:housenumber":"4909",
    "addr:postcode":"95405",
    "addr:street":"Stonehedge Dr",
    "iso:country":"US",
    "sg:address":"4909 Stonehedge Dr",
    "sg:city":"Santa Rosa",
    "sg:classifiers":[
        {
            "category":"Building & Trades",
            "subcategory":"Construction",
            "type":"Services"
        }
    ],
    "sg:phone":"+1 707 539 2196",
    "sg:postcode":"95405",
    "sg:province":"CA",
    "sg:tags":[
        "general",
        "contractor"
    ],
    "wof:name":"A P Construction",
    "wof:placetype":"venue"
},
  "geometry": {"coordinates":[-122.65316199999999,38.444586],"type":"Point"}
}