{
  "type": "Feature",
  "properties": {
    "addr:full":"1713 Kyrsten Ter Alpine CA 91901",
    "addr:housenumber":"1713",
    "addr:postcode":"91901",
    "addr:street":"Kyrsten Ter",
    "iso:country":"US",
    "sg:address":"1713 Kyrsten Ter",
    "sg:city":"Alpine",
    "sg:classifiers":[
        {
            "category":"Building & Trades",
            "subcategory":"Construction",
            "type":"Services"
        }
    ],
    "sg:phone":"+1 619 596 7688",
    "sg:postcode":"91901",
    "sg:province":"CA",
    "sg:tags":[
        "residential"
    ],
    "wof:name":"S J Brooks",
    "wof:placetype":"venue"
},
  "geometry": {"coordinates":[-116.778971,32.833939],"type":"Point"}
}