{
  "type": "Feature",
  "properties": {
    "iso:country":"US",
    "sg:address":"2485 Alvarado St",
    "sg:city":"Oxnard",
    "sg:classifiers":[
        {
            "category":"Retail",
            "subcategory":"Auto Repair",
            "type":"Services"
        }
    ],
    "sg:phone":"+1 805 983 3434",
    "sg:postcode":"93036",
    "sg:province":"CA",
    "sg:tags":[
        "repairing",
        "automobile"
    ],
    "wof:name":"Gavia's Mobile Mechanic",
    "wof:placetype":"venue"
},
  "geometry": {"coordinates":[-119.164053,34.229038],"type":"Point"}
}