{
  "type": "Feature",
  "properties": {
    "iso:country":"US",
    "sg:address":"951 Moraga Ave",
    "sg:city":"Piedmont",
    "sg:classifiers":[
        {
            "category":"Sports & Exercise",
            "subcategory":"Skate Park",
            "type":"Entertainment"
        }
    ],
    "sg:postcode":"94618",
    "sg:province":"CA",
    "sg:website":"www.ci.piedmont.ca.us/recreation...",
    "wof:name":"Kennelly Skate Park",
    "wof:placetype":"venue"
},
  "geometry": {"coordinates":[-122.22604200000001,37.829709],"type":"Point"}
}