{
  "type": "Feature",
  "properties": {
    "addr:full":"3516 G St Merced CA 95340",
    "addr:housenumber":"3516",
    "addr:postcode":"95340",
    "addr:street":"G St",
    "iso:country":"US",
    "sg:address":"3516 G St",
    "sg:city":"Merced",
    "sg:classifiers":[
        {
            "category":"Real Estate",
            "subcategory":"Real Estate Agent",
            "type":"Services"
        }
    ],
    "sg:phone":"+1 209 726 4663",
    "sg:postcode":"95340",
    "sg:province":"CA",
    "wof:name":"Good Neighbor Realtors",
    "wof:placetype":"venue"
},
  "geometry": {"coordinates":[-120.469013,37.330253],"type":"Point"}
}