{
  "type": "Feature",
  "properties": {
    "iso:country":"US",
    "sg:address":"111 Nut Tree Rd",
    "sg:city":"Vacaville",
    "sg:classifiers":[
        {
            "category":"Home & Garden",
            "subcategory":"Home Furnishings",
            "type":"Retail Goods"
        }
    ],
    "sg:phone":"+1 707 453 0620",
    "sg:postcode":"95687",
    "sg:province":"CA",
    "sg:tags":[
        "housewares"
    ],
    "sg:website":"www.lecreuset.com",
    "wof:name":"Le Creuset Factory Outlet",
    "wof:placetype":"venue"
},
  "geometry": {"coordinates":[-121.956756,38.368668],"type":"Point"}
}