{
  "type": "Feature",
  "properties": {
    "iso:country":"US",
    "sg:address":"3534 Tweedy Boulevard",
    "sg:city":"South Gate",
    "sg:classifiers":[
        {
            "category":"Food & Beverages",
            "subcategory":"Groceries & Convenience Stores",
            "type":"Retail Goods"
        }
    ],
    "sg:phone":"+1 323 566 4149",
    "sg:postcode":"90280",
    "sg:province":"CA",
    "wof:name":"K Discount Store",
    "wof:placetype":"venue"
},
  "geometry": {"coordinates":[-118.206839,33.944218],"type":"Point"}
}