{
  "type": "Feature",
  "properties": {
    "iso:country":"US",
    "sg:address":"2741 Via De La Valle",
    "sg:city":"Del Mar",
    "sg:classifiers":[
        {
            "category":"Retail",
            "subcategory":"Laundry & Dry Cleaning",
            "type":"Services"
        }
    ],
    "sg:phone":"+1 858 755 4887",
    "sg:postcode":"92014",
    "sg:province":"CA",
    "wof:name":"Continental Cleaners",
    "wof:placetype":"venue"
},
  "geometry": {"coordinates":[-117.24900100000001,32.980999],"type":"Point"}
}