{
  "type": "Feature",
  "properties": {
    "addr:full":"1933 Sunset Ln Fullerton CA 92833",
    "addr:housenumber":"1933",
    "addr:postcode":"92833",
    "addr:street":"Sunset Ln",
    "iso:country":"US",
    "sg:address":"1933 Sunset Ln",
    "sg:city":"Fullerton",
    "sg:classifiers":[
        {
            "category":"Building & Trades",
            "subcategory":"Construction",
            "type":"Services"
        }
    ],
    "sg:phone":"+1 714 738 8027",
    "sg:postcode":"92833",
    "sg:province":"CA",
    "sg:tags":[
        "wallcoverings-installation",
        "wallpaper",
        "painting",
        "contractor"
    ],
    "wof:name":"Teds Painting",
    "wof:placetype":"venue"
},
  "geometry": {"coordinates":[-117.960707,33.892203],"type":"Point"}
}