{
  "type": "Feature",
  "properties": {
    "iso:country":"US",
    "sg:address":"3908 Ave Verano",
    "sg:city":"Thousand Oaks",
    "sg:classifiers":[
        {
            "category":"Real Estate",
            "subcategory":"Real Estate Agent",
            "type":"Services"
        }
    ],
    "sg:phone":"+1 805 523 7362",
    "sg:postcode":"91360",
    "sg:province":"CA",
    "sg:tags":[
        "investment"
    ],
    "wof:name":"Clark Investments",
    "wof:placetype":"venue"
},
  "geometry": {"coordinates":[-118.85480800000001,34.231405],"type":"Point"}
}