{
  "type": "Feature",
  "properties": {
    "addr:full":"119 Oak St Manteca CA 95337",
    "addr:housenumber":"119",
    "addr:postcode":"95337",
    "addr:street":"Oak St",
    "iso:country":"US",
    "sg:address":"119 Oak St",
    "sg:city":"Manteca",
    "sg:classifiers":[
        {
            "category":"Wholesale",
            "subcategory":"Groceries",
            "type":"Manufacturing & Wholesale Goods"
        }
    ],
    "sg:phone":"+1 209 825 7022",
    "sg:postcode":"95337",
    "sg:province":"CA",
    "sg:tags":[
        "food",
        "product",
        "health"
    ],
    "wof:name":"Nutritional Care Inc",
    "wof:placetype":"venue"
},
  "geometry": {"coordinates":[-121.217265,37.794909],"type":"Point"}
}