{
  "type": "Feature",
  "properties": {
    "iso:country":"US",
    "sg:address":"295 Boeing Ct",
    "sg:city":"Livermore",
    "sg:classifiers":[
        {
            "category":"Building & Trades",
            "subcategory":"Equipment Rental",
            "type":"Services"
        }
    ],
    "sg:phone":"+1 925 455 0872",
    "sg:postcode":"94551",
    "sg:province":"CA",
    "sg:tags":[
        "yard",
        "leasing",
        "store"
    ],
    "wof:name":"Dmj Leasing Inc",
    "wof:placetype":"venue"
},
  "geometry": {"coordinates":[-121.799269,37.690921],"type":"Point"}
}