{
  "type": "Feature",
  "properties": {
    "addr:full":"459 S Van Ness Avenue Los Angeles CA 90020",
    "addr:housenumber":"459",
    "addr:postcode":"90020",
    "addr:street":"S Van Ness Avenue",
    "iso:country":"US",
    "sg:address":"459 S Van Ness Avenue",
    "sg:city":"Los Angeles",
    "sg:classifiers":[
        {
            "category":"Building & Trades",
            "subcategory":"Locksmith",
            "type":"Services"
        }
    ],
    "sg:phone":"+1 213 252 0909",
    "sg:postcode":"90020",
    "sg:province":"CA",
    "sg:tags":[
        "key"
    ],
    "sg:website":"www.quick-locksmith.com",
    "wof:name":"A Quick Locksmith",
    "wof:placetype":"venue"
},
  "geometry": {"coordinates":[-118.31501400000001,34.066052],"type":"Point"}
}