{
  "type": "Feature",
  "properties": {
    "addr:full":"2730 Tioga Way Sacramento CA 95821",
    "addr:housenumber":"2730",
    "addr:postcode":"95821",
    "addr:street":"Tioga Way",
    "iso:country":"US",
    "sg:address":"2730 Tioga Way",
    "sg:city":"Sacramento",
    "sg:classifiers":[
        {
            "category":"Shopping",
            "type":"Retail Goods"
        }
    ],
    "sg:phone":"+1 916 482 8553",
    "sg:postcode":"95821",
    "sg:province":"CA",
    "sg:tags":[
        "art",
        "gallery",
        "dealer"
    ],
    "wof:name":"New Renaissance Art",
    "wof:placetype":"venue"
},
  "geometry": {"coordinates":[-121.398657,38.620382],"type":"Point"}
}