{
  "type": "Feature",
  "properties": {
    "iso:country":"US",
    "sg:address":"832 9th St",
    "sg:city":"Imperial Beach",
    "sg:classifiers":[
        {
            "category":"Professional",
            "subcategory":"Computer Services",
            "type":"Services"
        }
    ],
    "sg:phone":"+1 619 575 6075",
    "sg:postcode":"91932",
    "sg:province":"CA",
    "sg:tags":[
        "repair",
        "datum",
        "system",
        "communication"
    ],
    "sg:website":"www.aprojas.com",
    "wof:name":"A P Rojas Network Solutions",
    "wof:placetype":"venue"
},
  "geometry": {"coordinates":[-117.114462,32.581659],"type":"Point"}
}