{
  "type": "Feature",
  "properties": {
    "addr:full":"2812 Windsor Ln Modesto CA 95350",
    "addr:housenumber":"2812",
    "addr:postcode":"ca 95350",
    "addr:street":"Windsor Ln",
    "iso:country":"US",
    "sg:address":"2812 Windsor Ln",
    "sg:city":"Modesto",
    "sg:classifiers":[
        {
            "category":"Professional",
            "subcategory":"Business Services",
            "type":"Services"
        }
    ],
    "sg:phone":"+1 209 524 4871",
    "sg:postcode":"95350",
    "sg:province":"CA",
    "sg:tags":[
        "development"
    ],
    "wof:name":"Hatch Road Management Corp",
    "wof:placetype":"venue"
},
  "geometry": {"coordinates":[-120.983097,37.681572],"type":"Point"}
}