{
  "type": "Feature",
  "properties": {
    "iso:country":"US",
    "sg:address":"17075 Newhope St",
    "sg:city":"Fountain Valley",
    "sg:classifiers":[
        {
            "category":"Professional",
            "type":"Services"
        }
    ],
    "sg:phone":"+1 714 432 9289",
    "sg:postcode":"92708",
    "sg:province":"CA",
    "wof:name":"Artistic Porcelain",
    "wof:placetype":"venue"
},
  "geometry": {"coordinates":[-117.928495,33.714882],"type":"Point"}
}