{
  "type": "Feature",
  "properties": {
    "addr:full":"510 Natoma Station Dr Folsom CA 95630",
    "addr:housenumber":"510",
    "addr:postcode":"95630",
    "addr:street":"Natoma Station Dr",
    "iso:country":"US",
    "sg:address":"510 Natoma Station Dr",
    "sg:city":"Folsom",
    "sg:classifiers":[
        {
            "category":"Personal",
            "subcategory":"Beauty Salon",
            "type":"Services"
        }
    ],
    "sg:phone":"+1 916 355 8036",
    "sg:postcode":"95630",
    "sg:province":"CA",
    "sg:tags":[
        "manicuring"
    ],
    "wof:name":"Mood Nail Salon At Blue Ravine",
    "wof:placetype":"venue"
},
  "geometry": {"coordinates":[-121.182126,38.647789],"type":"Point"}
}