{
  "type": "Feature",
  "properties": {
    "addr:full":"2621 Pico Blvd Santa Monica CA 90405",
    "addr:housenumber":"2621",
    "addr:postcode":"90405",
    "addr:street":"Pico Blvd",
    "iso:country":"US",
    "sg:address":"2621 Pico Blvd",
    "sg:city":"Santa Monica",
    "sg:classifiers":[
        {
            "category":"Retail",
            "subcategory":"Auto Repair",
            "type":"Services"
        }
    ],
    "sg:phone":"+1 310 317 4447",
    "sg:postcode":"90405",
    "sg:province":"CA",
    "sg:tags":[
        "transmission"
    ],
    "wof:name":"AAMCO Transmissions",
    "wof:placetype":"venue"
},
  "geometry": {"coordinates":[-118.461654,34.023652],"type":"Point"}
}