{
  "type": "Feature",
  "properties": {
    "addr:full":"3632 Via Alicia Oceanside CA 92056",
    "addr:housenumber":"3632",
    "addr:postcode":"92056",
    "addr:street":"Via Alicia",
    "iso:country":"US",
    "sg:address":"3632 Via Alicia",
    "sg:city":"Oceanside",
    "sg:classifiers":[
        {
            "category":"Shopping",
            "subcategory":"Bicycles & Sporting Goods",
            "type":"Retail Goods"
        },
        {
            "category":"Wholesale",
            "subcategory":"Sporting Goods",
            "type":"Manufacturing & Wholesale Goods"
        }
    ],
    "sg:phone":"+1 760 631 8222",
    "sg:postcode":"92056",
    "sg:province":"CA",
    "sg:tags":[
        "equipment",
        "manufacturer",
        "golf",
        "supplies-wholesale",
        "supply"
    ],
    "wof:name":"Mark Ziminsky Sales",
    "wof:placetype":"venue"
},
  "geometry": {"coordinates":[-117.254554,33.16712],"type":"Point"}
}