{
  "type": "Feature",
  "properties": {
    "addr:full":"2705 N Grand Ave Santa Ana CA 92701",
    "addr:housenumber":"2705",
    "addr:postcode":"92701",
    "addr:street":"N Grand Ave",
    "iso:country":"US",
    "sg:address":"2705 N Grand Ave",
    "sg:city":"Santa Ana",
    "sg:classifiers":[
        {
            "category":"Personal",
            "subcategory":"Barber",
            "type":"Services"
        }
    ],
    "sg:phone":"+1 714 744 1665",
    "sg:postcode":"92701",
    "sg:province":"CA",
    "sg:website":"www.number1barbershop.com",
    "wof:name":"Number 1 Barber Shop",
    "wof:placetype":"venue"
},
  "geometry": {"coordinates":[-117.852918,33.773599],"type":"Point"}
}