{
  "type": "Feature",
  "properties": {
    "iso:country":"US",
    "sg:address":"1200 Fair Oaks Ave",
    "sg:city":"South Pasadena",
    "sg:classifiers":[
        {
            "category":"Autos & Motor Vehicles",
            "subcategory":"Fuel & Gas Station",
            "type":"Retail Goods"
        }
    ],
    "sg:phone":"+1 626 799 8342",
    "sg:postcode":"91030",
    "sg:province":"CA",
    "sg:website":"www.chevron.com",
    "wof:name":"Fry's South Pasadena Chevron",
    "wof:placetype":"venue"
},
  "geometry": {"coordinates":[-118.150002,34.112202],"type":"Point"}
}