{
  "type": "Feature",
  "properties": {
    "addr:full":"7225 Redbank Rd Bakersfield CA 93307",
    "addr:housenumber":"7225",
    "addr:postcode":"93307",
    "addr:street":"Redbank Rd",
    "iso:country":"US",
    "sg:address":"7225 Redbank Rd",
    "sg:city":"Bakersfield",
    "sg:classifiers":[
        {
            "category":"Professional",
            "subcategory":"Management & Consulting",
            "type":"Services"
        }
    ],
    "sg:phone":"+1 661 366 1528",
    "sg:postcode":"93307",
    "sg:province":"CA",
    "sg:tags":[
        "party",
        "planning"
    ],
    "wof:name":"Countryside Pony Ranch",
    "wof:placetype":"venue"
},
  "geometry": {"coordinates":[-118.92309299999999,35.339711],"type":"Point"}
}