{
  "type": "Feature",
  "properties": {
    "iso:country":"US",
    "sg:address":"2901 Japonica Way",
    "sg:city":"Modesto",
    "sg:classifiers":[
        {
            "category":"Building & Trades",
            "subcategory":"Construction",
            "type":"Services"
        }
    ],
    "sg:phone":"+1 209 577 6676",
    "sg:postcode":"95354",
    "sg:province":"CA",
    "sg:tags":[
        "coping",
        "plastering",
        "tiling",
        "pool",
        "swimming"
    ],
    "wof:name":"Alpha Aquatics Pool & Spa",
    "wof:placetype":"venue"
},
  "geometry": {"coordinates":[-120.941217,37.640703],"type":"Point"}
}