{
  "type": "Feature",
  "properties": {
    "addr:full":"644 E Regent Street Inglewood CA 90301",
    "addr:housenumber":"644",
    "addr:postcode":"90301",
    "addr:street":"E Regent Street",
    "iso:country":"US",
    "sg:address":"644 E Regent Street",
    "sg:city":"Inglewood",
    "sg:classifiers":[
        {
            "category":"Health Services",
            "subcategory":"Doctor",
            "type":"Services"
        }
    ],
    "sg:phone":"+1 310 671 0488",
    "sg:postcode":"90301",
    "sg:province":"CA",
    "wof:name":"Allard Jean R MD Phys",
    "wof:placetype":"venue"
},
  "geometry": {"coordinates":[-118.345129,33.964509],"type":"Point"}
}