{
  "type": "Feature",
  "properties": {
    "iso:country":"US",
    "sg:address":"2115 S Blosser Rd",
    "sg:city":"Santa Maria",
    "sg:classifiers":[
        {
            "category":"Professional",
            "subcategory":"Business Services",
            "type":"Services"
        }
    ],
    "sg:phone":"+1 805 922 7258",
    "sg:postcode":"93458",
    "sg:province":"CA",
    "sg:tags":[
        "embroidery"
    ],
    "wof:name":"Express 4 Less",
    "wof:placetype":"venue"
},
  "geometry": {"coordinates":[-120.453935,34.922026],"type":"Point"}
}