{
  "type": "Feature",
  "properties": {
    "addr:full":"12800 Garden Grove Blvd Garden Grove CA 92843",
    "addr:housenumber":"12800",
    "addr:postcode":"92843",
    "addr:street":"Garden Grove Blvd",
    "iso:country":"US",
    "sg:address":"12800 Garden Grove Blvd",
    "sg:city":"Garden Grove",
    "sg:classifiers":[
        {
            "category":"Health Services",
            "subcategory":"Chiropractor",
            "type":"Services"
        }
    ],
    "sg:phone":"+1 714 636 2060",
    "sg:postcode":"92843",
    "sg:province":"CA",
    "wof:name":"Eledge Family Chiropractic",
    "wof:placetype":"venue"
},
  "geometry": {"coordinates":[-117.906121,33.774433],"type":"Point"}
}