{
  "type": "Feature",
  "properties": {
    "addr:full":"5511 E Las Lomas St Long Beach CA 90815",
    "addr:housenumber":"5511",
    "addr:postcode":"90815",
    "addr:street":"E Las Lomas St",
    "iso:country":"US",
    "sg:address":"5511 E Las Lomas St",
    "sg:city":"Long Beach",
    "sg:classifiers":[
        {
            "category":"Insurance",
            "subcategory":"Insurance Agent",
            "type":"Services"
        }
    ],
    "sg:phone":"+1 562 425 5020",
    "sg:postcode":"90815",
    "sg:province":"CA",
    "wof:name":"Blue Cross & Blue Shield",
    "wof:placetype":"venue"
},
  "geometry": {"coordinates":[-118.126515,33.783654],"type":"Point"}
}