{
  "type": "Feature",
  "properties": {
    "addr:full":"10250 Tembladera St Castroville CA 95012",
    "addr:housenumber":"10250",
    "addr:postcode":"95012",
    "addr:street":"Tembladera St",
    "iso:country":"US",
    "sg:address":"10250 Tembladera St",
    "sg:city":"Castroville",
    "sg:classifiers":[
        {
            "category":"Manufacturing",
            "subcategory":"Building Materials",
            "type":"Manufacturing & Wholesale Goods"
        }
    ],
    "sg:phone":"+1 831 633 4600",
    "sg:postcode":"95012",
    "sg:province":"CA",
    "sg:tags":[
        "cabinetmakers-commercial",
        "industrial"
    ],
    "wof:name":"Duarte Woodworks",
    "wof:placetype":"venue"
},
  "geometry": {"coordinates":[-121.76333200000001,36.768895],"type":"Point"}
}