{
  "type": "Feature",
  "properties": {
    "iso:country":"US",
    "sg:address":"4535 N Bendel Ave",
    "sg:city":"Fresno",
    "sg:classifiers":[
        {
            "category":"Wholesale",
            "subcategory":"Machinery & Supplies",
            "type":"Manufacturing & Wholesale Goods"
        }
    ],
    "sg:phone":"+1 559 276 8256",
    "sg:postcode":"93722",
    "sg:province":"CA",
    "sg:tags":[
        "car wash",
        "washing",
        "equipment",
        "vehicle",
        "polishing"
    ],
    "sg:website":"http://www.roscarwashsystems.com",
    "wof:name":"Richard Oakes & Son Inc",
    "wof:placetype":"venue"
},
  "geometry": {"coordinates":[-119.870323,36.803749],"type":"Point"}
}