{
  "type": "Feature",
  "properties": {
    "iso:country":"US",
    "sg:address":"20745 Nordhoff St",
    "sg:city":"Chatsworth",
    "sg:classifiers":[
        {
            "category":"Organizations",
            "subcategory":"Religious Organization",
            "type":"Services"
        }
    ],
    "sg:phone":"+1 818 718 6220",
    "sg:postcode":"91311",
    "sg:province":"CA",
    "sg:tags":[
        "church"
    ],
    "sg:website":"www.thegarden.cc",
    "wof:name":"Garden Christian Fellowship",
    "wof:placetype":"venue"
},
  "geometry": {"coordinates":[-118.581733,34.232731],"type":"Point"}
}