{
  "type": "Feature",
  "properties": {
    "addr:full":"4552 Whittier Blvd Los Angeles CA 90022",
    "addr:housenumber":"4552",
    "addr:postcode":"90022",
    "addr:street":"Whittier Blvd",
    "iso:country":"US",
    "sg:address":"4552 Whittier Blvd",
    "sg:city":"Los Angeles",
    "sg:classifiers":[
        {
            "category":"Home & Garden",
            "subcategory":"Furniture",
            "type":"Retail Goods"
        }
    ],
    "sg:phone":"+1 323 261 1136",
    "sg:postcode":"90022",
    "sg:province":"CA",
    "sg:tags":[
        "store"
    ],
    "sg:website":"www.WengerFurniture.com",
    "wof:name":"Wenger Furniture & Appliances",
    "wof:placetype":"venue"
},
  "geometry": {"coordinates":[-118.16922099999999,34.022899],"type":"Point"}
}