{
  "type": "Feature",
  "properties": {
    "iso:country":"US",
    "sg:address":"1119 R St",
    "sg:city":"Sacramento",
    "sg:classifiers":[
        {
            "category":"Manufacturing",
            "subcategory":"Tools & Machinery",
            "type":"Manufacturing & Wholesale Goods"
        },
        {
            "category":"Wholesale",
            "subcategory":"Electrical",
            "type":"Manufacturing & Wholesale Goods"
        }
    ],
    "sg:phone":"+1 916 444 7915",
    "sg:postcode":"95811",
    "sg:province":"CA",
    "sg:tags":[
        "equipment",
        "manufacturer",
        "supplies-wholesale",
        "electric",
        "supply"
    ],
    "sg:website":"http://www.hilineelectric.com",
    "wof:name":"Hi-Line Electric Co",
    "wof:placetype":"venue"
},
  "geometry": {"coordinates":[-121.49572499999999,38.571074],"type":"Point"}
}