{
  "type": "Feature",
  "properties": {
    "addr:full":"4637 E Chapman Ave Orange CA 92869",
    "addr:housenumber":"4637",
    "addr:postcode":"92869",
    "addr:street":"E Chapman Ave",
    "iso:country":"US",
    "sg:address":"4637 E Chapman Ave",
    "sg:city":"Orange",
    "sg:classifiers":[
        {
            "category":"Food & Beverages",
            "subcategory":"Ethnic Foods",
            "type":"Retail Goods"
        },
        {
            "category":"Food & Beverages",
            "subcategory":"Groceries & Convenience Stores",
            "type":"Retail Goods"
        }
    ],
    "sg:phone":"+1 714 771 1595",
    "sg:postcode":"92869",
    "sg:province":"CA",
    "wof:name":"La Carreta",
    "wof:placetype":"venue"
},
  "geometry": {"coordinates":[-117.80450399999999,33.788218],"type":"Point"}
}