{
  "type": "Feature",
  "properties": {
    "iso:country":"US",
    "sg:address":"3110 E Miraloma Ave",
    "sg:city":"Anaheim",
    "sg:classifiers":[
        {
            "category":"Wholesale",
            "subcategory":"Non-durable Goods",
            "type":"Manufacturing & Wholesale Goods"
        }
    ],
    "sg:phone":"+1 714 765 7599",
    "sg:postcode":"92806",
    "sg:province":"CA",
    "sg:tags":[
        "bag",
        "canvas",
        "cotton"
    ],
    "wof:name":"Acme Bag Co",
    "wof:placetype":"venue"
},
  "geometry": {"coordinates":[-117.858831,33.858234],"type":"Point"}
}