{
  "type": "Feature",
  "properties": {
    "addr:full":"936 Foothill Blvd San Luis Obispo CA 93405",
    "addr:housenumber":"936",
    "addr:postcode":"93405",
    "addr:street":"Foothill Blvd",
    "iso:country":"US",
    "sg:address":"936 Foothill Blvd",
    "sg:city":"San Luis Obispo",
    "sg:classifiers":[
        {
            "category":"Building & Trades",
            "subcategory":"Landscaping Services",
            "type":"Services"
        }
    ],
    "sg:phone":"+1 805 544 6697",
    "sg:postcode":"93405",
    "sg:province":"CA",
    "sg:tags":[
        "landscape",
        "contractor"
    ],
    "wof:name":"Larry Cusick Landscape Mgmt",
    "wof:placetype":"venue"
},
  "geometry": {"coordinates":[-120.669042,35.294122],"type":"Point"}
}