{
  "type": "Feature",
  "properties": {
    "addr:full":"7255 Joshua Ln Yucca Valley CA 92284",
    "addr:housenumber":"7255",
    "addr:postcode":"92284",
    "addr:street":"Joshua Ln",
    "iso:country":"US",
    "sg:address":"7255 Joshua Ln",
    "sg:city":"Yucca Valley",
    "sg:classifiers":[
        {
            "category":"Health Services",
            "subcategory":"Doctor",
            "type":"Services"
        }
    ],
    "sg:phone":"+1 760 365 8331",
    "sg:postcode":"92284",
    "sg:province":"CA",
    "sg:tags":[
        "dentist"
    ],
    "wof:name":"Joshua Lane Dental",
    "wof:placetype":"venue"
},
  "geometry": {"coordinates":[-116.414765,34.121441],"type":"Point"}
}