{
  "type": "Feature",
  "properties": {
    "addr:full":"1071 E Champlain Dr Fresno CA 93720",
    "addr:housenumber":"1071",
    "addr:postcode":"93720",
    "addr:street":"E Champlain Dr",
    "iso:country":"US",
    "sg:address":"1071 E Champlain Dr",
    "sg:city":"Fresno",
    "sg:classifiers":[
        {
            "category":"Retail",
            "subcategory":"Laundry & Dry Cleaning",
            "type":"Services"
        }
    ],
    "sg:phone":"+1 559 433 9620",
    "sg:postcode":"93720",
    "sg:province":"CA",
    "sg:tags":[
        "cleaners"
    ],
    "wof:name":"One Hour Martinizing",
    "wof:placetype":"venue"
},
  "geometry": {"coordinates":[-119.76546500000001,36.872782],"type":"Point"}
}