{
  "type": "Feature",
  "properties": {
    "addr:full":"27652 Crown Valley Parkway Mission Viejo CA 92691",
    "addr:housenumber":"27652",
    "addr:postcode":"92691",
    "addr:street":"Crown Valley Parkway",
    "iso:country":"US",
    "sg:address":"27652 Crown Valley Parkway",
    "sg:city":"Mission Viejo",
    "sg:classifiers":[
        {
            "category":"Health Services",
            "subcategory":"Chiropractor",
            "type":"Services"
        }
    ],
    "sg:phone":"+1 949 364 1901",
    "sg:postcode":"92691",
    "sg:province":"CA",
    "wof:name":"Crown Valley Chiro Care",
    "wof:placetype":"venue"
},
  "geometry": {"coordinates":[-117.670873,33.560443],"type":"Point"}
}