{
  "type": "Feature",
  "properties": {
    "addr:full":"10019 Brookline Woods Dr Bakersfield CA 93312",
    "addr:housenumber":"10019",
    "addr:postcode":"93312",
    "addr:street":"Brookline Woods Dr",
    "iso:country":"US",
    "sg:address":"10019 Brookline Woods Dr",
    "sg:city":"Bakersfield",
    "sg:classifiers":[
        {
            "category":"Freight",
            "type":"Transportation"
        },
        {
            "category":"Local Transit",
            "type":"Transportation"
        }
    ],
    "sg:phone":"+1 661 587 1041",
    "sg:postcode":"93312",
    "sg:province":"CA",
    "sg:tags":[
        "public",
        "trucking"
    ],
    "wof:name":"Global Express",
    "wof:placetype":"venue"
},
  "geometry": {"coordinates":[-119.113426,35.366612],"type":"Point"}
}