{
  "type": "Feature",
  "properties": {
    "iso:country":"US",
    "sg:address":"4222 Suzanne Dr",
    "sg:city":"Palo Alto",
    "sg:classifiers":[
        {
            "category":"Shopping",
            "subcategory":"Hobbies, Toys, & Games",
            "type":"Retail Goods"
        }
    ],
    "sg:phone":"+1 650 856 6054",
    "sg:postcode":"94306",
    "sg:province":"CA",
    "wof:name":"Model Steam",
    "wof:placetype":"venue"
},
  "geometry": {"coordinates":[-122.123137,37.40596],"type":"Point"}
}