{
  "type": "Feature",
  "properties": {
    "iso:country":"US",
    "sg:address":"11916 Long Beach Blvd",
    "sg:city":"Lynwood",
    "sg:classifiers":[
        {
            "category":"Shopping",
            "subcategory":"Gifts & Souvenirs",
            "type":"Retail Goods"
        }
    ],
    "sg:phone":"+1 310 638 0965",
    "sg:postcode":"90262",
    "sg:province":"CA",
    "sg:tags":[
        "party",
        "supply"
    ],
    "wof:name":"Jesus Malverde Party Supply",
    "wof:placetype":"venue"
},
  "geometry": {"coordinates":[-118.20932999999999,33.919324],"type":"Point"}
}