{
  "type": "Feature",
  "properties": {
    "addr:full":"5675 Mother Lode Dr Placerville CA 95667",
    "addr:housenumber":"5675",
    "addr:postcode":"95667",
    "addr:street":"Mother Lode Dr",
    "iso:country":"US",
    "sg:address":"5675 Mother Lode Dr",
    "sg:city":"Placerville",
    "sg:classifiers":[
        {
            "category":"Professional",
            "subcategory":"Business Services",
            "type":"Services"
        }
    ],
    "sg:phone":"+1 530 626 9977",
    "sg:postcode":"95667",
    "sg:province":"CA",
    "sg:tags":[
        "drafting"
    ],
    "wof:name":"Apple Hill-Homes",
    "wof:placetype":"venue"
},
  "geometry": {"coordinates":[-120.87042,38.679788],"type":"Point"}
}