{
  "type": "Feature",
  "properties": {
    "addr:full":"10660 Western Ave Stanton CA 90680",
    "addr:housenumber":"10660",
    "addr:postcode":"ca 90680",
    "addr:street":"Western Ave",
    "iso:country":"US",
    "sg:address":"10660 Western Ave",
    "sg:city":"Stanton",
    "sg:classifiers":[
        {
            "category":"Organizations",
            "subcategory":"Religious Organization",
            "type":"Services"
        }
    ],
    "sg:phone":"+1 714 484 8010",
    "sg:postcode":"90680",
    "sg:province":"CA",
    "sg:tags":[
        "church"
    ],
    "wof:name":"America Full Gospel Church",
    "wof:placetype":"venue"
},
  "geometry": {"coordinates":[-118.00190499999999,33.807853],"type":"Point"}
}