{
  "type": "Feature",
  "properties": {
    "iso:country":"US",
    "sg:address":"3165 De La Cruz Blvd",
    "sg:city":"Santa Clara",
    "sg:classifiers":[
        {
            "category":"Retail",
            "subcategory":"Laundry & Dry Cleaning",
            "type":"Services"
        }
    ],
    "sg:phone":"+1 408 988 3333",
    "sg:postcode":"95054",
    "sg:province":"CA",
    "wof:name":"United Cleaners Supply Llc",
    "wof:placetype":"venue"
},
  "geometry": {"coordinates":[-121.940128,37.380366],"type":"Point"}
}