{
  "type": "Feature",
  "properties": {
    "iso:country":"US",
    "sg:address":"6273 Nicolaus Rd",
    "sg:city":"Lincoln",
    "sg:phone":"+1 916 645 7456",
    "sg:postcode":"95648",
    "sg:province":"CA",
    "sg:tags":[
        "farm",
        "rice"
    ],
    "wof:name":"Stutz Farming",
    "wof:placetype":"venue"
},
  "geometry": {"coordinates":[-121.401382,38.897167],"type":"Point"}
}