{
  "type": "Feature",
  "properties": {
    "iso:country":"US",
    "sg:address":"1015 El Camino Real",
    "sg:city":"South San Francisco",
    "sg:classifiers":[
        {
            "category":"Food & Beverages",
            "subcategory":"Groceries & Convenience Stores",
            "type":"Retail Goods"
        }
    ],
    "sg:phone":"+1 650 616 1918",
    "sg:postcode":"94080",
    "sg:province":"CA",
    "wof:name":"Pacific Supermarket",
    "wof:placetype":"venue"
},
  "geometry": {"coordinates":[-122.435545,37.65501],"type":"Point"}
}