{
  "type": "Feature",
  "properties": {
    "iso:country":"US",
    "sg:address":"5649 E Corso Di Napoli",
    "sg:city":"Long Beach",
    "sg:classifiers":[
        {
            "category":"Professional",
            "type":"Services"
        }
    ],
    "sg:phone":"+1 562 439 6268",
    "sg:postcode":"90803",
    "sg:province":"CA",
    "wof:name":"Gilbert & Bertha Saarloos",
    "wof:placetype":"venue"
},
  "geometry": {"coordinates":[-118.124804,33.752564],"type":"Point"}
}