{
  "type": "Feature",
  "properties": {
    "iso:country":"US",
    "sg:address":"3259 California Blvd",
    "sg:city":"Napa",
    "sg:classifiers":[
        {
            "category":"Wholesale",
            "subcategory":"Non-durable Goods",
            "type":"Manufacturing & Wholesale Goods"
        },
        {
            "category":"Home & Garden",
            "subcategory":"Hardware",
            "type":"Retail Goods"
        },
        {
            "category":"Home & Garden",
            "subcategory":"Carpets & Floor Coverings",
            "type":"Retail Goods"
        }
    ],
    "sg:phone":"+1 707 252 6233",
    "sg:postcode":"94558",
    "sg:province":"CA",
    "sg:tags":[
        "supply",
        "supplies-wholesale",
        "machine",
        "equipment",
        "janitor",
        "manufacturer"
    ],
    "wof:name":"Vintage Janitorial Supplies",
    "wof:placetype":"venue"
},
  "geometry": {"coordinates":[-122.306534,38.318932],"type":"Point"}
}