{
  "type": "Feature",
  "properties": {
    "addr:full":"800 W San Carlos St San Jose CA 95110",
    "addr:housenumber":"800",
    "addr:postcode":"95110",
    "addr:street":"W San Carlos St",
    "iso:country":"US",
    "sg:address":"800 W San Carlos St",
    "sg:city":"San Jose",
    "sg:classifiers":[
        {
            "category":"Freight",
            "type":"Transportation"
        },
        {
            "category":"Building & Trades",
            "subcategory":"Equipment Rental",
            "type":"Services"
        }
    ],
    "sg:phone":"+1 408 297 4442",
    "sg:postcode":"95110",
    "sg:province":"CA",
    "sg:tags":[
        "general",
        "contractor"
    ],
    "wof:name":"Hertz Equipment Rental Inc",
    "wof:placetype":"venue"
},
  "geometry": {"coordinates":[-121.90499199999999,37.323772],"type":"Point"}
}