{
  "type": "Feature",
  "properties": {
    "addr:full":"543 Andover St San Francisco CA 94110",
    "addr:housenumber":"543",
    "addr:postcode":"94110",
    "addr:street":"Andover St",
    "iso:country":"US",
    "sg:address":"543 Andover St",
    "sg:city":"San Francisco",
    "sg:classifiers":[
        {
            "category":"Professional",
            "subcategory":"Management & Consulting",
            "type":"Services"
        }
    ],
    "sg:phone":"+1 415 648 7193",
    "sg:postcode":"94110",
    "sg:province":"CA",
    "sg:tags":[
        "consultant"
    ],
    "wof:name":"Stan Reynolds Consulting",
    "wof:placetype":"venue"
},
  "geometry": {"coordinates":[-122.416594,37.736689],"type":"Point"}
}