{
  "type": "Feature",
  "properties": {
    "iso:country":"US",
    "sg:address":"835 W Chapman Ave",
    "sg:city":"Orange",
    "sg:classifiers":[
        {
            "category":"Food & Beverages",
            "subcategory":"Liquor & Beverages",
            "type":"Retail Goods"
        }
    ],
    "sg:phone":"+1 714 538 1231",
    "sg:postcode":"92868",
    "sg:province":"CA",
    "sg:tags":[
        "beer",
        "spirit",
        "wine"
    ],
    "wof:name":"Royal Market Liquor",
    "wof:placetype":"venue"
},
  "geometry": {"coordinates":[-117.861,33.7878],"type":"Point"}
}