{
  "type": "Feature",
  "properties": {
    "iso:country":"US",
    "sg:address":"2107 E Palmdale Blvd",
    "sg:city":"Palmdale",
    "sg:classifiers":[
        {
            "category":"Shopping",
            "subcategory":"Used Merchandise",
            "type":"Retail Goods"
        }
    ],
    "sg:phone":"+1 661 267 1331",
    "sg:postcode":"93550",
    "sg:province":"CA",
    "sg:tags":[
        "antique"
    ],
    "wof:name":"Little House",
    "wof:placetype":"venue"
},
  "geometry": {"coordinates":[-118.091718,34.580167],"type":"Point"}
}