{
  "type": "Feature",
  "properties": {
    "addr:full":"317 5th St Eureka CA 95501",
    "addr:housenumber":"317",
    "addr:postcode":"95501",
    "addr:street":"5Th St",
    "iso:country":"US",
    "sg:address":"317 5th St",
    "sg:city":"Eureka",
    "sg:classifiers":[
        {
            "category":"Restaurant",
            "type":"Food & Drink"
        }
    ],
    "sg:phone":"+1 707 443 3373",
    "sg:postcode":"95501",
    "sg:province":"CA",
    "wof:name":"Amigas Burritos",
    "wof:placetype":"venue"
},
  "geometry": {"coordinates":[-124.16715499999999,40.801801],"type":"Point"}
}