{
  "type": "Feature",
  "properties": {
    "iso:country":"US",
    "sg:address":"1450 S Bundy Dr",
    "sg:city":"Los Angeles",
    "sg:classifiers":[
        {
            "category":"Retail",
            "subcategory":"Auto Repair",
            "type":"Services"
        }
    ],
    "sg:phone":"+1 310 826 7221",
    "sg:postcode":"90025",
    "sg:province":"CA",
    "sg:tags":[
        "transmission"
    ],
    "wof:name":"AAMCO Transmissions",
    "wof:placetype":"venue"
},
  "geometry": {"coordinates":[-118.46398000000001,34.041351],"type":"Point"}
}