{
  "type": "Feature",
  "properties": {
    "iso:country":"US",
    "sg:address":"15581 Toyon Drive",
    "sg:city":"Los Gatos",
    "sg:classifiers":[
        {
            "category":"Banks & Credit Unions",
            "subcategory":"Investment Brokerage",
            "type":"Services"
        }
    ],
    "sg:phone":"+1 408 354 9408",
    "sg:postcode":"95030",
    "sg:province":"CA",
    "sg:tags":[
        "investing"
    ],
    "wof:name":"Raisch Investment Group Ltd",
    "wof:placetype":"venue"
},
  "geometry": {"coordinates":[-121.994788,37.24122],"type":"Point"}
}