{
  "type": "Feature",
  "properties": {
    "iso:country":"US",
    "sg:address":"39 Stillman St",
    "sg:city":"San Francisco",
    "sg:classifiers":[
        {
            "category":"Professional",
            "subcategory":"Engineering",
            "type":"Services"
        }
    ],
    "sg:phone":"+1 415 284 9662",
    "sg:postcode":"94107",
    "sg:province":"CA",
    "sg:tags":[
        "engineer"
    ],
    "sg:website":"www.sharechive.com",
    "wof:name":"Share Chive Co",
    "wof:placetype":"venue"
},
  "geometry": {"coordinates":[-122.395644,37.782376],"type":"Point"}
}