{
  "type": "Feature",
  "properties": {
    "addr:full":"735 Market St San Francisco CA 94103",
    "addr:housenumber":"735",
    "addr:postcode":"94103",
    "addr:street":"Market St",
    "iso:country":"US",
    "sg:address":"735 Market St",
    "sg:city":"San Francisco",
    "sg:classifiers":[
        {
            "category":"Shopping",
            "subcategory":"Bicycles & Sporting Goods",
            "type":"Retail Goods"
        },
        {
            "category":"Sports & Exercise",
            "subcategory":"Golf",
            "type":"Entertainment"
        }
    ],
    "sg:phone":"+1 415 974 6979",
    "sg:postcode":"94103",
    "sg:province":"CA",
    "sg:website":"www.golfsmith.com/",
    "wof:name":"Golfsmith",
    "wof:placetype":"venue"
},
  "geometry": {"coordinates":[-122.40409200000001,37.786558],"type":"Point"}
}