{
  "type": "Feature",
  "properties": {
    "addr:full":"11380 Twin Cities Rd Galt CA 95632",
    "addr:housenumber":"11380",
    "addr:postcode":"95632",
    "addr:street":"Twin Cities Rd",
    "iso:country":"US",
    "sg:address":"11380 Twin Cities Rd",
    "sg:city":"Galt",
    "sg:classifiers":[
        {
            "category":"Building & Trades",
            "subcategory":"Construction",
            "type":"Services"
        }
    ],
    "sg:phone":"+1 209 748 2560",
    "sg:postcode":"95632",
    "sg:province":"CA",
    "sg:tags":[
        "maintenance",
        "contractor"
    ],
    "wof:name":"Genesis Fab",
    "wof:placetype":"venue"
},
  "geometry": {"coordinates":[-121.25761199999999,38.29178],"type":"Point"}
}