{
  "type": "Feature",
  "properties": {
    "addr:full":"3951 Alemany Boulevard San Francisco CA 94132",
    "addr:housenumber":"3951",
    "addr:postcode":"94132",
    "addr:street":"Alemany Boulevard",
    "iso:country":"US",
    "sg:address":"3951 Alemany Boulevard",
    "sg:city":"San Francisco",
    "sg:classifiers":[
        {
            "category":"Banks & Credit Unions",
            "subcategory":"Bank",
            "type":"Services"
        }
    ],
    "sg:phone":"+1 650 991 3275",
    "sg:postcode":"94132",
    "sg:province":"CA",
    "wof:name":"Sterling Bank and Trust",
    "wof:placetype":"venue"
},
  "geometry": {"coordinates":[-122.4687,37.710691],"type":"Point"}
}