{
  "type": "Feature",
  "properties": {
    "iso:country":"US",
    "sg:address":"4115 E 7th St Ste A",
    "sg:city":"Long Beach",
    "sg:classifiers":[
        {
            "category":"Personal",
            "type":"Services"
        },
        {
            "category":"Shopping",
            "subcategory":"Bridal",
            "type":"Retail Goods"
        }
    ],
    "sg:phone":"+1 562 438 5722",
    "sg:postcode":"90804",
    "sg:province":"CA",
    "sg:tags":[
        "sewing",
        "alteration"
    ],
    "wof:name":"Marta's Tailor Shop",
    "wof:placetype":"venue"
},
  "geometry": {"coordinates":[-118.143997,33.775398],"type":"Point"}
}