{
  "type": "Feature",
  "properties": {
    "iso:country":"US",
    "sg:address":"9201 W Sunset Boulevard",
    "sg:city":"West Hollywood",
    "sg:classifiers":[
        {
            "category":"Health Services",
            "subcategory":"Doctor",
            "type":"Services"
        }
    ],
    "sg:phone":"+1 310 550 0666",
    "sg:postcode":"90069",
    "sg:province":"CA",
    "sg:tags":[
        "dermatologist"
    ],
    "wof:name":"Danesh Sid MD",
    "wof:placetype":"venue"
},
  "geometry": {"coordinates":[-118.392302,34.090542],"type":"Point"}
}