{
  "type": "Feature",
  "properties": {
    "iso:country":"US",
    "sg:address":"575 5th St W",
    "sg:city":"Sonoma",
    "sg:classifiers":[
        {
            "category":"Shopping",
            "subcategory":"Bicycles & Sporting Goods",
            "type":"Retail Goods"
        }
    ],
    "sg:phone":"+1 707 938 5939",
    "sg:postcode":"95476",
    "sg:province":"CA",
    "sg:tags":[
        "saddlery",
        "harness"
    ],
    "wof:name":"Plush Seat Bottoms-Sonoma Sdle",
    "wof:placetype":"venue"
},
  "geometry": {"coordinates":[-122.468222,38.292212],"type":"Point"}
}