{
  "type": "Feature",
  "properties": {
    "addr:full":"1093 Airport Rd Imperial CA 92251",
    "addr:housenumber":"1093",
    "addr:postcode":"92251",
    "addr:street":"Airport Rd",
    "iso:country":"US",
    "sg:address":"1093 Airport Rd",
    "sg:city":"Imperial",
    "sg:classifiers":[
        {
            "category":"Travel",
            "subcategory":"Hotels & Motels",
            "type":"Entertainment"
        }
    ],
    "sg:phone":"+1 760 355 4500",
    "sg:postcode":"92251",
    "sg:province":"CA",
    "wof:name":"Imperial Valley Inn-Best Wstrn",
    "wof:placetype":"venue"
},
  "geometry": {"coordinates":[-115.571141,32.837971],"type":"Point"}
}