{
  "type": "Feature",
  "properties": {
    "iso:country":"US",
    "sg:address":"4075 Riverview Dr",
    "sg:city":"Riverside",
    "sg:classifiers":[
        {
            "category":"Wholesale",
            "subcategory":"Electrical",
            "type":"Manufacturing & Wholesale Goods"
        }
    ],
    "sg:phone":"+1 951 684 2639",
    "sg:postcode":"92509",
    "sg:province":"CA",
    "sg:tags":[
        "electric",
        "motor"
    ],
    "wof:name":"Electric Motor Industries",
    "wof:placetype":"venue"
},
  "geometry": {"coordinates":[-117.41395799999999,33.99874],"type":"Point"}
}