{
  "type": "Feature",
  "properties": {
    "addr:full":"1352 Lighthouse Ave Pacific Grove CA 93950",
    "addr:housenumber":"1352",
    "addr:postcode":"93950",
    "addr:street":"Lighthouse Ave",
    "iso:country":"US",
    "sg:address":"1352 Lighthouse Ave",
    "sg:city":"Pacific Grove",
    "sg:classifiers":[
        {
            "category":"Government",
            "subcategory":"Office",
            "type":"Public Place"
        }
    ],
    "sg:phone":"+1 831 648 8515",
    "sg:postcode":"93950",
    "sg:province":"CA",
    "wof:name":"Us Fisheries & Marine Life",
    "wof:placetype":"venue"
},
  "geometry": {"coordinates":[-121.934974,36.631562],"type":"Point"}
}