{
  "type": "Feature",
  "properties": {
    "addr:full":"690 S Fairview Ave Goleta CA 93117",
    "addr:housenumber":"690",
    "addr:postcode":"93117",
    "addr:street":"S Fairview Ave",
    "iso:country":"US",
    "sg:address":"690 S Fairview Ave",
    "sg:city":"Goleta",
    "sg:classifiers":[
        {
            "category":"Retail",
            "subcategory":"Auto Rental",
            "type":"Services"
        }
    ],
    "sg:phone":"+1 805 967 9489",
    "sg:postcode":"93117",
    "sg:province":"CA",
    "sg:tags":[
        "renting",
        "automobile"
    ],
    "wof:name":"Hertz Rent A Car",
    "wof:placetype":"venue"
},
  "geometry": {"coordinates":[-119.830534,34.426462],"type":"Point"}
}