{
  "type": "Feature",
  "properties": {
    "iso:country":"US",
    "sg:address":"731 S Fortuna Blvd",
    "sg:city":"Fortuna",
    "sg:classifiers":[
        {
            "category":"Personal",
            "subcategory":"Beauty Salon",
            "type":"Services"
        }
    ],
    "sg:phone":"+1 707 725 6266",
    "sg:postcode":"95540",
    "sg:province":"CA",
    "sg:tags":[
        "salons-equipment",
        "supply"
    ],
    "wof:name":"California Cuts",
    "wof:placetype":"venue"
},
  "geometry": {"coordinates":[-124.14666699999999,40.584067],"type":"Point"}
}