{
  "type": "Feature",
  "properties": {
    "addr:full":"22359 Birds Eye Dr Diamond Bar CA 91765",
    "addr:postcode":"22359;91765",
    "addr:street":"Birds Eye Dr",
    "iso:country":"US",
    "sg:address":"22359 Birds Eye Dr",
    "sg:city":"Diamond Bar",
    "sg:classifiers":[
        {
            "category":"Building & Trades",
            "subcategory":"Construction",
            "type":"Services"
        }
    ],
    "sg:phone":"+1 909 860 9452",
    "sg:postcode":"91765",
    "sg:province":"CA",
    "sg:tags":[
        "speculative",
        "builder"
    ],
    "wof:name":"Diamond Crest I & 3",
    "wof:placetype":"venue"
},
  "geometry": {"coordinates":[-117.82706399999999,33.998163],"type":"Point"}
}