{
  "type": "Feature",
  "properties": {
    "addr:full":"2763 Brookhill St La Crescenta CA 91214",
    "addr:housenumber":"2763",
    "addr:postcode":"91214",
    "addr:street":"Brookhill St",
    "iso:country":"US",
    "sg:address":"2763 Brookhill St",
    "sg:city":"La Crescenta",
    "sg:classifiers":[
        {
            "category":"Professional",
            "type":"Services"
        }
    ],
    "sg:phone":"+1 818 957 6345",
    "sg:postcode":"91214",
    "sg:province":"CA",
    "wof:name":"Tradeground Inc",
    "wof:placetype":"venue"
},
  "geometry": {"coordinates":[-118.238873,34.23344],"type":"Point"}
}