{
  "type": "Feature",
  "properties": {
    "iso:country":"US",
    "sg:address":"13344 Hawthorne Blvd",
    "sg:city":"Hawthorne",
    "sg:classifiers":[
        {
            "category":"Restaurant",
            "type":"Food & Drink"
        }
    ],
    "sg:phone":"+1 310 973 9066",
    "sg:postcode":"90250",
    "sg:province":"CA",
    "sg:tags":[
        "pizza"
    ],
    "wof:name":"Pizza Show",
    "wof:placetype":"venue"
},
  "geometry": {"coordinates":[-118.351997,33.911499],"type":"Point"}
}