{
  "type": "Feature",
  "properties": {
    "addr:full":"5002 Holt Blvd Montclair CA 91763",
    "addr:housenumber":"5002",
    "addr:postcode":"91763",
    "addr:street":"Holt Blvd",
    "iso:country":"US",
    "sg:address":"5002 Holt Blvd",
    "sg:city":"Montclair",
    "sg:classifiers":[
        {
            "category":"Professional",
            "type":"Services"
        }
    ],
    "sg:phone":"+1 909 620 4802",
    "sg:postcode":"91763",
    "sg:province":"CA",
    "sg:tags":[
        "establishment"
    ],
    "wof:name":"Mercadito Abasolo",
    "wof:placetype":"venue"
},
  "geometry": {"coordinates":[-117.691757,34.063307],"type":"Point"}
}