{
  "type": "Feature",
  "properties": {
    "addr:full":"5574 Danny Ave Cypress CA 90630",
    "addr:housenumber":"5574",
    "addr:postcode":"90630",
    "addr:street":"Danny Ave",
    "iso:country":"US",
    "sg:address":"5574 Danny Ave",
    "sg:city":"Cypress",
    "sg:classifiers":[
        {
            "category":"Building & Trades",
            "subcategory":"Construction",
            "type":"Services"
        }
    ],
    "sg:phone":"+1 714 527 7572",
    "sg:postcode":"90630",
    "sg:province":"CA",
    "sg:tags":[
        "general",
        "contractor"
    ],
    "wof:name":"Ryan Rusell Wells Construction",
    "wof:placetype":"venue"
},
  "geometry": {"coordinates":[-118.034057,33.832904],"type":"Point"}
}