{
  "type": "Feature",
  "properties": {
    "iso:country":"US",
    "sg:address":"11 Hillsdale Avenue",
    "sg:city":"Santa Cruz",
    "sg:classifiers":[
        {
            "category":"Sports & Exercise",
            "subcategory":"Playing Field",
            "type":"Entertainment"
        }
    ],
    "sg:phone":"+1 831 588 4098",
    "sg:postcode":"95060",
    "sg:province":"CA",
    "sg:tags":[
        "instruction",
        "fitness"
    ],
    "sg:website":"www.energetixfitness.com/index.html",
    "wof:name":"Energetix Fitness",
    "wof:placetype":"venue"
},
  "geometry": {"coordinates":[-122.03286300000001,37.018555],"type":"Point"}
}