{
  "type": "Feature",
  "properties": {
    "iso:country":"US",
    "sg:address":"21021 Barclay Ln",
    "sg:city":"Lake Forest",
    "sg:classifiers":[
        {
            "category":"Wholesale",
            "subcategory":"Hardware",
            "type":"Manufacturing & Wholesale Goods"
        }
    ],
    "sg:phone":"+1 949 395 8750",
    "sg:postcode":"92630",
    "sg:province":"CA",
    "sg:tags":[
        "purifying",
        "cleaning",
        "air"
    ],
    "wof:name":"Living Systems",
    "wof:placetype":"venue"
},
  "geometry": {"coordinates":[-117.663771,33.656933],"type":"Point"}
}