{
  "type": "Feature",
  "properties": {
    "iso:country":"US",
    "sg:address":"18411 Crenshaw Blvd",
    "sg:city":"Torrance",
    "sg:classifiers":[
        {
            "category":"Professional",
            "subcategory":"Employment Agencies",
            "type":"Services"
        }
    ],
    "sg:phone":"+1 310 516 9980",
    "sg:postcode":"90504",
    "sg:province":"CA",
    "sg:tags":[
        "opportunity"
    ],
    "wof:name":"California Medical Staffing",
    "wof:placetype":"venue"
},
  "geometry": {"coordinates":[-118.32652,33.864608],"type":"Point"}
}