{
  "type": "Feature",
  "properties": {
    "addr:full":"2600 North Ave Sacramento CA 95838",
    "addr:housenumber":"2600",
    "addr:postcode":"95838",
    "addr:street":"North Ave",
    "iso:country":"US",
    "sg:address":"2600 North Ave",
    "sg:city":"Sacramento",
    "sg:classifiers":[
        {
            "category":"Bus Charters",
            "type":"Transportation"
        }
    ],
    "sg:phone":"+1 916 648 0184",
    "sg:postcode":"95838",
    "sg:province":"CA",
    "sg:tags":[
        "rental"
    ],
    "wof:name":"Frontier Tours",
    "wof:placetype":"venue"
},
  "geometry": {"coordinates":[-121.40573500000001,38.639815],"type":"Point"}
}