{
  "type": "Feature",
  "properties": {
    "iso:country":"US",
    "sg:address":"1660 S Amphlett Boulevard Suite 128",
    "sg:city":"San Mateo",
    "sg:classifiers":[
        {
            "category":"Banks & Credit Unions",
            "subcategory":"Financial Services",
            "type":"Services"
        }
    ],
    "sg:phone":"+1 650 235 3500",
    "sg:postcode":"94402",
    "sg:province":"CA",
    "sg:tags":[
        "broker",
        "mortgage"
    ],
    "wof:name":"Mortgage World",
    "wof:placetype":"venue"
},
  "geometry": {"coordinates":[-122.301852,37.558747],"type":"Point"}
}