{
  "type": "Feature",
  "properties": {
    "addr:full":"100 el Camino Real Burlingame CA 94010",
    "addr:housenumber":"100",
    "addr:postcode":"94010",
    "addr:street":"El Camino Real",
    "iso:country":"US",
    "sg:address":"100 el Camino Real",
    "sg:city":"Burlingame",
    "sg:classifiers":[
        {
            "category":"Professional",
            "type":"Services"
        }
    ],
    "sg:phone":"+1 650 525 4535",
    "sg:postcode":"94010",
    "sg:province":"CA",
    "wof:name":"Phil Waddingham",
    "wof:placetype":"venue"
},
  "geometry": {"coordinates":[-122.346458,37.575448],"type":"Point"}
}