{
  "type": "Feature",
  "properties": {
    "addr:full":"1938 Autopark Way N Escondido CA 92029",
    "addr:housenumber":"1938",
    "addr:postcode":"92029",
    "addr:street":"Autopark Way N",
    "iso:country":"US",
    "sg:address":"1938 Autopark Way N",
    "sg:city":"Escondido",
    "sg:classifiers":[
        {
            "category":"Autos & Motor Vehicles",
            "subcategory":"Automobile Sales",
            "type":"Retail Goods"
        }
    ],
    "sg:phone":"+1 760 546 1200",
    "sg:postcode":"92029",
    "sg:province":"CA",
    "sg:tags":[
        "car",
        "dealer"
    ],
    "wof:name":"Volvo Escondido",
    "wof:placetype":"venue"
},
  "geometry": {"coordinates":[-117.108784,33.116823],"type":"Point"}
}