{
  "type": "Feature",
  "properties": {
    "iso:country":"US",
    "sg:address":"3221 Airflite Way",
    "sg:city":"Long Beach",
    "sg:classifiers":[
        {
            "category":"Professional",
            "type":"Services"
        }
    ],
    "sg:phone":"+1 562 426 5966",
    "sg:postcode":"90807",
    "sg:province":"CA",
    "sg:tags":[
        "establishment"
    ],
    "wof:name":"Flying M",
    "wof:placetype":"venue"
},
  "geometry": {"coordinates":[-118.159217,33.816889],"type":"Point"}
}