{
  "type": "Feature",
  "properties": {
    "addr:full":"4417 La Jolla Village Drive San Diego CA 92122",
    "addr:housenumber":"4417",
    "addr:postcode":"92122",
    "addr:street":"La Jolla Village Drive",
    "iso:country":"US",
    "sg:address":"4417 La Jolla Village Drive",
    "sg:city":"San Diego",
    "sg:classifiers":[
        {
            "category":"Wholesale",
            "subcategory":"Stationery",
            "type":"Manufacturing & Wholesale Goods"
        }
    ],
    "sg:phone":"+1 858 452 7515",
    "sg:postcode":"92122",
    "sg:province":"CA",
    "sg:tags":[
        "card"
    ],
    "wof:name":"Cynthia's Hallmark Shops",
    "wof:placetype":"venue"
},
  "geometry": {"coordinates":[-117.21145,32.873146],"type":"Point"}
}