{
  "type": "Feature",
  "properties": {
    "iso:country":"US",
    "sg:address":"1501 E Chestnut Ct Ste D",
    "sg:city":"Lompoc",
    "sg:classifiers":[
        {
            "category":"Autos & Motor Vehicles",
            "subcategory":"Auto Supplies",
            "type":"Retail Goods"
        },
        {
            "category":"Retail",
            "subcategory":"Auto Repair",
            "type":"Services"
        }
    ],
    "sg:phone":"+1 805 735 7340",
    "sg:postcode":"93436",
    "sg:province":"CA",
    "sg:tags":[
        "body",
        "automobile",
        "truck",
        "painting",
        "repairing"
    ],
    "wof:name":"Hot Rod Alley",
    "wof:placetype":"venue"
},
  "geometry": {"coordinates":[-120.440247,34.642818],"type":"Point"}
}