{
  "type": "Feature",
  "properties": {
    "addr:full":"1578 E Whitmore Ave #H Ceres CA 95307",
    "addr:housenumber":"1578",
    "addr:postcode":"95307",
    "addr:street":"E Whitmore Ave # H",
    "iso:country":"US",
    "sg:address":"1578 E Whitmore Ave #H",
    "sg:city":"Ceres",
    "sg:classifiers":[
        {
            "category":"Donuts",
            "subcategory":"None",
            "type":"Food & Drink"
        }
    ],
    "sg:phone":"+1 209 537 7200",
    "sg:postcode":"95307",
    "sg:province":"CA",
    "wof:name":"Glaze Donuts",
    "wof:placetype":"venue"
},
  "geometry": {"coordinates":[-120.969359,37.594204],"type":"Point"}
}