{
  "type": "Feature",
  "properties": {
    "iso:country":"US",
    "sg:address":"3225 Lakeshore Ave",
    "sg:city":"Oakland",
    "sg:classifiers":[
        {
            "category":"Health Services",
            "subcategory":"Health Practitioner",
            "type":"Services"
        }
    ],
    "sg:phone":"+1 510 465 6106",
    "sg:postcode":"94610",
    "sg:province":"CA",
    "sg:tags":[
        "psychologist"
    ],
    "wof:name":"Don F Fenn PHD",
    "wof:placetype":"venue"
},
  "geometry": {"coordinates":[-122.243516,37.811047],"type":"Point"}
}