{
  "type": "Feature",
  "properties": {
    "addr:full":"7651 Wellington Way San Diego CA 92111",
    "addr:housenumber":"7651",
    "addr:postcode":"92111",
    "addr:street":"Wellington Way",
    "iso:country":"US",
    "sg:address":"7651 Wellington Way",
    "sg:city":"San Diego",
    "sg:classifiers":[
        {
            "category":"Place Of Worship",
            "subcategory":"Church",
            "type":"Public Place"
        }
    ],
    "sg:phone":"+1 858 268 2330",
    "sg:postcode":"92111",
    "sg:province":"CA",
    "sg:website":"www.diveintoflood.com",
    "wof:name":"Flood Church",
    "wof:placetype":"venue"
},
  "geometry": {"coordinates":[-117.16039600000001,32.797845],"type":"Point"}
}