{
  "type": "Feature",
  "properties": {
    "addr:full":"570 E la Cadena Dr Ste F Riverside CA 92507",
    "addr:housenumber":"570",
    "addr:postcode":"92507",
    "addr:street":"E La Cadena Dr Ste F",
    "iso:country":"US",
    "sg:address":"570 E la Cadena Dr Ste F",
    "sg:city":"Riverside",
    "sg:classifiers":[
        {
            "category":"Autos & Motor Vehicles",
            "subcategory":"Automobile Sales",
            "type":"Retail Goods"
        },
        {
            "category":"Retail",
            "subcategory":"Car Wash",
            "type":"Services"
        }
    ],
    "sg:phone":"+1 951 276 3395",
    "sg:postcode":"92507",
    "sg:province":"CA",
    "sg:tags":[
        "used",
        "detailing"
    ],
    "wof:name":"Proto Motors",
    "wof:placetype":"venue"
},
  "geometry": {"coordinates":[-117.345022,34.011188],"type":"Point"}
}