{
  "type": "Feature",
  "properties": {
    "addr:full":"10502 Red Fir Rd Truckee CA 96161",
    "addr:housenumber":"10502",
    "addr:postcode":"96161",
    "addr:street":"Red Fir Rd",
    "iso:country":"US",
    "sg:address":"10502 Red Fir Rd",
    "sg:city":"Truckee",
    "sg:classifiers":[
        {
            "category":"Building & Trades",
            "subcategory":"Construction",
            "type":"Services"
        }
    ],
    "sg:phone":"+1 530 401 3627",
    "sg:postcode":"96161",
    "sg:province":"CA",
    "sg:tags":[
        "wallcoverings-installation",
        "wallpaper",
        "painting",
        "contractor"
    ],
    "wof:name":"Ekman Painting",
    "wof:placetype":"venue"
},
  "geometry": {"coordinates":[-120.169898,39.320722],"type":"Point"}
}