{
  "type": "Feature",
  "properties": {
    "addr:full":"360 E Jefferson Blvd Los Angeles CA 90011",
    "addr:housenumber":"360",
    "addr:postcode":"90011",
    "addr:street":"E Jefferson Blvd",
    "iso:country":"US",
    "sg:address":"360 E Jefferson Blvd",
    "sg:city":"Los Angeles",
    "sg:classifiers":[
        {
            "category":"Professional",
            "type":"Services"
        }
    ],
    "sg:phone":"+1 323 234 8060",
    "sg:postcode":"90011",
    "sg:province":"CA",
    "wof:name":"Marvel Sweater Inc",
    "wof:placetype":"venue"
},
  "geometry": {"coordinates":[-118.267826,34.016435],"type":"Point"}
}