{
  "type": "Feature",
  "properties": {
    "iso:country":"US",
    "sg:address":"885 Junipero Ave",
    "sg:city":"Pacific Grove",
    "sg:classifiers":[
        {
            "category":"Building & Trades",
            "subcategory":"Construction",
            "type":"Services"
        }
    ],
    "sg:phone":"+1 831 372 6929",
    "sg:postcode":"93950",
    "sg:province":"CA",
    "sg:tags":[
        "painter"
    ],
    "wof:name":"Woolem Painting & Decorating",
    "wof:placetype":"venue"
},
  "geometry": {"coordinates":[-121.928067,36.619236],"type":"Point"}
}