{
  "type": "Feature",
  "properties": {
    "addr:full":"256 Pennsylvania Ave San Francisco CA 94107",
    "addr:housenumber":"256",
    "addr:postcode":"94107",
    "addr:street":"Pennsylvania Ave",
    "iso:country":"US",
    "sg:address":"256 Pennsylvania Ave",
    "sg:city":"San Francisco",
    "sg:classifiers":[
        {
            "category":"Retail",
            "subcategory":"Animal Services",
            "type":"Services"
        }
    ],
    "sg:phone":"+1 415 255 9331",
    "sg:postcode":"94107",
    "sg:province":"CA",
    "wof:name":"Doggieday",
    "wof:placetype":"venue"
},
  "geometry": {"coordinates":[-122.39373000000001,37.764021],"type":"Point"}
}