{
  "type": "Feature",
  "properties": {
    "addr:full":"1113 Loma Vista Dr Napa CA 94558",
    "addr:housenumber":"1113",
    "addr:postcode":"94558",
    "addr:street":"Loma Vista Dr",
    "iso:country":"US",
    "sg:address":"1113 Loma Vista Dr",
    "sg:city":"Napa",
    "sg:classifiers":[
        {
            "category":"Building & Trades",
            "subcategory":"Landscaping Services",
            "type":"Services"
        }
    ],
    "sg:phone":"+1 707 224 3980",
    "sg:postcode":"94558",
    "sg:province":"CA",
    "sg:tags":[
        "landscape",
        "contractor"
    ],
    "wof:name":"R E Carr Landscape Contractor",
    "wof:placetype":"venue"
},
  "geometry": {"coordinates":[-122.292467,38.384151],"type":"Point"}
}