{
  "type": "Feature",
  "properties": {
    "addr:full":"934 Acapulco St Laguna Beach CA 92651",
    "addr:housenumber":"934",
    "addr:postcode":"92651",
    "addr:street":"Acapulco St",
    "iso:country":"US",
    "sg:address":"934 Acapulco St",
    "sg:city":"Laguna Beach",
    "sg:classifiers":[
        {
            "category":"Travel",
            "subcategory":"Travel Agent",
            "type":"Entertainment"
        }
    ],
    "sg:phone":"+1 949 499 9561",
    "sg:postcode":"92651",
    "sg:province":"CA",
    "sg:tags":[
        "agency",
        "bureau"
    ],
    "wof:name":"Nature Quest Tours",
    "wof:placetype":"venue"
},
  "geometry": {"coordinates":[-117.756409,33.529247],"type":"Point"}
}