{
  "type": "Feature",
  "properties": {
    "addr:full":"27886 del Rio Rd Temecula CA 92590",
    "addr:housenumber":"27886",
    "addr:postcode":"92590",
    "addr:street":"Del Rio Rd",
    "iso:country":"US",
    "sg:address":"27886 del Rio Rd",
    "sg:city":"Temecula",
    "sg:classifiers":[
        {
            "category":"Wholesale",
            "subcategory":"Electrical",
            "type":"Manufacturing & Wholesale Goods"
        }
    ],
    "sg:phone":"+1 951 695 0180",
    "sg:postcode":"92590",
    "sg:province":"CA",
    "sg:tags":[
        "electronic",
        "representative"
    ],
    "wof:name":"T L Svc",
    "wof:placetype":"venue"
},
  "geometry": {"coordinates":[-117.158439,33.507562],"type":"Point"}
}