{
  "type": "Feature",
  "properties": {
    "addr:full":"151 W Jackson St Hayward CA 94544",
    "addr:housenumber":"151",
    "addr:postcode":"94544",
    "addr:street":"W Jackson St",
    "iso:country":"US",
    "sg:address":"151 W Jackson St",
    "sg:city":"Hayward",
    "sg:classifiers":[
        {
            "category":"Restaurant",
            "type":"Food & Drink"
        }
    ],
    "sg:phone":"+1 510 887 7836",
    "sg:postcode":"94544",
    "sg:province":"CA",
    "wof:name":"Rickshaw Express",
    "wof:placetype":"venue"
},
  "geometry": {"coordinates":[-122.08899700000001,37.6535],"type":"Point"}
}