{
  "type": "Feature",
  "properties": {
    "addr:full":"2346 Chestnut St San Francisco CA 94123",
    "addr:housenumber":"2346",
    "addr:postcode":"94123",
    "addr:street":"Chestnut St",
    "iso:country":"US",
    "sg:address":"2346 Chestnut St",
    "sg:city":"San Francisco",
    "sg:classifiers":[
        {
            "category":"Restaurant",
            "type":"Food & Drink"
        }
    ],
    "sg:phone":"+1 415 346 1801",
    "sg:postcode":"94123",
    "sg:province":"CA",
    "wof:name":"Bechelli's Restaurant",
    "wof:placetype":"venue"
},
  "geometry": {"coordinates":[-122.442239,37.800151],"type":"Point"}
}