{
  "type": "Feature",
  "properties": {
    "iso:country":"US",
    "sg:address":"148 S. Citrus Street",
    "sg:city":"Orange",
    "sg:classifiers":[
        {
            "category":"Building & Trades",
            "subcategory":"Plumbing",
            "type":"Services"
        }
    ],
    "sg:phone":"+1 714 838 0937",
    "sg:postcode":"92868",
    "sg:province":"CA",
    "sg:website":"thelocalplumber.com",
    "wof:name":"The Local Plumber",
    "wof:placetype":"venue"
},
  "geometry": {"coordinates":[-117.863249,33.786958],"type":"Point"}
}