{
  "type": "Feature",
  "properties": {
    "iso:country":"US",
    "sg:address":"1254 Shirley Way",
    "sg:city":"Lincoln",
    "sg:classifiers":[
        {
            "category":"Professional",
            "subcategory":"Business Services",
            "type":"Services"
        }
    ],
    "sg:phone":"+1 916 956 1397",
    "sg:postcode":"95648",
    "sg:province":"CA",
    "sg:tags":[
        "notary"
    ],
    "wof:name":"Jewl's Mobile Notary",
    "wof:placetype":"venue"
},
  "geometry": {"coordinates":[-121.298919,38.885027],"type":"Point"}
}