{
  "type": "Feature",
  "properties": {
    "iso:country":"US",
    "sg:address":"27271 Ethanac Rd",
    "sg:city":"Sun City",
    "sg:classifiers":[
        {
            "category":"Autos & Motor Vehicles",
            "subcategory":"Auto Supplies",
            "type":"Retail Goods"
        }
    ],
    "sg:phone":"+1 951 928 9590",
    "sg:postcode":"92585",
    "sg:province":"CA",
    "sg:tags":[
        "tire"
    ],
    "wof:name":"Alicia's Truck & Tire Supply",
    "wof:placetype":"venue"
},
  "geometry": {"coordinates":[-117.183791,33.742818],"type":"Point"}
}