{
  "type": "Feature",
  "properties": {
    "addr:full":"18729 Main St Groveland CA 95321",
    "addr:housenumber":"18729",
    "addr:postcode":"95321",
    "addr:street":"Main St",
    "iso:country":"US",
    "sg:address":"18729 Main St",
    "sg:city":"Groveland",
    "sg:classifiers":[
        {
            "category":"Personal",
            "subcategory":"Beauty Salon",
            "type":"Services"
        }
    ],
    "sg:phone":"+1 209 962 6671",
    "sg:postcode":"95321",
    "sg:province":"CA",
    "wof:name":"Body Beautiful",
    "wof:placetype":"venue"
},
  "geometry": {"coordinates":[-120.23088799999999,37.838677],"type":"Point"}
}