{
  "type": "Feature",
  "properties": {
    "addr:full":"1310 N Red Gum St Anaheim CA 92806",
    "addr:housenumber":"1310",
    "addr:postcode":"92806",
    "addr:street":"N Red Gum St",
    "iso:country":"US",
    "sg:address":"1310 N Red Gum St",
    "sg:city":"Anaheim",
    "sg:classifiers":[
        {
            "category":"Building & Trades",
            "subcategory":"Construction",
            "type":"Services"
        }
    ],
    "sg:phone":"+1 714 630 9000",
    "sg:postcode":"92806",
    "sg:province":"CA",
    "sg:tags":[
        "mobile",
        "home"
    ],
    "wof:name":"Dynamics Engineering",
    "wof:placetype":"venue"
},
  "geometry": {"coordinates":[-117.867108,33.859616],"type":"Point"}
}