{
  "type": "Feature",
  "properties": {
    "addr:full":"1031 W Commonwealth Ave Fullerton CA 92833",
    "addr:housenumber":"1031",
    "addr:postcode":"92833",
    "addr:street":"W Commonwealth Ave",
    "iso:country":"US",
    "sg:address":"1031 W Commonwealth Ave",
    "sg:city":"Fullerton",
    "sg:classifiers":[
        {
            "category":"Travel",
            "subcategory":"Hotels & Motels",
            "type":"Entertainment"
        }
    ],
    "sg:phone":"+1 714 441 0623",
    "sg:postcode":"92833",
    "sg:province":"CA",
    "sg:tags":[
        "lodging"
    ],
    "wof:name":"Lucky Motel",
    "wof:placetype":"venue"
},
  "geometry": {"coordinates":[-117.942258,33.870396],"type":"Point"}
}