{
  "type": "Feature",
  "properties": {
    "addr:full":"19230 Ave 152 Porterville CA 93257",
    "addr:housenumber":"19230",
    "addr:postcode":"93257",
    "addr:street":"Ave 152",
    "iso:country":"US",
    "sg:address":"19230 Ave 152",
    "sg:city":"Porterville",
    "sg:classifiers":[
        {
            "category":"Professional",
            "subcategory":"Advertising",
            "type":"Services"
        }
    ],
    "sg:phone":"+1 559 782 5800",
    "sg:postcode":"93257",
    "sg:province":"CA",
    "sg:tags":[
        "counselor"
    ],
    "wof:name":"Allen West & Assoc",
    "wof:placetype":"venue"
},
  "geometry": {"coordinates":[-119.13441400000001,36.065933],"type":"Point"}
}