{
  "type": "Feature",
  "properties": {
    "addr:full":"3590 James Ln Concord CA 94519",
    "addr:housenumber":"3590",
    "addr:postcode":"94519",
    "addr:street":"James Ln",
    "iso:country":"US",
    "sg:address":"3590 James Ln",
    "sg:city":"Concord",
    "sg:classifiers":[
        {
            "category":"Utilities",
            "subcategory":"Telephone",
            "type":"Services"
        }
    ],
    "sg:phone":"+1 925 827 2189",
    "sg:postcode":"94519",
    "sg:province":"CA",
    "sg:tags":[
        "communications"
    ],
    "wof:name":"Professional Telephone Systems",
    "wof:placetype":"venue"
},
  "geometry": {"coordinates":[-122.00165800000001,37.97949],"type":"Point"}
}