{
  "type": "Feature",
  "properties": {
    "iso:country":"US",
    "sg:address":"21805 Foothill Blvd",
    "sg:city":"Hayward",
    "sg:classifiers":[
        {
            "category":"Retail",
            "subcategory":"Auto Repair",
            "type":"Services"
        }
    ],
    "sg:phone":"+1 510 581 6804",
    "sg:postcode":"94541",
    "sg:province":"CA",
    "sg:tags":[
        "repairing",
        "automobile",
        "radiator"
    ],
    "sg:website":"www.pankeysradiator.com",
    "wof:name":"Pankey's Radiator Repair",
    "wof:placetype":"venue"
},
  "geometry": {"coordinates":[-122.08696999999999,37.681158],"type":"Point"}
}