{
  "type": "Feature",
  "properties": {
    "iso:country":"US",
    "sg:address":"3281 State Hwy 138",
    "sg:city":"Pinon Hills",
    "sg:classifiers":[
        {
            "category":"Restaurant",
            "type":"Food & Drink"
        }
    ],
    "sg:phone":"+1 760 868 8863",
    "sg:postcode":"92372",
    "sg:province":"CA",
    "wof:name":"Rick's Roadside Cafe",
    "wof:placetype":"venue"
},
  "geometry": {"coordinates":[-117.58984100000001,34.411729],"type":"Point"}
}