{
  "type": "Feature",
  "properties": {
    "addr:full":"1637 E Valley Pkwy 172 Escondido CA 92027",
    "addr:housenumber":"1637;172",
    "addr:postcode":"92027",
    "addr:street":"E Valley Pkwy",
    "iso:country":"US",
    "sg:address":"1637 E Valley Pkwy 172",
    "sg:city":"Escondido",
    "sg:classifiers":[
        {
            "category":"Shopping",
            "subcategory":"Catalog Store",
            "type":"Retail Goods"
        }
    ],
    "sg:phone":"+1 760 735 8931",
    "sg:postcode":"92027",
    "sg:province":"CA",
    "sg:tags":[
        "mail",
        "order",
        "online"
    ],
    "wof:name":"Pns",
    "wof:placetype":"venue"
},
  "geometry": {"coordinates":[-117.058684,33.134341],"type":"Point"}
}