{
  "type": "Feature",
  "properties": {
    "addr:full":"2105 Roosevelt Ave Richmond CA 94801",
    "addr:housenumber":"2105",
    "addr:postcode":"94801",
    "addr:street":"Roosevelt Ave",
    "iso:country":"US",
    "sg:address":"2105 Roosevelt Ave",
    "sg:city":"Richmond",
    "sg:classifiers":[
        {
            "category":"Real Estate",
            "subcategory":"Real Estate Agent",
            "type":"Services"
        }
    ],
    "sg:phone":"+1 510 236 0391",
    "sg:postcode":"94801",
    "sg:province":"CA",
    "wof:name":"Mary L Smith",
    "wof:placetype":"venue"
},
  "geometry": {"coordinates":[-122.348546,37.940047],"type":"Point"}
}