{
  "type": "Feature",
  "properties": {
    "iso:country":"US",
    "sg:address":"455 Market Street Suite 1800",
    "sg:city":"San Francisco",
    "sg:classifiers":[
        {
            "category":"Real Estate",
            "subcategory":"Real Estate Services",
            "type":"Services"
        }
    ],
    "sg:phone":"+1 415 352 3025",
    "sg:postcode":"94105",
    "sg:province":"CA",
    "sg:tags":[
        "management",
        "property"
    ],
    "sg:website":"www.hancprop.com",
    "wof:name":"Hancock Properties, Inc.",
    "wof:placetype":"venue"
},
  "geometry": {"coordinates":[-122.398763,37.791325],"type":"Point"}
}