{
  "type": "Feature",
  "properties": {
    "addr:full":"228 12th St Del Mar CA 92014",
    "addr:housenumber":"228",
    "addr:postcode":"92014",
    "addr:street":"12Th St",
    "iso:country":"US",
    "sg:address":"228 12th St",
    "sg:city":"Del Mar",
    "sg:classifiers":[
        {
            "category":"Personal",
            "subcategory":"Beauty Salon",
            "type":"Services"
        }
    ],
    "sg:phone":"+1 858 794 8108",
    "sg:postcode":"92014",
    "sg:province":"CA",
    "wof:name":"Catey's By The Sea",
    "wof:placetype":"venue"
},
  "geometry": {"coordinates":[-117.264955,32.956335],"type":"Point"}
}