{
  "type": "Feature",
  "properties": {
    "addr:full":"34219 Kenwood Dr Fremont CA 94555",
    "addr:housenumber":"34219",
    "addr:postcode":"94555",
    "addr:street":"Kenwood Dr",
    "iso:country":"US",
    "sg:address":"34219 Kenwood Dr",
    "sg:city":"Fremont",
    "sg:classifiers":[
        {
            "category":"Professional",
            "subcategory":"Computer Services",
            "type":"Services"
        }
    ],
    "sg:phone":"+1 510 793 8546",
    "sg:postcode":"94555",
    "sg:province":"CA",
    "sg:tags":[
        "hardware",
        "provider",
        "internet",
        "software"
    ],
    "wof:name":"Solec",
    "wof:placetype":"venue"
},
  "geometry": {"coordinates":[-122.055418,37.562851],"type":"Point"}
}