{
  "type": "Feature",
  "properties": {
    "addr:full":"26877 Sierra Hwy Santa Clarita CA 91321",
    "addr:housenumber":"26877",
    "addr:postcode":"91321",
    "addr:street":"Sierra Hwy",
    "iso:country":"US",
    "sg:address":"26877 Sierra Hwy",
    "sg:city":"Santa Clarita",
    "sg:classifiers":[
        {
            "category":"Health Services",
            "subcategory":"Dentist",
            "type":"Services"
        }
    ],
    "sg:phone":"+1 951 200 3478",
    "sg:postcode":"91321",
    "sg:province":"CA",
    "sg:website":"www.canyoncountrydentalgroup.com...",
    "wof:name":"Canyon Country Dental Group & Orthodontics",
    "wof:placetype":"venue"
},
  "geometry": {"coordinates":[-118.46717599999999,34.404148],"type":"Point"}
}