{
  "type": "Feature",
  "properties": {
    "addr:full":"12819 Newton St Sylmar CA 91342",
    "addr:housenumber":"12819",
    "addr:postcode":"91342",
    "addr:street":"Newton St",
    "iso:country":"US",
    "sg:address":"12819 Newton St",
    "sg:city":"Sylmar",
    "sg:classifiers":[
        {
            "category":"Shopping",
            "subcategory":"Clothing, Apparel, & Fashions",
            "type":"Retail Goods"
        },
        {
            "category":"Manufacturing",
            "subcategory":"Apparel",
            "type":"Manufacturing & Wholesale Goods"
        }
    ],
    "sg:phone":"+1 818 581 1376",
    "sg:postcode":"91342",
    "sg:province":"CA",
    "sg:tags":[
        "clothing",
        "boys'",
        "clothing-men's-wholesale",
        "manufacturer"
    ],
    "wof:name":"The Nocturnal Clothing Line",
    "wof:placetype":"venue"
},
  "geometry": {"coordinates":[-118.413166,34.300603],"type":"Point"}
}