{
  "type": "Feature",
  "properties": {
    "addr:full":"130 Armstrong St Lakeport CA 95453",
    "addr:housenumber":"130",
    "addr:postcode":"95453",
    "addr:street":"Armstrong St",
    "iso:country":"US",
    "sg:address":"130 Armstrong St",
    "sg:city":"Lakeport",
    "sg:classifiers":[
        {
            "category":"Building & Trades",
            "subcategory":"Landscaping Services",
            "type":"Services"
        }
    ],
    "sg:phone":"+1 707 263 5110",
    "sg:postcode":"95453",
    "sg:province":"CA",
    "sg:tags":[
        "landscape"
    ],
    "wof:name":"Newts Nook",
    "wof:placetype":"venue"
},
  "geometry": {"coordinates":[-122.915874,39.041359],"type":"Point"}
}