{
  "type": "Feature",
  "properties": {
    "addr:full":"2033 E Ramsey St Banning CA 92220",
    "addr:housenumber":"2033",
    "addr:postcode":"92220",
    "addr:street":"E Ramsey St",
    "iso:country":"US",
    "sg:address":"2033 E Ramsey St",
    "sg:city":"Banning",
    "sg:classifiers":[
        {
            "category":"Government",
            "subcategory":"Office",
            "type":"Public Place"
        }
    ],
    "sg:phone":"+1 951 849 7504",
    "sg:postcode":"92220",
    "sg:province":"CA",
    "sg:tags":[
        "state",
        "program"
    ],
    "wof:name":"Transportation Dept",
    "wof:placetype":"venue"
},
  "geometry": {"coordinates":[-116.85850600000001,33.925446],"type":"Point"}
}