{
  "type": "Feature",
  "properties": {
    "iso:country":"US",
    "sg:address":"21950 Arnold Center Rd",
    "sg:city":"Carson",
    "sg:classifiers":[
        {
            "category":"Shopping",
            "subcategory":"Stationery & Office Supplies",
            "type":"Retail Goods"
        }
    ],
    "sg:phone":"+1 310 549 0000",
    "sg:postcode":"90810",
    "sg:province":"CA",
    "sg:tags":[
        "equipment"
    ],
    "sg:website":"www.newageinc.com",
    "wof:name":"New Age Electronics",
    "wof:placetype":"venue"
},
  "geometry": {"coordinates":[-118.230479,33.828482],"type":"Point"}
}