{
  "type": "Feature",
  "properties": {
    "addr:full":"1872 Fordham Ave Thousand Oaks CA 91360",
    "addr:housenumber":"1872",
    "addr:postcode":"91360",
    "addr:street":"Fordham Ave",
    "iso:country":"US",
    "sg:address":"1872 Fordham Ave",
    "sg:city":"Thousand Oaks",
    "sg:classifiers":[
        {
            "category":"Manufacturing",
            "subcategory":"Metals",
            "type":"Manufacturing & Wholesale Goods"
        }
    ],
    "sg:phone":"+1 805 495 6333",
    "sg:postcode":"91360",
    "sg:province":"CA",
    "sg:tags":[
        "enameling",
        "japanning",
        "lacquering"
    ],
    "wof:name":"Bathtubs & Sinks Refinishing",
    "wof:placetype":"venue"
},
  "geometry": {"coordinates":[-118.888312,34.202931],"type":"Point"}
}