{
  "type": "Feature",
  "properties": {
    "iso:country":"US",
    "sg:address":"26136 Via Pera",
    "sg:city":"Mission Viejo",
    "sg:classifiers":[
        {
            "category":"Professional",
            "type":"Services"
        }
    ],
    "sg:phone":"+1 949 689 8111",
    "sg:postcode":"92691",
    "sg:province":"CA",
    "wof:name":"Golf Unlimited",
    "wof:placetype":"venue"
},
  "geometry": {"coordinates":[-117.67674,33.62896],"type":"Point"}
}