{
  "type": "Feature",
  "properties": {
    "addr:full":"941 Chorro St San Luis Obispo CA 93401",
    "addr:housenumber":"941",
    "addr:postcode":"93401",
    "addr:street":"Chorro St",
    "iso:country":"US",
    "sg:address":"941 Chorro St",
    "sg:city":"San Luis Obispo",
    "sg:classifiers":[
        {
            "category":"Organizations",
            "subcategory":"Religious Organization",
            "type":"Services"
        },
        {
            "category":"Social Services",
            "type":"Services"
        }
    ],
    "sg:phone":"+1 805 541 9110",
    "sg:postcode":"93401",
    "sg:province":"CA",
    "sg:tags":[
        "welfare",
        "church"
    ],
    "wof:name":"Catholic Charities",
    "wof:placetype":"venue"
},
  "geometry": {"coordinates":[-120.663664,35.280775],"type":"Point"}
}