{
  "type": "Feature",
  "properties": {
    "addr:full":"3939 Maxson Rd El Monte CA 91732",
    "addr:housenumber":"3939",
    "addr:postcode":"91732",
    "addr:street":"Maxson Rd",
    "iso:country":"US",
    "sg:address":"3939 Maxson Rd",
    "sg:city":"El Monte",
    "sg:classifiers":[
        {
            "category":"Retail",
            "subcategory":"Laundry & Dry Cleaning",
            "type":"Services"
        }
    ],
    "sg:phone":"+1 626 575 5825",
    "sg:postcode":"91732",
    "sg:province":"CA",
    "sg:tags":[
        "cleaners",
        "rug",
        "carpet"
    ],
    "wof:name":"Navarrete Carpet Cleaning",
    "wof:placetype":"venue"
},
  "geometry": {"coordinates":[-118.00928399999999,34.072679],"type":"Point"}
}