{
  "type": "Feature",
  "properties": {
    "iso:country":"US",
    "sg:address":"829 W 8th St",
    "sg:city":"Azusa",
    "sg:classifiers":[
        {
            "category":"Professional",
            "type":"Services"
        }
    ],
    "sg:phone":"+1 626 650 0202",
    "sg:postcode":"91702",
    "sg:province":"CA",
    "sg:tags":[
        "establishment"
    ],
    "wof:name":"Oconca Inc",
    "wof:placetype":"venue"
},
  "geometry": {"coordinates":[-117.91672699999999,34.136132],"type":"Point"}
}