{
  "type": "Feature",
  "properties": {
    "addr:full":"10134 Foothill Blvd Rancho Cucamonga CA 91730",
    "addr:housenumber":"10134",
    "addr:postcode":"91730",
    "addr:street":"Foothill Blvd",
    "iso:country":"US",
    "sg:address":"10134 Foothill Blvd",
    "sg:city":"Rancho Cucamonga",
    "sg:classifiers":[
        {
            "category":"Recreation",
            "type":"Entertainment"
        }
    ],
    "sg:phone":"+1 909 414 9960",
    "sg:postcode":"91730",
    "sg:province":"CA",
    "sg:tags":[
        "amusement"
    ],
    "wof:name":"Bartender National School",
    "wof:placetype":"venue"
},
  "geometry": {"coordinates":[-117.580988,34.106713],"type":"Point"}
}