{
  "type": "Feature",
  "properties": {
    "iso:country":"US",
    "sg:address":"335 Carson Dr",
    "sg:city":"Hayward",
    "sg:classifiers":[
        {
            "category":"Taxi",
            "type":"Transportation"
        }
    ],
    "sg:phone":"+1 510 885 0436",
    "sg:postcode":"94544",
    "sg:province":"CA",
    "sg:tags":[
        "taxicab"
    ],
    "wof:name":"Hayward Yellow Cab",
    "wof:placetype":"venue"
},
  "geometry": {"coordinates":[-122.063381,37.64016],"type":"Point"}
}