{
  "type": "Feature",
  "properties": {
    "iso:country":"US",
    "sg:address":"1545 Tidelands Ave",
    "sg:city":"National City",
    "sg:classifiers":[
        {
            "category":"Building & Trades",
            "subcategory":"Construction",
            "type":"Services"
        }
    ],
    "sg:phone":"+1 619 474 4900",
    "sg:postcode":"91950",
    "sg:province":"CA",
    "sg:tags":[
        "contractor"
    ],
    "wof:name":"Healey Construction Co",
    "wof:placetype":"venue"
},
  "geometry": {"coordinates":[-117.115296,32.66416],"type":"Point"}
}