{
  "type": "Feature",
  "properties": {
    "iso:country":"US",
    "sg:address":"3686 Faust Ave",
    "sg:city":"Long Beach",
    "sg:classifiers":[
        {
            "category":"Building & Trades",
            "subcategory":"Plumbing",
            "type":"Services"
        }
    ],
    "sg:phone":"+1 562 235 9785",
    "sg:postcode":"90808",
    "sg:province":"CA",
    "sg:website":"www.SoCalPlumbingService.com",
    "wof:name":"SoCal Plumbing Service",
    "wof:placetype":"venue"
},
  "geometry": {"coordinates":[-118.114977,33.824515],"type":"Point"}
}