{
  "type": "Feature",
  "properties": {
    "addr:full":"88 West Main St Los Gatos CA 95030",
    "addr:housenumber":"88",
    "addr:postcode":"95030",
    "addr:street":"West Main St",
    "iso:country":"US",
    "sg:address":"88 West Main St",
    "sg:city":"Los Gatos",
    "sg:classifiers":[
        {
            "category":"Shopping",
            "type":"Retail Goods"
        }
    ],
    "sg:phone":"+1 408 399 4663",
    "sg:postcode":"95030",
    "sg:province":"CA",
    "sg:website":"www.allgoodshoppe.com",
    "wof:name":"All Good",
    "wof:placetype":"venue"
},
  "geometry": {"coordinates":[-121.98281900000001,37.222004],"type":"Point"}
}