{
  "type": "Feature",
  "properties": {
    "addr:full":"6591 Mossom Ln Anderson CA 96007",
    "addr:postcode":"6591;96007",
    "addr:street":"Mossom Ln",
    "iso:country":"US",
    "sg:address":"6591 Mossom Ln",
    "sg:city":"Anderson",
    "sg:classifiers":[
        {
            "category":"Building & Trades",
            "subcategory":"Cleaning & Sanitation",
            "type":"Services"
        },
        {
            "category":"Building & Trades",
            "subcategory":"Construction",
            "type":"Services"
        }
    ],
    "sg:phone":"+1 530 646 9406",
    "sg:postcode":"96007",
    "sg:province":"CA",
    "sg:tags":[
        "marble",
        "sealing",
        "terrazzo",
        "tile-cleaning",
        "refinishing"
    ],
    "wof:name":"Shingleton Tile And Trim",
    "wof:placetype":"venue"
},
  "geometry": {"coordinates":[-122.272972,40.477681],"type":"Point"}
}