{
  "type": "Feature",
  "properties": {
    "addr:full":"543 Howard St San Francisco CA 94105",
    "addr:housenumber":"543",
    "addr:postcode":"94105",
    "addr:street":"Howard St",
    "iso:country":"US",
    "sg:address":"543 Howard St",
    "sg:city":"San Francisco",
    "sg:classifiers":[
        {
            "category":"Education",
            "subcategory":"Special Training",
            "type":"Public Place"
        }
    ],
    "sg:phone":"+1 415 882 6300",
    "sg:postcode":"94105",
    "sg:province":"CA",
    "sg:tags":[
        "self",
        "motivational",
        "improvement"
    ],
    "sg:website":"www.landmark-education.com",
    "wof:name":"Landmark Education Corp",
    "wof:placetype":"venue"
},
  "geometry": {"coordinates":[-122.396035,37.788536],"type":"Point"}
}