{
  "type": "Feature",
  "properties": {
    "addr:full":"9800 Jefferson Blvd. Culver City CA 90232",
    "addr:housenumber":"9800",
    "addr:postcode":"90232",
    "addr:street":"Jefferson Blvd.",
    "iso:country":"US",
    "sg:address":"9800 Jefferson Blvd.",
    "sg:city":"Culver City",
    "sg:classifiers":[
        {
            "category":"Park",
            "type":"Public Place"
        }
    ],
    "sg:postcode":"90232",
    "sg:province":"CA",
    "wof:name":"Culver City Park",
    "wof:placetype":"venue"
},
  "geometry": {"coordinates":[-118.38800000000001,34.0158],"type":"Point"}
}