{
  "type": "Feature",
  "properties": {
    "iso:country":"US",
    "sg:address":"32147 Dunlap Blvd",
    "sg:city":"Yucaipa",
    "sg:classifiers":[
        {
            "category":"Building & Trades",
            "subcategory":"Construction",
            "type":"Services"
        }
    ],
    "sg:phone":"+1 909 446 8003",
    "sg:postcode":"92399",
    "sg:province":"CA",
    "sg:tags":[
        "dry wall",
        "contractor"
    ],
    "wof:name":"Strictly Textures",
    "wof:placetype":"venue"
},
  "geometry": {"coordinates":[-117.103548,34.022422],"type":"Point"}
}