{
  "type": "Feature",
  "properties": {
    "iso:country":"US",
    "sg:address":"238 Main St",
    "sg:city":"Salinas",
    "sg:classifiers":[
        {
            "category":"Wholesale",
            "subcategory":"Machinery & Supplies",
            "type":"Manufacturing & Wholesale Goods"
        }
    ],
    "sg:phone":"+1 831 422 9761",
    "sg:postcode":"93901",
    "sg:province":"CA",
    "sg:tags":[
        "equipment",
        "establishment"
    ],
    "wof:name":"T & M Clinton Beauty Supply",
    "wof:placetype":"venue"
},
  "geometry": {"coordinates":[-121.655195,36.675241],"type":"Point"}
}