{
  "type": "Feature",
  "properties": {
    "addr:full":"1119 Crystal St Porterville CA 93257",
    "addr:housenumber":"1119",
    "addr:postcode":"93257",
    "addr:street":"Crystal St",
    "iso:country":"US",
    "sg:address":"1119 Crystal St",
    "sg:city":"Porterville",
    "sg:classifiers":[
        {
            "category":"Freight",
            "type":"Transportation"
        }
    ],
    "sg:phone":"+1 559 783 1496",
    "sg:postcode":"93257",
    "sg:province":"CA",
    "sg:tags":[
        "operator",
        "local",
        "trucking"
    ],
    "wof:name":"Victorino C Alcantar",
    "wof:placetype":"venue"
},
  "geometry": {"coordinates":[-119.045417,36.044849],"type":"Point"}
}