{
  "type": "Feature",
  "properties": {
    "iso:country":"US",
    "sg:address":"5500 3rd St",
    "sg:city":"San Francisco",
    "sg:classifiers":[
        {
            "category":"Manufacturing",
            "subcategory":"Printing",
            "type":"Manufacturing & Wholesale Goods"
        }
    ],
    "sg:phone":"+1 650 553 9355",
    "sg:postcode":"94124",
    "sg:province":"CA",
    "sg:tags":[
        "printer"
    ],
    "wof:name":"Little City Press Printers",
    "wof:placetype":"venue"
},
  "geometry": {"coordinates":[-122.39357,37.72698],"type":"Point"}
}