{
  "type": "Feature",
  "properties": {
    "iso:country":"US",
    "sg:address":"109 S State St",
    "sg:city":"San Jacinto",
    "sg:classifiers":[
        {
            "category":"Home & Garden",
            "subcategory":"Furniture",
            "type":"Retail Goods"
        }
    ],
    "sg:phone":"+1 951 487 1411",
    "sg:postcode":"92583",
    "sg:province":"CA",
    "wof:name":"Figueroa Furniture",
    "wof:placetype":"venue"
},
  "geometry": {"coordinates":[-116.971868,33.786728],"type":"Point"}
}