{
  "type": "Feature",
  "properties": {
    "addr:full":"8500 Pershing Drive Unit 112 Playa Del Rey CA 90293",
    "addr:housenumber":"8500;112",
    "addr:postcode":"90293",
    "addr:street":"Pershing Drive Unit",
    "iso:country":"US",
    "sg:address":"8500 Pershing Drive Unit 112",
    "sg:city":"Playa Del Rey",
    "sg:classifiers":[
        {
            "category":"Wholesale",
            "subcategory":"Fruits & Vegetables",
            "type":"Manufacturing & Wholesale Goods"
        }
    ],
    "sg:phone":"+1 310 578 2978",
    "sg:postcode":"90293",
    "sg:province":"CA",
    "sg:tags":[
        "veggie"
    ],
    "wof:name":"Nagatoshi Organic",
    "wof:placetype":"venue"
},
  "geometry": {"coordinates":[-118.442239,33.956106],"type":"Point"}
}