{
  "type": "Feature",
  "properties": {
    "iso:country":"US",
    "sg:address":"432 Washington St",
    "sg:city":"Red Bluff",
    "sg:classifiers":[
        {
            "category":"Insurance",
            "subcategory":"Insurance Agent",
            "type":"Services"
        }
    ],
    "sg:phone":"+1 530 527 7203",
    "sg:postcode":"96080",
    "sg:province":"CA",
    "wof:name":"Alan Eddy Insurance Svc",
    "wof:placetype":"venue"
},
  "geometry": {"coordinates":[-122.234166,40.174983],"type":"Point"}
}