{
  "type": "Feature",
  "properties": {
    "iso:country":"US",
    "sg:address":"5417 Cahuenga Blvd",
    "sg:city":"North Hollywood",
    "sg:classifiers":[
        {
            "category":"Communications",
            "subcategory":"Film & Video Production",
            "type":"Services"
        },
        {
            "category":"Manufacturing",
            "subcategory":"Tools & Machinery",
            "type":"Manufacturing & Wholesale Goods"
        }
    ],
    "sg:phone":"+1 818 766 3525",
    "sg:postcode":"91601",
    "sg:province":"CA",
    "sg:tags":[
        "picture",
        "transformer",
        "producer",
        "mfg",
        "motion",
        "studio",
        "distribution"
    ],
    "sg:website":"www.denecke.com",
    "wof:name":"Denecke Inc",
    "wof:placetype":"venue"
},
  "geometry": {"coordinates":[-118.36162299999999,34.16978],"type":"Point"}
}