{
  "type": "Feature",
  "properties": {
    "iso:country":"US",
    "sg:address":"1400 W Lacey Blvd",
    "sg:city":"Hanford",
    "sg:classifiers":[
        {
            "category":"Professional",
            "subcategory":"Secretarial Services",
            "type":"Services"
        }
    ],
    "sg:phone":"+1 559 585 3450",
    "sg:postcode":"93230",
    "sg:province":"CA",
    "sg:tags":[
        "convention",
        "court",
        "reporter"
    ],
    "wof:name":"Kings Court Reporters",
    "wof:placetype":"venue"
},
  "geometry": {"coordinates":[-119.668448,36.327997],"type":"Point"}
}