{
  "type": "Feature",
  "properties": {
    "addr:full":"1714 W Claude St Compton CA 90220",
    "addr:housenumber":"1714",
    "addr:postcode":"90220",
    "addr:street":"W Claude St",
    "iso:country":"US",
    "sg:address":"1714 W Claude St",
    "sg:city":"Compton",
    "sg:classifiers":[
        {
            "category":"Social Services",
            "subcategory":"Child Care",
            "type":"Services"
        }
    ],
    "sg:phone":"+1 310 763 2109",
    "sg:postcode":"90220",
    "sg:province":"CA",
    "wof:name":"Noah's Ark Family Child Care",
    "wof:placetype":"venue"
},
  "geometry": {"coordinates":[-118.24836500000001,33.885898],"type":"Point"}
}