{
  "type": "Feature",
  "properties": {
    "addr:full":"11750 Dublin Blvd Dublin CA 94568",
    "addr:housenumber":"11750",
    "addr:postcode":"94568",
    "addr:street":"Dublin Blvd",
    "iso:country":"US",
    "sg:address":"11750 Dublin Blvd",
    "sg:city":"Dublin",
    "sg:classifiers":[
        {
            "category":"Insurance",
            "subcategory":"Insurance Agent",
            "type":"Services"
        }
    ],
    "sg:phone":"+1 925 828 7340",
    "sg:postcode":"94568",
    "sg:province":"CA",
    "wof:name":"State Farm Insurance",
    "wof:placetype":"venue"
},
  "geometry": {"coordinates":[-121.938545,37.701121],"type":"Point"}
}