{
  "type": "Feature",
  "properties": {
    "iso:country":"US",
    "sg:address":"642 N Ben Maddox Way",
    "sg:city":"Visalia",
    "sg:classifiers":[
        {
            "category":"Retail",
            "subcategory":"Auto Repair",
            "type":"Services"
        }
    ],
    "sg:phone":"+1 559 635 0384",
    "sg:postcode":"93292",
    "sg:province":"CA",
    "sg:tags":[
        "repairing",
        "automobile"
    ],
    "wof:name":"Martin's Auto Svc",
    "wof:placetype":"venue"
},
  "geometry": {"coordinates":[-119.278723,36.33785],"type":"Point"}
}