{
  "type": "Feature",
  "properties": {
    "iso:country":"US",
    "sg:address":"189 Sir Francis Drake Blvd",
    "sg:city":"Kentfield",
    "sg:classifiers":[
        {
            "category":"Real Estate",
            "subcategory":"Real Estate Agent",
            "type":"Services"
        }
    ],
    "sg:phone":"+1 415 460 0600",
    "sg:postcode":"94904",
    "sg:province":"CA",
    "wof:name":"Swift & Swift",
    "wof:placetype":"venue"
},
  "geometry": {"coordinates":[-122.520006,37.945557],"type":"Point"}
}