{
  "type": "Feature",
  "properties": {
    "addr:full":"2450 Fountain Ave South Lake Tahoe CA 96150",
    "addr:housenumber":"2450",
    "addr:postcode":"96150",
    "addr:street":"Fountain Ave",
    "iso:country":"US",
    "sg:address":"2450 Fountain Ave",
    "sg:city":"South Lake Tahoe",
    "sg:classifiers":[
        {
            "category":"Shopping",
            "subcategory":"Hobbies, Toys, & Games",
            "type":"Retail Goods"
        }
    ],
    "sg:phone":"+1 530 541 4984",
    "sg:postcode":"96150",
    "sg:province":"CA",
    "sg:tags":[
        "craft"
    ],
    "wof:name":"Creative Crafts",
    "wof:placetype":"venue"
},
  "geometry": {"coordinates":[-119.98227,38.916782],"type":"Point"}
}