{
  "type": "Feature",
  "properties": {
    "iso:country":"US",
    "sg:address":"631 Fulton Ave",
    "sg:city":"Sacramento",
    "sg:classifiers":[
        {
            "category":"Health Services",
            "subcategory":"Doctor",
            "type":"Services"
        }
    ],
    "sg:phone":"+1 415 561 1310",
    "sg:postcode":"95825",
    "sg:province":"CA",
    "sg:website":"www.lapsf.com",
    "wof:name":"Laparoscopic Associates of San Francisco",
    "wof:placetype":"venue"
},
  "geometry": {"coordinates":[-121.40338300000001,38.576383],"type":"Point"}
}