{
  "type": "Feature",
  "properties": {
    "iso:country":"US",
    "sg:address":"11445 Paramount Blvd",
    "sg:city":"Downey",
    "sg:classifiers":[
        {
            "category":"Real Estate",
            "subcategory":"Real Estate Services",
            "type":"Services"
        }
    ],
    "sg:phone":"+1 562 869 1919",
    "sg:postcode":"90241",
    "sg:province":"CA",
    "sg:website":"www.amybrick.com",
    "wof:name":"Brick Amy Realtor",
    "wof:placetype":"venue"
},
  "geometry": {"coordinates":[-118.139,33.940899],"type":"Point"}
}