{
  "type": "Feature",
  "properties": {
    "addr:full":"436 Windflower Ln Placentia CA 92870",
    "addr:housenumber":"436",
    "addr:postcode":"ca 92870",
    "addr:street":"Windflower Ln",
    "iso:country":"US",
    "sg:address":"436 Windflower Ln",
    "sg:city":"Placentia",
    "sg:classifiers":[
        {
            "category":"Professional",
            "type":"Services"
        }
    ],
    "sg:phone":"+1 714 572 2312",
    "sg:postcode":"92870",
    "sg:province":"CA",
    "wof:name":"Chimotherapy & Naturopath",
    "wof:placetype":"venue"
},
  "geometry": {"coordinates":[-117.860838,33.878739],"type":"Point"}
}