{
  "type": "Feature",
  "properties": {
    "addr:full":"1515 Clay St Oakland CA 94612",
    "addr:housenumber":"1515",
    "addr:postcode":"94612",
    "addr:street":"Clay St",
    "iso:country":"US",
    "sg:address":"1515 Clay St",
    "sg:city":"Oakland",
    "sg:classifiers":[
        {
            "category":"Government",
            "subcategory":"Office",
            "type":"Public Place"
        }
    ],
    "sg:phone":"+1 510 622 2861",
    "sg:postcode":"94612",
    "sg:province":"CA",
    "wof:name":"California Workers Cmpnstn",
    "wof:placetype":"venue"
},
  "geometry": {"coordinates":[-122.27286700000001,37.806551],"type":"Point"}
}