{
  "type": "Feature",
  "properties": {
    "addr:full":"2621 Merion Dr San Bruno CA 94066",
    "addr:housenumber":"2621",
    "addr:postcode":"94066",
    "addr:street":"Merion Dr",
    "iso:country":"US",
    "sg:address":"2621 Merion Dr",
    "sg:city":"San Bruno",
    "sg:classifiers":[
        {
            "category":"Building & Trades",
            "subcategory":"Construction",
            "type":"Services"
        }
    ],
    "sg:phone":"+1 650 873 8446",
    "sg:postcode":"94066",
    "sg:province":"CA",
    "sg:tags":[
        "roofing",
        "contractor"
    ],
    "wof:name":"K & J Roofing",
    "wof:placetype":"venue"
},
  "geometry": {"coordinates":[-122.454583,37.633852],"type":"Point"}
}