{
  "type": "Feature",
  "properties": {
    "iso:country":"US",
    "sg:address":"2191 Whittier Blvd",
    "sg:city":"Los Angeles",
    "sg:classifiers":[
        {
            "category":"Shopping",
            "subcategory":"Music",
            "type":"Retail Goods"
        }
    ],
    "sg:phone":"+1 323 262 3735",
    "sg:postcode":"90023",
    "sg:province":"CA",
    "sg:tags":[
        "video",
        "disc",
        "tape",
        "cassette"
    ],
    "wof:name":"Tele-Video",
    "wof:placetype":"venue"
},
  "geometry": {"coordinates":[-118.219771,34.036213],"type":"Point"}
}