{
  "type": "Feature",
  "properties": {
    "iso:country":"US",
    "sg:address":"309 Lowell Ln W",
    "sg:city":"Lafayette",
    "sg:classifiers":[
        {
            "category":"Professional",
            "subcategory":"Management & Consulting",
            "type":"Services"
        }
    ],
    "sg:phone":"+1 925 284 1878",
    "sg:postcode":"94549",
    "sg:province":"CA",
    "sg:tags":[
        "consultant",
        "business"
    ],
    "wof:name":"Kurt J Fraenkel",
    "wof:placetype":"venue"
},
  "geometry": {"coordinates":[-122.089516,37.859869],"type":"Point"}
}