{
  "type": "Feature",
  "properties": {
    "addr:full":"531 Commercial Way La Habra CA 90631",
    "addr:housenumber":"531",
    "addr:postcode":"90631",
    "addr:street":"Commercial Way",
    "iso:country":"US",
    "sg:address":"531 Commercial Way",
    "sg:city":"La Habra",
    "sg:classifiers":[
        {
            "category":"Retail",
            "subcategory":"Car Wash",
            "type":"Services"
        }
    ],
    "sg:phone":"+1 562 691 8484",
    "sg:postcode":"90631",
    "sg:province":"CA",
    "sg:tags":[
        "automobile",
        "detail",
        "clean"
    ],
    "wof:name":"Gorilla's Polishing",
    "wof:placetype":"venue"
},
  "geometry": {"coordinates":[-117.941236,33.927146],"type":"Point"}
}