{
  "type": "Feature",
  "properties": {
    "addr:full":"2912 Telegraph Rd Ventura CA 93003",
    "addr:housenumber":"2912",
    "addr:postcode":"93003",
    "addr:street":"Telegraph Rd",
    "iso:country":"US",
    "sg:address":"2912 Telegraph Rd",
    "sg:city":"Ventura",
    "sg:classifiers":[
        {
            "category":"Retail",
            "subcategory":"Car Wash",
            "type":"Services"
        }
    ],
    "sg:phone":"+1 805 643 7715",
    "sg:postcode":"93003",
    "sg:province":"CA",
    "sg:tags":[
        "polishing",
        "washing"
    ],
    "wof:name":"Five Points Car Wash",
    "wof:placetype":"venue"
},
  "geometry": {"coordinates":[-119.25577699999999,34.271829],"type":"Point"}
}