{
  "type": "Feature",
  "properties": {
    "iso:country":"US",
    "sg:address":"7911 Laguna Blvd",
    "sg:city":"Elk Grove",
    "sg:classifiers":[
        {
            "category":"Health Services",
            "subcategory":"Doctor",
            "type":"Services"
        }
    ],
    "sg:phone":"+1 916 733 5801",
    "sg:postcode":"95758",
    "sg:province":"CA",
    "sg:tags":[
        "physician",
        "surgeon"
    ],
    "wof:name":"Sean Nealon MD",
    "wof:placetype":"venue"
},
  "geometry": {"coordinates":[-121.40062500000001,38.422859],"type":"Point"}
}