{
  "type": "Feature",
  "properties": {
    "iso:country":"US",
    "sg:address":"2542 Montrose Ave",
    "sg:city":"Montrose",
    "sg:classifiers":[
        {
            "category":"Shopping",
            "subcategory":"Florist",
            "type":"Retail Goods"
        }
    ],
    "sg:phone":"+1 626 379 7030",
    "sg:postcode":"91020",
    "sg:province":"CA",
    "wof:name":"Trident Technology",
    "wof:placetype":"venue"
},
  "geometry": {"coordinates":[-118.234095,34.212332],"type":"Point"}
}