{
  "type": "Feature",
  "properties": {
    "iso:country":"US",
    "sg:address":"13645 Vanowen St",
    "sg:city":"Van Nuys",
    "sg:classifiers":[
        {
            "category":"Shopping",
            "subcategory":"Clothing, Apparel, & Fashions",
            "type":"Retail Goods"
        }
    ],
    "sg:phone":"+1 818 780 2557",
    "sg:postcode":"91405",
    "sg:province":"CA",
    "sg:tags":[
        "accessory",
        "clothing",
        "women's"
    ],
    "wof:name":"Designers collection",
    "wof:placetype":"venue"
},
  "geometry": {"coordinates":[-118.429472,34.194077],"type":"Point"}
}