{
  "type": "Feature",
  "properties": {
    "iso:country":"US",
    "sg:address":"7934 Clybourn Ave",
    "sg:city":"Sun Valley",
    "sg:classifiers":[
        {
            "category":"Communications",
            "subcategory":"Film & Video Production",
            "type":"Services"
        }
    ],
    "sg:phone":"+1 818 768 7260",
    "sg:postcode":"91352",
    "sg:province":"CA",
    "sg:tags":[
        "motion",
        "picture",
        "studio",
        "producer"
    ],
    "wof:name":"Krell Wonders Special Effects",
    "wof:placetype":"venue"
},
  "geometry": {"coordinates":[-118.364173,34.215066],"type":"Point"}
}