{
  "type": "Feature",
  "properties": {
    "addr:full":"6160 Bollinger Road San Jose CA 95129",
    "addr:housenumber":"6160",
    "addr:postcode":"95129",
    "addr:street":"Bollinger Road",
    "iso:country":"US",
    "sg:address":"6160 Bollinger Road",
    "sg:city":"San Jose",
    "sg:classifiers":[
        {
            "category":"Health Services",
            "subcategory":"Dentist",
            "type":"Services"
        }
    ],
    "sg:phone":"+1 408 446 3200",
    "sg:postcode":"95129",
    "sg:province":"CA",
    "wof:name":"Nazar Dental",
    "wof:placetype":"venue"
},
  "geometry": {"coordinates":[-122.011661,37.310608],"type":"Point"}
}