{
  "type": "Feature",
  "properties": {
    "iso:country":"US",
    "sg:address":"865 3rd Ave",
    "sg:city":"Chula Vista",
    "sg:classifiers":[
        {
            "category":"Health Services",
            "subcategory":"Doctor",
            "type":"Services"
        }
    ],
    "sg:phone":"+1 619 426 3400",
    "sg:postcode":"91911",
    "sg:province":"CA",
    "sg:tags":[
        "physician",
        "surgeon"
    ],
    "wof:name":"Advanced Eye Care",
    "wof:placetype":"venue"
},
  "geometry": {"coordinates":[-117.073026,32.624001],"type":"Point"}
}