{
  "type": "Feature",
  "properties": {
    "addr:full":"969 W State St Ontario CA 91762",
    "addr:housenumber":"969",
    "addr:postcode":"91762",
    "addr:street":"W State St",
    "iso:country":"US",
    "sg:address":"969 W State St",
    "sg:city":"Ontario",
    "sg:classifiers":[
        {
            "category":"Manufacturing",
            "subcategory":"Building Materials",
            "type":"Manufacturing & Wholesale Goods"
        }
    ],
    "sg:phone":"+1 909 923 1292",
    "sg:postcode":"91762",
    "sg:province":"CA",
    "sg:tags":[
        "mfg",
        "wood",
        "kitchen",
        "cabinet"
    ],
    "wof:name":"Kc Custom Cabinet Manufacturer",
    "wof:placetype":"venue"
},
  "geometry": {"coordinates":[-117.664948,34.05987],"type":"Point"}
}