{
  "type": "Feature",
  "properties": {
    "iso:country":"US",
    "sg:address":"20452 James Bay Cir",
    "sg:city":"Lake Forest",
    "sg:classifiers":[
        {
            "category":"Professional",
            "subcategory":"Advertising",
            "type":"Services"
        }
    ],
    "sg:phone":"+1 949 340 8920",
    "sg:postcode":"92630",
    "sg:province":"CA",
    "sg:tags":[
        "mailing",
        "shipping"
    ],
    "wof:name":"Super Source Direct",
    "wof:placetype":"venue"
},
  "geometry": {"coordinates":[-117.677575,33.666273],"type":"Point"}
}