{
  "type": "Feature",
  "properties": {
    "addr:full":"2550 23rd St San Francisco CA 94110",
    "addr:housenumber":"2550",
    "addr:postcode":"94110",
    "addr:street":"23Rd St",
    "iso:country":"US",
    "sg:address":"2550 23rd St",
    "sg:city":"San Francisco",
    "sg:classifiers":[
        {
            "category":"Professional",
            "subcategory":"Research",
            "type":"Services"
        }
    ],
    "sg:phone":"+1 415 826 7500",
    "sg:postcode":"94110",
    "sg:province":"CA",
    "sg:tags":[
        "development",
        "laboratory"
    ],
    "sg:website":"www.gladstone.ucsf.edu",
    "wof:name":"Gladstone Institutes",
    "wof:placetype":"venue"
},
  "geometry": {"coordinates":[-122.40463699999999,37.754468],"type":"Point"}
}