{
  "type": "Feature",
  "properties": {
    "iso:country":"US",
    "sg:address":"Swords Fencing Studio 2115 North Glenoaks Blvd.",
    "sg:city":"Burbank",
    "sg:classifiers":[
        {
            "category":"Arts & Performance",
            "subcategory":"Arts Center",
            "type":"Entertainment"
        },
        {
            "category":"Education",
            "subcategory":"Special Training",
            "type":"Public Place"
        }
    ],
    "sg:phone":"+1 818 364 8420",
    "sg:postcode":"91504",
    "sg:province":"CA",
    "sg:tags":[
        "school",
        "performing",
        "specialty"
    ],
    "sg:website":"www.theatricalcombat.com",
    "wof:name":"Academy of Theatrical Combat",
    "wof:placetype":"venue"
},
  "geometry": {"coordinates":[-118.326832,34.19791],"type":"Point"}
}