{
  "type": "Feature",
  "properties": {
    "iso:country":"US",
    "sg:address":"83256 Indio Blvd",
    "sg:city":"Indio",
    "sg:classifiers":[
        {
            "category":"Building & Trades",
            "subcategory":"Construction",
            "type":"Services"
        }
    ],
    "sg:phone":"+1 760 775 3744",
    "sg:postcode":"92201",
    "sg:province":"CA",
    "sg:tags":[
        "company"
    ],
    "sg:website":"www.brodiecabinets.com",
    "wof:name":"Brodie G Construction",
    "wof:placetype":"venue"
},
  "geometry": {"coordinates":[-116.212035,33.717853],"type":"Point"}
}