{
  "type": "Feature",
  "properties": {
    "addr:full":"1344 Glenwood Rd Glendale CA 91201",
    "addr:housenumber":"1344",
    "addr:postcode":"91201",
    "addr:street":"Glenwood Rd",
    "iso:country":"US",
    "sg:address":"1344 Glenwood Rd",
    "sg:city":"Glendale",
    "sg:classifiers":[
        {
            "category":"Building & Trades",
            "subcategory":"Electrical",
            "type":"Services"
        }
    ],
    "sg:phone":"+1 818 500 1188",
    "sg:postcode":"91201",
    "sg:province":"CA",
    "sg:tags":[
        "telecommunication",
        "contractor"
    ],
    "wof:name":"Advanced Communications",
    "wof:placetype":"venue"
},
  "geometry": {"coordinates":[-118.28131,34.168998],"type":"Point"}
}