{
  "type": "Feature",
  "properties": {
    "addr:full":"2460 Dayton St Santa Rosa CA 95403",
    "addr:housenumber":"2460",
    "addr:postcode":"ca 95403",
    "addr:street":"Dayton St",
    "iso:country":"US",
    "sg:address":"2460 Dayton St",
    "sg:city":"Santa Rosa",
    "sg:classifiers":[
        {
            "category":"Professional",
            "type":"Services"
        }
    ],
    "sg:phone":"+1 707 569 7590",
    "sg:postcode":"95403",
    "sg:province":"CA",
    "wof:name":"Auroras Gems",
    "wof:placetype":"venue"
},
  "geometry": {"coordinates":[-122.767785,38.46872],"type":"Point"}
}