{
  "type": "Feature",
  "properties": {
    "addr:full":"3025 Industry St Oceanside CA 92054",
    "addr:housenumber":"3025",
    "addr:postcode":"92054",
    "addr:street":"Industry St",
    "iso:country":"US",
    "sg:address":"3025 Industry St",
    "sg:city":"Oceanside",
    "sg:classifiers":[
        {
            "category":"Manufacturing",
            "subcategory":"Tools & Machinery",
            "type":"Manufacturing & Wholesale Goods"
        }
    ],
    "sg:phone":"+1 760 439 1700",
    "sg:postcode":"92054",
    "sg:province":"CA",
    "sg:tags":[
        "physician",
        "surgeon"
    ],
    "wof:name":"Clinicon Corp",
    "wof:placetype":"venue"
},
  "geometry": {"coordinates":[-117.332804,33.200384],"type":"Point"}
}