{
  "type": "Feature",
  "properties": {
    "addr:full":"499 Embarcadero Ste 2-16 Oakland CA 94606",
    "addr:housenumber":"499",
    "addr:postcode":"94606",
    "addr:street":"Embarcadero Ste 2-16",
    "iso:country":"US",
    "sg:address":"499 Embarcadero Ste 2-16",
    "sg:city":"Oakland",
    "sg:classifiers":[
        {
            "category":"Professional",
            "subcategory":"Management & Consulting",
            "type":"Services"
        }
    ],
    "sg:phone":"+1 510 465 2533",
    "sg:postcode":"94606",
    "sg:province":"CA",
    "sg:tags":[
        "counselor",
        "relation",
        "public"
    ],
    "wof:name":"Low Tech Ink",
    "wof:placetype":"venue"
},
  "geometry": {"coordinates":[-122.26007799999999,37.790112],"type":"Point"}
}