{
  "type": "Feature",
  "properties": {
    "iso:country":"US",
    "sg:address":"100 S. Ellsworth Ave Suite #707",
    "sg:city":"San Mateo",
    "sg:classifiers":[
        {
            "category":"Health Services",
            "subcategory":"Doctor",
            "type":"Services"
        }
    ],
    "sg:phone":"+1 650 348 1242",
    "sg:postcode":"94401",
    "sg:province":"CA",
    "sg:tags":[
        "dermatologist"
    ],
    "sg:website":"www.susanwolfmd.com",
    "wof:name":"Dr. Lynn Sydor",
    "wof:placetype":"venue"
},
  "geometry": {"coordinates":[-122.32546600000001,37.566368],"type":"Point"}
}