{
  "type": "Feature",
  "properties": {
    "iso:country":"US",
    "sg:address":"1607 5th St",
    "sg:city":"Eureka",
    "sg:classifiers":[
        {
            "category":"Retail",
            "subcategory":"Auto Repair",
            "type":"Services"
        }
    ],
    "sg:phone":"+1 707 445 2097",
    "sg:postcode":"95501",
    "sg:province":"CA",
    "sg:tags":[
        "transmission"
    ],
    "wof:name":"AAMCO Transmissions",
    "wof:placetype":"venue"
},
  "geometry": {"coordinates":[-124.153679,40.803943],"type":"Point"}
}