{
  "type": "Feature",
  "properties": {
    "iso:country":"US",
    "sg:address":"2025 E 7th St",
    "sg:city":"Long Beach",
    "sg:classifiers":[
        {
            "category":"Manufacturing",
            "subcategory":"Printing",
            "type":"Manufacturing & Wholesale Goods"
        }
    ],
    "sg:phone":"+1 562 433 2252",
    "sg:postcode":"90804",
    "sg:province":"CA",
    "sg:tags":[
        "lithographic"
    ],
    "wof:name":"A T Morgan Printing",
    "wof:placetype":"venue"
},
  "geometry": {"coordinates":[-118.167309,33.775419],"type":"Point"}
}