{
  "type": "Feature",
  "properties": {
    "iso:country":"US",
    "sg:address":"22365 El Toro Box 229",
    "sg:city":"Lake Forest",
    "sg:classifiers":[
        {
            "category":"Personal",
            "type":"Services"
        },
        {
            "category":"Building & Trades",
            "subcategory":"Pest Control",
            "type":"Services"
        }
    ],
    "sg:phone":"+1 949 716 2276",
    "sg:postcode":"92630",
    "sg:province":"CA",
    "sg:tags":[
        "home"
    ],
    "sg:website":"www.buzzoffbees.com/",
    "wof:name":"Buzz-Off Bee Removal Services",
    "wof:placetype":"venue"
},
  "geometry": {"coordinates":[-117.679579,33.637497],"type":"Point"}
}