{
  "type": "Feature",
  "properties": {
    "iso:country":"US",
    "sg:address":"324 Clement St",
    "sg:city":"San Francisco",
    "sg:classifiers":[
        {
            "category":"Food & Beverages",
            "subcategory":"Specialty",
            "type":"Retail Goods"
        }
    ],
    "sg:phone":"+1 415 666 3668",
    "sg:postcode":"94118",
    "sg:province":"CA",
    "sg:tags":[
        "herb",
        "ethnic"
    ],
    "sg:website":"www.chungchoucity.com",
    "wof:name":"Chung Chou City",
    "wof:placetype":"venue"
},
  "geometry": {"coordinates":[-122.46257900000001,37.783053],"type":"Point"}
}