{
  "type": "Feature",
  "properties": {
    "addr:full":"333 Old Newport Blvd Newport Beach CA 92663",
    "addr:housenumber":"333",
    "addr:postcode":"92663",
    "addr:street":"Old Newport Blvd",
    "iso:country":"US",
    "sg:address":"333 Old Newport Blvd",
    "sg:city":"Newport Beach",
    "sg:classifiers":[
        {
            "category":"Personal",
            "subcategory":"Beauty Salon",
            "type":"Services"
        }
    ],
    "sg:phone":"+1 949 722 3526",
    "sg:postcode":"92663",
    "sg:province":"CA",
    "sg:tags":[
        "hair"
    ],
    "wof:name":"Newport Heights Salon",
    "wof:placetype":"venue"
},
  "geometry": {"coordinates":[-117.927938,33.623923],"type":"Point"}
}