{
  "type": "Feature",
  "properties": {
    "addr:full":"1319 Westway Dr Woodland CA 95695",
    "addr:housenumber":"1319",
    "addr:postcode":"95695",
    "addr:street":"Westway Dr",
    "iso:country":"US",
    "sg:address":"1319 Westway Dr",
    "sg:city":"Woodland",
    "sg:classifiers":[
        {
            "category":"Building & Trades",
            "subcategory":"Construction",
            "type":"Services"
        }
    ],
    "sg:phone":"+1 530 662 8007",
    "sg:postcode":"95695",
    "sg:province":"CA",
    "sg:tags":[
        "nonresidential"
    ],
    "wof:name":"Buchignani & Sons",
    "wof:placetype":"venue"
},
  "geometry": {"coordinates":[-121.78572800000001,38.663306],"type":"Point"}
}