{
  "type": "Feature",
  "properties": {
    "iso:country":"US",
    "sg:address":"2114 Howard Ave",
    "sg:city":"San Carlos",
    "sg:classifiers":[
        {
            "category":"Shopping",
            "subcategory":"Photographic Equipment",
            "type":"Retail Goods"
        }
    ],
    "sg:phone":"+1 650 592 8049",
    "sg:postcode":"94070",
    "sg:province":"CA",
    "sg:tags":[
        "supply"
    ],
    "wof:name":"Creative Memories",
    "wof:placetype":"venue"
},
  "geometry": {"coordinates":[-122.259396,37.493411],"type":"Point"}
}