{
  "type": "Feature",
  "properties": {
    "iso:country":"US",
    "sg:address":"5076 Santa Fe St Ste D",
    "sg:city":"San Diego",
    "sg:classifiers":[
        {
            "category":"Building & Trades",
            "subcategory":"Construction",
            "type":"Services"
        },
        {
            "category":"Home & Garden",
            "subcategory":"Furniture",
            "type":"Retail Goods"
        }
    ],
    "sg:phone":"+1 858 490 2211",
    "sg:postcode":"92109",
    "sg:province":"CA",
    "sg:tags":[
        "interior",
        "design",
        "store"
    ],
    "wof:name":"Home Garden Imports",
    "wof:placetype":"venue"
},
  "geometry": {"coordinates":[-117.220707,32.815274],"type":"Point"}
}