{
  "type": "Feature",
  "properties": {
    "addr:full":"717 Washington St Oakland CA 94607",
    "addr:housenumber":"717",
    "addr:postcode":"94607",
    "addr:street":"Washington St",
    "iso:country":"US",
    "sg:address":"717 Washington St",
    "sg:city":"Oakland",
    "sg:classifiers":[
        {
            "category":"Professional",
            "subcategory":"Engineering",
            "type":"Services"
        },
        {
            "category":"Home & Garden",
            "subcategory":"Building Materials",
            "type":"Retail Goods"
        }
    ],
    "sg:phone":"+1 510 451 4075",
    "sg:postcode":"94607",
    "sg:province":"CA",
    "sg:tags":[
        "insulation",
        "consultant",
        "product",
        "conservation",
        "energy"
    ],
    "wof:name":"Alliance to Save Energy",
    "wof:placetype":"venue"
},
  "geometry": {"coordinates":[-122.275346,37.800109],"type":"Point"}
}