{
  "type": "Feature",
  "properties": {
    "addr:full":"480 San Anselmo Ave N San Bruno CA 94066",
    "addr:housenumber":"480",
    "addr:postcode":"94066",
    "addr:street":"San Anselmo Ave N",
    "iso:country":"US",
    "sg:address":"480 San Anselmo Ave N",
    "sg:city":"San Bruno",
    "sg:classifiers":[
        {
            "category":"Organizations",
            "subcategory":"Religious Organization",
            "type":"Services"
        }
    ],
    "sg:phone":"+1 650 588 4972",
    "sg:postcode":"94066",
    "sg:province":"CA",
    "sg:tags":[
        "church"
    ],
    "wof:name":"St John's United Church",
    "wof:placetype":"venue"
},
  "geometry": {"coordinates":[-122.409706,37.623082],"type":"Point"}
}