{
  "type": "Feature",
  "properties": {
    "iso:country":"US",
    "sg:address":"1500 Rosecrans Ave Ste 200",
    "sg:city":"Manhattan Beach",
    "sg:classifiers":[
        {
            "category":"Health Services",
            "subcategory":"Clinic",
            "type":"Services"
        },
        {
            "category":"Organizations",
            "subcategory":"Non-profit Organization",
            "type":"Services"
        }
    ],
    "sg:phone":"+1 877 272 6226",
    "sg:postcode":"90266",
    "sg:province":"CA",
    "sg:tags":[
        "medical",
        "service/non-profit",
        "community"
    ],
    "sg:website":"www.pancan.org",
    "wof:name":"Pancreatic Cancer Action Network",
    "wof:placetype":"venue"
},
  "geometry": {"coordinates":[-118.387501,33.901216],"type":"Point"}
}