{
  "type": "Feature",
  "properties": {
    "addr:full":"25710 Barton Rd Loma Linda CA 92354",
    "addr:housenumber":"25710",
    "addr:postcode":"92354",
    "addr:street":"Barton Rd",
    "iso:country":"US",
    "sg:address":"25710 Barton Rd",
    "sg:city":"Loma Linda",
    "sg:classifiers":[
        {
            "category":"Shopping",
            "subcategory":"Pharmacy",
            "type":"Retail Goods"
        }
    ],
    "sg:phone":"+1 909 799 6521",
    "sg:postcode":"92354",
    "sg:province":"CA",
    "sg:tags":[
        "photofinishing",
        "laboratory"
    ],
    "wof:name":"Rite Aid",
    "wof:placetype":"venue"
},
  "geometry": {"coordinates":[-117.23858799999999,34.048441],"type":"Point"}
}