{
  "type": "Feature",
  "properties": {
    "addr:full":"302 Hollister Street San Diego CA 92154",
    "addr:housenumber":"302",
    "addr:postcode":"92154",
    "addr:street":"Hollister Street",
    "iso:country":"US",
    "sg:address":"302 Hollister Street",
    "sg:city":"San Diego",
    "sg:classifiers":[
        {
            "category":"Home & Garden",
            "subcategory":"Garden Supply",
            "type":"Retail Goods"
        }
    ],
    "sg:phone":"+1 619 585 1118",
    "sg:postcode":"92154",
    "sg:province":"CA",
    "sg:tags":[
        "nursery",
        "gardening"
    ],
    "sg:website":"www.terrabellanursery.com/",
    "wof:name":"Terra Bella Nursery",
    "wof:placetype":"venue"
},
  "geometry": {"coordinates":[-117.08719499999999,32.592446],"type":"Point"}
}