{
  "type": "Feature",
  "properties": {
    "iso:country":"US",
    "sg:address":"9449 Main St",
    "sg:city":"Upper Lake",
    "sg:classifiers":[
        {
            "category":"Personal",
            "subcategory":"Beauty Salon",
            "type":"Services"
        }
    ],
    "sg:phone":"+1 707 275 2606",
    "sg:postcode":"95485",
    "sg:province":"CA",
    "wof:name":"B J's Beauty Boutique",
    "wof:placetype":"venue"
},
  "geometry": {"coordinates":[-122.91102600000001,39.164049],"type":"Point"}
}