{
  "type": "Feature",
  "properties": {
    "iso:country":"US",
    "sg:address":"2468 Balmoral St",
    "sg:city":"Union City",
    "sg:classifiers":[
        {
            "category":"Building & Trades",
            "subcategory":"Construction",
            "type":"Services"
        }
    ],
    "sg:phone":"+1 510 324 8254",
    "sg:postcode":"94587",
    "sg:province":"CA",
    "sg:tags":[
        "floor",
        "laying",
        "contractor"
    ],
    "wof:name":"Flooring Unlimited",
    "wof:placetype":"venue"
},
  "geometry": {"coordinates":[-122.05792700000001,37.601459],"type":"Point"}
}