{
  "type": "Feature",
  "properties": {
    "addr:full":"11181 Baker Rd Stockton CA 95215",
    "addr:housenumber":"11181",
    "addr:postcode":"95215",
    "addr:street":"Baker Rd",
    "iso:country":"US",
    "sg:address":"11181 Baker Rd",
    "sg:city":"Stockton",
    "sg:classifiers":[
        {
            "category":"Farming",
            "subcategory":"Crops",
            "type":"Manufacturing & Wholesale Goods"
        }
    ],
    "sg:phone":"+1 209 931 6524",
    "sg:postcode":"95215",
    "sg:province":"CA",
    "sg:tags":[
        "grove",
        "nut",
        "fruit",
        "tree",
        "orchard"
    ],
    "wof:name":"Bill Caminata Farms",
    "wof:placetype":"venue"
},
  "geometry": {"coordinates":[-121.178738,38.029085],"type":"Point"}
}