{
  "type": "Feature",
  "properties": {
    "addr:full":"22759 Hawthorne Blvd Torrance CA 90505",
    "addr:housenumber":"22759",
    "addr:postcode":"90505",
    "addr:street":"Hawthorne Blvd",
    "iso:country":"US",
    "sg:address":"22759 Hawthorne Blvd",
    "sg:city":"Torrance",
    "sg:classifiers":[
        {
            "category":"Health Services",
            "subcategory":"Dentist",
            "type":"Services"
        }
    ],
    "sg:phone":"+1 310 373 9522",
    "sg:postcode":"90505",
    "sg:province":"CA",
    "sg:tags":[
        "pediatric"
    ],
    "wof:name":"Catalan Beaverly Grace DMD",
    "wof:placetype":"venue"
},
  "geometry": {"coordinates":[-118.350998,33.821301],"type":"Point"}
}