{
  "type": "Feature",
  "properties": {
    "addr:full":"200 Hartz Ave Danville CA 94526",
    "addr:housenumber":"200",
    "addr:postcode":"94526",
    "addr:street":"Hartz Ave",
    "iso:country":"US",
    "sg:address":"200 Hartz Ave",
    "sg:city":"Danville",
    "sg:classifiers":[
        {
            "category":"Professional",
            "subcategory":"Business Services",
            "type":"Services"
        }
    ],
    "sg:phone":"+1 925 837 7393",
    "sg:postcode":"94526",
    "sg:province":"CA",
    "sg:tags":[
        "interior",
        "consultant",
        "design",
        "decorator"
    ],
    "wof:name":"Jerron West Inc",
    "wof:placetype":"venue"
},
  "geometry": {"coordinates":[-122.00148799999999,37.823209],"type":"Point"}
}