{
  "type": "Feature",
  "properties": {
    "addr:full":"5252 orange ave. Cypress CA 90630",
    "addr:housenumber":"5252",
    "addr:postcode":"90630",
    "addr:street":"Orange Ave.",
    "iso:country":"US",
    "sg:address":"5252 orange ave.",
    "sg:city":"Cypress",
    "sg:classifiers":[
        {
            "category":"Education",
            "subcategory":"Special Training",
            "type":"Public Place"
        }
    ],
    "sg:postcode":"90630",
    "sg:province":"CA",
    "sg:tags":[
        "tutoring"
    ],
    "sg:website":"www.mathonauts.com",
    "wof:name":"mathonauts tutoring",
    "wof:placetype":"venue"
},
  "geometry": {"coordinates":[-118.040657,33.823773],"type":"Point"}
}