{
  "type": "Feature",
  "properties": {
    "iso:country":"US",
    "sg:address":"4625 1st St",
    "sg:city":"Pleasanton",
    "sg:classifiers":[
        {
            "category":"Professional",
            "subcategory":"Business Services",
            "type":"Services"
        }
    ],
    "sg:phone":"+1 925 484 1400",
    "sg:postcode":"94566",
    "sg:province":"CA",
    "sg:tags":[
        "interior",
        "consultant",
        "design",
        "decorator"
    ],
    "wof:name":"Design Place",
    "wof:placetype":"venue"
},
  "geometry": {"coordinates":[-121.875505,37.658208],"type":"Point"}
}