{
  "type": "Feature",
  "properties": {
    "addr:full":"300 S Raymond Ave Pasadena CA 91105",
    "addr:housenumber":"300",
    "addr:postcode":"91105",
    "addr:street":"S Raymond Ave",
    "iso:country":"US",
    "sg:address":"300 S Raymond Ave",
    "sg:city":"Pasadena",
    "sg:classifiers":[
        {
            "category":"Shopping",
            "subcategory":"Clothing, Apparel, & Fashions",
            "type":"Retail Goods"
        }
    ],
    "sg:phone":"+1 626 578 0787",
    "sg:postcode":"91105",
    "sg:province":"CA",
    "sg:tags":[
        "t"
    ],
    "wof:name":"Maverick Embroidery Programs",
    "wof:placetype":"venue"
},
  "geometry": {"coordinates":[-118.148787,34.143387],"type":"Point"}
}