{
  "type": "Feature",
  "properties": {
    "iso:country":"US",
    "sg:address":"1453 Hollow Glen Rd",
    "sg:city":"Julian",
    "sg:classifiers":[
        {
            "category":"Manufacturing",
            "subcategory":"Printing",
            "type":"Manufacturing & Wholesale Goods"
        }
    ],
    "sg:phone":"+1 760 765 2231",
    "sg:postcode":"92036",
    "sg:province":"CA",
    "sg:tags":[
        "newspaper"
    ],
    "wof:name":"Julian News",
    "wof:placetype":"venue"
},
  "geometry": {"coordinates":[-116.590305,33.076287],"type":"Point"}
}