{
  "type": "Feature",
  "properties": {
    "addr:full":"2420 California St Stockton CA 95206",
    "addr:housenumber":"2420",
    "addr:postcode":"95206",
    "addr:street":"California St",
    "iso:country":"US",
    "sg:address":"2420 California St",
    "sg:city":"Stockton",
    "sg:classifiers":[
        {
            "category":"Manufacturing",
            "subcategory":"Metals",
            "type":"Manufacturing & Wholesale Goods"
        }
    ],
    "sg:phone":"+1 209 464 9474",
    "sg:postcode":"95206",
    "sg:province":"CA",
    "sg:tags":[
        "steel"
    ],
    "wof:name":"Pacific Steel Fabrication",
    "wof:placetype":"venue"
},
  "geometry": {"coordinates":[-121.277479,37.924724],"type":"Point"}
}