{
  "type": "Feature",
  "properties": {
    "iso:country":"US",
    "sg:address":"495 S Riverside Ave",
    "sg:city":"Rialto",
    "sg:classifiers":[
        {
            "category":"Building & Trades",
            "subcategory":"Landscaping Services",
            "type":"Services"
        }
    ],
    "sg:phone":"+1 909 421 8972",
    "sg:postcode":"92376",
    "sg:province":"CA",
    "wof:name":"Fedel Gardening Services",
    "wof:placetype":"venue"
},
  "geometry": {"coordinates":[-117.370288,34.094037],"type":"Point"}
}