{
  "type": "Feature",
  "properties": {
    "iso:country":"US",
    "sg:address":"4364 Bonita Rd",
    "sg:city":"Bonita",
    "sg:classifiers":[
        {
            "category":"Organizations",
            "subcategory":"Professional Association",
            "type":"Services"
        }
    ],
    "sg:phone":"+1 858 546 4400",
    "sg:postcode":"91902",
    "sg:province":"CA",
    "wof:name":"Mazdaznan Elector",
    "wof:placetype":"venue"
},
  "geometry": {"coordinates":[-117.03162,32.661102],"type":"Point"}
}