{
  "type": "Feature",
  "properties": {
    "iso:country":"US",
    "sg:address":"18531 Devonshire St",
    "sg:city":"Northridge",
    "sg:classifiers":[
        {
            "category":"Restaurant",
            "type":"Food & Drink"
        }
    ],
    "sg:phone":"+1 818 832 1183",
    "sg:postcode":"91324",
    "sg:province":"CA",
    "wof:name":"Kyoto Sushi",
    "wof:placetype":"venue"
},
  "geometry": {"coordinates":[-118.540589,34.25734],"type":"Point"}
}