{
  "type": "Feature",
  "properties": {
    "iso:country":"US",
    "sg:address":"1551 W Olive Ave",
    "sg:city":"Burbank",
    "sg:classifiers":[
        {
            "category":"Shopping",
            "subcategory":"Music",
            "type":"Retail Goods"
        }
    ],
    "sg:phone":"+1 818 842 2349",
    "sg:postcode":"91506",
    "sg:province":"CA",
    "sg:tags":[
        "compact",
        "record",
        "disc",
        "tape",
        "dvd's"
    ],
    "sg:website":"www.wherehouse.com",
    "wof:name":"Wherehouse Music",
    "wof:placetype":"venue"
},
  "geometry": {"coordinates":[-118.32199900000001,34.168201],"type":"Point"}
}