{
  "type": "Feature",
  "properties": {
    "addr:full":"7360 Alta Vis La Verne CA 91750",
    "addr:housenumber":"7360",
    "addr:postcode":"91750",
    "addr:street":"Vis",
    "iso:country":"US",
    "sg:address":"7360 Alta Vis",
    "sg:city":"La Verne",
    "sg:classifiers":[
        {
            "category":"Real Estate",
            "subcategory":"Real Estate Agent",
            "type":"Services"
        }
    ],
    "sg:phone":"+1 909 596 5481",
    "sg:postcode":"91750",
    "sg:province":"CA",
    "wof:name":"Bumstead & Assoc",
    "wof:placetype":"venue"
},
  "geometry": {"coordinates":[-117.760064,34.14768],"type":"Point"}
}