{
  "type": "Feature",
  "properties": {
    "addr:full":"511 Main St Chico CA 95928",
    "addr:housenumber":"511",
    "addr:postcode":"95928",
    "addr:street":"Main St",
    "iso:country":"US",
    "sg:address":"511 Main St",
    "sg:city":"Chico",
    "sg:classifiers":[
        {
            "category":"Recreation",
            "type":"Entertainment"
        }
    ],
    "sg:phone":"+1 530 343 8966",
    "sg:postcode":"95928",
    "sg:province":"CA",
    "sg:tags":[
        "martial",
        "arts",
        "instruction"
    ],
    "wof:name":"Chico Kuk Sul Do",
    "wof:placetype":"venue"
},
  "geometry": {"coordinates":[-121.83733100000001,39.727584],"type":"Point"}
}