{
  "type": "Feature",
  "properties": {
    "iso:country":"US",
    "sg:address":"3041 E Miraloma Ave",
    "sg:city":"Anaheim",
    "sg:classifiers":[
        {
            "category":"Utilities",
            "subcategory":"Cable",
            "type":"Services"
        }
    ],
    "sg:phone":"+1 714 632 7103",
    "sg:postcode":"92806",
    "sg:province":"CA",
    "sg:tags":[
        "television"
    ],
    "sg:website":"www.adelphia.com",
    "wof:name":"Adelphia",
    "wof:placetype":"venue"
},
  "geometry": {"coordinates":[-117.86062800000001,33.857938],"type":"Point"}
}