{
  "type": "Feature",
  "properties": {
    "iso:country":"US",
    "sg:address":"5161 Soquel Dr",
    "sg:city":"Soquel",
    "sg:classifiers":[
        {
            "category":"Professional",
            "subcategory":"Management & Consulting",
            "type":"Services"
        }
    ],
    "sg:phone":"+1 831 454 9696",
    "sg:postcode":"95073",
    "sg:province":"CA",
    "sg:tags":[
        "consultant",
        "educational"
    ],
    "wof:name":"Communication-Learning Place",
    "wof:placetype":"venue"
},
  "geometry": {"coordinates":[-121.950448,36.987241],"type":"Point"}
}