{
  "type": "Feature",
  "properties": {
    "addr:full":"895 Dove St Fl 5 Newport Beach CA 92660",
    "addr:housenumber":"895;5",
    "addr:postcode":"92660",
    "addr:street":"Dove St",
    "iso:country":"US",
    "sg:address":"895 Dove St Fl 5",
    "sg:city":"Newport Beach",
    "sg:classifiers":[
        {
            "category":"Building & Trades",
            "subcategory":"Construction",
            "type":"Services"
        }
    ],
    "sg:phone":"+1 714 706 4241",
    "sg:postcode":"92660",
    "sg:province":"CA",
    "sg:tags":[
        "contractor"
    ],
    "wof:name":"T C I Builders Inc",
    "wof:placetype":"venue"
},
  "geometry": {"coordinates":[-117.864739,33.658175],"type":"Point"}
}