{
  "type": "Feature",
  "properties": {
    "iso:country":"US",
    "sg:address":"5245 Ave Encinas",
    "sg:city":"Carlsbad",
    "sg:classifiers":[
        {
            "category":"Manufacturing",
            "subcategory":"Printing",
            "type":"Manufacturing & Wholesale Goods"
        }
    ],
    "sg:phone":"+1 760 438 7971",
    "sg:postcode":"92008",
    "sg:province":"CA",
    "sg:tags":[
        "printer",
        "commercial"
    ],
    "wof:name":"Shore Line Grafix Inc",
    "wof:placetype":"venue"
},
  "geometry": {"coordinates":[-117.330062,33.132742],"type":"Point"}
}