{
  "type": "Feature",
  "properties": {
    "addr:full":"11 Maple St Salinas CA 93901",
    "addr:housenumber":"11",
    "addr:postcode":"93901",
    "addr:street":"Maple St",
    "iso:country":"US",
    "sg:address":"11 Maple St",
    "sg:city":"Salinas",
    "sg:classifiers":[
        {
            "category":"Personal",
            "type":"Services"
        }
    ],
    "sg:phone":"+1 831 224 0916",
    "sg:postcode":"93901",
    "sg:province":"CA",
    "sg:tags":[
        "counseling"
    ],
    "wof:name":"Kang Tai Ma Ncc Lmft",
    "wof:placetype":"venue"
},
  "geometry": {"coordinates":[-121.65539,36.668402],"type":"Point"}
}