{
  "type": "Feature",
  "properties": {
    "iso:country":"US",
    "sg:address":"4817 Hannover Pl",
    "sg:city":"Fremont",
    "sg:classifiers":[
        {
            "category":"Shopping",
            "subcategory":"Stationery & Office Supplies",
            "type":"Retail Goods"
        },
        {
            "category":"Wholesale",
            "subcategory":"Office Equipment",
            "type":"Manufacturing & Wholesale Goods"
        }
    ],
    "sg:phone":"+1 510 490 3375",
    "sg:postcode":"94538",
    "sg:province":"CA",
    "sg:tags":[
        "envelope",
        "store",
        "furniture"
    ],
    "wof:name":"Office Solutions Interiors Inc.",
    "wof:placetype":"venue"
},
  "geometry": {"coordinates":[-121.961876,37.506275],"type":"Point"}
}