{
  "type": "Feature",
  "properties": {
    "addr:full":"23832 Rockfield Blvd Lake Forest CA 92630",
    "addr:housenumber":"23832",
    "addr:postcode":"92630",
    "addr:street":"Rockfield Blvd",
    "iso:country":"US",
    "sg:address":"23832 Rockfield Blvd",
    "sg:city":"Lake Forest",
    "sg:classifiers":[
        {
            "category":"Wholesale",
            "subcategory":"Meat",
            "type":"Manufacturing & Wholesale Goods"
        }
    ],
    "sg:phone":"+1 949 457 9566",
    "sg:postcode":"92630",
    "sg:province":"CA",
    "sg:tags":[
        "southern",
        "california",
        "sales",
        "for",
        "manufactured"
    ],
    "wof:name":"Thorn Apple Valley",
    "wof:placetype":"venue"
},
  "geometry": {"coordinates":[-117.71611799999999,33.628282],"type":"Point"}
}