{
  "type": "Feature",
  "properties": {
    "addr:full":"2242 San Marino St Oxnard CA 93033",
    "addr:housenumber":"2242",
    "addr:postcode":"93033",
    "addr:street":"San Marino St",
    "iso:country":"US",
    "sg:address":"2242 San Marino St",
    "sg:city":"Oxnard",
    "sg:classifiers":[
        {
            "category":"Building & Trades",
            "subcategory":"Plumbing",
            "type":"Services"
        }
    ],
    "sg:phone":"+1 805 487 6745",
    "sg:postcode":"93033",
    "sg:province":"CA",
    "sg:tags":[
        "plumbing",
        "contractor"
    ],
    "wof:name":"B P Plumbing/Rooter Contrs",
    "wof:placetype":"venue"
},
  "geometry": {"coordinates":[-119.17621699999999,34.178384],"type":"Point"}
}