{
  "type": "Feature",
  "properties": {
    "addr:full":"23734 Valencia Blvd Valencia CA 91355",
    "addr:housenumber":"23734",
    "addr:postcode":"91355",
    "addr:street":"Valencia Blvd",
    "iso:country":"US",
    "sg:address":"23734 Valencia Blvd",
    "sg:city":"Valencia",
    "sg:classifiers":[
        {
            "category":"Professional",
            "subcategory":"Accounting & Tax Preparation",
            "type":"Services"
        }
    ],
    "sg:phone":"+1 661 259 9470",
    "sg:postcode":"91355",
    "sg:province":"CA",
    "sg:tags":[
        "accountant"
    ],
    "wof:name":"Finch Dale F CPA",
    "wof:placetype":"venue"
},
  "geometry": {"coordinates":[-118.549004,34.417198],"type":"Point"}
}