{
  "type": "Feature",
  "properties": {
    "addr:full":"2304 S Castle Harbour Pl Ontario CA 91761",
    "addr:housenumber":"2304",
    "addr:postcode":"91761",
    "addr:street":"S Castle Harbour Pl",
    "iso:country":"US",
    "sg:address":"2304 S Castle Harbour Pl",
    "sg:city":"Ontario",
    "sg:classifiers":[
        {
            "category":"Wholesale",
            "subcategory":"Computers",
            "type":"Manufacturing & Wholesale Goods"
        }
    ],
    "sg:phone":"+1 909 923 5888",
    "sg:postcode":"91761",
    "sg:province":"CA",
    "sg:tags":[
        "equipment",
        "peripheral"
    ],
    "wof:name":"Pmt",
    "wof:placetype":"venue"
},
  "geometry": {"coordinates":[-117.616011,34.028726],"type":"Point"}
}