{
  "type": "Feature",
  "properties": {
    "addr:full":"7757 Hollywood Blvd West Hollywood CA 90046",
    "addr:housenumber":"7757",
    "addr:postcode":"90046",
    "addr:street":"Hollywood Blvd",
    "iso:country":"US",
    "sg:address":"7757 Hollywood Blvd",
    "sg:city":"West Hollywood",
    "sg:classifiers":[
        {
            "category":"Retail",
            "subcategory":"Self-service Laundry",
            "type":"Services"
        }
    ],
    "sg:phone":"+1 323 656 8207",
    "sg:postcode":"90046",
    "sg:province":"CA",
    "wof:name":"Laundry Land",
    "wof:placetype":"venue"
},
  "geometry": {"coordinates":[-118.35926600000001,34.101767],"type":"Point"}
}