{
  "type": "Feature",
  "properties": {
    "iso:country":"US",
    "sg:address":"343 Hushbeck Ave",
    "sg:city":"Watsonville",
    "sg:classifiers":[
        {
            "category":"Building & Trades",
            "subcategory":"Construction",
            "type":"Services"
        }
    ],
    "sg:phone":"+1 408 595 2567",
    "sg:postcode":"95076",
    "sg:province":"CA",
    "sg:tags":[
        "contractor"
    ],
    "wof:name":"Stripe A Lot",
    "wof:placetype":"venue"
},
  "geometry": {"coordinates":[-121.745742,36.91879],"type":"Point"}
}