{
  "type": "Feature",
  "properties": {
    "addr:full":"1720 John Way Templeton CA 93465",
    "addr:housenumber":"1720",
    "addr:postcode":"93465",
    "addr:street":"John Way",
    "iso:country":"US",
    "sg:address":"1720 John Way",
    "sg:city":"Templeton",
    "sg:classifiers":[
        {
            "category":"Personal",
            "type":"Services"
        }
    ],
    "sg:phone":"+1 805 434 5595",
    "sg:postcode":"93465",
    "sg:province":"CA",
    "wof:name":"Impressive Image Photography",
    "wof:placetype":"venue"
},
  "geometry": {"coordinates":[-120.647531,35.528692],"type":"Point"}
}