{
  "type": "Feature",
  "properties": {
    "iso:country":"US",
    "sg:address":"8850 Davona Dr",
    "sg:city":"Dublin",
    "sg:classifiers":[
        {
            "category":"Education",
            "subcategory":"School",
            "type":"Public Place"
        }
    ],
    "sg:phone":"+1 925 829 3857",
    "sg:postcode":"94568",
    "sg:province":"CA",
    "wof:name":"St Philip Lutheran School",
    "wof:placetype":"venue"
},
  "geometry": {"coordinates":[-121.936918,37.723824],"type":"Point"}
}