{
  "type": "Feature",
  "properties": {
    "addr:full":"12047 Yearling St Cerritos CA 90703",
    "addr:housenumber":"12047",
    "addr:postcode":"ca 90703",
    "addr:street":"Yearling St",
    "iso:country":"US",
    "sg:address":"12047 Yearling St",
    "sg:city":"Cerritos",
    "sg:classifiers":[
        {
            "category":"Professional",
            "subcategory":"Accounting & Tax Preparation",
            "type":"Services"
        }
    ],
    "sg:phone":"+1 562 865 4455",
    "sg:postcode":"90703",
    "sg:province":"CA",
    "sg:tags":[
        "return",
        "filing"
    ],
    "wof:name":"Amira's Tax & Bookkeeping Svc",
    "wof:placetype":"venue"
},
  "geometry": {"coordinates":[-118.075669,33.849391],"type":"Point"}
}