{
  "type": "Feature",
  "properties": {
    "iso:country":"US",
    "sg:address":"413 Leidesdorff St",
    "sg:city":"Folsom",
    "sg:classifiers":[
        {
            "category":"Professional",
            "subcategory":"Business Services",
            "type":"Services"
        }
    ],
    "sg:phone":"+1 916 351 1539",
    "sg:postcode":"95630",
    "sg:province":"CA",
    "wof:name":"Double D Enterprises",
    "wof:placetype":"venue"
},
  "geometry": {"coordinates":[-121.173293,38.680927],"type":"Point"}
}