{
  "type": "Feature",
  "properties": {
    "addr:full":"4436 Cll Real Santa Barbara CA 93110",
    "addr:postcode":"4436;93110",
    "addr:street":"Cll Real",
    "iso:country":"US",
    "sg:address":"4436 Cll Real",
    "sg:city":"Santa Barbara",
    "sg:classifiers":[
        {
            "category":"Government",
            "subcategory":"Office",
            "type":"Public Place"
        }
    ],
    "sg:phone":"+1 805 681 5645",
    "sg:postcode":"93110",
    "sg:province":"CA",
    "wof:name":"Pretrial Svcs",
    "wof:placetype":"venue"
},
  "geometry": {"coordinates":[-119.77763400000001,34.442418],"type":"Point"}
}