{
  "type": "Feature",
  "properties": {
    "iso:country":"US",
    "sg:address":"817 Vine St",
    "sg:city":"Los Angeles",
    "sg:classifiers":[
        {
            "category":"Professional",
            "subcategory":"Management & Consulting",
            "type":"Services"
        }
    ],
    "sg:phone":"+1 310 371 4211",
    "sg:postcode":"90038",
    "sg:province":"CA",
    "sg:tags":[
        "consultant",
        "educational"
    ],
    "wof:name":"E & I Intl Hollywood",
    "wof:placetype":"venue"
},
  "geometry": {"coordinates":[-118.326682,34.085901],"type":"Point"}
}