{
  "type": "Feature",
  "properties": {
    "addr:full":"715 Carolina St Vallejo CA 94590",
    "addr:housenumber":"715",
    "addr:postcode":"94590",
    "addr:street":"Carolina St",
    "iso:country":"US",
    "sg:address":"715 Carolina St",
    "sg:city":"Vallejo",
    "sg:classifiers":[
        {
            "category":"Building & Trades",
            "subcategory":"Construction",
            "type":"Services"
        }
    ],
    "sg:phone":"+1 707 373 9056",
    "sg:postcode":"94590",
    "sg:province":"CA",
    "sg:tags":[
        "residential"
    ],
    "wof:name":"Crail Construction",
    "wof:placetype":"venue"
},
  "geometry": {"coordinates":[-122.251751,38.103942],"type":"Point"}
}