{
  "type": "Feature",
  "properties": {
    "addr:full":"511 N La Cienega Blvd Los Angeles CA 90048",
    "addr:housenumber":"511",
    "addr:postcode":"90048",
    "addr:street":"N La Cienega Blvd",
    "iso:country":"US",
    "sg:address":"511 N La Cienega Blvd",
    "sg:city":"Los Angeles",
    "sg:classifiers":[
        {
            "category":"Arts & Performance",
            "subcategory":"Art Gallery",
            "type":"Entertainment"
        },
        {
            "category":"Museum",
            "type":"Entertainment"
        }
    ],
    "sg:phone":"+1 310 652 6030",
    "sg:postcode":"90048",
    "sg:province":"CA",
    "sg:website":"www.maceylipmanart.com",
    "wof:name":"Macey Lipman Art Gallery",
    "wof:placetype":"venue"
},
  "geometry": {"coordinates":[-118.376577,34.080659],"type":"Point"}
}