{
  "type": "Feature",
  "properties": {
    "iso:country":"US",
    "sg:address":"1212 N Plaza Dr",
    "sg:city":"Visalia",
    "sg:classifiers":[
        {
            "category":"Professional",
            "subcategory":"Engineering",
            "type":"Services"
        }
    ],
    "sg:phone":"+1 559 651 1337",
    "sg:postcode":"93291",
    "sg:province":"CA",
    "sg:tags":[
        "general",
        "contractor"
    ],
    "wof:name":"Lee's Paving Inc",
    "wof:placetype":"venue"
},
  "geometry": {"coordinates":[-119.394631,36.340574],"type":"Point"}
}