{
  "type": "Feature",
  "properties": {
    "iso:country":"US",
    "sg:address":"3500 Alameda",
    "sg:city":"Menlo Park",
    "sg:classifiers":[
        {
            "category":"Professional",
            "type":"Services"
        }
    ],
    "sg:phone":"+1 650 233 8861",
    "sg:postcode":"94025",
    "sg:province":"CA",
    "wof:name":"Trilogy Captial Patners",
    "wof:placetype":"venue"
},
  "geometry": {"coordinates":[-122.202381,37.432225],"type":"Point"}
}