{
  "type": "Feature",
  "properties": {
    "addr:full":"368 Anita St Chula Vista CA 91911",
    "addr:housenumber":"368",
    "addr:postcode":"91911",
    "addr:street":"Anita St",
    "iso:country":"US",
    "sg:address":"368 Anita St",
    "sg:city":"Chula Vista",
    "sg:classifiers":[
        {
            "category":"Wholesale",
            "subcategory":"Books, Periodicals, & Newspapers",
            "type":"Manufacturing & Wholesale Goods"
        }
    ],
    "sg:phone":"+1 619 426 6722",
    "sg:postcode":"91911",
    "sg:province":"CA",
    "wof:name":"Amazing Comics & Collectibles",
    "wof:placetype":"venue"
},
  "geometry": {"coordinates":[-117.06698799999999,32.598497],"type":"Point"}
}