{
  "type": "Feature",
  "properties": {
    "iso:country":"US",
    "sg:address":"118 S Riverside Ave",
    "sg:city":"Rialto",
    "sg:classifiers":[
        {
            "category":"Wholesale",
            "subcategory":"Medical Equipment & Supplies",
            "type":"Manufacturing & Wholesale Goods"
        }
    ],
    "sg:phone":"+1 909 746 0100",
    "sg:postcode":"92376",
    "sg:province":"CA",
    "sg:tags":[
        "soundproofing"
    ],
    "wof:name":"Las Amaya Electronics",
    "wof:placetype":"venue"
},
  "geometry": {"coordinates":[-117.370468,34.100231],"type":"Point"}
}