{
  "type": "Feature",
  "properties": {
    "addr:full":"17678 Valley Blvd Bloomington CA 92316",
    "addr:housenumber":"17678",
    "addr:postcode":"92316",
    "addr:street":"Valley Blvd",
    "iso:country":"US",
    "sg:address":"17678 Valley Blvd",
    "sg:city":"Bloomington",
    "sg:classifiers":[
        {
            "category":"Autos & Motor Vehicles",
            "subcategory":"Automobile Sales",
            "type":"Retail Goods"
        }
    ],
    "sg:phone":"+1 909 877 2022",
    "sg:postcode":"92316",
    "sg:province":"CA",
    "sg:tags":[
        "car",
        "dealer"
    ],
    "wof:name":"G T Motors",
    "wof:placetype":"venue"
},
  "geometry": {"coordinates":[-117.42277900000001,34.070485],"type":"Point"}
}