{
  "type": "Feature",
  "properties": {
    "iso:country":"US",
    "sg:address":"2203 Venice Blvd",
    "sg:city":"Los Angeles",
    "sg:classifiers":[
        {
            "category":"Retail",
            "subcategory":"Repair Shop",
            "type":"Services"
        }
    ],
    "sg:phone":"+1 323 733 7716",
    "sg:postcode":"90006",
    "sg:province":"CA",
    "sg:tags":[
        "lock",
        "locksmith"
    ],
    "sg:website":"www.bestlockandsafe.com",
    "wof:name":"Best Lock & Safe Svc",
    "wof:placetype":"venue"
},
  "geometry": {"coordinates":[-118.30762,34.043647],"type":"Point"}
}