{
  "type": "Feature",
  "properties": {
    "addr:full":"19410 Geyserville Ave Geyserville CA 95441",
    "addr:housenumber":"19410",
    "addr:postcode":"95441",
    "addr:street":"Geyserville Ave",
    "iso:country":"US",
    "sg:address":"19410 Geyserville Ave",
    "sg:city":"Geyserville",
    "sg:classifiers":[
        {
            "category":"Manufacturing",
            "subcategory":"Food",
            "type":"Manufacturing & Wholesale Goods"
        }
    ],
    "sg:phone":"+1 707 857 1651",
    "sg:postcode":"95441",
    "sg:province":"CA",
    "sg:tags":[
        "winery"
    ],
    "sg:website":"www.closdubois.com",
    "wof:name":"Clos Du Bois Wines Inc",
    "wof:placetype":"venue"
},
  "geometry": {"coordinates":[-122.88095800000001,38.686853],"type":"Point"}
}