{
  "type": "Feature",
  "properties": {
    "addr:full":"43720 15th St W Lancaster CA 93534",
    "addr:housenumber":"43720",
    "addr:postcode":"93534",
    "addr:street":"15Th St W",
    "iso:country":"US",
    "sg:address":"43720 15th St W",
    "sg:city":"Lancaster",
    "sg:classifiers":[
        {
            "category":"Restaurant",
            "type":"Food & Drink"
        }
    ],
    "sg:menulink":"http://www.allmenus.com/ca/north-antelope-valley/214173-taco-bell/menu/",
    "sg:phone":"+1 661 723 1488",
    "sg:postcode":"93534",
    "sg:province":"CA",
    "sg:tags":[
        "mexican"
    ],
    "wof:name":"Taco Bell",
    "wof:placetype":"venue"
},
  "geometry": {"coordinates":[-118.15600499999999,34.676974],"type":"Point"}
}