{
  "type": "Feature",
  "properties": {
    "iso:country":"US",
    "sg:address":"1527 19th St",
    "sg:city":"Bakersfield",
    "sg:classifiers":[
        {
            "category":"Building & Trades",
            "subcategory":"Equipment Rental",
            "type":"Services"
        }
    ],
    "sg:phone":"+1 661 327 3783",
    "sg:postcode":"93301",
    "sg:province":"CA",
    "sg:tags":[
        "disabled",
        "person",
        "supply"
    ],
    "wof:name":"Greater Los Angeles Council",
    "wof:placetype":"venue"
},
  "geometry": {"coordinates":[-119.019756,35.376154],"type":"Point"}
}