{
  "type": "Feature",
  "properties": {
    "addr:full":"333 W el Camino Real Sunnyvale CA 94087",
    "addr:housenumber":"333",
    "addr:postcode":"94087",
    "addr:street":"W El Camino Real",
    "iso:country":"US",
    "sg:address":"333 W el Camino Real",
    "sg:city":"Sunnyvale",
    "sg:classifiers":[
        {
            "category":"Health Services",
            "subcategory":"Chiropractor",
            "type":"Services"
        }
    ],
    "sg:phone":"+1 408 733 7330",
    "sg:postcode":"94087",
    "sg:province":"CA",
    "wof:name":"Silicon Valley Chiro Ctr",
    "wof:placetype":"venue"
},
  "geometry": {"coordinates":[-122.036691,37.369012],"type":"Point"}
}