{
  "type": "Feature",
  "properties": {
    "iso:country":"US",
    "sg:address":"5600 Kearny Mesa Rd",
    "sg:city":"San Diego",
    "sg:classifiers":[
        {
            "category":"Recreation",
            "type":"Entertainment"
        }
    ],
    "sg:phone":"+1 619 233 9452",
    "sg:postcode":"92111",
    "sg:province":"CA",
    "sg:tags":[
        "scooter",
        "motorcycle",
        "motor"
    ],
    "wof:name":"Route 66 Riders",
    "wof:placetype":"venue"
},
  "geometry": {"coordinates":[-117.137366,32.837379],"type":"Point"}
}