{
  "type": "Feature",
  "properties": {
    "addr:full":"7089 N Marks Ave Fresno CA 93711",
    "addr:housenumber":"7089",
    "addr:postcode":"93711",
    "addr:street":"N Marks Ave",
    "iso:country":"US",
    "sg:address":"7089 N Marks Ave",
    "sg:city":"Fresno",
    "sg:classifiers":[
        {
            "category":"Personal",
            "subcategory":"Tanning Parlor",
            "type":"Services"
        }
    ],
    "sg:phone":"+1 559 436 8268",
    "sg:postcode":"93711",
    "sg:province":"CA",
    "sg:tags":[
        "salon"
    ],
    "wof:name":"Sunsational Tans",
    "wof:placetype":"venue"
},
  "geometry": {"coordinates":[-119.847525,36.837907],"type":"Point"}
}