{
  "type": "Feature",
  "properties": {
    "iso:country":"US",
    "sg:address":"3247 E Gage Ave",
    "sg:city":"Huntington Park",
    "sg:classifiers":[
        {
            "category":"Insurance",
            "subcategory":"Insurance Agent",
            "type":"Services"
        }
    ],
    "sg:phone":"+1 323 583 2668",
    "sg:postcode":"90255",
    "sg:province":"CA",
    "wof:name":"A B Insurance",
    "wof:placetype":"venue"
},
  "geometry": {"coordinates":[-118.209025,33.980448],"type":"Point"}
}