{
  "type": "Feature",
  "properties": {
    "iso:country":"US",
    "sg:address":"11404 Imperial Hwy",
    "sg:city":"Norwalk",
    "sg:classifiers":[
        {
            "category":"Retail",
            "subcategory":"Auto Repair",
            "type":"Services"
        }
    ],
    "sg:phone":"+1 562 207 0870",
    "sg:postcode":"90650",
    "sg:province":"CA",
    "sg:tags":[
        "body",
        "painting",
        "repairing",
        "automobile"
    ],
    "wof:name":"Hi-Tech Collision & Glass Centers Inc",
    "wof:placetype":"venue"
},
  "geometry": {"coordinates":[-118.09046,33.917099],"type":"Point"}
}