{
  "type": "Feature",
  "properties": {
    "iso:country":"US",
    "sg:address":"3756 Oakes Dr",
    "sg:city":"Hayward",
    "sg:classifiers":[
        {
            "category":"Professional",
            "subcategory":"Accounting & Tax Preparation",
            "type":"Services"
        }
    ],
    "sg:phone":"+1 510 881 5500",
    "sg:postcode":"94542",
    "sg:province":"CA",
    "sg:tags":[
        "accountant"
    ],
    "wof:name":"William E Cox CPA",
    "wof:placetype":"venue"
},
  "geometry": {"coordinates":[-122.03722399999999,37.662949],"type":"Point"}
}