{
  "type": "Feature",
  "properties": {
    "iso:country":"US",
    "sg:address":"2525 El Camino Real Ste 264",
    "sg:city":"Carlsbad",
    "sg:classifiers":[
        {
            "category":"Shopping",
            "subcategory":"Pets & Pet Supplies",
            "type":"Retail Goods"
        }
    ],
    "sg:phone":"+1 760 730 0377",
    "sg:postcode":"92008",
    "sg:province":"CA",
    "sg:tags":[
        "store"
    ],
    "wof:name":"California Pets",
    "wof:placetype":"venue"
},
  "geometry": {"coordinates":[-117.34485100000001,33.167943],"type":"Point"}
}