{
  "type": "Feature",
  "properties": {
    "addr:full":"1150 Story Rd San Jose CA 95122",
    "addr:housenumber":"1150",
    "addr:postcode":"95122",
    "addr:street":"Story Rd",
    "iso:country":"US",
    "sg:address":"1150 Story Rd",
    "sg:city":"San Jose",
    "sg:classifiers":[
        {
            "category":"Restaurant",
            "type":"Food & Drink"
        }
    ],
    "sg:phone":"+1 408 278 1888",
    "sg:postcode":"95122",
    "sg:province":"CA",
    "sg:tags":[
        "vietnamese"
    ],
    "wof:name":"Com Tam Thanh",
    "wof:placetype":"venue"
},
  "geometry": {"coordinates":[-121.85359699999999,37.332612],"type":"Point"}
}