{
  "type": "Feature",
  "properties": {
    "addr:full":"420 Union St San Francisco CA 94133",
    "addr:housenumber":"420",
    "addr:postcode":"94133",
    "addr:street":"Union St",
    "iso:country":"US",
    "sg:address":"420 Union St",
    "sg:city":"San Francisco",
    "sg:classifiers":[
        {
            "category":"Education",
            "subcategory":"Library",
            "type":"Public Place"
        }
    ],
    "sg:phone":"+1 415 452 9294",
    "sg:postcode":"94133",
    "sg:province":"CA",
    "wof:name":"Re Sources",
    "wof:placetype":"venue"
},
  "geometry": {"coordinates":[-122.406735,37.800823],"type":"Point"}
}