{
  "type": "Feature",
  "properties": {
    "iso:country":"US",
    "sg:address":"807 S Ardmore Ave",
    "sg:city":"Los Angeles",
    "sg:classifiers":[
        {
            "category":"Restaurant",
            "type":"Food & Drink"
        }
    ],
    "sg:phone":"+1 213 487 0038",
    "sg:postcode":"90005",
    "sg:province":"CA",
    "wof:name":"Eighth Street Soondae",
    "wof:placetype":"venue"
},
  "geometry": {"coordinates":[-118.30205,34.055997],"type":"Point"}
}