{
  "type": "Feature",
  "properties": {
    "addr:full":"822 Stanford Ave Los Angeles CA 90021",
    "addr:housenumber":"822",
    "addr:postcode":"90021",
    "addr:street":"Stanford Ave",
    "iso:country":"US",
    "sg:address":"822 Stanford Ave",
    "sg:city":"Los Angeles",
    "sg:classifiers":[
        {
            "category":"Freight",
            "type":"Transportation"
        }
    ],
    "sg:phone":"+1 213 622 0283",
    "sg:postcode":"90021",
    "sg:province":"CA",
    "sg:tags":[
        "piece",
        "general"
    ],
    "wof:name":"El Textiles Warehouse",
    "wof:placetype":"venue"
},
  "geometry": {"coordinates":[-118.24756499999999,34.035316],"type":"Point"}
}