{
  "type": "Feature",
  "properties": {
    "iso:country":"US",
    "sg:address":"2408 21st St",
    "sg:city":"Sacramento",
    "sg:classifiers":[
        {
            "category":"Personal",
            "subcategory":"Barber",
            "type":"Services"
        }
    ],
    "sg:phone":"+1 916 457 1120",
    "sg:postcode":"95818",
    "sg:province":"CA",
    "sg:website":"sacramentobarbershop.com/",
    "wof:name":"Anthony's Barbershop",
    "wof:placetype":"venue"
},
  "geometry": {"coordinates":[-121.485384,38.560642],"type":"Point"}
}