{
  "type": "Feature",
  "properties": {
    "iso:country":"US",
    "sg:address":"2941 Anacapa Pl",
    "sg:city":"Fullerton",
    "sg:classifiers":[
        {
            "category":"Professional",
            "subcategory":"Management & Consulting",
            "type":"Services"
        }
    ],
    "sg:phone":"+1 714 626 0275",
    "sg:postcode":"92835",
    "sg:province":"CA",
    "sg:tags":[
        "consultant",
        "energy",
        "conservation"
    ],
    "wof:name":"Vanward Consulting",
    "wof:placetype":"venue"
},
  "geometry": {"coordinates":[-117.93319700000001,33.905273],"type":"Point"}
}