{
  "type": "Feature",
  "properties": {
    "addr:full":"138 N Orange Ave Fullerton CA 92833",
    "addr:housenumber":"138",
    "addr:postcode":"92833",
    "addr:street":"N Orange Ave",
    "iso:country":"US",
    "sg:address":"138 N Orange Ave",
    "sg:city":"Fullerton",
    "sg:classifiers":[
        {
            "category":"Wholesale",
            "subcategory":"Vending Machines",
            "type":"Manufacturing & Wholesale Goods"
        }
    ],
    "sg:phone":"+1 714 879 6162",
    "sg:postcode":"92833",
    "sg:province":"CA",
    "wof:name":"B & R Vending",
    "wof:placetype":"venue"
},
  "geometry": {"coordinates":[-117.942984,33.87378],"type":"Point"}
}