{
  "type": "Feature",
  "properties": {
    "addr:full":"270 Cimino St San Jose CA 95125",
    "addr:housenumber":"270",
    "addr:postcode":"95125",
    "addr:street":"Cimino St",
    "iso:country":"US",
    "sg:address":"270 Cimino St",
    "sg:city":"San Jose",
    "sg:classifiers":[
        {
            "category":"Retail",
            "subcategory":"Auto Repair",
            "type":"Services"
        }
    ],
    "sg:phone":"+1 408 977 0616",
    "sg:postcode":"95125",
    "sg:province":"CA",
    "wof:name":"Bob's Almaden Transmissions",
    "wof:placetype":"venue"
},
  "geometry": {"coordinates":[-121.870356,37.302717],"type":"Point"}
}