{
  "type": "Feature",
  "properties": {
    "addr:full":"901 Palomar Airport Rd Carlsbad CA 92009",
    "addr:housenumber":"901",
    "addr:postcode":"92009",
    "addr:street":"Palomar Airport Rd",
    "iso:country":"US",
    "sg:address":"901 Palomar Airport Rd",
    "sg:city":"Carlsbad",
    "sg:classifiers":[
        {
            "category":"Autos & Motor Vehicles",
            "subcategory":"Fuel & Gas Station",
            "type":"Retail Goods"
        },
        {
            "category":"Food & Beverages",
            "subcategory":"Groceries & Convenience Stores",
            "type":"Retail Goods"
        }
    ],
    "sg:postcode":"92009",
    "sg:province":"CA",
    "sg:website":"www.7-eleven.com/",
    "wof:name":"7-Eleven",
    "wof:placetype":"venue"
},
  "geometry": {"coordinates":[-117.318752,33.121624],"type":"Point"}
}