{
  "type": "Feature",
  "properties": {
    "addr:full":"1801 W Sunset Blvd Los Angeles CA 90026",
    "addr:housenumber":"1801",
    "addr:postcode":"90026",
    "addr:street":"W Sunset Blvd",
    "iso:country":"US",
    "sg:address":"1801 W Sunset Blvd",
    "sg:city":"Los Angeles",
    "sg:classifiers":[
        {
            "category":"Restaurant",
            "type":"Food & Drink"
        }
    ],
    "sg:phone":"+1 213 413 3232",
    "sg:postcode":"90026",
    "sg:province":"CA",
    "sg:tags":[
        "vietnamese"
    ],
    "sg:website":"www.xoiaeats.com/",
    "wof:name":"Xoia",
    "wof:placetype":"venue"
},
  "geometry": {"coordinates":[-118.259371,34.078],"type":"Point"}
}