{
  "type": "Feature",
  "properties": {
    "addr:full":"880 Park Ct Arcata CA 95521",
    "addr:housenumber":"880",
    "addr:postcode":"95521",
    "addr:street":"Park Ct",
    "iso:country":"US",
    "sg:address":"880 Park Ct",
    "sg:city":"Arcata",
    "sg:classifiers":[
        {
            "category":"Building & Trades",
            "subcategory":"Landscaping Services",
            "type":"Services"
        }
    ],
    "sg:phone":"+1 707 822 1332",
    "sg:postcode":"95521",
    "sg:province":"CA",
    "sg:tags":[
        "lawn",
        "garden",
        "maintenance",
        "grounds"
    ],
    "wof:name":"Ever Green Gardening Service",
    "wof:placetype":"venue"
},
  "geometry": {"coordinates":[-124.068416,40.867528],"type":"Point"}
}