{
  "type": "Feature",
  "properties": {
    "addr:full":"7220 Corte Pl Alta Loma CA 91701",
    "addr:housenumber":"7220",
    "addr:postcode":"91701",
    "addr:street":"Corte Pl",
    "iso:country":"US",
    "sg:address":"7220 Corte Pl",
    "sg:city":"Alta Loma",
    "sg:classifiers":[
        {
            "category":"Professional",
            "subcategory":"Business Services",
            "type":"Services"
        }
    ],
    "sg:phone":"+1 909 941 9833",
    "sg:postcode":"91701",
    "sg:province":"CA",
    "sg:tags":[
        "notary"
    ],
    "wof:name":"Budget Notary Svc",
    "wof:placetype":"venue"
},
  "geometry": {"coordinates":[-117.550752,34.122199],"type":"Point"}
}