{
  "type": "Feature",
  "properties": {
    "addr:full":"36517 Quail St Palmdale CA 93552",
    "addr:housenumber":"36517",
    "addr:postcode":"ca 93552",
    "addr:street":"Quail St",
    "iso:country":"US",
    "sg:address":"36517 Quail St",
    "sg:city":"Palmdale",
    "sg:classifiers":[
        {
            "category":"Utilities",
            "subcategory":"Refuse",
            "type":"Services"
        }
    ],
    "sg:phone":"+1 818 765 7669",
    "sg:postcode":"93552",
    "sg:province":"CA",
    "sg:tags":[
        "garbage",
        "collection"
    ],
    "wof:name":"Reduced Price Disposal",
    "wof:placetype":"venue"
},
  "geometry": {"coordinates":[-118.053572,34.544777],"type":"Point"}
}