{
  "type": "Feature",
  "properties": {
    "addr:full":"35 10th St Tracy CA 95376",
    "addr:housenumber":"35",
    "addr:postcode":"95376",
    "addr:street":"10Th St",
    "iso:country":"US",
    "sg:address":"35 10th St",
    "sg:city":"Tracy",
    "sg:classifiers":[
        {
            "category":"Professional",
            "type":"Services"
        }
    ],
    "sg:phone":"+1 209 834 8050",
    "sg:postcode":"95376",
    "sg:province":"CA",
    "sg:tags":[
        "establishment"
    ],
    "wof:name":"Regina Nordman Mft",
    "wof:placetype":"venue"
},
  "geometry": {"coordinates":[-121.424314,37.738605],"type":"Point"}
}