{
  "type": "Feature",
  "properties": {
    "addr:full":"420 Fair Haven Road Alameda CA 94501",
    "addr:housenumber":"420",
    "addr:postcode":"94501",
    "addr:street":"Fair Haven Road",
    "iso:country":"US",
    "sg:address":"420 Fair Haven Road",
    "sg:city":"Alameda",
    "sg:classifiers":[
        {
            "category":"Building & Trades",
            "subcategory":"Construction",
            "type":"Services"
        }
    ],
    "sg:phone":"+1 510 496 6008",
    "sg:postcode":"94501",
    "sg:province":"CA",
    "sg:tags":[
        "contractor"
    ],
    "wof:name":"Sun's Free Solar",
    "wof:placetype":"venue"
},
  "geometry": {"coordinates":[-122.26686599999999,37.762678],"type":"Point"}
}