{
  "type": "Feature",
  "properties": {
    "iso:country":"US",
    "sg:address":"1801 Bell Ave",
    "sg:city":"Sacramento",
    "sg:classifiers":[
        {
            "category":"Wholesale",
            "subcategory":"Construction Materials",
            "type":"Manufacturing & Wholesale Goods"
        },
        {
            "category":"Home & Garden",
            "subcategory":"Building Materials",
            "type":"Retail Goods"
        }
    ],
    "sg:phone":"+1 916 922 9327",
    "sg:postcode":"95838",
    "sg:province":"CA",
    "sg:tags":[
        "windows"
    ],
    "wof:name":"Alside Supply Center",
    "wof:placetype":"venue"
},
  "geometry": {"coordinates":[-121.426637,38.647391],"type":"Point"}
}