{
  "type": "Feature",
  "properties": {
    "addr:full":"12307 Ventura Blvd Studio City CA 91604",
    "addr:housenumber":"12307",
    "addr:postcode":"91604",
    "addr:street":"Ventura Blvd",
    "iso:country":"US",
    "sg:address":"12307 Ventura Blvd",
    "sg:city":"Studio City",
    "sg:classifiers":[
        {
            "category":"Professional",
            "subcategory":"Detective & Security Services",
            "type":"Services"
        }
    ],
    "sg:phone":"+1 818 623 6749",
    "sg:postcode":"91604",
    "sg:province":"CA",
    "sg:tags":[
        "investigator"
    ],
    "wof:name":"CIA Investigations",
    "wof:placetype":"venue"
},
  "geometry": {"coordinates":[-118.40290899999999,34.142963],"type":"Point"}
}