{
  "type": "Feature",
  "properties": {
    "addr:full":"2625 N Garey Ave Pomona CA 91767",
    "addr:housenumber":"2625",
    "addr:postcode":"91767",
    "addr:street":"N Garey Ave",
    "iso:country":"US",
    "sg:address":"2625 N Garey Ave",
    "sg:city":"Pomona",
    "sg:classifiers":[
        {
            "category":"Retail",
            "subcategory":"Laundry & Dry Cleaning",
            "type":"Services"
        }
    ],
    "sg:phone":"+1 909 392 3927",
    "sg:postcode":"91767",
    "sg:province":"CA",
    "sg:tags":[
        "cleaners"
    ],
    "wof:name":"O K Cleaners",
    "wof:placetype":"venue"
},
  "geometry": {"coordinates":[-117.74865,34.093287],"type":"Point"}
}