{
  "type": "Feature",
  "properties": {
    "addr:full":"4636 Watt Avenue North Highlands CA 95660",
    "addr:housenumber":"4636",
    "addr:postcode":"95660",
    "addr:street":"Watt Avenue",
    "iso:country":"US",
    "sg:address":"4636 Watt Avenue",
    "sg:city":"North Highlands",
    "sg:classifiers":[
        {
            "category":"Banks & Credit Unions",
            "subcategory":"Bank",
            "type":"Services"
        }
    ],
    "sg:phone":"+1 916 971 2238",
    "sg:postcode":"95660",
    "sg:province":"CA",
    "wof:name":"Safe Credit Union",
    "wof:placetype":"venue"
},
  "geometry": {"coordinates":[-121.382712,38.649717],"type":"Point"}
}