{
  "type": "Feature",
  "properties": {
    "addr:full":"670 W 17th St Costa Mesa CA 92627",
    "addr:housenumber":"670",
    "addr:postcode":"92627",
    "addr:street":"W 17Th St",
    "iso:country":"US",
    "sg:address":"670 W 17th St",
    "sg:city":"Costa Mesa",
    "sg:classifiers":[
        {
            "category":"Professional",
            "subcategory":"Management & Consulting",
            "type":"Services"
        }
    ],
    "sg:phone":"+1 949 574 8000",
    "sg:postcode":"92627",
    "sg:province":"CA",
    "sg:tags":[
        "marketing",
        "consultant"
    ],
    "wof:name":"Focus Sales & Marketing",
    "wof:placetype":"venue"
},
  "geometry": {"coordinates":[-117.925043,33.636247],"type":"Point"}
}