{
  "type": "Feature",
  "properties": {
    "addr:full":"51 Foley St Santa Rosa CA 95401",
    "addr:housenumber":"51",
    "addr:postcode":"ca 95401",
    "addr:street":"Foley St",
    "iso:country":"US",
    "sg:address":"51 Foley St",
    "sg:city":"Santa Rosa",
    "sg:classifiers":[
        {
            "category":"Home & Garden",
            "subcategory":"Building Materials",
            "type":"Retail Goods"
        }
    ],
    "sg:phone":"+1 707 523 4363",
    "sg:postcode":"95401",
    "sg:province":"CA",
    "sg:tags":[
        "energy",
        "conservation",
        "prod"
    ],
    "sg:website":"www.earthenergysystems.com",
    "wof:name":"Earth Energy Systems Inc",
    "wof:placetype":"venue"
},
  "geometry": {"coordinates":[-122.72795499999999,38.451938],"type":"Point"}
}