{
  "type": "Feature",
  "properties": {
    "addr:full":"370 Crenshaw Blvd Torrance CA 90503",
    "addr:housenumber":"370",
    "addr:postcode":"90503",
    "addr:street":"Crenshaw Blvd",
    "iso:country":"US",
    "sg:address":"370 Crenshaw Blvd",
    "sg:city":"Torrance",
    "sg:classifiers":[
        {
            "category":"Professional",
            "subcategory":"Management & Consulting",
            "type":"Services"
        }
    ],
    "sg:phone":"+1 310 787 4320",
    "sg:postcode":"90503",
    "sg:province":"CA",
    "sg:tags":[
        "consultant",
        "security",
        "system"
    ],
    "sg:website":"www.viatron.com",
    "wof:name":"Viatron Systems Inc",
    "wof:placetype":"venue"
},
  "geometry": {"coordinates":[-118.32867,33.846745],"type":"Point"}
}