{
  "type": "Feature",
  "properties": {
    "iso:country":"US",
    "sg:address":"1031 N Alvarado St",
    "sg:city":"Los Angeles",
    "sg:classifiers":[
        {
            "category":"Cinema",
            "subcategory":"Movie Rental",
            "type":"Entertainment"
        }
    ],
    "sg:phone":"+1 213 413 0860",
    "sg:postcode":"90026",
    "sg:province":"CA",
    "sg:tags":[
        "game",
        "video"
    ],
    "wof:name":"Go Video",
    "wof:placetype":"venue"
},
  "geometry": {"coordinates":[-118.264141,34.076786],"type":"Point"}
}