{
  "type": "Feature",
  "properties": {
    "iso:country":"US",
    "sg:address":"210 San Jose Ave # 24",
    "sg:city":"San Jose",
    "sg:classifiers":[
        {
            "category":"Home & Garden",
            "subcategory":"Home Furnishings",
            "type":"Retail Goods"
        },
        {
            "category":"Building & Trades",
            "subcategory":"Construction",
            "type":"Services"
        }
    ],
    "sg:phone":"+1 408 202 1017",
    "sg:postcode":"95125",
    "sg:province":"CA",
    "sg:tags":[
        "bath",
        "kitchen",
        "contractor"
    ],
    "sg:website":"renovatioremodeling.com",
    "wof:name":"Renovation Remodeling Contractors",
    "wof:placetype":"venue"
},
  "geometry": {"coordinates":[-121.87469900000001,37.309143],"type":"Point"}
}