{
  "type": "Feature",
  "properties": {
    "iso:country":"US",
    "sg:address":"2430 Samaritan Dr",
    "sg:city":"San Jose",
    "sg:classifiers":[
        {
            "category":"Health Services",
            "subcategory":"Doctor",
            "type":"Services"
        }
    ],
    "sg:phone":"+1 408 559 8847",
    "sg:postcode":"95124",
    "sg:province":"CA",
    "wof:name":"Group Orthopedics LLC",
    "wof:placetype":"venue"
},
  "geometry": {"coordinates":[-121.946539,37.250937],"type":"Point"}
}