{
  "type": "Feature",
  "properties": {
    "iso:country":"US",
    "sg:address":"116 S 12th St",
    "sg:city":"Santa Paula",
    "sg:classifiers":[
        {
            "category":"Shopping",
            "subcategory":"Hobbies, Toys, & Games",
            "type":"Retail Goods"
        }
    ],
    "sg:phone":"+1 805 525 7012",
    "sg:postcode":"93060",
    "sg:province":"CA",
    "sg:tags":[
        "model",
        "supply"
    ],
    "sg:website":"www.skytools.com",
    "wof:name":"SKYTOOLS.COM",
    "wof:placetype":"venue"
},
  "geometry": {"coordinates":[-119.055877,34.354962],"type":"Point"}
}