{
  "type": "Feature",
  "properties": {
    "addr:full":"4228 E Cesar E Chavez Avenue Los Angeles CA 90063",
    "addr:housenumber":"4228",
    "addr:postcode":"90063",
    "addr:street":"E Cesar E Chavez Avenue",
    "iso:country":"US",
    "sg:address":"4228 E Cesar E Chavez Avenue",
    "sg:city":"Los Angeles",
    "sg:classifiers":[
        {
            "category":"Shopping",
            "subcategory":"Florist",
            "type":"Retail Goods"
        }
    ],
    "sg:phone":"+1 323 261 1795",
    "sg:postcode":"90063",
    "sg:province":"CA",
    "wof:name":"Olgi's Flower",
    "wof:placetype":"venue"
},
  "geometry": {"coordinates":[-118.17473,34.040454],"type":"Point"}
}