{
  "type": "Feature",
  "properties": {
    "iso:country":"US",
    "sg:address":"1145 E Colorado St",
    "sg:city":"Glendale",
    "sg:classifiers":[
        {
            "category":"Food & Beverages",
            "subcategory":"Liquor & Beverages",
            "type":"Retail Goods"
        }
    ],
    "sg:phone":"+1 818 543 0947",
    "sg:postcode":"91205",
    "sg:province":"CA",
    "sg:tags":[
        "beer",
        "spirit",
        "wine"
    ],
    "wof:name":"A-1 Liquor",
    "wof:placetype":"venue"
},
  "geometry": {"coordinates":[-118.239998,34.142799],"type":"Point"}
}