{
  "type": "Feature",
  "properties": {
    "iso:country":"US",
    "sg:address":"7031 Koll Center Pkwy",
    "sg:city":"Pleasanton",
    "sg:classifiers":[
        {
            "category":"Professional",
            "subcategory":"Advertising",
            "type":"Services"
        }
    ],
    "sg:phone":"+1 925 461 6275",
    "sg:postcode":"94566",
    "sg:province":"CA",
    "sg:tags":[
        "counselor"
    ],
    "sg:website":"www.shennumgreen.com",
    "wof:name":"Shennum Green Inc",
    "wof:placetype":"venue"
},
  "geometry": {"coordinates":[-121.899969,37.662364],"type":"Point"}
}