{
  "type": "Feature",
  "properties": {
    "iso:country":"US",
    "sg:address":"222 E Glenarm St",
    "sg:city":"Pasadena",
    "sg:classifiers":[
        {
            "category":"Professional",
            "subcategory":"Computer Services",
            "type":"Services"
        }
    ],
    "sg:phone":"+1 626 696 3566",
    "sg:postcode":"91106",
    "sg:province":"CA",
    "sg:tags":[
        "repair"
    ],
    "wof:name":"My Internet Services",
    "wof:placetype":"venue"
},
  "geometry": {"coordinates":[-118.145639,34.127394],"type":"Point"}
}