{
  "type": "Feature",
  "properties": {
    "addr:full":"23236 Norrisgrove Ave Perris CA 92570",
    "addr:postcode":"23236;92570",
    "addr:street":"Norrisgrove Ave",
    "iso:country":"US",
    "sg:address":"23236 Norrisgrove Ave",
    "sg:city":"Perris",
    "sg:classifiers":[
        {
            "category":"Shopping",
            "subcategory":"Hobbies, Toys, & Games",
            "type":"Retail Goods"
        }
    ],
    "sg:phone":"+1 951 657 0670",
    "sg:postcode":"92570",
    "sg:province":"CA",
    "wof:name":"Imperial Base Toys & Hobbies",
    "wof:placetype":"venue"
},
  "geometry": {"coordinates":[-117.25836200000001,33.829765],"type":"Point"}
}