{
  "type": "Feature",
  "properties": {
    "addr:full":"746 Valencia Street, San Francisco, CA, USA",
    "addr:housenumber":"746",
    "addr:postcode":"94110",
    "addr:street":"Valencia Street",
    "addr:website":"http://www.craftsman-wolves.com/",
    "wof:name":"Craftsman and Wolves",
    "wof:placetype":"venue"
},
  "geometry": {"coordinates":[-122.421824,37.760957],"type":"Point"}
}