{
  "type": "Feature",
  "properties": {
    "iso:country":"US",
    "sg:address":"95 Linden St",
    "sg:city":"Oakland",
    "sg:classifiers":[
        {
            "category":"Wholesale",
            "subcategory":"Machinery & Supplies",
            "type":"Manufacturing & Wholesale Goods"
        }
    ],
    "sg:phone":"+1 510 302 6678",
    "sg:postcode":"94607",
    "sg:province":"CA",
    "sg:tags":[
        "equipment",
        "sporting",
        "industrial",
        "r"
    ],
    "wof:name":"Airsoft Extreme",
    "wof:placetype":"venue"
},
  "geometry": {"coordinates":[-122.28721,37.800157],"type":"Point"}
}