{
  "type": "Feature",
  "properties": {
    "iso:country":"US",
    "sg:address":"25225 Jefferson Ave",
    "sg:city":"Murrieta",
    "sg:classifiers":[
        {
            "category":"Building & Trades",
            "subcategory":"Construction",
            "type":"Services"
        }
    ],
    "sg:phone":"+1 951 677 1844",
    "sg:postcode":"92562",
    "sg:province":"CA",
    "sg:tags":[
        "contractor"
    ],
    "wof:name":"Madera Contractors",
    "wof:placetype":"venue"
},
  "geometry": {"coordinates":[-117.200352,33.551706],"type":"Point"}
}