{
  "type": "Feature",
  "properties": {
    "iso:country":"US",
    "sg:address":"10403 Collett Ave",
    "sg:city":"Granada Hills",
    "sg:classifiers":[
        {
            "category":"Professional",
            "subcategory":"Management & Consulting",
            "type":"Services"
        }
    ],
    "sg:phone":"+1 818 371 9024",
    "sg:postcode":"91344",
    "sg:province":"CA",
    "sg:tags":[
        "marketing",
        "consultant"
    ],
    "wof:name":"KKG Marketing Consutlants",
    "wof:placetype":"venue"
},
  "geometry": {"coordinates":[-118.48379799999999,34.259639],"type":"Point"}
}