{
  "type": "Feature",
  "properties": {
    "iso:country":"US",
    "sg:address":"1900 Church Ln",
    "sg:city":"San Pablo",
    "sg:classifiers":[
        {
            "category":"Professional",
            "type":"Services"
        }
    ],
    "sg:phone":"+1 510 232 9387",
    "sg:postcode":"94806",
    "sg:province":"CA",
    "sg:tags":[
        "establishment"
    ],
    "wof:name":"Cobbco",
    "wof:placetype":"venue"
},
  "geometry": {"coordinates":[-122.340834,37.958076],"type":"Point"}
}