{
  "type": "Feature",
  "properties": {
    "addr:full":"2139 N Tustin St Ste 1 Orange CA 92865",
    "addr:housenumber":"2139",
    "addr:postcode":"92865",
    "addr:street":"N Tustin St Ste 1",
    "iso:country":"US",
    "sg:address":"2139 N Tustin St Ste 1",
    "sg:city":"Orange",
    "sg:classifiers":[
        {
            "category":"Professional",
            "type":"Services"
        },
        {
            "category":"Restaurant",
            "type":"Food & Drink"
        }
    ],
    "sg:phone":"+1 714 637 3900",
    "sg:postcode":"92865",
    "sg:province":"CA",
    "sg:tags":[
        "mexican",
        "caterer"
    ],
    "sg:website":"bobbydsmexicanfood.com/",
    "wof:name":"Bobby D's Mexican Food",
    "wof:placetype":"venue"
},
  "geometry": {"coordinates":[-117.83546,33.823656],"type":"Point"}
}