{
  "type": "Feature",
  "properties": {
    "iso:country":"US",
    "sg:address":"6375 Little Uvas Rd",
    "sg:city":"Morgan Hill",
    "sg:classifiers":[
        {
            "category":"Manufacturing",
            "subcategory":"Retail Goods",
            "type":"Manufacturing & Wholesale Goods"
        }
    ],
    "sg:phone":"+1 408 605 4078",
    "sg:postcode":"95037",
    "sg:province":"CA",
    "sg:tags":[
        "manufacturer"
    ],
    "wof:name":"Quick Cord Systems",
    "wof:placetype":"venue"
},
  "geometry": {"coordinates":[-121.770475,37.11506],"type":"Point"}
}