{
  "type": "Feature",
  "properties": {
    "iso:country":"US",
    "sg:address":"12709 Prairie Ave",
    "sg:city":"Hawthorne",
    "sg:classifiers":[
        {
            "category":"Manufacturing",
            "subcategory":"Apparel",
            "type":"Manufacturing & Wholesale Goods"
        }
    ],
    "sg:phone":"+1 310 676 7660",
    "sg:postcode":"90250",
    "sg:province":"CA",
    "sg:tags":[
        "flag",
        "banner"
    ],
    "wof:name":"AAA Flag & Banner Mfg Co",
    "wof:placetype":"venue"
},
  "geometry": {"coordinates":[-118.343925,33.91763],"type":"Point"}
}