{
  "type": "Feature",
  "properties": {
    "addr:full":"1027 Palmyrita Ave Riverside CA 92507",
    "addr:housenumber":"1027",
    "addr:postcode":"92507",
    "addr:street":"Palmyrita Ave",
    "iso:country":"US",
    "sg:address":"1027 Palmyrita Ave",
    "sg:city":"Riverside",
    "sg:classifiers":[
        {
            "category":"Manufacturing",
            "subcategory":"Metals",
            "type":"Manufacturing & Wholesale Goods"
        }
    ],
    "sg:phone":"+1 951 683 7252",
    "sg:postcode":"92507",
    "sg:province":"CA",
    "sg:tags":[
        "steel",
        "tube",
        "sheet",
        "strip"
    ],
    "wof:name":"West Coast Wire & Steel",
    "wof:placetype":"venue"
},
  "geometry": {"coordinates":[-117.331817,34.004917],"type":"Point"}
}