{
  "type": "Feature",
  "properties": {
    "addr:full":"1166 London Way Napa CA 94559",
    "addr:housenumber":"1166",
    "addr:postcode":"94559",
    "addr:street":"London Way",
    "iso:country":"US",
    "sg:address":"1166 London Way",
    "sg:city":"Napa",
    "sg:classifiers":[
        {
            "category":"Building & Trades",
            "subcategory":"Construction",
            "type":"Services"
        }
    ],
    "sg:phone":"+1 707 255 6479",
    "sg:postcode":"94559",
    "sg:province":"CA",
    "sg:tags":[
        "roofing",
        "contractor"
    ],
    "wof:name":"Stubbs Roofing",
    "wof:placetype":"venue"
},
  "geometry": {"coordinates":[-122.26715900000001,38.284232],"type":"Point"}
}