{
  "type": "Feature",
  "properties": {
    "addr:full":"2075 Bering Dr San Jose CA 95131",
    "addr:housenumber":"2075",
    "addr:postcode":"95131",
    "addr:street":"Bering Dr",
    "iso:country":"US",
    "sg:address":"2075 Bering Dr",
    "sg:city":"San Jose",
    "sg:classifiers":[
        {
            "category":"Manufacturing",
            "subcategory":"Electronics",
            "type":"Manufacturing & Wholesale Goods"
        }
    ],
    "sg:phone":"+1 408 453 9882",
    "sg:postcode":"95131",
    "sg:province":"CA",
    "sg:tags":[
        "equipment",
        "electronic",
        "supply"
    ],
    "wof:name":"Advanced Modular Technology",
    "wof:placetype":"venue"
},
  "geometry": {"coordinates":[-121.917466,37.377095],"type":"Point"}
}