{
  "type": "Feature",
  "properties": {
    "addr:full":"202 W Lincoln Ave Ste G Orange CA 92865",
    "addr:housenumber":"202",
    "addr:postcode":"92865",
    "addr:street":"W Lincoln Ave Ste G",
    "iso:country":"US",
    "sg:address":"202 W Lincoln Ave Ste G",
    "sg:city":"Orange",
    "sg:classifiers":[
        {
            "category":"Real Estate",
            "subcategory":"Real Estate Services",
            "type":"Services"
        }
    ],
    "sg:phone":"+1 714 282 9684",
    "sg:postcode":"92865",
    "sg:province":"CA",
    "sg:tags":[
        "management",
        "property"
    ],
    "sg:website":"rpmocadvantage.com",
    "wof:name":"RPM OC Advantage",
    "wof:placetype":"venue"
},
  "geometry": {"coordinates":[-117.853782,33.835087],"type":"Point"}
}