{
  "type": "Feature",
  "properties": {
    "addr:full":"210 Lakeshire Dr Daly City CA 94015",
    "addr:housenumber":"210",
    "addr:postcode":"94015",
    "addr:street":"Lakeshire Dr",
    "iso:country":"US",
    "sg:address":"210 Lakeshire Dr",
    "sg:city":"Daly City",
    "sg:classifiers":[
        {
            "category":"Organizations",
            "subcategory":"Religious Organization",
            "type":"Services"
        }
    ],
    "sg:phone":"+1 650 992 5245",
    "sg:postcode":"94015",
    "sg:province":"CA",
    "sg:tags":[
        "church"
    ],
    "wof:name":"Jesus Christ Is Lord Church",
    "wof:placetype":"venue"
},
  "geometry": {"coordinates":[-122.483456,37.677275],"type":"Point"}
}