{
  "type": "Feature",
  "properties": {
    "addr:full":"3040 Saturn St Brea CA 92821",
    "addr:housenumber":"3040",
    "addr:postcode":"92821",
    "addr:street":"Saturn St",
    "iso:country":"US",
    "sg:address":"3040 Saturn St",
    "sg:city":"Brea",
    "sg:classifiers":[
        {
            "category":"Professional",
            "subcategory":"Accounting & Tax Preparation",
            "type":"Services"
        }
    ],
    "sg:phone":"+1 714 996 5492",
    "sg:postcode":"92821",
    "sg:province":"CA",
    "sg:tags":[
        "accountant"
    ],
    "wof:name":"Ferguson Metzner & Co",
    "wof:placetype":"venue"
},
  "geometry": {"coordinates":[-117.862573,33.90856],"type":"Point"}
}