{
  "type": "Feature",
  "properties": {
    "addr:full":"11052 Via el Mercado Los Alamitos CA 90720",
    "addr:housenumber":"11052",
    "addr:postcode":"90720",
    "addr:street":"Via El Mercado",
    "iso:country":"US",
    "sg:address":"11052 Via el Mercado",
    "sg:city":"Los Alamitos",
    "sg:classifiers":[
        {
            "category":"Wholesale",
            "subcategory":"Chemicals & Plastics",
            "type":"Manufacturing & Wholesale Goods"
        }
    ],
    "sg:phone":"+1 562 795 0470",
    "sg:postcode":"90720",
    "sg:province":"CA",
    "sg:tags":[
        "i",
        "industrial",
        "supply"
    ],
    "wof:name":"Fluid Recycling Service",
    "wof:placetype":"venue"
},
  "geometry": {"coordinates":[-118.038662,33.802001],"type":"Point"}
}