{
  "type": "Feature",
  "properties": {
    "addr:full":"5852 Burnet Ave Van Nuys CA 91411",
    "addr:housenumber":"5852",
    "addr:postcode":"91411",
    "addr:street":"Burnet Ave",
    "iso:country":"US",
    "sg:address":"5852 Burnet Ave",
    "sg:city":"Van Nuys",
    "sg:classifiers":[
        {
            "category":"Building & Trades",
            "subcategory":"Construction",
            "type":"Services"
        }
    ],
    "sg:phone":"+1 818 968 5777",
    "sg:postcode":"91411",
    "sg:province":"CA",
    "sg:tags":[
        "house"
    ],
    "wof:name":"Lego Construction Inc",
    "wof:placetype":"venue"
},
  "geometry": {"coordinates":[-118.462783,34.176588],"type":"Point"}
}