{
  "type": "Feature",
  "properties": {
    "addr:full":"1972 N St Firebaugh CA 93622",
    "addr:housenumber":"1972",
    "addr:postcode":"93622",
    "addr:street":"N St",
    "iso:country":"US",
    "sg:address":"1972 N St",
    "sg:city":"Firebaugh",
    "sg:classifiers":[
        {
            "category":"Farming",
            "subcategory":"Farm & Veterinary Services",
            "type":"Manufacturing & Wholesale Goods"
        }
    ],
    "sg:phone":"+1 559 659 2244",
    "sg:postcode":"93622",
    "sg:province":"CA",
    "sg:tags":[
        "seed",
        "grain",
        "cleaning"
    ],
    "wof:name":"Valley Seed Growers",
    "wof:placetype":"venue"
},
  "geometry": {"coordinates":[-120.450852,36.848383],"type":"Point"}
}