{
  "type": "Feature",
  "properties": {
    "iso:country":"US",
    "sg:address":"16027 Ventura Blvd",
    "sg:city":"Encino",
    "sg:classifiers":[
        {
            "category":"Home & Garden",
            "subcategory":"Furniture",
            "type":"Retail Goods"
        }
    ],
    "sg:phone":"+1 818 817 3100",
    "sg:postcode":"91436",
    "sg:province":"CA",
    "wof:name":"Viaquest",
    "wof:placetype":"venue"
},
  "geometry": {"coordinates":[-118.483125,34.156364],"type":"Point"}
}