{
  "type": "Feature",
  "properties": {
    "iso:country":"US",
    "sg:address":"2900 California St",
    "sg:city":"Oakland",
    "sg:classifiers":[
        {
            "category":"Building & Trades",
            "subcategory":"Landscaping Services",
            "type":"Services"
        }
    ],
    "sg:phone":"+1 510 530 5575",
    "sg:postcode":"94602",
    "sg:province":"CA",
    "sg:tags":[
        "lawn",
        "gardener",
        "maintenance",
        "ground"
    ],
    "wof:name":"Dawn's Gardening Service",
    "wof:placetype":"venue"
},
  "geometry": {"coordinates":[-122.203003,37.800098],"type":"Point"}
}