{
  "type": "Feature",
  "properties": {
    "addr:full":"15422 Crenshaw Blvd Gardena CA 90249",
    "addr:housenumber":"15422",
    "addr:postcode":"90249",
    "addr:street":"Crenshaw Blvd",
    "iso:country":"US",
    "sg:address":"15422 Crenshaw Blvd",
    "sg:city":"Gardena",
    "sg:classifiers":[
        {
            "category":"Health Services",
            "subcategory":"Dentist",
            "type":"Services"
        }
    ],
    "sg:phone":"+1 310 352 4939",
    "sg:postcode":"90249",
    "sg:province":"CA",
    "wof:name":"Vina Dental Group",
    "wof:placetype":"venue"
},
  "geometry": {"coordinates":[-118.32635399999999,33.890817],"type":"Point"}
}