{
  "type": "Feature",
  "properties": {
    "addr:full":"8065 Oasis St Fontana CA 92336",
    "addr:housenumber":"8065",
    "addr:postcode":"92336",
    "addr:street":"Oasis St",
    "iso:country":"US",
    "sg:address":"8065 Oasis St",
    "sg:city":"Fontana",
    "sg:classifiers":[
        {
            "category":"Shopping",
            "subcategory":"Luggage & Leather Goods",
            "type":"Retail Goods"
        }
    ],
    "sg:phone":"+1 909 350 3888",
    "sg:postcode":"92336",
    "sg:province":"CA",
    "sg:tags":[
        "portfolio"
    ],
    "wof:name":"Heritage Portfolios",
    "wof:placetype":"venue"
},
  "geometry": {"coordinates":[-117.496027,34.107586],"type":"Point"}
}