{
  "type": "Feature",
  "properties": {
    "iso:country":"US",
    "sg:address":"5246 E Beverly Blvd",
    "sg:city":"Los Angeles",
    "sg:classifiers":[
        {
            "category":"Personal",
            "subcategory":"Tattoo Parlor",
            "type":"Services"
        }
    ],
    "sg:phone":"+1 323 838 5903",
    "sg:postcode":"90022",
    "sg:province":"CA",
    "sg:tags":[
        "tattooing"
    ],
    "wof:name":"Thirteenth Floor Tattoo & Body",
    "wof:placetype":"venue"
},
  "geometry": {"coordinates":[-118.1529,34.031589],"type":"Point"}
}