{
  "type": "Feature",
  "properties": {
    "iso:country":"US",
    "sg:address":"117 W Main St",
    "sg:city":"Woodland",
    "sg:classifiers":[
        {
            "category":"Freight",
            "type":"Transportation"
        }
    ],
    "sg:phone":"+1 530 668 2410",
    "sg:postcode":"95695",
    "sg:province":"CA",
    "sg:tags":[
        "operator",
        "trucking"
    ],
    "wof:name":"Foothills Transportation Inc",
    "wof:placetype":"venue"
},
  "geometry": {"coordinates":[-121.790868,38.67754],"type":"Point"}
}