{
  "type": "Feature",
  "properties": {
    "addr:full":"712 D St San Rafael CA 94901",
    "addr:housenumber":"712",
    "addr:postcode":"94901",
    "addr:street":"D St",
    "iso:country":"US",
    "sg:address":"712 D St",
    "sg:city":"San Rafael",
    "sg:classifiers":[
        {
            "category":"Banks & Credit Unions",
            "subcategory":"Investment Brokerage",
            "type":"Services"
        }
    ],
    "sg:phone":"+1 415 457 5780",
    "sg:postcode":"94901",
    "sg:province":"CA",
    "sg:tags":[
        "preparation",
        "tax",
        "return"
    ],
    "wof:name":"Anspach Financial Services",
    "wof:placetype":"venue"
},
  "geometry": {"coordinates":[-122.532245,37.971416],"type":"Point"}
}