{
  "type": "Feature",
  "properties": {
    "addr:full":"180 Marguerite Avenue Mill Valley CA 94941",
    "addr:housenumber":"180",
    "addr:postcode":"94941",
    "addr:street":"Marguerite Avenue",
    "iso:country":"US",
    "sg:address":"180 Marguerite Avenue",
    "sg:city":"Mill Valley",
    "sg:classifiers":[
        {
            "category":"Professional",
            "subcategory":"Computer Services",
            "type":"Services"
        }
    ],
    "sg:postcode":"94941",
    "sg:province":"CA",
    "sg:tags":[
        "open",
        "business-directory",
        "search",
        "localsearch",
        "local-search",
        "global",
        "business-search",
        "reviews",
        "local-reviews",
        "business-reviews",
        "us",
        "uk",
        "canada",
        "australia",
        "wiki",
        "comments"
    ],
    "sg:website":"http://www.brownbook.net",
    "wof:name":"Brownbook.net",
    "wof:placetype":"venue"
},
  "geometry": {"coordinates":[-122.55545600000001,37.915537],"type":"Point"}
}