{
  "type": "Feature",
  "properties": {
    "iso:country":"US",
    "sg:address":"1701 Clearwood St",
    "sg:city":"Pittsburg",
    "sg:classifiers":[
        {
            "category":"Banks & Credit Unions",
            "subcategory":"Investment Brokerage",
            "type":"Services"
        }
    ],
    "sg:phone":"+1 925 261 9406",
    "sg:postcode":"94565",
    "sg:province":"CA",
    "sg:tags":[
        "advisory"
    ],
    "wof:name":"Real Estate Investors",
    "wof:placetype":"venue"
},
  "geometry": {"coordinates":[-121.94899700000001,38.01379],"type":"Point"}
}