{
  "type": "Feature",
  "properties": {
    "addr:full":"1350 Holman Rd Oakland CA 94610",
    "addr:housenumber":"1350",
    "addr:postcode":"94610",
    "addr:street":"Holman Rd",
    "iso:country":"US",
    "sg:address":"1350 Holman Rd",
    "sg:city":"Oakland",
    "sg:classifiers":[
        {
            "category":"Shopping",
            "subcategory":"Music",
            "type":"Retail Goods"
        }
    ],
    "sg:phone":"+1 510 834 0303",
    "sg:postcode":"94610",
    "sg:province":"CA",
    "wof:name":"Hillsdale Records",
    "wof:placetype":"venue"
},
  "geometry": {"coordinates":[-122.23043699999999,37.806291],"type":"Point"}
}