{
  "type": "Feature",
  "properties": {
    "addr:full":"333 S Anita Dr Orange CA 92868",
    "addr:housenumber":"333",
    "addr:postcode":"92868",
    "addr:street":"S Anita Dr",
    "iso:country":"US",
    "sg:address":"333 S Anita Dr",
    "sg:city":"Orange",
    "sg:classifiers":[
        {
            "category":"Professional",
            "subcategory":"Lawyer & Legal Services",
            "type":"Services"
        }
    ],
    "sg:phone":"+1 714 542 7520",
    "sg:postcode":"92868",
    "sg:province":"CA",
    "sg:tags":[
        "personal",
        "injury"
    ],
    "wof:name":"Kelley Susan C",
    "wof:placetype":"venue"
},
  "geometry": {"coordinates":[-117.881338,33.784012],"type":"Point"}
}