{
  "type": "Feature",
  "properties": {
    "iso:country":"US",
    "sg:address":"9801 Powerhouse Rd",
    "sg:city":"Newcastle",
    "sg:classifiers":[
        {
            "category":"Building & Trades",
            "subcategory":"Construction",
            "type":"Services"
        }
    ],
    "sg:phone":"+1 650 571 1250",
    "sg:postcode":"95658",
    "sg:province":"CA",
    "sg:tags":[
        "general",
        "contractor"
    ],
    "wof:name":"Grant Construction",
    "wof:placetype":"venue"
},
  "geometry": {"coordinates":[-121.111045,38.854788],"type":"Point"}
}