{
  "type": "Feature",
  "properties": {
    "addr:full":"222 W Lacey Blvd Hanford CA 93230",
    "addr:housenumber":"222",
    "addr:postcode":"ca 93230",
    "addr:street":"W Lacey Blvd",
    "iso:country":"US",
    "sg:address":"222 W Lacey Blvd",
    "sg:city":"Hanford",
    "sg:classifiers":[
        {
            "category":"Retail",
            "subcategory":"Laundry & Dry Cleaning",
            "type":"Services"
        }
    ],
    "sg:phone":"+1 559 584 2760",
    "sg:postcode":"93230",
    "sg:province":"CA",
    "sg:tags":[
        "cleaners"
    ],
    "wof:name":"Lamoure's Cleaners & Laundry",
    "wof:placetype":"venue"
},
  "geometry": {"coordinates":[-119.64920600000001,36.328042],"type":"Point"}
}