{
  "type": "Feature",
  "properties": {
    "addr:full":"321 Alvarado St Monterey CA 93940",
    "addr:housenumber":"321",
    "addr:postcode":"93940",
    "addr:street":"Alvarado St",
    "iso:country":"US",
    "sg:address":"321 Alvarado St",
    "sg:city":"Monterey",
    "sg:classifiers":[
        {
            "category":"Cinema",
            "subcategory":"Movie Theater",
            "type":"Entertainment"
        }
    ],
    "sg:phone":"+1 831 373 7678",
    "sg:postcode":"93940",
    "sg:province":"CA",
    "wof:name":"State Theatre Preservation Grp",
    "wof:placetype":"venue"
},
  "geometry": {"coordinates":[-121.894194,36.600128],"type":"Point"}
}