{
  "type": "Feature",
  "properties": {
    "iso:country":"US",
    "sg:address":"7270 8th St",
    "sg:city":"Buena Park",
    "sg:classifiers":[
        {
            "category":"Freight",
            "type":"Transportation"
        }
    ],
    "sg:phone":"+1 714 994 3857",
    "sg:postcode":"90621",
    "sg:province":"CA",
    "sg:tags":[
        "operator",
        "local",
        "trucking"
    ],
    "wof:name":"Manuel Cruz Trucking",
    "wof:placetype":"venue"
},
  "geometry": {"coordinates":[-118.005931,33.867104],"type":"Point"}
}