{
  "type": "Feature",
  "properties": {
    "addr:full":"1458 S San Pedro St Los Angeles CA 90015",
    "addr:housenumber":"1458",
    "addr:postcode":"90015",
    "addr:street":"S San Pedro St",
    "iso:country":"US",
    "sg:address":"1458 S San Pedro St",
    "sg:city":"Los Angeles",
    "sg:classifiers":[
        {
            "category":"Shopping",
            "subcategory":"Clothing, Apparel, & Fashions",
            "type":"Retail Goods"
        }
    ],
    "sg:phone":"+1 213 749 0379",
    "sg:postcode":"90015",
    "sg:province":"CA",
    "sg:tags":[
        "clothing",
        "women's"
    ],
    "wof:name":"Main Deal",
    "wof:placetype":"venue"
},
  "geometry": {"coordinates":[-118.254355,34.030459],"type":"Point"}
}