{
  "type": "Feature",
  "properties": {
    "addr:full":"20 City Blvd W Orange CA 92868",
    "addr:housenumber":"20",
    "addr:postcode":"92868",
    "addr:street":"City Blvd W",
    "iso:country":"US",
    "sg:address":"20 City Blvd W",
    "sg:city":"Orange",
    "sg:classifiers":[
        {
            "category":"Food & Beverages",
            "subcategory":"Bakery",
            "type":"Retail Goods"
        },
        {
            "category":"Bakery",
            "type":"Food & Drink"
        }
    ],
    "sg:phone":"+1 714 769 3438",
    "sg:postcode":"92868",
    "sg:province":"CA",
    "sg:tags":[
        "sandwich"
    ],
    "sg:website":"www.cornerbakerycafe.com/",
    "wof:name":"Corner Bakery Cafe",
    "wof:placetype":"venue"
},
  "geometry": {"coordinates":[-117.890579,33.783424],"type":"Point"}
}