{
  "type": "Feature",
  "properties": {
    "iso:country":"US",
    "sg:address":"3300 Vista Way",
    "sg:city":"Oceanside",
    "sg:classifiers":[
        {
            "category":"Health Services",
            "subcategory":"Doctor",
            "type":"Services"
        }
    ],
    "sg:phone":"+1 760 967 9204",
    "sg:postcode":"92056",
    "sg:province":"CA",
    "wof:name":"Barager R Richard",
    "wof:placetype":"venue"
},
  "geometry": {"coordinates":[-117.317481,33.18143],"type":"Point"}
}