{
  "type": "Feature",
  "properties": {
    "iso:country":"US",
    "sg:address":"8609 Dupree Ct",
    "sg:city":"Elk Grove",
    "sg:classifiers":[
        {
            "category":"Professional",
            "type":"Services"
        }
    ],
    "sg:phone":"+1 916 689 8597",
    "sg:postcode":"95624",
    "sg:province":"CA",
    "wof:name":"Tracy Brown",
    "wof:placetype":"venue"
},
  "geometry": {"coordinates":[-121.369159,38.444576],"type":"Point"}
}