{
  "type": "Feature",
  "properties": {
    "addr:full":"409 13th St 10th Fl Oakland CA 94612",
    "addr:housenumber":"409",
    "addr:postcode":"94612",
    "addr:street":"13Th St",
    "iso:country":"US",
    "sg:address":"409 13th St 10th Fl",
    "sg:city":"Oakland",
    "sg:classifiers":[
        {
            "category":"Banks & Credit Unions",
            "subcategory":"Atm",
            "type":"Services"
        }
    ],
    "sg:phone":"+1 510 465 0404",
    "sg:postcode":"94612",
    "sg:province":"CA",
    "sg:tags":[
        "bankruptcy"
    ],
    "sg:website":"Elkingtonlaw.com",
    "wof:name":"Sally J Elkington",
    "wof:placetype":"venue"
},
  "geometry": {"coordinates":[-122.270971,37.803112],"type":"Point"}
}