{
  "type": "Feature",
  "properties": {
    "iso:country":"US",
    "sg:address":"11687 Ramsdell Ct",
    "sg:city":"San Diego",
    "sg:classifiers":[
        {
            "category":"Shopping",
            "subcategory":"Gifts & Souvenirs",
            "type":"Retail Goods"
        }
    ],
    "sg:phone":"+1 858 549 4649",
    "sg:postcode":"92131",
    "sg:province":"CA",
    "wof:name":"Hallmark Consulting",
    "wof:placetype":"venue"
},
  "geometry": {"coordinates":[-117.098816,32.930622],"type":"Point"}
}