{
  "type": "Feature",
  "properties": {
    "addr:full":"700 Malaga Pl Ontario CA 91761",
    "addr:housenumber":"700",
    "addr:postcode":"91761",
    "addr:street":"Malaga Pl",
    "iso:country":"US",
    "sg:address":"700 Malaga Pl",
    "sg:city":"Ontario",
    "sg:classifiers":[
        {
            "category":"Wholesale",
            "subcategory":"Groceries",
            "type":"Manufacturing & Wholesale Goods"
        }
    ],
    "sg:phone":"+1 909 605 9662",
    "sg:postcode":"91761",
    "sg:province":"CA",
    "sg:tags":[
        "pizza"
    ],
    "wof:name":"Kraft Pizza",
    "wof:placetype":"venue"
},
  "geometry": {"coordinates":[-117.532033,34.057025],"type":"Point"}
}