{
  "type": "Feature",
  "properties": {
    "iso:country":"US",
    "sg:address":"36417 Seine Ct",
    "sg:city":"Winchester",
    "sg:classifiers":[
        {
            "category":"Education",
            "subcategory":"Preschool",
            "type":"Public Place"
        }
    ],
    "sg:phone":"+1 951 926 6241",
    "sg:postcode":"92596",
    "sg:province":"CA",
    "sg:tags":[
        "kindergarten"
    ],
    "wof:name":"Cranes Nest Family Preschool",
    "wof:placetype":"venue"
},
  "geometry": {"coordinates":[-117.112106,33.592857],"type":"Point"}
}