{
  "type": "Feature",
  "properties": {
    "addr:full":"2100 Webster St Ste 319 San Francisco CA 94115",
    "addr:housenumber":"2100",
    "addr:postcode":"94115",
    "addr:street":"Webster St Ste 319",
    "iso:country":"US",
    "sg:address":"2100 Webster St Ste 319",
    "sg:city":"San Francisco",
    "sg:classifiers":[
        {
            "category":"Health Services",
            "subcategory":"Doctor",
            "type":"Services"
        }
    ],
    "sg:phone":"+1 415 923 3123",
    "sg:postcode":"94115",
    "sg:province":"CA",
    "sg:website":"www.pgomg.yourmd.com",
    "wof:name":"Morey Filler, MD",
    "wof:placetype":"venue"
},
  "geometry": {"coordinates":[-122.432417,37.790082],"type":"Point"}
}