{
  "type": "Feature",
  "properties": {
    "addr:full":"2361 del Mar Rd Norco CA 92860",
    "addr:housenumber":"2361",
    "addr:postcode":"92860",
    "addr:street":"Del Mar Rd",
    "iso:country":"US",
    "sg:address":"2361 del Mar Rd",
    "sg:city":"Norco",
    "sg:classifiers":[
        {
            "category":"Building & Trades",
            "subcategory":"Plumbing",
            "type":"Services"
        }
    ],
    "sg:phone":"+1 951 371 1173",
    "sg:postcode":"92860",
    "sg:province":"CA",
    "sg:tags":[
        "conditioning",
        "contractor",
        "refrigeration",
        "system",
        "air"
    ],
    "wof:name":"Carroll William Industries",
    "wof:placetype":"venue"
},
  "geometry": {"coordinates":[-117.585587,33.916652],"type":"Point"}
}