{
  "type": "Feature",
  "properties": {
    "iso:country":"US",
    "sg:address":"130 Henderson Way",
    "sg:city":"Folsom",
    "sg:classifiers":[
        {
            "category":"Building & Trades",
            "subcategory":"Electrical",
            "type":"Services"
        }
    ],
    "sg:phone":"+1 916 351 1065",
    "sg:postcode":"95630",
    "sg:province":"CA",
    "sg:tags":[
        "electric",
        "contractor"
    ],
    "wof:name":"Camo Electric",
    "wof:placetype":"venue"
},
  "geometry": {"coordinates":[-121.15952299999999,38.680001],"type":"Point"}
}