{
  "type": "Feature",
  "properties": {
    "addr:full":"1200 Cape Cod Dr Modesto CA 95358",
    "addr:housenumber":"1200",
    "addr:postcode":"ca 95358",
    "addr:street":"Cape Cod Dr",
    "iso:country":"US",
    "sg:address":"1200 Cape Cod Dr",
    "sg:city":"Modesto",
    "sg:classifiers":[
        {
            "category":"Building & Trades",
            "subcategory":"Landscaping Services",
            "type":"Services"
        }
    ],
    "sg:phone":"+1 209 579 2605",
    "sg:postcode":"95358",
    "sg:province":"CA",
    "wof:name":"TLC Landscape Management",
    "wof:placetype":"venue"
},
  "geometry": {"coordinates":[-121.007931,37.603994],"type":"Point"}
}