{
  "type": "Feature",
  "properties": {
    "iso:country":"US",
    "sg:address":"9915 Rideau St",
    "sg:city":"Whittier",
    "sg:classifiers":[
        {
            "category":"Building & Trades",
            "subcategory":"Construction",
            "type":"Services"
        }
    ],
    "sg:phone":"+1 562 686 2744",
    "sg:postcode":"90601",
    "sg:province":"CA",
    "sg:tags":[
        "painter"
    ],
    "wof:name":"Los Painters",
    "wof:placetype":"venue"
},
  "geometry": {"coordinates":[-118.05953100000001,34.009603],"type":"Point"}
}