{
  "type": "Feature",
  "properties": {
    "addr:full":"1340 E Olympic Blvd Los Angeles CA 90021",
    "addr:housenumber":"1340",
    "addr:postcode":"90021",
    "addr:street":"E Olympic Blvd",
    "iso:country":"US",
    "sg:address":"1340 E Olympic Blvd",
    "sg:city":"Los Angeles",
    "sg:classifiers":[
        {
            "category":"Wholesale",
            "subcategory":"Fruits & Vegetables",
            "type":"Manufacturing & Wholesale Goods"
        }
    ],
    "sg:phone":"+1 213 623 6022",
    "sg:postcode":"90021",
    "sg:province":"CA",
    "sg:tags":[
        "veggie"
    ],
    "wof:name":"Garlic & Spice Inc",
    "wof:placetype":"venue"
},
  "geometry": {"coordinates":[-118.243878,34.164506],"type":"Point"}
}