{
  "type": "Feature",
  "properties": {
    "iso:country":"US",
    "sg:address":"12555 High Bluff Dr",
    "sg:city":"San Diego",
    "sg:classifiers":[
        {
            "category":"Professional",
            "subcategory":"Computer Services",
            "type":"Services"
        }
    ],
    "sg:phone":"+1 858 792 3000",
    "sg:postcode":"92130",
    "sg:province":"CA",
    "sg:tags":[
        "reporting",
        "datum"
    ],
    "wof:name":"Web Medics",
    "wof:placetype":"venue"
},
  "geometry": {"coordinates":[-117.240555,32.947479],"type":"Point"}
}