{
  "type": "Feature",
  "properties": {
    "addr:full":"5976 W Las Positas Blvd Pleasanton CA 94588",
    "addr:housenumber":"5976",
    "addr:postcode":"94588",
    "addr:street":"W Las Positas Blvd",
    "iso:country":"US",
    "sg:address":"5976 W Las Positas Blvd",
    "sg:city":"Pleasanton",
    "sg:classifiers":[
        {
            "category":"Manufacturing",
            "subcategory":"Food",
            "type":"Manufacturing & Wholesale Goods"
        }
    ],
    "sg:phone":"+1 925 460 9015",
    "sg:postcode":"94588",
    "sg:province":"CA",
    "sg:tags":[
        "product",
        "manufacturer"
    ],
    "wof:name":"Long Oliva & Assoc",
    "wof:placetype":"venue"
},
  "geometry": {"coordinates":[-121.901652,37.682264],"type":"Point"}
}