{
  "type": "Feature",
  "properties": {
    "addr:full":"21247 Questhaven Rd. Escondido CA 92029",
    "addr:housenumber":"21247",
    "addr:postcode":"92029",
    "addr:street":"Questhaven Rd.",
    "iso:country":"US",
    "sg:address":"21247 Questhaven Rd.",
    "sg:city":"Escondido",
    "sg:classifiers":[
        {
            "category":"Home & Garden",
            "subcategory":"Household Appliances",
            "type":"Retail Goods"
        },
        {
            "category":"Utilities",
            "subcategory":"Recycling",
            "type":"Services"
        },
        {
            "category":"Building & Trades",
            "subcategory":"Cleaning & Sanitation",
            "type":"Services"
        }
    ],
    "sg:phone":"+1 760 522 9998",
    "sg:postcode":"92029",
    "sg:province":"CA",
    "sg:tags":[
        "collecting",
        "system",
        "chemical",
        "equipment",
        "systems-pressure",
        "vacuum",
        "dust"
    ],
    "wof:name":"Spike Inc.",
    "wof:placetype":"venue"
},
  "geometry": {"coordinates":[-117.174465,33.097013],"type":"Point"}
}