{
  "type": "Feature",
  "properties": {
    "addr:full":"510 Civic Center Dr Oceanside CA 92054",
    "addr:housenumber":"510",
    "addr:postcode":"92054",
    "addr:street":"Civic Center Dr",
    "iso:country":"US",
    "sg:address":"510 Civic Center Dr",
    "sg:city":"Oceanside",
    "sg:classifiers":[
        {
            "category":"Manufacturing",
            "subcategory":"Signs",
            "type":"Manufacturing & Wholesale Goods"
        }
    ],
    "sg:phone":"+1 760 433 6366",
    "sg:postcode":"92054",
    "sg:province":"CA",
    "sg:tags":[
        "specialty",
        "mfg"
    ],
    "wof:name":"Sign Shop",
    "wof:placetype":"venue"
},
  "geometry": {"coordinates":[-117.380691,33.197869],"type":"Point"}
}