{
  "type": "Feature",
  "properties": {
    "addr:full":"5601 Hemlock St Sacramento CA 95841",
    "addr:housenumber":"5601",
    "addr:postcode":"95841",
    "addr:street":"Hemlock St",
    "iso:country":"US",
    "sg:address":"5601 Hemlock St",
    "sg:city":"Sacramento",
    "sg:classifiers":[
        {
            "category":"Place Of Worship",
            "subcategory":"Church",
            "type":"Public Place"
        }
    ],
    "sg:phone":"+1 916 332 2434",
    "sg:postcode":"95841",
    "sg:province":"CA",
    "sg:tags":[
        "churches-baptist-american"
    ],
    "wof:name":"First Baptist Church Of Foothill Farms ABC",
    "wof:placetype":"venue"
},
  "geometry": {"coordinates":[-121.341263,38.66806],"type":"Point"}
}