{
  "type": "Feature",
  "properties": {
    "iso:country":"US",
    "sg:address":"1519 La Cienega Blvd",
    "sg:city":"Los Angeles",
    "sg:classifiers":[
        {
            "category":"Professional",
            "subcategory":"Lawyer & Legal Services",
            "type":"Services"
        },
        {
            "category":"Travel",
            "subcategory":"Travel Agent",
            "type":"Entertainment"
        }
    ],
    "sg:phone":"+1 310 272 9156",
    "sg:postcode":"90035",
    "sg:province":"CA",
    "sg:tags":[
        "notary"
    ],
    "sg:website":"24houruspassport.com/",
    "wof:name":"24hour US Passport Service Center",
    "wof:placetype":"venue"
},
  "geometry": {"coordinates":[-118.376355,34.05017],"type":"Point"}
}