{
  "type": "Feature",
  "properties": {
    "addr:full":"9464 Palomino Ridge Dr Lakeside CA 92040",
    "addr:housenumber":"9464",
    "addr:postcode":"92040",
    "addr:street":"Palomino Ridge Dr",
    "iso:country":"US",
    "sg:address":"9464 Palomino Ridge Dr",
    "sg:city":"Lakeside",
    "sg:classifiers":[
        {
            "category":"Building & Trades",
            "subcategory":"Plumbing",
            "type":"Services"
        }
    ],
    "sg:phone":"+1 619 447 6467",
    "sg:postcode":"92040",
    "sg:province":"CA",
    "sg:tags":[
        "conditioning",
        "air",
        "system",
        "contractor"
    ],
    "wof:name":"Steve Bailey Air Cond Heating",
    "wof:placetype":"venue"
},
  "geometry": {"coordinates":[-116.878204,32.851947],"type":"Point"}
}