{
  "type": "Feature",
  "properties": {
    "addr:full":"983 Mission de Oro Dr Ste F Redding CA 96003",
    "addr:housenumber":"983",
    "addr:postcode":"96003",
    "addr:street":"Mission De Oro Dr Ste F",
    "iso:country":"US",
    "sg:address":"983 Mission de Oro Dr Ste F",
    "sg:city":"Redding",
    "sg:classifiers":[
        {
            "category":"Banks & Credit Unions",
            "subcategory":"Investment Brokerage",
            "type":"Services"
        },
        {
            "category":"Banks & Credit Unions",
            "subcategory":"Financial Services",
            "type":"Services"
        }
    ],
    "sg:phone":"+1 530 221 3880",
    "sg:postcode":"96003",
    "sg:province":"CA",
    "sg:tags":[
        "management",
        "mortgage"
    ],
    "wof:name":"Redding Mortgage Investments Inc",
    "wof:placetype":"venue"
},
  "geometry": {"coordinates":[-122.357558,40.593142],"type":"Point"}
}