{
  "type": "Feature",
  "properties": {
    "addr:full":"81 N Sanborn Rd Salinas CA 93905",
    "addr:housenumber":"81",
    "addr:postcode":"93905",
    "addr:street":"N Sanborn Rd",
    "iso:country":"US",
    "sg:address":"81 N Sanborn Rd",
    "sg:city":"Salinas",
    "sg:classifiers":[
        {
            "category":"Retail",
            "subcategory":"Auto Repair",
            "type":"Services"
        }
    ],
    "sg:phone":"+1 831 424 0011",
    "sg:postcode":"93905",
    "sg:province":"CA",
    "sg:tags":[
        "repairing",
        "automobile"
    ],
    "wof:name":"Rossi's Tire & Auto Svc",
    "wof:placetype":"venue"
},
  "geometry": {"coordinates":[-121.62753600000001,36.67536],"type":"Point"}
}