{
  "type": "Feature",
  "properties": {
    "addr:full":"5474 College Ave Oakland CA 94618",
    "addr:housenumber":"5474",
    "addr:postcode":"94618",
    "addr:street":"College Ave",
    "iso:country":"US",
    "sg:address":"5474 College Ave",
    "sg:city":"Oakland",
    "sg:classifiers":[
        {
            "category":"Shopping",
            "subcategory":"Used Merchandise",
            "type":"Retail Goods"
        }
    ],
    "sg:phone":"+1 510 653 1525",
    "sg:postcode":"94618",
    "sg:province":"CA",
    "sg:tags":[
        "vintage",
        "consignment"
    ],
    "wof:name":"Madame Butterfly",
    "wof:placetype":"venue"
},
  "geometry": {"coordinates":[-122.25099899999999,37.840099],"type":"Point"}
}