{
  "type": "Feature",
  "properties": {
    "iso:country":"US",
    "sg:address":"1424 14th St",
    "sg:city":"Sacramento",
    "sg:classifiers":[
        {
            "category":"Retail",
            "subcategory":"Laundry & Dry Cleaning",
            "type":"Services"
        }
    ],
    "sg:phone":"+1 916 441 4241",
    "sg:postcode":"95814",
    "sg:province":"CA",
    "sg:tags":[
        "cleaner"
    ],
    "wof:name":"Capital Dry Clean",
    "wof:placetype":"venue"
},
  "geometry": {"coordinates":[-121.490144,38.57356],"type":"Point"}
}