{
  "type": "Feature",
  "properties": {
    "addr:full":"8404 N Magnolia Ave Santee CA 92071",
    "addr:housenumber":"8404",
    "addr:postcode":"92071",
    "addr:street":"N Magnolia Ave",
    "iso:country":"US",
    "sg:address":"8404 N Magnolia Ave",
    "sg:city":"Santee",
    "sg:classifiers":[
        {
            "category":"Shopping",
            "type":"Retail Goods"
        }
    ],
    "sg:phone":"+1 619 562 1455",
    "sg:postcode":"92071",
    "sg:province":"CA",
    "sg:tags":[
        "wedding",
        "supply"
    ],
    "wof:name":"Butler Group Event Design",
    "wof:placetype":"venue"
},
  "geometry": {"coordinates":[-116.962406,32.829437],"type":"Point"}
}