{
  "type": "Feature",
  "properties": {
    "addr:full":"6161 El Cajon Blvd Ste B San Diego CA 92115",
    "addr:housenumber":"6161",
    "addr:postcode":"92115",
    "addr:street":"El Cajon Blvd Ste B",
    "iso:country":"US",
    "sg:address":"6161 El Cajon Blvd Ste B",
    "sg:city":"San Diego",
    "sg:classifiers":[
        {
            "category":"Professional",
            "subcategory":"Business Services",
            "type":"Services"
        }
    ],
    "sg:phone":"+1 619 286 7888",
    "sg:postcode":"92115",
    "sg:province":"CA",
    "sg:tags":[
        "delivery",
        "courier"
    ],
    "wof:name":"College Postal Plus",
    "wof:placetype":"venue"
},
  "geometry": {"coordinates":[-117.06465300000001,32.761693],"type":"Point"}
}