{
  "type": "Feature",
  "properties": {
    "iso:country":"US",
    "sg:address":"16890 State Highway 14",
    "sg:city":"Mojave",
    "sg:classifiers":[
        {
            "category":"Shopping",
            "subcategory":"Department Store",
            "type":"Retail Goods"
        }
    ],
    "sg:phone":"+1 661 824 2278",
    "sg:postcode":"93501",
    "sg:province":"CA",
    "wof:name":"Mojave Departement Store",
    "wof:placetype":"venue"
},
  "geometry": {"coordinates":[-118.176669,35.067277],"type":"Point"}
}