{
  "type": "Feature",
  "properties": {
    "addr:full":"3935 Goodland Ave Studio City CA 91604",
    "addr:housenumber":"3935",
    "addr:postcode":"91604",
    "addr:street":"Goodland Ave",
    "iso:country":"US",
    "sg:address":"3935 Goodland Ave",
    "sg:city":"Studio City",
    "sg:classifiers":[
        {
            "category":"Professional",
            "subcategory":"Management & Consulting",
            "type":"Services"
        }
    ],
    "sg:phone":"+1 818 769 6688",
    "sg:postcode":"91604",
    "sg:province":"CA",
    "sg:tags":[
        "consultant",
        "educational"
    ],
    "wof:name":"Edilife",
    "wof:placetype":"venue"
},
  "geometry": {"coordinates":[-118.406229,34.137012],"type":"Point"}
}