{
  "type": "Feature",
  "properties": {
    "iso:country":"US",
    "sg:address":"2400 Sand Hill Rd",
    "sg:city":"Menlo Park",
    "sg:classifiers":[
        {
            "category":"Professional",
            "subcategory":"Research",
            "type":"Services"
        }
    ],
    "sg:phone":"+1 650 854 9400",
    "sg:postcode":"94025",
    "sg:province":"CA",
    "sg:tags":[
        "foundation",
        "philanthropic"
    ],
    "sg:website":"www.kff.org",
    "wof:name":"Henry J Kaiser Family Fndtn",
    "wof:placetype":"venue"
},
  "geometry": {"coordinates":[-122.198734,37.422112],"type":"Point"}
}