{
  "type": "Feature",
  "properties": {
    "iso:country":"US",
    "sg:address":"3312 Industry Dr",
    "sg:city":"Signal Hill",
    "sg:classifiers":[
        {
            "category":"Building & Trades",
            "subcategory":"Pest Control",
            "type":"Services"
        }
    ],
    "sg:phone":"+1 562 597 9200",
    "sg:postcode":"90755",
    "sg:province":"CA",
    "wof:name":"Magic Care Termite Inc",
    "wof:placetype":"venue"
},
  "geometry": {"coordinates":[-118.153851,33.799285],"type":"Point"}
}