{
  "type": "Feature",
  "properties": {
    "iso:country":"US",
    "sg:address":"2570 E Orange Grove Blvd",
    "sg:city":"Pasadena",
    "sg:classifiers":[
        {
            "category":"Professional",
            "type":"Services"
        }
    ],
    "sg:phone":"+1 626 844 3445",
    "sg:postcode":"91107",
    "sg:province":"CA",
    "wof:name":"FDIC Postal Escrow",
    "wof:placetype":"venue"
},
  "geometry": {"coordinates":[-118.094986,34.158256],"type":"Point"}
}