{
  "type": "Feature",
  "properties": {
    "addr:full":"1812 Tice Valley Blvd Walnut Creek CA 94595",
    "addr:housenumber":"1812",
    "addr:postcode":"94595",
    "addr:street":"Tice Valley Blvd",
    "iso:country":"US",
    "sg:address":"1812 Tice Valley Blvd",
    "sg:city":"Walnut Creek",
    "sg:classifiers":[
        {
            "category":"Shopping",
            "subcategory":"Clothing, Apparel, & Fashions",
            "type":"Retail Goods"
        }
    ],
    "sg:phone":"+1 925 274 0243",
    "sg:postcode":"94595",
    "sg:province":"CA",
    "sg:tags":[
        "wear",
        "accessory"
    ],
    "wof:name":"Cathy's Fashions",
    "wof:placetype":"venue"
},
  "geometry": {"coordinates":[-122.07508900000001,37.879517],"type":"Point"}
}