{
  "type": "Feature",
  "properties": {
    "addr:full":"6411 Mitchell Ave Riverside CA 92505",
    "addr:housenumber":"6411",
    "addr:postcode":"92505",
    "addr:street":"Mitchell Ave",
    "iso:country":"US",
    "sg:address":"6411 Mitchell Ave",
    "sg:city":"Riverside",
    "sg:classifiers":[
        {
            "category":"Education",
            "subcategory":"School",
            "type":"Public Place"
        }
    ],
    "sg:phone":"+1 951 351 7528",
    "sg:postcode":"92505",
    "sg:province":"CA",
    "wof:name":"Rosemary Kennedy Elementary",
    "wof:placetype":"venue"
},
  "geometry": {"coordinates":[-117.491337,33.949206],"type":"Point"}
}