{
  "type": "Feature",
  "properties": {
    "addr:full":"10217 Oso Ave Chatsworth CA 91311",
    "addr:housenumber":"10217",
    "addr:postcode":"91311",
    "addr:street":"Oso Ave",
    "iso:country":"US",
    "sg:address":"10217 Oso Ave",
    "sg:city":"Chatsworth",
    "sg:classifiers":[
        {
            "category":"Retail",
            "subcategory":"Repair Shop",
            "type":"Services"
        }
    ],
    "sg:phone":"+1 818 341 4081",
    "sg:postcode":"91311",
    "sg:province":"CA",
    "sg:tags":[
        "electrical",
        "merchandise"
    ],
    "wof:name":"Ideal Typtr & Bus Mch Comp",
    "wof:placetype":"venue"
},
  "geometry": {"coordinates":[-118.575036,34.257053],"type":"Point"}
}