{
  "type": "Feature",
  "properties": {
    "addr:full":"9555 Old Castle Rd Valley Center CA 92082",
    "addr:housenumber":"9555",
    "addr:postcode":"92082",
    "addr:street":"Old Castle Rd",
    "iso:country":"US",
    "sg:address":"9555 Old Castle Rd",
    "sg:city":"Valley Center",
    "sg:classifiers":[
        {
            "category":"Professional",
            "subcategory":"Business Services",
            "type":"Services"
        }
    ],
    "sg:phone":"+1 760 749 2732",
    "sg:postcode":"92082",
    "sg:province":"CA",
    "sg:tags":[
        "interior",
        "consultant",
        "design",
        "decorator"
    ],
    "wof:name":"LA Maison",
    "wof:placetype":"venue"
},
  "geometry": {"coordinates":[-117.118607,33.251293],"type":"Point"}
}