{
  "type": "Feature",
  "properties": {
    "iso:country":"US",
    "sg:address":"5829 Atlantic Ave",
    "sg:city":"Long Beach",
    "sg:classifiers":[
        {
            "category":"Wholesale",
            "subcategory":"Non-durable Goods",
            "type":"Manufacturing & Wholesale Goods"
        }
    ],
    "sg:phone":"+1 562 422 0635",
    "sg:postcode":"90805",
    "sg:province":"CA",
    "wof:name":"Hanlico USA Co",
    "wof:placetype":"venue"
},
  "geometry": {"coordinates":[-118.185052,33.861363],"type":"Point"}
}