{
  "type": "Feature",
  "properties": {
    "addr:full":"25375 Mission Blvd Hayward CA 94544",
    "addr:housenumber":"25375",
    "addr:postcode":"94544",
    "addr:street":"Mission Blvd",
    "iso:country":"US",
    "sg:address":"25375 Mission Blvd",
    "sg:city":"Hayward",
    "sg:classifiers":[
        {
            "category":"Autos & Motor Vehicles",
            "subcategory":"Automobile Sales",
            "type":"Retail Goods"
        }
    ],
    "sg:phone":"+1 510 581 2700",
    "sg:postcode":"94544",
    "sg:province":"CA",
    "sg:tags":[
        "car"
    ],
    "sg:website":"www.bayautodealers.com",
    "wof:name":"Bay Auto Dealers",
    "wof:placetype":"venue"
},
  "geometry": {"coordinates":[-122.071793,37.656267],"type":"Point"}
}