{
  "type": "Feature",
  "properties": {
    "iso:country":"US",
    "sg:address":"2535 Kettner Boulevard Suite 1",
    "sg:city":"San Diego",
    "sg:classifiers":[
        {
            "category":"Landmark",
            "subcategory":"Tourist Information",
            "type":"Public Place"
        }
    ],
    "sg:phone":"+1 619 232 1108",
    "sg:postcode":"92101",
    "sg:province":"CA",
    "sg:tags":[
        "tour"
    ],
    "wof:name":"Break Away Tours",
    "wof:placetype":"venue"
},
  "geometry": {"coordinates":[-117.17209200000001,32.730397],"type":"Point"}
}