{
  "type": "Feature",
  "properties": {
    "addr:full":"2077 Swan Pl Fairfield CA 94533",
    "addr:housenumber":"2077",
    "addr:postcode":"94533",
    "addr:street":"Swan Pl",
    "iso:country":"US",
    "sg:address":"2077 Swan Pl",
    "sg:city":"Fairfield",
    "sg:classifiers":[
        {
            "category":"Freight",
            "type":"Transportation"
        }
    ],
    "sg:phone":"+1 707 427 3357",
    "sg:postcode":"94533",
    "sg:province":"CA",
    "sg:tags":[
        "operator",
        "trucking"
    ],
    "wof:name":"Amigo Services",
    "wof:placetype":"venue"
},
  "geometry": {"coordinates":[-122.017501,38.271397],"type":"Point"}
}