{
  "type": "Feature",
  "properties": {
    "iso:country":"US",
    "sg:address":"23898 Madison St",
    "sg:city":"Torrance",
    "sg:classifiers":[
        {
            "category":"Building & Trades",
            "subcategory":"Plumbing",
            "type":"Services"
        }
    ],
    "sg:phone":"+1 310 378 3715",
    "sg:postcode":"90505",
    "sg:province":"CA",
    "sg:tags":[
        "sheet",
        "work",
        "metal",
        "contractor"
    ],
    "wof:name":"Talins Co",
    "wof:placetype":"venue"
},
  "geometry": {"coordinates":[-118.348625,33.809964],"type":"Point"}
}