{
  "type": "Feature",
  "properties": {
    "addr:full":"17653 Chatsworth St Granada Hills CA 91344",
    "addr:housenumber":"17653",
    "addr:postcode":"91344",
    "addr:street":"Chatsworth St",
    "iso:country":"US",
    "sg:address":"17653 Chatsworth St",
    "sg:city":"Granada Hills",
    "sg:classifiers":[
        {
            "category":"Personal",
            "subcategory":"Beauty Salon",
            "type":"Services"
        }
    ],
    "sg:phone":"+1 818 366 1084",
    "sg:postcode":"91344",
    "sg:province":"CA",
    "wof:name":"Hair & Makeup By Tina",
    "wof:placetype":"venue"
},
  "geometry": {"coordinates":[-118.518783,34.26495],"type":"Point"}
}