{
  "type": "Feature",
  "properties": {
    "iso:country":"US",
    "sg:address":"11165 Sepulveda Blvd",
    "sg:city":"Mission Hills",
    "sg:classifiers":[
        {
            "category":"Health Services",
            "subcategory":"Clinic",
            "type":"Services"
        }
    ],
    "sg:phone":"+1 818 365 9531",
    "sg:postcode":"91345",
    "sg:province":"CA",
    "sg:tags":[
        "organization",
        "provider"
    ],
    "wof:name":"Facey Medical Foundation",
    "wof:placetype":"venue"
},
  "geometry": {"coordinates":[-118.467822,34.273521],"type":"Point"}
}