{
  "type": "Feature",
  "properties": {
    "addr:full":"325 Grove St Bishop CA 93514",
    "addr:housenumber":"325",
    "addr:postcode":"93514",
    "addr:street":"Grove St",
    "iso:country":"US",
    "sg:address":"325 Grove St",
    "sg:city":"Bishop",
    "sg:classifiers":[
        {
            "category":"Health Services",
            "subcategory":"Doctor",
            "type":"Services"
        }
    ],
    "sg:phone":"+1 760 873 6513",
    "sg:postcode":"93514",
    "sg:province":"CA",
    "sg:tags":[
        "dentist"
    ],
    "wof:name":"E Joseph Duncan DDS",
    "wof:placetype":"venue"
},
  "geometry": {"coordinates":[-118.397992,37.364705],"type":"Point"}
}