{
  "type": "Feature",
  "properties": {
    "addr:full":"366 40th St Oakland CA 94609",
    "addr:housenumber":"366",
    "addr:postcode":"94609",
    "addr:street":"40Th St",
    "iso:country":"US",
    "sg:address":"366 40th St",
    "sg:city":"Oakland",
    "sg:classifiers":[
        {
            "category":"Professional",
            "subcategory":"Management & Consulting",
            "type":"Services"
        }
    ],
    "sg:phone":"+1 510 893 3271",
    "sg:postcode":"94609",
    "sg:province":"CA",
    "sg:tags":[
        "counselor",
        "relation",
        "public"
    ],
    "wof:name":"One Pr Studios",
    "wof:placetype":"venue"
},
  "geometry": {"coordinates":[-122.258526,37.828191],"type":"Point"}
}