{
  "type": "Feature",
  "properties": {
    "iso:country":"US",
    "sg:address":"2015 McKinnon Ave",
    "sg:city":"San Francisco",
    "sg:classifiers":[
        {
            "category":"Freight",
            "type":"Transportation"
        }
    ],
    "sg:phone":"+1 415 826 5600",
    "sg:postcode":"94124",
    "sg:province":"CA",
    "sg:tags":[
        "operator",
        "trucking"
    ],
    "wof:name":"Four Brothers Trnsp Co",
    "wof:placetype":"venue"
},
  "geometry": {"coordinates":[-122.398368,37.740907],"type":"Point"}
}