{
  "type": "Feature",
  "properties": {
    "iso:country":"US",
    "sg:address":"8641 Wilshire Blvd",
    "sg:city":"Beverly Hills",
    "sg:classifiers":[
        {
            "category":"Organizations",
            "subcategory":"Non-profit Organization",
            "type":"Services"
        }
    ],
    "sg:phone":"+1 310 358 5757",
    "sg:postcode":"90211",
    "sg:province":"CA",
    "sg:tags":[
        "medical",
        "center"
    ],
    "wof:name":"Osteoporosis Medical Center",
    "wof:placetype":"venue"
},
  "geometry": {"coordinates":[-118.379801,34.066426],"type":"Point"}
}