{
  "type": "Feature",
  "properties": {
    "addr:full":"2457 Sawtelle Blvd Los Angeles CA 90064",
    "addr:housenumber":"2457",
    "addr:postcode":"90064",
    "addr:street":"Sawtelle Blvd",
    "iso:country":"US",
    "sg:address":"2457 Sawtelle Blvd",
    "sg:city":"Los Angeles",
    "sg:classifiers":[
        {
            "category":"Education",
            "subcategory":"Preschool",
            "type":"Public Place"
        },
        {
            "category":"Education",
            "subcategory":"School",
            "type":"Public Place"
        }
    ],
    "sg:phone":"+1 310 473 0772",
    "sg:postcode":"90064",
    "sg:province":"CA",
    "sg:tags":[
        "elementary"
    ],
    "wof:name":"Wonder Years Pre-School",
    "wof:placetype":"venue"
},
  "geometry": {"coordinates":[-118.43699599999999,34.033901],"type":"Point"}
}