{
  "type": "Feature",
  "properties": {
    "iso:country":"US",
    "sg:address":"9187 Valley View St",
    "sg:city":"Cypress",
    "sg:classifiers":[
        {
            "category":"Shopping",
            "subcategory":"Gifts & Souvenirs",
            "type":"Retail Goods"
        }
    ],
    "sg:phone":"+1 714 527 7821",
    "sg:postcode":"90630",
    "sg:province":"CA",
    "sg:tags":[
        "novelty"
    ],
    "wof:name":"Lucky D Designs Duds & Decor",
    "wof:placetype":"venue"
},
  "geometry": {"coordinates":[-118.028285,33.82742],"type":"Point"}
}