{
  "type": "Feature",
  "properties": {
    "iso:country":"US",
    "sg:address":"3647 Overland Ave",
    "sg:city":"Los Angeles",
    "sg:classifiers":[
        {
            "category":"Health Services",
            "subcategory":"Dentist",
            "type":"Services"
        }
    ],
    "sg:phone":"+1 310 559 7789",
    "sg:postcode":"90034",
    "sg:province":"CA",
    "sg:website":"www.archangelic-care.com",
    "wof:name":"Archangelic Dental Care",
    "wof:placetype":"venue"
},
  "geometry": {"coordinates":[-118.409504,34.021932],"type":"Point"}
}