{
  "type": "Feature",
  "properties": {
    "addr:full":"5180 N Fresno St Fresno CA 93710",
    "addr:housenumber":"5180",
    "addr:postcode":"93710",
    "addr:street":"N Fresno",
    "iso:country":"US",
    "sg:address":"5180 N Fresno St",
    "sg:city":"Fresno",
    "sg:classifiers":[
        {
            "category":"Health Services",
            "subcategory":"Health Practitioner",
            "type":"Services"
        }
    ],
    "sg:phone":"+1 559 224 1344",
    "sg:postcode":"93710",
    "sg:province":"CA",
    "sg:tags":[
        "audiologists"
    ],
    "wof:name":"Dorian Hearing Ctr",
    "wof:placetype":"venue"
},
  "geometry": {"coordinates":[-119.781282,36.811583],"type":"Point"}
}