{
  "type": "Feature",
  "properties": {
    "iso:country":"US",
    "sg:address":"1172 San Pablo Avenue Suite 103",
    "sg:city":"Albany",
    "sg:classifiers":[
        {
            "category":"Professional",
            "subcategory":"Computer Services",
            "type":"Services"
        }
    ],
    "sg:phone":"+1 510 527 4005",
    "sg:postcode":"94706",
    "sg:province":"CA",
    "sg:tags":[
        "repair"
    ],
    "wof:name":"Ammari Electronics",
    "wof:placetype":"venue"
},
  "geometry": {"coordinates":[-122.296997,37.883202],"type":"Point"}
}