{
  "type": "Feature",
  "properties": {
    "iso:country":"US",
    "sg:address":"1205 Coleman Ave",
    "sg:city":"Santa Clara",
    "sg:classifiers":[
        {
            "category":"Travel",
            "subcategory":"Travel Agent",
            "type":"Entertainment"
        }
    ],
    "sg:phone":"+1 408 289 2731",
    "sg:postcode":"95110",
    "sg:province":"CA",
    "sg:tags":[
        "agency"
    ],
    "wof:name":"American Express",
    "wof:placetype":"venue"
},
  "geometry": {"coordinates":[-121.934664,37.356704],"type":"Point"}
}