{
  "type": "Feature",
  "properties": {
    "iso:country":"US",
    "sg:address":"200 Lido Pl",
    "sg:city":"Fullerton",
    "sg:classifiers":[
        {
            "category":"Shopping",
            "subcategory":"Stationery & Office Supplies",
            "type":"Retail Goods"
        },
        {
            "category":"Manufacturing",
            "subcategory":"Paper Products",
            "type":"Manufacturing & Wholesale Goods"
        }
    ],
    "sg:phone":"+1 714 992 8038",
    "sg:postcode":"92835",
    "sg:province":"CA",
    "sg:tags":[
        "stationery-wholesale",
        "store",
        "manufacturer"
    ],
    "wof:name":"Mailbox Surprises",
    "wof:placetype":"venue"
},
  "geometry": {"coordinates":[-117.930817,33.89994],"type":"Point"}
}