{
  "type": "Feature",
  "properties": {
    "addr:full":"2200 W Florida Ave Hemet CA 92545",
    "addr:housenumber":"2200",
    "addr:postcode":"92545",
    "addr:street":"W Florida Ave",
    "iso:country":"US",
    "sg:address":"2200 W Florida Ave",
    "sg:city":"Hemet",
    "sg:classifiers":[
        {
            "category":"Shopping",
            "subcategory":"Photographic Equipment",
            "type":"Retail Goods"
        }
    ],
    "sg:phone":"+1 951 929 2244",
    "sg:postcode":"92545",
    "sg:province":"CA",
    "sg:tags":[
        "supply"
    ],
    "wof:name":"Kits Cameras",
    "wof:placetype":"venue"
},
  "geometry": {"coordinates":[-116.9945,33.747505],"type":"Point"}
}