{
  "type": "Feature",
  "properties": {
    "iso:country":"US",
    "sg:address":"San Francisco International Airport",
    "sg:city":"San Francisco",
    "sg:classifiers":[
        {
            "category":"Airline",
            "type":"Transportation"
        },
        {
            "category":"Local Transit",
            "type":"Transportation"
        }
    ],
    "sg:phone":"+1 650 821 8211",
    "sg:postcode":"94128",
    "sg:province":"CA",
    "sg:tags":[
        "shuttle",
        "airport",
        "public"
    ],
    "sg:website":"www.flysfo.com",
    "wof:name":"AirTrain",
    "wof:placetype":"venue"
},
  "geometry": {"coordinates":[-122.389979,37.615223],"type":"Point"}
}