{
  "type": "Feature",
  "properties": {
    "addr:full":"2515 Artesia Blvd Redondo Beach CA 90278",
    "addr:housenumber":"2515",
    "addr:postcode":"90278",
    "addr:street":"Artesia Blvd",
    "iso:country":"US",
    "sg:address":"2515 Artesia Blvd",
    "sg:city":"Redondo Beach",
    "sg:classifiers":[
        {
            "category":"Retail",
            "subcategory":"Repair Shop",
            "type":"Services"
        }
    ],
    "sg:phone":"+1 310 542 7100",
    "sg:postcode":"90278",
    "sg:province":"CA",
    "sg:tags":[
        "equipment",
        "beauty",
        "supply"
    ],
    "wof:name":"Christina Chiriani",
    "wof:placetype":"venue"
},
  "geometry": {"coordinates":[-118.364542,33.872926],"type":"Point"}
}