{
  "type": "Feature",
  "properties": {
    "addr:full":"15232 Stratford Ct Los Gatos CA 95030",
    "addr:housenumber":"15232",
    "addr:postcode":"95030",
    "addr:street":"Stratford Ct",
    "iso:country":"US",
    "sg:address":"15232 Stratford Ct",
    "sg:city":"Los Gatos",
    "sg:classifiers":[
        {
            "category":"Wholesale",
            "subcategory":"Jewelry",
            "type":"Manufacturing & Wholesale Goods"
        }
    ],
    "sg:phone":"+1 408 395 6923",
    "sg:postcode":"95030",
    "sg:province":"CA",
    "sg:tags":[
        "stone",
        "business"
    ],
    "wof:name":"Rowenas Designs",
    "wof:placetype":"venue"
},
  "geometry": {"coordinates":[-121.995704,37.246047],"type":"Point"}
}