{
  "type": "Feature",
  "properties": {
    "addr:full":"900 Market St. San Francisco CA 94102",
    "addr:housenumber":"900",
    "addr:postcode":"94102",
    "addr:street":"Market St.",
    "iso:country":"US",
    "sg:address":"900 Market St.",
    "sg:city":"San Francisco",
    "sg:classifiers":[
        {
            "category":"Restaurant",
            "type":"Food & Drink"
        }
    ],
    "sg:postcode":"94102",
    "sg:province":"CA",
    "sg:tags":[
        "flavor",
        "local"
    ],
    "wof:name":"Freelance Musicians On Market St. - Powell Inbound",
    "wof:placetype":"venue"
},
  "geometry": {"coordinates":[-122.407843,37.784196],"type":"Point"}
}