{
  "type": "Feature",
  "properties": {
    "iso:country":"US",
    "sg:address":"1540 Jefferson Boulevard",
    "sg:city":"West Sacramento",
    "sg:classifiers":[
        {
            "category":"Professional",
            "subcategory":"Lawyer & Legal Services",
            "type":"Services"
        }
    ],
    "sg:phone":"+1 916 374 0682",
    "sg:postcode":"95691",
    "sg:province":"CA",
    "wof:name":"Patrick & Euretig Llp",
    "wof:placetype":"venue"
},
  "geometry": {"coordinates":[-121.525419,38.567935],"type":"Point"}
}