{
  "type": "Feature",
  "properties": {
    "addr:full":"35014 85th St E Littlerock CA 93543",
    "addr:housenumber":"35014",
    "addr:postcode":"littlerock ca 93543",
    "addr:street":"85Th St E",
    "iso:country":"US",
    "sg:address":"35014 85th St E",
    "sg:city":"Littlerock",
    "sg:classifiers":[
        {
            "category":"Recreation",
            "subcategory":"Dog Park",
            "type":"Entertainment"
        },
        {
            "category":"Shopping",
            "subcategory":"Pets & Pet Supplies",
            "type":"Retail Goods"
        }
    ],
    "sg:phone":"+1 661 944 6890",
    "sg:postcode":"93543",
    "sg:province":"CA",
    "sg:tags":[
        "training"
    ],
    "wof:name":"Custom Dog Trning Barding Rnch",
    "wof:placetype":"venue"
},
  "geometry": {"coordinates":[-117.97930599999999,34.521209],"type":"Point"}
}