{
  "type": "Feature",
  "properties": {
    "addr:full":"1615 Boyd St Santa Ana CA 92705",
    "addr:housenumber":"1615",
    "addr:postcode":"92705",
    "addr:street":"Boyd St",
    "iso:country":"US",
    "sg:address":"1615 Boyd St",
    "sg:city":"Santa Ana",
    "sg:classifiers":[
        {
            "category":"Wholesale",
            "subcategory":"Durable Goods & Equipment",
            "type":"Manufacturing & Wholesale Goods"
        }
    ],
    "sg:phone":"+1 714 259 0838",
    "sg:postcode":"92705",
    "sg:province":"CA",
    "sg:tags":[
        "importer"
    ],
    "sg:website":"www.ciasons.com",
    "wof:name":"Ciasons Industrial Inc",
    "wof:placetype":"venue"
},
  "geometry": {"coordinates":[-117.83784900000001,33.725509],"type":"Point"}
}