{
  "type": "Feature",
  "properties": {
    "iso:country":"US",
    "sg:address":"12 Mauchly",
    "sg:city":"Irvine",
    "sg:classifiers":[
        {
            "category":"Professional",
            "subcategory":"Employment Agencies",
            "type":"Services"
        }
    ],
    "sg:phone":"+1 949 622 0909",
    "sg:postcode":"92618",
    "sg:province":"CA",
    "sg:tags":[
        "opportunity"
    ],
    "wof:name":"Best Domestic Svc Agency",
    "wof:placetype":"venue"
},
  "geometry": {"coordinates":[-117.735542,33.65236],"type":"Point"}
}