{
  "type": "Feature",
  "properties": {
    "addr:full":"1441 San Andreas Rd Watsonville CA 95076",
    "addr:housenumber":"1441",
    "addr:postcode":"95076",
    "addr:street":"San Andreas Rd",
    "iso:country":"US",
    "sg:address":"1441 San Andreas Rd",
    "sg:city":"Watsonville",
    "sg:classifiers":[
        {
            "category":"Arena",
            "subcategory":"Sports Club",
            "type":"Entertainment"
        }
    ],
    "sg:phone":"+1 831 247 0308",
    "sg:postcode":"95076",
    "sg:province":"CA",
    "sg:tags":[
        "health"
    ],
    "wof:name":"Excel Specialized Fitness",
    "wof:placetype":"venue"
},
  "geometry": {"coordinates":[-121.860619,36.931911],"type":"Point"}
}