{
  "type": "Feature",
  "properties": {
    "addr:full":"8216 Parkside Ct Sebastopol CA 95472",
    "addr:housenumber":"8216",
    "addr:postcode":"95472",
    "addr:street":"Parkside Ct",
    "iso:country":"US",
    "sg:address":"8216 Parkside Ct",
    "sg:city":"Sebastopol",
    "sg:classifiers":[
        {
            "category":"Recreation",
            "type":"Entertainment"
        }
    ],
    "sg:phone":"+1 707 823 1260",
    "sg:postcode":"95472",
    "sg:province":"CA",
    "sg:tags":[
        "club",
        "membership"
    ],
    "wof:name":"West County Tennis Association",
    "wof:placetype":"venue"
},
  "geometry": {"coordinates":[-122.844351,38.404792],"type":"Point"}
}