{
  "type": "Feature",
  "properties": {
    "iso:country":"US",
    "sg:address":"1550 McKinley Rd",
    "sg:city":"Napa",
    "sg:classifiers":[
        {
            "category":"Farming",
            "subcategory":"Livestock Farm",
            "type":"Manufacturing & Wholesale Goods"
        }
    ],
    "sg:phone":"+1 707 265 0990",
    "sg:postcode":"94558",
    "sg:province":"CA",
    "sg:tags":[
        "animal",
        "general"
    ],
    "wof:name":"Alpaca Island Ranch",
    "wof:placetype":"venue"
},
  "geometry": {"coordinates":[-122.272795,38.337872],"type":"Point"}
}