{
  "type": "Feature",
  "properties": {
    "addr:full":"7607 Fountain Ave Los Angeles CA 90046",
    "addr:housenumber":"7607",
    "addr:postcode":"90046",
    "addr:street":"Fountain Ave",
    "iso:country":"US",
    "sg:address":"7607 Fountain Ave",
    "sg:city":"Los Angeles",
    "sg:classifiers":[
        {
            "category":"Shopping",
            "type":"Retail Goods"
        }
    ],
    "sg:phone":"+1 323 969 8966",
    "sg:postcode":"90046",
    "sg:province":"CA",
    "sg:tags":[
        "miscellaneous",
        "store"
    ],
    "wof:name":"Happy Days",
    "wof:placetype":"venue"
},
  "geometry": {"coordinates":[-118.35599499999999,34.09449],"type":"Point"}
}