{
  "type": "Feature",
  "properties": {
    "iso:country":"US",
    "sg:address":"1680 Fruitvale Ave",
    "sg:city":"Oakland",
    "sg:classifiers":[
        {
            "category":"Restaurant",
            "type":"Food & Drink"
        },
        {
            "category":"Food Court",
            "type":"Food & Drink"
        }
    ],
    "sg:phone":"+1 510 610 0199",
    "sg:postcode":"94601",
    "sg:province":"CA",
    "sg:tags":[
        "mexican",
        "stand"
    ],
    "wof:name":"Tamales Acapulco",
    "wof:placetype":"venue"
},
  "geometry": {"coordinates":[-122.223972,37.781361],"type":"Point"}
}