{
  "type": "Feature",
  "properties": {
    "iso:country":"US",
    "sg:address":"395 S Tustin St",
    "sg:city":"Orange",
    "sg:classifiers":[
        {
            "category":"Professional",
            "subcategory":"Management & Consulting",
            "type":"Services"
        }
    ],
    "sg:phone":"+1 714 516 3370",
    "sg:postcode":"92866",
    "sg:province":"CA",
    "sg:tags":[
        "nonphysical",
        "commercial",
        "business",
        "res"
    ],
    "wof:name":"Rossier Park Elementary School",
    "wof:placetype":"venue"
},
  "geometry": {"coordinates":[-117.835658,33.782522],"type":"Point"}
}