{
  "type": "Feature",
  "properties": {
    "addr:full":"78211 Hollister Dr Palm Desert CA 92211",
    "addr:housenumber":"78211",
    "addr:postcode":"ca 92211",
    "addr:street":"Hollister Dr",
    "iso:country":"US",
    "sg:address":"78211 Hollister Dr",
    "sg:city":"Palm Desert",
    "sg:classifiers":[
        {
            "category":"Wholesale",
            "subcategory":"Apparel",
            "type":"Manufacturing & Wholesale Goods"
        }
    ],
    "sg:phone":"+1 760 200 9460",
    "sg:postcode":"92211",
    "sg:province":"CA",
    "sg:tags":[
        "rea",
        "kitchenware",
        "shoes",
        "sportswear"
    ],
    "wof:name":"Ports & Sports",
    "wof:placetype":"venue"
},
  "geometry": {"coordinates":[-116.297623,33.796449],"type":"Point"}
}