{
  "type": "Feature",
  "properties": {
    "iso:country":"US",
    "sg:address":"3180 US Hwy 50",
    "sg:city":"South Lake Tahoe",
    "sg:classifiers":[
        {
            "category":"Government",
            "subcategory":"Post Office",
            "type":"Public Place"
        }
    ],
    "sg:phone":"+1 530 000 1111",
    "sg:postcode":"96150",
    "sg:province":"CA",
    "wof:name":"US Post Office",
    "wof:placetype":"venue"
},
  "geometry": {"coordinates":[-119.976966,38.943042],"type":"Point"}
}