{
  "type": "Feature",
  "properties": {
    "addr:full":"2120 Trently Ln Beverly Hills CA 90210",
    "addr:housenumber":"2120",
    "addr:postcode":"90210",
    "addr:street":"Trently Ln",
    "iso:country":"US",
    "sg:address":"2120 Trently Ln",
    "sg:city":"Beverly Hills",
    "sg:classifiers":[
        {
            "category":"Building & Trades",
            "subcategory":"Construction",
            "type":"Services"
        }
    ],
    "sg:phone":"+1 310 285 0418",
    "sg:postcode":"90210",
    "sg:province":"CA",
    "sg:tags":[
        "contractor"
    ],
    "wof:name":"Quillin Construction",
    "wof:placetype":"venue"
},
  "geometry": {"coordinates":[-118.40234,34.111118],"type":"Point"}
}