{
  "type": "Feature",
  "properties": {
    "addr:full":"27072 Helendale Rd Helendale CA 92342",
    "addr:housenumber":"27072",
    "addr:postcode":"92342",
    "addr:street":"Helendale Rd",
    "iso:country":"US",
    "sg:address":"27072 Helendale Rd",
    "sg:city":"Helendale",
    "sg:classifiers":[
        {
            "category":"Government",
            "subcategory":"Post Office",
            "type":"Public Place"
        }
    ],
    "sg:phone":"+1 760 000 1111",
    "sg:postcode":"92342",
    "sg:province":"CA",
    "wof:name":"US Post Office",
    "wof:placetype":"venue"
},
  "geometry": {"coordinates":[-117.33289600000001,34.749195],"type":"Point"}
}