{
  "type": "Feature",
  "properties": {
    "addr:full":"760 Bodega Ave Petaluma CA 94952",
    "addr:housenumber":"760",
    "addr:postcode":"94952",
    "addr:street":"Bodega Ave",
    "iso:country":"US",
    "sg:address":"760 Bodega Ave",
    "sg:city":"Petaluma",
    "sg:classifiers":[
        {
            "category":"Building & Trades",
            "subcategory":"Landscaping Services",
            "type":"Services"
        }
    ],
    "sg:phone":"+1 925 634 8500",
    "sg:postcode":"94952",
    "sg:province":"CA",
    "sg:tags":[
        "designer",
        "landscape"
    ],
    "wof:name":"SDC-Site Development",
    "wof:placetype":"venue"
},
  "geometry": {"coordinates":[-122.65858900000001,38.234667],"type":"Point"}
}