{
  "type": "Feature",
  "properties": {
    "addr:full":"5241 Highcrest Dr Shingle Springs CA 95682",
    "addr:housenumber":"5241",
    "addr:postcode":"95682",
    "addr:street":"Highcrest Dr",
    "iso:country":"US",
    "sg:address":"5241 Highcrest Dr",
    "sg:city":"Shingle Springs",
    "sg:classifiers":[
        {
            "category":"Professional",
            "subcategory":"Computer Services",
            "type":"Services"
        }
    ],
    "sg:phone":"+1 530 677 9191",
    "sg:postcode":"95682",
    "sg:province":"CA",
    "sg:tags":[
        "equipment",
        "maintenance"
    ],
    "wof:name":"Protostar Computer Technology",
    "wof:placetype":"venue"
},
  "geometry": {"coordinates":[-120.96905,38.639985],"type":"Point"}
}