{
  "type": "Feature",
  "properties": {
    "iso:country":"US",
    "sg:address":"74271 Hwy 111",
    "sg:city":"Palm Desert",
    "sg:classifiers":[
        {
            "category":"Manufacturing",
            "subcategory":"Furniture",
            "type":"Manufacturing & Wholesale Goods"
        }
    ],
    "sg:phone":"+1 760 568 2037",
    "sg:postcode":"92260",
    "sg:province":"CA",
    "sg:tags":[
        "upholstered",
        "household",
        "mfg"
    ],
    "wof:name":"Home Collection The",
    "wof:placetype":"venue"
},
  "geometry": {"coordinates":[-116.370074,33.721246],"type":"Point"}
}