{
  "type": "Feature",
  "properties": {
    "addr:full":"1200 N Jefferson St Anaheim CA 92807",
    "addr:housenumber":"1200",
    "addr:postcode":"92807",
    "addr:street":"N Jefferson St",
    "iso:country":"US",
    "sg:address":"1200 N Jefferson St",
    "sg:city":"Anaheim",
    "sg:classifiers":[
        {
            "category":"Building & Trades",
            "subcategory":"Electrical",
            "type":"Services"
        }
    ],
    "sg:phone":"+1 714 632 9522",
    "sg:postcode":"92807",
    "sg:province":"CA",
    "sg:tags":[
        "electrician"
    ],
    "wof:name":"Newcal Electric Co Inc",
    "wof:placetype":"venue"
},
  "geometry": {"coordinates":[-117.837997,33.858101],"type":"Point"}
}