{
  "type": "Feature",
  "properties": {
    "addr:full":"2851 W 230th St Torrance CA 90505",
    "addr:housenumber":"2851",
    "addr:postcode":"90505",
    "addr:street":"W 230Th St",
    "iso:country":"US",
    "sg:address":"2851 W 230th St",
    "sg:city":"Torrance",
    "sg:classifiers":[
        {
            "category":"Professional",
            "subcategory":"Accounting & Tax Preparation",
            "type":"Services"
        }
    ],
    "sg:phone":"+1 310 534 2225",
    "sg:postcode":"90505",
    "sg:province":"CA",
    "sg:tags":[
        "bookkeeping",
        "general"
    ],
    "wof:name":"MCR Bookkeeping",
    "wof:placetype":"venue"
},
  "geometry": {"coordinates":[-118.3369,33.818634],"type":"Point"}
}