{
  "type": "Feature",
  "properties": {
    "iso:country":"US",
    "sg:address":"43200A Highway 101",
    "sg:city":"Laytonville",
    "sg:classifiers":[
        {
            "category":"Wholesale",
            "subcategory":"Hardware",
            "type":"Manufacturing & Wholesale Goods"
        },
        {
            "category":"Home & Garden",
            "subcategory":"Garden Supply",
            "type":"Retail Goods"
        },
        {
            "category":"Retail",
            "subcategory":"Repair Shop",
            "type":"Services"
        }
    ],
    "sg:phone":"+1 707 984 9110",
    "sg:postcode":"95454",
    "sg:province":"CA",
    "sg:tags":[
        "renting",
        "lawn",
        "outdoor",
        "power",
        "landscaping",
        "equipment-sales",
        "equipment",
        "saw"
    ],
    "sg:website":"http://www.stihlusa.com/",
    "wof:name":"Willits Power Equipment",
    "wof:placetype":"venue"
},
  "geometry": {"coordinates":[-123.483056,39.687768],"type":"Point"}
}