{
  "type": "Feature",
  "properties": {
    "addr:full":"128 E California Ave Ridgecrest CA 93555",
    "addr:housenumber":"128",
    "addr:postcode":"93555",
    "addr:street":"E California Ave",
    "iso:country":"US",
    "sg:address":"128 E California Ave",
    "sg:city":"Ridgecrest",
    "sg:classifiers":[
        {
            "category":"Organizations",
            "subcategory":"Professional Association",
            "type":"Services"
        }
    ],
    "sg:phone":"+1 760 375 8331",
    "sg:postcode":"93555",
    "sg:province":"CA",
    "sg:tags":[
        "chambers",
        "commerce"
    ],
    "wof:name":"Chamber Of Commerce",
    "wof:placetype":"venue"
},
  "geometry": {"coordinates":[-117.667857,35.620739],"type":"Point"}
}