{
  "type": "Feature",
  "properties": {
    "iso:country":"US",
    "sg:address":"26384 Carmel Rancho Ln",
    "sg:city":"Carmel",
    "sg:classifiers":[
        {
            "category":"Professional",
            "subcategory":"Accounting & Tax Preparation",
            "type":"Services"
        }
    ],
    "sg:phone":"+1 831 626 8388",
    "sg:postcode":"93923",
    "sg:province":"CA",
    "sg:tags":[
        "payroll"
    ],
    "wof:name":"Accurate Payroll Svc",
    "wof:placetype":"venue"
},
  "geometry": {"coordinates":[-121.905513,36.540403],"type":"Point"}
}