{
  "type": "Feature",
  "properties": {
    "addr:full":"600 E Valley Blvd San Gabriel CA 91776",
    "addr:housenumber":"600",
    "addr:postcode":"91776",
    "addr:street":"E Valley Blvd",
    "iso:country":"US",
    "sg:address":"600 E Valley Blvd",
    "sg:city":"San Gabriel",
    "sg:classifiers":[
        {
            "category":"Shopping",
            "subcategory":"Gifts & Souvenirs",
            "type":"Retail Goods"
        }
    ],
    "sg:phone":"+1 626 288 8668",
    "sg:postcode":"91776",
    "sg:province":"CA",
    "sg:tags":[
        "shop"
    ],
    "wof:name":"Treasure Palace",
    "wof:placetype":"venue"
},
  "geometry": {"coordinates":[-118.091418,34.080044],"type":"Point"}
}