{
  "type": "Feature",
  "properties": {
    "addr:full":"25045 Sunnymead Blvd Moreno Valley CA 92553",
    "addr:postcode":"25045;92553",
    "addr:street":"Sunnymead Blvd",
    "iso:country":"US",
    "sg:address":"25045 Sunnymead Blvd",
    "sg:city":"Moreno Valley",
    "sg:classifiers":[
        {
            "category":"Home & Garden",
            "subcategory":"Furniture",
            "type":"Retail Goods"
        }
    ],
    "sg:phone":"+1 951 247 2996",
    "sg:postcode":"92553",
    "sg:province":"CA",
    "wof:name":"Topline Furniture",
    "wof:placetype":"venue"
},
  "geometry": {"coordinates":[-117.223786,33.939223],"type":"Point"}
}