{
  "type": "Feature",
  "properties": {
    "addr:full":"2620 Kelp Ln Oxnard CA 93035",
    "addr:housenumber":"2620",
    "addr:postcode":"93035",
    "addr:street":"Kelp Ln",
    "iso:country":"US",
    "sg:address":"2620 Kelp Ln",
    "sg:city":"Oxnard",
    "sg:classifiers":[
        {
            "category":"Shopping",
            "subcategory":"Gifts & Souvenirs",
            "type":"Retail Goods"
        }
    ],
    "sg:phone":"+1 805 985 3328",
    "sg:postcode":"93035",
    "sg:province":"CA",
    "wof:name":"Choocho Gifts Distributing",
    "wof:placetype":"venue"
},
  "geometry": {"coordinates":[-119.209024,34.191918],"type":"Point"}
}