{
  "type": "Feature",
  "properties": {
    "addr:full":"11728 Goldring Rd Arcadia CA 91006",
    "addr:housenumber":"11728",
    "addr:postcode":"91006",
    "addr:street":"Goldring Rd",
    "iso:country":"US",
    "sg:address":"11728 Goldring Rd",
    "sg:city":"Arcadia",
    "sg:classifiers":[
        {
            "category":"Insurance",
            "subcategory":"Insurance Agent",
            "type":"Services"
        }
    ],
    "sg:phone":"+1 626 256 6211",
    "sg:postcode":"91006",
    "sg:province":"CA",
    "wof:name":"New Life Insurance",
    "wof:placetype":"venue"
},
  "geometry": {"coordinates":[-118.00744299999999,34.101231],"type":"Point"}
}