{
  "type": "Feature",
  "properties": {
    "addr:full":"201 Elderwood Dr Pleasant Hill CA 94523",
    "addr:housenumber":"201",
    "addr:postcode":"94523",
    "addr:street":"Elderwood Dr",
    "iso:country":"US",
    "sg:address":"201 Elderwood Dr",
    "sg:city":"Pleasant Hill",
    "sg:classifiers":[
        {
            "category":"Professional",
            "type":"Services"
        }
    ],
    "sg:phone":"+1 925 370 7821",
    "sg:postcode":"94523",
    "sg:province":"CA",
    "wof:name":"Bop With ME Baby",
    "wof:placetype":"venue"
},
  "geometry": {"coordinates":[-122.09738900000001,37.974558],"type":"Point"}
}