{
  "type": "Feature",
  "properties": {
    "iso:country":"US",
    "sg:address":"527 Center St",
    "sg:city":"Cedarville",
    "sg:classifiers":[
        {
            "category":"Wholesale",
            "subcategory":"Farm Supplies",
            "type":"Manufacturing & Wholesale Goods"
        }
    ],
    "sg:phone":"+1 530 279 6143",
    "sg:postcode":"96104",
    "sg:province":"NV",
    "sg:tags":[
        "alfalfa",
        "hay"
    ],
    "wof:name":"L Schultz Trucking",
    "wof:placetype":"venue"
},
  "geometry": {"coordinates":[-120.173514,41.529093],"type":"Point"}
}