{
  "type": "Feature",
  "properties": {
    "addr:full":"351 Northpoint Dr Redding CA 96003",
    "addr:housenumber":"351",
    "addr:postcode":"96003",
    "addr:street":"Northpoint Dr",
    "iso:country":"US",
    "sg:address":"351 Northpoint Dr",
    "sg:city":"Redding",
    "sg:classifiers":[
        {
            "category":"Organizations",
            "subcategory":"Religious Organization",
            "type":"Services"
        }
    ],
    "sg:phone":"+1 530 243 8222",
    "sg:postcode":"96003",
    "sg:province":"CA",
    "sg:tags":[
        "church"
    ],
    "wof:name":"Calvery Chapel Of Redding",
    "wof:placetype":"venue"
},
  "geometry": {"coordinates":[-122.38061999999999,40.61165],"type":"Point"}
}