{
  "type": "Feature",
  "properties": {
    "addr:full":"14842 Bowling Green St Westminster CA 92683",
    "addr:housenumber":"14842",
    "addr:postcode":"92683",
    "addr:street":"Bowling Green St",
    "iso:country":"US",
    "sg:address":"14842 Bowling Green St",
    "sg:city":"Westminster",
    "sg:classifiers":[
        {
            "category":"Real Estate",
            "subcategory":"Real Estate Services",
            "type":"Services"
        },
        {
            "category":"Real Estate",
            "subcategory":"Real Estate Agent",
            "type":"Services"
        }
    ],
    "sg:phone":"+1 714 839 8432",
    "sg:postcode":"92683",
    "sg:province":"CA",
    "sg:tags":[
        "buyer",
        "broker"
    ],
    "wof:name":"Ocal Realty",
    "wof:placetype":"venue"
},
  "geometry": {"coordinates":[-117.953163,33.747529],"type":"Point"}
}