{
  "type": "Feature",
  "properties": {
    "addr:full":"4286 Seven Hills Rd Castro Valley CA 94546",
    "addr:housenumber":"4286",
    "addr:postcode":"94546",
    "addr:street":"Seven Hills Rd",
    "iso:country":"US",
    "sg:address":"4286 Seven Hills Rd",
    "sg:city":"Castro Valley",
    "sg:classifiers":[
        {
            "category":"Personal",
            "subcategory":"Barber",
            "type":"Services"
        }
    ],
    "sg:phone":"+1 510 889 7414",
    "sg:postcode":"94546",
    "sg:province":"CA",
    "wof:name":"Marcie Davis At the Hair Benders",
    "wof:placetype":"venue"
},
  "geometry": {"coordinates":[-122.077003,37.709801],"type":"Point"}
}