{
  "type": "Feature",
  "properties": {
    "addr:full":"21245 Macarthur Dr Nuevo CA 92567",
    "addr:housenumber":"21245",
    "addr:postcode":"92567",
    "addr:street":"Macarthur Dr",
    "iso:country":"US",
    "sg:address":"21245 Macarthur Dr",
    "sg:city":"Nuevo",
    "sg:classifiers":[
        {
            "category":"Professional",
            "type":"Services"
        }
    ],
    "sg:phone":"+1 951 928 5113",
    "sg:postcode":"92567",
    "sg:province":"CA",
    "wof:name":"Personal Touch Concepts",
    "wof:placetype":"venue"
},
  "geometry": {"coordinates":[-117.12849799999999,33.814018],"type":"Point"}
}