{
  "type": "Feature",
  "properties": {
    "iso:country":"US",
    "sg:address":"1251 Oregon St",
    "sg:city":"Redding",
    "sg:classifiers":[
        {
            "category":"Organizations",
            "subcategory":"Community Association",
            "type":"Services"
        }
    ],
    "sg:phone":"+1 530 241 9168",
    "sg:postcode":"96001",
    "sg:province":"CA",
    "sg:tags":[
        "military"
    ],
    "wof:name":"Veterans Of Foreign Wars",
    "wof:placetype":"venue"
},
  "geometry": {"coordinates":[-122.395241,40.585488],"type":"Point"}
}