{
  "type": "Feature",
  "properties": {
    "addr:full":"13400 Saticoy St North Hollywood CA 91605",
    "addr:housenumber":"13400",
    "addr:postcode":"91605",
    "addr:street":"Saticoy St",
    "iso:country":"US",
    "sg:address":"13400 Saticoy St",
    "sg:city":"North Hollywood",
    "sg:classifiers":[
        {
            "category":"Building & Trades",
            "subcategory":"Plumbing",
            "type":"Services"
        }
    ],
    "sg:phone":"+1 818 982 6952",
    "sg:postcode":"91605",
    "sg:province":"CA",
    "wof:name":"Plumbing Installers",
    "wof:placetype":"venue"
},
  "geometry": {"coordinates":[-118.424693,34.208511],"type":"Point"}
}