{
  "type": "Feature",
  "properties": {
    "addr:full":"1515 Tulare St Fresno CA 93706",
    "addr:housenumber":"1515",
    "addr:postcode":"93706",
    "addr:street":"Tulare St",
    "iso:country":"US",
    "sg:address":"1515 Tulare St",
    "sg:city":"Fresno",
    "sg:classifiers":[
        {
            "category":"Restaurant",
            "type":"Food & Drink"
        }
    ],
    "sg:phone":"+1 559 498 8236",
    "sg:postcode":"93706",
    "sg:province":"CA",
    "wof:name":"El Rancho",
    "wof:placetype":"venue"
},
  "geometry": {"coordinates":[-119.794696,36.730682],"type":"Point"}
}