{
  "type": "Feature",
  "properties": {
    "addr:full":"2701 N Ontario St Burbank CA 91504",
    "addr:housenumber":"2701",
    "addr:postcode":"91504",
    "addr:street":"N Ontario St",
    "iso:country":"US",
    "sg:address":"2701 N Ontario St",
    "sg:city":"Burbank",
    "sg:classifiers":[
        {
            "category":"Manufacturing",
            "subcategory":"Rubber & Plastics",
            "type":"Manufacturing & Wholesale Goods"
        }
    ],
    "sg:phone":"+1 818 840 9288",
    "sg:postcode":"91504",
    "sg:province":"CA",
    "sg:tags":[
        "injection",
        "molding"
    ],
    "wof:name":"MCA",
    "wof:placetype":"venue"
},
  "geometry": {"coordinates":[-118.34434400000001,34.202269],"type":"Point"}
}