{
  "type": "Feature",
  "properties": {
    "iso:country":"US",
    "sg:address":"8581 Edgemont Circle",
    "sg:city":"Westminster",
    "sg:classifiers":[
        {
            "category":"Transit Center",
            "subcategory":"Passenger",
            "type":"Transportation"
        }
    ],
    "sg:phone":"+1 877 464 6146",
    "sg:postcode":"92683",
    "sg:province":"CA",
    "sg:website":"www.gogreenshuttleservice.com",
    "wof:name":"Go Green Shuttle Service",
    "wof:placetype":"venue"
},
  "geometry": {"coordinates":[-117.97931699999999,33.736629],"type":"Point"}
}