{
  "type": "Feature",
  "properties": {
    "iso:country":"US",
    "sg:address":"3500 W Olive Ave Ste 550",
    "sg:city":"Burbank",
    "sg:classifiers":[
        {
            "category":"Professional",
            "subcategory":"Employment Agencies",
            "type":"Services"
        }
    ],
    "sg:phone":"+1 818 845 6600",
    "sg:postcode":"91505",
    "sg:province":"CA",
    "wof:name":"Ajilon Finance",
    "wof:placetype":"venue"
},
  "geometry": {"coordinates":[-118.337997,34.152901],"type":"Point"}
}