{
  "type": "Feature",
  "properties": {
    "addr:full":"844 Manhattan Ave Hermosa Beach CA 90254",
    "addr:housenumber":"844",
    "addr:postcode":"90254",
    "addr:street":"Manhattan Ave",
    "iso:country":"US",
    "sg:address":"844 Manhattan Ave",
    "sg:city":"Hermosa Beach",
    "sg:classifiers":[
        {
            "category":"Professional",
            "type":"Services"
        }
    ],
    "sg:phone":"+1 310 318 9492",
    "sg:postcode":"90254",
    "sg:province":"CA",
    "wof:name":"Anthony T Fire",
    "wof:placetype":"venue"
},
  "geometry": {"coordinates":[-118.39852,33.860576],"type":"Point"}
}