{
  "type": "Feature",
  "properties": {
    "iso:country":"US",
    "sg:address":"805 W La Veta Ave Ste 104",
    "sg:city":"Orange",
    "sg:classifiers":[
        {
            "category":"Health Services",
            "subcategory":"Doctor",
            "type":"Services"
        }
    ],
    "sg:phone":"+1 714 972 9323",
    "sg:postcode":"92868",
    "sg:province":"CA",
    "wof:name":"Zahiri Hormoz MD",
    "wof:placetype":"venue"
},
  "geometry": {"coordinates":[-117.861465,33.780731],"type":"Point"}
}