{
  "type": "Feature",
  "properties": {
    "iso:country":"US",
    "sg:address":"6030 San Juan Ave",
    "sg:city":"Citrus Heights",
    "sg:classifiers":[
        {
            "category":"Personal",
            "subcategory":"Tanning Parlor",
            "type":"Services"
        },
        {
            "category":"Sports & Exercise",
            "subcategory":"Gym",
            "type":"Entertainment"
        },
        {
            "category":"Personal",
            "subcategory":"Skin Care",
            "type":"Services"
        }
    ],
    "sg:phone":"+1 916 727 1449",
    "sg:postcode":"95610",
    "sg:province":"CA",
    "sg:tags":[
        "trainer"
    ],
    "wof:name":"Slender You Tone & Tan Body Wrap Salon",
    "wof:placetype":"venue"
},
  "geometry": {"coordinates":[-121.29238100000001,38.675506],"type":"Point"}
}