{
  "type": "Feature",
  "properties": {
    "addr:full":"4738 Manzanita Ave Carmichael CA 95608",
    "addr:housenumber":"4738",
    "addr:postcode":"95608",
    "addr:street":"Manzanita Ave",
    "iso:country":"US",
    "sg:address":"4738 Manzanita Ave",
    "sg:city":"Carmichael",
    "sg:classifiers":[
        {
            "category":"Retail",
            "subcategory":"Portrait Studio",
            "type":"Services"
        }
    ],
    "sg:phone":"+1 916 483 6051",
    "sg:postcode":"95608",
    "sg:province":"CA",
    "sg:tags":[
        "photographer"
    ],
    "wof:name":"Laws Studio",
    "wof:placetype":"venue"
},
  "geometry": {"coordinates":[-121.327573,38.650313],"type":"Point"}
}