{
  "type": "Feature",
  "properties": {
    "addr:full":"337 S Robertson Blvd Beverly Hills CA 90035",
    "addr:housenumber":"337",
    "addr:postcode":"90035",
    "addr:street":"S Robertson Blvd",
    "iso:country":"US",
    "sg:address":"337 S Robertson Blvd",
    "sg:city":"Beverly Hills",
    "sg:classifiers":[
        {
            "category":"Professional",
            "type":"Services"
        }
    ],
    "sg:phone":"+1 310 659 2446",
    "sg:postcode":"90035",
    "sg:province":"CA",
    "sg:tags":[
        "establishment"
    ],
    "wof:name":"Reznik & Gershkowitz A Pro Crp",
    "wof:placetype":"venue"
},
  "geometry": {"coordinates":[-118.383551,34.062194],"type":"Point"}
}