{
  "type": "Feature",
  "properties": {
    "addr:full":"45 Castro Street San Francisco CA 94101",
    "addr:housenumber":"45",
    "addr:postcode":"94101",
    "addr:street":"Castro Street",
    "iso:country":"US",
    "sg:address":"45 Castro Street",
    "sg:city":"San Francisco",
    "sg:classifiers":[
        {
            "category":"Community Center",
            "type":"Public Place"
        }
    ],
    "sg:phone":"+1 415 600 6000",
    "sg:postcode":"94101",
    "sg:province":"CA",
    "sg:tags":[
        "medical"
    ],
    "wof:name":"Davies Medical Center",
    "wof:placetype":"venue"
},
  "geometry": {"coordinates":[-122.43575199999999,37.768624],"type":"Point"}
}