{
  "type": "Feature",
  "properties": {
    "iso:country":"US",
    "sg:address":"621 Hawaii St",
    "sg:city":"El Segundo",
    "sg:classifiers":[
        {
            "category":"Government",
            "subcategory":"Court House",
            "type":"Public Place"
        }
    ],
    "sg:phone":"+1 310 297 2432",
    "sg:postcode":"90245",
    "sg:province":"CA",
    "sg:tags":[
        "legal"
    ],
    "wof:name":"Child Support Services",
    "wof:placetype":"venue"
},
  "geometry": {"coordinates":[-118.38146999999999,33.906097],"type":"Point"}
}