{
  "type": "Feature",
  "properties": {
    "iso:country":"US",
    "sg:address":"6360 Stoneridge Mall Rd",
    "sg:city":"Pleasanton",
    "sg:classifiers":[
        {
            "category":"Professional",
            "subcategory":"Advertising",
            "type":"Services"
        }
    ],
    "sg:phone":"+1 925 251 0665",
    "sg:postcode":"94588",
    "sg:province":"CA",
    "sg:tags":[
        "distribution"
    ],
    "wof:name":"Herbalife Distributor",
    "wof:placetype":"venue"
},
  "geometry": {"coordinates":[-121.923061,37.691371],"type":"Point"}
}