{
  "type": "Feature",
  "properties": {
    "iso:country":"US",
    "sg:address":"11157 Washington Blvd",
    "sg:city":"Culver City",
    "sg:classifiers":[
        {
            "category":"Real Estate",
            "subcategory":"Real Estate Services",
            "type":"Services"
        }
    ],
    "sg:phone":"+1 310 202 0220",
    "sg:postcode":"90232",
    "sg:province":"CA",
    "sg:tags":[
        "management",
        "property"
    ],
    "wof:name":"National Community Development Assoc",
    "wof:placetype":"venue"
},
  "geometry": {"coordinates":[-118.41258000000001,34.191477],"type":"Point"}
}