{
  "type": "Feature",
  "properties": {
    "addr:full":"9855 Distribution Ave San Diego CA 92121",
    "addr:housenumber":"9855",
    "addr:postcode":"92121",
    "addr:street":"Distribution Ave",
    "iso:country":"US",
    "sg:address":"9855 Distribution Ave",
    "sg:city":"San Diego",
    "sg:classifiers":[
        {
            "category":"Manufacturing",
            "subcategory":"Printing",
            "type":"Manufacturing & Wholesale Goods"
        }
    ],
    "sg:phone":"+1 858 586 1268",
    "sg:postcode":"92121",
    "sg:province":"CA",
    "sg:tags":[
        "screen"
    ],
    "wof:name":"Marine Sunwear Intl",
    "wof:placetype":"venue"
},
  "geometry": {"coordinates":[-117.163088,32.886136],"type":"Point"}
}