{
  "type": "Feature",
  "properties": {
    "addr:full":"537 Newport Center Dr Newport Beach CA 92660",
    "addr:housenumber":"537",
    "addr:postcode":"92660",
    "addr:street":"Newport Center Dr",
    "iso:country":"US",
    "sg:address":"537 Newport Center Dr",
    "sg:city":"Newport Beach",
    "sg:classifiers":[
        {
            "category":"Professional",
            "subcategory":"Business Services",
            "type":"Services"
        }
    ],
    "sg:phone":"+1 949 640 2401",
    "sg:postcode":"92660",
    "sg:province":"CA",
    "wof:name":"On The Grow Enterprises",
    "wof:placetype":"venue"
},
  "geometry": {"coordinates":[-117.87238600000001,33.616018],"type":"Point"}
}