{
  "type": "Feature",
  "properties": {
    "iso:country":"US",
    "sg:address":"3600 Sisk Rd",
    "sg:city":"Modesto",
    "sg:classifiers":[
        {
            "category":"Utilities",
            "subcategory":"Mobile Phone",
            "type":"Services"
        }
    ],
    "sg:phone":"+1 209 545 4475",
    "sg:postcode":"95356",
    "sg:province":"CA",
    "sg:tags":[
        "communication",
        "radiotelephone"
    ],
    "wof:name":"AT&T",
    "wof:placetype":"venue"
},
  "geometry": {"coordinates":[-121.06166,37.690498],"type":"Point"}
}