{
  "type": "Feature",
  "properties": {
    "addr:full":"8504 Commerce Ave San Diego CA 92121",
    "addr:housenumber":"8504",
    "addr:postcode":"92121",
    "addr:street":"Commerce Ave",
    "iso:country":"US",
    "sg:address":"8504 Commerce Ave",
    "sg:city":"San Diego",
    "sg:classifiers":[
        {
            "category":"Professional",
            "subcategory":"Art Services",
            "type":"Services"
        }
    ],
    "sg:phone":"+1 858 530 1551",
    "sg:postcode":"92121",
    "sg:province":"CA",
    "sg:tags":[
        "photographer"
    ],
    "sg:website":"www.tippettphoto.com",
    "wof:name":"Clay Chapman Photography",
    "wof:placetype":"venue"
},
  "geometry": {"coordinates":[-117.167834,32.881835],"type":"Point"}
}