{
  "type": "Feature",
  "properties": {
    "addr:full":"5259 Lilac Ave Livermore CA 94551",
    "addr:housenumber":"5259",
    "addr:postcode":"94551",
    "addr:street":"Lilac Ave",
    "iso:country":"US",
    "sg:address":"5259 Lilac Ave",
    "sg:city":"Livermore",
    "sg:classifiers":[
        {
            "category":"Professional",
            "type":"Services"
        }
    ],
    "sg:phone":"+1 925 443 2693",
    "sg:postcode":"94551",
    "sg:province":"CA",
    "wof:name":"Samantha Savage",
    "wof:placetype":"venue"
},
  "geometry": {"coordinates":[-121.736886,37.714711],"type":"Point"}
}