{
  "type": "Feature",
  "properties": {
    "addr:full":"2608 183rd St Redondo Beach CA 90278",
    "addr:housenumber":"2608",
    "addr:postcode":"90278",
    "addr:street":"183Rd St",
    "iso:country":"US",
    "sg:address":"2608 183rd St",
    "sg:city":"Redondo Beach",
    "sg:classifiers":[
        {
            "category":"Manufacturing",
            "subcategory":"Metals",
            "type":"Manufacturing & Wholesale Goods"
        }
    ],
    "sg:phone":"+1 805 443 2637",
    "sg:postcode":"90278",
    "sg:province":"CA",
    "sg:tags":[
        "product",
        "fabricated",
        "mfg"
    ],
    "wof:name":"Creativewrench Co",
    "wof:placetype":"venue"
},
  "geometry": {"coordinates":[-118.36133,33.863988],"type":"Point"}
}