{
  "type": "Feature",
  "properties": {
    "addr:full":"555 S Flower Street Los Angeles CA 90071",
    "addr:housenumber":"555",
    "addr:postcode":"90071",
    "addr:street":"S Flower Street",
    "iso:country":"US",
    "sg:address":"555 S Flower Street",
    "sg:city":"Los Angeles",
    "sg:classifiers":[
        {
            "category":"Professional",
            "subcategory":"Lawyer & Legal Services",
            "type":"Services"
        }
    ],
    "sg:phone":"+1 213 892 9200",
    "sg:postcode":"90071",
    "sg:province":"CA",
    "wof:name":"Smooke Michael G",
    "wof:placetype":"venue"
},
  "geometry": {"coordinates":[-118.256967,34.050751],"type":"Point"}
}