{
  "type": "Feature",
  "properties": {
    "addr:full":"2195 S State St Ukiah CA 95482",
    "addr:housenumber":"2195",
    "addr:postcode":"ca 95482",
    "addr:street":"S State St",
    "iso:country":"US",
    "sg:address":"2195 S State St",
    "sg:city":"Ukiah",
    "sg:classifiers":[
        {
            "category":"Personal",
            "subcategory":"Beauty Salon",
            "type":"Services"
        }
    ],
    "sg:phone":"+1 707 354 0698",
    "sg:postcode":"95482",
    "sg:province":"CA",
    "wof:name":"Charlie's Full Svc Salon",
    "wof:placetype":"venue"
},
  "geometry": {"coordinates":[-123.202955,39.120883],"type":"Point"}
}