{
  "type": "Feature",
  "properties": {
    "iso:country":"US",
    "sg:address":"717 S San Gabriel Blvd",
    "sg:city":"San Gabriel",
    "sg:classifiers":[
        {
            "category":"Restaurant",
            "type":"Food & Drink"
        }
    ],
    "sg:phone":"+1 626 287 4645",
    "sg:postcode":"91776",
    "sg:province":"CA",
    "wof:name":"Azteca Restaurant",
    "wof:placetype":"venue"
},
  "geometry": {"coordinates":[-118.090953,34.093323],"type":"Point"}
}