{
  "type": "Feature",
  "properties": {
    "addr:full":"5805 Armada Dr Carlsbad CA 92008",
    "addr:housenumber":"5805",
    "addr:postcode":"92008",
    "addr:street":"Armada Dr",
    "iso:country":"US",
    "sg:address":"5805 Armada Dr",
    "sg:city":"Carlsbad",
    "sg:classifiers":[
        {
            "category":"Travel",
            "subcategory":"Hotels & Motels",
            "type":"Entertainment"
        }
    ],
    "sg:phone":"+1 760 827 3200",
    "sg:postcode":"92008",
    "sg:province":"CA",
    "sg:website":"www.marbrisaresort.com",
    "wof:name":"Grand Pacific Marbrisa Resort",
    "wof:placetype":"venue"
},
  "geometry": {"coordinates":[-117.316276,33.125306],"type":"Point"}
}