{
  "type": "Feature",
  "properties": {
    "addr:full":"11 El Sereno Orinda CA 94563",
    "addr:housenumber":"11",
    "addr:postcode":"94563",
    "addr:street":"El",
    "iso:country":"US",
    "sg:address":"11 El Sereno",
    "sg:city":"Orinda",
    "sg:classifiers":[
        {
            "category":"Winery",
            "type":"Food & Drink"
        }
    ],
    "sg:phone":"+1 925 254 8922",
    "sg:postcode":"94563",
    "sg:province":"CA",
    "sg:website":"www.dumol.com",
    "wof:name":"Dumol Wines",
    "wof:placetype":"venue"
},
  "geometry": {"coordinates":[-122.187084,37.897209],"type":"Point"}
}