{
  "type": "Feature",
  "properties": {
    "addr:full":"2937 Bristol St Ste A102 Costa Mesa CA 92626",
    "addr:housenumber":"2937",
    "addr:postcode":"92626",
    "addr:street":"Bristol St Ste A102 Costa",
    "iso:country":"US",
    "sg:address":"2937 Bristol St Ste A102",
    "sg:city":"Costa Mesa",
    "sg:classifiers":[
        {
            "category":"Restaurant",
            "type":"Food & Drink"
        }
    ],
    "sg:phone":"+1 714 545 1411",
    "sg:postcode":"92626",
    "sg:province":"CA",
    "sg:tags":[
        "new",
        "american",
        "brunch",
        "breakfast"
    ],
    "sg:website":"www.oldvinecafe.com",
    "wof:name":"Old Vine Caf?",
    "wof:placetype":"venue"
},
  "geometry": {"coordinates":[-117.88688399999999,33.677385],"type":"Point"}
}