{
  "type": "Feature",
  "properties": {
    "addr:full":"10866 Wilshire Blvd Los Angeles CA 90024",
    "addr:housenumber":"10866",
    "addr:postcode":"90024",
    "addr:street":"Wilshire Blvd",
    "iso:country":"US",
    "sg:address":"10866 Wilshire Blvd",
    "sg:city":"Los Angeles",
    "sg:classifiers":[
        {
            "category":"Professional",
            "subcategory":"Lawyer & Legal Services",
            "type":"Services"
        }
    ],
    "sg:phone":"+1 310 475 9606",
    "sg:postcode":"90024",
    "sg:province":"CA",
    "sg:tags":[
        "attorney"
    ],
    "wof:name":"Kenneth Dusick Law Office",
    "wof:placetype":"venue"
},
  "geometry": {"coordinates":[-118.44056,34.059692],"type":"Point"}
}