{
  "type": "Feature",
  "properties": {
    "addr:full":"1115 E Holt Blvd Ontario CA 91761",
    "addr:housenumber":"1115",
    "addr:postcode":"91761",
    "addr:street":"E Holt Blvd",
    "iso:country":"US",
    "sg:address":"1115 E Holt Blvd",
    "sg:city":"Ontario",
    "sg:classifiers":[
        {
            "category":"Retail",
            "subcategory":"Auto Repair",
            "type":"Services"
        }
    ],
    "sg:phone":"+1 909 983 7322",
    "sg:postcode":"91761",
    "sg:province":"CA",
    "sg:tags":[
        "repairing",
        "automobile"
    ],
    "wof:name":"All Cars Auto Body & Paint",
    "wof:placetype":"venue"
},
  "geometry": {"coordinates":[-117.63182,34.063485],"type":"Point"}
}