{
  "type": "Feature",
  "properties": {
    "iso:country":"US",
    "sg:address":"2816 Elmer Ln",
    "sg:city":"Bakersfield",
    "sg:classifiers":[
        {
            "category":"Building & Trades",
            "subcategory":"Construction",
            "type":"Services"
        }
    ],
    "sg:phone":"+1 661 391 9261",
    "sg:postcode":"93308",
    "sg:province":"CA",
    "sg:tags":[
        "contractor",
        "fence-sales"
    ],
    "wof:name":"Fence Menders",
    "wof:placetype":"venue"
},
  "geometry": {"coordinates":[-119.009529,35.432028],"type":"Point"}
}