{
  "type": "Feature",
  "properties": {
    "addr:full":"6079 Power Inn Rd Sacramento CA 95824",
    "addr:housenumber":"6079",
    "addr:postcode":"95824",
    "addr:street":"Power Inn Rd",
    "iso:country":"US",
    "sg:address":"6079 Power Inn Rd",
    "sg:city":"Sacramento",
    "sg:classifiers":[
        {
            "category":"Wholesale",
            "subcategory":"Construction Materials",
            "type":"Manufacturing & Wholesale Goods"
        }
    ],
    "sg:phone":"+1 916 383 0661",
    "sg:postcode":"95824",
    "sg:province":"CA",
    "sg:tags":[
        "lumber"
    ],
    "wof:name":"Commco",
    "wof:placetype":"venue"
},
  "geometry": {"coordinates":[-121.40903400000001,38.516687],"type":"Point"}
}