{
  "type": "Feature",
  "properties": {
    "iso:country":"US",
    "sg:address":"2250 Davis Ct",
    "sg:city":"Hayward",
    "sg:classifiers":[
        {
            "category":"Manufacturing",
            "subcategory":"Metals",
            "type":"Manufacturing & Wholesale Goods"
        }
    ],
    "sg:phone":"+1 510 887 6231",
    "sg:postcode":"94545",
    "sg:province":"CA",
    "sg:tags":[
        "steel"
    ],
    "wof:name":"National Metal Fabricators",
    "wof:placetype":"venue"
},
  "geometry": {"coordinates":[-122.132355,37.646679],"type":"Point"}
}