{
  "type": "Feature",
  "properties": {
    "iso:country":"US",
    "sg:address":"5630 District Blvd",
    "sg:city":"Bakersfield",
    "sg:classifiers":[
        {
            "category":"Social Services",
            "type":"Services"
        }
    ],
    "sg:phone":"+1 661 837 4393",
    "sg:postcode":"93313",
    "sg:province":"CA",
    "sg:tags":[
        "youth",
        "organization",
        "center"
    ],
    "wof:name":"Golden Empire Youth Football",
    "wof:placetype":"venue"
},
  "geometry": {"coordinates":[-119.065337,35.313134],"type":"Point"}
}