{
  "type": "Feature",
  "properties": {
    "addr:full":"3701 Old Santa Rita Rd Pleasanton CA 94588",
    "addr:housenumber":"3701",
    "addr:postcode":"94588",
    "addr:street":"Old Santa Rita Rd",
    "iso:country":"US",
    "sg:address":"3701 Old Santa Rita Rd",
    "sg:city":"Pleasanton",
    "sg:classifiers":[
        {
            "category":"Building & Trades",
            "subcategory":"Construction",
            "type":"Services"
        },
        {
            "category":"Retail",
            "subcategory":"Auto Repair",
            "type":"Services"
        }
    ],
    "sg:phone":"+1 925 227 1322",
    "sg:postcode":"94588",
    "sg:province":"CA",
    "sg:tags":[
        "glass",
        "coating",
        "tinting",
        "contractor"
    ],
    "wof:name":"Omega Tintwerks",
    "wof:placetype":"venue"
},
  "geometry": {"coordinates":[-121.878896,37.700414],"type":"Point"}
}