{
  "type": "Feature",
  "properties": {
    "addr:full":"510 3rd St Oakland CA 94607",
    "addr:housenumber":"510",
    "addr:postcode":"94607",
    "addr:street":"3Rd St",
    "iso:country":"US",
    "sg:address":"510 3rd St",
    "sg:city":"Oakland",
    "sg:classifiers":[
        {
            "category":"Professional",
            "subcategory":"Business Services",
            "type":"Services"
        }
    ],
    "sg:phone":"+1 510 987 8129",
    "sg:postcode":"94607",
    "sg:province":"CA",
    "sg:tags":[
        "handwriting",
        "expert"
    ],
    "sg:website":"www.doclab.com",
    "wof:name":"Fisher Forensic Document Lab",
    "wof:placetype":"venue"
},
  "geometry": {"coordinates":[-122.27737399999999,37.797417],"type":"Point"}
}