{
  "type": "Feature",
  "properties": {
    "addr:full":"124 N Brent St Ventura CA 93003",
    "addr:housenumber":"124",
    "addr:postcode":"93003",
    "addr:street":"N Brent St",
    "iso:country":"US",
    "sg:address":"124 N Brent St",
    "sg:city":"Ventura",
    "sg:classifiers":[
        {
            "category":"Health Services",
            "subcategory":"Doctor",
            "type":"Services"
        }
    ],
    "sg:phone":"+1 805 648 2227",
    "sg:postcode":"93003",
    "sg:province":"CA",
    "sg:tags":[
        "physician",
        "surgeon"
    ],
    "wof:name":"Advanced Surgical Assoc",
    "wof:placetype":"venue"
},
  "geometry": {"coordinates":[-119.256889,34.272771],"type":"Point"}
}