{
  "type": "Feature",
  "properties": {
    "iso:country":"US",
    "sg:address":"330 California St",
    "sg:city":"Tustin",
    "sg:classifiers":[
        {
            "category":"Building & Trades",
            "subcategory":"Construction",
            "type":"Services"
        }
    ],
    "sg:phone":"+1 562 508 2771",
    "sg:postcode":"92780",
    "sg:province":"CA",
    "sg:tags":[
        "contractor"
    ],
    "wof:name":"Integrity Garage Door Repair",
    "wof:placetype":"venue"
},
  "geometry": {"coordinates":[-117.828739,33.74239],"type":"Point"}
}