{
  "type": "Feature",
  "properties": {
    "iso:country":"US",
    "sg:address":"2731 Shelter Island Dr",
    "sg:city":"San Diego",
    "sg:classifiers":[
        {
            "category":"Shopping",
            "type":"Retail Goods"
        }
    ],
    "sg:phone":"+1 619 224 1204",
    "sg:postcode":"92106",
    "sg:province":"CA",
    "sg:tags":[
        "wedding",
        "supply"
    ],
    "wof:name":"Magical Party Rentals",
    "wof:placetype":"venue"
},
  "geometry": {"coordinates":[-117.228219,32.720838],"type":"Point"}
}