{
  "type": "Feature",
  "properties": {
    "addr:full":"323 Main St Watsonville CA 95076",
    "addr:housenumber":"323",
    "addr:postcode":"95076",
    "addr:street":"Main St",
    "iso:country":"US",
    "sg:address":"323 Main St",
    "sg:city":"Watsonville",
    "sg:classifiers":[
        {
            "category":"Restaurant",
            "type":"Food & Drink"
        }
    ],
    "sg:phone":"+1 831 768 9876",
    "sg:postcode":"95076",
    "sg:province":"CA",
    "sg:tags":[
        "dining",
        "fine",
        "mexican"
    ],
    "wof:name":"El Anteno",
    "wof:placetype":"venue"
},
  "geometry": {"coordinates":[-121.75601899999999,36.909457],"type":"Point"}
}