{
  "type": "Feature",
  "properties": {
    "addr:full":"5377 Eggers Dr Fremont CA 94536",
    "addr:housenumber":"5377",
    "addr:postcode":"94536",
    "addr:street":"Eggers Dr",
    "iso:country":"US",
    "sg:address":"5377 Eggers Dr",
    "sg:city":"Fremont",
    "sg:classifiers":[
        {
            "category":"Building & Trades",
            "subcategory":"Construction",
            "type":"Services"
        }
    ],
    "sg:phone":"+1 510 790 0372",
    "sg:postcode":"94536",
    "sg:province":"CA",
    "sg:tags":[
        "installation",
        "maintenance",
        "sign"
    ],
    "wof:name":"Metcalf Signs",
    "wof:placetype":"venue"
},
  "geometry": {"coordinates":[-122.008966,37.536136],"type":"Point"}
}