{
  "type": "Feature",
  "properties": {
    "addr:full":"15301 Farnsworth St San Leandro CA 94579",
    "addr:housenumber":"15301",
    "addr:postcode":"94579",
    "addr:street":"Farnsworth St",
    "iso:country":"US",
    "sg:address":"15301 Farnsworth St",
    "sg:city":"San Leandro",
    "sg:classifiers":[
        {
            "category":"Building & Trades",
            "subcategory":"Landscaping Services",
            "type":"Services"
        }
    ],
    "sg:phone":"+1 510 750 8432",
    "sg:postcode":"94579",
    "sg:province":"CA",
    "sg:tags":[
        "landscape",
        "contractor"
    ],
    "wof:name":"T B Landscaping By Mr Vo",
    "wof:placetype":"venue"
},
  "geometry": {"coordinates":[-122.151112,37.685448],"type":"Point"}
}