{
  "type": "Feature",
  "properties": {
    "iso:country":"US",
    "sg:address":"415 E de la Guerra St",
    "sg:city":"Santa Barbara",
    "sg:classifiers":[
        {
            "category":"Restaurant",
            "type":"Food & Drink"
        }
    ],
    "sg:phone":"+1 805 966 6041",
    "sg:postcode":"93101",
    "sg:province":"CA",
    "sg:tags":[
        "delicatessen"
    ],
    "wof:name":"Italian Grocery",
    "wof:placetype":"venue"
},
  "geometry": {"coordinates":[-119.694424,34.424256],"type":"Point"}
}