{
  "type": "Feature",
  "properties": {
    "addr:full":"260 S Halcyon Rd Arroyo Grande CA 93420",
    "addr:housenumber":"260",
    "addr:postcode":"93420",
    "addr:street":"S Halcyon Rd",
    "iso:country":"US",
    "sg:address":"260 S Halcyon Rd",
    "sg:city":"Arroyo Grande",
    "sg:classifiers":[
        {
            "category":"Health Services",
            "subcategory":"Chiropractor",
            "type":"Services"
        }
    ],
    "sg:phone":"+1 805 481 8807",
    "sg:postcode":"93420",
    "sg:province":"CA",
    "wof:name":"Davis Chiropractic Offices Inc",
    "wof:placetype":"venue"
},
  "geometry": {"coordinates":[-120.591646,35.115283],"type":"Point"}
}