{
  "type": "Feature",
  "properties": {
    "addr:full":"160 S Washington St Sonora CA 95370",
    "addr:housenumber":"160",
    "addr:postcode":"95370",
    "addr:street":"S Washington St",
    "iso:country":"US",
    "sg:address":"160 S Washington St",
    "sg:city":"Sonora",
    "sg:classifiers":[
        {
            "category":"Local Transit",
            "type":"Transportation"
        }
    ],
    "sg:phone":"+1 209 533 2698",
    "sg:postcode":"95370",
    "sg:province":"CA",
    "sg:tags":[
        "bus",
        "line"
    ],
    "wof:name":"Greyhound Bus Lines",
    "wof:placetype":"venue"
},
  "geometry": {"coordinates":[-120.382256,37.983209],"type":"Point"}
}