{
  "type": "Feature",
  "properties": {
    "addr:full":"11656 Central Ave Chino CA 91710",
    "addr:housenumber":"11656",
    "addr:postcode":"91710",
    "addr:street":"Central Ave",
    "iso:country":"US",
    "sg:address":"11656 Central Ave",
    "sg:city":"Chino",
    "sg:classifiers":[
        {
            "category":"Professional",
            "subcategory":"Engineering",
            "type":"Services"
        }
    ],
    "sg:phone":"+1 909 628 9971",
    "sg:postcode":"91710",
    "sg:province":"CA",
    "sg:tags":[
        "general",
        "contractor"
    ],
    "wof:name":"Rebar & More",
    "wof:placetype":"venue"
},
  "geometry": {"coordinates":[-117.689615,34.044035],"type":"Point"}
}