{
  "type": "Feature",
  "properties": {
    "addr:full":"201 Richards Blvd Sacramento CA 95811",
    "addr:housenumber":"201",
    "addr:postcode":"95811",
    "addr:street":"Richards Blvd",
    "iso:country":"US",
    "sg:address":"201 Richards Blvd",
    "sg:city":"Sacramento",
    "sg:classifiers":[
        {
            "category":"Taxi",
            "type":"Transportation"
        }
    ],
    "sg:phone":"+1 916 288 8500",
    "sg:postcode":"95811",
    "sg:province":"CA",
    "wof:name":"Cab Services",
    "wof:placetype":"venue"
},
  "geometry": {"coordinates":[-121.502182,38.597309],"type":"Point"}
}