{
  "type": "Feature",
  "properties": {
    "addr:full":"1615 Riverview Dr San Bernardino CA 92408",
    "addr:housenumber":"1615",
    "addr:postcode":"92408",
    "addr:street":"Riverview Dr",
    "iso:country":"US",
    "sg:address":"1615 Riverview Dr",
    "sg:city":"San Bernardino",
    "sg:classifiers":[
        {
            "category":"Building & Trades",
            "subcategory":"Construction",
            "type":"Services"
        }
    ],
    "sg:phone":"+1 909 478 9357",
    "sg:postcode":"92408",
    "sg:province":"CA",
    "sg:tags":[
        "restoration",
        "cleaning",
        "patio",
        "deck"
    ],
    "wof:name":"Barens Inc",
    "wof:placetype":"venue"
},
  "geometry": {"coordinates":[-117.24977,34.080497],"type":"Point"}
}