{
  "type": "Feature",
  "properties": {
    "addr:full":"78670 Via Sonata La Quinta CA 92253",
    "addr:housenumber":"78670",
    "addr:postcode":"92253",
    "addr:street":"Via Sonata",
    "iso:country":"US",
    "sg:address":"78670 Via Sonata",
    "sg:city":"La Quinta",
    "sg:classifiers":[
        {
            "category":"Freight",
            "type":"Transportation"
        }
    ],
    "sg:phone":"+1 760 831 4536",
    "sg:postcode":"92253",
    "sg:province":"CA",
    "sg:tags":[
        "operator",
        "personal",
        "local",
        "business",
        "trucking"
    ],
    "wof:name":"Jennifer Earred Service",
    "wof:placetype":"venue"
},
  "geometry": {"coordinates":[-116.292812,33.689584],"type":"Point"}
}