{
  "type": "Feature",
  "properties": {
    "iso:country":"US",
    "sg:address":"4000 Middlefield Rd",
    "sg:city":"Palo Alto",
    "sg:classifiers":[
        {
            "category":"Education",
            "subcategory":"Special Training",
            "type":"Public Place"
        }
    ],
    "sg:phone":"+1 650 969 1978",
    "sg:postcode":"94303",
    "sg:province":"CA",
    "sg:tags":[
        "tutoring"
    ],
    "wof:name":"Kumon Math & Reading Ctr",
    "wof:placetype":"venue"
},
  "geometry": {"coordinates":[-122.106881,37.417917],"type":"Point"}
}