{
  "type": "Feature",
  "properties": {
    "iso:country":"US",
    "sg:address":"5410 Stockdale Hwy",
    "sg:city":"Bakersfield",
    "sg:classifiers":[
        {
            "category":"Banks & Credit Unions",
            "subcategory":"Bank",
            "type":"Services"
        }
    ],
    "sg:phone":"+1 661 859 1216",
    "sg:postcode":"93309",
    "sg:province":"CA",
    "sg:tags":[
        "cashing",
        "personal",
        "check",
        "institution"
    ],
    "wof:name":"Advance America",
    "wof:placetype":"venue"
},
  "geometry": {"coordinates":[-119.066337,35.354339],"type":"Point"}
}