{
  "type": "Feature",
  "properties": {
    "addr:full":"3009 Douglas Blvd Roseville CA 95661",
    "addr:housenumber":"3009",
    "addr:postcode":"95661",
    "addr:street":"Douglas Blvd",
    "iso:country":"US",
    "sg:address":"3009 Douglas Blvd",
    "sg:city":"Roseville",
    "sg:classifiers":[
        {
            "category":"Shopping",
            "subcategory":"Computers & Home Electronics",
            "type":"Retail Goods"
        }
    ],
    "sg:phone":"+1 916 784 7878",
    "sg:postcode":"95661",
    "sg:province":"CA",
    "sg:tags":[
        "software"
    ],
    "sg:website":"www.schoolhousesoftware.com",
    "wof:name":"Schoolhouse Software Inc",
    "wof:placetype":"venue"
},
  "geometry": {"coordinates":[-121.24072200000001,38.744307],"type":"Point"}
}