{
  "type": "Feature",
  "properties": {
    "addr:full":"17244 Darwin Ave Ste J Hesperia CA 92345",
    "addr:housenumber":"17244",
    "addr:postcode":"92345",
    "addr:street":"Darwin Ave Ste J",
    "iso:country":"US",
    "sg:address":"17244 Darwin Ave Ste J",
    "sg:city":"Hesperia",
    "sg:classifiers":[
        {
            "category":"Wholesale",
            "subcategory":"Hardware",
            "type":"Manufacturing & Wholesale Goods"
        },
        {
            "category":"Home & Garden",
            "subcategory":"Hardware",
            "type":"Retail Goods"
        }
    ],
    "sg:phone":"+1 760 947 3304",
    "sg:postcode":"92345",
    "sg:province":"CA",
    "sg:tags":[
        "hardware-builders",
        "store"
    ],
    "wof:name":"Sophistication In Brass",
    "wof:placetype":"venue"
},
  "geometry": {"coordinates":[-117.284586,34.453206],"type":"Point"}
}