{
  "type": "Feature",
  "properties": {
    "iso:country":"US",
    "sg:address":"1188 Padre Dr",
    "sg:city":"Salinas",
    "sg:classifiers":[
        {
            "category":"Real Estate",
            "subcategory":"Real Estate Services",
            "type":"Services"
        },
        {
            "category":"Real Estate",
            "subcategory":"Real Estate Agent",
            "type":"Services"
        }
    ],
    "sg:phone":"+1 831 422 0682",
    "sg:postcode":"93901",
    "sg:province":"CA",
    "sg:tags":[
        "buyer",
        "broker"
    ],
    "wof:name":"Moser Cunningham Real Estate Inc.",
    "wof:placetype":"venue"
},
  "geometry": {"coordinates":[-121.661321,36.658515],"type":"Point"}
}