{
  "type": "Feature",
  "properties": {
    "iso:country":"US",
    "sg:address":"5404 Walnut Ave",
    "sg:city":"Irvine",
    "sg:classifiers":[
        {
            "category":"Personal",
            "subcategory":"Day Spa",
            "type":"Services"
        }
    ],
    "sg:phone":"+1 949 262 9219",
    "sg:postcode":"92604",
    "sg:province":"CA",
    "wof:name":"iBeauty Day Spa",
    "wof:placetype":"venue"
},
  "geometry": {"coordinates":[-117.76950600000001,33.690029],"type":"Point"}
}