{
  "type": "Feature",
  "properties": {
    "addr:full":"19186 Soledad Canyon Rd Canyon Cntry CA 91351",
    "addr:housenumber":"19186",
    "addr:postcode":"91351",
    "addr:street":"Soledad Canyon Rd",
    "iso:country":"US",
    "sg:address":"19186 Soledad Canyon Rd",
    "sg:city":"Canyon Cntry",
    "sg:classifiers":[
        {
            "category":"Shopping",
            "subcategory":"Beauty & Cosmetics",
            "type":"Retail Goods"
        },
        {
            "category":"Wholesale",
            "subcategory":"Machinery & Supplies",
            "type":"Manufacturing & Wholesale Goods"
        }
    ],
    "sg:phone":"+1 661 250 7317",
    "sg:postcode":"91351",
    "sg:province":"CA",
    "sg:tags":[
        "salon",
        "e",
        "merchandise"
    ],
    "sg:website":"www.sallybeauty.com",
    "wof:name":"Sally Beauty Supply",
    "wof:placetype":"venue"
},
  "geometry": {"coordinates":[-118.470001,34.415798],"type":"Point"}
}