{
  "type": "Feature",
  "properties": {
    "addr:full":"631 Long Beach Blvd Long Beach CA 90802",
    "addr:housenumber":"631",
    "addr:postcode":"90802",
    "addr:street":"Long Beach Blvd",
    "iso:country":"US",
    "sg:address":"631 Long Beach Blvd",
    "sg:city":"Long Beach",
    "sg:classifiers":[
        {
            "category":"Fast Food",
            "type":"Food & Drink"
        },
        {
            "category":"Restaurant",
            "type":"Food & Drink"
        }
    ],
    "sg:phone":"+1 562 437 5689",
    "sg:postcode":"90802",
    "sg:province":"CA",
    "sg:tags":[
        "mexican"
    ],
    "sg:website":"www.elpolloloco.com",
    "wof:name":"El Pollo Loco",
    "wof:placetype":"venue"
},
  "geometry": {"coordinates":[-118.18948899999999,33.774539],"type":"Point"}
}