{
  "type": "Feature",
  "properties": {
    "addr:full":"23 W Elm St Lodi CA 95240",
    "addr:housenumber":"23",
    "addr:postcode":"95240",
    "addr:street":"W Elm St",
    "iso:country":"US",
    "sg:address":"23 W Elm St",
    "sg:city":"Lodi",
    "sg:classifiers":[
        {
            "category":"Shopping",
            "subcategory":"Party Supplies",
            "type":"Retail Goods"
        },
        {
            "category":"Retail",
            "subcategory":"Event Space",
            "type":"Services"
        }
    ],
    "sg:phone":"+1 209 368 5222",
    "sg:postcode":"95240",
    "sg:province":"CA",
    "sg:tags":[
        "facility",
        "banquet",
        "reception",
        "wedding",
        "hall"
    ],
    "sg:website":"http://www.themerlot.info",
    "wof:name":"Merlot",
    "wof:placetype":"venue"
},
  "geometry": {"coordinates":[-121.272542,38.13536],"type":"Point"}
}