{
  "type": "Feature",
  "properties": {
    "addr:full":"2400 Clay Street San Francisco CA 94115",
    "addr:housenumber":"2400",
    "addr:postcode":"94115",
    "addr:street":"Clay Street",
    "iso:country":"US",
    "sg:address":"2400 Clay Street",
    "sg:city":"San Francisco",
    "sg:classifiers":[
        {
            "category":"Personal",
            "subcategory":"Hair Removal",
            "type":"Services"
        },
        {
            "category":"Personal",
            "subcategory":"Skin Care",
            "type":"Services"
        },
        {
            "category":"Personal",
            "subcategory":"Day Spa",
            "type":"Services"
        }
    ],
    "sg:phone":"+1 415 567 7200",
    "sg:postcode":"94115",
    "sg:province":"CA",
    "sg:tags":[
        "laser"
    ],
    "wof:name":"The Appearance Care Center",
    "wof:placetype":"venue"
},
  "geometry": {"coordinates":[-122.43268999999999,37.791077],"type":"Point"}
}