{
  "type": "Feature",
  "properties": {
    "iso:country":"US",
    "sg:address":"14041 Agony Hill Rd",
    "sg:city":"Grass Valley",
    "sg:classifiers":[
        {
            "category":"Building & Trades",
            "subcategory":"Landscaping Services",
            "type":"Services"
        }
    ],
    "sg:phone":"+1 530 477 5509",
    "sg:postcode":"95945",
    "sg:province":"CA",
    "sg:tags":[
        "landscape"
    ],
    "wof:name":"Flora & Forest",
    "wof:placetype":"venue"
},
  "geometry": {"coordinates":[-121.006084,39.18382],"type":"Point"}
}