{
  "type": "Feature",
  "properties": {
    "addr:full":"800 S Main St Corona CA 92882",
    "addr:housenumber":"800",
    "addr:postcode":"92882",
    "addr:street":"S Main St",
    "iso:country":"US",
    "sg:address":"800 S Main St",
    "sg:city":"Corona",
    "sg:classifiers":[
        {
            "category":"Health Services",
            "subcategory":"Hospital",
            "type":"Services"
        }
    ],
    "sg:phone":"+1 951 372 9152",
    "sg:postcode":"92882",
    "sg:province":"CA",
    "sg:tags":[
        "general"
    ],
    "wof:name":"Main Hospital",
    "wof:placetype":"venue"
},
  "geometry": {"coordinates":[-117.56685299999999,33.872298],"type":"Point"}
}