{
  "type": "Feature",
  "properties": {
    "iso:country":"US",
    "sg:address":"227 Kearney Exd",
    "sg:city":"Watsonville",
    "sg:classifiers":[
        {
            "category":"Building & Trades",
            "subcategory":"Construction",
            "type":"Services"
        }
    ],
    "sg:phone":"+1 831 724 4432",
    "sg:postcode":"95076",
    "sg:province":"CA",
    "sg:tags":[
        "fabricator",
        "metal"
    ],
    "wof:name":"Large's Metal Fabrication",
    "wof:placetype":"venue"
},
  "geometry": {"coordinates":[-121.766353,36.908032],"type":"Point"}
}