{
  "type": "Feature",
  "properties": {
    "addr:full":"5442 Castle Manor Dr San Jose CA 95129",
    "addr:housenumber":"5442",
    "addr:postcode":"95129",
    "addr:street":"Castle Manor Dr",
    "iso:country":"US",
    "sg:address":"5442 Castle Manor Dr",
    "sg:city":"San Jose",
    "sg:classifiers":[
        {
            "category":"Professional",
            "subcategory":"Research",
            "type":"Services"
        },
        {
            "category":"Professional",
            "subcategory":"Management & Consulting",
            "type":"Services"
        }
    ],
    "sg:phone":"+1 408 986 0123",
    "sg:postcode":"95129",
    "sg:province":"CA",
    "sg:tags":[
        "development",
        "product",
        "business",
        "mfg",
        "marketing",
        "motor",
        "vehicle"
    ],
    "wof:name":"Advanced Results Co Inc",
    "wof:placetype":"venue"
},
  "geometry": {"coordinates":[-121.999056,37.298803],"type":"Point"}
}