{
  "type": "Feature",
  "properties": {
    "iso:country":"US",
    "sg:address":"6 Circle Dr",
    "sg:city":"Belvedere Tibrn",
    "sg:classifiers":[
        {
            "category":"Shopping",
            "subcategory":"Clothing, Apparel, & Fashions",
            "type":"Retail Goods"
        }
    ],
    "sg:phone":"+1 415 388 2749",
    "sg:postcode":"94920",
    "sg:province":"CA",
    "sg:tags":[
        "alteration"
    ],
    "wof:name":"NAZ Alteration & New Items",
    "wof:placetype":"venue"
},
  "geometry": {"coordinates":[-122.496466,37.898023],"type":"Point"}
}