{
  "type": "Feature",
  "properties": {
    "addr:full":"3600 Standish Ave Santa Rosa CA 95407",
    "addr:housenumber":"3600",
    "addr:postcode":"95407",
    "addr:street":"Standish Ave",
    "iso:country":"US",
    "sg:address":"3600 Standish Ave",
    "sg:city":"Santa Rosa",
    "sg:classifiers":[
        {
            "category":"Manufacturing",
            "subcategory":"Metals",
            "type":"Manufacturing & Wholesale Goods"
        }
    ],
    "sg:phone":"+1 707 586 1798",
    "sg:postcode":"95407",
    "sg:province":"CA",
    "sg:tags":[
        "tank"
    ],
    "wof:name":"PBC Mfg Intl",
    "wof:placetype":"venue"
},
  "geometry": {"coordinates":[-122.722998,38.387212],"type":"Point"}
}