{
  "type": "Feature",
  "properties": {
    "addr:full":"400 N Harbor Blvd Anaheim CA 92805",
    "addr:housenumber":"400",
    "addr:postcode":"92805",
    "addr:street":"N Harbor Blvd",
    "iso:country":"US",
    "sg:address":"400 N Harbor Blvd",
    "sg:city":"Anaheim",
    "sg:classifiers":[
        {
            "category":"Park",
            "type":"Public Place"
        },
        {
            "category":"Sports & Exercise",
            "subcategory":"Swimming Pool",
            "type":"Entertainment"
        }
    ],
    "sg:postcode":"92805",
    "sg:province":"CA",
    "sg:website":"www.anaheim.net/",
    "wof:name":"Pearson Park & Pool",
    "wof:placetype":"venue"
},
  "geometry": {"coordinates":[-117.91871999999999,33.837904],"type":"Point"}
}