{
  "type": "Feature",
  "properties": {
    "iso:country":"US",
    "sg:address":"3167 Rockgate Pl",
    "sg:city":"Simi Valley",
    "sg:classifiers":[
        {
            "category":"Manufacturing",
            "subcategory":"Motor Vehicles & Parts",
            "type":"Manufacturing & Wholesale Goods"
        }
    ],
    "sg:phone":"+1 805 583 1335",
    "sg:postcode":"93063",
    "sg:province":"CA",
    "sg:tags":[
        "auto",
        "mfg",
        "trimming"
    ],
    "wof:name":"Creative Designs By Patty",
    "wof:placetype":"venue"
},
  "geometry": {"coordinates":[-118.721018,34.292068],"type":"Point"}
}