{
  "type": "Feature",
  "properties": {
    "iso:country":"US",
    "sg:address":"14857 Gale Ave",
    "sg:city":"Hacienda Heights",
    "sg:classifiers":[
        {
            "category":"Manufacturing",
            "subcategory":"Apparel",
            "type":"Manufacturing & Wholesale Goods"
        }
    ],
    "sg:phone":"+1 626 333 6327",
    "sg:postcode":"91745",
    "sg:province":"CA",
    "sg:tags":[
        "textile",
        "product",
        "fabricated",
        "mfg"
    ],
    "wof:name":"Stitching Horse Ltd",
    "wof:placetype":"venue"
},
  "geometry": {"coordinates":[-117.98254,34.017828],"type":"Point"}
}