{
  "type": "Feature",
  "properties": {
    "addr:full":"8801 Beau Maison Way Bakersfield CA 93311",
    "addr:housenumber":"8801",
    "addr:postcode":"93311",
    "addr:street":"Beau Maison Way",
    "iso:country":"US",
    "sg:address":"8801 Beau Maison Way",
    "sg:city":"Bakersfield",
    "sg:classifiers":[
        {
            "category":"Professional",
            "type":"Services"
        }
    ],
    "sg:phone":"+1 661 665 0665",
    "sg:postcode":"93311",
    "sg:province":"CA",
    "wof:name":"Divine Concepts",
    "wof:placetype":"venue"
},
  "geometry": {"coordinates":[-119.100677,35.338766],"type":"Point"}
}