{
  "type": "Feature",
  "properties": {
    "addr:full":"17108 Edwards Rd Cerritos CA 90703",
    "addr:housenumber":"17108",
    "addr:postcode":"ca 90703",
    "addr:street":"Edwards Rd",
    "iso:country":"US",
    "sg:address":"17108 Edwards Rd",
    "sg:city":"Cerritos",
    "sg:classifiers":[
        {
            "category":"Manufacturing",
            "subcategory":"Food",
            "type":"Manufacturing & Wholesale Goods"
        }
    ],
    "sg:phone":"+1 562 926 3385",
    "sg:postcode":"90703",
    "sg:province":"CA",
    "sg:tags":[
        "sugar"
    ],
    "wof:name":"Arrowhead Syrup Sales Inc",
    "wof:placetype":"venue"
},
  "geometry": {"coordinates":[-118.034381,33.876341],"type":"Point"}
}