{
  "type": "Feature",
  "properties": {
    "iso:country":"US",
    "sg:address":"421 N Chapel Ave",
    "sg:city":"Alhambra",
    "sg:classifiers":[
        {
            "category":"Banks & Credit Unions",
            "subcategory":"Bank",
            "type":"Services"
        }
    ],
    "sg:phone":"+1 626 627 9716",
    "sg:postcode":"91801",
    "sg:province":"CA",
    "sg:tags":[
        "broker",
        "mortgage"
    ],
    "wof:name":"Finance Company",
    "wof:placetype":"venue"
},
  "geometry": {"coordinates":[-118.127506,34.101965],"type":"Point"}
}