{
  "type": "Feature",
  "properties": {
    "addr:full":"26071 Merit Cir Laguna Hills CA 92653",
    "addr:postcode":"26071;92653",
    "addr:street":"Merit Cir",
    "iso:country":"US",
    "sg:address":"26071 Merit Cir",
    "sg:city":"Laguna Hills",
    "sg:classifiers":[
        {
            "category":"Professional",
            "subcategory":"Lawyer & Legal Services",
            "type":"Services"
        }
    ],
    "sg:phone":"+1 949 582 8833",
    "sg:postcode":"92653",
    "sg:province":"CA",
    "sg:tags":[
        "attorney"
    ],
    "wof:name":"Conrad G Tuohey A Pro Law Corp",
    "wof:placetype":"venue"
},
  "geometry": {"coordinates":[-117.67455699999999,33.574162],"type":"Point"}
}