{
  "type": "Feature",
  "properties": {
    "addr:full":"311 3rd St San Francisco CA 94107",
    "addr:housenumber":"311",
    "addr:postcode":"94107",
    "addr:street":"3Rd St",
    "iso:country":"US",
    "sg:address":"311 3rd St",
    "sg:city":"San Francisco",
    "sg:classifiers":[
        {
            "category":"Restaurant",
            "type":"Food & Drink"
        }
    ],
    "sg:menulink":"http://www.allmenus.com/ca/san-francisco/91319-bong-su/menu/",
    "sg:phone":"+1 415 536 5800",
    "sg:postcode":"94107",
    "sg:province":"CA",
    "sg:tags":[
        "asian",
        "vietnamese"
    ],
    "wof:name":"Bong Su",
    "wof:placetype":"venue"
},
  "geometry": {"coordinates":[-122.398791,37.783657],"type":"Point"}
}