{
  "type": "Feature",
  "properties": {
    "addr:full":"18455 Santa Yolanda Cir Fountain Valley CA 92708",
    "addr:housenumber":"18455",
    "addr:postcode":"92708",
    "addr:street":"Santa Yolanda Cir",
    "iso:country":"US",
    "sg:address":"18455 Santa Yolanda Cir",
    "sg:city":"Fountain Valley",
    "sg:classifiers":[
        {
            "category":"Real Estate",
            "subcategory":"Real Estate Agent",
            "type":"Services"
        }
    ],
    "sg:phone":"+1 714 968 5308",
    "sg:postcode":"92708",
    "sg:province":"CA",
    "wof:name":"Art of Real Estate",
    "wof:placetype":"venue"
},
  "geometry": {"coordinates":[-117.973046,33.69549],"type":"Point"}
}