{
  "type": "Feature",
  "properties": {
    "iso:country":"US",
    "sg:address":"32395 Clinton Keith Rd # B6",
    "sg:city":"Wildomar",
    "sg:classifiers":[
        {
            "category":"Banks & Credit Unions",
            "subcategory":"Financial Services",
            "type":"Services"
        }
    ],
    "sg:phone":"+1 951 678 5650",
    "sg:postcode":"92595",
    "sg:province":"CA",
    "sg:tags":[
        "financing",
        "cashing",
        "loan",
        "payday",
        "alternative",
        "check"
    ],
    "sg:website":"http://www.bvcashadvance.com",
    "wof:name":"B V Cash Advance",
    "wof:placetype":"venue"
},
  "geometry": {"coordinates":[-117.252089,33.589315],"type":"Point"}
}