{
  "type": "Feature",
  "properties": {
    "iso:country":"US",
    "sg:address":"17752 Sampson Ln",
    "sg:city":"Huntington Beach",
    "sg:classifiers":[
        {
            "category":"Retail",
            "subcategory":"Repair Shop",
            "type":"Services"
        }
    ],
    "sg:phone":"+1 714 847 5547",
    "sg:postcode":"92647",
    "sg:province":"CA",
    "sg:tags":[
        "reupholstery",
        "furniture"
    ],
    "wof:name":"Fibertech",
    "wof:placetype":"venue"
},
  "geometry": {"coordinates":[-117.99699699999999,33.704011],"type":"Point"}
}