{
  "type": "Feature",
  "properties": {
    "iso:country":"US",
    "sg:address":"1529 W Pacific Coast Hwy",
    "sg:city":"Long Beach",
    "sg:classifiers":[
        {
            "category":"Shopping",
            "subcategory":"Books",
            "type":"Retail Goods"
        }
    ],
    "sg:phone":"+1 562 437 9312",
    "sg:postcode":"90810",
    "sg:province":"CA",
    "sg:tags":[
        "dealer"
    ],
    "wof:name":"Pacific World Books",
    "wof:placetype":"venue"
},
  "geometry": {"coordinates":[-118.213421,33.789927],"type":"Point"}
}