{
  "type": "Feature",
  "properties": {
    "iso:country":"US",
    "sg:address":"1125 N Lincoln St",
    "sg:city":"Stockton",
    "sg:classifiers":[
        {
            "category":"Social Services",
            "type":"Services"
        }
    ],
    "sg:phone":"+1 209 465 5433",
    "sg:postcode":"95203",
    "sg:province":"CA",
    "sg:tags":[
        "organization",
        "welfare"
    ],
    "wof:name":"Community Of Caring",
    "wof:placetype":"venue"
},
  "geometry": {"coordinates":[-121.300845,37.96297],"type":"Point"}
}