{
  "type": "Feature",
  "properties": {
    "addr:full":"7071 Carroll Rd San Diego CA 92121",
    "addr:housenumber":"7071",
    "addr:postcode":"92121",
    "addr:street":"Carroll Rd",
    "iso:country":"US",
    "sg:address":"7071 Carroll Rd",
    "sg:city":"San Diego",
    "sg:classifiers":[
        {
            "category":"Manufacturing",
            "subcategory":"Tools & Machinery",
            "type":"Manufacturing & Wholesale Goods"
        }
    ],
    "sg:phone":"+1 858 452 0562",
    "sg:postcode":"92121",
    "sg:province":"CA",
    "sg:tags":[
        "contractor"
    ],
    "wof:name":"Anchor Construction Inc",
    "wof:placetype":"venue"
},
  "geometry": {"coordinates":[-117.168683,32.885239],"type":"Point"}
}