{
  "type": "Feature",
  "properties": {
    "iso:country":"US",
    "sg:address":"14114 Victory Blvd",
    "sg:city":"Van Nuys",
    "sg:classifiers":[
        {
            "category":"Utilities",
            "subcategory":"Mobile Phone",
            "type":"Services"
        }
    ],
    "sg:phone":"+1 818 786 0545",
    "sg:postcode":"91401",
    "sg:province":"CA",
    "sg:tags":[
        "telephone",
        "cellular"
    ],
    "wof:name":"Star's Wireless",
    "wof:placetype":"venue"
},
  "geometry": {"coordinates":[-118.441907,34.186589],"type":"Point"}
}