{
  "type": "Feature",
  "properties": {
    "iso:country":"US",
    "sg:address":"6815 Whitsett Ave",
    "sg:city":"North Hollywood",
    "sg:classifiers":[
        {
            "category":"Health Services",
            "subcategory":"Medical Lab",
            "type":"Services"
        }
    ],
    "sg:phone":"+1 818 708 0268",
    "sg:postcode":"91605",
    "sg:province":"CA",
    "sg:tags":[
        "laboratory"
    ],
    "wof:name":"Valley Imaging Assoc",
    "wof:placetype":"venue"
},
  "geometry": {"coordinates":[-118.405325,34.196685],"type":"Point"}
}