{
  "type": "Feature",
  "properties": {
    "addr:full":"924 W Olive Ave Burbank CA 91506",
    "addr:housenumber":"924",
    "addr:postcode":"91506",
    "addr:street":"W Olive Ave",
    "iso:country":"US",
    "sg:address":"924 W Olive Ave",
    "sg:city":"Burbank",
    "sg:classifiers":[
        {
            "category":"Travel",
            "subcategory":"Hotels & Motels",
            "type":"Entertainment"
        }
    ],
    "sg:phone":"+1 818 848 5100",
    "sg:postcode":"91506",
    "sg:province":"CA",
    "sg:website":"www.portofinoburbank.com",
    "wof:name":"Portofino Inn",
    "wof:placetype":"venue"
},
  "geometry": {"coordinates":[-118.317001,34.1735],"type":"Point"}
}