{
  "type": "Feature",
  "properties": {
    "addr:full":"5857 San Pablo Ave Oakland CA 94608",
    "addr:housenumber":"5857",
    "addr:postcode":"94608",
    "addr:street":"San Pablo Ave",
    "iso:country":"US",
    "sg:address":"5857 San Pablo Ave",
    "sg:city":"Oakland",
    "sg:classifiers":[
        {
            "category":"Arts & Performance",
            "subcategory":"Art Gallery",
            "type":"Entertainment"
        }
    ],
    "sg:phone":"+1 510 923 1544",
    "sg:postcode":"94608",
    "sg:province":"CA",
    "sg:website":"www.forthriteprinting.com",
    "wof:name":"Forthrite Gallery",
    "wof:placetype":"venue"
},
  "geometry": {"coordinates":[-122.283776,37.841929],"type":"Point"}
}