{
  "type": "Feature",
  "properties": {
    "iso:country":"US",
    "sg:address":"14355 Cottage Cir",
    "sg:city":"Chino Hills",
    "sg:classifiers":[
        {
            "category":"Professional",
            "type":"Services"
        }
    ],
    "sg:phone":"+1 909 469 4489",
    "sg:postcode":"91709",
    "sg:province":"CA",
    "wof:name":"Ayuda Para Latinos",
    "wof:placetype":"venue"
},
  "geometry": {"coordinates":[-117.757481,33.99092],"type":"Point"}
}