{
  "type": "Feature",
  "properties": {
    "addr:full":"8827 Beverly Blvd Los Angeles CA 90048",
    "addr:housenumber":"8827",
    "addr:postcode":"90048",
    "addr:street":"Beverly Blvd",
    "iso:country":"US",
    "sg:address":"8827 Beverly Blvd",
    "sg:city":"Los Angeles",
    "sg:classifiers":[
        {
            "category":"Arts & Performance",
            "subcategory":"Theater",
            "type":"Entertainment"
        }
    ],
    "sg:phone":"+1 310 859 8877",
    "sg:postcode":"90048",
    "sg:province":"CA",
    "sg:tags":[
        "talent",
        "agency",
        "casting"
    ],
    "wof:name":"Shapiro-Lichtman Inc",
    "wof:placetype":"venue"
},
  "geometry": {"coordinates":[-118.384567,34.077247],"type":"Point"}
}