{
  "type": "Feature",
  "properties": {
    "addr:full":"17 Pintail Irvine CA 92604",
    "addr:housenumber":"17",
    "addr:postcode":"92604",
    "addr:street":"Pintail",
    "iso:country":"US",
    "sg:address":"17 Pintail",
    "sg:city":"Irvine",
    "sg:classifiers":[
        {
            "category":"Professional",
            "type":"Services"
        }
    ],
    "sg:phone":"+1 949 733 1229",
    "sg:postcode":"92604",
    "sg:province":"CA",
    "wof:name":"Tabby",
    "wof:placetype":"venue"
},
  "geometry": {"coordinates":[-117.79322000000001,33.68485],"type":"Point"}
}