{
  "type": "Feature",
  "properties": {
    "addr:full":"8362 Buffalo Ave Panorama City CA 91402",
    "addr:housenumber":"8362",
    "addr:postcode":"91402",
    "addr:street":"Buffalo Ave",
    "iso:country":"US",
    "sg:address":"8362 Buffalo Ave",
    "sg:city":"Panorama City",
    "sg:classifiers":[
        {
            "category":"Banks & Credit Unions",
            "subcategory":"Investment Brokerage",
            "type":"Services"
        }
    ],
    "sg:phone":"+1 818 988 2898",
    "sg:postcode":"91402",
    "sg:province":"CA",
    "sg:tags":[
        "security",
        "stock",
        "bond"
    ],
    "wof:name":"Brookstreet Securities Corp",
    "wof:placetype":"venue"
},
  "geometry": {"coordinates":[-118.432007,34.223727],"type":"Point"}
}