{
  "type": "Feature",
  "properties": {
    "addr:full":"35640 Lundy Dr Newark CA 94560",
    "addr:housenumber":"35640",
    "addr:postcode":"94560",
    "addr:street":"Lundy Dr",
    "iso:country":"US",
    "sg:address":"35640 Lundy Dr",
    "sg:city":"Newark",
    "sg:classifiers":[
        {
            "category":"Organizations",
            "subcategory":"Community Association",
            "type":"Services"
        }
    ],
    "sg:phone":"+1 510 552 3758",
    "sg:postcode":"94560",
    "sg:province":"CA",
    "sg:tags":[
        "support",
        "business"
    ],
    "wof:name":"Lodestar Support Svc",
    "wof:placetype":"venue"
},
  "geometry": {"coordinates":[-122.03617,37.55405],"type":"Point"}
}