{
  "type": "Feature",
  "properties": {
    "iso:country":"US",
    "sg:address":"3007 Malibu Canyon Rd",
    "sg:city":"Malibu",
    "sg:classifiers":[
        {
            "category":"Professional",
            "subcategory":"Research",
            "type":"Services"
        }
    ],
    "sg:phone":"+1 310 317 8900",
    "sg:postcode":"90265",
    "sg:province":"CA",
    "sg:tags":[
        "commercial",
        "physical"
    ],
    "wof:name":"Ceres Inc",
    "wof:placetype":"venue"
},
  "geometry": {"coordinates":[-118.692421,34.042809],"type":"Point"}
}