{
  "type": "Feature",
  "properties": {
    "iso:country":"US",
    "sg:address":"4747 Brooks St",
    "sg:city":"Montclair",
    "sg:classifiers":[
        {
            "category":"Manufacturing",
            "subcategory":"Metals",
            "type":"Manufacturing & Wholesale Goods"
        }
    ],
    "sg:phone":"+1 909 626 4014",
    "sg:postcode":"91763",
    "sg:province":"CA",
    "sg:tags":[
        "tool",
        "mfg"
    ],
    "sg:website":"www.adaptertool.com",
    "wof:name":"Adapter Tool Products",
    "wof:placetype":"venue"
},
  "geometry": {"coordinates":[-117.703039,34.061585],"type":"Point"}
}