{
  "type": "Feature",
  "properties": {
    "iso:country":"US",
    "sg:address":"439 2nd St",
    "sg:city":"Woodland",
    "sg:classifiers":[
        {
            "category":"Organizations",
            "subcategory":"Religious Organization",
            "type":"Services"
        }
    ],
    "sg:phone":"+1 530 406 8579",
    "sg:postcode":"95695",
    "sg:province":"CA",
    "sg:tags":[
        "church"
    ],
    "wof:name":"Church Of The Rock",
    "wof:placetype":"venue"
},
  "geometry": {"coordinates":[-121.771837,38.676332],"type":"Point"}
}