{
  "type": "Feature",
  "properties": {
    "addr:full":"1230 N St Ofc Sacramento CA 95814",
    "addr:housenumber":"1230",
    "addr:postcode":"95814",
    "addr:street":"N St",
    "iso:country":"US",
    "sg:address":"1230 N St Ofc",
    "sg:city":"Sacramento",
    "sg:classifiers":[
        {
            "category":"Education",
            "subcategory":"Special Training",
            "type":"Public Place"
        }
    ],
    "sg:phone":"+1 916 443 6788",
    "sg:postcode":"95814",
    "sg:province":"CA",
    "sg:tags":[
        "aid",
        "instruction",
        "safety",
        "first"
    ],
    "wof:name":"State Job Workshops",
    "wof:placetype":"venue"
},
  "geometry": {"coordinates":[-121.49224599999999,38.575046],"type":"Point"}
}