{
  "type": "Feature",
  "properties": {
    "iso:country":"US",
    "sg:address":"1753 Landess Ave",
    "sg:city":"Milpitas",
    "sg:classifiers":[
        {
            "category":"Health Services",
            "subcategory":"Chiropractor",
            "type":"Services"
        }
    ],
    "sg:phone":"+1 408 942 8787",
    "sg:postcode":"95035",
    "sg:province":"CA",
    "wof:name":"Grewal Chiropractic",
    "wof:placetype":"venue"
},
  "geometry": {"coordinates":[-121.873624,37.416583],"type":"Point"}
}