{
  "type": "Feature",
  "properties": {
    "addr:full":"2441 Ramona Expy San Jacinto CA 92582",
    "addr:housenumber":"2441",
    "addr:postcode":"92582",
    "addr:street":"Ramona Expy",
    "iso:country":"US",
    "sg:address":"2441 Ramona Expy",
    "sg:city":"San Jacinto",
    "sg:classifiers":[
        {
            "category":"Wholesale",
            "subcategory":"Farm Supplies",
            "type":"Manufacturing & Wholesale Goods"
        }
    ],
    "sg:phone":"+1 951 487 8897",
    "sg:postcode":"92582",
    "sg:province":"CA",
    "sg:tags":[
        "feed"
    ],
    "wof:name":"Ramona Commodities Inc",
    "wof:placetype":"venue"
},
  "geometry": {"coordinates":[-117.005353,33.823691],"type":"Point"}
}