{
  "type": "Feature",
  "properties": {
    "addr:full":"44751 Date Ave Lancaster CA 93534",
    "addr:housenumber":"44751",
    "addr:postcode":"93534",
    "addr:street":"Date Ave",
    "iso:country":"US",
    "sg:address":"44751 Date Ave",
    "sg:city":"Lancaster",
    "sg:classifiers":[
        {
            "category":"Real Estate",
            "subcategory":"Real Estate Services",
            "type":"Services"
        },
        {
            "category":"Real Estate",
            "subcategory":"Real Estate Agent",
            "type":"Services"
        }
    ],
    "sg:phone":"+1 661 945 5783",
    "sg:postcode":"93534",
    "sg:province":"CA",
    "sg:tags":[
        "buyer",
        "broker"
    ],
    "wof:name":"Liberty Realty",
    "wof:placetype":"venue"
},
  "geometry": {"coordinates":[-118.14035699999999,34.695249],"type":"Point"}
}