{
  "type": "Feature",
  "properties": {
    "addr:full":"2236 Martin Luther King Jr Way Oakland CA 94612",
    "addr:housenumber":"2236",
    "addr:postcode":"94612",
    "addr:street":"Martin Luther King Jr Way",
    "iso:country":"US",
    "sg:address":"2236 Martin Luther King Jr Way",
    "sg:city":"Oakland",
    "sg:classifiers":[
        {
            "category":"Building & Trades",
            "subcategory":"Cleaning & Sanitation",
            "type":"Services"
        },
        {
            "category":"Autos & Motor Vehicles",
            "subcategory":"Auto Supplies",
            "type":"Retail Goods"
        },
        {
            "category":"Shopping",
            "type":"Retail Goods"
        }
    ],
    "sg:phone":"+1 510 893 0611",
    "sg:postcode":"94612",
    "sg:province":"CA",
    "sg:tags":[
        "equipment-wholesale",
        "rug",
        "equipment",
        "furniture",
        "carpet",
        "manufacturer"
    ],
    "wof:name":"All Star Products",
    "wof:placetype":"venue"
},
  "geometry": {"coordinates":[-122.272758,37.812531],"type":"Point"}
}