{
  "type": "Feature",
  "properties": {
    "addr:full":"550 S Hill St Ste 510 Los Angeles CA 90013",
    "addr:housenumber":"550",
    "addr:postcode":"90013",
    "addr:street":"S Hill St Ste 510",
    "iso:country":"US",
    "sg:address":"550 S Hill St Ste 510",
    "sg:city":"Los Angeles",
    "sg:classifiers":[
        {
            "category":"Shopping",
            "subcategory":"Jewelry",
            "type":"Retail Goods"
        }
    ],
    "sg:phone":"+1 213 622 7262",
    "sg:postcode":"90013",
    "sg:province":"CA",
    "sg:website":"www.wilsonsjewelry.com",
    "wof:name":"Wilson's Jewelry",
    "wof:placetype":"venue"
},
  "geometry": {"coordinates":[-118.252421,34.047543],"type":"Point"}
}