{
  "type": "Feature",
  "properties": {
    "iso:country":"US",
    "sg:address":"790 Alvarado Rd",
    "sg:city":"Berkeley",
    "sg:classifiers":[
        {
            "category":"Real Estate",
            "subcategory":"Architect",
            "type":"Services"
        }
    ],
    "sg:phone":"+1 510 841 7141",
    "sg:postcode":"94705",
    "sg:province":"CA",
    "sg:tags":[
        "home",
        "builder",
        "construction",
        "architectural",
        "house"
    ],
    "wof:name":"Robert Mueller Design",
    "wof:placetype":"venue"
},
  "geometry": {"coordinates":[-122.239001,37.860128],"type":"Point"}
}