{
  "type": "Feature",
  "properties": {
    "addr:full":"622 Broadway San Francisco CA 94133",
    "addr:housenumber":"622",
    "addr:postcode":"94133",
    "addr:street":"Broadway",
    "iso:country":"US",
    "sg:address":"622 Broadway",
    "sg:city":"San Francisco",
    "sg:classifiers":[
        {
            "category":"Shopping",
            "subcategory":"Discount & Variety Stores",
            "type":"Retail Goods"
        }
    ],
    "sg:phone":"+1 415 772 9183",
    "sg:postcode":"94133",
    "sg:province":"CA",
    "wof:name":"Lucky Star Discount Store",
    "wof:placetype":"venue"
},
  "geometry": {"coordinates":[-122.407387,37.797865],"type":"Point"}
}