{
  "type": "Feature",
  "properties": {
    "addr:full":"920 11th Ave Delano CA 93215",
    "addr:housenumber":"920",
    "addr:postcode":"93215",
    "addr:street":"11Th Ave",
    "iso:country":"US",
    "sg:address":"920 11th Ave",
    "sg:city":"Delano",
    "sg:classifiers":[
        {
            "category":"Banks & Credit Unions",
            "subcategory":"Bank",
            "type":"Services"
        }
    ],
    "sg:phone":"+1 661 725 2524",
    "sg:postcode":"93215",
    "sg:province":"CA",
    "wof:name":"Wells Fargo Bank",
    "wof:placetype":"venue"
},
  "geometry": {"coordinates":[-119.244823,35.770488],"type":"Point"}
}