{
  "type": "Feature",
  "properties": {
    "iso:country":"US",
    "sg:address":"519 Parrott St",
    "sg:city":"San Jose",
    "sg:classifiers":[
        {
            "category":"Wholesale",
            "subcategory":"Electrical",
            "type":"Manufacturing & Wholesale Goods"
        }
    ],
    "sg:phone":"+1 408 928 2000",
    "sg:postcode":"95112",
    "sg:province":"CA",
    "sg:tags":[
        "equipment"
    ],
    "wof:name":"PSI",
    "wof:placetype":"venue"
},
  "geometry": {"coordinates":[-121.851286,37.307844],"type":"Point"}
}