{
  "type": "Feature",
  "properties": {
    "addr:full":"6092 Pony Express Trl Pollock Pines CA 95726",
    "addr:housenumber":"6092",
    "addr:postcode":"95726",
    "addr:street":"Pony Express Trl",
    "iso:country":"US",
    "sg:address":"6092 Pony Express Trl",
    "sg:city":"Pollock Pines",
    "sg:classifiers":[
        {
            "category":"Professional",
            "subcategory":"Accounting & Tax Preparation",
            "type":"Services"
        }
    ],
    "sg:phone":"+1 530 644 2227",
    "sg:postcode":"95726",
    "sg:province":"CA",
    "sg:tags":[
        "return",
        "filing"
    ],
    "wof:name":"Turner's Tax Svc",
    "wof:placetype":"venue"
},
  "geometry": {"coordinates":[-120.592974,38.757443],"type":"Point"}
}