{
  "type": "Feature",
  "properties": {
    "addr:full":"86075 60th Ave Thermal CA 92274",
    "addr:housenumber":"86075",
    "addr:postcode":"92274",
    "addr:street":"60Th Ave",
    "iso:country":"US",
    "sg:address":"86075 60th Ave",
    "sg:city":"Thermal",
    "sg:classifiers":[
        {
            "category":"Building & Trades",
            "subcategory":"Plumbing",
            "type":"Services"
        }
    ],
    "sg:phone":"+1 760 399 8600",
    "sg:postcode":"92274",
    "sg:province":"CA",
    "sg:tags":[
        "preparation",
        "contractor",
        "crop",
        "f"
    ],
    "wof:name":"Oak Flat Hay Company",
    "wof:placetype":"venue"
},
  "geometry": {"coordinates":[-116.16388999999999,33.612935],"type":"Point"}
}