{
  "type": "Feature",
  "properties": {
    "iso:country":"US",
    "sg:address":"22889 Kingsford Way",
    "sg:city":"Hayward",
    "sg:classifiers":[
        {
            "category":"Building & Trades",
            "subcategory":"Electrical",
            "type":"Services"
        }
    ],
    "sg:phone":"+1 510 537 1800",
    "sg:postcode":"94541",
    "sg:province":"CA",
    "sg:tags":[
        "industrial",
        "electrician",
        "contractors-commercial",
        "electric"
    ],
    "wof:name":"1st Class Electric",
    "wof:placetype":"venue"
},
  "geometry": {"coordinates":[-122.083681,37.666673],"type":"Point"}
}