{
  "type": "Feature",
  "properties": {
    "addr:full":"618 W Bradley Ave El Cajon CA 92020",
    "addr:housenumber":"618",
    "addr:postcode":"92020",
    "addr:street":"W Bradley Ave",
    "iso:country":"US",
    "sg:address":"618 W Bradley Ave",
    "sg:city":"El Cajon",
    "sg:classifiers":[
        {
            "category":"Building & Trades",
            "subcategory":"Construction",
            "type":"Services"
        },
        {
            "category":"Manufacturing",
            "subcategory":"Rubber & Plastics",
            "type":"Manufacturing & Wholesale Goods"
        }
    ],
    "sg:phone":"+1 619 444 9442",
    "sg:postcode":"92020",
    "sg:province":"CA",
    "sg:tags":[
        "mfg",
        "laminated",
        "cabinet",
        "wood",
        "maker",
        "kitchen"
    ],
    "wof:name":"A-1 Plastics",
    "wof:placetype":"venue"
},
  "geometry": {"coordinates":[-116.970992,32.817012],"type":"Point"}
}