{
  "type": "Feature",
  "properties": {
    "iso:country":"US",
    "sg:address":"506 Fulmar Dr",
    "sg:city":"Suisun City",
    "sg:classifiers":[
        {
            "category":"Building & Trades",
            "subcategory":"Cleaning & Sanitation",
            "type":"Services"
        }
    ],
    "sg:phone":"+1 707 429 0115",
    "sg:postcode":"94585",
    "sg:province":"CA",
    "sg:tags":[
        "venetian",
        "blind"
    ],
    "wof:name":"Affordable Blind Cleaning",
    "wof:placetype":"venue"
},
  "geometry": {"coordinates":[-121.991692,38.244864],"type":"Point"}
}