{
  "type": "Feature",
  "properties": {
    "iso:country":"US",
    "sg:address":"8329 Fair Oaks Boulevard",
    "sg:city":"Carmichael",
    "sg:classifiers":[
        {
            "category":"Health Services",
            "subcategory":"Dentist",
            "type":"Services"
        }
    ],
    "sg:phone":"+1 916 944 4782",
    "sg:postcode":"95608",
    "sg:province":"CA",
    "wof:name":"Healthy Image Dental Group",
    "wof:placetype":"venue"
},
  "geometry": {"coordinates":[-121.30880999999999,38.636569],"type":"Point"}
}