{
  "type": "Feature",
  "properties": {
    "iso:country":"US",
    "sg:address":"462 W Putnam Ave",
    "sg:city":"Porterville",
    "sg:classifiers":[
        {
            "category":"Health Services",
            "subcategory":"Medical Lab",
            "type":"Services"
        }
    ],
    "sg:phone":"+1 559 782 1065",
    "sg:postcode":"93257",
    "sg:province":"CA",
    "sg:tags":[
        "x",
        "laboratory"
    ],
    "wof:name":"Putnam X-Ray Ctr Inc",
    "wof:placetype":"venue"
},
  "geometry": {"coordinates":[-119.026598,36.069593],"type":"Point"}
}