{
  "type": "Feature",
  "properties": {
    "iso:country":"US",
    "sg:address":"520 N Coast Hwy",
    "sg:city":"Oceanside",
    "sg:classifiers":[
        {
            "category":"Real Estate",
            "subcategory":"Real Estate Services",
            "type":"Services"
        }
    ],
    "sg:phone":"+1 760 421 0108",
    "sg:postcode":"92054",
    "sg:province":"CA",
    "wof:name":"Real Property Network",
    "wof:placetype":"venue"
},
  "geometry": {"coordinates":[-117.38166699999999,33.198731],"type":"Point"}
}