{
  "type": "Feature",
  "properties": {
    "iso:country":"US",
    "sg:address":"607 Evi Ct",
    "sg:city":"Stockton",
    "sg:classifiers":[
        {
            "category":"Manufacturing",
            "subcategory":"Printing",
            "type":"Manufacturing & Wholesale Goods"
        }
    ],
    "sg:phone":"+1 209 234 6565",
    "sg:postcode":"95206",
    "sg:province":"CA",
    "sg:tags":[
        "lithographic",
        "commercial"
    ],
    "wof:name":"Dina Pre Press & Printing",
    "wof:placetype":"venue"
},
  "geometry": {"coordinates":[-121.29258299999999,37.903999],"type":"Point"}
}