{
  "type": "Feature",
  "properties": {
    "addr:full":"8729 Sunland Blvd Sun Valley CA 91352",
    "addr:housenumber":"8729",
    "addr:postcode":"91352",
    "addr:street":"Sunland Blvd",
    "iso:country":"US",
    "sg:address":"8729 Sunland Blvd",
    "sg:city":"Sun Valley",
    "sg:classifiers":[
        {
            "category":"Restaurant",
            "type":"Food & Drink"
        }
    ],
    "sg:phone":"+1 818 504 9154",
    "sg:postcode":"91352",
    "sg:province":"CA",
    "wof:name":"Carnitas Michoacan",
    "wof:placetype":"venue"
},
  "geometry": {"coordinates":[-118.36632400000001,34.228379],"type":"Point"}
}