{
  "type": "Feature",
  "properties": {
    "addr:full":"424 Callan Ave San Leandro CA 94577",
    "addr:housenumber":"424",
    "addr:postcode":"94577",
    "addr:street":"Callan Ave",
    "iso:country":"US",
    "sg:address":"424 Callan Ave",
    "sg:city":"San Leandro",
    "sg:classifiers":[
        {
            "category":"Real Estate",
            "subcategory":"Real Estate Operator",
            "type":"Services"
        }
    ],
    "sg:phone":"+1 510 357 8058",
    "sg:postcode":"94577",
    "sg:province":"CA",
    "sg:tags":[
        "apartment"
    ],
    "wof:name":"Creekside Apartments",
    "wof:placetype":"venue"
},
  "geometry": {"coordinates":[-122.152,37.7271],"type":"Point"}
}