{
  "type": "Feature",
  "properties": {
    "addr:full":"3130 Wilshire Blvd Ste 500 Los Angeles CA 90010",
    "addr:housenumber":"3130",
    "addr:postcode":"90010",
    "addr:street":"Wilshire Blvd Ste 500",
    "iso:country":"US",
    "sg:address":"3130 Wilshire Blvd Ste 500",
    "sg:city":"Los Angeles",
    "sg:classifiers":[
        {
            "category":"Insurance",
            "subcategory":"Health Insurance",
            "type":"Services"
        }
    ],
    "sg:phone":"+1 213 487 1670",
    "sg:postcode":"90010",
    "sg:province":"CA",
    "sg:tags":[
        "market"
    ],
    "wof:name":"Healthy Land Inc",
    "wof:placetype":"venue"
},
  "geometry": {"coordinates":[-118.290001,34.061798],"type":"Point"}
}