{
  "type": "Feature",
  "properties": {
    "iso:country":"US",
    "sg:address":"2156 Newport Boulevard",
    "sg:city":"Costa Mesa",
    "sg:classifiers":[
        {
            "category":"Banks & Credit Unions",
            "subcategory":"Financial Services",
            "type":"Services"
        }
    ],
    "sg:phone":"+1 949 646 1195",
    "sg:postcode":"92627",
    "sg:province":"CA",
    "sg:tags":[
        "broker",
        "mortgage"
    ],
    "wof:name":"Schultz Lynn",
    "wof:placetype":"venue"
},
  "geometry": {"coordinates":[-117.908734,33.650969],"type":"Point"}
}