{
  "type": "Feature",
  "properties": {
    "addr:full":"1177 E Shaw Ave Fresno CA 93710",
    "addr:housenumber":"1177",
    "addr:postcode":"93710",
    "addr:street":"E Shaw Ave",
    "iso:country":"US",
    "sg:address":"1177 E Shaw Ave",
    "sg:city":"Fresno",
    "sg:classifiers":[
        {
            "category":"Professional",
            "subcategory":"Accounting & Tax Preparation",
            "type":"Services"
        }
    ],
    "sg:phone":"+1 559 225 0347",
    "sg:postcode":"93710",
    "sg:province":"CA",
    "sg:tags":[
        "return",
        "filing"
    ],
    "wof:name":"United Tax Svc",
    "wof:placetype":"venue"
},
  "geometry": {"coordinates":[-119.76714699999999,36.8085],"type":"Point"}
}