{
  "type": "Feature",
  "properties": {
    "addr:full":"33 Manor Ave Gustine CA 95322",
    "addr:housenumber":"33",
    "addr:postcode":"95322",
    "addr:street":"Manor Ave",
    "iso:country":"US",
    "sg:address":"33 Manor Ave",
    "sg:city":"Gustine",
    "sg:classifiers":[
        {
            "category":"Freight",
            "type":"Transportation"
        }
    ],
    "sg:phone":"+1 209 854 6585",
    "sg:postcode":"95322",
    "sg:province":"CA",
    "sg:tags":[
        "operator",
        "local",
        "trucking"
    ],
    "wof:name":"Silveira Trucking",
    "wof:placetype":"venue"
},
  "geometry": {"coordinates":[-120.99118300000001,37.250539],"type":"Point"}
}