{
  "type": "Feature",
  "properties": {
    "iso:country":"US",
    "sg:address":"710 N 9th St",
    "sg:city":"San Jose",
    "sg:classifiers":[
        {
            "category":"Wholesale",
            "subcategory":"Auto Parts",
            "type":"Manufacturing & Wholesale Goods"
        }
    ],
    "sg:phone":"+1 408 971 7745",
    "sg:postcode":"95112",
    "sg:province":"CA",
    "sg:tags":[
        "body",
        "automobile",
        "shop"
    ],
    "wof:name":"American Trading Co",
    "wof:placetype":"venue"
},
  "geometry": {"coordinates":[-121.893812,37.355704],"type":"Point"}
}