{
  "type": "Feature",
  "properties": {
    "addr:full":"566 Larkspur St Soledad CA 93960",
    "addr:housenumber":"566",
    "addr:postcode":"93960",
    "addr:street":"Larkspur St",
    "iso:country":"US",
    "sg:address":"566 Larkspur St",
    "sg:city":"Soledad",
    "sg:classifiers":[
        {
            "category":"Banks & Credit Unions",
            "subcategory":"Investment Brokerage",
            "type":"Services"
        }
    ],
    "sg:phone":"+1 831 678 2103",
    "sg:postcode":"93960",
    "sg:province":"CA",
    "sg:tags":[
        "security"
    ],
    "wof:name":"National Franchise Network",
    "wof:placetype":"venue"
},
  "geometry": {"coordinates":[-121.32815100000001,36.435034],"type":"Point"}
}