{
  "type": "Feature",
  "properties": {
    "addr:full":"1914 14th St Santa Monica CA 90404",
    "addr:housenumber":"1914",
    "addr:postcode":"90404",
    "addr:street":"14Th St",
    "iso:country":"US",
    "sg:address":"1914 14th St",
    "sg:city":"Santa Monica",
    "sg:classifiers":[
        {
            "category":"Wholesale",
            "subcategory":"Groceries",
            "type":"Manufacturing & Wholesale Goods"
        }
    ],
    "sg:phone":"+1 310 450 1464",
    "sg:postcode":"90404",
    "sg:province":"CA",
    "sg:tags":[
        "grocer"
    ],
    "wof:name":"Giancola Brothers Inc",
    "wof:placetype":"venue"
},
  "geometry": {"coordinates":[-118.47701499999999,34.016629],"type":"Point"}
}