{
  "type": "Feature",
  "properties": {
    "addr:full":"334 Mason St San Francisco CA 94102",
    "addr:housenumber":"334",
    "addr:postcode":"94102",
    "addr:street":"Mason St",
    "iso:country":"US",
    "sg:address":"334 Mason St",
    "sg:city":"San Francisco",
    "sg:classifiers":[
        {
            "category":"Tea Room",
            "subcategory":"None",
            "type":"Food & Drink"
        },
        {
            "category":"Travel",
            "subcategory":"Hotels & Motels",
            "type":"Entertainment"
        }
    ],
    "sg:phone":"+1 415 781 5050",
    "sg:postcode":"94102",
    "sg:province":"CA",
    "sg:website":"www.kinggeorge.com",
    "wof:name":"King George Hotel",
    "wof:placetype":"venue"
},
  "geometry": {"coordinates":[-122.409811,37.786779],"type":"Point"}
}