{
  "type": "Feature",
  "properties": {
    "addr:full":"1610 E 1st St Santa Ana CA 92701",
    "addr:housenumber":"1610",
    "addr:postcode":"92701",
    "addr:street":"E 1St St",
    "iso:country":"US",
    "sg:address":"1610 E 1st St",
    "sg:city":"Santa Ana",
    "sg:classifiers":[
        {
            "category":"Retail",
            "subcategory":"Funeral Services",
            "type":"Services"
        }
    ],
    "sg:phone":"+1 714 543 9351",
    "sg:postcode":"92701",
    "sg:province":"CA",
    "sg:tags":[
        "cemetery"
    ],
    "wof:name":"MacDougall Family Mortuary",
    "wof:placetype":"venue"
},
  "geometry": {"coordinates":[-117.846001,33.7453],"type":"Point"}
}