{
  "type": "Feature",
  "properties": {
    "iso:country":"US",
    "sg:address":"105 Chalet Woods Cir",
    "sg:city":"Campbell",
    "sg:classifiers":[
        {
            "category":"Building & Trades",
            "subcategory":"Construction",
            "type":"Services"
        }
    ],
    "sg:phone":"+1 408 583 0556",
    "sg:postcode":"95008",
    "sg:province":"CA",
    "sg:tags":[
        "general",
        "contractor"
    ],
    "wof:name":"Saarman Construction LTD",
    "wof:placetype":"venue"
},
  "geometry": {"coordinates":[-121.934991,37.281885],"type":"Point"}
}