{
  "type": "Feature",
  "properties": {
    "iso:country":"US",
    "sg:address":"1315 23rd Ave",
    "sg:city":"San Francisco",
    "sg:classifiers":[
        {
            "category":"Insurance",
            "subcategory":"Insurance Agent",
            "type":"Services"
        }
    ],
    "sg:phone":"+1 415 665 5118",
    "sg:postcode":"94122",
    "sg:province":"CA",
    "wof:name":"State Farm Insurance",
    "wof:placetype":"venue"
},
  "geometry": {"coordinates":[-122.481368,37.761773],"type":"Point"}
}