{
  "type": "Feature",
  "properties": {
    "iso:country":"US",
    "sg:address":"4009 Pestana Pl",
    "sg:city":"Fremont",
    "sg:classifiers":[
        {
            "category":"Wholesale",
            "subcategory":"Electrical",
            "type":"Manufacturing & Wholesale Goods"
        }
    ],
    "sg:phone":"+1 510 252 9900",
    "sg:postcode":"94538",
    "sg:province":"CA",
    "sg:tags":[
        "control"
    ],
    "wof:name":"Control Process Apparatus",
    "wof:placetype":"venue"
},
  "geometry": {"coordinates":[-121.949333,37.504301],"type":"Point"}
}