{
  "type": "Feature",
  "properties": {
    "iso:country":"US",
    "sg:address":"159 Kentucky St",
    "sg:city":"Petaluma",
    "sg:classifiers":[
        {
            "category":"Health Services",
            "subcategory":"Health Practitioner",
            "type":"Services"
        }
    ],
    "sg:phone":"+1 707 763 4679",
    "sg:postcode":"94952",
    "sg:province":"CA",
    "sg:tags":[
        "psychotherapist"
    ],
    "wof:name":"Rhonda Gerhard",
    "wof:placetype":"venue"
},
  "geometry": {"coordinates":[-122.641682,38.234725],"type":"Point"}
}