{
  "type": "Feature",
  "properties": {
    "iso:country":"US",
    "sg:address":"1711 N Victory Pl",
    "sg:city":"Burbank",
    "sg:classifiers":[
        {
            "category":"Coffee & Tea",
            "type":"Food & Drink"
        }
    ],
    "sg:phone":"+1 818 843 3979",
    "sg:postcode":"91502",
    "sg:province":"CA",
    "sg:website":"www.starbucks.com",
    "wof:name":"Starbucks",
    "wof:placetype":"venue"
},
  "geometry": {"coordinates":[-118.328446,34.191411],"type":"Point"}
}