{
  "type": "Feature",
  "properties": {
    "iso:country":"US",
    "sg:address":"4413 N Crystal Ave",
    "sg:city":"Fresno",
    "sg:classifiers":[
        {
            "category":"Building & Trades",
            "subcategory":"Construction",
            "type":"Services"
        }
    ],
    "sg:phone":"+1 559 228 0979",
    "sg:postcode":"93705",
    "sg:province":"CA",
    "sg:tags":[
        "roofing",
        "contractor"
    ],
    "wof:name":"All Weather Roofing",
    "wof:placetype":"venue"
},
  "geometry": {"coordinates":[-119.83151599999999,36.7967],"type":"Point"}
}