{
  "type": "Feature",
  "properties": {
    "addr:full":"4200 Stine Rd Bakersfield CA 93313",
    "addr:housenumber":"4200",
    "addr:postcode":"93313",
    "addr:street":"Stine Rd",
    "iso:country":"US",
    "sg:address":"4200 Stine Rd",
    "sg:city":"Bakersfield",
    "sg:classifiers":[
        {
            "category":"Personal",
            "subcategory":"Nail Salon",
            "type":"Services"
        }
    ],
    "sg:phone":"+1 661 831 7751",
    "sg:postcode":"93313",
    "sg:province":"CA",
    "wof:name":"Nails Spa Time",
    "wof:placetype":"venue"
},
  "geometry": {"coordinates":[-119.05658699999999,35.317026],"type":"Point"}
}