{
  "type": "Feature",
  "properties": {
    "iso:country":"US",
    "sg:address":"780 Arlington St",
    "sg:city":"Cambria",
    "sg:classifiers":[
        {
            "category":"Personal",
            "subcategory":"Beauty Salon",
            "type":"Services"
        },
        {
            "category":"Personal",
            "subcategory":"Nail Salon",
            "type":"Services"
        }
    ],
    "sg:phone":"+1 805 927 3301",
    "sg:postcode":"93428",
    "sg:province":"CA",
    "sg:tags":[
        "hair",
        "makeup",
        "artist"
    ],
    "sg:website":"Pacifichaircambria.com",
    "wof:name":"Pacific Hair",
    "wof:placetype":"venue"
},
  "geometry": {"coordinates":[-121.099998,35.5676],"type":"Point"}
}