{
  "type": "Feature",
  "properties": {
    "iso:country":"US",
    "sg:address":"8764 Holloway Dr",
    "sg:city":"West Hollywood",
    "sg:classifiers":[
        {
            "category":"Arts & Performance",
            "subcategory":"Theater",
            "type":"Entertainment"
        }
    ],
    "sg:phone":"+1 818 783 7940",
    "sg:postcode":"90069",
    "sg:province":"CA",
    "sg:tags":[
        "talent",
        "agency",
        "casting"
    ],
    "wof:name":"Bernard Feldman Management",
    "wof:placetype":"venue"
},
  "geometry": {"coordinates":[-118.38217899999999,34.090506],"type":"Point"}
}