{
  "type": "Feature",
  "properties": {
    "addr:full":"5342 Bancroft Ave Oakland CA 94601",
    "addr:housenumber":"5342",
    "addr:postcode":"94601",
    "addr:street":"Bancroft Ave",
    "iso:country":"US",
    "sg:address":"5342 Bancroft Ave",
    "sg:city":"Oakland",
    "sg:classifiers":[
        {
            "category":"Retail",
            "subcategory":"Auto Repair",
            "type":"Services"
        }
    ],
    "sg:phone":"+1 510 436 5423",
    "sg:postcode":"94601",
    "sg:province":"CA",
    "sg:tags":[
        "repairing",
        "automobile"
    ],
    "wof:name":"Bancroft Complete Auto Repair",
    "wof:placetype":"venue"
},
  "geometry": {"coordinates":[-122.202003,37.771702],"type":"Point"}
}