{
  "type": "Feature",
  "properties": {
    "iso:country":"US",
    "sg:address":"38675 Rancho Los Cerritos Dr",
    "sg:city":"Indio",
    "sg:classifiers":[
        {
            "category":"Building & Trades",
            "subcategory":"Landscaping Services",
            "type":"Services"
        }
    ],
    "sg:phone":"+1 760 360 8678",
    "sg:postcode":"92203",
    "sg:province":"CA",
    "sg:tags":[
        "landscape",
        "contractor"
    ],
    "wof:name":"Desert Pride Landscape Maint",
    "wof:placetype":"venue"
},
  "geometry": {"coordinates":[-116.283177,33.768296],"type":"Point"}
}