{
  "type": "Feature",
  "properties": {
    "iso:country":"US",
    "sg:address":"807 N Ventura Ave",
    "sg:city":"Ventura",
    "sg:classifiers":[
        {
            "category":"Shopping",
            "subcategory":"Shoes",
            "type":"Retail Goods"
        }
    ],
    "sg:phone":"+1 805 643 7380",
    "sg:postcode":"93001",
    "sg:province":"CA",
    "wof:name":"Julie's Shoes & Fashion",
    "wof:placetype":"venue"
},
  "geometry": {"coordinates":[-119.29794800000001,34.291019],"type":"Point"}
}