{
  "type": "Feature",
  "properties": {
    "iso:country":"US",
    "sg:address":"40575 California Oaks Rd",
    "sg:city":"Murrieta",
    "sg:classifiers":[
        {
            "category":"Restaurant",
            "type":"Food & Drink"
        }
    ],
    "sg:phone":"+1 951 698 4410",
    "sg:postcode":"92562",
    "sg:province":"CA",
    "wof:name":"Sombrero Mexican Food",
    "wof:placetype":"venue"
},
  "geometry": {"coordinates":[-117.201374,33.575376],"type":"Point"}
}