{
  "type": "Feature",
  "properties": {
    "iso:country":"US",
    "sg:address":"820 N Phillips Ave",
    "sg:city":"West Covina",
    "sg:classifiers":[
        {
            "category":"Health Services",
            "subcategory":"Nursing And Care Facility",
            "type":"Services"
        }
    ],
    "sg:phone":"+1 626 859 2266",
    "sg:postcode":"91791",
    "sg:province":"CA",
    "sg:tags":[
        "hospice"
    ],
    "sg:website":"www.cvhp.org",
    "wof:name":"Citrus Valley Hospice",
    "wof:placetype":"venue"
},
  "geometry": {"coordinates":[-117.905507,34.085136],"type":"Point"}
}