{
  "type": "Feature",
  "properties": {
    "addr:full":"10813 Shellabarger Rd Bakersfield CA 93312",
    "addr:housenumber":"10813",
    "addr:postcode":"93312",
    "addr:street":"Shellabarger Rd",
    "iso:country":"US",
    "sg:address":"10813 Shellabarger Rd",
    "sg:city":"Bakersfield",
    "sg:classifiers":[
        {
            "category":"Building & Trades",
            "subcategory":"Construction",
            "type":"Services"
        }
    ],
    "sg:phone":"+1 661 587 6772",
    "sg:postcode":"93312",
    "sg:province":"CA",
    "sg:tags":[
        "roofing",
        "contractor"
    ],
    "wof:name":"Ken's Roofing",
    "wof:placetype":"venue"
},
  "geometry": {"coordinates":[-119.121623,35.372459],"type":"Point"}
}