{
  "type": "Feature",
  "properties": {
    "iso:country":"US",
    "sg:address":"2816 Ostrom Rd",
    "sg:city":"Marysville",
    "sg:classifiers":[
        {
            "category":"Freight",
            "type":"Transportation"
        }
    ],
    "sg:phone":"+1 530 742 5300",
    "sg:postcode":"95962",
    "sg:province":"CA",
    "sg:tags":[
        "trucking"
    ],
    "wof:name":"A-1 Construction Equipment Svc",
    "wof:placetype":"venue"
},
  "geometry": {"coordinates":[-121.511906,39.069361],"type":"Point"}
}