{
  "type": "Feature",
  "properties": {
    "addr:full":"21310 San Ramon Valley Blvd San Ramon CA 94583",
    "addr:housenumber":"21310",
    "addr:postcode":"94583",
    "addr:street":"San Ramon Valley Blvd",
    "iso:country":"US",
    "sg:address":"21310 San Ramon Valley Blvd",
    "sg:city":"San Ramon",
    "sg:classifiers":[
        {
            "category":"Health Services",
            "subcategory":"Doctor",
            "type":"Services"
        }
    ],
    "sg:phone":"+1 925 828 0824",
    "sg:postcode":"94583",
    "sg:province":"CA",
    "sg:tags":[
        "dentist"
    ],
    "wof:name":"Gental Dentistry For Kids Only",
    "wof:placetype":"venue"
},
  "geometry": {"coordinates":[-121.943676,37.727124],"type":"Point"}
}