{
  "type": "Feature",
  "properties": {
    "iso:country":"US",
    "sg:address":"516 E Chapman Ave",
    "sg:city":"Orange",
    "sg:classifiers":[
        {
            "category":"Health Services",
            "subcategory":"Chiropractor",
            "type":"Services"
        }
    ],
    "sg:phone":"+1 714 633 1648",
    "sg:postcode":"92866",
    "sg:province":"CA",
    "sg:website":"www.lpchiro.com/",
    "wof:name":"Lundquist & Patterson Chiropractic Center",
    "wof:placetype":"venue"
},
  "geometry": {"coordinates":[-117.848,33.7878],"type":"Point"}
}