{
  "type": "Feature",
  "properties": {
    "iso:country":"US",
    "sg:address":"4146 Mount Alifan Pl",
    "sg:city":"San Diego",
    "sg:classifiers":[
        {
            "category":"Shopping",
            "subcategory":"Clothing, Apparel, & Fashions",
            "type":"Retail Goods"
        }
    ],
    "sg:phone":"+1 858 292 6083",
    "sg:postcode":"92111",
    "sg:province":"CA",
    "sg:tags":[
        "theatrical",
        "costume"
    ],
    "wof:name":"MLH",
    "wof:placetype":"venue"
},
  "geometry": {"coordinates":[-117.179117,32.817143],"type":"Point"}
}