{
  "type": "Feature",
  "properties": {
    "addr:full":"839 Walnut Ln Winters CA 95694",
    "addr:housenumber":"839",
    "addr:postcode":"95694",
    "addr:street":"Walnut Ln",
    "iso:country":"US",
    "sg:address":"839 Walnut Ln",
    "sg:city":"Winters",
    "sg:classifiers":[
        {
            "category":"Professional",
            "type":"Services"
        }
    ],
    "sg:phone":"+1 530 795 2309",
    "sg:postcode":"95694",
    "sg:province":"CA",
    "wof:name":"Richard Atherton",
    "wof:placetype":"venue"
},
  "geometry": {"coordinates":[-121.96737299999999,38.529495],"type":"Point"}
}