{
  "type": "Feature",
  "properties": {
    "addr:full":"388 Market St San Francisco CA 94111",
    "addr:housenumber":"388",
    "addr:postcode":"94111",
    "addr:street":"Market St",
    "iso:country":"US",
    "sg:address":"388 Market St",
    "sg:city":"San Francisco",
    "sg:classifiers":[
        {
            "category":"Restaurant",
            "type":"Food & Drink"
        }
    ],
    "sg:menulink":"http://www.allmenus.com/ca/san-francisco/56950-subway/menu/",
    "sg:phone":"+1 415 391 2824",
    "sg:postcode":"94111",
    "sg:province":"CA",
    "sg:tags":[
        "american",
        "sandwich"
    ],
    "wof:name":"Subway",
    "wof:placetype":"venue"
},
  "geometry": {"coordinates":[-122.398207,37.79186],"type":"Point"}
}