{
  "type": "Feature",
  "properties": {
    "addr:full":"5624 N Blackstone Ave Fresno CA 93710",
    "addr:housenumber":"5624",
    "addr:postcode":"93710",
    "addr:street":"N Blackstone Ave",
    "iso:country":"US",
    "sg:address":"5624 N Blackstone Ave",
    "sg:city":"Fresno",
    "sg:classifiers":[
        {
            "category":"Education",
            "subcategory":"Special Training",
            "type":"Public Place"
        }
    ],
    "sg:phone":"+1 559 261 2525",
    "sg:postcode":"93710",
    "sg:province":"CA",
    "sg:tags":[
        "proficiency",
        "test",
        "driving"
    ],
    "wof:name":"Drive America Driving Schools",
    "wof:placetype":"venue"
},
  "geometry": {"coordinates":[-119.790278,36.822454],"type":"Point"}
}