{
  "type": "Feature",
  "properties": {
    "iso:country":"US",
    "sg:address":"244 Pleasant Ave",
    "sg:city":"Santa Rosa",
    "sg:classifiers":[
        {
            "category":"Shopping",
            "subcategory":"Computers & Home Electronics",
            "type":"Retail Goods"
        }
    ],
    "sg:phone":"+1 707 838 9736",
    "sg:postcode":"95403",
    "sg:province":"CA",
    "wof:name":"Video Tronix",
    "wof:placetype":"venue"
},
  "geometry": {"coordinates":[-122.78456,38.540257],"type":"Point"}
}