{
  "type": "Feature",
  "properties": {
    "addr:full":"2044 Concourse Dr San Jose CA 95131",
    "addr:housenumber":"2044",
    "addr:postcode":"95131",
    "addr:street":"Concourse Dr",
    "iso:country":"US",
    "sg:address":"2044 Concourse Dr",
    "sg:city":"San Jose",
    "sg:classifiers":[
        {
            "category":"Professional",
            "type":"Services"
        }
    ],
    "sg:phone":"+1 408 432 0324",
    "sg:postcode":"95131",
    "sg:province":"CA",
    "sg:tags":[
        "establishment"
    ],
    "wof:name":"Concourse Partners",
    "wof:placetype":"venue"
},
  "geometry": {"coordinates":[-121.895869,37.39673],"type":"Point"}
}