{
  "type": "Feature",
  "properties": {
    "iso:country":"US",
    "sg:address":"2249 Las Posas Rd",
    "sg:city":"Camarillo",
    "sg:classifiers":[
        {
            "category":"Personal",
            "subcategory":"Beauty Salon",
            "type":"Services"
        }
    ],
    "sg:phone":"+1 805 482 4520",
    "sg:postcode":"93010",
    "sg:province":"CA",
    "sg:tags":[
        "nail",
        "manicuring"
    ],
    "wof:name":"Melay Nails",
    "wof:placetype":"venue"
},
  "geometry": {"coordinates":[-119.041,34.236401],"type":"Point"}
}