{
  "type": "Feature",
  "properties": {
    "addr:full":"1793 Union St San Francisco CA 94123",
    "addr:housenumber":"1793",
    "addr:postcode":"94123",
    "addr:street":"Union St",
    "iso:country":"US",
    "sg:address":"1793 Union St",
    "sg:city":"San Francisco",
    "sg:classifiers":[
        {
            "category":"Utilities",
            "subcategory":"Telephone",
            "type":"Services"
        }
    ],
    "sg:phone":"+1 415 346 5950",
    "sg:postcode":"94123",
    "sg:province":"CA",
    "sg:tags":[
        "marketing",
        "internet"
    ],
    "wof:name":"Webloyaltycom Inc",
    "wof:placetype":"venue"
},
  "geometry": {"coordinates":[-122.427682,37.798047],"type":"Point"}
}