{
  "type": "Feature",
  "properties": {
    "addr:full":"1461 Railroad St Corona CA 92882",
    "addr:housenumber":"1461",
    "addr:postcode":"92882",
    "addr:street":"Railroad St",
    "iso:country":"US",
    "sg:address":"1461 Railroad St",
    "sg:city":"Corona",
    "sg:classifiers":[
        {
            "category":"Manufacturing",
            "subcategory":"Wood Products",
            "type":"Manufacturing & Wholesale Goods"
        },
        {
            "category":"Manufacturing",
            "subcategory":"Paper Products",
            "type":"Manufacturing & Wholesale Goods"
        }
    ],
    "sg:phone":"+1 951 278 2100",
    "sg:postcode":"92882",
    "sg:province":"CA",
    "sg:tags":[
        "boxes-corrugated",
        "fiber",
        "boxes-folding-manufacturers"
    ],
    "wof:name":"Thoro-Packaging Inc",
    "wof:placetype":"venue"
},
  "geometry": {"coordinates":[-117.58273699999999,33.887781],"type":"Point"}
}