{
  "type": "Feature",
  "properties": {
    "iso:country":"US",
    "sg:address":"6701 32nd St",
    "sg:city":"North Highlands",
    "sg:classifiers":[
        {
            "category":"Manufacturing",
            "subcategory":"Lumber",
            "type":"Manufacturing & Wholesale Goods"
        }
    ],
    "sg:phone":"+1 916 332 8733",
    "sg:postcode":"95660",
    "sg:province":"CA",
    "sg:tags":[
        "a",
        "as",
        "logger",
        "operates"
    ],
    "wof:name":"Forrest Tree Service",
    "wof:placetype":"venue"
},
  "geometry": {"coordinates":[-121.392115,38.691953],"type":"Point"}
}