{
  "type": "Feature",
  "properties": {
    "iso:country":"US",
    "sg:address":"800 Jones St",
    "sg:city":"Berkeley",
    "sg:classifiers":[
        {
            "category":"Organizations",
            "subcategory":"Non-profit Organization",
            "type":"Services"
        }
    ],
    "sg:phone":"+1 510 525 5272",
    "sg:postcode":"94710",
    "sg:province":"CA",
    "wof:name":"Berkeley Community Fund",
    "wof:placetype":"venue"
},
  "geometry": {"coordinates":[-122.300066,37.875229],"type":"Point"}
}