{
  "type": "Feature",
  "properties": {
    "addr:full":"2307 Wayne Ave Los Angeles CA 90027",
    "addr:housenumber":"2307",
    "addr:postcode":"90027",
    "addr:street":"Wayne Ave",
    "iso:country":"US",
    "sg:address":"2307 Wayne Ave",
    "sg:city":"Los Angeles",
    "sg:classifiers":[
        {
            "category":"Manufacturing",
            "subcategory":"Glass & Minerals",
            "type":"Manufacturing & Wholesale Goods"
        }
    ],
    "sg:phone":"+1 323 664 9922",
    "sg:postcode":"90027",
    "sg:province":"CA",
    "sg:tags":[
        "product",
        "mfg"
    ],
    "wof:name":"Alejandres Creative Artistry",
    "wof:placetype":"venue"
},
  "geometry": {"coordinates":[-118.28127000000001,34.114084],"type":"Point"}
}