{
  "type": "Feature",
  "properties": {
    "addr:full":"218 S Diamond Bar Blvd Diamond Bar CA 91765",
    "addr:housenumber":"218",
    "addr:postcode":"91765",
    "addr:street":"S Diamond Bar Blvd",
    "iso:country":"US",
    "sg:address":"218 S Diamond Bar Blvd",
    "sg:city":"Diamond Bar",
    "sg:classifiers":[
        {
            "category":"Restaurant",
            "type":"Food & Drink"
        }
    ],
    "sg:phone":"+1 909 860 1671",
    "sg:postcode":"91765",
    "sg:province":"CA",
    "wof:name":"Taco Bell",
    "wof:placetype":"venue"
},
  "geometry": {"coordinates":[-117.81051600000001,34.0219],"type":"Point"}
}