{
  "type": "Feature",
  "properties": {
    "addr:full":"25336 Mission Blvd Hayward CA 94544",
    "addr:housenumber":"25336",
    "addr:postcode":"94544",
    "addr:street":"Mission Blvd",
    "iso:country":"US",
    "sg:address":"25336 Mission Blvd",
    "sg:city":"Hayward",
    "sg:classifiers":[
        {
            "category":"Retail",
            "subcategory":"Auto Repair",
            "type":"Services"
        }
    ],
    "sg:phone":"+1 510 727 0976",
    "sg:postcode":"94544",
    "sg:province":"CA",
    "sg:tags":[
        "detailing"
    ],
    "sg:website":"www.sunshineautodetailing.com",
    "wof:name":"Sunshine Auto Detailing",
    "wof:placetype":"venue"
},
  "geometry": {"coordinates":[-122.07078799999999,37.656611],"type":"Point"}
}