{
  "type": "Feature",
  "properties": {
    "addr:full":"1440 Broadway Ste 701 Oakland CA 94612",
    "addr:housenumber":"1440",
    "addr:postcode":"94612",
    "addr:street":"Broadway Ste 701",
    "iso:country":"US",
    "sg:address":"1440 Broadway Ste 701",
    "sg:city":"Oakland",
    "sg:classifiers":[
        {
            "category":"Organizations",
            "subcategory":"Non-profit Organization",
            "type":"Services"
        }
    ],
    "sg:phone":"+1 510 302 0430",
    "sg:postcode":"94612",
    "sg:province":"CA",
    "sg:tags":[
        "service/non-profit",
        "community"
    ],
    "sg:website":"www.cbecal.org",
    "wof:name":"Communities for a Better Environment",
    "wof:placetype":"venue"
},
  "geometry": {"coordinates":[-122.270594,37.804698],"type":"Point"}
}