{
  "type": "Feature",
  "properties": {
    "addr:full":"7959 Mason Ave Winnetka CA 91306",
    "addr:housenumber":"7959",
    "addr:postcode":"91306",
    "addr:street":"Mason Ave",
    "iso:country":"US",
    "sg:address":"7959 Mason Ave",
    "sg:city":"Winnetka",
    "sg:classifiers":[
        {
            "category":"Building & Trades",
            "subcategory":"Construction",
            "type":"Services"
        }
    ],
    "sg:phone":"+1 818 998 6023",
    "sg:postcode":"91306",
    "sg:province":"CA",
    "sg:tags":[
        "contractor"
    ],
    "wof:name":"Sandobal Plastering",
    "wof:placetype":"venue"
},
  "geometry": {"coordinates":[-118.579835,34.215033],"type":"Point"}
}