{
  "type": "Feature",
  "properties": {
    "addr:full":"7500 Katella Ave Stanton CA 90680",
    "addr:housenumber":"7500",
    "addr:postcode":"ca 90680",
    "addr:street":"Katella Ave",
    "iso:country":"US",
    "sg:address":"7500 Katella Ave",
    "sg:city":"Stanton",
    "sg:classifiers":[
        {
            "category":"Restaurant",
            "type":"Food & Drink"
        }
    ],
    "sg:phone":"+1 714 901 6389",
    "sg:postcode":"90680",
    "sg:province":"CA",
    "sg:tags":[
        "asian",
        "pan",
        "japanese"
    ],
    "wof:name":"Mr Teriyaki",
    "wof:placetype":"venue"
},
  "geometry": {"coordinates":[-118.001561,33.802454],"type":"Point"}
}