{
  "type": "Feature",
  "properties": {
    "addr:full":"2500 Mason St San Francisco CA 94133",
    "addr:housenumber":"2500",
    "addr:postcode":"94133",
    "addr:street":"Mason St",
    "iso:country":"US",
    "sg:address":"2500 Mason St",
    "sg:city":"San Francisco",
    "sg:classifiers":[
        {
            "category":"Shopping",
            "subcategory":"Gifts & Souvenirs",
            "type":"Retail Goods"
        }
    ],
    "sg:phone":"+1 415 982 4234",
    "sg:postcode":"94133",
    "sg:province":"CA",
    "sg:tags":[
        "shop"
    ],
    "wof:name":"W H Smith",
    "wof:placetype":"venue"
},
  "geometry": {"coordinates":[-122.41397499999999,37.807483],"type":"Point"}
}