{
  "type": "Feature",
  "properties": {
    "addr:full":"732 Durshire Way Sunnyvale CA 94087",
    "addr:housenumber":"732",
    "addr:postcode":"94087",
    "addr:street":"Durshire Way",
    "iso:country":"US",
    "sg:address":"732 Durshire Way",
    "sg:city":"Sunnyvale",
    "sg:classifiers":[
        {
            "category":"Shopping",
            "type":"Retail Goods"
        }
    ],
    "sg:phone":"+1 408 749 9318",
    "sg:postcode":"94087",
    "sg:province":"CA",
    "sg:tags":[
        "merchandise"
    ],
    "wof:name":"Technology Bridge",
    "wof:placetype":"venue"
},
  "geometry": {"coordinates":[-122.020661,37.34382],"type":"Point"}
}