{
  "type": "Feature",
  "properties": {
    "iso:country":"US",
    "sg:address":"1701 Novato Blvd Ste 304",
    "sg:city":"Novato",
    "sg:classifiers":[
        {
            "category":"Professional",
            "subcategory":"Lawyer & Legal Services",
            "type":"Services"
        }
    ],
    "sg:phone":"+1 415 898 5958",
    "sg:postcode":"94947",
    "sg:province":"CA",
    "sg:tags":[
        "plan"
    ],
    "wof:name":"Pollak & Cusack",
    "wof:placetype":"venue"
},
  "geometry": {"coordinates":[-122.578979,38.106258],"type":"Point"}
}