{
  "type": "Feature",
  "properties": {
    "iso:country":"US",
    "sg:address":"4100 Baldwin Park Blvd",
    "sg:city":"Baldwin Park",
    "sg:classifiers":[
        {
            "category":"Social Services",
            "type":"Services"
        }
    ],
    "sg:phone":"+1 626 813 0102",
    "sg:postcode":"91706",
    "sg:province":"CA",
    "sg:tags":[
        "organization",
        "welfare"
    ],
    "wof:name":"YWCA",
    "wof:placetype":"venue"
},
  "geometry": {"coordinates":[-117.964833,34.087522],"type":"Point"}
}