{
  "type": "Feature",
  "properties": {
    "iso:country":"US",
    "sg:address":"6171 Mission Gorge Rd Ste 103",
    "sg:city":"San Diego",
    "sg:classifiers":[
        {
            "category":"Restaurant",
            "type":"Food & Drink"
        }
    ],
    "sg:phone":"+1 619 280 8551",
    "sg:postcode":"92120",
    "sg:province":"CA",
    "sg:tags":[
        "sushi",
        "bar",
        "japanese"
    ],
    "wof:name":"Toro Sushi",
    "wof:placetype":"venue"
},
  "geometry": {"coordinates":[-117.097737,32.78691],"type":"Point"}
}