{
  "type": "Feature",
  "properties": {
    "iso:country":"US",
    "sg:address":"320 S Euclid St",
    "sg:city":"Anaheim",
    "sg:classifiers":[
        {
            "category":"Shopping",
            "subcategory":"Florist",
            "type":"Retail Goods"
        }
    ],
    "sg:phone":"+1 714 772 9254",
    "sg:postcode":"92802",
    "sg:province":"CA",
    "wof:name":"Designs by Marina",
    "wof:placetype":"venue"
},
  "geometry": {"coordinates":[-117.942001,33.8283],"type":"Point"}
}