{
  "type": "Feature",
  "properties": {
    "iso:country":"US",
    "sg:address":"1204 Smith Avenue",
    "sg:city":"Campbell",
    "sg:classifiers":[
        {
            "category":"Building & Trades",
            "subcategory":"Pest Control",
            "type":"Services"
        }
    ],
    "sg:phone":"+1 408 377 2505",
    "sg:postcode":"95008",
    "sg:province":"CA",
    "wof:name":"Termite Busters",
    "wof:placetype":"venue"
},
  "geometry": {"coordinates":[-121.969227,37.274167],"type":"Point"}
}