{
  "type": "Feature",
  "properties": {
    "iso:country":"US",
    "sg:address":"1030 E el Camino Real",
    "sg:city":"Sunnyvale",
    "sg:classifiers":[
        {
            "category":"Building & Trades",
            "subcategory":"Construction",
            "type":"Services"
        }
    ],
    "sg:phone":"+1 408 244 8584",
    "sg:postcode":"94087",
    "sg:province":"CA",
    "sg:tags":[
        "ceiling"
    ],
    "wof:name":"Gabino's Interiors",
    "wof:placetype":"venue"
},
  "geometry": {"coordinates":[-122.007589,37.352031],"type":"Point"}
}