{
  "type": "Feature",
  "properties": {
    "addr:full":"17127 Pioneer Blvd Artesia CA 90701",
    "addr:housenumber":"17127",
    "addr:postcode":"90701",
    "addr:street":"Pioneer Blvd",
    "iso:country":"US",
    "sg:address":"17127 Pioneer Blvd",
    "sg:city":"Artesia",
    "sg:classifiers":[
        {
            "category":"Real Estate",
            "subcategory":"Real Estate Agent",
            "type":"Services"
        }
    ],
    "sg:phone":"+1 562 860 4211",
    "sg:postcode":"90701",
    "sg:province":"CA",
    "wof:name":"Empire Properties Realtors",
    "wof:placetype":"venue"
},
  "geometry": {"coordinates":[-118.08237800000001,33.87626],"type":"Point"}
}