{
  "type": "Feature",
  "properties": {
    "iso:country":"US",
    "sg:address":"1492 N Main St",
    "sg:city":"Salinas",
    "sg:classifiers":[
        {
            "category":"Banks & Credit Unions",
            "subcategory":"Bank",
            "type":"Services"
        }
    ],
    "sg:phone":"+1 831 449 7294",
    "sg:postcode":"93906",
    "sg:province":"CA",
    "sg:tags":[
        "loan"
    ],
    "wof:name":"Beneficial California Inc",
    "wof:placetype":"venue"
},
  "geometry": {"coordinates":[-121.653333,36.70688],"type":"Point"}
}