{
  "type": "Feature",
  "properties": {
    "iso:country":"US",
    "sg:address":"3678 N Freeway Blvd",
    "sg:city":"Sacramento",
    "sg:classifiers":[
        {
            "category":"Food & Beverages",
            "subcategory":"Liquor & Beverages",
            "type":"Retail Goods"
        }
    ],
    "sg:phone":"+1 916 419 6808",
    "sg:postcode":"95834",
    "sg:province":"CA",
    "sg:tags":[
        "beer",
        "spirit",
        "wine"
    ],
    "sg:website":"www.bevmo.com",
    "wof:name":"BevMo",
    "wof:placetype":"venue"
},
  "geometry": {"coordinates":[-121.49677200000001,38.639043],"type":"Point"}
}