{
  "type": "Feature",
  "properties": {
    "iso:country":"US",
    "sg:address":"3530 W Adams Blvd",
    "sg:city":"Los Angeles",
    "sg:classifiers":[
        {
            "category":"Food & Beverages",
            "subcategory":"Specialty",
            "type":"Retail Goods"
        }
    ],
    "sg:phone":"+1 323 733 4260",
    "sg:postcode":"90018",
    "sg:province":"CA",
    "sg:tags":[
        "vitamin"
    ],
    "wof:name":"Point Of Sales Inc",
    "wof:placetype":"venue"
},
  "geometry": {"coordinates":[-118.322873,34.032548],"type":"Point"}
}