{
  "type": "Feature",
  "properties": {
    "addr:full":"2012 Abalone Ave Torrance CA 90501",
    "addr:housenumber":"2012",
    "addr:postcode":"90501",
    "addr:street":"Abalone Ave",
    "iso:country":"US",
    "sg:address":"2012 Abalone Ave",
    "sg:city":"Torrance",
    "sg:classifiers":[
        {
            "category":"Utilities",
            "subcategory":"Cable",
            "type":"Services"
        }
    ],
    "sg:phone":"+1 310 782 9043",
    "sg:postcode":"90501",
    "sg:province":"CA",
    "sg:tags":[
        "television"
    ],
    "wof:name":"Dish Network",
    "wof:placetype":"venue"
},
  "geometry": {"coordinates":[-118.31160300000001,33.827322],"type":"Point"}
}