{
  "type": "Feature",
  "properties": {
    "addr:full":"5361 Laverne Cir Westminster CA 92683",
    "addr:housenumber":"5361",
    "addr:postcode":"92683",
    "addr:street":"Laverne Cir",
    "iso:country":"US",
    "sg:address":"5361 Laverne Cir",
    "sg:city":"Westminster",
    "sg:classifiers":[
        {
            "category":"Building & Trades",
            "subcategory":"Equipment Rental",
            "type":"Services"
        }
    ],
    "sg:phone":"+1 714 892 7099",
    "sg:postcode":"92683",
    "sg:province":"CA",
    "sg:tags":[
        "leasing"
    ],
    "wof:name":"Getting You There Cheap",
    "wof:placetype":"venue"
},
  "geometry": {"coordinates":[-118.03498,33.768473],"type":"Point"}
}