{
  "type": "Feature",
  "properties": {
    "addr:full":"465 N Roxbury Dr Beverly Hills CA 90210",
    "addr:housenumber":"465",
    "addr:postcode":"90210",
    "addr:street":"N Roxbury Dr",
    "iso:country":"US",
    "sg:address":"465 N Roxbury Dr",
    "sg:city":"Beverly Hills",
    "sg:classifiers":[
        {
            "category":"Health Services",
            "subcategory":"Medical Lab",
            "type":"Services"
        }
    ],
    "sg:phone":"+1 310 859 9173",
    "sg:postcode":"90210",
    "sg:province":"CA",
    "sg:tags":[
        "laboratory"
    ],
    "wof:name":"Quest Diagnostics",
    "wof:placetype":"venue"
},
  "geometry": {"coordinates":[-118.40613999999999,34.067168],"type":"Point"}
}