{
  "type": "Feature",
  "properties": {
    "iso:country":"US",
    "sg:address":"575 Menlo Dr",
    "sg:city":"Rocklin",
    "sg:classifiers":[
        {
            "category":"Organizations",
            "subcategory":"Community Association",
            "type":"Services"
        }
    ],
    "sg:phone":"+1 916 632 8800",
    "sg:postcode":"95765",
    "sg:province":"CA",
    "sg:tags":[
        "fraternal"
    ],
    "wof:name":"Special Order Systems",
    "wof:placetype":"venue"
},
  "geometry": {"coordinates":[-121.296995,38.812723],"type":"Point"}
}