{
  "type": "Feature",
  "properties": {
    "addr:full":"10041 Reese Cir Salinas CA 93907",
    "addr:housenumber":"10041",
    "addr:postcode":"93907",
    "addr:street":"Reese Cir",
    "iso:country":"US",
    "sg:address":"10041 Reese Cir",
    "sg:city":"Salinas",
    "sg:classifiers":[
        {
            "category":"Retail",
            "subcategory":"Auto Repair",
            "type":"Services"
        }
    ],
    "sg:phone":"+1 831 663 9348",
    "sg:postcode":"93907",
    "sg:province":"CA",
    "sg:tags":[
        "body",
        "automobile",
        "painting",
        "repairing"
    ],
    "wof:name":"Casler Classic",
    "wof:placetype":"venue"
},
  "geometry": {"coordinates":[-121.66812299999999,36.771937],"type":"Point"}
}