{
  "type": "Feature",
  "properties": {
    "addr:full":"3716 Clifton Pl Glendale CA 91201",
    "addr:housenumber":"3716",
    "addr:postcode":"91201",
    "addr:street":"Clifton Pl",
    "iso:country":"US",
    "sg:address":"3716 Clifton Pl",
    "sg:city":"Glendale",
    "sg:classifiers":[
        {
            "category":"Building & Trades",
            "subcategory":"Electrical",
            "type":"Services"
        }
    ],
    "sg:phone":"+1 818 249 9900",
    "sg:postcode":"91201",
    "sg:province":"CA",
    "sg:tags":[
        "electrician"
    ],
    "sg:website":"www.jeffcoelectric.com",
    "wof:name":"Jeffco Electric",
    "wof:placetype":"venue"
},
  "geometry": {"coordinates":[-118.292,34.170601],"type":"Point"}
}