{
  "type": "Feature",
  "properties": {
    "addr:full":"1949 Falstone Ave Hacienda Heights CA 91745",
    "addr:housenumber":"1949",
    "addr:postcode":"91745",
    "addr:street":"Falstone Ave",
    "iso:country":"US",
    "sg:address":"1949 Falstone Ave",
    "sg:city":"Hacienda Heights",
    "sg:classifiers":[
        {
            "category":"Professional",
            "type":"Services"
        }
    ],
    "sg:phone":"+1 626 369 8480",
    "sg:postcode":"91745",
    "sg:province":"CA",
    "wof:name":"American Y&F Co Inc",
    "wof:placetype":"venue"
},
  "geometry": {"coordinates":[-117.964422,33.997153],"type":"Point"}
}