{
  "type": "Feature",
  "properties": {
    "addr:full":"4896 Mascagni St Ventura CA 93003",
    "addr:housenumber":"4896",
    "addr:postcode":"93003",
    "addr:street":"Mascagni St",
    "iso:country":"US",
    "sg:address":"4896 Mascagni St",
    "sg:city":"Ventura",
    "sg:classifiers":[
        {
            "category":"Professional",
            "subcategory":"Business Services",
            "type":"Services"
        }
    ],
    "sg:phone":"+1 805 642 6773",
    "sg:postcode":"93003",
    "sg:province":"CA",
    "sg:tags":[
        "interior",
        "consultant",
        "design",
        "decorator"
    ],
    "wof:name":"Pacific Interiors",
    "wof:placetype":"venue"
},
  "geometry": {"coordinates":[-119.227484,34.267361],"type":"Point"}
}