{
  "type": "Feature",
  "properties": {
    "addr:full":"1670 S Amphlett Blvd San Mateo CA 94402",
    "addr:housenumber":"1670",
    "addr:postcode":"94402",
    "addr:street":"S Amphlett Blvd",
    "iso:country":"US",
    "sg:address":"1670 S Amphlett Blvd",
    "sg:city":"San Mateo",
    "sg:classifiers":[
        {
            "category":"Banks & Credit Unions",
            "subcategory":"Bank",
            "type":"Services"
        }
    ],
    "sg:phone":"+1 650 378 8518",
    "sg:postcode":"94402",
    "sg:province":"CA",
    "sg:tags":[
        "institution",
        "business"
    ],
    "wof:name":"United Lending Group",
    "wof:placetype":"venue"
},
  "geometry": {"coordinates":[-122.300358,37.556911],"type":"Point"}
}