{
  "type": "Feature",
  "properties": {
    "iso:country":"US",
    "sg:address":"150 California St 14th Floor",
    "sg:city":"San Francisco",
    "sg:classifiers":[
        {
            "category":"Real Estate",
            "subcategory":"Real Estate Services",
            "type":"Services"
        }
    ],
    "sg:phone":"+1 415 421 5900",
    "sg:postcode":"94111",
    "sg:province":"CA",
    "sg:website":"www.studley.com",
    "wof:name":"Studley",
    "wof:placetype":"venue"
},
  "geometry": {"coordinates":[-122.398156,37.793422],"type":"Point"}
}