{
  "type": "Feature",
  "properties": {
    "addr:full":"3050 Bonita Rd National City CA 91910",
    "addr:housenumber":"3050",
    "addr:postcode":"91910",
    "addr:street":"Bonita Rd",
    "iso:country":"US",
    "sg:address":"3050 Bonita Rd",
    "sg:city":"National City",
    "sg:classifiers":[
        {
            "category":"Manufacturing",
            "subcategory":"Printing",
            "type":"Manufacturing & Wholesale Goods"
        }
    ],
    "sg:phone":"+1 619 475 2740",
    "sg:postcode":"91910",
    "sg:province":"CA",
    "sg:tags":[
        "poster"
    ],
    "wof:name":"Posters & Frames",
    "wof:placetype":"venue"
},
  "geometry": {"coordinates":[-117.057919,32.647714],"type":"Point"}
}