{
  "type": "Feature",
  "properties": {
    "addr:full":"9420 Valley Ford Rd Petaluma CA 94952",
    "addr:housenumber":"9420",
    "addr:postcode":"94952",
    "addr:street":"Valley Ford Rd",
    "iso:country":"US",
    "sg:address":"9420 Valley Ford Rd",
    "sg:city":"Petaluma",
    "sg:classifiers":[
        {
            "category":"Farming",
            "subcategory":"Dairy Farm",
            "type":"Manufacturing & Wholesale Goods"
        }
    ],
    "sg:phone":"+1 707 795 5971",
    "sg:postcode":"94952",
    "sg:province":"CA",
    "wof:name":"W Diamond Ranch",
    "wof:placetype":"venue"
},
  "geometry": {"coordinates":[-122.829818,38.301064],"type":"Point"}
}