{
  "type": "Feature",
  "properties": {
    "iso:country":"US",
    "sg:address":"3000 S Santa Fe Ave",
    "sg:city":"Los Angeles",
    "sg:classifiers":[
        {
            "category":"Wholesale",
            "subcategory":"Apparel",
            "type":"Manufacturing & Wholesale Goods"
        }
    ],
    "sg:phone":"+1 323 846 0991",
    "sg:postcode":"90058",
    "sg:province":"CA",
    "sg:tags":[
        "hosiery"
    ],
    "wof:name":"Royal Hosiery Corp",
    "wof:placetype":"venue"
},
  "geometry": {"coordinates":[-118.23023999999999,34.008998],"type":"Point"}
}