{
  "type": "Feature",
  "properties": {
    "iso:country":"US",
    "sg:address":"3604 Stockton Blvd",
    "sg:city":"Sacramento",
    "sg:classifiers":[
        {
            "category":"Place Of Worship",
            "subcategory":"Church",
            "type":"Public Place"
        },
        {
            "category":"Place Of Worship",
            "type":"Public Place"
        },
        {
            "category":"Organizations",
            "subcategory":"Religious Organization",
            "type":"Services"
        }
    ],
    "sg:phone":"+1 916 444 1908",
    "sg:postcode":"95820",
    "sg:province":"CA",
    "sg:tags":[
        "churches-messianic",
        "churches-non-denominational"
    ],
    "sg:website":"http://www.ftfmishchan.org",
    "wof:name":"First Tabernacle Fellowship",
    "wof:placetype":"venue"
},
  "geometry": {"coordinates":[-121.451232,38.54195],"type":"Point"}
}