{
  "type": "Feature",
  "properties": {
    "iso:country":"US",
    "sg:address":"6461 Brockton Ave",
    "sg:city":"Riverside",
    "sg:classifiers":[
        {
            "category":"Banks & Credit Unions",
            "subcategory":"Bank",
            "type":"Services"
        }
    ],
    "sg:phone":"+1 951 274 7838",
    "sg:postcode":"92506",
    "sg:province":"CA",
    "sg:tags":[
        "loan"
    ],
    "wof:name":"P & A Mortgage",
    "wof:placetype":"venue"
},
  "geometry": {"coordinates":[-117.396839,33.955218],"type":"Point"}
}