{
  "type": "Feature",
  "properties": {
    "iso:country":"US",
    "sg:address":"4230 E Florida Ave",
    "sg:city":"Hemet",
    "sg:classifiers":[
        {
            "category":"Personal",
            "subcategory":"Beauty Salon",
            "type":"Services"
        },
        {
            "category":"Personal",
            "subcategory":"Nail Salon",
            "type":"Services"
        }
    ],
    "sg:phone":"+1 951 927 1596",
    "sg:postcode":"92544",
    "sg:province":"CA",
    "wof:name":"Nail Heaven",
    "wof:placetype":"venue"
},
  "geometry": {"coordinates":[-116.92674599999999,33.747742],"type":"Point"}
}