{
  "type": "Feature",
  "properties": {
    "iso:country":"US",
    "sg:address":"4717 Geary Blvd",
    "sg:city":"San Francisco",
    "sg:classifiers":[
        {
            "category":"Personal",
            "subcategory":"Beauty Salon",
            "type":"Services"
        }
    ],
    "sg:phone":"+1 415 668 0538",
    "sg:postcode":"94118",
    "sg:province":"CA",
    "sg:tags":[
        "hair"
    ],
    "wof:name":"Salon Creation",
    "wof:placetype":"venue"
},
  "geometry": {"coordinates":[-122.470018,37.780697],"type":"Point"}
}