{
  "type": "Feature",
  "properties": {
    "iso:country":"US",
    "sg:address":"178 N Marina Dr",
    "sg:city":"Long Beach",
    "sg:classifiers":[
        {
            "category":"Ferry",
            "type":"Transportation"
        }
    ],
    "sg:phone":"+1 562 493 0951",
    "sg:postcode":"90803",
    "sg:province":"CA",
    "sg:tags":[
        "water",
        "passenger",
        "transport"
    ],
    "wof:name":"Sundiver LLC",
    "wof:placetype":"venue"
},
  "geometry": {"coordinates":[-118.110148,33.750295],"type":"Point"}
}