{
  "type": "Feature",
  "properties": {
    "iso:country":"US",
    "sg:address":"428 G St",
    "sg:city":"San Diego",
    "sg:classifiers":[
        {
            "category":"Shopping",
            "subcategory":"Tobacco",
            "type":"Retail Goods"
        }
    ],
    "sg:phone":"+1 619 239 5272",
    "sg:postcode":"92101",
    "sg:province":"CA",
    "sg:tags":[
        "product"
    ],
    "wof:name":"Gaslamp Tobacco Shoppe",
    "wof:placetype":"venue"
},
  "geometry": {"coordinates":[-117.160392,32.712636],"type":"Point"}
}