{
  "type": "Feature",
  "properties": {
    "addr:full":"1200 Gloria Way Modesto CA 95350",
    "addr:housenumber":"1200",
    "addr:postcode":"ca 95350",
    "addr:street":"Gloria Way",
    "iso:country":"US",
    "sg:address":"1200 Gloria Way",
    "sg:city":"Modesto",
    "sg:classifiers":[
        {
            "category":"Shopping",
            "type":"Retail Goods"
        }
    ],
    "sg:phone":"+1 209 526 5411",
    "sg:postcode":"95350",
    "sg:province":"CA",
    "sg:tags":[
        "merchandise"
    ],
    "wof:name":"Mid-Valley Stamp Shop",
    "wof:placetype":"venue"
},
  "geometry": {"coordinates":[-120.975639,37.66126],"type":"Point"}
}