{
  "type": "Feature",
  "properties": {
    "iso:country":"US",
    "sg:address":"18826 N Lower Sacramento Rd",
    "sg:city":"Woodbridge",
    "sg:classifiers":[
        {
            "category":"Professional",
            "subcategory":"Accounting & Tax Preparation",
            "type":"Services"
        }
    ],
    "sg:phone":"+1 209 334 3630",
    "sg:postcode":"95258",
    "sg:province":"CA",
    "sg:tags":[
        "return",
        "accountants-certified",
        "preparation-business",
        "public"
    ],
    "sg:website":"http://www.npearsoncpa.com",
    "wof:name":"Norman O Pearson Cpa",
    "wof:placetype":"venue"
},
  "geometry": {"coordinates":[-121.301067,38.152957],"type":"Point"}
}