{
  "type": "Feature",
  "properties": {
    "iso:country":"US",
    "sg:address":"13648 Shady Knoll Ct",
    "sg:city":"Moorpark",
    "sg:classifiers":[
        {
            "category":"Building & Trades",
            "subcategory":"Construction",
            "type":"Services"
        }
    ],
    "sg:phone":"+1 805 523 2326",
    "sg:postcode":"93021",
    "sg:province":"CA",
    "sg:tags":[
        "coping",
        "plastering",
        "tiling",
        "pool",
        "swimming"
    ],
    "wof:name":"Azure Pools",
    "wof:placetype":"venue"
},
  "geometry": {"coordinates":[-118.872372,34.262546],"type":"Point"}
}