{
  "type": "Feature",
  "properties": {
    "iso:country":"US",
    "sg:address":"1840 N San Marcos Rd",
    "sg:city":"Santa Barbara",
    "sg:classifiers":[
        {
            "category":"Recreation",
            "type":"Entertainment"
        }
    ],
    "sg:phone":"+1 805 683 4454",
    "sg:postcode":"93111",
    "sg:province":"CA",
    "sg:tags":[
        "riding",
        "training"
    ],
    "wof:name":"McMillan Farm",
    "wof:placetype":"venue"
},
  "geometry": {"coordinates":[-119.799347,34.474461],"type":"Point"}
}