{
  "type": "Feature",
  "properties": {
    "addr:full":"1311 N Main St Los Angeles CA 90012",
    "addr:housenumber":"1311",
    "addr:postcode":"90012",
    "addr:street":"N Main St",
    "iso:country":"US",
    "sg:address":"1311 N Main St",
    "sg:city":"Los Angeles",
    "sg:classifiers":[
        {
            "category":"Wholesale",
            "subcategory":"Non-durable Goods",
            "type":"Manufacturing & Wholesale Goods"
        }
    ],
    "sg:phone":"+1 323 223 6326",
    "sg:postcode":"90012",
    "sg:province":"CA",
    "wof:name":"LI Hing Kong",
    "wof:placetype":"venue"
},
  "geometry": {"coordinates":[-118.231427,34.064828],"type":"Point"}
}