{
  "type": "Feature",
  "properties": {
    "addr:full":"68132 Valley Vista Dr Cathedral City CA 92234",
    "addr:housenumber":"68132",
    "addr:postcode":"92234",
    "addr:street":"Valley Vista Dr",
    "iso:country":"US",
    "sg:address":"68132 Valley Vista Dr",
    "sg:city":"Cathedral City",
    "sg:classifiers":[
        {
            "category":"Professional",
            "subcategory":"Lawyer & Legal Services",
            "type":"Services"
        }
    ],
    "sg:phone":"+1 760 328 0501",
    "sg:postcode":"92234",
    "sg:province":"CA",
    "wof:name":"Nelson Walter R Attorney",
    "wof:placetype":"venue"
},
  "geometry": {"coordinates":[-116.47537699999999,33.765498],"type":"Point"}
}