{
  "type": "Feature",
  "properties": {
    "addr:full":"5939 Canoga Ave Woodland Hills CA 91367",
    "addr:housenumber":"5939",
    "addr:postcode":"91367",
    "addr:street":"Canoga Ave",
    "iso:country":"US",
    "sg:address":"5939 Canoga Ave",
    "sg:city":"Woodland Hills",
    "sg:classifiers":[
        {
            "category":"Banks & Credit Unions",
            "subcategory":"Bank",
            "type":"Services"
        }
    ],
    "sg:phone":"+1 818 712 9672",
    "sg:postcode":"91367",
    "sg:province":"CA",
    "wof:name":"First Bank & Trust",
    "wof:placetype":"venue"
},
  "geometry": {"coordinates":[-118.598,34.177299],"type":"Point"}
}