{
  "type": "Feature",
  "properties": {
    "addr:full":"930 N Loren Ave Azusa CA 91702",
    "addr:housenumber":"930",
    "addr:postcode":"91702",
    "addr:street":"N Loren Ave",
    "iso:country":"US",
    "sg:address":"930 N Loren Ave",
    "sg:city":"Azusa",
    "sg:classifiers":[
        {
            "category":"Building & Trades",
            "subcategory":"Construction",
            "type":"Services"
        }
    ],
    "sg:phone":"+1 626 334 1800",
    "sg:postcode":"91702",
    "sg:province":"CA",
    "sg:tags":[
        "roofing",
        "industrial",
        "contractors-commercial",
        "contractor"
    ],
    "wof:name":"Alliance Roofing Company",
    "wof:placetype":"venue"
},
  "geometry": {"coordinates":[-117.923744,34.137372],"type":"Point"}
}