{
  "type": "Feature",
  "properties": {
    "addr:full":"4475 Mission Blvd San Diego CA 92109",
    "addr:housenumber":"4475",
    "addr:postcode":"92109",
    "addr:street":"Mission Blvd",
    "iso:country":"US",
    "sg:address":"4475 Mission Blvd",
    "sg:city":"San Diego",
    "sg:classifiers":[
        {
            "category":"Arena",
            "subcategory":"Sports Club",
            "type":"Entertainment"
        }
    ],
    "sg:phone":"+1 858 483 8777",
    "sg:postcode":"92109",
    "sg:province":"CA",
    "sg:tags":[
        "manager",
        "recruiter",
        "promoter"
    ],
    "wof:name":"Bicycling West Inc",
    "wof:placetype":"venue"
},
  "geometry": {"coordinates":[-117.255486,32.796557],"type":"Point"}
}