{
  "type": "Feature",
  "properties": {
    "iso:country":"US",
    "sg:address":"49174 Buena Vista Dr",
    "sg:city":"Morongo Valley",
    "sg:classifiers":[
        {
            "category":"Wholesale",
            "subcategory":"Office Equipment",
            "type":"Manufacturing & Wholesale Goods"
        }
    ],
    "sg:phone":"+1 760 363 7987",
    "sg:postcode":"92256",
    "sg:province":"CA",
    "wof:name":"Bank Card USA",
    "wof:placetype":"venue"
},
  "geometry": {"coordinates":[-116.589612,34.052171],"type":"Point"}
}