{
  "type": "Feature",
  "properties": {
    "addr:full":"13831 S Menlo Ave Gardena CA 90247",
    "addr:housenumber":"13831",
    "addr:postcode":"90247",
    "addr:street":"S Menlo Ave",
    "iso:country":"US",
    "sg:address":"13831 S Menlo Ave",
    "sg:city":"Gardena",
    "sg:classifiers":[
        {
            "category":"Professional",
            "type":"Services"
        }
    ],
    "sg:phone":"+1 310 532 4177",
    "sg:postcode":"90247",
    "sg:province":"CA",
    "sg:tags":[
        "establishment"
    ],
    "wof:name":"Yilma Shimeils",
    "wof:placetype":"venue"
},
  "geometry": {"coordinates":[-118.28940299999999,33.904767],"type":"Point"}
}