{
  "type": "Feature",
  "properties": {
    "iso:country":"US",
    "sg:address":"584 Poli St",
    "sg:city":"Ventura",
    "sg:classifiers":[
        {
            "category":"Professional",
            "type":"Services"
        }
    ],
    "sg:phone":"+1 805 653 9233",
    "sg:postcode":"93001",
    "sg:province":"CA",
    "sg:tags":[
        "establishment"
    ],
    "wof:name":"Wadelaw",
    "wof:placetype":"venue"
},
  "geometry": {"coordinates":[-119.29234599999999,34.282038],"type":"Point"}
}