{
  "type": "Feature",
  "properties": {
    "iso:country":"US",
    "sg:address":"6990 Village Pkwy",
    "sg:city":"Dublin",
    "sg:classifiers":[
        {
            "category":"Professional",
            "subcategory":"Art Services",
            "type":"Services"
        }
    ],
    "sg:phone":"+1 925 602 0635",
    "sg:postcode":"94568",
    "sg:province":"CA",
    "sg:tags":[
        "graphic",
        "designer"
    ],
    "wof:name":"Millenium Graphics",
    "wof:placetype":"venue"
},
  "geometry": {"coordinates":[-121.9255,37.70801],"type":"Point"}
}