{
  "type": "Feature",
  "properties": {
    "addr:full":"104 Pierce Ave Manteca CA 95336",
    "addr:housenumber":"104",
    "addr:postcode":"95336",
    "addr:street":"Pierce Ave",
    "iso:country":"US",
    "sg:address":"104 Pierce Ave",
    "sg:city":"Manteca",
    "sg:classifiers":[
        {
            "category":"Bars & Pubs",
            "type":"Food & Drink"
        }
    ],
    "sg:phone":"+1 209 825 7773",
    "sg:postcode":"95336",
    "sg:province":"CA",
    "wof:name":"Extreme Sports Lounge",
    "wof:placetype":"venue"
},
  "geometry": {"coordinates":[-121.219684,37.797627],"type":"Point"}
}