{
  "type": "Feature",
  "properties": {
    "iso:country":"US",
    "sg:address":"511 W Indianapolis Ave",
    "sg:city":"Clovis",
    "sg:classifiers":[
        {
            "category":"Wholesale",
            "subcategory":"Non-durable Goods",
            "type":"Manufacturing & Wholesale Goods"
        }
    ],
    "sg:phone":"+1 559 289 9158",
    "sg:postcode":"93612",
    "sg:province":"CA",
    "wof:name":"Tee Shirts and Hats DOT Com",
    "wof:placetype":"venue"
},
  "geometry": {"coordinates":[-119.722183,36.799118],"type":"Point"}
}