{
  "type": "Feature",
  "properties": {
    "addr:full":"4753 Paradise Ct Rocklin CA 95677",
    "addr:housenumber":"4753",
    "addr:postcode":"95677",
    "addr:street":"Paradise Ct",
    "iso:country":"US",
    "sg:address":"4753 Paradise Ct",
    "sg:city":"Rocklin",
    "sg:classifiers":[
        {
            "category":"Professional",
            "type":"Services"
        }
    ],
    "sg:phone":"+1 916 624 7323",
    "sg:postcode":"95677",
    "sg:province":"CA",
    "wof:name":"Bibles Plus",
    "wof:placetype":"venue"
},
  "geometry": {"coordinates":[-121.21616299999999,38.783068],"type":"Point"}
}