{
  "type": "Feature",
  "properties": {
    "addr:full":"310 Harbor Dr Sausalito CA 94965",
    "addr:housenumber":"310",
    "addr:postcode":"94965",
    "addr:street":"Harbor Dr",
    "iso:country":"US",
    "sg:address":"310 Harbor Dr",
    "sg:city":"Sausalito",
    "sg:classifiers":[
        {
            "category":"Shopping",
            "subcategory":"Bicycles & Sporting Goods",
            "type":"Retail Goods"
        }
    ],
    "sg:phone":"+1 415 332 4200",
    "sg:postcode":"94965",
    "sg:province":"CA",
    "sg:tags":[
        "tackle",
        "fishing"
    ],
    "wof:name":"Salty's Bait & Tackle",
    "wof:placetype":"venue"
},
  "geometry": {"coordinates":[-122.50000900000001,37.867397],"type":"Point"}
}