{
  "type": "Feature",
  "properties": {
    "addr:full":"5162 del Este Cir La Palma CA 90623",
    "addr:housenumber":"5162",
    "addr:postcode":"90623",
    "addr:street":"Del Este Cir",
    "iso:country":"US",
    "sg:address":"5162 del Este Cir",
    "sg:city":"La Palma",
    "sg:classifiers":[
        {
            "category":"Wholesale",
            "subcategory":"Construction Materials",
            "type":"Manufacturing & Wholesale Goods"
        }
    ],
    "sg:phone":"+1 714 229 8453",
    "sg:postcode":"90623",
    "sg:province":"CA",
    "sg:tags":[
        "tile"
    ],
    "wof:name":"ABC Imports",
    "wof:placetype":"venue"
},
  "geometry": {"coordinates":[-118.042045,33.840763],"type":"Point"}
}