{
  "type": "Feature",
  "properties": {
    "iso:country":"US",
    "sg:address":"924 N Filbert St",
    "sg:city":"Stockton",
    "sg:classifiers":[
        {
            "category":"Organizations",
            "subcategory":"Religious Organization",
            "type":"Services"
        }
    ],
    "sg:phone":"+1 209 462 6560",
    "sg:postcode":"95205",
    "sg:province":"CA",
    "sg:tags":[
        "church"
    ],
    "wof:name":"Crosstown Community Church",
    "wof:placetype":"venue"
},
  "geometry": {"coordinates":[-121.257753,37.969138],"type":"Point"}
}