{
  "type": "Feature",
  "properties": {
    "iso:country":"US",
    "sg:address":"1591 W Hamilton Ave",
    "sg:city":"El Centro",
    "sg:classifiers":[
        {
            "category":"Professional",
            "type":"Services"
        }
    ],
    "sg:phone":"+1 760 352 5426",
    "sg:postcode":"92243",
    "sg:province":"CA",
    "wof:name":"Archibald Mark Dessert Truste",
    "wof:placetype":"venue"
},
  "geometry": {"coordinates":[-115.573603,32.785615],"type":"Point"}
}