{
  "type": "Feature",
  "properties": {
    "iso:country":"US",
    "sg:address":"5521 Reseda Blvd",
    "sg:city":"Tarzana",
    "sg:classifiers":[
        {
            "category":"Professional",
            "subcategory":"Accounting & Tax Preparation",
            "type":"Services"
        }
    ],
    "sg:phone":"+1 818 774 1095",
    "sg:postcode":"91356",
    "sg:province":"CA",
    "sg:tags":[
        "accountant"
    ],
    "wof:name":"Arnold Dubin & Co",
    "wof:placetype":"venue"
},
  "geometry": {"coordinates":[-118.53607599999999,34.172252],"type":"Point"}
}