{
  "type": "Feature",
  "properties": {
    "iso:country":"US",
    "sg:address":"670 W Napa St",
    "sg:city":"Sonoma",
    "sg:classifiers":[
        {
            "category":"Professional",
            "subcategory":"Lawyer & Legal Services",
            "type":"Services"
        }
    ],
    "sg:phone":"+1 707 996 3647",
    "sg:postcode":"95476",
    "sg:province":"CA",
    "sg:tags":[
        "attorney"
    ],
    "wof:name":"Newton Dal Pogetto Law Offices",
    "wof:placetype":"venue"
},
  "geometry": {"coordinates":[-122.470833,38.293249],"type":"Point"}
}