{
  "type": "Feature",
  "properties": {
    "iso:country":"US",
    "sg:address":"1702 W 135th Street",
    "sg:city":"Gardena",
    "sg:classifiers":[
        {
            "category":"Building & Trades",
            "subcategory":"Plumbing",
            "type":"Services"
        }
    ],
    "sg:phone":"+1 310 327 1114",
    "sg:postcode":"90249",
    "sg:province":"CA",
    "wof:name":"Sjl Plumbing & Piping",
    "wof:placetype":"venue"
},
  "geometry": {"coordinates":[-118.30746000000001,33.909279],"type":"Point"}
}