{
  "type": "Feature",
  "properties": {
    "addr:full":"16429 Bellflower Blvd Bellflower CA 90706",
    "addr:housenumber":"16429",
    "addr:postcode":"90706",
    "addr:street":"Bellflower Blvd",
    "iso:country":"US",
    "sg:address":"16429 Bellflower Blvd",
    "sg:city":"Bellflower",
    "sg:classifiers":[
        {
            "category":"Travel",
            "subcategory":"Travel Agent",
            "type":"Entertainment"
        }
    ],
    "sg:phone":"+1 562 461 1201",
    "sg:postcode":"90706",
    "sg:province":"CA",
    "sg:tags":[
        "agency",
        "bureau"
    ],
    "wof:name":"Compton Travel Svc",
    "wof:placetype":"venue"
},
  "geometry": {"coordinates":[-118.125331,33.884909],"type":"Point"}
}