{
  "type": "Feature",
  "properties": {
    "iso:country":"US",
    "sg:address":"4759 Hollywood Blvd",
    "sg:city":"Los Angeles",
    "sg:classifiers":[
        {
            "category":"Shopping",
            "subcategory":"Computers & Home Electronics",
            "type":"Retail Goods"
        }
    ],
    "sg:phone":"+1 323 660 0481",
    "sg:postcode":"90027",
    "sg:province":"CA",
    "sg:tags":[
        "equipment",
        "electronic",
        "supply"
    ],
    "wof:name":"Olympic Electronics",
    "wof:placetype":"venue"
},
  "geometry": {"coordinates":[-118.29424899999999,34.101849],"type":"Point"}
}