{
  "type": "Feature",
  "properties": {
    "iso:country":"US",
    "sg:address":"2323 N Moorpark Rd",
    "sg:city":"Thousand Oaks",
    "sg:classifiers":[
        {
            "category":"Education",
            "subcategory":"School",
            "type":"Public Place"
        }
    ],
    "sg:phone":"+1 805 379 0437",
    "sg:postcode":"91360",
    "sg:province":"CA",
    "wof:name":"Thousand Oaks High Sch Band Rm",
    "wof:placetype":"venue"
},
  "geometry": {"coordinates":[-118.868291,34.212142],"type":"Point"}
}