{
  "type": "Feature",
  "properties": {
    "iso:country":"US",
    "sg:address":"518 W 6th St",
    "sg:city":"Antioch",
    "sg:classifiers":[
        {
            "category":"Place Of Worship",
            "subcategory":"Church",
            "type":"Public Place"
        },
        {
            "category":"Place Of Worship",
            "type":"Public Place"
        }
    ],
    "sg:phone":"+1 925 706 2534",
    "sg:postcode":"94509",
    "sg:province":"CA",
    "sg:tags":[
        "churches-baptist-general",
        "churches-baptist"
    ],
    "wof:name":"Iglesia Biblica Bautista De Antioquia",
    "wof:placetype":"venue"
},
  "geometry": {"coordinates":[-121.81274999999999,38.01405],"type":"Point"}
}