{
  "type": "Feature",
  "properties": {
    "addr:full":"462 S Marengo Ave Pasadena CA 91101",
    "addr:housenumber":"462",
    "addr:postcode":"91101",
    "addr:street":"S Marengo Ave",
    "iso:country":"US",
    "sg:address":"462 S Marengo Ave",
    "sg:city":"Pasadena",
    "sg:classifiers":[
        {
            "category":"Professional",
            "subcategory":"Lawyer & Legal Services",
            "type":"Services"
        }
    ],
    "sg:phone":"+1 626 796 4730",
    "sg:postcode":"91101",
    "sg:province":"CA",
    "sg:tags":[
        "attorney"
    ],
    "wof:name":"Brian D Heckmann",
    "wof:placetype":"venue"
},
  "geometry": {"coordinates":[-118.14579000000001,34.136987],"type":"Point"}
}