{
  "type": "Feature",
  "properties": {
    "addr:full":"2021 California St San Francisco CA 94109",
    "addr:housenumber":"2021",
    "addr:postcode":"94109",
    "addr:street":"California St",
    "iso:country":"US",
    "sg:address":"2021 California St",
    "sg:city":"San Francisco",
    "sg:classifiers":[
        {
            "category":"Real Estate",
            "subcategory":"Real Estate Operator",
            "type":"Services"
        }
    ],
    "sg:postcode":"94109",
    "sg:province":"CA",
    "sg:tags":[
        "apartment"
    ],
    "wof:name":"2021 California",
    "wof:placetype":"venue"
},
  "geometry": {"coordinates":[-122.427846,37.789358],"type":"Point"}
}