{
  "type": "Feature",
  "properties": {
    "iso:country":"US",
    "sg:address":"23080 Blue Bird Dr",
    "sg:city":"Sun City",
    "sg:classifiers":[
        {
            "category":"Professional",
            "type":"Services"
        }
    ],
    "sg:phone":"+1 951 244 6245",
    "sg:postcode":"92587",
    "sg:province":"CA",
    "wof:name":"Ray Uren",
    "wof:placetype":"venue"
},
  "geometry": {"coordinates":[-117.25686,33.678728],"type":"Point"}
}