{
  "type": "Feature",
  "properties": {
    "addr:full":"823 W Washington St San Diego CA 92103",
    "addr:housenumber":"823",
    "addr:postcode":"92103",
    "addr:street":"W Washington St",
    "iso:country":"US",
    "sg:address":"823 W Washington St",
    "sg:city":"San Diego",
    "sg:classifiers":[
        {
            "category":"Shopping",
            "subcategory":"Used Merchandise",
            "type":"Retail Goods"
        }
    ],
    "sg:phone":"+1 619 260 0686",
    "sg:postcode":"92103",
    "sg:province":"CA",
    "sg:tags":[
        "art",
        "gallery"
    ],
    "wof:name":"Folk Art International",
    "wof:placetype":"venue"
},
  "geometry": {"coordinates":[-117.170998,32.749699],"type":"Point"}
}