{
  "type": "Feature",
  "properties": {
    "addr:full":"927 10th St Modesto CA 95354",
    "addr:housenumber":"927",
    "addr:postcode":"ca 95354",
    "addr:street":"10Th St",
    "iso:country":"US",
    "sg:address":"927 10th St",
    "sg:city":"Modesto",
    "sg:classifiers":[
        {
            "category":"Bars & Pubs",
            "type":"Food & Drink"
        }
    ],
    "sg:phone":"+1 209 577 4776",
    "sg:postcode":"95354",
    "sg:province":"CA",
    "sg:tags":[
        "dance",
        "club",
        "lounge",
        "cocktail"
    ],
    "sg:website":"www.copperrhino.com",
    "wof:name":"Copper Rhino",
    "wof:placetype":"venue"
},
  "geometry": {"coordinates":[-120.999696,37.640002],"type":"Point"}
}