{
  "type": "Feature",
  "properties": {
    "addr:full":"516 5th St Eureka CA 95501",
    "addr:housenumber":"516",
    "addr:postcode":"95501",
    "addr:street":"5Th St",
    "iso:country":"US",
    "sg:address":"516 5th St",
    "sg:city":"Eureka",
    "sg:classifiers":[
        {
            "category":"Health Services",
            "subcategory":"Health Practitioner",
            "type":"Services"
        }
    ],
    "sg:phone":"+1 707 444 8900",
    "sg:postcode":"95501",
    "sg:province":"CA",
    "sg:tags":[
        "therapist",
        "physical"
    ],
    "wof:name":"Bikram's Yoga Clg Of India",
    "wof:placetype":"venue"
},
  "geometry": {"coordinates":[-124.164993,40.801941],"type":"Point"}
}