{
  "type": "Feature",
  "properties": {
    "addr:full":"420 W Baseline Rd Ste B Glendora CA 91740",
    "addr:housenumber":"420",
    "addr:postcode":"91740",
    "addr:street":"W Baseline Rd Ste B",
    "iso:country":"US",
    "sg:address":"420 W Baseline Rd Ste B",
    "sg:city":"Glendora",
    "sg:classifiers":[
        {
            "category":"Real Estate",
            "subcategory":"Real Estate Services",
            "type":"Services"
        },
        {
            "category":"Banks & Credit Unions",
            "subcategory":"Financial Services",
            "type":"Services"
        }
    ],
    "sg:phone":"+1 626 914 2796",
    "sg:postcode":"91740",
    "sg:province":"CA",
    "sg:tags":[
        "loan",
        "mortgage"
    ],
    "sg:website":"http://www.eaglemoney.com",
    "wof:name":"Eagle Mortgage",
    "wof:placetype":"venue"
},
  "geometry": {"coordinates":[-117.870295,34.121349],"type":"Point"}
}