{
  "type": "Feature",
  "properties": {
    "addr:full":"5011 Clayton Rd Concord CA 94521",
    "addr:housenumber":"5011",
    "addr:postcode":"94521",
    "addr:street":"Clayton Rd",
    "iso:country":"US",
    "sg:address":"5011 Clayton Rd",
    "sg:city":"Concord",
    "sg:classifiers":[
        {
            "category":"Health Services",
            "subcategory":"Chiropractor",
            "type":"Services"
        }
    ],
    "sg:phone":"+1 925 682 4941",
    "sg:postcode":"94521",
    "sg:province":"CA",
    "wof:name":"Barta Chiropractic",
    "wof:placetype":"venue"
},
  "geometry": {"coordinates":[-121.968974,37.956257],"type":"Point"}
}