{
  "type": "Feature",
  "properties": {
    "addr:full":"2001 Van Ness Ave Ste 404 San Francisco CA 94109",
    "addr:housenumber":"2001",
    "addr:postcode":"94109",
    "addr:street":"Van Ness Ave Ste 404",
    "iso:country":"US",
    "sg:address":"2001 Van Ness Ave Ste 404",
    "sg:city":"San Francisco",
    "sg:classifiers":[
        {
            "category":"Personal",
            "subcategory":"Massage",
            "type":"Services"
        }
    ],
    "sg:phone":"+1 415 640 2367",
    "sg:postcode":"94109",
    "sg:province":"CA",
    "sg:website":"www.nathanfreebody.com",
    "wof:name":"Nathan Freebody Massage",
    "wof:placetype":"venue"
},
  "geometry": {"coordinates":[-122.42353900000001,37.79408],"type":"Point"}
}