{
  "type": "Feature",
  "properties": {
    "iso:country":"US",
    "sg:address":"1000 E Ocean Blvd",
    "sg:city":"Long Beach",
    "sg:classifiers":[
        {
            "category":"Wholesale",
            "subcategory":"Electrical",
            "type":"Manufacturing & Wholesale Goods"
        }
    ],
    "sg:phone":"+1 562 598 5563",
    "sg:postcode":"90802",
    "sg:province":"CA",
    "sg:tags":[
        "parts",
        "electronic"
    ],
    "wof:name":"Bernard Kessler & Assoc Ltd",
    "wof:placetype":"venue"
},
  "geometry": {"coordinates":[-118.180481,33.766071],"type":"Point"}
}