{
  "type": "Feature",
  "properties": {
    "iso:country":"US",
    "sg:address":"18300 State Hwy 18",
    "sg:city":"Apple Valley",
    "sg:classifiers":[
        {
            "category":"Health Services",
            "subcategory":"Hospital",
            "type":"Services"
        }
    ],
    "sg:phone":"+1 760 242 2311",
    "sg:postcode":"92307",
    "sg:province":"CA",
    "sg:tags":[
        "general"
    ],
    "wof:name":"Saint Mary Medical Center",
    "wof:placetype":"venue"
},
  "geometry": {"coordinates":[-117.264729,34.540388],"type":"Point"}
}