{
  "type": "Feature",
  "properties": {
    "addr:full":"200 7th Avenue Suite 110 Santa Cruz CA 95062",
    "addr:housenumber":"200",
    "addr:postcode":"95062",
    "addr:street":"7Th Avenue Suite 110",
    "iso:country":"US",
    "sg:address":"200 7th Avenue Suite 110",
    "sg:city":"Santa Cruz",
    "sg:classifiers":[
        {
            "category":"Real Estate",
            "subcategory":"Architect",
            "type":"Services"
        }
    ],
    "sg:phone":"+1 831 465 9910",
    "sg:postcode":"95062",
    "sg:province":"CA",
    "wof:name":"Boyd William Rennie Archietect",
    "wof:placetype":"venue"
},
  "geometry": {"coordinates":[-121.998454,36.964078],"type":"Point"}
}