{
  "type": "Feature",
  "properties": {
    "iso:country":"US",
    "sg:address":"111 W 7th St",
    "sg:city":"Los Angeles",
    "sg:classifiers":[
        {
            "category":"Shopping",
            "subcategory":"Clothing, Apparel, & Fashions",
            "type":"Retail Goods"
        }
    ],
    "sg:phone":"+1 213 683 8235",
    "sg:postcode":"90014",
    "sg:province":"CA",
    "wof:name":"JMT Fashions",
    "wof:placetype":"venue"
},
  "geometry": {"coordinates":[-118.25165200000001,34.044175],"type":"Point"}
}