{
  "type": "Feature",
  "properties": {
    "addr:full":"285 N el Camino Real Encinitas CA 92024",
    "addr:housenumber":"285",
    "addr:postcode":"92024",
    "addr:street":"N El Camino Real",
    "iso:country":"US",
    "sg:address":"285 N el Camino Real",
    "sg:city":"Encinitas",
    "sg:classifiers":[
        {
            "category":"Health Services",
            "subcategory":"Doctor",
            "type":"Services"
        }
    ],
    "sg:phone":"+1 760 436 4511",
    "sg:postcode":"92024",
    "sg:province":"CA",
    "sg:tags":[
        "clinic"
    ],
    "wof:name":"North Coast Pediatric Medical",
    "wof:placetype":"venue"
},
  "geometry": {"coordinates":[-117.259851,33.049125],"type":"Point"}
}