{
  "type": "Feature",
  "properties": {
    "iso:country":"US",
    "sg:address":"1620 W Redondo Beach Blvd Marukai Food Court",
    "sg:city":"Gardena",
    "sg:classifiers":[
        {
            "category":"Restaurant",
            "type":"Food & Drink"
        }
    ],
    "sg:phone":"+1 310 516 6639",
    "sg:postcode":"90247",
    "sg:province":"CA",
    "sg:tags":[
        "japanese"
    ],
    "sg:website":"www.marukai.com/location-e.html#...",
    "wof:name":"Sawtelle Kitchen",
    "wof:placetype":"venue"
},
  "geometry": {"coordinates":[-118.30550700000001,33.889687],"type":"Point"}
}