{
  "type": "Feature",
  "properties": {
    "addr:full":"1620 W Redondo Beach Blvd Marukai Food Court Gardena CA 90247",
    "addr:housenumber":"1620",
    "addr:postcode":"90247",
    "addr:street":"W Redondo Beach Blvd",
    "iso:country":"US",
    "sg:address":"1620 W Redondo Beach Blvd Marukai Food Court",
    "sg:city":"Gardena",
    "sg:classifiers":[
        {
            "category":"Restaurant",
            "type":"Food & Drink"
        }
    ],
    "sg:phone":"+1 310 516 6639",
    "sg:postcode":"90247",
    "sg:province":"CA",
    "sg:tags":[
        "japanese"
    ],
    "sg:website":"www.marukai.com/location-e.html#...",
    "wof:name":"Sawtelle Kitchen",
    "wof:placetype":"venue"
},
  "geometry": {"coordinates":[-118.30550700000001,33.889687],"type":"Point"}
}