{
  "type": "Feature",
  "properties": {
    "addr:full":"1170 Foxworthy Avenue San Jose CA 95118",
    "addr:housenumber":"1170",
    "addr:postcode":"95118",
    "addr:street":"Foxworthy Avenue",
    "iso:country":"US",
    "sg:address":"1170 Foxworthy Avenue",
    "sg:city":"San Jose",
    "sg:classifiers":[
        {
            "category":"Place Of Worship",
            "subcategory":"Church",
            "type":"Public Place"
        }
    ],
    "sg:phone":"+1 408 265 1570",
    "sg:postcode":"95118",
    "sg:province":"CA",
    "wof:name":"Church of Christ Central",
    "wof:placetype":"venue"
},
  "geometry": {"coordinates":[-121.88137399999999,37.277763],"type":"Point"}
}