{
  "type": "Feature",
  "properties": {
    "addr:full":"1675 Rogers Ave San Jose CA 95112",
    "addr:housenumber":"1675",
    "addr:postcode":"95112",
    "addr:street":"Rogers Ave",
    "iso:country":"US",
    "sg:address":"1675 Rogers Ave",
    "sg:city":"San Jose",
    "sg:classifiers":[
        {
            "category":"Utilities",
            "subcategory":"Refuse",
            "type":"Services"
        }
    ],
    "sg:phone":"+1 408 392 8207",
    "sg:postcode":"95112",
    "sg:province":"CA",
    "sg:tags":[
        "disposal",
        "waste"
    ],
    "wof:name":"Waste Management",
    "wof:placetype":"venue"
},
  "geometry": {"coordinates":[-121.905411,37.370688],"type":"Point"}
}