{
  "type": "Feature",
  "properties": {
    "addr:full":"8637 Cherry Ave Fontana CA 92335",
    "addr:housenumber":"8637",
    "addr:postcode":"92335",
    "addr:street":"Cherry Ave",
    "iso:country":"US",
    "sg:address":"8637 Cherry Ave",
    "sg:city":"Fontana",
    "sg:classifiers":[
        {
            "category":"Autos & Motor Vehicles",
            "subcategory":"Auto Supplies",
            "type":"Retail Goods"
        },
        {
            "category":"Retail",
            "subcategory":"Auto Repair",
            "type":"Services"
        }
    ],
    "sg:phone":"+1 909 829 6800",
    "sg:postcode":"92335",
    "sg:province":"CA",
    "sg:tags":[
        "lettering",
        "automobile",
        "body",
        "truck",
        "painting",
        "repairing"
    ],
    "wof:name":"Heritage Collision Center",
    "wof:placetype":"venue"
},
  "geometry": {"coordinates":[-117.4888,34.097101],"type":"Point"}
}