{
  "type": "Feature",
  "properties": {
    "addr:full":"9 N el Dorado St Stockton CA 95202",
    "addr:housenumber":"9",
    "addr:postcode":"95202",
    "addr:street":"N El Dorado St",
    "iso:country":"US",
    "sg:address":"9 N el Dorado St",
    "sg:city":"Stockton",
    "sg:classifiers":[
        {
            "category":"Insurance",
            "subcategory":"Insurance Agent",
            "type":"Services"
        }
    ],
    "sg:phone":"+1 209 461 0170",
    "sg:postcode":"95202",
    "sg:province":"CA",
    "wof:name":"State Farm Insurance",
    "wof:placetype":"venue"
},
  "geometry": {"coordinates":[-121.28976299999999,37.952639],"type":"Point"}
}