{
  "type": "Feature",
  "properties": {
    "iso:country":"US",
    "sg:address":"1233 Sanguinetti Rd",
    "sg:city":"Sonora",
    "sg:classifiers":[
        {
            "category":"Shopping",
            "subcategory":"Gifts & Souvenirs",
            "type":"Retail Goods"
        }
    ],
    "sg:phone":"+1 209 588 1301",
    "sg:postcode":"95370",
    "sg:province":"CA",
    "sg:tags":[
        "shop"
    ],
    "wof:name":"Hallmark HLC2",
    "wof:placetype":"venue"
},
  "geometry": {"coordinates":[-120.36106,37.974593],"type":"Point"}
}