{
  "type": "Feature",
  "properties": {
    "addr:full":"1200 Artesia Blvd Hermosa Beach CA 90254",
    "addr:housenumber":"1200",
    "addr:postcode":"90254",
    "addr:street":"Artesia Blvd",
    "iso:country":"US",
    "sg:address":"1200 Artesia Blvd",
    "sg:city":"Hermosa Beach",
    "sg:classifiers":[
        {
            "category":"Health Services",
            "subcategory":"Chiropractor",
            "type":"Services"
        }
    ],
    "sg:phone":"+1 310 374 9025",
    "sg:postcode":"90254",
    "sg:province":"CA",
    "sg:website":"www.frankamatodabco.com",
    "wof:name":"Dynamic Chiropractic",
    "wof:placetype":"venue"
},
  "geometry": {"coordinates":[-118.391688,33.872817],"type":"Point"}
}