{
  "type": "Feature",
  "properties": {
    "addr:full":"3828 Willat Ave Culver City CA 90232",
    "addr:housenumber":"3828",
    "addr:postcode":"90232",
    "addr:street":"Willat Ave",
    "iso:country":"US",
    "sg:address":"3828 Willat Ave",
    "sg:city":"Culver City",
    "sg:classifiers":[
        {
            "category":"Manufacturing",
            "subcategory":"Food",
            "type":"Manufacturing & Wholesale Goods"
        }
    ],
    "sg:phone":"+1 310 477 2229",
    "sg:postcode":"90232",
    "sg:province":"CA",
    "sg:tags":[
        "product",
        "eating",
        "mfg"
    ],
    "wof:name":"Buona Forchetta Inc",
    "wof:placetype":"venue"
},
  "geometry": {"coordinates":[-118.390962,34.026565],"type":"Point"}
}