{
  "type": "Feature",
  "properties": {
    "iso:country":"US",
    "sg:address":"300 N Swall Dr",
    "sg:city":"Beverly Hills",
    "sg:classifiers":[
        {
            "category":"Building & Trades",
            "subcategory":"Construction",
            "type":"Services"
        }
    ],
    "sg:phone":"+1 310 550 6333",
    "sg:postcode":"90211",
    "sg:province":"CA",
    "sg:tags":[
        "contractor"
    ],
    "wof:name":"Dean Barry Construction Co",
    "wof:placetype":"venue"
},
  "geometry": {"coordinates":[-118.385705,34.071662],"type":"Point"}
}