{
  "type": "Feature",
  "properties": {
    "iso:country":"US",
    "sg:address":"1517 Park St",
    "sg:city":"Alameda",
    "sg:classifiers":[
        {
            "category":"Professional",
            "subcategory":"Art Services",
            "type":"Services"
        },
        {
            "category":"Communications",
            "type":"Services"
        }
    ],
    "sg:phone":"+1 415 350 8244",
    "sg:postcode":"94501",
    "sg:province":"CA",
    "sg:tags":[
        "web",
        "graphic",
        "design"
    ],
    "sg:website":"www.2020visual.net",
    "wof:name":"20/20 Visual",
    "wof:placetype":"venue"
},
  "geometry": {"coordinates":[-122.241742,37.766058],"type":"Point"}
}