{
  "type": "Feature",
  "properties": {
    "iso:country":"US",
    "sg:address":"17300 17th St",
    "sg:city":"Irvine",
    "sg:classifiers":[
        {
            "category":"Wholesale",
            "subcategory":"Drugs",
            "type":"Manufacturing & Wholesale Goods"
        }
    ],
    "sg:phone":"+1 714 832 4524",
    "sg:postcode":"92648",
    "sg:province":"CA",
    "sg:tags":[
        "product",
        "sunglasses"
    ],
    "wof:name":"Mid America Sales Company",
    "wof:placetype":"venue"
},
  "geometry": {"coordinates":[-117.992074,33.683189],"type":"Point"}
}