{
  "type": "Feature",
  "properties": {
    "iso:country":"US",
    "sg:address":"2048 Cotner Avenue",
    "sg:city":"Los Angeles",
    "sg:classifiers":[
        {
            "category":"Building & Trades",
            "subcategory":"Construction",
            "type":"Services"
        }
    ],
    "sg:phone":"+1 310 477 3775",
    "sg:postcode":"90025",
    "sg:province":"CA",
    "sg:tags":[
        "contractor"
    ],
    "wof:name":"The J D Group",
    "wof:placetype":"venue"
},
  "geometry": {"coordinates":[-118.440991,34.041015],"type":"Point"}
}