{
  "type": "Feature",
  "properties": {
    "addr:full":"680 S State St Ukiah CA 95482",
    "addr:housenumber":"680",
    "addr:postcode":"ca 95482",
    "addr:street":"S State St",
    "iso:country":"US",
    "sg:address":"680 S State St",
    "sg:city":"Ukiah",
    "sg:classifiers":[
        {
            "category":"Shopping",
            "subcategory":"Pharmacy",
            "type":"Retail Goods"
        }
    ],
    "sg:phone":"+1 707 462 6850",
    "sg:postcode":"95482",
    "sg:province":"CA",
    "sg:tags":[
        "aid",
        "first",
        "store",
        "drug",
        "supply"
    ],
    "sg:website":"http://www.riteaid.com",
    "wof:name":"Rite Aid",
    "wof:placetype":"venue"
},
  "geometry": {"coordinates":[-123.206531,39.143451],"type":"Point"}
}