{
  "type": "Feature",
  "properties": {
    "addr:full":"3014 Whittier Blvd Los Angeles CA 90023",
    "addr:housenumber":"3014",
    "addr:postcode":"90023",
    "addr:street":"Whittier Blvd",
    "iso:country":"US",
    "sg:address":"3014 Whittier Blvd",
    "sg:city":"Los Angeles",
    "sg:classifiers":[
        {
            "category":"Building & Trades",
            "subcategory":"Plumbing",
            "type":"Services"
        }
    ],
    "sg:phone":"+1 323 268 8118",
    "sg:postcode":"90023",
    "sg:province":"CA",
    "sg:tags":[
        "contractor"
    ],
    "wof:name":"R C Plumbing",
    "wof:placetype":"venue"
},
  "geometry": {"coordinates":[-118.20700100000001,34.0303],"type":"Point"}
}