{
  "type": "Feature",
  "properties": {
    "iso:country":"US",
    "sg:address":"42257 6th St W",
    "sg:city":"Lancaster",
    "sg:classifiers":[
        {
            "category":"Wholesale",
            "subcategory":"Chemicals & Plastics",
            "type":"Manufacturing & Wholesale Goods"
        }
    ],
    "sg:phone":"+1 661 949 0015",
    "sg:postcode":"93534",
    "sg:province":"CA",
    "sg:tags":[
        "oxygen"
    ],
    "wof:name":"Lincare",
    "wof:placetype":"venue"
},
  "geometry": {"coordinates":[-118.14121,34.650796],"type":"Point"}
}