{
  "type": "Feature",
  "properties": {
    "iso:country":"US",
    "sg:address":"25431 Cabot Rd",
    "sg:city":"Laguna Hills",
    "sg:classifiers":[
        {
            "category":"Professional",
            "subcategory":"Art Services",
            "type":"Services"
        }
    ],
    "sg:phone":"+1 949 588 6747",
    "sg:postcode":"92653",
    "sg:province":"CA",
    "sg:tags":[
        "mfg",
        "civil",
        "commercial",
        "decal",
        "design",
        "engineer"
    ],
    "wof:name":"Aguilar Lrry Plg Grding Design",
    "wof:placetype":"venue"
},
  "geometry": {"coordinates":[-117.674688,33.592496],"type":"Point"}
}