{
  "type": "Feature",
  "properties": {
    "iso:country":"US",
    "sg:address":"1005 A Ave",
    "sg:city":"National City",
    "sg:classifiers":[
        {
            "category":"Social Services",
            "type":"Services"
        }
    ],
    "sg:phone":"+1 619 477 0165",
    "sg:postcode":"91950",
    "sg:province":"CA",
    "sg:tags":[
        "organization",
        "welfare"
    ],
    "wof:name":"Natl City WIC Program",
    "wof:placetype":"venue"
},
  "geometry": {"coordinates":[-117.104929,32.673428],"type":"Point"}
}