{
  "type": "Feature",
  "properties": {
    "addr:full":"7288 Littler Ct Moorpark CA 93021",
    "addr:housenumber":"7288",
    "addr:postcode":"ca 93021",
    "addr:street":"Littler Ct",
    "iso:country":"US",
    "sg:address":"7288 Littler Ct",
    "sg:city":"Moorpark",
    "sg:classifiers":[
        {
            "category":"Building & Trades",
            "subcategory":"Construction",
            "type":"Services"
        }
    ],
    "sg:phone":"+1 805 432 0098",
    "sg:postcode":"93021",
    "sg:province":"CA",
    "sg:tags":[
        "management"
    ],
    "wof:name":"Tri-Valley Construction Management",
    "wof:placetype":"venue"
},
  "geometry": {"coordinates":[-118.890168,34.305894],"type":"Point"}
}