{
  "type": "Feature",
  "properties": {
    "addr:full":"28160 Ave Primavera Cathedral City CA 92234",
    "addr:housenumber":"28160",
    "addr:postcode":"92234",
    "addr:street":"Ave Primavera",
    "iso:country":"US",
    "sg:address":"28160 Ave Primavera",
    "sg:city":"Cathedral City",
    "sg:classifiers":[
        {
            "category":"Building & Trades",
            "subcategory":"Construction",
            "type":"Services"
        }
    ],
    "sg:phone":"+1 760 327 0684",
    "sg:postcode":"92234",
    "sg:province":"CA",
    "sg:tags":[
        "contractor"
    ],
    "wof:name":"Salvador Escoto Pools",
    "wof:placetype":"venue"
},
  "geometry": {"coordinates":[-116.461563,33.843847],"type":"Point"}
}