{
  "type": "Feature",
  "properties": {
    "iso:country":"US",
    "sg:address":"2807 Metropolitan Pl",
    "sg:city":"Pomona",
    "sg:classifiers":[
        {
            "category":"Manufacturing",
            "subcategory":"Tools & Machinery",
            "type":"Manufacturing & Wholesale Goods"
        }
    ],
    "sg:phone":"+1 909 593 4985",
    "sg:postcode":"91767",
    "sg:province":"CA",
    "wof:name":"General Nucleonics Inc",
    "wof:placetype":"venue"
},
  "geometry": {"coordinates":[-117.75432000000001,34.097706],"type":"Point"}
}