{
  "type": "Feature",
  "properties": {
    "iso:country":"US",
    "sg:address":"9463 Las Tunas Dr",
    "sg:city":"Temple City",
    "sg:classifiers":[
        {
            "category":"Education",
            "subcategory":"Special Training",
            "type":"Public Place"
        }
    ],
    "sg:phone":"+1 626 237 0800",
    "sg:postcode":"91780",
    "sg:province":"CA",
    "sg:tags":[
        "school",
        "interest"
    ],
    "wof:name":"JEI Learning Ctr",
    "wof:placetype":"venue"
},
  "geometry": {"coordinates":[-118.064165,34.106292],"type":"Point"}
}