{
  "type": "Feature",
  "properties": {
    "addr:full":"8423 San Fernando Rd Sun Valley CA 91352",
    "addr:housenumber":"8423",
    "addr:postcode":"91352",
    "addr:street":"San Fernando Rd",
    "iso:country":"US",
    "sg:address":"8423 San Fernando Rd",
    "sg:city":"Sun Valley",
    "sg:classifiers":[
        {
            "category":"Autos & Motor Vehicles",
            "subcategory":"Automobile Sales",
            "type":"Retail Goods"
        }
    ],
    "sg:phone":"+1 818 767 4900",
    "sg:postcode":"91352",
    "sg:province":"CA",
    "sg:tags":[
        "car",
        "dealer"
    ],
    "wof:name":"El Primo Auto Sales",
    "wof:placetype":"venue"
},
  "geometry": {"coordinates":[-118.37639799999999,34.224676],"type":"Point"}
}