{
  "type": "Feature",
  "properties": {
    "iso:country":"US",
    "sg:address":"12924 Yukon Ave",
    "sg:city":"Hawthorne",
    "sg:classifiers":[
        {
            "category":"Retail",
            "subcategory":"Repair Shop",
            "type":"Services"
        }
    ],
    "sg:phone":"+1 310 672 4319",
    "sg:postcode":"90250",
    "sg:province":"CA",
    "sg:tags":[
        "piano",
        "organ-tuning",
        "refinishing",
        "restoration",
        "furniture"
    ],
    "wof:name":"Xpert Furniture Refinishing Co.",
    "wof:placetype":"venue"
},
  "geometry": {"coordinates":[-118.335176,33.915292],"type":"Point"}
}