{
  "type": "Feature",
  "properties": {
    "addr:full":"3463 Idaho Dr Santa Rosa CA 95405",
    "addr:housenumber":"3463",
    "addr:postcode":"95405",
    "addr:street":"Idaho Dr",
    "iso:country":"US",
    "sg:address":"3463 Idaho Dr",
    "sg:city":"Santa Rosa",
    "sg:classifiers":[
        {
            "category":"Restaurant",
            "type":"Food & Drink"
        }
    ],
    "sg:phone":"+1 707 578 3734",
    "sg:postcode":"95405",
    "sg:province":"CA",
    "sg:tags":[
        "eating"
    ],
    "wof:name":"Its Only Natural Catering",
    "wof:placetype":"venue"
},
  "geometry": {"coordinates":[-122.670388,38.445789],"type":"Point"}
}