{
  "type": "Feature",
  "properties": {
    "iso:country":"US",
    "sg:address":"9600 Toledo Way",
    "sg:city":"Irvine",
    "sg:classifiers":[
        {
            "category":"Manufacturing",
            "subcategory":"Apparel",
            "type":"Manufacturing & Wholesale Goods"
        }
    ],
    "sg:phone":"+1 949 252 1197",
    "sg:postcode":"92630",
    "sg:province":"CA",
    "sg:tags":[
        "ready",
        "mfg"
    ],
    "wof:name":"Rusty Apparel",
    "wof:placetype":"venue"
},
  "geometry": {"coordinates":[-117.711563,33.654134],"type":"Point"}
}