{
  "type": "Feature",
  "properties": {
    "addr:full":"733 Main St Ramona CA 92065",
    "addr:housenumber":"733",
    "addr:postcode":"92065",
    "addr:street":"Main St",
    "iso:country":"US",
    "sg:address":"733 Main St",
    "sg:city":"Ramona",
    "sg:classifiers":[
        {
            "category":"Shopping",
            "subcategory":"Clothing, Apparel, & Fashions",
            "type":"Retail Goods"
        }
    ],
    "sg:phone":"+1 760 789 7521",
    "sg:postcode":"92065",
    "sg:province":"CA",
    "sg:tags":[
        "furnishing"
    ],
    "wof:name":"Moda Casual Aguirre",
    "wof:placetype":"venue"
},
  "geometry": {"coordinates":[-116.864963,33.044099],"type":"Point"}
}