{
  "type": "Feature",
  "properties": {
    "iso:country":"US",
    "sg:address":"23436 Madero",
    "sg:city":"Mission Viejo",
    "sg:classifiers":[
        {
            "category":"Manufacturing",
            "subcategory":"Electronics",
            "type":"Manufacturing & Wholesale Goods"
        }
    ],
    "sg:phone":"+1 949 830 0965",
    "sg:postcode":"92691",
    "sg:province":"CA",
    "sg:tags":[
        "mfg",
        "related",
        "semiconductor",
        "part",
        "devices",
        "electronic"
    ],
    "wof:name":"Asat Inc",
    "wof:placetype":"venue"
},
  "geometry": {"coordinates":[-117.679462,33.624599],"type":"Point"}
}