{
  "type": "Feature",
  "properties": {
    "iso:country":"US",
    "sg:address":"20968 Ventura Blvd",
    "sg:city":"Woodland Hills",
    "sg:classifiers":[
        {
            "category":"Autos & Motor Vehicles",
            "subcategory":"Auto Supplies",
            "type":"Retail Goods"
        }
    ],
    "sg:phone":"+1 818 347 0321",
    "sg:postcode":"91364",
    "sg:province":"CA",
    "sg:tags":[
        "equipment",
        "air",
        "conditioning",
        "automobile"
    ],
    "wof:name":"Southern California Auto Ctr",
    "wof:placetype":"venue"
},
  "geometry": {"coordinates":[-118.589422,34.16639],"type":"Point"}
}