{
  "type": "Feature",
  "properties": {
    "addr:full":"460 E Easy St Simi Valley CA 93065",
    "addr:housenumber":"460",
    "addr:postcode":"93065",
    "addr:street":"E Easy St",
    "iso:country":"US",
    "sg:address":"460 E Easy St",
    "sg:city":"Simi Valley",
    "sg:classifiers":[
        {
            "category":"Building & Trades",
            "subcategory":"Construction",
            "type":"Services"
        }
    ],
    "sg:phone":"+1 805 583 4228",
    "sg:postcode":"93065",
    "sg:province":"CA",
    "sg:tags":[
        "contractor"
    ],
    "wof:name":"JKF Construction Co",
    "wof:placetype":"venue"
},
  "geometry": {"coordinates":[-118.78641500000001,34.274053],"type":"Point"}
}