{
  "type": "Feature",
  "properties": {
    "iso:country":"US",
    "sg:address":"1708 Franklin St",
    "sg:city":"Oakland",
    "sg:classifiers":[
        {
            "category":"Health Services",
            "subcategory":"Doctor",
            "type":"Services"
        }
    ],
    "sg:phone":"+1 510 465 7777",
    "sg:postcode":"94612",
    "sg:province":"CA",
    "sg:tags":[
        "surgeon",
        "oral"
    ],
    "wof:name":"Fudgen Wendell P DDS",
    "wof:placetype":"venue"
},
  "geometry": {"coordinates":[-122.26799800000001,37.8064],"type":"Point"}
}