{
  "type": "Feature",
  "properties": {
    "iso:country":"US",
    "sg:address":"100 S San Mateo Drive",
    "sg:city":"San Mateo",
    "sg:classifiers":[
        {
            "category":"Health Services",
            "subcategory":"Doctor",
            "type":"Services"
        }
    ],
    "sg:phone":"+1 650 696 4100",
    "sg:postcode":"94401",
    "sg:province":"CA",
    "sg:tags":[
        "cardiologist"
    ],
    "wof:name":"Guttas Charles K MD",
    "wof:placetype":"venue"
},
  "geometry": {"coordinates":[-122.325639,37.565965],"type":"Point"}
}