{
  "type": "Feature",
  "properties": {
    "iso:country":"US",
    "sg:address":"2 Alondra",
    "sg:city":"Irvine",
    "sg:classifiers":[
        {
            "category":"Real Estate",
            "subcategory":"Real Estate Services",
            "type":"Services"
        }
    ],
    "sg:phone":"+1 714 838 9911",
    "sg:postcode":"92620",
    "sg:province":"CA",
    "sg:tags":[
        "management",
        "property"
    ],
    "wof:name":"Key Property Management Inc",
    "wof:placetype":"venue"
},
  "geometry": {"coordinates":[-117.766504,33.719],"type":"Point"}
}