{
  "type": "Feature",
  "properties": {
    "addr:full":"25624 Walnut St Lomita CA 90717",
    "addr:housenumber":"25624",
    "addr:postcode":"90717",
    "addr:street":"Walnut St",
    "iso:country":"US",
    "sg:address":"25624 Walnut St",
    "sg:city":"Lomita",
    "sg:classifiers":[
        {
            "category":"Communications",
            "type":"Services"
        }
    ],
    "sg:phone":"+1 310 539 2639",
    "sg:postcode":"90717",
    "sg:province":"CA",
    "wof:name":"Beyond Communications",
    "wof:placetype":"venue"
},
  "geometry": {"coordinates":[-118.31207999999999,33.790681],"type":"Point"}
}