{
  "type": "Feature",
  "properties": {
    "addr:full":"1285 Columbia Ave Riverside CA 92507",
    "addr:housenumber":"1285",
    "addr:postcode":"92507",
    "addr:street":"Columbia Ave",
    "iso:country":"US",
    "sg:address":"1285 Columbia Ave",
    "sg:city":"Riverside",
    "sg:classifiers":[
        {
            "category":"Wholesale",
            "subcategory":"Electrical",
            "type":"Manufacturing & Wholesale Goods"
        }
    ],
    "sg:phone":"+1 951 686 0550",
    "sg:postcode":"92507",
    "sg:province":"CA",
    "sg:tags":[
        "sound",
        "equipment",
        "system"
    ],
    "sg:website":"www.muzak.com",
    "wof:name":"Muzak",
    "wof:placetype":"venue"
},
  "geometry": {"coordinates":[-117.334745,34.001222],"type":"Point"}
}