{
  "type": "Feature",
  "properties": {
    "addr:full":"6835 Trinidad Dr San Jose CA 95120",
    "addr:housenumber":"6835",
    "addr:postcode":"95120",
    "addr:street":"Trinidad Dr",
    "iso:country":"US",
    "sg:address":"6835 Trinidad Dr",
    "sg:city":"San Jose",
    "sg:classifiers":[
        {
            "category":"Education",
            "subcategory":"Preschool",
            "type":"Public Place"
        },
        {
            "category":"Education",
            "subcategory":"School",
            "type":"Public Place"
        }
    ],
    "sg:phone":"+1 408 997 0424",
    "sg:postcode":"95120",
    "sg:province":"CA",
    "sg:tags":[
        "elementary"
    ],
    "sg:website":"www.a-cs.org",
    "wof:name":"Almaden Country School",
    "wof:placetype":"venue"
},
  "geometry": {"coordinates":[-121.852176,37.218847],"type":"Point"}
}