{
  "type": "Feature",
  "properties": {
    "iso:country":"US",
    "sg:address":"4500 Campus Dr",
    "sg:city":"Newport Beach",
    "sg:classifiers":[
        {
            "category":"Restaurant",
            "type":"Food & Drink"
        }
    ],
    "sg:phone":"+1 949 548 7600",
    "sg:postcode":"92660",
    "sg:province":"CA",
    "sg:tags":[
        "delivery"
    ],
    "wof:name":"Gourmet Shuttle Inc",
    "wof:placetype":"venue"
},
  "geometry": {"coordinates":[-117.86579500000001,33.671281],"type":"Point"}
}