{
  "type": "Feature",
  "properties": {
    "addr:full":"227 W Janss Rd Thousand Oaks CA 91360",
    "addr:housenumber":"227",
    "addr:postcode":"91360",
    "addr:street":"W Janss Rd",
    "iso:country":"US",
    "sg:address":"227 W Janss Rd",
    "sg:city":"Thousand Oaks",
    "sg:classifiers":[
        {
            "category":"Health Services",
            "subcategory":"Podiatrist",
            "type":"Services"
        }
    ],
    "sg:phone":"+1 805 497 6979",
    "sg:postcode":"91360",
    "sg:province":"CA",
    "wof:name":"Los Robles Podiatry Group",
    "wof:placetype":"venue"
},
  "geometry": {"coordinates":[-118.88495899999999,34.205935],"type":"Point"}
}