{
  "type": "Feature",
  "properties": {
    "addr:full":"1622 E Olympic Blvd Los Angeles CA 90021",
    "addr:housenumber":"1622",
    "addr:postcode":"90021",
    "addr:street":"E Olympic Blvd",
    "iso:country":"US",
    "sg:address":"1622 E Olympic Blvd",
    "sg:city":"Los Angeles",
    "sg:classifiers":[
        {
            "category":"Wholesale",
            "subcategory":"Durable Goods & Equipment",
            "type":"Manufacturing & Wholesale Goods"
        }
    ],
    "sg:phone":"+1 213 593 1332",
    "sg:postcode":"90021",
    "sg:province":"CA",
    "sg:tags":[
        "importer",
        "store",
        "candy"
    ],
    "sg:website":"www.tornandglasser.com",
    "wof:name":"Torn & Glasser",
    "wof:placetype":"venue"
},
  "geometry": {"coordinates":[-118.241997,34.029701],"type":"Point"}
}