{
  "type": "Feature",
  "properties": {
    "addr:full":"79 Tucker Ave San Francisco CA 94134",
    "addr:housenumber":"79",
    "addr:postcode":"94134",
    "addr:street":"Tucker Ave",
    "iso:country":"US",
    "sg:address":"79 Tucker Ave",
    "sg:city":"San Francisco",
    "sg:classifiers":[
        {
            "category":"Shopping",
            "type":"Retail Goods"
        }
    ],
    "sg:phone":"+1 415 467 9341",
    "sg:postcode":"94134",
    "sg:province":"CA",
    "sg:tags":[
        "merchandise"
    ],
    "wof:name":"Picture Window",
    "wof:placetype":"venue"
},
  "geometry": {"coordinates":[-122.40407500000001,37.715109],"type":"Point"}
}