{
  "type": "Feature",
  "properties": {
    "iso:country":"US",
    "sg:address":"6195 Ojas Azules Pl",
    "sg:city":"San Miguel",
    "sg:classifiers":[
        {
            "category":"Building & Trades",
            "subcategory":"Construction",
            "type":"Services"
        }
    ],
    "sg:phone":"+1 805 467 2226",
    "sg:postcode":"93451",
    "sg:province":"CA",
    "sg:tags":[
        "contractor"
    ],
    "wof:name":"F E O'Connors Contractor",
    "wof:placetype":"venue"
},
  "geometry": {"coordinates":[-120.574429,35.71418],"type":"Point"}
}