{
  "type": "Feature",
  "properties": {
    "iso:country":"US",
    "sg:address":"66800 Pierson Blvd",
    "sg:city":"Desert Hot Spgs",
    "sg:classifiers":[
        {
            "category":"Real Estate",
            "subcategory":"Real Estate Operator",
            "type":"Services"
        }
    ],
    "sg:phone":"+1 760 329 8855",
    "sg:postcode":"92240",
    "sg:province":"CA",
    "sg:tags":[
        "apartment"
    ],
    "wof:name":"Sandy Palms Apts",
    "wof:placetype":"venue"
},
  "geometry": {"coordinates":[-116.49555700000001,33.961535],"type":"Point"}
}