{
  "type": "Feature",
  "properties": {
    "iso:country":"US",
    "sg:address":"6171 N Winton Way",
    "sg:city":"Winton",
    "sg:classifiers":[
        {
            "category":"Retail",
            "subcategory":"Auto Repair",
            "type":"Services"
        }
    ],
    "sg:phone":"+1 209 358 1847",
    "sg:postcode":"95388",
    "sg:province":"CA",
    "sg:tags":[
        "repairing",
        "automobile"
    ],
    "wof:name":"Taylor's Muffler Radiator",
    "wof:placetype":"venue"
},
  "geometry": {"coordinates":[-120.613692,37.376775],"type":"Point"}
}