{
  "type": "Feature",
  "properties": {
    "addr:full":"145 Cinnabar Way Hercules CA 94547",
    "addr:housenumber":"145",
    "addr:postcode":"94547",
    "addr:street":"Cinnabar Way",
    "iso:country":"US",
    "sg:address":"145 Cinnabar Way",
    "sg:city":"Hercules",
    "sg:classifiers":[
        {
            "category":"Building & Trades",
            "subcategory":"Construction",
            "type":"Services"
        }
    ],
    "sg:phone":"+1 510 245 2704",
    "sg:postcode":"94547",
    "sg:province":"CA",
    "sg:tags":[
        "fire",
        "restoration",
        "damage"
    ],
    "wof:name":"Royal Carpet Maintenance",
    "wof:placetype":"venue"
},
  "geometry": {"coordinates":[-122.275535,38.005192],"type":"Point"}
}