{
  "type": "Feature",
  "properties": {
    "iso:country":"US",
    "sg:address":"1630 W 11th St",
    "sg:city":"Upland",
    "sg:classifiers":[
        {
            "category":"Wholesale",
            "subcategory":"Medical Equipment & Supplies",
            "type":"Manufacturing & Wholesale Goods"
        }
    ],
    "sg:phone":"+1 909 931 1211",
    "sg:postcode":"91786",
    "sg:province":"CA",
    "wof:name":"Warehouse",
    "wof:placetype":"venue"
},
  "geometry": {"coordinates":[-117.684603,34.103164],"type":"Point"}
}