{
  "type": "Feature",
  "properties": {
    "iso:country":"US",
    "sg:address":"1319 Park St",
    "sg:city":"Paso Robles",
    "sg:classifiers":[
        {
            "category":"Shopping",
            "subcategory":"Gifts & Souvenirs",
            "type":"Retail Goods"
        }
    ],
    "sg:phone":"+1 805 237 2750",
    "sg:postcode":"93446",
    "sg:province":"CA",
    "wof:name":"Vietnam Imports",
    "wof:placetype":"venue"
},
  "geometry": {"coordinates":[-120.690349,35.628692],"type":"Point"}
}