{
  "type": "Feature",
  "properties": {
    "addr:full":"1726 Solano Ave Berkeley CA 94707",
    "addr:housenumber":"1726",
    "addr:postcode":"94707",
    "addr:street":"Solano Ave",
    "iso:country":"US",
    "sg:address":"1726 Solano Ave",
    "sg:city":"Berkeley",
    "sg:classifiers":[
        {
            "category":"Real Estate",
            "subcategory":"Real Estate Agent",
            "type":"Services"
        }
    ],
    "sg:phone":"+1 510 558 8900",
    "sg:postcode":"94707",
    "sg:province":"CA",
    "wof:name":"New Spring Real Estate",
    "wof:placetype":"venue"
},
  "geometry": {"coordinates":[-122.281991,37.891111],"type":"Point"}
}