{
  "type": "Feature",
  "properties": {
    "addr:full":"784 O'Farrell St San Francisco CA 94109",
    "addr:housenumber":"784",
    "addr:postcode":"94109",
    "addr:street":"O'Farrell St",
    "iso:country":"US",
    "sg:address":"784 O'Farrell St",
    "sg:city":"San Francisco",
    "sg:classifiers":[
        {
            "category":"Food & Beverages",
            "subcategory":"Groceries & Convenience Stores",
            "type":"Retail Goods"
        }
    ],
    "sg:postcode":"94109",
    "sg:province":"CA",
    "wof:name":"Mirex",
    "wof:placetype":"venue"
},
  "geometry": {"coordinates":[-122.417649,37.785204],"type":"Point"}
}