{
  "type": "Feature",
  "properties": {
    "addr:full":"202 N Mariposa St Fresno CA 93701",
    "addr:housenumber":"202",
    "addr:postcode":"93701",
    "addr:street":"N Mariposa St",
    "iso:country":"US",
    "sg:address":"202 N Mariposa St",
    "sg:city":"Fresno",
    "sg:classifiers":[
        {
            "category":"Education",
            "subcategory":"School",
            "type":"Public Place"
        }
    ],
    "sg:phone":"+1 559 457 2960",
    "sg:postcode":"93701",
    "sg:province":"CA",
    "wof:name":"Jefferson Elementary School",
    "wof:placetype":"venue"
},
  "geometry": {"coordinates":[-119.779183,36.745831],"type":"Point"}
}