{
  "type": "Feature",
  "properties": {
    "iso:country":"US",
    "sg:address":"2109 Colina Vista Way",
    "sg:city":"Costa Mesa",
    "sg:classifiers":[
        {
            "category":"Shopping",
            "subcategory":"Bicycles & Sporting Goods",
            "type":"Retail Goods"
        }
    ],
    "sg:phone":"+1 949 548 6683",
    "sg:postcode":"92627",
    "sg:province":"CA",
    "wof:name":"Bubinga Cruisers & Clothi",
    "wof:placetype":"venue"
},
  "geometry": {"coordinates":[-117.902842,33.644346],"type":"Point"}
}