{
  "type": "Feature",
  "properties": {
    "addr:full":"334 Conway Dr Danville CA 94526",
    "addr:housenumber":"334",
    "addr:postcode":"94526",
    "addr:street":"Conway Dr",
    "iso:country":"US",
    "sg:address":"334 Conway Dr",
    "sg:city":"Danville",
    "sg:classifiers":[
        {
            "category":"Shopping",
            "subcategory":"Jewelry",
            "type":"Retail Goods"
        }
    ],
    "sg:phone":"+1 925 820 2808",
    "sg:postcode":"94526",
    "sg:province":"CA",
    "sg:tags":[
        "designer"
    ],
    "wof:name":"Zola Simone Designs",
    "wof:placetype":"venue"
},
  "geometry": {"coordinates":[-121.970781,37.791389],"type":"Point"}
}