{
  "type": "Feature",
  "properties": {
    "addr:full":"6200 Wilshire Boulevard Los Angeles CA 90048",
    "addr:housenumber":"6200",
    "addr:postcode":"90048",
    "addr:street":"Wilshire Boulevard",
    "iso:country":"US",
    "sg:address":"6200 Wilshire Boulevard",
    "sg:city":"Los Angeles",
    "sg:classifiers":[
        {
            "category":"Health Services",
            "subcategory":"Dentist",
            "type":"Services"
        }
    ],
    "sg:phone":"+1 323 938 6137",
    "sg:postcode":"90048",
    "sg:province":"CA",
    "wof:name":"Wilshire Dental Care",
    "wof:placetype":"venue"
},
  "geometry": {"coordinates":[-118.363646,34.062856],"type":"Point"}
}