{
  "type": "Feature",
  "properties": {
    "iso:country":"US",
    "sg:address":"492 Rio Lindo Ave",
    "sg:city":"Chico",
    "sg:classifiers":[
        {
            "category":"Education",
            "subcategory":"Special Training",
            "type":"Public Place"
        }
    ],
    "sg:phone":"+1 530 891 4357",
    "sg:postcode":"95926",
    "sg:province":"CA",
    "sg:tags":[
        "aid",
        "instruction",
        "first"
    ],
    "sg:website":"www.firstresponder.com",
    "wof:name":"First Responder EMS Inc",
    "wof:placetype":"venue"
},
  "geometry": {"coordinates":[-121.851238,39.756011],"type":"Point"}
}