{
  "type": "Feature",
  "properties": {
    "iso:country":"US",
    "sg:address":"12419 Squirrel Creek Rd",
    "sg:city":"Grass Valley",
    "sg:classifiers":[
        {
            "category":"Food & Beverages",
            "subcategory":"Specialty",
            "type":"Retail Goods"
        }
    ],
    "sg:phone":"+1 530 274 2787",
    "sg:postcode":"95945",
    "sg:province":"CA",
    "sg:tags":[
        "health",
        "diet"
    ],
    "wof:name":"Nikken Distributor",
    "wof:placetype":"venue"
},
  "geometry": {"coordinates":[-121.09599900000001,39.220536],"type":"Point"}
}