{
  "type": "Feature",
  "properties": {
    "addr:full":"4200 82nd St Sacramento CA 95826",
    "addr:housenumber":"4200",
    "addr:postcode":"95826",
    "addr:street":"82Nd St",
    "iso:country":"US",
    "sg:address":"4200 82nd St",
    "sg:city":"Sacramento",
    "sg:classifiers":[
        {
            "category":"Manufacturing",
            "subcategory":"Tools & Machinery",
            "type":"Manufacturing & Wholesale Goods"
        }
    ],
    "sg:phone":"+1 916 386 0608",
    "sg:postcode":"95826",
    "sg:province":"CA",
    "sg:tags":[
        "equipment",
        "system",
        "automation"
    ],
    "wof:name":"Automation Industries",
    "wof:placetype":"venue"
},
  "geometry": {"coordinates":[-121.404402,38.53634],"type":"Point"}
}