{
  "type": "Feature",
  "properties": {
    "addr:full":"5131 W 139th St Hawthorne CA 90250",
    "addr:housenumber":"5131",
    "addr:postcode":"90250",
    "addr:street":"W 139Th St",
    "iso:country":"US",
    "sg:address":"5131 W 139th St",
    "sg:city":"Hawthorne",
    "sg:classifiers":[
        {
            "category":"Retail",
            "subcategory":"Laundry & Dry Cleaning",
            "type":"Services"
        }
    ],
    "sg:phone":"+1 310 644 0044",
    "sg:postcode":"90250",
    "sg:province":"CA",
    "sg:tags":[
        "cleaners",
        "rug",
        "carpet"
    ],
    "wof:name":"Raggedy Annes Cleaning Svc",
    "wof:placetype":"venue"
},
  "geometry": {"coordinates":[-118.369173,33.905272],"type":"Point"}
}