{
  "type": "Feature",
  "properties": {
    "iso:country":"US",
    "sg:address":"2670 E Gage Ave",
    "sg:city":"Huntington Park",
    "sg:classifiers":[
        {
            "category":"Food & Beverages",
            "subcategory":"Bakery",
            "type":"Retail Goods"
        }
    ],
    "sg:phone":"+1 323 583 2080",
    "sg:postcode":"90255",
    "sg:province":"CA",
    "sg:tags":[
        "doughnut"
    ],
    "wof:name":"Rainbow Donuts",
    "wof:placetype":"venue"
},
  "geometry": {"coordinates":[-118.223015,33.98157],"type":"Point"}
}