{
  "type": "Feature",
  "properties": {
    "iso:country":"US",
    "sg:address":"863 Powell St",
    "sg:city":"Hollister",
    "sg:classifiers":[
        {
            "category":"Building & Trades",
            "subcategory":"Construction",
            "type":"Services"
        }
    ],
    "sg:phone":"+1 831 637 2359",
    "sg:postcode":"95023",
    "sg:province":"CA",
    "sg:tags":[
        "painter"
    ],
    "wof:name":"Custom Painting By Chris",
    "wof:placetype":"venue"
},
  "geometry": {"coordinates":[-121.407779,36.845701],"type":"Point"}
}