{
  "type": "Feature",
  "properties": {
    "iso:country":"US",
    "sg:address":"350 Cambridge Ave",
    "sg:city":"Palo Alto",
    "sg:classifiers":[
        {
            "category":"Education",
            "subcategory":"Special Training",
            "type":"Public Place"
        }
    ],
    "sg:phone":"+1 650 321 1867",
    "sg:postcode":"94306",
    "sg:province":"CA",
    "sg:tags":[
        "school",
        "language"
    ],
    "sg:website":"www.languagego.com",
    "wof:name":"Language Studies Institute",
    "wof:placetype":"venue"
},
  "geometry": {"coordinates":[-122.144216,37.4288],"type":"Point"}
}