{
  "type": "Feature",
  "properties": {
    "iso:country":"US",
    "sg:address":"2480 Mission Street Suite 323",
    "sg:city":"San Francisco",
    "sg:classifiers":[
        {
            "category":"Health Services",
            "subcategory":"Dentist",
            "type":"Services"
        }
    ],
    "sg:phone":"+1 415 648 3200",
    "sg:postcode":"94110",
    "sg:province":"CA",
    "sg:tags":[
        "orthodontist"
    ],
    "wof:name":"Michael J Horii DDS",
    "wof:placetype":"venue"
},
  "geometry": {"coordinates":[-122.418999,37.757401],"type":"Point"}
}