{
  "type": "Feature",
  "properties": {
    "addr:full":"7365 Greenbush Ave North Hollywood CA 91605",
    "addr:housenumber":"7365",
    "addr:postcode":"91605",
    "addr:street":"Greenbush Ave",
    "iso:country":"US",
    "sg:address":"7365 Greenbush Ave",
    "sg:city":"North Hollywood",
    "sg:classifiers":[
        {
            "category":"Building & Trades",
            "subcategory":"Construction",
            "type":"Services"
        }
    ],
    "sg:phone":"+1 818 982 5500",
    "sg:postcode":"91605",
    "sg:province":"CA",
    "sg:tags":[
        "contractor"
    ],
    "wof:name":"Hammer & Trowel Builders Inc",
    "wof:placetype":"venue"
},
  "geometry": {"coordinates":[-118.426272,34.205607],"type":"Point"}
}