{
  "type": "Feature",
  "properties": {
    "iso:country":"US",
    "sg:address":"45 Moana Cir",
    "sg:city":"Tahoma",
    "sg:classifiers":[
        {
            "category":"Professional",
            "type":"Services"
        }
    ],
    "sg:phone":"+1 530 525 0906",
    "sg:postcode":"96161",
    "sg:province":"CA",
    "sg:tags":[
        "establishment"
    ],
    "wof:name":"Moynihan & Moynihan",
    "wof:placetype":"venue"
},
  "geometry": {"coordinates":[-120.139981,39.070973],"type":"Point"}
}