{
  "type": "Feature",
  "properties": {
    "addr:full":"11257 National Blvd Ste 2 Los Angeles CA 90034",
    "addr:housenumber":"11257",
    "addr:postcode":"90034",
    "addr:street":"National Blvd Ste 2",
    "iso:country":"US",
    "sg:address":"11257 National Blvd Ste 2",
    "sg:city":"Los Angeles",
    "sg:classifiers":[
        {
            "category":"Personal",
            "type":"Services"
        },
        {
            "category":"Professional",
            "subcategory":"Art Services",
            "type":"Services"
        }
    ],
    "sg:phone":"+1 818 308 4393",
    "sg:postcode":"90034",
    "sg:province":"CA",
    "sg:tags":[
        "photographer",
        "home"
    ],
    "sg:website":"www.youinpictures.net",
    "wof:name":"You...In Pictures!",
    "wof:placetype":"venue"
},
  "geometry": {"coordinates":[-118.430066,34.026836],"type":"Point"}
}