{
  "type": "Feature",
  "properties": {
    "iso:country":"US",
    "sg:address":"2135 Montebello Town Center",
    "sg:city":"Montebello",
    "sg:classifiers":[
        {
            "category":"Shopping",
            "subcategory":"Clothing, Apparel, & Fashions",
            "type":"Retail Goods"
        }
    ],
    "sg:phone":"+1 323 722 2712",
    "sg:postcode":"90640",
    "sg:province":"CA",
    "wof:name":"Rave 606",
    "wof:placetype":"venue"
},
  "geometry": {"coordinates":[-118.087397,34.035885],"type":"Point"}
}