{
  "type": "Feature",
  "properties": {
    "iso:country":"US",
    "sg:address":"1625 Centinela Ave",
    "sg:city":"Inglewood",
    "sg:classifiers":[
        {
            "category":"Wholesale",
            "subcategory":"Construction Materials",
            "type":"Manufacturing & Wholesale Goods"
        },
        {
            "category":"Manufacturing",
            "subcategory":"Retail Goods",
            "type":"Manufacturing & Wholesale Goods"
        }
    ],
    "sg:phone":"+1 310 417 3458",
    "sg:postcode":"90302",
    "sg:province":"CA",
    "sg:tags":[
        "wooden",
        "pallet",
        "assembly",
        "fabricating"
    ],
    "wof:name":"Investments In Action Inc",
    "wof:placetype":"venue"
},
  "geometry": {"coordinates":[-118.368197,33.977059],"type":"Point"}
}