{
  "type": "Feature",
  "properties": {
    "addr:full":"2616 Union Ave San Jose CA 95124",
    "addr:housenumber":"2616",
    "addr:postcode":"95124",
    "addr:street":"Union Ave",
    "iso:country":"US",
    "sg:address":"2616 Union Ave",
    "sg:city":"San Jose",
    "sg:classifiers":[
        {
            "category":"Restaurant",
            "type":"Food & Drink"
        }
    ],
    "sg:phone":"+1 408 377 0254",
    "sg:postcode":"95124",
    "sg:province":"CA",
    "wof:name":"Taqueria Rincon Alteno",
    "wof:placetype":"venue"
},
  "geometry": {"coordinates":[-121.933998,37.2743],"type":"Point"}
}