{
  "type": "Feature",
  "properties": {
    "addr:full":"11370 Amalgam Way Rancho Cordova CA 95670",
    "addr:postcode":"11370;95670",
    "addr:street":"Amalgam Way",
    "iso:country":"US",
    "sg:address":"11370 Amalgam Way",
    "sg:city":"Rancho Cordova",
    "sg:classifiers":[
        {
            "category":"Building & Trades",
            "subcategory":"Landscaping Services",
            "type":"Services"
        }
    ],
    "sg:phone":"+1 916 638 2545",
    "sg:postcode":"95670",
    "sg:province":"CA",
    "sg:tags":[
        "landscape",
        "contractor"
    ],
    "wof:name":"Brooktree Landscaping Co",
    "wof:placetype":"venue"
},
  "geometry": {"coordinates":[-121.26006599999999,38.61606],"type":"Point"}
}