{
  "type": "Feature",
  "properties": {
    "addr:full":"112 N 2nd St La Puente CA 91744",
    "addr:housenumber":"112",
    "addr:postcode":"91744",
    "addr:street":"N 2Nd St",
    "iso:country":"US",
    "sg:address":"112 N 2nd St",
    "sg:city":"La Puente",
    "sg:classifiers":[
        {
            "category":"Professional",
            "subcategory":"Detective & Security Services",
            "type":"Services"
        }
    ],
    "sg:phone":"+1 626 937 6184",
    "sg:postcode":"91744",
    "sg:province":"CA",
    "sg:tags":[
        "guard",
        "patrol"
    ],
    "wof:name":"Event Protection",
    "wof:placetype":"venue"
},
  "geometry": {"coordinates":[-117.951436,34.021581],"type":"Point"}
}