{
  "type": "Feature",
  "properties": {
    "addr:full":"262 Alden Ct Windsor CA 95492",
    "addr:housenumber":"262",
    "addr:postcode":"95492",
    "addr:street":"Alden Ct",
    "iso:country":"US",
    "sg:address":"262 Alden Ct",
    "sg:city":"Windsor",
    "sg:classifiers":[
        {
            "category":"Retail",
            "subcategory":"Laundry & Dry Cleaning",
            "type":"Services"
        }
    ],
    "sg:phone":"+1 707 836 7760",
    "sg:postcode":"95492",
    "sg:province":"CA",
    "sg:tags":[
        "cleaner"
    ],
    "wof:name":"Dry Cleaning To Your Door",
    "wof:placetype":"venue"
},
  "geometry": {"coordinates":[-122.801062,38.545521],"type":"Point"}
}