{
  "type": "Feature",
  "properties": {
    "addr:full":"530 12st Sacramento CA 95814",
    "addr:housenumber":"530",
    "addr:postcode":"95814",
    "addr:street":"12St",
    "iso:country":"US",
    "sg:address":"530 12st",
    "sg:city":"Sacramento",
    "sg:classifiers":[
        {
            "category":"Sports & Exercise",
            "subcategory":"Gym",
            "type":"Entertainment"
        }
    ],
    "sg:phone":"+1 901 338 7529",
    "sg:postcode":"95814",
    "sg:province":"CA",
    "sg:tags":[
        "trainer"
    ],
    "sg:website":"reynoldsperformance.com",
    "wof:name":"Reynolds Performance Personal Training",
    "wof:placetype":"venue"
},
  "geometry": {"coordinates":[-121.48868,38.584585],"type":"Point"}
}