{
  "type": "Feature",
  "properties": {
    "iso:country":"US",
    "sg:address":"174 Evergreen Ave",
    "sg:city":"Daly City",
    "sg:classifiers":[
        {
            "category":"Building & Trades",
            "subcategory":"Landscaping Services",
            "type":"Services"
        }
    ],
    "sg:phone":"+1 415 756 4810",
    "sg:postcode":"94014",
    "sg:province":"CA",
    "sg:website":"TGLANDSCAPINGANDMORE.COM",
    "wof:name":"T&G Landscaping",
    "wof:placetype":"venue"
},
  "geometry": {"coordinates":[-122.456402,37.706188],"type":"Point"}
}