{
  "type": "Feature",
  "properties": {
    "addr:full":"2600 Franklin Canyon Drive Beverly Hills CA 90210",
    "addr:housenumber":"2600",
    "addr:postcode":"90210",
    "addr:street":"Franklin Canyon Drive",
    "iso:country":"US",
    "sg:address":"2600 Franklin Canyon Drive",
    "sg:city":"Beverly Hills",
    "sg:classifiers":[
        {
            "category":"Park",
            "type":"Public Place"
        }
    ],
    "sg:phone":"+1 310 858 0417",
    "sg:postcode":"90210",
    "sg:province":"CA",
    "wof:name":"William O Douglas Outdoors Classroom",
    "wof:placetype":"venue"
},
  "geometry": {"coordinates":[-118.41174700000001,34.120773],"type":"Point"}
}