{
  "type": "Feature",
  "properties": {
    "addr:full":"545 Sutter St San Francisco CA 94102",
    "addr:housenumber":"545",
    "addr:postcode":"94102",
    "addr:street":"Sutter St",
    "iso:country":"US",
    "sg:address":"545 Sutter St",
    "sg:city":"San Francisco",
    "sg:classifiers":[
        {
            "category":"Education",
            "subcategory":"College",
            "type":"Public Place"
        }
    ],
    "sg:phone":"+1 415 397 4929",
    "sg:postcode":"94102",
    "sg:province":"CA",
    "sg:tags":[
        "academic",
        "school"
    ],
    "sg:website":"www.greatwesternuniversity.org",
    "wof:name":"Great Western University",
    "wof:placetype":"venue"
},
  "geometry": {"coordinates":[-122.409645,37.789036],"type":"Point"}
}