{
  "type": "Feature",
  "properties": {
    "addr:full":"5353 E Appian Way Long Beach CA 90803",
    "addr:housenumber":"5353",
    "addr:postcode":"90803",
    "addr:street":"E Appian Way",
    "iso:country":"US",
    "sg:address":"5353 E Appian Way",
    "sg:city":"Long Beach",
    "sg:classifiers":[
        {
            "category":"Professional",
            "subcategory":"Employment Agencies",
            "type":"Services"
        }
    ],
    "sg:phone":"+1 562 434 0100",
    "sg:postcode":"90803",
    "sg:province":"CA",
    "sg:tags":[
        "modeling"
    ],
    "wof:name":"Unity Talent Management",
    "wof:placetype":"venue"
},
  "geometry": {"coordinates":[-118.12591399999999,33.76282],"type":"Point"}
}