{
  "type": "Feature",
  "properties": {
    "iso:country":"US",
    "sg:address":"901 Chevy St",
    "sg:city":"Belmont",
    "sg:classifiers":[
        {
            "category":"Personal",
            "type":"Services"
        }
    ],
    "sg:phone":"+1 650 483 4694",
    "sg:postcode":"94002",
    "sg:province":"CA",
    "sg:tags":[
        "home"
    ],
    "wof:name":"Playhouses Etc.",
    "wof:placetype":"venue"
},
  "geometry": {"coordinates":[-122.28927899999999,37.514501],"type":"Point"}
}