{
  "type": "Feature",
  "properties": {
    "addr:full":"1100 Davis St San Leandro CA 94577",
    "addr:housenumber":"1100",
    "addr:postcode":"94577",
    "addr:street":"Davis St",
    "iso:country":"US",
    "sg:address":"1100 Davis St",
    "sg:city":"San Leandro",
    "sg:classifiers":[
        {
            "category":"Retail",
            "subcategory":"Storage",
            "type":"Services"
        }
    ],
    "sg:phone":"+1 510 545 4583",
    "sg:postcode":"94577",
    "sg:province":"CA",
    "sg:tags":[
        "self"
    ],
    "sg:website":"www.storquest.com",
    "wof:name":"StorQuest Self Storage",
    "wof:placetype":"venue"
},
  "geometry": {"coordinates":[-122.16834,37.722223],"type":"Point"}
}