{
  "type": "Feature",
  "properties": {
    "iso:country":"US",
    "sg:address":"317 S Broadway",
    "sg:city":"Los Angeles",
    "sg:classifiers":[
        {
            "category":"Restaurant",
            "type":"Food & Drink"
        }
    ],
    "sg:phone":"+1 213 680 3363",
    "sg:postcode":"90013",
    "sg:province":"CA",
    "wof:name":"Jose Chiquito",
    "wof:placetype":"venue"
},
  "geometry": {"coordinates":[-118.248001,34.050701],"type":"Point"}
}