{
  "type": "Feature",
  "properties": {
    "addr:full":"1815 Ygnacio Valley Rd Walnut Creek CA 94598",
    "addr:housenumber":"1815",
    "addr:postcode":"94598",
    "addr:street":"Ygnacio Valley Rd",
    "iso:country":"US",
    "sg:address":"1815 Ygnacio Valley Rd",
    "sg:city":"Walnut Creek",
    "sg:classifiers":[
        {
            "category":"Food & Beverages",
            "subcategory":"Fruits & Vegetables",
            "type":"Retail Goods"
        }
    ],
    "sg:phone":"+1 925 256 7882",
    "sg:postcode":"94598",
    "sg:province":"CA",
    "sg:tags":[
        "juice"
    ],
    "wof:name":"Planet Juice",
    "wof:placetype":"venue"
},
  "geometry": {"coordinates":[-122.03879499999999,37.918067],"type":"Point"}
}