{
  "type": "Feature",
  "properties": {
    "iso:country":"US",
    "sg:address":"133 E de la Guerra St",
    "sg:city":"Santa Barbara",
    "sg:classifiers":[
        {
            "category":"Manufacturing",
            "subcategory":"Tools & Machinery",
            "type":"Manufacturing & Wholesale Goods"
        }
    ],
    "sg:phone":"+1 805 682 5166",
    "sg:postcode":"93101",
    "sg:province":"CA",
    "sg:tags":[
        "lubricating",
        "system",
        "devices"
    ],
    "wof:name":"Torr Lube Co",
    "wof:placetype":"venue"
},
  "geometry": {"coordinates":[-119.69749400000001,34.421738],"type":"Point"}
}