{
  "type": "Feature",
  "properties": {
    "iso:country":"US",
    "sg:address":"15975 Mandan Rd",
    "sg:city":"Apple Valley",
    "sg:classifiers":[
        {
            "category":"Arts & Performance",
            "subcategory":"Theater",
            "type":"Entertainment"
        }
    ],
    "sg:phone":"+1 760 242 3039",
    "sg:postcode":"92307",
    "sg:province":"CA",
    "sg:tags":[
        "clown"
    ],
    "wof:name":"Clowns Unlimited",
    "wof:placetype":"venue"
},
  "geometry": {"coordinates":[-117.23982599999999,34.543078],"type":"Point"}
}