{
  "type": "Feature",
  "properties": {
    "addr:full":"2727 Kansas Ave Riverside CA 92507",
    "addr:housenumber":"2727",
    "addr:postcode":"92507",
    "addr:street":"Kansas Ave",
    "iso:country":"US",
    "sg:address":"2727 Kansas Ave",
    "sg:city":"Riverside",
    "sg:classifiers":[
        {
            "category":"Autos & Motor Vehicles",
            "subcategory":"Automobile Sales",
            "type":"Retail Goods"
        },
        {
            "category":"Autos & Motor Vehicles",
            "subcategory":"Auto Supplies",
            "type":"Retail Goods"
        },
        {
            "category":"Utilities",
            "subcategory":"Recycling",
            "type":"Services"
        }
    ],
    "sg:phone":"+1 951 276 1687",
    "sg:postcode":"92507",
    "sg:province":"CA",
    "sg:tags":[
        "accessories-wholesale",
        "part",
        "parts",
        "salvage",
        "manufacturer"
    ],
    "wof:name":"The Recycler Core Company Inc",
    "wof:placetype":"venue"
},
  "geometry": {"coordinates":[-117.357215,33.987719],"type":"Point"}
}