{
  "type": "Feature",
  "properties": {
    "iso:country":"US",
    "sg:address":"2701 E Chapman Ave",
    "sg:city":"Fullerton",
    "sg:classifiers":[
        {
            "category":"Shopping",
            "subcategory":"Bicycles & Sporting Goods",
            "type":"Retail Goods"
        }
    ],
    "sg:phone":"+1 714 278 9397",
    "sg:postcode":"92831",
    "sg:province":"CA",
    "wof:name":"Top Gunretail Services",
    "wof:placetype":"venue"
},
  "geometry": {"coordinates":[-117.883204,33.874347],"type":"Point"}
}