{
  "type": "Feature",
  "properties": {
    "addr:full":"1036 West Capitol Avenue West Sacramento CA 95691",
    "addr:housenumber":"1036",
    "addr:postcode":"95691",
    "addr:street":"West Capitol Avenue",
    "iso:country":"US",
    "sg:address":"1036 West Capitol Avenue",
    "sg:city":"West Sacramento",
    "sg:classifiers":[
        {
            "category":"Restaurant",
            "type":"Food & Drink"
        }
    ],
    "sg:postcode":"95691",
    "sg:province":"CA",
    "sg:tags":[
        "breakfast",
        "brunch"
    ],
    "wof:name":"Blue Blizz Yogurt",
    "wof:placetype":"venue"
},
  "geometry": {"coordinates":[-121.51957899999999,38.582156],"type":"Point"}
}