{
  "type": "Feature",
  "properties": {
    "iso:country":"US",
    "sg:address":"138 Marion Trl",
    "sg:city":"Chester",
    "sg:classifiers":[
        {
            "category":"Retail",
            "subcategory":"Auto Repair",
            "type":"Services"
        }
    ],
    "sg:phone":"+1 530 258 2820",
    "sg:postcode":"96020",
    "sg:province":"CA",
    "sg:tags":[
        "repairing",
        "automobile"
    ],
    "wof:name":"Jones Auto & Truck Repair",
    "wof:placetype":"venue"
},
  "geometry": {"coordinates":[-121.21420999999999,40.242437],"type":"Point"}
}