{
  "type": "Feature",
  "properties": {
    "addr:full":"1 Maritime Plaza San Francisco CA 94111",
    "addr:housenumber":"1",
    "addr:postcode":"94111",
    "addr:street":"Maritime Plaza San Francisco",
    "iso:country":"US",
    "sg:address":"1 Maritime Plaza",
    "sg:city":"San Francisco",
    "sg:classifiers":[
        {
            "category":"Professional",
            "subcategory":"Lawyer & Legal Services",
            "type":"Services"
        }
    ],
    "sg:phone":"+1 415 434 4484",
    "sg:postcode":"94111",
    "sg:province":"CA",
    "wof:name":"Foley & Lardner",
    "wof:placetype":"venue"
},
  "geometry": {"coordinates":[-122.399002,37.795502],"type":"Point"}
}