{
  "type": "Feature",
  "properties": {
    "addr:full":"9070 Irvine Center Dr Irvine CA 92618",
    "addr:housenumber":"9070",
    "addr:postcode":"92618",
    "addr:street":"Irvine Center Dr",
    "iso:country":"US",
    "sg:address":"9070 Irvine Center Dr",
    "sg:city":"Irvine",
    "sg:classifiers":[
        {
            "category":"Professional",
            "subcategory":"Computer Services",
            "type":"Services"
        }
    ],
    "sg:phone":"+1 949 336 6666",
    "sg:postcode":"92618",
    "sg:province":"CA",
    "sg:tags":[
        "repair"
    ],
    "sg:website":"www.celergynetworks.com",
    "wof:name":"Celergy Networks",
    "wof:placetype":"venue"
},
  "geometry": {"coordinates":[-117.74048500000001,33.637109],"type":"Point"}
}