{
  "type": "Feature",
  "properties": {
    "iso:country":"US",
    "sg:address":"13326 Burbank Blvd",
    "sg:city":"Sherman Oaks",
    "sg:classifiers":[
        {
            "category":"Shopping",
            "subcategory":"Clothing, Apparel, & Fashions",
            "type":"Retail Goods"
        }
    ],
    "sg:phone":"+1 818 787 6113",
    "sg:postcode":"91401",
    "sg:province":"CA",
    "wof:name":"Carolina Fashion",
    "wof:placetype":"venue"
},
  "geometry": {"coordinates":[-118.424215,34.172053],"type":"Point"}
}