{
  "type": "Feature",
  "properties": {
    "addr:full":"803 S Pacific Ave San Pedro CA 90731",
    "addr:housenumber":"803",
    "addr:postcode":"90731",
    "addr:street":"S Pacific Ave",
    "iso:country":"US",
    "sg:address":"803 S Pacific Ave",
    "sg:city":"San Pedro",
    "sg:classifiers":[
        {
            "category":"Communications",
            "type":"Services"
        }
    ],
    "sg:phone":"+1 310 547 1399",
    "sg:postcode":"90731",
    "sg:province":"CA",
    "wof:name":"Rytel Communications",
    "wof:placetype":"venue"
},
  "geometry": {"coordinates":[-118.287983,33.737553],"type":"Point"}
}