{
  "type": "Feature",
  "properties": {
    "iso:country":"US",
    "sg:address":"102 Carrol Ct",
    "sg:city":"Stateline",
    "sg:classifiers":[
        {
            "category":"Communications",
            "subcategory":"Film & Video Production",
            "type":"Services"
        }
    ],
    "sg:phone":"+1 775 588 6050",
    "sg:postcode":"89449",
    "sg:province":"CA",
    "sg:tags":[
        "taping"
    ],
    "wof:name":"Stateline Video Productions",
    "wof:placetype":"venue"
},
  "geometry": {"coordinates":[-119.897481,38.98802],"type":"Point"}
}