{
  "type": "Feature",
  "properties": {
    "iso:country":"US",
    "sg:address":"362 Elm Ave",
    "sg:city":"Auburn",
    "sg:classifiers":[
        {
            "category":"Shopping",
            "subcategory":"Books",
            "type":"Retail Goods"
        }
    ],
    "sg:phone":"+1 530 823 2914",
    "sg:postcode":"95603",
    "sg:province":"CA",
    "sg:tags":[
        "dealer"
    ],
    "wof:name":"Wayside Christian Books & Gfts",
    "wof:placetype":"venue"
},
  "geometry": {"coordinates":[-121.07366,38.903676],"type":"Point"}
}