{
  "type": "Feature",
  "properties": {
    "addr:full":"13054 S Highland Ave Selma CA 93662",
    "addr:housenumber":"13054",
    "addr:postcode":"93662",
    "addr:street":"S Highland Ave",
    "iso:country":"US",
    "sg:address":"13054 S Highland Ave",
    "sg:city":"Selma",
    "sg:classifiers":[
        {
            "category":"Building & Trades",
            "subcategory":"Plumbing",
            "type":"Services"
        }
    ],
    "sg:phone":"+1 559 896 1330",
    "sg:postcode":"93662",
    "sg:province":"CA",
    "sg:tags":[
        "contractor"
    ],
    "wof:name":"Mechanical Plumbing Works Inc",
    "wof:placetype":"venue"
},
  "geometry": {"coordinates":[-119.628705,36.541236],"type":"Point"}
}