{
  "type": "Feature",
  "properties": {
    "iso:country":"US",
    "sg:address":"31300 Hawthorne St",
    "sg:city":"Menifee",
    "sg:classifiers":[
        {
            "category":"Retail",
            "subcategory":"Repair Shop",
            "type":"Services"
        }
    ],
    "sg:phone":"+1 951 679 2613",
    "sg:postcode":"92584",
    "sg:province":"CA",
    "sg:tags":[
        "piano",
        "restoration",
        "organ-tuning"
    ],
    "wof:name":"Precision Piano Service",
    "wof:placetype":"venue"
},
  "geometry": {"coordinates":[-117.212577,33.666243],"type":"Point"}
}