{
  "type": "Feature",
  "properties": {
    "addr:full":"609 S Mariposa Ave Los Angeles CA 90005",
    "addr:housenumber":"609",
    "addr:postcode":"90005",
    "addr:street":"S Mariposa Ave",
    "iso:country":"US",
    "sg:address":"609 S Mariposa Ave",
    "sg:city":"Los Angeles",
    "sg:classifiers":[
        {
            "category":"Shopping",
            "subcategory":"Clothing, Apparel, & Fashions",
            "type":"Retail Goods"
        }
    ],
    "sg:phone":"+1 213 480 0111",
    "sg:postcode":"90005",
    "sg:province":"CA",
    "sg:tags":[
        "sportswear"
    ],
    "wof:name":"Yes Slim",
    "wof:placetype":"venue"
},
  "geometry": {"coordinates":[-118.299269,34.062655],"type":"Point"}
}