{
  "type": "Feature",
  "properties": {
    "iso:country":"US",
    "sg:address":"1504 S Lexington St",
    "sg:city":"Delano",
    "sg:classifiers":[
        {
            "category":"Taxi",
            "type":"Transportation"
        }
    ],
    "sg:phone":"+1 661 721 3333",
    "sg:postcode":"93215",
    "sg:province":"CA",
    "sg:tags":[
        "taxicab"
    ],
    "wof:name":"Delano City Dial A Ride",
    "wof:placetype":"venue"
},
  "geometry": {"coordinates":[-119.237641,35.739262],"type":"Point"}
}