{
  "type": "Feature",
  "properties": {
    "iso:country":"US",
    "sg:address":"218 W Lincoln Ave",
    "sg:city":"Orange",
    "sg:classifiers":[
        {
            "category":"Building & Trades",
            "subcategory":"Construction",
            "type":"Services"
        }
    ],
    "sg:phone":"+1 714 632 6717",
    "sg:postcode":"92865",
    "sg:province":"CA",
    "sg:tags":[
        "contractor"
    ],
    "wof:name":"K D C Construction",
    "wof:placetype":"venue"
},
  "geometry": {"coordinates":[-117.854207,33.835031],"type":"Point"}
}