{
  "type": "Feature",
  "properties": {
    "addr:full":"1928 W Olympic Blvd Los Angeles CA 90006",
    "addr:housenumber":"1928",
    "addr:postcode":"90006",
    "addr:street":"W Olympic Blvd",
    "iso:country":"US",
    "sg:address":"1928 W Olympic Blvd",
    "sg:city":"Los Angeles",
    "sg:classifiers":[
        {
            "category":"Utilities",
            "subcategory":"Mobile Phone",
            "type":"Services"
        }
    ],
    "sg:phone":"+1 213 381 8050",
    "sg:postcode":"90006",
    "sg:province":"CA",
    "sg:tags":[
        "communication",
        "radiotelephone"
    ],
    "wof:name":"Sunset Cellular Downtown",
    "wof:placetype":"venue"
},
  "geometry": {"coordinates":[-118.278491,34.051001],"type":"Point"}
}