{
  "type": "Feature",
  "properties": {
    "addr:full":"31161 Niguel Rd Laguna Niguel CA 92677",
    "addr:housenumber":"31161",
    "addr:postcode":"92677",
    "addr:street":"Niguel Rd",
    "iso:country":"US",
    "sg:address":"31161 Niguel Rd",
    "sg:city":"Laguna Niguel",
    "sg:classifiers":[
        {
            "category":"Personal",
            "subcategory":"Beauty Salon",
            "type":"Services"
        }
    ],
    "sg:phone":"+1 949 661 5581",
    "sg:postcode":"92677",
    "sg:province":"CA",
    "sg:tags":[
        "manicuring"
    ],
    "wof:name":"Nail Solutions",
    "wof:placetype":"venue"
},
  "geometry": {"coordinates":[-117.707903,33.507508],"type":"Point"}
}