{
  "type": "Feature",
  "properties": {
    "addr:full":"1842 E Colorado Blvd Pasadena CA 91107",
    "addr:housenumber":"1842",
    "addr:postcode":"91107",
    "addr:street":"E Colorado Blvd",
    "iso:country":"US",
    "sg:address":"1842 E Colorado Blvd",
    "sg:city":"Pasadena",
    "sg:classifiers":[
        {
            "category":"Restaurant",
            "type":"Food & Drink"
        }
    ],
    "sg:phone":"+1 626 792 1412",
    "sg:postcode":"91107",
    "sg:province":"CA",
    "sg:tags":[
        "indonesian",
        "chinese"
    ],
    "wof:name":"Top Restaurant",
    "wof:placetype":"venue"
},
  "geometry": {"coordinates":[-118.11231600000001,34.146012],"type":"Point"}
}