{
  "type": "Feature",
  "properties": {
    "iso:country":"US",
    "sg:address":"15338 Cinnabar Ct",
    "sg:city":"Chino Hills",
    "sg:classifiers":[
        {
            "category":"Professional",
            "subcategory":"Art Services",
            "type":"Services"
        }
    ],
    "sg:phone":"+1 909 597 4394",
    "sg:postcode":"91709",
    "sg:province":"CA",
    "sg:tags":[
        "photographer"
    ],
    "sg:website":"www.peterrogersphoto.com",
    "wof:name":"Peter Rogers Photography",
    "wof:placetype":"venue"
},
  "geometry": {"coordinates":[-117.755275,33.974266],"type":"Point"}
}