{
  "type": "Feature",
  "properties": {
    "addr:full":"1318 E Florence Ave Los Angeles CA 90001",
    "addr:housenumber":"1318",
    "addr:postcode":"90001",
    "addr:street":"E Florence Ave",
    "iso:country":"US",
    "sg:address":"1318 E Florence Ave",
    "sg:city":"Los Angeles",
    "sg:classifiers":[
        {
            "category":"Health Services",
            "subcategory":"Doctor",
            "type":"Services"
        }
    ],
    "sg:phone":"+1 323 584 9525",
    "sg:postcode":"90001",
    "sg:province":"CA",
    "sg:tags":[
        "clinic"
    ],
    "wof:name":"Florence Family Clinic",
    "wof:placetype":"venue"
},
  "geometry": {"coordinates":[-118.250664,33.974686],"type":"Point"}
}