{
  "type": "Feature",
  "properties": {
    "iso:country":"US",
    "sg:address":"1008 W Brooks St",
    "sg:city":"Ontario",
    "sg:classifiers":[
        {
            "category":"Retail",
            "subcategory":"Car Wash",
            "type":"Services"
        }
    ],
    "sg:phone":"+1 909 984 0373",
    "sg:postcode":"91762",
    "sg:province":"CA",
    "sg:tags":[
        "automobile",
        "detail",
        "clean"
    ],
    "wof:name":"Galvez Detail",
    "wof:placetype":"venue"
},
  "geometry": {"coordinates":[-117.667054,34.061984],"type":"Point"}
}