{
  "type": "Feature",
  "properties": {
    "addr:full":"361 S Fairfax Ave Los Angeles CA 90036",
    "addr:housenumber":"361",
    "addr:postcode":"90036",
    "addr:street":"S Fairfax Ave",
    "iso:country":"US",
    "sg:address":"361 S Fairfax Ave",
    "sg:city":"Los Angeles",
    "sg:classifiers":[
        {
            "category":"Bars & Pubs",
            "type":"Food & Drink"
        },
        {
            "category":"Bars & Pubs",
            "subcategory":"Wine Bar",
            "type":"Food & Drink"
        }
    ],
    "sg:phone":"+1 323 651 1442",
    "sg:postcode":"90036",
    "sg:province":"CA",
    "wof:name":"Sheddy's",
    "wof:placetype":"venue"
},
  "geometry": {"coordinates":[-118.361418,34.070359],"type":"Point"}
}