{
  "type": "Feature",
  "properties": {
    "addr:full":"31681 Riverside Dr Lake Elsinore CA 92530",
    "addr:housenumber":"31681",
    "addr:postcode":"92530",
    "addr:street":"Riverside Dr",
    "iso:country":"US",
    "sg:address":"31681 Riverside Dr",
    "sg:city":"Lake Elsinore",
    "sg:classifiers":[
        {
            "category":"Health Services",
            "subcategory":"Health Practitioner",
            "type":"Services"
        }
    ],
    "sg:phone":"+1 951 471 5156",
    "sg:postcode":"92530",
    "sg:province":"CA",
    "sg:tags":[
        "acupuncture"
    ],
    "wof:name":"Cc Acupuncture Clinic",
    "wof:placetype":"venue"
},
  "geometry": {"coordinates":[-117.370186,33.680506],"type":"Point"}
}