{
  "type": "Feature",
  "properties": {
    "addr:full":"1032 Stoneridge Mall Rd Pleasanton CA 94588",
    "addr:housenumber":"1032",
    "addr:postcode":"94588",
    "addr:street":"Stoneridge Mall Rd",
    "iso:country":"US",
    "sg:address":"1032 Stoneridge Mall Rd",
    "sg:city":"Pleasanton",
    "sg:classifiers":[
        {
            "category":"Shopping",
            "type":"Retail Goods"
        }
    ],
    "sg:phone":"+1 925 225 0270",
    "sg:postcode":"94588",
    "sg:province":"CA",
    "sg:tags":[
        "perfume"
    ],
    "wof:name":"Perfumania",
    "wof:placetype":"venue"
},
  "geometry": {"coordinates":[-121.924352,37.693951],"type":"Point"}
}