{
  "type": "Feature",
  "properties": {
    "iso:country":"US",
    "sg:address":"1054 Mar Vista Dr",
    "sg:city":"Vista",
    "sg:classifiers":[
        {
            "category":"Farming",
            "subcategory":"Nursery",
            "type":"Manufacturing & Wholesale Goods"
        },
        {
            "category":"Shopping",
            "subcategory":"Crafts & Fabrics",
            "type":"Retail Goods"
        }
    ],
    "sg:phone":"+1 760 940 0346",
    "sg:postcode":"92081",
    "sg:province":"CA",
    "sg:tags":[
        "florists'",
        "supply",
        "equipment",
        "florist",
        "supplies-wholesale",
        "growers'",
        "manufacturer"
    ],
    "wof:name":"United Plant Growers, Inc.",
    "wof:placetype":"venue"
},
  "geometry": {"coordinates":[-117.243756,33.178105],"type":"Point"}
}