{
  "type": "Feature",
  "properties": {
    "addr:full":"2505 Samaritan Dr San Jose CA 95124",
    "addr:housenumber":"2505",
    "addr:postcode":"95124",
    "addr:street":"Samaritan Dr",
    "iso:country":"US",
    "sg:address":"2505 Samaritan Dr",
    "sg:city":"San Jose",
    "sg:classifiers":[
        {
            "category":"Health Services",
            "subcategory":"Doctor",
            "type":"Services"
        }
    ],
    "sg:phone":"+1 408 356 9900",
    "sg:postcode":"95124",
    "sg:province":"CA",
    "wof:name":"Vrittamani Latha M.D.",
    "wof:placetype":"venue"
},
  "geometry": {"coordinates":[-121.94973899999999,37.251422],"type":"Point"}
}