{
  "type": "Feature",
  "properties": {
    "iso:country":"US",
    "sg:address":"665 Pine Ave",
    "sg:city":"Pacific Grove",
    "sg:classifiers":[
        {
            "category":"Social Services",
            "type":"Services"
        }
    ],
    "sg:phone":"+1 831 646 0293",
    "sg:postcode":"93950",
    "sg:province":"CA",
    "sg:tags":[
        "counselor",
        "marriage",
        "family"
    ],
    "wof:name":"Lloyd Parker",
    "wof:placetype":"venue"
},
  "geometry": {"coordinates":[-121.921292,36.619451],"type":"Point"}
}