{
  "type": "Feature",
  "properties": {
    "addr:full":"12103 Beach Blvd Stanton CA 90680",
    "addr:housenumber":"12103",
    "addr:postcode":"ca 90680",
    "addr:street":"Beach Blvd",
    "iso:country":"US",
    "sg:address":"12103 Beach Blvd",
    "sg:city":"Stanton",
    "sg:classifiers":[
        {
            "category":"Shopping",
            "subcategory":"Tobacco",
            "type":"Retail Goods"
        }
    ],
    "sg:phone":"+1 714 894 3134",
    "sg:postcode":"90680",
    "sg:province":"CA",
    "sg:tags":[
        "shop"
    ],
    "wof:name":"S & I Tobacco Center",
    "wof:placetype":"venue"
},
  "geometry": {"coordinates":[-117.993184,33.787087],"type":"Point"}
}