{
  "type": "Feature",
  "properties": {
    "iso:country":"US",
    "sg:address":"1340 Woolner Ave",
    "sg:city":"Fairfield",
    "sg:classifiers":[
        {
            "category":"Freight",
            "type":"Transportation"
        }
    ],
    "sg:phone":"+1 707 425 8495",
    "sg:postcode":"94533",
    "sg:province":"CA",
    "sg:tags":[
        "local",
        "storage",
        "trucking"
    ],
    "wof:name":"Solano Moving & Storage Co",
    "wof:placetype":"venue"
},
  "geometry": {"coordinates":[-122.05351,38.245206],"type":"Point"}
}