{
  "type": "Feature",
  "properties": {
    "addr:full":"85266 Cairo St Coachella CA 92236",
    "addr:housenumber":"85266",
    "addr:postcode":"92236",
    "addr:street":"Cairo St",
    "iso:country":"US",
    "sg:address":"85266 Cairo St",
    "sg:city":"Coachella",
    "sg:classifiers":[
        {
            "category":"Wholesale",
            "subcategory":"Apparel",
            "type":"Manufacturing & Wholesale Goods"
        }
    ],
    "sg:phone":"+1 760 398 0454",
    "sg:postcode":"92236",
    "sg:province":"CA",
    "sg:tags":[
        "clothing"
    ],
    "wof:name":"JP Sports & More",
    "wof:placetype":"venue"
},
  "geometry": {"coordinates":[-116.177836,33.672437],"type":"Point"}
}