{
  "type": "Feature",
  "properties": {
    "iso:country":"US",
    "sg:address":"17851 Scaroni Ave",
    "sg:city":"Shafter",
    "sg:phone":"+1 661 746 4887",
    "sg:postcode":"93263",
    "sg:province":"CA",
    "sg:tags":[
        "farm",
        "cotton"
    ],
    "wof:name":"Harvey Funk",
    "wof:placetype":"venue"
},
  "geometry": {"coordinates":[-119.31382600000001,35.505373],"type":"Point"}
}