{
  "type": "Feature",
  "properties": {
    "addr:full":"1675 W Mission Blvd Pomona CA 91766",
    "addr:housenumber":"1675",
    "addr:postcode":"91766",
    "addr:street":"W Mission Blvd",
    "iso:country":"US",
    "sg:address":"1675 W Mission Blvd",
    "sg:city":"Pomona",
    "sg:classifiers":[
        {
            "category":"Manufacturing",
            "subcategory":"Pet Food",
            "type":"Manufacturing & Wholesale Goods"
        },
        {
            "category":"Wholesale",
            "subcategory":"Groceries",
            "type":"Manufacturing & Wholesale Goods"
        }
    ],
    "sg:phone":"+1 909 620 6016",
    "sg:postcode":"91766",
    "sg:province":"CA",
    "sg:tags":[
        "mfg"
    ],
    "sg:website":"www.nutroproducts.com",
    "wof:name":"Nutro Products Inc",
    "wof:placetype":"venue"
},
  "geometry": {"coordinates":[-117.778811,34.05386],"type":"Point"}
}