{
  "type": "Feature",
  "properties": {
    "addr:full":"438 E Meats Ave Orange CA 92865",
    "addr:housenumber":"438",
    "addr:postcode":"92865",
    "addr:street":"E Meats Ave",
    "iso:country":"US",
    "sg:address":"438 E Meats Ave",
    "sg:city":"Orange",
    "sg:classifiers":[
        {
            "category":"Building & Trades",
            "subcategory":"Pest Control",
            "type":"Services"
        }
    ],
    "sg:phone":"+1 714 282 0553",
    "sg:postcode":"92865",
    "sg:province":"CA",
    "wof:name":"Megafume",
    "wof:placetype":"venue"
},
  "geometry": {"coordinates":[-117.84952699999999,33.822876],"type":"Point"}
}