{
  "type": "Feature",
  "properties": {
    "iso:country":"US",
    "sg:address":"113 Blazeford Gulch",
    "sg:city":"Oroville",
    "sg:classifiers":[
        {
            "category":"Building & Trades",
            "subcategory":"Construction",
            "type":"Services"
        }
    ],
    "sg:phone":"+1 530 589 4257",
    "sg:postcode":"95966",
    "sg:province":"CA",
    "sg:tags":[
        "tile",
        "dealer"
    ],
    "wof:name":"Rimrock Tile",
    "wof:placetype":"venue"
},
  "geometry": {"coordinates":[-121.45768099999999,39.436336],"type":"Point"}
}