{
  "type": "Feature",
  "properties": {
    "iso:country":"US",
    "sg:address":"3277 Foothill Dr",
    "sg:city":"Thousand Oaks",
    "sg:classifiers":[
        {
            "category":"Social Services",
            "subcategory":"Child Care",
            "type":"Services"
        }
    ],
    "sg:phone":"+1 805 379 3798",
    "sg:postcode":"91361",
    "sg:province":"CA",
    "sg:tags":[
        "center"
    ],
    "sg:website":"www.littledreamers.com",
    "wof:name":"Little Dreamers Early Chldhd",
    "wof:placetype":"venue"
},
  "geometry": {"coordinates":[-118.84034,34.164592],"type":"Point"}
}