{
  "type": "Feature",
  "properties": {
    "iso:country":"US",
    "sg:address":"10100 Rosecrans Ave",
    "sg:city":"Bellflower",
    "sg:classifiers":[
        {
            "category":"Utilities",
            "subcategory":"Cable",
            "type":"Services"
        }
    ],
    "sg:phone":"+1 562 461 0377",
    "sg:postcode":"90706",
    "sg:province":"CA",
    "sg:tags":[
        "satellite",
        "carrier"
    ],
    "wof:name":"Direct A Satellite TV",
    "wof:placetype":"venue"
},
  "geometry": {"coordinates":[-118.117557,33.901962],"type":"Point"}
}