{
  "type": "Feature",
  "properties": {
    "iso:country":"US",
    "sg:address":"1122 S 57th St",
    "sg:city":"Richmond",
    "sg:classifiers":[
        {
            "category":"Health Services",
            "subcategory":"Doctor",
            "type":"Services"
        }
    ],
    "sg:phone":"+1 415 218 4286",
    "sg:postcode":"94804",
    "sg:province":"CA",
    "sg:tags":[
        "physician",
        "surgeon"
    ],
    "wof:name":"Ihitesham Vul Haq",
    "wof:placetype":"venue"
},
  "geometry": {"coordinates":[-122.315308,37.916167],"type":"Point"}
}