{
  "type": "Feature",
  "properties": {
    "iso:country":"US",
    "sg:address":"120 Sienna Way",
    "sg:city":"San Rafael",
    "sg:classifiers":[
        {
            "category":"Recreation",
            "type":"Entertainment"
        }
    ],
    "sg:phone":"+1 415 459 7900",
    "sg:postcode":"94901",
    "sg:province":"CA",
    "sg:tags":[
        "charter",
        "boat"
    ],
    "wof:name":"Papagallo Yacht Charters",
    "wof:placetype":"venue"
},
  "geometry": {"coordinates":[-122.515304,37.985052],"type":"Point"}
}