{
  "type": "Feature",
  "properties": {
    "iso:country":"US",
    "sg:address":"28217 Newbird Dr",
    "sg:city":"Santa Clarita",
    "sg:classifiers":[
        {
            "category":"Professional",
            "subcategory":"Research",
            "type":"Services"
        }
    ],
    "sg:phone":"+1 661 296 4888",
    "sg:postcode":"91350",
    "sg:province":"CA",
    "sg:tags":[
        "environmental",
        "ecological"
    ],
    "wof:name":"Environmental Consultants LTD",
    "wof:placetype":"venue"
},
  "geometry": {"coordinates":[-118.500244,34.454564],"type":"Point"}
}