{
  "type": "Feature",
  "properties": {
    "iso:country":"US",
    "sg:address":"50 Sevilla Dr",
    "sg:city":"Los Altos",
    "sg:classifiers":[
        {
            "category":"Professional",
            "type":"Services"
        }
    ],
    "sg:phone":"+1 650 559 6055",
    "sg:postcode":"94022",
    "sg:province":"CA",
    "wof:name":"Tarnegolet LLC",
    "wof:placetype":"venue"
},
  "geometry": {"coordinates":[-122.112591,37.389754],"type":"Point"}
}