{
  "type": "Feature",
  "properties": {
    "iso:country":"US",
    "sg:address":"26801 Agoura Rd",
    "sg:city":"Agoura Hills",
    "sg:classifiers":[
        {
            "category":"Utilities",
            "subcategory":"Telephone",
            "type":"Services"
        },
        {
            "category":"Manufacturing",
            "subcategory":"Tools & Machinery",
            "type":"Manufacturing & Wholesale Goods"
        }
    ],
    "sg:phone":"+1 818 880 3500",
    "sg:postcode":"91301",
    "sg:province":"CA",
    "sg:tags":[
        "networking",
        "telecommunication",
        "mfg",
        "system",
        "computer",
        "switching"
    ],
    "sg:website":"www.alcatel.com",
    "wof:name":"Alcatel Internetworking Inc",
    "wof:placetype":"venue"
},
  "geometry": {"coordinates":[-118.708524,34.139236],"type":"Point"}
}