{
  "type": "Feature",
  "properties": {
    "iso:country":"US",
    "sg:address":"2030 Airport Rd",
    "sg:city":"Napa",
    "sg:classifiers":[
        {
            "category":"Government",
            "subcategory":"Fire Station",
            "type":"Public Place"
        },
        {
            "category":"Airline",
            "type":"Transportation"
        }
    ],
    "sg:phone":"+1 707 253 4300",
    "sg:postcode":"94558",
    "sg:province":"CA",
    "sg:tags":[
        "consultant",
        "airport",
        "protection"
    ],
    "sg:website":"http://www.nvrpolice.com",
    "wof:name":"APC - Napa County Airport",
    "wof:placetype":"venue"
},
  "geometry": {"coordinates":[-122.273375,38.219045],"type":"Point"}
}