{
  "type": "Feature",
  "properties": {
    "iso:country":"US",
    "sg:address":"5707 Catherwood Dr",
    "sg:city":"La Canada Flintridge",
    "sg:classifiers":[
        {
            "category":"Food & Beverages",
            "subcategory":"Bakery",
            "type":"Retail Goods"
        }
    ],
    "sg:phone":"+1 818 790 4751",
    "sg:postcode":"91011",
    "sg:province":"CA",
    "sg:tags":[
        "product",
        "mfg"
    ],
    "wof:name":"Elis Donut House",
    "wof:placetype":"venue"
},
  "geometry": {"coordinates":[-118.194063,34.22058],"type":"Point"}
}