{
  "type": "Feature",
  "properties": {
    "iso:country":"US",
    "sg:address":"603 Terrace Dr",
    "sg:city":"San Dimas",
    "sg:classifiers":[
        {
            "category":"Autos & Motor Vehicles",
            "subcategory":"Auto Supplies",
            "type":"Retail Goods"
        }
    ],
    "sg:phone":"+1 909 592 4118",
    "sg:postcode":"91773",
    "sg:province":"CA",
    "sg:tags":[
        "tire"
    ],
    "wof:name":"AM-Pac Tire Distr",
    "wof:placetype":"venue"
},
  "geometry": {"coordinates":[-117.816404,34.100588],"type":"Point"}
}