{
  "type": "Feature",
  "properties": {
    "addr:full":"208 Lakewood Center Mall Lakewood CA 90712",
    "addr:housenumber":"208",
    "addr:postcode":"90712",
    "addr:street":"Lakewood;Mall",
    "iso:country":"US",
    "sg:address":"208 Lakewood Center Mall",
    "sg:city":"Lakewood",
    "sg:classifiers":[
        {
            "category":"Coffee & Tea",
            "type":"Food & Drink"
        }
    ],
    "sg:menulink":"http://www.allmenus.com/ca/long-beach-lakewood/119535-starbucks-coffee/menu/",
    "sg:phone":"+1 562 531 4533",
    "sg:postcode":"90712",
    "sg:province":"CA",
    "sg:tags":[
        "american"
    ],
    "wof:name":"Starbucks Coffee",
    "wof:placetype":"venue"
},
  "geometry": {"coordinates":[-118.13833099999999,33.852231],"type":"Point"}
}