{
  "type": "Feature",
  "properties": {
    "addr:full":"10164 Woodale Ave Pacoima CA 91331",
    "addr:postcode":"10164;91331",
    "addr:street":"Woodale Ave",
    "iso:country":"US",
    "sg:address":"10164 Woodale Ave",
    "sg:city":"Pacoima",
    "sg:classifiers":[
        {
            "category":"Freight",
            "type":"Transportation"
        }
    ],
    "sg:phone":"+1 818 896 5286",
    "sg:postcode":"91331",
    "sg:province":"CA",
    "sg:tags":[
        "moving",
        "household",
        "without",
        "storage"
    ],
    "wof:name":"MST Moving Service",
    "wof:placetype":"venue"
},
  "geometry": {"coordinates":[-118.443614,34.255405],"type":"Point"}
}