{
  "type": "Feature",
  "properties": {
    "iso:country":"US",
    "sg:address":"2400 Decatur Road",
    "sg:city":"San Diego",
    "sg:classifiers":[
        {
            "category":"Freight",
            "type":"Transportation"
        }
    ],
    "sg:phone":"+1 619 222 7257",
    "sg:postcode":"92106",
    "sg:province":"CA",
    "sg:tags":[
        "shipping"
    ],
    "sg:website":"www.postalannex.com/5007",
    "wof:name":"Postal Annex",
    "wof:placetype":"venue"
},
  "geometry": {"coordinates":[-117.21619099999999,32.734844],"type":"Point"}
}