{
  "type": "Feature",
  "properties": {
    "iso:country":"US",
    "sg:address":"315 E Cotati Ave Ste B",
    "sg:city":"Cotati",
    "sg:classifiers":[
        {
            "category":"Personal",
            "subcategory":"Beauty Salon",
            "type":"Services"
        }
    ],
    "sg:phone":"+1 707 795 2002",
    "sg:postcode":"94931",
    "sg:province":"CA",
    "sg:tags":[
        "hair",
        "stylist"
    ],
    "sg:website":"http://www.medusas.com",
    "wof:name":"Medusa's",
    "wof:placetype":"venue"
},
  "geometry": {"coordinates":[-122.70105100000001,38.32796],"type":"Point"}
}