{
  "type": "Feature",
  "properties": {
    "addr:full":"16040 Harbor Blvd Fountain Valley CA 92708",
    "addr:housenumber":"16040",
    "addr:postcode":"92708",
    "addr:street":"Harbor Blvd",
    "iso:country":"US",
    "sg:address":"16040 Harbor Blvd",
    "sg:city":"Fountain Valley",
    "sg:classifiers":[
        {
            "category":"Cinema",
            "subcategory":"Movie Rental",
            "type":"Entertainment"
        },
        {
            "category":"Shopping",
            "subcategory":"Music",
            "type":"Retail Goods"
        }
    ],
    "sg:phone":"+1 714 418 1543",
    "sg:postcode":"92708",
    "sg:province":"CA",
    "sg:tags":[
        "game",
        "video",
        "dvd's"
    ],
    "wof:name":"House Of DVD's",
    "wof:placetype":"venue"
},
  "geometry": {"coordinates":[-117.91962700000001,33.730381],"type":"Point"}
}