{
  "type": "Feature",
  "properties": {
    "iso:country":"US",
    "sg:address":"18695 Newman Ave",
    "sg:city":"Riverside",
    "sg:classifiers":[
        {
            "category":"Building & Trades",
            "subcategory":"Construction",
            "type":"Services"
        }
    ],
    "sg:phone":"+1 951 850 7560",
    "sg:postcode":"92508",
    "sg:province":"CA",
    "sg:tags":[
        "excavation",
        "contractor"
    ],
    "wof:name":"Aje Backhoe & Tractor Service",
    "wof:placetype":"venue"
},
  "geometry": {"coordinates":[-117.339952,33.867141],"type":"Point"}
}