{
  "type": "Feature",
  "properties": {
    "iso:country":"US",
    "sg:address":"10962 S Main St",
    "sg:city":"Los Angeles",
    "sg:classifiers":[
        {
            "category":"Retail",
            "subcategory":"Car Wash",
            "type":"Services"
        }
    ],
    "sg:phone":"+1 323 418 1321",
    "sg:postcode":"90061",
    "sg:province":"CA",
    "wof:name":"Acapulco Hand Car Wash",
    "wof:placetype":"venue"
},
  "geometry": {"coordinates":[-118.273482,33.936133],"type":"Point"}
}