{
  "type": "Feature",
  "properties": {
    "addr:full":"1523 Rollins Rd Burlingame CA 94010",
    "addr:housenumber":"1523",
    "addr:postcode":"94010",
    "addr:street":"Rollins Rd",
    "iso:country":"US",
    "sg:address":"1523 Rollins Rd",
    "sg:city":"Burlingame",
    "sg:classifiers":[
        {
            "category":"Organizations",
            "subcategory":"Non-profit Organization",
            "type":"Services"
        }
    ],
    "sg:phone":"+1 408 367 2190",
    "sg:postcode":"94010",
    "sg:province":"CA",
    "sg:tags":[
        "information",
        "alcoholism",
        "treatment"
    ],
    "wof:name":"Camp Recovery Ctr",
    "wof:placetype":"venue"
},
  "geometry": {"coordinates":[-122.37572900000001,37.595639],"type":"Point"}
}