{
  "type": "Feature",
  "properties": {
    "addr:full":"11127 S Western Avenue Los Angeles CA 90047",
    "addr:housenumber":"11127",
    "addr:postcode":"90047",
    "addr:street":"S Western Avenue",
    "iso:country":"US",
    "sg:address":"11127 S Western Avenue",
    "sg:city":"Los Angeles",
    "sg:classifiers":[
        {
            "category":"Social Services",
            "subcategory":"Child Care",
            "type":"Services"
        }
    ],
    "sg:phone":"+1 323 757 1200",
    "sg:postcode":"90047",
    "sg:province":"CA",
    "sg:tags":[
        "day"
    ],
    "wof:name":"Ruby's Christian Academy",
    "wof:placetype":"venue"
},
  "geometry": {"coordinates":[-118.308965,33.933007],"type":"Point"}
}