{
  "type": "Feature",
  "properties": {
    "addr:full":"1033 Sierra Dr Turlock CA 95380",
    "addr:housenumber":"1033",
    "addr:postcode":"95380",
    "addr:street":"Sierra Dr",
    "iso:country":"US",
    "sg:address":"1033 Sierra Dr",
    "sg:city":"Turlock",
    "sg:classifiers":[
        {
            "category":"Travel",
            "subcategory":"Hotels & Motels",
            "type":"Entertainment"
        }
    ],
    "sg:phone":"+1 209 632 5086",
    "sg:postcode":"95380",
    "sg:province":"CA",
    "sg:tags":[
        "membership",
        "lodging"
    ],
    "wof:name":"Alpha Delta Kappa Sororit",
    "wof:placetype":"venue"
},
  "geometry": {"coordinates":[-120.834076,37.501948],"type":"Point"}
}