{
  "type": "Feature",
  "properties": {
    "iso:country":"US",
    "sg:address":"1816 4th St",
    "sg:city":"Berkeley",
    "sg:classifiers":[
        {
            "category":"Shopping",
            "subcategory":"Clothing, Apparel, & Fashions",
            "type":"Retail Goods"
        }
    ],
    "sg:phone":"+1 510 526 0350",
    "sg:postcode":"94710",
    "sg:province":"CA",
    "sg:tags":[
        "lingerie"
    ],
    "wof:name":"Isabelle",
    "wof:placetype":"venue"
},
  "geometry": {"coordinates":[-122.30103,37.871105],"type":"Point"}
}