{
  "type": "Feature",
  "properties": {
    "addr:full":"1027 Shary Ct Concord CA 94518",
    "addr:housenumber":"1027",
    "addr:postcode":"94518",
    "addr:street":"Shary Ct",
    "iso:country":"US",
    "sg:address":"1027 Shary Ct",
    "sg:city":"Concord",
    "sg:classifiers":[
        {
            "category":"Manufacturing",
            "subcategory":"Furniture",
            "type":"Manufacturing & Wholesale Goods"
        }
    ],
    "sg:phone":"+1 925 798 3250",
    "sg:postcode":"94518",
    "sg:province":"CA",
    "sg:tags":[
        "mfg",
        "plastic",
        "laminated",
        "cabinet"
    ],
    "wof:name":"Andco Plastics",
    "wof:placetype":"venue"
},
  "geometry": {"coordinates":[-122.031477,37.954947],"type":"Point"}
}