{
  "type": "Feature",
  "properties": {
    "iso:country":"US",
    "sg:address":"Corporate Headquarters 2013 Farallon Dr",
    "sg:city":"San Leandro",
    "sg:classifiers":[
        {
            "category":"Sports & Exercise",
            "subcategory":"Bicycle Rental",
            "type":"Entertainment"
        }
    ],
    "sg:phone":"+1 408 269 9300",
    "sg:postcode":"94577",
    "sg:province":"CA",
    "sg:tags":[
        "wear"
    ],
    "sg:website":"www.thenorthface.com",
    "wof:name":"The North Face",
    "wof:placetype":"venue"
},
  "geometry": {"coordinates":[-122.16513399999999,37.692853],"type":"Point"}
}