{
  "type": "Feature",
  "properties": {
    "addr:full":"1225 Innsbruck Drive Sunnyvale CA 94089 ",
    "addr:housenumber":"1225",
    "addr:postcode":"94089",
    "addr:street":"Innsbruck Drive",
    "iso:country":"US",
    "sg:address":"1225 Innsbruck Drive",
    "sg:city":"Sunnyvale",
    "sg:classifiers":[
        {
            "category":"Manufacturing",
            "subcategory":"Electronics",
            "type":"Manufacturing & Wholesale Goods"
        }
    ],
    "sg:phone":"+1 408 400 0578",
    "sg:postcode":"94089 ",
    "sg:province":"CA",
    "sg:website":"http://www.adestotech.com/",
    "wof:name":"Adesto Technologies",
    "wof:placetype":"venue"
},
  "geometry": {"coordinates":[-122.014138,37.406725],"type":"Point"}
}