{
  "type": "Feature",
  "properties": {
    "iso:country":"US",
    "sg:address":"3120 S Hacienda Blvd",
    "sg:city":"Hacienda Heights",
    "sg:classifiers":[
        {
            "category":"Health Services",
            "subcategory":"Chiropractor",
            "type":"Services"
        }
    ],
    "sg:phone":"+1 626 333 2273",
    "sg:postcode":"91745",
    "sg:province":"CA",
    "wof:name":"Lyle Hawk DC",
    "wof:placetype":"venue"
},
  "geometry": {"coordinates":[-117.972103,33.979743],"type":"Point"}
}