{
  "type": "Feature",
  "properties": {
    "addr:full":"30 Stephens Ct Orinda CA 94525",
    "addr:housenumber":"30",
    "addr:postcode":"94525",
    "addr:street":"Stephens Ct",
    "iso:country":"US",
    "sg:address":"30 Stephens Ct",
    "sg:city":"Orinda",
    "sg:classifiers":[
        {
            "category":"Professional",
            "subcategory":"Engineering",
            "type":"Services"
        }
    ],
    "sg:phone":"+1 925 284 4000",
    "sg:postcode":"94525",
    "sg:province":"CA",
    "sg:tags":[
        "general",
        "contractor"
    ],
    "wof:name":"Edward Searby Pro Engineer",
    "wof:placetype":"venue"
},
  "geometry": {"coordinates":[-122.218446,38.047328],"type":"Point"}
}