{
  "type": "Feature",
  "properties": {
    "addr:full":"2061 Business Center Drive Irvine CA 92612",
    "addr:housenumber":"2061",
    "addr:postcode":"92612",
    "addr:street":"Business Center Drive",
    "iso:country":"US",
    "sg:address":"2061 Business Center Drive",
    "sg:city":"Irvine",
    "sg:classifiers":[
        {
            "category":"Professional",
            "subcategory":"Accounting & Tax Preparation",
            "type":"Services"
        }
    ],
    "sg:phone":"+1 949 955 0555",
    "sg:postcode":"92612",
    "sg:province":"CA",
    "sg:tags":[
        "accountant"
    ],
    "wof:name":"Zarrinkelk Kashefipour and Company",
    "wof:placetype":"venue"
},
  "geometry": {"coordinates":[-117.857118,33.678329],"type":"Point"}
}