{
  "type": "Feature",
  "properties": {
    "addr:full":"1223 Fremont Blvd Ste B Seaside CA 93955",
    "addr:housenumber":"1223",
    "addr:postcode":"93955",
    "addr:street":"Fremont Blvd Ste B",
    "iso:country":"US",
    "sg:address":"1223 Fremont Blvd Ste B",
    "sg:city":"Seaside",
    "sg:phone":"+1 831 899 5214",
    "sg:postcode":"93955",
    "sg:province":"CA",
    "wof:name":"Coats Auto Body & Repair",
    "wof:placetype":"venue"
},
  "geometry": {"coordinates":[-121.84854900000001,36.603168],"type":"Point"}
}