{
  "type": "Feature",
  "properties": {
    "addr:full":"11045 Maple Ave Bloomington CA 92316",
    "addr:housenumber":"11045",
    "addr:postcode":"92316",
    "addr:street":"Maple Ave",
    "iso:country":"US",
    "sg:address":"11045 Maple Ave",
    "sg:city":"Bloomington",
    "sg:classifiers":[
        {
            "category":"Manufacturing",
            "subcategory":"Metals",
            "type":"Manufacturing & Wholesale Goods"
        }
    ],
    "sg:phone":"+1 909 877 4376",
    "sg:postcode":"92316",
    "sg:province":"CA",
    "sg:tags":[
        "steel",
        "distributor",
        "warehouse",
        "fabricated",
        "structural"
    ],
    "wof:name":"Mik-Ron Steel Co. Inc.",
    "wof:placetype":"venue"
},
  "geometry": {"coordinates":[-117.405113,34.054008],"type":"Point"}
}