{
  "type": "Feature",
  "properties": {
    "iso:country":"US",
    "sg:address":"920 Vine St Apt 71",
    "sg:city":"Oceanside",
    "sg:classifiers":[
        {
            "category":"Travel",
            "subcategory":"Hotels & Motels",
            "type":"Entertainment"
        }
    ],
    "sg:phone":"+1 760 576 6684",
    "sg:postcode":"92054",
    "sg:province":"CA",
    "wof:name":"Dog Days",
    "wof:placetype":"venue"
},
  "geometry": {"coordinates":[-117.36483800000001,33.189291],"type":"Point"}
}