{
  "type": "Feature",
  "properties": {
    "addr:full":"5310 Sierra St Riverside CA 92504",
    "addr:housenumber":"5310",
    "addr:postcode":"92504",
    "addr:street":"Sierra St",
    "iso:country":"US",
    "sg:address":"5310 Sierra St",
    "sg:city":"Riverside",
    "sg:classifiers":[
        {
            "category":"Autos & Motor Vehicles",
            "subcategory":"Fuel & Gas Station",
            "type":"Retail Goods"
        }
    ],
    "sg:phone":"+1 951 352 9400",
    "sg:postcode":"92504",
    "sg:province":"CA",
    "sg:tags":[
        "oil"
    ],
    "wof:name":"Western Gasoline",
    "wof:placetype":"venue"
},
  "geometry": {"coordinates":[-117.42247399999999,33.948957],"type":"Point"}
}