{
  "type": "Feature",
  "properties": {
    "addr:full":"42 Summit Dr Corte Madera CA 94925",
    "addr:housenumber":"42",
    "addr:postcode":"94925",
    "addr:street":"Summit Dr",
    "iso:country":"US",
    "sg:address":"42 Summit Dr",
    "sg:city":"Corte Madera",
    "sg:classifiers":[
        {
            "category":"Manufacturing",
            "subcategory":"Toys & Sporting Goods",
            "type":"Manufacturing & Wholesale Goods"
        }
    ],
    "sg:phone":"+1 415 927 3527",
    "sg:postcode":"94925",
    "sg:province":"CA",
    "sg:tags":[
        "stuffed",
        "doll"
    ],
    "wof:name":"Stone Soup Designs",
    "wof:placetype":"venue"
},
  "geometry": {"coordinates":[-122.53518699999999,37.925221],"type":"Point"}
}