{
  "type": "Feature",
  "properties": {
    "addr:full":"710 Centinela Ave Inglewood CA 90302",
    "addr:housenumber":"710",
    "addr:postcode":"90302",
    "addr:street":"Centinela Ave",
    "iso:country":"US",
    "sg:address":"710 Centinela Ave",
    "sg:city":"Inglewood",
    "sg:classifiers":[
        {
            "category":"Wholesale",
            "subcategory":"Scrap",
            "type":"Manufacturing & Wholesale Goods"
        }
    ],
    "sg:phone":"+1 310 674 6651",
    "sg:postcode":"90302",
    "sg:province":"CA",
    "sg:tags":[
        "metal",
        "iron"
    ],
    "wof:name":"Lako Enterprises",
    "wof:placetype":"venue"
},
  "geometry": {"coordinates":[-118.352603,33.975819],"type":"Point"}
}