{
  "type": "Feature",
  "properties": {
    "addr:full":"2651 Blanding Ave Ste H Alameda CA 94501",
    "addr:housenumber":"2651",
    "addr:postcode":"94501",
    "addr:street":"Blanding Ave Ste H",
    "iso:country":"US",
    "sg:address":"2651 Blanding Ave Ste H",
    "sg:city":"Alameda",
    "sg:classifiers":[
        {
            "category":"Restaurant",
            "type":"Food & Drink"
        }
    ],
    "sg:phone":"+1 510 748 8600",
    "sg:postcode":"94501",
    "sg:province":"CA",
    "sg:tags":[
        "pizza"
    ],
    "sg:website":"www.roundtablepizza.com",
    "wof:name":"Round Table Pizza",
    "wof:placetype":"venue"
},
  "geometry": {"coordinates":[-122.233313,37.768306],"type":"Point"}
}