{
  "type": "Feature",
  "properties": {
    "addr:full":"3964 30th St San Diego CA 92104",
    "addr:housenumber":"3964",
    "addr:postcode":"92104",
    "addr:street":"30Th St",
    "iso:country":"US",
    "sg:address":"3964 30th St",
    "sg:city":"San Diego",
    "sg:classifiers":[
        {
            "category":"Personal",
            "subcategory":"Beauty Salon",
            "type":"Services"
        }
    ],
    "sg:phone":"+1 619 260 1351",
    "sg:postcode":"92104",
    "sg:province":"CA",
    "wof:name":"Joan P Owens",
    "wof:placetype":"venue"
},
  "geometry": {"coordinates":[-117.13022100000001,32.749103],"type":"Point"}
}