{
  "type": "Feature",
  "properties": {
    "iso:country":"US",
    "sg:address":"1011 Main St",
    "sg:city":"Delano",
    "sg:classifiers":[
        {
            "category":"Food & Beverages",
            "subcategory":"Specialty",
            "type":"Retail Goods"
        }
    ],
    "sg:phone":"+1 661 725 8324",
    "sg:postcode":"93215",
    "sg:province":"CA",
    "sg:tags":[
        "health",
        "diet"
    ],
    "wof:name":"Sunshine Natural Source",
    "wof:placetype":"venue"
},
  "geometry": {"coordinates":[-119.245991,35.77025],"type":"Point"}
}