{
  "type": "Feature",
  "properties": {
    "iso:country":"US",
    "sg:address":"5120 Lake Isabella Blvd",
    "sg:city":"Lake Isabella",
    "sg:classifiers":[
        {
            "category":"Health Services",
            "subcategory":"Doctor",
            "type":"Services"
        }
    ],
    "sg:phone":"+1 760 379 5911",
    "sg:postcode":"93240",
    "sg:province":"CA",
    "sg:tags":[
        "dentist"
    ],
    "wof:name":"KERN Valley Dental Ctr",
    "wof:placetype":"venue"
},
  "geometry": {"coordinates":[-118.481672,35.611428],"type":"Point"}
}