{
  "type": "Feature",
  "properties": {
    "iso:country":"US",
    "sg:address":"404 Front St",
    "sg:city":"Avila Beach",
    "sg:classifiers":[
        {
            "category":"Restaurant",
            "type":"Food & Drink"
        }
    ],
    "sg:phone":"+1 805 595 7555",
    "sg:postcode":"93424",
    "sg:province":"CA",
    "wof:name":"Custom House",
    "wof:placetype":"venue"
},
  "geometry": {"coordinates":[-120.734215,35.179055],"type":"Point"}
}