{
  "type": "Feature",
  "properties": {
    "iso:country":"US",
    "sg:address":"4864 Market St",
    "sg:city":"Ventura",
    "sg:classifiers":[
        {
            "category":"Building & Trades",
            "subcategory":"Cleaning & Sanitation",
            "type":"Services"
        }
    ],
    "sg:phone":"+1 805 644 0392",
    "sg:postcode":"93003",
    "sg:province":"CA",
    "sg:tags":[
        "janitor"
    ],
    "wof:name":"Harbor Buidling Maintenance",
    "wof:placetype":"venue"
},
  "geometry": {"coordinates":[-119.225971,34.257581],"type":"Point"}
}