{
  "type": "Feature",
  "properties": {
    "iso:country":"US",
    "sg:address":"12740 Earhart Ave",
    "sg:city":"Auburn",
    "sg:classifiers":[
        {
            "category":"Wholesale",
            "subcategory":"Medical Equipment & Supplies",
            "type":"Manufacturing & Wholesale Goods"
        },
        {
            "category":"Professional",
            "subcategory":"Research",
            "type":"Services"
        }
    ],
    "sg:phone":"+1 530 888 8871",
    "sg:postcode":"95602",
    "sg:province":"CA",
    "sg:tags":[
        "res",
        "product",
        "physical",
        "commercial",
        "biotechnology"
    ],
    "wof:name":"Miltenyi Biotec Inc",
    "wof:placetype":"venue"
},
  "geometry": {"coordinates":[-121.086544,38.950681],"type":"Point"}
}