{
  "type": "Feature",
  "properties": {
    "addr:full":"14 N San Mateo Dr San Mateo CA 94401",
    "addr:housenumber":"14",
    "addr:postcode":"94401",
    "addr:street":"N San Mateo Dr",
    "iso:country":"US",
    "sg:address":"14 N San Mateo Dr",
    "sg:city":"San Mateo",
    "sg:classifiers":[
        {
            "category":"Education",
            "subcategory":"Vocational School",
            "type":"Public Place"
        }
    ],
    "sg:phone":"+1 650 685 6616",
    "sg:postcode":"94401",
    "sg:province":"CA",
    "sg:tags":[
        "technical",
        "trade"
    ],
    "wof:name":"Ca School Of Modern Science",
    "wof:placetype":"venue"
},
  "geometry": {"coordinates":[-122.326694,37.566977],"type":"Point"}
}