{
  "type": "Feature",
  "properties": {
    "addr:full":"1421 Solano St Corning CA 96021",
    "addr:housenumber":"1421",
    "addr:postcode":"96021",
    "addr:street":"Solano St",
    "iso:country":"US",
    "sg:address":"1421 Solano St",
    "sg:city":"Corning",
    "sg:classifiers":[
        {
            "category":"Autos & Motor Vehicles",
            "subcategory":"Automobile Sales",
            "type":"Retail Goods"
        }
    ],
    "sg:phone":"+1 530 824 4872",
    "sg:postcode":"96021",
    "sg:province":"CA",
    "sg:tags":[
        "car",
        "dealer"
    ],
    "wof:name":"Mike's Service",
    "wof:placetype":"venue"
},
  "geometry": {"coordinates":[-122.18520100000001,39.927843],"type":"Point"}
}