{
  "type": "Feature",
  "properties": {
    "addr:full":"5725 Alcoa Ave Los Angeles CA 90058",
    "addr:postcode":"5725;90058",
    "addr:street":"Alcoa Ave",
    "iso:country":"US",
    "sg:address":"5725 Alcoa Ave",
    "sg:city":"Los Angeles",
    "sg:classifiers":[
        {
            "category":"Shopping",
            "subcategory":"Clothing, Apparel, & Fashions",
            "type":"Retail Goods"
        },
        {
            "category":"Food & Beverages",
            "subcategory":"Farmers Market",
            "type":"Retail Goods"
        },
        {
            "category":"Food & Beverages",
            "subcategory":"Ethnic Foods",
            "type":"Retail Goods"
        }
    ],
    "sg:phone":"+1 323 582 6000",
    "sg:postcode":"90058",
    "sg:province":"CA",
    "sg:tags":[
        "clothing",
        "women's"
    ],
    "sg:website":"www.concordfarms.com",
    "wof:name":"Concord Farms",
    "wof:placetype":"venue"
},
  "geometry": {"coordinates":[-118.20934699999999,33.990577],"type":"Point"}
}