{
  "type": "Feature",
  "properties": {
    "iso:country":"US",
    "sg:address":"24355 Magic Mountain Pkwy",
    "sg:city":"Valencia",
    "sg:classifiers":[
        {
            "category":"Shopping",
            "subcategory":"Crafts & Fabrics",
            "type":"Retail Goods"
        }
    ],
    "sg:phone":"+1 661 253 4326",
    "sg:postcode":"91355",
    "sg:province":"CA",
    "sg:tags":[
        "store"
    ],
    "wof:name":"Jo-Ann Fabrics & Crafts",
    "wof:placetype":"venue"
},
  "geometry": {"coordinates":[-118.556999,34.417999],"type":"Point"}
}