{
  "type": "Feature",
  "properties": {
    "iso:country":"US",
    "sg:address":"46531 Fish Rock Rd",
    "sg:city":"Gualala",
    "sg:classifiers":[
        {
            "category":"Professional",
            "subcategory":"Detective & Security Services",
            "type":"Services"
        }
    ],
    "sg:phone":"+1 707 884 4534",
    "sg:postcode":"95445",
    "sg:province":"CA",
    "sg:tags":[
        "information",
        "bureau"
    ],
    "wof:name":"Computer Consulting Services",
    "wof:placetype":"venue"
},
  "geometry": {"coordinates":[-123.585037,38.808673],"type":"Point"}
}