{
  "type": "Feature",
  "properties": {
    "addr:full":"966 E El Camino Real Sunnyvale CA 94087",
    "addr:housenumber":"966",
    "addr:postcode":"94087",
    "addr:street":"E El Camino Real",
    "iso:country":"US",
    "sg:address":"966 E El Camino Real",
    "sg:city":"Sunnyvale",
    "sg:classifiers":[
        {
            "category":"Retail",
            "subcategory":"Auto Repair",
            "type":"Services"
        }
    ],
    "sg:phone":"+1 408 738 2318",
    "sg:postcode":"94087",
    "sg:province":"CA",
    "sg:website":"www.worldmufflers.com",
    "wof:name":"World Mufflers",
    "wof:placetype":"venue"
},
  "geometry": {"coordinates":[-122.01035400000001,37.3518],"type":"Point"}
}