{
  "type": "Feature",
  "properties": {
    "iso:country":"US",
    "sg:address":"10411 River Park Pl",
    "sg:city":"Truckee",
    "sg:classifiers":[
        {
            "category":"Retail",
            "subcategory":"Veterinary Services",
            "type":"Services"
        }
    ],
    "sg:phone":"+1 530 587 7200",
    "sg:postcode":"96161",
    "sg:province":"CA",
    "sg:tags":[
        "clinic",
        "hospital"
    ],
    "sg:website":"http://www.sierrapetclinic.com/",
    "wof:name":"Sierra Pet Clinic",
    "wof:placetype":"venue"
},
  "geometry": {"coordinates":[-120.19302999999999,39.322222],"type":"Point"}
}