{
  "type": "Feature",
  "properties": {
    "addr:full":"105 Rainbow Ln Watsonville CA 95076",
    "addr:housenumber":"105",
    "addr:postcode":"95076",
    "addr:street":"Rainbow Ln",
    "iso:country":"US",
    "sg:address":"105 Rainbow Ln",
    "sg:city":"Watsonville",
    "sg:classifiers":[
        {
            "category":"Freight",
            "type":"Transportation"
        }
    ],
    "sg:phone":"+1 831 728 3880",
    "sg:postcode":"95076",
    "sg:province":"CA",
    "sg:tags":[
        "operator",
        "local",
        "trucking"
    ],
    "wof:name":"Gutierrez Trucking",
    "wof:placetype":"venue"
},
  "geometry": {"coordinates":[-121.795709,36.965432],"type":"Point"}
}