{
  "type": "Feature",
  "properties": {
    "iso:country":"US",
    "sg:address":"1640 Florin Rd",
    "sg:city":"Sacramento",
    "sg:classifiers":[
        {
            "category":"Building & Trades",
            "subcategory":"Construction",
            "type":"Services"
        }
    ],
    "sg:phone":"+1 916 564 1471",
    "sg:postcode":"95822",
    "sg:province":"CA",
    "sg:tags":[
        "roofing",
        "contractor"
    ],
    "wof:name":"All Weather Roofing",
    "wof:placetype":"venue"
},
  "geometry": {"coordinates":[-121.501763,38.495606],"type":"Point"}
}