{
  "type": "Feature",
  "properties": {
    "iso:country":"US",
    "sg:address":"437 Figueroa St",
    "sg:city":"Monterey",
    "sg:classifiers":[
        {
            "category":"Health Services",
            "subcategory":"Health Practitioner",
            "type":"Services"
        }
    ],
    "sg:phone":"+1 831 649 1991",
    "sg:postcode":"93940",
    "sg:province":"CA",
    "sg:tags":[
        "psychologist"
    ],
    "wof:name":"Counseling Svc",
    "wof:placetype":"venue"
},
  "geometry": {"coordinates":[-121.890365,36.59813],"type":"Point"}
}