{
  "type": "Feature",
  "properties": {
    "addr:full":"1637 Spring St Paso Robles CA 93446",
    "addr:housenumber":"1637",
    "addr:postcode":"93446",
    "addr:street":"Spring St",
    "iso:country":"US",
    "sg:address":"1637 Spring St",
    "sg:city":"Paso Robles",
    "sg:classifiers":[
        {
            "category":"Food & Beverages",
            "subcategory":"Liquor & Beverages",
            "type":"Retail Goods"
        }
    ],
    "sg:phone":"+1 805 239 3387",
    "sg:postcode":"93446",
    "sg:province":"CA",
    "wof:name":"J-N-J's Liquor",
    "wof:placetype":"venue"
},
  "geometry": {"coordinates":[-120.691818,35.631484],"type":"Point"}
}