{
  "type": "Feature",
  "properties": {
    "addr:full":"109 Town and Country Dr Danville CA 94526",
    "addr:housenumber":"109",
    "addr:postcode":"94526",
    "addr:street":"Town And Country Dr",
    "iso:country":"US",
    "sg:address":"109 Town and Country Dr",
    "sg:city":"Danville",
    "sg:classifiers":[
        {
            "category":"Home & Garden",
            "subcategory":"Furniture",
            "type":"Retail Goods"
        }
    ],
    "sg:phone":"+1 925 838 1721",
    "sg:postcode":"94526",
    "sg:province":"CA",
    "wof:name":"Blue Tomatoes Home Furnishings",
    "wof:placetype":"venue"
},
  "geometry": {"coordinates":[-121.998124,37.81485],"type":"Point"}
}