{
  "type": "Feature",
  "properties": {
    "iso:country":"US",
    "sg:address":"1015 Cass St",
    "sg:city":"Monterey",
    "sg:classifiers":[
        {
            "category":"Personal",
            "subcategory":"Beauty Salon",
            "type":"Services"
        }
    ],
    "sg:phone":"+1 831 646 0689",
    "sg:postcode":"93940",
    "sg:province":"CA",
    "wof:name":"Peninsula Electrolysis",
    "wof:placetype":"venue"
},
  "geometry": {"coordinates":[-121.896829,36.591684],"type":"Point"}
}