{
  "type": "Feature",
  "properties": {
    "iso:country":"US",
    "sg:address":"6003 Kelton Ave",
    "sg:city":"La Mesa",
    "sg:classifiers":[
        {
            "category":"Manufacturing",
            "subcategory":"Electronics",
            "type":"Manufacturing & Wholesale Goods"
        }
    ],
    "sg:phone":"+1 619 460 1129",
    "sg:postcode":"91942",
    "sg:province":"CA",
    "sg:tags":[
        "equipment",
        "mfg",
        "home"
    ],
    "wof:name":"Silversmith Audio",
    "wof:placetype":"venue"
},
  "geometry": {"coordinates":[-117.016823,32.789118],"type":"Point"}
}