{
  "type": "Feature",
  "properties": {
    "addr:full":"100 Country Club San Francisco CA 94132",
    "addr:housenumber":"100",
    "addr:postcode":"94132",
    "addr:street":"Country Club",
    "iso:country":"US",
    "sg:address":"100 Country Club",
    "sg:city":"San Francisco",
    "sg:classifiers":[
        {
            "category":"Personal",
            "type":"Services"
        }
    ],
    "sg:phone":"+1 415 609 7031",
    "sg:postcode":"94132",
    "sg:province":"CA",
    "sg:tags":[
        "home"
    ],
    "sg:website":"www.bhauser.com/BHauserWaterCons...",
    "wof:name":"Robert Hauser Construction",
    "wof:placetype":"venue"
},
  "geometry": {"coordinates":[-122.49664900000001,37.729993],"type":"Point"}
}