{
  "type": "Feature",
  "properties": {
    "iso:country":"US",
    "sg:address":"753 Webster St",
    "sg:city":"Palo Alto",
    "sg:classifiers":[
        {
            "category":"Professional",
            "subcategory":"Lawyer & Legal Services",
            "type":"Services"
        }
    ],
    "sg:phone":"+1 650 325 6996",
    "sg:postcode":"94301",
    "sg:province":"CA",
    "sg:tags":[
        "attorney"
    ],
    "wof:name":"Kenneth H Nordin",
    "wof:placetype":"venue"
},
  "geometry": {"coordinates":[-122.154787,37.447637],"type":"Point"}
}