{
  "type": "Feature",
  "properties": {
    "iso:country":"US",
    "sg:address":"701 Palomar Airport Rd Ste 300",
    "sg:city":"Carlsbad",
    "sg:classifiers":[
        {
            "category":"Health Services",
            "subcategory":"Health Practitioner",
            "type":"Services"
        }
    ],
    "sg:phone":"+1 800 251 0364",
    "sg:postcode":"92011",
    "sg:province":"CA",
    "sg:tags":[
        "home",
        "care"
    ],
    "sg:website":"www.healthsecurity1.com/",
    "wof:name":"HealthSecurity1.com",
    "wof:placetype":"venue"
},
  "geometry": {"coordinates":[-117.32409199999999,33.121379],"type":"Point"}
}