{
  "type": "Feature",
  "properties": {
    "iso:country":"US",
    "sg:address":"548 E 31st St",
    "sg:city":"Los Angeles",
    "sg:classifiers":[
        {
            "category":"Shopping",
            "subcategory":"Crafts & Fabrics",
            "type":"Retail Goods"
        }
    ],
    "sg:phone":"+1 213 746 1800",
    "sg:postcode":"90011",
    "sg:province":"CA",
    "sg:tags":[
        "textile"
    ],
    "wof:name":"Omega Textiles",
    "wof:placetype":"venue"
},
  "geometry": {"coordinates":[-118.264201,34.017846],"type":"Point"}
}