{
  "type": "Feature",
  "properties": {
    "addr:full":"15153 Lester Ln Los Gatos CA 95032",
    "addr:housenumber":"15153",
    "addr:postcode":"95032",
    "addr:street":"Lester Ln",
    "iso:country":"US",
    "sg:address":"15153 Lester Ln",
    "sg:city":"Los Gatos",
    "sg:classifiers":[
        {
            "category":"Shopping",
            "subcategory":"Computers & Home Electronics",
            "type":"Retail Goods"
        }
    ],
    "sg:phone":"+1 408 358 5150",
    "sg:postcode":"95032",
    "sg:province":"CA",
    "sg:tags":[
        "software"
    ],
    "wof:name":"Royal Software",
    "wof:placetype":"venue"
},
  "geometry": {"coordinates":[-121.954365,37.249086],"type":"Point"}
}