{
  "type": "Feature",
  "properties": {
    "iso:country":"US",
    "sg:address":"445 Kenwood Dr",
    "sg:city":"Lemoore",
    "sg:classifiers":[
        {
            "category":"Organizations",
            "subcategory":"Labor Organization",
            "type":"Services"
        }
    ],
    "sg:phone":"+1 559 925 1215",
    "sg:postcode":"93245",
    "sg:province":"CA",
    "wof:name":"Calif School Employees Assn",
    "wof:placetype":"venue"
},
  "geometry": {"coordinates":[-119.797771,36.293023],"type":"Point"}
}