{
  "type": "Feature",
  "properties": {
    "iso:country":"US",
    "sg:address":"19706 E Arrow Hwy",
    "sg:city":"Covina",
    "sg:classifiers":[
        {
            "category":"Bars & Pubs",
            "subcategory":"Sports Bar",
            "type":"Food & Drink"
        }
    ],
    "sg:phone":"+1 626 915 2597",
    "sg:postcode":"91724",
    "sg:province":"CA",
    "sg:tags":[
        "hall",
        "pool"
    ],
    "wof:name":"Cue-Time Family Billiards",
    "wof:placetype":"venue"
},
  "geometry": {"coordinates":[-117.86647000000001,34.106662],"type":"Point"}
}