{
  "type": "Feature",
  "properties": {
    "addr:full":"9100 Fletcher Pkwy La Mesa CA 91942",
    "addr:housenumber":"9100",
    "addr:postcode":"91942",
    "addr:street":"Fletcher Pkwy",
    "iso:country":"US",
    "sg:address":"9100 Fletcher Pkwy",
    "sg:city":"La Mesa",
    "sg:classifiers":[
        {
            "category":"Shopping",
            "subcategory":"Bicycles & Sporting Goods",
            "type":"Retail Goods"
        }
    ],
    "sg:phone":"+1 619 465 9000",
    "sg:postcode":"91942",
    "sg:province":"CA",
    "wof:name":"Retro Sports",
    "wof:placetype":"venue"
},
  "geometry": {"coordinates":[-117.002202,32.792861],"type":"Point"}
}