{
  "type": "Feature",
  "properties": {
    "iso:country":"US",
    "sg:address":"9960 Babbitt Ave",
    "sg:city":"Northridge",
    "sg:classifiers":[
        {
            "category":"Professional",
            "subcategory":"Management & Consulting",
            "type":"Services"
        }
    ],
    "sg:phone":"+1 818 886 8353",
    "sg:postcode":"91325",
    "sg:province":"CA",
    "sg:tags":[
        "vending",
        "mfg",
        "sales",
        "direct",
        "machine",
        "retail"
    ],
    "wof:name":"Howard Enterprises",
    "wof:placetype":"venue"
},
  "geometry": {"coordinates":[-118.50993099999999,34.253123],"type":"Point"}
}