{
  "type": "Feature",
  "properties": {
    "addr:full":"650 Olympia Ave Seaside CA 93955",
    "addr:housenumber":"650",
    "addr:postcode":"93955",
    "addr:street":"Olympia Ave",
    "iso:country":"US",
    "sg:address":"650 Olympia Ave",
    "sg:city":"Seaside",
    "sg:classifiers":[
        {
            "category":"Government",
            "subcategory":"Office",
            "type":"Public Place"
        }
    ],
    "sg:phone":"+1 831 899 6232",
    "sg:postcode":"93955",
    "sg:province":"CA",
    "sg:tags":[
        "village"
    ],
    "wof:name":"Street & Sewer Maintenance",
    "wof:placetype":"venue"
},
  "geometry": {"coordinates":[-121.849637,36.609928],"type":"Point"}
}