{
  "type": "Feature",
  "properties": {
    "iso:country":"US",
    "sg:address":"1500 Eastridge Ave",
    "sg:city":"Riverside",
    "sg:classifiers":[
        {
            "category":"Restaurant",
            "type":"Food & Drink"
        }
    ],
    "sg:phone":"+1 951 778 6433",
    "sg:postcode":"92507",
    "sg:province":"CA",
    "wof:name":"T J' S",
    "wof:placetype":"venue"
},
  "geometry": {"coordinates":[-117.30378899999999,33.931159],"type":"Point"}
}