{
  "type": "Feature",
  "properties": {
    "addr:full":"1563 Solano Ave Berkeley CA 94707",
    "addr:housenumber":"1563",
    "addr:postcode":"94707",
    "addr:street":"Solano Ave",
    "iso:country":"US",
    "sg:address":"1563 Solano Ave",
    "sg:city":"Berkeley",
    "sg:classifiers":[
        {
            "category":"Personal",
            "type":"Services"
        }
    ],
    "sg:phone":"+1 888 501 8369",
    "sg:postcode":"94707",
    "sg:province":"CA",
    "sg:tags":[
        "mover"
    ],
    "sg:website":"www.berkeleylocalmovers.com",
    "wof:name":"Berkeley Movers",
    "wof:placetype":"venue"
},
  "geometry": {"coordinates":[-122.28548000000001,37.891332],"type":"Point"}
}