{
  "type": "Feature",
  "properties": {
    "iso:country":"US",
    "sg:address":"531 W Rincon Ave",
    "sg:city":"Campbell",
    "sg:classifiers":[
        {
            "category":"Social Services",
            "subcategory":"Child Care",
            "type":"Services"
        }
    ],
    "sg:phone":"+1 408 866 2585",
    "sg:postcode":"95008",
    "sg:province":"CA",
    "sg:tags":[
        "day"
    ],
    "sg:website":"www.armoniapreschool.com",
    "wof:name":"Centro Armonia Spanish Immersion School",
    "wof:placetype":"venue"
},
  "geometry": {"coordinates":[-121.95958,37.285193],"type":"Point"}
}