{
  "type": "Feature",
  "properties": {
    "iso:country":"US",
    "sg:address":"4420 Hotel Circle Ct",
    "sg:city":"San Diego",
    "sg:classifiers":[
        {
            "category":"Professional",
            "subcategory":"Lawyer & Legal Services",
            "type":"Services"
        }
    ],
    "sg:phone":"+1 619 262 5297",
    "sg:postcode":"92108",
    "sg:province":"CA",
    "sg:tags":[
        "attorney"
    ],
    "wof:name":"Brandyn De Lynne",
    "wof:placetype":"venue"
},
  "geometry": {"coordinates":[-117.172092,32.760501],"type":"Point"}
}