{
  "type": "Feature",
  "properties": {
    "addr:full":"117 Shaver St San Rafael CA 94901",
    "addr:housenumber":"117",
    "addr:postcode":"94901",
    "addr:street":"Shaver St",
    "iso:country":"US",
    "sg:address":"117 Shaver St",
    "sg:city":"San Rafael",
    "sg:classifiers":[
        {
            "category":"Building & Trades",
            "subcategory":"Construction",
            "type":"Services"
        }
    ],
    "sg:phone":"+1 415 454 2719",
    "sg:postcode":"94901",
    "sg:province":"CA",
    "sg:tags":[
        "contractor"
    ],
    "wof:name":"Mc Guire & Sons",
    "wof:placetype":"venue"
},
  "geometry": {"coordinates":[-122.534705,37.972811],"type":"Point"}
}