{
  "type": "Feature",
  "properties": {
    "iso:country":"US",
    "sg:address":"3121 Jay St",
    "sg:city":"Santa Clara",
    "sg:classifiers":[
        {
            "category":"Professional",
            "subcategory":"Computer Services",
            "type":"Services"
        }
    ],
    "sg:phone":"+1 408 213 5600",
    "sg:postcode":"95054",
    "sg:province":"CA",
    "sg:tags":[
        "communications",
        "datum",
        "system"
    ],
    "wof:name":"Exavio Inc",
    "wof:placetype":"venue"
},
  "geometry": {"coordinates":[-121.961625,37.378012],"type":"Point"}
}