{
  "type": "Feature",
  "properties": {
    "addr:full":"4095 Harrison St Carlsbad CA 92008",
    "addr:housenumber":"4095",
    "addr:postcode":"92008",
    "addr:street":"Harrison St",
    "iso:country":"US",
    "sg:address":"4095 Harrison St",
    "sg:city":"Carlsbad",
    "sg:classifiers":[
        {
            "category":"Recreation",
            "type":"Entertainment"
        }
    ],
    "sg:phone":"+1 760 730 0029",
    "sg:postcode":"92008",
    "sg:province":"CA",
    "sg:tags":[
        "amusement"
    ],
    "wof:name":"Carlsbad Surf School",
    "wof:placetype":"venue"
},
  "geometry": {"coordinates":[-117.334304,33.150504],"type":"Point"}
}