{
  "type": "Feature",
  "properties": {
    "addr:full":"306 E Pico Blvd Los Angeles CA 90015",
    "addr:housenumber":"306",
    "addr:postcode":"90015",
    "addr:street":"E Pico Blvd",
    "iso:country":"US",
    "sg:address":"306 E Pico Blvd",
    "sg:city":"Los Angeles",
    "sg:classifiers":[
        {
            "category":"Shopping",
            "subcategory":"Clothing, Apparel, & Fashions",
            "type":"Retail Goods"
        }
    ],
    "sg:phone":"+1 213 747 4262",
    "sg:postcode":"90015",
    "sg:province":"CA",
    "wof:name":"Coco's",
    "wof:placetype":"venue"
},
  "geometry": {"coordinates":[-118.257316,34.034535],"type":"Point"}
}