{
  "type": "Feature",
  "properties": {
    "iso:country":"US",
    "sg:address":"11046 Wood St",
    "sg:city":"Castroville",
    "sg:classifiers":[
        {
            "category":"Professional",
            "subcategory":"Accounting & Tax Preparation",
            "type":"Services"
        }
    ],
    "sg:phone":"+1 831 633 2143",
    "sg:postcode":"95012",
    "sg:province":"CA",
    "sg:tags":[
        "return",
        "filing"
    ],
    "wof:name":"Yepez Bookkeeping & Tax",
    "wof:placetype":"venue"
},
  "geometry": {"coordinates":[-121.7505,36.760795],"type":"Point"}
}