{
  "type": "Feature",
  "properties": {
    "addr:full":"206 N Coast Hwy Oceanside CA 92054",
    "addr:housenumber":"206",
    "addr:postcode":"92054",
    "addr:street":"N Coast Hwy",
    "iso:country":"US",
    "sg:address":"206 N Coast Hwy",
    "sg:city":"Oceanside",
    "sg:classifiers":[
        {
            "category":"Arts & Performance",
            "subcategory":"Art Gallery",
            "type":"Entertainment"
        }
    ],
    "sg:phone":"+1 760 757 5644",
    "sg:postcode":"92054",
    "sg:province":"CA",
    "wof:name":"Jay Reilly Images",
    "wof:placetype":"venue"
},
  "geometry": {"coordinates":[-117.37940500000001,33.196039],"type":"Point"}
}