{
  "type": "Feature",
  "properties": {
    "addr:full":"17431 Bellflower Blvd Bellflower CA 90706",
    "addr:housenumber":"17431",
    "addr:postcode":"90706",
    "addr:street":"Bellflower Blvd",
    "iso:country":"US",
    "sg:address":"17431 Bellflower Blvd",
    "sg:city":"Bellflower",
    "sg:classifiers":[
        {
            "category":"Professional",
            "type":"Services"
        }
    ],
    "sg:phone":"+1 562 461 8888",
    "sg:postcode":"90706",
    "sg:province":"CA",
    "wof:name":"Move Up Inc",
    "wof:placetype":"venue"
},
  "geometry": {"coordinates":[-118.125243,33.873276],"type":"Point"}
}