{
  "type": "Feature",
  "properties": {
    "addr:full":"2318 Lillie Ave Summerland CA 93067",
    "addr:housenumber":"2318",
    "addr:postcode":"93067",
    "addr:street":"Lillie Ave",
    "iso:country":"US",
    "sg:address":"2318 Lillie Ave",
    "sg:city":"Summerland",
    "sg:classifiers":[
        {
            "category":"Fast Food",
            "type":"Food & Drink"
        },
        {
            "category":"Restaurant",
            "type":"Food & Drink"
        }
    ],
    "sg:phone":"+1 805 969 6135",
    "sg:postcode":"93067",
    "sg:province":"CA",
    "sg:tags":[
        "traditional",
        "burger",
        "american"
    ],
    "wof:name":"The Nugget",
    "wof:placetype":"venue"
},
  "geometry": {"coordinates":[-119.59699999999999,34.419701],"type":"Point"}
}