{
  "type": "Feature",
  "properties": {
    "iso:country":"US",
    "sg:address":"101 Main St",
    "sg:city":"Huntington Beach",
    "sg:classifiers":[
        {
            "category":"Professional",
            "subcategory":"Management & Consulting",
            "type":"Services"
        }
    ],
    "sg:phone":"+1 714 374 3330",
    "sg:postcode":"92648",
    "sg:province":"CA",
    "sg:tags":[
        "marketing",
        "ticket",
        "sport",
        "promotion"
    ],
    "wof:name":"Schulte Sports Enterprises",
    "wof:placetype":"venue"
},
  "geometry": {"coordinates":[-118.00109,33.658069],"type":"Point"}
}