{
  "type": "Feature",
  "properties": {
    "addr:full":"801 Franklin St Oakland CA 94607",
    "addr:housenumber":"801",
    "addr:postcode":"94607",
    "addr:street":"Franklin St",
    "iso:country":"US",
    "sg:address":"801 Franklin St",
    "sg:city":"Oakland",
    "sg:classifiers":[
        {
            "category":"Professional",
            "subcategory":"Business Services",
            "type":"Services"
        }
    ],
    "sg:phone":"+1 510 268 3588",
    "sg:postcode":"94607",
    "sg:province":"CA",
    "wof:name":"Fire Link",
    "wof:placetype":"venue"
},
  "geometry": {"coordinates":[-122.27216,37.800409],"type":"Point"}
}