{
  "type": "Feature",
  "properties": {
    "iso:country":"US",
    "sg:address":"2133 Civic Center Dr W",
    "sg:city":"Santa Ana",
    "sg:classifiers":[
        {
            "category":"Wholesale",
            "subcategory":"Medical Equipment & Supplies",
            "type":"Manufacturing & Wholesale Goods"
        }
    ],
    "sg:phone":"+1 714 542 2971",
    "sg:postcode":"92703",
    "sg:province":"CA",
    "wof:name":"SC Dental Supply",
    "wof:placetype":"venue"
},
  "geometry": {"coordinates":[-117.902518,33.751515],"type":"Point"}
}