{
  "type": "Feature",
  "properties": {
    "addr:full":"2678 Hamner Ave Norco CA 92860",
    "addr:housenumber":"2678",
    "addr:postcode":"92860",
    "addr:street":"Hamner Ave",
    "iso:country":"US",
    "sg:address":"2678 Hamner Ave",
    "sg:city":"Norco",
    "sg:classifiers":[
        {
            "category":"Professional",
            "subcategory":"Art Services",
            "type":"Services"
        }
    ],
    "sg:phone":"+1 951 272 2333",
    "sg:postcode":"92860",
    "sg:province":"CA",
    "sg:tags":[
        "graphic",
        "designer"
    ],
    "wof:name":"P & 2m DESIGN",
    "wof:placetype":"venue"
},
  "geometry": {"coordinates":[-117.55953,33.920229],"type":"Point"}
}