{
  "type": "Feature",
  "properties": {
    "iso:country":"US",
    "sg:address":"5211 Boyd Rd",
    "sg:city":"Arcata",
    "sg:classifiers":[
        {
            "category":"Building & Trades",
            "subcategory":"Construction",
            "type":"Services"
        }
    ],
    "sg:phone":"+1 707 825 6565",
    "sg:postcode":"95521",
    "sg:province":"CA",
    "sg:tags":[
        "excavation",
        "paving",
        "road",
        "contractor"
    ],
    "wof:name":"G R Sundberg Inc.",
    "wof:placetype":"venue"
},
  "geometry": {"coordinates":[-124.068065,40.910649],"type":"Point"}
}