{
  "type": "Feature",
  "properties": {
    "addr:full":"1122 Los Vallecitos Blvd San Marcos CA 92069",
    "addr:housenumber":"1122",
    "addr:postcode":"92069",
    "addr:street":"Los Vallecitos Blvd",
    "iso:country":"US",
    "sg:address":"1122 Los Vallecitos Blvd",
    "sg:city":"San Marcos",
    "sg:classifiers":[
        {
            "category":"Shopping",
            "type":"Retail Goods"
        }
    ],
    "sg:phone":"+1 760 744 9600",
    "sg:postcode":"92069",
    "sg:province":"CA",
    "sg:tags":[
        "spa",
        "hot",
        "tub"
    ],
    "sg:website":"www.spapartsdepot.com",
    "wof:name":"Caldera Spas & Baths",
    "wof:placetype":"venue"
},
  "geometry": {"coordinates":[-117.187624,33.142076],"type":"Point"}
}