{
  "type": "Feature",
  "properties": {
    "addr:full":"1623 Minnie St Santa Ana CA 92707",
    "addr:housenumber":"1623",
    "addr:postcode":"92707",
    "addr:street":"Minnie St",
    "iso:country":"US",
    "sg:address":"1623 Minnie St",
    "sg:city":"Santa Ana",
    "sg:classifiers":[
        {
            "category":"Manufacturing",
            "subcategory":"Glass & Minerals",
            "type":"Manufacturing & Wholesale Goods"
        }
    ],
    "sg:phone":"+1 714 547 7391",
    "sg:postcode":"92707",
    "sg:province":"CA",
    "sg:tags":[
        "abrasive",
        "product"
    ],
    "wof:name":"CTI Carbide Tools-Industry",
    "wof:placetype":"venue"
},
  "geometry": {"coordinates":[-117.854981,33.725972],"type":"Point"}
}