{
  "type": "Feature",
  "properties": {
    "iso:country":"US",
    "sg:address":"203 W Martin Luther King Jr Blvd",
    "sg:city":"Los Angeles",
    "sg:classifiers":[
        {
            "category":"Professional",
            "type":"Services"
        }
    ],
    "sg:phone":"+1 323 235 0400",
    "sg:postcode":"90037",
    "sg:province":"CA",
    "sg:tags":[
        "establishment"
    ],
    "wof:name":"Cutting House",
    "wof:placetype":"venue"
},
  "geometry": {"coordinates":[-118.275229,34.011202],"type":"Point"}
}