{
  "type": "Feature",
  "properties": {
    "addr:full":"2955 S Fowler Ave Fresno CA 93725",
    "addr:housenumber":"2955",
    "addr:postcode":"93725",
    "addr:street":"S Fowler Ave",
    "iso:country":"US",
    "sg:address":"2955 S Fowler Ave",
    "sg:city":"Fresno",
    "sg:classifiers":[
        {
            "category":"Social Services",
            "subcategory":"Child Care",
            "type":"Services"
        }
    ],
    "sg:phone":"+1 559 291 0342",
    "sg:postcode":"93725",
    "sg:province":"CA",
    "sg:tags":[
        "kindergarten",
        "academic",
        "school"
    ],
    "wof:name":"Young World II",
    "wof:placetype":"venue"
},
  "geometry": {"coordinates":[-119.682047,36.699595],"type":"Point"}
}