{
  "type": "Feature",
  "properties": {
    "addr:full":"46247 Arabia St Indio CA 92201",
    "addr:postcode":"46247;92201",
    "addr:street":"Arabia St",
    "iso:country":"US",
    "sg:address":"46247 Arabia St",
    "sg:city":"Indio",
    "sg:classifiers":[
        {
            "category":"Farming",
            "subcategory":"Farm & Veterinary Services",
            "type":"Manufacturing & Wholesale Goods"
        }
    ],
    "sg:phone":"+1 760 347 2335",
    "sg:postcode":"92201",
    "sg:province":"CA",
    "sg:tags":[
        "management"
    ],
    "wof:name":"HMS Agricultural Corp",
    "wof:placetype":"venue"
},
  "geometry": {"coordinates":[-116.225121,33.711214],"type":"Point"}
}