{
  "type": "Feature",
  "properties": {
    "iso:country":"US",
    "sg:address":"13075 Baker Rd",
    "sg:city":"Red Bluff",
    "sg:classifiers":[
        {
            "category":"Wholesale",
            "subcategory":"Farm Supplies",
            "type":"Manufacturing & Wholesale Goods"
        }
    ],
    "sg:phone":"+1 530 529 9868",
    "sg:postcode":"96080",
    "sg:province":"CA",
    "sg:tags":[
        "feed"
    ],
    "wof:name":"Westside Sales",
    "wof:placetype":"venue"
},
  "geometry": {"coordinates":[-122.26109700000001,40.17236],"type":"Point"}
}