{
  "type": "Feature",
  "properties": {
    "iso:country":"US",
    "sg:address":"4519 Everett Avenue",
    "sg:city":"Los Angeles",
    "sg:classifiers":[
        {
            "category":"Shopping",
            "subcategory":"Clothing, Apparel, & Fashions",
            "type":"Retail Goods"
        }
    ],
    "sg:phone":"+1 323 589 1604",
    "sg:postcode":"90058",
    "sg:province":"CA",
    "sg:tags":[
        "clothing",
        "women's"
    ],
    "wof:name":"Premium Denim",
    "wof:placetype":"venue"
},
  "geometry": {"coordinates":[-118.199563,34.000618],"type":"Point"}
}