{
  "type": "Feature",
  "properties": {
    "addr:full":"29318 Golden Meadow Dr Rancho Pls Vrds CA 90275",
    "addr:housenumber":"29318",
    "addr:postcode":"90275",
    "addr:street":"Golden Meadow Dr",
    "iso:country":"US",
    "sg:address":"29318 Golden Meadow Dr",
    "sg:city":"Rancho Pls Vrds",
    "sg:classifiers":[
        {
            "category":"Shopping",
            "subcategory":"Florist",
            "type":"Retail Goods"
        }
    ],
    "sg:phone":"+1 310 544 2251",
    "sg:postcode":"90275",
    "sg:province":"CA",
    "wof:name":"Felines & Flowers By Sande",
    "wof:placetype":"venue"
},
  "geometry": {"coordinates":[-118.403091,33.76803],"type":"Point"}
}