{
  "type": "Feature",
  "properties": {
    "addr:full":"520 Hauser Boulevard Los Angeles CA 90036",
    "addr:housenumber":"520",
    "addr:postcode":"90036",
    "addr:street":"Hauser Boulevard",
    "iso:country":"US",
    "sg:address":"520 Hauser Boulevard",
    "sg:city":"Los Angeles",
    "sg:classifiers":[
        {
            "category":"Personal",
            "type":"Services"
        }
    ],
    "sg:phone":"+1 323 933 1693",
    "sg:postcode":"90036",
    "sg:province":"CA",
    "sg:tags":[
        "party",
        "planning",
        "event"
    ],
    "wof:name":"The Entertainment Group",
    "wof:placetype":"venue"
},
  "geometry": {"coordinates":[-118.350543,34.066356],"type":"Point"}
}