{
  "type": "Feature",
  "properties": {
    "iso:country":"US",
    "sg:address":"18415 Avalon Blvd",
    "sg:city":"Carson",
    "sg:classifiers":[
        {
            "category":"Restaurant",
            "type":"Food & Drink"
        }
    ],
    "sg:phone":"+1 310 327 4866",
    "sg:postcode":"90746",
    "sg:province":"CA",
    "sg:website":"http://www.chongscuisine.com",
    "wof:name":"Chong's Restaurant",
    "wof:placetype":"venue"
},
  "geometry": {"coordinates":[-118.26599899999999,33.862801],"type":"Point"}
}