{
  "type": "Feature",
  "properties": {
    "iso:country":"US",
    "sg:address":"701 M St",
    "sg:city":"Modesto",
    "sg:classifiers":[
        {
            "category":"Autos & Motor Vehicles",
            "subcategory":"Auto Supplies",
            "type":"Retail Goods"
        }
    ],
    "sg:phone":"+1 209 525 3545",
    "sg:postcode":"95354",
    "sg:province":"CA",
    "sg:tags":[
        "automobile",
        "parts"
    ],
    "wof:name":"Modesto Clutch & Brake Inc",
    "wof:placetype":"venue"
},
  "geometry": {"coordinates":[-121.005622,37.641943],"type":"Point"}
}