{
  "type": "Feature",
  "properties": {
    "iso:country":"US",
    "sg:address":"1340 Arnold Dr",
    "sg:city":"Martinez",
    "sg:classifiers":[
        {
            "category":"Social Services",
            "subcategory":"Job Training",
            "type":"Services"
        }
    ],
    "sg:phone":"+1 925 370 1818",
    "sg:postcode":"94553",
    "sg:province":"CA",
    "sg:tags":[
        "retardation",
        "disabled",
        "mental",
        "dev"
    ],
    "wof:name":"Association-Retarded Citizens",
    "wof:placetype":"venue"
},
  "geometry": {"coordinates":[-122.09866100000001,37.993185],"type":"Point"}
}