{
  "type": "Feature",
  "properties": {
    "iso:country":"US",
    "sg:address":"23845 Summit Rd",
    "sg:city":"Los Gatos",
    "sg:classifiers":[
        {
            "category":"Education",
            "subcategory":"School",
            "type":"Public Place"
        }
    ],
    "sg:phone":"+1 408 353 2389",
    "sg:postcode":"95033",
    "sg:province":"CA",
    "wof:name":"Loma Prieta Independent Home",
    "wof:placetype":"venue"
},
  "geometry": {"coordinates":[-121.943939,37.127085],"type":"Point"}
}