{
  "type": "Feature",
  "properties": {
    "iso:country":"US",
    "sg:address":"901 N Carpenter Rd Ste 4",
    "sg:city":"Modesto",
    "sg:classifiers":[
        {
            "category":"Food & Beverages",
            "subcategory":"Candy",
            "type":"Retail Goods"
        },
        {
            "category":"Ice Cream",
            "type":"Food & Drink"
        }
    ],
    "sg:phone":"+1 209 549 2466",
    "sg:postcode":"95351",
    "sg:province":"CA",
    "sg:tags":[
        "frozen",
        "dessert",
        "yogurt"
    ],
    "wof:name":"Baskin-Robbins 31 Flavors",
    "wof:placetype":"venue"
},
  "geometry": {"coordinates":[-121.03199600000001,37.648381],"type":"Point"}
}