{
  "type": "Feature",
  "properties": {
    "iso:country":"US",
    "sg:address":"3508 el Camino Real",
    "sg:city":"Palo Alto",
    "sg:classifiers":[
        {
            "category":"Retail",
            "subcategory":"Auto Repair",
            "type":"Services"
        }
    ],
    "sg:phone":"+1 650 424 8077",
    "sg:postcode":"94306",
    "sg:province":"CA",
    "sg:tags":[
        "repairing",
        "automobile"
    ],
    "wof:name":"Palo Alto Auto Repairs Inc",
    "wof:placetype":"venue"
},
  "geometry": {"coordinates":[-122.134014,37.418706],"type":"Point"}
}