{
  "type": "Feature",
  "properties": {
    "iso:country":"US",
    "sg:address":"1192 W Katella Ave",
    "sg:city":"Anaheim",
    "sg:classifiers":[
        {
            "category":"Restaurant",
            "type":"Food & Drink"
        }
    ],
    "sg:phone":"+1 714 533 2900",
    "sg:postcode":"92802",
    "sg:province":"CA",
    "wof:name":"Anaheim Chicken Factory",
    "wof:placetype":"venue"
},
  "geometry": {"coordinates":[-117.92722999999999,33.803204],"type":"Point"}
}