{
  "type": "Feature",
  "properties": {
    "addr:full":"2452 W Tahoe Ave Caruthers CA 93609",
    "addr:housenumber":"2452",
    "addr:postcode":"93609",
    "addr:street":"W Tahoe Ave",
    "iso:country":"US",
    "sg:address":"2452 W Tahoe Ave",
    "sg:city":"Caruthers",
    "sg:classifiers":[
        {
            "category":"Insurance",
            "subcategory":"Hazard Insurance",
            "type":"Services"
        }
    ],
    "sg:phone":"+1 559 275 8800",
    "sg:postcode":"93609",
    "sg:province":"CA",
    "wof:name":"Gil Properites",
    "wof:placetype":"venue"
},
  "geometry": {"coordinates":[-119.83571000000001,36.540291],"type":"Point"}
}