{
  "type": "Feature",
  "properties": {
    "addr:full":"4026 E Holland Ave Fresno CA 93726",
    "addr:housenumber":"4026",
    "addr:postcode":"93726",
    "addr:street":"E Holland Ave",
    "iso:country":"US",
    "sg:address":"4026 E Holland Ave",
    "sg:city":"Fresno",
    "sg:classifiers":[
        {
            "category":"Building & Trades",
            "subcategory":"Cleaning & Sanitation",
            "type":"Services"
        }
    ],
    "sg:phone":"+1 559 227 4263",
    "sg:postcode":"93726",
    "sg:province":"CA",
    "sg:tags":[
        "house"
    ],
    "wof:name":"Trini's House Cleaning",
    "wof:placetype":"venue"
},
  "geometry": {"coordinates":[-119.75595,36.797243],"type":"Point"}
}