{
  "type": "Feature",
  "properties": {
    "addr:full":"8581 Larthorn Dr Huntington Beach CA 92646",
    "addr:housenumber":"8581",
    "addr:postcode":"92646",
    "addr:street":"Larthorn Dr",
    "iso:country":"US",
    "sg:address":"8581 Larthorn Dr",
    "sg:city":"Huntington Beach",
    "sg:classifiers":[
        {
            "category":"Real Estate",
            "subcategory":"Real Estate Agent",
            "type":"Services"
        }
    ],
    "sg:phone":"+1 714 968 7628",
    "sg:postcode":"92646",
    "sg:province":"CA",
    "sg:tags":[
        "commercial"
    ],
    "wof:name":"Southern CA Industrial Prpts",
    "wof:placetype":"venue"
},
  "geometry": {"coordinates":[-117.977794,33.66791],"type":"Point"}
}