{
  "type": "Feature",
  "properties": {
    "addr:full":"45th Avenue San Francisco CA 94102",
    "addr:postcode":"94102",
    "addr:street":"45Th Avenue",
    "iso:country":"US",
    "sg:address":"45th Avenue",
    "sg:city":"San Francisco",
    "sg:classifiers":[
        {
            "category":"Museum",
            "subcategory":"Zoo",
            "type":"Entertainment"
        }
    ],
    "sg:phone":"+1 415 753 7058",
    "sg:postcode":"94102",
    "sg:province":"CA",
    "wof:name":"Zoo Shop Sloat Bl At",
    "wof:placetype":"venue"
},
  "geometry": {"coordinates":[-122.417,37.780998],"type":"Point"}
}