{
  "type": "Feature",
  "properties": {
    "addr:full":"1730 Geary Blvd San Francisco CA 94115",
    "addr:housenumber":"1730",
    "addr:postcode":"94115",
    "addr:street":"Geary Blvd",
    "iso:country":"US",
    "sg:address":"1730 Geary Blvd",
    "sg:city":"San Francisco",
    "sg:classifiers":[
        {
            "category":"Wholesale",
            "subcategory":"Stationery",
            "type":"Manufacturing & Wholesale Goods"
        }
    ],
    "sg:phone":"+1 415 921 3821",
    "sg:postcode":"94115",
    "sg:province":"CA",
    "sg:tags":[
        "card"
    ],
    "sg:website":"www.asakichi.com",
    "wof:name":"Asakichi Iron Teapot",
    "wof:placetype":"venue"
},
  "geometry": {"coordinates":[-122.431827,37.784664],"type":"Point"}
}