{
  "type": "Feature",
  "properties": {
    "iso:country":"US",
    "sg:address":"2130 de la Cruz Blvd",
    "sg:city":"Santa Clara",
    "sg:classifiers":[
        {
            "category":"Wholesale",
            "subcategory":"Machinery & Supplies",
            "type":"Manufacturing & Wholesale Goods"
        }
    ],
    "sg:phone":"+1 408 727 9444",
    "sg:postcode":"95050",
    "sg:province":"CA",
    "sg:tags":[
        "tool"
    ],
    "sg:website":"www.boschtools.com",
    "wof:name":"Robert Bosch Tool Corp",
    "wof:placetype":"venue"
},
  "geometry": {"coordinates":[-121.941585,37.362198],"type":"Point"}
}