{
  "type": "Feature",
  "properties": {
    "addr:full":"1880 Century Park E Suite 300 Los Angeles CA 90067",
    "addr:housenumber":"1880",
    "addr:postcode":"90067",
    "addr:street":"Century Park E Suite 300",
    "iso:country":"US",
    "sg:address":"1880 Century Park E Suite 300",
    "sg:city":"Los Angeles",
    "sg:classifiers":[
        {
            "category":"Professional",
            "subcategory":"Lawyer & Legal Services",
            "type":"Services"
        }
    ],
    "sg:phone":"+1 310 553 6822",
    "sg:postcode":"90067",
    "sg:province":"CA",
    "wof:name":"Menes Barry A ESQ",
    "wof:placetype":"venue"
},
  "geometry": {"coordinates":[-118.41449,34.061375],"type":"Point"}
}