{
  "type": "Feature",
  "properties": {
    "iso:country":"US",
    "sg:address":"777 W Vista Way Ste 102",
    "sg:city":"Vista",
    "sg:classifiers":[
        {
            "category":"Professional",
            "subcategory":"Printing & Photocopies",
            "type":"Services"
        }
    ],
    "sg:phone":"+1 760 758 1140",
    "sg:postcode":"92083",
    "sg:province":"CA",
    "sg:website":"www.760print.com",
    "wof:name":"Creative Printing",
    "wof:placetype":"venue"
},
  "geometry": {"coordinates":[-117.257847,33.194475],"type":"Point"}
}