{
  "type": "Feature",
  "properties": {
    "iso:country":"US",
    "sg:address":"39115 Cedar Blvd",
    "sg:city":"Newark",
    "sg:classifiers":[
        {
            "category":"Wholesale",
            "subcategory":"Groceries",
            "type":"Manufacturing & Wholesale Goods"
        }
    ],
    "sg:phone":"+1 510 713 9588",
    "sg:postcode":"94560",
    "sg:province":"CA",
    "sg:tags":[
        "tea",
        "room"
    ],
    "wof:name":"Tea Station",
    "wof:placetype":"venue"
},
  "geometry": {"coordinates":[-122.00614899999999,37.52411],"type":"Point"}
}