{
  "type": "Feature",
  "properties": {
    "iso:country":"US",
    "sg:address":"7325 Sierra Ave",
    "sg:city":"Fontana",
    "sg:classifiers":[
        {
            "category":"Food & Beverages",
            "subcategory":"Groceries & Convenience Stores",
            "type":"Retail Goods"
        }
    ],
    "sg:phone":"+1 909 854 7474",
    "sg:postcode":"92336",
    "sg:province":"CA",
    "wof:name":"AM PM Mini Mart",
    "wof:placetype":"venue"
},
  "geometry": {"coordinates":[-117.435811,34.119893],"type":"Point"}
}