{
  "type": "Feature",
  "properties": {
    "addr:full":"621 Monterey St Redlands CA 92373",
    "addr:housenumber":"621",
    "addr:postcode":"92373",
    "addr:street":"Monterey St",
    "iso:country":"US",
    "sg:address":"621 Monterey St",
    "sg:city":"Redlands",
    "sg:classifiers":[
        {
            "category":"Building & Trades",
            "subcategory":"Landscaping Services",
            "type":"Services"
        },
        {
            "category":"Home & Garden",
            "subcategory":"Garden Supply",
            "type":"Retail Goods"
        },
        {
            "category":"Home & Garden",
            "subcategory":"Building Materials",
            "type":"Retail Goods"
        },
        {
            "category":"Building & Trades",
            "subcategory":"Construction",
            "type":"Services"
        },
        {
            "category":"Manufacturing",
            "subcategory":"Building Materials",
            "type":"Manufacturing & Wholesale Goods"
        }
    ],
    "sg:phone":"+1 909 792 3029",
    "sg:postcode":"92373",
    "sg:province":"CA",
    "sg:tags":[
        "decorative",
        "ponds",
        "lawn",
        "designer",
        "wall",
        "consultant",
        "sprinklers-garden",
        "plant",
        "lake",
        "water",
        "concrete-stamped",
        "retaining",
        "contractor",
        "landscape"
    ],
    "sg:website":"http://www.creativepaul.com",
    "wof:name":"Creative Landscapes by Paul C Woltze",
    "wof:placetype":"venue"
},
  "geometry": {"coordinates":[-117.18667600000001,34.040513],"type":"Point"}
}