{
  "type": "Feature",
  "properties": {
    "addr:full":"711 S San Joaquin St Stockton CA 95203",
    "addr:housenumber":"711",
    "addr:postcode":"95203",
    "addr:street":"S San Joaquin St",
    "iso:country":"US",
    "sg:address":"711 S San Joaquin St",
    "sg:city":"Stockton",
    "sg:classifiers":[
        {
            "category":"Home & Garden",
            "subcategory":"Building Materials",
            "type":"Retail Goods"
        }
    ],
    "sg:phone":"+1 209 462 1700",
    "sg:postcode":"95203",
    "sg:province":"CA",
    "wof:name":"Marble Palace Inc",
    "wof:placetype":"venue"
},
  "geometry": {"coordinates":[-121.285224,37.945784],"type":"Point"}
}