{
  "type": "Feature",
  "properties": {
    "iso:country":"US",
    "sg:address":"5609 Edgeview Dr",
    "sg:city":"Discovery Bay",
    "sg:classifiers":[
        {
            "category":"Manufacturing",
            "subcategory":"Paper Products",
            "type":"Manufacturing & Wholesale Goods"
        }
    ],
    "sg:phone":"+1 925 634 0202",
    "sg:postcode":"94505",
    "sg:province":"CA",
    "sg:tags":[
        "corrugated",
        "solid",
        "fiber",
        "box"
    ],
    "wof:name":"Willamette Industries",
    "wof:placetype":"venue"
},
  "geometry": {"coordinates":[-121.598695,37.900566],"type":"Point"}
}