{
  "type": "Feature",
  "properties": {
    "addr:full":"2431 Durant Ave Ste B Berkeley CA 94704",
    "addr:housenumber":"2431",
    "addr:postcode":"94704",
    "addr:street":"Durant Ave Ste B",
    "iso:country":"US",
    "sg:address":"2431 Durant Ave Ste B",
    "sg:city":"Berkeley",
    "sg:classifiers":[
        {
            "category":"Building & Trades",
            "subcategory":"Cleaning & Sanitation",
            "type":"Services"
        }
    ],
    "sg:phone":"+1 510 725 4970",
    "sg:postcode":"94704",
    "sg:province":"CA",
    "sg:tags":[
        "fire",
        "water",
        "restoration",
        "damage"
    ],
    "sg:website":"http://fresh-environment.com",
    "wof:name":"Fresh Environment - Water Damage Restoration Service In Berkeley Ca",
    "wof:placetype":"venue"
},
  "geometry": {"coordinates":[-122.259789,37.867722],"type":"Point"}
}