{
  "type": "Feature",
  "properties": {
    "iso:country":"US",
    "sg:address":"471 Grand Ave",
    "sg:city":"South San Francisco",
    "sg:classifiers":[
        {
            "category":"Retail",
            "subcategory":"Laundry & Dry Cleaning",
            "type":"Services"
        }
    ],
    "sg:phone":"+1 650 588 7349",
    "sg:postcode":"94080",
    "sg:province":"CA",
    "sg:tags":[
        "cleaner"
    ],
    "wof:name":"Wardrobe Cleaners",
    "wof:placetype":"venue"
},
  "geometry": {"coordinates":[-122.415001,37.6562],"type":"Point"}
}