{
  "type": "Feature",
  "properties": {
    "addr:full":"17885 Sky Park Cir Irvine CA 92614",
    "addr:housenumber":"17885",
    "addr:postcode":"92614",
    "addr:street":"Sky Park Cir",
    "iso:country":"US",
    "sg:address":"17885 Sky Park Cir",
    "sg:city":"Irvine",
    "sg:classifiers":[
        {
            "category":"Insurance",
            "subcategory":"Health Insurance",
            "type":"Services"
        }
    ],
    "sg:phone":"+1 949 861 8700",
    "sg:postcode":"92614",
    "sg:province":"CA",
    "sg:tags":[
        "market"
    ],
    "wof:name":"Global Nutritution",
    "wof:placetype":"venue"
},
  "geometry": {"coordinates":[-117.859094,33.691309],"type":"Point"}
}