{
  "type": "Feature",
  "properties": {
    "addr:full":"17305 Von Karman Ave Ste 109 Irvine CA 92614",
    "addr:housenumber":"17305",
    "addr:postcode":"92614",
    "addr:street":"Von Karman Ave Ste 109",
    "iso:country":"US",
    "sg:address":"17305 Von Karman Ave Ste 109",
    "sg:city":"Irvine",
    "sg:classifiers":[
        {
            "category":"Health Services",
            "subcategory":"Health Practitioner",
            "type":"Services"
        }
    ],
    "sg:phone":"+1 949 679 8818",
    "sg:postcode":"92614",
    "sg:province":"CA",
    "sg:tags":[
        "acupuncture"
    ],
    "sg:website":"www.globalhealthandsports.com",
    "wof:name":"Global Health & Sports Institute",
    "wof:placetype":"venue"
},
  "geometry": {"coordinates":[-117.841645,33.690377],"type":"Point"}
}