{
  "type": "Feature",
  "properties": {
    "iso:country":"US",
    "sg:address":"22748 Boxwood Ln",
    "sg:city":"Santa Clarita",
    "sg:classifiers":[
        {
            "category":"Health Services",
            "subcategory":"Optometrist",
            "type":"Services"
        },
        {
            "category":"Shopping",
            "subcategory":"Optician",
            "type":"Retail Goods"
        }
    ],
    "sg:phone":"+1 661 513 0169",
    "sg:postcode":"91390",
    "sg:province":"CA",
    "sg:tags":[
        "eyewear"
    ],
    "wof:name":"US Pharma Lab",
    "wof:placetype":"venue"
},
  "geometry": {"coordinates":[-118.530998,34.472698],"type":"Point"}
}