{
  "type": "Feature",
  "properties": {
    "iso:country":"US",
    "sg:address":"31704 Pepper Tree St",
    "sg:city":"Winchester",
    "sg:classifiers":[
        {
            "category":"Real Estate",
            "subcategory":"Real Estate Services",
            "type":"Services"
        },
        {
            "category":"Real Estate",
            "subcategory":"Real Estate Agent",
            "type":"Services"
        }
    ],
    "sg:phone":"+1 951 491 5052",
    "sg:postcode":"92596",
    "sg:province":"CA",
    "sg:tags":[
        "buyer",
        "broker"
    ],
    "wof:name":"Sca Real Estate",
    "wof:placetype":"venue"
},
  "geometry": {"coordinates":[-117.105442,33.585562],"type":"Point"}
}