{
  "type": "Feature",
  "properties": {
    "addr:full":"27231 La Paz Rd Ste C Laguna Niguel CA 92677",
    "addr:housenumber":"27231",
    "addr:postcode":"92677",
    "addr:street":"La Paz Rd Ste C",
    "iso:country":"US",
    "sg:address":"27231 La Paz Rd Ste C",
    "sg:city":"Laguna Niguel",
    "sg:classifiers":[
        {
            "category":"Social Services",
            "subcategory":"Child Care",
            "type":"Services"
        }
    ],
    "sg:phone":"+1 949 448 0814",
    "sg:postcode":"92677",
    "sg:province":"CA",
    "sg:tags":[
        "day"
    ],
    "sg:website":"www.playmateswcc.com",
    "wof:name":"Playmates A Wee Care Club",
    "wof:placetype":"venue"
},
  "geometry": {"coordinates":[-117.707801,33.56763],"type":"Point"}
}