{
  "type": "Feature",
  "properties": {
    "addr:full":"125 Mill St Grass Valley CA 95945",
    "addr:housenumber":"125",
    "addr:postcode":"95945",
    "addr:street":"Mill St",
    "iso:country":"US",
    "sg:address":"125 Mill St",
    "sg:city":"Grass Valley",
    "sg:classifiers":[
        {
            "category":"Shopping",
            "subcategory":"Used Merchandise",
            "type":"Retail Goods"
        }
    ],
    "sg:phone":"+1 530 274 1917",
    "sg:postcode":"95945",
    "sg:province":"CA",
    "sg:tags":[
        "antique"
    ],
    "wof:name":"Gold Rush Antiques",
    "wof:placetype":"venue"
},
  "geometry": {"coordinates":[-121.062881,39.218709],"type":"Point"}
}