{
  "type": "Feature",
  "properties": {
    "iso:country":"US",
    "sg:address":"6975 Pentz Rd",
    "sg:city":"Paradise",
    "sg:classifiers":[
        {
            "category":"Place Of Worship",
            "subcategory":"Church",
            "type":"Public Place"
        },
        {
            "category":"Place Of Worship",
            "type":"Public Place"
        },
        {
            "category":"Organizations",
            "subcategory":"Religious Organization",
            "type":"Services"
        }
    ],
    "sg:phone":"+1 530 877 7391",
    "sg:postcode":"95969",
    "sg:province":"CA",
    "sg:tags":[
        "churches-baptist-general",
        "churches-baptist-southern",
        "churches-baptist"
    ],
    "wof:name":"Paradise Ridge Southern Baptist Church",
    "wof:placetype":"venue"
},
  "geometry": {"coordinates":[-121.579593,39.788482],"type":"Point"}
}