{
  "type": "Feature",
  "properties": {
    "addr:full":"1330 E 16th St Los Angeles CA 90021",
    "addr:housenumber":"1330",
    "addr:postcode":"90021",
    "addr:street":"E 16Th St",
    "iso:country":"US",
    "sg:address":"1330 E 16th St",
    "sg:city":"Los Angeles",
    "sg:classifiers":[
        {
            "category":"Real Estate",
            "subcategory":"Real Estate Operator",
            "type":"Services"
        }
    ],
    "sg:phone":"+1 213 765 0712",
    "sg:postcode":"90021",
    "sg:province":"CA",
    "sg:tags":[
        "apartment"
    ],
    "wof:name":"Villa Properties",
    "wof:placetype":"venue"
},
  "geometry": {"coordinates":[-118.247598,34.025703],"type":"Point"}
}