{
  "type": "Feature",
  "properties": {
    "iso:country":"US",
    "sg:address":"1122 Crenshaw Blvd",
    "sg:city":"Torrance",
    "sg:classifiers":[
        {
            "category":"Health Services",
            "subcategory":"Doctor",
            "type":"Services"
        },
        {
            "category":"Health Services",
            "subcategory":"Dentist",
            "type":"Services"
        }
    ],
    "sg:phone":"+1 310 831 0348",
    "sg:postcode":"90501",
    "sg:province":"CA",
    "sg:tags":[
        "surgeon",
        "oral",
        "orthodontist"
    ],
    "wof:name":"Goode John DDS",
    "wof:placetype":"venue"
},
  "geometry": {"coordinates":[-118.329002,33.837002],"type":"Point"}
}