{
  "type": "Feature",
  "properties": {
    "addr:full":"501 San Fernando Mission Blvd San Fernando CA 91340",
    "addr:housenumber":"501",
    "addr:postcode":"91340",
    "addr:street":"San Fernando Mission Blvd",
    "iso:country":"US",
    "sg:address":"501 San Fernando Mission Blvd",
    "sg:city":"San Fernando",
    "sg:classifiers":[
        {
            "category":"Professional",
            "subcategory":"Lawyer & Legal Services",
            "type":"Services"
        }
    ],
    "sg:phone":"+1 818 361 0456",
    "sg:postcode":"91340",
    "sg:province":"CA",
    "sg:tags":[
        "naturalization",
        "immigration"
    ],
    "wof:name":"M D Immigration Svc",
    "wof:placetype":"venue"
},
  "geometry": {"coordinates":[-118.446214,34.281794],"type":"Point"}
}