{
  "type": "Feature",
  "properties": {
    "iso:country":"US",
    "sg:address":"912 E Belmont Ave",
    "sg:city":"Fresno",
    "sg:classifiers":[
        {
            "category":"Health Services",
            "subcategory":"Health Practitioner",
            "type":"Services"
        }
    ],
    "sg:phone":"+1 559 441 1568",
    "sg:postcode":"93701",
    "sg:province":"CA",
    "sg:tags":[
        "acupuncture"
    ],
    "wof:name":"Chinese Acupuncture & Herbs",
    "wof:placetype":"venue"
},
  "geometry": {"coordinates":[-119.79903400000001,36.750344],"type":"Point"}
}