{
  "type": "Feature",
  "properties": {
    "addr:full":"1625 Clark Ave Long Beach CA 90815",
    "addr:housenumber":"1625",
    "addr:postcode":"90815",
    "addr:street":"Clark Ave",
    "iso:country":"US",
    "sg:address":"1625 Clark Ave",
    "sg:city":"Long Beach",
    "sg:classifiers":[
        {
            "category":"Home & Garden",
            "subcategory":"Carpets & Floor Coverings",
            "type":"Retail Goods"
        }
    ],
    "sg:phone":"+1 562 985 1155",
    "sg:postcode":"90815",
    "sg:province":"CA",
    "sg:tags":[
        "dealer",
        "rug"
    ],
    "wof:name":"Stanley Steemer Carpet Cleaner",
    "wof:placetype":"venue"
},
  "geometry": {"coordinates":[-118.134123,33.78544],"type":"Point"}
}