{
  "type": "Feature",
  "properties": {
    "iso:country":"US",
    "sg:address":"3612 Kings Way Apt 2",
    "sg:city":"Sacramento",
    "sg:classifiers":[
        {
            "category":"Building & Trades",
            "subcategory":"Landscaping Services",
            "type":"Services"
        },
        {
            "category":"Home & Garden",
            "subcategory":"Garden Supply",
            "type":"Retail Goods"
        },
        {
            "category":"Wholesale",
            "subcategory":"Machinery & Supplies",
            "type":"Manufacturing & Wholesale Goods"
        }
    ],
    "sg:phone":"+1 916 483 1663",
    "sg:postcode":"95821",
    "sg:province":"CA",
    "sg:tags":[
        "lawn",
        "system",
        "sprinklers-garden",
        "irrigation",
        "contractor",
        "equipment",
        "landscape"
    ],
    "wof:name":"George Richards Landscape & Turf",
    "wof:placetype":"venue"
},
  "geometry": {"coordinates":[-121.380548,38.614058],"type":"Point"}
}