{
  "type": "Feature",
  "properties": {
    "addr:full":"667 S Western Ave Los Angeles CA 90005",
    "addr:housenumber":"667",
    "addr:postcode":"90005",
    "addr:street":"S Western Ave",
    "iso:country":"US",
    "sg:address":"667 S Western Ave",
    "sg:city":"Los Angeles",
    "sg:classifiers":[
        {
            "category":"Restaurant",
            "type":"Food & Drink"
        }
    ],
    "sg:phone":"+1 213 368 0710",
    "sg:postcode":"90005",
    "sg:province":"CA",
    "sg:tags":[
        "vietnamese"
    ],
    "sg:website":"www.pho2000.com/location2.html",
    "wof:name":"Pho 2000",
    "wof:placetype":"venue"
},
  "geometry": {"coordinates":[-118.30911999999999,34.060807],"type":"Point"}
}