{
  "type": "Feature",
  "properties": {
    "iso:country":"US",
    "sg:address":"225 N Lima St",
    "sg:city":"Sierra Madre",
    "sg:classifiers":[
        {
            "category":"Professional",
            "type":"Services"
        }
    ],
    "sg:phone":"+1 626 836 3300",
    "sg:postcode":"91024",
    "sg:province":"CA",
    "sg:website":"www.smithasbury.com",
    "wof:name":"Smith Asbury Inc",
    "wof:placetype":"venue"
},
  "geometry": {"coordinates":[-118.060328,34.165879],"type":"Point"}
}