{
  "type": "Feature",
  "properties": {
    "iso:country":"US",
    "sg:address":"54411 Village Center Dr",
    "sg:city":"Idyllwild",
    "sg:classifiers":[
        {
            "category":"Food & Beverages",
            "subcategory":"Groceries & Convenience Stores",
            "type":"Retail Goods"
        }
    ],
    "sg:phone":"+1 951 659 2737",
    "sg:postcode":"92549",
    "sg:province":"CA",
    "sg:tags":[
        "grocer"
    ],
    "wof:name":"Fairway Foods Inc",
    "wof:placetype":"venue"
},
  "geometry": {"coordinates":[-116.710994,33.743264],"type":"Point"}
}