{
  "type": "Feature",
  "properties": {
    "addr:full":"1969 Tully Rd Ste 70 San Jose CA 95122",
    "addr:housenumber":"1969",
    "addr:postcode":"95122",
    "addr:street":"Tully Rd Ste 70 San Jose",
    "iso:country":"US",
    "sg:address":"1969 Tully Rd Ste 70",
    "sg:city":"San Jose",
    "sg:classifiers":[
        {
            "category":"Restaurant",
            "type":"Food & Drink"
        }
    ],
    "sg:phone":"+1 408 923 1322",
    "sg:postcode":"95122",
    "sg:province":"CA",
    "sg:tags":[
        "barbeque"
    ],
    "sg:website":"www.rib-liciousbbq.com/",
    "wof:name":"Rib-licious BBQ",
    "wof:placetype":"venue"
},
  "geometry": {"coordinates":[-121.821618,37.325956],"type":"Point"}
}