{
  "type": "Feature",
  "properties": {
    "addr:full":"1740 Dove Ct Hayward CA 94545",
    "addr:housenumber":"1740",
    "addr:postcode":"94545",
    "addr:street":"Dove Ct",
    "iso:country":"US",
    "sg:address":"1740 Dove Ct",
    "sg:city":"Hayward",
    "sg:classifiers":[
        {
            "category":"Transit Center",
            "subcategory":"Freight",
            "type":"Transportation"
        },
        {
            "category":"Freight",
            "type":"Transportation"
        }
    ],
    "sg:phone":"+1 510 912 1107",
    "sg:postcode":"94545",
    "sg:province":"CA",
    "sg:tags":[
        "local",
        "trucking-motor",
        "trucking"
    ],
    "wof:name":"Polanco Bros Trucking",
    "wof:placetype":"venue"
},
  "geometry": {"coordinates":[-122.079426,37.621964],"type":"Point"}
}