{
  "type": "Feature",
  "properties": {
    "iso:country":"US",
    "sg:address":"4649 Geary Blvd",
    "sg:city":"San Francisco",
    "sg:classifiers":[
        {
            "category":"Restaurant",
            "type":"Food & Drink"
        }
    ],
    "sg:menulink":"http://www.allmenus.com/ca/san-francisco/178133-jack-in-the-box/menu/",
    "sg:phone":"+1 415 752 4916",
    "sg:postcode":"94118",
    "sg:province":"CA",
    "sg:tags":[
        "burger",
        "american"
    ],
    "wof:name":"Jack in the Box",
    "wof:placetype":"venue"
},
  "geometry": {"coordinates":[-122.46930500000001,37.780489],"type":"Point"}
}