{
  "type": "Feature",
  "properties": {
    "addr:full":"44620 Valley Central Way Lancaster CA 93536",
    "addr:housenumber":"44620",
    "addr:postcode":"93536",
    "addr:street":"Valley Central Way",
    "iso:country":"US",
    "sg:address":"44620 Valley Central Way",
    "sg:city":"Lancaster",
    "sg:classifiers":[
        {
            "category":"Shopping",
            "subcategory":"Stationery & Office Supplies",
            "type":"Retail Goods"
        }
    ],
    "sg:phone":"+1 661 723 1277",
    "sg:postcode":"93536",
    "sg:province":"CA",
    "sg:website":"www.staples.com",
    "wof:name":"Staples The Office Superstore",
    "wof:placetype":"venue"
},
  "geometry": {"coordinates":[-118.17211,34.692307],"type":"Point"}
}