{
  "type": "Feature",
  "properties": {
    "addr:full":"2750 Clearwater St Los Angeles CA 90039",
    "addr:housenumber":"2750",
    "addr:postcode":"90039",
    "addr:street":"Clearwater St",
    "iso:country":"US",
    "sg:address":"2750 Clearwater St",
    "sg:city":"Los Angeles",
    "sg:classifiers":[
        {
            "category":"Manufacturing",
            "subcategory":"Food",
            "type":"Manufacturing & Wholesale Goods"
        }
    ],
    "sg:phone":"+1 323 660 9279",
    "sg:postcode":"90039",
    "sg:province":"CA",
    "sg:tags":[
        "retail"
    ],
    "wof:name":"Burning Lotus Designs",
    "wof:placetype":"venue"
},
  "geometry": {"coordinates":[-118.25342000000001,34.107094],"type":"Point"}
}