{
  "type": "Feature",
  "properties": {
    "addr:full":"606 Sunnyvale Pl Vacaville CA 95687",
    "addr:housenumber":"606",
    "addr:postcode":"95687",
    "addr:street":"Sunnyvale Pl",
    "iso:country":"US",
    "sg:address":"606 Sunnyvale Pl",
    "sg:city":"Vacaville",
    "sg:classifiers":[
        {
            "category":"Arts & Performance",
            "subcategory":"Theater",
            "type":"Entertainment"
        }
    ],
    "sg:phone":"+1 707 469 0650",
    "sg:postcode":"95687",
    "sg:province":"CA",
    "sg:tags":[
        "live",
        "music"
    ],
    "wof:name":"Masters Musec",
    "wof:placetype":"venue"
},
  "geometry": {"coordinates":[-121.95267800000001,38.360505],"type":"Point"}
}