{
  "type": "Feature",
  "properties": {
    "addr:full":"460 Montgomery St San Ramon CA 94583",
    "addr:housenumber":"460",
    "addr:postcode":"ca 94583",
    "addr:street":"Montgomery St",
    "iso:country":"US",
    "sg:address":"460 Montgomery St",
    "sg:city":"San Ramon",
    "sg:classifiers":[
        {
            "category":"Professional",
            "subcategory":"Business Services",
            "type":"Services"
        }
    ],
    "sg:phone":"+1 925 275 8055",
    "sg:postcode":"94583",
    "sg:province":"CA",
    "sg:tags":[
        "interior",
        "consultant",
        "design",
        "decorator"
    ],
    "wof:name":"At Home Decor & Design",
    "wof:placetype":"venue"
},
  "geometry": {"coordinates":[-121.953019,37.763897],"type":"Point"}
}