{
  "type": "Feature",
  "properties": {
    "iso:country":"US",
    "sg:address":"206 S Pacific Coast Hwy",
    "sg:city":"Redondo Beach",
    "sg:classifiers":[
        {
            "category":"Travel",
            "subcategory":"Hotels & Motels",
            "type":"Entertainment"
        }
    ],
    "sg:phone":"+1 310 318 1811",
    "sg:postcode":"90277",
    "sg:province":"CA",
    "wof:name":"Redondo Pier Inn",
    "wof:placetype":"venue"
},
  "geometry": {"coordinates":[-118.385346,33.838366],"type":"Point"}
}