{
  "type": "Feature",
  "properties": {
    "iso:country":"US",
    "sg:address":"566 S Madera Ave",
    "sg:city":"Kerman",
    "sg:classifiers":[
        {
            "category":"Restaurant",
            "type":"Food & Drink"
        }
    ],
    "sg:phone":"+1 559 846 8988",
    "sg:postcode":"93630",
    "sg:province":"CA",
    "wof:name":"Kathy's",
    "wof:placetype":"venue"
},
  "geometry": {"coordinates":[-120.06014999999999,36.726174],"type":"Point"}
}