{
  "type": "Feature",
  "properties": {
    "iso:country":"US",
    "sg:address":"250 Montgomery St",
    "sg:city":"San Francisco",
    "sg:classifiers":[
        {
            "category":"Professional",
            "subcategory":"Lawyer & Legal Services",
            "type":"Services"
        }
    ],
    "sg:phone":"+1 415 397 4345",
    "sg:postcode":"94104",
    "sg:province":"CA",
    "sg:website":"www.booskalaw.com",
    "wof:name":"Steven A. Booska, Attorney At Law",
    "wof:placetype":"venue"
},
  "geometry": {"coordinates":[-122.402276,37.791583],"type":"Point"}
}