{
  "type": "Feature",
  "properties": {
    "addr:full":"226 S Glasgow Ave Inglewood CA 90301",
    "addr:housenumber":"226",
    "addr:postcode":"90301",
    "addr:street":"S Glasgow Ave",
    "iso:country":"US",
    "sg:address":"226 S Glasgow Ave",
    "sg:city":"Inglewood",
    "sg:classifiers":[
        {
            "category":"Real Estate",
            "subcategory":"Real Estate Services",
            "type":"Services"
        },
        {
            "category":"Building & Trades",
            "subcategory":"Construction",
            "type":"Services"
        }
    ],
    "sg:phone":"+1 310 410 8500",
    "sg:postcode":"90301",
    "sg:province":"CA",
    "sg:tags":[
        "contractor"
    ],
    "sg:website":"www.glasgowmc.com/",
    "wof:name":"Glasgow Maintenance Company",
    "wof:placetype":"venue"
},
  "geometry": {"coordinates":[-118.371832,33.960865],"type":"Point"}
}