{
  "type": "Feature",
  "properties": {
    "addr:full":"590 Harbor St Morro Bay CA 93442",
    "addr:housenumber":"590",
    "addr:postcode":"93442",
    "addr:street":"Harbor St",
    "iso:country":"US",
    "sg:address":"590 Harbor St",
    "sg:city":"Morro Bay",
    "sg:classifiers":[
        {
            "category":"Health Services",
            "subcategory":"Optometrist",
            "type":"Services"
        }
    ],
    "sg:phone":"+1 805 545 8100",
    "sg:postcode":"93442",
    "sg:province":"CA",
    "wof:name":"OLDENBURG J BRENT MD",
    "wof:placetype":"venue"
},
  "geometry": {"coordinates":[-120.846653,35.366792],"type":"Point"}
}