{
  "type": "Feature",
  "properties": {
    "addr:full":"948 Weldwood Ct Los Gatos CA 95032",
    "addr:housenumber":"948",
    "addr:postcode":"95032",
    "addr:street":"Weldwood Ct",
    "iso:country":"US",
    "sg:address":"948 Weldwood Ct",
    "sg:city":"Los Gatos",
    "sg:classifiers":[
        {
            "category":"Professional",
            "subcategory":"Computer Services",
            "type":"Services"
        }
    ],
    "sg:phone":"+1 408 866 8080",
    "sg:postcode":"95032",
    "sg:province":"CA",
    "sg:tags":[
        "hardware",
        "provider",
        "internet",
        "software"
    ],
    "wof:name":"Streaming 21 Inc",
    "wof:placetype":"venue"
},
  "geometry": {"coordinates":[-121.972719,37.262678],"type":"Point"}
}