{
  "type": "Feature",
  "properties": {
    "iso:country":"US",
    "sg:address":"1026 Oak Grove Rd",
    "sg:city":"Concord",
    "sg:classifiers":[
        {
            "category":"Government",
            "subcategory":"Office",
            "type":"Public Place"
        }
    ],
    "sg:phone":"+1 925 646 5468",
    "sg:postcode":"94518",
    "sg:province":"CA",
    "wof:name":"Contra Costa Cnty Mental Hlth",
    "wof:placetype":"venue"
},
  "geometry": {"coordinates":[-122.035479,37.950151],"type":"Point"}
}