{
  "type": "Feature",
  "properties": {
    "addr:full":"25345 Crenshaw Blvd Torrance CA 90505",
    "addr:housenumber":"25345",
    "addr:postcode":"90505",
    "addr:street":"Crenshaw Blvd",
    "iso:country":"US",
    "sg:address":"25345 Crenshaw Blvd",
    "sg:city":"Torrance",
    "sg:classifiers":[
        {
            "category":"Juice Bar",
            "subcategory":"None",
            "type":"Food & Drink"
        }
    ],
    "sg:phone":"+1 310 530 3268",
    "sg:postcode":"90505",
    "sg:province":"CA",
    "sg:tags":[
        "smoothy"
    ],
    "sg:website":"www.robeks.com",
    "wof:name":"Robeks Juice",
    "wof:placetype":"venue"
},
  "geometry": {"coordinates":[-118.330614,33.793763],"type":"Point"}
}