{
  "type": "Feature",
  "properties": {
    "iso:country":"US",
    "sg:address":"1213 Simi Town Center Way",
    "sg:city":"Simi Valley",
    "sg:classifiers":[
        {
            "category":"Restaurant",
            "type":"Food & Drink"
        }
    ],
    "sg:menulink":"http://www.allmenus.com/ca/simi-valley/8444-islands/menu/",
    "sg:phone":"+1 805 577 0693",
    "sg:postcode":"93065",
    "sg:province":"CA",
    "sg:tags":[
        "burger",
        "american"
    ],
    "wof:name":"Islands Fine Burgers & Drinks",
    "wof:placetype":"venue"
},
  "geometry": {"coordinates":[-118.77621499999999,34.283481],"type":"Point"}
}