{
  "type": "Feature",
  "properties": {
    "iso:country":"US",
    "sg:address":"29910 Ohana Cir",
    "sg:city":"Lake Elsinore",
    "sg:classifiers":[
        {
            "category":"Banks & Credit Unions",
            "subcategory":"Investment Brokerage",
            "type":"Services"
        }
    ],
    "sg:phone":"+1 951 530 1400",
    "sg:postcode":"92532",
    "sg:province":"CA",
    "wof:name":"Arudius Investment Group Inc",
    "wof:placetype":"venue"
},
  "geometry": {"coordinates":[-117.327978,33.682777],"type":"Point"}
}