{
  "type": "Feature",
  "properties": {
    "addr:full":"975 N. Batavia, Unit C Orange CA 92867",
    "addr:housenumber":"975;unit c",
    "addr:postcode":"92867",
    "addr:street":"N.",
    "iso:country":"US",
    "sg:address":"975 N. Batavia, Unit C",
    "sg:city":"Orange",
    "sg:classifiers":[
        {
            "category":"Retail",
            "subcategory":"Auto Repair",
            "type":"Services"
        }
    ],
    "sg:phone":"+1 714 633 9355",
    "sg:postcode":"92867",
    "sg:province":"CA",
    "sg:tags":[
        "body",
        "shop"
    ],
    "sg:website":"www.mobworks.com",
    "wof:name":"Mobworks Autobody and Paint",
    "wof:placetype":"venue"
},
  "geometry": {"coordinates":[-117.861757,33.804782],"type":"Point"}
}