{
  "type": "Feature",
  "properties": {
    "addr:full":"4664 Lawler Ct La Mesa CA 91941",
    "addr:housenumber":"4664",
    "addr:postcode":"91941",
    "addr:street":"Lawler Ct",
    "iso:country":"US",
    "sg:address":"4664 Lawler Ct",
    "sg:city":"La Mesa",
    "sg:classifiers":[
        {
            "category":"Professional",
            "subcategory":"Management & Consulting",
            "type":"Services"
        }
    ],
    "sg:phone":"+1 619 460 8874",
    "sg:postcode":"91941",
    "sg:province":"CA",
    "sg:tags":[
        "consultant"
    ],
    "wof:name":"WRM Consulting",
    "wof:placetype":"venue"
},
  "geometry": {"coordinates":[-116.987041,32.762956],"type":"Point"}
}