{
  "type": "Feature",
  "properties": {
    "iso:country":"US",
    "sg:address":"15876 Amston Ct",
    "sg:city":"Chino Hills",
    "sg:classifiers":[
        {
            "category":"Arts & Performance",
            "subcategory":"Theater",
            "type":"Entertainment"
        }
    ],
    "sg:phone":"+1 909 597 5119",
    "sg:postcode":"91709",
    "sg:province":"CA",
    "sg:tags":[
        "live",
        "music"
    ],
    "sg:website":"www.homeoilchange.com",
    "wof:name":"Anda DJ",
    "wof:placetype":"venue"
},
  "geometry": {"coordinates":[-117.684806,33.966713],"type":"Point"}
}