{
  "type": "Feature",
  "properties": {
    "addr:full":"10573 Larch Ave Bloomington CA 92316",
    "addr:housenumber":"10573",
    "addr:postcode":"92316",
    "addr:street":"Larch Ave",
    "iso:country":"US",
    "sg:address":"10573 Larch Ave",
    "sg:city":"Bloomington",
    "sg:classifiers":[
        {
            "category":"Wholesale",
            "subcategory":"Hardware",
            "type":"Manufacturing & Wholesale Goods"
        },
        {
            "category":"Building & Trades",
            "subcategory":"Equipment Rental",
            "type":"Services"
        },
        {
            "category":"Home & Garden",
            "subcategory":"Hardware",
            "type":"Retail Goods"
        }
    ],
    "sg:phone":"+1 909 877 1418",
    "sg:postcode":"92316",
    "sg:province":"CA",
    "sg:tags":[
        "contractor",
        "hardware-builders",
        "store",
        "supply"
    ],
    "sg:website":"http://www.paneljacks.com",
    "wof:name":"Panel Jack Co.",
    "wof:placetype":"venue"
},
  "geometry": {"coordinates":[-117.392054,34.061851],"type":"Point"}
}