{
  "type": "Feature",
  "properties": {
    "iso:country":"US",
    "sg:address":"1295 State Hwy 99",
    "sg:city":"Gridley",
    "sg:classifiers":[
        {
            "category":"Home & Garden",
            "subcategory":"Building Materials",
            "type":"Retail Goods"
        }
    ],
    "sg:phone":"+1 530 846 5842",
    "sg:postcode":"95948",
    "sg:province":"CA",
    "sg:tags":[
        "mixed",
        "concrete"
    ],
    "wof:name":"Feather River Concrete Product",
    "wof:placetype":"venue"
},
  "geometry": {"coordinates":[-121.68789,39.354116],"type":"Point"}
}