{
  "type": "Feature",
  "properties": {
    "iso:country":"US",
    "sg:address":"27192 Sun City Blvd",
    "sg:city":"Sun City",
    "sg:classifiers":[
        {
            "category":"Personal",
            "subcategory":"Beauty Salon",
            "type":"Services"
        }
    ],
    "sg:phone":"+1 951 679 6359",
    "sg:postcode":"92586",
    "sg:province":"CA",
    "wof:name":"Golden Hair Cuts",
    "wof:placetype":"venue"
},
  "geometry": {"coordinates":[-117.193815,33.712915],"type":"Point"}
}