{
  "type": "Feature",
  "properties": {
    "addr:full":"2840 Hulen Pl Riverside CA 92507",
    "addr:housenumber":"2840",
    "addr:postcode":"92507",
    "addr:street":"Hulen Pl",
    "iso:country":"US",
    "sg:address":"2840 Hulen Pl",
    "sg:city":"Riverside",
    "sg:classifiers":[
        {
            "category":"Building & Trades",
            "subcategory":"Construction",
            "type":"Services"
        }
    ],
    "sg:phone":"+1 951 686 1250",
    "sg:postcode":"92507",
    "sg:province":"CA",
    "sg:tags":[
        "contractor"
    ],
    "wof:name":"SNR Construction Inc",
    "wof:placetype":"venue"
},
  "geometry": {"coordinates":[-117.353824,33.986917],"type":"Point"}
}