{
  "type": "Feature",
  "properties": {
    "addr:full":"16509 S Western Ave Gardena CA 90247",
    "addr:housenumber":"16509",
    "addr:postcode":"90247",
    "addr:street":"S Western Ave",
    "iso:country":"US",
    "sg:address":"16509 S Western Ave",
    "sg:city":"Gardena",
    "sg:classifiers":[
        {
            "category":"Health Services",
            "subcategory":"Medical Lab",
            "type":"Services"
        }
    ],
    "sg:phone":"+1 310 293 3131",
    "sg:postcode":"90247",
    "sg:province":"CA",
    "sg:tags":[
        "laboratory"
    ],
    "wof:name":"Cana Dental Arts",
    "wof:placetype":"venue"
},
  "geometry": {"coordinates":[-118.309214,33.88019],"type":"Point"}
}