{
  "type": "Feature",
  "properties": {
    "addr:full":"690 W Main St El Centro CA 92243",
    "addr:housenumber":"690",
    "addr:postcode":"92243",
    "addr:street":"W Main St",
    "iso:country":"US",
    "sg:address":"690 W Main St",
    "sg:city":"El Centro",
    "sg:classifiers":[
        {
            "category":"Shopping",
            "subcategory":"Computers & Home Electronics",
            "type":"Retail Goods"
        }
    ],
    "sg:phone":"+1 760 352 4288",
    "sg:postcode":"92243",
    "sg:province":"CA",
    "sg:tags":[
        "television",
        "radio"
    ],
    "wof:name":"Randy's TV & Electronics",
    "wof:placetype":"venue"
},
  "geometry": {"coordinates":[-115.557154,32.792909],"type":"Point"}
}