{
  "type": "Feature",
  "properties": {
    "addr:full":"14221 Lambert Rd Whittier CA 90605",
    "addr:housenumber":"14221",
    "addr:postcode":"90605",
    "addr:street":"Lambert Rd",
    "iso:country":"US",
    "sg:address":"14221 Lambert Rd",
    "sg:city":"Whittier",
    "sg:classifiers":[
        {
            "category":"Wholesale",
            "subcategory":"Non-durable Goods",
            "type":"Manufacturing & Wholesale Goods"
        },
        {
            "category":"Shopping",
            "subcategory":"Bicycles & Sporting Goods",
            "type":"Retail Goods"
        },
        {
            "category":"Building & Trades",
            "subcategory":"Construction",
            "type":"Services"
        },
        {
            "category":"Sports & Exercise",
            "subcategory":"Swimming Pool",
            "type":"Entertainment"
        }
    ],
    "sg:phone":"+1 562 696 0235",
    "sg:postcode":"90605",
    "sg:province":"CA",
    "sg:tags":[
        "dry",
        "repair",
        "goods-wholesale",
        "supply",
        "cover",
        "consulting",
        "equipment",
        "designing",
        "enclosure"
    ],
    "sg:website":"http://www.davidspoolsupplies.com",
    "wof:name":"David's Pool Supplies & Service",
    "wof:placetype":"venue"
},
  "geometry": {"coordinates":[-118.02417199999999,33.948654],"type":"Point"}
}