{
  "type": "Feature",
  "properties": {
    "iso:country":"US",
    "sg:address":"5619 Cottle Rd",
    "sg:city":"San Jose",
    "sg:classifiers":[
        {
            "category":"Personal",
            "subcategory":"Barber",
            "type":"Services"
        }
    ],
    "sg:phone":"+1 408 224 7700",
    "sg:postcode":"95123",
    "sg:province":"CA",
    "wof:name":"Krown Barber Shop",
    "wof:placetype":"venue"
},
  "geometry": {"coordinates":[-121.804142,37.251083],"type":"Point"}
}