{
  "type": "Feature",
  "properties": {
    "iso:country":"US",
    "sg:address":"4750 Lincoln Blvd",
    "sg:city":"Marina del Rey",
    "sg:classifiers":[
        {
            "category":"Sports & Exercise",
            "subcategory":"Gym",
            "type":"Entertainment"
        }
    ],
    "sg:phone":"+1 323 836 5556",
    "sg:postcode":"90292",
    "sg:province":"CA",
    "sg:tags":[
        "yoga"
    ],
    "sg:website":"www.mypurelightyoga.com/",
    "wof:name":"Pure Light Yoga",
    "wof:placetype":"venue"
},
  "geometry": {"coordinates":[-118.437347,33.979258],"type":"Point"}
}