{
  "type": "Feature",
  "properties": {
    "iso:country":"US",
    "sg:address":"2690 N Marks Ave",
    "sg:city":"Fresno",
    "sg:classifiers":[
        {
            "category":"Freight",
            "type":"Transportation"
        }
    ],
    "sg:phone":"+1 559 276 9601",
    "sg:postcode":"93722",
    "sg:province":"CA",
    "sg:tags":[
        "trucking"
    ],
    "wof:name":"KHR Express",
    "wof:placetype":"venue"
},
  "geometry": {"coordinates":[-119.845786,36.777834],"type":"Point"}
}