{
  "type": "Feature",
  "properties": {
    "iso:country":"US",
    "sg:address":"2212 Pico Blvd",
    "sg:city":"Santa Monica",
    "sg:classifiers":[
        {
            "category":"Insurance",
            "subcategory":"Title Insurance",
            "type":"Services"
        }
    ],
    "sg:phone":"+1 310 566 4730",
    "sg:postcode":"90405",
    "sg:province":"CA",
    "wof:name":"ATI LLC",
    "wof:placetype":"venue"
},
  "geometry": {"coordinates":[-118.466559,34.020881],"type":"Point"}
}