{
  "type": "Feature",
  "properties": {
    "iso:country":"US",
    "sg:address":"451 Dumbarton Ave",
    "sg:city":"Redwood City",
    "sg:classifiers":[
        {
            "category":"Professional",
            "subcategory":"Management & Consulting",
            "type":"Services"
        }
    ],
    "sg:phone":"+1 650 568 0477",
    "sg:postcode":"94063",
    "sg:province":"CA",
    "sg:tags":[
        "control",
        "builder"
    ],
    "wof:name":"Zmay Construction",
    "wof:placetype":"venue"
},
  "geometry": {"coordinates":[-122.208251,37.476043],"type":"Point"}
}