{
  "type": "Feature",
  "properties": {
    "addr:full":"2971 Martha St Anderson CA 96007",
    "addr:housenumber":"2971",
    "addr:postcode":"96007",
    "addr:street":"Martha St",
    "iso:country":"US",
    "sg:address":"2971 Martha St",
    "sg:city":"Anderson",
    "sg:classifiers":[
        {
            "category":"Health Services",
            "subcategory":"Clinic",
            "type":"Services"
        },
        {
            "category":"Health Services",
            "subcategory":"Health Practitioner",
            "type":"Services"
        },
        {
            "category":"Community Center",
            "subcategory":"Social",
            "type":"Public Place"
        }
    ],
    "sg:phone":"+1 877 770 5880",
    "sg:postcode":"96007",
    "sg:province":"CA",
    "sg:tags":[
        "control",
        "information",
        "weight",
        "smoker",
        "hypnotherapy",
        "treatment",
        "reducing"
    ],
    "sg:website":"http://inspirehypnosis.reachlocal.com/?scid=1727447",
    "wof:name":"Professional Weight Loss, Smoking and Stress",
    "wof:placetype":"venue"
},
  "geometry": {"coordinates":[-122.29745800000001,40.452291],"type":"Point"}
}