{
  "type": "Feature",
  "properties": {
    "addr:full":"6153 Cahuenga Blvd North Hollywood CA 91606",
    "addr:housenumber":"6153",
    "addr:postcode":"91606",
    "addr:street":"Cahuenga Blvd",
    "iso:country":"US",
    "sg:address":"6153 Cahuenga Blvd",
    "sg:city":"North Hollywood",
    "sg:classifiers":[
        {
            "category":"Education",
            "subcategory":"School",
            "type":"Public Place"
        }
    ],
    "sg:phone":"+1 818 761 7363",
    "sg:postcode":"91606",
    "sg:province":"CA",
    "sg:tags":[
        "high",
        "middle",
        "elementary"
    ],
    "wof:name":"St Patrick's Catholic School",
    "wof:placetype":"venue"
},
  "geometry": {"coordinates":[-118.36199999999999,34.181702],"type":"Point"}
}