{
  "type": "Feature",
  "properties": {
    "iso:country":"US",
    "sg:address":"20004 State Rd",
    "sg:city":"Cerritos",
    "sg:classifiers":[
        {
            "category":"Wholesale",
            "subcategory":"Painting Supplies",
            "type":"Manufacturing & Wholesale Goods"
        }
    ],
    "sg:phone":"+1 562 924 7757",
    "sg:postcode":"90703",
    "sg:province":"CA",
    "sg:tags":[
        "product",
        "polyurethane"
    ],
    "wof:name":"Foam Molders & Specialties",
    "wof:placetype":"venue"
},
  "geometry": {"coordinates":[-118.095028,33.848393],"type":"Point"}
}