{
  "type": "Feature",
  "properties": {
    "iso:country":"US",
    "sg:address":"11599 Arno Rd",
    "sg:city":"Galt",
    "sg:classifiers":[
        {
            "category":"Building & Trades",
            "subcategory":"Construction",
            "type":"Services"
        }
    ],
    "sg:phone":"+1 916 687 6077",
    "sg:postcode":"95632",
    "sg:province":"CA",
    "sg:tags":[
        "general",
        "contractor"
    ],
    "wof:name":"Jeff Stroud Construction",
    "wof:placetype":"venue"
},
  "geometry": {"coordinates":[-121.246685,38.343073],"type":"Point"}
}