{
  "type": "Feature",
  "properties": {
    "addr:full":"2358 E Main St Ventura CA 93003",
    "addr:housenumber":"2358",
    "addr:postcode":"93003",
    "addr:street":"E Main St",
    "iso:country":"US",
    "sg:address":"2358 E Main St",
    "sg:city":"Ventura",
    "sg:classifiers":[
        {
            "category":"Food & Beverages",
            "subcategory":"Bakery",
            "type":"Retail Goods"
        }
    ],
    "sg:phone":"+1 805 643 0861",
    "sg:postcode":"93003",
    "sg:province":"CA",
    "sg:tags":[
        "baker"
    ],
    "wof:name":"City Bakery & Cafe",
    "wof:placetype":"venue"
},
  "geometry": {"coordinates":[-119.265083,34.276386],"type":"Point"}
}