{
  "type": "Feature",
  "properties": {
    "iso:country":"US",
    "sg:address":"432 1st St",
    "sg:city":"Rodeo",
    "sg:classifiers":[
        {
            "category":"Organizations",
            "subcategory":"Labor Organization",
            "type":"Services"
        }
    ],
    "sg:phone":"+1 510 799 4445",
    "sg:postcode":"94572",
    "sg:province":"CA",
    "wof:name":"Pace",
    "wof:placetype":"venue"
},
  "geometry": {"coordinates":[-122.26945000000001,38.036988],"type":"Point"}
}