{
  "type": "Feature",
  "properties": {
    "addr:full":"2600 E Bidwell St Folsom CA 95630",
    "addr:housenumber":"2600",
    "addr:postcode":"95630",
    "addr:street":"E Bidwell St",
    "iso:country":"US",
    "sg:address":"2600 E Bidwell St",
    "sg:city":"Folsom",
    "sg:classifiers":[
        {
            "category":"Real Estate",
            "subcategory":"Real Estate Services",
            "type":"Services"
        },
        {
            "category":"Banks & Credit Unions",
            "subcategory":"Financial Services",
            "type":"Services"
        }
    ],
    "sg:phone":"+1 916 988 5858",
    "sg:postcode":"95630",
    "sg:province":"CA",
    "sg:tags":[
        "loan",
        "mortgage"
    ],
    "wof:name":"Masters Team Mortgage",
    "wof:placetype":"venue"
},
  "geometry": {"coordinates":[-121.130737,38.66003],"type":"Point"}
}