{
  "type": "Feature",
  "properties": {
    "iso:country":"US",
    "sg:address":"800 W 6th St",
    "sg:city":"Los Angeles",
    "sg:classifiers":[
        {
            "category":"Professional",
            "subcategory":"Lawyer & Legal Services",
            "type":"Services"
        }
    ],
    "sg:phone":"+1 213 622 1300",
    "sg:postcode":"90017",
    "sg:province":"CA",
    "wof:name":"Kim & Song Llp",
    "wof:placetype":"venue"
},
  "geometry": {"coordinates":[-118.257929,34.050115],"type":"Point"}
}