{
  "type": "Feature",
  "properties": {
    "addr:full":"1506 W 61st Street Los Angeles CA 90047",
    "addr:housenumber":"1506",
    "addr:postcode":"90047",
    "addr:street":"W 61St Street",
    "iso:country":"US",
    "sg:address":"1506 W 61st Street",
    "sg:city":"Los Angeles",
    "sg:classifiers":[
        {
            "category":"Education",
            "subcategory":"Preschool",
            "type":"Public Place"
        },
        {
            "category":"Education",
            "subcategory":"School",
            "type":"Public Place"
        }
    ],
    "sg:phone":"+1 323 750 4218",
    "sg:postcode":"90047",
    "sg:province":"CA",
    "sg:tags":[
        "elementary"
    ],
    "wof:name":"L A Urban League Head Start",
    "wof:placetype":"venue"
},
  "geometry": {"coordinates":[-118.303113,33.984701],"type":"Point"}
}