{
  "type": "Feature",
  "properties": {
    "addr:full":"3674 Hwy 128 Geyserville CA 95441",
    "addr:housenumber":"3674",
    "addr:postcode":"95441",
    "addr:street":"Hwy 128",
    "iso:country":"US",
    "sg:address":"3674 Hwy 128",
    "sg:city":"Geyserville",
    "sg:classifiers":[
        {
            "category":"Farming",
            "subcategory":"Vineyard",
            "type":"Manufacturing & Wholesale Goods"
        }
    ],
    "sg:phone":"+1 707 857 4234",
    "sg:postcode":"95441",
    "sg:province":"CA",
    "sg:tags":[
        "grape"
    ],
    "wof:name":"Wasson Vineyards",
    "wof:placetype":"venue"
},
  "geometry": {"coordinates":[-122.852126,38.691817],"type":"Point"}
}