{
  "type": "Feature",
  "properties": {
    "iso:country":"US",
    "sg:address":"155 E Campbell Ave",
    "sg:city":"Campbell",
    "sg:classifiers":[
        {
            "category":"Real Estate",
            "subcategory":"Real Estate Agent",
            "type":"Services"
        }
    ],
    "sg:phone":"+1 408 379 1532",
    "sg:postcode":"95008",
    "sg:province":"CA",
    "sg:tags":[
        "appraiser"
    ],
    "wof:name":"Quality Appraisals",
    "wof:placetype":"venue"
},
  "geometry": {"coordinates":[-121.946078,37.287115],"type":"Point"}
}