{
  "type": "Feature",
  "properties": {
    "addr:full":"2156 S Atlantic Blvd Monterey Park CA 91754",
    "addr:housenumber":"2156",
    "addr:postcode":"91754",
    "addr:street":"S Atlantic Blvd",
    "iso:country":"US",
    "sg:address":"2156 S Atlantic Blvd",
    "sg:city":"Monterey Park",
    "sg:classifiers":[
        {
            "category":"Banks & Credit Unions",
            "subcategory":"Bank",
            "type":"Services"
        }
    ],
    "sg:phone":"+1 323 869 2200",
    "sg:postcode":"91754",
    "sg:province":"CA",
    "sg:tags":[
        "mortgage"
    ],
    "wof:name":"Countrywide",
    "wof:placetype":"venue"
},
  "geometry": {"coordinates":[-118.14599699999999,34.037676],"type":"Point"}
}