{
  "type": "Feature",
  "properties": {
    "addr:full":"221 E 3rd St Corona CA 92879",
    "addr:housenumber":"221",
    "addr:postcode":"92879",
    "addr:street":"E 3Rd St",
    "iso:country":"US",
    "sg:address":"221 E 3rd St",
    "sg:city":"Corona",
    "sg:classifiers":[
        {
            "category":"Shopping",
            "subcategory":"Pharmacy",
            "type":"Retail Goods"
        }
    ],
    "sg:phone":"+1 951 735 4600",
    "sg:postcode":"92879",
    "sg:province":"CA",
    "wof:name":"Corona Drugs",
    "wof:placetype":"venue"
},
  "geometry": {"coordinates":[-117.56370200000001,33.87836],"type":"Point"}
}