{
  "type": "Feature",
  "properties": {
    "iso:country":"US",
    "sg:address":"221 E 3rd St",
    "sg:city":"Corona",
    "sg:classifiers":[
        {
            "category":"Shopping",
            "subcategory":"Pharmacy",
            "type":"Retail Goods"
        }
    ],
    "sg:phone":"+1 951 735 4600",
    "sg:postcode":"92879",
    "sg:province":"CA",
    "wof:name":"Corona Drugs",
    "wof:placetype":"venue"
},
  "geometry": {"coordinates":[-117.563702,33.87836],"type":"Point"}
}