{
  "type": "Feature",
  "properties": {
    "addr:full":"3436 South Ct Palo Alto CA 94306",
    "addr:housenumber":"3436",
    "addr:postcode":"94306",
    "addr:street":"South Ct",
    "iso:country":"US",
    "sg:address":"3436 South Ct",
    "sg:city":"Palo Alto",
    "sg:classifiers":[
        {
            "category":"Banks & Credit Unions",
            "subcategory":"Bank",
            "type":"Services"
        }
    ],
    "sg:phone":"+1 650 424 8723",
    "sg:postcode":"94306",
    "sg:province":"CA",
    "sg:tags":[
        "broker",
        "mortgage"
    ],
    "wof:name":"Golden Bay Realty",
    "wof:placetype":"venue"
},
  "geometry": {"coordinates":[-122.12196900000001,37.421419],"type":"Point"}
}