{
  "type": "Feature",
  "properties": {
    "addr:full":"10227 Prospect Ave Santee CA 92071",
    "addr:housenumber":"10227",
    "addr:postcode":"92071",
    "addr:street":"Prospect Ave",
    "iso:country":"US",
    "sg:address":"10227 Prospect Ave",
    "sg:city":"Santee",
    "sg:classifiers":[
        {
            "category":"Retail",
            "subcategory":"Auto Repair",
            "type":"Services"
        }
    ],
    "sg:phone":"+1 619 449 5191",
    "sg:postcode":"92071",
    "sg:province":"CA",
    "sg:tags":[
        "repairing",
        "automobile"
    ],
    "wof:name":"Doe's Automotive Ctr",
    "wof:placetype":"venue"
},
  "geometry": {"coordinates":[-116.975494,32.831209],"type":"Point"}
}