{
  "type": "Feature",
  "properties": {
    "iso:country":"US",
    "sg:address":"9275 Baseline Rd",
    "sg:city":"Rancho Cucamonga",
    "sg:classifiers":[
        {
            "category":"Health Services",
            "subcategory":"Doctor",
            "type":"Services"
        }
    ],
    "sg:phone":"+1 909 945 5008",
    "sg:postcode":"91730",
    "sg:province":"CA",
    "sg:tags":[
        "dentist"
    ],
    "wof:name":"Samir Batniji & Assoc",
    "wof:placetype":"venue"
},
  "geometry": {"coordinates":[-117.603207,34.121472],"type":"Point"}
}