{
  "type": "Feature",
  "properties": {
    "addr:full":"2395 21st Ave San Francisco CA 94116",
    "addr:housenumber":"2395",
    "addr:postcode":"94116",
    "addr:street":"21St Ave",
    "iso:country":"US",
    "sg:address":"2395 21st Ave",
    "sg:city":"San Francisco",
    "sg:classifiers":[
        {
            "category":"Shopping",
            "type":"Retail Goods"
        },
        {
            "category":"Shopping",
            "subcategory":"Gifts & Souvenirs",
            "type":"Retail Goods"
        }
    ],
    "sg:phone":"+1 415 731 1842",
    "sg:postcode":"94116",
    "sg:province":"CA",
    "sg:tags":[
        "collectible",
        "merchandise"
    ],
    "wof:name":"Arrow Stamp Company",
    "wof:placetype":"venue"
},
  "geometry": {"coordinates":[-122.47801,37.744742],"type":"Point"}
}