{
  "type": "Feature",
  "properties": {
    "iso:country":"US",
    "sg:address":"1036 Highland Dr",
    "sg:city":"Del Mar",
    "sg:classifiers":[
        {
            "category":"Professional",
            "subcategory":"Research",
            "type":"Services"
        }
    ],
    "sg:phone":"+1 858 755 9437",
    "sg:postcode":"92014",
    "sg:province":"CA",
    "sg:tags":[
        "development",
        "laboratory"
    ],
    "wof:name":"Cladan Technologies Inc",
    "wof:placetype":"venue"
},
  "geometry": {"coordinates":[-117.253202,32.986892],"type":"Point"}
}