{
  "type": "Feature",
  "properties": {
    "iso:country":"US",
    "sg:address":"5065 Boyd Rd",
    "sg:city":"Arcata",
    "sg:classifiers":[
        {
            "category":"Food & Beverages",
            "subcategory":"Bakery",
            "type":"Retail Goods"
        }
    ],
    "sg:phone":"+1 707 825 0490",
    "sg:postcode":"95521",
    "sg:province":"CA",
    "sg:tags":[
        "baker"
    ],
    "wof:name":"William's Bakery",
    "wof:placetype":"venue"
},
  "geometry": {"coordinates":[-124.06706800000001,40.910776],"type":"Point"}
}