{
  "type": "Feature",
  "properties": {
    "addr:full":"1333 Reche Canyon Rd Colton CA 92324",
    "addr:housenumber":"1333",
    "addr:postcode":"92324",
    "addr:street":"Reche Canyon Rd",
    "iso:country":"US",
    "sg:address":"1333 Reche Canyon Rd",
    "sg:city":"Colton",
    "sg:classifiers":[
        {
            "category":"Retail",
            "subcategory":"Laundry & Dry Cleaning",
            "type":"Services"
        }
    ],
    "sg:phone":"+1 909 825 4373",
    "sg:postcode":"92324",
    "sg:province":"CA",
    "sg:tags":[
        "cleaners",
        "rug",
        "carpet"
    ],
    "wof:name":"A Pete & Re-Pete Carpet Clean",
    "wof:placetype":"venue"
},
  "geometry": {"coordinates":[-117.28867099999999,34.047958],"type":"Point"}
}