{
  "type": "Feature",
  "properties": {
    "addr:full":"27 Ketch St Marina Del Rey CA 90292",
    "addr:housenumber":"27",
    "addr:postcode":"90292",
    "addr:street":"Ketch St",
    "iso:country":"US",
    "sg:address":"27 Ketch St",
    "sg:city":"Marina Del Rey",
    "sg:classifiers":[
        {
            "category":"Real Estate",
            "subcategory":"Real Estate Agent",
            "type":"Services"
        }
    ],
    "sg:phone":"+1 310 821 4448",
    "sg:postcode":"90292",
    "sg:province":"CA",
    "wof:name":"Westland Mortgage Inc",
    "wof:placetype":"venue"
},
  "geometry": {"coordinates":[-118.461022,33.973789],"type":"Point"}
}