{
  "type": "Feature",
  "properties": {
    "addr:full":"3687 Folsom St San Francisco CA 94110",
    "addr:housenumber":"3687",
    "addr:postcode":"94110",
    "addr:street":"Folsom St",
    "iso:country":"US",
    "sg:address":"3687 Folsom St",
    "sg:city":"San Francisco",
    "sg:classifiers":[
        {
            "category":"Real Estate",
            "subcategory":"Architect",
            "type":"Services"
        }
    ],
    "sg:phone":"+1 415 282 4428",
    "sg:postcode":"94110",
    "sg:province":"CA",
    "sg:website":"www.leehammack.com",
    "wof:name":"Edward Lee Hammack",
    "wof:placetype":"venue"
},
  "geometry": {"coordinates":[-122.413106,37.740432],"type":"Point"}
}