{
  "type": "Feature",
  "properties": {
    "iso:country":"US",
    "sg:address":"3412 Ming Ave",
    "sg:city":"Bakersfield",
    "sg:classifiers":[
        {
            "category":"Shopping",
            "subcategory":"Department Store",
            "type":"Retail Goods"
        }
    ],
    "sg:phone":"+1 661 831 2942",
    "sg:postcode":"93309",
    "sg:province":"CA",
    "wof:name":"T J Maxx",
    "wof:placetype":"venue"
},
  "geometry": {"coordinates":[-119.040154,35.339552],"type":"Point"}
}