{
  "type": "Feature",
  "properties": {
    "iso:country":"US",
    "sg:address":"34177 Fremont Blvd",
    "sg:city":"Fremont",
    "sg:classifiers":[
        {
            "category":"Food & Beverages",
            "subcategory":"Liquor & Beverages",
            "type":"Retail Goods"
        }
    ],
    "sg:phone":"+1 510 795 1007",
    "sg:postcode":"94555",
    "sg:province":"CA",
    "wof:name":"Charter Liquors",
    "wof:placetype":"venue"
},
  "geometry": {"coordinates":[-122.044711,37.5768],"type":"Point"}
}