{
  "type": "Feature",
  "properties": {
    "addr:full":"34177 Fremont Blvd Fremont CA 94555",
    "addr:housenumber":"34177",
    "addr:postcode":"94555",
    "addr:street":"Fremont Blvd",
    "iso:country":"US",
    "sg:address":"34177 Fremont Blvd",
    "sg:city":"Fremont",
    "sg:classifiers":[
        {
            "category":"Food & Beverages",
            "subcategory":"Liquor & Beverages",
            "type":"Retail Goods"
        }
    ],
    "sg:phone":"+1 510 795 1007",
    "sg:postcode":"94555",
    "sg:province":"CA",
    "wof:name":"Charter Liquors",
    "wof:placetype":"venue"
},
  "geometry": {"coordinates":[-122.04471100000001,37.5768],"type":"Point"}
}