{
  "type": "Feature",
  "properties": {
    "iso:country":"US",
    "sg:address":"11914 Front St",
    "sg:city":"Norwalk",
    "sg:classifiers":[
        {
            "category":"Building & Trades",
            "subcategory":"Construction",
            "type":"Services"
        }
    ],
    "sg:phone":"+1 562 860 0604",
    "sg:postcode":"90650",
    "sg:province":"CA",
    "sg:tags":[
        "sweeping",
        "street",
        "municipal"
    ],
    "wof:name":"Nationwide Environmental Svcs",
    "wof:placetype":"venue"
},
  "geometry": {"coordinates":[-118.08128000000001,33.911323],"type":"Point"}
}