{
  "type": "Feature",
  "properties": {
    "iso:country":"US",
    "sg:address":"8005 Archibald Ave",
    "sg:city":"Rancho Cucamonga",
    "sg:classifiers":[
        {
            "category":"Professional",
            "subcategory":"Computer Services",
            "type":"Services"
        }
    ],
    "sg:phone":"+1 909 944 7104",
    "sg:postcode":"91730",
    "sg:province":"CA",
    "sg:tags":[
        "repair"
    ],
    "wof:name":"Computer Guy Co",
    "wof:placetype":"venue"
},
  "geometry": {"coordinates":[-117.593403,34.107609],"type":"Point"}
}