{
  "type": "Feature",
  "properties": {
    "addr:full":"200 Derrick Ave Mendota CA 93640",
    "addr:housenumber":"200",
    "addr:postcode":"93640",
    "addr:street":"Derrick Ave",
    "iso:country":"US",
    "sg:address":"200 Derrick Ave",
    "sg:city":"Mendota",
    "sg:classifiers":[
        {
            "category":"Restaurant",
            "type":"Food & Drink"
        }
    ],
    "sg:phone":"+1 559 655 8678",
    "sg:postcode":"93640",
    "sg:province":"CA",
    "sg:tags":[
        "asian",
        "chinese",
        "pan"
    ],
    "wof:name":"Wong's Restaurant",
    "wof:placetype":"venue"
},
  "geometry": {"coordinates":[-120.394508,36.433805],"type":"Point"}
}