{
  "type": "Feature",
  "properties": {
    "iso:country":"US",
    "sg:address":"16 W Curtis St",
    "sg:city":"Salinas",
    "sg:classifiers":[
        {
            "category":"Personal",
            "subcategory":"Beauty Salon",
            "type":"Services"
        }
    ],
    "sg:phone":"+1 831 444 6584",
    "sg:postcode":"93906",
    "sg:province":"CA",
    "wof:name":"Personal Touch Salon",
    "wof:placetype":"venue"
},
  "geometry": {"coordinates":[-121.653886,36.701692],"type":"Point"}
}