{
  "type": "Feature",
  "properties": {
    "iso:country":"US",
    "sg:address":"24422 Hawthorne Blvd Ste B",
    "sg:city":"Torrance",
    "sg:phone":"+1 310 791 0903",
    "sg:postcode":"90505",
    "sg:province":"CA",
    "wof:name":"J T Hair Salon",
    "wof:placetype":"venue"
},
  "geometry": {"coordinates":[-118.35111999999999,33.801753],"type":"Point"}
}