{
  "type": "Feature",
  "properties": {
    "iso:country":"US",
    "sg:address":"1103 Hamner Ave",
    "sg:city":"Norco",
    "sg:classifiers":[
        {
            "category":"Manufacturing",
            "subcategory":"Motor Vehicles & Parts",
            "type":"Manufacturing & Wholesale Goods"
        }
    ],
    "sg:phone":"+1 951 371 8672",
    "sg:postcode":"92860",
    "sg:province":"CA",
    "sg:tags":[
        "mfg"
    ],
    "wof:name":"Ameduri Racing Products",
    "wof:placetype":"venue"
},
  "geometry": {"coordinates":[-117.562634,33.899094],"type":"Point"}
}