{
  "type": "Feature",
  "properties": {
    "addr:full":"1851 10th Ave Oakland CA 94606",
    "addr:housenumber":"1851",
    "addr:postcode":"94606",
    "addr:street":"10Th Ave",
    "iso:country":"US",
    "sg:address":"1851 10th Ave",
    "sg:city":"Oakland",
    "sg:classifiers":[
        {
            "category":"Social Services",
            "type":"Services"
        }
    ],
    "sg:phone":"+1 510 534 1986",
    "sg:postcode":"94606",
    "sg:province":"CA",
    "sg:tags":[
        "worker"
    ],
    "wof:name":"Allied Fellowship Svc",
    "wof:placetype":"venue"
},
  "geometry": {"coordinates":[-122.245543,37.795092],"type":"Point"}
}