{
  "type": "Feature",
  "properties": {
    "iso:country":"US",
    "sg:address":"3651 S El Camino Real",
    "sg:city":"San Mateo",
    "sg:classifiers":[
        {
            "category":"Retail",
            "subcategory":"Car Wash",
            "type":"Services"
        }
    ],
    "sg:phone":"+1 650 341 2503",
    "sg:postcode":"94403",
    "sg:province":"CA",
    "wof:name":"Hillsdale Carwash",
    "wof:placetype":"venue"
},
  "geometry": {"coordinates":[-122.293999,37.534],"type":"Point"}
}