{
  "type": "Feature",
  "properties": {
    "addr:full":"387 12th St Oakland CA 94607",
    "addr:housenumber":"387",
    "addr:postcode":"94607",
    "addr:street":"12Th St",
    "iso:country":"US",
    "sg:address":"387 12th St",
    "sg:city":"Oakland",
    "sg:classifiers":[
        {
            "category":"Organizations",
            "subcategory":"Professional Association",
            "type":"Services"
        }
    ],
    "sg:phone":"+1 510 763 7710",
    "sg:postcode":"94607",
    "sg:province":"CA",
    "wof:name":"Lee's Family Benevolent Assn",
    "wof:placetype":"venue"
},
  "geometry": {"coordinates":[-122.27015900000001,37.80205],"type":"Point"}
}