{
  "type": "Feature",
  "properties": {
    "addr:full":"1894 E Washington Blvd Pasadena CA 91104",
    "addr:housenumber":"1894",
    "addr:postcode":"91104",
    "addr:street":"E Washington Blvd",
    "iso:country":"US",
    "sg:address":"1894 E Washington Blvd",
    "sg:city":"Pasadena",
    "sg:classifiers":[
        {
            "category":"Wholesale",
            "subcategory":"Jewelry",
            "type":"Manufacturing & Wholesale Goods"
        }
    ],
    "sg:phone":"+1 626 564 8888",
    "sg:postcode":"91104",
    "sg:province":"CA",
    "sg:tags":[
        "watch"
    ],
    "wof:name":"Fuzo Watch Collection",
    "wof:placetype":"venue"
},
  "geometry": {"coordinates":[-118.111414,34.169068],"type":"Point"}
}