{
  "type": "Feature",
  "properties": {
    "addr:full":"16660 Paramount Blvd Paramount CA 90723",
    "addr:housenumber":"16660",
    "addr:postcode":"90723",
    "addr:street":"Paramount Blvd",
    "iso:country":"US",
    "sg:address":"16660 Paramount Blvd",
    "sg:city":"Paramount",
    "sg:classifiers":[
        {
            "category":"Health Services",
            "subcategory":"Doctor",
            "type":"Services"
        }
    ],
    "sg:phone":"+1 562 404 0503",
    "sg:postcode":"90723",
    "sg:province":"CA",
    "sg:tags":[
        "physician",
        "family",
        "practice",
        "surgeons",
        "medicine"
    ],
    "wof:name":"S Tan Joseph Md",
    "wof:placetype":"venue"
},
  "geometry": {"coordinates":[-118.15998399999999,33.882579],"type":"Point"}
}