{
  "type": "Feature",
  "properties": {
    "addr:full":"1343 Montana Dr Concord CA 94521",
    "addr:housenumber":"1343",
    "addr:postcode":"94521",
    "addr:street":"Montana Dr",
    "iso:country":"US",
    "sg:address":"1343 Montana Dr",
    "sg:city":"Concord",
    "sg:classifiers":[
        {
            "category":"Building & Trades",
            "subcategory":"Construction",
            "type":"Services"
        }
    ],
    "sg:phone":"+1 925 383 2947",
    "sg:postcode":"94521",
    "sg:province":"CA",
    "sg:tags":[
        "house"
    ],
    "wof:name":"Kaljian Construction",
    "wof:placetype":"venue"
},
  "geometry": {"coordinates":[-121.95381999999999,37.942472],"type":"Point"}
}