{
  "type": "Feature",
  "properties": {
    "iso:country":"US",
    "sg:address":"1468 E Foothill Blvd",
    "sg:city":"San Luis Obispo",
    "sg:classifiers":[
        {
            "category":"Organizations",
            "subcategory":"Religious Organization",
            "type":"Services"
        }
    ],
    "sg:phone":"+1 805 543 7367",
    "sg:postcode":"93405",
    "sg:province":"CA",
    "wof:name":"Front Porch Campus Ministries",
    "wof:placetype":"venue"
},
  "geometry": {"coordinates":[-120.661575,35.296445],"type":"Point"}
}