{
  "type": "Feature",
  "properties": {
    "addr:full":"1243 Saviers Rd Oxnard CA 93033",
    "addr:housenumber":"1243",
    "addr:postcode":"93033",
    "addr:street":"Saviers Rd",
    "iso:country":"US",
    "sg:address":"1243 Saviers Rd",
    "sg:city":"Oxnard",
    "sg:classifiers":[
        {
            "category":"Personal",
            "subcategory":"Nail Salon",
            "type":"Services"
        }
    ],
    "sg:phone":"+1 805 483 1687",
    "sg:postcode":"93033",
    "sg:province":"CA",
    "wof:name":"Lady Nails",
    "wof:placetype":"venue"
},
  "geometry": {"coordinates":[-119.177558,34.187577],"type":"Point"}
}