{
  "type": "Feature",
  "properties": {
    "addr:full":"17185 Via Barranca del Zorro Rancho Santa Fe CA 92067",
    "addr:housenumber":"17185",
    "addr:postcode":"92067",
    "addr:street":"Via Barranca Del Zorro",
    "iso:country":"US",
    "sg:address":"17185 Via Barranca del Zorro",
    "sg:city":"Rancho Santa Fe",
    "sg:classifiers":[
        {
            "category":"Building & Trades",
            "subcategory":"Construction",
            "type":"Services"
        }
    ],
    "sg:phone":"+1 858 756 0157",
    "sg:postcode":"92067",
    "sg:province":"CA",
    "sg:tags":[
        "contractor"
    ],
    "wof:name":"S & G Construction LLC",
    "wof:placetype":"venue"
},
  "geometry": {"coordinates":[-117.187792,33.009195],"type":"Point"}
}