{
  "type": "Feature",
  "properties": {
    "addr:full":"22360 Loch Lomond Dr Sun City CA 92587",
    "addr:housenumber":"22360",
    "addr:postcode":"92587",
    "addr:street":"Loch Lomond Dr",
    "iso:country":"US",
    "sg:address":"22360 Loch Lomond Dr",
    "sg:city":"Sun City",
    "sg:classifiers":[
        {
            "category":"Professional",
            "type":"Services"
        }
    ],
    "sg:phone":"+1 951 244 4634",
    "sg:postcode":"92587",
    "sg:province":"CA",
    "wof:name":"Strictnine Street Wear",
    "wof:placetype":"venue"
},
  "geometry": {"coordinates":[-117.271293,33.679137],"type":"Point"}
}