{
  "type": "Feature",
  "properties": {
    "iso:country":"US",
    "sg:address":"1420 Industrial Ave",
    "sg:city":"San Jose",
    "sg:classifiers":[
        {
            "category":"Real Estate",
            "subcategory":"Architect",
            "type":"Services"
        }
    ],
    "sg:phone":"+1 408 984 3939",
    "sg:postcode":"95112",
    "sg:province":"CA",
    "sg:tags":[
        "illustrator",
        "architectural"
    ],
    "wof:name":"Sunseri Design",
    "wof:placetype":"venue"
},
  "geometry": {"coordinates":[-121.900197,37.370898],"type":"Point"}
}