{
  "type": "Feature",
  "properties": {
    "iso:country":"US",
    "sg:address":"1040 Cll Recodo",
    "sg:city":"San Clemente",
    "sg:classifiers":[
        {
            "category":"Shopping",
            "subcategory":"Jewelry",
            "type":"Retail Goods"
        }
    ],
    "sg:phone":"+1 949 366 8610",
    "sg:postcode":"92673",
    "sg:province":"CA",
    "sg:tags":[
        "jeweler"
    ],
    "sg:website":"www.safashions.com",
    "wof:name":"S & A Wholesale Fashion Jwlry",
    "wof:placetype":"venue"
},
  "geometry": {"coordinates":[-117.598632,33.453529],"type":"Point"}
}