{
  "type": "Feature",
  "properties": {
    "addr:full":"4747 Snow Dr San Jose CA 95111",
    "addr:housenumber":"4747",
    "addr:postcode":"95111",
    "addr:street":"Snow Dr",
    "iso:country":"US",
    "sg:address":"4747 Snow Dr",
    "sg:city":"San Jose",
    "sg:classifiers":[
        {
            "category":"Professional",
            "subcategory":"Business Services",
            "type":"Services"
        }
    ],
    "sg:phone":"+1 408 226 3374",
    "sg:postcode":"95111",
    "sg:province":"CA",
    "sg:tags":[
        "recording",
        "studio"
    ],
    "sg:website":"www.daytimeproductions.com",
    "wof:name":"Daytime Productions",
    "wof:placetype":"venue"
},
  "geometry": {"coordinates":[-121.808431,37.277265],"type":"Point"}
}