{
  "type": "Feature",
  "properties": {
    "addr:full":"402 Loma Alta Dr Santa Barbara CA 93109",
    "addr:housenumber":"402",
    "addr:postcode":"93109",
    "addr:street":"Loma Alta Dr",
    "iso:country":"US",
    "sg:address":"402 Loma Alta Dr",
    "sg:city":"Santa Barbara",
    "sg:classifiers":[
        {
            "category":"Professional",
            "subcategory":"Business Services",
            "type":"Services"
        }
    ],
    "sg:phone":"+1 805 966 6374",
    "sg:postcode":"93109",
    "sg:province":"CA",
    "sg:tags":[
        "recording",
        "studio"
    ],
    "sg:website":"www.mastertracks.net",
    "wof:name":"Master Tracks Recording",
    "wof:placetype":"venue"
},
  "geometry": {"coordinates":[-119.70356700000001,34.408025],"type":"Point"}
}