{
  "type": "Feature",
  "properties": {
    "iso:country":"US",
    "sg:address":"1444 N California Blvd",
    "sg:city":"Walnut Creek",
    "sg:classifiers":[
        {
            "category":"Restaurant",
            "type":"Food & Drink"
        }
    ],
    "sg:menulink":"http://www.allmenus.com/ca/central-contra-costa/267389-mccoveys/menu/",
    "sg:phone":"+1 925 944 9444",
    "sg:postcode":"94596",
    "sg:province":"CA",
    "sg:tags":[
        "american"
    ],
    "wof:name":"McCovey's",
    "wof:placetype":"venue"
},
  "geometry": {"coordinates":[-122.06329100000001,37.898953],"type":"Point"}
}