{
  "type": "Feature",
  "properties": {
    "addr:full":"14226 Bourgeois Way San Diego CA 92129",
    "addr:housenumber":"14226",
    "addr:postcode":"92129",
    "addr:street":"Bourgeois Way",
    "iso:country":"US",
    "sg:address":"14226 Bourgeois Way",
    "sg:city":"San Diego",
    "sg:classifiers":[
        {
            "category":"Wholesale",
            "subcategory":"Home Furnishings",
            "type":"Manufacturing & Wholesale Goods"
        }
    ],
    "sg:phone":"+1 858 484 2243",
    "sg:postcode":"92129",
    "sg:province":"CA",
    "wof:name":"Golden State Enterprises",
    "wof:placetype":"venue"
},
  "geometry": {"coordinates":[-117.12809900000001,32.976829],"type":"Point"}
}