{
  "type": "Feature",
  "properties": {
    "addr:full":"3160 Terrace Dr Riverside CA 92507",
    "addr:housenumber":"3160",
    "addr:postcode":"92507",
    "addr:street":"Terrace Dr",
    "iso:country":"US",
    "sg:address":"3160 Terrace Dr",
    "sg:city":"Riverside",
    "sg:classifiers":[
        {
            "category":"Professional",
            "subcategory":"Management & Consulting",
            "type":"Services"
        }
    ],
    "sg:phone":"+1 951 682 0655",
    "sg:postcode":"92507",
    "sg:province":"CA",
    "sg:tags":[
        "retail",
        "direct",
        "sales"
    ],
    "wof:name":"One Of A Kind Designs",
    "wof:placetype":"venue"
},
  "geometry": {"coordinates":[-117.310301,33.984651],"type":"Point"}
}