{
  "type": "Feature",
  "properties": {
    "addr:full":"717 S Myrtle Ave Monrovia CA 91016",
    "addr:housenumber":"717",
    "addr:postcode":"91016",
    "addr:street":"S Myrtle Ave",
    "iso:country":"US",
    "sg:address":"717 S Myrtle Ave",
    "sg:city":"Monrovia",
    "sg:classifiers":[
        {
            "category":"Manufacturing",
            "subcategory":"Electronics",
            "type":"Manufacturing & Wholesale Goods"
        }
    ],
    "sg:phone":"+1 626 358 2559",
    "sg:postcode":"91016",
    "sg:province":"CA",
    "sg:tags":[
        "equipment",
        "telephone",
        "system"
    ],
    "sg:website":"www.dynametric.com",
    "wof:name":"Dynametric",
    "wof:placetype":"venue"
},
  "geometry": {"coordinates":[-118.000936,34.144633],"type":"Point"}
}