{
  "type": "Feature",
  "properties": {
    "iso:country":"US",
    "sg:address":"1580 Francisco St",
    "sg:city":"Torrance",
    "sg:classifiers":[
        {
            "category":"Professional",
            "subcategory":"Art Services",
            "type":"Services"
        }
    ],
    "sg:phone":"+1 310 525 1600",
    "sg:postcode":"90501",
    "sg:province":"CA",
    "sg:tags":[
        "photographer"
    ],
    "wof:name":"Pictage",
    "wof:placetype":"venue"
},
  "geometry": {"coordinates":[-118.307261,33.848332],"type":"Point"}
}