{
  "type": "Feature",
  "properties": {
    "addr:full":"129 Cabrillo St Costa Mesa CA 92627",
    "addr:housenumber":"129",
    "addr:postcode":"92627",
    "addr:street":"Cabrillo St",
    "iso:country":"US",
    "sg:address":"129 Cabrillo St",
    "sg:city":"Costa Mesa",
    "sg:classifiers":[
        {
            "category":"Travel",
            "subcategory":"Hotels & Motels",
            "type":"Entertainment"
        }
    ],
    "sg:phone":"+1 949 548 2823",
    "sg:postcode":"92627",
    "sg:province":"CA",
    "sg:tags":[
        "resort",
        "operation"
    ],
    "wof:name":"Bamboo Beach Resort",
    "wof:placetype":"venue"
},
  "geometry": {"coordinates":[-117.91975100000001,33.637827],"type":"Point"}
}