{
  "type": "Feature",
  "properties": {
    "addr:full":"8510 Production Ave San Diego CA 92121",
    "addr:housenumber":"8510",
    "addr:postcode":"92121",
    "addr:street":"Production Ave",
    "iso:country":"US",
    "sg:address":"8510 Production Ave",
    "sg:city":"San Diego",
    "sg:classifiers":[
        {
            "category":"Professional",
            "subcategory":"Art Services",
            "type":"Services"
        }
    ],
    "sg:phone":"+1 858 271 1159",
    "sg:postcode":"92121",
    "sg:province":"CA",
    "sg:tags":[
        "graphic",
        "designer"
    ],
    "wof:name":"Logo's 2000",
    "wof:placetype":"venue"
},
  "geometry": {"coordinates":[-117.165093,32.885437],"type":"Point"}
}