{
  "type": "Feature",
  "properties": {
    "addr:full":"1243 E Spruce Ave Fresno CA 93720",
    "addr:housenumber":"1243",
    "addr:postcode":"93720",
    "addr:street":"E Spruce Ave",
    "iso:country":"US",
    "sg:address":"1243 E Spruce Ave",
    "sg:city":"Fresno",
    "sg:classifiers":[
        {
            "category":"Health Services",
            "subcategory":"Doctor",
            "type":"Services"
        }
    ],
    "sg:phone":"+1 559 439 7226",
    "sg:postcode":"93720",
    "sg:province":"CA",
    "sg:tags":[
        "physician",
        "surgeon"
    ],
    "wof:name":"Physicians Imaging",
    "wof:placetype":"venue"
},
  "geometry": {"coordinates":[-119.760048,36.841845],"type":"Point"}
}