{
  "type": "Feature",
  "properties": {
    "iso:country":"US",
    "sg:address":"5131 State Rte 140",
    "sg:city":"Mariposa",
    "sg:classifiers":[
        {
            "category":"Health Services",
            "subcategory":"Doctor",
            "type":"Services"
        }
    ],
    "sg:phone":"+1 209 966 4600",
    "sg:postcode":"95338",
    "sg:province":"CA",
    "sg:tags":[
        "dentist"
    ],
    "wof:name":"Richard Rowan DDS",
    "wof:placetype":"venue"
},
  "geometry": {"coordinates":[-119.971149,37.490483],"type":"Point"}
}