{
  "type": "Feature",
  "properties": {
    "iso:country":"US",
    "sg:address":"3870 Chicago Ave",
    "sg:city":"Riverside",
    "sg:classifiers":[
        {
            "category":"Restaurant",
            "type":"Food & Drink"
        }
    ],
    "sg:phone":"+1 951 788 4410",
    "sg:postcode":"92507",
    "sg:province":"CA",
    "wof:name":"Tony's Mexican Food",
    "wof:placetype":"venue"
},
  "geometry": {"coordinates":[-117.348423,33.972525],"type":"Point"}
}