{
  "type": "Feature",
  "properties": {
    "addr:full":"16000 Ventura Blvd Encino CA 91436",
    "addr:housenumber":"16000",
    "addr:postcode":"91436",
    "addr:street":"Ventura Blvd",
    "iso:country":"US",
    "sg:address":"16000 Ventura Blvd",
    "sg:city":"Encino",
    "sg:classifiers":[
        {
            "category":"Professional",
            "subcategory":"Lawyer & Legal Services",
            "type":"Services"
        }
    ],
    "sg:phone":"+1 818 382 6480",
    "sg:postcode":"91436",
    "sg:province":"CA",
    "sg:tags":[
        "attorney"
    ],
    "wof:name":"John AC Gibson Law Office",
    "wof:placetype":"venue"
},
  "geometry": {"coordinates":[-118.483616,34.156369],"type":"Point"}
}