{
  "type": "Feature",
  "properties": {
    "addr:full":"1102 Broadway Santa Monica CA 90401",
    "addr:housenumber":"1102",
    "addr:postcode":"90401",
    "addr:street":"Broadway",
    "iso:country":"US",
    "sg:address":"1102 Broadway",
    "sg:city":"Santa Monica",
    "sg:classifiers":[
        {
            "category":"Recreation",
            "type":"Entertainment"
        }
    ],
    "sg:phone":"+1 310 394 5188",
    "sg:postcode":"90401",
    "sg:province":"CA",
    "sg:tags":[
        "martial",
        "arts",
        "instruction"
    ],
    "wof:name":"United Studios Of Self Defense",
    "wof:placetype":"venue"
},
  "geometry": {"coordinates":[-118.486462,34.020752],"type":"Point"}
}