{
  "type": "Feature",
  "properties": {
    "addr:full":"503 Clement St San Francisco CA 94118",
    "addr:housenumber":"503",
    "addr:postcode":"94118",
    "addr:street":"Clement St",
    "iso:country":"US",
    "sg:address":"503 Clement St",
    "sg:city":"San Francisco",
    "sg:classifiers":[
        {
            "category":"Restaurant",
            "type":"Food & Drink"
        }
    ],
    "sg:menulink":"http://www.allmenus.com/ca/san-francisco/62732-wing-lee-bakery/menu/",
    "sg:phone":"+1 415 668 9481",
    "sg:postcode":"94118",
    "sg:province":"CA",
    "sg:tags":[
        "dim",
        "sum",
        "asian"
    ],
    "wof:name":"Wing Lee Bakery",
    "wof:placetype":"venue"
},
  "geometry": {"coordinates":[-122.464583,37.782984],"type":"Point"}
}