{
  "type": "Feature",
  "properties": {
    "iso:country":"US",
    "sg:address":"9791 Lincoln Village Dr",
    "sg:city":"Sacramento",
    "sg:classifiers":[
        {
            "category":"Food & Beverages",
            "subcategory":"Liquor & Beverages",
            "type":"Retail Goods"
        }
    ],
    "sg:phone":"+1 916 366 5638",
    "sg:postcode":"95827",
    "sg:province":"CA",
    "sg:tags":[
        "beer",
        "spirit",
        "wine"
    ],
    "wof:name":"Liquor Loft",
    "wof:placetype":"venue"
},
  "geometry": {"coordinates":[-121.33200100000001,38.561798],"type":"Point"}
}