{
  "type": "Feature",
  "properties": {
    "addr:full":"503 1/2 S Myrtle Ave Monrovia CA 91016",
    "addr:housenumber":"503 1 / 2 s",
    "addr:postcode":"91016",
    "addr:street":"Myrtle Ave",
    "iso:country":"US",
    "sg:address":"503 1/2 S Myrtle Ave",
    "sg:city":"Monrovia",
    "sg:classifiers":[
        {
            "category":"Communications",
            "subcategory":"Film & Video Production",
            "type":"Services"
        }
    ],
    "sg:phone":"+1 818 331 0544",
    "sg:postcode":"91016",
    "sg:province":"CA",
    "sg:tags":[
        "tv",
        "radio",
        "services-commercial",
        "companies-film"
    ],
    "wof:name":"Hitclub Management",
    "wof:placetype":"venue"
},
  "geometry": {"coordinates":[-118.000961,34.146958],"type":"Point"}
}