{
  "type": "Feature",
  "properties": {
    "addr:full":"736 Boyd St Santa Rosa CA 95407",
    "addr:housenumber":"736",
    "addr:postcode":"ca 95407",
    "addr:street":"Boyd St",
    "iso:country":"US",
    "sg:address":"736 Boyd St",
    "sg:city":"Santa Rosa",
    "sg:classifiers":[
        {
            "category":"Professional",
            "type":"Services"
        }
    ],
    "sg:phone":"+1 707 526 0695",
    "sg:postcode":"95407",
    "sg:province":"CA",
    "wof:name":"Bathelt Friedrich",
    "wof:placetype":"venue"
},
  "geometry": {"coordinates":[-122.719354,38.429834],"type":"Point"}
}