{
  "type": "Feature",
  "properties": {
    "iso:country":"US",
    "sg:address":"1620 Victory Blvd",
    "sg:city":"Glendale",
    "sg:classifiers":[
        {
            "category":"Social Services",
            "subcategory":"Job Training",
            "type":"Services"
        }
    ],
    "sg:phone":"+1 818 244 8912",
    "sg:postcode":"91201",
    "sg:province":"CA",
    "sg:tags":[
        "rehabilitation"
    ],
    "wof:name":"Hayashi & Assoc",
    "wof:placetype":"venue"
},
  "geometry": {"coordinates":[-118.29881,34.159961],"type":"Point"}
}