{
  "type": "Feature",
  "properties": {
    "iso:country":"US",
    "sg:address":"8006 S Central Ave",
    "sg:city":"Los Angeles",
    "sg:classifiers":[
        {
            "category":"Social Services",
            "type":"Services"
        }
    ],
    "sg:phone":"+1 323 582 9810",
    "sg:postcode":"90001",
    "sg:province":"CA",
    "sg:tags":[
        "organization",
        "welfare"
    ],
    "wof:name":"Healthy Nutrition Ctr",
    "wof:placetype":"venue"
},
  "geometry": {"coordinates":[-118.256319,33.965699],"type":"Point"}
}