{
  "type": "Feature",
  "properties": {
    "addr:full":"17554 S Chateau Fresno Ave Riverdale CA 93656",
    "addr:housenumber":"17554",
    "addr:postcode":"93656",
    "addr:street":"S;Fresno Ave",
    "iso:country":"US",
    "sg:address":"17554 S Chateau Fresno Ave",
    "sg:city":"Riverdale",
    "sg:classifiers":[
        {
            "category":"Farming",
            "subcategory":"Vineyard",
            "type":"Manufacturing & Wholesale Goods"
        }
    ],
    "sg:phone":"+1 559 867 1236",
    "sg:postcode":"93656",
    "sg:province":"CA",
    "sg:tags":[
        "grape"
    ],
    "wof:name":"Rockin S Ranch",
    "wof:placetype":"venue"
},
  "geometry": {"coordinates":[-119.941194,36.481509],"type":"Point"}
}