{
  "type": "Feature",
  "properties": {
    "addr:full":"570 Marsh St San Luis Obispo CA 93401",
    "addr:housenumber":"570",
    "addr:postcode":"93401",
    "addr:street":"Marsh St",
    "iso:country":"US",
    "sg:address":"570 Marsh St",
    "sg:city":"San Luis Obispo",
    "sg:classifiers":[
        {
            "category":"Real Estate",
            "subcategory":"Real Estate Agent",
            "type":"Services"
        }
    ],
    "sg:phone":"+1 805 544 4422",
    "sg:postcode":"93401",
    "sg:province":"CA",
    "wof:name":"Real Property Investments",
    "wof:placetype":"venue"
},
  "geometry": {"coordinates":[-120.665756,35.276723],"type":"Point"}
}