{
  "type": "Feature",
  "properties": {
    "addr:full":"11874 San Pablo Avenue El Cerrito CA 94530",
    "addr:housenumber":"11874",
    "addr:postcode":"94530",
    "addr:street":"San Pablo Avenue",
    "iso:country":"US",
    "sg:address":"11874 San Pablo Avenue",
    "sg:city":"El Cerrito",
    "sg:classifiers":[
        {
            "category":"Home & Garden",
            "subcategory":"Building Materials",
            "type":"Retail Goods"
        },
        {
            "category":"Building & Trades",
            "subcategory":"Electrical",
            "type":"Services"
        }
    ],
    "sg:phone":"+1 510 233 5776",
    "sg:postcode":"94530",
    "sg:province":"CA",
    "sg:tags":[
        "equipment",
        "lighting",
        "fixture",
        "electrician"
    ],
    "wof:name":"Finn Electric",
    "wof:placetype":"venue"
},
  "geometry": {"coordinates":[-122.320999,37.929298],"type":"Point"}
}