{
  "type": "Feature",
  "properties": {
    "iso:country":"US",
    "sg:address":"2675 Junipero Ave",
    "sg:city":"Signal Hill",
    "sg:classifiers":[
        {
            "category":"Shopping",
            "subcategory":"Discount & Variety Stores",
            "type":"Retail Goods"
        }
    ],
    "sg:phone":"+1 562 216 2200",
    "sg:postcode":"90755",
    "sg:province":"CA",
    "sg:tags":[
        "merchandise",
        "general"
    ],
    "wof:name":"Ross Organic Specialty Sales",
    "wof:placetype":"venue"
},
  "geometry": {"coordinates":[-118.163308,33.804935],"type":"Point"}
}