{
  "type": "Feature",
  "properties": {
    "iso:country":"US",
    "sg:address":"14531 Galway St",
    "sg:city":"Westminster",
    "sg:classifiers":[
        {
            "category":"Professional",
            "type":"Services"
        }
    ],
    "sg:phone":"+1 714 531 1675",
    "sg:postcode":"92683",
    "sg:province":"CA",
    "wof:name":"Chasers",
    "wof:placetype":"venue"
},
  "geometry": {"coordinates":[-117.962748,33.751672],"type":"Point"}
}