{
  "type": "Feature",
  "properties": {
    "addr:full":"1050 Broad St San Luis Obispo CA 93401",
    "addr:housenumber":"1050",
    "addr:postcode":"93401",
    "addr:street":"Broad St",
    "iso:country":"US",
    "sg:address":"1050 Broad St",
    "sg:city":"San Luis Obispo",
    "sg:classifiers":[
        {
            "category":"Shopping",
            "subcategory":"Bicycles & Sporting Goods",
            "type":"Retail Goods"
        }
    ],
    "sg:phone":"+1 805 593 0850",
    "sg:postcode":"93401",
    "sg:province":"CA",
    "wof:name":"TKD Surf Shop",
    "wof:placetype":"venue"
},
  "geometry": {"coordinates":[-120.664666,35.279179],"type":"Point"}
}