{
  "type": "Feature",
  "properties": {
    "addr:full":"4407 Elkhorn Boulevard Sacramento CA 95842",
    "addr:housenumber":"4407",
    "addr:postcode":"95842",
    "addr:street":"Elkhorn Boulevard",
    "iso:country":"US",
    "sg:address":"4407 Elkhorn Boulevard",
    "sg:city":"Sacramento",
    "sg:classifiers":[
        {
            "category":"Retail",
            "subcategory":"Veterinary Services",
            "type":"Services"
        }
    ],
    "sg:phone":"+1 916 334 4884",
    "sg:postcode":"95842",
    "sg:province":"CA",
    "sg:tags":[
        "veterinarian"
    ],
    "wof:name":"Elkhorn-Walerga Animal Hospital",
    "wof:placetype":"venue"
},
  "geometry": {"coordinates":[-121.36144400000001,38.694696],"type":"Point"}
}