{
  "type": "Feature",
  "properties": {
    "addr:full":"845 E Valley Blvd San Gabriel CA 91776",
    "addr:housenumber":"845",
    "addr:postcode":"91776",
    "addr:street":"E Valley Blvd",
    "iso:country":"US",
    "sg:address":"845 E Valley Blvd",
    "sg:city":"San Gabriel",
    "sg:classifiers":[
        {
            "category":"Manufacturing",
            "subcategory":"Furniture",
            "type":"Manufacturing & Wholesale Goods"
        },
        {
            "category":"Building & Trades",
            "subcategory":"Construction",
            "type":"Services"
        }
    ],
    "sg:phone":"+1 626 307 0702",
    "sg:postcode":"91776",
    "sg:province":"CA",
    "sg:tags":[
        "mfg",
        "residential",
        "nonresidential",
        "cabinet",
        "wood",
        "maker"
    ],
    "wof:name":"California Fixtures",
    "wof:placetype":"venue"
},
  "geometry": {"coordinates":[-118.08818599999999,34.080346],"type":"Point"}
}