{
  "type": "Feature",
  "properties": {
    "iso:country":"US",
    "sg:address":"29 Pier",
    "sg:city":"San Francisco",
    "sg:classifiers":[
        {
            "category":"Professional",
            "subcategory":"Lawyer & Legal Services",
            "type":"Services"
        }
    ],
    "sg:phone":"+1 415 982 3008",
    "sg:postcode":"94105",
    "sg:province":"CA",
    "sg:tags":[
        "attorney"
    ],
    "wof:name":"Law & Admiralty Office",
    "wof:placetype":"venue"
},
  "geometry": {"coordinates":[-122.39478099999999,37.795642],"type":"Point"}
}