{
  "type": "Feature",
  "properties": {
    "addr:full":"1300 El Sobrante Rd Corona CA 92879",
    "addr:housenumber":"1300",
    "addr:postcode":"92879",
    "addr:street":"El Sobrante Rd",
    "iso:country":"US",
    "sg:address":"1300 El Sobrante Rd",
    "sg:city":"Corona",
    "sg:classifiers":[
        {
            "category":"Restaurant",
            "type":"Food & Drink"
        },
        {
            "category":"Bakery",
            "type":"Food & Drink"
        }
    ],
    "sg:menulink":"http://www.allmenus.com/ca/corona/218672-cocos-bakery-restaurant/menu/",
    "sg:phone":"+1 951 371 3300",
    "sg:postcode":"92879",
    "sg:province":"CA",
    "sg:tags":[
        "sandwich",
        "salad",
        "american",
        "soup",
        "bakery",
        "pastry",
        "wrap",
        "wing"
    ],
    "wof:name":"Coco's Bakery Restaurant",
    "wof:placetype":"venue"
},
  "geometry": {"coordinates":[-117.54502599999999,33.868092],"type":"Point"}
}