{
  "type": "Feature",
  "properties": {
    "iso:country":"US",
    "sg:address":"302 Center St",
    "sg:city":"Jackson",
    "sg:classifiers":[
        {
            "category":"Home & Garden",
            "subcategory":"Building Materials",
            "type":"Retail Goods"
        },
        {
            "category":"Building & Trades",
            "subcategory":"Construction",
            "type":"Services"
        }
    ],
    "sg:phone":"+1 209 223 5010",
    "sg:postcode":"95642",
    "sg:province":"CA",
    "sg:tags":[
        "paint",
        "improvement",
        "contractor"
    ],
    "wof:name":"Handy Bob's",
    "wof:placetype":"venue"
},
  "geometry": {"coordinates":[-120.769784,38.348423],"type":"Point"}
}