{
  "type": "Feature",
  "properties": {
    "addr:full":"1775 E Palm Canyon Dr Palm Springs CA 92264",
    "addr:housenumber":"1775",
    "addr:postcode":"92264",
    "addr:street":"E Palm Canyon Dr",
    "iso:country":"US",
    "sg:address":"1775 E Palm Canyon Dr",
    "sg:city":"Palm Springs",
    "sg:classifiers":[
        {
            "category":"Shopping",
            "subcategory":"Mobile Phones",
            "type":"Retail Goods"
        }
    ],
    "sg:phone":"+1 760 325 7200",
    "sg:postcode":"92264",
    "sg:province":"CA",
    "wof:name":"Gowireless Inc",
    "wof:placetype":"venue"
},
  "geometry": {"coordinates":[-116.527388,33.801287],"type":"Point"}
}