{
  "type": "Feature",
  "properties": {
    "addr:full":"498 Superior Ave San Leandro CA 94577",
    "addr:housenumber":"498",
    "addr:postcode":"94577",
    "addr:street":"Superior Ave",
    "iso:country":"US",
    "sg:address":"498 Superior Ave",
    "sg:city":"San Leandro",
    "sg:classifiers":[
        {
            "category":"Building & Trades",
            "subcategory":"Landscaping Services",
            "type":"Services"
        }
    ],
    "sg:phone":"+1 510 569 2030",
    "sg:postcode":"94577",
    "sg:province":"CA",
    "sg:tags":[
        "landscape",
        "contractor"
    ],
    "wof:name":"Prosperous Plants Landscaping",
    "wof:placetype":"venue"
},
  "geometry": {"coordinates":[-122.142909,37.738093],"type":"Point"}
}