{
  "type": "Feature",
  "properties": {
    "addr:full":"3622 Broderick Street Apt 2 San Francisco CA 94123",
    "addr:housenumber":"3622;2",
    "addr:postcode":"94123",
    "addr:street":"Broderick Street Apt",
    "iso:country":"US",
    "sg:address":"3622 Broderick Street Apt 2",
    "sg:city":"San Francisco",
    "sg:classifiers":[
        {
            "category":"Building & Trades",
            "subcategory":"Construction",
            "type":"Services"
        }
    ],
    "sg:phone":"+1 415 433 4431",
    "sg:postcode":"94123",
    "sg:province":"CA",
    "sg:tags":[
        "interior",
        "design"
    ],
    "wof:name":"Andary Design",
    "wof:placetype":"venue"
},
  "geometry": {"coordinates":[-122.445324,37.803732],"type":"Point"}
}