{
  "type": "Feature",
  "properties": {
    "addr:full":"109 Sierra Woods Cir Folsom CA 95630",
    "addr:housenumber":"109",
    "addr:postcode":"95630",
    "addr:street":"Sierra Woods Cir",
    "iso:country":"US",
    "sg:address":"109 Sierra Woods Cir",
    "sg:city":"Folsom",
    "sg:classifiers":[
        {
            "category":"Personal",
            "subcategory":"Beauty Salon",
            "type":"Services"
        }
    ],
    "sg:phone":"+1 916 984 5258",
    "sg:postcode":"95630",
    "sg:province":"CA",
    "wof:name":"Shear Bliss Salon",
    "wof:placetype":"venue"
},
  "geometry": {"coordinates":[-121.15537999999999,38.679732],"type":"Point"}
}