{
  "type": "Feature",
  "properties": {
    "addr:full":"6350 Beech Ave Orangevale CA 95662",
    "addr:housenumber":"6350",
    "addr:postcode":"95662",
    "addr:street":"Beech Ave",
    "iso:country":"US",
    "sg:address":"6350 Beech Ave",
    "sg:city":"Orangevale",
    "sg:classifiers":[
        {
            "category":"Building & Trades",
            "subcategory":"Electrical",
            "type":"Services"
        }
    ],
    "sg:phone":"+1 916 989 0106",
    "sg:postcode":"95662",
    "sg:province":"CA",
    "sg:tags":[
        "electric",
        "contractor"
    ],
    "wof:name":"Jay Starbuck Electric",
    "wof:placetype":"venue"
},
  "geometry": {"coordinates":[-121.230197,38.681013],"type":"Point"}
}