{
  "type": "Feature",
  "properties": {
    "addr:full":"585 Columbus Ave San Francisco CA 94133",
    "addr:housenumber":"585",
    "addr:postcode":"94133",
    "addr:street":"Columbus Ave",
    "iso:country":"US",
    "sg:address":"585 Columbus Ave",
    "sg:city":"San Francisco",
    "sg:classifiers":[
        {
            "category":"Food & Beverages",
            "subcategory":"Liquor & Beverages",
            "type":"Retail Goods"
        }
    ],
    "sg:phone":"+1 415 362 4444",
    "sg:postcode":"94133",
    "sg:province":"CA",
    "sg:tags":[
        "beer",
        "spirit",
        "wine"
    ],
    "sg:website":"www.sfcoitliquor.com",
    "wof:name":"Coit Liquor",
    "wof:placetype":"venue"
},
  "geometry": {"coordinates":[-122.408967,37.799396],"type":"Point"}
}