{
  "type": "Feature",
  "properties": {
    "addr:full":"196 College Ave Los Gatos CA 95030",
    "addr:housenumber":"196",
    "addr:postcode":"95030",
    "addr:street":"College Ave",
    "iso:country":"US",
    "sg:address":"196 College Ave",
    "sg:city":"Los Gatos",
    "sg:classifiers":[
        {
            "category":"Real Estate",
            "subcategory":"Architect",
            "type":"Services"
        }
    ],
    "sg:phone":"+1 408 395 3525",
    "sg:postcode":"95030",
    "sg:province":"CA",
    "wof:name":"Lien John Architect",
    "wof:placetype":"venue"
},
  "geometry": {"coordinates":[-121.983002,37.215801],"type":"Point"}
}