{
  "type": "Feature",
  "properties": {
    "iso:country":"US",
    "sg:address":"2150 Appian Way",
    "sg:city":"Pinole",
    "sg:classifiers":[
        {
            "category":"Health Services",
            "subcategory":"Doctor",
            "type":"Services"
        }
    ],
    "sg:phone":"+1 510 724 3922",
    "sg:postcode":"94564",
    "sg:province":"CA",
    "sg:tags":[
        "dentist"
    ],
    "wof:name":"East Bay Oral Surgery",
    "wof:placetype":"venue"
},
  "geometry": {"coordinates":[-122.300358,37.991373],"type":"Point"}
}