{
  "type": "Feature",
  "properties": {
    "addr:full":"2428 Shannon Ln Walnut Creek CA 94598",
    "addr:housenumber":"2428",
    "addr:postcode":"94598",
    "addr:street":"Shannon Ln",
    "iso:country":"US",
    "sg:address":"2428 Shannon Ln",
    "sg:city":"Walnut Creek",
    "sg:classifiers":[
        {
            "category":"Insurance",
            "subcategory":"Insurance Agent",
            "type":"Services"
        }
    ],
    "sg:phone":"+1 925 945 7711",
    "sg:postcode":"94598",
    "sg:province":"CA",
    "wof:name":"Insurance Market Place",
    "wof:placetype":"venue"
},
  "geometry": {"coordinates":[-122.03552999999999,37.932699],"type":"Point"}
}