{
  "type": "Feature",
  "properties": {
    "iso:country":"US",
    "sg:address":"407 W Imperial Hwy",
    "sg:city":"Brea",
    "sg:classifiers":[
        {
            "category":"Shopping",
            "type":"Retail Goods"
        }
    ],
    "sg:phone":"+1 714 990 9495",
    "sg:postcode":"92821",
    "sg:province":"CA",
    "sg:tags":[
        "telephone",
        "cellular"
    ],
    "wof:name":"24x7",
    "wof:placetype":"venue"
},
  "geometry": {"coordinates":[-117.904683,33.917449],"type":"Point"}
}