{
  "type": "Feature",
  "properties": {
    "addr:full":"4060 Campus Drive Suite 200 Newport Beach CA 92660",
    "addr:housenumber":"4060",
    "addr:postcode":"92660",
    "addr:street":"Campus Drive Suite 200",
    "iso:country":"US",
    "sg:address":"4060 Campus Drive Suite 200",
    "sg:city":"Newport Beach",
    "sg:classifiers":[
        {
            "category":"Banks & Credit Unions",
            "subcategory":"Financial Services",
            "type":"Services"
        }
    ],
    "sg:phone":"+1 949 251 9293",
    "sg:postcode":"92660",
    "sg:province":"CA",
    "sg:tags":[
        "broker",
        "mortgage"
    ],
    "wof:name":"City One National",
    "wof:placetype":"venue"
},
  "geometry": {"coordinates":[-117.871202,33.666142],"type":"Point"}
}