{
  "type": "Feature",
  "properties": {
    "iso:country":"US",
    "sg:address":"26655 Tiger Creek Rd",
    "sg:city":"Pioneer",
    "sg:classifiers":[
        {
            "category":"Manufacturing",
            "subcategory":"Buildings",
            "type":"Manufacturing & Wholesale Goods"
        },
        {
            "category":"Real Estate",
            "subcategory":"Real Estate Services",
            "type":"Services"
        },
        {
            "category":"Building & Trades",
            "subcategory":"Construction",
            "type":"Services"
        }
    ],
    "sg:phone":"+1 209 295 8886",
    "sg:postcode":"95666",
    "sg:province":"CA",
    "sg:tags":[
        "management",
        "builder",
        "broker",
        "contractor",
        "buyer",
        "home"
    ],
    "wof:name":"Sierra Homes & Properties Pioneer",
    "wof:placetype":"venue"
},
  "geometry": {"coordinates":[-120.530826,38.444294],"type":"Point"}
}