{
  "type": "Feature",
  "properties": {
    "iso:country":"US",
    "sg:address":"7063 del Norte Dr",
    "sg:city":"Goleta",
    "sg:classifiers":[
        {
            "category":"Retail",
            "subcategory":"Laundry & Dry Cleaning",
            "type":"Services"
        }
    ],
    "sg:phone":"+1 805 968 1120",
    "sg:postcode":"93117",
    "sg:province":"CA",
    "sg:tags":[
        "cleaners",
        "rug",
        "carpet"
    ],
    "wof:name":"A A Carpet Cleaner",
    "wof:placetype":"venue"
},
  "geometry": {"coordinates":[-119.874245,34.436358],"type":"Point"}
}