{
  "type": "Feature",
  "properties": {
    "iso:country":"US",
    "sg:address":"14044 Ramona Blvd",
    "sg:city":"Baldwin Park",
    "sg:classifiers":[
        {
            "category":"Retail",
            "subcategory":"Auto Rental",
            "type":"Services"
        }
    ],
    "sg:phone":"+1 626 814 0299",
    "sg:postcode":"91706",
    "sg:province":"CA",
    "sg:tags":[
        "recreational",
        "leasing",
        "vehicle"
    ],
    "wof:name":"Cruise America Motorhome",
    "wof:placetype":"venue"
},
  "geometry": {"coordinates":[-117.967226,34.08455],"type":"Point"}
}