{
  "type": "Feature",
  "properties": {
    "addr:full":"4510 Weedpatch Hwy Bakersfield CA 93307",
    "addr:housenumber":"4510",
    "addr:postcode":"93307",
    "addr:street":"Weedpatch Hwy",
    "iso:country":"US",
    "sg:address":"4510 Weedpatch Hwy",
    "sg:city":"Bakersfield",
    "sg:classifiers":[
        {
            "category":"Retail",
            "subcategory":"Auto Repair",
            "type":"Services"
        }
    ],
    "sg:phone":"+1 661 836 1204",
    "sg:postcode":"93307",
    "sg:province":"CA",
    "sg:tags":[
        "wrecker"
    ],
    "wof:name":"Agency Towing",
    "wof:placetype":"venue"
},
  "geometry": {"coordinates":[-118.91431,35.312508],"type":"Point"}
}