{
  "type": "Feature",
  "properties": {
    "iso:country":"US",
    "sg:address":"9538 Brighton Way",
    "sg:city":"Beverly Hills",
    "sg:classifiers":[
        {
            "category":"Food & Beverages",
            "subcategory":"Liquor & Beverages",
            "type":"Retail Goods"
        }
    ],
    "sg:phone":"+1 310 247 9901",
    "sg:postcode":"90210",
    "sg:province":"CA",
    "sg:tags":[
        "wine"
    ],
    "wof:name":"French Wine Celler",
    "wof:placetype":"venue"
},
  "geometry": {"coordinates":[-118.403576,34.068721],"type":"Point"}
}