{
  "type": "Feature",
  "properties": {
    "addr:full":"3401 Dale Rd Modesto CA 95356",
    "addr:housenumber":"3401",
    "addr:postcode":"ca 95356",
    "addr:street":"Dale Rd",
    "iso:country":"US",
    "sg:address":"3401 Dale Rd",
    "sg:city":"Modesto",
    "sg:classifiers":[
        {
            "category":"Professional",
            "subcategory":"Accounting & Tax Preparation",
            "type":"Services"
        },
        {
            "category":"Banks & Credit Unions",
            "subcategory":"Financial Services",
            "type":"Services"
        }
    ],
    "sg:phone":"+1 209 571 1760",
    "sg:postcode":"95356",
    "sg:province":"CA",
    "sg:tags":[
        "return",
        "preparation-business",
        "taxes-consultants",
        "loan",
        "reporting",
        "representative",
        "alternative",
        "bookkeeping"
    ],
    "sg:website":"http://www.hrblock.com",
    "wof:name":"H&R Block",
    "wof:placetype":"venue"
},
  "geometry": {"coordinates":[-121.04995,37.688171],"type":"Point"}
}