{
  "type": "Feature",
  "properties": {
    "addr:full":"1330 Broadway Ste 515 Oakland CA 94612",
    "addr:housenumber":"1330",
    "addr:postcode":"94612",
    "addr:street":"Broadway Ste 515",
    "iso:country":"US",
    "sg:address":"1330 Broadway Ste 515",
    "sg:city":"Oakland",
    "sg:classifiers":[
        {
            "category":"Professional",
            "subcategory":"Lawyer & Legal Services",
            "type":"Services"
        }
    ],
    "sg:phone":"+1 510 834 9944",
    "sg:postcode":"94612",
    "sg:province":"CA",
    "wof:name":"Ukoha-Ajike Endy Law Office Of",
    "wof:placetype":"venue"
},
  "geometry": {"coordinates":[-122.27134599999999,37.803783],"type":"Point"}
}