{
  "type": "Feature",
  "properties": {
    "iso:country":"US",
    "sg:address":"125 N McKinley St",
    "sg:city":"Corona",
    "sg:classifiers":[
        {
            "category":"Shopping",
            "subcategory":"Department Store",
            "type":"Retail Goods"
        }
    ],
    "sg:phone":"+1 951 371 1339",
    "sg:postcode":"92879",
    "sg:province":"CA",
    "wof:name":"Dollar Tree",
    "wof:placetype":"venue"
},
  "geometry": {"coordinates":[-117.515942,33.883993],"type":"Point"}
}