{
  "type": "Feature",
  "properties": {
    "addr:full":"29245 Lakeview Ave Nuevo CA 92567",
    "addr:housenumber":"29245",
    "addr:postcode":"92567",
    "addr:street":"Lakeview Ave",
    "iso:country":"US",
    "sg:address":"29245 Lakeview Ave",
    "sg:city":"Nuevo",
    "sg:classifiers":[
        {
            "category":"Government",
            "subcategory":"Post Office",
            "type":"Public Place"
        }
    ],
    "sg:phone":"+1 951 000 1111",
    "sg:postcode":"92567",
    "sg:province":"CA",
    "wof:name":"US Post Office",
    "wof:placetype":"venue"
},
  "geometry": {"coordinates":[-117.137587,33.815062],"type":"Point"}
}