{
  "type": "Feature",
  "properties": {
    "addr:full":"900 Dana Dr Redding CA 96003",
    "addr:housenumber":"900",
    "addr:postcode":"96003",
    "addr:street":"Dana Dr",
    "iso:country":"US",
    "sg:address":"900 Dana Dr",
    "sg:city":"Redding",
    "sg:classifiers":[
        {
            "category":"Shopping",
            "subcategory":"Clothing, Apparel, & Fashions",
            "type":"Retail Goods"
        }
    ],
    "sg:phone":"+1 530 223 6826",
    "sg:postcode":"96003",
    "sg:province":"CA",
    "wof:name":"Deb",
    "wof:placetype":"venue"
},
  "geometry": {"coordinates":[-122.354051,40.585809],"type":"Point"}
}