{
  "type": "Feature",
  "properties": {
    "iso:country":"US",
    "sg:address":"29611 Exeter St",
    "sg:city":"Lucerne Valley",
    "sg:classifiers":[
        {
            "category":"Travel",
            "subcategory":"Hotels & Motels",
            "type":"Entertainment"
        }
    ],
    "sg:phone":"+1 760 248 7049",
    "sg:postcode":"92356",
    "sg:province":"CA",
    "sg:tags":[
        "resort"
    ],
    "wof:name":"Sundowner Ranch",
    "wof:placetype":"venue"
},
  "geometry": {"coordinates":[-117.015574,34.480448],"type":"Point"}
}