{
  "type": "Feature",
  "properties": {
    "addr:full":"1355 Summit Rd Lafayette CA 94549",
    "addr:housenumber":"1355",
    "addr:postcode":"94549",
    "addr:street":"Summit Rd",
    "iso:country":"US",
    "sg:address":"1355 Summit Rd",
    "sg:city":"Lafayette",
    "sg:classifiers":[
        {
            "category":"Manufacturing",
            "subcategory":"Metals",
            "type":"Manufacturing & Wholesale Goods"
        },
        {
            "category":"Health Services",
            "subcategory":"Clinic",
            "type":"Services"
        }
    ],
    "sg:phone":"+1 925 939 8595",
    "sg:postcode":"94549",
    "sg:province":"CA",
    "sg:tags":[
        "laboratories-metallurgical",
        "metallurgist"
    ],
    "wof:name":"Lakso, Gordon E",
    "wof:placetype":"venue"
},
  "geometry": {"coordinates":[-122.09118599999999,37.908952],"type":"Point"}
}