{
  "type": "Feature",
  "properties": {
    "addr:full":"727 Esplanade Redondo Beach CA 90277",
    "addr:housenumber":"727",
    "addr:postcode":"90277",
    "addr:street":"Esplanade",
    "iso:country":"US",
    "sg:address":"727 Esplanade",
    "sg:city":"Redondo Beach",
    "sg:classifiers":[
        {
            "category":"Wholesale",
            "subcategory":"Durable Goods & Equipment",
            "type":"Manufacturing & Wholesale Goods"
        }
    ],
    "sg:phone":"+1 310 316 9121",
    "sg:postcode":"90277",
    "sg:province":"CA",
    "wof:name":"Rapacini Imports",
    "wof:placetype":"venue"
},
  "geometry": {"coordinates":[-118.389771,33.829669],"type":"Point"}
}