{
  "type": "Feature",
  "properties": {
    "iso:country":"US",
    "sg:address":"11921 Indiana Ave",
    "sg:city":"Riverside",
    "sg:classifiers":[
        {
            "category":"Retail",
            "subcategory":"Repair Shop",
            "type":"Services"
        }
    ],
    "sg:phone":"+1 951 687 9590",
    "sg:postcode":"92503",
    "sg:province":"CA",
    "sg:tags":[
        "bathtub",
        "sink",
        "refinishing"
    ],
    "wof:name":"Tub-Tech",
    "wof:placetype":"venue"
},
  "geometry": {"coordinates":[-117.487265,33.889939],"type":"Point"}
}