{
  "type": "Feature",
  "properties": {
    "iso:country":"US",
    "sg:address":"320 Sherwood Rd",
    "sg:city":"Paso Robles",
    "sg:classifiers":[
        {
            "category":"Organizations",
            "subcategory":"Community Association",
            "type":"Services"
        }
    ],
    "sg:phone":"+1 805 238 4355",
    "sg:postcode":"93446",
    "sg:province":"CA",
    "sg:tags":[
        "fraternal"
    ],
    "wof:name":"Masonic Lodge",
    "wof:placetype":"venue"
},
  "geometry": {"coordinates":[-120.653496,35.615733],"type":"Point"}
}