{
  "type": "Feature",
  "properties": {
    "iso:country":"US",
    "sg:address":"3909 Tyler St",
    "sg:city":"Riverside",
    "sg:classifiers":[
        {
            "category":"Insurance",
            "subcategory":"Insurance Agent",
            "type":"Services"
        }
    ],
    "sg:phone":"+1 951 785 7171",
    "sg:postcode":"92503",
    "sg:province":"CA",
    "wof:name":"Allstate Insurance",
    "wof:placetype":"venue"
},
  "geometry": {"coordinates":[-117.463928,33.915113],"type":"Point"}
}