{
  "type": "Feature",
  "properties": {
    "addr:full":"4355 Pacific St Rocklin CA 95677",
    "addr:housenumber":"4355",
    "addr:postcode":"95677",
    "addr:street":"Pacific St",
    "iso:country":"US",
    "sg:address":"4355 Pacific St",
    "sg:city":"Rocklin",
    "sg:classifiers":[
        {
            "category":"Professional",
            "subcategory":"Business Services",
            "type":"Services"
        }
    ],
    "sg:phone":"+1 916 624 1649",
    "sg:postcode":"95677",
    "sg:province":"CA",
    "sg:tags":[
        "drafting"
    ],
    "wof:name":"Taylor Design & Drafting Svc",
    "wof:placetype":"venue"
},
  "geometry": {"coordinates":[-121.22024399999999,38.80324],"type":"Point"}
}