{
  "type": "Feature",
  "properties": {
    "addr:full":"19300 Ike Jones Rd Santa Ana CA 92707",
    "addr:housenumber":"19300",
    "addr:postcode":"92707",
    "addr:street":"Ike Jones Rd",
    "iso:country":"US",
    "sg:address":"19300 Ike Jones Rd",
    "sg:city":"Santa Ana",
    "sg:classifiers":[
        {
            "category":"Wholesale",
            "subcategory":"Machinery & Supplies",
            "type":"Manufacturing & Wholesale Goods"
        }
    ],
    "sg:phone":"+1 714 429 9682",
    "sg:postcode":"92707",
    "sg:province":"CA",
    "sg:tags":[
        "a",
        "repair",
        "engineering"
    ],
    "wof:name":"Jet Ventures International",
    "wof:placetype":"venue"
},
  "geometry": {"coordinates":[-117.87036999999999,33.67732],"type":"Point"}
}