{
  "type": "Feature",
  "properties": {
    "iso:country":"US",
    "sg:address":"9261 Skyway Rd",
    "sg:city":"Paradise",
    "sg:classifiers":[
        {
            "category":"Wholesale",
            "subcategory":"Hardware",
            "type":"Manufacturing & Wholesale Goods"
        }
    ],
    "sg:phone":"+1 530 872 9425",
    "sg:postcode":"95969",
    "sg:province":"CA",
    "sg:tags":[
        "tool"
    ],
    "sg:website":"www.sirtools.com",
    "wof:name":"Sir Tools",
    "wof:placetype":"venue"
},
  "geometry": {"coordinates":[-121.583536,39.799604],"type":"Point"}
}