{
  "type": "Feature",
  "properties": {
    "addr:full":"1546 Camden Ave Campbell CA 95008",
    "addr:housenumber":"1546",
    "addr:postcode":"95008",
    "addr:street":"Camden Ave",
    "iso:country":"US",
    "sg:address":"1546 Camden Ave",
    "sg:city":"Campbell",
    "sg:classifiers":[
        {
            "category":"Restaurant",
            "type":"Food & Drink"
        }
    ],
    "sg:phone":"+1 408 626 7986",
    "sg:postcode":"95008",
    "sg:province":"CA",
    "sg:tags":[
        "american",
        "latin"
    ],
    "wof:name":"Pupuser?a Los Dubon",
    "wof:placetype":"venue"
},
  "geometry": {"coordinates":[-121.941823,37.267222],"type":"Point"}
}