{
  "type": "Feature",
  "properties": {
    "iso:country":"US",
    "sg:address":"250 Sawpit Creek Spr",
    "sg:city":"Cedarpines Park",
    "sg:classifiers":[
        {
            "category":"Building & Trades",
            "subcategory":"Construction",
            "type":"Services"
        }
    ],
    "sg:phone":"+1 909 338 9936",
    "sg:postcode":"92325",
    "sg:province":"CA",
    "sg:tags":[
        "contractor"
    ],
    "wof:name":"Cec Construction Co",
    "wof:placetype":"venue"
},
  "geometry": {"coordinates":[-117.33867100000001,34.255503],"type":"Point"}
}