{
  "type": "Feature",
  "properties": {
    "iso:country":"US",
    "sg:address":"111 E Linden Ave",
    "sg:city":"Burbank",
    "sg:classifiers":[
        {
            "category":"Communications",
            "subcategory":"Film & Video Production",
            "type":"Services"
        }
    ],
    "sg:phone":"+1 818 840 0696",
    "sg:postcode":"91502",
    "sg:province":"CA",
    "sg:tags":[
        "motion",
        "picture",
        "studio",
        "producer"
    ],
    "sg:website":"www.gravyinc.com",
    "wof:name":"Made",
    "wof:placetype":"venue"
},
  "geometry": {"coordinates":[-118.29861,34.171545],"type":"Point"}
}