{
  "type": "Feature",
  "properties": {
    "addr:full":"6286 El Camino Real Carlsbad CA 92009",
    "addr:housenumber":"6286",
    "addr:postcode":"92009",
    "addr:street":"El Camino Real",
    "iso:country":"US",
    "sg:address":"6286 El Camino Real",
    "sg:city":"Carlsbad",
    "sg:classifiers":[
        {
            "category":"Education",
            "subcategory":"Preschool",
            "type":"Public Place"
        },
        {
            "category":"Education",
            "subcategory":"School",
            "type":"Public Place"
        }
    ],
    "sg:phone":"+1 760 603 9173",
    "sg:postcode":"92009",
    "sg:province":"CA",
    "sg:tags":[
        "elementary"
    ],
    "wof:name":"Asperations Pre-School",
    "wof:placetype":"venue"
},
  "geometry": {"coordinates":[-117.266854,33.120135],"type":"Point"}
}