{
  "type": "Feature",
  "properties": {
    "addr:full":"106 S Main St Lake Elsinore CA 92530",
    "addr:housenumber":"106",
    "addr:postcode":"92530",
    "addr:street":"S Main St",
    "iso:country":"US",
    "sg:address":"106 S Main St",
    "sg:city":"Lake Elsinore",
    "sg:classifiers":[
        {
            "category":"Organizations",
            "subcategory":"Membership Organization",
            "type":"Services"
        }
    ],
    "sg:phone":"+1 951 245 4986",
    "sg:postcode":"92530",
    "sg:province":"CA",
    "sg:tags":[
        "museum",
        "historical"
    ],
    "wof:name":"Lake Elsinore Historical Society",
    "wof:placetype":"venue"
},
  "geometry": {"coordinates":[-117.328003,33.667999],"type":"Point"}
}