{
  "type": "Feature",
  "properties": {
    "iso:country":"US",
    "sg:address":"200 Goodman St",
    "sg:city":"Bakersfield",
    "sg:classifiers":[
        {
            "category":"Freight",
            "type":"Transportation"
        }
    ],
    "sg:phone":"+1 661 667 3541",
    "sg:postcode":"93305",
    "sg:province":"CA",
    "sg:tags":[
        "trucking"
    ],
    "wof:name":"Specialty Product & Trucking",
    "wof:placetype":"venue"
},
  "geometry": {"coordinates":[-118.994092,35.392319],"type":"Point"}
}