{
  "type": "Feature",
  "properties": {
    "iso:country":"US",
    "sg:address":"2583 N. Palm Canyon Dr Ste 200",
    "sg:city":"Palm Springs",
    "sg:classifiers":[
        {
            "category":"Real Estate",
            "subcategory":"Real Estate Services",
            "type":"Services"
        }
    ],
    "sg:phone":"+1 760 327 9700",
    "sg:postcode":"92262",
    "sg:province":"CA",
    "sg:tags":[
        "management",
        "property"
    ],
    "sg:website":"kplselectpropertymanagement.com",
    "wof:name":"KPL Property Management",
    "wof:placetype":"venue"
},
  "geometry": {"coordinates":[-116.55285499999999,33.853118],"type":"Point"}
}