{
  "type": "Feature",
  "properties": {
    "iso:country":"US",
    "sg:address":"7150 Power Inn Rd",
    "sg:city":"Sacramento",
    "sg:classifiers":[
        {
            "category":"Retail",
            "subcategory":"Car Wash",
            "type":"Services"
        }
    ],
    "sg:phone":"+1 916 386 2118",
    "sg:postcode":"95828",
    "sg:province":"CA",
    "sg:tags":[
        "automobile",
        "detail",
        "clean"
    ],
    "wof:name":"1 Handwash",
    "wof:placetype":"venue"
},
  "geometry": {"coordinates":[-121.409028,38.49673],"type":"Point"}
}