{
  "type": "Feature",
  "properties": {
    "addr:full":"409 9th avenue #309 San Diego CA 92101",
    "addr:housenumber":"409",
    "addr:postcode":"92101",
    "addr:street":"9Th Avenue # 309",
    "iso:country":"US",
    "sg:address":"409 9th avenue #309",
    "sg:city":"San Diego",
    "sg:classifiers":[
        {
            "category":"Real Estate",
            "subcategory":"Real Estate Agent",
            "type":"Services"
        }
    ],
    "sg:phone":"+1 858 869 3940",
    "sg:postcode":"92101",
    "sg:province":"CA",
    "sg:website":"www.sethobyrne.com",
    "wof:name":"Seth O'Byrne, Realtor",
    "wof:placetype":"venue"
},
  "geometry": {"coordinates":[-117.15648299999999,32.709557],"type":"Point"}
}