{
  "type": "Feature",
  "properties": {
    "addr:full":"1045 34th St Sacramento CA 95816",
    "addr:housenumber":"1045",
    "addr:postcode":"95816",
    "addr:street":"34Th St",
    "iso:country":"US",
    "sg:address":"1045 34th St",
    "sg:city":"Sacramento",
    "sg:classifiers":[
        {
            "category":"Home & Garden",
            "subcategory":"Home Furnishings",
            "type":"Retail Goods"
        }
    ],
    "sg:phone":"+1 916 442 2868",
    "sg:postcode":"95816",
    "sg:province":"CA",
    "wof:name":"Cutlery 2000",
    "wof:placetype":"venue"
},
  "geometry": {"coordinates":[-121.46185199999999,38.570377],"type":"Point"}
}