{
  "type": "Feature",
  "properties": {
    "addr:full":"12034 Riverside Dr Valley Village CA 91607",
    "addr:housenumber":"12034",
    "addr:postcode":"91607",
    "addr:street":"Riverside Dr",
    "iso:country":"US",
    "sg:address":"12034 Riverside Dr",
    "sg:city":"Valley Village",
    "sg:classifiers":[
        {
            "category":"Recreation",
            "type":"Entertainment"
        }
    ],
    "sg:phone":"+1 818 761 1129",
    "sg:postcode":"91607",
    "sg:province":"CA",
    "sg:tags":[
        "instruction",
        "chess"
    ],
    "wof:name":"Educhess",
    "wof:placetype":"venue"
},
  "geometry": {"coordinates":[-118.396456,34.157538],"type":"Point"}
}