{
  "type": "Feature",
  "properties": {
    "addr:full":"6030 Wilshire Blvd Los Angeles CA 90036",
    "addr:housenumber":"6030",
    "addr:postcode":"90036",
    "addr:street":"Wilshire Blvd",
    "iso:country":"US",
    "sg:address":"6030 Wilshire Blvd",
    "sg:city":"Los Angeles",
    "sg:classifiers":[
        {
            "category":"Manufacturing",
            "subcategory":"Printing",
            "type":"Manufacturing & Wholesale Goods"
        }
    ],
    "sg:phone":"+1 323 965 1575",
    "sg:postcode":"90036",
    "sg:province":"CA",
    "sg:tags":[
        "publisher",
        "software"
    ],
    "wof:name":"Bicoastal Media",
    "wof:placetype":"venue"
},
  "geometry": {"coordinates":[-118.360527,34.062739],"type":"Point"}
}