{
  "type": "Feature",
  "properties": {
    "iso:country":"US",
    "sg:address":"705 Gold Lake Dr",
    "sg:city":"Folsom",
    "sg:classifiers":[
        {
            "category":"Real Estate",
            "subcategory":"Real Estate Services",
            "type":"Services"
        }
    ],
    "sg:phone":"+1 916 608 7590",
    "sg:postcode":"95630",
    "sg:province":"CA",
    "sg:tags":[
        "company",
        "abstract",
        "title"
    ],
    "wof:name":"Financial Title Company",
    "wof:placetype":"venue"
},
  "geometry": {"coordinates":[-121.17982499999999,38.677078],"type":"Point"}
}