{
  "type": "Feature",
  "properties": {
    "iso:country":"US",
    "sg:address":"460 Pleasant Valley Rd",
    "sg:city":"Diamond Springs",
    "sg:classifiers":[
        {
            "category":"Restaurant",
            "type":"Food & Drink"
        }
    ],
    "sg:phone":"+1 530 621 3327",
    "sg:postcode":"95619",
    "sg:province":"CA",
    "wof:name":"Deb's Frosty",
    "wof:placetype":"venue"
},
  "geometry": {"coordinates":[-120.817721,38.693829],"type":"Point"}
}