{
  "type": "Feature",
  "properties": {
    "addr:full":"St. Vincent de Paul Society 169 Stillman St San Francisco CA 94107",
    "addr:housenumber":"169",
    "addr:postcode":"94107",
    "addr:street":"Stillman St",
    "iso:country":"US",
    "sg:address":"St. Vincent de Paul Society 169 Stillman St",
    "sg:city":"San Francisco",
    "sg:classifiers":[
        {
            "category":"Arts & Performance",
            "subcategory":"Art Gallery",
            "type":"Entertainment"
        }
    ],
    "sg:phone":"+1 415 977 1270",
    "sg:postcode":"94107",
    "sg:province":"CA",
    "sg:website":"www.svdp-sf.org/DISCARDED/index....",
    "wof:name":"Discarded to Divine",
    "wof:placetype":"venue"
},
  "geometry": {"coordinates":[-122.397735,37.780444],"type":"Point"}
}