{
  "type": "Feature",
  "properties": {
    "addr:full":"55 Sutter St San Francisco CA 94104",
    "addr:housenumber":"55",
    "addr:postcode":"94104",
    "addr:street":"Sutter St",
    "iso:country":"US",
    "sg:address":"55 Sutter St",
    "sg:city":"San Francisco",
    "sg:classifiers":[
        {
            "category":"Retail",
            "subcategory":"Laundry & Dry Cleaning",
            "type":"Services"
        }
    ],
    "sg:phone":"+1 415 274 9949",
    "sg:postcode":"94104",
    "sg:province":"CA",
    "sg:tags":[
        "cleaner"
    ],
    "wof:name":"ABC Cleaners",
    "wof:placetype":"venue"
},
  "geometry": {"coordinates":[-122.401453,37.790188],"type":"Point"}
}