{
  "type": "Feature",
  "properties": {
    "addr:full":"10920 S Vermont Ave Los Angeles CA 90044",
    "addr:housenumber":"10920",
    "addr:postcode":"90044",
    "addr:street":"S Vermont Ave",
    "iso:country":"US",
    "sg:address":"10920 S Vermont Ave",
    "sg:city":"Los Angeles",
    "sg:classifiers":[
        {
            "category":"Organizations",
            "subcategory":"Religious Organization",
            "type":"Services"
        }
    ],
    "sg:phone":"+1 323 777 9000",
    "sg:postcode":"90044",
    "sg:province":"CA",
    "sg:tags":[
        "church"
    ],
    "wof:name":"Christian Theological Learning",
    "wof:placetype":"venue"
},
  "geometry": {"coordinates":[-118.29153599999999,33.936788],"type":"Point"}
}