{
  "type": "Feature",
  "properties": {
    "iso:country":"US",
    "sg:address":"310 Washington Blvd",
    "sg:city":"Venice",
    "sg:classifiers":[
        {
            "category":"Real Estate",
            "subcategory":"Developer",
            "type":"Services"
        }
    ],
    "sg:phone":"+1 310 827 0171",
    "sg:postcode":"90292",
    "sg:province":"CA",
    "sg:website":"www.leehomes.net",
    "wof:name":"Lee Group",
    "wof:placetype":"venue"
},
  "geometry": {"coordinates":[-118.464222,33.980471],"type":"Point"}
}