{
  "type": "Feature",
  "properties": {
    "addr:full":"1248 Alderwood Ave Sunnyvale CA 94089",
    "addr:housenumber":"1248",
    "addr:postcode":"94089",
    "addr:street":"Alderwood Ave",
    "iso:country":"US",
    "sg:address":"1248 Alderwood Ave",
    "sg:city":"Sunnyvale",
    "sg:classifiers":[
        {
            "category":"Freight",
            "type":"Transportation"
        }
    ],
    "sg:phone":"+1 408 543 8686",
    "sg:postcode":"94089",
    "sg:province":"CA",
    "sg:tags":[
        "arrangement"
    ],
    "wof:name":"Moto Kart LLC",
    "wof:placetype":"venue"
},
  "geometry": {"coordinates":[-121.994652,37.405716],"type":"Point"}
}