{
  "type": "Feature",
  "properties": {
    "iso:country":"US",
    "sg:address":"30636 Carter Rd",
    "sg:city":"Farmington",
    "sg:classifiers":[
        {
            "category":"Wholesale",
            "subcategory":"Poultry",
            "type":"Manufacturing & Wholesale Goods"
        }
    ],
    "sg:phone":"+1 209 886 5625",
    "sg:postcode":"95230",
    "sg:province":"CA",
    "wof:name":"Wilfie Egg Farms Inc",
    "wof:placetype":"venue"
},
  "geometry": {"coordinates":[-120.94447599999999,37.88665],"type":"Point"}
}