{
  "type": "Feature",
  "properties": {
    "iso:country":"US",
    "sg:address":"279 Imperial Dr",
    "sg:city":"Pacifica",
    "sg:classifiers":[
        {
            "category":"Real Estate",
            "subcategory":"Real Estate Operator",
            "type":"Services"
        }
    ],
    "sg:phone":"+1 650 355 1002",
    "sg:postcode":"94044",
    "sg:province":"CA",
    "sg:tags":[
        "apartment"
    ],
    "wof:name":"Fairmont Apartments",
    "wof:placetype":"venue"
},
  "geometry": {"coordinates":[-122.476732,37.658108],"type":"Point"}
}