{
  "type": "Feature",
  "properties": {
    "iso:country":"US",
    "sg:address":"246 Grant St",
    "sg:city":"Coalinga",
    "sg:classifiers":[
        {
            "category":"Building & Trades",
            "subcategory":"Construction",
            "type":"Services"
        }
    ],
    "sg:phone":"+1 559 935 2476",
    "sg:postcode":"93210",
    "sg:province":"CA",
    "sg:tags":[
        "coping",
        "plastering",
        "tiling",
        "pool",
        "swimming"
    ],
    "wof:name":"Clay's Pool Svc",
    "wof:placetype":"venue"
},
  "geometry": {"coordinates":[-120.355665,36.146139],"type":"Point"}
}