{
  "type": "Feature",
  "properties": {
    "iso:country":"US",
    "sg:address":"12747 Rd 168",
    "sg:city":"Porterville",
    "sg:classifiers":[
        {
            "category":"Retail",
            "subcategory":"Repair Shop",
            "type":"Services"
        }
    ],
    "sg:phone":"+1 559 793 0521",
    "sg:postcode":"93257",
    "sg:province":"CA",
    "sg:tags":[
        "welding"
    ],
    "wof:name":"R V Ironworks",
    "wof:placetype":"venue"
},
  "geometry": {"coordinates":[-119.197301,36.01505],"type":"Point"}
}