{
  "type": "Feature",
  "properties": {
    "iso:country":"US",
    "sg:address":"1029 J St Ste 310",
    "sg:city":"Sacramento",
    "sg:classifiers":[
        {
            "category":"Professional",
            "subcategory":"Business Services",
            "type":"Services"
        }
    ],
    "sg:phone":"+1 916 447 8420",
    "sg:postcode":"95814",
    "sg:province":"CA",
    "sg:tags":[
        "lobbyist"
    ],
    "wof:name":"Davis And Donnelly Frost",
    "wof:placetype":"venue"
},
  "geometry": {"coordinates":[-121.49305200000001,38.580219],"type":"Point"}
}