{
  "type": "Feature",
  "properties": {
    "addr:full":"7840 Firestone Blvd Downey CA 90241",
    "addr:housenumber":"7840",
    "addr:postcode":"90241",
    "addr:street":"Firestone Blvd",
    "iso:country":"US",
    "sg:address":"7840 Firestone Blvd",
    "sg:city":"Downey",
    "sg:classifiers":[
        {
            "category":"Personal",
            "subcategory":"Beauty Salon",
            "type":"Services"
        }
    ],
    "sg:phone":"+1 562 923 6016",
    "sg:postcode":"90241",
    "sg:province":"CA",
    "wof:name":"Young Again Hair & Nail",
    "wof:placetype":"venue"
},
  "geometry": {"coordinates":[-118.14109999999999,33.944362],"type":"Point"}
}