{
  "type": "Feature",
  "properties": {
    "iso:country":"US",
    "sg:address":"250 N Robertson Blvd Suite 206",
    "sg:city":"Beverly Hills",
    "sg:classifiers":[
        {
            "category":"Health Services",
            "subcategory":"Doctor",
            "type":"Services"
        }
    ],
    "sg:phone":"+1 310 385 3526",
    "sg:postcode":"90211",
    "sg:province":"CA",
    "sg:website":"www.cedars-sinai.edu/Patients/Ph...",
    "wof:name":"Daniel Stone, MD",
    "wof:placetype":"venue"
},
  "geometry": {"coordinates":[-118.383501,34.069636],"type":"Point"}
}