{
  "type": "Feature",
  "properties": {
    "addr:full":"89 W Colorado Blvd Pasadena CA 91105",
    "addr:housenumber":"89",
    "addr:postcode":"91105",
    "addr:street":"W Colorado Blvd",
    "iso:country":"US",
    "sg:address":"89 W Colorado Blvd",
    "sg:city":"Pasadena",
    "sg:classifiers":[
        {
            "category":"Shopping",
            "subcategory":"Optician",
            "type":"Retail Goods"
        }
    ],
    "sg:phone":"+1 626 449 1423",
    "sg:postcode":"91105",
    "sg:province":"CA",
    "sg:tags":[
        "eyewear"
    ],
    "wof:name":"Sunglass Hut International-Watch Station",
    "wof:placetype":"venue"
},
  "geometry": {"coordinates":[-118.152,34.145599],"type":"Point"}
}