{
  "type": "Feature",
  "properties": {
    "addr:full":"1364 S. Hill St. Los Angeles CA 90015",
    "addr:housenumber":"1364",
    "addr:postcode":"90015",
    "addr:street":"S. Hill St.",
    "iso:country":"US",
    "sg:address":"1364 S. Hill St.",
    "sg:city":"Los Angeles",
    "sg:classifiers":[
        {
            "category":"Shopping",
            "subcategory":"Crafts & Fabrics",
            "type":"Retail Goods"
        }
    ],
    "sg:phone":"+1 213 748 1418",
    "sg:postcode":"90015",
    "sg:province":"CA",
    "sg:tags":[
        "art",
        "knitting",
        "supply"
    ],
    "wof:name":"International Design Supplies, Inc.",
    "wof:placetype":"venue"
},
  "geometry": {"coordinates":[-118.263279,34.036223],"type":"Point"}
}