{
  "type": "Feature",
  "properties": {
    "addr:full":"9332 Jamacha Rd Spring Valley CA 91977",
    "addr:housenumber":"9332",
    "addr:postcode":"91977",
    "addr:street":"Jamacha Rd",
    "iso:country":"US",
    "sg:address":"9332 Jamacha Rd",
    "sg:city":"Spring Valley",
    "sg:classifiers":[
        {
            "category":"Utilities",
            "subcategory":"Recycling",
            "type":"Services"
        }
    ],
    "sg:phone":"+1 619 337 3727",
    "sg:postcode":"91977",
    "sg:province":"CA",
    "wof:name":"Indoor Recycling Center",
    "wof:placetype":"venue"
},
  "geometry": {"coordinates":[-116.997354,32.714923],"type":"Point"}
}