{
  "type": "Feature",
  "properties": {
    "addr:full":"123 N Salinas St Santa Barbara CA 93103",
    "addr:housenumber":"123",
    "addr:postcode":"93103",
    "addr:street":"N Salinas St",
    "iso:country":"US",
    "sg:address":"123 N Salinas St",
    "sg:city":"Santa Barbara",
    "sg:classifiers":[
        {
            "category":"Building & Trades",
            "subcategory":"Construction",
            "type":"Services"
        }
    ],
    "sg:phone":"+1 805 564 8777",
    "sg:postcode":"93103",
    "sg:province":"CA",
    "sg:tags":[
        "contractor"
    ],
    "wof:name":"Concrete Impressions",
    "wof:placetype":"venue"
},
  "geometry": {"coordinates":[-119.67696599999999,34.428904],"type":"Point"}
}