{
  "type": "Feature",
  "properties": {
    "addr:full":"1626 Orchard Ave Los Angeles CA 90006",
    "addr:housenumber":"1626",
    "addr:postcode":"90006",
    "addr:street":"Orchard Ave",
    "iso:country":"US",
    "sg:address":"1626 Orchard Ave",
    "sg:city":"Los Angeles",
    "sg:classifiers":[
        {
            "category":"Building & Trades",
            "subcategory":"Construction",
            "type":"Services"
        }
    ],
    "sg:phone":"+1 213 744 0505",
    "sg:postcode":"90006",
    "sg:province":"CA",
    "sg:tags":[
        "general",
        "contractor"
    ],
    "wof:name":"Construction Concepts",
    "wof:placetype":"venue"
},
  "geometry": {"coordinates":[-118.288456,34.043509],"type":"Point"}
}