{
  "type": "Feature",
  "properties": {
    "iso:country":"US",
    "sg:address":"1106 W Barkley Ave",
    "sg:city":"Orange",
    "sg:classifiers":[
        {
            "category":"Retail",
            "subcategory":"Repair Shop",
            "type":"Services"
        }
    ],
    "sg:phone":"+1 714 639 8574",
    "sg:postcode":"92868",
    "sg:province":"CA",
    "sg:tags":[
        "equipment",
        "hydraulic"
    ],
    "sg:website":"www.bfpna.com",
    "wof:name":"Berendsen Fluid Power Inc",
    "wof:placetype":"venue"
},
  "geometry": {"coordinates":[-117.862469,33.800762],"type":"Point"}
}