{
  "type": "Feature",
  "properties": {
    "iso:country":"US",
    "sg:address":"15910 Ventura Blvd",
    "sg:city":"Encino",
    "sg:classifiers":[
        {
            "category":"Professional",
            "subcategory":"Accounting & Tax Preparation",
            "type":"Services"
        }
    ],
    "sg:phone":"+1 818 783 2985",
    "sg:postcode":"91436",
    "sg:province":"CA",
    "sg:tags":[
        "accountant"
    ],
    "wof:name":"Theodore M Rosenthal CPA",
    "wof:placetype":"venue"
},
  "geometry": {"coordinates":[-118.481263,34.155966],"type":"Point"}
}