{
  "type": "Feature",
  "properties": {
    "addr:full":"26446 Old Rd Moreno Valley CA 92570",
    "addr:housenumber":"26446",
    "addr:postcode":"92570",
    "addr:street":"Old Rd",
    "iso:country":"US",
    "sg:address":"26446 Old Rd",
    "sg:city":"Moreno Valley",
    "sg:classifiers":[
        {
            "category":"Wholesale",
            "subcategory":"Hardware",
            "type":"Manufacturing & Wholesale Goods"
        }
    ],
    "sg:phone":"+1 951 242 2796",
    "sg:postcode":"92570",
    "sg:province":"CA",
    "wof:name":"Shawn M Gottschalk",
    "wof:placetype":"venue"
},
  "geometry": {"coordinates":[-117.291445,33.775803],"type":"Point"}
}