{
  "type": "Feature",
  "properties": {
    "addr:full":"7969 Foothill Blvd Sunland CA 91040",
    "addr:housenumber":"7969",
    "addr:postcode":"91040",
    "addr:street":"Foothill Blvd",
    "iso:country":"US",
    "sg:address":"7969 Foothill Blvd",
    "sg:city":"Sunland",
    "sg:classifiers":[
        {
            "category":"Health Services",
            "subcategory":"Chiropractor",
            "type":"Services"
        }
    ],
    "sg:phone":"+1 818 353 4435",
    "sg:postcode":"91040",
    "sg:province":"CA",
    "sg:tags":[
        "herb",
        "clinic",
        "retail",
        "vitamin",
        "chiropractic"
    ],
    "wof:name":"Sunland Chiropractic Ctr",
    "wof:placetype":"venue"
},
  "geometry": {"coordinates":[-118.306561,34.259646],"type":"Point"}
}