{
  "type": "Feature",
  "properties": {
    "addr:full":"1450 Sebastopol Rd Santa Rosa CA 95407",
    "addr:housenumber":"1450",
    "addr:postcode":"95407",
    "addr:street":"Sebastopol Rd",
    "iso:country":"US",
    "sg:address":"1450 Sebastopol Rd",
    "sg:city":"Santa Rosa",
    "sg:classifiers":[
        {
            "category":"Retail",
            "subcategory":"Car Wash",
            "type":"Services"
        }
    ],
    "sg:phone":"+1 707 526 6267",
    "sg:postcode":"95407",
    "sg:province":"CA",
    "sg:tags":[
        "polishing",
        "washing"
    ],
    "wof:name":"Roseland Self-Svc Car Wash",
    "wof:placetype":"venue"
},
  "geometry": {"coordinates":[-122.735542,38.427989],"type":"Point"}
}