{
  "type": "Feature",
  "properties": {
    "iso:country":"US",
    "sg:address":"2601 E Victoria St",
    "sg:city":"Compton",
    "sg:classifiers":[
        {
            "category":"Manufacturing",
            "subcategory":"Aerospace",
            "type":"Manufacturing & Wholesale Goods"
        }
    ],
    "sg:phone":"+1 310 332 5160",
    "sg:postcode":"90220",
    "sg:province":"CA",
    "sg:tags":[
        "aircraft",
        "mfg"
    ],
    "wof:name":"Richard A Shackelford",
    "wof:placetype":"venue"
},
  "geometry": {"coordinates":[-118.219775,33.864382],"type":"Point"}
}