{
  "type": "Feature",
  "properties": {
    "addr:full":"817 First Street Brentwood CA 94513",
    "addr:housenumber":"817",
    "addr:postcode":"94513",
    "addr:street":"First Street",
    "iso:country":"US",
    "sg:address":"817 First Street",
    "sg:city":"Brentwood",
    "sg:classifiers":[
        {
            "category":"Education",
            "subcategory":"Dance Studio",
            "type":"Public Place"
        }
    ],
    "sg:phone":"+1 925 516 3667",
    "sg:postcode":"94513",
    "sg:province":"CA",
    "sg:website":"reddoordance.com/",
    "wof:name":"Red Door Dance Studio",
    "wof:placetype":"venue"
},
  "geometry": {"coordinates":[-121.696062,37.933999],"type":"Point"}
}