{
  "type": "Feature",
  "properties": {
    "addr:full":"26888 The Old Rd Valencia CA 91381",
    "addr:housenumber":"26888",
    "addr:postcode":"91381",
    "addr:street":"The Old Rd",
    "iso:country":"US",
    "sg:address":"26888 The Old Rd",
    "sg:city":"Valencia",
    "sg:classifiers":[
        {
            "category":"Fast Food",
            "type":"Food & Drink"
        },
        {
            "category":"Restaurant",
            "type":"Food & Drink"
        },
        {
            "category":"Food & Beverages",
            "subcategory":"Groceries & Convenience Stores",
            "type":"Retail Goods"
        }
    ],
    "sg:phone":"+1 661 255 9991",
    "sg:postcode":"91381",
    "sg:province":"CA",
    "sg:tags":[
        "shop",
        "american",
        "sandwich",
        "take"
    ],
    "sg:website":"http://www.subway.com",
    "wof:name":"Subway",
    "wof:placetype":"venue"
},
  "geometry": {"coordinates":[-118.57935000000001,34.409855],"type":"Point"}
}