{
  "type": "Feature",
  "properties": {
    "iso:country":"US",
    "sg:address":"385 Bel Marin Keys Blvd",
    "sg:city":"Novato",
    "sg:classifiers":[
        {
            "category":"Fast Food",
            "type":"Food & Drink"
        },
        {
            "category":"Restaurant",
            "type":"Food & Drink"
        }
    ],
    "sg:phone":"+1 415 883 8017",
    "sg:postcode":"94949",
    "sg:province":"CA",
    "sg:tags":[
        "style",
        "thai",
        "asian",
        "family",
        "pan"
    ],
    "wof:name":"Arun Thai Restaurant",
    "wof:placetype":"venue"
},
  "geometry": {"coordinates":[-122.537893,38.074545],"type":"Point"}
}