{
  "type": "Feature",
  "properties": {
    "iso:country":"US",
    "sg:address":"2367 Market St",
    "sg:city":"San Francisco",
    "sg:classifiers":[
        {
            "category":"Restaurant",
            "type":"Food & Drink"
        }
    ],
    "sg:phone":"+1 415 431 3463",
    "sg:postcode":"94114",
    "sg:province":"CA",
    "wof:name":"Khun Phoa Thai Cuisine II",
    "wof:placetype":"venue"
},
  "geometry": {"coordinates":[-122.43380999999999,37.76358],"type":"Point"}
}