{
  "type": "Feature",
  "properties": {
    "addr:full":"69040 E Palm Canyon Dr Cathedral City CA 92234",
    "addr:housenumber":"69040",
    "addr:postcode":"92234",
    "addr:street":"E Palm Canyon Dr",
    "iso:country":"US",
    "sg:address":"69040 E Palm Canyon Dr",
    "sg:city":"Cathedral City",
    "sg:classifiers":[
        {
            "category":"Personal",
            "subcategory":"Nail Salon",
            "type":"Services"
        }
    ],
    "sg:phone":"+1 760 318 4360",
    "sg:postcode":"92234",
    "sg:province":"CA",
    "wof:name":"Nail Tech",
    "wof:placetype":"venue"
},
  "geometry": {"coordinates":[-116.458067,33.77806],"type":"Point"}
}