{
  "type": "Feature",
  "properties": {
    "addr:full":"41910 Boardwalk Palm Desert CA 92211",
    "addr:housenumber":"41910",
    "addr:postcode":"ca 92211",
    "addr:street":"Boardwalk",
    "iso:country":"US",
    "sg:address":"41910 Boardwalk",
    "sg:city":"Palm Desert",
    "sg:classifiers":[
        {
            "category":"Building & Trades",
            "subcategory":"Cleaning & Sanitation",
            "type":"Services"
        }
    ],
    "sg:phone":"+1 760 346 4122",
    "sg:postcode":"92211",
    "sg:province":"CA",
    "sg:tags":[
        "property",
        "maintenance"
    ],
    "wof:name":"Best Property Svc",
    "wof:placetype":"venue"
},
  "geometry": {"coordinates":[-116.355029,33.745011],"type":"Point"}
}