{
  "type": "Feature",
  "properties": {
    "addr:full":"83827 Tamarisk Ave Indio CA 92201",
    "addr:postcode":"83827;92201",
    "addr:street":"Tamarisk Ave",
    "iso:country":"US",
    "sg:address":"83827 Tamarisk Ave",
    "sg:city":"Indio",
    "sg:classifiers":[
        {
            "category":"Retail",
            "subcategory":"Auto Rental",
            "type":"Services"
        }
    ],
    "sg:phone":"+1 760 347 8266",
    "sg:postcode":"92201",
    "sg:province":"CA",
    "sg:tags":[
        "home",
        "leasing",
        "motor"
    ],
    "wof:name":"Coachella Valley Rv Rentals",
    "wof:placetype":"venue"
},
  "geometry": {"coordinates":[-116.201673,33.710312],"type":"Point"}
}