{
  "type": "Feature",
  "properties": {
    "addr:full":"411 Borel Avenue Suite 440 San Mateo CA 94402",
    "addr:housenumber":"411",
    "addr:postcode":"94402",
    "addr:street":"Borel Avenue Suite 440",
    "iso:country":"US",
    "sg:address":"411 Borel Avenue Suite 440",
    "sg:city":"San Mateo",
    "sg:classifiers":[
        {
            "category":"Professional",
            "subcategory":"Lawyer & Legal Services",
            "type":"Services"
        }
    ],
    "sg:phone":"+1 650 524 2144",
    "sg:postcode":"94402",
    "sg:province":"CA",
    "sg:tags":[
        "divorce",
        "law",
        "family"
    ],
    "sg:website":"www.hansonflg.com",
    "wof:name":"Hanson Family Law Group",
    "wof:placetype":"venue"
},
  "geometry": {"coordinates":[-122.31990999999999,37.549122],"type":"Point"}
}