{
  "type": "Feature",
  "properties": {
    "addr:full":"901 N Wilson St San Bernardino CA 92411",
    "addr:housenumber":"901",
    "addr:postcode":"92411",
    "addr:street":"N Wilson St",
    "iso:country":"US",
    "sg:address":"901 N Wilson St",
    "sg:city":"San Bernardino",
    "sg:classifiers":[
        {
            "category":"Education",
            "subcategory":"School",
            "type":"Public Place"
        }
    ],
    "sg:phone":"+1 909 888 0493",
    "sg:postcode":"92411",
    "sg:province":"CA",
    "wof:name":"San Bernardino West Head Start",
    "wof:placetype":"venue"
},
  "geometry": {"coordinates":[-117.324461,34.116275],"type":"Point"}
}