{
  "type": "Feature",
  "properties": {
    "iso:country":"US",
    "sg:address":"2025 E 7th St",
    "sg:city":"Long Beach",
    "sg:classifiers":[
        {
            "category":"Education",
            "subcategory":"School",
            "type":"Public Place"
        }
    ],
    "sg:phone":"+1 562 284 0108",
    "sg:postcode":"90804",
    "sg:province":"CA",
    "sg:tags":[
        "high",
        "middle",
        "elementary"
    ],
    "wof:name":"Tay Academy",
    "wof:placetype":"venue"
},
  "geometry": {"coordinates":[-118.167372,33.775477],"type":"Point"}
}