{
  "type": "Feature",
  "properties": {
    "iso:country":"US",
    "sg:address":"4382 Alamo St",
    "sg:city":"Simi Valley",
    "sg:classifiers":[
        {
            "category":"Professional",
            "subcategory":"Lawyer & Legal Services",
            "type":"Services"
        }
    ],
    "sg:phone":"+1 805 527 4668",
    "sg:postcode":"93063",
    "sg:province":"CA",
    "sg:tags":[
        "attorney"
    ],
    "wof:name":"William R Robinson",
    "wof:placetype":"venue"
},
  "geometry": {"coordinates":[-118.709293,34.286215],"type":"Point"}
}