{
  "type": "Feature",
  "properties": {
    "addr:full":"2028 Gateway Pl San Jose CA 95110",
    "addr:housenumber":"2028",
    "addr:postcode":"95110",
    "addr:street":"Gateway Pl",
    "iso:country":"US",
    "sg:address":"2028 Gateway Pl",
    "sg:city":"San Jose",
    "sg:classifiers":[
        {
            "category":"Utilities",
            "subcategory":"Telephone",
            "type":"Services"
        }
    ],
    "sg:phone":"+1 408 350 8098",
    "sg:postcode":"95110",
    "sg:province":"CA",
    "sg:tags":[
        "telecommunication"
    ],
    "wof:name":"SS8 Networks",
    "wof:placetype":"venue"
},
  "geometry": {"coordinates":[-121.92252000000001,37.370781],"type":"Point"}
}