{
  "type": "Feature",
  "properties": {
    "addr:full":"1816 W Sunset Blvd Los Angeles CA 90026",
    "addr:housenumber":"1816",
    "addr:postcode":"90026",
    "addr:street":"W Sunset Blvd",
    "iso:country":"US",
    "sg:address":"1816 W Sunset Blvd",
    "sg:city":"Los Angeles",
    "sg:classifiers":[
        {
            "category":"Home & Garden",
            "subcategory":"Furniture",
            "type":"Retail Goods"
        }
    ],
    "sg:phone":"+1 213 353 0251",
    "sg:postcode":"90026",
    "sg:province":"CA",
    "wof:name":"Luna's Furnitures",
    "wof:placetype":"venue"
},
  "geometry": {"coordinates":[-118.260347,34.077971],"type":"Point"}
}