{
  "type": "Feature",
  "properties": {
    "addr:full":"2138 Verdugo Blvd Montrose CA 91020",
    "addr:housenumber":"2138",
    "addr:postcode":"91020",
    "addr:street":"Verdugo Blvd",
    "iso:country":"US",
    "sg:address":"2138 Verdugo Blvd",
    "sg:city":"Montrose",
    "sg:classifiers":[
        {
            "category":"Restaurant",
            "type":"Food & Drink"
        }
    ],
    "sg:phone":"+1 818 249 4393",
    "sg:postcode":"91020",
    "sg:province":"CA",
    "sg:tags":[
        "chinese"
    ],
    "sg:website":"www.newmoonrestaurants.com",
    "wof:name":"New Moon Restaurant",
    "wof:placetype":"venue"
},
  "geometry": {"coordinates":[-118.22402700000001,34.204875],"type":"Point"}
}