{
  "type": "Feature",
  "properties": {
    "iso:country":"US",
    "sg:address":"10988 W Larch Rd",
    "sg:city":"Tracy",
    "sg:classifiers":[
        {
            "category":"Building & Trades",
            "subcategory":"Landscaping Services",
            "type":"Services"
        }
    ],
    "sg:phone":"+1 209 832 9694",
    "sg:postcode":"95304",
    "sg:province":"CA",
    "sg:tags":[
        "landscape",
        "contractor"
    ],
    "wof:name":"Sandhu Landscaping",
    "wof:placetype":"venue"
},
  "geometry": {"coordinates":[-121.452181,37.764936],"type":"Point"}
}