{
  "type": "Feature",
  "properties": {
    "addr:full":"2980 W 8th Street Los Angeles CA 90005",
    "addr:housenumber":"2980",
    "addr:postcode":"90005",
    "addr:street":"W 8Th Street",
    "iso:country":"US",
    "sg:address":"2980 W 8th Street",
    "sg:city":"Los Angeles",
    "sg:classifiers":[
        {
            "category":"Cinema",
            "subcategory":"Movie Rental",
            "type":"Entertainment"
        }
    ],
    "sg:phone":"+1 213 385 4702",
    "sg:postcode":"90005",
    "sg:province":"CA",
    "sg:tags":[
        "game",
        "video"
    ],
    "wof:name":"El Chasis Video",
    "wof:placetype":"venue"
},
  "geometry": {"coordinates":[-118.29088,34.057837],"type":"Point"}
}