{
  "type": "Feature",
  "properties": {
    "iso:country":"US",
    "sg:address":"227 Elm St",
    "sg:city":"San Mateo",
    "sg:classifiers":[
        {
            "category":"Wholesale",
            "subcategory":"Farm Supplies",
            "type":"Manufacturing & Wholesale Goods"
        }
    ],
    "sg:phone":"+1 650 343 2836",
    "sg:postcode":"94401",
    "sg:province":"CA",
    "sg:tags":[
        "raw",
        "product",
        "material"
    ],
    "wof:name":"Covantage Inc",
    "wof:placetype":"venue"
},
  "geometry": {"coordinates":[-122.33184900000001,37.569772],"type":"Point"}
}