{
  "type": "Feature",
  "properties": {
    "addr:full":"44366 S Grimmer Blvd Fremont CA 94538",
    "addr:housenumber":"44366",
    "addr:postcode":"94538",
    "addr:street":"S Grimmer Blvd",
    "iso:country":"US",
    "sg:address":"44366 S Grimmer Blvd",
    "sg:city":"Fremont",
    "sg:classifiers":[
        {
            "category":"Professional",
            "subcategory":"Testing Lab",
            "type":"Services"
        }
    ],
    "sg:phone":"+1 510 490 4307",
    "sg:postcode":"94538",
    "sg:province":"CA",
    "sg:tags":[
        "laboratory"
    ],
    "wof:name":"EMCE Engineering",
    "wof:placetype":"venue"
},
  "geometry": {"coordinates":[-121.955068,37.502728],"type":"Point"}
}