{
  "type": "Feature",
  "properties": {
    "iso:country":"US",
    "sg:address":"5485 Hemlock St",
    "sg:city":"Sacramento",
    "sg:classifiers":[
        {
            "category":"Building & Trades",
            "subcategory":"Plumbing",
            "type":"Services"
        }
    ],
    "sg:phone":"+1 916 443 1023",
    "sg:postcode":"95841",
    "sg:province":"CA",
    "sg:tags":[
        "plumbing",
        "contractor"
    ],
    "wof:name":"Allstate Plumbing Heating AC",
    "wof:placetype":"venue"
},
  "geometry": {"coordinates":[-121.341335,38.664788],"type":"Point"}
}