{
  "type": "Feature",
  "properties": {
    "addr:full":"600 Battery St San Francisco CA 94111",
    "addr:housenumber":"600",
    "addr:postcode":"94111",
    "addr:street":"Battery St",
    "iso:country":"US",
    "sg:address":"600 Battery St",
    "sg:city":"San Francisco",
    "sg:classifiers":[
        {
            "category":"Professional",
            "subcategory":"Advertising",
            "type":"Services"
        }
    ],
    "sg:phone":"+1 415 820 8000",
    "sg:postcode":"94111",
    "sg:province":"CA",
    "sg:tags":[
        "agency"
    ],
    "wof:name":"E Business Strategy",
    "wof:placetype":"venue"
},
  "geometry": {"coordinates":[-122.400863,37.797654],"type":"Point"}
}