{
  "type": "Feature",
  "properties": {
    "iso:country":"US",
    "sg:address":"31795 State Hwy 18",
    "sg:city":"Lucerne Valley",
    "sg:classifiers":[
        {
            "category":"Home & Garden",
            "subcategory":"Hardware",
            "type":"Retail Goods"
        }
    ],
    "sg:phone":"+1 760 248 6224",
    "sg:postcode":"92356",
    "sg:province":"CA",
    "sg:tags":[
        "tool",
        "used"
    ],
    "wof:name":"Valley Hardware Tool",
    "wof:placetype":"venue"
},
  "geometry": {"coordinates":[-116.971515,34.443679],"type":"Point"}
}