{
  "type": "Feature",
  "properties": {
    "addr:full":"3432 Main St Cottonwood CA 96022",
    "addr:housenumber":"3432",
    "addr:postcode":"96022",
    "addr:street":"Main St",
    "iso:country":"US",
    "sg:address":"3432 Main St",
    "sg:city":"Cottonwood",
    "sg:classifiers":[
        {
            "category":"Professional",
            "type":"Services"
        }
    ],
    "sg:phone":"+1 530 347 1995",
    "sg:postcode":"96022",
    "sg:province":"CA",
    "sg:tags":[
        "establishment"
    ],
    "wof:name":"K J Enterprises",
    "wof:placetype":"venue"
},
  "geometry": {"coordinates":[-122.28111199999999,40.38811],"type":"Point"}
}