{
  "type": "Feature",
  "properties": {
    "addr:full":"817 S 1st St Alhambra CA 91801",
    "addr:housenumber":"817",
    "addr:postcode":"91801",
    "addr:street":"S 1St St",
    "iso:country":"US",
    "sg:address":"817 S 1st St",
    "sg:city":"Alhambra",
    "sg:classifiers":[
        {
            "category":"Health Services",
            "subcategory":"Health Practitioner",
            "type":"Services"
        }
    ],
    "sg:phone":"+1 626 288 0437",
    "sg:postcode":"91801",
    "sg:province":"CA",
    "sg:tags":[
        "nutritionist"
    ],
    "wof:name":"D E Trong",
    "wof:placetype":"venue"
},
  "geometry": {"coordinates":[-118.12419199999999,34.084931],"type":"Point"}
}