{
  "type": "Feature",
  "properties": {
    "iso:country":"US",
    "sg:address":"5180 Sonoma Blvd",
    "sg:city":"Vallejo",
    "sg:classifiers":[
        {
            "category":"Restaurant",
            "type":"Food & Drink"
        }
    ],
    "sg:phone":"+1 707 649 8213",
    "sg:postcode":"94589",
    "sg:province":"CA",
    "wof:name":"Mc Donald's",
    "wof:placetype":"venue"
},
  "geometry": {"coordinates":[-122.254327,38.148559],"type":"Point"}
}