{
  "type": "Feature",
  "properties": {
    "iso:country":"US",
    "sg:address":"1234 S Aurora St",
    "sg:city":"Stockton",
    "sg:classifiers":[
        {
            "category":"Retail",
            "subcategory":"Auto Rental",
            "type":"Services"
        },
        {
            "category":"Retail",
            "subcategory":"Storage",
            "type":"Services"
        }
    ],
    "sg:phone":"+1 209 946 0866",
    "sg:postcode":"95206",
    "sg:province":"CA",
    "sg:tags":[
        "moving-self",
        "truck"
    ],
    "sg:website":"http://www.uhaul.com/Locations/Rentals-near-Stockton-CA-95206/021133",
    "wof:name":"U-Haul Neighborhood Dealer - Charter Way Tow",
    "wof:placetype":"venue"
},
  "geometry": {"coordinates":[-121.276048,37.942272],"type":"Point"}
}