{
  "type": "Feature",
  "properties": {
    "iso:country":"US",
    "sg:address":"25395 Hancock Ave",
    "sg:city":"Murrieta",
    "sg:classifiers":[
        {
            "category":"Health Services",
            "subcategory":"Optometrist",
            "type":"Services"
        }
    ],
    "sg:phone":"+1 951 696 5388",
    "sg:postcode":"92562",
    "sg:province":"CA",
    "wof:name":"Inland Eye Clinic Medical Grp",
    "wof:placetype":"venue"
},
  "geometry": {"coordinates":[-117.185169,33.559491],"type":"Point"}
}