{
  "type": "Feature",
  "properties": {
    "addr:full":"15795 Highland Dr San Jose CA 95127",
    "addr:housenumber":"15795",
    "addr:postcode":"95127",
    "addr:street":"Highland Dr",
    "iso:country":"US",
    "sg:address":"15795 Highland Dr",
    "sg:city":"San Jose",
    "sg:classifiers":[
        {
            "category":"Health Services",
            "subcategory":"Doctor",
            "type":"Services"
        }
    ],
    "sg:phone":"+1 408 251 5007",
    "sg:postcode":"95127",
    "sg:province":"CA",
    "sg:tags":[
        "physician",
        "surgeon"
    ],
    "wof:name":"Raymond L Reynaud MD",
    "wof:placetype":"venue"
},
  "geometry": {"coordinates":[-121.81332500000001,37.388085],"type":"Point"}
}