{
  "type": "Feature",
  "properties": {
    "addr:full":"1524 S Flower St Santa Ana CA 92707",
    "addr:housenumber":"1524",
    "addr:postcode":"92707",
    "addr:street":"S Flower St",
    "iso:country":"US",
    "sg:address":"1524 S Flower St",
    "sg:city":"Santa Ana",
    "sg:classifiers":[
        {
            "category":"Restaurant",
            "type":"Food & Drink"
        }
    ],
    "sg:phone":"+1 714 545 5584",
    "sg:postcode":"92707",
    "sg:province":"CA",
    "sg:tags":[
        "mexican"
    ],
    "wof:name":"Las Brisas De Apatzingan",
    "wof:placetype":"venue"
},
  "geometry": {"coordinates":[-117.876999,33.727001],"type":"Point"}
}