{
  "type": "Feature",
  "properties": {
    "addr:full":"PO BOX 345 Palm Springs CA 92263",
    "addr:housenumber":"po;345",
    "addr:postcode":"92263",
    "addr:street":"Box",
    "iso:country":"US",
    "sg:address":"PO BOX 345",
    "sg:city":"Palm Springs",
    "sg:classifiers":[
        {
            "category":"Professional",
            "subcategory":"Business Services",
            "type":"Services"
        }
    ],
    "sg:postcode":"92263",
    "sg:province":"CA",
    "sg:tags":[
        "social--venture--capital",
        "non-profit",
        "b-corporations",
        "fund--raising",
        "auctions",
        "reverse-auctions",
        "sms"
    ],
    "sg:website":"http://www.bid4good.com",
    "wof:name":"Bid 4 Good",
    "wof:placetype":"venue"
},
  "geometry": {"coordinates":[-116.535887,33.761076],"type":"Point"}
}