{
  "type": "Feature",
  "properties": {
    "addr:full":"2463 Glen Exeter Way San Jose CA 95148",
    "addr:housenumber":"2463",
    "addr:postcode":"95148",
    "addr:street":"Glen Exeter Way",
    "iso:country":"US",
    "sg:address":"2463 Glen Exeter Way",
    "sg:city":"San Jose",
    "sg:classifiers":[
        {
            "category":"Social Services",
            "subcategory":"Adult Care",
            "type":"Services"
        }
    ],
    "sg:phone":"+1 408 274 6125",
    "sg:postcode":"95148",
    "sg:province":"CA",
    "sg:tags":[
        "home",
        "residential"
    ],
    "wof:name":"Glen Manor Residential Home",
    "wof:placetype":"venue"
},
  "geometry": {"coordinates":[-121.807303,37.331551],"type":"Point"}
}