{
  "type": "Feature",
  "properties": {
    "iso:country":"US",
    "sg:address":"307 Columbus St",
    "sg:city":"Bakersfield",
    "sg:classifiers":[
        {
            "category":"Retail",
            "subcategory":"Auto Repair",
            "type":"Services"
        }
    ],
    "sg:phone":"+1 661 323 5209",
    "sg:postcode":"93305",
    "sg:province":"CA",
    "sg:tags":[
        "repairing",
        "automobile"
    ],
    "wof:name":"Steve Foust Automotive",
    "wof:placetype":"venue"
},
  "geometry": {"coordinates":[-118.992507,35.397415],"type":"Point"}
}