{
  "type": "Feature",
  "properties": {
    "addr:full":"1151 Vancouver Avenue Burlingame CA 94010",
    "addr:housenumber":"1151",
    "addr:postcode":"94010",
    "addr:street":"Vancouver Avenue",
    "iso:country":"US",
    "sg:address":"1151 Vancouver Avenue",
    "sg:city":"Burlingame",
    "sg:classifiers":[
        {
            "category":"Education",
            "subcategory":"School",
            "type":"Public Place"
        }
    ],
    "sg:phone":"+1 650 343 5500",
    "sg:postcode":"94010",
    "sg:province":"CA",
    "sg:tags":[
        "high",
        "middle",
        "elementary"
    ],
    "wof:name":"Cclc Roosevelt Elementary",
    "wof:placetype":"venue"
},
  "geometry": {"coordinates":[-122.369539,37.579843],"type":"Point"}
}