{
  "type": "Feature",
  "properties": {
    "addr:full":"20 San Felipe Ave San Francisco CA 94127",
    "addr:housenumber":"20",
    "addr:postcode":"94127",
    "addr:street":"San Felipe Ave",
    "iso:country":"US",
    "sg:address":"20 San Felipe Ave",
    "sg:city":"San Francisco",
    "sg:classifiers":[
        {
            "category":"Professional",
            "type":"Services"
        }
    ],
    "sg:phone":"+1 415 449 1219",
    "sg:postcode":"94127",
    "sg:province":"CA",
    "wof:name":"Amy G Rassen Inc",
    "wof:placetype":"venue"
},
  "geometry": {"coordinates":[-122.46319099999999,37.73242],"type":"Point"}
}