{
  "type": "Feature",
  "properties": {
    "addr:full":"1515 S Main St Santa Ana CA 92707",
    "addr:housenumber":"1515",
    "addr:postcode":"92707",
    "addr:street":"S Main St",
    "iso:country":"US",
    "sg:address":"1515 S Main St",
    "sg:city":"Santa Ana",
    "sg:classifiers":[
        {
            "category":"Manufacturing",
            "subcategory":"Leather Goods",
            "type":"Manufacturing & Wholesale Goods"
        }
    ],
    "sg:phone":"+1 714 667 1514",
    "sg:postcode":"92707",
    "sg:province":"CA",
    "wof:name":"Hugo's Custom Leather Interiors",
    "wof:placetype":"venue"
},
  "geometry": {"coordinates":[-117.867626,33.727031],"type":"Point"}
}