{
  "type": "Feature",
  "properties": {
    "addr:full":"337 Locust St Santa Cruz CA 95060",
    "addr:housenumber":"337",
    "addr:postcode":"95060",
    "addr:street":"Locust St",
    "iso:country":"US",
    "sg:address":"337 Locust St",
    "sg:city":"Santa Cruz",
    "sg:classifiers":[
        {
            "category":"Government",
            "subcategory":"Office",
            "type":"Public Place"
        }
    ],
    "sg:phone":"+1 831 420 5150",
    "sg:postcode":"95060",
    "sg:province":"CA",
    "sg:tags":[
        "city",
        "planning",
        "dev"
    ],
    "wof:name":"Santa Cruz Redevelopment Agcy",
    "wof:placetype":"venue"
},
  "geometry": {"coordinates":[-122.030316,36.974491],"type":"Point"}
}