{
  "type": "Feature",
  "properties": {
    "addr:full":"222 E 211 St Carson CA 90745",
    "addr:housenumber":"222",
    "addr:postcode":"90745",
    "addr:street":"E 211 St",
    "iso:country":"US",
    "sg:address":"222 E 211 St",
    "sg:city":"Carson",
    "sg:classifiers":[
        {
            "category":"Professional",
            "type":"Services"
        }
    ],
    "sg:phone":"+1 310 867 9796",
    "sg:postcode":"90745",
    "sg:province":"CA",
    "sg:tags":[
        "caterer"
    ],
    "sg:website":"hawaiiancatering.yolasite.com",
    "wof:name":"Iwalanis Hawaiian Catering",
    "wof:placetype":"venue"
},
  "geometry": {"coordinates":[-118.27465100000001,33.837933],"type":"Point"}
}