{
  "type": "Feature",
  "properties": {
    "iso:country":"US",
    "sg:address":"4750 Florin Rd",
    "sg:city":"Sacramento",
    "sg:classifiers":[
        {
            "category":"Retail",
            "subcategory":"Auto Repair",
            "type":"Services"
        }
    ],
    "sg:phone":"+1 916 393 1448",
    "sg:postcode":"95823",
    "sg:province":"CA",
    "sg:tags":[
        "automobile",
        "smog"
    ],
    "wof:name":"Smog Stop",
    "wof:placetype":"venue"
},
  "geometry": {"coordinates":[-121.451421,38.495995],"type":"Point"}
}