{
  "type": "Feature",
  "properties": {
    "iso:country":"US",
    "sg:address":"18425 Burbank Blvd",
    "sg:city":"Tarzana",
    "sg:classifiers":[
        {
            "category":"Professional",
            "subcategory":"Detective & Security Services",
            "type":"Services"
        }
    ],
    "sg:phone":"+1 818 774 0113",
    "sg:postcode":"91356",
    "sg:province":"CA",
    "sg:tags":[
        "guard",
        "patrol"
    ],
    "wof:name":"ABM Security Svc",
    "wof:placetype":"venue"
},
  "geometry": {"coordinates":[-118.535679,34.172421],"type":"Point"}
}