{
  "type": "Feature",
  "properties": {
    "addr:full":"125 N Maple Ave Fresno CA 93702",
    "addr:housenumber":"125",
    "addr:postcode":"93702",
    "addr:street":"N Maple Ave",
    "iso:country":"US",
    "sg:address":"125 N Maple Ave",
    "sg:city":"Fresno",
    "sg:classifiers":[
        {
            "category":"Personal",
            "subcategory":"Barber",
            "type":"Services"
        }
    ],
    "sg:phone":"+1 559 251 6848",
    "sg:postcode":"93702",
    "sg:province":"CA",
    "wof:name":"Gil's Barber Shop",
    "wof:placetype":"venue"
},
  "geometry": {"coordinates":[-119.745508,36.743547],"type":"Point"}
}