{
  "type": "Feature",
  "properties": {
    "addr:full":"316 S Irwindale Ave Azusa CA 91702",
    "addr:housenumber":"316",
    "addr:postcode":"91702",
    "addr:street":"S Irwindale Ave",
    "iso:country":"US",
    "sg:address":"316 S Irwindale Ave",
    "sg:city":"Azusa",
    "sg:classifiers":[
        {
            "category":"Utilities",
            "subcategory":"Telephone",
            "type":"Services"
        },
        {
            "category":"Communications",
            "type":"Services"
        }
    ],
    "sg:phone":"+1 626 308 0398",
    "sg:postcode":"91702",
    "sg:province":"CA",
    "sg:tags":[
        "equipment",
        "data",
        "system"
    ],
    "wof:name":"J Doering Communications",
    "wof:placetype":"venue"
},
  "geometry": {"coordinates":[-117.93382,34.117674],"type":"Point"}
}