{
  "type": "Feature",
  "properties": {
    "addr:full":"2132 W Pacific Coast Hwy Long Beach CA 90810",
    "addr:housenumber":"2132",
    "addr:postcode":"90810",
    "addr:street":"W Pacific Coast Hwy",
    "iso:country":"US",
    "sg:address":"2132 W Pacific Coast Hwy",
    "sg:city":"Long Beach",
    "sg:classifiers":[
        {
            "category":"Autos & Motor Vehicles",
            "subcategory":"Auto Supplies",
            "type":"Retail Goods"
        }
    ],
    "sg:phone":"+1 562 590 5595",
    "sg:postcode":"90810",
    "sg:province":"CA",
    "sg:tags":[
        "tire"
    ],
    "wof:name":"Macias Tire Sales",
    "wof:placetype":"venue"
},
  "geometry": {"coordinates":[-118.220001,33.790001],"type":"Point"}
}