{
  "type": "Feature",
  "properties": {
    "addr:full":"471 C St Chula Vista CA 91910",
    "addr:housenumber":"471",
    "addr:postcode":"91910",
    "addr:street":"C St",
    "iso:country":"US",
    "sg:address":"471 C St",
    "sg:city":"Chula Vista",
    "sg:classifiers":[
        {
            "category":"Retail",
            "subcategory":"Storage",
            "type":"Services"
        }
    ],
    "sg:phone":"+1 619 422 0128",
    "sg:postcode":"91910",
    "sg:province":"CA",
    "sg:tags":[
        "self"
    ],
    "sg:website":"www.securitypublicstorage.com/SP...",
    "wof:name":"Security Public Storage",
    "wof:placetype":"venue"
},
  "geometry": {"coordinates":[-117.09086600000001,32.651192],"type":"Point"}
}