{
  "type": "Feature",
  "properties": {
    "addr:full":"23002 Lela Dr Diamond Bar CA 91765",
    "addr:postcode":"23002;91765",
    "addr:street":"Lela Dr",
    "iso:country":"US",
    "sg:address":"23002 Lela Dr",
    "sg:city":"Diamond Bar",
    "sg:classifiers":[
        {
            "category":"Insurance",
            "subcategory":"Insurance Agent",
            "type":"Services"
        }
    ],
    "sg:phone":"+1 909 861 2517",
    "sg:postcode":"91765",
    "sg:province":"CA",
    "wof:name":"Blue Cross & Blue Shield",
    "wof:placetype":"venue"
},
  "geometry": {"coordinates":[-117.815184,34.026408],"type":"Point"}
}