{
  "type": "Feature",
  "properties": {
    "addr:full":"3255 W Rosecrans Avenue Hawthorne CA 90250",
    "addr:housenumber":"3255",
    "addr:postcode":"90250",
    "addr:street":"W Rosecrans Avenue",
    "iso:country":"US",
    "sg:address":"3255 W Rosecrans Avenue",
    "sg:city":"Hawthorne",
    "sg:classifiers":[
        {
            "category":"Restaurant",
            "type":"Food & Drink"
        }
    ],
    "sg:phone":"+1 310 978 0456",
    "sg:postcode":"90250",
    "sg:province":"CA",
    "sg:tags":[
        "chinese"
    ],
    "wof:name":"Chinese Express Fast Food",
    "wof:placetype":"venue"
},
  "geometry": {"coordinates":[-118.329471,33.901816],"type":"Point"}
}