{
  "type": "Feature",
  "properties": {
    "iso:country":"US",
    "sg:address":"3409 Wood Glen Ct",
    "sg:city":"Rocklin",
    "sg:classifiers":[
        {
            "category":"Professional",
            "subcategory":"Business Services",
            "type":"Services"
        }
    ],
    "sg:phone":"+1 916 624 0921",
    "sg:postcode":"95677",
    "sg:province":"CA",
    "sg:tags":[
        "interior",
        "consultant",
        "design",
        "decorator"
    ],
    "wof:name":"Interiors By Rebekka",
    "wof:placetype":"venue"
},
  "geometry": {"coordinates":[-121.232442,38.822227],"type":"Point"}
}