{
  "type": "Feature",
  "properties": {
    "addr:full":"1955 41st Avenue Suite A2 Capitola CA 95010",
    "addr:housenumber":"1955",
    "addr:postcode":"95010",
    "addr:street":"41St Avenue Suite A2",
    "iso:country":"US",
    "sg:address":"1955 41st Avenue Suite A2",
    "sg:city":"Capitola",
    "sg:classifiers":[
        {
            "category":"Restaurant",
            "type":"Food & Drink"
        }
    ],
    "sg:phone":"+1 831 476 1818",
    "sg:postcode":"95010",
    "sg:province":"CA",
    "wof:name":"Tj Express",
    "wof:placetype":"venue"
},
  "geometry": {"coordinates":[-121.965005,36.977623],"type":"Point"}
}