{
  "type": "Feature",
  "properties": {
    "iso:country":"US",
    "sg:address":"3250 Ashford St. Unit P",
    "sg:city":"San Diego",
    "sg:classifiers":[
        {
            "category":"Real Estate",
            "subcategory":"Real Estate Operator",
            "type":"Services"
        }
    ],
    "sg:phone":"+1 858 360 0027",
    "sg:postcode":"92111",
    "sg:province":"CA",
    "sg:tags":[
        "apartment"
    ],
    "wof:name":"Judy Bridges and Barbara Guentner",
    "wof:placetype":"venue"
},
  "geometry": {"coordinates":[-117.160228,32.803287],"type":"Point"}
}