{
  "type": "Feature",
  "properties": {
    "addr:full":"3909 Chapman Pl Riverside CA 92506",
    "addr:housenumber":"3909",
    "addr:postcode":"92506",
    "addr:street":"Chapman Pl",
    "iso:country":"US",
    "sg:address":"3909 Chapman Pl",
    "sg:city":"Riverside",
    "sg:classifiers":[
        {
            "category":"Manufacturing",
            "subcategory":"Printing",
            "type":"Manufacturing & Wholesale Goods"
        }
    ],
    "sg:phone":"+1 951 682 3221",
    "sg:postcode":"92506",
    "sg:province":"CA",
    "sg:tags":[
        "print",
        "shop",
        "screen"
    ],
    "wof:name":"Screenmasters",
    "wof:placetype":"venue"
},
  "geometry": {"coordinates":[-117.389596,33.970353],"type":"Point"}
}