{
  "type": "Feature",
  "properties": {
    "addr:full":"106 Anacapa Dr Camarillo CA 93010",
    "addr:housenumber":"106",
    "addr:postcode":"93010",
    "addr:street":"Anacapa Dr",
    "iso:country":"US",
    "sg:address":"106 Anacapa Dr",
    "sg:city":"Camarillo",
    "sg:classifiers":[
        {
            "category":"Food & Beverages",
            "subcategory":"Specialty",
            "type":"Retail Goods"
        }
    ],
    "sg:phone":"+1 805 482 9758",
    "sg:postcode":"93010",
    "sg:province":"CA",
    "sg:tags":[
        "vitamin"
    ],
    "wof:name":"A C Enterprize",
    "wof:placetype":"venue"
},
  "geometry": {"coordinates":[-119.04413,34.236645],"type":"Point"}
}