{
  "type": "Feature",
  "properties": {
    "iso:country":"US",
    "sg:address":"5755 W Everett Ave",
    "sg:city":"Fresno",
    "sg:classifiers":[
        {
            "category":"Retail",
            "subcategory":"Animal Services",
            "type":"Services"
        }
    ],
    "sg:phone":"+1 559 275 3838",
    "sg:postcode":"93722",
    "sg:province":"CA",
    "sg:tags":[
        "pet"
    ],
    "wof:name":"Scoop Doggy-Doo",
    "wof:placetype":"venue"
},
  "geometry": {"coordinates":[-119.890597,36.848199],"type":"Point"}
}