{
  "type": "Feature",
  "properties": {
    "addr:full":"5250 W Century Blvd # 107 Los Angeles CA 90045",
    "addr:housenumber":"5250",
    "addr:postcode":"90045",
    "addr:street":"W Century Blvd # 107",
    "iso:country":"US",
    "sg:address":"5250 W Century Blvd # 107",
    "sg:city":"Los Angeles",
    "sg:classifiers":[
        {
            "category":"Autos & Motor Vehicles",
            "subcategory":"Automobile Sales",
            "type":"Retail Goods"
        },
        {
            "category":"Travel",
            "subcategory":"Hotels & Motels",
            "type":"Entertainment"
        }
    ],
    "sg:phone":"+1 310 216 7275",
    "sg:postcode":"90045",
    "sg:province":"CA",
    "sg:tags":[
        "car"
    ],
    "sg:website":"www.californiavanrental.com",
    "wof:name":"California Van Rental",
    "wof:placetype":"venue"
},
  "geometry": {"coordinates":[-118.371042,33.945312],"type":"Point"}
}