{
  "type": "Feature",
  "properties": {
    "addr:full":"6800 Reseda Blvd Reseda CA 91335",
    "addr:housenumber":"6800",
    "addr:postcode":"91335",
    "addr:street":"Reseda Blvd",
    "iso:country":"US",
    "sg:address":"6800 Reseda Blvd",
    "sg:city":"Reseda",
    "sg:classifiers":[
        {
            "category":"Home & Garden",
            "subcategory":"Furniture",
            "type":"Retail Goods"
        }
    ],
    "sg:phone":"+1 818 705 0124",
    "sg:postcode":"91335",
    "sg:province":"CA",
    "sg:tags":[
        "store"
    ],
    "wof:name":"Muebleria La Sabrosa 2",
    "wof:placetype":"venue"
},
  "geometry": {"coordinates":[-118.536041,34.193851],"type":"Point"}
}