{
  "type": "Feature",
  "properties": {
    "iso:country":"US",
    "sg:address":"3515 Sweetwater Spgs Blvd",
    "sg:city":"Spring Valley",
    "sg:classifiers":[
        {
            "category":"Restaurant",
            "type":"Food & Drink"
        }
    ],
    "sg:phone":"+1 619 670 7126",
    "sg:postcode":"91978",
    "sg:province":"CA",
    "sg:tags":[
        "mexican"
    ],
    "wof:name":"Pedro's Mexican Restaurant",
    "wof:placetype":"venue"
},
  "geometry": {"coordinates":[-116.973,32.742699],"type":"Point"}
}