{
  "type": "Feature",
  "properties": {
    "addr:full":"37521 Golden Cir Palmdale CA 93550",
    "addr:housenumber":"37521",
    "addr:postcode":"ca 93550",
    "addr:street":"Golden Cir",
    "iso:country":"US",
    "sg:address":"37521 Golden Cir",
    "sg:city":"Palmdale",
    "sg:classifiers":[
        {
            "category":"Professional",
            "type":"Services"
        }
    ],
    "sg:phone":"+1 661 273 3442",
    "sg:postcode":"93550",
    "sg:province":"CA",
    "wof:name":"Clearwater Technician",
    "wof:placetype":"venue"
},
  "geometry": {"coordinates":[-118.05860300000001,34.564092],"type":"Point"}
}