{
  "type": "Feature",
  "properties": {
    "addr:full":"1241 Franklin Mall Santa Clara CA 95050",
    "addr:housenumber":"1241",
    "addr:postcode":"95050",
    "addr:street":"Franklin Mall",
    "iso:country":"US",
    "sg:address":"1241 Franklin Mall",
    "sg:city":"Santa Clara",
    "sg:classifiers":[
        {
            "category":"Personal",
            "subcategory":"Nail Salon",
            "type":"Services"
        }
    ],
    "sg:phone":"+1 408 985 7941",
    "sg:postcode":"95050",
    "sg:province":"CA",
    "wof:name":"Charming Nails",
    "wof:placetype":"venue"
},
  "geometry": {"coordinates":[-121.947998,37.348999],"type":"Point"}
}