{
  "type": "Feature",
  "properties": {
    "addr:full":"233 Chula Vista St Chula Vista CA 91910",
    "addr:housenumber":"233",
    "addr:postcode":"91910",
    "addr:street":"Chula Vista St",
    "iso:country":"US",
    "sg:address":"233 Chula Vista St",
    "sg:city":"Chula Vista",
    "sg:classifiers":[
        {
            "category":"Real Estate",
            "subcategory":"Real Estate Agent",
            "type":"Services"
        }
    ],
    "sg:phone":"+1 619 427 1777",
    "sg:postcode":"91910",
    "sg:province":"CA",
    "wof:name":"Century Realty",
    "wof:placetype":"venue"
},
  "geometry": {"coordinates":[-117.079846,32.650524],"type":"Point"}
}