{
  "type": "Feature",
  "properties": {
    "addr:full":"10401 Roselle St San Diego CA 92121",
    "addr:housenumber":"10401",
    "addr:postcode":"92121",
    "addr:street":"Roselle St",
    "iso:country":"US",
    "sg:address":"10401 Roselle St",
    "sg:city":"San Diego",
    "sg:classifiers":[
        {
            "category":"Wholesale",
            "subcategory":"Computers",
            "type":"Manufacturing & Wholesale Goods"
        }
    ],
    "sg:phone":"+1 858 909 0459",
    "sg:postcode":"92121",
    "sg:province":"CA",
    "wof:name":"Radi Sys Corp",
    "wof:placetype":"venue"
},
  "geometry": {"coordinates":[-117.217415,32.892501],"type":"Point"}
}