{
  "type": "Feature",
  "properties": {
    "addr:full":"9310 Shadow Hill Rd Santee CA 92071",
    "addr:housenumber":"9310",
    "addr:postcode":"92071",
    "addr:street":"Shadow Hill Rd",
    "iso:country":"US",
    "sg:address":"9310 Shadow Hill Rd",
    "sg:city":"Santee",
    "sg:classifiers":[
        {
            "category":"Manufacturing",
            "subcategory":"Building Materials",
            "type":"Manufacturing & Wholesale Goods"
        }
    ],
    "sg:phone":"+1 619 840 7561",
    "sg:postcode":"92071",
    "sg:province":"CA",
    "sg:tags":[
        "mfg",
        "wood",
        "kitchen",
        "cabinet"
    ],
    "wof:name":"Dons Cabinets",
    "wof:placetype":"venue"
},
  "geometry": {"coordinates":[-116.958037,32.843878],"type":"Point"}
}