{
  "type": "Feature",
  "properties": {
    "iso:country":"US",
    "sg:address":"27759 Laurel Creek Cir",
    "sg:city":"Valencia",
    "sg:classifiers":[
        {
            "category":"Manufacturing",
            "subcategory":"Tools & Machinery",
            "type":"Manufacturing & Wholesale Goods"
        }
    ],
    "sg:phone":"+1 661 297 8070",
    "sg:postcode":"91354",
    "sg:province":"CA",
    "sg:tags":[
        "mfg",
        "apparatus",
        "welding"
    ],
    "wof:name":"JC & Assoc",
    "wof:placetype":"venue"
},
  "geometry": {"coordinates":[-118.53766400000001,34.454843],"type":"Point"}
}