{
  "type": "Feature",
  "properties": {
    "addr:full":"12930 Saratoga Ave Saratoga CA 95070",
    "addr:housenumber":"12930",
    "addr:postcode":"95070",
    "addr:street":"Saratoga Ave",
    "iso:country":"US",
    "sg:address":"12930 Saratoga Ave",
    "sg:city":"Saratoga",
    "sg:classifiers":[
        {
            "category":"Social Services",
            "subcategory":"Child Care",
            "type":"Services"
        }
    ],
    "sg:phone":"+1 408 973 1301",
    "sg:postcode":"95070",
    "sg:province":"CA",
    "sg:tags":[
        "day"
    ],
    "wof:name":"Stratford School",
    "wof:placetype":"venue"
},
  "geometry": {"coordinates":[-122.05166199999999,37.280723],"type":"Point"}
}