{
  "type": "Feature",
  "properties": {
    "iso:country":"US",
    "sg:address":"2137 W Temple St",
    "sg:city":"Los Angeles",
    "sg:classifiers":[
        {
            "category":"Restaurant",
            "type":"Food & Drink"
        }
    ],
    "sg:phone":"+1 213 484 0099",
    "sg:postcode":"90026",
    "sg:province":"CA",
    "sg:tags":[
        "cuban"
    ],
    "wof:name":"La Caridad Restaurant",
    "wof:placetype":"venue"
},
  "geometry": {"coordinates":[-118.268997,34.0704],"type":"Point"}
}