{
  "type": "Feature",
  "properties": {
    "addr:full":"101 W. Manchester Blvd. Inglewood CA 90301",
    "addr:housenumber":"101",
    "addr:postcode":"90301",
    "addr:street":"W. Manchester Blvd.",
    "iso:country":"US",
    "sg:address":"101 W. Manchester Blvd.",
    "sg:city":"Inglewood",
    "sg:classifiers":[
        {
            "category":"Education",
            "subcategory":"Library",
            "type":"Public Place"
        }
    ],
    "sg:phone":"+1 310 412 5380",
    "sg:postcode":"90301",
    "sg:province":"CA",
    "sg:website":"www.cityofinglewood.org/depts/li...",
    "wof:name":"Inglewood Public Library - Main Library",
    "wof:placetype":"venue"
},
  "geometry": {"coordinates":[-118.356095,33.961793],"type":"Point"}
}