{
  "type": "Feature",
  "properties": {
    "iso:country":"US",
    "sg:address":"539 League Ave",
    "sg:city":"La Puente",
    "sg:classifiers":[
        {
            "category":"Wholesale",
            "subcategory":"Durable Goods & Equipment",
            "type":"Manufacturing & Wholesale Goods"
        }
    ],
    "sg:phone":"+1 626 333 6608",
    "sg:postcode":"91744",
    "sg:province":"CA",
    "wof:name":"Love Linnie",
    "wof:placetype":"venue"
},
  "geometry": {"coordinates":[-117.973035,34.04201],"type":"Point"}
}