{
  "type": "Feature",
  "properties": {
    "addr:full":"6901 Topanga Canyon Blvd Canoga Park CA 91303",
    "addr:housenumber":"6901",
    "addr:postcode":"91303",
    "addr:street":"Topanga Canyon Blvd",
    "iso:country":"US",
    "sg:address":"6901 Topanga Canyon Blvd",
    "sg:city":"Canoga Park",
    "sg:classifiers":[
        {
            "category":"Home & Garden",
            "subcategory":"Household Appliances",
            "type":"Retail Goods"
        }
    ],
    "sg:phone":"+1 818 782 9259",
    "sg:postcode":"91303",
    "sg:province":"CA",
    "sg:tags":[
        "cleaners",
        "vacuum"
    ],
    "wof:name":"Kirby Sensation",
    "wof:placetype":"venue"
},
  "geometry": {"coordinates":[-118.60583800000001,34.196416],"type":"Point"}
}