{
  "type": "Feature",
  "properties": {
    "addr:full":"20045 Stevens Creek Blvd Cupertino CA 95014",
    "addr:housenumber":"20045",
    "addr:postcode":"95014",
    "addr:street":"Stevens Creek Blvd",
    "iso:country":"US",
    "sg:address":"20045 Stevens Creek Blvd",
    "sg:city":"Cupertino",
    "sg:classifiers":[
        {
            "category":"Health Services",
            "subcategory":"Hospital",
            "type":"Services"
        }
    ],
    "sg:phone":"+1 408 725 9070",
    "sg:postcode":"95014",
    "sg:province":"CA",
    "sg:tags":[
        "equipment",
        "supply"
    ],
    "wof:name":"Si Bone",
    "wof:placetype":"venue"
},
  "geometry": {"coordinates":[-122.023864,37.322999],"type":"Point"}
}