{
  "type": "Feature",
  "properties": {
    "addr:full":"3409 Johnston Ave Redondo Beach CA 90278",
    "addr:housenumber":"3409",
    "addr:postcode":"90278",
    "addr:street":"Johnston Ave",
    "iso:country":"US",
    "sg:address":"3409 Johnston Ave",
    "sg:city":"Redondo Beach",
    "sg:classifiers":[
        {
            "category":"Building & Trades",
            "subcategory":"Plumbing",
            "type":"Services"
        }
    ],
    "sg:phone":"+1 310 376 0779",
    "sg:postcode":"90278",
    "sg:province":"CA",
    "sg:tags":[
        "plumbing",
        "contractor"
    ],
    "wof:name":"Carl The Plumber",
    "wof:placetype":"venue"
},
  "geometry": {"coordinates":[-118.36939599999999,33.88678],"type":"Point"}
}