{
  "type": "Feature",
  "properties": {
    "iso:country":"US",
    "sg:address":"1158 Cirby Way",
    "sg:city":"Roseville",
    "sg:classifiers":[
        {
            "category":"Health Services",
            "subcategory":"Dentist",
            "type":"Services"
        }
    ],
    "sg:phone":"+1 916 786 6676",
    "sg:postcode":"95661",
    "sg:province":"CA",
    "sg:tags":[
        "denture",
        "dentists-prosthodontists",
        "dentistry",
        "implant",
        "dentists-implantology"
    ],
    "sg:website":"http://www.binondentalimplants.com",
    "wof:name":"Binon Paul P DDS MSD",
    "wof:placetype":"venue"
},
  "geometry": {"coordinates":[-121.273094,38.729496],"type":"Point"}
}