{
  "type": "Feature",
  "properties": {
    "addr:full":"2202 Wilshire Blvd Santa Monica CA 90403",
    "addr:housenumber":"2202",
    "addr:postcode":"90403",
    "addr:street":"Wilshire Blvd",
    "iso:country":"US",
    "sg:address":"2202 Wilshire Blvd",
    "sg:city":"Santa Monica",
    "sg:classifiers":[
        {
            "category":"Health Services",
            "subcategory":"Doctor",
            "type":"Services"
        }
    ],
    "sg:phone":"+1 310 586 1300",
    "sg:postcode":"90403",
    "sg:province":"CA",
    "sg:tags":[
        "physician",
        "surgeon"
    ],
    "wof:name":"Tower Imaging Medical Group",
    "wof:placetype":"venue"
},
  "geometry": {"coordinates":[-118.48062299999999,34.033323],"type":"Point"}
}