{
  "type": "Feature",
  "properties": {
    "iso:country":"US",
    "sg:address":"161 E Orange Grove Ave",
    "sg:city":"Burbank",
    "sg:classifiers":[
        {
            "category":"Professional",
            "type":"Services"
        }
    ],
    "sg:phone":"+1 818 558 1115",
    "sg:postcode":"91501",
    "sg:province":"CA",
    "wof:name":"Kabab Factory",
    "wof:placetype":"venue"
},
  "geometry": {"coordinates":[-118.310566,34.180938],"type":"Point"}
}