{
  "type": "Feature",
  "properties": {
    "iso:country":"US",
    "sg:address":"5425 Mountain View Dr",
    "sg:city":"Redding",
    "sg:classifiers":[
        {
            "category":"Food & Beverages",
            "subcategory":"Groceries & Convenience Stores",
            "type":"Retail Goods"
        }
    ],
    "sg:phone":"+1 530 241 1909",
    "sg:postcode":"96003",
    "sg:province":"CA",
    "wof:name":"Time To Stop",
    "wof:placetype":"venue"
},
  "geometry": {"coordinates":[-122.362112,40.620124],"type":"Point"}
}