{
  "type": "Feature",
  "properties": {
    "iso:country":"US",
    "sg:address":"1721 N Westwood St",
    "sg:city":"Porterville",
    "sg:classifiers":[
        {
            "category":"Restaurant",
            "type":"Food & Drink"
        }
    ],
    "sg:phone":"+1 559 793 1335",
    "sg:postcode":"93257",
    "sg:province":"CA",
    "wof:name":"Mahal Pargat",
    "wof:placetype":"venue"
},
  "geometry": {"coordinates":[-119.07078199999999,36.095577],"type":"Point"}
}