{
  "type": "Feature",
  "properties": {
    "addr:full":"3908 Escondido Dr Malibu CA 90265",
    "addr:housenumber":"3908",
    "addr:postcode":"90265",
    "addr:street":"Escondido Dr",
    "iso:country":"US",
    "sg:address":"3908 Escondido Dr",
    "sg:city":"Malibu",
    "sg:classifiers":[
        {
            "category":"Personal",
            "type":"Services"
        }
    ],
    "sg:phone":"+1 310 457 5119",
    "sg:postcode":"90265",
    "sg:province":"CA",
    "sg:tags":[
        "wedding",
        "chapel"
    ],
    "wof:name":"Malibu Phoenix Retreat",
    "wof:placetype":"venue"
},
  "geometry": {"coordinates":[-118.77627,34.051937],"type":"Point"}
}