{
  "type": "Feature",
  "properties": {
    "addr:full":"204 16th Pl Costa Mesa CA 92627",
    "addr:housenumber":"204",
    "addr:postcode":"92627",
    "addr:street":"16Th Pl",
    "iso:country":"US",
    "sg:address":"204 16th Pl",
    "sg:city":"Costa Mesa",
    "sg:classifiers":[
        {
            "category":"Education",
            "subcategory":"College",
            "type":"Public Place"
        }
    ],
    "sg:phone":"+1 949 642 0735",
    "sg:postcode":"92627",
    "sg:province":"CA",
    "sg:tags":[
        "academic",
        "school"
    ],
    "wof:name":"Sports Massage Training Inst",
    "wof:placetype":"venue"
},
  "geometry": {"coordinates":[-117.91918200000001,33.632294],"type":"Point"}
}