{
  "type": "Feature",
  "properties": {
    "iso:country":"US",
    "sg:address":"460 Martinelli St",
    "sg:city":"Watsonville",
    "sg:classifiers":[
        {
            "category":"Farming",
            "subcategory":"Orchard",
            "type":"Manufacturing & Wholesale Goods"
        }
    ],
    "sg:phone":"+1 831 724 0435",
    "sg:postcode":"95076",
    "sg:province":"CA",
    "sg:tags":[
        "apple"
    ],
    "wof:name":"John A Lukrich",
    "wof:placetype":"venue"
},
  "geometry": {"coordinates":[-121.751745,36.926339],"type":"Point"}
}