{
  "type": "Feature",
  "properties": {
    "addr:full":"3818 Ocean View Blvd Montrose CA 91020",
    "addr:housenumber":"3818",
    "addr:postcode":"91020",
    "addr:street":"Ocean View Blvd",
    "iso:country":"US",
    "sg:address":"3818 Ocean View Blvd",
    "sg:city":"Montrose",
    "sg:classifiers":[
        {
            "category":"Personal",
            "subcategory":"Beauty Salon",
            "type":"Services"
        },
        {
            "category":"Personal",
            "subcategory":"Barber",
            "type":"Services"
        }
    ],
    "sg:phone":"+1 818 957 3700",
    "sg:postcode":"91020",
    "sg:province":"CA",
    "wof:name":"Studio 18 Salon",
    "wof:placetype":"venue"
},
  "geometry": {"coordinates":[-118.22801200000001,34.206211],"type":"Point"}
}