{
  "type": "Feature",
  "properties": {
    "addr:full":"2332 D St La Verne CA 91750",
    "addr:housenumber":"2332",
    "addr:postcode":"91750",
    "addr:street":"D St",
    "iso:country":"US",
    "sg:address":"2332 D St",
    "sg:city":"La Verne",
    "sg:classifiers":[
        {
            "category":"Banks & Credit Unions",
            "subcategory":"Bank",
            "type":"Services"
        }
    ],
    "sg:phone":"+1 909 392 9544",
    "sg:postcode":"91750",
    "sg:province":"CA",
    "sg:tags":[
        "loan",
        "real estate"
    ],
    "wof:name":"Novastar Home Mortgage Inc",
    "wof:placetype":"venue"
},
  "geometry": {"coordinates":[-117.769814,34.101144],"type":"Point"}
}