{
  "type": "Feature",
  "properties": {
    "iso:country":"US",
    "sg:address":"2222 Francisco Dr",
    "sg:city":"El Dorado Hills",
    "sg:classifiers":[
        {
            "category":"Food & Beverages",
            "subcategory":"Groceries & Convenience Stores",
            "type":"Retail Goods"
        }
    ],
    "sg:phone":"+1 916 933 1421",
    "sg:postcode":"95762",
    "sg:province":"CA",
    "sg:tags":[
        "grocer"
    ],
    "wof:name":"Hilltop Market & Deli",
    "wof:placetype":"venue"
},
  "geometry": {"coordinates":[-121.086118,38.712601],"type":"Point"}
}