{
  "type": "Feature",
  "properties": {
    "addr:full":"101 Hyde St San Francisco CA 94102",
    "addr:housenumber":"101",
    "addr:postcode":"94102",
    "addr:street":"Hyde St",
    "iso:country":"US",
    "sg:address":"101 Hyde St",
    "sg:city":"San Francisco",
    "sg:classifiers":[
        {
            "category":"Building & Trades",
            "subcategory":"Cleaning & Sanitation",
            "type":"Services"
        },
        {
            "category":"Home & Garden",
            "subcategory":"Carpets & Floor Coverings",
            "type":"Retail Goods"
        }
    ],
    "sg:phone":"+1 415 738 0631",
    "sg:postcode":"94102",
    "sg:province":"CA",
    "sg:tags":[
        "carpeting"
    ],
    "sg:website":"www.sparklingcarpets.com",
    "wof:name":"AAA Sparkling Carpets",
    "wof:placetype":"venue"
},
  "geometry": {"coordinates":[-122.415897,37.781804],"type":"Point"}
}