{
  "type": "Feature",
  "properties": {
    "iso:country":"US",
    "sg:address":"555 N Benson Ave",
    "sg:city":"Upland",
    "sg:classifiers":[
        {
            "category":"Insurance",
            "subcategory":"Insurance Agent",
            "type":"Services"
        }
    ],
    "sg:phone":"+1 909 920 5104",
    "sg:postcode":"91786",
    "sg:province":"CA",
    "wof:name":"Larry Gutierrez",
    "wof:placetype":"venue"
},
  "geometry": {"coordinates":[-117.680994,34.101181],"type":"Point"}
}