{
  "type": "Feature",
  "properties": {
    "addr:full":"2300 Polvorosa Dr San Leandro CA 94577",
    "addr:housenumber":"2300",
    "addr:postcode":"94577",
    "addr:street":"Polvorosa Dr",
    "iso:country":"US",
    "sg:address":"2300 Polvorosa Dr",
    "sg:city":"San Leandro",
    "sg:classifiers":[
        {
            "category":"Building & Trades",
            "subcategory":"Construction",
            "type":"Services"
        }
    ],
    "sg:phone":"+1 510 895 2700",
    "sg:postcode":"94577",
    "sg:province":"CA",
    "sg:tags":[
        "tile",
        "dealer"
    ],
    "wof:name":"Superior Tile Co",
    "wof:placetype":"venue"
},
  "geometry": {"coordinates":[-122.188196,37.709485],"type":"Point"}
}