{
  "type": "Feature",
  "properties": {
    "iso:country":"US",
    "sg:address":"288 W Valley Blvd",
    "sg:city":"Alhambra",
    "sg:classifiers":[
        {
            "category":"Professional",
            "subcategory":"Lawyer & Legal Services",
            "type":"Services"
        }
    ],
    "sg:phone":"+1 626 284 1828",
    "sg:postcode":"91801",
    "sg:province":"CA",
    "sg:tags":[
        "consultant",
        "attorney",
        "law",
        "immigration",
        "naturalization"
    ],
    "wof:name":"Ytula",
    "wof:placetype":"venue"
},
  "geometry": {"coordinates":[-118.1254,34.078427],"type":"Point"}
}