{
  "type": "Feature",
  "properties": {
    "addr:full":"1940 Webster St Oakland CA 94612",
    "addr:housenumber":"1940",
    "addr:postcode":"94612",
    "addr:street":"Webster St",
    "iso:country":"US",
    "sg:address":"1940 Webster St",
    "sg:city":"Oakland",
    "sg:classifiers":[
        {
            "category":"Health Services",
            "subcategory":"Health Practitioner",
            "type":"Services"
        }
    ],
    "sg:phone":"+1 510 271 4760",
    "sg:postcode":"94612",
    "sg:province":"CA",
    "sg:tags":[
        "therapist",
        "physical"
    ],
    "wof:name":"Comprehenxive Orthopedic Rehab",
    "wof:placetype":"venue"
},
  "geometry": {"coordinates":[-122.26647199999999,37.806957],"type":"Point"}
}