{
  "type": "Feature",
  "properties": {
    "addr:full":"2619 W Beverly Blvd Montebello CA 90640",
    "addr:housenumber":"2619",
    "addr:postcode":"90640",
    "addr:street":"W Beverly Blvd",
    "iso:country":"US",
    "sg:address":"2619 W Beverly Blvd",
    "sg:city":"Montebello",
    "sg:classifiers":[
        {
            "category":"Wholesale",
            "subcategory":"Machinery & Supplies",
            "type":"Manufacturing & Wholesale Goods"
        }
    ],
    "sg:phone":"+1 323 722 6961",
    "sg:postcode":"90640",
    "sg:province":"CA",
    "sg:tags":[
        "salon",
        "beauty"
    ],
    "wof:name":"Black & White Distrs",
    "wof:placetype":"venue"
},
  "geometry": {"coordinates":[-118.130675,34.02078],"type":"Point"}
}