{
  "type": "Feature",
  "properties": {
    "addr:full":"855 Front Street San Francisco CA 94111",
    "addr:housenumber":"855",
    "addr:postcode":"94111",
    "addr:street":"Front Street",
    "iso:country":"US",
    "sg:address":"855 Front Street",
    "sg:city":"San Francisco",
    "sg:classifiers":[
        {
            "category":"Professional",
            "subcategory":"Lawyer & Legal Services",
            "type":"Services"
        }
    ],
    "sg:phone":"+1 415 781 4400",
    "sg:postcode":"94111",
    "sg:province":"CA",
    "wof:name":"Pia Robert J Mbv Law Llp",
    "wof:placetype":"venue"
},
  "geometry": {"coordinates":[-122.400187,37.799484],"type":"Point"}
}