{
  "type": "Feature",
  "properties": {
    "addr:full":"1161 Mission St San Francisco CA 94103",
    "addr:housenumber":"1161",
    "addr:postcode":"94103",
    "addr:street":"Mission St",
    "iso:country":"US",
    "sg:address":"1161 Mission St",
    "sg:city":"San Francisco",
    "sg:classifiers":[
        {
            "category":"Food & Beverages",
            "subcategory":"Specialty",
            "type":"Retail Goods"
        }
    ],
    "sg:phone":"+1 415 684 9288",
    "sg:postcode":"94103",
    "sg:province":"CA",
    "wof:name":"M Cafe",
    "wof:placetype":"venue"
},
  "geometry": {"coordinates":[-122.411996,37.777901],"type":"Point"}
}