{
  "type": "Feature",
  "properties": {
    "iso:country":"US",
    "sg:address":"5917 Noble Ave",
    "sg:city":"Van Nuys",
    "sg:classifiers":[
        {
            "category":"Shopping",
            "subcategory":"Bicycles & Sporting Goods",
            "type":"Retail Goods"
        }
    ],
    "sg:phone":"+1 818 782 6165",
    "sg:postcode":"91411",
    "sg:province":"CA",
    "sg:tags":[
        "saddlery",
        "harness"
    ],
    "wof:name":"Amspec Products",
    "wof:placetype":"venue"
},
  "geometry": {"coordinates":[-118.461884,34.179083],"type":"Point"}
}