{
  "type": "Feature",
  "properties": {
    "iso:country":"US",
    "sg:address":"9055 Soquel Drive Suite G",
    "sg:city":"Aptos",
    "sg:classifiers":[
        {
            "category":"Health Services",
            "subcategory":"Doctor",
            "type":"Services"
        },
        {
            "category":"Health Services",
            "subcategory":"Clinic",
            "type":"Services"
        }
    ],
    "sg:phone":"+1 831 457 3000",
    "sg:postcode":"95003",
    "sg:province":"CA",
    "sg:tags":[
        "counseling",
        "mental"
    ],
    "sg:website":"www.debrabungermd.medem.com",
    "wof:name":"Debra L Bunger, MD",
    "wof:placetype":"venue"
},
  "geometry": {"coordinates":[-121.890384,36.97627],"type":"Point"}
}