{
  "type": "Feature",
  "properties": {
    "addr:full":"68571 E Palm Canyon Dr Cathedral City CA 92234",
    "addr:housenumber":"68571",
    "addr:postcode":"92234",
    "addr:street":"E Palm Canyon Dr",
    "iso:country":"US",
    "sg:address":"68571 E Palm Canyon Dr",
    "sg:city":"Cathedral City",
    "sg:classifiers":[
        {
            "category":"Shopping",
            "subcategory":"Musical Instruments",
            "type":"Retail Goods"
        }
    ],
    "sg:phone":"+1 760 321 1808",
    "sg:postcode":"92234",
    "sg:province":"CA",
    "sg:tags":[
        "music",
        "dealer"
    ],
    "wof:name":"Musical Rodriguez",
    "wof:placetype":"venue"
},
  "geometry": {"coordinates":[-116.465468,33.7801],"type":"Point"}
}