{
  "type": "Feature",
  "properties": {
    "addr:full":"5921 Trajan Dr Fair Oaks CA 95628",
    "addr:postcode":"5921;95628",
    "addr:street":"Trajan Dr",
    "iso:country":"US",
    "sg:address":"5921 Trajan Dr",
    "sg:city":"Fair Oaks",
    "sg:classifiers":[
        {
            "category":"Building & Trades",
            "subcategory":"Construction",
            "type":"Services"
        }
    ],
    "sg:phone":"+1 916 961 7366",
    "sg:postcode":"95628",
    "sg:province":"CA",
    "sg:tags":[
        "contractor"
    ],
    "sg:website":"www.hsgconstruction.com/",
    "wof:name":"Heritage Service Group",
    "wof:placetype":"venue"
},
  "geometry": {"coordinates":[-121.248824,38.674513],"type":"Point"}
}