{
  "type": "Feature",
  "properties": {
    "iso:country":"US",
    "sg:address":"10119 Washington Blvd",
    "sg:city":"Culver City",
    "sg:classifiers":[
        {
            "category":"Home & Garden",
            "subcategory":"Home Furnishings",
            "type":"Retail Goods"
        }
    ],
    "sg:phone":"+1 310 558 3124",
    "sg:postcode":"90232",
    "sg:province":"CA",
    "sg:tags":[
        "pottery"
    ],
    "wof:name":"Pottery Plus",
    "wof:placetype":"venue"
},
  "geometry": {"coordinates":[-118.399674,34.020452],"type":"Point"}
}