{
  "type": "Feature",
  "properties": {
    "addr:full":"4653 Corte Mar de Corazon San Diego CA 92130",
    "addr:housenumber":"4653",
    "addr:postcode":"92130",
    "addr:street":"Corte Mar De Corazon",
    "iso:country":"US",
    "sg:address":"4653 Corte Mar de Corazon",
    "sg:city":"San Diego",
    "sg:classifiers":[
        {
            "category":"Organizations",
            "subcategory":"Professional Association",
            "type":"Services"
        }
    ],
    "sg:phone":"+1 858 792 5218",
    "sg:postcode":"92130",
    "sg:province":"CA",
    "wof:name":"Diplomatic Tradecraft Assoc",
    "wof:placetype":"venue"
},
  "geometry": {"coordinates":[-117.213824,32.92221],"type":"Point"}
}