{
  "type": "Feature",
  "properties": {
    "iso:country":"US",
    "sg:address":"Ardmore And Pico",
    "sg:city":"Los Angeles",
    "sg:classifiers":[
        {
            "category":"Restaurant",
            "type":"Food & Drink"
        },
        {
            "category":"Food & Beverages",
            "subcategory":"Ethnic Foods",
            "type":"Retail Goods"
        }
    ],
    "sg:postcode":"90006",
    "sg:province":"CA",
    "sg:tags":[
        "mexican"
    ],
    "wof:name":"Jose's Tacos",
    "wof:placetype":"venue"
},
  "geometry": {"coordinates":[-118.302543,34.047204],"type":"Point"}
}