{
  "type": "Feature",
  "properties": {
    "addr:full":"1420 Lake St Glendale CA 91201",
    "addr:housenumber":"1420",
    "addr:postcode":"91201",
    "addr:street":"Lake St",
    "iso:country":"US",
    "sg:address":"1420 Lake St",
    "sg:city":"Glendale",
    "sg:classifiers":[
        {
            "category":"Communications",
            "subcategory":"Film & Video Production",
            "type":"Services"
        }
    ],
    "sg:phone":"+1 818 241 1605",
    "sg:postcode":"91201",
    "sg:province":"CA",
    "sg:tags":[
        "taping"
    ],
    "wof:name":"Les Is More Productions",
    "wof:placetype":"venue"
},
  "geometry": {"coordinates":[-118.29360699999999,34.160294],"type":"Point"}
}