{
  "type": "Feature",
  "properties": {
    "iso:country":"US",
    "sg:address":"2500 Petaluma Blvd N",
    "sg:city":"Petaluma",
    "sg:classifiers":[
        {
            "category":"Home & Garden",
            "subcategory":"Garden Supply",
            "type":"Retail Goods"
        },
        {
            "category":"Wholesale",
            "subcategory":"Construction Materials",
            "type":"Manufacturing & Wholesale Goods"
        },
        {
            "category":"Home & Garden",
            "subcategory":"Building Materials",
            "type":"Retail Goods"
        },
        {
            "category":"Building & Trades",
            "subcategory":"Construction",
            "type":"Services"
        },
        {
            "category":"Utilities",
            "subcategory":"Natural Gas",
            "type":"Services"
        }
    ],
    "sg:phone":"+1 707 762 0505",
    "sg:postcode":"94952",
    "sg:province":"CA",
    "sg:tags":[
        "stone",
        "sand",
        "landscaping",
        "lawn",
        "face",
        "equipment",
        "shape",
        "concrete",
        "brick-clay-common",
        "mixed",
        "gravel",
        "concrete-ready",
        "block"
    ],
    "sg:website":"http://www.sonomarinmaterials.com",
    "wof:name":"Sonomarin Landscape Materials",
    "wof:placetype":"venue"
},
  "geometry": {"coordinates":[-122.65378,38.256851],"type":"Point"}
}