{
  "type": "Feature",
  "properties": {
    "addr:full":"20660 Bahama St Chatsworth CA 91311",
    "addr:housenumber":"20660",
    "addr:postcode":"91311",
    "addr:street":"Bahama St",
    "iso:country":"US",
    "sg:address":"20660 Bahama St",
    "sg:city":"Chatsworth",
    "sg:classifiers":[
        {
            "category":"Banks & Credit Unions",
            "subcategory":"Bank",
            "type":"Services"
        }
    ],
    "sg:phone":"+1 805 460 0125",
    "sg:postcode":"91311",
    "sg:province":"CA",
    "sg:tags":[
        "commercial"
    ],
    "wof:name":"Santa Lucia Bank Automated Boo",
    "wof:placetype":"venue"
},
  "geometry": {"coordinates":[-118.582672,34.231875],"type":"Point"}
}