{
  "type": "Feature",
  "properties": {
    "addr:full":"1520 N Cahuenga Blvd Suite 7 Los Angeles CA 90028",
    "addr:housenumber":"1520",
    "addr:postcode":"90028",
    "addr:street":"N Cahuenga Blvd Suite 7",
    "iso:country":"US",
    "sg:address":"1520 N Cahuenga Blvd Suite 7",
    "sg:city":"Los Angeles",
    "sg:classifiers":[
        {
            "category":"Fast Food",
            "type":"Food & Drink"
        },
        {
            "category":"Bars & Pubs",
            "type":"Food & Drink"
        }
    ],
    "sg:phone":"+1 323 469 3100",
    "sg:postcode":"90028",
    "sg:province":"CA",
    "sg:tags":[
        "burger",
        "gastropubs"
    ],
    "sg:website":"www.umamiburger.com",
    "wof:name":"Umami Burger",
    "wof:placetype":"venue"
},
  "geometry": {"coordinates":[-118.329089,34.098834],"type":"Point"}
}