{
  "type": "Feature",
  "properties": {
    "addr:full":"1507 Traske Rd Encinitas CA 92024",
    "addr:housenumber":"1507",
    "addr:postcode":"92024",
    "addr:street":"Traske Rd",
    "iso:country":"US",
    "sg:address":"1507 Traske Rd",
    "sg:city":"Encinitas",
    "sg:classifiers":[
        {
            "category":"Organizations",
            "subcategory":"Membership Organization",
            "type":"Services"
        }
    ],
    "sg:phone":"+1 760 632 5411",
    "sg:postcode":"92024",
    "sg:province":"CA",
    "wof:name":"Fsh Society",
    "wof:placetype":"venue"
},
  "geometry": {"coordinates":[-117.25420699999999,33.048282],"type":"Point"}
}