{
  "type": "Feature",
  "properties": {
    "iso:country":"US",
    "sg:address":"2749 Saturn St",
    "sg:city":"Brea",
    "sg:classifiers":[
        {
            "category":"Professional",
            "subcategory":"Engineering",
            "type":"Services"
        }
    ],
    "sg:phone":"+1 562 691 7736",
    "sg:postcode":"92821",
    "sg:province":"CA",
    "sg:tags":[
        "engineer"
    ],
    "sg:website":"www.amtec-eng.com",
    "wof:name":"Amtec Engineering Corp",
    "wof:placetype":"venue"
},
  "geometry": {"coordinates":[-117.857291,33.908874],"type":"Point"}
}