{
  "type": "Feature",
  "properties": {
    "iso:country":"US",
    "sg:address":"650 W Duarte Rd",
    "sg:city":"Arcadia",
    "sg:classifiers":[
        {
            "category":"Insurance",
            "subcategory":"Insurance Agent",
            "type":"Services"
        }
    ],
    "sg:phone":"+1 626 446 8846",
    "sg:postcode":"91007",
    "sg:province":"CA",
    "wof:name":"Wia Marketing Inc",
    "wof:placetype":"venue"
},
  "geometry": {"coordinates":[-118.053338,34.126269],"type":"Point"}
}