{
  "type": "Feature",
  "properties": {
    "iso:country":"US",
    "sg:address":"289 Gold Mine Dr",
    "sg:city":"San Francisco",
    "sg:classifiers":[
        {
            "category":"Building & Trades",
            "subcategory":"Electrical",
            "type":"Services"
        }
    ],
    "sg:phone":"+1 415 824 5100",
    "sg:postcode":"94131",
    "sg:province":"CA",
    "sg:tags":[
        "electrical",
        "contractor"
    ],
    "wof:name":"Electric Connection Inc",
    "wof:placetype":"venue"
},
  "geometry": {"coordinates":[-122.43996799999999,37.742175],"type":"Point"}
}