{
  "type": "Feature",
  "properties": {
    "iso:country":"US",
    "sg:address":"2220 Cedar Street",
    "sg:city":"Berkeley",
    "sg:classifiers":[
        {
            "category":"Health Services",
            "subcategory":"Clinic",
            "type":"Services"
        }
    ],
    "sg:phone":"+1 510 704 8046",
    "sg:postcode":"94709",
    "sg:province":"CA",
    "sg:tags":[
        "counseling",
        "mental"
    ],
    "wof:name":"California Counseling Institute",
    "wof:placetype":"venue"
},
  "geometry": {"coordinates":[-122.26599899999999,37.8787],"type":"Point"}
}