{
  "type": "Feature",
  "properties": {
    "addr:full":"1487 Morgan Rd San Bernardino CA 92407",
    "addr:housenumber":"1487",
    "addr:postcode":"92407",
    "addr:street":"Morgan Rd",
    "iso:country":"US",
    "sg:address":"1487 Morgan Rd",
    "sg:city":"San Bernardino",
    "sg:classifiers":[
        {
            "category":"Building & Trades",
            "subcategory":"Locksmith",
            "type":"Services"
        }
    ],
    "sg:phone":"+1 909 475 3213",
    "sg:postcode":"92407",
    "sg:province":"CA",
    "sg:tags":[
        "key"
    ],
    "wof:name":"Eddie Lock and Key",
    "wof:placetype":"venue"
},
  "geometry": {"coordinates":[-117.321715,34.168413],"type":"Point"}
}