{
  "type": "Feature",
  "properties": {
    "addr:full":"5308 11th Ave Los Angeles CA 90043",
    "addr:housenumber":"5308",
    "addr:postcode":"90043",
    "addr:street":"11Th Ave",
    "iso:country":"US",
    "sg:address":"5308 11th Ave",
    "sg:city":"Los Angeles",
    "sg:classifiers":[
        {
            "category":"Manufacturing",
            "subcategory":"Printing",
            "type":"Manufacturing & Wholesale Goods"
        }
    ],
    "sg:phone":"+1 323 292 8227",
    "sg:postcode":"90043",
    "sg:province":"CA",
    "sg:tags":[
        "publishing"
    ],
    "wof:name":"Heartsung Lura Ball",
    "wof:placetype":"venue"
},
  "geometry": {"coordinates":[-118.329308,33.994136],"type":"Point"}
}