{
  "type": "Feature",
  "properties": {
    "iso:country":"US",
    "sg:address":"3106 Leisure Ct",
    "sg:city":"San Jose",
    "sg:classifiers":[
        {
            "category":"Shopping",
            "subcategory":"Stationery & Office Supplies",
            "type":"Retail Goods"
        }
    ],
    "sg:phone":"+1 408 923 5250",
    "sg:postcode":"95132",
    "sg:province":"CA",
    "sg:tags":[
        "album",
        "scrapbook"
    ],
    "wof:name":"Touching Memories",
    "wof:placetype":"venue"
},
  "geometry": {"coordinates":[-121.851302,37.395871],"type":"Point"}
}