{
  "type": "Feature",
  "properties": {
    "addr:full":"2051 Carousel Dr Hollister CA 95023",
    "addr:housenumber":"2051",
    "addr:postcode":"hollister ca 95023",
    "addr:street":"Carousel Dr",
    "iso:country":"US",
    "sg:address":"2051 Carousel Dr",
    "sg:city":"Hollister",
    "sg:classifiers":[
        {
            "category":"Wholesale",
            "subcategory":"Computers",
            "type":"Manufacturing & Wholesale Goods"
        },
        {
            "category":"Wholesale",
            "subcategory":"Office Equipment",
            "type":"Manufacturing & Wholesale Goods"
        }
    ],
    "sg:phone":"+1 831 630 0190",
    "sg:postcode":"95023",
    "sg:province":"CA",
    "sg:tags":[
        "scanning",
        "code",
        "bar"
    ],
    "wof:name":"Lowery Computer Products Inc",
    "wof:placetype":"venue"
},
  "geometry": {"coordinates":[-121.38822999999999,36.830726],"type":"Point"}
}