{
  "type": "Feature",
  "properties": {
    "addr:full":"20 Arnold Pl Goleta CA 93117",
    "addr:housenumber":"20",
    "addr:postcode":"93117",
    "addr:street":"Arnold Pl",
    "iso:country":"US",
    "sg:address":"20 Arnold Pl",
    "sg:city":"Goleta",
    "sg:classifiers":[
        {
            "category":"Manufacturing",
            "subcategory":"Glass & Minerals",
            "type":"Manufacturing & Wholesale Goods"
        }
    ],
    "sg:phone":"+1 805 964 4410",
    "sg:postcode":"93117",
    "sg:province":"CA",
    "sg:tags":[
        "instrument",
        "scientific",
        "apparatus"
    ],
    "sg:website":"www.dynasen.com",
    "wof:name":"Dynasen Inc",
    "wof:placetype":"venue"
},
  "geometry": {"coordinates":[-119.845963,34.429846],"type":"Point"}
}