{
  "type": "Feature",
  "properties": {
    "addr:full":"11942 Downey Ave Downey CA 90242",
    "addr:housenumber":"11942",
    "addr:postcode":"90242",
    "addr:street":"Downey Ave",
    "iso:country":"US",
    "sg:address":"11942 Downey Ave",
    "sg:city":"Downey",
    "sg:classifiers":[
        {
            "category":"Wholesale",
            "subcategory":"Vending Machines",
            "type":"Manufacturing & Wholesale Goods"
        }
    ],
    "sg:phone":"+1 562 260 6801",
    "sg:postcode":"90242",
    "sg:province":"CA",
    "wof:name":"R Munchies",
    "wof:placetype":"venue"
},
  "geometry": {"coordinates":[-118.139116,33.93146],"type":"Point"}
}