{
  "type": "Feature",
  "properties": {
    "iso:country":"US",
    "sg:address":"138 W Commonwealth Ave",
    "sg:city":"Fullerton",
    "sg:classifiers":[
        {
            "category":"Building & Trades",
            "subcategory":"Locksmith",
            "type":"Services"
        }
    ],
    "sg:phone":"+1 714 252 4230",
    "sg:postcode":"92832",
    "sg:province":"CA",
    "sg:tags":[
        "key"
    ],
    "sg:website":"www.availablelocksmithinc.com/Fu...",
    "wof:name":"AVL Locksmith Fullerton",
    "wof:placetype":"venue"
},
  "geometry": {"coordinates":[-117.925994,33.870285],"type":"Point"}
}