{
  "type": "Feature",
  "properties": {
    "addr:full":"30750 Old Windmill Rd Menifee CA 92584",
    "addr:housenumber":"30750",
    "addr:postcode":"92584",
    "addr:street":"Old Windmill Rd",
    "iso:country":"US",
    "sg:address":"30750 Old Windmill Rd",
    "sg:city":"Menifee",
    "sg:classifiers":[
        {
            "category":"Manufacturing",
            "subcategory":"Wood Products",
            "type":"Manufacturing & Wholesale Goods"
        }
    ],
    "sg:phone":"+1 951 775 9472",
    "sg:postcode":"92584",
    "sg:province":"CA",
    "sg:tags":[
        "millwork-wholesale",
        "millwork",
        "manufacturer"
    ],
    "wof:name":"Cavs Wood Works",
    "wof:placetype":"venue"
},
  "geometry": {"coordinates":[-117.182123,33.673658],"type":"Point"}
}