{
  "type": "Feature",
  "properties": {
    "addr:full":"3309 Pico Blvd Santa Monica CA 90405",
    "addr:housenumber":"3309",
    "addr:postcode":"90405",
    "addr:street":"Pico Blvd",
    "iso:country":"US",
    "sg:address":"3309 Pico Blvd",
    "sg:city":"Santa Monica",
    "sg:classifiers":[
        {
            "category":"Building & Trades",
            "subcategory":"Construction",
            "type":"Services"
        }
    ],
    "sg:phone":"+1 310 453 4776",
    "sg:postcode":"90405",
    "sg:province":"CA",
    "sg:tags":[
        "residential",
        "designer"
    ],
    "wof:name":"Brian Wesley & Assoc",
    "wof:placetype":"venue"
},
  "geometry": {"coordinates":[-118.454345,34.027401],"type":"Point"}
}