{
  "type": "Feature",
  "properties": {
    "iso:country":"US",
    "sg:address":"263 Vineyard Blvd",
    "sg:city":"Morgan Hill",
    "sg:classifiers":[
        {
            "category":"Professional",
            "type":"Services"
        }
    ],
    "sg:phone":"+1 408 799 1294",
    "sg:postcode":"95037",
    "sg:province":"CA",
    "sg:tags":[
        "establishment"
    ],
    "wof:name":"Finishing Touch By Diana",
    "wof:placetype":"venue"
},
  "geometry": {"coordinates":[-121.641329,37.110051],"type":"Point"}
}