{
  "type": "Feature",
  "properties": {
    "addr:full":"3295 Donna Dr Carlsbad CA 92008",
    "addr:housenumber":"3295",
    "addr:postcode":"92008",
    "addr:street":"Donna Dr",
    "iso:country":"US",
    "sg:address":"3295 Donna Dr",
    "sg:city":"Carlsbad",
    "sg:classifiers":[
        {
            "category":"Banks & Credit Unions",
            "subcategory":"Financial Services",
            "type":"Services"
        }
    ],
    "sg:phone":"+1 760 434 3338",
    "sg:postcode":"92008",
    "sg:province":"CA",
    "sg:tags":[
        "broker",
        "mortgage"
    ],
    "wof:name":"Solutions Real Estate & Mortgage Co",
    "wof:placetype":"venue"
},
  "geometry": {"coordinates":[-117.328003,33.169201],"type":"Point"}
}