{
  "type": "Feature",
  "properties": {
    "addr:full":"3800 W Century Blvd Inglewood CA 90303",
    "addr:housenumber":"3800",
    "addr:postcode":"90303",
    "addr:street":"W Century Blvd",
    "iso:country":"US",
    "sg:address":"3800 W Century Blvd",
    "sg:city":"Inglewood",
    "sg:classifiers":[
        {
            "category":"Freight",
            "type":"Transportation"
        }
    ],
    "sg:phone":"+1 310 671 1669",
    "sg:postcode":"90303",
    "sg:province":"CA",
    "sg:tags":[
        "arrangement"
    ],
    "wof:name":"Muller Shipping Corp",
    "wof:placetype":"venue"
},
  "geometry": {"coordinates":[-118.33982399999999,33.945459],"type":"Point"}
}