{
  "type": "Feature",
  "properties": {
    "iso:country":"US",
    "sg:address":"172 Wikiup Dr",
    "sg:city":"Santa Rosa",
    "sg:classifiers":[
        {
            "category":"Personal",
            "subcategory":"Beauty Salon",
            "type":"Services"
        }
    ],
    "sg:phone":"+1 707 523 3025",
    "sg:postcode":"95403",
    "sg:province":"CA",
    "wof:name":"Next Level Hair Designs-Hazel",
    "wof:placetype":"venue"
},
  "geometry": {"coordinates":[-122.758263,38.508175],"type":"Point"}
}