{
  "type": "Feature",
  "properties": {
    "iso:country":"US",
    "sg:address":"12909 Victory Blvd",
    "sg:city":"Los Angeles",
    "sg:classifiers":[
        {
            "category":"Restaurant",
            "type":"Food & Drink"
        }
    ],
    "sg:phone":"+1 818 985 0611",
    "sg:postcode":"91606",
    "sg:province":"CA",
    "sg:tags":[
        "kosher"
    ],
    "sg:website":"www.bramispizza.com/",
    "wof:name":"Brami's Kosher Pizza North Hollywood",
    "wof:placetype":"venue"
},
  "geometry": {"coordinates":[-118.414345,34.186687],"type":"Point"}
}