{
  "type": "Feature",
  "properties": {
    "iso:country":"US",
    "sg:address":"13908 la Forge St",
    "sg:city":"Whittier",
    "sg:classifiers":[
        {
            "category":"Professional",
            "subcategory":"Engineering",
            "type":"Services"
        }
    ],
    "sg:phone":"+1 626 890 9626",
    "sg:postcode":"90605",
    "sg:province":"CA",
    "sg:tags":[
        "refrigeration",
        "engineer"
    ],
    "wof:name":"Mechanical Alliance Inc.",
    "wof:placetype":"venue"
},
  "geometry": {"coordinates":[-118.028074,33.953991],"type":"Point"}
}