{
  "type": "Feature",
  "properties": {
    "addr:full":"3760 Airport Rd Paso Robles CA 93446",
    "addr:housenumber":"3760",
    "addr:postcode":"93446",
    "addr:street":"Airport Rd",
    "iso:country":"US",
    "sg:address":"3760 Airport Rd",
    "sg:city":"Paso Robles",
    "sg:classifiers":[
        {
            "category":"Wholesale",
            "subcategory":"Machinery & Supplies",
            "type":"Manufacturing & Wholesale Goods"
        }
    ],
    "sg:phone":"+1 805 227 4482",
    "sg:postcode":"93446",
    "sg:province":"CA",
    "sg:tags":[
        "truck"
    ],
    "wof:name":"Quality Custom Svc",
    "wof:placetype":"venue"
},
  "geometry": {"coordinates":[-120.640907,35.656982],"type":"Point"}
}