{
  "type": "Feature",
  "properties": {
    "addr:full":"6101 Will Rogers Street Los Angeles CA 90045",
    "addr:housenumber":"6101",
    "addr:postcode":"90045",
    "addr:street":"Will Rogers Street",
    "iso:country":"US",
    "sg:address":"6101 Will Rogers Street",
    "sg:city":"Los Angeles",
    "sg:classifiers":[
        {
            "category":"Building & Trades",
            "subcategory":"Cleaning & Sanitation",
            "type":"Services"
        }
    ],
    "sg:phone":"+1 310 645 3463",
    "sg:postcode":"90045",
    "sg:province":"CA",
    "sg:tags":[
        "carpet"
    ],
    "wof:name":"Kentwood Carpet Care",
    "wof:placetype":"venue"
},
  "geometry": {"coordinates":[-118.39121799999999,33.955524],"type":"Point"}
}