{
  "type": "Feature",
  "properties": {
    "iso:country":"US",
    "sg:address":"1894 Olive St",
    "sg:city":"Highland",
    "sg:classifiers":[
        {
            "category":"Organizations",
            "subcategory":"Religious Organization",
            "type":"Services"
        }
    ],
    "sg:phone":"+1 909 425 9374",
    "sg:postcode":"92346",
    "sg:province":"CA",
    "wof:name":"Mind Of Christ Ministries",
    "wof:placetype":"venue"
},
  "geometry": {"coordinates":[-117.221362,34.12913],"type":"Point"}
}