{
  "type": "Feature",
  "properties": {
    "addr:full":"3787 Transport St Ste A2 Ventura CA 93003",
    "addr:housenumber":"3787",
    "addr:postcode":"93003",
    "addr:street":"Transport St Ste A2",
    "iso:country":"US",
    "sg:address":"3787 Transport St Ste A2",
    "sg:city":"Ventura",
    "sg:classifiers":[
        {
            "category":"Autos & Motor Vehicles",
            "subcategory":"Automobile Sales",
            "type":"Retail Goods"
        }
    ],
    "sg:phone":"+1 805 644 7795",
    "sg:postcode":"93003",
    "sg:province":"CA",
    "sg:tags":[
        "dealers-used",
        "car",
        "used",
        "cars-wholesale",
        "new"
    ],
    "wof:name":"Reliable Auto Sales",
    "wof:placetype":"venue"
},
  "geometry": {"coordinates":[-119.244107,34.257579],"type":"Point"}
}