{
  "type": "Feature",
  "properties": {
    "addr:full":"970 N Broadway Los Angeles CA 90012",
    "addr:housenumber":"970",
    "addr:postcode":"90012",
    "addr:street":"N Broadway",
    "iso:country":"US",
    "sg:address":"970 N Broadway",
    "sg:city":"Los Angeles",
    "sg:classifiers":[
        {
            "category":"Professional",
            "subcategory":"Management & Consulting",
            "type":"Services"
        }
    ],
    "sg:phone":"+1 213 626 6857",
    "sg:postcode":"90012",
    "sg:province":"CA",
    "sg:tags":[
        "engineer"
    ],
    "wof:name":"Hsin Hing Business Svc",
    "wof:placetype":"venue"
},
  "geometry": {"coordinates":[-118.235838,34.06663],"type":"Point"}
}