{
  "type": "Feature",
  "properties": {
    "iso:country":"US",
    "sg:address":"1241 W Brooks St",
    "sg:city":"Ontario",
    "sg:classifiers":[
        {
            "category":"Wholesale",
            "subcategory":"Electrical",
            "type":"Manufacturing & Wholesale Goods"
        }
    ],
    "sg:phone":"+1 909 983 2654",
    "sg:postcode":"91762",
    "sg:province":"CA",
    "sg:tags":[
        "equipment",
        "electric",
        "supply"
    ],
    "wof:name":"Consolidated Electrical Distrs",
    "wof:placetype":"venue"
},
  "geometry": {"coordinates":[-117.673866,34.061884],"type":"Point"}
}