{
  "type": "Feature",
  "properties": {
    "addr:full":"426 Dallas Dr Campbell CA 95008",
    "addr:housenumber":"426",
    "addr:postcode":"95008",
    "addr:street":"Dallas Dr",
    "iso:country":"US",
    "sg:address":"426 Dallas Dr",
    "sg:city":"Campbell",
    "sg:classifiers":[
        {
            "category":"Recreation",
            "type":"Entertainment"
        }
    ],
    "sg:phone":"+1 408 371 0595",
    "sg:postcode":"95008",
    "sg:province":"CA",
    "sg:tags":[
        "mfg"
    ],
    "wof:name":"Loom",
    "wof:placetype":"venue"
},
  "geometry": {"coordinates":[-121.94231600000001,37.273771],"type":"Point"}
}