{
  "type": "Feature",
  "properties": {
    "iso:country":"US",
    "sg:address":"1685 Brandywine Ave",
    "sg:city":"Chula Vista",
    "sg:classifiers":[
        {
            "category":"Manufacturing",
            "subcategory":"Metals",
            "type":"Manufacturing & Wholesale Goods"
        }
    ],
    "sg:phone":"+1 619 421 1355",
    "sg:postcode":"91911",
    "sg:province":"CA",
    "sg:tags":[
        "joint",
        "expansion"
    ],
    "sg:website":"www.hyspan.com",
    "wof:name":"Hyspan Precision Products",
    "wof:placetype":"venue"
},
  "geometry": {"coordinates":[-117.029369,32.596737],"type":"Point"}
}