{
  "type": "Feature",
  "properties": {
    "addr:full":"8610 Brentwood Blvd Brentwood CA 94513",
    "addr:housenumber":"8610",
    "addr:postcode":"ca 94513",
    "addr:street":"Brentwood Blvd",
    "iso:country":"US",
    "sg:address":"8610 Brentwood Blvd",
    "sg:city":"Brentwood",
    "sg:classifiers":[
        {
            "category":"Restaurant",
            "type":"Food & Drink"
        }
    ],
    "sg:phone":"+1 925 513 8871",
    "sg:postcode":"94513",
    "sg:province":"CA",
    "sg:tags":[
        "chinese"
    ],
    "wof:name":"China Villa Restaurant",
    "wof:placetype":"venue"
},
  "geometry": {"coordinates":[-121.691762,37.926859],"type":"Point"}
}