{
  "type": "Feature",
  "properties": {
    "iso:country":"US",
    "sg:address":"215 Riverside Dr",
    "sg:city":"Cloverdale",
    "sg:classifiers":[
        {
            "category":"Shopping",
            "subcategory":"Gifts & Souvenirs",
            "type":"Retail Goods"
        }
    ],
    "sg:phone":"+1 707 894 8515",
    "sg:postcode":"95425",
    "sg:province":"CA",
    "sg:tags":[
        "party",
        "supply"
    ],
    "wof:name":"Party Beginnings",
    "wof:placetype":"venue"
},
  "geometry": {"coordinates":[-123.009075,38.827492],"type":"Point"}
}