{
  "type": "Feature",
  "properties": {
    "iso:country":"US",
    "sg:address":"1418 W Redondo Beach Blvd",
    "sg:city":"Gardena",
    "sg:classifiers":[
        {
            "category":"Shopping",
            "subcategory":"Catalog Store",
            "type":"Retail Goods"
        }
    ],
    "sg:phone":"+1 310 769 0100",
    "sg:postcode":"90247",
    "sg:province":"CA",
    "sg:tags":[
        "mail",
        "house"
    ],
    "wof:name":"Jsm Usa Inc",
    "wof:placetype":"venue"
},
  "geometry": {"coordinates":[-118.30174,33.890833],"type":"Point"}
}