{
  "type": "Feature",
  "properties": {
    "addr:full":"282870 Spenceville Rd Wheatland CA 95692",
    "addr:housenumber":"282870",
    "addr:postcode":"95692",
    "addr:street":"Spenceville Rd",
    "iso:country":"US",
    "sg:address":"282870 Spenceville Rd",
    "sg:city":"Wheatland",
    "sg:classifiers":[
        {
            "category":"Farming",
            "subcategory":"Livestock Farm",
            "type":"Manufacturing & Wholesale Goods"
        },
        {
            "category":"Farming",
            "subcategory":"Farm & Veterinary Services",
            "type":"Manufacturing & Wholesale Goods"
        }
    ],
    "sg:phone":"+1 530 633 2510",
    "sg:postcode":"95692",
    "sg:province":"CA",
    "sg:tags":[
        "breeder"
    ],
    "wof:name":"Browne Cattle Co",
    "wof:placetype":"venue"
},
  "geometry": {"coordinates":[-121.30806699999999,39.111069],"type":"Point"}
}