{
  "type": "Feature",
  "properties": {
    "iso:country":"US",
    "sg:address":"4135 Northgate Blvd",
    "sg:city":"Sacramento",
    "sg:classifiers":[
        {
            "category":"Communications",
            "subcategory":"Radio Station",
            "type":"Services"
        }
    ],
    "sg:phone":"+1 916 641 8191",
    "sg:postcode":"95834",
    "sg:province":"CA",
    "sg:tags":[
        "broadcast",
        "broadcasting"
    ],
    "sg:website":"http://www.familyradio.com",
    "wof:name":"Keber 1210 Am",
    "wof:placetype":"venue"
},
  "geometry": {"coordinates":[-121.47676199999999,38.644032],"type":"Point"}
}