{
  "type": "Feature",
  "properties": {
    "addr:full":"29040 Portola Pkwy Lake Forest CA 92630",
    "addr:housenumber":"29040",
    "addr:postcode":"92630",
    "addr:street":"Portola Pkwy",
    "iso:country":"US",
    "sg:address":"29040 Portola Pkwy",
    "sg:city":"Lake Forest",
    "sg:classifiers":[
        {
            "category":"Retail",
            "subcategory":"Veterinary Services",
            "type":"Services"
        },
        {
            "category":"Retail",
            "subcategory":"Pet Boarding",
            "type":"Services"
        }
    ],
    "sg:phone":"+1 949 380 1255",
    "sg:postcode":"92630",
    "sg:province":"CA",
    "sg:tags":[
        "veterinarian",
        "boarding/pet",
        "sitting"
    ],
    "wof:name":"Foothill Animal Hospital",
    "wof:placetype":"venue"
},
  "geometry": {"coordinates":[-117.654332,33.662564],"type":"Point"}
}