{
  "type": "Feature",
  "properties": {
    "iso:country":"US",
    "sg:address":"9506 Main St",
    "sg:city":"Plymouth",
    "sg:classifiers":[
        {
            "category":"Shopping",
            "subcategory":"Computers & Home Electronics",
            "type":"Retail Goods"
        }
    ],
    "sg:phone":"+1 209 245 3012",
    "sg:postcode":"95669",
    "sg:province":"CA",
    "sg:tags":[
        "game",
        "video"
    ],
    "wof:name":"Movies Popcorn & More",
    "wof:placetype":"venue"
},
  "geometry": {"coordinates":[-120.844962,38.481854],"type":"Point"}
}