{
  "type": "Feature",
  "properties": {
    "addr:full":"77849 Cll Arroba La Quinta CA 92253",
    "addr:housenumber":"77849",
    "addr:postcode":"92253",
    "addr:street":"Cll Arroba",
    "iso:country":"US",
    "sg:address":"77849 Cll Arroba",
    "sg:city":"La Quinta",
    "sg:classifiers":[
        {
            "category":"Real Estate",
            "subcategory":"Real Estate Agent",
            "type":"Services"
        }
    ],
    "sg:phone":"+1 760 771 6661",
    "sg:postcode":"92253",
    "sg:province":"CA",
    "sg:tags":[
        "inspection"
    ],
    "wof:name":"Desert Empire Home Inspection",
    "wof:placetype":"venue"
},
  "geometry": {"coordinates":[-116.30664400000001,33.65791],"type":"Point"}
}