{
  "type": "Feature",
  "properties": {
    "addr:full":"2025 Otoole Ave San Jose CA 95131",
    "addr:housenumber":"2025",
    "addr:postcode":"95131",
    "addr:street":"Otoole Ave",
    "iso:country":"US",
    "sg:address":"2025 Otoole Ave",
    "sg:city":"San Jose",
    "sg:classifiers":[
        {
            "category":"Professional",
            "subcategory":"Computer Services",
            "type":"Services"
        }
    ],
    "sg:phone":"+1 408 435 7372",
    "sg:postcode":"95131",
    "sg:province":"CA",
    "sg:tags":[
        "repair"
    ],
    "wof:name":"New Concepts Repair & Manufacturing Services",
    "wof:placetype":"venue"
},
  "geometry": {"coordinates":[-121.906094,37.387351],"type":"Point"}
}