{
  "type": "Feature",
  "properties": {
    "iso:country":"US",
    "sg:address":"9560 Topanga Canyon Blvd",
    "sg:city":"Chatsworth",
    "sg:classifiers":[
        {
            "category":"Professional",
            "subcategory":"Accounting & Tax Preparation",
            "type":"Services"
        }
    ],
    "sg:phone":"+1 818 998 1302",
    "sg:postcode":"91311",
    "sg:province":"CA",
    "sg:tags":[
        "accountant"
    ],
    "wof:name":"Michael J Horowitz CPA",
    "wof:placetype":"venue"
},
  "geometry": {"coordinates":[-118.606469,34.243181],"type":"Point"}
}