{
  "type": "Feature",
  "properties": {
    "iso:country":"US",
    "sg:address":"1058 Dell Ave",
    "sg:city":"Campbell",
    "sg:classifiers":[
        {
            "category":"Building & Trades",
            "subcategory":"Construction",
            "type":"Services"
        }
    ],
    "sg:phone":"+1 408 378 7793",
    "sg:postcode":"95008",
    "sg:province":"CA",
    "sg:tags":[
        "masonry"
    ],
    "wof:name":"Jones Masonry",
    "wof:placetype":"venue"
},
  "geometry": {"coordinates":[-121.952622,37.269705],"type":"Point"}
}