{
  "type": "Feature",
  "properties": {
    "addr:full":"1755 N Valley Center Ave Glendora CA 91740",
    "addr:housenumber":"1755",
    "addr:postcode":"91740",
    "addr:street":"N Valley Center Ave",
    "iso:country":"US",
    "sg:address":"1755 N Valley Center Ave",
    "sg:city":"Glendora",
    "sg:classifiers":[
        {
            "category":"Professional",
            "subcategory":"Business Services",
            "type":"Services"
        }
    ],
    "sg:phone":"+1 909 305 9788",
    "sg:postcode":"91740",
    "sg:province":"CA",
    "sg:tags":[
        "packaging"
    ],
    "wof:name":"Valley Center Shipping",
    "wof:placetype":"venue"
},
  "geometry": {"coordinates":[-117.837711,34.107385],"type":"Point"}
}