{
  "type": "Feature",
  "properties": {
    "iso:country":"US",
    "sg:address":"1220 U St",
    "sg:city":"Rio Linda",
    "sg:classifiers":[
        {
            "category":"Wholesale",
            "subcategory":"Home Furnishings",
            "type":"Manufacturing & Wholesale Goods"
        },
        {
            "category":"Home & Garden",
            "subcategory":"Home Furnishings",
            "type":"Retail Goods"
        }
    ],
    "sg:phone":"+1 916 991 1353",
    "sg:postcode":"95673",
    "sg:province":"CA",
    "sg:tags":[
        "installation",
        "drapery"
    ],
    "wof:name":"Precision Window Coverings",
    "wof:placetype":"venue"
},
  "geometry": {"coordinates":[-121.434052,38.704768],"type":"Point"}
}