{
  "type": "Feature",
  "properties": {
    "iso:country":"US",
    "sg:address":"500 N Brand Blvd Ste 920",
    "sg:city":"Glendale",
    "sg:classifiers":[
        {
            "category":"Professional",
            "subcategory":"Lawyer & Legal Services",
            "type":"Services"
        }
    ],
    "sg:phone":"+1 818 507 8100",
    "sg:postcode":"91203",
    "sg:province":"CA",
    "wof:name":"Montes Raul M Atty",
    "wof:placetype":"venue"
},
  "geometry": {"coordinates":[-118.254997,34.153],"type":"Point"}
}