{
  "type": "Feature",
  "properties": {
    "iso:country":"US",
    "sg:address":"220 Main St",
    "sg:city":"Los Altos",
    "sg:classifiers":[
        {
            "category":"Building & Trades",
            "subcategory":"Construction",
            "type":"Services"
        }
    ],
    "sg:phone":"+1 650 941 5119",
    "sg:postcode":"94022",
    "sg:province":"CA",
    "sg:tags":[
        "builder",
        "operative",
        "contractor"
    ],
    "wof:name":"Gordon Snedigar Construction",
    "wof:placetype":"venue"
},
  "geometry": {"coordinates":[-122.116505,37.378503],"type":"Point"}
}