{
  "type": "Feature",
  "properties": {
    "addr:full":"1613 W 2nd St Pomona CA 91766",
    "addr:housenumber":"1613",
    "addr:postcode":"91766",
    "addr:street":"W 2Nd St",
    "iso:country":"US",
    "sg:address":"1613 W 2nd St",
    "sg:city":"Pomona",
    "sg:classifiers":[
        {
            "category":"Manufacturing",
            "subcategory":"Apparel",
            "type":"Manufacturing & Wholesale Goods"
        }
    ],
    "sg:phone":"+1 909 629 8900",
    "sg:postcode":"91766",
    "sg:province":"CA",
    "sg:tags":[
        "clothing-men's-wholesale",
        "manufacturer"
    ],
    "wof:name":"Maxxsel Apparel Inc",
    "wof:placetype":"venue"
},
  "geometry": {"coordinates":[-117.774298,34.057196],"type":"Point"}
}