{
  "type": "Feature",
  "properties": {
    "iso:country":"US",
    "sg:address":"5439 Auburn Blvd",
    "sg:city":"Sacramento",
    "sg:classifiers":[
        {
            "category":"Home & Garden",
            "subcategory":"Hardware",
            "type":"Retail Goods"
        }
    ],
    "sg:phone":"+1 916 344 6297",
    "sg:postcode":"95841",
    "sg:province":"CA",
    "sg:tags":[
        "store"
    ],
    "sg:website":"www.harborfreight.com",
    "wof:name":"Harbor Freight Tools",
    "wof:placetype":"venue"
},
  "geometry": {"coordinates":[-121.338024,38.669009],"type":"Point"}
}