{
  "type": "Feature",
  "properties": {
    "iso:country":"US",
    "sg:address":"12000 Main St",
    "sg:city":"Lamont",
    "sg:classifiers":[
        {
            "category":"Wholesale",
            "subcategory":"Fruits & Vegetables",
            "type":"Manufacturing & Wholesale Goods"
        }
    ],
    "sg:phone":"+1 661 845 2315",
    "sg:postcode":"93241",
    "sg:province":"CA",
    "sg:tags":[
        "shipper"
    ],
    "wof:name":"Cal Organic Farms",
    "wof:placetype":"venue"
},
  "geometry": {"coordinates":[-118.914416,35.248294],"type":"Point"}
}