{
  "type": "Feature",
  "properties": {
    "addr:full":"3167 E Millbrae Ave Fresno CA 93710",
    "addr:housenumber":"3167",
    "addr:postcode":"93710",
    "addr:street":"E Millbrae Ave",
    "iso:country":"US",
    "sg:address":"3167 E Millbrae Ave",
    "sg:city":"Fresno",
    "sg:classifiers":[
        {
            "category":"Building & Trades",
            "subcategory":"Landscaping Services",
            "type":"Services"
        }
    ],
    "sg:phone":"+1 559 299 2031",
    "sg:postcode":"93710",
    "sg:province":"CA",
    "sg:tags":[
        "landscape",
        "contractor"
    ],
    "wof:name":"Gateway Landscapes",
    "wof:placetype":"venue"
},
  "geometry": {"coordinates":[-119.73234600000001,36.83689],"type":"Point"}
}