{
  "type": "Feature",
  "properties": {
    "iso:country":"US",
    "sg:address":"5119 Blue Bell Ct",
    "sg:city":"Fort Irwin",
    "sg:classifiers":[
        {
            "category":"Personal",
            "type":"Services"
        }
    ],
    "sg:phone":"+1 760 386 0933",
    "sg:postcode":"92310",
    "sg:province":"CA",
    "sg:tags":[
        "babysitting"
    ],
    "wof:name":"Arivizu  Francy",
    "wof:placetype":"venue"
},
  "geometry": {"coordinates":[-116.706164,35.267777],"type":"Point"}
}