{
  "type": "Feature",
  "properties": {
    "iso:country":"US",
    "sg:address":"430 Magnolia Ave",
    "sg:city":"Petaluma",
    "sg:classifiers":[
        {
            "category":"Real Estate",
            "subcategory":"Developer",
            "type":"Services"
        }
    ],
    "sg:phone":"+1 707 762 6683",
    "sg:postcode":"94952",
    "sg:province":"CA",
    "sg:tags":[
        "cemetery"
    ],
    "wof:name":"Cypress Hill Memorial Park",
    "wof:placetype":"venue"
},
  "geometry": {"coordinates":[-122.6541,38.245678],"type":"Point"}
}