{
  "type": "Feature",
  "properties": {
    "addr:full":"2338 Alisal Rd Salinas CA 93908",
    "addr:postcode":"2338;93908",
    "addr:street":"Alisal Rd",
    "iso:country":"US",
    "sg:address":"2338 Alisal Rd",
    "sg:city":"Salinas",
    "sg:classifiers":[
        {
            "category":"Farming",
            "subcategory":"Nursery",
            "type":"Manufacturing & Wholesale Goods"
        }
    ],
    "sg:phone":"+1 831 757 3730",
    "sg:postcode":"93908",
    "sg:province":"CA",
    "sg:tags":[
        "ornamental"
    ],
    "wof:name":"Alisal Greenhouse Inc",
    "wof:placetype":"venue"
},
  "geometry": {"coordinates":[-121.545751,36.632123],"type":"Point"}
}