{
  "type": "Feature",
  "properties": {
    "iso:country":"US",
    "sg:address":"4155 Arbolado Dr",
    "sg:city":"Walnut Creek",
    "sg:classifiers":[
        {
            "category":"Professional",
            "subcategory":"Management & Consulting",
            "type":"Services"
        }
    ],
    "sg:phone":"+1 925 890 9714",
    "sg:postcode":"94598",
    "sg:province":"CA",
    "sg:tags":[
        "business"
    ],
    "wof:name":"Deyoung Envmtl Consulting",
    "wof:placetype":"venue"
},
  "geometry": {"coordinates":[-121.990551,37.915568],"type":"Point"}
}