{
  "type": "Feature",
  "properties": {
    "addr:full":"1800 Fruitdale Avenue San Jose CA 95128",
    "addr:housenumber":"1800",
    "addr:postcode":"95128",
    "addr:street":"Fruitdale Avenue",
    "iso:country":"US",
    "sg:address":"1800 Fruitdale Avenue",
    "sg:city":"San Jose",
    "sg:classifiers":[
        {
            "category":"Sports & Exercise",
            "subcategory":"Sports Center",
            "type":"Entertainment"
        }
    ],
    "sg:phone":"+1 408 292 2935",
    "sg:postcode":"95128",
    "sg:province":"CA",
    "sg:tags":[
        "amateur",
        "team"
    ],
    "sg:website":"www.campbellusd.k12.ca.us",
    "wof:name":"San Jose City of",
    "wof:placetype":"venue"
},
  "geometry": {"coordinates":[-121.92433,37.310657],"type":"Point"}
}