{
  "type": "Feature",
  "properties": {
    "addr:full":"641 N Palm St La Habra CA 90631",
    "addr:housenumber":"641",
    "addr:postcode":"90631",
    "addr:street":"N Palm St",
    "iso:country":"US",
    "sg:address":"641 N Palm St",
    "sg:city":"La Habra",
    "sg:classifiers":[
        {
            "category":"Building & Trades",
            "subcategory":"Construction",
            "type":"Services"
        }
    ],
    "sg:phone":"+1 562 697 1300",
    "sg:postcode":"90631",
    "sg:province":"CA",
    "sg:tags":[
        "woodworker"
    ],
    "wof:name":"Lifestyle Woodworks",
    "wof:placetype":"venue"
},
  "geometry": {"coordinates":[-117.924413,33.938318],"type":"Point"}
}