{
  "type": "Feature",
  "properties": {
    "addr:full":"13013 Los Nietos Rd Santa Fe Springs CA 90670",
    "addr:housenumber":"13013",
    "addr:postcode":"90670",
    "addr:street":"Los Nietos Rd",
    "iso:country":"US",
    "sg:address":"13013 Los Nietos Rd",
    "sg:city":"Santa Fe Springs",
    "sg:classifiers":[
        {
            "category":"Manufacturing",
            "subcategory":"Retail Goods",
            "type":"Manufacturing & Wholesale Goods"
        }
    ],
    "sg:phone":"+1 562 944 1544",
    "sg:postcode":"90670",
    "sg:province":"CA",
    "sg:tags":[
        "manufacturer"
    ],
    "sg:website":"www.ranchhousedoors.com",
    "wof:name":"Ranch House Doors",
    "wof:placetype":"venue"
},
  "geometry": {"coordinates":[-118.054368,33.945869],"type":"Point"}
}