{
  "type": "Feature",
  "properties": {
    "addr:full":"29612 Wickerd Rd Menifee CA 92584",
    "addr:housenumber":"29612",
    "addr:postcode":"92584",
    "addr:street":"Wickerd Rd",
    "iso:country":"US",
    "sg:address":"29612 Wickerd Rd",
    "sg:city":"Menifee",
    "sg:classifiers":[
        {
            "category":"Building & Trades",
            "subcategory":"Construction",
            "type":"Services"
        }
    ],
    "sg:phone":"+1 714 533 4000",
    "sg:postcode":"92584",
    "sg:province":"CA",
    "sg:tags":[
        "concrete",
        "pumping"
    ],
    "wof:name":"E Z Way Concrete Pumping Svc",
    "wof:placetype":"venue"
},
  "geometry": {"coordinates":[-117.145275,33.649329],"type":"Point"}
}