{
  "type": "Feature",
  "properties": {
    "iso:country":"US",
    "sg:address":"344 E Morton Ave",
    "sg:city":"Porterville",
    "sg:classifiers":[
        {
            "category":"Organizations",
            "subcategory":"Religious Organization",
            "type":"Services"
        }
    ],
    "sg:phone":"+1 559 782 0130",
    "sg:postcode":"93257",
    "sg:province":"CA",
    "sg:tags":[
        "church"
    ],
    "sg:website":"www.presbychurch.org",
    "wof:name":"Foothill Community Presbytrn",
    "wof:placetype":"venue"
},
  "geometry": {"coordinates":[-119.008783,36.073104],"type":"Point"}
}