{
  "type": "Feature",
  "properties": {
    "iso:country":"US",
    "sg:address":"4075 Mowry Ave",
    "sg:city":"Fremont",
    "sg:classifiers":[
        {
            "category":"Wholesale",
            "subcategory":"Home Furnishings",
            "type":"Manufacturing & Wholesale Goods"
        }
    ],
    "sg:phone":"+1 510 795 2727",
    "sg:postcode":"94538",
    "sg:province":"CA",
    "sg:tags":[
        "dish",
        "soap"
    ],
    "wof:name":"Designer Soap Dish & Deco",
    "wof:placetype":"venue"
},
  "geometry": {"coordinates":[-121.988596,37.548607],"type":"Point"}
}