{
  "type": "Feature",
  "properties": {
    "iso:country":"US",
    "sg:address":"568 E El Camino Real",
    "sg:city":"Sunnyvale",
    "sg:classifiers":[
        {
            "category":"Restaurant",
            "type":"Food & Drink"
        },
        {
            "category":"Food & Beverages",
            "subcategory":"Ethnic Foods",
            "type":"Retail Goods"
        }
    ],
    "sg:phone":"+1 408 738 4996",
    "sg:postcode":"94087",
    "sg:province":"CA",
    "sg:tags":[
        "soul",
        "barbeque"
    ],
    "sg:website":"www.hbutlersbbq.com",
    "wof:name":"H. Butler's BBQ",
    "wof:placetype":"venue"
},
  "geometry": {"coordinates":[-122.025362,37.361944],"type":"Point"}
}