{
  "type": "Feature",
  "properties": {
    "addr:full":"4812 Dunman Ave Woodland Hills CA 91364",
    "addr:postcode":"4812;91364",
    "addr:street":"Dunman Ave",
    "iso:country":"US",
    "sg:address":"4812 Dunman Ave",
    "sg:city":"Woodland Hills",
    "sg:classifiers":[
        {
            "category":"Professional",
            "subcategory":"Lawyer & Legal Services",
            "type":"Services"
        }
    ],
    "sg:phone":"+1 818 224 3517",
    "sg:postcode":"91364",
    "sg:province":"CA",
    "wof:name":"Valley Industrial Products",
    "wof:placetype":"venue"
},
  "geometry": {"coordinates":[-118.627095,34.157794],"type":"Point"}
}