{
  "type": "Feature",
  "properties": {
    "addr:full":"7214 Melrose Ave Los Angeles CA 90046",
    "addr:housenumber":"7214",
    "addr:postcode":"90046",
    "addr:street":"Melrose Ave",
    "iso:country":"US",
    "sg:address":"7214 Melrose Ave",
    "sg:city":"Los Angeles",
    "sg:classifiers":[
        {
            "category":"Communications",
            "subcategory":"Film & Video Production",
            "type":"Services"
        }
    ],
    "sg:phone":"+1 323 938 8080",
    "sg:postcode":"90046",
    "sg:province":"CA",
    "sg:tags":[
        "motion",
        "picture",
        "studio",
        "producer"
    ],
    "sg:website":"www.filmsyndicate.com",
    "wof:name":"Film Syndicate Inc",
    "wof:placetype":"venue"
},
  "geometry": {"coordinates":[-118.347143,34.083421],"type":"Point"}
}