{
  "type": "Feature",
  "properties": {
    "iso:country":"US",
    "sg:address":"28 Carson",
    "sg:city":"Irvine",
    "sg:classifiers":[
        {
            "category":"Social Services",
            "subcategory":"Child Care",
            "type":"Services"
        },
        {
            "category":"Education",
            "subcategory":"Preschool",
            "type":"Public Place"
        },
        {
            "category":"Education",
            "subcategory":"School",
            "type":"Public Place"
        }
    ],
    "sg:phone":"+1 949 651 0224",
    "sg:postcode":"92620",
    "sg:province":"CA",
    "sg:tags":[
        "elementary",
        "day"
    ],
    "wof:name":"Rainbow Rising-Northwood",
    "wof:placetype":"venue"
},
  "geometry": {"coordinates":[-117.769667,33.705535],"type":"Point"}
}