{
  "type": "Feature",
  "properties": {
    "addr:full":"100 Drumm St San Francisco CA 94111",
    "addr:housenumber":"100",
    "addr:postcode":"94111",
    "addr:street":"Drumm St",
    "iso:country":"US",
    "sg:address":"100 Drumm St",
    "sg:city":"San Francisco",
    "sg:classifiers":[
        {
            "category":"Restaurant",
            "type":"Food & Drink"
        }
    ],
    "sg:phone":"+1 415 318 1800",
    "sg:postcode":"94111",
    "sg:province":"CA",
    "sg:tags":[
        "sandwich"
    ],
    "sg:website":"www.birleys.com",
    "wof:name":"Birley Sandwiches",
    "wof:placetype":"venue"
},
  "geometry": {"coordinates":[-122.39660000000001,37.794653],"type":"Point"}
}