{
  "type": "Feature",
  "properties": {
    "addr:full":"1544 Newell Ave Walnut Creek CA 94595",
    "addr:housenumber":"1544",
    "addr:postcode":"94595",
    "addr:street":"Newell Ave",
    "iso:country":"US",
    "sg:address":"1544 Newell Ave",
    "sg:city":"Walnut Creek",
    "sg:classifiers":[
        {
            "category":"Food & Beverages",
            "subcategory":"Bakery",
            "type":"Retail Goods"
        }
    ],
    "sg:phone":"+1 925 256 1137",
    "sg:postcode":"94595",
    "sg:province":"CA",
    "sg:tags":[
        "cookie",
        "cracker"
    ],
    "wof:name":"Cookies By Design",
    "wof:placetype":"venue"
},
  "geometry": {"coordinates":[-122.05845600000001,37.893127],"type":"Point"}
}