{
  "type": "Feature",
  "properties": {
    "iso:country":"US",
    "sg:address":"8166 W Sunset Blvd",
    "sg:city":"W Hollywood",
    "sg:classifiers":[
        {
            "category":"Restaurant",
            "type":"Food & Drink"
        }
    ],
    "sg:phone":"+1 323 650 8128",
    "sg:postcode":"90046",
    "sg:province":"CA",
    "sg:tags":[
        "pizza"
    ],
    "wof:name":"Jacopo's Pizzeria",
    "wof:placetype":"venue"
},
  "geometry": {"coordinates":[-118.37446,34.094814],"type":"Point"}
}