{
  "type": "Feature",
  "properties": {
    "addr:full":"2954 Alhambra Dr Cameron Park CA 95682",
    "addr:housenumber":"2954",
    "addr:postcode":"95682",
    "addr:street":"Alhambra Dr",
    "iso:country":"US",
    "sg:address":"2954 Alhambra Dr",
    "sg:city":"Cameron Park",
    "sg:classifiers":[
        {
            "category":"Real Estate",
            "subcategory":"Surveying",
            "type":"Services"
        }
    ],
    "sg:phone":"+1 530 677 3348",
    "sg:postcode":"95682",
    "sg:province":"CA",
    "sg:tags":[
        "surveyor"
    ],
    "wof:name":"Brewster & Assoc",
    "wof:placetype":"venue"
},
  "geometry": {"coordinates":[-120.990442,38.689377],"type":"Point"}
}