{
  "type": "Feature",
  "properties": {
    "iso:country":"US",
    "sg:address":"2464 Wyda Way Apt 4",
    "sg:city":"Sacramento",
    "sg:classifiers":[
        {
            "category":"Building & Trades",
            "subcategory":"Cleaning & Sanitation",
            "type":"Services"
        },
        {
            "category":"Retail",
            "subcategory":"Laundry & Dry Cleaning",
            "type":"Services"
        }
    ],
    "sg:phone":"+1 916 271 0409",
    "sg:postcode":"95825",
    "sg:province":"CA",
    "sg:tags":[
        "house",
        "cleaning-industrial",
        "cleaner",
        "contractor"
    ],
    "wof:name":"Perrigo Cleaning Co",
    "wof:placetype":"venue"
},
  "geometry": {"coordinates":[-121.404207,38.599831],"type":"Point"}
}