{
  "type": "Feature",
  "properties": {
    "iso:country":"US",
    "sg:address":"8383 Wilshire Boulevard",
    "sg:city":"Beverly Hills",
    "sg:classifiers":[
        {
            "category":"Professional",
            "subcategory":"Accounting & Tax Preparation",
            "type":"Services"
        }
    ],
    "sg:phone":"+1 323 651 0466",
    "sg:postcode":"90211",
    "sg:province":"CA",
    "sg:tags":[
        "accountant"
    ],
    "wof:name":"Hammer Thomas F CPA",
    "wof:placetype":"venue"
},
  "geometry": {"coordinates":[-118.373908,34.064667],"type":"Point"}
}