{
  "type": "Feature",
  "properties": {
    "addr:full":"1050 N Carpenter Rd Modesto CA 95351",
    "addr:housenumber":"1050",
    "addr:postcode":"ca 95351",
    "addr:street":"N Carpenter Rd",
    "iso:country":"US",
    "sg:address":"1050 N Carpenter Rd",
    "sg:city":"Modesto",
    "sg:classifiers":[
        {
            "category":"Insurance",
            "subcategory":"Hazard Insurance",
            "type":"Services"
        }
    ],
    "sg:phone":"+1 209 576 3333",
    "sg:postcode":"95351",
    "sg:province":"CA",
    "sg:tags":[
        "bond"
    ],
    "wof:name":"Singh Bail Bonds Inc",
    "wof:placetype":"venue"
},
  "geometry": {"coordinates":[-121.030192,37.646579],"type":"Point"}
}