{
  "type": "Feature",
  "properties": {
    "iso:country":"US",
    "sg:address":"675 N 1st St",
    "sg:city":"San Jose",
    "sg:classifiers":[
        {
            "category":"Professional",
            "subcategory":"Management & Consulting",
            "type":"Services"
        }
    ],
    "sg:phone":"+1 408 792 2925",
    "sg:postcode":"95112",
    "sg:province":"CA",
    "sg:tags":[
        "personnel",
        "consultant"
    ],
    "wof:name":"Echo Staffing",
    "wof:placetype":"venue"
},
  "geometry": {"coordinates":[-121.899868,37.348417],"type":"Point"}
}