{
  "type": "Feature",
  "properties": {
    "iso:country":"US",
    "sg:address":"4025 Spencer St",
    "sg:city":"Torrance",
    "sg:classifiers":[
        {
            "category":"Wholesale",
            "subcategory":"Durable Goods & Equipment",
            "type":"Manufacturing & Wholesale Goods"
        },
        {
            "category":"Wholesale",
            "subcategory":"Non-durable Goods",
            "type":"Manufacturing & Wholesale Goods"
        }
    ],
    "sg:phone":"+1 310 371 3003",
    "sg:postcode":"90503",
    "sg:province":"CA",
    "sg:tags":[
        "exporter",
        "gen",
        "merchandise"
    ],
    "wof:name":"Passion USA LLC",
    "wof:placetype":"venue"
},
  "geometry": {"coordinates":[-118.356998,33.845066],"type":"Point"}
}