{
  "type": "Feature",
  "properties": {
    "iso:country":"US",
    "sg:address":"121 E Orangeburg Ave",
    "sg:city":"Modesto",
    "sg:classifiers":[
        {
            "category":"Banks & Credit Unions",
            "subcategory":"Financial Services",
            "type":"Services"
        }
    ],
    "sg:phone":"+1 209 338 0808",
    "sg:postcode":"95350",
    "sg:province":"CA",
    "sg:tags":[
        "broker",
        "mortgage"
    ],
    "wof:name":"Platinum Gold Investments Inc",
    "wof:placetype":"venue"
},
  "geometry": {"coordinates":[-120.99335600000001,37.663802],"type":"Point"}
}