{
  "type": "Feature",
  "properties": {
    "addr:full":"10190 Systems Pkwy Sacramento CA 95827",
    "addr:housenumber":"10190",
    "addr:postcode":"95827",
    "addr:street":"Systems Pkwy",
    "iso:country":"US",
    "sg:address":"10190 Systems Pkwy",
    "sg:city":"Sacramento",
    "sg:classifiers":[
        {
            "category":"Building & Trades",
            "subcategory":"Pest Control",
            "type":"Services"
        }
    ],
    "sg:phone":"+1 916 361 0504",
    "sg:postcode":"95827",
    "sg:province":"CA",
    "wof:name":"Orkin Exterminating Co",
    "wof:placetype":"venue"
},
  "geometry": {"coordinates":[-121.312029,38.565422],"type":"Point"}
}