{
  "type": "Feature",
  "properties": {
    "iso:country":"US",
    "sg:address":"2817 E Whitmore Ave",
    "sg:city":"Ceres",
    "sg:classifiers":[
        {
            "category":"Professional",
            "type":"Services"
        }
    ],
    "sg:phone":"+1 209 667 8264",
    "sg:postcode":"95307",
    "sg:province":"CA",
    "wof:name":"Noelene Badiou",
    "wof:placetype":"venue"
},
  "geometry": {"coordinates":[-120.941447,37.594724],"type":"Point"}
}