{
  "type": "Feature",
  "properties": {
    "addr:full":"10350 Friars Rd San Diego CA 92120",
    "addr:housenumber":"10350",
    "addr:postcode":"92120",
    "addr:street":"Friars Rd",
    "iso:country":"US",
    "sg:address":"10350 Friars Rd",
    "sg:city":"San Diego",
    "sg:classifiers":[
        {
            "category":"Shopping",
            "subcategory":"Pharmacy",
            "type":"Retail Goods"
        }
    ],
    "sg:phone":"+1 619 563 9990",
    "sg:postcode":"92120",
    "sg:province":"CA",
    "sg:tags":[
        "drugstore"
    ],
    "sg:website":"www.cvs.com",
    "wof:name":"CVS pharmacy",
    "wof:placetype":"venue"
},
  "geometry": {"coordinates":[-117.10048999999999,32.790537],"type":"Point"}
}