{
  "type": "Feature",
  "properties": {
    "addr:full":"26711 Westhaven Dr Laguna Hills CA 92653",
    "addr:housenumber":"26711",
    "addr:postcode":"92653",
    "addr:street":"Westhaven Dr",
    "iso:country":"US",
    "sg:address":"26711 Westhaven Dr",
    "sg:city":"Laguna Hills",
    "sg:classifiers":[
        {
            "category":"Professional",
            "subcategory":"Management & Consulting",
            "type":"Services"
        }
    ],
    "sg:phone":"+1 949 683 2450",
    "sg:postcode":"92653",
    "sg:province":"CA",
    "sg:tags":[
        "counselor",
        "public",
        "relations"
    ],
    "wof:name":"Allen Group",
    "wof:placetype":"venue"
},
  "geometry": {"coordinates":[-117.698392,33.573955],"type":"Point"}
}