{
  "type": "Feature",
  "properties": {
    "iso:country":"US",
    "sg:address":"3614 S Broadway",
    "sg:city":"Los Angeles",
    "sg:classifiers":[
        {
            "category":"Manufacturing",
            "subcategory":"Apparel",
            "type":"Manufacturing & Wholesale Goods"
        }
    ],
    "sg:phone":"+1 323 232 3841",
    "sg:postcode":"90007",
    "sg:province":"CA",
    "sg:tags":[
        "sewing",
        "contractor"
    ],
    "wof:name":"World Trim",
    "wof:placetype":"venue"
},
  "geometry": {"coordinates":[-118.275273,34.016693],"type":"Point"}
}