{
  "type": "Feature",
  "properties": {
    "iso:country":"US",
    "sg:address":"4134 Jack Dale Way",
    "sg:city":"Oroville",
    "sg:classifiers":[
        {
            "category":"Professional",
            "subcategory":"Lawyer & Legal Services",
            "type":"Services"
        }
    ],
    "sg:phone":"+1 530 532 1363",
    "sg:postcode":"95965",
    "sg:province":"CA",
    "sg:tags":[
        "attorney"
    ],
    "wof:name":"William H Stuart III",
    "wof:placetype":"venue"
},
  "geometry": {"coordinates":[-121.49051900000001,39.777063],"type":"Point"}
}