{
  "type": "Feature",
  "properties": {
    "iso:country":"US",
    "sg:address":"1000 S Central Ave",
    "sg:city":"Glendale",
    "sg:classifiers":[
        {
            "category":"Food & Beverages",
            "subcategory":"Groceries & Convenience Stores",
            "type":"Retail Goods"
        }
    ],
    "sg:phone":"+1 818 244 8109",
    "sg:postcode":"91204",
    "sg:province":"CA",
    "sg:website":"www.albertsons.com",
    "wof:name":"Albertsons",
    "wof:placetype":"venue"
},
  "geometry": {"coordinates":[-118.258003,34.134201],"type":"Point"}
}