{
  "type": "Feature",
  "properties": {
    "addr:full":"707 Highland Ave Piedmont CA 94611",
    "addr:housenumber":"707",
    "addr:postcode":"94611",
    "addr:street":"Highland Ave",
    "iso:country":"US",
    "sg:address":"707 Highland Ave",
    "sg:city":"Piedmont",
    "sg:classifiers":[
        {
            "category":"Social Services",
            "type":"Services"
        }
    ],
    "sg:phone":"+1 510 985 3031",
    "sg:postcode":"94611",
    "sg:province":"CA",
    "sg:tags":[
        "youth",
        "organization",
        "center"
    ],
    "wof:name":"Camp Fire USA Oakland East Bay",
    "wof:placetype":"venue"
},
  "geometry": {"coordinates":[-122.23022400000001,37.824269],"type":"Point"}
}