{
  "type": "Feature",
  "properties": {
    "addr:full":"2305 Wilshire Blvd Santa Monica CA 90403",
    "addr:housenumber":"2305",
    "addr:postcode":"90403",
    "addr:street":"Wilshire Blvd",
    "iso:country":"US",
    "sg:address":"2305 Wilshire Blvd",
    "sg:city":"Santa Monica",
    "sg:classifiers":[
        {
            "category":"Travel",
            "subcategory":"Travel Agent",
            "type":"Entertainment"
        }
    ],
    "sg:phone":"+1 310 315 9143",
    "sg:postcode":"90403",
    "sg:province":"CA",
    "sg:tags":[
        "passenger",
        "transportation",
        "arrangement"
    ],
    "wof:name":"Hawaiian Airlines Agent Reserv",
    "wof:placetype":"venue"
},
  "geometry": {"coordinates":[-118.479957,34.03406],"type":"Point"}
}