{
  "type": "Feature",
  "properties": {
    "iso:country":"US",
    "sg:address":"891 Camino De La Reina",
    "sg:city":"San Diego",
    "sg:classifiers":[
        {
            "category":"Fast Food",
            "type":"Food & Drink"
        }
    ],
    "sg:phone":"+1 619 299 2270",
    "sg:postcode":"92108",
    "sg:province":"CA",
    "sg:tags":[
        "burger"
    ],
    "sg:website":"www.fuddruckers.com/",
    "wof:name":"Fuddruckers",
    "wof:placetype":"venue"
},
  "geometry": {"coordinates":[-117.15662500000001,32.767317],"type":"Point"}
}