{
  "type": "Feature",
  "properties": {
    "addr:full":"1858 30th Avenue San Francisco CA 94122",
    "addr:housenumber":"1858",
    "addr:postcode":"94122",
    "addr:street":"30Th Avenue",
    "iso:country":"US",
    "sg:address":"1858 30th Avenue",
    "sg:city":"San Francisco",
    "sg:classifiers":[
        {
            "category":"Personal",
            "type":"Services"
        }
    ],
    "sg:phone":"+1 510 477 8822",
    "sg:postcode":"94122",
    "sg:province":"CA",
    "sg:tags":[
        "mover"
    ],
    "wof:name":"Happy Moving",
    "wof:placetype":"venue"
},
  "geometry": {"coordinates":[-122.487999,37.752602],"type":"Point"}
}