{
  "type": "Feature",
  "properties": {
    "addr:full":"9710 Winter Gardens Blvd Lakeside CA 92040",
    "addr:housenumber":"9710",
    "addr:postcode":"92040",
    "addr:street":"Winter Gardens Blvd",
    "iso:country":"US",
    "sg:address":"9710 Winter Gardens Blvd",
    "sg:city":"Lakeside",
    "sg:classifiers":[
        {
            "category":"Insurance",
            "subcategory":"Insurance Agent",
            "type":"Services"
        }
    ],
    "sg:phone":"+1 619 390 9077",
    "sg:postcode":"92040",
    "sg:province":"CA",
    "wof:name":"Allstate Insurance",
    "wof:placetype":"venue"
},
  "geometry": {"coordinates":[-116.931161,32.8543],"type":"Point"}
}