{
  "type": "Feature",
  "properties": {
    "addr:full":"21207 Gladiolos Way Lake Forest CA 92630",
    "addr:housenumber":"21207",
    "addr:postcode":"92630",
    "addr:street":"Gladiolos Way",
    "iso:country":"US",
    "sg:address":"21207 Gladiolos Way",
    "sg:city":"Lake Forest",
    "sg:classifiers":[
        {
            "category":"Professional",
            "subcategory":"Business Services",
            "type":"Services"
        }
    ],
    "sg:phone":"+1 949 707 1424",
    "sg:postcode":"92630",
    "sg:province":"CA",
    "sg:tags":[
        "translator",
        "interpreter"
    ],
    "wof:name":"M & S Interpreters",
    "wof:placetype":"venue"
},
  "geometry": {"coordinates":[-117.685479,33.656351],"type":"Point"}
}