{
  "type": "Feature",
  "properties": {
    "addr:full":"1 Tillman Plz San Francisco CA 94108",
    "addr:housenumber":"1",
    "addr:postcode":"94108",
    "addr:street":"Tillman Plz",
    "iso:country":"US",
    "sg:address":"1 Tillman Plz",
    "sg:city":"San Francisco",
    "sg:classifiers":[
        {
            "category":"Professional",
            "subcategory":"Business Services",
            "type":"Services"
        }
    ],
    "sg:phone":"+1 415 362 9750",
    "sg:postcode":"94108",
    "sg:province":"CA",
    "sg:tags":[
        "relation",
        "public"
    ],
    "sg:website":"networkafterwork.com/",
    "wof:name":"Network After Work",
    "wof:placetype":"venue"
},
  "geometry": {"coordinates":[-122.40572,37.789438],"type":"Point"}
}