{
  "type": "Feature",
  "properties": {
    "addr:full":"6922 Hollywood Blvd Ste 107 Los Angeles CA 90028",
    "addr:housenumber":"6922",
    "addr:postcode":"90028",
    "addr:street":"Hollywood Blvd Ste 107",
    "iso:country":"US",
    "sg:address":"6922 Hollywood Blvd Ste 107",
    "sg:city":"Los Angeles",
    "sg:classifiers":[
        {
            "category":"Ice Cream",
            "type":"Food & Drink"
        }
    ],
    "sg:phone":"+1 323 465 9097",
    "sg:postcode":"90028",
    "sg:province":"CA",
    "sg:tags":[
        "frozen",
        "yogurt"
    ],
    "sg:website":"www.cefiore.com",
    "wof:name":"C?fiore",
    "wof:placetype":"venue"
},
  "geometry": {"coordinates":[-118.34116400000001,34.101552],"type":"Point"}
}