{
  "type": "Feature",
  "properties": {
    "addr:full":"250 N Cedros Ave Solana Beach CA 92075",
    "addr:housenumber":"250",
    "addr:postcode":"92075",
    "addr:street":"N Cedros Ave",
    "iso:country":"US",
    "sg:address":"250 N Cedros Ave",
    "sg:city":"Solana Beach",
    "sg:classifiers":[
        {
            "category":"Real Estate",
            "subcategory":"Architect",
            "type":"Services"
        }
    ],
    "sg:phone":"+1 858 436 7777",
    "sg:postcode":"92075",
    "sg:province":"CA",
    "wof:name":"Jlc Architecture Inc",
    "wof:placetype":"venue"
},
  "geometry": {"coordinates":[-117.271424,32.995662],"type":"Point"}
}