{
  "type": "Feature",
  "properties": {
    "addr:full":"33 Hidden Valley Rd Lafayette CA 94549",
    "addr:housenumber":"33",
    "addr:postcode":"94549",
    "addr:street":"Hidden Valley Rd",
    "iso:country":"US",
    "sg:address":"33 Hidden Valley Rd",
    "sg:city":"Lafayette",
    "sg:classifiers":[
        {
            "category":"Health Services",
            "subcategory":"Nursing And Care Facility",
            "type":"Services"
        }
    ],
    "sg:phone":"+1 925 284 5201",
    "sg:postcode":"94549",
    "sg:province":"CA",
    "sg:tags":[
        "home",
        "retirement",
        "community"
    ],
    "wof:name":"Hidden Valley Care Home",
    "wof:placetype":"venue"
},
  "geometry": {"coordinates":[-122.15637700000001,37.886591],"type":"Point"}
}