{
  "type": "Feature",
  "properties": {
    "iso:country":"US",
    "sg:address":"28821 Paseo Campana",
    "sg:city":"Mission Viejo",
    "sg:classifiers":[
        {
            "category":"Travel",
            "subcategory":"Hotels & Motels",
            "type":"Entertainment"
        }
    ],
    "sg:phone":"+1 949 305 2260",
    "sg:postcode":"92692",
    "sg:province":"CA",
    "sg:tags":[
        "house",
        "guest"
    ],
    "sg:website":"www.georgesmauivacation.com",
    "wof:name":"Georges Maui Vacation",
    "wof:placetype":"venue"
},
  "geometry": {"coordinates":[-117.627735,33.649366],"type":"Point"}
}