{
  "type": "Feature",
  "properties": {
    "iso:country":"US",
    "sg:address":"119 Martin St",
    "sg:city":"Nevada City",
    "sg:classifiers":[
        {
            "category":"Professional",
            "subcategory":"Business Services",
            "type":"Services"
        }
    ],
    "sg:phone":"+1 530 470 9120",
    "sg:postcode":"95959",
    "sg:province":"CA",
    "sg:tags":[
        "recording",
        "studio"
    ],
    "sg:website":"www.voxosonic.com",
    "wof:name":"Voxosonic",
    "wof:placetype":"venue"
},
  "geometry": {"coordinates":[-121.014763,39.253971],"type":"Point"}
}