{
  "type": "Feature",
  "properties": {
    "addr:full":"43094 Via Dos Picos Temecula CA 92590",
    "addr:housenumber":"43094",
    "addr:postcode":"92590",
    "addr:street":"Via Dos Picos",
    "iso:country":"US",
    "sg:address":"43094 Via Dos Picos",
    "sg:city":"Temecula",
    "sg:classifiers":[
        {
            "category":"Building & Trades",
            "subcategory":"Construction",
            "type":"Services"
        }
    ],
    "sg:phone":"+1 951 695 6722",
    "sg:postcode":"92590",
    "sg:province":"CA",
    "sg:tags":[
        "concrete",
        "contractor"
    ],
    "wof:name":"Shay Enterprises Inc",
    "wof:placetype":"venue"
},
  "geometry": {"coordinates":[-117.162012,33.505102],"type":"Point"}
}