{
  "type": "Feature",
  "properties": {
    "addr:full":"2893 Marisa Ct Riverside CA 92503",
    "addr:housenumber":"2893",
    "addr:postcode":"92503",
    "addr:street":"Marisa Ct",
    "iso:country":"US",
    "sg:address":"2893 Marisa Ct",
    "sg:city":"Riverside",
    "sg:classifiers":[
        {
            "category":"Shopping",
            "subcategory":"Used Merchandise",
            "type":"Retail Goods"
        }
    ],
    "sg:phone":"+1 951 351 8760",
    "sg:postcode":"92503",
    "sg:province":"CA",
    "sg:tags":[
        "antique"
    ],
    "wof:name":"Grandpa's Treasures",
    "wof:placetype":"venue"
},
  "geometry": {"coordinates":[-117.429394,33.910184],"type":"Point"}
}