{
  "type": "Feature",
  "properties": {
    "iso:country":"US",
    "sg:address":"47336 Oasis St",
    "sg:city":"Indio",
    "sg:classifiers":[
        {
            "category":"Government",
            "subcategory":"Office",
            "type":"Public Place"
        }
    ],
    "sg:phone":"+1 760 863 3000",
    "sg:postcode":"92201",
    "sg:province":"CA",
    "sg:tags":[
        "county",
        "program"
    ],
    "sg:website":"www.rcoe.k12.ca.us",
    "wof:name":"Riverside County Education Ofc",
    "wof:placetype":"venue"
},
  "geometry": {"coordinates":[-116.22081,33.707262],"type":"Point"}
}