{
  "type": "Feature",
  "properties": {
    "addr:full":"1100 Mandela Ct Palo Alto CA 94303",
    "addr:housenumber":"1100",
    "addr:postcode":"94303",
    "addr:street":"Mandela Ct",
    "iso:country":"US",
    "sg:address":"1100 Mandela Ct",
    "sg:city":"Palo Alto",
    "sg:classifiers":[
        {
            "category":"Wholesale",
            "subcategory":"Vending Machines",
            "type":"Manufacturing & Wholesale Goods"
        }
    ],
    "sg:phone":"+1 650 325 1751",
    "sg:postcode":"94303",
    "sg:province":"CA",
    "wof:name":"Thompson Family Vending Co",
    "wof:placetype":"venue"
},
  "geometry": {"coordinates":[-122.129614,37.468317],"type":"Point"}
}