{
  "type": "Feature",
  "properties": {
    "iso:country":"US",
    "sg:address":"At VCA Lakewood Animal Hospital 10701 South Street",
    "sg:city":"Cerritos",
    "sg:classifiers":[
        {
            "category":"Shopping",
            "subcategory":"Pets & Pet Supplies",
            "type":"Retail Goods"
        }
    ],
    "sg:phone":"+1 562 926 3600",
    "sg:postcode":"90703",
    "sg:province":"CA",
    "sg:tags":[
        "groomers"
    ],
    "wof:name":"You Dirty Dog",
    "wof:placetype":"venue"
},
  "geometry": {"coordinates":[-118.107944,33.858628],"type":"Point"}
}