{
  "type": "Feature",
  "properties": {
    "iso:country":"US",
    "sg:address":"121 Carmody Cir",
    "sg:city":"Folsom",
    "sg:classifiers":[
        {
            "category":"Wholesale",
            "subcategory":"Plants",
            "type":"Manufacturing & Wholesale Goods"
        }
    ],
    "sg:phone":"+1 916 987 1010",
    "sg:postcode":"95630",
    "sg:province":"CA",
    "sg:tags":[
        "supply"
    ],
    "wof:name":"Mary-Lou Vocalist & Flora",
    "wof:placetype":"venue"
},
  "geometry": {"coordinates":[-121.183943,38.703894],"type":"Point"}
}