{
  "type": "Feature",
  "properties": {
    "iso:country":"US",
    "sg:address":"3546 First Ave",
    "sg:city":"San Diego",
    "sg:classifiers":[
        {
            "category":"Retail",
            "subcategory":"Animal Services",
            "type":"Services"
        }
    ],
    "sg:phone":"+1 619 544 0764",
    "sg:postcode":"92103",
    "sg:province":"CA",
    "sg:tags":[
        "pet"
    ],
    "sg:website":"www.sniffpetcare.com/",
    "wof:name":"Sniff Pet Care",
    "wof:placetype":"venue"
},
  "geometry": {"coordinates":[-117.163884,32.742432],"type":"Point"}
}