{
  "type": "Feature",
  "properties": {
    "addr:full":"431 Dr Martin Luther King Jr Blvd Bakersfield CA 93307",
    "addr:housenumber":"431",
    "addr:postcode":"93307",
    "addr:street":"Dr Martin Luther King Jr Blvd",
    "iso:country":"US",
    "sg:address":"431 Dr Martin Luther King Jr Blvd",
    "sg:city":"Bakersfield",
    "sg:classifiers":[
        {
            "category":"Food & Beverages",
            "subcategory":"Groceries & Convenience Stores",
            "type":"Retail Goods"
        }
    ],
    "sg:phone":"+1 661 324 1121",
    "sg:postcode":"93307",
    "sg:province":"CA",
    "sg:tags":[
        "grocer"
    ],
    "wof:name":"Roy's Market",
    "wof:placetype":"venue"
},
  "geometry": {"coordinates":[-118.985174,35.362342],"type":"Point"}
}