{
  "type": "Feature",
  "properties": {
    "addr:full":"391 E Main St Ventura CA 93001",
    "addr:housenumber":"391",
    "addr:postcode":"93001",
    "addr:street":"E Main St",
    "iso:country":"US",
    "sg:address":"391 E Main St",
    "sg:city":"Ventura",
    "sg:classifiers":[
        {
            "category":"Utilities",
            "subcategory":"Refuse",
            "type":"Services"
        }
    ],
    "sg:phone":"+1 805 983 7220",
    "sg:postcode":"93001",
    "sg:province":"CA",
    "sg:tags":[
        "system"
    ],
    "wof:name":"Book Recycling Center",
    "wof:placetype":"venue"
},
  "geometry": {"coordinates":[-119.295817,34.280882],"type":"Point"}
}