{
  "type": "Feature",
  "properties": {
    "addr:full":"10450 Cochran Ave Riverside CA 92505",
    "addr:housenumber":"10450",
    "addr:postcode":"92505",
    "addr:street":"Cochran Ave",
    "iso:country":"US",
    "sg:address":"10450 Cochran Ave",
    "sg:city":"Riverside",
    "sg:classifiers":[
        {
            "category":"Building & Trades",
            "subcategory":"Construction",
            "type":"Services"
        }
    ],
    "sg:phone":"+1 951 353 1718",
    "sg:postcode":"92505",
    "sg:province":"CA",
    "sg:tags":[
        "dry wall",
        "contractor"
    ],
    "wof:name":"Class A Drywall & Texture",
    "wof:placetype":"venue"
},
  "geometry": {"coordinates":[-117.466523,33.913515],"type":"Point"}
}