{
  "type": "Feature",
  "properties": {
    "iso:country":"US",
    "sg:address":"13615 Stowe Dr",
    "sg:city":"Poway",
    "sg:classifiers":[
        {
            "category":"Shopping",
            "subcategory":"Bicycles & Sporting Goods",
            "type":"Retail Goods"
        }
    ],
    "sg:phone":"+1 858 486 3105",
    "sg:postcode":"92064",
    "sg:province":"CA",
    "sg:tags":[
        "equipment",
        "skateboard"
    ],
    "wof:name":"Skate America",
    "wof:placetype":"venue"
},
  "geometry": {"coordinates":[-117.034378,32.941531],"type":"Point"}
}