{
  "type": "Feature",
  "properties": {
    "iso:country":"US",
    "sg:address":"2232 National Ave",
    "sg:city":"San Diego",
    "sg:classifiers":[
        {
            "category":"Organizations",
            "subcategory":"Religious Organization",
            "type":"Services"
        }
    ],
    "sg:phone":"+1 619 696 1156",
    "sg:postcode":"92113",
    "sg:province":"CA",
    "sg:tags":[
        "church"
    ],
    "wof:name":"Mission Of God",
    "wof:placetype":"venue"
},
  "geometry": {"coordinates":[-117.13889399999999,32.6965],"type":"Point"}
}