{
  "type": "Feature",
  "properties": {
    "addr:full":"8075 7th Ave Hanford CA 93230",
    "addr:housenumber":"8075",
    "addr:postcode":"ca 93230",
    "addr:street":"7Th Ave",
    "iso:country":"US",
    "sg:address":"8075 7th Ave",
    "sg:city":"Hanford",
    "sg:phone":"+1 559 582 5788",
    "sg:postcode":"93230",
    "sg:province":"CA",
    "sg:tags":[
        "farm",
        "wheat"
    ],
    "wof:name":"Blanchard Farms Inc",
    "wof:placetype":"venue"
},
  "geometry": {"coordinates":[-119.582939,36.356415],"type":"Point"}
}