{
  "type": "Feature",
  "properties": {
    "iso:country":"US",
    "sg:address":"43488 Dodaro Dr",
    "sg:city":"Temecula",
    "sg:classifiers":[
        {
            "category":"Real Estate",
            "subcategory":"Real Estate Services",
            "type":"Services"
        },
        {
            "category":"Real Estate",
            "subcategory":"Real Estate Agent",
            "type":"Services"
        }
    ],
    "sg:phone":"+1 951 303 1688",
    "sg:postcode":"92592",
    "sg:province":"CA",
    "sg:tags":[
        "management"
    ],
    "wof:name":"Dra Investments Inc",
    "wof:placetype":"venue"
},
  "geometry": {"coordinates":[-117.094317,33.496732],"type":"Point"}
}