{
  "type": "Feature",
  "properties": {
    "addr:full":"4455 Concord Ave Santa Rosa CA 95407",
    "addr:housenumber":"4455",
    "addr:postcode":"95407",
    "addr:street":"Concord Ave",
    "iso:country":"US",
    "sg:address":"4455 Concord Ave",
    "sg:city":"Santa Rosa",
    "sg:classifiers":[
        {
            "category":"Professional",
            "subcategory":"Lawyer & Legal Services",
            "type":"Services"
        }
    ],
    "sg:phone":"+1 707 578 4239",
    "sg:postcode":"95407",
    "sg:province":"CA",
    "sg:tags":[
        "attorney"
    ],
    "wof:name":"Robert Giffin",
    "wof:placetype":"venue"
},
  "geometry": {"coordinates":[-122.776895,38.41106],"type":"Point"}
}