{
  "type": "Feature",
  "properties": {
    "addr:full":"175 Pomeroy Ave Pismo Beach CA 93449",
    "addr:housenumber":"175",
    "addr:postcode":"93449",
    "addr:street":"Pomeroy Ave",
    "iso:country":"US",
    "sg:address":"175 Pomeroy Ave",
    "sg:city":"Pismo Beach",
    "sg:classifiers":[
        {
            "category":"Shopping",
            "subcategory":"Gifts & Souvenirs",
            "type":"Retail Goods"
        }
    ],
    "sg:phone":"+1 805 773 0713",
    "sg:postcode":"93449",
    "sg:province":"CA",
    "sg:tags":[
        "shop"
    ],
    "wof:name":"Once Upon A Time",
    "wof:placetype":"venue"
},
  "geometry": {"coordinates":[-120.642672,35.139676],"type":"Point"}
}