{
  "type": "Feature",
  "properties": {
    "iso:country":"US",
    "sg:address":"13500 Hubbard St",
    "sg:city":"Sylmar",
    "sg:classifiers":[
        {
            "category":"Autos & Motor Vehicles",
            "subcategory":"Fuel & Gas Station",
            "type":"Retail Goods"
        }
    ],
    "sg:phone":"+1 818 361 3112",
    "sg:postcode":"91342",
    "sg:province":"CA",
    "sg:tags":[
        "oil"
    ],
    "wof:name":"Barry's Chevron Svc",
    "wof:placetype":"venue"
},
  "geometry": {"coordinates":[-118.427692,34.309749],"type":"Point"}
}