{
  "type": "Feature",
  "properties": {
    "addr:full":"8851 Garden Grove Blvd Garden Grove CA 92844",
    "addr:housenumber":"8851",
    "addr:postcode":"92844",
    "addr:street":"Garden Grove Blvd",
    "iso:country":"US",
    "sg:address":"8851 Garden Grove Blvd",
    "sg:city":"Garden Grove",
    "sg:classifiers":[
        {
            "category":"Professional",
            "type":"Services"
        }
    ],
    "sg:phone":"+1 714 530 1314",
    "sg:postcode":"92844",
    "sg:province":"CA",
    "wof:name":"Maponaru",
    "wof:placetype":"venue"
},
  "geometry": {"coordinates":[-117.978196,33.773965],"type":"Point"}
}