{
  "type": "Feature",
  "properties": {
    "iso:country":"US",
    "sg:address":"44841 San Pablo Ave",
    "sg:city":"Palm Desert",
    "sg:classifiers":[
        {
            "category":"Sports & Exercise",
            "subcategory":"Bicycle Rental",
            "type":"Entertainment"
        }
    ],
    "sg:phone":"+1 760 321 9444",
    "sg:postcode":"92260",
    "sg:province":"CA",
    "sg:tags":[
        "bike"
    ],
    "wof:name":"Native Cycles-Bicycle Tours",
    "wof:placetype":"venue"
},
  "geometry": {"coordinates":[-116.38274699999999,33.722506],"type":"Point"}
}