{
  "type": "Feature",
  "properties": {
    "addr:full":"652 Petaluma Ave Sebastopol CA 95472",
    "addr:housenumber":"652",
    "addr:postcode":"95472",
    "addr:street":"Petaluma Ave",
    "iso:country":"US",
    "sg:address":"652 Petaluma Ave",
    "sg:city":"Sebastopol",
    "sg:classifiers":[
        {
            "category":"Real Estate",
            "subcategory":"Real Estate Services",
            "type":"Services"
        }
    ],
    "sg:phone":"+1 707 824 6320",
    "sg:postcode":"95472",
    "sg:province":"CA",
    "sg:tags":[
        "company",
        "title"
    ],
    "wof:name":"Financial Title Co",
    "wof:placetype":"venue"
},
  "geometry": {"coordinates":[-122.819604,38.395897],"type":"Point"}
}