{
  "type": "Feature",
  "properties": {
    "iso:country":"US",
    "sg:address":"1850 Redondo Beach Blvd",
    "sg:city":"Gardena",
    "sg:classifiers":[
        {
            "category":"Restaurant",
            "type":"Food & Drink"
        }
    ],
    "sg:phone":"+1 310 217 1130",
    "sg:postcode":"90247",
    "sg:province":"CA",
    "sg:tags":[
        "vietnamese"
    ],
    "wof:name":"Pho Consomme",
    "wof:placetype":"venue"
},
  "geometry": {"coordinates":[-118.310677,33.887995],"type":"Point"}
}