{
  "type": "Feature",
  "properties": {
    "addr:full":"8926 Benson Ave Montclair CA 91763",
    "addr:housenumber":"8926",
    "addr:postcode":"91763",
    "addr:street":"Benson Ave",
    "iso:country":"US",
    "sg:address":"8926 Benson Ave",
    "sg:city":"Montclair",
    "sg:classifiers":[
        {
            "category":"Wholesale",
            "subcategory":"Machinery & Supplies",
            "type":"Manufacturing & Wholesale Goods"
        }
    ],
    "sg:phone":"+1 909 985 3799",
    "sg:postcode":"91763",
    "sg:province":"CA",
    "sg:tags":[
        "industrial",
        "refrigeration",
        "equipment-commercial"
    ],
    "wof:name":"California Industrial",
    "wof:placetype":"venue"
},
  "geometry": {"coordinates":[-117.680965,34.092263],"type":"Point"}
}