{
  "type": "Feature",
  "properties": {
    "iso:country":"US",
    "sg:address":"306 Bassett St",
    "sg:city":"King City",
    "sg:classifiers":[
        {
            "category":"Social Services",
            "type":"Services"
        }
    ],
    "sg:phone":"+1 831 385 3988",
    "sg:postcode":"93930",
    "sg:province":"CA",
    "sg:tags":[
        "organization",
        "welfare"
    ],
    "wof:name":"King City Salvation Army",
    "wof:placetype":"venue"
},
  "geometry": {"coordinates":[-121.12572900000001,36.212041],"type":"Point"}
}