{
  "type": "Feature",
  "properties": {
    "iso:country":"US",
    "sg:address":"4120 Cameron Park Dr",
    "sg:city":"Cameron Park",
    "sg:classifiers":[
        {
            "category":"Professional",
            "subcategory":"Lawyer & Legal Services",
            "type":"Services"
        }
    ],
    "sg:phone":"+1 530 672 8008",
    "sg:postcode":"95682",
    "sg:province":"CA",
    "sg:tags":[
        "attorney"
    ],
    "wof:name":"J Kent O'Mara",
    "wof:placetype":"venue"
},
  "geometry": {"coordinates":[-120.968902,38.655917],"type":"Point"}
}