{
  "type": "Feature",
  "properties": {
    "addr:full":"5200 S Santa Fe Ave Los Angeles CA 90058",
    "addr:housenumber":"5200",
    "addr:postcode":"90058",
    "addr:street":"S Santa Fe Ave",
    "iso:country":"US",
    "sg:address":"5200 S Santa Fe Ave",
    "sg:city":"Los Angeles",
    "sg:classifiers":[
        {
            "category":"Retail",
            "subcategory":"Auto Repair",
            "type":"Services"
        }
    ],
    "sg:phone":"+1 323 588 3894",
    "sg:postcode":"90058",
    "sg:province":"CA",
    "sg:tags":[
        "truck"
    ],
    "wof:name":"Santro",
    "wof:placetype":"venue"
},
  "geometry": {"coordinates":[-118.230234,33.995241],"type":"Point"}
}