{
  "type": "Feature",
  "properties": {
    "addr:full":"317 S Broadway Los Angeles CA 90013",
    "addr:housenumber":"317",
    "addr:postcode":"90013",
    "addr:street":"S Broadway",
    "iso:country":"US",
    "sg:address":"317 S Broadway",
    "sg:city":"Los Angeles",
    "sg:classifiers":[
        {
            "category":"Shopping",
            "subcategory":"Discount & Variety Stores",
            "type":"Retail Goods"
        }
    ],
    "sg:phone":"+1 213 620 1267",
    "sg:postcode":"90013",
    "sg:province":"CA",
    "wof:name":"Grand Central Ninty Nine Cents",
    "wof:placetype":"venue"
},
  "geometry": {"coordinates":[-118.24923699999999,34.049802],"type":"Point"}
}