{
  "type": "Feature",
  "properties": {
    "addr:full":"7559 Hansom Dr Oakland CA 94605",
    "addr:housenumber":"7559",
    "addr:postcode":"94605",
    "addr:street":"Hansom Dr",
    "iso:country":"US",
    "sg:address":"7559 Hansom Dr",
    "sg:city":"Oakland",
    "sg:classifiers":[
        {
            "category":"Professional",
            "subcategory":"Business Services",
            "type":"Services"
        }
    ],
    "sg:phone":"+1 510 569 5259",
    "sg:postcode":"94605",
    "sg:province":"CA",
    "sg:tags":[
        "development"
    ],
    "wof:name":"Cafe Innovation",
    "wof:placetype":"venue"
},
  "geometry": {"coordinates":[-122.14207,37.781652],"type":"Point"}
}