{
  "type": "Feature",
  "properties": {
    "iso:country":"US",
    "sg:address":"30218 Hwy 78",
    "sg:city":"Santa Ysabel",
    "sg:classifiers":[
        {
            "category":"Shopping",
            "subcategory":"Gifts & Souvenirs",
            "type":"Retail Goods"
        }
    ],
    "sg:phone":"+1 760 765 2530",
    "sg:postcode":"92070",
    "sg:province":"CA",
    "sg:tags":[
        "shop"
    ],
    "sg:website":"www.crossroadstreasures.net",
    "wof:name":"Crossroads Treasures",
    "wof:placetype":"venue"
},
  "geometry": {"coordinates":[-116.674353,33.109151],"type":"Point"}
}