{
  "type": "Feature",
  "properties": {
    "addr:full":"672 Pavilion Dr Fairfield CA 94534",
    "addr:housenumber":"672",
    "addr:postcode":"94534",
    "addr:street":"Pavilion Dr",
    "iso:country":"US",
    "sg:address":"672 Pavilion Dr",
    "sg:city":"Fairfield",
    "sg:classifiers":[
        {
            "category":"Shopping",
            "type":"Retail Goods"
        }
    ],
    "sg:phone":"+1 707 864 9077",
    "sg:postcode":"94534",
    "sg:province":"CA",
    "sg:tags":[
        "merchandise"
    ],
    "wof:name":"Sierra West Gallery",
    "wof:placetype":"venue"
},
  "geometry": {"coordinates":[-122.14742200000001,38.221582],"type":"Point"}
}