{
  "type": "Feature",
  "properties": {
    "iso:country":"US",
    "sg:address":"13131 166th St",
    "sg:city":"Cerritos",
    "sg:classifiers":[
        {
            "category":"Professional",
            "subcategory":"Advertising",
            "type":"Services"
        }
    ],
    "sg:phone":"+1 562 365 0387",
    "sg:postcode":"90703",
    "sg:province":"CA",
    "sg:tags":[
        "demonstration"
    ],
    "wof:name":"SPI",
    "wof:placetype":"venue"
},
  "geometry": {"coordinates":[-118.050551,33.880623],"type":"Point"}
}