{
  "type": "Feature",
  "properties": {
    "addr:full":"528 N Stockton St Stockton CA 95203",
    "addr:housenumber":"528",
    "addr:postcode":"95203",
    "addr:street":"N Stockton St",
    "iso:country":"US",
    "sg:address":"528 N Stockton St",
    "sg:city":"Stockton",
    "sg:classifiers":[
        {
            "category":"Building & Trades",
            "subcategory":"Pest Control",
            "type":"Services"
        }
    ],
    "sg:phone":"+1 209 368 3174",
    "sg:postcode":"95203",
    "sg:province":"CA",
    "sg:website":"www.delkpestcontrol.com",
    "wof:name":"Termite Control Co",
    "wof:placetype":"venue"
},
  "geometry": {"coordinates":[-121.304304,37.956225],"type":"Point"}
}