{
  "type": "Feature",
  "properties": {
    "iso:country":"US",
    "sg:address":"328 Foothill Dr",
    "sg:city":"Fillmore",
    "sg:classifiers":[
        {
            "category":"Professional",
            "type":"Services"
        }
    ],
    "sg:phone":"+1 805 524 1580",
    "sg:postcode":"93015",
    "sg:province":"CA",
    "wof:name":"Gregory Products",
    "wof:placetype":"venue"
},
  "geometry": {"coordinates":[-118.913777,34.4116],"type":"Point"}
}