{
  "type": "Feature",
  "properties": {
    "addr:full":"840 N Norma St Ridgecrest CA 93555",
    "addr:housenumber":"840",
    "addr:postcode":"93555",
    "addr:street":"N Norma St",
    "iso:country":"US",
    "sg:address":"840 N Norma St",
    "sg:city":"Ridgecrest",
    "sg:classifiers":[
        {
            "category":"Health Services",
            "subcategory":"Chiropractor",
            "type":"Services"
        }
    ],
    "sg:phone":"+1 760 371 1300",
    "sg:postcode":"93555",
    "sg:province":"CA",
    "wof:name":"Podell Chiropractic Ctr",
    "wof:placetype":"venue"
},
  "geometry": {"coordinates":[-117.678614,35.636015],"type":"Point"}
}