{
  "type": "Feature",
  "properties": {
    "iso:country":"US",
    "sg:address":"3021 Citrus Cir",
    "sg:city":"Walnut Creek",
    "sg:classifiers":[
        {
            "category":"Banks & Credit Unions",
            "subcategory":"Bank",
            "type":"Services"
        }
    ],
    "sg:phone":"+1 925 287 8400",
    "sg:postcode":"94598",
    "sg:province":"CA",
    "sg:tags":[
        "loan",
        "real estate"
    ],
    "wof:name":"Mortgage Practice",
    "wof:placetype":"venue"
},
  "geometry": {"coordinates":[-122.01369800000001,37.929533],"type":"Point"}
}