{
  "type": "Feature",
  "properties": {
    "addr:full":"1240 S Main St Los Angeles CA 90015",
    "addr:housenumber":"1240",
    "addr:postcode":"90015",
    "addr:street":"S Main St",
    "iso:country":"US",
    "sg:address":"1240 S Main St",
    "sg:city":"Los Angeles",
    "sg:classifiers":[
        {
            "category":"Shopping",
            "subcategory":"Clothing, Apparel, & Fashions",
            "type":"Retail Goods"
        }
    ],
    "sg:phone":"+1 213 765 0822",
    "sg:postcode":"90015",
    "sg:province":"CA",
    "wof:name":"Fuentes Fashion",
    "wof:placetype":"venue"
},
  "geometry": {"coordinates":[-118.259777,34.037031],"type":"Point"}
}