{
  "type": "Feature",
  "properties": {
    "iso:country":"US",
    "sg:address":"5817 Shattuck Ave",
    "sg:city":"Oakland",
    "sg:classifiers":[
        {
            "category":"Bars & Pubs",
            "type":"Food & Drink"
        },
        {
            "category":"Food & Beverages",
            "subcategory":"Ethnic Foods",
            "type":"Retail Goods"
        },
        {
            "category":"Professional",
            "type":"Services"
        }
    ],
    "sg:phone":"+1 510 428 1935",
    "sg:postcode":"94609",
    "sg:province":"CA",
    "sg:tags":[
        "soul",
        "caterer"
    ],
    "sg:website":"dorseyslocker.com",
    "wof:name":"Dorsey's Locker",
    "wof:placetype":"venue"
},
  "geometry": {"coordinates":[-122.264999,37.8437],"type":"Point"}
}