{
  "type": "Feature",
  "properties": {
    "addr:full":"998 San Antonio Ave Palo Alto CA 94303",
    "addr:housenumber":"998",
    "addr:postcode":"94303",
    "addr:street":"San Antonio Ave",
    "iso:country":"US",
    "sg:address":"998 San Antonio Ave",
    "sg:city":"Palo Alto",
    "sg:classifiers":[
        {
            "category":"Professional",
            "type":"Services"
        }
    ],
    "sg:phone":"+1 650 494 7861",
    "sg:postcode":"94303",
    "sg:province":"CA",
    "sg:tags":[
        "establishment"
    ],
    "wof:name":"Anjuman E Jamali",
    "wof:placetype":"venue"
},
  "geometry": {"coordinates":[-122.10137,37.424099],"type":"Point"}
}