{
  "type": "Feature",
  "properties": {
    "iso:country":"US",
    "sg:address":"75 Mill St",
    "sg:city":"San Rafael",
    "sg:classifiers":[
        {
            "category":"Retail",
            "subcategory":"Auto Repair",
            "type":"Services"
        }
    ],
    "sg:phone":"+1 415 454 5157",
    "sg:postcode":"94901",
    "sg:province":"CA",
    "sg:tags":[
        "body",
        "automobile",
        "painting"
    ],
    "wof:name":"Barsotti's Body & Fender Svc",
    "wof:placetype":"venue"
},
  "geometry": {"coordinates":[-122.50967900000001,37.964608],"type":"Point"}
}