{
  "type": "Feature",
  "properties": {
    "iso:country":"US",
    "sg:address":"3088 Pio Pico Dr",
    "sg:city":"Carlsbad",
    "sg:classifiers":[
        {
            "category":"Health Services",
            "subcategory":"Doctor",
            "type":"Services"
        }
    ],
    "sg:phone":"+1 760 730 0163",
    "sg:postcode":"92008",
    "sg:province":"CA",
    "sg:tags":[
        "cardiologist"
    ],
    "wof:name":"San Diego Cardiovascular Group",
    "wof:placetype":"venue"
},
  "geometry": {"coordinates":[-117.340985,33.162545],"type":"Point"}
}