{
  "type": "Feature",
  "properties": {
    "iso:country":"US",
    "sg:address":"1072 Lake Blvd",
    "sg:city":"Redding",
    "sg:classifiers":[
        {
            "category":"Personal",
            "subcategory":"Beauty Salon",
            "type":"Services"
        }
    ],
    "sg:phone":"+1 530 244 1433",
    "sg:postcode":"96003",
    "sg:province":"CA",
    "sg:tags":[
        "hair",
        "stylist"
    ],
    "wof:name":"Le Monaco's",
    "wof:placetype":"venue"
},
  "geometry": {"coordinates":[-122.403465,40.622729],"type":"Point"}
}