{
  "type": "Feature",
  "properties": {
    "addr:full":"665 N E St San Bernardino CA 92410",
    "addr:housenumber":"665",
    "addr:postcode":"92410",
    "addr:street":"N E St",
    "iso:country":"US",
    "sg:address":"665 N E St",
    "sg:city":"San Bernardino",
    "sg:classifiers":[
        {
            "category":"Professional",
            "subcategory":"Lawyer & Legal Services",
            "type":"Services"
        }
    ],
    "sg:phone":"+1 909 888 4996",
    "sg:postcode":"92410",
    "sg:province":"CA",
    "sg:tags":[
        "attorney"
    ],
    "wof:name":"Consumer's Law Group Ads Inc",
    "wof:placetype":"venue"
},
  "geometry": {"coordinates":[-117.29409200000001,34.111786],"type":"Point"}
}