{
  "type": "Feature",
  "properties": {
    "addr:full":"2734 E Alondra Blvd Compton CA 90221",
    "addr:housenumber":"2734",
    "addr:postcode":"90221",
    "addr:street":"E Alondra Blvd",
    "iso:country":"US",
    "sg:address":"2734 E Alondra Blvd",
    "sg:city":"Compton",
    "sg:classifiers":[
        {
            "category":"Organizations",
            "subcategory":"Religious Organization",
            "type":"Services"
        }
    ],
    "sg:phone":"+1 310 763 0444",
    "sg:postcode":"90221",
    "sg:province":"CA",
    "sg:tags":[
        "church"
    ],
    "wof:name":"Hope Of Glory Missionary Bapt",
    "wof:placetype":"venue"
},
  "geometry": {"coordinates":[-118.194265,33.888695],"type":"Point"}
}