{
  "type": "Feature",
  "properties": {
    "iso:country":"US",
    "sg:address":"1813 Royo Ranchero Dr",
    "sg:city":"Yuba City",
    "sg:classifiers":[
        {
            "category":"Building & Trades",
            "subcategory":"Plumbing",
            "type":"Services"
        }
    ],
    "sg:phone":"+1 530 671 7924",
    "sg:postcode":"95993",
    "sg:province":"CA",
    "sg:tags":[
        "contractor"
    ],
    "wof:name":"Don Jacobsen Plumbing",
    "wof:placetype":"venue"
},
  "geometry": {"coordinates":[-121.677953,39.152524],"type":"Point"}
}