{
  "type": "Feature",
  "properties": {
    "addr:full":"6689 Downey Ave Long Beach CA 90805",
    "addr:housenumber":"6689",
    "addr:postcode":"90805",
    "addr:street":"Downey Ave",
    "iso:country":"US",
    "sg:address":"6689 Downey Ave",
    "sg:city":"Long Beach",
    "sg:classifiers":[
        {
            "category":"Shopping",
            "subcategory":"Music",
            "type":"Retail Goods"
        }
    ],
    "sg:phone":"+1 562 602 2131",
    "sg:postcode":"90805",
    "sg:province":"CA",
    "sg:tags":[
        "game",
        "disc",
        "tape",
        "video",
        "rental",
        "cassette"
    ],
    "wof:name":"92 Cent Video",
    "wof:placetype":"venue"
},
  "geometry": {"coordinates":[-118.151323,33.875737],"type":"Point"}
}