{
  "type": "Feature",
  "properties": {
    "addr:full":"1637 Nadeau St Los Angeles CA 90001",
    "addr:housenumber":"1637",
    "addr:postcode":"90001",
    "addr:street":"Nadeau St",
    "iso:country":"US",
    "sg:address":"1637 Nadeau St",
    "sg:city":"Los Angeles",
    "sg:classifiers":[
        {
            "category":"Manufacturing",
            "subcategory":"Metals",
            "type":"Manufacturing & Wholesale Goods"
        }
    ],
    "sg:phone":"+1 323 583 7233",
    "sg:postcode":"90001",
    "sg:province":"CA",
    "sg:tags":[
        "metalwork",
        "sheet",
        "mfg"
    ],
    "wof:name":"Express Metal Sheet Products I",
    "wof:placetype":"venue"
},
  "geometry": {"coordinates":[-118.243408,33.967492],"type":"Point"}
}