{
  "type": "Feature",
  "properties": {
    "addr:full":"19961 Beach Blvd Huntington Beach CA 92648",
    "addr:housenumber":"19961",
    "addr:postcode":"92648",
    "addr:street":"Beach Blvd",
    "iso:country":"US",
    "sg:address":"19961 Beach Blvd",
    "sg:city":"Huntington Beach",
    "sg:classifiers":[
        {
            "category":"Retail",
            "subcategory":"Auto Repair",
            "type":"Services"
        }
    ],
    "sg:phone":"+1 714 536 6519",
    "sg:postcode":"92648",
    "sg:province":"CA",
    "sg:website":"www.econolube.com",
    "wof:name":"Econo Lube 'n Tune",
    "wof:placetype":"venue"
},
  "geometry": {"coordinates":[-117.989053,33.672734],"type":"Point"}
}