{
  "type": "Feature",
  "properties": {
    "addr:full":"6994 El Camino Real Ste 109 Carlsbad CA 92009",
    "addr:housenumber":"6994",
    "addr:postcode":"92009",
    "addr:street":"El Camino Real Ste 109",
    "iso:country":"US",
    "sg:address":"6994 El Camino Real Ste 109",
    "sg:city":"Carlsbad",
    "sg:classifiers":[
        {
            "category":"Sports & Exercise",
            "subcategory":"Gym",
            "type":"Entertainment"
        },
        {
            "category":"Health Services",
            "subcategory":"Health Practitioner",
            "type":"Services"
        }
    ],
    "sg:phone":"+1 760 268 1023",
    "sg:postcode":"92009",
    "sg:province":"CA",
    "sg:tags":[
        "nutritionist",
        "trainer"
    ],
    "sg:website":"www.sandiegopremiertraining.com",
    "wof:name":"San Diego Premier Training",
    "wof:placetype":"venue"
},
  "geometry": {"coordinates":[-117.266476,33.102899],"type":"Point"}
}