{
  "type": "Feature",
  "properties": {
    "iso:country":"US",
    "sg:address":"12432 Lampson Ave",
    "sg:city":"Garden Grove",
    "sg:classifiers":[
        {
            "category":"Restaurant",
            "type":"Food & Drink"
        }
    ],
    "sg:phone":"+1 714 539 4258",
    "sg:postcode":"92842",
    "sg:province":"CA",
    "sg:tags":[
        "mexican"
    ],
    "wof:name":"El Rosario Carniceria y Taqueria",
    "wof:placetype":"venue"
},
  "geometry": {"coordinates":[-117.915831,33.781642],"type":"Point"}
}