{
  "type": "Feature",
  "properties": {
    "iso:country":"US",
    "sg:address":"2201 W Washington St",
    "sg:city":"Stockton",
    "sg:classifiers":[
        {
            "category":"Wholesale",
            "subcategory":"Metals & Minerals",
            "type":"Manufacturing & Wholesale Goods"
        }
    ],
    "sg:phone":"+1 209 939 9310",
    "sg:postcode":"95203",
    "sg:province":"CA",
    "sg:tags":[
        "center"
    ],
    "wof:name":"Alco Iron & Metal Company",
    "wof:placetype":"venue"
},
  "geometry": {"coordinates":[-121.321455,37.945246],"type":"Point"}
}