{
  "type": "Feature",
  "properties": {
    "addr:full":"350 Kiely Blvd San Jose CA 95129",
    "addr:housenumber":"350",
    "addr:postcode":"95129",
    "addr:street":"Kiely Blvd",
    "iso:country":"US",
    "sg:address":"350 Kiely Blvd",
    "sg:city":"San Jose",
    "sg:classifiers":[
        {
            "category":"Retail",
            "subcategory":"Auto Repair",
            "type":"Services"
        }
    ],
    "sg:phone":"+1 408 246 4335",
    "sg:postcode":"95129",
    "sg:province":"CA",
    "sg:tags":[
        "repairing",
        "automobile",
        "radiator"
    ],
    "wof:name":"A-1 Radiator",
    "wof:placetype":"venue"
},
  "geometry": {"coordinates":[-121.975385,37.320692],"type":"Point"}
}