{
  "type": "Feature",
  "properties": {
    "addr:full":"11486 C Ave Auburn CA 95603",
    "addr:housenumber":"11486",
    "addr:postcode":"ca 95603",
    "addr:street":"C Ave",
    "iso:country":"US",
    "sg:address":"11486 C Ave",
    "sg:city":"Auburn",
    "sg:classifiers":[
        {
            "category":"Personal",
            "subcategory":"Beauty Salon",
            "type":"Services"
        }
    ],
    "sg:phone":"+1 530 885 2290",
    "sg:postcode":"95603",
    "sg:province":"CA",
    "wof:name":"Patti's C Avenue Hair Studio",
    "wof:placetype":"venue"
},
  "geometry": {"coordinates":[-121.10404200000001,38.938689],"type":"Point"}
}