{
  "type": "Feature",
  "properties": {
    "addr:full":"1101 Airport Rd Imperial CA 92251",
    "addr:housenumber":"1101",
    "addr:postcode":"92251",
    "addr:street":"Airport Rd",
    "iso:country":"US",
    "sg:address":"1101 Airport Rd",
    "sg:city":"Imperial",
    "sg:classifiers":[
        {
            "category":"Organizations",
            "subcategory":"Professional Association",
            "type":"Services"
        }
    ],
    "sg:phone":"+1 760 355 2844",
    "sg:postcode":"92251",
    "sg:province":"CA",
    "wof:name":"American Heart Assn",
    "wof:placetype":"venue"
},
  "geometry": {"coordinates":[-115.57077700000001,32.838091],"type":"Point"}
}