{
  "type": "Feature",
  "properties": {
    "addr:full":"420 40th, Oakland, CA",
    "iso:country":"US",
    "name:eng_x_preferred":[
        "1-2-3-4 Go! Records"
    ],
    "wof:name":"1-2-3-4 Go! Records",
    "wof:placetype":"venue"
},
  "geometry": {"coordinates":[-122.197811,37.785199],"type":"Point"}
}