{
  "type": "Feature",
  "properties": {
    "iso:country":"US",
    "sg:address":"22342 Ave Empresa",
    "sg:city":"Rcho Sta Marg",
    "sg:classifiers":[
        {
            "category":"Freight",
            "type":"Transportation"
        }
    ],
    "sg:phone":"+1 949 766 0275",
    "sg:postcode":"92688",
    "sg:province":"CA",
    "wof:name":"Freight Brokers Inc",
    "wof:placetype":"venue"
},
  "geometry": {"coordinates":[-117.607185,33.637007],"type":"Point"}
}