{
  "type": "Feature",
  "properties": {
    "addr:full":"3200 Willow Pass Rd Concord CA 94519",
    "addr:housenumber":"3200",
    "addr:postcode":"94519",
    "addr:street":"Willow Pass Rd",
    "iso:country":"US",
    "sg:address":"3200 Willow Pass Rd",
    "sg:city":"Concord",
    "sg:classifiers":[
        {
            "category":"Food & Beverages",
            "subcategory":"Groceries & Convenience Stores",
            "type":"Retail Goods"
        }
    ],
    "sg:phone":"+1 925 685 4211",
    "sg:postcode":"94519",
    "sg:province":"CA",
    "sg:tags":[
        "alcoholic"
    ],
    "wof:name":"Century Market",
    "wof:placetype":"venue"
},
  "geometry": {"coordinates":[-122.01776700000001,37.982293],"type":"Point"}
}