{
  "type": "Feature",
  "properties": {
    "addr:full":"8670 Wilshire Blvd Beverly Hills CA 90211",
    "addr:housenumber":"8670",
    "addr:postcode":"90211",
    "addr:street":"Wilshire Blvd",
    "iso:country":"US",
    "sg:address":"8670 Wilshire Blvd",
    "sg:city":"Beverly Hills",
    "sg:classifiers":[
        {
            "category":"Cafe",
            "type":"Food & Drink"
        },
        {
            "category":"Restaurant",
            "type":"Food & Drink"
        }
    ],
    "sg:menulink":"http://www.allmenus.com/ca/los-angeles/33518-cafe-alexander/menu/",
    "sg:phone":"+1 310 652 2210",
    "sg:postcode":"90211",
    "sg:province":"CA",
    "sg:tags":[
        "american"
    ],
    "wof:name":"Cafe Alexander",
    "wof:placetype":"venue"
},
  "geometry": {"coordinates":[-118.380661,34.066311],"type":"Point"}
}