{
  "type": "Feature",
  "properties": {
    "addr:full":"2066 Clarmar Way San Jose CA 95128",
    "addr:housenumber":"2066",
    "addr:postcode":"95128",
    "addr:street":"Clarmar Way",
    "iso:country":"US",
    "sg:address":"2066 Clarmar Way",
    "sg:city":"San Jose",
    "sg:classifiers":[
        {
            "category":"Professional",
            "subcategory":"Management & Consulting",
            "type":"Services"
        }
    ],
    "sg:phone":"+1 408 298 8850",
    "sg:postcode":"95128",
    "sg:province":"CA",
    "sg:tags":[
        "consultant",
        "business"
    ],
    "wof:name":"Neilsen Consulting",
    "wof:placetype":"venue"
},
  "geometry": {"coordinates":[-121.93429999999999,37.32639],"type":"Point"}
}