{
  "type": "Feature",
  "properties": {
    "addr:full":"6830 Via del Oro San Jose CA 95119",
    "addr:housenumber":"6830",
    "addr:postcode":"95119",
    "addr:street":"Via Del Oro",
    "iso:country":"US",
    "sg:address":"6830 Via del Oro",
    "sg:city":"San Jose",
    "sg:classifiers":[
        {
            "category":"Professional",
            "subcategory":"Computer Services",
            "type":"Services"
        }
    ],
    "sg:phone":"+1 408 448 4304",
    "sg:postcode":"95119",
    "sg:province":"CA",
    "sg:tags":[
        "internet"
    ],
    "wof:name":"Sage Technologies Biotech",
    "wof:placetype":"venue"
},
  "geometry": {"coordinates":[-121.77780300000001,37.231871],"type":"Point"}
}