{
  "type": "Feature",
  "properties": {
    "addr:full":"2125 8th Ave Oakland CA 94606",
    "addr:housenumber":"2125",
    "addr:postcode":"94606",
    "addr:street":"8Th Ave",
    "iso:country":"US",
    "sg:address":"2125 8th Ave",
    "sg:city":"Oakland",
    "sg:classifiers":[
        {
            "category":"Health Services",
            "subcategory":"Health Practitioner",
            "type":"Services"
        }
    ],
    "sg:phone":"+1 510 832 0718",
    "sg:postcode":"94606",
    "sg:province":"CA",
    "sg:tags":[
        "acupuncture"
    ],
    "wof:name":"Ben Liu Acupuncture",
    "wof:placetype":"venue"
},
  "geometry": {"coordinates":[-122.244733,37.798438],"type":"Point"}
}