{
  "type": "Feature",
  "properties": {
    "iso:country":"US",
    "sg:address":"2325 3rd St Ste 214",
    "sg:city":"San Francisco",
    "sg:classifiers":[
        {
            "category":"Wholesale",
            "subcategory":"Stationery",
            "type":"Manufacturing & Wholesale Goods"
        },
        {
            "category":"Shopping",
            "subcategory":"Bridal",
            "type":"Retail Goods"
        }
    ],
    "sg:phone":"+1 415 252 7635",
    "sg:postcode":"94107",
    "sg:province":"CA",
    "sg:tags":[
        "card"
    ],
    "sg:website":"www.emmarosepapery.com",
    "wof:name":"EmmaRose Papery",
    "wof:placetype":"venue"
},
  "geometry": {"coordinates":[-122.388374,37.759574],"type":"Point"}
}