{
  "type": "Feature",
  "properties": {
    "addr:full":"114 W Colorado Blvd Monrovia CA 91016",
    "addr:housenumber":"114",
    "addr:postcode":"91016",
    "addr:street":"W Colorado Blvd",
    "iso:country":"US",
    "sg:address":"114 W Colorado Blvd",
    "sg:city":"Monrovia",
    "sg:classifiers":[
        {
            "category":"Utilities",
            "subcategory":"Telephone",
            "type":"Services"
        }
    ],
    "sg:phone":"+1 626 358 1057",
    "sg:postcode":"91016",
    "sg:province":"CA",
    "sg:tags":[
        "web",
        "design",
        "provider"
    ],
    "wof:name":"Internetwork Designs Inc",
    "wof:placetype":"venue"
},
  "geometry": {"coordinates":[-118.001232,34.14582],"type":"Point"}
}