{
  "type": "Feature",
  "properties": {
    "addr:full":"231 Salinas St Salinas CA 93901",
    "addr:housenumber":"231",
    "addr:postcode":"93901",
    "addr:street":"Salinas St",
    "iso:country":"US",
    "sg:address":"231 Salinas St",
    "sg:city":"Salinas",
    "sg:classifiers":[
        {
            "category":"Bars & Pubs",
            "subcategory":"Lounge",
            "type":"Food & Drink"
        },
        {
            "category":"Restaurant",
            "type":"Food & Drink"
        }
    ],
    "sg:phone":"+1 831 424 3212",
    "sg:postcode":"93901",
    "sg:province":"CA",
    "sg:tags":[
        "cocktail"
    ],
    "wof:name":"Jaime's Lounge",
    "wof:placetype":"venue"
},
  "geometry": {"coordinates":[-121.656176,36.67427],"type":"Point"}
}