{
  "type": "Feature",
  "properties": {
    "addr:full":"830 Wagon Wheel Rd Oxnard CA 93036",
    "addr:housenumber":"830",
    "addr:postcode":"93036",
    "addr:street":"Wagon Wheel Rd",
    "iso:country":"US",
    "sg:address":"830 Wagon Wheel Rd",
    "sg:city":"Oxnard",
    "sg:classifiers":[
        {
            "category":"Wholesale",
            "subcategory":"Durable Goods & Equipment",
            "type":"Manufacturing & Wholesale Goods"
        }
    ],
    "sg:phone":"+1 805 983 3188",
    "sg:postcode":"93036",
    "sg:province":"CA",
    "wof:name":"Coast Hockey Supply",
    "wof:placetype":"venue"
},
  "geometry": {"coordinates":[-119.179349,34.233441],"type":"Point"}
}