{
  "type": "Feature",
  "properties": {
    "iso:country":"US",
    "sg:address":"5870 Moraga Ave",
    "sg:city":"Piedmont",
    "sg:classifiers":[
        {
            "category":"Building & Trades",
            "subcategory":"Construction",
            "type":"Services"
        }
    ],
    "sg:phone":"+1 510 595 0771",
    "sg:postcode":"94611",
    "sg:province":"CA",
    "sg:tags":[
        "carpenter"
    ],
    "wof:name":"David Ruechelle Finish Crpntry",
    "wof:placetype":"venue"
},
  "geometry": {"coordinates":[-122.218746,37.832987],"type":"Point"}
}