{
  "type": "Feature",
  "properties": {
    "iso:country":"US",
    "sg:address":"5108 Calmview Ave",
    "sg:city":"Baldwin Park",
    "sg:classifiers":[
        {
            "category":"Manufacturing",
            "subcategory":"Metals",
            "type":"Manufacturing & Wholesale Goods"
        }
    ],
    "sg:phone":"+1 626 960 1821",
    "sg:postcode":"91706",
    "sg:province":"CA",
    "sg:tags":[
        "hardware"
    ],
    "wof:name":"L & M Metal Products Inc",
    "wof:placetype":"venue"
},
  "geometry": {"coordinates":[-117.947834,34.104722],"type":"Point"}
}