{
  "type": "Feature",
  "properties": {
    "addr:full":"4526 Chateau Dr San Diego CA 92117",
    "addr:housenumber":"4526",
    "addr:postcode":"92117",
    "addr:street":"Chateau Dr",
    "iso:country":"US",
    "sg:address":"4526 Chateau Dr",
    "sg:city":"San Diego",
    "sg:classifiers":[
        {
            "category":"Building & Trades",
            "subcategory":"Construction",
            "type":"Services"
        }
    ],
    "sg:phone":"+1 858 650 0360",
    "sg:postcode":"92117",
    "sg:province":"CA",
    "sg:tags":[
        "fence",
        "contractor"
    ],
    "wof:name":"Outlaw Fence Co",
    "wof:placetype":"venue"
},
  "geometry": {"coordinates":[-117.191592,32.829413],"type":"Point"}
}