{
  "type": "Feature",
  "properties": {
    "iso:country":"US",
    "sg:address":"1448 W 178th St",
    "sg:city":"Gardena",
    "sg:classifiers":[
        {
            "category":"Manufacturing",
            "subcategory":"Printing",
            "type":"Manufacturing & Wholesale Goods"
        }
    ],
    "sg:phone":"+1 310 768 1662",
    "sg:postcode":"90248",
    "sg:province":"CA",
    "sg:tags":[
        "commercial"
    ],
    "wof:name":"Deluxe Printing",
    "wof:placetype":"venue"
},
  "geometry": {"coordinates":[-118.301014,33.869149],"type":"Point"}
}