{
  "type": "Feature",
  "properties": {
    "addr:full":"1613 E Chapman Ave Fullerton CA 92831",
    "addr:housenumber":"1613",
    "addr:postcode":"92831",
    "addr:street":"E Chapman Ave",
    "iso:country":"US",
    "sg:address":"1613 E Chapman Ave",
    "sg:city":"Fullerton",
    "sg:classifiers":[
        {
            "category":"Insurance",
            "subcategory":"Insurance Agent",
            "type":"Services"
        }
    ],
    "sg:phone":"+1 714 525 2168",
    "sg:postcode":"92831",
    "sg:province":"CA",
    "wof:name":"Allstate Insurance",
    "wof:placetype":"venue"
},
  "geometry": {"coordinates":[-117.89847899999999,33.874231],"type":"Point"}
}