{
  "type": "Feature",
  "properties": {
    "iso:country":"US",
    "sg:address":"3450 Arden Rd",
    "sg:city":"Hayward",
    "sg:classifiers":[
        {
            "category":"Wholesale",
            "subcategory":"Durable Goods & Equipment",
            "type":"Manufacturing & Wholesale Goods"
        }
    ],
    "sg:phone":"+1 510 264 9696",
    "sg:postcode":"94545",
    "sg:province":"CA",
    "sg:tags":[
        "exporter"
    ],
    "wof:name":"Meitetsu Inc",
    "wof:placetype":"venue"
},
  "geometry": {"coordinates":[-122.114481,37.622242],"type":"Point"}
}