{
  "type": "Feature",
  "properties": {
    "addr:full":"1700 Palopinto Ave Glendora CA 91741",
    "addr:housenumber":"1700",
    "addr:postcode":"91741",
    "addr:street":"Palopinto Ave",
    "iso:country":"US",
    "sg:address":"1700 Palopinto Ave",
    "sg:city":"Glendora",
    "sg:classifiers":[
        {
            "category":"Organizations",
            "subcategory":"Religious Organization",
            "type":"Services"
        }
    ],
    "sg:phone":"+1 626 914 4833",
    "sg:postcode":"91741",
    "sg:province":"CA",
    "sg:tags":[
        "church"
    ],
    "sg:website":"www.glenkirkchurch.org",
    "wof:name":"Glenkirk Presbyterian Church",
    "wof:placetype":"venue"
},
  "geometry": {"coordinates":[-117.83292899999999,34.132495],"type":"Point"}
}