{
  "type": "Feature",
  "properties": {
    "iso:country":"US",
    "sg:address":"400 S Victory Blvd",
    "sg:city":"Burbank",
    "sg:classifiers":[
        {
            "category":"Professional",
            "subcategory":"Advertising",
            "type":"Services"
        }
    ],
    "sg:phone":"+1 818 955 5704",
    "sg:postcode":"91502",
    "sg:province":"CA",
    "sg:tags":[
        "medium",
        "buying"
    ],
    "sg:website":"www.newmarkcommunications.com",
    "wof:name":"Newmark Communications",
    "wof:placetype":"venue"
},
  "geometry": {"coordinates":[-118.314564,34.170184],"type":"Point"}
}