{
  "type": "Feature",
  "properties": {
    "iso:country":"US",
    "sg:address":"2183 Mission St",
    "sg:city":"San Francisco",
    "sg:classifiers":[
        {
            "category":"Arts & Performance",
            "subcategory":"Art Gallery",
            "type":"Entertainment"
        },
        {
            "category":"Arts & Performance",
            "subcategory":"Music",
            "type":"Entertainment"
        }
    ],
    "sg:phone":"+1 415 255 7227",
    "sg:postcode":"94110",
    "sg:province":"CA",
    "sg:tags":[
        "venue"
    ],
    "sg:website":"www.sf-submission.com/",
    "wof:name":"Sub-Mission Gallery",
    "wof:placetype":"venue"
},
  "geometry": {"coordinates":[-122.419032,37.762131],"type":"Point"}
}