{
  "type": "Feature",
  "properties": {
    "iso:country":"US",
    "sg:address":"31813 Mission Trl",
    "sg:city":"Lake Elsinore",
    "sg:classifiers":[
        {
            "category":"Professional",
            "subcategory":"Accounting & Tax Preparation",
            "type":"Services"
        }
    ],
    "sg:phone":"+1 951 471 3959",
    "sg:postcode":"92595",
    "sg:province":"CA",
    "sg:tags":[
        "return",
        "filing"
    ],
    "wof:name":"J B Svc",
    "wof:placetype":"venue"
},
  "geometry": {"coordinates":[-117.298632,33.657486],"type":"Point"}
}