{
  "type": "Feature",
  "properties": {
    "iso:country":"US",
    "sfac:artist":"Igarashi, Takenobu",
    "sfac:created_at":"01/01/1970 12:33:27 AM +0000",
    "sfac:display_dimensions":"16 in. x 44 in.",
    "sfac:location_description":"City Department : Laguna Honda : North Residence : Mezzanine : Southwest Wall #2",
    "sfac:medium":"Wood and powder coated stainless steel",
    "sfac:revision":"2-693011d6d5b3549be4dc7f8d52b6a38e",
    "sfac:title":"Untitled [wood relief]",
    "wof:name":"Untitled [wood relief]",
    "wof:placetype":"venue"
},
  "geometry": {"coordinates":[-122.4556651,37.7478586],"type":"Point"}
}