{
  "type": "Feature",
  "properties": {
    "addr:full":"1530 W Commonwealth Ave Fullerton CA 92833",
    "addr:housenumber":"1530",
    "addr:postcode":"92833",
    "addr:street":"W Commonwealth Ave",
    "iso:country":"US",
    "sg:address":"1530 W Commonwealth Ave",
    "sg:city":"Fullerton",
    "sg:classifiers":[
        {
            "category":"Manufacturing",
            "subcategory":"Retail Goods",
            "type":"Manufacturing & Wholesale Goods"
        }
    ],
    "sg:phone":"+1 714 992 2123",
    "sg:postcode":"92833",
    "sg:province":"CA",
    "sg:tags":[
        "florist",
        "product",
        "mfg"
    ],
    "sg:website":"www.kingsflowersfullerton.com",
    "wof:name":"King's Flowers",
    "wof:placetype":"venue"
},
  "geometry": {"coordinates":[-117.94899700000001,33.870201],"type":"Point"}
}