{
  "type": "Feature",
  "properties": {
    "iso:country":"US",
    "sg:address":"4925 el Camino Ave",
    "sg:city":"Carmichael",
    "sg:classifiers":[
        {
            "category":"Building & Trades",
            "subcategory":"Cleaning & Sanitation",
            "type":"Services"
        }
    ],
    "sg:phone":"+1 916 488 1654",
    "sg:postcode":"95608",
    "sg:province":"CA",
    "sg:tags":[
        "window"
    ],
    "wof:name":"Clear Vision Window Cleaning",
    "wof:placetype":"venue"
},
  "geometry": {"coordinates":[-121.348601,38.610132],"type":"Point"}
}