{
  "type": "Feature",
  "properties": {
    "iso:country":"US",
    "sg:address":"551 N Farmersville Blvd",
    "sg:city":"Farmersville",
    "sg:classifiers":[
        {
            "category":"Restaurant",
            "type":"Food & Drink"
        }
    ],
    "sg:phone":"+1 559 747 0467",
    "sg:postcode":"93223",
    "sg:province":"CA",
    "sg:tags":[
        "mexican"
    ],
    "wof:name":"Ana Maria's",
    "wof:placetype":"venue"
},
  "geometry": {"coordinates":[-119.20713000000001,36.301739],"type":"Point"}
}