{
  "type": "Feature",
  "properties": {
    "iso:country":"US",
    "sg:address":"15939 Old Valley Blvd",
    "sg:city":"La Puente",
    "sg:classifiers":[
        {
            "category":"Shopping",
            "type":"Retail Goods"
        }
    ],
    "sg:phone":"+1 626 918 2519",
    "sg:postcode":"91744",
    "sg:province":"CA",
    "sg:tags":[
        "art",
        "gallery",
        "dealer"
    ],
    "wof:name":"Scoville Art & Signs",
    "wof:placetype":"venue"
},
  "geometry": {"coordinates":[-117.951836,34.018377],"type":"Point"}
}