{
  "type": "Feature",
  "properties": {
    "iso:country":"US",
    "sg:address":"3445 American River Dr",
    "sg:city":"Sacramento",
    "sg:classifiers":[
        {
            "category":"Professional",
            "subcategory":"Business Services",
            "type":"Services"
        }
    ],
    "sg:phone":"+1 916 974 3355",
    "sg:postcode":"95864",
    "sg:province":"CA",
    "sg:tags":[
        "holding"
    ],
    "wof:name":"Sierra Holdings",
    "wof:placetype":"venue"
},
  "geometry": {"coordinates":[-121.385389,38.569776],"type":"Point"}
}