{
  "type": "Feature",
  "properties": {
    "iso:country":"US",
    "sg:address":"1090 N Western Ave",
    "sg:city":"San Pedro",
    "sg:classifiers":[
        {
            "category":"Fast Food",
            "type":"Food & Drink"
        }
    ],
    "sg:phone":"+1 800 786 1000",
    "sg:postcode":"90731",
    "sg:province":"CA",
    "sg:tags":[
        "burger"
    ],
    "sg:website":"www.in-n-out.com",
    "wof:name":"In-N-Out Burger",
    "wof:placetype":"venue"
},
  "geometry": {"coordinates":[-118.308903,33.753596],"type":"Point"}
}