{
  "type": "Feature",
  "properties": {
    "iso:country":"US",
    "sg:address":"674 Redondo Ave",
    "sg:city":"Long Beach",
    "sg:classifiers":[
        {
            "category":"Coffee & Tea",
            "type":"Food & Drink"
        },
        {
            "category":"Bars & Pubs",
            "subcategory":"Hookah Bar",
            "type":"Food & Drink"
        }
    ],
    "sg:phone":"+1 562 434 6799",
    "sg:postcode":"90814",
    "sg:province":"CA",
    "sg:website":"www.exhalecafe.com",
    "wof:name":"Exhale",
    "wof:placetype":"venue"
},
  "geometry": {"coordinates":[-118.15241,33.774873],"type":"Point"}
}