{
  "type": "Feature",
  "properties": {
    "iso:country":"US",
    "sg:address":"1455 Market Street",
    "sg:city":"San Francisco",
    "sg:classifiers":[
        {
            "category":"Food & Beverages",
            "subcategory":"Groceries & Convenience Stores",
            "type":"Retail Goods"
        }
    ],
    "sg:phone":"+1 415 861 6545",
    "sg:postcode":"94103",
    "sg:province":"CA",
    "wof:name":"Russell's Convenience Store",
    "wof:placetype":"venue"
},
  "geometry": {"coordinates":[-122.41799899999999,37.776001],"type":"Point"}
}