{
  "type": "Feature",
  "properties": {
    "iso:country":"US",
    "sg:address":"308 S the Strand",
    "sg:city":"Oceanside",
    "sg:classifiers":[
        {
            "category":"Real Estate",
            "subcategory":"Real Estate Operator",
            "type":"Services"
        }
    ],
    "sg:phone":"+1 760 721 8000",
    "sg:postcode":"92054",
    "sg:province":"CA",
    "sg:tags":[
        "apartment"
    ],
    "sg:website":"http://LandsEnd.com",
    "wof:name":"Lands End",
    "wof:placetype":"venue"
},
  "geometry": {"coordinates":[-117.379997,33.189899],"type":"Point"}
}