{
  "type": "Feature",
  "properties": {
    "iso:country":"US",
    "sg:address":"2555 Huntington Dr",
    "sg:city":"San Marino",
    "sg:classifiers":[
        {
            "category":"Restaurant",
            "type":"Food & Drink"
        },
        {
            "category":"Food & Beverages",
            "subcategory":"Bakery",
            "type":"Retail Goods"
        }
    ],
    "sg:phone":"+1 626 793 4114",
    "sg:postcode":"91108",
    "sg:province":"CA",
    "sg:tags":[
        "sandwich",
        "pizza"
    ],
    "sg:website":"tonyspizzasanmarino.com",
    "wof:name":"Tony's Pizza",
    "wof:placetype":"venue"
},
  "geometry": {"coordinates":[-118.099628,34.124432],"type":"Point"}
}