{
  "type": "Feature",
  "properties": {
    "iso:country":"US",
    "sg:address":"650 S Westlake Blvd",
    "sg:city":"Thousand Oaks",
    "sg:classifiers":[
        {
            "category":"Travel",
            "subcategory":"Travel Agent",
            "type":"Entertainment"
        }
    ],
    "sg:phone":"+1 805 778 1600",
    "sg:postcode":"91362",
    "sg:province":"CA",
    "sg:tags":[
        "agency",
        "bureau"
    ],
    "wof:name":"Travel Store Inc",
    "wof:placetype":"venue"
},
  "geometry": {"coordinates":[-118.82332,34.160089],"type":"Point"}
}