{
  "type": "Feature",
  "properties": {
    "iso:country":"US",
    "sg:address":"7005 Brockton Ave",
    "sg:city":"Riverside",
    "sg:classifiers":[
        {
            "category":"Organizations",
            "subcategory":"Religious Organization",
            "type":"Services"
        }
    ],
    "sg:phone":"+1 951 781 9855",
    "sg:postcode":"92506",
    "sg:province":"CA",
    "sg:tags":[
        "church"
    ],
    "sg:website":"www.stcofa.org",
    "wof:name":"St Catherine's Catholic",
    "wof:placetype":"venue"
},
  "geometry": {"coordinates":[-117.395539,33.944255],"type":"Point"}
}