{
  "type": "Feature",
  "properties": {
    "iso:country":"US",
    "sg:address":"10745 Riverside Dr Ste B",
    "sg:city":"North Hollywood",
    "sg:classifiers":[
        {
            "category":"Health Services",
            "subcategory":"Dentist",
            "type":"Services"
        }
    ],
    "sg:phone":"+1 818 980 2887",
    "sg:postcode":"91602",
    "sg:province":"CA",
    "wof:name":"Esteban D. Bonilla, DDS",
    "wof:placetype":"venue"
},
  "geometry": {"coordinates":[-118.365098,34.152566],"type":"Point"}
}