{
  "type": "Feature",
  "properties": {
    "addr:full":"27221 McCall Blvd Sun City CA 92585",
    "addr:housenumber":"27221",
    "addr:postcode":"92585",
    "addr:street":"Mccall Blvd",
    "iso:country":"US",
    "sg:address":"27221 McCall Blvd",
    "sg:city":"Sun City",
    "sg:classifiers":[
        {
            "category":"Organizations",
            "subcategory":"Community Association",
            "type":"Services"
        }
    ],
    "sg:phone":"+1 951 679 9493",
    "sg:postcode":"92585",
    "sg:province":"CA",
    "sg:tags":[
        "fraternal"
    ],
    "wof:name":"Masonic Lodge",
    "wof:placetype":"venue"
},
  "geometry": {"coordinates":[-117.185985,33.715112],"type":"Point"}
}