{
  "type": "Feature",
  "properties": {
    "iso:country":"US",
    "sg:address":"222 N I St",
    "sg:city":"Lompoc",
    "sg:classifiers":[
        {
            "category":"Organizations",
            "subcategory":"Religious Organization",
            "type":"Services"
        }
    ],
    "sg:phone":"+1 805 735 3079",
    "sg:postcode":"93436",
    "sg:province":"CA",
    "sg:tags":[
        "church"
    ],
    "wof:name":"St James Missionary Baptist",
    "wof:placetype":"venue"
},
  "geometry": {"coordinates":[-120.459108,34.641002],"type":"Point"}
}