{
  "type": "Feature",
  "properties": {
    "addr:full":"1040 N Batavia St Orange CA 92868",
    "addr:housenumber":"1040",
    "addr:postcode":"92868",
    "addr:street":"N Batavia St",
    "iso:country":"US",
    "sg:address":"1040 N Batavia St",
    "sg:city":"Orange",
    "sg:classifiers":[
        {
            "category":"Shopping",
            "subcategory":"Computers & Home Electronics",
            "type":"Retail Goods"
        }
    ],
    "sg:phone":"+1 714 744 8383",
    "sg:postcode":"92868",
    "sg:province":"CA",
    "sg:tags":[
        "equipment",
        "dealer"
    ],
    "wof:name":"Paramount Disc Mfg",
    "wof:placetype":"venue"
},
  "geometry": {"coordinates":[-117.861807,33.803537],"type":"Point"}
}