{
  "type": "Feature",
  "properties": {
    "iso:country":"US",
    "sg:address":"666 Bridgeway",
    "sg:city":"Sausalito",
    "sg:classifiers":[
        {
            "category":"Arts & Performance",
            "subcategory":"Art Gallery",
            "type":"Entertainment"
        }
    ],
    "sg:phone":"+1 415 332 3805",
    "sg:postcode":"94965",
    "sg:province":"CA",
    "wof:name":"Royal Arts Company",
    "wof:placetype":"venue"
},
  "geometry": {"coordinates":[-122.47875500000001,37.855273],"type":"Point"}
}