{
  "type": "Feature",
  "properties": {
    "iso:country":"US",
    "sg:address":"20991 Carrolton Ave",
    "sg:city":"Ripon",
    "sg:classifiers":[
        {
            "category":"Building & Trades",
            "subcategory":"Landscaping Services",
            "type":"Services"
        }
    ],
    "sg:phone":"+1 209 599 6333",
    "sg:postcode":"95366",
    "sg:province":"CA",
    "sg:tags":[
        "lawn",
        "garden",
        "janitorial"
    ],
    "wof:name":"Realestate Services",
    "wof:placetype":"venue"
},
  "geometry": {"coordinates":[-121.069527,37.765572],"type":"Point"}
}