{
  "type": "Feature",
  "properties": {
    "addr:full":"138 Pinedale Ave Sacramento CA 95838",
    "addr:housenumber":"138",
    "addr:postcode":"95838",
    "addr:street":"Pinedale Ave",
    "iso:country":"US",
    "sg:address":"138 Pinedale Ave",
    "sg:city":"Sacramento",
    "sg:classifiers":[
        {
            "category":"Food & Beverages",
            "subcategory":"Groceries & Convenience Stores",
            "type":"Retail Goods"
        }
    ],
    "sg:phone":"+1 916 289 4097",
    "sg:postcode":"95838",
    "sg:province":"CA",
    "wof:name":"Natomas Oriental Market",
    "wof:placetype":"venue"
},
  "geometry": {"coordinates":[-121.462667,38.658035],"type":"Point"}
}