{
  "type": "Feature",
  "properties": {
    "addr:full":"368 E Date Ave Porterville CA 93257",
    "addr:housenumber":"368",
    "addr:postcode":"93257",
    "addr:street":"E Date Ave",
    "iso:country":"US",
    "sg:address":"368 E Date Ave",
    "sg:city":"Porterville",
    "sg:classifiers":[
        {
            "category":"Social Services",
            "type":"Services"
        }
    ],
    "sg:phone":"+1 559 782 8645",
    "sg:postcode":"93257",
    "sg:province":"CA",
    "sg:tags":[
        "organization",
        "welfare"
    ],
    "wof:name":"Comision Honorifica Mexicana",
    "wof:placetype":"venue"
},
  "geometry": {"coordinates":[-119.009896,36.058607],"type":"Point"}
}