{
  "type": "Feature",
  "properties": {
    "iso:country":"US",
    "sg:address":"14074 Sweet Grass Ln",
    "sg:city":"Chino Hills",
    "sg:classifiers":[
        {
            "category":"Building & Trades",
            "subcategory":"Construction",
            "type":"Services"
        }
    ],
    "sg:phone":"+1 909 902 9018",
    "sg:postcode":"91709",
    "sg:province":"CA",
    "sg:tags":[
        "general",
        "contractor"
    ],
    "wof:name":"P M Construction",
    "wof:placetype":"venue"
},
  "geometry": {"coordinates":[-117.76388300000001,33.998173],"type":"Point"}
}