{
  "type": "Feature",
  "properties": {
    "addr:full":"114 S Campus Ave Ontario CA 91761",
    "addr:housenumber":"114",
    "addr:postcode":"91761",
    "addr:street":"S Campus Ave",
    "iso:country":"US",
    "sg:address":"114 S Campus Ave",
    "sg:city":"Ontario",
    "sg:classifiers":[
        {
            "category":"Home & Garden",
            "subcategory":"Household Appliances",
            "type":"Retail Goods"
        }
    ],
    "sg:phone":"+1 909 986 9789",
    "sg:postcode":"91761",
    "sg:province":"CA",
    "sg:website":"www.cagles.com",
    "wof:name":"Cagle's Appliances",
    "wof:placetype":"venue"
},
  "geometry": {"coordinates":[-117.64143300000001,34.062514],"type":"Point"}
}