{
  "type": "Feature",
  "properties": {
    "addr:full":"1115 Cowper St Berkeley CA 94702",
    "addr:housenumber":"1115",
    "addr:postcode":"94702",
    "addr:street":"Cowper St",
    "iso:country":"US",
    "sg:address":"1115 Cowper St",
    "sg:city":"Berkeley",
    "sg:classifiers":[
        {
            "category":"Building & Trades",
            "subcategory":"Landscaping Services",
            "type":"Services"
        }
    ],
    "sg:phone":"+1 510 848 6752",
    "sg:postcode":"94702",
    "sg:province":"CA",
    "sg:tags":[
        "tree"
    ],
    "wof:name":"Arbor Artist",
    "wof:placetype":"venue"
},
  "geometry": {"coordinates":[-122.29136200000001,37.867249],"type":"Point"}
}