{
  "type": "Feature",
  "properties": {
    "iso:country":"US",
    "sg:address":"12718 Schabarum Ave",
    "sg:city":"Baldwin Park",
    "sg:classifiers":[
        {
            "category":"Utilities",
            "subcategory":"Mobile Phone",
            "type":"Services"
        }
    ],
    "sg:phone":"+1 626 614 0188",
    "sg:postcode":"91706",
    "sg:province":"CA",
    "sg:tags":[
        "telephone",
        "cellular"
    ],
    "sg:website":"www.beyondcell.com",
    "wof:name":"Beyond Cell Intl",
    "wof:placetype":"venue"
},
  "geometry": {"coordinates":[-117.995378,34.080609],"type":"Point"}
}