{
  "type": "Feature",
  "properties": {
    "addr:full":"1290 Scott St El Cerrito CA 94530",
    "addr:housenumber":"1290",
    "addr:postcode":"94530",
    "addr:street":"Scott St",
    "iso:country":"US",
    "sg:address":"1290 Scott St",
    "sg:city":"El Cerrito",
    "sg:classifiers":[
        {
            "category":"Organizations",
            "subcategory":"Community Association",
            "type":"Services"
        }
    ],
    "sg:phone":"+1 510 235 8312",
    "sg:postcode":"94530",
    "sg:province":"CA",
    "wof:name":"Camp Hermes",
    "wof:placetype":"venue"
},
  "geometry": {"coordinates":[-122.30186500000001,37.918084],"type":"Point"}
}