{
  "type": "Feature",
  "properties": {
    "iso:country":"US",
    "sg:address":"1036 2nd St",
    "sg:city":"Lafayette",
    "sg:classifiers":[
        {
            "category":"Arena",
            "subcategory":"Sports Club",
            "type":"Entertainment"
        }
    ],
    "sg:phone":"+1 866 852 8496",
    "sg:postcode":"94549",
    "sg:province":"CA",
    "sg:tags":[
        "basketball"
    ],
    "wof:name":"Norcal Elite Basketball Team",
    "wof:placetype":"venue"
},
  "geometry": {"coordinates":[-122.113634,37.893441],"type":"Point"}
}