{
  "type": "Feature",
  "properties": {
    "addr:full":"3201 20th Ave San Francisco CA 94132",
    "addr:housenumber":"3201",
    "addr:postcode":"94132",
    "addr:street":"20Th Ave",
    "iso:country":"US",
    "sg:address":"3201 20th Ave",
    "sg:city":"San Francisco",
    "sg:classifiers":[
        {
            "category":"Shopping",
            "subcategory":"Computers & Home Electronics",
            "type":"Retail Goods"
        }
    ],
    "sg:phone":"+1 415 731 3700",
    "sg:postcode":"94132",
    "sg:province":"CA",
    "sg:tags":[
        "equipment",
        "electronic",
        "supply"
    ],
    "sg:website":"www.goodguys.com",
    "wof:name":"Good Guys",
    "wof:placetype":"venue"
},
  "geometry": {"coordinates":[-122.475683,37.727745],"type":"Point"}
}