{
  "type": "Feature",
  "properties": {
    "iso:country":"US",
    "sg:address":"300 S Spring St",
    "sg:city":"Los Angeles",
    "sg:classifiers":[
        {
            "category":"Government",
            "subcategory":"Office",
            "type":"Public Place"
        }
    ],
    "sg:phone":"+1 213 346 6330",
    "sg:postcode":"90013",
    "sg:province":"CA",
    "sg:tags":[
        "sector",
        "regulation",
        "commercial"
    ],
    "wof:name":"Research Sttistical Analis Bur",
    "wof:placetype":"venue"
},
  "geometry": {"coordinates":[-118.248293,34.04882],"type":"Point"}
}