{
  "type": "Feature",
  "properties": {
    "addr:full":"6422 Magnolia Ave Riverside CA 92506",
    "addr:housenumber":"6422",
    "addr:postcode":"92506",
    "addr:street":"Magnolia Ave",
    "iso:country":"US",
    "sg:address":"6422 Magnolia Ave",
    "sg:city":"Riverside",
    "sg:classifiers":[
        {
            "category":"Personal",
            "subcategory":"Beauty Salon",
            "type":"Services"
        }
    ],
    "sg:phone":"+1 951 782 0669",
    "sg:postcode":"92506",
    "sg:province":"CA",
    "wof:name":"Javier's The Hair Salon",
    "wof:placetype":"venue"
},
  "geometry": {"coordinates":[-117.395571,33.954775],"type":"Point"}
}