{
  "type": "Feature",
  "properties": {
    "iso:country":"US",
    "sg:address":"706 Deep Valley Dr",
    "sg:city":"Palos Verdes Peninsula",
    "sg:classifiers":[
        {
            "category":"Manufacturing",
            "subcategory":"Printing",
            "type":"Manufacturing & Wholesale Goods"
        }
    ],
    "sg:phone":"+1 310 541 1789",
    "sg:postcode":"90274",
    "sg:province":"CA",
    "sg:tags":[
        "shop",
        "commercial"
    ],
    "wof:name":"Hillside Press Inc",
    "wof:placetype":"venue"
},
  "geometry": {"coordinates":[-118.37093,33.770333],"type":"Point"}
}