{
  "type": "Feature",
  "properties": {
    "iso:country":"US",
    "sg:address":"11601 Wilshire Blvd",
    "sg:city":"Los Angeles",
    "sg:classifiers":[
        {
            "category":"Utilities",
            "subcategory":"Telephone",
            "type":"Services"
        }
    ],
    "sg:phone":"+1 310 231 3537",
    "sg:postcode":"90025",
    "sg:province":"CA",
    "sg:tags":[
        "communications"
    ],
    "wof:name":"Valueflashcom Inc",
    "wof:placetype":"venue"
},
  "geometry": {"coordinates":[-118.460072,34.050095],"type":"Point"}
}