{
  "type": "Feature",
  "properties": {
    "iso:country":"US",
    "sg:address":"3921 California Way",
    "sg:city":"Livermore",
    "sg:classifiers":[
        {
            "category":"Building & Trades",
            "subcategory":"Construction",
            "type":"Services"
        },
        {
            "category":"Military Area",
            "subcategory":"Armory",
            "type":"Public Place"
        }
    ],
    "sg:phone":"+1 925 606 1363",
    "sg:postcode":"94550",
    "sg:province":"CA",
    "sg:tags":[
        "repair",
        "fence-sales",
        "fence",
        "contractor"
    ],
    "wof:name":"Apex Fence Co",
    "wof:placetype":"venue"
},
  "geometry": {"coordinates":[-121.75098300000001,37.682161],"type":"Point"}
}