{
  "type": "Feature",
  "properties": {
    "addr:full":"1397 Montgomery Rd Red Bluff CA 96080",
    "addr:housenumber":"1397",
    "addr:postcode":"96080",
    "addr:street":"Montgomery Rd",
    "iso:country":"US",
    "sg:address":"1397 Montgomery Rd",
    "sg:city":"Red Bluff",
    "sg:classifiers":[
        {
            "category":"Manufacturing",
            "subcategory":"Lumber",
            "type":"Manufacturing & Wholesale Goods"
        }
    ],
    "sg:phone":"+1 530 529 2121",
    "sg:postcode":"96080",
    "sg:province":"CA",
    "sg:tags":[
        "company",
        "logging"
    ],
    "wof:name":"Violetti Brothers Logging Co",
    "wof:placetype":"venue"
},
  "geometry": {"coordinates":[-122.2251,40.155659],"type":"Point"}
}