{
  "type": "Feature",
  "properties": {
    "addr:full":"3539 Adams Ave San Diego CA 92116",
    "addr:housenumber":"3539",
    "addr:postcode":"92116",
    "addr:street":"Adams Ave",
    "iso:country":"US",
    "sg:address":"3539 Adams Ave",
    "sg:city":"San Diego",
    "sg:classifiers":[
        {
            "category":"Personal",
            "subcategory":"Beauty Salon",
            "type":"Services"
        }
    ],
    "sg:phone":"+1 619 584 2845",
    "sg:postcode":"92116",
    "sg:province":"CA",
    "wof:name":"Haircuts Etc",
    "wof:placetype":"venue"
},
  "geometry": {"coordinates":[-117.117125,32.763244],"type":"Point"}
}