{
  "type": "Feature",
  "properties": {
    "iso:country":"US",
    "sg:address":"540 Barneveld Ave",
    "sg:city":"San Francisco",
    "sg:classifiers":[
        {
            "category":"Manufacturing",
            "subcategory":"Printing",
            "type":"Manufacturing & Wholesale Goods"
        }
    ],
    "sg:phone":"+1 415 642 4278",
    "sg:postcode":"94124",
    "sg:province":"CA",
    "sg:tags":[
        "screen"
    ],
    "wof:name":"Native Grafix",
    "wof:placetype":"venue"
},
  "geometry": {"coordinates":[-122.40447399999999,37.739366],"type":"Point"}
}