{
  "type": "Feature",
  "properties": {
    "addr:full":"425 Coloma St Sausalito CA 94965",
    "addr:housenumber":"425",
    "addr:postcode":"94965",
    "addr:street":"Coloma St",
    "iso:country":"US",
    "sg:address":"425 Coloma St",
    "sg:city":"Sausalito",
    "sg:classifiers":[
        {
            "category":"Professional",
            "subcategory":"Business Services",
            "type":"Services"
        }
    ],
    "sg:phone":"+1 415 332 6289",
    "sg:postcode":"94965",
    "sg:province":"CA",
    "sg:tags":[
        "recording",
        "studio"
    ],
    "sg:website":"www.studiodrecording.com",
    "wof:name":"Studio D Recording",
    "wof:placetype":"venue"
},
  "geometry": {"coordinates":[-122.50286,37.868109],"type":"Point"}
}