{
  "type": "Feature",
  "properties": {
    "iso:country":"US",
    "sg:address":"700 E Redlands Blvd",
    "sg:city":"Redlands",
    "sg:classifiers":[
        {
            "category":"Shopping",
            "subcategory":"Gifts & Souvenirs",
            "type":"Retail Goods"
        }
    ],
    "sg:phone":"+1 909 793 8266",
    "sg:postcode":"92373",
    "sg:province":"CA",
    "sg:tags":[
        "shop"
    ],
    "wof:name":"Tanning Options",
    "wof:placetype":"venue"
},
  "geometry": {"coordinates":[-117.174104,34.053457],"type":"Point"}
}