{
  "type": "Feature",
  "properties": {
    "addr:full":"801 Marine Pkwy Redwood City CA 94065",
    "addr:housenumber":"801",
    "addr:postcode":"94065",
    "addr:street":"Marine Pkwy",
    "iso:country":"US",
    "sg:address":"801 Marine Pkwy",
    "sg:city":"Redwood City",
    "sg:classifiers":[
        {
            "category":"Real Estate",
            "subcategory":"Real Estate Operator",
            "type":"Services"
        }
    ],
    "sg:phone":"+1 650 593 4300",
    "sg:postcode":"94065",
    "sg:province":"CA",
    "sg:tags":[
        "apartment"
    ],
    "wof:name":"Indian Creek Garden Apartments",
    "wof:placetype":"venue"
},
  "geometry": {"coordinates":[-122.248606,37.538596],"type":"Point"}
}