{
  "type": "Feature",
  "properties": {
    "addr:full":"1748 Cesar Chavez San Francisco CA 94124",
    "addr:housenumber":"1748",
    "addr:postcode":"94124",
    "addr:street":"Cesar Chavez",
    "iso:country":"US",
    "sg:address":"1748 Cesar Chavez",
    "sg:city":"San Francisco",
    "sg:classifiers":[
        {
            "category":"Social Services",
            "type":"Services"
        }
    ],
    "sg:phone":"+1 415 647 0771",
    "sg:postcode":"94124",
    "sg:province":"CA",
    "sg:tags":[
        "organization",
        "welfare"
    ],
    "wof:name":"Jcccnc-Bingo",
    "wof:placetype":"venue"
},
  "geometry": {"coordinates":[-122.39473,37.74992],"type":"Point"}
}