{
  "type": "Feature",
  "properties": {
    "iso:country":"US",
    "sg:address":"15999 Cypress St",
    "sg:city":"Irwindale",
    "sg:classifiers":[
        {
            "category":"Organizations",
            "subcategory":"Labor Organization",
            "type":"Services"
        }
    ],
    "sg:phone":"+1 213 624 6487",
    "sg:postcode":"91706",
    "sg:province":"CA",
    "wof:name":"UTU-Mta Trust Fund",
    "wof:placetype":"venue"
},
  "geometry": {"coordinates":[-117.934251,34.096061],"type":"Point"}
}