{
  "type": "Feature",
  "properties": {
    "addr:full":"2710 W 54th St Los Angeles CA 90043",
    "addr:housenumber":"2710",
    "addr:postcode":"90043",
    "addr:street":"W 54Th St",
    "iso:country":"US",
    "sg:address":"2710 W 54th St",
    "sg:city":"Los Angeles",
    "sg:classifiers":[
        {
            "category":"Education",
            "subcategory":"Special Training",
            "type":"Public Place"
        }
    ],
    "sg:phone":"+1 323 374 0605",
    "sg:postcode":"90043",
    "sg:province":"CA",
    "sg:tags":[
        "tutoring"
    ],
    "wof:name":"N Blue Educational Tutoring",
    "wof:placetype":"venue"
},
  "geometry": {"coordinates":[-118.322998,33.993301],"type":"Point"}
}