{
  "type": "Feature",
  "properties": {
    "iso:country":"US",
    "sg:address":"3848 Campus Drive Suite 113",
    "sg:city":"Newport Beach",
    "sg:classifiers":[
        {
            "category":"Retail",
            "subcategory":"Auto Rental",
            "type":"Services"
        }
    ],
    "sg:phone":"+1 949 474 8375",
    "sg:postcode":"92660",
    "sg:province":"CA",
    "sg:tags":[
        "car"
    ],
    "wof:name":"West Coast Rent A Car",
    "wof:placetype":"venue"
},
  "geometry": {"coordinates":[-117.873126,33.664226],"type":"Point"}
}