{
  "type": "Feature",
  "properties": {
    "iso:country":"US",
    "sg:address":"2880 E Miraloma Ave",
    "sg:city":"Anaheim",
    "sg:classifiers":[
        {
            "category":"Retail",
            "subcategory":"Auto Repair",
            "type":"Services"
        }
    ],
    "sg:phone":"+1 714 632 5822",
    "sg:postcode":"92806",
    "sg:province":"CA",
    "sg:tags":[
        "body",
        "automobile",
        "painting"
    ],
    "wof:name":"Automobile Paint Specialist",
    "wof:placetype":"venue"
},
  "geometry": {"coordinates":[-117.869043,33.855562],"type":"Point"}
}