{
  "type": "Feature",
  "properties": {
    "addr:full":"12300 Wilshire Blvd Los Angeles CA 90025",
    "addr:housenumber":"12300",
    "addr:postcode":"90025",
    "addr:street":"Wilshire Blvd",
    "iso:country":"US",
    "sg:address":"12300 Wilshire Blvd",
    "sg:city":"Los Angeles",
    "sg:classifiers":[
        {
            "category":"Shopping",
            "subcategory":"Musical Instruments",
            "type":"Retail Goods"
        }
    ],
    "sg:phone":"+1 310 481 3954",
    "sg:postcode":"90025",
    "sg:province":"CA",
    "sg:tags":[
        "music",
        "dealer"
    ],
    "wof:name":"Bully Music Assoc",
    "wof:placetype":"venue"
},
  "geometry": {"coordinates":[-118.469652,34.042335],"type":"Point"}
}