{
  "type": "Feature",
  "properties": {
    "addr:full":"551 River Hills Ct Simi Valley CA 93065",
    "addr:housenumber":"551",
    "addr:postcode":"93065",
    "addr:street":"River Hills Ct",
    "iso:country":"US",
    "sg:address":"551 River Hills Ct",
    "sg:city":"Simi Valley",
    "sg:classifiers":[
        {
            "category":"Building & Trades",
            "subcategory":"Construction",
            "type":"Services"
        }
    ],
    "sg:phone":"+1 805 583 1423",
    "sg:postcode":"93065",
    "sg:province":"CA",
    "sg:tags":[
        "home",
        "general",
        "contractor"
    ],
    "wof:name":"Rice Construction Co",
    "wof:placetype":"venue"
},
  "geometry": {"coordinates":[-118.789025,34.249733],"type":"Point"}
}