{
  "type": "Feature",
  "properties": {
    "iso:country":"US",
    "sg:address":"1439 Golf Course Dr",
    "sg:city":"Windsor",
    "sg:classifiers":[
        {
            "category":"Building & Trades",
            "subcategory":"Electrical",
            "type":"Services"
        }
    ],
    "sg:phone":"+1 707 837 7474",
    "sg:postcode":"95492",
    "sg:province":"CA",
    "sg:tags":[
        "electric",
        "contractor"
    ],
    "wof:name":"Jim Miller Electric",
    "wof:placetype":"venue"
},
  "geometry": {"coordinates":[-122.805374,38.530325],"type":"Point"}
}