{
  "type": "Feature",
  "properties": {
    "addr:full":"17601 S Denver Ave Gardena CA 90248",
    "addr:housenumber":"17601",
    "addr:postcode":"90248",
    "addr:street":"S Denver Ave",
    "iso:country":"US",
    "sg:address":"17601 S Denver Ave",
    "sg:city":"Gardena",
    "sg:classifiers":[
        {
            "category":"Real Estate",
            "subcategory":"Real Estate Agent",
            "type":"Services"
        }
    ],
    "sg:phone":"+1 310 715 6559",
    "sg:postcode":"90248",
    "sg:province":"CA",
    "wof:name":"Guardian Properties LLC",
    "wof:placetype":"venue"
},
  "geometry": {"coordinates":[-118.283236,33.870993],"type":"Point"}
}