{
  "type": "Feature",
  "properties": {
    "iso:country":"US",
    "sg:address":"9649 Westminster Ave",
    "sg:city":"Garden Grove",
    "sg:classifiers":[
        {
            "category":"Real Estate",
            "subcategory":"Real Estate Operator",
            "type":"Services"
        }
    ],
    "sg:phone":"+1 714 638 3751",
    "sg:postcode":"92844",
    "sg:province":"CA",
    "sg:tags":[
        "apartment"
    ],
    "wof:name":"Rose Garden Apartments",
    "wof:placetype":"venue"
},
  "geometry": {"coordinates":[-117.960999,33.759499],"type":"Point"}
}