{
  "type": "Feature",
  "properties": {
    "iso:country":"US",
    "sg:address":"7415 Eigleberry St",
    "sg:city":"Gilroy",
    "sg:classifiers":[
        {
            "category":"Professional",
            "subcategory":"Lawyer & Legal Services",
            "type":"Services"
        }
    ],
    "sg:phone":"+1 408 842 3144",
    "sg:postcode":"95020",
    "sg:province":"CA",
    "sg:tags":[
        "attorney"
    ],
    "wof:name":"Johnson & Simoni",
    "wof:placetype":"venue"
},
  "geometry": {"coordinates":[-121.57061,37.007788],"type":"Point"}
}