{
  "type": "Feature",
  "properties": {
    "addr:full":"890 N Columbia Ave Claremont CA 91711",
    "addr:housenumber":"890",
    "addr:postcode":"91711",
    "addr:street":"N Columbia Ave",
    "iso:country":"US",
    "sg:address":"890 N Columbia Ave",
    "sg:city":"Claremont",
    "sg:classifiers":[
        {
            "category":"Education",
            "subcategory":"College",
            "type":"Public Place"
        }
    ],
    "sg:phone":"+1 909 621 8088",
    "sg:postcode":"91711",
    "sg:province":"CA",
    "sg:tags":[
        "academic",
        "school"
    ],
    "wof:name":"Claremont Mc Kenna",
    "wof:placetype":"venue"
},
  "geometry": {"coordinates":[-117.711392,34.101678],"type":"Point"}
}