{
  "type": "Feature",
  "properties": {
    "iso:country":"US",
    "sg:address":"4214 Mission St",
    "sg:city":"San Francisco",
    "sg:classifiers":[
        {
            "category":"Manufacturing",
            "subcategory":"Signs",
            "type":"Manufacturing & Wholesale Goods"
        }
    ],
    "sg:phone":"+1 415 587 5060",
    "sg:postcode":"94112",
    "sg:province":"CA",
    "sg:tags":[
        "specialty",
        "merchandise",
        "mfg"
    ],
    "wof:name":"Rehoboth Signs",
    "wof:placetype":"venue"
},
  "geometry": {"coordinates":[-122.430775,37.729442],"type":"Point"}
}