{
  "type": "Feature",
  "properties": {
    "iso:country":"US",
    "sg:address":"800 West 6th Street",
    "sg:city":"Los Angeles",
    "sg:classifiers":[
        {
            "category":"Personal",
            "type":"Services"
        }
    ],
    "sg:phone":"+1 213 891 9565",
    "sg:postcode":"90017",
    "sg:province":"CA",
    "sg:tags":[
        "local"
    ],
    "wof:name":"Athena Parking",
    "wof:placetype":"venue"
},
  "geometry": {"coordinates":[-118.257496,34.050115],"type":"Point"}
}