{
  "type": "Feature",
  "properties": {
    "addr:full":"1331 Goucher St Pacific Plsds CA 90272",
    "addr:housenumber":"1331",
    "addr:postcode":"90272",
    "addr:street":"Goucher St",
    "iso:country":"US",
    "sg:address":"1331 Goucher St",
    "sg:city":"Pacific Plsds",
    "sg:classifiers":[
        {
            "category":"Real Estate",
            "subcategory":"Architect",
            "type":"Services"
        }
    ],
    "sg:phone":"+1 310 573 4300",
    "sg:postcode":"90272",
    "sg:province":"CA",
    "wof:name":"Hatch Colasuonno Studio",
    "wof:placetype":"venue"
},
  "geometry": {"coordinates":[-118.522662,34.053647],"type":"Point"}
}