{
  "type": "Feature",
  "properties": {
    "addr:full":"2425 Rivera St San Francisco CA 94116",
    "addr:housenumber":"2425",
    "addr:postcode":"94116",
    "addr:street":"Rivera St",
    "iso:country":"US",
    "sg:address":"2425 Rivera St",
    "sg:city":"San Francisco",
    "sg:classifiers":[
        {
            "category":"Professional",
            "type":"Services"
        }
    ],
    "sg:phone":"+1 415 731 1532",
    "sg:postcode":"94116",
    "sg:province":"CA",
    "wof:name":"Helen D C Jodoin Ms",
    "wof:placetype":"venue"
},
  "geometry": {"coordinates":[-122.492887,37.745959],"type":"Point"}
}