{
  "type": "Feature",
  "properties": {
    "iso:country":"US",
    "sg:address":"2917 Sienna Ln",
    "sg:city":"Sacramento",
    "sg:classifiers":[
        {
            "category":"Real Estate",
            "subcategory":"Developer",
            "type":"Services"
        }
    ],
    "sg:phone":"+1 916 484 7191",
    "sg:postcode":"95864",
    "sg:province":"CA",
    "wof:name":"Sienna Estates Owners Association",
    "wof:placetype":"venue"
},
  "geometry": {"coordinates":[-121.394093,38.583257],"type":"Point"}
}