{
  "type": "Feature",
  "properties": {
    "addr:full":"1300 Whitley Ave Corcoran CA 93212",
    "addr:housenumber":"1300",
    "addr:postcode":"93212",
    "addr:street":"Whitley Ave",
    "iso:country":"US",
    "sg:address":"1300 Whitley Ave",
    "sg:city":"Corcoran",
    "sg:classifiers":[
        {
            "category":"Restaurant",
            "type":"Food & Drink"
        }
    ],
    "sg:phone":"+1 559 992 4107",
    "sg:postcode":"93212",
    "sg:province":"CA",
    "wof:name":"King Frosty",
    "wof:placetype":"venue"
},
  "geometry": {"coordinates":[-119.56356,36.098042],"type":"Point"}
}