{
  "type": "Feature",
  "properties": {
    "addr:full":"724 4th St Orland CA 95963",
    "addr:housenumber":"724",
    "addr:postcode":"95963",
    "addr:street":"4Th St",
    "iso:country":"US",
    "sg:address":"724 4th St",
    "sg:city":"Orland",
    "sg:classifiers":[
        {
            "category":"Manufacturing",
            "subcategory":"Printing",
            "type":"Manufacturing & Wholesale Goods"
        }
    ],
    "sg:phone":"+1 530 865 8402",
    "sg:postcode":"95963",
    "sg:province":"CA",
    "sg:tags":[
        "equipment",
        "computer",
        "printer"
    ],
    "wof:name":"Ink Well",
    "wof:placetype":"venue"
},
  "geometry": {"coordinates":[-122.194101,39.747119],"type":"Point"}
}