{
  "type": "Feature",
  "properties": {
    "addr:full":"209 Harding Blvd Roseville CA 95678",
    "addr:housenumber":"209",
    "addr:postcode":"95678",
    "addr:street":"Harding Blvd",
    "iso:country":"US",
    "sg:address":"209 Harding Blvd",
    "sg:city":"Roseville",
    "sg:classifiers":[
        {
            "category":"Professional",
            "subcategory":"Detective & Security Services",
            "type":"Services"
        }
    ],
    "sg:phone":"+1 916 773 5057",
    "sg:postcode":"95678",
    "sg:province":"CA",
    "sg:tags":[
        "guard",
        "patrol"
    ],
    "sg:website":"www.scssecurity.com",
    "wof:name":"SCS Security Inc",
    "wof:placetype":"venue"
},
  "geometry": {"coordinates":[-121.270436,38.748338],"type":"Point"}
}