{
  "type": "Feature",
  "properties": {
    "iso:country":"US",
    "sg:address":"5225 Canyon Crest Dr Suite 301 A",
    "sg:city":"Riverside",
    "sg:classifiers":[
        {
            "category":"Banks & Credit Unions",
            "subcategory":"Investment Brokerage",
            "type":"Services"
        },
        {
            "category":"Banks & Credit Unions",
            "subcategory":"Bank",
            "type":"Services"
        },
        {
            "category":"Banks & Credit Unions",
            "subcategory":"Financial Services",
            "type":"Services"
        }
    ],
    "sg:phone":"+1 951 824 6464",
    "sg:postcode":"92507",
    "sg:province":"CA",
    "sg:tags":[
        "advisory",
        "mutual",
        "retirement",
        "annuity",
        "broker",
        "fund",
        "planning",
        "plan",
        "consultant",
        "security",
        "bond",
        "insurance",
        "stock"
    ],
    "sg:website":"http://national.citysearch.com/profile/external/602439186/riverside_ca/edward_jones_allyn_c_fresh.html?publisher=yellowpages&reference_id=1&placement=ypwebsitemip",
    "wof:name":"Edward Jones - ALLYN C FRESH",
    "wof:placetype":"venue"
},
  "geometry": {"coordinates":[-117.329407,33.956506],"type":"Point"}
}