{
  "type": "Feature",
  "properties": {
    "iso:country":"US",
    "sg:address":"3427 Fayance Pl",
    "sg:city":"Thousand Oaks",
    "sg:classifiers":[
        {
            "category":"Building & Trades",
            "subcategory":"Construction",
            "type":"Services"
        }
    ],
    "sg:phone":"+1 805 492 8111",
    "sg:postcode":"91362",
    "sg:province":"CA",
    "sg:tags":[
        "acoustical",
        "contractor"
    ],
    "wof:name":"Tom & Jerry Acoustical Ceiling",
    "wof:placetype":"venue"
},
  "geometry": {"coordinates":[-118.844386,34.22554],"type":"Point"}
}