{
  "type": "Feature",
  "properties": {
    "addr:full":"3427 Fayance Pl Thousand Oaks CA 91362",
    "addr:housenumber":"3427",
    "addr:postcode":"91362",
    "addr:street":"Fayance Pl",
    "iso:country":"US",
    "sg:address":"3427 Fayance Pl",
    "sg:city":"Thousand Oaks",
    "sg:classifiers":[
        {
            "category":"Building & Trades",
            "subcategory":"Construction",
            "type":"Services"
        }
    ],
    "sg:phone":"+1 805 492 8111",
    "sg:postcode":"91362",
    "sg:province":"CA",
    "sg:tags":[
        "acoustical",
        "contractor"
    ],
    "wof:name":"Tom & Jerry Acoustical Ceiling",
    "wof:placetype":"venue"
},
  "geometry": {"coordinates":[-118.844386,34.22554],"type":"Point"}
}