{
  "type": "Feature",
  "properties": {
    "iso:country":"US",
    "sg:address":"3832 Sepulveda Blvd Marukai Food Court",
    "sg:city":"Torrance",
    "sg:classifiers":[
        {
            "category":"Restaurant",
            "type":"Food & Drink"
        }
    ],
    "sg:phone":"+1 310 375 1538",
    "sg:postcode":"90505",
    "sg:province":"CA",
    "sg:tags":[
        "japanese"
    ],
    "wof:name":"Morizo Sushi Kaisen",
    "wof:placetype":"venue"
},
  "geometry": {"coordinates":[-118.352702,33.825579],"type":"Point"}
}