{
  "type": "Feature",
  "properties": {
    "addr:full":"402 N Soto St Los Angeles CA 90033",
    "addr:housenumber":"402",
    "addr:postcode":"90033",
    "addr:street":"N Soto St",
    "iso:country":"US",
    "sg:address":"402 N Soto St",
    "sg:city":"Los Angeles",
    "sg:classifiers":[
        {
            "category":"Professional",
            "type":"Services"
        }
    ],
    "sg:phone":"+1 213 233 7891",
    "sg:postcode":"90033",
    "sg:province":"CA",
    "wof:name":"Trios Los Ases De Roberto Loza",
    "wof:placetype":"venue"
},
  "geometry": {"coordinates":[-118.206755,34.048268],"type":"Point"}
}