{
  "type": "Feature",
  "properties": {
    "addr:full":"2322 Midway Dr Santa Rosa CA 95405",
    "addr:housenumber":"2322",
    "addr:postcode":"95405",
    "addr:street":"Midway Dr",
    "iso:country":"US",
    "sg:address":"2322 Midway Dr",
    "sg:city":"Santa Rosa",
    "sg:classifiers":[
        {
            "category":"Shopping",
            "subcategory":"Clothing, Apparel, & Fashions",
            "type":"Retail Goods"
        }
    ],
    "sg:phone":"+1 707 542 3941",
    "sg:postcode":"95405",
    "sg:province":"CA",
    "sg:tags":[
        "lingerie"
    ],
    "wof:name":"Marga's Intimate Apparel",
    "wof:placetype":"venue"
},
  "geometry": {"coordinates":[-122.69094200000001,38.444955],"type":"Point"}
}