{
  "type": "Feature",
  "properties": {
    "addr:full":"530 E Cerritos Ave Anaheim CA 92805",
    "addr:housenumber":"530",
    "addr:postcode":"92805",
    "addr:street":"E Cerritos Ave",
    "iso:country":"US",
    "sg:address":"530 E Cerritos Ave",
    "sg:city":"Anaheim",
    "sg:classifiers":[
        {
            "category":"Manufacturing",
            "subcategory":"Rubber & Plastics",
            "type":"Manufacturing & Wholesale Goods"
        }
    ],
    "sg:phone":"+1 714 778 4786",
    "sg:postcode":"92805",
    "sg:province":"CA",
    "sg:tags":[
        "product",
        "mfg"
    ],
    "sg:website":"www.artisticplastics.com",
    "wof:name":"Artistic Plastics Inc",
    "wof:placetype":"venue"
},
  "geometry": {"coordinates":[-117.900882,33.810526],"type":"Point"}
}