{
  "type": "Feature",
  "properties": {
    "addr:full":"11654 Maltman Dr Grass Valley CA 95945",
    "addr:housenumber":"11654",
    "addr:postcode":"95945",
    "addr:street":"Maltman Dr",
    "iso:country":"US",
    "sg:address":"11654 Maltman Dr",
    "sg:city":"Grass Valley",
    "sg:classifiers":[
        {
            "category":"Building & Trades",
            "subcategory":"Construction",
            "type":"Services"
        }
    ],
    "sg:phone":"+1 530 272 1040",
    "sg:postcode":"95945",
    "sg:province":"CA",
    "sg:tags":[
        "water",
        "well",
        "drilling"
    ],
    "wof:name":"M & M Water Systems",
    "wof:placetype":"venue"
},
  "geometry": {"coordinates":[-121.03874500000001,39.235375],"type":"Point"}
}