{
  "type": "Feature",
  "properties": {
    "addr:full":"5120 N Long Beach Blvd Long Beach CA 90807",
    "addr:housenumber":"5120",
    "addr:postcode":"90807",
    "addr:street":"N Long Beach Blvd",
    "iso:country":"US",
    "sg:address":"5120 N Long Beach Blvd",
    "sg:city":"Long Beach",
    "sg:classifiers":[
        {
            "category":"Autos & Motor Vehicles",
            "subcategory":"Fuel & Gas Station",
            "type":"Retail Goods"
        }
    ],
    "sg:postcode":"90807",
    "sg:province":"CA",
    "wof:name":"Limited Oil",
    "wof:placetype":"venue"
},
  "geometry": {"coordinates":[-118.18926500000001,33.799847],"type":"Point"}
}