{
  "type": "Feature",
  "properties": {
    "iso:country":"US",
    "sg:address":"2404 K St",
    "sg:city":"Sacramento",
    "sg:classifiers":[
        {
            "category":"Shopping",
            "subcategory":"Clothing, Apparel, & Fashions",
            "type":"Retail Goods"
        }
    ],
    "sg:phone":"+1 916 444 1188",
    "sg:postcode":"95816",
    "sg:province":"CA",
    "sg:tags":[
        "item",
        "boutique"
    ],
    "wof:name":"Dara Denim",
    "wof:placetype":"venue"
},
  "geometry": {"coordinates":[-121.473753,38.573755],"type":"Point"}
}