{
  "type": "Feature",
  "properties": {
    "addr:full":"10640 Fern Ave Stanton CA 90680",
    "addr:housenumber":"10640",
    "addr:postcode":"ca 90680",
    "addr:street":"Fern Ave",
    "iso:country":"US",
    "sg:address":"10640 Fern Ave",
    "sg:city":"Stanton",
    "sg:classifiers":[
        {
            "category":"Manufacturing",
            "subcategory":"Metals",
            "type":"Manufacturing & Wholesale Goods"
        }
    ],
    "sg:phone":"+1 714 827 7105",
    "sg:postcode":"90680",
    "sg:province":"CA",
    "sg:tags":[
        "plumbing",
        "fixture",
        "supply"
    ],
    "wof:name":"Plumbing & Maintenance Supply",
    "wof:placetype":"venue"
},
  "geometry": {"coordinates":[-117.988845,33.808173],"type":"Point"}
}