{
  "type": "Feature",
  "properties": {
    "addr:full":"150 Pacific St Tustin CA 92780",
    "addr:housenumber":"150",
    "addr:postcode":"92780",
    "addr:street":"Pacific St",
    "iso:country":"US",
    "sg:address":"150 Pacific St",
    "sg:city":"Tustin",
    "sg:classifiers":[
        {
            "category":"Building & Trades",
            "subcategory":"Landscaping Services",
            "type":"Services"
        }
    ],
    "sg:phone":"+1 714 544 0427",
    "sg:postcode":"92780",
    "sg:province":"CA",
    "sg:tags":[
        "architect",
        "landscape"
    ],
    "sg:website":"www.5star-landscape.com",
    "wof:name":"Five Star Landscape Design",
    "wof:placetype":"venue"
},
  "geometry": {"coordinates":[-117.82988400000001,33.744822],"type":"Point"}
}