{
  "type": "Feature",
  "properties": {
    "addr:full":"2116 Westwood Boulevard Los Angeles CA 90025",
    "addr:housenumber":"2116",
    "addr:postcode":"90025",
    "addr:street":"Westwood Boulevard",
    "iso:country":"US",
    "sg:address":"2116 Westwood Boulevard",
    "sg:city":"Los Angeles",
    "sg:classifiers":[
        {
            "category":"Building & Trades",
            "subcategory":"Locksmith",
            "type":"Services"
        }
    ],
    "sg:phone":"+1 310 405 6043",
    "sg:postcode":"90025",
    "sg:province":"CA",
    "sg:tags":[
        "key"
    ],
    "wof:name":"All Day 7 Day Locks & Locksmith",
    "wof:placetype":"venue"
},
  "geometry": {"coordinates":[-118.432475,34.044521],"type":"Point"}
}