{
  "type": "Feature",
  "properties": {
    "iso:country":"US",
    "sg:address":"737 Bentwood Dr",
    "sg:city":"El Cajon",
    "sg:classifiers":[
        {
            "category":"Shopping",
            "subcategory":"Bicycles & Sporting Goods",
            "type":"Retail Goods"
        }
    ],
    "sg:phone":"+1 619 448 7793",
    "sg:postcode":"92021",
    "sg:province":"CA",
    "sg:tags":[
        "matt",
        "gymnastic"
    ],
    "wof:name":"West Coast Mat Repair",
    "wof:placetype":"venue"
},
  "geometry": {"coordinates":[-116.9525,32.822486],"type":"Point"}
}