{
  "type": "Feature",
  "properties": {
    "addr:full":"2155 Verdugo Blvd Montrose CA 91020",
    "addr:housenumber":"2155",
    "addr:postcode":"91020",
    "addr:street":"Verdugo Blvd",
    "iso:country":"US",
    "sg:address":"2155 Verdugo Blvd",
    "sg:city":"Montrose",
    "sg:classifiers":[
        {
            "category":"Personal",
            "type":"Services"
        }
    ],
    "sg:phone":"+1 818 248 2475",
    "sg:postcode":"91020",
    "sg:province":"CA",
    "sg:tags":[
        "notary",
        "receiving",
        "mail"
    ],
    "wof:name":"Montrose Mail Boxes",
    "wof:placetype":"venue"
},
  "geometry": {"coordinates":[-118.22399900000001,34.2048],"type":"Point"}
}