{
  "type": "Feature",
  "properties": {
    "iso:country":"US",
    "sg:address":"12804 18th St",
    "sg:city":"Chino",
    "sg:classifiers":[
        {
            "category":"Professional",
            "type":"Services"
        }
    ],
    "sg:phone":"+1 909 627 6440",
    "sg:postcode":"91710",
    "sg:province":"CA",
    "wof:name":"Rangel Ramiro",
    "wof:placetype":"venue"
},
  "geometry": {"coordinates":[-117.677441,34.020908],"type":"Point"}
}