{
  "type": "Feature",
  "properties": {
    "iso:country":"US",
    "sg:address":"179 L St",
    "sg:city":"Lincoln",
    "sg:classifiers":[
        {
            "category":"Building & Trades",
            "subcategory":"Construction",
            "type":"Services"
        }
    ],
    "sg:phone":"+1 916 434 0585",
    "sg:postcode":"95648",
    "sg:province":"CA",
    "sg:tags":[
        "repairing",
        "remodeling",
        "contractor"
    ],
    "wof:name":"Mcdowell Construction",
    "wof:placetype":"venue"
},
  "geometry": {"coordinates":[-121.299069,38.887606],"type":"Point"}
}