{
  "type": "Feature",
  "properties": {
    "iso:country":"US",
    "sg:address":"8622 S Gate Ave",
    "sg:city":"South Gate",
    "sg:classifiers":[
        {
            "category":"Restaurant",
            "type":"Food & Drink"
        }
    ],
    "sg:phone":"+1 562 806 8009",
    "sg:postcode":"90280",
    "sg:province":"CA",
    "sg:tags":[
        "shop",
        "coffee"
    ],
    "wof:name":"Starbucks",
    "wof:placetype":"venue"
},
  "geometry": {"coordinates":[-118.214433,33.955292],"type":"Point"}
}