{
  "type": "Feature",
  "properties": {
    "addr:full":"6370 Magnolia Ave Riverside CA 92506",
    "addr:housenumber":"6370",
    "addr:postcode":"92506",
    "addr:street":"Magnolia Ave",
    "iso:country":"US",
    "sg:address":"6370 Magnolia Ave",
    "sg:city":"Riverside",
    "sg:classifiers":[
        {
            "category":"Personal",
            "type":"Services"
        }
    ],
    "sg:phone":"+1 951 808 7526",
    "sg:postcode":"92506",
    "sg:province":"CA",
    "sg:tags":[
        "credit",
        "debt",
        "counseling"
    ],
    "wof:name":"Springboard Non Profit",
    "wof:placetype":"venue"
},
  "geometry": {"coordinates":[-117.394711,33.95623],"type":"Point"}
}