{
  "type": "Feature",
  "properties": {
    "iso:country":"US",
    "sg:address":"395 State Hwy 65",
    "sg:city":"Lincoln",
    "sg:classifiers":[
        {
            "category":"Professional",
            "subcategory":"Management & Consulting",
            "type":"Services"
        }
    ],
    "sg:phone":"+1 916 408 3663",
    "sg:postcode":"95648",
    "sg:province":"CA",
    "sg:tags":[
        "real estate"
    ],
    "wof:name":"Century 21 Select Real Estate",
    "wof:placetype":"venue"
},
  "geometry": {"coordinates":[-121.292753,38.890441],"type":"Point"}
}