{
  "type": "Feature",
  "properties": {
    "addr:full":"186 Dawson Dr Camarillo CA 93012",
    "addr:housenumber":"186",
    "addr:postcode":"93012",
    "addr:street":"Dawson Dr",
    "iso:country":"US",
    "sg:address":"186 Dawson Dr",
    "sg:city":"Camarillo",
    "sg:classifiers":[
        {
            "category":"Professional",
            "type":"Services"
        }
    ],
    "sg:phone":"+1 805 388 0789",
    "sg:postcode":"93012",
    "sg:province":"CA",
    "wof:name":"Parrott Aire",
    "wof:placetype":"venue"
},
  "geometry": {"coordinates":[-119.033952,34.21501],"type":"Point"}
}