{
  "type": "Feature",
  "properties": {
    "addr:full":"12 S 1st St Ste 613 San Jose CA 95113",
    "addr:housenumber":"12",
    "addr:postcode":"95113",
    "addr:street":"S 1St St Ste 613",
    "iso:country":"US",
    "sg:address":"12 S 1st St Ste 613",
    "sg:city":"San Jose",
    "sg:classifiers":[
        {
            "category":"Professional",
            "subcategory":"Lawyer & Legal Services",
            "type":"Services"
        }
    ],
    "sg:phone":"+1 408 286 6619",
    "sg:postcode":"95113",
    "sg:province":"CA",
    "wof:name":"Wang Adam Law Office Of",
    "wof:placetype":"venue"
},
  "geometry": {"coordinates":[-121.890208,37.336049],"type":"Point"}
}