{
  "type": "Feature",
  "properties": {
    "addr:full":"3502 W Orange Ave Anaheim CA 92804",
    "addr:housenumber":"3502",
    "addr:postcode":"92804",
    "addr:street":"W Orange Ave",
    "iso:country":"US",
    "sg:address":"3502 W Orange Ave",
    "sg:city":"Anaheim",
    "sg:classifiers":[
        {
            "category":"Building & Trades",
            "subcategory":"Locksmith",
            "type":"Services"
        }
    ],
    "sg:phone":"+1 714 535 5335",
    "sg:postcode":"92804",
    "sg:province":"CA",
    "sg:tags":[
        "key"
    ],
    "wof:name":"24Hr Locksmith Anaheim",
    "wof:placetype":"venue"
},
  "geometry": {"coordinates":[-118.00900300000001,33.824699],"type":"Point"}
}