{
  "type": "Feature",
  "properties": {
    "addr:full":"1134 Cory Ave West Hollywood CA 90069",
    "addr:housenumber":"1134",
    "addr:postcode":"90069",
    "addr:street":"Cory Ave",
    "iso:country":"US",
    "sg:address":"1134 Cory Ave",
    "sg:city":"West Hollywood",
    "sg:classifiers":[
        {
            "category":"Professional",
            "subcategory":"Management & Consulting",
            "type":"Services"
        }
    ],
    "sg:phone":"+1 310 271 1003",
    "sg:postcode":"90069",
    "sg:province":"CA",
    "sg:tags":[
        "consultant"
    ],
    "wof:name":"Leslie Lewis Consulting",
    "wof:placetype":"venue"
},
  "geometry": {"coordinates":[-118.391363,34.09197],"type":"Point"}
}