{
  "type": "Feature",
  "properties": {
    "iso:country":"US",
    "sg:address":"17777 Main Street",
    "sg:city":"Irvine",
    "sg:classifiers":[
        {
            "category":"Personal",
            "subcategory":"Nail Salon",
            "type":"Services"
        }
    ],
    "sg:phone":"+1 949 756 0464",
    "sg:postcode":"92614",
    "sg:province":"CA",
    "wof:name":"Glamour Den",
    "wof:placetype":"venue"
},
  "geometry": {"coordinates":[-117.859673,33.684672],"type":"Point"}
}