{
  "type": "Feature",
  "properties": {
    "addr:full":"7247 Otay Mesa Rd San Diego CA 92154",
    "addr:housenumber":"7247",
    "addr:postcode":"92154",
    "addr:street":"Otay Mesa Rd",
    "iso:country":"US",
    "sg:address":"7247 Otay Mesa Rd",
    "sg:city":"San Diego",
    "sg:classifiers":[
        {
            "category":"Retail",
            "subcategory":"Auto Repair",
            "type":"Services"
        }
    ],
    "sg:phone":"+1 619 661 1022",
    "sg:postcode":"92154",
    "sg:province":"CA",
    "sg:tags":[
        "wrecker"
    ],
    "sg:website":"www.roadone.com",
    "wof:name":"Road One",
    "wof:placetype":"venue"
},
  "geometry": {"coordinates":[-116.98591399999999,32.567957],"type":"Point"}
}