{
  "type": "Feature",
  "properties": {
    "addr:full":"9841 Shadow Way Sunland CA 91040",
    "addr:housenumber":"9841",
    "addr:postcode":"91040",
    "addr:street":"Shadow Way",
    "iso:country":"US",
    "sg:address":"9841 Shadow Way",
    "sg:city":"Sunland",
    "sg:classifiers":[
        {
            "category":"Manufacturing",
            "subcategory":"Building Materials",
            "type":"Manufacturing & Wholesale Goods"
        }
    ],
    "sg:phone":"+1 818 353 1932",
    "sg:postcode":"91040",
    "sg:province":"CA",
    "sg:tags":[
        "mfg"
    ],
    "wof:name":"Woodware By George",
    "wof:placetype":"venue"
},
  "geometry": {"coordinates":[-118.34404499999999,34.249365],"type":"Point"}
}