{
  "type": "Feature",
  "properties": {
    "addr:full":"8700 Washington Blvd Pico Rivera CA 90660",
    "addr:housenumber":"8700",
    "addr:postcode":"90660",
    "addr:street":"Washington Blvd",
    "iso:country":"US",
    "sg:address":"8700 Washington Blvd",
    "sg:city":"Pico Rivera",
    "sg:classifiers":[
        {
            "category":"Restaurant",
            "type":"Food & Drink"
        },
        {
            "category":"Bars & Pubs",
            "subcategory":"Dive Bar",
            "type":"Food & Drink"
        }
    ],
    "sg:phone":"+1 562 942 2403",
    "sg:postcode":"90660",
    "sg:province":"CA",
    "sg:tags":[
        "mexican"
    ],
    "wof:name":"Mariscos La Sirenita",
    "wof:placetype":"venue"
},
  "geometry": {"coordinates":[-118.100998,33.985001],"type":"Point"}
}