{
  "type": "Feature",
  "properties": {
    "iso:country":"US",
    "sg:address":"421 Biscayne Ave",
    "sg:city":"Foster City",
    "sg:classifiers":[
        {
            "category":"Professional",
            "type":"Services"
        }
    ],
    "sg:phone":"+1 650 571 5820",
    "sg:postcode":"94404",
    "sg:province":"CA",
    "sg:tags":[
        "establishment"
    ],
    "wof:name":"Micocom Technology",
    "wof:placetype":"venue"
},
  "geometry": {"coordinates":[-122.270321,37.536832],"type":"Point"}
}