{
  "type": "Feature",
  "properties": {
    "addr:full":"732 Tuolumne St Vallejo CA 94590",
    "addr:housenumber":"732",
    "addr:postcode":"94590",
    "addr:street":"Tuolumne St",
    "iso:country":"US",
    "sg:address":"732 Tuolumne St",
    "sg:city":"Vallejo",
    "sg:classifiers":[
        {
            "category":"Bars & Pubs",
            "type":"Food & Drink"
        }
    ],
    "sg:phone":"+1 707 554 0551",
    "sg:postcode":"94590",
    "sg:province":"CA",
    "sg:tags":[
        "lounge",
        "cocktail"
    ],
    "wof:name":"Village Cocktail Lounge",
    "wof:placetype":"venue"
},
  "geometry": {"coordinates":[-122.238186,38.107281],"type":"Point"}
}