{
  "type": "Feature",
  "properties": {
    "iso:country":"US",
    "sg:address":"129 E Woodvale Ave",
    "sg:city":"Orange",
    "sg:classifiers":[
        {
            "category":"Building & Trades",
            "subcategory":"Equipment Rental",
            "type":"Services"
        }
    ],
    "sg:phone":"+1 714 282 1919",
    "sg:postcode":"92865",
    "sg:province":"CA",
    "sg:tags":[
        "contractor"
    ],
    "wof:name":"Beck's Backhoe",
    "wof:placetype":"venue"
},
  "geometry": {"coordinates":[-117.850016,33.830997],"type":"Point"}
}