{
  "type": "Feature",
  "properties": {
    "addr:full":"1828 Cabrillo Hwy N Half Moon Bay CA 94019",
    "addr:housenumber":"1828",
    "addr:postcode":"94019",
    "addr:street":"Cabrillo Hwy N",
    "iso:country":"US",
    "sg:address":"1828 Cabrillo Hwy N",
    "sg:city":"Half Moon Bay",
    "sg:classifiers":[
        {
            "category":"Recreation",
            "type":"Entertainment"
        }
    ],
    "sg:phone":"+1 650 726 2362",
    "sg:postcode":"94019",
    "sg:province":"CA",
    "sg:tags":[
        "stable"
    ],
    "wof:name":"Sea Horse & Friendly Acres",
    "wof:placetype":"venue"
},
  "geometry": {"coordinates":[-122.445162,37.481758],"type":"Point"}
}