{
  "type": "Feature",
  "properties": {
    "iso:country":"US",
    "sg:address":"15651 Valley Blvd",
    "sg:city":"City Of Industry",
    "sg:classifiers":[
        {
            "category":"Restaurant",
            "type":"Food & Drink"
        }
    ],
    "sg:phone":"+1 626 333 1975",
    "sg:postcode":"91744",
    "sg:province":"CA",
    "wof:name":"Haley's Bar & Grill",
    "wof:placetype":"venue"
},
  "geometry": {"coordinates":[-117.957471,34.019447],"type":"Point"}
}