{
  "type": "Feature",
  "properties": {
    "addr:full":"11480 Brookshire Ave # 303 Downey CA 90241",
    "addr:housenumber":"11480",
    "addr:postcode":"90241",
    "addr:street":"Brookshire Ave # 303",
    "iso:country":"US",
    "sg:address":"11480 Brookshire Ave # 303",
    "sg:city":"Downey",
    "sg:classifiers":[
        {
            "category":"Health Services",
            "subcategory":"Doctor",
            "type":"Services"
        }
    ],
    "sg:phone":"+1 562 862 5160",
    "sg:postcode":"90241",
    "sg:province":"CA",
    "sg:tags":[
        "physician",
        "pediatrics-otorhinolaryngology",
        "surgeons",
        "otorhinolaryngology",
        "nose",
        "throat",
        "surgeon",
        "ear"
    ],
    "wof:name":"Elias Ayoub Md",
    "wof:placetype":"venue"
},
  "geometry": {"coordinates":[-118.131496,33.935828],"type":"Point"}
}