{
  "type": "Feature",
  "properties": {
    "iso:country":"US",
    "sg:address":"8324 Crestshire Cir",
    "sg:city":"Orangevale",
    "sg:classifiers":[
        {
            "category":"Professional",
            "subcategory":"Computer Services",
            "type":"Services"
        }
    ],
    "sg:phone":"+1 916 216 6474",
    "sg:postcode":"95662",
    "sg:province":"CA",
    "sg:tags":[
        "website",
        "design"
    ],
    "wof:name":"Nco Consulting",
    "wof:placetype":"venue"
},
  "geometry": {"coordinates":[-121.253239,38.682071],"type":"Point"}
}