{
  "type": "Feature",
  "properties": {
    "addr:full":"1975 W 11th St Tracy CA 95376",
    "addr:housenumber":"1975",
    "addr:postcode":"95376",
    "addr:street":"W 11Th St",
    "iso:country":"US",
    "sg:address":"1975 W 11th St",
    "sg:city":"Tracy",
    "sg:classifiers":[
        {
            "category":"Home & Garden",
            "subcategory":"Hardware",
            "type":"Retail Goods"
        }
    ],
    "sg:phone":"+1 209 834 2808",
    "sg:postcode":"95376",
    "sg:province":"CA",
    "wof:name":"Orchard Supply Hardware",
    "wof:placetype":"venue"
},
  "geometry": {"coordinates":[-121.445295,37.739708],"type":"Point"}
}