{
  "type": "Feature",
  "properties": {
    "addr:full":"121 E St Rio Linda CA 95673",
    "addr:housenumber":"121",
    "addr:postcode":"95673",
    "addr:street":"E St",
    "iso:country":"US",
    "sg:address":"121 E St",
    "sg:city":"Rio Linda",
    "sg:classifiers":[
        {
            "category":"Personal",
            "type":"Services"
        }
    ],
    "sg:phone":"+1 916 300 2203",
    "sg:postcode":"95673",
    "sg:province":"CA",
    "sg:tags":[
        "therapist",
        "massage"
    ],
    "wof:name":"Addictive Knead",
    "wof:placetype":"venue"
},
  "geometry": {"coordinates":[-121.464017,38.676841],"type":"Point"}
}