{
  "type": "Feature",
  "properties": {
    "iso:country":"US",
    "sg:address":"8888 Balboa Ave",
    "sg:city":"San Diego",
    "sg:classifiers":[
        {
            "category":"Education",
            "subcategory":"University",
            "type":"Public Place"
        }
    ],
    "sg:phone":"+1 858 499 0202",
    "sg:postcode":"92123",
    "sg:province":"CA",
    "sg:tags":[
        "college"
    ],
    "sg:website":"www.coleman.edu",
    "wof:name":"Coleman University",
    "wof:placetype":"venue"
},
  "geometry": {"coordinates":[-117.13644600000001,32.822181],"type":"Point"}
}