{
  "type": "Feature",
  "properties": {
    "iso:country":"US",
    "sg:address":"23150 Sycamore Ln",
    "sg:city":"Crestline",
    "sg:classifiers":[
        {
            "category":"Professional",
            "subcategory":"Art Services",
            "type":"Services"
        }
    ],
    "sg:phone":"+1 909 338 2882",
    "sg:postcode":"92407",
    "sg:province":"CA",
    "sg:tags":[
        "graphic",
        "designer"
    ],
    "wof:name":"Aerograffiti Design",
    "wof:placetype":"venue"
},
  "geometry": {"coordinates":[-117.300449,34.244861],"type":"Point"}
}