{
  "type": "Feature",
  "properties": {
    "addr:full":"1890 Bryant St San Francisco CA 94110",
    "addr:housenumber":"1890",
    "addr:postcode":"94110",
    "addr:street":"Bryant St",
    "iso:country":"US",
    "sg:address":"1890 Bryant St",
    "sg:city":"San Francisco",
    "sg:classifiers":[
        {
            "category":"Arts & Performance",
            "subcategory":"Arts Center",
            "type":"Entertainment"
        }
    ],
    "sg:phone":"+1 415 701 7346",
    "sg:postcode":"94110",
    "sg:province":"CA",
    "sg:website":"www.sfhora.org",
    "wof:name":"SFHORA",
    "wof:placetype":"venue"
},
  "geometry": {"coordinates":[-122.410301,37.763157],"type":"Point"}
}