{
  "type": "Feature",
  "properties": {
    "iso:country":"US",
    "sg:address":"122 Jonathon Ct",
    "sg:city":"Galt",
    "sg:classifiers":[
        {
            "category":"Recreation",
            "type":"Entertainment"
        }
    ],
    "sg:phone":"+1 209 744 9107",
    "sg:postcode":"95632",
    "sg:province":"CA",
    "sg:tags":[
        "concessionaire"
    ],
    "wof:name":"MMT Enterprises",
    "wof:placetype":"venue"
},
  "geometry": {"coordinates":[-121.316174,38.25421],"type":"Point"}
}