{
  "type": "Feature",
  "properties": {
    "iso:country":"US",
    "sg:address":"7880 Van Nuys Blvd",
    "sg:city":"Panorama City",
    "sg:classifiers":[
        {
            "category":"Ice Cream",
            "type":"Food & Drink"
        }
    ],
    "sg:phone":"+1 818 997 7557",
    "sg:postcode":"91402",
    "sg:province":"CA",
    "sg:tags":[
        "frozen",
        "yogurt"
    ],
    "wof:name":"Penguins",
    "wof:placetype":"venue"
},
  "geometry": {"coordinates":[-118.44899700000001,34.213799],"type":"Point"}
}