{
  "type": "Feature",
  "properties": {
    "addr:full":"1800 Diesel Dr Sacramento CA 95838",
    "addr:housenumber":"1800",
    "addr:postcode":"95838",
    "addr:street":"Diesel Dr",
    "iso:country":"US",
    "sg:address":"1800 Diesel Dr",
    "sg:city":"Sacramento",
    "sg:classifiers":[
        {
            "category":"Manufacturing",
            "subcategory":"Petroleum Products",
            "type":"Manufacturing & Wholesale Goods"
        }
    ],
    "sg:phone":"+1 916 648 1537",
    "sg:postcode":"95838",
    "sg:province":"CA",
    "wof:name":"MVP Petroleum Engineering",
    "wof:placetype":"venue"
},
  "geometry": {"coordinates":[-121.42767000000001,38.649134],"type":"Point"}
}