{
  "type": "Feature",
  "properties": {
    "iso:country":"US",
    "sg:address":"43511 70th St E",
    "sg:city":"Lancaster",
    "sg:classifiers":[
        {
            "category":"Farming",
            "subcategory":"Farm",
            "type":"Manufacturing & Wholesale Goods"
        }
    ],
    "sg:phone":"+1 661 946 9022",
    "sg:postcode":"93535",
    "sg:province":"CA",
    "wof:name":"Calandri Sunrise Farms",
    "wof:placetype":"venue"
},
  "geometry": {"coordinates":[-118.005309,34.674019],"type":"Point"}
}