{
  "type": "Feature",
  "properties": {
    "iso:country":"US",
    "sg:address":"1989 Eaton Ave",
    "sg:city":"Hemet",
    "sg:classifiers":[
        {
            "category":"Building & Trades",
            "subcategory":"Construction",
            "type":"Services"
        }
    ],
    "sg:phone":"+1 951 652 1013",
    "sg:postcode":"92545",
    "sg:province":"CA",
    "sg:tags":[
        "contractor"
    ],
    "wof:name":"Merrill Gardens Construction",
    "wof:placetype":"venue"
},
  "geometry": {"coordinates":[-116.990966,33.76557],"type":"Point"}
}