{
  "type": "Feature",
  "properties": {
    "addr:full":"1155 Ellis St San Francisco CA 94109",
    "addr:housenumber":"1155",
    "addr:postcode":"94109",
    "addr:street":"Ellis St",
    "iso:country":"US",
    "sg:address":"1155 Ellis St",
    "sg:city":"San Francisco",
    "sg:classifiers":[
        {
            "category":"Real Estate",
            "subcategory":"Real Estate Operator",
            "type":"Services"
        }
    ],
    "sg:phone":"+1 415 921 3038",
    "sg:postcode":"94109",
    "sg:province":"CA",
    "sg:tags":[
        "apartment"
    ],
    "wof:name":"Normandy Apartments",
    "wof:placetype":"venue"
},
  "geometry": {"coordinates":[-122.426863,37.783025],"type":"Point"}
}