{
  "type": "Feature",
  "properties": {
    "iso:country":"US",
    "sg:address":"8070 Langdon Ave",
    "sg:city":"Van Nuys",
    "sg:classifiers":[
        {
            "category":"Real Estate",
            "subcategory":"Real Estate Operator",
            "type":"Services"
        }
    ],
    "sg:phone":"+1 818 989 9277",
    "sg:postcode":"91406",
    "sg:province":"CA",
    "sg:tags":[
        "apartment"
    ],
    "wof:name":"Langdon Gardens",
    "wof:placetype":"venue"
},
  "geometry": {"coordinates":[-118.469831,34.220946],"type":"Point"}
}