{
  "type": "Feature",
  "properties": {
    "addr:full":"6710 N West Ave Fresno CA 93711",
    "addr:housenumber":"6710",
    "addr:postcode":"93711",
    "addr:street":"N West Ave",
    "iso:country":"US",
    "sg:address":"6710 N West Ave",
    "sg:city":"Fresno",
    "sg:classifiers":[
        {
            "category":"Real Estate",
            "subcategory":"Real Estate Agent",
            "type":"Services"
        }
    ],
    "sg:phone":"+1 559 288 8721",
    "sg:postcode":"93711",
    "sg:province":"CA",
    "wof:name":"Lien K Le",
    "wof:placetype":"venue"
},
  "geometry": {"coordinates":[-119.826285,36.834818],"type":"Point"}
}