{
  "type": "Feature",
  "properties": {
    "addr:full":"21 N E St Porterville CA 93257",
    "addr:housenumber":"21",
    "addr:postcode":"93257",
    "addr:street":"N E St",
    "iso:country":"US",
    "sg:address":"21 N E St",
    "sg:city":"Porterville",
    "sg:classifiers":[
        {
            "category":"Retail",
            "subcategory":"Auto Repair",
            "type":"Services"
        }
    ],
    "sg:phone":"+1 559 784 5464",
    "sg:postcode":"93257",
    "sg:province":"CA",
    "sg:tags":[
        "body",
        "automobile",
        "painting"
    ],
    "wof:name":"Expertise Auto Paint & Body",
    "wof:placetype":"venue"
},
  "geometry": {"coordinates":[-119.02002400000001,36.066134],"type":"Point"}
}