{
  "type": "Feature",
  "properties": {
    "iso:country":"US",
    "sg:address":"11976 Woodside Ave",
    "sg:city":"Lakeside",
    "sg:classifiers":[
        {
            "category":"Manufacturing",
            "subcategory":"Tools & Machinery",
            "type":"Manufacturing & Wholesale Goods"
        }
    ],
    "sg:phone":"+1 619 448 8802",
    "sg:postcode":"92040",
    "sg:province":"CA",
    "sg:tags":[
        "machine",
        "shop"
    ],
    "wof:name":"Hi Performance Machine Inc",
    "wof:placetype":"venue"
},
  "geometry": {"coordinates":[-116.932097,32.855972],"type":"Point"}
}