{
  "type": "Feature",
  "properties": {
    "iso:country":"US",
    "sg:address":"2303 E Brookside Ave",
    "sg:city":"Orange",
    "sg:classifiers":[
        {
            "category":"Professional",
            "subcategory":"Business Services",
            "type":"Services"
        }
    ],
    "sg:phone":"+1 714 637 8437",
    "sg:postcode":"92867",
    "sg:province":"CA",
    "sg:tags":[
        "apparel",
        "on",
        "finished",
        "embroidery"
    ],
    "wof:name":"Rainbow Embroidery Company",
    "wof:placetype":"venue"
},
  "geometry": {"coordinates":[-117.828389,33.815152],"type":"Point"}
}