{
  "type": "Feature",
  "properties": {
    "addr:full":"15188 Main St Hesperia CA 92345",
    "addr:housenumber":"15188",
    "addr:postcode":"92345",
    "addr:street":"Main St",
    "iso:country":"US",
    "sg:address":"15188 Main St",
    "sg:city":"Hesperia",
    "sg:classifiers":[
        {
            "category":"Shopping",
            "subcategory":"Party Supplies",
            "type":"Retail Goods"
        }
    ],
    "sg:phone":"+1 760 949 2803",
    "sg:postcode":"92345",
    "sg:province":"CA",
    "sg:tags":[
        "favors",
        "decoration"
    ],
    "wof:name":"Pericos Party Supply",
    "wof:placetype":"venue"
},
  "geometry": {"coordinates":[-117.33143099999999,34.427052],"type":"Point"}
}