{
  "type": "Feature",
  "properties": {
    "iso:country":"US",
    "sg:address":"7390 el Camino Real",
    "sg:city":"Atascadero",
    "sg:classifiers":[
        {
            "category":"Building & Trades",
            "subcategory":"Electrical",
            "type":"Services"
        }
    ],
    "sg:phone":"+1 805 434 2116",
    "sg:postcode":"93422",
    "sg:province":"CA",
    "sg:tags":[
        "electric",
        "contractor"
    ],
    "wof:name":"Mc Namara Electric",
    "wof:placetype":"venue"
},
  "geometry": {"coordinates":[-120.664018,35.485342],"type":"Point"}
}