{
  "type": "Feature",
  "properties": {
    "addr:full":"401 E Perkins St Ukiah CA 95482",
    "addr:housenumber":"401",
    "addr:postcode":"ca 95482",
    "addr:street":"E Perkins St",
    "iso:country":"US",
    "sg:address":"401 E Perkins St",
    "sg:city":"Ukiah",
    "sg:classifiers":[
        {
            "category":"Personal",
            "subcategory":"Beauty Salon",
            "type":"Services"
        }
    ],
    "sg:phone":"+1 707 462 3637",
    "sg:postcode":"95482",
    "sg:province":"CA",
    "wof:name":"Nails Etc",
    "wof:placetype":"venue"
},
  "geometry": {"coordinates":[-123.20124300000001,39.151046],"type":"Point"}
}