{
  "type": "Feature",
  "properties": {
    "addr:full":"10688 5th Ave Hesperia CA 92345",
    "addr:housenumber":"10688",
    "addr:postcode":"92345",
    "addr:street":"5Th Ave",
    "iso:country":"US",
    "sg:address":"10688 5th Ave",
    "sg:city":"Hesperia",
    "sg:classifiers":[
        {
            "category":"Shopping",
            "subcategory":"Computers & Home Electronics",
            "type":"Retail Goods"
        }
    ],
    "sg:phone":"+1 760 244 8266",
    "sg:postcode":"92345",
    "sg:province":"CA",
    "wof:name":"Clay Sherman Reid",
    "wof:placetype":"venue"
},
  "geometry": {"coordinates":[-117.308595,34.448726],"type":"Point"}
}