{
  "type": "Feature",
  "properties": {
    "addr:full":"5197 Mertensia St Oceanside CA 92056",
    "addr:housenumber":"5197",
    "addr:postcode":"92056",
    "addr:street":"Mertensia St",
    "iso:country":"US",
    "sg:address":"5197 Mertensia St",
    "sg:city":"Oceanside",
    "sg:classifiers":[
        {
            "category":"Banks & Credit Unions",
            "subcategory":"Financial Services",
            "type":"Services"
        }
    ],
    "sg:phone":"+1 760 941 6726",
    "sg:postcode":"92056",
    "sg:province":"CA",
    "sg:tags":[
        "trust",
        "management"
    ],
    "wof:name":"Berridge Family Trust",
    "wof:placetype":"venue"
},
  "geometry": {"coordinates":[-117.26106799999999,33.166181],"type":"Point"}
}