{
  "type": "Feature",
  "properties": {
    "iso:country":"US",
    "sg:address":"5970 Corporate Ave",
    "sg:city":"Cypress",
    "sg:classifiers":[
        {
            "category":"Restaurant",
            "type":"Food & Drink"
        }
    ],
    "sg:phone":"+1 714 226 9686",
    "sg:postcode":"90630",
    "sg:province":"CA",
    "wof:name":"Wendy's Old Fashioned Hamburgers",
    "wof:placetype":"venue"
},
  "geometry": {"coordinates":[-118.028999,33.807899],"type":"Point"}
}