{
  "type": "Feature",
  "properties": {
    "addr:full":"3160 de la Cruz Blvd Santa Clara CA 95054",
    "addr:housenumber":"3160",
    "addr:postcode":"95054",
    "addr:street":"De La Cruz Blvd",
    "iso:country":"US",
    "sg:address":"3160 de la Cruz Blvd",
    "sg:city":"Santa Clara",
    "sg:classifiers":[
        {
            "category":"Professional",
            "type":"Services"
        }
    ],
    "sg:phone":"+1 408 855 1238",
    "sg:postcode":"95054",
    "sg:province":"CA",
    "sg:tags":[
        "establishment"
    ],
    "wof:name":"Linic LLC",
    "wof:placetype":"venue"
},
  "geometry": {"coordinates":[-121.94026599999999,37.380386],"type":"Point"}
}