{
  "type": "Feature",
  "properties": {
    "iso:country":"US",
    "sg:address":"427 Shell Ave",
    "sg:city":"National City",
    "sg:classifiers":[
        {
            "category":"Wholesale",
            "subcategory":"Drugs",
            "type":"Manufacturing & Wholesale Goods"
        }
    ],
    "sg:phone":"+1 619 267 9394",
    "sg:postcode":"91950",
    "sg:province":"CA",
    "sg:tags":[
        "retail",
        "soap"
    ],
    "wof:name":"Bidet Soap",
    "wof:placetype":"venue"
},
  "geometry": {"coordinates":[-117.072552,32.687032],"type":"Point"}
}