{
  "type": "Feature",
  "properties": {
    "addr:full":"561 Fisher Cir Folsom CA 95630",
    "addr:housenumber":"561",
    "addr:postcode":"95630",
    "addr:street":"Fisher Cir",
    "iso:country":"US",
    "sg:address":"561 Fisher Cir",
    "sg:city":"Folsom",
    "sg:classifiers":[
        {
            "category":"Shopping",
            "subcategory":"Clothing, Apparel, & Fashions",
            "type":"Retail Goods"
        }
    ],
    "sg:phone":"+1 916 838 0440",
    "sg:postcode":"95630",
    "sg:province":"CA",
    "sg:tags":[
        "lingerie"
    ],
    "wof:name":"Botticelli Body",
    "wof:placetype":"venue"
},
  "geometry": {"coordinates":[-121.16752700000001,38.654784],"type":"Point"}
}