{
  "type": "Feature",
  "properties": {
    "iso:country":"US",
    "sg:address":"25634 Alessandro Blvd",
    "sg:city":"Moreno Valley",
    "sg:classifiers":[
        {
            "category":"Education",
            "subcategory":"School",
            "type":"Public Place"
        }
    ],
    "sg:phone":"+1 951 485 5600",
    "sg:postcode":"92553",
    "sg:province":"CA",
    "sg:website":"www.mvusd.k12.ca.us",
    "wof:name":"Moreno Valley School District",
    "wof:placetype":"venue"
},
  "geometry": {"coordinates":[-117.21621500000001,33.917264],"type":"Point"}
}