{
  "type": "Feature",
  "properties": {
    "iso:country":"US",
    "sg:address":"5592 W San Madele Ave",
    "sg:city":"Fresno",
    "sg:classifiers":[
        {
            "category":"Retail",
            "subcategory":"Auto Repair",
            "type":"Services"
        }
    ],
    "sg:phone":"+1 559 277 2121",
    "sg:postcode":"93722",
    "sg:province":"CA",
    "sg:tags":[
        "repairing",
        "automobile"
    ],
    "wof:name":"Nef's Automotive",
    "wof:placetype":"venue"
},
  "geometry": {"coordinates":[-119.891079,36.814467],"type":"Point"}
}