{
  "type": "Feature",
  "properties": {
    "addr:full":"1900 Lakeshore Blvd Lakeport CA 95453",
    "addr:housenumber":"1900",
    "addr:postcode":"95453",
    "addr:street":"Lakeshore Blvd",
    "iso:country":"US",
    "sg:address":"1900 Lakeshore Blvd",
    "sg:city":"Lakeport",
    "sg:classifiers":[
        {
            "category":"Real Estate",
            "subcategory":"Real Estate Agent",
            "type":"Services"
        }
    ],
    "sg:phone":"+1 707 263 3000",
    "sg:postcode":"95453",
    "sg:province":"CA",
    "sg:tags":[
        "appraiser"
    ],
    "wof:name":"Pat Sanchez Appraisals",
    "wof:placetype":"venue"
},
  "geometry": {"coordinates":[-122.915139,39.055831],"type":"Point"}
}