{
  "type": "Feature",
  "properties": {
    "iso:country":"US",
    "sg:address":"3728 Atlantic Ave",
    "sg:city":"Long Beach",
    "sg:classifiers":[
        {
            "category":"Real Estate",
            "subcategory":"Real Estate Services",
            "type":"Services"
        },
        {
            "category":"Banks & Credit Unions",
            "subcategory":"Financial Services",
            "type":"Services"
        }
    ],
    "sg:phone":"+1 562 989 4091",
    "sg:postcode":"90807",
    "sg:province":"CA",
    "sg:tags":[
        "broker",
        "mortgage"
    ],
    "wof:name":"Golden Empire Mortgage",
    "wof:placetype":"venue"
},
  "geometry": {"coordinates":[-118.184999,33.825247],"type":"Point"}
}