{
  "type": "Feature",
  "properties": {
    "addr:full":"30 W Colorado Blvd Pasadena CA 91105",
    "addr:housenumber":"30",
    "addr:postcode":"91105",
    "addr:street":"W Colorado Blvd",
    "iso:country":"US",
    "sg:address":"30 W Colorado Blvd",
    "sg:city":"Pasadena",
    "sg:classifiers":[
        {
            "category":"Shopping",
            "subcategory":"Gifts & Souvenirs",
            "type":"Retail Goods"
        }
    ],
    "sg:phone":"+1 626 449 5599",
    "sg:postcode":"91105",
    "sg:province":"CA",
    "sg:tags":[
        "shop"
    ],
    "wof:name":"Perfect Gift",
    "wof:placetype":"venue"
},
  "geometry": {"coordinates":[-118.150464,34.145773],"type":"Point"}
}