{
  "type": "Feature",
  "properties": {
    "addr:full":"10863 Iron Mountain Rd Redding CA 96001",
    "addr:housenumber":"10863",
    "addr:postcode":"96001",
    "addr:street":"Iron Mountain Rd",
    "iso:country":"US",
    "sg:address":"10863 Iron Mountain Rd",
    "sg:city":"Redding",
    "sg:classifiers":[
        {
            "category":"Wholesale",
            "subcategory":"Construction Materials",
            "type":"Manufacturing & Wholesale Goods"
        }
    ],
    "sg:phone":"+1 530 246 0405",
    "sg:postcode":"96001",
    "sg:province":"CA",
    "sg:tags":[
        "lumber"
    ],
    "sg:website":"www.kellerlumbersales.com",
    "wof:name":"Keller Lumber Sales Inc",
    "wof:placetype":"venue"
},
  "geometry": {"coordinates":[-122.463571,40.603497],"type":"Point"}
}