{
  "type": "Feature",
  "properties": {
    "iso:country":"US",
    "sg:address":"2040 N Winery Ave",
    "sg:city":"Fresno",
    "sg:classifiers":[
        {
            "category":"Shopping",
            "subcategory":"Bicycles & Sporting Goods",
            "type":"Retail Goods"
        }
    ],
    "sg:phone":"+1 559 251 1427",
    "sg:postcode":"93703",
    "sg:province":"CA",
    "wof:name":"Mroutdoor",
    "wof:placetype":"venue"
},
  "geometry": {"coordinates":[-119.731677,36.770049],"type":"Point"}
}