{
  "type": "Feature",
  "properties": {
    "iso:country":"US",
    "sg:address":"21510 Schoenborn St",
    "sg:city":"Canoga Park",
    "sg:classifiers":[
        {
            "category":"Retail",
            "subcategory":"Auto Repair",
            "type":"Services"
        }
    ],
    "sg:phone":"+1 818 992 7871",
    "sg:postcode":"91304",
    "sg:province":"CA",
    "sg:tags":[
        "body",
        "shop"
    ],
    "wof:name":"Westside Valley Auto Body",
    "wof:placetype":"venue"
},
  "geometry": {"coordinates":[-118.59899900000001,34.221001],"type":"Point"}
}