{
  "type": "Feature",
  "properties": {
    "addr:full":"203 W 6th St Los Angeles CA 90014",
    "addr:housenumber":"203",
    "addr:postcode":"90014",
    "addr:street":"W 6Th St",
    "iso:country":"US",
    "sg:address":"203 W 6th St",
    "sg:city":"Los Angeles",
    "sg:classifiers":[
        {
            "category":"Shopping",
            "subcategory":"Clothing, Apparel, & Fashions",
            "type":"Retail Goods"
        }
    ],
    "sg:phone":"+1 213 612 0140",
    "sg:postcode":"90014",
    "sg:province":"CA",
    "sg:tags":[
        "sport",
        "wear"
    ],
    "wof:name":"B B Fashions",
    "wof:placetype":"venue"
},
  "geometry": {"coordinates":[-118.25196800000001,34.046693],"type":"Point"}
}