{
  "type": "Feature",
  "properties": {
    "iso:country":"US",
    "sg:address":"18305 Hawthorne Blvd",
    "sg:city":"Torrance",
    "sg:classifiers":[
        {
            "category":"Shopping",
            "subcategory":"Pets & Pet Supplies",
            "type":"Retail Goods"
        }
    ],
    "sg:phone":"+1 310 542 6442",
    "sg:postcode":"90504",
    "sg:province":"CA",
    "sg:tags":[
        "store"
    ],
    "wof:name":"Pet City Torrance",
    "wof:placetype":"venue"
},
  "geometry": {"coordinates":[-118.352997,33.8643],"type":"Point"}
}