{
  "type": "Feature",
  "properties": {
    "addr:full":"1941 Johnson Ave San Luis Obispo CA 93401",
    "addr:housenumber":"1941",
    "addr:postcode":"93401",
    "addr:street":"Johnson Ave",
    "iso:country":"US",
    "sg:address":"1941 Johnson Ave",
    "sg:city":"San Luis Obispo",
    "sg:classifiers":[
        {
            "category":"Organizations",
            "subcategory":"Community Association",
            "type":"Services"
        }
    ],
    "sg:phone":"+1 805 543 1233",
    "sg:postcode":"93401",
    "sg:province":"CA",
    "sg:tags":[
        "military"
    ],
    "wof:name":"Veterans Affairs Community",
    "wof:placetype":"venue"
},
  "geometry": {"coordinates":[-120.649559,35.277787],"type":"Point"}
}