{
  "type": "Feature",
  "properties": {
    "addr:full":"1428 S Central Park Ave W Anaheim CA 92802",
    "addr:housenumber":"1428",
    "addr:postcode":"92802",
    "addr:street":"S Central Park Ave W",
    "iso:country":"US",
    "sg:address":"1428 S Central Park Ave W",
    "sg:city":"Anaheim",
    "sg:classifiers":[
        {
            "category":"Wholesale",
            "subcategory":"Durable Goods & Equipment",
            "type":"Manufacturing & Wholesale Goods"
        }
    ],
    "sg:phone":"+1 714 533 8118",
    "sg:postcode":"92802",
    "sg:province":"CA",
    "sg:tags":[
        "importer"
    ],
    "wof:name":"Apolio Athletics",
    "wof:placetype":"venue"
},
  "geometry": {"coordinates":[-117.931828,33.825707],"type":"Point"}
}