{
  "type": "Feature",
  "properties": {
    "iso:country":"US",
    "sg:address":"301 N Canon Drive Suite 326",
    "sg:city":"Beverly Hills",
    "sg:classifiers":[
        {
            "category":"Banks & Credit Unions",
            "subcategory":"Investment Brokerage",
            "type":"Services"
        }
    ],
    "sg:phone":"+1 310 275 9396",
    "sg:postcode":"90210",
    "sg:province":"CA",
    "sg:tags":[
        "investing"
    ],
    "wof:name":"Sardacorp",
    "wof:placetype":"venue"
},
  "geometry": {"coordinates":[-118.399525,34.069211],"type":"Point"}
}