{
  "type": "Feature",
  "properties": {
    "addr:full":"397 E 18th St San Bernardino CA 92404",
    "addr:housenumber":"397",
    "addr:postcode":"92404",
    "addr:street":"E 18Th St",
    "iso:country":"US",
    "sg:address":"397 E 18th St",
    "sg:city":"San Bernardino",
    "sg:classifiers":[
        {
            "category":"Freight",
            "type":"Transportation"
        }
    ],
    "sg:phone":"+1 909 883 0822",
    "sg:postcode":"92404",
    "sg:province":"CA",
    "sg:tags":[
        "operator",
        "local",
        "trucking"
    ],
    "wof:name":"Henry Lf Trucking",
    "wof:placetype":"venue"
},
  "geometry": {"coordinates":[-117.276751,34.131046],"type":"Point"}
}