{
  "type": "Feature",
  "properties": {
    "addr:full":"3427 Evergreen Cir West Sacramento CA 95691",
    "addr:housenumber":"3427",
    "addr:postcode":"95691",
    "addr:street":"Evergreen Cir",
    "iso:country":"US",
    "sg:address":"3427 Evergreen Cir",
    "sg:city":"West Sacramento",
    "sg:classifiers":[
        {
            "category":"Building & Trades",
            "subcategory":"Construction",
            "type":"Services"
        }
    ],
    "sg:phone":"+1 916 376 0385",
    "sg:postcode":"95691",
    "sg:province":"CA",
    "sg:tags":[
        "concrete",
        "contractor"
    ],
    "wof:name":"San Jose Concrete",
    "wof:placetype":"venue"
},
  "geometry": {"coordinates":[-121.556113,38.576289],"type":"Point"}
}