{
  "type": "Feature",
  "properties": {
    "addr:full":"21644 Ave 196 Strathmore CA 93267",
    "addr:housenumber":"21644",
    "addr:postcode":"93267",
    "addr:street":"Ave 196",
    "iso:country":"US",
    "sg:address":"21644 Ave 196",
    "sg:city":"Strathmore",
    "sg:classifiers":[
        {
            "category":"Education",
            "subcategory":"School",
            "type":"Public Place"
        }
    ],
    "sg:phone":"+1 559 568 1741",
    "sg:postcode":"93267",
    "sg:province":"CA",
    "sg:tags":[
        "district"
    ],
    "wof:name":"Sunnyside Elementary School",
    "wof:placetype":"venue"
},
  "geometry": {"coordinates":[-119.086223,36.14557],"type":"Point"}
}