{
  "type": "Feature",
  "properties": {
    "iso:country":"US",
    "sg:address":"70 Lum St",
    "sg:city":"Weott",
    "sg:classifiers":[
        {
            "category":"Government",
            "subcategory":"Fire Station",
            "type":"Public Place"
        }
    ],
    "sg:phone":"+1 707 946 1953",
    "sg:postcode":"95571",
    "sg:province":"CA",
    "sg:tags":[
        "department"
    ],
    "wof:name":"Wieott Volunteer Fire Dept",
    "wof:placetype":"venue"
},
  "geometry": {"coordinates":[-123.922512,40.323497],"type":"Point"}
}