{
  "type": "Feature",
  "properties": {
    "iso:country":"US",
    "sg:address":"2441 Newcastle Ave",
    "sg:city":"Cardiff By Sea",
    "sg:classifiers":[
        {
            "category":"Building & Trades",
            "subcategory":"Electrical",
            "type":"Services"
        }
    ],
    "sg:phone":"+1 760 753 4440",
    "sg:postcode":"92007",
    "sg:province":"CA",
    "sg:tags":[
        "electric",
        "contractor"
    ],
    "wof:name":"Del Mar Electric",
    "wof:placetype":"venue"
},
  "geometry": {"coordinates":[-117.27750899999999,33.016221],"type":"Point"}
}