{
  "type": "Feature",
  "properties": {
    "addr:full":"39665 Benavente Ave Fremont CA 94539",
    "addr:housenumber":"39665",
    "addr:postcode":"94539",
    "addr:street":"Benavente Ave",
    "iso:country":"US",
    "sg:address":"39665 Benavente Ave",
    "sg:city":"Fremont",
    "sg:classifiers":[
        {
            "category":"Shopping",
            "type":"Retail Goods"
        }
    ],
    "sg:phone":"+1 510 656 6136",
    "sg:postcode":"94539",
    "sg:province":"CA",
    "sg:tags":[
        "merchandise"
    ],
    "wof:name":"ADT Iser",
    "wof:placetype":"venue"
},
  "geometry": {"coordinates":[-121.953763,37.560766],"type":"Point"}
}