{
  "type": "Feature",
  "properties": {
    "addr:full":"555 Broadway Chula Vista CA 91910",
    "addr:housenumber":"555",
    "addr:postcode":"91910",
    "addr:street":"Broadway",
    "iso:country":"US",
    "sg:address":"555 Broadway",
    "sg:city":"Chula Vista",
    "sg:classifiers":[
        {
            "category":"Banks & Credit Unions",
            "subcategory":"Financial Services",
            "type":"Services"
        }
    ],
    "sg:phone":"+1 619 426 2104",
    "sg:postcode":"91910",
    "sg:province":"CA",
    "sg:tags":[
        "international",
        "trade"
    ],
    "wof:name":"Prachi Trading",
    "wof:placetype":"venue"
},
  "geometry": {"coordinates":[-117.088735,32.629432],"type":"Point"}
}