{
  "type": "Feature",
  "properties": {
    "iso:country":"US",
    "sg:address":"170 N Main St",
    "sg:city":"Porterville",
    "sg:classifiers":[
        {
            "category":"Bars & Pubs",
            "type":"Food & Drink"
        },
        {
            "category":"Bars & Pubs",
            "subcategory":"Lounge",
            "type":"Food & Drink"
        }
    ],
    "sg:phone":"+1 559 784 5912",
    "sg:postcode":"93257",
    "sg:province":"CA",
    "sg:tags":[
        "brew",
        "cocktail"
    ],
    "wof:name":"The Mecca",
    "wof:placetype":"venue"
},
  "geometry": {"coordinates":[-119.01625,36.06838],"type":"Point"}
}