{
  "type": "Feature",
  "properties": {
    "addr:full":"800 Portola Dr Del Rey Oaks CA 93940",
    "addr:housenumber":"800",
    "addr:postcode":"93940",
    "addr:street":"Portola Dr Del",
    "iso:country":"US",
    "sg:address":"800 Portola Dr",
    "sg:city":"Del Rey Oaks",
    "sg:classifiers":[
        {
            "category":"Personal",
            "subcategory":"Beauty Salon",
            "type":"Services"
        }
    ],
    "sg:phone":"+1 831 394 8028",
    "sg:postcode":"93940",
    "sg:province":"CA",
    "wof:name":"Peninsula Hair Cutting Co",
    "wof:placetype":"venue"
},
  "geometry": {"coordinates":[-121.847465,36.597049],"type":"Point"}
}