{
  "type": "Feature",
  "properties": {
    "addr:full":"3425 W Whitesbridge Ave Fresno CA 93706",
    "addr:housenumber":"3425",
    "addr:postcode":"93706",
    "addr:street":"W Whitesbridge Ave",
    "iso:country":"US",
    "sg:address":"3425 W Whitesbridge Ave",
    "sg:city":"Fresno",
    "sg:classifiers":[
        {
            "category":"Farming",
            "subcategory":"Farm",
            "type":"Manufacturing & Wholesale Goods"
        }
    ],
    "sg:phone":"+1 559 289 5371",
    "sg:postcode":"93706",
    "sg:province":"CA",
    "sg:tags":[
        "crop",
        "general"
    ],
    "wof:name":"Flynn Farms",
    "wof:placetype":"venue"
},
  "geometry": {"coordinates":[-119.86217499999999,36.735419],"type":"Point"}
}