{
  "type": "Feature",
  "properties": {
    "addr:full":"340 Van Ness Ave Ste D Torrance CA 90501",
    "addr:housenumber":"340",
    "addr:postcode":"90501",
    "addr:street":"Van Ness Ave Ste D",
    "iso:country":"US",
    "sg:address":"340 Van Ness Ave Ste D",
    "sg:city":"Torrance",
    "sg:classifiers":[
        {
            "category":"Retail",
            "subcategory":"Auto Repair",
            "type":"Services"
        }
    ],
    "sg:phone":"+1 310 320 3302",
    "sg:postcode":"90501",
    "sg:province":"CA",
    "wof:name":"Edelweiss",
    "wof:placetype":"venue"
},
  "geometry": {"coordinates":[-118.318001,33.846802],"type":"Point"}
}