{
  "type": "Feature",
  "properties": {
    "iso:country":"US",
    "sg:address":"2150 E Foothill Blvd",
    "sg:city":"Glendora",
    "sg:classifiers":[
        {
            "category":"Professional",
            "subcategory":"Management & Consulting",
            "type":"Services"
        }
    ],
    "sg:phone":"+1 626 963 6025",
    "sg:postcode":"91741",
    "sg:province":"CA",
    "sg:tags":[
        "consultant"
    ],
    "wof:name":"John Dye Metal Fab",
    "wof:placetype":"venue"
},
  "geometry": {"coordinates":[-117.82505500000001,34.136147],"type":"Point"}
}