{
  "type": "Feature",
  "properties": {
    "addr:full":"1810 Cypress Ave San Diego CA 92103",
    "addr:housenumber":"1810",
    "addr:postcode":"92103",
    "addr:street":"Cypress Ave",
    "iso:country":"US",
    "sg:address":"1810 Cypress Ave",
    "sg:city":"San Diego",
    "sg:classifiers":[
        {
            "category":"Professional",
            "type":"Services"
        }
    ],
    "sg:phone":"+1 619 501 3152",
    "sg:postcode":"92103",
    "sg:province":"CA",
    "wof:name":"Sabrina and Juan Carlos Flores",
    "wof:placetype":"venue"
},
  "geometry": {"coordinates":[-117.145867,32.744426],"type":"Point"}
}