{
  "type": "Feature",
  "properties": {
    "iso:country":"US",
    "sg:address":"7264 Auburn Blvd",
    "sg:city":"Citrus Heights",
    "sg:classifiers":[
        {
            "category":"Building & Trades",
            "subcategory":"Plumbing",
            "type":"Services"
        }
    ],
    "sg:phone":"+1 916 722 5451",
    "sg:postcode":"95610",
    "sg:province":"CA",
    "sg:tags":[
        "conditioning",
        "air",
        "system",
        "contractor"
    ],
    "wof:name":"Capitol Mechanical",
    "wof:placetype":"venue"
},
  "geometry": {"coordinates":[-121.290249,38.697875],"type":"Point"}
}