{
  "type": "Feature",
  "properties": {
    "iso:country":"US",
    "sg:address":"2155 San Jose Avenue",
    "sg:city":"San Francisco",
    "sg:classifiers":[
        {
            "category":"Education",
            "subcategory":"Preschool",
            "type":"Public Place"
        },
        {
            "category":"Education",
            "subcategory":"School",
            "type":"Public Place"
        }
    ],
    "sg:phone":"+1 415 334 3267",
    "sg:postcode":"94112",
    "sg:province":"CA",
    "sg:tags":[
        "elementary"
    ],
    "wof:name":"Economic Opportunity Council of San Francisco",
    "wof:placetype":"venue"
},
  "geometry": {"coordinates":[-122.445999,37.721699],"type":"Point"}
}