{
  "type": "Feature",
  "properties": {
    "iso:country":"US",
    "sg:address":"1359 Van Dyke Ave",
    "sg:city":"San Francisco",
    "sg:classifiers":[
        {
            "category":"Professional",
            "type":"Services"
        }
    ],
    "sg:phone":"+1 415 822 2620",
    "sg:postcode":"94124",
    "sg:province":"CA",
    "sg:tags":[
        "establishment"
    ],
    "wof:name":"Driveline Specialties",
    "wof:placetype":"venue"
},
  "geometry": {"coordinates":[-122.38784,37.726357],"type":"Point"}
}