{
  "type": "Feature",
  "properties": {
    "addr:full":"12160 Community Rd Poway CA 92064",
    "addr:housenumber":"12160",
    "addr:postcode":"ca 92064",
    "addr:street":"Community Rd",
    "iso:country":"US",
    "sg:address":"12160 Community Rd",
    "sg:city":"Poway",
    "sg:classifiers":[
        {
            "category":"Autos & Motor Vehicles",
            "subcategory":"Boat Sales",
            "type":"Retail Goods"
        }
    ],
    "sg:phone":"+1 858 486 4380",
    "sg:postcode":"92064",
    "sg:province":"CA",
    "sg:tags":[
        "watercraft"
    ],
    "sg:website":"www.albaaction.com",
    "wof:name":"Alba Action Sports",
    "wof:placetype":"venue"
},
  "geometry": {"coordinates":[-117.046121,32.938851],"type":"Point"}
}