{
  "type": "Feature",
  "properties": {
    "addr:full":"1661 W Lancaster Blvd Lancaster CA 93534",
    "addr:housenumber":"1661",
    "addr:postcode":"93534",
    "addr:street":"W Lancaster Blvd",
    "iso:country":"US",
    "sg:address":"1661 W Lancaster Blvd",
    "sg:city":"Lancaster",
    "sg:classifiers":[
        {
            "category":"Professional",
            "type":"Services"
        }
    ],
    "sg:phone":"+1 661 951 9988",
    "sg:postcode":"93534",
    "sg:province":"CA",
    "sg:tags":[
        "establishment"
    ],
    "wof:name":"Feeling Hopeless Feeling Dsprt",
    "wof:placetype":"venue"
},
  "geometry": {"coordinates":[-118.160183,34.69679],"type":"Point"}
}