{
  "type": "Feature",
  "properties": {
    "addr:full":"2D Avenue & E 10th Oakland CA 94601",
    "addr:housenumber":"2d",
    "addr:postcode":"94601",
    "addr:street":"Avenue & E 10Th",
    "iso:country":"US",
    "sg:address":"2D Avenue & E 10th",
    "sg:city":"Oakland",
    "sg:classifiers":[
        {
            "category":"Social Services",
            "subcategory":"Child Care",
            "type":"Services"
        },
        {
            "category":"Education",
            "subcategory":"University",
            "type":"Public Place"
        }
    ],
    "sg:phone":"+1 510 464 3575",
    "sg:postcode":"94601",
    "sg:province":"CA",
    "sg:tags":[
        "college",
        "day"
    ],
    "wof:name":"Laney College",
    "wof:placetype":"venue"
},
  "geometry": {"coordinates":[-122.218002,37.779701],"type":"Point"}
}