{
  "type": "Feature",
  "properties": {
    "iso:country":"US",
    "sg:address":"2832 College Avenue",
    "sg:city":"Berkeley",
    "sg:classifiers":[
        {
            "category":"Professional",
            "subcategory":"Lawyer & Legal Services",
            "type":"Services"
        }
    ],
    "sg:phone":"+1 510 845 4457",
    "sg:postcode":"94705",
    "sg:province":"CA",
    "sg:tags":[
        "divorce",
        "law",
        "family"
    ],
    "sg:website":"www.wingermediation.com",
    "wof:name":"Mediation & Collaborative Practice Of Ariel B. Winger",
    "wof:placetype":"venue"
},
  "geometry": {"coordinates":[-122.25353,37.858801],"type":"Point"}
}