{
  "type": "Feature",
  "properties": {
    "addr:full":"21384 Ramona Ave Apple Valley CA 92307",
    "addr:housenumber":"21384",
    "addr:postcode":"92307",
    "addr:street":"Ramona Ave",
    "iso:country":"US",
    "sg:address":"21384 Ramona Ave",
    "sg:city":"Apple Valley",
    "sg:classifiers":[
        {
            "category":"Manufacturing",
            "subcategory":"Tools & Machinery",
            "type":"Manufacturing & Wholesale Goods"
        }
    ],
    "sg:phone":"+1 760 240 4726",
    "sg:postcode":"92307",
    "sg:province":"CA",
    "sg:tags":[
        "residential",
        "lighting",
        "fixture",
        "mfg"
    ],
    "wof:name":"Robmar",
    "wof:placetype":"venue"
},
  "geometry": {"coordinates":[-117.19754,34.519042],"type":"Point"}
}