{
  "type": "Feature",
  "properties": {
    "addr:full":"9850 52nd St Riverside CA 92509",
    "addr:housenumber":"9850",
    "addr:postcode":"92509",
    "addr:street":"52Nd St",
    "iso:country":"US",
    "sg:address":"9850 52nd St",
    "sg:city":"Riverside",
    "sg:classifiers":[
        {
            "category":"Manufacturing",
            "subcategory":"Chemicals & Compounds",
            "type":"Manufacturing & Wholesale Goods"
        }
    ],
    "sg:phone":"+1 951 681 3336",
    "sg:postcode":"92509",
    "sg:province":"CA",
    "sg:tags":[
        "treating",
        "heat",
        "metal"
    ],
    "wof:name":"D & S Sales",
    "wof:placetype":"venue"
},
  "geometry": {"coordinates":[-117.50047600000001,33.992658],"type":"Point"}
}