{
  "type": "Feature",
  "properties": {
    "iso:country":"US",
    "sg:address":"110 N Soto St",
    "sg:city":"Los Angeles",
    "sg:classifiers":[
        {
            "category":"Retail",
            "subcategory":"Auto Repair",
            "type":"Services"
        }
    ],
    "sg:phone":"+1 323 264 6614",
    "sg:postcode":"90033",
    "sg:province":"CA",
    "sg:tags":[
        "body",
        "shop"
    ],
    "wof:name":"A & B Auto Body",
    "wof:placetype":"venue"
},
  "geometry": {"coordinates":[-118.209,34.043999],"type":"Point"}
}