{
  "type": "Feature",
  "properties": {
    "addr:full":"16390 Whitefield Ct Chino Hills CA 91709",
    "addr:housenumber":"16390",
    "addr:postcode":"91709",
    "addr:street":"Whitefield Ct",
    "iso:country":"US",
    "sg:address":"16390 Whitefield Ct",
    "sg:city":"Chino Hills",
    "sg:classifiers":[
        {
            "category":"Utilities",
            "subcategory":"Telephone",
            "type":"Services"
        }
    ],
    "sg:phone":"+1 909 606 2785",
    "sg:postcode":"91709",
    "sg:province":"CA",
    "sg:tags":[
        "communications",
        "computer",
        "related"
    ],
    "wof:name":"Pk Consulting",
    "wof:placetype":"venue"
},
  "geometry": {"coordinates":[-117.70907200000001,33.955971],"type":"Point"}
}