{
  "type": "Feature",
  "properties": {
    "addr:full":"1456 Professional Dr Petaluma CA 94954",
    "addr:housenumber":"1456",
    "addr:postcode":"94954",
    "addr:street":"Professional Dr",
    "iso:country":"US",
    "sg:address":"1456 Professional Dr",
    "sg:city":"Petaluma",
    "sg:classifiers":[
        {
            "category":"Health Services",
            "subcategory":"Health Practitioner",
            "type":"Services"
        }
    ],
    "sg:phone":"+1 707 763 2537",
    "sg:postcode":"94954",
    "sg:province":"CA",
    "sg:tags":[
        "pathologist",
        "speech"
    ],
    "wof:name":"Speech & Language Svc",
    "wof:placetype":"venue"
},
  "geometry": {"coordinates":[-122.633751,38.255067],"type":"Point"}
}