{
  "type": "Feature",
  "properties": {
    "addr:full":"3726 Earle Ave Rosemead CA 91770",
    "addr:housenumber":"3726",
    "addr:postcode":"91770",
    "addr:street":"Earle Ave",
    "iso:country":"US",
    "sg:address":"3726 Earle Ave",
    "sg:city":"Rosemead",
    "sg:classifiers":[
        {
            "category":"Professional",
            "type":"Services"
        }
    ],
    "sg:phone":"+1 626 288 5350",
    "sg:postcode":"91770",
    "sg:province":"CA",
    "wof:name":"Bugarins Nursery",
    "wof:placetype":"venue"
},
  "geometry": {"coordinates":[-118.08480900000001,34.07566],"type":"Point"}
}