{
  "type": "Feature",
  "properties": {
    "addr:full":"116 McPherson St Santa Cruz CA 95060",
    "addr:housenumber":"116",
    "addr:postcode":"95060",
    "addr:street":"Mcpherson St",
    "iso:country":"US",
    "sg:address":"116 McPherson St",
    "sg:city":"Santa Cruz",
    "sg:classifiers":[
        {
            "category":"Retail",
            "subcategory":"Repair Shop",
            "type":"Services"
        }
    ],
    "sg:phone":"+1 831 459 9944",
    "sg:postcode":"95060",
    "sg:province":"CA",
    "sg:tags":[
        "welding"
    ],
    "wof:name":"Arc Tec",
    "wof:placetype":"venue"
},
  "geometry": {"coordinates":[-122.049094,36.960144],"type":"Point"}
}