{
  "type": "Feature",
  "properties": {
    "iso:country":"US",
    "sg:address":"1610 N Lemon St",
    "sg:city":"Anaheim",
    "sg:classifiers":[
        {
            "category":"Restaurant",
            "type":"Food & Drink"
        }
    ],
    "sg:phone":"+1 714 441 0888",
    "sg:postcode":"92801",
    "sg:province":"CA",
    "wof:name":"La Express",
    "wof:placetype":"venue"
},
  "geometry": {"coordinates":[-117.914001,33.8629],"type":"Point"}
}