{
  "type": "Feature",
  "properties": {
    "iso:country":"US",
    "sg:address":"470 S Rancho Santa Fe Rd",
    "sg:city":"San Marcos",
    "sg:classifiers":[
        {
            "category":"Professional",
            "subcategory":"Business Services",
            "type":"Services"
        }
    ],
    "sg:phone":"+1 760 599 1040",
    "sg:postcode":"92078",
    "sg:province":"CA",
    "sg:tags":[
        "notary"
    ],
    "wof:name":"Palomar Tax & Business Mgmt",
    "wof:placetype":"venue"
},
  "geometry": {"coordinates":[-117.203889,33.139227],"type":"Point"}
}