{
  "type": "Feature",
  "properties": {
    "addr:full":"3801 Miranda Ave Palo Alto CA 94304",
    "addr:housenumber":"3801",
    "addr:postcode":"94304",
    "addr:street":"Miranda Ave",
    "iso:country":"US",
    "sg:address":"3801 Miranda Ave",
    "sg:city":"Palo Alto",
    "sg:classifiers":[
        {
            "category":"Building & Trades",
            "subcategory":"Cleaning & Sanitation",
            "type":"Services"
        }
    ],
    "sg:phone":"+1 650 424 1164",
    "sg:postcode":"94304",
    "sg:province":"CA",
    "sg:tags":[
        "janitor"
    ],
    "wof:name":"Neal's Janitorial Svc",
    "wof:placetype":"venue"
},
  "geometry": {"coordinates":[-122.145713,37.404565],"type":"Point"}
}