{
  "type": "Feature",
  "properties": {
    "iso:country":"US",
    "sg:address":"8081 Holland Dr",
    "sg:city":"Huntington Beach",
    "sg:classifiers":[
        {
            "category":"Building & Trades",
            "subcategory":"Landscaping Services",
            "type":"Services"
        }
    ],
    "sg:phone":"+1 714 841 3132",
    "sg:postcode":"92647",
    "sg:province":"CA",
    "wof:name":"Fitzgerald Tree Service",
    "wof:placetype":"venue"
},
  "geometry": {"coordinates":[-117.988874,33.710325],"type":"Point"}
}