{
  "type": "Feature",
  "properties": {
    "addr:full":"3451 W Olympic Blvd Los Angeles CA 90019",
    "addr:housenumber":"3451",
    "addr:postcode":"90019",
    "addr:street":"W Olympic Blvd",
    "iso:country":"US",
    "sg:address":"3451 W Olympic Blvd",
    "sg:city":"Los Angeles",
    "sg:classifiers":[
        {
            "category":"Retail",
            "subcategory":"Auto Repair",
            "type":"Services"
        }
    ],
    "sg:phone":"+1 323 733 8621",
    "sg:postcode":"90019",
    "sg:province":"CA",
    "wof:name":"Econo Lube N Tune Brakes Number 18",
    "wof:placetype":"venue"
},
  "geometry": {"coordinates":[-118.314003,34.052502],"type":"Point"}
}