{
  "type": "Feature",
  "properties": {
    "iso:country":"US",
    "sg:address":"15245 Nubia St",
    "sg:city":"Baldwin Park",
    "sg:classifiers":[
        {
            "category":"Retail",
            "subcategory":"Auto Repair",
            "type":"Services"
        }
    ],
    "sg:phone":"+1 626 960 5341",
    "sg:postcode":"91706",
    "sg:province":"CA",
    "sg:tags":[
        "exchanging",
        "engine"
    ],
    "sg:website":"www.gex.com",
    "wof:name":"GEX Intl Corp",
    "wof:placetype":"venue"
},
  "geometry": {"coordinates":[-117.946457,34.103397],"type":"Point"}
}