{
  "type": "Feature",
  "properties": {
    "addr:full":"8765 W Pico Blvd Los Angeles CA 90035",
    "addr:housenumber":"8765",
    "addr:postcode":"90035",
    "addr:street":"W Pico Blvd",
    "iso:country":"US",
    "sg:address":"8765 W Pico Blvd",
    "sg:city":"Los Angeles",
    "sg:classifiers":[
        {
            "category":"Shopping",
            "subcategory":"Gifts & Souvenirs",
            "type":"Retail Goods"
        }
    ],
    "sg:phone":"+1 310 278 2233",
    "sg:postcode":"90035",
    "sg:province":"CA",
    "sg:tags":[
        "shop"
    ],
    "wof:name":"Golden City",
    "wof:placetype":"venue"
},
  "geometry": {"coordinates":[-118.38341800000001,34.054777],"type":"Point"}
}