{
  "type": "Feature",
  "properties": {
    "iso:country":"US",
    "sg:address":"1109 E Champlain Dr",
    "sg:city":"Fresno",
    "sg:phone":"+1 559 434 5511",
    "sg:postcode":"93720",
    "sg:province":"CA",
    "wof:name":"Azam Clinical Skin & Body Care",
    "wof:placetype":"venue"
},
  "geometry": {"coordinates":[-119.76351099999999,36.87139],"type":"Point"}
}