{
  "type": "Feature",
  "properties": {
    "addr:full":"1109 E Champlain Dr Fresno CA 93720",
    "addr:housenumber":"1109",
    "addr:postcode":"93720",
    "addr:street":"E Champlain Dr",
    "iso:country":"US",
    "sg:address":"1109 E Champlain Dr",
    "sg:city":"Fresno",
    "sg:phone":"+1 559 434 5511",
    "sg:postcode":"93720",
    "sg:province":"CA",
    "wof:name":"Azam Clinical Skin & Body Care",
    "wof:placetype":"venue"
},
  "geometry": {"coordinates":[-119.76351099999999,36.87139],"type":"Point"}
}