{
  "type": "Feature",
  "properties": {
    "addr:full":"4271 Myrtle Ave San Diego CA 92105",
    "addr:housenumber":"4271",
    "addr:postcode":"92105",
    "addr:street":"Myrtle Ave",
    "iso:country":"US",
    "sg:address":"4271 Myrtle Ave",
    "sg:city":"San Diego",
    "sg:classifiers":[
        {
            "category":"Education",
            "subcategory":"School",
            "type":"Public Place"
        }
    ],
    "sg:phone":"+1 619 640 4000",
    "sg:postcode":"92105",
    "sg:province":"CA",
    "sg:tags":[
        "high",
        "middle",
        "elementary"
    ],
    "wof:name":"San Diego Unified School District",
    "wof:placetype":"venue"
},
  "geometry": {"coordinates":[-117.102682,32.742002],"type":"Point"}
}