{
  "type": "Feature",
  "properties": {
    "addr:full":"327 W Compton Blvd Compton CA 90220",
    "addr:housenumber":"327",
    "addr:postcode":"90220",
    "addr:street":"W Compton Blvd",
    "iso:country":"US",
    "sg:address":"327 W Compton Blvd",
    "sg:city":"Compton",
    "sg:classifiers":[
        {
            "category":"Personal",
            "subcategory":"Beauty Salon",
            "type":"Services"
        }
    ],
    "sg:phone":"+1 310 639 7985",
    "sg:postcode":"90220",
    "sg:province":"CA",
    "wof:name":"House Of Braids II",
    "wof:placetype":"venue"
},
  "geometry": {"coordinates":[-118.22820400000001,33.896028],"type":"Point"}
}