{
  "type": "Feature",
  "properties": {
    "addr:full":"802 Magnolia Ave Corona CA 92879",
    "addr:housenumber":"802",
    "addr:postcode":"92879",
    "addr:street":"Magnolia Ave",
    "iso:country":"US",
    "sg:address":"802 Magnolia Ave",
    "sg:city":"Corona",
    "sg:classifiers":[
        {
            "category":"Health Services",
            "subcategory":"Medical Lab",
            "type":"Services"
        }
    ],
    "sg:phone":"+1 951 279 0494",
    "sg:postcode":"92879",
    "sg:province":"CA",
    "sg:tags":[
        "laboratory"
    ],
    "wof:name":"Corona Laser Ctr",
    "wof:placetype":"venue"
},
  "geometry": {"coordinates":[-117.552869,33.859602],"type":"Point"}
}