{
  "type": "Feature",
  "properties": {
    "iso:country":"US",
    "sg:address":"16550 Vanowen St",
    "sg:city":"Van Nuys",
    "sg:classifiers":[
        {
            "category":"Travel",
            "subcategory":"Travel Agent",
            "type":"Entertainment"
        }
    ],
    "sg:phone":"+1 323 550 1195",
    "sg:postcode":"91406",
    "sg:province":"CA",
    "sg:tags":[
        "agency"
    ],
    "wof:name":"Ultra Travel",
    "wof:placetype":"venue"
},
  "geometry": {"coordinates":[-118.493646,34.19382],"type":"Point"}
}