{
  "type": "Feature",
  "properties": {
    "addr:full":"3428 Albee St Eureka CA 95503",
    "addr:housenumber":"3428",
    "addr:postcode":"95503",
    "addr:street":"Albee St",
    "iso:country":"US",
    "sg:address":"3428 Albee St",
    "sg:city":"Eureka",
    "sg:classifiers":[
        {
            "category":"Building & Trades",
            "subcategory":"Cleaning & Sanitation",
            "type":"Services"
        }
    ],
    "sg:phone":"+1 707 442 6592",
    "sg:postcode":"95503",
    "sg:province":"CA",
    "sg:tags":[
        "janitor"
    ],
    "wof:name":"Steinle's Maintenance",
    "wof:placetype":"venue"
},
  "geometry": {"coordinates":[-124.17582,40.778885],"type":"Point"}
}