{
  "type": "Feature",
  "properties": {
    "addr:full":"225 Harris Ct S San Francisco CA 94080",
    "addr:housenumber":"225",
    "addr:postcode":"94080",
    "addr:street":"Harris Ct S",
    "iso:country":"US",
    "sg:address":"225 Harris Ct",
    "sg:city":"S San Francisco",
    "sg:classifiers":[
        {
            "category":"Manufacturing",
            "subcategory":"Electronics",
            "type":"Manufacturing & Wholesale Goods"
        }
    ],
    "sg:phone":"+1 650 583 8908",
    "sg:postcode":"94080",
    "sg:province":"CA",
    "sg:tags":[
        "equipment",
        "electronic",
        "supply"
    ],
    "wof:name":"Century Technology",
    "wof:placetype":"venue"
},
  "geometry": {"coordinates":[-122.40239200000001,37.650894],"type":"Point"}
}