{
  "type": "Feature",
  "properties": {
    "iso:country":"US",
    "sg:address":"21730 Stevens Creek Blvd Ste 102",
    "sg:city":"Cupertino",
    "sg:classifiers":[
        {
            "category":"Health Services",
            "subcategory":"Chiropractor",
            "type":"Services"
        }
    ],
    "sg:phone":"+1 408 255 2592",
    "sg:postcode":"95014",
    "sg:province":"CA",
    "sg:website":"www.montavistafamilychiro.com",
    "wof:name":"Monta Vista Family Chiropractic",
    "wof:placetype":"venue"
},
  "geometry": {"coordinates":[-122.054692,37.322719],"type":"Point"}
}