{
  "type": "Feature",
  "properties": {
    "addr:full":"6515 S Sepulveda Blvd Los Angeles CA 90045",
    "addr:housenumber":"6515",
    "addr:postcode":"90045",
    "addr:street":"S Sepulveda Blvd",
    "iso:country":"US",
    "sg:address":"6515 S Sepulveda Blvd",
    "sg:city":"Los Angeles",
    "sg:classifiers":[
        {
            "category":"Restaurant",
            "type":"Food & Drink"
        }
    ],
    "sg:phone":"+1 310 338 9153",
    "sg:postcode":"90045",
    "sg:province":"CA",
    "sg:tags":[
        "mexican"
    ],
    "sg:website":"www.vivafreshmexicangrill.com/",
    "wof:name":"Viva Fresh Mexican Grill",
    "wof:placetype":"venue"
},
  "geometry": {"coordinates":[-118.394997,33.980801],"type":"Point"}
}