{
  "type": "Feature",
  "properties": {
    "iso:country":"US",
    "sg:address":"12822 Whittier Blvd",
    "sg:city":"Whittier",
    "sg:classifiers":[
        {
            "category":"Health Services",
            "subcategory":"Clinic",
            "type":"Services"
        }
    ],
    "sg:phone":"+1 562 945 4565",
    "sg:postcode":"90602",
    "sg:province":"CA",
    "sg:tags":[
        "medical",
        "group",
        "doctor"
    ],
    "wof:name":"San Marcos Medical",
    "wof:placetype":"venue"
},
  "geometry": {"coordinates":[-118.039001,33.9664],"type":"Point"}
}