{
  "type": "Feature",
  "properties": {
    "addr:full":"3311 Druid Ln Los Alamitos CA 90720",
    "addr:housenumber":"3311",
    "addr:postcode":"90720",
    "addr:street":"Druid Ln",
    "iso:country":"US",
    "sg:address":"3311 Druid Ln",
    "sg:city":"Los Alamitos",
    "sg:classifiers":[
        {
            "category":"Professional",
            "type":"Services"
        }
    ],
    "sg:phone":"+1 562 493 5557",
    "sg:postcode":"90720",
    "sg:province":"CA",
    "wof:name":"Extrap2b",
    "wof:placetype":"venue"
},
  "geometry": {"coordinates":[-118.075603,33.778864],"type":"Point"}
}