{
  "type": "Feature",
  "properties": {
    "addr:full":"6431 Fairmount Avenue Suite 9 El Cerrito CA 94530",
    "addr:housenumber":"6431",
    "addr:postcode":"94530",
    "addr:street":"Fairmount Avenue Suite 9",
    "iso:country":"US",
    "sg:address":"6431 Fairmount Avenue Suite 9",
    "sg:city":"El Cerrito",
    "sg:classifiers":[
        {
            "category":"Health Services",
            "subcategory":"Dentist",
            "type":"Services"
        }
    ],
    "sg:phone":"+1 510 558 9262",
    "sg:postcode":"94530",
    "sg:province":"CA",
    "sg:website":"www.dukesdental.com/",
    "wof:name":"Dawn M. Dukes DDS & David A. Concepcion DDS",
    "wof:placetype":"venue"
},
  "geometry": {"coordinates":[-122.30100299999999,37.9011],"type":"Point"}
}