{
  "type": "Feature",
  "properties": {
    "iso:country":"US",
    "sg:address":"1222 N Tustin St",
    "sg:city":"Orange",
    "sg:classifiers":[
        {
            "category":"Professional",
            "subcategory":"Employment Agencies",
            "type":"Services"
        }
    ],
    "sg:phone":"+1 714 289 0064",
    "sg:postcode":"92867",
    "sg:province":"CA",
    "wof:name":"Tri State Staffing",
    "wof:placetype":"venue"
},
  "geometry": {"coordinates":[-117.83587900000001,33.807836],"type":"Point"}
}