{
  "type": "Feature",
  "properties": {
    "iso:country":"US",
    "sg:address":"1520 Wanda Ave",
    "sg:city":"Seaside",
    "sg:classifiers":[
        {
            "category":"Education",
            "subcategory":"Special Training",
            "type":"Public Place"
        }
    ],
    "sg:phone":"+1 831 394 2602",
    "sg:postcode":"93955",
    "sg:province":"CA",
    "sg:tags":[
        "school",
        "instruction",
        "art"
    ],
    "wof:name":"Painting Seminar",
    "wof:placetype":"venue"
},
  "geometry": {"coordinates":[-121.832573,36.604017],"type":"Point"}
}