{
  "type": "Feature",
  "properties": {
    "addr:full":"25850 McBean Pkwy Valencia CA 91355",
    "addr:housenumber":"25850",
    "addr:postcode":"91355",
    "addr:street":"Mcbean Pkwy",
    "iso:country":"US",
    "sg:address":"25850 McBean Pkwy",
    "sg:city":"Valencia",
    "sg:classifiers":[
        {
            "category":"Education",
            "subcategory":"Special Training",
            "type":"Public Place"
        }
    ],
    "sg:phone":"+1 661 284 3070",
    "sg:postcode":"91355",
    "sg:province":"CA",
    "sg:tags":[
        "tutoring"
    ],
    "sg:website":"www.escore.com",
    "wof:name":"Score! Educational Ctr",
    "wof:placetype":"venue"
},
  "geometry": {"coordinates":[-118.55521899999999,34.407236],"type":"Point"}
}