{
  "type": "Feature",
  "properties": {
    "iso:country":"US",
    "sg:address":"4142 E Church Ave",
    "sg:city":"Fresno",
    "sg:classifiers":[
        {
            "category":"Retail",
            "subcategory":"Auto Repair",
            "type":"Services"
        }
    ],
    "sg:phone":"+1 559 233 9357",
    "sg:postcode":"93725",
    "sg:province":"CA",
    "sg:tags":[
        "wrecker"
    ],
    "wof:name":"Gilbert's Towing",
    "wof:placetype":"venue"
},
  "geometry": {"coordinates":[-119.755718,36.714077],"type":"Point"}
}