{
  "type": "Feature",
  "properties": {
    "iso:country":"US",
    "sg:address":"680 Taylor Ave",
    "sg:city":"Sunnyvale",
    "sg:classifiers":[
        {
            "category":"Manufacturing",
            "subcategory":"Tools & Machinery",
            "type":"Manufacturing & Wholesale Goods"
        }
    ],
    "sg:phone":"+1 408 720 7100",
    "sg:postcode":"94085",
    "sg:province":"CA",
    "sg:tags":[
        "motion",
        "product",
        "mfg"
    ],
    "wof:name":"Parker Distribution & Svc Ctr",
    "wof:placetype":"venue"
},
  "geometry": {"coordinates":[-122.01717600000001,37.383248],"type":"Point"}
}