{
  "type": "Feature",
  "properties": {
    "iso:country":"US",
    "sg:address":"10621 Sierra Rd",
    "sg:city":"Phelan",
    "sg:classifiers":[
        {
            "category":"Real Estate",
            "subcategory":"Developer",
            "type":"Services"
        }
    ],
    "sg:phone":"+1 760 949 7714",
    "sg:postcode":"92392",
    "sg:province":"CA",
    "sg:tags":[
        "mobile",
        "home"
    ],
    "wof:name":"Pepe's Mobile Home Svc",
    "wof:placetype":"venue"
},
  "geometry": {"coordinates":[-117.430241,34.466789],"type":"Point"}
}