{
  "type": "Feature",
  "properties": {
    "addr:full":"5990 1/2 W Pico Blvd Los Angeles CA 90035",
    "addr:housenumber":"5990 1 / 2",
    "addr:postcode":"90035",
    "addr:street":"W Pico Blvd",
    "iso:country":"US",
    "sg:address":"5990 1/2 W Pico Blvd",
    "sg:city":"Los Angeles",
    "sg:classifiers":[
        {
            "category":"Restaurant",
            "type":"Food & Drink"
        }
    ],
    "sg:phone":"+1 323 939 3233",
    "sg:postcode":"90035",
    "sg:province":"CA",
    "sg:tags":[
        "ethiopian"
    ],
    "wof:name":"Awash Restaurant",
    "wof:placetype":"venue"
},
  "geometry": {"coordinates":[-118.370846,34.052067],"type":"Point"}
}