{
  "type": "Feature",
  "properties": {
    "iso:country":"US",
    "sg:address":"1623 Mission Dr",
    "sg:city":"Solvang",
    "sg:classifiers":[
        {
            "category":"Building & Trades",
            "subcategory":"Construction",
            "type":"Services"
        }
    ],
    "sg:phone":"+1 805 688 7524",
    "sg:postcode":"93463",
    "sg:province":"CA",
    "sg:tags":[
        "general",
        "contractor"
    ],
    "wof:name":"Innovative Design & Constr",
    "wof:placetype":"venue"
},
  "geometry": {"coordinates":[-120.14108899999999,34.596028],"type":"Point"}
}