{
  "type": "Feature",
  "properties": {
    "iso:country":"US",
    "sg:address":"5819 Telegraph Rd",
    "sg:city":"City Of Commerce",
    "sg:classifiers":[
        {
            "category":"Wholesale",
            "subcategory":"Stationery",
            "type":"Manufacturing & Wholesale Goods"
        }
    ],
    "sg:phone":"+1 323 728 8888",
    "sg:postcode":"90040",
    "sg:province":"CA",
    "sg:tags":[
        "box",
        "purchase",
        "fiber",
        "display",
        "point"
    ],
    "wof:name":"Justman Packaging & Display",
    "wof:placetype":"venue"
},
  "geometry": {"coordinates":[-118.150184,34.002211],"type":"Point"}
}