{
  "type": "Feature",
  "properties": {
    "iso:country":"US",
    "sg:address":"610 West Ash Street Suite 1900",
    "sg:city":"San Diego",
    "sg:classifiers":[
        {
            "category":"Professional",
            "subcategory":"Computer Services",
            "type":"Services"
        }
    ],
    "sg:phone":"+421 2/322 441 11",
    "sg:postcode":"92101",
    "sg:province":"CA",
    "sg:tags":[
        "antivirus",
        "security",
        "antispam",
        "heuristics"
    ],
    "sg:website":"http://www.eset.sk/sk",
    "wof:name":"ESET",
    "wof:placetype":"venue"
},
  "geometry": {"coordinates":[-117.169089,32.719951],"type":"Point"}
}