{
  "type": "Feature",
  "properties": {
    "addr:full":"4615 W Century Blvd Inglewood CA 90304",
    "addr:housenumber":"4615",
    "addr:postcode":"90304",
    "addr:street":"W Century Blvd",
    "iso:country":"US",
    "sg:address":"4615 W Century Blvd",
    "sg:city":"Inglewood",
    "sg:classifiers":[
        {
            "category":"Real Estate",
            "subcategory":"Real Estate Agent",
            "type":"Services"
        }
    ],
    "sg:phone":"+1 310 330 3990",
    "sg:postcode":"90304",
    "sg:province":"CA",
    "sg:tags":[
        "management",
        "property"
    ],
    "wof:name":"Seville Properties",
    "wof:placetype":"venue"
},
  "geometry": {"coordinates":[-118.35700199999999,33.945301],"type":"Point"}
}