{
  "type": "Feature",
  "properties": {
    "addr:full":"819W Striker Ave Sacramento CA 95834",
    "addr:housenumber":"819w",
    "addr:postcode":"95834",
    "addr:street":"Striker Ave",
    "iso:country":"US",
    "sg:address":"819W Striker Ave",
    "sg:city":"Sacramento",
    "sg:classifiers":[
        {
            "category":"Shopping",
            "subcategory":"Jewelry",
            "type":"Retail Goods"
        }
    ],
    "sg:phone":"+1 916 922 4608",
    "sg:postcode":"95834",
    "sg:province":"CA",
    "wof:name":"Gtl",
    "wof:placetype":"venue"
},
  "geometry": {"coordinates":[-121.47944699999999,38.651235],"type":"Point"}
}