{
  "type": "Feature",
  "properties": {
    "iso:country":"US",
    "sg:address":"4718 Clairemont Mesa Blvd",
    "sg:city":"San Diego",
    "sg:classifiers":[
        {
            "category":"Restaurant",
            "type":"Food & Drink"
        }
    ],
    "sg:phone":"+1 858 274 2040",
    "sg:postcode":"92117",
    "sg:province":"CA",
    "sg:tags":[
        "chinese"
    ],
    "sg:website":"www.littlesheephotpot.com",
    "wof:name":"Little Sheep Mongolian Hot Pot & Grill / Xiao Fei Yang",
    "wof:placetype":"venue"
},
  "geometry": {"coordinates":[-117.18937099999999,32.83455],"type":"Point"}
}