{
  "type": "Feature",
  "properties": {
    "addr:full":"68303 Ramon Rd Cathedral City CA 92234",
    "addr:housenumber":"68303",
    "addr:postcode":"92234",
    "addr:street":"Ramon Rd",
    "iso:country":"US",
    "sg:address":"68303 Ramon Rd",
    "sg:city":"Cathedral City",
    "sg:classifiers":[
        {
            "category":"Shopping",
            "subcategory":"Hobbies, Toys, & Games",
            "type":"Retail Goods"
        }
    ],
    "sg:phone":"+1 760 202 8225",
    "sg:postcode":"92234",
    "sg:province":"CA",
    "wof:name":"Desert Hobbies",
    "wof:placetype":"venue"
},
  "geometry": {"coordinates":[-116.469585,33.815851],"type":"Point"}
}