{
  "type": "Feature",
  "properties": {
    "iso:country":"US",
    "sg:address":"264 San Jose St",
    "sg:city":"Salinas",
    "sg:classifiers":[
        {
            "category":"Health Services",
            "subcategory":"Doctor",
            "type":"Services"
        }
    ],
    "sg:phone":"+1 831 424 0885",
    "sg:postcode":"93901",
    "sg:province":"CA",
    "sg:tags":[
        "dentist"
    ],
    "wof:name":"Jeffrey R Cohen DDS",
    "wof:placetype":"venue"
},
  "geometry": {"coordinates":[-121.646665,36.658339],"type":"Point"}
}