{
  "type": "Feature",
  "properties": {
    "iso:country":"US",
    "sg:address":"4161 Baldwin Park Blvd",
    "sg:city":"Baldwin Park",
    "sg:classifiers":[
        {
            "category":"Organizations",
            "subcategory":"Religious Organization",
            "type":"Services"
        }
    ],
    "sg:phone":"+1 626 337 3371",
    "sg:postcode":"91706",
    "sg:province":"CA",
    "sg:tags":[
        "church"
    ],
    "wof:name":"First Christian Church",
    "wof:placetype":"venue"
},
  "geometry": {"coordinates":[-117.964896,34.085861],"type":"Point"}
}