{
  "type": "Feature",
  "properties": {
    "iso:country":"US",
    "sg:address":"12258 Platina Rd",
    "sg:city":"Igo",
    "sg:classifiers":[
        {
            "category":"Real Estate",
            "subcategory":"Real Estate Agent",
            "type":"Services"
        }
    ],
    "sg:phone":"+1 530 396 2482",
    "sg:postcode":"96047",
    "sg:province":"CA",
    "wof:name":"Mov-N-Up Real Estate",
    "wof:placetype":"venue"
},
  "geometry": {"coordinates":[-122.59845199999999,40.47651],"type":"Point"}
}