{
  "type": "Feature",
  "properties": {
    "acgov:api":"848.0",
    "acgov:type":"ES",
    "addr:full":"35521 Cabrillo Dr Fremont CA",
    "wof:categories":[
        "education_and_religion:education=school"
    ],
    "wof:name":"Patterson Elementary",
    "wof:placetype":"venue"
},
  "geometry": {"coordinates":[-122.03086522127836,37.56215659999809],"type":"Point"}
}