{
  "type": "Feature",
  "properties": {
    "iso:country":"US",
    "sg:address":"13353 Alondra Blvd",
    "sg:city":"Santa Fe Springs",
    "sg:classifiers":[
        {
            "category":"Freight",
            "type":"Transportation"
        }
    ],
    "sg:phone":"+1 562 802 5858",
    "sg:postcode":"90670",
    "sg:province":"CA",
    "wof:name":"Rapid Freight Inc",
    "wof:placetype":"venue"
},
  "geometry": {"coordinates":[-118.04767,33.88792],"type":"Point"}
}