{
  "type": "Feature",
  "properties": {
    "addr:full":"18042 Ventura Blvd Encino CA 91316",
    "addr:housenumber":"18042",
    "addr:postcode":"91316",
    "addr:street":"Ventura Blvd",
    "iso:country":"US",
    "sg:address":"18042 Ventura Blvd",
    "sg:city":"Encino",
    "sg:classifiers":[
        {
            "category":"Personal",
            "subcategory":"Beauty Salon",
            "type":"Services"
        }
    ],
    "sg:phone":"+1 818 343 0259",
    "sg:postcode":"91316",
    "sg:province":"CA",
    "wof:name":"Simi & Mina Hairstylist",
    "wof:placetype":"venue"
},
  "geometry": {"coordinates":[-118.52627200000001,34.16498],"type":"Point"}
}