{
  "type": "Feature",
  "properties": {
    "addr:full":"265 Dry Creek Rd Aptos CA 95003",
    "addr:housenumber":"265",
    "addr:postcode":"ca 95003",
    "addr:street":"Dry Creek Rd",
    "iso:country":"US",
    "sg:address":"265 Dry Creek Rd",
    "sg:city":"Aptos",
    "sg:classifiers":[
        {
            "category":"Retail",
            "subcategory":"Laundry & Dry Cleaning",
            "type":"Services"
        },
        {
            "category":"Building & Trades",
            "subcategory":"Construction",
            "type":"Services"
        },
        {
            "category":"Building & Trades",
            "subcategory":"Cleaning & Sanitation",
            "type":"Services"
        }
    ],
    "sg:phone":"+1 831 688 7847",
    "sg:postcode":"95003",
    "sg:province":"CA",
    "sg:tags":[
        "cleaner",
        "fire",
        "rug",
        "damage",
        "water",
        "restoration",
        "tile-contractors",
        "carpet"
    ],
    "sg:website":"http://www.thedoctorclean.com",
    "wof:name":"Doctor Clean",
    "wof:placetype":"venue"
},
  "geometry": {"coordinates":[-121.88800000000001,36.962002],"type":"Point"}
}