{
  "type": "Feature",
  "properties": {
    "addr:full":"2261 Shafter Ave San Francisco CA 94124",
    "addr:housenumber":"2261",
    "addr:postcode":"94124",
    "addr:street":"Shafter Ave",
    "iso:country":"US",
    "sg:address":"2261 Shafter Ave",
    "sg:city":"San Francisco",
    "sg:classifiers":[
        {
            "category":"Personal",
            "type":"Services"
        }
    ],
    "sg:phone":"+1 415 550 9328",
    "sg:postcode":"94124",
    "sg:province":"CA",
    "sg:tags":[
        "local"
    ],
    "sg:website":"www.mackmetal.com",
    "wof:name":"Jefferson Mack Metals",
    "wof:placetype":"venue"
},
  "geometry": {"coordinates":[-122.404304,37.738735],"type":"Point"}
}