{
  "type": "Feature",
  "properties": {
    "iso:country":"US",
    "sg:address":"2000 W Toledo Pl",
    "sg:city":"La Habra",
    "sg:classifiers":[
        {
            "category":"Professional",
            "type":"Services"
        }
    ],
    "sg:phone":"+1 562 690 3977",
    "sg:postcode":"90631",
    "sg:province":"CA",
    "wof:name":"Childamerica",
    "wof:placetype":"venue"
},
  "geometry": {"coordinates":[-117.97086,33.928675],"type":"Point"}
}