{
  "type": "Feature",
  "properties": {
    "iso:country":"US",
    "sg:address":"7825 Fay Ave Ste 320",
    "sg:city":"La Jolla",
    "sg:classifiers":[
        {
            "category":"Professional",
            "subcategory":"Lawyer & Legal Services",
            "type":"Services"
        }
    ],
    "sg:phone":"+1 858 454 9927",
    "sg:postcode":"92037",
    "sg:province":"CA",
    "wof:name":"Tschirin Darryl Atty",
    "wof:placetype":"venue"
},
  "geometry": {"coordinates":[-117.275002,32.8452],"type":"Point"}
}