{
  "type": "Feature",
  "properties": {
    "iso:country":"US",
    "sg:address":"3021 Q St",
    "sg:city":"North Highlands",
    "sg:classifiers":[
        {
            "category":"Building & Trades",
            "subcategory":"Construction",
            "type":"Services"
        }
    ],
    "sg:phone":"+1 916 334 1450",
    "sg:postcode":"95660",
    "sg:province":"CA",
    "sg:tags":[
        "contractor"
    ],
    "wof:name":"Ralph Maeda Construction",
    "wof:placetype":"venue"
},
  "geometry": {"coordinates":[-121.392458,38.697728],"type":"Point"}
}