{
  "type": "Feature",
  "properties": {
    "addr:full":"366 San Miguel Drive Newport Beach CA 92660",
    "addr:housenumber":"366",
    "addr:postcode":"92660",
    "addr:street":"San Miguel Drive",
    "iso:country":"US",
    "sg:address":"366 San Miguel Drive",
    "sg:city":"Newport Beach",
    "sg:classifiers":[
        {
            "category":"Sports & Exercise",
            "subcategory":"Gym",
            "type":"Entertainment"
        }
    ],
    "sg:phone":"+1 949 719 2683",
    "sg:postcode":"92660",
    "sg:province":"CA",
    "sg:tags":[
        "trainer"
    ],
    "wof:name":"Endermologie by Jannae",
    "wof:placetype":"venue"
},
  "geometry": {"coordinates":[-117.871622,33.612445],"type":"Point"}
}