{
  "type": "Feature",
  "properties": {
    "addr:full":"7936 W 3rd St Los Angeles CA 90048",
    "addr:housenumber":"7936",
    "addr:postcode":"90048",
    "addr:street":"W 3Rd St",
    "iso:country":"US",
    "sg:address":"7936 W 3rd St",
    "sg:city":"Los Angeles",
    "sg:classifiers":[
        {
            "category":"Shopping",
            "subcategory":"Florist",
            "type":"Retail Goods"
        }
    ],
    "sg:phone":"+1 323 655 7171",
    "sg:postcode":"90048",
    "sg:province":"CA",
    "wof:name":"Beverly Blossoms",
    "wof:placetype":"venue"
},
  "geometry": {"coordinates":[-118.363085,34.071718],"type":"Point"}
}