{
  "type": "Feature",
  "properties": {
    "addr:full":"1410 Rocky Ridge Dr Roseville CA 95661",
    "addr:housenumber":"1410",
    "addr:postcode":"95661",
    "addr:street":"Rocky Ridge Dr",
    "iso:country":"US",
    "sg:address":"1410 Rocky Ridge Dr",
    "sg:city":"Roseville",
    "sg:classifiers":[
        {
            "category":"Professional",
            "subcategory":"Lawyer & Legal Services",
            "type":"Services"
        }
    ],
    "sg:phone":"+1 916 773 7838",
    "sg:postcode":"95661",
    "sg:province":"CA",
    "sg:tags":[
        "divorce",
        "attorney",
        "law",
        "family"
    ],
    "wof:name":"C Kristine White Attorney",
    "wof:placetype":"venue"
},
  "geometry": {"coordinates":[-121.243207,38.75301],"type":"Point"}
}