{
  "type": "Feature",
  "properties": {
    "addr:full":"23651 Miranda St Woodland Hills CA 91367",
    "addr:housenumber":"23651",
    "addr:postcode":"91367",
    "addr:street":"Miranda St",
    "iso:country":"US",
    "sg:address":"23651 Miranda St",
    "sg:city":"Woodland Hills",
    "sg:classifiers":[
        {
            "category":"Professional",
            "subcategory":"Lawyer & Legal Services",
            "type":"Services"
        }
    ],
    "sg:phone":"+1 818 999 9999",
    "sg:postcode":"91367",
    "sg:province":"CA",
    "sg:tags":[
        "attorney"
    ],
    "wof:name":"Matt Koohanim Law Offices",
    "wof:placetype":"venue"
},
  "geometry": {"coordinates":[-118.64228300000001,34.174747],"type":"Point"}
}