{
  "type": "Feature",
  "properties": {
    "iso:country":"US",
    "sg:address":"23651 Miranda St",
    "sg:city":"Woodland Hills",
    "sg:classifiers":[
        {
            "category":"Professional",
            "subcategory":"Lawyer & Legal Services",
            "type":"Services"
        }
    ],
    "sg:phone":"+1 818 999 9999",
    "sg:postcode":"91367",
    "sg:province":"CA",
    "sg:tags":[
        "attorney"
    ],
    "wof:name":"Matt Koohanim Law Offices",
    "wof:placetype":"venue"
},
  "geometry": {"coordinates":[-118.642283,34.174747],"type":"Point"}
}