{
  "type": "Feature",
  "properties": {
    "addr:full":"1780 Old Bayshore Hwy San Jose CA 95112",
    "addr:housenumber":"1780",
    "addr:postcode":"95112",
    "addr:street":"Old Bayshore Hwy",
    "iso:country":"US",
    "sg:address":"1780 Old Bayshore Hwy",
    "sg:city":"San Jose",
    "sg:classifiers":[
        {
            "category":"Building & Trades",
            "subcategory":"Plumbing",
            "type":"Services"
        }
    ],
    "sg:phone":"+1 408 436 0705",
    "sg:postcode":"95112",
    "sg:province":"CA",
    "sg:tags":[
        "system",
        "radiant",
        "cooling",
        "heating"
    ],
    "wof:name":"Accura Mechanical",
    "wof:placetype":"venue"
},
  "geometry": {"coordinates":[-121.909446,37.369664],"type":"Point"}
}