{
  "type": "Feature",
  "properties": {
    "addr:full":"464 Fogg St Colton CA 92324",
    "addr:housenumber":"464",
    "addr:postcode":"92324",
    "addr:street":"Fogg St",
    "iso:country":"US",
    "sg:address":"464 Fogg St",
    "sg:city":"Colton",
    "sg:classifiers":[
        {
            "category":"Retail",
            "subcategory":"Auto Repair",
            "type":"Services"
        }
    ],
    "sg:phone":"+1 909 370 0328",
    "sg:postcode":"92324",
    "sg:province":"CA",
    "sg:tags":[
        "repairing",
        "automobile"
    ],
    "wof:name":"J & S Auto Electric & Repair",
    "wof:placetype":"venue"
},
  "geometry": {"coordinates":[-117.33099300000001,34.052661],"type":"Point"}
}