{
  "type": "Feature",
  "properties": {
    "iso:country":"US",
    "sg:address":"15 Pamaron Way Ste L",
    "sg:city":"Novato",
    "sg:classifiers":[
        {
            "category":"Wholesale",
            "subcategory":"Medical Equipment & Supplies",
            "type":"Manufacturing & Wholesale Goods"
        }
    ],
    "sg:phone":"+1 415 883 7891",
    "sg:postcode":"94949",
    "sg:province":"CA",
    "sg:tags":[
        "device",
        "surgical",
        "orthopedic",
        "appliance",
        "prosthetic"
    ],
    "wof:name":"Hanger Prosthetics & Orthotics",
    "wof:placetype":"venue"
},
  "geometry": {"coordinates":[-122.531301,38.068115],"type":"Point"}
}