{
  "type": "Feature",
  "properties": {
    "iso:country":"US",
    "sg:address":"8651 Foothill Blvd",
    "sg:city":"Rancho Cucamonga",
    "sg:classifiers":[
        {
            "category":"Wholesale",
            "subcategory":"Groceries",
            "type":"Manufacturing & Wholesale Goods"
        }
    ],
    "sg:phone":"+1 909 981 6900",
    "sg:postcode":"91730",
    "sg:province":"CA",
    "sg:tags":[
        "general"
    ],
    "wof:name":"Freshway Enterprises",
    "wof:placetype":"venue"
},
  "geometry": {"coordinates":[-117.61407800000001,34.106573],"type":"Point"}
}