{
  "type": "Feature",
  "properties": {
    "addr:full":"1000 Sansome St Ste 300 San Francisco CA 94111",
    "addr:housenumber":"1000",
    "addr:postcode":"94111",
    "addr:street":"Sansome St Ste 300",
    "iso:country":"US",
    "sg:address":"1000 Sansome St Ste 300",
    "sg:city":"San Francisco",
    "sg:classifiers":[
        {
            "category":"Communications",
            "type":"Services"
        }
    ],
    "sg:phone":"+1 415 490 4200",
    "sg:postcode":"94111",
    "sg:province":"CA",
    "sg:tags":[
        "medium",
        "mass"
    ],
    "sg:website":"www.rmgnetworks.com",
    "wof:name":"RMG Networks",
    "wof:placetype":"venue"
},
  "geometry": {"coordinates":[-122.402118,37.799684],"type":"Point"}
}