{
  "type": "Feature",
  "properties": {
    "iso:country":"US",
    "sg:address":"35649 Barbara Ln",
    "sg:city":"Yucaipa",
    "sg:classifiers":[
        {
            "category":"Building & Trades",
            "subcategory":"Construction",
            "type":"Services"
        }
    ],
    "sg:phone":"+1 909 790 9996",
    "sg:postcode":"92399",
    "sg:province":"CA",
    "sg:tags":[
        "contractor"
    ],
    "wof:name":"Prestige Pools",
    "wof:placetype":"venue"
},
  "geometry": {"coordinates":[-117.027094,34.01489],"type":"Point"}
}