{
  "type": "Feature",
  "properties": {
    "iso:country":"US",
    "sg:address":"1879 26th Ave",
    "sg:city":"San Francisco",
    "sg:classifiers":[
        {
            "category":"Professional",
            "subcategory":"Engineering",
            "type":"Services"
        }
    ],
    "sg:phone":"+1 415 731 4959",
    "sg:postcode":"94122",
    "sg:province":"CA",
    "sg:tags":[
        "equipment",
        "electrical"
    ],
    "sg:website":"www.sertek.com",
    "wof:name":"Sertek",
    "wof:placetype":"venue"
},
  "geometry": {"coordinates":[-122.484001,37.753525],"type":"Point"}
}