{
  "type": "Feature",
  "properties": {
    "addr:full":"207 Boulderidge Ct Vacaville CA 95688",
    "addr:housenumber":"207",
    "addr:postcode":"95688",
    "addr:street":"Boulderidge Ct",
    "iso:country":"US",
    "sg:address":"207 Boulderidge Ct",
    "sg:city":"Vacaville",
    "sg:classifiers":[
        {
            "category":"Building & Trades",
            "subcategory":"Landscaping Services",
            "type":"Services"
        }
    ],
    "sg:phone":"+1 707 446 1195",
    "sg:postcode":"95688",
    "sg:province":"CA",
    "wof:name":"Lawn Works",
    "wof:placetype":"venue"
},
  "geometry": {"coordinates":[-121.97968899999999,38.388867],"type":"Point"}
}