{
  "type": "Feature",
  "properties": {
    "iso:country":"US",
    "sg:address":"9915 Santa Monica Blvd",
    "sg:city":"Beverly Hills",
    "sg:classifiers":[
        {
            "category":"Social Services",
            "type":"Services"
        }
    ],
    "sg:phone":"+1 310 273 0500",
    "sg:postcode":"90212",
    "sg:province":"CA",
    "sg:tags":[
        "counselor",
        "marriage",
        "family"
    ],
    "wof:name":"Terri Asanovich Marriage",
    "wof:placetype":"venue"
},
  "geometry": {"coordinates":[-118.41269,34.065548],"type":"Point"}
}