{
  "type": "Feature",
  "properties": {
    "addr:full":"511 3rd St Rodeo CA 94572",
    "addr:housenumber":"511",
    "addr:postcode":"94572",
    "addr:street":"3Rd St",
    "iso:country":"US",
    "sg:address":"511 3rd St",
    "sg:city":"Rodeo",
    "sg:classifiers":[
        {
            "category":"Autos & Motor Vehicles",
            "subcategory":"Motorcycle Sales",
            "type":"Retail Goods"
        }
    ],
    "sg:phone":"+1 510 799 1930",
    "sg:postcode":"94572",
    "sg:province":"CA",
    "wof:name":"Third Street Motorcycles",
    "wof:placetype":"venue"
},
  "geometry": {"coordinates":[-122.267511,38.034522],"type":"Point"}
}