{
  "type": "Feature",
  "properties": {
    "addr:full":"3288 Pierce St Ste C129 Richmond CA 94804",
    "addr:housenumber":"3288",
    "addr:postcode":"94804",
    "addr:street":"Pierce St Ste C129",
    "iso:country":"US",
    "sg:address":"3288 Pierce St Ste C129",
    "sg:city":"Richmond",
    "sg:classifiers":[
        {
            "category":"Personal",
            "subcategory":"Skin Care",
            "type":"Services"
        }
    ],
    "sg:phone":"+1 510 526 8287",
    "sg:postcode":"94804",
    "sg:province":"CA",
    "wof:name":"Magic Skin Care",
    "wof:placetype":"venue"
},
  "geometry": {"coordinates":[-122.308998,37.897999],"type":"Point"}
}