{
  "type": "Feature",
  "properties": {
    "addr:full":"5119 N Valley Center Ave Covina CA 91724",
    "addr:housenumber":"5119",
    "addr:postcode":"91724",
    "addr:street":"N Valley Center Ave",
    "iso:country":"US",
    "sg:address":"5119 N Valley Center Ave",
    "sg:city":"Covina",
    "sg:classifiers":[
        {
            "category":"Place Of Worship",
            "subcategory":"Church",
            "type":"Public Place"
        },
        {
            "category":"Place Of Worship",
            "type":"Public Place"
        }
    ],
    "sg:phone":"+1 626 963 3749",
    "sg:postcode":"91724",
    "sg:province":"CA",
    "sg:tags":[
        "covenant",
        "churches-evangelical",
        "churches-covenant"
    ],
    "wof:name":"Arabic Evangelical Church",
    "wof:placetype":"venue"
},
  "geometry": {"coordinates":[-117.837665,34.106423],"type":"Point"}
}