{
  "type": "Feature",
  "properties": {
    "iso:country":"US",
    "sg:address":"5890 San Jacinto Rd",
    "sg:city":"Atascadero",
    "sg:classifiers":[
        {
            "category":"Organizations",
            "subcategory":"Religious Organization",
            "type":"Services"
        }
    ],
    "sg:phone":"+1 805 466 1752",
    "sg:postcode":"93422",
    "sg:province":"CA",
    "sg:tags":[
        "church"
    ],
    "wof:name":"Church Of Christ",
    "wof:placetype":"venue"
},
  "geometry": {"coordinates":[-120.679022,35.495785],"type":"Point"}
}