{
  "type": "Feature",
  "properties": {
    "iso:country":"US",
    "sg:address":"2400-2498 W 149th St",
    "sg:city":"Gardena",
    "sg:classifiers":[
        {
            "category":"Park",
            "type":"Public Place"
        }
    ],
    "sg:phone":"+1 310 217 9560",
    "sg:postcode":"90249",
    "sg:province":"CA",
    "wof:name":"Thornburg Park",
    "wof:placetype":"venue"
},
  "geometry": {"coordinates":[-118.32046,33.896625],"type":"Point"}
}