{
  "type": "Feature",
  "properties": {
    "iso:country":"US",
    "sg:address":"1743 Tehama St",
    "sg:city":"Redding",
    "sg:classifiers":[
        {
            "category":"Professional",
            "subcategory":"Lawyer & Legal Services",
            "type":"Services"
        }
    ],
    "sg:phone":"+1 530 245 0102",
    "sg:postcode":"96001",
    "sg:province":"CA",
    "sg:tags":[
        "attorney",
        "practice"
    ],
    "wof:name":"Bennett Roland L Attorney At Law",
    "wof:placetype":"venue"
},
  "geometry": {"coordinates":[-122.395408,40.584328],"type":"Point"}
}