{
  "type": "Feature",
  "properties": {
    "iso:country":"US",
    "sg:address":"21625 Valley Blvd",
    "sg:city":"Walnut",
    "sg:classifiers":[
        {
            "category":"Restaurant",
            "type":"Food & Drink"
        }
    ],
    "sg:menulink":"http://www.allmenus.com/ca/east-san-gabriel-valley/89881-applebees/menu/",
    "sg:phone":"+1 909 594 1140",
    "sg:postcode":"91789",
    "sg:province":"CA",
    "sg:tags":[
        "burger",
        "american",
        "sandwich",
        "soup"
    ],
    "wof:name":"Applebee's",
    "wof:placetype":"venue"
},
  "geometry": {"coordinates":[-117.83553000000001,34.027977],"type":"Point"}
}