{
  "type": "Feature",
  "properties": {
    "addr:full":"400 E 7th St Los Angeles CA 90014",
    "addr:housenumber":"400",
    "addr:postcode":"90014",
    "addr:street":"E 7Th St",
    "iso:country":"US",
    "sg:address":"400 E 7th St",
    "sg:city":"Los Angeles",
    "sg:classifiers":[
        {
            "category":"Restaurant",
            "type":"Food & Drink"
        }
    ],
    "sg:phone":"+1 213 891 1069",
    "sg:postcode":"90014",
    "sg:province":"CA",
    "wof:name":"Lalos No 2",
    "wof:placetype":"venue"
},
  "geometry": {"coordinates":[-118.24856200000001,34.04179],"type":"Point"}
}