{
  "type": "Feature",
  "properties": {
    "iso:country":"US",
    "sg:address":"14340 Bolsa Chica Rd",
    "sg:city":"Westminster",
    "sg:classifiers":[
        {
            "category":"Real Estate",
            "subcategory":"Real Estate Operator",
            "type":"Services"
        }
    ],
    "sg:phone":"+1 714 379 4888",
    "sg:postcode":"92683",
    "sg:province":"CA",
    "sg:tags":[
        "building",
        "commercial"
    ],
    "wof:name":"Birchbrook Office Park LLC",
    "wof:placetype":"venue"
},
  "geometry": {"coordinates":[-118.04263,33.7525],"type":"Point"}
}