{
  "type": "Feature",
  "properties": {
    "addr:full":"1251 Sepulveda Blvd Torrance CA 90502",
    "addr:housenumber":"1251",
    "addr:postcode":"90502",
    "addr:street":"Sepulveda Blvd",
    "iso:country":"US",
    "sg:address":"1251 Sepulveda Blvd",
    "sg:city":"Torrance",
    "sg:classifiers":[
        {
            "category":"Building & Trades",
            "subcategory":"Construction",
            "type":"Services"
        }
    ],
    "sg:phone":"+1 310 834 1853",
    "sg:postcode":"90502",
    "sg:province":"CA",
    "sg:tags":[
        "handyman"
    ],
    "wof:name":"Neal Palmer Handyman Svc",
    "wof:placetype":"venue"
},
  "geometry": {"coordinates":[-118.2979,33.81295],"type":"Point"}
}