{
  "type": "Feature",
  "properties": {
    "iso:country":"US",
    "sg:address":"801 Sierra Vista Way # 37",
    "sg:city":"Yreka",
    "sg:classifiers":[
        {
            "category":"Building & Trades",
            "subcategory":"Landscaping Services",
            "type":"Services"
        }
    ],
    "sg:phone":"+1 530 905 1368",
    "sg:postcode":"96097",
    "sg:province":"CA",
    "sg:tags":[
        "gardener"
    ],
    "wof:name":"Raymond E Marsh",
    "wof:placetype":"venue"
},
  "geometry": {"coordinates":[-122.62412999999999,41.732498],"type":"Point"}
}