{
  "type": "Feature",
  "properties": {
    "iso:country":"US",
    "sg:address":"130 E Oris St",
    "sg:city":"Compton",
    "sg:classifiers":[
        {
            "category":"Wholesale",
            "subcategory":"Construction Materials",
            "type":"Manufacturing & Wholesale Goods"
        }
    ],
    "sg:phone":"+1 310 886 1000",
    "sg:postcode":"90222",
    "sg:province":"CA",
    "sg:tags":[
        "concrete",
        "form"
    ],
    "wof:name":"Concrete Tie",
    "wof:placetype":"venue"
},
  "geometry": {"coordinates":[-118.22664,33.90848],"type":"Point"}
}