{
  "type": "Feature",
  "properties": {
    "addr:full":"20981 Magnolia St Huntington Beach CA 92646",
    "addr:housenumber":"20981",
    "addr:postcode":"92646",
    "addr:street":"Magnolia St",
    "iso:country":"US",
    "sg:address":"20981 Magnolia St",
    "sg:city":"Huntington Beach",
    "sg:classifiers":[
        {
            "category":"Banks & Credit Unions",
            "subcategory":"Bank",
            "type":"Services"
        }
    ],
    "sg:phone":"+1 714 536 8819",
    "sg:postcode":"92646",
    "sg:province":"CA",
    "sg:website":"www.citi.com",
    "wof:name":"Citibank",
    "wof:placetype":"venue"
},
  "geometry": {"coordinates":[-117.971917,33.658673],"type":"Point"}
}