{
  "type": "Feature",
  "properties": {
    "addr:full":"36 Hegenberger Ct Oakland CA 94621",
    "addr:housenumber":"36",
    "addr:postcode":"94621",
    "addr:street":"Hegenberger Ct",
    "iso:country":"US",
    "sg:address":"36 Hegenberger Ct",
    "sg:city":"Oakland",
    "sg:phone":"+1 510 633 9533",
    "sg:postcode":"94621",
    "sg:province":"CA",
    "wof:name":"Carpet Wrhhse Dicks Wholesale",
    "wof:placetype":"venue"
},
  "geometry": {"coordinates":[-122.194232,37.736379],"type":"Point"}
}