{
  "type": "Feature",
  "properties": {
    "addr:full":"141 E Saint Joseph St Arcadia CA 91006",
    "addr:housenumber":"141",
    "addr:postcode":"91006",
    "addr:street":"E Saint Joseph St",
    "iso:country":"US",
    "sg:address":"141 E Saint Joseph St",
    "sg:city":"Arcadia",
    "sg:classifiers":[
        {
            "category":"Shopping",
            "subcategory":"Musical Instruments",
            "type":"Retail Goods"
        }
    ],
    "sg:phone":"+1 626 446 0808",
    "sg:postcode":"91006",
    "sg:province":"CA",
    "sg:tags":[
        "durable"
    ],
    "wof:name":"Amac Violin Center",
    "wof:placetype":"venue"
},
  "geometry": {"coordinates":[-118.026353,34.143483],"type":"Point"}
}