{
  "type": "Feature",
  "properties": {
    "addr:full":"340 Brannan Street, Suite 100 San Francsico CA 94107",
    "addr:housenumber":"340",
    "addr:postcode":"94107",
    "addr:street":"Brannan Street Suite 100 San Francsico",
    "iso:country":"US",
    "sg:address":"340 Brannan Street, Suite 100",
    "sg:city":"San Francsico",
    "sg:classifiers":[
        {
            "category":"Professional",
            "subcategory":"Computer Services",
            "type":"Services"
        }
    ],
    "sg:postcode":"94107",
    "sg:province":"CA",
    "sg:tags":[
        "crunchyroll",
        "anime",
        "manga",
        "video",
        "gaming",
        "music",
        "kdrama",
        "jdrama",
        "subscription"
    ],
    "sg:website":"http://www.crunchyroll.com/",
    "wof:name":"Crunchyroll",
    "wof:placetype":"venue"
},
  "geometry": {"coordinates":[-122.392938,37.781325],"type":"Point"}
}