{
  "type": "Feature",
  "properties": {
    "iso:country":"US",
    "sg:address":"1122 E Lincoln Ave",
    "sg:city":"Orange",
    "sg:classifiers":[
        {
            "category":"Shopping",
            "subcategory":"Jewelry",
            "type":"Retail Goods"
        }
    ],
    "sg:phone":"+1 714 974 7655",
    "sg:postcode":"92865",
    "sg:province":"CA",
    "wof:name":"Kramar Jewelers",
    "wof:placetype":"venue"
},
  "geometry": {"coordinates":[-117.84200300000001,33.8363],"type":"Point"}
}