{
  "type": "Feature",
  "properties": {
    "iso:country":"US",
    "sg:address":"1313 N Milpitas Blvd",
    "sg:city":"Milpitas",
    "sg:classifiers":[
        {
            "category":"Insurance",
            "subcategory":"Insurance Agent",
            "type":"Services"
        }
    ],
    "sg:phone":"+1 408 586 9924",
    "sg:postcode":"95035",
    "sg:province":"CA",
    "wof:name":"IOF Foresters",
    "wof:placetype":"venue"
},
  "geometry": {"coordinates":[-121.908906,37.446166],"type":"Point"}
}