{
  "type": "Feature",
  "properties": {
    "iso:country":"US",
    "sg:address":"12354 Dogwood Rd",
    "sg:city":"Grass Valley",
    "sg:classifiers":[
        {
            "category":"Building & Trades",
            "subcategory":"Construction",
            "type":"Services"
        }
    ],
    "sg:phone":"+1 530 273 6800",
    "sg:postcode":"95945",
    "sg:province":"CA",
    "sg:tags":[
        "house"
    ],
    "wof:name":"Platner Construction & Dev",
    "wof:placetype":"venue"
},
  "geometry": {"coordinates":[-120.988427,39.21314],"type":"Point"}
}