{
  "type": "Feature",
  "properties": {
    "iso:country":"US",
    "sg:address":"1176 Fairview Ave",
    "sg:city":"Redwood City",
    "sg:classifiers":[
        {
            "category":"Shopping",
            "type":"Retail Goods"
        }
    ],
    "sg:phone":"+1 650 364 3474",
    "sg:postcode":"94061",
    "sg:province":"CA",
    "sg:tags":[
        "pet",
        "food",
        "supply"
    ],
    "wof:name":"Down Under Tropical Fish",
    "wof:placetype":"venue"
},
  "geometry": {"coordinates":[-122.23969,37.465455],"type":"Point"}
}