{
  "type": "Feature",
  "properties": {
    "addr:full":"2010 W Burbank Blvd Burbank CA 91506",
    "addr:housenumber":"2010",
    "addr:postcode":"91506",
    "addr:street":"W Burbank Blvd",
    "iso:country":"US",
    "sg:address":"2010 W Burbank Blvd",
    "sg:city":"Burbank",
    "sg:classifiers":[
        {
            "category":"Autos & Motor Vehicles",
            "subcategory":"Motorcycle Sales",
            "type":"Retail Goods"
        }
    ],
    "sg:phone":"+1 818 842 8200",
    "sg:postcode":"91506",
    "sg:province":"CA",
    "sg:tags":[
        "scooter"
    ],
    "sg:website":"www.gizmoshobby.com",
    "wof:name":"Gizmo's Hobby",
    "wof:placetype":"venue"
},
  "geometry": {"coordinates":[-118.33352600000001,34.180195],"type":"Point"}
}