{
  "type": "Feature",
  "properties": {
    "addr:full":"5630 Odea Dr Sacramento CA 95824",
    "addr:housenumber":"5630",
    "addr:postcode":"95824",
    "addr:street":"Odea Dr",
    "iso:country":"US",
    "sg:address":"5630 Odea Dr",
    "sg:city":"Sacramento",
    "sg:classifiers":[
        {
            "category":"Personal",
            "subcategory":"Beauty Salon",
            "type":"Services"
        }
    ],
    "sg:phone":"+1 916 428 2569",
    "sg:postcode":"95824",
    "sg:province":"CA",
    "wof:name":"Tanya's Hairstyle",
    "wof:placetype":"venue"
},
  "geometry": {"coordinates":[-121.456917,38.523047],"type":"Point"}
}