{
  "type": "Feature",
  "properties": {
    "iso:country":"US",
    "sg:address":"199 E Central Ave",
    "sg:city":"San Bernardino",
    "sg:classifiers":[
        {
            "category":"Wholesale",
            "subcategory":"Plants",
            "type":"Manufacturing & Wholesale Goods"
        }
    ],
    "sg:phone":"+1 909 890 2393",
    "sg:postcode":"92408",
    "sg:province":"CA",
    "sg:tags":[
        "supply"
    ],
    "wof:name":"Floral Supply Syndicate",
    "wof:placetype":"venue"
},
  "geometry": {"coordinates":[-117.280996,34.086048],"type":"Point"}
}