{
  "type": "Feature",
  "properties": {
    "addr:full":"634 Grand Ave Oakland CA 94610",
    "addr:housenumber":"634",
    "addr:postcode":"94610",
    "addr:street":"Grand Ave",
    "iso:country":"US",
    "sg:address":"634 Grand Ave",
    "sg:city":"Oakland",
    "sg:classifiers":[
        {
            "category":"Real Estate",
            "subcategory":"Real Estate Services",
            "type":"Services"
        },
        {
            "category":"Real Estate",
            "subcategory":"Real Estate Agent",
            "type":"Services"
        }
    ],
    "sg:phone":"+1 510 339 4411",
    "sg:postcode":"94610",
    "sg:province":"CA",
    "sg:tags":[
        "buyer",
        "management",
        "broker"
    ],
    "wof:name":"Bravura Worldwide Properties",
    "wof:placetype":"venue"
},
  "geometry": {"coordinates":[-122.249354,37.809595],"type":"Point"}
}