{
  "type": "Feature",
  "properties": {
    "addr:full":"115 Valencia Street San Francisco CA 94103",
    "addr:housenumber":"115",
    "addr:postcode":"94103",
    "addr:street":"Valencia Street",
    "iso:country":"US",
    "sg:address":"115 Valencia Street",
    "sg:city":"San Francisco",
    "sg:classifiers":[
        {
            "category":"Real Estate",
            "subcategory":"Architect",
            "type":"Services"
        }
    ],
    "sg:phone":"+1 415 431 8601",
    "sg:postcode":"94103",
    "sg:province":"CA",
    "sg:website":"www.moraarchitects.com",
    "wof:name":"Mora Architects Aia",
    "wof:placetype":"venue"
},
  "geometry": {"coordinates":[-122.421997,37.771198],"type":"Point"}
}