{
  "type": "Feature",
  "properties": {
    "addr:full":"11270 Goss St Sun Valley CA 91352",
    "addr:housenumber":"11270",
    "addr:postcode":"91352",
    "addr:street":"Goss St",
    "iso:country":"US",
    "sg:address":"11270 Goss St",
    "sg:city":"Sun Valley",
    "sg:classifiers":[
        {
            "category":"Manufacturing",
            "subcategory":"Tools & Machinery",
            "type":"Manufacturing & Wholesale Goods"
        }
    ],
    "sg:phone":"+1 818 767 6363",
    "sg:postcode":"91352",
    "sg:province":"CA",
    "sg:tags":[
        "motion",
        "picture",
        "supply"
    ],
    "wof:name":"Bogen Cine",
    "wof:placetype":"venue"
},
  "geometry": {"coordinates":[-118.37799800000001,34.222476],"type":"Point"}
}