{
  "type": "Feature",
  "properties": {
    "iso:country":"US",
    "sg:address":"280 San Pedro Rd",
    "sg:city":"Daly City",
    "sg:classifiers":[
        {
            "category":"Retail",
            "subcategory":"Auto Repair",
            "type":"Services"
        }
    ],
    "sg:phone":"+1 650 755 0983",
    "sg:postcode":"94014",
    "sg:province":"CA",
    "sg:tags":[
        "repairing",
        "automobile"
    ],
    "wof:name":"J & K Auto Repair",
    "wof:placetype":"venue"
},
  "geometry": {"coordinates":[-122.469077,37.687118],"type":"Point"}
}