{
  "type": "Feature",
  "properties": {
    "iso:country":"US",
    "sg:address":"4672 W Jennifer Ave",
    "sg:city":"Fresno",
    "sg:classifiers":[
        {
            "category":"Health Services",
            "subcategory":"Medical Lab",
            "type":"Services"
        }
    ],
    "sg:phone":"+1 559 275 9600",
    "sg:postcode":"93722",
    "sg:province":"CA",
    "sg:tags":[
        "laboratory"
    ],
    "wof:name":"Majestic Orthodontic Lab",
    "wof:placetype":"venue"
},
  "geometry": {"coordinates":[-119.878761,36.811692],"type":"Point"}
}