{
  "type": "Feature",
  "properties": {
    "addr:full":"125 E 18th St Merced CA 95340",
    "addr:housenumber":"125",
    "addr:postcode":"95340",
    "addr:street":"E 18Th St",
    "iso:country":"US",
    "sg:address":"125 E 18th St",
    "sg:city":"Merced",
    "sg:classifiers":[
        {
            "category":"Social Services",
            "subcategory":"Child Care",
            "type":"Services"
        }
    ],
    "sg:phone":"+1 209 385 6453",
    "sg:postcode":"95340",
    "sg:province":"CA",
    "sg:tags":[
        "kindergarten",
        "academic",
        "school"
    ],
    "wof:name":"Merced Parent Nursery School",
    "wof:placetype":"venue"
},
  "geometry": {"coordinates":[-120.47319299999999,37.298954],"type":"Point"}
}