{
  "type": "Feature",
  "properties": {
    "addr:full":"1960 Chicago Ave Riverside CA 92507",
    "addr:housenumber":"1960",
    "addr:postcode":"92507",
    "addr:street":"Chicago Ave",
    "iso:country":"US",
    "sg:address":"1960 Chicago Ave",
    "sg:city":"Riverside",
    "sg:classifiers":[
        {
            "category":"Restaurant",
            "type":"Food & Drink"
        }
    ],
    "sg:phone":"+1 951 684 6861",
    "sg:postcode":"92507",
    "sg:province":"CA",
    "wof:name":"M & M Deli",
    "wof:placetype":"venue"
},
  "geometry": {"coordinates":[-117.34835200000001,33.994068],"type":"Point"}
}