{
  "type": "Feature",
  "properties": {
    "iso:country":"US",
    "sg:address":"4 Park Plz",
    "sg:city":"Irvine",
    "sg:classifiers":[
        {
            "category":"Sports & Exercise",
            "subcategory":"Gym",
            "type":"Entertainment"
        }
    ],
    "sg:phone":"+1 949 253 3111",
    "sg:postcode":"92614",
    "sg:province":"CA",
    "sg:tags":[
        "trainer"
    ],
    "sg:website":"www.comppartners.com",
    "wof:name":"Comppartners",
    "wof:placetype":"venue"
},
  "geometry": {"coordinates":[-117.838227,33.678245],"type":"Point"}
}