{
  "type": "Feature",
  "properties": {
    "iso:country":"US",
    "sg:address":"265 Market Way",
    "sg:city":"Salinas",
    "sg:classifiers":[
        {
            "category":"Home & Garden",
            "subcategory":"Household Appliances",
            "type":"Retail Goods"
        }
    ],
    "sg:phone":"+1 831 757 8141",
    "sg:postcode":"93901",
    "sg:province":"CA",
    "sg:tags":[
        "refrigerator",
        "freezer"
    ],
    "wof:name":"Astech Appliance",
    "wof:placetype":"venue"
},
  "geometry": {"coordinates":[-121.64901500000001,36.678532],"type":"Point"}
}