{
  "type": "Feature",
  "properties": {
    "addr:full":"322 Culver Blvd Playa Del Rey CA 90293",
    "addr:housenumber":"322",
    "addr:postcode":"90293",
    "addr:street":"Culver Blvd",
    "iso:country":"US",
    "sg:address":"322 Culver Blvd",
    "sg:city":"Playa Del Rey",
    "sg:classifiers":[
        {
            "category":"Shopping",
            "subcategory":"Computers & Home Electronics",
            "type":"Retail Goods"
        }
    ],
    "sg:phone":"+1 323 750 8287",
    "sg:postcode":"90293",
    "sg:province":"CA",
    "sg:tags":[
        "parts",
        "supply"
    ],
    "wof:name":"Universal Computer Supplies",
    "wof:placetype":"venue"
},
  "geometry": {"coordinates":[-118.44746000000001,33.959373],"type":"Point"}
}