{
  "type": "Feature",
  "properties": {
    "addr:full":"2175 Proctor Valley Rd Chula Vista CA 91914",
    "addr:housenumber":"2175",
    "addr:postcode":"91914",
    "addr:street":"Proctor Valley Rd",
    "iso:country":"US",
    "sg:address":"2175 Proctor Valley Rd",
    "sg:city":"Chula Vista",
    "sg:classifiers":[
        {
            "category":"Education",
            "subcategory":"School",
            "type":"Public Place"
        }
    ],
    "sg:phone":"+1 619 397 5225",
    "sg:postcode":"91914",
    "sg:province":"CA",
    "wof:name":"Liberty Elementary School",
    "wof:placetype":"venue"
},
  "geometry": {"coordinates":[-116.974508,32.663925],"type":"Point"}
}