{
  "type": "Feature",
  "properties": {
    "iso:country":"US",
    "sg:address":"24025 Park Sorrento Ste 240",
    "sg:city":"Calabasas",
    "sg:classifiers":[
        {
            "category":"Professional",
            "subcategory":"Lawyer & Legal Services",
            "type":"Services"
        }
    ],
    "sg:phone":"+1 818 594 0075",
    "sg:postcode":"91302",
    "sg:province":"CA",
    "wof:name":"McClean Wayne",
    "wof:placetype":"venue"
},
  "geometry": {"coordinates":[-118.64903099999999,34.152209],"type":"Point"}
}