{
  "type": "Feature",
  "properties": {
    "addr:full":"819 Miraflores Ave San Pedro CA 90731",
    "addr:postcode":"90731",
    "addr:street":"819 Miraflores Ave",
    "iso:country":"US",
    "sg:address":"819 Miraflores Ave",
    "sg:city":"San Pedro",
    "sg:classifiers":[
        {
            "category":"Shopping",
            "subcategory":"Bicycles & Sporting Goods",
            "type":"Retail Goods"
        }
    ],
    "sg:phone":"+1 310 833 4521",
    "sg:postcode":"90731",
    "sg:province":"CA",
    "sg:tags":[
        "netting"
    ],
    "wof:name":"U S Net & Batting Cage Co",
    "wof:placetype":"venue"
},
  "geometry": {"coordinates":[-118.294355,33.752775],"type":"Point"}
}