{
  "type": "Feature",
  "properties": {
    "addr:full":"418 E Cypress Ave Redding CA 96002",
    "addr:housenumber":"418",
    "addr:postcode":"96002",
    "addr:street":"E Cypress Ave",
    "iso:country":"US",
    "sg:address":"418 E Cypress Ave",
    "sg:city":"Redding",
    "sg:classifiers":[
        {
            "category":"Autos & Motor Vehicles",
            "subcategory":"Automobile Sales",
            "type":"Retail Goods"
        }
    ],
    "sg:phone":"+1 530 226 0418",
    "sg:postcode":"96002",
    "sg:province":"CA",
    "sg:tags":[
        "new",
        "used",
        "car"
    ],
    "wof:name":"Redding Kia",
    "wof:placetype":"venue"
},
  "geometry": {"coordinates":[-122.364508,40.571058],"type":"Point"}
}