{
  "type": "Feature",
  "properties": {
    "addr:full":"1490 N Claremont Blvd Claremont CA 91711",
    "addr:housenumber":"1490",
    "addr:postcode":"91711",
    "addr:street":"N Claremont Blvd",
    "iso:country":"US",
    "sg:address":"1490 N Claremont Blvd",
    "sg:city":"Claremont",
    "sg:classifiers":[
        {
            "category":"Banks & Credit Unions",
            "subcategory":"Investment Brokerage",
            "type":"Services"
        }
    ],
    "sg:phone":"+1 909 447 2079",
    "sg:postcode":"91711",
    "sg:province":"CA",
    "sg:tags":[
        "management"
    ],
    "wof:name":"Glencrest Investment Advisors",
    "wof:placetype":"venue"
},
  "geometry": {"coordinates":[-117.70199,34.110959],"type":"Point"}
}