{
  "type": "Feature",
  "properties": {
    "iso:country":"US",
    "sg:address":"1887 W San Carlos St",
    "sg:city":"San Jose",
    "sg:classifiers":[
        {
            "category":"Shopping",
            "subcategory":"Used Merchandise",
            "type":"Retail Goods"
        }
    ],
    "sg:phone":"+1 408 289 1929",
    "sg:postcode":"95128",
    "sg:province":"CA",
    "sg:tags":[
        "antique"
    ],
    "wof:name":"Annette's Antiques & Collectibles",
    "wof:placetype":"venue"
},
  "geometry": {"coordinates":[-121.92800099999999,37.323399],"type":"Point"}
}