{
  "type": "Feature",
  "properties": {
    "iso:country":"US",
    "sg:address":"3125 W Florida Ave",
    "sg:city":"Hemet",
    "sg:classifiers":[
        {
            "category":"Food & Beverages",
            "subcategory":"Groceries & Convenience Stores",
            "type":"Retail Goods"
        }
    ],
    "sg:phone":"+1 951 658 0111",
    "sg:postcode":"92545",
    "sg:province":"CA",
    "sg:tags":[
        "grocer"
    ],
    "wof:name":"Vons Co",
    "wof:placetype":"venue"
},
  "geometry": {"coordinates":[-117.003794,33.747317],"type":"Point"}
}