{
  "type": "Feature",
  "properties": {
    "iso:country":"US",
    "sg:address":"540 E Main St",
    "sg:city":"Grass Valley",
    "sg:classifiers":[
        {
            "category":"Health Services",
            "subcategory":"Clinic",
            "type":"Services"
        }
    ],
    "sg:phone":"+1 530 274 9016",
    "sg:postcode":"95945",
    "sg:province":"CA",
    "wof:name":"Great Health Solutions",
    "wof:placetype":"venue"
},
  "geometry": {"coordinates":[-121.054019,39.224257],"type":"Point"}
}