{
  "type": "Feature",
  "properties": {
    "iso:country":"US",
    "sg:address":"275 Hilltop Dr",
    "sg:city":"Redding",
    "sg:classifiers":[
        {
            "category":"Real Estate",
            "subcategory":"Real Estate Services",
            "type":"Services"
        },
        {
            "category":"Real Estate",
            "subcategory":"Real Estate Agent",
            "type":"Services"
        }
    ],
    "sg:phone":"+1 530 605 4280",
    "sg:postcode":"96003",
    "sg:province":"CA",
    "sg:tags":[
        "buyer",
        "broker"
    ],
    "wof:name":"Baco Realty",
    "wof:placetype":"venue"
},
  "geometry": {"coordinates":[-122.37411400000001,40.601687],"type":"Point"}
}