{
  "type": "Feature",
  "properties": {
    "addr:full":"227 Mississippi St San Francisco CA 94107",
    "addr:housenumber":"227",
    "addr:postcode":"94107",
    "addr:street":"Mississippi St",
    "iso:country":"US",
    "sg:address":"227 Mississippi St",
    "sg:city":"San Francisco",
    "sg:classifiers":[
        {
            "category":"Wholesale",
            "subcategory":"Jewelry",
            "type":"Manufacturing & Wholesale Goods"
        }
    ],
    "sg:phone":"+1 415 863 1770",
    "sg:postcode":"94107",
    "sg:province":"CA",
    "sg:tags":[
        "fine",
        "mfg"
    ],
    "wof:name":"Agor Vicente",
    "wof:placetype":"venue"
},
  "geometry": {"coordinates":[-122.394544,37.763038],"type":"Point"}
}