{
  "type": "Feature",
  "properties": {
    "iso:country":"US",
    "sg:address":"21 Lower Ragsdale Dr",
    "sg:city":"Monterey",
    "sg:classifiers":[
        {
            "category":"Manufacturing",
            "subcategory":"Chemicals & Compounds",
            "type":"Manufacturing & Wholesale Goods"
        }
    ],
    "sg:phone":"+1 831 644 0300",
    "sg:postcode":"93940",
    "sg:province":"CA",
    "sg:tags":[
        "cosmetic"
    ],
    "wof:name":"Pharmagel International Inc",
    "wof:placetype":"venue"
},
  "geometry": {"coordinates":[-121.81648,36.575535],"type":"Point"}
}