{
  "type": "Feature",
  "properties": {
    "addr:full":"34717 Yucaipa Blvd Yucaipa CA 92399",
    "addr:postcode":"34717;92399",
    "addr:street":"Yucaipa Blvd",
    "iso:country":"US",
    "sg:address":"34717 Yucaipa Blvd",
    "sg:city":"Yucaipa",
    "sg:classifiers":[
        {
            "category":"Food & Beverages",
            "subcategory":"Supermarket",
            "type":"Retail Goods"
        },
        {
            "category":"Food & Beverages",
            "subcategory":"Groceries & Convenience Stores",
            "type":"Retail Goods"
        }
    ],
    "sg:phone":"+1 909 797 2033",
    "sg:postcode":"92399",
    "sg:province":"CA",
    "sg:tags":[
        "super"
    ],
    "wof:name":"Asaderos Supermarket",
    "wof:placetype":"venue"
},
  "geometry": {"coordinates":[-117.047229,34.033469],"type":"Point"}
}