{
  "type": "Feature",
  "properties": {
    "iso:country":"US",
    "sg:address":"1880 Century Park W Suite 2100",
    "sg:city":"Los Angeles",
    "sg:classifiers":[
        {
            "category":"Professional",
            "subcategory":"Employment Agencies",
            "type":"Services"
        }
    ],
    "sg:phone":"+1 310 553 5208",
    "sg:postcode":"90067",
    "sg:province":"CA",
    "wof:name":"Career Images",
    "wof:placetype":"venue"
},
  "geometry": {"coordinates":[-118.420172,34.057779],"type":"Point"}
}