{
  "type": "Feature",
  "properties": {
    "iso:country":"US",
    "sg:address":"1600 Sisk Rd",
    "sg:city":"Modesto",
    "sg:classifiers":[
        {
            "category":"Autos & Motor Vehicles",
            "subcategory":"Fuel & Gas Station",
            "type":"Retail Goods"
        }
    ],
    "sg:phone":"+1 209 526 6222",
    "sg:postcode":"95350",
    "sg:province":"CA",
    "sg:website":"www.chevron.com",
    "wof:name":"Chevron Stations Inc",
    "wof:placetype":"venue"
},
  "geometry": {"coordinates":[-121.03299699999999,37.6679],"type":"Point"}
}