{
  "type": "Feature",
  "properties": {
    "addr:full":"27 Maxwell St Lodi CA 95240",
    "addr:housenumber":"27",
    "addr:postcode":"95240",
    "addr:street":"Maxwell St",
    "iso:country":"US",
    "sg:address":"27 Maxwell St",
    "sg:city":"Lodi",
    "sg:classifiers":[
        {
            "category":"Wholesale",
            "subcategory":"Auto Parts",
            "type":"Manufacturing & Wholesale Goods"
        }
    ],
    "sg:phone":"+1 209 366 1700",
    "sg:postcode":"95240",
    "sg:province":"CA",
    "sg:tags":[
        "body",
        "shop",
        "automobile"
    ],
    "wof:name":"Spray Booth Doctor",
    "wof:placetype":"venue"
},
  "geometry": {"coordinates":[-121.270084,38.113083],"type":"Point"}
}