{
  "type": "Feature",
  "properties": {
    "addr:full":"2733 Lander Ave Turlock CA 95380",
    "addr:housenumber":"2733",
    "addr:postcode":"95380",
    "addr:street":"Lander Ave",
    "iso:country":"US",
    "sg:address":"2733 Lander Ave",
    "sg:city":"Turlock",
    "sg:classifiers":[
        {
            "category":"Food & Beverages",
            "subcategory":"Groceries & Convenience Stores",
            "type":"Retail Goods"
        }
    ],
    "sg:phone":"+1 209 667 0610",
    "sg:postcode":"95380",
    "sg:province":"CA",
    "sg:tags":[
        "grocer"
    ],
    "wof:name":"Airport Grocery",
    "wof:placetype":"venue"
},
  "geometry": {"coordinates":[-120.849098,37.467883],"type":"Point"}
}