{
  "type": "Feature",
  "properties": {
    "iso:country":"US",
    "sg:address":"2025 Gateway Pl Ste 100",
    "sg:city":"San Jose",
    "sg:classifiers":[
        {
            "category":"Real Estate",
            "subcategory":"Real Estate Services",
            "type":"Services"
        }
    ],
    "sg:phone":"+1 408 453 5100",
    "sg:postcode":"95110",
    "sg:province":"CA",
    "sg:tags":[
        "management",
        "property"
    ],
    "wof:name":"C M Stratplan",
    "wof:placetype":"venue"
},
  "geometry": {"coordinates":[-121.922997,37.370602],"type":"Point"}
}