{
  "type": "Feature",
  "properties": {
    "addr:full":"13208 Myford Rd Ste 330 Tustin CA 92782",
    "addr:housenumber":"13208",
    "addr:postcode":"92782",
    "addr:street":"Myford Rd Ste 330",
    "iso:country":"US",
    "sg:address":"13208 Myford Rd Ste 330",
    "sg:city":"Tustin",
    "sg:classifiers":[
        {
            "category":"Building & Trades",
            "subcategory":"Construction",
            "type":"Services"
        }
    ],
    "sg:phone":"+1 714 838 4959",
    "sg:postcode":"92782",
    "sg:province":"CA",
    "sg:tags":[
        "air",
        "heating",
        "conditioning/hvac"
    ],
    "sg:website":"hvacservicetustin.com#cid=yelp",
    "wof:name":"American Alliance HVAC Service Inc",
    "wof:placetype":"venue"
},
  "geometry": {"coordinates":[-117.789574,33.731836],"type":"Point"}
}