{
  "type": "Feature",
  "properties": {
    "iso:country":"US",
    "sg:address":"3180 Giannini Rd",
    "sg:city":"Atwater",
    "sg:classifiers":[
        {
            "category":"Travel",
            "subcategory":"Travel Agent",
            "type":"Entertainment"
        }
    ],
    "sg:phone":"+1 209 357 0000",
    "sg:postcode":"95301",
    "sg:province":"CA",
    "sg:tags":[
        "agency",
        "bureau"
    ],
    "wof:name":"A Great Vacations",
    "wof:placetype":"venue"
},
  "geometry": {"coordinates":[-120.599385,37.333301],"type":"Point"}
}