{
  "type": "Feature",
  "properties": {
    "addr:full":"591 Cam de la Reina San Diego CA 92108",
    "addr:housenumber":"591",
    "addr:postcode":"92108",
    "addr:street":"Cam De La Reina",
    "iso:country":"US",
    "sg:address":"591 Cam de la Reina",
    "sg:city":"San Diego",
    "sg:classifiers":[
        {
            "category":"Banks & Credit Unions",
            "subcategory":"Bank",
            "type":"Services"
        }
    ],
    "sg:phone":"+1 619 497 6303",
    "sg:postcode":"92108",
    "sg:province":"CA",
    "sg:tags":[
        "loan",
        "real estate"
    ],
    "wof:name":"Aaron Mortgage Group",
    "wof:placetype":"venue"
},
  "geometry": {"coordinates":[-117.161958,32.766304],"type":"Point"}
}