{
  "type": "Feature",
  "properties": {
    "addr:full":"151 10th St San Francisco CA 94103",
    "addr:housenumber":"151",
    "addr:postcode":"94103",
    "addr:street":"10Th St",
    "iso:country":"US",
    "sg:address":"151 10th St",
    "sg:city":"San Francisco",
    "sg:classifiers":[
        {
            "category":"Wholesale",
            "subcategory":"Apparel",
            "type":"Manufacturing & Wholesale Goods"
        }
    ],
    "sg:phone":"+1 415 558 0606",
    "sg:postcode":"94103",
    "sg:province":"CA",
    "wof:name":"Golden Gate Embroidery Inc",
    "wof:placetype":"venue"
},
  "geometry": {"coordinates":[-122.415649,37.775231],"type":"Point"}
}