{
  "type": "Feature",
  "properties": {
    "addr:full":"2590 S Bascom Avenue San Jose CA 95124",
    "addr:housenumber":"2590",
    "addr:postcode":"95124",
    "addr:street":"S Bascom Avenue",
    "iso:country":"US",
    "sg:address":"2590 S Bascom Avenue",
    "sg:city":"San Jose",
    "sg:classifiers":[
        {
            "category":"Restaurant",
            "type":"Food & Drink"
        }
    ],
    "sg:phone":"+1 408 371 1802",
    "sg:postcode":"95124",
    "sg:province":"CA",
    "wof:name":"Manley's Donut Shop",
    "wof:placetype":"venue"
},
  "geometry": {"coordinates":[-121.933751,37.274644],"type":"Point"}
}