{
  "type": "Feature",
  "properties": {
    "addr:full":"8526 Florence Ave Downey CA 90240",
    "addr:housenumber":"8526",
    "addr:postcode":"90240",
    "addr:street":"Florence Ave",
    "iso:country":"US",
    "sg:address":"8526 Florence Ave",
    "sg:city":"Downey",
    "sg:classifiers":[
        {
            "category":"Professional",
            "subcategory":"Lawyer & Legal Services",
            "type":"Services"
        }
    ],
    "sg:phone":"+1 562 622 0288",
    "sg:postcode":"90240",
    "sg:province":"CA",
    "sg:tags":[
        "divorce",
        "law",
        "family"
    ],
    "wof:name":"Law Offices of Dorothy L Carfrae",
    "wof:placetype":"venue"
},
  "geometry": {"coordinates":[-118.12200199999999,33.9496],"type":"Point"}
}