{
  "type": "Feature",
  "properties": {
    "addr:full":"614 E Main St Santa Maria CA 93454",
    "addr:housenumber":"614",
    "addr:postcode":"93454",
    "addr:street":"E Main St",
    "iso:country":"US",
    "sg:address":"614 E Main St",
    "sg:city":"Santa Maria",
    "sg:classifiers":[
        {
            "category":"Health Services",
            "subcategory":"Doctor",
            "type":"Services"
        }
    ],
    "sg:phone":"+1 805 349 9949",
    "sg:postcode":"93454",
    "sg:province":"CA",
    "sg:tags":[
        "clinic"
    ],
    "wof:name":"Auburn Pain Clinic",
    "wof:placetype":"venue"
},
  "geometry": {"coordinates":[-120.425955,34.953007],"type":"Point"}
}