{
  "type": "Feature",
  "properties": {
    "iso:country":"US",
    "sg:address":"619 N Croft Ave",
    "sg:city":"West Hollywood",
    "sg:classifiers":[
        {
            "category":"Shopping",
            "subcategory":"Clothing, Apparel, & Fashions",
            "type":"Retail Goods"
        }
    ],
    "sg:phone":"+1 323 297 0414",
    "sg:postcode":"90048",
    "sg:province":"CA",
    "sg:tags":[
        "men's",
        "clothing",
        "women's"
    ],
    "sg:website":"apc.fr/us/en/index.php",
    "wof:name":"A.P.C.",
    "wof:placetype":"venue"
},
  "geometry": {"coordinates":[-118.374362,34.082585],"type":"Point"}
}