{
  "type": "Feature",
  "properties": {
    "iso:country":"US",
    "sg:address":"2855 Stevens Creek Blvd",
    "sg:city":"Santa Clara",
    "sg:classifiers":[
        {
            "category":"Home & Garden",
            "subcategory":"Home Furnishings",
            "type":"Retail Goods"
        }
    ],
    "sg:phone":"+1 408 244 4554",
    "sg:postcode":"95014",
    "sg:province":"CA",
    "sg:tags":[
        "beveled",
        "glass",
        "ornamental"
    ],
    "wof:name":"J & R Products",
    "wof:placetype":"venue"
},
  "geometry": {"coordinates":[-121.945719,37.323439],"type":"Point"}
}