{
  "type": "Feature",
  "properties": {
    "addr:full":"5815 Thornhill Dr Oakland CA 94611",
    "addr:housenumber":"5815",
    "addr:postcode":"94611",
    "addr:street":"Thornhill Dr",
    "iso:country":"US",
    "sg:address":"5815 Thornhill Dr",
    "sg:city":"Oakland",
    "sg:classifiers":[
        {
            "category":"Social Services",
            "subcategory":"Child Care",
            "type":"Services"
        },
        {
            "category":"Education",
            "subcategory":"Preschool",
            "type":"Public Place"
        },
        {
            "category":"Education",
            "subcategory":"School",
            "type":"Public Place"
        }
    ],
    "sg:phone":"+1 510 339 7213",
    "sg:postcode":"94611",
    "sg:province":"CA",
    "sg:tags":[
        "kindergarten",
        "elementary"
    ],
    "wof:name":"Montclair Community Play Center",
    "wof:placetype":"venue"
},
  "geometry": {"coordinates":[-122.21199799999999,37.835701],"type":"Point"}
}