{
  "type": "Feature",
  "properties": {
    "addr:full":"426 E Arbor Vitae St Inglewood CA 90301",
    "addr:housenumber":"426",
    "addr:postcode":"90301",
    "addr:street":"E Arbor Vitae St",
    "iso:country":"US",
    "sg:address":"426 E Arbor Vitae St",
    "sg:city":"Inglewood",
    "sg:classifiers":[
        {
            "category":"Health Services",
            "subcategory":"Doctor",
            "type":"Services"
        },
        {
            "category":"Health Services",
            "subcategory":"Chiropractor",
            "type":"Services"
        }
    ],
    "sg:phone":"+1 310 672 4110",
    "sg:postcode":"90301",
    "sg:province":"CA",
    "sg:tags":[
        "podiatrist"
    ],
    "wof:name":"Safaeian Mike DC",
    "wof:placetype":"venue"
},
  "geometry": {"coordinates":[-118.34899900000001,33.952599],"type":"Point"}
}