{
  "type": "Feature",
  "properties": {
    "addr:full":"2721 East St Anderson CA 96007",
    "addr:housenumber":"2721",
    "addr:postcode":"96007",
    "addr:street":"East St",
    "iso:country":"US",
    "sg:address":"2721 East St",
    "sg:city":"Anderson",
    "sg:classifiers":[
        {
            "category":"Retail",
            "subcategory":"Auto Repair",
            "type":"Services"
        }
    ],
    "sg:phone":"+1 530 365 3777",
    "sg:postcode":"96007",
    "sg:province":"CA",
    "sg:tags":[
        "muffler",
        "exhaust",
        "system"
    ],
    "wof:name":"George's Muffler",
    "wof:placetype":"venue"
},
  "geometry": {"coordinates":[-122.295924,40.449722],"type":"Point"}
}