{
  "type": "Feature",
  "properties": {
    "addr:full":"1800 National City Blvd National City CA 91950",
    "addr:housenumber":"1800",
    "addr:postcode":"91950",
    "addr:street":"National City Blvd",
    "iso:country":"US",
    "sg:address":"1800 National City Blvd",
    "sg:city":"National City",
    "sg:classifiers":[
        {
            "category":"Autos & Motor Vehicles",
            "subcategory":"Automobile Sales",
            "type":"Retail Goods"
        }
    ],
    "sg:phone":"+1 619 474 8483",
    "sg:postcode":"91950",
    "sg:province":"CA",
    "sg:tags":[
        "car",
        "dealer"
    ],
    "wof:name":"In & Out Cars",
    "wof:placetype":"venue"
},
  "geometry": {"coordinates":[-117.102873,32.665453],"type":"Point"}
}