{
  "type": "Feature",
  "properties": {
    "iso:country":"US",
    "sg:address":"34400 Fremont Blvd",
    "sg:city":"Fremont",
    "sg:classifiers":[
        {
            "category":"Restaurant",
            "type":"Food & Drink"
        }
    ],
    "sg:phone":"+1 510 792 6234",
    "sg:postcode":"94555",
    "sg:province":"CA",
    "wof:name":"Pho 99 Vietnamese Restaurant",
    "wof:placetype":"venue"
},
  "geometry": {"coordinates":[-122.04109,37.57513],"type":"Point"}
}