{
  "type": "Feature",
  "properties": {
    "addr:full":"14411 Kittridge St Apt 101 Van Nuys CA 91405",
    "addr:housenumber":"14411;101",
    "addr:postcode":"91405",
    "addr:street":"Kittridge St Apt",
    "iso:country":"US",
    "sg:address":"14411 Kittridge St Apt 101",
    "sg:city":"Van Nuys",
    "sg:classifiers":[
        {
            "category":"Real Estate",
            "subcategory":"Real Estate Operator",
            "type":"Services"
        }
    ],
    "sg:phone":"+1 818 780 7498",
    "sg:postcode":"91405",
    "sg:province":"CA",
    "sg:tags":[
        "apartment"
    ],
    "wof:name":"Kittridge Glen Apartments",
    "wof:placetype":"venue"
},
  "geometry": {"coordinates":[-118.44699900000001,34.190701],"type":"Point"}
}