{
  "type": "Feature",
  "properties": {
    "addr:full":"2198 Chestnut Street San Francisco CA 94123",
    "addr:housenumber":"2198",
    "addr:postcode":"94123",
    "addr:street":"Chestnut Street",
    "iso:country":"US",
    "sg:address":"2198 Chestnut Street",
    "sg:city":"San Francisco",
    "sg:classifiers":[
        {
            "category":"Banks & Credit Unions",
            "subcategory":"Bank",
            "type":"Services"
        }
    ],
    "sg:phone":"+1 415 346 2901",
    "sg:postcode":"94123",
    "sg:province":"CA",
    "wof:name":"Citibank, NA",
    "wof:placetype":"venue"
},
  "geometry": {"coordinates":[-122.439494,37.800418],"type":"Point"}
}