{
  "type": "Feature",
  "properties": {
    "iso:country":"US",
    "sg:address":"3471 Via Lido",
    "sg:city":"Newport Beach",
    "sg:classifiers":[
        {
            "category":"Autos & Motor Vehicles",
            "subcategory":"Boat Sales",
            "type":"Retail Goods"
        }
    ],
    "sg:phone":"+1 949 675 9840",
    "sg:postcode":"92663",
    "sg:province":"CA",
    "sg:tags":[
        "dealer",
        "sales"
    ],
    "sg:website":"www.dimenmarine.com",
    "wof:name":"Dimen Marine",
    "wof:placetype":"venue"
},
  "geometry": {"coordinates":[-117.928875,33.618026],"type":"Point"}
}