{
  "type": "Feature",
  "properties": {
    "iso:country":"US",
    "sg:address":"9045 Canberra Dr",
    "sg:city":"Sacramento",
    "sg:classifiers":[
        {
            "category":"Education",
            "subcategory":"School",
            "type":"Public Place"
        }
    ],
    "sg:phone":"+1 916 228 5890",
    "sg:postcode":"95826",
    "sg:province":"CA",
    "sg:tags":[
        "elementary"
    ],
    "wof:name":"Golden Empire Elementary School",
    "wof:placetype":"venue"
},
  "geometry": {"coordinates":[-121.366997,38.541302],"type":"Point"}
}