{
  "type": "Feature",
  "properties": {
    "iso:country":"US",
    "sg:address":"10721 Walker St",
    "sg:city":"Cypress",
    "sg:classifiers":[
        {
            "category":"Wholesale",
            "subcategory":"Office Equipment",
            "type":"Manufacturing & Wholesale Goods"
        }
    ],
    "sg:phone":"+1 714 761 6368",
    "sg:postcode":"90630",
    "sg:province":"CA",
    "sg:tags":[
        "credit",
        "system",
        "card"
    ],
    "sg:website":"www.id-tech.net",
    "wof:name":"I D Tech",
    "wof:placetype":"venue"
},
  "geometry": {"coordinates":[-118.037031,33.807185],"type":"Point"}
}