{
  "type": "Feature",
  "properties": {
    "addr:full":"16880 Van Buren Blvd Riverside CA 92504",
    "addr:housenumber":"16880",
    "addr:postcode":"92504",
    "addr:street":"Van Buren Blvd",
    "iso:country":"US",
    "sg:address":"16880 Van Buren Blvd",
    "sg:city":"Riverside",
    "sg:classifiers":[
        {
            "category":"Restaurant",
            "type":"Food & Drink"
        }
    ],
    "sg:menulink":"http://www.allmenus.com/ca/riverside/147952-farmer-boys/menu/",
    "sg:phone":"+1 951 789 9080",
    "sg:postcode":"92504",
    "sg:province":"CA",
    "sg:tags":[
        "american"
    ],
    "wof:name":"Farmer Boys",
    "wof:placetype":"venue"
},
  "geometry": {"coordinates":[-117.36809100000001,33.882873],"type":"Point"}
}