{
  "type": "Feature",
  "properties": {
    "addr:full":"1122 Roosevelt Ave National City CA 91950",
    "addr:housenumber":"1122",
    "addr:postcode":"91950",
    "addr:street":"Roosevelt Ave",
    "iso:country":"US",
    "sg:address":"1122 Roosevelt Ave",
    "sg:city":"National City",
    "sg:classifiers":[
        {
            "category":"Retail",
            "subcategory":"Laundry & Dry Cleaning",
            "type":"Services"
        }
    ],
    "sg:phone":"+1 619 477 2385",
    "sg:postcode":"91950",
    "sg:province":"CA",
    "sg:tags":[
        "linen",
        "supply"
    ],
    "sg:website":"www.morganservices.com",
    "wof:name":"Morgan Linen Svc",
    "wof:placetype":"venue"
},
  "geometry": {"coordinates":[-117.10676599999999,32.672245],"type":"Point"}
}