{
  "type": "Feature",
  "properties": {
    "iso:country":"US",
    "sg:address":"1052 Tata Ln",
    "sg:city":"South Lake Tahoe",
    "sg:classifiers":[
        {
            "category":"Government",
            "subcategory":"Office",
            "type":"Public Place"
        }
    ],
    "sg:phone":"+1 530 542 6012",
    "sg:postcode":"96150",
    "sg:province":"CA",
    "sg:tags":[
        "village"
    ],
    "wof:name":"Business Licenses",
    "wof:placetype":"venue"
},
  "geometry": {"coordinates":[-120.007005,38.910342],"type":"Point"}
}