{
  "type": "Feature",
  "properties": {
    "addr:full":"5300 Whittier Blvd Los Angeles CA 90022",
    "addr:housenumber":"5300",
    "addr:postcode":"90022",
    "addr:street":"Whittier Blvd",
    "iso:country":"US",
    "sg:address":"5300 Whittier Blvd",
    "sg:city":"Los Angeles",
    "sg:classifiers":[
        {
            "category":"Health Services",
            "subcategory":"Doctor",
            "type":"Services"
        }
    ],
    "sg:phone":"+1 323 263 9685",
    "sg:postcode":"90022",
    "sg:province":"CA",
    "sg:tags":[
        "physician",
        "surgeon"
    ],
    "wof:name":"Pacific Alliance Medical Center",
    "wof:placetype":"venue"
},
  "geometry": {"coordinates":[-118.155998,34.0201],"type":"Point"}
}