{
  "type": "Feature",
  "properties": {
    "iso:country":"US",
    "sg:address":"873 Turquoise St",
    "sg:city":"San Diego",
    "sg:classifiers":[
        {
            "category":"Arts & Performance",
            "subcategory":"Theater",
            "type":"Entertainment"
        }
    ],
    "sg:phone":"+1 619 582 7883",
    "sg:postcode":"92109",
    "sg:province":"CA",
    "sg:tags":[
        "entertainer",
        "business"
    ],
    "wof:name":"Arte Flamenco Puro Academy",
    "wof:placetype":"venue"
},
  "geometry": {"coordinates":[-117.258367,32.808697],"type":"Point"}
}