{
  "type": "Feature",
  "properties": {
    "addr:full":"3816 Pioneer Trl South Lake Tahoe CA 96150",
    "addr:housenumber":"3816",
    "addr:postcode":"96150",
    "addr:street":"Pioneer Trl",
    "iso:country":"US",
    "sg:address":"3816 Pioneer Trl",
    "sg:city":"South Lake Tahoe",
    "sg:classifiers":[
        {
            "category":"Communications",
            "subcategory":"Film & Video Production",
            "type":"Services"
        }
    ],
    "sg:phone":"+1 530 544 5281",
    "sg:postcode":"96150",
    "sg:province":"CA",
    "sg:tags":[
        "taping"
    ],
    "wof:name":"Arlequin Productions",
    "wof:placetype":"venue"
},
  "geometry": {"coordinates":[-119.94882699999999,38.947897],"type":"Point"}
}