{
  "type": "Feature",
  "properties": {
    "addr:full":"34537 Melissa Ter Fremont CA 94555",
    "addr:housenumber":"34537",
    "addr:postcode":"94555",
    "addr:street":"Melissa Ter",
    "iso:country":"US",
    "sg:address":"34537 Melissa Ter",
    "sg:city":"Fremont",
    "sg:classifiers":[
        {
            "category":"Professional",
            "subcategory":"Management & Consulting",
            "type":"Services"
        }
    ],
    "sg:phone":"+1 510 794 5040",
    "sg:postcode":"94555",
    "sg:province":"CA",
    "sg:tags":[
        "retail",
        "direct",
        "sales"
    ],
    "wof:name":"Zee Foods LLC",
    "wof:placetype":"venue"
},
  "geometry": {"coordinates":[-122.058369,37.554179],"type":"Point"}
}