{
  "type": "Feature",
  "properties": {
    "addr:full":"1305 S Cloverdale Blvd Cloverdale CA 95425",
    "addr:housenumber":"1305",
    "addr:postcode":"95425",
    "addr:street":"S Cloverdale Blvd",
    "iso:country":"US",
    "sg:address":"1305 S Cloverdale Blvd",
    "sg:city":"Cloverdale",
    "sg:classifiers":[
        {
            "category":"Building & Trades",
            "subcategory":"Plumbing",
            "type":"Services"
        }
    ],
    "sg:phone":"+1 707 894 7775",
    "sg:postcode":"95425",
    "sg:province":"CA",
    "sg:tags":[
        "plumbing",
        "contractor"
    ],
    "wof:name":"Sonoma County Plumbing",
    "wof:placetype":"venue"
},
  "geometry": {"coordinates":[-123.012154,38.783709],"type":"Point"}
}