{
  "type": "Feature",
  "properties": {
    "addr:full":"208 S Crescent Dr Beverly Hills CA 90212",
    "addr:housenumber":"208",
    "addr:postcode":"90212",
    "addr:street":"S Crescent Dr",
    "iso:country":"US",
    "sg:address":"208 S Crescent Dr",
    "sg:city":"Beverly Hills",
    "sg:classifiers":[
        {
            "category":"Wholesale",
            "subcategory":"Jewelry",
            "type":"Manufacturing & Wholesale Goods"
        }
    ],
    "sg:phone":"+1 310 273 5721",
    "sg:postcode":"90212",
    "sg:province":"CA",
    "sg:tags":[
        "stone"
    ],
    "wof:name":"Iris & Chloe",
    "wof:placetype":"venue"
},
  "geometry": {"coordinates":[-118.395836,34.06244],"type":"Point"}
}