{
  "type": "Feature",
  "properties": {
    "iso:country":"US",
    "sg:address":"7624 Citrus Ave",
    "sg:city":"Oroville",
    "sg:classifiers":[
        {
            "category":"Farming",
            "subcategory":"Livestock Farm",
            "type":"Manufacturing & Wholesale Goods"
        }
    ],
    "sg:phone":"+1 530 533 6435",
    "sg:postcode":"95966",
    "sg:province":"CA",
    "sg:tags":[
        "crop",
        "general"
    ],
    "wof:name":"Kirk Sundahl",
    "wof:placetype":"venue"
},
  "geometry": {"coordinates":[-121.530893,39.424346],"type":"Point"}
}