{
  "type": "Feature",
  "properties": {
    "addr:full":"4482 Market St Ste 406 Ventura CA 93003",
    "addr:housenumber":"4482",
    "addr:postcode":"93003",
    "addr:street":"Market St Ste 406",
    "iso:country":"US",
    "sg:address":"4482 Market St Ste 406",
    "sg:city":"Ventura",
    "sg:classifiers":[
        {
            "category":"Health Services",
            "subcategory":"Doctor",
            "type":"Services"
        }
    ],
    "sg:phone":"+1 805 644 0544",
    "sg:postcode":"93003",
    "sg:province":"CA",
    "sg:tags":[
        "psychologist"
    ],
    "wof:name":"Nightingale John A Ph.D.",
    "wof:placetype":"venue"
},
  "geometry": {"coordinates":[-119.232916,34.257237],"type":"Point"}
}