{
  "type": "Feature",
  "properties": {
    "addr:full":"3828 W Sunset Blvd Los Angeles CA 90026",
    "addr:housenumber":"3828",
    "addr:postcode":"90026",
    "addr:street":"W Sunset Blvd",
    "iso:country":"US",
    "sg:address":"3828 W Sunset Blvd",
    "sg:city":"Los Angeles",
    "sg:classifiers":[
        {
            "category":"Shopping",
            "subcategory":"Clothing, Apparel, & Fashions",
            "type":"Retail Goods"
        }
    ],
    "sg:phone":"+1 323 662 8132",
    "sg:postcode":"90026",
    "sg:province":"CA",
    "sg:tags":[
        "navy",
        "army"
    ],
    "wof:name":"Surplus Value Center",
    "wof:placetype":"venue"
},
  "geometry": {"coordinates":[-118.278999,34.091599],"type":"Point"}
}