{
  "type": "Feature",
  "properties": {
    "iso:country":"US",
    "sg:address":"21 Bennington",
    "sg:city":"Irvine",
    "sg:classifiers":[
        {
            "category":"Banks & Credit Unions",
            "subcategory":"Financial Services",
            "type":"Services"
        }
    ],
    "sg:phone":"+1 949 262 0545",
    "sg:postcode":"92620",
    "sg:province":"CA",
    "sg:tags":[
        "trust",
        "management"
    ],
    "wof:name":"Schlesinger Family Living Tr",
    "wof:placetype":"venue"
},
  "geometry": {"coordinates":[-117.762254,33.706617],"type":"Point"}
}