{
  "type": "Feature",
  "properties": {
    "iso:country":"US",
    "sg:address":"2202 S Figueroa St.",
    "sg:city":"Los Angeles",
    "sg:classifiers":[
        {
            "category":"Landmark",
            "subcategory":"Tourist Information",
            "type":"Public Place"
        }
    ],
    "sg:phone":"+1 213 385 3004",
    "sg:postcode":"90007",
    "sg:province":"CA",
    "sg:tags":[
        "tour"
    ],
    "sg:website":"www.tourslosangeles.com#cid=yelp",
    "wof:name":"Guideline Tours",
    "wof:placetype":"venue"
},
  "geometry": {"coordinates":[-118.273931,34.031382],"type":"Point"}
}