{
  "type": "Feature",
  "properties": {
    "iso:country":"US",
    "sg:address":"3713 Sardinia Island Way",
    "sg:city":"Sacramento",
    "sg:classifiers":[
        {
            "category":"Building & Trades",
            "subcategory":"Construction",
            "type":"Services"
        }
    ],
    "sg:phone":"+1 916 285 0512",
    "sg:postcode":"95834",
    "sg:province":"CA",
    "sg:tags":[
        "contractor"
    ],
    "wof:name":"Morrison Homes West Shore",
    "wof:placetype":"venue"
},
  "geometry": {"coordinates":[-121.544415,38.645987],"type":"Point"}
}