{
  "type": "Feature",
  "properties": {
    "iso:country":"US",
    "sg:address":"745 W Katella Ave",
    "sg:city":"Orange",
    "sg:classifiers":[
        {
            "category":"Shopping",
            "subcategory":"Discount & Variety Stores",
            "type":"Retail Goods"
        }
    ],
    "sg:phone":"+1 714 997 3865",
    "sg:postcode":"92867",
    "sg:province":"CA",
    "sg:tags":[
        "merchandise",
        "general"
    ],
    "wof:name":"Milano Merchandise",
    "wof:placetype":"venue"
},
  "geometry": {"coordinates":[-117.86129,33.809096],"type":"Point"}
}