{
  "type": "Feature",
  "properties": {
    "addr:full":"721 Brea Canyon Rd Ste 10 Walnut CA 91789",
    "addr:housenumber":"721;10",
    "addr:postcode":"91789",
    "addr:street":"Brea Canyon Rd Ste",
    "iso:country":"US",
    "sg:address":"721 Brea Canyon Rd Ste 10",
    "sg:city":"Walnut",
    "sg:classifiers":[
        {
            "category":"Manufacturing",
            "subcategory":"Food",
            "type":"Manufacturing & Wholesale Goods"
        }
    ],
    "sg:phone":"+1 626 854 6045",
    "sg:postcode":"91789",
    "sg:province":"CA",
    "sg:tags":[
        "coffee",
        "tea-wholesale",
        "manufacturer"
    ],
    "wof:name":"Austin Tea & Ginseng Inc",
    "wof:placetype":"venue"
},
  "geometry": {"coordinates":[-117.84652699999999,34.003929],"type":"Point"}
}