{
  "type": "Feature",
  "properties": {
    "addr:full":"2843 Pierpont Blvd Ventura CA 93001",
    "addr:housenumber":"2843",
    "addr:postcode":"93001",
    "addr:street":"Pierpont Blvd",
    "iso:country":"US",
    "sg:address":"2843 Pierpont Blvd",
    "sg:city":"Ventura",
    "sg:classifiers":[
        {
            "category":"Professional",
            "subcategory":"Employment Agencies",
            "type":"Services"
        }
    ],
    "sg:phone":"+1 805 643 4243",
    "sg:postcode":"93001",
    "sg:province":"CA",
    "sg:tags":[
        "help",
        "supply"
    ],
    "wof:name":"Joe Neary Modeling Company",
    "wof:placetype":"venue"
},
  "geometry": {"coordinates":[-119.267754,34.256281],"type":"Point"}
}