{
  "type": "Feature",
  "properties": {
    "iso:country":"US",
    "sg:address":"26876 The Old Rd",
    "sg:city":"Valencia",
    "sg:classifiers":[
        {
            "category":"Restaurant",
            "type":"Food & Drink"
        }
    ],
    "sg:phone":"+1 661 254 2018",
    "sg:postcode":"91381",
    "sg:province":"CA",
    "sg:tags":[
        "cajun/creole",
        "cuban",
        "latin",
        "caribbean",
        "american"
    ],
    "sg:website":"www.mojitocuisine.com",
    "wof:name":"Mojito Caribbean Cuisine",
    "wof:placetype":"venue"
},
  "geometry": {"coordinates":[-118.579391,34.410271],"type":"Point"}
}