{
  "type": "Feature",
  "properties": {
    "addr:full":"200 Sandpointe Ave Santa Ana CA 92707",
    "addr:housenumber":"200",
    "addr:postcode":"92707",
    "addr:street":"Sandpointe Ave",
    "iso:country":"US",
    "sg:address":"200 Sandpointe Ave",
    "sg:city":"Santa Ana",
    "sg:classifiers":[
        {
            "category":"Professional",
            "subcategory":"Lawyer & Legal Services",
            "type":"Services"
        }
    ],
    "sg:phone":"+1 714 241 4721",
    "sg:postcode":"92707",
    "sg:province":"CA",
    "sg:tags":[
        "consulting",
        "management"
    ],
    "wof:name":"Holly E Parks",
    "wof:placetype":"venue"
},
  "geometry": {"coordinates":[-117.86586200000001,33.697664],"type":"Point"}
}