{
  "type": "Feature",
  "properties": {
    "addr:full":"2004 University Avenue Berkeley CA 94704",
    "addr:housenumber":"2004",
    "addr:postcode":"94704",
    "addr:street":"University Avenue",
    "iso:country":"US",
    "sg:address":"2004 University Avenue",
    "sg:city":"Berkeley",
    "sg:classifiers":[
        {
            "category":"Shopping",
            "subcategory":"Florist",
            "type":"Retail Goods"
        }
    ],
    "sg:phone":"+1 510 524 8208",
    "sg:postcode":"94704",
    "sg:province":"CA",
    "wof:name":"Darling's Sunset Florist",
    "wof:placetype":"venue"
},
  "geometry": {"coordinates":[-122.261002,37.864799],"type":"Point"}
}