{
  "type": "Feature",
  "properties": {
    "iso:country":"US",
    "sg:address":"1859 W 169th St",
    "sg:city":"Gardena",
    "sg:classifiers":[
        {
            "category":"Freight",
            "type":"Transportation"
        }
    ],
    "sg:phone":"+1 310 327 3500",
    "sg:postcode":"90247",
    "sg:province":"CA",
    "sg:tags":[
        "delivery"
    ],
    "sg:website":"www.minutemandelivery.com",
    "wof:name":"Minute Man Delivery",
    "wof:placetype":"venue"
},
  "geometry": {"coordinates":[-118.31204200000001,33.87839],"type":"Point"}
}