{
  "type": "Feature",
  "properties": {
    "iso:country":"US",
    "sg:address":"2027 N Main St",
    "sg:city":"Salinas",
    "sg:classifiers":[
        {
            "category":"Personal",
            "subcategory":"Beauty Salon",
            "type":"Services"
        }
    ],
    "sg:phone":"+1 831 443 9330",
    "sg:postcode":"93906",
    "sg:province":"CA",
    "wof:name":"Destiny Magic Hair Salon",
    "wof:placetype":"venue"
},
  "geometry": {"coordinates":[-121.65633800000001,36.722028],"type":"Point"}
}