{
  "type": "Feature",
  "properties": {
    "iso:country":"US",
    "sg:address":"10524 Rubio Ave",
    "sg:city":"Granada Hills",
    "sg:classifiers":[
        {
            "category":"Professional",
            "type":"Services"
        }
    ],
    "sg:phone":"+1 818 368 7861",
    "sg:postcode":"91344",
    "sg:province":"CA",
    "wof:name":"Ezra Rafael Abrahamy",
    "wof:placetype":"venue"
},
  "geometry": {"coordinates":[-118.49569099999999,34.262375],"type":"Point"}
}