{
  "type": "Feature",
  "properties": {
    "addr:full":"1719 W Verdugo Ave Burbank CA 91506",
    "addr:housenumber":"1719",
    "addr:postcode":"91506",
    "addr:street":"W Verdugo Ave",
    "iso:country":"US",
    "sg:address":"1719 W Verdugo Ave",
    "sg:city":"Burbank",
    "sg:classifiers":[
        {
            "category":"Arena",
            "subcategory":"Sports Club",
            "type":"Entertainment"
        }
    ],
    "sg:phone":"+1 818 276 1936",
    "sg:postcode":"91506",
    "sg:province":"CA",
    "sg:tags":[
        "martial art"
    ],
    "sg:website":"academyofarms.com",
    "wof:name":"Academy of Arms",
    "wof:placetype":"venue"
},
  "geometry": {"coordinates":[-118.323447,34.167797],"type":"Point"}
}