{
  "type": "Feature",
  "properties": {
    "iso:country":"US",
    "sg:address":"10706 Orange Grove Ave",
    "sg:city":"Whittier",
    "sg:classifiers":[
        {
            "category":"Education",
            "subcategory":"School",
            "type":"Public Place"
        }
    ],
    "sg:phone":"+1 562 789 3076",
    "sg:postcode":"90601",
    "sg:province":"CA",
    "sg:tags":[
        "high",
        "middle",
        "elementary"
    ],
    "wof:name":"Whittier City Elementary School District",
    "wof:placetype":"venue"
},
  "geometry": {"coordinates":[-118.05999799999999,33.996498],"type":"Point"}
}