{
  "type": "Feature",
  "properties": {
    "iso:country":"US",
    "sg:address":"525 College Ave",
    "sg:city":"Santa Rosa",
    "sg:classifiers":[
        {
            "category":"Real Estate",
            "subcategory":"Real Estate Services",
            "type":"Services"
        }
    ],
    "sg:phone":"+1 707 543 8410",
    "sg:postcode":"95404",
    "sg:province":"CA",
    "sg:tags":[
        "company",
        "title"
    ],
    "wof:name":"Financial Title Co",
    "wof:placetype":"venue"
},
  "geometry": {"coordinates":[-122.716465,38.445685],"type":"Point"}
}