{
  "type": "Feature",
  "properties": {
    "addr:full":"2383 Lomita Blvd Ste 116 Lomita CA 90717",
    "addr:housenumber":"2383",
    "addr:postcode":"90717",
    "addr:street":"Lomita Blvd Ste 116",
    "iso:country":"US",
    "sg:address":"2383 Lomita Blvd Ste 116",
    "sg:city":"Lomita",
    "sg:classifiers":[
        {
            "category":"Restaurant",
            "type":"Food & Drink"
        }
    ],
    "sg:phone":"+1 310 325 6674",
    "sg:postcode":"90717",
    "sg:province":"CA",
    "sg:tags":[
        "japanese"
    ],
    "wof:name":"Eboshi Noodle Bar",
    "wof:placetype":"venue"
},
  "geometry": {"coordinates":[-118.324997,33.804501],"type":"Point"}
}