{
  "type": "Feature",
  "properties": {
    "iso:country":"US",
    "sg:address":"2701 5th St Ste 3",
    "sg:city":"Sacramento",
    "sg:classifiers":[
        {
            "category":"Government",
            "subcategory":"Office",
            "type":"Public Place"
        }
    ],
    "sg:phone":"+1 916 874 2430",
    "sg:postcode":"95818",
    "sg:province":"CA",
    "sg:tags":[
        "government-united",
        "state"
    ],
    "sg:website":"http://www.saccountybids.com",
    "wof:name":"Human Assistance Dept",
    "wof:placetype":"venue"
},
  "geometry": {"coordinates":[-121.509163,38.560735],"type":"Point"}
}