{
  "type": "Feature",
  "properties": {
    "iso:country":"US",
    "sg:address":"11305 183rd St",
    "sg:city":"Cerritos",
    "sg:classifiers":[
        {
            "category":"Restaurant",
            "type":"Food & Drink"
        }
    ],
    "sg:phone":"+1 562 865 0300",
    "sg:postcode":"90703",
    "sg:province":"CA",
    "sg:tags":[
        "filipino"
    ],
    "sg:website":"www.josephinesbistroandbar.com/",
    "wof:name":"Josephine's Bistro and Bar",
    "wof:placetype":"venue"
},
  "geometry": {"coordinates":[-118.092869,33.866016],"type":"Point"}
}