{
  "type": "Feature",
  "properties": {
    "addr:full":"8967 Fullbright Ave Chatsworth CA 91311",
    "addr:housenumber":"8967",
    "addr:postcode":"91311",
    "addr:street":"Fullbright Ave",
    "iso:country":"US",
    "sg:address":"8967 Fullbright Ave",
    "sg:city":"Chatsworth",
    "sg:classifiers":[
        {
            "category":"Communications",
            "subcategory":"Film & Video Production",
            "type":"Services"
        }
    ],
    "sg:phone":"+1 818 701 4424",
    "sg:postcode":"91311",
    "sg:province":"CA",
    "sg:tags":[
        "taping"
    ],
    "wof:name":"Extreme Video & Assoc",
    "wof:placetype":"venue"
},
  "geometry": {"coordinates":[-118.57762099999999,34.234255],"type":"Point"}
}