{
  "type": "Feature",
  "properties": {
    "iso:country":"US",
    "sg:address":"7718 Gloria Ave",
    "sg:city":"Van Nuys",
    "sg:classifiers":[
        {
            "category":"Retail",
            "subcategory":"Auto Repair",
            "type":"Services"
        }
    ],
    "sg:phone":"+1 818 780 9101",
    "sg:postcode":"91406",
    "sg:province":"CA",
    "sg:tags":[
        "repairing",
        "automobile"
    ],
    "wof:name":"Larry's Automotive Repair",
    "wof:placetype":"venue"
},
  "geometry": {"coordinates":[-118.47922699999999,34.209904],"type":"Point"}
}