{
  "type": "Feature",
  "properties": {
    "addr:full":"2711 Garden Rd Monterey CA 93940",
    "addr:housenumber":"2711",
    "addr:postcode":"93940",
    "addr:street":"Garden Rd",
    "iso:country":"US",
    "sg:address":"2711 Garden Rd",
    "sg:city":"Monterey",
    "sg:classifiers":[
        {
            "category":"Professional",
            "subcategory":"Lawyer & Legal Services",
            "type":"Services"
        }
    ],
    "sg:phone":"+1 831 373 8035",
    "sg:postcode":"93940",
    "sg:province":"CA",
    "sg:tags":[
        "attorney",
        "negligence",
        "practice",
        "liability",
        "malpractice",
        "law"
    ],
    "sg:website":"http://www.dunnion.com",
    "wof:name":"The Dunnion Law Firm A P C",
    "wof:placetype":"venue"
},
  "geometry": {"coordinates":[-121.849521,36.585513],"type":"Point"}
}