{
  "type": "Feature",
  "properties": {
    "iso:country":"US",
    "sg:address":"5542 Whittier Blvd",
    "sg:city":"Commerce",
    "sg:classifiers":[
        {
            "category":"Health Services",
            "subcategory":"Doctor",
            "type":"Services"
        }
    ],
    "sg:phone":"+1 323 722 8700",
    "sg:postcode":"90022",
    "sg:province":"CA",
    "sg:tags":[
        "dental",
        "clinic",
        "dentist"
    ],
    "wof:name":"Commerce Dental",
    "wof:placetype":"venue"
},
  "geometry": {"coordinates":[-118.150952,34.01906],"type":"Point"}
}