{
  "type": "Feature",
  "properties": {
    "iso:country":"US",
    "sg:address":"3581 Mt Diablo Blvd Ste 225",
    "sg:city":"Lafayette",
    "sg:classifiers":[
        {
            "category":"Insurance",
            "subcategory":"Hazard Insurance",
            "type":"Services"
        },
        {
            "category":"Insurance",
            "subcategory":"Insurance Agent",
            "type":"Services"
        },
        {
            "category":"Insurance",
            "subcategory":"Life Insurance",
            "type":"Services"
        }
    ],
    "sg:phone":"+1 925 298 4312",
    "sg:postcode":"94549",
    "sg:province":"CA",
    "sg:tags":[
        "auto",
        "property",
        "casualty"
    ],
    "wof:name":"Francis, Judy - State Farm Insurance Agent",
    "wof:placetype":"venue"
},
  "geometry": {"coordinates":[-122.122069,37.891616],"type":"Point"}
}