{
  "type": "Feature",
  "properties": {
    "iso:country":"US",
    "sg:address":"1148 Fulton Ave Ste C",
    "sg:city":"Sacramento",
    "sg:classifiers":[
        {
            "category":"Bars & Pubs",
            "subcategory":"Lounge",
            "type":"Food & Drink"
        }
    ],
    "sg:phone":"+1 916 481 2024",
    "sg:postcode":"95825",
    "sg:province":"CA",
    "sg:tags":[
        "cocktail"
    ],
    "wof:name":"Stoly's",
    "wof:placetype":"venue"
},
  "geometry": {"coordinates":[-121.405884,38.574459],"type":"Point"}
}