{
  "type": "Feature",
  "properties": {
    "iso:country":"US",
    "sg:address":"155 E Albertoni St",
    "sg:city":"Carson",
    "sg:classifiers":[
        {
            "category":"Freight",
            "type":"Transportation"
        }
    ],
    "sg:phone":"+1 310 329 0399",
    "sg:postcode":"90746",
    "sg:province":"CA",
    "sg:tags":[
        "courier"
    ],
    "sg:website":"www.dynamexcorp.com",
    "wof:name":"Dynamex Corp",
    "wof:placetype":"venue"
},
  "geometry": {"coordinates":[-118.273482,33.871414],"type":"Point"}
}