{
  "type": "Feature",
  "properties": {
    "iso:country":"US",
    "sg:address":"353 W Main St",
    "sg:city":"Woodland",
    "sg:classifiers":[
        {
            "category":"Retail",
            "subcategory":"Self-service Laundry",
            "type":"Services"
        }
    ],
    "sg:phone":"+1 530 668 1438",
    "sg:postcode":"95695",
    "sg:province":"CA",
    "wof:name":"Westgate Wash N Dry",
    "wof:placetype":"venue"
},
  "geometry": {"coordinates":[-121.80038999999999,38.677591],"type":"Point"}
}