{
  "type": "Feature",
  "properties": {
    "addr:full":"1557 E Ave R Palmdale CA 93550",
    "addr:housenumber":"1557",
    "addr:postcode":"ca 93550",
    "addr:street":"E Ave R",
    "iso:country":"US",
    "sg:address":"1557 E Ave R",
    "sg:city":"Palmdale",
    "sg:classifiers":[
        {
            "category":"Utilities",
            "subcategory":"Mobile Phone",
            "type":"Services"
        }
    ],
    "sg:phone":"+1 661 272 2850",
    "sg:postcode":"93550",
    "sg:province":"CA",
    "sg:tags":[
        "communication",
        "radiotelephone"
    ],
    "wof:name":"Ingenieria Digital Wireless",
    "wof:placetype":"venue"
},
  "geometry": {"coordinates":[-118.100494,34.572748],"type":"Point"}
}