{
  "type": "Feature",
  "properties": {
    "iso:country":"US",
    "sg:address":"13712 Desmond St",
    "sg:city":"Pacoima",
    "sg:classifiers":[
        {
            "category":"Professional",
            "subcategory":"Detective & Security Services",
            "type":"Services"
        }
    ],
    "sg:phone":"+1 818 389 2277",
    "sg:postcode":"91331",
    "sg:province":"CA",
    "sg:tags":[
        "information",
        "bureau"
    ],
    "wof:name":"Selective Tax Services",
    "wof:placetype":"venue"
},
  "geometry": {"coordinates":[-118.431285,34.274198],"type":"Point"}
}