{
  "type": "Feature",
  "properties": {
    "iso:country":"US",
    "sg:address":"1351 Powell Street",
    "sg:city":"San Francisco",
    "sg:classifiers":[
        {
            "category":"Banks & Credit Unions",
            "subcategory":"Bank",
            "type":"Services"
        }
    ],
    "sg:phone":"+1 415 986 6999",
    "sg:postcode":"94133",
    "sg:province":"CA",
    "sg:website":"www.metropolitanbank.com",
    "wof:name":"Metropolitan Bank",
    "wof:placetype":"venue"
},
  "geometry": {"coordinates":[-122.410004,37.797199],"type":"Point"}
}