{
  "type": "Feature",
  "properties": {
    "iso:country":"US",
    "sg:address":"11532 Claridge Dr",
    "sg:city":"Rancho Cucamonga",
    "sg:classifiers":[
        {
            "category":"Building & Trades",
            "subcategory":"Plumbing",
            "type":"Services"
        }
    ],
    "sg:phone":"+1 909 948 9159",
    "sg:postcode":"91730",
    "sg:province":"CA",
    "sg:tags":[
        "contractor"
    ],
    "wof:name":"Beme Services",
    "wof:placetype":"venue"
},
  "geometry": {"coordinates":[-117.552535,34.116929],"type":"Point"}
}