{
  "type": "Feature",
  "properties": {
    "iso:country":"US",
    "sg:address":"485 Los Coches St",
    "sg:city":"Milpitas",
    "sg:classifiers":[
        {
            "category":"Health Services",
            "subcategory":"Chiropractor",
            "type":"Services"
        }
    ],
    "sg:phone":"+1 408 946 9332",
    "sg:postcode":"95035",
    "sg:province":"CA",
    "wof:name":"Lana Hutnick, DC",
    "wof:placetype":"venue"
},
  "geometry": {"coordinates":[-121.896939,37.43102],"type":"Point"}
}