{
  "type": "Feature",
  "properties": {
    "addr:full":"37130 Calico Blvd Yermo CA 92398",
    "addr:housenumber":"37130",
    "addr:postcode":"92398",
    "addr:street":"Calico Blvd",
    "iso:country":"US",
    "sg:address":"37130 Calico Blvd",
    "sg:city":"Yermo",
    "sg:classifiers":[
        {
            "category":"Real Estate",
            "subcategory":"Real Estate Operator",
            "type":"Services"
        }
    ],
    "sg:phone":"+1 760 254 2525",
    "sg:postcode":"92398",
    "sg:province":"CA",
    "sg:tags":[
        "mobile",
        "home",
        "community"
    ],
    "wof:name":"Oasis Palms Mobile Home Park",
    "wof:placetype":"venue"
},
  "geometry": {"coordinates":[-116.854865,34.908951],"type":"Point"}
}