{
  "type": "Feature",
  "properties": {
    "addr:full":"807 Washington St Oakland CA 94607",
    "addr:housenumber":"807",
    "addr:postcode":"94607",
    "addr:street":"Washington St",
    "iso:country":"US",
    "sg:address":"807 Washington St",
    "sg:city":"Oakland",
    "sg:classifiers":[
        {
            "category":"Personal",
            "subcategory":"Beauty Salon",
            "type":"Services"
        },
        {
            "category":"Personal",
            "subcategory":"Skin Care",
            "type":"Services"
        },
        {
            "category":"Personal",
            "subcategory":"Nail Salon",
            "type":"Services"
        }
    ],
    "sg:phone":"+1 510 835 5634",
    "sg:postcode":"94607",
    "sg:province":"CA",
    "sg:tags":[
        "hair"
    ],
    "sg:website":"www.ajudadayspa.com",
    "wof:name":"Ajuda Day Spa",
    "wof:placetype":"venue"
},
  "geometry": {"coordinates":[-122.274947,37.8008],"type":"Point"}
}