{
  "type": "Feature",
  "properties": {
    "iso:country":"US",
    "sg:address":"226 Airport Pkwy",
    "sg:city":"San Jose",
    "sg:classifiers":[
        {
            "category":"Professional",
            "subcategory":"Accounting & Tax Preparation",
            "type":"Services"
        }
    ],
    "sg:phone":"+1 408 454 2455",
    "sg:postcode":"95110",
    "sg:province":"CA",
    "sg:tags":[
        "accountant"
    ],
    "wof:name":"Jefferson Wells Intl",
    "wof:placetype":"venue"
},
  "geometry": {"coordinates":[-121.92207,37.369652],"type":"Point"}
}