{
  "type": "Feature",
  "properties": {
    "addr:full":"1130 E Broadway Glendale CA 91205",
    "addr:housenumber":"1130",
    "addr:postcode":"91205",
    "addr:street":"E Broadway",
    "iso:country":"US",
    "sg:address":"1130 E Broadway",
    "sg:city":"Glendale",
    "sg:classifiers":[
        {
            "category":"Building & Trades",
            "subcategory":"Construction",
            "type":"Services"
        }
    ],
    "sg:phone":"+1 818 541 7118",
    "sg:postcode":"91205",
    "sg:province":"CA",
    "sg:tags":[
        "product",
        "asphalt"
    ],
    "wof:name":"Marlyn Ostrich Factory",
    "wof:placetype":"venue"
},
  "geometry": {"coordinates":[-118.23961199999999,34.146228],"type":"Point"}
}