{
  "type": "Feature",
  "properties": {
    "addr:full":"7050 Owensmouth Ave Canoga Park CA 91303",
    "addr:housenumber":"7050",
    "addr:postcode":"91303",
    "addr:street":"Owensmouth Ave",
    "iso:country":"US",
    "sg:address":"7050 Owensmouth Ave",
    "sg:city":"Canoga Park",
    "sg:classifiers":[
        {
            "category":"Insurance",
            "subcategory":"Insurance Agent",
            "type":"Services"
        }
    ],
    "sg:phone":"+1 818 987 6888",
    "sg:postcode":"91303",
    "sg:province":"CA",
    "wof:name":"Quick General Svc",
    "wof:placetype":"venue"
},
  "geometry": {"coordinates":[-118.601484,34.198272],"type":"Point"}
}