{
  "type": "Feature",
  "properties": {
    "addr:full":"933 San Pablo Ave Albany CA 94706",
    "addr:housenumber":"933",
    "addr:postcode":"94706",
    "addr:street":"San Pablo Ave",
    "iso:country":"US",
    "sg:address":"933 San Pablo Ave",
    "sg:city":"Albany",
    "sg:classifiers":[
        {
            "category":"Professional",
            "subcategory":"Computer Services",
            "type":"Services"
        }
    ],
    "sg:phone":"+1 510 526 2626",
    "sg:postcode":"94706",
    "sg:province":"CA",
    "sg:tags":[
        "repair"
    ],
    "sg:website":"www.at2k.com",
    "wof:name":"Advance Technology 2000",
    "wof:placetype":"venue"
},
  "geometry": {"coordinates":[-122.29850999999999,37.88904],"type":"Point"}
}