{
  "type": "Feature",
  "properties": {
    "addr:full":"6968 Sunrise Blvd Citrus Heights CA 95610",
    "addr:housenumber":"6968",
    "addr:postcode":"95610",
    "addr:street":"Sunrise Blvd",
    "iso:country":"US",
    "sg:address":"6968 Sunrise Blvd",
    "sg:city":"Citrus Heights",
    "sg:classifiers":[
        {
            "category":"Building & Trades",
            "subcategory":"Locksmith",
            "type":"Services"
        }
    ],
    "sg:phone":"+1 916 943 0377",
    "sg:postcode":"95610",
    "sg:province":"CA",
    "sg:tags":[
        "key"
    ],
    "sg:website":"www.availablelocksmithinc.com/Ci...",
    "wof:name":"Lockout Locksmith",
    "wof:placetype":"venue"
},
  "geometry": {"coordinates":[-121.271553,38.692763],"type":"Point"}
}