{
  "type": "Feature",
  "properties": {
    "addr:full":"2937 Union Ave San Jose CA 95124",
    "addr:housenumber":"2937",
    "addr:postcode":"95124",
    "addr:street":"Union Ave",
    "iso:country":"US",
    "sg:address":"2937 Union Ave",
    "sg:city":"San Jose",
    "sg:classifiers":[
        {
            "category":"Health Services",
            "subcategory":"Health Practitioner",
            "type":"Services"
        },
        {
            "category":"Health Services",
            "subcategory":"Chiropractor",
            "type":"Services"
        }
    ],
    "sg:phone":"+1 408 559 0771",
    "sg:postcode":"95124",
    "sg:province":"CA",
    "sg:tags":[
        "nutritionist",
        "therapy",
        "physical"
    ],
    "wof:name":"Ross A. Ali",
    "wof:placetype":"venue"
},
  "geometry": {"coordinates":[-121.931663,37.268076],"type":"Point"}
}