{
  "type": "Feature",
  "properties": {
    "iso:country":"US",
    "sg:address":"1601 Centinela Avenue",
    "sg:city":"Inglewood",
    "sg:classifiers":[
        {
            "category":"Food & Beverages",
            "subcategory":"Groceries & Convenience Stores",
            "type":"Retail Goods"
        }
    ],
    "sg:phone":"+1 310 645 2211",
    "sg:postcode":"90302",
    "sg:province":"CA",
    "wof:name":"AA Mini Mart",
    "wof:placetype":"venue"
},
  "geometry": {"coordinates":[-118.367265,33.976937],"type":"Point"}
}