{
  "type": "Feature",
  "properties": {
    "addr:full":"16221 Construction Cir W Irvine CA 92606",
    "addr:housenumber":"16221",
    "addr:postcode":"92606",
    "addr:street":"Construction Cir W",
    "iso:country":"US",
    "sg:address":"16221 Construction Cir W",
    "sg:city":"Irvine",
    "sg:classifiers":[
        {
            "category":"Professional",
            "type":"Services"
        },
        {
            "category":"Ice Cream",
            "type":"Food & Drink"
        }
    ],
    "sg:phone":"+1 949 939 5318",
    "sg:postcode":"92606",
    "sg:province":"CA",
    "sg:tags":[
        "frozen",
        "yogurt",
        "caterer"
    ],
    "sg:website":"www.konaiceoc.com",
    "wof:name":"Kona Ice Shave Ice of Orange County",
    "wof:placetype":"venue"
},
  "geometry": {"coordinates":[-117.820851,33.695253],"type":"Point"}
}