{
  "type": "Feature",
  "properties": {
    "addr:full":"133 The Crossroads Carmel CA 93923",
    "addr:housenumber":"133",
    "addr:postcode":"93923",
    "addr:street":"The Crossroads",
    "iso:country":"US",
    "sg:address":"133 The Crossroads",
    "sg:city":"Carmel",
    "sg:classifiers":[
        {
            "category":"Restaurant",
            "type":"Food & Drink"
        }
    ],
    "sg:phone":"+1 831 625 3367",
    "sg:postcode":"93923",
    "sg:province":"CA",
    "sg:tags":[
        "chinese"
    ],
    "wof:name":"CROSSROADS SHOPPING VILLAGE THE",
    "wof:placetype":"venue"
},
  "geometry": {"coordinates":[-121.908693,36.538029],"type":"Point"}
}