{
  "type": "Feature",
  "properties": {
    "addr:full":"1730 W 10th St Antioch CA 94509",
    "addr:housenumber":"1730",
    "addr:postcode":"ca 94509",
    "addr:street":"W 10Th St",
    "iso:country":"US",
    "sg:address":"1730 W 10th St",
    "sg:city":"Antioch",
    "sg:classifiers":[
        {
            "category":"Autos & Motor Vehicles",
            "subcategory":"Auto Supplies",
            "type":"Retail Goods"
        }
    ],
    "sg:phone":"+1 925 753 5093",
    "sg:postcode":"94509",
    "sg:province":"CA",
    "sg:tags":[
        "tire"
    ],
    "wof:name":"Discount Tire & Wheel",
    "wof:placetype":"venue"
},
  "geometry": {"coordinates":[-121.828574,38.012568],"type":"Point"}
}