{
  "type": "Feature",
  "properties": {
    "iso:country":"US",
    "sg:address":"3544 W Beverly Blvd",
    "sg:city":"Montebello",
    "sg:classifiers":[
        {
            "category":"Building & Trades",
            "subcategory":"Construction",
            "type":"Services"
        }
    ],
    "sg:phone":"+1 323 728 6400",
    "sg:postcode":"90640",
    "sg:province":"CA",
    "sg:tags":[
        "general",
        "contractor"
    ],
    "wof:name":"Monterey Construction Co",
    "wof:placetype":"venue"
},
  "geometry": {"coordinates":[-118.142185,34.02525],"type":"Point"}
}