{
  "type": "Feature",
  "properties": {
    "addr:full":"22896 Myrtle St Hayward CA 94541",
    "addr:housenumber":"22896",
    "addr:postcode":"94541",
    "addr:street":"Myrtle St",
    "iso:country":"US",
    "sg:address":"22896 Myrtle St",
    "sg:city":"Hayward",
    "sg:classifiers":[
        {
            "category":"Personal",
            "subcategory":"Beauty Salon",
            "type":"Services"
        }
    ],
    "sg:phone":"+1 510 690 9942",
    "sg:postcode":"94541",
    "sg:province":"CA",
    "sg:tags":[
        "manicuring"
    ],
    "wof:name":"Ten Fabulous Nails",
    "wof:placetype":"venue"
},
  "geometry": {"coordinates":[-122.09049899999999,37.66444],"type":"Point"}
}