{
  "type": "Feature",
  "properties": {
    "iso:country":"US",
    "sg:address":"1054 South De Anza Blvd. Suite 202",
    "sg:city":"San Jose",
    "sg:classifiers":[
        {
            "category":"Professional",
            "subcategory":"Computer Services",
            "type":"Services"
        }
    ],
    "sg:phone":"+1 408 777 7930",
    "sg:postcode":"95129",
    "sg:province":"CA",
    "sg:website":"http://www.notifycorp.com/",
    "wof:name":"Notify Technology",
    "wof:placetype":"venue"
},
  "geometry": {"coordinates":[-122.03225999999999,37.30918],"type":"Point"}
}