{
  "type": "Feature",
  "properties": {
    "addr:full":"3742 S Flower St Los Angeles CA 90007",
    "addr:housenumber":"3742",
    "addr:postcode":"90007",
    "addr:street":"S Flower St",
    "iso:country":"US",
    "sg:address":"3742 S Flower St",
    "sg:city":"Los Angeles",
    "sg:classifiers":[
        {
            "category":"Bars & Pubs",
            "subcategory":"Hookah Bar",
            "type":"Food & Drink"
        }
    ],
    "sg:phone":"+1 213 478 0090",
    "sg:postcode":"90007",
    "sg:province":"CA",
    "sg:website":"www.lotusonflower.com",
    "wof:name":"Lotus on Flower",
    "wof:placetype":"venue"
},
  "geometry": {"coordinates":[-118.281603,34.017142],"type":"Point"}
}