{
  "type": "Feature",
  "properties": {
    "iso:country":"US",
    "sg:address":"3808 W Riverside Dr",
    "sg:city":"Burbank",
    "sg:classifiers":[
        {
            "category":"Health Services",
            "subcategory":"Chiropractor",
            "type":"Services"
        }
    ],
    "sg:phone":"+1 818 563 1990",
    "sg:postcode":"91505",
    "sg:province":"CA",
    "wof:name":"Robert E Gibbons DC",
    "wof:placetype":"venue"
},
  "geometry": {"coordinates":[-118.34169799999999,34.152252],"type":"Point"}
}