{
  "type": "Feature",
  "properties": {
    "addr:full":"934 S Andreasen Dr Escondido CA 92029",
    "addr:housenumber":"934",
    "addr:postcode":"92029",
    "addr:street":"S Andreasen Dr",
    "iso:country":"US",
    "sg:address":"934 S Andreasen Dr",
    "sg:city":"Escondido",
    "sg:classifiers":[
        {
            "category":"Professional",
            "type":"Services"
        },
        {
            "category":"Professional",
            "subcategory":"Art Services",
            "type":"Services"
        }
    ],
    "sg:phone":"+1 760 741 0667",
    "sg:postcode":"92029",
    "sg:province":"CA",
    "sg:tags":[
        "photographer"
    ],
    "wof:name":"Level 3 Visual Arts",
    "wof:placetype":"venue"
},
  "geometry": {"coordinates":[-117.115503,33.11282],"type":"Point"}
}