{
  "type": "Feature",
  "properties": {
    "addr:full":"2032 Saint Maru Ln Mckinleyville CA 95519",
    "addr:housenumber":"2032",
    "addr:postcode":"95519",
    "addr:street":"Saint Maru Ln",
    "iso:country":"US",
    "sg:address":"2032 Saint Maru Ln",
    "sg:city":"Mckinleyville",
    "sg:classifiers":[
        {
            "category":"Wholesale",
            "subcategory":"Stationery",
            "type":"Manufacturing & Wholesale Goods"
        }
    ],
    "sg:phone":"+1 707 840 9140",
    "sg:postcode":"95519",
    "sg:province":"CA",
    "sg:tags":[
        "cards",
        "greeting"
    ],
    "wof:name":"Radiance Productions",
    "wof:placetype":"venue"
},
  "geometry": {"coordinates":[-124.095568,40.920797],"type":"Point"}
}