{
  "type": "Feature",
  "properties": {
    "iso:country":"US",
    "sg:address":"7211 Haven Ave",
    "sg:city":"Alta Loma",
    "sg:classifiers":[
        {
            "category":"Food & Beverages",
            "subcategory":"Specialty",
            "type":"Retail Goods"
        }
    ],
    "sg:phone":"+1 909 980 6893",
    "sg:postcode":"91701",
    "sg:province":"CA",
    "sg:tags":[
        "health",
        "diet"
    ],
    "wof:name":"J C Discount Health Food",
    "wof:placetype":"venue"
},
  "geometry": {"coordinates":[-117.575798,34.122279],"type":"Point"}
}