{
  "type": "Feature",
  "properties": {
    "addr:full":"12582 2nd. Street # 78 Yucaipa CA 92399",
    "addr:housenumber":"12582",
    "addr:postcode":"92399",
    "addr:street":"2Nd Street # 78",
    "iso:country":"US",
    "sg:address":"12582 2nd. Street # 78",
    "sg:city":"Yucaipa",
    "sg:classifiers":[
        {
            "category":"Professional",
            "type":"Services"
        }
    ],
    "sg:phone":"+1 909 797 1024",
    "sg:postcode":"92399",
    "sg:province":"CA",
    "sg:tags":[
        "writer"
    ],
    "wof:name":"Writer-Spin",
    "wof:placetype":"venue"
},
  "geometry": {"coordinates":[-117.04321299999999,34.0251],"type":"Point"}
}