{
  "type": "Feature",
  "properties": {
    "iso:country":"US",
    "sg:address":"761 Mabury Rd Ste 65",
    "sg:city":"San Jose",
    "sg:classifiers":[
        {
            "category":"Building & Trades",
            "subcategory":"Cleaning & Sanitation",
            "type":"Services"
        }
    ],
    "sg:phone":"+1 408 573 7912",
    "sg:postcode":"95133",
    "sg:province":"CA",
    "wof:name":"Pino Building Maintenance",
    "wof:placetype":"venue"
},
  "geometry": {"coordinates":[-121.889877,37.363926],"type":"Point"}
}