{
  "type": "Feature",
  "properties": {
    "addr:full":"2673 Suisun Ave San Jose CA 95121",
    "addr:housenumber":"2673",
    "addr:postcode":"95121",
    "addr:street":"Suisun Ave",
    "iso:country":"US",
    "sg:address":"2673 Suisun Ave",
    "sg:city":"San Jose",
    "sg:classifiers":[
        {
            "category":"Personal",
            "subcategory":"Skin Care",
            "type":"Services"
        }
    ],
    "sg:phone":"+1 408 274 6402",
    "sg:postcode":"95121",
    "sg:province":"CA",
    "wof:name":"Care Free Permanent Make-Up",
    "wof:placetype":"venue"
},
  "geometry": {"coordinates":[-121.792,37.308102],"type":"Point"}
}