{
  "type": "Feature",
  "properties": {
    "addr:full":"100 Cross St San Luis Obispo CA 93401",
    "addr:housenumber":"100",
    "addr:postcode":"93401",
    "addr:street":"Cross St",
    "iso:country":"US",
    "sg:address":"100 Cross St",
    "sg:city":"San Luis Obispo",
    "sg:classifiers":[
        {
            "category":"Banks & Credit Unions",
            "subcategory":"Investment Brokerage",
            "type":"Services"
        }
    ],
    "sg:phone":"+1 805 542 9008",
    "sg:postcode":"93401",
    "sg:province":"CA",
    "sg:tags":[
        "security"
    ],
    "wof:name":"UBS Financial Svc",
    "wof:placetype":"venue"
},
  "geometry": {"coordinates":[-120.671131,35.245891],"type":"Point"}
}