{
  "type": "Feature",
  "properties": {
    "addr:full":"6660 Narrowgauge Way Sacramento CA 95823",
    "addr:postcode":"6660;95823",
    "addr:street":"Narrowgauge Way",
    "iso:country":"US",
    "sg:address":"6660 Narrowgauge Way",
    "sg:city":"Sacramento",
    "sg:classifiers":[
        {
            "category":"Shopping",
            "subcategory":"Clothing, Apparel, & Fashions",
            "type":"Retail Goods"
        }
    ],
    "sg:phone":"+1 916 423 3580",
    "sg:postcode":"95823",
    "sg:province":"CA",
    "wof:name":"Lynette Custom Tailoring",
    "wof:placetype":"venue"
},
  "geometry": {"coordinates":[-121.42352099999999,38.460865],"type":"Point"}
}