{
  "type": "Feature",
  "properties": {
    "iso:country":"US",
    "sg:address":"4800 Woodley Ave",
    "sg:city":"Encino",
    "sg:classifiers":[
        {
            "category":"Real Estate",
            "subcategory":"Real Estate Operator",
            "type":"Services"
        }
    ],
    "sg:phone":"+1 818 986 5590",
    "sg:postcode":"91436",
    "sg:province":"CA",
    "sg:tags":[
        "apartment"
    ],
    "wof:name":"Lever Apartments",
    "wof:placetype":"venue"
},
  "geometry": {"coordinates":[-118.483656,34.157579],"type":"Point"}
}