{
  "type": "Feature",
  "properties": {
    "addr:full":"6285 Bernhard Ave Richmond CA 94805",
    "addr:housenumber":"6285",
    "addr:postcode":"94805",
    "addr:street":"Bernhard Ave",
    "iso:country":"US",
    "sg:address":"6285 Bernhard Ave",
    "sg:city":"Richmond",
    "sg:classifiers":[
        {
            "category":"Professional",
            "subcategory":"Engineering",
            "type":"Services"
        }
    ],
    "sg:phone":"+1 510 233 4077",
    "sg:postcode":"94805",
    "sg:province":"CA",
    "sg:tags":[
        "engineer"
    ],
    "wof:name":"Seismic Engineering & Constr",
    "wof:placetype":"venue"
},
  "geometry": {"coordinates":[-122.312433,37.944751],"type":"Point"}
}