{
  "type": "Feature",
  "properties": {
    "addr:full":"26960 Cherry Hills Blvd Ste C Sun City CA 92586",
    "addr:housenumber":"26960",
    "addr:postcode":"92586",
    "addr:street":"Cherry Hills Blvd Ste C",
    "iso:country":"US",
    "sg:address":"26960 Cherry Hills Blvd Ste C",
    "sg:city":"Sun City",
    "sg:classifiers":[
        {
            "category":"Health Services",
            "subcategory":"Doctor",
            "type":"Services"
        }
    ],
    "sg:phone":"+1 951 679 4611",
    "sg:postcode":"92586",
    "sg:province":"CA",
    "wof:name":"Kapelusznik David M.d.",
    "wof:placetype":"venue"
},
  "geometry": {"coordinates":[-117.18901200000001,33.711281],"type":"Point"}
}