{
  "type": "Feature",
  "properties": {
    "iso:country":"US",
    "sg:address":"11130 Kenyon Way",
    "sg:city":"Alta Loma",
    "sg:classifiers":[
        {
            "category":"Professional",
            "subcategory":"Business Services",
            "type":"Services"
        }
    ],
    "sg:phone":"+1 909 941 6461",
    "sg:postcode":"91701",
    "sg:province":"CA",
    "sg:tags":[
        "interior",
        "consultant",
        "design",
        "decorator"
    ],
    "wof:name":"Everything In Its Place",
    "wof:placetype":"venue"
},
  "geometry": {"coordinates":[-117.563819,34.134065],"type":"Point"}
}