{
  "type": "Feature",
  "properties": {
    "addr:full":"1525 Bryant St San Francisco CA 94103",
    "addr:housenumber":"1525",
    "addr:postcode":"94103",
    "addr:street":"Bryant St",
    "iso:country":"US",
    "sg:address":"1525 Bryant St",
    "sg:city":"San Francisco",
    "sg:classifiers":[
        {
            "category":"Wholesale",
            "subcategory":"Groceries",
            "type":"Manufacturing & Wholesale Goods"
        }
    ],
    "sg:phone":"+1 415 552 0950",
    "sg:postcode":"94103",
    "sg:province":"CA",
    "sg:tags":[
        "baker"
    ],
    "wof:name":"Continental Baking Co Inc",
    "wof:placetype":"venue"
},
  "geometry": {"coordinates":[-122.41055799999999,37.767221],"type":"Point"}
}