{
  "type": "Feature",
  "properties": {
    "addr:full":"202 W Lincoln Ave Ste K Orange CA 92865",
    "addr:housenumber":"202",
    "addr:postcode":"92865",
    "addr:street":"W Lincoln Ave Ste K",
    "iso:country":"US",
    "sg:address":"202 W Lincoln Ave Ste K",
    "sg:city":"Orange",
    "sg:classifiers":[
        {
            "category":"Insurance",
            "subcategory":"Hazard Insurance",
            "type":"Services"
        },
        {
            "category":"Insurance",
            "subcategory":"Insurance Agent",
            "type":"Services"
        },
        {
            "category":"Insurance",
            "subcategory":"Life Insurance",
            "type":"Services"
        },
        {
            "category":"Insurance",
            "subcategory":"Title Insurance",
            "type":"Services"
        }
    ],
    "sg:phone":"+1 714 998 3332",
    "sg:postcode":"92865",
    "sg:province":"CA",
    "sg:tags":[
        "auto",
        "commercial",
        "business",
        "homeowner"
    ],
    "sg:website":"http://www.farmersagent.com/fbigner/",
    "wof:name":"Fred Bigner Insurance Agency Inc - Farmers Insurance",
    "wof:placetype":"venue"
},
  "geometry": {"coordinates":[-117.85383899999999,33.835462],"type":"Point"}
}