{
  "type": "Feature",
  "properties": {
    "addr:full":"5811 S Denker Avenue Los Angeles CA 90047",
    "addr:housenumber":"5811",
    "addr:postcode":"90047",
    "addr:street":"S Denker Avenue",
    "iso:country":"US",
    "sg:address":"5811 S Denker Avenue",
    "sg:city":"Los Angeles",
    "sg:classifiers":[
        {
            "category":"Retail",
            "subcategory":"Auto Repair",
            "type":"Services"
        }
    ],
    "sg:phone":"+1 310 693 0223",
    "sg:postcode":"90047",
    "sg:province":"CA",
    "sg:website":"www.mels-auto.com",
    "wof:name":"Mels Auto Repair",
    "wof:placetype":"venue"
},
  "geometry": {"coordinates":[-118.30443099999999,33.987812],"type":"Point"}
}