{
  "type": "Feature",
  "properties": {
    "addr:full":"1221 Gravenstein Hwy S Sebastopol CA 95472",
    "addr:housenumber":"1221",
    "addr:postcode":"95472",
    "addr:street":"Gravenstein Hwy S",
    "iso:country":"US",
    "sg:address":"1221 Gravenstein Hwy S",
    "sg:city":"Sebastopol",
    "sg:classifiers":[
        {
            "category":"Manufacturing",
            "subcategory":"Signs",
            "type":"Manufacturing & Wholesale Goods"
        }
    ],
    "sg:phone":"+1 707 824 1845",
    "sg:postcode":"95472",
    "sg:province":"CA",
    "sg:tags":[
        "specialty",
        "mfg"
    ],
    "wof:name":"Ron Blair Signs",
    "wof:placetype":"venue"
},
  "geometry": {"coordinates":[-122.813734,38.387784],"type":"Point"}
}