{
  "type": "Feature",
  "properties": {
    "addr:full":"25906 Newport Rd Menifee CA 92584",
    "addr:housenumber":"25906",
    "addr:postcode":"92584",
    "addr:street":"Newport Rd",
    "iso:country":"US",
    "sg:address":"25906 Newport Rd",
    "sg:city":"Menifee",
    "sg:classifiers":[
        {
            "category":"Wholesale",
            "subcategory":"Medical Equipment & Supplies",
            "type":"Manufacturing & Wholesale Goods"
        },
        {
            "category":"Shopping",
            "subcategory":"Beauty & Cosmetics",
            "type":"Retail Goods"
        },
        {
            "category":"Food & Beverages",
            "subcategory":"Specialty",
            "type":"Retail Goods"
        },
        {
            "category":"Retail",
            "subcategory":"Portrait Studio",
            "type":"Services"
        },
        {
            "category":"Shopping",
            "subcategory":"Gifts & Souvenirs",
            "type":"Retail Goods"
        },
        {
            "category":"Retail",
            "subcategory":"Photofinishing",
            "type":"Services"
        },
        {
            "category":"Shopping",
            "subcategory":"Pharmacy",
            "type":"Retail Goods"
        }
    ],
    "sg:phone":"+1 951 679 5199",
    "sg:postcode":"92584",
    "sg:province":"CA",
    "sg:tags":[
        "product",
        "photo",
        "photography",
        "vitamin",
        "greeting",
        "supplement",
        "health",
        "card",
        "wellness",
        "aid",
        "finishing",
        "perfume",
        "drugstore",
        "store",
        "first"
    ],
    "sg:website":"http://www.riteaid.com",
    "wof:name":"Rite Aid",
    "wof:placetype":"venue"
},
  "geometry": {"coordinates":[-117.208,33.684799],"type":"Point"}
}