{
  "type": "Feature",
  "properties": {
    "addr:full":"17064 McGuffie Rd Salinas CA 93907",
    "addr:postcode":"17064;93907",
    "addr:street":"Mcguffie Rd",
    "iso:country":"US",
    "sg:address":"17064 McGuffie Rd",
    "sg:city":"Salinas",
    "sg:classifiers":[
        {
            "category":"Building & Trades",
            "subcategory":"Cleaning & Sanitation",
            "type":"Services"
        }
    ],
    "sg:phone":"+1 831 663 4611",
    "sg:postcode":"93907",
    "sg:province":"CA",
    "sg:tags":[
        "maintenance"
    ],
    "wof:name":"Equipment Maintenance Svcs Inc",
    "wof:placetype":"venue"
},
  "geometry": {"coordinates":[-121.67929100000001,36.792483],"type":"Point"}
}