{
  "type": "Feature",
  "properties": {
    "iso:country":"US",
    "sg:address":"3496 Louis Dr",
    "sg:city":"Newbury Park",
    "sg:classifiers":[
        {
            "category":"Health Services",
            "subcategory":"Medical Lab",
            "type":"Services"
        }
    ],
    "sg:phone":"+1 805 499 9797",
    "sg:postcode":"91320",
    "sg:province":"CA",
    "sg:tags":[
        "laboratory"
    ],
    "wof:name":"Ortho Tech",
    "wof:placetype":"venue"
},
  "geometry": {"coordinates":[-118.947663,34.184292],"type":"Point"}
}