{
  "type": "Feature",
  "properties": {
    "iso:country":"US",
    "sg:address":"2044 Bryant St",
    "sg:city":"San Francisco",
    "sg:classifiers":[
        {
            "category":"Manufacturing",
            "subcategory":"Tools & Machinery",
            "type":"Manufacturing & Wholesale Goods"
        }
    ],
    "sg:phone":"+1 415 695 9117",
    "sg:postcode":"94110",
    "sg:province":"CA",
    "sg:tags":[
        "machine",
        "shop"
    ],
    "wof:name":"Production Specialties",
    "wof:placetype":"venue"
},
  "geometry": {"coordinates":[-122.410115,37.761051],"type":"Point"}
}