{
  "type": "Feature",
  "properties": {
    "addr:full":"2829 Shattuck Avenue Berkeley CA 94705",
    "addr:housenumber":"2829",
    "addr:postcode":"94705",
    "addr:street":"Shattuck Avenue",
    "iso:country":"US",
    "sg:address":"2829 Shattuck Avenue",
    "sg:city":"Berkeley",
    "sg:classifiers":[
        {
            "category":"Social Services",
            "subcategory":"Job Training",
            "type":"Services"
        },
        {
            "category":"Social Services",
            "subcategory":"Retirement Home",
            "type":"Services"
        },
        {
            "category":"Health Services",
            "subcategory":"Hospital",
            "type":"Services"
        }
    ],
    "sg:phone":"+1 510 665 2800",
    "sg:postcode":"94705",
    "sg:province":"CA",
    "sg:tags":[
        "living",
        "nursing",
        "homes-skilled",
        "facility",
        "assisted",
        "convalescent"
    ],
    "wof:name":"Elmwood Care Center",
    "wof:placetype":"venue"
},
  "geometry": {"coordinates":[-122.266998,37.8573],"type":"Point"}
}