{
  "type": "Feature",
  "properties": {
    "addr:full":"25186 Miles Ave Lake Forest CA 92630",
    "addr:housenumber":"25186",
    "addr:postcode":"92630",
    "addr:street":"Miles Ave",
    "iso:country":"US",
    "sg:address":"25186 Miles Ave",
    "sg:city":"Lake Forest",
    "sg:classifiers":[
        {
            "category":"Real Estate",
            "subcategory":"Real Estate Agent",
            "type":"Services"
        }
    ],
    "sg:phone":"+1 949 230 3836",
    "sg:postcode":"92630",
    "sg:province":"CA",
    "sg:tags":[
        "management"
    ],
    "wof:name":"South Coast Investment Svc",
    "wof:placetype":"venue"
},
  "geometry": {"coordinates":[-117.6905,33.63117],"type":"Point"}
}