{
  "type": "Feature",
  "properties": {
    "iso:country":"US",
    "sg:address":"2727 Kurtz St",
    "sg:city":"San Diego",
    "sg:classifiers":[
        {
            "category":"Professional",
            "type":"Services"
        }
    ],
    "sg:phone":"+1 619 291 4211",
    "sg:postcode":"92110",
    "sg:province":"CA",
    "sg:tags":[
        "establishment"
    ],
    "wof:name":"Deltec",
    "wof:placetype":"venue"
},
  "geometry": {"coordinates":[-117.200614,32.750174],"type":"Point"}
}