{
  "type": "Feature",
  "properties": {
    "addr:full":"1153 Rancho Dr Ojai CA 93023",
    "addr:housenumber":"1153",
    "addr:postcode":"93023",
    "addr:street":"Rancho Dr",
    "iso:country":"US",
    "sg:address":"1153 Rancho Dr",
    "sg:city":"Ojai",
    "sg:classifiers":[
        {
            "category":"Professional",
            "type":"Services"
        }
    ],
    "sg:phone":"+1 805 646 3312",
    "sg:postcode":"93023",
    "sg:province":"CA",
    "wof:name":"Family Schreiner",
    "wof:placetype":"venue"
},
  "geometry": {"coordinates":[-119.268631,34.450856],"type":"Point"}
}