{
  "type": "Feature",
  "properties": {
    "iso:country":"US",
    "sg:address":"27588 Sierra Hwy",
    "sg:city":"Santa Clarita",
    "sg:classifiers":[
        {
            "category":"Food & Beverages",
            "subcategory":"Groceries & Convenience Stores",
            "type":"Retail Goods"
        }
    ],
    "sg:phone":"+1 661 298 1510",
    "sg:postcode":"91351",
    "sg:province":"CA",
    "sg:website":"7-eleven.com",
    "wof:name":"7 Eleven",
    "wof:placetype":"venue"
},
  "geometry": {"coordinates":[-118.455798,34.416326],"type":"Point"}
}