{
  "type": "Feature",
  "properties": {
    "addr:full":"6104 Banner Ct San Jose CA 95123",
    "addr:housenumber":"6104",
    "addr:postcode":"95123",
    "addr:street":"Banner Ct",
    "iso:country":"US",
    "sg:address":"6104 Banner Ct",
    "sg:city":"San Jose",
    "sg:classifiers":[
        {
            "category":"Building & Trades",
            "subcategory":"Construction",
            "type":"Services"
        }
    ],
    "sg:phone":"+1 408 227 3896",
    "sg:postcode":"95123",
    "sg:province":"CA",
    "sg:tags":[
        "contractor"
    ],
    "wof:name":"Francisco Tile",
    "wof:placetype":"venue"
},
  "geometry": {"coordinates":[-121.82307,37.236718],"type":"Point"}
}