{
  "type": "Feature",
  "properties": {
    "addr:full":"901 Battery St San Francisco CA 94111",
    "addr:housenumber":"901",
    "addr:postcode":"94111",
    "addr:street":"Battery St",
    "iso:country":"US",
    "sg:address":"901 Battery St",
    "sg:city":"San Francisco",
    "sg:classifiers":[
        {
            "category":"Real Estate",
            "subcategory":"Real Estate Agent",
            "type":"Services"
        }
    ],
    "sg:phone":"+1 415 362 5372",
    "sg:postcode":"94111",
    "sg:province":"CA",
    "sg:tags":[
        "management"
    ],
    "wof:name":"Gordon Group",
    "wof:placetype":"venue"
},
  "geometry": {"coordinates":[-122.401428,37.800459],"type":"Point"}
}