{
  "type": "Feature",
  "properties": {
    "addr:full":"4374 Eagle Rock Blvd Los Angeles CA 90041",
    "addr:housenumber":"4374",
    "addr:postcode":"90041",
    "addr:street":"Eagle Rock Blvd",
    "iso:country":"US",
    "sg:address":"4374 Eagle Rock Blvd",
    "sg:city":"Los Angeles",
    "sg:classifiers":[
        {
            "category":"Retail",
            "subcategory":"Animal Services",
            "type":"Services"
        }
    ],
    "sg:phone":"+1 323 255 5714",
    "sg:postcode":"90041",
    "sg:province":"CA",
    "sg:tags":[
        "pet",
        "grooming",
        "washing",
        "store"
    ],
    "wof:name":"Hal's Eagle Rock Pet Shop",
    "wof:placetype":"venue"
},
  "geometry": {"coordinates":[-118.220962,34.12365],"type":"Point"}
}