{
  "type": "Feature",
  "properties": {
    "addr:full":"1277 Prospect St La Jolla CA 92037",
    "addr:housenumber":"1277",
    "addr:postcode":"92037",
    "addr:street":"Prospect St",
    "iso:country":"US",
    "sg:address":"1277 Prospect St",
    "sg:city":"La Jolla",
    "sg:classifiers":[
        {
            "category":"Restaurant",
            "type":"Food & Drink"
        }
    ],
    "sg:phone":"+1 858 456 7118",
    "sg:postcode":"92037",
    "sg:province":"CA",
    "sg:tags":[
        "sushi",
        "bar",
        "japanese"
    ],
    "sg:website":"www.tadashisushi.signonsandiego....",
    "wof:name":"Tadashi Sushi",
    "wof:placetype":"venue"
},
  "geometry": {"coordinates":[-117.271004,32.8489],"type":"Point"}
}