{
  "type": "Feature",
  "properties": {
    "iso:country":"US",
    "sg:address":"2323 Fairfield Ave",
    "sg:city":"Fairfield",
    "sg:classifiers":[
        {
            "category":"Personal",
            "subcategory":"Beauty Salon",
            "type":"Services"
        }
    ],
    "sg:phone":"+1 707 720 5042",
    "sg:postcode":"94533",
    "sg:province":"CA",
    "wof:name":"Braids By Toya",
    "wof:placetype":"venue"
},
  "geometry": {"coordinates":[-122.045328,38.271667],"type":"Point"}
}