{
  "type": "Feature",
  "properties": {
    "addr:full":"14411 Norwalk Ln Poway CA 92064",
    "addr:housenumber":"14411",
    "addr:postcode":"ca 92064",
    "addr:street":"Norwalk Ln",
    "iso:country":"US",
    "sg:address":"14411 Norwalk Ln",
    "sg:city":"Poway",
    "sg:classifiers":[
        {
            "category":"Social Services",
            "subcategory":"Child Care",
            "type":"Services"
        }
    ],
    "sg:phone":"+1 858 486 4420",
    "sg:postcode":"92064",
    "sg:province":"CA",
    "sg:tags":[
        "kindergarten",
        "academic",
        "school"
    ],
    "sg:website":"www.powaycountrypreschool.com",
    "wof:name":"Poway Country Preschool",
    "wof:placetype":"venue"
},
  "geometry": {"coordinates":[-117.03949799999999,32.975444],"type":"Point"}
}