{
  "type": "Feature",
  "properties": {
    "addr:full":"8323 Baldwin St Oakland CA 94621",
    "addr:housenumber":"8323",
    "addr:postcode":"94621",
    "addr:street":"Baldwin St",
    "iso:country":"US",
    "sg:address":"8323 Baldwin St",
    "sg:city":"Oakland",
    "sg:classifiers":[
        {
            "category":"Organizations",
            "subcategory":"Membership Organization",
            "type":"Services"
        }
    ],
    "sg:phone":"+1 510 569 0702",
    "sg:postcode":"94621",
    "sg:province":"CA",
    "sg:tags":[
        "society",
        "humane"
    ],
    "sg:website":"www.oaklandspca.org",
    "wof:name":"Oakland SPCA-Facility",
    "wof:placetype":"venue"
},
  "geometry": {"coordinates":[-122.19450000000001,37.747014],"type":"Point"}
}