{
  "type": "Feature",
  "properties": {
    "iso:country":"US",
    "sg:address":"601 E Glenoaks Blvd",
    "sg:city":"Glendale",
    "sg:classifiers":[
        {
            "category":"Professional",
            "subcategory":"Engineering",
            "type":"Services"
        },
        {
            "category":"Real Estate",
            "subcategory":"Surveying",
            "type":"Services"
        }
    ],
    "sg:phone":"+1 949 548 6888",
    "sg:postcode":"91207",
    "sg:province":"CA",
    "sg:tags":[
        "civil",
        "surveyor",
        "land",
        "engineer"
    ],
    "wof:name":"Hennon Surveying & Mapping Inc",
    "wof:placetype":"venue"
},
  "geometry": {"coordinates":[-118.249062,34.15831],"type":"Point"}
}