{
  "type": "Feature",
  "properties": {
    "iso:country":"US",
    "sg:address":"9922 Inwood Rd",
    "sg:city":"Folsom",
    "sg:classifiers":[
        {
            "category":"Building & Trades",
            "subcategory":"Pest Control",
            "type":"Services"
        }
    ],
    "sg:phone":"+1 916 988 5879",
    "sg:postcode":"95630",
    "sg:province":"CA",
    "wof:name":"River Rat Pest Control",
    "wof:placetype":"venue"
},
  "geometry": {"coordinates":[-121.173905,38.700955],"type":"Point"}
}