{
  "type": "Feature",
  "properties": {
    "addr:full":"1515 Folsom Ave San Pablo CA 94806",
    "addr:housenumber":"1515",
    "addr:postcode":"94806",
    "addr:street":"Folsom Ave",
    "iso:country":"US",
    "sg:address":"1515 Folsom Ave",
    "sg:city":"San Pablo",
    "sg:classifiers":[
        {
            "category":"Government",
            "subcategory":"Office",
            "type":"Public Place"
        }
    ],
    "sg:phone":"+1 510 215 3077",
    "sg:postcode":"94806",
    "sg:province":"CA",
    "sg:tags":[
        "village"
    ],
    "wof:name":"San Pablo Community Developmnt",
    "wof:placetype":"venue"
},
  "geometry": {"coordinates":[-122.354041,37.961268],"type":"Point"}
}