{
  "type": "Feature",
  "properties": {
    "iso:country":"US",
    "sg:address":"134 Oxford",
    "sg:city":"Irvine",
    "sg:classifiers":[
        {
            "category":"Wholesale",
            "subcategory":"Apparel",
            "type":"Manufacturing & Wholesale Goods"
        }
    ],
    "sg:phone":"+1 949 823 0020",
    "sg:postcode":"92612",
    "sg:province":"CA",
    "sg:tags":[
        "clothing"
    ],
    "wof:name":"Franco Shade",
    "wof:placetype":"venue"
},
  "geometry": {"coordinates":[-117.826797,33.651668],"type":"Point"}
}