{
  "type": "Feature",
  "properties": {
    "iso:country":"US",
    "sg:address":"6812 6th Ave",
    "sg:city":"Rio Linda",
    "sg:classifiers":[
        {
            "category":"Retail",
            "subcategory":"Auto Repair",
            "type":"Services"
        }
    ],
    "sg:phone":"+1 916 335 0788",
    "sg:postcode":"95673",
    "sg:province":"CA",
    "sg:tags":[
        "repairing",
        "automobile"
    ],
    "wof:name":"Thompson's Auto Repair",
    "wof:placetype":"venue"
},
  "geometry": {"coordinates":[-121.451008,38.692704],"type":"Point"}
}