{
  "type": "Feature",
  "properties": {
    "addr:full":"605 W Murray Ave Visalia CA 93291",
    "addr:housenumber":"605",
    "addr:postcode":"93291",
    "addr:street":"W Murray Ave",
    "iso:country":"US",
    "sg:address":"605 W Murray Ave",
    "sg:city":"Visalia",
    "sg:classifiers":[
        {
            "category":"Shopping",
            "type":"Retail Goods"
        }
    ],
    "sg:phone":"+1 559 667 4353",
    "sg:postcode":"93291",
    "sg:province":"CA",
    "sg:tags":[
        "merchandise"
    ],
    "wof:name":"The Mega Depot",
    "wof:placetype":"venue"
},
  "geometry": {"coordinates":[-119.297813,36.33374],"type":"Point"}
}