{
  "type": "Feature",
  "properties": {
    "addr:full":"216 S Hartson St Napa CA 94559",
    "addr:housenumber":"216",
    "addr:postcode":"94559",
    "addr:street":"S Hartson St",
    "iso:country":"US",
    "sg:address":"216 S Hartson St",
    "sg:city":"Napa",
    "sg:classifiers":[
        {
            "category":"Retail",
            "subcategory":"Repair Shop",
            "type":"Services"
        }
    ],
    "sg:phone":"+1 707 225 2807",
    "sg:postcode":"94559",
    "sg:province":"CA",
    "sg:tags":[
        "lock",
        "locksmith"
    ],
    "wof:name":"GEN Enterprise",
    "wof:placetype":"venue"
},
  "geometry": {"coordinates":[-122.295153,38.284985],"type":"Point"}
}