{
  "type": "Feature",
  "properties": {
    "iso:country":"US",
    "sg:address":"7821 Burnet Ave",
    "sg:city":"Van Nuys",
    "sg:classifiers":[
        {
            "category":"Building & Trades",
            "subcategory":"Electrical",
            "type":"Services"
        }
    ],
    "sg:phone":"+1 818 781 2340",
    "sg:postcode":"91405",
    "sg:province":"CA",
    "sg:tags":[
        "telecommunication",
        "contractor"
    ],
    "wof:name":"Smart Connect",
    "wof:placetype":"venue"
},
  "geometry": {"coordinates":[-118.463002,34.213585],"type":"Point"}
}