{
  "type": "Feature",
  "properties": {
    "iso:country":"US",
    "sg:address":"901 Euclid Ave",
    "sg:city":"Beaumont",
    "sg:classifiers":[
        {
            "category":"Organizations",
            "subcategory":"Religious Organization",
            "type":"Services"
        }
    ],
    "sg:phone":"+1 951 845 4317",
    "sg:postcode":"92223",
    "sg:province":"CA",
    "wof:name":"First Baptist Church",
    "wof:placetype":"venue"
},
  "geometry": {"coordinates":[-116.978996,33.934299],"type":"Point"}
}