{
  "type": "Feature",
  "properties": {
    "iso:country":"US",
    "sg:address":"1137 Strawberry Ln",
    "sg:city":"Glendora",
    "sg:classifiers":[
        {
            "category":"Building & Trades",
            "subcategory":"Cleaning & Sanitation",
            "type":"Services"
        }
    ],
    "sg:phone":"+1 626 339 0934",
    "sg:postcode":"91740",
    "sg:province":"CA",
    "sg:tags":[
        "janitor"
    ],
    "sg:website":"www.jjjanitorial.com",
    "wof:name":"J & J Janitorial Svc",
    "wof:placetype":"venue"
},
  "geometry": {"coordinates":[-117.840568,34.107417],"type":"Point"}
}