{
  "type": "Feature",
  "properties": {
    "addr:full":"7760 Monterey St Gilroy CA 95020",
    "addr:housenumber":"7760",
    "addr:postcode":"95020",
    "addr:street":"Monterey St",
    "iso:country":"US",
    "sg:address":"7760 Monterey St",
    "sg:city":"Gilroy",
    "sg:classifiers":[
        {
            "category":"Restaurant",
            "type":"Food & Drink"
        }
    ],
    "sg:phone":"+1 408 842 8611",
    "sg:postcode":"95020",
    "sg:province":"CA",
    "wof:name":"Great China Garden",
    "wof:placetype":"venue"
},
  "geometry": {"coordinates":[-121.570953,37.011873],"type":"Point"}
}