{
  "type": "Feature",
  "properties": {
    "iso:country":"US",
    "sg:address":"225 Walk Cir",
    "sg:city":"Santa Cruz",
    "sg:classifiers":[
        {
            "category":"Manufacturing",
            "subcategory":"Lumber",
            "type":"Manufacturing & Wholesale Goods"
        }
    ],
    "sg:phone":"+1 831 466 9169",
    "sg:postcode":"95060",
    "sg:province":"CA",
    "sg:tags":[
        "company",
        "logging"
    ],
    "sg:website":"www.drafthorsesforhire.com",
    "wof:name":"Draft Horses For Hire",
    "wof:placetype":"venue"
},
  "geometry": {"coordinates":[-122.036833,36.960671],"type":"Point"}
}