{
  "type": "Feature",
  "properties": {
    "iso:country":"US",
    "sg:address":"24334 Rockfield Boulevard",
    "sg:city":"Lake Forest",
    "sg:classifiers":[
        {
            "category":"Shopping",
            "subcategory":"Crafts & Fabrics",
            "type":"Retail Goods"
        }
    ],
    "sg:phone":"+1 949 855 4871",
    "sg:postcode":"92630",
    "sg:province":"CA",
    "sg:tags":[
        "store"
    ],
    "wof:name":"Home Fabrics",
    "wof:placetype":"venue"
},
  "geometry": {"coordinates":[-117.704308,33.616237],"type":"Point"}
}