{
  "type": "Feature",
  "properties": {
    "iso:country":"US",
    "sg:address":"3292 E Westfall Rd",
    "sg:city":"Mariposa",
    "sg:classifiers":[
        {
            "category":"Personal",
            "subcategory":"Beauty Salon",
            "type":"Services"
        }
    ],
    "sg:phone":"+1 209 742 7077",
    "sg:postcode":"95338",
    "sg:province":"CA",
    "wof:name":"Triangle Family Hair Care",
    "wof:placetype":"venue"
},
  "geometry": {"coordinates":[-119.809998,37.500674],"type":"Point"}
}