{
  "type": "Feature",
  "properties": {
    "addr:full":"250 Commerce Irvine CA 92602",
    "addr:housenumber":"250",
    "addr:postcode":"92602",
    "addr:street":"Commerce",
    "iso:country":"US",
    "sg:address":"250 Commerce",
    "sg:city":"Irvine",
    "sg:classifiers":[
        {
            "category":"Banks & Credit Unions",
            "subcategory":"Financial Services",
            "type":"Services"
        }
    ],
    "sg:phone":"+1 949 453 0113",
    "sg:postcode":"92602",
    "sg:province":"CA",
    "sg:tags":[
        "broker",
        "mortgage"
    ],
    "sg:website":"www.centexhomes.com",
    "wof:name":"Centex Homes",
    "wof:placetype":"venue"
},
  "geometry": {"coordinates":[-117.77631599999999,33.727149],"type":"Point"}
}