{
  "type": "Feature",
  "properties": {
    "iso:country":"US",
    "sg:address":"23 Grant Ave",
    "sg:city":"San Francisco",
    "sg:classifiers":[
        {
            "category":"Professional",
            "type":"Services"
        }
    ],
    "sg:phone":"+1 415 901 2450",
    "sg:postcode":"94108",
    "sg:province":"CA",
    "sg:tags":[
        "establishment"
    ],
    "wof:name":"Gomingle Com",
    "wof:placetype":"venue"
},
  "geometry": {"coordinates":[-122.404994,37.787082],"type":"Point"}
}