{
  "type": "Feature",
  "properties": {
    "iso:country":"US",
    "sg:address":"4429 Lindsey Ave",
    "sg:city":"Pico Rivera",
    "sg:classifiers":[
        {
            "category":"Professional",
            "type":"Services"
        }
    ],
    "sg:phone":"+1 562 699 5247",
    "sg:postcode":"90660",
    "sg:province":"CA",
    "wof:name":"Desiree Garnica",
    "wof:placetype":"venue"
},
  "geometry": {"coordinates":[-118.07942300000001,34.006794],"type":"Point"}
}