{
  "type": "Feature",
  "properties": {
    "iso:country":"US",
    "sg:address":"353 Dominguez Way",
    "sg:city":"El Cajon",
    "sg:classifiers":[
        {
            "category":"Real Estate",
            "subcategory":"Real Estate Operator",
            "type":"Services"
        }
    ],
    "sg:phone":"+1 858 751 6330",
    "sg:postcode":"92021",
    "sg:province":"CA",
    "sg:tags":[
        "apartment"
    ],
    "wof:name":"Lamp Lighter & Continental",
    "wof:placetype":"venue"
},
  "geometry": {"coordinates":[-116.949964,32.800026],"type":"Point"}
}