{
  "type": "Feature",
  "properties": {
    "iso:country":"US",
    "sg:address":"5474 Moreno St",
    "sg:city":"Montclair",
    "sg:classifiers":[
        {
            "category":"Restaurant",
            "type":"Food & Drink"
        }
    ],
    "sg:phone":"+1 909 985 0399",
    "sg:postcode":"91763",
    "sg:province":"CA",
    "wof:name":"Stop & Eat",
    "wof:placetype":"venue"
},
  "geometry": {"coordinates":[-117.683447,34.088815],"type":"Point"}
}