{
  "type": "Feature",
  "properties": {
    "addr:full":"666 W Ave I Lancaster CA 93534",
    "addr:housenumber":"666",
    "addr:postcode":"93534",
    "addr:street":"W Ave I",
    "iso:country":"US",
    "sg:address":"666 W Ave I",
    "sg:city":"Lancaster",
    "sg:classifiers":[
        {
            "category":"Farming",
            "subcategory":"Vineyard",
            "type":"Manufacturing & Wholesale Goods"
        }
    ],
    "sg:phone":"+1 661 942 6113",
    "sg:postcode":"93534",
    "sg:province":"CA",
    "sg:tags":[
        "grape"
    ],
    "wof:name":"Cameo Vineyards",
    "wof:placetype":"venue"
},
  "geometry": {"coordinates":[-118.142353,34.703939],"type":"Point"}
}