{
  "type": "Feature",
  "properties": {
    "iso:country":"US",
    "sg:address":"20220 Spence Rd",
    "sg:city":"Salinas",
    "sg:classifiers":[
        {
            "category":"Farming",
            "subcategory":"Nursery",
            "type":"Manufacturing & Wholesale Goods"
        }
    ],
    "sg:phone":"+1 831 422 3784",
    "sg:postcode":"93908",
    "sg:province":"CA",
    "wof:name":"Utos Greenhouse Inc",
    "wof:placetype":"venue"
},
  "geometry": {"coordinates":[-121.542182,36.628279],"type":"Point"}
}