{
  "type": "Feature",
  "properties": {
    "iso:country":"US",
    "sg:address":"431 W Riverside Dr",
    "sg:city":"Burbank",
    "sg:classifiers":[
        {
            "category":"Freight",
            "type":"Transportation"
        }
    ],
    "sg:phone":"+1 818 989 9953",
    "sg:postcode":"91506",
    "sg:province":"CA",
    "sg:tags":[
        "operator",
        "trucking"
    ],
    "wof:name":"C & M Relocations Services",
    "wof:placetype":"venue"
},
  "geometry": {"coordinates":[-118.309474,34.161556],"type":"Point"}
}