{
  "type": "Feature",
  "properties": {
    "iso:country":"US",
    "sg:address":"1905 S Ola Vis",
    "sg:city":"San Clemente",
    "sg:classifiers":[
        {
            "category":"Professional",
            "type":"Services"
        }
    ],
    "sg:phone":"+1 949 498 8476",
    "sg:postcode":"92672",
    "sg:province":"CA",
    "wof:name":"Spyros",
    "wof:placetype":"venue"
},
  "geometry": {"coordinates":[-117.6063,33.41277],"type":"Point"}
}