{
  "type": "Feature",
  "properties": {
    "iso:country":"US",
    "sg:address":"3413 Douglas Ct",
    "sg:city":"San Mateo",
    "sg:classifiers":[
        {
            "category":"Shopping",
            "subcategory":"Computers & Home Electronics",
            "type":"Retail Goods"
        }
    ],
    "sg:phone":"+1 650 312 9160",
    "sg:postcode":"94403",
    "sg:province":"CA",
    "sg:tags":[
        "equipment",
        "electronic",
        "supply"
    ],
    "wof:name":"Carrol's TV",
    "wof:placetype":"venue"
},
  "geometry": {"coordinates":[-122.325157,37.52435],"type":"Point"}
}