{
  "type": "Feature",
  "properties": {
    "addr:full":"7281 Westminster Boulevard Westminster CA 92683",
    "addr:housenumber":"7281",
    "addr:postcode":"92683",
    "addr:street":"Westminster Boulevard",
    "iso:country":"US",
    "sg:address":"7281 Westminster Boulevard",
    "sg:city":"Westminster",
    "sg:classifiers":[
        {
            "category":"Retail",
            "subcategory":"Auto Repair",
            "type":"Services"
        }
    ],
    "sg:phone":"+1 714 891 1113",
    "sg:postcode":"92683",
    "sg:province":"CA",
    "sg:website":"www.markdibella.com/",
    "wof:name":"MD Automotive",
    "wof:placetype":"venue"
},
  "geometry": {"coordinates":[-118.001791,33.759249],"type":"Point"}
}