{
  "type": "Feature",
  "properties": {
    "addr:full":"796 34th Ave San Francisco CA 94121",
    "addr:housenumber":"796",
    "addr:postcode":"94121",
    "addr:street":"34Th Ave",
    "iso:country":"US",
    "sg:address":"796 34th Ave",
    "sg:city":"San Francisco",
    "sg:classifiers":[
        {
            "category":"Building & Trades",
            "subcategory":"Construction",
            "type":"Services"
        }
    ],
    "sg:phone":"+1 415 386 0393",
    "sg:postcode":"94121",
    "sg:province":"CA",
    "sg:tags":[
        "nonresidential"
    ],
    "wof:name":"All City Construction Co",
    "wof:placetype":"venue"
},
  "geometry": {"coordinates":[-122.493998,37.775828],"type":"Point"}
}