{
  "type": "Feature",
  "properties": {
    "addr:full":"6736 Corbin Ave Reseda CA 91337",
    "addr:housenumber":"6736",
    "addr:postcode":"91337",
    "addr:street":"Corbin Ave",
    "iso:country":"US",
    "sg:address":"6736 Corbin Ave",
    "sg:city":"Reseda",
    "sg:classifiers":[
        {
            "category":"Restaurant",
            "type":"Food & Drink"
        }
    ],
    "sg:phone":"+1 818 342 8710",
    "sg:postcode":"91337",
    "sg:province":"CA",
    "sg:tags":[
        "middle",
        "turkish",
        "mediterranean",
        "eastern"
    ],
    "sg:website":"www.sakosmediterraneancuisine.com",
    "wof:name":"Sako's Mediterranean Cuisine",
    "wof:placetype":"venue"
},
  "geometry": {"coordinates":[-118.562241,34.193118],"type":"Point"}
}