{
  "type": "Feature",
  "properties": {
    "iso:country":"US",
    "sg:address":"1611 N St",
    "sg:city":"Firebaugh",
    "sg:classifiers":[
        {
            "category":"Food & Beverages",
            "subcategory":"Groceries & Convenience Stores",
            "type":"Retail Goods"
        }
    ],
    "sg:phone":"+1 559 659 3231",
    "sg:postcode":"93622",
    "sg:province":"CA",
    "sg:tags":[
        "market"
    ],
    "wof:name":"Fiesta Latino Market",
    "wof:placetype":"venue"
},
  "geometry": {"coordinates":[-120.452159,36.852981],"type":"Point"}
}