{
  "type": "Feature",
  "properties": {
    "iso:country":"US",
    "sg:address":"27910 Lakes Edge Rd",
    "sg:city":"Lake Arrowhead",
    "sg:classifiers":[
        {
            "category":"Professional",
            "type":"Services"
        }
    ],
    "sg:phone":"+1 909 337 2894",
    "sg:postcode":"92407",
    "sg:province":"CA",
    "sg:tags":[
        "establishment"
    ],
    "wof:name":"Arrowhead Lake",
    "wof:placetype":"venue"
},
  "geometry": {"coordinates":[-117.192136,34.250627],"type":"Point"}
}