{
  "type": "Feature",
  "properties": {
    "addr:full":"1970 Inglis Way Roseville CA 95678",
    "addr:housenumber":"1970",
    "addr:postcode":"95678",
    "addr:street":"Inglis Way",
    "iso:country":"US",
    "sg:address":"1970 Inglis Way",
    "sg:city":"Roseville",
    "sg:classifiers":[
        {
            "category":"Building & Trades",
            "subcategory":"Construction",
            "type":"Services"
        }
    ],
    "sg:phone":"+1 916 773 0790",
    "sg:postcode":"95678",
    "sg:province":"CA",
    "sg:tags":[
        "altering",
        "remodeling",
        "contractor"
    ],
    "wof:name":"Mgm Handy Works & Remodeling",
    "wof:placetype":"venue"
},
  "geometry": {"coordinates":[-121.29773400000001,38.732397],"type":"Point"}
}