{
  "type": "Feature",
  "properties": {
    "addr:full":"1549 Polk Street San Francisco CA 94109",
    "addr:housenumber":"1549",
    "addr:postcode":"94109",
    "addr:street":"Polk Street",
    "iso:country":"US",
    "sg:address":"1549 Polk Street",
    "sg:city":"San Francisco",
    "sg:classifiers":[
        {
            "category":"Donuts",
            "subcategory":"None",
            "type":"Food & Drink"
        }
    ],
    "sg:phone":"+1 415 885 1942",
    "sg:postcode":"94109",
    "sg:province":"CA",
    "wof:name":"Donuts & Things",
    "wof:placetype":"venue"
},
  "geometry": {"coordinates":[-122.420998,37.791302],"type":"Point"}
}