{
  "type": "Feature",
  "properties": {
    "addr:full":"85 N Raymond Ave Pasadena CA 91103",
    "addr:housenumber":"85",
    "addr:postcode":"91103",
    "addr:street":"N Raymond Ave",
    "iso:country":"US",
    "sg:address":"85 N Raymond Ave",
    "sg:city":"Pasadena",
    "sg:classifiers":[
        {
            "category":"Professional",
            "subcategory":"Advertising",
            "type":"Services"
        }
    ],
    "sg:phone":"+1 626 792 3933",
    "sg:postcode":"91103",
    "sg:province":"CA",
    "sg:tags":[
        "designer",
        "display",
        "producer"
    ],
    "sg:website":"www.olandtdesigngroup.com",
    "wof:name":"Olandt & Assoc",
    "wof:placetype":"venue"
},
  "geometry": {"coordinates":[-118.148982,34.147181],"type":"Point"}
}