{
  "type": "Feature",
  "properties": {
    "addr:full":"3860 Crenshaw Blvd Los Angeles CA 90008",
    "addr:housenumber":"3860",
    "addr:postcode":"90008",
    "addr:street":"Crenshaw Blvd",
    "iso:country":"US",
    "sg:address":"3860 Crenshaw Blvd",
    "sg:city":"Los Angeles",
    "sg:classifiers":[
        {
            "category":"Professional",
            "subcategory":"Business Services",
            "type":"Services"
        }
    ],
    "sg:phone":"+1 323 290 9204",
    "sg:postcode":"90008",
    "sg:province":"CA",
    "wof:name":"EEP Business Svc",
    "wof:placetype":"venue"
},
  "geometry": {"coordinates":[-118.334807,34.015407],"type":"Point"}
}