{
  "type": "Feature",
  "properties": {
    "addr:full":"18482 San Bernardino Ave Bloomington CA 92316",
    "addr:housenumber":"18482",
    "addr:postcode":"92316",
    "addr:street":"San Bernardino Ave",
    "iso:country":"US",
    "sg:address":"18482 San Bernardino Ave",
    "sg:city":"Bloomington",
    "sg:classifiers":[
        {
            "category":"Building & Trades",
            "subcategory":"Landscaping Services",
            "type":"Services"
        }
    ],
    "sg:phone":"+1 909 357 2064",
    "sg:postcode":"92316",
    "sg:province":"CA",
    "wof:name":"Javier Lawn Service",
    "wof:placetype":"venue"
},
  "geometry": {"coordinates":[-117.403144,34.077741],"type":"Point"}
}