{
  "type": "Feature",
  "properties": {
    "iso:country":"US",
    "sg:address":"10554 Santa Lucia Rd",
    "sg:city":"Cupertino",
    "sg:classifiers":[
        {
            "category":"Manufacturing",
            "subcategory":"Tools & Machinery",
            "type":"Manufacturing & Wholesale Goods"
        }
    ],
    "sg:phone":"+1 408 517 0690",
    "sg:postcode":"95014",
    "sg:province":"CA",
    "sg:tags":[
        "instrumentation",
        "fiber",
        "optic",
        "mfg"
    ],
    "wof:name":"O E Labs",
    "wof:placetype":"venue"
},
  "geometry": {"coordinates":[-122.070055,37.312743],"type":"Point"}
}