{
  "type": "Feature",
  "properties": {
    "iso:country":"US",
    "sg:address":"133 W Peace River Dr",
    "sg:city":"Fresno",
    "sg:classifiers":[
        {
            "category":"Real Estate",
            "subcategory":"Real Estate Agent",
            "type":"Services"
        }
    ],
    "sg:phone":"+1 559 435 8440",
    "sg:postcode":"93711",
    "sg:province":"CA",
    "sg:tags":[
        "inspection"
    ],
    "wof:name":"American Home Inspections",
    "wof:placetype":"venue"
},
  "geometry": {"coordinates":[-119.793058,36.867394],"type":"Point"}
}