{
  "type": "Feature",
  "properties": {
    "addr:full":"6556 Hollywood Blvd Los Angeles CA 90028",
    "addr:housenumber":"6556",
    "addr:postcode":"90028",
    "addr:street":"Hollywood Blvd",
    "iso:country":"US",
    "sg:address":"6556 Hollywood Blvd",
    "sg:city":"Los Angeles",
    "sg:classifiers":[
        {
            "category":"Shopping",
            "subcategory":"Clothing, Apparel, & Fashions",
            "type":"Retail Goods"
        }
    ],
    "sg:phone":"+1 323 462 5984",
    "sg:postcode":"90028",
    "sg:province":"CA",
    "sg:tags":[
        "handbag"
    ],
    "wof:name":"Contempo",
    "wof:placetype":"venue"
},
  "geometry": {"coordinates":[-118.333152,34.101506],"type":"Point"}
}