{
  "type": "Feature",
  "properties": {
    "addr:full":"2076 Chestnut St San Francisco CA 94123",
    "addr:housenumber":"2076",
    "addr:postcode":"94123",
    "addr:street":"Chestnut St",
    "iso:country":"US",
    "sg:address":"2076 Chestnut St",
    "sg:city":"San Francisco",
    "sg:classifiers":[
        {
            "category":"Sports & Exercise",
            "subcategory":"Gym",
            "type":"Entertainment"
        }
    ],
    "sg:phone":"+1 415 572 4437",
    "sg:postcode":"94123",
    "sg:province":"CA",
    "sg:tags":[
        "trainer"
    ],
    "sg:website":"www.marathonmatt.com",
    "wof:name":"Marathon Matt",
    "wof:placetype":"venue"
},
  "geometry": {"coordinates":[-122.437798,37.800905],"type":"Point"}
}