{
  "type": "Feature",
  "properties": {
    "iso:country":"US",
    "sg:address":"819 Rosemount Rd",
    "sg:city":"Oakland",
    "sg:classifiers":[
        {
            "category":"Building & Trades",
            "subcategory":"Construction",
            "type":"Services"
        }
    ],
    "sg:phone":"+1 510 465 1266",
    "sg:postcode":"94610",
    "sg:province":"CA",
    "sg:tags":[
        "painter"
    ],
    "wof:name":"Antoniades Mike Painting Co",
    "wof:placetype":"venue"
},
  "geometry": {"coordinates":[-122.23699999999999,37.808701],"type":"Point"}
}