{
  "type": "Feature",
  "properties": {
    "addr:full":"719 Capitola Ave Capitola CA 95010",
    "addr:housenumber":"719",
    "addr:postcode":"95010",
    "addr:street":"Capitola Ave",
    "iso:country":"US",
    "sg:address":"719 Capitola Ave",
    "sg:city":"Capitola",
    "sg:classifiers":[
        {
            "category":"Wholesale",
            "subcategory":"Vending Machines",
            "type":"Manufacturing & Wholesale Goods"
        }
    ],
    "sg:phone":"+1 831 239 1738",
    "sg:postcode":"95010",
    "sg:province":"CA",
    "wof:name":"Friendly Vending",
    "wof:placetype":"venue"
},
  "geometry": {"coordinates":[-121.952977,36.979386],"type":"Point"}
}