{
  "type": "Feature",
  "properties": {
    "addr:full":"6507 Fallbrook Ave Canoga Park CA 91307",
    "addr:housenumber":"6507",
    "addr:postcode":"91307",
    "addr:street":"Fallbrook Ave",
    "iso:country":"US",
    "sg:address":"6507 Fallbrook Ave",
    "sg:city":"Canoga Park",
    "sg:classifiers":[
        {
            "category":"Professional",
            "type":"Services"
        }
    ],
    "sg:phone":"+1 818 888 8029",
    "sg:postcode":"91307",
    "sg:province":"CA",
    "sg:tags":[
        "establishment"
    ],
    "wof:name":"Perfumella",
    "wof:placetype":"venue"
},
  "geometry": {"coordinates":[-118.62344,34.188398],"type":"Point"}
}