{
  "type": "Feature",
  "properties": {
    "addr:full":"4742 San Fernando Rd Glendale CA 91204",
    "addr:housenumber":"4742",
    "addr:postcode":"91204",
    "addr:street":"San Fernando Rd",
    "iso:country":"US",
    "sg:address":"4742 San Fernando Rd",
    "sg:city":"Glendale",
    "sg:classifiers":[
        {
            "category":"Manufacturing",
            "subcategory":"Retail Goods",
            "type":"Manufacturing & Wholesale Goods"
        }
    ],
    "sg:phone":"+1 323 259 4545",
    "sg:postcode":"91204",
    "sg:province":"CA",
    "sg:tags":[
        "rubber",
        "stamp"
    ],
    "sg:website":"www.newstampontheblock.com",
    "wof:name":"New Stamp On The Block",
    "wof:placetype":"venue"
},
  "geometry": {"coordinates":[-118.267143,34.137761],"type":"Point"}
}