{
  "type": "Feature",
  "properties": {
    "addr:full":"3653 San Fernando Rd Glendale CA 91204",
    "addr:housenumber":"3653",
    "addr:postcode":"91204",
    "addr:street":"San Fernando Rd",
    "iso:country":"US",
    "sg:address":"3653 San Fernando Rd",
    "sg:city":"Glendale",
    "sg:classifiers":[
        {
            "category":"Wholesale",
            "subcategory":"Electrical",
            "type":"Manufacturing & Wholesale Goods"
        }
    ],
    "sg:phone":"+1 323 245 7783",
    "sg:postcode":"91204",
    "sg:province":"CA",
    "sg:tags":[
        "equipment",
        "electric",
        "supply"
    ],
    "wof:name":"Wholesale Electric Inc",
    "wof:placetype":"venue"
},
  "geometry": {"coordinates":[-118.253406,34.122433],"type":"Point"}
}