{
  "type": "Feature",
  "properties": {
    "iso:country":"US",
    "sg:address":"400 S 2nd Ave",
    "sg:city":"Barstow",
    "sg:classifiers":[
        {
            "category":"Shopping",
            "subcategory":"Pharmacy",
            "type":"Retail Goods"
        }
    ],
    "sg:phone":"+1 760 256 5614",
    "sg:postcode":"92311",
    "sg:province":"CA",
    "wof:name":"Prescription Shop",
    "wof:placetype":"venue"
},
  "geometry": {"coordinates":[-117.0262,34.89562],"type":"Point"}
}