{
  "type": "Feature",
  "properties": {
    "addr:full":"194 W Club Center Dr San Bernardino CA 92408",
    "addr:housenumber":"194",
    "addr:postcode":"92408",
    "addr:street":"W Club Center Dr",
    "iso:country":"US",
    "sg:address":"194 W Club Center Dr",
    "sg:city":"San Bernardino",
    "sg:classifiers":[
        {
            "category":"Bars & Pubs",
            "type":"Food & Drink"
        }
    ],
    "sg:phone":"+1 909 824 2406",
    "sg:postcode":"92408",
    "sg:province":"CA",
    "wof:name":"Club",
    "wof:placetype":"venue"
},
  "geometry": {"coordinates":[-117.28410700000001,34.060553],"type":"Point"}
}