{
  "type": "Feature",
  "properties": {
    "iso:country":"US",
    "sg:address":"194 W Club Center Dr",
    "sg:city":"San Bernardino",
    "sg:classifiers":[
        {
            "category":"Bars & Pubs",
            "type":"Food & Drink"
        }
    ],
    "sg:phone":"+1 909 824 2406",
    "sg:postcode":"92408",
    "sg:province":"CA",
    "wof:name":"Club",
    "wof:placetype":"venue"
},
  "geometry": {"coordinates":[-117.284107,34.060553],"type":"Point"}
}