{
  "type": "Feature",
  "properties": {
    "iso:country":"US",
    "sg:address":"948 Pulteney Pl",
    "sg:city":"Windsor",
    "sg:classifiers":[
        {
            "category":"Professional",
            "subcategory":"Art Services",
            "type":"Services"
        }
    ],
    "sg:phone":"+1 707 838 0489",
    "sg:postcode":"95492",
    "sg:province":"CA",
    "sg:tags":[
        "interior",
        "designer",
        "decorator"
    ],
    "wof:name":"Richard L Peters",
    "wof:placetype":"venue"
},
  "geometry": {"coordinates":[-122.805097,38.555199],"type":"Point"}
}