{
  "type": "Feature",
  "properties": {
    "iso:country":"US",
    "sg:address":"630 Wilshire Blvd",
    "sg:city":"Santa Monica",
    "sg:classifiers":[
        {
            "category":"Shopping",
            "subcategory":"Photographic Equipment",
            "type":"Retail Goods"
        }
    ],
    "sg:phone":"+1 310 393 3089",
    "sg:postcode":"90401",
    "sg:province":"CA",
    "sg:tags":[
        "supply"
    ],
    "wof:name":"Ritz Camera Ctr",
    "wof:placetype":"venue"
},
  "geometry": {"coordinates":[-118.496152,34.020736],"type":"Point"}
}