{
  "type": "Feature",
  "properties": {
    "addr:full":"4690 Natomas Blvd Sacramento CA 95835",
    "addr:postcode":"4690;95835",
    "addr:street":"Natomas Blvd",
    "iso:country":"US",
    "sg:address":"4690 Natomas Blvd",
    "sg:city":"Sacramento",
    "sg:classifiers":[
        {
            "category":"Health Services",
            "subcategory":"Dentist",
            "type":"Services"
        }
    ],
    "sg:phone":"+1 916 515 4500",
    "sg:postcode":"95835",
    "sg:province":"CA",
    "wof:name":"Judy-Loan T Hoang, DDS",
    "wof:placetype":"venue"
},
  "geometry": {"coordinates":[-121.511962,38.658608],"type":"Point"}
}