{
  "type": "Feature",
  "properties": {
    "addr:full":"1471 N Occidental Blvd Los Angeles CA 90026",
    "addr:housenumber":"1471",
    "addr:postcode":"90026",
    "addr:street":"N Occidental Blvd",
    "iso:country":"US",
    "sg:address":"1471 N Occidental Blvd",
    "sg:city":"Los Angeles",
    "sg:classifiers":[
        {
            "category":"Real Estate",
            "subcategory":"Real Estate Agent",
            "type":"Services"
        }
    ],
    "sg:phone":"+1 323 644 9191",
    "sg:postcode":"90026",
    "sg:province":"CA",
    "wof:name":"Realty Association",
    "wof:placetype":"venue"
},
  "geometry": {"coordinates":[-118.26969099999999,34.085311],"type":"Point"}
}