{
  "type": "Feature",
  "properties": {
    "iso:country":"US",
    "sg:address":"380 N San Jacinto St",
    "sg:city":"Hemet",
    "sg:classifiers":[
        {
            "category":"Professional",
            "subcategory":"Accounting & Tax Preparation",
            "type":"Services"
        }
    ],
    "sg:phone":"+1 951 652 6080",
    "sg:postcode":"92544",
    "sg:province":"CA",
    "sg:tags":[
        "billing"
    ],
    "wof:name":"RMI Management Svc",
    "wof:placetype":"venue"
},
  "geometry": {"coordinates":[-116.95859,33.752723],"type":"Point"}
}