{
  "type": "Feature",
  "properties": {
    "iso:country":"US",
    "sg:address":"1501 Del Paso Boulevard",
    "sg:city":"Sacramento",
    "sg:classifiers":[
        {
            "category":"Banks & Credit Unions",
            "subcategory":"Financial Services",
            "type":"Services"
        }
    ],
    "sg:phone":"+1 916 927 9840",
    "sg:postcode":"95815",
    "sg:province":"CA",
    "sg:tags":[
        "broker",
        "mortgage"
    ],
    "wof:name":"Wells Fargo Home Mortgage",
    "wof:placetype":"venue"
},
  "geometry": {"coordinates":[-121.458675,38.606544],"type":"Point"}
}