{
  "type": "Feature",
  "properties": {
    "addr:full":"360 Post St Suite 404 San Francisco CA 94108",
    "addr:housenumber":"360",
    "addr:postcode":"94108",
    "addr:street":"Post St Suite 404",
    "iso:country":"US",
    "sg:address":"360 Post St Suite 404",
    "sg:city":"San Francisco",
    "sg:classifiers":[
        {
            "category":"Travel",
            "subcategory":"Travel Agent",
            "type":"Entertainment"
        }
    ],
    "sg:phone":"+1 415 291 8435",
    "sg:postcode":"94108",
    "sg:province":"CA",
    "sg:website":"www.borneousa.com",
    "wof:name":"Borneo International",
    "wof:placetype":"venue"
},
  "geometry": {"coordinates":[-122.407663,37.788673],"type":"Point"}
}