{
  "type": "Feature",
  "properties": {
    "iso:country":"US",
    "sg:address":"39755 Notting Hill Rd",
    "sg:city":"Murrieta",
    "sg:classifiers":[
        {
            "category":"Professional",
            "type":"Services"
        }
    ],
    "sg:phone":"+1 951 696 1984",
    "sg:postcode":"92563",
    "sg:province":"CA",
    "sg:tags":[
        "establishment"
    ],
    "wof:name":"Cory Mc Millin Co",
    "wof:placetype":"venue"
},
  "geometry": {"coordinates":[-117.16843900000001,33.557866],"type":"Point"}
}