{
  "type": "Feature",
  "properties": {
    "addr:full":"1175 Chess Dr Foster City CA 94404",
    "addr:housenumber":"1175",
    "addr:postcode":"94404",
    "addr:street":"Chess Dr",
    "iso:country":"US",
    "sg:address":"1175 Chess Dr",
    "sg:city":"Foster City",
    "sg:classifiers":[
        {
            "category":"Professional",
            "subcategory":"Computer Services",
            "type":"Services"
        }
    ],
    "sg:phone":"+1 650 341 9600",
    "sg:postcode":"94404",
    "sg:province":"CA",
    "sg:tags":[
        "repair"
    ],
    "sg:website":"www.darcomtech.com",
    "wof:name":"Darcom Technologies Inc",
    "wof:placetype":"venue"
},
  "geometry": {"coordinates":[-122.274747,37.564778],"type":"Point"}
}