{
  "type": "Feature",
  "properties": {
    "addr:full":"6824 Brynhurst Ave Los Angeles CA 90043",
    "addr:postcode":"6824;90043",
    "addr:street":"Brynhurst Ave",
    "iso:country":"US",
    "sg:address":"6824 Brynhurst Ave",
    "sg:city":"Los Angeles",
    "sg:classifiers":[
        {
            "category":"Building & Trades",
            "subcategory":"Construction",
            "type":"Services"
        }
    ],
    "sg:phone":"+1 323 752 8800",
    "sg:postcode":"90043",
    "sg:province":"CA",
    "sg:tags":[
        "maker",
        "cabinet"
    ],
    "sg:website":"www.izhaks.com",
    "wof:name":"Izhak's Custom Interiors Inc",
    "wof:placetype":"venue"
},
  "geometry": {"coordinates":[-118.333716,33.977077],"type":"Point"}
}