{
  "type": "Feature",
  "properties": {
    "iso:country":"US",
    "sg:address":"4608 Grenadier Pl",
    "sg:city":"Castro Valley",
    "sg:classifiers":[
        {
            "category":"Manufacturing",
            "subcategory":"Glass & Minerals",
            "type":"Manufacturing & Wholesale Goods"
        }
    ],
    "sg:phone":"+1 510 886 2203",
    "sg:postcode":"94546",
    "sg:province":"CA",
    "sg:tags":[
        "mfg",
        "ceramics"
    ],
    "wof:name":"Aerospace Ceramics Inc",
    "wof:placetype":"venue"
},
  "geometry": {"coordinates":[-122.086139,37.718971],"type":"Point"}
}