{
  "type": "Feature",
  "properties": {
    "addr:full":"14442 Whittier Blvd Whittier CA 90605",
    "addr:housenumber":"14442",
    "addr:postcode":"90605",
    "addr:street":"Whittier Blvd",
    "iso:country":"US",
    "sg:address":"14442 Whittier Blvd",
    "sg:city":"Whittier",
    "sg:classifiers":[
        {
            "category":"Professional",
            "subcategory":"Detective & Security Services",
            "type":"Services"
        }
    ],
    "sg:phone":"+1 562 698 1984",
    "sg:postcode":"90605",
    "sg:province":"CA",
    "sg:tags":[
        "guard",
        "patrol"
    ],
    "wof:name":"Southwest International Inc",
    "wof:placetype":"venue"
},
  "geometry": {"coordinates":[-118.01656199999999,33.953904],"type":"Point"}
}