{
  "type": "Feature",
  "properties": {
    "iso:country":"US",
    "sg:address":"15838 Arminta St",
    "sg:city":"Van Nuys",
    "sg:classifiers":[
        {
            "category":"Building & Trades",
            "subcategory":"Pest Control",
            "type":"Services"
        }
    ],
    "sg:phone":"+1 818 376 7501",
    "sg:postcode":"91406",
    "sg:province":"CA",
    "wof:name":"Benchmark Termite Control",
    "wof:placetype":"venue"
},
  "geometry": {"coordinates":[-118.478091,34.21381],"type":"Point"}
}