{
  "type": "Feature",
  "properties": {
    "iso:country":"US",
    "sg:address":"1 Mustang Dr",
    "sg:city":"San Luis Obispo",
    "sg:classifiers":[
        {
            "category":"Travel",
            "subcategory":"Bed & Breakfast",
            "type":"Entertainment"
        }
    ],
    "sg:phone":"+1 805 783 2500",
    "sg:postcode":"93405",
    "sg:province":"CA",
    "sg:tags":[
        "housing",
        "student"
    ],
    "sg:website":"www.universityhouse.com",
    "wof:name":"Mustang Village Apartments",
    "wof:placetype":"venue"
},
  "geometry": {"coordinates":[-120.665047,35.29517],"type":"Point"}
}