{
  "type": "Feature",
  "properties": {
    "iso:country":"US",
    "sg:address":"306 N Willis St",
    "sg:city":"Visalia",
    "sg:classifiers":[
        {
            "category":"Professional",
            "subcategory":"Management & Consulting",
            "type":"Services"
        }
    ],
    "sg:phone":"+1 559 733 4256",
    "sg:postcode":"93291",
    "sg:province":"CA",
    "sg:tags":[
        "consultant",
        "relation",
        "labor"
    ],
    "sg:website":"www.pacificemployers.com",
    "wof:name":"Pacific Employer's",
    "wof:placetype":"venue"
},
  "geometry": {"coordinates":[-119.297632,36.33234],"type":"Point"}
}