{
  "type": "Feature",
  "properties": {
    "iso:country":"US",
    "sg:address":"3597 del Valle Pkwy",
    "sg:city":"Pleasanton",
    "sg:classifiers":[
        {
            "category":"Taxi",
            "type":"Transportation"
        }
    ],
    "sg:phone":"+1 925 833 7777",
    "sg:postcode":"94566",
    "sg:province":"CA",
    "sg:tags":[
        "taxicab"
    ],
    "wof:name":"Taxi DOT Com",
    "wof:placetype":"venue"
},
  "geometry": {"coordinates":[-121.857911,37.666644],"type":"Point"}
}