{
  "type": "Feature",
  "properties": {
    "iso:country":"US",
    "sg:address":"3737 Central Ave",
    "sg:city":"Riverside",
    "sg:classifiers":[
        {
            "category":"Home & Garden",
            "subcategory":"Household Appliances",
            "type":"Retail Goods"
        }
    ],
    "sg:phone":"+1 951 784 3737",
    "sg:postcode":"92506",
    "sg:province":"CA",
    "sg:tags":[
        "cleaners",
        "vacuum"
    ],
    "wof:name":"Kirby Vacuum Repair",
    "wof:placetype":"venue"
},
  "geometry": {"coordinates":[-117.39502400000001,33.953614],"type":"Point"}
}