{
  "type": "Feature",
  "properties": {
    "iso:country":"US",
    "sg:address":"14 Miller Ave",
    "sg:city":"Mill Valley",
    "sg:classifiers":[
        {
            "category":"Shopping",
            "subcategory":"Clothing, Apparel, & Fashions",
            "type":"Retail Goods"
        }
    ],
    "sg:phone":"+1 415 388 2390",
    "sg:postcode":"94941",
    "sg:province":"CA",
    "wof:name":"Margaret O'Leary",
    "wof:placetype":"venue"
},
  "geometry": {"coordinates":[-122.548283,37.906192],"type":"Point"}
}