{
  "type": "Feature",
  "properties": {
    "addr:full":"7501 N 1st St Fresno CA 93720",
    "addr:housenumber":"7501",
    "addr:postcode":"93720",
    "addr:street":"N 1St St",
    "iso:country":"US",
    "sg:address":"7501 N 1st St",
    "sg:city":"Fresno",
    "sg:classifiers":[
        {
            "category":"Wholesale",
            "subcategory":"Toys & Hobbies",
            "type":"Manufacturing & Wholesale Goods"
        }
    ],
    "sg:phone":"+1 559 435 4985",
    "sg:postcode":"93720",
    "sg:province":"CA",
    "sg:tags":[
        "wholesaler"
    ],
    "wof:name":"Wise Trading",
    "wof:placetype":"venue"
},
  "geometry": {"coordinates":[-119.774631,36.846485],"type":"Point"}
}