{
  "type": "Feature",
  "properties": {
    "iso:country":"US",
    "sg:address":"1439 Stannage Ave.",
    "sg:city":"Berkeley",
    "sg:classifiers":[
        {
            "category":"Building & Trades",
            "subcategory":"Landscaping Services",
            "type":"Services"
        }
    ],
    "sg:phone":"+1 510 525 2041",
    "sg:postcode":"94702",
    "sg:province":"CA",
    "sg:website":"www.carlopessanolandscaping.com",
    "wof:name":"Carlo Pessano Landscaping",
    "wof:placetype":"venue"
},
  "geometry": {"coordinates":[-122.292771,37.877683],"type":"Point"}
}