{
  "type": "Feature",
  "properties": {
    "addr:full":"236 S Reese Pl Burbank CA 91506",
    "addr:housenumber":"236",
    "addr:postcode":"91506",
    "addr:street":"S Reese Pl",
    "iso:country":"US",
    "sg:address":"236 S Reese Pl",
    "sg:city":"Burbank",
    "sg:classifiers":[
        {
            "category":"Building & Trades",
            "subcategory":"Landscaping Services",
            "type":"Services"
        }
    ],
    "sg:phone":"+1 818 845 3460",
    "sg:postcode":"91506",
    "sg:province":"CA",
    "wof:name":"Bobs Tree Service",
    "wof:placetype":"venue"
},
  "geometry": {"coordinates":[-118.32219600000001,34.16592],"type":"Point"}
}