{
  "type": "Feature",
  "properties": {
    "iso:country":"US",
    "sg:address":"12791 Newport Ave Ste 202",
    "sg:city":"Tustin",
    "sg:classifiers":[
        {
            "category":"Health Services",
            "subcategory":"Doctor",
            "type":"Services"
        }
    ],
    "sg:phone":"+1 714 508 2105",
    "sg:postcode":"92780",
    "sg:province":"CA",
    "sg:tags":[
        "surgeon",
        "cosmetic"
    ],
    "sg:website":"www.colemanplasticsurgery.com",
    "wof:name":"James Coleman, MD",
    "wof:placetype":"venue"
},
  "geometry": {"coordinates":[-117.80978500000001,33.750573],"type":"Point"}
}