{
  "type": "Feature",
  "properties": {
    "addr:full":"5112 Katella Ave Los Alamitos CA 90720",
    "addr:housenumber":"5112",
    "addr:postcode":"90720",
    "addr:street":"Katella Ave",
    "iso:country":"US",
    "sg:address":"5112 Katella Ave",
    "sg:city":"Los Alamitos",
    "sg:classifiers":[
        {
            "category":"Professional",
            "subcategory":"Employment Agencies",
            "type":"Services"
        }
    ],
    "sg:phone":"+1 562 936 0070",
    "sg:postcode":"90720",
    "sg:province":"CA",
    "sg:tags":[
        "help",
        "contractor"
    ],
    "wof:name":"Drake Intl",
    "wof:placetype":"venue"
},
  "geometry": {"coordinates":[-118.041344,33.803],"type":"Point"}
}