{
  "type": "Feature",
  "properties": {
    "addr:full":"1014 Stockton St San Francisco CA 94108",
    "addr:housenumber":"1014",
    "addr:postcode":"94108",
    "addr:street":"Stockton St",
    "iso:country":"US",
    "sg:address":"1014 Stockton St",
    "sg:city":"San Francisco",
    "sg:classifiers":[
        {
            "category":"Shopping",
            "subcategory":"Clothing, Apparel, & Fashions",
            "type":"Retail Goods"
        }
    ],
    "sg:phone":"+1 415 788 8869",
    "sg:postcode":"94108",
    "sg:province":"CA",
    "wof:name":"Tai Chong Co",
    "wof:placetype":"venue"
},
  "geometry": {"coordinates":[-122.408159,37.795709],"type":"Point"}
}