{
  "type": "Feature",
  "properties": {
    "iso:country":"US",
    "sg:address":"1505 E Sierra Ave",
    "sg:city":"Fresno",
    "sg:classifiers":[
        {
            "category":"Wholesale",
            "subcategory":"Hardware",
            "type":"Manufacturing & Wholesale Goods"
        }
    ],
    "sg:phone":"+1 559 431 6767",
    "sg:postcode":"93710",
    "sg:province":"CA",
    "sg:tags":[
        "furnace"
    ],
    "wof:name":"Chuck's Appliance Repair",
    "wof:placetype":"venue"
},
  "geometry": {"coordinates":[-119.76058999999999,36.830176],"type":"Point"}
}