{
  "type": "Feature",
  "properties": {
    "addr:full":"4000 Ruffin Rd San Diego CA 92123",
    "addr:housenumber":"4000",
    "addr:postcode":"92123",
    "addr:street":"Ruffin Rd",
    "iso:country":"US",
    "sg:address":"4000 Ruffin Rd",
    "sg:city":"San Diego",
    "sg:classifiers":[
        {
            "category":"Wholesale",
            "subcategory":"Medical Equipment & Supplies",
            "type":"Manufacturing & Wholesale Goods"
        }
    ],
    "sg:phone":"+1 858 637 6400",
    "sg:postcode":"92123",
    "sg:province":"CA",
    "sg:tags":[
        "physician",
        "surgeon"
    ],
    "sg:website":"www.sharp.com",
    "wof:name":"Sharp Health Care",
    "wof:placetype":"venue"
},
  "geometry": {"coordinates":[-117.124025,32.816856],"type":"Point"}
}