{
  "type": "Feature",
  "properties": {
    "iso:country":"US",
    "sg:address":"443 Dutton Ave",
    "sg:city":"Santa Rosa",
    "sg:classifiers":[
        {
            "category":"Food & Beverages",
            "subcategory":"Bakery",
            "type":"Retail Goods"
        }
    ],
    "sg:phone":"+1 707 568 7051",
    "sg:postcode":"95407",
    "sg:province":"CA",
    "sg:tags":[
        "baker"
    ],
    "wof:name":"Pasteles Fiesta",
    "wof:placetype":"venue"
},
  "geometry": {"coordinates":[-122.725549,38.431134],"type":"Point"}
}