{
  "type": "Feature",
  "properties": {
    "addr:full":"1006 N East St Alturas CA 96101",
    "addr:housenumber":"1006",
    "addr:postcode":"96101",
    "addr:street":"N East St",
    "iso:country":"US",
    "sg:address":"1006 N East St",
    "sg:city":"Alturas",
    "sg:classifiers":[
        {
            "category":"Personal",
            "subcategory":"Beauty Salon",
            "type":"Services"
        }
    ],
    "sg:phone":"+1 530 233 4539",
    "sg:postcode":"96101",
    "sg:province":"CA",
    "sg:tags":[
        "manicuring"
    ],
    "wof:name":"House Of Nails",
    "wof:placetype":"venue"
},
  "geometry": {"coordinates":[-120.539968,41.494533],"type":"Point"}
}