{
  "type": "Feature",
  "properties": {
    "iso:country":"US",
    "sg:address":"3085 E 4th St",
    "sg:city":"Los Angeles",
    "sg:classifiers":[
        {
            "category":"Autos & Motor Vehicles",
            "subcategory":"Fuel & Gas Station",
            "type":"Retail Goods"
        }
    ],
    "sg:phone":"+1 323 264 8687",
    "sg:postcode":"90063",
    "sg:province":"CA",
    "wof:name":"Frontino's Automotive Services",
    "wof:placetype":"venue"
},
  "geometry": {"coordinates":[-118.200996,34.035801],"type":"Point"}
}