{
  "type": "Feature",
  "properties": {
    "addr:full":"42 Surfside Ave Surfside CA 90743",
    "addr:housenumber":"42",
    "addr:postcode":"90743",
    "addr:street":"Surfside Ave",
    "iso:country":"US",
    "sg:address":"42 Surfside Ave",
    "sg:city":"Surfside",
    "sg:classifiers":[
        {
            "category":"Manufacturing",
            "subcategory":"Signs",
            "type":"Manufacturing & Wholesale Goods"
        }
    ],
    "sg:phone":"+1 562 592 5838",
    "sg:postcode":"90743",
    "sg:province":"CA",
    "wof:name":"Absolute Sign",
    "wof:placetype":"venue"
},
  "geometry": {"coordinates":[-118.085404,33.728428],"type":"Point"}
}