{
  "type": "Feature",
  "properties": {
    "addr:full":"2585 Warbler Ave Ventura CA 93003",
    "addr:housenumber":"2585",
    "addr:postcode":"93003",
    "addr:street":"Warbler Ave",
    "iso:country":"US",
    "sg:address":"2585 Warbler Ave",
    "sg:city":"Ventura",
    "sg:classifiers":[
        {
            "category":"Building & Trades",
            "subcategory":"Landscaping Services",
            "type":"Services"
        }
    ],
    "sg:phone":"+1 805 984 1723",
    "sg:postcode":"93003",
    "sg:province":"CA",
    "sg:tags":[
        "tree"
    ],
    "wof:name":"Frank Fuentes Tree Cutting",
    "wof:placetype":"venue"
},
  "geometry": {"coordinates":[-119.19670600000001,34.253494],"type":"Point"}
}