{
  "type": "Feature",
  "properties": {
    "iso:country":"US",
    "sg:address":"1054 N Dutton Ave",
    "sg:city":"Santa Rosa",
    "sg:classifiers":[
        {
            "category":"Manufacturing",
            "subcategory":"Metals",
            "type":"Manufacturing & Wholesale Goods"
        }
    ],
    "sg:phone":"+1 707 545 5915",
    "sg:postcode":"95401",
    "sg:province":"CA",
    "sg:tags":[
        "fabricated",
        "structural"
    ],
    "wof:name":"Kauth Brothers Inc",
    "wof:placetype":"venue"
},
  "geometry": {"coordinates":[-122.73036,38.445488],"type":"Point"}
}