{
  "type": "Feature",
  "properties": {
    "addr:full":"8040 N Orchard St Fresno CA 93720",
    "addr:housenumber":"8040",
    "addr:postcode":"93720",
    "addr:street":"N Orchard St",
    "iso:country":"US",
    "sg:address":"8040 N Orchard St",
    "sg:city":"Fresno",
    "sg:classifiers":[
        {
            "category":"Personal",
            "type":"Services"
        }
    ],
    "sg:phone":"+1 559 435 8541",
    "sg:postcode":"93720",
    "sg:province":"CA",
    "sg:tags":[
        "miscellaneous"
    ],
    "wof:name":"Lisa A Naffziger Personal Svc",
    "wof:placetype":"venue"
},
  "geometry": {"coordinates":[-119.777801,36.852381],"type":"Point"}
}