{
  "type": "Feature",
  "properties": {
    "iso:country":"US",
    "sg:address":"1868 Clayton Rd",
    "sg:city":"Concord",
    "sg:classifiers":[
        {
            "category":"Social Services",
            "type":"Services"
        }
    ],
    "sg:phone":"+1 925 686 5077",
    "sg:postcode":"94520",
    "sg:province":"CA",
    "sg:tags":[
        "counselor",
        "marriage",
        "family"
    ],
    "wof:name":"Fran Montgomery Offices",
    "wof:placetype":"venue"
},
  "geometry": {"coordinates":[-122.035746,37.973694],"type":"Point"}
}