{
  "type": "Feature",
  "properties": {
    "iso:country":"US",
    "sg:address":"3075 Southgate Ln",
    "sg:city":"Chico",
    "sg:classifiers":[
        {
            "category":"Home & Garden",
            "subcategory":"Building Materials",
            "type":"Retail Goods"
        }
    ],
    "sg:phone":"+1 530 895 3710",
    "sg:postcode":"95928",
    "sg:province":"CA",
    "sg:tags":[
        "door"
    ],
    "wof:name":"Sam's Door Shop",
    "wof:placetype":"venue"
},
  "geometry": {"coordinates":[-121.782139,39.698557],"type":"Point"}
}