{
  "type": "Feature",
  "properties": {
    "addr:full":"14940 Brookstone Dr Poway CA 92064",
    "addr:housenumber":"14940",
    "addr:postcode":"ca 92064",
    "addr:street":"Brookstone Dr",
    "iso:country":"US",
    "sg:address":"14940 Brookstone Dr",
    "sg:city":"Poway",
    "sg:classifiers":[
        {
            "category":"Manufacturing",
            "subcategory":"Electronics",
            "type":"Manufacturing & Wholesale Goods"
        }
    ],
    "sg:phone":"+1 858 748 0988",
    "sg:postcode":"92064",
    "sg:province":"CA",
    "sg:tags":[
        "equipment",
        "mfg",
        "communications"
    ],
    "wof:name":"Traffic Monitoring Servic",
    "wof:placetype":"venue"
},
  "geometry": {"coordinates":[-117.05714,32.985394],"type":"Point"}
}