{
  "type": "Feature",
  "properties": {
    "addr:full":"1920 Union St Ste 13 Oakland CA 94607",
    "addr:housenumber":"1920",
    "addr:postcode":"94607",
    "addr:street":"Union St Ste 13",
    "iso:country":"US",
    "sg:address":"1920 Union St Ste 13",
    "sg:city":"Oakland",
    "sg:classifiers":[
        {
            "category":"Shopping",
            "subcategory":"Bridal",
            "type":"Retail Goods"
        },
        {
            "category":"Wholesale",
            "subcategory":"Stationery",
            "type":"Manufacturing & Wholesale Goods"
        },
        {
            "category":"Wholesale",
            "subcategory":"Books, Periodicals, & Newspapers",
            "type":"Manufacturing & Wholesale Goods"
        }
    ],
    "sg:phone":"+1 510 839 7573",
    "sg:postcode":"94607",
    "sg:province":"CA",
    "sg:tags":[
        "publisher",
        "book",
        "card"
    ],
    "sg:website":"kavamorepress.com/",
    "wof:name":"Kavamore Press",
    "wof:placetype":"venue"
},
  "geometry": {"coordinates":[-122.286562,37.814015],"type":"Point"}
}