{
  "type": "Feature",
  "properties": {
    "iso:country":"US",
    "sg:address":"45168 Elm Ave",
    "sg:city":"Lancaster",
    "sg:classifiers":[
        {
            "category":"Retail",
            "subcategory":"Animal Services",
            "type":"Services"
        }
    ],
    "sg:phone":"+1 661 948 3851",
    "sg:postcode":"93534",
    "sg:province":"CA",
    "sg:tags":[
        "pet",
        "grooming",
        "washing",
        "specialty"
    ],
    "wof:name":"Sharon's Canine Coiffures",
    "wof:placetype":"venue"
},
  "geometry": {"coordinates":[-118.142735,34.702784],"type":"Point"}
}