{
  "type": "Feature",
  "properties": {
    "addr:full":"8617 Colima Rd Whittier CA 90605",
    "addr:housenumber":"8617",
    "addr:postcode":"90605",
    "addr:street":"Colima Rd",
    "iso:country":"US",
    "sg:address":"8617 Colima Rd",
    "sg:city":"Whittier",
    "sg:classifiers":[
        {
            "category":"Health Services",
            "subcategory":"Medical Lab",
            "type":"Services"
        }
    ],
    "sg:phone":"+1 562 696 5167",
    "sg:postcode":"90605",
    "sg:province":"CA",
    "sg:tags":[
        "laboratory"
    ],
    "wof:name":"Platinum Dental Ceramics",
    "wof:placetype":"venue"
},
  "geometry": {"coordinates":[-118.002354,33.955103],"type":"Point"}
}