{
  "type": "Feature",
  "properties": {
    "iso:country":"US",
    "sg:address":"2020 Bonifacio St",
    "sg:city":"Concord",
    "sg:classifiers":[
        {
            "category":"Professional",
            "subcategory":"Lawyer & Legal Services",
            "type":"Services"
        }
    ],
    "sg:phone":"+1 925 825 3393",
    "sg:postcode":"94520",
    "sg:province":"CA",
    "sg:tags":[
        "attorney"
    ],
    "wof:name":"Scramstad & Bryan PC",
    "wof:placetype":"venue"
},
  "geometry": {"coordinates":[-122.036252,37.979085],"type":"Point"}
}