{
  "type": "Feature",
  "properties": {
    "addr:full":"317 Aurora Dr Perris CA 92571",
    "addr:housenumber":"317",
    "addr:postcode":"92571",
    "addr:street":"Aurora Dr",
    "iso:country":"US",
    "sg:address":"317 Aurora Dr",
    "sg:city":"Perris",
    "sg:classifiers":[
        {
            "category":"Professional",
            "subcategory":"Printing & Photocopies",
            "type":"Services"
        }
    ],
    "sg:phone":"+1 951 657 9607",
    "sg:postcode":"92571",
    "sg:province":"CA",
    "sg:tags":[
        "lithographer"
    ],
    "wof:name":"Gt Printing",
    "wof:placetype":"venue"
},
  "geometry": {"coordinates":[-117.219055,33.809296],"type":"Point"}
}