{
  "type": "Feature",
  "properties": {
    "iso:country":"US",
    "sg:address":"5750 Wilshire Blvd",
    "sg:city":"Los Angeles",
    "sg:classifiers":[
        {
            "category":"Communications",
            "subcategory":"Television Station",
            "type":"Services"
        }
    ],
    "sg:phone":"+1 323 692 4880",
    "sg:postcode":"90036",
    "sg:province":"CA",
    "sg:tags":[
        "broadcasting",
        "co"
    ],
    "sg:website":"www.eonline.com",
    "wof:name":"E Online",
    "wof:placetype":"venue"
},
  "geometry": {"coordinates":[-118.354606,34.06238],"type":"Point"}
}