{
  "type": "Feature",
  "properties": {
    "addr:full":"2500 E Main St Barstow CA 92311",
    "addr:housenumber":"2500",
    "addr:postcode":"92311",
    "addr:street":"E Main St",
    "iso:country":"US",
    "sg:address":"2500 E Main St",
    "sg:city":"Barstow",
    "sg:classifiers":[
        {
            "category":"Retail",
            "subcategory":"Animal Services",
            "type":"Services"
        }
    ],
    "sg:phone":"+1 760 252 8200",
    "sg:postcode":"92311",
    "sg:province":"CA",
    "sg:tags":[
        "personal"
    ],
    "wof:name":"New Animal Hospital",
    "wof:placetype":"venue"
},
  "geometry": {"coordinates":[-116.993723,34.885439],"type":"Point"}
}