{
  "type": "Feature",
  "properties": {
    "addr:full":"187 S Mountain Ave Upland CA 91786",
    "addr:housenumber":"187",
    "addr:postcode":"91786",
    "addr:street":"S Mountain Ave",
    "iso:country":"US",
    "sg:address":"187 S Mountain Ave",
    "sg:city":"Upland",
    "sg:classifiers":[
        {
            "category":"Restaurant",
            "type":"Food & Drink"
        }
    ],
    "sg:menulink":"http://www.allmenus.com/ca/ontario/174570-wendys/menu/",
    "sg:phone":"+1 909 982 9370",
    "sg:postcode":"91786",
    "sg:province":"CA",
    "sg:tags":[
        "burger",
        "american",
        "soup"
    ],
    "wof:name":"Wendy's",
    "wof:placetype":"venue"
},
  "geometry": {"coordinates":[-117.670574,34.092747],"type":"Point"}
}