{
  "type": "Feature",
  "properties": {
    "iso:country":"US",
    "sg:address":"4171 Piedmont Ave",
    "sg:city":"Oakland",
    "sg:classifiers":[
        {
            "category":"Social Services",
            "type":"Services"
        },
        {
            "category":"Personal",
            "type":"Services"
        }
    ],
    "sg:phone":"+1 510 985 1208",
    "sg:postcode":"94611",
    "sg:province":"CA",
    "sg:tags":[
        "counseling",
        "individual",
        "family",
        "counselors-licensed",
        "therapist",
        "marriage",
        "child",
        "professional",
        "counselor"
    ],
    "wof:name":"Bronwyn Warren Ma Mft",
    "wof:placetype":"venue"
},
  "geometry": {"coordinates":[-122.25137599999999,37.827213],"type":"Point"}
}