{
  "type": "Feature",
  "properties": {
    "addr:full":"150 Spear Street San Francisco CA 94105",
    "addr:housenumber":"150",
    "addr:postcode":"94105",
    "addr:street":"Spear Street",
    "iso:country":"US",
    "sg:address":"150 Spear Street",
    "sg:city":"San Francisco",
    "sg:classifiers":[
        {
            "category":"Professional",
            "subcategory":"Lawyer & Legal Services",
            "type":"Services"
        }
    ],
    "sg:phone":"+1 415 541 0200",
    "sg:postcode":"94105",
    "sg:province":"CA",
    "wof:name":"Young David Attys",
    "wof:placetype":"venue"
},
  "geometry": {"coordinates":[-122.393293,37.791908],"type":"Point"}
}