{
  "type": "Feature",
  "properties": {
    "iso:country":"US",
    "sg:address":"417 Alvarado St",
    "sg:city":"Monterey",
    "sg:classifiers":[
        {
            "category":"Cinema",
            "subcategory":"Movie Theater",
            "type":"Entertainment"
        }
    ],
    "sg:phone":"+1 831 372 4555",
    "sg:postcode":"93940",
    "sg:province":"CA",
    "wof:name":"State Theatre",
    "wof:placetype":"venue"
},
  "geometry": {"coordinates":[-121.89444899999999,36.599358],"type":"Point"}
}