{
  "type": "Feature",
  "properties": {
    "iso:country":"US",
    "sg:address":"3615 Brookline Ave.",
    "sg:city":"Rosemead",
    "sg:classifiers":[
        {
            "category":"Personal",
            "type":"Services"
        }
    ],
    "sg:phone":"+1 626 272 9268",
    "sg:postcode":"91770",
    "sg:province":"CA",
    "sg:tags":[
        "planning",
        "wedding"
    ],
    "wof:name":"Suzy Karaoke",
    "wof:placetype":"venue"
},
  "geometry": {"coordinates":[-118.057711,34.074713],"type":"Point"}
}