{
  "type": "Feature",
  "properties": {
    "iso:country":"US",
    "sg:address":"581 N Palm Ave",
    "sg:city":"Hemet",
    "sg:classifiers":[
        {
            "category":"Retail",
            "subcategory":"Auto Repair",
            "type":"Services"
        }
    ],
    "sg:phone":"+1 951 658 2020",
    "sg:postcode":"92543",
    "sg:province":"CA",
    "sg:tags":[
        "repairing",
        "automobile"
    ],
    "wof:name":"BNB Automotive Repair",
    "wof:placetype":"venue"
},
  "geometry": {"coordinates":[-116.98052300000001,33.756227],"type":"Point"}
}