{
  "type": "Feature",
  "properties": {
    "iso:country":"US",
    "sg:address":"1497 Gray Ave",
    "sg:city":"Yuba City",
    "sg:classifiers":[
        {
            "category":"Real Estate",
            "subcategory":"Surveying",
            "type":"Services"
        }
    ],
    "sg:phone":"+1 530 671 3625",
    "sg:postcode":"95991",
    "sg:province":"CA",
    "sg:tags":[
        "surveyor"
    ],
    "wof:name":"R Lee Hixson Surveyor",
    "wof:placetype":"venue"
},
  "geometry": {"coordinates":[-121.630026,39.150903],"type":"Point"}
}