{
  "type": "Feature",
  "properties": {
    "addr:full":"614 W Fairway Blvd Big Bear City CA 92314",
    "addr:housenumber":"614",
    "addr:postcode":"92314",
    "addr:street":"W Fairway Blvd",
    "iso:country":"US",
    "sg:address":"614 W Fairway Blvd",
    "sg:city":"Big Bear City",
    "sg:classifiers":[
        {
            "category":"Autos & Motor Vehicles",
            "subcategory":"Boat Sales",
            "type":"Retail Goods"
        }
    ],
    "sg:phone":"+1 909 584 7612",
    "sg:postcode":"92314",
    "sg:province":"CA",
    "sg:tags":[
        "dealer",
        "sales"
    ],
    "wof:name":"Valley-Wide Marine Repair",
    "wof:placetype":"venue"
},
  "geometry": {"coordinates":[-116.85693999999999,34.262435],"type":"Point"}
}