{
  "type": "Feature",
  "properties": {
    "iso:country":"US",
    "sg:address":"3030 W Olympic Blvd # 211",
    "sg:city":"Los Angeles",
    "sg:classifiers":[
        {
            "category":"Professional",
            "subcategory":"Art Services",
            "type":"Services"
        }
    ],
    "sg:phone":"+1 213 908 6391",
    "sg:postcode":"90006",
    "sg:province":"CA",
    "sg:tags":[
        "graphic",
        "design"
    ],
    "wof:name":"Color Tango Design",
    "wof:placetype":"venue"
},
  "geometry": {"coordinates":[-118.301547,34.052218],"type":"Point"}
}