{
  "type": "Feature",
  "properties": {
    "iso:country":"US",
    "sg:address":"119 Neptune Pl",
    "sg:city":"San Ramon",
    "sg:classifiers":[
        {
            "category":"Banks & Credit Unions",
            "subcategory":"Investment Brokerage",
            "type":"Services"
        }
    ],
    "sg:phone":"+1 925 833 0616",
    "sg:postcode":"94583",
    "sg:province":"CA",
    "sg:tags":[
        "consultant",
        "financing"
    ],
    "wof:name":"L B Financial Svc",
    "wof:placetype":"venue"
},
  "geometry": {"coordinates":[-121.924403,37.729273],"type":"Point"}
}