{
  "type": "Feature",
  "properties": {
    "addr:full":"20929 Ventura Blvd Woodland Hills CA 91364",
    "addr:housenumber":"20929",
    "addr:postcode":"91364",
    "addr:street":"Ventura Blvd",
    "iso:country":"US",
    "sg:address":"20929 Ventura Blvd",
    "sg:city":"Woodland Hills",
    "sg:classifiers":[
        {
            "category":"Personal",
            "subcategory":"Barber",
            "type":"Services"
        }
    ],
    "sg:phone":"+1 818 703 7587",
    "sg:postcode":"91364",
    "sg:province":"CA",
    "wof:name":"David Maggiora",
    "wof:placetype":"venue"
},
  "geometry": {"coordinates":[-118.590228,34.166636],"type":"Point"}
}