{
  "type": "Feature",
  "properties": {
    "iso:country":"US",
    "sg:address":"409 Tehama St",
    "sg:city":"San Francisco",
    "sg:classifiers":[
        {
            "category":"Wholesale",
            "subcategory":"Plants",
            "type":"Manufacturing & Wholesale Goods"
        }
    ],
    "sg:phone":"+1 415 495 1900",
    "sg:postcode":"94103",
    "sg:province":"CA",
    "sg:tags":[
        "supply"
    ],
    "wof:name":"Soma Wholesale Florist",
    "wof:placetype":"venue"
},
  "geometry": {"coordinates":[-122.406431,37.779406],"type":"Point"}
}