{
  "type": "Feature",
  "properties": {
    "addr:full":"3761 6th Ave San Diego CA 92103",
    "addr:housenumber":"3761",
    "addr:postcode":"92103",
    "addr:street":"6Th Ave",
    "iso:country":"US",
    "sg:address":"3761 6th Ave",
    "sg:city":"San Diego",
    "sg:classifiers":[
        {
            "category":"Restaurant",
            "type":"Food & Drink"
        }
    ],
    "sg:menulink":"http://www.allmenus.com/ca/san-diego/219351-lotus-thai/menu/",
    "sg:phone":"+1 619 299 8272",
    "sg:postcode":"92103",
    "sg:province":"CA",
    "sg:tags":[
        "thai",
        "asian"
    ],
    "wof:name":"Lotus Thai",
    "wof:placetype":"venue"
},
  "geometry": {"coordinates":[-117.159199,32.746341],"type":"Point"}
}