{
  "type": "Feature",
  "properties": {
    "addr:full":"1381 Westwood Blvd Los Angeles CA 90024",
    "addr:housenumber":"1381",
    "addr:postcode":"90024",
    "addr:street":"Westwood Blvd",
    "iso:country":"US",
    "sg:address":"1381 Westwood Blvd",
    "sg:city":"Los Angeles",
    "sg:classifiers":[
        {
            "category":"Communications",
            "subcategory":"Film & Video Production",
            "type":"Services"
        }
    ],
    "sg:phone":"+1 310 444 9220",
    "sg:postcode":"90024",
    "sg:province":"CA",
    "sg:tags":[
        "duplication",
        "tape"
    ],
    "wof:name":"Caro Photography & Video",
    "wof:placetype":"venue"
},
  "geometry": {"coordinates":[-118.442078,34.055831],"type":"Point"}
}