{
  "type": "Feature",
  "properties": {
    "iso:country":"US",
    "sg:address":"591 S Jefferson St",
    "sg:city":"Napa",
    "sg:classifiers":[
        {
            "category":"Retail",
            "subcategory":"Car Wash",
            "type":"Services"
        }
    ],
    "sg:phone":"+1 707 258 2845",
    "sg:postcode":"94559",
    "sg:province":"CA",
    "sg:tags":[
        "polishing",
        "washing"
    ],
    "wof:name":"Elephant Car Wash",
    "wof:placetype":"venue"
},
  "geometry": {"coordinates":[-122.29382099999999,38.283034],"type":"Point"}
}