{
  "type": "Feature",
  "properties": {
    "iso:country":"US",
    "sg:address":"12265 World Trade Dr",
    "sg:city":"San Diego",
    "sg:classifiers":[
        {
            "category":"Home & Garden",
            "subcategory":"Furniture",
            "type":"Retail Goods"
        }
    ],
    "sg:phone":"+1 858 385 9400",
    "sg:postcode":"92128",
    "sg:province":"CA",
    "wof:name":"Roomors Home Furnishing",
    "wof:placetype":"venue"
},
  "geometry": {"coordinates":[-117.072746,32.987723],"type":"Point"}
}