{
  "type": "Feature",
  "properties": {
    "iso:country":"US",
    "sg:address":"32494 Rd 132",
    "sg:city":"Visalia",
    "sg:classifiers":[
        {
            "category":"Farming",
            "subcategory":"Orchard",
            "type":"Manufacturing & Wholesale Goods"
        }
    ],
    "sg:phone":"+1 559 732 7428",
    "sg:postcode":"93292",
    "sg:province":"CA",
    "sg:tags":[
        "citrus",
        "grove",
        "fruit"
    ],
    "wof:name":"Andy Verhoeven",
    "wof:placetype":"venue"
},
  "geometry": {"coordinates":[-119.2787,36.375292],"type":"Point"}
}