{
  "type": "Feature",
  "properties": {
    "iso:country":"US",
    "sg:address":"1752 E Ave J",
    "sg:city":"Lancaster",
    "sg:classifiers":[
        {
            "category":"Professional",
            "type":"Services"
        }
    ],
    "sg:phone":"+1 661 946 6303",
    "sg:postcode":"93535",
    "sg:province":"CA",
    "wof:name":"Progress Plus",
    "wof:placetype":"venue"
},
  "geometry": {"coordinates":[-118.098439,34.689575],"type":"Point"}
}