{
  "type": "Feature",
  "properties": {
    "iso:country":"US",
    "sg:address":"1884 W 11th St",
    "sg:city":"Tracy",
    "sg:classifiers":[
        {
            "category":"Education",
            "subcategory":"Special Training",
            "type":"Public Place"
        }
    ],
    "sg:phone":"+1 209 833 9400",
    "sg:postcode":"95376",
    "sg:province":"CA",
    "sg:tags":[
        "tutoring"
    ],
    "wof:name":"Tracy Kumon Ctr",
    "wof:placetype":"venue"
},
  "geometry": {"coordinates":[-121.446326,37.739514],"type":"Point"}
}