{
  "type": "Feature",
  "properties": {
    "addr:full":"616 Ramona St Palo Alto CA 94301",
    "addr:housenumber":"616",
    "addr:postcode":"94301",
    "addr:street":"Ramona St",
    "iso:country":"US",
    "sg:address":"616 Ramona St",
    "sg:city":"Palo Alto",
    "sg:classifiers":[
        {
            "category":"Professional",
            "subcategory":"Accounting & Tax Preparation",
            "type":"Services"
        }
    ],
    "sg:phone":"+1 650 326 5477",
    "sg:postcode":"94301",
    "sg:province":"CA",
    "sg:tags":[
        "return",
        "filing"
    ],
    "wof:name":"AAAA Insurance & Tax",
    "wof:placetype":"venue"
},
  "geometry": {"coordinates":[-122.159886,37.443777],"type":"Point"}
}