{
  "type": "Feature",
  "properties": {
    "addr:full":"3065 Porter St Soquel CA 95073",
    "addr:housenumber":"3065",
    "addr:postcode":"95073",
    "addr:street":"Porter St",
    "iso:country":"US",
    "sg:address":"3065 Porter St",
    "sg:city":"Soquel",
    "sg:classifiers":[
        {
            "category":"Health Services",
            "subcategory":"Chiropractor",
            "type":"Services"
        }
    ],
    "sg:phone":"+1 831 477 1830",
    "sg:postcode":"95073",
    "sg:province":"CA",
    "wof:name":"Homer Frances DC",
    "wof:placetype":"venue"
},
  "geometry": {"coordinates":[-121.95700100000001,36.989201],"type":"Point"}
}