{
  "type": "Feature",
  "properties": {
    "addr:full":"3031 Telegraph Ave Ste 241 Berkeley CA 94705",
    "addr:housenumber":"3031",
    "addr:postcode":"94705",
    "addr:street":"Telegraph Ave Ste 241",
    "iso:country":"US",
    "sg:address":"3031 Telegraph Ave Ste 241",
    "sg:city":"Berkeley",
    "sg:classifiers":[
        {
            "category":"Health Services",
            "subcategory":"Doctor",
            "type":"Services"
        }
    ],
    "sg:phone":"+1 510 549 2038",
    "sg:postcode":"94705",
    "sg:province":"CA",
    "sg:tags":[
        "physician",
        "surgeons",
        "medicine",
        "surgeon",
        "rehabilitation",
        "physical"
    ],
    "wof:name":"Pico Elaine L Md",
    "wof:placetype":"venue"
},
  "geometry": {"coordinates":[-122.259804,37.85519],"type":"Point"}
}