{
  "type": "Feature",
  "properties": {
    "iso:country":"US",
    "sg:address":"18601 Amate Cir",
    "sg:city":"Villa Park",
    "sg:classifiers":[
        {
            "category":"Professional",
            "subcategory":"Business Services",
            "type":"Services"
        },
        {
            "category":"Wholesale",
            "subcategory":"Home Furnishings",
            "type":"Manufacturing & Wholesale Goods"
        }
    ],
    "sg:phone":"+1 714 637 4866",
    "sg:postcode":"92861",
    "sg:province":"CA",
    "sg:tags":[
        "interior",
        "consultant",
        "design",
        "decorator"
    ],
    "wof:name":"Acquisitions",
    "wof:placetype":"venue"
},
  "geometry": {"coordinates":[-117.807861,33.817483],"type":"Point"}
}