{
  "type": "Feature",
  "properties": {
    "iso:country":"US",
    "sg:address":"140 Foothill Blvd",
    "sg:city":"La Canada Fltrdg",
    "sg:classifiers":[
        {
            "category":"Social Services",
            "subcategory":"Child Care",
            "type":"Services"
        }
    ],
    "sg:phone":"+1 818 354 3418",
    "sg:postcode":"91011",
    "sg:province":"CA",
    "wof:name":"Child Education CENTER-Jpl",
    "wof:placetype":"venue"
},
  "geometry": {"coordinates":[-118.181591,34.19573],"type":"Point"}
}