{
  "type": "Feature",
  "properties": {
    "iso:country":"US",
    "sg:address":"2800 W March Ln",
    "sg:city":"Stockton",
    "sg:classifiers":[
        {
            "category":"Restaurant",
            "type":"Food & Drink"
        }
    ],
    "sg:phone":"+1 209 957 3989",
    "sg:postcode":"95219",
    "sg:province":"CA",
    "sg:tags":[
        "style",
        "family"
    ],
    "wof:name":"Lodi Moo Moo's Corporate Office",
    "wof:placetype":"venue"
},
  "geometry": {"coordinates":[-121.346127,37.984302],"type":"Point"}
}