{
  "type": "Feature",
  "properties": {
    "iso:country":"US",
    "sg:address":"27019 Helmond Dr",
    "sg:city":"Agoura Hills",
    "sg:classifiers":[
        {
            "category":"Professional",
            "subcategory":"Lawyer & Legal Services",
            "type":"Services"
        }
    ],
    "sg:phone":"+1 818 991 1659",
    "sg:postcode":"91301",
    "sg:province":"CA",
    "wof:name":"Law Offices Of John DeBrauwere",
    "wof:placetype":"venue"
},
  "geometry": {"coordinates":[-118.714206,34.142506],"type":"Point"}
}