{
  "type": "Feature",
  "properties": {
    "addr:full":"De Anza College 21250 Stevens Creek Blvd Cupertino CA 95014",
    "addr:housenumber":"21250",
    "addr:postcode":"95014",
    "addr:street":"De;Stevens Creek Blvd",
    "iso:country":"US",
    "sg:address":"De Anza College 21250 Stevens Creek Blvd",
    "sg:city":"Cupertino",
    "sg:classifiers":[
        {
            "category":"Museum",
            "type":"Entertainment"
        }
    ],
    "sg:phone":"+1 408 864 8814",
    "sg:postcode":"95014",
    "sg:province":"CA",
    "sg:website":"www.planetarium.fhda.edu",
    "wof:name":"Fujitsu Planetarium",
    "wof:placetype":"venue"
},
  "geometry": {"coordinates":[-122.04461000000001,37.319267],"type":"Point"}
}