{
  "type": "Feature",
  "properties": {
    "iso:country":"US",
    "sg:address":"3414 W Ball Rd # B",
    "sg:city":"Anaheim",
    "sg:classifiers":[
        {
            "category":"Cinema",
            "subcategory":"Movie Rental",
            "type":"Entertainment"
        }
    ],
    "sg:phone":"+1 714 828 6644",
    "sg:postcode":"92804",
    "sg:province":"CA",
    "sg:tags":[
        "game",
        "video"
    ],
    "wof:name":"Omni Video",
    "wof:placetype":"venue"
},
  "geometry": {"coordinates":[-118.008754,33.816773],"type":"Point"}
}