{
  "type": "Feature",
  "properties": {
    "iso:country":"US",
    "sg:address":"3435 Ocean Park Blvd",
    "sg:city":"Santa Monica",
    "sg:classifiers":[
        {
            "category":"Freight",
            "type":"Transportation"
        }
    ],
    "sg:phone":"+1 310 470 6844",
    "sg:postcode":"90405",
    "sg:province":"CA",
    "sg:tags":[
        "courier"
    ],
    "wof:name":"Super Cartero",
    "wof:placetype":"venue"
},
  "geometry": {"coordinates":[-118.449147,34.022815],"type":"Point"}
}