{
  "type": "Feature",
  "properties": {
    "iso:country":"US",
    "sg:address":"52 Mission Cir",
    "sg:city":"Santa Rosa",
    "sg:classifiers":[
        {
            "category":"Shopping",
            "subcategory":"Florist",
            "type":"Retail Goods"
        }
    ],
    "sg:phone":"+1 707 539 6140",
    "sg:postcode":"95409",
    "sg:province":"CA",
    "sg:website":"www.windingrose.com",
    "wof:name":"Winding Rose Florist & Gifts",
    "wof:placetype":"venue"
},
  "geometry": {"coordinates":[-122.674253,38.457432],"type":"Point"}
}