{
  "type": "Feature",
  "properties": {
    "iso:country":"US",
    "sg:address":"1953 Lake Shore Ave",
    "sg:city":"Los Angeles",
    "sg:classifiers":[
        {
            "category":"Social Services",
            "subcategory":"Child Care",
            "type":"Services"
        },
        {
            "category":"Education",
            "subcategory":"Preschool",
            "type":"Public Place"
        }
    ],
    "sg:phone":"+1 323 660 9665",
    "sg:postcode":"90039",
    "sg:province":"CA",
    "sg:tags":[
        "day"
    ],
    "sg:website":"www.ourplaygroup.org",
    "wof:name":"Echo-Park-Silver Lake People's Child Care Center",
    "wof:placetype":"venue"
},
  "geometry": {"coordinates":[-118.254997,34.089298],"type":"Point"}
}