{
  "type": "Feature",
  "properties": {
    "iso:country":"US",
    "sg:address":"144 Walnut Ave",
    "sg:city":"Santa Cruz",
    "sg:classifiers":[
        {
            "category":"Home & Garden",
            "subcategory":"Building Materials",
            "type":"Retail Goods"
        }
    ],
    "sg:phone":"+1 831 459 0505",
    "sg:postcode":"95060",
    "sg:province":"CA",
    "sg:tags":[
        "windows"
    ],
    "wof:name":"Tose Supply Co",
    "wof:placetype":"venue"
},
  "geometry": {"coordinates":[-122.028063,36.973203],"type":"Point"}
}