{
  "type": "Feature",
  "properties": {
    "addr:full":"1121 7th St Oakland CA 94607",
    "addr:housenumber":"1121",
    "addr:postcode":"94607",
    "addr:street":"7Th St",
    "iso:country":"US",
    "sg:address":"1121 7th St",
    "sg:city":"Oakland",
    "sg:classifiers":[
        {
            "category":"Transit Center",
            "subcategory":"Freight",
            "type":"Transportation"
        },
        {
            "category":"Freight",
            "type":"Transportation"
        }
    ],
    "sg:phone":"+1 510 433 1020",
    "sg:postcode":"94607",
    "sg:province":"CA",
    "sg:tags":[
        "trucking-motor",
        "trucking"
    ],
    "sg:website":"http://www.noblepitts.com",
    "wof:name":"Mason Dixon Intermodal, Inc.",
    "wof:placetype":"venue"
},
  "geometry": {"coordinates":[-122.287558,37.80372],"type":"Point"}
}