{
  "type": "Feature",
  "properties": {
    "iso:country":"US",
    "sg:address":"3101 National Ave",
    "sg:city":"San Diego",
    "sg:classifiers":[
        {
            "category":"Food & Beverages",
            "subcategory":"Liquor & Beverages",
            "type":"Retail Goods"
        }
    ],
    "sg:phone":"+1 619 235 6028",
    "sg:postcode":"92113",
    "sg:province":"CA",
    "wof:name":"Ideal Market",
    "wof:placetype":"venue"
},
  "geometry": {"coordinates":[-117.12532,32.695969],"type":"Point"}
}