{
  "type": "Feature",
  "properties": {
    "iso:country":"US",
    "sg:address":"1701 Skyway Dr",
    "sg:city":"Bakersfield",
    "sg:classifiers":[
        {
            "category":"Manufacturing",
            "subcategory":"Petroleum Products",
            "type":"Manufacturing & Wholesale Goods"
        }
    ],
    "sg:phone":"+1 661 393 6061",
    "sg:postcode":"93308",
    "sg:province":"CA",
    "sg:tags":[
        "oil",
        "refiner"
    ],
    "wof:name":"Nevada Refining Co",
    "wof:placetype":"venue"
},
  "geometry": {"coordinates":[-119.049724,35.433625],"type":"Point"}
}