{
  "type": "Feature",
  "properties": {
    "addr:full":"2716 Ocean Park Blvd Santa Monica CA 90405",
    "addr:housenumber":"2716",
    "addr:postcode":"90405",
    "addr:street":"Ocean Park Blvd",
    "iso:country":"US",
    "sg:address":"2716 Ocean Park Blvd",
    "sg:city":"Santa Monica",
    "sg:classifiers":[
        {
            "category":"Professional",
            "type":"Services"
        }
    ],
    "sg:phone":"+1 310 450 3100",
    "sg:postcode":"90405",
    "sg:province":"CA",
    "wof:name":"Kanasawa Inc",
    "wof:placetype":"venue"
},
  "geometry": {"coordinates":[-118.456295,34.018402],"type":"Point"}
}