{
  "type": "Feature",
  "properties": {
    "addr:full":"18613 Orange St Bloomington CA 92316",
    "addr:housenumber":"18613",
    "addr:postcode":"92316",
    "addr:street":"Orange St",
    "iso:country":"US",
    "sg:address":"18613 Orange St",
    "sg:city":"Bloomington",
    "sg:classifiers":[
        {
            "category":"Real Estate",
            "subcategory":"Real Estate Agent",
            "type":"Services"
        }
    ],
    "sg:phone":"+1 909 820 6400",
    "sg:postcode":"92316",
    "sg:province":"CA",
    "wof:name":"Metzgar & Assoc Real Est Svc",
    "wof:placetype":"venue"
},
  "geometry": {"coordinates":[-117.39838899999999,34.064929],"type":"Point"}
}