{
  "type": "Feature",
  "properties": {
    "addr:full":"2560 N Beachwood Dr Los Angeles CA 90068",
    "addr:housenumber":"2560",
    "addr:postcode":"90068",
    "addr:street":"N Beachwood Dr",
    "iso:country":"US",
    "sg:address":"2560 N Beachwood Dr",
    "sg:city":"Los Angeles",
    "sg:classifiers":[
        {
            "category":"Organizations",
            "subcategory":"Religious Organization",
            "type":"Services"
        }
    ],
    "sg:phone":"+1 323 461 2559",
    "sg:postcode":"90068",
    "sg:province":"CA",
    "wof:name":"Besant Lodge",
    "wof:placetype":"venue"
},
  "geometry": {"coordinates":[-118.320999,34.1166],"type":"Point"}
}