{
  "type": "Feature",
  "properties": {
    "addr:full":"3896 Vineyard Ave Pleasanton CA 94566",
    "addr:housenumber":"3896",
    "addr:postcode":"94566",
    "addr:street":"Vineyard Ave",
    "iso:country":"US",
    "sg:address":"3896 Vineyard Ave",
    "sg:city":"Pleasanton",
    "sg:classifiers":[
        {
            "category":"Building & Trades",
            "subcategory":"Construction",
            "type":"Services"
        }
    ],
    "sg:phone":"+1 925 461 0516",
    "sg:postcode":"94566",
    "sg:province":"CA",
    "sg:tags":[
        "painter"
    ],
    "wof:name":"S R Painting",
    "wof:placetype":"venue"
},
  "geometry": {"coordinates":[-121.86355500000001,37.662977],"type":"Point"}
}