{
  "type": "Feature",
  "properties": {
    "iso:country":"US",
    "sfac:artist":"Piazzoni, Gottardo Fidele Ponziano",
    "sfac:created_at":"1932?",
    "sfac:credit_line":"Purchased for the San Francisco Main Library",
    "sfac:display_dimensions":"6' X 11'",
    "sfac:location_description":"Museum : deYoung Museum",
    "sfac:medium":"Oil on canvas",
    "sfac:revision":"2-da741f10dd7934e2acd3ca27b6cdd579",
    "sfac:title":"Night",
    "wof:name":"Night",
    "wof:placetype":"venue"
},
  "geometry": {"coordinates":[-122.467485,37.771673],"type":"Point"}
}