{
  "type": "Feature",
  "properties": {
    "addr:full":"7001 White Ln Bakersfield CA 93309",
    "addr:housenumber":"7001",
    "addr:postcode":"93309",
    "addr:street":"White Ln",
    "iso:country":"US",
    "sg:address":"7001 White Ln",
    "sg:city":"Bakersfield",
    "sg:classifiers":[
        {
            "category":"Retail",
            "subcategory":"Auto Repair",
            "type":"Services"
        }
    ],
    "sg:phone":"+1 661 834 7664",
    "sg:postcode":"93309",
    "sg:province":"CA",
    "sg:tags":[
        "automobile",
        "diagnostic"
    ],
    "wof:name":"Speedy Smog",
    "wof:placetype":"venue"
},
  "geometry": {"coordinates":[-119.082747,35.318145],"type":"Point"}
}