{
  "type": "Feature",
  "properties": {
    "addr:full":"152 E. Dana Street Mountain View CA 94041",
    "addr:housenumber":"152",
    "addr:postcode":"94041",
    "addr:street":"E. Dana Street",
    "iso:country":"US",
    "sg:address":"152 E. Dana Street",
    "sg:city":"Mountain View",
    "sg:classifiers":[
        {
            "category":"Professional",
            "type":"Services"
        },
        {
            "category":"Social Services",
            "subcategory":"Child Care",
            "type":"Services"
        }
    ],
    "sg:phone":"+1 650 209 4846",
    "sg:postcode":"94041",
    "sg:province":"CA",
    "sg:tags":[
        "day"
    ],
    "sg:website":"www.cubesandcrayons.com",
    "wof:name":"Cubes & Crayons",
    "wof:placetype":"venue"
},
  "geometry": {"coordinates":[-122.066463,37.387026],"type":"Point"}
}