{
  "type": "Feature",
  "properties": {
    "addr:full":"1426 Carrousel Ln Sacramento CA 95822",
    "addr:housenumber":"1426",
    "addr:postcode":"95822",
    "addr:street":"Carrousel Ln",
    "iso:country":"US",
    "sg:address":"1426 Carrousel Ln",
    "sg:city":"Sacramento",
    "sg:classifiers":[
        {
            "category":"Manufacturing",
            "subcategory":"Pottery",
            "type":"Manufacturing & Wholesale Goods"
        }
    ],
    "sg:phone":"+1 916 452 7181",
    "sg:postcode":"95822",
    "sg:province":"CA",
    "sg:tags":[
        "pottery-wholesale",
        "manufacturer"
    ],
    "wof:name":"Panama Pottery",
    "wof:placetype":"venue"
},
  "geometry": {"coordinates":[-121.503114,38.535884],"type":"Point"}
}