{
  "type": "Feature",
  "properties": {
    "addr:full":"17150 Franchi Pl Grass Valley CA 95949",
    "addr:housenumber":"17150",
    "addr:postcode":"95949",
    "addr:street":"Franchi Pl",
    "iso:country":"US",
    "sg:address":"17150 Franchi Pl",
    "sg:city":"Grass Valley",
    "sg:classifiers":[
        {
            "category":"Building & Trades",
            "subcategory":"Landscaping Services",
            "type":"Services"
        }
    ],
    "sg:phone":"+1 530 268 0807",
    "sg:postcode":"95949",
    "sg:province":"CA",
    "sg:tags":[
        "landscape",
        "contractor"
    ],
    "wof:name":"Curb Appeal",
    "wof:placetype":"venue"
},
  "geometry": {"coordinates":[-121.13167300000001,39.062535],"type":"Point"}
}