{
  "type": "Feature",
  "properties": {
    "iso:country":"US",
    "sg:address":"3969 Pleasant Hill Ln",
    "sg:city":"Rancho Cordova",
    "sg:classifiers":[
        {
            "category":"Professional",
            "subcategory":"Management & Consulting",
            "type":"Services"
        }
    ],
    "sg:phone":"+1 916 351 0600",
    "sg:postcode":"95742",
    "sg:province":"CA",
    "sg:tags":[
        "consultant"
    ],
    "wof:name":"Bualco Consulting",
    "wof:placetype":"venue"
},
  "geometry": {"coordinates":[-121.159645,38.557947],"type":"Point"}
}