{
  "type": "Feature",
  "properties": {
    "iso:country":"US",
    "sg:address":"2560 Teepee Dr",
    "sg:city":"Stockton",
    "sg:classifiers":[
        {
            "category":"Shopping",
            "subcategory":"Computers & Home Electronics",
            "type":"Retail Goods"
        }
    ],
    "sg:phone":"+1 209 547 9909",
    "sg:postcode":"95205",
    "sg:province":"CA",
    "sg:tags":[
        "equipment",
        "satellite",
        "system",
        "antenna"
    ],
    "wof:name":"Valley Reception",
    "wof:placetype":"venue"
},
  "geometry": {"coordinates":[-121.252326,37.985361],"type":"Point"}
}