{
  "type": "Feature",
  "properties": {
    "addr:full":"10205 Riverside Dr Los Angeles CA 91602",
    "addr:housenumber":"10205",
    "addr:postcode":"91602",
    "addr:street":"Riverside Dr",
    "iso:country":"US",
    "sg:address":"10205 Riverside Dr",
    "sg:city":"Los Angeles",
    "sg:classifiers":[
        {
            "category":"Real Estate",
            "subcategory":"Real Estate Agent",
            "type":"Services"
        }
    ],
    "sg:phone":"+1 818 481 8643",
    "sg:postcode":"91602",
    "sg:province":"CA",
    "wof:name":"Jon Molin Ramsey Shilling Associates",
    "wof:placetype":"venue"
},
  "geometry": {"coordinates":[-118.35288300000001,34.152228],"type":"Point"}
}