{
  "type": "Feature",
  "properties": {
    "iso:country":"US",
    "sg:address":"6155 Palm Ave",
    "sg:city":"San Bernardino",
    "sg:classifiers":[
        {
            "category":"Social Services",
            "type":"Services"
        }
    ],
    "sg:phone":"+1 909 887 6960",
    "sg:postcode":"92407",
    "sg:province":"CA",
    "sg:tags":[
        "counselor",
        "marriage",
        "family"
    ],
    "wof:name":"Braun Family Svc",
    "wof:placetype":"venue"
},
  "geometry": {"coordinates":[-117.36055,34.192226],"type":"Point"}
}