{
  "type": "Feature",
  "properties": {
    "addr:full":"915 Howard Ave Burlingame CA 94010",
    "addr:housenumber":"915",
    "addr:postcode":"94010",
    "addr:street":"Howard Ave",
    "iso:country":"US",
    "sg:address":"915 Howard Ave",
    "sg:city":"Burlingame",
    "sg:classifiers":[
        {
            "category":"Professional",
            "type":"Services"
        }
    ],
    "sg:phone":"+1 650 347 7102",
    "sg:postcode":"94010",
    "sg:province":"CA",
    "wof:name":"American Hellenic Veteran",
    "wof:placetype":"venue"
},
  "geometry": {"coordinates":[-122.342015,37.579734],"type":"Point"}
}