{
  "type": "Feature",
  "properties": {
    "iso:country":"US",
    "sg:address":"375 Bristol Street",
    "sg:city":"Costa Mesa",
    "sg:classifiers":[
        {
            "category":"Professional",
            "subcategory":"Computer Services",
            "type":"Services"
        }
    ],
    "sg:phone":"+1 714 966 9800",
    "sg:postcode":"92626",
    "sg:province":"CA",
    "sg:tags":[
        "stereo",
        "installation"
    ],
    "wof:name":"Wave Auto Sound",
    "wof:placetype":"venue"
},
  "geometry": {"coordinates":[-117.880689,33.667933],"type":"Point"}
}