{
  "type": "Feature",
  "properties": {
    "addr:full":"10592 Nambe Rd Apple Valley CA 92308",
    "addr:housenumber":"10592",
    "addr:postcode":"92308",
    "addr:street":"Nambe Rd",
    "iso:country":"US",
    "sg:address":"10592 Nambe Rd",
    "sg:city":"Apple Valley",
    "sg:classifiers":[
        {
            "category":"Retail",
            "subcategory":"Repair Shop",
            "type":"Services"
        }
    ],
    "sg:phone":"+1 760 247 3085",
    "sg:postcode":"92308",
    "sg:province":"CA",
    "sg:tags":[
        "equipment",
        "conditioning",
        "air"
    ],
    "wof:name":"Ted's Air Conditioning & Htng",
    "wof:placetype":"venue"
},
  "geometry": {"coordinates":[-117.183812,34.44401],"type":"Point"}
}