{
  "type": "Feature",
  "properties": {
    "acgov:api":"784.0",
    "acgov:type":"ES",
    "addr:full":"800 Marylin Avenue Livermore CA",
    "wof:categories":[
        "education_and_religion:education=school"
    ],
    "wof:name":"Marylin Avenue Elementary",
    "wof:placetype":"venue"
},
  "geometry": {"coordinates":[-121.78666331744222,37.68400574174795],"type":"Point"}
}