{
  "type": "Feature",
  "properties": {
    "iso:country":"US",
    "sg:address":"10651 Eastborne Ave",
    "sg:city":"Los Angeles",
    "sg:classifiers":[
        {
            "category":"Freight",
            "type":"Transportation"
        }
    ],
    "sg:phone":"+1 310 470 0896",
    "sg:postcode":"90024",
    "sg:province":"CA",
    "sg:tags":[
        "operator",
        "trucking"
    ],
    "wof:name":"Krupatrans",
    "wof:placetype":"venue"
},
  "geometry": {"coordinates":[-118.43136199999999,34.05402],"type":"Point"}
}