{
  "type": "Feature",
  "properties": {
    "iso:country":"US",
    "sg:address":"3340 Airport Rd",
    "sg:city":"Paso Robles",
    "sg:classifiers":[
        {
            "category":"Manufacturing",
            "subcategory":"Buildings",
            "type":"Manufacturing & Wholesale Goods"
        }
    ],
    "sg:phone":"+1 805 712 4307",
    "sg:postcode":"93446",
    "sg:province":"CA",
    "sg:tags":[
        "home",
        "log",
        "cabin"
    ],
    "wof:name":"East Wicker Way",
    "wof:placetype":"venue"
},
  "geometry": {"coordinates":[-120.640945,35.649067],"type":"Point"}
}