{
  "type": "Feature",
  "properties": {
    "iso:country":"US",
    "sg:address":"2710 Capitol Ave",
    "sg:city":"Sacramento",
    "sg:classifiers":[
        {
            "category":"Health Services",
            "subcategory":"Doctor",
            "type":"Services"
        }
    ],
    "sg:phone":"+1 916 448 2261",
    "sg:postcode":"95816",
    "sg:province":"CA",
    "wof:name":"Metts Julius F Md",
    "wof:placetype":"venue"
},
  "geometry": {"coordinates":[-121.47189,38.570703],"type":"Point"}
}