{
  "type": "Feature",
  "properties": {
    "iso:country":"US",
    "sg:address":"11950 Ventura Blvd",
    "sg:city":"Studio City",
    "sg:classifiers":[
        {
            "category":"Real Estate",
            "subcategory":"Real Estate Agent",
            "type":"Services"
        }
    ],
    "sg:phone":"+1 818 783 0133",
    "sg:postcode":"91604",
    "sg:province":"CA",
    "sg:tags":[
        "broker"
    ],
    "wof:name":"Terman Realty",
    "wof:placetype":"venue"
},
  "geometry": {"coordinates":[-118.392043,34.143094],"type":"Point"}
}