{
  "type": "Feature",
  "properties": {
    "iso:country":"US",
    "sg:address":"14190 Firestone Blvd",
    "sg:city":"Santa Fe Springs",
    "sg:classifiers":[
        {
            "category":"Professional",
            "subcategory":"Computer Services",
            "type":"Services"
        }
    ],
    "sg:phone":"+1 562 926 7555",
    "sg:postcode":"90670",
    "sg:province":"CA",
    "sg:tags":[
        "repair"
    ],
    "wof:name":"Think Computers",
    "wof:placetype":"venue"
},
  "geometry": {"coordinates":[-118.03159,33.885537],"type":"Point"}
}