{
  "type": "Feature",
  "properties": {
    "addr:full":"27667 Bouquet Canyon Rd Santa Clarita CA 91350",
    "addr:housenumber":"27667",
    "addr:postcode":"91350",
    "addr:street":"Bouquet Canyon Rd",
    "iso:country":"US",
    "sg:address":"27667 Bouquet Canyon Rd",
    "sg:city":"Santa Clarita",
    "sg:classifiers":[
        {
            "category":"Coffee & Tea",
            "type":"Food & Drink"
        }
    ],
    "sg:menulink":"http://www.allmenus.com/ca/newhall/116614-starbucks-coffee/menu/",
    "sg:phone":"+1 661 263 9681",
    "sg:postcode":"91350",
    "sg:province":"CA",
    "sg:tags":[
        "american"
    ],
    "wof:name":"Starbucks Coffee",
    "wof:placetype":"venue"
},
  "geometry": {"coordinates":[-118.51060200000001,34.443189],"type":"Point"}
}