{
  "type": "Feature",
  "properties": {
    "addr:full":"5900 Rodeo Rd Los Angeles CA 90016",
    "addr:housenumber":"5900",
    "addr:postcode":"90016",
    "addr:street":"Rodeo Rd",
    "iso:country":"US",
    "sg:address":"5900 Rodeo Rd",
    "sg:city":"Los Angeles",
    "sg:classifiers":[
        {
            "category":"Building & Trades",
            "subcategory":"Construction",
            "type":"Services"
        }
    ],
    "sg:phone":"+1 310 842 8560",
    "sg:postcode":"90016",
    "sg:province":"CA",
    "sg:tags":[
        "general",
        "contractor"
    ],
    "wof:name":"Hollister Construction Co",
    "wof:placetype":"venue"
},
  "geometry": {"coordinates":[-118.37626899999999,34.021837],"type":"Point"}
}