{
  "type": "Feature",
  "properties": {
    "addr:full":"1281 University Ave San Diego CA 92103",
    "addr:housenumber":"1281",
    "addr:postcode":"92103",
    "addr:street":"University Ave",
    "iso:country":"US",
    "sg:address":"1281 University Ave",
    "sg:city":"San Diego",
    "sg:classifiers":[
        {
            "category":"Personal",
            "type":"Services"
        }
    ],
    "sg:phone":"+1 619 237 0167",
    "sg:postcode":"92103",
    "sg:province":"CA",
    "sg:tags":[
        "therapist",
        "massage"
    ],
    "wof:name":"Magickal Massage",
    "wof:placetype":"venue"
},
  "geometry": {"coordinates":[-117.152053,32.748426],"type":"Point"}
}