{
  "type": "Feature",
  "properties": {
    "iso:country":"US",
    "sg:address":"1042 Walker Ave",
    "sg:city":"Oakland",
    "sg:classifiers":[
        {
            "category":"Social Services",
            "type":"Services"
        },
        {
            "category":"Professional",
            "subcategory":"Employment Agencies",
            "type":"Services"
        }
    ],
    "sg:phone":"+1 510 839 2126",
    "sg:postcode":"94610",
    "sg:province":"CA",
    "sg:tags":[
        "workers'",
        "placement",
        "volunteer"
    ],
    "wof:name":"Wilson Wherewithal Foundation",
    "wof:placetype":"venue"
},
  "geometry": {"coordinates":[-122.244118,37.816928],"type":"Point"}
}