{
  "type": "Feature",
  "properties": {
    "addr:full":"1175 Industrial Ave Escondido CA 92029",
    "addr:housenumber":"1175",
    "addr:postcode":"92029",
    "addr:street":"Industrial Ave",
    "iso:country":"US",
    "sg:address":"1175 Industrial Ave",
    "sg:city":"Escondido",
    "sg:classifiers":[
        {
            "category":"Wholesale",
            "subcategory":"Non-durable Goods",
            "type":"Manufacturing & Wholesale Goods"
        }
    ],
    "sg:phone":"+1 760 747 0513",
    "sg:postcode":"92029",
    "sg:province":"CA",
    "sg:tags":[
        "aquarium"
    ],
    "sg:website":"www.seawatervisions.com",
    "wof:name":"Sea Water Visions",
    "wof:placetype":"venue"
},
  "geometry": {"coordinates":[-117.104901,33.11871],"type":"Point"}
}