{
  "type": "Feature",
  "properties": {
    "iso:country":"US",
    "sg:address":"406 W Dana St",
    "sg:city":"Mountain View",
    "sg:classifiers":[
        {
            "category":"Wholesale",
            "subcategory":"Durable Goods & Equipment",
            "type":"Manufacturing & Wholesale Goods"
        }
    ],
    "sg:phone":"+1 650 575 4919",
    "sg:postcode":"94041",
    "sg:province":"CA",
    "sg:tags":[
        "laser"
    ],
    "sg:website":"www.laserk.com",
    "wof:name":"Laser Kinetics Inc",
    "wof:placetype":"venue"
},
  "geometry": {"coordinates":[-122.076374,37.3911],"type":"Point"}
}