{
  "type": "Feature",
  "properties": {
    "addr:full":"59704 State Rte 70 Cromberg CA 96103",
    "addr:housenumber":"59704",
    "addr:postcode":"96103",
    "addr:street":"State Rte 70",
    "iso:country":"US",
    "sg:address":"59704 State Rte 70",
    "sg:city":"Cromberg",
    "sg:classifiers":[
        {
            "category":"Travel",
            "subcategory":"Campground",
            "type":"Entertainment"
        }
    ],
    "sg:phone":"+1 530 836 2426",
    "sg:postcode":"96103",
    "sg:province":"CA",
    "wof:name":"Golden Coach Rv Resort",
    "wof:placetype":"venue"
},
  "geometry": {"coordinates":[-120.684899,39.854826],"type":"Point"}
}