{
  "type": "Feature",
  "properties": {
    "addr:full":"1000 Universal Studios Blvd Ste 222 North Hollywood CA 91608",
    "addr:housenumber":"1000",
    "addr:postcode":"91608",
    "addr:street":"Universal Studios Blvd Ste 222",
    "iso:country":"US",
    "sg:address":"1000 Universal Studios Blvd Ste 222",
    "sg:city":"North Hollywood",
    "sg:classifiers":[
        {
            "category":"Arts & Performance",
            "subcategory":"Comedy Club",
            "type":"Entertainment"
        }
    ],
    "sg:phone":"+1 818 824 6545",
    "sg:postcode":"91608",
    "sg:province":"CA",
    "sg:website":"www.thejonlovitzcomedyclub.com",
    "wof:name":"The Jon Lovitz Comedy Club",
    "wof:placetype":"venue"
},
  "geometry": {"coordinates":[-118.351613,34.134345],"type":"Point"}
}