{
  "type": "Feature",
  "properties": {
    "iso:country":"US",
    "sg:address":"7746 Church St",
    "sg:city":"Yucca Valley",
    "sg:classifiers":[
        {
            "category":"Recreation",
            "type":"Entertainment"
        }
    ],
    "sg:phone":"+1 760 365 8112",
    "sg:postcode":"92284",
    "sg:province":"CA",
    "sg:tags":[
        "instruction",
        "gymnastic"
    ],
    "wof:name":"Yucca Valley Gymnastics",
    "wof:placetype":"venue"
},
  "geometry": {"coordinates":[-116.436076,34.111258],"type":"Point"}
}