{
  "type": "Feature",
  "properties": {
    "iso:country":"US",
    "sg:address":"6064 E Hackamore Ln",
    "sg:city":"Anaheim",
    "sg:classifiers":[
        {
            "category":"Professional",
            "subcategory":"Accounting & Tax Preparation",
            "type":"Services"
        }
    ],
    "sg:phone":"+1 714 921 3109",
    "sg:postcode":"92807",
    "sg:province":"CA",
    "sg:tags":[
        "billing"
    ],
    "wof:name":"Quality Medical Billing Svc",
    "wof:placetype":"venue"
},
  "geometry": {"coordinates":[-117.780144,33.837358],"type":"Point"}
}