{
  "type": "Feature",
  "properties": {
    "iso:country":"US",
    "sg:address":"418 Silvertree Ln",
    "sg:city":"Redlands",
    "sg:classifiers":[
        {
            "category":"Professional",
            "type":"Services"
        }
    ],
    "sg:phone":"+1 909 748 0012",
    "sg:postcode":"92374",
    "sg:province":"CA",
    "wof:name":"Clara Diab",
    "wof:placetype":"venue"
},
  "geometry": {"coordinates":[-117.145967,34.046846],"type":"Point"}
}