{
  "type": "Feature",
  "properties": {
    "addr:full":"222 N Mayo Ave Compton CA 90221",
    "addr:housenumber":"222",
    "addr:postcode":"90221",
    "addr:street":"N Mayo Ave",
    "iso:country":"US",
    "sg:address":"222 N Mayo Ave",
    "sg:city":"Compton",
    "sg:classifiers":[
        {
            "category":"Social Services",
            "subcategory":"Child Care",
            "type":"Services"
        }
    ],
    "sg:phone":"+1 310 856 3996",
    "sg:postcode":"90221",
    "sg:province":"CA",
    "sg:tags":[
        "nursery",
        "day"
    ],
    "wof:name":"Shannon's Daycare",
    "wof:placetype":"venue"
},
  "geometry": {"coordinates":[-118.212997,33.896999],"type":"Point"}
}