{
  "type": "Feature",
  "properties": {
    "addr:full":"500 12th St Oakland CA 94607",
    "addr:housenumber":"500",
    "addr:postcode":"94607",
    "addr:street":"12Th St",
    "iso:country":"US",
    "sg:address":"500 12th St",
    "sg:city":"Oakland",
    "sg:classifiers":[
        {
            "category":"Home & Garden",
            "subcategory":"Garden Supply",
            "type":"Retail Goods"
        },
        {
            "category":"Shopping",
            "subcategory":"Florist",
            "type":"Retail Goods"
        },
        {
            "category":"Shopping",
            "subcategory":"Gifts & Souvenirs",
            "type":"Retail Goods"
        },
        {
            "category":"Shopping",
            "subcategory":"Crafts & Fabrics",
            "type":"Retail Goods"
        },
        {
            "category":"Farming",
            "subcategory":"Nursery",
            "type":"Manufacturing & Wholesale Goods"
        }
    ],
    "sg:phone":"+1 510 836 6450",
    "sg:postcode":"94607",
    "sg:province":"CA",
    "sg:tags":[
        "plant",
        "nurseries-plants",
        "etc-retail",
        "tree",
        "dried",
        "basket",
        "trees-silk",
        "flowers"
    ],
    "sg:website":"www.citybloom.com",
    "wof:name":"CityBloom",
    "wof:placetype":"venue"
},
  "geometry": {"coordinates":[-122.272918,37.803409],"type":"Point"}
}