{
  "type": "Feature",
  "properties": {
    "addr:full":"200 Admiral Callaghan Ln Vallejo CA 94591",
    "addr:housenumber":"200",
    "addr:postcode":"94591",
    "addr:street":"Admiral Callaghan Ln",
    "iso:country":"US",
    "sg:address":"200 Admiral Callaghan Ln",
    "sg:city":"Vallejo",
    "sg:classifiers":[
        {
            "category":"Organizations",
            "subcategory":"Religious Organization",
            "type":"Services"
        }
    ],
    "sg:phone":"+1 707 644 5286",
    "sg:postcode":"94591",
    "sg:province":"CA",
    "sg:tags":[
        "church"
    ],
    "sg:website":"www.north-hills.org",
    "wof:name":"North Hills Baptist Church",
    "wof:placetype":"venue"
},
  "geometry": {"coordinates":[-122.229186,38.111903],"type":"Point"}
}