{
  "type": "Feature",
  "properties": {
    "addr:full":"6312 Spring Ridge Dr Bakersfield CA 93313",
    "addr:housenumber":"6312",
    "addr:postcode":"93313",
    "addr:street":"Spring Ridge Dr",
    "iso:country":"US",
    "sg:address":"6312 Spring Ridge Dr",
    "sg:city":"Bakersfield",
    "sg:classifiers":[
        {
            "category":"Farming",
            "subcategory":"Farm",
            "type":"Manufacturing & Wholesale Goods"
        }
    ],
    "sg:phone":"+1 661 835 8407",
    "sg:postcode":"93313",
    "sg:province":"CA",
    "wof:name":"J S Partnership",
    "wof:placetype":"venue"
},
  "geometry": {"coordinates":[-119.062014,35.298208],"type":"Point"}
}