{
  "type": "Feature",
  "properties": {
    "iso:country":"US",
    "sg:address":"468 N Camden Dr",
    "sg:city":"Beverly Hills",
    "sg:classifiers":[
        {
            "category":"Retail",
            "subcategory":"Photofinishing",
            "type":"Services"
        }
    ],
    "sg:phone":"+1 310 860 5641",
    "sg:postcode":"90210",
    "sg:province":"CA",
    "sg:tags":[
        "photo",
        "finishing"
    ],
    "wof:name":"Enigma Films",
    "wof:placetype":"venue"
},
  "geometry": {"coordinates":[-118.404026,34.068598],"type":"Point"}
}