{
  "type": "Feature",
  "properties": {
    "iso:country":"US",
    "sg:address":"6622 Melrose Avenue",
    "sg:city":"Los Angeles",
    "sg:classifiers":[
        {
            "category":"Shopping",
            "subcategory":"Computers & Home Electronics",
            "type":"Retail Goods"
        }
    ],
    "sg:phone":"+1 323 931 4500",
    "sg:postcode":"90038",
    "sg:province":"CA",
    "wof:name":"Tv Masters",
    "wof:placetype":"venue"
},
  "geometry": {"coordinates":[-118.339407,34.083564],"type":"Point"}
}