{
  "type": "Feature",
  "properties": {
    "addr:full":"6622 Melrose Avenue Los Angeles CA 90038",
    "addr:housenumber":"6622",
    "addr:postcode":"90038",
    "addr:street":"Melrose Avenue",
    "iso:country":"US",
    "sg:address":"6622 Melrose Avenue",
    "sg:city":"Los Angeles",
    "sg:classifiers":[
        {
            "category":"Shopping",
            "subcategory":"Computers & Home Electronics",
            "type":"Retail Goods"
        }
    ],
    "sg:phone":"+1 323 931 4500",
    "sg:postcode":"90038",
    "sg:province":"CA",
    "wof:name":"Tv Masters",
    "wof:placetype":"venue"
},
  "geometry": {"coordinates":[-118.33940699999999,34.083564],"type":"Point"}
}