{
  "type": "Feature",
  "properties": {
    "iso:country":"US",
    "sg:address":"9742 Variel Ave",
    "sg:city":"Chatsworth",
    "sg:classifiers":[
        {
            "category":"Home & Garden",
            "subcategory":"Furniture",
            "type":"Retail Goods"
        }
    ],
    "sg:phone":"+1 818 700 5885",
    "sg:postcode":"91311",
    "sg:province":"CA",
    "sg:tags":[
        "equipment",
        "kitchen",
        "cabinet"
    ],
    "wof:name":"A Plus Quality Kitchen",
    "wof:placetype":"venue"
},
  "geometry": {"coordinates":[-118.592853,34.249209],"type":"Point"}
}