{
  "type": "Feature",
  "properties": {
    "addr:full":"22 Stone St Salinas CA 93901",
    "addr:housenumber":"22",
    "addr:postcode":"93901",
    "addr:street":"Stone St",
    "iso:country":"US",
    "sg:address":"22 Stone St",
    "sg:city":"Salinas",
    "sg:classifiers":[
        {
            "category":"Organizations",
            "subcategory":"Religious Organization",
            "type":"Services"
        }
    ],
    "sg:phone":"+1 831 424 4076",
    "sg:postcode":"93901",
    "sg:province":"CA",
    "sg:tags":[
        "church"
    ],
    "wof:name":"Diocese Of Monterey",
    "wof:placetype":"venue"
},
  "geometry": {"coordinates":[-121.65904,36.677579],"type":"Point"}
}