{
  "type": "Feature",
  "properties": {
    "addr:full":"610 E Carson St Long Beach CA 90807",
    "addr:housenumber":"610",
    "addr:postcode":"90807",
    "addr:street":"E Carson St",
    "iso:country":"US",
    "sg:address":"610 E Carson St",
    "sg:city":"Long Beach",
    "sg:classifiers":[
        {
            "category":"Fast Food",
            "type":"Food & Drink"
        },
        {
            "category":"Restaurant",
            "type":"Food & Drink"
        }
    ],
    "sg:phone":"+1 562 424 0900",
    "sg:postcode":"90807",
    "sg:province":"CA",
    "sg:tags":[
        "sushi",
        "bar"
    ],
    "sg:website":"www.sushiboy.net",
    "wof:name":"Sushi Boy",
    "wof:placetype":"venue"
},
  "geometry": {"coordinates":[-118.184359,33.831751],"type":"Point"}
}