{
  "type": "Feature",
  "properties": {
    "addr:full":"3474 2nd St Norco CA 92860",
    "addr:housenumber":"3474",
    "addr:postcode":"92860",
    "addr:street":"2Nd St",
    "iso:country":"US",
    "sg:address":"3474 2nd St",
    "sg:city":"Norco",
    "sg:classifiers":[
        {
            "category":"Professional",
            "subcategory":"Accounting & Tax Preparation",
            "type":"Services"
        }
    ],
    "sg:phone":"+1 951 735 8299",
    "sg:postcode":"92860",
    "sg:province":"CA",
    "sg:tags":[
        "return",
        "filing"
    ],
    "wof:name":"Bill's Tax Svc",
    "wof:placetype":"venue"
},
  "geometry": {"coordinates":[-117.580046,33.908616],"type":"Point"}
}