{
  "type": "Feature",
  "properties": {
    "addr:full":"503 North St Woodland CA 95695",
    "addr:housenumber":"503",
    "addr:postcode":"95695",
    "addr:street":"North St",
    "iso:country":"US",
    "sg:address":"503 North St",
    "sg:city":"Woodland",
    "sg:classifiers":[
        {
            "category":"Manufacturing",
            "subcategory":"Tools & Machinery",
            "type":"Manufacturing & Wholesale Goods"
        }
    ],
    "sg:phone":"+1 530 668 1983",
    "sg:postcode":"95695",
    "sg:province":"CA",
    "sg:tags":[
        "terminal",
        "computer",
        "mfg"
    ],
    "wof:name":"G056 Co",
    "wof:placetype":"venue"
},
  "geometry": {"coordinates":[-121.773984,38.68002],"type":"Point"}
}