{
  "type": "Feature",
  "properties": {
    "addr:full":"4037 Arden Dr El Monte CA 91731",
    "addr:housenumber":"4037",
    "addr:postcode":"91731",
    "addr:street":"Arden Dr",
    "iso:country":"US",
    "sg:address":"4037 Arden Dr",
    "sg:city":"El Monte",
    "sg:classifiers":[
        {
            "category":"Health Services",
            "subcategory":"Health Practitioner",
            "type":"Services"
        }
    ],
    "sg:phone":"+1 626 444 8264",
    "sg:postcode":"91731",
    "sg:province":"CA",
    "sg:tags":[
        "nutritionist"
    ],
    "wof:name":"Koch Nutrition Center Inc",
    "wof:placetype":"venue"
},
  "geometry": {"coordinates":[-118.045998,34.080502],"type":"Point"}
}