{
  "type": "Feature",
  "properties": {
    "addr:full":"8159 Lakespring Way Sacramento CA 95828",
    "addr:housenumber":"8159",
    "addr:postcode":"95828",
    "addr:street":"Lakespring Way",
    "iso:country":"US",
    "sg:address":"8159 Lakespring Way",
    "sg:city":"Sacramento",
    "sg:classifiers":[
        {
            "category":"Professional",
            "type":"Services"
        }
    ],
    "sg:phone":"+1 916 682 5928",
    "sg:postcode":"95828",
    "sg:province":"CA",
    "wof:name":"Facing Stone USA",
    "wof:placetype":"venue"
},
  "geometry": {"coordinates":[-121.388752,38.461231],"type":"Point"}
}