{
  "type": "Feature",
  "properties": {
    "addr:full":"4030 Colmery Ct San Jose CA 95118",
    "addr:housenumber":"4030",
    "addr:postcode":"95118",
    "addr:street":"Colmery Ct",
    "iso:country":"US",
    "sg:address":"4030 Colmery Ct",
    "sg:city":"San Jose",
    "sg:classifiers":[
        {
            "category":"Home & Garden",
            "subcategory":"Household Appliances",
            "type":"Retail Goods"
        }
    ],
    "sg:phone":"+1 408 249 7817",
    "sg:postcode":"95118",
    "sg:province":"CA",
    "sg:tags":[
        "equipment",
        "air",
        "filtration",
        "purification"
    ],
    "wof:name":"Innovative Ideas",
    "wof:placetype":"venue"
},
  "geometry": {"coordinates":[-121.899978,37.262137],"type":"Point"}
}