{
  "type": "Feature",
  "properties": {
    "addr:full":"2764 Olsen Rd Rio Vista CA 94571",
    "addr:housenumber":"2764",
    "addr:postcode":"94571",
    "addr:street":"Olsen Rd",
    "iso:country":"US",
    "sg:address":"2764 Olsen Rd",
    "sg:city":"Rio Vista",
    "sg:classifiers":[
        {
            "category":"Recreation",
            "type":"Entertainment"
        }
    ],
    "sg:phone":"+1 707 374 2983",
    "sg:postcode":"94571",
    "sg:province":"CA",
    "sg:tags":[
        "parks"
    ],
    "wof:name":"Wildlife Companions",
    "wof:placetype":"venue"
},
  "geometry": {"coordinates":[-121.843073,38.162074],"type":"Point"}
}