{
  "type": "Feature",
  "properties": {
    "addr:full":"1226 Washington St Calistoga CA 94515",
    "addr:housenumber":"1226",
    "addr:postcode":"94515",
    "addr:street":"Washington St",
    "iso:country":"US",
    "sg:address":"1226 Washington St",
    "sg:city":"Calistoga",
    "sg:classifiers":[
        {
            "category":"Bars & Pubs",
            "type":"Food & Drink"
        },
        {
            "category":"Restaurant",
            "type":"Food & Drink"
        }
    ],
    "sg:menulink":"http://www.allmenus.com/ca/calistoga/51253-wappo-bar-and-bistro/menu/",
    "sg:phone":"+1 707 942 4712",
    "sg:postcode":"94515",
    "sg:province":"CA",
    "sg:tags":[
        "american"
    ],
    "wof:name":"Wappo Bar And Bistro",
    "wof:placetype":"venue"
},
  "geometry": {"coordinates":[-122.579334,38.578676],"type":"Point"}
}