{
  "type": "Feature",
  "properties": {
    "addr:full":"2230 Cam Centroloma Fullerton CA 92833",
    "addr:housenumber":"2230",
    "addr:postcode":"92833",
    "addr:street":"Cam Centroloma",
    "iso:country":"US",
    "sg:address":"2230 Cam Centroloma",
    "sg:city":"Fullerton",
    "sg:classifiers":[
        {
            "category":"Wholesale",
            "subcategory":"Non-durable Goods",
            "type":"Manufacturing & Wholesale Goods"
        }
    ],
    "sg:phone":"+1 714 680 0278",
    "sg:postcode":"92833",
    "sg:province":"CA",
    "sg:tags":[
        "stone"
    ],
    "wof:name":"Golden West Sales",
    "wof:placetype":"venue"
},
  "geometry": {"coordinates":[-117.95670699999999,33.895412],"type":"Point"}
}