{
  "type": "Feature",
  "properties": {
    "iso:country":"US",
    "sg:address":"2741 Fruitridge Rd",
    "sg:city":"Sacramento",
    "sg:classifiers":[
        {
            "category":"Communications",
            "subcategory":"Film & Video Production",
            "type":"Services"
        }
    ],
    "sg:phone":"+1 916 455 8757",
    "sg:postcode":"95820",
    "sg:province":"CA",
    "sg:tags":[
        "taping"
    ],
    "wof:name":"Promociones Mejia",
    "wof:placetype":"venue"
},
  "geometry": {"coordinates":[-121.478027,38.524919],"type":"Point"}
}