{
  "type": "Feature",
  "properties": {
    "iso:country":"US",
    "sg:address":"1435 N Market Boulevard",
    "sg:city":"Sacramento",
    "sg:classifiers":[
        {
            "category":"Building & Trades",
            "subcategory":"Construction",
            "type":"Services"
        },
        {
            "category":"Home & Garden",
            "subcategory":"Carpets & Floor Coverings",
            "type":"Retail Goods"
        }
    ],
    "sg:phone":"+1 916 419 2930",
    "sg:postcode":"95834",
    "sg:province":"CA",
    "sg:tags":[
        "flooring",
        "contractor"
    ],
    "wof:name":"Tile Outlet",
    "wof:placetype":"venue"
},
  "geometry": {"coordinates":[-121.49459899999999,38.646725],"type":"Point"}
}