{
  "type": "Feature",
  "properties": {
    "addr:full":"9956 Lakewood Boulevard Downey CA 90240",
    "addr:housenumber":"9956",
    "addr:postcode":"90240",
    "addr:street":"Lakewood Boulevard",
    "iso:country":"US",
    "sg:address":"9956 Lakewood Boulevard",
    "sg:city":"Downey",
    "sg:classifiers":[
        {
            "category":"Food & Beverages",
            "subcategory":"Liquor & Beverages",
            "type":"Retail Goods"
        }
    ],
    "sg:phone":"+1 562 869 8464",
    "sg:postcode":"90240",
    "sg:province":"CA",
    "sg:tags":[
        "beer",
        "spirit",
        "wine"
    ],
    "wof:name":"A B C Liquor Market",
    "wof:placetype":"venue"
},
  "geometry": {"coordinates":[-118.11635,33.949211],"type":"Point"}
}