{
  "type": "Feature",
  "properties": {
    "addr:full":"2617 San Pablo Ave Berkeley CA 94702",
    "addr:housenumber":"2617",
    "addr:postcode":"94702",
    "addr:street":"San Pablo Ave",
    "iso:country":"US",
    "sg:address":"2617 San Pablo Ave",
    "sg:city":"Berkeley",
    "sg:classifiers":[
        {
            "category":"Shopping",
            "subcategory":"Bicycles & Sporting Goods",
            "type":"Retail Goods"
        }
    ],
    "sg:phone":"+1 510 704 8990",
    "sg:postcode":"94702",
    "sg:province":"CA",
    "wof:name":"Lucky Bait Shop",
    "wof:placetype":"venue"
},
  "geometry": {"coordinates":[-122.288948,37.859199],"type":"Point"}
}