{
  "type": "Feature",
  "properties": {
    "iso:country":"US",
    "sg:address":"601 Francisco Blvd E",
    "sg:city":"San Rafael",
    "sg:classifiers":[
        {
            "category":"Autos & Motor Vehicles",
            "subcategory":"Motorcycle Sales",
            "type":"Retail Goods"
        }
    ],
    "sg:phone":"+1 415 456 3345",
    "sg:postcode":"94901",
    "sg:province":"CA",
    "sg:tags":[
        "scooter"
    ],
    "wof:name":"Hattar Motorsports",
    "wof:placetype":"venue"
},
  "geometry": {"coordinates":[-122.512118,37.964023],"type":"Point"}
}