{
  "type": "Feature",
  "properties": {
    "addr:full":"501 Ryan Dr Pleasant Hill CA 94523",
    "addr:housenumber":"501",
    "addr:postcode":"94523",
    "addr:street":"Ryan Dr",
    "iso:country":"US",
    "sg:address":"501 Ryan Dr",
    "sg:city":"Pleasant Hill",
    "sg:classifiers":[
        {
            "category":"Real Estate",
            "subcategory":"Real Estate Operator",
            "type":"Services"
        }
    ],
    "sg:phone":"+1 925 682 2424",
    "sg:postcode":"94523",
    "sg:province":"CA",
    "sg:tags":[
        "apartment"
    ],
    "wof:name":"Brookside Apartments",
    "wof:placetype":"venue"
},
  "geometry": {"coordinates":[-122.075714,37.977189],"type":"Point"}
}