{
  "type": "Feature",
  "properties": {
    "iso:country":"US",
    "sg:address":"4630 Campus Drive Suite 200",
    "sg:city":"Newport Beach",
    "sg:classifiers":[
        {
            "category":"Banks & Credit Unions",
            "subcategory":"Financial Services",
            "type":"Services"
        }
    ],
    "sg:phone":"+1 949 476 1900",
    "sg:postcode":"92660",
    "sg:province":"CA",
    "sg:tags":[
        "broker",
        "mortgage"
    ],
    "wof:name":"Apex Associates",
    "wof:placetype":"venue"
},
  "geometry": {"coordinates":[-117.86597399999999,33.670931],"type":"Point"}
}