{
  "type": "Feature",
  "properties": {
    "iso:country":"US",
    "sg:address":"1742 Zinfandel Dr",
    "sg:city":"Lodi",
    "sg:classifiers":[
        {
            "category":"Home & Garden",
            "subcategory":"Household Appliances",
            "type":"Retail Goods"
        }
    ],
    "sg:phone":"+1 209 334 2686",
    "sg:postcode":"95242",
    "sg:province":"CA",
    "wof:name":"Ralph Wyatt Appliance Repair",
    "wof:placetype":"venue"
},
  "geometry": {"coordinates":[-121.29002199999999,38.111277],"type":"Point"}
}