{
  "type": "Feature",
  "properties": {
    "iso:country":"US",
    "sg:address":"2917 W Olympic Blvd",
    "sg:city":"Los Angeles",
    "sg:classifiers":[
        {
            "category":"Personal",
            "subcategory":"Nail Salon",
            "type":"Services"
        }
    ],
    "sg:phone":"+1 213 739 0703",
    "sg:postcode":"90006",
    "sg:province":"CA",
    "wof:name":"Nail Story",
    "wof:placetype":"venue"
},
  "geometry": {"coordinates":[-118.298433,34.052632],"type":"Point"}
}