{
  "type": "Feature",
  "properties": {
    "iso:country":"US",
    "sg:address":"10761 Burbank Blvd",
    "sg:city":"North Hollywood",
    "sg:classifiers":[
        {
            "category":"Professional",
            "type":"Services"
        }
    ],
    "sg:phone":"+1 818 755 8807",
    "sg:postcode":"91601",
    "sg:province":"CA",
    "wof:name":"Smyrna",
    "wof:placetype":"venue"
},
  "geometry": {"coordinates":[-118.36552399999999,34.172232],"type":"Point"}
}