{
  "type": "Feature",
  "properties": {
    "iso:country":"US",
    "sg:address":"684 West Garvey Ave",
    "sg:city":"Monterey Park",
    "sg:classifiers":[
        {
            "category":"Building & Trades",
            "subcategory":"Construction",
            "type":"Services"
        }
    ],
    "sg:phone":"+1 626 241 9321",
    "sg:postcode":"91754",
    "sg:province":"CA",
    "sg:tags":[
        "contractor"
    ],
    "wof:name":"Expert Installation and Service, Fast, Friendly Service",
    "wof:placetype":"venue"
},
  "geometry": {"coordinates":[-118.131821,34.062395],"type":"Point"}
}