{
  "type": "Feature",
  "properties": {
    "addr:full":"1412 Freedom Blvd Watsonville CA 95076",
    "addr:housenumber":"1412",
    "addr:postcode":"95076",
    "addr:street":"Freedom Blvd",
    "iso:country":"US",
    "sg:address":"1412 Freedom Blvd",
    "sg:city":"Watsonville",
    "sg:classifiers":[
        {
            "category":"Retail",
            "subcategory":"Self-service Laundry",
            "type":"Services"
        }
    ],
    "sg:phone":"+1 831 728 7254",
    "sg:postcode":"95076",
    "sg:province":"CA",
    "wof:name":"Cerstview Laundromat",
    "wof:placetype":"venue"
},
  "geometry": {"coordinates":[-121.76403000000001,36.925864],"type":"Point"}
}