{
  "type": "Feature",
  "properties": {
    "addr:full":"2805 Theater Dr Paso Robles CA 93446",
    "addr:housenumber":"2805",
    "addr:postcode":"93446",
    "addr:street":"Theater Dr",
    "iso:country":"US",
    "sg:address":"2805 Theater Dr",
    "sg:city":"Paso Robles",
    "sg:classifiers":[
        {
            "category":"Home & Garden",
            "subcategory":"Mobile Homes",
            "type":"Retail Goods"
        }
    ],
    "sg:phone":"+1 805 239 3460",
    "sg:postcode":"93446",
    "sg:province":"CA",
    "wof:name":"B J's Mobile Home Ctr Inc",
    "wof:placetype":"venue"
},
  "geometry": {"coordinates":[-120.69813499999999,35.574559],"type":"Point"}
}