{
  "type": "Feature",
  "properties": {
    "iso:country":"US",
    "sg:address":"360 Tesconi Cir",
    "sg:city":"Santa Rosa",
    "sg:classifiers":[
        {
            "category":"Wholesale",
            "subcategory":"Construction Materials",
            "type":"Manufacturing & Wholesale Goods"
        }
    ],
    "sg:phone":"+1 707 526 5995",
    "sg:postcode":"95401",
    "sg:province":"CA",
    "wof:name":"Oakbourne",
    "wof:placetype":"venue"
},
  "geometry": {"coordinates":[-122.733772,38.447845],"type":"Point"}
}