{
  "type": "Feature",
  "properties": {
    "addr:full":"1193 Rudgwick Dr Roseville CA 95747",
    "addr:housenumber":"1193",
    "addr:postcode":"95747",
    "addr:street":"Rudgwick Dr",
    "iso:country":"US",
    "sg:address":"1193 Rudgwick Dr",
    "sg:city":"Roseville",
    "sg:classifiers":[
        {
            "category":"Travel",
            "subcategory":"Travel Agent",
            "type":"Entertainment"
        }
    ],
    "sg:phone":"+1 916 784 8004",
    "sg:postcode":"95747",
    "sg:province":"CA",
    "sg:tags":[
        "representative"
    ],
    "wof:name":"Unicorn Travel",
    "wof:placetype":"venue"
},
  "geometry": {"coordinates":[-121.342635,38.75522],"type":"Point"}
}