{
  "type": "Feature",
  "properties": {
    "addr:full":"8920 Greenback Ln Orangevale CA 95662",
    "addr:housenumber":"8920",
    "addr:postcode":"95662",
    "addr:street":"Greenback Ln",
    "iso:country":"US",
    "sg:address":"8920 Greenback Ln",
    "sg:city":"Orangevale",
    "sg:classifiers":[
        {
            "category":"Personal",
            "subcategory":"Beauty Salon",
            "type":"Services"
        }
    ],
    "sg:phone":"+1 916 988 3000",
    "sg:postcode":"95662",
    "sg:province":"CA",
    "wof:name":"Cutting Edge Hair Design",
    "wof:placetype":"venue"
},
  "geometry": {"coordinates":[-121.221694,38.678309],"type":"Point"}
}