{
  "type": "Feature",
  "properties": {
    "addr:full":"41725 170th St E Lancaster CA 93535",
    "addr:housenumber":"41725",
    "addr:postcode":"93535",
    "addr:street":"170Th St E",
    "iso:country":"US",
    "sg:address":"41725 170th St E",
    "sg:city":"Lancaster",
    "sg:classifiers":[
        {
            "category":"Education",
            "subcategory":"School",
            "type":"Public Place"
        }
    ],
    "sg:phone":"+1 661 264 1790",
    "sg:postcode":"93535",
    "sg:province":"CA",
    "wof:name":"Wilsona School District",
    "wof:placetype":"venue"
},
  "geometry": {"coordinates":[-117.82735099999999,34.641837],"type":"Point"}
}