{
  "type": "Feature",
  "properties": {
    "iso:country":"US",
    "sg:address":"41725 170th St E",
    "sg:city":"Lancaster",
    "sg:classifiers":[
        {
            "category":"Education",
            "subcategory":"School",
            "type":"Public Place"
        }
    ],
    "sg:phone":"+1 661 264 1790",
    "sg:postcode":"93535",
    "sg:province":"CA",
    "wof:name":"Wilsona School District",
    "wof:placetype":"venue"
},
  "geometry": {"coordinates":[-117.827351,34.641837],"type":"Point"}
}