{
  "type": "Feature",
  "properties": {
    "iso:country":"US",
    "sg:address":"2026 Chilton Dr",
    "sg:city":"Glendale",
    "sg:classifiers":[
        {
            "category":"Professional",
            "type":"Services"
        }
    ],
    "sg:phone":"+1 818 729 0917",
    "sg:postcode":"91201",
    "sg:province":"CA",
    "wof:name":"Orchid Society of Souther",
    "wof:placetype":"venue"
},
  "geometry": {"coordinates":[-118.288978,34.185218],"type":"Point"}
}