{
  "type": "Feature",
  "properties": {
    "iso:country":"US",
    "sg:address":"6731 Westminster Blvd",
    "sg:city":"Westminster",
    "sg:classifiers":[
        {
            "category":"Health Services",
            "subcategory":"Doctor",
            "type":"Services"
        }
    ],
    "sg:phone":"+1 714 894 3306",
    "sg:postcode":"92683",
    "sg:province":"CA",
    "sg:tags":[
        "surgeon",
        "oral"
    ],
    "wof:name":"Marcos Sam DDS",
    "wof:placetype":"venue"
},
  "geometry": {"coordinates":[-117.99099699999999,33.7556],"type":"Point"}
}