{
  "type": "Feature",
  "properties": {
    "iso:country":"US",
    "sg:address":"706 Idylberry Rd",
    "sg:city":"San Rafael",
    "sg:classifiers":[
        {
            "category":"Professional",
            "subcategory":"Management & Consulting",
            "type":"Services"
        }
    ],
    "sg:phone":"+1 415 507 9603",
    "sg:postcode":"94903",
    "sg:province":"CA",
    "sg:tags":[
        "business"
    ],
    "wof:name":"Powerlight Coaching",
    "wof:placetype":"venue"
},
  "geometry": {"coordinates":[-122.55991,38.028357],"type":"Point"}
}