{
  "type": "Feature",
  "properties": {
    "iso:country":"US",
    "sg:address":"40063 Bella Vista Rd",
    "sg:city":"Temecula",
    "sg:classifiers":[
        {
            "category":"Building & Trades",
            "subcategory":"Construction",
            "type":"Services"
        }
    ],
    "sg:phone":"+1 951 676 7547",
    "sg:postcode":"92592",
    "sg:province":"CA",
    "sg:tags":[
        "contractor"
    ],
    "wof:name":"Rowland Tile",
    "wof:placetype":"venue"
},
  "geometry": {"coordinates":[-117.019989,33.543689],"type":"Point"}
}