{
  "type": "Feature",
  "properties": {
    "iso:country":"US",
    "sg:address":"2701 W Burbank Blvd",
    "sg:city":"Burbank",
    "sg:classifiers":[
        {
            "category":"Manufacturing",
            "subcategory":"Metals",
            "type":"Manufacturing & Wholesale Goods"
        }
    ],
    "sg:phone":"+1 818 842 8787",
    "sg:postcode":"91505",
    "sg:province":"CA",
    "sg:tags":[
        "engraver"
    ],
    "sg:website":"www.calprecisiongraphics.com",
    "wof:name":"Cal-Precision Graphics Inc",
    "wof:placetype":"venue"
},
  "geometry": {"coordinates":[-118.340423,34.178073],"type":"Point"}
}