{
  "type": "Feature",
  "properties": {
    "iso:country":"US",
    "sg:address":"2938 Crocker Ave",
    "sg:city":"Redwood City",
    "sg:classifiers":[
        {
            "category":"Autos & Motor Vehicles",
            "subcategory":"Fuel & Gas Station",
            "type":"Retail Goods"
        }
    ],
    "sg:phone":"+1 650 361 1205",
    "sg:postcode":"94063",
    "sg:province":"CA",
    "sg:tags":[
        "oil"
    ],
    "wof:name":"Alpha Smog",
    "wof:placetype":"venue"
},
  "geometry": {"coordinates":[-122.20777699999999,37.475135],"type":"Point"}
}