{
  "type": "Feature",
  "properties": {
    "addr:full":"1224 Village Way Unit B Santa Ana CA 92705",
    "addr:housenumber":"1224",
    "addr:postcode":"92705",
    "addr:street":"Village Way Unit B",
    "iso:country":"US",
    "sg:address":"1224 Village Way Unit B",
    "sg:city":"Santa Ana",
    "sg:classifiers":[
        {
            "category":"Shopping",
            "subcategory":"Bicycles & Sporting Goods",
            "type":"Retail Goods"
        }
    ],
    "sg:phone":"+1 714 553 9730",
    "sg:postcode":"92705",
    "sg:province":"CA",
    "sg:tags":[
        "bike"
    ],
    "sg:website":"www.peregrinecyclery.com",
    "wof:name":"Peregrine Cyclery",
    "wof:placetype":"venue"
},
  "geometry": {"coordinates":[-117.835864,33.733376],"type":"Point"}
}