{
  "type": "Feature",
  "properties": {
    "iso:country":"US",
    "sg:address":"155 Belgrave Ave",
    "sg:city":"San Francisco",
    "sg:classifiers":[
        {
            "category":"Health Services",
            "subcategory":"Doctor",
            "type":"Services"
        }
    ],
    "sg:phone":"+1 415 566 3611",
    "sg:postcode":"94117",
    "sg:province":"CA",
    "sg:tags":[
        "physician",
        "surgeon"
    ],
    "wof:name":"Madlyn W Stein MD",
    "wof:placetype":"venue"
},
  "geometry": {"coordinates":[-122.450388,37.759484],"type":"Point"}
}