{
  "type": "Feature",
  "properties": {
    "iso:country":"US",
    "sg:address":"4851 E Alder Dr",
    "sg:city":"San Diego",
    "sg:classifiers":[
        {
            "category":"Real Estate",
            "subcategory":"Real Estate Agent",
            "type":"Services"
        }
    ],
    "sg:phone":"+1 619 563 3610",
    "sg:postcode":"92116",
    "sg:province":"CA",
    "wof:name":"Catton Property Management",
    "wof:placetype":"venue"
},
  "geometry": {"coordinates":[-117.098284,32.766624],"type":"Point"}
}