{
  "type": "Feature",
  "properties": {
    "addr:full":"12430 Whittier Blvd Whittier CA 90602",
    "addr:housenumber":"12430",
    "addr:postcode":"90602",
    "addr:street":"Whittier Blvd",
    "iso:country":"US",
    "sg:address":"12430 Whittier Blvd",
    "sg:city":"Whittier",
    "sg:classifiers":[
        {
            "category":"Education",
            "subcategory":"Vocational School",
            "type":"Public Place"
        }
    ],
    "sg:phone":"+1 562 698 1279",
    "sg:postcode":"90602",
    "sg:province":"CA",
    "wof:name":"Academy Of Textiles & Flooring",
    "wof:placetype":"venue"
},
  "geometry": {"coordinates":[-118.04486799999999,33.972268],"type":"Point"}
}