{
  "type": "Feature",
  "properties": {
    "addr:full":"560 N Gilbert St Fullerton CA 92833",
    "addr:housenumber":"560",
    "addr:postcode":"92833",
    "addr:street":"N Gilbert St",
    "iso:country":"US",
    "sg:address":"560 N Gilbert St",
    "sg:city":"Fullerton",
    "sg:classifiers":[
        {
            "category":"Mining & Drilling",
            "type":"Manufacturing & Wholesale Goods"
        }
    ],
    "sg:phone":"+1 714 449 6723",
    "sg:postcode":"92833",
    "sg:province":"CA",
    "sg:tags":[
        "field"
    ],
    "wof:name":"Cargill",
    "wof:placetype":"venue"
},
  "geometry": {"coordinates":[-117.968205,33.874135],"type":"Point"}
}