{
  "type": "Feature",
  "properties": {
    "iso:country":"US",
    "sg:address":"535 W Lambert Rd Frnt",
    "sg:city":"Brea",
    "sg:classifiers":[
        {
            "category":"Wholesale",
            "subcategory":"Electrical",
            "type":"Manufacturing & Wholesale Goods"
        }
    ],
    "sg:phone":"+1 714 672 0200",
    "sg:postcode":"92821",
    "sg:province":"CA",
    "sg:tags":[
        "semiconductor",
        "device"
    ],
    "wof:name":"Trade Tronics International",
    "wof:placetype":"venue"
},
  "geometry": {"coordinates":[-117.903976,33.924705],"type":"Point"}
}