{
  "type": "Feature",
  "properties": {
    "iso:country":"US",
    "sg:address":"1757 Mesa Verde Ave",
    "sg:city":"Ventura",
    "sg:classifiers":[
        {
            "category":"Professional",
            "subcategory":"Lawyer & Legal Services",
            "type":"Services"
        }
    ],
    "sg:phone":"+1 805 644 6596",
    "sg:postcode":"93003",
    "sg:province":"CA",
    "sg:tags":[
        "attorney"
    ],
    "wof:name":"Robert R Garcia",
    "wof:placetype":"venue"
},
  "geometry": {"coordinates":[-119.216921,34.258453],"type":"Point"}
}