{
  "type": "Feature",
  "properties": {
    "addr:full":"13074 Cmt Cristobal Del Mar CA 92014",
    "addr:postcode":"13074;92014",
    "addr:street":"Cmt Cristobal",
    "iso:country":"US",
    "sg:address":"13074 Cmt Cristobal",
    "sg:city":"Del Mar",
    "sg:classifiers":[
        {
            "category":"Manufacturing",
            "subcategory":"Furniture",
            "type":"Manufacturing & Wholesale Goods"
        }
    ],
    "sg:phone":"+1 858 481 9577",
    "sg:postcode":"92014",
    "sg:province":"CA",
    "sg:tags":[
        "mfg"
    ],
    "wof:name":"Sinclair Jordan Designs",
    "wof:placetype":"venue"
},
  "geometry": {"coordinates":[-117.242487,32.937619],"type":"Point"}
}