{
  "type": "Feature",
  "properties": {
    "iso:country":"US",
    "sg:address":"631 S Broadway",
    "sg:city":"Los Angeles",
    "sg:classifiers":[
        {
            "category":"Wholesale",
            "subcategory":"Jewelry",
            "type":"Manufacturing & Wholesale Goods"
        }
    ],
    "sg:phone":"+1 213 622 6211",
    "sg:postcode":"90014",
    "sg:province":"CA",
    "sg:tags":[
        "stone"
    ],
    "wof:name":"Czar Jewelry",
    "wof:placetype":"venue"
},
  "geometry": {"coordinates":[-118.253088,34.045698],"type":"Point"}
}