{
  "type": "Feature",
  "properties": {
    "iso:country":"US",
    "sg:address":"1905 E Lincoln Ave",
    "sg:city":"Anaheim",
    "sg:classifiers":[
        {
            "category":"Retail",
            "subcategory":"Auto Repair",
            "type":"Services"
        }
    ],
    "sg:phone":"+1 714 491 0241",
    "sg:postcode":"92805",
    "sg:province":"CA",
    "wof:name":"Harbor Auto Care II",
    "wof:placetype":"venue"
},
  "geometry": {"coordinates":[-117.89099899999999,33.840302],"type":"Point"}
}