{
  "type": "Feature",
  "properties": {
    "addr:full":"2428 Glenfaire Dr Rancho Cordova CA 95670",
    "addr:housenumber":"2428",
    "addr:postcode":"95670",
    "addr:street":"Glenfaire Dr",
    "iso:country":"US",
    "sg:address":"2428 Glenfaire Dr",
    "sg:city":"Rancho Cordova",
    "sg:classifiers":[
        {
            "category":"Retail",
            "subcategory":"Laundry & Dry Cleaning",
            "type":"Services"
        }
    ],
    "sg:phone":"+1 916 635 0192",
    "sg:postcode":"95670",
    "sg:province":"CA",
    "sg:tags":[
        "cleaners",
        "rug",
        "carpet"
    ],
    "wof:name":"Carpet Call",
    "wof:placetype":"venue"
},
  "geometry": {"coordinates":[-121.290037,38.60634],"type":"Point"}
}