{
  "type": "Feature",
  "properties": {
    "iso:country":"US",
    "sg:address":"3239 San Gabriel Blvd",
    "sg:city":"Rosemead",
    "sg:classifiers":[
        {
            "category":"Health Services",
            "subcategory":"Chiropractor",
            "type":"Services"
        }
    ],
    "sg:phone":"+1 626 573 8458",
    "sg:postcode":"91770",
    "sg:province":"CA",
    "wof:name":"Abundant Life Chiropractic",
    "wof:placetype":"venue"
},
  "geometry": {"coordinates":[-118.090638,34.067404],"type":"Point"}
}