{
  "type": "Feature",
  "properties": {
    "addr:full":"727 Lincoln Ave Napa CA 94558",
    "addr:housenumber":"727",
    "addr:postcode":"94558",
    "addr:street":"Lincoln Ave",
    "iso:country":"US",
    "sg:address":"727 Lincoln Ave",
    "sg:city":"Napa",
    "sg:classifiers":[
        {
            "category":"Building & Trades",
            "subcategory":"Construction",
            "type":"Services"
        }
    ],
    "sg:phone":"+1 707 254 9443",
    "sg:postcode":"94558",
    "sg:province":"CA",
    "sg:tags":[
        "steam",
        "cleaning"
    ],
    "wof:name":"Fire Free",
    "wof:placetype":"venue"
},
  "geometry": {"coordinates":[-122.28744399999999,38.309864],"type":"Point"}
}