{
  "type": "Feature",
  "properties": {
    "addr:full":"600 Main St Watsonville CA 95076",
    "addr:housenumber":"600",
    "addr:postcode":"95076",
    "addr:street":"Main St",
    "iso:country":"US",
    "sg:address":"600 Main St",
    "sg:city":"Watsonville",
    "sg:classifiers":[
        {
            "category":"Food & Beverages",
            "subcategory":"Bakery",
            "type":"Retail Goods"
        }
    ],
    "sg:phone":"+1 831 728 2158",
    "sg:postcode":"95076",
    "sg:province":"CA",
    "sg:tags":[
        "baker"
    ],
    "wof:name":"Watsonville Bakery & Market",
    "wof:placetype":"venue"
},
  "geometry": {"coordinates":[-121.760867,36.914449],"type":"Point"}
}