{
  "type": "Feature",
  "properties": {
    "addr:full":"8055 Armour St San Diego CA 92111",
    "addr:housenumber":"8055",
    "addr:postcode":"92111",
    "addr:street":"Armour St",
    "iso:country":"US",
    "sg:address":"8055 Armour St",
    "sg:city":"San Diego",
    "sg:classifiers":[
        {
            "category":"Restaurant",
            "type":"Food & Drink"
        }
    ],
    "sg:menulink":"http://www.allmenus.com/ca/san-diego/123902-quiznos-sub/menu/",
    "sg:phone":"+1 858 292 4593",
    "sg:postcode":"92111",
    "sg:province":"CA",
    "sg:tags":[
        "wrap",
        "american",
        "sandwich"
    ],
    "wof:name":"Quiznos Sub",
    "wof:placetype":"venue"
},
  "geometry": {"coordinates":[-117.149992,32.819684],"type":"Point"}
}