{
  "type": "Feature",
  "properties": {
    "iso:country":"US",
    "sg:address":"3842 Little Rock Dr",
    "sg:city":"Antelope",
    "sg:classifiers":[
        {
            "category":"Real Estate",
            "subcategory":"Real Estate Agent",
            "type":"Services"
        }
    ],
    "sg:phone":"+1 916 334 6745",
    "sg:postcode":"95843",
    "sg:province":"CA",
    "wof:name":"R D Real Estate",
    "wof:placetype":"venue"
},
  "geometry": {"coordinates":[-121.374824,38.705215],"type":"Point"}
}