{
  "type": "Feature",
  "properties": {
    "iso:country":"US",
    "sg:address":"846 W Palmdale Blvd",
    "sg:city":"Palmdale",
    "sg:classifiers":[
        {
            "category":"Shopping",
            "subcategory":"Computers & Home Electronics",
            "type":"Retail Goods"
        }
    ],
    "sg:phone":"+1 661 273 0001",
    "sg:postcode":"93551",
    "sg:province":"CA",
    "sg:tags":[
        "equipment",
        "dealer"
    ],
    "wof:name":"National Computer Corp",
    "wof:placetype":"venue"
},
  "geometry": {"coordinates":[-118.14647,34.58694],"type":"Point"}
}