{
  "type": "Feature",
  "properties": {
    "addr:full":"3845 E Miraloma Ave Anaheim CA 92806",
    "addr:housenumber":"3845",
    "addr:postcode":"92806",
    "addr:street":"E Miraloma Ave",
    "iso:country":"US",
    "sg:address":"3845 E Miraloma Ave",
    "sg:city":"Anaheim",
    "sg:classifiers":[
        {
            "category":"Manufacturing",
            "subcategory":"Electronics",
            "type":"Manufacturing & Wholesale Goods"
        }
    ],
    "sg:phone":"+1 714 572 0969",
    "sg:postcode":"92806",
    "sg:province":"CA",
    "sg:tags":[
        "mfg",
        "bo",
        "component",
        "printed",
        "circuit",
        "electronic"
    ],
    "wof:name":"Icci",
    "wof:placetype":"venue"
},
  "geometry": {"coordinates":[-117.83154999999999,33.862891],"type":"Point"}
}