{
  "type": "Feature",
  "properties": {
    "addr:full":"7701 Orion Ave Van Nuys CA 91406",
    "addr:housenumber":"7701",
    "addr:postcode":"91406",
    "addr:street":"Orion Ave",
    "iso:country":"US",
    "sg:address":"7701 Orion Ave",
    "sg:city":"Van Nuys",
    "sg:classifiers":[
        {
            "category":"Building & Trades",
            "subcategory":"Construction",
            "type":"Services"
        }
    ],
    "sg:phone":"+1 818 782 8956",
    "sg:postcode":"91406",
    "sg:province":"CA",
    "sg:tags":[
        "general",
        "contractor"
    ],
    "wof:name":"L T Construction & Development",
    "wof:placetype":"venue"
},
  "geometry": {"coordinates":[-118.470569,34.211172],"type":"Point"}
}