{
  "type": "Feature",
  "properties": {
    "addr:full":"18170 Main St Jamestown CA 95327",
    "addr:housenumber":"18170",
    "addr:postcode":"95327",
    "addr:street":"Main St",
    "iso:country":"US",
    "sg:address":"18170 Main St",
    "sg:city":"Jamestown",
    "sg:classifiers":[
        {
            "category":"Shopping",
            "subcategory":"Jewelry",
            "type":"Retail Goods"
        }
    ],
    "sg:phone":"+1 209 984 4482",
    "sg:postcode":"95327",
    "sg:province":"CA",
    "sg:tags":[
        "jeweler"
    ],
    "wof:name":"Woods Creek Jewelry Co",
    "wof:placetype":"venue"
},
  "geometry": {"coordinates":[-120.42349,37.952354],"type":"Point"}
}