{
  "type": "Feature",
  "properties": {
    "iso:country":"US",
    "sg:address":"11601 Ocala Ct",
    "sg:city":"Moreno Valley",
    "sg:classifiers":[
        {
            "category":"Building & Trades",
            "subcategory":"Landscaping Services",
            "type":"Services"
        }
    ],
    "sg:phone":"+1 951 924 9277",
    "sg:postcode":"92557",
    "sg:province":"CA",
    "wof:name":"Sears",
    "wof:placetype":"venue"
},
  "geometry": {"coordinates":[-117.241405,33.952492],"type":"Point"}
}