{
  "type": "Feature",
  "properties": {
    "addr:full":"34428 Yucaipa Blvd Yucaipa CA 92399",
    "addr:postcode":"34428;92399",
    "addr:street":"Yucaipa Blvd",
    "iso:country":"US",
    "sg:address":"34428 Yucaipa Blvd",
    "sg:city":"Yucaipa",
    "sg:classifiers":[
        {
            "category":"Wholesale",
            "subcategory":"Machinery & Supplies",
            "type":"Manufacturing & Wholesale Goods"
        }
    ],
    "sg:phone":"+1 909 795 7820",
    "sg:postcode":"92399",
    "sg:province":"CA",
    "sg:tags":[
        "printer",
        "cartridge"
    ],
    "wof:name":"Cork Industries Inc",
    "wof:placetype":"venue"
},
  "geometry": {"coordinates":[-117.054354,34.033961],"type":"Point"}
}