{
  "type": "Feature",
  "properties": {
    "iso:country":"US",
    "sg:address":"2785 E Thompson Blvd",
    "sg:city":"Ventura",
    "sg:classifiers":[
        {
            "category":"Personal",
            "subcategory":"Beauty Salon",
            "type":"Services"
        },
        {
            "category":"Personal",
            "subcategory":"Barber",
            "type":"Services"
        },
        {
            "category":"Shopping",
            "subcategory":"Beauty & Cosmetics",
            "type":"Retail Goods"
        },
        {
            "category":"Personal",
            "subcategory":"Nail Salon",
            "type":"Services"
        }
    ],
    "sg:phone":"+1 805 652 0449",
    "sg:postcode":"93003",
    "sg:province":"CA",
    "sg:tags":[
        "equipment",
        "perfume",
        "salons-equipment",
        "supply"
    ],
    "wof:name":"Angel Beauty Supply & Salon Co",
    "wof:placetype":"venue"
},
  "geometry": {"coordinates":[-119.258655,34.272043],"type":"Point"}
}