{
  "type": "Feature",
  "properties": {
    "iso:country":"US",
    "sg:address":"25901 Serenata Dr",
    "sg:city":"Mission Viejo",
    "sg:classifiers":[
        {
            "category":"Manufacturing",
            "subcategory":"Retail Goods",
            "type":"Manufacturing & Wholesale Goods"
        }
    ],
    "sg:phone":"+1 949 472 2233",
    "sg:postcode":"92691",
    "sg:province":"CA",
    "sg:tags":[
        "item",
        "design",
        "christmas",
        "mfg"
    ],
    "wof:name":"Gini Garner Co",
    "wof:placetype":"venue"
},
  "geometry": {"coordinates":[-117.66485,33.58557],"type":"Point"}
}