{
  "type": "Feature",
  "properties": {
    "iso:country":"US",
    "sg:address":"442 N Blackstone Ave",
    "sg:city":"Fresno",
    "sg:classifiers":[
        {
            "category":"Personal",
            "subcategory":"Beauty Salon",
            "type":"Services"
        }
    ],
    "sg:phone":"+1 559 498 6530",
    "sg:postcode":"93701",
    "sg:province":"CA",
    "wof:name":"Pilar's Touch",
    "wof:placetype":"venue"
},
  "geometry": {"coordinates":[-119.79044500000001,36.749643],"type":"Point"}
}