{
  "type": "Feature",
  "properties": {
    "addr:full":"788 Gravenstein Hwy N Sebastopol CA 95472",
    "addr:housenumber":"788",
    "addr:postcode":"95472",
    "addr:street":"Gravenstein Hwy N",
    "iso:country":"US",
    "sg:address":"788 Gravenstein Hwy N",
    "sg:city":"Sebastopol",
    "sg:classifiers":[
        {
            "category":"Shopping",
            "subcategory":"Pharmacy",
            "type":"Retail Goods"
        }
    ],
    "sg:phone":"+1 707 823 7209",
    "sg:postcode":"95472",
    "sg:province":"CA",
    "wof:name":"Longs Drug",
    "wof:placetype":"venue"
},
  "geometry": {"coordinates":[-122.841404,38.410556],"type":"Point"}
}