{
  "type": "Feature",
  "properties": {
    "addr:full":"3659 India St San Diego CA 92103",
    "addr:housenumber":"3659",
    "addr:postcode":"92103",
    "addr:street":"India St",
    "iso:country":"US",
    "sg:address":"3659 India St",
    "sg:city":"San Diego",
    "sg:classifiers":[
        {
            "category":"Building & Trades",
            "subcategory":"Construction",
            "type":"Services"
        }
    ],
    "sg:phone":"+1 619 291 4500",
    "sg:postcode":"92103",
    "sg:province":"CA",
    "sg:tags":[
        "contractor"
    ],
    "wof:name":"Bison Construction Inc",
    "wof:placetype":"venue"
},
  "geometry": {"coordinates":[-117.17970699999999,32.741543],"type":"Point"}
}