{
  "type": "Feature",
  "properties": {
    "iso:country":"US",
    "sg:address":"23030 Greenwood Ave",
    "sg:city":"Torrance",
    "sg:classifiers":[
        {
            "category":"Wholesale",
            "subcategory":"Apparel",
            "type":"Manufacturing & Wholesale Goods"
        }
    ],
    "sg:phone":"+1 310 325 5370",
    "sg:postcode":"90505",
    "sg:province":"CA",
    "sg:tags":[
        "piece",
        "fabric"
    ],
    "wof:name":"Sonoda International",
    "wof:placetype":"venue"
},
  "geometry": {"coordinates":[-118.33471,33.817173],"type":"Point"}
}