{
  "type": "Feature",
  "properties": {
    "iso:country":"US",
    "sg:address":"18626 Knapp St",
    "sg:city":"Northridge",
    "sg:classifiers":[
        {
            "category":"Professional",
            "subcategory":"Accounting & Tax Preparation",
            "type":"Services"
        }
    ],
    "sg:phone":"+1 818 700 1236",
    "sg:postcode":"91324",
    "sg:province":"CA",
    "sg:tags":[
        "return",
        "filing"
    ],
    "wof:name":"Sharon L Ray",
    "wof:placetype":"venue"
},
  "geometry": {"coordinates":[-118.539934,34.238136],"type":"Point"}
}