{
  "type": "Feature",
  "properties": {
    "iso:country":"US",
    "sg:address":"4280 Redwood Hwy",
    "sg:city":"San Rafael",
    "sg:classifiers":[
        {
            "category":"Personal",
            "subcategory":"Barber",
            "type":"Services"
        }
    ],
    "sg:phone":"+1 415 472 4247",
    "sg:postcode":"94903",
    "sg:province":"CA",
    "wof:name":"Hair Exchange",
    "wof:placetype":"venue"
},
  "geometry": {"coordinates":[-122.541259,38.013876],"type":"Point"}
}