{
  "type": "Feature",
  "properties": {
    "addr:full":"3959 Denker Ave Los Angeles CA 90062",
    "addr:housenumber":"3959",
    "addr:postcode":"90062",
    "addr:street":"Denker Ave",
    "iso:country":"US",
    "sg:address":"3959 Denker Ave",
    "sg:city":"Los Angeles",
    "sg:classifiers":[
        {
            "category":"Wholesale",
            "subcategory":"Hardware",
            "type":"Manufacturing & Wholesale Goods"
        }
    ],
    "sg:phone":"+1 323 292 6527",
    "sg:postcode":"90062",
    "sg:province":"CA",
    "sg:tags":[
        "plumbing",
        "computer",
        "custom"
    ],
    "wof:name":"Hydro Clear Systems Inc",
    "wof:placetype":"venue"
},
  "geometry": {"coordinates":[-118.30461699999999,34.012444],"type":"Point"}
}