{
  "type": "Feature",
  "properties": {
    "addr:full":"22926 Mariposa Ave Torrance CA 90502",
    "addr:housenumber":"22926",
    "addr:postcode":"90502",
    "addr:street":"Mariposa Ave",
    "iso:country":"US",
    "sg:address":"22926 Mariposa Ave",
    "sg:city":"Torrance",
    "sg:classifiers":[
        {
            "category":"Building & Trades",
            "subcategory":"Construction",
            "type":"Services"
        }
    ],
    "sg:phone":"+1 310 325 2079",
    "sg:postcode":"90502",
    "sg:province":"CA",
    "sg:tags":[
        "maker",
        "cabinet"
    ],
    "wof:name":"Bundy & Thomas",
    "wof:placetype":"venue"
},
  "geometry": {"coordinates":[-118.297184,33.814128],"type":"Point"}
}