{
  "type": "Feature",
  "properties": {
    "iso:country":"US",
    "sg:address":"2063 S Atlantic Blvd",
    "sg:city":"Monterey Park",
    "sg:classifiers":[
        {
            "category":"Personal",
            "subcategory":"Nail Salon",
            "type":"Services"
        }
    ],
    "sg:phone":"+1 323 263 2899",
    "sg:postcode":"91754",
    "sg:province":"CA",
    "wof:name":"Plus Nails",
    "wof:placetype":"venue"
},
  "geometry": {"coordinates":[-118.14299800000001,34.0396],"type":"Point"}
}