{
  "type": "Feature",
  "properties": {
    "addr:full":"145 Vallecitos de Oro San Marcos CA 92069",
    "addr:housenumber":"145",
    "addr:postcode":"92069",
    "addr:street":"Vallecitos De Oro",
    "iso:country":"US",
    "sg:address":"145 Vallecitos de Oro",
    "sg:city":"San Marcos",
    "sg:classifiers":[
        {
            "category":"Building & Trades",
            "subcategory":"Construction",
            "type":"Services"
        }
    ],
    "sg:phone":"+1 760 591 3996",
    "sg:postcode":"92069",
    "sg:province":"CA",
    "sg:tags":[
        "concrete",
        "contractor"
    ],
    "wof:name":"Bighorn Construction Co",
    "wof:placetype":"venue"
},
  "geometry": {"coordinates":[-117.18022999999999,33.142404],"type":"Point"}
}