{
  "type": "Feature",
  "properties": {
    "addr:full":"23899 Madison St Torrance CA 90505",
    "addr:housenumber":"23899",
    "addr:postcode":"90505",
    "addr:street":"Madison St",
    "iso:country":"US",
    "sg:address":"23899 Madison St",
    "sg:city":"Torrance",
    "sg:classifiers":[
        {
            "category":"Autos & Motor Vehicles",
            "subcategory":"Automobile Sales",
            "type":"Retail Goods"
        }
    ],
    "sg:phone":"+1 310 791 7029",
    "sg:postcode":"90505",
    "sg:province":"CA",
    "sg:tags":[
        "performance",
        "race",
        "dealer"
    ],
    "wof:name":"Podell Industries",
    "wof:placetype":"venue"
},
  "geometry": {"coordinates":[-118.348767,33.810012],"type":"Point"}
}