{
  "type": "Feature",
  "properties": {
    "addr:full":"13905 Equitable Rd Cerritos CA 90703",
    "addr:postcode":"13905;ca 90703",
    "addr:street":"Equitable Rd",
    "iso:country":"US",
    "sg:address":"13905 Equitable Rd",
    "sg:city":"Cerritos",
    "sg:classifiers":[
        {
            "category":"Retail",
            "subcategory":"Laundry & Dry Cleaning",
            "type":"Services"
        }
    ],
    "sg:phone":"+1 888 404 3473",
    "sg:postcode":"90703",
    "sg:province":"CA",
    "sg:tags":[
        "cleaner",
        "rug",
        "carpet"
    ],
    "wof:name":"Masters Emergency and Restoration Services Inc.",
    "wof:placetype":"venue"
},
  "geometry": {"coordinates":[-118.03534000000001,33.878689],"type":"Point"}
}