{
  "type": "Feature",
  "properties": {
    "iso:country":"US",
    "sg:address":"1200 E Hillsdale Blvd",
    "sg:city":"San Mateo",
    "sg:classifiers":[
        {
            "category":"Freight",
            "type":"Transportation"
        }
    ],
    "sg:phone":"+1 415 613 1987",
    "sg:postcode":"94404",
    "sg:province":"CA",
    "sg:tags":[
        "sea",
        "foreign"
    ],
    "wof:name":"Japex International",
    "wof:placetype":"venue"
},
  "geometry": {"coordinates":[-122.26532,37.5693],"type":"Point"}
}