{
  "type": "Feature",
  "properties": {
    "addr:full":"1600 South Douglas Road Anaheim CA 92806",
    "addr:housenumber":"1600",
    "addr:postcode":"92806",
    "addr:street":"South Douglas Road",
    "iso:country":"US",
    "sg:address":"1600 South Douglas Road",
    "sg:city":"Anaheim",
    "sg:classifiers":[
        {
            "category":"Professional",
            "subcategory":"Lawyer & Legal Services",
            "type":"Services"
        }
    ],
    "sg:phone":"+1 800 872 5925",
    "sg:postcode":"92806",
    "sg:province":"CA",
    "sg:website":"www.howardnassiri.com",
    "wof:name":"Howard Nassiri",
    "wof:placetype":"venue"
},
  "geometry": {"coordinates":[-117.893376,33.725252],"type":"Point"}
}