{
  "type": "Feature",
  "properties": {
    "iso:country":"US",
    "sg:address":"4001 Santa Rita Rd",
    "sg:city":"Pleasanton",
    "sg:classifiers":[
        {
            "category":"Ice Cream",
            "type":"Food & Drink"
        }
    ],
    "sg:menulink":"http://www.allmenus.com/ca/livermore-pleasanton/242508-baskin-robbins/menu/",
    "sg:phone":"+1 925 463 3161",
    "sg:postcode":"94588",
    "sg:province":"CA",
    "sg:tags":[
        "american"
    ],
    "wof:name":"Baskin-Robbins",
    "wof:placetype":"venue"
},
  "geometry": {"coordinates":[-121.87460299999999,37.697515],"type":"Point"}
}