{
  "type": "Feature",
  "properties": {
    "addr:full":"1141 Ramona Ln Petaluma CA 94954",
    "addr:housenumber":"1141",
    "addr:postcode":"94954",
    "addr:street":"Ramona Ln",
    "iso:country":"US",
    "sg:address":"1141 Ramona Ln",
    "sg:city":"Petaluma",
    "sg:classifiers":[
        {
            "category":"Building & Trades",
            "subcategory":"Construction",
            "type":"Services"
        }
    ],
    "sg:phone":"+1 707 766 7104",
    "sg:postcode":"94954",
    "sg:province":"CA",
    "sg:tags":[
        "nonresidential"
    ],
    "wof:name":"All Cities Enterprises",
    "wof:placetype":"venue"
},
  "geometry": {"coordinates":[-122.61993699999999,38.239193],"type":"Point"}
}