{
  "type": "Feature",
  "properties": {
    "iso:country":"US",
    "sg:address":"1 Corporate Plaza Dr",
    "sg:city":"Newport Beach",
    "sg:classifiers":[
        {
            "category":"Professional",
            "subcategory":"Lawyer & Legal Services",
            "type":"Services"
        }
    ],
    "sg:phone":"+1 949 759 7888",
    "sg:postcode":"92660",
    "sg:province":"CA",
    "sg:tags":[
        "attorney"
    ],
    "wof:name":"James P Barone",
    "wof:placetype":"venue"
},
  "geometry": {"coordinates":[-117.876835,33.607183],"type":"Point"}
}