{
  "type": "Feature",
  "properties": {
    "addr:full":"27007 McBean Pkwy Valencia CA 91355",
    "addr:postcode":"27007;91355",
    "addr:street":"Mcbean Pkwy",
    "iso:country":"US",
    "sg:address":"27007 McBean Pkwy",
    "sg:city":"Valencia",
    "sg:classifiers":[
        {
            "category":"Restaurant",
            "type":"Food & Drink"
        }
    ],
    "sg:phone":"+1 661 228 2000",
    "sg:postcode":"91355",
    "sg:province":"CA",
    "wof:name":"Arg Enterprises Inc",
    "wof:placetype":"venue"
},
  "geometry": {"coordinates":[-118.562046,34.425725],"type":"Point"}
}