{
  "type": "Feature",
  "properties": {
    "addr:full":"49 Monte Vista Ln Sonora CA 95370",
    "addr:housenumber":"49",
    "addr:postcode":"95370",
    "addr:street":"Monte Vista Ln",
    "iso:country":"US",
    "sg:address":"49 Monte Vista Ln",
    "sg:city":"Sonora",
    "sg:classifiers":[
        {
            "category":"Social Services",
            "type":"Services"
        }
    ],
    "sg:phone":"+1 209 533 0767",
    "sg:postcode":"95370",
    "sg:province":"CA",
    "sg:tags":[
        "counselor",
        "marriage",
        "family"
    ],
    "wof:name":"James P Willey",
    "wof:placetype":"venue"
},
  "geometry": {"coordinates":[-120.381371,37.987877],"type":"Point"}
}