{
  "type": "Feature",
  "properties": {
    "iso:country":"US",
    "sg:address":"9735 Wilshire Blvd",
    "sg:city":"Beverly Hills",
    "sg:classifiers":[
        {
            "category":"Health Services",
            "subcategory":"Doctor",
            "type":"Services"
        }
    ],
    "sg:phone":"+1 310 276 0746",
    "sg:postcode":"90212",
    "sg:province":"CA",
    "sg:tags":[
        "dentist"
    ],
    "wof:name":"Dana L Adams DDS",
    "wof:placetype":"venue"
},
  "geometry": {"coordinates":[-118.406707,34.067071],"type":"Point"}
}