{
  "type": "Feature",
  "properties": {
    "iso:country":"US",
    "sg:address":"7065 Acampo Rd",
    "sg:city":"Acampo",
    "sg:classifiers":[
        {
            "category":"Farming",
            "subcategory":"Livestock Farm",
            "type":"Manufacturing & Wholesale Goods"
        }
    ],
    "sg:phone":"+1 209 334 5800",
    "sg:postcode":"95220",
    "sg:province":"CA",
    "sg:tags":[
        "beekeeper"
    ],
    "wof:name":"Precision Surfaces",
    "wof:placetype":"venue"
},
  "geometry": {"coordinates":[-121.243385,38.174462],"type":"Point"}
}