{
  "type": "Feature",
  "properties": {
    "iso:country":"US",
    "sg:address":"7250 Carson Blvd",
    "sg:city":"Long Beach",
    "sg:classifiers":[
        {
            "category":"Autos & Motor Vehicles",
            "subcategory":"Auto Supplies",
            "type":"Retail Goods"
        }
    ],
    "sg:phone":"+1 562 425 5113",
    "sg:postcode":"90808",
    "sg:province":"CA",
    "sg:tags":[
        "tire"
    ],
    "sg:website":"www.walmart.com",
    "wof:name":"Walmart Tire and Lube",
    "wof:placetype":"venue"
},
  "geometry": {"coordinates":[-118.091279,33.829601],"type":"Point"}
}