{
  "type": "Feature",
  "properties": {
    "addr:full":"1885 E Ventura Blvd Oxnard CA 93036",
    "addr:housenumber":"1885",
    "addr:postcode":"93036",
    "addr:street":"E Ventura Blvd",
    "iso:country":"US",
    "sg:address":"1885 E Ventura Blvd",
    "sg:city":"Oxnard",
    "sg:classifiers":[
        {
            "category":"Shopping",
            "subcategory":"Bicycles & Sporting Goods",
            "type":"Retail Goods"
        }
    ],
    "sg:phone":"+1 805 485 5222",
    "sg:postcode":"93036",
    "sg:province":"CA",
    "wof:name":"Sport Chalet",
    "wof:placetype":"venue"
},
  "geometry": {"coordinates":[-119.16068199999999,34.22599],"type":"Point"}
}