{
  "type": "Feature",
  "properties": {
    "addr:full":"13745 Old Morro Rd Atascadero CA 93422",
    "addr:housenumber":"13745",
    "addr:postcode":"93422",
    "addr:street":"Old Morro Rd",
    "iso:country":"US",
    "sg:address":"13745 Old Morro Rd",
    "sg:city":"Atascadero",
    "sg:classifiers":[
        {
            "category":"Manufacturing",
            "subcategory":"Printing",
            "type":"Manufacturing & Wholesale Goods"
        }
    ],
    "sg:phone":"+1 805 466 9507",
    "sg:postcode":"93422",
    "sg:province":"CA",
    "sg:tags":[
        "book"
    ],
    "wof:name":"Edward A English",
    "wof:placetype":"venue"
},
  "geometry": {"coordinates":[-120.70831200000001,35.45041],"type":"Point"}
}