{
  "type": "Feature",
  "properties": {
    "addr:full":"855 Mathew St Santa Clara CA 95050",
    "addr:housenumber":"855",
    "addr:postcode":"95050",
    "addr:street":"Mathew St",
    "iso:country":"US",
    "sg:address":"855 Mathew St",
    "sg:city":"Santa Clara",
    "sg:classifiers":[
        {
            "category":"Manufacturing",
            "subcategory":"Furniture",
            "type":"Manufacturing & Wholesale Goods"
        }
    ],
    "sg:phone":"+1 408 727 4616",
    "sg:postcode":"95050",
    "sg:province":"CA",
    "sg:tags":[
        "blind"
    ],
    "wof:name":"Louis H Hill Co Inc",
    "wof:placetype":"venue"
},
  "geometry": {"coordinates":[-121.948578,37.363118],"type":"Point"}
}