{
  "type": "Feature",
  "properties": {
    "iso:country":"US",
    "sg:address":"26860 Seco Canyon Rd",
    "sg:city":"Santa Clarita",
    "sg:classifiers":[
        {
            "category":"Organizations",
            "subcategory":"Religious Organization",
            "type":"Services"
        }
    ],
    "sg:phone":"+1 661 296 6784",
    "sg:postcode":"91350",
    "sg:province":"CA",
    "sg:tags":[
        "church"
    ],
    "sg:website":"www.northparkcommunity.org",
    "wof:name":"Northpark Community Church",
    "wof:placetype":"venue"
},
  "geometry": {"coordinates":[-118.532387,34.436727],"type":"Point"}
}