{
  "type": "Feature",
  "properties": {
    "addr:full":"937 Cole Ave Los Angeles CA 90038",
    "addr:housenumber":"937",
    "addr:postcode":"90038",
    "addr:street":"Cole Ave",
    "iso:country":"US",
    "sg:address":"937 Cole Ave",
    "sg:city":"Los Angeles",
    "sg:classifiers":[
        {
            "category":"Retail",
            "subcategory":"Repair Shop",
            "type":"Services"
        }
    ],
    "sg:phone":"+1 323 962 7076",
    "sg:postcode":"90038",
    "sg:province":"CA",
    "sg:tags":[
        "equipment",
        "photographic"
    ],
    "wof:name":"Silvino Pro Flash Rx",
    "wof:placetype":"venue"
},
  "geometry": {"coordinates":[-118.329953,34.088256],"type":"Point"}
}