{
  "type": "Feature",
  "properties": {
    "addr:full":"1544 Fulton St Fresno CA 93721",
    "addr:housenumber":"1544",
    "addr:postcode":"93721",
    "addr:street":"Fulton St",
    "iso:country":"US",
    "sg:address":"1544 Fulton St",
    "sg:city":"Fresno",
    "sg:classifiers":[
        {
            "category":"Arts & Performance",
            "subcategory":"Theater",
            "type":"Entertainment"
        }
    ],
    "sg:phone":"+1 559 486 3333",
    "sg:postcode":"93721",
    "sg:province":"CA",
    "sg:website":"www.theatre3.com",
    "wof:name":"Theatre 3",
    "wof:placetype":"venue"
},
  "geometry": {"coordinates":[-119.796172,36.739467],"type":"Point"}
}