{
  "type": "Feature",
  "properties": {
    "addr:full":"28202 Cabot Rd Ste 300 Laguna Niguel CA 92677",
    "addr:housenumber":"28202",
    "addr:postcode":"92677",
    "addr:street":"Cabot Rd Ste 300",
    "iso:country":"US",
    "sg:address":"28202 Cabot Rd Ste 300",
    "sg:city":"Laguna Niguel",
    "sg:classifiers":[
        {
            "category":"Professional",
            "subcategory":"Lawyer & Legal Services",
            "type":"Services"
        }
    ],
    "sg:phone":"+1 949 661 3300",
    "sg:postcode":"92677",
    "sg:province":"CA",
    "sg:tags":[
        "divorce",
        "law",
        "family"
    ],
    "wof:name":"Hoy William T Atty",
    "wof:placetype":"venue"
},
  "geometry": {"coordinates":[-117.679001,33.551998],"type":"Point"}
}