{
  "type": "Feature",
  "properties": {
    "addr:full":"PO Box 35518 Los Angeles CA 90035",
    "addr:housenumber":"po box 35518",
    "addr:postcode":"90035",
    "iso:country":"US",
    "sg:address":"PO Box 35518",
    "sg:city":"Los Angeles",
    "sg:classifiers":[
        {
            "category":"Food & Beverages",
            "subcategory":"Candy",
            "type":"Retail Goods"
        }
    ],
    "sg:phone":"+1 323 938 0518",
    "sg:postcode":"90035",
    "sg:province":"CA",
    "sg:tags":[
        "store"
    ],
    "wof:name":"Uncle Darrow's Cajun Candy Company Inc",
    "wof:placetype":"venue"
},
  "geometry": {"coordinates":[-118.38200399999999,34.0518],"type":"Point"}
}