{
  "type": "Feature",
  "properties": {
    "addr:full":"4900 Topanga Canyon Blvd. Topanga Cyn & Dumetz Woodland Hills CA 91364",
    "addr:housenumber":"4900",
    "addr:postcode":"91364",
    "addr:street":"Topanga Canyon Blvd.",
    "iso:country":"US",
    "sg:address":"4900 Topanga Canyon Blvd. Topanga Cyn & Dumetz",
    "sg:city":"Woodland Hills",
    "sg:classifiers":[
        {
            "category":"Coffee & Tea",
            "type":"Food & Drink"
        }
    ],
    "sg:phone":"+1 818 704 1730",
    "sg:postcode":"91364",
    "sg:province":"CA",
    "wof:name":"Starbucks",
    "wof:placetype":"venue"
},
  "geometry": {"coordinates":[-118.605441,34.157177],"type":"Point"}
}