{
  "type": "Feature",
  "properties": {
    "addr:full":"9501 Balboa Blvd Northridge CA 91325",
    "addr:housenumber":"9501",
    "addr:postcode":"91325",
    "addr:street":"Balboa Blvd",
    "iso:country":"US",
    "sg:address":"9501 Balboa Blvd",
    "sg:city":"Northridge",
    "sg:classifiers":[
        {
            "category":"Education",
            "subcategory":"School",
            "type":"Public Place"
        }
    ],
    "sg:phone":"+1 818 886 6751",
    "sg:postcode":"91325",
    "sg:province":"CA",
    "sg:tags":[
        "religious"
    ],
    "wof:name":"St Nicholas School",
    "wof:placetype":"venue"
},
  "geometry": {"coordinates":[-118.502458,34.244182],"type":"Point"}
}