{
  "type": "Feature",
  "properties": {
    "iso:country":"US",
    "sg:address":"9454 Corbin Ave",
    "sg:city":"Northridge",
    "sg:classifiers":[
        {
            "category":"Autos & Motor Vehicles",
            "subcategory":"Fuel & Gas Station",
            "type":"Retail Goods"
        }
    ],
    "sg:phone":"+1 818 993 7120",
    "sg:postcode":"91324",
    "sg:province":"CA",
    "sg:tags":[
        "oil"
    ],
    "wof:name":"Arco Palace",
    "wof:placetype":"venue"
},
  "geometry": {"coordinates":[-118.562235,34.239915],"type":"Point"}
}