{
  "type": "Feature",
  "properties": {
    "iso:country":"US",
    "sg:address":"3885 Convoy St",
    "sg:city":"San Diego",
    "sg:classifiers":[
        {
            "category":"Retail",
            "subcategory":"Auto Repair",
            "type":"Services"
        }
    ],
    "sg:phone":"+1 858 571 7768",
    "sg:postcode":"92111",
    "sg:province":"CA",
    "sg:tags":[
        "automobile",
        "customizing"
    ],
    "wof:name":"San Diego Auto Connection",
    "wof:placetype":"venue"
},
  "geometry": {"coordinates":[-117.153388,32.811315],"type":"Point"}
}