{
  "type": "Feature",
  "properties": {
    "iso:country":"US",
    "sg:address":"2118 Willow Pass Rd Ste 100b",
    "sg:city":"Concord",
    "sg:classifiers":[
        {
            "category":"Restaurant",
            "type":"Food & Drink"
        }
    ],
    "sg:menulink":"http://www.allmenus.com/ca/central-contra-costa/285025-luna-restaurante/menu/",
    "sg:phone":"+1 925 691 4080",
    "sg:postcode":"94520",
    "sg:province":"CA",
    "sg:tags":[
        "italian"
    ],
    "wof:name":"Luna Restaurante",
    "wof:placetype":"venue"
},
  "geometry": {"coordinates":[-122.033413,37.976497],"type":"Point"}
}