{
  "type": "Feature",
  "properties": {
    "iso:country":"US",
    "sg:address":"6740 Kester Ave",
    "sg:city":"Van Nuys",
    "sg:classifiers":[
        {
            "category":"Organizations",
            "subcategory":"Non-profit Organization",
            "type":"Services"
        }
    ],
    "sg:phone":"+1 818 994 7454",
    "sg:postcode":"91405",
    "sg:province":"CA",
    "sg:tags":[
        "info",
        "addiction",
        "abuse",
        "treatment",
        "drug"
    ],
    "wof:name":"I-Adarp",
    "wof:placetype":"venue"
},
  "geometry": {"coordinates":[-118.45737800000001,34.193889],"type":"Point"}
}