{
  "type": "Feature",
  "properties": {
    "iso:country":"US",
    "sg:address":"23361 Golden Springs Dr",
    "sg:city":"Diamond Bar",
    "sg:classifiers":[
        {
            "category":"Professional",
            "type":"Services"
        }
    ],
    "sg:phone":"+1 909 861 8520",
    "sg:postcode":"91765",
    "sg:province":"CA",
    "wof:name":"Xarposh",
    "wof:placetype":"venue"
},
  "geometry": {"coordinates":[-117.810969,34.017343],"type":"Point"}
}