{
  "type": "Feature",
  "properties": {
    "iso:country":"US",
    "sg:address":"14930 Oka Road",
    "sg:city":"Los Gatos",
    "sg:classifiers":[
        {
            "category":"Real Estate",
            "subcategory":"Real Estate Operator",
            "type":"Services"
        }
    ],
    "sg:phone":"+1 408 356 3145",
    "sg:postcode":"95032",
    "sg:province":"CA",
    "sg:tags":[
        "apartment"
    ],
    "wof:name":"La Mar Apartments",
    "wof:placetype":"venue"
},
  "geometry": {"coordinates":[-121.955387,37.238858],"type":"Point"}
}