{
  "type": "Feature",
  "properties": {
    "iso:country":"US",
    "sg:address":"705 Venice Blvd",
    "sg:city":"Venice",
    "sg:classifiers":[
        {
            "category":"Shopping",
            "type":"Retail Goods"
        }
    ],
    "sg:phone":"+1 310 821 5373",
    "sg:postcode":"90291",
    "sg:province":"CA",
    "sg:tags":[
        "used",
        "merchandise"
    ],
    "wof:name":"Antique Art Boutique",
    "wof:placetype":"venue"
},
  "geometry": {"coordinates":[-118.458656,33.990827],"type":"Point"}
}