{
  "type": "Feature",
  "properties": {
    "addr:full":"2 Main St San Quentin CA 94964",
    "addr:housenumber":"2",
    "addr:postcode":"94964",
    "addr:street":"Main St",
    "iso:country":"US",
    "sg:address":"2 Main St",
    "sg:city":"San Quentin",
    "sg:classifiers":[
        {
            "category":"Social Services",
            "type":"Services"
        }
    ],
    "sg:phone":"+1 415 456 4200",
    "sg:postcode":"94964",
    "sg:province":"CA",
    "sg:tags":[
        "organization",
        "welfare"
    ],
    "wof:name":"House At San Quentin",
    "wof:placetype":"venue"
},
  "geometry": {"coordinates":[-122.482546,37.941732],"type":"Point"}
}