{
  "type": "Feature",
  "properties": {
    "addr:full":"6917 Valjean Ave Van Nuys CA 91406",
    "addr:housenumber":"6917",
    "addr:postcode":"91406",
    "addr:street":"Valjean Ave",
    "iso:country":"US",
    "sg:address":"6917 Valjean Ave",
    "sg:city":"Van Nuys",
    "sg:classifiers":[
        {
            "category":"Wholesale",
            "subcategory":"Electrical",
            "type":"Manufacturing & Wholesale Goods"
        }
    ],
    "sg:phone":"+1 818 285 6888",
    "sg:postcode":"91406",
    "sg:province":"CA",
    "sg:tags":[
        "equipment",
        "electronic",
        "supply"
    ],
    "sg:website":"www.valutone.com",
    "wof:name":"Volutone",
    "wof:placetype":"venue"
},
  "geometry": {"coordinates":[-118.485913,34.196118],"type":"Point"}
}