{
  "type": "Feature",
  "properties": {
    "iso:country":"US",
    "sg:address":"14630 Kinley Dr",
    "sg:city":"Healdsburg",
    "sg:classifiers":[
        {
            "category":"Shopping",
            "subcategory":"Bicycles & Sporting Goods",
            "type":"Retail Goods"
        }
    ],
    "sg:phone":"+1 707 431 4212",
    "sg:postcode":"95448",
    "sg:province":"CA",
    "wof:name":"Russian River Tack",
    "wof:placetype":"venue"
},
  "geometry": {"coordinates":[-122.879418,38.615486],"type":"Point"}
}