{
  "type": "Feature",
  "properties": {
    "addr:full":"8109 Winter Gardens Blvd Lakeside CA 92040",
    "addr:housenumber":"8109",
    "addr:postcode":"92040",
    "addr:street":"Winter Gardens Blvd",
    "iso:country":"US",
    "sg:address":"8109 Winter Gardens Blvd",
    "sg:city":"Lakeside",
    "sg:classifiers":[
        {
            "category":"Wholesale",
            "subcategory":"Auto Parts",
            "type":"Manufacturing & Wholesale Goods"
        }
    ],
    "sg:phone":"+1 619 390 1592",
    "sg:postcode":"92040",
    "sg:province":"CA",
    "sg:tags":[
        "tire"
    ],
    "wof:name":"Imperial Tire Inc",
    "wof:placetype":"venue"
},
  "geometry": {"coordinates":[-116.933499,32.825891],"type":"Point"}
}