{
  "type": "Feature",
  "properties": {
    "addr:full":"1385 W Blaine St Riverside CA 92507",
    "addr:housenumber":"1385",
    "addr:postcode":"92507",
    "addr:street":"W Blaine St",
    "iso:country":"US",
    "sg:address":"1385 W Blaine St",
    "sg:city":"Riverside",
    "sg:classifiers":[
        {
            "category":"Shopping",
            "subcategory":"Tobacco",
            "type":"Retail Goods"
        },
        {
            "category":"Wholesale",
            "subcategory":"Construction Materials",
            "type":"Manufacturing & Wholesale Goods"
        }
    ],
    "sg:phone":"+1 951 684 4818",
    "sg:postcode":"92507",
    "sg:province":"CA",
    "sg:tags":[
        "pipe",
        "cigarette",
        "cigar",
        "smoker",
        "article"
    ],
    "wof:name":"Smoke And More",
    "wof:placetype":"venue"
},
  "geometry": {"coordinates":[-117.34145100000001,33.982991],"type":"Point"}
}