{
  "type": "Feature",
  "properties": {
    "addr:full":"12759 Brandt Rd Lockeford CA 95237",
    "addr:housenumber":"12759",
    "addr:postcode":"95237",
    "addr:street":"Brandt Rd",
    "iso:country":"US",
    "sg:address":"12759 Brandt Rd",
    "sg:city":"Lockeford",
    "sg:classifiers":[
        {
            "category":"Retail",
            "subcategory":"Auto Repair",
            "type":"Services"
        }
    ],
    "sg:phone":"+1 209 727 0732",
    "sg:postcode":"95237",
    "sg:province":"CA",
    "sg:tags":[
        "body",
        "automobile",
        "painting"
    ],
    "wof:name":"Auto House",
    "wof:placetype":"venue"
},
  "geometry": {"coordinates":[-121.166044,38.146894],"type":"Point"}
}