{
  "type": "Feature",
  "properties": {
    "iso:country":"US",
    "sg:address":"65265 San Jacinto Ln",
    "sg:city":"Desert Hot Spgs",
    "sg:classifiers":[
        {
            "category":"Manufacturing",
            "subcategory":"Tools & Machinery",
            "type":"Manufacturing & Wholesale Goods"
        }
    ],
    "sg:phone":"+1 760 288 2234",
    "sg:postcode":"92240",
    "sg:province":"CA",
    "sg:tags":[
        "equipment",
        "conveyor",
        "conveying"
    ],
    "wof:name":"Lift Equipment Inc",
    "wof:placetype":"venue"
},
  "geometry": {"coordinates":[-116.526018,33.94483],"type":"Point"}
}