{
  "type": "Feature",
  "properties": {
    "iso:country":"US",
    "sg:address":"10715 Villa Bonita",
    "sg:city":"Spring Valley",
    "sg:classifiers":[
        {
            "category":"Personal",
            "type":"Services"
        }
    ],
    "sg:phone":"+1 619 670 0213",
    "sg:postcode":"91978",
    "sg:province":"CA",
    "sg:tags":[
        "therapist",
        "massage"
    ],
    "wof:name":"Advanced Health Therapeutics",
    "wof:placetype":"venue"
},
  "geometry": {"coordinates":[-116.96405,32.735241],"type":"Point"}
}