{
  "type": "Feature",
  "properties": {
    "addr:full":"13370 Kirkham Way Poway CA 92064",
    "addr:housenumber":"13370",
    "addr:postcode":"ca 92064",
    "addr:street":"Kirkham Way",
    "iso:country":"US",
    "sg:address":"13370 Kirkham Way",
    "sg:city":"Poway",
    "sg:classifiers":[
        {
            "category":"Building & Trades",
            "subcategory":"Construction",
            "type":"Services"
        }
    ],
    "sg:phone":"+1 858 513 6580",
    "sg:postcode":"92064",
    "sg:province":"CA",
    "sg:tags":[
        "contractor"
    ],
    "wof:name":"I-TEC Installation Technology",
    "wof:placetype":"venue"
},
  "geometry": {"coordinates":[-117.045761,32.93509],"type":"Point"}
}