{
  "type": "Feature",
  "properties": {
    "iso:country":"US",
    "sg:address":"1242 Hermosa Ave",
    "sg:city":"Hermosa Beach",
    "sg:classifiers":[
        {
            "category":"Shopping",
            "subcategory":"Clothing, Apparel, & Fashions",
            "type":"Retail Goods"
        }
    ],
    "sg:phone":"+1 310 372 7906",
    "sg:postcode":"90254",
    "sg:province":"CA",
    "wof:name":"Fernando's",
    "wof:placetype":"venue"
},
  "geometry": {"coordinates":[-118.40012,33.862925],"type":"Point"}
}