{
  "type": "Feature",
  "properties": {
    "iso:country":"US",
    "sg:address":"939 Sierra St",
    "sg:city":"Kingsburg",
    "sg:classifiers":[
        {
            "category":"Cinema",
            "subcategory":"Movie Rental",
            "type":"Entertainment"
        }
    ],
    "sg:phone":"+1 559 897 8903",
    "sg:postcode":"93631",
    "sg:province":"CA",
    "sg:tags":[
        "leasing",
        "video",
        "disc",
        "tape"
    ],
    "wof:name":"Blockbuster Video",
    "wof:placetype":"venue"
},
  "geometry": {"coordinates":[-119.557455,36.517985],"type":"Point"}
}