{
  "type": "Feature",
  "properties": {
    "addr:full":"565 Pier Ave Hermosa Beach CA 90254",
    "addr:housenumber":"565",
    "addr:postcode":"90254",
    "addr:street":"Pier Ave",
    "iso:country":"US",
    "sg:address":"565 Pier Ave",
    "sg:city":"Hermosa Beach",
    "sg:classifiers":[
        {
            "category":"Government",
            "subcategory":"Post Office",
            "type":"Public Place"
        }
    ],
    "sg:phone":"+1 310 000 1111",
    "sg:postcode":"90254",
    "sg:province":"CA",
    "wof:name":"US Post Office",
    "wof:placetype":"venue"
},
  "geometry": {"coordinates":[-118.39577300000001,33.864583],"type":"Point"}
}