{
  "type": "Feature",
  "properties": {
    "iso:country":"US",
    "sg:address":"3303 Harbor Boulevard",
    "sg:city":"Costa Mesa",
    "sg:classifiers":[
        {
            "category":"Insurance",
            "subcategory":"Health Insurance",
            "type":"Services"
        }
    ],
    "sg:phone":"+1 949 645 7373",
    "sg:postcode":"92626",
    "sg:province":"CA",
    "sg:tags":[
        "market"
    ],
    "wof:name":"Shaklee Products Distributors",
    "wof:placetype":"venue"
},
  "geometry": {"coordinates":[-117.919594,33.691696],"type":"Point"}
}