{
  "type": "Feature",
  "properties": {
    "addr:full":"531 Jefferson St Napa CA 94559",
    "addr:housenumber":"531",
    "addr:postcode":"94559",
    "addr:street":"Jefferson St",
    "iso:country":"US",
    "sg:address":"531 Jefferson St",
    "sg:city":"Napa",
    "sg:classifiers":[
        {
            "category":"Health Services",
            "subcategory":"Health Practitioner",
            "type":"Services"
        }
    ],
    "sg:phone":"+1 707 224 6810",
    "sg:postcode":"94559",
    "sg:province":"CA",
    "sg:tags":[
        "psychologist"
    ],
    "wof:name":"Judith Speed PHD",
    "wof:placetype":"venue"
},
  "geometry": {"coordinates":[-122.29407,38.29366],"type":"Point"}
}