{
  "type": "Feature",
  "properties": {
    "addr:full":"1600 Kings Rd Newport Beach CA 92663",
    "addr:housenumber":"1600",
    "addr:postcode":"92663",
    "addr:street":"Kings Rd",
    "iso:country":"US",
    "sg:address":"1600 Kings Rd",
    "sg:city":"Newport Beach",
    "sg:classifiers":[
        {
            "category":"Real Estate",
            "subcategory":"Developer",
            "type":"Services"
        }
    ],
    "sg:phone":"+1 949 477 4717",
    "sg:postcode":"92663",
    "sg:province":"CA",
    "sg:tags":[
        "insurance"
    ],
    "wof:name":"Pridelands",
    "wof:placetype":"venue"
},
  "geometry": {"coordinates":[-117.91567499999999,33.617538],"type":"Point"}
}