{
  "type": "Feature",
  "properties": {
    "addr:full":"11003 Main St Lamont CA 93241",
    "addr:housenumber":"11003",
    "addr:postcode":"93241",
    "addr:street":"Main St",
    "iso:country":"US",
    "sg:address":"11003 Main St",
    "sg:city":"Lamont",
    "sg:classifiers":[
        {
            "category":"Insurance",
            "subcategory":"Insurance Agent",
            "type":"Services"
        }
    ],
    "sg:phone":"+1 661 845 1397",
    "sg:postcode":"93241",
    "sg:province":"CA",
    "wof:name":"Garcia & Assoc",
    "wof:placetype":"venue"
},
  "geometry": {"coordinates":[-118.914332,35.254893],"type":"Point"}
}