{
  "type": "Feature",
  "properties": {
    "iso:country":"US",
    "sg:address":"5204 Dietrich Rd",
    "sg:city":"Brawley",
    "sg:classifiers":[
        {
            "category":"Wholesale",
            "subcategory":"Machinery & Supplies",
            "type":"Manufacturing & Wholesale Goods"
        }
    ],
    "sg:phone":"+1 760 344 3360",
    "sg:postcode":"92227",
    "sg:province":"CA",
    "sg:tags":[
        "farm",
        "equipment"
    ],
    "wof:name":"Cox Equipment Co",
    "wof:placetype":"venue"
},
  "geometry": {"coordinates":[-115.488716,33.044298],"type":"Point"}
}