{
  "type": "Feature",
  "properties": {
    "iso:country":"US",
    "sg:address":"21335 Monterra",
    "sg:city":"Lake Forest",
    "sg:classifiers":[
        {
            "category":"Shopping",
            "subcategory":"Music",
            "type":"Retail Goods"
        }
    ],
    "sg:phone":"+1 949 369 6902",
    "sg:postcode":"92630",
    "sg:province":"CA",
    "sg:tags":[
        "video",
        "disc",
        "tape",
        "cassette"
    ],
    "wof:name":"Star Video",
    "wof:placetype":"venue"
},
  "geometry": {"coordinates":[-117.668432,33.653091],"type":"Point"}
}