{
  "type": "Feature",
  "properties": {
    "addr:full":"5825 W Sunset Blvd Los Angeles CA 90028",
    "addr:housenumber":"5825",
    "addr:postcode":"90028",
    "addr:street":"W Sunset Blvd",
    "iso:country":"US",
    "sg:address":"5825 W Sunset Blvd",
    "sg:city":"Los Angeles",
    "sg:classifiers":[
        {
            "category":"Government",
            "subcategory":"Office",
            "type":"Public Place"
        }
    ],
    "sg:phone":"+1 323 469 7343",
    "sg:postcode":"90028",
    "sg:province":"CA",
    "sg:tags":[
        "international",
        "affairs"
    ],
    "wof:name":"Consulate Of Belize",
    "wof:placetype":"venue"
},
  "geometry": {"coordinates":[-118.317516,34.098126],"type":"Point"}
}