{
  "type": "Feature",
  "properties": {
    "iso:country":"US",
    "sg:address":"23142 Alcalde Dr Ste D2",
    "sg:city":"Laguna Hills",
    "sg:classifiers":[
        {
            "category":"Home & Garden",
            "subcategory":"Carpets & Floor Coverings",
            "type":"Retail Goods"
        }
    ],
    "sg:phone":"+1 949 837 3184",
    "sg:postcode":"92653",
    "sg:province":"CA",
    "sg:tags":[
        "flooring"
    ],
    "wof:name":"Marshall's Design",
    "wof:placetype":"venue"
},
  "geometry": {"coordinates":[-117.726207,33.622339],"type":"Point"}
}