{
  "type": "Feature",
  "properties": {
    "iso:country":"US",
    "sg:address":"5555 Jackson Dr",
    "sg:city":"La Mesa",
    "sg:classifiers":[
        {
            "category":"Wholesale",
            "subcategory":"Machinery & Supplies",
            "type":"Manufacturing & Wholesale Goods"
        }
    ],
    "sg:phone":"+1 619 741 7757",
    "sg:postcode":"91942",
    "sg:province":"CA",
    "sg:tags":[
        "carpet",
        "cleaning",
        "rug"
    ],
    "wof:name":"Mold Inspection & Lab Test",
    "wof:placetype":"venue"
},
  "geometry": {"coordinates":[-117.018797,32.780584],"type":"Point"}
}