{
  "type": "Feature",
  "properties": {
    "iso:country":"US",
    "sg:address":"1188 Padre Dr",
    "sg:city":"Salinas",
    "sg:classifiers":[
        {
            "category":"Insurance",
            "subcategory":"Insurance Agent",
            "type":"Services"
        }
    ],
    "sg:phone":"+1 831 753 5815",
    "sg:postcode":"93901",
    "sg:province":"CA",
    "wof:name":"Critchfield & Assoc",
    "wof:placetype":"venue"
},
  "geometry": {"coordinates":[-121.661436,36.659558],"type":"Point"}
}