{
  "type": "Feature",
  "properties": {
    "addr:full":"43700 17th St W Lancaster CA 93534",
    "addr:housenumber":"43700",
    "addr:postcode":"93534",
    "addr:street":"17Th St W",
    "iso:country":"US",
    "sg:address":"43700 17th St W",
    "sg:city":"Lancaster",
    "sg:classifiers":[
        {
            "category":"Health Services",
            "subcategory":"Doctor",
            "type":"Services"
        }
    ],
    "sg:phone":"+1 661 948 0557",
    "sg:postcode":"93534",
    "sg:province":"CA",
    "sg:tags":[
        "dentist"
    ],
    "wof:name":"Melissa C Nabors DDS",
    "wof:placetype":"venue"
},
  "geometry": {"coordinates":[-118.161208,34.675832],"type":"Point"}
}