{
  "type": "Feature",
  "properties": {
    "iso:country":"US",
    "sg:address":"411 Grand Avenue",
    "sg:city":"Oakland",
    "sg:classifiers":[
        {
            "category":"Health Services",
            "subcategory":"Health Practitioner",
            "type":"Services"
        }
    ],
    "sg:phone":"+1 510 465 3338",
    "sg:postcode":"94610",
    "sg:province":"CA",
    "sg:tags":[
        "therapy",
        "physical"
    ],
    "wof:name":"Advanced Physical Medicine & Rehab Group",
    "wof:placetype":"venue"
},
  "geometry": {"coordinates":[-122.253557,37.808692],"type":"Point"}
}