{
  "type": "Feature",
  "properties": {
    "addr:full":"221 Encinal St Santa Cruz CA 95060",
    "addr:housenumber":"221",
    "addr:postcode":"95060",
    "addr:street":"Encinal St",
    "iso:country":"US",
    "sg:address":"221 Encinal St",
    "sg:city":"Santa Cruz",
    "sg:classifiers":[
        {
            "category":"Building & Trades",
            "subcategory":"Construction",
            "type":"Services"
        }
    ],
    "sg:phone":"+1 831 429 8904",
    "sg:postcode":"95060",
    "sg:province":"CA",
    "sg:tags":[
        "contractor"
    ],
    "sg:website":"rcrfabrication.com",
    "wof:name":"RCR Fabrications",
    "wof:placetype":"venue"
},
  "geometry": {"coordinates":[-122.03306000000001,36.986682],"type":"Point"}
}