{
  "type": "Feature",
  "properties": {
    "addr:full":"710 Green Valley Rd Watsonville CA 95076",
    "addr:housenumber":"710",
    "addr:postcode":"95076",
    "addr:street":"Green Valley Rd",
    "iso:country":"US",
    "sg:address":"710 Green Valley Rd",
    "sg:city":"Watsonville",
    "sg:classifiers":[
        {
            "category":"Social Services",
            "subcategory":"Child Care",
            "type":"Services"
        }
    ],
    "sg:phone":"+1 831 722 7811",
    "sg:postcode":"95076",
    "sg:province":"CA",
    "sg:tags":[
        "kindergarten",
        "academic",
        "school"
    ],
    "wof:name":"Noah's Ark Pre-School & Day Cr",
    "wof:placetype":"venue"
},
  "geometry": {"coordinates":[-121.764943,36.962845],"type":"Point"}
}