{
  "type": "Feature",
  "properties": {
    "iso:country":"US",
    "sg:address":"3397 Saint Helena Hwy",
    "sg:city":"St Helena",
    "sg:classifiers":[
        {
            "category":"Farming",
            "subcategory":"Vineyard",
            "type":"Manufacturing & Wholesale Goods"
        },
        {
            "category":"Manufacturing",
            "subcategory":"Food",
            "type":"Manufacturing & Wholesale Goods"
        }
    ],
    "sg:phone":"+1 707 967 5500",
    "sg:postcode":"94574",
    "sg:province":"CA",
    "sg:tags":[
        "grape",
        "winery"
    ],
    "wof:name":"Engel Family Vineyards",
    "wof:placetype":"venue"
},
  "geometry": {"coordinates":[-122.508791,38.541498],"type":"Point"}
}