{
  "type": "Feature",
  "properties": {
    "iso:country":"US",
    "sg:address":"2239 Honolulu Ave",
    "sg:city":"Montrose",
    "sg:classifiers":[
        {
            "category":"Shopping",
            "subcategory":"Clothing, Apparel, & Fashions",
            "type":"Retail Goods"
        }
    ],
    "sg:phone":"+1 818 249 8095",
    "sg:postcode":"91020",
    "sg:province":"CA",
    "sg:tags":[
        "accessory",
        "clothing",
        "women's"
    ],
    "sg:website":"www.anniesscandal.com",
    "wof:name":"Annie's Scandal",
    "wof:placetype":"venue"
},
  "geometry": {"coordinates":[-118.225998,34.205101],"type":"Point"}
}