{
  "type": "Feature",
  "properties": {
    "addr:full":"17722 Pioneer Blvd Artesia CA 90701",
    "addr:housenumber":"17722",
    "addr:postcode":"90701",
    "addr:street":"Pioneer Blvd",
    "iso:country":"US",
    "sg:address":"17722 Pioneer Blvd",
    "sg:city":"Artesia",
    "sg:phone":"+1 562 402 1171",
    "sg:postcode":"90701",
    "sg:province":"CA",
    "wof:name":"The Property Management Company",
    "wof:placetype":"venue"
},
  "geometry": {"coordinates":[-118.082185,33.869964],"type":"Point"}
}