{
  "type": "Feature",
  "properties": {
    "addr:full":"1020 N 4th St San Jose CA 95112",
    "addr:housenumber":"1020",
    "addr:postcode":"95112",
    "addr:street":"N 4Th St",
    "iso:country":"US",
    "sg:address":"1020 N 4th St",
    "sg:city":"San Jose",
    "sg:classifiers":[
        {
            "category":"Shopping",
            "type":"Retail Goods"
        },
        {
            "category":"Food & Beverages",
            "subcategory":"Groceries & Convenience Stores",
            "type":"Retail Goods"
        }
    ],
    "sg:phone":"+1 408 286 3636",
    "sg:postcode":"95112",
    "sg:province":"CA",
    "wof:name":"Truong Hung Supermarket",
    "wof:placetype":"venue"
},
  "geometry": {"coordinates":[-121.902,37.357201],"type":"Point"}
}