{
  "type": "Feature",
  "properties": {
    "iso:country":"US",
    "sg:address":"2416 W Tahoe St",
    "sg:city":"Caruthers",
    "sg:classifiers":[
        {
            "category":"Restaurant",
            "type":"Food & Drink"
        }
    ],
    "sg:phone":"+1 559 864 2021",
    "sg:postcode":"93609",
    "sg:province":"CA",
    "wof:name":"Tacos Y Marsicos Colima",
    "wof:placetype":"venue"
},
  "geometry": {"coordinates":[-119.835399,36.540655],"type":"Point"}
}