{
  "type": "Feature",
  "properties": {
    "addr:full":"11812 Wilmington Ave Los Angeles CA 90059",
    "addr:housenumber":"11812",
    "addr:postcode":"90059",
    "addr:street":"Wilmington Ave",
    "iso:country":"US",
    "sg:address":"11812 Wilmington Ave",
    "sg:city":"Los Angeles",
    "sg:classifiers":[
        {
            "category":"Fast Food",
            "type":"Food & Drink"
        },
        {
            "category":"Food & Beverages",
            "subcategory":"Bakery",
            "type":"Retail Goods"
        }
    ],
    "sg:phone":"+1 323 567 7009",
    "sg:postcode":"90059",
    "sg:province":"CA",
    "sg:tags":[
        "sandwich"
    ],
    "sg:website":"www.subway.com",
    "wof:name":"Subway",
    "wof:placetype":"venue"
},
  "geometry": {"coordinates":[-118.239029,33.92591],"type":"Point"}
}