{
  "type": "Feature",
  "properties": {
    "iso:country":"US",
    "sg:address":"1309 Saviers Rd",
    "sg:city":"Oxnard",
    "sg:classifiers":[
        {
            "category":"Food & Beverages",
            "subcategory":"Liquor & Beverages",
            "type":"Retail Goods"
        }
    ],
    "sg:phone":"+1 805 483 0830",
    "sg:postcode":"93033",
    "sg:province":"CA",
    "wof:name":"Crown's Market Liquor",
    "wof:placetype":"venue"
},
  "geometry": {"coordinates":[-119.17753399999999,34.186338],"type":"Point"}
}