{
  "type": "Feature",
  "properties": {
    "addr:full":"2424 Clement St San Francisco CA 94121",
    "addr:housenumber":"2424",
    "addr:postcode":"94121",
    "addr:street":"Clement St",
    "iso:country":"US",
    "sg:address":"2424 Clement St",
    "sg:city":"San Francisco",
    "sg:classifiers":[
        {
            "category":"Education",
            "subcategory":"Special Training",
            "type":"Public Place"
        }
    ],
    "sg:phone":"+1 415 305 1703",
    "sg:postcode":"94121",
    "sg:province":"CA",
    "sg:tags":[
        "school",
        "tutoring",
        "specialty"
    ],
    "sg:website":"www.quantumleapschool.com",
    "wof:name":"Quantum Leap School",
    "wof:placetype":"venue"
},
  "geometry": {"coordinates":[-122.485361,37.78205],"type":"Point"}
}