{
  "type": "Feature",
  "properties": {
    "iso:country":"US",
    "sg:address":"1704 W 2nd St",
    "sg:city":"Santa Ana",
    "sg:classifiers":[
        {
            "category":"Personal",
            "subcategory":"Barber",
            "type":"Services"
        }
    ],
    "sg:phone":"+1 714 835 0243",
    "sg:postcode":"92703",
    "sg:province":"CA",
    "wof:name":"Duke's Barber Shop",
    "wof:placetype":"venue"
},
  "geometry": {"coordinates":[-117.891998,33.7463],"type":"Point"}
}