{
  "type": "Feature",
  "properties": {
    "addr:full":"11320 Bullis Rd Lynwood CA 90262",
    "addr:housenumber":"11320",
    "addr:postcode":"90262",
    "addr:street":"Bullis Rd",
    "iso:country":"US",
    "sg:address":"11320 Bullis Rd",
    "sg:city":"Lynwood",
    "sg:classifiers":[
        {
            "category":"Education",
            "subcategory":"Library",
            "type":"Public Place"
        }
    ],
    "sg:phone":"+1 310 635 7121",
    "sg:postcode":"90262",
    "sg:province":"CA",
    "sg:tags":[
        "educational",
        "program",
        "administrative"
    ],
    "wof:name":"County Public Library",
    "wof:placetype":"venue"
},
  "geometry": {"coordinates":[-118.199423,33.927237],"type":"Point"}
}