{
  "type": "Feature",
  "properties": {
    "iso:country":"US",
    "sg:address":"25555 Hesperian Blvd",
    "sg:city":"Hayward",
    "sg:classifiers":[
        {
            "category":"Shopping",
            "subcategory":"Books",
            "type":"Retail Goods"
        }
    ],
    "sg:phone":"+1 510 783 9800",
    "sg:postcode":"94545",
    "sg:province":"CA",
    "sg:tags":[
        "university",
        "college"
    ],
    "sg:website":"www.chabotbookstore.com",
    "wof:name":"Chabot College",
    "wof:placetype":"venue"
},
  "geometry": {"coordinates":[-122.101997,37.640099],"type":"Point"}
}