{
  "type": "Feature",
  "properties": {
    "iso:country":"US",
    "sg:address":"1540 E Amar Rd",
    "sg:city":"West Covina",
    "sg:classifiers":[
        {
            "category":"Autos & Motor Vehicles",
            "subcategory":"Auto Supplies",
            "type":"Retail Goods"
        }
    ],
    "sg:phone":"+1 626 810 9936",
    "sg:postcode":"91792",
    "sg:province":"CA",
    "sg:tags":[
        "automobile",
        "parts"
    ],
    "wof:name":"Pep Boys Supercenter",
    "wof:placetype":"venue"
},
  "geometry": {"coordinates":[-117.91413799999999,34.030903],"type":"Point"}
}