{
  "type": "Feature",
  "properties": {
    "iso:country":"US",
    "sg:address":"755 Wall Street",
    "sg:city":"Los Angeles",
    "sg:classifiers":[
        {
            "category":"Home & Garden",
            "subcategory":"Garden Supply",
            "type":"Retail Goods"
        }
    ],
    "sg:phone":"+1 213 624 0937",
    "sg:postcode":"90014",
    "sg:province":"CA",
    "sg:tags":[
        "nursery",
        "gardening"
    ],
    "wof:name":"Kono & Sons",
    "wof:placetype":"venue"
},
  "geometry": {"coordinates":[-118.249038,34.041279],"type":"Point"}
}