{
  "type": "Feature",
  "properties": {
    "addr:full":"2502 N Main St Santa Ana CA 92706",
    "addr:housenumber":"2502",
    "addr:postcode":"92706",
    "addr:street":"N Main St",
    "iso:country":"US",
    "sg:address":"2502 N Main St",
    "sg:city":"Santa Ana",
    "sg:classifiers":[
        {
            "category":"Retail",
            "subcategory":"Auto Rental",
            "type":"Services"
        }
    ],
    "sg:phone":"+1 714 535 1700",
    "sg:postcode":"92706",
    "sg:province":"CA",
    "sg:tags":[
        "truck",
        "leasing"
    ],
    "wof:name":"Penske",
    "wof:placetype":"venue"
},
  "geometry": {"coordinates":[-117.86742700000001,33.772077],"type":"Point"}
}