{
  "type": "Feature",
  "properties": {
    "addr:full":"1511 Railroad St Corona CA 92880",
    "addr:housenumber":"1511",
    "addr:postcode":"92880",
    "addr:street":"Railroad St",
    "iso:country":"US",
    "sg:address":"1511 Railroad St",
    "sg:city":"Corona",
    "sg:classifiers":[
        {
            "category":"Wholesale",
            "subcategory":"Construction Materials",
            "type":"Manufacturing & Wholesale Goods"
        }
    ],
    "sg:phone":"+1 951 273 0394",
    "sg:postcode":"92880",
    "sg:province":"CA",
    "sg:tags":[
        "granite"
    ],
    "wof:name":"Marble Man Stone Shapers",
    "wof:placetype":"venue"
},
  "geometry": {"coordinates":[-117.59261100000001,33.891418],"type":"Point"}
}