{
  "type": "Feature",
  "properties": {
    "addr:full":"6440 Bellaire Ave North Hollywood CA 91606",
    "addr:housenumber":"6440",
    "addr:postcode":"91606",
    "addr:street":"Bellaire Ave",
    "iso:country":"US",
    "sg:address":"6440 Bellaire Ave",
    "sg:city":"North Hollywood",
    "sg:classifiers":[
        {
            "category":"Building & Trades",
            "subcategory":"Construction",
            "type":"Services"
        }
    ],
    "sg:phone":"+1 818 508 1415",
    "sg:postcode":"91606",
    "sg:province":"CA",
    "sg:tags":[
        "house",
        "remodeling",
        "general"
    ],
    "wof:name":"Environmental Home Improvement",
    "wof:placetype":"venue"
},
  "geometry": {"coordinates":[-118.40898300000001,34.190182],"type":"Point"}
}