{
  "type": "Feature",
  "properties": {
    "iso:country":"US",
    "sg:address":"10349 Long Beach Blvd",
    "sg:city":"Lynwood",
    "sg:classifiers":[
        {
            "category":"Insurance",
            "subcategory":"Hazard Insurance",
            "type":"Services"
        }
    ],
    "sg:phone":"+1 323 566 1625",
    "sg:postcode":"90262",
    "sg:province":"CA",
    "sg:tags":[
        "commercial",
        "business"
    ],
    "wof:name":"La Popular De Seguros",
    "wof:placetype":"venue"
},
  "geometry": {"coordinates":[-118.21468400000001,33.940587],"type":"Point"}
}