{
  "type": "Feature",
  "properties": {
    "addr:full":"8782 Gardena Rd Lakeside CA 92040",
    "addr:housenumber":"8782",
    "addr:postcode":"92040",
    "addr:street":"Gardena Rd",
    "iso:country":"US",
    "sg:address":"8782 Gardena Rd",
    "sg:city":"Lakeside",
    "sg:classifiers":[
        {
            "category":"Professional",
            "type":"Services"
        }
    ],
    "sg:phone":"+1 619 561 3072",
    "sg:postcode":"92040",
    "sg:province":"CA",
    "wof:name":"Thomas R Hopster",
    "wof:placetype":"venue"
},
  "geometry": {"coordinates":[-116.93592700000001,32.836796],"type":"Point"}
}