{
  "type": "Feature",
  "properties": {
    "iso:country":"US",
    "sg:address":"785 N Mary Ave",
    "sg:city":"Sunnyvale",
    "sg:classifiers":[
        {
            "category":"Professional",
            "subcategory":"Computer Services",
            "type":"Services"
        }
    ],
    "sg:phone":"+1 408 542 7500",
    "sg:postcode":"94085",
    "sg:province":"CA",
    "sg:tags":[
        "publisher",
        "software",
        "developer",
        "services-wholesale"
    ],
    "sg:website":"http://www.centrify.com",
    "wof:name":"Centrify Corp",
    "wof:placetype":"venue"
},
  "geometry": {"coordinates":[-122.03532800000001,37.398035],"type":"Point"}
}