{
  "type": "Feature",
  "properties": {
    "iso:country":"US",
    "sg:address":"17759 Buttercup Cir",
    "sg:city":"Sonora",
    "sg:classifiers":[
        {
            "category":"Professional",
            "subcategory":"Business Services",
            "type":"Services"
        }
    ],
    "sg:phone":"+1 209 532 7320",
    "sg:postcode":"95370",
    "sg:province":"CA",
    "sg:tags":[
        "tank",
        "testing",
        "inspection"
    ],
    "wof:name":"Alltech Consulting",
    "wof:placetype":"venue"
},
  "geometry": {"coordinates":[-120.305981,37.945419],"type":"Point"}
}