{
  "type": "Feature",
  "properties": {
    "iso:country":"US",
    "sg:address":"16020 S Western Ave",
    "sg:city":"Gardena",
    "sg:classifiers":[
        {
            "category":"Education",
            "subcategory":"School",
            "type":"Public Place"
        }
    ],
    "sg:phone":"+1 310 323 3886",
    "sg:postcode":"90247",
    "sg:province":"CA",
    "wof:name":"Pacific Highlands Academy",
    "wof:placetype":"venue"
},
  "geometry": {"coordinates":[-118.30906,33.885772],"type":"Point"}
}