{
  "type": "Feature",
  "properties": {
    "iso:country":"US",
    "sg:address":"Saint Francis Memorial Hospital 900 Hyde St",
    "sg:city":"San Francisco",
    "sg:classifiers":[
        {
            "category":"Health Services",
            "subcategory":"Doctor",
            "type":"Services"
        }
    ],
    "sg:phone":"+1 415 667 0905",
    "sg:postcode":"94109",
    "sg:province":"CA",
    "sg:tags":[
        "pediatrician",
        "psychiatrist"
    ],
    "wof:name":"Christian Secord, MD",
    "wof:placetype":"venue"
},
  "geometry": {"coordinates":[-122.41704900000001,37.789675],"type":"Point"}
}