{
  "type": "Feature",
  "properties": {
    "iso:country":"US",
    "sg:address":"14321 Bear Valley Rd",
    "sg:city":"Victorville",
    "sg:classifiers":[
        {
            "category":"Fast Food",
            "type":"Food & Drink"
        },
        {
            "category":"Restaurant",
            "type":"Food & Drink"
        }
    ],
    "sg:phone":"+1 760 244 3800",
    "sg:postcode":"92392",
    "sg:province":"CA",
    "sg:tags":[
        "style",
        "take",
        "family"
    ],
    "wof:name":"Archibald's Restaurant",
    "wof:placetype":"venue"
},
  "geometry": {"coordinates":[-117.349615,34.470409],"type":"Point"}
}