{
  "type": "Feature",
  "properties": {
    "addr:full":"1227 W 14th St San Pedro CA 90731",
    "addr:housenumber":"1227",
    "addr:postcode":"90731",
    "addr:street":"W 14Th St",
    "iso:country":"US",
    "sg:address":"1227 W 14th St",
    "sg:city":"San Pedro",
    "sg:classifiers":[
        {
            "category":"Wholesale",
            "subcategory":"Machinery & Supplies",
            "type":"Manufacturing & Wholesale Goods"
        }
    ],
    "sg:phone":"+1 310 514 2163",
    "sg:postcode":"90731",
    "sg:province":"CA",
    "sg:tags":[
        "equipment",
        "product",
        "strapping"
    ],
    "wof:name":"N & J Enterprises Inc",
    "wof:placetype":"venue"
},
  "geometry": {"coordinates":[-118.3051,33.731485],"type":"Point"}
}