{
  "type": "Feature",
  "properties": {
    "iso:country":"US",
    "sg:address":"4031 Governor Dr",
    "sg:city":"San Diego",
    "sg:classifiers":[
        {
            "category":"Personal",
            "subcategory":"Beauty Salon",
            "type":"Services"
        },
        {
            "category":"Personal",
            "subcategory":"Barber",
            "type":"Services"
        }
    ],
    "sg:phone":"+1 858 453 0407",
    "sg:postcode":"92122",
    "sg:province":"CA",
    "sg:tags":[
        "hair"
    ],
    "wof:name":"University Square Barber Shop",
    "wof:placetype":"venue"
},
  "geometry": {"coordinates":[-117.202609,32.854525],"type":"Point"}
}