{
  "type": "Feature",
  "properties": {
    "iso:country":"US",
    "sg:address":"2102 Glacier Ln",
    "sg:city":"Santa Maria",
    "sg:classifiers":[
        {
            "category":"Professional",
            "type":"Services"
        }
    ],
    "sg:phone":"+1 805 937 2469",
    "sg:postcode":"93455",
    "sg:province":"CA",
    "wof:name":"Minor Oma",
    "wof:placetype":"venue"
},
  "geometry": {"coordinates":[-120.380726,34.869556],"type":"Point"}
}