{
  "type": "Feature",
  "properties": {
    "iso:country":"US",
    "sg:address":"25524 Aragon Way",
    "sg:city":"Yorba Linda",
    "sg:classifiers":[
        {
            "category":"Building & Trades",
            "subcategory":"Landscaping Services",
            "type":"Services"
        }
    ],
    "sg:phone":"+1 714 694 0155",
    "sg:postcode":"92887",
    "sg:province":"CA",
    "wof:name":"Fk Landscape Maintenance",
    "wof:placetype":"venue"
},
  "geometry": {"coordinates":[-117.704564,33.874545],"type":"Point"}
}