{
  "type": "Feature",
  "properties": {
    "iso:country":"US",
    "sg:address":"9618 Garden Grove Blvd",
    "sg:city":"Garden Grove",
    "sg:classifiers":[
        {
            "category":"Travel",
            "subcategory":"Travel Agent",
            "type":"Entertainment"
        }
    ],
    "sg:phone":"+1 714 638 8877",
    "sg:postcode":"92844",
    "sg:province":"CA",
    "sg:tags":[
        "agency"
    ],
    "wof:name":"Kd Travel & Tour",
    "wof:placetype":"venue"
},
  "geometry": {"coordinates":[-117.96554500000001,33.773903],"type":"Point"}
}