{
  "type": "Feature",
  "properties": {
    "iso:country":"US",
    "sg:address":"1100 S Maple Ave",
    "sg:city":"Montebello",
    "sg:classifiers":[
        {
            "category":"Retail",
            "subcategory":"Auto Repair",
            "type":"Services"
        }
    ],
    "sg:phone":"+1 323 722 5553",
    "sg:postcode":"90640",
    "sg:province":"CA",
    "sg:tags":[
        "lettering",
        "truck"
    ],
    "wof:name":"B & M Truck Body Repair",
    "wof:placetype":"venue"
},
  "geometry": {"coordinates":[-118.124905,33.994878],"type":"Point"}
}