{
  "type": "Feature",
  "properties": {
    "addr:full":"1782 Orange Tree Ln Redlands CA 92374",
    "addr:housenumber":"1782",
    "addr:postcode":"92374",
    "addr:street":"Orange Tree Ln",
    "iso:country":"US",
    "sg:address":"1782 Orange Tree Ln",
    "sg:city":"Redlands",
    "sg:classifiers":[
        {
            "category":"Banks & Credit Unions",
            "subcategory":"Investment Brokerage",
            "type":"Services"
        }
    ],
    "sg:phone":"+1 909 307 8220",
    "sg:postcode":"92374",
    "sg:province":"CA",
    "sg:tags":[
        "security"
    ],
    "wof:name":"KWB & Assoc Inc",
    "wof:placetype":"venue"
},
  "geometry": {"coordinates":[-117.21382800000001,34.067912],"type":"Point"}
}