{
  "type": "Feature",
  "properties": {
    "addr:full":"327 W D St Lemoore CA 93245",
    "addr:housenumber":"327",
    "addr:postcode":"93245",
    "addr:street":"W D St",
    "iso:country":"US",
    "sg:address":"327 W D St",
    "sg:city":"Lemoore",
    "sg:classifiers":[
        {
            "category":"Shopping",
            "subcategory":"Clothing, Apparel, & Fashions",
            "type":"Retail Goods"
        }
    ],
    "sg:phone":"+1 559 925 9120",
    "sg:postcode":"93245",
    "sg:province":"CA",
    "sg:tags":[
        "uniform"
    ],
    "wof:name":"Valley Uniforms & Formal Wear",
    "wof:placetype":"venue"
},
  "geometry": {"coordinates":[-119.78521600000001,36.301652],"type":"Point"}
}