{
  "type": "Feature",
  "properties": {
    "iso:country":"US",
    "sg:address":"2816 W Pico Blvd",
    "sg:city":"Los Angeles",
    "sg:classifiers":[
        {
            "category":"Personal",
            "subcategory":"Beauty Salon",
            "type":"Services"
        }
    ],
    "sg:phone":"+1 323 735 1122",
    "sg:postcode":"90006",
    "sg:province":"CA",
    "wof:name":"Lupe's Beauty Salon",
    "wof:placetype":"venue"
},
  "geometry": {"coordinates":[-118.30061000000001,34.047151],"type":"Point"}
}