{
  "type": "Feature",
  "properties": {
    "iso:country":"US",
    "sg:address":"50 W Bullard Ave",
    "sg:city":"Clovis",
    "sg:classifiers":[
        {
            "category":"Personal",
            "subcategory":"Beauty Salon",
            "type":"Services"
        }
    ],
    "sg:phone":"+1 559 297 1967",
    "sg:postcode":"93612",
    "sg:province":"CA",
    "wof:name":"Hair By Darlene & Maycelle",
    "wof:placetype":"venue"
},
  "geometry": {"coordinates":[-119.70992699999999,36.822933],"type":"Point"}
}