{
  "type": "Feature",
  "properties": {
    "iso:country":"US",
    "sg:address":"1511 6th St",
    "sg:city":"Norco",
    "sg:classifiers":[
        {
            "category":"Restaurant",
            "type":"Food & Drink"
        }
    ],
    "sg:menulink":"http://www.allmenus.com/ca/norco/216042-mcdonalds/menu/",
    "sg:postcode":"92860",
    "sg:province":"CA",
    "sg:tags":[
        "burger",
        "american"
    ],
    "wof:name":"McDonald's",
    "wof:placetype":"venue"
},
  "geometry": {"coordinates":[-117.55471,33.938298],"type":"Point"}
}