{
  "type": "Feature",
  "properties": {
    "addr:full":"2033 Adonis Way Sacramento CA 95864",
    "addr:housenumber":"2033",
    "addr:postcode":"95864",
    "addr:street":"Adonis Way",
    "iso:country":"US",
    "sg:address":"2033 Adonis Way",
    "sg:city":"Sacramento",
    "sg:classifiers":[
        {
            "category":"Professional",
            "subcategory":"Employment Agencies",
            "type":"Services"
        }
    ],
    "sg:phone":"+1 916 481 8092",
    "sg:postcode":"95864",
    "sg:province":"CA",
    "sg:website":"www.cooperpersonnel.com",
    "wof:name":"Cooper Personnel Services",
    "wof:placetype":"venue"
},
  "geometry": {"coordinates":[-121.35745300000001,38.602749],"type":"Point"}
}