{
  "type": "Feature",
  "properties": {
    "iso:country":"US",
    "sg:address":"21937 Highway 46",
    "sg:city":"Lost Hills",
    "sg:classifiers":[
        {
            "category":"Restaurant",
            "type":"Food & Drink"
        }
    ],
    "sg:menulink":"http://www.allmenus.com/ca/wasco/171056-carls-jr/menu/",
    "sg:phone":"+1 661 797 2542",
    "sg:postcode":"93249",
    "sg:province":"CA",
    "sg:tags":[
        "burger",
        "american"
    ],
    "wof:name":"Carl's Jr.",
    "wof:placetype":"venue"
},
  "geometry": {"coordinates":[-119.659678,35.615717],"type":"Point"}
}