{
  "type": "Feature",
  "properties": {
    "iso:country":"US",
    "sg:address":"750 Columbia St",
    "sg:city":"Brea",
    "sg:classifiers":[
        {
            "category":"Wholesale",
            "subcategory":"Hardware",
            "type":"Manufacturing & Wholesale Goods"
        }
    ],
    "sg:phone":"+1 714 671 3888",
    "sg:postcode":"92821",
    "sg:province":"CA",
    "sg:tags":[
        "fixture"
    ],
    "wof:name":"Aspen Interiors",
    "wof:placetype":"venue"
},
  "geometry": {"coordinates":[-117.908365,33.930362],"type":"Point"}
}