{
  "type": "Feature",
  "properties": {
    "addr:full":"28035 Dorothy Dr Agoura Hills CA 91301",
    "addr:housenumber":"28035",
    "addr:postcode":"91301",
    "addr:street":"Dorothy Dr",
    "iso:country":"US",
    "sg:address":"28035 Dorothy Dr",
    "sg:city":"Agoura Hills",
    "sg:classifiers":[
        {
            "category":"Professional",
            "subcategory":"Management & Consulting",
            "type":"Services"
        }
    ],
    "sg:phone":"+1 818 991 6509",
    "sg:postcode":"91301",
    "sg:province":"CA",
    "sg:tags":[
        "food"
    ],
    "wof:name":"Sodexho",
    "wof:placetype":"venue"
},
  "geometry": {"coordinates":[-118.73721,34.142088],"type":"Point"}
}