{
  "type": "Feature",
  "properties": {
    "iso:country":"US",
    "sg:address":"791 Price St",
    "sg:city":"Pismo Beach",
    "sg:classifiers":[
        {
            "category":"Real Estate",
            "subcategory":"Real Estate Agent",
            "type":"Services"
        }
    ],
    "sg:phone":"+1 805 773 1200",
    "sg:postcode":"93449",
    "sg:province":"CA",
    "sg:tags":[
        "rental",
        "vacation"
    ],
    "wof:name":"Maya's Vacation Rentals",
    "wof:placetype":"venue"
},
  "geometry": {"coordinates":[-120.64015999999999,35.141703],"type":"Point"}
}