{
  "type": "Feature",
  "properties": {
    "addr:full":"2055 Chenault Pl Simi Valley CA 93065",
    "addr:housenumber":"2055",
    "addr:postcode":"93065",
    "addr:street":"Chenault Pl",
    "iso:country":"US",
    "sg:address":"2055 Chenault Pl",
    "sg:city":"Simi Valley",
    "sg:classifiers":[
        {
            "category":"Professional",
            "type":"Services"
        }
    ],
    "sg:phone":"+1 661 478 2237",
    "sg:postcode":"93065",
    "sg:province":"CA",
    "wof:name":"Coupons Galore",
    "wof:placetype":"venue"
},
  "geometry": {"coordinates":[-118.809501,34.273052],"type":"Point"}
}