{
  "type": "Feature",
  "properties": {
    "addr:full":"414 Lano St San Jose CA 95125",
    "addr:housenumber":"414",
    "addr:postcode":"95125",
    "addr:street":"Lano St",
    "iso:country":"US",
    "sg:address":"414 Lano St",
    "sg:city":"San Jose",
    "sg:classifiers":[
        {
            "category":"Building & Trades",
            "subcategory":"Plumbing",
            "type":"Services"
        },
        {
            "category":"Building & Trades",
            "subcategory":"Construction",
            "type":"Services"
        }
    ],
    "sg:phone":"+1 408 613 6566",
    "sg:postcode":"95125",
    "sg:province":"CA",
    "sg:tags":[
        "contractor"
    ],
    "sg:website":"www.mrrescueplumbing.com/sanjose",
    "wof:name":"Mr Rescue Plumbing & Drain Cleaning of San Jose",
    "wof:placetype":"venue"
},
  "geometry": {"coordinates":[-121.877438,37.305809],"type":"Point"}
}