{
  "type": "Feature",
  "properties": {
    "addr:full":"1914 S Bundy Dr Los Angeles CA 90025",
    "addr:housenumber":"1914",
    "addr:postcode":"90025",
    "addr:street":"S Bundy Dr",
    "iso:country":"US",
    "sg:address":"1914 S Bundy Dr",
    "sg:city":"Los Angeles",
    "sg:classifiers":[
        {
            "category":"Health Services",
            "subcategory":"Health Practitioner",
            "type":"Services"
        }
    ],
    "sg:phone":"+1 310 979 0951",
    "sg:postcode":"90025",
    "sg:province":"CA",
    "sg:tags":[
        "therapist",
        "physical"
    ],
    "wof:name":"Aquatic Rehab Sport Med",
    "wof:placetype":"venue"
},
  "geometry": {"coordinates":[-118.455645,34.034149],"type":"Point"}
}