{
  "type": "Feature",
  "properties": {
    "iso:country":"US",
    "sg:address":"415 Tennessee St",
    "sg:city":"Redlands",
    "sg:classifiers":[
        {
            "category":"Manufacturing",
            "subcategory":"Printing",
            "type":"Manufacturing & Wholesale Goods"
        }
    ],
    "sg:phone":"+1 909 798 0122",
    "sg:postcode":"92373",
    "sg:province":"CA",
    "sg:tags":[
        "commercial",
        "printer",
        "lithographic"
    ],
    "wof:name":"PIP Printing",
    "wof:placetype":"venue"
},
  "geometry": {"coordinates":[-117.200181,34.060585],"type":"Point"}
}