{
  "type": "Feature",
  "properties": {
    "iso:country":"US",
    "sg:address":"3959 Wilshire Blvd #B27",
    "sg:city":"Los Angeles",
    "sg:classifiers":[
        {
            "category":"Personal",
            "subcategory":"Massage",
            "type":"Services"
        }
    ],
    "sg:phone":"+1 213 739 9990",
    "sg:postcode":"90010",
    "sg:province":"CA",
    "wof:name":"Serene Thai Massage",
    "wof:placetype":"venue"
},
  "geometry": {"coordinates":[-118.313299,34.062039],"type":"Point"}
}