{
  "type": "Feature",
  "properties": {
    "addr:full":"2250 Central St Richmond CA 94801",
    "addr:housenumber":"2250",
    "addr:postcode":"94801",
    "addr:street":"Central St",
    "iso:country":"US",
    "sg:address":"2250 Central St",
    "sg:city":"Richmond",
    "sg:classifiers":[
        {
            "category":"Personal",
            "type":"Services"
        }
    ],
    "sg:phone":"+1 510 965 1112",
    "sg:postcode":"94801",
    "sg:province":"CA",
    "sg:tags":[
        "property",
        "maintenance"
    ],
    "wof:name":"Upsi",
    "wof:placetype":"venue"
},
  "geometry": {"coordinates":[-122.36985,37.964648],"type":"Point"}
}