{
  "type": "Feature",
  "properties": {
    "iso:country":"US",
    "sg:address":"3549 Cam del Rio S",
    "sg:city":"San Diego",
    "sg:classifiers":[
        {
            "category":"Health Services",
            "subcategory":"Health Practitioner",
            "type":"Services"
        }
    ],
    "sg:phone":"+1 619 281 0616",
    "sg:postcode":"92108",
    "sg:province":"CA",
    "sg:tags":[
        "psychologist"
    ],
    "wof:name":"Green & Green Phd's",
    "wof:placetype":"venue"
},
  "geometry": {"coordinates":[-117.11891,32.777407],"type":"Point"}
}