{
  "type": "Feature",
  "properties": {
    "addr:full":"1200 Vine St Los Angeles CA 90038",
    "addr:housenumber":"1200",
    "addr:postcode":"90038",
    "addr:street":"Vine St",
    "iso:country":"US",
    "sg:address":"1200 Vine St",
    "sg:city":"Los Angeles",
    "sg:classifiers":[
        {
            "category":"Shopping",
            "subcategory":"Thrift Store",
            "type":"Retail Goods"
        }
    ],
    "sg:phone":"+1 323 469 2357",
    "sg:postcode":"90038",
    "sg:province":"CA",
    "wof:name":"Goodwill",
    "wof:placetype":"venue"
},
  "geometry": {"coordinates":[-118.325996,34.0928],"type":"Point"}
}