{
  "type": "Feature",
  "properties": {
    "addr:full":"231 S Grevillea Avenue Inglewood CA 90301",
    "addr:housenumber":"231",
    "addr:postcode":"90301",
    "addr:street":"S Grevillea Avenue",
    "iso:country":"US",
    "sg:address":"231 S Grevillea Avenue",
    "sg:city":"Inglewood",
    "sg:classifiers":[
        {
            "category":"Education",
            "subcategory":"School",
            "type":"Public Place"
        }
    ],
    "sg:phone":"+1 310 680 5200",
    "sg:postcode":"90301",
    "sg:province":"CA",
    "sg:tags":[
        "high",
        "middle",
        "elementary"
    ],
    "wof:name":"Inglewood Unified School District",
    "wof:placetype":"venue"
},
  "geometry": {"coordinates":[-118.354883,33.961318],"type":"Point"}
}