{
  "type": "Feature",
  "properties": {
    "addr:full":"4981 Twin Pines Loop Georgetown CA 95634",
    "addr:housenumber":"4981",
    "addr:postcode":"95634",
    "addr:street":"Twin Pines Loop",
    "iso:country":"US",
    "sg:address":"4981 Twin Pines Loop",
    "sg:city":"Georgetown",
    "sg:classifiers":[
        {
            "category":"Building & Trades",
            "subcategory":"Landscaping Services",
            "type":"Services"
        }
    ],
    "sg:phone":"+1 530 333 0795",
    "sg:postcode":"95634",
    "sg:province":"CA",
    "wof:name":"Miyamotos Lawn & Garden Svc",
    "wof:placetype":"venue"
},
  "geometry": {"coordinates":[-120.833608,38.86433],"type":"Point"}
}