{
  "type": "Feature",
  "properties": {
    "iso:country":"US",
    "sg:address":"638 Lindero Canyon Rd",
    "sg:city":"Agoura Hills",
    "sg:classifiers":[
        {
            "category":"Wholesale",
            "subcategory":"Durable Goods & Equipment",
            "type":"Manufacturing & Wholesale Goods"
        }
    ],
    "sg:phone":"+1 818 865 8678",
    "sg:postcode":"91377",
    "sg:province":"CA",
    "wof:name":"Fluid Systems Sales Co",
    "wof:placetype":"venue"
},
  "geometry": {"coordinates":[-118.78650399999999,34.182276],"type":"Point"}
}