{
  "type": "Feature",
  "properties": {
    "addr:full":"3565 N de Lay Ave Covina CA 91723",
    "addr:housenumber":"3565",
    "addr:postcode":"91723",
    "addr:street":"N De Lay Ave",
    "iso:country":"US",
    "sg:address":"3565 N de Lay Ave",
    "sg:city":"Covina",
    "sg:classifiers":[
        {
            "category":"Banks & Credit Unions",
            "subcategory":"Financial Services",
            "type":"Services"
        }
    ],
    "sg:phone":"+1 626 332 3739",
    "sg:postcode":"91723",
    "sg:province":"CA",
    "sg:tags":[
        "trust",
        "investment",
        "real estate"
    ],
    "wof:name":"Mary G Buerger Trust",
    "wof:placetype":"venue"
},
  "geometry": {"coordinates":[-117.87429299999999,34.080796],"type":"Point"}
}