{
  "type": "Feature",
  "properties": {
    "iso:country":"US",
    "sg:address":"2645 Greenvalley Rd",
    "sg:city":"Los Angeles",
    "sg:classifiers":[
        {
            "category":"Insurance",
            "subcategory":"Health Insurance",
            "type":"Services"
        }
    ],
    "sg:phone":"+1 888 388 8723",
    "sg:postcode":"90046",
    "sg:province":"CA",
    "sg:tags":[
        "carrier"
    ],
    "wof:name":"Thru Traffic",
    "wof:placetype":"venue"
},
  "geometry": {"coordinates":[-118.391428,34.117071],"type":"Point"}
}