{
  "type": "Feature",
  "properties": {
    "iso:country":"US",
    "sg:address":"7572 Autumn Chase Dr",
    "sg:city":"Highland",
    "sg:classifiers":[
        {
            "category":"Building & Trades",
            "subcategory":"Electrical",
            "type":"Services"
        }
    ],
    "sg:phone":"+1 909 864 4183",
    "sg:postcode":"92346",
    "sg:province":"CA",
    "sg:tags":[
        "electrical",
        "contractor"
    ],
    "wof:name":"Flanagan Electric",
    "wof:placetype":"venue"
},
  "geometry": {"coordinates":[-117.179952,34.116203],"type":"Point"}
}