{
  "type": "Feature",
  "properties": {
    "addr:full":"16019 Adelante St Irwindale CA 91702",
    "addr:postcode":"16019;91702",
    "addr:street":"Adelante St",
    "iso:country":"US",
    "sg:address":"16019 Adelante St",
    "sg:city":"Irwindale",
    "sg:classifiers":[
        {
            "category":"Manufacturing",
            "subcategory":"Tools & Machinery",
            "type":"Manufacturing & Wholesale Goods"
        }
    ],
    "sg:phone":"+1 626 334 0298",
    "sg:postcode":"91702",
    "sg:province":"CA",
    "sg:tags":[
        "plastic"
    ],
    "wof:name":"A J Brewer Specialties",
    "wof:placetype":"venue"
},
  "geometry": {"coordinates":[-117.93135700000001,34.126718],"type":"Point"}
}