{
  "type": "Feature",
  "properties": {
    "addr:full":"1586 Industrial Ave San Jose CA 95112",
    "addr:housenumber":"1586",
    "addr:postcode":"95112",
    "addr:street":"Industrial Ave",
    "iso:country":"US",
    "sg:address":"1586 Industrial Ave",
    "sg:city":"San Jose",
    "sg:classifiers":[
        {
            "category":"Retail",
            "subcategory":"Auto Rental",
            "type":"Services"
        }
    ],
    "sg:phone":"+1 408 292 2113",
    "sg:postcode":"95112",
    "sg:province":"CA",
    "sg:tags":[
        "trailer",
        "utility"
    ],
    "wof:name":"Cruise America Inc",
    "wof:placetype":"venue"
},
  "geometry": {"coordinates":[-121.89841199999999,37.369056],"type":"Point"}
}