{
  "type": "Feature",
  "properties": {
    "iso:country":"US",
    "sg:address":"700 S Lake Ave",
    "sg:city":"Pasadena",
    "sg:classifiers":[
        {
            "category":"Real Estate",
            "subcategory":"Real Estate Agent",
            "type":"Services"
        }
    ],
    "sg:phone":"+1 626 524 0711",
    "sg:postcode":"91106",
    "sg:province":"CA",
    "wof:name":"Four Percent Solution",
    "wof:placetype":"venue"
},
  "geometry": {"coordinates":[-118.132166,34.133683],"type":"Point"}
}