{
  "type": "Feature",
  "properties": {
    "addr:full":"2950 Sycamore Dr Simi Valley CA 93065",
    "addr:housenumber":"2950",
    "addr:postcode":"93065",
    "addr:street":"Sycamore Dr",
    "iso:country":"US",
    "sg:address":"2950 Sycamore Dr",
    "sg:city":"Simi Valley",
    "sg:classifiers":[
        {
            "category":"Health Services",
            "subcategory":"Doctor",
            "type":"Services"
        }
    ],
    "sg:phone":"+1 805 527 6400",
    "sg:postcode":"93065",
    "sg:province":"CA",
    "sg:tags":[
        "dentist"
    ],
    "wof:name":"Ted Chaffee DDS",
    "wof:placetype":"venue"
},
  "geometry": {"coordinates":[-118.743904,34.28762],"type":"Point"}
}