{
  "type": "Feature",
  "properties": {
    "addr:full":"27795 Mission Blvd Hayward CA 94544",
    "addr:housenumber":"27795",
    "addr:postcode":"94544",
    "addr:street":"Mission Blvd",
    "iso:country":"US",
    "sg:address":"27795 Mission Blvd",
    "sg:city":"Hayward",
    "sg:classifiers":[
        {
            "category":"Autos & Motor Vehicles",
            "subcategory":"Automobile Sales",
            "type":"Retail Goods"
        }
    ],
    "sg:phone":"+1 510 881 2277",
    "sg:postcode":"94544",
    "sg:province":"CA",
    "sg:tags":[
        "car",
        "used"
    ],
    "sg:website":"http://www.baycityautosales.com",
    "wof:name":"Bay City Auto",
    "wof:placetype":"venue"
},
  "geometry": {"coordinates":[-122.058609,37.640511],"type":"Point"}
}