{
  "type": "Feature",
  "properties": {
    "iso:country":"US",
    "sg:address":"4050 Mariposa Dr",
    "sg:city":"Santa Barbara",
    "sg:classifiers":[
        {
            "category":"Wholesale",
            "subcategory":"Non-durable Goods",
            "type":"Manufacturing & Wholesale Goods"
        }
    ],
    "sg:phone":"+1 805 682 4330",
    "sg:postcode":"93110",
    "sg:province":"CA",
    "wof:name":"E P I",
    "wof:placetype":"venue"
},
  "geometry": {"coordinates":[-119.757194,34.411251],"type":"Point"}
}