{
  "type": "Feature",
  "properties": {
    "iso:country":"US",
    "sg:address":"120 Essex Ct",
    "sg:city":"San Bruno",
    "sg:classifiers":[
        {
            "category":"Retail",
            "subcategory":"Auto Repair",
            "type":"Services"
        }
    ],
    "sg:phone":"+1 650 875 9323",
    "sg:postcode":"94066",
    "sg:province":"CA",
    "sg:tags":[
        "repairing",
        "automobile",
        "radiator"
    ],
    "wof:name":"G & G Radiator",
    "wof:placetype":"venue"
},
  "geometry": {"coordinates":[-122.433043,37.62061],"type":"Point"}
}