{
  "type": "Feature",
  "properties": {
    "addr:full":"4760 S Broadway Los Angeles CA 90037",
    "addr:housenumber":"4760",
    "addr:postcode":"90037",
    "addr:street":"S Broadway",
    "iso:country":"US",
    "sg:address":"4760 S Broadway",
    "sg:city":"Los Angeles",
    "sg:classifiers":[
        {
            "category":"Travel",
            "subcategory":"Hotels & Motels",
            "type":"Entertainment"
        }
    ],
    "sg:phone":"+1 323 232 2011",
    "sg:postcode":"90037",
    "sg:province":"CA",
    "wof:name":"Crown Inn",
    "wof:placetype":"venue"
},
  "geometry": {"coordinates":[-118.27800000000001,33.9995],"type":"Point"}
}