{
  "type": "Feature",
  "properties": {
    "iso:country":"US",
    "sg:address":"321 W Avenue S G",
    "sg:city":"Palmdale",
    "sg:classifiers":[
        {
            "category":"Professional",
            "type":"Services"
        },
        {
            "category":"Personal",
            "type":"Services"
        },
        {
            "category":"Retail",
            "subcategory":"Storage",
            "type":"Services"
        }
    ],
    "sg:phone":"+1 661 949 1077",
    "sg:postcode":"93551",
    "sg:province":"CA",
    "sg:tags":[
        "moving-self",
        "full",
        "material",
        "movers-commercial",
        "industrial",
        "moving",
        "services-labor",
        "mover"
    ],
    "wof:name":"D & L Movers",
    "wof:placetype":"venue"
},
  "geometry": {"coordinates":[-118.130528,34.631145],"type":"Point"}
}