{
  "type": "Feature",
  "properties": {
    "addr:full":"281 Yamane Dr Gilroy CA 95020",
    "addr:housenumber":"281",
    "addr:postcode":"95020",
    "addr:street":"Yamane Dr",
    "iso:country":"US",
    "sg:address":"281 Yamane Dr",
    "sg:city":"Gilroy",
    "sg:classifiers":[
        {
            "category":"Wholesale",
            "subcategory":"Construction Materials",
            "type":"Manufacturing & Wholesale Goods"
        }
    ],
    "sg:phone":"+1 408 842 0022",
    "sg:postcode":"95020",
    "sg:province":"CA",
    "sg:tags":[
        "rock"
    ],
    "wof:name":"South County Building Material",
    "wof:placetype":"venue"
},
  "geometry": {"coordinates":[-121.57571900000001,37.027059],"type":"Point"}
}