{
  "type": "Feature",
  "properties": {
    "addr:full":"Bellflower Blvd & Stearns St Long Beach CA 90815",
    "addr:postcode":"90815",
    "addr:street":"Bellflower Blvd & Stearns St",
    "iso:country":"US",
    "sg:address":"Bellflower Blvd & Stearns St",
    "sg:city":"Long Beach",
    "sg:classifiers":[
        {
            "category":"Shopping Center",
            "type":"Public Place"
        }
    ],
    "sg:postcode":"90815",
    "sg:province":"CA",
    "wof:name":"Los Altos Shopping Center",
    "wof:placetype":"venue"
},
  "geometry": {"coordinates":[-118.125336,33.796032],"type":"Point"}
}