{
  "type": "Feature",
  "properties": {
    "iso:country":"US",
    "sg:address":"337 W Manchester Blvd",
    "sg:city":"Inglewood",
    "sg:classifiers":[
        {
            "category":"Retail",
            "subcategory":"Auto Repair",
            "type":"Services"
        }
    ],
    "sg:phone":"+1 310 674 8905",
    "sg:postcode":"90301",
    "sg:province":"CA",
    "sg:tags":[
        "repairing",
        "automobile"
    ],
    "sg:website":"www.rennermotorsport.com",
    "wof:name":"Renner Motorsports",
    "wof:placetype":"venue"
},
  "geometry": {"coordinates":[-118.361215,33.962001],"type":"Point"}
}