{
  "type": "Feature",
  "properties": {
    "addr:full":"295 9th St Oakland CA 94607",
    "addr:housenumber":"295",
    "addr:postcode":"94607",
    "addr:street":"9Th St",
    "iso:country":"US",
    "sg:address":"295 9th St",
    "sg:city":"Oakland",
    "sg:classifiers":[
        {
            "category":"Food & Beverages",
            "subcategory":"Bakery",
            "type":"Retail Goods"
        },
        {
            "category":"Bakery",
            "type":"Food & Drink"
        }
    ],
    "sg:phone":"+1 510 832 5025",
    "sg:postcode":"94607",
    "sg:province":"CA",
    "sg:tags":[
        "cooky",
        "cracker",
        "pastry",
        "wedding",
        "cake"
    ],
    "sg:website":"www.personalized-fortune-cookies...",
    "wof:name":"Tom's Bakery",
    "wof:placetype":"venue"
},
  "geometry": {"coordinates":[-122.269997,37.799301],"type":"Point"}
}