{
  "type": "Feature",
  "properties": {
    "iso:country":"US",
    "sg:address":"19755 E Lorencita Dr",
    "sg:city":"Covina",
    "sg:classifiers":[
        {
            "category":"Building & Trades",
            "subcategory":"Plumbing",
            "type":"Services"
        }
    ],
    "sg:phone":"+1 626 331 6700",
    "sg:postcode":"91724",
    "sg:province":"CA",
    "sg:tags":[
        "plumber",
        "industrial",
        "contractors-commercial"
    ],
    "wof:name":"D Z Plumbing",
    "wof:placetype":"venue"
},
  "geometry": {"coordinates":[-117.866647,34.062967],"type":"Point"}
}