{
  "type": "Feature",
  "properties": {
    "addr:full":"6375 Burnett Ct Ventura CA 93003",
    "addr:housenumber":"6375",
    "addr:postcode":"93003",
    "addr:street":"Burnett Ct",
    "iso:country":"US",
    "sg:address":"6375 Burnett Ct",
    "sg:city":"Ventura",
    "sg:classifiers":[
        {
            "category":"Shopping",
            "type":"Retail Goods"
        }
    ],
    "sg:phone":"+1 805 642 3711",
    "sg:postcode":"93003",
    "sg:province":"CA",
    "sg:tags":[
        "merchandise"
    ],
    "wof:name":"Hrs Stamp Specialist",
    "wof:placetype":"venue"
},
  "geometry": {"coordinates":[-119.210655,34.283175],"type":"Point"}
}