{
  "type": "Feature",
  "properties": {
    "iso:country":"US",
    "sg:address":"11215 Mountain View Ave",
    "sg:city":"Loma Linda",
    "sg:classifiers":[
        {
            "category":"Restaurant",
            "type":"Food & Drink"
        }
    ],
    "sg:phone":"+1 909 796 6500",
    "sg:postcode":"92354",
    "sg:province":"CA",
    "wof:name":"42nd Street Bagel Cafe",
    "wof:placetype":"venue"
},
  "geometry": {"coordinates":[-117.243561,34.048684],"type":"Point"}
}