{
  "type": "Feature",
  "properties": {
    "iso:country":"US",
    "sg:address":"627 State St",
    "sg:city":"Santa Barbara",
    "sg:classifiers":[
        {
            "category":"Shopping",
            "subcategory":"Shoes",
            "type":"Retail Goods"
        }
    ],
    "sg:phone":"+1 805 962 2866",
    "sg:postcode":"93101",
    "sg:province":"CA",
    "wof:name":"Payless Shoe Source",
    "wof:placetype":"venue"
},
  "geometry": {"coordinates":[-119.697812,34.418363],"type":"Point"}
}