{
  "type": "Feature",
  "properties": {
    "addr:full":"825 S Mellon Ave Manteca CA 95337",
    "addr:housenumber":"825",
    "addr:postcode":"95337",
    "addr:street":"S Mellon Ave",
    "iso:country":"US",
    "sg:address":"825 S Mellon Ave",
    "sg:city":"Manteca",
    "sg:classifiers":[
        {
            "category":"Manufacturing",
            "subcategory":"Metals",
            "type":"Manufacturing & Wholesale Goods"
        }
    ],
    "sg:phone":"+1 209 239 2296",
    "sg:postcode":"95337",
    "sg:province":"CA",
    "sg:tags":[
        "spinning"
    ],
    "wof:name":"D K Enterprises",
    "wof:placetype":"venue"
},
  "geometry": {"coordinates":[-121.211871,37.78963],"type":"Point"}
}