{
  "type": "Feature",
  "properties": {
    "iso:country":"US",
    "sg:address":"4740 E Austin Way",
    "sg:city":"Fresno",
    "sg:classifiers":[
        {
            "category":"Building & Trades",
            "subcategory":"Electrical",
            "type":"Services"
        }
    ],
    "sg:phone":"+1 559 292 1817",
    "sg:postcode":"93726",
    "sg:province":"CA",
    "sg:tags":[
        "electric",
        "contractor"
    ],
    "wof:name":"Crown Electric",
    "wof:placetype":"venue"
},
  "geometry": {"coordinates":[-119.737825,36.794898],"type":"Point"}
}