{
  "type": "Feature",
  "properties": {
    "addr:full":"7540 E Kettleman Ln Lodi CA 95240",
    "addr:housenumber":"7540",
    "addr:postcode":"95240",
    "addr:street":"E Kettleman Ln",
    "iso:country":"US",
    "sg:address":"7540 E Kettleman Ln",
    "sg:city":"Lodi",
    "sg:classifiers":[
        {
            "category":"Farming",
            "subcategory":"Vineyard",
            "type":"Manufacturing & Wholesale Goods"
        }
    ],
    "sg:phone":"+1 209 369 4976",
    "sg:postcode":"95240",
    "sg:province":"CA",
    "sg:tags":[
        "grape"
    ],
    "wof:name":"Pat Hale Vineyards",
    "wof:placetype":"venue"
},
  "geometry": {"coordinates":[-121.217844,38.115878],"type":"Point"}
}