{
  "type": "Feature",
  "properties": {
    "iso:country":"US",
    "sg:address":"518 N Mentor Ave Apt 203",
    "sg:city":"Pasadena",
    "sg:classifiers":[
        {
            "category":"Social Services",
            "type":"Services"
        },
        {
            "category":"Professional",
            "subcategory":"Employment Agencies",
            "type":"Services"
        }
    ],
    "sg:phone":"+1 626 564 9310",
    "sg:postcode":"91106",
    "sg:province":"CA",
    "sg:tags":[
        "workers'",
        "placement",
        "volunteer"
    ],
    "wof:name":"Scholars Academic Foundation",
    "wof:placetype":"venue"
},
  "geometry": {"coordinates":[-118.13095300000001,34.154815],"type":"Point"}
}