{
  "type": "Feature",
  "properties": {
    "iso:country":"US",
    "sg:address":"24915 Myers Ave",
    "sg:city":"Moreno Valley",
    "sg:classifiers":[
        {
            "category":"Professional",
            "type":"Services"
        }
    ],
    "sg:phone":"+1 951 242 8437",
    "sg:postcode":"92553",
    "sg:province":"CA",
    "wof:name":"Michael C Lathrop",
    "wof:placetype":"venue"
},
  "geometry": {"coordinates":[-117.229889,33.933556],"type":"Point"}
}