{
  "type": "Feature",
  "properties": {
    "addr:full":"3120 Ramona Ave Sacramento CA 95826",
    "addr:housenumber":"3120",
    "addr:postcode":"95826",
    "addr:street":"Ramona Ave",
    "iso:country":"US",
    "sg:address":"3120 Ramona Ave",
    "sg:city":"Sacramento",
    "sg:classifiers":[
        {
            "category":"Professional",
            "type":"Services"
        }
    ],
    "sg:phone":"+1 916 373 5751",
    "sg:postcode":"95826",
    "sg:province":"CA",
    "wof:name":"M&N1",
    "wof:placetype":"venue"
},
  "geometry": {"coordinates":[-121.41471300000001,38.545707],"type":"Point"}
}