{
  "type": "Feature",
  "properties": {
    "addr:full":"1750 Montgomery St San Francisco CA 94111",
    "addr:housenumber":"1750",
    "addr:postcode":"94111",
    "addr:street":"Montgomery St",
    "iso:country":"US",
    "sg:address":"1750 Montgomery St",
    "sg:city":"San Francisco",
    "sg:classifiers":[
        {
            "category":"Professional",
            "subcategory":"Advertising",
            "type":"Services"
        }
    ],
    "sg:phone":"+1 415 773 5336",
    "sg:postcode":"94111",
    "sg:province":"CA",
    "wof:name":"Lamar Advertising Co",
    "wof:placetype":"venue"
},
  "geometry": {"coordinates":[-122.405209,37.805231],"type":"Point"}
}