{
  "type": "Feature",
  "properties": {
    "iso:country":"US",
    "sg:address":"1814 Franklin St Ste 800",
    "sg:city":"Oakland",
    "sg:classifiers":[
        {
            "category":"Professional",
            "subcategory":"Lawyer & Legal Services",
            "type":"Services"
        }
    ],
    "sg:phone":"+1 510 451 2777",
    "sg:postcode":"94612",
    "sg:province":"CA",
    "wof:name":"Willoughby Doyle LLP",
    "wof:placetype":"venue"
},
  "geometry": {"coordinates":[-122.267939,37.806748],"type":"Point"}
}