{
  "type": "Feature",
  "properties": {
    "iso:country":"US",
    "sg:address":"4496 Salisbury Dr",
    "sg:city":"Carlsbad",
    "sg:classifiers":[
        {
            "category":"Building & Trades",
            "subcategory":"Construction",
            "type":"Services"
        }
    ],
    "sg:phone":"+1 760 434 7826",
    "sg:postcode":"92008",
    "sg:province":"CA",
    "sg:tags":[
        "house"
    ],
    "wof:name":"Stellar Builders Inc",
    "wof:placetype":"venue"
},
  "geometry": {"coordinates":[-117.312944,33.160852],"type":"Point"}
}