{
  "type": "Feature",
  "properties": {
    "iso:country":"US",
    "sg:address":"2671 S Dolphin St",
    "sg:city":"San Pedro",
    "sg:classifiers":[
        {
            "category":"Freight",
            "type":"Transportation"
        }
    ],
    "sg:phone":"+1 310 832 5670",
    "sg:postcode":"90731",
    "sg:province":"CA",
    "sg:tags":[
        "local",
        "storage",
        "trucking"
    ],
    "wof:name":"Robert Joseph Bruschi Jr",
    "wof:placetype":"venue"
},
  "geometry": {"coordinates":[-118.30843299999999,33.71896],"type":"Point"}
}