{
  "type": "Feature",
  "properties": {
    "iso:country":"US",
    "sg:address":"1712 W 84th Pl",
    "sg:city":"Los Angeles",
    "sg:classifiers":[
        {
            "category":"Social Services",
            "subcategory":"Child Care",
            "type":"Services"
        }
    ],
    "sg:phone":"+1 323 759 8057",
    "sg:postcode":"90047",
    "sg:province":"CA",
    "wof:name":"Platinum Child Care Inc",
    "wof:placetype":"venue"
},
  "geometry": {"coordinates":[-118.308757,33.961727],"type":"Point"}
}