{
  "type": "Feature",
  "properties": {
    "iso:country":"US",
    "sg:address":"181 Brookside Dr",
    "sg:city":"Richmond",
    "sg:classifiers":[
        {
            "category":"Wholesale",
            "subcategory":"Medical Equipment & Supplies",
            "type":"Manufacturing & Wholesale Goods"
        }
    ],
    "sg:phone":"+1 800 676 2525",
    "sg:postcode":"94801",
    "sg:province":"CA",
    "sg:tags":[
        "trusses-construction"
    ],
    "wof:name":"Simon Evans Truss",
    "wof:placetype":"venue"
},
  "geometry": {"coordinates":[-122.368655,37.965165],"type":"Point"}
}