{
  "type": "Feature",
  "properties": {
    "iso:country":"US",
    "sg:address":"15800 Hesperian Blvd",
    "sg:city":"Hayward",
    "sg:classifiers":[
        {
            "category":"Restaurant",
            "type":"Food & Drink"
        },
        {
            "category":"Bars & Pubs",
            "subcategory":"Nightclub",
            "type":"Food & Drink"
        }
    ],
    "sg:phone":"+1 510 276 1400",
    "sg:postcode":"94541",
    "sg:province":"CA",
    "sg:tags":[
        "nightlife"
    ],
    "sg:website":"www.blackangus.com",
    "wof:name":"Black Angus Restaurant Stuart Anderson's",
    "wof:placetype":"venue"
},
  "geometry": {"coordinates":[-122.089996,37.6745],"type":"Point"}
}