{
  "type": "Feature",
  "properties": {
    "addr:full":"3275 Kifer Rd Santa Clara CA 95051",
    "addr:housenumber":"3275",
    "addr:postcode":"95051",
    "addr:street":"Kifer Rd",
    "iso:country":"US",
    "sg:address":"3275 Kifer Rd",
    "sg:city":"Santa Clara",
    "sg:classifiers":[
        {
            "category":"Shopping",
            "subcategory":"Computers & Home Electronics",
            "type":"Retail Goods"
        }
    ],
    "sg:phone":"+1 408 735 1600",
    "sg:postcode":"95051",
    "sg:province":"CA",
    "sg:tags":[
        "software"
    ],
    "sg:website":"www.unitex.net",
    "wof:name":"Unitex Group",
    "wof:placetype":"venue"
},
  "geometry": {"coordinates":[-121.985659,37.374062],"type":"Point"}
}