{
  "type": "Feature",
  "properties": {
    "iso:country":"US",
    "sg:address":"5121 Business Center Dr",
    "sg:city":"Fairfield",
    "sg:classifiers":[
        {
            "category":"Home & Garden",
            "subcategory":"Carpets & Floor Coverings",
            "type":"Retail Goods"
        }
    ],
    "sg:phone":"+1 707 864 1307",
    "sg:postcode":"94534",
    "sg:province":"CA",
    "sg:tags":[
        "mattress"
    ],
    "wof:name":"Sleep Train Mattress Centers",
    "wof:placetype":"venue"
},
  "geometry": {"coordinates":[-122.142984,38.21494],"type":"Point"}
}