{
  "type": "Feature",
  "properties": {
    "addr:full":"4248 Martingale Way Newport Beach CA 92660",
    "addr:housenumber":"4248",
    "addr:postcode":"92660",
    "addr:street":"Martingale Way",
    "iso:country":"US",
    "sg:address":"4248 Martingale Way",
    "sg:city":"Newport Beach",
    "sg:classifiers":[
        {
            "category":"Arts & Performance",
            "subcategory":"Theater",
            "type":"Entertainment"
        }
    ],
    "sg:phone":"+1 949 851 5187",
    "sg:postcode":"92660",
    "sg:province":"CA",
    "wof:name":"Mermaid",
    "wof:placetype":"venue"
},
  "geometry": {"coordinates":[-117.865157,33.665973],"type":"Point"}
}