{
  "type": "Feature",
  "properties": {
    "addr:full":"646 State Rte 12 Rio Vista CA 94571",
    "addr:housenumber":"646",
    "addr:postcode":"94571",
    "addr:street":"State Rte 12",
    "iso:country":"US",
    "sg:address":"646 State Rte 12",
    "sg:city":"Rio Vista",
    "sg:classifiers":[
        {
            "category":"Restaurant",
            "type":"Food & Drink"
        }
    ],
    "sg:phone":"+1 707 374 5359",
    "sg:postcode":"94571",
    "sg:province":"CA",
    "wof:name":"Maria's Mexican Food Rstrnt",
    "wof:placetype":"venue"
},
  "geometry": {"coordinates":[-121.695419,38.16065],"type":"Point"}
}