{
  "type": "Feature",
  "properties": {
    "addr:full":"763 E Monte Vista Ave Vacaville CA 95688",
    "addr:housenumber":"763",
    "addr:postcode":"95688",
    "addr:street":"E Monte Vista Ave",
    "iso:country":"US",
    "sg:address":"763 E Monte Vista Ave",
    "sg:city":"Vacaville",
    "sg:phone":"+1 707 447 8900",
    "sg:postcode":"95688",
    "sg:province":"CA",
    "wof:name":"Blondies Classic Cuts & Colors",
    "wof:placetype":"venue"
},
  "geometry": {"coordinates":[-121.98280200000001,38.35894],"type":"Point"}
}