{
  "type": "Feature",
  "properties": {
    "addr:full":"8413 63rd St Riverside CA 92509",
    "addr:housenumber":"8413",
    "addr:postcode":"92509",
    "addr:street":"63Rd St",
    "iso:country":"US",
    "sg:address":"8413 63rd St",
    "sg:city":"Riverside",
    "sg:classifiers":[
        {
            "category":"Building & Trades",
            "subcategory":"Electrical",
            "type":"Services"
        }
    ],
    "sg:phone":"+1 951 681 7128",
    "sg:postcode":"92509",
    "sg:province":"CA",
    "sg:tags":[
        "telecommunication",
        "contractor"
    ],
    "wof:name":"Jitney Co Inc",
    "wof:placetype":"venue"
},
  "geometry": {"coordinates":[-117.471598,33.972807],"type":"Point"}
}