{
  "type": "Feature",
  "properties": {
    "addr:full":"915 I St Ste 2000 Sacramento CA 95814",
    "addr:housenumber":"915",
    "addr:postcode":"95814",
    "addr:street":"I St Ste 2000",
    "iso:country":"US",
    "sg:address":"915 I St Ste 2000",
    "sg:city":"Sacramento",
    "sg:classifiers":[
        {
            "category":"Education",
            "subcategory":"Library",
            "type":"Public Place"
        }
    ],
    "sg:phone":"+1 916 264 2758",
    "sg:postcode":"95814",
    "sg:province":"CA",
    "wof:name":"Sacramento Public Library",
    "wof:placetype":"venue"
},
  "geometry": {"coordinates":[-121.494111,38.581698],"type":"Point"}
}