{
  "type": "Feature",
  "properties": {
    "iso:country":"US",
    "sg:address":"655 13th St",
    "sg:city":"Oakland",
    "sg:classifiers":[
        {
            "category":"Organizations",
            "subcategory":"Community Association",
            "type":"Services"
        }
    ],
    "sg:phone":"+1 510 832 1966",
    "sg:postcode":"94612",
    "sg:province":"CA",
    "sg:tags":[
        "environmental",
        "org"
    ],
    "wof:name":"Student Conservation Assn",
    "wof:placetype":"venue"
},
  "geometry": {"coordinates":[-122.276477,37.805457],"type":"Point"}
}