{
  "type": "Feature",
  "properties": {
    "iso:country":"US",
    "sg:address":"30944 San Clemente St",
    "sg:city":"Hayward",
    "sg:classifiers":[
        {
            "category":"Professional",
            "subcategory":"Research",
            "type":"Services"
        }
    ],
    "sg:phone":"+1 510 324 0340",
    "sg:postcode":"94544",
    "sg:province":"CA",
    "sg:tags":[
        "environmental",
        "ecological"
    ],
    "wof:name":"Jaco Environmental",
    "wof:placetype":"venue"
},
  "geometry": {"coordinates":[-122.052467,37.619328],"type":"Point"}
}