{
  "type": "Feature",
  "properties": {
    "addr:full":"784 Admiral Callaghan Ln Vallejo CA 94591",
    "addr:housenumber":"784",
    "addr:postcode":"94591",
    "addr:street":"Admiral Callaghan Ln",
    "iso:country":"US",
    "sg:address":"784 Admiral Callaghan Ln",
    "sg:city":"Vallejo",
    "sg:classifiers":[
        {
            "category":"Retail",
            "subcategory":"Laundry & Dry Cleaning",
            "type":"Services"
        }
    ],
    "sg:phone":"+1 707 552 8885",
    "sg:postcode":"94591",
    "sg:province":"CA",
    "sg:tags":[
        "cleaners"
    ],
    "wof:name":"Redwood Cleaners",
    "wof:placetype":"venue"
},
  "geometry": {"coordinates":[-122.22805200000001,38.125066],"type":"Point"}
}