{
  "type": "Feature",
  "properties": {
    "iso:country":"US",
    "sg:address":"LIttle Tokyo",
    "sg:city":"Los Angeles",
    "sg:classifiers":[
        {
            "category":"Restaurant",
            "type":"Food & Drink"
        }
    ],
    "sg:postcode":"90189",
    "sg:province":"CA",
    "sg:tags":[
        "flavor",
        "local"
    ],
    "sg:website":"www.nebuta-la.org/",
    "wof:name":"Nisei Week Parade",
    "wof:placetype":"venue"
},
  "geometry": {"coordinates":[-118.255804,34.039585],"type":"Point"}
}