{
  "type": "Feature",
  "properties": {
    "iso:country":"US",
    "sg:address":"200 S Emerald Dr",
    "sg:city":"Vista",
    "sg:classifiers":[
        {
            "category":"Retail",
            "subcategory":"Repair Shop",
            "type":"Services"
        }
    ],
    "sg:phone":"+1 760 738 1111",
    "sg:postcode":"92081",
    "sg:province":"CA",
    "sg:tags":[
        "lock",
        "locksmith"
    ],
    "wof:name":"Golden State Lock Svc",
    "wof:placetype":"venue"
},
  "geometry": {"coordinates":[-117.279579,33.186565],"type":"Point"}
}