{
  "type": "Feature",
  "properties": {
    "addr:full":"12848 Pioneer Blvd Norwalk CA 90650",
    "addr:housenumber":"12848",
    "addr:postcode":"90650",
    "addr:street":"Pioneer Blvd",
    "iso:country":"US",
    "sg:address":"12848 Pioneer Blvd",
    "sg:city":"Norwalk",
    "sg:classifiers":[
        {
            "category":"Real Estate",
            "subcategory":"Real Estate Services",
            "type":"Services"
        },
        {
            "category":"Real Estate",
            "subcategory":"Real Estate Agent",
            "type":"Services"
        }
    ],
    "sg:phone":"+1 562 868 6716",
    "sg:postcode":"90650",
    "sg:province":"CA",
    "sg:tags":[
        "buyer",
        "broker"
    ],
    "wof:name":"Mnm Property Management",
    "wof:placetype":"venue"
},
  "geometry": {"coordinates":[-118.08174099999999,33.913362],"type":"Point"}
}