{
  "type": "Feature",
  "properties": {
    "addr:full":"1928 Cam del Sol Oxnard CA 93030",
    "addr:housenumber":"1928",
    "addr:postcode":"93030",
    "addr:street":"Cam Del Sol",
    "iso:country":"US",
    "sg:address":"1928 Cam del Sol",
    "sg:city":"Oxnard",
    "sg:classifiers":[
        {
            "category":"Real Estate",
            "subcategory":"Real Estate Operator",
            "type":"Services"
        }
    ],
    "sg:phone":"+1 805 983 0998",
    "sg:postcode":"93030",
    "sg:province":"CA",
    "sg:tags":[
        "apartment"
    ],
    "wof:name":"Camino Del Sol Senior Apt",
    "wof:placetype":"venue"
},
  "geometry": {"coordinates":[-119.158602,34.206268],"type":"Point"}
}