{
  "type": "Feature",
  "properties": {
    "addr:full":"5824 Robertson Ave Carmichael CA 95608",
    "addr:housenumber":"5824",
    "addr:postcode":"95608",
    "addr:street":"Robertson Ave",
    "iso:country":"US",
    "sg:address":"5824 Robertson Ave",
    "sg:city":"Carmichael",
    "sg:classifiers":[
        {
            "category":"Retail",
            "subcategory":"Repair Shop",
            "type":"Services"
        }
    ],
    "sg:phone":"+1 916 486 4845",
    "sg:postcode":"95608",
    "sg:province":"CA",
    "sg:tags":[
        "upholsterer"
    ],
    "wof:name":"Dickinson's Furniture Factory",
    "wof:placetype":"venue"
},
  "geometry": {"coordinates":[-121.32929300000001,38.620712],"type":"Point"}
}