{
  "type": "Feature",
  "properties": {
    "addr:full":"6742 Balboa Blvd Van Nuys CA 91406",
    "addr:housenumber":"6742",
    "addr:postcode":"91406",
    "addr:street":"Balboa Blvd",
    "iso:country":"US",
    "sg:address":"6742 Balboa Blvd",
    "sg:city":"Van Nuys",
    "sg:classifiers":[
        {
            "category":"Personal",
            "subcategory":"Barber",
            "type":"Services"
        }
    ],
    "sg:phone":"+1 818 901 0139",
    "sg:postcode":"91406",
    "sg:province":"CA",
    "wof:name":"Angel's Barber Shop",
    "wof:placetype":"venue"
},
  "geometry": {"coordinates":[-118.501041,34.193858],"type":"Point"}
}