{
  "type": "Feature",
  "properties": {
    "addr:full":"211 N Canon Dr Beverly Hills CA 90210",
    "addr:housenumber":"211",
    "addr:postcode":"90210",
    "addr:street":"N Canon Dr",
    "iso:country":"US",
    "sg:address":"211 N Canon Dr",
    "sg:city":"Beverly Hills",
    "sg:classifiers":[
        {
            "category":"Shopping",
            "subcategory":"Florist",
            "type":"Retail Goods"
        }
    ],
    "sg:phone":"+1 310 205 9501",
    "sg:postcode":"90210",
    "sg:province":"CA",
    "wof:name":"Paradise Garden Florist Inc",
    "wof:placetype":"venue"
},
  "geometry": {"coordinates":[-118.399415,34.06902],"type":"Point"}
}