{
  "type": "Feature",
  "properties": {
    "addr:full":"1029 E 4th St Long Beach CA 90802",
    "addr:housenumber":"1029",
    "addr:postcode":"90802",
    "addr:street":"E 4Th St",
    "iso:country":"US",
    "sg:address":"1029 E 4th St",
    "sg:city":"Long Beach",
    "sg:classifiers":[
        {
            "category":"Wholesale",
            "subcategory":"Durable Goods & Equipment",
            "type":"Manufacturing & Wholesale Goods"
        }
    ],
    "sg:phone":"+1 562 432 6434",
    "sg:postcode":"90802",
    "sg:province":"CA",
    "wof:name":"Golden Reception Party Supply",
    "wof:placetype":"venue"
},
  "geometry": {"coordinates":[-118.178636,33.771782],"type":"Point"}
}