{
  "type": "Feature",
  "properties": {
    "iso:country":"US",
    "sg:address":"4053 Chestnut St",
    "sg:city":"Riverside",
    "sg:classifiers":[
        {
            "category":"Professional",
            "subcategory":"Management & Consulting",
            "type":"Services"
        },
        {
            "category":"Government",
            "subcategory":"Office",
            "type":"Public Place"
        }
    ],
    "sg:phone":"+1 951 320 7020",
    "sg:postcode":"92501",
    "sg:province":"CA",
    "sg:tags":[
        "development",
        "consultant",
        "training"
    ],
    "wof:name":"Charo Community Development Co",
    "wof:placetype":"venue"
},
  "geometry": {"coordinates":[-117.37975,33.981242],"type":"Point"}
}