{
  "type": "Feature",
  "properties": {
    "addr:full":"21810 S Vermont Ave Torrance CA 90502",
    "addr:housenumber":"21810",
    "addr:postcode":"90502",
    "addr:street":"S Vermont Ave",
    "iso:country":"US",
    "sg:address":"21810 S Vermont Ave",
    "sg:city":"Torrance",
    "sg:classifiers":[
        {
            "category":"Manufacturing",
            "subcategory":"Building Materials",
            "type":"Manufacturing & Wholesale Goods"
        },
        {
            "category":"Home & Garden",
            "subcategory":"Furniture",
            "type":"Retail Goods"
        }
    ],
    "sg:phone":"+1 310 618 9606",
    "sg:postcode":"90502",
    "sg:province":"CA",
    "sg:tags":[
        "equipment",
        "cabinet",
        "wood",
        "kitchen",
        "mfg"
    ],
    "wof:name":"Rafa's Cabinet",
    "wof:placetype":"venue"
},
  "geometry": {"coordinates":[-118.290227,33.831363],"type":"Point"}
}