{
  "type": "Feature",
  "properties": {
    "addr:full":"211 10th St Ste 268 Oakland CA 94607",
    "addr:housenumber":"211",
    "addr:postcode":"94607",
    "addr:street":"10Th St Ste 268",
    "iso:country":"US",
    "sg:address":"211 10th St Ste 268",
    "sg:city":"Oakland",
    "sg:classifiers":[
        {
            "category":"Professional",
            "subcategory":"Engineering",
            "type":"Services"
        }
    ],
    "sg:phone":"+1 510 763 5245",
    "sg:postcode":"94607",
    "sg:province":"CA",
    "sg:tags":[
        "engineer",
        "structural"
    ],
    "wof:name":"Applied Structural Associates",
    "wof:placetype":"venue"
},
  "geometry": {"coordinates":[-122.267202,37.799316],"type":"Point"}
}