{
  "type": "Feature",
  "properties": {
    "iso:country":"US",
    "sg:address":"290 Division St",
    "sg:city":"San Francisco",
    "sg:classifiers":[
        {
            "category":"Professional",
            "subcategory":"Engineering",
            "type":"Services"
        }
    ],
    "sg:phone":"+1 415 621 3908",
    "sg:postcode":"94103",
    "sg:province":"CA",
    "sg:tags":[
        "engineer"
    ],
    "sg:website":"www.remdesign.com",
    "wof:name":"REM Design",
    "wof:placetype":"venue"
},
  "geometry": {"coordinates":[-122.409878,37.769183],"type":"Point"}
}