{
  "type": "Feature",
  "properties": {
    "addr:full":"11750 Washington Blvd Los Angeles CA 90066",
    "addr:housenumber":"11750",
    "addr:postcode":"90066",
    "addr:street":"Washington Blvd",
    "iso:country":"US",
    "sg:address":"11750 Washington Blvd",
    "sg:city":"Los Angeles",
    "sg:classifiers":[
        {
            "category":"Travel",
            "subcategory":"Hotels & Motels",
            "type":"Entertainment"
        }
    ],
    "sg:phone":"+1 310 390 4044",
    "sg:postcode":"90066",
    "sg:province":"CA",
    "wof:name":"Paradise Motel",
    "wof:placetype":"venue"
},
  "geometry": {"coordinates":[-118.418454,33.999442],"type":"Point"}
}