{
  "type": "Feature",
  "properties": {
    "iso:country":"US",
    "sg:address":"44 N Lassen St",
    "sg:city":"Susanville",
    "sg:classifiers":[
        {
            "category":"Government",
            "subcategory":"Office",
            "type":"Public Place"
        }
    ],
    "sg:phone":"+1 530 257 1022",
    "sg:postcode":"96130",
    "sg:province":"CA",
    "sg:tags":[
        "village"
    ],
    "wof:name":"Susanville Building Inspection",
    "wof:placetype":"venue"
},
  "geometry": {"coordinates":[-120.661705,40.419219],"type":"Point"}
}