{
  "type": "Feature",
  "properties": {
    "iso:country":"US",
    "sg:address":"7763 N 1st St",
    "sg:city":"Fresno",
    "sg:classifiers":[
        {
            "category":"Retail",
            "subcategory":"Laundry & Dry Cleaning",
            "type":"Services"
        }
    ],
    "sg:phone":"+1 559 436 1277",
    "sg:postcode":"93720",
    "sg:province":"CA",
    "sg:tags":[
        "cleaners"
    ],
    "wof:name":"One Hour Martinizing",
    "wof:placetype":"venue"
},
  "geometry": {"coordinates":[-119.774619,36.850469],"type":"Point"}
}