{
  "type": "Feature",
  "properties": {
    "iso:country":"US",
    "sg:address":"406 Center St",
    "sg:city":"Taft",
    "sg:classifiers":[
        {
            "category":"Shopping",
            "subcategory":"Gifts & Souvenirs",
            "type":"Retail Goods"
        }
    ],
    "sg:phone":"+1 661 763 5085",
    "sg:postcode":"93268",
    "sg:province":"CA",
    "sg:tags":[
        "shop"
    ],
    "wof:name":"Emy's Variety Store",
    "wof:placetype":"venue"
},
  "geometry": {"coordinates":[-119.458867,35.140985],"type":"Point"}
}