{
  "type": "Feature",
  "properties": {
    "iso:country":"US",
    "sg:address":"6516 Ave Juan Diaz",
    "sg:city":"Riverside",
    "sg:classifiers":[
        {
            "category":"Professional",
            "subcategory":"Business Services",
            "type":"Services"
        }
    ],
    "sg:phone":"+1 951 681 9101",
    "sg:postcode":"92509",
    "sg:province":"CA",
    "sg:tags":[
        "building",
        "inspection"
    ],
    "wof:name":"Inspection Services Unlimited",
    "wof:placetype":"venue"
},
  "geometry": {"coordinates":[-117.436854,33.972436],"type":"Point"}
}