{
  "type": "Feature",
  "properties": {
    "addr:full":"2321 Harrison Ave Eureka CA 95501",
    "addr:housenumber":"2321",
    "addr:postcode":"95501",
    "addr:street":"Harrison Ave",
    "iso:country":"US",
    "sg:address":"2321 Harrison Ave",
    "sg:city":"Eureka",
    "sg:classifiers":[
        {
            "category":"Health Services",
            "subcategory":"Doctor",
            "type":"Services"
        }
    ],
    "sg:phone":"+1 707 822 7661",
    "sg:postcode":"95501",
    "sg:province":"CA",
    "sg:tags":[
        "physician",
        "surgeon"
    ],
    "wof:name":"North Coast Surgical Spec",
    "wof:placetype":"venue"
},
  "geometry": {"coordinates":[-124.139535,40.786534],"type":"Point"}
}