{
  "type": "Feature",
  "properties": {
    "addr:full":"335 Mission St Santa Cruz CA 95060",
    "addr:housenumber":"335",
    "addr:postcode":"95060",
    "addr:street":"Mission St",
    "iso:country":"US",
    "sg:address":"335 Mission St",
    "sg:city":"Santa Cruz",
    "sg:classifiers":[
        {
            "category":"Autos & Motor Vehicles",
            "subcategory":"Fuel & Gas Station",
            "type":"Retail Goods"
        }
    ],
    "sg:phone":"+1 831 426 3595",
    "sg:postcode":"95060",
    "sg:province":"CA",
    "sg:tags":[
        "oil"
    ],
    "wof:name":"Valero",
    "wof:placetype":"venue"
},
  "geometry": {"coordinates":[-122.03306499999999,36.975632],"type":"Point"}
}