{
  "type": "Feature",
  "properties": {
    "iso:country":"US",
    "sg:address":"335 Mission St",
    "sg:city":"Santa Cruz",
    "sg:classifiers":[
        {
            "category":"Autos & Motor Vehicles",
            "subcategory":"Fuel & Gas Station",
            "type":"Retail Goods"
        }
    ],
    "sg:phone":"+1 831 426 3595",
    "sg:postcode":"95060",
    "sg:province":"CA",
    "sg:tags":[
        "oil"
    ],
    "wof:name":"Valero",
    "wof:placetype":"venue"
},
  "geometry": {"coordinates":[-122.033065,36.975632],"type":"Point"}
}