{
  "type": "Feature",
  "properties": {
    "addr:full":"2967 Michelson Dr. Ste G225 Irvine CA 92612",
    "addr:postcode":"2967;92612",
    "addr:street":"Michelson Dr. Ste G225",
    "iso:country":"US",
    "sg:address":"2967 Michelson Dr. Ste G225",
    "sg:city":"Irvine",
    "sg:classifiers":[
        {
            "category":"Building & Trades",
            "subcategory":"Pest Control",
            "type":"Services"
        }
    ],
    "sg:phone":"+1 949 829 2847",
    "sg:postcode":"92612",
    "sg:province":"CA",
    "sg:website":"www.mybugprofessional.com/",
    "wof:name":"Bug Professional Pest Control",
    "wof:placetype":"venue"
},
  "geometry": {"coordinates":[-117.844864,33.671004],"type":"Point"}
}