{
  "type": "Feature",
  "properties": {
    "addr:full":"1001 Murphy Ranch Road Milpitas CA 95035",
    "addr:housenumber":"1001",
    "addr:postcode":"95035",
    "addr:street":"Murphy Ranch Road",
    "iso:country":"US",
    "sg:address":"1001 Murphy Ranch Road",
    "sg:city":"Milpitas",
    "sg:classifiers":[
        {
            "category":"Manufacturing",
            "subcategory":"Electronics",
            "type":"Manufacturing & Wholesale Goods"
        }
    ],
    "sg:phone":"+1 408 432 8888",
    "sg:postcode":"95035",
    "sg:province":"CA",
    "sg:website":"http://www.intersil.com",
    "wof:name":"Intersil",
    "wof:placetype":"venue"
},
  "geometry": {"coordinates":[-121.925077,37.416375],"type":"Point"}
}