{
  "type": "Feature",
  "properties": {
    "addr:full":"821 Borregas Ave Sunnyvale CA 94085",
    "addr:housenumber":"821",
    "addr:postcode":"94085",
    "addr:street":"Borregas Ave",
    "iso:country":"US",
    "sg:address":"821 Borregas Ave",
    "sg:city":"Sunnyvale",
    "sg:classifiers":[
        {
            "category":"Restaurant",
            "type":"Food & Drink"
        }
    ],
    "sg:phone":"+1 408 744 0622",
    "sg:postcode":"94085",
    "sg:province":"CA",
    "sg:tags":[
        "mexican"
    ],
    "sg:website":"www.rubystaqueria.com",
    "wof:name":"Ruby's Taqueria",
    "wof:placetype":"venue"
},
  "geometry": {"coordinates":[-122.023003,37.395802],"type":"Point"}
}