{
  "type": "Feature",
  "properties": {
    "addr:full":"25551 Elder Ave Moreno Valley CA 92557",
    "addr:housenumber":"25551",
    "addr:postcode":"92557",
    "addr:street":"Elder Ave",
    "iso:country":"US",
    "sg:address":"25551 Elder Ave",
    "sg:city":"Moreno Valley",
    "sg:classifiers":[
        {
            "category":"Building & Trades",
            "subcategory":"Pest Control",
            "type":"Services"
        }
    ],
    "sg:phone":"+1 951 924 0767",
    "sg:postcode":"92557",
    "sg:province":"CA",
    "wof:name":"Mc Iver's Exterminators",
    "wof:placetype":"venue"
},
  "geometry": {"coordinates":[-117.219005,33.939938],"type":"Point"}
}