{
  "type": "Feature",
  "properties": {
    "addr:full":"9016 Balboa Blvd Northridge CA 91325",
    "addr:housenumber":"9016",
    "addr:postcode":"91325",
    "addr:street":"Balboa Blvd",
    "iso:country":"US",
    "sg:address":"9016 Balboa Blvd",
    "sg:city":"Northridge",
    "sg:classifiers":[
        {
            "category":"Professional",
            "subcategory":"Accounting & Tax Preparation",
            "type":"Services"
        },
        {
            "category":"Banks & Credit Unions",
            "subcategory":"Financial Services",
            "type":"Services"
        }
    ],
    "sg:phone":"+1 818 892 2148",
    "sg:postcode":"91325",
    "sg:province":"CA",
    "sg:tags":[
        "return",
        "preparation-business",
        "taxes-consultants",
        "loan",
        "reporting",
        "representative",
        "alternative",
        "bookkeeping"
    ],
    "sg:website":"http://www.hrblock.com",
    "wof:name":"H&R Block",
    "wof:placetype":"venue"
},
  "geometry": {"coordinates":[-118.50252999999999,34.234959],"type":"Point"}
}