{
  "type": "Feature",
  "properties": {
    "iso:country":"US",
    "sg:address":"8950 Arrow Rte",
    "sg:city":"Rancho Cucamonga",
    "sg:classifiers":[
        {
            "category":"Real Estate",
            "subcategory":"Real Estate Operator",
            "type":"Services"
        }
    ],
    "sg:phone":"+1 909 980 5835",
    "sg:postcode":"91730",
    "sg:province":"CA",
    "sg:tags":[
        "apartment"
    ],
    "wof:name":"Vineyard Village",
    "wof:placetype":"venue"
},
  "geometry": {"coordinates":[-117.610855,34.099442],"type":"Point"}
}