{
  "type": "Feature",
  "properties": {
    "addr:full":"3416 W Beverly Blvd Montebello CA 90640",
    "addr:housenumber":"3416",
    "addr:postcode":"90640",
    "addr:street":"W Beverly Blvd",
    "iso:country":"US",
    "sg:address":"3416 W Beverly Blvd",
    "sg:city":"Montebello",
    "sg:classifiers":[
        {
            "category":"Shopping",
            "subcategory":"Bicycles & Sporting Goods",
            "type":"Retail Goods"
        }
    ],
    "sg:phone":"+1 323 728 2788",
    "sg:postcode":"90640",
    "sg:province":"CA",
    "sg:tags":[
        "bike"
    ],
    "wof:name":"Rudy's Bicycle Shop",
    "wof:placetype":"venue"
},
  "geometry": {"coordinates":[-118.14099899999999,34.025002],"type":"Point"}
}