{
  "type": "Feature",
  "properties": {
    "addr:full":"732 Center Dr San Marcos CA 92069",
    "addr:housenumber":"732",
    "addr:postcode":"92069",
    "addr:street":"Center Dr",
    "iso:country":"US",
    "sg:address":"732 Center Dr",
    "sg:city":"San Marcos",
    "sg:classifiers":[
        {
            "category":"Health Services",
            "subcategory":"Optometrist",
            "type":"Services"
        }
    ],
    "sg:phone":"+1 760 839 5161",
    "sg:postcode":"92069",
    "sg:province":"CA",
    "wof:name":"Robert Gentile OD",
    "wof:placetype":"venue"
},
  "geometry": {"coordinates":[-117.12432200000001,33.136051],"type":"Point"}
}