{
  "type": "Feature",
  "properties": {
    "addr:full":"9844 National Boulevard Los Angeles CA 90034",
    "addr:housenumber":"9844",
    "addr:postcode":"90034",
    "addr:street":"National Boulevard",
    "iso:country":"US",
    "sg:address":"9844 National Boulevard",
    "sg:city":"Los Angeles",
    "sg:classifiers":[
        {
            "category":"Restaurant",
            "type":"Food & Drink"
        }
    ],
    "sg:phone":"+1 310 815 9966",
    "sg:postcode":"90034",
    "sg:province":"CA",
    "sg:tags":[
        "pizza"
    ],
    "wof:name":"Papa John's Pizza",
    "wof:placetype":"venue"
},
  "geometry": {"coordinates":[-118.401999,34.030861],"type":"Point"}
}