{
  "type": "Feature",
  "properties": {
    "addr:full":"20200 Spence Rd Salinas CA 93908",
    "addr:housenumber":"20200",
    "addr:postcode":"93908",
    "addr:street":"Spence Rd",
    "iso:country":"US",
    "sg:address":"20200 Spence Rd",
    "sg:city":"Salinas",
    "sg:classifiers":[
        {
            "category":"Farming",
            "subcategory":"Nursery",
            "type":"Manufacturing & Wholesale Goods"
        }
    ],
    "sg:phone":"+1 831 422 3990",
    "sg:postcode":"93908",
    "sg:province":"CA",
    "sg:tags":[
        "cut",
        "grows",
        "flower"
    ],
    "wof:name":"Tashiro Nursery",
    "wof:placetype":"venue"
},
  "geometry": {"coordinates":[-121.54182299999999,36.628562],"type":"Point"}
}