{
  "type": "Feature",
  "properties": {
    "iso:country":"US",
    "sg:address":"17201 Hiawatha St",
    "sg:city":"Granada Hills",
    "sg:classifiers":[
        {
            "category":"Wholesale",
            "subcategory":"Durable Goods & Equipment",
            "type":"Manufacturing & Wholesale Goods"
        }
    ],
    "sg:phone":"+1 818 363 2190",
    "sg:postcode":"91344",
    "sg:province":"CA",
    "sg:tags":[
        "exporter"
    ],
    "wof:name":"Marchanay Inter-Trade Co LTD",
    "wof:placetype":"venue"
},
  "geometry": {"coordinates":[-118.509897,34.259378],"type":"Point"}
}