{
  "type": "Feature",
  "properties": {
    "addr:full":"522 7th St Oakland CA 94607",
    "addr:housenumber":"522",
    "addr:postcode":"94607",
    "addr:street":"7Th St",
    "iso:country":"US",
    "sg:address":"522 7th St",
    "sg:city":"Oakland",
    "sg:classifiers":[
        {
            "category":"Communications",
            "subcategory":"Newspaper",
            "type":"Services"
        }
    ],
    "sg:phone":"+1 510 763 5255",
    "sg:postcode":"94607",
    "sg:province":"CA",
    "sg:tags":[
        "magazine"
    ],
    "wof:name":"Thoi Bao Magazine",
    "wof:placetype":"venue"
},
  "geometry": {"coordinates":[-122.275892,37.800328],"type":"Point"}
}