{
  "type": "Feature",
  "properties": {
    "addr:full":"401 Parnassus Ave San Francisco CA 94143",
    "addr:housenumber":"401",
    "addr:postcode":"94143",
    "addr:street":"Parnassus Ave",
    "iso:country":"US",
    "sg:address":"401 Parnassus Ave",
    "sg:city":"San Francisco",
    "sg:classifiers":[
        {
            "category":"Manufacturing",
            "subcategory":"Tools & Machinery",
            "type":"Manufacturing & Wholesale Goods"
        }
    ],
    "sg:phone":"+1 415 476 7675",
    "sg:postcode":"94143",
    "sg:province":"CA",
    "sg:tags":[
        "mfg",
        "commercial",
        "lab",
        "physical"
    ],
    "wof:name":"SF Treatment Research Ctr",
    "wof:placetype":"venue"
},
  "geometry": {"coordinates":[-122.457536,37.763566],"type":"Point"}
}