{
  "type": "Feature",
  "properties": {
    "addr:full":"2348 Alva Ave El Cerrito CA 94530",
    "addr:housenumber":"2348",
    "addr:postcode":"94530",
    "addr:street":"Alva Ave",
    "iso:country":"US",
    "sg:address":"2348 Alva Ave",
    "sg:city":"El Cerrito",
    "sg:classifiers":[
        {
            "category":"Professional",
            "subcategory":"Engineering",
            "type":"Services"
        }
    ],
    "sg:phone":"+1 510 525 4212",
    "sg:postcode":"94530",
    "sg:province":"CA",
    "sg:tags":[
        "engineer"
    ],
    "wof:name":"Head Engineering & Constr",
    "wof:placetype":"venue"
},
  "geometry": {"coordinates":[-122.311708,37.934258],"type":"Point"}
}