{
  "type": "Feature",
  "properties": {
    "addr:full":"1342 E Chapman Ave Orange CA 92866",
    "addr:housenumber":"1342",
    "addr:postcode":"92866",
    "addr:street":"E Chapman Ave",
    "iso:country":"US",
    "sg:address":"1342 E Chapman Ave",
    "sg:city":"Orange",
    "sg:classifiers":[
        {
            "category":"Real Estate",
            "subcategory":"Real Estate Agent",
            "type":"Services"
        }
    ],
    "sg:phone":"+1 714 647 5505",
    "sg:postcode":"92866",
    "sg:province":"CA",
    "wof:name":"Twentyone Ballin Inc",
    "wof:placetype":"venue"
},
  "geometry": {"coordinates":[-117.839395,33.787832],"type":"Point"}
}