{
  "type": "Feature",
  "properties": {
    "addr:full":"2617 Via Verona Lancaster CA 93535",
    "addr:housenumber":"2617",
    "addr:postcode":"93535",
    "addr:street":"Via Verona",
    "iso:country":"US",
    "sg:address":"2617 Via Verona",
    "sg:city":"Lancaster",
    "sg:classifiers":[
        {
            "category":"Manufacturing",
            "subcategory":"Printing",
            "type":"Manufacturing & Wholesale Goods"
        }
    ],
    "sg:phone":"+1 661 946 2746",
    "sg:postcode":"93535",
    "sg:province":"CA",
    "sg:tags":[
        "publishing"
    ],
    "wof:name":"Truedesigns",
    "wof:placetype":"venue"
},
  "geometry": {"coordinates":[-118.083049,34.691047],"type":"Point"}
}