{
  "type": "Feature",
  "properties": {
    "addr:full":"4340 Santa Fe Rd San Luis Obispo CA 93401",
    "addr:housenumber":"4340",
    "addr:postcode":"93401",
    "addr:street":"Santa Fe Rd",
    "iso:country":"US",
    "sg:address":"4340 Santa Fe Rd",
    "sg:city":"San Luis Obispo",
    "sg:classifiers":[
        {
            "category":"Manufacturing",
            "subcategory":"Tools & Machinery",
            "type":"Manufacturing & Wholesale Goods"
        }
    ],
    "sg:phone":"+1 805 544 5572",
    "sg:postcode":"93401",
    "sg:province":"CA",
    "sg:tags":[
        "physician",
        "surgeon"
    ],
    "sg:website":"www.ctint.org",
    "wof:name":"C T Intl",
    "wof:placetype":"venue"
},
  "geometry": {"coordinates":[-120.64918400000001,35.238667],"type":"Point"}
}