{
  "type": "Feature",
  "properties": {
    "iso:country":"US",
    "sg:address":"4340 Santa Fe Rd",
    "sg:city":"San Luis Obispo",
    "sg:classifiers":[
        {
            "category":"Manufacturing",
            "subcategory":"Tools & Machinery",
            "type":"Manufacturing & Wholesale Goods"
        }
    ],
    "sg:phone":"+1 805 544 5572",
    "sg:postcode":"93401",
    "sg:province":"CA",
    "sg:tags":[
        "physician",
        "surgeon"
    ],
    "sg:website":"www.ctint.org",
    "wof:name":"C T Intl",
    "wof:placetype":"venue"
},
  "geometry": {"coordinates":[-120.649184,35.238667],"type":"Point"}
}