{
  "type": "Feature",
  "properties": {
    "addr:full":"1135 Walsh Ave Suite 101 Santa Clara CA 95050",
    "addr:housenumber":"1135",
    "addr:postcode":"95050",
    "addr:street":"Walsh Ave Suite 101",
    "iso:country":"US",
    "sg:address":"1135 Walsh Ave Suite 101",
    "sg:city":"Santa Clara",
    "sg:classifiers":[
        {
            "category":"Professional",
            "subcategory":"Computer Services",
            "type":"Services"
        }
    ],
    "sg:phone":"+1 408 970 8566",
    "sg:postcode":"95050",
    "sg:province":"CA",
    "sg:tags":[
        "repair"
    ],
    "wof:name":"Securematics",
    "wof:placetype":"venue"
},
  "geometry": {"coordinates":[-121.953501,37.369839],"type":"Point"}
}