{
  "type": "Feature",
  "properties": {
    "iso:country":"US",
    "sg:address":"13255 Black Mountain Rd",
    "sg:city":"San Diego",
    "sg:classifiers":[
        {
            "category":"Banks & Credit Unions",
            "subcategory":"Bank",
            "type":"Services"
        }
    ],
    "sg:phone":"+1 858 538 8667",
    "sg:postcode":"92129",
    "sg:province":"CA",
    "sg:tags":[
        "national",
        "commercial"
    ],
    "wof:name":"Wells Fargo",
    "wof:placetype":"venue"
},
  "geometry": {"coordinates":[-117.129811,32.955425],"type":"Point"}
}