{
  "type": "Feature",
  "properties": {
    "iso:country":"US",
    "sg:address":"420 5th St",
    "sg:city":"San Francisco",
    "sg:classifiers":[
        {
            "category":"Autos & Motor Vehicles",
            "subcategory":"Automobile Sales",
            "type":"Retail Goods"
        }
    ],
    "sg:phone":"+1 415 794 6744",
    "sg:postcode":"94105",
    "sg:province":"CA",
    "sg:tags":[
        "limo"
    ],
    "sg:website":"www.giantreeflimo.com",
    "wof:name":"Giant Reef Limousine",
    "wof:placetype":"venue"
},
  "geometry": {"coordinates":[-122.401652,37.778703],"type":"Point"}
}