{
  "type": "Feature",
  "properties": {
    "addr:full":"20202 State Rd Cerritos CA 90703",
    "addr:housenumber":"20202",
    "addr:postcode":"ca 90703",
    "addr:street":"State Rd",
    "iso:country":"US",
    "sg:address":"20202 State Rd",
    "sg:city":"Cerritos",
    "sg:classifiers":[
        {
            "category":"Manufacturing",
            "subcategory":"Tools & Machinery",
            "type":"Manufacturing & Wholesale Goods"
        }
    ],
    "sg:phone":"+1 562 809 5228",
    "sg:postcode":"90703",
    "sg:province":"CA",
    "sg:tags":[
        "equipment",
        "industrial",
        "mfg"
    ],
    "sg:website":"www.bestlinepro.com",
    "wof:name":"Bestline Products Inc",
    "wof:placetype":"venue"
},
  "geometry": {"coordinates":[-118.094922,33.847672],"type":"Point"}
}