{
  "type": "Feature",
  "properties": {
    "addr:full":"331 Main St Half Moon Bay CA 94019",
    "addr:housenumber":"331",
    "addr:postcode":"94019",
    "addr:street":"Main St",
    "iso:country":"US",
    "sg:address":"331 Main St",
    "sg:city":"Half Moon Bay",
    "sg:classifiers":[
        {
            "category":"Wholesale",
            "subcategory":"Farm Supplies",
            "type":"Manufacturing & Wholesale Goods"
        }
    ],
    "sg:phone":"+1 650 726 4814",
    "sg:postcode":"94019",
    "sg:province":"CA",
    "sg:tags":[
        "feed"
    ],
    "wof:name":"Half Moon Bay Feed & Fuel",
    "wof:placetype":"venue"
},
  "geometry": {"coordinates":[-122.428944,37.465056],"type":"Point"}
}