{
  "type": "Feature",
  "properties": {
    "addr:full":"14504 S Western Ave Gardena CA 90249",
    "addr:housenumber":"14504",
    "addr:postcode":"90249",
    "addr:street":"S Western Ave",
    "iso:country":"US",
    "sg:address":"14504 S Western Ave",
    "sg:city":"Gardena",
    "sg:classifiers":[
        {
            "category":"Personal",
            "subcategory":"Barber",
            "type":"Services"
        }
    ],
    "sg:phone":"+1 310 515 9367",
    "sg:postcode":"90249",
    "sg:province":"CA",
    "wof:name":"El Senor Barber Salon",
    "wof:placetype":"venue"
},
  "geometry": {"coordinates":[-118.30895599999999,33.899949],"type":"Point"}
}