{
  "type": "Feature",
  "properties": {
    "addr:full":"3972 el Camino Real Palo Alto CA 94306",
    "addr:housenumber":"3972",
    "addr:postcode":"94306",
    "addr:street":"El Camino Real",
    "iso:country":"US",
    "sg:address":"3972 el Camino Real",
    "sg:city":"Palo Alto",
    "sg:classifiers":[
        {
            "category":"Retail",
            "subcategory":"Auto Repair",
            "type":"Services"
        }
    ],
    "sg:phone":"+1 650 493 1371",
    "sg:postcode":"94306",
    "sg:province":"CA",
    "sg:tags":[
        "repairing",
        "automobile"
    ],
    "wof:name":"Jim Davis Automotive",
    "wof:placetype":"venue"
},
  "geometry": {"coordinates":[-122.128444,37.415752],"type":"Point"}
}