{
  "type": "Feature",
  "properties": {
    "iso:country":"US",
    "sg:address":"1310 el Paseo de Saratoga",
    "sg:city":"San Jose",
    "sg:classifiers":[
        {
            "category":"Home & Garden",
            "subcategory":"Furniture",
            "type":"Retail Goods"
        }
    ],
    "sg:phone":"+1 408 379 2640",
    "sg:postcode":"95130",
    "sg:province":"CA",
    "sg:website":"www.norwalkfurnitureidea.com",
    "wof:name":"Norwalk-The Furniture Idea",
    "wof:placetype":"venue"
},
  "geometry": {"coordinates":[-121.990165,37.289231],"type":"Point"}
}