{
  "type": "Feature",
  "properties": {
    "addr:full":"3311 W Manchester Blvd Inglewood CA 90305",
    "addr:housenumber":"3311",
    "addr:postcode":"90305",
    "addr:street":"W Manchester Blvd",
    "iso:country":"US",
    "sg:address":"3311 W Manchester Blvd",
    "sg:city":"Inglewood",
    "sg:classifiers":[
        {
            "category":"Government",
            "subcategory":"Office",
            "type":"Public Place"
        }
    ],
    "sg:phone":"+1 323 752 3700",
    "sg:postcode":"90305",
    "sg:province":"CA",
    "sg:tags":[
        "housing",
        "program"
    ],
    "wof:name":"Cybersonic Rcrds Inc Urbn MSC",
    "wof:placetype":"venue"
},
  "geometry": {"coordinates":[-118.329684,33.96013],"type":"Point"}
}