{
  "type": "Feature",
  "properties": {
    "addr:full":"4000 Truxel Rd Ste A5 Sacramento CA 95834",
    "addr:postcode":"4000;95834",
    "addr:street":"Truxel Rd Ste A5",
    "iso:country":"US",
    "sg:address":"4000 Truxel Rd Ste A5",
    "sg:city":"Sacramento",
    "sg:classifiers":[
        {
            "category":"Restaurant",
            "type":"Food & Drink"
        }
    ],
    "sg:phone":"+1 916 928 8041",
    "sg:postcode":"95834",
    "sg:province":"CA",
    "sg:tags":[
        "barbeque"
    ],
    "wof:name":"House of Chicken Wings and Things",
    "wof:placetype":"venue"
},
  "geometry": {"coordinates":[-121.508555,38.641752],"type":"Point"}
}