{
  "type": "Feature",
  "properties": {
    "iso:country":"US",
    "sg:address":"11011 Tujunga Dr",
    "sg:city":"Apple Valley",
    "sg:classifiers":[
        {
            "category":"Building & Trades",
            "subcategory":"Electrical",
            "type":"Services"
        }
    ],
    "sg:phone":"+1 760 247 5609",
    "sg:postcode":"92308",
    "sg:province":"CA",
    "sg:tags":[
        "electrical",
        "contractor"
    ],
    "wof:name":"Jones Electric",
    "wof:placetype":"venue"
},
  "geometry": {"coordinates":[-117.14852399999999,34.453609],"type":"Point"}
}