{
  "type": "Feature",
  "properties": {
    "iso:country":"US",
    "sg:address":"415 S Union Ave",
    "sg:city":"Bakersfield",
    "sg:classifiers":[
        {
            "category":"Restaurant",
            "type":"Food & Drink"
        }
    ],
    "sg:phone":"+1 661 637 0506",
    "sg:postcode":"93307",
    "sg:province":"CA",
    "wof:name":"Phine's Cafe",
    "wof:placetype":"venue"
},
  "geometry": {"coordinates":[-119.003079,35.348765],"type":"Point"}
}