{
  "type": "Feature",
  "properties": {
    "iso:country":"US",
    "sg:address":"333 N Palm Canyon Dr",
    "sg:city":"Palm Springs",
    "sg:classifiers":[
        {
            "category":"Personal",
            "subcategory":"Adult",
            "type":"Services"
        }
    ],
    "sg:phone":"+1 760 318 6221",
    "sg:postcode":"92262",
    "sg:province":"CA",
    "sg:tags":[
        "escort"
    ],
    "wof:name":"First Clas Escorts",
    "wof:placetype":"venue"
},
  "geometry": {"coordinates":[-116.54690100000001,33.827298],"type":"Point"}
}