{
  "type": "Feature",
  "properties": {
    "iso:country":"US",
    "sg:address":"6822 Milwood Ave",
    "sg:city":"Canoga Park",
    "sg:classifiers":[
        {
            "category":"Shopping",
            "subcategory":"Computers & Home Electronics",
            "type":"Retail Goods"
        }
    ],
    "sg:phone":"+1 818 992 6709",
    "sg:postcode":"91303",
    "sg:province":"CA",
    "sg:tags":[
        "equipment",
        "dealer"
    ],
    "wof:name":"Sky Tech Computers Inc",
    "wof:placetype":"venue"
},
  "geometry": {"coordinates":[-118.594179,34.19489],"type":"Point"}
}