{
  "type": "Feature",
  "properties": {
    "addr:full":"727 W Channel Islands Blvd Port Hueneme CA 93041",
    "addr:housenumber":"727",
    "addr:postcode":"93041",
    "addr:street":"W Channel Islands Blvd",
    "iso:country":"US",
    "sg:address":"727 W Channel Islands Blvd",
    "sg:city":"Port Hueneme",
    "sg:classifiers":[
        {
            "category":"Food & Beverages",
            "subcategory":"Groceries & Convenience Stores",
            "type":"Retail Goods"
        }
    ],
    "sg:phone":"+1 805 985 2536",
    "sg:postcode":"93041",
    "sg:province":"CA",
    "sg:tags":[
        "supermarket"
    ],
    "wof:name":"Vons 2433",
    "wof:placetype":"venue"
},
  "geometry": {"coordinates":[-119.218074,34.175816],"type":"Point"}
}