{
  "type": "Feature",
  "properties": {
    "addr:full":"4910 Dehesa Rd El Cajon CA 92019",
    "addr:housenumber":"4910",
    "addr:postcode":"92019",
    "addr:street":"Dehesa Rd",
    "iso:country":"US",
    "sg:address":"4910 Dehesa Rd",
    "sg:city":"El Cajon",
    "sg:classifiers":[
        {
            "category":"Shopping",
            "type":"Retail Goods"
        }
    ],
    "sg:phone":"+1 619 401 0552",
    "sg:postcode":"92019",
    "sg:province":"CA",
    "sg:tags":[
        "miscellaneous",
        "store"
    ],
    "wof:name":"Not To Be Ignored",
    "wof:placetype":"venue"
},
  "geometry": {"coordinates":[-116.84546,32.787811],"type":"Point"}
}