{
  "type": "Feature",
  "properties": {
    "iso:country":"US",
    "sg:address":"1114 Beachwood Way",
    "sg:city":"Oceanside",
    "sg:classifiers":[
        {
            "category":"Shopping",
            "subcategory":"Gifts & Souvenirs",
            "type":"Retail Goods"
        }
    ],
    "sg:phone":"+1 760 940 8198",
    "sg:postcode":"92057",
    "sg:province":"CA",
    "sg:tags":[
        "shop"
    ],
    "wof:name":"Family Tradition",
    "wof:placetype":"venue"
},
  "geometry": {"coordinates":[-117.290718,33.229859],"type":"Point"}
}