{
  "type": "Feature",
  "properties": {
    "iso:country":"US",
    "sg:address":"235 S F St",
    "sg:city":"Oxnard",
    "sg:classifiers":[
        {
            "category":"Health Services",
            "subcategory":"Clinic",
            "type":"Services"
        }
    ],
    "sg:phone":"+1 805 483 0279",
    "sg:postcode":"93030",
    "sg:province":"CA",
    "sg:tags":[
        "welfare"
    ],
    "wof:name":"Natural Health Strategies",
    "wof:placetype":"venue"
},
  "geometry": {"coordinates":[-119.18510499999999,34.201233],"type":"Point"}
}