{
  "type": "Feature",
  "properties": {
    "addr:full":"1660 Chicago Ave Riverside CA 92507",
    "addr:housenumber":"1660",
    "addr:postcode":"92507",
    "addr:street":"Chicago Ave",
    "iso:country":"US",
    "sg:address":"1660 Chicago Ave",
    "sg:city":"Riverside",
    "sg:classifiers":[
        {
            "category":"Professional",
            "subcategory":"Computer Services",
            "type":"Services"
        }
    ],
    "sg:phone":"+1 951 788 6038",
    "sg:postcode":"92507",
    "sg:province":"CA",
    "sg:tags":[
        "electronics"
    ],
    "wof:name":"Thermolife",
    "wof:placetype":"venue"
},
  "geometry": {"coordinates":[-117.34836300000001,33.990949],"type":"Point"}
}