{
  "type": "Feature",
  "properties": {
    "addr:full":"6345 Crenshaw Blvd Los Angeles CA 90043",
    "addr:housenumber":"6345",
    "addr:postcode":"90043",
    "addr:street":"Crenshaw Blvd",
    "iso:country":"US",
    "sg:address":"6345 Crenshaw Blvd",
    "sg:city":"Los Angeles",
    "sg:classifiers":[
        {
            "category":"Travel",
            "subcategory":"Hotels & Motels",
            "type":"Entertainment"
        }
    ],
    "sg:phone":"+1 323 751 3227",
    "sg:postcode":"90043",
    "sg:province":"CA",
    "wof:name":"Cornett Motel",
    "wof:placetype":"venue"
},
  "geometry": {"coordinates":[-118.331001,33.982101],"type":"Point"}
}