{
  "type": "Feature",
  "properties": {
    "addr:full":"1701 W Slauson Ave Los Angeles CA 90047",
    "addr:housenumber":"1701",
    "addr:postcode":"90047",
    "addr:street":"W Slauson Ave",
    "iso:country":"US",
    "sg:address":"1701 W Slauson Ave",
    "sg:city":"Los Angeles",
    "sg:classifiers":[
        {
            "category":"Retail",
            "subcategory":"Storage",
            "type":"Services"
        }
    ],
    "sg:phone":"+1 323 295 8500",
    "sg:postcode":"90047",
    "sg:province":"CA",
    "sg:tags":[
        "self"
    ],
    "sg:website":"www.storquest.com",
    "wof:name":"Storquest Self Storage",
    "wof:placetype":"venue"
},
  "geometry": {"coordinates":[-118.306406,33.98911],"type":"Point"}
}