{
  "type": "Feature",
  "properties": {
    "iso:country":"US",
    "sg:address":"3134 E 1st St",
    "sg:city":"Long Beach",
    "sg:classifiers":[
        {
            "category":"Professional",
            "subcategory":"Business Services",
            "type":"Services"
        }
    ],
    "sg:phone":"+1 562 930 1088",
    "sg:postcode":"90803",
    "sg:province":"CA",
    "sg:tags":[
        "good"
    ],
    "wof:name":"Design Interiors",
    "wof:placetype":"venue"
},
  "geometry": {"coordinates":[-118.15427200000001,33.762662],"type":"Point"}
}