{
  "type": "Feature",
  "properties": {
    "iso:country":"US",
    "sg:address":"340 Abbott St",
    "sg:city":"Salinas",
    "sg:classifiers":[
        {
            "category":"Autos & Motor Vehicles",
            "subcategory":"Auto Supplies",
            "type":"Retail Goods"
        },
        {
            "category":"Retail",
            "subcategory":"Auto Repair",
            "type":"Services"
        }
    ],
    "sg:phone":"+1 831 757 2419",
    "sg:postcode":"93901",
    "sg:province":"CA",
    "sg:tags":[
        "body",
        "lettering",
        "automobile",
        "truck",
        "painting",
        "repairing"
    ],
    "wof:name":"Styles Collision Center",
    "wof:placetype":"venue"
},
  "geometry": {"coordinates":[-121.644572,36.666365],"type":"Point"}
}