{
  "type": "Feature",
  "properties": {
    "iso:country":"US",
    "sg:address":"16742 Placerita Cyn Rd",
    "sg:city":"Newhall",
    "sg:classifiers":[
        {
            "category":"Animal Shelter",
            "type":"Public Place"
        },
        {
            "category":"Retail",
            "subcategory":"Pet Boarding",
            "type":"Services"
        }
    ],
    "sg:phone":"+1 661 255 0097",
    "sg:postcode":"91321",
    "sg:province":"CA",
    "sg:tags":[
        "boarding/pet",
        "sitting"
    ],
    "sg:website":"www.newleash.org/",
    "wof:name":"New Leash On Life Animal Rescue",
    "wof:placetype":"venue"
},
  "geometry": {"coordinates":[-118.425264,34.375505],"type":"Point"}
}