{
  "type": "Feature",
  "properties": {
    "addr:full":"451 S Market St Inglewood CA 90301",
    "addr:housenumber":"451",
    "addr:postcode":"90301",
    "addr:street":"S Market St",
    "iso:country":"US",
    "sg:address":"451 S Market St",
    "sg:city":"Inglewood",
    "sg:classifiers":[
        {
            "category":"Retail",
            "subcategory":"Auto Repair",
            "type":"Services"
        }
    ],
    "sg:phone":"+1 310 674 6206",
    "sg:postcode":"90301",
    "sg:province":"CA",
    "sg:tags":[
        "automobile",
        "top",
        "upholstery"
    ],
    "wof:name":"Supreme Auto & Home Upholstery",
    "wof:placetype":"venue"
},
  "geometry": {"coordinates":[-118.35202200000001,33.958052],"type":"Point"}
}