{
  "type": "Feature",
  "properties": {
    "iso:country":"US",
    "sg:address":"20286 Carrey Rd",
    "sg:city":"Walnut",
    "sg:classifiers":[
        {
            "category":"Shopping",
            "subcategory":"Computers & Home Electronics",
            "type":"Retail Goods"
        }
    ],
    "sg:phone":"+1 909 598 1266",
    "sg:postcode":"91789",
    "sg:province":"CA",
    "sg:tags":[
        "equipment",
        "dealer"
    ],
    "sg:website":"www.lpc-tech.com",
    "wof:name":"Lpc Technology",
    "wof:placetype":"venue"
},
  "geometry": {"coordinates":[-117.861678,34.013321],"type":"Point"}
}