{
  "type": "Feature",
  "properties": {
    "addr:full":"3044 S Centre City Pkwy Escondido CA 92029",
    "addr:housenumber":"3044",
    "addr:postcode":"92029",
    "addr:street":"S Centre City Pkwy",
    "iso:country":"US",
    "sg:address":"3044 S Centre City Pkwy",
    "sg:city":"Escondido",
    "sg:classifiers":[
        {
            "category":"Real Estate",
            "subcategory":"Real Estate Agent",
            "type":"Services"
        }
    ],
    "sg:phone":"+1 760 746 9127",
    "sg:postcode":"92029",
    "sg:province":"CA",
    "sg:tags":[
        "management"
    ],
    "wof:name":"Barret Condo Management Mntnc",
    "wof:placetype":"venue"
},
  "geometry": {"coordinates":[-117.07341,33.078376],"type":"Point"}
}