{
  "type": "Feature",
  "properties": {
    "iso:country":"US",
    "sg:address":"225 Main St",
    "sg:city":"Chico",
    "sg:classifiers":[
        {
            "category":"Shopping",
            "subcategory":"Gifts & Souvenirs",
            "type":"Retail Goods"
        }
    ],
    "sg:phone":"+1 530 342 9035",
    "sg:postcode":"95928",
    "sg:province":"CA",
    "sg:tags":[
        "shop"
    ],
    "wof:name":"Brambley Cottage",
    "wof:placetype":"venue"
},
  "geometry": {"coordinates":[-121.839755,39.729768],"type":"Point"}
}