{
  "type": "Feature",
  "properties": {
    "iso:country":"US",
    "sg:address":"41221 Via Aguila",
    "sg:city":"Temecula",
    "sg:classifiers":[
        {
            "category":"Freight",
            "type":"Transportation"
        }
    ],
    "sg:phone":"+1 951 699 8621",
    "sg:postcode":"92591",
    "sg:province":"CA",
    "sg:tags":[
        "local",
        "except",
        "trucking"
    ],
    "wof:name":"The American Dream Mvg & Stor",
    "wof:placetype":"venue"
},
  "geometry": {"coordinates":[-117.119956,33.521729],"type":"Point"}
}