{
  "type": "Feature",
  "properties": {
    "addr:full":"2260 Douglas Blvd Roseville CA 95678",
    "addr:housenumber":"2260",
    "addr:postcode":"95678",
    "addr:street":"Douglas Blvd",
    "iso:country":"US",
    "sg:address":"2260 Douglas Blvd",
    "sg:city":"Roseville",
    "sg:classifiers":[
        {
            "category":"Professional",
            "subcategory":"Accounting & Tax Preparation",
            "type":"Services"
        }
    ],
    "sg:phone":"+1 916 782 3400",
    "sg:postcode":"95678",
    "sg:province":"CA",
    "sg:tags":[
        "accountant"
    ],
    "wof:name":"Boxler & Van Erp",
    "wof:placetype":"venue"
},
  "geometry": {"coordinates":[-121.248543,38.744206],"type":"Point"}
}