{
  "type": "Feature",
  "properties": {
    "addr:full":"2870 State St Carlsbad CA 92008",
    "addr:housenumber":"2870",
    "addr:postcode":"92008",
    "addr:street":"State St",
    "iso:country":"US",
    "sg:address":"2870 State St",
    "sg:city":"Carlsbad",
    "sg:classifiers":[
        {
            "category":"Home & Garden",
            "subcategory":"Carpets & Floor Coverings",
            "type":"Retail Goods"
        }
    ],
    "sg:phone":"+1 760 729 1515",
    "sg:postcode":"92008",
    "sg:province":"CA",
    "wof:name":"Aria Carpet Carlsbad",
    "wof:placetype":"venue"
},
  "geometry": {"coordinates":[-117.349847,33.161146],"type":"Point"}
}