{
  "type": "Feature",
  "properties": {
    "addr:full":"274 Gil Blas Rd Danville CA 94526",
    "addr:housenumber":"274",
    "addr:postcode":"94526",
    "addr:street":"Gil Blas Rd",
    "iso:country":"US",
    "sg:address":"274 Gil Blas Rd",
    "sg:city":"Danville",
    "sg:classifiers":[
        {
            "category":"Professional",
            "subcategory":"Business Services",
            "type":"Services"
        }
    ],
    "sg:phone":"+1 510 887 6559",
    "sg:postcode":"94526",
    "sg:province":"CA",
    "sg:tags":[
        "plant",
        "design",
        "maintenance"
    ],
    "sg:website":"www.ficusnfern.com",
    "wof:name":"Ficus & Fern",
    "wof:placetype":"venue"
},
  "geometry": {"coordinates":[-121.9783,37.820493],"type":"Point"}
}