{
  "type": "Feature",
  "properties": {
    "iso:country":"US",
    "sg:address":"717 Battery St",
    "sg:city":"San Francisco",
    "sg:classifiers":[
        {
            "category":"Banks & Credit Unions",
            "subcategory":"Financial Services",
            "type":"Services"
        }
    ],
    "sg:phone":"+1 415 263 7465",
    "sg:postcode":"94111",
    "sg:province":"CA",
    "sg:tags":[
        "investor"
    ],
    "wof:name":"Musto Properties Inc",
    "wof:placetype":"venue"
},
  "geometry": {"coordinates":[-122.40106,37.79821],"type":"Point"}
}