{
  "type": "Feature",
  "properties": {
    "addr:full":"800 McGarry St Los Angeles CA 90021",
    "addr:housenumber":"800",
    "addr:postcode":"90021",
    "addr:street":"Mcgarry St",
    "iso:country":"US",
    "sg:address":"800 McGarry St",
    "sg:city":"Los Angeles",
    "sg:classifiers":[
        {
            "category":"Wholesale",
            "subcategory":"Fruits & Vegetables",
            "type":"Manufacturing & Wholesale Goods"
        }
    ],
    "sg:phone":"+1 213 622 6971",
    "sg:postcode":"90021",
    "sg:province":"CA",
    "sg:tags":[
        "veggie"
    ],
    "wof:name":"Vegas Connection Inc",
    "wof:placetype":"venue"
},
  "geometry": {"coordinates":[-118.238998,34.030399],"type":"Point"}
}