{
  "type": "Feature",
  "properties": {
    "addr:full":"7617 3rd Ave Hesperia CA 92345",
    "addr:housenumber":"7617",
    "addr:postcode":"92345",
    "addr:street":"3Rd Ave",
    "iso:country":"US",
    "sg:address":"7617 3rd Ave",
    "sg:city":"Hesperia",
    "sg:classifiers":[
        {
            "category":"Building & Trades",
            "subcategory":"Construction",
            "type":"Services"
        }
    ],
    "sg:phone":"+1 760 948 3127",
    "sg:postcode":"92345",
    "sg:province":"CA",
    "sg:tags":[
        "contractor"
    ],
    "wof:name":"B & L Enterprises",
    "wof:placetype":"venue"
},
  "geometry": {"coordinates":[-117.316523,34.385262],"type":"Point"}
}