{
  "type": "Feature",
  "properties": {
    "addr:full":"32679 Sea Gate Dr Rancho Palos Verdes CA 90275",
    "addr:housenumber":"32679",
    "addr:postcode":"90275",
    "addr:street":"Sea Gate Dr",
    "iso:country":"US",
    "sg:address":"32679 Sea Gate Dr",
    "sg:city":"Rancho Palos Verdes",
    "sg:classifiers":[
        {
            "category":"Professional",
            "type":"Services"
        }
    ],
    "sg:phone":"+1 310 377 4445",
    "sg:postcode":"90275",
    "sg:province":"CA",
    "wof:name":"Bauendeckel Inc",
    "wof:placetype":"venue"
},
  "geometry": {"coordinates":[-118.38831999999999,33.743026],"type":"Point"}
}