{
  "type": "Feature",
  "properties": {
    "addr:full":"1212 S Main St Salinas CA 93901",
    "addr:housenumber":"1212",
    "addr:postcode":"93901",
    "addr:street":"S Main St",
    "iso:country":"US",
    "sg:address":"1212 S Main St",
    "sg:city":"Salinas",
    "sg:classifiers":[
        {
            "category":"Insurance",
            "subcategory":"Insurance Agent",
            "type":"Services"
        }
    ],
    "sg:phone":"+1 831 757 5265",
    "sg:postcode":"93901",
    "sg:province":"CA",
    "sg:tags":[
        "processing"
    ],
    "wof:name":"Tri-Counties Welfare Trust Fnd",
    "wof:placetype":"venue"
},
  "geometry": {"coordinates":[-121.659762,36.656994],"type":"Point"}
}