{
  "type": "Feature",
  "properties": {
    "addr:full":"1760 Sitka Ct Mckinleyville CA 95519",
    "addr:housenumber":"1760",
    "addr:postcode":"95519",
    "addr:street":"Sitka Ct",
    "iso:country":"US",
    "sg:address":"1760 Sitka Ct",
    "sg:city":"Mckinleyville",
    "sg:classifiers":[
        {
            "category":"Restaurant",
            "type":"Food & Drink"
        }
    ],
    "sg:phone":"+1 707 839 1330",
    "sg:postcode":"95519",
    "sg:province":"CA",
    "sg:tags":[
        "eating"
    ],
    "wof:name":"We Cader Picnic Tables",
    "wof:placetype":"venue"
},
  "geometry": {"coordinates":[-124.09816600000001,40.938256],"type":"Point"}
}