{
  "type": "Feature",
  "properties": {
    "iso:country":"US",
    "sg:address":"3380 Gilman Rd",
    "sg:city":"El Monte",
    "sg:classifiers":[
        {
            "category":"Manufacturing",
            "subcategory":"Tools & Machinery",
            "type":"Manufacturing & Wholesale Goods"
        }
    ],
    "sg:phone":"+1 626 443 8616",
    "sg:postcode":"91732",
    "sg:province":"CA",
    "sg:tags":[
        "stairway",
        "moving",
        "elevator"
    ],
    "sg:website":"www.bore-max.com",
    "wof:name":"Bore-Max Co",
    "wof:placetype":"venue"
},
  "geometry": {"coordinates":[-118.00673999999999,34.06371],"type":"Point"}
}