{
  "type": "Feature",
  "properties": {
    "iso:country":"US",
    "sg:address":"2429 W McFadden Ave",
    "sg:city":"Santa Ana",
    "sg:classifiers":[
        {
            "category":"Wholesale",
            "subcategory":"Scrap",
            "type":"Manufacturing & Wholesale Goods"
        }
    ],
    "sg:phone":"+1 714 554 3213",
    "sg:postcode":"92704",
    "sg:province":"CA",
    "sg:tags":[
        "recycling",
        "center"
    ],
    "wof:name":"Garcia Recycling",
    "wof:placetype":"venue"
},
  "geometry": {"coordinates":[-117.902231,33.734575],"type":"Point"}
}