{
  "type": "Feature",
  "properties": {
    "iso:country":"US",
    "sg:address":"46790 Lakeview Blvd",
    "sg:city":"Fremont",
    "sg:classifiers":[
        {
            "category":"Manufacturing",
            "subcategory":"Electronics",
            "type":"Manufacturing & Wholesale Goods"
        }
    ],
    "sg:phone":"+1 510 657 8396",
    "sg:postcode":"94538",
    "sg:province":"CA",
    "sg:tags":[
        "semiconductor",
        "devices"
    ],
    "wof:name":"Pictologic Inc",
    "wof:placetype":"venue"
},
  "geometry": {"coordinates":[-121.938418,37.482531],"type":"Point"}
}