{
  "type": "Feature",
  "properties": {
    "addr:full":"19661 Ditmar Ln Huntington Beach CA 92646",
    "addr:postcode":"19661;92646",
    "addr:street":"Ditmar Ln",
    "iso:country":"US",
    "sg:address":"19661 Ditmar Ln",
    "sg:city":"Huntington Beach",
    "sg:classifiers":[
        {
            "category":"Shopping",
            "subcategory":"Catalog Store",
            "type":"Retail Goods"
        }
    ],
    "sg:phone":"+1 714 968 2768",
    "sg:postcode":"92646",
    "sg:province":"CA",
    "sg:tags":[
        "mail",
        "house"
    ],
    "wof:name":"Goldyne",
    "wof:placetype":"venue"
},
  "geometry": {"coordinates":[-117.981435,33.676368],"type":"Point"}
}