{
  "type": "Feature",
  "properties": {
    "addr:full":"10463 Austin Dr Spring Valley CA 91978",
    "addr:housenumber":"10463",
    "addr:postcode":"91978",
    "addr:street":"Austin Dr",
    "iso:country":"US",
    "sg:address":"10463 Austin Dr",
    "sg:city":"Spring Valley",
    "sg:classifiers":[
        {
            "category":"Retail",
            "subcategory":"Auto Repair",
            "type":"Services"
        }
    ],
    "sg:phone":"+1 619 660 1994",
    "sg:postcode":"91978",
    "sg:province":"CA",
    "sg:tags":[
        "automobile",
        "installation",
        "glass"
    ],
    "sg:website":"www.expertautoglass.com",
    "wof:name":"Expert Auto Glass Inc",
    "wof:placetype":"venue"
},
  "geometry": {"coordinates":[-116.96506599999999,32.731749],"type":"Point"}
}