{
  "type": "Feature",
  "properties": {
    "addr:full":"226 N Euclid Ave Ontario CA 91762",
    "addr:housenumber":"226",
    "addr:postcode":"91762",
    "addr:street":"N Euclid Ave",
    "iso:country":"US",
    "sg:address":"226 N Euclid Ave",
    "sg:city":"Ontario",
    "sg:classifiers":[
        {
            "category":"Shopping",
            "subcategory":"Tobacco",
            "type":"Retail Goods"
        }
    ],
    "sg:phone":"+1 909 988 3126",
    "sg:postcode":"91762",
    "sg:province":"CA",
    "sg:tags":[
        "cigarette",
        "cigar",
        "dealer"
    ],
    "wof:name":"Express West",
    "wof:placetype":"venue"
},
  "geometry": {"coordinates":[-117.65093899999999,34.065481],"type":"Point"}
}