{
  "type": "Feature",
  "properties": {
    "iso:country":"US",
    "sg:address":"428 S Grand View Street",
    "sg:city":"Los Angeles",
    "sg:classifiers":[
        {
            "category":"Real Estate",
            "subcategory":"Real Estate Operator",
            "type":"Services"
        }
    ],
    "sg:phone":"+1 213 487 7765",
    "sg:postcode":"90057",
    "sg:province":"CA",
    "sg:tags":[
        "apartment"
    ],
    "wof:name":"Grand View Apartments",
    "wof:placetype":"venue"
},
  "geometry": {"coordinates":[-118.275965,34.06219],"type":"Point"}
}