{
  "type": "Feature",
  "properties": {
    "iso:country":"US",
    "sg:address":"387 N Escondido Blvd Ste C",
    "sg:city":"Escondido",
    "sg:classifiers":[
        {
            "category":"Personal",
            "subcategory":"Nail Salon",
            "type":"Services"
        }
    ],
    "sg:phone":"+1 760 737 9096",
    "sg:postcode":"92025",
    "sg:province":"CA",
    "wof:name":"International Deluxe Nails & Spa",
    "wof:placetype":"venue"
},
  "geometry": {"coordinates":[-117.086304,33.123277],"type":"Point"}
}