{
  "type": "Feature",
  "properties": {
    "addr:full":"529 Carlsbad Village Dr Ste A Carlsbad CA 92008",
    "addr:housenumber":"529",
    "addr:postcode":"92008",
    "addr:street":"Carlsbad Village Dr Ste A",
    "iso:country":"US",
    "sg:address":"529 Carlsbad Village Dr Ste A",
    "sg:city":"Carlsbad",
    "sg:classifiers":[
        {
            "category":"Personal",
            "type":"Services"
        }
    ],
    "sg:phone":"+1 760 729 7219",
    "sg:postcode":"92008",
    "sg:province":"CA",
    "sg:tags":[
        "sewing",
        "alteration"
    ],
    "wof:name":"Vega's Tailor Shop",
    "wof:placetype":"venue"
},
  "geometry": {"coordinates":[-117.348,33.159901],"type":"Point"}
}