{
  "type": "Feature",
  "properties": {
    "iso:country":"US",
    "sg:address":"6711 Arlington Ave",
    "sg:city":"Riverside",
    "sg:classifiers":[
        {
            "category":"Freight",
            "type":"Transportation"
        }
    ],
    "sg:phone":"+1 951 688 2763",
    "sg:postcode":"92504",
    "sg:province":"CA",
    "sg:tags":[
        "operator",
        "local",
        "trucking"
    ],
    "wof:name":"O and R Trucking Inc",
    "wof:placetype":"venue"
},
  "geometry": {"coordinates":[-117.442522,33.945962],"type":"Point"}
}