{
  "type": "Feature",
  "properties": {
    "iso:country":"US",
    "sg:address":"2860 Main St",
    "sg:city":"San Diego",
    "sg:classifiers":[
        {
            "category":"Restaurant",
            "type":"Food & Drink"
        }
    ],
    "sg:phone":"+1 619 696 3906",
    "sg:postcode":"92113",
    "sg:province":"CA",
    "sg:tags":[
        "mexican"
    ],
    "sg:website":"myspace.com/chagosmexfood",
    "wof:name":"Chago's Mexican Food",
    "wof:placetype":"venue"
},
  "geometry": {"coordinates":[-117.132441,32.692793],"type":"Point"}
}