{
  "type": "Feature",
  "properties": {
    "addr:full":"373 S Monroe St San Jose CA 95128",
    "addr:housenumber":"373",
    "addr:postcode":"95128",
    "addr:street":"S Monroe St",
    "iso:country":"US",
    "sg:address":"373 S Monroe St",
    "sg:city":"San Jose",
    "sg:classifiers":[
        {
            "category":"Personal",
            "type":"Services"
        }
    ],
    "sg:phone":"+1 408 509 1197",
    "sg:postcode":"95128",
    "sg:province":"CA",
    "sg:tags":[
        "therapist",
        "massage"
    ],
    "wof:name":"L A Health Ctr",
    "wof:placetype":"venue"
},
  "geometry": {"coordinates":[-121.94339100000001,37.3221],"type":"Point"}
}