{
  "type": "Feature",
  "properties": {
    "addr:full":"1235 Produce Row Los Angeles CA 90021",
    "addr:housenumber":"1235",
    "addr:postcode":"90021",
    "addr:street":"Produce Row",
    "iso:country":"US",
    "sg:address":"1235 Produce Row",
    "sg:city":"Los Angeles",
    "sg:classifiers":[
        {
            "category":"Wholesale",
            "subcategory":"Fruits & Vegetables",
            "type":"Manufacturing & Wholesale Goods"
        }
    ],
    "sg:phone":"+1 213 623 3692",
    "sg:postcode":"90021",
    "sg:province":"CA",
    "sg:tags":[
        "veggie"
    ],
    "wof:name":"Rancho Moreno",
    "wof:placetype":"venue"
},
  "geometry": {"coordinates":[-118.244536,34.033831],"type":"Point"}
}