{
  "type": "Feature",
  "properties": {
    "addr:full":"595 Venice Blvd Venice CA 90291",
    "addr:housenumber":"595",
    "addr:postcode":"90291",
    "addr:street":"Venice Blvd",
    "iso:country":"US",
    "sg:address":"595 Venice Blvd",
    "sg:city":"Venice",
    "sg:classifiers":[
        {
            "category":"Retail",
            "subcategory":"Auto Repair",
            "type":"Services"
        }
    ],
    "sg:phone":"+1 310 396 0069",
    "sg:postcode":"90291",
    "sg:province":"CA",
    "sg:tags":[
        "body",
        "automobile",
        "painting"
    ],
    "wof:name":"Mars Body Shop",
    "wof:placetype":"venue"
},
  "geometry": {"coordinates":[-118.46454799999999,33.987624],"type":"Point"}
}