{
  "type": "Feature",
  "properties": {
    "iso:country":"US",
    "sg:address":"18 Bonita St",
    "sg:city":"Arcadia",
    "sg:classifiers":[
        {
            "category":"Wholesale",
            "subcategory":"Electrical",
            "type":"Manufacturing & Wholesale Goods"
        }
    ],
    "sg:phone":"+1 626 294 9103",
    "sg:postcode":"91006",
    "sg:province":"CA",
    "sg:tags":[
        "electronic"
    ],
    "wof:name":"4 Star Elctronic Component Sls",
    "wof:placetype":"venue"
},
  "geometry": {"coordinates":[-118.028729,34.137806],"type":"Point"}
}