{
  "type": "Feature",
  "properties": {
    "addr:full":"43136 Christy St Fremont CA 94538",
    "addr:housenumber":"43136",
    "addr:postcode":"94538",
    "addr:street":"Christy St",
    "iso:country":"US",
    "sg:address":"43136 Christy St",
    "sg:city":"Fremont",
    "sg:classifiers":[
        {
            "category":"Insurance",
            "subcategory":"Insurance Agent",
            "type":"Services"
        }
    ],
    "sg:phone":"+1 510 490 7815",
    "sg:postcode":"94538",
    "sg:province":"CA",
    "wof:name":"Value Insurance Svc LLC",
    "wof:placetype":"venue"
},
  "geometry": {"coordinates":[-121.972516,37.506327],"type":"Point"}
}