{
  "type": "Feature",
  "properties": {
    "addr:full":"296A Addison St San Francisco CA 94131",
    "addr:housenumber":"296a",
    "addr:postcode":"94131",
    "addr:street":"Addison St",
    "iso:country":"US",
    "sg:address":"296A Addison St",
    "sg:city":"San Francisco",
    "sg:classifiers":[
        {
            "category":"Real Estate",
            "subcategory":"Real Estate Operator",
            "type":"Services"
        }
    ],
    "sg:phone":"+1 415 334 2698",
    "sg:postcode":"94131",
    "sg:province":"CA",
    "sg:tags":[
        "apartment"
    ],
    "sg:website":"www.DiamondViewAssoc.com",
    "wof:name":"Diamond View Apartments",
    "wof:placetype":"venue"
},
  "geometry": {"coordinates":[-122.43426599999999,37.74015],"type":"Point"}
}