{
  "type": "Feature",
  "properties": {
    "iso:country":"US",
    "sg:address":"725 Gilman St",
    "sg:city":"Berkeley",
    "sg:phone":"+1 510 849 1514",
    "sg:postcode":"94710",
    "sg:province":"CA",
    "sg:website":"http://www.tagpottery.com",
    "wof:name":"Tag Pottery & Fountains",
    "wof:placetype":"venue"
},
  "geometry": {"coordinates":[-122.30349,37.878941],"type":"Point"}
}