{
  "type": "Feature",
  "properties": {
    "iso:country":"US",
    "sg:address":"1133 Atlantic Ave",
    "sg:city":"Long Beach",
    "sg:classifiers":[
        {
            "category":"Travel",
            "subcategory":"Hotels & Motels",
            "type":"Entertainment"
        },
        {
            "category":"Retail",
            "subcategory":"Event Space",
            "type":"Services"
        }
    ],
    "sg:phone":"+1 562 590 8858",
    "sg:postcode":"90813",
    "sg:province":"CA",
    "sg:tags":[
        "venue"
    ],
    "sg:website":"www.holidayinn.com",
    "wof:name":"Holiday Inn Hotel Long Beach - Dwtn Area",
    "wof:placetype":"venue"
},
  "geometry": {"coordinates":[-118.185416,33.781667],"type":"Point"}
}