{
  "type": "Feature",
  "properties": {
    "addr:full":"9129 Elk Grove Blvd Elk Grove CA 95624",
    "addr:housenumber":"9129",
    "addr:postcode":"95624",
    "addr:street":"Elk Grove Blvd",
    "iso:country":"US",
    "sg:address":"9129 Elk Grove Blvd",
    "sg:city":"Elk Grove",
    "sg:classifiers":[
        {
            "category":"Real Estate",
            "subcategory":"Real Estate Agent",
            "type":"Services"
        }
    ],
    "sg:phone":"+1 916 685 2100",
    "sg:postcode":"95624",
    "sg:province":"CA",
    "wof:name":"Century 21",
    "wof:placetype":"venue"
},
  "geometry": {"coordinates":[-121.362301,38.409017],"type":"Point"}
}