{
  "type": "Feature",
  "properties": {
    "addr:full":"1890 19th Ave San Francisco CA 94122",
    "addr:housenumber":"1890",
    "addr:postcode":"94122",
    "addr:street":"19Th Ave",
    "iso:country":"US",
    "sg:address":"1890 19th Ave",
    "sg:city":"San Francisco",
    "sg:classifiers":[
        {
            "category":"Autos & Motor Vehicles",
            "subcategory":"Fuel & Gas Station",
            "type":"Retail Goods"
        }
    ],
    "sg:phone":"+1 415 731 2733",
    "sg:postcode":"94122",
    "sg:province":"CA",
    "wof:name":"B & W Chevron",
    "wof:placetype":"venue"
},
  "geometry": {"coordinates":[-122.47596,37.752639],"type":"Point"}
}