{
  "type": "Feature",
  "properties": {
    "addr:full":"55 Francisco St San Francisco CA 94133",
    "addr:housenumber":"55",
    "addr:postcode":"94133",
    "addr:street":"Francisco St",
    "iso:country":"US",
    "sg:address":"55 Francisco St",
    "sg:city":"San Francisco",
    "sg:classifiers":[
        {
            "category":"Parking",
            "type":"Transportation"
        }
    ],
    "sg:postcode":"94133",
    "sg:province":"CA",
    "wof:name":"Ace Parking",
    "wof:placetype":"venue"
},
  "geometry": {"coordinates":[-122.406245,37.80561],"type":"Point"}
}