{
  "type": "Feature",
  "properties": {
    "addr:full":"4425 Jamboree Road Newport Beach CA 92660",
    "addr:housenumber":"4425",
    "addr:postcode":"92660",
    "addr:street":"Jamboree Road",
    "iso:country":"US",
    "sg:address":"4425 Jamboree Road",
    "sg:city":"Newport Beach",
    "sg:classifiers":[
        {
            "category":"Professional",
            "subcategory":"Accounting & Tax Preparation",
            "type":"Services"
        }
    ],
    "sg:phone":"+1 949 474 0895",
    "sg:postcode":"92660",
    "sg:province":"CA",
    "sg:tags":[
        "accountant"
    ],
    "wof:name":"Colclaser Jas G CPA",
    "wof:placetype":"venue"
},
  "geometry": {"coordinates":[-117.85765499999999,33.662694],"type":"Point"}
}