{
  "type": "Feature",
  "properties": {
    "addr:full":"22326 Main Street Hayward CA 94541",
    "addr:housenumber":"22326",
    "addr:postcode":"94541",
    "addr:street":"Main Street",
    "iso:country":"US",
    "sg:address":"22326 Main Street",
    "sg:city":"Hayward",
    "sg:classifiers":[
        {
            "category":"Real Estate",
            "subcategory":"Real Estate Agent",
            "type":"Services"
        }
    ],
    "sg:phone":"+1 510 728 8610",
    "sg:postcode":"94541",
    "sg:province":"CA",
    "sg:website":"www.haywardandfohl.com",
    "wof:name":"Hayward and Fohl Realty - Jose Gonzalez",
    "wof:placetype":"venue"
},
  "geometry": {"coordinates":[-122.08475,37.675393],"type":"Point"}
}