{
  "type": "Feature",
  "properties": {
    "iso:country":"US",
    "sg:address":"17868 State Hwy 18",
    "sg:city":"Apple Valley",
    "sg:classifiers":[
        {
            "category":"Freight",
            "type":"Transportation"
        }
    ],
    "sg:phone":"+1 760 427 2398",
    "sg:postcode":"92307",
    "sg:province":"CA",
    "sg:tags":[
        "arrangement"
    ],
    "wof:name":"Barak Trucking",
    "wof:placetype":"venue"
},
  "geometry": {"coordinates":[-117.275015,34.5398],"type":"Point"}
}