{
  "type": "Feature",
  "properties": {
    "addr:full":"345 S. Serrano Los Angeles CA 90020",
    "addr:housenumber":"345",
    "addr:postcode":"90020",
    "addr:street":"S. Serrano",
    "iso:country":"US",
    "sg:address":"345 S. Serrano",
    "sg:city":"Los Angeles",
    "sg:classifiers":[
        {
            "category":"Communications",
            "subcategory":"Newspaper",
            "type":"Services"
        }
    ],
    "sg:phone":"+1 213 706 0010",
    "sg:postcode":"90020",
    "sg:province":"CA",
    "sg:tags":[
        "print",
        "medium"
    ],
    "sg:website":"www.lapinoymagazine.com",
    "wof:name":"la pinoy magazine",
    "wof:placetype":"venue"
},
  "geometry": {"coordinates":[-118.306988,34.067664],"type":"Point"}
}