{
  "type": "Feature",
  "properties": {
    "iso:country":"US",
    "sg:address":"2560 E Chapman Ave",
    "sg:city":"Orange",
    "sg:phone":"+1 949 419 6921",
    "sg:postcode":"92869",
    "sg:province":"CA",
    "sg:website":"http://www.aandegaragedoors.com",
    "wof:name":"A & E Garage Doors",
    "wof:placetype":"venue"
},
  "geometry": {"coordinates":[-117.82607,33.787823],"type":"Point"}
}