{
  "type": "Feature",
  "properties": {
    "addr:full":"5300 Pso Rancho Castilla Los Angeles CA 90032",
    "addr:housenumber":"5300",
    "addr:postcode":"90032",
    "addr:street":"Pso Rancho Castilla",
    "iso:country":"US",
    "sg:address":"5300 Pso Rancho Castilla",
    "sg:city":"Los Angeles",
    "sg:classifiers":[
        {
            "category":"Education",
            "subcategory":"College",
            "type":"Public Place"
        }
    ],
    "sg:phone":"+1 323 343 2527",
    "sg:postcode":"90032",
    "sg:province":"CA",
    "wof:name":"California State University",
    "wof:placetype":"venue"
},
  "geometry": {"coordinates":[-118.163319,34.069848],"type":"Point"}
}