{
  "type": "Feature",
  "properties": {
    "iso:country":"US",
    "sg:address":"2200 Monroe St",
    "sg:city":"Santa Clara",
    "sg:classifiers":[
        {
            "category":"Building & Trades",
            "subcategory":"Construction",
            "type":"Services"
        }
    ],
    "sg:phone":"+1 408 244 7800",
    "sg:postcode":"95050",
    "sg:province":"CA",
    "sg:tags":[
        "general",
        "contractor"
    ],
    "wof:name":"Frame To Final Construction",
    "wof:placetype":"venue"
},
  "geometry": {"coordinates":[-121.96424,37.362449],"type":"Point"}
}