{
  "type": "Feature",
  "properties": {
    "addr:full":"11843 Washington Blvd Whittier CA 90606",
    "addr:housenumber":"11843",
    "addr:postcode":"90606",
    "addr:street":"Washington Blvd",
    "iso:country":"US",
    "sg:address":"11843 Washington Blvd",
    "sg:city":"Whittier",
    "sg:classifiers":[
        {
            "category":"Food & Beverages",
            "subcategory":"Liquor & Beverages",
            "type":"Retail Goods"
        }
    ],
    "sg:phone":"+1 562 693 4494",
    "sg:postcode":"90606",
    "sg:province":"CA",
    "sg:tags":[
        "beer",
        "spirit",
        "wine"
    ],
    "wof:name":"Bills Liquor & Deli",
    "wof:placetype":"venue"
},
  "geometry": {"coordinates":[-118.05999799999999,33.969501],"type":"Point"}
}