{
  "type": "Feature",
  "properties": {
    "iso:country":"US",
    "sg:address":"910 Bern Ct",
    "sg:city":"San Jose",
    "sg:classifiers":[
        {
            "category":"Professional",
            "type":"Services"
        }
    ],
    "sg:phone":"+1 408 467 5560",
    "sg:postcode":"95112",
    "sg:province":"CA",
    "wof:name":"Wang Labs Inc",
    "wof:placetype":"venue"
},
  "geometry": {"coordinates":[-121.894915,37.375685],"type":"Point"}
}