{
  "type": "Feature",
  "properties": {
    "iso:country":"US",
    "sg:address":"9481 Mariposa Rd",
    "sg:city":"Hesperia",
    "sg:classifiers":[
        {
            "category":"Wholesale",
            "subcategory":"Machinery & Supplies",
            "type":"Manufacturing & Wholesale Goods"
        }
    ],
    "sg:phone":"+1 760 949 7708",
    "sg:postcode":"92344",
    "sg:province":"CA",
    "sg:tags":[
        "contractor"
    ],
    "sg:website":"www.earthworkstrux.com",
    "wof:name":"Earthworks Trucks & Equipment",
    "wof:placetype":"venue"
},
  "geometry": {"coordinates":[-117.390634,34.412573],"type":"Point"}
}