{
  "type": "Feature",
  "properties": {
    "iso:country":"US",
    "sg:address":"901 Hoyer Rd",
    "sg:city":"Newman",
    "sg:classifiers":[
        {
            "category":"Education",
            "subcategory":"School",
            "type":"Public Place"
        }
    ],
    "sg:phone":"+1 209 862 2984",
    "sg:postcode":"95360",
    "sg:province":"CA",
    "wof:name":"Yolo Middle School",
    "wof:placetype":"venue"
},
  "geometry": {"coordinates":[-121.033844,37.311264],"type":"Point"}
}