{
  "type": "Feature",
  "properties": {
    "addr:full":"864 E Ramsey St Banning CA 92220",
    "addr:housenumber":"864",
    "addr:postcode":"92220",
    "addr:street":"E Ramsey St",
    "iso:country":"US",
    "sg:address":"864 E Ramsey St",
    "sg:city":"Banning",
    "sg:classifiers":[
        {
            "category":"Food & Beverages",
            "subcategory":"Liquor & Beverages",
            "type":"Retail Goods"
        }
    ],
    "sg:phone":"+1 951 849 7931",
    "sg:postcode":"92220",
    "sg:province":"CA",
    "sg:tags":[
        "beer",
        "spirit",
        "wine"
    ],
    "wof:name":"Sportsmans Liquor",
    "wof:placetype":"venue"
},
  "geometry": {"coordinates":[-116.866997,33.925301],"type":"Point"}
}