{
  "type": "Feature",
  "properties": {
    "iso:country":"US",
    "sg:address":"861 Nevada St",
    "sg:city":"Auburn",
    "sg:classifiers":[
        {
            "category":"Wholesale",
            "subcategory":"Machinery & Supplies",
            "type":"Manufacturing & Wholesale Goods"
        },
        {
            "category":"Manufacturing",
            "subcategory":"Tools & Machinery",
            "type":"Manufacturing & Wholesale Goods"
        }
    ],
    "sg:phone":"+1 530 889 9469",
    "sg:postcode":"95603",
    "sg:province":"CA",
    "sg:tags":[
        "repairing",
        "mfg",
        "industrial",
        "general"
    ],
    "wof:name":"Sierra Equipment Repair Inc",
    "wof:placetype":"venue"
},
  "geometry": {"coordinates":[-121.082721,38.918177],"type":"Point"}
}