{
  "type": "Feature",
  "properties": {
    "iso:country":"US",
    "sg:address":"1366 Erin Ave",
    "sg:city":"Upland",
    "sg:classifiers":[
        {
            "category":"Professional",
            "type":"Services"
        }
    ],
    "sg:phone":"+1 909 981 4326",
    "sg:postcode":"91786",
    "sg:province":"CA",
    "wof:name":"Sean Flint",
    "wof:placetype":"venue"
},
  "geometry": {"coordinates":[-117.668234,34.112696],"type":"Point"}
}