{
  "type": "Feature",
  "properties": {
    "iso:country":"US",
    "sg:address":"401 San Pablo Ter",
    "sg:city":"Pacifica",
    "sg:classifiers":[
        {
            "category":"Building & Trades",
            "subcategory":"Landscaping Services",
            "type":"Services"
        }
    ],
    "sg:phone":"+1 650 359 1016",
    "sg:postcode":"94044",
    "sg:province":"CA",
    "sg:tags":[
        "landscape"
    ],
    "wof:name":"Newman Landscapes",
    "wof:placetype":"venue"
},
  "geometry": {"coordinates":[-122.483659,37.634012],"type":"Point"}
}