{
  "type": "Feature",
  "properties": {
    "iso:country":"US",
    "sg:address":"22203 S Vermont Ave",
    "sg:city":"Torrance",
    "sg:classifiers":[
        {
            "category":"Retail",
            "subcategory":"Auto Repair",
            "type":"Services"
        }
    ],
    "sg:phone":"+1 310 533 0953",
    "sg:postcode":"90502",
    "sg:province":"CA",
    "sg:tags":[
        "body",
        "automobile",
        "painting"
    ],
    "wof:name":"Delta Auto Body Commercials",
    "wof:placetype":"venue"
},
  "geometry": {"coordinates":[-118.29034,33.826091],"type":"Point"}
}