{
  "type": "Feature",
  "properties": {
    "addr:full":"1310 Ribera Pl Oxnard CA 93030",
    "addr:housenumber":"1310",
    "addr:postcode":"93030",
    "addr:street":"Ribera Pl",
    "iso:country":"US",
    "sg:address":"1310 Ribera Pl",
    "sg:city":"Oxnard",
    "sg:classifiers":[
        {
            "category":"Manufacturing",
            "subcategory":"Chemicals & Compounds",
            "type":"Manufacturing & Wholesale Goods"
        },
        {
            "category":"Wholesale",
            "subcategory":"Metals & Minerals",
            "type":"Manufacturing & Wholesale Goods"
        }
    ],
    "sg:phone":"+1 805 485 7500",
    "sg:postcode":"93030",
    "sg:province":"CA",
    "sg:tags":[
        "titanium",
        "center"
    ],
    "wof:name":"Express Metals Company",
    "wof:placetype":"venue"
},
  "geometry": {"coordinates":[-119.15092199999999,34.21392],"type":"Point"}
}