{
  "type": "Feature",
  "properties": {
    "iso:country":"US",
    "sg:address":"9970 Horn Rd",
    "sg:city":"Sacramento",
    "sg:classifiers":[
        {
            "category":"Building & Trades",
            "subcategory":"Construction",
            "type":"Services"
        },
        {
            "category":"Utilities",
            "subcategory":"Natural Gas",
            "type":"Services"
        },
        {
            "category":"Home & Garden",
            "subcategory":"Building Materials",
            "type":"Retail Goods"
        },
        {
            "category":"Home & Garden",
            "subcategory":"Carpets & Floor Coverings",
            "type":"Retail Goods"
        },
        {
            "category":"Manufacturing",
            "subcategory":"Wood Products",
            "type":"Manufacturing & Wholesale Goods"
        },
        {
            "category":"Manufacturing",
            "subcategory":"Glass & Minerals",
            "type":"Manufacturing & Wholesale Goods"
        }
    ],
    "sg:phone":"+1 916 361 8191",
    "sg:postcode":"95827",
    "sg:province":"CA",
    "sg:tags":[
        "stone",
        "flooring",
        "hardwood",
        "marble-natural",
        "tile-contractors",
        "granite",
        "glass-block"
    ],
    "sg:website":"www.cortopassitile.com",
    "wof:name":"Cortopassi Tile & Stone",
    "wof:placetype":"venue"
},
  "geometry": {"coordinates":[-121.322642,38.576311],"type":"Point"}
}