{
  "type": "Feature",
  "properties": {
    "addr:full":"425 N Hale Ave Escondido CA 92029",
    "addr:housenumber":"425",
    "addr:postcode":"92029",
    "addr:street":"N Hale Ave",
    "iso:country":"US",
    "sg:address":"425 N Hale Ave",
    "sg:city":"Escondido",
    "sg:classifiers":[
        {
            "category":"Building & Trades",
            "subcategory":"Construction",
            "type":"Services"
        }
    ],
    "sg:phone":"+1 760 737 9393",
    "sg:postcode":"92029",
    "sg:province":"CA",
    "sg:tags":[
        "maker",
        "cabinet"
    ],
    "wof:name":"Door's & Cabinet's By Archie",
    "wof:placetype":"venue"
},
  "geometry": {"coordinates":[-117.10226299999999,33.118769],"type":"Point"}
}