{
  "type": "Feature",
  "properties": {
    "addr:full":"10608 Lonon Ave Bakersfield CA 93312",
    "addr:housenumber":"10608",
    "addr:postcode":"93312",
    "addr:street":"Lonon Ave",
    "iso:country":"US",
    "sg:address":"10608 Lonon Ave",
    "sg:city":"Bakersfield",
    "sg:classifiers":[
        {
            "category":"Building & Trades",
            "subcategory":"Construction",
            "type":"Services"
        }
    ],
    "sg:phone":"+1 661 589 6502",
    "sg:postcode":"93312",
    "sg:province":"CA",
    "sg:tags":[
        "weather",
        "stripping",
        "contractor"
    ],
    "wof:name":"R C Enterprises Weather Strip",
    "wof:placetype":"venue"
},
  "geometry": {"coordinates":[-119.121967,35.39292],"type":"Point"}
}