{
  "type": "Feature",
  "properties": {
    "addr:full":"11914 Ventura Blvd Studio City CA 91604",
    "addr:housenumber":"11914",
    "addr:postcode":"91604",
    "addr:street":"Ventura Blvd",
    "iso:country":"US",
    "sg:address":"11914 Ventura Blvd",
    "sg:city":"Studio City",
    "sg:classifiers":[
        {
            "category":"Shopping",
            "subcategory":"Pharmacy",
            "type":"Retail Goods"
        }
    ],
    "sg:phone":"+1 818 761 1400",
    "sg:postcode":"91604",
    "sg:province":"CA",
    "sg:tags":[
        "drugstore"
    ],
    "wof:name":"Toluca Pharmacy",
    "wof:placetype":"venue"
},
  "geometry": {"coordinates":[-118.39145600000001,34.142659],"type":"Point"}
}