{
  "type": "Feature",
  "properties": {
    "addr:full":"2120 Colorado Blvd Eagle Rock CA 90041",
    "addr:housenumber":"2120",
    "addr:postcode":"90041",
    "addr:street":"Colorado Blvd",
    "iso:country":"US",
    "sg:address":"2120 Colorado Blvd",
    "sg:city":"Eagle Rock",
    "sg:classifiers":[
        {
            "category":"Restaurant",
            "type":"Food & Drink"
        }
    ],
    "sg:postcode":"90041",
    "sg:province":"CA",
    "sg:tags":[
        "flavor",
        "local"
    ],
    "wof:name":"Meditation Water Garden",
    "wof:placetype":"venue"
},
  "geometry": {"coordinates":[-118.212886,34.13909],"type":"Point"}
}