{
  "type": "Feature",
  "properties": {
    "iso:country":"US",
    "sg:address":"3300 Broadway St",
    "sg:city":"Eureka",
    "sg:classifiers":[
        {
            "category":"Food & Beverages",
            "subcategory":"Candy",
            "type":"Retail Goods"
        }
    ],
    "sg:phone":"+1 707 442 6259",
    "sg:postcode":"95501",
    "sg:province":"CA",
    "sg:tags":[
        "confectionery"
    ],
    "wof:name":"Candy Tyme",
    "wof:placetype":"venue"
},
  "geometry": {"coordinates":[-124.18653500000001,40.779651],"type":"Point"}
}