{
  "type": "Feature",
  "properties": {
    "iso:country":"US",
    "sg:address":"13367 Yosemite Blvd",
    "sg:city":"Waterford",
    "sg:classifiers":[
        {
            "category":"Professional",
            "subcategory":"Management & Consulting",
            "type":"Services"
        }
    ],
    "sg:phone":"+1 209 523 9050",
    "sg:postcode":"95386",
    "sg:province":"CA",
    "sg:tags":[
        "selling",
        "establishment",
        "direct"
    ],
    "wof:name":"Shaklee Distributor",
    "wof:placetype":"venue"
},
  "geometry": {"coordinates":[-120.75131,37.639785],"type":"Point"}
}