{
  "type": "Feature",
  "properties": {
    "addr:full":"963 Pacific Ave San Francisco CA 94133",
    "addr:housenumber":"963",
    "addr:postcode":"94133",
    "addr:street":"Pacific Ave",
    "iso:country":"US",
    "sg:address":"963 Pacific Ave",
    "sg:city":"San Francisco",
    "sg:classifiers":[
        {
            "category":"Manufacturing",
            "subcategory":"Apparel",
            "type":"Manufacturing & Wholesale Goods"
        }
    ],
    "sg:phone":"+1 415 989 9528",
    "sg:postcode":"94133",
    "sg:province":"CA",
    "sg:tags":[
        "sewing",
        "contractor"
    ],
    "wof:name":"Young Fung Co",
    "wof:placetype":"venue"
},
  "geometry": {"coordinates":[-122.410511,37.796443],"type":"Point"}
}