{
  "type": "Feature",
  "properties": {
    "addr:full":"430 Nutmeg St San Diego CA 92103",
    "addr:housenumber":"430",
    "addr:postcode":"92103",
    "addr:street":"Nutmeg St",
    "iso:country":"US",
    "sg:address":"430 Nutmeg St",
    "sg:city":"San Diego",
    "sg:classifiers":[
        {
            "category":"Health Services",
            "subcategory":"Health Practitioner",
            "type":"Services"
        }
    ],
    "sg:phone":"+1 619 291 7440",
    "sg:postcode":"92103",
    "sg:province":"CA",
    "sg:tags":[
        "psychologist"
    ],
    "wof:name":"D G Huffman PHD",
    "wof:placetype":"venue"
},
  "geometry": {"coordinates":[-117.160568,32.733547],"type":"Point"}
}