{
  "type": "Feature",
  "properties": {
    "addr:full":"500 McClay Rd Novato CA 94947",
    "addr:housenumber":"500",
    "addr:postcode":"94947",
    "addr:street":"Mcclay Rd",
    "iso:country":"US",
    "sg:address":"500 McClay Rd",
    "sg:city":"Novato",
    "sg:classifiers":[
        {
            "category":"Professional",
            "subcategory":"Computer Services",
            "type":"Services"
        }
    ],
    "sg:phone":"+1 415 892 5408",
    "sg:postcode":"94947",
    "sg:province":"CA",
    "sg:tags":[
        "consultant",
        "designer"
    ],
    "sg:website":"www.thistledewproductions.com",
    "wof:name":"Personal Tech Support",
    "wof:placetype":"venue"
},
  "geometry": {"coordinates":[-122.598215,38.095968],"type":"Point"}
}