{
  "type": "Feature",
  "properties": {
    "iso:country":"US",
    "sg:address":"614 14th St",
    "sg:city":"Oakland",
    "sg:classifiers":[
        {
            "category":"Building & Trades",
            "subcategory":"Locksmith",
            "type":"Services"
        }
    ],
    "sg:phone":"+1 800 294 8181",
    "sg:postcode":"94612",
    "sg:province":"CA",
    "sg:tags":[
        "lock"
    ],
    "wof:name":"USALocksmith.com",
    "wof:placetype":"venue"
},
  "geometry": {"coordinates":[-122.275133,37.805877],"type":"Point"}
}