{
  "type": "Feature",
  "properties": {
    "addr:full":"26926 Cherry Hills Blvd Sun City CA 92586",
    "addr:housenumber":"26926",
    "addr:postcode":"92586",
    "addr:street":"Cherry Hills Blvd",
    "iso:country":"US",
    "sg:address":"26926 Cherry Hills Blvd",
    "sg:city":"Sun City",
    "sg:classifiers":[
        {
            "category":"Health Services",
            "subcategory":"Doctor",
            "type":"Services"
        }
    ],
    "sg:phone":"+1 951 246 1433",
    "sg:postcode":"92586",
    "sg:province":"CA",
    "sg:tags":[
        "medical",
        "imaging"
    ],
    "wof:name":"Open Mri Of Sun City",
    "wof:placetype":"venue"
},
  "geometry": {"coordinates":[-117.19169599999999,33.71032],"type":"Point"}
}