{
  "type": "Feature",
  "properties": {
    "addr:full":"365 W Garvey Ave Monterey Park CA 91754",
    "addr:housenumber":"365",
    "addr:postcode":"91754",
    "addr:street":"W Garvey Ave",
    "iso:country":"US",
    "sg:address":"365 W Garvey Ave",
    "sg:city":"Monterey Park",
    "sg:classifiers":[
        {
            "category":"Travel",
            "subcategory":"Travel Agent",
            "type":"Entertainment"
        }
    ],
    "sg:phone":"+1 626 307 0399",
    "sg:postcode":"91754",
    "sg:province":"CA",
    "sg:tags":[
        "operator",
        "tour"
    ],
    "wof:name":"Melody Tours",
    "wof:placetype":"venue"
},
  "geometry": {"coordinates":[-118.126704,34.062602],"type":"Point"}
}