{
  "type": "Feature",
  "properties": {
    "addr:full":"10150 Aldea Ave Northridge CA 91325",
    "addr:housenumber":"10150",
    "addr:postcode":"91325",
    "addr:street":"Aldea Ave",
    "iso:country":"US",
    "sg:address":"10150 Aldea Ave",
    "sg:city":"Northridge",
    "sg:classifiers":[
        {
            "category":"Professional",
            "type":"Services"
        }
    ],
    "sg:phone":"+1 818 886 3995",
    "sg:postcode":"91325",
    "sg:province":"CA",
    "wof:name":"Richard D Mainwarring",
    "wof:placetype":"venue"
},
  "geometry": {"coordinates":[-118.508842,34.255951],"type":"Point"}
}