{
  "type": "Feature",
  "properties": {
    "iso:country":"US",
    "sg:address":"1030 E Palm Ave",
    "sg:city":"Orange",
    "sg:classifiers":[
        {
            "category":"Manufacturing",
            "subcategory":"Retail Goods",
            "type":"Manufacturing & Wholesale Goods"
        }
    ],
    "sg:phone":"+1 714 744 8913",
    "sg:postcode":"92866",
    "sg:province":"CA",
    "sg:tags":[
        "marking",
        "devices",
        "mfg"
    ],
    "wof:name":"Coast Rbr Stamp Manufactoring",
    "wof:placetype":"venue"
},
  "geometry": {"coordinates":[-117.842543,33.791387],"type":"Point"}
}