{
  "type": "Feature",
  "properties": {
    "iso:country":"US",
    "sg:address":"2331 W Tahoe St",
    "sg:city":"Caruthers",
    "sg:classifiers":[
        {
            "category":"Personal",
            "subcategory":"Beauty Salon",
            "type":"Services"
        }
    ],
    "sg:phone":"+1 559 864 1520",
    "sg:postcode":"93609",
    "sg:province":"CA",
    "wof:name":"Clip-N-Cut Hair Salon",
    "wof:placetype":"venue"
},
  "geometry": {"coordinates":[-119.833074,36.542281],"type":"Point"}
}