{
  "type": "Feature",
  "properties": {
    "addr:full":"29150 S Lake Shore Dr Agoura Hills CA 91301",
    "addr:housenumber":"29150",
    "addr:postcode":"91301",
    "addr:street":"S Lake Shore Dr",
    "iso:country":"US",
    "sg:address":"29150 S Lake Shore Dr",
    "sg:city":"Agoura Hills",
    "sg:classifiers":[
        {
            "category":"Communications",
            "subcategory":"Film & Video Production",
            "type":"Services"
        }
    ],
    "sg:phone":"+1 818 991 4434",
    "sg:postcode":"91301",
    "sg:province":"CA",
    "sg:tags":[
        "motion",
        "picture",
        "studio",
        "producer"
    ],
    "wof:name":"Malibu Lake Productions",
    "wof:placetype":"venue"
},
  "geometry": {"coordinates":[-118.7569,34.106285],"type":"Point"}
}