{
  "type": "Feature",
  "properties": {
    "addr:full":"9 Littlewood Dr Piedmont CA 94611",
    "addr:housenumber":"9",
    "addr:postcode":"94611",
    "addr:street":"Littlewood Dr",
    "iso:country":"US",
    "sg:address":"9 Littlewood Dr",
    "sg:city":"Piedmont",
    "sg:classifiers":[
        {
            "category":"Banks & Credit Unions",
            "subcategory":"Investment Brokerage",
            "type":"Services"
        }
    ],
    "sg:phone":"+1 510 655 0279",
    "sg:postcode":"94611",
    "sg:province":"CA",
    "sg:tags":[
        "consultant",
        "planning",
        "financial"
    ],
    "wof:name":"Arellano & Butler",
    "wof:placetype":"venue"
},
  "geometry": {"coordinates":[-122.221785,37.82379],"type":"Point"}
}