{
  "type": "Feature",
  "properties": {
    "addr:full":"1054 Shary Cir Concord CA 94518",
    "addr:housenumber":"1054",
    "addr:postcode":"94518",
    "addr:street":"Shary Cir",
    "iso:country":"US",
    "sg:address":"1054 Shary Cir",
    "sg:city":"Concord",
    "sg:classifiers":[
        {
            "category":"Building & Trades",
            "subcategory":"Construction",
            "type":"Services"
        }
    ],
    "sg:phone":"+1 925 459 0260",
    "sg:postcode":"94518",
    "sg:province":"CA",
    "sg:tags":[
        "maintenance",
        "contractor"
    ],
    "wof:name":"MSW Maintenance Svc",
    "wof:placetype":"venue"
},
  "geometry": {"coordinates":[-122.030739,37.95327],"type":"Point"}
}