{
  "type": "Feature",
  "properties": {
    "iso:country":"US",
    "sg:address":"4341 Opal Ave",
    "sg:city":"Cypress",
    "sg:classifiers":[
        {
            "category":"Banks & Credit Unions",
            "subcategory":"Investment Brokerage",
            "type":"Services"
        }
    ],
    "sg:phone":"+1 714 595 1330",
    "sg:postcode":"90630",
    "sg:province":"CA",
    "wof:name":"Capital Research & Investments",
    "wof:placetype":"venue"
},
  "geometry": {"coordinates":[-118.056907,33.840065],"type":"Point"}
}