{
  "type": "Feature",
  "properties": {
    "iso:country":"US",
    "sg:address":"3673 Mallard Dr",
    "sg:city":"Benicia",
    "sg:classifiers":[
        {
            "category":"Building & Trades",
            "subcategory":"Equipment Rental",
            "type":"Services"
        }
    ],
    "sg:phone":"+1 707 748 1990",
    "sg:postcode":"94510",
    "sg:province":"CA",
    "sg:tags":[
        "yard"
    ],
    "wof:name":"Ahern Rentals",
    "wof:placetype":"venue"
},
  "geometry": {"coordinates":[-122.126086,38.067832],"type":"Point"}
}