{
  "type": "Feature",
  "properties": {
    "addr:full":"2511 S Winchester Blvd Campbell CA 95008",
    "addr:housenumber":"2511",
    "addr:postcode":"95008",
    "addr:street":"S Winchester Blvd",
    "iso:country":"US",
    "sg:address":"2511 S Winchester Blvd",
    "sg:city":"Campbell",
    "sg:classifiers":[
        {
            "category":"Education",
            "subcategory":"Special Training",
            "type":"Public Place"
        }
    ],
    "sg:phone":"+1 408 374 6284",
    "sg:postcode":"95008",
    "sg:province":"CA",
    "sg:tags":[
        "tutoring"
    ],
    "sg:website":"www.mathnasium.com/campbell",
    "wof:name":"Mathnasium",
    "wof:placetype":"venue"
},
  "geometry": {"coordinates":[-121.949787,37.278083],"type":"Point"}
}