{
  "type": "Feature",
  "properties": {
    "addr:full":"1352 W 13th St Merced CA 95341",
    "addr:housenumber":"1352",
    "addr:postcode":"95341",
    "addr:street":"W 13Th St",
    "iso:country":"US",
    "sg:address":"1352 W 13th St",
    "sg:city":"Merced",
    "sg:phone":"+1 209 723 5636",
    "sg:postcode":"95341",
    "sg:province":"CA",
    "wof:name":"La Morenita Restaurant",
    "wof:placetype":"venue"
},
  "geometry": {"coordinates":[-120.498255,37.30174],"type":"Point"}
}