{
  "type": "Feature",
  "properties": {
    "addr:full":"2191 Oregon Ave Long Beach CA 90806",
    "addr:housenumber":"2191",
    "addr:postcode":"90806",
    "addr:street":"Oregon Ave",
    "iso:country":"US",
    "sg:address":"2191 Oregon Ave",
    "sg:city":"Long Beach",
    "sg:classifiers":[
        {
            "category":"Shopping",
            "subcategory":"Jewelry",
            "type":"Retail Goods"
        },
        {
            "category":"Shopping",
            "subcategory":"Florist",
            "type":"Retail Goods"
        }
    ],
    "sg:phone":"+1 800 556 7717",
    "sg:postcode":"90806",
    "sg:province":"CA",
    "sg:website":"www.kwcreativedesigns.com",
    "wof:name":"KW Creative Designs",
    "wof:placetype":"venue"
},
  "geometry": {"coordinates":[-118.20195,33.796971],"type":"Point"}
}