{
  "type": "Feature",
  "properties": {
    "iso:country":"US",
    "sg:address":"Crissy Field Center 1199 East Beach, Presidio",
    "sg:city":"San Francisco",
    "sg:classifiers":[
        {
            "category":"Coffee & Tea",
            "type":"Food & Drink"
        },
        {
            "category":"Food & Beverages",
            "subcategory":"Bakery",
            "type":"Retail Goods"
        }
    ],
    "sg:phone":"+1 415 561 7756",
    "sg:postcode":"94129",
    "sg:province":"CA",
    "sg:tags":[
        "sandwich"
    ],
    "sg:website":"www.parksconservancy.org/our-wor...",
    "wof:name":"Crissy Field Center Cafe",
    "wof:placetype":"venue"
},
  "geometry": {"coordinates":[-122.449208,37.805836],"type":"Point"}
}