{
  "type": "Feature",
  "properties": {
    "iso:country":"US",
    "sg:address":"25 Pacifica Ste 5330",
    "sg:city":"Irvine",
    "sg:classifiers":[
        {
            "category":"Professional",
            "type":"Services"
        },
        {
            "category":"Personal",
            "type":"Services"
        }
    ],
    "sg:phone":"+1 949 500 6122",
    "sg:postcode":"92618",
    "sg:province":"CA",
    "sg:tags":[
        "chef",
        "caterer"
    ],
    "sg:website":"www.2sharpknives.com",
    "wof:name":"2 sharp knives",
    "wof:placetype":"venue"
},
  "geometry": {"coordinates":[-117.74985599999999,33.651298],"type":"Point"}
}