{
  "type": "Feature",
  "properties": {
    "iso:country":"US",
    "sg:address":"3868 E Main St",
    "sg:city":"Ventura",
    "sg:classifiers":[
        {
            "category":"Restaurant",
            "type":"Food & Drink"
        }
    ],
    "sg:phone":"+1 805 656 4571",
    "sg:postcode":"93003",
    "sg:province":"CA",
    "sg:tags":[
        "out"
    ],
    "wof:name":"Evita's Mexican Cafe",
    "wof:placetype":"venue"
},
  "geometry": {"coordinates":[-119.239428,34.263441],"type":"Point"}
}