{
  "type": "Feature",
  "properties": {
    "addr:full":"19700 Bloomfield Ave Cerritos CA 90703",
    "addr:housenumber":"19700",
    "addr:postcode":"ca 90703",
    "addr:street":"Bloomfield Ave",
    "iso:country":"US",
    "sg:address":"19700 Bloomfield Ave",
    "sg:city":"Cerritos",
    "sg:classifiers":[
        {
            "category":"Sports & Exercise",
            "subcategory":"Tennis Court",
            "type":"Entertainment"
        }
    ],
    "sg:phone":"+1 562 402 7667",
    "sg:postcode":"90703",
    "sg:province":"CA",
    "wof:name":"Miller Rusty Tennis Academy",
    "wof:placetype":"venue"
},
  "geometry": {"coordinates":[-118.06300400000001,33.851501],"type":"Point"}
}