{
  "type": "Feature",
  "properties": {
    "addr:full":"275 Magnolia Ave Larkspur CA 94939",
    "addr:housenumber":"275",
    "addr:postcode":"94939",
    "addr:street":"Magnolia Ave",
    "iso:country":"US",
    "sg:address":"275 Magnolia Ave",
    "sg:city":"Larkspur",
    "sg:classifiers":[
        {
            "category":"Real Estate",
            "subcategory":"Architect",
            "type":"Services"
        }
    ],
    "sg:phone":"+1 415 924 1211",
    "sg:postcode":"94939",
    "sg:province":"CA",
    "wof:name":"Martin Bielik",
    "wof:placetype":"venue"
},
  "geometry": {"coordinates":[-122.536057,37.932779],"type":"Point"}
}