{
  "type": "Feature",
  "properties": {
    "iso:country":"US",
    "sg:address":"5320 Eagan Ct",
    "sg:city":"Rohnert Park",
    "sg:classifiers":[
        {
            "category":"Utilities",
            "subcategory":"Telephone",
            "type":"Services"
        }
    ],
    "sg:phone":"+1 707 584 3790",
    "sg:postcode":"94928",
    "sg:province":"CA",
    "sg:tags":[
        "communications"
    ],
    "wof:name":"Global Phone Solutions",
    "wof:placetype":"venue"
},
  "geometry": {"coordinates":[-122.68880900000001,38.359674],"type":"Point"}
}