{
  "type": "Feature",
  "properties": {
    "addr:full":"2890 de la Cruz Blvd Santa Clara CA 95050",
    "addr:housenumber":"2890",
    "addr:postcode":"95050",
    "addr:street":"De La Cruz Blvd",
    "iso:country":"US",
    "sg:address":"2890 de la Cruz Blvd",
    "sg:city":"Santa Clara",
    "sg:classifiers":[
        {
            "category":"Manufacturing",
            "subcategory":"Chemicals & Compounds",
            "type":"Manufacturing & Wholesale Goods"
        }
    ],
    "sg:phone":"+1 408 289 0482",
    "sg:postcode":"95050",
    "sg:province":"CA",
    "sg:tags":[
        "mfg"
    ],
    "wof:name":"FMC Corporation",
    "wof:placetype":"venue"
},
  "geometry": {"coordinates":[-121.943275,37.371896],"type":"Point"}
}