{
  "type": "Feature",
  "properties": {
    "addr:full":"2468 Woodberry Ave Hemet CA 92544",
    "addr:housenumber":"2468",
    "addr:postcode":"92544",
    "addr:street":"Woodberry Ave",
    "iso:country":"US",
    "sg:address":"2468 Woodberry Ave",
    "sg:city":"Hemet",
    "sg:classifiers":[
        {
            "category":"Professional",
            "type":"Services"
        }
    ],
    "sg:phone":"+1 951 658 4600",
    "sg:postcode":"92544",
    "sg:province":"CA",
    "sg:tags":[
        "establishment"
    ],
    "wof:name":"Preferred Professional Care",
    "wof:placetype":"venue"
},
  "geometry": {"coordinates":[-116.94566399999999,33.752096],"type":"Point"}
}