{
  "type": "Feature",
  "properties": {
    "iso:country":"US",
    "sg:address":"6715 Hollywood Blvd",
    "sg:city":"Los Angeles",
    "sg:classifiers":[
        {
            "category":"Personal",
            "type":"Services"
        }
    ],
    "sg:phone":"+1 323 462 8172",
    "sg:postcode":"90028",
    "sg:province":"CA",
    "sg:tags":[
        "sewing",
        "alteration"
    ],
    "wof:name":"Cipriano Custom Tailors",
    "wof:placetype":"venue"
},
  "geometry": {"coordinates":[-118.336998,34.101601],"type":"Point"}
}