{
  "type": "Feature",
  "properties": {
    "iso:country":"US",
    "sg:address":"2275 W Lincoln Ave",
    "sg:city":"Anaheim",
    "sg:classifiers":[
        {
            "category":"Place Of Worship",
            "type":"Public Place"
        },
        {
            "category":"Government",
            "subcategory":"Post Office",
            "type":"Public Place"
        },
        {
            "category":"Organizations",
            "subcategory":"Religious Organization",
            "type":"Services"
        }
    ],
    "sg:phone":"+1 714 491 8007",
    "sg:postcode":"92801",
    "sg:province":"CA",
    "sg:tags":[
        "alliance",
        "churches-christian",
        "missionary",
        "church"
    ],
    "wof:name":"Vietnamese District",
    "wof:placetype":"venue"
},
  "geometry": {"coordinates":[-117.96199799999999,33.832401],"type":"Point"}
}