{
  "type": "Feature",
  "properties": {
    "addr:full":"1090 Eugenia Pl Carpinteria CA 93013",
    "addr:housenumber":"1090",
    "addr:postcode":"93013",
    "addr:street":"Eugenia Pl",
    "iso:country":"US",
    "sg:address":"1090 Eugenia Pl",
    "sg:city":"Carpinteria",
    "sg:classifiers":[
        {
            "category":"Retail",
            "subcategory":"Auto Repair",
            "type":"Services"
        }
    ],
    "sg:phone":"+1 805 566 6672",
    "sg:postcode":"93013",
    "sg:province":"CA",
    "sg:tags":[
        "automobile",
        "restoration",
        "classic"
    ],
    "wof:name":"Noble Engineering",
    "wof:placetype":"venue"
},
  "geometry": {"coordinates":[-119.516575,34.398913],"type":"Point"}
}