{
  "type": "Feature",
  "properties": {
    "iso:country":"US",
    "sg:address":"21650 W Manning Ave",
    "sg:city":"San Joaquin",
    "sg:classifiers":[
        {
            "category":"Education",
            "subcategory":"School",
            "type":"Public Place"
        }
    ],
    "sg:phone":"+1 559 693 2904",
    "sg:postcode":"93660",
    "sg:province":"CA",
    "wof:name":"San Joaquin Headstart Homebase",
    "wof:placetype":"venue"
},
  "geometry": {"coordinates":[-120.18058499999999,36.603528],"type":"Point"}
}