{
  "type": "Feature",
  "properties": {
    "addr:full":"3470 E Florida Ave Hemet CA 92544",
    "addr:housenumber":"3470",
    "addr:postcode":"92544",
    "addr:street":"E Florida Ave",
    "iso:country":"US",
    "sg:address":"3470 E Florida Ave",
    "sg:city":"Hemet",
    "sg:classifiers":[
        {
            "category":"Retail",
            "subcategory":"Car Wash",
            "type":"Services"
        }
    ],
    "sg:phone":"+1 951 765 9866",
    "sg:postcode":"92544",
    "sg:province":"CA",
    "sg:tags":[
        "polishing",
        "washing"
    ],
    "wof:name":"Sunrise City Corp",
    "wof:placetype":"venue"
},
  "geometry": {"coordinates":[-116.934259,33.747798],"type":"Point"}
}