{
  "type": "Feature",
  "properties": {
    "iso:country":"US",
    "sg:address":"8835 Swasey Dr",
    "sg:city":"Redding",
    "sg:classifiers":[
        {
            "category":"Education",
            "subcategory":"School",
            "type":"Public Place"
        }
    ],
    "sg:phone":"+1 530 243 0561",
    "sg:postcode":"96001",
    "sg:province":"CA",
    "sg:tags":[
        "elementary"
    ],
    "wof:name":"Grant Elementary School District",
    "wof:placetype":"venue"
},
  "geometry": {"coordinates":[-122.47371200000001,40.540884],"type":"Point"}
}