{
  "type": "Feature",
  "properties": {
    "addr:full":"6301 Quarry Rd Spring Valley CA 91977",
    "addr:housenumber":"6301",
    "addr:postcode":"91977",
    "addr:street":"Quarry Rd",
    "iso:country":"US",
    "sg:address":"6301 Quarry Rd",
    "sg:city":"Spring Valley",
    "sg:classifiers":[
        {
            "category":"Wholesale",
            "subcategory":"Scrap",
            "type":"Manufacturing & Wholesale Goods"
        }
    ],
    "sg:phone":"+1 619 475 1005",
    "sg:postcode":"91977",
    "sg:province":"CA",
    "sg:tags":[
        "material"
    ],
    "wof:name":"Sweetwater Auto Wrecking",
    "wof:placetype":"venue"
},
  "geometry": {"coordinates":[-117.006373,32.701091],"type":"Point"}
}