{
  "type": "Feature",
  "properties": {
    "iso:country":"US",
    "sg:address":"10465 E Stockton Blvd",
    "sg:city":"Elk Grove",
    "sg:classifiers":[
        {
            "category":"Bars & Pubs",
            "type":"Food & Drink"
        }
    ],
    "sg:phone":"+1 916 685 1020",
    "sg:postcode":"95624",
    "sg:province":"CA",
    "sg:tags":[
        "lounge",
        "cocktail"
    ],
    "wof:name":"Murphy's Saloon",
    "wof:placetype":"venue"
},
  "geometry": {"coordinates":[-121.364884,38.379854],"type":"Point"}
}