{
  "type": "Feature",
  "properties": {
    "addr:full":"29385 Rancho California Rd Temecula CA 92591",
    "addr:housenumber":"29385",
    "addr:postcode":"92591",
    "addr:street":"Rancho California Rd",
    "iso:country":"US",
    "sg:address":"29385 Rancho California Rd",
    "sg:city":"Temecula",
    "sg:classifiers":[
        {
            "category":"Social Services",
            "type":"Services"
        }
    ],
    "sg:phone":"+1 951 693 1641",
    "sg:postcode":"92591",
    "sg:province":"CA",
    "sg:tags":[
        "organization",
        "welfare"
    ],
    "wof:name":"Lutheran Social Svc",
    "wof:placetype":"venue"
},
  "geometry": {"coordinates":[-117.14543,33.504962],"type":"Point"}
}