{
  "type": "Feature",
  "properties": {
    "addr:full":"865 E Foothill Blvd Rialto CA 92376",
    "addr:housenumber":"865",
    "addr:postcode":"92376",
    "addr:street":"E Foothill Blvd",
    "iso:country":"US",
    "sg:address":"865 E Foothill Blvd",
    "sg:city":"Rialto",
    "sg:classifiers":[
        {
            "category":"Wholesale",
            "subcategory":"Jewelry",
            "type":"Manufacturing & Wholesale Goods"
        }
    ],
    "sg:phone":"+1 909 875 1555",
    "sg:postcode":"92376",
    "sg:province":"CA",
    "sg:tags":[
        "platinum",
        "silver",
        "gold"
    ],
    "wof:name":"Pawn Stop",
    "wof:placetype":"venue"
},
  "geometry": {"coordinates":[-117.355279,34.106721],"type":"Point"}
}