{
  "type": "Feature",
  "properties": {
    "addr:full":"1741 W Katella Ave Anaheim CA 92804",
    "addr:housenumber":"1741",
    "addr:postcode":"92804",
    "addr:street":"W Katella Ave",
    "iso:country":"US",
    "sg:address":"1741 W Katella Ave",
    "sg:city":"Anaheim",
    "sg:classifiers":[
        {
            "category":"Education",
            "subcategory":"Special Training",
            "type":"Public Place"
        }
    ],
    "sg:phone":"+1 714 776 8405",
    "sg:postcode":"92804",
    "sg:province":"CA",
    "sg:tags":[
        "school",
        "specialty"
    ],
    "wof:name":"Coast Health Educational Centers Inc",
    "wof:placetype":"venue"
},
  "geometry": {"coordinates":[-117.94314,33.803337],"type":"Point"}
}