{
  "type": "Feature",
  "properties": {
    "iso:country":"US",
    "sg:address":"1537 Franklin St Ste 208",
    "sg:city":"San Francisco",
    "sg:classifiers":[
        {
            "category":"Professional",
            "subcategory":"Lawyer & Legal Services",
            "type":"Services"
        }
    ],
    "sg:phone":"+1 415 928 1441",
    "sg:postcode":"94109",
    "sg:province":"CA",
    "sg:tags":[
        "divorce",
        "law",
        "family"
    ],
    "wof:name":"Penzotti L Bailey",
    "wof:placetype":"venue"
},
  "geometry": {"coordinates":[-122.42399500000001,37.788797],"type":"Point"}
}