{
  "type": "Feature",
  "properties": {
    "iso:country":"US",
    "sg:address":"Pereira and W Peltason",
    "sg:city":"Irvine",
    "sg:classifiers":[
        {
            "category":"Shopping",
            "subcategory":"Bicycles & Sporting Goods",
            "type":"Retail Goods"
        },
        {
            "category":"Sports & Exercise",
            "subcategory":"Bicycle Rental",
            "type":"Entertainment"
        }
    ],
    "sg:phone":"+1 949 824 3123",
    "sg:postcode":"92612",
    "sg:province":"CA",
    "sg:tags":[
        "bike"
    ],
    "sg:website":"bikereligion.com",
    "wof:name":"Bike Religion",
    "wof:placetype":"venue"
},
  "geometry": {"coordinates":[-117.842842,33.650085],"type":"Point"}
}