{
  "type": "Feature",
  "properties": {
    "iso:country":"US",
    "sg:address":"333 Cobalt Way",
    "sg:city":"Sunnyvale",
    "sg:classifiers":[
        {
            "category":"Wholesale",
            "subcategory":"Metals & Minerals",
            "type":"Manufacturing & Wholesale Goods"
        }
    ],
    "sg:phone":"+1 408 885 9473",
    "sg:postcode":"94085",
    "sg:province":"CA",
    "sg:tags":[
        "wire"
    ],
    "wof:name":"Cable Source",
    "wof:placetype":"venue"
},
  "geometry": {"coordinates":[-121.995271,37.377786],"type":"Point"}
}