{
  "type": "Feature",
  "properties": {
    "addr:full":"50 E Highland Ave Sierra Madre CA 91024",
    "addr:housenumber":"50",
    "addr:postcode":"91024",
    "addr:street":"E Highland Ave",
    "iso:country":"US",
    "sg:address":"50 E Highland Ave",
    "sg:city":"Sierra Madre",
    "sg:classifiers":[
        {
            "category":"Farming",
            "subcategory":"Livestock Farm",
            "type":"Manufacturing & Wholesale Goods"
        }
    ],
    "sg:phone":"+1 626 836 3446",
    "sg:postcode":"91024",
    "sg:province":"CA",
    "sg:tags":[
        "animal",
        "general"
    ],
    "wof:name":"Packer Ranch Co",
    "wof:placetype":"venue"
},
  "geometry": {"coordinates":[-118.051873,34.164339],"type":"Point"}
}