{
  "type": "Feature",
  "properties": {
    "iso:country":"US",
    "sg:address":"3304 State St",
    "sg:city":"Santa Barbara",
    "sg:classifiers":[
        {
            "category":"Banks & Credit Unions",
            "subcategory":"Bank",
            "type":"Services"
        }
    ],
    "sg:phone":"+1 805 563 6400",
    "sg:postcode":"93105",
    "sg:province":"CA",
    "sg:tags":[
        "state"
    ],
    "wof:name":"First Bank & Trust",
    "wof:placetype":"venue"
},
  "geometry": {"coordinates":[-119.736463,34.440481],"type":"Point"}
}