{
  "type": "Feature",
  "properties": {
    "iso:country":"US",
    "sg:address":"16508 S Berendo Avenue",
    "sg:city":"Gardena",
    "sg:classifiers":[
        {
            "category":"Personal",
            "subcategory":"Nail Salon",
            "type":"Services"
        }
    ],
    "sg:phone":"+1 310 538 1966",
    "sg:postcode":"90247",
    "sg:province":"CA",
    "wof:name":"Combs Full Service Salon",
    "wof:placetype":"venue"
},
  "geometry": {"coordinates":[-118.293547,33.881209],"type":"Point"}
}