{
  "type": "Feature",
  "properties": {
    "iso:country":"US",
    "sg:address":"1322 2nd St",
    "sg:city":"Pacific Plsds",
    "sg:classifiers":[
        {
            "category":"Recreation",
            "type":"Entertainment"
        }
    ],
    "sg:phone":"+1 310 459 1051",
    "sg:postcode":"90266",
    "sg:province":"CA",
    "sg:tags":[
        "information",
        "sport"
    ],
    "wof:name":"Baseball Fervor",
    "wof:placetype":"venue"
},
  "geometry": {"coordinates":[-118.39145600000001,33.880009],"type":"Point"}
}