{
  "type": "Feature",
  "properties": {
    "addr:full":"1520 W El Camino Avenue Located in Bel Air plaza on Truxel and W. El Camino ave. Sacramento CA 95833",
    "addr:housenumber":"1520",
    "addr:postcode":"95833",
    "addr:street":"W El Camino Avenue Located In Bel;El Camino Ave.",
    "iso:country":"US",
    "sg:address":"1520 W El Camino Avenue Located in Bel Air plaza on Truxel and W. El Camino ave.",
    "sg:city":"Sacramento",
    "sg:classifiers":[
        {
            "category":"Health Services",
            "subcategory":"Dentist",
            "type":"Services"
        }
    ],
    "sg:phone":"+1 916 921 6051",
    "sg:postcode":"95833",
    "sg:province":"CA",
    "wof:name":"Cheng Wayne Y DDS",
    "wof:placetype":"venue"
},
  "geometry": {"coordinates":[-121.495639,38.612853],"type":"Point"}
}