{
  "type": "Feature",
  "properties": {
    "addr:full":"1000 Burnett Ave Ste 445 Concord CA 94520",
    "addr:housenumber":"1000",
    "addr:postcode":"94520",
    "addr:street":"Burnett Ave Ste 445",
    "iso:country":"US",
    "sg:address":"1000 Burnett Ave Ste 445",
    "sg:city":"Concord",
    "sg:classifiers":[
        {
            "category":"Professional",
            "subcategory":"Engineering",
            "type":"Services"
        }
    ],
    "sg:phone":"+1 925 677 7439",
    "sg:postcode":"94520",
    "sg:province":"CA",
    "sg:tags":[
        "engineer",
        "integration",
        "system"
    ],
    "sg:website":"http://www.rimkus.com",
    "wof:name":"Rimkus Consulting Group, Inc.",
    "wof:placetype":"venue"
},
  "geometry": {"coordinates":[-122.061592,37.975761],"type":"Point"}
}