{
  "type": "Feature",
  "properties": {
    "addr:full":"4320 Atlantic Ave Long Beach CA 90807",
    "addr:housenumber":"4320",
    "addr:postcode":"90807",
    "addr:street":"Atlantic Ave",
    "iso:country":"US",
    "sg:address":"4320 Atlantic Ave",
    "sg:city":"Long Beach",
    "sg:classifiers":[
        {
            "category":"Personal",
            "type":"Services"
        },
        {
            "category":"Professional",
            "subcategory":"Employment Agencies",
            "type":"Services"
        }
    ],
    "sg:phone":"+1 562 426 4165",
    "sg:postcode":"90807",
    "sg:province":"CA",
    "sg:tags":[
        "welcoming",
        "newcomer",
        "for"
    ],
    "wof:name":"Hospitality Guild Ltd",
    "wof:placetype":"venue"
},
  "geometry": {"coordinates":[-118.184923,33.835256],"type":"Point"}
}