{
  "type": "Feature",
  "properties": {
    "addr:full":"1480 E Harvard Blvd Santa Paula CA 93060",
    "addr:housenumber":"1480",
    "addr:postcode":"93060",
    "addr:street":"E Harvard Blvd",
    "iso:country":"US",
    "sg:address":"1480 E Harvard Blvd",
    "sg:city":"Santa Paula",
    "sg:classifiers":[
        {
            "category":"Retail",
            "subcategory":"Auto Repair",
            "type":"Services"
        }
    ],
    "sg:phone":"+1 805 933 3199",
    "sg:postcode":"93060",
    "sg:province":"CA",
    "sg:tags":[
        "repairing",
        "automobile"
    ],
    "wof:name":"Tarango's Auto Diesel Repair",
    "wof:placetype":"venue"
},
  "geometry": {"coordinates":[-119.051697,34.355043],"type":"Point"}
}