{
  "type": "Feature",
  "properties": {
    "addr:full":"3130 5th Ave San Diego CA 92103",
    "addr:housenumber":"3130",
    "addr:postcode":"92103",
    "addr:street":"5Th Ave",
    "iso:country":"US",
    "sg:address":"3130 5th Ave",
    "sg:city":"San Diego",
    "sg:classifiers":[
        {
            "category":"Health Services",
            "subcategory":"Health Practitioner",
            "type":"Services"
        }
    ],
    "sg:phone":"+1 619 574 0924",
    "sg:postcode":"92103",
    "sg:province":"CA",
    "sg:tags":[
        "psychologist"
    ],
    "wof:name":"Tina L Buckner",
    "wof:placetype":"venue"
},
  "geometry": {"coordinates":[-117.16042400000001,32.738394],"type":"Point"}
}