{
  "type": "Feature",
  "properties": {
    "addr:full":"1770 Deavers Dr San Marcos CA 92069",
    "addr:housenumber":"1770",
    "addr:postcode":"92069",
    "addr:street":"Deavers Dr",
    "iso:country":"US",
    "sg:address":"1770 Deavers Dr",
    "sg:city":"San Marcos",
    "sg:classifiers":[
        {
            "category":"Restaurant",
            "type":"Food & Drink"
        }
    ],
    "sg:phone":"+1 760 738 5988",
    "sg:postcode":"92069",
    "sg:province":"CA",
    "wof:name":"Severson Group",
    "wof:placetype":"venue"
},
  "geometry": {"coordinates":[-117.11995,33.141219],"type":"Point"}
}