{
  "type": "Feature",
  "properties": {
    "iso:country":"US",
    "sg:address":"19852 Temescal Canyon Rd",
    "sg:city":"Corona",
    "sg:classifiers":[
        {
            "category":"Restaurant",
            "type":"Food & Drink"
        }
    ],
    "sg:phone":"+1 951 340 1647",
    "sg:postcode":"92881",
    "sg:province":"CA",
    "wof:name":"LA Esquina Del Sabor Mex Food",
    "wof:placetype":"venue"
},
  "geometry": {"coordinates":[-117.517418,33.831061],"type":"Point"}
}