{
  "type": "Feature",
  "properties": {
    "addr:full":"19852 Temescal Canyon Rd Corona CA 92881",
    "addr:housenumber":"19852",
    "addr:postcode":"92881",
    "addr:street":"Temescal Canyon Rd",
    "iso:country":"US",
    "sg:address":"19852 Temescal Canyon Rd",
    "sg:city":"Corona",
    "sg:classifiers":[
        {
            "category":"Restaurant",
            "type":"Food & Drink"
        }
    ],
    "sg:phone":"+1 951 340 1647",
    "sg:postcode":"92881",
    "sg:province":"CA",
    "wof:name":"LA Esquina Del Sabor Mex Food",
    "wof:placetype":"venue"
},
  "geometry": {"coordinates":[-117.51741800000001,33.831061],"type":"Point"}
}