{
  "type": "Feature",
  "properties": {
    "iso:country":"US",
    "sg:address":"2025 W Feemster Ave",
    "sg:city":"Visalia",
    "sg:classifiers":[
        {
            "category":"Real Estate",
            "subcategory":"Real Estate Services",
            "type":"Services"
        }
    ],
    "sg:phone":"+1 559 741 7270",
    "sg:postcode":"93277",
    "sg:province":"CA",
    "sg:tags":[
        "company",
        "title"
    ],
    "wof:name":"Financial Title Co",
    "wof:placetype":"venue"
},
  "geometry": {"coordinates":[-119.314911,36.317614],"type":"Point"}
}