{
  "type": "Feature",
  "properties": {
    "iso:country":"US",
    "sg:address":"239 Oak St",
    "sg:city":"Mountain View",
    "sg:classifiers":[
        {
            "category":"Health Services",
            "subcategory":"Clinic",
            "type":"Services"
        }
    ],
    "sg:phone":"+1 650 960 3468",
    "sg:postcode":"94041",
    "sg:province":"CA",
    "sg:tags":[
        "home"
    ],
    "wof:name":"Bill-Personal Attendant",
    "wof:placetype":"venue"
},
  "geometry": {"coordinates":[-122.082707,37.394336],"type":"Point"}
}