{
  "type": "Feature",
  "properties": {
    "iso:country":"US",
    "sg:address":"2001 Addison St",
    "sg:city":"Berkeley",
    "sg:classifiers":[
        {
            "category":"Manufacturing",
            "subcategory":"Buildings",
            "type":"Manufacturing & Wholesale Goods"
        }
    ],
    "sg:phone":"+1 510 486 1900",
    "sg:postcode":"94704",
    "sg:province":"CA",
    "sg:tags":[
        "home",
        "builder"
    ],
    "wof:name":"Constat Inc.",
    "wof:placetype":"venue"
},
  "geometry": {"coordinates":[-122.27063,37.870861],"type":"Point"}
}