{
  "type": "Feature",
  "properties": {
    "addr:full":"2466 Pardi Way Placerville CA 95667",
    "addr:housenumber":"2466",
    "addr:postcode":"95667",
    "addr:street":"Pardi Way",
    "iso:country":"US",
    "sg:address":"2466 Pardi Way",
    "sg:city":"Placerville",
    "sg:classifiers":[
        {
            "category":"Professional",
            "type":"Services"
        }
    ],
    "sg:phone":"+1 530 642 0888",
    "sg:postcode":"95667",
    "sg:province":"CA",
    "wof:name":"Traci L Lamorey-Yocom",
    "wof:placetype":"venue"
},
  "geometry": {"coordinates":[-120.79996199999999,38.720669],"type":"Point"}
}