{
  "type": "Feature",
  "properties": {
    "iso:country":"US",
    "sg:address":"200 Paul St",
    "sg:city":"San Francisco",
    "sg:classifiers":[
        {
            "category":"Utilities",
            "type":"Services"
        }
    ],
    "sg:phone":"+1 800 296 8915",
    "sg:postcode":"94124",
    "sg:province":"CA",
    "sg:tags":[
        "provider",
        "internet"
    ],
    "sg:website":"www.colocationamerica.com",
    "wof:name":"Colocation America",
    "wof:placetype":"venue"
},
  "geometry": {"coordinates":[-122.398607,37.723182],"type":"Point"}
}