{
  "type": "Feature",
  "properties": {
    "iso:country":"US",
    "sg:address":"1968 Williams St",
    "sg:city":"San Leandro",
    "sg:classifiers":[
        {
            "category":"Wholesale",
            "subcategory":"Home Furnishings",
            "type":"Manufacturing & Wholesale Goods"
        }
    ],
    "sg:phone":"+1 510 483 2500",
    "sg:postcode":"94577",
    "sg:province":"CA",
    "sg:tags":[
        "floor",
        "covering"
    ],
    "wof:name":"Direct Sales Floors",
    "wof:placetype":"venue"
},
  "geometry": {"coordinates":[-122.177661,37.710308],"type":"Point"}
}