{
  "type": "Feature",
  "properties": {
    "iso:country":"US",
    "sg:address":"15834 Main St",
    "sg:city":"La Puente",
    "sg:classifiers":[
        {
            "category":"Shopping",
            "subcategory":"Clothing, Apparel, & Fashions",
            "type":"Retail Goods"
        }
    ],
    "sg:phone":"+1 626 961 6000",
    "sg:postcode":"91744",
    "sg:province":"CA",
    "sg:tags":[
        "theatrical",
        "costume"
    ],
    "wof:name":"Dracula's Castle",
    "wof:placetype":"venue"
},
  "geometry": {"coordinates":[-117.95403399999999,34.020083],"type":"Point"}
}