{
  "type": "Feature",
  "properties": {
    "addr:full":"1330 S Bascom Ave San Jose CA 95128",
    "addr:housenumber":"1330",
    "addr:postcode":"95128",
    "addr:street":"S Bascom Ave",
    "iso:country":"US",
    "sg:address":"1330 S Bascom Ave",
    "sg:city":"San Jose",
    "sg:classifiers":[
        {
            "category":"Professional",
            "subcategory":"Lawyer & Legal Services",
            "type":"Services"
        }
    ],
    "sg:phone":"+1 408 292 0666",
    "sg:postcode":"95128",
    "sg:province":"CA",
    "sg:tags":[
        "naturalization",
        "immigration"
    ],
    "wof:name":"Lee & Assoc Law Offices",
    "wof:placetype":"venue"
},
  "geometry": {"coordinates":[-121.93168900000001,37.29931],"type":"Point"}
}