{
  "type": "Feature",
  "properties": {
    "iso:country":"US",
    "sg:address":"28 2nd St",
    "sg:city":"San Francisco",
    "sg:classifiers":[
        {
            "category":"Professional",
            "subcategory":"Engineering",
            "type":"Services"
        }
    ],
    "sg:phone":"+1 415 908 0555",
    "sg:postcode":"94105",
    "sg:province":"CA",
    "sg:tags":[
        "engineer"
    ],
    "wof:name":"Bello & Assoc Structural",
    "wof:placetype":"venue"
},
  "geometry": {"coordinates":[-122.40118699999999,37.789086],"type":"Point"}
}