{
  "type": "Feature",
  "properties": {
    "iso:country":"US",
    "sg:address":"4526 Azalia Dr",
    "sg:city":"Tarzana",
    "sg:classifiers":[
        {
            "category":"Building & Trades",
            "subcategory":"Equipment Rental",
            "type":"Services"
        }
    ],
    "sg:phone":"+1 818 269 4120",
    "sg:postcode":"91356",
    "sg:province":"CA",
    "sg:tags":[
        "yard",
        "leasing",
        "store"
    ],
    "wof:name":"Signature Leasing",
    "wof:placetype":"venue"
},
  "geometry": {"coordinates":[-118.53773700000001,34.153026],"type":"Point"}
}