{
  "type": "Feature",
  "properties": {
    "addr:full":"500 Lawrence Expy Ste C Sunnyvale CA 94086",
    "addr:housenumber":"500",
    "addr:postcode":"94086",
    "addr:street":"Lawrence Expy Ste C",
    "iso:country":"US",
    "sg:address":"500 Lawrence Expy Ste C",
    "sg:city":"Sunnyvale",
    "sg:classifiers":[
        {
            "category":"Restaurant",
            "type":"Food & Drink"
        }
    ],
    "sg:phone":"+1 408 736 2411",
    "sg:postcode":"94086",
    "sg:province":"CA",
    "sg:tags":[
        "middle",
        "mediterranean",
        "eastern"
    ],
    "sg:website":"www.falafelbite.com/",
    "wof:name":"Falafel Bite",
    "wof:placetype":"venue"
},
  "geometry": {"coordinates":[-121.994995,37.381676],"type":"Point"}
}