{
  "type": "Feature",
  "properties": {
    "iso:country":"US",
    "sg:address":"3435 Ocean Park Blvd",
    "sg:city":"Santa Monica",
    "sg:classifiers":[
        {
            "category":"Building & Trades",
            "subcategory":"Landscaping Services",
            "type":"Services"
        }
    ],
    "sg:phone":"+1 310 391 6136",
    "sg:postcode":"90405",
    "sg:province":"CA",
    "sg:tags":[
        "landscape",
        "contractor"
    ],
    "wof:name":"Artisan Landscape & Masonry",
    "wof:placetype":"venue"
},
  "geometry": {"coordinates":[-118.449147,34.022815],"type":"Point"}
}