{
  "type": "Feature",
  "properties": {
    "addr:full":"2736 N Pacific Ave Stockton CA 95204",
    "addr:housenumber":"2736",
    "addr:postcode":"95204",
    "addr:street":"N Pacific Ave",
    "iso:country":"US",
    "sg:address":"2736 N Pacific Ave",
    "sg:city":"Stockton",
    "sg:classifiers":[
        {
            "category":"Professional",
            "subcategory":"Business Services",
            "type":"Services"
        }
    ],
    "sg:phone":"+1 209 469 3500",
    "sg:postcode":"95204",
    "sg:province":"CA",
    "sg:tags":[
        "drafting"
    ],
    "wof:name":"Winkelman Drafting Svc",
    "wof:placetype":"venue"
},
  "geometry": {"coordinates":[-121.30315299999999,37.975414],"type":"Point"}
}