{
  "type": "Feature",
  "properties": {
    "addr:full":"3237 Idaho Pl Costa Mesa CA 92626",
    "addr:housenumber":"3237",
    "addr:postcode":"92626",
    "addr:street":"Idaho Pl",
    "iso:country":"US",
    "sg:address":"3237 Idaho Pl",
    "sg:city":"Costa Mesa",
    "sg:classifiers":[
        {
            "category":"Manufacturing",
            "subcategory":"Printing",
            "type":"Manufacturing & Wholesale Goods"
        }
    ],
    "sg:phone":"+1 714 434 9500",
    "sg:postcode":"92626",
    "sg:province":"CA",
    "sg:tags":[
        "information",
        "medical",
        "publisher"
    ],
    "wof:name":"Biomedical Market Newsletter",
    "wof:placetype":"venue"
},
  "geometry": {"coordinates":[-117.929687,33.688335],"type":"Point"}
}