{
  "type": "Feature",
  "properties": {
    "iso:country":"US",
    "sg:address":"120 Hawthorne Avenue, Suite 103",
    "sg:city":"Palo Alto",
    "sg:classifiers":[
        {
            "category":"Professional",
            "subcategory":"Computer Services",
            "type":"Services"
        }
    ],
    "sg:postcode":"94301",
    "sg:province":"CA",
    "sg:website":"http://www.questbridge.org/",
    "wof:name":"QuestBridge",
    "wof:placetype":"venue"
},
  "geometry": {"coordinates":[-122.167272,37.446141],"type":"Point"}
}