{
  "type": "Feature",
  "properties": {
    "iso:country":"US",
    "sg:address":"1650 California St",
    "sg:city":"San Francisco",
    "sg:classifiers":[
        {
            "category":"Professional",
            "subcategory":"Accounting & Tax Preparation",
            "type":"Services"
        }
    ],
    "sg:phone":"+1 415 776 1856",
    "sg:postcode":"94109",
    "sg:province":"CA",
    "sg:tags":[
        "accountant"
    ],
    "wof:name":"Brian C Proses, CPA",
    "wof:placetype":"venue"
},
  "geometry": {"coordinates":[-122.42153500000001,37.790616],"type":"Point"}
}