{
  "type": "Feature",
  "properties": {
    "iso:country":"US",
    "sg:address":"326 Towne Ave",
    "sg:city":"Los Angeles",
    "sg:classifiers":[
        {
            "category":"Health Services",
            "subcategory":"Clinic",
            "type":"Services"
        }
    ],
    "sg:phone":"+1 213 368 0909",
    "sg:postcode":"90021",
    "sg:province":"CA",
    "sg:tags":[
        "home",
        "care"
    ],
    "wof:name":"Soho Skin Care",
    "wof:placetype":"venue"
},
  "geometry": {"coordinates":[-118.240417,34.044721],"type":"Point"}
}