{
  "type": "Feature",
  "properties": {
    "iso:country":"US",
    "sg:address":"13010 Lake Wildwood Dr",
    "sg:city":"Penn Valley",
    "sg:classifiers":[
        {
            "category":"Travel",
            "subcategory":"Hotels & Motels",
            "type":"Entertainment"
        }
    ],
    "sg:phone":"+1 530 432 8669",
    "sg:postcode":"95946",
    "sg:province":"CA",
    "sg:tags":[
        "operation"
    ],
    "wof:name":"Inn At Nesika Beach",
    "wof:placetype":"venue"
},
  "geometry": {"coordinates":[-121.189584,39.236363],"type":"Point"}
}