{
  "type": "Feature",
  "properties": {
    "iso:country":"US",
    "sg:address":"225 E Mount Diablo Ave",
    "sg:city":"Tracy",
    "sg:classifiers":[
        {
            "category":"Manufacturing",
            "subcategory":"Tools & Machinery",
            "type":"Manufacturing & Wholesale Goods"
        }
    ],
    "sg:phone":"+1 209 832 8952",
    "sg:postcode":"95376",
    "sg:province":"CA",
    "sg:tags":[
        "computer",
        "electronic",
        "mfg"
    ],
    "wof:name":"Dell Computer",
    "wof:placetype":"venue"
},
  "geometry": {"coordinates":[-121.421657,37.729275],"type":"Point"}
}