{
  "type": "Feature",
  "properties": {
    "addr:full":"12731 Towne Center Drive Suite H Cerritos CA 90703",
    "addr:housenumber":"12731",
    "addr:postcode":"ca 90703",
    "addr:street":"Towne Center Drive Suite H",
    "iso:country":"US",
    "sg:address":"12731 Towne Center Drive Suite H",
    "sg:city":"Cerritos",
    "sg:classifiers":[
        {
            "category":"Ice Cream",
            "type":"Food & Drink"
        }
    ],
    "sg:phone":"+1 562 809 8438",
    "sg:postcode":"90703",
    "sg:province":"CA",
    "sg:tags":[
        "frozen",
        "yogurt"
    ],
    "sg:website":"www.thegoldenspoon.com",
    "wof:name":"Golden Spoon Frozen Yogurt",
    "wof:placetype":"venue"
},
  "geometry": {"coordinates":[-118.060997,33.870098],"type":"Point"}
}