{
  "type": "Feature",
  "properties": {
    "addr:full":"2820 Stormes Ave Oroville CA 95966",
    "addr:housenumber":"2820",
    "addr:postcode":"95966",
    "addr:street":"Stormes Ave",
    "iso:country":"US",
    "sg:address":"2820 Stormes Ave",
    "sg:city":"Oroville",
    "sg:classifiers":[
        {
            "category":"Restaurant",
            "type":"Food & Drink"
        }
    ],
    "sg:phone":"+1 530 534 5661",
    "sg:postcode":"95966",
    "sg:province":"CA",
    "sg:tags":[
        "eating"
    ],
    "wof:name":"Great Walrus Kettle Korn",
    "wof:placetype":"venue"
},
  "geometry": {"coordinates":[-121.542098,39.512413],"type":"Point"}
}