{
  "type": "Feature",
  "properties": {
    "addr:full":"6648 Smith Rd Oakdale CA 95361",
    "addr:housenumber":"6648",
    "addr:postcode":"95361",
    "addr:street":"Smith Rd",
    "iso:country":"US",
    "sg:address":"6648 Smith Rd",
    "sg:city":"Oakdale",
    "sg:classifiers":[
        {
            "category":"Building & Trades",
            "subcategory":"Construction",
            "type":"Services"
        }
    ],
    "sg:phone":"+1 209 847 0539",
    "sg:postcode":"95361",
    "sg:province":"CA",
    "sg:tags":[
        "excavating",
        "contractor"
    ],
    "wof:name":"Dirt Works",
    "wof:placetype":"venue"
},
  "geometry": {"coordinates":[-120.81210799999999,37.730682],"type":"Point"}
}