{
  "type": "Feature",
  "properties": {
    "addr:full":"219 South St Hollister CA 95023",
    "addr:housenumber":"219",
    "addr:postcode":"hollister ca 95023",
    "addr:street":"South St",
    "iso:country":"US",
    "sg:address":"219 South St",
    "sg:city":"Hollister",
    "sg:classifiers":[
        {
            "category":"Personal",
            "subcategory":"Beauty Salon",
            "type":"Services"
        }
    ],
    "sg:phone":"+1 831 638 9873",
    "sg:postcode":"95023",
    "sg:province":"CA",
    "wof:name":"Luminous",
    "wof:placetype":"venue"
},
  "geometry": {"coordinates":[-121.401573,36.848339],"type":"Point"}
}