{
  "type": "Feature",
  "properties": {
    "iso:country":"US",
    "sg:address":"24300 Town Center Dr Ste 105",
    "sg:city":"Valencia",
    "sg:classifiers":[
        {
            "category":"Food & Beverages",
            "subcategory":"Liquor & Beverages",
            "type":"Retail Goods"
        }
    ],
    "sg:phone":"+1 661 254 9300",
    "sg:postcode":"91355",
    "sg:province":"CA",
    "sg:tags":[
        "beer",
        "spirit",
        "wine"
    ],
    "wof:name":"Valencia Wine Company Inc",
    "wof:placetype":"venue"
},
  "geometry": {"coordinates":[-118.560467,34.417085],"type":"Point"}
}