{
  "type": "Feature",
  "properties": {
    "addr:full":"2280 Micro Pl Escondido CA 92029",
    "addr:housenumber":"2280",
    "addr:postcode":"92029",
    "addr:street":"Micro Pl",
    "iso:country":"US",
    "sg:address":"2280 Micro Pl",
    "sg:city":"Escondido",
    "sg:classifiers":[
        {
            "category":"Building & Trades",
            "subcategory":"Electrical",
            "type":"Services"
        }
    ],
    "sg:phone":"+1 760 489 1611",
    "sg:postcode":"92029",
    "sg:province":"CA",
    "sg:tags":[
        "communication",
        "system",
        "contractor"
    ],
    "wof:name":"Ficom Corporation",
    "wof:placetype":"venue"
},
  "geometry": {"coordinates":[-117.126549,33.130911],"type":"Point"}
}