{
  "type": "Feature",
  "properties": {
    "iso:country":"US",
    "sg:address":"5395 Ruffin Road",
    "sg:city":"San Diego",
    "sg:classifiers":[
        {
            "category":"Shopping",
            "subcategory":"Pharmacy",
            "type":"Retail Goods"
        }
    ],
    "sg:phone":"+1 858 277 8884",
    "sg:postcode":"92123",
    "sg:province":"CA",
    "sg:tags":[
        "drugstore"
    ],
    "wof:name":"San Diego Compounding Pharmacy United Drugs",
    "wof:placetype":"venue"
},
  "geometry": {"coordinates":[-117.126662,32.832778],"type":"Point"}
}