{
  "type": "Feature",
  "properties": {
    "addr:full":"6391 Atlantic Avenue Bell CA 90201",
    "addr:housenumber":"6391",
    "addr:postcode":"90201",
    "addr:street":"Atlantic Avenue",
    "iso:country":"US",
    "sg:address":"6391 Atlantic Avenue",
    "sg:city":"Bell",
    "sg:classifiers":[
        {
            "category":"Juice Bar",
            "subcategory":"None",
            "type":"Food & Drink"
        }
    ],
    "sg:phone":"+1 323 773 2622",
    "sg:postcode":"90201",
    "sg:province":"CA",
    "sg:tags":[
        "smoothy"
    ],
    "wof:name":"Boba Loca",
    "wof:placetype":"venue"
},
  "geometry": {"coordinates":[-118.187054,33.978147],"type":"Point"}
}