{
  "type": "Feature",
  "properties": {
    "iso:country":"US",
    "sg:address":"619 Linden Ave",
    "sg:city":"Carpinteria",
    "sg:classifiers":[
        {
            "category":"Shopping",
            "subcategory":"Gifts & Souvenirs",
            "type":"Retail Goods"
        }
    ],
    "sg:phone":"+1 805 684 4882",
    "sg:postcode":"93013",
    "sg:province":"CA",
    "sg:tags":[
        "persona"
    ],
    "wof:name":"House of Fun Casa Debroma",
    "wof:placetype":"venue"
},
  "geometry": {"coordinates":[-119.520883,34.396948],"type":"Point"}
}