{
  "type": "Feature",
  "properties": {
    "addr:full":"6466 Moraga Ave Piedmont CA 94611",
    "addr:housenumber":"6466",
    "addr:postcode":"94611",
    "addr:street":"Moraga Ave",
    "iso:country":"US",
    "sg:address":"6466 Moraga Ave",
    "sg:city":"Piedmont",
    "sg:classifiers":[
        {
            "category":"Shopping",
            "subcategory":"Stationery & Office Supplies",
            "type":"Retail Goods"
        }
    ],
    "sg:phone":"+1 510 339 9850",
    "sg:postcode":"94611",
    "sg:province":"CA",
    "sg:tags":[
        "stationer"
    ],
    "wof:name":"Paperclip Montclair Village",
    "wof:placetype":"venue"
},
  "geometry": {"coordinates":[-122.210624,37.826497],"type":"Point"}
}