{
  "type": "Feature",
  "properties": {
    "addr:full":"5800 Madison Ave Ste K Sacramento CA 95841",
    "addr:housenumber":"5800",
    "addr:postcode":"95841",
    "addr:street":"Madison Ave Ste K",
    "iso:country":"US",
    "sg:address":"5800 Madison Ave Ste K",
    "sg:city":"Sacramento",
    "sg:phone":"+1 916 348 1880",
    "sg:postcode":"95841",
    "sg:province":"CA",
    "wof:name":"Thai Hut",
    "wof:placetype":"venue"
},
  "geometry": {"coordinates":[-121.328343,38.660584],"type":"Point"}
}