{
  "type": "Feature",
  "properties": {
    "addr:full":"23033 Huber Ave Torrance CA 90501",
    "addr:housenumber":"23033",
    "addr:postcode":"90501",
    "addr:street":"Huber Ave",
    "iso:country":"US",
    "sg:address":"23033 Huber Ave",
    "sg:city":"Torrance",
    "sg:classifiers":[
        {
            "category":"Professional",
            "subcategory":"Business Services",
            "type":"Services"
        }
    ],
    "sg:phone":"+1 310 325 6750",
    "sg:postcode":"90501",
    "sg:province":"CA",
    "sg:tags":[
        "transportation",
        "freight",
        "arrangement"
    ],
    "wof:name":"Blaydes-Shalkowski Ginger Cust",
    "wof:placetype":"venue"
},
  "geometry": {"coordinates":[-118.310936,33.816398],"type":"Point"}
}