{
  "type": "Feature",
  "properties": {
    "iso:country":"US",
    "sg:address":"120 Kearny St",
    "sg:city":"San Francisco",
    "sg:classifiers":[
        {
            "category":"Banks & Credit Unions",
            "subcategory":"Bank",
            "type":"Services"
        }
    ],
    "sg:phone":"+1 650 321 0500",
    "sg:postcode":"94108",
    "sg:province":"CA",
    "wof:name":"Presidio Bank",
    "wof:placetype":"venue"
},
  "geometry": {"coordinates":[-122.403555,37.789209],"type":"Point"}
}