{
  "type": "Feature",
  "properties": {
    "addr:full":"Omni Los Angeles Hotel 930 Wilshire Boulevard Los Angeles CA 90017",
    "addr:housenumber":"930",
    "addr:postcode":"90017",
    "addr:street":"Wilshire Boulevard",
    "iso:country":"US",
    "sg:address":"Omni Los Angeles Hotel 930 Wilshire Boulevard",
    "sg:city":"Los Angeles",
    "sg:classifiers":[
        {
            "category":"Shopping",
            "subcategory":"Gifts & Souvenirs",
            "type":"Retail Goods"
        }
    ],
    "sg:phone":"+1 213 622 5067",
    "sg:postcode":"90017",
    "sg:province":"CA",
    "sg:tags":[
        "flower"
    ],
    "wof:name":"Dave's Flowers & Gift Baskets",
    "wof:placetype":"venue"
},
  "geometry": {"coordinates":[-118.259829,34.050108],"type":"Point"}
}