{
  "type": "Feature",
  "properties": {
    "addr:full":"1541 S Patton Ave San Pedro CA 90731",
    "addr:housenumber":"1541",
    "addr:postcode":"90731",
    "addr:street":"S Patton Ave",
    "iso:country":"US",
    "sg:address":"1541 S Patton Ave",
    "sg:city":"San Pedro",
    "sg:classifiers":[
        {
            "category":"Manufacturing",
            "subcategory":"Printing",
            "type":"Manufacturing & Wholesale Goods"
        }
    ],
    "sg:phone":"+1 310 547 2656",
    "sg:postcode":"90731",
    "sg:province":"CA",
    "sg:tags":[
        "publisher"
    ],
    "wof:name":"Mad Dog Publishing",
    "wof:placetype":"venue"
},
  "geometry": {"coordinates":[-118.305668,33.730119],"type":"Point"}
}