{
  "type": "Feature",
  "properties": {
    "iso:country":"US",
    "sg:address":"7863 Cll Juela",
    "sg:city":"La Jolla",
    "sg:classifiers":[
        {
            "category":"Real Estate",
            "subcategory":"Real Estate Agent",
            "type":"Services"
        }
    ],
    "sg:phone":"+1 858 459 0601",
    "sg:postcode":"92037",
    "sg:province":"CA",
    "sg:tags":[
        "broker"
    ],
    "sg:website":"www.lajollarealtyexperts.com",
    "wof:name":"Realty Experts Shores",
    "wof:placetype":"venue"
},
  "geometry": {"coordinates":[-117.254951,32.849973],"type":"Point"}
}