{
  "type": "Feature",
  "properties": {
    "addr:full":"8479 Melrose Ave West Hollywood CA 90069",
    "addr:housenumber":"8479",
    "addr:postcode":"90069",
    "addr:street":"Melrose Ave",
    "iso:country":"US",
    "sg:address":"8479 Melrose Ave",
    "sg:city":"West Hollywood",
    "sg:classifiers":[
        {
            "category":"Restaurant",
            "type":"Food & Drink"
        }
    ],
    "sg:phone":"+1 323 782 1104",
    "sg:postcode":"90069",
    "sg:province":"CA",
    "sg:tags":[
        "brasserie",
        "french"
    ],
    "sg:website":"www.commecarestaurant.com",
    "wof:name":"Comme Ca",
    "wof:placetype":"venue"
},
  "geometry": {"coordinates":[-118.375896,34.082538],"type":"Point"}
}