{
  "type": "Feature",
  "properties": {
    "iso:country":"US",
    "sg:address":"482 W Birch Ct",
    "sg:city":"Hanford",
    "sg:classifiers":[
        {
            "category":"Building & Trades",
            "subcategory":"Construction",
            "type":"Services"
        }
    ],
    "sg:phone":"+1 559 582 5865",
    "sg:postcode":"93230",
    "sg:province":"CA",
    "sg:tags":[
        "dry wall",
        "contractor"
    ],
    "wof:name":"Jack Dean Drywall",
    "wof:placetype":"venue"
},
  "geometry": {"coordinates":[-119.65173799999999,36.355665],"type":"Point"}
}