{
  "type": "Feature",
  "properties": {
    "iso:country":"US",
    "sg:address":"51335 Harrison St",
    "sg:city":"Coachella",
    "sg:classifiers":[
        {
            "category":"Shopping",
            "subcategory":"Clothing, Apparel, & Fashions",
            "type":"Retail Goods"
        }
    ],
    "sg:phone":"+1 760 398 9801",
    "sg:postcode":"92236",
    "sg:province":"CA",
    "sg:tags":[
        "infant",
        "wear"
    ],
    "wof:name":"Kids In Style",
    "wof:placetype":"venue"
},
  "geometry": {"coordinates":[-116.181676,33.678059],"type":"Point"}
}