{
  "type": "Feature",
  "properties": {
    "addr:full":"2933 el Nido Dr Altadena CA 91001",
    "addr:housenumber":"2933",
    "addr:postcode":"91001",
    "addr:street":"El Nido Dr",
    "iso:country":"US",
    "sg:address":"2933 el Nido Dr",
    "sg:city":"Altadena",
    "sg:classifiers":[
        {
            "category":"Social Services",
            "type":"Services"
        }
    ],
    "sg:phone":"+1 626 798 0853",
    "sg:postcode":"91001",
    "sg:province":"CA",
    "wof:name":"Sycamores School",
    "wof:placetype":"venue"
},
  "geometry": {"coordinates":[-118.164714,34.196264],"type":"Point"}
}