{
  "type": "Feature",
  "properties": {
    "addr:full":"219 S Martin Dr Zephyr Cove CA 89448",
    "addr:housenumber":"219",
    "addr:postcode":"89448",
    "addr:street":"S Martin Dr",
    "iso:country":"US",
    "sg:address":"219 S Martin Dr",
    "sg:city":"Zephyr Cove",
    "sg:classifiers":[
        {
            "category":"Building & Trades",
            "subcategory":"Construction",
            "type":"Services"
        }
    ],
    "sg:phone":"+1 775 588 6647",
    "sg:postcode":"89448",
    "sg:province":"CA",
    "sg:tags":[
        "dry wall",
        "contractor"
    ],
    "wof:name":"Doug Maselli Drywall",
    "wof:placetype":"venue"
},
  "geometry": {"coordinates":[-119.953468,38.999833],"type":"Point"}
}