{
  "type": "Feature",
  "properties": {
    "iso:country":"US",
    "sg:address":"2908 Foothill Blvd",
    "sg:city":"La Crescenta",
    "sg:classifiers":[
        {
            "category":"Personal",
            "subcategory":"Beauty Salon",
            "type":"Services"
        }
    ],
    "sg:phone":"+1 818 957 5350",
    "sg:postcode":"91214",
    "sg:province":"CA",
    "sg:tags":[
        "manicuring"
    ],
    "wof:name":"Lily's Nail Salon",
    "wof:placetype":"venue"
},
  "geometry": {"coordinates":[-118.243093,34.226004],"type":"Point"}
}