{
  "type": "Feature",
  "properties": {
    "addr:full":"4401 Twain Ave San Diego CA 92120",
    "addr:housenumber":"4401",
    "addr:postcode":"92120",
    "addr:street":"Twain Ave",
    "iso:country":"US",
    "sg:address":"4401 Twain Ave",
    "sg:city":"San Diego",
    "sg:classifiers":[
        {
            "category":"Wholesale",
            "subcategory":"Electrical",
            "type":"Manufacturing & Wholesale Goods"
        }
    ],
    "sg:phone":"+1 619 282 9884",
    "sg:postcode":"92120",
    "sg:province":"CA",
    "sg:tags":[
        "control",
        "security",
        "system"
    ],
    "wof:name":"Electro Specialty Systems",
    "wof:placetype":"venue"
},
  "geometry": {"coordinates":[-117.100763,32.784945],"type":"Point"}
}