{
  "type": "Feature",
  "properties": {
    "addr:full":"1102 E Santa Clara St San Jose CA 95116",
    "addr:housenumber":"1102",
    "addr:postcode":"95116",
    "addr:street":"E Santa Clara St",
    "iso:country":"US",
    "sg:address":"1102 E Santa Clara St",
    "sg:city":"San Jose",
    "sg:classifiers":[
        {
            "category":"Education",
            "subcategory":"Library",
            "type":"Public Place"
        }
    ],
    "sg:phone":"+1 408 808 3075",
    "sg:postcode":"95116",
    "sg:province":"CA",
    "sg:website":"www.sjlibrary.org",
    "wof:name":"East San Jose Carnegie Branch Library",
    "wof:placetype":"venue"
},
  "geometry": {"coordinates":[-121.868636,37.346575],"type":"Point"}
}