{
  "type": "Feature",
  "properties": {
    "addr:full":"640 N San Jacinto St Hemet CA 92543",
    "addr:housenumber":"640",
    "addr:postcode":"92543",
    "addr:street":"N San Jacinto St",
    "iso:country":"US",
    "sg:address":"640 N San Jacinto St",
    "sg:city":"Hemet",
    "sg:classifiers":[
        {
            "category":"Health Services",
            "subcategory":"Doctor",
            "type":"Services"
        }
    ],
    "sg:phone":"+1 951 765 3174",
    "sg:postcode":"92543",
    "sg:province":"CA",
    "sg:tags":[
        "dentist"
    ],
    "wof:name":"Area Dental Ctr",
    "wof:placetype":"venue"
},
  "geometry": {"coordinates":[-116.958617,33.754907],"type":"Point"}
}