{
  "type": "Feature",
  "properties": {
    "addr:full":"315 S Mission Dr San Gabriel CA 91776",
    "addr:housenumber":"315",
    "addr:postcode":"91776",
    "addr:street":"S Mission Dr",
    "iso:country":"US",
    "sg:address":"315 S Mission Dr",
    "sg:city":"San Gabriel",
    "sg:classifiers":[
        {
            "category":"Education",
            "subcategory":"Special Training",
            "type":"Public Place"
        }
    ],
    "sg:phone":"+1 626 289 8944",
    "sg:postcode":"91776",
    "sg:province":"CA",
    "sg:tags":[
        "instruction",
        "driving"
    ],
    "sg:website":"www.study-at-home.com",
    "wof:name":"Calif Driver Improvement Inc",
    "wof:placetype":"venue"
},
  "geometry": {"coordinates":[-118.108549,34.097274],"type":"Point"}
}