{
  "type": "Feature",
  "properties": {
    "iso:country":"US",
    "sg:address":"894 Palm Ave",
    "sg:city":"Imperial Beach",
    "sg:classifiers":[
        {
            "category":"Health Services",
            "subcategory":"Optometrist",
            "type":"Services"
        },
        {
            "category":"Shopping",
            "subcategory":"Optician",
            "type":"Retail Goods"
        }
    ],
    "sg:phone":"+1 619 424 9333",
    "sg:postcode":"91932",
    "sg:province":"CA",
    "sg:tags":[
        "eyewear"
    ],
    "wof:name":"Hanono Helfon Dr",
    "wof:placetype":"venue"
},
  "geometry": {"coordinates":[-117.113998,32.584],"type":"Point"}
}