{
  "type": "Feature",
  "properties": {
    "iso:country":"US",
    "sg:address":"1350 S el Camino Real",
    "sg:city":"Encinitas",
    "sg:classifiers":[
        {
            "category":"Health Services",
            "subcategory":"Nursing And Care Facility",
            "type":"Services"
        }
    ],
    "sg:phone":"+1 760 479 1818",
    "sg:postcode":"92024",
    "sg:province":"CA",
    "sg:tags":[
        "home",
        "convalescent"
    ],
    "sg:website":"www.somerfordplace.com",
    "wof:name":"Somerford Place",
    "wof:placetype":"venue"
},
  "geometry": {"coordinates":[-117.2565,33.033785],"type":"Point"}
}