{
  "type": "Feature",
  "properties": {
    "iso:country":"US",
    "sg:address":"1617 Pacific Ave",
    "sg:city":"Oxnard",
    "sg:classifiers":[
        {
            "category":"Organizations",
            "subcategory":"Religious Organization",
            "type":"Services"
        }
    ],
    "sg:phone":"+1 805 483 5648",
    "sg:postcode":"93033",
    "sg:province":"CA",
    "sg:tags":[
        "church"
    ],
    "wof:name":"Church Of Jesus Christ-Oxnard",
    "wof:placetype":"venue"
},
  "geometry": {"coordinates":[-119.165221,34.184008],"type":"Point"}
}