{
  "type": "Feature",
  "properties": {
    "addr:full":"23944 County Road 98 Woodland CA 95695",
    "addr:housenumber":"23944",
    "addr:postcode":"95695",
    "addr:street":"County Road 98",
    "iso:country":"US",
    "sg:address":"23944 County Road 98",
    "sg:city":"Woodland",
    "sg:classifiers":[
        {
            "category":"Bars & Pubs",
            "type":"Food & Drink"
        },
        {
            "category":"Restaurant",
            "type":"Food & Drink"
        }
    ],
    "sg:phone":"+1 530 668 0207",
    "sg:postcode":"95695",
    "sg:province":"CA",
    "sg:tags":[
        "brew",
        "grill"
    ],
    "wof:name":"Plainfield Station",
    "wof:placetype":"venue"
},
  "geometry": {"coordinates":[-121.803124,38.589994],"type":"Point"}
}