{
  "type": "Feature",
  "properties": {
    "iso:country":"US",
    "sg:address":"7006 Chimineas Ave",
    "sg:city":"Reseda",
    "sg:classifiers":[
        {
            "category":"Building & Trades",
            "subcategory":"Construction",
            "type":"Services"
        }
    ],
    "sg:phone":"+1 818 577 3924",
    "sg:postcode":"91335",
    "sg:province":"CA",
    "sg:tags":[
        "handyman"
    ],
    "wof:name":"Lens Repair",
    "wof:placetype":"venue"
},
  "geometry": {"coordinates":[-118.52842099999999,34.197602],"type":"Point"}
}