{
  "type": "Feature",
  "properties": {
    "addr:full":"1430 Martin Luther King Jr Way Berkeley CA 94709",
    "addr:housenumber":"1430",
    "addr:postcode":"94709",
    "addr:street":"Martin Luther King Jr Way",
    "iso:country":"US",
    "sg:address":"1430 Martin Luther King Jr Way",
    "sg:city":"Berkeley",
    "sg:classifiers":[
        {
            "category":"Health Services",
            "subcategory":"Podiatrist",
            "type":"Services"
        }
    ],
    "sg:phone":"+1 510 528 2308",
    "sg:postcode":"94709",
    "sg:province":"CA",
    "sg:tags":[
        "equipment",
        "supply"
    ],
    "wof:name":"Care Plus Inc",
    "wof:placetype":"venue"
},
  "geometry": {"coordinates":[-122.274038,37.880881],"type":"Point"}
}