{
  "type": "Feature",
  "properties": {
    "iso:country":"US",
    "sg:address":"800 Portola Dr Ste D",
    "sg:city":"Monterey",
    "sg:classifiers":[
        {
            "category":"Professional",
            "subcategory":"Accounting & Tax Preparation",
            "type":"Services"
        }
    ],
    "sg:phone":"+1 831 392 0584",
    "sg:postcode":"93940",
    "sg:province":"CA",
    "sg:tags":[
        "return",
        "preparation-business"
    ],
    "wof:name":"Mc Collester Tax & Bus Svcs",
    "wof:placetype":"venue"
},
  "geometry": {"coordinates":[-121.85032699999999,36.599079],"type":"Point"}
}