{
  "type": "Feature",
  "properties": {
    "addr:full":"16 Yellowwood Way Irvine CA 92612",
    "addr:housenumber":"16",
    "addr:postcode":"92612",
    "addr:street":"Yellowwood Way",
    "iso:country":"US",
    "sg:address":"16 Yellowwood Way",
    "sg:city":"Irvine",
    "sg:classifiers":[
        {
            "category":"Retail",
            "subcategory":"Portrait Studio",
            "type":"Services"
        }
    ],
    "sg:phone":"+1 949 654 5873",
    "sg:postcode":"92612",
    "sg:province":"CA",
    "sg:tags":[
        "photographer"
    ],
    "wof:name":"A & M Photography & Video",
    "wof:placetype":"venue"
},
  "geometry": {"coordinates":[-117.822926,33.658587],"type":"Point"}
}