{
  "type": "Feature",
  "properties": {
    "addr:full":"12595 Hesperia Rd Victorville CA 92395",
    "addr:housenumber":"12595",
    "addr:postcode":"92395",
    "addr:street":"Hesperia Rd",
    "iso:country":"US",
    "sg:address":"12595 Hesperia Rd",
    "sg:city":"Victorville",
    "sg:classifiers":[
        {
            "category":"Health Services",
            "subcategory":"Optometrist",
            "type":"Services"
        }
    ],
    "sg:phone":"+1 760 245 5364",
    "sg:postcode":"92395",
    "sg:province":"CA",
    "wof:name":"Desert Optometry",
    "wof:placetype":"venue"
},
  "geometry": {"coordinates":[-117.290616,34.481813],"type":"Point"}
}