{
  "type": "Feature",
  "properties": {
    "addr:full":"7850 White Ln Bakersfield CA 93309",
    "addr:housenumber":"7850",
    "addr:postcode":"93309",
    "addr:street":"White Ln",
    "iso:country":"US",
    "sg:address":"7850 White Ln",
    "sg:city":"Bakersfield",
    "sg:classifiers":[
        {
            "category":"Professional",
            "subcategory":"Research",
            "type":"Services"
        }
    ],
    "sg:phone":"+1 661 837 2660",
    "sg:postcode":"93309",
    "sg:province":"CA",
    "sg:tags":[
        "environmental",
        "ecological"
    ],
    "wof:name":"Rap Services",
    "wof:placetype":"venue"
},
  "geometry": {"coordinates":[-119.08895800000001,35.31831],"type":"Point"}
}