{
  "type": "Feature",
  "properties": {
    "addr:full":"4382 W Shaw Ave Fresno CA 93722",
    "addr:housenumber":"4382",
    "addr:postcode":"93722",
    "addr:street":"W Shaw Ave",
    "iso:country":"US",
    "sg:address":"4382 W Shaw Ave",
    "sg:city":"Fresno",
    "sg:classifiers":[
        {
            "category":"Personal",
            "subcategory":"Beauty Salon",
            "type":"Services"
        }
    ],
    "sg:phone":"+1 559 275 4664",
    "sg:postcode":"93722",
    "sg:province":"CA",
    "wof:name":"Shear Stylez",
    "wof:placetype":"venue"
},
  "geometry": {"coordinates":[-119.87048299999999,36.808326],"type":"Point"}
}