{
  "type": "Feature",
  "properties": {
    "addr:full":"1370 Trancas St Napa CA 94558",
    "addr:housenumber":"1370",
    "addr:postcode":"94558",
    "addr:street":"Trancas St",
    "iso:country":"US",
    "sg:address":"1370 Trancas St",
    "sg:city":"Napa",
    "sg:classifiers":[
        {
            "category":"Professional",
            "subcategory":"Management & Consulting",
            "type":"Services"
        }
    ],
    "sg:phone":"+1 707 207 0477",
    "sg:postcode":"94558",
    "sg:province":"CA",
    "sg:tags":[
        "consultant",
        "medical"
    ],
    "wof:name":"M D Advisors",
    "wof:placetype":"venue"
},
  "geometry": {"coordinates":[-122.302325,38.322496],"type":"Point"}
}