{
  "type": "Feature",
  "properties": {
    "addr:full":"919 The Alameda Berkeley CA 94707",
    "addr:housenumber":"919",
    "addr:postcode":"94707",
    "addr:street":"The Alameda",
    "iso:country":"US",
    "sg:address":"919 The Alameda",
    "sg:city":"Berkeley",
    "sg:classifiers":[
        {
            "category":"Social Services",
            "type":"Services"
        }
    ],
    "sg:phone":"+1 510 527 2150",
    "sg:postcode":"94707",
    "sg:province":"CA",
    "sg:tags":[
        "stress",
        "management"
    ],
    "wof:name":"Linda Carlson",
    "wof:placetype":"venue"
},
  "geometry": {"coordinates":[-122.276938,37.890993],"type":"Point"}
}