{
  "type": "Feature",
  "properties": {
    "addr:full":"1001 Veterans Blvd Redwood City CA 94063",
    "addr:housenumber":"1001",
    "addr:postcode":"94063",
    "addr:street":"Veterans Blvd",
    "iso:country":"US",
    "sg:address":"1001 Veterans Blvd",
    "sg:city":"Redwood City",
    "sg:classifiers":[
        {
            "category":"Restaurant",
            "type":"Food & Drink"
        }
    ],
    "sg:phone":"+1 650 361 1230",
    "sg:postcode":"94063",
    "sg:province":"CA",
    "wof:name":"Carl's Jr",
    "wof:placetype":"venue"
},
  "geometry": {"coordinates":[-122.225928,37.489926],"type":"Point"}
}