{
  "type": "Feature",
  "properties": {
    "addr:full":"565 Thomas L Berkley Way Oakland CA 94612",
    "addr:housenumber":"565",
    "addr:postcode":"94612",
    "addr:street":"Thomas L Berkley Way",
    "iso:country":"US",
    "sg:address":"565 Thomas L Berkley Way",
    "sg:city":"Oakland",
    "sg:classifiers":[
        {
            "category":"Government",
            "subcategory":"Office",
            "type":"Public Place"
        }
    ],
    "sg:phone":"+1 510 893 5123",
    "sg:postcode":"94612",
    "sg:province":"CA",
    "sg:tags":[
        "smog",
        "check"
    ],
    "wof:name":"Autohouse Car Repair the",
    "wof:placetype":"venue"
},
  "geometry": {"coordinates":[-122.269997,37.809502],"type":"Point"}
}