{
  "type": "Feature",
  "properties": {
    "addr:full":"445 Bush Street San Francisco CA 94108",
    "addr:housenumber":"445",
    "addr:postcode":"94108",
    "addr:street":"Bush Street",
    "iso:country":"US",
    "sg:address":"445 Bush Street",
    "sg:city":"San Francisco",
    "sg:classifiers":[
        {
            "category":"Professional",
            "subcategory":"Lawyer & Legal Services",
            "type":"Services"
        }
    ],
    "sg:phone":"+1 415 861 2265",
    "sg:postcode":"94108",
    "sg:province":"CA",
    "wof:name":"Barron Nancy Atty",
    "wof:placetype":"venue"
},
  "geometry": {"coordinates":[-122.40494200000001,37.790661],"type":"Point"}
}