{
  "type": "Feature",
  "properties": {
    "addr:full":"3626 E Pacific Coast Hwy Long Beach CA 90804",
    "addr:housenumber":"3626",
    "addr:postcode":"90804",
    "addr:street":"E Pacific Coast Hwy",
    "iso:country":"US",
    "sg:address":"3626 E Pacific Coast Hwy",
    "sg:city":"Long Beach",
    "sg:classifiers":[
        {
            "category":"Real Estate",
            "subcategory":"Real Estate Agent",
            "type":"Services"
        }
    ],
    "sg:phone":"+1 562 597 0500",
    "sg:postcode":"90804",
    "sg:province":"CA",
    "wof:name":"Pacific Property Assets",
    "wof:placetype":"venue"
},
  "geometry": {"coordinates":[-118.148365,33.789759],"type":"Point"}
}