{
  "type": "Feature",
  "properties": {
    "iso:country":"US",
    "sg:address":"1445 Brooks St Ste K",
    "sg:city":"Ontario",
    "sg:classifiers":[
        {
            "category":"Manufacturing",
            "subcategory":"Tools & Machinery",
            "type":"Manufacturing & Wholesale Goods"
        }
    ],
    "sg:phone":"+1 909 988 2445",
    "sg:postcode":"91762",
    "sg:province":"CA",
    "sg:tags":[
        "die",
        "maker"
    ],
    "wof:name":"H B Tool & Die Co",
    "wof:placetype":"venue"
},
  "geometry": {"coordinates":[-117.67810900000001,34.061812],"type":"Point"}
}