{
  "type": "Feature",
  "properties": {
    "iso:country":"US",
    "sg:address":"136 S Central Ave",
    "sg:city":"Los Angeles",
    "sg:classifiers":[
        {
            "category":"Restaurant",
            "type":"Food & Drink"
        }
    ],
    "sg:phone":"+1 213 625 2228",
    "sg:postcode":"90012",
    "sg:province":"CA",
    "sg:tags":[
        "chinese"
    ],
    "wof:name":"Green Bamboo",
    "wof:placetype":"venue"
},
  "geometry": {"coordinates":[-118.238998,34.048599],"type":"Point"}
}