{
  "type": "Feature",
  "properties": {
    "addr:full":"204 N Victory Blvd Burbank CA 91502",
    "addr:housenumber":"204",
    "addr:postcode":"91502",
    "addr:street":"N Victory Blvd",
    "iso:country":"US",
    "sg:address":"204 N Victory Blvd",
    "sg:city":"Burbank",
    "sg:classifiers":[
        {
            "category":"Social Services",
            "type":"Services"
        },
        {
            "category":"Education",
            "subcategory":"Special Training",
            "type":"Public Place"
        }
    ],
    "sg:phone":"+1 818 842 4933",
    "sg:postcode":"91502",
    "sg:province":"CA",
    "wof:name":"Adult Basic Learning Envmt",
    "wof:placetype":"venue"
},
  "geometry": {"coordinates":[-118.31716400000001,34.174887],"type":"Point"}
}