{
  "type": "Feature",
  "properties": {
    "addr:full":"1168 Valley Quail Cir San Jose CA 95120",
    "addr:housenumber":"1168",
    "addr:postcode":"95120",
    "addr:street":"Valley Quail Cir",
    "iso:country":"US",
    "sg:address":"1168 Valley Quail Cir",
    "sg:city":"San Jose",
    "sg:classifiers":[
        {
            "category":"Manufacturing",
            "subcategory":"Electronics",
            "type":"Manufacturing & Wholesale Goods"
        }
    ],
    "sg:phone":"+1 408 554 1032",
    "sg:postcode":"95120",
    "sg:province":"CA",
    "sg:tags":[
        "system",
        "mfg"
    ],
    "wof:name":"Almaden Semiconductor Inc",
    "wof:placetype":"venue"
},
  "geometry": {"coordinates":[-121.849752,37.205657],"type":"Point"}
}