{
  "type": "Feature",
  "properties": {
    "addr:full":"33 W Mission St Santa Barbara CA 93101",
    "addr:housenumber":"33",
    "addr:postcode":"93101",
    "addr:street":"W Mission St",
    "iso:country":"US",
    "sg:address":"33 W Mission St",
    "sg:city":"Santa Barbara",
    "sg:classifiers":[
        {
            "category":"Professional",
            "subcategory":"Lawyer & Legal Services",
            "type":"Services"
        }
    ],
    "sg:phone":"+1 805 682 2600",
    "sg:postcode":"93101",
    "sg:province":"CA",
    "sg:tags":[
        "attorney"
    ],
    "wof:name":"Thomas A Johnson Law Offices",
    "wof:placetype":"venue"
},
  "geometry": {"coordinates":[-119.715459,34.43006],"type":"Point"}
}