{
  "type": "Feature",
  "properties": {
    "addr:full":"149 E Main St Grass Valley CA 95945",
    "addr:housenumber":"149",
    "addr:postcode":"95945",
    "addr:street":"E Main St",
    "iso:country":"US",
    "sg:address":"149 E Main St",
    "sg:city":"Grass Valley",
    "sg:classifiers":[
        {
            "category":"Autos & Motor Vehicles",
            "subcategory":"Automobile Sales",
            "type":"Retail Goods"
        }
    ],
    "sg:phone":"+1 530 477 1455",
    "sg:postcode":"95945",
    "sg:province":"CA",
    "sg:tags":[
        "car",
        "dealer"
    ],
    "wof:name":"Madonna Auto Sales",
    "wof:placetype":"venue"
},
  "geometry": {"coordinates":[-121.060221,39.219444],"type":"Point"}
}