{
  "type": "Feature",
  "properties": {
    "iso:country":"US",
    "sg:address":"1450 Wallace Ave",
    "sg:city":"San Francisco",
    "sg:classifiers":[
        {
            "category":"Wholesale",
            "subcategory":"Seafood",
            "type":"Manufacturing & Wholesale Goods"
        }
    ],
    "sg:phone":"+1 415 822 6309",
    "sg:postcode":"94124",
    "sg:province":"CA",
    "wof:name":"Charlie Seafood",
    "wof:placetype":"venue"
},
  "geometry": {"coordinates":[-122.38844,37.725934],"type":"Point"}
}