{
  "type": "Feature",
  "properties": {
    "addr:full":"18527 S Western Avenue Gardena CA 90248",
    "addr:housenumber":"18527",
    "addr:postcode":"90248",
    "addr:street":"S Western Avenue",
    "iso:country":"US",
    "sg:address":"18527 S Western Avenue",
    "sg:city":"Gardena",
    "sg:classifiers":[
        {
            "category":"Health Services",
            "subcategory":"Dentist",
            "type":"Services"
        }
    ],
    "sg:phone":"+1 310 532 2774",
    "sg:postcode":"90248",
    "sg:province":"CA",
    "wof:name":"Wong Suzie DDS",
    "wof:placetype":"venue"
},
  "geometry": {"coordinates":[-118.309016,33.862917],"type":"Point"}
}