{
  "type": "Feature",
  "properties": {
    "iso:country":"US",
    "sg:address":"4620 Galena St Ste D",
    "sg:city":"Riverside",
    "sg:classifiers":[
        {
            "category":"Bars & Pubs",
            "type":"Food & Drink"
        },
        {
            "category":"Bars & Pubs",
            "subcategory":"Lounge",
            "type":"Food & Drink"
        }
    ],
    "sg:phone":"+1 951 685 1516",
    "sg:postcode":"92509",
    "sg:province":"CA",
    "sg:tags":[
        "cocktail"
    ],
    "wof:name":"Horseshoe Lounge",
    "wof:placetype":"venue"
},
  "geometry": {"coordinates":[-117.49897799999999,34.003601],"type":"Point"}
}