{
  "type": "Feature",
  "properties": {
    "iso:country":"US",
    "sg:address":"6833 Magnolia Ave",
    "sg:city":"Riverside",
    "sg:classifiers":[
        {
            "category":"Real Estate",
            "subcategory":"Real Estate Agent",
            "type":"Services"
        }
    ],
    "sg:phone":"+1 951 787 0320",
    "sg:postcode":"92506",
    "sg:province":"CA",
    "sg:tags":[
        "consultant"
    ],
    "wof:name":"AAMAX Real Estate Apprsrs",
    "wof:placetype":"venue"
},
  "geometry": {"coordinates":[-117.39924600000001,33.94921],"type":"Point"}
}