{
  "type": "Feature",
  "properties": {
    "addr:full":"1735 N 1st St Ste 300 San Jose CA 95112",
    "addr:housenumber":"1735",
    "addr:postcode":"95112",
    "addr:street":"N 1St St Ste 300",
    "iso:country":"US",
    "sg:address":"1735 N 1st St Ste 300",
    "sg:city":"San Jose",
    "sg:classifiers":[
        {
            "category":"Professional",
            "subcategory":"Lawyer & Legal Services",
            "type":"Services"
        }
    ],
    "sg:phone":"+1 800 500 5342",
    "sg:postcode":"95112",
    "sg:province":"CA",
    "sg:website":"earlcarterlaw.com",
    "wof:name":"The Law Offices of Earl Carter & Associates",
    "wof:placetype":"venue"
},
  "geometry": {"coordinates":[-121.91486999999999,37.368516],"type":"Point"}
}