{
  "type": "Feature",
  "properties": {
    "addr:full":"1910 State St San Diego CA 92101",
    "addr:housenumber":"1910",
    "addr:postcode":"92101",
    "addr:street":"State St",
    "iso:country":"US",
    "sg:address":"1910 State St",
    "sg:city":"San Diego",
    "sg:classifiers":[
        {
            "category":"Professional",
            "subcategory":"Lawyer & Legal Services",
            "type":"Services"
        }
    ],
    "sg:phone":"+1 619 234 6704",
    "sg:postcode":"92101",
    "sg:province":"CA",
    "sg:tags":[
        "attorney",
        "bureau"
    ],
    "wof:name":"Applied Graphic Sciences",
    "wof:placetype":"venue"
},
  "geometry": {"coordinates":[-117.167377,32.725798],"type":"Point"}
}