{
  "type": "Feature",
  "properties": {
    "addr:full":"17860 Ideal Pkwy Manteca CA 95336",
    "addr:housenumber":"17860",
    "addr:postcode":"95336",
    "addr:street":"Ideal Pkwy",
    "iso:country":"US",
    "sg:address":"17860 Ideal Pkwy",
    "sg:city":"Manteca",
    "sg:classifiers":[
        {
            "category":"Building & Trades",
            "subcategory":"Landscaping Services",
            "type":"Services"
        }
    ],
    "sg:phone":"+1 209 825 4411",
    "sg:postcode":"95336",
    "sg:province":"CA",
    "sg:tags":[
        "landscape",
        "contractor"
    ],
    "wof:name":"Spectrum Lanscape Services Inc.",
    "wof:placetype":"venue"
},
  "geometry": {"coordinates":[-121.172101,37.798912],"type":"Point"}
}