{
  "type": "Feature",
  "properties": {
    "iso:country":"US",
    "sg:address":"14149 Ramona Blvd",
    "sg:city":"Baldwin Park",
    "sg:classifiers":[
        {
            "category":"Retail",
            "subcategory":"Repair Shop",
            "type":"Services"
        }
    ],
    "sg:phone":"+1 626 939 9029",
    "sg:postcode":"91706",
    "sg:province":"CA",
    "sg:tags":[
        "key"
    ],
    "wof:name":"David's Locksmith",
    "wof:placetype":"venue"
},
  "geometry": {"coordinates":[-117.965696,34.08531],"type":"Point"}
}