{
  "type": "Feature",
  "properties": {
    "addr:full":"13921 Olive Mesa Ct Poway CA 92064",
    "addr:housenumber":"13921",
    "addr:postcode":"ca 92064",
    "addr:street":"Olive Mesa Ct",
    "iso:country":"US",
    "sg:address":"13921 Olive Mesa Ct",
    "sg:city":"Poway",
    "sg:classifiers":[
        {
            "category":"Community Center",
            "subcategory":"Youth",
            "type":"Public Place"
        }
    ],
    "sg:phone":"+1 858 842 2097",
    "sg:postcode":"92064",
    "sg:province":"CA",
    "wof:name":"Cub Scout Pack 618",
    "wof:placetype":"venue"
},
  "geometry": {"coordinates":[-117.041186,32.966486],"type":"Point"}
}