{
  "type": "Feature",
  "properties": {
    "iso:country":"US",
    "sg:address":"16540 Gault St",
    "sg:city":"Van Nuys",
    "sg:classifiers":[
        {
            "category":"Wholesale",
            "subcategory":"Electrical",
            "type":"Manufacturing & Wholesale Goods"
        }
    ],
    "sg:phone":"+1 818 908 9666",
    "sg:postcode":"91406",
    "sg:province":"CA",
    "sg:tags":[
        "supply",
        "sign"
    ],
    "sg:website":"www.signsupply.com",
    "wof:name":"Ordway Sign Supply Inc",
    "wof:placetype":"venue"
},
  "geometry": {"coordinates":[-118.49420499999999,34.199262],"type":"Point"}
}