{
  "type": "Feature",
  "properties": {
    "iso:country":"US",
    "sg:address":"2440 Las Posas Rd",
    "sg:city":"Camarillo",
    "sg:classifiers":[
        {
            "category":"Health Services",
            "subcategory":"Chiropractor",
            "type":"Services"
        }
    ],
    "sg:phone":"+1 805 384 0101",
    "sg:postcode":"93010",
    "sg:province":"CA",
    "wof:name":"Active Chiropractic and Wellness Center",
    "wof:placetype":"venue"
},
  "geometry": {"coordinates":[-119.03700600000001,34.236976],"type":"Point"}
}