{
  "type": "Feature",
  "properties": {
    "iso:country":"US",
    "sg:address":"450 N Roxbury Dr",
    "sg:city":"Beverly Hills",
    "sg:classifiers":[
        {
            "category":"Health Services",
            "subcategory":"Doctor",
            "type":"Services"
        }
    ],
    "sg:phone":"+1 310 246 4621",
    "sg:postcode":"90210",
    "sg:province":"CA",
    "wof:name":"Hill David PHD",
    "wof:placetype":"venue"
},
  "geometry": {"coordinates":[-118.406998,34.068199],"type":"Point"}
}