{
  "type": "Feature",
  "properties": {
    "addr:full":"99 Douglas Rd Oakley CA 94561",
    "addr:housenumber":"99",
    "addr:postcode":"94561",
    "addr:street":"Douglas Rd",
    "iso:country":"US",
    "sg:address":"99 Douglas Rd",
    "sg:city":"Oakley",
    "sg:classifiers":[
        {
            "category":"Home & Garden",
            "subcategory":"Building Materials",
            "type":"Retail Goods"
        }
    ],
    "sg:phone":"+1 925 754 8393",
    "sg:postcode":"94561",
    "sg:province":"CA",
    "sg:tags":[
        "door"
    ],
    "wof:name":"Pacific Coast Overhead Doors",
    "wof:placetype":"venue"
},
  "geometry": {"coordinates":[-121.693842,37.975645],"type":"Point"}
}