{
  "type": "Feature",
  "properties": {
    "iso:country":"US",
    "sg:address":"1010 Gravenstein Ave",
    "sg:city":"Sebastopol",
    "sg:classifiers":[
        {
            "category":"Retail",
            "subcategory":"Animal Services",
            "type":"Services"
        }
    ],
    "sg:phone":"+1 707 829 2488",
    "sg:postcode":"95472",
    "sg:province":"CA",
    "wof:name":"Barking Lot",
    "wof:placetype":"venue"
},
  "geometry": {"coordinates":[-122.81595900000001,38.390046],"type":"Point"}
}