{
  "type": "Feature",
  "properties": {
    "iso:country":"US",
    "sg:address":"29550 Nuevo Rd",
    "sg:city":"Nuevo",
    "sg:classifiers":[
        {
            "category":"Personal",
            "subcategory":"Beauty Salon",
            "type":"Services"
        }
    ],
    "sg:phone":"+1 951 683 9718",
    "sg:postcode":"92567",
    "sg:province":"CA",
    "wof:name":"Yolanda's Hair Salon",
    "wof:placetype":"venue"
},
  "geometry": {"coordinates":[-117.146793,33.801325],"type":"Point"}
}