{
  "type": "Feature",
  "properties": {
    "iso:country":"US",
    "sg:address":"508 Pavillions Ln",
    "sg:city":"Sacramento",
    "sg:classifiers":[
        {
            "category":"Coffee & Tea",
            "type":"Food & Drink"
        }
    ],
    "sg:phone":"+1 916 779 0516",
    "sg:postcode":"95825",
    "sg:province":"CA",
    "wof:name":"Bella Bru Express",
    "wof:placetype":"venue"
},
  "geometry": {"coordinates":[-121.410383,38.574628],"type":"Point"}
}