{
  "type": "Feature",
  "properties": {
    "addr:full":"69 N Washington St Sonora CA 95370",
    "addr:housenumber":"69",
    "addr:postcode":"95370",
    "addr:street":"N Washington St",
    "iso:country":"US",
    "sg:address":"69 N Washington St",
    "sg:city":"Sonora",
    "sg:classifiers":[
        {
            "category":"Organizations",
            "subcategory":"Religious Organization",
            "type":"Services"
        }
    ],
    "sg:phone":"+1 209 532 4141",
    "sg:postcode":"95370",
    "sg:province":"CA",
    "sg:tags":[
        "church"
    ],
    "wof:name":"First Church-Christ Scientist",
    "wof:placetype":"venue"
},
  "geometry": {"coordinates":[-120.383388,37.985524],"type":"Point"}
}