{
  "type": "Feature",
  "properties": {
    "addr:full":"27240 Turnberry Ln Ste 200 Valencia CA 91355",
    "addr:postcode":"27240;91355",
    "addr:street":"Turnberry Ln Ste 200",
    "iso:country":"US",
    "sg:address":"27240 Turnberry Ln Ste 200",
    "sg:city":"Valencia",
    "sg:classifiers":[
        {
            "category":"Professional",
            "subcategory":"Lawyer & Legal Services",
            "type":"Services"
        }
    ],
    "sg:phone":"+1 661 362 0718",
    "sg:postcode":"91355",
    "sg:province":"CA",
    "sg:tags":[
        "divorce",
        "law",
        "family"
    ],
    "sg:website":"www.chromanlaw.com",
    "wof:name":"Chroman Steven B Law Offices Of",
    "wof:placetype":"venue"
},
  "geometry": {"coordinates":[-118.61096499999999,34.443877],"type":"Point"}
}