{
  "type": "Feature",
  "properties": {
    "addr:full":"1771 del Prado Pomona CA 91768",
    "addr:housenumber":"1771",
    "addr:postcode":"91768",
    "addr:street":"Del Prado",
    "iso:country":"US",
    "sg:address":"1771 del Prado",
    "sg:city":"Pomona",
    "sg:classifiers":[
        {
            "category":"Professional",
            "subcategory":"Business Services",
            "type":"Services"
        }
    ],
    "sg:phone":"+1 909 868 0032",
    "sg:postcode":"91768",
    "sg:province":"CA",
    "sg:tags":[
        "interior",
        "consultant",
        "design",
        "decorator"
    ],
    "wof:name":"Designs By Sharon",
    "wof:placetype":"venue"
},
  "geometry": {"coordinates":[-117.778385,34.079018],"type":"Point"}
}