{
  "type": "Feature",
  "properties": {
    "addr:full":"1600 Pacific Ave Venice CA 90291",
    "addr:housenumber":"1600",
    "addr:postcode":"90291",
    "addr:street":"Pacific Ave",
    "iso:country":"US",
    "sg:address":"1600 Pacific Ave",
    "sg:city":"Venice",
    "sg:classifiers":[
        {
            "category":"Home & Garden",
            "subcategory":"Home Furnishings",
            "type":"Retail Goods"
        }
    ],
    "sg:phone":"+1 310 450 4116",
    "sg:postcode":"90291",
    "sg:province":"CA",
    "sg:tags":[
        "repair",
        "furniture",
        "re"
    ],
    "wof:name":"Snapdragon",
    "wof:placetype":"venue"
},
  "geometry": {"coordinates":[-118.47201699999999,33.987466],"type":"Point"}
}