{
  "type": "Feature",
  "properties": {
    "addr:full":"4101 Falling Leaf Dr Encino CA 91316",
    "addr:housenumber":"4101",
    "addr:postcode":"91316",
    "addr:street":"Falling Leaf Dr",
    "iso:country":"US",
    "sg:address":"4101 Falling Leaf Dr",
    "sg:city":"Encino",
    "sg:classifiers":[
        {
            "category":"Home & Garden",
            "subcategory":"Household Appliances",
            "type":"Retail Goods"
        }
    ],
    "sg:phone":"+1 310 285 0789",
    "sg:postcode":"91316",
    "sg:province":"CA",
    "wof:name":"Mercury Refrigeration & AC",
    "wof:placetype":"venue"
},
  "geometry": {"coordinates":[-118.526281,34.145672],"type":"Point"}
}