{
  "type": "Feature",
  "properties": {
    "iso:country":"US",
    "sg:address":"5143 Waring Rd",
    "sg:city":"San Diego",
    "sg:classifiers":[
        {
            "category":"Shopping",
            "type":"Retail Goods"
        }
    ],
    "sg:phone":"+1 619 229 2505",
    "sg:postcode":"92120",
    "sg:province":"CA",
    "sg:tags":[
        "cards",
        "sport",
        "baseball",
        "memorabilia"
    ],
    "sg:website":"www.cjsportscards.com",
    "wof:name":"C J's Sports Cards Memorabila",
    "wof:placetype":"venue"
},
  "geometry": {"coordinates":[-117.081407,32.79181],"type":"Point"}
}