{
  "type": "Feature",
  "properties": {
    "addr:full":"889 Pierce Ct Thousand Oaks CA 91360",
    "addr:housenumber":"889",
    "addr:postcode":"91360",
    "addr:street":"Pierce Ct",
    "iso:country":"US",
    "sg:address":"889 Pierce Ct",
    "sg:city":"Thousand Oaks",
    "sg:classifiers":[
        {
            "category":"Professional",
            "type":"Services"
        }
    ],
    "sg:phone":"+1 805 370 0900",
    "sg:postcode":"91360",
    "sg:province":"CA",
    "sg:tags":[
        "establishment"
    ],
    "wof:name":"Americana Bancorp",
    "wof:placetype":"venue"
},
  "geometry": {"coordinates":[-118.862937,34.177988],"type":"Point"}
}