{
  "type": "Feature",
  "properties": {
    "addr:full":"3619 Honeyglen Way Ontario CA 91761",
    "addr:postcode":"3619;91761",
    "addr:street":"Honeyglen Way",
    "iso:country":"US",
    "sg:address":"3619 Honeyglen Way",
    "sg:city":"Ontario",
    "sg:classifiers":[
        {
            "category":"Building & Trades",
            "subcategory":"Electrical",
            "type":"Services"
        }
    ],
    "sg:phone":"+1 909 947 7898",
    "sg:postcode":"91761",
    "sg:province":"CA",
    "sg:tags":[
        "electric",
        "contractor"
    ],
    "wof:name":"A & C Electrical",
    "wof:placetype":"venue"
},
  "geometry": {"coordinates":[-117.572492,34.024801],"type":"Point"}
}