{
  "type": "Feature",
  "properties": {
    "addr:full":"6220 Mission Gorge Rd San Diego CA 92120",
    "addr:housenumber":"6220",
    "addr:postcode":"92120",
    "addr:street":"Mission Gorge Rd",
    "iso:country":"US",
    "sg:address":"6220 Mission Gorge Rd",
    "sg:city":"San Diego",
    "sg:classifiers":[
        {
            "category":"Retail",
            "subcategory":"Auto Repair",
            "type":"Services"
        }
    ],
    "sg:phone":"+1 619 280 9555",
    "sg:postcode":"92120",
    "sg:province":"CA",
    "sg:tags":[
        "automobile",
        "used",
        "general"
    ],
    "wof:name":"A E Teasley Enterprises",
    "wof:placetype":"venue"
},
  "geometry": {"coordinates":[-117.097801,32.788012],"type":"Point"}
}