{
  "type": "Feature",
  "properties": {
    "addr:full":"538 Lighthouse Ave Monterey CA 93940",
    "addr:housenumber":"538",
    "addr:postcode":"93940",
    "addr:street":"Lighthouse Ave",
    "iso:country":"US",
    "sg:address":"538 Lighthouse Ave",
    "sg:city":"Monterey",
    "sg:classifiers":[
        {
            "category":"Restaurant",
            "type":"Food & Drink"
        }
    ],
    "sg:phone":"+1 831 641 0130",
    "sg:postcode":"93940",
    "sg:province":"CA",
    "wof:name":"Loose Noodle Pasta House",
    "wof:placetype":"venue"
},
  "geometry": {"coordinates":[-121.901374,36.613208],"type":"Point"}
}