{
  "type": "Feature",
  "properties": {
    "iso:country":"US",
    "sg:address":"4200 South Lincoln Boulevard",
    "sg:city":"Marina del Rey",
    "sg:classifiers":[
        {
            "category":"Professional",
            "subcategory":"Art Services",
            "type":"Services"
        },
        {
            "category":"Professional",
            "subcategory":"Printing & Photocopies",
            "type":"Services"
        }
    ],
    "sg:phone":"+1 310 577 0300",
    "sg:postcode":"90292",
    "sg:province":"CA",
    "sg:tags":[
        "photographer",
        "graphic",
        "design"
    ],
    "sg:website":"www.Signtist.com",
    "wof:name":"Signtist",
    "wof:placetype":"venue"
},
  "geometry": {"coordinates":[-118.444109,33.987037],"type":"Point"}
}