{
  "type": "Feature",
  "properties": {
    "addr:full":"320 Cedar St Ste 2 Santa Cruz CA 95060",
    "addr:housenumber":"320",
    "addr:postcode":"95060",
    "addr:street":"Cedar St Ste 2",
    "iso:country":"US",
    "sg:address":"320 Cedar St Ste 2",
    "sg:city":"Santa Cruz",
    "sg:classifiers":[
        {
            "category":"Arts & Performance",
            "subcategory":"Music",
            "type":"Entertainment"
        },
        {
            "category":"Retail",
            "subcategory":"Event Space",
            "type":"Services"
        }
    ],
    "sg:phone":"+1 831 427 2227",
    "sg:postcode":"95060",
    "sg:province":"CA",
    "sg:tags":[
        "venue"
    ],
    "sg:website":"www.kuumbwajazz.org",
    "wof:name":"Kuumbwa Jazz Center",
    "wof:placetype":"venue"
},
  "geometry": {"coordinates":[-122.026341,36.969551],"type":"Point"}
}