{
  "type": "Feature",
  "properties": {
    "addr:full":"872 Bergamo Ave San Jacinto CA 92583",
    "addr:housenumber":"872",
    "addr:postcode":"92583",
    "addr:street":"Bergamo Ave",
    "iso:country":"US",
    "sg:address":"872 Bergamo Ave",
    "sg:city":"San Jacinto",
    "sg:classifiers":[
        {
            "category":"Personal",
            "subcategory":"Beauty Salon",
            "type":"Services"
        }
    ],
    "sg:phone":"+1 951 654 9012",
    "sg:postcode":"92583",
    "sg:province":"CA",
    "wof:name":"Thee Image Creator",
    "wof:placetype":"venue"
},
  "geometry": {"coordinates":[-116.93216200000001,33.797122],"type":"Point"}
}