{
  "type": "Feature",
  "properties": {
    "addr:full":"20925 Dillon Dr Redding CA 96003",
    "addr:housenumber":"20925",
    "addr:postcode":"96003",
    "addr:street":"Dillon Dr",
    "iso:country":"US",
    "sg:address":"20925 Dillon Dr",
    "sg:city":"Redding",
    "sg:classifiers":[
        {
            "category":"Personal",
            "subcategory":"Beauty Salon",
            "type":"Services"
        }
    ],
    "sg:phone":"+1 530 549 4188",
    "sg:postcode":"96003",
    "sg:province":"CA",
    "wof:name":"Toni's Fitting Image",
    "wof:placetype":"venue"
},
  "geometry": {"coordinates":[-122.28316599999999,40.621943],"type":"Point"}
}