{
  "type": "Feature",
  "properties": {
    "addr:full":"3780 E Dakota Ave Fresno CA 93726",
    "addr:housenumber":"3780",
    "addr:postcode":"93726",
    "addr:street":"E Dakota Ave",
    "iso:country":"US",
    "sg:address":"3780 E Dakota Ave",
    "sg:city":"Fresno",
    "sg:classifiers":[
        {
            "category":"Wholesale",
            "subcategory":"Home Furnishings",
            "type":"Manufacturing & Wholesale Goods"
        }
    ],
    "sg:phone":"+1 559 277 5601",
    "sg:postcode":"93726",
    "sg:province":"CA",
    "sg:tags":[
        "closet",
        "accessory"
    ],
    "sg:website":"www.aboutheadsup.com",
    "wof:name":"Heads Up Closet Organizers",
    "wof:placetype":"venue"
},
  "geometry": {"coordinates":[-119.76260000000001,36.786768],"type":"Point"}
}