{
  "type": "Feature",
  "properties": {
    "iso:country":"US",
    "sg:address":"3780 E Dakota Ave",
    "sg:city":"Fresno",
    "sg:classifiers":[
        {
            "category":"Wholesale",
            "subcategory":"Home Furnishings",
            "type":"Manufacturing & Wholesale Goods"
        }
    ],
    "sg:phone":"+1 559 277 5601",
    "sg:postcode":"93726",
    "sg:province":"CA",
    "sg:tags":[
        "closet",
        "accessory"
    ],
    "sg:website":"www.aboutheadsup.com",
    "wof:name":"Heads Up Closet Organizers",
    "wof:placetype":"venue"
},
  "geometry": {"coordinates":[-119.7626,36.786768],"type":"Point"}
}