{
  "type": "Feature",
  "properties": {
    "iso:country":"US",
    "sg:address":"650 Trade Way",
    "sg:city":"Turlock",
    "sg:classifiers":[
        {
            "category":"Professional",
            "subcategory":"Business Services",
            "type":"Services"
        }
    ],
    "sg:phone":"+1 209 668 6300",
    "sg:postcode":"95380",
    "sg:province":"CA",
    "sg:tags":[
        "packaging"
    ],
    "wof:name":"Gilbreth Packaging System",
    "wof:placetype":"venue"
},
  "geometry": {"coordinates":[-120.881608,37.48543],"type":"Point"}
}