{
  "type": "Feature",
  "properties": {
    "addr:full":"4247 Grand View Boulevard Los Angeles CA 90066",
    "addr:housenumber":"4247",
    "addr:postcode":"90066",
    "addr:street":"Grand View Boulevard",
    "iso:country":"US",
    "sg:address":"4247 Grand View Boulevard",
    "sg:city":"Los Angeles",
    "sg:classifiers":[
        {
            "category":"Building & Trades",
            "subcategory":"Plumbing",
            "type":"Services"
        }
    ],
    "sg:phone":"+1 310 839 6615",
    "sg:postcode":"90066",
    "sg:province":"CA",
    "wof:name":"Lomardo-Stokx Plumbing",
    "wof:placetype":"venue"
},
  "geometry": {"coordinates":[-118.424414,33.99649],"type":"Point"}
}