{
  "type": "Feature",
  "properties": {
    "iso:country":"US",
    "sg:address":"1445 Hudson St",
    "sg:city":"Redwood City",
    "sg:classifiers":[
        {
            "category":"Sports & Exercise",
            "subcategory":"Gym",
            "type":"Entertainment"
        }
    ],
    "sg:phone":"+1 650 368 4168",
    "sg:postcode":"94061",
    "sg:province":"CA",
    "sg:tags":[
        "club",
        "health",
        "studio",
        "gymnasium"
    ],
    "sg:website":"www.ymcamidpen.org",
    "wof:name":"YMCA",
    "wof:placetype":"venue"
},
  "geometry": {"coordinates":[-122.226823,37.470122],"type":"Point"}
}