{
  "type": "Feature",
  "properties": {
    "iso:country":"US",
    "sg:address":"5839 Temple City Blvd",
    "sg:city":"Temple City",
    "sg:classifiers":[
        {
            "category":"Education",
            "subcategory":"Dance Studio",
            "type":"Public Place"
        }
    ],
    "sg:phone":"+1 626 285 4888",
    "sg:postcode":"91780",
    "sg:province":"CA",
    "sg:tags":[
        "art",
        "performing",
        "instruction",
        "dancing"
    ],
    "wof:name":"Li's Dance Studio",
    "wof:placetype":"venue"
},
  "geometry": {"coordinates":[-118.060997,34.1064],"type":"Point"}
}