{
  "type": "Feature",
  "properties": {
    "addr:full":"1865 Powell Dr Ventura CA 93004",
    "addr:housenumber":"1865",
    "addr:postcode":"93004",
    "addr:street":"Powell Dr",
    "iso:country":"US",
    "sg:address":"1865 Powell Dr",
    "sg:city":"Ventura",
    "sg:classifiers":[
        {
            "category":"Farming",
            "subcategory":"Berry Farm",
            "type":"Manufacturing & Wholesale Goods"
        }
    ],
    "sg:phone":"+1 805 659 2982",
    "sg:postcode":"93004",
    "sg:province":"CA",
    "sg:tags":[
        "strawberry"
    ],
    "wof:name":"Ito Brothers Inc",
    "wof:placetype":"venue"
},
  "geometry": {"coordinates":[-119.17029700000001,34.262766],"type":"Point"}
}