{
  "type": "Feature",
  "properties": {
    "addr:full":"353 S Fairfax Ave Los Angeles CA 90036",
    "addr:housenumber":"353",
    "addr:postcode":"90036",
    "addr:street":"S Fairfax Ave",
    "iso:country":"US",
    "sg:address":"353 S Fairfax Ave",
    "sg:city":"Los Angeles",
    "sg:classifiers":[
        {
            "category":"Manufacturing",
            "subcategory":"Signs",
            "type":"Manufacturing & Wholesale Goods"
        }
    ],
    "sg:phone":"+1 323 658 5221",
    "sg:postcode":"90036",
    "sg:province":"CA",
    "wof:name":"Sign-Tist",
    "wof:placetype":"venue"
},
  "geometry": {"coordinates":[-118.361479,34.069936],"type":"Point"}
}