{
  "type": "Feature",
  "properties": {
    "addr:full":"1720 4th St Santa Rosa CA 95404",
    "addr:housenumber":"1720",
    "addr:postcode":"ca 95404",
    "addr:street":"4Th St",
    "iso:country":"US",
    "sg:address":"1720 4th St",
    "sg:city":"Santa Rosa",
    "sg:classifiers":[
        {
            "category":"Health Services",
            "subcategory":"Hospital",
            "type":"Services"
        }
    ],
    "sg:phone":"+1 707 546 8100",
    "sg:postcode":"95404",
    "sg:province":"CA",
    "wof:name":"4th St Laser & Surgery Ctr",
    "wof:placetype":"venue"
},
  "geometry": {"coordinates":[-122.698387,38.44915],"type":"Point"}
}