{
  "type": "Feature",
  "properties": {
    "iso:country":"US",
    "sg:address":"620 Indiana St",
    "sg:city":"Benicia",
    "sg:classifiers":[
        {
            "category":"Wholesale",
            "subcategory":"Machinery & Supplies",
            "type":"Manufacturing & Wholesale Goods"
        }
    ],
    "sg:phone":"+1 707 746 1379",
    "sg:postcode":"94510",
    "sg:province":"CA",
    "sg:tags":[
        "pipe",
        "fitting"
    ],
    "wof:name":"Wilson Industries Inc",
    "wof:placetype":"venue"
},
  "geometry": {"coordinates":[-122.12822,38.073927],"type":"Point"}
}