{
  "type": "Feature",
  "properties": {
    "iso:country":"US",
    "sg:address":"2658 Spring St",
    "sg:city":"Redwood City",
    "sg:classifiers":[
        {
            "category":"Building & Trades",
            "subcategory":"Construction",
            "type":"Services"
        },
        {
            "category":"Autos & Motor Vehicles",
            "subcategory":"Auto Supplies",
            "type":"Retail Goods"
        }
    ],
    "sg:phone":"+1 650 363 8852",
    "sg:postcode":"94063",
    "sg:province":"CA",
    "sg:tags":[
        "waterproofing",
        "contractor"
    ],
    "sg:website":"www.sprayonlining.com",
    "wof:name":"Spray On Lining & Coating",
    "wof:placetype":"venue"
},
  "geometry": {"coordinates":[-122.208591,37.482386],"type":"Point"}
}