{
  "type": "Feature",
  "properties": {
    "addr:full":"2810 E Lincoln Ave Anaheim CA 92806",
    "addr:housenumber":"2810",
    "addr:postcode":"92806",
    "addr:street":"E Lincoln Ave",
    "iso:country":"US",
    "sg:address":"2810 E Lincoln Ave",
    "sg:city":"Anaheim",
    "sg:classifiers":[
        {
            "category":"Restaurant",
            "type":"Food & Drink"
        }
    ],
    "sg:menulink":"http://www.allmenus.com/ca/anaheim-santa-ana-garden-grove/171127-carls-jr/menu/",
    "sg:phone":"+1 714 630 2874",
    "sg:postcode":"92806",
    "sg:province":"CA",
    "sg:tags":[
        "burger",
        "american"
    ],
    "wof:name":"Carl's Jr.",
    "wof:placetype":"venue"
},
  "geometry": {"coordinates":[-117.87096200000001,33.836987],"type":"Point"}
}