{
  "type": "Feature",
  "properties": {
    "addr:full":"2007 Emerson St Bakersfield CA 93309",
    "addr:housenumber":"2007",
    "addr:postcode":"93309",
    "addr:street":"Emerson St",
    "iso:country":"US",
    "sg:address":"2007 Emerson St",
    "sg:city":"Bakersfield",
    "sg:classifiers":[
        {
            "category":"Wholesale",
            "subcategory":"Vending Machines",
            "type":"Manufacturing & Wholesale Goods"
        }
    ],
    "sg:phone":"+1 661 833 8537",
    "sg:postcode":"93309",
    "sg:province":"CA",
    "wof:name":"Picann Enterprises",
    "wof:placetype":"venue"
},
  "geometry": {"coordinates":[-119.057258,35.336664],"type":"Point"}
}