{
  "type": "Feature",
  "properties": {
    "iso:country":"US",
    "sg:address":"14311 Cerise Ave",
    "sg:city":"Hawthorne",
    "sg:classifiers":[
        {
            "category":"Retail",
            "subcategory":"Repair Shop",
            "type":"Services"
        }
    ],
    "sg:phone":"+1 310 644 8878",
    "sg:postcode":"90250",
    "sg:province":"CA",
    "sg:tags":[
        "related"
    ],
    "wof:name":"Sers",
    "wof:placetype":"venue"
},
  "geometry": {"coordinates":[-118.333072,33.90093],"type":"Point"}
}