{
  "type": "Feature",
  "properties": {
    "addr:full":"1528 Milton Rd Napa CA 94559",
    "addr:housenumber":"1528",
    "addr:postcode":"94559",
    "addr:street":"Milton Rd",
    "iso:country":"US",
    "sg:address":"1528 Milton Rd",
    "sg:city":"Napa",
    "sg:classifiers":[
        {
            "category":"Professional",
            "subcategory":"Accounting & Tax Preparation",
            "type":"Services"
        }
    ],
    "sg:phone":"+1 707 224 3424",
    "sg:postcode":"94559",
    "sg:province":"CA",
    "sg:tags":[
        "return",
        "filing"
    ],
    "wof:name":"Jack T Smith",
    "wof:placetype":"venue"
},
  "geometry": {"coordinates":[-122.30918800000001,38.208765],"type":"Point"}
}