{
  "type": "Feature",
  "properties": {
    "addr:full":"4182 S Vermont Ave Los Angeles CA 90037",
    "addr:housenumber":"4182",
    "addr:postcode":"90037",
    "addr:street":"S Vermont Ave",
    "iso:country":"US",
    "sg:address":"4182 S Vermont Ave",
    "sg:city":"Los Angeles",
    "sg:classifiers":[
        {
            "category":"Restaurant",
            "type":"Food & Drink"
        }
    ],
    "sg:phone":"+1 323 234 4797",
    "sg:postcode":"90037",
    "sg:province":"CA",
    "wof:name":"Tom's Hamburgers",
    "wof:placetype":"venue"
},
  "geometry": {"coordinates":[-118.291465,34.007996],"type":"Point"}
}