{
  "type": "Feature",
  "properties": {
    "addr:full":"2106 Santa Fe Ave Hughson CA 95326",
    "addr:housenumber":"2106",
    "addr:postcode":"95326",
    "addr:street":"Santa Fe Ave",
    "iso:country":"US",
    "sg:address":"2106 Santa Fe Ave",
    "sg:city":"Hughson",
    "sg:classifiers":[
        {
            "category":"Wholesale",
            "subcategory":"Machinery & Supplies",
            "type":"Manufacturing & Wholesale Goods"
        },
        {
            "category":"Professional",
            "subcategory":"Management & Consulting",
            "type":"Services"
        }
    ],
    "sg:phone":"+1 209 883 4900",
    "sg:postcode":"95326",
    "sg:province":"CA",
    "sg:tags":[
        "agricultural",
        "consultant"
    ],
    "wof:name":"Mid Valley Agricultural Svcs",
    "wof:placetype":"venue"
},
  "geometry": {"coordinates":[-120.870028,37.598013],"type":"Point"}
}