{
  "type": "Feature",
  "properties": {
    "iso:country":"US",
    "sg:address":"1540 Sycamore Ave",
    "sg:city":"Hercules",
    "sg:classifiers":[
        {
            "category":"Wholesale",
            "subcategory":"Computers",
            "type":"Manufacturing & Wholesale Goods"
        },
        {
            "category":"Internet Cafe",
            "subcategory":"None",
            "type":"Food & Drink"
        },
        {
            "category":"Professional",
            "subcategory":"Computer Services",
            "type":"Services"
        }
    ],
    "sg:phone":"+1 510 839 2894",
    "sg:postcode":"94547",
    "sg:province":"CA",
    "sg:tags":[
        "repair",
        "product",
        "designer",
        "network",
        "consultant",
        "system",
        "equipment",
        "design",
        "equipment-service",
        "software"
    ],
    "wof:name":"Aldon Computer Group",
    "wof:placetype":"venue"
},
  "geometry": {"coordinates":[-122.27092500000001,38.009199],"type":"Point"}
}