{
  "type": "Feature",
  "properties": {
    "addr:full":"3620 Kurtz St San Diego CA 92110",
    "addr:housenumber":"3620",
    "addr:postcode":"92110",
    "addr:street":"Kurtz St",
    "iso:country":"US",
    "sg:address":"3620 Kurtz St",
    "sg:city":"San Diego",
    "sg:classifiers":[
        {
            "category":"Professional",
            "type":"Services"
        }
    ],
    "sg:phone":"+1 619 686 5800",
    "sg:postcode":"92110",
    "sg:province":"CA",
    "wof:name":"West Hazmat Drilling Corp",
    "wof:placetype":"venue"
},
  "geometry": {"coordinates":[-117.211631,32.757119],"type":"Point"}
}