{
  "type": "Feature",
  "properties": {
    "addr:full":"2043 Westcliff Drive Newport Beach CA 92660",
    "addr:housenumber":"2043",
    "addr:postcode":"92660",
    "addr:street":"Westcliff Drive",
    "iso:country":"US",
    "sg:address":"2043 Westcliff Drive",
    "sg:city":"Newport Beach",
    "sg:classifiers":[
        {
            "category":"Professional",
            "subcategory":"Lawyer & Legal Services",
            "type":"Services"
        }
    ],
    "sg:phone":"+1 949 646 1900",
    "sg:postcode":"92660",
    "sg:province":"CA",
    "wof:name":"Conn Robert L Attorney At Law",
    "wof:placetype":"venue"
},
  "geometry": {"coordinates":[-117.90762100000001,33.627622],"type":"Point"}
}