{
  "type": "Feature",
  "properties": {
    "addr:full":"8980 Roblar Rd Petaluma CA 94952",
    "addr:postcode":"8980;94952",
    "addr:street":"Roblar Rd",
    "iso:country":"US",
    "sg:address":"8980 Roblar Rd",
    "sg:city":"Petaluma",
    "sg:classifiers":[
        {
            "category":"Farming",
            "subcategory":"Dairy Farm",
            "type":"Manufacturing & Wholesale Goods"
        }
    ],
    "sg:phone":"+1 707 795 5507",
    "sg:postcode":"94952",
    "sg:province":"CA",
    "wof:name":"Ramiro Avila",
    "wof:placetype":"venue"
},
  "geometry": {"coordinates":[-122.836918,38.306424],"type":"Point"}
}