{
  "type": "Feature",
  "properties": {
    "addr:full":"4525 E Atherton St Long Beach CA 90815",
    "addr:housenumber":"4525",
    "addr:postcode":"90815",
    "addr:street":"E Atherton St",
    "iso:country":"US",
    "sg:address":"4525 E Atherton St",
    "sg:city":"Long Beach",
    "sg:classifiers":[
        {
            "category":"Professional",
            "type":"Services"
        }
    ],
    "sg:phone":"+1 562 439 0045",
    "sg:postcode":"90815",
    "sg:province":"CA",
    "wof:name":"A Terrance Dickens",
    "wof:placetype":"venue"
},
  "geometry": {"coordinates":[-118.13906,33.78992],"type":"Point"}
}