{
  "type": "Feature",
  "properties": {
    "addr:full":"120 N Broadway Santa Maria CA 93454",
    "addr:housenumber":"120",
    "addr:postcode":"93454",
    "addr:street":"N Broadway",
    "iso:country":"US",
    "sg:address":"120 N Broadway",
    "sg:city":"Santa Maria",
    "sg:classifiers":[
        {
            "category":"Real Estate",
            "subcategory":"Real Estate Operator",
            "type":"Services"
        }
    ],
    "sg:phone":"+1 805 922 5226",
    "sg:postcode":"93454",
    "sg:province":"CA",
    "sg:tags":[
        "building",
        "commercial",
        "apt"
    ],
    "wof:name":"Union Plaza Apartments",
    "wof:placetype":"venue"
},
  "geometry": {"coordinates":[-120.435704,34.953952],"type":"Point"}
}