{
  "type": "Feature",
  "properties": {
    "iso:country":"US",
    "sg:address":"14900 Apple Valley Rd",
    "sg:city":"Apple Valley",
    "sg:classifiers":[
        {
            "category":"Government",
            "subcategory":"Police Station",
            "type":"Public Place"
        }
    ],
    "sg:phone":"+1 760 240 7400",
    "sg:postcode":"92307",
    "sg:province":"CA",
    "sg:tags":[
        "sheriff"
    ],
    "wof:name":"Apple Valley Police",
    "wof:placetype":"venue"
},
  "geometry": {"coordinates":[-117.24847699999999,34.521308],"type":"Point"}
}