{
  "type": "Feature",
  "properties": {
    "iso:country":"US",
    "sg:address":"2024 N Tustin Ave",
    "sg:city":"Orange",
    "sg:classifiers":[
        {
            "category":"Restaurant",
            "type":"Food & Drink"
        }
    ],
    "sg:phone":"+1 714 974 0999",
    "sg:postcode":"92865",
    "sg:province":"CA",
    "sg:tags":[
        "vietnamese"
    ],
    "wof:name":"Super Pho",
    "wof:placetype":"venue"
},
  "geometry": {"coordinates":[-117.83599100000001,33.821667],"type":"Point"}
}