{
  "type": "Feature",
  "properties": {
    "addr:full":"1043 S Glendora Ave West Covina CA 91790",
    "addr:housenumber":"1043",
    "addr:postcode":"91790",
    "addr:street":"S Glendora Ave",
    "iso:country":"US",
    "sg:address":"1043 S Glendora Ave",
    "sg:city":"West Covina",
    "sg:classifiers":[
        {
            "category":"Insurance",
            "subcategory":"Insurance Agent",
            "type":"Services"
        }
    ],
    "sg:phone":"+1 626 962 1177",
    "sg:postcode":"91790",
    "sg:province":"CA",
    "wof:name":"State Farm Insurance",
    "wof:placetype":"venue"
},
  "geometry": {"coordinates":[-117.936176,34.057692],"type":"Point"}
}