{
  "type": "Feature",
  "properties": {
    "iso:country":"US",
    "sg:address":"1208 Apollo Way",
    "sg:city":"Sunnyvale",
    "sg:classifiers":[
        {
            "category":"Insurance",
            "subcategory":"Insurance Agent",
            "type":"Services"
        }
    ],
    "sg:phone":"+1 408 730 9990",
    "sg:postcode":"94086",
    "sg:province":"CA",
    "wof:name":"Philadelphia Insurance Co",
    "wof:placetype":"venue"
},
  "geometry": {"coordinates":[-121.994075,37.378322],"type":"Point"}
}