{
  "type": "Feature",
  "properties": {
    "addr:full":"942 W Main St Merced CA 95340",
    "addr:housenumber":"942",
    "addr:postcode":"95340",
    "addr:street":"W Main St",
    "iso:country":"US",
    "sg:address":"942 W Main St",
    "sg:city":"Merced",
    "sg:classifiers":[
        {
            "category":"Personal",
            "subcategory":"Beauty Salon",
            "type":"Services"
        }
    ],
    "sg:phone":"+1 209 723 8887",
    "sg:postcode":"95340",
    "sg:province":"CA",
    "wof:name":"Laura Parish",
    "wof:placetype":"venue"
},
  "geometry": {"coordinates":[-120.490415,37.30389],"type":"Point"}
}