{
  "type": "Feature",
  "properties": {
    "addr:full":"17304 N Friant Rd Friant CA 93626",
    "addr:housenumber":"17304",
    "addr:postcode":"93626",
    "addr:street":"N Friant Rd",
    "iso:country":"US",
    "sg:address":"17304 N Friant Rd",
    "sg:city":"Friant",
    "sg:classifiers":[
        {
            "category":"Restaurant",
            "type":"Food & Drink"
        }
    ],
    "sg:phone":"+1 559 822 2220",
    "sg:postcode":"93626",
    "sg:province":"CA",
    "wof:name":"Dam Diner",
    "wof:placetype":"venue"
},
  "geometry": {"coordinates":[-119.713938,36.986009],"type":"Point"}
}