{
  "type": "Feature",
  "properties": {
    "addr:full":"3017 Adams Ave San Diego CA 92116",
    "addr:housenumber":"3017",
    "addr:postcode":"92116",
    "addr:street":"Adams Ave",
    "iso:country":"US",
    "sg:address":"3017 Adams Ave",
    "sg:city":"San Diego",
    "sg:classifiers":[
        {
            "category":"Shopping",
            "subcategory":"Clothing, Apparel, & Fashions",
            "type":"Retail Goods"
        }
    ],
    "sg:phone":"+1 619 640 8456",
    "sg:postcode":"92116",
    "sg:province":"CA",
    "sg:tags":[
        "sewing",
        "alteration"
    ],
    "wof:name":"An's Alteration",
    "wof:placetype":"venue"
},
  "geometry": {"coordinates":[-117.129887,32.762827],"type":"Point"}
}