{
  "type": "Feature",
  "properties": {
    "addr:full":"12025 Susan Dr Granada Hills CA 91344",
    "addr:housenumber":"12025",
    "addr:postcode":"91344",
    "addr:street":"Susan Dr",
    "iso:country":"US",
    "sg:address":"12025 Susan Dr",
    "sg:city":"Granada Hills",
    "sg:classifiers":[
        {
            "category":"Real Estate",
            "subcategory":"Real Estate Agent",
            "type":"Services"
        }
    ],
    "sg:phone":"+1 818 363 6900",
    "sg:postcode":"91344",
    "sg:province":"CA",
    "wof:name":"Royal Hills Realty Inc",
    "wof:placetype":"venue"
},
  "geometry": {"coordinates":[-118.494668,34.28967],"type":"Point"}
}