{
  "type": "Feature",
  "properties": {
    "addr:full":"6901 Topanga Canyon Blvd Canoga Park CA 91303",
    "addr:housenumber":"6901",
    "addr:postcode":"91303",
    "addr:street":"Topanga Canyon Blvd",
    "iso:country":"US",
    "sg:address":"6901 Topanga Canyon Blvd",
    "sg:city":"Canoga Park",
    "sg:classifiers":[
        {
            "category":"Banks & Credit Unions",
            "subcategory":"Financial Services",
            "type":"Services"
        }
    ],
    "sg:phone":"+1 818 716 1597",
    "sg:postcode":"91303",
    "sg:province":"CA",
    "sg:tags":[
        "broker",
        "mortgage"
    ],
    "wof:name":"California Homes and Loan",
    "wof:placetype":"venue"
},
  "geometry": {"coordinates":[-118.606154,34.195573],"type":"Point"}
}