{
  "type": "Feature",
  "properties": {
    "addr:full":"8000 Bay Ave California City CA 93505",
    "addr:housenumber":"8000",
    "addr:postcode":"93505",
    "addr:street":"Bay Ave",
    "iso:country":"US",
    "sg:address":"8000 Bay Ave",
    "sg:city":"California City",
    "sg:classifiers":[
        {
            "category":"Travel",
            "subcategory":"Travel Agent",
            "type":"Entertainment"
        }
    ],
    "sg:phone":"+1 760 373 1259",
    "sg:postcode":"93505",
    "sg:province":"CA",
    "sg:tags":[
        "passenger",
        "agency",
        "transportation",
        "arrangement"
    ],
    "wof:name":"Travel Cnnctions-California Cy",
    "wof:placetype":"venue"
},
  "geometry": {"coordinates":[-117.98563799999999,35.124364],"type":"Point"}
}