{
  "type": "Feature",
  "properties": {
    "addr:full":"18387 State Hwy 18 Apple Valley CA 92307",
    "addr:housenumber":"18387",
    "addr:postcode":"92307",
    "addr:street":"State Hwy 18",
    "iso:country":"US",
    "sg:address":"18387 State Hwy 18",
    "sg:city":"Apple Valley",
    "sg:classifiers":[
        {
            "category":"Health Services",
            "subcategory":"Health Practitioner",
            "type":"Services"
        }
    ],
    "sg:phone":"+1 760 946 6036",
    "sg:postcode":"92307",
    "sg:province":"CA",
    "sg:tags":[
        "pathologist",
        "speech"
    ],
    "wof:name":"Lela M Kelly Speech Pthlgst",
    "wof:placetype":"venue"
},
  "geometry": {"coordinates":[-117.26300000000001,34.539827],"type":"Point"}
}