{
  "type": "Feature",
  "properties": {
    "addr:full":"690 Lee Ave San Leandro CA 94577",
    "addr:housenumber":"690",
    "addr:postcode":"94577",
    "addr:street":"Lee Ave",
    "iso:country":"US",
    "sg:address":"690 Lee Ave",
    "sg:city":"San Leandro",
    "sg:classifiers":[
        {
            "category":"Banks & Credit Unions",
            "subcategory":"Financial Services",
            "type":"Services"
        }
    ],
    "sg:phone":"+1 510 750 4119",
    "sg:postcode":"94577",
    "sg:province":"CA",
    "sg:tags":[
        "investor"
    ],
    "wof:name":"PI Investments",
    "wof:placetype":"venue"
},
  "geometry": {"coordinates":[-122.152452,37.733188],"type":"Point"}
}