{
  "type": "Feature",
  "properties": {
    "iso:country":"US",
    "sg:address":"341 Cobalt Way Ste 205",
    "sg:city":"Sunnyvale",
    "sg:classifiers":[
        {
            "category":"Wholesale",
            "subcategory":"Computers",
            "type":"Manufacturing & Wholesale Goods"
        }
    ],
    "sg:phone":"+1 408 898 4714",
    "sg:postcode":"94085",
    "sg:province":"CA",
    "wof:name":"C9 Networks Inc",
    "wof:placetype":"venue"
},
  "geometry": {"coordinates":[-121.99385700000001,37.377995],"type":"Point"}
}