{
  "type": "Feature",
  "properties": {
    "iso:country":"US",
    "sg:address":"25392 Shawnee Dr",
    "sg:city":"Lake Forest",
    "sg:classifiers":[
        {
            "category":"Freight",
            "type":"Transportation"
        }
    ],
    "sg:phone":"+1 949 250 1515",
    "sg:postcode":"92630",
    "sg:province":"CA",
    "sg:tags":[
        "packing",
        "crating"
    ],
    "sg:website":"www.advancedpacking.com",
    "wof:name":"Advanced Packing & Shipping",
    "wof:placetype":"venue"
},
  "geometry": {"coordinates":[-117.68729,33.6447],"type":"Point"}
}