{
  "type": "Feature",
  "properties": {
    "iso:country":"US",
    "sg:address":"3415 Sweet Dr",
    "sg:city":"Lafayette",
    "sg:classifiers":[
        {
            "category":"Professional",
            "type":"Services"
        }
    ],
    "sg:phone":"+1 925 284 5699",
    "sg:postcode":"94549",
    "sg:province":"CA",
    "wof:name":"Lind John",
    "wof:placetype":"venue"
},
  "geometry": {"coordinates":[-122.111311,37.880847],"type":"Point"}
}