{
  "type": "Feature",
  "properties": {
    "addr:full":"495 Arbor Road Menlo Park CA 94025",
    "addr:housenumber":"495",
    "addr:postcode":"94025",
    "addr:street":"Arbor Road",
    "iso:country":"US",
    "sg:address":"495 Arbor Road",
    "sg:city":"Menlo Park",
    "sg:classifiers":[
        {
            "category":"Professional",
            "subcategory":"Computer Services",
            "type":"Services"
        }
    ],
    "sg:phone":"+1 650 847 5739",
    "sg:postcode":"94025",
    "sg:province":"CA",
    "sg:tags":[
        "team-collaboration",
        "extranet",
        "virtual-data-room",
        "virtual-deal-room",
        "ftp-replacement",
        "large-file-transfer",
        "secure-file-transfer",
        "enterprise-2-0",
        "p2p",
        "saas"
    ],
    "sg:website":"http://www.contentcircles.com",
    "wof:name":"Content Circles",
    "wof:placetype":"venue"
},
  "geometry": {"coordinates":[-122.18168799999999,37.443284],"type":"Point"}
}