{
  "type": "Feature",
  "properties": {
    "addr:full":"10001 Maine Ave Lakeside CA 92040",
    "addr:housenumber":"10001",
    "addr:postcode":"92040",
    "addr:street":"Maine Ave",
    "iso:country":"US",
    "sg:address":"10001 Maine Ave",
    "sg:city":"Lakeside",
    "sg:classifiers":[
        {
            "category":"Restaurant",
            "type":"Food & Drink"
        }
    ],
    "sg:phone":"+1 619 390 1990",
    "sg:postcode":"92040",
    "sg:province":"CA",
    "sg:tags":[
        "shop",
        "coffee"
    ],
    "sg:website":"www.the-golden-goose.com",
    "wof:name":"Golden Goose Coffee & Antiques",
    "wof:placetype":"venue"
},
  "geometry": {"coordinates":[-116.92211,32.861409],"type":"Point"}
}