{
  "type": "Feature",
  "properties": {
    "iso:country":"US",
    "sg:address":"9980 Scripps Ranch Blvd",
    "sg:city":"San Diego",
    "sg:classifiers":[
        {
            "category":"Personal",
            "subcategory":"Beauty Salon",
            "type":"Services"
        }
    ],
    "sg:phone":"+1 858 271 9705",
    "sg:postcode":"92131",
    "sg:province":"CA",
    "wof:name":"Great Clips",
    "wof:placetype":"venue"
},
  "geometry": {"coordinates":[-117.098499,32.903025],"type":"Point"}
}