{
  "type": "Feature",
  "properties": {
    "iso:country":"US",
    "sg:address":"2830 Wear St",
    "sg:city":"Bakersfield",
    "sg:classifiers":[
        {
            "category":"Real Estate",
            "subcategory":"Surveying",
            "type":"Services"
        }
    ],
    "sg:phone":"+1 661 589 7166",
    "sg:postcode":"93308",
    "sg:province":"CA",
    "sg:tags":[
        "surveyor",
        "land",
        "engineer"
    ],
    "wof:name":"Pairish, Jim Surveying Co",
    "wof:placetype":"venue"
},
  "geometry": {"coordinates":[-119.078852,35.385377],"type":"Point"}
}