{
  "type": "Feature",
  "properties": {
    "addr:full":"20046 E Arrow Hwy Covina CA 91724",
    "addr:housenumber":"20046",
    "addr:postcode":"91724",
    "addr:street":"E Arrow Hwy",
    "iso:country":"US",
    "sg:address":"20046 E Arrow Hwy",
    "sg:city":"Covina",
    "sg:classifiers":[
        {
            "category":"Shopping",
            "subcategory":"Clothing, Apparel, & Fashions",
            "type":"Retail Goods"
        }
    ],
    "sg:phone":"+1 626 859 2808",
    "sg:postcode":"91724",
    "sg:province":"CA",
    "sg:tags":[
        "t-shirt",
        "clothing",
        "store"
    ],
    "wof:name":"Ocean Discount Tee Shirts",
    "wof:placetype":"venue"
},
  "geometry": {"coordinates":[-117.862251,34.106621],"type":"Point"}
}