{
  "type": "Feature",
  "properties": {
    "iso:country":"US",
    "sg:address":"25401 Cabot Rd",
    "sg:city":"Laguna Hills",
    "sg:classifiers":[
        {
            "category":"Professional",
            "type":"Services"
        }
    ],
    "sg:phone":"+1 949 859 8576",
    "sg:postcode":"92653",
    "sg:province":"CA",
    "sg:tags":[
        "establishment"
    ],
    "wof:name":"Linda Rogers & Assoc",
    "wof:placetype":"venue"
},
  "geometry": {"coordinates":[-117.67466,33.592351],"type":"Point"}
}