{
  "type": "Feature",
  "properties": {
    "iso:country":"US",
    "sg:address":"10025 Flower St",
    "sg:city":"Bellflower",
    "sg:classifiers":[
        {
            "category":"Government",
            "subcategory":"Court House",
            "type":"Public Place"
        }
    ],
    "sg:phone":"+1 562 804 8085",
    "sg:postcode":"90706",
    "sg:province":"CA",
    "sg:tags":[
        "legal"
    ],
    "wof:name":"District Attorney",
    "wof:placetype":"venue"
},
  "geometry": {"coordinates":[-118.120024,33.882189],"type":"Point"}
}