{
  "type": "Feature",
  "properties": {
    "iso:country":"US",
    "sg:address":"6462 Hollis St",
    "sg:city":"Emeryville",
    "sg:classifiers":[
        {
            "category":"Retail",
            "subcategory":"Laundry & Dry Cleaning",
            "type":"Services"
        }
    ],
    "sg:postcode":"94608",
    "sg:province":"CA",
    "wof:name":"Glashaus Cleaners",
    "wof:placetype":"venue"
},
  "geometry": {"coordinates":[-122.291115,37.845687],"type":"Point"}
}