{
  "type": "Feature",
  "properties": {
    "iso:country":"US",
    "sg:address":"7230 Medical Center Dr Ste 204",
    "sg:city":"West Hills",
    "sg:classifiers":[
        {
            "category":"Health Services",
            "subcategory":"Doctor",
            "type":"Services"
        }
    ],
    "sg:phone":"+1 818 346 5000",
    "sg:postcode":"91307",
    "sg:province":"CA",
    "sg:tags":[
        "obstetrician",
        "gynecologist"
    ],
    "wof:name":"Linda S. Katz, MD",
    "wof:placetype":"venue"
},
  "geometry": {"coordinates":[-118.629023,34.201676],"type":"Point"}
}