{
  "type": "Feature",
  "properties": {
    "addr:full":"2576 Castro Valley Blvd Castro Valley CA 94546",
    "addr:housenumber":"2576",
    "addr:postcode":"94546",
    "addr:street":"Castro Valley Blvd",
    "iso:country":"US",
    "sg:address":"2576 Castro Valley Blvd",
    "sg:city":"Castro Valley",
    "sg:classifiers":[
        {
            "category":"Shopping",
            "subcategory":"Bicycles & Sporting Goods",
            "type":"Retail Goods"
        },
        {
            "category":"Arena",
            "subcategory":"Sports Club",
            "type":"Entertainment"
        }
    ],
    "sg:phone":"+1 510 889 9313",
    "sg:postcode":"94546",
    "sg:province":"CA",
    "sg:website":"bapfskateboarding.com",
    "wof:name":"Bapf Skateshop",
    "wof:placetype":"venue"
},
  "geometry": {"coordinates":[-122.0882,37.693595],"type":"Point"}
}