{
  "type": "Feature",
  "properties": {
    "iso:country":"US",
    "sg:address":"657 Mission Street",
    "sg:city":"San Francisco",
    "sg:classifiers":[
        {
            "category":"Organizations",
            "subcategory":"Non-profit Organization",
            "type":"Services"
        }
    ],
    "sg:phone":"+1 800 464 6240",
    "sg:postcode":"94105",
    "sg:province":"CA",
    "sg:tags":[
        "service/non-profit",
        "community"
    ],
    "wof:name":"Arthritis Foundation-Northern Calif Chapter",
    "wof:placetype":"venue"
},
  "geometry": {"coordinates":[-122.40113700000001,37.787029],"type":"Point"}
}