{
  "type": "Feature",
  "properties": {
    "iso:country":"US",
    "sg:address":"530 Cll la Roda",
    "sg:city":"Camarillo",
    "sg:classifiers":[
        {
            "category":"Government",
            "subcategory":"Fire Station",
            "type":"Public Place"
        }
    ],
    "sg:phone":"+1 805 445 0060",
    "sg:postcode":"93010",
    "sg:province":"CA",
    "sg:tags":[
        "dry",
        "repair",
        "s",
        "protection",
        "design",
        "install",
        "wet"
    ],
    "wof:name":"Mac Fire Protection",
    "wof:placetype":"venue"
},
  "geometry": {"coordinates":[-119.06653,34.223331],"type":"Point"}
}