{
  "type": "Feature",
  "properties": {
    "addr:full":"2446 Verna Ct San Leandro CA 94577",
    "addr:housenumber":"2446",
    "addr:postcode":"94577",
    "addr:street":"Verna Ct",
    "iso:country":"US",
    "sg:address":"2446 Verna Ct",
    "sg:city":"San Leandro",
    "sg:classifiers":[
        {
            "category":"Building & Trades",
            "subcategory":"Construction",
            "type":"Services"
        }
    ],
    "sg:phone":"+1 510 667 9138",
    "sg:postcode":"94577",
    "sg:province":"CA",
    "sg:tags":[
        "tile",
        "dealer"
    ],
    "sg:website":"www.grandtile.com",
    "wof:name":"Grand Tile & Cabinet",
    "wof:placetype":"venue"
},
  "geometry": {"coordinates":[-122.17261499999999,37.707615],"type":"Point"}
}