{
  "type": "Feature",
  "properties": {
    "addr:full":"1445 S East End Ave # 101 Pomona CA 91766",
    "addr:housenumber":"1445",
    "addr:postcode":"91766",
    "addr:street":"S East End Ave # 101",
    "iso:country":"US",
    "sg:address":"1445 S East End Ave # 101",
    "sg:city":"Pomona",
    "sg:classifiers":[
        {
            "category":"Building & Trades",
            "subcategory":"Construction",
            "type":"Services"
        }
    ],
    "sg:phone":"+1 909 620 3822",
    "sg:postcode":"91766",
    "sg:province":"CA",
    "sg:tags":[
        "industrial",
        "wallcoverings-installation",
        "wallpaper",
        "contractor",
        "contractors-commercial",
        "painting"
    ],
    "wof:name":"Americal Contractors Corporation",
    "wof:placetype":"venue"
},
  "geometry": {"coordinates":[-117.723555,34.048202],"type":"Point"}
}