{
  "type": "Feature",
  "properties": {
    "addr:full":"3405 Cahuenga Blvd W Los Angeles CA 90068",
    "addr:housenumber":"3405",
    "addr:postcode":"90068",
    "addr:street":"Cahuenga Blvd W",
    "iso:country":"US",
    "sg:address":"3405 Cahuenga Blvd W",
    "sg:city":"Los Angeles",
    "sg:classifiers":[
        {
            "category":"Professional",
            "type":"Services"
        }
    ],
    "sg:phone":"+1 323 876 3444",
    "sg:postcode":"90068",
    "sg:province":"CA",
    "sg:tags":[
        "editorial"
    ],
    "wof:name":"Shapeshifter",
    "wof:placetype":"venue"
},
  "geometry": {"coordinates":[-118.35278599999999,34.131979],"type":"Point"}
}