{
  "type": "Feature",
  "properties": {
    "iso:country":"US",
    "sg:address":"962 E Lincoln St Unit A",
    "sg:city":"Banning",
    "sg:classifiers":[
        {
            "category":"Building & Trades",
            "subcategory":"Construction",
            "type":"Services"
        }
    ],
    "sg:phone":"+1 951 922 1198",
    "sg:postcode":"92220",
    "sg:province":"CA",
    "sg:tags":[
        "contractor"
    ],
    "sg:website":"garagedoorsbanning.com#cid=yelp",
    "wof:name":"Pro-Rise Garage Door Company",
    "wof:placetype":"venue"
},
  "geometry": {"coordinates":[-116.866304,33.92127],"type":"Point"}
}