{
  "type": "Feature",
  "properties": {
    "iso:country":"US",
    "sg:address":"12062 Valley View St Ste 103",
    "sg:city":"Garden Grove",
    "sg:classifiers":[
        {
            "category":"Education",
            "subcategory":"University",
            "type":"Public Place"
        }
    ],
    "sg:phone":"+1 714 230 8301",
    "sg:postcode":"92845",
    "sg:province":"CA",
    "sg:tags":[
        "college"
    ],
    "wof:name":"California State Long Beach University",
    "wof:placetype":"venue"
},
  "geometry": {"coordinates":[-118.02800000000001,33.787399],"type":"Point"}
}