{
  "type": "Feature",
  "properties": {
    "addr:full":"823 S Prairie Ave Inglewood CA 90301",
    "addr:housenumber":"823",
    "addr:postcode":"90301",
    "addr:street":"S Prairie Ave",
    "iso:country":"US",
    "sg:address":"823 S Prairie Ave",
    "sg:city":"Inglewood",
    "sg:classifiers":[
        {
            "category":"Travel",
            "subcategory":"Hotels & Motels",
            "type":"Entertainment"
        }
    ],
    "sg:phone":"+1 310 673 1919",
    "sg:postcode":"90301",
    "sg:province":"CA",
    "wof:name":"Hollywood Park Motel",
    "wof:placetype":"venue"
},
  "geometry": {"coordinates":[-118.344002,33.9533],"type":"Point"}
}