{
  "type": "Feature",
  "properties": {
    "addr:full":"1037 Abbott St Salinas CA 93901",
    "addr:housenumber":"1037",
    "addr:postcode":"93901",
    "addr:street":"Abbott St",
    "iso:country":"US",
    "sg:address":"1037 Abbott St",
    "sg:city":"Salinas",
    "sg:classifiers":[
        {
            "category":"Freight",
            "type":"Transportation"
        }
    ],
    "sg:phone":"+1 831 422 1712",
    "sg:postcode":"93901",
    "sg:province":"CA",
    "sg:tags":[
        "packing",
        "crating"
    ],
    "wof:name":"Smith Packing Inc",
    "wof:placetype":"venue"
},
  "geometry": {"coordinates":[-121.632423,36.656006],"type":"Point"}
}