{
  "type": "Feature",
  "properties": {
    "iso:country":"US",
    "sg:address":"2946 W 7th St",
    "sg:city":"Los Angeles",
    "sg:classifiers":[
        {
            "category":"Health Services",
            "subcategory":"Health Practitioner",
            "type":"Services"
        }
    ],
    "sg:phone":"+1 213 385 7078",
    "sg:postcode":"90005",
    "sg:province":"CA",
    "sg:tags":[
        "acupuncture"
    ],
    "wof:name":"Odong Chinese Herb",
    "wof:placetype":"venue"
},
  "geometry": {"coordinates":[-118.288002,34.059898],"type":"Point"}
}