{
  "type": "Feature",
  "properties": {
    "addr:full":"3673 San Fernando Rd Glendale CA 91204",
    "addr:housenumber":"3673",
    "addr:postcode":"91204",
    "addr:street":"San Fernando Rd",
    "iso:country":"US",
    "sg:address":"3673 San Fernando Rd",
    "sg:city":"Glendale",
    "sg:classifiers":[
        {
            "category":"Real Estate",
            "subcategory":"Real Estate Services",
            "type":"Services"
        }
    ],
    "sg:phone":"+1 818 956 0196",
    "sg:postcode":"91204",
    "sg:province":"CA",
    "sg:tags":[
        "management",
        "property"
    ],
    "wof:name":"Barker Management Inc.",
    "wof:placetype":"venue"
},
  "geometry": {"coordinates":[-118.253867,34.122552],"type":"Point"}
}