{
  "type": "Feature",
  "properties": {
    "iso:country":"US",
    "sg:address":"1825 Dairy Ave",
    "sg:city":"Corcoran",
    "sg:classifiers":[
        {
            "category":"Restaurant",
            "type":"Food & Drink"
        }
    ],
    "sg:phone":"+1 559 992 2356",
    "sg:postcode":"93212",
    "sg:province":"CA",
    "wof:name":"Mariscos El-Captain",
    "wof:placetype":"venue"
},
  "geometry": {"coordinates":[-119.572028,36.090357],"type":"Point"}
}