{
  "type": "Feature",
  "properties": {
    "addr:full":"2580 Fontaine Rd San Jose CA 95121",
    "addr:housenumber":"2580",
    "addr:postcode":"95121",
    "addr:street":"Fontaine Rd",
    "iso:country":"US",
    "sg:address":"2580 Fontaine Rd",
    "sg:city":"San Jose",
    "sg:classifiers":[
        {
            "category":"Real Estate",
            "subcategory":"Real Estate Operator",
            "type":"Services"
        }
    ],
    "sg:phone":"+1 408 238 0841",
    "sg:postcode":"95121",
    "sg:province":"CA",
    "sg:tags":[
        "apartment"
    ],
    "wof:name":"Casa Real Apartments",
    "wof:placetype":"venue"
},
  "geometry": {"coordinates":[-121.828802,37.31647],"type":"Point"}
}