{
  "type": "Feature",
  "properties": {
    "addr:full":"20615 Vanowen St Canoga Park CA 91306",
    "addr:postcode":"20615;91306",
    "addr:street":"Vanowen St",
    "iso:country":"US",
    "sg:address":"20615 Vanowen St",
    "sg:city":"Canoga Park",
    "sg:classifiers":[
        {
            "category":"Real Estate",
            "subcategory":"Real Estate Operator",
            "type":"Services"
        }
    ],
    "sg:phone":"+1 818 887 6808",
    "sg:postcode":"91306",
    "sg:province":"CA",
    "sg:tags":[
        "apartment"
    ],
    "wof:name":"Vanowen Apartment",
    "wof:placetype":"venue"
},
  "geometry": {"coordinates":[-118.582599,34.193907],"type":"Point"}
}