{
  "type": "Feature",
  "properties": {
    "addr:full":"21902 San Miguel St Woodland Hills CA 91364",
    "addr:housenumber":"21902",
    "addr:postcode":"91364",
    "addr:street":"San Miguel St",
    "iso:country":"US",
    "sg:address":"21902 San Miguel St",
    "sg:city":"Woodland Hills",
    "sg:classifiers":[
        {
            "category":"Building & Trades",
            "subcategory":"Construction",
            "type":"Services"
        }
    ],
    "sg:phone":"+1 818 704 0245",
    "sg:postcode":"91364",
    "sg:province":"CA",
    "sg:tags":[
        "contractor"
    ],
    "wof:name":"S P M Construction",
    "wof:placetype":"venue"
},
  "geometry": {"coordinates":[-118.604479,34.158422],"type":"Point"}
}