{
  "type": "Feature",
  "properties": {
    "iso:country":"US",
    "sg:address":"308 W Verdugo Ave",
    "sg:city":"Burbank",
    "sg:classifiers":[
        {
            "category":"Professional",
            "type":"Services"
        }
    ],
    "sg:phone":"+1 818 303 0238",
    "sg:postcode":"91502",
    "sg:province":"CA",
    "sg:tags":[
        "establishment"
    ],
    "wof:name":"Max Post",
    "wof:placetype":"venue"
},
  "geometry": {"coordinates":[-118.31439399999999,34.1707],"type":"Point"}
}