{
  "type": "Feature",
  "properties": {
    "addr:full":"1849 Bayshore Hwy Ste 210 Burlingame CA 94010",
    "addr:housenumber":"1849",
    "addr:postcode":"94010",
    "addr:street":"Bayshore Hwy Ste 210",
    "iso:country":"US",
    "sg:address":"1849 Bayshore Hwy Ste 210",
    "sg:city":"Burlingame",
    "sg:classifiers":[
        {
            "category":"Professional",
            "subcategory":"Art Services",
            "type":"Services"
        }
    ],
    "sg:phone":"+1 415 284 5090",
    "sg:postcode":"94010",
    "sg:province":"CA",
    "sg:tags":[
        "graphic",
        "designer"
    ],
    "sg:website":"http://www.kmpdesign.com",
    "wof:name":"Kmp Design",
    "wof:placetype":"venue"
},
  "geometry": {"coordinates":[-122.37383,37.603353],"type":"Point"}
}