{
  "type": "Feature",
  "properties": {
    "iso:country":"US",
    "sg:address":"457 Broadway St",
    "sg:city":"Fresno",
    "sg:classifiers":[
        {
            "category":"Home & Garden",
            "subcategory":"Home Furnishings",
            "type":"Retail Goods"
        }
    ],
    "sg:phone":"+1 559 237 1210",
    "sg:postcode":"93721",
    "sg:province":"CA",
    "sg:tags":[
        "upholstery",
        "fabric"
    ],
    "wof:name":"Graves Upholstery & Supplies",
    "wof:placetype":"venue"
},
  "geometry": {"coordinates":[-119.78509699999999,36.727514],"type":"Point"}
}