{
  "type": "Feature",
  "properties": {
    "iso:country":"US",
    "sg:address":"5681 Morningside Dr",
    "sg:city":"San Jose",
    "sg:classifiers":[
        {
            "category":"Travel",
            "subcategory":"Travel Agent",
            "type":"Entertainment"
        }
    ],
    "sg:phone":"+1 408 270 3842",
    "sg:postcode":"95138",
    "sg:province":"CA",
    "sg:tags":[
        "agency"
    ],
    "wof:name":"Siliver Creek Travel",
    "wof:placetype":"venue"
},
  "geometry": {"coordinates":[-121.769477,37.27436],"type":"Point"}
}