{
  "type": "Feature",
  "properties": {
    "iso:country":"US",
    "sg:address":"2028 Westwood Blvd",
    "sg:city":"Los Angeles",
    "sg:classifiers":[
        {
            "category":"Education",
            "subcategory":"Music School",
            "type":"Public Place"
        },
        {
            "category":"Shopping",
            "subcategory":"Music",
            "type":"Retail Goods"
        },
        {
            "category":"Shopping",
            "subcategory":"Comic Books",
            "type":"Retail Goods"
        }
    ],
    "sg:phone":"+1 310 474 8685",
    "sg:postcode":"90025",
    "sg:province":"CA",
    "sg:tags":[
        "instrument",
        "teacher",
        "dvd's",
        "musical"
    ],
    "wof:name":"Rhino Records Westwood",
    "wof:placetype":"venue"
},
  "geometry": {"coordinates":[-118.433998,34.046001],"type":"Point"}
}