{
  "type": "Feature",
  "properties": {
    "iso:country":"US",
    "sg:address":"2234 30th St",
    "sg:city":"San Diego",
    "sg:classifiers":[
        {
            "category":"Wholesale",
            "subcategory":"Plants",
            "type":"Manufacturing & Wholesale Goods"
        }
    ],
    "sg:phone":"+1 619 239 2271",
    "sg:postcode":"92104",
    "sg:province":"CA",
    "sg:tags":[
        "supply"
    ],
    "wof:name":"My Back Yard",
    "wof:placetype":"venue"
},
  "geometry": {"coordinates":[-117.13024,32.729289],"type":"Point"}
}