{
  "type": "Feature",
  "properties": {
    "addr:full":"10101 Streeter Rd Auburn CA 95602",
    "addr:housenumber":"10101",
    "addr:postcode":"ca 95602",
    "addr:street":"Streeter Rd",
    "iso:country":"US",
    "sg:address":"10101 Streeter Rd",
    "sg:city":"Auburn",
    "sg:classifiers":[
        {
            "category":"Wholesale",
            "subcategory":"Sporting Goods",
            "type":"Manufacturing & Wholesale Goods"
        }
    ],
    "sg:phone":"+1 530 268 8347",
    "sg:postcode":"95602",
    "sg:province":"CA",
    "wof:name":"Raymar Manufacturing",
    "wof:placetype":"venue"
},
  "geometry": {"coordinates":[-121.098253,39.034546],"type":"Point"}
}