{
  "type": "Feature",
  "properties": {
    "iso:country":"US",
    "sg:address":"7161 Yosemite Blvd",
    "sg:city":"Modesto",
    "sg:classifiers":[
        {
            "category":"Farming",
            "subcategory":"Crops",
            "type":"Manufacturing & Wholesale Goods"
        }
    ],
    "sg:phone":"+1 209 523 4213",
    "sg:postcode":"95357",
    "sg:province":"CA",
    "sg:tags":[
        "grove",
        "nut",
        "tree"
    ],
    "wof:name":"Lilly Nut Farms",
    "wof:placetype":"venue"
},
  "geometry": {"coordinates":[-120.86277,37.638768],"type":"Point"}
}