{
  "type": "Feature",
  "properties": {
    "iso:country":"US",
    "sg:address":"390 Rutherford Ave",
    "sg:city":"Redwood City",
    "sg:classifiers":[
        {
            "category":"Professional",
            "type":"Services"
        }
    ],
    "sg:phone":"+1 650 367 0422",
    "sg:postcode":"94061",
    "sg:province":"CA",
    "sg:tags":[
        "art",
        "restoring"
    ],
    "wof:name":"Jonathan S Fisher Master Fine",
    "wof:placetype":"venue"
},
  "geometry": {"coordinates":[-122.223584,37.455698],"type":"Point"}
}