{
  "type": "Feature",
  "properties": {
    "addr:full":"2611 San Carlos Avenue San Carlos CA 94070",
    "addr:housenumber":"2611",
    "addr:postcode":"94070",
    "addr:street":"San Carlos Avenue",
    "iso:country":"US",
    "sg:address":"2611 San Carlos Avenue",
    "sg:city":"San Carlos",
    "sg:classifiers":[
        {
            "category":"Building & Trades",
            "subcategory":"Construction",
            "type":"Services"
        }
    ],
    "sg:phone":"+1 650 593 6000",
    "sg:postcode":"94070",
    "sg:province":"CA",
    "sg:tags":[
        "contractor"
    ],
    "wof:name":"Weber Kitchens & Construction",
    "wof:placetype":"venue"
},
  "geometry": {"coordinates":[-122.282044,37.506503],"type":"Point"}
}