{
  "type": "Feature",
  "properties": {
    "addr:full":"909 23rd St Richmond CA 94804",
    "addr:housenumber":"909",
    "addr:postcode":"94804",
    "addr:street":"23Rd St",
    "iso:country":"US",
    "sg:address":"909 23rd St",
    "sg:city":"Richmond",
    "sg:classifiers":[
        {
            "category":"Autos & Motor Vehicles",
            "subcategory":"Automobile Sales",
            "type":"Retail Goods"
        }
    ],
    "sg:phone":"+1 510 235 5444",
    "sg:postcode":"94804",
    "sg:province":"CA",
    "sg:tags":[
        "car",
        "dealer"
    ],
    "wof:name":"Automax Baja Motors",
    "wof:placetype":"venue"
},
  "geometry": {"coordinates":[-122.347538,37.94534],"type":"Point"}
}