{
  "type": "Feature",
  "properties": {
    "addr:full":"113 E Hawthorne St Fallbrook CA 92028",
    "addr:housenumber":"113",
    "addr:postcode":"92028",
    "addr:street":"E Hawthorne St",
    "iso:country":"US",
    "sg:address":"113 E Hawthorne St",
    "sg:city":"Fallbrook",
    "sg:classifiers":[
        {
            "category":"Professional",
            "subcategory":"Accounting & Tax Preparation",
            "type":"Services"
        }
    ],
    "sg:phone":"+1 760 728 6425",
    "sg:postcode":"92028",
    "sg:province":"CA",
    "sg:tags":[
        "return",
        "filing"
    ],
    "wof:name":"Newton & Assoc",
    "wof:placetype":"venue"
},
  "geometry": {"coordinates":[-117.25091399999999,33.382734],"type":"Point"}
}