{
  "type": "Feature",
  "properties": {
    "addr:full":"11 Isla Vista Ln San Rafael CA 94901",
    "addr:postcode":"94901",
    "addr:street":"Isla Vista Ln",
    "iso:country":"US",
    "sg:address":"11 Isla Vista Ln",
    "sg:city":"San Rafael",
    "sg:classifiers":[
        {
            "category":"Communications",
            "type":"Services"
        }
    ],
    "sg:phone":"+1 415 339 9369",
    "sg:postcode":"94901",
    "sg:province":"CA",
    "sg:tags":[
        "communication"
    ],
    "wof:name":"High Octane Communications",
    "wof:placetype":"venue"
},
  "geometry": {"coordinates":[-122.49942299999999,37.963255],"type":"Point"}
}