{
  "type": "Feature",
  "properties": {
    "iso:country":"US",
    "sg:address":"3000 Capitol Ave",
    "sg:city":"Sacramento",
    "sg:classifiers":[
        {
            "category":"Retail",
            "subcategory":"Auto Repair",
            "type":"Services"
        }
    ],
    "sg:phone":"+1 916 732 4346",
    "sg:postcode":"95816",
    "sg:province":"CA",
    "sg:tags":[
        "automobile",
        "lubrication"
    ],
    "sg:website":"www.jiffylubeca.com",
    "wof:name":"Jiffy Lube",
    "wof:placetype":"venue"
},
  "geometry": {"coordinates":[-121.46700300000001,38.569599],"type":"Point"}
}