{
  "type": "Feature",
  "properties": {
    "iso:country":"US",
    "sg:address":"15000 Whirlaway Ln",
    "sg:city":"Chino Hills",
    "sg:classifiers":[
        {
            "category":"Education",
            "subcategory":"School",
            "type":"Public Place"
        }
    ],
    "sg:phone":"+1 909 393 4087",
    "sg:postcode":"91709",
    "sg:province":"CA",
    "sg:website":"www.chino.k12.ca.us",
    "wof:name":"Glenmeade Elementary School",
    "wof:placetype":"venue"
},
  "geometry": {"coordinates":[-117.72122899999999,33.980498],"type":"Point"}
}