{
  "type": "Feature",
  "properties": {
    "addr:full":"1587 15th St #402 San Francisco CA 94103",
    "addr:housenumber":"1587",
    "addr:postcode":"94103",
    "addr:street":"15Th St # 402",
    "iso:country":"US",
    "sg:address":"1587 15th St #402",
    "sg:city":"San Francisco",
    "sg:classifiers":[
        {
            "category":"Home & Garden",
            "subcategory":"Carpets & Floor Coverings",
            "type":"Retail Goods"
        }
    ],
    "sg:phone":"+1 510 589 1930",
    "sg:postcode":"94103",
    "sg:province":"CA",
    "sg:tags":[
        "flooring"
    ],
    "wof:name":"Team Ted Tile",
    "wof:placetype":"venue"
},
  "geometry": {"coordinates":[-122.419511,37.766702],"type":"Point"}
}