{
  "type": "Feature",
  "properties": {
    "addr:full":"36730 Hinkley Rd Hinkley CA 92347",
    "addr:postcode":"36730;92347",
    "addr:street":"Hinkley Rd",
    "iso:country":"US",
    "sg:address":"36730 Hinkley Rd",
    "sg:city":"Hinkley",
    "sg:classifiers":[
        {
            "category":"Home & Garden",
            "subcategory":"Building Materials",
            "type":"Retail Goods"
        }
    ],
    "sg:phone":"+1 760 253 2688",
    "sg:postcode":"92347",
    "sg:province":"CA",
    "sg:tags":[
        "carpentry",
        "contractor"
    ],
    "wof:name":"Woodshed Enterprises",
    "wof:placetype":"venue"
},
  "geometry": {"coordinates":[-117.18909499999999,34.916975],"type":"Point"}
}