{
  "type": "Feature",
  "properties": {
    "addr:full":"6145 el Cajon Blvd San Diego CA 92115",
    "addr:housenumber":"6145",
    "addr:postcode":"92115",
    "addr:street":"El Cajon Blvd",
    "iso:country":"US",
    "sg:address":"6145 el Cajon Blvd",
    "sg:city":"San Diego",
    "sg:classifiers":[
        {
            "category":"Shopping",
            "subcategory":"Gifts & Souvenirs",
            "type":"Retail Goods"
        }
    ],
    "sg:phone":"+1 619 286 6007",
    "sg:postcode":"92115",
    "sg:province":"CA",
    "sg:tags":[
        "shop"
    ],
    "wof:name":"Dani's Hallmark Shop",
    "wof:placetype":"venue"
},
  "geometry": {"coordinates":[-117.065788,32.761926],"type":"Point"}
}