{
  "type": "Feature",
  "properties": {
    "addr:full":"710 W Valencia Mesa Dr Fullerton CA 92835",
    "addr:housenumber":"710",
    "addr:postcode":"92835",
    "addr:street":"W Valencia Mesa Dr",
    "iso:country":"US",
    "sg:address":"710 W Valencia Mesa Dr",
    "sg:city":"Fullerton",
    "sg:classifiers":[
        {
            "category":"Professional",
            "subcategory":"Management & Consulting",
            "type":"Services"
        }
    ],
    "sg:phone":"+1 714 335 2115",
    "sg:postcode":"92835",
    "sg:province":"CA",
    "sg:tags":[
        "party",
        "planning"
    ],
    "wof:name":"Mitzvah Magic",
    "wof:placetype":"venue"
},
  "geometry": {"coordinates":[-117.93756399999999,33.888036],"type":"Point"}
}