{
  "type": "Feature",
  "properties": {
    "iso:country":"US",
    "sg:address":"72-191 Hwy 111",
    "sg:city":"Palm Desert",
    "sg:classifiers":[
        {
            "category":"Restaurant",
            "type":"Food & Drink"
        },
        {
            "category":"Recreation",
            "subcategory":"Dance Hall",
            "type":"Entertainment"
        }
    ],
    "sg:phone":"+1 760 773 1711",
    "sg:postcode":"92260",
    "sg:province":"CA",
    "sg:tags":[
        "club"
    ],
    "sg:website":"www.clubsouthbeach.net",
    "wof:name":"South Beach Restaurant & Nightclub",
    "wof:placetype":"venue"
},
  "geometry": {"coordinates":[-116.382597,33.722008],"type":"Point"}
}