{
  "type": "Feature",
  "properties": {
    "iso:country":"US",
    "sg:address":"255 S Rengstorff Ave",
    "sg:city":"Mountain View",
    "sg:classifiers":[
        {
            "category":"Wholesale",
            "subcategory":"Groceries",
            "type":"Manufacturing & Wholesale Goods"
        }
    ],
    "sg:phone":"+1 650 969 7810",
    "sg:postcode":"94040",
    "sg:province":"CA",
    "wof:name":"Ed Gees Distributing Co",
    "wof:placetype":"venue"
},
  "geometry": {"coordinates":[-122.09848,37.40135],"type":"Point"}
}