{
  "type": "Feature",
  "properties": {
    "addr:full":"916 N Western Ave San Pedro CA 90732",
    "addr:housenumber":"916",
    "addr:postcode":"90732",
    "addr:street":"N Western Ave",
    "iso:country":"US",
    "sg:address":"916 N Western Ave",
    "sg:city":"San Pedro",
    "sg:classifiers":[
        {
            "category":"Landmark",
            "subcategory":"Tourist Information",
            "type":"Public Place"
        }
    ],
    "sg:phone":"+1 310 832 3428",
    "sg:postcode":"90732",
    "sg:province":"CA",
    "sg:tags":[
        "tour"
    ],
    "sg:website":"www.fiatpilgrimages.net",
    "wof:name":"Fiat Pilgrimages Inc",
    "wof:placetype":"venue"
},
  "geometry": {"coordinates":[-118.308806,33.751263],"type":"Point"}
}