{
  "type": "Feature",
  "properties": {
    "iso:country":"US",
    "sg:address":"360 N Fortuna Blvd",
    "sg:city":"Fortuna",
    "sg:classifiers":[
        {
            "category":"Home & Garden",
            "subcategory":"Building Materials",
            "type":"Retail Goods"
        }
    ],
    "sg:phone":"+1 707 725 3287",
    "sg:postcode":"95540",
    "sg:province":"CA",
    "sg:tags":[
        "glass",
        "window",
        "plate"
    ],
    "wof:name":"George's Glass",
    "wof:placetype":"venue"
},
  "geometry": {"coordinates":[-124.146699,40.59553],"type":"Point"}
}