{
  "type": "Feature",
  "properties": {
    "addr:full":"575 Via Cantebria Encinitas CA 92024",
    "addr:housenumber":"575",
    "addr:postcode":"92024",
    "addr:street":"Via Cantebria",
    "iso:country":"US",
    "sg:address":"575 Via Cantebria",
    "sg:city":"Encinitas",
    "sg:classifiers":[
        {
            "category":"Professional",
            "subcategory":"Business Services",
            "type":"Services"
        }
    ],
    "sg:phone":"+1 760 436 1989",
    "sg:postcode":"92024",
    "sg:province":"CA",
    "wof:name":"Mercy Housing California",
    "wof:placetype":"venue"
},
  "geometry": {"coordinates":[-117.26761999999999,33.054788],"type":"Point"}
}