{
  "type": "Feature",
  "properties": {
    "iso:country":"US",
    "sg:address":"5348 Topanga Canyon Blvd",
    "sg:city":"Woodland Hills",
    "sg:classifiers":[
        {
            "category":"Health Services",
            "subcategory":"Health Practitioner",
            "type":"Services"
        }
    ],
    "sg:phone":"+1 818 347 8120",
    "sg:postcode":"91364",
    "sg:province":"CA",
    "sg:tags":[
        "hypnotist"
    ],
    "wof:name":"Susan Shaw",
    "wof:placetype":"venue"
},
  "geometry": {"coordinates":[-118.605682,34.167036],"type":"Point"}
}