{
  "type": "Feature",
  "properties": {
    "iso:country":"US",
    "sg:address":"11051 Cobblestone Dr",
    "sg:city":"Rancho Cordova",
    "sg:classifiers":[
        {
            "category":"Professional",
            "subcategory":"Advertising",
            "type":"Services"
        }
    ],
    "sg:phone":"+1 916 984 6380",
    "sg:postcode":"95670",
    "sg:province":"CA",
    "wof:name":"PRETTYBLOOMS.COM",
    "wof:placetype":"venue"
},
  "geometry": {"coordinates":[-121.27395,38.612518],"type":"Point"}
}