{
  "type": "Feature",
  "properties": {
    "addr:full":"13475 Danielson St Poway CA 92064",
    "addr:housenumber":"13475",
    "addr:postcode":"ca 92064",
    "addr:street":"Danielson St",
    "iso:country":"US",
    "sg:address":"13475 Danielson St",
    "sg:city":"Poway",
    "sg:classifiers":[
        {
            "category":"Professional",
            "subcategory":"Engineering",
            "type":"Services"
        }
    ],
    "sg:phone":"+1 858 375 5009",
    "sg:postcode":"92064",
    "sg:province":"CA",
    "sg:tags":[
        "energy",
        "management",
        "engineer"
    ],
    "wof:name":"Powercast",
    "wof:placetype":"venue"
},
  "geometry": {"coordinates":[-117.037885,32.939868],"type":"Point"}
}