{
  "type": "Feature",
  "properties": {
    "iso:country":"US",
    "sg:address":"1224 139th Ave",
    "sg:city":"San Leandro",
    "sg:classifiers":[
        {
            "category":"Building & Trades",
            "subcategory":"Construction",
            "type":"Services"
        }
    ],
    "sg:phone":"+1 510 614 1067",
    "sg:postcode":"94578",
    "sg:province":"CA",
    "sg:tags":[
        "contractor"
    ],
    "wof:name":"Jesse Roofing",
    "wof:placetype":"venue"
},
  "geometry": {"coordinates":[-122.140429,37.713173],"type":"Point"}
}