{
  "type": "Feature",
  "properties": {
    "addr:full":"499 W Orange Show Rd San Bernardino CA 92408",
    "addr:housenumber":"499",
    "addr:postcode":"92408",
    "addr:street":"W Orange Show Rd",
    "iso:country":"US",
    "sg:address":"499 W Orange Show Rd",
    "sg:city":"San Bernardino",
    "sg:phone":"+1 704 540 2042",
    "sg:postcode":"92408",
    "sg:province":"CA",
    "wof:name":"Citysearch.com",
    "wof:placetype":"venue"
},
  "geometry": {"coordinates":[-117.294141,34.079545],"type":"Point"}
}