{
  "type": "Feature",
  "properties": {
    "addr:full":"3336 Bradshaw Road Sacramento CA 95827",
    "addr:housenumber":"3336",
    "addr:postcode":"95827",
    "addr:street":"Bradshaw Road",
    "iso:country":"US",
    "sg:address":"3336 Bradshaw Road",
    "sg:city":"Sacramento",
    "sg:classifiers":[
        {
            "category":"Food & Beverages",
            "subcategory":"Groceries & Convenience Stores",
            "type":"Retail Goods"
        }
    ],
    "sg:phone":"+1 916 369 9740",
    "sg:postcode":"95827",
    "sg:province":"CA",
    "wof:name":"Convenience Aquisition Company",
    "wof:placetype":"venue"
},
  "geometry": {"coordinates":[-121.336277,38.563146],"type":"Point"}
}