{
  "type": "Feature",
  "properties": {
    "addr:full":"2312 Arden Way Sacramento CA 95825",
    "addr:housenumber":"2312",
    "addr:postcode":"95825",
    "addr:street":"Arden Way",
    "iso:country":"US",
    "sg:address":"2312 Arden Way",
    "sg:city":"Sacramento",
    "sg:classifiers":[
        {
            "category":"Fast Food",
            "type":"Food & Drink"
        }
    ],
    "sg:phone":"+1 916 927 2231",
    "sg:postcode":"95825",
    "sg:province":"CA",
    "wof:name":"Kfc-A & W",
    "wof:placetype":"venue"
},
  "geometry": {"coordinates":[-121.410004,38.5961],"type":"Point"}
}