{
  "type": "Feature",
  "properties": {
    "addr:full":"184 W 3rd St Pomona CA 91766",
    "addr:housenumber":"184",
    "addr:postcode":"91766",
    "addr:street":"W 3Rd St",
    "iso:country":"US",
    "sg:address":"184 W 3rd St",
    "sg:city":"Pomona",
    "sg:classifiers":[
        {
            "category":"Professional",
            "subcategory":"Business Services",
            "type":"Services"
        }
    ],
    "sg:phone":"+1 909 981 4211",
    "sg:postcode":"91766",
    "sg:province":"CA",
    "wof:name":"M B & Assoc",
    "wof:placetype":"venue"
},
  "geometry": {"coordinates":[-117.750426,34.056852],"type":"Point"}
}