{
  "type": "Feature",
  "properties": {
    "iso:country":"US",
    "sg:address":"14608 Carmenita Rd",
    "sg:city":"Norwalk",
    "sg:classifiers":[
        {
            "category":"Wholesale",
            "subcategory":"Electrical",
            "type":"Manufacturing & Wholesale Goods"
        }
    ],
    "sg:phone":"+1 562 802 5250",
    "sg:postcode":"90650",
    "sg:province":"CA",
    "sg:tags":[
        "light",
        "tube",
        "fixture",
        "equipment",
        "lighting",
        "bulb"
    ],
    "wof:name":"Crown Lighting",
    "wof:placetype":"venue"
},
  "geometry": {"coordinates":[-118.046997,33.898701],"type":"Point"}
}