{
  "type": "Feature",
  "properties": {
    "addr:full":"3602 E Orangeburg Ave Modesto CA 95355",
    "addr:housenumber":"3602",
    "addr:postcode":"ca 95355",
    "addr:street":"E Orangeburg Ave",
    "iso:country":"US",
    "sg:address":"3602 E Orangeburg Ave",
    "sg:city":"Modesto",
    "sg:classifiers":[
        {
            "category":"Professional",
            "type":"Services"
        }
    ],
    "sg:phone":"+1 209 526 8934",
    "sg:postcode":"95355",
    "sg:province":"CA",
    "sg:tags":[
        "establishment"
    ],
    "wof:name":"Kannous Comfort Care",
    "wof:placetype":"venue"
},
  "geometry": {"coordinates":[-120.92734299999999,37.663521],"type":"Point"}
}