{
  "type": "Feature",
  "properties": {
    "iso:country":"US",
    "sg:address":"2627 Town and Country Village",
    "sg:city":"Sacramento",
    "sg:classifiers":[
        {
            "category":"Restaurant",
            "type":"Food & Drink"
        }
    ],
    "sg:phone":"+1 916 977 1877",
    "sg:postcode":"95821",
    "sg:province":"CA",
    "wof:name":"Chateau by A Shot of Class",
    "wof:placetype":"venue"
},
  "geometry": {"coordinates":[-121.400813,38.618311],"type":"Point"}
}