{
  "type": "Feature",
  "properties": {
    "iso:country":"US",
    "sg:address":"256 W Highland Ave",
    "sg:city":"San Bernardino",
    "sg:classifiers":[
        {
            "category":"Shopping",
            "subcategory":"Jewelry",
            "type":"Retail Goods"
        }
    ],
    "sg:phone":"+1 909 475 1253",
    "sg:postcode":"92405",
    "sg:province":"CA",
    "sg:tags":[
        "jeweler"
    ],
    "wof:name":"Pawn Co Jewelry & Loan",
    "wof:placetype":"venue"
},
  "geometry": {"coordinates":[-117.289559,34.136043],"type":"Point"}
}