{
  "type": "Feature",
  "properties": {
    "addr:full":"866 Elise St Chula Vista CA 91911",
    "addr:housenumber":"866",
    "addr:postcode":"91911",
    "addr:street":"Elise St",
    "iso:country":"US",
    "sg:address":"866 Elise St",
    "sg:city":"Chula Vista",
    "sg:classifiers":[
        {
            "category":"Professional",
            "type":"Services"
        }
    ],
    "sg:phone":"+1 619 575 2043",
    "sg:postcode":"91911",
    "sg:province":"CA",
    "wof:name":"A Plus Compressor Svc",
    "wof:placetype":"venue"
},
  "geometry": {"coordinates":[-117.09072500000001,32.599642],"type":"Point"}
}