{
  "type": "Feature",
  "properties": {
    "iso:country":"US",
    "sg:address":"100 Corson St",
    "sg:city":"Pasadena",
    "sg:classifiers":[
        {
            "category":"Professional",
            "subcategory":"Lawyer & Legal Services",
            "type":"Services"
        }
    ],
    "sg:phone":"+1 626 793 0300",
    "sg:postcode":"91103",
    "sg:province":"CA",
    "sg:tags":[
        "attorney"
    ],
    "wof:name":"Robert L Toms Sr",
    "wof:placetype":"venue"
},
  "geometry": {"coordinates":[-118.148111,34.151168],"type":"Point"}
}