{
  "type": "Feature",
  "properties": {
    "iso:country":"US",
    "sg:address":"201 N Bush St",
    "sg:city":"Santa Ana",
    "sg:classifiers":[
        {
            "category":"Shopping",
            "type":"Retail Goods"
        }
    ],
    "sg:phone":"+1 714 623 3139",
    "sg:postcode":"92701",
    "sg:province":"CA",
    "sg:tags":[
        "art",
        "gallery",
        "dealer"
    ],
    "wof:name":"Cent Gallery",
    "wof:placetype":"venue"
},
  "geometry": {"coordinates":[-117.86661,33.74713],"type":"Point"}
}