{
  "type": "Feature",
  "properties": {
    "addr:full":"28871 Hedgerow Mission Viejo CA 92692",
    "addr:housenumber":"28871",
    "addr:postcode":"92692",
    "addr:street":"Hedgerow",
    "iso:country":"US",
    "sg:address":"28871 Hedgerow",
    "sg:city":"Mission Viejo",
    "sg:classifiers":[
        {
            "category":"Professional",
            "subcategory":"Lawyer & Legal Services",
            "type":"Services"
        }
    ],
    "sg:phone":"+1 949 420 0600",
    "sg:postcode":"92692",
    "sg:province":"CA",
    "sg:tags":[
        "attorney"
    ],
    "wof:name":"Arnold H Wurman Law Offices",
    "wof:placetype":"venue"
},
  "geometry": {"coordinates":[-117.628272,33.643512],"type":"Point"}
}