{
  "type": "Feature",
  "properties": {
    "iso:country":"US",
    "sg:address":"2200 Sand Creek Rd",
    "sg:city":"Brentwood",
    "sg:classifiers":[
        {
            "category":"Real Estate",
            "subcategory":"Real Estate Services",
            "type":"Services"
        }
    ],
    "sg:phone":"+1 925 634 8811",
    "sg:postcode":"94513",
    "sg:province":"CA",
    "wof:name":"Mann Jason rltr",
    "wof:placetype":"venue"
},
  "geometry": {"coordinates":[-121.734081,37.943342],"type":"Point"}
}