{
  "type": "Feature",
  "properties": {
    "addr:full":"125 W Pine St Stockton CA 95204",
    "addr:housenumber":"125",
    "addr:postcode":"95204",
    "addr:street":"W Pine St",
    "iso:country":"US",
    "sg:address":"125 W Pine St",
    "sg:city":"Stockton",
    "sg:classifiers":[
        {
            "category":"Professional",
            "subcategory":"Management & Consulting",
            "type":"Services"
        }
    ],
    "sg:phone":"+1 209 948 3307",
    "sg:postcode":"95204",
    "sg:province":"CA",
    "sg:tags":[
        "consultant",
        "educational"
    ],
    "wof:name":"Kevin Clark Eductional",
    "wof:placetype":"venue"
},
  "geometry": {"coordinates":[-121.30022,37.972003],"type":"Point"}
}