{
  "type": "Feature",
  "properties": {
    "iso:country":"US",
    "sg:address":"1180 Alamo Pintado Rd",
    "sg:city":"Solvang",
    "sg:classifiers":[
        {
            "category":"Communications",
            "subcategory":"Film & Video Production",
            "type":"Services"
        }
    ],
    "sg:phone":"+1 805 686 1010",
    "sg:postcode":"93463",
    "sg:province":"CA",
    "sg:tags":[
        "taping"
    ],
    "wof:name":"Classic Video Productions",
    "wof:placetype":"venue"
},
  "geometry": {"coordinates":[-120.121055,34.617802],"type":"Point"}
}