{
  "type": "Feature",
  "properties": {
    "addr:full":"18850 Norwalk Blvd Artesia CA 90701",
    "addr:housenumber":"18850",
    "addr:postcode":"90701",
    "addr:street":"Norwalk Blvd",
    "iso:country":"US",
    "sg:address":"18850 Norwalk Blvd",
    "sg:city":"Artesia",
    "sg:classifiers":[
        {
            "category":"Shopping",
            "subcategory":"Books",
            "type":"Retail Goods"
        }
    ],
    "sg:phone":"+1 562 865 8882",
    "sg:postcode":"90701",
    "sg:province":"CA",
    "sg:tags":[
        "bookstore"
    ],
    "wof:name":"V W Culture Co",
    "wof:placetype":"venue"
},
  "geometry": {"coordinates":[-118.07199900000001,33.8606],"type":"Point"}
}