{
  "type": "Feature",
  "properties": {
    "addr:full":"359 White Sands Dr Vacaville CA 95687",
    "addr:housenumber":"359",
    "addr:postcode":"95687",
    "addr:street":"White Sands Dr",
    "iso:country":"US",
    "sg:address":"359 White Sands Dr",
    "sg:city":"Vacaville",
    "sg:classifiers":[
        {
            "category":"Banks & Credit Unions",
            "subcategory":"Investment Brokerage",
            "type":"Services"
        }
    ],
    "sg:phone":"+1 707 448 9007",
    "sg:postcode":"95687",
    "sg:province":"CA",
    "sg:tags":[
        "security"
    ],
    "wof:name":"Financial Network Inv Corp",
    "wof:placetype":"venue"
},
  "geometry": {"coordinates":[-121.936198,38.370578],"type":"Point"}
}