{
  "type": "Feature",
  "properties": {
    "addr:full":"2809 Fulton Avenue Sacramento CA 95821",
    "addr:housenumber":"2809",
    "addr:postcode":"95821",
    "addr:street":"Fulton Avenue",
    "iso:country":"US",
    "sg:address":"2809 Fulton Avenue",
    "sg:city":"Sacramento",
    "sg:classifiers":[
        {
            "category":"Retail",
            "subcategory":"Auto Repair",
            "type":"Services"
        }
    ],
    "sg:phone":"+1 916 481 2240",
    "sg:postcode":"95821",
    "sg:province":"CA",
    "sg:website":"marcomuffler.com/",
    "wof:name":"Marco Muffler",
    "wof:placetype":"venue"
},
  "geometry": {"coordinates":[-121.4016,38.616454],"type":"Point"}
}