{
  "type": "Feature",
  "properties": {
    "addr:full":"2310 N 1st St San Jose CA 95131",
    "addr:housenumber":"2310",
    "addr:postcode":"95131",
    "addr:street":"N 1St St",
    "iso:country":"US",
    "sg:address":"2310 N 1st St",
    "sg:city":"San Jose",
    "sg:classifiers":[
        {
            "category":"Professional",
            "type":"Services"
        }
    ],
    "sg:phone":"+1 408 993 4700",
    "sg:postcode":"95131",
    "sg:province":"CA",
    "wof:name":"County of Santa Clara War",
    "wof:placetype":"venue"
},
  "geometry": {"coordinates":[-121.92516500000001,37.382647],"type":"Point"}
}