{
  "type": "Feature",
  "properties": {
    "addr:full":"713 S Blossom Rd Waterford CA 95386",
    "addr:housenumber":"713",
    "addr:postcode":"95386",
    "addr:street":"S Blossom Rd",
    "iso:country":"US",
    "sg:address":"713 S Blossom Rd",
    "sg:city":"Waterford",
    "sg:classifiers":[
        {
            "category":"Farming",
            "subcategory":"Crops",
            "type":"Manufacturing & Wholesale Goods"
        }
    ],
    "sg:phone":"+1 209 874 2498",
    "sg:postcode":"95386",
    "sg:province":"CA",
    "sg:tags":[
        "grove",
        "nut",
        "tree"
    ],
    "wof:name":"Samuel Tyson",
    "wof:placetype":"venue"
},
  "geometry": {"coordinates":[-120.79669699999999,37.631395],"type":"Point"}
}