{
  "type": "Feature",
  "properties": {
    "addr:full":"11997 Magnolia Ave Riverside CA 92503",
    "addr:housenumber":"11997",
    "addr:postcode":"92503",
    "addr:street":"Magnolia Ave",
    "iso:country":"US",
    "sg:address":"11997 Magnolia Ave",
    "sg:city":"Riverside",
    "sg:classifiers":[
        {
            "category":"Building & Trades",
            "subcategory":"Landscaping Services",
            "type":"Services"
        }
    ],
    "sg:phone":"+1 951 689 6377",
    "sg:postcode":"92503",
    "sg:province":"CA",
    "sg:tags":[
        "landscape"
    ],
    "wof:name":"Barnett Eric R & Lndscpe Archt",
    "wof:placetype":"venue"
},
  "geometry": {"coordinates":[-117.49691,33.891949],"type":"Point"}
}