{
  "type": "Feature",
  "properties": {
    "addr:full":"22222 Foothill Blvd #601 Hayward CA 94541",
    "addr:housenumber":"22222;601",
    "addr:postcode":"94541",
    "addr:street":"Foothill Blvd #",
    "iso:country":"US",
    "sg:address":"22222 Foothill Blvd #601",
    "sg:city":"Hayward",
    "sg:classifiers":[
        {
            "category":"Restaurant",
            "type":"Food & Drink"
        }
    ],
    "sg:phone":"+1 510 886 2244",
    "sg:postcode":"94541",
    "sg:province":"CA",
    "sg:tags":[
        "breakfast",
        "brunch",
        "diner"
    ],
    "sg:website":"www.ihop.com/",
    "wof:name":"IHOP - International House of Pancakes",
    "wof:placetype":"venue"
},
  "geometry": {"coordinates":[-122.08508500000001,37.680693],"type":"Point"}
}