{
  "type": "Feature",
  "properties": {
    "addr:full":"19858 Jolora Ave Corona CA 92881",
    "addr:housenumber":"19858",
    "addr:postcode":"92881",
    "addr:street":"Jolora Ave",
    "iso:country":"US",
    "sg:address":"19858 Jolora Ave",
    "sg:city":"Corona",
    "sg:classifiers":[
        {
            "category":"Freight",
            "type":"Transportation"
        }
    ],
    "sg:phone":"+1 951 734 1712",
    "sg:postcode":"92881",
    "sg:province":"CA",
    "sg:tags":[
        "operator",
        "trucking"
    ],
    "wof:name":"Marc England Trucking",
    "wof:placetype":"venue"
},
  "geometry": {"coordinates":[-117.519075,33.829443],"type":"Point"}
}