{
  "type": "Feature",
  "properties": {
    "iso:country":"US",
    "sg:address":"135 S Park Ave",
    "sg:city":"San Francisco",
    "sg:classifiers":[
        {
            "category":"Professional",
            "subcategory":"Art Services",
            "type":"Services"
        }
    ],
    "sg:phone":"+1 415 546 1701",
    "sg:postcode":"94107",
    "sg:province":"CA",
    "sg:tags":[
        "graphic",
        "designer"
    ],
    "sg:website":"www.stevenleedesign.com",
    "wof:name":"Steven Lee Design",
    "wof:placetype":"venue"
},
  "geometry": {"coordinates":[-122.39418499999999,37.781103],"type":"Point"}
}