{
  "type": "Feature",
  "properties": {
    "iso:country":"US",
    "sg:address":"2377 Brookhill Dr",
    "sg:city":"Camarillo",
    "sg:classifiers":[
        {
            "category":"Real Estate",
            "subcategory":"Real Estate Services",
            "type":"Services"
        },
        {
            "category":"Real Estate",
            "subcategory":"Real Estate Agent",
            "type":"Services"
        }
    ],
    "sg:phone":"+1 805 947 8668",
    "sg:postcode":"93010",
    "sg:province":"CA",
    "sg:tags":[
        "buyer",
        "broker"
    ],
    "wof:name":"Keller Williams Realty",
    "wof:placetype":"venue"
},
  "geometry": {"coordinates":[-119.03963,34.242335],"type":"Point"}
}