{
  "type": "Feature",
  "properties": {
    "iso:country":"US",
    "sg:address":"1536 Encinitas Blvd",
    "sg:city":"Encinitas",
    "sg:classifiers":[
        {
            "category":"Health Services",
            "subcategory":"Optometrist",
            "type":"Services"
        }
    ],
    "sg:phone":"+1 760 942 9785",
    "sg:postcode":"92024",
    "sg:province":"CA",
    "wof:name":"Torgerson Duane R OD & Laser Associates",
    "wof:placetype":"venue"
},
  "geometry": {"coordinates":[-117.253998,33.045601],"type":"Point"}
}