{
  "type": "Feature",
  "properties": {
    "iso:country":"US",
    "sg:address":"12388 Brookhurst St",
    "sg:city":"Garden Grove",
    "sg:classifiers":[
        {
            "category":"Health Services",
            "subcategory":"Doctor",
            "type":"Services"
        }
    ],
    "sg:phone":"+1 714 638 2101",
    "sg:postcode":"92840",
    "sg:province":"CA",
    "sg:tags":[
        "surgeon",
        "oral"
    ],
    "wof:name":"Nguyen Kimanh Thi DDS",
    "wof:placetype":"venue"
},
  "geometry": {"coordinates":[-117.959,33.781399],"type":"Point"}
}