{
  "type": "Feature",
  "properties": {
    "addr:full":"18010 Crenshaw Blvd Torrance CA 90504",
    "addr:housenumber":"18010",
    "addr:postcode":"90504",
    "addr:street":"Crenshaw Blvd",
    "iso:country":"US",
    "sg:address":"18010 Crenshaw Blvd",
    "sg:city":"Torrance",
    "sg:classifiers":[
        {
            "category":"Travel",
            "subcategory":"Travel Agent",
            "type":"Entertainment"
        }
    ],
    "sg:phone":"+1 310 516 1253",
    "sg:postcode":"90504",
    "sg:province":"CA",
    "sg:tags":[
        "agency"
    ],
    "wof:name":"Age of Travel",
    "wof:placetype":"venue"
},
  "geometry": {"coordinates":[-118.326393,33.865617],"type":"Point"}
}