{
  "type": "Feature",
  "properties": {
    "addr:full":"1130 E William Street San Jose CA 95116",
    "addr:housenumber":"1130",
    "addr:postcode":"95116",
    "addr:street":"E William Street",
    "iso:country":"US",
    "sg:address":"1130 E William Street",
    "sg:city":"San Jose",
    "sg:classifiers":[
        {
            "category":"Bars & Pubs",
            "subcategory":"Nightclub",
            "type":"Food & Drink"
        }
    ],
    "sg:phone":"+1 408 292 0262",
    "sg:postcode":"95116",
    "sg:province":"CA",
    "sg:tags":[
        "nightlife"
    ],
    "wof:name":"Discoteca Nuevo Indito",
    "wof:placetype":"venue"
},
  "geometry": {"coordinates":[-121.863388,37.340444],"type":"Point"}
}