{
  "type": "Feature",
  "properties": {
    "iso:country":"US",
    "sg:address":"2929 Health Center Drive",
    "sg:city":"San Diego",
    "sg:classifiers":[
        {
            "category":"Health Services",
            "subcategory":"Doctor",
            "type":"Services"
        },
        {
            "category":"Health Services",
            "subcategory":"Hospital",
            "type":"Services"
        },
        {
            "category":"Shopping",
            "subcategory":"Pharmacy",
            "type":"Retail Goods"
        }
    ],
    "sg:phone":"+1 858 939 6531",
    "sg:postcode":"92123",
    "sg:province":"CA",
    "sg:tags":[
        "drugstore"
    ],
    "wof:name":"Person John MD",
    "wof:placetype":"venue"
},
  "geometry": {"coordinates":[-117.156991,32.79658],"type":"Point"}
}