{
  "type": "Feature",
  "properties": {
    "iso:country":"US",
    "sg:address":"2920 Middlefield Rd",
    "sg:city":"Redwood City",
    "sg:classifiers":[
        {
            "category":"Autos & Motor Vehicles",
            "subcategory":"Automobile Sales",
            "type":"Retail Goods"
        }
    ],
    "sg:phone":"+1 650 306 9049",
    "sg:postcode":"94063",
    "sg:province":"CA",
    "sg:tags":[
        "used"
    ],
    "wof:name":"Gonzalez Auto Sales",
    "wof:placetype":"venue"
},
  "geometry": {"coordinates":[-122.208113,37.474524],"type":"Point"}
}