{
  "type": "Feature",
  "properties": {
    "iso:country":"US",
    "sg:address":"15024 Jackson Rd",
    "sg:city":"Sloughhouse",
    "sg:classifiers":[
        {
            "category":"Farming",
            "subcategory":"Livestock Farm",
            "type":"Manufacturing & Wholesale Goods"
        }
    ],
    "sg:phone":"+1 916 354 2884",
    "sg:postcode":"95683",
    "sg:province":"CA",
    "sg:tags":[
        "ranch"
    ],
    "wof:name":"Gold Spring Angus Ranch",
    "wof:placetype":"venue"
},
  "geometry": {"coordinates":[-121.090548,38.49102],"type":"Point"}
}