{
  "type": "Feature",
  "properties": {
    "iso:country":"US",
    "sg:address":"1164 Euclid Ave",
    "sg:city":"Berkeley",
    "sg:classifiers":[
        {
            "category":"Health Services",
            "subcategory":"Health Practitioner",
            "type":"Services"
        },
        {
            "category":"Organizations",
            "subcategory":"Community Association",
            "type":"Services"
        }
    ],
    "sg:phone":"+1 510 527 5675",
    "sg:postcode":"94708",
    "sg:province":"CA",
    "sg:tags":[
        "lie",
        "detection",
        "control",
        "weight"
    ],
    "sg:website":"http://www.truthtools.com/",
    "wof:name":"Advanced Truth Tools",
    "wof:placetype":"venue"
},
  "geometry": {"coordinates":[-122.261686,37.887509],"type":"Point"}
}