{
  "type": "Feature",
  "properties": {
    "addr:full":"384 S Tustin St Orange CA 92866",
    "addr:housenumber":"384",
    "addr:postcode":"92866",
    "addr:street":"S Tustin St",
    "iso:country":"US",
    "sg:address":"384 S Tustin St",
    "sg:city":"Orange",
    "sg:classifiers":[
        {
            "category":"Shopping",
            "subcategory":"Clothing, Apparel, & Fashions",
            "type":"Retail Goods"
        }
    ],
    "sg:phone":"+1 714 771 3883",
    "sg:postcode":"92866",
    "sg:province":"CA",
    "wof:name":"Jennys Wig Center",
    "wof:placetype":"venue"
},
  "geometry": {"coordinates":[-117.835807,33.782976],"type":"Point"}
}