{
  "type": "Feature",
  "properties": {
    "addr:full":"753 S Main St Angels Camp CA 95222",
    "addr:housenumber":"753",
    "addr:postcode":"95222",
    "addr:street":"S Main St",
    "iso:country":"US",
    "sg:address":"753 S Main St",
    "sg:city":"Angels Camp",
    "sg:classifiers":[
        {
            "category":"Museum",
            "type":"Entertainment"
        }
    ],
    "sg:phone":"+1 209 736 2963",
    "sg:postcode":"95222",
    "sg:province":"CA",
    "wof:name":"Angels Camp City Museum",
    "wof:placetype":"venue"
},
  "geometry": {"coordinates":[-120.545637,38.075277],"type":"Point"}
}