{
  "type": "Feature",
  "properties": {
    "addr:full":"568 Constitution Ave Camarillo CA 93012",
    "addr:housenumber":"568",
    "addr:postcode":"93012",
    "addr:street":"Constitution Ave",
    "iso:country":"US",
    "sg:address":"568 Constitution Ave",
    "sg:city":"Camarillo",
    "sg:classifiers":[
        {
            "category":"Manufacturing",
            "subcategory":"Food",
            "type":"Manufacturing & Wholesale Goods"
        }
    ],
    "sg:phone":"+1 805 482 5350",
    "sg:postcode":"93012",
    "sg:province":"CA",
    "sg:tags":[
        "preparation",
        "mfg"
    ],
    "wof:name":"J G Distribution",
    "wof:placetype":"venue"
},
  "geometry": {"coordinates":[-119.031465,34.205958],"type":"Point"}
}