{
  "type": "Feature",
  "properties": {
    "iso:country":"US",
    "sg:address":"752 12th St",
    "sg:city":"Manhattan Beach",
    "sg:classifiers":[
        {
            "category":"Professional",
            "type":"Services"
        }
    ],
    "sg:phone":"+1 310 831 0027",
    "sg:postcode":"90266",
    "sg:province":"CA",
    "wof:name":"Sherrill Ammersmark",
    "wof:placetype":"venue"
},
  "geometry": {"coordinates":[-118.404843,33.887478],"type":"Point"}
}