{
  "type": "Feature",
  "properties": {
    "addr:full":"1785 Bryce Ave Turlock CA 95380",
    "addr:housenumber":"1785",
    "addr:postcode":"95380",
    "addr:street":"Bryce Ave",
    "iso:country":"US",
    "sg:address":"1785 Bryce Ave",
    "sg:city":"Turlock",
    "sg:classifiers":[
        {
            "category":"Local Transit",
            "type":"Transportation"
        }
    ],
    "sg:phone":"+1 209 678 1511",
    "sg:postcode":"95380",
    "sg:province":"CA",
    "wof:name":"Mid-Valley Transportation",
    "wof:placetype":"venue"
},
  "geometry": {"coordinates":[-120.86811299999999,37.508101],"type":"Point"}
}