{
  "type": "Feature",
  "properties": {
    "addr:full":"1135 Harrold St Crescent City CA 95531",
    "addr:housenumber":"1135",
    "addr:postcode":"95531",
    "addr:street":"Harrold St Crescent",
    "iso:country":"US",
    "sg:address":"1135 Harrold St",
    "sg:city":"Crescent City",
    "sg:classifiers":[
        {
            "category":"Organizations",
            "subcategory":"Community Association",
            "type":"Services"
        }
    ],
    "sg:phone":"+1 707 464 7740",
    "sg:postcode":"95531",
    "sg:province":"CA",
    "sg:tags":[
        "fraternal"
    ],
    "wof:name":"Loyal Order Of Moose",
    "wof:placetype":"venue"
},
  "geometry": {"coordinates":[-124.197081,41.766079],"type":"Point"}
}