{
  "type": "Feature",
  "properties": {
    "iso:country":"US",
    "sg:address":"849 S Broadway",
    "sg:city":"Los Angeles",
    "sg:classifiers":[
        {
            "category":"Manufacturing",
            "subcategory":"Apparel",
            "type":"Manufacturing & Wholesale Goods"
        }
    ],
    "sg:phone":"+1 213 489 7600",
    "sg:postcode":"90014",
    "sg:province":"CA",
    "sg:tags":[
        "women's",
        "clothing",
        "outerwear",
        "mfg"
    ],
    "wof:name":"Pegasus Fashion Import",
    "wof:placetype":"venue"
},
  "geometry": {"coordinates":[-118.25542,34.043021],"type":"Point"}
}