{
  "type": "Feature",
  "properties": {
    "iso:country":"US",
    "sg:address":"1127 11th St",
    "sg:city":"Sacramento",
    "sg:classifiers":[
        {
            "category":"Organizations",
            "subcategory":"Professional Association",
            "type":"Services"
        }
    ],
    "sg:phone":"+1 916 447 3828",
    "sg:postcode":"95814",
    "sg:province":"CA",
    "wof:name":"Associated Builders & Contrs",
    "wof:placetype":"venue"
},
  "geometry": {"coordinates":[-121.492667,38.578552],"type":"Point"}
}