{
  "type": "Feature",
  "properties": {
    "addr:full":"5592 Engineer Dr Huntington Beach CA 92649",
    "addr:housenumber":"5592",
    "addr:postcode":"92649",
    "addr:street":"Engineer Dr",
    "iso:country":"US",
    "sg:address":"5592 Engineer Dr",
    "sg:city":"Huntington Beach",
    "sg:classifiers":[
        {
            "category":"Sports & Exercise",
            "subcategory":"Bicycle Rental",
            "type":"Entertainment"
        }
    ],
    "sg:phone":"+1 714 895 2444",
    "sg:postcode":"92649",
    "sg:province":"CA",
    "sg:tags":[
        "wear"
    ],
    "wof:name":"Truwest Inc",
    "wof:placetype":"venue"
},
  "geometry": {"coordinates":[-118.030998,33.742699],"type":"Point"}
}