{
  "type": "Feature",
  "properties": {
    "addr:full":"16459 Illinois Ave Paramount CA 90723",
    "addr:housenumber":"16459",
    "addr:postcode":"90723",
    "addr:street":"Illinois Ave",
    "iso:country":"US",
    "sg:address":"16459 Illinois Ave",
    "sg:city":"Paramount",
    "sg:classifiers":[
        {
            "category":"Wholesale",
            "subcategory":"Groceries",
            "type":"Manufacturing & Wholesale Goods"
        }
    ],
    "sg:phone":"+1 562 634 2641",
    "sg:postcode":"90723",
    "sg:province":"CA",
    "sg:tags":[
        "molasses",
        "industrial"
    ],
    "wof:name":"Artesia Molasses Co",
    "wof:placetype":"venue"
},
  "geometry": {"coordinates":[-118.16542,33.883953],"type":"Point"}
}