{
  "type": "Feature",
  "properties": {
    "addr:full":"1009 Headlands Dr Napa CA 94558",
    "addr:housenumber":"1009",
    "addr:postcode":"94558",
    "addr:street":"Headlands Dr",
    "iso:country":"US",
    "sg:address":"1009 Headlands Dr",
    "sg:city":"Napa",
    "sg:classifiers":[
        {
            "category":"Utilities",
            "subcategory":"Telephone",
            "type":"Services"
        }
    ],
    "sg:phone":"+1 707 966 2712",
    "sg:postcode":"94558",
    "sg:province":"CA",
    "sg:tags":[
        "telecommunication"
    ],
    "wof:name":"Valley Comm",
    "wof:placetype":"venue"
},
  "geometry": {"coordinates":[-122.184928,38.518443],"type":"Point"}
}