{
  "type": "Feature",
  "properties": {
    "addr:full":"16325 Silver Oaks Dr Sylmar CA 91342",
    "addr:housenumber":"16325",
    "addr:postcode":"91342",
    "addr:street":"Silver Oaks Dr",
    "iso:country":"US",
    "sg:address":"16325 Silver Oaks Dr",
    "sg:city":"Sylmar",
    "sg:classifiers":[
        {
            "category":"Sports & Exercise",
            "subcategory":"Golf",
            "type":"Entertainment"
        }
    ],
    "sg:phone":"+1 818 833 8900",
    "sg:postcode":"91342",
    "sg:province":"CA",
    "sg:tags":[
        "course"
    ],
    "wof:name":"Cascades Golf Club",
    "wof:placetype":"venue"
},
  "geometry": {"coordinates":[-118.48829600000001,34.322184],"type":"Point"}
}