{
  "type": "Feature",
  "properties": {
    "addr:full":"3700 N Chester Ave Bakersfield CA 93308",
    "addr:housenumber":"3700",
    "addr:postcode":"93308",
    "addr:street":"N Chester Ave",
    "iso:country":"US",
    "sg:address":"3700 N Chester Ave",
    "sg:city":"Bakersfield",
    "sg:classifiers":[
        {
            "category":"Food & Beverages",
            "subcategory":"Groceries & Convenience Stores",
            "type":"Retail Goods"
        }
    ],
    "sg:phone":"+1 661 392 0190",
    "sg:postcode":"93308",
    "sg:province":"CA",
    "wof:name":"Johnny Quik Food Store",
    "wof:placetype":"venue"
},
  "geometry": {"coordinates":[-119.02214499999999,35.44182],"type":"Point"}
}