{
  "type": "Feature",
  "properties": {
    "iso:country":"US",
    "sg:address":"7467 Pepper St",
    "sg:city":"Rancho Cucamonga",
    "sg:classifiers":[
        {
            "category":"Professional",
            "subcategory":"Research",
            "type":"Services"
        }
    ],
    "sg:phone":"+1 909 228 2225",
    "sg:postcode":"91730",
    "sg:province":"CA",
    "sg:tags":[
        "environmental",
        "ecological"
    ],
    "wof:name":"Green Tree Environmental Mgmt",
    "wof:placetype":"venue"
},
  "geometry": {"coordinates":[-117.603647,34.117568],"type":"Point"}
}