{
  "type": "Feature",
  "properties": {
    "iso:country":"US",
    "sg:address":"1515 S Saticoy Ave",
    "sg:city":"Ventura",
    "sg:classifiers":[
        {
            "category":"Professional",
            "subcategory":"Management & Consulting",
            "type":"Services"
        }
    ],
    "sg:phone":"+1 805 647 4083",
    "sg:postcode":"93004",
    "sg:province":"CA",
    "sg:tags":[
        "association"
    ],
    "wof:name":"Cooperative Store",
    "wof:placetype":"venue"
},
  "geometry": {"coordinates":[-119.154841,34.275319],"type":"Point"}
}