{
  "type": "Feature",
  "properties": {
    "addr:full":"9801 Fair Oaks Blvd Fair Oaks CA 95628",
    "addr:housenumber":"9801",
    "addr:postcode":"95628",
    "addr:street":"Fair Oaks Blvd",
    "iso:country":"US",
    "sg:address":"9801 Fair Oaks Blvd",
    "sg:city":"Fair Oaks",
    "sg:classifiers":[
        {
            "category":"Health Services",
            "subcategory":"Clinic",
            "type":"Services"
        }
    ],
    "sg:phone":"+1 916 536 5450",
    "sg:postcode":"95628",
    "sg:province":"CA",
    "sg:tags":[
        "home"
    ],
    "wof:name":"Sutter Visiting Nurse Assn",
    "wof:placetype":"venue"
},
  "geometry": {"coordinates":[-121.275549,38.639384],"type":"Point"}
}