{
  "type": "Feature",
  "properties": {
    "addr:full":"9211 Bolsa Ave # 226 Westminster CA 92683",
    "addr:housenumber":"9211",
    "addr:postcode":"92683",
    "addr:street":"Bolsa Ave # 226",
    "iso:country":"US",
    "sg:address":"9211 Bolsa Ave # 226",
    "sg:city":"Westminster",
    "sg:classifiers":[
        {
            "category":"Personal",
            "subcategory":"Massage",
            "type":"Services"
        }
    ],
    "sg:phone":"+1 714 892 8889",
    "sg:postcode":"92683",
    "sg:province":"CA",
    "wof:name":"Jolly Feet",
    "wof:placetype":"venue"
},
  "geometry": {"coordinates":[-117.968509,33.744921],"type":"Point"}
}