{
  "type": "Feature",
  "properties": {
    "addr:full":"6601 W Sunset Blvd Los Angeles CA 90028",
    "addr:housenumber":"6601",
    "addr:postcode":"90028",
    "addr:street":"W Sunset Blvd",
    "iso:country":"US",
    "sg:address":"6601 W Sunset Blvd",
    "sg:city":"Los Angeles",
    "sg:classifiers":[
        {
            "category":"Restaurant",
            "type":"Food & Drink"
        }
    ],
    "sg:phone":"+1 323 467 3840",
    "sg:postcode":"90028",
    "sg:province":"CA",
    "sg:tags":[
        "traditional",
        "american"
    ],
    "wof:name":"Ponchik Factory",
    "wof:placetype":"venue"
},
  "geometry": {"coordinates":[-118.33346,34.098196],"type":"Point"}
}