{
  "type": "Feature",
  "properties": {
    "iso:country":"US",
    "sg:address":"3312 Esperanza Dr",
    "sg:city":"Concord",
    "sg:classifiers":[
        {
            "category":"Building & Trades",
            "subcategory":"Cleaning & Sanitation",
            "type":"Services"
        }
    ],
    "sg:phone":"+1 925 682 1738",
    "sg:postcode":"94519",
    "sg:province":"CA",
    "sg:tags":[
        "window"
    ],
    "wof:name":"All Bay Pro Window Cleaning",
    "wof:placetype":"venue"
},
  "geometry": {"coordinates":[-122.02512299999999,37.992852],"type":"Point"}
}