{
  "type": "Feature",
  "properties": {
    "addr:full":"550 Water Street Suite J4 Santa Cruz CA 95060",
    "addr:housenumber":"550",
    "addr:postcode":"95060",
    "addr:street":"Water Street Suite J4",
    "iso:country":"US",
    "sg:address":"550 Water Street Suite J4",
    "sg:city":"Santa Cruz",
    "sg:classifiers":[
        {
            "category":"Health Services",
            "subcategory":"Doctor",
            "type":"Services"
        },
        {
            "category":"Health Services",
            "subcategory":"Health Practitioner",
            "type":"Services"
        }
    ],
    "sg:phone":"+1 831 423 2298",
    "sg:postcode":"95060",
    "sg:province":"CA",
    "sg:tags":[
        "acupuncture"
    ],
    "wof:name":"Turzo Enterprises",
    "wof:placetype":"venue"
},
  "geometry": {"coordinates":[-122.01903299999999,36.980257],"type":"Point"}
}