{
  "type": "Feature",
  "properties": {
    "iso:country":"US",
    "sg:address":"5525 Brooks St",
    "sg:city":"Montclair",
    "sg:classifiers":[
        {
            "category":"Shopping",
            "subcategory":"Discount & Variety Stores",
            "type":"Retail Goods"
        }
    ],
    "sg:phone":"+1 909 988 0819",
    "sg:postcode":"91763",
    "sg:province":"CA",
    "sg:tags":[
        "merchandise",
        "general"
    ],
    "wof:name":"American Power Products",
    "wof:placetype":"venue"
},
  "geometry": {"coordinates":[-117.681258,34.061711],"type":"Point"}
}