{
  "type": "Feature",
  "properties": {
    "addr:full":"1975 Pennsylvania Ave Fairfield CA 94533",
    "addr:housenumber":"1975",
    "addr:postcode":"94533",
    "addr:street":"Pennsylvania Ave",
    "iso:country":"US",
    "sg:address":"1975 Pennsylvania Ave",
    "sg:city":"Fairfield",
    "sg:classifiers":[
        {
            "category":"Education",
            "subcategory":"School",
            "type":"Public Place"
        }
    ],
    "sg:phone":"+1 707 399 5000",
    "sg:postcode":"94533",
    "sg:province":"CA",
    "sg:tags":[
        "district"
    ],
    "wof:name":"Fairfld-Sisun Unified Schl Dst",
    "wof:placetype":"venue"
},
  "geometry": {"coordinates":[-122.04983199999999,38.262418],"type":"Point"}
}