{
  "type": "Feature",
  "properties": {
    "addr:full":"20504 Ventura Blvd Woodland Hills CA 91364",
    "addr:housenumber":"20504",
    "addr:postcode":"91364",
    "addr:street":"Ventura Blvd",
    "iso:country":"US",
    "sg:address":"20504 Ventura Blvd",
    "sg:city":"Woodland Hills",
    "sg:classifiers":[
        {
            "category":"Building & Trades",
            "subcategory":"Construction",
            "type":"Services"
        }
    ],
    "sg:phone":"+1 818 932 4616",
    "sg:postcode":"91364",
    "sg:province":"CA",
    "sg:tags":[
        "resurfacing",
        "laying",
        "refinishing",
        "floor"
    ],
    "wof:name":"Durandela Flooring Brokers",
    "wof:placetype":"venue"
},
  "geometry": {"coordinates":[-118.58045300000001,34.167777],"type":"Point"}
}