{
  "type": "Feature",
  "properties": {
    "addr:full":"1691 Newcomb Ave San Francisco CA 94124",
    "addr:housenumber":"1691",
    "addr:postcode":"94124",
    "addr:street":"Newcomb Ave",
    "iso:country":"US",
    "sg:address":"1691 Newcomb Ave",
    "sg:city":"San Francisco",
    "sg:classifiers":[
        {
            "category":"Social Services",
            "subcategory":"Adult Care",
            "type":"Services"
        }
    ],
    "sg:phone":"+1 415 550 9335",
    "sg:postcode":"94124",
    "sg:province":"CA",
    "sg:tags":[
        "home",
        "residential"
    ],
    "wof:name":"Mae Bea Andrews Boarding Care",
    "wof:placetype":"venue"
},
  "geometry": {"coordinates":[-122.390843,37.73562],"type":"Point"}
}