{
  "type": "Feature",
  "properties": {
    "iso:country":"US",
    "sg:address":"389 8th St",
    "sg:city":"Oakland",
    "sg:classifiers":[
        {
            "category":"Restaurant",
            "type":"Food & Drink"
        }
    ],
    "sg:phone":"+1 510 465 1940",
    "sg:postcode":"94607",
    "sg:province":"CA",
    "sg:tags":[
        "chinese"
    ],
    "wof:name":"New Gold Medal Restaurant",
    "wof:placetype":"venue"
},
  "geometry": {"coordinates":[-122.27231,37.799634],"type":"Point"}
}