{
  "type": "Feature",
  "properties": {
    "addr:full":"13468 Granite Creek Rd San Diego CA 92128",
    "addr:housenumber":"13468",
    "addr:postcode":"92128",
    "addr:street":"Granite Creek Rd",
    "iso:country":"US",
    "sg:address":"13468 Granite Creek Rd",
    "sg:city":"San Diego",
    "sg:classifiers":[
        {
            "category":"Building & Trades",
            "subcategory":"Construction",
            "type":"Services"
        }
    ],
    "sg:phone":"+1 858 679 7462",
    "sg:postcode":"92128",
    "sg:province":"CA",
    "sg:tags":[
        "equipment",
        "station"
    ],
    "wof:name":"Petroleum PETS",
    "wof:placetype":"venue"
},
  "geometry": {"coordinates":[-117.088832,32.962676],"type":"Point"}
}