{
  "type": "Feature",
  "properties": {
    "iso:country":"US",
    "sg:address":"7736 Fay Ave",
    "sg:city":"La Jolla",
    "sg:classifiers":[
        {
            "category":"Professional",
            "type":"Services"
        }
    ],
    "sg:phone":"+1 858 551 3215",
    "sg:postcode":"92037",
    "sg:province":"CA",
    "sg:tags":[
        "establishment"
    ],
    "wof:name":"Marie Aube's",
    "wof:placetype":"venue"
},
  "geometry": {"coordinates":[-117.27511800000001,32.844237],"type":"Point"}
}