{
  "type": "Feature",
  "properties": {
    "iso:country":"US",
    "sg:address":"2326 W Jefferson Blvd",
    "sg:city":"Los Angeles",
    "sg:classifiers":[
        {
            "category":"Organizations",
            "subcategory":"Religious Organization",
            "type":"Services"
        }
    ],
    "sg:phone":"+1 323 733 4127",
    "sg:postcode":"90018",
    "sg:province":"CA",
    "sg:tags":[
        "church"
    ],
    "wof:name":"Foursquare Church",
    "wof:placetype":"venue"
},
  "geometry": {"coordinates":[-118.32099100000001,34.025499],"type":"Point"}
}