{
  "type": "Feature",
  "properties": {
    "addr:full":"2728 W Magnolia Ave Caruthers CA 93609",
    "addr:housenumber":"2728",
    "addr:postcode":"93609",
    "addr:street":"W Magnolia Ave",
    "iso:country":"US",
    "sg:address":"2728 W Magnolia Ave",
    "sg:city":"Caruthers",
    "sg:classifiers":[
        {
            "category":"Freight",
            "type":"Transportation"
        }
    ],
    "sg:phone":"+1 559 864 8587",
    "sg:postcode":"93609",
    "sg:province":"CA",
    "sg:tags":[
        "trucking"
    ],
    "wof:name":"JBS Logistics Inc",
    "wof:placetype":"venue"
},
  "geometry": {"coordinates":[-119.841481,36.510957],"type":"Point"}
}