{
  "type": "Feature",
  "properties": {
    "addr:full":"Edgewater Place Shopping Center 951 C Edgewater Blvd Foster City CA 94404",
    "addr:housenumber":"951 c",
    "addr:postcode":"94404",
    "addr:street":"Edgewater;Edgewater Blvd",
    "iso:country":"US",
    "sg:address":"Edgewater Place Shopping Center 951 C Edgewater Blvd",
    "sg:city":"Foster City",
    "sg:classifiers":[
        {
            "category":"Health Services",
            "subcategory":"Dentist",
            "type":"Services"
        }
    ],
    "sg:phone":"+1 650 345 3183",
    "sg:postcode":"94404",
    "sg:province":"CA",
    "wof:name":"Stephen A. Quon, D.D.S.",
    "wof:placetype":"venue"
},
  "geometry": {"coordinates":[-122.27176300000001,37.544911],"type":"Point"}
}