{
  "type": "Feature",
  "properties": {
    "addr:full":"246 E Baseline St San Bernardino CA 92410",
    "addr:housenumber":"246",
    "addr:postcode":"92410",
    "addr:street":"E Baseline St",
    "iso:country":"US",
    "sg:address":"246 E Baseline St",
    "sg:city":"San Bernardino",
    "sg:classifiers":[
        {
            "category":"Restaurant",
            "type":"Food & Drink"
        }
    ],
    "sg:phone":"+1 909 322 9818",
    "sg:postcode":"92410",
    "sg:province":"CA",
    "sg:tags":[
        "eating"
    ],
    "wof:name":"Mariscos LA Sirena",
    "wof:placetype":"venue"
},
  "geometry": {"coordinates":[-117.280753,34.121403],"type":"Point"}
}