{
  "type": "Feature",
  "properties": {
    "addr:full":"2944 Stevenson Dr Pebble Beach CA 93953",
    "addr:housenumber":"2944",
    "addr:postcode":"93953",
    "addr:street":"Stevenson Dr",
    "iso:country":"US",
    "sg:address":"2944 Stevenson Dr",
    "sg:city":"Pebble Beach",
    "sg:classifiers":[
        {
            "category":"Building & Trades",
            "subcategory":"Plumbing",
            "type":"Services"
        }
    ],
    "sg:phone":"+1 831 476 8888",
    "sg:postcode":"93953",
    "sg:province":"CA",
    "sg:tags":[
        "plumbing",
        "contractor"
    ],
    "wof:name":"Mr Rooter",
    "wof:placetype":"venue"
},
  "geometry": {"coordinates":[-121.951983,36.603525],"type":"Point"}
}