{
  "type": "Feature",
  "properties": {
    "addr:full":"34277 Ethan Ter Fremont CA 94555",
    "addr:housenumber":"34277",
    "addr:postcode":"94555",
    "addr:street":"Ethan Ter",
    "iso:country":"US",
    "sg:address":"34277 Ethan Ter",
    "sg:city":"Fremont",
    "sg:classifiers":[
        {
            "category":"Manufacturing",
            "subcategory":"Food",
            "type":"Manufacturing & Wholesale Goods"
        }
    ],
    "sg:phone":"+1 510 796 4534",
    "sg:postcode":"94555",
    "sg:province":"CA",
    "sg:tags":[
        "product",
        "dairy",
        "mfg"
    ],
    "wof:name":"1004inusa",
    "wof:placetype":"venue"
},
  "geometry": {"coordinates":[-122.052286,37.566056],"type":"Point"}
}