{
  "type": "Feature",
  "properties": {
    "addr:full":"9512 Hillhaven Ave Tujunga CA 91042",
    "addr:postcode":"9512;91042",
    "addr:street":"Hillhaven Ave",
    "iso:country":"US",
    "sg:address":"9512 Hillhaven Ave",
    "sg:city":"Tujunga",
    "sg:classifiers":[
        {
            "category":"Health Services",
            "subcategory":"Optometrist",
            "type":"Services"
        }
    ],
    "sg:phone":"+1 818 353 6381",
    "sg:postcode":"91042",
    "sg:province":"CA",
    "sg:tags":[
        "good",
        "optical"
    ],
    "wof:name":"R G B Optical",
    "wof:placetype":"venue"
},
  "geometry": {"coordinates":[-118.292689,34.242465],"type":"Point"}
}