{
  "type": "Feature",
  "properties": {
    "iso:country":"US",
    "sg:address":"1139 W Olive Ave",
    "sg:city":"Porterville",
    "sg:classifiers":[
        {
            "category":"Wholesale",
            "subcategory":"Medical Equipment & Supplies",
            "type":"Manufacturing & Wholesale Goods"
        }
    ],
    "sg:phone":"+1 559 781 9226",
    "sg:postcode":"93257",
    "sg:province":"CA",
    "sg:tags":[
        "physician",
        "surgeon"
    ],
    "wof:name":"Med Mart-Pacific Pulmonary Svc",
    "wof:placetype":"venue"
},
  "geometry": {"coordinates":[-119.040555,36.065902],"type":"Point"}
}