{
  "type": "Feature",
  "properties": {
    "addr:full":"5155 Carriage Way Antioch CA 94531",
    "addr:housenumber":"5155",
    "addr:postcode":"ca 94531",
    "addr:street":"Carriage Way",
    "iso:country":"US",
    "sg:address":"5155 Carriage Way",
    "sg:city":"Antioch",
    "sg:classifiers":[
        {
            "category":"Retail",
            "subcategory":"Repair Shop",
            "type":"Services"
        }
    ],
    "sg:phone":"+1 925 755 1500",
    "sg:postcode":"94531",
    "sg:province":"CA",
    "sg:tags":[
        "upholsterer"
    ],
    "wof:name":"Arm Carpet & Upholstery C",
    "wof:placetype":"venue"
},
  "geometry": {"coordinates":[-121.756432,37.971624],"type":"Point"}
}