{
  "type": "Feature",
  "properties": {
    "addr:full":"150 Lombard St San Francisco CA 94111",
    "addr:housenumber":"150",
    "addr:postcode":"94111",
    "addr:street":"Lombard St",
    "iso:country":"US",
    "sg:address":"150 Lombard St",
    "sg:city":"San Francisco",
    "sg:classifiers":[
        {
            "category":"Health Services",
            "subcategory":"Health Practitioner",
            "type":"Services"
        },
        {
            "category":"Health Services",
            "subcategory":"Chiropractor",
            "type":"Services"
        }
    ],
    "sg:phone":"+1 415 421 1115",
    "sg:postcode":"94111",
    "sg:province":"CA",
    "sg:tags":[
        "acupuncture"
    ],
    "wof:name":"Tom L Viland DC",
    "wof:placetype":"venue"
},
  "geometry": {"coordinates":[-122.404178,37.80445],"type":"Point"}
}