{
  "type": "Feature",
  "properties": {
    "iso:country":"US",
    "sg:address":"2008 Kehoe Ave",
    "sg:city":"San Mateo",
    "sg:classifiers":[
        {
            "category":"Building & Trades",
            "subcategory":"Landscaping Services",
            "type":"Services"
        }
    ],
    "sg:phone":"+1 650 572 0589",
    "sg:postcode":"94403",
    "sg:province":"CA",
    "wof:name":"Ohara Nobu Gardening Service",
    "wof:placetype":"venue"
},
  "geometry": {"coordinates":[-122.294514,37.565469],"type":"Point"}
}