{
  "type": "Feature",
  "properties": {
    "iso:country":"US",
    "sg:address":"342 N Rodeo Dr",
    "sg:city":"Beverly Hills",
    "sg:classifiers":[
        {
            "category":"Shopping",
            "subcategory":"Clothing, Apparel, & Fashions",
            "type":"Retail Goods"
        }
    ],
    "sg:phone":"+1 310 271 5788",
    "sg:postcode":"90210",
    "sg:province":"CA",
    "sg:tags":[
        "fur",
        "business"
    ],
    "wof:name":"Rubin Budd Furs",
    "wof:placetype":"venue"
},
  "geometry": {"coordinates":[-118.401974,34.068229],"type":"Point"}
}