{
  "type": "Feature",
  "properties": {
    "addr:full":"590 N Yosemite Ave Oakdale CA 95361",
    "addr:housenumber":"590",
    "addr:postcode":"95361",
    "addr:street":"N Yosemite Ave",
    "iso:country":"US",
    "sg:address":"590 N Yosemite Ave",
    "sg:city":"Oakdale",
    "sg:classifiers":[
        {
            "category":"Organizations",
            "subcategory":"Professional Association",
            "type":"Services"
        }
    ],
    "sg:phone":"+1 209 847 2244",
    "sg:postcode":"95361",
    "sg:province":"CA",
    "sg:tags":[
        "chambers",
        "commerce"
    ],
    "sg:website":"www.oakdalechamber.com",
    "wof:name":"Oakdale Chamber Of Commerce",
    "wof:placetype":"venue"
},
  "geometry": {"coordinates":[-120.850442,37.771358],"type":"Point"}
}