{
  "type": "Feature",
  "properties": {
    "addr:full":"2324 Clemson Dr Davis CA 95618",
    "addr:housenumber":"2324",
    "addr:postcode":"95618",
    "addr:street":"Clemson Dr",
    "iso:country":"US",
    "sg:address":"2324 Clemson Dr",
    "sg:city":"Davis",
    "sg:classifiers":[
        {
            "category":"Building & Trades",
            "subcategory":"Landscaping Services",
            "type":"Services"
        }
    ],
    "sg:phone":"+1 530 756 0372",
    "sg:postcode":"95618",
    "sg:province":"CA",
    "sg:tags":[
        "lawn",
        "maintenance",
        "grounds"
    ],
    "wof:name":"Hibiscus Gardening",
    "wof:placetype":"venue"
},
  "geometry": {"coordinates":[-121.724532,38.56051],"type":"Point"}
}