{
  "type": "Feature",
  "properties": {
    "addr:full":"78401 US Hwy 111 La Quinta CA 92253",
    "addr:postcode":"78401;92253",
    "addr:street":"Us Hwy 111",
    "iso:country":"US",
    "sg:address":"78401 US Hwy 111",
    "sg:city":"La Quinta",
    "sg:classifiers":[
        {
            "category":"Government",
            "subcategory":"Office",
            "type":"Public Place"
        }
    ],
    "sg:phone":"+1 760 564 4888",
    "sg:postcode":"92253",
    "sg:province":"CA",
    "wof:name":"Riverside Cnty Salton Sea Auth",
    "wof:placetype":"venue"
},
  "geometry": {"coordinates":[-116.297087,33.715888],"type":"Point"}
}