{
  "type": "Feature",
  "properties": {
    "iso:country":"US",
    "sg:address":"3620 N Long Beach Blvd",
    "sg:city":"Long Beach",
    "sg:classifiers":[
        {
            "category":"Real Estate",
            "subcategory":"Architect",
            "type":"Services"
        }
    ],
    "sg:phone":"+1 562 595 0078",
    "sg:postcode":"90807",
    "sg:province":"CA",
    "sg:website":"www.robertstewartarchitects.com",
    "wof:name":"Robert Stewart Architects",
    "wof:placetype":"venue"
},
  "geometry": {"coordinates":[-118.189278,33.822325],"type":"Point"}
}