{
  "type": "Feature",
  "properties": {
    "addr:full":"327 W E St Colton CA 92324",
    "addr:housenumber":"327",
    "addr:postcode":"92324",
    "addr:street":"W E St",
    "iso:country":"US",
    "sg:address":"327 W E St",
    "sg:city":"Colton",
    "sg:classifiers":[
        {
            "category":"Real Estate",
            "subcategory":"Developer",
            "type":"Services"
        }
    ],
    "sg:phone":"+1 951 538 4319",
    "sg:postcode":"92324",
    "sg:province":"CA",
    "wof:name":"Noriega Development",
    "wof:placetype":"venue"
},
  "geometry": {"coordinates":[-117.32722099999999,34.071766],"type":"Point"}
}