{
  "type": "Feature",
  "properties": {
    "iso:country":"US",
    "sg:address":"14835 Bessemer St",
    "sg:city":"Van Nuys",
    "sg:phone":"+1 818 785 5751",
    "sg:postcode":"91411",
    "sg:province":"CA",
    "sg:tags":[
        "equipment",
        "commercial"
    ],
    "wof:name":"Thoro Strmtic Glasswashing Sys",
    "wof:placetype":"venue"
},
  "geometry": {"coordinates":[-118.454999,34.180874],"type":"Point"}
}