{
  "type": "Feature",
  "properties": {
    "iso:country":"US",
    "sg:address":"9806 Maine Ave",
    "sg:city":"Lakeside",
    "sg:classifiers":[
        {
            "category":"Autos & Motor Vehicles",
            "subcategory":"Automobile Sales",
            "type":"Retail Goods"
        }
    ],
    "sg:phone":"+1 619 312 0667",
    "sg:postcode":"92040",
    "sg:province":"CA",
    "sg:tags":[
        "new",
        "used",
        "car"
    ],
    "wof:name":"Road Motors",
    "wof:placetype":"venue"
},
  "geometry": {"coordinates":[-116.92135399999999,32.857391],"type":"Point"}
}