{
  "type": "Feature",
  "properties": {
    "addr:full":"4237 Los Serranos Blvd Chino Hills CA 91709",
    "addr:housenumber":"4237",
    "addr:postcode":"91709",
    "addr:street":"Los Serranos Blvd",
    "iso:country":"US",
    "sg:address":"4237 Los Serranos Blvd",
    "sg:city":"Chino Hills",
    "sg:classifiers":[
        {
            "category":"Manufacturing",
            "subcategory":"Toys & Sporting Goods",
            "type":"Manufacturing & Wholesale Goods"
        }
    ],
    "sg:phone":"+1 909 606 5323",
    "sg:postcode":"91709",
    "sg:province":"CA",
    "sg:tags":[
        "mfg"
    ],
    "wof:name":"Mattell",
    "wof:placetype":"venue"
},
  "geometry": {"coordinates":[-117.712188,33.973912],"type":"Point"}
}