{
  "type": "Feature",
  "properties": {
    "iso:country":"US",
    "sg:address":"3690 Auto Mall Dr",
    "sg:city":"Westlake Village",
    "sg:classifiers":[
        {
            "category":"Autos & Motor Vehicles",
            "subcategory":"Automobile Sales",
            "type":"Retail Goods"
        }
    ],
    "sg:phone":"+1 805 482 6191",
    "sg:postcode":"91362",
    "sg:province":"CA",
    "sg:tags":[
        "car",
        "dealer"
    ],
    "wof:name":"Nesen Cadillac Inc",
    "wof:placetype":"venue"
},
  "geometry": {"coordinates":[-118.831857,34.162713],"type":"Point"}
}