{
  "type": "Feature",
  "properties": {
    "addr:full":"1109 W Visalia Rd Exeter CA 93221",
    "addr:housenumber":"1109",
    "addr:postcode":"93221",
    "addr:street":"W Visalia Rd",
    "iso:country":"US",
    "sg:address":"1109 W Visalia Rd",
    "sg:city":"Exeter",
    "sg:classifiers":[
        {
            "category":"Restaurant",
            "type":"Food & Drink"
        }
    ],
    "sg:phone":"+1 559 592 5810",
    "sg:postcode":"93221",
    "sg:province":"CA",
    "wof:name":"Mc Donald's",
    "wof:placetype":"venue"
},
  "geometry": {"coordinates":[-119.154464,36.297265],"type":"Point"}
}