{
  "type": "Feature",
  "properties": {
    "addr:full":"9520 Mission Blvd Riverside CA 92509",
    "addr:housenumber":"9520",
    "addr:postcode":"92509",
    "addr:street":"Mission Blvd",
    "iso:country":"US",
    "sg:address":"9520 Mission Blvd",
    "sg:city":"Riverside",
    "sg:classifiers":[
        {
            "category":"Organizations",
            "subcategory":"Community Association",
            "type":"Services"
        }
    ],
    "sg:phone":"+1 951 685 4257",
    "sg:postcode":"92509",
    "sg:province":"CA",
    "sg:tags":[
        "military"
    ],
    "wof:name":"American Legion",
    "wof:placetype":"venue"
},
  "geometry": {"coordinates":[-117.491416,34.011688],"type":"Point"}
}