{
  "type": "Feature",
  "properties": {
    "addr:full":"1153 Tylee St Vista CA 92083",
    "addr:housenumber":"1153",
    "addr:postcode":"92083",
    "addr:street":"Tylee St",
    "iso:country":"US",
    "sg:address":"1153 Tylee St",
    "sg:city":"Vista",
    "sg:classifiers":[
        {
            "category":"Personal",
            "type":"Services"
        }
    ],
    "sg:phone":"+1 760 631 3216",
    "sg:postcode":"92083",
    "sg:province":"CA",
    "sg:tags":[
        "miscellaneous",
        "errand"
    ],
    "wof:name":"Errands Plus",
    "wof:placetype":"venue"
},
  "geometry": {"coordinates":[-117.264414,33.200663],"type":"Point"}
}