{
  "type": "Feature",
  "properties": {
    "addr:full":"924 Montana Ave Santa Monica CA 90403",
    "addr:housenumber":"924",
    "addr:postcode":"90403",
    "addr:street":"Montana Ave",
    "iso:country":"US",
    "sg:address":"924 Montana Ave",
    "sg:city":"Santa Monica",
    "sg:classifiers":[
        {
            "category":"Retail",
            "subcategory":"Laundry & Dry Cleaning",
            "type":"Services"
        }
    ],
    "sg:phone":"+1 310 394 9418",
    "sg:postcode":"90403",
    "sg:province":"CA",
    "wof:name":"Fox Coin Laundries",
    "wof:placetype":"venue"
},
  "geometry": {"coordinates":[-118.49954099999999,34.028513],"type":"Point"}
}