{
  "type": "Feature",
  "properties": {
    "addr:full":"32387 Auberry Rd Auberry CA 93602",
    "addr:housenumber":"32387",
    "addr:postcode":"93602",
    "addr:street":"Auberry Rd",
    "iso:country":"US",
    "sg:address":"32387 Auberry Rd",
    "sg:city":"Auberry",
    "sg:classifiers":[
        {
            "category":"Retail",
            "subcategory":"Auto Repair",
            "type":"Services"
        }
    ],
    "sg:phone":"+1 559 855 2940",
    "sg:postcode":"93602",
    "sg:province":"CA",
    "sg:tags":[
        "repairing",
        "automobile"
    ],
    "wof:name":"Cliffside Auto Ctr",
    "wof:placetype":"venue"
},
  "geometry": {"coordinates":[-119.490273,37.068524],"type":"Point"}
}