{
  "type": "Feature",
  "properties": {
    "addr:full":"3941 Meadow Wood Dr El Dorado Hills CA 95762",
    "addr:housenumber":"3941",
    "addr:postcode":"95762",
    "addr:street":"Meadow Wood Dr",
    "iso:country":"US",
    "sg:address":"3941 Meadow Wood Dr",
    "sg:city":"El Dorado Hills",
    "sg:classifiers":[
        {
            "category":"Manufacturing",
            "subcategory":"Tools & Machinery",
            "type":"Manufacturing & Wholesale Goods"
        }
    ],
    "sg:phone":"+1 916 353 2626",
    "sg:postcode":"95762",
    "sg:province":"CA",
    "sg:tags":[
        "surgical",
        "mfg"
    ],
    "wof:name":"JB Call Div of Blickman H",
    "wof:placetype":"venue"
},
  "geometry": {"coordinates":[-121.072451,38.678151],"type":"Point"}
}