{
  "type": "Feature",
  "properties": {
    "iso:country":"US",
    "sg:address":"21758 Walnut Ave",
    "sg:city":"Grand Terrace",
    "sg:classifiers":[
        {
            "category":"Manufacturing",
            "subcategory":"Chemicals & Compounds",
            "type":"Manufacturing & Wholesale Goods"
        }
    ],
    "sg:phone":"+1 909 783 7815",
    "sg:postcode":"92313",
    "sg:province":"CA",
    "sg:tags":[
        "herbal",
        "supplement",
        "nutritional",
        "mfg"
    ],
    "wof:name":"Bio-Defense Nutritionals Inc",
    "wof:placetype":"venue"
},
  "geometry": {"coordinates":[-117.329829,34.037899],"type":"Point"}
}