{
  "type": "Feature",
  "properties": {
    "iso:country":"US",
    "sg:address":"2042 Girard St",
    "sg:city":"Delano",
    "sg:classifiers":[
        {
            "category":"Shopping",
            "subcategory":"Hobbies, Toys, & Games",
            "type":"Retail Goods"
        }
    ],
    "sg:phone":"+1 661 725 1617",
    "sg:postcode":"93215",
    "sg:province":"CA",
    "sg:tags":[
        "craft",
        "supply"
    ],
    "wof:name":"Anita Craft & Gifts",
    "wof:placetype":"venue"
},
  "geometry": {"coordinates":[-119.249717,35.783892],"type":"Point"}
}