{
  "type": "Feature",
  "properties": {
    "addr:full":"305 High St Delano CA 93215",
    "addr:housenumber":"305",
    "addr:postcode":"93215",
    "addr:street":"High St",
    "iso:country":"US",
    "sg:address":"305 High St",
    "sg:city":"Delano",
    "sg:classifiers":[
        {
            "category":"Autos & Motor Vehicles",
            "subcategory":"Fuel & Gas Station",
            "type":"Retail Goods"
        }
    ],
    "sg:phone":"+1 661 725 8232",
    "sg:postcode":"93215",
    "sg:province":"CA",
    "sg:tags":[
        "oil"
    ],
    "wof:name":"Bill's Chevron",
    "wof:placetype":"venue"
},
  "geometry": {"coordinates":[-119.244968,35.759667],"type":"Point"}
}