{
  "type": "Feature",
  "properties": {
    "addr:full":"1454 Claudia Dr Sacramento CA 95822",
    "addr:housenumber":"1454",
    "addr:postcode":"95822",
    "addr:street":"Claudia Dr",
    "iso:country":"US",
    "sg:address":"1454 Claudia Dr",
    "sg:city":"Sacramento",
    "sg:classifiers":[
        {
            "category":"Insurance",
            "subcategory":"Insurance Agent",
            "type":"Services"
        }
    ],
    "sg:phone":"+1 916 392 6530",
    "sg:postcode":"95822",
    "sg:province":"CA",
    "wof:name":"Hutcheon Ins Services",
    "wof:placetype":"venue"
},
  "geometry": {"coordinates":[-121.503601,38.523093],"type":"Point"}
}