{
  "type": "Feature",
  "properties": {
    "iso:country":"US",
    "sg:address":"27681 Golondrina",
    "sg:city":"Mission Viejo",
    "sg:classifiers":[
        {
            "category":"Utilities",
            "subcategory":"Telephone",
            "type":"Services"
        }
    ],
    "sg:phone":"+1 949 583 3172",
    "sg:postcode":"92692",
    "sg:province":"CA",
    "sg:tags":[
        "communications"
    ],
    "wof:name":"Toshiba America",
    "wof:placetype":"venue"
},
  "geometry": {"coordinates":[-117.647433,33.603985],"type":"Point"}
}