{
  "type": "Feature",
  "properties": {
    "addr:full":"11800 Santa Lucia Rd Atascadero CA 93422",
    "addr:housenumber":"11800",
    "addr:postcode":"93422",
    "addr:street":"Santa Lucia Rd",
    "iso:country":"US",
    "sg:address":"11800 Santa Lucia Rd",
    "sg:city":"Atascadero",
    "sg:classifiers":[
        {
            "category":"Recreation",
            "type":"Entertainment"
        }
    ],
    "sg:phone":"+1 805 610 8102",
    "sg:postcode":"93422",
    "sg:province":"CA",
    "sg:tags":[
        "stable"
    ],
    "wof:name":"Double F Horseshoeing",
    "wof:placetype":"venue"
},
  "geometry": {"coordinates":[-120.70975900000001,35.472335],"type":"Point"}
}