{
  "type": "Feature",
  "properties": {
    "iso:country":"US",
    "sg:address":"335 N Main St",
    "sg:city":"Alturas",
    "sg:classifiers":[
        {
            "category":"Real Estate",
            "subcategory":"Real Estate Agent",
            "type":"Services"
        }
    ],
    "sg:phone":"+1 530 233 3551",
    "sg:postcode":"96101",
    "sg:province":"CA",
    "wof:name":"Tate Realty",
    "wof:placetype":"venue"
},
  "geometry": {"coordinates":[-120.54255000000001,41.486947],"type":"Point"}
}