{
  "type": "Feature",
  "properties": {
    "iso:country":"US",
    "sg:address":"2215 W Mission Rd",
    "sg:city":"Alhambra",
    "sg:classifiers":[
        {
            "category":"Education",
            "subcategory":"Vocational School",
            "type":"Public Place"
        }
    ],
    "sg:phone":"+1 626 312 4732",
    "sg:postcode":"91803",
    "sg:province":"CA",
    "sg:tags":[
        "technical",
        "trade"
    ],
    "sg:website":"www.cci.edu",
    "wof:name":"Cci Alhambra 180",
    "wof:placetype":"venue"
},
  "geometry": {"coordinates":[-118.151765,34.079417],"type":"Point"}
}