{
  "type": "Feature",
  "properties": {
    "iso:country":"US",
    "sg:address":"1415 W Garvey Ave N",
    "sg:city":"West Covina",
    "sg:classifiers":[
        {
            "category":"Wholesale",
            "subcategory":"Groceries",
            "type":"Manufacturing & Wholesale Goods"
        }
    ],
    "sg:phone":"+1 626 960 2727",
    "sg:postcode":"91790",
    "sg:province":"CA",
    "sg:tags":[
        "food",
        "broker"
    ],
    "wof:name":"Concept Food Brokers",
    "wof:placetype":"venue"
},
  "geometry": {"coordinates":[-117.937881,34.072728],"type":"Point"}
}