{
  "type": "Feature",
  "properties": {
    "iso:country":"US",
    "sg:address":"2426 Glen Canyon Rd",
    "sg:city":"Santa Cruz",
    "sg:classifiers":[
        {
            "category":"Shopping",
            "subcategory":"Computers & Home Electronics",
            "type":"Retail Goods"
        }
    ],
    "sg:phone":"+1 831 438 3510",
    "sg:postcode":"95060",
    "sg:province":"CA",
    "sg:tags":[
        "software"
    ],
    "wof:name":"Rogue Wave Software Inc",
    "wof:placetype":"venue"
},
  "geometry": {"coordinates":[-122.020298,37.026602],"type":"Point"}
}