{
  "type": "Feature",
  "properties": {
    "addr:full":"236 8th Ave La Puente CA 91746",
    "addr:housenumber":"236",
    "addr:postcode":"91746",
    "addr:street":"8Th Ave",
    "iso:country":"US",
    "sg:address":"236 8th Ave",
    "sg:city":"La Puente",
    "sg:classifiers":[
        {
            "category":"Manufacturing",
            "subcategory":"Paper Products",
            "type":"Manufacturing & Wholesale Goods"
        }
    ],
    "sg:phone":"+1 626 336 8689",
    "sg:postcode":"91746",
    "sg:province":"CA",
    "sg:tags":[
        "stationery"
    ],
    "sg:website":"www.greenwichint.com",
    "wof:name":"Greenwich International",
    "wof:placetype":"venue"
},
  "geometry": {"coordinates":[-117.973581,34.0301],"type":"Point"}
}