{
  "type": "Feature",
  "properties": {
    "addr:full":"27811 Ave Hopkins Valencia CA 91355",
    "addr:housenumber":"27811",
    "addr:postcode":"91355",
    "addr:street":"Ave Hopkins",
    "iso:country":"US",
    "sg:address":"27811 Ave Hopkins",
    "sg:city":"Valencia",
    "sg:classifiers":[
        {
            "category":"Shopping",
            "subcategory":"Computers & Home Electronics",
            "type":"Retail Goods"
        }
    ],
    "sg:phone":"+1 661 255 1617",
    "sg:postcode":"91355",
    "sg:province":"CA",
    "sg:tags":[
        "television",
        "radio"
    ],
    "wof:name":"T V Maintenance",
    "wof:placetype":"venue"
},
  "geometry": {"coordinates":[-118.57440800000001,34.432698],"type":"Point"}
}