{
  "type": "Feature",
  "properties": {
    "iso:country":"US",
    "sg:address":"14204 Frame Rd",
    "sg:city":"Poway",
    "sg:classifiers":[
        {
            "category":"Building & Trades",
            "subcategory":"Plumbing",
            "type":"Services"
        }
    ],
    "sg:phone":"+1 858 679 8100",
    "sg:postcode":"92064",
    "sg:province":"CA",
    "sg:tags":[
        "conditioning",
        "air",
        "system",
        "contractor"
    ],
    "wof:name":"All Weather Plumbing Heating",
    "wof:placetype":"venue"
},
  "geometry": {"coordinates":[-117.060949,32.97083],"type":"Point"}
}