{
  "type": "Feature",
  "properties": {
    "iso:country":"US",
    "sg:address":"29224 S Lake Shore Dr",
    "sg:city":"Agoura Hills",
    "sg:classifiers":[
        {
            "category":"Shopping",
            "subcategory":"Photographic Equipment",
            "type":"Retail Goods"
        }
    ],
    "sg:phone":"+1 818 865 6099",
    "sg:postcode":"91301",
    "sg:province":"CA",
    "sg:tags":[
        "supply"
    ],
    "wof:name":"Camera Truckcom",
    "wof:placetype":"venue"
},
  "geometry": {"coordinates":[-118.75899200000001,34.106349],"type":"Point"}
}