{
  "type": "Feature",
  "properties": {
    "addr:full":"22801 Ventura Blvd Woodland Hills CA 91364",
    "addr:housenumber":"22801",
    "addr:postcode":"91364",
    "addr:street":"Ventura Blvd",
    "iso:country":"US",
    "sg:address":"22801 Ventura Blvd",
    "sg:city":"Woodland Hills",
    "sg:classifiers":[
        {
            "category":"Arts & Performance",
            "subcategory":"Theater",
            "type":"Entertainment"
        }
    ],
    "sg:phone":"+1 818 224 3210",
    "sg:postcode":"91364",
    "sg:province":"CA",
    "sg:tags":[
        "television",
        "program",
        "producer"
    ],
    "wof:name":"Headquarters Productions",
    "wof:placetype":"venue"
},
  "geometry": {"coordinates":[-118.624289,34.165721],"type":"Point"}
}