{
  "type": "Feature",
  "properties": {
    "addr:full":"1311 W El Segundo Boulevard Compton CA 90222",
    "addr:housenumber":"1311",
    "addr:postcode":"90222",
    "addr:street":"W El Segundo Boulevard",
    "iso:country":"US",
    "sg:address":"1311 W El Segundo Boulevard",
    "sg:city":"Compton",
    "sg:classifiers":[
        {
            "category":"Building & Trades",
            "subcategory":"Pest Control",
            "type":"Services"
        }
    ],
    "sg:phone":"+1 310 537 8221",
    "sg:postcode":"90222",
    "sg:province":"CA",
    "wof:name":"3 D Pest Control Company",
    "wof:placetype":"venue"
},
  "geometry": {"coordinates":[-118.245645,33.916162],"type":"Point"}
}