{
  "type": "Feature",
  "properties": {
    "addr:full":"900 W 17th St Santa Ana CA 92706",
    "addr:housenumber":"900",
    "addr:postcode":"92706",
    "addr:street":"W 17Th St",
    "iso:country":"US",
    "sg:address":"900 W 17th St",
    "sg:city":"Santa Ana",
    "sg:classifiers":[
        {
            "category":"Wholesale",
            "subcategory":"Groceries",
            "type":"Manufacturing & Wholesale Goods"
        }
    ],
    "sg:phone":"+1 714 836 1912",
    "sg:postcode":"92706",
    "sg:province":"CA",
    "wof:name":"Ajb Enterprises",
    "wof:placetype":"venue"
},
  "geometry": {"coordinates":[-117.87742799999999,33.760053],"type":"Point"}
}