{
  "type": "Feature",
  "properties": {
    "addr:full":"500 N Ventura Ave Ventura CA 93001",
    "addr:housenumber":"500",
    "addr:postcode":"93001",
    "addr:street":"N Ventura Ave",
    "iso:country":"US",
    "sg:address":"500 N Ventura Ave",
    "sg:city":"Ventura",
    "sg:classifiers":[
        {
            "category":"Retail",
            "subcategory":"Auto Repair",
            "type":"Services"
        }
    ],
    "sg:phone":"+1 805 648 5262",
    "sg:postcode":"93001",
    "sg:province":"CA",
    "sg:tags":[
        "repairing",
        "automobile"
    ],
    "wof:name":"Ventura Automotive Repair",
    "wof:placetype":"venue"
},
  "geometry": {"coordinates":[-119.29895999999999,34.287082],"type":"Point"}
}