{
  "type": "Feature",
  "properties": {
    "addr:full":"9800 Topanga Canyon Blvd Chatsworth CA 91311",
    "addr:postcode":"9800;91311",
    "addr:street":"Topanga Canyon Blvd",
    "iso:country":"US",
    "sg:address":"9800 Topanga Canyon Blvd",
    "sg:city":"Chatsworth",
    "sg:classifiers":[
        {
            "category":"Wholesale",
            "subcategory":"Scrap",
            "type":"Manufacturing & Wholesale Goods"
        }
    ],
    "sg:phone":"+1 818 709 6264",
    "sg:postcode":"91311",
    "sg:province":"CA",
    "sg:tags":[
        "rag"
    ],
    "wof:name":"Gold Mine Enterprises",
    "wof:placetype":"venue"
},
  "geometry": {"coordinates":[-118.60596,34.249967],"type":"Point"}
}