{
  "type": "Feature",
  "properties": {
    "addr:full":"12047 Riverside Dr Lakeside CA 92040",
    "addr:housenumber":"12047",
    "addr:postcode":"92040",
    "addr:street":"Riverside Dr",
    "iso:country":"US",
    "sg:address":"12047 Riverside Dr",
    "sg:city":"Lakeside",
    "sg:classifiers":[
        {
            "category":"Retail",
            "subcategory":"Repair Shop",
            "type":"Services"
        }
    ],
    "sg:phone":"+1 619 390 3797",
    "sg:postcode":"92040",
    "sg:province":"CA",
    "sg:tags":[
        "street",
        "lighting",
        "standard"
    ],
    "wof:name":"Patterson Brothers Lighting",
    "wof:placetype":"venue"
},
  "geometry": {"coordinates":[-116.93359700000001,32.866041],"type":"Point"}
}