{
  "type": "Feature",
  "properties": {
    "iso:country":"US",
    "sg:address":"415 E Olive Ave",
    "sg:city":"Turlock",
    "sg:classifiers":[
        {
            "category":"Personal",
            "subcategory":"Beauty Salon",
            "type":"Services"
        }
    ],
    "sg:phone":"+1 209 668 4628",
    "sg:postcode":"95380",
    "sg:province":"CA",
    "wof:name":"Jax Hair Co",
    "wof:placetype":"venue"
},
  "geometry": {"coordinates":[-120.844894,37.496941],"type":"Point"}
}