{
  "type": "Feature",
  "properties": {
    "addr:full":"3626 Saviers Rd Oxnard CA 93033",
    "addr:housenumber":"3626",
    "addr:postcode":"93033",
    "addr:street":"Saviers Rd",
    "iso:country":"US",
    "sg:address":"3626 Saviers Rd",
    "sg:city":"Oxnard",
    "sg:classifiers":[
        {
            "category":"Food & Beverages",
            "subcategory":"Groceries & Convenience Stores",
            "type":"Retail Goods"
        }
    ],
    "sg:phone":"+1 805 487 0577",
    "sg:postcode":"93033",
    "sg:province":"CA",
    "wof:name":"Oriental Mini Mart",
    "wof:placetype":"venue"
},
  "geometry": {"coordinates":[-119.177531,34.169066],"type":"Point"}
}