{
  "type": "Feature",
  "properties": {
    "iso:country":"US",
    "sg:address":"301 N Garfield Ave Ste D102",
    "sg:city":"Monterey Park",
    "sg:classifiers":[
        {
            "category":"Restaurant",
            "type":"Food & Drink"
        }
    ],
    "sg:phone":"+1 626 571 8387",
    "sg:postcode":"91754",
    "sg:province":"CA",
    "wof:name":"Yun Chuan Garden, Inc.",
    "wof:placetype":"venue"
},
  "geometry": {"coordinates":[-118.122871,34.064961],"type":"Point"}
}