{
  "type": "Feature",
  "properties": {
    "iso:country":"US",
    "sg:address":"1542 S Santa Fe Ave",
    "sg:city":"Vista",
    "sg:classifiers":[
        {
            "category":"Real Estate",
            "subcategory":"Real Estate Agent",
            "type":"Services"
        }
    ],
    "sg:phone":"+1 760 758 3333",
    "sg:postcode":"92084",
    "sg:province":"CA",
    "wof:name":"Meier Realty",
    "wof:placetype":"venue"
},
  "geometry": {"coordinates":[-117.217015,33.181541],"type":"Point"}
}