{
  "type": "Feature",
  "properties": {
    "iso:country":"US",
    "sg:address":"2448 Johnson Ave",
    "sg:city":"San Luis Obispo",
    "sg:classifiers":[
        {
            "category":"Building & Trades",
            "subcategory":"Plumbing",
            "type":"Services"
        }
    ],
    "sg:phone":"+1 805 543 7388",
    "sg:postcode":"93401",
    "sg:province":"CA",
    "sg:tags":[
        "plumbing",
        "contractor"
    ],
    "wof:name":"Gillespie Plumbing",
    "wof:placetype":"venue"
},
  "geometry": {"coordinates":[-120.644179,35.271919],"type":"Point"}
}