{
  "type": "Feature",
  "properties": {
    "iso:country":"US",
    "sg:address":"570 Bowker Rd",
    "sg:city":"Calexico",
    "sg:classifiers":[
        {
            "category":"Retail",
            "subcategory":"Auto Repair",
            "type":"Services"
        }
    ],
    "sg:phone":"+1 760 357 3257",
    "sg:postcode":"92231",
    "sg:province":"CA",
    "sg:tags":[
        "wrecker"
    ],
    "wof:name":"Johnson's Service",
    "wof:placetype":"venue"
},
  "geometry": {"coordinates":[-115.465277,32.680825],"type":"Point"}
}