{
  "type": "Feature",
  "properties": {
    "addr:full":"1970 Taylor Rd Bethel Island CA 94511",
    "addr:housenumber":"1970",
    "addr:postcode":"94511",
    "addr:street":"Taylor Rd",
    "iso:country":"US",
    "sg:address":"1970 Taylor Rd",
    "sg:city":"Bethel Island",
    "sg:classifiers":[
        {
            "category":"Recreation",
            "subcategory":"Marina",
            "type":"Entertainment"
        }
    ],
    "sg:phone":"+1 925 684 2657",
    "sg:postcode":"94511",
    "sg:province":"CA",
    "wof:name":"New Anchor Marina",
    "wof:placetype":"venue"
},
  "geometry": {"coordinates":[-121.658779,38.024982],"type":"Point"}
}