{
  "type": "Feature",
  "properties": {
    "addr:full":"2512 Samaritan Ct San Jose CA 95124",
    "addr:housenumber":"2512",
    "addr:postcode":"95124",
    "addr:street":"Samaritan Ct",
    "iso:country":"US",
    "sg:address":"2512 Samaritan Ct",
    "sg:city":"San Jose",
    "sg:classifiers":[
        {
            "category":"Health Services",
            "subcategory":"Doctor",
            "type":"Services"
        }
    ],
    "sg:phone":"+1 408 356 3181",
    "sg:postcode":"95124",
    "sg:province":"CA",
    "wof:name":"Seng Helen MD",
    "wof:placetype":"venue"
},
  "geometry": {"coordinates":[-121.949997,37.251202],"type":"Point"}
}