{
  "type": "Feature",
  "properties": {
    "addr:full":"964 Weber Cir Ventura CA 93003",
    "addr:housenumber":"964",
    "addr:postcode":"93003",
    "addr:street":"Weber Cir",
    "iso:country":"US",
    "sg:address":"964 Weber Cir",
    "sg:city":"Ventura",
    "sg:classifiers":[
        {
            "category":"Home & Garden",
            "subcategory":"Hardware",
            "type":"Retail Goods"
        }
    ],
    "sg:phone":"+1 805 642 9240",
    "sg:postcode":"93003",
    "sg:province":"CA",
    "wof:name":"Ocean Blue Tools",
    "wof:placetype":"venue"
},
  "geometry": {"coordinates":[-119.22967,34.264856],"type":"Point"}
}