{
  "type": "Feature",
  "properties": {
    "iso:country":"US",
    "sg:address":"1325 E Julian St",
    "sg:city":"San Jose",
    "sg:classifiers":[
        {
            "category":"Home & Garden",
            "subcategory":"Building Materials",
            "type":"Retail Goods"
        }
    ],
    "sg:phone":"+1 408 993 9710",
    "sg:postcode":"95116",
    "sg:province":"CA",
    "wof:name":"Gypsum Drywall Supply",
    "wof:placetype":"venue"
},
  "geometry": {"coordinates":[-121.868764,37.352522],"type":"Point"}
}