{
  "type": "Feature",
  "properties": {
    "addr:full":"12018 Bonavista Ln Whittier CA 90604",
    "addr:housenumber":"12018",
    "addr:postcode":"90604",
    "addr:street":"Bonavista Ln",
    "iso:country":"US",
    "sg:address":"12018 Bonavista Ln",
    "sg:city":"Whittier",
    "sg:classifiers":[
        {
            "category":"Health Services",
            "subcategory":"Clinic",
            "type":"Services"
        }
    ],
    "sg:phone":"+1 562 944 0108",
    "sg:postcode":"90604",
    "sg:province":"CA",
    "sg:tags":[
        "welfare"
    ],
    "wof:name":"Monique Home Health Care",
    "wof:placetype":"venue"
},
  "geometry": {"coordinates":[-118.031408,33.920477],"type":"Point"}
}