{
  "type": "Feature",
  "properties": {
    "addr:full":"13709 Burbank Blvd Van Nuys CA 91401",
    "addr:housenumber":"13709",
    "addr:postcode":"91401",
    "addr:street":"Burbank Blvd",
    "iso:country":"US",
    "sg:address":"13709 Burbank Blvd",
    "sg:city":"Van Nuys",
    "sg:classifiers":[
        {
            "category":"Wholesale",
            "subcategory":"Non-durable Goods",
            "type":"Manufacturing & Wholesale Goods"
        }
    ],
    "sg:phone":"+1 818 779 0242",
    "sg:postcode":"91401",
    "sg:province":"CA",
    "wof:name":"Milestone Awards & Marketing",
    "wof:placetype":"venue"
},
  "geometry": {"coordinates":[-118.432033,34.1722],"type":"Point"}
}