{
  "type": "Feature",
  "properties": {
    "addr:full":"268 Granite St Simi Valley CA 93065",
    "addr:housenumber":"268",
    "addr:postcode":"93065",
    "addr:street":"Granite St",
    "iso:country":"US",
    "sg:address":"268 Granite St",
    "sg:city":"Simi Valley",
    "sg:classifiers":[
        {
            "category":"Building & Trades",
            "subcategory":"Pest Control",
            "type":"Services"
        }
    ],
    "sg:phone":"+1 805 578 0117",
    "sg:postcode":"93065",
    "sg:province":"CA",
    "wof:name":"Carter's Pest Control",
    "wof:placetype":"venue"
},
  "geometry": {"coordinates":[-118.79341599999999,34.244675],"type":"Point"}
}