{
  "type": "Feature",
  "properties": {
    "iso:country":"US",
    "sg:address":"7303 Cam Tassajara",
    "sg:city":"Pleasanton",
    "sg:classifiers":[
        {
            "category":"Retail",
            "subcategory":"Animal Services",
            "type":"Services"
        }
    ],
    "sg:phone":"+1 925 828 6449",
    "sg:postcode":"94588",
    "sg:province":"CA",
    "wof:name":"Tassajara Kennel",
    "wof:placetype":"venue"
},
  "geometry": {"coordinates":[-121.871262,37.727218],"type":"Point"}
}