{
  "type": "Feature",
  "properties": {
    "iso:country":"US",
    "sg:address":"751 7th Ave",
    "sg:city":"San Diego",
    "sg:classifiers":[
        {
            "category":"Professional",
            "subcategory":"Business Services",
            "type":"Services"
        }
    ],
    "sg:phone":"+1 619 235 2662",
    "sg:postcode":"92101",
    "sg:province":"CA",
    "sg:tags":[
        "translator",
        "interpreter"
    ],
    "wof:name":"Scribe Consulting",
    "wof:placetype":"venue"
},
  "geometry": {"coordinates":[-117.158252,32.713096],"type":"Point"}
}