{
  "type": "Feature",
  "properties": {
    "addr:full":"5451 Avenida Encinas Ste D Carlsbad CA 92008",
    "addr:housenumber":"5451",
    "addr:postcode":"92008",
    "addr:street":"Avenida Encinas Ste D",
    "iso:country":"US",
    "sg:address":"5451 Avenida Encinas Ste D",
    "sg:city":"Carlsbad",
    "sg:classifiers":[
        {
            "category":"Retail",
            "subcategory":"Portrait Studio",
            "type":"Services"
        }
    ],
    "sg:phone":"+1 760 931 6809",
    "sg:postcode":"92008",
    "sg:province":"CA",
    "sg:tags":[
        "photography",
        "store"
    ],
    "sg:website":"www.northcoastphoto.com/",
    "wof:name":"North Coast Photo",
    "wof:placetype":"venue"
},
  "geometry": {"coordinates":[-117.326404,33.12842],"type":"Point"}
}