{
  "type": "Feature",
  "properties": {
    "iso:country":"US",
    "sg:address":"707 Elm St",
    "sg:city":"San Carlos",
    "sg:classifiers":[
        {
            "category":"Social Services",
            "subcategory":"Adult Care",
            "type":"Services"
        }
    ],
    "sg:phone":"+1 650 595 1500",
    "sg:postcode":"94070",
    "sg:province":"CA",
    "sg:tags":[
        "home",
        "residential"
    ],
    "sg:website":"www.scelms.com",
    "wof:name":"San Carlos Elms",
    "wof:placetype":"venue"
},
  "geometry": {"coordinates":[-122.25976,37.502491],"type":"Point"}
}