{
  "type": "Feature",
  "properties": {
    "addr:full":"1104 S Los Angeles St Los Angeles CA 90015",
    "addr:housenumber":"1104",
    "addr:postcode":"90015",
    "addr:street":"S;Angeles St",
    "iso:country":"US",
    "sg:address":"1104 S Los Angeles St",
    "sg:city":"Los Angeles",
    "sg:classifiers":[
        {
            "category":"Wholesale",
            "subcategory":"Non-durable Goods",
            "type":"Manufacturing & Wholesale Goods"
        }
    ],
    "sg:phone":"+1 213 747 0849",
    "sg:postcode":"90015",
    "sg:province":"CA",
    "wof:name":"A C T Group Inc",
    "wof:placetype":"venue"
},
  "geometry": {"coordinates":[-118.258225,34.036949],"type":"Point"}
}