{
  "type": "Feature",
  "properties": {
    "addr:full":"555 Brundage Ln Bakersfield CA 93304",
    "addr:housenumber":"555",
    "addr:postcode":"93304",
    "addr:street":"Brundage Ln",
    "iso:country":"US",
    "sg:address":"555 Brundage Ln",
    "sg:city":"Bakersfield",
    "sg:classifiers":[
        {
            "category":"Food & Beverages",
            "subcategory":"Groceries & Convenience Stores",
            "type":"Retail Goods"
        }
    ],
    "sg:phone":"+1 661 328 9930",
    "sg:postcode":"93304",
    "sg:province":"CA",
    "sg:tags":[
        "grocer"
    ],
    "wof:name":"Family Food",
    "wof:placetype":"venue"
},
  "geometry": {"coordinates":[-119.007206,35.353836],"type":"Point"}
}