{
  "type": "Feature",
  "properties": {
    "addr:full":"1632 Firestone Boulevard Los Angeles CA 90001",
    "addr:housenumber":"1632",
    "addr:postcode":"90001",
    "addr:street":"Firestone Boulevard",
    "iso:country":"US",
    "sg:address":"1632 Firestone Boulevard",
    "sg:city":"Los Angeles",
    "sg:classifiers":[
        {
            "category":"Restaurant",
            "type":"Food & Drink"
        }
    ],
    "sg:phone":"+1 323 584 6119",
    "sg:postcode":"90001",
    "sg:province":"CA",
    "wof:name":"Hong Kong Bowl",
    "wof:placetype":"venue"
},
  "geometry": {"coordinates":[-118.244646,33.960056],"type":"Point"}
}