{
  "type": "Feature",
  "properties": {
    "iso:country":"US",
    "sg:address":"5 Windemere Ln",
    "sg:city":"Aptos",
    "sg:classifiers":[
        {
            "category":"Building & Trades",
            "subcategory":"Construction",
            "type":"Services"
        }
    ],
    "sg:phone":"+1 831 662 9305",
    "sg:postcode":"95003",
    "sg:province":"CA",
    "sg:tags":[
        "roofing",
        "industrial",
        "contractors-commercial",
        "contractor"
    ],
    "wof:name":"Brooks Roofing",
    "wof:placetype":"venue"
},
  "geometry": {"coordinates":[-121.91202800000001,36.982925],"type":"Point"}
}