{
  "type": "Feature",
  "properties": {
    "addr:full":"19 Hamilton Dr Novato CA 94949",
    "addr:housenumber":"19",
    "addr:postcode":"94949",
    "addr:street":"Hamilton Dr",
    "iso:country":"US",
    "sg:address":"19 Hamilton Dr",
    "sg:city":"Novato",
    "sg:classifiers":[
        {
            "category":"Home & Garden",
            "subcategory":"Furniture",
            "type":"Retail Goods"
        }
    ],
    "sg:phone":"+1 415 883 3304",
    "sg:postcode":"94949",
    "sg:province":"CA",
    "wof:name":"Office World Inc",
    "wof:placetype":"venue"
},
  "geometry": {"coordinates":[-122.53983700000001,38.074621],"type":"Point"}
}