{
  "type": "Feature",
  "properties": {
    "addr:full":"3126 Oak Knoll Dr West Covina CA 91791",
    "addr:housenumber":"3126",
    "addr:postcode":"91791",
    "addr:street":"Oak Knoll Dr",
    "iso:country":"US",
    "sg:address":"3126 Oak Knoll Dr",
    "sg:city":"West Covina",
    "sg:classifiers":[
        {
            "category":"Building & Trades",
            "subcategory":"Construction",
            "type":"Services"
        }
    ],
    "sg:phone":"+1 626 966 8095",
    "sg:postcode":"91791",
    "sg:province":"CA",
    "sg:tags":[
        "house"
    ],
    "wof:name":"Walton Construction",
    "wof:placetype":"venue"
},
  "geometry": {"coordinates":[-117.878754,34.06948],"type":"Point"}
}