{
  "type": "Feature",
  "properties": {
    "iso:country":"US",
    "sg:address":"2645 Point Reyes Way",
    "sg:city":"Sacramento",
    "sg:classifiers":[
        {
            "category":"Communications",
            "subcategory":"Television Station",
            "type":"Services"
        }
    ],
    "sg:phone":"+1 916 364 1260",
    "sg:postcode":"95826",
    "sg:province":"CA",
    "sg:tags":[
        "satellite",
        "antenna",
        "cable",
        "tv",
        "system",
        "equipment"
    ],
    "wof:name":"Rey Satellites System",
    "wof:placetype":"venue"
},
  "geometry": {"coordinates":[-121.365143,38.563804],"type":"Point"}
}