{
  "type": "Feature",
  "properties": {
    "addr:full":"437 J St San Diego CA 92101",
    "addr:housenumber":"437",
    "addr:postcode":"92101",
    "addr:street":"J St",
    "iso:country":"US",
    "sg:address":"437 J St",
    "sg:city":"San Diego",
    "sg:classifiers":[
        {
            "category":"Real Estate",
            "subcategory":"Real Estate Services",
            "type":"Services"
        }
    ],
    "sg:phone":"+1 619 239 5815",
    "sg:postcode":"92101",
    "sg:province":"CA",
    "sg:tags":[
        "management",
        "property"
    ],
    "wof:name":"P J Property Management",
    "wof:placetype":"venue"
},
  "geometry": {"coordinates":[-117.160004,32.709499],"type":"Point"}
}