{
  "type": "Feature",
  "properties": {
    "addr:full":"656 E San Bernardino Rd Covina CA 91723",
    "addr:housenumber":"656",
    "addr:postcode":"91723",
    "addr:street":"E San Bernardino Rd",
    "iso:country":"US",
    "sg:address":"656 E San Bernardino Rd",
    "sg:city":"Covina",
    "sg:classifiers":[
        {
            "category":"Building & Trades",
            "subcategory":"Construction",
            "type":"Services"
        }
    ],
    "sg:phone":"+1 626 967 5790",
    "sg:postcode":"91723",
    "sg:province":"CA",
    "sg:tags":[
        "contractor"
    ],
    "wof:name":"Ramirez Construction",
    "wof:placetype":"venue"
},
  "geometry": {"coordinates":[-117.877987,34.090931],"type":"Point"}
}