{
  "type": "Feature",
  "properties": {
    "iso:country":"US",
    "sg:address":"1072 Folsom St, Suite 342",
    "sg:city":"San Francisco",
    "sg:classifiers":[
        {
            "category":"Building & Trades",
            "subcategory":"Plumbing",
            "type":"Services"
        }
    ],
    "sg:phone":"+1 415 261 2413",
    "sg:postcode":"94103",
    "sg:province":"CA",
    "wof:name":"Bayshore Plumbing Services",
    "wof:placetype":"venue"
},
  "geometry": {"coordinates":[-122.40735100000001,37.777447],"type":"Point"}
}