{
  "type": "Feature",
  "properties": {
    "iso:country":"US",
    "sg:address":"8421 Wilshire Blvd",
    "sg:city":"Beverly Hills",
    "sg:classifiers":[
        {
            "category":"Health Services",
            "subcategory":"Doctor",
            "type":"Services"
        }
    ],
    "sg:phone":"+1 323 658 8975",
    "sg:postcode":"90211",
    "sg:province":"CA",
    "wof:name":"Fishman Joel MA",
    "wof:placetype":"venue"
},
  "geometry": {"coordinates":[-118.374448,34.065177],"type":"Point"}
}