{
  "type": "Feature",
  "properties": {
    "iso:country":"US",
    "sg:address":"7956 Lester Ave",
    "sg:city":"Lemon Grove",
    "sg:classifiers":[
        {
            "category":"Building & Trades",
            "subcategory":"Pest Control",
            "type":"Services"
        }
    ],
    "sg:phone":"+1 619 465 6872",
    "sg:postcode":"91945",
    "sg:province":"CA",
    "sg:tags":[
        "spraying"
    ],
    "wof:name":"GLS Spray Svc Inc",
    "wof:placetype":"venue"
},
  "geometry": {"coordinates":[-117.02806,32.743818],"type":"Point"}
}