{
  "type": "Feature",
  "properties": {
    "addr:full":"23315 Main St Carson CA 90745",
    "addr:housenumber":"23315",
    "addr:postcode":"90745",
    "addr:street":"Main St",
    "iso:country":"US",
    "sg:address":"23315 Main St",
    "sg:city":"Carson",
    "sg:classifiers":[
        {
            "category":"Food & Beverages",
            "subcategory":"Liquor & Beverages",
            "type":"Retail Goods"
        }
    ],
    "sg:phone":"+1 310 835 5206",
    "sg:postcode":"90745",
    "sg:province":"CA",
    "sg:tags":[
        "beer",
        "spirit",
        "wine"
    ],
    "wof:name":"Anchor T Corporation",
    "wof:placetype":"venue"
},
  "geometry": {"coordinates":[-118.27600099999999,33.813801],"type":"Point"}
}