{
  "type": "Feature",
  "properties": {
    "addr:full":"5800 STANFORD RANCH RD ROCKLIN CA 95765",
    "addr:housenumber":"5800",
    "addr:postcode":"95765",
    "addr:street":"Stanford Ranch Rd",
    "iso:country":"US",
    "sg:address":"5800 STANFORD RANCH RD",
    "sg:city":"ROCKLIN",
    "sg:classifiers":[
        {
            "category":"Health Services",
            "subcategory":"Dentist",
            "type":"Services"
        }
    ],
    "sg:phone":"+1 916 435 4222",
    "sg:postcode":"95765",
    "sg:province":"CA",
    "sg:tags":[
        "dentists-oral",
        "product",
        "dentists-cosmetic",
        "maxillofacial",
        "denture",
        "dentists-prosthodontists",
        "teeth",
        "dentists-pediatric",
        "dentists-orthodontists",
        "whitening",
        "dentistry",
        "implant",
        "surgery",
        "dentists-implantology"
    ],
    "sg:website":"http://www.scorzadds.com",
    "wof:name":"Stanford Ranch Family Dentistry",
    "wof:placetype":"venue"
},
  "geometry": {"coordinates":[-121.26196299999999,38.80003],"type":"Point"}
}