{
  "type": "Feature",
  "properties": {
    "addr:full":"368 28th St Oakland CA 94609",
    "addr:housenumber":"368",
    "addr:postcode":"94609",
    "addr:street":"28Th St",
    "iso:country":"US",
    "sg:address":"368 28th St",
    "sg:city":"Oakland",
    "sg:classifiers":[
        {
            "category":"Health Services",
            "subcategory":"Doctor",
            "type":"Services"
        }
    ],
    "sg:phone":"+1 510 204 8408",
    "sg:postcode":"94609",
    "sg:province":"CA",
    "wof:name":"Scott Robert MD",
    "wof:placetype":"venue"
},
  "geometry": {"coordinates":[-122.264999,37.816502],"type":"Point"}
}