{
  "type": "Feature",
  "properties": {
    "iso:country":"US",
    "sg:address":"4223 Glencoe Avenue",
    "sg:city":"Marina Del Rey",
    "sg:classifiers":[
        {
            "category":"Professional",
            "subcategory":"Lawyer & Legal Services",
            "type":"Services"
        }
    ],
    "sg:phone":"+1 310 301 8005",
    "sg:postcode":"90292",
    "sg:province":"CA",
    "sg:tags":[
        "divorce",
        "law",
        "family"
    ],
    "wof:name":"Steven R",
    "wof:placetype":"venue"
},
  "geometry": {"coordinates":[-118.441389,33.988377],"type":"Point"}
}