{
  "type": "Feature",
  "properties": {
    "iso:country":"US",
    "sg:address":"1612 W Glenoaks Blvd",
    "sg:city":"Glendale",
    "sg:classifiers":[
        {
            "category":"Sports & Exercise",
            "subcategory":"Gym",
            "type":"Entertainment"
        }
    ],
    "sg:phone":"+1 818 549 0700",
    "sg:postcode":"91201",
    "sg:province":"CA",
    "sg:tags":[
        "trainer"
    ],
    "wof:name":"All American Health Care",
    "wof:placetype":"venue"
},
  "geometry": {"coordinates":[-118.28800200000001,34.169899],"type":"Point"}
}