{
  "type": "Feature",
  "properties": {
    "iso:country":"US",
    "sg:address":"4343 Peralta Blvd",
    "sg:city":"Fremont",
    "sg:classifiers":[
        {
            "category":"Autos & Motor Vehicles",
            "subcategory":"Auto Supplies",
            "type":"Retail Goods"
        },
        {
            "category":"Retail",
            "subcategory":"Auto Repair",
            "type":"Services"
        }
    ],
    "sg:phone":"+1 510 796 9900",
    "sg:postcode":"94536",
    "sg:province":"CA",
    "sg:tags":[
        "automobile",
        "part",
        "truck"
    ],
    "sg:website":"http://clickserve.dartsearch.net/link/click?lid=43000000313869837&ds_s_kwgid=58000000006820725&ds_e_matchtype={MatchType}&ds_e_kwdid={OrderItemId}&ds_e_adid={AdId}&ds_url_v=2",
    "wof:name":"Stevenson Tire",
    "wof:placetype":"venue"
},
  "geometry": {"coordinates":[-122.00972299999999,37.55431],"type":"Point"}
}