{
  "type": "Feature",
  "properties": {
    "addr:full":"625 E Market St Stockton CA 95205",
    "addr:housenumber":"625",
    "addr:postcode":"95205",
    "addr:street":"E Market St",
    "iso:country":"US",
    "sg:address":"625 E Market St",
    "sg:city":"Stockton",
    "sg:classifiers":[
        {
            "category":"Building & Trades",
            "subcategory":"Plumbing",
            "type":"Services"
        }
    ],
    "sg:phone":"+1 209 460 0777",
    "sg:postcode":"95205",
    "sg:province":"CA",
    "sg:tags":[
        "conditioning",
        "air",
        "system",
        "contractor"
    ],
    "wof:name":"Breeze Air Systems",
    "wof:placetype":"venue"
},
  "geometry": {"coordinates":[-121.28196699999999,37.953064],"type":"Point"}
}