{
  "type": "Feature",
  "properties": {
    "iso:country":"US",
    "sg:address":"3540 Wilshire Blvd",
    "sg:city":"Los Angeles",
    "sg:classifiers":[
        {
            "category":"Shopping",
            "subcategory":"Gifts & Souvenirs",
            "type":"Retail Goods"
        }
    ],
    "sg:phone":"+1 213 388 3657",
    "sg:postcode":"90010",
    "sg:province":"CA",
    "sg:tags":[
        "shop"
    ],
    "wof:name":"Ever Green Smoke & Mini Market",
    "wof:placetype":"venue"
},
  "geometry": {"coordinates":[-118.301928,34.061659],"type":"Point"}
}