{
  "type": "Feature",
  "properties": {
    "addr:full":"500 Arbour Ln Hollister CA 95023",
    "addr:housenumber":"500",
    "addr:postcode":"hollister ca 95023",
    "addr:street":"Arbour Ln",
    "iso:country":"US",
    "sg:address":"500 Arbour Ln",
    "sg:city":"Hollister",
    "sg:classifiers":[
        {
            "category":"Retail",
            "subcategory":"Auto Rental",
            "type":"Services"
        }
    ],
    "sg:phone":"+1 831 637 0236",
    "sg:postcode":"95023",
    "sg:province":"CA",
    "sg:tags":[
        "leasing",
        "tractor"
    ],
    "wof:name":"4th Tractor Svc",
    "wof:placetype":"venue"
},
  "geometry": {"coordinates":[-121.391493,36.855747],"type":"Point"}
}