{
  "type": "Feature",
  "properties": {
    "addr:full":"697 N 4th St San Jose CA 95112",
    "addr:housenumber":"697",
    "addr:postcode":"95112",
    "addr:street":"N 4Th St",
    "iso:country":"US",
    "sg:address":"697 N 4th St",
    "sg:city":"San Jose",
    "sg:classifiers":[
        {
            "category":"Autos & Motor Vehicles",
            "subcategory":"Fuel & Gas Station",
            "type":"Retail Goods"
        }
    ],
    "sg:phone":"+1 408 286 7788",
    "sg:postcode":"95112",
    "sg:province":"CA",
    "wof:name":"Arco-Taylor Gas Company",
    "wof:placetype":"venue"
},
  "geometry": {"coordinates":[-121.897003,37.3503],"type":"Point"}
}