{
  "type": "Feature",
  "properties": {
    "iso:country":"US",
    "sg:address":"20 City Blvd W",
    "sg:city":"Orange",
    "sg:classifiers":[
        {
            "category":"Professional",
            "type":"Services"
        }
    ],
    "sg:phone":"+1 714 978 2123",
    "sg:postcode":"92868",
    "sg:province":"CA",
    "wof:name":"Virtual Games",
    "wof:placetype":"venue"
},
  "geometry": {"coordinates":[-117.894764,33.780216],"type":"Point"}
}