{
  "type": "Feature",
  "properties": {
    "iso:country":"US",
    "sg:address":"399 Chandler Pl",
    "sg:city":"San Bernardino",
    "sg:classifiers":[
        {
            "category":"Government",
            "subcategory":"Office",
            "type":"Public Place"
        }
    ],
    "sg:phone":"+1 909 384 5108",
    "sg:postcode":"92408",
    "sg:province":"CA",
    "sg:tags":[
        "village"
    ],
    "wof:name":"San Bernardino Water Rclmtn",
    "wof:placetype":"venue"
},
  "geometry": {"coordinates":[-117.292975,34.077479],"type":"Point"}
}