{
  "type": "Feature",
  "properties": {
    "iso:country":"US",
    "sg:address":"333 Crown Vista Dr",
    "sg:city":"Gardena",
    "sg:classifiers":[
        {
            "category":"Building & Trades",
            "subcategory":"Plumbing",
            "type":"Services"
        }
    ],
    "sg:phone":"+1 310 769 0116",
    "sg:postcode":"90248",
    "sg:province":"CA",
    "sg:tags":[
        "heating",
        "contractor"
    ],
    "wof:name":"Meadows Mechanical",
    "wof:placetype":"venue"
},
  "geometry": {"coordinates":[-118.27953100000001,33.896816],"type":"Point"}
}