{
  "type": "Feature",
  "properties": {
    "iso:country":"US",
    "sg:address":"8853 3rd Ave",
    "sg:city":"Hesperia",
    "sg:classifiers":[
        {
            "category":"Retail",
            "subcategory":"Repair Shop",
            "type":"Services"
        },
        {
            "category":"Wholesale",
            "subcategory":"Electrical",
            "type":"Manufacturing & Wholesale Goods"
        }
    ],
    "sg:phone":"+1 760 947 9917",
    "sg:postcode":"92345",
    "sg:province":"CA",
    "sg:tags":[
        "radio",
        "comm",
        "system",
        "electronic"
    ],
    "wof:name":"High Desert C B",
    "wof:placetype":"venue"
},
  "geometry": {"coordinates":[-117.309393,34.409202],"type":"Point"}
}