{
  "type": "Feature",
  "properties": {
    "iso:country":"US",
    "sg:address":"988 Market Street",
    "sg:city":"San Francisco",
    "sg:classifiers":[
        {
            "category":"Communications",
            "subcategory":"Newspaper",
            "type":"Services"
        }
    ],
    "sg:phone":"+1 415 826 1100",
    "sg:postcode":"94102",
    "sg:province":"CA",
    "sg:tags":[
        "print",
        "medium"
    ],
    "wof:name":"SF Independent",
    "wof:placetype":"venue"
},
  "geometry": {"coordinates":[-122.410004,37.7826],"type":"Point"}
}