{
  "type": "Feature",
  "properties": {
    "addr:full":"1130 N Lincoln Way Ste C Galt CA 95632",
    "addr:housenumber":"1130",
    "addr:postcode":"95632",
    "addr:street":"N Lincoln Way Ste C",
    "iso:country":"US",
    "sg:address":"1130 N Lincoln Way Ste C",
    "sg:city":"Galt",
    "sg:classifiers":[
        {
            "category":"Autos & Motor Vehicles",
            "subcategory":"Auto Supplies",
            "type":"Retail Goods"
        },
        {
            "category":"Retail",
            "subcategory":"Auto Repair",
            "type":"Services"
        }
    ],
    "sg:phone":"+1 209 745 1500",
    "sg:postcode":"95632",
    "sg:province":"CA",
    "sg:tags":[
        "exhaust",
        "automobile",
        "system",
        "accessory",
        "part",
        "muffler"
    ],
    "wof:name":"Performance Muffler & Brake",
    "wof:placetype":"venue"
},
  "geometry": {"coordinates":[-121.30037299999999,38.257555],"type":"Point"}
}