{
  "type": "Feature",
  "properties": {
    "addr:full":"315 E Avenue K Lancaster CA 93535",
    "addr:housenumber":"315",
    "addr:postcode":"93535",
    "addr:street":"E Avenue",
    "iso:country":"US",
    "sg:address":"315 E Avenue K",
    "sg:city":"Lancaster",
    "sg:classifiers":[
        {
            "category":"Place Of Worship",
            "type":"Public Place"
        }
    ],
    "sg:phone":"+1 661 949 7601",
    "sg:postcode":"93535",
    "sg:province":"CA",
    "sg:tags":[
        "church"
    ],
    "wof:name":"Diamond Black Gospel Prod",
    "wof:placetype":"venue"
},
  "geometry": {"coordinates":[-118.12440100000001,34.674993],"type":"Point"}
}