{
  "type": "Feature",
  "properties": {
    "addr:full":"3500 College Blvd Oceanside CA 92056",
    "addr:housenumber":"3500",
    "addr:postcode":"92056",
    "addr:street":"College Blvd",
    "iso:country":"US",
    "sg:address":"3500 College Blvd",
    "sg:city":"Oceanside",
    "sg:classifiers":[
        {
            "category":"Banks & Credit Unions",
            "subcategory":"Bank",
            "type":"Services"
        }
    ],
    "sg:phone":"+1 760 643 1900",
    "sg:postcode":"92056",
    "sg:province":"CA",
    "wof:name":"1st Pacific Bank of California",
    "wof:placetype":"venue"
},
  "geometry": {"coordinates":[-117.295998,33.181801],"type":"Point"}
}