{
  "type": "Feature",
  "properties": {
    "addr:full":"7751 Alabama Ave Ste. 11 Canoga Park CA 91304",
    "addr:housenumber":"7751",
    "addr:postcode":"91304",
    "addr:street":"Alabama Ave Ste. 11",
    "iso:country":"US",
    "sg:address":"7751 Alabama Ave Ste. 11",
    "sg:city":"Canoga Park",
    "sg:classifiers":[
        {
            "category":"Professional",
            "subcategory":"Computer Services",
            "type":"Services"
        }
    ],
    "sg:postcode":"91304",
    "sg:province":"CA",
    "sg:tags":[
        "free-digital-signage"
    ],
    "sg:website":"http://www.MediaSignage.com",
    "wof:name":"MediaSignage Inc.",
    "wof:placetype":"venue"
},
  "geometry": {"coordinates":[-118.599486,34.210992],"type":"Point"}
}