{
  "type": "Feature",
  "properties": {
    "iso:country":"US",
    "sg:address":"9747 Businesspark Ave",
    "sg:city":"San Diego",
    "sg:classifiers":[
        {
            "category":"Wholesale",
            "subcategory":"Seafood",
            "type":"Manufacturing & Wholesale Goods"
        }
    ],
    "sg:phone":"+1 858 693 3565",
    "sg:postcode":"92131",
    "sg:province":"CA",
    "sg:tags":[
        "fish"
    ],
    "wof:name":"Dicarlo Seafood Co",
    "wof:placetype":"venue"
},
  "geometry": {"coordinates":[-117.111969,32.900449],"type":"Point"}
}