{
  "type": "Feature",
  "properties": {
    "addr:full":"550 Montgomery St San Francisco CA 94111",
    "addr:housenumber":"550",
    "addr:postcode":"94111",
    "addr:street":"Montgomery St",
    "iso:country":"US",
    "sg:address":"550 Montgomery St",
    "sg:city":"San Francisco",
    "sg:classifiers":[
        {
            "category":"Professional",
            "subcategory":"Lawyer & Legal Services",
            "type":"Services"
        }
    ],
    "sg:phone":"+1 415 395 9331",
    "sg:postcode":"94111",
    "sg:province":"CA",
    "wof:name":"Hoffman Flora",
    "wof:placetype":"venue"
},
  "geometry": {"coordinates":[-122.402902,37.794386],"type":"Point"}
}