{
  "type": "Feature",
  "properties": {
    "iso:country":"US",
    "sg:address":"5713 Greenridge Rd",
    "sg:city":"Castro Valley",
    "sg:classifiers":[
        {
            "category":"Travel",
            "subcategory":"Hotels & Motels",
            "type":"Entertainment"
        }
    ],
    "sg:phone":"+1 510 582 9347",
    "sg:postcode":"94552",
    "sg:province":"CA",
    "sg:tags":[
        "operation"
    ],
    "wof:name":"Harry Inn",
    "wof:placetype":"venue"
},
  "geometry": {"coordinates":[-122.046078,37.708567],"type":"Point"}
}