{
  "type": "Feature",
  "properties": {
    "iso:country":"US",
    "sg:address":"2180 Garnet Ave",
    "sg:city":"San Diego",
    "sg:classifiers":[
        {
            "category":"Personal",
            "type":"Services"
        }
    ],
    "sg:phone":"+1 619 265 2558",
    "sg:postcode":"92109",
    "sg:province":"CA",
    "sg:tags":[
        "therapist",
        "massage"
    ],
    "wof:name":"A Sacred Place For Women",
    "wof:placetype":"venue"
},
  "geometry": {"coordinates":[-117.231368,32.801954],"type":"Point"}
}