{
  "type": "Feature",
  "properties": {
    "iso:country":"US",
    "sg:address":"2111 Research Dr",
    "sg:city":"Livermore",
    "sg:classifiers":[
        {
            "category":"Manufacturing",
            "subcategory":"Metals",
            "type":"Manufacturing & Wholesale Goods"
        }
    ],
    "sg:phone":"+1 925 371 7787",
    "sg:postcode":"94550",
    "sg:province":"CA",
    "sg:tags":[
        "product",
        "fabricated"
    ],
    "wof:name":"Machined Parts USA Inc",
    "wof:placetype":"venue"
},
  "geometry": {"coordinates":[-121.721279,37.678457],"type":"Point"}
}