{
  "type": "Feature",
  "properties": {
    "addr:full":"3402 W MacArthur Blvd Ste B Santa Ana CA 92704",
    "addr:housenumber":"3402",
    "addr:postcode":"92704",
    "addr:street":"W Macarthur Blvd Ste B",
    "iso:country":"US",
    "sg:address":"3402 W MacArthur Blvd Ste B",
    "sg:city":"Santa Ana",
    "sg:classifiers":[
        {
            "category":"Professional",
            "subcategory":"Printing & Photocopies",
            "type":"Services"
        }
    ],
    "sg:phone":"+1 714 979 2392",
    "sg:postcode":"92704",
    "sg:province":"CA",
    "wof:name":"SIR Speedy Printing Centers",
    "wof:placetype":"venue"
},
  "geometry": {"coordinates":[-117.916,33.702],"type":"Point"}
}