{
  "type": "Feature",
  "properties": {
    "iso:country":"US",
    "sg:address":"644 S Olive St",
    "sg:city":"Los Angeles",
    "sg:classifiers":[
        {
            "category":"Shopping",
            "subcategory":"Gifts & Souvenirs",
            "type":"Retail Goods"
        }
    ],
    "sg:phone":"+1 213 622 8757",
    "sg:postcode":"90014",
    "sg:province":"CA",
    "wof:name":"Olive Snack & Gift Shop",
    "wof:placetype":"venue"
},
  "geometry": {"coordinates":[-118.254963,34.0472],"type":"Point"}
}