{
  "type": "Feature",
  "properties": {
    "addr:full":"1024 Woodland Dr Turlock CA 95382",
    "addr:housenumber":"1024",
    "addr:postcode":"95382",
    "addr:street":"Woodland Dr",
    "iso:country":"US",
    "sg:address":"1024 Woodland Dr",
    "sg:city":"Turlock",
    "sg:classifiers":[
        {
            "category":"Freight",
            "type":"Transportation"
        }
    ],
    "sg:phone":"+1 209 678 1940",
    "sg:postcode":"95382",
    "sg:province":"CA",
    "sg:tags":[
        "operator",
        "local",
        "trucking"
    ],
    "wof:name":"M & B Trucking",
    "wof:placetype":"venue"
},
  "geometry": {"coordinates":[-120.861912,37.533512],"type":"Point"}
}