{
  "type": "Feature",
  "properties": {
    "iso:country":"US",
    "sg:address":"2687 Veteran Ave",
    "sg:city":"Los Angeles",
    "sg:classifiers":[
        {
            "category":"Building & Trades",
            "subcategory":"Landscaping Services",
            "type":"Services"
        }
    ],
    "sg:phone":"+1 310 478 0725",
    "sg:postcode":"90064",
    "sg:province":"CA",
    "sg:tags":[
        "tree",
        "trimming"
    ],
    "wof:name":"J & T Tree Co",
    "wof:placetype":"venue"
},
  "geometry": {"coordinates":[-118.428369,34.035654],"type":"Point"}
}