{
  "type": "Feature",
  "properties": {
    "addr:full":"555 State Hwy 20 E Upper Lake CA 95485",
    "addr:housenumber":"555",
    "addr:postcode":"95485",
    "addr:street":"State Hwy 20 E",
    "iso:country":"US",
    "sg:address":"555 State Hwy 20 E",
    "sg:city":"Upper Lake",
    "sg:classifiers":[
        {
            "category":"Autos & Motor Vehicles",
            "subcategory":"Auto Supplies",
            "type":"Retail Goods"
        }
    ],
    "sg:phone":"+1 707 275 2351",
    "sg:postcode":"95485",
    "sg:province":"CA",
    "sg:tags":[
        "automobile",
        "parts"
    ],
    "wof:name":"Handy Auto Supply",
    "wof:placetype":"venue"
},
  "geometry": {"coordinates":[-122.90607799999999,39.161728],"type":"Point"}
}