{
  "type": "Feature",
  "properties": {
    "iso:country":"US",
    "sg:address":"1312 Lincoln Blvd",
    "sg:city":"Santa Monica",
    "sg:classifiers":[
        {
            "category":"Organizations",
            "subcategory":"Professional Association",
            "type":"Services"
        }
    ],
    "sg:phone":"+1 310 451 0090",
    "sg:postcode":"90401",
    "sg:province":"CA",
    "wof:name":"Wedding & Portrait Phtgrphrs",
    "wof:placetype":"venue"
},
  "geometry": {"coordinates":[-118.491579,34.019666],"type":"Point"}
}