{
  "type": "Feature",
  "properties": {
    "iso:country":"US",
    "sg:address":"4540 Campus Dr",
    "sg:city":"Newport Beach",
    "sg:classifiers":[
        {
            "category":"Professional",
            "subcategory":"Accounting & Tax Preparation",
            "type":"Services"
        }
    ],
    "sg:phone":"+1 949 252 1242",
    "sg:postcode":"92660",
    "sg:province":"CA",
    "sg:tags":[
        "return"
    ],
    "wof:name":"Altieri Lino V Ltd",
    "wof:placetype":"venue"
},
  "geometry": {"coordinates":[-117.86561,33.671285],"type":"Point"}
}