{
  "type": "Feature",
  "properties": {
    "addr:full":"157 Van Ness Ave Santa Cruz CA 95060",
    "addr:housenumber":"157",
    "addr:postcode":"95060",
    "addr:street":"Van Ness Ave",
    "iso:country":"US",
    "sg:address":"157 Van Ness Ave",
    "sg:city":"Santa Cruz",
    "sg:classifiers":[
        {
            "category":"Real Estate",
            "subcategory":"Architect",
            "type":"Services"
        }
    ],
    "sg:phone":"+1 831 423 1316",
    "sg:postcode":"95060",
    "sg:province":"CA",
    "sg:website":"www.boonelow.com",
    "wof:name":"Boone & Low Architects & Planners",
    "wof:placetype":"venue"
},
  "geometry": {"coordinates":[-122.037003,36.9683],"type":"Point"}
}