{
  "type": "Feature",
  "properties": {
    "addr:full":"2020 N. Grand Ave. Santa Ana CA 92701",
    "addr:housenumber":"2020",
    "addr:postcode":"92701",
    "addr:street":"N. Grand Ave.",
    "iso:country":"US",
    "sg:address":"2020 N. Grand Ave.",
    "sg:city":"Santa Ana",
    "sg:classifiers":[
        {
            "category":"Restaurant",
            "type":"Food & Drink"
        }
    ],
    "sg:phone":"+1 714 835 2828",
    "sg:postcode":"92701",
    "sg:province":"CA",
    "sg:tags":[
        "chinese"
    ],
    "wof:name":"China Town Express",
    "wof:placetype":"venue"
},
  "geometry": {"coordinates":[-117.851876,33.762967],"type":"Point"}
}