{
  "type": "Feature",
  "properties": {
    "iso:country":"US",
    "sg:address":"3732 San Fernando Rd",
    "sg:city":"Glendale",
    "sg:classifiers":[
        {
            "category":"Professional",
            "type":"Services"
        },
        {
            "category":"Shopping",
            "subcategory":"Florist",
            "type":"Retail Goods"
        }
    ],
    "sg:phone":"+1 818 243 2326",
    "sg:postcode":"91204",
    "sg:province":"CA",
    "sg:tags":[
        "planning",
        "event"
    ],
    "sg:website":"www.thedezignshop.com",
    "wof:name":"Design Shop",
    "wof:placetype":"venue"
},
  "geometry": {"coordinates":[-118.25599699999999,34.124802],"type":"Point"}
}