{
  "type": "Feature",
  "properties": {
    "addr:full":"1855 E Vista Way Ste 9 Vista CA 92084",
    "addr:housenumber":"1855",
    "addr:postcode":"92084",
    "addr:street":"E Vista Way Ste 9",
    "iso:country":"US",
    "sg:address":"1855 E Vista Way Ste 9",
    "sg:city":"Vista",
    "sg:classifiers":[
        {
            "category":"Community Center",
            "type":"Public Place"
        }
    ],
    "sg:phone":"+1 760 940 1836",
    "sg:postcode":"92084",
    "sg:province":"CA",
    "sg:tags":[
        "medical"
    ],
    "wof:name":"Drug Court Vista",
    "wof:placetype":"venue"
},
  "geometry": {"coordinates":[-117.225998,33.227901],"type":"Point"}
}