{
  "type": "Feature",
  "properties": {
    "iso:country":"US",
    "sg:address":"22312 Kirkwood",
    "sg:city":"Lake Forest",
    "sg:classifiers":[
        {
            "category":"Manufacturing",
            "subcategory":"Printing",
            "type":"Manufacturing & Wholesale Goods"
        }
    ],
    "sg:phone":"+1 949 770 8050",
    "sg:postcode":"92630",
    "sg:province":"CA",
    "wof:name":"Southern California Bicyclist",
    "wof:placetype":"venue"
},
  "geometry": {"coordinates":[-117.696575,33.638546],"type":"Point"}
}