{
  "type": "Feature",
  "properties": {
    "addr:full":"74000 Country Club Dr Palm Desert CA 92260",
    "addr:housenumber":"74000",
    "addr:postcode":"ca 92260",
    "addr:street":"Country Club Dr",
    "iso:country":"US",
    "sg:address":"74000 Country Club Dr",
    "sg:city":"Palm Desert",
    "sg:classifiers":[
        {
            "category":"Health Services",
            "subcategory":"Doctor",
            "type":"Services"
        }
    ],
    "sg:phone":"+1 760 568 0108",
    "sg:postcode":"92260",
    "sg:province":"CA",
    "sg:tags":[
        "podiatrist"
    ],
    "sg:website":"www.coachellavalleypodiatrist.com",
    "wof:name":"Danciger Harvey R DPM",
    "wof:placetype":"venue"
},
  "geometry": {"coordinates":[-116.38099699999999,33.725201],"type":"Point"}
}