{
  "type": "Feature",
  "properties": {
    "addr:full":"820 N Hollywood Way Burbank CA 91505",
    "addr:housenumber":"820",
    "addr:postcode":"91505",
    "addr:street":"N Hollywood Way",
    "iso:country":"US",
    "sg:address":"820 N Hollywood Way",
    "sg:city":"Burbank",
    "sg:classifiers":[
        {
            "category":"Shopping",
            "subcategory":"Hobbies, Toys, & Games",
            "type":"Retail Goods"
        },
        {
            "category":"Shopping",
            "subcategory":"Books",
            "type":"Retail Goods"
        }
    ],
    "sg:phone":"+1 818 848 9144",
    "sg:postcode":"91505",
    "sg:province":"CA",
    "sg:tags":[
        "shop",
        "hobby",
        "bookstore"
    ],
    "wof:name":"The Last Grenadier",
    "wof:placetype":"venue"
},
  "geometry": {"coordinates":[-118.34538999999999,34.165281],"type":"Point"}
}