{
  "type": "Feature",
  "properties": {
    "iso:country":"US",
    "sg:address":"702 W Town And Country Rd",
    "sg:city":"Orange",
    "sg:classifiers":[
        {
            "category":"Real Estate",
            "subcategory":"Real Estate Agent",
            "type":"Services"
        }
    ],
    "sg:phone":"+1 714 245 5570",
    "sg:postcode":"92868",
    "sg:province":"CA",
    "wof:name":"Southern Calif., Ccim Chapter",
    "wof:placetype":"venue"
},
  "geometry": {"coordinates":[-117.859691,33.776539],"type":"Point"}
}