{
  "type": "Feature",
  "properties": {
    "addr:full":"2121 E Woodlyn Rd Pasadena CA 91104",
    "addr:housenumber":"2121",
    "addr:postcode":"91104",
    "addr:street":"E Woodlyn Rd",
    "iso:country":"US",
    "sg:address":"2121 E Woodlyn Rd",
    "sg:city":"Pasadena",
    "sg:classifiers":[
        {
            "category":"Education",
            "subcategory":"School",
            "type":"Public Place"
        }
    ],
    "sg:phone":"+1 626 794 8646",
    "sg:postcode":"91104",
    "sg:province":"CA",
    "wof:name":"Terrile Science & Technical",
    "wof:placetype":"venue"
},
  "geometry": {"coordinates":[-118.10855599999999,34.166978],"type":"Point"}
}