{
  "type": "Feature",
  "properties": {
    "iso:country":"US",
    "sg:address":"2341 Drake Ct",
    "sg:city":"Placerville",
    "sg:classifiers":[
        {
            "category":"Building & Trades",
            "subcategory":"Construction",
            "type":"Services"
        }
    ],
    "sg:phone":"+1 530 621 9978",
    "sg:postcode":"95667",
    "sg:province":"CA",
    "sg:tags":[
        "contractor"
    ],
    "wof:name":"Perez Drywall",
    "wof:placetype":"venue"
},
  "geometry": {"coordinates":[-120.843788,38.729178],"type":"Point"}
}