{
  "type": "Feature",
  "properties": {
    "iso:country":"US",
    "sg:address":"1225 Fallon St",
    "sg:city":"Oakland",
    "sg:classifiers":[
        {
            "category":"Government",
            "subcategory":"City Hall",
            "type":"Public Place"
        }
    ],
    "sg:phone":"+1 510 272 6906",
    "sg:postcode":"94612",
    "sg:province":"CA",
    "wof:name":"Ren? C. Davidson Alameda County Courthouse",
    "wof:placetype":"venue"
},
  "geometry": {"coordinates":[-122.262613,37.79972],"type":"Point"}
}