{
  "type": "Feature",
  "properties": {
    "addr:full":"1456 Railroad Ave Livermore CA 94550",
    "addr:housenumber":"1456",
    "addr:postcode":"94550",
    "addr:street":"Railroad Ave",
    "iso:country":"US",
    "sg:address":"1456 Railroad Ave",
    "sg:city":"Livermore",
    "sg:classifiers":[
        {
            "category":"Sports & Exercise",
            "subcategory":"Gym",
            "type":"Entertainment"
        }
    ],
    "sg:phone":"+1 925 447 4496",
    "sg:postcode":"94550",
    "sg:province":"CA",
    "sg:tags":[
        "club",
        "health",
        "studio",
        "gymnasium"
    ],
    "wof:name":"24 Hour Fitness",
    "wof:placetype":"venue"
},
  "geometry": {"coordinates":[-121.777012,37.681184],"type":"Point"}
}