{
  "type": "Feature",
  "properties": {
    "iso:country":"US",
    "sg:address":"2222 Workman St",
    "sg:city":"Los Angeles",
    "sg:classifiers":[
        {
            "category":"Shopping",
            "type":"Retail Goods"
        }
    ],
    "sg:phone":"+1 323 222 2093",
    "sg:postcode":"90031",
    "sg:province":"CA",
    "sg:tags":[
        "merchandise"
    ],
    "wof:name":"Silkflowersartcom",
    "wof:placetype":"venue"
},
  "geometry": {"coordinates":[-118.214326,34.071871],"type":"Point"}
}