{
  "type": "Feature",
  "properties": {
    "addr:full":"2560 Orange Ave Newport Beach CA 92627",
    "addr:housenumber":"2560",
    "addr:postcode":"92627",
    "addr:street":"Orange Ave",
    "iso:country":"US",
    "sg:address":"2560 Orange Ave",
    "sg:city":"Newport Beach",
    "sg:classifiers":[
        {
            "category":"Building & Trades",
            "subcategory":"Landscaping Services",
            "type":"Services"
        }
    ],
    "sg:phone":"+1 949 223 0000",
    "sg:postcode":"92627",
    "sg:province":"CA",
    "wof:name":"Costa Verde Landscape Inc",
    "wof:placetype":"venue"
},
  "geometry": {"coordinates":[-117.89461300000001,33.65953],"type":"Point"}
}