{
  "type": "Feature",
  "properties": {
    "addr:full":"22 E Main St Ione CA 95640",
    "addr:housenumber":"22",
    "addr:postcode":"ca 95640",
    "addr:street":"E Main St",
    "iso:country":"US",
    "sg:address":"22 E Main St",
    "sg:city":"Ione",
    "sg:classifiers":[
        {
            "category":"Government",
            "subcategory":"Post Office",
            "type":"Public Place"
        }
    ],
    "sg:phone":"+1 209 274 6478",
    "sg:postcode":"95640",
    "sg:province":"CA",
    "sg:tags":[
        "postal",
        "us"
    ],
    "sg:website":"www.usps.com",
    "wof:name":"US Post Office",
    "wof:placetype":"venue"
},
  "geometry": {"coordinates":[-120.93252699999999,38.352827],"type":"Point"}
}