{
  "type": "Feature",
  "properties": {
    "addr:full":"19725 Sherman Way Winnetka CA 91306",
    "addr:housenumber":"19725",
    "addr:postcode":"91306",
    "addr:street":"Sherman Way",
    "iso:country":"US",
    "sg:address":"19725 Sherman Way",
    "sg:city":"Winnetka",
    "sg:classifiers":[
        {
            "category":"Professional",
            "subcategory":"Accounting & Tax Preparation",
            "type":"Services"
        }
    ],
    "sg:phone":"+1 818 717 0855",
    "sg:postcode":"91306",
    "sg:province":"CA",
    "sg:tags":[
        "accountant"
    ],
    "wof:name":"Lawrence J Danny CPA",
    "wof:placetype":"venue"
},
  "geometry": {"coordinates":[-118.564013,34.201035],"type":"Point"}
}