{
  "type": "Feature",
  "properties": {
    "addr:full":"4455 Enterprise St Fremont CA 94538",
    "addr:housenumber":"4455",
    "addr:postcode":"94538",
    "addr:street":"Enterprise St",
    "iso:country":"US",
    "sg:address":"4455 Enterprise St",
    "sg:city":"Fremont",
    "sg:classifiers":[
        {
            "category":"Building & Trades",
            "subcategory":"Construction",
            "type":"Services"
        }
    ],
    "sg:phone":"+1 510 657 3686",
    "sg:postcode":"94538",
    "sg:province":"CA",
    "sg:tags":[
        "contractor"
    ],
    "wof:name":"Blocka",
    "wof:placetype":"venue"
},
  "geometry": {"coordinates":[-121.959929,37.503484],"type":"Point"}
}