{
  "type": "Feature",
  "properties": {
    "iso:country":"US",
    "sg:address":"1100 W Katella Ave",
    "sg:city":"Orange",
    "sg:classifiers":[
        {
            "category":"Professional",
            "subcategory":"Lawyer & Legal Services",
            "type":"Services"
        }
    ],
    "sg:phone":"+1 714 538 9700",
    "sg:postcode":"92867",
    "sg:province":"CA",
    "wof:name":"Orr Elizabeth Attorney At Law",
    "wof:placetype":"venue"
},
  "geometry": {"coordinates":[-117.862999,33.808998],"type":"Point"}
}