{
  "type": "Feature",
  "properties": {
    "iso:country":"US",
    "sg:address":"6383 Atlantic Ave",
    "sg:city":"Bell",
    "sg:classifiers":[
        {
            "category":"Real Estate",
            "subcategory":"Real Estate Agent",
            "type":"Services"
        }
    ],
    "sg:phone":"+1 323 773 7132",
    "sg:postcode":"90201",
    "sg:province":"CA",
    "wof:name":"Prudential",
    "wof:placetype":"venue"
},
  "geometry": {"coordinates":[-118.186587,33.98067],"type":"Point"}
}