{
  "type": "Feature",
  "properties": {
    "iso:country":"US",
    "sg:address":"5601 W Slauson Avenue",
    "sg:city":"Culver City",
    "sg:classifiers":[
        {
            "category":"Organizations",
            "subcategory":"Non-profit Organization",
            "type":"Services"
        }
    ],
    "sg:phone":"+1 310 216 2701",
    "sg:postcode":"90230",
    "sg:province":"CA",
    "sg:tags":[
        "service/non-profit",
        "community"
    ],
    "wof:name":"College Summit",
    "wof:placetype":"venue"
},
  "geometry": {"coordinates":[-118.378844,33.989112],"type":"Point"}
}