{
  "type": "Feature",
  "properties": {
    "addr:full":"22201 Sawyers Ln Willits CA 95490",
    "addr:postcode":"22201;95490",
    "addr:street":"Sawyers Ln",
    "iso:country":"US",
    "sg:address":"22201 Sawyers Ln",
    "sg:city":"Willits",
    "sg:phone":"+1 707 459 5736",
    "sg:postcode":"95490",
    "sg:province":"CA",
    "sg:tags":[
        "farm",
        "field",
        "crop"
    ],
    "wof:name":"Farnsworth Vernlyn",
    "wof:placetype":"venue"
},
  "geometry": {"coordinates":[-123.32674299999999,39.398785],"type":"Point"}
}