{
  "type": "Feature",
  "properties": {
    "addr:full":"931 Via Fedora Santa Maria CA 93455",
    "addr:housenumber":"931",
    "addr:postcode":"93455",
    "addr:street":"Via Fedora",
    "iso:country":"US",
    "sg:address":"931 Via Fedora",
    "sg:city":"Santa Maria",
    "sg:classifiers":[
        {
            "category":"Wholesale",
            "subcategory":"Plants",
            "type":"Manufacturing & Wholesale Goods"
        }
    ],
    "sg:phone":"+1 805 934 0242",
    "sg:postcode":"93455",
    "sg:province":"CA",
    "sg:tags":[
        "supply"
    ],
    "wof:name":"Scents Sweet Meadow",
    "wof:placetype":"venue"
},
  "geometry": {"coordinates":[-120.420682,34.859492],"type":"Point"}
}