{
  "type": "Feature",
  "properties": {
    "addr:full":"14392 Hoover St Westminster CA 92683",
    "addr:housenumber":"14392",
    "addr:postcode":"92683",
    "addr:street":"Hoover St",
    "iso:country":"US",
    "sg:address":"14392 Hoover St",
    "sg:city":"Westminster",
    "sg:classifiers":[
        {
            "category":"Manufacturing",
            "subcategory":"Printing",
            "type":"Manufacturing & Wholesale Goods"
        }
    ],
    "sg:phone":"+1 714 898 9289",
    "sg:postcode":"92683",
    "sg:province":"CA",
    "sg:tags":[
        "commercial"
    ],
    "wof:name":"Alf's Printing",
    "wof:placetype":"venue"
},
  "geometry": {"coordinates":[-117.998425,33.754049],"type":"Point"}
}