{
  "type": "Feature",
  "properties": {
    "iso:country":"US",
    "sg:address":"4121 S Broadway",
    "sg:city":"Los Angeles",
    "sg:classifiers":[
        {
            "category":"Home & Garden",
            "subcategory":"Furniture",
            "type":"Retail Goods"
        }
    ],
    "sg:phone":"+1 323 233 3071",
    "sg:postcode":"90037",
    "sg:province":"CA",
    "wof:name":"Muebleria Rosales",
    "wof:placetype":"venue"
},
  "geometry": {"coordinates":[-118.27842699999999,34.008609],"type":"Point"}
}