{
  "type": "Feature",
  "properties": {
    "iso:country":"US",
    "sg:address":"1541 Sweeny Ct",
    "sg:city":"El Cajon",
    "sg:classifiers":[
        {
            "category":"Building & Trades",
            "subcategory":"Construction",
            "type":"Services"
        }
    ],
    "sg:phone":"+1 619 670 0760",
    "sg:postcode":"92019",
    "sg:province":"CA",
    "sg:tags":[
        "contractor"
    ],
    "wof:name":"Western Waterworks",
    "wof:placetype":"venue"
},
  "geometry": {"coordinates":[-116.899012,32.768504],"type":"Point"}
}