{
  "type": "Feature",
  "properties": {
    "addr:full":"210 W Barioni Blvd Imperial CA 92251",
    "addr:housenumber":"210",
    "addr:postcode":"92251",
    "addr:street":"W Barioni Blvd",
    "iso:country":"US",
    "sg:address":"210 W Barioni Blvd",
    "sg:city":"Imperial",
    "sg:classifiers":[
        {
            "category":"Real Estate",
            "subcategory":"Real Estate Operator",
            "type":"Services"
        }
    ],
    "sg:phone":"+1 760 355 4563",
    "sg:postcode":"92251",
    "sg:province":"CA",
    "sg:tags":[
        "apartment"
    ],
    "wof:name":"Imperial Villa Apartments",
    "wof:placetype":"venue"
},
  "geometry": {"coordinates":[-115.57227,32.847409],"type":"Point"}
}