{
  "type": "Feature",
  "properties": {
    "addr:full":"20218 Hillford Ave Carson CA 90746",
    "addr:postcode":"20218;90746",
    "addr:street":"Hillford Ave",
    "iso:country":"US",
    "sg:address":"20218 Hillford Ave",
    "sg:city":"Carson",
    "sg:classifiers":[
        {
            "category":"Building & Trades",
            "subcategory":"Equipment Rental",
            "type":"Services"
        }
    ],
    "sg:phone":"+1 310 637 2110",
    "sg:postcode":"90746",
    "sg:province":"CA",
    "sg:tags":[
        "leasing"
    ],
    "wof:name":"Coast II Coast Studio Truck",
    "wof:placetype":"venue"
},
  "geometry": {"coordinates":[-118.245284,33.84975],"type":"Point"}
}