{
  "type": "Feature",
  "properties": {
    "addr:full":"891 Saratoga Ave San Jose CA 95129",
    "addr:housenumber":"891",
    "addr:postcode":"95129",
    "addr:street":"Saratoga Ave",
    "iso:country":"US",
    "sg:address":"891 Saratoga Ave",
    "sg:city":"San Jose",
    "sg:classifiers":[
        {
            "category":"Professional",
            "subcategory":"Accounting & Tax Preparation",
            "type":"Services"
        }
    ],
    "sg:phone":"+1 408 252 6810",
    "sg:postcode":"95129",
    "sg:province":"CA",
    "sg:tags":[
        "bookkeeping",
        "general"
    ],
    "sg:website":"www.businesstaxbookkeeping.com",
    "wof:name":"BUSINESS Tax & Bookkeeping",
    "wof:placetype":"venue"
},
  "geometry": {"coordinates":[-121.97740400000001,37.311083],"type":"Point"}
}