{
  "type": "Feature",
  "properties": {
    "iso:country":"US",
    "sg:address":"355 Commerce Cir",
    "sg:city":"Sacramento",
    "sg:classifiers":[
        {
            "category":"Social Services",
            "type":"Services"
        },
        {
            "category":"Organizations",
            "subcategory":"Community Association",
            "type":"Services"
        }
    ],
    "sg:phone":"+1 916 929 2992",
    "sg:postcode":"95815",
    "sg:province":"CA",
    "wof:name":"Rotary Club Of Sacramento",
    "wof:placetype":"venue"
},
  "geometry": {"coordinates":[-121.459461,38.599737],"type":"Point"}
}