{
  "type": "Feature",
  "properties": {
    "addr:full":"981 S Western Ave Los Angeles CA 90006",
    "addr:housenumber":"981",
    "addr:postcode":"90006",
    "addr:street":"S Western Ave",
    "iso:country":"US",
    "sg:address":"981 S Western Ave",
    "sg:city":"Los Angeles",
    "sg:classifiers":[
        {
            "category":"Professional",
            "subcategory":"Accounting & Tax Preparation",
            "type":"Services"
        }
    ],
    "sg:phone":"+1 323 734 8722",
    "sg:postcode":"90006",
    "sg:province":"CA",
    "sg:tags":[
        "bookkeeping",
        "general"
    ],
    "wof:name":"WOON Suk Im Accounting & Tax",
    "wof:placetype":"venue"
},
  "geometry": {"coordinates":[-118.309129,34.052958],"type":"Point"}
}