{
  "type": "Feature",
  "properties": {
    "addr:full":"12544 Saticoy St North Hollywood CA 91605",
    "addr:housenumber":"12544",
    "addr:postcode":"91605",
    "addr:street":"Saticoy St",
    "iso:country":"US",
    "sg:address":"12544 Saticoy St",
    "sg:city":"North Hollywood",
    "sg:classifiers":[
        {
            "category":"Government",
            "subcategory":"Office",
            "type":"Public Place"
        }
    ],
    "sg:phone":"+1 818 989 8005",
    "sg:postcode":"91605",
    "sg:province":"CA",
    "sg:tags":[
        "city",
        "parking",
        "enforcement"
    ],
    "wof:name":"Valley Parking Enforcement Off",
    "wof:placetype":"venue"
},
  "geometry": {"coordinates":[-118.405764,34.208383],"type":"Point"}
}