{
  "type": "Feature",
  "properties": {
    "addr:full":"863 Liberty Dr Napa CA 94559",
    "addr:housenumber":"863",
    "addr:postcode":"94559",
    "addr:street":"Liberty Dr",
    "iso:country":"US",
    "sg:address":"863 Liberty Dr",
    "sg:city":"Napa",
    "sg:classifiers":[
        {
            "category":"Farming",
            "subcategory":"Livestock Farm",
            "type":"Manufacturing & Wholesale Goods"
        }
    ],
    "sg:phone":"+1 707 265 6311",
    "sg:postcode":"94559",
    "sg:province":"CA",
    "sg:tags":[
        "ranch"
    ],
    "wof:name":"Liberty Ranch Legacy Court",
    "wof:placetype":"venue"
},
  "geometry": {"coordinates":[-122.27277100000001,38.292515],"type":"Point"}
}