{
  "type": "Feature",
  "properties": {
    "iso:country":"US",
    "sg:address":"863 Liberty Dr",
    "sg:city":"Napa",
    "sg:classifiers":[
        {
            "category":"Farming",
            "subcategory":"Livestock Farm",
            "type":"Manufacturing & Wholesale Goods"
        }
    ],
    "sg:phone":"+1 707 265 6311",
    "sg:postcode":"94559",
    "sg:province":"CA",
    "sg:tags":[
        "ranch"
    ],
    "wof:name":"Liberty Ranch Legacy Court",
    "wof:placetype":"venue"
},
  "geometry": {"coordinates":[-122.272771,38.292515],"type":"Point"}
}