{
  "type": "Feature",
  "properties": {
    "iso:country":"US",
    "sg:address":"4710 El Camino Real",
    "sg:city":"Los Altos",
    "sg:classifiers":[
        {
            "category":"Bakery",
            "type":"Food & Drink"
        }
    ],
    "sg:menulink":"http://www.allmenus.com/ca/san-jose/54899-marie-callenders/menu/",
    "sg:phone":"+1 650 941 8989",
    "sg:postcode":"94022",
    "sg:province":"CA",
    "sg:tags":[
        "american",
        "pastry"
    ],
    "wof:name":"Marie Callender's",
    "wof:placetype":"venue"
},
  "geometry": {"coordinates":[-122.111738,37.399798],"type":"Point"}
}