{
  "type": "Feature",
  "properties": {
    "addr:full":"25125 Santa Clara St Ste H Hayward CA 94544",
    "addr:postcode":"25125;94544",
    "addr:street":"Santa Clara St Ste H",
    "iso:country":"US",
    "sg:address":"25125 Santa Clara St Ste H",
    "sg:city":"Hayward",
    "sg:classifiers":[
        {
            "category":"Shopping",
            "subcategory":"Shoes",
            "type":"Retail Goods"
        }
    ],
    "sg:phone":"+1 510 780 9670",
    "sg:postcode":"94544",
    "sg:province":"CA",
    "sg:tags":[
        "store"
    ],
    "wof:name":"Foot Express",
    "wof:placetype":"venue"
},
  "geometry": {"coordinates":[-122.007943,37.648578],"type":"Point"}
}