{
  "type": "Feature",
  "properties": {
    "addr:full":"8464 Jalal St Lakeside CA 92040",
    "addr:housenumber":"8464",
    "addr:postcode":"92040",
    "addr:street":"Jalal St",
    "iso:country":"US",
    "sg:address":"8464 Jalal St",
    "sg:city":"Lakeside",
    "sg:classifiers":[
        {
            "category":"Building & Trades",
            "subcategory":"Construction",
            "type":"Services"
        }
    ],
    "sg:phone":"+1 619 938 1755",
    "sg:postcode":"92040",
    "sg:province":"CA",
    "sg:tags":[
        "concrete",
        "contractor"
    ],
    "sg:website":"www.empirepavingcompany.com",
    "wof:name":"Empire Paving Co",
    "wof:placetype":"venue"
},
  "geometry": {"coordinates":[-116.927711,32.831353],"type":"Point"}
}