{
  "type": "Feature",
  "properties": {
    "iso:country":"US",
    "sg:address":"2316 Cedar Ave",
    "sg:city":"Long Beach",
    "sg:classifiers":[
        {
            "category":"Home & Garden",
            "subcategory":"Home Furnishings",
            "type":"Retail Goods"
        }
    ],
    "sg:phone":"+1 562 857 2625",
    "sg:postcode":"90806",
    "sg:province":"CA",
    "wof:name":"Express Blinds",
    "wof:placetype":"venue"
},
  "geometry": {"coordinates":[-118.194722,33.800455],"type":"Point"}
}