{
  "type": "Feature",
  "properties": {
    "iso:country":"US",
    "sg:address":"1696 Denver Ave",
    "sg:city":"Claremont",
    "sg:classifiers":[
        {
            "category":"Wholesale",
            "subcategory":"Scrap",
            "type":"Manufacturing & Wholesale Goods"
        }
    ],
    "sg:phone":"+1 909 624 3807",
    "sg:postcode":"91711",
    "sg:province":"CA",
    "sg:tags":[
        "material"
    ],
    "wof:name":"Global Exchange Network",
    "wof:placetype":"venue"
},
  "geometry": {"coordinates":[-117.704919,34.116278],"type":"Point"}
}