{
  "type": "Feature",
  "properties": {
    "iso:country":"US",
    "sg:address":"19216 Singing Hills Dr",
    "sg:city":"Northridge",
    "sg:classifiers":[
        {
            "category":"Recreation",
            "type":"Entertainment"
        }
    ],
    "sg:phone":"+1 818 360 1071",
    "sg:postcode":"91326",
    "sg:province":"CA",
    "sg:tags":[
        "club",
        "country",
        "pro",
        "private",
        "shop"
    ],
    "wof:name":"Porter Valley Catering",
    "wof:placetype":"venue"
},
  "geometry": {"coordinates":[-118.552311,34.276331],"type":"Point"}
}