{
  "type": "Feature",
  "properties": {
    "addr:full":"4941 Clairemont Drive San Diego CA 92117",
    "addr:housenumber":"4941",
    "addr:postcode":"92117",
    "addr:street":"Clairemont Drive",
    "iso:country":"US",
    "sg:address":"4941 Clairemont Drive",
    "sg:city":"San Diego",
    "sg:classifiers":[
        {
            "category":"Personal",
            "subcategory":"Hair Removal",
            "type":"Services"
        },
        {
            "category":"Shopping Center",
            "type":"Public Place"
        },
        {
            "category":"Personal",
            "subcategory":"Nail Salon",
            "type":"Services"
        }
    ],
    "sg:phone":"+1 858 270 5032",
    "sg:postcode":"92117",
    "sg:province":"CA",
    "wof:name":"Clairemont Town Square Shopping Center",
    "wof:placetype":"venue"
},
  "geometry": {"coordinates":[-117.20383099999999,32.832653],"type":"Point"}
}