{
  "type": "Feature",
  "properties": {
    "iso:country":"US",
    "sg:address":"13970 Stowe Dr",
    "sg:city":"Poway",
    "sg:classifiers":[
        {
            "category":"Shopping",
            "subcategory":"Computers & Home Electronics",
            "type":"Retail Goods"
        }
    ],
    "sg:phone":"+1 858 848 2000",
    "sg:postcode":"92064",
    "sg:province":"CA",
    "sg:tags":[
        "programing",
        "custom"
    ],
    "wof:name":"Adcs Inc",
    "wof:placetype":"venue"
},
  "geometry": {"coordinates":[-117.029034,32.940588],"type":"Point"}
}