{
  "type": "Feature",
  "properties": {
    "addr:full":"9355 Sepulveda Blvd Sepulveda CA 91343",
    "addr:housenumber":"9355",
    "addr:postcode":"91343",
    "addr:street":"Sepulveda Blvd",
    "iso:country":"US",
    "sg:address":"9355 Sepulveda Blvd",
    "sg:city":"Sepulveda",
    "sg:classifiers":[
        {
            "category":"Travel",
            "subcategory":"Hotels & Motels",
            "type":"Entertainment"
        }
    ],
    "sg:phone":"+1 818 892 8918",
    "sg:postcode":"91343",
    "sg:province":"CA",
    "wof:name":"Pink Cloud Motel",
    "wof:placetype":"venue"
},
  "geometry": {"coordinates":[-118.46750400000001,34.241792],"type":"Point"}
}