{
  "type": "Feature",
  "properties": {
    "addr:full":"9305 Sungold Way Sacramento CA 95826",
    "addr:housenumber":"9305",
    "addr:postcode":"95826",
    "addr:street":"Sungold Way",
    "iso:country":"US",
    "sg:address":"9305 Sungold Way",
    "sg:city":"Sacramento",
    "sg:classifiers":[
        {
            "category":"Building & Trades",
            "subcategory":"Plumbing",
            "type":"Services"
        }
    ],
    "sg:phone":"+1 916 370 5339",
    "sg:postcode":"95826",
    "sg:province":"CA",
    "sg:tags":[
        "plumber"
    ],
    "wof:name":"Flynn Plumbing",
    "wof:placetype":"venue"
},
  "geometry": {"coordinates":[-121.35373300000001,38.558832],"type":"Point"}
}