{
  "type": "Feature",
  "properties": {
    "addr:full":"1984 Indian Hill Blvd Pomona CA 91767",
    "addr:housenumber":"1984",
    "addr:postcode":"91767",
    "addr:street":"Indian Hill Blvd",
    "iso:country":"US",
    "sg:address":"1984 Indian Hill Blvd",
    "sg:city":"Pomona",
    "sg:classifiers":[
        {
            "category":"Home & Garden",
            "subcategory":"Home Furnishings",
            "type":"Retail Goods"
        }
    ],
    "sg:phone":"+1 909 625 7788",
    "sg:postcode":"91767",
    "sg:province":"CA",
    "wof:name":"Andys Custom Draperies",
    "wof:placetype":"venue"
},
  "geometry": {"coordinates":[-117.719179,34.079338],"type":"Point"}
}