{
  "type": "Feature",
  "properties": {
    "addr:full":"3511 Edison Way Menlo Park CA 94025",
    "addr:housenumber":"3511",
    "addr:postcode":"94025",
    "addr:street":"Edison Way",
    "iso:country":"US",
    "sg:address":"3511 Edison Way",
    "sg:city":"Menlo Park",
    "sg:classifiers":[
        {
            "category":"Retail",
            "subcategory":"Auto Repair",
            "type":"Services"
        }
    ],
    "sg:phone":"+1 650 365 0432",
    "sg:postcode":"94025",
    "sg:province":"CA",
    "sg:tags":[
        "repairing",
        "automobile"
    ],
    "wof:name":"Dieter's German Car Repair",
    "wof:placetype":"venue"
},
  "geometry": {"coordinates":[-122.19672300000001,37.476655],"type":"Point"}
}