{
  "type": "Feature",
  "properties": {
    "iso:country":"US",
    "sg:address":"5312 Derry Ave",
    "sg:city":"Agoura Hills",
    "sg:classifiers":[
        {
            "category":"Banks & Credit Unions",
            "subcategory":"Financial Services",
            "type":"Services"
        }
    ],
    "sg:phone":"+1 818 889 0070",
    "sg:postcode":"91301",
    "sg:province":"CA",
    "sg:tags":[
        "international",
        "trade"
    ],
    "wof:name":"American European Trading Inc",
    "wof:placetype":"venue"
},
  "geometry": {"coordinates":[-118.74790900000001,34.147439],"type":"Point"}
}