{
  "type": "Feature",
  "properties": {
    "addr:full":"1618 Ohms Way Costa Mesa CA 92627",
    "addr:postcode":"1618;92627",
    "addr:street":"Ohms Way",
    "iso:country":"US",
    "sg:address":"1618 Ohms Way",
    "sg:city":"Costa Mesa",
    "sg:classifiers":[
        {
            "category":"Building & Trades",
            "subcategory":"Electrical",
            "type":"Services"
        }
    ],
    "sg:phone":"+1 949 631 8777",
    "sg:postcode":"92627",
    "sg:province":"CA",
    "sg:tags":[
        "electric",
        "contractor"
    ],
    "wof:name":"Noor Electrical",
    "wof:placetype":"venue"
},
  "geometry": {"coordinates":[-117.92828799999999,33.634329],"type":"Point"}
}