{
  "type": "Feature",
  "properties": {
    "addr:full":"2320 Wyda Way Sacramento CA 95825",
    "addr:housenumber":"2320",
    "addr:postcode":"95825",
    "addr:street":"Wyda Way",
    "iso:country":"US",
    "sg:address":"2320 Wyda Way",
    "sg:city":"Sacramento",
    "sg:classifiers":[
        {
            "category":"Building & Trades",
            "subcategory":"Landscaping Services",
            "type":"Services"
        }
    ],
    "sg:phone":"+1 916 925 0328",
    "sg:postcode":"95825",
    "sg:province":"CA",
    "sg:tags":[
        "tree"
    ],
    "wof:name":"AAA Tree Svc",
    "wof:placetype":"venue"
},
  "geometry": {"coordinates":[-121.41032800000001,38.599832],"type":"Point"}
}