{
  "type": "Feature",
  "properties": {
    "iso:country":"US",
    "sg:address":"515 N Palm Canyon Dr",
    "sg:city":"Palm Springs",
    "sg:classifiers":[
        {
            "category":"Restaurant",
            "type":"Food & Drink"
        }
    ],
    "sg:phone":"+1 760 416 2244",
    "sg:postcode":"92262",
    "sg:province":"CA",
    "sg:tags":[
        "shop",
        "tea",
        "coffee"
    ],
    "sg:website":"www.kofficoffee.com",
    "wof:name":"Palm Springs Koffi",
    "wof:placetype":"venue"
},
  "geometry": {"coordinates":[-116.546997,33.830601],"type":"Point"}
}