{
  "type": "Feature",
  "properties": {
    "addr:full":"2050 N Imperial Ave El Centro CA 92231",
    "addr:housenumber":"2050",
    "addr:postcode":"92231",
    "addr:street":"N Imperial Ave",
    "iso:country":"US",
    "sg:address":"2050 N Imperial Ave",
    "sg:city":"El Centro",
    "sg:classifiers":[
        {
            "category":"Shopping",
            "subcategory":"Department Store",
            "type":"Retail Goods"
        }
    ],
    "sg:phone":"+1 760 337 1600",
    "sg:postcode":"92231",
    "sg:province":"CA",
    "sg:tags":[
        "discount",
        "dept",
        "pharmacy"
    ],
    "sg:website":"www.walmart.com",
    "wof:name":"Wal-Mart",
    "wof:placetype":"venue"
},
  "geometry": {"coordinates":[-115.56997200000001,32.816031],"type":"Point"}
}