{
  "type": "Feature",
  "properties": {
    "addr:full":"2481 Deerwood Dr San Ramon CA 94583",
    "addr:housenumber":"2481",
    "addr:postcode":"94583",
    "addr:street":"Deerwood Dr",
    "iso:country":"US",
    "sg:address":"2481 Deerwood Dr",
    "sg:city":"San Ramon",
    "sg:classifiers":[
        {
            "category":"Real Estate",
            "subcategory":"Real Estate Services",
            "type":"Services"
        }
    ],
    "sg:phone":"+1 925 743 8200",
    "sg:postcode":"94583",
    "sg:province":"CA",
    "sg:tags":[
        "management",
        "property"
    ],
    "wof:name":"Sungard Recovery Services Lp",
    "wof:placetype":"venue"
},
  "geometry": {"coordinates":[-121.996002,37.775002],"type":"Point"}
}