{
  "type": "Feature",
  "properties": {
    "addr:full":"13360 W Washington Blvd Los Angeles CA 90066",
    "addr:housenumber":"13360",
    "addr:postcode":"90066",
    "addr:street":"W Washington Blvd",
    "iso:country":"US",
    "sg:address":"13360 W Washington Blvd",
    "sg:city":"Los Angeles",
    "sg:classifiers":[
        {
            "category":"Organizations",
            "subcategory":"Non-profit Organization",
            "type":"Services"
        }
    ],
    "sg:phone":"+1 310 301 4490",
    "sg:postcode":"90066",
    "sg:province":"CA",
    "sg:tags":[
        "service/non-profit",
        "community"
    ],
    "wof:name":"Goodwill Industries of",
    "wof:placetype":"venue"
},
  "geometry": {"coordinates":[-118.443001,33.992901],"type":"Point"}
}