{
  "type": "Feature",
  "properties": {
    "addr:full":"582 Market Street Fl 18 San Francisco CA 94104",
    "addr:housenumber":"582;18",
    "addr:postcode":"94104",
    "addr:street":"Market Street Fl",
    "iso:country":"US",
    "sg:address":"582 Market Street Fl 18",
    "sg:city":"San Francisco",
    "sg:classifiers":[
        {
            "category":"Professional",
            "subcategory":"Lawyer & Legal Services",
            "type":"Services"
        }
    ],
    "sg:phone":"+1 415 693 0504",
    "sg:postcode":"94104",
    "sg:province":"CA",
    "sg:website":"www.westbaylaw.com",
    "wof:name":"Schreiber Christina A",
    "wof:placetype":"venue"
},
  "geometry": {"coordinates":[-122.40100099999999,37.789398],"type":"Point"}
}