{
  "type": "Feature",
  "properties": {
    "iso:country":"US",
    "sg:address":"21781 E Springfield Ave",
    "sg:city":"Reedley",
    "sg:classifiers":[
        {
            "category":"Farming",
            "subcategory":"Farm & Veterinary Services",
            "type":"Manufacturing & Wholesale Goods"
        }
    ],
    "sg:phone":"+1 559 638 4155",
    "sg:postcode":"93654",
    "sg:province":"CA",
    "sg:tags":[
        "spraying",
        "commercial"
    ],
    "wof:name":"Tuckers Spraying Inc",
    "wof:placetype":"venue"
},
  "geometry": {"coordinates":[-119.403913,36.596729],"type":"Point"}
}