{
  "type": "Feature",
  "properties": {
    "iso:country":"US",
    "sg:address":"6612 Eastern Ave",
    "sg:city":"Bell",
    "sg:classifiers":[
        {
            "category":"Shopping",
            "subcategory":"Bicycles & Sporting Goods",
            "type":"Retail Goods"
        }
    ],
    "sg:phone":"+1 323 771 1815",
    "sg:postcode":"90201",
    "sg:province":"CA",
    "wof:name":"La Route",
    "wof:placetype":"venue"
},
  "geometry": {"coordinates":[-118.163921,33.972567],"type":"Point"}
}