{
  "type": "Feature",
  "properties": {
    "iso:country":"US",
    "sg:address":"3133 Jack Northrop Ave",
    "sg:city":"Hawthorne",
    "sg:classifiers":[
        {
            "category":"Communications",
            "subcategory":"Film & Video Production",
            "type":"Services"
        }
    ],
    "sg:phone":"+1 310 265 2480",
    "sg:postcode":"90250",
    "sg:province":"CA",
    "sg:tags":[
        "picture",
        "companies-film",
        "producer",
        "tv",
        "services-commercial",
        "motion",
        "studio",
        "radio"
    ],
    "wof:name":"15 40 Productions",
    "wof:placetype":"venue"
},
  "geometry": {"coordinates":[-118.327641,33.919685],"type":"Point"}
}