{
  "type": "Feature",
  "properties": {
    "addr:full":"1460 E Holt Ave Pomona CA 91767",
    "addr:housenumber":"1460",
    "addr:postcode":"91767",
    "addr:street":"E Holt Ave",
    "iso:country":"US",
    "sg:address":"1460 E Holt Ave",
    "sg:city":"Pomona",
    "sg:classifiers":[
        {
            "category":"Personal",
            "subcategory":"Beauty Salon",
            "type":"Services"
        }
    ],
    "sg:phone":"+1 909 620 8277",
    "sg:postcode":"91767",
    "sg:province":"CA",
    "sg:tags":[
        "school"
    ],
    "wof:name":"Pomona Cosmetology School",
    "wof:placetype":"venue"
},
  "geometry": {"coordinates":[-117.721386,34.063012],"type":"Point"}
}