{
  "type": "Feature",
  "properties": {
    "addr:full":"5201 Stevens Creek Blvd Santa Clara CA 95051",
    "addr:housenumber":"5201",
    "addr:postcode":"95051",
    "addr:street":"Stevens Creek Blvd",
    "iso:country":"US",
    "sg:address":"5201 Stevens Creek Blvd",
    "sg:city":"Santa Clara",
    "sg:classifiers":[
        {
            "category":"Home & Garden",
            "subcategory":"Home Furnishings",
            "type":"Retail Goods"
        }
    ],
    "sg:phone":"+1 408 260 2219",
    "sg:postcode":"95051",
    "sg:province":"CA",
    "sg:tags":[
        "bath",
        "kitchen"
    ],
    "sg:website":"www.bedbathandbeyond.com",
    "wof:name":"Bed Bath & Beyond",
    "wof:placetype":"venue"
},
  "geometry": {"coordinates":[-121.99363700000001,37.324071],"type":"Point"}
}