{
  "type": "Feature",
  "properties": {
    "iso:country":"US",
    "sg:address":"25471 Arctic Ocean Dr",
    "sg:city":"Lake Forest",
    "sg:classifiers":[
        {
            "category":"Wholesale",
            "subcategory":"Durable Goods & Equipment",
            "type":"Manufacturing & Wholesale Goods"
        }
    ],
    "sg:phone":"+1 949 380 7556",
    "sg:postcode":"92630",
    "sg:province":"CA",
    "sg:tags":[
        "importer"
    ],
    "sg:website":"www.momo.it",
    "wof:name":"Momo Automotive",
    "wof:placetype":"venue"
},
  "geometry": {"coordinates":[-117.686701,33.667877],"type":"Point"}
}