{
  "type": "Feature",
  "properties": {
    "addr:full":"15512 Crenshaw Blvd Gardena CA 90249",
    "addr:housenumber":"15512",
    "addr:postcode":"90249",
    "addr:street":"Crenshaw Blvd",
    "iso:country":"US",
    "sg:address":"15512 Crenshaw Blvd",
    "sg:city":"Gardena",
    "sg:classifiers":[
        {
            "category":"Building & Trades",
            "subcategory":"Plumbing",
            "type":"Services"
        }
    ],
    "sg:phone":"+1 310 329 3470",
    "sg:postcode":"90249",
    "sg:province":"CA",
    "sg:tags":[
        "plumbing",
        "contractor"
    ],
    "wof:name":"California Plumbing",
    "wof:placetype":"venue"
},
  "geometry": {"coordinates":[-118.326442,33.890235],"type":"Point"}
}