{
  "type": "Feature",
  "properties": {
    "addr:full":"3325 Birchwood Ln San Jose CA 95132",
    "addr:housenumber":"3325",
    "addr:postcode":"95132",
    "addr:street":"Birchwood Ln",
    "iso:country":"US",
    "sg:address":"3325 Birchwood Ln",
    "sg:city":"San Jose",
    "sg:classifiers":[
        {
            "category":"Recreation",
            "type":"Entertainment"
        }
    ],
    "sg:phone":"+1 408 263 6155",
    "sg:postcode":"95132",
    "sg:province":"CA",
    "sg:tags":[
        "pool",
        "swimming"
    ],
    "sg:website":"www.pool4.com",
    "wof:name":"Northwood Park Pool Imprvmt",
    "wof:placetype":"venue"
},
  "geometry": {"coordinates":[-121.864379,37.416115],"type":"Point"}
}