{
  "type": "Feature",
  "properties": {
    "addr:full":"222 W 4th St Frnt Santa Ana CA 92701",
    "addr:housenumber":"222",
    "addr:postcode":"92701",
    "addr:street":"W 4Th St",
    "iso:country":"US",
    "sg:address":"222 W 4th St Frnt",
    "sg:city":"Santa Ana",
    "sg:classifiers":[
        {
            "category":"Home & Garden",
            "subcategory":"Garden Supply",
            "type":"Retail Goods"
        }
    ],
    "sg:phone":"+1 714 542 4061",
    "sg:postcode":"92701",
    "sg:province":"CA",
    "sg:tags":[
        "nursery",
        "gardening"
    ],
    "wof:name":"Centro Botanica Latina No 1",
    "wof:placetype":"venue"
},
  "geometry": {"coordinates":[-117.86900300000001,33.748001],"type":"Point"}
}