{
  "type": "Feature",
  "properties": {
    "addr:full":"6640 Cherry Ave Long Beach CA 90805",
    "addr:housenumber":"6640",
    "addr:postcode":"90805",
    "addr:street":"Cherry Ave",
    "iso:country":"US",
    "sg:address":"6640 Cherry Ave",
    "sg:city":"Long Beach",
    "sg:classifiers":[
        {
            "category":"Autos & Motor Vehicles",
            "subcategory":"Auto Supplies",
            "type":"Retail Goods"
        }
    ],
    "sg:phone":"+1 562 408 2882",
    "sg:postcode":"90805",
    "sg:province":"CA",
    "sg:tags":[
        "automobile",
        "parts"
    ],
    "wof:name":"E-Z Auto Parts",
    "wof:placetype":"venue"
},
  "geometry": {"coordinates":[-118.16860800000001,33.874828],"type":"Point"}
}