{
  "type": "Feature",
  "properties": {
    "addr:full":"6767 51st St San Diego CA 92120",
    "addr:housenumber":"6767",
    "addr:postcode":"92120",
    "addr:street":"51St St",
    "iso:country":"US",
    "sg:address":"6767 51st St",
    "sg:city":"San Diego",
    "sg:classifiers":[
        {
            "category":"Organizations",
            "subcategory":"Religious Organization",
            "type":"Services"
        }
    ],
    "sg:phone":"+1 619 582 0572",
    "sg:postcode":"92120",
    "sg:province":"CA",
    "sg:tags":[
        "church"
    ],
    "wof:name":"Church Of Jesus Christ Of Lds",
    "wof:placetype":"venue"
},
  "geometry": {"coordinates":[-117.08326700000001,32.795593],"type":"Point"}
}