{
  "type": "Feature",
  "properties": {
    "iso:country":"US",
    "sg:address":"6232 La Salle Ave",
    "sg:city":"Oakland",
    "sg:classifiers":[
        {
            "category":"Professional",
            "subcategory":"Art Services",
            "type":"Services"
        }
    ],
    "sg:phone":"+1 510 339 0274",
    "sg:postcode":"94611",
    "sg:province":"CA",
    "sg:tags":[
        "photographer"
    ],
    "wof:name":"Studio Montclair",
    "wof:placetype":"venue"
},
  "geometry": {"coordinates":[-122.23200199999999,37.8284],"type":"Point"}
}