{
  "type": "Feature",
  "properties": {
    "iso:country":"US",
    "sg:address":"7987 Wente Way",
    "sg:city":"Sacramento",
    "sg:classifiers":[
        {
            "category":"Professional",
            "subcategory":"Engineering",
            "type":"Services"
        }
    ],
    "sg:phone":"+1 916 869 4464",
    "sg:postcode":"95829",
    "sg:province":"CA",
    "sg:tags":[
        "engineer"
    ],
    "wof:name":"K D Myers Consulting",
    "wof:placetype":"venue"
},
  "geometry": {"coordinates":[-121.35904,38.467258],"type":"Point"}
}