{
  "type": "Feature",
  "properties": {
    "addr:full":"854 Calhoun St San Jose CA 95116",
    "addr:housenumber":"854",
    "addr:postcode":"95116",
    "addr:street":"Calhoun St",
    "iso:country":"US",
    "sg:address":"854 Calhoun St",
    "sg:city":"San Jose",
    "sg:classifiers":[
        {
            "category":"Building & Trades",
            "subcategory":"Landscaping Services",
            "type":"Services"
        }
    ],
    "sg:phone":"+1 408 279 6417",
    "sg:postcode":"95116",
    "sg:province":"CA",
    "wof:name":"Jose Machado Landscaping",
    "wof:placetype":"venue"
},
  "geometry": {"coordinates":[-121.872287,37.343669],"type":"Point"}
}