{
  "type": "Feature",
  "properties": {
    "iso:country":"US",
    "sg:address":"3600 Harbor Blvd 223",
    "sg:city":"Oxnard",
    "sg:classifiers":[
        {
            "category":"Professional",
            "subcategory":"Computer Services",
            "type":"Services"
        },
        {
            "category":"Internet Cafe",
            "subcategory":"None",
            "type":"Food & Drink"
        }
    ],
    "sg:phone":"+1 888 248 5765",
    "sg:postcode":"93035",
    "sg:province":"CA",
    "sg:tags":[
        "publisher",
        "product",
        "developer",
        "software"
    ],
    "wof:name":"Mirror Image Translations & Services",
    "wof:placetype":"venue"
},
  "geometry": {"coordinates":[-119.229851,34.16848],"type":"Point"}
}