{
  "type": "Feature",
  "properties": {
    "iso:country":"US",
    "sg:address":"2462 Atlas Peak Rd",
    "sg:city":"Napa",
    "sg:phone":"+1 800 794 7387",
    "sg:postcode":"94558",
    "sg:province":"CA",
    "wof:name":"Bubbling Well Pet Memorial Park",
    "wof:placetype":"venue"
},
  "geometry": {"coordinates":[-122.254829,38.369201],"type":"Point"}
}