{
  "type": "Feature",
  "properties": {
    "addr:full":"500 Beach Street San Francisco CA 94133",
    "addr:housenumber":"500",
    "addr:postcode":"94133",
    "addr:street":"Beach Street",
    "iso:country":"US",
    "sg:address":"500 Beach Street",
    "sg:city":"San Francisco",
    "sg:classifiers":[
        {
            "category":"Coffee & Tea",
            "type":"Food & Drink"
        }
    ],
    "sg:phone":"+1 415 776 7907",
    "sg:postcode":"94133",
    "sg:province":"CA",
    "sg:website":"www.starbucks.com",
    "wof:name":"Starbucks Coffee",
    "wof:placetype":"venue"
},
  "geometry": {"coordinates":[-122.41100299999999,37.799301],"type":"Point"}
}