{
  "type": "Feature",
  "properties": {
    "iso:country":"US",
    "sg:address":"2491 Rice Ave",
    "sg:city":"West Sacramento",
    "sg:classifiers":[
        {
            "category":"Home & Garden",
            "subcategory":"Building Materials",
            "type":"Retail Goods"
        }
    ],
    "sg:phone":"+1 916 371 5320",
    "sg:postcode":"95691",
    "sg:province":"CA",
    "sg:tags":[
        "door"
    ],
    "sg:website":"www.rsdoors.com",
    "wof:name":"R & S Of Sacramento Sales",
    "wof:placetype":"venue"
},
  "geometry": {"coordinates":[-121.540578,38.587238],"type":"Point"}
}