{
  "type": "Feature",
  "properties": {
    "iso:country":"US",
    "sg:address":"3760 Wilshire Blvd",
    "sg:city":"Los Angeles",
    "sg:classifiers":[
        {
            "category":"Bars & Pubs",
            "type":"Food & Drink"
        }
    ],
    "sg:phone":"+1 213 388 3383",
    "sg:postcode":"90005",
    "sg:province":"CA",
    "wof:name":"37sixty",
    "wof:placetype":"venue"
},
  "geometry": {"coordinates":[-118.30807799999999,34.061675],"type":"Point"}
}