{
  "type": "Feature",
  "properties": {
    "addr:full":"4409 Sugar Maple Ct Concord CA 94521",
    "addr:housenumber":"4409",
    "addr:postcode":"94521",
    "addr:street":"Sugar Maple Ct",
    "iso:country":"US",
    "sg:address":"4409 Sugar Maple Ct",
    "sg:city":"Concord",
    "sg:classifiers":[
        {
            "category":"Communications",
            "subcategory":"Film & Video Production",
            "type":"Services"
        }
    ],
    "sg:phone":"+1 925 858 2303",
    "sg:postcode":"94521",
    "sg:province":"CA",
    "sg:tags":[
        "taping"
    ],
    "wof:name":"Tycomm Productions",
    "wof:placetype":"venue"
},
  "geometry": {"coordinates":[-121.983329,37.951263],"type":"Point"}
}