{
  "type": "Feature",
  "properties": {
    "iso:country":"US",
    "sg:address":"46460 Jasmine Ln",
    "sg:city":"Indio",
    "sg:classifiers":[
        {
            "category":"Retail",
            "subcategory":"Animal Services",
            "type":"Services"
        }
    ],
    "sg:phone":"+1 760 342 9844",
    "sg:postcode":"92201",
    "sg:province":"CA",
    "sg:tags":[
        "pet",
        "grooming",
        "washing"
    ],
    "wof:name":"Dirty Dog Grooming",
    "wof:placetype":"venue"
},
  "geometry": {"coordinates":[-116.258696,33.711399],"type":"Point"}
}