{
  "type": "Feature",
  "properties": {
    "iso:country":"US",
    "sg:address":"641 Wooldridge Ave",
    "sg:city":"Holtville",
    "sg:classifiers":[
        {
            "category":"Freight",
            "type":"Transportation"
        }
    ],
    "sg:phone":"+1 760 356 2214",
    "sg:postcode":"92250",
    "sg:province":"CA",
    "sg:tags":[
        "local",
        "storage",
        "trucking"
    ],
    "wof:name":"RR Enterprises",
    "wof:placetype":"venue"
},
  "geometry": {"coordinates":[-115.386796,32.817504],"type":"Point"}
}