{
  "type": "Feature",
  "properties": {
    "iso:country":"US",
    "sg:address":"22870 2nd St",
    "sg:city":"Hayward",
    "sg:classifiers":[
        {
            "category":"Social Services",
            "type":"Services"
        }
    ],
    "sg:phone":"+1 510 768 3100",
    "sg:postcode":"94541",
    "sg:province":"CA",
    "sg:tags":[
        "counseling"
    ],
    "wof:name":"Catholic Counseling Svc",
    "wof:placetype":"venue"
},
  "geometry": {"coordinates":[-122.076773,37.672749],"type":"Point"}
}