{
  "type": "Feature",
  "properties": {
    "addr:full":"1842 Washington Way Venice CA 90291",
    "addr:housenumber":"1842",
    "addr:postcode":"90291",
    "addr:street":"Washington Way",
    "iso:country":"US",
    "sg:address":"1842 Washington Way",
    "sg:city":"Venice",
    "sg:classifiers":[
        {
            "category":"Manufacturing",
            "subcategory":"Printing",
            "type":"Manufacturing & Wholesale Goods"
        }
    ],
    "sg:phone":"+1 323 938 3700",
    "sg:postcode":"90291",
    "sg:province":"CA",
    "sg:tags":[
        "multimedia"
    ],
    "sg:website":"www.whitenoise.net",
    "wof:name":"White Noise Productions Inc",
    "wof:placetype":"venue"
},
  "geometry": {"coordinates":[-118.459968,33.987841],"type":"Point"}
}