{
  "type": "Feature",
  "properties": {
    "addr:full":"1003 Roleen Dr Vallejo CA 94589",
    "addr:housenumber":"1003",
    "addr:postcode":"94589",
    "addr:street":"Roleen Dr",
    "iso:country":"US",
    "sg:address":"1003 Roleen Dr",
    "sg:city":"Vallejo",
    "sg:classifiers":[
        {
            "category":"Social Services",
            "subcategory":"Child Care",
            "type":"Services"
        }
    ],
    "sg:phone":"+1 707 643 3180",
    "sg:postcode":"94589",
    "sg:province":"CA",
    "wof:name":"Armstrong Family Daycare",
    "wof:placetype":"venue"
},
  "geometry": {"coordinates":[-122.260408,38.149334],"type":"Point"}
}