{
  "type": "Feature",
  "properties": {
    "addr:full":"500 N Allen Ave Pasadena CA 91106",
    "addr:housenumber":"500",
    "addr:postcode":"91106",
    "addr:street":"N Allen Ave",
    "iso:country":"US",
    "sg:address":"500 N Allen Ave",
    "sg:city":"Pasadena",
    "sg:classifiers":[
        {
            "category":"Home & Garden",
            "subcategory":"Home Furnishings",
            "type":"Retail Goods"
        },
        {
            "category":"Shopping",
            "subcategory":"Antiques",
            "type":"Retail Goods"
        }
    ],
    "sg:phone":"+1 626 628 6416",
    "sg:postcode":"91106",
    "sg:province":"CA",
    "sg:tags":[
        "decor"
    ],
    "sg:website":"atticonallen.com",
    "wof:name":"The Attic on Allen",
    "wof:placetype":"venue"
},
  "geometry": {"coordinates":[-118.113158,34.15489],"type":"Point"}
}