{
  "type": "Feature",
  "properties": {
    "iso:country":"US",
    "sg:address":"530 19th St",
    "sg:city":"San Diego",
    "sg:classifiers":[
        {
            "category":"Shopping",
            "subcategory":"Gifts & Souvenirs",
            "type":"Retail Goods"
        }
    ],
    "sg:phone":"+1 619 702 7147",
    "sg:postcode":"92102",
    "sg:province":"CA",
    "wof:name":"Martinez Gifts",
    "wof:placetype":"venue"
},
  "geometry": {"coordinates":[-117.146788,32.711204],"type":"Point"}
}