{
  "type": "Feature",
  "properties": {
    "addr:full":"8300 La Palma Ave Buena Park CA 90620",
    "addr:housenumber":"8300",
    "addr:postcode":"90620",
    "addr:street":"La Palma Ave",
    "iso:country":"US",
    "sg:address":"8300 La Palma Ave",
    "sg:city":"Buena Park",
    "sg:classifiers":[
        {
            "category":"Restaurant",
            "type":"Food & Drink"
        }
    ],
    "sg:menulink":"http://www.allmenus.com/ca/anaheim-santa-ana-garden-grove/72196-sbarro/menu/",
    "sg:phone":"+1 714 229 0013",
    "sg:postcode":"90620",
    "sg:province":"CA",
    "sg:tags":[
        "american",
        "pizza"
    ],
    "wof:name":"Sbarro",
    "wof:placetype":"venue"
},
  "geometry": {"coordinates":[-117.988017,33.846656],"type":"Point"}
}