{
  "type": "Feature",
  "properties": {
    "addr:full":"456 Shatto Pl Los Angeles CA 90020",
    "addr:housenumber":"456",
    "addr:postcode":"90020",
    "addr:street":"Shatto Pl",
    "iso:country":"US",
    "sg:address":"456 Shatto Pl",
    "sg:city":"Los Angeles",
    "sg:classifiers":[
        {
            "category":"Real Estate",
            "subcategory":"Real Estate Agent",
            "type":"Services"
        }
    ],
    "sg:phone":"+1 213 383 4686",
    "sg:postcode":"90020",
    "sg:province":"CA",
    "wof:name":"Core Realty",
    "wof:placetype":"venue"
},
  "geometry": {"coordinates":[-118.289862,34.066225],"type":"Point"}
}