{
  "type": "Feature",
  "properties": {
    "addr:full":"10821 Vanowen St North Hollywood CA 91605",
    "addr:housenumber":"10821",
    "addr:postcode":"91605",
    "addr:street":"Vanowen St",
    "iso:country":"US",
    "sg:address":"10821 Vanowen St",
    "sg:city":"North Hollywood",
    "sg:classifiers":[
        {
            "category":"Personal",
            "type":"Services"
        }
    ],
    "sg:phone":"+1 818 200 4105",
    "sg:postcode":"91605",
    "sg:province":"CA",
    "sg:tags":[
        "local"
    ],
    "wof:name":"Affirmative Bail Bonds",
    "wof:placetype":"venue"
},
  "geometry": {"coordinates":[-118.366721,34.193985],"type":"Point"}
}