{
  "type": "Feature",
  "properties": {
    "addr:full":"1027 W 96th St Los Angeles CA 90044",
    "addr:housenumber":"1027",
    "addr:postcode":"90044",
    "addr:street":"W 96Th St",
    "iso:country":"US",
    "sg:address":"1027 W 96th St",
    "sg:city":"Los Angeles",
    "sg:classifiers":[
        {
            "category":"Education",
            "subcategory":"Preschool",
            "type":"Public Place"
        },
        {
            "category":"Education",
            "subcategory":"School",
            "type":"Public Place"
        }
    ],
    "sg:phone":"+1 323 777 0920",
    "sg:postcode":"90044",
    "sg:province":"CA",
    "sg:tags":[
        "elementary"
    ],
    "wof:name":"Ninety-Fifth Street Combination Children's Center",
    "wof:placetype":"venue"
},
  "geometry": {"coordinates":[-118.292,33.948601],"type":"Point"}
}