{
  "type": "Feature",
  "properties": {
    "addr:full":"9378 Stanford Ln Durham CA 95938",
    "addr:housenumber":"9378",
    "addr:postcode":"95938",
    "addr:street":"Stanford Ln",
    "iso:country":"US",
    "sg:address":"9378 Stanford Ln",
    "sg:city":"Durham",
    "sg:classifiers":[
        {
            "category":"Wholesale",
            "subcategory":"Machinery & Supplies",
            "type":"Manufacturing & Wholesale Goods"
        }
    ],
    "sg:phone":"+1 530 891 4722",
    "sg:postcode":"95938",
    "sg:province":"CA",
    "sg:tags":[
        "machine",
        "equipment",
        "establishment",
        "vending",
        "op"
    ],
    "wof:name":"Valley Vending",
    "wof:placetype":"venue"
},
  "geometry": {"coordinates":[-121.786367,39.644383],"type":"Point"}
}