{
  "type": "Feature",
  "properties": {
    "iso:country":"US",
    "sg:address":"17767 Colfax Hwy",
    "sg:city":"Grass Valley",
    "sg:classifiers":[
        {
            "category":"Building & Trades",
            "subcategory":"Construction",
            "type":"Services"
        }
    ],
    "sg:phone":"+1 530 274 8569",
    "sg:postcode":"95945",
    "sg:province":"CA",
    "sg:tags":[
        "repairing",
        "remodeling",
        "contractor"
    ],
    "wof:name":"All Star Construction",
    "wof:placetype":"venue"
},
  "geometry": {"coordinates":[-120.96839300000001,39.163352],"type":"Point"}
}