{
  "type": "Feature",
  "properties": {
    "addr:full":"315 Cam del Remedio Santa Barbara CA 93110",
    "addr:housenumber":"315",
    "addr:postcode":"93110",
    "addr:street":"Cam Del Remedio",
    "iso:country":"US",
    "sg:address":"315 Cam del Remedio",
    "sg:city":"Santa Barbara",
    "sg:classifiers":[
        {
            "category":"Government",
            "subcategory":"Office",
            "type":"Public Place"
        }
    ],
    "sg:phone":"+1 805 681 4500",
    "sg:postcode":"93110",
    "sg:province":"CA",
    "wof:name":"Santa Barbara County Veteran's",
    "wof:placetype":"venue"
},
  "geometry": {"coordinates":[-119.779478,34.445674],"type":"Point"}
}