{
  "type": "Feature",
  "properties": {
    "addr:full":"3577 Herman Ave San Diego CA 92104",
    "addr:housenumber":"3577",
    "addr:postcode":"92104",
    "addr:street":"Herman Ave",
    "iso:country":"US",
    "sg:address":"3577 Herman Ave",
    "sg:city":"San Diego",
    "sg:classifiers":[
        {
            "category":"Professional",
            "type":"Services"
        }
    ],
    "sg:phone":"+1 858 457 8385",
    "sg:postcode":"92104",
    "sg:province":"CA",
    "wof:name":"Picture This",
    "wof:placetype":"venue"
},
  "geometry": {"coordinates":[-117.125996,32.742385],"type":"Point"}
}