{
  "type": "Feature",
  "properties": {
    "addr:full":"17450 Mount Herrman St Fountain Valley CA 92708",
    "addr:housenumber":"17450",
    "addr:postcode":"92708",
    "addr:street":"Mount;St",
    "iso:country":"US",
    "sg:address":"17450 Mount Herrman St",
    "sg:city":"Fountain Valley",
    "sg:classifiers":[
        {
            "category":"Building & Trades",
            "subcategory":"Construction",
            "type":"Services"
        }
    ],
    "sg:phone":"+1 949 581 0403",
    "sg:postcode":"92708",
    "sg:province":"CA",
    "sg:tags":[
        "contractor"
    ],
    "wof:name":"JW Roofing",
    "wof:placetype":"venue"
},
  "geometry": {"coordinates":[-117.93244799999999,33.710926],"type":"Point"}
}