{
  "type": "Feature",
  "properties": {
    "addr:full":"8500 Beverly Ctr Ste 773 Los Angeles CA 90048",
    "addr:housenumber":"8500",
    "addr:postcode":"90048",
    "addr:street":"Beverly Ctr Ste 773",
    "iso:country":"US",
    "sg:address":"8500 Beverly Ctr Ste 773",
    "sg:city":"Los Angeles",
    "sg:classifiers":[
        {
            "category":"Shopping",
            "subcategory":"Beauty & Cosmetics",
            "type":"Retail Goods"
        }
    ],
    "sg:phone":"+1 310 659 6201",
    "sg:postcode":"90048",
    "sg:province":"CA",
    "sg:tags":[
        "supply"
    ],
    "sg:website":"www.maccosmetics.com",
    "wof:name":"MAC",
    "wof:placetype":"venue"
},
  "geometry": {"coordinates":[-118.376696,34.076042],"type":"Point"}
}