{
  "type": "Feature",
  "properties": {
    "iso:country":"US",
    "sg:address":"4934 San Juan Ave",
    "sg:city":"Fair Oaks",
    "sg:classifiers":[
        {
            "category":"Taxi",
            "type":"Transportation"
        }
    ],
    "sg:phone":"+1 916 967 7143",
    "sg:postcode":"95628",
    "sg:province":"CA",
    "wof:name":"Shire Kevin Lee & Joy Crystal",
    "wof:placetype":"venue"
},
  "geometry": {"coordinates":[-121.292103,38.656465],"type":"Point"}
}