{
  "type": "Feature",
  "properties": {
    "addr:full":"River Rd and Martinelli Dr Forestville CA 95436",
    "addr:postcode":"95436",
    "addr:street":"River Rd;Martinelli Dr",
    "iso:country":"US",
    "sg:address":"River Rd and Martinelli Dr",
    "sg:city":"Forestville",
    "sg:classifiers":[
        {
            "category":"Travel",
            "subcategory":"Bed & Breakfast",
            "type":"Entertainment"
        }
    ],
    "sg:postcode":"95436",
    "sg:province":"CA",
    "sg:website":"www.SummerlandCabin.com",
    "wof:name":"Summerland Cabin",
    "wof:placetype":"venue"
},
  "geometry": {"coordinates":[-122.909971,38.503376],"type":"Point"}
}