{
  "type": "Feature",
  "properties": {
    "addr:full":"15101 Nelson Ave Kingsburg CA 93631",
    "addr:housenumber":"15101",
    "addr:postcode":"93631",
    "addr:street":"Nelson Ave",
    "iso:country":"US",
    "sg:address":"15101 Nelson Ave",
    "sg:city":"Kingsburg",
    "sg:classifiers":[
        {
            "category":"Farming",
            "subcategory":"Vineyard",
            "type":"Manufacturing & Wholesale Goods"
        }
    ],
    "sg:phone":"+1 559 897 2083",
    "sg:postcode":"93631",
    "sg:province":"CA",
    "sg:tags":[
        "grape"
    ],
    "wof:name":"George Sanwo",
    "wof:placetype":"venue"
},
  "geometry": {"coordinates":[-119.579814,36.5122],"type":"Point"}
}