{
  "type": "Feature",
  "properties": {
    "addr:full":"18630 S Pioneer Blvd Artesia CA 90701",
    "addr:housenumber":"18630",
    "addr:postcode":"90701",
    "addr:street":"S Pioneer Blvd",
    "iso:country":"US",
    "sg:address":"18630 S Pioneer Blvd",
    "sg:city":"Artesia",
    "sg:classifiers":[
        {
            "category":"Shopping",
            "subcategory":"Music",
            "type":"Retail Goods"
        }
    ],
    "sg:phone":"+1 562 924 1910",
    "sg:postcode":"90701",
    "sg:province":"CA",
    "sg:tags":[
        "dvd's"
    ],
    "wof:name":"Rhythm",
    "wof:placetype":"venue"
},
  "geometry": {"coordinates":[-118.082038,33.861932],"type":"Point"}
}