{
  "type": "Feature",
  "properties": {
    "iso:country":"US",
    "sg:address":"1837 E 7th St",
    "sg:city":"Long Beach",
    "sg:classifiers":[
        {
            "category":"Restaurant",
            "type":"Food & Drink"
        }
    ],
    "sg:phone":"+1 562 599 1080",
    "sg:postcode":"90813",
    "sg:province":"CA",
    "wof:name":"LA Rizza's Pizza House",
    "wof:placetype":"venue"
},
  "geometry": {"coordinates":[-118.16906899999999,33.775416],"type":"Point"}
}