{
  "type": "Feature",
  "properties": {
    "addr:full":"14610 Aliso Dr Fontana CA 92337",
    "addr:housenumber":"14610",
    "addr:postcode":"92337",
    "addr:street":"Aliso Dr",
    "iso:country":"US",
    "sg:address":"14610 Aliso Dr",
    "sg:city":"Fontana",
    "sg:classifiers":[
        {
            "category":"Shopping",
            "subcategory":"Bicycles & Sporting Goods",
            "type":"Retail Goods"
        }
    ],
    "sg:phone":"+1 909 350 4769",
    "sg:postcode":"92337",
    "sg:province":"CA",
    "wof:name":"Kidzone",
    "wof:placetype":"venue"
},
  "geometry": {"coordinates":[-117.488865,34.060169],"type":"Point"}
}