{
  "type": "Feature",
  "properties": {
    "iso:country":"US",
    "sg:address":"2520 Berryessa Rd",
    "sg:city":"San Jose",
    "sg:classifiers":[
        {
            "category":"Personal",
            "subcategory":"Beauty Salon",
            "type":"Services"
        }
    ],
    "sg:phone":"+1 408 272 1912",
    "sg:postcode":"95132",
    "sg:province":"CA",
    "wof:name":"San Jose Permanent Makeup",
    "wof:placetype":"venue"
},
  "geometry": {"coordinates":[-121.859548,37.387331],"type":"Point"}
}