{
  "type": "Feature",
  "properties": {
    "iso:country":"US",
    "sg:address":"9454 Wilshire Blvd",
    "sg:city":"Beverly Hills",
    "sg:classifiers":[
        {
            "category":"Banks & Credit Unions",
            "subcategory":"Financial Services",
            "type":"Services"
        }
    ],
    "sg:phone":"+1 310 276 5030",
    "sg:postcode":"90212",
    "sg:province":"CA",
    "sg:tags":[
        "trust",
        "investment",
        "real estate"
    ],
    "wof:name":"Mike Davidov Investments",
    "wof:placetype":"venue"
},
  "geometry": {"coordinates":[-118.398597,34.066982],"type":"Point"}
}