{
  "type": "Feature",
  "properties": {
    "iso:country":"US",
    "sg:address":"2737 S Croddy Way",
    "sg:city":"Santa Ana",
    "sg:classifiers":[
        {
            "category":"Health Services",
            "subcategory":"Dentist",
            "type":"Services"
        }
    ],
    "sg:phone":"+1 714 751 0121",
    "sg:postcode":"92704",
    "sg:province":"CA",
    "wof:name":"Coastal Bio Care",
    "wof:placetype":"venue"
},
  "geometry": {"coordinates":[-117.921637,33.710705],"type":"Point"}
}