{
  "type": "Feature",
  "properties": {
    "iso:country":"US",
    "sg:address":"869 Cayo Grande Ct",
    "sg:city":"Newbury Park",
    "sg:classifiers":[
        {
            "category":"Building & Trades",
            "subcategory":"Plumbing",
            "type":"Services"
        }
    ],
    "sg:phone":"+1 805 499 3744",
    "sg:postcode":"91320",
    "sg:province":"CA",
    "sg:tags":[
        "contractor"
    ],
    "wof:name":"Stimson Plumbing",
    "wof:placetype":"venue"
},
  "geometry": {"coordinates":[-118.958387,34.191039],"type":"Point"}
}