{
  "type": "Feature",
  "properties": {
    "addr:full":"421 Leoni Dr Grover Beach CA 93433",
    "addr:housenumber":"421",
    "addr:postcode":"93433",
    "addr:street":"Leoni Dr",
    "iso:country":"US",
    "sg:address":"421 Leoni Dr",
    "sg:city":"Grover Beach",
    "sg:classifiers":[
        {
            "category":"Manufacturing",
            "subcategory":"Tools & Machinery",
            "type":"Manufacturing & Wholesale Goods"
        }
    ],
    "sg:phone":"+1 805 481 3378",
    "sg:postcode":"93433",
    "sg:province":"CA",
    "sg:tags":[
        "stairway",
        "moving",
        "elevator"
    ],
    "wof:name":"Elpro Inc",
    "wof:placetype":"venue"
},
  "geometry": {"coordinates":[-120.62357799999999,35.113423],"type":"Point"}
}