{
  "type": "Feature",
  "properties": {
    "addr:full":"801 4th Ave San Diego CA 92101",
    "addr:housenumber":"801",
    "addr:postcode":"92101",
    "addr:street":"4Th Ave",
    "iso:country":"US",
    "sg:address":"801 4th Ave",
    "sg:city":"San Diego",
    "sg:classifiers":[
        {
            "category":"Restaurant",
            "type":"Food & Drink"
        }
    ],
    "sg:phone":"+1 619 615 7625",
    "sg:postcode":"92101",
    "sg:province":"CA",
    "sg:tags":[
        "traditional",
        "american"
    ],
    "sg:website":"www.hardrock.com/sandiego",
    "wof:name":"Hard Rock Cafe",
    "wof:placetype":"venue"
},
  "geometry": {"coordinates":[-117.16100299999999,32.713699],"type":"Point"}
}