{
  "type": "Feature",
  "properties": {
    "addr:full":"21250 Stevens Creek Blvd Cupertino CA 95014",
    "addr:housenumber":"21250",
    "addr:postcode":"95014",
    "addr:street":"Stevens Creek Blvd",
    "iso:country":"US",
    "sg:address":"21250 Stevens Creek Blvd",
    "sg:city":"Cupertino",
    "sg:classifiers":[
        {
            "category":"Sports & Exercise",
            "subcategory":"Sports Center",
            "type":"Entertainment"
        },
        {
            "category":"Community Center",
            "type":"Public Place"
        }
    ],
    "sg:phone":"+1 408 864 8987",
    "sg:postcode":"95014",
    "sg:province":"CA",
    "sg:tags":[
        "recreation"
    ],
    "wof:name":"California History Ctr",
    "wof:placetype":"venue"
},
  "geometry": {"coordinates":[-122.046047,37.3228],"type":"Point"}
}