{
  "type": "Feature",
  "properties": {
    "iso:country":"US",
    "sg:address":"224 S C St",
    "sg:city":"Madera",
    "sg:classifiers":[
        {
            "category":"Recreation",
            "type":"Entertainment"
        }
    ],
    "sg:phone":"+1 559 673 9754",
    "sg:postcode":"93638",
    "sg:province":"CA",
    "sg:tags":[
        "parlor",
        "billiard"
    ],
    "wof:name":"Primavera Pool Hall & Cafe",
    "wof:placetype":"venue"
},
  "geometry": {"coordinates":[-120.056217,36.962053],"type":"Point"}
}