{
  "type": "Feature",
  "properties": {
    "addr:full":"304 Taraval St San Francisco CA 94116",
    "addr:housenumber":"304",
    "addr:postcode":"94116",
    "addr:street":"Taraval St",
    "iso:country":"US",
    "sg:address":"304 Taraval St",
    "sg:city":"San Francisco",
    "sg:classifiers":[
        {
            "category":"Personal",
            "subcategory":"Beauty Salon",
            "type":"Services"
        }
    ],
    "sg:phone":"+1 415 509 2280",
    "sg:postcode":"94116",
    "sg:province":"CA",
    "sg:tags":[
        "hair"
    ],
    "wof:name":"Hair by Angela",
    "wof:placetype":"venue"
},
  "geometry": {"coordinates":[-122.469443,37.743352],"type":"Point"}
}