{
  "type": "Feature",
  "properties": {
    "addr:full":"640 S Hill St Ste 238 Los Angeles CA 90014",
    "addr:housenumber":"640",
    "addr:postcode":"90014",
    "addr:street":"S Hill St Ste 238",
    "iso:country":"US",
    "sg:address":"640 S Hill St Ste 238",
    "sg:city":"Los Angeles",
    "sg:classifiers":[
        {
            "category":"Shopping",
            "subcategory":"Jewelry",
            "type":"Retail Goods"
        }
    ],
    "sg:phone":"+1 213 489 7885",
    "sg:postcode":"90014",
    "sg:province":"CA",
    "wof:name":"Conti Aoro Jewelry",
    "wof:placetype":"venue"
},
  "geometry": {"coordinates":[-118.253998,34.046799],"type":"Point"}
}