{
  "type": "Feature",
  "properties": {
    "addr:full":"2345 S Watney Way Fairfield CA 94533",
    "addr:housenumber":"2345",
    "addr:postcode":"94533",
    "addr:street":"S Watney Way",
    "iso:country":"US",
    "sg:address":"2345 S Watney Way",
    "sg:city":"Fairfield",
    "sg:classifiers":[
        {
            "category":"Freight",
            "type":"Transportation"
        }
    ],
    "sg:phone":"+1 707 864 5422",
    "sg:postcode":"94533",
    "sg:province":"CA",
    "sg:tags":[
        "mover"
    ],
    "wof:name":"Redball Inc",
    "wof:placetype":"venue"
},
  "geometry": {"coordinates":[-122.070589,38.234365],"type":"Point"}
}