{
  "type": "Feature",
  "properties": {
    "iso:country":"US",
    "sg:address":"1600 E 4th St",
    "sg:city":"Los Angeles",
    "sg:classifiers":[
        {
            "category":"Food & Beverages",
            "subcategory":"Liquor & Beverages",
            "type":"Retail Goods"
        }
    ],
    "sg:phone":"+1 323 269 0098",
    "sg:postcode":"90033",
    "sg:province":"CA",
    "wof:name":"B & G Liquors",
    "wof:placetype":"venue"
},
  "geometry": {"coordinates":[-118.222147,34.042942],"type":"Point"}
}