{
  "type": "Feature",
  "properties": {
    "addr:full":"8350 Santa Monica Boulevard West Hollywood CA 90069",
    "addr:housenumber":"8350",
    "addr:postcode":"90069",
    "addr:street":"Santa Monica Boulevard",
    "iso:country":"US",
    "sg:address":"8350 Santa Monica Boulevard",
    "sg:city":"West Hollywood",
    "sg:classifiers":[
        {
            "category":"Education",
            "subcategory":"Kindergarten",
            "type":"Public Place"
        }
    ],
    "sg:phone":"+1 323 656 8877",
    "sg:postcode":"90069",
    "sg:province":"CA",
    "sg:tags":[
        "school",
        "driving"
    ],
    "wof:name":"L A Driver Education Center",
    "wof:placetype":"venue"
},
  "geometry": {"coordinates":[-118.371742,34.090655],"type":"Point"}
}