{
  "type": "Feature",
  "properties": {
    "addr:full":"1415 Fulton Rd Santa Rosa CA 95403",
    "addr:housenumber":"1415",
    "addr:postcode":"95403",
    "addr:street":"Fulton Rd",
    "iso:country":"US",
    "sg:address":"1415 Fulton Rd",
    "sg:city":"Santa Rosa",
    "sg:classifiers":[
        {
            "category":"Personal",
            "type":"Services"
        }
    ],
    "sg:phone":"+1 707 527 6488",
    "sg:postcode":"95403",
    "sg:province":"CA",
    "sg:tags":[
        "mail",
        "receiving"
    ],
    "wof:name":"Mail Center Etc",
    "wof:placetype":"venue"
},
  "geometry": {"coordinates":[-122.769644,38.458638],"type":"Point"}
}