{
  "type": "Feature",
  "properties": {
    "iso:country":"US",
    "sg:address":"3014 E Walnut St",
    "sg:city":"Ontario",
    "sg:classifiers":[
        {
            "category":"Building & Trades",
            "subcategory":"Plumbing",
            "type":"Services"
        }
    ],
    "sg:phone":"+1 909 923 5896",
    "sg:postcode":"91761",
    "sg:province":"CA",
    "sg:tags":[
        "contractor"
    ],
    "wof:name":"Plumbers On Call",
    "wof:placetype":"venue"
},
  "geometry": {"coordinates":[-117.585814,34.024915],"type":"Point"}
}