{
  "type": "Feature",
  "properties": {
    "iso:country":"US",
    "sg:address":"5988 E State Hwy 140",
    "sg:city":"Merced",
    "sg:classifiers":[
        {
            "category":"Farming",
            "subcategory":"Farm & Veterinary Services",
            "type":"Manufacturing & Wholesale Goods"
        }
    ],
    "sg:phone":"+1 209 384 8659",
    "sg:postcode":"95340",
    "sg:province":"CA",
    "sg:tags":[
        "management"
    ],
    "wof:name":"Horizon Farm Shop",
    "wof:placetype":"venue"
},
  "geometry": {"coordinates":[-120.381896,37.295989],"type":"Point"}
}