{
  "type": "Feature",
  "properties": {
    "addr:full":"1006 Carpenter Rd #5 Modesto CA 95351",
    "addr:housenumber":"1006",
    "addr:postcode":"ca 95351",
    "addr:street":"Carpenter Rd # 5",
    "iso:country":"US",
    "sg:address":"1006 Carpenter Rd #5",
    "sg:city":"Modesto",
    "sg:classifiers":[
        {
            "category":"Building & Trades",
            "subcategory":"Plumbing",
            "type":"Services"
        }
    ],
    "sg:phone":"+1 209 524 8312",
    "sg:postcode":"95351",
    "sg:province":"CA",
    "sg:website":"www.triceplumbing.com",
    "wof:name":"Trice Plumbing Sevice",
    "wof:placetype":"venue"
},
  "geometry": {"coordinates":[-121.03048800000001,37.628853],"type":"Point"}
}