{
  "type": "Feature",
  "properties": {
    "iso:country":"US",
    "sg:address":"13579 Whittram Ave",
    "sg:city":"Fontana",
    "sg:classifiers":[
        {
            "category":"Professional",
            "subcategory":"Research",
            "type":"Services"
        }
    ],
    "sg:phone":"+1 909 356 4521",
    "sg:postcode":"92335",
    "sg:province":"CA",
    "sg:tags":[
        "environmental",
        "ecological"
    ],
    "wof:name":"Advance Environmental Inc",
    "wof:placetype":"venue"
},
  "geometry": {"coordinates":[-117.50237799999999,34.094582],"type":"Point"}
}