{
  "type": "Feature",
  "properties": {
    "addr:full":"3000 Riverside Dr Los Angeles CA 90039",
    "addr:housenumber":"3000",
    "addr:postcode":"90039",
    "addr:street":"Riverside Dr",
    "iso:country":"US",
    "sg:address":"3000 Riverside Dr",
    "sg:city":"Los Angeles",
    "sg:classifiers":[
        {
            "category":"Building & Trades",
            "subcategory":"Cleaning & Sanitation",
            "type":"Services"
        }
    ],
    "sg:phone":"+1 323 660 7388",
    "sg:postcode":"90039",
    "sg:province":"CA",
    "sg:tags":[
        "carpet"
    ],
    "sg:website":"www.thomasrugcleaning.com",
    "wof:name":"Thomas Rug Cleaning Company and Ararat Oriental Rugs",
    "wof:placetype":"venue"
},
  "geometry": {"coordinates":[-118.266071,34.111251],"type":"Point"}
}