{
  "type": "Feature",
  "properties": {
    "addr:full":"1339 Lincoln Ave Calistoga CA 94515",
    "addr:housenumber":"1339",
    "addr:postcode":"94515",
    "addr:street":"Lincoln Ave",
    "iso:country":"US",
    "sg:address":"1339 Lincoln Ave",
    "sg:city":"Calistoga",
    "sg:classifiers":[
        {
            "category":"Personal",
            "subcategory":"Massage",
            "type":"Services"
        },
        {
            "category":"Personal",
            "subcategory":"Day Spa",
            "type":"Services"
        }
    ],
    "sg:phone":"+1 707 942 5296",
    "sg:postcode":"94515",
    "sg:province":"CA",
    "sg:website":"www.lincolnavenuespa.com/",
    "wof:name":"Lincoln Avenue Spa",
    "wof:placetype":"venue"
},
  "geometry": {"coordinates":[-122.58000199999999,38.577599],"type":"Point"}
}