{
  "type": "Feature",
  "properties": {
    "addr:full":"308 Center St Healdsburg CA 95448",
    "addr:housenumber":"308",
    "addr:postcode":"95448",
    "addr:street":"Center St",
    "iso:country":"US",
    "sg:address":"308 Center St",
    "sg:city":"Healdsburg",
    "sg:classifiers":[
        {
            "category":"Food & Beverages",
            "subcategory":"Bakery",
            "type":"Retail Goods"
        }
    ],
    "sg:phone":"+1 707 431 2719",
    "sg:postcode":"95448",
    "sg:province":"CA",
    "sg:tags":[
        "baker"
    ],
    "sg:website":"www.downtownbakery.net",
    "wof:name":"Downtown Bakery & Creamery",
    "wof:placetype":"venue"
},
  "geometry": {"coordinates":[-122.86944800000001,38.610985],"type":"Point"}
}