{
  "type": "Feature",
  "properties": {
    "iso:country":"US",
    "sg:address":"4650 Border Village Rd",
    "sg:city":"San Ysidro",
    "sg:classifiers":[
        {
            "category":"Utilities",
            "subcategory":"Mobile Phone",
            "type":"Services"
        }
    ],
    "sg:phone":"+1 619 615 0827",
    "sg:postcode":"92173",
    "sg:province":"CA",
    "sg:tags":[
        "telephone",
        "cellular"
    ],
    "wof:name":"Skytell Wireless",
    "wof:placetype":"venue"
},
  "geometry": {"coordinates":[-117.038387,32.549104],"type":"Point"}
}