{
  "type": "Feature",
  "properties": {
    "addr:full":"2913 Jorie Ave Bakersfield CA 93304",
    "addr:housenumber":"2913",
    "addr:postcode":"93304",
    "addr:street":"Jorie Ave",
    "iso:country":"US",
    "sg:address":"2913 Jorie Ave",
    "sg:city":"Bakersfield",
    "sg:classifiers":[
        {
            "category":"Professional",
            "subcategory":"Computer Services",
            "type":"Services"
        }
    ],
    "sg:phone":"+1 661 831 1836",
    "sg:postcode":"93304",
    "sg:province":"CA",
    "sg:tags":[
        "programming"
    ],
    "sg:website":"www.cypressnet.com",
    "wof:name":"Cypress Technologies",
    "wof:placetype":"venue"
},
  "geometry": {"coordinates":[-119.03683599999999,35.32433],"type":"Point"}
}