{
  "type": "Feature",
  "properties": {
    "iso:country":"US",
    "sg:address":"1195 W Foothill Blvd",
    "sg:city":"Azusa",
    "sg:classifiers":[
        {
            "category":"Autos & Motor Vehicles",
            "subcategory":"Fuel & Gas Station",
            "type":"Retail Goods"
        }
    ],
    "sg:phone":"+1 626 969 4271",
    "sg:postcode":"91702",
    "sg:province":"CA",
    "sg:tags":[
        "oil"
    ],
    "wof:name":"Shell",
    "wof:placetype":"venue"
},
  "geometry": {"coordinates":[-117.924021,34.133636],"type":"Point"}
}