{
  "type": "Feature",
  "properties": {
    "addr:full":"249 N Ivy St Escondido CA 92025",
    "addr:housenumber":"249",
    "addr:postcode":"92025",
    "addr:street":"N Ivy St",
    "iso:country":"US",
    "sg:address":"249 N Ivy St",
    "sg:city":"Escondido",
    "sg:classifiers":[
        {
            "category":"Autos & Motor Vehicles",
            "subcategory":"Auto Supplies",
            "type":"Retail Goods"
        }
    ],
    "sg:phone":"+1 760 743 5646",
    "sg:postcode":"92025",
    "sg:province":"CA",
    "sg:tags":[
        "automobile",
        "stereo",
        "radio"
    ],
    "wof:name":"Escondido Auto Sound",
    "wof:placetype":"venue"
},
  "geometry": {"coordinates":[-117.07804400000001,33.124629],"type":"Point"}
}