{
  "type": "Feature",
  "properties": {
    "addr:full":"915 S Mateo St Los Angeles CA 90021",
    "addr:housenumber":"915",
    "addr:postcode":"90021",
    "addr:street":"S Mateo St",
    "iso:country":"US",
    "sg:address":"915 S Mateo St",
    "sg:city":"Los Angeles",
    "sg:classifiers":[
        {
            "category":"Bars & Pubs",
            "subcategory":"Nightclub",
            "type":"Food & Drink"
        }
    ],
    "sg:phone":"+1 213 239 9718",
    "sg:postcode":"90021",
    "sg:province":"CA",
    "sg:tags":[
        "nightlife"
    ],
    "wof:name":"Silver Factory Studios",
    "wof:placetype":"venue"
},
  "geometry": {"coordinates":[-118.232574,34.031923],"type":"Point"}
}