{
  "type": "Feature",
  "properties": {
    "iso:country":"US",
    "sg:address":"469 Silverado Trl S",
    "sg:city":"St Helena",
    "sg:classifiers":[
        {
            "category":"Building & Trades",
            "subcategory":"Construction",
            "type":"Services"
        }
    ],
    "sg:phone":"+1 707 963 8274",
    "sg:postcode":"94574",
    "sg:province":"CA",
    "sg:tags":[
        "contractor"
    ],
    "wof:name":"Sbd Construction & Development",
    "wof:placetype":"venue"
},
  "geometry": {"coordinates":[-122.434181,38.50359],"type":"Point"}
}