{
  "type": "Feature",
  "properties": {
    "iso:country":"US",
    "sg:address":"13017 Artesia Blvd",
    "sg:city":"Cerritos",
    "sg:classifiers":[
        {
            "category":"Communications",
            "subcategory":"News Services",
            "type":"Services"
        }
    ],
    "sg:phone":"+1 562 802 2449",
    "sg:postcode":"90703",
    "sg:province":"CA",
    "wof:name":"S D News Svc",
    "wof:placetype":"venue"
},
  "geometry": {"coordinates":[-118.05363,33.873281],"type":"Point"}
}