{
  "type": "Feature",
  "properties": {
    "addr:full":"1230 Creston St Santa Maria CA 93454",
    "addr:housenumber":"1230",
    "addr:postcode":"93454",
    "addr:street":"Creston St",
    "iso:country":"US",
    "sg:address":"1230 Creston St",
    "sg:city":"Santa Maria",
    "sg:classifiers":[
        {
            "category":"Arts & Performance",
            "subcategory":"Theater",
            "type":"Entertainment"
        }
    ],
    "sg:phone":"+1 805 925 7780",
    "sg:postcode":"93454",
    "sg:province":"CA",
    "sg:tags":[
        "live",
        "music"
    ],
    "wof:name":"Muir Music DJ Svc",
    "wof:placetype":"venue"
},
  "geometry": {"coordinates":[-120.41554499999999,34.970768],"type":"Point"}
}