{
  "type": "Feature",
  "properties": {
    "iso:country":"US",
    "sg:address":"1830 Sequoia Avenue",
    "sg:city":"Burlingame",
    "sg:classifiers":[
        {
            "category":"Real Estate",
            "subcategory":"Real Estate Operator",
            "type":"Services"
        }
    ],
    "sg:phone":"+1 650 697 0627",
    "sg:postcode":"94010",
    "sg:province":"CA",
    "sg:tags":[
        "apartment"
    ],
    "sg:website":"www.woodmontrentals.com",
    "wof:name":"Burlingame West Apartments",
    "wof:placetype":"venue"
},
  "geometry": {"coordinates":[-122.388955,37.591699],"type":"Point"}
}