{
  "type": "Feature",
  "properties": {
    "addr:full":"1137 Pauline Ave Modesto CA 95358",
    "addr:housenumber":"1137",
    "addr:postcode":"ca 95358",
    "addr:street":"Pauline Ave",
    "iso:country":"US",
    "sg:address":"1137 Pauline Ave",
    "sg:city":"Modesto",
    "sg:classifiers":[
        {
            "category":"Professional",
            "subcategory":"Advertising",
            "type":"Services"
        }
    ],
    "sg:phone":"+1 209 571 0498",
    "sg:postcode":"95358",
    "sg:province":"CA",
    "sg:tags":[
        "distribution"
    ],
    "wof:name":"Building Materials Distr",
    "wof:placetype":"venue"
},
  "geometry": {"coordinates":[-121.05359,37.6348],"type":"Point"}
}