{
  "type": "Feature",
  "properties": {
    "iso:country":"US",
    "sg:address":"8033 Big Springs Rd",
    "sg:city":"Montague",
    "sg:classifiers":[
        {
            "category":"Manufacturing",
            "subcategory":"Lumber",
            "type":"Manufacturing & Wholesale Goods"
        }
    ],
    "sg:phone":"+1 530 459 5426",
    "sg:postcode":"96064",
    "sg:province":"CA",
    "sg:tags":[
        "forestry"
    ],
    "wof:name":"William L Kleaver",
    "wof:placetype":"venue"
},
  "geometry": {"coordinates":[-122.399602,41.628005],"type":"Point"}
}