{
  "type": "Feature",
  "properties": {
    "addr:full":"20861 Wilbeam Ave Ste 1 Castro Valley CA 94546",
    "addr:postcode":"20861;94546",
    "addr:street":"Wilbeam Ave Ste 1",
    "iso:country":"US",
    "sg:address":"20861 Wilbeam Ave Ste 1",
    "sg:city":"Castro Valley",
    "sg:classifiers":[
        {
            "category":"Building & Trades",
            "subcategory":"Construction",
            "type":"Services"
        }
    ],
    "sg:phone":"+1 510 888 9488",
    "sg:postcode":"94546",
    "sg:province":"CA",
    "sg:tags":[
        "installation",
        "solar"
    ],
    "sg:website":"www.thesolarco.com",
    "wof:name":"The Solar Company",
    "wof:placetype":"venue"
},
  "geometry": {"coordinates":[-122.077603,37.694854],"type":"Point"}
}