{
  "type": "Feature",
  "properties": {
    "addr:full":"1000 N Coast Hwy #6 Laguna Beach CA 92651",
    "addr:housenumber":"1000",
    "addr:postcode":"92651",
    "addr:street":"N Coast Hwy # 6",
    "iso:country":"US",
    "sg:address":"1000 N Coast Hwy #6",
    "sg:city":"Laguna Beach",
    "sg:classifiers":[
        {
            "category":"Personal",
            "subcategory":"Massage",
            "type":"Services"
        }
    ],
    "sg:phone":"+1 949 280 0992",
    "sg:postcode":"92651",
    "sg:province":"CA",
    "wof:name":"OC Sports Massage",
    "wof:placetype":"venue"
},
  "geometry": {"coordinates":[-117.797737,33.54779],"type":"Point"}
}