{
  "type": "Feature",
  "properties": {
    "addr:full":"12862 Garden Grove Blvd Garden Grove CA 92843",
    "addr:housenumber":"12862",
    "addr:postcode":"92843",
    "addr:street":"Garden Grove Blvd",
    "iso:country":"US",
    "sg:address":"12862 Garden Grove Blvd",
    "sg:city":"Garden Grove",
    "sg:classifiers":[
        {
            "category":"Banks & Credit Unions",
            "subcategory":"Bank",
            "type":"Services"
        }
    ],
    "sg:phone":"+1 714 539 4190",
    "sg:postcode":"92843",
    "sg:province":"CA",
    "sg:tags":[
        "loan",
        "real estate"
    ],
    "wof:name":"Able Mortgage",
    "wof:placetype":"venue"
},
  "geometry": {"coordinates":[-117.90692300000001,33.774353],"type":"Point"}
}