{
  "type": "Feature",
  "properties": {
    "addr:full":"1073 H St Arcata CA 95521",
    "addr:housenumber":"1073",
    "addr:postcode":"95521",
    "addr:street":"H St",
    "iso:country":"US",
    "sg:address":"1073 H St",
    "sg:city":"Arcata",
    "sg:classifiers":[
        {
            "category":"Shopping",
            "subcategory":"Used Merchandise",
            "type":"Retail Goods"
        }
    ],
    "sg:phone":"+1 707 826 1256",
    "sg:postcode":"95521",
    "sg:province":"CA",
    "sg:tags":[
        "antique"
    ],
    "wof:name":"One Man's Treasure",
    "wof:placetype":"venue"
},
  "geometry": {"coordinates":[-124.086438,40.870045],"type":"Point"}
}