{
  "type": "Feature",
  "properties": {
    "addr:full":"850 S Baldwin Ave Arcadia CA 91007",
    "addr:housenumber":"850",
    "addr:postcode":"91007",
    "addr:street":"S Baldwin Ave",
    "iso:country":"US",
    "sg:address":"850 S Baldwin Ave",
    "sg:city":"Arcadia",
    "sg:phone":"+1 626 294 9628",
    "sg:postcode":"91007",
    "sg:province":"CA",
    "wof:name":"Cafe Deco",
    "wof:placetype":"venue"
},
  "geometry": {"coordinates":[-118.054573,34.130621],"type":"Point"}
}