{
  "type": "Feature",
  "properties": {
    "iso:country":"US",
    "sg:address":"24331 El Toro Rd",
    "sg:city":"Laguna Woods",
    "sg:classifiers":[
        {
            "category":"Health Services",
            "subcategory":"Doctor",
            "type":"Services"
        }
    ],
    "sg:phone":"+1 949 586 3200",
    "sg:postcode":"92637",
    "sg:province":"CA",
    "sg:tags":[
        "orthopedist"
    ],
    "wof:name":"Veneziano Christopher MD",
    "wof:placetype":"venue"
},
  "geometry": {"coordinates":[-117.72942500000001,33.609398],"type":"Point"}
}