{
  "type": "Feature",
  "properties": {
    "addr:full":"1021 E Walnut St Pasadena CA 91106",
    "addr:housenumber":"1021",
    "addr:postcode":"91106",
    "addr:street":"E Walnut St",
    "iso:country":"US",
    "sg:address":"1021 E Walnut St",
    "sg:city":"Pasadena",
    "sg:classifiers":[
        {
            "category":"Professional",
            "subcategory":"Employment Agencies",
            "type":"Services"
        }
    ],
    "sg:phone":"+1 626 795 2560",
    "sg:postcode":"91106",
    "sg:province":"CA",
    "sg:tags":[
        "modeling"
    ],
    "wof:name":"Adrian Teen Models Agency",
    "wof:placetype":"venue"
},
  "geometry": {"coordinates":[-118.12835800000001,34.149687],"type":"Point"}
}