{
  "type": "Feature",
  "properties": {
    "addr:full":"333 Clark Ave Pomona CA 91767",
    "addr:housenumber":"333",
    "addr:postcode":"91767",
    "addr:street":"Clark Ave",
    "iso:country":"US",
    "sg:address":"333 Clark Ave",
    "sg:city":"Pomona",
    "sg:classifiers":[
        {
            "category":"Manufacturing",
            "subcategory":"Apparel",
            "type":"Manufacturing & Wholesale Goods"
        }
    ],
    "sg:phone":"+1 909 397 8088",
    "sg:postcode":"91767",
    "sg:province":"CA",
    "sg:tags":[
        "sewing",
        "contractor"
    ],
    "wof:name":"Giang's Fashions",
    "wof:placetype":"venue"
},
  "geometry": {"coordinates":[-117.72933399999999,34.061709],"type":"Point"}
}