{
  "type": "Feature",
  "properties": {
    "addr:full":"1 Jenner Irvine CA 92618",
    "addr:housenumber":"1",
    "addr:postcode":"92618",
    "addr:street":"Jenner",
    "iso:country":"US",
    "sg:address":"1 Jenner",
    "sg:city":"Irvine",
    "sg:classifiers":[
        {
            "category":"Communications",
            "type":"Services"
        }
    ],
    "sg:phone":"+1 949 743 2000",
    "sg:postcode":"92618",
    "sg:province":"CA",
    "sg:tags":[
        "content",
        "delivery",
        "network",
        "provides"
    ],
    "wof:name":"Vitalstream",
    "wof:placetype":"venue"
},
  "geometry": {"coordinates":[-117.766965,33.654436],"type":"Point"}
}