{
  "type": "Feature",
  "properties": {
    "iso:country":"US",
    "sg:address":"1401 Avocado Ave",
    "sg:city":"Newport Beach",
    "sg:classifiers":[
        {
            "category":"Health Services",
            "subcategory":"Doctor",
            "type":"Services"
        }
    ],
    "sg:phone":"+1 949 760 0700",
    "sg:postcode":"92660",
    "sg:province":"CA",
    "sg:tags":[
        "physician",
        "surgeon"
    ],
    "wof:name":"Henry I Baylis MD",
    "wof:placetype":"venue"
},
  "geometry": {"coordinates":[-117.871731,33.611116],"type":"Point"}
}