{
  "type": "Feature",
  "properties": {
    "addr:full":"951 W F St Ontario CA 91762",
    "addr:housenumber":"951",
    "addr:postcode":"91762",
    "addr:street":"W F St",
    "iso:country":"US",
    "sg:address":"951 W F St",
    "sg:city":"Ontario",
    "sg:classifiers":[
        {
            "category":"Building & Trades",
            "subcategory":"Plumbing",
            "type":"Services"
        }
    ],
    "sg:phone":"+1 909 208 7808",
    "sg:postcode":"91762",
    "sg:province":"CA",
    "sg:tags":[
        "plumber",
        "industrial",
        "contractors-commercial"
    ],
    "wof:name":"The Specialist Plumbing",
    "wof:placetype":"venue"
},
  "geometry": {"coordinates":[-117.66620399999999,34.069672],"type":"Point"}
}