{
  "type": "Feature",
  "properties": {
    "addr:full":"354 S Main St Altaville CA 95221",
    "addr:housenumber":"354",
    "addr:postcode":"95221",
    "addr:street":"S Main St",
    "iso:country":"US",
    "sg:address":"354 S Main St",
    "sg:city":"Altaville",
    "sg:classifiers":[
        {
            "category":"Sports & Exercise",
            "subcategory":"Gym",
            "type":"Entertainment"
        }
    ],
    "sg:phone":"+1 209 736 0600",
    "sg:postcode":"95221",
    "sg:province":"CA",
    "sg:tags":[
        "club",
        "health",
        "studio",
        "gymnasium"
    ],
    "wof:name":"Curves For Women",
    "wof:placetype":"venue"
},
  "geometry": {"coordinates":[-120.55313,38.078657],"type":"Point"}
}