{
  "type": "Feature",
  "properties": {
    "addr:full":"4517 3rd St San Francisco CA 94124",
    "addr:housenumber":"4517",
    "addr:postcode":"94124",
    "addr:street":"3Rd St",
    "iso:country":"US",
    "sg:address":"4517 3rd St",
    "sg:city":"San Francisco",
    "sg:classifiers":[
        {
            "category":"Food & Beverages",
            "subcategory":"Groceries & Convenience Stores",
            "type":"Retail Goods"
        }
    ],
    "sg:phone":"+1 415 282 3722",
    "sg:postcode":"94124",
    "sg:province":"CA",
    "sg:tags":[
        "grocer"
    ],
    "wof:name":"Super Save Market",
    "wof:placetype":"venue"
},
  "geometry": {"coordinates":[-122.389967,37.736473],"type":"Point"}
}