{
  "type": "Feature",
  "properties": {
    "addr:full":"1057 Helsam Ave Oxnard CA 93036",
    "addr:housenumber":"1057",
    "addr:postcode":"93036",
    "addr:street":"Helsam Ave",
    "iso:country":"US",
    "sg:address":"1057 Helsam Ave",
    "sg:city":"Oxnard",
    "sg:classifiers":[
        {
            "category":"Freight",
            "type":"Transportation"
        }
    ],
    "sg:phone":"+1 805 485 2116",
    "sg:postcode":"93036",
    "sg:province":"CA",
    "sg:tags":[
        "operator",
        "trucking"
    ],
    "wof:name":"Armando & Sons Trucking",
    "wof:placetype":"venue"
},
  "geometry": {"coordinates":[-119.155225,34.236404],"type":"Point"}
}