{
  "type": "Feature",
  "properties": {
    "addr:full":"11203 Tuxford St Sun Valley CA 91352",
    "addr:housenumber":"11203",
    "addr:postcode":"91352",
    "addr:street":"Tuxford St",
    "iso:country":"US",
    "sg:address":"11203 Tuxford St",
    "sg:city":"Sun Valley",
    "sg:classifiers":[
        {
            "category":"Wholesale",
            "subcategory":"Auto Parts",
            "type":"Manufacturing & Wholesale Goods"
        }
    ],
    "sg:phone":"+1 323 875 3620",
    "sg:postcode":"91352",
    "sg:province":"CA",
    "sg:tags":[
        "automobile",
        "supply"
    ],
    "sg:website":"www.mercedesdismantlers.com",
    "wof:name":"Sun Valley Mercedes Dismantler",
    "wof:placetype":"venue"
},
  "geometry": {"coordinates":[-118.37682100000001,34.230613],"type":"Point"}
}