{
  "type": "Feature",
  "properties": {
    "iso:country":"US",
    "sg:address":"15131 Washington Dr",
    "sg:city":"Fontana",
    "sg:classifiers":[
        {
            "category":"Professional",
            "subcategory":"Management & Consulting",
            "type":"Services"
        },
        {
            "category":"Freight",
            "type":"Transportation"
        },
        {
            "category":"Local Transit",
            "type":"Transportation"
        }
    ],
    "sg:phone":"+1 909 357 0819",
    "sg:postcode":"92335",
    "sg:province":"CA",
    "sg:tags":[
        "logistics",
        "provider",
        "broker",
        "trucking"
    ],
    "wof:name":"Godoy Logistics",
    "wof:placetype":"venue"
},
  "geometry": {"coordinates":[-117.475568,34.06717],"type":"Point"}
}