{
  "type": "Feature",
  "properties": {
    "iso:country":"US",
    "sg:address":"784 31st Ave",
    "sg:city":"San Francisco",
    "sg:classifiers":[
        {
            "category":"Professional",
            "subcategory":"Computer Services",
            "type":"Services"
        }
    ],
    "sg:phone":"+1 415 876 0802",
    "sg:postcode":"94121",
    "sg:province":"CA",
    "sg:tags":[
        "consultant",
        "designer"
    ],
    "wof:name":"BIT 64 Inc",
    "wof:placetype":"venue"
},
  "geometry": {"coordinates":[-122.490768,37.775746],"type":"Point"}
}