{
  "type": "Feature",
  "properties": {
    "iso:country":"US",
    "sg:address":"1591 Sunland Lane",
    "sg:city":"Costa Mesa",
    "sg:classifiers":[
        {
            "category":"Home & Garden",
            "subcategory":"Building Materials",
            "type":"Retail Goods"
        },
        {
            "category":"Building & Trades",
            "subcategory":"Construction",
            "type":"Services"
        }
    ],
    "sg:phone":"+1 714 241 3888",
    "sg:postcode":"92626",
    "sg:province":"CA",
    "sg:tags":[
        "interior",
        "design",
        "supply"
    ],
    "sg:website":"www.oneilcabinets.com",
    "wof:name":"O'Neil Cabinets",
    "wof:placetype":"venue"
},
  "geometry": {"coordinates":[-117.924716,33.694084],"type":"Point"}
}