{
  "type": "Feature",
  "properties": {
    "iso:country":"US",
    "sg:address":"5975 Mission St",
    "sg:city":"Daly City",
    "sg:classifiers":[
        {
            "category":"Retail",
            "subcategory":"Auto Repair",
            "type":"Services"
        }
    ],
    "sg:phone":"+1 415 337 5425",
    "sg:postcode":"94014",
    "sg:province":"CA",
    "sg:tags":[
        "repairing",
        "automobile"
    ],
    "wof:name":"Autometrix",
    "wof:placetype":"venue"
},
  "geometry": {"coordinates":[-122.45430899999999,37.708006],"type":"Point"}
}