{
  "type": "Feature",
  "properties": {
    "iso:country":"US",
    "sg:address":"1688 Willow St Ste C",
    "sg:city":"San Jose",
    "sg:classifiers":[
        {
            "category":"Health Services",
            "subcategory":"Doctor",
            "type":"Services"
        }
    ],
    "sg:phone":"+1 408 266 8563",
    "sg:postcode":"95125",
    "sg:province":"CA",
    "sg:tags":[
        "cardiologist"
    ],
    "wof:name":"Owens John P MD",
    "wof:placetype":"venue"
},
  "geometry": {"coordinates":[-121.917,37.302502],"type":"Point"}
}