{
  "type": "Feature",
  "properties": {
    "addr:full":"2443 Fillmore St San Francisco CA 94115",
    "addr:housenumber":"2443",
    "addr:postcode":"94115",
    "addr:street":"Fillmore St",
    "iso:country":"US",
    "sg:address":"2443 Fillmore St",
    "sg:city":"San Francisco",
    "sg:classifiers":[
        {
            "category":"Freight",
            "type":"Transportation"
        },
        {
            "category":"Professional",
            "subcategory":"Lawyer & Legal Services",
            "type":"Services"
        },
        {
            "category":"Professional",
            "subcategory":"Printing & Photocopies",
            "type":"Services"
        }
    ],
    "sg:phone":"+1 415 922 6245",
    "sg:postcode":"94115",
    "sg:province":"CA",
    "sg:tags":[
        "notary",
        "shipping"
    ],
    "sg:website":"www.upsstore.com",
    "wof:name":"The UPS Store",
    "wof:placetype":"venue"
},
  "geometry": {"coordinates":[-122.43480599999999,37.792193],"type":"Point"}
}