{
  "type": "Feature",
  "properties": {
    "iso:country":"US",
    "sg:address":"110 Porter Ln",
    "sg:city":"Auburn",
    "sg:classifiers":[
        {
            "category":"Wholesale",
            "subcategory":"Sporting Goods",
            "type":"Manufacturing & Wholesale Goods"
        }
    ],
    "sg:phone":"+1 530 823 0931",
    "sg:postcode":"95602",
    "sg:province":"CA",
    "wof:name":"Canyon Raft Rentals",
    "wof:placetype":"venue"
},
  "geometry": {"coordinates":[-121.04421600000001,38.949826],"type":"Point"}
}