{
  "type": "Feature",
  "properties": {
    "addr:full":"1027 Cll Trepadora San Clemente CA 92673",
    "addr:housenumber":"1027",
    "addr:postcode":"92673",
    "addr:street":"Cll Trepadora",
    "iso:country":"US",
    "sg:address":"1027 Cll Trepadora",
    "sg:city":"San Clemente",
    "sg:classifiers":[
        {
            "category":"Wholesale",
            "subcategory":"Metals & Minerals",
            "type":"Manufacturing & Wholesale Goods"
        }
    ],
    "sg:phone":"+1 949 492 5031",
    "sg:postcode":"92673",
    "sg:province":"CA",
    "sg:tags":[
        "specialty"
    ],
    "wof:name":"Gamut Metal Coat",
    "wof:placetype":"venue"
},
  "geometry": {"coordinates":[-117.60096299999999,33.453213],"type":"Point"}
}