{
  "type": "Feature",
  "properties": {
    "addr:full":"19200 Stevens Creek Blvd Ste 130 Cupertino CA 95014",
    "addr:housenumber":"19200",
    "addr:postcode":"95014",
    "addr:street":"Stevens Creek Blvd Ste 130",
    "iso:country":"US",
    "sg:address":"19200 Stevens Creek Blvd Ste 130",
    "sg:city":"Cupertino",
    "sg:classifiers":[
        {
            "category":"Banks & Credit Unions",
            "subcategory":"Financial Services",
            "type":"Services"
        }
    ],
    "sg:phone":"+1 408 907 0116",
    "sg:postcode":"95014",
    "sg:province":"CA",
    "sg:tags":[
        "broker",
        "mortgage"
    ],
    "sg:website":"www.pacificfidelitymortgage.com/",
    "wof:name":"Pacific Fidelity Mortgage",
    "wof:placetype":"venue"
},
  "geometry": {"coordinates":[-122.008392,37.32243],"type":"Point"}
}