{
  "type": "Feature",
  "properties": {
    "addr:full":"600 W Broadway San Diego CA 92101",
    "addr:housenumber":"600",
    "addr:postcode":"92101",
    "addr:street":"W Broadway",
    "iso:country":"US",
    "sg:address":"600 W Broadway",
    "sg:city":"San Diego",
    "sg:classifiers":[
        {
            "category":"Communications",
            "subcategory":"Radio Station",
            "type":"Services"
        }
    ],
    "sg:phone":"+1 619 235 0600",
    "sg:postcode":"92101",
    "sg:province":"CA",
    "wof:name":"La Nueva 106 5",
    "wof:placetype":"venue"
},
  "geometry": {"coordinates":[-117.16799899999999,32.715801],"type":"Point"}
}