{
  "type": "Feature",
  "properties": {
    "addr:full":"Doubletree Hotel San Francisco Airport 835 Airport Blvd Burlingame CA 94010",
    "addr:housenumber":"835",
    "addr:postcode":"94010",
    "addr:street":"Airport Blvd",
    "iso:country":"US",
    "sg:address":"Doubletree Hotel San Francisco Airport 835 Airport Blvd",
    "sg:city":"Burlingame",
    "sg:classifiers":[
        {
            "category":"Restaurant",
            "type":"Food & Drink"
        }
    ],
    "sg:phone":"+1 650 344 5500",
    "sg:postcode":"94010",
    "sg:province":"CA",
    "sg:tags":[
        "traditional",
        "american"
    ],
    "wof:name":"Chutney Grill",
    "wof:placetype":"venue"
},
  "geometry": {"coordinates":[-122.350415,37.591044],"type":"Point"}
}