{
  "type": "Feature",
  "properties": {
    "addr:full":"2236 W Monte Vista Ave Visalia CA 93277",
    "addr:housenumber":"2236",
    "addr:postcode":"93277",
    "addr:street":"W Monte Vista Ave",
    "iso:country":"US",
    "sg:address":"2236 W Monte Vista Ave",
    "sg:city":"Visalia",
    "sg:classifiers":[
        {
            "category":"Professional",
            "subcategory":"Advertising",
            "type":"Services"
        }
    ],
    "sg:phone":"+1 559 734 5515",
    "sg:postcode":"93277",
    "sg:province":"CA",
    "sg:tags":[
        "guide"
    ],
    "sg:website":"www.star-s.com",
    "wof:name":"Star S Publishing",
    "wof:placetype":"venue"
},
  "geometry": {"coordinates":[-119.317452,36.305108],"type":"Point"}
}