{
  "type": "Feature",
  "properties": {
    "addr:full":"3350 Sacramento St San Francisco CA 94118",
    "addr:housenumber":"3350",
    "addr:postcode":"94118",
    "addr:street":"Sacramento St",
    "iso:country":"US",
    "sg:address":"3350 Sacramento St",
    "sg:city":"San Francisco",
    "sg:classifiers":[
        {
            "category":"Home & Garden",
            "subcategory":"Home Furnishings",
            "type":"Retail Goods"
        }
    ],
    "sg:phone":"+1 415 921 6046",
    "sg:postcode":"94118",
    "sg:province":"CA",
    "sg:tags":[
        "lamp",
        "shades"
    ],
    "wof:name":"Elements",
    "wof:placetype":"venue"
},
  "geometry": {"coordinates":[-122.44798900000001,37.788157],"type":"Point"}
}