{
  "type": "Feature",
  "properties": {
    "addr:full":"14950 Oxnard St Van Nuys CA 91401",
    "addr:housenumber":"14950",
    "addr:postcode":"91401",
    "addr:street":"Oxnard St",
    "iso:country":"US",
    "sg:address":"14950 Oxnard St",
    "sg:city":"Van Nuys",
    "sg:classifiers":[
        {
            "category":"Retail",
            "subcategory":"Auto Repair",
            "type":"Services"
        }
    ],
    "sg:phone":"+1 818 779 2590",
    "sg:postcode":"91401",
    "sg:province":"CA",
    "sg:tags":[
        "body",
        "automobile",
        "painting"
    ],
    "wof:name":"Rydell Automotive Auto Body",
    "wof:placetype":"venue"
},
  "geometry": {"coordinates":[-118.459626,34.179384],"type":"Point"}
}