{
  "type": "Feature",
  "properties": {
    "addr:full":"7457 Eton Ave Canoga Park CA 91303",
    "addr:housenumber":"7457",
    "addr:postcode":"91303",
    "addr:street":"Eton Ave",
    "iso:country":"US",
    "sg:address":"7457 Eton Ave",
    "sg:city":"Canoga Park",
    "sg:classifiers":[
        {
            "category":"Retail",
            "subcategory":"Auto Repair",
            "type":"Services"
        }
    ],
    "sg:phone":"+1 818 676 1758",
    "sg:postcode":"91303",
    "sg:province":"CA",
    "sg:tags":[
        "repairing",
        "automobile"
    ],
    "wof:name":"Gonzalez Repair",
    "wof:placetype":"venue"
},
  "geometry": {"coordinates":[-118.595551,34.205446],"type":"Point"}
}