{
  "type": "Feature",
  "properties": {
    "iso:country":"US",
    "sg:address":"40 N Fairview Ave",
    "sg:city":"Goleta",
    "sg:classifiers":[
        {
            "category":"Retail",
            "subcategory":"Car Wash",
            "type":"Services"
        }
    ],
    "sg:phone":"+1 805 967 1910",
    "sg:postcode":"93117",
    "sg:province":"CA",
    "sg:tags":[
        "automobile",
        "detail",
        "clean"
    ],
    "wof:name":"Fairview Auto Salon",
    "wof:placetype":"venue"
},
  "geometry": {"coordinates":[-119.830493,34.441241],"type":"Point"}
}