{
  "type": "Feature",
  "properties": {
    "addr:full":"Desert Crossing Shop Palm Desert CA 92260",
    "addr:postcode":"92260",
    "addr:street":"Desert",
    "iso:country":"US",
    "sg:address":"Desert Crossing Shop",
    "sg:city":"Palm Desert",
    "sg:classifiers":[
        {
            "category":"Restaurant",
            "type":"Food & Drink"
        }
    ],
    "sg:phone":"+1 760 341 6653",
    "sg:postcode":"92260",
    "sg:province":"CA",
    "wof:name":"Hometown Buffet",
    "wof:placetype":"venue"
},
  "geometry": {"coordinates":[-116.38099699999999,33.725201],"type":"Point"}
}