{
  "type": "Feature",
  "properties": {
    "addr:full":"2190 Stokes St Ste 102 San Jose CA 95128",
    "addr:housenumber":"2190",
    "addr:postcode":"95128",
    "addr:street":"Stokes St Ste 102",
    "iso:country":"US",
    "sg:address":"2190 Stokes St Ste 102",
    "sg:city":"San Jose",
    "sg:classifiers":[
        {
            "category":"Professional",
            "subcategory":"Accounting & Tax Preparation",
            "type":"Services"
        }
    ],
    "sg:phone":"+1 408 918 3161",
    "sg:postcode":"95128",
    "sg:province":"CA",
    "sg:tags":[
        "accountant"
    ],
    "sg:website":"www.taxtrimmers.com",
    "wof:name":"Michael Gray, CPA",
    "wof:placetype":"venue"
},
  "geometry": {"coordinates":[-121.93079,37.301139],"type":"Point"}
}