{
  "type": "Feature",
  "properties": {
    "iso:country":"US",
    "sg:address":"830 E 5th St",
    "sg:city":"Oxnard",
    "sg:classifiers":[
        {
            "category":"Retail",
            "subcategory":"Auto Repair",
            "type":"Services"
        }
    ],
    "sg:phone":"+1 805 487 7559",
    "sg:postcode":"93030",
    "sg:province":"CA",
    "sg:tags":[
        "repairing",
        "automobile"
    ],
    "wof:name":"Ebenecer Auto Repair",
    "wof:placetype":"venue"
},
  "geometry": {"coordinates":[-119.16664900000001,34.196988],"type":"Point"}
}