{
  "type": "Feature",
  "properties": {
    "addr:full":"30690 Rancho California Rd Temecula CA 92591",
    "addr:housenumber":"30690",
    "addr:postcode":"92591",
    "addr:street":"Rancho California Rd",
    "iso:country":"US",
    "sg:address":"30690 Rancho California Rd",
    "sg:city":"Temecula",
    "sg:classifiers":[
        {
            "category":"Retail",
            "subcategory":"Auto Repair",
            "type":"Services"
        }
    ],
    "sg:phone":"+1 951 694 5460",
    "sg:postcode":"92591",
    "sg:province":"CA",
    "sg:tags":[
        "general"
    ],
    "wof:name":"Najjar Lube Centers Inc",
    "wof:placetype":"venue"
},
  "geometry": {"coordinates":[-117.124748,33.508132],"type":"Point"}
}