{
  "type": "Feature",
  "properties": {
    "iso:country":"US",
    "sg:address":"4747 W el Segundo Blvd",
    "sg:city":"Hawthorne",
    "sg:classifiers":[
        {
            "category":"Real Estate",
            "subcategory":"Real Estate Agent",
            "type":"Services"
        }
    ],
    "sg:phone":"+1 310 679 6225",
    "sg:postcode":"90250",
    "sg:province":"CA",
    "sg:website":"www.guyhocker.com",
    "wof:name":"Guy Hocker Realtors",
    "wof:placetype":"venue"
},
  "geometry": {"coordinates":[-118.360262,33.916485],"type":"Point"}
}