{
  "type": "Feature",
  "properties": {
    "addr:full":"2987 Holiday Ct Morgan Hill CA 95037",
    "addr:housenumber":"2987",
    "addr:postcode":"95037",
    "addr:street":"Holiday Ct",
    "iso:country":"US",
    "sg:address":"2987 Holiday Ct",
    "sg:city":"Morgan Hill",
    "sg:classifiers":[
        {
            "category":"Real Estate",
            "subcategory":"Real Estate Agent",
            "type":"Services"
        }
    ],
    "sg:phone":"+1 408 782 7771",
    "sg:postcode":"95037",
    "sg:province":"CA",
    "wof:name":"Dynamic Realty",
    "wof:placetype":"venue"
},
  "geometry": {"coordinates":[-121.61304699999999,37.158403],"type":"Point"}
}