{
  "type": "Feature",
  "properties": {
    "iso:country":"US",
    "sg:address":"2987 Holiday Ct",
    "sg:city":"Morgan Hill",
    "sg:classifiers":[
        {
            "category":"Real Estate",
            "subcategory":"Real Estate Agent",
            "type":"Services"
        }
    ],
    "sg:phone":"+1 408 782 7771",
    "sg:postcode":"95037",
    "sg:province":"CA",
    "wof:name":"Dynamic Realty",
    "wof:placetype":"venue"
},
  "geometry": {"coordinates":[-121.613047,37.158403],"type":"Point"}
}