{
  "type": "Feature",
  "properties": {
    "iso:country":"US",
    "sg:address":"1910 Shadowridge Dr",
    "sg:city":"Vista",
    "sg:classifiers":[
        {
            "category":"Sports & Exercise",
            "subcategory":"Gym",
            "type":"Entertainment"
        }
    ],
    "sg:phone":"+1 760 727 1001",
    "sg:postcode":"92081",
    "sg:province":"CA",
    "wof:name":"Shadowridge Jazzercise",
    "wof:placetype":"venue"
},
  "geometry": {"coordinates":[-117.24911400000001,33.157717],"type":"Point"}
}