{
  "type": "Feature",
  "properties": {
    "addr:full":"6725 Compton Ave Los Angeles CA 90001",
    "addr:housenumber":"6725",
    "addr:postcode":"90001",
    "addr:street":"Compton Ave",
    "iso:country":"US",
    "sg:address":"6725 Compton Ave",
    "sg:city":"Los Angeles",
    "sg:classifiers":[
        {
            "category":"Food & Beverages",
            "subcategory":"Groceries & Convenience Stores",
            "type":"Retail Goods"
        }
    ],
    "sg:phone":"+1 323 589 1962",
    "sg:postcode":"90001",
    "sg:province":"CA",
    "wof:name":"Lulu Minimarket",
    "wof:placetype":"venue"
},
  "geometry": {"coordinates":[-118.247855,33.979031],"type":"Point"}
}