{
  "type": "Feature",
  "properties": {
    "iso:country":"US",
    "sg:address":"2160 Lundy Ave",
    "sg:city":"San Jose",
    "sg:classifiers":[
        {
            "category":"Professional",
            "subcategory":"Management & Consulting",
            "type":"Services"
        }
    ],
    "sg:phone":"+1 408 321 7480",
    "sg:postcode":"95131",
    "sg:province":"CA",
    "sg:tags":[
        "international",
        "business"
    ],
    "sg:website":"www.2c.com",
    "wof:name":"Meyers Internet Svc",
    "wof:placetype":"venue"
},
  "geometry": {"coordinates":[-121.891061,37.39974],"type":"Point"}
}