{
  "type": "Feature",
  "properties": {
    "iso:country":"US",
    "sg:address":"1530 Royal Oak Dr",
    "sg:city":"Petaluma",
    "sg:classifiers":[
        {
            "category":"Real Estate",
            "subcategory":"Real Estate Operator",
            "type":"Services"
        }
    ],
    "sg:phone":"+1 707 762 4117",
    "sg:postcode":"94954",
    "sg:province":"CA",
    "sg:tags":[
        "mobile",
        "home",
        "community"
    ],
    "wof:name":"Royal Oaks Senior Community",
    "wof:placetype":"venue"
},
  "geometry": {"coordinates":[-122.64318799999999,38.263971],"type":"Point"}
}