{
  "type": "Feature",
  "properties": {
    "addr:full":"2033 Clement Ave Alameda CA 94501",
    "addr:housenumber":"2033",
    "addr:postcode":"94501",
    "addr:street":"Clement Ave",
    "iso:country":"US",
    "sg:address":"2033 Clement Ave",
    "sg:city":"Alameda",
    "sg:classifiers":[
        {
            "category":"Real Estate",
            "subcategory":"Architect",
            "type":"Services"
        }
    ],
    "sg:phone":"+1 510 523 5172",
    "sg:postcode":"94501",
    "sg:province":"CA",
    "sg:tags":[
        "illustrator",
        "architectural"
    ],
    "wof:name":"Guidelines",
    "wof:placetype":"venue"
},
  "geometry": {"coordinates":[-122.245859,37.773082],"type":"Point"}
}