{
  "type": "Feature",
  "properties": {
    "iso:country":"US",
    "sg:address":"770 Estates Dr",
    "sg:city":"Aptos",
    "sg:classifiers":[
        {
            "category":"Professional",
            "subcategory":"Art Services",
            "type":"Services"
        }
    ],
    "sg:phone":"+1 831 688 2428",
    "sg:postcode":"95003",
    "sg:province":"CA",
    "sg:tags":[
        "photographer"
    ],
    "sg:website":"www.artofemotion.com",
    "wof:name":"The Art of Emotion",
    "wof:placetype":"venue"
},
  "geometry": {"coordinates":[-121.921071,36.980546],"type":"Point"}
}