{
  "type": "Feature",
  "properties": {
    "iso:country":"US",
    "sg:address":"205 Canyon Way",
    "sg:city":"Arroyo Grande",
    "sg:classifiers":[
        {
            "category":"Building & Trades",
            "subcategory":"Construction",
            "type":"Services"
        }
    ],
    "sg:phone":"+1 805 481 0026",
    "sg:postcode":"93420",
    "sg:province":"CA",
    "sg:tags":[
        "mobile",
        "home"
    ],
    "wof:name":"KML Construction Co",
    "wof:placetype":"venue"
},
  "geometry": {"coordinates":[-120.584209,35.137859],"type":"Point"}
}