{
  "type": "Feature",
  "properties": {
    "iso:country":"US",
    "sg:address":"1101 Dove St",
    "sg:city":"Newport Beach",
    "sg:classifiers":[
        {
            "category":"Banks & Credit Unions",
            "subcategory":"Bank",
            "type":"Services"
        }
    ],
    "sg:phone":"+1 949 797 0100",
    "sg:postcode":"92660",
    "sg:province":"CA",
    "sg:tags":[
        "loan",
        "real estate"
    ],
    "wof:name":"Surfside Funding",
    "wof:placetype":"venue"
},
  "geometry": {"coordinates":[-117.865343,33.660894],"type":"Point"}
}