{
  "type": "Feature",
  "properties": {
    "addr:full":"3696 Sunnyside Dr Riverside CA 92506",
    "addr:housenumber":"3696",
    "addr:postcode":"92506",
    "addr:street":"Sunnyside Dr",
    "iso:country":"US",
    "sg:address":"3696 Sunnyside Dr",
    "sg:city":"Riverside",
    "sg:classifiers":[
        {
            "category":"Personal",
            "subcategory":"Beauty Salon",
            "type":"Services"
        }
    ],
    "sg:phone":"+1 951 781 2130",
    "sg:postcode":"92506",
    "sg:province":"CA",
    "wof:name":"Karen Graham",
    "wof:placetype":"venue"
},
  "geometry": {"coordinates":[-117.395399,33.954506],"type":"Point"}
}