{
  "type": "Feature",
  "properties": {
    "iso:country":"US",
    "sg:address":"764 Market St",
    "sg:city":"San Francisco",
    "sg:classifiers":[
        {
            "category":"Shopping",
            "subcategory":"Shoes",
            "type":"Retail Goods"
        }
    ],
    "sg:phone":"+1 415 399 0721",
    "sg:postcode":"94102",
    "sg:province":"CA",
    "wof:name":"Aerosoles",
    "wof:placetype":"venue"
},
  "geometry": {"coordinates":[-122.40523899999999,37.786491],"type":"Point"}
}