{
  "type": "Feature",
  "properties": {
    "addr:full":"3137 E 26th St Los Angeles CA 90023",
    "addr:housenumber":"3137",
    "addr:postcode":"90023",
    "addr:street":"E 26Th St",
    "iso:country":"US",
    "sg:address":"3137 E 26th St",
    "sg:city":"Los Angeles",
    "sg:classifiers":[
        {
            "category":"Manufacturing",
            "subcategory":"Tools & Machinery",
            "type":"Manufacturing & Wholesale Goods"
        }
    ],
    "sg:phone":"+1 323 266 7111",
    "sg:postcode":"90023",
    "sg:province":"CA",
    "sg:tags":[
        "product",
        "aerosol",
        "mfg"
    ],
    "sg:website":"www.fourstarchemical.com",
    "wof:name":"Four Star Chemical",
    "wof:placetype":"venue"
},
  "geometry": {"coordinates":[-118.212655,34.012728],"type":"Point"}
}