{
  "type": "Feature",
  "properties": {
    "iso:country":"US",
    "sg:address":"5045 Wilshire Blvd",
    "sg:city":"Los Angeles",
    "sg:classifiers":[
        {
            "category":"Autos & Motor Vehicles",
            "subcategory":"Automobile Sales",
            "type":"Retail Goods"
        }
    ],
    "sg:phone":"+1 323 963 7900",
    "sg:postcode":"90036",
    "sg:province":"CA",
    "sg:tags":[
        "limo"
    ],
    "wof:name":"LAX Limousine Service",
    "wof:placetype":"venue"
},
  "geometry": {"coordinates":[-118.34007,34.062162],"type":"Point"}
}