{
  "type": "Feature",
  "properties": {
    "iso:country":"US",
    "sg:address":"2025 Clement St #2",
    "sg:city":"San Francisco",
    "sg:classifiers":[
        {
            "category":"Restaurant",
            "type":"Food & Drink"
        }
    ],
    "sg:postcode":"94121",
    "sg:province":"CA",
    "wof:name":"Cosmic Shepherd's Pie",
    "wof:placetype":"venue"
},
  "geometry": {"coordinates":[-122.481022,37.781947],"type":"Point"}
}