{
  "type": "Feature",
  "properties": {
    "addr:full":"4617 Kimber Ave Bakersfield CA 93307",
    "addr:housenumber":"4617",
    "addr:postcode":"93307",
    "addr:street":"Kimber Ave",
    "iso:country":"US",
    "sg:address":"4617 Kimber Ave",
    "sg:city":"Bakersfield",
    "sg:classifiers":[
        {
            "category":"Building & Trades",
            "subcategory":"Plumbing",
            "type":"Services"
        }
    ],
    "sg:phone":"+1 661 322 0660",
    "sg:postcode":"93307",
    "sg:province":"CA",
    "sg:tags":[
        "plumbing",
        "contractor"
    ],
    "wof:name":"Sunset Mechanical",
    "wof:placetype":"venue"
},
  "geometry": {"coordinates":[-118.94981199999999,35.350445],"type":"Point"}
}