{
  "type": "Feature",
  "properties": {
    "iso:country":"US",
    "sg:address":"360 E 4th St Ste D",
    "sg:city":"Perris",
    "sg:classifiers":[
        {
            "category":"Insurance",
            "subcategory":"Hazard Insurance",
            "type":"Services"
        }
    ],
    "sg:phone":"+1 951 940 9593",
    "sg:postcode":"92570",
    "sg:province":"CA",
    "sg:tags":[
        "commercial",
        "business"
    ],
    "wof:name":"Guidance Insurance Agency",
    "wof:placetype":"venue"
},
  "geometry": {"coordinates":[-117.222587,33.782379],"type":"Point"}
}