{
  "type": "Feature",
  "properties": {
    "iso:country":"US",
    "sg:address":"2556 Cottage Way",
    "sg:city":"Sacramento",
    "sg:classifiers":[
        {
            "category":"Professional",
            "subcategory":"Management & Consulting",
            "type":"Services"
        }
    ],
    "sg:phone":"+1 916 487 8606",
    "sg:postcode":"95825",
    "sg:province":"CA",
    "sg:tags":[
        "consultant",
        "energy",
        "conservation"
    ],
    "wof:name":"Capital Resources Of Cali",
    "wof:placetype":"venue"
},
  "geometry": {"coordinates":[-121.402926,38.603366],"type":"Point"}
}