{
  "type": "Feature",
  "properties": {
    "iso:country":"US",
    "sg:address":"3250 Sage Rd",
    "sg:city":"Fallbrook",
    "sg:classifiers":[
        {
            "category":"Government",
            "subcategory":"Fire Station",
            "type":"Public Place"
        }
    ],
    "sg:phone":"+1 760 723 9408",
    "sg:postcode":"92028",
    "sg:province":"CA",
    "sg:tags":[
        "relief",
        "disaster",
        "recovery"
    ],
    "wof:name":"Seacoast Carpert Care",
    "wof:placetype":"venue"
},
  "geometry": {"coordinates":[-117.174179,33.330061],"type":"Point"}
}