{
  "type": "Feature",
  "properties": {
    "addr:full":"21484 S Colusa Ave Five Points CA 93624",
    "addr:housenumber":"21484",
    "addr:postcode":"93624",
    "addr:street":"S Colusa Ave",
    "iso:country":"US",
    "sg:address":"21484 S Colusa Ave",
    "sg:city":"Five Points",
    "sg:classifiers":[
        {
            "category":"Farming",
            "subcategory":"Farm & Veterinary Services",
            "type":"Manufacturing & Wholesale Goods"
        },
        {
            "category":"Wholesale",
            "subcategory":"Fruits & Vegetables",
            "type":"Manufacturing & Wholesale Goods"
        }
    ],
    "sg:phone":"+1 559 884 2441",
    "sg:postcode":"93624",
    "sg:province":"CA",
    "sg:tags":[
        "packing",
        "shipper",
        "plant"
    ],
    "wof:name":"Telesis Onion Co",
    "wof:placetype":"venue"
},
  "geometry": {"coordinates":[-120.19385,36.312878],"type":"Point"}
}