{
  "type": "Feature",
  "properties": {
    "iso:country":"US",
    "sg:address":"1016 Clinton St",
    "sg:city":"Napa",
    "sg:classifiers":[
        {
            "category":"Insurance",
            "subcategory":"Insurance Agent",
            "type":"Services"
        },
        {
            "category":"Insurance",
            "subcategory":"Hazard Insurance",
            "type":"Services"
        },
        {
            "category":"Insurance",
            "subcategory":"Title Insurance",
            "type":"Services"
        },
        {
            "category":"Insurance",
            "subcategory":"Life Insurance",
            "type":"Services"
        }
    ],
    "sg:phone":"+1 707 265 6565",
    "sg:postcode":"94559",
    "sg:province":"CA",
    "sg:tags":[
        "auto",
        "commercial",
        "business",
        "homeowner"
    ],
    "sg:website":"http://www.farmersagent.com/mguerrero1/",
    "wof:name":"Domingo Guerrero - Farmers Insurance",
    "wof:placetype":"venue"
},
  "geometry": {"coordinates":[-122.287324,38.301225],"type":"Point"}
}