{
  "type": "Feature",
  "properties": {
    "iso:country":"US",
    "sg:address":"10331 Stanford Ave",
    "sg:city":"Garden Grove",
    "sg:classifiers":[
        {
            "category":"Education",
            "subcategory":"School",
            "type":"Public Place"
        }
    ],
    "sg:phone":"+1 714 663 6104",
    "sg:postcode":"92840",
    "sg:province":"CA",
    "sg:tags":[
        "high",
        "middle",
        "elementary"
    ],
    "wof:name":"Anthony Elementary School",
    "wof:placetype":"venue"
},
  "geometry": {"coordinates":[-117.952003,33.777802],"type":"Point"}
}