{
  "type": "Feature",
  "properties": {
    "addr:full":"820 Capitola Rd Santa Cruz CA 95062",
    "addr:housenumber":"820",
    "addr:postcode":"95062",
    "addr:street":"Capitola Rd",
    "iso:country":"US",
    "sg:address":"820 Capitola Rd",
    "sg:city":"Santa Cruz",
    "sg:classifiers":[
        {
            "category":"Health Services",
            "subcategory":"Health Practitioner",
            "type":"Services"
        }
    ],
    "sg:phone":"+1 831 475 8885",
    "sg:postcode":"95062",
    "sg:province":"CA",
    "sg:tags":[
        "acupuncture"
    ],
    "wof:name":"Pouls Kathleen Marie Lac",
    "wof:placetype":"venue"
},
  "geometry": {"coordinates":[-121.99099699999999,36.978699],"type":"Point"}
}