{
  "type": "Feature",
  "properties": {
    "addr:full":"643 Laurel St San Carlos CA 94070",
    "addr:housenumber":"643",
    "addr:postcode":"94070",
    "addr:street":"Laurel St",
    "iso:country":"US",
    "sg:address":"643 Laurel St",
    "sg:city":"San Carlos",
    "sg:classifiers":[
        {
            "category":"Shopping",
            "subcategory":"Jewelry",
            "type":"Retail Goods"
        }
    ],
    "sg:phone":"+1 650 592 8813",
    "sg:postcode":"94070",
    "sg:province":"CA",
    "sg:tags":[
        "jeweler"
    ],
    "wof:name":"Accent On Jewelry",
    "wof:placetype":"venue"
},
  "geometry": {"coordinates":[-122.260204,37.505846],"type":"Point"}
}