{
  "type": "Feature",
  "properties": {
    "addr:full":"371 Van Ness Way Torrance CA 90501",
    "addr:housenumber":"371",
    "addr:postcode":"90501",
    "addr:street":"Van Ness Way",
    "iso:country":"US",
    "sg:address":"371 Van Ness Way",
    "sg:city":"Torrance",
    "sg:classifiers":[
        {
            "category":"Organizations",
            "subcategory":"Religious Organization",
            "type":"Services"
        }
    ],
    "sg:phone":"+1 310 328 4648",
    "sg:postcode":"90501",
    "sg:province":"CA",
    "wof:name":"Harvest Time Ministries USA",
    "wof:placetype":"venue"
},
  "geometry": {"coordinates":[-118.31891299999999,33.846286],"type":"Point"}
}