{
  "type": "Feature",
  "properties": {
    "addr:full":"1910 Walters Ct Fairfield CA 94533",
    "addr:housenumber":"1910",
    "addr:postcode":"94533",
    "addr:street":"Walters Ct",
    "iso:country":"US",
    "sg:address":"1910 Walters Ct",
    "sg:city":"Fairfield",
    "sg:classifiers":[
        {
            "category":"Retail",
            "subcategory":"Auto Rental",
            "type":"Services"
        }
    ],
    "sg:phone":"+1 707 427 1209",
    "sg:postcode":"94533",
    "sg:province":"CA",
    "sg:tags":[
        "renting",
        "truck",
        "leasing"
    ],
    "wof:name":"U-Haul Co",
    "wof:placetype":"venue"
},
  "geometry": {"coordinates":[-121.992102,38.269824],"type":"Point"}
}