{
  "type": "Feature",
  "properties": {
    "iso:country":"US",
    "sg:address":"707 3rd St",
    "sg:city":"West Sacramento",
    "sg:classifiers":[
        {
            "category":"Professional",
            "subcategory":"Management & Consulting",
            "type":"Services"
        }
    ],
    "sg:phone":"+1 916 617 1144",
    "sg:postcode":"95605",
    "sg:province":"CA",
    "wof:name":"USI Companies Inc",
    "wof:placetype":"venue"
},
  "geometry": {"coordinates":[-121.51136,38.582359],"type":"Point"}
}