{
  "type": "Feature",
  "properties": {
    "iso:country":"US",
    "sg:address":"63 Bovet Rd",
    "sg:city":"San Mateo",
    "sg:classifiers":[
        {
            "category":"Wholesale",
            "subcategory":"Stationery",
            "type":"Manufacturing & Wholesale Goods"
        }
    ],
    "sg:phone":"+1 650 345 6400",
    "sg:postcode":"94402",
    "sg:province":"CA",
    "sg:tags":[
        "cards",
        "greeting"
    ],
    "wof:name":"Comsotec Corp",
    "wof:placetype":"venue"
},
  "geometry": {"coordinates":[-122.316143,37.549903],"type":"Point"}
}