{
  "type": "Feature",
  "properties": {
    "iso:country":"US",
    "sg:address":"24621 Foresthill Rd",
    "sg:city":"Foresthill",
    "sg:classifiers":[
        {
            "category":"Organizations",
            "subcategory":"Community Association",
            "type":"Services"
        }
    ],
    "sg:phone":"+1 530 367 2273",
    "sg:postcode":"95631",
    "sg:province":"CA",
    "sg:tags":[
        "fraternal"
    ],
    "wof:name":"Covenant Lodge",
    "wof:placetype":"venue"
},
  "geometry": {"coordinates":[-120.813856,39.02099],"type":"Point"}
}