{
  "type": "Feature",
  "properties": {
    "iso:country":"US",
    "sg:address":"103 Bardin Rd",
    "sg:city":"Salinas",
    "sg:classifiers":[
        {
            "category":"Shopping",
            "subcategory":"Florist",
            "type":"Retail Goods"
        }
    ],
    "sg:phone":"+1 831 424 2926",
    "sg:postcode":"93905",
    "sg:province":"CA",
    "wof:name":"Mariposa Flowers",
    "wof:placetype":"venue"
},
  "geometry": {"coordinates":[-121.605822,36.678501],"type":"Point"}
}