{
  "type": "Feature",
  "properties": {
    "addr:full":"9046 Three Seasons Rd San Diego CA 92126",
    "addr:housenumber":"9046",
    "addr:postcode":"92126",
    "addr:street":"Three Seasons Rd",
    "iso:country":"US",
    "sg:address":"9046 Three Seasons Rd",
    "sg:city":"San Diego",
    "sg:classifiers":[
        {
            "category":"Building & Trades",
            "subcategory":"Construction",
            "type":"Services"
        }
    ],
    "sg:phone":"+1 858 549 9059",
    "sg:postcode":"92126",
    "sg:province":"CA",
    "sg:tags":[
        "siding",
        "contractor"
    ],
    "wof:name":"American Standard Siding",
    "wof:placetype":"venue"
},
  "geometry": {"coordinates":[-117.12979300000001,32.904802],"type":"Point"}
}