{
  "type": "Feature",
  "properties": {
    "addr:full":"240 Tennessee St Vallejo CA 94590",
    "addr:housenumber":"240",
    "addr:postcode":"94590",
    "addr:street":"Tennessee St",
    "iso:country":"US",
    "sg:address":"240 Tennessee St",
    "sg:city":"Vallejo",
    "sg:classifiers":[
        {
            "category":"Banks & Credit Unions",
            "subcategory":"Bank",
            "type":"Services"
        }
    ],
    "sg:phone":"+1 707 648 2825",
    "sg:postcode":"94590",
    "sg:province":"CA",
    "sg:tags":[
        "cashing",
        "check"
    ],
    "wof:name":"Cash & Go",
    "wof:placetype":"venue"
},
  "geometry": {"coordinates":[-122.259055,38.110064],"type":"Point"}
}