{
  "type": "Feature",
  "properties": {
    "iso:country":"US",
    "sg:address":"1855 1st Ave",
    "sg:city":"San Diego",
    "sg:classifiers":[
        {
            "category":"Professional",
            "subcategory":"Lawyer & Legal Services",
            "type":"Services"
        }
    ],
    "sg:phone":"+1 619 233 1779",
    "sg:postcode":"92101",
    "sg:province":"CA",
    "sg:tags":[
        "attorney"
    ],
    "wof:name":"Sean E O'Keefe",
    "wof:placetype":"venue"
},
  "geometry": {"coordinates":[-117.163809,32.724525],"type":"Point"}
}