{
  "type": "Feature",
  "properties": {
    "addr:full":"5050 Ave Encinas Carlsbad CA 92008",
    "addr:housenumber":"5050",
    "addr:postcode":"92008",
    "addr:street":"Ave Encinas",
    "iso:country":"US",
    "sg:address":"5050 Ave Encinas",
    "sg:city":"Carlsbad",
    "sg:classifiers":[
        {
            "category":"Professional",
            "subcategory":"Computer Services",
            "type":"Services"
        }
    ],
    "sg:phone":"+1 760 930 0075",
    "sg:postcode":"92008",
    "sg:province":"CA",
    "sg:tags":[
        "consultant",
        "designer"
    ],
    "sg:website":"www.interknowlogy.com",
    "wof:name":"Interknowlogy",
    "wof:placetype":"venue"
},
  "geometry": {"coordinates":[-117.329092,33.13105],"type":"Point"}
}