{
  "type": "Feature",
  "properties": {
    "iso:country":"US",
    "sg:address":"9274 Franklin Blvd",
    "sg:city":"Elk Grove",
    "sg:classifiers":[
        {
            "category":"Utilities",
            "type":"Services"
        }
    ],
    "sg:phone":"+1 916 834 8591",
    "sg:postcode":"95758",
    "sg:province":"CA",
    "sg:tags":[
        "sanitary"
    ],
    "wof:name":"Aces Sweeping Service",
    "wof:placetype":"venue"
},
  "geometry": {"coordinates":[-121.448515,38.420198],"type":"Point"}
}