{
  "type": "Feature",
  "properties": {
    "iso:country":"US",
    "sg:address":"26901 Hansen Rd",
    "sg:city":"Tracy",
    "sg:classifiers":[
        {
            "category":"Wholesale",
            "subcategory":"Construction Materials",
            "type":"Manufacturing & Wholesale Goods"
        }
    ],
    "sg:phone":"+1 209 836 3125",
    "sg:postcode":"95377",
    "sg:province":"CA",
    "sg:tags":[
        "concrete",
        "product"
    ],
    "sg:website":"www.eprecast.com/index.php",
    "wof:name":"Concrete Products Inc",
    "wof:placetype":"venue"
},
  "geometry": {"coordinates":[-121.51309999999999,37.709607],"type":"Point"}
}