{
  "type": "Feature",
  "properties": {
    "iso:country":"US",
    "sg:address":"4025 W El Segundo Boulevard",
    "sg:city":"Hawthorne",
    "sg:classifiers":[
        {
            "category":"Fast Food",
            "type":"Food & Drink"
        },
        {
            "category":"Restaurant",
            "type":"Food & Drink"
        }
    ],
    "sg:phone":"+1 310 676 3707",
    "sg:postcode":"90250",
    "sg:province":"CA",
    "sg:tags":[
        "take"
    ],
    "wof:name":"Jim's Burgers",
    "wof:placetype":"venue"
},
  "geometry": {"coordinates":[-118.344177,33.916353],"type":"Point"}
}