{
  "type": "Feature",
  "properties": {
    "iso:country":"US",
    "sg:address":"3300 Veda St",
    "sg:city":"Redding",
    "sg:classifiers":[
        {
            "category":"Social Services",
            "type":"Services"
        }
    ],
    "sg:phone":"+1 530 242 1492",
    "sg:postcode":"96001",
    "sg:province":"CA",
    "sg:tags":[
        "organization",
        "welfare"
    ],
    "wof:name":"Faithworks",
    "wof:placetype":"venue"
},
  "geometry": {"coordinates":[-122.389061,40.566402],"type":"Point"}
}