{
  "type": "Feature",
  "properties": {
    "iso:country":"US",
    "sg:address":"340 9th St",
    "sg:city":"Oakland",
    "sg:classifiers":[
        {
            "category":"Shopping",
            "subcategory":"Mobile Phones",
            "type":"Retail Goods"
        }
    ],
    "sg:phone":"+1 510 251 1688",
    "sg:postcode":"94607",
    "sg:province":"CA",
    "wof:name":"Infinitel Communications",
    "wof:placetype":"venue"
},
  "geometry": {"coordinates":[-122.271004,37.7999],"type":"Point"}
}