{
  "type": "Feature",
  "properties": {
    "addr:full":"316 N Corona Ave Ontario CA 91764",
    "addr:housenumber":"316",
    "addr:postcode":"91764",
    "addr:street":"N Corona Ave",
    "iso:country":"US",
    "sg:address":"316 N Corona Ave",
    "sg:city":"Ontario",
    "sg:classifiers":[
        {
            "category":"Wholesale",
            "subcategory":"Non-durable Goods",
            "type":"Manufacturing & Wholesale Goods"
        }
    ],
    "sg:phone":"+1 909 937 6420",
    "sg:postcode":"91764",
    "sg:province":"CA",
    "sg:tags":[
        "novelty"
    ],
    "wof:name":"Martin Industries-Light Sticks",
    "wof:placetype":"venue"
},
  "geometry": {"coordinates":[-117.613343,34.066873],"type":"Point"}
}