{
  "type": "Feature",
  "properties": {
    "addr:full":"1566 32nd Ave San Francisco CA 94122",
    "addr:housenumber":"1566",
    "addr:postcode":"94122",
    "addr:street":"32Nd Ave",
    "iso:country":"US",
    "sg:address":"1566 32nd Ave",
    "sg:city":"San Francisco",
    "sg:classifiers":[
        {
            "category":"Education",
            "subcategory":"Preschool",
            "type":"Public Place"
        }
    ],
    "sg:postcode":"94122",
    "sg:province":"CA",
    "sg:website":"www.sfmontessoriacademy.com",
    "wof:name":"San Francisco Montessori Academy",
    "wof:placetype":"venue"
},
  "geometry": {"coordinates":[-122.490379,37.757991],"type":"Point"}
}