{
  "type": "Feature",
  "properties": {
    "iso:country":"US",
    "sg:address":"13538 Imperial Hwy",
    "sg:city":"Santa Fe Springs",
    "sg:classifiers":[
        {
            "category":"Restaurant",
            "type":"Food & Drink"
        }
    ],
    "sg:phone":"+1 562 404 0527",
    "sg:postcode":"90670",
    "sg:province":"CA",
    "sg:tags":[
        "out"
    ],
    "wof:name":"Paloma Mexican Foods Corp",
    "wof:placetype":"venue"
},
  "geometry": {"coordinates":[-118.04297699999999,33.916884],"type":"Point"}
}