{
  "type": "Feature",
  "properties": {
    "addr:full":"6919 Jennings Rd Modesto CA 95358",
    "addr:housenumber":"6919",
    "addr:postcode":"ca 95358",
    "addr:street":"Jennings Rd",
    "iso:country":"US",
    "sg:address":"6919 Jennings Rd",
    "sg:city":"Modesto",
    "sg:classifiers":[
        {
            "category":"Utilities",
            "subcategory":"Fuel Oil & Lpg",
            "type":"Services"
        }
    ],
    "sg:phone":"+1 209 537 7056",
    "sg:postcode":"95358",
    "sg:province":"CA",
    "sg:tags":[
        "firewood"
    ],
    "wof:name":"Zwar's Firewood Svc",
    "wof:placetype":"venue"
},
  "geometry": {"coordinates":[-121.06740000000001,37.52294],"type":"Point"}
}