{
  "type": "Feature",
  "properties": {
    "addr:full":"21761 Martin St Perris CA 92570",
    "addr:housenumber":"21761",
    "addr:postcode":"92570",
    "addr:street":"Martin St",
    "iso:country":"US",
    "sg:address":"21761 Martin St",
    "sg:city":"Perris",
    "sg:classifiers":[
        {
            "category":"Building & Trades",
            "subcategory":"Landscaping Services",
            "type":"Services"
        }
    ],
    "sg:phone":"+1 951 657 9042",
    "sg:postcode":"92570",
    "sg:province":"CA",
    "sg:tags":[
        "landscape"
    ],
    "wof:name":"Emiliano S Landscaping",
    "wof:placetype":"venue"
},
  "geometry": {"coordinates":[-117.278991,33.844539],"type":"Point"}
}