{
  "type": "Feature",
  "properties": {
    "iso:country":"US",
    "sg:address":"14840 Waverly Downs Way",
    "sg:city":"San Diego",
    "sg:classifiers":[
        {
            "category":"Education",
            "subcategory":"School",
            "type":"Public Place"
        }
    ],
    "sg:phone":"+1 858 674 4707",
    "sg:postcode":"92128",
    "sg:province":"CA",
    "wof:name":"Highland Ranch Elementary Schl",
    "wof:placetype":"venue"
},
  "geometry": {"coordinates":[-117.071185,32.984322],"type":"Point"}
}