{
  "type": "Feature",
  "properties": {
    "iso:country":"US",
    "sg:address":"1205 Filbert St",
    "sg:city":"Richmond",
    "sg:classifiers":[
        {
            "category":"Wholesale",
            "subcategory":"Fruits & Vegetables",
            "type":"Manufacturing & Wholesale Goods"
        }
    ],
    "sg:phone":"+1 510 233 3480",
    "sg:postcode":"94801",
    "sg:province":"CA",
    "sg:tags":[
        "veggie"
    ],
    "wof:name":"Mom's & Pop's",
    "wof:placetype":"venue"
},
  "geometry": {"coordinates":[-122.366997,37.9506],"type":"Point"}
}