{
  "type": "Feature",
  "properties": {
    "addr:full":"119 W 51st St Long Beach CA 90805",
    "addr:housenumber":"119",
    "addr:postcode":"90805",
    "addr:street":"W 51St St",
    "iso:country":"US",
    "sg:address":"119 W 51st St",
    "sg:city":"Long Beach",
    "sg:classifiers":[
        {
            "category":"Health Services",
            "subcategory":"Nursing And Care Facility",
            "type":"Services"
        }
    ],
    "sg:phone":"+1 562 423 9216",
    "sg:postcode":"90805",
    "sg:province":"CA",
    "sg:tags":[
        "home",
        "rest"
    ],
    "wof:name":"Gemini Board & Care",
    "wof:placetype":"venue"
},
  "geometry": {"coordinates":[-118.200774,33.848835],"type":"Point"}
}