{
  "type": "Feature",
  "properties": {
    "iso:country":"US",
    "sg:address":"12889 San Pablo Ave",
    "sg:city":"Richmond",
    "sg:classifiers":[
        {
            "category":"Restaurant",
            "type":"Food & Drink"
        }
    ],
    "sg:phone":"+1 510 237 1996",
    "sg:postcode":"94808",
    "sg:province":"CA",
    "sg:tags":[
        "barbeque"
    ],
    "wof:name":"Pit Boss Barbeque",
    "wof:placetype":"venue"
},
  "geometry": {"coordinates":[-122.33062200000001,37.946986],"type":"Point"}
}