{
  "type": "Feature",
  "properties": {
    "addr:full":"8085 State Rte 49 Mokelumne Hill CA 95245",
    "addr:housenumber":"8085",
    "addr:postcode":"95245",
    "addr:street":"State Rte 49",
    "iso:country":"US",
    "sg:address":"8085 State Rte 49",
    "sg:city":"Mokelumne Hill",
    "sg:classifiers":[
        {
            "category":"Professional",
            "type":"Services"
        },
        {
            "category":"Personal",
            "subcategory":"Beauty Salon",
            "type":"Services"
        }
    ],
    "sg:phone":"+1 209 286 1128",
    "sg:postcode":"95245",
    "sg:province":"CA",
    "wof:name":"Family Treasures",
    "wof:placetype":"venue"
},
  "geometry": {"coordinates":[-120.705718,38.298522],"type":"Point"}
}