{
  "type": "Feature",
  "properties": {
    "addr:full":"30401 Andreen Rd Valley Center CA 92082",
    "addr:housenumber":"30401",
    "addr:postcode":"92082",
    "addr:street":"Andreen Rd",
    "iso:country":"US",
    "sg:address":"30401 Andreen Rd",
    "sg:city":"Valley Center",
    "sg:classifiers":[
        {
            "category":"Building & Trades",
            "subcategory":"Construction",
            "type":"Services"
        }
    ],
    "sg:phone":"+1 760 749 2296",
    "sg:postcode":"92082",
    "sg:province":"CA",
    "sg:tags":[
        "house"
    ],
    "wof:name":"Guzman Lndscp Const",
    "wof:placetype":"venue"
},
  "geometry": {"coordinates":[-117.111166,33.260196],"type":"Point"}
}