{
  "type": "Feature",
  "properties": {
    "iso:country":"US",
    "sg:address":"17472 Ventura Blvd",
    "sg:city":"Encino",
    "sg:classifiers":[
        {
            "category":"Home & Garden",
            "subcategory":"Carpets & Floor Coverings",
            "type":"Retail Goods"
        }
    ],
    "sg:phone":"+1 818 995 6566",
    "sg:postcode":"91316",
    "sg:province":"CA",
    "sg:tags":[
        "dealer",
        "rug"
    ],
    "wof:name":"Carpet Concourse Design",
    "wof:placetype":"venue"
},
  "geometry": {"coordinates":[-118.512592,34.161141],"type":"Point"}
}