{
  "type": "Feature",
  "properties": {
    "iso:country":"US",
    "sg:address":"2634 Abedul St",
    "sg:city":"Carlsbad",
    "sg:classifiers":[
        {
            "category":"Home & Garden",
            "subcategory":"Household Appliances",
            "type":"Retail Goods"
        }
    ],
    "sg:phone":"+1 760 436 2838",
    "sg:postcode":"92009",
    "sg:province":"CA",
    "wof:name":"Bob's Appliance Svc",
    "wof:placetype":"venue"
},
  "geometry": {"coordinates":[-117.24705899999999,33.10806],"type":"Point"}
}