{
  "type": "Feature",
  "properties": {
    "iso:country":"US",
    "sg:address":"4190 Truxel Rd",
    "sg:city":"Sacramento",
    "sg:classifiers":[
        {
            "category":"Real Estate",
            "subcategory":"Real Estate Services",
            "type":"Services"
        }
    ],
    "sg:phone":"+1 916 515 2200",
    "sg:postcode":"95834",
    "sg:province":"CA",
    "sg:tags":[
        "company",
        "title"
    ],
    "wof:name":"Alliance Title Co",
    "wof:placetype":"venue"
},
  "geometry": {"coordinates":[-121.509864,38.650101],"type":"Point"}
}