{
  "type": "Feature",
  "properties": {
    "iso:country":"US",
    "sg:address":"2239 Mira Vista Drive",
    "sg:city":"El Cerrito",
    "sg:classifiers":[
        {
            "category":"Winery",
            "type":"Food & Drink"
        },
        {
            "category":"Professional",
            "type":"Services"
        },
        {
            "category":"Personal",
            "type":"Services"
        },
        {
            "category":"Food & Beverages",
            "subcategory":"Liquor & Beverages",
            "type":"Retail Goods"
        }
    ],
    "sg:phone":"+1 510 778 8255",
    "sg:postcode":"94530",
    "sg:province":"CA",
    "sg:tags":[
        "spirit",
        "beer",
        "planning",
        "caterer",
        "party",
        "event",
        "wine"
    ],
    "sg:website":"www.tastefirst.com",
    "wof:name":"Taste First",
    "wof:placetype":"venue"
},
  "geometry": {"coordinates":[-122.31315600000001,37.930951],"type":"Point"}
}