{
  "type": "Feature",
  "properties": {
    "iso:country":"US",
    "sg:address":"500 Golden Gate Ave",
    "sg:city":"San Francisco",
    "sg:classifiers":[
        {
            "category":"Banks & Credit Unions",
            "subcategory":"Bank",
            "type":"Services"
        }
    ],
    "sg:phone":"+1 800 241 5626",
    "sg:postcode":"94102",
    "sg:province":"CA",
    "sg:website":"www.golden1.com",
    "wof:name":"The Golden 1 Credit Union",
    "wof:placetype":"venue"
},
  "geometry": {"coordinates":[-122.418999,37.7813],"type":"Point"}
}