{
  "type": "Feature",
  "properties": {
    "iso:country":"US",
    "sg:address":"1900 N 1st St",
    "sg:city":"Dixon",
    "sg:classifiers":[
        {
            "category":"Wholesale",
            "subcategory":"Petroleum",
            "type":"Manufacturing & Wholesale Goods"
        }
    ],
    "sg:phone":"+1 707 678 2061",
    "sg:postcode":"95620",
    "sg:province":"CA",
    "sg:tags":[
        "bulk",
        "oil",
        "gasoline"
    ],
    "wof:name":"Ramos Oil",
    "wof:placetype":"venue"
},
  "geometry": {"coordinates":[-121.82221800000001,38.464776],"type":"Point"}
}