{
  "type": "Feature",
  "properties": {
    "addr:full":"6514 Lonetree Blvd Ste 100 Rocklin CA 95765",
    "addr:housenumber":"6514",
    "addr:postcode":"95765",
    "addr:street":"Lonetree Blvd Ste 100",
    "iso:country":"US",
    "sg:address":"6514 Lonetree Blvd Ste 100",
    "sg:city":"Rocklin",
    "sg:classifiers":[
        {
            "category":"Health Services",
            "subcategory":"Doctor",
            "type":"Services"
        },
        {
            "category":"Health Services",
            "subcategory":"Dentist",
            "type":"Services"
        }
    ],
    "sg:phone":"+1 916 797 2700",
    "sg:postcode":"95765",
    "sg:province":"CA",
    "sg:tags":[
        "dentists-oral",
        "physician",
        "maxillofacial",
        "dental",
        "surgeons",
        "dentists-orthodontists",
        "clinic",
        "surgeon",
        "dentistry",
        "implant",
        "oral",
        "surgery",
        "dentists-implantology"
    ],
    "sg:website":"http://www.kingoralsurgery.com",
    "wof:name":"King Oral & Maxillofacial Surgery Center",
    "wof:placetype":"venue"
},
  "geometry": {"coordinates":[-121.293542,38.805002],"type":"Point"}
}