{
  "type": "Feature",
  "properties": {
    "addr:full":"636 N Main St Bishop CA 93514",
    "addr:housenumber":"636",
    "addr:postcode":"93514",
    "addr:street":"N Main St",
    "iso:country":"US",
    "sg:address":"636 N Main St",
    "sg:city":"Bishop",
    "sg:classifiers":[
        {
            "category":"Travel",
            "subcategory":"Hotels & Motels",
            "type":"Entertainment"
        }
    ],
    "sg:phone":"+1 760 872 2423",
    "sg:postcode":"93514",
    "sg:province":"CA",
    "sg:website":"www.holidayinnbishop.com",
    "wof:name":"Holiday Inn Express Bishop",
    "wof:placetype":"venue"
},
  "geometry": {"coordinates":[-118.395268,37.366132],"type":"Point"}
}