{
  "type": "Feature",
  "properties": {
    "iso:country":"US",
    "sg:address":"10300 International Blvd",
    "sg:city":"Oakland",
    "sg:classifiers":[
        {
            "category":"Retail",
            "subcategory":"Auto Repair",
            "type":"Services"
        }
    ],
    "sg:phone":"+1 510 636 8530",
    "sg:postcode":"94603",
    "sg:province":"CA",
    "sg:tags":[
        "muffler",
        "exhaust",
        "system"
    ],
    "wof:name":"R T Custom Exhaust & Svc Ctr",
    "wof:placetype":"venue"
},
  "geometry": {"coordinates":[-122.167519,37.740467],"type":"Point"}
}