{
  "type": "Feature",
  "properties": {
    "iso:country":"US",
    "sg:address":"15425 Eiffel Cir",
    "sg:city":"Irvine",
    "sg:classifiers":[
        {
            "category":"Manufacturing",
            "subcategory":"Jewelry",
            "type":"Manufacturing & Wholesale Goods"
        }
    ],
    "sg:phone":"+1 949 294 2079",
    "sg:postcode":"92604",
    "sg:province":"CA",
    "sg:tags":[
        "material",
        "mfg"
    ],
    "wof:name":"Sherrys Intriguing Designs",
    "wof:placetype":"venue"
},
  "geometry": {"coordinates":[-117.78207500000001,33.683272],"type":"Point"}
}