{
  "type": "Feature",
  "properties": {
    "addr:full":"308 W Line St Bishop CA 93514",
    "addr:housenumber":"308",
    "addr:postcode":"93514",
    "addr:street":"W Line St",
    "iso:country":"US",
    "sg:address":"308 W Line St",
    "sg:city":"Bishop",
    "sg:classifiers":[
        {
            "category":"Professional",
            "subcategory":"Lawyer & Legal Services",
            "type":"Services"
        }
    ],
    "sg:phone":"+1 760 872 8226",
    "sg:postcode":"93514",
    "sg:province":"CA",
    "sg:tags":[
        "practice",
        "attorney",
        "criminal",
        "law"
    ],
    "wof:name":"Law Offices Of Corpora, Elizabeth",
    "wof:placetype":"venue"
},
  "geometry": {"coordinates":[-118.39639099999999,37.3614],"type":"Point"}
}