{
  "type": "Feature",
  "properties": {
    "addr:full":"302 Bryant St Palo Alto CA 94301",
    "addr:housenumber":"302",
    "addr:postcode":"94301",
    "addr:street":"Bryant St",
    "iso:country":"US",
    "sg:address":"302 Bryant St",
    "sg:city":"Palo Alto",
    "sg:classifiers":[
        {
            "category":"Real Estate",
            "subcategory":"Architect",
            "type":"Services"
        }
    ],
    "sg:phone":"+1 650 331 7264",
    "sg:postcode":"94301",
    "sg:province":"CA",
    "sg:tags":[
        "home",
        "planning",
        "design"
    ],
    "wof:name":"Pavlovic Gordana & Assoc",
    "wof:placetype":"venue"
},
  "geometry": {"coordinates":[-122.163358,37.446919],"type":"Point"}
}