{
  "type": "Feature",
  "properties": {
    "iso:country":"US",
    "sg:address":"1388 Court St Suite G",
    "sg:city":"Redding",
    "sg:classifiers":[
        {
            "category":"Professional",
            "type":"Services"
        },
        {
            "category":"Professional",
            "subcategory":"Lawyer & Legal Services",
            "type":"Services"
        },
        {
            "category":"Organizations",
            "subcategory":"Professional Association",
            "type":"Services"
        }
    ],
    "sg:phone":"+1 530 244 4610",
    "sg:postcode":"96001",
    "sg:province":"CA",
    "sg:tags":[
        "attorney",
        "document",
        "form",
        "family",
        "divorce",
        "assistance",
        "mediation",
        "paralegal",
        "plan",
        "law"
    ],
    "sg:website":"http://www.arrowsmithlegal.com",
    "wof:name":"Arrowsmith Legal Services",
    "wof:placetype":"venue"
},
  "geometry": {"coordinates":[-122.396191,40.584245],"type":"Point"}
}