{
  "type": "Feature",
  "properties": {
    "addr:full":"27 Northwinds Aliso Viejo CA 92656",
    "addr:housenumber":"27",
    "addr:postcode":"92656",
    "addr:street":"Northwinds",
    "iso:country":"US",
    "sg:address":"27 Northwinds",
    "sg:city":"Aliso Viejo",
    "sg:classifiers":[
        {
            "category":"Home & Garden",
            "subcategory":"Building Materials",
            "type":"Retail Goods"
        }
    ],
    "sg:phone":"+1 949 362 8208",
    "sg:postcode":"92656",
    "sg:province":"CA",
    "wof:name":"West Enterprises",
    "wof:placetype":"venue"
},
  "geometry": {"coordinates":[-117.737225,33.594408],"type":"Point"}
}