{
  "type": "Feature",
  "properties": {
    "iso:country":"US",
    "sg:address":"16565 Juniper St",
    "sg:city":"Hesperia",
    "sg:classifiers":[
        {
            "category":"Autos & Motor Vehicles",
            "subcategory":"Auto Supplies",
            "type":"Retail Goods"
        }
    ],
    "sg:phone":"+1 760 947 7817",
    "sg:postcode":"92345",
    "sg:province":"CA",
    "sg:tags":[
        "tire"
    ],
    "wof:name":"Alvarez Tire Service",
    "wof:placetype":"venue"
},
  "geometry": {"coordinates":[-117.30236600000001,34.423529],"type":"Point"}
}