{
  "type": "Feature",
  "properties": {
    "iso:country":"US",
    "sg:address":"1300 Dove St",
    "sg:city":"Newport Beach",
    "sg:classifiers":[
        {
            "category":"Building & Trades",
            "subcategory":"Construction",
            "type":"Services"
        }
    ],
    "sg:phone":"+1 949 660 7200",
    "sg:postcode":"92660",
    "sg:province":"CA",
    "sg:tags":[
        "painter"
    ],
    "wof:name":"United Maintenance & Painting",
    "wof:placetype":"venue"
},
  "geometry": {"coordinates":[-117.865785,33.663449],"type":"Point"}
}