{
  "type": "Feature",
  "properties": {
    "addr:full":"500 Arguello St Redwood City CA 94063",
    "addr:housenumber":"500",
    "addr:postcode":"94063",
    "addr:street":"Arguello St",
    "iso:country":"US",
    "sg:address":"500 Arguello St",
    "sg:city":"Redwood City",
    "sg:classifiers":[
        {
            "category":"Professional",
            "subcategory":"Lawyer & Legal Services",
            "type":"Services"
        }
    ],
    "sg:phone":"+1 650 839 5070",
    "sg:postcode":"94063",
    "sg:province":"CA",
    "sg:tags":[
        "attorney"
    ],
    "sg:website":"www.fr.com",
    "wof:name":"Fish & Richardson",
    "wof:placetype":"venue"
},
  "geometry": {"coordinates":[-122.233869,37.487576],"type":"Point"}
}