{
  "type": "Feature",
  "properties": {
    "iso:country":"US",
    "sg:address":"1460 1st St",
    "sg:city":"Napa",
    "sg:classifiers":[
        {
            "category":"Shopping",
            "subcategory":"Clothing, Apparel, & Fashions",
            "type":"Retail Goods"
        }
    ],
    "sg:phone":"+1 707 226 5965",
    "sg:postcode":"94559",
    "sg:province":"CA",
    "sg:tags":[
        "baby",
        "accessory"
    ],
    "wof:name":"Cribs & Bibs",
    "wof:placetype":"venue"
},
  "geometry": {"coordinates":[-122.288881,38.297612],"type":"Point"}
}