{
  "type": "Feature",
  "properties": {
    "iso:country":"US",
    "sg:address":"18299 Mount Baldy Cir",
    "sg:city":"Fountain Valley",
    "sg:classifiers":[
        {
            "category":"Home & Garden",
            "subcategory":"Carpets & Floor Coverings",
            "type":"Retail Goods"
        }
    ],
    "sg:phone":"+1 714 378 9300",
    "sg:postcode":"92708",
    "sg:province":"CA",
    "sg:tags":[
        "flooring"
    ],
    "wof:name":"A & B Floor Covering",
    "wof:placetype":"venue"
},
  "geometry": {"coordinates":[-117.93699599999999,33.698101],"type":"Point"}
}