{
  "type": "Feature",
  "properties": {
    "iso:country":"US",
    "sg:address":"3309 S Mooney Blvd",
    "sg:city":"Visalia",
    "sg:classifiers":[
        {
            "category":"Shopping",
            "subcategory":"Stationery & Office Supplies",
            "type":"Retail Goods"
        },
        {
            "category":"Food & Beverages",
            "subcategory":"Candy",
            "type":"Retail Goods"
        },
        {
            "category":"Shopping",
            "subcategory":"Party Supplies",
            "type":"Retail Goods"
        },
        {
            "category":"Shopping",
            "subcategory":"Gifts & Souvenirs",
            "type":"Retail Goods"
        },
        {
            "category":"Shopping",
            "subcategory":"Florist",
            "type":"Retail Goods"
        }
    ],
    "sg:phone":"+1 559 635 1787",
    "sg:postcode":"93277",
    "sg:province":"CA",
    "sg:tags":[
        "shop",
        "confectionery",
        "store",
        "wedding"
    ],
    "wof:name":"Green Goddess",
    "wof:placetype":"venue"
},
  "geometry": {"coordinates":[-119.31377999999999,36.301293],"type":"Point"}
}