{
  "type": "Feature",
  "properties": {
    "addr:full":"3239 Chicago Ave Riverside CA 92507",
    "addr:housenumber":"3239",
    "addr:postcode":"92507",
    "addr:street":"Chicago Ave",
    "iso:country":"US",
    "sg:address":"3239 Chicago Ave",
    "sg:city":"Riverside",
    "sg:classifiers":[
        {
            "category":"Insurance",
            "subcategory":"Insurance Agent",
            "type":"Services"
        }
    ],
    "sg:phone":"+1 951 684 8450",
    "sg:postcode":"92507",
    "sg:province":"CA",
    "wof:name":"State Farm Insurance",
    "wof:placetype":"venue"
},
  "geometry": {"coordinates":[-117.348524,33.986121],"type":"Point"}
}