{
  "type": "Feature",
  "properties": {
    "iso:country":"US",
    "sg:address":"26557 State Highway 18",
    "sg:city":"Rimforest",
    "sg:classifiers":[
        {
            "category":"Wholesale",
            "subcategory":"Home Furnishings",
            "type":"Manufacturing & Wholesale Goods"
        },
        {
            "category":"Home & Garden",
            "subcategory":"Carpets & Floor Coverings",
            "type":"Retail Goods"
        }
    ],
    "sg:phone":"+1 909 337 8300",
    "sg:postcode":"92378",
    "sg:province":"CA",
    "sg:tags":[
        "blind",
        "shade",
        "carpeting"
    ],
    "wof:name":"Mountain Home Carpet Center",
    "wof:placetype":"venue"
},
  "geometry": {"coordinates":[-117.22418500000001,34.229643],"type":"Point"}
}