{
  "type": "Feature",
  "properties": {
    "addr:full":"583 Glenburry Way San Jose CA 95123",
    "addr:housenumber":"583",
    "addr:postcode":"95123",
    "addr:street":"Glenburry Way",
    "iso:country":"US",
    "sg:address":"583 Glenburry Way",
    "sg:city":"San Jose",
    "sg:classifiers":[
        {
            "category":"Professional",
            "subcategory":"Computer Services",
            "type":"Services"
        }
    ],
    "sg:phone":"+1 408 281 8532",
    "sg:postcode":"95123",
    "sg:province":"CA",
    "sg:tags":[
        "hardware",
        "provider",
        "internet",
        "software"
    ],
    "wof:name":"Result Marketing Ctr",
    "wof:placetype":"venue"
},
  "geometry": {"coordinates":[-121.846698,37.253743],"type":"Point"}
}