{
  "type": "Feature",
  "properties": {
    "iso:country":"US",
    "sg:address":"14041 Slover Ave",
    "sg:city":"Fontana",
    "sg:classifiers":[
        {
            "category":"Wholesale",
            "subcategory":"Construction Materials",
            "type":"Manufacturing & Wholesale Goods"
        }
    ],
    "sg:phone":"+1 909 356 1263",
    "sg:postcode":"92337",
    "sg:province":"CA",
    "sg:tags":[
        "pallet",
        "skid"
    ],
    "wof:name":"Pallet Market",
    "wof:placetype":"venue"
},
  "geometry": {"coordinates":[-117.49990200000001,34.062832],"type":"Point"}
}