{
  "type": "Feature",
  "properties": {
    "addr:full":"1624 Coconut Ln El Cajon CA 92021",
    "addr:housenumber":"1624",
    "addr:postcode":"92021",
    "addr:street":"Coconut Ln",
    "iso:country":"US",
    "sg:address":"1624 Coconut Ln",
    "sg:city":"El Cajon",
    "sg:classifiers":[
        {
            "category":"Banks & Credit Unions",
            "subcategory":"Financial Services",
            "type":"Services"
        }
    ],
    "sg:phone":"+1 619 444 1492",
    "sg:postcode":"92021",
    "sg:province":"CA",
    "sg:tags":[
        "trust",
        "management"
    ],
    "wof:name":"Landes Family Trust",
    "wof:placetype":"venue"
},
  "geometry": {"coordinates":[-116.92667,32.82049],"type":"Point"}
}