{
  "type": "Feature",
  "properties": {
    "addr:full":"12717 Bentley St Waterford CA 95386",
    "addr:housenumber":"12717",
    "addr:postcode":"95386",
    "addr:street":"Bentley St",
    "iso:country":"US",
    "sg:address":"12717 Bentley St",
    "sg:city":"Waterford",
    "sg:classifiers":[
        {
            "category":"Professional",
            "subcategory":"Computer Services",
            "type":"Services"
        }
    ],
    "sg:phone":"+1 209 874 9964",
    "sg:postcode":"95386",
    "sg:province":"CA",
    "sg:tags":[
        "repair"
    ],
    "wof:name":"Integrity Computers",
    "wof:placetype":"venue"
},
  "geometry": {"coordinates":[-120.760107,37.641445],"type":"Point"}
}