{
  "type": "Feature",
  "properties": {
    "iso:country":"US",
    "sg:address":"2400 S P St",
    "sg:city":"Bakersfield",
    "sg:classifiers":[
        {
            "category":"Organizations",
            "subcategory":"Religious Organization",
            "type":"Services"
        }
    ],
    "sg:phone":"+1 661 397 8651",
    "sg:postcode":"93304",
    "sg:province":"CA",
    "sg:tags":[
        "church"
    ],
    "wof:name":"Sikh Temple",
    "wof:placetype":"venue"
},
  "geometry": {"coordinates":[-119.011879,35.332192],"type":"Point"}
}