{
  "type": "Feature",
  "properties": {
    "addr:full":"5408 Walnut Ave Irvine CA 92604",
    "addr:housenumber":"5408",
    "addr:postcode":"92604",
    "addr:street":"Walnut Ave",
    "iso:country":"US",
    "sg:address":"5408 Walnut Ave",
    "sg:city":"Irvine",
    "sg:classifiers":[
        {
            "category":"Health Services",
            "subcategory":"Doctor",
            "type":"Services"
        }
    ],
    "sg:phone":"+1 949 653 2849",
    "sg:postcode":"92604",
    "sg:province":"CA",
    "wof:name":"Ga Ju Soon DO",
    "wof:placetype":"venue"
},
  "geometry": {"coordinates":[-117.772003,33.689602],"type":"Point"}
}