{
  "type": "Feature",
  "properties": {
    "addr:full":"652 Buchanan St Davis CA 95616",
    "addr:housenumber":"652",
    "addr:postcode":"95616",
    "addr:street":"Buchanan St",
    "iso:country":"US",
    "sg:address":"652 Buchanan St",
    "sg:city":"Davis",
    "sg:classifiers":[
        {
            "category":"Organizations",
            "subcategory":"Religious Organization",
            "type":"Services"
        }
    ],
    "sg:phone":"+1 530 758 6140",
    "sg:postcode":"95616",
    "sg:province":"CA",
    "wof:name":"Gideons International",
    "wof:placetype":"venue"
},
  "geometry": {"coordinates":[-121.77134,38.547934],"type":"Point"}
}