{
  "type": "Feature",
  "properties": {
    "addr:full":"645 W Pine Ave El Segundo CA 90245",
    "addr:housenumber":"645",
    "addr:postcode":"90245",
    "addr:street":"W Pine Ave",
    "iso:country":"US",
    "sg:address":"645 W Pine Ave",
    "sg:city":"El Segundo",
    "sg:classifiers":[
        {
            "category":"Wholesale",
            "subcategory":"Sporting Goods",
            "type":"Manufacturing & Wholesale Goods"
        }
    ],
    "sg:phone":"+1 310 615 0787",
    "sg:postcode":"90245",
    "sg:province":"CA",
    "wof:name":"Quick Fin Release",
    "wof:placetype":"venue"
},
  "geometry": {"coordinates":[-118.42367400000001,33.922281],"type":"Point"}
}