{
  "type": "Feature",
  "properties": {
    "iso:country":"US",
    "sg:address":"5010 Geary Blvd",
    "sg:city":"San Francisco",
    "sg:classifiers":[
        {
            "category":"Banks & Credit Unions",
            "subcategory":"Investment Brokerage",
            "type":"Services"
        }
    ],
    "sg:phone":"+1 415 387 0500",
    "sg:postcode":"94118",
    "sg:province":"CA",
    "sg:tags":[
        "consultant",
        "planning",
        "financial"
    ],
    "wof:name":"Larry J Anderson",
    "wof:placetype":"venue"
},
  "geometry": {"coordinates":[-122.473951,37.780693],"type":"Point"}
}