{
  "type": "Feature",
  "properties": {
    "iso:country":"US",
    "sg:address":"1945 E el Norte Pkwy",
    "sg:city":"Escondido",
    "sg:classifiers":[
        {
            "category":"Food & Beverages",
            "subcategory":"Meat & Fish",
            "type":"Retail Goods"
        }
    ],
    "sg:phone":"+1 760 839 6850",
    "sg:postcode":"92027",
    "sg:province":"CA",
    "wof:name":"Speciality Meats",
    "wof:placetype":"venue"
},
  "geometry": {"coordinates":[-117.062202,33.150888],"type":"Point"}
}