{
  "type": "Feature",
  "properties": {
    "iso:country":"US",
    "sg:address":"11061 Los Alamitos Blvd",
    "sg:city":"Los Alamitos",
    "sg:classifiers":[
        {
            "category":"Restaurant",
            "type":"Food & Drink"
        },
        {
            "category":"Food & Beverages",
            "subcategory":"Meat & Fish",
            "type":"Retail Goods"
        }
    ],
    "sg:phone":"+1 562 594 4553",
    "sg:postcode":"90720",
    "sg:province":"CA",
    "sg:tags":[
        "seafood",
        "market"
    ],
    "sg:website":"www.originalfishcompany.com",
    "wof:name":"The Original Fish Company",
    "wof:placetype":"venue"
},
  "geometry": {"coordinates":[-118.071808,33.80278],"type":"Point"}
}