{
  "type": "Feature",
  "properties": {
    "iso:country":"US",
    "sg:address":"600 Citadel Dr",
    "sg:city":"City Of Commerce",
    "sg:classifiers":[
        {
            "category":"Real Estate",
            "subcategory":"Real Estate Agent",
            "type":"Services"
        }
    ],
    "sg:phone":"+1 323 724 2246",
    "sg:postcode":"90040",
    "sg:province":"CA",
    "sg:tags":[
        "support"
    ],
    "sg:website":"www.trammellcrow.com",
    "wof:name":"Trammell Crow Co",
    "wof:placetype":"venue"
},
  "geometry": {"coordinates":[-118.152298,34.004815],"type":"Point"}
}