{
  "type": "Feature",
  "properties": {
    "addr:full":"7922 Rosecrans Ave Ste F Paramount CA 90723",
    "addr:housenumber":"7922",
    "addr:postcode":"90723",
    "addr:street":"Rosecrans Ave Ste F",
    "iso:country":"US",
    "sg:address":"7922 Rosecrans Ave Ste F",
    "sg:city":"Paramount",
    "sg:classifiers":[
        {
            "category":"Personal",
            "subcategory":"Beauty Salon",
            "type":"Services"
        },
        {
            "category":"Personal",
            "subcategory":"Skin Care",
            "type":"Services"
        }
    ],
    "sg:phone":"+1 562 634 7942",
    "sg:postcode":"90723",
    "sg:province":"CA",
    "sg:tags":[
        "hair"
    ],
    "wof:name":"Hair & Skin Care Center",
    "wof:placetype":"venue"
},
  "geometry": {"coordinates":[-118.161041,33.903156],"type":"Point"}
}