{
  "type": "Feature",
  "properties": {
    "iso:country":"US",
    "sg:address":"540 47th St",
    "sg:city":"Oakland",
    "sg:classifiers":[
        {
            "category":"Manufacturing",
            "subcategory":"Tools & Machinery",
            "type":"Manufacturing & Wholesale Goods"
        }
    ],
    "sg:phone":"+1 510 654 7488",
    "sg:postcode":"94609",
    "sg:province":"CA",
    "sg:tags":[
        "pattern",
        "industrial",
        "maker",
        "mfg"
    ],
    "sg:website":"http://www.hieberts.com",
    "wof:name":"Hiebert Sculpture Works",
    "wof:placetype":"venue"
},
  "geometry": {"coordinates":[-122.26396200000001,37.834474],"type":"Point"}
}