{
  "type": "Feature",
  "properties": {
    "iso:country":"US",
    "sg:address":"2240 Gladys Ave",
    "sg:city":"Rosemead",
    "sg:classifiers":[
        {
            "category":"Building & Trades",
            "subcategory":"Cleaning & Sanitation",
            "type":"Services"
        }
    ],
    "sg:phone":"+1 626 307 1005",
    "sg:postcode":"91770",
    "sg:province":"CA",
    "sg:tags":[
        "janitor"
    ],
    "wof:name":"Jj's Mobile Blind Cleaning",
    "wof:placetype":"venue"
},
  "geometry": {"coordinates":[-118.089298,34.054966],"type":"Point"}
}