{
  "type": "Feature",
  "properties": {
    "addr:full":"480 Laurie Ln Thousand Oaks CA 91360",
    "addr:housenumber":"480",
    "addr:postcode":"91360",
    "addr:street":"Laurie Ln",
    "iso:country":"US",
    "sg:address":"480 Laurie Ln",
    "sg:city":"Thousand Oaks",
    "sg:classifiers":[
        {
            "category":"Personal",
            "type":"Services"
        }
    ],
    "sg:phone":"+1 805 494 8481",
    "sg:postcode":"91360",
    "sg:province":"CA",
    "sg:tags":[
        "therapist",
        "massage"
    ],
    "wof:name":"Rick Hermelin",
    "wof:placetype":"venue"
},
  "geometry": {"coordinates":[-118.87192,34.184704],"type":"Point"}
}