{
  "type": "Feature",
  "properties": {
    "addr:full":"40960 Valley of the Falls Dr Forest Falls CA 92339",
    "addr:housenumber":"40960",
    "addr:postcode":"92339",
    "addr:street":"Valley Of The;Dr Forest",
    "iso:country":"US",
    "sg:address":"40960 Valley of the Falls Dr",
    "sg:city":"Forest Falls",
    "sg:classifiers":[
        {
            "category":"Real Estate",
            "subcategory":"Real Estate Agent",
            "type":"Services"
        }
    ],
    "sg:phone":"+1 909 794 8956",
    "sg:postcode":"92339",
    "sg:province":"CA",
    "wof:name":"Mountain Air Real Estate",
    "wof:placetype":"venue"
},
  "geometry": {"coordinates":[-116.910273,34.085956],"type":"Point"}
}