{
  "type": "Feature",
  "properties": {
    "iso:country":"US",
    "sg:address":"899 Clifton Ct",
    "sg:city":"Vacaville",
    "sg:classifiers":[
        {
            "category":"Professional",
            "subcategory":"Management & Consulting",
            "type":"Services"
        }
    ],
    "sg:phone":"+1 707 446 6446",
    "sg:postcode":"95688",
    "sg:province":"CA",
    "sg:tags":[
        "consultant"
    ],
    "wof:name":"First Phase Consultants",
    "wof:placetype":"venue"
},
  "geometry": {"coordinates":[-121.976687,38.390065],"type":"Point"}
}