{
  "type": "Feature",
  "properties": {
    "addr:full":"7670 El Camino Real Carlsbad CA 92009",
    "addr:housenumber":"7670",
    "addr:postcode":"92009",
    "addr:street":"El Camino Real",
    "iso:country":"US",
    "sg:address":"7670 El Camino Real",
    "sg:city":"Carlsbad",
    "sg:classifiers":[
        {
            "category":"Restaurant",
            "type":"Food & Drink"
        }
    ],
    "sg:menulink":"http://www.allmenus.com/ca/oceanside-escondido/26708-tommy-vs/menu/",
    "sg:phone":"+1 760 943 8182",
    "sg:postcode":"92009",
    "sg:province":"CA",
    "sg:tags":[
        "american"
    ],
    "wof:name":"Tommy V's",
    "wof:placetype":"venue"
},
  "geometry": {"coordinates":[-117.26870599999999,33.086539],"type":"Point"}
}