{
  "type": "Feature",
  "properties": {
    "addr:full":"28331 Preakness Dr Tehachapi CA 93561",
    "addr:housenumber":"28331",
    "addr:postcode":"93561",
    "addr:street":"Preakness Dr",
    "iso:country":"US",
    "sg:address":"28331 Preakness Dr",
    "sg:city":"Tehachapi",
    "sg:classifiers":[
        {
            "category":"Professional",
            "type":"Services"
        }
    ],
    "sg:phone":"+1 661 822 1256",
    "sg:postcode":"93561",
    "sg:province":"CA",
    "wof:name":"Windswept Enterprises Svc",
    "wof:placetype":"venue"
},
  "geometry": {"coordinates":[-118.63400300000001,35.079108],"type":"Point"}
}