{
  "type": "Feature",
  "properties": {
    "addr:full":"575 Coombsville Rd Napa CA 94558",
    "addr:housenumber":"575",
    "addr:postcode":"94558",
    "addr:street":"Coombsville Rd",
    "iso:country":"US",
    "sg:address":"575 Coombsville Rd",
    "sg:city":"Napa",
    "sg:classifiers":[
        {
            "category":"Personal",
            "subcategory":"Beauty Salon",
            "type":"Services"
        }
    ],
    "sg:phone":"+1 707 254 9945",
    "sg:postcode":"94558",
    "sg:province":"CA",
    "wof:name":"David Magna Workshop",
    "wof:placetype":"venue"
},
  "geometry": {"coordinates":[-122.270445,38.297496],"type":"Point"}
}