{
  "type": "Feature",
  "properties": {
    "iso:country":"US",
    "sg:address":"2585 E Perrin Ave Ste 102",
    "sg:city":"Fresno",
    "sg:classifiers":[
        {
            "category":"Health Services",
            "subcategory":"Clinic",
            "type":"Services"
        }
    ],
    "sg:phone":"+1 559 322 5877",
    "sg:postcode":"93720",
    "sg:province":"CA",
    "sg:tags":[
        "information",
        "mental"
    ],
    "wof:name":"Suicide Loss Fresno Survivors of",
    "wof:placetype":"venue"
},
  "geometry": {"coordinates":[-119.73903799999999,36.873957],"type":"Point"}
}