{
  "type": "Feature",
  "properties": {
    "iso:country":"US",
    "sg:address":"150 Shoreline Hwy",
    "sg:city":"Mill Valley",
    "sg:classifiers":[
        {
            "category":"Manufacturing",
            "subcategory":"Watercraft",
            "type":"Manufacturing & Wholesale Goods"
        }
    ],
    "sg:phone":"+1 415 331 4532",
    "sg:postcode":"94965",
    "sg:province":"CA",
    "wof:name":"T T F N Limited",
    "wof:placetype":"venue"
},
  "geometry": {"coordinates":[-122.522606,37.879536],"type":"Point"}
}