{
  "type": "Feature",
  "properties": {
    "addr:full":"13081 Central Ave Boulder Creek CA 95006",
    "addr:postcode":"13081;95006",
    "addr:street":"Central Ave",
    "iso:country":"US",
    "sg:address":"13081 Central Ave",
    "sg:city":"Boulder Creek",
    "sg:classifiers":[
        {
            "category":"Shopping",
            "subcategory":"Pharmacy",
            "type":"Retail Goods"
        }
    ],
    "sg:phone":"+1 831 338 2144",
    "sg:postcode":"95006",
    "sg:province":"CA",
    "wof:name":"Boulder Creek Pharmacy",
    "wof:placetype":"venue"
},
  "geometry": {"coordinates":[-122.121827,37.123669],"type":"Point"}
}