{
  "type": "Feature",
  "properties": {
    "iso:country":"US",
    "sg:address":"625 del Sol Ave",
    "sg:city":"Pleasanton",
    "sg:classifiers":[
        {
            "category":"Professional",
            "subcategory":"Art Services",
            "type":"Services"
        }
    ],
    "sg:phone":"+1 925 846 8310",
    "sg:postcode":"94566",
    "sg:province":"CA",
    "sg:tags":[
        "designer",
        "display",
        "producer"
    ],
    "wof:name":"Bnh Designs Inc",
    "wof:placetype":"venue"
},
  "geometry": {"coordinates":[-121.865792,37.65804],"type":"Point"}
}