{
  "type": "Feature",
  "properties": {
    "iso:country":"US",
    "sg:address":"40282 State Hwy 41",
    "sg:city":"Oakhurst",
    "sg:classifiers":[
        {
            "category":"Health Services",
            "subcategory":"Doctor",
            "type":"Services"
        }
    ],
    "sg:phone":"+1 559 658 2166",
    "sg:postcode":"93644",
    "sg:province":"CA",
    "sg:tags":[
        "dentist"
    ],
    "wof:name":"Christopher Rose DDS",
    "wof:placetype":"venue"
},
  "geometry": {"coordinates":[-119.65025,37.333222],"type":"Point"}
}