{
  "type": "Feature",
  "properties": {
    "iso:country":"US",
    "sg:address":"4248 24th St",
    "sg:city":"Sacramento",
    "sg:classifiers":[
        {
            "category":"Autos & Motor Vehicles",
            "subcategory":"Automobile Sales",
            "type":"Retail Goods"
        }
    ],
    "sg:phone":"+1 916 456 8956",
    "sg:postcode":"95822",
    "sg:province":"CA",
    "sg:tags":[
        "car",
        "dealer"
    ],
    "wof:name":"David's Autos & Detail",
    "wof:placetype":"venue"
},
  "geometry": {"coordinates":[-121.483397,38.535514],"type":"Point"}
}