{
  "type": "Feature",
  "properties": {
    "iso:country":"US",
    "sg:address":"1177 Shasta St",
    "sg:city":"Redding",
    "sg:classifiers":[
        {
            "category":"Restaurant",
            "type":"Food & Drink"
        }
    ],
    "sg:phone":"+1 530 241 2575",
    "sg:postcode":"96001",
    "sg:province":"CA",
    "wof:name":"Maverick's",
    "wof:placetype":"venue"
},
  "geometry": {"coordinates":[-122.389004,40.586943],"type":"Point"}
}