{
  "type": "Feature",
  "properties": {
    "iso:country":"US",
    "sg:address":"615 W Foothill Blvd",
    "sg:city":"Glendora",
    "sg:classifiers":[
        {
            "category":"Retail",
            "subcategory":"Veterinary Services",
            "type":"Services"
        }
    ],
    "sg:phone":"+1 626 335 4912",
    "sg:postcode":"91741",
    "sg:province":"CA",
    "sg:tags":[
        "hospital",
        "animal"
    ],
    "wof:name":"West Foothill Animal Hospital",
    "wof:placetype":"venue"
},
  "geometry": {"coordinates":[-117.873475,34.136131],"type":"Point"}
}