{
  "type": "Feature",
  "properties": {
    "addr:full":"2525 Walnut Avenue Carmichael CA 95608",
    "addr:housenumber":"2525",
    "addr:postcode":"95608",
    "addr:street":"Walnut Avenue",
    "iso:country":"US",
    "sg:address":"2525 Walnut Avenue",
    "sg:city":"Carmichael",
    "sg:classifiers":[
        {
            "category":"Personal",
            "subcategory":"Massage",
            "type":"Services"
        }
    ],
    "sg:phone":"+1 916 482 1403",
    "sg:postcode":"95608",
    "sg:province":"CA",
    "wof:name":"Maily Therapy Massage",
    "wof:placetype":"venue"
},
  "geometry": {"coordinates":[-121.34610600000001,38.611356],"type":"Point"}
}