{
  "type": "Feature",
  "properties": {
    "addr:full":"1434 State Hwy 99 Gridley CA 95948",
    "addr:housenumber":"1434",
    "addr:postcode":"95948",
    "addr:street":"State Hwy 99",
    "iso:country":"US",
    "sg:address":"1434 State Hwy 99",
    "sg:city":"Gridley",
    "sg:phone":"+1 530 846 5662",
    "sg:postcode":"95948",
    "sg:province":"CA",
    "sg:tags":[
        "gas"
    ],
    "wof:name":"Ameri Gas Inc",
    "wof:placetype":"venue"
},
  "geometry": {"coordinates":[-121.687845,39.357134],"type":"Point"}
}