{
  "type": "Feature",
  "properties": {
    "iso:country":"US",
    "sg:address":"1921 E Wright Cir",
    "sg:city":"Anaheim",
    "sg:classifiers":[
        {
            "category":"Personal",
            "type":"Services"
        }
    ],
    "sg:phone":"+1 310 372 7850",
    "sg:postcode":"92806",
    "sg:province":"CA",
    "sg:tags":[
        "mover"
    ],
    "wof:name":"Starving Veterans Moving & Storage Co",
    "wof:placetype":"venue"
},
  "geometry": {"coordinates":[-117.889,33.805302],"type":"Point"}
}