{
  "type": "Feature",
  "properties": {
    "addr:full":"3003 N Blackstone Ave Fresno CA 93704",
    "addr:housenumber":"3003",
    "addr:postcode":"93704",
    "addr:street":"N Blackstone Ave",
    "iso:country":"US",
    "sg:address":"3003 N Blackstone Ave",
    "sg:city":"Fresno",
    "sg:classifiers":[
        {
            "category":"Professional",
            "subcategory":"Lawyer & Legal Services",
            "type":"Services"
        }
    ],
    "sg:phone":"+1 559 222 2274",
    "sg:postcode":"93704",
    "sg:province":"CA",
    "sg:tags":[
        "attorney",
        "bureau"
    ],
    "wof:name":"Eddings Attorney Svc",
    "wof:placetype":"venue"
},
  "geometry": {"coordinates":[-119.79061400000001,36.778603],"type":"Point"}
}