{
  "type": "Feature",
  "properties": {
    "addr:full":"2428 State St Santa Barbara CA 93105",
    "addr:housenumber":"2428",
    "addr:postcode":"93105",
    "addr:street":"State St",
    "iso:country":"US",
    "sg:address":"2428 State St",
    "sg:city":"Santa Barbara",
    "sg:classifiers":[
        {
            "category":"Retail",
            "subcategory":"Auto Repair",
            "type":"Services"
        }
    ],
    "sg:phone":"+1 805 884 9915",
    "sg:postcode":"93105",
    "sg:province":"CA",
    "sg:tags":[
        "repairing",
        "automobile"
    ],
    "wof:name":"Auto House Salcbuog Inc",
    "wof:placetype":"venue"
},
  "geometry": {"coordinates":[-119.72067300000001,34.43526],"type":"Point"}
}