{
  "type": "Feature",
  "properties": {
    "iso:country":"US",
    "sg:address":"9243 Reseda Blvd",
    "sg:city":"Northridge",
    "sg:classifiers":[
        {
            "category":"Organizations",
            "subcategory":"Religious Organization",
            "type":"Services"
        }
    ],
    "sg:phone":"+1 818 885 8707",
    "sg:postcode":"91324",
    "sg:province":"CA",
    "sg:tags":[
        "church"
    ],
    "wof:name":"Christian Science Reading Room",
    "wof:placetype":"venue"
},
  "geometry": {"coordinates":[-118.536162,34.238343],"type":"Point"}
}