{
  "type": "Feature",
  "properties": {
    "addr:full":"30 Albion St San Francisco CA 94103",
    "addr:housenumber":"30",
    "addr:postcode":"94103",
    "addr:street":"Albion St",
    "iso:country":"US",
    "sg:address":"30 Albion St",
    "sg:city":"San Francisco",
    "sg:classifiers":[
        {
            "category":"Health Services",
            "subcategory":"Health Practitioner",
            "type":"Services"
        }
    ],
    "sg:phone":"+1 415 861 1101",
    "sg:postcode":"94103",
    "sg:province":"CA",
    "sg:tags":[
        "acupuncture"
    ],
    "wof:name":"Chicken Soup Chinese Medicine",
    "wof:placetype":"venue"
},
  "geometry": {"coordinates":[-122.42322799999999,37.765328],"type":"Point"}
}