{
  "type": "Feature",
  "properties": {
    "addr:full":"2625 Sleepy Hollow Pl Glendale CA 91206",
    "addr:housenumber":"2625",
    "addr:postcode":"91206",
    "addr:street":"Sleepy Hollow Pl",
    "iso:country":"US",
    "sg:address":"2625 Sleepy Hollow Pl",
    "sg:city":"Glendale",
    "sg:classifiers":[
        {
            "category":"Professional",
            "subcategory":"Accounting & Tax Preparation",
            "type":"Services"
        }
    ],
    "sg:phone":"+1 818 956 8010",
    "sg:postcode":"91206",
    "sg:province":"CA",
    "sg:tags":[
        "return",
        "filing"
    ],
    "wof:name":"M & Y Accounting & Tax Svc",
    "wof:placetype":"venue"
},
  "geometry": {"coordinates":[-118.20722499999999,34.148308],"type":"Point"}
}