{
  "type": "Feature",
  "properties": {
    "iso:country":"US",
    "sg:address":"1445 Cortez Ct",
    "sg:city":"Walnut Creek",
    "sg:classifiers":[
        {
            "category":"Insurance",
            "subcategory":"Insurance Agent",
            "type":"Services"
        }
    ],
    "sg:phone":"+1 925 947 1412",
    "sg:postcode":"94598",
    "sg:province":"CA",
    "sg:tags":[
        "accident"
    ],
    "wof:name":"A Specialist In LTC & Di",
    "wof:placetype":"venue"
},
  "geometry": {"coordinates":[-122.040076,37.907713],"type":"Point"}
}