{
  "type": "Feature",
  "properties": {
    "addr:full":"430 E 10th St Oakland CA 94606",
    "addr:housenumber":"430",
    "addr:postcode":"94606",
    "addr:street":"E 10Th St",
    "iso:country":"US",
    "sg:address":"430 E 10th St",
    "sg:city":"Oakland",
    "sg:classifiers":[
        {
            "category":"Retail",
            "subcategory":"Repair Shop",
            "type":"Services"
        }
    ],
    "sg:phone":"+1 510 834 8803",
    "sg:postcode":"94606",
    "sg:province":"CA",
    "sg:tags":[
        "scooter",
        "scooters-parts",
        "motorcycle",
        "motor",
        "supply"
    ],
    "sg:website":"http://www.hayasamotorbikes.com",
    "wof:name":"Hayasa Motorbikes",
    "wof:placetype":"venue"
},
  "geometry": {"coordinates":[-122.25700399999999,37.7938],"type":"Point"}
}