{
  "type": "Feature",
  "properties": {
    "addr:full":"30550 Union City Blvd Union City CA 94587",
    "addr:housenumber":"30550",
    "addr:postcode":"94587",
    "addr:street":"Union City Blvd",
    "iso:country":"US",
    "sg:address":"30550 Union City Blvd",
    "sg:city":"Union City",
    "sg:classifiers":[
        {
            "category":"Manufacturing",
            "subcategory":"Tools & Machinery",
            "type":"Manufacturing & Wholesale Goods"
        }
    ],
    "sg:phone":"+1 510 881 5285",
    "sg:postcode":"94587",
    "sg:province":"CA",
    "sg:tags":[
        "machine",
        "shop"
    ],
    "wof:name":"Kovowerk",
    "wof:placetype":"venue"
},
  "geometry": {"coordinates":[-122.081671,37.598893],"type":"Point"}
}