{
  "type": "Feature",
  "properties": {
    "addr:full":"1305 Ocean Front Walk Venice CA 90291",
    "addr:housenumber":"1305",
    "addr:postcode":"90291",
    "addr:street":"Ocean Front Walk",
    "iso:country":"US",
    "sg:address":"1305 Ocean Front Walk",
    "sg:city":"Venice",
    "sg:classifiers":[
        {
            "category":"Travel",
            "subcategory":"Hotels & Motels",
            "type":"Entertainment"
        }
    ],
    "sg:phone":"+1 310 396 4559",
    "sg:postcode":"90291",
    "sg:province":"CA",
    "wof:name":"Venice Beach Suites",
    "wof:placetype":"venue"
},
  "geometry": {"coordinates":[-118.474687,33.987905],"type":"Point"}
}