{
  "type": "Feature",
  "properties": {
    "addr:full":"402 E. Gutierrez St. Santa Barbara CA 93101",
    "addr:housenumber":"402",
    "addr:postcode":"93101",
    "addr:street":"E. Gutierrez St.",
    "iso:country":"US",
    "sg:address":"402 E. Gutierrez St.",
    "sg:city":"Santa Barbara",
    "sg:classifiers":[
        {
            "category":"Professional",
            "subcategory":"Computer Services",
            "type":"Services"
        }
    ],
    "sg:phone":"+1 866 622 8817",
    "sg:postcode":"93101",
    "sg:province":"CA",
    "sg:tags":[
        "grassroots",
        "fundraising",
        "donations",
        "philanthropy"
    ],
    "sg:website":"http://www.givezooks.com",
    "wof:name":"givezooks!",
    "wof:placetype":"venue"
},
  "geometry": {"coordinates":[-119.68851100000001,34.421085],"type":"Point"}
}