{
  "type": "Feature",
  "properties": {
    "addr:full":"9246 Dunbarton Rd Santee CA 92071",
    "addr:housenumber":"9246",
    "addr:postcode":"92071",
    "addr:street":"Dunbarton Rd",
    "iso:country":"US",
    "sg:address":"9246 Dunbarton Rd",
    "sg:city":"Santee",
    "sg:classifiers":[
        {
            "category":"Wholesale",
            "subcategory":"Office Equipment",
            "type":"Manufacturing & Wholesale Goods"
        }
    ],
    "sg:phone":"+1 619 449 7210",
    "sg:postcode":"92071",
    "sg:province":"CA",
    "wof:name":"Minolta Service",
    "wof:placetype":"venue"
},
  "geometry": {"coordinates":[-116.99996299999999,32.848825],"type":"Point"}
}