{
  "type": "Feature",
  "properties": {
    "addr:full":"1170 Clark St. San Jose CA 95125",
    "addr:housenumber":"1170",
    "addr:postcode":"95125",
    "addr:street":"Clark St.",
    "iso:country":"US",
    "sg:address":"1170 Clark St.",
    "sg:city":"San Jose",
    "sg:classifiers":[
        {
            "category":"Building & Trades",
            "subcategory":"Construction",
            "type":"Services"
        }
    ],
    "sg:phone":"+1 408 690 6059",
    "sg:postcode":"95125",
    "sg:province":"CA",
    "sg:tags":[
        "contractor"
    ],
    "sg:website":"www.vandonzel.com",
    "wof:name":"Vandonzel Construction",
    "wof:placetype":"venue"
},
  "geometry": {"coordinates":[-121.891192,37.312023],"type":"Point"}
}