{
  "type": "Feature",
  "properties": {
    "iso:country":"US",
    "sg:address":"41 Auto Centre Drive Ste 111",
    "sg:city":"Foothill Ranch",
    "sg:classifiers":[
        {
            "category":"Personal",
            "subcategory":"Barber",
            "type":"Services"
        }
    ],
    "sg:phone":"+1 949 215 6000",
    "sg:postcode":"92610",
    "sg:province":"CA",
    "wof:name":"V's Barbershop",
    "wof:placetype":"venue"
},
  "geometry": {"coordinates":[-117.661754,33.675802],"type":"Point"}
}