{
  "type": "Feature",
  "properties": {
    "iso:country":"US",
    "sg:address":"806 W 7th St",
    "sg:city":"Los Angeles",
    "sg:classifiers":[
        {
            "category":"Shopping",
            "subcategory":"Tobacco",
            "type":"Retail Goods"
        }
    ],
    "sg:phone":"+1 213 995 1257",
    "sg:postcode":"90017",
    "sg:province":"CA",
    "sg:tags":[
        "shop",
        "cigarette",
        "cigar"
    ],
    "sg:website":"www.diplomatcigars.com",
    "wof:name":"Diplomat Cigar Shop",
    "wof:placetype":"venue"
},
  "geometry": {"coordinates":[-118.25900300000001,34.049198],"type":"Point"}
}