{
  "type": "Feature",
  "properties": {
    "iso:country":"US",
    "sg:address":"1704 Highway 46",
    "sg:city":"Wasco",
    "sg:classifiers":[
        {
            "category":"Travel",
            "subcategory":"Hotels & Motels",
            "type":"Entertainment"
        }
    ],
    "sg:phone":"+1 877 574 2464",
    "sg:postcode":"93280",
    "sg:province":"CA",
    "sg:tags":[
        "lodging"
    ],
    "sg:website":"http://book.bestwestern.com/bestwestern/priceAvail.do?propertyCode=05688&cm_mmc=IYP-_-YP-_-property-_-5688",
    "wof:name":"Best Western Wasco Inn & Suites",
    "wof:placetype":"venue"
},
  "geometry": {"coordinates":[-119.345246,35.601555],"type":"Point"}
}