{
  "type": "Feature",
  "properties": {
    "iso:country":"US",
    "sg:address":"222 W 39th Avenue",
    "sg:city":"San Mateo",
    "sg:classifiers":[
        {
            "category":"Health Services",
            "subcategory":"Doctor",
            "type":"Services"
        }
    ],
    "sg:phone":"+1 650 573 2421",
    "sg:postcode":"94403",
    "sg:province":"CA",
    "wof:name":"Meier James MD",
    "wof:placetype":"venue"
},
  "geometry": {"coordinates":[-122.299706,37.530111],"type":"Point"}
}