{
  "type": "Feature",
  "properties": {
    "iso:country":"US",
    "sg:address":"439 F St",
    "sg:city":"Lincoln",
    "sg:classifiers":[
        {
            "category":"Personal",
            "subcategory":"Barber",
            "type":"Services"
        }
    ],
    "sg:phone":"+1 916 645 7596",
    "sg:postcode":"95648",
    "sg:province":"CA",
    "wof:name":"Family Haircut",
    "wof:placetype":"venue"
},
  "geometry": {"coordinates":[-121.29147399999999,38.891031],"type":"Point"}
}