{
  "type": "Feature",
  "properties": {
    "iso:country":"US",
    "sg:address":"3586 Homestead Rd",
    "sg:city":"Santa Clara",
    "sg:classifiers":[
        {
            "category":"Food & Beverages",
            "subcategory":"Bakery",
            "type":"Retail Goods"
        }
    ],
    "sg:phone":"+1 408 248 4952",
    "sg:postcode":"95051",
    "sg:province":"CA",
    "sg:tags":[
        "sandwich"
    ],
    "wof:name":"Subway",
    "wof:placetype":"venue"
},
  "geometry": {"coordinates":[-121.99400300000001,37.337898],"type":"Point"}
}