{
  "type": "Feature",
  "properties": {
    "iso:country":"US",
    "sg:address":"9151 Atlanta Ave",
    "sg:city":"Huntington Beach",
    "sg:classifiers":[
        {
            "category":"Recreation",
            "type":"Entertainment"
        }
    ],
    "sg:phone":"+1 714 536 3600",
    "sg:postcode":"92646",
    "sg:province":"CA",
    "sg:tags":[
        "aquarium"
    ],
    "wof:name":"Aqua Doc Aquarium Sales & Svc",
    "wof:placetype":"venue"
},
  "geometry": {"coordinates":[-117.969746,33.65782],"type":"Point"}
}