{
  "type": "Feature",
  "properties": {
    "addr:full":"18211 Beach Boulevard Huntington Beach CA 92648",
    "addr:housenumber":"18211",
    "addr:postcode":"92648",
    "addr:street":"Beach Boulevard",
    "iso:country":"US",
    "sg:address":"18211 Beach Boulevard",
    "sg:city":"Huntington Beach",
    "sg:classifiers":[
        {
            "category":"Autos & Motor Vehicles",
            "subcategory":"Automobile Sales",
            "type":"Retail Goods"
        }
    ],
    "sg:phone":"+1 714 847 6087",
    "sg:postcode":"92648",
    "sg:province":"CA",
    "sg:tags":[
        "car"
    ],
    "wof:name":"Delillo Chevrolet",
    "wof:placetype":"venue"
},
  "geometry": {"coordinates":[-117.989611,33.699059],"type":"Point"}
}