{
  "type": "Feature",
  "properties": {
    "addr:full":"325 River St Ste A Santa Cruz CA 95060",
    "addr:housenumber":"325",
    "addr:postcode":"95060",
    "addr:street":"River St Ste A",
    "iso:country":"US",
    "sg:address":"325 River St Ste A",
    "sg:city":"Santa Cruz",
    "sg:classifiers":[
        {
            "category":"Food & Beverages",
            "subcategory":"Liquor & Beverages",
            "type":"Retail Goods"
        },
        {
            "category":"Shopping",
            "subcategory":"Crafts & Fabrics",
            "type":"Retail Goods"
        }
    ],
    "sg:phone":"+1 831 454 9665",
    "sg:postcode":"95060",
    "sg:province":"CA",
    "sg:tags":[
        "beer",
        "art",
        "spirit",
        "wine"
    ],
    "sg:website":"www.breworganic.com",
    "wof:name":"Seven Bridges Cooperative",
    "wof:placetype":"venue"
},
  "geometry": {"coordinates":[-122.028811,36.980909],"type":"Point"}
}