{
  "type": "Feature",
  "properties": {
    "addr:full":"3587 Pleasant Knoll Dr San Jose CA 95148",
    "addr:housenumber":"3587",
    "addr:postcode":"95148",
    "addr:street":"Pleasant Knoll Dr",
    "iso:country":"US",
    "sg:address":"3587 Pleasant Knoll Dr",
    "sg:city":"San Jose",
    "sg:classifiers":[
        {
            "category":"Freight",
            "type":"Transportation"
        }
    ],
    "sg:phone":"+1 408 528 0165",
    "sg:postcode":"95148",
    "sg:province":"CA",
    "sg:tags":[
        "operator",
        "local",
        "trucking"
    ],
    "wof:name":"Herreras Twin Trucking",
    "wof:placetype":"venue"
},
  "geometry": {"coordinates":[-121.792022,37.350168],"type":"Point"}
}