{
  "type": "Feature",
  "properties": {
    "addr:full":"240 E Shady Grove Dr Riverside CA 92507",
    "addr:housenumber":"240",
    "addr:postcode":"92507",
    "addr:street":"E Shady Grove Dr",
    "iso:country":"US",
    "sg:address":"240 E Shady Grove Dr",
    "sg:city":"Riverside",
    "sg:classifiers":[
        {
            "category":"Professional",
            "subcategory":"Accounting & Tax Preparation",
            "type":"Services"
        }
    ],
    "sg:phone":"+1 951 276 9204",
    "sg:postcode":"92507",
    "sg:province":"CA",
    "sg:tags":[
        "bookkeeping",
        "general"
    ],
    "wof:name":"Accounting Etcetera",
    "wof:placetype":"venue"
},
  "geometry": {"coordinates":[-117.31148899999999,33.981154],"type":"Point"}
}