{
  "type": "Feature",
  "properties": {
    "addr:full":"233 N Jackson St Glendale CA 91206",
    "addr:housenumber":"233",
    "addr:postcode":"91206",
    "addr:street":"N Jackson St",
    "iso:country":"US",
    "sg:address":"233 N Jackson St",
    "sg:city":"Glendale",
    "sg:classifiers":[
        {
            "category":"Education",
            "subcategory":"School",
            "type":"Public Place"
        }
    ],
    "sg:phone":"+1 818 241 3111",
    "sg:postcode":"91206",
    "sg:province":"CA",
    "sg:tags":[
        "elementary"
    ],
    "sg:website":"www.glendale.k12.ca.us",
    "wof:name":"Board of Education of Glendale",
    "wof:placetype":"venue"
},
  "geometry": {"coordinates":[-118.25,34.148602],"type":"Point"}
}