{
  "type": "Feature",
  "properties": {
    "addr:full":"12786 Railroad Dr Cutler CA 93615",
    "addr:housenumber":"12786",
    "addr:postcode":"93615",
    "addr:street":"Railroad Dr",
    "iso:country":"US",
    "sg:address":"12786 Railroad Dr",
    "sg:city":"Cutler",
    "sg:classifiers":[
        {
            "category":"Fast Food",
            "type":"Food & Drink"
        },
        {
            "category":"Restaurant",
            "type":"Food & Drink"
        }
    ],
    "sg:phone":"+1 559 528 2414",
    "sg:postcode":"93615",
    "sg:province":"CA",
    "sg:tags":[
        "mexican",
        "take"
    ],
    "wof:name":"La Esperanza",
    "wof:placetype":"venue"
},
  "geometry": {"coordinates":[-119.287014,36.522128],"type":"Point"}
}