{
  "type": "Feature",
  "properties": {
    "iso:country":"US",
    "sg:address":"6400 E Marina Dr",
    "sg:city":"Long Beach",
    "sg:classifiers":[
        {
            "category":"Manufacturing",
            "subcategory":"Apparel",
            "type":"Manufacturing & Wholesale Goods"
        }
    ],
    "sg:phone":"+1 562 598 9441",
    "sg:postcode":"90803",
    "sg:province":"CA",
    "sg:tags":[
        "product",
        "mfg"
    ],
    "wof:name":"Ullman Sails Inc",
    "wof:placetype":"venue"
},
  "geometry": {"coordinates":[-118.112399,33.757315],"type":"Point"}
}