{
  "type": "Feature",
  "properties": {
    "addr:full":"2290 W El Camino Real Mountain View CA 94040",
    "addr:housenumber":"2290",
    "addr:postcode":"94040",
    "addr:street":"W El Camino Real",
    "iso:country":"US",
    "sg:address":"2290 W El Camino Real",
    "sg:city":"Mountain View",
    "sg:classifiers":[
        {
            "category":"Restaurant",
            "type":"Food & Drink"
        }
    ],
    "sg:menulink":"http://www.allmenus.com/ca/san-jose/19579-amber-india-restaurant/menu/",
    "sg:phone":"+1 650 968 7511",
    "sg:postcode":"94040",
    "sg:province":"CA",
    "sg:tags":[
        "indian",
        "asian"
    ],
    "wof:name":"Amber India Restaurant",
    "wof:placetype":"venue"
},
  "geometry": {"coordinates":[-122.105746,37.397557],"type":"Point"}
}