{
  "type": "Feature",
  "properties": {
    "addr:full":"860 N Main St Orange CA 92868",
    "addr:housenumber":"860",
    "addr:postcode":"92868",
    "addr:street":"N Main St",
    "iso:country":"US",
    "sg:address":"860 N Main St",
    "sg:city":"Orange",
    "sg:classifiers":[
        {
            "category":"Shopping",
            "subcategory":"Used Merchandise",
            "type":"Retail Goods"
        }
    ],
    "sg:phone":"+1 714 363 0263",
    "sg:postcode":"92868",
    "sg:province":"CA",
    "sg:tags":[
        "antique"
    ],
    "wof:name":"Aunt Jo's Antique Emporium",
    "wof:placetype":"venue"
},
  "geometry": {"coordinates":[-117.866778,33.801661],"type":"Point"}
}