{
  "type": "Feature",
  "properties": {
    "iso:country":"US",
    "sg:address":"1112 Phoenix Ave",
    "sg:city":"Seaside",
    "sg:classifiers":[
        {
            "category":"Building & Trades",
            "subcategory":"Pest Control",
            "type":"Services"
        }
    ],
    "sg:phone":"+1 831 392 1345",
    "sg:postcode":"93955",
    "sg:province":"CA",
    "wof:name":"Bay View Pest Control Svc",
    "wof:placetype":"venue"
},
  "geometry": {"coordinates":[-121.84021199999999,36.613],"type":"Point"}
}