{
  "type": "Feature",
  "properties": {
    "iso:country":"US",
    "sg:address":"931 W Hoover Ave",
    "sg:city":"Orange",
    "sg:classifiers":[
        {
            "category":"Wholesale",
            "subcategory":"Stationery",
            "type":"Manufacturing & Wholesale Goods"
        }
    ],
    "sg:phone":"+1 714 279 9090",
    "sg:postcode":"92867",
    "sg:province":"CA",
    "sg:tags":[
        "box",
        "fiber"
    ],
    "wof:name":"Boxes Express Paper Co",
    "wof:placetype":"venue"
},
  "geometry": {"coordinates":[-117.863152,33.807509],"type":"Point"}
}