{
  "type": "Feature",
  "properties": {
    "iso:country":"US",
    "sg:address":"333 S Anita Dr",
    "sg:city":"Orange",
    "sg:classifiers":[
        {
            "category":"Professional",
            "subcategory":"Secretarial Services",
            "type":"Services"
        }
    ],
    "sg:phone":"+1 714 634 4800",
    "sg:postcode":"92868",
    "sg:province":"CA",
    "sg:tags":[
        "convention",
        "court",
        "reporter"
    ],
    "sg:website":"www.biehlandbell.com",
    "wof:name":"Biehl & Bell",
    "wof:placetype":"venue"
},
  "geometry": {"coordinates":[-117.881096,33.787086],"type":"Point"}
}