{
  "type": "Feature",
  "properties": {
    "addr:full":"24921 Dana Dr Dana Point CA 92629",
    "addr:housenumber":"24921",
    "addr:postcode":"92629",
    "addr:street":"Dana Dr",
    "iso:country":"US",
    "sg:address":"24921 Dana Dr",
    "sg:city":"Dana Point",
    "sg:classifiers":[
        {
            "category":"Professional",
            "subcategory":"Management & Consulting",
            "type":"Services"
        }
    ],
    "sg:phone":"+1 949 488 9721",
    "sg:postcode":"92629",
    "sg:province":"CA",
    "sg:tags":[
        "consultant",
        "business"
    ],
    "wof:name":"Alexis Resource Corp",
    "wof:placetype":"venue"
},
  "geometry": {"coordinates":[-117.697186,33.458057],"type":"Point"}
}