{
  "type": "Feature",
  "properties": {
    "addr:full":"3907 Carpenter Ct Studio City CA 91604",
    "addr:housenumber":"3907",
    "addr:postcode":"91604",
    "addr:street":"Carpenter Ct",
    "iso:country":"US",
    "sg:address":"3907 Carpenter Ct",
    "sg:city":"Studio City",
    "sg:classifiers":[
        {
            "category":"Building & Trades",
            "subcategory":"Construction",
            "type":"Services"
        }
    ],
    "sg:phone":"+1 818 509 8668",
    "sg:postcode":"91604",
    "sg:province":"CA",
    "sg:tags":[
        "residential",
        "general",
        "contractor"
    ],
    "wof:name":"A & R Construction & Dev",
    "wof:placetype":"venue"
},
  "geometry": {"coordinates":[-118.39073399999999,34.140939],"type":"Point"}
}