{
  "type": "Feature",
  "properties": {
    "addr:full":"38001 Old Stage Rd Gualala CA 95445",
    "addr:housenumber":"38001",
    "addr:postcode":"95445",
    "addr:street":"Old Stage Rd",
    "iso:country":"US",
    "sg:address":"38001 Old Stage Rd",
    "sg:city":"Gualala",
    "sg:classifiers":[
        {
            "category":"Home & Garden",
            "subcategory":"Home Furnishings",
            "type":"Retail Goods"
        },
        {
            "category":"Building & Trades",
            "subcategory":"Construction",
            "type":"Services"
        },
        {
            "category":"Manufacturing",
            "subcategory":"Building Materials",
            "type":"Manufacturing & Wholesale Goods"
        }
    ],
    "sg:phone":"+1 707 884 1004",
    "sg:postcode":"95445",
    "sg:province":"CA",
    "sg:tags":[
        "industrial",
        "cabinetmakers-commercial",
        "cabinet",
        "refacing",
        "resurfacing",
        "maker",
        "cabinets-refinishing",
        "kitchen"
    ],
    "wof:name":"Gualala Joinery",
    "wof:placetype":"venue"
},
  "geometry": {"coordinates":[-123.53098300000001,38.800121],"type":"Point"}
}