{
  "type": "Feature",
  "properties": {
    "iso:country":"US",
    "sg:address":"6311 Wilshire Blvd",
    "sg:city":"Los Angeles",
    "sg:classifiers":[
        {
            "category":"Bars & Pubs",
            "subcategory":"Sports Bar",
            "type":"Food & Drink"
        },
        {
            "category":"Restaurant",
            "type":"Food & Drink"
        }
    ],
    "sg:phone":"+1 323 651 5433",
    "sg:postcode":"90048",
    "sg:province":"CA",
    "sg:tags":[
        "traditional",
        "american"
    ],
    "sg:website":"www.thevarsityla.com",
    "wof:name":"The Varsity LA",
    "wof:placetype":"venue"
},
  "geometry": {"coordinates":[-118.365871,34.063663],"type":"Point"}
}