{
  "type": "Feature",
  "properties": {
    "iso:country":"US",
    "sg:address":"3525 Alma St",
    "sg:city":"Palo Alto",
    "sg:classifiers":[
        {
            "category":"Real Estate",
            "subcategory":"Real Estate Agent",
            "type":"Services"
        }
    ],
    "sg:phone":"+1 650 843 0740",
    "sg:postcode":"94306",
    "sg:province":"CA",
    "sg:tags":[
        "appraiser"
    ],
    "wof:name":"Reitman Group",
    "wof:placetype":"venue"
},
  "geometry": {"coordinates":[-122.125423,37.419326],"type":"Point"}
}