{
  "type": "Feature",
  "properties": {
    "addr:full":"5693 Ave 304 Visalia CA 93291",
    "addr:housenumber":"5693",
    "addr:postcode":"93291",
    "addr:street":"Ave 304",
    "iso:country":"US",
    "sg:address":"5693 Ave 304",
    "sg:city":"Visalia",
    "sg:classifiers":[
        {
            "category":"Farming",
            "subcategory":"Orchard",
            "type":"Manufacturing & Wholesale Goods"
        }
    ],
    "sg:phone":"+1 559 651 0932",
    "sg:postcode":"93291",
    "sg:province":"CA",
    "sg:tags":[
        "fruit",
        "tree"
    ],
    "wof:name":"Hershel T Clevenger",
    "wof:placetype":"venue"
},
  "geometry": {"coordinates":[-119.446482,36.341658],"type":"Point"}
}