{
  "type": "Feature",
  "properties": {
    "iso:country":"US",
    "sg:address":"201 E Sierra Ave",
    "sg:city":"Cotati",
    "sg:classifiers":[
        {
            "category":"Restaurant",
            "type":"Food & Drink"
        }
    ],
    "sg:phone":"+1 707 793 9312",
    "sg:postcode":"94931",
    "sg:province":"CA",
    "sg:tags":[
        "sandwich"
    ],
    "wof:name":"Cafe Med",
    "wof:placetype":"venue"
},
  "geometry": {"coordinates":[-122.705113,38.328956],"type":"Point"}
}