{
  "type": "Feature",
  "properties": {
    "addr:full":"3135 Verdugo Road Los Angeles CA 90065",
    "addr:housenumber":"3135",
    "addr:postcode":"90065",
    "addr:street":"Verdugo Road",
    "iso:country":"US",
    "sg:address":"3135 Verdugo Road",
    "sg:city":"Los Angeles",
    "sg:classifiers":[
        {
            "category":"Building & Trades",
            "subcategory":"Plumbing",
            "type":"Services"
        }
    ],
    "sg:phone":"+1 323 257 0202",
    "sg:postcode":"90065",
    "sg:province":"CA",
    "sg:website":"www.picassoplumbing.com",
    "wof:name":"Picasso Plumbing",
    "wof:placetype":"venue"
},
  "geometry": {"coordinates":[-118.237471,34.108398],"type":"Point"}
}