{
  "type": "Feature",
  "properties": {
    "iso:country":"US",
    "sg:address":"17275 Tamara Ln",
    "sg:city":"Watsonville",
    "sg:classifiers":[
        {
            "category":"Building & Trades",
            "subcategory":"Cleaning & Sanitation",
            "type":"Services"
        },
        {
            "category":"Home & Garden",
            "subcategory":"Carpets & Floor Coverings",
            "type":"Retail Goods"
        }
    ],
    "sg:phone":"+1 831 786 0456",
    "sg:postcode":"95076",
    "sg:province":"CA",
    "sg:tags":[
        "carpeting"
    ],
    "sg:website":"www.mbs-carpetcleaning.com",
    "wof:name":"MBS Carpet Cleaning",
    "wof:placetype":"venue"
},
  "geometry": {"coordinates":[-121.66986900000001,36.842131],"type":"Point"}
}