{
  "type": "Feature",
  "properties": {
    "addr:full":"423 30th St Hermosa Beach CA 90254",
    "addr:housenumber":"423",
    "addr:postcode":"90254",
    "addr:street":"30Th St",
    "iso:country":"US",
    "sg:address":"423 30th St",
    "sg:city":"Hermosa Beach",
    "sg:classifiers":[
        {
            "category":"Real Estate",
            "subcategory":"Real Estate Agent",
            "type":"Services"
        }
    ],
    "sg:phone":"+1 310 379 6655",
    "sg:postcode":"90254",
    "sg:province":"CA",
    "wof:name":"Bay Pacific Properties",
    "wof:placetype":"venue"
},
  "geometry": {"coordinates":[-118.402503,33.876069],"type":"Point"}
}