{
  "type": "Feature",
  "properties": {
    "addr:full":"3103 Falcon St San Diego CA 92103",
    "addr:housenumber":"3103",
    "addr:postcode":"92103",
    "addr:street":"Falcon St",
    "iso:country":"US",
    "sg:address":"3103 Falcon St",
    "sg:city":"San Diego",
    "sg:classifiers":[
        {
            "category":"Banks & Credit Unions",
            "subcategory":"Bank",
            "type":"Services"
        }
    ],
    "sg:phone":"+1 619 574 9150",
    "sg:postcode":"92103",
    "sg:province":"CA",
    "sg:tags":[
        "loan"
    ],
    "wof:name":"Loan Processing By Coral",
    "wof:placetype":"venue"
},
  "geometry": {"coordinates":[-117.170357,32.737927],"type":"Point"}
}