{
  "type": "Feature",
  "properties": {
    "iso:country":"US",
    "sg:address":"7083 Riverside Blvd",
    "sg:city":"Sacramento",
    "sg:classifiers":[
        {
            "category":"Wholesale",
            "subcategory":"Non-durable Goods",
            "type":"Manufacturing & Wholesale Goods"
        }
    ],
    "sg:phone":"+1 916 928 9428",
    "sg:postcode":"95831",
    "sg:province":"CA",
    "sg:tags":[
        "dry",
        "goods-wholesale"
    ],
    "wof:name":"Vicki's Beauty Supply",
    "wof:placetype":"venue"
},
  "geometry": {"coordinates":[-121.551783,38.49783],"type":"Point"}
}