{
  "type": "Feature",
  "properties": {
    "addr:full":"1501 Corporate Dr Ste B8 Ladera Ranch CA 92694",
    "addr:housenumber":"1501",
    "addr:postcode":"92694",
    "addr:street":"Corporate Dr Ste B8",
    "iso:country":"US",
    "sg:address":"1501 Corporate Dr Ste B8",
    "sg:city":"Ladera Ranch",
    "sg:classifiers":[
        {
            "category":"Personal",
            "subcategory":"Beauty Salon",
            "type":"Services"
        }
    ],
    "sg:phone":"+1 949 365 1012",
    "sg:postcode":"92694",
    "sg:province":"CA",
    "sg:tags":[
        "hair"
    ],
    "sg:website":"www.therighthairsalon.com",
    "wof:name":"The Right Hair",
    "wof:placetype":"venue"
},
  "geometry": {"coordinates":[-117.629137,33.556351],"type":"Point"}
}