{
  "type": "Feature",
  "properties": {
    "iso:country":"US",
    "sg:address":"1063 S Railroad Ave",
    "sg:city":"San Mateo",
    "sg:classifiers":[
        {
            "category":"Retail",
            "subcategory":"Auto Repair",
            "type":"Services"
        }
    ],
    "sg:phone":"+1 650 349 4404",
    "sg:postcode":"94402",
    "sg:province":"CA",
    "wof:name":"MGS Auto Service",
    "wof:placetype":"venue"
},
  "geometry": {"coordinates":[-122.31501900000001,37.560218],"type":"Point"}
}