{
  "type": "Feature",
  "properties": {
    "addr:full":"1643 Stephanie Way Ceres CA 95307",
    "addr:housenumber":"1643",
    "addr:postcode":"95307",
    "addr:street":"Stephanie Way",
    "iso:country":"US",
    "sg:address":"1643 Stephanie Way",
    "sg:city":"Ceres",
    "sg:classifiers":[
        {
            "category":"Recreation",
            "type":"Entertainment"
        }
    ],
    "sg:phone":"+1 209 968 0130",
    "sg:postcode":"95307",
    "sg:province":"CA",
    "sg:tags":[
        "concessionaire"
    ],
    "wof:name":"Top Dog Delicious Hot Dogs",
    "wof:placetype":"venue"
},
  "geometry": {"coordinates":[-120.969132,37.605591],"type":"Point"}
}