{
  "type": "Feature",
  "properties": {
    "iso:country":"US",
    "sg:address":"1205 Pine Street",
    "sg:city":"San Francisco",
    "sg:classifiers":[
        {
            "category":"Retail",
            "subcategory":"Laundry & Dry Cleaning",
            "type":"Services"
        }
    ],
    "sg:phone":"+1 415 922 1928",
    "sg:postcode":"94109",
    "sg:province":"CA",
    "wof:name":"Cheuks Cleaners",
    "wof:placetype":"venue"
},
  "geometry": {"coordinates":[-122.416,37.7901],"type":"Point"}
}