{
  "type": "Feature",
  "properties": {
    "iso:country":"US",
    "sg:address":"1902 Westwood Blvd. Suite 209",
    "sg:city":"Los Angeles",
    "sg:classifiers":[
        {
            "category":"Professional",
            "type":"Services"
        }
    ],
    "sg:phone":"+1 310 475 6960",
    "sg:postcode":"90025",
    "sg:province":"CA",
    "wof:name":"Star Fire Protection Inc.",
    "wof:placetype":"venue"
},
  "geometry": {"coordinates":[-118.43529700000001,34.048015],"type":"Point"}
}