{
  "type": "Feature",
  "properties": {
    "addr:full":"39146 Wild Bird Ln Cassel CA 96016",
    "addr:housenumber":"39146",
    "addr:postcode":"96016",
    "addr:street":"Wild Bird Ln",
    "iso:country":"US",
    "sg:address":"39146 Wild Bird Ln",
    "sg:city":"Cassel",
    "sg:classifiers":[
        {
            "category":"Freight",
            "type":"Transportation"
        }
    ],
    "sg:phone":"+1 530 335 2416",
    "sg:postcode":"96016",
    "sg:province":"CA",
    "sg:tags":[
        "trucking"
    ],
    "wof:name":"Bill Hanan Trucking",
    "wof:placetype":"venue"
},
  "geometry": {"coordinates":[-121.589343,40.975065],"type":"Point"}
}