{
  "type": "Feature",
  "properties": {
    "iso:country":"US",
    "sg:address":"150 Post St",
    "sg:city":"San Francisco",
    "sg:classifiers":[
        {
            "category":"Shopping",
            "subcategory":"Clothing, Apparel, & Fashions",
            "type":"Retail Goods"
        }
    ],
    "sg:phone":"+1 415 397 4500",
    "sg:postcode":"94108",
    "sg:province":"CA",
    "sg:website":"www.brooksbrothers.com",
    "wof:name":"Brooks Brothers",
    "wof:placetype":"venue"
},
  "geometry": {"coordinates":[-122.405134,37.788784],"type":"Point"}
}