{
  "type": "Feature",
  "properties": {
    "iso:country":"US",
    "sg:address":"4538 Flores Ave",
    "sg:city":"Rohnert Park",
    "sg:classifiers":[
        {
            "category":"Professional",
            "type":"Services"
        }
    ],
    "sg:phone":"+1 707 584 0752",
    "sg:postcode":"94928",
    "sg:province":"CA",
    "wof:name":"Improved Piping Products",
    "wof:placetype":"venue"
},
  "geometry": {"coordinates":[-122.706163,38.368055],"type":"Point"}
}