{
  "type": "Feature",
  "properties": {
    "iso:country":"US",
    "sg:address":"205 S West St",
    "sg:city":"Visalia",
    "sg:classifiers":[
        {
            "category":"Health Services",
            "subcategory":"Doctor",
            "type":"Services"
        }
    ],
    "sg:phone":"+1 559 582 0453",
    "sg:postcode":"93291",
    "sg:province":"CA",
    "sg:tags":[
        "physician",
        "surgeon"
    ],
    "wof:name":"Dean J Limbert MD",
    "wof:placetype":"venue"
},
  "geometry": {"coordinates":[-119.29666,36.328815],"type":"Point"}
}