{
  "type": "Feature",
  "properties": {
    "addr:full":"555 Oakdale St Folsom CA 95630",
    "addr:housenumber":"555",
    "addr:postcode":"95630",
    "addr:street":"Oakdale St",
    "iso:country":"US",
    "sg:address":"555 Oakdale St",
    "sg:city":"Folsom",
    "sg:classifiers":[
        {
            "category":"Professional",
            "subcategory":"Accounting & Tax Preparation",
            "type":"Services"
        }
    ],
    "sg:phone":"+1 916 294 0200",
    "sg:postcode":"95630",
    "sg:province":"CA",
    "sg:tags":[
        "bookkeeping",
        "return",
        "accountants-certified",
        "preparation-business",
        "public"
    ],
    "sg:website":"http://www.msncpa.net",
    "wof:name":"Nord & Associates CPA's",
    "wof:placetype":"venue"
},
  "geometry": {"coordinates":[-121.18122,38.672392],"type":"Point"}
}