{
  "type": "Feature",
  "properties": {
    "iso:country":"US",
    "sg:address":"1952 Cumberland Dr",
    "sg:city":"West Covina",
    "sg:classifiers":[
        {
            "category":"Professional",
            "type":"Services"
        }
    ],
    "sg:phone":"+1 213 892 1838",
    "sg:postcode":"91792",
    "sg:province":"CA",
    "wof:name":"Rosa Rodriguez",
    "wof:placetype":"venue"
},
  "geometry": {"coordinates":[-117.91387400000001,34.038212],"type":"Point"}
}