{
  "type": "Feature",
  "properties": {
    "iso:country":"US",
    "sg:address":"14536 Brookhurst Street",
    "sg:city":"Westminster",
    "sg:classifiers":[
        {
            "category":"Health Services",
            "subcategory":"Doctor",
            "type":"Services"
        }
    ],
    "sg:phone":"+1 714 775 8383",
    "sg:postcode":"92683",
    "sg:province":"CA",
    "wof:name":"Tran Hanh MD-Uci Medical Group",
    "wof:placetype":"venue"
},
  "geometry": {"coordinates":[-117.95482199999999,33.751884],"type":"Point"}
}