{
  "type": "Feature",
  "properties": {
    "addr:full":"642 Moulton Ave Los Angeles CA 90031",
    "addr:housenumber":"642",
    "addr:postcode":"90031",
    "addr:street":"Moulton Ave",
    "iso:country":"US",
    "sg:address":"642 Moulton Ave",
    "sg:city":"Los Angeles",
    "sg:classifiers":[
        {
            "category":"Professional",
            "subcategory":"Art Services",
            "type":"Services"
        }
    ],
    "sg:phone":"+1 323 276 9720",
    "sg:postcode":"90031",
    "sg:province":"CA",
    "sg:tags":[
        "graphic",
        "designer"
    ],
    "wof:name":"Richard Ankrom",
    "wof:placetype":"venue"
},
  "geometry": {"coordinates":[-118.219937,34.063816],"type":"Point"}
}