{
  "type": "Feature",
  "properties": {
    "iso:country":"US",
    "sg:address":"477 Canyon Vista Dr",
    "sg:city":"Newbury Park",
    "sg:classifiers":[
        {
            "category":"Professional",
            "type":"Services"
        }
    ],
    "sg:phone":"+1 805 499 4756",
    "sg:postcode":"91320",
    "sg:province":"CA",
    "wof:name":"P M I",
    "wof:placetype":"venue"
},
  "geometry": {"coordinates":[-118.908665,34.187805],"type":"Point"}
}