{
  "type": "Feature",
  "properties": {
    "iso:country":"US",
    "sg:address":"25570 The Old Rd",
    "sg:city":"Stevenson Ranch",
    "sg:classifiers":[
        {
            "category":"Shopping",
            "subcategory":"Stationery & Office Supplies",
            "type":"Retail Goods"
        }
    ],
    "sg:phone":"+1 661 286 2700",
    "sg:postcode":"91381",
    "sg:province":"CA",
    "sg:tags":[
        "printing"
    ],
    "wof:name":"Staples the Office Superstore",
    "wof:placetype":"venue"
},
  "geometry": {"coordinates":[-118.57199900000001,34.384602],"type":"Point"}
}