{
  "type": "Feature",
  "properties": {
    "addr:full":"1523 E Colorado St Glendale CA 91205",
    "addr:housenumber":"1523",
    "addr:postcode":"91205",
    "addr:street":"E Colorado St",
    "iso:country":"US",
    "sg:address":"1523 E Colorado St",
    "sg:city":"Glendale",
    "sg:classifiers":[
        {
            "category":"Travel",
            "subcategory":"Hotels & Motels",
            "type":"Entertainment"
        }
    ],
    "sg:phone":"+1 818 244 8195",
    "sg:postcode":"91205",
    "sg:province":"CA",
    "wof:name":"Manhattan Motel",
    "wof:placetype":"venue"
},
  "geometry": {"coordinates":[-118.231003,34.142899],"type":"Point"}
}