{
  "type": "Feature",
  "properties": {
    "iso:country":"US",
    "sg:address":"710 Lawrence Expressway",
    "sg:city":"Santa Clara",
    "sg:classifiers":[
        {
            "category":"Health Services",
            "subcategory":"Doctor",
            "type":"Services"
        }
    ],
    "sg:phone":"+1 408 851 1000",
    "sg:postcode":"95051",
    "sg:province":"CA",
    "wof:name":"Dr. Sheeja Das",
    "wof:placetype":"venue"
},
  "geometry": {"coordinates":[-121.99578099999999,37.33525],"type":"Point"}
}