{
  "type": "Feature",
  "properties": {
    "addr:full":"29 Bell Way Ventura CA 93001",
    "addr:housenumber":"29",
    "addr:postcode":"93001",
    "addr:street":"Bell Way",
    "iso:country":"US",
    "sg:address":"29 Bell Way",
    "sg:city":"Ventura",
    "sg:classifiers":[
        {
            "category":"Real Estate",
            "subcategory":"Real Estate Operator",
            "type":"Services"
        }
    ],
    "sg:phone":"+1 805 643 4278",
    "sg:postcode":"93001",
    "sg:province":"CA",
    "sg:tags":[
        "mobile",
        "home",
        "site"
    ],
    "wof:name":"Bell Way Trailer Park",
    "wof:placetype":"venue"
},
  "geometry": {"coordinates":[-119.30129599999999,34.291846],"type":"Point"}
}