{
  "type": "Feature",
  "properties": {
    "addr:full":"27632 el Lazo Laguna Niguel CA 92677",
    "addr:housenumber":"27632",
    "addr:postcode":"92677",
    "addr:street":"El Lazo",
    "iso:country":"US",
    "sg:address":"27632 el Lazo",
    "sg:city":"Laguna Niguel",
    "sg:classifiers":[
        {
            "category":"Organizations",
            "subcategory":"Religious Organization",
            "type":"Services"
        }
    ],
    "sg:phone":"+1 949 425 3787",
    "sg:postcode":"92677",
    "sg:province":"CA",
    "sg:tags":[
        "church"
    ],
    "wof:name":"Vineyard Community Church",
    "wof:placetype":"venue"
},
  "geometry": {"coordinates":[-117.709565,33.563066],"type":"Point"}
}