{
  "type": "Feature",
  "properties": {
    "addr:full":"237 N L St Tulare CA 93274",
    "addr:housenumber":"237",
    "addr:postcode":"93274",
    "addr:street":"N L St",
    "iso:country":"US",
    "sg:address":"237 N L St",
    "sg:city":"Tulare",
    "sg:classifiers":[
        {
            "category":"Restaurant",
            "type":"Food & Drink"
        }
    ],
    "sg:phone":"+1 559 685 0455",
    "sg:postcode":"93274",
    "sg:province":"CA",
    "wof:name":"Hazel's Kitchen",
    "wof:placetype":"venue"
},
  "geometry": {"coordinates":[-119.34541,36.210292],"type":"Point"}
}