{
  "type": "Feature",
  "properties": {
    "iso:country":"US",
    "sg:address":"100 N Glendora Ave",
    "sg:city":"Glendora",
    "sg:classifiers":[
        {
            "category":"Banks & Credit Unions",
            "subcategory":"Investment Brokerage",
            "type":"Services"
        }
    ],
    "sg:phone":"+1 626 914 4929",
    "sg:postcode":"91741",
    "sg:province":"CA",
    "sg:tags":[
        "commodity"
    ],
    "wof:name":"20 20 Trading Co",
    "wof:placetype":"venue"
},
  "geometry": {"coordinates":[-117.86544000000001,34.136678],"type":"Point"}
}