{
  "type": "Feature",
  "properties": {
    "addr:full":"1720 W Ball Rd Anaheim CA 92804",
    "addr:housenumber":"1720",
    "addr:postcode":"92804",
    "addr:street":"W Ball Rd",
    "iso:country":"US",
    "sg:address":"1720 W Ball Rd",
    "sg:city":"Anaheim",
    "sg:classifiers":[
        {
            "category":"Real Estate",
            "subcategory":"Real Estate Agent",
            "type":"Services"
        }
    ],
    "sg:phone":"+1 714 533 2072",
    "sg:postcode":"92804",
    "sg:province":"CA",
    "sg:tags":[
        "management"
    ],
    "sg:website":"www.barkermanagement.com",
    "wof:name":"Barker Management Inc",
    "wof:placetype":"venue"
},
  "geometry": {"coordinates":[-117.942436,33.81785],"type":"Point"}
}