{
  "type": "Feature",
  "properties": {
    "addr:full":"5829 Preston Ave Livermore CA 94551",
    "addr:housenumber":"5829",
    "addr:postcode":"94551",
    "addr:street":"Preston Ave",
    "iso:country":"US",
    "sg:address":"5829 Preston Ave",
    "sg:city":"Livermore",
    "sg:classifiers":[
        {
            "category":"Manufacturing",
            "subcategory":"Metals",
            "type":"Manufacturing & Wholesale Goods"
        },
        {
            "category":"Home & Garden",
            "subcategory":"Building Materials",
            "type":"Retail Goods"
        },
        {
            "category":"Building & Trades",
            "subcategory":"Construction",
            "type":"Services"
        },
        {
            "category":"Military Area",
            "subcategory":"Armory",
            "type":"Public Place"
        }
    ],
    "sg:phone":"+1 925 373 0149",
    "sg:postcode":"94551",
    "sg:province":"CA",
    "sg:tags":[
        "repair",
        "door",
        "fence",
        "work",
        "contractor",
        "garage",
        "opener",
        "iron",
        "fence-sales"
    ],
    "sg:website":"http://www.lafayetteiron.com",
    "wof:name":"Lafayette Iron Works & Co. Inc.",
    "wof:placetype":"venue"
},
  "geometry": {"coordinates":[-121.72463399999999,37.705367],"type":"Point"}
}