{
  "type": "Feature",
  "properties": {
    "iso:country":"US",
    "sg:address":"15380 Beach Blvd Ste B",
    "sg:city":"Westminster",
    "sg:classifiers":[
        {
            "category":"Restaurant",
            "type":"Food & Drink"
        }
    ],
    "sg:phone":"+1 714 898 5400",
    "sg:postcode":"92683",
    "sg:province":"CA",
    "wof:name":"Lynda Sandwich",
    "wof:placetype":"venue"
},
  "geometry": {"coordinates":[-117.988939,33.739335],"type":"Point"}
}