{
  "type": "Feature",
  "properties": {
    "iso:country":"US",
    "sg:address":"2030 Nottingham Dr",
    "sg:city":"Fairfield",
    "sg:classifiers":[
        {
            "category":"Building & Trades",
            "subcategory":"Landscaping Services",
            "type":"Services"
        }
    ],
    "sg:phone":"+1 707 429 3487",
    "sg:postcode":"94533",
    "sg:province":"CA",
    "sg:tags":[
        "lawn",
        "maintenance",
        "grounds"
    ],
    "wof:name":"Evergreen Gardening Servi",
    "wof:placetype":"venue"
},
  "geometry": {"coordinates":[-122.046211,38.267605],"type":"Point"}
}