{
  "type": "Feature",
  "properties": {
    "addr:full":"1400 Shattuck Ave Berkeley CA 94709",
    "addr:housenumber":"1400",
    "addr:postcode":"94709",
    "addr:street":"Shattuck Ave",
    "iso:country":"US",
    "sg:address":"1400 Shattuck Ave",
    "sg:city":"Berkeley",
    "sg:classifiers":[
        {
            "category":"Shopping",
            "subcategory":"Computers & Home Electronics",
            "type":"Retail Goods"
        }
    ],
    "sg:phone":"+1 415 491 1544",
    "sg:postcode":"94709",
    "sg:province":"CA",
    "sg:tags":[
        "software"
    ],
    "sg:website":"www.mind-control.com",
    "wof:name":"Mind Control Software",
    "wof:placetype":"venue"
},
  "geometry": {"coordinates":[-122.269367,37.881074],"type":"Point"}
}