{
  "type": "Feature",
  "properties": {
    "iso:country":"US",
    "sg:address":"7881 Sandholdt Rd B Dock",
    "sg:city":"Moss Landing",
    "sg:classifiers":[
        {
            "category":"Recreation",
            "subcategory":"Boat Charter",
            "type":"Entertainment"
        },
        {
            "category":"Landmark",
            "subcategory":"Tourist Information",
            "type":"Public Place"
        }
    ],
    "sg:phone":"+1 831 392 7867",
    "sg:postcode":"95039",
    "sg:province":"CA",
    "sg:tags":[
        "boating",
        "tour"
    ],
    "sg:website":"www.westwindcharter.com",
    "wof:name":"West Wind Charter",
    "wof:placetype":"venue"
},
  "geometry": {"coordinates":[-121.786456,36.799379],"type":"Point"}
}