{
  "type": "Feature",
  "properties": {
    "addr:full":"13906 York Ave Poway CA 92064",
    "addr:housenumber":"13906",
    "addr:postcode":"ca 92064",
    "addr:street":"York Ave",
    "iso:country":"US",
    "sg:address":"13906 York Ave",
    "sg:city":"Poway",
    "sg:classifiers":[
        {
            "category":"Manufacturing",
            "subcategory":"Toys & Sporting Goods",
            "type":"Manufacturing & Wholesale Goods"
        }
    ],
    "sg:phone":"+1 858 486 2853",
    "sg:postcode":"92064",
    "sg:province":"CA",
    "sg:tags":[
        "mfg"
    ],
    "wof:name":"Village Skateboards",
    "wof:placetype":"venue"
},
  "geometry": {"coordinates":[-117.039017,32.966539],"type":"Point"}
}