{
  "type": "Feature",
  "properties": {
    "iso:country":"US",
    "sg:address":"3625 Del Amo Blvd Ste 245",
    "sg:city":"Torrance",
    "sg:classifiers":[
        {
            "category":"Professional",
            "subcategory":"Advertising",
            "type":"Services"
        }
    ],
    "sg:phone":"+1 310 371 8408",
    "sg:postcode":"90503",
    "sg:province":"CA",
    "sg:tags":[
        "marketing"
    ],
    "sg:website":"www.miwgroup.com",
    "wof:name":"MIW Marketing and Consulting Group",
    "wof:placetype":"venue"
},
  "geometry": {"coordinates":[-118.350348,33.849924],"type":"Point"}
}