{
  "type": "Feature",
  "properties": {
    "iso:country":"US",
    "sg:address":"1384 E F St",
    "sg:city":"Oakdale",
    "sg:classifiers":[
        {
            "category":"Education",
            "subcategory":"School",
            "type":"Public Place"
        }
    ],
    "sg:phone":"+1 209 847 7003",
    "sg:postcode":"95361",
    "sg:province":"CA",
    "wof:name":"Oakdale High School Transportation",
    "wof:placetype":"venue"
},
  "geometry": {"coordinates":[-120.833989,37.771568],"type":"Point"}
}