{
  "type": "Feature",
  "properties": {
    "iso:country":"US",
    "sg:address":"582 Market St",
    "sg:city":"San Francisco",
    "sg:classifiers":[
        {
            "category":"Professional",
            "subcategory":"Lawyer & Legal Services",
            "type":"Services"
        }
    ],
    "sg:phone":"+1 415 835 3789",
    "sg:postcode":"94104",
    "sg:province":"CA",
    "sg:tags":[
        "attorney"
    ],
    "wof:name":"Marita K Marshall Law Office",
    "wof:placetype":"venue"
},
  "geometry": {"coordinates":[-122.401486,37.789319],"type":"Point"}
}