{
  "type": "Feature",
  "properties": {
    "addr:full":"9925 Choiceana Ave Hesperia CA 92345",
    "addr:housenumber":"9925",
    "addr:postcode":"92345",
    "addr:street":"Choiceana Ave",
    "iso:country":"US",
    "sg:address":"9925 Choiceana Ave",
    "sg:city":"Hesperia",
    "sg:classifiers":[
        {
            "category":"Real Estate",
            "subcategory":"Real Estate Services",
            "type":"Services"
        },
        {
            "category":"Real Estate",
            "subcategory":"Real Estate Agent",
            "type":"Services"
        }
    ],
    "sg:phone":"+1 760 949 1829",
    "sg:postcode":"92345",
    "sg:province":"CA",
    "sg:tags":[
        "buyer",
        "broker"
    ],
    "sg:website":"http://www.realtyworld-tc.com",
    "wof:name":"Realty World Town & Country Partners",
    "wof:placetype":"venue"
},
  "geometry": {"coordinates":[-117.250685,34.428023],"type":"Point"}
}