{
  "type": "Feature",
  "properties": {
    "iso:country":"US",
    "sg:address":"9527 Bexley Dr",
    "sg:city":"Pico Rivera",
    "sg:classifiers":[
        {
            "category":"Personal",
            "subcategory":"Tattoo Parlor",
            "type":"Services"
        }
    ],
    "sg:phone":"+1 562 556 1282",
    "sg:postcode":"90660",
    "sg:province":"CA",
    "sg:website":"www.facebook.com",
    "wof:name":"Never Die Tattoos",
    "wof:placetype":"venue"
},
  "geometry": {"coordinates":[-118.078676,33.991929],"type":"Point"}
}