{
  "type": "Feature",
  "properties": {
    "iso:country":"US",
    "sg:address":"5662 Crest Ave",
    "sg:city":"Riverside",
    "sg:classifiers":[
        {
            "category":"Organizations",
            "subcategory":"Religious Organization",
            "type":"Services"
        }
    ],
    "sg:phone":"+1 951 354 8113",
    "sg:postcode":"92503",
    "sg:province":"CA",
    "sg:tags":[
        "church"
    ],
    "wof:name":"Arlington Apostolic Church",
    "wof:placetype":"venue"
},
  "geometry": {"coordinates":[-117.474757,33.938153],"type":"Point"}
}