{
  "type": "Feature",
  "properties": {
    "addr:full":"4324 Florence Avenue Bell CA 90201",
    "addr:housenumber":"4324",
    "addr:postcode":"90201",
    "addr:street":"Florence Avenue",
    "iso:country":"US",
    "sg:address":"4324 Florence Avenue",
    "sg:city":"Bell",
    "sg:classifiers":[
        {
            "category":"Real Estate",
            "subcategory":"Real Estate Services",
            "type":"Services"
        },
        {
            "category":"Real Estate",
            "subcategory":"Developer",
            "type":"Services"
        }
    ],
    "sg:phone":"+1 323 771 3377",
    "sg:postcode":"90201",
    "sg:province":"CA",
    "sg:tags":[
        "management",
        "property"
    ],
    "wof:name":"Senior Citizens Housing Development Corporation of Bell",
    "wof:placetype":"venue"
},
  "geometry": {"coordinates":[-118.190622,33.970574],"type":"Point"}
}