{
  "type": "Feature",
  "properties": {
    "addr:full":"9560 Wilshire Blvd Beverly Hills CA 90212",
    "addr:housenumber":"9560",
    "addr:postcode":"90212",
    "addr:street":"Wilshire Blvd",
    "iso:country":"US",
    "sg:address":"9560 Wilshire Blvd",
    "sg:city":"Beverly Hills",
    "sg:classifiers":[
        {
            "category":"Shopping",
            "subcategory":"Shoes",
            "type":"Retail Goods"
        }
    ],
    "sg:phone":"+1 310 275 9998",
    "sg:postcode":"90212",
    "sg:province":"CA",
    "sg:tags":[
        "store"
    ],
    "sg:website":"www.jenlanedp.com",
    "wof:name":"Nike Town",
    "wof:placetype":"venue"
},
  "geometry": {"coordinates":[-118.402023,34.066939],"type":"Point"}
}