{
  "type": "Feature",
  "properties": {
    "iso:country":"US",
    "sg:address":"85 Federal St",
    "sg:city":"San Francisco",
    "sg:classifiers":[
        {
            "category":"Building & Trades",
            "subcategory":"Construction",
            "type":"Services"
        }
    ],
    "sg:phone":"+1 415 544 8150",
    "sg:postcode":"94107",
    "sg:province":"CA",
    "sg:tags":[
        "elevator"
    ],
    "sg:website":"www.thyssenkruppelevator.com",
    "wof:name":"Thyssen Krupp Elevator",
    "wof:placetype":"venue"
},
  "geometry": {"coordinates":[-122.391744,37.783854],"type":"Point"}
}