{
  "type": "Feature",
  "properties": {
    "iso:country":"US",
    "sg:address":"8065 Webb Ave",
    "sg:city":"North Hollywood",
    "sg:classifiers":[
        {
            "category":"Cinema",
            "subcategory":"Movie Rental",
            "type":"Entertainment"
        }
    ],
    "sg:phone":"+1 818 504 6438",
    "sg:postcode":"91605",
    "sg:province":"CA",
    "sg:tags":[
        "leasing",
        "video",
        "disc",
        "tape"
    ],
    "wof:name":"Hollywood Video",
    "wof:placetype":"venue"
},
  "geometry": {"coordinates":[-118.390203,34.21813],"type":"Point"}
}