{
  "type": "Feature",
  "properties": {
    "iso:country":"US",
    "sg:address":"22133 S Vermont Ave",
    "sg:city":"Torrance",
    "sg:classifiers":[
        {
            "category":"Home & Garden",
            "subcategory":"Carpets & Floor Coverings",
            "type":"Retail Goods"
        }
    ],
    "sg:phone":"+1 310 787 0704",
    "sg:postcode":"90502",
    "sg:province":"CA",
    "sg:tags":[
        "linoleum",
        "material",
        "installation",
        "rug",
        "carpeting"
    ],
    "wof:name":"Westchester Carpets",
    "wof:placetype":"venue"
},
  "geometry": {"coordinates":[-118.290001,33.826401],"type":"Point"}
}