{
  "type": "Feature",
  "properties": {
    "addr:full":"11039 Shoemaker Ave Santa Fe Springs CA 90650",
    "addr:housenumber":"11039",
    "addr:postcode":"90650",
    "addr:street":"Shoemaker Ave",
    "iso:country":"US",
    "sg:address":"11039 Shoemaker Ave",
    "sg:city":"Santa Fe Springs",
    "sg:classifiers":[
        {
            "category":"Retail",
            "subcategory":"Auto Repair",
            "type":"Services"
        }
    ],
    "sg:phone":"+1 562 697 6462",
    "sg:postcode":"90650",
    "sg:province":"CA",
    "sg:tags":[
        "truck"
    ],
    "wof:name":"Fodor's Diesel Svc",
    "wof:placetype":"venue"
},
  "geometry": {"coordinates":[-118.05528099999999,33.931059],"type":"Point"}
}