{
  "type": "Feature",
  "properties": {
    "iso:country":"US",
    "sg:address":"1402 McGaw Ave",
    "sg:city":"Irvine",
    "sg:classifiers":[
        {
            "category":"Wholesale",
            "subcategory":"Hardware",
            "type":"Manufacturing & Wholesale Goods"
        }
    ],
    "sg:phone":"+1 949 851 2298",
    "sg:postcode":"92614",
    "sg:province":"CA",
    "sg:tags":[
        "fastener"
    ],
    "wof:name":"Emhart Heli-Coil Co",
    "wof:placetype":"venue"
},
  "geometry": {"coordinates":[-117.852881,33.698097],"type":"Point"}
}