{
  "type": "Feature",
  "properties": {
    "iso:country":"US",
    "sg:address":"70 el Camino Ave",
    "sg:city":"San Rafael",
    "sg:classifiers":[
        {
            "category":"Building & Trades",
            "subcategory":"Construction",
            "type":"Services"
        }
    ],
    "sg:phone":"+1 415 457 6075",
    "sg:postcode":"94901",
    "sg:province":"CA",
    "sg:tags":[
        "contractor"
    ],
    "wof:name":"Roa Construction",
    "wof:placetype":"venue"
},
  "geometry": {"coordinates":[-122.54089500000001,37.974841],"type":"Point"}
}