{
  "type": "Feature",
  "properties": {
    "iso:country":"US",
    "sg:address":"11165 Kelly Ct",
    "sg:city":"Grass Valley",
    "sg:classifiers":[
        {
            "category":"Manufacturing",
            "subcategory":"Metals",
            "type":"Manufacturing & Wholesale Goods"
        }
    ],
    "sg:phone":"+1 530 477 6055",
    "sg:postcode":"95949",
    "sg:province":"CA",
    "sg:tags":[
        "engraver"
    ],
    "wof:name":"Movin N Groovin",
    "wof:placetype":"venue"
},
  "geometry": {"coordinates":[-121.066121,39.110127],"type":"Point"}
}