{
  "type": "Feature",
  "properties": {
    "iso:country":"US",
    "sg:address":"1843 Buena Vista Ave",
    "sg:city":"Livermore",
    "sg:classifiers":[
        {
            "category":"Professional",
            "subcategory":"Secretarial Services",
            "type":"Services"
        }
    ],
    "sg:phone":"+1 925 449 5459",
    "sg:postcode":"94550",
    "sg:province":"CA",
    "sg:tags":[
        "convention",
        "court",
        "reporter"
    ],
    "wof:name":"Williams Reporting Svc",
    "wof:placetype":"venue"
},
  "geometry": {"coordinates":[-121.73534100000001,37.675577],"type":"Point"}
}