{
  "type": "Feature",
  "properties": {
    "iso:country":"US",
    "sg:address":"12785 Murphy Ave",
    "sg:city":"San Martin",
    "sg:classifiers":[
        {
            "category":"Building & Trades",
            "subcategory":"Pest Control",
            "type":"Services"
        }
    ],
    "sg:phone":"+1 408 686 1660",
    "sg:postcode":"95046",
    "sg:province":"CA",
    "wof:name":"A Wild West Pest Control Svc",
    "wof:placetype":"venue"
},
  "geometry": {"coordinates":[-121.601423,37.081017],"type":"Point"}
}