{
  "type": "Feature",
  "properties": {
    "iso:country":"US",
    "sg:address":"5714 Mission Blvd",
    "sg:city":"Riverside",
    "sg:classifiers":[
        {
            "category":"Shopping",
            "subcategory":"Gifts & Souvenirs",
            "type":"Retail Goods"
        }
    ],
    "sg:phone":"+1 951 369 0978",
    "sg:postcode":"92509",
    "sg:province":"CA",
    "sg:tags":[
        "shop"
    ],
    "wof:name":"Concept 2000",
    "wof:placetype":"venue"
},
  "geometry": {"coordinates":[-117.411969,33.999496],"type":"Point"}
}