{
  "type": "Feature",
  "properties": {
    "addr:full":"1431 S Main St Willits CA 95490",
    "addr:housenumber":"1431",
    "addr:postcode":"95490",
    "addr:street":"S Main St",
    "iso:country":"US",
    "sg:address":"1431 S Main St",
    "sg:city":"Willits",
    "sg:classifiers":[
        {
            "category":"Health Services",
            "subcategory":"Health Practitioner",
            "type":"Services"
        }
    ],
    "sg:phone":"+1 707 459 6772",
    "sg:postcode":"95490",
    "sg:province":"CA",
    "sg:tags":[
        "therapist",
        "physical"
    ],
    "wof:name":"Brooktrails Physical Therapy",
    "wof:placetype":"venue"
},
  "geometry": {"coordinates":[-123.349243,39.396301],"type":"Point"}
}