{
  "type": "Feature",
  "properties": {
    "iso:country":"US",
    "sg:address":"1120 Waterloo Rd",
    "sg:city":"Stockton",
    "sg:classifiers":[
        {
            "category":"Manufacturing",
            "subcategory":"Toys & Sporting Goods",
            "type":"Manufacturing & Wholesale Goods"
        },
        {
            "category":"Shopping",
            "subcategory":"Bicycles & Sporting Goods",
            "type":"Retail Goods"
        }
    ],
    "sg:phone":"+1 209 937 0390",
    "sg:postcode":"95205",
    "sg:province":"CA",
    "sg:tags":[
        "goods-wholesale",
        "manufacturer"
    ],
    "wof:name":"Soccer City",
    "wof:placetype":"venue"
},
  "geometry": {"coordinates":[-121.270752,37.969292],"type":"Point"}
}