{
  "type": "Feature",
  "properties": {
    "addr:full":"19182 Bonner Way Cottonwood CA 96022",
    "addr:postcode":"19182;96022",
    "addr:street":"Bonner Way",
    "iso:country":"US",
    "sg:address":"19182 Bonner Way",
    "sg:city":"Cottonwood",
    "sg:classifiers":[
        {
            "category":"Home & Garden",
            "subcategory":"Home Furnishings",
            "type":"Retail Goods"
        }
    ],
    "sg:phone":"+1 530 527 3077",
    "sg:postcode":"96022",
    "sg:province":"CA",
    "sg:tags":[
        "venetian",
        "blind"
    ],
    "wof:name":"Budget Blinds Of Redbluff",
    "wof:placetype":"venue"
},
  "geometry": {"coordinates":[-122.327547,40.283442],"type":"Point"}
}