{
  "type": "Feature",
  "properties": {
    "iso:country":"US",
    "sg:address":"188 Pheasant Way",
    "sg:city":"Oakley",
    "sg:classifiers":[
        {
            "category":"Professional",
            "subcategory":"Management & Consulting",
            "type":"Services"
        }
    ],
    "sg:phone":"+1 925 625 7630",
    "sg:postcode":"94561",
    "sg:province":"CA",
    "sg:tags":[
        "consultant",
        "construction"
    ],
    "wof:name":"Stauffer Consulting Svc",
    "wof:placetype":"venue"
},
  "geometry": {"coordinates":[-121.687367,37.983676],"type":"Point"}
}