{
  "type": "Feature",
  "properties": {
    "iso:country":"US",
    "sg:address":"12908 W Washington Blvd",
    "sg:city":"Los Angeles",
    "sg:classifiers":[
        {
            "category":"Retail",
            "subcategory":"Auto Repair",
            "type":"Services"
        }
    ],
    "sg:phone":"+1 310 827 3310",
    "sg:postcode":"90066",
    "sg:province":"CA",
    "wof:name":"Zuckett Import Motors",
    "wof:placetype":"venue"
},
  "geometry": {"coordinates":[-118.438004,33.995201],"type":"Point"}
}