{
  "type": "Feature",
  "properties": {
    "iso:country":"US",
    "sg:address":"1010 Wilshire Blvd Ste 1414",
    "sg:city":"Los Angeles",
    "sg:classifiers":[
        {
            "category":"Real Estate",
            "subcategory":"Real Estate Agent",
            "type":"Services"
        }
    ],
    "sg:phone":"+1 213 785 5327",
    "sg:postcode":"90017",
    "sg:province":"CA",
    "sg:website":"www.blackwoodpropertiesinc.com",
    "wof:name":"Blackwood Properties, Inc.",
    "wof:placetype":"venue"
},
  "geometry": {"coordinates":[-118.26196,34.051564],"type":"Point"}
}