{
  "type": "Feature",
  "properties": {
    "iso:country":"US",
    "sg:address":"12751 Moreno Beach Dr",
    "sg:city":"Moreno Valley",
    "sg:classifiers":[
        {
            "category":"Coffee & Tea",
            "type":"Food & Drink"
        }
    ],
    "sg:menulink":"http://www.allmenus.com/ca/perris-valley/118656-starbucks-coffee/menu/",
    "sg:phone":"+1 951 485 6878",
    "sg:postcode":"92555",
    "sg:province":"CA",
    "sg:tags":[
        "american"
    ],
    "wof:name":"Starbucks Coffee",
    "wof:placetype":"venue"
},
  "geometry": {"coordinates":[-117.17617799999999,33.933335],"type":"Point"}
}