{
  "type": "Feature",
  "properties": {
    "iso:country":"US",
    "sg:address":"3836 Spenceville Rd",
    "sg:city":"Wheatland",
    "sg:classifiers":[
        {
            "category":"Banks & Credit Unions",
            "subcategory":"Bank",
            "type":"Services"
        }
    ],
    "sg:phone":"+1 530 633 4232",
    "sg:postcode":"95692",
    "sg:province":"CA",
    "sg:tags":[
        "loan",
        "real estate"
    ],
    "wof:name":"Pioneer Mortgage",
    "wof:placetype":"venue"
},
  "geometry": {"coordinates":[-121.34925200000001,39.074067],"type":"Point"}
}