{
  "type": "Feature",
  "properties": {
    "addr:full":"4940 Triggs St Los Angeles CA 90022",
    "addr:housenumber":"4940",
    "addr:postcode":"90022",
    "addr:street":"Triggs St",
    "iso:country":"US",
    "sg:address":"4940 Triggs St",
    "sg:city":"Los Angeles",
    "sg:classifiers":[
        {
            "category":"Freight",
            "type":"Transportation"
        }
    ],
    "sg:phone":"+1 323 266 1072",
    "sg:postcode":"90022",
    "sg:province":"CA",
    "sg:tags":[
        "forwarder"
    ],
    "wof:name":"Gilbert Air Cargo Inc",
    "wof:placetype":"venue"
},
  "geometry": {"coordinates":[-118.163625,34.012092],"type":"Point"}
}