{
  "type": "Feature",
  "properties": {
    "addr:full":"817 Arnold Dr Martinez CA 94553",
    "addr:housenumber":"817",
    "addr:postcode":"94553",
    "addr:street":"Arnold Dr",
    "iso:country":"US",
    "sg:address":"817 Arnold Dr",
    "sg:city":"Martinez",
    "sg:classifiers":[
        {
            "category":"Shopping",
            "subcategory":"Used Merchandise",
            "type":"Retail Goods"
        },
        {
            "category":"Wholesale",
            "subcategory":"Furniture",
            "type":"Manufacturing & Wholesale Goods"
        }
    ],
    "sg:phone":"+1 925 372 8229",
    "sg:postcode":"94553",
    "sg:province":"CA",
    "sg:tags":[
        "antique"
    ],
    "wof:name":"Antique Connection Inc",
    "wof:placetype":"venue"
},
  "geometry": {"coordinates":[-122.11408299999999,37.997036],"type":"Point"}
}