{
  "type": "Feature",
  "properties": {
    "iso:country":"US",
    "sg:address":"7868 State St",
    "sg:city":"Huntington Park",
    "sg:classifiers":[
        {
            "category":"Professional",
            "type":"Services"
        }
    ],
    "sg:phone":"+1 323 587 5764",
    "sg:postcode":"90255",
    "sg:province":"CA",
    "wof:name":"Alfa Y Omega Suits",
    "wof:placetype":"venue"
},
  "geometry": {"coordinates":[-118.210472,33.965625],"type":"Point"}
}