{
  "type": "Feature",
  "properties": {
    "iso:country":"US",
    "sg:address":"6600 W 4th St",
    "sg:city":"Rio Linda",
    "sg:classifiers":[
        {
            "category":"Building & Trades",
            "subcategory":"Construction",
            "type":"Services"
        }
    ],
    "sg:phone":"+1 916 991 2995",
    "sg:postcode":"95673",
    "sg:province":"CA",
    "sg:tags":[
        "painter"
    ],
    "sg:website":"www.progressive-paint.com",
    "wof:name":"Progressive Painting",
    "wof:placetype":"venue"
},
  "geometry": {"coordinates":[-121.470658,38.691134],"type":"Point"}
}