{
  "type": "Feature",
  "properties": {
    "addr:full":"17831 S Western Ave Gardena CA 90248",
    "addr:housenumber":"17831",
    "addr:postcode":"90248",
    "addr:street":"S Western Ave",
    "iso:country":"US",
    "sg:address":"17831 S Western Ave",
    "sg:city":"Gardena",
    "sg:classifiers":[
        {
            "category":"Manufacturing",
            "subcategory":"Rubber & Plastics",
            "type":"Manufacturing & Wholesale Goods"
        }
    ],
    "sg:phone":"+1 310 532 8020",
    "sg:postcode":"90248",
    "sg:province":"CA",
    "wof:name":"Phillips Brothers Plastics",
    "wof:placetype":"venue"
},
  "geometry": {"coordinates":[-118.309214,33.867744],"type":"Point"}
}