{
  "type": "Feature",
  "properties": {
    "addr:full":"1628 Edgewood Dr Alhambra CA 91803",
    "addr:housenumber":"1628",
    "addr:postcode":"91803",
    "addr:street":"Edgewood Dr",
    "iso:country":"US",
    "sg:address":"1628 Edgewood Dr",
    "sg:city":"Alhambra",
    "sg:classifiers":[
        {
            "category":"Manufacturing",
            "subcategory":"Metals",
            "type":"Manufacturing & Wholesale Goods"
        }
    ],
    "sg:phone":"+1 626 282 0855",
    "sg:postcode":"91803",
    "sg:province":"CA",
    "sg:tags":[
        "tool",
        "mfg"
    ],
    "wof:name":"Snap-On Tools",
    "wof:placetype":"venue"
},
  "geometry": {"coordinates":[-118.14857000000001,34.074338],"type":"Point"}
}