{
  "type": "Feature",
  "properties": {
    "addr:full":"8810 Hemlock St Rancho Cucamonga CA 91730",
    "addr:housenumber":"8810",
    "addr:postcode":"91730",
    "addr:street":"Hemlock St",
    "iso:country":"US",
    "sg:address":"8810 Hemlock St",
    "sg:city":"Rancho Cucamonga",
    "sg:classifiers":[
        {
            "category":"Museum",
            "type":"Entertainment"
        }
    ],
    "sg:phone":"+1 909 989 4970",
    "sg:postcode":"91730",
    "sg:province":"CA",
    "wof:name":"Casa De Rancho Cucamonga",
    "wof:placetype":"venue"
},
  "geometry": {"coordinates":[-117.61041400000001,34.110126],"type":"Point"}
}