{
  "type": "Feature",
  "properties": {
    "addr:full":"15745 Stagg St Van Nuys CA 91406",
    "addr:postcode":"15745;91406",
    "addr:street":"Stagg St",
    "iso:country":"US",
    "sg:address":"15745 Stagg St",
    "sg:city":"Van Nuys",
    "sg:classifiers":[
        {
            "category":"Arts & Performance",
            "subcategory":"Theater",
            "type":"Entertainment"
        }
    ],
    "sg:phone":"+1 818 909 2299",
    "sg:postcode":"91406",
    "sg:province":"CA",
    "sg:tags":[
        "equipment",
        "theatrical",
        "supply"
    ],
    "sg:website":"www.blacksheepent.net",
    "wof:name":"Black Sheep Enterprises",
    "wof:placetype":"venue"
},
  "geometry": {"coordinates":[-118.476309,34.212143],"type":"Point"}
}