{
  "type": "Feature",
  "properties": {
    "iso:country":"US",
    "sg:address":"115 E Gish Rd",
    "sg:city":"San Jose",
    "sg:classifiers":[
        {
            "category":"Social Services",
            "type":"Services"
        }
    ],
    "sg:phone":"+1 408 437 8800",
    "sg:postcode":"95112",
    "sg:province":"CA",
    "sg:tags":[
        "housing",
        "assistance"
    ],
    "sg:website":"www.helpscc.org",
    "wof:name":"Community Technology Alliance",
    "wof:placetype":"venue"
},
  "geometry": {"coordinates":[-121.90721000000001,37.363082],"type":"Point"}
}