{
  "type": "Feature",
  "properties": {
    "addr:full":"414 Jackson St San Francisco CA 94111",
    "addr:housenumber":"414",
    "addr:postcode":"94111",
    "addr:street":"Jackson St",
    "iso:country":"US",
    "sg:address":"414 Jackson St",
    "sg:city":"San Francisco",
    "sg:classifiers":[
        {
            "category":"Professional",
            "subcategory":"Research",
            "type":"Services"
        }
    ],
    "sg:phone":"+1 415 291 0230",
    "sg:postcode":"94111",
    "sg:province":"CA",
    "sg:tags":[
        "environmental",
        "ecological"
    ],
    "wof:name":"Duffey Co",
    "wof:placetype":"venue"
},
  "geometry": {"coordinates":[-122.40216100000001,37.79667],"type":"Point"}
}