{
  "type": "Feature",
  "properties": {
    "iso:country":"US",
    "sg:address":"12155 Magnolia Ave",
    "sg:city":"Riverside",
    "sg:classifiers":[
        {
            "category":"Building & Trades",
            "subcategory":"Construction",
            "type":"Services"
        }
    ],
    "sg:phone":"+1 951 354 2882",
    "sg:postcode":"92503",
    "sg:province":"CA",
    "sg:tags":[
        "home",
        "builder"
    ],
    "wof:name":"Stevco Framing",
    "wof:placetype":"venue"
},
  "geometry": {"coordinates":[-117.494562,33.893559],"type":"Point"}
}