{
  "type": "Feature",
  "properties": {
    "addr:full":"71 Fortune Dr Irvine CA 92618",
    "addr:housenumber":"71",
    "addr:postcode":"92618",
    "addr:street":"Fortune Dr",
    "iso:country":"US",
    "sg:address":"71 Fortune Dr",
    "sg:city":"Irvine",
    "sg:classifiers":[
        {
            "category":"Manufacturing",
            "subcategory":"Printing",
            "type":"Manufacturing & Wholesale Goods"
        }
    ],
    "sg:phone":"+1 949 450 0558",
    "sg:postcode":"92618",
    "sg:province":"CA",
    "sg:tags":[
        "poster"
    ],
    "wof:name":"Art & Frames",
    "wof:placetype":"venue"
},
  "geometry": {"coordinates":[-117.74264100000001,33.649729],"type":"Point"}
}