{
  "type": "Feature",
  "properties": {
    "iso:country":"US",
    "sg:address":"3235 Danville Blvd",
    "sg:city":"Alamo",
    "sg:classifiers":[
        {
            "category":"Home & Garden",
            "subcategory":"Home Furnishings",
            "type":"Retail Goods"
        },
        {
            "category":"Professional",
            "subcategory":"Art Services",
            "type":"Services"
        },
        {
            "category":"Home & Garden",
            "subcategory":"Carpets & Floor Coverings",
            "type":"Retail Goods"
        },
        {
            "category":"Home & Garden",
            "subcategory":"Furniture",
            "type":"Retail Goods"
        }
    ],
    "sg:phone":"+1 925 837 9188",
    "sg:postcode":"94507",
    "sg:province":"CA",
    "sg:tags":[
        "draperies",
        "decor",
        "designer",
        "house",
        "rug",
        "window",
        "planning",
        "design",
        "treatment",
        "interior",
        "curtain",
        "decorator",
        "store"
    ],
    "sg:website":"http://www.designconceptsalamo.com",
    "wof:name":"Design Concepts",
    "wof:placetype":"venue"
},
  "geometry": {"coordinates":[-122.031677,37.848724],"type":"Point"}
}