{
  "type": "Feature",
  "properties": {
    "addr:full":"3010 Eagle St Los Angeles CA 90063",
    "addr:housenumber":"3010",
    "addr:postcode":"90063",
    "addr:street":"Eagle St",
    "iso:country":"US",
    "sg:address":"3010 Eagle St",
    "sg:city":"Los Angeles",
    "sg:classifiers":[
        {
            "category":"Social Services",
            "subcategory":"Child Care",
            "type":"Services"
        }
    ],
    "sg:phone":"+1 323 264 1945",
    "sg:postcode":"90063",
    "sg:province":"CA",
    "sg:tags":[
        "kindergarten",
        "academic",
        "school"
    ],
    "wof:name":"Foundation For Early Childhood",
    "wof:placetype":"venue"
},
  "geometry": {"coordinates":[-118.201937,34.035156],"type":"Point"}
}