{
  "type": "Feature",
  "properties": {
    "addr:full":"315 S Beverly Dr Beverly Hills CA 90212",
    "addr:housenumber":"315",
    "addr:postcode":"90212",
    "addr:street":"S Beverly Dr",
    "iso:country":"US",
    "sg:address":"315 S Beverly Dr",
    "sg:city":"Beverly Hills",
    "sg:classifiers":[
        {
            "category":"Health Services",
            "subcategory":"Health Practitioner",
            "type":"Services"
        }
    ],
    "sg:phone":"+1 310 277 8081",
    "sg:postcode":"90212",
    "sg:province":"CA",
    "sg:tags":[
        "psychologist"
    ],
    "wof:name":"Nancy E Addison PHD",
    "wof:placetype":"venue"
},
  "geometry": {"coordinates":[-118.399156,34.060968],"type":"Point"}
}