{
  "type": "Feature",
  "properties": {
    "iso:country":"US",
    "sg:address":"1969 Zonal Avenue",
    "sg:city":"Los Angeles",
    "sg:classifiers":[
        {
            "category":"Banks & Credit Unions",
            "subcategory":"Bank",
            "type":"Services"
        },
        {
            "category":"Education",
            "subcategory":"University",
            "type":"Public Place"
        }
    ],
    "sg:phone":"+1 323 442 1897",
    "sg:postcode":"90089",
    "sg:province":"CA",
    "sg:tags":[
        "college"
    ],
    "wof:name":"University of Southern California",
    "wof:placetype":"venue"
},
  "geometry": {"coordinates":[-118.287141,34.021187],"type":"Point"}
}