{
  "type": "Feature",
  "properties": {
    "addr:full":"1634 Centinela Ave Inglewood CA 90302",
    "addr:housenumber":"1634",
    "addr:postcode":"90302",
    "addr:street":"Centinela Ave",
    "iso:country":"US",
    "sg:address":"1634 Centinela Ave",
    "sg:city":"Inglewood",
    "sg:classifiers":[
        {
            "category":"Personal",
            "subcategory":"Beauty Salon",
            "type":"Services"
        }
    ],
    "sg:phone":"+1 310 216 7765",
    "sg:postcode":"90302",
    "sg:province":"CA",
    "sg:tags":[
        "shop"
    ],
    "wof:name":"Restoration The Salon",
    "wof:placetype":"venue"
},
  "geometry": {"coordinates":[-118.368037,33.977194],"type":"Point"}
}