{
  "type": "Feature",
  "properties": {
    "addr:full":"420 San Mateo Ave San Bruno CA 94066",
    "addr:housenumber":"420",
    "addr:postcode":"94066",
    "addr:street":"San Mateo Ave",
    "iso:country":"US",
    "sg:address":"420 San Mateo Ave",
    "sg:city":"San Bruno",
    "sg:classifiers":[
        {
            "category":"Travel",
            "subcategory":"Hotels & Motels",
            "type":"Entertainment"
        }
    ],
    "sg:phone":"+1 650 615 9543",
    "sg:postcode":"94066",
    "sg:province":"CA",
    "sg:tags":[
        "resort"
    ],
    "wof:name":"Spa Vacations",
    "wof:placetype":"venue"
},
  "geometry": {"coordinates":[-122.411171,37.622507],"type":"Point"}
}