{
  "type": "Feature",
  "properties": {
    "addr:full":"905 Henderson Ave Sunnyvale CA 94086",
    "addr:housenumber":"905",
    "addr:postcode":"94086",
    "addr:street":"Henderson Ave",
    "iso:country":"US",
    "sg:address":"905 Henderson Ave",
    "sg:city":"Sunnyvale",
    "sg:classifiers":[
        {
            "category":"Building & Trades",
            "subcategory":"Cleaning & Sanitation",
            "type":"Services"
        },
        {
            "category":"Home & Garden",
            "subcategory":"Carpets & Floor Coverings",
            "type":"Retail Goods"
        }
    ],
    "sg:phone":"+1 408 481 0282",
    "sg:postcode":"94086",
    "sg:province":"CA",
    "sg:tags":[
        "carpeting"
    ],
    "sg:website":"www.radiantcarpetcleaning.com",
    "wof:name":"Radiant Carpet & Upholstery Cleaning",
    "wof:placetype":"venue"
},
  "geometry": {"coordinates":[-122.005264,37.358213],"type":"Point"}
}