{
  "type": "Feature",
  "properties": {
    "addr:full":"9589 Ave C Niland CA 92257",
    "addr:housenumber":"9589",
    "addr:postcode":"92257",
    "addr:street":"Ave C Niland",
    "iso:country":"US",
    "sg:address":"9589 Ave C",
    "sg:city":"Niland",
    "sg:classifiers":[
        {
            "category":"Travel",
            "subcategory":"Hotels & Motels",
            "type":"Entertainment"
        }
    ],
    "sg:phone":"+1 760 354 1781",
    "sg:postcode":"92257",
    "sg:province":"CA",
    "wof:name":"B & B Motel",
    "wof:placetype":"venue"
},
  "geometry": {"coordinates":[-115.731847,33.351134],"type":"Point"}
}