{
  "type": "Feature",
  "properties": {
    "addr:full":"1624 E Carson St Carson CA 90745",
    "addr:housenumber":"1624",
    "addr:postcode":"90745",
    "addr:street":"E Carson St",
    "iso:country":"US",
    "sg:address":"1624 E Carson St",
    "sg:city":"Carson",
    "sg:classifiers":[
        {
            "category":"Manufacturing",
            "subcategory":"Food",
            "type":"Manufacturing & Wholesale Goods"
        },
        {
            "category":"Wholesale",
            "subcategory":"Groceries",
            "type":"Manufacturing & Wholesale Goods"
        }
    ],
    "sg:phone":"+1 310 830 5451",
    "sg:postcode":"90745",
    "sg:province":"CA",
    "sg:tags":[
        "baker",
        "product",
        "mfg"
    ],
    "sg:website":"www.puritanbakery.net",
    "wof:name":"Puritan Bakery Inc",
    "wof:placetype":"venue"
},
  "geometry": {"coordinates":[-118.242554,33.831576],"type":"Point"}
}