{
  "type": "Feature",
  "properties": {
    "iso:country":"US",
    "sg:address":"1174 Los Altos Ave",
    "sg:city":"Los Altos",
    "sg:classifiers":[
        {
            "category":"Personal",
            "subcategory":"Beauty Salon",
            "type":"Services"
        }
    ],
    "sg:phone":"+1 408 294 7010",
    "sg:postcode":"94022",
    "sg:province":"CA",
    "wof:name":"Kay's Hair Design",
    "wof:placetype":"venue"
},
  "geometry": {"coordinates":[-122.119167,37.403694],"type":"Point"}
}