{
  "type": "Feature",
  "properties": {
    "addr:full":"600 E Chapman Ave Orange CA 92866",
    "addr:housenumber":"600",
    "addr:postcode":"92866",
    "addr:street":"E Chapman Ave",
    "iso:country":"US",
    "sg:address":"600 E Chapman Ave",
    "sg:city":"Orange",
    "sg:classifiers":[
        {
            "category":"Retail",
            "subcategory":"Animal Services",
            "type":"Services"
        }
    ],
    "sg:phone":"+1 714 538 2287",
    "sg:postcode":"92866",
    "sg:province":"CA",
    "sg:tags":[
        "sitting",
        "pet",
        "veterinary",
        "membership",
        "boarding/pet",
        "lodging"
    ],
    "wof:name":"All-Cat Veterinary Clinic",
    "wof:placetype":"venue"
},
  "geometry": {"coordinates":[-117.84699999999999,33.7878],"type":"Point"}
}