{
  "type": "Feature",
  "properties": {
    "iso:country":"US",
    "sg:address":"3600 Lime St",
    "sg:city":"Riverside",
    "sg:classifiers":[
        {
            "category":"Professional",
            "subcategory":"Testing Lab",
            "type":"Services"
        }
    ],
    "sg:phone":"+1 951 351 8091",
    "sg:postcode":"92501",
    "sg:province":"CA",
    "sg:tags":[
        "calibration"
    ],
    "wof:name":"Kaye Instruments Inc",
    "wof:placetype":"venue"
},
  "geometry": {"coordinates":[-117.370314,33.981358],"type":"Point"}
}