{
  "type": "Feature",
  "properties": {
    "iso:country":"US",
    "sg:address":"18627 Pioneer Blvd",
    "sg:city":"Artesia",
    "sg:classifiers":[
        {
            "category":"Food & Beverages",
            "subcategory":"Bakery",
            "type":"Retail Goods"
        }
    ],
    "sg:phone":"+1 562 865 1201",
    "sg:postcode":"90701",
    "sg:province":"CA",
    "sg:tags":[
        "baker"
    ],
    "wof:name":"Artesia Bakery",
    "wof:placetype":"venue"
},
  "geometry": {"coordinates":[-118.082214,33.861749],"type":"Point"}
}