{
  "type": "Feature",
  "properties": {
    "iso:country":"US",
    "sg:address":"40836 20th St W",
    "sg:city":"Palmdale",
    "sg:classifiers":[
        {
            "category":"Organizations",
            "subcategory":"Non-profit Organization",
            "type":"Services"
        }
    ],
    "sg:phone":"+1 661 947 8357",
    "sg:postcode":"93551",
    "sg:province":"CA",
    "sg:tags":[
        "information",
        "alcoholism",
        "treatment"
    ],
    "wof:name":"Crossroads Ranch",
    "wof:placetype":"venue"
},
  "geometry": {"coordinates":[-118.16547300000001,34.624392],"type":"Point"}
}