{
  "type": "Feature",
  "properties": {
    "iso:country":"US",
    "sg:address":"10802 College Pl",
    "sg:city":"Cerritos",
    "sg:classifiers":[
        {
            "category":"Health Services",
            "subcategory":"Hospital",
            "type":"Services"
        }
    ],
    "sg:phone":"+1 562 924 0099",
    "sg:postcode":"90703",
    "sg:province":"CA",
    "sg:website":"www.collegehospitals.com",
    "wof:name":"Hospital Helpline",
    "wof:placetype":"venue"
},
  "geometry": {"coordinates":[-118.102997,33.884899],"type":"Point"}
}