{
  "type": "Feature",
  "properties": {
    "addr:full":"104 S Kingston St San Mateo CA 94401",
    "addr:housenumber":"104",
    "addr:postcode":"94401",
    "addr:street":"S Kingston St",
    "iso:country":"US",
    "sg:address":"104 S Kingston St",
    "sg:city":"San Mateo",
    "sg:classifiers":[
        {
            "category":"Retail",
            "subcategory":"Pet Boarding",
            "type":"Services"
        }
    ],
    "sg:phone":"+1 650 346 1851",
    "sg:postcode":"94401",
    "sg:province":"CA",
    "sg:tags":[
        "boarding/pet",
        "sitting"
    ],
    "wof:name":"Home Alone Doggie Daycare",
    "wof:placetype":"venue"
},
  "geometry": {"coordinates":[-122.31563800000001,37.573296],"type":"Point"}
}