{
  "type": "Feature",
  "properties": {
    "iso:country":"US",
    "sg:address":"1600 E Holt Ave Spc H16",
    "sg:city":"Pomona",
    "sg:classifiers":[
        {
            "category":"Utilities",
            "subcategory":"Mobile Phone",
            "type":"Services"
        },
        {
            "category":"Shopping",
            "subcategory":"Mobile Phones",
            "type":"Retail Goods"
        }
    ],
    "sg:phone":"+1 909 235 0988",
    "sg:postcode":"91767",
    "sg:province":"CA",
    "sg:tags":[
        "equipment",
        "telephone",
        "cellular",
        "supply"
    ],
    "sg:website":"http://www.A1Cell.com",
    "wof:name":"A1 Cellular",
    "wof:placetype":"venue"
},
  "geometry": {"coordinates":[-117.7192,34.063061],"type":"Point"}
}