{
  "type": "Feature",
  "properties": {
    "iso:country":"US",
    "sg:address":"1610 Diamond Valley Ln",
    "sg:city":"Chino Hills",
    "sg:classifiers":[
        {
            "category":"Wholesale",
            "subcategory":"Durable Goods & Equipment",
            "type":"Manufacturing & Wholesale Goods"
        }
    ],
    "sg:phone":"+1 909 627 6335",
    "sg:postcode":"91709",
    "sg:province":"CA",
    "sg:tags":[
        "exporter"
    ],
    "wof:name":"Sunny Co",
    "wof:placetype":"venue"
},
  "geometry": {"coordinates":[-117.769024,33.994309],"type":"Point"}
}