{
  "type": "Feature",
  "properties": {
    "addr:full":"3121 W 139th St Hawthorne CA 90250",
    "addr:housenumber":"3121",
    "addr:postcode":"90250",
    "addr:street":"W 139Th St",
    "iso:country":"US",
    "sg:address":"3121 W 139th St",
    "sg:city":"Hawthorne",
    "sg:classifiers":[
        {
            "category":"Wholesale",
            "subcategory":"Electrical",
            "type":"Manufacturing & Wholesale Goods"
        }
    ],
    "sg:phone":"+1 310 973 8350",
    "sg:postcode":"90250",
    "sg:province":"CA",
    "sg:tags":[
        "electric",
        "motor"
    ],
    "sg:website":"www.ampss.com",
    "wof:name":"AMPSS",
    "wof:placetype":"venue"
},
  "geometry": {"coordinates":[-118.327761,33.905632],"type":"Point"}
}