{
  "type": "Feature",
  "properties": {
    "addr:full":"229 16th St San Diego CA 92101",
    "addr:housenumber":"229",
    "addr:postcode":"92101",
    "addr:street":"16Th St",
    "iso:country":"US",
    "sg:address":"229 16th St",
    "sg:city":"San Diego",
    "sg:classifiers":[
        {
            "category":"Local Transit",
            "type":"Transportation"
        }
    ],
    "sg:phone":"+1 619 224 6157",
    "sg:postcode":"92101",
    "sg:province":"CA",
    "wof:name":"Sea Blue Shuttle",
    "wof:placetype":"venue"
},
  "geometry": {"coordinates":[-117.149356,32.708075],"type":"Point"}
}