{
  "type": "Feature",
  "properties": {
    "iso:country":"US",
    "sg:address":"344 Main St",
    "sg:city":"Vacaville",
    "sg:classifiers":[
        {
            "category":"Shopping",
            "subcategory":"Clothing, Apparel, & Fashions",
            "type":"Retail Goods"
        }
    ],
    "sg:phone":"+1 707 449 0350",
    "sg:postcode":"95688",
    "sg:province":"CA",
    "sg:tags":[
        "shop",
        "bridal"
    ],
    "wof:name":"Tux-N-Tailor Bridal",
    "wof:placetype":"venue"
},
  "geometry": {"coordinates":[-121.98909999999999,38.356565],"type":"Point"}
}