{
  "type": "Feature",
  "properties": {
    "addr:full":"4327 Redondo Beach Blvd Lawndale CA 90260",
    "addr:housenumber":"4327",
    "addr:postcode":"ca 90260",
    "addr:street":"Redondo Beach Blvd",
    "iso:country":"US",
    "sg:address":"4327 Redondo Beach Blvd",
    "sg:city":"Lawndale",
    "sg:classifiers":[
        {
            "category":"Personal",
            "type":"Services"
        }
    ],
    "sg:phone":"+1 310 214 7960",
    "sg:postcode":"90260",
    "sg:province":"CA",
    "sg:tags":[
        "sewing",
        "alteration"
    ],
    "wof:name":"Ace Tailoring",
    "wof:placetype":"venue"
},
  "geometry": {"coordinates":[-118.350998,33.874699],"type":"Point"}
}