{
  "type": "Feature",
  "properties": {
    "addr:full":"13423 Andy St Cerritos CA 90703",
    "addr:housenumber":"13423",
    "addr:postcode":"ca 90703",
    "addr:street":"Andy St",
    "iso:country":"US",
    "sg:address":"13423 Andy St",
    "sg:city":"Cerritos",
    "sg:classifiers":[
        {
            "category":"Social Services",
            "subcategory":"Job Training",
            "type":"Services"
        }
    ],
    "sg:phone":"+1 562 402 0092",
    "sg:postcode":"90703",
    "sg:province":"CA",
    "sg:tags":[
        "technician",
        "assistant",
        "school",
        "dental",
        "medical"
    ],
    "wof:name":"American Career College",
    "wof:placetype":"venue"
},
  "geometry": {"coordinates":[-118.045117,33.862541],"type":"Point"}
}