{
  "type": "Feature",
  "properties": {
    "iso:country":"US",
    "sg:address":"26722 Hyte Rd",
    "sg:city":"Rancho Palos Verdes",
    "sg:classifiers":[
        {
            "category":"Manufacturing",
            "subcategory":"Tools & Machinery",
            "type":"Manufacturing & Wholesale Goods"
        }
    ],
    "sg:phone":"+1 310 375 2959",
    "sg:postcode":"90275",
    "sg:province":"CA",
    "sg:tags":[
        "equipment",
        "peripheral",
        "computer",
        "mfg"
    ],
    "wof:name":"Richard J Jablonski",
    "wof:placetype":"venue"
},
  "geometry": {"coordinates":[-118.383138,33.786417],"type":"Point"}
}