{
  "type": "Feature",
  "properties": {
    "iso:country":"US",
    "sg:address":"361 S Raymond Ave",
    "sg:city":"Pasadena",
    "sg:classifiers":[
        {
            "category":"Retail",
            "subcategory":"Animal Services",
            "type":"Services"
        }
    ],
    "sg:phone":"+1 626 792 7151",
    "sg:postcode":"91105",
    "sg:province":"CA",
    "sg:tags":[
        "pet",
        "shelter",
        "store",
        "boarding/pet",
        "sitting"
    ],
    "sg:website":"www.pasadenahumane.org",
    "wof:name":"Pasadena Humane Society & SPCA",
    "wof:placetype":"venue"
},
  "geometry": {"coordinates":[-118.149255,34.139648],"type":"Point"}
}