{
  "type": "Feature",
  "properties": {
    "addr:full":"602 E 4th Ave San Mateo CA 94401",
    "addr:housenumber":"602",
    "addr:postcode":"94401",
    "addr:street":"E 4Th Ave",
    "iso:country":"US",
    "sg:address":"602 E 4th Ave",
    "sg:city":"San Mateo",
    "sg:classifiers":[
        {
            "category":"Coffee & Tea",
            "type":"Food & Drink"
        }
    ],
    "sg:postcode":"94401",
    "sg:province":"CA",
    "sg:website":"cuppyscoffee.com",
    "wof:name":"Cuppy's Coffee",
    "wof:placetype":"venue"
},
  "geometry": {"coordinates":[-122.319159,37.566403],"type":"Point"}
}