{
  "type": "Feature",
  "properties": {
    "addr:full":"5191 3rd St San Francisco CA 94124",
    "addr:housenumber":"5191",
    "addr:postcode":"94124",
    "addr:street":"3Rd St",
    "iso:country":"US",
    "sg:address":"5191 3rd St",
    "sg:city":"San Francisco",
    "sg:classifiers":[
        {
            "category":"Professional",
            "subcategory":"Detective & Security Services",
            "type":"Services"
        }
    ],
    "sg:phone":"+1 415 671 0264",
    "sg:postcode":"94124",
    "sg:province":"CA",
    "sg:tags":[
        "guard",
        "patrol"
    ],
    "wof:name":"Bay Area Security Svc",
    "wof:placetype":"venue"
},
  "geometry": {"coordinates":[-122.391856,37.731098],"type":"Point"}
}