{
  "type": "Feature",
  "properties": {
    "iso:country":"US",
    "sg:address":"513 1st St",
    "sg:city":"Rodeo",
    "sg:classifiers":[
        {
            "category":"Professional",
            "subcategory":"Printing & Photocopies",
            "type":"Services"
        }
    ],
    "sg:phone":"+1 510 799 4656",
    "sg:postcode":"94572",
    "sg:province":"CA",
    "sg:tags":[
        "medal",
        "plaque",
        "trophies"
    ],
    "wof:name":"Holm Patches & Caps",
    "wof:placetype":"venue"
},
  "geometry": {"coordinates":[-122.26904999999999,38.037019],"type":"Point"}
}