{
  "type": "Feature",
  "properties": {
    "addr:full":"1561 Shumaker Way San Jose CA 95131",
    "addr:housenumber":"1561",
    "addr:postcode":"95131",
    "addr:street":"Shumaker Way",
    "iso:country":"US",
    "sg:address":"1561 Shumaker Way",
    "sg:city":"San Jose",
    "sg:classifiers":[
        {
            "category":"Professional",
            "subcategory":"Business Services",
            "type":"Services"
        }
    ],
    "sg:phone":"+1 408 251 2960",
    "sg:postcode":"95131",
    "sg:province":"CA",
    "sg:tags":[
        "delivery",
        "courier"
    ],
    "sg:website":"forexworld.us/kahon/",
    "wof:name":"Forex Cargo",
    "wof:placetype":"venue"
},
  "geometry": {"coordinates":[-121.87605000000001,37.390982],"type":"Point"}
}