{
  "type": "Feature",
  "properties": {
    "iso:country":"US",
    "sg:address":"5860 88th St",
    "sg:city":"Sacramento",
    "sg:classifiers":[
        {
            "category":"Home & Garden",
            "subcategory":"Carpets & Floor Coverings",
            "type":"Retail Goods"
        }
    ],
    "sg:phone":"+1 916 381 5034",
    "sg:postcode":"95828",
    "sg:province":"CA",
    "sg:tags":[
        "material"
    ],
    "wof:name":"Floor Service Supply Co",
    "wof:placetype":"venue"
},
  "geometry": {"coordinates":[-121.375916,38.525063],"type":"Point"}
}