{
  "type": "Feature",
  "properties": {
    "addr:full":"1333 S Main St Santa Ana CA 92707",
    "addr:housenumber":"1333",
    "addr:postcode":"92707",
    "addr:street":"S Main St",
    "iso:country":"US",
    "sg:address":"1333 S Main St",
    "sg:city":"Santa Ana",
    "sg:classifiers":[
        {
            "category":"Local Transit",
            "type":"Transportation"
        }
    ],
    "sg:phone":"+1 949 574 0700",
    "sg:postcode":"92707",
    "sg:province":"CA",
    "sg:tags":[
        "limo"
    ],
    "wof:name":"Mirage Limousine",
    "wof:placetype":"venue"
},
  "geometry": {"coordinates":[-117.8677,33.73039],"type":"Point"}
}