{
  "type": "Feature",
  "properties": {
    "addr:full":"2900 Main St #67 Alameda CA 94501",
    "addr:housenumber":"2900;67",
    "addr:postcode":"94501",
    "addr:street":"Main St #;Alameda",
    "iso:country":"US",
    "sg:address":"2900 Main St #67",
    "sg:city":"Alameda",
    "sg:classifiers":[
        {
            "category":"Recreation",
            "subcategory":"Boat Charter",
            "type":"Entertainment"
        },
        {
            "category":"Building & Trades",
            "subcategory":"Construction",
            "type":"Services"
        }
    ],
    "sg:phone":"+1 510 908 3939",
    "sg:postcode":"94501",
    "sg:province":"CA",
    "sg:tags":[
        "interior",
        "boating",
        "design"
    ],
    "sg:website":"www.wrightwaydesigns.com",
    "wof:name":"Wright Way Designs",
    "wof:placetype":"venue"
},
  "geometry": {"coordinates":[-122.292627,37.788624],"type":"Point"}
}