{
  "type": "Feature",
  "properties": {
    "iso:country":"US",
    "sg:address":"686 Anton Blvd",
    "sg:city":"Costa Mesa",
    "sg:classifiers":[
        {
            "category":"Travel",
            "subcategory":"Hotels & Motels",
            "type":"Entertainment"
        }
    ],
    "sg:phone":"+1 714 540 2500",
    "sg:postcode":"92626",
    "sg:province":"CA",
    "sg:website":"www.starwoodhotels.com/westin/pr...",
    "wof:name":"The Westin South Coast Plaza, Costa Mesa",
    "wof:placetype":"venue"
},
  "geometry": {"coordinates":[-117.88418299999999,33.690754],"type":"Point"}
}