{
  "type": "Feature",
  "properties": {
    "addr:full":"607 San Ramon Valley Blvd Danville CA 94526",
    "addr:housenumber":"607",
    "addr:postcode":"94526",
    "addr:street":"San Ramon Valley Blvd",
    "iso:country":"US",
    "sg:address":"607 San Ramon Valley Blvd",
    "sg:city":"Danville",
    "sg:classifiers":[
        {
            "category":"Food & Beverages",
            "subcategory":"Liquor & Beverages",
            "type":"Retail Goods"
        }
    ],
    "sg:phone":"+1 925 837 2111",
    "sg:postcode":"94526",
    "sg:province":"CA",
    "wof:name":"Ernie's Wines & Liquors",
    "wof:placetype":"venue"
},
  "geometry": {"coordinates":[-121.99620400000001,37.814653],"type":"Point"}
}