{
  "type": "Feature",
  "properties": {
    "addr:full":"31 Festivo Irvine CA 92606",
    "addr:housenumber":"31",
    "addr:postcode":"92606",
    "addr:street":"Festivo",
    "iso:country":"US",
    "sg:address":"31 Festivo",
    "sg:city":"Irvine",
    "sg:classifiers":[
        {
            "category":"Shopping",
            "subcategory":"Party Supplies",
            "type":"Retail Goods"
        }
    ],
    "sg:phone":"+1 949 387 2789",
    "sg:postcode":"92606",
    "sg:province":"CA",
    "wof:name":"The",
    "wof:placetype":"venue"
},
  "geometry": {"coordinates":[-117.809967,33.692931],"type":"Point"}
}