{
  "type": "Feature",
  "properties": {
    "iso:country":"US",
    "sg:address":"825 Pacific Ave",
    "sg:city":"Long Beach",
    "sg:classifiers":[
        {
            "category":"Health Services",
            "subcategory":"Optometrist",
            "type":"Services"
        }
    ],
    "sg:phone":"+1 562 436 9771",
    "sg:postcode":"90813",
    "sg:province":"CA",
    "sg:tags":[
        "ophthalmologist"
    ],
    "wof:name":"Sulit Hector L MD A Medical Corporation",
    "wof:placetype":"venue"
},
  "geometry": {"coordinates":[-118.194,33.777199],"type":"Point"}
}