{
  "type": "Feature",
  "properties": {
    "iso:country":"US",
    "sg:address":"7870 Stalmer St",
    "sg:city":"San Diego",
    "sg:classifiers":[
        {
            "category":"Real Estate",
            "subcategory":"Real Estate Operator",
            "type":"Services"
        }
    ],
    "sg:phone":"+1 858 277 4843",
    "sg:postcode":"92111",
    "sg:province":"CA",
    "sg:tags":[
        "apartment"
    ],
    "wof:name":"Wexford Manor",
    "wof:placetype":"venue"
},
  "geometry": {"coordinates":[-117.154999,32.8078],"type":"Point"}
}