{
  "type": "Feature",
  "properties": {
    "iso:country":"US",
    "sg:address":"2361 Autumn Dr",
    "sg:city":"Oceanside",
    "sg:classifiers":[
        {
            "category":"Building & Trades",
            "subcategory":"Landscaping Services",
            "type":"Services"
        }
    ],
    "sg:phone":"+1 760 758 2414",
    "sg:postcode":"92056",
    "sg:province":"CA",
    "wof:name":"Good Seasons Landscaping Maint",
    "wof:placetype":"venue"
},
  "geometry": {"coordinates":[-117.273014,33.206575],"type":"Point"}
}