{
  "type": "Feature",
  "properties": {
    "addr:full":"3100 Countryside Dr Turlock CA 95380",
    "addr:housenumber":"3100",
    "addr:postcode":"95380",
    "addr:street":"Countryside Dr",
    "iso:country":"US",
    "sg:address":"3100 Countryside Dr",
    "sg:city":"Turlock",
    "sg:classifiers":[
        {
            "category":"Restaurant",
            "type":"Food & Drink"
        },
        {
            "category":"Food & Beverages",
            "subcategory":"Fruits & Vegetables",
            "type":"Retail Goods"
        }
    ],
    "sg:menulink":"http://www.allmenus.com/ca/turlock/135731-jamba-juice/menu/",
    "sg:phone":"+1 209 656 0941",
    "sg:postcode":"95380",
    "sg:province":"CA",
    "sg:tags":[
        "smoothy",
        "juice",
        "american"
    ],
    "wof:name":"Jamba Juice",
    "wof:placetype":"venue"
},
  "geometry": {"coordinates":[-120.880782,37.521252],"type":"Point"}
}