{
  "type": "Feature",
  "properties": {
    "iso:country":"US",
    "sg:address":"4011 Lake Tahoe Blvd",
    "sg:city":"South Lake Tahoe",
    "sg:classifiers":[
        {
            "category":"Travel",
            "subcategory":"Hotels & Motels",
            "type":"Entertainment"
        }
    ],
    "sg:phone":"+1 530 544 6000",
    "sg:postcode":"96150",
    "sg:province":"CA",
    "wof:name":"Travelodge",
    "wof:placetype":"venue"
},
  "geometry": {"coordinates":[-119.94510699999999,38.954854],"type":"Point"}
}