{
  "type": "Feature",
  "properties": {
    "addr:full":"2272 Colorado Blvd Los Angeles CA 90041",
    "addr:housenumber":"2272",
    "addr:postcode":"90041",
    "addr:street":"Colorado Blvd",
    "iso:country":"US",
    "sg:address":"2272 Colorado Blvd",
    "sg:city":"Los Angeles",
    "sg:classifiers":[
        {
            "category":"Building & Trades",
            "subcategory":"Cleaning & Sanitation",
            "type":"Services"
        }
    ],
    "sg:phone":"+1 323 258 7068",
    "sg:postcode":"90041",
    "sg:province":"CA",
    "sg:tags":[
        "janitor"
    ],
    "wof:name":"Aces Carpet & Upholstery Clng",
    "wof:placetype":"venue"
},
  "geometry": {"coordinates":[-118.214421,34.13906],"type":"Point"}
}