{
  "type": "Feature",
  "properties": {
    "iso:country":"US",
    "sg:address":"21965 Green Sage Ct",
    "sg:city":"Salinas",
    "sg:classifiers":[
        {
            "category":"Professional",
            "type":"Services"
        }
    ],
    "sg:phone":"+1 831 455 9051",
    "sg:postcode":"93908",
    "sg:province":"CA",
    "wof:name":"Darshen Sidhu",
    "wof:placetype":"venue"
},
  "geometry": {"coordinates":[-121.644465,36.605741],"type":"Point"}
}