{
  "type": "Feature",
  "properties": {
    "addr:full":"1075 Atlas Peak Rd Napa CA 94558",
    "addr:housenumber":"1075",
    "addr:postcode":"94558",
    "addr:street":"Atlas Peak Rd",
    "iso:country":"US",
    "sg:address":"1075 Atlas Peak Rd",
    "sg:city":"Napa",
    "sg:classifiers":[
        {
            "category":"Wholesale",
            "subcategory":"Machinery & Supplies",
            "type":"Manufacturing & Wholesale Goods"
        }
    ],
    "sg:phone":"+1 707 224 4475",
    "sg:postcode":"94558",
    "sg:province":"CA",
    "sg:tags":[
        "truck"
    ],
    "wof:name":"Napa Drayage & Wholesale Co",
    "wof:placetype":"venue"
},
  "geometry": {"coordinates":[-122.26161399999999,38.338175],"type":"Point"}
}