{
  "type": "Feature",
  "properties": {
    "iso:country":"US",
    "sg:address":"9797 Dillard Rd",
    "sg:city":"Wilton",
    "sg:classifiers":[
        {
            "category":"Food & Beverages",
            "subcategory":"Groceries & Convenience Stores",
            "type":"Retail Goods"
        }
    ],
    "sg:phone":"+1 916 687 6252",
    "sg:postcode":"95693",
    "sg:province":"CA",
    "sg:tags":[
        "grocer"
    ],
    "wof:name":"Dillard Store",
    "wof:placetype":"venue"
},
  "geometry": {"coordinates":[-121.25672299999999,38.401536],"type":"Point"}
}