{
  "type": "Feature",
  "properties": {
    "iso:country":"US",
    "sg:address":"4440 Florin Rd",
    "sg:city":"Sacramento",
    "sg:classifiers":[
        {
            "category":"Shopping",
            "subcategory":"Clothing, Apparel, & Fashions",
            "type":"Retail Goods"
        }
    ],
    "sg:phone":"+1 916 392 6477",
    "sg:postcode":"95823",
    "sg:province":"CA",
    "wof:name":"Fashions 5",
    "wof:placetype":"venue"
},
  "geometry": {"coordinates":[-121.451982,38.49599],"type":"Point"}
}