{
  "type": "Feature",
  "properties": {
    "addr:full":"106 N Glassell St Orange CA 92866",
    "addr:housenumber":"106",
    "addr:postcode":"92866",
    "addr:street":"N Glassell St",
    "iso:country":"US",
    "sg:address":"106 N Glassell St",
    "sg:city":"Orange",
    "sg:classifiers":[
        {
            "category":"Restaurant",
            "type":"Food & Drink"
        },
        {
            "category":"Ice Cream",
            "type":"Food & Drink"
        },
        {
            "category":"Internet Cafe",
            "subcategory":"None",
            "type":"Food & Drink"
        }
    ],
    "sg:phone":"+1 714 289 1255",
    "sg:postcode":"92866",
    "sg:province":"CA",
    "sg:tags":[
        "frozen",
        "yogurt",
        "italian"
    ],
    "sg:website":"www.cafelucca.com",
    "wof:name":"Cafe Lucca",
    "wof:placetype":"venue"
},
  "geometry": {"coordinates":[-117.85323099999999,33.78847],"type":"Point"}
}