{
  "type": "Feature",
  "properties": {
    "addr:full":"1855 W Katella Ave Orange CA 92867",
    "addr:housenumber":"1855",
    "addr:postcode":"92867",
    "addr:street":"W Katella Ave",
    "iso:country":"US",
    "sg:address":"1855 W Katella Ave",
    "sg:city":"Orange",
    "sg:classifiers":[
        {
            "category":"Professional",
            "subcategory":"Engineering",
            "type":"Services"
        }
    ],
    "sg:phone":"+1 714 639 1429",
    "sg:postcode":"92867",
    "sg:province":"CA",
    "sg:tags":[
        "engineer"
    ],
    "sg:website":"www.dcgainc.com",
    "wof:name":"Donn Gilmore & Assoc Inc",
    "wof:placetype":"venue"
},
  "geometry": {"coordinates":[-117.868274,33.808652],"type":"Point"}
}