{
  "type": "Feature",
  "properties": {
    "iso:country":"US",
    "sg:address":"1723 Havana St",
    "sg:city":"Seaside",
    "sg:classifiers":[
        {
            "category":"Professional",
            "subcategory":"Computer Services",
            "type":"Services"
        }
    ],
    "sg:phone":"+1 831 899 2373",
    "sg:postcode":"93955",
    "sg:province":"CA",
    "wof:name":"Creative Design Printing Inc",
    "wof:placetype":"venue"
},
  "geometry": {"coordinates":[-121.82263,36.612346],"type":"Point"}
}