{
  "type": "Feature",
  "properties": {
    "iso:country":"US",
    "sg:address":"455 N El Molino Ave",
    "sg:city":"Pasadena",
    "sg:classifiers":[
        {
            "category":"Real Estate",
            "subcategory":"Architect",
            "type":"Services"
        }
    ],
    "sg:phone":"+1 626 796 1966",
    "sg:postcode":"91101",
    "sg:province":"CA",
    "wof:name":"Richard T Santos Aia Architect",
    "wof:placetype":"venue"
},
  "geometry": {"coordinates":[-118.137141,34.15367],"type":"Point"}
}