{
  "type": "Feature",
  "properties": {
    "addr:full":"39990 Faure Rd Hemet CA 92544",
    "addr:postcode":"39990;92544",
    "addr:street":"Faure Rd",
    "iso:country":"US",
    "sg:address":"39990 Faure Rd",
    "sg:city":"Hemet",
    "sg:classifiers":[
        {
            "category":"Building & Trades",
            "subcategory":"Construction",
            "type":"Services"
        }
    ],
    "sg:phone":"+1 951 767 0508",
    "sg:postcode":"92544",
    "sg:province":"CA",
    "sg:tags":[
        "general",
        "contractor"
    ],
    "wof:name":"Taylor & Son Construction",
    "wof:placetype":"venue"
},
  "geometry": {"coordinates":[-116.898355,33.545897],"type":"Point"}
}