{
  "type": "Feature",
  "properties": {
    "addr:full":"1743 Pacific Coast Hwy Lomita CA 90717",
    "addr:housenumber":"1743",
    "addr:postcode":"90717",
    "addr:street":"Pacific Coast Hwy",
    "iso:country":"US",
    "sg:address":"1743 Pacific Coast Hwy",
    "sg:city":"Lomita",
    "sg:classifiers":[
        {
            "category":"Personal",
            "subcategory":"Nail Salon",
            "type":"Services"
        }
    ],
    "sg:phone":"+1 310 891 3584",
    "sg:postcode":"90717",
    "sg:province":"CA",
    "wof:name":"CT Nails & Spa",
    "wof:placetype":"venue"
},
  "geometry": {"coordinates":[-118.308453,33.789607],"type":"Point"}
}