{
  "type": "Feature",
  "properties": {
    "addr:full":"5188 Butterwood Cir Orangevale CA 95662",
    "addr:housenumber":"5188",
    "addr:postcode":"95662",
    "addr:street":"Butterwood Cir",
    "iso:country":"US",
    "sg:address":"5188 Butterwood Cir",
    "sg:city":"Orangevale",
    "sg:classifiers":[
        {
            "category":"Real Estate",
            "subcategory":"Real Estate Services",
            "type":"Services"
        },
        {
            "category":"Real Estate",
            "subcategory":"Real Estate Agent",
            "type":"Services"
        }
    ],
    "sg:phone":"+1 916 204 1985",
    "sg:postcode":"95662",
    "sg:province":"CA",
    "sg:tags":[
        "buyer",
        "broker"
    ],
    "wof:name":"Lyon Real Estate",
    "wof:placetype":"venue"
},
  "geometry": {"coordinates":[-121.20374700000001,38.660071],"type":"Point"}
}