{
  "type": "Feature",
  "properties": {
    "iso:country":"US",
    "sg:address":"2608 Ashby St",
    "sg:city":"Bakersfield",
    "sg:classifiers":[
        {
            "category":"Building & Trades",
            "subcategory":"Construction",
            "type":"Services"
        }
    ],
    "sg:phone":"+1 661 589 4021",
    "sg:postcode":"93308",
    "sg:province":"CA",
    "sg:tags":[
        "coping",
        "plastering",
        "tiling",
        "pool",
        "swimming"
    ],
    "wof:name":"Valley Pool Svc",
    "wof:placetype":"venue"
},
  "geometry": {"coordinates":[-119.013744,35.433068],"type":"Point"}
}