{
  "type": "Feature",
  "properties": {
    "addr:full":"310 Sutter St San Francisco CA 94108",
    "addr:housenumber":"310",
    "addr:postcode":"94108",
    "addr:street":"Sutter St",
    "iso:country":"US",
    "sg:address":"310 Sutter St",
    "sg:city":"San Francisco",
    "sg:classifiers":[
        {
            "category":"Professional",
            "subcategory":"Employment Agencies",
            "type":"Services"
        }
    ],
    "sg:phone":"+1 415 982 5500",
    "sg:postcode":"94108",
    "sg:province":"CA",
    "sg:tags":[
        "opportunity"
    ],
    "wof:name":"Gravity People",
    "wof:placetype":"venue"
},
  "geometry": {"coordinates":[-122.40684299999999,37.789528],"type":"Point"}
}