{
  "type": "Feature",
  "properties": {
    "addr:full":"25432 Trabuco Rd Lake Forest CA 92630",
    "addr:housenumber":"25432",
    "addr:postcode":"92630",
    "addr:street":"Trabuco Rd",
    "iso:country":"US",
    "sg:address":"25432 Trabuco Rd",
    "sg:city":"Lake Forest",
    "sg:classifiers":[
        {
            "category":"Autos & Motor Vehicles",
            "subcategory":"Automobile Sales",
            "type":"Retail Goods"
        }
    ],
    "sg:phone":"+1 714 952 2967",
    "sg:postcode":"92630",
    "sg:province":"CA",
    "sg:tags":[
        "limo"
    ],
    "wof:name":"Norman Lewis First Class Limousine Service",
    "wof:placetype":"venue"
},
  "geometry": {"coordinates":[-117.68698999999999,33.648061],"type":"Point"}
}