{
  "type": "Feature",
  "properties": {
    "iso:country":"US",
    "sg:address":"2324 Eagle Ave",
    "sg:city":"Alameda",
    "sg:classifiers":[
        {
            "category":"Shopping",
            "type":"Retail Goods"
        }
    ],
    "sg:phone":"+1 510 521 9526",
    "sg:postcode":"94501",
    "sg:province":"CA",
    "sg:tags":[
        "product",
        "merchandise",
        "mfg"
    ],
    "sg:website":"www.accessiblehomelift.com",
    "wof:name":"Accessible Home Lift Co",
    "wof:placetype":"venue"
},
  "geometry": {"coordinates":[-122.23938200000001,37.7691],"type":"Point"}
}