{
  "type": "Feature",
  "properties": {
    "addr:full":"133 W Chapman Ave Fullerton CA 92832",
    "addr:housenumber":"133",
    "addr:postcode":"92832",
    "addr:street":"W Chapman Ave",
    "iso:country":"US",
    "sg:address":"133 W Chapman Ave",
    "sg:city":"Fullerton",
    "sg:classifiers":[
        {
            "category":"Restaurant",
            "type":"Food & Drink"
        }
    ],
    "sg:phone":"+1 714 441 1392",
    "sg:postcode":"92832",
    "sg:province":"CA",
    "sg:tags":[
        "mexican"
    ],
    "sg:website":"www.eatchronictacos.com/",
    "wof:name":"Chronic Tacos",
    "wof:placetype":"venue"
},
  "geometry": {"coordinates":[-117.925766,33.874275],"type":"Point"}
}