{
  "type": "Feature",
  "properties": {
    "iso:country":"US",
    "sg:address":"10367 San Pablo Ave",
    "sg:city":"El Cerrito",
    "sg:classifiers":[
        {
            "category":"Food & Beverages",
            "subcategory":"Specialty",
            "type":"Retail Goods"
        }
    ],
    "sg:phone":"+1 510 526 1155",
    "sg:postcode":"94530",
    "sg:province":"CA",
    "sg:tags":[
        "health",
        "market",
        "diet"
    ],
    "sg:website":"www.naturalgrocery.com",
    "wof:name":"El Cerrito Natural Grocery Company",
    "wof:placetype":"venue"
},
  "geometry": {"coordinates":[-122.306472,37.907411],"type":"Point"}
}