{
  "type": "Feature",
  "properties": {
    "iso:country":"US",
    "sg:address":"4359 Town Center Blvd",
    "sg:city":"El Dorado Hills",
    "sg:classifiers":[
        {
            "category":"Shopping",
            "type":"Retail Goods"
        }
    ],
    "sg:phone":"+1 916 939 1845",
    "sg:postcode":"95762",
    "sg:province":"CA",
    "sg:tags":[
        "art",
        "gallery",
        "dealer"
    ],
    "wof:name":"Hang It Up",
    "wof:placetype":"venue"
},
  "geometry": {"coordinates":[-121.068028,38.650208],"type":"Point"}
}