{
  "type": "Feature",
  "properties": {
    "addr:full":"972 Red Gum Ln Nipomo CA 93444",
    "addr:housenumber":"972",
    "addr:postcode":"93444",
    "addr:street":"Red Gum Ln",
    "iso:country":"US",
    "sg:address":"972 Red Gum Ln",
    "sg:city":"Nipomo",
    "sg:classifiers":[
        {
            "category":"Manufacturing",
            "subcategory":"Buildings",
            "type":"Manufacturing & Wholesale Goods"
        },
        {
            "category":"Building & Trades",
            "subcategory":"Construction",
            "type":"Services"
        }
    ],
    "sg:phone":"+1 805 929 6854",
    "sg:postcode":"93444",
    "sg:province":"CA",
    "sg:tags":[
        "consultant",
        "builder",
        "management",
        "contractor",
        "home"
    ],
    "wof:name":"Pave Rite Construction Inc",
    "wof:placetype":"venue"
},
  "geometry": {"coordinates":[-120.51020800000001,35.035529],"type":"Point"}
}