{
  "type": "Feature",
  "properties": {
    "addr:full":"2111 N Westwood St Porterville CA 93257",
    "addr:housenumber":"2111",
    "addr:postcode":"93257",
    "addr:street":"N Westwood St",
    "iso:country":"US",
    "sg:address":"2111 N Westwood St",
    "sg:city":"Porterville",
    "sg:classifiers":[
        {
            "category":"Professional",
            "type":"Services"
        }
    ],
    "sg:phone":"+1 559 784 2895",
    "sg:postcode":"93257",
    "sg:province":"CA",
    "wof:name":"Paul K Brown",
    "wof:placetype":"venue"
},
  "geometry": {"coordinates":[-119.071004,36.103474],"type":"Point"}
}