{
  "type": "Feature",
  "properties": {
    "iso:country":"US",
    "sg:address":"825 Arnold Dr Ste 8",
    "sg:city":"Martinez",
    "sg:classifiers":[
        {
            "category":"Retail",
            "subcategory":"Laundry & Dry Cleaning",
            "type":"Services"
        },
        {
            "category":"Building & Trades",
            "subcategory":"Cleaning & Sanitation",
            "type":"Services"
        }
    ],
    "sg:phone":"+1 925 228 7422",
    "sg:postcode":"94553",
    "sg:province":"CA",
    "sg:tags":[
        "cleaner",
        "upholstery",
        "rug",
        "carpet"
    ],
    "wof:name":"Bob's Chem-Dry",
    "wof:placetype":"venue"
},
  "geometry": {"coordinates":[-122.117384,37.996737],"type":"Point"}
}