{
  "type": "Feature",
  "properties": {
    "addr:full":"1618 W 67th Street Los Angeles CA 90047",
    "addr:housenumber":"1618",
    "addr:postcode":"90047",
    "addr:street":"W 67Th Street",
    "iso:country":"US",
    "sg:address":"1618 W 67th Street",
    "sg:city":"Los Angeles",
    "sg:classifiers":[
        {
            "category":"Building & Trades",
            "subcategory":"Plumbing",
            "type":"Services"
        }
    ],
    "sg:phone":"+1 323 778 5417",
    "sg:postcode":"90047",
    "sg:province":"CA",
    "wof:name":"Andrade Plumbing & Electrical",
    "wof:placetype":"venue"
},
  "geometry": {"coordinates":[-118.305143,33.978605],"type":"Point"}
}