{
  "type": "Feature",
  "properties": {
    "addr:full":"16927 Devonshire St Granada Hills CA 91344",
    "addr:housenumber":"16927",
    "addr:postcode":"91344",
    "addr:street":"Devonshire St",
    "iso:country":"US",
    "sg:address":"16927 Devonshire St",
    "sg:city":"Granada Hills",
    "sg:classifiers":[
        {
            "category":"Personal",
            "subcategory":"Beauty Salon",
            "type":"Services"
        }
    ],
    "sg:phone":"+1 818 368 7588",
    "sg:postcode":"91344",
    "sg:province":"CA",
    "wof:name":"Supercuts",
    "wof:placetype":"venue"
},
  "geometry": {"coordinates":[-118.498127,34.257564],"type":"Point"}
}