{
  "type": "Feature",
  "properties": {
    "iso:country":"US",
    "sg:address":"207 N Vermont Ave",
    "sg:city":"Los Angeles",
    "sg:classifiers":[
        {
            "category":"Sports & Exercise",
            "subcategory":"Bicycle Rental",
            "type":"Entertainment"
        }
    ],
    "sg:phone":"+1 213 749 5600",
    "sg:postcode":"90004",
    "sg:province":"CA",
    "sg:tags":[
        "wear"
    ],
    "sg:website":"acemartialartssupply.com",
    "wof:name":"Ace Martial Arts Supply",
    "wof:placetype":"venue"
},
  "geometry": {"coordinates":[-118.29186,34.074896],"type":"Point"}
}