{
  "type": "Feature",
  "properties": {
    "addr:full":"3120 Main St San Diego CA 92113",
    "addr:housenumber":"3120",
    "addr:postcode":"92113",
    "addr:street":"Main St",
    "iso:country":"US",
    "sg:address":"3120 Main St",
    "sg:city":"San Diego",
    "sg:classifiers":[
        {
            "category":"Retail",
            "subcategory":"Repair Shop",
            "type":"Services"
        },
        {
            "category":"Professional",
            "subcategory":"Computer Services",
            "type":"Services"
        }
    ],
    "sg:phone":"+1 619 646 1632",
    "sg:postcode":"92113",
    "sg:province":"CA",
    "sg:tags":[
        "electronics",
        "installation",
        "stereo"
    ],
    "wof:name":"AAA Mobile Stereo Installs",
    "wof:placetype":"venue"
},
  "geometry": {"coordinates":[-117.12677499999999,32.693131],"type":"Point"}
}