{
  "type": "Feature",
  "properties": {
    "iso:country":"US",
    "sg:address":"1404 Franklin St Ste 350",
    "sg:city":"Oakland",
    "sg:classifiers":[
        {
            "category":"Professional",
            "subcategory":"Engineering",
            "type":"Services"
        }
    ],
    "sg:phone":"+1 510 433 0828",
    "sg:postcode":"94612",
    "sg:province":"CA",
    "sg:tags":[
        "consulting",
        "structural",
        "engineer"
    ],
    "sg:website":"http://www.olmm.com",
    "wof:name":"Olmm Consulting Engineers",
    "wof:placetype":"venue"
},
  "geometry": {"coordinates":[-122.269949,37.803869],"type":"Point"}
}