{
  "type": "Feature",
  "properties": {
    "iso:country":"US",
    "sg:address":"6925 Sycamore Rd",
    "sg:city":"Atascadero",
    "sg:classifiers":[
        {
            "category":"Retail",
            "subcategory":"Repair Shop",
            "type":"Services"
        }
    ],
    "sg:phone":"+1 805 466 8073",
    "sg:postcode":"93422",
    "sg:province":"CA",
    "sg:tags":[
        "equipment",
        "conditioning",
        "air"
    ],
    "wof:name":"Pacific Air",
    "wof:placetype":"venue"
},
  "geometry": {"coordinates":[-120.65543,35.498155],"type":"Point"}
}