{
  "type": "Feature",
  "properties": {
    "addr:full":"1110 1st St Coronado CA 92118",
    "addr:housenumber":"1110",
    "addr:postcode":"92118",
    "addr:street":"1St St",
    "iso:country":"US",
    "sg:address":"1110 1st St",
    "sg:city":"Coronado",
    "sg:classifiers":[
        {
            "category":"Shopping",
            "subcategory":"Clothing, Apparel, & Fashions",
            "type":"Retail Goods"
        }
    ],
    "sg:phone":"+1 619 435 4780",
    "sg:postcode":"92118",
    "sg:province":"CA",
    "sg:tags":[
        "accessory",
        "clothing",
        "women's"
    ],
    "wof:name":"Zazen",
    "wof:placetype":"venue"
},
  "geometry": {"coordinates":[-117.171997,32.698601],"type":"Point"}
}