{
  "type": "Feature",
  "properties": {
    "iso:country":"US",
    "sg:address":"4500 Campus Drive",
    "sg:city":"Newport Beach",
    "sg:classifiers":[
        {
            "category":"Retail",
            "subcategory":"Auto Rental",
            "type":"Services"
        }
    ],
    "sg:phone":"+1 949 955 9494",
    "sg:postcode":"92660",
    "sg:province":"CA",
    "sg:tags":[
        "car"
    ],
    "wof:name":"Ritz Rent A Car",
    "wof:placetype":"venue"
},
  "geometry": {"coordinates":[-117.867088,33.670154],"type":"Point"}
}