{
  "type": "Feature",
  "properties": {
    "addr:full":"1649 E Miraloma Ave Placentia CA 92870",
    "addr:housenumber":"1649",
    "addr:postcode":"ca 92870",
    "addr:street":"E Miraloma Ave",
    "iso:country":"US",
    "sg:address":"1649 E Miraloma Ave",
    "sg:city":"Placentia",
    "sg:phone":"+1 714 630 9422",
    "sg:postcode":"92870",
    "sg:province":"CA",
    "wof:name":"Kennametal Inc",
    "wof:placetype":"venue"
},
  "geometry": {"coordinates":[-117.828647,33.862789],"type":"Point"}
}