{
  "type": "Feature",
  "properties": {
    "iso:country":"US",
    "sg:address":"1915 Solano St",
    "sg:city":"Corning",
    "sg:classifiers":[
        {
            "category":"Real Estate",
            "subcategory":"Real Estate Agent",
            "type":"Services"
        }
    ],
    "sg:phone":"+1 530 824 9775",
    "sg:postcode":"96021",
    "sg:province":"CA",
    "wof:name":"Oliveira Properties",
    "wof:placetype":"venue"
},
  "geometry": {"coordinates":[-122.19236100000001,39.927934],"type":"Point"}
}