{
  "type": "Feature",
  "properties": {
    "iso:country":"US",
    "sg:address":"24261 Sunnybrook Cir",
    "sg:city":"Lake Forest",
    "sg:classifiers":[
        {
            "category":"Retail",
            "subcategory":"Laundry & Dry Cleaning",
            "type":"Services"
        }
    ],
    "sg:phone":"+1 949 584 0660",
    "sg:postcode":"92630",
    "sg:province":"CA",
    "sg:tags":[
        "cleaners"
    ],
    "wof:name":"Clean Sweep Inc",
    "wof:placetype":"venue"
},
  "geometry": {"coordinates":[-117.706617,33.627172],"type":"Point"}
}