{
  "type": "Feature",
  "properties": {
    "iso:country":"US",
    "sfac:artist":"Dill, Laddie John",
    "sfac:created_at":"01/01/1970 12:32:57 AM +0000",
    "sfac:credit_line":"Purchased by the San Francisco Art Commission for the San Francisco International Airport.",
    "sfac:display_dimensions":"60 in. x 84 in.",
    "sfac:location_description":"Airport : Terminal 2 : Gate 59",
    "sfac:medium":"Cement, polymer and glass",
    "sfac:revision":"2-4749ee890dfeaebdba35ee3aaf0f0380",
    "sfac:title":"Untitled",
    "wof:name":"Untitled",
    "wof:placetype":"venue"
},
  "geometry": {"coordinates":[-122.389979,37.615223],"type":"Point"}
}