{
  "type": "Feature",
  "properties": {
    "addr:full":"403 Broadway Millbrae CA 94030",
    "addr:housenumber":"403",
    "addr:postcode":"94030",
    "addr:street":"Broadway",
    "iso:country":"US",
    "sg:address":"403 Broadway",
    "sg:city":"Millbrae",
    "sg:classifiers":[
        {
            "category":"Personal",
            "subcategory":"Shoe Repair & Shine",
            "type":"Services"
        }
    ],
    "sg:phone":"+1 650 692 5155",
    "sg:postcode":"94030",
    "sg:province":"CA",
    "wof:name":"Broadway Cobbler",
    "wof:placetype":"venue"
},
  "geometry": {"coordinates":[-122.39299800000001,37.601601],"type":"Point"}
}