{
  "type": "Feature",
  "properties": {
    "addr:full":"7572 North Ave Lemon Grove CA 91945",
    "addr:housenumber":"7572",
    "addr:postcode":"91945",
    "addr:street":"North Ave",
    "iso:country":"US",
    "sg:address":"7572 North Ave",
    "sg:city":"Lemon Grove",
    "sg:classifiers":[
        {
            "category":"Retail",
            "subcategory":"Veterinary Services",
            "type":"Services"
        }
    ],
    "sg:phone":"+1 619 463 0301",
    "sg:postcode":"91945",
    "sg:province":"CA",
    "sg:tags":[
        "veterinarian"
    ],
    "wof:name":"Lemon Grove Veterinary Hospital",
    "wof:placetype":"venue"
},
  "geometry": {"coordinates":[-117.03600299999999,32.7444],"type":"Point"}
}