{
  "type": "Feature",
  "properties": {
    "addr:full":"1151 San Juan St Tustin CA 92780",
    "addr:housenumber":"1151",
    "addr:postcode":"92780",
    "addr:street":"San Juan St",
    "iso:country":"US",
    "sg:address":"1151 San Juan St",
    "sg:city":"Tustin",
    "sg:classifiers":[
        {
            "category":"Social Services",
            "subcategory":"Child Care",
            "type":"Services"
        }
    ],
    "sg:phone":"+1 714 669 1320",
    "sg:postcode":"92780",
    "sg:province":"CA",
    "sg:tags":[
        "day"
    ],
    "wof:name":"Lambert C D C",
    "wof:placetype":"venue"
},
  "geometry": {"coordinates":[-117.817123,33.739641],"type":"Point"}
}