{
  "type": "Feature",
  "properties": {
    "addr:full":"8440 Enterprise Way Oakland CA 94621",
    "addr:housenumber":"8440",
    "addr:postcode":"94621",
    "addr:street":"Enterprise Way",
    "iso:country":"US",
    "sg:address":"8440 Enterprise Way",
    "sg:city":"Oakland",
    "sg:classifiers":[
        {
            "category":"Building & Trades",
            "subcategory":"Landscaping Services",
            "type":"Services"
        }
    ],
    "sg:phone":"+1 510 636 1191",
    "sg:postcode":"94621",
    "sg:province":"CA",
    "sg:tags":[
        "lawn",
        "gardener"
    ],
    "wof:name":"A W L",
    "wof:placetype":"venue"
},
  "geometry": {"coordinates":[-122.193899,37.743196],"type":"Point"}
}