{
  "type": "Feature",
  "properties": {
    "iso:country":"US",
    "sg:address":"307 S Borchard Dr",
    "sg:city":"Ventura",
    "sg:classifiers":[
        {
            "category":"Insurance",
            "subcategory":"Insurance Agent",
            "type":"Services"
        }
    ],
    "sg:phone":"+1 805 648 2384",
    "sg:postcode":"93003",
    "sg:province":"CA",
    "wof:name":"Farmers Insurance Group",
    "wof:placetype":"venue"
},
  "geometry": {"coordinates":[-119.26196899999999,34.269845],"type":"Point"}
}