{
  "type": "Feature",
  "properties": {
    "iso:country":"US",
    "sg:address":"5120 E La Palma Ave Ste 203",
    "sg:city":"Anaheim",
    "sg:classifiers":[
        {
            "category":"Professional",
            "subcategory":"Lawyer & Legal Services",
            "type":"Services"
        }
    ],
    "sg:phone":"+1 714 777 1228",
    "sg:postcode":"92807",
    "sg:province":"CA",
    "wof:name":"Iida Myles Law Offices of",
    "wof:placetype":"venue"
},
  "geometry": {"coordinates":[-117.80500000000001,33.859501],"type":"Point"}
}