{
  "type": "Feature",
  "properties": {
    "addr:full":"317 Culver Blvd Playa Del Rey CA 90293",
    "addr:housenumber":"317",
    "addr:postcode":"90293",
    "addr:street":"Culver Blvd",
    "iso:country":"US",
    "sg:address":"317 Culver Blvd",
    "sg:city":"Playa Del Rey",
    "sg:classifiers":[
        {
            "category":"Food & Beverages",
            "subcategory":"Liquor & Beverages",
            "type":"Retail Goods"
        }
    ],
    "sg:phone":"+1 310 821 2421",
    "sg:postcode":"90293",
    "sg:province":"CA",
    "sg:tags":[
        "beer",
        "spirit",
        "wine"
    ],
    "wof:name":"Sand Dune Liquor Store",
    "wof:placetype":"venue"
},
  "geometry": {"coordinates":[-118.44699900000001,33.960201],"type":"Point"}
}