{
  "type": "Feature",
  "properties": {
    "addr:full":"4601 Student St Ventura CA 93003",
    "addr:housenumber":"4601",
    "addr:postcode":"93003",
    "addr:street":"Student St",
    "iso:country":"US",
    "sg:address":"4601 Student St",
    "sg:city":"Ventura",
    "sg:classifiers":[
        {
            "category":"Building & Trades",
            "subcategory":"Electrical",
            "type":"Services"
        }
    ],
    "sg:phone":"+1 805 644 5466",
    "sg:postcode":"93003",
    "sg:province":"CA",
    "sg:tags":[
        "electric",
        "contractor"
    ],
    "wof:name":"Patterson Electric",
    "wof:placetype":"venue"
},
  "geometry": {"coordinates":[-119.230384,34.274335],"type":"Point"}
}