{
  "type": "Feature",
  "properties": {
    "addr:full":"40780 Fremont Blvd Fremont CA 94538",
    "addr:housenumber":"40780",
    "addr:postcode":"94538",
    "addr:street":"Fremont Blvd",
    "iso:country":"US",
    "sg:address":"40780 Fremont Blvd",
    "sg:city":"Fremont",
    "sg:classifiers":[
        {
            "category":"Real Estate",
            "subcategory":"Real Estate Agent",
            "type":"Services"
        }
    ],
    "sg:phone":"+1 510 656 7653",
    "sg:postcode":"94538",
    "sg:province":"CA",
    "wof:name":"Connolly Real Estate Team",
    "wof:placetype":"venue"
},
  "geometry": {"coordinates":[-121.962735,37.534953],"type":"Point"}
}