{
  "type": "Feature",
  "properties": {
    "addr:full":"989 Franklin St Ste B Oakland CA 94607",
    "addr:housenumber":"989",
    "addr:postcode":"94607",
    "addr:street":"Franklin St Ste B",
    "iso:country":"US",
    "sg:address":"989 Franklin St Ste B",
    "sg:city":"Oakland",
    "sg:classifiers":[
        {
            "category":"Home & Garden",
            "subcategory":"Garden Supply",
            "type":"Retail Goods"
        },
        {
            "category":"Shopping",
            "subcategory":"Gifts & Souvenirs",
            "type":"Retail Goods"
        },
        {
            "category":"Shopping",
            "subcategory":"Crafts & Fabrics",
            "type":"Retail Goods"
        },
        {
            "category":"Shopping",
            "subcategory":"Florist",
            "type":"Retail Goods"
        }
    ],
    "sg:phone":"+1 510 986 1818",
    "sg:postcode":"94607",
    "sg:province":"CA",
    "sg:tags":[
        "plant",
        "etc-retail",
        "dried",
        "basket",
        "trees-silk",
        "flowers"
    ],
    "sg:website":"http://www.fromtheheart.biz",
    "wof:name":"From The Heart Florist",
    "wof:placetype":"venue"
},
  "geometry": {"coordinates":[-122.27172299999999,37.801007],"type":"Point"}
}