{
  "type": "Feature",
  "properties": {
    "iso:country":"US",
    "sg:address":"1790 S Bascom Ave",
    "sg:city":"Campbell",
    "sg:classifiers":[
        {
            "category":"Ice Cream",
            "type":"Food & Drink"
        }
    ],
    "sg:phone":"+1 408 377 9868",
    "sg:postcode":"95008",
    "sg:province":"CA",
    "sg:tags":[
        "frozen",
        "yogurt"
    ],
    "sg:website":"www.yogurt-land.com/",
    "wof:name":"Yogurtland",
    "wof:placetype":"venue"
},
  "geometry": {"coordinates":[-121.93156399999999,37.291275],"type":"Point"}
}