{
  "type": "Feature",
  "properties": {
    "iso:country":"US",
    "sg:address":"3055 Wilshire Blvd",
    "sg:city":"Los Angeles",
    "sg:classifiers":[
        {
            "category":"Professional",
            "subcategory":"Advertising",
            "type":"Services"
        }
    ],
    "sg:phone":"+1 213 252 0544",
    "sg:postcode":"90010",
    "sg:province":"CA",
    "sg:tags":[
        "counselor"
    ],
    "wof:name":"Art Work Co",
    "wof:placetype":"venue"
},
  "geometry": {"coordinates":[-118.287467,34.061892],"type":"Point"}
}