{
  "type": "Feature",
  "properties": {
    "iso:country":"US",
    "sg:address":"3854 Orchid Ln",
    "sg:city":"Calabasas",
    "sg:classifiers":[
        {
            "category":"Wholesale",
            "subcategory":"Machinery & Supplies",
            "type":"Manufacturing & Wholesale Goods"
        }
    ],
    "sg:phone":"+1 818 716 9714",
    "sg:postcode":"91302",
    "sg:province":"CA",
    "sg:tags":[
        "equipment",
        "industrial"
    ],
    "wof:name":"Universal Automation Solutions",
    "wof:placetype":"venue"
},
  "geometry": {"coordinates":[-118.707042,34.128838],"type":"Point"}
}