{
  "type": "Feature",
  "properties": {
    "iso:country":"US",
    "sg:address":"300 MacDonald Ave",
    "sg:city":"Richmond",
    "sg:classifiers":[
        {
            "category":"Travel",
            "subcategory":"Hotels & Motels",
            "type":"Entertainment"
        }
    ],
    "sg:phone":"+1 510 965 1759",
    "sg:postcode":"94801",
    "sg:province":"CA",
    "wof:name":"Point Molate Resort",
    "wof:placetype":"venue"
},
  "geometry": {"coordinates":[-122.366567,37.935697],"type":"Point"}
}