{
  "type": "Feature",
  "properties": {
    "addr:full":"11500 W Olympic Boulevard Los Angeles CA 90064",
    "addr:housenumber":"11500",
    "addr:postcode":"90064",
    "addr:street":"W Olympic Boulevard",
    "iso:country":"US",
    "sg:address":"11500 W Olympic Boulevard",
    "sg:city":"Los Angeles",
    "sg:classifiers":[
        {
            "category":"Health Services",
            "subcategory":"Dentist",
            "type":"Services"
        }
    ],
    "sg:phone":"+1 310 477 1691",
    "sg:postcode":"90064",
    "sg:province":"CA",
    "wof:name":"Feldbaum Morton M DDS",
    "wof:placetype":"venue"
},
  "geometry": {"coordinates":[-118.427233,34.033991],"type":"Point"}
}