{
  "type": "Feature",
  "properties": {
    "addr:full":"1201 South Figueroa Street Los Angeles CA 90015",
    "addr:housenumber":"1201",
    "addr:postcode":"90015",
    "addr:street":"South Figueroa Street",
    "iso:country":"US",
    "sg:address":"1201 South Figueroa Street",
    "sg:city":"Los Angeles",
    "sg:classifiers":[
        {
            "category":"Professional",
            "subcategory":"Employment Agencies",
            "type":"Services"
        }
    ],
    "sg:phone":"+1 800 448 7775",
    "sg:postcode":"90015",
    "sg:province":"CA",
    "sg:website":"www.careerbuilder.com",
    "wof:name":"Careerbuilder.com Job Fair",
    "wof:placetype":"venue"
},
  "geometry": {"coordinates":[-118.26662399999999,34.042148],"type":"Point"}
}