{
  "type": "Feature",
  "properties": {
    "iso:country":"US",
    "sg:address":"319 Santa Monica Blvd",
    "sg:city":"Santa Monica",
    "sg:classifiers":[
        {
            "category":"Professional",
            "type":"Services"
        }
    ],
    "sg:phone":"+1 310 836 0764",
    "sg:postcode":"90401",
    "sg:province":"CA",
    "wof:name":"Speed Jones",
    "wof:placetype":"venue"
},
  "geometry": {"coordinates":[-118.495344,34.016317],"type":"Point"}
}