{
  "type": "Feature",
  "properties": {
    "iso:country":"US",
    "sg:address":"2820 Crow Canyon Rd",
    "sg:city":"San Ramon",
    "sg:classifiers":[
        {
            "category":"Food & Beverages",
            "subcategory":"Groceries & Convenience Stores",
            "type":"Retail Goods"
        }
    ],
    "sg:phone":"+1 925 831 4996",
    "sg:postcode":"94583",
    "sg:province":"CA",
    "wof:name":"Fast Easy Mart 18",
    "wof:placetype":"venue"
},
  "geometry": {"coordinates":[-121.978209,37.775929],"type":"Point"}
}