{
  "type": "Feature",
  "properties": {
    "addr:full":"310 Westlake Center Daly City CA 94015",
    "addr:housenumber":"310",
    "addr:postcode":"94015",
    "addr:street":"Westlake Center",
    "iso:country":"US",
    "sg:address":"310 Westlake Center",
    "sg:city":"Daly City",
    "sg:classifiers":[
        {
            "category":"Ice Cream",
            "type":"Food & Drink"
        }
    ],
    "sg:phone":"+1 650 992 5734",
    "sg:postcode":"94015",
    "sg:province":"CA",
    "sg:tags":[
        "frozen",
        "yogurt"
    ],
    "sg:website":"www.baskinrobbins.com",
    "wof:name":"Baskin Robbins",
    "wof:placetype":"venue"
},
  "geometry": {"coordinates":[-122.483064,37.701039],"type":"Point"}
}