{
  "type": "Feature",
  "properties": {
    "iso:country":"US",
    "sg:address":"25150 Hancock Ave Ste 210",
    "sg:city":"Murrieta",
    "sg:classifiers":[
        {
            "category":"Health Services",
            "subcategory":"Doctor",
            "type":"Services"
        }
    ],
    "sg:phone":"+1 951 461 6988",
    "sg:postcode":"92562",
    "sg:province":"CA",
    "sg:tags":[
        "physician",
        "surgeon",
        "neurology",
        "surgeons"
    ],
    "wof:name":"Abshire Bret Md Ucsd",
    "wof:placetype":"venue"
},
  "geometry": {"coordinates":[-117.182411,33.565849],"type":"Point"}
}