{
  "type": "Feature",
  "properties": {
    "iso:country":"US",
    "sg:address":"514 Kim Pl",
    "sg:city":"Hayward",
    "sg:classifiers":[
        {
            "category":"Real Estate",
            "subcategory":"Real Estate Agent",
            "type":"Services"
        }
    ],
    "sg:phone":"+1 510 782 8511",
    "sg:postcode":"94544",
    "sg:province":"CA",
    "wof:name":"Chaney Properties",
    "wof:placetype":"venue"
},
  "geometry": {"coordinates":[-122.093417,37.649181],"type":"Point"}
}