{
  "type": "Feature",
  "properties": {
    "addr:full":"221 Pine St San Francisco CA 94104",
    "addr:housenumber":"221",
    "addr:postcode":"94104",
    "addr:street":"Pine St",
    "iso:country":"US",
    "sg:address":"221 Pine St",
    "sg:city":"San Francisco",
    "sg:classifiers":[
        {
            "category":"Professional",
            "type":"Services"
        }
    ],
    "sg:phone":"+1 415 834 9095",
    "sg:postcode":"94104",
    "sg:province":"CA",
    "sg:tags":[
        "establishment"
    ],
    "wof:name":"Chan So Wah & Sons Inc",
    "wof:placetype":"venue"
},
  "geometry": {"coordinates":[-122.400732,37.792065],"type":"Point"}
}