{
  "type": "Feature",
  "properties": {
    "iso:country":"US",
    "sg:address":"1938 N Beale Rd",
    "sg:city":"Marysville",
    "sg:classifiers":[
        {
            "category":"Professional",
            "subcategory":"Accounting & Tax Preparation",
            "type":"Services"
        },
        {
            "category":"Insurance",
            "subcategory":"Hazard Insurance",
            "type":"Services"
        }
    ],
    "sg:phone":"+1 530 741 2001",
    "sg:postcode":"95901",
    "sg:province":"CA",
    "sg:tags":[
        "commercial",
        "return",
        "business",
        "preparation-business"
    ],
    "sg:website":"http://www.pena1stop.com",
    "wof:name":"Pena Insurance & Tax Services",
    "wof:placetype":"venue"
},
  "geometry": {"coordinates":[-121.545934,39.127864],"type":"Point"}
}