{
  "type": "Feature",
  "properties": {
    "addr:full":"1421 Secret Ravine Pkwy Ste 101 Roseville CA 95661",
    "addr:housenumber":"1421",
    "addr:postcode":"95661",
    "addr:street":"Secret Ravine Pkwy Ste 101",
    "iso:country":"US",
    "sg:address":"1421 Secret Ravine Pkwy Ste 101",
    "sg:city":"Roseville",
    "sg:classifiers":[
        {
            "category":"Health Services",
            "subcategory":"Dentist",
            "type":"Services"
        }
    ],
    "sg:phone":"+1 916 781 3743",
    "sg:postcode":"95661",
    "sg:province":"CA",
    "sg:tags":[
        "dentists-endodontists"
    ],
    "wof:name":"Doms A Rocklin DDS",
    "wof:placetype":"venue"
},
  "geometry": {"coordinates":[-121.243971,38.76423],"type":"Point"}
}