{
  "type": "Feature",
  "properties": {
    "addr:full":"6380 Wilshire Blvd Los Angeles CA 90048",
    "addr:housenumber":"6380",
    "addr:postcode":"90048",
    "addr:street":"Wilshire Blvd",
    "iso:country":"US",
    "sg:address":"6380 Wilshire Blvd",
    "sg:city":"Los Angeles",
    "sg:classifiers":[
        {
            "category":"Professional",
            "subcategory":"Employment Agencies",
            "type":"Services"
        }
    ],
    "sg:phone":"+1 323 782 7777",
    "sg:postcode":"90048",
    "sg:province":"CA",
    "wof:name":"Pcr Advantage Llc",
    "wof:placetype":"venue"
},
  "geometry": {"coordinates":[-118.36799600000001,34.063599],"type":"Point"}
}