{
  "type": "Feature",
  "properties": {
    "addr:full":"101 Spear St San Francisco CA 94105",
    "addr:housenumber":"101",
    "addr:postcode":"94105",
    "addr:street":"Spear St",
    "iso:country":"US",
    "sg:address":"101 Spear St",
    "sg:city":"San Francisco",
    "sg:classifiers":[
        {
            "category":"Manufacturing",
            "subcategory":"Printing",
            "type":"Manufacturing & Wholesale Goods"
        }
    ],
    "sg:phone":"+1 415 227 1669",
    "sg:postcode":"94105",
    "sg:province":"CA",
    "sg:tags":[
        "publisher",
        "software"
    ],
    "sg:website":"www.rippleeffects.com",
    "wof:name":"Ripple Effects",
    "wof:placetype":"venue"
},
  "geometry": {"coordinates":[-122.39252500000001,37.791311],"type":"Point"}
}