{
  "type": "Feature",
  "properties": {
    "addr:full":"42150 Blacow Rd Fremont CA 94538",
    "addr:postcode":"42150;94538",
    "addr:street":"Blacow Rd",
    "iso:country":"US",
    "sg:address":"42150 Blacow Rd",
    "sg:city":"Fremont",
    "sg:classifiers":[
        {
            "category":"Real Estate",
            "subcategory":"Real Estate Agent",
            "type":"Services"
        }
    ],
    "sg:phone":"+1 510 979 9790",
    "sg:postcode":"94538",
    "sg:province":"CA",
    "wof:name":"King Real Estate",
    "wof:placetype":"venue"
},
  "geometry": {"coordinates":[-121.95893100000001,37.523803],"type":"Point"}
}