{
  "type": "Feature",
  "properties": {
    "iso:country":"US",
    "sg:address":"6103 Candor St",
    "sg:city":"Lakewood",
    "sg:classifiers":[
        {
            "category":"Wholesale",
            "subcategory":"Non-durable Goods",
            "type":"Manufacturing & Wholesale Goods"
        }
    ],
    "sg:phone":"+1 562 804 3609",
    "sg:postcode":"90713",
    "sg:province":"CA",
    "wof:name":"Ancient Memory",
    "wof:placetype":"venue"
},
  "geometry": {"coordinates":[-118.112351,33.855564],"type":"Point"}
}