{
  "type": "Feature",
  "properties": {
    "addr:full":"1065 E Hillsdale Boulevard Foster City CA 94404",
    "addr:housenumber":"1065",
    "addr:postcode":"94404",
    "addr:street":"E Hillsdale Boulevard",
    "iso:country":"US",
    "sg:address":"1065 E Hillsdale Boulevard",
    "sg:city":"Foster City",
    "sg:classifiers":[
        {
            "category":"Wholesale",
            "subcategory":"Computers",
            "type":"Manufacturing & Wholesale Goods"
        }
    ],
    "sg:phone":"+1 650 286 1086",
    "sg:postcode":"94404",
    "sg:province":"CA",
    "sg:website":"www.trivad.com",
    "wof:name":"Trivad",
    "wof:placetype":"venue"
},
  "geometry": {"coordinates":[-122.270048,37.560358],"type":"Point"}
}