{
  "type": "Feature",
  "properties": {
    "iso:country":"US",
    "sg:address":"1386 Bello Mar Dr",
    "sg:city":"Encinitas",
    "sg:classifiers":[
        {
            "category":"Wholesale",
            "subcategory":"Machinery & Supplies",
            "type":"Manufacturing & Wholesale Goods"
        }
    ],
    "sg:phone":"+1 760 635 9183",
    "sg:postcode":"92024",
    "sg:province":"CA",
    "sg:tags":[
        "pulley"
    ],
    "sg:website":"www.jjcassociates.com",
    "wof:name":"JJC & Assoc",
    "wof:placetype":"venue"
},
  "geometry": {"coordinates":[-117.27887800000001,33.082994],"type":"Point"}
}