{
  "type": "Feature",
  "properties": {
    "iso:country":"US",
    "sg:address":"1212 Oakland Rd",
    "sg:city":"San Jose",
    "sg:classifiers":[
        {
            "category":"Building & Trades",
            "subcategory":"Electrical",
            "type":"Services"
        }
    ],
    "sg:phone":"+1 408 436 1627",
    "sg:postcode":"95112",
    "sg:province":"CA",
    "sg:tags":[
        "electrical",
        "contractor"
    ],
    "wof:name":"B GS Electrical Service",
    "wof:placetype":"venue"
},
  "geometry": {"coordinates":[-121.89171,37.364694],"type":"Point"}
}