{
  "type": "Feature",
  "properties": {
    "addr:full":"342 Central Ave Fillmore CA 93015",
    "addr:housenumber":"342",
    "addr:postcode":"93015",
    "addr:street":"Central Ave",
    "iso:country":"US",
    "sg:address":"342 Central Ave",
    "sg:city":"Fillmore",
    "sg:classifiers":[
        {
            "category":"Personal",
            "subcategory":"Tanning Parlor",
            "type":"Services"
        }
    ],
    "sg:phone":"+1 805 524 0201",
    "sg:postcode":"93015",
    "sg:province":"CA",
    "sg:tags":[
        "salon"
    ],
    "wof:name":"Oasis Tanning Salon",
    "wof:placetype":"venue"
},
  "geometry": {"coordinates":[-118.913775,34.400669],"type":"Point"}
}