{
  "type": "Feature",
  "properties": {
    "iso:country":"US",
    "sg:address":"2360 E Bidwell St",
    "sg:city":"Folsom",
    "sg:classifiers":[
        {
            "category":"Banks & Credit Unions",
            "subcategory":"Bank",
            "type":"Services"
        }
    ],
    "sg:phone":"+1 916 984 3900",
    "sg:postcode":"95630",
    "sg:province":"CA",
    "sg:tags":[
        "broker",
        "mortgage"
    ],
    "wof:name":"Morrison Financial Svcs LLC",
    "wof:placetype":"venue"
},
  "geometry": {"coordinates":[-121.152823,38.669048],"type":"Point"}
}