{
  "type": "Feature",
  "properties": {
    "addr:full":"425 Hartnell Rd Santa Maria CA 93455",
    "addr:housenumber":"425",
    "addr:postcode":"93455",
    "addr:street":"Hartnell Rd",
    "iso:country":"US",
    "sg:address":"425 Hartnell Rd",
    "sg:city":"Santa Maria",
    "sg:classifiers":[
        {
            "category":"Government",
            "subcategory":"Office",
            "type":"Public Place"
        }
    ],
    "sg:phone":"+1 805 528 7980",
    "sg:postcode":"93455",
    "sg:province":"CA",
    "sg:tags":[
        "enforcement",
        "law",
        "agency"
    ],
    "wof:name":"Special Agent-Los Osos Cal",
    "wof:placetype":"venue"
},
  "geometry": {"coordinates":[-120.43881500000001,34.867971],"type":"Point"}
}