{
  "type": "Feature",
  "properties": {
    "addr:full":"1830 Valpreda St Burbank CA 91504",
    "addr:postcode":"1830;91504",
    "addr:street":"Valpreda St",
    "iso:country":"US",
    "sg:address":"1830 Valpreda St",
    "sg:city":"Burbank",
    "sg:classifiers":[
        {
            "category":"Manufacturing",
            "subcategory":"Printing",
            "type":"Manufacturing & Wholesale Goods"
        }
    ],
    "sg:phone":"+1 818 840 0288",
    "sg:postcode":"91504",
    "sg:province":"CA",
    "wof:name":"Seven Worldwide Inc",
    "wof:placetype":"venue"
},
  "geometry": {"coordinates":[-118.332972,34.193138],"type":"Point"}
}