{
  "type": "Feature",
  "properties": {
    "addr:full":"1220 W Nance St Perris CA 92571",
    "addr:housenumber":"1220",
    "addr:postcode":"92571",
    "addr:street":"W Nance St",
    "iso:country":"US",
    "sg:address":"1220 W Nance St",
    "sg:city":"Perris",
    "sg:classifiers":[
        {
            "category":"Shopping",
            "type":"Retail Goods"
        }
    ],
    "sg:phone":"+1 951 943 8978",
    "sg:postcode":"92571",
    "sg:province":"CA",
    "sg:tags":[
        "cards",
        "sport",
        "baseball",
        "memorabilia"
    ],
    "wof:name":"Best Image",
    "wof:placetype":"venue"
},
  "geometry": {"coordinates":[-117.244822,33.855577],"type":"Point"}
}