{
  "type": "Feature",
  "properties": {
    "addr:city":"Longbeach",
    "addr:full":"6442 El Paseo St Longbeach, Ca 90815-3403",
    "addr:house_number":"6442",
    "addr:housenumber":"6442",
    "addr:phone":"+1 562-431-4003",
    "addr:postcode":"90815-3403",
    "addr:road":"El Paseo St",
    "addr:state":"CA",
    "addr:street":"E El Paseo St",
    "iso:country":"US",
    "sg:address":"6442 E el Paseo St",
    "sg:city":"Long Beach",
    "sg:classifiers":[
        {
            "category":"Government",
            "subcategory":"Office",
            "type":"Public Place"
        }
    ],
    "sg:phone":"+1 562 431 4003",
    "sg:postcode":"90815",
    "sg:province":"CA",
    "sg:tags":[
        "conservation"
    ],
    "wof:airports":[
        102531511,
        102528985
    ],
    "wof:name":"International Wildlife Carvers Association",
    "wof:placetype":"venue"
},
  "geometry": {"coordinates":[-118.10626999999999,33.79423],"type":"Point"}
}