{
  "type": "Feature",
  "properties": {
    "addr:full":"6442 E el Paseo St Long Beach CA 90815",
    "addr:housenumber":"6442",
    "addr:postcode":"90815",
    "addr:street":"E El Paseo St",
    "iso:country":"US",
    "sg:address":"6442 E el Paseo St",
    "sg:city":"Long Beach",
    "sg:classifiers":[
        {
            "category":"Government",
            "subcategory":"Office",
            "type":"Public Place"
        }
    ],
    "sg:phone":"+1 562 431 4003",
    "sg:postcode":"90815",
    "sg:province":"CA",
    "sg:tags":[
        "conservation"
    ],
    "wof:name":"Interntnal Wldlife Crvers Assn",
    "wof:placetype":"venue"
},
  "geometry": {"coordinates":[-118.10765000000001,33.794439],"type":"Point"}
}