{
  "type": "Feature",
  "properties": {
    "addr:full":"4127 Pallon Ct San Diego CA 92124",
    "addr:housenumber":"4127",
    "addr:postcode":"92124",
    "addr:street":"Pallon Ct",
    "iso:country":"US",
    "sg:address":"4127 Pallon Ct",
    "sg:city":"San Diego",
    "sg:classifiers":[
        {
            "category":"Banks & Credit Unions",
            "subcategory":"Financial Services",
            "type":"Services"
        }
    ],
    "sg:phone":"+1 858 277 8646",
    "sg:postcode":"92124",
    "sg:province":"CA",
    "sg:tags":[
        "trust",
        "management"
    ],
    "wof:name":"Cox Revocable Living Trust",
    "wof:placetype":"venue"
},
  "geometry": {"coordinates":[-117.08853499999999,32.819247],"type":"Point"}
}