{
  "type": "Feature",
  "properties": {
    "addr:full":"4935 McConnell Ave Los Angeles CA 90066",
    "addr:housenumber":"4935",
    "addr:postcode":"90066",
    "addr:street":"Mcconnell Ave",
    "iso:country":"US",
    "sg:address":"4935 McConnell Ave",
    "sg:city":"Los Angeles",
    "sg:classifiers":[
        {
            "category":"Shopping",
            "subcategory":"Shoes",
            "type":"Retail Goods"
        }
    ],
    "sg:phone":"+1 310 827 8024",
    "sg:postcode":"90066",
    "sg:province":"CA",
    "sg:tags":[
        "store"
    ],
    "wof:name":"Warehouse Shoe Sale",
    "wof:placetype":"venue"
},
  "geometry": {"coordinates":[-118.424376,33.982585],"type":"Point"}
}