{
  "type": "Feature",
  "properties": {
    "addr:full":"613 W Valley Pkwy Escondido CA 92025",
    "addr:housenumber":"613",
    "addr:postcode":"92025",
    "addr:street":"W Valley Pkwy",
    "iso:country":"US",
    "sg:address":"613 W Valley Pkwy",
    "sg:city":"Escondido",
    "sg:classifiers":[
        {
            "category":"Banks & Credit Unions",
            "subcategory":"Bank",
            "type":"Services"
        }
    ],
    "sg:phone":"+1 760 741 3312",
    "sg:postcode":"92025",
    "sg:province":"CA",
    "wof:name":"California Bank & Trust",
    "wof:placetype":"venue"
},
  "geometry": {"coordinates":[-117.09039799999999,33.118374],"type":"Point"}
}