{
  "type": "Feature",
  "properties": {
    "iso:country":"US",
    "sg:address":"240 N H St",
    "sg:city":"Fresno",
    "sg:classifiers":[
        {
            "category":"Restaurant",
            "type":"Food & Drink"
        }
    ],
    "sg:phone":"+1 559 237 7455",
    "sg:postcode":"93701",
    "sg:province":"CA",
    "sg:tags":[
        "barbecue"
    ],
    "wof:name":"T J's Barbeque & More",
    "wof:placetype":"venue"
},
  "geometry": {"coordinates":[-119.80807,36.746598],"type":"Point"}
}