{
  "type": "Feature",
  "properties": {
    "addr:full":"11845 W Olympic Blvd Los Angeles CA 90064",
    "addr:housenumber":"11845",
    "addr:postcode":"90064",
    "addr:street":"W Olympic Blvd",
    "iso:country":"US",
    "sg:address":"11845 W Olympic Blvd",
    "sg:city":"Los Angeles",
    "sg:classifiers":[
        {
            "category":"Building & Trades",
            "subcategory":"Construction",
            "type":"Services"
        }
    ],
    "sg:phone":"+1 310 312 8200",
    "sg:postcode":"90064",
    "sg:province":"CA",
    "sg:tags":[
        "contractor"
    ],
    "wof:name":"Trimax Construction Corp",
    "wof:placetype":"venue"
},
  "geometry": {"coordinates":[-118.453254,34.032552],"type":"Point"}
}