{
  "type": "Feature",
  "properties": {
    "iso:country":"US",
    "sg:address":"6621 San Fernando Rd",
    "sg:city":"Glendale",
    "sg:classifiers":[
        {
            "category":"Retail",
            "subcategory":"Auto Repair",
            "type":"Services"
        }
    ],
    "sg:phone":"+1 818 243 2574",
    "sg:postcode":"91201",
    "sg:province":"CA",
    "wof:name":"Juan's Auto Repair",
    "wof:placetype":"venue"
},
  "geometry": {"coordinates":[-118.29299899999999,34.169201],"type":"Point"}
}