{
  "type": "Feature",
  "properties": {
    "iso:country":"US",
    "sg:address":"1332 Anacapa St",
    "sg:city":"Santa Barbara",
    "sg:classifiers":[
        {
            "category":"Banks & Credit Unions",
            "subcategory":"Bank",
            "type":"Services"
        }
    ],
    "sg:phone":"+1 805 564 5062",
    "sg:postcode":"93101",
    "sg:province":"CA",
    "sg:tags":[
        "loan",
        "real estate"
    ],
    "wof:name":"Wells Fargo Home Mortgage Inc",
    "wof:placetype":"venue"
},
  "geometry": {"coordinates":[-119.70573,34.426281],"type":"Point"}
}