{
  "type": "Feature",
  "properties": {
    "iso:country":"US",
    "sg:address":"3611 Cahuenga Blvd W",
    "sg:city":"Los Angeles",
    "sg:classifiers":[
        {
            "category":"Wholesale",
            "subcategory":"Electrical",
            "type":"Manufacturing & Wholesale Goods"
        }
    ],
    "sg:phone":"+1 323 876 5454",
    "sg:postcode":"90068",
    "sg:province":"CA",
    "sg:tags":[
        "shaver"
    ],
    "sg:website":"www.parksproducts.com",
    "wof:name":"Parks Products",
    "wof:placetype":"venue"
},
  "geometry": {"coordinates":[-118.360894,34.134751],"type":"Point"}
}