{
  "type": "Feature",
  "properties": {
    "addr:full":"2667 Cam del Rio S San Diego CA 92108",
    "addr:housenumber":"2667",
    "addr:postcode":"92108",
    "addr:street":"Cam Del Rio S",
    "iso:country":"US",
    "sg:address":"2667 Cam del Rio S",
    "sg:city":"San Diego",
    "sg:classifiers":[
        {
            "category":"Health Services",
            "subcategory":"Clinic",
            "type":"Services"
        }
    ],
    "sg:phone":"+1 619 497 1107",
    "sg:postcode":"92108",
    "sg:province":"CA",
    "wof:name":"Nightingale Home Health Care",
    "wof:placetype":"venue"
},
  "geometry": {"coordinates":[-117.135869,32.769924],"type":"Point"}
}