{
  "type": "Feature",
  "properties": {
    "addr:full":"230 Cochrane Plz Morgan Hill CA 95037",
    "addr:housenumber":"230",
    "addr:postcode":"95037",
    "addr:street":"Cochrane Plz",
    "iso:country":"US",
    "sg:address":"230 Cochrane Plz",
    "sg:city":"Morgan Hill",
    "sg:classifiers":[
        {
            "category":"Ice Cream",
            "type":"Food & Drink"
        }
    ],
    "sg:menulink":"http://www.allmenus.com/ca/san-jose/242406-baskin-robbins/menu/",
    "sg:phone":"+1 408 776 8037",
    "sg:postcode":"95037",
    "sg:province":"CA",
    "sg:tags":[
        "american"
    ],
    "wof:name":"Baskin-Robbins",
    "wof:placetype":"venue"
},
  "geometry": {"coordinates":[-121.654957,37.150727],"type":"Point"}
}