{
  "type": "Feature",
  "properties": {
    "addr:full":"11641 Pike St Santa Fe Springs CA 90670",
    "addr:housenumber":"11641",
    "addr:postcode":"90670",
    "addr:street":"Pike St",
    "iso:country":"US",
    "sg:address":"11641 Pike St",
    "sg:city":"Santa Fe Springs",
    "sg:classifiers":[
        {
            "category":"Manufacturing",
            "subcategory":"Chemicals & Compounds",
            "type":"Manufacturing & Wholesale Goods"
        }
    ],
    "sg:phone":"+1 562 908 0405",
    "sg:postcode":"90670",
    "sg:province":"CA",
    "sg:tags":[
        "preparation",
        "s",
        "gd",
        "mfg"
    ],
    "wof:name":"Chemifax",
    "wof:placetype":"venue"
},
  "geometry": {"coordinates":[-118.074513,33.955905],"type":"Point"}
}