{
  "type": "Feature",
  "properties": {
    "iso:country":"US",
    "sg:address":"101 E Channel Rd",
    "sg:city":"Benicia",
    "sg:classifiers":[
        {
            "category":"Manufacturing",
            "subcategory":"Metals",
            "type":"Manufacturing & Wholesale Goods"
        }
    ],
    "sg:phone":"+1 707 745 8111",
    "sg:postcode":"94510",
    "sg:province":"CA",
    "sg:tags":[
        "machine",
        "plate",
        "work",
        "fabricated",
        "shop"
    ],
    "wof:name":"Benicia Fabrication & Machine",
    "wof:placetype":"venue"
},
  "geometry": {"coordinates":[-122.137342,38.079346],"type":"Point"}
}