{
  "type": "Feature",
  "properties": {
    "addr:full":"435 N 8th St Brawley CA 92227",
    "addr:housenumber":"435",
    "addr:postcode":"92227",
    "addr:street":"N 8Th St",
    "iso:country":"US",
    "sg:address":"435 N 8th St",
    "sg:city":"Brawley",
    "sg:classifiers":[
        {
            "category":"Retail",
            "subcategory":"Repair Shop",
            "type":"Services"
        }
    ],
    "sg:phone":"+1 760 344 3640",
    "sg:postcode":"92227",
    "sg:province":"CA",
    "sg:tags":[
        "upholsterer"
    ],
    "wof:name":"Flores Brothers Upholstery Shp",
    "wof:placetype":"venue"
},
  "geometry": {"coordinates":[-115.52932199999999,32.982682],"type":"Point"}
}