{
  "type": "Feature",
  "properties": {
    "addr:full":"238 S Mission Rd Los Angeles CA 90033",
    "addr:housenumber":"238",
    "addr:postcode":"90033",
    "addr:street":"S Mission Rd",
    "iso:country":"US",
    "sg:address":"238 S Mission Rd",
    "sg:city":"Los Angeles",
    "sg:classifiers":[
        {
            "category":"Wholesale",
            "subcategory":"Home Furnishings",
            "type":"Manufacturing & Wholesale Goods"
        }
    ],
    "sg:phone":"+1 323 780 2788",
    "sg:postcode":"90033",
    "sg:province":"CA",
    "wof:name":"Topco Overseas Co",
    "wof:placetype":"venue"
},
  "geometry": {"coordinates":[-118.22761,34.044716],"type":"Point"}
}