{
  "type": "Feature",
  "properties": {
    "iso:country":"US",
    "sg:address":"2029 E 1st Street",
    "sg:city":"Los Angeles",
    "sg:classifiers":[
        {
            "category":"Shopping",
            "subcategory":"Department Store",
            "type":"Retail Goods"
        }
    ],
    "sg:phone":"+1 323 264 6602",
    "sg:postcode":"90033",
    "sg:province":"CA",
    "wof:name":"98 Cents Express Discount Store",
    "wof:placetype":"venue"
},
  "geometry": {"coordinates":[-118.213995,34.045134],"type":"Point"}
}