{
  "type": "Feature",
  "properties": {
    "addr:full":"3010 I St Sacramento CA 95816",
    "addr:housenumber":"3010",
    "addr:postcode":"95816",
    "addr:street":"I St",
    "iso:country":"US",
    "sg:address":"3010 I St",
    "sg:city":"Sacramento",
    "sg:classifiers":[
        {
            "category":"Social Services",
            "type":"Services"
        }
    ],
    "sg:phone":"+1 916 444 7388",
    "sg:postcode":"95816",
    "sg:province":"CA",
    "sg:tags":[
        "worker"
    ],
    "wof:name":"Rosalie G Roth",
    "wof:placetype":"venue"
},
  "geometry": {"coordinates":[-121.46486400000001,38.573821],"type":"Point"}
}