{
  "type": "Feature",
  "properties": {
    "addr:full":"1534 Rollins Road Burlingame CA 94010",
    "addr:housenumber":"1534",
    "addr:postcode":"94010",
    "addr:street":"Rollins Road",
    "iso:country":"US",
    "sg:address":"1534 Rollins Road",
    "sg:city":"Burlingame",
    "sg:classifiers":[
        {
            "category":"Professional",
            "type":"Services"
        }
    ],
    "sg:phone":"+1 650 692 2315",
    "sg:postcode":"94010",
    "sg:province":"CA",
    "sg:tags":[
        "caterer"
    ],
    "wof:name":"Yamato Flight Kitchen",
    "wof:placetype":"venue"
},
  "geometry": {"coordinates":[-122.371089,37.59346],"type":"Point"}
}