{
  "type": "Feature",
  "properties": {
    "addr:full":"9460 Mira Mesa Blvd San Diego CA 92126",
    "addr:housenumber":"9460",
    "addr:postcode":"92126",
    "addr:street":"Mira Mesa Blvd",
    "iso:country":"US",
    "sg:address":"9460 Mira Mesa Blvd",
    "sg:city":"San Diego",
    "sg:classifiers":[
        {
            "category":"Home & Garden",
            "subcategory":"Household Appliances",
            "type":"Retail Goods"
        }
    ],
    "sg:phone":"+1 858 586 7100",
    "sg:postcode":"92126",
    "sg:province":"CA",
    "sg:tags":[
        "cleaners",
        "vacuum"
    ],
    "wof:name":"Oreck Floor Care Ctr",
    "wof:placetype":"venue"
},
  "geometry": {"coordinates":[-117.122843,32.917255],"type":"Point"}
}