{
  "type": "Feature",
  "properties": {
    "iso:country":"US",
    "sg:address":"467 N Wilma Ave",
    "sg:city":"Ripon",
    "sg:classifiers":[
        {
            "category":"Education",
            "subcategory":"Dance Studio",
            "type":"Public Place"
        }
    ],
    "sg:phone":"+1 209 599 1161",
    "sg:postcode":"95366",
    "sg:province":"CA",
    "sg:tags":[
        "instruction",
        "dancing"
    ],
    "sg:website":"www.dancersincorporated.com",
    "wof:name":"Dancer's Inc",
    "wof:placetype":"venue"
},
  "geometry": {"coordinates":[-121.135559,37.743667],"type":"Point"}
}