{
  "type": "Feature",
  "properties": {
    "addr:full":"3230 Mitchell Rd Ceres CA 95307",
    "addr:housenumber":"3230",
    "addr:postcode":"95307",
    "addr:street":"Mitchell Rd",
    "iso:country":"US",
    "sg:address":"3230 Mitchell Rd",
    "sg:city":"Ceres",
    "sg:classifiers":[
        {
            "category":"Utilities",
            "subcategory":"Mobile Phone",
            "type":"Services"
        }
    ],
    "sg:phone":"+1 209 531 1300",
    "sg:postcode":"95307",
    "sg:province":"CA",
    "sg:tags":[
        "communication",
        "telephone",
        "cellular",
        "radiotelephone"
    ],
    "wof:name":"Sunstar Wireless Plus",
    "wof:placetype":"venue"
},
  "geometry": {"coordinates":[-120.938697,37.590951],"type":"Point"}
}