{
  "type": "Feature",
  "properties": {
    "iso:country":"US",
    "sg:address":"1733 1/2 Sacramento St",
    "sg:city":"Berkeley",
    "sg:classifiers":[
        {
            "category":"Sports & Exercise",
            "subcategory":"Playing Field",
            "type":"Entertainment"
        }
    ],
    "sg:phone":"+1 510 239 6842",
    "sg:postcode":"94703",
    "sg:province":"CA",
    "sg:tags":[
        "instruction",
        "fitness"
    ],
    "wof:name":"Capoeirobics",
    "wof:placetype":"venue"
},
  "geometry": {"coordinates":[-122.28220399999999,37.873599],"type":"Point"}
}