{
  "type": "Feature",
  "properties": {
    "iso:country":"US",
    "sg:address":"2425 E Curtis Ct",
    "sg:city":"Glendora",
    "sg:classifiers":[
        {
            "category":"Freight",
            "type":"Transportation"
        }
    ],
    "sg:phone":"+1 626 963 9787",
    "sg:postcode":"91741",
    "sg:province":"CA",
    "sg:tags":[
        "operator",
        "equipment",
        "local",
        "trucking"
    ],
    "wof:name":"Skip Eckardt Service Inc",
    "wof:placetype":"venue"
},
  "geometry": {"coordinates":[-117.82023100000001,34.127556],"type":"Point"}
}