{
  "type": "Feature",
  "properties": {
    "addr:full":"8 Equestrian Ct Novato CA 94945",
    "addr:housenumber":"8",
    "addr:postcode":"94945",
    "addr:street":"Equestrian Ct",
    "iso:country":"US",
    "sg:address":"8 Equestrian Ct",
    "sg:city":"Novato",
    "sg:classifiers":[
        {
            "category":"Building & Trades",
            "subcategory":"Landscaping Services",
            "type":"Services"
        }
    ],
    "sg:phone":"+1 415 899 9721",
    "sg:postcode":"94945",
    "sg:province":"CA",
    "sg:tags":[
        "landscape"
    ],
    "wof:name":"Eric Rayner Landscaping",
    "wof:placetype":"venue"
},
  "geometry": {"coordinates":[-122.557526,38.115293],"type":"Point"}
}