{
  "type": "Feature",
  "properties": {
    "iso:country":"US",
    "sg:address":"779 Contada Cir",
    "sg:city":"Danville",
    "sg:classifiers":[
        {
            "category":"Shopping",
            "subcategory":"Catalog Store",
            "type":"Retail Goods"
        }
    ],
    "sg:phone":"+1 925 831 2938",
    "sg:postcode":"94526",
    "sg:province":"CA",
    "sg:tags":[
        "e"
    ],
    "wof:name":"Bnw Ventures LLC",
    "wof:placetype":"venue"
},
  "geometry": {"coordinates":[-121.986904,37.820695],"type":"Point"}
}