{
  "type": "Feature",
  "properties": {
    "iso:country":"US",
    "sg:address":"13771 S Prescott Rd",
    "sg:city":"Manteca",
    "sg:classifiers":[
        {
            "category":"Building & Trades",
            "subcategory":"Pest Control",
            "type":"Services"
        }
    ],
    "sg:phone":"+1 209 982 4338",
    "sg:postcode":"95336",
    "sg:province":"CA",
    "sg:tags":[
        "insecticide"
    ],
    "wof:name":"Pacific Southwest Irrigation",
    "wof:placetype":"venue"
},
  "geometry": {"coordinates":[-121.16695,37.839317],"type":"Point"}
}