{
  "type": "Feature",
  "properties": {
    "iso:country":"US",
    "sg:address":"1640 Camino Del Rio N Level 1, Store 1222",
    "sg:city":"San Diego",
    "sg:classifiers":[
        {
            "category":"Shopping",
            "subcategory":"Luggage & Leather Goods",
            "type":"Retail Goods"
        }
    ],
    "sg:phone":"+1 619 291 9191",
    "sg:postcode":"92108",
    "sg:province":"CA",
    "wof:name":"VIP Luggage & Gifts",
    "wof:placetype":"venue"
},
  "geometry": {"coordinates":[-117.14668500000001,32.767784],"type":"Point"}
}