{
  "type": "Feature",
  "properties": {
    "addr:full":"1889 Union St San Francisco CA 94123",
    "addr:housenumber":"1889",
    "addr:postcode":"94123",
    "addr:street":"Union St",
    "iso:country":"US",
    "sg:address":"1889 Union St",
    "sg:city":"San Francisco",
    "sg:classifiers":[
        {
            "category":"Personal",
            "subcategory":"Beauty Salon",
            "type":"Services"
        }
    ],
    "sg:phone":"+1 415 776 7010",
    "sg:postcode":"94123",
    "sg:province":"CA",
    "wof:name":"Lila Tchaickosky",
    "wof:placetype":"venue"
},
  "geometry": {"coordinates":[-122.429379,37.79783],"type":"Point"}
}