{
  "type": "Feature",
  "properties": {
    "iso:country":"US",
    "sg:address":"24964 State Hwy 74",
    "sg:city":"Perris",
    "sg:classifiers":[
        {
            "category":"Organizations",
            "subcategory":"Religious Organization",
            "type":"Services"
        }
    ],
    "sg:phone":"+1 951 943 1988",
    "sg:postcode":"92570",
    "sg:province":"CA",
    "sg:tags":[
        "church"
    ],
    "wof:name":"Bible Tabernacle Fellowship",
    "wof:placetype":"venue"
},
  "geometry": {"coordinates":[-117.271432,33.75815],"type":"Point"}
}