{
  "type": "Feature",
  "properties": {
    "iso:country":"US",
    "sg:address":"7439 Mission Gorge Rd",
    "sg:city":"San Diego",
    "sg:classifiers":[
        {
            "category":"Shopping",
            "subcategory":"Crafts & Fabrics",
            "type":"Retail Goods"
        }
    ],
    "sg:phone":"+1 619 287 4788",
    "sg:postcode":"92120",
    "sg:province":"CA",
    "sg:tags":[
        "sewing"
    ],
    "wof:name":"Stitch-A-Cross",
    "wof:placetype":"venue"
},
  "geometry": {"coordinates":[-117.079005,32.806739],"type":"Point"}
}