{
  "type": "Feature",
  "properties": {
    "addr:full":"1808 N Chester Ave Bakersfield CA 93308",
    "addr:housenumber":"1808",
    "addr:postcode":"93308",
    "addr:street":"N Chester Ave",
    "iso:country":"US",
    "sg:address":"1808 N Chester Ave",
    "sg:city":"Bakersfield",
    "sg:classifiers":[
        {
            "category":"Shopping",
            "subcategory":"Used Merchandise",
            "type":"Retail Goods"
        }
    ],
    "sg:phone":"+1 661 393 2294",
    "sg:postcode":"93308",
    "sg:province":"CA",
    "sg:tags":[
        "furniture"
    ],
    "wof:name":"Fiddle Stix Used Furniture",
    "wof:placetype":"venue"
},
  "geometry": {"coordinates":[-119.02113,35.423128],"type":"Point"}
}