{
  "type": "Feature",
  "properties": {
    "addr:full":"4326 Atlantic Ave Long Beach CA 90807",
    "addr:housenumber":"4326",
    "addr:postcode":"90807",
    "addr:street":"Atlantic Ave",
    "iso:country":"US",
    "sg:address":"4326 Atlantic Ave",
    "sg:city":"Long Beach",
    "sg:classifiers":[
        {
            "category":"Professional",
            "subcategory":"Lawyer & Legal Services",
            "type":"Services"
        }
    ],
    "sg:phone":"+1 562 424 0502",
    "sg:postcode":"90807",
    "sg:province":"CA",
    "sg:tags":[
        "divorce",
        "attorney",
        "law",
        "family"
    ],
    "sg:website":"www.rothenberglaw.net",
    "wof:name":"Law Firm of Marc S. Rothenberg",
    "wof:placetype":"venue"
},
  "geometry": {"coordinates":[-118.18499799999999,33.8354],"type":"Point"}
}