{
  "type": "Feature",
  "properties": {
    "addr:full":"4706 Balboa Blvd Encino CA 91316",
    "addr:housenumber":"4706",
    "addr:postcode":"91316",
    "addr:street":"Balboa Blvd",
    "iso:country":"US",
    "sg:address":"4706 Balboa Blvd",
    "sg:city":"Encino",
    "sg:classifiers":[
        {
            "category":"Building & Trades",
            "subcategory":"Electrical",
            "type":"Services"
        }
    ],
    "sg:phone":"+1 818 783 3014",
    "sg:postcode":"91316",
    "sg:province":"CA",
    "sg:tags":[
        "electric",
        "contractor"
    ],
    "wof:name":"Electrical Nutrition",
    "wof:placetype":"venue"
},
  "geometry": {"coordinates":[-118.50425199999999,34.153669],"type":"Point"}
}