{
  "type": "Feature",
  "properties": {
    "iso:country":"US",
    "sg:address":"1131 Old Woman Springs Rd",
    "sg:city":"Yucca Valley",
    "sg:classifiers":[
        {
            "category":"Retail",
            "subcategory":"Auto Repair",
            "type":"Services"
        }
    ],
    "sg:phone":"+1 760 364 1131",
    "sg:postcode":"92284",
    "sg:province":"CA",
    "sg:tags":[
        "repairing",
        "automobile"
    ],
    "wof:name":"Ott's Auto Repair",
    "wof:placetype":"venue"
},
  "geometry": {"coordinates":[-116.439542,34.232778],"type":"Point"}
}