{
  "type": "Feature",
  "properties": {
    "addr:full":"6061 N Fresno St Fresno CA 93710",
    "addr:housenumber":"6061",
    "addr:postcode":"93710",
    "addr:street":"N Fresno",
    "iso:country":"US",
    "sg:address":"6061 N Fresno St",
    "sg:city":"Fresno",
    "sg:classifiers":[
        {
            "category":"Real Estate",
            "subcategory":"Real Estate Services",
            "type":"Services"
        },
        {
            "category":"Banks & Credit Unions",
            "subcategory":"Financial Services",
            "type":"Services"
        }
    ],
    "sg:phone":"+1 559 436 6880",
    "sg:postcode":"93710",
    "sg:province":"CA",
    "sg:tags":[
        "buyer",
        "loan",
        "broker",
        "mortgage"
    ],
    "sg:website":"http://www.hilltoplending.com",
    "wof:name":"Elite Mortgage & Financial Service",
    "wof:placetype":"venue"
},
  "geometry": {"coordinates":[-119.78140999999999,36.82415],"type":"Point"}
}