{
  "type": "Feature",
  "properties": {
    "iso:country":"US",
    "sg:address":"2597 Warwick Ln",
    "sg:city":"Santa Cruz",
    "sg:classifiers":[
        {
            "category":"Shopping",
            "type":"Retail Goods"
        }
    ],
    "sg:phone":"+1 831 475 7976",
    "sg:postcode":"95065",
    "sg:province":"CA",
    "sg:tags":[
        "pet",
        "shop"
    ],
    "wof:name":"Santa Cruz Reptiles",
    "wof:placetype":"venue"
},
  "geometry": {"coordinates":[-121.972871,36.991752],"type":"Point"}
}