{
  "type": "Feature",
  "properties": {
    "iso:country":"US",
    "sg:address":"2536 Macgregor Ct",
    "sg:city":"Napa",
    "sg:classifiers":[
        {
            "category":"Manufacturing",
            "subcategory":"Lumber",
            "type":"Manufacturing & Wholesale Goods"
        }
    ],
    "sg:phone":"+1 707 255 8266",
    "sg:postcode":"94558",
    "sg:province":"CA",
    "sg:tags":[
        "operation",
        "timber",
        "tract"
    ],
    "wof:name":"NAPA Valley Orchids",
    "wof:placetype":"venue"
},
  "geometry": {"coordinates":[-122.323053,38.316425],"type":"Point"}
}