{
  "type": "Feature",
  "properties": {
    "addr:full":"5979 Avalon Blvd Los Angeles CA 90003",
    "addr:housenumber":"5979",
    "addr:postcode":"90003",
    "addr:street":"Avalon Blvd",
    "iso:country":"US",
    "sg:address":"5979 Avalon Blvd",
    "sg:city":"Los Angeles",
    "sg:classifiers":[
        {
            "category":"Retail",
            "subcategory":"Auto Repair",
            "type":"Services"
        }
    ],
    "sg:phone":"+1 323 235 6272",
    "sg:postcode":"90003",
    "sg:province":"CA",
    "sg:tags":[
        "body",
        "shop",
        "painting",
        "automobile"
    ],
    "wof:name":"Pacos Body Shop",
    "wof:placetype":"venue"
},
  "geometry": {"coordinates":[-118.264999,33.985298],"type":"Point"}
}