{
  "type": "Feature",
  "properties": {
    "iso:country":"US",
    "sg:address":"24411 Health Center Dr",
    "sg:city":"Laguna Hills",
    "sg:classifiers":[
        {
            "category":"Professional",
            "subcategory":"Business Services",
            "type":"Services"
        }
    ],
    "sg:phone":"+1 949 916 9965",
    "sg:postcode":"92653",
    "sg:province":"CA",
    "sg:tags":[
        "transcribing",
        "disc"
    ],
    "wof:name":"Cynthia K Lyle",
    "wof:placetype":"venue"
},
  "geometry": {"coordinates":[-117.708252,33.607213],"type":"Point"}
}