{
  "type": "Feature",
  "properties": {
    "addr:full":"115 Cherry Blossom Dr San Jose CA 95123",
    "addr:housenumber":"115",
    "addr:postcode":"95123",
    "addr:street":"Cherry Blossom Dr",
    "iso:country":"US",
    "sg:address":"115 Cherry Blossom Dr",
    "sg:city":"San Jose",
    "sg:classifiers":[
        {
            "category":"Social Services",
            "subcategory":"Child Care",
            "type":"Services"
        }
    ],
    "sg:phone":"+1 831 728 3572",
    "sg:postcode":"95123",
    "sg:province":"CA",
    "wof:name":"Cherry Blossom Infant & Child",
    "wof:placetype":"venue"
},
  "geometry": {"coordinates":[-121.816755,37.257174],"type":"Point"}
}