{
  "type": "Feature",
  "properties": {
    "addr:full":"7949 Silverton Ave San Diego CA 92126",
    "addr:housenumber":"7949",
    "addr:postcode":"92126",
    "addr:street":"Silverton Ave",
    "iso:country":"US",
    "sg:address":"7949 Silverton Ave",
    "sg:city":"San Diego",
    "sg:classifiers":[
        {
            "category":"Wholesale",
            "subcategory":"Machinery & Supplies",
            "type":"Manufacturing & Wholesale Goods"
        }
    ],
    "sg:phone":"+1 858 566 5427",
    "sg:postcode":"92126",
    "sg:province":"CA",
    "sg:tags":[
        "equipment",
        "industrial"
    ],
    "wof:name":"California Air Tools",
    "wof:placetype":"venue"
},
  "geometry": {"coordinates":[-117.14842,32.89054],"type":"Point"}
}