{
  "type": "Feature",
  "properties": {
    "addr:full":"1043 Garnet Ave San Diego CA 92109",
    "addr:housenumber":"1043",
    "addr:postcode":"92109",
    "addr:street":"Garnet Ave",
    "iso:country":"US",
    "sg:address":"1043 Garnet Ave",
    "sg:city":"San Diego",
    "sg:classifiers":[
        {
            "category":"Shopping",
            "subcategory":"Clothing, Apparel, & Fashions",
            "type":"Retail Goods"
        },
        {
            "category":"Shopping",
            "subcategory":"Shoes",
            "type":"Retail Goods"
        }
    ],
    "sg:phone":"+1 858 490 0411",
    "sg:postcode":"92109",
    "sg:province":"CA",
    "sg:tags":[
        "store",
        "accessory"
    ],
    "sg:website":"www.shopfwd.com",
    "wof:name":"Forward Footwear",
    "wof:placetype":"venue"
},
  "geometry": {"coordinates":[-117.25080199999999,32.797582],"type":"Point"}
}