{
  "type": "Feature",
  "properties": {
    "addr:full":"37505 Dusterberry Way Fremont CA 94536",
    "addr:housenumber":"37505",
    "addr:postcode":"94536",
    "addr:street":"Dusterberry Way",
    "iso:country":"US",
    "sg:address":"37505 Dusterberry Way",
    "sg:city":"Fremont",
    "sg:classifiers":[
        {
            "category":"Retail",
            "subcategory":"Car Wash",
            "type":"Services"
        }
    ],
    "sg:phone":"+1 510 713 2877",
    "sg:postcode":"94536",
    "sg:province":"CA",
    "sg:tags":[
        "polishing",
        "washing"
    ],
    "wof:name":"Red Carpet Car Wash",
    "wof:placetype":"venue"
},
  "geometry": {"coordinates":[-122.00888,37.553156],"type":"Point"}
}