{
  "type": "Feature",
  "properties": {
    "iso:country":"US",
    "sg:address":"1035 E Sample Ave",
    "sg:city":"Fresno",
    "sg:classifiers":[
        {
            "category":"Building & Trades",
            "subcategory":"Construction",
            "type":"Services"
        }
    ],
    "sg:phone":"+1 559 439 7684",
    "sg:postcode":"93710",
    "sg:province":"CA",
    "sg:tags":[
        "general",
        "contractor"
    ],
    "wof:name":"Forseth Construction",
    "wof:placetype":"venue"
},
  "geometry": {"coordinates":[-119.770532,36.827286],"type":"Point"}
}