{
  "type": "Feature",
  "properties": {
    "addr:full":"7771 Santa Ana Rd Ventura CA 93001",
    "addr:housenumber":"7771",
    "addr:postcode":"93001",
    "addr:street":"Santa Ana Rd",
    "iso:country":"US",
    "sg:address":"7771 Santa Ana Rd",
    "sg:city":"Ventura",
    "sg:classifiers":[
        {
            "category":"Communications",
            "type":"Services"
        }
    ],
    "sg:phone":"+1 805 649 3075",
    "sg:postcode":"93001",
    "sg:province":"CA",
    "sg:tags":[
        "communication"
    ],
    "wof:name":"Communications By Frontrunner",
    "wof:placetype":"venue"
},
  "geometry": {"coordinates":[-119.313806,34.357654],"type":"Point"}
}