{
  "type": "Feature",
  "properties": {
    "addr:full":"34790 Lencioni Ave Bakersfield CA 93308",
    "addr:postcode":"34790;93308",
    "addr:street":"Lencioni Ave",
    "iso:country":"US",
    "sg:address":"34790 Lencioni Ave",
    "sg:city":"Bakersfield",
    "sg:classifiers":[
        {
            "category":"Home & Garden",
            "subcategory":"Building Materials",
            "type":"Retail Goods"
        }
    ],
    "sg:phone":"+1 661 213 3088",
    "sg:postcode":"93308",
    "sg:province":"CA",
    "sg:tags":[
        "energy",
        "conservation",
        "product"
    ],
    "wof:name":"West American Energy Corp.",
    "wof:placetype":"venue"
},
  "geometry": {"coordinates":[-119.084136,35.447343],"type":"Point"}
}