{
  "type": "Feature",
  "properties": {
    "addr:full":"11211 Gold Country Boulevard Gold River CA 95670",
    "addr:housenumber":"11211",
    "addr:postcode":"95670",
    "addr:street":"Gold Country Boulevard",
    "iso:country":"US",
    "sg:address":"11211 Gold Country Boulevard",
    "sg:city":"Gold River",
    "sg:classifiers":[
        {
            "category":"Professional",
            "subcategory":"Accounting & Tax Preparation",
            "type":"Services"
        }
    ],
    "sg:phone":"+1 916 631 3696",
    "sg:postcode":"95670",
    "sg:province":"CA",
    "sg:tags":[
        "accountant"
    ],
    "wof:name":"Nelson Scott G CPA",
    "wof:placetype":"venue"
},
  "geometry": {"coordinates":[-121.26550899999999,38.628158],"type":"Point"}
}