{
  "type": "Feature",
  "properties": {
    "iso:country":"US",
    "sg:address":"426 E 30th St",
    "sg:city":"National City",
    "sg:classifiers":[
        {
            "category":"Building & Trades",
            "subcategory":"Construction",
            "type":"Services"
        }
    ],
    "sg:phone":"+1 619 474 2843",
    "sg:postcode":"91950",
    "sg:province":"CA",
    "sg:tags":[
        "maker",
        "cabinet"
    ],
    "wof:name":"Olsen-Simmons Cabinetry",
    "wof:placetype":"venue"
},
  "geometry": {"coordinates":[-117.09357,32.658443],"type":"Point"}
}