{
  "type": "Feature",
  "properties": {
    "iso:country":"US",
    "sg:address":"314 N Glendora Ave",
    "sg:city":"Glendora",
    "sg:classifiers":[
        {
            "category":"Organizations",
            "subcategory":"Membership Organization",
            "type":"Services"
        }
    ],
    "sg:phone":"+1 626 963 0419",
    "sg:postcode":"91741",
    "sg:province":"CA",
    "sg:tags":[
        "historical"
    ],
    "wof:name":"Glendora Historical Society",
    "wof:placetype":"venue"
},
  "geometry": {"coordinates":[-117.865362,34.140041],"type":"Point"}
}