{
  "type": "Feature",
  "properties": {
    "addr:full":"1049 Vernon Way El Cajon CA 92020",
    "addr:housenumber":"1049",
    "addr:postcode":"92020",
    "addr:street":"Vernon Way",
    "iso:country":"US",
    "sg:address":"1049 Vernon Way",
    "sg:city":"El Cajon",
    "sg:classifiers":[
        {
            "category":"Retail",
            "subcategory":"Repair Shop",
            "type":"Services"
        }
    ],
    "sg:phone":"+1 619 448 6825",
    "sg:postcode":"92020",
    "sg:province":"CA",
    "sg:tags":[
        "reupholstery",
        "furniture"
    ],
    "wof:name":"Quickstitch",
    "wof:placetype":"venue"
},
  "geometry": {"coordinates":[-116.974998,32.811901],"type":"Point"}
}