{
  "type": "Feature",
  "properties": {
    "iso:country":"US",
    "sg:address":"6 Rustic Way",
    "sg:city":"Orinda",
    "sg:classifiers":[
        {
            "category":"Wholesale",
            "subcategory":"Plants",
            "type":"Manufacturing & Wholesale Goods"
        }
    ],
    "sg:phone":"+1 925 254 7118",
    "sg:postcode":"94563",
    "sg:province":"CA",
    "sg:tags":[
        "supply"
    ],
    "wof:name":"Spring Cottage Designs",
    "wof:placetype":"venue"
},
  "geometry": {"coordinates":[-122.158259,37.865916],"type":"Point"}
}