{
  "type": "Feature",
  "properties": {
    "addr:full":"West Branch Station 820 N San Vicente Blvd West Hollywood CA 90069",
    "addr:housenumber":"820",
    "addr:postcode":"90069",
    "addr:street":"N San Vicente Blvd",
    "iso:country":"US",
    "sg:address":"West Branch Station 820 N San Vicente Blvd",
    "sg:city":"West Hollywood",
    "sg:classifiers":[
        {
            "category":"Government",
            "subcategory":"Post Office",
            "type":"Public Place"
        }
    ],
    "sg:postcode":"90069",
    "sg:province":"CA",
    "sg:website":"www.usps.com",
    "wof:name":"United States Post Office",
    "wof:placetype":"venue"
},
  "geometry": {"coordinates":[-118.384226,34.085704],"type":"Point"}
}