{
  "type": "Feature",
  "properties": {
    "addr:full":"1728 B St Hayward CA 94541",
    "addr:housenumber":"1728",
    "addr:postcode":"94541",
    "addr:street":"B St",
    "iso:country":"US",
    "sg:address":"1728 B St",
    "sg:city":"Hayward",
    "sg:classifiers":[
        {
            "category":"Professional",
            "subcategory":"Lawyer & Legal Services",
            "type":"Services"
        }
    ],
    "sg:phone":"+1 510 881 5405",
    "sg:postcode":"94541",
    "sg:province":"CA",
    "sg:tags":[
        "attorney"
    ],
    "wof:name":"William D Gibbs",
    "wof:placetype":"venue"
},
  "geometry": {"coordinates":[-122.07127,37.679786],"type":"Point"}
}