{
  "type": "Feature",
  "properties": {
    "iso:country":"US",
    "sg:address":"23240 Lyons Ave",
    "sg:city":"Newhall",
    "sg:classifiers":[
        {
            "category":"Real Estate",
            "subcategory":"Real Estate Agent",
            "type":"Services"
        }
    ],
    "sg:phone":"+1 661 255 5428",
    "sg:postcode":"91321",
    "sg:province":"CA",
    "wof:name":"Real Estate Co-Santa Clarita",
    "wof:placetype":"venue"
},
  "geometry": {"coordinates":[-118.538959,34.379739],"type":"Point"}
}