{
  "type": "Feature",
  "properties": {
    "addr:full":"339 Caledonia St Sausalito CA 94965",
    "addr:housenumber":"339",
    "addr:postcode":"94965",
    "addr:street":"Caledonia St",
    "iso:country":"US",
    "sg:address":"339 Caledonia St",
    "sg:city":"Sausalito",
    "sg:classifiers":[
        {
            "category":"Professional",
            "subcategory":"Art Services",
            "type":"Services"
        },
        {
            "category":"Professional",
            "subcategory":"Business Services",
            "type":"Services"
        }
    ],
    "sg:phone":"+1 415 332 1782",
    "sg:postcode":"94965",
    "sg:province":"CA",
    "sg:tags":[
        "development",
        "product",
        "graphic",
        "designers-industrial",
        "marketing",
        "commercial",
        "designer",
        "design"
    ],
    "wof:name":"Dana Kay Design",
    "wof:placetype":"venue"
},
  "geometry": {"coordinates":[-122.48743,37.859714],"type":"Point"}
}