{
  "type": "Feature",
  "properties": {
    "iso:country":"US",
    "sg:address":"1440 Hill St",
    "sg:city":"El Cajon",
    "sg:classifiers":[
        {
            "category":"Retail",
            "subcategory":"Repair Shop",
            "type":"Services"
        }
    ],
    "sg:phone":"+1 619 444 5606",
    "sg:postcode":"92020",
    "sg:province":"CA",
    "sg:tags":[
        "refinish",
        "furniture"
    ],
    "wof:name":"Linden Painting & Refinishing",
    "wof:placetype":"venue"
},
  "geometry": {"coordinates":[-116.978864,32.784086],"type":"Point"}
}