{
  "type": "Feature",
  "properties": {
    "addr:full":"214 W Olympic Boulevard Los Angeles CA 90015",
    "addr:housenumber":"214",
    "addr:postcode":"90015",
    "addr:street":"W Olympic Boulevard",
    "iso:country":"US",
    "sg:address":"214 W Olympic Boulevard",
    "sg:city":"Los Angeles",
    "sg:classifiers":[
        {
            "category":"Shopping",
            "subcategory":"Clothing, Apparel, & Fashions",
            "type":"Retail Goods"
        }
    ],
    "sg:phone":"+1 213 749 0191",
    "sg:postcode":"90015",
    "sg:province":"CA",
    "sg:tags":[
        "clothing",
        "women's"
    ],
    "wof:name":"Private Brand Merchandising Corporation",
    "wof:placetype":"venue"
},
  "geometry": {"coordinates":[-118.257766,34.041288],"type":"Point"}
}