{
  "type": "Feature",
  "properties": {
    "iso:country":"US",
    "sg:address":"3116 Huckleberry Dr",
    "sg:city":"Corona",
    "sg:classifiers":[
        {
            "category":"Wholesale",
            "subcategory":"Meat",
            "type":"Manufacturing & Wholesale Goods"
        }
    ],
    "sg:phone":"+1 951 734 5110",
    "sg:postcode":"92882",
    "sg:province":"CA",
    "wof:name":"Mana Meat Training",
    "wof:placetype":"venue"
},
  "geometry": {"coordinates":[-117.627256,33.877551],"type":"Point"}
}