{
  "type": "Feature",
  "properties": {
    "iso:country":"US",
    "sg:address":"3827 E Cesar E Chavez Ave",
    "sg:city":"Los Angeles",
    "sg:classifiers":[
        {
            "category":"Retail",
            "subcategory":"Auto Repair",
            "type":"Services"
        }
    ],
    "sg:phone":"+1 323 262 8544",
    "sg:postcode":"90063",
    "sg:province":"CA",
    "sg:tags":[
        "wrecker"
    ],
    "wof:name":"C & R Towing",
    "wof:placetype":"venue"
},
  "geometry": {"coordinates":[-118.183843,34.040596],"type":"Point"}
}