{
  "type": "Feature",
  "properties": {
    "addr:full":"120 E de la Guerra St Santa Barbara CA 93101",
    "addr:housenumber":"120",
    "addr:postcode":"93101",
    "addr:street":"E De La Guerra St",
    "iso:country":"US",
    "sg:address":"120 E de la Guerra St",
    "sg:city":"Santa Barbara",
    "sg:classifiers":[
        {
            "category":"Real Estate",
            "subcategory":"Architect",
            "type":"Services"
        }
    ],
    "sg:phone":"+1 805 966 1200",
    "sg:postcode":"93101",
    "sg:province":"CA",
    "wof:name":"Edwards & Pitman",
    "wof:placetype":"venue"
},
  "geometry": {"coordinates":[-119.697468,34.421654],"type":"Point"}
}