{
  "type": "Feature",
  "properties": {
    "addr:full":"1625 S Main St Yreka CA 96097",
    "addr:housenumber":"1625",
    "addr:postcode":"96097",
    "addr:street":"S Main St",
    "iso:country":"US",
    "sg:address":"1625 S Main St",
    "sg:city":"Yreka",
    "sg:classifiers":[
        {
            "category":"Farming",
            "subcategory":"Fish & Marine Products",
            "type":"Manufacturing & Wholesale Goods"
        }
    ],
    "sg:phone":"+1 530 841 2550",
    "sg:postcode":"96097",
    "sg:province":"CA",
    "sg:tags":[
        "management"
    ],
    "wof:name":"Fish and Game CA Dept of",
    "wof:placetype":"venue"
},
  "geometry": {"coordinates":[-122.64265399999999,41.708573],"type":"Point"}
}