{
  "type": "Feature",
  "properties": {
    "iso:country":"US",
    "sg:address":"2160 E el Monte Way",
    "sg:city":"Dinuba",
    "sg:classifiers":[
        {
            "category":"Cinema",
            "subcategory":"Movie Rental",
            "type":"Entertainment"
        }
    ],
    "sg:phone":"+1 559 591 4647",
    "sg:postcode":"93618",
    "sg:province":"CA",
    "sg:tags":[
        "leasing",
        "video",
        "disc",
        "tape"
    ],
    "wof:name":"Blockbuster Video",
    "wof:placetype":"venue"
},
  "geometry": {"coordinates":[-119.373684,36.54544],"type":"Point"}
}