{
  "type": "Feature",
  "properties": {
    "iso:country":"US",
    "sg:address":"29101 Burrough Valley Rd",
    "sg:city":"Tollhouse",
    "sg:classifiers":[
        {
            "category":"Professional",
            "type":"Services"
        }
    ],
    "sg:phone":"+1 559 855 8846",
    "sg:postcode":"93667",
    "sg:province":"CA",
    "sg:tags":[
        "janitorial"
    ],
    "wof:name":"White Glove Janitorial",
    "wof:placetype":"venue"
},
  "geometry": {"coordinates":[-119.37934199999999,36.972486],"type":"Point"}
}