{
  "type": "Feature",
  "properties": {
    "addr:full":"6682 Selma Ave Los Angeles CA 90028",
    "addr:housenumber":"6682",
    "addr:postcode":"90028",
    "addr:street":"Selma Ave",
    "iso:country":"US",
    "sg:address":"6682 Selma Ave",
    "sg:city":"Los Angeles",
    "sg:classifiers":[
        {
            "category":"Wholesale",
            "subcategory":"Durable Goods & Equipment",
            "type":"Manufacturing & Wholesale Goods"
        }
    ],
    "sg:phone":"+1 323 464 0800",
    "sg:postcode":"90028",
    "sg:province":"CA",
    "sg:tags":[
        "exporter"
    ],
    "wof:name":"World Wide Business Solutions",
    "wof:placetype":"venue"
},
  "geometry": {"coordinates":[-118.335399,34.099625],"type":"Point"}
}