{
  "type": "Feature",
  "properties": {
    "addr:full":"1386 Tennis Club Dr Encinitas CA 92024",
    "addr:housenumber":"1386",
    "addr:postcode":"92024",
    "addr:street":"Tennis Club Dr",
    "iso:country":"US",
    "sg:address":"1386 Tennis Club Dr",
    "sg:city":"Encinitas",
    "sg:classifiers":[
        {
            "category":"Building & Trades",
            "subcategory":"Construction",
            "type":"Services"
        }
    ],
    "sg:phone":"+1 760 753 0116",
    "sg:postcode":"92024",
    "sg:province":"CA",
    "sg:tags":[
        "dry wall",
        "contractor"
    ],
    "wof:name":"Perfect Patch",
    "wof:placetype":"venue"
},
  "geometry": {"coordinates":[-117.258053,33.028967],"type":"Point"}
}