{
  "type": "Feature",
  "properties": {
    "iso:country":"US",
    "sg:address":"2451 E Chapman Ave",
    "sg:city":"Fullerton",
    "sg:classifiers":[
        {
            "category":"Personal",
            "type":"Services"
        }
    ],
    "sg:phone":"+1 714 871 6782",
    "sg:postcode":"92831",
    "sg:province":"CA",
    "sg:tags":[
        "sewing",
        "alteration"
    ],
    "sg:website":"www.embroidme-fullerton.com",
    "wof:name":"Embroidme",
    "wof:placetype":"venue"
},
  "geometry": {"coordinates":[-117.88836999999999,33.874219],"type":"Point"}
}