{
  "type": "Feature",
  "properties": {
    "addr:full":"2107 Carrere St Bakersfield CA 93308",
    "addr:housenumber":"2107",
    "addr:postcode":"93308",
    "addr:street":"Carrere St",
    "iso:country":"US",
    "sg:address":"2107 Carrere St",
    "sg:city":"Bakersfield",
    "sg:classifiers":[
        {
            "category":"Communications",
            "type":"Services"
        }
    ],
    "sg:phone":"+1 661 392 9320",
    "sg:postcode":"93308",
    "sg:province":"CA",
    "wof:name":"Leaf House Media",
    "wof:placetype":"venue"
},
  "geometry": {"coordinates":[-119.019791,35.425058],"type":"Point"}
}