{
  "type": "Feature",
  "properties": {
    "iso:country":"US",
    "sg:address":"10297 Cold Harbor Ave",
    "sg:city":"Cupertino",
    "sg:classifiers":[
        {
            "category":"Home & Garden",
            "subcategory":"Carpets & Floor Coverings",
            "type":"Retail Goods"
        }
    ],
    "sg:phone":"+1 408 446 5797",
    "sg:postcode":"95014",
    "sg:province":"CA",
    "sg:tags":[
        "dealer",
        "rug"
    ],
    "wof:name":"Econo Carpet",
    "wof:placetype":"venue"
},
  "geometry": {"coordinates":[-122.018521,37.318839],"type":"Point"}
}