{
  "type": "Feature",
  "properties": {
    "addr:full":"3596 University Ave San Diego CA 92104",
    "addr:housenumber":"3596",
    "addr:postcode":"92104",
    "addr:street":"University Ave",
    "iso:country":"US",
    "sg:address":"3596 University Ave",
    "sg:city":"San Diego",
    "sg:classifiers":[
        {
            "category":"Shopping",
            "subcategory":"Adult",
            "type":"Retail Goods"
        }
    ],
    "sg:phone":"+1 619 281 8129",
    "sg:postcode":"92104",
    "sg:province":"CA",
    "sg:tags":[
        "entertainment"
    ],
    "wof:name":"Minx Show Girls",
    "wof:placetype":"venue"
},
  "geometry": {"coordinates":[-117.11599699999999,32.749599],"type":"Point"}
}