{
  "type": "Feature",
  "properties": {
    "iso:country":"US",
    "sg:address":"6701 Partridge Dr",
    "sg:city":"Ventura",
    "sg:classifiers":[
        {
            "category":"Building & Trades",
            "subcategory":"Construction",
            "type":"Services"
        }
    ],
    "sg:phone":"+1 805 644 7946",
    "sg:postcode":"93003",
    "sg:province":"CA",
    "sg:tags":[
        "coping",
        "plastering",
        "tiling",
        "pool",
        "swimming"
    ],
    "wof:name":"Pool Repair & Supply",
    "wof:placetype":"venue"
},
  "geometry": {"coordinates":[-119.199341,34.261741],"type":"Point"}
}