{
  "type": "Feature",
  "properties": {
    "addr:full":"181 Rea Ave Ste 202B El Cajon CA 92020",
    "addr:housenumber":"181",
    "addr:postcode":"92020",
    "addr:street":"Rea Ave Ste 202B",
    "iso:country":"US",
    "sg:address":"181 Rea Ave Ste 202B",
    "sg:city":"El Cajon",
    "sg:classifiers":[
        {
            "category":"Professional",
            "subcategory":"Lawyer & Legal Services",
            "type":"Services"
        }
    ],
    "sg:phone":"+1 619 518 2358",
    "sg:postcode":"92020",
    "sg:province":"CA",
    "sg:tags":[
        "litigation"
    ],
    "wof:name":"Emily C Grisafi",
    "wof:placetype":"venue"
},
  "geometry": {"coordinates":[-116.96038299999999,32.795474],"type":"Point"}
}