{
  "type": "Feature",
  "properties": {
    "iso:country":"US",
    "sg:address":"1510 Alamo Dr",
    "sg:city":"Vacaville",
    "sg:classifiers":[
        {
            "category":"Shopping",
            "subcategory":"Gifts & Souvenirs",
            "type":"Retail Goods"
        }
    ],
    "sg:phone":"+1 707 426 4097",
    "sg:postcode":"95687",
    "sg:province":"CA",
    "sg:tags":[
        "novelty",
        "sales"
    ],
    "wof:name":"Card 2 Net Inc",
    "wof:placetype":"venue"
},
  "geometry": {"coordinates":[-121.983029,38.335417],"type":"Point"}
}