{
  "type": "Feature",
  "properties": {
    "iso:country":"US",
    "sg:address":"5750 Via Real",
    "sg:city":"Carpinteria",
    "sg:classifiers":[
        {
            "category":"Utilities",
            "subcategory":"Refuse",
            "type":"Services"
        }
    ],
    "sg:phone":"+1 805 684 3026",
    "sg:postcode":"93013",
    "sg:province":"CA",
    "sg:tags":[
        "system"
    ],
    "wof:name":"Sharma Pin S Recycli",
    "wof:placetype":"venue"
},
  "geometry": {"coordinates":[-119.502308,34.390173],"type":"Point"}
}