{
  "type": "Feature",
  "properties": {
    "iso:country":"US",
    "sg:address":"240 Trotter Dr",
    "sg:city":"Vallejo",
    "sg:classifiers":[
        {
            "category":"Building & Trades",
            "subcategory":"Landscaping Services",
            "type":"Services"
        }
    ],
    "sg:phone":"+1 707 557 9331",
    "sg:postcode":"94591",
    "sg:province":"CA",
    "sg:tags":[
        "landscape",
        "contractor"
    ],
    "wof:name":"Quality Landscaping & Mntnc",
    "wof:placetype":"venue"
},
  "geometry": {"coordinates":[-122.212639,38.120985],"type":"Point"}
}