{
  "type": "Feature",
  "properties": {
    "iso:country":"US",
    "sg:address":"13630 Tucker Ave",
    "sg:city":"Chino",
    "sg:classifiers":[
        {
            "category":"Banks & Credit Unions",
            "subcategory":"Financial Services",
            "type":"Services"
        }
    ],
    "sg:phone":"+1 909 287 0470",
    "sg:postcode":"91710",
    "sg:province":"CA",
    "sg:tags":[
        "financing"
    ],
    "sg:website":"http://www.worldwidefunding.com",
    "wof:name":"Worldwide Funding",
    "wof:placetype":"venue"
},
  "geometry": {"coordinates":[-117.715856,34.004865],"type":"Point"}
}