{
  "type": "Feature",
  "properties": {
    "addr:full":"1222 39th Ave San Francisco CA 94122",
    "addr:housenumber":"1222",
    "addr:postcode":"94122",
    "addr:street":"39Th Ave",
    "iso:country":"US",
    "sg:address":"1222 39th Ave",
    "sg:city":"San Francisco",
    "sg:classifiers":[
        {
            "category":"Airline",
            "type":"Transportation"
        }
    ],
    "sg:phone":"+1 415 664 0892",
    "sg:postcode":"94122",
    "sg:province":"CA",
    "sg:tags":[
        "scheduled",
        "air"
    ],
    "wof:name":"Amigo Air Corp Inc",
    "wof:placetype":"venue"
},
  "geometry": {"coordinates":[-122.498504,37.763043],"type":"Point"}
}