{
  "type": "Feature",
  "properties": {
    "addr:full":"398 State Pl Escondido CA 92029",
    "addr:housenumber":"398",
    "addr:postcode":"92029",
    "addr:street":"State Pl",
    "iso:country":"US",
    "sg:address":"398 State Pl",
    "sg:city":"Escondido",
    "sg:classifiers":[
        {
            "category":"Shopping",
            "type":"Retail Goods"
        }
    ],
    "sg:phone":"+1 760 741 1412",
    "sg:postcode":"92029",
    "sg:province":"CA",
    "sg:tags":[
        "electrical",
        "merchandise",
        "contractor"
    ],
    "wof:name":"Christian Company",
    "wof:placetype":"venue"
},
  "geometry": {"coordinates":[-117.111204,33.122321],"type":"Point"}
}