{
  "type": "Feature",
  "properties": {
    "iso:country":"US",
    "sg:address":"5325 Engle Rd",
    "sg:city":"Carmichael",
    "sg:classifiers":[
        {
            "category":"Education",
            "subcategory":"School",
            "type":"Public Place"
        }
    ],
    "sg:phone":"+1 916 481 7905",
    "sg:postcode":"95608",
    "sg:province":"CA",
    "sg:tags":[
        "academic",
        "special"
    ],
    "wof:name":"Jane Lathrop School",
    "wof:placetype":"venue"
},
  "geometry": {"coordinates":[-121.339904,38.631883],"type":"Point"}
}