{
  "type": "Feature",
  "properties": {
    "iso:country":"US",
    "sg:address":"6295 Flores Rd",
    "sg:city":"Atascadero",
    "sg:classifiers":[
        {
            "category":"Professional",
            "subcategory":"Detective & Security Services",
            "type":"Services"
        }
    ],
    "sg:phone":"+1 805 466 1345",
    "sg:postcode":"93422",
    "sg:province":"CA",
    "sg:tags":[
        "information",
        "bureau"
    ],
    "wof:name":"Capital Information Services",
    "wof:placetype":"venue"
},
  "geometry": {"coordinates":[-120.68633,35.479061],"type":"Point"}
}