{
  "type": "Feature",
  "properties": {
    "addr:full":"5833 Murietta Ave Van Nuys CA 91401",
    "addr:housenumber":"5833",
    "addr:postcode":"91401",
    "addr:street":"Murietta Ave",
    "iso:country":"US",
    "sg:address":"5833 Murietta Ave",
    "sg:city":"Van Nuys",
    "sg:classifiers":[
        {
            "category":"Shopping",
            "subcategory":"Computers & Home Electronics",
            "type":"Retail Goods"
        }
    ],
    "sg:phone":"+1 323 353 5287",
    "sg:postcode":"91401",
    "sg:province":"CA",
    "wof:name":"Geek Chic Co Inc",
    "wof:placetype":"venue"
},
  "geometry": {"coordinates":[-118.43892,34.176666],"type":"Point"}
}