{
  "type": "Feature",
  "properties": {
    "iso:country":"US",
    "sg:address":"6762 Mount Pakron Dr",
    "sg:city":"San Jose",
    "sg:classifiers":[
        {
            "category":"Shopping",
            "subcategory":"Clothing, Apparel, & Fashions",
            "type":"Retail Goods"
        }
    ],
    "sg:phone":"+1 408 476 8828",
    "sg:postcode":"95120",
    "sg:province":"CA",
    "sg:tags":[
        "family"
    ],
    "wof:name":"Cre8 Clothing",
    "wof:placetype":"venue"
},
  "geometry": {"coordinates":[-121.85115500000001,37.214979],"type":"Point"}
}