{
  "type": "Feature",
  "properties": {
    "iso:country":"US",
    "sg:address":"7225 Yorktown Dr",
    "sg:city":"Gilroy",
    "sg:classifiers":[
        {
            "category":"Social Services",
            "subcategory":"Child Care",
            "type":"Services"
        }
    ],
    "sg:phone":"+1 408 847 3519",
    "sg:postcode":"95020",
    "sg:province":"CA",
    "wof:name":"A Little Thinkers Child Care",
    "wof:placetype":"venue"
},
  "geometry": {"coordinates":[-121.58298499999999,36.998946],"type":"Point"}
}