{
  "type": "Feature",
  "properties": {
    "addr:full":"702 W Las Tunas Dr San Gabriel CA 91776",
    "addr:housenumber":"702",
    "addr:postcode":"91776",
    "addr:street":"W Las Tunas Dr",
    "iso:country":"US",
    "sg:address":"702 W Las Tunas Dr",
    "sg:city":"San Gabriel",
    "sg:classifiers":[
        {
            "category":"Shopping",
            "type":"Retail Goods"
        }
    ],
    "sg:phone":"+1 626 457 9777",
    "sg:postcode":"91776",
    "sg:province":"CA",
    "sg:tags":[
        "cards",
        "sport",
        "baseball",
        "memorabilia"
    ],
    "sg:website":"www.championcollectables.com",
    "wof:name":"Champion Sports Collectables",
    "wof:placetype":"venue"
},
  "geometry": {"coordinates":[-118.109471,34.102409],"type":"Point"}
}