{
  "type": "Feature",
  "properties": {
    "addr:full":"1715 Montague Grenada Rd Montague CA 96064",
    "addr:housenumber":"1715",
    "addr:postcode":"96064",
    "addr:street":"Montague Grenada Rd",
    "iso:country":"US",
    "sg:address":"1715 Montague Grenada Rd",
    "sg:city":"Montague",
    "sg:classifiers":[
        {
            "category":"Farming",
            "subcategory":"Livestock Farm",
            "type":"Manufacturing & Wholesale Goods"
        }
    ],
    "sg:phone":"+1 530 842 2425",
    "sg:postcode":"96064",
    "sg:province":"CA",
    "sg:tags":[
        "ranch"
    ],
    "wof:name":"Val Verde Ranch",
    "wof:placetype":"venue"
},
  "geometry": {"coordinates":[-122.536513,41.713141],"type":"Point"}
}