{
  "type": "Feature",
  "properties": {
    "iso:country":"US",
    "sg:address":"799 E Foothill Blvd",
    "sg:city":"San Luis Obispo",
    "sg:classifiers":[
        {
            "category":"Personal",
            "subcategory":"Beauty Salon",
            "type":"Services"
        }
    ],
    "sg:phone":"+1 805 783 2676",
    "sg:postcode":"93405",
    "sg:province":"CA",
    "sg:tags":[
        "manicuring"
    ],
    "wof:name":"Fresher Nails",
    "wof:placetype":"venue"
},
  "geometry": {"coordinates":[-120.671654,35.294098],"type":"Point"}
}