{
  "type": "Feature",
  "properties": {
    "iso:country":"US",
    "sg:address":"2223 E Wellington Ave",
    "sg:city":"Santa Ana",
    "sg:classifiers":[
        {
            "category":"Professional",
            "subcategory":"Lawyer & Legal Services",
            "type":"Services"
        }
    ],
    "sg:phone":"+1 714 540 0211",
    "sg:postcode":"92701",
    "sg:province":"CA",
    "wof:name":"Gee Andrea Taylor Atty",
    "wof:placetype":"venue"
},
  "geometry": {"coordinates":[-117.835975,33.755929],"type":"Point"}
}