{
  "type": "Feature",
  "properties": {
    "addr:full":"2110 S Hacienda Blvd Hacienda Heights CA 91745",
    "addr:housenumber":"2110",
    "addr:postcode":"91745",
    "addr:street":"S Hacienda Blvd",
    "iso:country":"US",
    "sg:address":"2110 S Hacienda Blvd",
    "sg:city":"Hacienda Heights",
    "sg:classifiers":[
        {
            "category":"Wholesale",
            "subcategory":"Computers",
            "type":"Manufacturing & Wholesale Goods"
        },
        {
            "category":"Shopping",
            "subcategory":"Computers & Home Electronics",
            "type":"Retail Goods"
        }
    ],
    "sg:phone":"+1 626 330 3879",
    "sg:postcode":"91745",
    "sg:province":"CA",
    "sg:tags":[
        "software"
    ],
    "wof:name":"Accuracy Computer Systems Inc",
    "wof:placetype":"venue"
},
  "geometry": {"coordinates":[-117.968334,33.994871],"type":"Point"}
}