{
  "type": "Feature",
  "properties": {
    "addr:full":"21015 Mulholland Dr Woodland Hills CA 91364",
    "addr:housenumber":"21015",
    "addr:postcode":"91364",
    "addr:street":"Mulholland Dr",
    "iso:country":"US",
    "sg:address":"21015 Mulholland Dr",
    "sg:city":"Woodland Hills",
    "sg:classifiers":[
        {
            "category":"Professional",
            "subcategory":"Lawyer & Legal Services",
            "type":"Services"
        }
    ],
    "sg:phone":"+1 818 703 7609",
    "sg:postcode":"91364",
    "sg:province":"CA",
    "sg:tags":[
        "attorney"
    ],
    "wof:name":"Rosemary Woodlock",
    "wof:placetype":"venue"
},
  "geometry": {"coordinates":[-118.590039,34.143837],"type":"Point"}
}