{
  "type": "Feature",
  "properties": {
    "addr:full":"605 Market Street Suite 1200 San Francisco CA 94105",
    "addr:housenumber":"605",
    "addr:postcode":"94105",
    "addr:street":"Market Street Suite 1200",
    "iso:country":"US",
    "sg:address":"605 Market Street Suite 1200",
    "sg:city":"San Francisco",
    "sg:classifiers":[
        {
            "category":"Professional",
            "subcategory":"Lawyer & Legal Services",
            "type":"Services"
        }
    ],
    "sg:phone":"+1 415 274 7551",
    "sg:postcode":"94105",
    "sg:province":"CA",
    "sg:website":"www.legalusvisa.com",
    "wof:name":"Immigration Law Offices of Barbara-Ann Williams, PC",
    "wof:placetype":"venue"
},
  "geometry": {"coordinates":[-122.40128799999999,37.788947],"type":"Point"}
}