{
  "type": "Feature",
  "properties": {
    "iso:country":"US",
    "sg:address":"12722 Birch Ave",
    "sg:city":"Hawthorne",
    "sg:classifiers":[
        {
            "category":"Building & Trades",
            "subcategory":"Electrical",
            "type":"Services"
        }
    ],
    "sg:phone":"+1 310 644 1308",
    "sg:postcode":"90250",
    "sg:province":"CA",
    "sg:tags":[
        "communications",
        "contractor"
    ],
    "wof:name":"Butler Telecom Inc",
    "wof:placetype":"venue"
},
  "geometry": {"coordinates":[-118.350203,33.916507],"type":"Point"}
}