{
  "type": "Feature",
  "properties": {
    "addr:full":"649 W Imperial Hwy Brea CA 92821",
    "addr:housenumber":"649",
    "addr:postcode":"92821",
    "addr:street":"W Imperial Hwy",
    "iso:country":"US",
    "sg:address":"649 W Imperial Hwy",
    "sg:city":"Brea",
    "sg:classifiers":[
        {
            "category":"Banks & Credit Unions",
            "subcategory":"Bank",
            "type":"Services"
        }
    ],
    "sg:phone":"+1 714 257 9261",
    "sg:postcode":"92821",
    "sg:province":"CA",
    "sg:tags":[
        "cashing",
        "check"
    ],
    "wof:name":"California Budget Finance",
    "wof:placetype":"venue"
},
  "geometry": {"coordinates":[-117.906819,33.917404],"type":"Point"}
}