{
  "type": "Feature",
  "properties": {
    "addr:full":"630 Main St Woodland CA 95695",
    "addr:housenumber":"630",
    "addr:postcode":"95695",
    "addr:street":"Main St",
    "iso:country":"US",
    "sg:address":"630 Main St",
    "sg:city":"Woodland",
    "sg:classifiers":[
        {
            "category":"Shopping",
            "subcategory":"Gifts & Souvenirs",
            "type":"Retail Goods"
        }
    ],
    "sg:phone":"+1 530 668 1909",
    "sg:postcode":"95695",
    "sg:province":"CA",
    "sg:tags":[
        "shop"
    ],
    "wof:name":"Dodie's Collectibles & Fine",
    "wof:placetype":"venue"
},
  "geometry": {"coordinates":[-121.772256,38.677408],"type":"Point"}
}