{
  "type": "Feature",
  "properties": {
    "iso:country":"US",
    "sg:address":"1102 South St",
    "sg:city":"Corning",
    "sg:classifiers":[
        {
            "category":"Retail",
            "subcategory":"Repair Shop",
            "type":"Services"
        }
    ],
    "sg:phone":"+1 530 824 2991",
    "sg:postcode":"96021",
    "sg:province":"CA",
    "sg:tags":[
        "antique",
        "restoring"
    ],
    "wof:name":"Treasure House",
    "wof:placetype":"venue"
},
  "geometry": {"coordinates":[-122.179523,39.925907],"type":"Point"}
}