{
  "type": "Feature",
  "properties": {
    "iso:country":"US",
    "sg:address":"1506 S New Haven Ln",
    "sg:city":"Glendora",
    "sg:classifiers":[
        {
            "category":"Building & Trades",
            "subcategory":"Construction",
            "type":"Services"
        }
    ],
    "sg:phone":"+1 626 339 1455",
    "sg:postcode":"91740",
    "sg:province":"CA",
    "sg:tags":[
        "roofing",
        "industrial",
        "contractors-commercial",
        "contractor"
    ],
    "wof:name":"Raindance Roofing",
    "wof:placetype":"venue"
},
  "geometry": {"coordinates":[-117.857997,34.111851],"type":"Point"}
}