{
  "type": "Feature",
  "properties": {
    "addr:full":"962 Geneva Ave San Francisco CA 94112",
    "addr:housenumber":"962",
    "addr:postcode":"94112",
    "addr:street":"Geneva Ave",
    "iso:country":"US",
    "sg:address":"962 Geneva Ave",
    "sg:city":"San Francisco",
    "sg:classifiers":[
        {
            "category":"Insurance",
            "subcategory":"Insurance Agent",
            "type":"Services"
        }
    ],
    "sg:phone":"+1 415 333 2853",
    "sg:postcode":"94112",
    "sg:province":"CA",
    "wof:name":"Primerica Financial Svc",
    "wof:placetype":"venue"
},
  "geometry": {"coordinates":[-122.43968099999999,37.715653],"type":"Point"}
}