{
  "type": "Feature",
  "properties": {
    "iso:country":"US",
    "sg:address":"75 N Marengo Ave",
    "sg:city":"Pasadena",
    "sg:classifiers":[
        {
            "category":"Arts & Performance",
            "subcategory":"Arts Center",
            "type":"Entertainment"
        }
    ],
    "sg:phone":"+1 626 577 5922",
    "sg:postcode":"91101",
    "sg:province":"CA",
    "sg:tags":[
        "performing"
    ],
    "sg:website":"www.theatre360.org",
    "wof:name":"Theatre 360",
    "wof:placetype":"venue"
},
  "geometry": {"coordinates":[-118.14650899999999,34.147164],"type":"Point"}
}