{
  "type": "Feature",
  "properties": {
    "addr:full":"3209 Cadillac Dr San Jose CA 95117",
    "addr:housenumber":"3209",
    "addr:postcode":"95117",
    "addr:street":"Cadillac Dr",
    "iso:country":"US",
    "sg:address":"3209 Cadillac Dr",
    "sg:city":"San Jose",
    "sg:classifiers":[
        {
            "category":"Building & Trades",
            "subcategory":"Construction",
            "type":"Services"
        }
    ],
    "sg:phone":"+1 408 871 2548",
    "sg:postcode":"95117",
    "sg:province":"CA",
    "sg:tags":[
        "general",
        "contractor"
    ],
    "wof:name":"Jose & Leo's Improvements",
    "wof:placetype":"venue"
},
  "geometry": {"coordinates":[-121.951633,37.296933],"type":"Point"}
}