{
  "type": "Feature",
  "properties": {
    "addr:full":"1211 N Vermont Avenue Los Angeles CA 90029",
    "addr:housenumber":"1211",
    "addr:postcode":"90029",
    "addr:street":"N Vermont Avenue",
    "iso:country":"US",
    "sg:address":"1211 N Vermont Avenue",
    "sg:city":"Los Angeles",
    "sg:classifiers":[
        {
            "category":"Health Services",
            "subcategory":"Health Practitioner",
            "type":"Services"
        },
        {
            "category":"Health Services",
            "subcategory":"Chiropractor",
            "type":"Services"
        }
    ],
    "sg:phone":"+1 323 663 0259",
    "sg:postcode":"90029",
    "sg:province":"CA",
    "sg:tags":[
        "therapy",
        "physical"
    ],
    "sg:website":"www.chiropaincare.com",
    "wof:name":"Khoury Antoine G DC",
    "wof:placetype":"venue"
},
  "geometry": {"coordinates":[-118.291753,34.093651],"type":"Point"}
}