{
  "type": "Feature",
  "properties": {
    "iso:country":"US",
    "sg:address":"327 Arden Ave",
    "sg:city":"Glendale",
    "sg:classifiers":[
        {
            "category":"Arts & Performance",
            "subcategory":"Theater",
            "type":"Entertainment"
        }
    ],
    "sg:phone":"+1 818 241 1029",
    "sg:postcode":"91203",
    "sg:province":"CA",
    "wof:name":"Ronald C Roeschlaub",
    "wof:placetype":"venue"
},
  "geometry": {"coordinates":[-118.260516,34.158541],"type":"Point"}
}