{
  "type": "Feature",
  "properties": {
    "iso:country":"US",
    "sg:address":"1133 Saint Francis Dr",
    "sg:city":"Concord",
    "sg:classifiers":[
        {
            "category":"Wholesale",
            "subcategory":"Apparel",
            "type":"Manufacturing & Wholesale Goods"
        }
    ],
    "sg:phone":"+1 925 288 9901",
    "sg:postcode":"94509",
    "sg:province":"CA",
    "sg:tags":[
        "footwear"
    ],
    "wof:name":"Vanloga & Associat",
    "wof:placetype":"venue"
},
  "geometry": {"coordinates":[-121.82408599999999,37.997322],"type":"Point"}
}