{
  "type": "Feature",
  "properties": {
    "addr:full":"1002 E Robinson Ave Fresno CA 93704",
    "addr:housenumber":"1002",
    "addr:postcode":"93704",
    "addr:street":"E Robinson Ave",
    "iso:country":"US",
    "sg:address":"1002 E Robinson Ave",
    "sg:city":"Fresno",
    "sg:classifiers":[
        {
            "category":"Personal",
            "type":"Services"
        }
    ],
    "sg:phone":"+1 559 229 9810",
    "sg:postcode":"93704",
    "sg:province":"CA",
    "sg:tags":[
        "therapist",
        "massage"
    ],
    "wof:name":"A Unique Touch",
    "wof:placetype":"venue"
},
  "geometry": {"coordinates":[-119.798271,36.78576],"type":"Point"}
}