{
  "type": "Feature",
  "properties": {
    "addr:full":"1601 McKinnon Ave San Francisco CA 94124",
    "addr:housenumber":"1601",
    "addr:postcode":"94124",
    "addr:street":"Mckinnon Ave",
    "iso:country":"US",
    "sg:address":"1601 McKinnon Ave",
    "sg:city":"San Francisco",
    "sg:classifiers":[
        {
            "category":"Education",
            "subcategory":"School",
            "type":"Public Place"
        }
    ],
    "sg:phone":"+1 415 206 9101",
    "sg:postcode":"94124",
    "sg:province":"CA",
    "wof:name":"Peace Site Academy Elementary",
    "wof:placetype":"venue"
},
  "geometry": {"coordinates":[-122.390145,37.73639],"type":"Point"}
}