{
  "type": "Feature",
  "properties": {
    "iso:country":"US",
    "sg:address":"2960 Airway Ave B101",
    "sg:city":"Costa Mesa",
    "sg:classifiers":[
        {
            "category":"Retail",
            "subcategory":"Auto Repair",
            "type":"Services"
        }
    ],
    "sg:phone":"+1 714 540 3044",
    "sg:postcode":"92626",
    "sg:province":"CA",
    "sg:website":"www.alexsautoperformanceplus.com/",
    "wof:name":"Alex's Auto Performance Plus",
    "wof:placetype":"venue"
},
  "geometry": {"coordinates":[-117.87626299999999,33.669233],"type":"Point"}
}