{
  "type": "Feature",
  "properties": {
    "addr:full":"398 Broadway St El Centro CA 92243",
    "addr:housenumber":"398",
    "addr:postcode":"92243",
    "addr:street":"Broadway St",
    "iso:country":"US",
    "sg:address":"398 Broadway St",
    "sg:city":"El Centro",
    "sg:classifiers":[
        {
            "category":"Communications",
            "type":"Services"
        }
    ],
    "sg:phone":"+1 760 337 5566",
    "sg:postcode":"92243",
    "sg:province":"CA",
    "sg:tags":[
        "communication"
    ],
    "wof:name":"Media Communications",
    "wof:placetype":"venue"
},
  "geometry": {"coordinates":[-115.54881399999999,32.793853],"type":"Point"}
}