{
  "type": "Feature",
  "properties": {
    "iso:country":"US",
    "sg:address":"4060 S El Camino Real",
    "sg:city":"San Mateo",
    "sg:classifiers":[
        {
            "category":"Restaurant",
            "type":"Food & Drink"
        }
    ],
    "sg:menulink":"http://www.allmenus.com/ca/san-mateo/87970-little-caesars-pizza/menu/",
    "sg:phone":"+1 650 341 6161",
    "sg:postcode":"94403",
    "sg:province":"CA",
    "sg:tags":[
        "american",
        "pizza"
    ],
    "wof:name":"Little Caesar's Pizza",
    "wof:placetype":"venue"
},
  "geometry": {"coordinates":[-122.290693,37.531506],"type":"Point"}
}