{
  "type": "Feature",
  "properties": {
    "addr:full":"100 W Hamilton Ave Campbell CA 95008",
    "addr:housenumber":"100",
    "addr:postcode":"95008",
    "addr:street":"W Hamilton Ave",
    "iso:country":"US",
    "sg:address":"100 W Hamilton Ave",
    "sg:city":"Campbell",
    "sg:classifiers":[
        {
            "category":"Retail",
            "subcategory":"Laundry & Dry Cleaning",
            "type":"Services"
        }
    ],
    "sg:phone":"+1 408 379 4032",
    "sg:postcode":"95008",
    "sg:province":"CA",
    "wof:name":"Choice Laundromat",
    "wof:placetype":"venue"
},
  "geometry": {"coordinates":[-121.95188,37.29377],"type":"Point"}
}