{
  "type": "Feature",
  "properties": {
    "iso:country":"US",
    "sg:address":"2681 Cameron Park Dr",
    "sg:city":"Cameron Park",
    "sg:classifiers":[
        {
            "category":"Professional",
            "subcategory":"Advertising",
            "type":"Services"
        }
    ],
    "sg:phone":"+1 530 676 2060",
    "sg:postcode":"95682",
    "sg:province":"CA",
    "sg:tags":[
        "mail"
    ],
    "wof:name":"Tegarden Enterprises",
    "wof:placetype":"venue"
},
  "geometry": {"coordinates":[-120.995457,38.69834],"type":"Point"}
}