{
  "type": "Feature",
  "properties": {
    "iso:country":"US",
    "sg:address":"255 N Market St Ste 200",
    "sg:city":"San Jose",
    "sg:classifiers":[
        {
            "category":"Organizations",
            "subcategory":"Non-profit Organization",
            "type":"Services"
        }
    ],
    "sg:phone":"+1 408 291 0062",
    "sg:postcode":"95110",
    "sg:province":"CA",
    "sg:tags":[
        "service/non-profit",
        "community"
    ],
    "wof:name":"Summer Search Silicon Valley",
    "wof:placetype":"venue"
},
  "geometry": {"coordinates":[-121.89493299999999,37.339087],"type":"Point"}
}