{
  "type": "Feature",
  "properties": {
    "iso:country":"US",
    "sg:address":"2261 The Alameda",
    "sg:city":"Santa Clara",
    "sg:classifiers":[
        {
            "category":"Arts & Performance",
            "subcategory":"Art Gallery",
            "type":"Entertainment"
        }
    ],
    "sg:phone":"+1 408 249 7662",
    "sg:postcode":"95050",
    "sg:province":"CA",
    "wof:name":"Gallery Blu",
    "wof:placetype":"venue"
},
  "geometry": {"coordinates":[-121.931999,37.344398],"type":"Point"}
}