{
  "type": "Feature",
  "properties": {
    "iso:country":"US",
    "sg:address":"12501 Burbank Blvd",
    "sg:city":"Valley Village",
    "sg:classifiers":[
        {
            "category":"Shopping",
            "subcategory":"Jewelry",
            "type":"Retail Goods"
        }
    ],
    "sg:phone":"+1 818 761 2979",
    "sg:postcode":"91607",
    "sg:province":"CA",
    "wof:name":"Golden Bay Jewelers",
    "wof:placetype":"venue"
},
  "geometry": {"coordinates":[-118.404999,34.172199],"type":"Point"}
}