{
  "type": "Feature",
  "properties": {
    "iso:country":"US",
    "sg:address":"1841 Indian Hill Blvd",
    "sg:city":"Pomona",
    "sg:classifiers":[
        {
            "category":"Personal",
            "type":"Services"
        }
    ],
    "sg:phone":"+1 909 946 4359",
    "sg:postcode":"91767",
    "sg:province":"CA",
    "sg:tags":[
        "wear",
        "formal"
    ],
    "wof:name":"After Six Rittmann's Tux Shop",
    "wof:placetype":"venue"
},
  "geometry": {"coordinates":[-117.71932099999999,34.077496],"type":"Point"}
}