{
  "type": "Feature",
  "properties": {
    "iso:country":"US",
    "sg:address":"710 East 22nd Street #102",
    "sg:city":"Oakland",
    "sg:classifiers":[
        {
            "category":"Banks & Credit Unions",
            "subcategory":"Financial Services",
            "type":"Services"
        }
    ],
    "sg:phone":"+1 415 505 3115",
    "sg:postcode":"94606",
    "sg:province":"CA",
    "sg:website":"www.SmallBizMaven.com",
    "wof:name":"SmallBizMaven",
    "wof:placetype":"venue"
},
  "geometry": {"coordinates":[-122.244635,37.799391],"type":"Point"}
}