{
  "type": "Feature",
  "properties": {
    "addr:full":"40525 California Oaks Rd Murrieta CA 92562",
    "addr:housenumber":"40525",
    "addr:postcode":"92562",
    "addr:street":"California Oaks Rd",
    "iso:country":"US",
    "sg:address":"40525 California Oaks Rd",
    "sg:city":"Murrieta",
    "sg:classifiers":[
        {
            "category":"Banks & Credit Unions",
            "subcategory":"Investment Brokerage",
            "type":"Services"
        }
    ],
    "sg:phone":"+1 951 600 1606",
    "sg:postcode":"92562",
    "sg:province":"CA",
    "sg:tags":[
        "security"
    ],
    "wof:name":"Edward Jones Co",
    "wof:placetype":"venue"
},
  "geometry": {"coordinates":[-117.201303,33.575902],"type":"Point"}
}