{
  "type": "Feature",
  "properties": {
    "addr:full":"401 E Ranch Rd Sacramento CA 95825",
    "addr:housenumber":"401",
    "addr:postcode":"95825",
    "addr:street":"E Ranch Rd",
    "iso:country":"US",
    "sg:address":"401 E Ranch Rd",
    "sg:city":"Sacramento",
    "sg:classifiers":[
        {
            "category":"Real Estate",
            "subcategory":"Architect",
            "type":"Services"
        }
    ],
    "sg:phone":"+1 916 485 8044",
    "sg:postcode":"95825",
    "sg:province":"CA",
    "wof:name":"Engler Assessment Mgmt Intl",
    "wof:placetype":"venue"
},
  "geometry": {"coordinates":[-121.404757,38.570452],"type":"Point"}
}