{
  "type": "Feature",
  "properties": {
    "iso:country":"US",
    "sg:address":"873 Flores Way",
    "sg:city":"Rio Vista",
    "sg:classifiers":[
        {
            "category":"Health Services",
            "subcategory":"Nursing And Care Facility",
            "type":"Services"
        }
    ],
    "sg:phone":"+1 707 374 5333",
    "sg:postcode":"94571",
    "sg:province":"CA",
    "wof:name":"Abbey Rose Manor",
    "wof:placetype":"venue"
},
  "geometry": {"coordinates":[-121.69462900000001,38.161396],"type":"Point"}
}