{
  "type": "Feature",
  "properties": {
    "iso:country":"US",
    "sg:address":"350 Hawthorne Ave",
    "sg:city":"Oakland",
    "sg:classifiers":[
        {
            "category":"Health Services",
            "subcategory":"Doctor",
            "type":"Services"
        }
    ],
    "sg:phone":"+1 510 869 6567",
    "sg:postcode":"94609",
    "sg:province":"CA",
    "sg:tags":[
        "physician",
        "surgeon"
    ],
    "wof:name":"East Bay Pathology Group",
    "wof:placetype":"venue"
},
  "geometry": {"coordinates":[-122.264115,37.821015],"type":"Point"}
}