{
  "type": "Feature",
  "properties": {
    "addr:full":"12250 W Lincoln Ave Fresno CA 93706",
    "addr:housenumber":"12250",
    "addr:postcode":"93706",
    "addr:street":"W Lincoln Ave",
    "iso:country":"US",
    "sg:address":"12250 W Lincoln Ave",
    "sg:city":"Fresno",
    "sg:classifiers":[
        {
            "category":"Farming",
            "subcategory":"Farm",
            "type":"Manufacturing & Wholesale Goods"
        }
    ],
    "sg:phone":"+1 559 846 7461",
    "sg:postcode":"93706",
    "sg:province":"CA",
    "wof:name":"Hillview Dairy Farm",
    "wof:placetype":"venue"
},
  "geometry": {"coordinates":[-120.01227400000001,36.647642],"type":"Point"}
}