{
  "type": "Feature",
  "properties": {
    "iso:country":"US",
    "sg:address":"25339 Via Saludo",
    "sg:city":"Valencia",
    "sg:classifiers":[
        {
            "category":"Restaurant",
            "type":"Food & Drink"
        }
    ],
    "sg:phone":"+1 661 253 1504",
    "sg:postcode":"91355",
    "sg:province":"CA",
    "sg:tags":[
        "eating"
    ],
    "wof:name":"Gail Silvers",
    "wof:placetype":"venue"
},
  "geometry": {"coordinates":[-118.543387,34.395304],"type":"Point"}
}