{
  "type": "Feature",
  "properties": {
    "addr:full":"7954 Hollywood Blvd West Hollywood CA 90046",
    "addr:housenumber":"7954",
    "addr:postcode":"90046",
    "addr:street":"Hollywood Blvd",
    "iso:country":"US",
    "sg:address":"7954 Hollywood Blvd",
    "sg:city":"West Hollywood",
    "sg:classifiers":[
        {
            "category":"Restaurant",
            "type":"Food & Drink"
        }
    ],
    "sg:phone":"+1 323 848 9141",
    "sg:postcode":"90046",
    "sg:province":"CA",
    "wof:name":"Los Tacos",
    "wof:placetype":"venue"
},
  "geometry": {"coordinates":[-118.363041,34.101217],"type":"Point"}
}