{
  "type": "Feature",
  "properties": {
    "addr:full":"625 E Valley Blvd San Gabriel CA 91776",
    "addr:housenumber":"625",
    "addr:postcode":"91776",
    "addr:street":"E Valley Blvd",
    "iso:country":"US",
    "sg:address":"625 E Valley Blvd",
    "sg:city":"San Gabriel",
    "sg:classifiers":[
        {
            "category":"Personal",
            "subcategory":"Beauty Salon",
            "type":"Services"
        }
    ],
    "sg:phone":"+1 626 573 0268",
    "sg:postcode":"91776",
    "sg:province":"CA",
    "sg:tags":[
        "hair"
    ],
    "wof:name":"Perfect Image Beauty Salon",
    "wof:placetype":"venue"
},
  "geometry": {"coordinates":[-118.092071,34.0805],"type":"Point"}
}