{
  "type": "Feature",
  "properties": {
    "iso:country":"US",
    "sg:address":"1184 W 2nd St",
    "sg:city":"San Bernardino",
    "sg:classifiers":[
        {
            "category":"Food & Beverages",
            "subcategory":"Groceries & Convenience Stores",
            "type":"Retail Goods"
        }
    ],
    "sg:phone":"+1 909 383 3642",
    "sg:postcode":"92410",
    "sg:province":"CA",
    "sg:tags":[
        "market"
    ],
    "wof:name":"El Tigre Inc",
    "wof:placetype":"venue"
},
  "geometry": {"coordinates":[-117.308064,34.102803],"type":"Point"}
}