{
  "type": "Feature",
  "properties": {
    "iso:country":"US",
    "sg:address":"11803 W Washington Blvd",
    "sg:city":"Los Angeles",
    "sg:classifiers":[
        {
            "category":"Health Services",
            "subcategory":"Doctor",
            "type":"Services"
        },
        {
            "category":"Personal",
            "subcategory":"Massage",
            "type":"Services"
        },
        {
            "category":"Health Services",
            "subcategory":"Chiropractor",
            "type":"Services"
        }
    ],
    "sg:phone":"+1 310 572 1515",
    "sg:postcode":"90066",
    "sg:province":"CA",
    "sg:tags":[
        "medicine",
        "sport"
    ],
    "wof:name":"Westside Health-Chiropractic",
    "wof:placetype":"venue"
},
  "geometry": {"coordinates":[-118.418947,33.998818],"type":"Point"}
}