{
  "type": "Feature",
  "properties": {
    "addr:full":"5180 Reservation Rd Placerville CA 95667",
    "addr:housenumber":"5180",
    "addr:postcode":"95667",
    "addr:street":"Reservation Rd",
    "iso:country":"US",
    "sg:address":"5180 Reservation Rd",
    "sg:city":"Placerville",
    "sg:classifiers":[
        {
            "category":"Manufacturing",
            "subcategory":"Jewelry",
            "type":"Manufacturing & Wholesale Goods"
        }
    ],
    "sg:phone":"+1 530 677 0240",
    "sg:postcode":"95667",
    "sg:province":"CA",
    "sg:tags":[
        "precious",
        "metal",
        "mfg"
    ],
    "wof:name":"H5 Business Services",
    "wof:placetype":"venue"
},
  "geometry": {"coordinates":[-120.899383,38.704072],"type":"Point"}
}