{
  "type": "Feature",
  "properties": {
    "addr:full":"5675 Walnut Ridge Dr Agoura Hills CA 91301",
    "addr:housenumber":"5675",
    "addr:postcode":"91301",
    "addr:street":"Walnut Ridge Dr",
    "iso:country":"US",
    "sg:address":"5675 Walnut Ridge Dr",
    "sg:city":"Agoura Hills",
    "sg:classifiers":[
        {
            "category":"Building & Trades",
            "subcategory":"Construction",
            "type":"Services"
        }
    ],
    "sg:phone":"+1 818 707 3405",
    "sg:postcode":"91301",
    "sg:province":"CA",
    "sg:tags":[
        "nonresidential"
    ],
    "wof:name":"Oved Dagan Construction",
    "wof:placetype":"venue"
},
  "geometry": {"coordinates":[-118.771069,34.153377],"type":"Point"}
}