{
  "type": "Feature",
  "properties": {
    "addr:full":"19055 Sherman Way Reseda CA 91335",
    "addr:housenumber":"19055",
    "addr:postcode":"91335",
    "addr:street":"Sherman Way",
    "iso:country":"US",
    "sg:address":"19055 Sherman Way",
    "sg:city":"Reseda",
    "sg:classifiers":[
        {
            "category":"Real Estate",
            "subcategory":"Real Estate Services",
            "type":"Services"
        },
        {
            "category":"Real Estate",
            "subcategory":"Real Estate Operator",
            "type":"Services"
        }
    ],
    "sg:phone":"+1 818 609 8569",
    "sg:postcode":"91335",
    "sg:province":"CA",
    "sg:tags":[
        "vacancy",
        "apartment",
        "rental",
        "listing"
    ],
    "wof:name":"Reseda Homestyle Apartments",
    "wof:placetype":"venue"
},
  "geometry": {"coordinates":[-118.548528,34.201172],"type":"Point"}
}