{
  "type": "Feature",
  "properties": {
    "iso:country":"US",
    "sg:address":"17800 Castleton Street Suite 300",
    "sg:city":"City of Industry",
    "sg:classifiers":[
        {
            "category":"Professional",
            "subcategory":"Computer Services",
            "type":"Services"
        }
    ],
    "sg:phone":"+1 626 581 3335",
    "sg:postcode":"91748",
    "sg:province":"CA",
    "sg:website":"http://digitaldevelopmentpartners.com",
    "wof:name":"Digital Development Partners",
    "wof:placetype":"venue"
},
  "geometry": {"coordinates":[-117.923754,33.99558],"type":"Point"}
}