{
  "type": "Feature",
  "properties": {
    "iso:country":"US",
    "sg:address":"17525 Alder St",
    "sg:city":"Hesperia",
    "sg:classifiers":[
        {
            "category":"Arts & Performance",
            "subcategory":"Theater",
            "type":"Entertainment"
        }
    ],
    "sg:phone":"+1 760 947 5726",
    "sg:postcode":"92345",
    "sg:province":"CA",
    "sg:tags":[
        "live",
        "music"
    ],
    "wof:name":"Ka Sandra",
    "wof:placetype":"venue"
},
  "geometry": {"coordinates":[-117.280602,34.461925],"type":"Point"}
}