{
  "type": "Feature",
  "properties": {
    "iso:country":"US",
    "sg:address":"11405 Firestone Blvd",
    "sg:city":"Norwalk",
    "sg:classifiers":[
        {
            "category":"Personal",
            "subcategory":"Beauty Salon",
            "type":"Services"
        }
    ],
    "sg:phone":"+1 562 864 6801",
    "sg:postcode":"90650",
    "sg:province":"CA",
    "wof:name":"PHD Beauty Salon",
    "wof:placetype":"venue"
},
  "geometry": {"coordinates":[-118.090256,33.917429],"type":"Point"}
}