{
  "type": "Feature",
  "properties": {
    "addr:full":"1420 Ocean Dr Manhattan Beach CA 90266",
    "addr:housenumber":"1420",
    "addr:postcode":"90266",
    "addr:street":"Ocean Dr",
    "iso:country":"US",
    "sg:address":"1420 Ocean Dr",
    "sg:city":"Manhattan Beach",
    "sg:classifiers":[
        {
            "category":"Professional",
            "subcategory":"Advertising",
            "type":"Services"
        }
    ],
    "sg:phone":"+1 310 939 7000",
    "sg:postcode":"90266",
    "sg:province":"CA",
    "sg:tags":[
        "counselor"
    ],
    "wof:name":"Hurst Partners",
    "wof:placetype":"venue"
},
  "geometry": {"coordinates":[-118.412431,33.886611],"type":"Point"}
}