{
  "type": "Feature",
  "properties": {
    "iso:country":"US",
    "sg:address":"3686 Gloreen Ct",
    "sg:city":"Riverside",
    "sg:classifiers":[
        {
            "category":"Building & Trades",
            "subcategory":"Construction",
            "type":"Services"
        }
    ],
    "sg:phone":"+1 951 358 0212",
    "sg:postcode":"92504",
    "sg:province":"CA",
    "sg:tags":[
        "contractor"
    ],
    "wof:name":"AP Masonry Construction",
    "wof:placetype":"venue"
},
  "geometry": {"coordinates":[-117.417091,33.934455],"type":"Point"}
}