{
  "type": "Feature",
  "properties": {
    "iso:country":"US",
    "sg:address":"249 Yosemite Ave",
    "sg:city":"Manteca",
    "sg:classifiers":[
        {
            "category":"Shopping",
            "subcategory":"Department Store",
            "type":"Retail Goods"
        }
    ],
    "sg:phone":"+1 209 239 8636",
    "sg:postcode":"95336",
    "sg:province":"CA",
    "wof:name":"Vicious Rag",
    "wof:placetype":"venue"
},
  "geometry": {"coordinates":[-121.21501499999999,37.797485],"type":"Point"}
}