{
  "type": "Feature",
  "properties": {
    "addr:full":"3207 Thorn St San Diego CA 92104",
    "addr:housenumber":"3207",
    "addr:postcode":"92104",
    "addr:street":"Thorn St",
    "iso:country":"US",
    "sg:address":"3207 Thorn St",
    "sg:city":"San Diego",
    "sg:classifiers":[
        {
            "category":"Personal",
            "subcategory":"Barber",
            "type":"Services"
        }
    ],
    "sg:phone":"+1 619 517 4226",
    "sg:postcode":"92104",
    "sg:province":"CA",
    "wof:name":"JV Barber",
    "wof:placetype":"venue"
},
  "geometry": {"coordinates":[-117.12469,32.73925],"type":"Point"}
}