{
  "type": "Feature",
  "properties": {
    "iso:country":"US",
    "sg:address":"935 Silver Spur Road",
    "sg:city":"Rolling Hills Estate",
    "sg:classifiers":[
        {
            "category":"Banks & Credit Unions",
            "subcategory":"Bank",
            "type":"Services"
        }
    ],
    "sg:phone":"+1 310 541 9894",
    "sg:postcode":"90274",
    "sg:province":"CA",
    "wof:name":"Citibank West Fsb",
    "wof:placetype":"venue"
},
  "geometry": {"coordinates":[-118.365357,33.769746],"type":"Point"}
}