{
  "type": "Feature",
  "properties": {
    "iso:country":"US",
    "sg:address":"2124 Potomac Ave",
    "sg:city":"Bakersfield",
    "sg:classifiers":[
        {
            "category":"Building & Trades",
            "subcategory":"Equipment Rental",
            "type":"Services"
        }
    ],
    "sg:phone":"+1 661 328 1653",
    "sg:postcode":"93307",
    "sg:province":"CA",
    "sg:tags":[
        "yard",
        "leasing",
        "store"
    ],
    "wof:name":"Vic's Paint Boost Specialty & Rental",
    "wof:placetype":"venue"
},
  "geometry": {"coordinates":[-118.96967100000001,35.364941],"type":"Point"}
}