{
  "type": "Feature",
  "properties": {
    "addr:full":"13320 Riverside Dr Sherman Oaks CA 91423",
    "addr:housenumber":"13320",
    "addr:postcode":"91423",
    "addr:street":"Riverside Dr",
    "iso:country":"US",
    "sg:address":"13320 Riverside Dr",
    "sg:city":"Sherman Oaks",
    "sg:classifiers":[
        {
            "category":"Health Services",
            "subcategory":"Doctor",
            "type":"Services"
        }
    ],
    "sg:phone":"+1 818 905 7100",
    "sg:postcode":"91423",
    "sg:province":"CA",
    "sg:tags":[
        "physician",
        "surgeon"
    ],
    "wof:name":"Philip Biderman MD",
    "wof:placetype":"venue"
},
  "geometry": {"coordinates":[-118.42336400000001,34.157537],"type":"Point"}
}