{
  "type": "Feature",
  "properties": {
    "addr:full":"3261 Cardiff Ln Granite Bay CA 95746",
    "addr:housenumber":"3261",
    "addr:postcode":"95746",
    "addr:street":"Cardiff Ln",
    "iso:country":"US",
    "sg:address":"3261 Cardiff Ln",
    "sg:city":"Granite Bay",
    "sg:classifiers":[
        {
            "category":"Local Transit",
            "type":"Transportation"
        }
    ],
    "sg:phone":"+1 916 788 0250",
    "sg:postcode":"95746",
    "sg:province":"CA",
    "sg:tags":[
        "passenger"
    ],
    "wof:name":"Corporate Trnsprtion Solutions",
    "wof:placetype":"venue"
},
  "geometry": {"coordinates":[-121.219482,38.735436],"type":"Point"}
}