{
  "type": "Feature",
  "properties": {
    "iso:country":"US",
    "sg:address":"5506 Goodland Ave",
    "sg:city":"Valley Village",
    "sg:classifiers":[
        {
            "category":"Professional",
            "subcategory":"Management & Consulting",
            "type":"Services"
        }
    ],
    "sg:phone":"+1 818 769 0076",
    "sg:postcode":"91607",
    "sg:province":"CA",
    "sg:tags":[
        "consultant",
        "lighting"
    ],
    "wof:name":"Luminations",
    "wof:placetype":"venue"
},
  "geometry": {"coordinates":[-118.411871,34.171144],"type":"Point"}
}