{
  "type": "Feature",
  "properties": {
    "addr:full":"785 Coastland Dr Palo Alto CA 94303",
    "addr:housenumber":"785",
    "addr:postcode":"94303",
    "addr:street":"Coastland Dr",
    "iso:country":"US",
    "sg:address":"785 Coastland Dr",
    "sg:city":"Palo Alto",
    "sg:classifiers":[
        {
            "category":"Professional",
            "type":"Services"
        }
    ],
    "sg:phone":"+1 408 346 3788",
    "sg:postcode":"94303",
    "sg:province":"CA",
    "wof:name":"Jaisook RHO",
    "wof:placetype":"venue"
},
  "geometry": {"coordinates":[-122.13125599999999,37.435464],"type":"Point"}
}