{
  "type": "Feature",
  "properties": {
    "iso:country":"US",
    "sg:address":"3606 W Slauson Ave",
    "sg:city":"Los Angeles",
    "sg:classifiers":[
        {
            "category":"Personal",
            "subcategory":"Beauty Salon",
            "type":"Services"
        }
    ],
    "sg:phone":"+1 323 294 5340",
    "sg:postcode":"90043",
    "sg:province":"CA",
    "wof:name":"Darling Nail",
    "wof:placetype":"venue"
},
  "geometry": {"coordinates":[-118.33640200000001,33.988894],"type":"Point"}
}