{
  "type": "Feature",
  "properties": {
    "addr:full":"501 J St Sacramento CA 95814",
    "addr:housenumber":"501",
    "addr:postcode":"95814",
    "addr:street":"J St",
    "iso:country":"US",
    "sg:address":"501 J St",
    "sg:city":"Sacramento",
    "sg:classifiers":[
        {
            "category":"Professional",
            "subcategory":"Management & Consulting",
            "type":"Services"
        }
    ],
    "sg:phone":"+1 916 442 6996",
    "sg:postcode":"95814",
    "sg:province":"CA",
    "sg:tags":[
        "construction"
    ],
    "wof:name":"Kitchell Corrections Project",
    "wof:placetype":"venue"
},
  "geometry": {"coordinates":[-121.49878200000001,38.581731],"type":"Point"}
}