{
  "type": "Feature",
  "properties": {
    "addr:full":"657 Walnut St San Bruno CA 94066",
    "addr:housenumber":"657",
    "addr:postcode":"94066",
    "addr:street":"Walnut St",
    "iso:country":"US",
    "sg:address":"657 Walnut St",
    "sg:city":"San Bruno",
    "sg:classifiers":[
        {
            "category":"Manufacturing",
            "subcategory":"Printing",
            "type":"Manufacturing & Wholesale Goods"
        }
    ],
    "sg:phone":"+1 650 873 3983",
    "sg:postcode":"94066",
    "sg:province":"CA",
    "sg:tags":[
        "printer"
    ],
    "wof:name":"J S Camin's Music & Media",
    "wof:placetype":"venue"
},
  "geometry": {"coordinates":[-122.407256,37.632793],"type":"Point"}
}