{
  "type": "Feature",
  "properties": {
    "addr:full":"1705 E Capitol Expressway Suite 10 San Jose CA 95121",
    "addr:housenumber":"1705;10",
    "addr:postcode":"95121",
    "addr:street":"E Capitol Expressway Suite;Jose",
    "iso:country":"US",
    "sg:address":"1705 E Capitol Expressway Suite 10",
    "sg:city":"San Jose",
    "sg:classifiers":[
        {
            "category":"Shopping",
            "subcategory":"Mobile Phones",
            "type":"Retail Goods"
        }
    ],
    "sg:phone":"+1 408 270 1733",
    "sg:postcode":"95121",
    "sg:province":"CA",
    "wof:name":"T Mobile",
    "wof:placetype":"venue"
},
  "geometry": {"coordinates":[-121.810507,37.307543],"type":"Point"}
}