{
  "type": "Feature",
  "properties": {
    "addr:full":"850 Main St Cambria CA 93428",
    "addr:housenumber":"850",
    "addr:postcode":"93428",
    "addr:street":"Main St",
    "iso:country":"US",
    "sg:address":"850 Main St",
    "sg:city":"Cambria",
    "sg:classifiers":[
        {
            "category":"Food & Beverages",
            "subcategory":"Groceries & Convenience Stores",
            "type":"Retail Goods"
        }
    ],
    "sg:phone":"+1 805 927 0975",
    "sg:postcode":"93428",
    "sg:province":"CA",
    "wof:name":"Cambria General Store",
    "wof:placetype":"venue"
},
  "geometry": {"coordinates":[-121.09899900000001,35.5667],"type":"Point"}
}