{
  "type": "Feature",
  "properties": {
    "iso:country":"US",
    "sg:address":"15460 Valley Blvd",
    "sg:city":"City Of Industry",
    "sg:classifiers":[
        {
            "category":"Retail",
            "subcategory":"Auto Repair",
            "type":"Services"
        }
    ],
    "sg:phone":"+1 626 336 4595",
    "sg:postcode":"91746",
    "sg:province":"CA",
    "sg:tags":[
        "repairing",
        "automobile"
    ],
    "wof:name":"P J Bonifacio Motorworks",
    "wof:placetype":"venue"
},
  "geometry": {"coordinates":[-117.963739,34.026842],"type":"Point"}
}