{
  "type": "Feature",
  "properties": {
    "iso:country":"US",
    "sg:address":"6306 Eureka Avenue",
    "sg:city":"El Cerrito",
    "sg:classifiers":[
        {
            "category":"Professional",
            "subcategory":"Lawyer & Legal Services",
            "type":"Services"
        }
    ],
    "sg:phone":"+1 510 524 7750",
    "sg:postcode":"94530",
    "sg:province":"CA",
    "wof:name":"Kessler Darren J",
    "wof:placetype":"venue"
},
  "geometry": {"coordinates":[-122.30500000000001,37.9062],"type":"Point"}
}