{
  "type": "Feature",
  "properties": {
    "addr:full":"1848 E 57th St Los Angeles CA 90058",
    "addr:housenumber":"1848",
    "addr:postcode":"90058",
    "addr:street":"E 57Th St",
    "iso:country":"US",
    "sg:address":"1848 E 57th St",
    "sg:city":"Los Angeles",
    "sg:classifiers":[
        {
            "category":"Retail",
            "subcategory":"Repair Shop",
            "type":"Services"
        }
    ],
    "sg:phone":"+1 323 585 1715",
    "sg:postcode":"90058",
    "sg:province":"CA",
    "sg:tags":[
        "welding"
    ],
    "wof:name":"S K Welding Inc",
    "wof:placetype":"venue"
},
  "geometry": {"coordinates":[-118.23924,33.991152],"type":"Point"}
}