{
  "type": "Feature",
  "properties": {
    "iso:country":"US",
    "sg:address":"3111 Scotts Valley Dr.",
    "sg:city":"Scotts Valley",
    "sg:classifiers":[
        {
            "category":"Personal",
            "subcategory":"Beauty Salon",
            "type":"Services"
        },
        {
            "category":"Personal",
            "subcategory":"Barber",
            "type":"Services"
        }
    ],
    "sg:phone":"+1 831 440 0330",
    "sg:postcode":"95066",
    "sg:province":"CA",
    "sg:tags":[
        "hair"
    ],
    "wof:name":"Cookie's Cutters, A Graceful Hair Salon",
    "wof:placetype":"venue"
},
  "geometry": {"coordinates":[-122.024586,37.043544],"type":"Point"}
}