{
  "type": "Feature",
  "properties": {
    "addr:full":"8772 Valley Blvd Rosemead CA 91770",
    "addr:housenumber":"8772",
    "addr:postcode":"91770",
    "addr:street":"Valley Blvd",
    "iso:country":"US",
    "sg:address":"8772 Valley Blvd",
    "sg:city":"Rosemead",
    "sg:classifiers":[
        {
            "category":"Restaurant",
            "type":"Food & Drink"
        }
    ],
    "sg:phone":"+1 626 280 8389",
    "sg:postcode":"91770",
    "sg:province":"CA",
    "sg:tags":[
        "seafood"
    ],
    "wof:name":"Hunan Seafood",
    "wof:placetype":"venue"
},
  "geometry": {"coordinates":[-118.078391,34.080655],"type":"Point"}
}