{
  "type": "Feature",
  "properties": {
    "iso:country":"US",
    "sg:address":"10807 Rush St # A",
    "sg:city":"South El Monte",
    "sg:classifiers":[
        {
            "category":"Retail",
            "subcategory":"Auto Repair",
            "type":"Services"
        }
    ],
    "sg:phone":"+1 626 401 3228",
    "sg:postcode":"91733",
    "sg:province":"CA",
    "sg:tags":[
        "body",
        "shop"
    ],
    "wof:name":"Garvey Auto Body",
    "wof:placetype":"venue"
},
  "geometry": {"coordinates":[-118.039001,34.051998],"type":"Point"}
}