{
  "type": "Feature",
  "properties": {
    "addr:full":"1491 Bridge St Yuba City CA 95993",
    "addr:housenumber":"1491",
    "addr:postcode":"95993",
    "addr:street":"Bridge St",
    "iso:country":"US",
    "sg:address":"1491 Bridge St",
    "sg:city":"Yuba City",
    "sg:classifiers":[
        {
            "category":"Real Estate",
            "subcategory":"Real Estate Operator",
            "type":"Services"
        }
    ],
    "sg:phone":"+1 530 671 6223",
    "sg:postcode":"95993",
    "sg:province":"CA",
    "sg:tags":[
        "apartment"
    ],
    "wof:name":"Westbridge Townhouses",
    "wof:placetype":"venue"
},
  "geometry": {"coordinates":[-121.63553400000001,39.132387],"type":"Point"}
}