{
  "type": "Feature",
  "properties": {
    "iso:country":"US",
    "sg:address":"7709 S Laurelglen Blvd",
    "sg:city":"Bakersfield",
    "sg:classifiers":[
        {
            "category":"Building & Trades",
            "subcategory":"Pest Control",
            "type":"Services"
        }
    ],
    "sg:phone":"+1 661 834 6445",
    "sg:postcode":"93309",
    "sg:province":"CA",
    "wof:name":"DOA Pest Solutions",
    "wof:placetype":"venue"
},
  "geometry": {"coordinates":[-119.089581,35.325321],"type":"Point"}
}