{
  "type": "Feature",
  "properties": {
    "addr:full":"6115 Orange Ave Long Beach CA 90805",
    "addr:housenumber":"6115",
    "addr:postcode":"90805",
    "addr:street":"Orange Ave",
    "iso:country":"US",
    "sg:address":"6115 Orange Ave",
    "sg:city":"Long Beach",
    "sg:classifiers":[
        {
            "category":"Professional",
            "subcategory":"Accounting & Tax Preparation",
            "type":"Services"
        }
    ],
    "sg:phone":"+1 562 984 9438",
    "sg:postcode":"90805",
    "sg:province":"CA",
    "sg:tags":[
        "return",
        "filing"
    ],
    "wof:name":"Walker Tax & Financial Inc",
    "wof:placetype":"venue"
},
  "geometry": {"coordinates":[-118.177318,33.867354],"type":"Point"}
}