{
  "type": "Feature",
  "properties": {
    "addr:full":"1166 Mission Rd South San Francisco CA 94080",
    "addr:housenumber":"1166",
    "addr:postcode":"94080",
    "addr:street":"Mission Rd",
    "iso:country":"US",
    "sg:address":"1166 Mission Rd",
    "sg:city":"South San Francisco",
    "sg:classifiers":[
        {
            "category":"Shopping",
            "subcategory":"Pharmacy",
            "type":"Retail Goods"
        }
    ],
    "sg:phone":"+1 650 589 4133",
    "sg:postcode":"94080",
    "sg:province":"CA",
    "sg:tags":[
        "drugstore"
    ],
    "wof:name":"Sunshine Center Pharmacy",
    "wof:placetype":"venue"
},
  "geometry": {"coordinates":[-122.439003,37.661701],"type":"Point"}
}