{
  "type": "Feature",
  "properties": {
    "addr:full":"2015 Preisker Ln Santa Maria CA 93454",
    "addr:housenumber":"2015",
    "addr:postcode":"93454",
    "addr:street":"Preisker Ln",
    "iso:country":"US",
    "sg:address":"2015 Preisker Ln",
    "sg:city":"Santa Maria",
    "sg:classifiers":[
        {
            "category":"Wholesale",
            "subcategory":"Machinery & Supplies",
            "type":"Manufacturing & Wholesale Goods"
        }
    ],
    "sg:phone":"+1 805 349 3766",
    "sg:postcode":"93454",
    "sg:province":"CA",
    "sg:tags":[
        "janitor",
        "establishment",
        "equipment"
    ],
    "wof:name":"Commercial Sanitary Supply",
    "wof:placetype":"venue"
},
  "geometry": {"coordinates":[-120.43176099999999,34.979101],"type":"Point"}
}