{
  "type": "Feature",
  "properties": {
    "iso:country":"US",
    "sg:address":"47240 W Eldorado Dr",
    "sg:city":"Indian Wells",
    "sg:classifiers":[
        {
            "category":"Professional",
            "subcategory":"Management & Consulting",
            "type":"Services"
        }
    ],
    "sg:phone":"+1 760 568 1416",
    "sg:postcode":"92210",
    "sg:province":"CA",
    "sg:tags":[
        "consultant",
        "business"
    ],
    "wof:name":"Tappan Enterprises",
    "wof:placetype":"venue"
},
  "geometry": {"coordinates":[-116.34131600000001,33.706051],"type":"Point"}
}