{
  "type": "Feature",
  "properties": {
    "addr:full":"8430 S Gate Ave South Gate CA 90280",
    "addr:housenumber":"8430",
    "addr:postcode":"90280",
    "addr:street":"S Gate Ave;Gate",
    "iso:country":"US",
    "sg:address":"8430 S Gate Ave",
    "sg:city":"South Gate",
    "sg:classifiers":[
        {
            "category":"Real Estate",
            "subcategory":"Real Estate Agent",
            "type":"Services"
        }
    ],
    "sg:phone":"+1 323 566 3115",
    "sg:postcode":"90280",
    "sg:province":"CA",
    "wof:name":"Delmar Property Management",
    "wof:placetype":"venue"
},
  "geometry": {"coordinates":[-118.21369799999999,33.95975],"type":"Point"}
}