{
  "type": "Feature",
  "properties": {
    "iso:country":"US",
    "sg:address":"890 Cactus Ln",
    "sg:city":"Carpinteria",
    "sg:classifiers":[
        {
            "category":"Shopping",
            "subcategory":"Pets & Pet Supplies",
            "type":"Retail Goods"
        }
    ],
    "sg:phone":"+1 805 684 9988",
    "sg:postcode":"93013",
    "sg:province":"CA",
    "sg:tags":[
        "store"
    ],
    "wof:name":"Petcetera",
    "wof:placetype":"venue"
},
  "geometry": {"coordinates":[-119.51799800000001,34.398102],"type":"Point"}
}