{
  "type": "Feature",
  "properties": {
    "addr:full":"19233 Wells Dr Tarzana CA 91356",
    "addr:housenumber":"19233",
    "addr:postcode":"91356",
    "addr:street":"Wells Dr",
    "iso:country":"US",
    "sg:address":"19233 Wells Dr",
    "sg:city":"Tarzana",
    "sg:classifiers":[
        {
            "category":"Health Services",
            "subcategory":"Doctor",
            "type":"Services"
        }
    ],
    "sg:phone":"+1 818 346 2239",
    "sg:postcode":"91356",
    "sg:province":"CA",
    "sg:tags":[
        "physician",
        "surgeon"
    ],
    "wof:name":"West Hills Anesthesia Care Grp",
    "wof:placetype":"venue"
},
  "geometry": {"coordinates":[-118.553183,34.163882],"type":"Point"}
}