{
  "type": "Feature",
  "properties": {
    "iso:country":"US",
    "sg:address":"750 S Lincoln Ave",
    "sg:city":"Corona",
    "sg:classifiers":[
        {
            "category":"Communications",
            "type":"Services"
        }
    ],
    "sg:phone":"+1 714 397 1910",
    "sg:postcode":"92882",
    "sg:province":"CA",
    "sg:tags":[
        "telecommunication"
    ],
    "wof:name":"Wireless Infrastructure Svcs",
    "wof:placetype":"venue"
},
  "geometry": {"coordinates":[-117.58350799999999,33.875678],"type":"Point"}
}