{
  "type": "Feature",
  "properties": {
    "iso:country":"US",
    "sg:address":"5119 W El Segundo Blvd",
    "sg:city":"Hawthorne",
    "sg:classifiers":[
        {
            "category":"Restaurant",
            "type":"Food & Drink"
        }
    ],
    "sg:phone":"+1 310 676 8228",
    "sg:postcode":"90250",
    "sg:province":"CA",
    "sg:tags":[
        "american",
        "latin"
    ],
    "sg:website":"www.arcense.com",
    "wof:name":"Pupuseria Arcense",
    "wof:placetype":"venue"
},
  "geometry": {"coordinates":[-118.367555,33.916419],"type":"Point"}
}