{
  "type": "Feature",
  "properties": {
    "iso:country":"US",
    "sg:address":"934 E Alosta Ave",
    "sg:city":"Azusa",
    "sg:classifiers":[
        {
            "category":"Personal",
            "subcategory":"Beauty Salon",
            "type":"Services"
        }
    ],
    "sg:phone":"+1 626 633 1924",
    "sg:postcode":"91702",
    "sg:province":"CA",
    "wof:name":"Lam Beauty & Barber Salon",
    "wof:placetype":"venue"
},
  "geometry": {"coordinates":[-117.88575299999999,34.12865],"type":"Point"}
}