{
  "type": "Feature",
  "properties": {
    "addr:full":"950 Sebastopol Rd Santa Rosa CA 95407",
    "addr:housenumber":"950",
    "addr:postcode":"95407",
    "addr:street":"Sebastopol Rd",
    "iso:country":"US",
    "sg:address":"950 Sebastopol Rd",
    "sg:city":"Santa Rosa",
    "sg:classifiers":[
        {
            "category":"Education",
            "subcategory":"School",
            "type":"Public Place"
        }
    ],
    "sg:phone":"+1 707 545 0100",
    "sg:postcode":"95407",
    "sg:province":"CA",
    "wof:name":"Roseland Elem Sch Dist",
    "wof:placetype":"venue"
},
  "geometry": {"coordinates":[-122.73159200000001,38.42903],"type":"Point"}
}