{
  "type": "Feature",
  "properties": {
    "addr:full":"3203 Luyung Drive Rancho Cordova CA 95742",
    "addr:housenumber":"3203",
    "addr:postcode":"95742",
    "addr:street":"Luyung Drive",
    "iso:country":"US",
    "sg:address":"3203 Luyung Drive",
    "sg:city":"Rancho Cordova",
    "sg:classifiers":[
        {
            "category":"Building & Trades",
            "subcategory":"Construction",
            "type":"Services"
        },
        {
            "category":"Building & Trades",
            "subcategory":"Electrical",
            "type":"Services"
        }
    ],
    "sg:phone":"+1 916 631 9293",
    "sg:postcode":"95742",
    "sg:province":"CA",
    "sg:tags":[
        "installation",
        "electrician",
        "solar"
    ],
    "sg:website":"www.solaron.net",
    "wof:name":"Solaron Pool Heating",
    "wof:placetype":"venue"
},
  "geometry": {"coordinates":[-121.25516,38.586811],"type":"Point"}
}