{
  "type": "Feature",
  "properties": {
    "addr:full":"239 S Catalina St Ventura CA 93001",
    "addr:housenumber":"239",
    "addr:postcode":"93001",
    "addr:street":"S Catalina St",
    "iso:country":"US",
    "sg:address":"239 S Catalina St",
    "sg:city":"Ventura",
    "sg:classifiers":[
        {
            "category":"Personal",
            "subcategory":"Beauty Salon",
            "type":"Services"
        }
    ],
    "sg:phone":"+1 805 643 1239",
    "sg:postcode":"93001",
    "sg:province":"CA",
    "wof:name":"Kathy's Hair Shack",
    "wof:placetype":"venue"
},
  "geometry": {"coordinates":[-119.270206,34.274639],"type":"Point"}
}