{
  "type": "Feature",
  "properties": {
    "addr:full":"1550 Moorland Dr San Diego CA 92109",
    "addr:housenumber":"1550",
    "addr:postcode":"92109",
    "addr:street":"Moorland Dr",
    "iso:country":"US",
    "sg:address":"1550 Moorland Dr",
    "sg:city":"San Diego",
    "sg:classifiers":[
        {
            "category":"Health Services",
            "subcategory":"Doctor",
            "type":"Services"
        }
    ],
    "sg:phone":"+1 858 273 0753",
    "sg:postcode":"92109",
    "sg:province":"CA",
    "sg:tags":[
        "physician",
        "surgeon"
    ],
    "wof:name":"William M Bristow MD",
    "wof:placetype":"venue"
},
  "geometry": {"coordinates":[-117.237764,32.786664],"type":"Point"}
}