{
  "type": "Feature",
  "properties": {
    "iso:country":"US",
    "sg:address":"10680 Balboa Blvd",
    "sg:city":"Granada Hills",
    "sg:classifiers":[
        {
            "category":"Restaurant",
            "type":"Food & Drink"
        }
    ],
    "sg:menulink":"http://www.allmenus.com/ca/san-fernando-valley/150284-subway/menu/",
    "sg:phone":"+1 818 366 2422",
    "sg:postcode":"91344",
    "sg:province":"CA",
    "sg:tags":[
        "american",
        "sandwich"
    ],
    "wof:name":"Subway",
    "wof:placetype":"venue"
},
  "geometry": {"coordinates":[-118.502269,34.264295],"type":"Point"}
}