{
  "type": "Feature",
  "properties": {
    "iso:country":"US",
    "sg:address":"612 G St",
    "sg:city":"Eureka",
    "sg:classifiers":[
        {
            "category":"Recreation",
            "type":"Entertainment"
        }
    ],
    "sg:phone":"+1 707 443 6381",
    "sg:postcode":"95501",
    "sg:province":"CA",
    "sg:tags":[
        "club",
        "membership"
    ],
    "wof:name":"Humboldt Singles Club",
    "wof:placetype":"venue"
},
  "geometry": {"coordinates":[-124.164733,40.801105],"type":"Point"}
}