{
  "type": "Feature",
  "properties": {
    "addr:full":"2708 Marconi Avenue Sacramento CA 95821",
    "addr:housenumber":"2708",
    "addr:postcode":"95821",
    "addr:street":"Marconi Avenue",
    "iso:country":"US",
    "sg:address":"2708 Marconi Avenue",
    "sg:city":"Sacramento",
    "sg:classifiers":[
        {
            "category":"Arena",
            "subcategory":"Sports Club",
            "type":"Entertainment"
        }
    ],
    "sg:phone":"+1 916 485 1444",
    "sg:postcode":"95821",
    "sg:province":"CA",
    "sg:tags":[
        "martial art",
        "instruction"
    ],
    "wof:name":"Family Martial Arts",
    "wof:placetype":"venue"
},
  "geometry": {"coordinates":[-121.398802,38.617858],"type":"Point"}
}