{
  "type": "Feature",
  "properties": {
    "addr:full":"8927 Amigo Ave Northridge CA 91324",
    "addr:housenumber":"8927",
    "addr:postcode":"91324",
    "addr:street":"Amigo Ave",
    "iso:country":"US",
    "sg:address":"8927 Amigo Ave",
    "sg:city":"Northridge",
    "sg:classifiers":[
        {
            "category":"Real Estate",
            "subcategory":"Real Estate Services",
            "type":"Services"
        },
        {
            "category":"Real Estate",
            "subcategory":"Real Estate Agent",
            "type":"Services"
        }
    ],
    "sg:phone":"+1 818 407 1947",
    "sg:postcode":"91324",
    "sg:province":"CA",
    "sg:tags":[
        "management"
    ],
    "wof:name":"On Way Re Investments",
    "wof:placetype":"venue"
},
  "geometry": {"coordinates":[-118.53810900000001,34.232225],"type":"Point"}
}