{
  "type": "Feature",
  "properties": {
    "iso:country":"US",
    "sg:address":"2501 Wilshire Blvd",
    "sg:city":"Los Angeles",
    "sg:classifiers":[
        {
            "category":"Real Estate",
            "subcategory":"Real Estate Agent",
            "type":"Services"
        }
    ],
    "sg:phone":"+1 213 389 9803",
    "sg:postcode":"90057",
    "sg:province":"CA",
    "wof:name":"Hayworth",
    "wof:placetype":"venue"
},
  "geometry": {"coordinates":[-118.281417,34.060506],"type":"Point"}
}