{
  "type": "Feature",
  "properties": {
    "iso:country":"US",
    "sg:address":"700 23rd St",
    "sg:city":"Bakersfield",
    "sg:classifiers":[
        {
            "category":"Retail",
            "subcategory":"Auto Repair",
            "type":"Services"
        }
    ],
    "sg:phone":"+1 661 327 7966",
    "sg:postcode":"93301",
    "sg:province":"CA",
    "sg:tags":[
        "automobile",
        "electric"
    ],
    "wof:name":"Medearis Electric",
    "wof:placetype":"venue"
},
  "geometry": {"coordinates":[-119.010592,35.380002],"type":"Point"}
}