{
  "type": "Feature",
  "properties": {
    "addr:full":"6810 Five Star Blvd Rocklin CA 95677",
    "addr:housenumber":"6810",
    "addr:postcode":"95677",
    "addr:street":"Five Star Blvd",
    "iso:country":"US",
    "sg:address":"6810 Five Star Blvd",
    "sg:city":"Rocklin",
    "sg:classifiers":[
        {
            "category":"Banks & Credit Unions",
            "subcategory":"Bank",
            "type":"Services"
        }
    ],
    "sg:phone":"+1 916 625 0610",
    "sg:postcode":"95677",
    "sg:province":"CA",
    "sg:tags":[
        "depository",
        "banking",
        "institution",
        "personal"
    ],
    "wof:name":"Beneficial",
    "wof:placetype":"venue"
},
  "geometry": {"coordinates":[-121.265423,38.781954],"type":"Point"}
}