{
  "type": "Feature",
  "properties": {
    "addr:full":"4875 Spring Rd Moorpark CA 93021",
    "addr:housenumber":"4875",
    "addr:postcode":"ca 93021",
    "addr:street":"Spring Rd",
    "iso:country":"US",
    "sg:address":"4875 Spring Rd",
    "sg:city":"Moorpark",
    "sg:classifiers":[
        {
            "category":"Professional",
            "subcategory":"Engineering",
            "type":"Services"
        }
    ],
    "sg:phone":"+1 805 529 3220",
    "sg:postcode":"93021",
    "sg:province":"CA",
    "sg:tags":[
        "general",
        "contractor"
    ],
    "wof:name":"A-C Construction Corp",
    "wof:placetype":"venue"
},
  "geometry": {"coordinates":[-118.87465899999999,34.276873],"type":"Point"}
}