{
  "type": "Feature",
  "properties": {
    "addr:full":"2141 Abbott St Oxnard CA 93033",
    "addr:housenumber":"2141",
    "addr:postcode":"93033",
    "addr:street":"Abbott St",
    "iso:country":"US",
    "sg:address":"2141 Abbott St",
    "sg:city":"Oxnard",
    "sg:classifiers":[
        {
            "category":"Shopping",
            "subcategory":"Computers & Home Electronics",
            "type":"Retail Goods"
        }
    ],
    "sg:phone":"+1 805 488 8806",
    "sg:postcode":"93033",
    "sg:province":"CA",
    "sg:tags":[
        "high",
        "fidelity",
        "stereophonic"
    ],
    "wof:name":"Ray Flick's Stereo Repair",
    "wof:placetype":"venue"
},
  "geometry": {"coordinates":[-119.151589,34.157163],"type":"Point"}
}