{
  "type": "Feature",
  "properties": {
    "iso:country":"US",
    "sg:address":"12421 Pearce St",
    "sg:city":"Garden Grove",
    "sg:classifiers":[
        {
            "category":"Shopping",
            "subcategory":"Clothing, Apparel, & Fashions",
            "type":"Retail Goods"
        }
    ],
    "sg:phone":"+1 714 534 4498",
    "sg:postcode":"92843",
    "sg:province":"CA",
    "wof:name":"Kelly Bridal & Prom",
    "wof:placetype":"venue"
},
  "geometry": {"coordinates":[-117.911841,33.76962],"type":"Point"}
}