{
  "type": "Feature",
  "properties": {
    "iso:country":"US",
    "sg:address":"785 Shadowridge Dr",
    "sg:city":"Vista",
    "sg:classifiers":[
        {
            "category":"Coffee & Tea",
            "type":"Food & Drink"
        },
        {
            "category":"Restaurant",
            "type":"Food & Drink"
        },
        {
            "category":"Food & Beverages",
            "subcategory":"Groceries & Convenience Stores",
            "type":"Retail Goods"
        }
    ],
    "sg:phone":"+1 760 727 5479",
    "sg:postcode":"92083",
    "sg:province":"CA",
    "sg:tags":[
        "espresso",
        "american",
        "latin",
        "mexican",
        "japanese"
    ],
    "wof:name":"Jumping Bean Cafe",
    "wof:placetype":"venue"
},
  "geometry": {"coordinates":[-117.221339,33.166222],"type":"Point"}
}