{
  "type": "Feature",
  "properties": {
    "iso:country":"US",
    "sg:address":"4200 Via Real",
    "sg:city":"Carpinteria",
    "sg:classifiers":[
        {
            "category":"Travel",
            "subcategory":"Hotels & Motels",
            "type":"Entertainment"
        }
    ],
    "sg:phone":"+1 805 684 6921",
    "sg:postcode":"93013",
    "sg:province":"CA",
    "sg:website":"www.motel6.com",
    "wof:name":"Motel 6 Carpinteria North",
    "wof:placetype":"venue"
},
  "geometry": {"coordinates":[-119.53721,34.405694],"type":"Point"}
}