{
  "type": "Feature",
  "properties": {
    "addr:full":"2929 La Cienega Boulevard Culver City CA 90232",
    "addr:housenumber":"2929",
    "addr:postcode":"90232",
    "addr:street":"La Cienega Boulevard",
    "iso:country":"US",
    "sg:address":"2929 La Cienega Boulevard",
    "sg:city":"Culver City",
    "sg:classifiers":[
        {
            "category":"Retail",
            "subcategory":"Auto Repair",
            "type":"Services"
        }
    ],
    "sg:phone":"+1 310 733 4138",
    "sg:postcode":"90232",
    "sg:province":"CA",
    "wof:name":"Annex Automotive Services",
    "wof:placetype":"venue"
},
  "geometry": {"coordinates":[-118.37298199999999,34.0318],"type":"Point"}
}