{
  "type": "Feature",
  "properties": {
    "addr:full":"44827 San Pablo Ave Palm Desert CA 92260",
    "addr:housenumber":"44827",
    "addr:postcode":"ca 92260",
    "addr:street":"San Pablo Ave",
    "iso:country":"US",
    "sg:address":"44827 San Pablo Ave",
    "sg:city":"Palm Desert",
    "sg:classifiers":[
        {
            "category":"Restaurant",
            "type":"Food & Drink"
        }
    ],
    "sg:phone":"+1 760 776 8888",
    "sg:postcode":"92260",
    "sg:province":"CA",
    "wof:name":"Restaurant Express",
    "wof:placetype":"venue"
},
  "geometry": {"coordinates":[-116.382608,33.723503],"type":"Point"}
}