{
  "type": "Feature",
  "properties": {
    "addr:full":"2970 Grace Ln Costa Mesa CA 92626",
    "addr:housenumber":"2970",
    "addr:postcode":"92626",
    "addr:street":"Grace Ln",
    "iso:country":"US",
    "sg:address":"2970 Grace Ln",
    "sg:city":"Costa Mesa",
    "sg:classifiers":[
        {
            "category":"Building & Trades",
            "subcategory":"Construction",
            "type":"Services"
        }
    ],
    "sg:phone":"+1 714 546 5730",
    "sg:postcode":"92626",
    "sg:province":"CA",
    "sg:tags":[
        "masonry",
        "contractor"
    ],
    "wof:name":"Jasper & Sons Masonry Inc",
    "wof:placetype":"venue"
},
  "geometry": {"coordinates":[-117.902495,33.67894],"type":"Point"}
}