{
  "type": "Feature",
  "properties": {
    "iso:country":"US",
    "sg:address":"1950 E 20th St",
    "sg:city":"Chico",
    "sg:classifiers":[
        {
            "category":"Shopping",
            "subcategory":"Clothing, Apparel, & Fashions",
            "type":"Retail Goods"
        }
    ],
    "sg:phone":"+1 530 898 9358",
    "sg:postcode":"95928",
    "sg:province":"CA",
    "sg:tags":[
        "sportswear"
    ],
    "wof:name":"American Eagle Outfitters",
    "wof:placetype":"venue"
},
  "geometry": {"coordinates":[-121.80262999999999,39.727383],"type":"Point"}
}