{
  "type": "Feature",
  "properties": {
    "addr:full":"27959 Cabot Rd Laguna Niguel CA 92677",
    "addr:housenumber":"27959",
    "addr:postcode":"92677",
    "addr:street":"Cabot Rd",
    "iso:country":"US",
    "sg:address":"27959 Cabot Rd",
    "sg:city":"Laguna Niguel",
    "sg:classifiers":[
        {
            "category":"Shopping",
            "subcategory":"Pets & Pet Supplies",
            "type":"Retail Goods"
        }
    ],
    "sg:phone":"+1 949 582 5056",
    "sg:postcode":"92677",
    "sg:province":"CA",
    "sg:tags":[
        "store"
    ],
    "wof:name":"American Horse Products",
    "wof:placetype":"venue"
},
  "geometry": {"coordinates":[-117.679306,33.558129],"type":"Point"}
}