{
  "type": "Feature",
  "properties": {
    "addr:full":"13397 S Henderson Rd Caruthers CA 93609",
    "addr:housenumber":"13397",
    "addr:postcode":"93609",
    "addr:street":"S Henderson Rd",
    "iso:country":"US",
    "sg:address":"13397 S Henderson Rd",
    "sg:city":"Caruthers",
    "sg:classifiers":[
        {
            "category":"Manufacturing",
            "subcategory":"Tools & Machinery",
            "type":"Manufacturing & Wholesale Goods"
        }
    ],
    "sg:phone":"+1 559 864 8940",
    "sg:postcode":"93609",
    "sg:province":"CA",
    "sg:tags":[
        "machine",
        "shop"
    ],
    "wof:name":"Potter's Engine Machine Shop",
    "wof:placetype":"venue"
},
  "geometry": {"coordinates":[-119.83264,36.542527],"type":"Point"}
}