{
  "type": "Feature",
  "properties": {
    "iso:country":"US",
    "sg:address":"8540 Crosspointe Ct",
    "sg:city":"Antelope",
    "sg:classifiers":[
        {
            "category":"Professional",
            "subcategory":"Art Services",
            "type":"Services"
        }
    ],
    "sg:phone":"+1 916 728 1737",
    "sg:postcode":"95843",
    "sg:province":"CA",
    "sg:tags":[
        "photographer"
    ],
    "wof:name":"J P David Photo Design",
    "wof:placetype":"venue"
},
  "geometry": {"coordinates":[-121.344083,38.724206],"type":"Point"}
}