{
  "type": "Feature",
  "properties": {
    "iso:country":"US",
    "sg:address":"14993 Meridian Rd",
    "sg:city":"Castroville",
    "sg:classifiers":[
        {
            "category":"Building & Trades",
            "subcategory":"Cleaning & Sanitation",
            "type":"Services"
        }
    ],
    "sg:phone":"+1 831 809 7674",
    "sg:postcode":"95012",
    "sg:province":"CA",
    "sg:tags":[
        "janitor"
    ],
    "wof:name":"Contreras Cleaning Svc",
    "wof:placetype":"venue"
},
  "geometry": {"coordinates":[-121.703982,36.789145],"type":"Point"}
}