{
  "type": "Feature",
  "properties": {
    "addr:full":"9735 Wilshire Blvd Beverly Hills CA 90212",
    "addr:housenumber":"9735",
    "addr:postcode":"90212",
    "addr:street":"Wilshire Blvd",
    "iso:country":"US",
    "sg:address":"9735 Wilshire Blvd",
    "sg:city":"Beverly Hills",
    "sg:classifiers":[
        {
            "category":"Health Services",
            "subcategory":"Medical Lab",
            "type":"Services"
        }
    ],
    "sg:phone":"+1 310 385 9240",
    "sg:postcode":"90212",
    "sg:province":"CA",
    "sg:tags":[
        "laboratory"
    ],
    "wof:name":"Westcliff Medical Laboratories",
    "wof:placetype":"venue"
},
  "geometry": {"coordinates":[-118.406707,34.067071],"type":"Point"}
}