{
  "type": "Feature",
  "properties": {
    "addr:full":"560 S Los Angeles St Los Angeles CA 90013",
    "addr:housenumber":"560",
    "addr:postcode":"90013",
    "addr:street":"S;Angeles St",
    "iso:country":"US",
    "sg:address":"560 S Los Angeles St",
    "sg:city":"Los Angeles",
    "sg:classifiers":[
        {
            "category":"Shopping",
            "type":"Retail Goods"
        }
    ],
    "sg:phone":"+1 213 623 8633",
    "sg:postcode":"90013",
    "sg:province":"CA",
    "sg:tags":[
        "art",
        "gallery",
        "dealer"
    ],
    "wof:name":"B & N Prima Group Inc",
    "wof:placetype":"venue"
},
  "geometry": {"coordinates":[-118.248124,34.04544],"type":"Point"}
}