{
  "type": "Feature",
  "properties": {
    "iso:country":"US",
    "sg:address":"2570 W el Camino Real",
    "sg:city":"Mountain View",
    "sg:classifiers":[
        {
            "category":"Professional",
            "subcategory":"Accounting & Tax Preparation",
            "type":"Services"
        }
    ],
    "sg:phone":"+1 650 988 7300",
    "sg:postcode":"94040",
    "sg:province":"CA",
    "sg:tags":[
        "return",
        "filing"
    ],
    "sg:website":"www.americanexpress.com",
    "wof:name":"American Express Tax & Bus Svc",
    "wof:placetype":"venue"
},
  "geometry": {"coordinates":[-122.112236,37.400553],"type":"Point"}
}