{
  "type": "Feature",
  "properties": {
    "addr:full":"1411 Marsh St San Luis Obispo CA 93401",
    "addr:housenumber":"1411",
    "addr:postcode":"93401",
    "addr:street":"Marsh St",
    "iso:country":"US",
    "sg:address":"1411 Marsh St",
    "sg:city":"San Luis Obispo",
    "sg:classifiers":[
        {
            "category":"Health Services",
            "subcategory":"Health Practitioner",
            "type":"Services"
        }
    ],
    "sg:phone":"+1 805 544 0201",
    "sg:postcode":"93401",
    "sg:province":"CA",
    "sg:tags":[
        "psychologist"
    ],
    "wof:name":"Cynthia Breaux PHD",
    "wof:placetype":"venue"
},
  "geometry": {"coordinates":[-120.65329300000001,35.284642],"type":"Point"}
}