{
  "type": "Feature",
  "properties": {
    "addr:full":"43424 Copeland Cir Lancaster CA 93535",
    "addr:housenumber":"43424",
    "addr:postcode":"93535",
    "addr:street":"Copeland Cir",
    "iso:country":"US",
    "sg:address":"43424 Copeland Cir",
    "sg:city":"Lancaster",
    "sg:classifiers":[
        {
            "category":"Manufacturing",
            "subcategory":"Tools & Machinery",
            "type":"Manufacturing & Wholesale Goods"
        }
    ],
    "sg:phone":"+1 661 940 1909",
    "sg:postcode":"93535",
    "sg:province":"CA",
    "sg:tags":[
        "machine",
        "shop"
    ],
    "wof:name":"Hardway Manufacturing",
    "wof:placetype":"venue"
},
  "geometry": {"coordinates":[-118.12576799999999,34.671586],"type":"Point"}
}