{
  "type": "Feature",
  "properties": {
    "iso:country":"US",
    "sg:address":"43424 Copeland Cir",
    "sg:city":"Lancaster",
    "sg:classifiers":[
        {
            "category":"Manufacturing",
            "subcategory":"Tools & Machinery",
            "type":"Manufacturing & Wholesale Goods"
        }
    ],
    "sg:phone":"+1 661 940 1909",
    "sg:postcode":"93535",
    "sg:province":"CA",
    "sg:tags":[
        "machine",
        "shop"
    ],
    "wof:name":"Hardway Manufacturing",
    "wof:placetype":"venue"
},
  "geometry": {"coordinates":[-118.125768,34.671586],"type":"Point"}
}