{
  "type": "Feature",
  "properties": {
    "iso:country":"US",
    "sg:address":"5919 West 3rd St",
    "sg:city":"Los Angeles",
    "sg:classifiers":[
        {
            "category":"Shopping",
            "subcategory":"Used Merchandise",
            "type":"Retail Goods"
        }
    ],
    "sg:phone":"+1 310 869 5239",
    "sg:postcode":"90036",
    "sg:province":"CA",
    "sg:tags":[
        "vintage",
        "consignment"
    ],
    "sg:website":"www.mariemonsod.com/",
    "wof:name":"Marie Monsod",
    "wof:placetype":"venue"
},
  "geometry": {"coordinates":[-118.349203,34.069818],"type":"Point"}
}