{
  "type": "Feature",
  "properties": {
    "iso:country":"US",
    "sg:address":"494 N Allen Ave",
    "sg:city":"Pasadena",
    "sg:classifiers":[
        {
            "category":"Professional",
            "subcategory":"Advertising",
            "type":"Services"
        }
    ],
    "sg:phone":"+1 626 792 9080",
    "sg:postcode":"91106",
    "sg:province":"CA",
    "sg:tags":[
        "counselor"
    ],
    "wof:name":"B K Jacobs Enterprises",
    "wof:placetype":"venue"
},
  "geometry": {"coordinates":[-118.113139,34.154688],"type":"Point"}
}