{
  "type": "Feature",
  "properties": {
    "iso:country":"US",
    "sg:address":"23792 New Delhi St",
    "sg:city":"Mission Viejo",
    "sg:classifiers":[
        {
            "category":"Home & Garden",
            "subcategory":"Building Materials",
            "type":"Retail Goods"
        }
    ],
    "sg:phone":"+1 949 951 8037",
    "sg:postcode":"92691",
    "sg:province":"CA",
    "wof:name":"GMC Cabinetry",
    "wof:placetype":"venue"
},
  "geometry": {"coordinates":[-117.685531,33.616675],"type":"Point"}
}