{
  "type": "Feature",
  "properties": {
    "addr:full":"2756 Alvarado St Ste A San Leandro CA 94577",
    "addr:housenumber":"2756",
    "addr:postcode":"94577",
    "addr:street":"Alvarado St Ste A",
    "iso:country":"US",
    "sg:address":"2756 Alvarado St Ste A",
    "sg:city":"San Leandro",
    "sg:classifiers":[
        {
            "category":"Home & Garden",
            "subcategory":"Furniture",
            "type":"Retail Goods"
        }
    ],
    "sg:phone":"+1 510 351 9223",
    "sg:postcode":"94577",
    "sg:province":"CA",
    "sg:tags":[
        "store"
    ],
    "wof:name":"West Pacific Trading Co",
    "wof:placetype":"venue"
},
  "geometry": {"coordinates":[-122.153999,37.708302],"type":"Point"}
}