{
  "type": "Feature",
  "properties": {
    "iso:country":"US",
    "sg:address":"1314 N Clybourn Ave",
    "sg:city":"Burbank",
    "sg:classifiers":[
        {
            "category":"Building & Trades",
            "subcategory":"Locksmith",
            "type":"Services"
        }
    ],
    "sg:phone":"+1 818 841 6229",
    "sg:postcode":"91505",
    "sg:province":"CA",
    "sg:tags":[
        "lock",
        "industrial",
        "locksmiths-commercial"
    ],
    "wof:name":"Wolf Pack Productions",
    "wof:placetype":"venue"
},
  "geometry": {"coordinates":[-118.35638400000001,34.168859],"type":"Point"}
}