{
  "type": "Feature",
  "properties": {
    "addr:full":"3161 W Tyler Ave Anaheim CA 92801",
    "addr:housenumber":"3161",
    "addr:postcode":"92801",
    "addr:street":"W Tyler Ave",
    "iso:country":"US",
    "sg:address":"3161 W Tyler Ave",
    "sg:city":"Anaheim",
    "sg:classifiers":[
        {
            "category":"Professional",
            "type":"Services"
        }
    ],
    "sg:phone":"+1 714 826 1838",
    "sg:postcode":"92801",
    "sg:province":"CA",
    "wof:name":"Ninrodo Teodoro",
    "wof:placetype":"venue"
},
  "geometry": {"coordinates":[-117.99987900000001,33.833817],"type":"Point"}
}