{
  "type": "Feature",
  "properties": {
    "addr:full":"33 Merriewood Cir Oakland CA 94611",
    "addr:housenumber":"33",
    "addr:postcode":"94611",
    "addr:street":"Merriewood Cir",
    "iso:country":"US",
    "sg:address":"33 Merriewood Cir",
    "sg:city":"Oakland",
    "sg:classifiers":[
        {
            "category":"Professional",
            "type":"Services"
        }
    ],
    "sg:phone":"+1 510 594 8545",
    "sg:postcode":"94611",
    "sg:province":"CA",
    "wof:name":"Humboldt Brewery Co",
    "wof:placetype":"venue"
},
  "geometry": {"coordinates":[-122.212858,37.836665],"type":"Point"}
}