{
  "type": "Feature",
  "properties": {
    "addr:full":"66 E Santa Clara St San Jose CA 95113",
    "addr:housenumber":"66",
    "addr:postcode":"95113",
    "addr:street":"E Santa Clara St",
    "iso:country":"US",
    "sg:address":"66 E Santa Clara St",
    "sg:city":"San Jose",
    "sg:classifiers":[
        {
            "category":"Banks & Credit Unions",
            "subcategory":"Bank",
            "type":"Services"
        }
    ],
    "sg:phone":"+1 408 298 8600",
    "sg:postcode":"95113",
    "sg:province":"CA",
    "sg:tags":[
        "management",
        "loan",
        "real estate",
        "property"
    ],
    "sg:website":"www.scisj.com",
    "wof:name":"Saratoga Capital Inc",
    "wof:placetype":"venue"
},
  "geometry": {"coordinates":[-121.889,37.3367],"type":"Point"}
}