{
  "type": "Feature",
  "properties": {
    "iso:country":"US",
    "sg:address":"1020 E Prosperity Ave",
    "sg:city":"Tulare",
    "sg:classifiers":[
        {
            "category":"Autos & Motor Vehicles",
            "subcategory":"Auto Supplies",
            "type":"Retail Goods"
        }
    ],
    "sg:phone":"+1 559 688 2464",
    "sg:postcode":"93274",
    "sg:province":"CA",
    "sg:tags":[
        "tire"
    ],
    "wof:name":"T F Tire & Svc",
    "wof:placetype":"venue"
},
  "geometry": {"coordinates":[-119.331745,36.225444],"type":"Point"}
}