{
  "type": "Feature",
  "properties": {
    "addr:full":"38033 26th St E Palmdale CA 93550",
    "addr:housenumber":"38033",
    "addr:postcode":"ca 93550",
    "addr:street":"26Th St E",
    "iso:country":"US",
    "sg:address":"38033 26th St E",
    "sg:city":"Palmdale",
    "sg:classifiers":[
        {
            "category":"Building & Trades",
            "subcategory":"Landscaping Services",
            "type":"Services"
        }
    ],
    "sg:phone":"+1 661 947 4856",
    "sg:postcode":"93550",
    "sg:province":"CA",
    "sg:tags":[
        "landscape"
    ],
    "wof:name":"Carlins Landscape",
    "wof:placetype":"venue"
},
  "geometry": {"coordinates":[-118.083611,34.574099],"type":"Point"}
}