{
  "type": "Feature",
  "properties": {
    "addr:full":"4433 Exchange Ave Los Angeles CA 90058",
    "addr:housenumber":"4433",
    "addr:postcode":"90058",
    "addr:street":"Exchange Ave",
    "iso:country":"US",
    "sg:address":"4433 Exchange Ave",
    "sg:city":"Los Angeles",
    "sg:classifiers":[
        {
            "category":"Professional",
            "type":"Services"
        },
        {
            "category":"Manufacturing",
            "subcategory":"Motor Vehicles & Parts",
            "type":"Manufacturing & Wholesale Goods"
        }
    ],
    "sg:phone":"+1 323 583 3560",
    "sg:postcode":"90058",
    "sg:province":"CA",
    "sg:tags":[
        "equipment",
        "railroad",
        "establishment",
        "mfg"
    ],
    "wof:name":"M K Rail Corp",
    "wof:placetype":"venue"
},
  "geometry": {"coordinates":[-118.198694,34.001962],"type":"Point"}
}