{
  "type": "Feature",
  "properties": {
    "addr:full":"2033 Beatrice Court, unit 5 San Jose CA 95128",
    "addr:housenumber":"2033;5",
    "addr:postcode":"95128",
    "addr:street":"Beatrice Court Unit",
    "iso:country":"US",
    "sg:address":"2033 Beatrice Court, unit 5",
    "sg:city":"San Jose",
    "sg:classifiers":[
        {
            "category":"Building & Trades",
            "subcategory":"Construction",
            "type":"Services"
        }
    ],
    "sg:phone":"+1 650 834 1842",
    "sg:postcode":"95128",
    "sg:province":"CA",
    "sg:tags":[
        "contractor"
    ],
    "sg:website":"www.flagoverhead.com",
    "wof:name":"Flag Overhead Garage Door Service",
    "wof:placetype":"venue"
},
  "geometry": {"coordinates":[-121.928494,37.309483],"type":"Point"}
}