{
  "type": "Feature",
  "properties": {
    "addr:full":"8016 Raytheon Rd San Diego CA 92111",
    "addr:housenumber":"8016",
    "addr:postcode":"92111",
    "addr:street":"Raytheon Rd",
    "iso:country":"US",
    "sg:address":"8016 Raytheon Rd",
    "sg:city":"San Diego",
    "sg:classifiers":[
        {
            "category":"Wholesale",
            "subcategory":"Construction Materials",
            "type":"Manufacturing & Wholesale Goods"
        }
    ],
    "sg:phone":"+1 619 420 1892",
    "sg:postcode":"92111",
    "sg:province":"CA",
    "sg:tags":[
        "gates"
    ],
    "wof:name":"Ledezma Iron Works",
    "wof:placetype":"venue"
},
  "geometry": {"coordinates":[-117.151672,32.830944],"type":"Point"}
}