{
  "type": "Feature",
  "properties": {
    "iso:country":"US",
    "sg:address":"627 College Ave",
    "sg:city":"Santa Rosa",
    "sg:classifiers":[
        {
            "category":"Social Services",
            "type":"Services"
        }
    ],
    "sg:phone":"+1 707 544 7000",
    "sg:postcode":"95404",
    "sg:province":"CA",
    "sg:tags":[
        "counselor",
        "marriage",
        "family"
    ],
    "wof:name":"Robert B Casanova",
    "wof:placetype":"venue"
},
  "geometry": {"coordinates":[-122.71508799999999,38.445647],"type":"Point"}
}