{
  "type": "Feature",
  "properties": {
    "addr:full":"3201 F St Bakersfield CA 93301",
    "addr:housenumber":"3201",
    "addr:postcode":"93301",
    "addr:street":"F St",
    "iso:country":"US",
    "sg:address":"3201 F St",
    "sg:city":"Bakersfield",
    "sg:classifiers":[
        {
            "category":"Home & Garden",
            "subcategory":"Furniture",
            "type":"Retail Goods"
        }
    ],
    "sg:phone":"+1 661 326 0886",
    "sg:postcode":"93301",
    "sg:province":"CA",
    "wof:name":"Rocio's Furniture",
    "wof:placetype":"venue"
},
  "geometry": {"coordinates":[-119.023532,35.387259],"type":"Point"}
}