{
  "type": "Feature",
  "properties": {
    "iso:country":"US",
    "sg:address":"1205 Broadway Plz",
    "sg:city":"Walnut Creek",
    "sg:classifiers":[
        {
            "category":"Restaurant",
            "type":"Food & Drink"
        }
    ],
    "sg:menulink":"http://www.allmenus.com/ca/central-contra-costa/6663-pf-changs/menu/",
    "sg:phone":"+1 925 979 9070",
    "sg:postcode":"94596",
    "sg:province":"CA",
    "sg:tags":[
        "japanese",
        "chinese",
        "asian"
    ],
    "wof:name":"P.F. Chang's",
    "wof:placetype":"venue"
},
  "geometry": {"coordinates":[-122.058465,37.896356],"type":"Point"}
}