{
  "type": "Feature",
  "properties": {
    "iso:country":"US",
    "sg:address":"1494 Alice St",
    "sg:city":"Oakland",
    "sg:classifiers":[
        {
            "category":"Real Estate",
            "subcategory":"Real Estate Operator",
            "type":"Services"
        }
    ],
    "sg:phone":"+1 510 832 9448",
    "sg:postcode":"94612",
    "sg:province":"CA",
    "sg:tags":[
        "boarding",
        "house"
    ],
    "wof:name":"Maxwell Lodge",
    "wof:placetype":"venue"
},
  "geometry": {"coordinates":[-122.266458,37.802496],"type":"Point"}
}