{
  "type": "Feature",
  "properties": {
    "iso:country":"US",
    "sg:address":"42630 Tennessee Ave",
    "sg:city":"Palm Desert",
    "sg:classifiers":[
        {
            "category":"Professional",
            "subcategory":"Accounting & Tax Preparation",
            "type":"Services"
        }
    ],
    "sg:phone":"+1 760 360 3646",
    "sg:postcode":"92211",
    "sg:province":"CA",
    "sg:tags":[
        "accountant"
    ],
    "wof:name":"E K Williams & Co",
    "wof:placetype":"venue"
},
  "geometry": {"coordinates":[-116.327056,33.734202],"type":"Point"}
}