{
  "type": "Feature",
  "properties": {
    "addr:full":"9845 Horn Rd Sacramento CA 95827",
    "addr:postcode":"9845;95827",
    "addr:street":"Horn Rd",
    "iso:country":"US",
    "sg:address":"9845 Horn Rd",
    "sg:city":"Sacramento",
    "sg:classifiers":[
        {
            "category":"Restaurant",
            "type":"Food & Drink"
        }
    ],
    "sg:phone":"+1 916 857 0650",
    "sg:postcode":"95827",
    "sg:province":"CA",
    "sg:tags":[
        "pizza"
    ],
    "wof:name":"Mountain Mike's Pizza Corporate Office",
    "wof:placetype":"venue"
},
  "geometry": {"coordinates":[-121.32907899999999,38.574699],"type":"Point"}
}