{
  "type": "Feature",
  "properties": {
    "addr:full":"3421 N San Fernando Rd Los Angeles CA 90065",
    "addr:housenumber":"3421",
    "addr:postcode":"90065",
    "addr:street":"N San Fernando Rd",
    "iso:country":"US",
    "sg:address":"3421 N San Fernando Rd",
    "sg:city":"Los Angeles",
    "sg:classifiers":[
        {
            "category":"Manufacturing",
            "subcategory":"Glass & Minerals",
            "type":"Manufacturing & Wholesale Goods"
        }
    ],
    "sg:phone":"+1 323 257 7553",
    "sg:postcode":"90065",
    "sg:province":"CA",
    "sg:tags":[
        "tile"
    ],
    "sg:website":"www.daltile.com",
    "wof:name":"Dal-Tile",
    "wof:placetype":"venue"
},
  "geometry": {"coordinates":[-118.251036,34.120194],"type":"Point"}
}