{
  "type": "Feature",
  "properties": {
    "iso:country":"US",
    "sg:address":"601 Red Fir Ln",
    "sg:city":"Etna",
    "sg:classifiers":[
        {
            "category":"Building & Trades",
            "subcategory":"Construction",
            "type":"Services"
        }
    ],
    "sg:phone":"+1 530 467 5177",
    "sg:postcode":"96027",
    "sg:province":"CA",
    "sg:tags":[
        "contractor"
    ],
    "wof:name":"M T Construction",
    "wof:placetype":"venue"
},
  "geometry": {"coordinates":[-122.919771,41.522455],"type":"Point"}
}