{
  "type": "Feature",
  "properties": {
    "addr:full":"383 Rhode Island Street San Francisco CA 94103",
    "addr:housenumber":"383",
    "addr:postcode":"94103",
    "addr:street":"Rhode Island Street",
    "iso:country":"US",
    "sg:address":"383 Rhode Island Street",
    "sg:city":"San Francisco",
    "sg:classifiers":[
        {
            "category":"Real Estate",
            "subcategory":"Real Estate Services",
            "type":"Services"
        }
    ],
    "sg:phone":"+1 415 255 8888",
    "sg:postcode":"94103",
    "sg:province":"CA",
    "sg:tags":[
        "management",
        "property"
    ],
    "wof:name":"Wentworth Property Management",
    "wof:placetype":"venue"
},
  "geometry": {"coordinates":[-122.414652,37.77234],"type":"Point"}
}