{
  "type": "Feature",
  "properties": {
    "iso:country":"US",
    "sg:address":"3815 Marconi Ave",
    "sg:city":"Sacramento",
    "sg:classifiers":[
        {
            "category":"Real Estate",
            "subcategory":"Developer",
            "type":"Services"
        }
    ],
    "sg:phone":"+1 916 481 2600",
    "sg:postcode":"95821",
    "sg:province":"CA",
    "wof:name":"Crescendo Properties",
    "wof:placetype":"venue"
},
  "geometry": {"coordinates":[-121.375516,38.617782],"type":"Point"}
}