{
  "type": "Feature",
  "properties": {
    "addr:full":"13661 Victory Blvd Van Nuys CA 91401",
    "addr:housenumber":"13661",
    "addr:postcode":"91401",
    "addr:street":"Victory Blvd",
    "iso:country":"US",
    "sg:address":"13661 Victory Blvd",
    "sg:city":"Van Nuys",
    "sg:classifiers":[
        {
            "category":"Restaurant",
            "type":"Food & Drink"
        }
    ],
    "sg:menulink":"http://www.allmenus.com/ca/san-fernando-valley/88006-little-caesars-pizza/menu/",
    "sg:phone":"+1 818 989 2826",
    "sg:postcode":"91401",
    "sg:province":"CA",
    "sg:tags":[
        "american",
        "pizza"
    ],
    "wof:name":"Little Caesar's Pizza",
    "wof:placetype":"venue"
},
  "geometry": {"coordinates":[-118.43091800000001,34.186671],"type":"Point"}
}