{
  "type": "Feature",
  "properties": {
    "addr:full":"7507 Monterey St Gilroy CA 95020",
    "addr:housenumber":"7507",
    "addr:postcode":"95020",
    "addr:street":"Monterey St",
    "iso:country":"US",
    "sg:address":"7507 Monterey St",
    "sg:city":"Gilroy",
    "sg:classifiers":[
        {
            "category":"Shopping",
            "subcategory":"Used Merchandise",
            "type":"Retail Goods"
        }
    ],
    "sg:phone":"+1 408 848 3788",
    "sg:postcode":"95020",
    "sg:province":"CA",
    "wof:name":"Monterey Street Antiques",
    "wof:placetype":"venue"
},
  "geometry": {"coordinates":[-121.57004000000001,37.00962],"type":"Point"}
}