{
  "type": "Feature",
  "properties": {
    "iso:country":"US",
    "sg:address":"1249 W Gardena Blvd",
    "sg:city":"Gardena",
    "sg:classifiers":[
        {
            "category":"Health Services",
            "subcategory":"Doctor",
            "type":"Services"
        }
    ],
    "sg:phone":"+1 310 538 0400",
    "sg:postcode":"90247",
    "sg:province":"CA",
    "sg:tags":[
        "clinic"
    ],
    "wof:name":"Gardena Medical Clinic",
    "wof:placetype":"venue"
},
  "geometry": {"coordinates":[-118.296527,33.881521],"type":"Point"}
}