{
  "type": "Feature",
  "properties": {
    "addr:full":"15025 Palmdale Rd Victorville CA 92392",
    "addr:postcode":"15025;92392",
    "addr:street":"Palmdale Rd",
    "iso:country":"US",
    "sg:address":"15025 Palmdale Rd",
    "sg:city":"Victorville",
    "sg:classifiers":[
        {
            "category":"Autos & Motor Vehicles",
            "subcategory":"Auto Supplies",
            "type":"Retail Goods"
        },
        {
            "category":"Retail",
            "subcategory":"Auto Repair",
            "type":"Services"
        }
    ],
    "sg:phone":"+1 760 952 1258",
    "sg:postcode":"92392",
    "sg:province":"CA",
    "sg:tags":[
        "recap",
        "balancing",
        "retread",
        "tire",
        "wheels-aligning"
    ],
    "wof:name":"Big Paul's Used Tires",
    "wof:placetype":"venue"
},
  "geometry": {"coordinates":[-117.335994,34.506811],"type":"Point"}
}