{
  "type": "Feature",
  "properties": {
    "addr:full":"12610 S Western Avenue Los Angeles CA 90047",
    "addr:housenumber":"12610",
    "addr:postcode":"90047",
    "addr:street":"S Western Avenue",
    "iso:country":"US",
    "sg:address":"12610 S Western Avenue",
    "sg:city":"Los Angeles",
    "sg:classifiers":[
        {
            "category":"Health Services",
            "subcategory":"Doctor",
            "type":"Services"
        }
    ],
    "sg:phone":"+1 323 757 1853",
    "sg:postcode":"90047",
    "sg:province":"CA",
    "sg:tags":[
        "medicine",
        "practice",
        "internal",
        "family"
    ],
    "wof:name":"Chu Jae S MD",
    "wof:placetype":"venue"
},
  "geometry": {"coordinates":[-118.30919299999999,33.918],"type":"Point"}
}