{
  "type": "Feature",
  "properties": {
    "iso:country":"US",
    "sg:address":"808 S Vermont Ave",
    "sg:city":"Los Angeles",
    "sg:classifiers":[
        {
            "category":"Wholesale",
            "subcategory":"Toys & Hobbies",
            "type":"Manufacturing & Wholesale Goods"
        }
    ],
    "sg:phone":"+1 213 382 4051",
    "sg:postcode":"90005",
    "sg:province":"CA",
    "sg:tags":[
        "wholesaler"
    ],
    "wof:name":"New Gold Coast Corp",
    "wof:placetype":"venue"
},
  "geometry": {"coordinates":[-118.291549,34.056958],"type":"Point"}
}