{
  "type": "Feature",
  "properties": {
    "iso:country":"US",
    "sg:address":"15 Quail Ln",
    "sg:city":"Watsonville",
    "sg:classifiers":[
        {
            "category":"Shopping",
            "subcategory":"Jewelry",
            "type":"Retail Goods"
        }
    ],
    "sg:phone":"+1 831 768 0259",
    "sg:postcode":"95076",
    "sg:province":"CA",
    "sg:tags":[
        "jeweler"
    ],
    "wof:name":"Pearl Restringing By Estelle",
    "wof:placetype":"venue"
},
  "geometry": {"coordinates":[-121.821099,36.970171],"type":"Point"}
}