{
  "type": "Feature",
  "properties": {
    "iso:country":"US",
    "sg:address":"4200 Mother Lode Dr",
    "sg:city":"Shingle Springs",
    "sg:classifiers":[
        {
            "category":"Health Services",
            "subcategory":"Doctor",
            "type":"Services"
        }
    ],
    "sg:phone":"+1 530 672 1616",
    "sg:postcode":"95682",
    "sg:province":"CA",
    "sg:tags":[
        "dentist"
    ],
    "wof:name":"Richard J Sommerdyke Inc",
    "wof:placetype":"venue"
},
  "geometry": {"coordinates":[-120.926555,38.665625],"type":"Point"}
}