{
  "type": "Feature",
  "properties": {
    "addr:full":"13351 South St Cerritos CA 90703",
    "addr:housenumber":"13351",
    "addr:postcode":"ca 90703",
    "addr:street":"South St",
    "iso:country":"US",
    "sg:address":"13351 South St",
    "sg:city":"Cerritos",
    "sg:classifiers":[
        {
            "category":"Restaurant",
            "type":"Food & Drink"
        }
    ],
    "sg:phone":"+1 562 809 4112",
    "sg:postcode":"90703",
    "sg:province":"CA",
    "wof:name":"China Express",
    "wof:placetype":"venue"
},
  "geometry": {"coordinates":[-118.04696,33.85875],"type":"Point"}
}