{
  "type": "Feature",
  "properties": {
    "iso:country":"US",
    "sg:address":"37215 Dondero Way",
    "sg:city":"Fremont",
    "sg:classifiers":[
        {
            "category":"Taxi",
            "type":"Transportation"
        }
    ],
    "sg:phone":"+1 510 793 2181",
    "sg:postcode":"94536",
    "sg:province":"CA",
    "sg:tags":[
        "delivery"
    ],
    "wof:name":"Humberto Contreras Delivery",
    "wof:placetype":"venue"
},
  "geometry": {"coordinates":[-122.01774399999999,37.548105],"type":"Point"}
}