{
  "type": "Feature",
  "properties": {
    "addr:full":"334 S Patterson Ave Santa Barbara CA 93111",
    "addr:housenumber":"334",
    "addr:postcode":"93111",
    "addr:street":"S Patterson Ave",
    "iso:country":"US",
    "sg:address":"334 S Patterson Ave",
    "sg:city":"Santa Barbara",
    "sg:classifiers":[
        {
            "category":"Health Services",
            "subcategory":"Medical Lab",
            "type":"Services"
        }
    ],
    "sg:phone":"+1 805 964 4550",
    "sg:postcode":"93111",
    "sg:province":"CA",
    "sg:tags":[
        "laboratory"
    ],
    "wof:name":"Santa Barbara Pathlogy Lbrtry",
    "wof:placetype":"venue"
},
  "geometry": {"coordinates":[-119.81054399999999,34.431926],"type":"Point"}
}