{
  "type": "Feature",
  "properties": {
    "addr:full":"2560 9th St Berkeley CA 94710",
    "addr:housenumber":"2560",
    "addr:postcode":"94710",
    "addr:street":"9Th St",
    "iso:country":"US",
    "sg:address":"2560 9th St",
    "sg:city":"Berkeley",
    "sg:classifiers":[
        {
            "category":"Organizations",
            "subcategory":"Professional Association",
            "type":"Services"
        }
    ],
    "sg:phone":"+1 510 528 8649",
    "sg:postcode":"94710",
    "sg:province":"CA",
    "wof:name":"Usenix Association",
    "wof:placetype":"venue"
},
  "geometry": {"coordinates":[-122.291726,37.86013],"type":"Point"}
}