{
  "type": "Feature",
  "properties": {
    "iso:country":"US",
    "sg:address":"120 Churchill Rd",
    "sg:city":"Hollister",
    "sg:classifiers":[
        {
            "category":"Building & Trades",
            "subcategory":"Landscaping Services",
            "type":"Services"
        }
    ],
    "sg:phone":"+1 831 637 1700",
    "sg:postcode":"95023",
    "sg:province":"CA",
    "sg:tags":[
        "landscape"
    ],
    "wof:name":"Landscape Design By Rosemary B",
    "wof:placetype":"venue"
},
  "geometry": {"coordinates":[-121.378379,36.925053],"type":"Point"}
}