{
  "type": "Feature",
  "properties": {
    "addr:full":"358 Los Encinos Ct San Jose CA 95134",
    "addr:housenumber":"358",
    "addr:postcode":"95134",
    "addr:street":"Los Encinos Ct",
    "iso:country":"US",
    "sg:address":"358 Los Encinos Ct",
    "sg:city":"San Jose",
    "sg:classifiers":[
        {
            "category":"Professional",
            "subcategory":"Computer Services",
            "type":"Services"
        }
    ],
    "sg:phone":"+1 408 254 2557",
    "sg:postcode":"95134",
    "sg:province":"CA",
    "sg:tags":[
        "repair"
    ],
    "wof:name":"NSC",
    "wof:placetype":"venue"
},
  "geometry": {"coordinates":[-121.945797,37.417129],"type":"Point"}
}