{
  "type": "Feature",
  "properties": {
    "iso:country":"US",
    "sg:address":"18118 Rd 26",
    "sg:city":"Madera",
    "sg:classifiers":[
        {
            "category":"Arts & Performance",
            "subcategory":"Theater",
            "type":"Entertainment"
        }
    ],
    "sg:phone":"+1 559 661 2176",
    "sg:postcode":"93638",
    "sg:province":"CA",
    "sg:tags":[
        "live",
        "music"
    ],
    "wof:name":"Music Man Entertainment",
    "wof:placetype":"venue"
},
  "geometry": {"coordinates":[-120.07441,37.012778],"type":"Point"}
}