{
  "type": "Feature",
  "properties": {
    "iso:country":"US",
    "sg:address":"935 Poplar St",
    "sg:city":"Chico",
    "sg:classifiers":[
        {
            "category":"Shopping",
            "subcategory":"Used Merchandise",
            "type":"Retail Goods"
        }
    ],
    "sg:phone":"+1 530 345 8016",
    "sg:postcode":"95928",
    "sg:province":"CA",
    "wof:name":"Lost In Time Antiques",
    "wof:placetype":"venue"
},
  "geometry": {"coordinates":[-121.82781199999999,39.729463],"type":"Point"}
}