{
  "type": "Feature",
  "properties": {
    "addr:full":"71 Stevenson St 22nd Fl San Francisco CA 94105",
    "addr:housenumber":"71",
    "addr:postcode":"94105",
    "addr:street":"Stevenson St;Fl",
    "iso:country":"US",
    "sg:address":"71 Stevenson St 22nd Fl",
    "sg:city":"San Francisco",
    "sg:classifiers":[
        {
            "category":"Shopping",
            "subcategory":"Beauty & Cosmetics",
            "type":"Retail Goods"
        }
    ],
    "sg:phone":"+1 415 489 5000",
    "sg:postcode":"94105",
    "sg:province":"CA",
    "sg:tags":[
        "supply"
    ],
    "sg:website":"www.bareescentuals.com",
    "wof:name":"Bare Escentuals",
    "wof:placetype":"venue"
},
  "geometry": {"coordinates":[-122.400043,37.789461],"type":"Point"}
}