{
  "type": "Feature",
  "properties": {
    "iso:country":"US",
    "sg:address":"6513 Ranchito Ave",
    "sg:city":"Van Nuys",
    "sg:classifiers":[
        {
            "category":"Professional",
            "subcategory":"Management & Consulting",
            "type":"Services"
        }
    ],
    "sg:phone":"+1 818 788 1428",
    "sg:postcode":"91401",
    "sg:province":"CA",
    "sg:tags":[
        "retail",
        "direct",
        "sales"
    ],
    "wof:name":"Sweet N Kynd Foods",
    "wof:placetype":"venue"
},
  "geometry": {"coordinates":[-118.435692,34.188979],"type":"Point"}
}