{
  "type": "Feature",
  "properties": {
    "iso:country":"US",
    "sg:address":"5006 Sunrise Blvd",
    "sg:city":"Fair Oaks",
    "sg:classifiers":[
        {
            "category":"Real Estate",
            "subcategory":"Real Estate Services",
            "type":"Services"
        }
    ],
    "sg:phone":"+1 916 962 2119",
    "sg:postcode":"95628",
    "sg:province":"CA",
    "sg:tags":[
        "company",
        "title"
    ],
    "sg:website":"www.landamerica.com",
    "wof:name":"Land America Commonwealth",
    "wof:placetype":"venue"
},
  "geometry": {"coordinates":[-121.272372,38.655505],"type":"Point"}
}