{
  "type": "Feature",
  "properties": {
    "addr:full":"1525 N Beale Rd Marysville CA 95901",
    "addr:housenumber":"1525",
    "addr:postcode":"95901",
    "addr:street":"N Beale Rd",
    "iso:country":"US",
    "sg:address":"1525 N Beale Rd",
    "sg:city":"Marysville",
    "sg:classifiers":[
        {
            "category":"Real Estate",
            "subcategory":"Real Estate Operator",
            "type":"Services"
        }
    ],
    "sg:phone":"+1 530 743 8825",
    "sg:postcode":"95901",
    "sg:province":"CA",
    "sg:tags":[
        "apartment"
    ],
    "wof:name":"Beale Star Apartments",
    "wof:placetype":"venue"
},
  "geometry": {"coordinates":[-121.563474,39.127318],"type":"Point"}
}