{
  "type": "Feature",
  "properties": {
    "iso:country":"US",
    "sg:address":"2046 Orange St",
    "sg:city":"Rosamond",
    "sg:classifiers":[
        {
            "category":"Shopping",
            "subcategory":"Gifts & Souvenirs",
            "type":"Retail Goods"
        }
    ],
    "sg:phone":"+1 661 256 3935",
    "sg:postcode":"93560",
    "sg:province":"CA",
    "sg:tags":[
        "shop"
    ],
    "wof:name":"Exciting World Of Embroidery",
    "wof:placetype":"venue"
},
  "geometry": {"coordinates":[-118.167887,34.857037],"type":"Point"}
}