{
  "type": "Feature",
  "properties": {
    "iso:country":"US",
    "sg:address":"29231 Heathercliff Rd",
    "sg:city":"Malibu",
    "sg:classifiers":[
        {
            "category":"Communications",
            "type":"Services"
        }
    ],
    "sg:phone":"+1 310 457 5580",
    "sg:postcode":"90265",
    "sg:province":"CA",
    "sg:tags":[
        "communication"
    ],
    "wof:name":"Behr Communications",
    "wof:placetype":"venue"
},
  "geometry": {"coordinates":[-118.80978899999999,34.02029],"type":"Point"}
}