{
  "type": "Feature",
  "properties": {
    "addr:full":"15477 Ventura Blvd Sherman Oaks CA 91403",
    "addr:housenumber":"15477",
    "addr:postcode":"91403",
    "addr:street":"Ventura Blvd",
    "iso:country":"US",
    "sg:address":"15477 Ventura Blvd",
    "sg:city":"Sherman Oaks",
    "sg:classifiers":[
        {
            "category":"Real Estate",
            "subcategory":"Real Estate Agent",
            "type":"Services"
        }
    ],
    "sg:phone":"+1 818 817 9800",
    "sg:postcode":"91403",
    "sg:province":"CA",
    "wof:name":"Era Winners Group",
    "wof:placetype":"venue"
},
  "geometry": {"coordinates":[-118.469983,34.154441],"type":"Point"}
}