{
  "type": "Feature",
  "properties": {
    "iso:country":"US",
    "sg:address":"11154 Whittier Blvd",
    "sg:city":"Whittier",
    "sg:classifiers":[
        {
            "category":"Personal",
            "subcategory":"Beauty Salon",
            "type":"Services"
        }
    ],
    "sg:phone":"+1 562 695 4519",
    "sg:postcode":"90606",
    "sg:province":"CA",
    "sg:tags":[
        "hair"
    ],
    "wof:name":"Daisy's Beauty Salon",
    "wof:placetype":"venue"
},
  "geometry": {"coordinates":[-118.059998,33.986698],"type":"Point"}
}