{
  "type": "Feature",
  "properties": {
    "addr:full":"113 Ferrari Ranch Rd Lincoln CA 95648",
    "addr:housenumber":"113",
    "addr:postcode":"95648",
    "addr:street":"Ferrari Ranch Rd",
    "iso:country":"US",
    "sg:address":"113 Ferrari Ranch Rd",
    "sg:city":"Lincoln",
    "sg:classifiers":[
        {
            "category":"Shopping",
            "subcategory":"Department Store",
            "type":"Retail Goods"
        },
        {
            "category":"Shopping",
            "subcategory":"Clothing, Apparel, & Fashions",
            "type":"Retail Goods"
        },
        {
            "category":"Shopping",
            "subcategory":"Shoes",
            "type":"Retail Goods"
        }
    ],
    "sg:phone":"+1 916 409 9980",
    "sg:postcode":"95648",
    "sg:province":"CA",
    "sg:tags":[
        "clothing"
    ],
    "sg:website":"http://www.rossstores.com",
    "wof:name":"Ross Dress For Less",
    "wof:placetype":"venue"
},
  "geometry": {"coordinates":[-121.30394200000001,38.873804],"type":"Point"}
}