{
  "type": "Feature",
  "properties": {
    "addr:full":"3375 Scott Boulevard Suite 434 Santa Clara CA 95054",
    "addr:housenumber":"3375",
    "addr:postcode":"95054",
    "addr:street":"Scott Boulevard Suite 434",
    "iso:country":"US",
    "sg:address":"3375 Scott Boulevard Suite 434",
    "sg:city":"Santa Clara",
    "sg:classifiers":[
        {
            "category":"Professional",
            "subcategory":"Accounting & Tax Preparation",
            "type":"Services"
        }
    ],
    "sg:phone":"+1 408 980 8194",
    "sg:postcode":"95054",
    "sg:province":"CA",
    "sg:tags":[
        "accountant"
    ],
    "wof:name":"Boncyk Accountancy Corporation",
    "wof:placetype":"venue"
},
  "geometry": {"coordinates":[-121.98491,37.380621],"type":"Point"}
}