{
  "type": "Feature",
  "properties": {
    "iso:country":"US",
    "sg:address":"155 W Birch St",
    "sg:city":"Brea",
    "sg:classifiers":[
        {
            "category":"Cinema",
            "subcategory":"Movie Theater",
            "type":"Entertainment"
        }
    ],
    "sg:phone":"+1 714 672 1000",
    "sg:postcode":"92821",
    "sg:province":"CA",
    "sg:tags":[
        "motion",
        "picture"
    ],
    "wof:name":"Brea Stadium East 12",
    "wof:placetype":"venue"
},
  "geometry": {"coordinates":[-117.900015,33.918608],"type":"Point"}
}