{
  "type": "Feature",
  "properties": {
    "addr:full":"158 Northgate Dr Manteca CA 95336",
    "addr:housenumber":"158",
    "addr:postcode":"95336",
    "addr:street":"Northgate Dr",
    "iso:country":"US",
    "sg:address":"158 Northgate Dr",
    "sg:city":"Manteca",
    "sg:classifiers":[
        {
            "category":"Personal",
            "subcategory":"Barber",
            "type":"Services"
        }
    ],
    "sg:phone":"+1 209 825 9116",
    "sg:postcode":"95336",
    "sg:province":"CA",
    "wof:name":"Family Barber Shop",
    "wof:placetype":"venue"
},
  "geometry": {"coordinates":[-121.220082,37.818996],"type":"Point"}
}