{
  "type": "Feature",
  "properties": {
    "addr:full":"12988 Carmel Creek Road San Diego CA 92130",
    "addr:housenumber":"12988",
    "addr:postcode":"92130",
    "addr:street":"Carmel Creek Road",
    "iso:country":"US",
    "sg:address":"12988 Carmel Creek Road",
    "sg:city":"San Diego",
    "sg:classifiers":[
        {
            "category":"Building & Trades",
            "subcategory":"Construction",
            "type":"Services"
        }
    ],
    "sg:phone":"+1 858 350 8008",
    "sg:postcode":"92130",
    "sg:province":"CA",
    "sg:tags":[
        "contractor"
    ],
    "wof:name":"Ortiz John W Building Repair and Associates",
    "wof:placetype":"venue"
},
  "geometry": {"coordinates":[-117.226888,32.952671],"type":"Point"}
}