{
  "type": "Feature",
  "properties": {
    "addr:full":"4592 Appian Way El Sobrante CA 94803",
    "addr:housenumber":"4592",
    "addr:postcode":"94803",
    "addr:street":"Appian Way",
    "iso:country":"US",
    "sg:address":"4592 Appian Way",
    "sg:city":"El Sobrante",
    "sg:classifiers":[
        {
            "category":"Education",
            "subcategory":"Dance Studio",
            "type":"Public Place"
        }
    ],
    "sg:phone":"+1 510 223 3262",
    "sg:postcode":"94803",
    "sg:province":"CA",
    "sg:tags":[
        "instruction",
        "dancing"
    ],
    "wof:name":"Sherrie's Dance Studio",
    "wof:placetype":"venue"
},
  "geometry": {"coordinates":[-122.30429100000001,37.97193],"type":"Point"}
}