{
  "type": "Feature",
  "properties": {
    "iso:country":"US",
    "sg:address":"4592 Appian Way",
    "sg:city":"El Sobrante",
    "sg:classifiers":[
        {
            "category":"Education",
            "subcategory":"Dance Studio",
            "type":"Public Place"
        }
    ],
    "sg:phone":"+1 510 223 3262",
    "sg:postcode":"94803",
    "sg:province":"CA",
    "sg:tags":[
        "instruction",
        "dancing"
    ],
    "wof:name":"Sherrie's Dance Studio",
    "wof:placetype":"venue"
},
  "geometry": {"coordinates":[-122.304291,37.97193],"type":"Point"}
}