{
  "type": "Feature",
  "properties": {
    "iso:country":"US",
    "sg:address":"1322 2nd St",
    "sg:city":"Santa Monica",
    "sg:classifiers":[
        {
            "category":"Professional",
            "subcategory":"Advertising",
            "type":"Services"
        }
    ],
    "sg:phone":"+1 310 656 9103",
    "sg:postcode":"90401",
    "sg:province":"CA",
    "sg:tags":[
        "counselor"
    ],
    "wof:name":"Streamlined Advertising",
    "wof:placetype":"venue"
},
  "geometry": {"coordinates":[-118.497404,34.015141],"type":"Point"}
}