{
  "type": "Feature",
  "properties": {
    "addr:full":"1580 Winchester Blvd Ste 205 Campbell CA 95008",
    "addr:housenumber":"1580",
    "addr:postcode":"95008",
    "addr:street":"Winchester Blvd Ste 205",
    "iso:country":"US",
    "sg:address":"1580 Winchester Blvd Ste 205",
    "sg:city":"Campbell",
    "sg:classifiers":[
        {
            "category":"Health Services",
            "subcategory":"Dentist",
            "type":"Services"
        }
    ],
    "sg:phone":"+1 408 374 1973",
    "sg:postcode":"95008",
    "sg:province":"CA",
    "wof:name":"Foulk Donald M DDS Inc",
    "wof:placetype":"venue"
},
  "geometry": {"coordinates":[-121.949997,37.295101],"type":"Point"}
}