{
  "type": "Feature",
  "properties": {
    "iso:country":"US",
    "sg:address":"23801 Calabasas Rd",
    "sg:city":"Calabasas",
    "sg:classifiers":[
        {
            "category":"Professional",
            "subcategory":"Research",
            "type":"Services"
        }
    ],
    "sg:phone":"+1 818 591 2408",
    "sg:postcode":"91302",
    "sg:province":"CA",
    "sg:tags":[
        "analysis",
        "market"
    ],
    "sg:website":"http://www.davisresearch.com",
    "wof:name":"Davis Market Research",
    "wof:placetype":"venue"
},
  "geometry": {"coordinates":[-118.64525500000001,34.155035],"type":"Point"}
}