{
  "type": "Feature",
  "properties": {
    "iso:country":"US",
    "sg:address":"5657 Wilshire Blvd",
    "sg:city":"Los Angeles",
    "sg:classifiers":[
        {
            "category":"Education",
            "subcategory":"Special Training",
            "type":"Public Place"
        }
    ],
    "sg:phone":"+1 323 931 9245",
    "sg:postcode":"90036",
    "sg:province":"CA",
    "sg:tags":[
        "dramatic",
        "instruction"
    ],
    "wof:name":"Eric Morris Actors Workshop",
    "wof:placetype":"venue"
},
  "geometry": {"coordinates":[-118.35247200000001,34.062412],"type":"Point"}
}