{
  "type": "Feature",
  "properties": {
    "addr:full":"8 Admiral Dr Emeryville CA 94608",
    "addr:housenumber":"8",
    "addr:postcode":"94608",
    "addr:street":"Admiral Dr",
    "iso:country":"US",
    "sg:address":"8 Admiral Dr",
    "sg:city":"Emeryville",
    "sg:classifiers":[
        {
            "category":"Real Estate",
            "subcategory":"Real Estate Agent",
            "type":"Services"
        }
    ],
    "sg:phone":"+1 415 469 9900",
    "sg:postcode":"94608",
    "sg:province":"CA",
    "wof:name":"New California Investment Corp",
    "wof:placetype":"venue"
},
  "geometry": {"coordinates":[-122.30383999999999,37.839187],"type":"Point"}
}