{
  "type": "Feature",
  "properties": {
    "addr:full":"216 Fern St Santa Cruz CA 95060",
    "addr:housenumber":"216",
    "addr:postcode":"95060",
    "addr:street":"Fern St",
    "iso:country":"US",
    "sg:address":"216 Fern St",
    "sg:city":"Santa Cruz",
    "sg:classifiers":[
        {
            "category":"Professional",
            "subcategory":"Art Services",
            "type":"Services"
        }
    ],
    "sg:phone":"+1 831 423 8786",
    "sg:postcode":"95060",
    "sg:province":"CA",
    "sg:tags":[
        "photographer"
    ],
    "wof:name":"Paul Titangos Photography",
    "wof:placetype":"venue"
},
  "geometry": {"coordinates":[-122.03209200000001,36.9859],"type":"Point"}
}