{
  "type": "Feature",
  "properties": {
    "iso:country":"US",
    "sg:address":"20685 Tumeric Way",
    "sg:city":"Jamul",
    "sg:classifiers":[
        {
            "category":"Recreation",
            "subcategory":"Campground",
            "type":"Entertainment"
        }
    ],
    "sg:phone":"+1 619 468 3951",
    "sg:postcode":"91935",
    "sg:province":"CA",
    "sg:tags":[
        "recreational",
        "park",
        "vehicle"
    ],
    "wof:name":"Ohms R V Ranch",
    "wof:placetype":"venue"
},
  "geometry": {"coordinates":[-116.704491,32.675789],"type":"Point"}
}