{
  "type": "Feature",
  "properties": {
    "iso:country":"US",
    "sg:address":"4204 San Juan Ave",
    "sg:city":"Fair Oaks",
    "sg:classifiers":[
        {
            "category":"Autos & Motor Vehicles",
            "subcategory":"Automobile Sales",
            "type":"Retail Goods"
        }
    ],
    "sg:phone":"+1 916 213 5777",
    "sg:postcode":"95628",
    "sg:province":"CA",
    "sg:tags":[
        "used"
    ],
    "wof:name":"A-1 Cars & Truck",
    "wof:placetype":"venue"
},
  "geometry": {"coordinates":[-121.291883,38.639245],"type":"Point"}
}