{
  "type": "Feature",
  "properties": {
    "iso:country":"US",
    "sg:address":"21720 S Vermont Ave",
    "sg:city":"Torrance",
    "sg:classifiers":[
        {
            "category":"Utilities",
            "subcategory":"Mobile Phone",
            "type":"Services"
        }
    ],
    "sg:phone":"+1 310 320 2727",
    "sg:postcode":"90502",
    "sg:province":"CA",
    "sg:tags":[
        "telephone",
        "cellular"
    ],
    "wof:name":"All Wireless",
    "wof:placetype":"venue"
},
  "geometry": {"coordinates":[-118.290212,33.830297],"type":"Point"}
}