{
  "type": "Feature",
  "properties": {
    "addr:full":"12704 Milton St Los Angeles CA 90066",
    "addr:housenumber":"12704",
    "addr:postcode":"90066",
    "addr:street":"Milton St",
    "iso:country":"US",
    "sg:address":"12704 Milton St",
    "sg:city":"Los Angeles",
    "sg:classifiers":[
        {
            "category":"Real Estate",
            "subcategory":"Real Estate Agent",
            "type":"Services"
        }
    ],
    "sg:phone":"+1 310 821 7422",
    "sg:postcode":"90066",
    "sg:province":"CA",
    "wof:name":"Dennis Blunk",
    "wof:placetype":"venue"
},
  "geometry": {"coordinates":[-118.423131,33.982576],"type":"Point"}
}