{
  "type": "Feature",
  "properties": {
    "addr:full":"8332 Greenleaf Ave Whittier CA 90602",
    "addr:housenumber":"8332",
    "addr:postcode":"90602",
    "addr:street":"Greenleaf Ave",
    "iso:country":"US",
    "sg:address":"8332 Greenleaf Ave",
    "sg:city":"Whittier",
    "sg:classifiers":[
        {
            "category":"Travel",
            "subcategory":"Campground",
            "type":"Entertainment"
        }
    ],
    "sg:phone":"+1 562 945 1999",
    "sg:postcode":"90602",
    "sg:province":"CA",
    "sg:tags":[
        "camp"
    ],
    "wof:name":"Camping Around For Persons",
    "wof:placetype":"venue"
},
  "geometry": {"coordinates":[-118.03877300000001,33.963927],"type":"Point"}
}