{
  "type": "Feature",
  "properties": {
    "iso:country":"US",
    "sg:address":"8363 Foothill Blvd",
    "sg:city":"Rancho Cucamonga",
    "sg:classifiers":[
        {
            "category":"Wholesale",
            "subcategory":"Machinery & Supplies",
            "type":"Manufacturing & Wholesale Goods"
        }
    ],
    "sg:phone":"+1 909 579 8229",
    "sg:postcode":"91730",
    "sg:province":"CA",
    "sg:tags":[
        "equipment",
        "industrial"
    ],
    "wof:name":"Peek-A-Boo Ultrasound",
    "wof:placetype":"venue"
},
  "geometry": {"coordinates":[-117.62034300000001,34.104754],"type":"Point"}
}