{
  "type": "Feature",
  "properties": {
    "iso:country":"US",
    "sg:address":"6800 Co Rd 19",
    "sg:city":"Orland",
    "sg:classifiers":[
        {
            "category":"Farming",
            "subcategory":"Crops",
            "type":"Manufacturing & Wholesale Goods"
        }
    ],
    "sg:phone":"+1 530 865 3212",
    "sg:postcode":"95963",
    "sg:province":"CA",
    "sg:tags":[
        "farm"
    ],
    "wof:name":"Luther Sharpsteen",
    "wof:placetype":"venue"
},
  "geometry": {"coordinates":[-122.16541,39.728991],"type":"Point"}
}