{
  "type": "Feature",
  "properties": {
    "addr:full":"1183 Bille Rd Paradise CA 95969",
    "addr:housenumber":"1183",
    "addr:postcode":"95969",
    "addr:street":"Bille Rd",
    "iso:country":"US",
    "sg:address":"1183 Bille Rd",
    "sg:city":"Paradise",
    "sg:classifiers":[
        {
            "category":"Manufacturing",
            "subcategory":"Food",
            "type":"Manufacturing & Wholesale Goods"
        }
    ],
    "sg:phone":"+1 530 872 9167",
    "sg:postcode":"95969",
    "sg:province":"CA",
    "sg:tags":[
        "mfg"
    ],
    "wof:name":"Joy-Lyns Candies Inc",
    "wof:placetype":"venue"
},
  "geometry": {"coordinates":[-121.60373800000001,39.77047],"type":"Point"}
}