{
  "type": "Feature",
  "properties": {
    "addr:full":"1511 Clement Street San Francisco CA 94118",
    "addr:housenumber":"1511",
    "addr:postcode":"94118",
    "addr:street":"Clement Street",
    "iso:country":"US",
    "sg:address":"1511 Clement Street",
    "sg:city":"San Francisco",
    "sg:classifiers":[
        {
            "category":"Health Services",
            "subcategory":"Doctor",
            "type":"Services"
        }
    ],
    "sg:phone":"+1 415 387 5556",
    "sg:postcode":"94118",
    "sg:province":"CA",
    "sg:tags":[
        "podiatrist"
    ],
    "wof:name":"Todd William R DPM",
    "wof:placetype":"venue"
},
  "geometry": {"coordinates":[-122.475998,37.782299],"type":"Point"}
}