{
  "type": "Feature",
  "properties": {
    "addr:full":"9144 Deering Ave Chatsworth CA 91311",
    "addr:housenumber":"9144",
    "addr:postcode":"91311",
    "addr:street":"Deering Ave",
    "iso:country":"US",
    "sg:address":"9144 Deering Ave",
    "sg:city":"Chatsworth",
    "sg:classifiers":[
        {
            "category":"Sports & Exercise",
            "subcategory":"Athletic Track",
            "type":"Entertainment"
        }
    ],
    "sg:phone":"+1 818 882 3073",
    "sg:postcode":"91311",
    "sg:province":"CA",
    "sg:tags":[
        "tape",
        "discs-wholesale",
        "video",
        "manufacturer"
    ],
    "wof:name":"Sin City Entertainment",
    "wof:placetype":"venue"
},
  "geometry": {"coordinates":[-118.596092,34.236532],"type":"Point"}
}