{
  "type": "Feature",
  "properties": {
    "iso:country":"US",
    "sg:address":"1504 Franklin St Ste 102",
    "sg:city":"Oakland",
    "sg:classifiers":[
        {
            "category":"Professional",
            "subcategory":"Detective & Security Services",
            "type":"Services"
        }
    ],
    "sg:phone":"+1 510 663 8600",
    "sg:postcode":"94612",
    "sg:province":"CA",
    "sg:tags":[
        "control",
        "monitoring",
        "consultant",
        "system",
        "equipment"
    ],
    "sg:website":"http://www.operationdignity.org",
    "wof:name":"Robot Genius Inc",
    "wof:placetype":"venue"
},
  "geometry": {"coordinates":[-122.269346,37.804837],"type":"Point"}
}