{
  "type": "Feature",
  "properties": {
    "addr:full":"14676 Pipeline Ave Chino Hills CA 91709",
    "addr:housenumber":"14676",
    "addr:postcode":"91709",
    "addr:street":"Pipeline Ave",
    "iso:country":"US",
    "sg:address":"14676 Pipeline Ave",
    "sg:city":"Chino Hills",
    "sg:classifiers":[
        {
            "category":"Restaurant",
            "type":"Food & Drink"
        }
    ],
    "sg:menulink":"http://www.allmenus.com/ca/ontario/87723-little-caesars-pizza/menu/",
    "sg:phone":"+1 909 393 8088",
    "sg:postcode":"91709",
    "sg:province":"CA",
    "sg:tags":[
        "american",
        "pizza"
    ],
    "wof:name":"Little Caesar's Pizza",
    "wof:placetype":"venue"
},
  "geometry": {"coordinates":[-117.715155,33.986025],"type":"Point"}
}