{
  "type": "Feature",
  "properties": {
    "iso:country":"US",
    "sg:address":"1050 Franklin St",
    "sg:city":"San Francisco",
    "sg:classifiers":[
        {
            "category":"Organizations",
            "subcategory":"Religious Organization",
            "type":"Services"
        }
    ],
    "sg:phone":"+1 415 861 4809",
    "sg:postcode":"94109",
    "sg:province":"CA",
    "sg:tags":[
        "church"
    ],
    "wof:name":"Sacred Heart Society",
    "wof:placetype":"venue"
},
  "geometry": {"coordinates":[-122.422742,37.784423],"type":"Point"}
}