{
  "type": "Feature",
  "properties": {
    "iso:country":"US",
    "sg:address":"15700 S Avalon Blvd",
    "sg:city":"Compton",
    "sg:classifiers":[
        {
            "category":"Home & Garden",
            "subcategory":"Home Furnishings",
            "type":"Retail Goods"
        }
    ],
    "sg:phone":"+1 213 725 4528",
    "sg:postcode":"90220",
    "sg:province":"CA",
    "sg:tags":[
        "mirror"
    ],
    "sg:website":"http://www.headwestinc.com/outlet.html",
    "wof:name":"Head West Factory Outlet Store",
    "wof:placetype":"venue"
},
  "geometry": {"coordinates":[-118.265288,33.888755],"type":"Point"}
}