{
  "type": "Feature",
  "properties": {
    "iso:country":"US",
    "sg:address":"1331 Deloach Ct",
    "sg:city":"San Jose",
    "sg:classifiers":[
        {
            "category":"Travel",
            "subcategory":"Travel Agent",
            "type":"Entertainment"
        }
    ],
    "sg:phone":"+1 408 559 4414",
    "sg:postcode":"95125",
    "sg:province":"CA",
    "sg:tags":[
        "agency"
    ],
    "wof:name":"Way To Go Travel",
    "wof:placetype":"venue"
},
  "geometry": {"coordinates":[-121.926873,37.298471],"type":"Point"}
}