{
  "type": "Feature",
  "properties": {
    "iso:country":"US",
    "sg:address":"4211 Barrymore Dr",
    "sg:city":"San Jose",
    "sg:classifiers":[
        {
            "category":"Shopping",
            "type":"Retail Goods"
        }
    ],
    "sg:phone":"+1 408 244 9948",
    "sg:postcode":"95117",
    "sg:province":"CA",
    "sg:tags":[
        "bird"
    ],
    "wof:name":"K L Bird & Supplies",
    "wof:placetype":"venue"
},
  "geometry": {"coordinates":[-121.976581,37.303523],"type":"Point"}
}