{
  "type": "Feature",
  "properties": {
    "addr:full":"1933 Davis St San Leandro CA 94577",
    "addr:housenumber":"1933",
    "addr:postcode":"94577",
    "addr:street":"Davis St",
    "iso:country":"US",
    "sg:address":"1933 Davis St",
    "sg:city":"San Leandro",
    "sg:classifiers":[
        {
            "category":"Food & Beverages",
            "subcategory":"Chocolate",
            "type":"Retail Goods"
        }
    ],
    "sg:phone":"+1 510 568 2436",
    "sg:postcode":"94577",
    "sg:province":"CA",
    "sg:tags":[
        "shop",
        "chocolatiers"
    ],
    "sg:website":"www.sees.com",
    "wof:name":"See's Candies",
    "wof:placetype":"venue"
},
  "geometry": {"coordinates":[-122.180961,37.718003],"type":"Point"}
}