{
  "type": "Feature",
  "properties": {
    "iso:country":"US",
    "sg:address":"5 E Lewelling Blvd",
    "sg:city":"San Lorenzo",
    "sg:classifiers":[
        {
            "category":"Restaurant",
            "type":"Food & Drink"
        }
    ],
    "sg:phone":"+1 510 481 0571",
    "sg:postcode":"94580",
    "sg:province":"CA",
    "sg:tags":[
        "mexican"
    ],
    "wof:name":"Taqueria El Mezcal",
    "wof:placetype":"venue"
},
  "geometry": {"coordinates":[-122.12254299999999,37.68642],"type":"Point"}
}