{
  "type": "Feature",
  "properties": {
    "iso:country":"US",
    "sg:address":"3636 American River Drive",
    "sg:city":"Sacramento",
    "sg:classifiers":[
        {
            "category":"Restaurant",
            "type":"Food & Drink"
        }
    ],
    "sg:phone":"+1 916 974 7961",
    "sg:postcode":"95864",
    "sg:province":"CA",
    "wof:name":"The Riverwalk Cafe",
    "wof:placetype":"venue"
},
  "geometry": {"coordinates":[-121.376761,38.570089],"type":"Point"}
}