{
  "type": "Feature",
  "properties": {
    "addr:full":"1350 Hayes St Benicia CA 94510",
    "addr:housenumber":"1350",
    "addr:postcode":"94510",
    "addr:street":"Hayes St",
    "iso:country":"US",
    "sg:address":"1350 Hayes St",
    "sg:city":"Benicia",
    "sg:classifiers":[
        {
            "category":"Insurance",
            "subcategory":"Hazard Insurance",
            "type":"Services"
        }
    ],
    "sg:phone":"+1 707 747 4789",
    "sg:postcode":"94510",
    "sg:province":"CA",
    "wof:name":"Gabriel Benefit Svc",
    "wof:placetype":"venue"
},
  "geometry": {"coordinates":[-122.139066,38.047636],"type":"Point"}
}