{
  "type": "Feature",
  "properties": {
    "addr:full":"1880 Thornsberry Rd Sonoma CA 95476",
    "addr:housenumber":"1880",
    "addr:postcode":"95476",
    "addr:street":"Thornsberry Rd",
    "iso:country":"US",
    "sg:address":"1880 Thornsberry Rd",
    "sg:city":"Sonoma",
    "sg:classifiers":[
        {
            "category":"Wholesale",
            "subcategory":"Farm Supplies",
            "type":"Manufacturing & Wholesale Goods"
        }
    ],
    "sg:phone":"+1 707 664 6610",
    "sg:postcode":"95476",
    "sg:province":"CA",
    "wof:name":"United Molassses Co Inc",
    "wof:placetype":"venue"
},
  "geometry": {"coordinates":[-122.42417,38.292725],"type":"Point"}
}