{
  "type": "Feature",
  "properties": {
    "addr:full":"28081 Klamath Ct Laguna Niguel CA 92677",
    "addr:postcode":"28081;92677",
    "addr:street":"Klamath Ct",
    "iso:country":"US",
    "sg:address":"28081 Klamath Ct",
    "sg:city":"Laguna Niguel",
    "sg:classifiers":[
        {
            "category":"Shopping",
            "subcategory":"Computers & Home Electronics",
            "type":"Retail Goods"
        }
    ],
    "sg:phone":"+1 949 425 0322",
    "sg:postcode":"92677",
    "sg:province":"CA",
    "sg:tags":[
        "agency",
        "advertising",
        "mfg"
    ],
    "wof:name":"Desktop Designs",
    "wof:placetype":"venue"
},
  "geometry": {"coordinates":[-117.70207499999999,33.55454],"type":"Point"}
}