{
  "type": "Feature",
  "properties": {
    "addr:full":"1631 Lander Ave Turlock CA 95380",
    "addr:housenumber":"1631",
    "addr:postcode":"95380",
    "addr:street":"Lander Ave",
    "iso:country":"US",
    "sg:address":"1631 Lander Ave",
    "sg:city":"Turlock",
    "sg:classifiers":[
        {
            "category":"Food & Beverages",
            "subcategory":"Groceries & Convenience Stores",
            "type":"Retail Goods"
        }
    ],
    "sg:phone":"+1 209 632 2306",
    "sg:postcode":"95380",
    "sg:province":"CA",
    "sg:tags":[
        "grocer",
        "super",
        "supermarket"
    ],
    "sg:website":"http://www.SaveMart.com",
    "wof:name":"Save Mart Supermarkets",
    "wof:placetype":"venue"
},
  "geometry": {"coordinates":[-120.849001,37.47774],"type":"Point"}
}