{
  "type": "Feature",
  "properties": {
    "iso:country":"US",
    "sg:address":"1600 E 25th St",
    "sg:city":"Los Angeles",
    "sg:classifiers":[
        {
            "category":"Banks & Credit Unions",
            "subcategory":"Financial Services",
            "type":"Services"
        }
    ],
    "sg:phone":"+1 323 232 0288",
    "sg:postcode":"90011",
    "sg:province":"CA",
    "sg:tags":[
        "international",
        "trade"
    ],
    "wof:name":"Sun Power Trading Inc",
    "wof:placetype":"venue"
},
  "geometry": {"coordinates":[-118.243235,34.014503],"type":"Point"}
}