{
  "type": "Feature",
  "properties": {
    "iso:country":"US",
    "sg:address":"12663 Glenoaks Blvd",
    "sg:city":"Sylmar",
    "sg:classifiers":[
        {
            "category":"Shopping",
            "subcategory":"Shoes",
            "type":"Retail Goods"
        }
    ],
    "sg:phone":"+1 818 364 2990",
    "sg:postcode":"91342",
    "sg:province":"CA",
    "wof:name":"Shoe Hut",
    "wof:placetype":"venue"
},
  "geometry": {"coordinates":[-118.44101,34.300757],"type":"Point"}
}