{
  "type": "Feature",
  "properties": {
    "addr:full":"2378 W Tahoe Ave Caruthers CA 93609",
    "addr:housenumber":"2378",
    "addr:postcode":"93609",
    "addr:street":"W Tahoe Ave",
    "iso:country":"US",
    "sg:address":"2378 W Tahoe Ave",
    "sg:city":"Caruthers",
    "sg:classifiers":[
        {
            "category":"Real Estate",
            "subcategory":"Real Estate Services",
            "type":"Services"
        },
        {
            "category":"Real Estate",
            "subcategory":"Real Estate Agent",
            "type":"Services"
        }
    ],
    "sg:phone":"+1 559 864 4372",
    "sg:postcode":"93609",
    "sg:province":"CA",
    "sg:tags":[
        "management"
    ],
    "wof:name":"Herb Hanson",
    "wof:placetype":"venue"
},
  "geometry": {"coordinates":[-119.83428000000001,36.541401],"type":"Point"}
}