{
  "type": "Feature",
  "properties": {
    "addr:full":"3290 Mission St San Francisco CA 94110",
    "addr:housenumber":"3290",
    "addr:postcode":"94110",
    "addr:street":"Mission St",
    "iso:country":"US",
    "sg:address":"3290 Mission St",
    "sg:city":"San Francisco",
    "sg:classifiers":[
        {
            "category":"Personal",
            "subcategory":"Beauty Salon",
            "type":"Services"
        }
    ],
    "sg:phone":"+1 650 991 1409",
    "sg:postcode":"94110",
    "sg:province":"CA",
    "wof:name":"Princess Salon",
    "wof:placetype":"venue"
},
  "geometry": {"coordinates":[-122.42032500000001,37.745312],"type":"Point"}
}