{
  "type": "Feature",
  "properties": {
    "iso:country":"US",
    "sg:address":"275 Colgan Ave",
    "sg:city":"Santa Rosa",
    "sg:classifiers":[
        {
            "category":"Building & Trades",
            "subcategory":"Construction",
            "type":"Services"
        }
    ],
    "sg:phone":"+1 707 539 7048",
    "sg:postcode":"95404",
    "sg:province":"CA",
    "sg:tags":[
        "contractor"
    ],
    "wof:name":"R L & T",
    "wof:placetype":"venue"
},
  "geometry": {"coordinates":[-122.713312,38.421243],"type":"Point"}
}