{
  "type": "Feature",
  "properties": {
    "addr:full":"3250 E Frontera St Anaheim CA 92806",
    "addr:housenumber":"3250",
    "addr:postcode":"92806",
    "addr:street":"E Frontera St",
    "iso:country":"US",
    "sg:address":"3250 E Frontera St",
    "sg:city":"Anaheim",
    "sg:classifiers":[
        {
            "category":"Manufacturing",
            "subcategory":"Metals",
            "type":"Manufacturing & Wholesale Goods"
        }
    ],
    "sg:phone":"+1 714 630 6523",
    "sg:postcode":"92806",
    "sg:province":"CA",
    "sg:tags":[
        "copper",
        "foundry"
    ],
    "wof:name":"Adams Steel Inc",
    "wof:placetype":"venue"
},
  "geometry": {"coordinates":[-117.84835,33.849272],"type":"Point"}
}