{
  "type": "Feature",
  "properties": {
    "addr:full":"13400 S Figueroa St Los Angeles CA 90061",
    "addr:housenumber":"13400",
    "addr:postcode":"90061",
    "addr:street":"S Figueroa St",
    "iso:country":"US",
    "sg:address":"13400 S Figueroa St",
    "sg:city":"Los Angeles",
    "sg:classifiers":[
        {
            "category":"Building & Trades",
            "subcategory":"Construction",
            "type":"Services"
        }
    ],
    "sg:phone":"+1 310 515 6843",
    "sg:postcode":"90061",
    "sg:province":"CA",
    "sg:tags":[
        "contractor"
    ],
    "sg:website":"www.geosupport.com",
    "wof:name":"August Construction & Drilling",
    "wof:placetype":"venue"
},
  "geometry": {"coordinates":[-118.282652,33.909291],"type":"Point"}
}