{
  "type": "Feature",
  "properties": {
    "iso:country":"US",
    "sg:address":"1304 Castro St",
    "sg:city":"San Francisco",
    "sg:classifiers":[
        {
            "category":"Personal",
            "type":"Services"
        }
    ],
    "sg:phone":"+1 415 821 7369",
    "sg:postcode":"94114",
    "sg:province":"CA",
    "sg:tags":[
        "wedding",
        "chapel"
    ],
    "wof:name":"Ceremonies & Celebrations",
    "wof:placetype":"venue"
},
  "geometry": {"coordinates":[-122.434084,37.750522],"type":"Point"}
}