{
  "type": "Feature",
  "properties": {
    "iso:country":"US",
    "sg:address":"1800 E Garry Ave Ste 208",
    "sg:city":"Santa Ana",
    "sg:classifiers":[
        {
            "category":"Real Estate",
            "subcategory":"Real Estate Services",
            "type":"Services"
        }
    ],
    "sg:phone":"+1 949 261 1166",
    "sg:postcode":"92705",
    "sg:province":"CA",
    "sg:tags":[
        "management",
        "property"
    ],
    "wof:name":"Magnolia Enterprises",
    "wof:placetype":"venue"
},
  "geometry": {"coordinates":[-117.852997,33.705002],"type":"Point"}
}