{
  "type": "Feature",
  "properties": {
    "addr:full":"37531 Fremont Blvd Fremont CA 94536",
    "addr:housenumber":"37531",
    "addr:postcode":"94536",
    "addr:street":"Fremont Blvd",
    "iso:country":"US",
    "sg:address":"37531 Fremont Blvd",
    "sg:city":"Fremont",
    "sg:classifiers":[
        {
            "category":"Social Services",
            "subcategory":"Child Care",
            "type":"Services"
        }
    ],
    "sg:phone":"+1 510 792 8415",
    "sg:postcode":"94536",
    "sg:province":"CA",
    "wof:name":"A Childs Hideaway",
    "wof:placetype":"venue"
},
  "geometry": {"coordinates":[-122.005188,37.557185],"type":"Point"}
}