{
  "type": "Feature",
  "properties": {
    "iso:country":"US",
    "sg:address":"1155 W Mahalo Pl",
    "sg:city":"Compton",
    "sg:classifiers":[
        {
            "category":"Manufacturing",
            "subcategory":"Tools & Machinery",
            "type":"Manufacturing & Wholesale Goods"
        }
    ],
    "sg:phone":"+1 310 325 6112",
    "sg:postcode":"90220",
    "sg:province":"CA",
    "sg:tags":[
        "machine",
        "shop"
    ],
    "sg:website":"www.aandveng.com",
    "wof:name":"A & V Engineering",
    "wof:placetype":"venue"
},
  "geometry": {"coordinates":[-118.244306,33.871344],"type":"Point"}
}