{
  "type": "Feature",
  "properties": {
    "addr:full":"265 E Olympic Boulevard Los Angeles CA 90015",
    "addr:housenumber":"265",
    "addr:postcode":"90015",
    "addr:street":"E Olympic Boulevard",
    "iso:country":"US",
    "sg:address":"265 E Olympic Boulevard",
    "sg:city":"Los Angeles",
    "sg:classifiers":[
        {
            "category":"Shopping",
            "subcategory":"Clothing, Apparel, & Fashions",
            "type":"Retail Goods"
        }
    ],
    "sg:phone":"+1 213 614 8839",
    "sg:postcode":"90015",
    "sg:province":"CA",
    "sg:tags":[
        "accessory",
        "clothing",
        "women's"
    ],
    "wof:name":"Anna Collection",
    "wof:placetype":"venue"
},
  "geometry": {"coordinates":[-118.254705,34.038893],"type":"Point"}
}