{
  "type": "Feature",
  "properties": {
    "addr:full":"710 H St Fresno CA 93721",
    "addr:housenumber":"710",
    "addr:postcode":"93721",
    "addr:street":"H St",
    "iso:country":"US",
    "sg:address":"710 H St",
    "sg:city":"Fresno",
    "sg:classifiers":[
        {
            "category":"Manufacturing",
            "subcategory":"Retail Goods",
            "type":"Manufacturing & Wholesale Goods"
        }
    ],
    "sg:phone":"+1 559 268 3038",
    "sg:postcode":"93721",
    "sg:province":"CA",
    "sg:tags":[
        "burial",
        "casket",
        "mfg"
    ],
    "wof:name":"Western Casket Mfg Co",
    "wof:placetype":"venue"
},
  "geometry": {"coordinates":[-119.789856,36.730418],"type":"Point"}
}