{
  "type": "Feature",
  "properties": {
    "iso:country":"US",
    "sg:address":"1400 Coleman Ave",
    "sg:city":"Santa Clara",
    "sg:classifiers":[
        {
            "category":"Professional",
            "subcategory":"Computer Services",
            "type":"Services"
        }
    ],
    "sg:phone":"+1 408 844 9391",
    "sg:postcode":"95050",
    "sg:province":"CA",
    "wof:name":"Integrated Netcomm Corp",
    "wof:placetype":"venue"
},
  "geometry": {"coordinates":[-121.94004,37.35837],"type":"Point"}
}