{
  "type": "Feature",
  "properties": {
    "iso:country":"US",
    "sg:address":"22892 Willard Ave",
    "sg:city":"Lake Forest",
    "sg:classifiers":[
        {
            "category":"Manufacturing",
            "subcategory":"Tools & Machinery",
            "type":"Manufacturing & Wholesale Goods"
        }
    ],
    "sg:phone":"+1 949 837 8741",
    "sg:postcode":"92630",
    "sg:province":"CA",
    "sg:tags":[
        "machine",
        "shop"
    ],
    "wof:name":"Weber Tool & Mfg",
    "wof:placetype":"venue"
},
  "geometry": {"coordinates":[-117.69461,33.630774],"type":"Point"}
}