{
  "type": "Feature",
  "properties": {
    "iso:country":"US",
    "sg:address":"2575 N Tustin St",
    "sg:city":"Orange",
    "sg:classifiers":[
        {
            "category":"Fast Food",
            "type":"Food & Drink"
        }
    ],
    "sg:phone":"+1 714 685 1707",
    "sg:postcode":"92865",
    "sg:province":"CA",
    "sg:website":"www.chickfila.com",
    "wof:name":"Chick-fil-A",
    "wof:placetype":"venue"
},
  "geometry": {"coordinates":[-117.83620500000001,33.830906],"type":"Point"}
}