{
  "type": "Feature",
  "properties": {
    "addr:full":"341 Castro St San Leandro CA 94577",
    "addr:housenumber":"341",
    "addr:postcode":"94577",
    "addr:street":"Castro St",
    "iso:country":"US",
    "sg:address":"341 Castro St",
    "sg:city":"San Leandro",
    "sg:classifiers":[
        {
            "category":"Taxi",
            "type":"Transportation"
        }
    ],
    "sg:phone":"+1 510 297 0101",
    "sg:postcode":"94577",
    "sg:province":"CA",
    "wof:name":"Yellow Cab",
    "wof:placetype":"venue"
},
  "geometry": {"coordinates":[-122.154287,37.718655],"type":"Point"}
}