{
  "type": "Feature",
  "properties": {
    "iso:country":"US",
    "sg:address":"51 Howard Ave",
    "sg:city":"Santa Paula",
    "sg:classifiers":[
        {
            "category":"Building & Trades",
            "subcategory":"Electrical",
            "type":"Services"
        }
    ],
    "sg:phone":"+1 805 525 7029",
    "sg:postcode":"93022",
    "sg:province":"CA",
    "sg:tags":[
        "work",
        "electrical"
    ],
    "wof:name":"Bates Electric",
    "wof:placetype":"venue"
},
  "geometry": {"coordinates":[-119.284202,34.417095],"type":"Point"}
}