{
  "type": "Feature",
  "properties": {
    "addr:full":"1607 Marjorie Crst Redlands CA 92373",
    "addr:housenumber":"1607",
    "addr:postcode":"92373",
    "addr:street":"Marjorie Crst",
    "iso:country":"US",
    "sg:address":"1607 Marjorie Crst",
    "sg:city":"Redlands",
    "sg:classifiers":[
        {
            "category":"Professional",
            "subcategory":"Engineering",
            "type":"Services"
        }
    ],
    "sg:phone":"+1 909 793 5247",
    "sg:postcode":"92373",
    "sg:province":"CA",
    "sg:tags":[
        "engineer"
    ],
    "wof:name":"Robert T Mac Intyre Consulting",
    "wof:placetype":"venue"
},
  "geometry": {"coordinates":[-117.14649,34.031259],"type":"Point"}
}