{
  "type": "Feature",
  "properties": {
    "addr:full":"8707 Lankershim Blvd Sun Valley CA 91352",
    "addr:housenumber":"8707",
    "addr:postcode":"91352",
    "addr:street":"Lankershim Blvd",
    "iso:country":"US",
    "sg:address":"8707 Lankershim Blvd",
    "sg:city":"Sun Valley",
    "sg:classifiers":[
        {
            "category":"Home & Garden",
            "subcategory":"Home Furnishings",
            "type":"Retail Goods"
        }
    ],
    "sg:phone":"+1 818 768 3100",
    "sg:postcode":"91352",
    "sg:province":"CA",
    "sg:tags":[
        "trade",
        "contractor"
    ],
    "wof:name":"Peters Draperys & Blinds",
    "wof:placetype":"venue"
},
  "geometry": {"coordinates":[-118.387832,34.227674],"type":"Point"}
}