{
  "type": "Feature",
  "properties": {
    "iso:country":"US",
    "sg:address":"3709 Candlewood Dr",
    "sg:city":"Bakersfield",
    "sg:classifiers":[
        {
            "category":"Manufacturing",
            "subcategory":"Toys & Sporting Goods",
            "type":"Manufacturing & Wholesale Goods"
        }
    ],
    "sg:phone":"+1 661 871 3088",
    "sg:postcode":"93306",
    "sg:province":"CA",
    "sg:tags":[
        "mfg"
    ],
    "wof:name":"ME & My Friends",
    "wof:placetype":"venue"
},
  "geometry": {"coordinates":[-118.952236,35.406675],"type":"Point"}
}