{
  "type": "Feature",
  "properties": {
    "iso:country":"US",
    "sg:address":"219 S Broadway",
    "sg:city":"Turlock",
    "sg:classifiers":[
        {
            "category":"Social Services",
            "type":"Services"
        }
    ],
    "sg:phone":"+1 209 669 9355",
    "sg:postcode":"95380",
    "sg:province":"CA",
    "sg:tags":[
        "organization",
        "welfare"
    ],
    "wof:name":"Samaritan House",
    "wof:placetype":"venue"
},
  "geometry": {"coordinates":[-120.846104,37.491699],"type":"Point"}
}