{
  "type": "Feature",
  "properties": {
    "iso:country":"US",
    "sg:address":"9535 Mission Gorge Rd",
    "sg:city":"Santee",
    "sg:classifiers":[
        {
            "category":"Retail",
            "subcategory":"Auto Repair",
            "type":"Services"
        }
    ],
    "sg:phone":"+1 619 449 2155",
    "sg:postcode":"92071",
    "sg:province":"CA",
    "sg:tags":[
        "repairing",
        "automobile"
    ],
    "sg:website":"www.expresstire.com",
    "wof:name":"Express Tire",
    "wof:placetype":"venue"
},
  "geometry": {"coordinates":[-116.989307,32.838612],"type":"Point"}
}