{
  "type": "Feature",
  "properties": {
    "addr:full":"20800 Vintage St Chatsworth CA 91311",
    "addr:housenumber":"20800",
    "addr:postcode":"91311",
    "addr:street":"Vintage St",
    "iso:country":"US",
    "sg:address":"20800 Vintage St",
    "sg:city":"Chatsworth",
    "sg:classifiers":[
        {
            "category":"Professional",
            "subcategory":"Business Services",
            "type":"Services"
        }
    ],
    "sg:phone":"+1 818 709 4493",
    "sg:postcode":"91311",
    "sg:province":"CA",
    "wof:name":"Fholiz Business Bureau",
    "wof:placetype":"venue"
},
  "geometry": {"coordinates":[-118.58673,34.251723],"type":"Point"}
}