{
  "type": "Feature",
  "properties": {
    "addr:full":"35 Chantilly Pl Oakley CA 94561",
    "addr:housenumber":"35",
    "addr:postcode":"94561",
    "addr:street":"Chantilly Pl",
    "iso:country":"US",
    "sg:address":"35 Chantilly Pl",
    "sg:city":"Oakley",
    "sg:classifiers":[
        {
            "category":"Social Services",
            "subcategory":"Child Care",
            "type":"Services"
        }
    ],
    "sg:phone":"+1 925 679 0760",
    "sg:postcode":"94561",
    "sg:province":"CA",
    "wof:name":"Jule's Little Gems Childcare",
    "wof:placetype":"venue"
},
  "geometry": {"coordinates":[-121.724362,38.003057],"type":"Point"}
}