{
  "type": "Feature",
  "properties": {
    "iso:country":"US",
    "sg:address":"136 N Ashwood Ave",
    "sg:city":"Ventura",
    "sg:classifiers":[
        {
            "category":"Insurance",
            "subcategory":"Insurance Agent",
            "type":"Services"
        }
    ],
    "sg:phone":"+1 805 642 8566",
    "sg:postcode":"93003",
    "sg:province":"CA",
    "wof:name":"Stafford Robertson Agency",
    "wof:placetype":"venue"
},
  "geometry": {"coordinates":[-119.239314,34.275163],"type":"Point"}
}