{
  "type": "Feature",
  "properties": {
    "addr:full":"11471 Sutton Way Grass Valley CA 95945",
    "addr:housenumber":"11471",
    "addr:postcode":"95945",
    "addr:street":"Sutton Way",
    "iso:country":"US",
    "sg:address":"11471 Sutton Way",
    "sg:city":"Grass Valley",
    "sg:classifiers":[
        {
            "category":"Health Services",
            "subcategory":"Hospital",
            "type":"Services"
        }
    ],
    "sg:phone":"+1 530 274 7911",
    "sg:postcode":"95945",
    "sg:province":"CA",
    "sg:tags":[
        "mental"
    ],
    "wof:name":"Nancy Bascom",
    "wof:placetype":"venue"
},
  "geometry": {"coordinates":[-121.03610999999999,39.232726],"type":"Point"}
}