{
  "type": "Feature",
  "properties": {
    "iso:country":"US",
    "sg:address":"100 Estates Dr",
    "sg:city":"Roseville",
    "sg:classifiers":[
        {
            "category":"Professional",
            "subcategory":"Lawyer & Legal Services",
            "type":"Services"
        }
    ],
    "sg:phone":"+1 916 782 4228",
    "sg:postcode":"95678",
    "sg:province":"CA",
    "sg:tags":[
        "attorney"
    ],
    "wof:name":"Jon J Del Bino Attorney",
    "wof:placetype":"venue"
},
  "geometry": {"coordinates":[-121.276706,38.747334],"type":"Point"}
}