{
  "type": "Feature",
  "properties": {
    "iso:country":"US",
    "sg:address":"438 E Brown Ave",
    "sg:city":"Fresno",
    "sg:classifiers":[
        {
            "category":"Building & Trades",
            "subcategory":"Construction",
            "type":"Services"
        }
    ],
    "sg:phone":"+1 559 292 4085",
    "sg:postcode":"93704",
    "sg:province":"CA",
    "sg:tags":[
        "contractor"
    ],
    "wof:name":"GFC Construction",
    "wof:placetype":"venue"
},
  "geometry": {"coordinates":[-119.807709,36.774799],"type":"Point"}
}