{
  "type": "Feature",
  "properties": {
    "addr:full":"500 Pointe Dr Brea CA 92821",
    "addr:housenumber":"500",
    "addr:postcode":"92821",
    "addr:street":"Pointe Dr",
    "iso:country":"US",
    "sg:address":"500 Pointe Dr",
    "sg:city":"Brea",
    "sg:classifiers":[
        {
            "category":"Autos & Motor Vehicles",
            "subcategory":"Automobile Sales",
            "type":"Retail Goods"
        }
    ],
    "sg:phone":"+1 714 482 1400",
    "sg:postcode":"92821",
    "sg:province":"CA",
    "sg:tags":[
        "car",
        "used"
    ],
    "wof:name":"AutoTrader com",
    "wof:placetype":"venue"
},
  "geometry": {"coordinates":[-117.877595,33.927586],"type":"Point"}
}