{
  "type": "Feature",
  "properties": {
    "iso:country":"US",
    "sg:address":"3669 Arundell Cir",
    "sg:city":"Ventura",
    "sg:classifiers":[
        {
            "category":"Home & Garden",
            "subcategory":"Building Materials",
            "type":"Retail Goods"
        }
    ],
    "sg:phone":"+1 805 642 7873",
    "sg:postcode":"93003",
    "sg:province":"CA",
    "sg:tags":[
        "glass",
        "window",
        "plate"
    ],
    "wof:name":"Glass Monkey",
    "wof:placetype":"venue"
},
  "geometry": {"coordinates":[-119.24787499999999,34.259497],"type":"Point"}
}