{
  "type": "Feature",
  "properties": {
    "iso:country":"US",
    "sg:address":"3624 Verbena Dr",
    "sg:city":"Rialto",
    "sg:classifiers":[
        {
            "category":"Organizations",
            "subcategory":"Religious Organization",
            "type":"Services"
        }
    ],
    "sg:phone":"+1 951 218 1840",
    "sg:postcode":"92377",
    "sg:province":"CA",
    "sg:tags":[
        "church"
    ],
    "wof:name":"Thee Upper Room",
    "wof:placetype":"venue"
},
  "geometry": {"coordinates":[-117.416118,34.163721],"type":"Point"}
}