{
  "type": "Feature",
  "properties": {
    "iso:country":"US",
    "sg:address":"950 Orcutt Rd",
    "sg:city":"San Luis Obispo",
    "sg:phone":"+1 805 748 5677",
    "sg:postcode":"93401",
    "sg:province":"CA",
    "sg:tags":[
        "product",
        "petroleum"
    ],
    "wof:name":"West Coast Fuel",
    "wof:placetype":"venue"
},
  "geometry": {"coordinates":[-120.644486,35.261443],"type":"Point"}
}