{
  "type": "Feature",
  "properties": {
    "addr:full":"1100 N Kidder Creek Rd Greenview CA 96037",
    "addr:housenumber":"1100",
    "addr:postcode":"96037",
    "addr:street":"N Kidder Creek Rd",
    "iso:country":"US",
    "sg:address":"1100 N Kidder Creek Rd",
    "sg:city":"Greenview",
    "sg:classifiers":[
        {
            "category":"Manufacturing",
            "subcategory":"Tools & Machinery",
            "type":"Manufacturing & Wholesale Goods"
        }
    ],
    "sg:phone":"+1 530 468 5195",
    "sg:postcode":"96037",
    "sg:province":"CA",
    "wof:name":"Vern's Welding & Equipment",
    "wof:placetype":"venue"
},
  "geometry": {"coordinates":[-122.929571,41.548553],"type":"Point"}
}