{
  "type": "Feature",
  "properties": {
    "iso:country":"US",
    "sg:address":"575 N Shoreline Blvd",
    "sg:city":"Mountain View",
    "sg:classifiers":[
        {
            "category":"Arts & Performance",
            "subcategory":"Festival",
            "type":"Entertainment"
        }
    ],
    "sg:postcode":"94043",
    "sg:province":"CA",
    "sg:website":"www.midorikai.com/",
    "wof:name":"Midori Kai Boutique",
    "wof:placetype":"venue"
},
  "geometry": {"coordinates":[-122.077337,37.402308],"type":"Point"}
}