{
  "type": "Feature",
  "properties": {
    "addr:full":"12 Lyra Irvine CA 92603",
    "addr:housenumber":"12",
    "addr:postcode":"92603",
    "addr:street":"Lyra",
    "iso:country":"US",
    "sg:address":"12 Lyra",
    "sg:city":"Irvine",
    "sg:classifiers":[
        {
            "category":"Professional",
            "subcategory":"Employment Agencies",
            "type":"Services"
        }
    ],
    "sg:phone":"+1 949 854 8439",
    "sg:postcode":"92603",
    "sg:province":"CA",
    "wof:name":"Expertech Consulting",
    "wof:placetype":"venue"
},
  "geometry": {"coordinates":[-117.810035,33.642113],"type":"Point"}
}