{
  "type": "Feature",
  "properties": {
    "iso:country":"US",
    "sg:address":"742 Felspar St",
    "sg:city":"San Diego",
    "sg:classifiers":[
        {
            "category":"Shopping",
            "subcategory":"Bicycles & Sporting Goods",
            "type":"Retail Goods"
        }
    ],
    "sg:phone":"+1 858 272 1274",
    "sg:postcode":"92109",
    "sg:province":"CA",
    "sg:tags":[
        "bike",
        "rental"
    ],
    "sg:website":"www.bicycle-discovery.com",
    "wof:name":"Bicycle Discovery",
    "wof:placetype":"venue"
},
  "geometry": {"coordinates":[-117.25700399999999,32.797199],"type":"Point"}
}