{
  "type": "Feature",
  "properties": {
    "iso:country":"US",
    "sg:address":"2827 Carob St",
    "sg:city":"Newport Beach",
    "sg:classifiers":[
        {
            "category":"Professional",
            "type":"Services"
        }
    ],
    "sg:phone":"+1 949 644 1974",
    "sg:postcode":"92660",
    "sg:province":"CA",
    "wof:name":"Donovan Bernauer",
    "wof:placetype":"venue"
},
  "geometry": {"coordinates":[-117.869591,33.643552],"type":"Point"}
}