{
  "type": "Feature",
  "properties": {
    "addr:full":"1950 Santa Rosa Ave Santa Rosa CA 95407",
    "addr:housenumber":"1950",
    "addr:postcode":"95407",
    "addr:street":"Santa Rosa Ave",
    "iso:country":"US",
    "sg:address":"1950 Santa Rosa Ave",
    "sg:city":"Santa Rosa",
    "sg:classifiers":[
        {
            "category":"Home & Garden",
            "subcategory":"Household Appliances",
            "type":"Retail Goods"
        }
    ],
    "sg:phone":"+1 707 545 1078",
    "sg:postcode":"95407",
    "sg:province":"CA",
    "wof:name":"Best Buy",
    "wof:placetype":"venue"
},
  "geometry": {"coordinates":[-122.713419,38.420692],"type":"Point"}
}