{
  "type": "Feature",
  "properties": {
    "addr:full":"164 W Hospitality Ln San Bernardino CA 92408",
    "addr:housenumber":"164",
    "addr:postcode":"92408",
    "addr:street":"W Hospitality Ln",
    "iso:country":"US",
    "sg:address":"164 W Hospitality Ln",
    "sg:city":"San Bernardino",
    "sg:classifiers":[
        {
            "category":"Professional",
            "subcategory":"Computer Services",
            "type":"Services"
        }
    ],
    "sg:phone":"+1 909 890 4050",
    "sg:postcode":"92408",
    "sg:province":"CA",
    "sg:tags":[
        "consultant",
        "designer",
        "datum",
        "system"
    ],
    "wof:name":"Data Institute",
    "wof:placetype":"venue"
},
  "geometry": {"coordinates":[-117.286986,34.06576],"type":"Point"}
}