{
  "type": "Feature",
  "properties": {
    "iso:country":"US",
    "sg:address":"8212 Calendula Dr",
    "sg:city":"Buena Park",
    "sg:classifiers":[
        {
            "category":"Health Services",
            "subcategory":"Clinic",
            "type":"Services"
        }
    ],
    "sg:phone":"+1 714 994 5293",
    "sg:postcode":"90620",
    "sg:province":"CA",
    "sg:tags":[
        "home"
    ],
    "wof:name":"ASGB Master Svc",
    "wof:placetype":"venue"
},
  "geometry": {"coordinates":[-117.99171200000001,33.853907],"type":"Point"}
}