{
  "type": "Feature",
  "properties": {
    "addr:full":"15000 Crenshaw Blvd Gardena CA 90249",
    "addr:housenumber":"15000",
    "addr:postcode":"90249",
    "addr:street":"Crenshaw Blvd",
    "iso:country":"US",
    "sg:address":"15000 Crenshaw Blvd",
    "sg:city":"Gardena",
    "sg:classifiers":[
        {
            "category":"Shopping",
            "subcategory":"Gifts & Souvenirs",
            "type":"Retail Goods"
        }
    ],
    "sg:phone":"+1 310 515 5190",
    "sg:postcode":"90249",
    "sg:province":"CA",
    "wof:name":"Morning Glory",
    "wof:placetype":"venue"
},
  "geometry": {"coordinates":[-118.326437,33.897411],"type":"Point"}
}