{
  "type": "Feature",
  "properties": {
    "iso:country":"US",
    "name:eng_x_preferred":[
        "SF-08C Vollmer Peak Nike Site"
    ],
    "wof:name":"SF-08C Vollmer Peak Nike Site",
    "wof:placetype":"venue"
},
  "geometry": {"coordinates":[-122.22188,37.88366],"type":"Point"}
}