{
  "type": "Feature",
  "properties": {
    "addr:full":"13719 Alma Ave Gardena CA 90249",
    "addr:housenumber":"13719",
    "addr:postcode":"90249",
    "addr:street":"Alma Ave",
    "iso:country":"US",
    "sg:address":"13719 Alma Ave",
    "sg:city":"Gardena",
    "sg:classifiers":[
        {
            "category":"Home & Garden",
            "subcategory":"Carpets & Floor Coverings",
            "type":"Retail Goods"
        }
    ],
    "sg:phone":"+1 310 768 1497",
    "sg:postcode":"90249",
    "sg:province":"CA",
    "sg:tags":[
        "flooring"
    ],
    "wof:name":"Sde Carpet Technology",
    "wof:placetype":"venue"
},
  "geometry": {"coordinates":[-118.30310799999999,33.907053],"type":"Point"}
}