{
  "type": "Feature",
  "properties": {
    "addr:full":"8521 Younger Creek Dr Sacramento CA 95828",
    "addr:housenumber":"8521",
    "addr:postcode":"95828",
    "addr:street":"Younger Creek Dr",
    "iso:country":"US",
    "sg:address":"8521 Younger Creek Dr",
    "sg:city":"Sacramento",
    "sg:classifiers":[
        {
            "category":"Home & Garden",
            "subcategory":"Carpets & Floor Coverings",
            "type":"Retail Goods"
        }
    ],
    "sg:phone":"+1 916 381 3100",
    "sg:postcode":"95828",
    "sg:province":"CA",
    "sg:tags":[
        "dealer",
        "rug"
    ],
    "wof:name":"Merchants Carpet",
    "wof:placetype":"venue"
},
  "geometry": {"coordinates":[-121.385198,38.516799],"type":"Point"}
}