{
  "type": "Feature",
  "properties": {
    "iso:country":"US",
    "sg:address":"4641 Pell Dr Ste 16",
    "sg:city":"Sacramento",
    "sg:classifiers":[
        {
            "category":"Wholesale",
            "subcategory":"Machinery & Supplies",
            "type":"Manufacturing & Wholesale Goods"
        }
    ],
    "sg:phone":"+1 916 924 1054",
    "sg:postcode":"95838",
    "sg:province":"CA",
    "sg:tags":[
        "industrial",
        "machinery-new",
        "equipment",
        "used",
        "supplies-wholesale"
    ],
    "wof:name":"L S I",
    "wof:placetype":"venue"
},
  "geometry": {"coordinates":[-121.47148,38.650094],"type":"Point"}
}