{
  "type": "Feature",
  "properties": {
    "iso:country":"US",
    "sg:address":"4305 University Ave",
    "sg:city":"San Diego",
    "sg:classifiers":[
        {
            "category":"Social Services",
            "type":"Services"
        }
    ],
    "sg:phone":"+1 619 501 1804",
    "sg:postcode":"92105",
    "sg:province":"CA",
    "sg:tags":[
        "organization",
        "welfare"
    ],
    "wof:name":"Pacific Inst For Comm Org",
    "wof:placetype":"venue"
},
  "geometry": {"coordinates":[-117.100955,32.749538],"type":"Point"}
}