{
  "type": "Feature",
  "properties": {
    "addr:full":"6361 Clark Rd Paradise CA 95969",
    "addr:housenumber":"6361",
    "addr:postcode":"95969",
    "addr:street":"Clark Rd",
    "iso:country":"US",
    "sg:address":"6361 Clark Rd",
    "sg:city":"Paradise",
    "sg:classifiers":[
        {
            "category":"Restaurant",
            "type":"Food & Drink"
        }
    ],
    "sg:menulink":"http://www.allmenus.com/ca/paradise/197940-kfc---kentucky-fried-chicken/menu/",
    "sg:phone":"+1 530 877 1301",
    "sg:postcode":"95969",
    "sg:province":"CA",
    "sg:tags":[
        "american",
        "chicken"
    ],
    "wof:name":"KFC - Kentucky Fried Chicken",
    "wof:placetype":"venue"
},
  "geometry": {"coordinates":[-121.598539,39.770075],"type":"Point"}
}