{
  "type": "Feature",
  "properties": {
    "iso:country":"US",
    "sg:address":"2451 Meadowview Rd",
    "sg:city":"Sacramento",
    "sg:classifiers":[
        {
            "category":"Wholesale",
            "subcategory":"Toys & Hobbies",
            "type":"Manufacturing & Wholesale Goods"
        }
    ],
    "sg:phone":"+1 916 275 3148",
    "sg:postcode":"95832",
    "sg:province":"CA",
    "sg:tags":[
        "wholesaler"
    ],
    "wof:name":"R J Wholesale",
    "wof:placetype":"venue"
},
  "geometry": {"coordinates":[-121.476001,38.481539],"type":"Point"}
}