{
  "type": "Feature",
  "properties": {
    "addr:full":"3625 W Barstow Ave Fresno CA 93711",
    "addr:housenumber":"3625",
    "addr:postcode":"93711",
    "addr:street":"W Barstow Ave",
    "iso:country":"US",
    "sg:address":"3625 W Barstow Ave",
    "sg:city":"Fresno",
    "sg:classifiers":[
        {
            "category":"Home & Garden",
            "subcategory":"Garden Supply",
            "type":"Retail Goods"
        }
    ],
    "sg:phone":"+1 559 618 2755",
    "sg:postcode":"93711",
    "sg:province":"CA",
    "sg:tags":[
        "fountain",
        "display"
    ],
    "wof:name":"California Dream Gardens",
    "wof:placetype":"venue"
},
  "geometry": {"coordinates":[-119.85985100000001,36.815342],"type":"Point"}
}