{
  "type": "Feature",
  "properties": {
    "addr:full":"19718 Sherman Way Winnetka CA 91306",
    "addr:housenumber":"19718",
    "addr:postcode":"91306",
    "addr:street":"Sherman Way",
    "iso:country":"US",
    "sg:address":"19718 Sherman Way",
    "sg:city":"Winnetka",
    "sg:classifiers":[
        {
            "category":"Food & Beverages",
            "subcategory":"Groceries & Convenience Stores",
            "type":"Retail Goods"
        }
    ],
    "sg:phone":"+1 818 996 1331",
    "sg:postcode":"91306",
    "sg:province":"CA",
    "wof:name":"Smart & Final",
    "wof:placetype":"venue"
},
  "geometry": {"coordinates":[-118.56199599999999,34.201099],"type":"Point"}
}