{
  "type": "Feature",
  "properties": {
    "addr:full":"52370 Ave Madero La Quinta CA 92253",
    "addr:housenumber":"52370",
    "addr:postcode":"92253",
    "addr:street":"Ave Madero",
    "iso:country":"US",
    "sg:address":"52370 Ave Madero",
    "sg:city":"La Quinta",
    "sg:classifiers":[
        {
            "category":"Food & Beverages",
            "subcategory":"Specialty",
            "type":"Retail Goods"
        }
    ],
    "sg:phone":"+1 760 880 2653",
    "sg:postcode":"92253",
    "sg:province":"CA",
    "sg:tags":[
        "vitamin"
    ],
    "wof:name":"Indigenous Technologies",
    "wof:placetype":"venue"
},
  "geometry": {"coordinates":[-116.317413,33.668477],"type":"Point"}
}