{
  "type": "Feature",
  "properties": {
    "addr:full":"2209 Harbor Bay Pkwy Alameda CA 94502",
    "addr:housenumber":"2209",
    "addr:postcode":"94502",
    "addr:street":"Harbor Bay Pkwy",
    "iso:country":"US",
    "sg:address":"2209 Harbor Bay Pkwy",
    "sg:city":"Alameda",
    "sg:classifiers":[
        {
            "category":"Banks & Credit Unions",
            "subcategory":"Financial Services",
            "type":"Services"
        }
    ],
    "sg:phone":"+1 510 864 8010",
    "sg:postcode":"94502",
    "sg:province":"CA",
    "sg:tags":[
        "broker",
        "mortgage"
    ],
    "wof:name":"Campbell-Harris Security Equip",
    "wof:placetype":"venue"
},
  "geometry": {"coordinates":[-122.249696,37.7313],"type":"Point"}
}