{
  "type": "Feature",
  "properties": {
    "iso:country":"US",
    "sg:address":"705 N Vulcan Ave",
    "sg:city":"Encinitas",
    "sg:classifiers":[
        {
            "category":"Personal",
            "subcategory":"Massage",
            "type":"Services"
        }
    ],
    "sg:phone":"+1 858 361 5096",
    "sg:postcode":"92024",
    "sg:province":"CA",
    "sg:website":"www.massagebywendy.com",
    "wof:name":"Massage by Wendy",
    "wof:placetype":"venue"
},
  "geometry": {"coordinates":[-117.300572,33.062034],"type":"Point"}
}