{
  "type": "Feature",
  "properties": {
    "addr:full":"1040 N Hollywood Way Burbank CA 91505",
    "addr:housenumber":"1040",
    "addr:postcode":"91505",
    "addr:street":"N Hollywood Way",
    "iso:country":"US",
    "sg:address":"1040 N Hollywood Way",
    "sg:city":"Burbank",
    "sg:classifiers":[
        {
            "category":"Personal",
            "subcategory":"Nail Salon",
            "type":"Services"
        }
    ],
    "sg:phone":"+1 818 840 0242",
    "sg:postcode":"91505",
    "sg:province":"CA",
    "wof:name":"Tulip Nails",
    "wof:placetype":"venue"
},
  "geometry": {"coordinates":[-118.34699999999999,34.169201],"type":"Point"}
}