{
  "type": "Feature",
  "properties": {
    "addr:full":"2055 Gateway Place Suite 400 San Jose CA 95110",
    "addr:housenumber":"2055",
    "addr:postcode":"95110",
    "addr:street":"Gateway Place Suite 400",
    "iso:country":"US",
    "sg:address":"2055 Gateway Place Suite 400",
    "sg:city":"San Jose",
    "sg:classifiers":[
        {
            "category":"Professional",
            "subcategory":"Lawyer & Legal Services",
            "type":"Services"
        }
    ],
    "sg:phone":"+1 408 467 3808",
    "sg:postcode":"95110",
    "sg:province":"CA",
    "wof:name":"The Kline Law Firm PC",
    "wof:placetype":"venue"
},
  "geometry": {"coordinates":[-121.923849,37.371169],"type":"Point"}
}