{
  "type": "Feature",
  "properties": {
    "iso:country":"US",
    "sg:address":"12215 Ventura Blvd",
    "sg:city":"Studio City",
    "sg:classifiers":[
        {
            "category":"Sports & Exercise",
            "subcategory":"Gym",
            "type":"Entertainment"
        }
    ],
    "sg:phone":"+1 818 209 2870",
    "sg:postcode":"91604",
    "sg:province":"CA",
    "sg:tags":[
        "trainer"
    ],
    "sg:website":"www.fitnessdoc.com/",
    "wof:name":"Fitness Doc Personal Training, Jennifer Felch",
    "wof:placetype":"venue"
},
  "geometry": {"coordinates":[-118.39911600000001,34.143355],"type":"Point"}
}