{
  "type": "Feature",
  "properties": {
    "addr:full":"2171 E 25th Street Los Angeles CA 90058",
    "addr:housenumber":"2171",
    "addr:postcode":"90058",
    "addr:street":"E 25Th Street",
    "iso:country":"US",
    "sg:address":"2171 E 25th Street",
    "sg:city":"Los Angeles",
    "sg:classifiers":[
        {
            "category":"Shopping",
            "subcategory":"Clothing, Apparel, & Fashions",
            "type":"Retail Goods"
        }
    ],
    "sg:phone":"+1 323 583 3033",
    "sg:postcode":"90058",
    "sg:province":"CA",
    "sg:tags":[
        "accessory",
        "clothing",
        "women's"
    ],
    "wof:name":"Piano",
    "wof:placetype":"venue"
},
  "geometry": {"coordinates":[-118.23129,34.014934],"type":"Point"}
}