{
  "type": "Feature",
  "properties": {
    "iso:country":"US",
    "sg:address":"6769 Mallee St",
    "sg:city":"Carlsbad",
    "sg:classifiers":[
        {
            "category":"Shopping",
            "type":"Retail Goods"
        }
    ],
    "sg:phone":"+1 760 603 0727",
    "sg:postcode":"92011",
    "sg:province":"CA",
    "sg:tags":[
        "telephone",
        "cellular"
    ],
    "wof:name":"Cingular Wireless",
    "wof:placetype":"venue"
},
  "geometry": {"coordinates":[-117.280292,33.104341],"type":"Point"}
}