{
  "type": "Feature",
  "properties": {
    "addr:full":"8138 S Gate Ave South Gate CA 90280",
    "addr:housenumber":"8138",
    "addr:postcode":"90280",
    "addr:street":"S Gate Ave;Gate",
    "iso:country":"US",
    "sg:address":"8138 S Gate Ave",
    "sg:city":"South Gate",
    "sg:classifiers":[
        {
            "category":"Shopping",
            "subcategory":"Bicycles & Sporting Goods",
            "type":"Retail Goods"
        }
    ],
    "sg:phone":"+1 323 587 0490",
    "sg:postcode":"90280",
    "sg:province":"CA",
    "wof:name":"H P Sporting Goods",
    "wof:placetype":"venue"
},
  "geometry": {"coordinates":[-118.21347799999999,33.9613],"type":"Point"}
}