{
  "type": "Feature",
  "properties": {
    "addr:full":"8410 W 3rd St Los Angeles CA 90048",
    "addr:housenumber":"8410",
    "addr:postcode":"90048",
    "addr:street":"W 3Rd St",
    "iso:country":"US",
    "sg:address":"8410 W 3rd St",
    "sg:city":"Los Angeles",
    "sg:classifiers":[
        {
            "category":"Shopping",
            "subcategory":"Musical Instruments",
            "type":"Retail Goods"
        }
    ],
    "sg:phone":"+1 323 651 2020",
    "sg:postcode":"90048",
    "sg:province":"CA",
    "wof:name":"Geisler Music",
    "wof:placetype":"venue"
},
  "geometry": {"coordinates":[-118.373895,34.073012],"type":"Point"}
}