{
  "type": "Feature",
  "properties": {
    "iso:country":"US",
    "sg:address":"44 Montgomery Street Suite 2080",
    "sg:city":"San Francisco",
    "sg:classifiers":[
        {
            "category":"Professional",
            "subcategory":"Lawyer & Legal Services",
            "type":"Services"
        }
    ],
    "sg:phone":"+1 415 362 6252",
    "sg:postcode":"94104",
    "sg:province":"CA",
    "wof:name":"Sugarman & Cannon",
    "wof:placetype":"venue"
},
  "geometry": {"coordinates":[-122.402,37.7896],"type":"Point"}
}