{
  "type": "Feature",
  "properties": {
    "addr:full":"3443 Main St Chula Vista CA 91911",
    "addr:housenumber":"3443",
    "addr:postcode":"91911",
    "addr:street":"Main St",
    "iso:country":"US",
    "sg:address":"3443 Main St",
    "sg:city":"Chula Vista",
    "sg:classifiers":[
        {
            "category":"Freight",
            "type":"Transportation"
        }
    ],
    "sg:phone":"+1 619 426 5348",
    "sg:postcode":"91911",
    "sg:province":"CA",
    "sg:tags":[
        "operator",
        "trucking"
    ],
    "wof:name":"E-Z Way Transport",
    "wof:placetype":"venue"
},
  "geometry": {"coordinates":[-117.05895,32.59466],"type":"Point"}
}