{
  "type": "Feature",
  "properties": {
    "addr:full":"9248 Westminster Blvd Westminster CA 92683",
    "addr:housenumber":"9248",
    "addr:postcode":"92683",
    "addr:street":"Westminster Blvd",
    "iso:country":"US",
    "sg:address":"9248 Westminster Blvd",
    "sg:city":"Westminster",
    "sg:classifiers":[
        {
            "category":"Food & Beverages",
            "subcategory":"Candy",
            "type":"Retail Goods"
        }
    ],
    "sg:phone":"+1 714 903 2571",
    "sg:postcode":"92683",
    "sg:province":"CA",
    "sg:tags":[
        "dessert"
    ],
    "wof:name":"Yogurt Delights",
    "wof:placetype":"venue"
},
  "geometry": {"coordinates":[-117.981094,33.759269],"type":"Point"}
}