{
  "type": "Feature",
  "properties": {
    "iso:country":"US",
    "sg:address":"1812 Dwight Way",
    "sg:city":"Berkeley",
    "sg:classifiers":[
        {
            "category":"Organizations",
            "subcategory":"Professional Association",
            "type":"Services"
        }
    ],
    "sg:phone":"+1 510 843 1506",
    "sg:postcode":"94703",
    "sg:province":"CA",
    "wof:name":"Dwight Place Home Owners Assn",
    "wof:placetype":"venue"
},
  "geometry": {"coordinates":[-122.273911,37.863038],"type":"Point"}
}