{
  "type": "Feature",
  "properties": {
    "iso:country":"US",
    "sg:address":"715 Silver Spur Road Suite 102",
    "sg:city":"Rolling Hills Estate",
    "sg:classifiers":[
        {
            "category":"Personal",
            "subcategory":"Nail Salon",
            "type":"Services"
        }
    ],
    "sg:phone":"+1 310 541 1156",
    "sg:postcode":"90274",
    "sg:province":"CA",
    "wof:name":"Nail Boutique",
    "wof:placetype":"venue"
},
  "geometry": {"coordinates":[-118.369556,33.770753],"type":"Point"}
}