{
  "type": "Feature",
  "properties": {
    "addr:full":"29018 Arrowhead Ave Barstow CA 92311",
    "addr:housenumber":"29018",
    "addr:postcode":"92311",
    "addr:street":"Arrowhead Ave",
    "iso:country":"US",
    "sg:address":"29018 Arrowhead Ave",
    "sg:city":"Barstow",
    "sg:classifiers":[
        {
            "category":"Building & Trades",
            "subcategory":"Construction",
            "type":"Services"
        }
    ],
    "sg:phone":"+1 760 256 9396",
    "sg:postcode":"92311",
    "sg:province":"CA",
    "sg:tags":[
        "contractor"
    ],
    "wof:name":"Louise Miller",
    "wof:placetype":"venue"
},
  "geometry": {"coordinates":[-117.02621499999999,34.913583],"type":"Point"}
}