{
  "type": "Feature",
  "properties": {
    "iso:country":"US",
    "sg:address":"1173 Fremont Blvd Ste B",
    "sg:city":"Seaside",
    "sg:classifiers":[
        {
            "category":"Health Services",
            "subcategory":"Clinic",
            "type":"Services"
        },
        {
            "category":"Health Services",
            "subcategory":"Medical Lab",
            "type":"Services"
        }
    ],
    "sg:phone":"+1 877 312 7315",
    "sg:postcode":"93955",
    "sg:province":"CA",
    "sg:tags":[
        "information",
        "aid",
        "welfare"
    ],
    "sg:website":"http://national.citysearch.com/profile/external/603805142/seaside_ca/std_test_express_seaside.html?publisher=yellowpages&reference_id=1&placement=ypwebsitemip",
    "wof:name":"STD Test Express Seaside",
    "wof:placetype":"venue"
},
  "geometry": {"coordinates":[-121.849109,36.601998],"type":"Point"}
}