{
  "type": "Feature",
  "properties": {
    "addr:full":"8181 Mission Gorge Rd Ste H San Diego CA 92120",
    "addr:housenumber":"8181",
    "addr:postcode":"92120",
    "addr:street":"Mission Gorge Rd Ste H",
    "iso:country":"US",
    "sg:address":"8181 Mission Gorge Rd Ste H",
    "sg:city":"San Diego",
    "sg:classifiers":[
        {
            "category":"Shopping",
            "subcategory":"Pets & Pet Supplies",
            "type":"Retail Goods"
        }
    ],
    "sg:phone":"+1 619 265 7422",
    "sg:postcode":"92120",
    "sg:province":"CA",
    "sg:tags":[
        "groomers"
    ],
    "sg:website":"www.priscillasgrooming.com/",
    "wof:name":"Priscilla's Grooming",
    "wof:placetype":"venue"
},
  "geometry": {"coordinates":[-117.060019,32.816558],"type":"Point"}
}