{
  "type": "Feature",
  "properties": {
    "addr:full":"275 Aptos Beach Dr Aptos CA 95003",
    "addr:housenumber":"275",
    "addr:postcode":"ca 95003",
    "addr:street":"Beach Dr",
    "iso:country":"US",
    "sg:address":"275 Aptos Beach Dr",
    "sg:city":"Aptos",
    "sg:classifiers":[
        {
            "category":"Insurance",
            "subcategory":"Insurance Agent",
            "type":"Services"
        }
    ],
    "sg:phone":"+1 831 662 0597",
    "sg:postcode":"95003",
    "sg:province":"CA",
    "wof:name":"Farmers Insurance Group",
    "wof:placetype":"venue"
},
  "geometry": {"coordinates":[-121.897763,36.972494],"type":"Point"}
}