{
  "type": "Feature",
  "properties": {
    "addr:full":"201 Nevada St Auburn CA 95603",
    "addr:housenumber":"201",
    "addr:postcode":"ca 95603",
    "addr:street":"Nevada St",
    "iso:country":"US",
    "sg:address":"201 Nevada St",
    "sg:city":"Auburn",
    "sg:classifiers":[
        {
            "category":"Building & Trades",
            "subcategory":"Plumbing",
            "type":"Services"
        }
    ],
    "sg:phone":"+1 530 878 1836",
    "sg:postcode":"95603",
    "sg:province":"CA",
    "sg:tags":[
        "conditioning",
        "air",
        "system",
        "contractor"
    ],
    "wof:name":"Refrigeration & Equip Svc",
    "wof:placetype":"venue"
},
  "geometry": {"coordinates":[-121.081418,38.900515],"type":"Point"}
}