{
  "type": "Feature",
  "properties": {
    "addr:full":"3088 24th Street San Francisco CA 94110",
    "addr:housenumber":"3088",
    "addr:postcode":"94110",
    "addr:street":"24Th Street",
    "iso:country":"US",
    "sg:address":"3088 24th Street",
    "sg:city":"San Francisco",
    "sg:classifiers":[
        {
            "category":"Bars & Pubs",
            "type":"Food & Drink"
        }
    ],
    "sg:postcode":"94110",
    "sg:province":"CA",
    "wof:name":"El Mexicano",
    "wof:placetype":"venue"
},
  "geometry": {"coordinates":[-122.413791,37.752707],"type":"Point"}
}