{
  "type": "Feature",
  "properties": {
    "addr:full":"6535 Caballero Blvd Buena Park CA 90620",
    "addr:housenumber":"6535",
    "addr:postcode":"90620",
    "addr:street":"Caballero Blvd",
    "iso:country":"US",
    "sg:address":"6535 Caballero Blvd",
    "sg:city":"Buena Park",
    "sg:classifiers":[
        {
            "category":"Restaurant",
            "type":"Food & Drink"
        },
        {
            "category":"Social Services",
            "subcategory":"Retirement Home",
            "type":"Services"
        }
    ],
    "sg:phone":"+1 626 960 2800",
    "sg:postcode":"90620",
    "sg:province":"CA",
    "sg:tags":[
        "mexican"
    ],
    "wof:name":"Senor Felixs Gourmet Mexican Food",
    "wof:placetype":"venue"
},
  "geometry": {"coordinates":[-118.019997,33.865898],"type":"Point"}
}