{
  "type": "Feature",
  "properties": {
    "addr:full":"441 S Clovercrest Ln San Ramon CA 94582",
    "addr:housenumber":"441",
    "addr:postcode":"94582",
    "addr:street":"S Clovercrest Ln",
    "iso:country":"US",
    "sg:address":"441 S Clovercrest Ln",
    "sg:city":"San Ramon",
    "sg:classifiers":[
        {
            "category":"Building & Trades",
            "subcategory":"Construction",
            "type":"Services"
        }
    ],
    "sg:phone":"+1 925 736 3801",
    "sg:postcode":"94582",
    "sg:province":"CA",
    "sg:tags":[
        "contractor"
    ],
    "wof:name":"V2k The Vrtual Win Fashion Str",
    "wof:placetype":"venue"
},
  "geometry": {"coordinates":[-116.97654900000001,33.031572],"type":"Point"}
}