{
  "type": "Feature",
  "properties": {
    "iso:country":"US",
    "sg:address":"5663 Case Ave",
    "sg:city":"North Hollywood",
    "sg:classifiers":[
        {
            "category":"Building & Trades",
            "subcategory":"Electrical",
            "type":"Services"
        }
    ],
    "sg:phone":"+1 818 760 1177",
    "sg:postcode":"91601",
    "sg:province":"CA",
    "sg:tags":[
        "electric",
        "contractor"
    ],
    "wof:name":"Sosa Electric",
    "wof:placetype":"venue"
},
  "geometry": {"coordinates":[-118.372007,34.174652],"type":"Point"}
}