{
  "type": "Feature",
  "properties": {
    "iso:country":"US",
    "sg:address":"3971 Irvine Blvd Ste 110",
    "sg:city":"Irvine",
    "sg:classifiers":[
        {
            "category":"Health Services",
            "subcategory":"Optometrist",
            "type":"Services"
        },
        {
            "category":"Shopping",
            "subcategory":"Optician",
            "type":"Retail Goods"
        },
        {
            "category":"Health Services",
            "subcategory":"Doctor",
            "type":"Services"
        }
    ],
    "sg:phone":"+1 714 505 0555",
    "sg:postcode":"92620",
    "sg:province":"CA",
    "sg:tags":[
        "eyewear"
    ],
    "sg:website":"www.npoptometry.com",
    "wof:name":"Northpark Optometry",
    "wof:placetype":"venue"
},
  "geometry": {"coordinates":[-117.771592,33.72293],"type":"Point"}
}