{
  "type": "Feature",
  "properties": {
    "iso:country":"US",
    "sg:address":"1401 Bailey Ave",
    "sg:city":"Needles",
    "sg:classifiers":[
        {
            "category":"Health Services",
            "subcategory":"Doctor",
            "type":"Services"
        }
    ],
    "sg:phone":"+1 760 326 5614",
    "sg:postcode":"92363",
    "sg:province":"CA",
    "sg:tags":[
        "physician",
        "family",
        "practice",
        "surgeons",
        "medicine"
    ],
    "wof:name":"K Cunningham",
    "wof:placetype":"venue"
},
  "geometry": {"coordinates":[-114.618317,34.832969],"type":"Point"}
}