{
  "type": "Feature",
  "properties": {
    "addr:full":"1811 Morton Ave Los Angeles CA 90026",
    "addr:housenumber":"1811",
    "addr:postcode":"90026",
    "addr:street":"Morton Ave",
    "iso:country":"US",
    "sg:address":"1811 Morton Ave",
    "sg:city":"Los Angeles",
    "sg:classifiers":[
        {
            "category":"Real Estate",
            "subcategory":"Real Estate Operator",
            "type":"Services"
        }
    ],
    "sg:phone":"+1 213 250 3704",
    "sg:postcode":"90026",
    "sg:province":"CA",
    "sg:tags":[
        "apartment"
    ],
    "wof:name":"Morton Garden Apartments",
    "wof:placetype":"venue"
},
  "geometry": {"coordinates":[-118.249644,34.085005],"type":"Point"}
}