{
  "type": "Feature",
  "properties": {
    "iso:country":"US",
    "sg:address":"6027 Etiwanda Ave",
    "sg:city":"Tarzana",
    "sg:classifiers":[
        {
            "category":"Shopping",
            "subcategory":"Bicycles & Sporting Goods",
            "type":"Retail Goods"
        }
    ],
    "sg:phone":"+1 818 996 9490",
    "sg:postcode":"91356",
    "sg:province":"CA",
    "wof:name":"Barry Kay Enterprises",
    "wof:placetype":"venue"
},
  "geometry": {"coordinates":[-118.53089900000001,34.178456],"type":"Point"}
}