{
  "type": "Feature",
  "properties": {
    "addr:full":"510 31st St Ste D Newport Beach CA 92663",
    "addr:housenumber":"510",
    "addr:postcode":"92663",
    "addr:street":"31St St Ste D",
    "iso:country":"US",
    "sg:address":"510 31st St Ste D",
    "sg:city":"Newport Beach",
    "sg:classifiers":[
        {
            "category":"Personal",
            "type":"Services"
        }
    ],
    "sg:phone":"+1 949 642 0044",
    "sg:postcode":"92663",
    "sg:province":"CA",
    "sg:tags":[
        "local"
    ],
    "sg:website":"www.socalsweeping.com",
    "wof:name":"So Cal Sweeping",
    "wof:placetype":"venue"
},
  "geometry": {"coordinates":[-117.928038,33.615136],"type":"Point"}
}