{
  "type": "Feature",
  "properties": {
    "addr:full":"1310 Petaluma Hill Rd Santa Rosa CA 95404",
    "addr:housenumber":"1310",
    "addr:postcode":"95404",
    "addr:street":"Petaluma Hill Rd",
    "iso:country":"US",
    "sg:address":"1310 Petaluma Hill Rd",
    "sg:city":"Santa Rosa",
    "sg:classifiers":[
        {
            "category":"Restaurant",
            "type":"Food & Drink"
        }
    ],
    "sg:phone":"+1 707 545 5158",
    "sg:postcode":"95404",
    "sg:province":"CA",
    "wof:name":"Mi Rancho Restaurante",
    "wof:placetype":"venue"
},
  "geometry": {"coordinates":[-122.70866700000001,38.424863],"type":"Point"}
}