{
  "type": "Feature",
  "properties": {
    "iso:country":"US",
    "sg:address":"1310 Petaluma Hill Rd",
    "sg:city":"Santa Rosa",
    "sg:classifiers":[
        {
            "category":"Restaurant",
            "type":"Food & Drink"
        }
    ],
    "sg:phone":"+1 707 545 5158",
    "sg:postcode":"95404",
    "sg:province":"CA",
    "wof:name":"Mi Rancho Restaurante",
    "wof:placetype":"venue"
},
  "geometry": {"coordinates":[-122.708667,38.424863],"type":"Point"}
}