{
  "type": "Feature",
  "properties": {
    "iso:country":"US",
    "sg:address":"100 Drumm St",
    "sg:city":"San Francisco",
    "sg:classifiers":[
        {
            "category":"Banks & Credit Unions",
            "subcategory":"Investment Brokerage",
            "type":"Services"
        }
    ],
    "sg:phone":"+1 415 954 5400",
    "sg:postcode":"94111",
    "sg:province":"CA",
    "sg:tags":[
        "management"
    ],
    "wof:name":"RCM",
    "wof:placetype":"venue"
},
  "geometry": {"coordinates":[-122.3966,37.794653],"type":"Point"}
}