{
  "type": "Feature",
  "properties": {
    "addr:full":"7040 W Sunset Blvd Los Angeles CA 90028",
    "addr:housenumber":"7040",
    "addr:postcode":"90028",
    "addr:street":"W Sunset Blvd",
    "iso:country":"US",
    "sg:address":"7040 W Sunset Blvd",
    "sg:city":"Los Angeles",
    "sg:classifiers":[
        {
            "category":"Arts & Performance",
            "subcategory":"Theater",
            "type":"Entertainment"
        }
    ],
    "sg:phone":"+1 323 890 1969",
    "sg:postcode":"90028",
    "sg:province":"CA",
    "sg:tags":[
        "bureau"
    ],
    "wof:name":"Three Moons Entertainment",
    "wof:placetype":"venue"
},
  "geometry": {"coordinates":[-118.34392200000001,34.097888],"type":"Point"}
}