{
  "type": "Feature",
  "properties": {
    "iso:country":"US",
    "sg:address":"3201 Canterbury Ct",
    "sg:city":"Modesto",
    "sg:classifiers":[
        {
            "category":"Social Services",
            "type":"Services"
        },
        {
            "category":"Professional",
            "subcategory":"Employment Agencies",
            "type":"Services"
        }
    ],
    "sg:phone":"+1 209 578 1448",
    "sg:postcode":"95350",
    "sg:province":"CA",
    "sg:tags":[
        "workers'",
        "placement",
        "volunteer"
    ],
    "sg:website":"http://www.pnwkiwanis.org",
    "wof:name":"North Modesto Kiwanis Club",
    "wof:placetype":"venue"
},
  "geometry": {"coordinates":[-120.992104,37.685009],"type":"Point"}
}