{
  "type": "Feature",
  "properties": {
    "iso:country":"US",
    "sg:address":"1844 Divisadero St",
    "sg:city":"San Francisco",
    "sg:classifiers":[
        {
            "category":"Health Services",
            "subcategory":"Optometrist",
            "type":"Services"
        }
    ],
    "sg:phone":"+1 415 409 0888",
    "sg:postcode":"94115",
    "sg:province":"CA",
    "sg:tags":[
        "ophthalmologist"
    ],
    "sg:website":"www.dramythich.com",
    "wof:name":"AccuVision Optometry",
    "wof:placetype":"venue"
},
  "geometry": {"coordinates":[-122.440078,37.786849],"type":"Point"}
}