{
  "type": "Feature",
  "properties": {
    "iso:country":"US",
    "sg:address":"2809 Bechelli Ln",
    "sg:city":"Redding",
    "sg:classifiers":[
        {
            "category":"Health Services",
            "subcategory":"Doctor",
            "type":"Services"
        }
    ],
    "sg:phone":"+1 530 223 0441",
    "sg:postcode":"96002",
    "sg:province":"CA",
    "sg:tags":[
        "dentist"
    ],
    "wof:name":"Kenneth Hanson Inc",
    "wof:placetype":"venue"
},
  "geometry": {"coordinates":[-122.36247,40.563839],"type":"Point"}
}