{
  "type": "Feature",
  "properties": {
    "iso:country":"US",
    "sg:address":"6878 S Maple Ave",
    "sg:city":"Fresno",
    "sg:classifiers":[
        {
            "category":"Manufacturing",
            "subcategory":"Food",
            "type":"Manufacturing & Wholesale Goods"
        }
    ],
    "sg:phone":"+1 559 834 5064",
    "sg:postcode":"93725",
    "sg:province":"CA",
    "sg:tags":[
        "dehydrated",
        "farm",
        "grain",
        "cash",
        "mfg"
    ],
    "wof:name":"George Eskelsen",
    "wof:placetype":"venue"
},
  "geometry": {"coordinates":[-119.7457,36.639892],"type":"Point"}
}