{
  "type": "Feature",
  "properties": {
    "addr:full":"8610 Van Nuys Blvd Panorama City CA 91402",
    "addr:housenumber":"8610",
    "addr:postcode":"91402",
    "addr:street":"Van Nuys Blvd",
    "iso:country":"US",
    "sg:address":"8610 Van Nuys Blvd",
    "sg:city":"Panorama City",
    "sg:classifiers":[
        {
            "category":"Real Estate",
            "subcategory":"Real Estate Operator",
            "type":"Services"
        }
    ],
    "sg:phone":"+1 818 892 7816",
    "sg:postcode":"91402",
    "sg:province":"CA",
    "sg:tags":[
        "mall",
        "shopping",
        "center"
    ],
    "wof:name":"Plaza Del Valle",
    "wof:placetype":"venue"
},
  "geometry": {"coordinates":[-118.449022,34.225601],"type":"Point"}
}