{
  "type": "Feature",
  "properties": {
    "addr:full":"17752 Sky Park Cir Irvine CA 92614",
    "addr:housenumber":"17752",
    "addr:postcode":"92614",
    "addr:street":"Sky Park Cir",
    "iso:country":"US",
    "sg:address":"17752 Sky Park Cir",
    "sg:city":"Irvine",
    "sg:classifiers":[
        {
            "category":"Manufacturing",
            "subcategory":"Printing",
            "type":"Manufacturing & Wholesale Goods"
        }
    ],
    "sg:phone":"+1 949 756 2579",
    "sg:postcode":"92614",
    "sg:province":"CA",
    "sg:tags":[
        "publisher",
        "software"
    ],
    "wof:name":"Double Wide Software",
    "wof:placetype":"venue"
},
  "geometry": {"coordinates":[-117.85527,33.689285],"type":"Point"}
}