{
  "type": "Feature",
  "properties": {
    "iso:country":"US",
    "sg:address":"3464 Murphy Canyon Rd",
    "sg:city":"San Diego",
    "sg:classifiers":[
        {
            "category":"Retail",
            "subcategory":"Laundry & Dry Cleaning",
            "type":"Services"
        }
    ],
    "sg:phone":"+1 858 560 8522",
    "sg:postcode":"92123",
    "sg:province":"CA",
    "sg:tags":[
        "cleaner"
    ],
    "wof:name":"Mirage Cleaners",
    "wof:placetype":"venue"
},
  "geometry": {"coordinates":[-117.113998,32.8064],"type":"Point"}
}