{
  "type": "Feature",
  "properties": {
    "iso:country":"US",
    "sg:address":"34861 Yucaipa Blvd Ste C",
    "sg:city":"Yucaipa",
    "sg:phone":"+1 909 797 5505",
    "sg:postcode":"92399",
    "sg:province":"CA",
    "wof:name":"Custom Metal Fabrication",
    "wof:placetype":"venue"
},
  "geometry": {"coordinates":[-117.04402,34.033877],"type":"Point"}
}