{
  "type": "Feature",
  "properties": {
    "addr:full":"4763 Oakwood Ave Los Angeles CA 90004",
    "addr:housenumber":"4763",
    "addr:postcode":"90004",
    "addr:street":"Oakwood Ave",
    "iso:country":"US",
    "sg:address":"4763 Oakwood Ave",
    "sg:city":"Los Angeles",
    "sg:classifiers":[
        {
            "category":"Building & Trades",
            "subcategory":"Construction",
            "type":"Services"
        }
    ],
    "sg:phone":"+1 323 461 1547",
    "sg:postcode":"90004",
    "sg:province":"CA",
    "sg:tags":[
        "business",
        "contractor"
    ],
    "wof:name":"Sparkling Pools Service",
    "wof:placetype":"venue"
},
  "geometry": {"coordinates":[-118.310196,34.07735],"type":"Point"}
}