{
  "type": "Feature",
  "properties": {
    "addr:full":"1416 C St Livingston CA 95334",
    "addr:housenumber":"1416",
    "addr:postcode":"95334",
    "addr:street":"C St",
    "iso:country":"US",
    "sg:address":"1416 C St",
    "sg:city":"Livingston",
    "sg:classifiers":[
        {
            "category":"Government",
            "subcategory":"Office",
            "type":"Public Place"
        }
    ],
    "sg:phone":"+1 209 394 8041",
    "sg:postcode":"95334",
    "sg:province":"CA",
    "sg:tags":[
        "city"
    ],
    "sg:website":"www.livingstonca.org",
    "wof:name":"Livingston City Hall",
    "wof:placetype":"venue"
},
  "geometry": {"coordinates":[-120.723131,37.385055],"type":"Point"}
}