{
  "type": "Feature",
  "properties": {
    "iso:country":"US",
    "sg:address":"1115 W Main St",
    "sg:city":"Santa Maria",
    "sg:classifiers":[
        {
            "category":"Restaurant",
            "type":"Food & Drink"
        }
    ],
    "sg:phone":"+1 805 349 8111",
    "sg:postcode":"93458",
    "sg:province":"CA",
    "wof:name":"LA Villa",
    "wof:placetype":"venue"
},
  "geometry": {"coordinates":[-120.451787,34.953422],"type":"Point"}
}