{
  "type": "Feature",
  "properties": {
    "addr:full":"250 Casa Verde Way Monterey CA 93940",
    "addr:housenumber":"250",
    "addr:postcode":"93940",
    "addr:street":"Casa Verde Way",
    "iso:country":"US",
    "sg:address":"250 Casa Verde Way",
    "sg:city":"Monterey",
    "sg:classifiers":[
        {
            "category":"Food & Beverages",
            "subcategory":"Groceries & Convenience Stores",
            "type":"Retail Goods"
        }
    ],
    "sg:phone":"+1 831 372 6824",
    "sg:postcode":"93940",
    "sg:province":"CA",
    "sg:tags":[
        "grocer"
    ],
    "wof:name":"LA Sala's Bi-Rite Market",
    "wof:placetype":"venue"
},
  "geometry": {"coordinates":[-121.865635,36.599749],"type":"Point"}
}