{
  "type": "Feature",
  "properties": {
    "iso:country":"US",
    "sg:address":"839 2nd St # D",
    "sg:city":"Encinitas",
    "sg:classifiers":[
        {
            "category":"Real Estate",
            "subcategory":"Real Estate Services",
            "type":"Services"
        }
    ],
    "sg:phone":"+1 760 943 1170",
    "sg:postcode":"92024",
    "sg:province":"CA",
    "sg:tags":[
        "management",
        "property"
    ],
    "wof:name":"De La Torre Rentals",
    "wof:placetype":"venue"
},
  "geometry": {"coordinates":[-117.293999,33.041242],"type":"Point"}
}