{
  "type": "Feature",
  "properties": {
    "iso:country":"US",
    "sg:address":"4324 Chelsea Way",
    "sg:city":"Concord",
    "sg:classifiers":[
        {
            "category":"Local Transit",
            "type":"Transportation"
        }
    ],
    "sg:phone":"+1 925 685 1502",
    "sg:postcode":"94521",
    "sg:province":"CA",
    "sg:tags":[
        "passenger"
    ],
    "wof:name":"Baywide Livery LLC",
    "wof:placetype":"venue"
},
  "geometry": {"coordinates":[-121.997325,37.953933],"type":"Point"}
}