{
  "type": "Feature",
  "properties": {
    "iso:country":"US",
    "sg:address":"2630 Dixie St",
    "sg:city":"Rosamond",
    "sg:classifiers":[
        {
            "category":"Real Estate",
            "subcategory":"Real Estate Operator",
            "type":"Services"
        }
    ],
    "sg:phone":"+1 661 256 3495",
    "sg:postcode":"93560",
    "sg:province":"CA",
    "sg:tags":[
        "apartment"
    ],
    "wof:name":"Rosamond Village Apartments",
    "wof:placetype":"venue"
},
  "geometry": {"coordinates":[-118.16638399999999,34.858836],"type":"Point"}
}