{
  "type": "Feature",
  "properties": {
    "iso:country":"US",
    "sg:address":"14431 Ventura Blvd Ste 205",
    "sg:city":"Sherman Oaks",
    "sg:classifiers":[
        {
            "category":"Building & Trades",
            "subcategory":"Cleaning & Sanitation",
            "type":"Services"
        }
    ],
    "sg:phone":"+1 818 355 2962",
    "sg:postcode":"91423",
    "sg:province":"CA",
    "sg:tags":[
        "home"
    ],
    "wof:name":"Sylvia's Professional Cleaning",
    "wof:placetype":"venue"
},
  "geometry": {"coordinates":[-118.44765200000001,34.150733],"type":"Point"}
}