{
  "type": "Feature",
  "properties": {
    "iso:country":"US",
    "sg:address":"529 S Granada Ave",
    "sg:city":"Alhambra",
    "sg:classifiers":[
        {
            "category":"Wholesale",
            "subcategory":"Office Equipment",
            "type":"Manufacturing & Wholesale Goods"
        }
    ],
    "sg:phone":"+1 626 318 3018",
    "sg:postcode":"91801",
    "sg:province":"CA",
    "wof:name":"Snappy Copy Office Machines",
    "wof:placetype":"venue"
},
  "geometry": {"coordinates":[-118.11401499999999,34.093983],"type":"Point"}
}