{
  "type": "Feature",
  "properties": {
    "iso:country":"US",
    "sg:address":"102 E Main Street",
    "sg:city":"El Cajon",
    "sg:classifiers":[
        {
            "category":"Shopping",
            "subcategory":"Antiques",
            "type":"Retail Goods"
        }
    ],
    "sg:phone":"+1 619 312 2690",
    "sg:postcode":"92020",
    "sg:province":"CA",
    "sg:website":"shopthecornerstore.wordpress.com",
    "wof:name":"The Corner Store",
    "wof:placetype":"venue"
},
  "geometry": {"coordinates":[-116.96213299999999,32.795207],"type":"Point"}
}