{
  "type": "Feature",
  "properties": {
    "iso:country":"US",
    "sg:address":"2303 W Fremont St",
    "sg:city":"Stockton",
    "sg:classifiers":[
        {
            "category":"Restaurant",
            "type":"Food & Drink"
        }
    ],
    "sg:phone":"+1 209 462 0151",
    "sg:postcode":"95203",
    "sg:province":"CA",
    "wof:name":"Simoni's Cafe",
    "wof:placetype":"venue"
},
  "geometry": {"coordinates":[-121.32884199999999,37.955354],"type":"Point"}
}