{
  "type": "Feature",
  "properties": {
    "addr:full":"5225 Canyon Crest Dr Riverside CA 92507",
    "addr:housenumber":"5225",
    "addr:postcode":"92507",
    "addr:street":"Canyon Crest Dr",
    "iso:country":"US",
    "sg:address":"5225 Canyon Crest Dr",
    "sg:city":"Riverside",
    "sg:classifiers":[
        {
            "category":"Retail",
            "subcategory":"Repair Shop",
            "type":"Services"
        }
    ],
    "sg:phone":"+1 951 689 6100",
    "sg:postcode":"92507",
    "sg:province":"CA",
    "sg:tags":[
        "lock",
        "locksmith"
    ],
    "wof:name":"Don's Lock & Key",
    "wof:placetype":"venue"
},
  "geometry": {"coordinates":[-117.330217,33.957615],"type":"Point"}
}