{
  "type": "Feature",
  "properties": {
    "addr:full":"23430 Hawthorne Blvd Ste 110 Torrance CA 90505",
    "addr:housenumber":"23430",
    "addr:postcode":"90505",
    "addr:street":"Hawthorne Blvd Ste 110",
    "iso:country":"US",
    "sg:address":"23430 Hawthorne Blvd Ste 110",
    "sg:city":"Torrance",
    "sg:classifiers":[
        {
            "category":"Restaurant",
            "type":"Food & Drink"
        }
    ],
    "sg:phone":"+1 310 373 3555",
    "sg:postcode":"90505",
    "sg:province":"CA",
    "wof:name":"Skypark Cafe the",
    "wof:placetype":"venue"
},
  "geometry": {"coordinates":[-118.350998,33.813202],"type":"Point"}
}