{
  "type": "Feature",
  "properties": {
    "iso:country":"US",
    "sg:address":"17822 17th St",
    "sg:city":"Tustin",
    "sg:classifiers":[
        {
            "category":"Banks & Credit Unions",
            "subcategory":"Bank",
            "type":"Services"
        }
    ],
    "sg:phone":"+1 949 929 2400",
    "sg:postcode":"92780",
    "sg:province":"CA",
    "wof:name":"Colonial National Bancorp",
    "wof:placetype":"venue"
},
  "geometry": {"coordinates":[-117.821512,33.759679],"type":"Point"}
}