{
  "type": "Feature",
  "properties": {
    "iso:country":"US",
    "sg:address":"2005 W Hedges Ave",
    "sg:city":"Fresno",
    "sg:classifiers":[
        {
            "category":"Retail",
            "subcategory":"Auto Rental",
            "type":"Services"
        }
    ],
    "sg:phone":"+1 559 264 4625",
    "sg:postcode":"93728",
    "sg:province":"CA",
    "sg:tags":[
        "limousine"
    ],
    "wof:name":"Angel's Limousine",
    "wof:placetype":"venue"
},
  "geometry": {"coordinates":[-119.834611,36.759251],"type":"Point"}
}