{
  "type": "Feature",
  "properties": {
    "addr:full":"1115 S Prairie Ave Inglewood CA 90301",
    "addr:housenumber":"1115",
    "addr:postcode":"90301",
    "addr:street":"S Prairie Ave",
    "iso:country":"US",
    "sg:address":"1115 S Prairie Ave",
    "sg:city":"Inglewood",
    "sg:classifiers":[
        {
            "category":"Home & Garden",
            "subcategory":"Furniture",
            "type":"Retail Goods"
        }
    ],
    "sg:phone":"+1 310 671 6508",
    "sg:postcode":"90301",
    "sg:province":"CA",
    "sg:tags":[
        "mattress"
    ],
    "wof:name":"Mattress Moses Sleep Shop",
    "wof:placetype":"venue"
},
  "geometry": {"coordinates":[-118.343908,33.949072],"type":"Point"}
}