{
  "type": "Feature",
  "properties": {
    "iso:country":"US",
    "sg:address":"1069 7th St",
    "sg:city":"Wasco",
    "sg:classifiers":[
        {
            "category":"Real Estate",
            "subcategory":"Real Estate Agent",
            "type":"Services"
        }
    ],
    "sg:phone":"+1 661 758 6401",
    "sg:postcode":"93280",
    "sg:province":"CA",
    "wof:name":"Mc Guire Realty",
    "wof:placetype":"venue"
},
  "geometry": {"coordinates":[-119.33719600000001,35.594171],"type":"Point"}
}