{
  "type": "Feature",
  "properties": {
    "iso:country":"US",
    "sg:address":"1225 Venture Ln",
    "sg:city":"Turlock",
    "sg:classifiers":[
        {
            "category":"Farming",
            "subcategory":"Farm & Veterinary Services",
            "type":"Manufacturing & Wholesale Goods"
        }
    ],
    "sg:phone":"+1 209 667 8378",
    "sg:postcode":"95380",
    "sg:province":"CA",
    "sg:tags":[
        "breeder",
        "livestock"
    ],
    "wof:name":"All West/Select Sires",
    "wof:placetype":"venue"
},
  "geometry": {"coordinates":[-120.863106,37.478425],"type":"Point"}
}