{
  "type": "Feature",
  "properties": {
    "addr:full":"10 N Main St Milpitas CA 95035",
    "addr:housenumber":"10",
    "addr:postcode":"95035",
    "addr:street":"N Main St",
    "iso:country":"US",
    "sg:address":"10 N Main St",
    "sg:city":"Milpitas",
    "sg:classifiers":[
        {
            "category":"Autos & Motor Vehicles",
            "subcategory":"Fuel & Gas Station",
            "type":"Retail Goods"
        }
    ],
    "sg:phone":"+1 408 934 9656",
    "sg:postcode":"95035",
    "sg:province":"CA",
    "wof:name":"Main Street Gas",
    "wof:placetype":"venue"
},
  "geometry": {"coordinates":[-121.906998,37.431599],"type":"Point"}
}