{
  "type": "Feature",
  "properties": {
    "iso:country":"US",
    "sg:address":"40665 Winchester Rd",
    "sg:city":"Temecula",
    "sg:classifiers":[
        {
            "category":"Restaurant",
            "type":"Food & Drink"
        }
    ],
    "sg:phone":"+1 951 296 9400",
    "sg:postcode":"92591",
    "sg:province":"CA",
    "sg:tags":[
        "parlor",
        "ice",
        "cream"
    ],
    "wof:name":"Holy Cow Creamery",
    "wof:placetype":"venue"
},
  "geometry": {"coordinates":[-117.156567,33.527177],"type":"Point"}
}