{
  "type": "Feature",
  "properties": {
    "iso:country":"US",
    "sg:address":"12950 Main St",
    "sg:city":"Garden Grove",
    "sg:classifiers":[
        {
            "category":"Shopping",
            "subcategory":"Jewelry",
            "type":"Retail Goods"
        }
    ],
    "sg:phone":"+1 714 537 5625",
    "sg:postcode":"92840",
    "sg:province":"CA",
    "sg:website":"www.ttcollection.com",
    "wof:name":"T & T Collection",
    "wof:placetype":"venue"
},
  "geometry": {"coordinates":[-117.941002,33.777199],"type":"Point"}
}