{
  "type": "Feature",
  "properties": {
    "iso:country":"US",
    "sg:address":"3909 Bradshaw Road",
    "sg:city":"Sacramento",
    "sg:classifiers":[
        {
            "category":"Professional",
            "subcategory":"Management & Consulting",
            "type":"Services"
        },
        {
            "category":"Education",
            "subcategory":"Special Training",
            "type":"Public Place"
        },
        {
            "category":"Education",
            "subcategory":"Kindergarten",
            "type":"Public Place"
        },
        {
            "category":"Professional",
            "subcategory":"Business Services",
            "type":"Services"
        }
    ],
    "sg:phone":"+1 916 366 7233",
    "sg:postcode":"95827",
    "sg:province":"CA",
    "sg:tags":[
        "school",
        "coach",
        "driving",
        "consultant",
        "instruction",
        "safety",
        "aid",
        "first"
    ],
    "sg:website":"www.safetycenter.org",
    "wof:name":"Safety Center",
    "wof:placetype":"venue"
},
  "geometry": {"coordinates":[-121.336028,38.553145],"type":"Point"}
}