{
  "type": "Feature",
  "properties": {
    "addr:full":"1420 24th St Santa Monica CA 90404",
    "addr:housenumber":"1420",
    "addr:postcode":"90404",
    "addr:street":"24Th St",
    "iso:country":"US",
    "sg:address":"1420 24th St",
    "sg:city":"Santa Monica",
    "sg:classifiers":[
        {
            "category":"Shopping",
            "subcategory":"Bicycles & Sporting Goods",
            "type":"Retail Goods"
        }
    ],
    "sg:phone":"+1 310 829 5064",
    "sg:postcode":"90404",
    "sg:province":"CA",
    "wof:name":"Cycles Griffon",
    "wof:placetype":"venue"
},
  "geometry": {"coordinates":[-118.476237,34.031384],"type":"Point"}
}