{
  "type": "Feature",
  "properties": {
    "addr:full":"3224 Yorba Linda Blvd Fullerton CA 92831",
    "addr:housenumber":"3224",
    "addr:postcode":"92831",
    "addr:street":"Yorba Linda Blvd",
    "iso:country":"US",
    "sg:address":"3224 Yorba Linda Blvd",
    "sg:city":"Fullerton",
    "sg:classifiers":[
        {
            "category":"Retail",
            "subcategory":"Repair Shop",
            "type":"Services"
        }
    ],
    "sg:phone":"+1 888 878 7227",
    "sg:postcode":"92831",
    "sg:province":"CA",
    "sg:tags":[
        "fix-it"
    ],
    "wof:name":"Orange County Appliance Repair",
    "wof:placetype":"venue"
},
  "geometry": {"coordinates":[-117.869512,33.888723],"type":"Point"}
}