{
  "type": "Feature",
  "properties": {
    "addr:full":"17972 Sky Park Cir Irvine CA 92614",
    "addr:housenumber":"17972",
    "addr:postcode":"92614",
    "addr:street":"Sky Park Cir",
    "iso:country":"US",
    "sg:address":"17972 Sky Park Cir",
    "sg:city":"Irvine",
    "sg:classifiers":[
        {
            "category":"Professional",
            "subcategory":"Advertising",
            "type":"Services"
        }
    ],
    "sg:phone":"+1 949 260 1343",
    "sg:postcode":"92614",
    "sg:province":"CA",
    "sg:tags":[
        "counselor"
    ],
    "wof:name":"J R Mc Kee Group",
    "wof:placetype":"venue"
},
  "geometry": {"coordinates":[-117.85946199999999,33.689327],"type":"Point"}
}