{
  "type": "Feature",
  "properties": {
    "iso:country":"US",
    "sg:address":"9550 Flair Dr Ste 521",
    "sg:city":"El Monte",
    "sg:classifiers":[
        {
            "category":"Communications",
            "subcategory":"Television Station",
            "type":"Services"
        }
    ],
    "sg:phone":"+1 626 454 5935",
    "sg:postcode":"91731",
    "sg:province":"CA",
    "wof:name":"Ksci T V Station",
    "wof:placetype":"venue"
},
  "geometry": {"coordinates":[-118.060997,34.071999],"type":"Point"}
}