{
  "type": "Feature",
  "properties": {
    "iso:country":"US",
    "sg:address":"18381 Goldenwest St",
    "sg:city":"Huntington Beach",
    "sg:classifiers":[
        {
            "category":"Retail",
            "subcategory":"Animal Services",
            "type":"Services"
        }
    ],
    "sg:phone":"+1 714 847 5093",
    "sg:postcode":"92648",
    "sg:province":"CA",
    "wof:name":"Jacox Tracy",
    "wof:placetype":"venue"
},
  "geometry": {"coordinates":[-118.006468,33.694168],"type":"Point"}
}