{
  "type": "Feature",
  "properties": {
    "addr:full":"40713 Highway 41 Ste 5 Oakhurst CA 93644",
    "addr:housenumber":"40713",
    "addr:postcode":"93644",
    "addr:street":"Highway 41 Ste 5",
    "iso:country":"US",
    "sg:address":"40713 Highway 41 Ste 5",
    "sg:city":"Oakhurst",
    "sg:phone":"+1 559 642 4900",
    "sg:postcode":"93644",
    "sg:province":"CA",
    "wof:name":"Todd's Cookhouse Bar-B-Que",
    "wof:placetype":"venue"
},
  "geometry": {"coordinates":[-119.635023,37.363838],"type":"Point"}
}