{
  "type": "Feature",
  "properties": {
    "iso:country":"US",
    "sg:address":"1201 Alhambra Blvd",
    "sg:city":"Sacramento",
    "sg:classifiers":[
        {
            "category":"Health Services",
            "subcategory":"Clinic",
            "type":"Services"
        }
    ],
    "sg:phone":"+1 916 455 2229",
    "sg:postcode":"95816",
    "sg:province":"CA",
    "sg:tags":[
        "osteopathic"
    ],
    "wof:name":"Therese Rosellini Do",
    "wof:placetype":"venue"
},
  "geometry": {"coordinates":[-121.46618700000001,38.57058],"type":"Point"}
}