{
  "type": "Feature",
  "properties": {
    "addr:full":"920 Glenneyre St Laguna Beach CA 92651",
    "addr:housenumber":"920",
    "addr:postcode":"92651",
    "addr:street":"Glenneyre St",
    "iso:country":"US",
    "sg:address":"920 Glenneyre St",
    "sg:city":"Laguna Beach",
    "sg:classifiers":[
        {
            "category":"Professional",
            "subcategory":"Management & Consulting",
            "type":"Services"
        }
    ],
    "sg:phone":"+1 949 494 4553",
    "sg:postcode":"92651",
    "sg:province":"CA",
    "sg:tags":[
        "consultant",
        "business"
    ],
    "wof:name":"Rosenberg Group",
    "wof:placetype":"venue"
},
  "geometry": {"coordinates":[-117.776901,33.535656],"type":"Point"}
}