{
  "type": "Feature",
  "properties": {
    "iso:country":"US",
    "sg:address":"4727 Golf View Ct",
    "sg:city":"Santa Rosa",
    "sg:classifiers":[
        {
            "category":"Building & Trades",
            "subcategory":"Landscaping Services",
            "type":"Services"
        }
    ],
    "sg:phone":"+1 707 579 3716",
    "sg:postcode":"95405",
    "sg:province":"CA",
    "sg:tags":[
        "designer",
        "landscape"
    ],
    "wof:name":"California Land Art",
    "wof:placetype":"venue"
},
  "geometry": {"coordinates":[-122.654556,38.425711],"type":"Point"}
}