{
  "type": "Feature",
  "properties": {
    "iso:country":"US",
    "sg:address":"3980 Skylark Rd",
    "sg:city":"Santa Ynez",
    "sg:classifiers":[
        {
            "category":"Professional",
            "type":"Services"
        }
    ],
    "sg:phone":"+1 805 686 9779",
    "sg:postcode":"93460",
    "sg:province":"CA",
    "sg:tags":[
        "establishment"
    ],
    "wof:name":"Sharp Precision",
    "wof:placetype":"venue"
},
  "geometry": {"coordinates":[-120.066784,34.594193],"type":"Point"}
}