{
  "type": "Feature",
  "properties": {
    "addr:full":"17901 Lyons Valley Rd Jamul CA 91935",
    "addr:housenumber":"17901",
    "addr:postcode":"91935",
    "addr:street":"Lyons Valley Rd",
    "iso:country":"US",
    "sg:address":"17901 Lyons Valley Rd",
    "sg:city":"Jamul",
    "sg:classifiers":[
        {
            "category":"Building & Trades",
            "subcategory":"Electrical",
            "type":"Services"
        }
    ],
    "sg:phone":"+1 619 468 3677",
    "sg:postcode":"91935",
    "sg:province":"CA",
    "sg:tags":[
        "electrician"
    ],
    "wof:name":"Jcj Electric",
    "wof:placetype":"venue"
},
  "geometry": {"coordinates":[-116.76028100000001,32.713889],"type":"Point"}
}