{
  "type": "Feature",
  "properties": {
    "iso:country":"US",
    "sg:address":"153 Mercury Cir",
    "sg:city":"Pomona",
    "sg:classifiers":[
        {
            "category":"Freight",
            "type":"Transportation"
        }
    ],
    "sg:phone":"+1 909 468 3866",
    "sg:postcode":"91768",
    "sg:province":"CA",
    "sg:tags":[
        "arrangement"
    ],
    "wof:name":"HSD Bloom",
    "wof:placetype":"venue"
},
  "geometry": {"coordinates":[-117.800954,34.055581],"type":"Point"}
}