{
  "type": "Feature",
  "properties": {
    "addr:full":"709 Sycamore Ave Glendora CA 91741",
    "addr:housenumber":"709",
    "addr:postcode":"91741",
    "addr:street":"Sycamore Ave",
    "iso:country":"US",
    "sg:address":"709 Sycamore Ave",
    "sg:city":"Glendora",
    "sg:classifiers":[
        {
            "category":"Professional",
            "subcategory":"Computer Services",
            "type":"Services"
        }
    ],
    "sg:phone":"+1 626 857 3558",
    "sg:postcode":"91741",
    "sg:province":"CA",
    "sg:tags":[
        "related"
    ],
    "wof:name":"Computer Sciences Corporation",
    "wof:placetype":"venue"
},
  "geometry": {"coordinates":[-117.857277,34.13519],"type":"Point"}
}