{
  "type": "Feature",
  "properties": {
    "iso:country":"US",
    "sg:address":"229 Fallbrook Ave",
    "sg:city":"Newbury Park",
    "sg:classifiers":[
        {
            "category":"Professional",
            "subcategory":"Employment Agencies",
            "type":"Services"
        }
    ],
    "sg:phone":"+1 805 375 6367",
    "sg:postcode":"91320",
    "sg:province":"CA",
    "sg:tags":[
        "consultant",
        "search",
        "executive"
    ],
    "wof:name":"Executive Resources",
    "wof:placetype":"venue"
},
  "geometry": {"coordinates":[-118.955294,34.175681],"type":"Point"}
}