{
  "type": "Feature",
  "properties": {
    "addr:full":"900 Lincoln Ave San Jose CA 95126",
    "addr:housenumber":"900",
    "addr:postcode":"95126",
    "addr:street":"Lincoln Ave",
    "iso:country":"US",
    "sg:address":"900 Lincoln Ave",
    "sg:city":"San Jose",
    "sg:classifiers":[
        {
            "category":"Freight",
            "type":"Transportation"
        }
    ],
    "sg:phone":"+1 408 297 9051",
    "sg:postcode":"95126",
    "sg:province":"CA",
    "sg:tags":[
        "beverage",
        "alcoholic"
    ],
    "wof:name":"Paul Runberg",
    "wof:placetype":"venue"
},
  "geometry": {"coordinates":[-121.904467,37.312915],"type":"Point"}
}