{
  "type": "Feature",
  "properties": {
    "iso:country":"US",
    "sg:address":"1810 13th St",
    "sg:city":"Reedley",
    "sg:classifiers":[
        {
            "category":"Professional",
            "type":"Services"
        }
    ],
    "sg:phone":"+1 559 638 9740",
    "sg:postcode":"93654",
    "sg:province":"CA",
    "wof:name":"Moreno Motors",
    "wof:placetype":"venue"
},
  "geometry": {"coordinates":[-119.45003199999999,36.593444],"type":"Point"}
}