{
  "type": "Feature",
  "properties": {
    "iso:country":"US",
    "sg:address":"7111 Winnetka Ave",
    "sg:city":"Canoga Park",
    "sg:classifiers":[
        {
            "category":"Community Center",
            "type":"Public Place"
        }
    ],
    "sg:phone":"+1 818 347 4215",
    "sg:postcode":"91306",
    "sg:province":"CA",
    "sg:tags":[
        "medical"
    ],
    "wof:name":"Canaoga Park Discount",
    "wof:placetype":"venue"
},
  "geometry": {"coordinates":[-118.571155,34.199421],"type":"Point"}
}