{
  "type": "Feature",
  "properties": {
    "addr:full":"18252 Sherman Way Reseda CA 91335",
    "addr:housenumber":"18252",
    "addr:postcode":"91335",
    "addr:street":"Sherman Way",
    "iso:country":"US",
    "sg:address":"18252 Sherman Way",
    "sg:city":"Reseda",
    "sg:classifiers":[
        {
            "category":"Retail",
            "subcategory":"Repair Shop",
            "type":"Services"
        }
    ],
    "sg:phone":"+1 818 705 1255",
    "sg:postcode":"91335",
    "sg:province":"CA",
    "sg:tags":[
        "equipment",
        "laundry"
    ],
    "wof:name":"Laundry Center",
    "wof:placetype":"venue"
},
  "geometry": {"coordinates":[-118.52891099999999,34.200933],"type":"Point"}
}