{
  "type": "Feature",
  "properties": {
    "addr:full":"5914 Summer Country Dr Bakersfield CA 93313",
    "addr:housenumber":"5914",
    "addr:postcode":"93313",
    "addr:street":"Summer Country Dr",
    "iso:country":"US",
    "sg:address":"5914 Summer Country Dr",
    "sg:city":"Bakersfield",
    "sg:classifiers":[
        {
            "category":"Social Services",
            "type":"Services"
        }
    ],
    "sg:phone":"+1 661 396 9766",
    "sg:postcode":"93313",
    "sg:province":"CA",
    "sg:tags":[
        "program",
        "services-information",
        "referral"
    ],
    "wof:name":"Bass Developmental L L C",
    "wof:placetype":"venue"
},
  "geometry": {"coordinates":[-119.069112,35.300379],"type":"Point"}
}