{
  "type": "Feature",
  "properties": {
    "iso:country":"US",
    "sg:address":"1516 Oak Street Ste.208",
    "sg:city":"Alameda",
    "sg:classifiers":[
        {
            "category":"Insurance",
            "subcategory":"Hazard Insurance",
            "type":"Services"
        }
    ],
    "sg:phone":"+1 510 814 0572",
    "sg:postcode":"94501",
    "sg:province":"CA",
    "sg:website":"www.hartmaninsurance.com",
    "wof:name":"Hartman Insurance Services",
    "wof:placetype":"venue"
},
  "geometry": {"coordinates":[-122.24259600000001,37.766509],"type":"Point"}
}