{
  "type": "Feature",
  "properties": {
    "iso:country":"US",
    "sg:address":"18561 Parthenia St",
    "sg:city":"Northridge",
    "sg:classifiers":[
        {
            "category":"Freight",
            "type":"Transportation"
        }
    ],
    "sg:phone":"+1 818 349 1677",
    "sg:postcode":"91324",
    "sg:province":"CA",
    "sg:tags":[
        "industrial",
        "general",
        "machinery",
        "mfg"
    ],
    "wof:name":"Am-Par Manufacturing Company",
    "wof:placetype":"venue"
},
  "geometry": {"coordinates":[-118.537163,34.22831],"type":"Point"}
}