{
  "type": "Feature",
  "properties": {
    "iso:country":"US",
    "sg:address":"4940 E Kings Canyon Rd",
    "sg:city":"Fresno",
    "sg:classifiers":[
        {
            "category":"Professional",
            "type":"Services"
        }
    ],
    "sg:phone":"+1 559 453 0616",
    "sg:postcode":"93727",
    "sg:province":"CA",
    "wof:name":"Cali Blue Jeans",
    "wof:placetype":"venue"
},
  "geometry": {"coordinates":[-119.729051,36.735829],"type":"Point"}
}