{
  "type": "Feature",
  "properties": {
    "addr:full":"1656 Skyline Blvd Burlingame CA 94010",
    "addr:housenumber":"1656",
    "addr:postcode":"94010",
    "addr:street":"Skyline Blvd",
    "iso:country":"US",
    "sg:address":"1656 Skyline Blvd",
    "sg:city":"Burlingame",
    "sg:classifiers":[
        {
            "category":"Home & Garden",
            "subcategory":"Furniture",
            "type":"Retail Goods"
        }
    ],
    "sg:phone":"+1 650 697 3709",
    "sg:postcode":"94010",
    "sg:province":"CA",
    "sg:tags":[
        "store"
    ],
    "wof:name":"Saladmaster",
    "wof:placetype":"venue"
},
  "geometry": {"coordinates":[-122.399062,37.577063],"type":"Point"}
}