{
  "type": "Feature",
  "properties": {
    "iso:country":"US",
    "sg:address":"1236 Regent St Ste B",
    "sg:city":"Alameda",
    "sg:classifiers":[
        {
            "category":"Building & Trades",
            "subcategory":"Plumbing",
            "type":"Services"
        }
    ],
    "sg:phone":"+1 510 917 0119",
    "sg:postcode":"94501",
    "sg:province":"CA",
    "sg:website":"www.bonafideplumbing.com",
    "wof:name":"Bonafide Plumbing Co.",
    "wof:placetype":"venue"
},
  "geometry": {"coordinates":[-122.24266299999999,37.760609],"type":"Point"}
}