{
  "type": "Feature",
  "properties": {
    "addr:full":"2321 W March Ln Stockton CA 95207",
    "addr:housenumber":"2321",
    "addr:postcode":"95207",
    "addr:street":"W March Ln",
    "iso:country":"US",
    "sg:address":"2321 W March Ln",
    "sg:city":"Stockton",
    "sg:classifiers":[
        {
            "category":"Real Estate",
            "subcategory":"Real Estate Services",
            "type":"Services"
        }
    ],
    "sg:phone":"+1 209 954 4135",
    "sg:postcode":"95207",
    "sg:province":"CA",
    "sg:tags":[
        "company",
        "title"
    ],
    "wof:name":"Financial Title Co",
    "wof:placetype":"venue"
},
  "geometry": {"coordinates":[-121.336646,37.985379],"type":"Point"}
}