{
  "type": "Feature",
  "properties": {
    "iso:country":"US",
    "sg:address":"13360 Portofino Dr",
    "sg:city":"Del Mar",
    "sg:classifiers":[
        {
            "category":"Shopping",
            "subcategory":"Computers & Home Electronics",
            "type":"Retail Goods"
        }
    ],
    "sg:phone":"+1 858 755 8128",
    "sg:postcode":"92014",
    "sg:province":"CA",
    "sg:tags":[
        "related"
    ],
    "wof:name":"Gary Parks Enterprises",
    "wof:placetype":"venue"
},
  "geometry": {"coordinates":[-117.24368800000001,32.943358],"type":"Point"}
}