{
  "type": "Feature",
  "properties": {
    "iso:country":"US",
    "sg:address":"1401 el Camino Ave",
    "sg:city":"Sacramento",
    "sg:classifiers":[
        {
            "category":"Professional",
            "subcategory":"Management & Consulting",
            "type":"Services"
        }
    ],
    "sg:phone":"+1 916 649 2154",
    "sg:postcode":"95815",
    "sg:province":"CA",
    "sg:tags":[
        "marketing",
        "training"
    ],
    "wof:name":"United Dealer Services",
    "wof:placetype":"venue"
},
  "geometry": {"coordinates":[-121.43377,38.610917],"type":"Point"}
}