{
  "type": "Feature",
  "properties": {
    "iso:country":"US",
    "sg:address":"241 S San Mateo Dr",
    "sg:city":"San Mateo",
    "sg:classifiers":[
        {
            "category":"Personal",
            "subcategory":"Massage",
            "type":"Services"
        },
        {
            "category":"Personal",
            "subcategory":"Day Spa",
            "type":"Services"
        }
    ],
    "sg:phone":"+1 650 343 7383",
    "sg:postcode":"94401",
    "sg:province":"CA",
    "sg:website":"www.revespasalon.com/",
    "wof:name":"Reve Spa Salon",
    "wof:placetype":"venue"
},
  "geometry": {"coordinates":[-122.324474,37.564611],"type":"Point"}
}