{
  "type": "Feature",
  "properties": {
    "addr:full":"4860 E Harvest Rd Acampo CA 95220",
    "addr:housenumber":"4860",
    "addr:postcode":"95220",
    "addr:street":"E Harvest Rd",
    "iso:country":"US",
    "sg:address":"4860 E Harvest Rd",
    "sg:city":"Acampo",
    "sg:classifiers":[
        {
            "category":"Mining & Drilling",
            "type":"Manufacturing & Wholesale Goods"
        }
    ],
    "sg:phone":"+1 209 368 3343",
    "sg:postcode":"95220",
    "sg:province":"CA",
    "sg:tags":[
        "company"
    ],
    "wof:name":"Shoup Well Drilling & Pumps",
    "wof:placetype":"venue"
},
  "geometry": {"coordinates":[-121.25895199999999,38.176739],"type":"Point"}
}