{
  "type": "Feature",
  "properties": {
    "iso:country":"US",
    "sg:address":"3065 Porter St",
    "sg:city":"Soquel",
    "sg:classifiers":[
        {
            "category":"Banks & Credit Unions",
            "subcategory":"Bank",
            "type":"Services"
        }
    ],
    "sg:phone":"+1 831 479 7777",
    "sg:postcode":"95073",
    "sg:province":"CA",
    "sg:tags":[
        "mortgage",
        "loan",
        "broker",
        "real estate"
    ],
    "wof:name":"Associated Home Loans",
    "wof:placetype":"venue"
},
  "geometry": {"coordinates":[-121.957425,36.988203],"type":"Point"}
}