{
  "type": "Feature",
  "properties": {
    "iso:country":"US",
    "sg:address":"2605 Jacaranda Ave",
    "sg:city":"Carlsbad",
    "sg:classifiers":[
        {
            "category":"Building & Trades",
            "subcategory":"Cleaning & Sanitation",
            "type":"Services"
        }
    ],
    "sg:phone":"+1 760 420 2075",
    "sg:postcode":"92009",
    "sg:province":"CA",
    "sg:tags":[
        "janitor"
    ],
    "wof:name":"Cleaning Co",
    "wof:placetype":"venue"
},
  "geometry": {"coordinates":[-117.251693,33.067721],"type":"Point"}
}