{
  "type": "Feature",
  "properties": {
    "iso:country":"US",
    "sg:address":"2425 Haley St",
    "sg:city":"Bakersfield",
    "sg:classifiers":[
        {
            "category":"Food & Beverages",
            "subcategory":"Specialty",
            "type":"Retail Goods"
        }
    ],
    "sg:phone":"+1 661 872 3200",
    "sg:postcode":"93305",
    "sg:province":"CA",
    "sg:tags":[
        "health",
        "diet"
    ],
    "wof:name":"Nature Sunshine Ctr",
    "wof:placetype":"venue"
},
  "geometry": {"coordinates":[-118.976264,35.393809],"type":"Point"}
}