{
  "type": "Feature",
  "properties": {
    "iso:country":"US",
    "sg:address":"43185 Corte Almeria",
    "sg:city":"Temecula",
    "sg:classifiers":[
        {
            "category":"Building & Trades",
            "subcategory":"Electrical",
            "type":"Services"
        }
    ],
    "sg:phone":"+1 951 302 4500",
    "sg:postcode":"92592",
    "sg:province":"CA",
    "sg:tags":[
        "industrial",
        "electrician",
        "contractors-commercial",
        "electric"
    ],
    "wof:name":"Seaport Electric",
    "wof:placetype":"venue"
},
  "geometry": {"coordinates":[-117.10008999999999,33.496751],"type":"Point"}
}