{
  "type": "Feature",
  "properties": {
    "addr:full":"8441 Schmeidt Rd Lodi CA 95240",
    "addr:housenumber":"8441",
    "addr:postcode":"95240",
    "addr:street":"Schmeidt Rd",
    "iso:country":"US",
    "sg:address":"8441 Schmeidt Rd",
    "sg:city":"Lodi",
    "sg:classifiers":[
        {
            "category":"Manufacturing",
            "subcategory":"Food",
            "type":"Manufacturing & Wholesale Goods"
        }
    ],
    "sg:phone":"+1 209 369 5755",
    "sg:postcode":"95240",
    "sg:province":"CA",
    "sg:tags":[
        "mfg"
    ],
    "wof:name":"Glen Mokelumne Vineyard",
    "wof:placetype":"venue"
},
  "geometry": {"coordinates":[-121.20647200000001,38.153385],"type":"Point"}
}