{
  "type": "Feature",
  "properties": {
    "addr:full":"13128 Magnolia St Ste D Garden Grove CA 92844",
    "addr:housenumber":"13128",
    "addr:postcode":"92844",
    "addr:street":"Magnolia St Ste D",
    "iso:country":"US",
    "sg:address":"13128 Magnolia St Ste D",
    "sg:city":"Garden Grove",
    "sg:classifiers":[
        {
            "category":"Government",
            "subcategory":"Office",
            "type":"Public Place"
        }
    ],
    "sg:phone":"+1 714 636 0019",
    "sg:postcode":"92844",
    "sg:province":"CA",
    "sg:tags":[
        "smog",
        "check"
    ],
    "wof:name":"Andy Test Only Center",
    "wof:placetype":"venue"
},
  "geometry": {"coordinates":[-117.97199999999999,33.771801],"type":"Point"}
}