{
  "type": "Feature",
  "properties": {
    "iso:country":"US",
    "sg:address":"423 N Fries Ave",
    "sg:city":"Wilmington",
    "sg:classifiers":[
        {
            "category":"Food & Beverages",
            "subcategory":"Meat & Fish",
            "type":"Retail Goods"
        }
    ],
    "sg:phone":"+1 310 518 0820",
    "sg:postcode":"90744",
    "sg:province":"CA",
    "sg:tags":[
        "shop"
    ],
    "wof:name":"Guadalajara Meat Mkt",
    "wof:placetype":"venue"
},
  "geometry": {"coordinates":[-118.264999,33.774399],"type":"Point"}
}