{
  "type": "Feature",
  "properties": {
    "addr:full":"1213 E 14th St Los Angeles CA 90021",
    "addr:housenumber":"1213",
    "addr:postcode":"90021",
    "addr:street":"E 14Th St",
    "iso:country":"US",
    "sg:address":"1213 E 14th St",
    "sg:city":"Los Angeles",
    "sg:classifiers":[
        {
            "category":"Shopping",
            "subcategory":"Crafts & Fabrics",
            "type":"Retail Goods"
        }
    ],
    "sg:phone":"+1 213 688 9790",
    "sg:postcode":"90021",
    "sg:province":"CA",
    "sg:tags":[
        "sewing"
    ],
    "wof:name":"Knit Resource Inc",
    "wof:placetype":"venue"
},
  "geometry": {"coordinates":[-118.24693600000001,34.028566],"type":"Point"}
}