{
  "type": "Feature",
  "properties": {
    "addr:full":"505 W Broadway Long Beach CA 90802",
    "addr:housenumber":"505",
    "addr:postcode":"90802",
    "addr:street":"W Broadway",
    "iso:country":"US",
    "sg:address":"505 W Broadway",
    "sg:city":"Long Beach",
    "sg:classifiers":[
        {
            "category":"Wholesale",
            "subcategory":"Machinery & Supplies",
            "type":"Manufacturing & Wholesale Goods"
        }
    ],
    "sg:phone":"+1 562 432 4478",
    "sg:postcode":"90802",
    "sg:province":"CA",
    "sg:tags":[
        "ship",
        "chandler"
    ],
    "wof:name":"Julian Ship Supplies",
    "wof:placetype":"venue"
},
  "geometry": {"coordinates":[-118.198577,33.769359],"type":"Point"}
}