{
  "type": "Feature",
  "properties": {
    "iso:country":"US",
    "sg:address":"8511 Sherwood Drive",
    "sg:city":"West Hollywood",
    "sg:classifiers":[
        {
            "category":"Home & Garden",
            "subcategory":"Garden Supply",
            "type":"Retail Goods"
        }
    ],
    "sg:phone":"+1 310 659 5468",
    "sg:postcode":"90069",
    "sg:province":"CA",
    "sg:tags":[
        "nursery",
        "gardening"
    ],
    "wof:name":"La Cienega Nursery",
    "wof:placetype":"venue"
},
  "geometry": {"coordinates":[-118.376692,34.084737],"type":"Point"}
}