{
  "type": "Feature",
  "properties": {
    "addr:full":"4174 Technology Dr Fremont CA 94538",
    "addr:housenumber":"4174",
    "addr:postcode":"94538",
    "addr:street":"Technology Dr",
    "iso:country":"US",
    "sg:address":"4174 Technology Dr",
    "sg:city":"Fremont",
    "sg:classifiers":[
        {
            "category":"Manufacturing",
            "subcategory":"Electronics",
            "type":"Manufacturing & Wholesale Goods"
        }
    ],
    "sg:phone":"+1 510 438 7982",
    "sg:postcode":"94538",
    "sg:province":"CA",
    "sg:tags":[
        "semiconductor",
        "devices"
    ],
    "wof:name":"Infrant Technologies",
    "wof:placetype":"venue"
},
  "geometry": {"coordinates":[-121.95438300000001,37.509105],"type":"Point"}
}