{
  "type": "Feature",
  "properties": {
    "addr:full":"3432 Main St Cottonwood CA 96022",
    "addr:housenumber":"3432",
    "addr:postcode":"96022",
    "addr:street":"Main St",
    "iso:country":"US",
    "sg:address":"3432 Main St",
    "sg:city":"Cottonwood",
    "sg:classifiers":[
        {
            "category":"Insurance",
            "subcategory":"Insurance Agent",
            "type":"Services"
        }
    ],
    "sg:phone":"+1 530 347 7232",
    "sg:postcode":"96022",
    "sg:province":"CA",
    "wof:name":"AFLAC",
    "wof:placetype":"venue"
},
  "geometry": {"coordinates":[-122.28111199999999,40.38811],"type":"Point"}
}