{
  "type": "Feature",
  "properties": {
    "addr:full":"46 Minna St San Francisco CA 94105",
    "addr:housenumber":"46",
    "addr:postcode":"94105",
    "addr:street":"Minna St",
    "iso:country":"US",
    "sg:address":"46 Minna St",
    "sg:city":"San Francisco",
    "sg:classifiers":[
        {
            "category":"Bars & Pubs",
            "subcategory":"Gay Bar",
            "type":"Food & Drink"
        },
        {
            "category":"Recreation",
            "subcategory":"Dance Hall",
            "type":"Entertainment"
        }
    ],
    "sg:postcode":"94105",
    "sg:province":"CA",
    "sg:tags":[
        "club"
    ],
    "sg:website":"www.myspace.com/fembar",
    "wof:name":"Fem Bar",
    "wof:placetype":"venue"
},
  "geometry": {"coordinates":[-122.398219,37.788414],"type":"Point"}
}