{
  "type": "Feature",
  "properties": {
    "addr:full":"1411 N Broadway Santa Ana CA 92706",
    "addr:housenumber":"1411",
    "addr:postcode":"92706",
    "addr:street":"N Broadway",
    "iso:country":"US",
    "sg:address":"1411 N Broadway",
    "sg:city":"Santa Ana",
    "sg:classifiers":[
        {
            "category":"Organizations",
            "subcategory":"Non-profit Organization",
            "type":"Services"
        }
    ],
    "sg:phone":"+1 714 542 3577",
    "sg:postcode":"92706",
    "sg:province":"CA",
    "sg:tags":[
        "service/non-profit",
        "community"
    ],
    "wof:name":"Wise Place",
    "wof:placetype":"venue"
},
  "geometry": {"coordinates":[-117.870003,33.757401],"type":"Point"}
}