{
  "type": "Feature",
  "properties": {
    "addr:full":"1350 W Robinhood Dr Stockton CA 95207",
    "addr:housenumber":"1350",
    "addr:postcode":"95207",
    "addr:street":"W Robinhood Dr",
    "iso:country":"US",
    "sg:address":"1350 W Robinhood Dr",
    "sg:city":"Stockton",
    "sg:classifiers":[
        {
            "category":"Real Estate",
            "subcategory":"Real Estate Agent",
            "type":"Services"
        }
    ],
    "sg:phone":"+1 209 952 0040",
    "sg:postcode":"95207",
    "sg:province":"CA",
    "wof:name":"DPM Real Estate Appraisals",
    "wof:placetype":"venue"
},
  "geometry": {"coordinates":[-121.32409,37.998441],"type":"Point"}
}