{
  "type": "Feature",
  "properties": {
    "addr:full":"16 Indiana Irvine CA 92606",
    "addr:housenumber":"16",
    "addr:postcode":"92606",
    "addr:street":"Indiana",
    "iso:country":"US",
    "sg:address":"16 Indiana",
    "sg:city":"Irvine",
    "sg:classifiers":[
        {
            "category":"Professional",
            "type":"Services"
        }
    ],
    "sg:phone":"+1 949 653 7094",
    "sg:postcode":"92606",
    "sg:province":"CA",
    "wof:name":"Gamil M Messiha",
    "wof:placetype":"venue"
},
  "geometry": {"coordinates":[-117.795528,33.710976],"type":"Point"}
}