{
  "type": "Feature",
  "properties": {
    "iso:country":"US",
    "sg:address":"1222 E Florence Ave",
    "sg:city":"Los Angeles",
    "sg:classifiers":[
        {
            "category":"Manufacturing",
            "subcategory":"Metals",
            "type":"Manufacturing & Wholesale Goods"
        }
    ],
    "sg:phone":"+1 323 589 0348",
    "sg:postcode":"90001",
    "sg:province":"CA",
    "sg:tags":[
        "metalwork",
        "ornamental",
        "work",
        "architectural",
        "mfg"
    ],
    "wof:name":"Lucio's Ironworks",
    "wof:placetype":"venue"
},
  "geometry": {"coordinates":[-118.253268,33.974699],"type":"Point"}
}