{
  "type": "Feature",
  "properties": {
    "addr:full":"6691 Smokewood Cir Anaheim CA 92807",
    "addr:housenumber":"6691",
    "addr:postcode":"92807",
    "addr:street":"Smokewood Cir",
    "iso:country":"US",
    "sg:address":"6691 Smokewood Cir",
    "sg:city":"Anaheim",
    "sg:classifiers":[
        {
            "category":"Retail",
            "subcategory":"Portrait Studio",
            "type":"Services"
        }
    ],
    "sg:phone":"+1 714 363 9690",
    "sg:postcode":"92807",
    "sg:province":"CA",
    "sg:tags":[
        "photographer"
    ],
    "sg:website":"www.classicstudios.net",
    "wof:name":"Classic Photography",
    "wof:placetype":"venue"
},
  "geometry": {"coordinates":[-117.75632899999999,33.83075],"type":"Point"}
}