{
  "type": "Feature",
  "properties": {
    "addr:full":"5339 Santa Monica Blvd Los Angeles CA 90029",
    "addr:housenumber":"5339",
    "addr:postcode":"90029",
    "addr:street":"Santa Monica Blvd",
    "iso:country":"US",
    "sg:address":"5339 Santa Monica Blvd",
    "sg:city":"Los Angeles",
    "sg:classifiers":[
        {
            "category":"Shopping",
            "subcategory":"Florist",
            "type":"Retail Goods"
        }
    ],
    "sg:phone":"+1 323 464 1535",
    "sg:postcode":"90029",
    "sg:province":"CA",
    "wof:name":"Holland Flowers",
    "wof:placetype":"venue"
},
  "geometry": {"coordinates":[-118.305908,34.090864],"type":"Point"}
}