{
  "type": "Feature",
  "properties": {
    "addr:full":"6309 Watt Ave Ste 110 North Highlands CA 95660",
    "addr:housenumber":"6309",
    "addr:postcode":"95660",
    "addr:street":"Watt Ave Ste 110",
    "iso:country":"US",
    "sg:address":"6309 Watt Ave Ste 110",
    "sg:city":"North Highlands",
    "sg:classifiers":[
        {
            "category":"Retail",
            "subcategory":"Auto Repair",
            "type":"Services"
        }
    ],
    "sg:phone":"+1 916 334 9304",
    "sg:postcode":"95660",
    "sg:province":"CA",
    "wof:name":"Hi Tech Transmissions",
    "wof:placetype":"venue"
},
  "geometry": {"coordinates":[-121.383003,38.681198],"type":"Point"}
}