{
  "type": "Feature",
  "properties": {
    "addr:full":"13233 Whistler Ave Granada Hills CA 91344",
    "addr:housenumber":"13233",
    "addr:postcode":"91344",
    "addr:street":"Whistler Ave",
    "iso:country":"US",
    "sg:address":"13233 Whistler Ave",
    "sg:city":"Granada Hills",
    "sg:classifiers":[
        {
            "category":"Shopping",
            "subcategory":"Clothing, Apparel, & Fashions",
            "type":"Retail Goods"
        }
    ],
    "sg:phone":"+1 818 366 9232",
    "sg:postcode":"91344",
    "sg:province":"CA",
    "wof:name":"Costume-Shopcom",
    "wof:placetype":"venue"
},
  "geometry": {"coordinates":[-118.507401,34.309108],"type":"Point"}
}