{
  "type": "Feature",
  "properties": {
    "addr:full":"13655 Khalid Ct Grass Valley CA 95949",
    "addr:housenumber":"13655",
    "addr:postcode":"95949",
    "addr:street":"Khalid Ct",
    "iso:country":"US",
    "sg:address":"13655 Khalid Ct",
    "sg:city":"Grass Valley",
    "sg:classifiers":[
        {
            "category":"Health Services",
            "subcategory":"Health Practitioner",
            "type":"Services"
        }
    ],
    "sg:phone":"+1 530 271 0370",
    "sg:postcode":"95949",
    "sg:province":"CA",
    "sg:tags":[
        "psychologist"
    ],
    "wof:name":"Pamlyn Kelly PHD",
    "wof:placetype":"venue"
},
  "geometry": {"coordinates":[-121.096141,39.180284],"type":"Point"}
}