{
  "type": "Feature",
  "properties": {
    "iso:country":"US",
    "sg:address":"671 Ross Ct",
    "sg:city":"Sonoma",
    "sg:classifiers":[
        {
            "category":"Manufacturing",
            "subcategory":"Building Materials",
            "type":"Manufacturing & Wholesale Goods"
        }
    ],
    "sg:phone":"+1 707 935 5942",
    "sg:postcode":"95476",
    "sg:province":"CA",
    "sg:tags":[
        "mfg"
    ],
    "wof:name":"Roycroft Woodworks",
    "wof:placetype":"venue"
},
  "geometry": {"coordinates":[-122.484552,38.293215],"type":"Point"}
}