{
  "type": "Feature",
  "properties": {
    "iso:country":"US",
    "sg:address":"655 E D St",
    "sg:city":"Wilmington",
    "sg:classifiers":[
        {
            "category":"Mining & Drilling",
            "type":"Manufacturing & Wholesale Goods"
        }
    ],
    "sg:phone":"+1 310 834 4411",
    "sg:postcode":"90744",
    "sg:province":"CA",
    "sg:tags":[
        "gas",
        "oil",
        "well"
    ],
    "wof:name":"Cooper & Brain Oil Co",
    "wof:placetype":"venue"
},
  "geometry": {"coordinates":[-118.254997,33.7747],"type":"Point"}
}