{
  "type": "Feature",
  "properties": {
    "addr:full":"1550 Hotel Cir N Suite 140 San Diego CA 92108",
    "addr:housenumber":"1550",
    "addr:postcode":"92108",
    "addr:street":"Hotel Cir N Suite 140",
    "iso:country":"US",
    "sg:address":"1550 Hotel Cir N Suite 140",
    "sg:city":"San Diego",
    "sg:classifiers":[
        {
            "category":"Real Estate",
            "subcategory":"Architect",
            "type":"Services"
        }
    ],
    "sg:phone":"+1 619 298 4400",
    "sg:postcode":"92108",
    "sg:province":"CA",
    "wof:name":"Walt Conwell Architects",
    "wof:placetype":"venue"
},
  "geometry": {"coordinates":[-117.13461,32.776033],"type":"Point"}
}