{
  "type": "Feature",
  "properties": {
    "addr:full":"1244 6th St Port Hueneme CA 93041",
    "addr:housenumber":"1244",
    "addr:postcode":"93041",
    "addr:street":"6Th St",
    "iso:country":"US",
    "sg:address":"1244 6th St",
    "sg:city":"Port Hueneme",
    "sg:classifiers":[
        {
            "category":"Wholesale",
            "subcategory":"Machinery & Supplies",
            "type":"Manufacturing & Wholesale Goods"
        }
    ],
    "sg:phone":"+1 805 483 3984",
    "sg:postcode":"93041",
    "sg:province":"CA",
    "wof:name":"Nichols Irrigation Repair",
    "wof:placetype":"venue"
},
  "geometry": {"coordinates":[-119.192768,34.158811],"type":"Point"}
}