{
  "type": "Feature",
  "properties": {
    "iso:country":"US",
    "sg:address":"1101 Monterey Pass Rd",
    "sg:city":"Monterey Park",
    "sg:classifiers":[
        {
            "category":"Manufacturing",
            "subcategory":"Printing",
            "type":"Manufacturing & Wholesale Goods"
        }
    ],
    "sg:phone":"+1 323 266 0326",
    "sg:postcode":"91754",
    "sg:province":"CA",
    "sg:tags":[
        "printer"
    ],
    "wof:name":"Dean's Screens",
    "wof:placetype":"venue"
},
  "geometry": {"coordinates":[-118.15308,34.052334],"type":"Point"}
}