{
  "type": "Feature",
  "properties": {
    "addr:full":"1766 Tennyson Dr Concord CA 94521",
    "addr:housenumber":"1766",
    "addr:postcode":"94521",
    "addr:street":"Tennyson Dr",
    "iso:country":"US",
    "sg:address":"1766 Tennyson Dr",
    "sg:city":"Concord",
    "sg:classifiers":[
        {
            "category":"Building & Trades",
            "subcategory":"Construction",
            "type":"Services"
        }
    ],
    "sg:phone":"+1 925 827 2706",
    "sg:postcode":"94521",
    "sg:province":"CA",
    "sg:tags":[
        "general",
        "commercial",
        "contractor"
    ],
    "wof:name":"Richard D Ross Construction",
    "wof:placetype":"venue"
},
  "geometry": {"coordinates":[-121.95684799999999,37.957907],"type":"Point"}
}