{
  "type": "Feature",
  "properties": {
    "addr:full":"Alameda Towne Center 523 S Shore Ctr W Alameda CA 94501",
    "addr:housenumber":"523",
    "addr:postcode":"94501",
    "addr:street":"Alameda Towne;S Shore Ctr W",
    "iso:country":"US",
    "sg:address":"Alameda Towne Center 523 S Shore Ctr W",
    "sg:city":"Alameda",
    "sg:classifiers":[
        {
            "category":"Shopping",
            "subcategory":"Clothing, Apparel, & Fashions",
            "type":"Retail Goods"
        }
    ],
    "sg:phone":"+1 510 337 1335",
    "sg:postcode":"94501",
    "sg:province":"CA",
    "sg:tags":[
        "children's",
        "clothing"
    ],
    "sg:website":"www.childrensplace.com",
    "wof:name":"Childrens Place",
    "wof:placetype":"venue"
},
  "geometry": {"coordinates":[-122.252354,37.759378],"type":"Point"}
}