{
  "type": "Feature",
  "properties": {
    "addr:full":"5128 Whittier Blvd Los Angeles CA 90022",
    "addr:housenumber":"5128",
    "addr:postcode":"90022",
    "addr:street":"Whittier Blvd",
    "iso:country":"US",
    "sg:address":"5128 Whittier Blvd",
    "sg:city":"Los Angeles",
    "sg:classifiers":[
        {
            "category":"Recreation",
            "type":"Entertainment"
        }
    ],
    "sg:phone":"+1 323 267 8782",
    "sg:postcode":"90022",
    "sg:province":"CA",
    "sg:tags":[
        "parlor",
        "billiard"
    ],
    "wof:name":"Borja's Poolroom",
    "wof:placetype":"venue"
},
  "geometry": {"coordinates":[-118.158871,34.020676],"type":"Point"}
}