{
  "type": "Feature",
  "properties": {
    "addr:full":"23332 Hawthorne Blvd Torrance CA 90505",
    "addr:housenumber":"23332",
    "addr:postcode":"90505",
    "addr:street":"Hawthorne Blvd",
    "iso:country":"US",
    "sg:address":"23332 Hawthorne Blvd",
    "sg:city":"Torrance",
    "sg:classifiers":[
        {
            "category":"Health Services",
            "subcategory":"Chiropractor",
            "type":"Services"
        }
    ],
    "sg:phone":"+1 310 373 4371",
    "sg:postcode":"90505",
    "sg:province":"CA",
    "wof:name":"ABC Chiropractic",
    "wof:placetype":"venue"
},
  "geometry": {"coordinates":[-118.350844,33.814361],"type":"Point"}
}