{
  "type": "Feature",
  "properties": {
    "addr:full":"1525 N Placentia Ave Ste G Placentia CA 92870",
    "addr:housenumber":"1525",
    "addr:postcode":"ca 92870",
    "addr:street":"N Placentia Ave Ste G",
    "iso:country":"US",
    "sg:address":"1525 N Placentia Ave Ste G",
    "sg:city":"Placentia",
    "sg:classifiers":[
        {
            "category":"Health Services",
            "subcategory":"Health Practitioner",
            "type":"Services"
        }
    ],
    "sg:phone":"+1 800 516 3535",
    "sg:postcode":"92870",
    "sg:province":"CA",
    "sg:tags":[
        "control",
        "weight"
    ],
    "sg:website":"http://www.weightwatchers.com/Index.aspx?cid=YP",
    "wof:name":"Weight Watchers - Placentia",
    "wof:placetype":"venue"
},
  "geometry": {"coordinates":[-117.873992,33.890663],"type":"Point"}
}