{
  "type": "Feature",
  "properties": {
    "addr:full":"137 Lewis St Auburn CA 95603",
    "addr:housenumber":"137",
    "addr:postcode":"ca 95603",
    "addr:street":"Lewis St",
    "iso:country":"US",
    "sg:address":"137 Lewis St",
    "sg:city":"Auburn",
    "sg:classifiers":[
        {
            "category":"Personal",
            "subcategory":"Beauty Salon",
            "type":"Services"
        }
    ],
    "sg:phone":"+1 530 823 8521",
    "sg:postcode":"95603",
    "sg:province":"CA",
    "sg:tags":[
        "hair",
        "stylist"
    ],
    "wof:name":"Adele'sl Boutique & Hair Salon",
    "wof:placetype":"venue"
},
  "geometry": {"coordinates":[-121.070114,38.89847],"type":"Point"}
}