{
  "type": "Feature",
  "properties": {
    "iso:country":"US",
    "sg:address":"3100 W Warner Ave",
    "sg:city":"Santa Ana",
    "sg:classifiers":[
        {
            "category":"Banks & Credit Unions",
            "subcategory":"Financial Services",
            "type":"Services"
        }
    ],
    "sg:phone":"+1 714 957 3311",
    "sg:postcode":"92704",
    "sg:province":"CA",
    "sg:tags":[
        "broker",
        "mortgage"
    ],
    "wof:name":"Roseman Mortgage Company",
    "wof:placetype":"venue"
},
  "geometry": {"coordinates":[-117.910161,33.715023],"type":"Point"}
}