{
  "type": "Feature",
  "properties": {
    "iso:country":"US",
    "sg:address":"18260 Lakeview Ct",
    "sg:city":"Los Gatos",
    "sg:classifiers":[
        {
            "category":"Home & Garden",
            "subcategory":"Carpets & Floor Coverings",
            "type":"Retail Goods"
        }
    ],
    "sg:phone":"+1 408 354 5905",
    "sg:postcode":"95033",
    "sg:province":"CA",
    "wof:name":"South Bay Floors",
    "wof:placetype":"venue"
},
  "geometry": {"coordinates":[-121.996399,37.19205],"type":"Point"}
}