{
  "type": "Feature",
  "properties": {
    "addr:full":"613 Faxon Ave San Francisco CA 94112",
    "addr:housenumber":"613",
    "addr:postcode":"94112",
    "addr:street":"Faxon Ave",
    "iso:country":"US",
    "sg:address":"613 Faxon Ave",
    "sg:city":"San Francisco",
    "sg:classifiers":[
        {
            "category":"Building & Trades",
            "subcategory":"Construction",
            "type":"Services"
        }
    ],
    "sg:phone":"+1 415 563 8292",
    "sg:postcode":"94112",
    "sg:province":"CA",
    "sg:tags":[
        "resurfacing",
        "laying",
        "refinishing",
        "floor"
    ],
    "wof:name":"Ralph Jurado Hardwood Floors",
    "wof:placetype":"venue"
},
  "geometry": {"coordinates":[-122.45995000000001,37.72528],"type":"Point"}
}