{
  "type": "Feature",
  "properties": {
    "iso:country":"US",
    "sg:address":"5205 Ave Encinas",
    "sg:city":"Carlsbad",
    "sg:classifiers":[
        {
            "category":"Wholesale",
            "subcategory":"Medical Equipment & Supplies",
            "type":"Manufacturing & Wholesale Goods"
        }
    ],
    "sg:phone":"+1 760 431 8543",
    "sg:postcode":"92008",
    "sg:province":"CA",
    "sg:tags":[
        "physician",
        "surgeon",
        "merchandise"
    ],
    "wof:name":"North Coast Home Health Pdts",
    "wof:placetype":"venue"
},
  "geometry": {"coordinates":[-117.32978199999999,33.132439],"type":"Point"}
}