{
  "type": "Feature",
  "properties": {
    "iso:country":"US",
    "sg:address":"6389 Scarlett Ct",
    "sg:city":"Dublin",
    "sg:classifiers":[
        {
            "category":"Building & Trades",
            "subcategory":"Landscaping Services",
            "type":"Services"
        }
    ],
    "sg:phone":"+1 925 803 8580",
    "sg:postcode":"94568",
    "sg:province":"CA",
    "sg:tags":[
        "topsoil"
    ],
    "wof:name":"Kobold's Garden Supply",
    "wof:placetype":"venue"
},
  "geometry": {"coordinates":[-121.909035,37.70514],"type":"Point"}
}