{
  "type": "Feature",
  "properties": {
    "iso:country":"US",
    "sg:address":"1511C S Main St",
    "sg:city":"Willits",
    "sg:classifiers":[
        {
            "category":"Retail",
            "subcategory":"Auto Repair",
            "type":"Services"
        }
    ],
    "sg:phone":"+1 707 459 0594",
    "sg:postcode":"95490",
    "sg:province":"CA",
    "sg:tags":[
        "body",
        "painting",
        "repairing",
        "automobile"
    ],
    "wof:name":"Body Works Gym",
    "wof:placetype":"venue"
},
  "geometry": {"coordinates":[-123.348907,39.394642],"type":"Point"}
}