{
  "type": "Feature",
  "properties": {
    "addr:full":"1 Front St San Francisco CA 94111",
    "addr:housenumber":"1",
    "addr:postcode":"94111",
    "addr:street":"Front St",
    "iso:country":"US",
    "sg:address":"1 Front St",
    "sg:city":"San Francisco",
    "sg:classifiers":[
        {
            "category":"Insurance",
            "subcategory":"Hazard Insurance",
            "type":"Services"
        }
    ],
    "sg:phone":"+1 415 782 8179",
    "sg:postcode":"94111",
    "sg:province":"CA",
    "sg:tags":[
        "property",
        "other",
        "casualty"
    ],
    "wof:name":"Liberty Mutual",
    "wof:placetype":"venue"
},
  "geometry": {"coordinates":[-122.398588,37.792408],"type":"Point"}
}