{
  "type": "Feature",
  "properties": {
    "addr:full":"39 Walker St Watsonville CA 95076",
    "addr:housenumber":"39",
    "addr:postcode":"95076",
    "addr:street":"Walker St",
    "iso:country":"US",
    "sg:address":"39 Walker St",
    "sg:city":"Watsonville",
    "sg:classifiers":[
        {
            "category":"Professional",
            "subcategory":"Art Services",
            "type":"Services"
        }
    ],
    "sg:phone":"+1 831 768 0919",
    "sg:postcode":"95076",
    "sg:province":"CA",
    "sg:tags":[
        "graphic",
        "designer"
    ],
    "wof:name":"Smh Design & Craft",
    "wof:placetype":"venue"
},
  "geometry": {"coordinates":[-121.757407,36.904834],"type":"Point"}
}