{
  "type": "Feature",
  "properties": {
    "addr:full":"5160 Poston Dr San Jose CA 95136",
    "addr:housenumber":"5160",
    "addr:postcode":"95136",
    "addr:street":"Poston Dr",
    "iso:country":"US",
    "sg:address":"5160 Poston Dr",
    "sg:city":"San Jose",
    "sg:classifiers":[
        {
            "category":"Home & Garden",
            "subcategory":"Building Materials",
            "type":"Retail Goods"
        }
    ],
    "sg:phone":"+1 408 224 1956",
    "sg:postcode":"95136",
    "sg:province":"CA",
    "sg:tags":[
        "equipment",
        "electric",
        "supply"
    ],
    "wof:name":"Safe Haven Enterprises",
    "wof:placetype":"venue"
},
  "geometry": {"coordinates":[-121.82669300000001,37.261314],"type":"Point"}
}