{
  "type": "Feature",
  "properties": {
    "addr:full":"11771 W.Pico Blvd. Los Angeles CA 90064",
    "addr:housenumber":"11771",
    "addr:postcode":"90064",
    "addr:street":"W.Pico Blvd.",
    "iso:country":"US",
    "sg:address":"11771 W.Pico Blvd.",
    "sg:city":"Los Angeles",
    "sg:classifiers":[
        {
            "category":"Retail",
            "subcategory":"Auto Repair",
            "type":"Services"
        }
    ],
    "sg:phone":"+1 310 231 1933",
    "sg:postcode":"90064",
    "sg:province":"CA",
    "sg:tags":[
        "detailing"
    ],
    "wof:name":"George & Joe's Detail",
    "wof:placetype":"venue"
},
  "geometry": {"coordinates":[-118.447354,34.031108],"type":"Point"}
}