{
  "type": "Feature",
  "properties": {
    "iso:country":"US",
    "sg:address":"224 S Main St",
    "sg:city":"Pomona",
    "sg:classifiers":[
        {
            "category":"Manufacturing",
            "subcategory":"Printing",
            "type":"Manufacturing & Wholesale Goods"
        }
    ],
    "sg:phone":"+1 909 620 9034",
    "sg:postcode":"91766",
    "sg:province":"CA",
    "sg:tags":[
        "newspaper"
    ],
    "wof:name":"Civil Citizen's Journal",
    "wof:placetype":"venue"
},
  "geometry": {"coordinates":[-117.752214,34.057099],"type":"Point"}
}