{
  "type": "Feature",
  "properties": {
    "addr:full":"73300 el Paseo Palm Desert CA 92260",
    "addr:housenumber":"73300",
    "addr:postcode":"ca 92260",
    "addr:street":"El Paseo",
    "iso:country":"US",
    "sg:address":"73300 el Paseo",
    "sg:city":"Palm Desert",
    "sg:classifiers":[
        {
            "category":"Home & Garden",
            "subcategory":"Home Furnishings",
            "type":"Retail Goods"
        }
    ],
    "sg:phone":"+1 760 340 0984",
    "sg:postcode":"92260",
    "sg:province":"CA",
    "sg:tags":[
        "housewares"
    ],
    "wof:name":"Dansk Factory Outlet",
    "wof:placetype":"venue"
},
  "geometry": {"coordinates":[-116.385666,33.719845],"type":"Point"}
}