{
  "type": "Feature",
  "properties": {
    "addr:full":"1345 Western Ave Glendale CA 91201",
    "addr:housenumber":"1345",
    "addr:postcode":"91201",
    "addr:street":"Western Ave",
    "iso:country":"US",
    "sg:address":"1345 Western Ave",
    "sg:city":"Glendale",
    "sg:classifiers":[
        {
            "category":"Professional",
            "type":"Services"
        }
    ],
    "sg:phone":"+1 818 243 9104",
    "sg:postcode":"91201",
    "sg:province":"CA",
    "wof:name":"Albert Khudanyan",
    "wof:placetype":"venue"
},
  "geometry": {"coordinates":[-118.28373999999999,34.176685],"type":"Point"}
}