{
  "type": "Feature",
  "properties": {
    "iso:country":"US",
    "sg:address":"4201 Florin Perkins Rd",
    "sg:city":"Sacramento",
    "sg:classifiers":[
        {
            "category":"Government",
            "subcategory":"City Hall",
            "type":"Public Place"
        }
    ],
    "sg:phone":"+1 916 383 2122",
    "sg:postcode":"95826",
    "sg:province":"CA",
    "wof:name":"Jackson Road Landfill",
    "wof:placetype":"venue"
},
  "geometry": {"coordinates":[-121.39099899999999,38.537601],"type":"Point"}
}