{
  "type": "Feature",
  "properties": {
    "addr:full":"800 N San Mateo Dr San Mateo CA 94401",
    "addr:housenumber":"800",
    "addr:postcode":"94401",
    "addr:street":"N San Mateo Dr",
    "iso:country":"US",
    "sg:address":"800 N San Mateo Dr",
    "sg:city":"San Mateo",
    "sg:classifiers":[
        {
            "category":"Professional",
            "subcategory":"Computer Services",
            "type":"Services"
        }
    ],
    "sg:phone":"+1 650 227 2600",
    "sg:postcode":"94401",
    "sg:province":"CA",
    "sg:tags":[
        "hardware",
        "provider",
        "internet",
        "software"
    ],
    "sg:website":"www.ultradns.com",
    "wof:name":"Ultra DNS Corp",
    "wof:placetype":"venue"
},
  "geometry": {"coordinates":[-122.339375,37.577055],"type":"Point"}
}