{
  "type": "Feature",
  "properties": {
    "iso:country":"US",
    "sg:address":"2940 Westwood Blvd",
    "sg:city":"Los Angeles",
    "sg:classifiers":[
        {
            "category":"Wholesale",
            "subcategory":"Stationery",
            "type":"Manufacturing & Wholesale Goods"
        }
    ],
    "sg:phone":"+1 310 556 0695",
    "sg:postcode":"90064",
    "sg:province":"CA",
    "sg:tags":[
        "school",
        "supply"
    ],
    "wof:name":"Cover It",
    "wof:placetype":"venue"
},
  "geometry": {"coordinates":[-118.421174,34.031073],"type":"Point"}
}