{
  "type": "Feature",
  "properties": {
    "iso:country":"US",
    "sg:address":"909 N Grand Ave",
    "sg:city":"Santa Ana",
    "sg:classifiers":[
        {
            "category":"Autos & Motor Vehicles",
            "subcategory":"Automobile Sales",
            "type":"Retail Goods"
        },
        {
            "category":"Retail",
            "subcategory":"Auto Repair",
            "type":"Services"
        }
    ],
    "sg:phone":"+1 888 694 1641",
    "sg:postcode":"92701",
    "sg:province":"CA",
    "sg:tags":[
        "car"
    ],
    "sg:website":"www.kiadepot.com",
    "wof:name":"The Kia & Suzuki Depot",
    "wof:placetype":"venue"
},
  "geometry": {"coordinates":[-117.851237,33.753378],"type":"Point"}
}