{
  "type": "Feature",
  "properties": {
    "iso:country":"US",
    "sg:address":"725 Court St",
    "sg:city":"Martinez",
    "sg:classifiers":[
        {
            "category":"Government",
            "subcategory":"Court House",
            "type":"Public Place"
        }
    ],
    "sg:phone":"+1 925 957 2200",
    "sg:postcode":"94553",
    "sg:province":"CA",
    "sg:tags":[
        "county",
        "counsel"
    ],
    "wof:name":"Contra Costa County Dist Atty",
    "wof:placetype":"venue"
},
  "geometry": {"coordinates":[-122.13387400000001,38.018053],"type":"Point"}
}