{
  "type": "Feature",
  "properties": {
    "addr:full":"809 Broadway Ste 3 Sonoma CA 95476",
    "addr:housenumber":"809",
    "addr:postcode":"95476",
    "addr:street":"Broadway Ste 3",
    "iso:country":"US",
    "sg:address":"809 Broadway Ste 3",
    "sg:city":"Sonoma",
    "sg:classifiers":[
        {
            "category":"Professional",
            "subcategory":"Lawyer & Legal Services",
            "type":"Services"
        }
    ],
    "sg:phone":"+1 707 938 3654",
    "sg:postcode":"95476",
    "sg:province":"CA",
    "sg:tags":[
        "attorney",
        "partnership",
        "estate",
        "business",
        "corporation",
        "wills",
        "practice",
        "planning",
        "plan",
        "trust",
        "law"
    ],
    "wof:name":"Harris, Charles E Law Office",
    "wof:placetype":"venue"
},
  "geometry": {"coordinates":[-122.458679,38.28642],"type":"Point"}
}