{
  "type": "Feature",
  "properties": {
    "addr:full":"17940 Berta Canyon Rd Salinas CA 93907",
    "addr:housenumber":"17940",
    "addr:postcode":"93907",
    "addr:street":"Berta Canyon Rd",
    "iso:country":"US",
    "sg:address":"17940 Berta Canyon Rd",
    "sg:city":"Salinas",
    "sg:classifiers":[
        {
            "category":"Retail",
            "subcategory":"Animal Services",
            "type":"Services"
        }
    ],
    "sg:phone":"+1 831 663 6218",
    "sg:postcode":"93907",
    "sg:province":"CA",
    "wof:name":"Doggone Kenneless Boarding",
    "wof:placetype":"venue"
},
  "geometry": {"coordinates":[-121.661123,36.790006],"type":"Point"}
}