{
  "type": "Feature",
  "properties": {
    "iso:country":"US",
    "sg:address":"1532 E La Palma Ave",
    "sg:city":"Anaheim",
    "sg:classifiers":[
        {
            "category":"Real Estate",
            "subcategory":"Real Estate Operator",
            "type":"Services"
        }
    ],
    "sg:phone":"+1 714 563 9836",
    "sg:postcode":"92805",
    "sg:province":"CA",
    "sg:tags":[
        "apartment"
    ],
    "wof:name":"La Palma Apartments",
    "wof:placetype":"venue"
},
  "geometry": {"coordinates":[-117.897003,33.847198],"type":"Point"}
}