{
  "type": "Feature",
  "properties": {
    "iso:country":"US",
    "sg:address":"3110 E Guasti Rd",
    "sg:city":"Ontario",
    "sg:classifiers":[
        {
            "category":"Building & Trades",
            "subcategory":"Construction",
            "type":"Services"
        }
    ],
    "sg:phone":"+1 909 937 7525",
    "sg:postcode":"91761",
    "sg:province":"CA",
    "sg:tags":[
        "contractor"
    ],
    "wof:name":"KPRS Construction Svc",
    "wof:placetype":"venue"
},
  "geometry": {"coordinates":[-117.582649,34.066059],"type":"Point"}
}