{
  "type": "Feature",
  "properties": {
    "iso:country":"US",
    "sg:address":"1524 2nd St",
    "sg:city":"San Rafael",
    "sg:classifiers":[
        {
            "category":"Retail",
            "subcategory":"Auto Repair",
            "type":"Services"
        }
    ],
    "sg:phone":"+1 415 457 5823",
    "sg:postcode":"94901",
    "sg:province":"CA",
    "sg:tags":[
        "automobile",
        "lubrication"
    ],
    "wof:name":"Pennzoil 10 Minute Oil Change",
    "wof:placetype":"venue"
},
  "geometry": {"coordinates":[-122.53424200000001,37.971808],"type":"Point"}
}