{
  "type": "Feature",
  "properties": {
    "addr:full":"19586 Black Rd Los Gatos CA 95033",
    "addr:housenumber":"19586",
    "addr:postcode":"95033",
    "addr:street":"Black Rd",
    "iso:country":"US",
    "sg:address":"19586 Black Rd",
    "sg:city":"Los Gatos",
    "sg:classifiers":[
        {
            "category":"Building & Trades",
            "subcategory":"Construction",
            "type":"Services"
        }
    ],
    "sg:phone":"+1 408 354 5463",
    "sg:postcode":"95033",
    "sg:province":"CA",
    "sg:tags":[
        "designer"
    ],
    "wof:name":"Industrial Designline",
    "wof:placetype":"venue"
},
  "geometry": {"coordinates":[-122.011295,37.192302],"type":"Point"}
}