{
  "type": "Feature",
  "properties": {
    "addr:full":"8531 Thys Ct Sacramento CA 95828",
    "addr:housenumber":"8531",
    "addr:postcode":"95828",
    "addr:street":"Thys Ct",
    "iso:country":"US",
    "sg:address":"8531 Thys Ct",
    "sg:city":"Sacramento",
    "sg:classifiers":[
        {
            "category":"Restaurant",
            "type":"Food & Drink"
        }
    ],
    "sg:phone":"+1 916 686 6899",
    "sg:postcode":"95828",
    "sg:province":"CA",
    "sg:tags":[
        "eating"
    ],
    "wof:name":"J S Soft Ice Cream",
    "wof:placetype":"venue"
},
  "geometry": {"coordinates":[-121.387522,38.51887],"type":"Point"}
}