{
  "type": "Feature",
  "properties": {
    "addr:full":"1218 E Broadway Glendale CA 91205",
    "addr:housenumber":"1218",
    "addr:postcode":"91205",
    "addr:street":"E Broadway",
    "iso:country":"US",
    "sg:address":"1218 E Broadway",
    "sg:city":"Glendale",
    "sg:classifiers":[
        {
            "category":"Personal",
            "subcategory":"Nail Salon",
            "type":"Services"
        }
    ],
    "sg:phone":"+1 818 244 3155",
    "sg:postcode":"91205",
    "sg:province":"CA",
    "wof:name":"Natural Nails-Hair & Face",
    "wof:placetype":"venue"
},
  "geometry": {"coordinates":[-118.238998,34.146099],"type":"Point"}
}