{
  "type": "Feature",
  "properties": {
    "addr:full":"4466 E Pine Ave Fresno CA 93703",
    "addr:housenumber":"4466",
    "addr:postcode":"93703",
    "addr:street":"E Pine Ave",
    "iso:country":"US",
    "sg:address":"4466 E Pine Ave",
    "sg:city":"Fresno",
    "sg:classifiers":[
        {
            "category":"Professional",
            "type":"Services"
        }
    ],
    "sg:phone":"+1 559 252 0064",
    "sg:postcode":"93703",
    "sg:province":"CA",
    "wof:name":"Kare-A-Lot Kids",
    "wof:placetype":"venue"
},
  "geometry": {"coordinates":[-119.75125300000001,36.762217],"type":"Point"}
}