{
  "type": "Feature",
  "properties": {
    "iso:country":"US",
    "sg:address":"43130 Main St",
    "sg:city":"Fall River Mills",
    "sg:classifiers":[
        {
            "category":"Professional",
            "subcategory":"Lawyer & Legal Services",
            "type":"Services"
        }
    ],
    "sg:phone":"+1 530 336 5050",
    "sg:postcode":"96028",
    "sg:province":"CA",
    "sg:tags":[
        "attorney"
    ],
    "wof:name":"Nichols Catterton Downing Reed",
    "wof:placetype":"venue"
},
  "geometry": {"coordinates":[-121.43817300000001,41.002281],"type":"Point"}
}