{
  "type": "Feature",
  "properties": {
    "addr:full":"4985 Stoetz Ln Occidental CA 95472",
    "addr:postcode":"4985;95472",
    "addr:street":"Stoetz Ln",
    "iso:country":"US",
    "sg:address":"4985 Stoetz Ln",
    "sg:city":"Occidental",
    "sg:classifiers":[
        {
            "category":"Government",
            "subcategory":"Office",
            "type":"Public Place"
        }
    ],
    "sg:phone":"+1 707 874 3711",
    "sg:postcode":"95472",
    "sg:province":"CA",
    "wof:name":"Occidental Refuse Disposal",
    "wof:placetype":"venue"
},
  "geometry": {"coordinates":[-122.94567499999999,38.441352],"type":"Point"}
}