{
  "type": "Feature",
  "properties": {
    "addr:full":"300 Manhattan Beach Blvd Manhattan Beach CA 90266",
    "addr:housenumber":"300",
    "addr:postcode":"90266",
    "addr:street":"Manhattan Beach Blvd",
    "iso:country":"US",
    "sg:address":"300 Manhattan Beach Blvd",
    "sg:city":"Manhattan Beach",
    "sg:classifiers":[
        {
            "category":"Shopping",
            "subcategory":"Clothing, Apparel, & Fashions",
            "type":"Retail Goods"
        },
        {
            "category":"Shopping",
            "subcategory":"Jewelry",
            "type":"Retail Goods"
        }
    ],
    "sg:phone":"+1 310 798 4577",
    "sg:postcode":"90266",
    "sg:province":"CA",
    "sg:tags":[
        "clothing",
        "women's"
    ],
    "wof:name":"Lulu's",
    "wof:placetype":"venue"
},
  "geometry": {"coordinates":[-118.410004,33.885101],"type":"Point"}
}