{
  "type": "Feature",
  "properties": {
    "iso:country":"US",
    "sg:address":"995 E Kamm Ave",
    "sg:city":"Dinuba",
    "sg:classifiers":[
        {
            "category":"Building & Trades",
            "subcategory":"Landscaping Services",
            "type":"Services"
        }
    ],
    "sg:phone":"+1 559 591 6310",
    "sg:postcode":"93618",
    "sg:province":"CA",
    "wof:name":"Dugays Landscape",
    "wof:placetype":"venue"
},
  "geometry": {"coordinates":[-119.385266,36.531255],"type":"Point"}
}