{
  "type": "Feature",
  "properties": {
    "iso:country":"US",
    "sg:address":"5170 Greenbrier Avenue",
    "sg:city":"San Diego",
    "sg:classifiers":[
        {
            "category":"Education",
            "subcategory":"School",
            "type":"Public Place"
        }
    ],
    "sg:phone":"+1 619 583 3233",
    "sg:postcode":"92120",
    "sg:province":"CA",
    "sg:tags":[
        "high",
        "middle",
        "elementary"
    ],
    "wof:name":"Lewis Middle School",
    "wof:placetype":"venue"
},
  "geometry": {"coordinates":[-117.08241,32.795432],"type":"Point"}
}