{
  "type": "Feature",
  "properties": {
    "iso:country":"US",
    "sg:address":"1094 Cudahy Pl",
    "sg:city":"San Diego",
    "sg:classifiers":[
        {
            "category":"Organizations",
            "subcategory":"Professional Association",
            "type":"Services"
        }
    ],
    "sg:phone":"+1 619 232 7196",
    "sg:postcode":"92110",
    "sg:province":"CA",
    "wof:name":"Citizens Coordinate-Century 3",
    "wof:placetype":"venue"
},
  "geometry": {"coordinates":[-117.201317,32.766465],"type":"Point"}
}