{
  "type": "Feature",
  "properties": {
    "addr:full":"1525 MacArthur Boulevard Suite 11 Costa Mesa CA 92626",
    "addr:housenumber":"1525;11",
    "addr:postcode":"92626",
    "addr:street":"Macarthur Boulevard Suite",
    "iso:country":"US",
    "sg:address":"1525 MacArthur Boulevard Suite 11",
    "sg:city":"Costa Mesa",
    "sg:classifiers":[
        {
            "category":"Shopping",
            "subcategory":"Clothing, Apparel, & Fashions",
            "type":"Retail Goods"
        }
    ],
    "sg:phone":"+1 714 546 3438",
    "sg:postcode":"92626",
    "sg:province":"CA",
    "sg:tags":[
        "clothing",
        "women's"
    ],
    "wof:name":"Polynesian Design",
    "wof:placetype":"venue"
},
  "geometry": {"coordinates":[-117.92089199999999,33.701998],"type":"Point"}
}