{
  "type": "Feature",
  "properties": {
    "addr:full":"3501 McHenry Ave Modesto CA 95356",
    "addr:housenumber":"3501",
    "addr:postcode":"ca 95356",
    "addr:street":"Mchenry Ave",
    "iso:country":"US",
    "sg:address":"3501 McHenry Ave",
    "sg:city":"Modesto",
    "sg:classifiers":[
        {
            "category":"Cinema",
            "subcategory":"Movie Rental",
            "type":"Entertainment"
        }
    ],
    "sg:phone":"+1 209 572 2414",
    "sg:postcode":"95356",
    "sg:province":"CA",
    "sg:tags":[
        "leasing",
        "video",
        "disc",
        "tape"
    ],
    "wof:name":"Hollywood Video",
    "wof:placetype":"venue"
},
  "geometry": {"coordinates":[-120.994325,37.691161],"type":"Point"}
}