{
  "type": "Feature",
  "properties": {
    "addr:full":"6251 Eastside Rd Redding CA 96001",
    "addr:housenumber":"6251",
    "addr:postcode":"96001",
    "addr:street":"Eastside Rd",
    "iso:country":"US",
    "sg:address":"6251 Eastside Rd",
    "sg:city":"Redding",
    "sg:classifiers":[
        {
            "category":"Retail",
            "subcategory":"Auto Repair",
            "type":"Services"
        }
    ],
    "sg:phone":"+1 530 241 3320",
    "sg:postcode":"96001",
    "sg:province":"CA",
    "sg:tags":[
        "body",
        "automobile",
        "painting",
        "repairing"
    ],
    "sg:website":"http://reddingcollisioncenter.com",
    "wof:name":"Redding Collision Center Inc.",
    "wof:placetype":"venue"
},
  "geometry": {"coordinates":[-122.38215700000001,40.524909],"type":"Point"}
}