{
  "type": "Feature",
  "properties": {
    "addr:full":"14020 Pioneer Blvd Norwalk CA 90650",
    "addr:housenumber":"14020",
    "addr:postcode":"90650",
    "addr:street":"Pioneer Blvd",
    "iso:country":"US",
    "sg:address":"14020 Pioneer Blvd",
    "sg:city":"Norwalk",
    "sg:classifiers":[
        {
            "category":"Shopping",
            "subcategory":"Shoes",
            "type":"Retail Goods"
        }
    ],
    "sg:phone":"+1 562 466 1888",
    "sg:postcode":"90650",
    "sg:province":"CA",
    "sg:tags":[
        "store"
    ],
    "wof:name":"Family Shoe Store",
    "wof:placetype":"venue"
},
  "geometry": {"coordinates":[-118.237318,33.903899],"type":"Point"}
}