{
  "type": "Feature",
  "properties": {
    "iso:country":"US",
    "sg:address":"1720 Pacific Coast Hwy",
    "sg:city":"Huntington Beach",
    "sg:classifiers":[
        {
            "category":"Professional",
            "subcategory":"Business Services",
            "type":"Services"
        }
    ],
    "sg:phone":"+1 714 969 7001",
    "sg:postcode":"92648",
    "sg:province":"CA",
    "wof:name":"Coastline Trading Group",
    "wof:placetype":"venue"
},
  "geometry": {"coordinates":[-118.013149,33.665223],"type":"Point"}
}