{
  "type": "Feature",
  "properties": {
    "addr:full":"925 Lakeville St Petaluma CA 94952",
    "addr:housenumber":"925",
    "addr:postcode":"94952",
    "addr:street":"Lakeville St",
    "iso:country":"US",
    "sg:address":"925 Lakeville St",
    "sg:city":"Petaluma",
    "sg:classifiers":[
        {
            "category":"Professional",
            "subcategory":"Lawyer & Legal Services",
            "type":"Services"
        }
    ],
    "sg:phone":"+1 707 935 0373",
    "sg:postcode":"94952",
    "sg:province":"CA",
    "wof:name":"Beresky Timothy J Law Office",
    "wof:placetype":"venue"
},
  "geometry": {"coordinates":[-122.623136,38.235449],"type":"Point"}
}