{
  "type": "Feature",
  "properties": {
    "addr:full":"2433 Carleton St Berkeley CA 94704",
    "addr:housenumber":"2433",
    "addr:postcode":"94704",
    "addr:street":"Carleton St",
    "iso:country":"US",
    "sg:address":"2433 Carleton St",
    "sg:city":"Berkeley",
    "sg:classifiers":[
        {
            "category":"Health Services",
            "subcategory":"Clinic",
            "type":"Services"
        }
    ],
    "sg:phone":"+1 510 548 0161",
    "sg:postcode":"94704",
    "sg:province":"CA",
    "sg:tags":[
        "counseling",
        "mental"
    ],
    "wof:name":"Sara Grunstein",
    "wof:placetype":"venue"
},
  "geometry": {"coordinates":[-122.258825,37.862354],"type":"Point"}
}