{
  "type": "Feature",
  "properties": {
    "addr:full":"43833 Cameron Hills Dr Fremont CA 94539",
    "addr:housenumber":"43833",
    "addr:postcode":"94539",
    "addr:street":"Cameron Hills Dr",
    "iso:country":"US",
    "sg:address":"43833 Cameron Hills Dr",
    "sg:city":"Fremont",
    "sg:classifiers":[
        {
            "category":"Building & Trades",
            "subcategory":"Construction",
            "type":"Services"
        }
    ],
    "sg:phone":"+1 510 687 1010",
    "sg:postcode":"94539",
    "sg:province":"CA",
    "sg:tags":[
        "coping",
        "plastering",
        "tiling",
        "pool",
        "swimming"
    ],
    "wof:name":"Mission Valley Pool Svc",
    "wof:placetype":"venue"
},
  "geometry": {"coordinates":[-121.93424,37.518021],"type":"Point"}
}