{
  "type": "Feature",
  "properties": {
    "addr:full":"61 Rocket Cir Rancho Cordova CA 95742",
    "addr:housenumber":"61",
    "addr:postcode":"95742",
    "addr:street":"Rocket Cir",
    "iso:country":"US",
    "sg:address":"61 Rocket Cir",
    "sg:city":"Rancho Cordova",
    "sg:classifiers":[
        {
            "category":"Real Estate",
            "subcategory":"Real Estate Operator",
            "type":"Services"
        }
    ],
    "sg:phone":"+1 916 351 0251",
    "sg:postcode":"95742",
    "sg:province":"CA",
    "sg:tags":[
        "mobile",
        "home",
        "community"
    ],
    "wof:name":"Twilight Rv & Mobile Home Park",
    "wof:placetype":"venue"
},
  "geometry": {"coordinates":[-121.21437,38.630874],"type":"Point"}
}