{
  "type": "Feature",
  "properties": {
    "addr:full":"6505 Wilshire Blvd Los Angeles CA 90048",
    "addr:housenumber":"6505",
    "addr:postcode":"90048",
    "addr:street":"Wilshire Blvd",
    "iso:country":"US",
    "sg:address":"6505 Wilshire Blvd",
    "sg:city":"Los Angeles",
    "sg:classifiers":[
        {
            "category":"Professional",
            "subcategory":"Research",
            "type":"Services"
        }
    ],
    "sg:phone":"+1 323 761 8700",
    "sg:postcode":"90048",
    "sg:province":"CA",
    "sg:tags":[
        "foundation",
        "philanthropic"
    ],
    "sg:website":"www.jewishfoundationla.org",
    "wof:name":"Jewish Community Foundation",
    "wof:placetype":"venue"
},
  "geometry": {"coordinates":[-118.370018,34.063992],"type":"Point"}
}