{
  "type": "Feature",
  "properties": {
    "iso:country":"US",
    "sg:address":"20443 Gas Point Rd",
    "sg:city":"Cottonwood",
    "sg:classifiers":[
        {
            "category":"Personal",
            "subcategory":"Beauty Salon",
            "type":"Services"
        }
    ],
    "sg:phone":"+1 530 347 3345",
    "sg:postcode":"96022",
    "sg:province":"CA",
    "wof:name":"Liz's Beauty Shop",
    "wof:placetype":"venue"
},
  "geometry": {"coordinates":[-122.292018,40.389301],"type":"Point"}
}