{
  "type": "Feature",
  "properties": {
    "addr:full":"2701 Stone Valley Rd Alamo CA 94507",
    "addr:housenumber":"2701",
    "addr:postcode":"94507",
    "addr:street":"Stone Valley Rd",
    "iso:country":"US",
    "sg:address":"2701 Stone Valley Rd",
    "sg:city":"Alamo",
    "sg:classifiers":[
        {
            "category":"Recreation",
            "type":"Entertainment"
        }
    ],
    "sg:phone":"+1 925 837 2428",
    "sg:postcode":"94507",
    "sg:province":"CA",
    "sg:tags":[
        "instruction",
        "swimming"
    ],
    "wof:name":"Sue's Swim School",
    "wof:placetype":"venue"
},
  "geometry": {"coordinates":[-121.997186,37.847454],"type":"Point"}
}