{
  "type": "Feature",
  "properties": {
    "iso:country":"US",
    "sg:address":"700 N Pacific Coast Hwy",
    "sg:city":"Redondo Beach",
    "sg:classifiers":[
        {
            "category":"Professional",
            "subcategory":"Computer Services",
            "type":"Services"
        }
    ],
    "sg:phone":"+1 310 374 4336",
    "sg:postcode":"90277",
    "sg:province":"CA",
    "sg:tags":[
        "processing",
        "datum"
    ],
    "wof:name":"Red Stamp LLC",
    "wof:placetype":"venue"
},
  "geometry": {"coordinates":[-118.389804,33.853252],"type":"Point"}
}