{
  "type": "Feature",
  "properties": {
    "iso:country":"US",
    "sg:address":"1675 Ramstree Dr",
    "sg:city":"San Jose",
    "sg:classifiers":[
        {
            "category":"Local Transit",
            "type":"Transportation"
        }
    ],
    "sg:phone":"+1 408 866 6608",
    "sg:postcode":"95131",
    "sg:province":"CA",
    "sg:tags":[
        "airport"
    ],
    "wof:name":"SJC Airporter Shuttle",
    "wof:placetype":"venue"
},
  "geometry": {"coordinates":[-121.88085599999999,37.394684],"type":"Point"}
}