{
  "type": "Feature",
  "properties": {
    "iso:country":"US",
    "sg:address":"3610 1st St",
    "sg:city":"Riverside",
    "sg:classifiers":[
        {
            "category":"Professional",
            "subcategory":"Secretarial Services",
            "type":"Services"
        }
    ],
    "sg:phone":"+1 951 684 7977",
    "sg:postcode":"92501",
    "sg:province":"CA",
    "sg:tags":[
        "reporting"
    ],
    "wof:name":"Hutchings Court Reporters LLC",
    "wof:placetype":"venue"
},
  "geometry": {"coordinates":[-117.369861,33.988588],"type":"Point"}
}