{
  "type": "Feature",
  "properties": {
    "addr:full":"1821 Lakeville Hwy Petaluma CA 94954",
    "addr:housenumber":"1821",
    "addr:postcode":"94954",
    "addr:street":"Lakeville Hwy",
    "iso:country":"US",
    "sg:address":"1821 Lakeville Hwy",
    "sg:city":"Petaluma",
    "sg:classifiers":[
        {
            "category":"Real Estate",
            "subcategory":"Real Estate Operator",
            "type":"Services"
        }
    ],
    "sg:phone":"+1 707 763 3344",
    "sg:postcode":"94954",
    "sg:province":"CA",
    "sg:tags":[
        "mobile",
        "home",
        "community"
    ],
    "wof:name":"Littlewoods Mobile Villa",
    "wof:placetype":"venue"
},
  "geometry": {"coordinates":[-122.610525,38.233208],"type":"Point"}
}