{
  "type": "Feature",
  "properties": {
    "iso:country":"US",
    "sg:address":"3744 E Wawona Ave",
    "sg:city":"Fresno",
    "sg:classifiers":[
        {
            "category":"Wholesale",
            "subcategory":"Construction Materials",
            "type":"Manufacturing & Wholesale Goods"
        }
    ],
    "sg:phone":"+1 559 266 3600",
    "sg:postcode":"93725",
    "sg:province":"CA",
    "sg:tags":[
        "lumber"
    ],
    "wof:name":"Hardwoods Inc California",
    "wof:placetype":"venue"
},
  "geometry": {"coordinates":[-119.725093,36.682375],"type":"Point"}
}