{
  "type": "Feature",
  "properties": {
    "addr:full":"1405 S Bascom Ave San Jose CA 95128",
    "addr:housenumber":"1405",
    "addr:postcode":"95128",
    "addr:street":"S Bascom Ave",
    "iso:country":"US",
    "sg:address":"1405 S Bascom Ave",
    "sg:city":"San Jose",
    "sg:classifiers":[
        {
            "category":"Real Estate",
            "subcategory":"Real Estate Services",
            "type":"Services"
        }
    ],
    "sg:phone":"+1 408 885 1133",
    "sg:postcode":"95128",
    "sg:province":"CA",
    "sg:tags":[
        "company",
        "title"
    ],
    "wof:name":"Western Title Reporting Svc",
    "wof:placetype":"venue"
},
  "geometry": {"coordinates":[-121.931754,37.298155],"type":"Point"}
}