{
  "type": "Feature",
  "properties": {
    "iso:country":"US",
    "sg:address":"1520 Robyn Rd",
    "sg:city":"Escondido",
    "sg:classifiers":[
        {
            "category":"Health Services",
            "subcategory":"Doctor",
            "type":"Services"
        }
    ],
    "sg:phone":"+1 760 743 4855",
    "sg:postcode":"92025",
    "sg:province":"CA",
    "sg:tags":[
        "physician",
        "family",
        "practice",
        "surgeons",
        "medicine"
    ],
    "wof:name":"Oretsky, Martin Md Inc A P",
    "wof:placetype":"venue"
},
  "geometry": {"coordinates":[-117.064415,33.110979],"type":"Point"}
}