{
  "type": "Feature",
  "properties": {
    "iso:country":"US",
    "sg:address":"9 Kearny Street",
    "sg:city":"San Francisco",
    "sg:classifiers":[
        {
            "category":"Professional",
            "subcategory":"Accounting & Tax Preparation",
            "type":"Services"
        }
    ],
    "sg:phone":"+1 415 546 7718",
    "sg:postcode":"94108",
    "sg:province":"CA",
    "sg:tags":[
        "accountant"
    ],
    "wof:name":"Chan & Leung Llp",
    "wof:placetype":"venue"
},
  "geometry": {"coordinates":[-122.403578,37.787815],"type":"Point"}
}