{
  "type": "Feature",
  "properties": {
    "addr:full":"78645 Moonstone Ln Palm Desert CA 92211",
    "addr:housenumber":"78645",
    "addr:postcode":"ca 92211",
    "addr:street":"Moonstone Ln",
    "iso:country":"US",
    "sg:address":"78645 Moonstone Ln",
    "sg:city":"Palm Desert",
    "sg:classifiers":[
        {
            "category":"Retail",
            "subcategory":"Repair Shop",
            "type":"Services"
        }
    ],
    "sg:phone":"+1 760 200 0290",
    "sg:postcode":"92211",
    "sg:province":"CA",
    "sg:tags":[
        "water",
        "equipment",
        "softening"
    ],
    "wof:name":"Fresh Water Systems",
    "wof:placetype":"venue"
},
  "geometry": {"coordinates":[-116.287262,33.787614],"type":"Point"}
}