{
  "type": "Feature",
  "properties": {
    "iso:country":"US",
    "sg:address":"436 5th St",
    "sg:city":"Colusa",
    "sg:classifiers":[
        {
            "category":"Professional",
            "type":"Services"
        }
    ],
    "sg:phone":"+1 530 458 8395",
    "sg:postcode":"95932",
    "sg:province":"CA",
    "wof:name":"Morris E Moody",
    "wof:placetype":"venue"
},
  "geometry": {"coordinates":[-122.00884600000001,39.211949],"type":"Point"}
}