{
  "type": "Feature",
  "properties": {
    "addr:full":"1755 Creekside Oaks Dr # 100 Sacramento CA 95833",
    "addr:housenumber":"1755",
    "addr:postcode":"95833",
    "addr:street":"Creekside Oaks Dr # 100",
    "iso:country":"US",
    "sg:address":"1755 Creekside Oaks Dr # 100",
    "sg:city":"Sacramento",
    "sg:classifiers":[
        {
            "category":"Structure",
            "subcategory":"Office Building",
            "type":"Public Place"
        }
    ],
    "sg:phone":"+1 916 263 5506",
    "sg:postcode":"95833",
    "sg:province":"CA",
    "sg:tags":[
        "park"
    ],
    "wof:name":"Seismic Safety Commission, California",
    "wof:placetype":"venue"
},
  "geometry": {"coordinates":[-121.49958700000001,38.609371],"type":"Point"}
}