{
  "type": "Feature",
  "properties": {
    "addr:full":"800 Wilshire Blvd Los Angeles CA 90017",
    "addr:housenumber":"800",
    "addr:postcode":"90017",
    "addr:street":"Wilshire Blvd",
    "iso:country":"US",
    "sg:address":"800 Wilshire Blvd",
    "sg:city":"Los Angeles",
    "sg:classifiers":[
        {
            "category":"Professional",
            "subcategory":"Lawyer & Legal Services",
            "type":"Services"
        }
    ],
    "sg:phone":"+1 213 622 4750",
    "sg:postcode":"90017",
    "sg:province":"CA",
    "wof:name":"Crouchley John S Atty",
    "wof:placetype":"venue"
},
  "geometry": {"coordinates":[-118.258638,34.049348],"type":"Point"}
}