{
  "type": "Feature",
  "properties": {
    "addr:full":"29300 Kohoutek Way Union City CA 94587",
    "addr:housenumber":"29300",
    "addr:postcode":"94587",
    "addr:street":"Kohoutek Way",
    "iso:country":"US",
    "sg:address":"29300 Kohoutek Way",
    "sg:city":"Union City",
    "sg:classifiers":[
        {
            "category":"Professional",
            "subcategory":"Computer Services",
            "type":"Services"
        }
    ],
    "sg:phone":"+1 510 675 9800",
    "sg:postcode":"94587",
    "sg:province":"CA",
    "sg:tags":[
        "repair"
    ],
    "sg:website":"www.firmtek.com",
    "wof:name":"Firmtek LLC",
    "wof:placetype":"venue"
},
  "geometry": {"coordinates":[-122.295428,37.608627],"type":"Point"}
}