{
  "type": "Feature",
  "properties": {
    "addr:full":"8720 Melrose Ave Los Angeles CA 90069",
    "addr:housenumber":"8720",
    "addr:postcode":"90069",
    "addr:street":"Melrose Ave",
    "iso:country":"US",
    "sg:address":"8720 Melrose Ave",
    "sg:city":"Los Angeles",
    "sg:classifiers":[
        {
            "category":"Professional",
            "subcategory":"Business Services",
            "type":"Services"
        }
    ],
    "sg:phone":"+1 310 659 3531",
    "sg:postcode":"90069",
    "sg:province":"CA",
    "sg:tags":[
        "interior",
        "consultant",
        "design",
        "decorator"
    ],
    "wof:name":"Hallberg & Wiseley",
    "wof:placetype":"venue"
},
  "geometry": {"coordinates":[-118.384685,34.080796],"type":"Point"}
}