{
  "type": "Feature",
  "properties": {
    "addr:full":"970 Roosevelt Ste 200 Irvine CA 92620",
    "addr:housenumber":"970",
    "addr:postcode":"92620",
    "addr:street":"Roosevelt Ste 200",
    "iso:country":"US",
    "sg:address":"970 Roosevelt Ste 200",
    "sg:city":"Irvine",
    "sg:classifiers":[
        {
            "category":"Manufacturing",
            "subcategory":"Leather Goods",
            "type":"Manufacturing & Wholesale Goods"
        }
    ],
    "sg:phone":"+1 949 748 8008",
    "sg:postcode":"92620",
    "sg:province":"CA",
    "sg:website":"www.bagbeltbeyond.com",
    "wof:name":"Bag Belt Beyond",
    "wof:placetype":"venue"
},
  "geometry": {"coordinates":[-117.76669,33.6948],"type":"Point"}
}