{
  "type": "Feature",
  "properties": {
    "addr:full":"13670 Montague St Pacoima CA 91331",
    "addr:housenumber":"13670",
    "addr:postcode":"91331",
    "addr:street":"Montague St",
    "iso:country":"US",
    "sg:address":"13670 Montague St",
    "sg:city":"Pacoima",
    "sg:classifiers":[
        {
            "category":"Education",
            "subcategory":"School",
            "type":"Public Place"
        }
    ],
    "sg:phone":"+1 818 892 1104",
    "sg:postcode":"91331",
    "sg:province":"CA",
    "wof:name":"Canterbury Ave Elementary Schl",
    "wof:placetype":"venue"
},
  "geometry": {"coordinates":[-118.429605,34.234203],"type":"Point"}
}