{
  "type": "Feature",
  "properties": {
    "iso:country":"US",
    "sg:address":"1575 Westwood Blvd",
    "sg:city":"Los Angeles",
    "sg:classifiers":[
        {
            "category":"Home & Garden",
            "subcategory":"Furniture",
            "type":"Retail Goods"
        }
    ],
    "sg:phone":"+1 310 453 2255",
    "sg:postcode":"90024",
    "sg:province":"CA",
    "wof:name":"Roma Design",
    "wof:placetype":"venue"
},
  "geometry": {"coordinates":[-118.440349,34.053747],"type":"Point"}
}