{
  "type": "Feature",
  "properties": {
    "addr:full":"9335 Airway Rd San Diego CA 92154",
    "addr:housenumber":"9335",
    "addr:postcode":"92154",
    "addr:street":"Airway Rd",
    "iso:country":"US",
    "sg:address":"9335 Airway Rd",
    "sg:city":"San Diego",
    "sg:classifiers":[
        {
            "category":"Manufacturing",
            "subcategory":"Rubber & Plastics",
            "type":"Manufacturing & Wholesale Goods"
        }
    ],
    "sg:phone":"+1 619 710 4805",
    "sg:postcode":"92154",
    "sg:province":"CA",
    "wof:name":"Industrial Plastics Solutions",
    "wof:placetype":"venue"
},
  "geometry": {"coordinates":[-116.940787,32.560249],"type":"Point"}
}