{
  "type": "Feature",
  "properties": {
    "iso:country":"US",
    "sg:address":"216 E Ave K",
    "sg:city":"Lancaster",
    "sg:classifiers":[
        {
            "category":"Manufacturing",
            "subcategory":"Furniture",
            "type":"Manufacturing & Wholesale Goods"
        }
    ],
    "sg:phone":"+1 661 729 8931",
    "sg:postcode":"93535",
    "sg:province":"CA",
    "sg:tags":[
        "wood",
        "household",
        "cabinet",
        "kitchen",
        "mfg"
    ],
    "wof:name":"Radford Cabinets Inc",
    "wof:placetype":"venue"
},
  "geometry": {"coordinates":[-118.125081,34.674922],"type":"Point"}
}