{
  "type": "Feature",
  "properties": {
    "addr:full":"1371 N Vallejo Way Upland CA 91786",
    "addr:housenumber":"1371",
    "addr:postcode":"91786",
    "addr:street":"N Vallejo Way",
    "iso:country":"US",
    "sg:address":"1371 N Vallejo Way",
    "sg:city":"Upland",
    "sg:classifiers":[
        {
            "category":"Professional",
            "type":"Services"
        }
    ],
    "sg:phone":"+1 909 608 0244",
    "sg:postcode":"91786",
    "sg:province":"CA",
    "wof:name":"W Derald Miles Machine",
    "wof:placetype":"venue"
},
  "geometry": {"coordinates":[-117.659761,34.114136],"type":"Point"}
}