{
  "type": "Feature",
  "properties": {
    "iso:country":"US",
    "sg:address":"8860 Welk View Dr",
    "sg:city":"Escondido",
    "sg:classifiers":[
        {
            "category":"Travel",
            "subcategory":"Resort",
            "type":"Entertainment"
        }
    ],
    "sg:phone":"+1 760 749 5079",
    "sg:postcode":"92026",
    "sg:province":"CA",
    "wof:name":"Welk Resort Group",
    "wof:placetype":"venue"
},
  "geometry": {"coordinates":[-117.129701,33.235449],"type":"Point"}
}