{
  "type": "Feature",
  "properties": {
    "iso:country":"US",
    "sg:address":"15504 S Western Ave",
    "sg:city":"Gardena",
    "sg:classifiers":[
        {
            "category":"Real Estate",
            "subcategory":"Real Estate Agent",
            "type":"Services"
        }
    ],
    "sg:phone":"+1 310 808 0650",
    "sg:postcode":"90249",
    "sg:province":"CA",
    "sg:tags":[
        "management"
    ],
    "sg:website":"www.theabbeyco.com",
    "wof:name":"Abbey Co",
    "wof:placetype":"venue"
},
  "geometry": {"coordinates":[-118.30914,33.888528],"type":"Point"}
}