{
  "type": "Feature",
  "properties": {
    "addr:full":"1157 6th Ave San Diego CA 92101",
    "addr:housenumber":"1157",
    "addr:postcode":"92101",
    "addr:street":"6Th Ave",
    "iso:country":"US",
    "sg:address":"1157 6th Ave",
    "sg:city":"San Diego",
    "sg:classifiers":[
        {
            "category":"Restaurant",
            "type":"Food & Drink"
        }
    ],
    "sg:phone":"+1 619 338 0400",
    "sg:postcode":"92101",
    "sg:province":"CA",
    "sg:tags":[
        "italian"
    ],
    "sg:website":"www.mamaguccis.com/",
    "wof:name":"Mama Gucci's",
    "wof:placetype":"venue"
},
  "geometry": {"coordinates":[-117.158997,32.7173],"type":"Point"}
}