{
  "type": "Feature",
  "properties": {
    "addr:full":"13296 Appleby Ct Moreno Valley CA 92553",
    "addr:housenumber":"13296",
    "addr:postcode":"92553",
    "addr:street":"Appleby Ct",
    "iso:country":"US",
    "sg:address":"13296 Appleby Ct",
    "sg:city":"Moreno Valley",
    "sg:classifiers":[
        {
            "category":"Retail",
            "subcategory":"Laundry & Dry Cleaning",
            "type":"Services"
        }
    ],
    "sg:phone":"+1 951 653 8971",
    "sg:postcode":"92553",
    "sg:province":"CA",
    "sg:tags":[
        "cleaners",
        "rug",
        "carpet"
    ],
    "wof:name":"Best Carpet Cleaner",
    "wof:placetype":"venue"
},
  "geometry": {"coordinates":[-117.26297700000001,33.92698],"type":"Point"}
}