{
  "type": "Feature",
  "properties": {
    "addr:full":"2930 W Imperial Hwy Inglewood CA 90303",
    "addr:housenumber":"2930",
    "addr:postcode":"90303",
    "addr:street":"W Imperial Hwy",
    "iso:country":"US",
    "sg:address":"2930 W Imperial Hwy",
    "sg:city":"Inglewood",
    "sg:classifiers":[
        {
            "category":"Government",
            "subcategory":"Office",
            "type":"Public Place"
        }
    ],
    "sg:phone":"+1 323 779 2199",
    "sg:postcode":"90303",
    "sg:province":"CA",
    "sg:tags":[
        "job"
    ],
    "wof:name":"Employment Development CA Dept",
    "wof:placetype":"venue"
},
  "geometry": {"coordinates":[-118.32572,33.930824],"type":"Point"}
}