{
  "type": "Feature",
  "properties": {
    "addr:full":"14785 Jeffrey Rd Irvine CA 92618",
    "addr:housenumber":"14785",
    "addr:postcode":"92618",
    "addr:street":"Jeffrey Rd",
    "iso:country":"US",
    "sg:address":"14785 Jeffrey Rd",
    "sg:city":"Irvine",
    "sg:classifiers":[
        {
            "category":"Education",
            "subcategory":"Kindergarten",
            "type":"Public Place"
        }
    ],
    "sg:phone":"+1 949 551 4860",
    "sg:postcode":"92618",
    "sg:province":"CA",
    "sg:tags":[
        "school",
        "driving"
    ],
    "sg:website":"www.aateendriving.com",
    "wof:name":"AA Teen Driving Academy",
    "wof:placetype":"venue"
},
  "geometry": {"coordinates":[-117.77193200000001,33.688566],"type":"Point"}
}