{
  "type": "Feature",
  "properties": {
    "addr:full":"4780 E Jensen Ave Fresno CA 93725",
    "addr:housenumber":"4780",
    "addr:postcode":"93725",
    "addr:street":"E Jensen Ave",
    "iso:country":"US",
    "sg:address":"4780 E Jensen Ave",
    "sg:city":"Fresno",
    "sg:classifiers":[
        {
            "category":"Manufacturing",
            "subcategory":"Tools & Machinery",
            "type":"Manufacturing & Wholesale Goods"
        },
        {
            "category":"Building & Trades",
            "subcategory":"Equipment Rental",
            "type":"Services"
        }
    ],
    "sg:phone":"+1 559 263 9622",
    "sg:postcode":"93725",
    "sg:province":"CA",
    "sg:tags":[
        "construction",
        "yard",
        "store"
    ],
    "sg:website":"http://www.epwparts.com",
    "wof:name":"Equipment Parts Wholesale",
    "wof:placetype":"venue"
},
  "geometry": {"coordinates":[-119.738523,36.706819],"type":"Point"}
}