{
  "type": "Feature",
  "properties": {
    "addr:full":"671 Oak Grove Ave Menlo Park CA 94025",
    "addr:housenumber":"671",
    "addr:postcode":"94025",
    "addr:street":"Oak Grove Ave",
    "iso:country":"US",
    "sg:address":"671 Oak Grove Ave",
    "sg:city":"Menlo Park",
    "sg:classifiers":[
        {
            "category":"Health Services",
            "subcategory":"Doctor",
            "type":"Services"
        }
    ],
    "sg:phone":"+1 650 473 1686",
    "sg:postcode":"94025",
    "sg:province":"CA",
    "sg:tags":[
        "physician",
        "surgeon"
    ],
    "wof:name":"Carmen Roman MD",
    "wof:placetype":"venue"
},
  "geometry": {"coordinates":[-122.185766,37.452531],"type":"Point"}
}