{
  "type": "Feature",
  "properties": {
    "addr:full":"2701 K St Sacramento CA 95816",
    "addr:housenumber":"2701",
    "addr:postcode":"95816",
    "addr:street":"K St",
    "iso:country":"US",
    "sg:address":"2701 K St",
    "sg:city":"Sacramento",
    "sg:classifiers":[
        {
            "category":"Professional",
            "subcategory":"Advertising",
            "type":"Services"
        }
    ],
    "sg:phone":"+1 916 492 9657",
    "sg:postcode":"95816",
    "sg:province":"CA",
    "wof:name":"Hunter Gatherers Inc",
    "wof:placetype":"venue"
},
  "geometry": {"coordinates":[-121.469686,38.572745],"type":"Point"}
}