{
  "type": "Feature",
  "properties": {
    "iso:country":"US",
    "sg:address":"16260 Ventura Blvd",
    "sg:city":"Encino",
    "sg:classifiers":[
        {
            "category":"Health Services",
            "subcategory":"Doctor",
            "type":"Services"
        }
    ],
    "sg:phone":"+1 818 905 9700",
    "sg:postcode":"91436",
    "sg:province":"CA",
    "sg:tags":[
        "physician",
        "surgeon"
    ],
    "wof:name":"Alpha Health Care Inc",
    "wof:placetype":"venue"
},
  "geometry": {"coordinates":[-118.48507499999999,34.15641],"type":"Point"}
}