{
  "type": "Feature",
  "properties": {
    "addr:full":"1245 University Ave Riverside CA 92507",
    "addr:housenumber":"1245",
    "addr:postcode":"92507",
    "addr:street":"University Ave",
    "iso:country":"US",
    "sg:address":"1245 University Ave",
    "sg:city":"Riverside",
    "sg:classifiers":[
        {
            "category":"Restaurant",
            "type":"Food & Drink"
        }
    ],
    "sg:menulink":"http://www.allmenus.com/ca/riverside/8512-dennys/menu/",
    "sg:phone":"+1 951 684 6171",
    "sg:postcode":"92507",
    "sg:province":"CA",
    "sg:tags":[
        "american",
        "diner"
    ],
    "wof:name":"Denny's",
    "wof:placetype":"venue"
},
  "geometry": {"coordinates":[-117.338804,33.97564],"type":"Point"}
}