{
  "type": "Feature",
  "properties": {
    "addr:full":"25129 2nd St Hayward CA 94541",
    "addr:housenumber":"25129",
    "addr:postcode":"94541",
    "addr:street":"2Nd St",
    "iso:country":"US",
    "sg:address":"25129 2nd St",
    "sg:city":"Hayward",
    "sg:classifiers":[
        {
            "category":"Professional",
            "type":"Services"
        }
    ],
    "sg:phone":"+1 510 583 7717",
    "sg:postcode":"94541",
    "sg:province":"CA",
    "wof:name":"Samuel Cassi",
    "wof:placetype":"venue"
},
  "geometry": {"coordinates":[-122.05349699999999,37.668082],"type":"Point"}
}