{
  "type": "Feature",
  "properties": {
    "addr:full":"1499 Bayshore Hwy Ste 230 Burlingame CA 94010",
    "addr:housenumber":"1499",
    "addr:postcode":"94010",
    "addr:street":"Bayshore Hwy Ste 230",
    "iso:country":"US",
    "sg:address":"1499 Bayshore Hwy Ste 230",
    "sg:city":"Burlingame",
    "sg:classifiers":[
        {
            "category":"Professional",
            "subcategory":"Business Services",
            "type":"Services"
        }
    ],
    "sg:phone":"+1 650 697 7704",
    "sg:postcode":"94010",
    "sg:province":"CA",
    "sg:tags":[
        "delivery",
        "courier"
    ],
    "sg:website":"www.mrtruckinglogistics.com",
    "wof:name":"Mr Trucking",
    "wof:placetype":"venue"
},
  "geometry": {"coordinates":[-122.36660000000001,37.597092],"type":"Point"}
}