{
  "type": "Feature",
  "properties": {
    "iso:country":"US",
    "sg:address":"2400 Coffee Rd",
    "sg:city":"Modesto",
    "sg:classifiers":[
        {
            "category":"Retail",
            "subcategory":"Self-service Laundry",
            "type":"Services"
        }
    ],
    "sg:phone":"+1 209 574 5946",
    "sg:postcode":"95355",
    "sg:province":"CA",
    "wof:name":"Laundry Day",
    "wof:placetype":"venue"
},
  "geometry": {"coordinates":[-120.975725,37.676842],"type":"Point"}
}