{
  "type": "Feature",
  "properties": {
    "addr:full":"1403 N Lake Ave Pasadena CA 91104",
    "addr:housenumber":"1403",
    "addr:postcode":"91104",
    "addr:street":"N Lake Ave",
    "iso:country":"US",
    "sg:address":"1403 N Lake Ave",
    "sg:city":"Pasadena",
    "sg:classifiers":[
        {
            "category":"Wholesale",
            "subcategory":"Office Equipment",
            "type":"Manufacturing & Wholesale Goods"
        }
    ],
    "sg:phone":"+1 626 296 9544",
    "sg:postcode":"91104",
    "sg:province":"CA",
    "sg:tags":[
        "supply"
    ],
    "wof:name":"Standard Office Products",
    "wof:placetype":"venue"
},
  "geometry": {"coordinates":[-118.13227999999999,34.169451],"type":"Point"}
}