{
  "type": "Feature",
  "properties": {
    "iso:country":"US",
    "sg:address":"1894 Curtis St",
    "sg:city":"Loma Linda",
    "sg:classifiers":[
        {
            "category":"Social Services",
            "type":"Services"
        }
    ],
    "sg:phone":"+1 909 796 5589",
    "sg:postcode":"92354",
    "sg:province":"CA",
    "sg:tags":[
        "care",
        "center",
        "day"
    ],
    "wof:name":"Faith Adult Residential Faclty",
    "wof:placetype":"venue"
},
  "geometry": {"coordinates":[-117.24790900000001,34.068406],"type":"Point"}
}