{
  "type": "Feature",
  "properties": {
    "iso:country":"US",
    "sg:address":"3555 5th Ave",
    "sg:city":"San Diego",
    "sg:classifiers":[
        {
            "category":"Professional",
            "subcategory":"Lawyer & Legal Services",
            "type":"Services"
        }
    ],
    "sg:phone":"+1 619 692 0800",
    "sg:postcode":"92103",
    "sg:province":"CA",
    "wof:name":"Schaeffer James C",
    "wof:placetype":"venue"
},
  "geometry": {"coordinates":[-117.160004,32.742599],"type":"Point"}
}