{
  "type": "Feature",
  "properties": {
    "addr:full":"2703 Santa Monica Blvd Santa Monica CA 90404",
    "addr:housenumber":"2703",
    "addr:postcode":"90404",
    "addr:street":"Santa Monica Blvd",
    "iso:country":"US",
    "sg:address":"2703 Santa Monica Blvd",
    "sg:city":"Santa Monica",
    "sg:classifiers":[
        {
            "category":"Autos & Motor Vehicles",
            "subcategory":"Automobile Sales",
            "type":"Retail Goods"
        }
    ],
    "sg:phone":"+1 310 449 7771",
    "sg:postcode":"90404",
    "sg:province":"CA",
    "sg:tags":[
        "wholesale",
        "used",
        "sales",
        "car"
    ],
    "wof:name":"Omni Auto Trade",
    "wof:placetype":"venue"
},
  "geometry": {"coordinates":[-118.472612,34.034767],"type":"Point"}
}