{
  "type": "Feature",
  "properties": {
    "addr:full":"4850 Graywood Ave Long Beach CA 90808",
    "addr:housenumber":"4850",
    "addr:postcode":"90808",
    "addr:street":"Graywood Ave",
    "iso:country":"US",
    "sg:address":"4850 Graywood Ave",
    "sg:city":"Long Beach",
    "sg:classifiers":[
        {
            "category":"Professional",
            "subcategory":"Management & Consulting",
            "type":"Services"
        }
    ],
    "sg:phone":"+1 562 421 3085",
    "sg:postcode":"90808",
    "sg:province":"CA",
    "sg:tags":[
        "retail",
        "direct",
        "sales"
    ],
    "wof:name":"Logic Resources Inc",
    "wof:placetype":"venue"
},
  "geometry": {"coordinates":[-118.138104,33.843938],"type":"Point"}
}