{
  "type": "Feature",
  "properties": {
    "addr:full":"6191 Ave 290 Visalia CA 93277",
    "addr:housenumber":"6191",
    "addr:postcode":"93277",
    "addr:street":"Ave 290",
    "iso:country":"US",
    "sg:address":"6191 Ave 290",
    "sg:city":"Visalia",
    "sg:classifiers":[
        {
            "category":"Wholesale",
            "subcategory":"Groceries",
            "type":"Manufacturing & Wholesale Goods"
        }
    ],
    "sg:phone":"+1 559 651 3696",
    "sg:postcode":"93277",
    "sg:province":"CA",
    "sg:tags":[
        "grocer"
    ],
    "wof:name":"Costa Farms",
    "wof:placetype":"venue"
},
  "geometry": {"coordinates":[-119.435422,36.316247],"type":"Point"}
}