{
  "type": "Feature",
  "properties": {
    "iso:country":"US",
    "sg:address":"973 Chesterton Ave",
    "sg:city":"Redwood City",
    "sg:classifiers":[
        {
            "category":"Building & Trades",
            "subcategory":"Landscaping Services",
            "type":"Services"
        }
    ],
    "sg:phone":"+1 650 364 6268",
    "sg:postcode":"94061",
    "sg:province":"CA",
    "wof:name":"Clean Cut Garden Service",
    "wof:placetype":"venue"
},
  "geometry": {"coordinates":[-122.247899,37.463499],"type":"Point"}
}