{
  "type": "Feature",
  "properties": {
    "addr:full":"4200 Trabuco Road Suite 180 Irvine CA 92620",
    "addr:housenumber":"4200",
    "addr:postcode":"92620",
    "addr:street":"Trabuco Road Suite 180",
    "iso:country":"US",
    "sg:address":"4200 Trabuco Road Suite 180",
    "sg:city":"Irvine",
    "sg:classifiers":[
        {
            "category":"Health Services",
            "subcategory":"Health Practitioner",
            "type":"Services"
        },
        {
            "category":"Health Services",
            "subcategory":"Chiropractor",
            "type":"Services"
        }
    ],
    "sg:phone":"+1 949 552 1172",
    "sg:postcode":"92620",
    "sg:province":"CA",
    "sg:tags":[
        "nutritionist"
    ],
    "wof:name":"Perle Lisa DC",
    "wof:placetype":"venue"
},
  "geometry": {"coordinates":[-117.77948600000001,33.70845],"type":"Point"}
}