{
  "type": "Feature",
  "properties": {
    "iso:country":"US",
    "sg:address":"29363 Avocet Ln",
    "sg:city":"Laguna Niguel",
    "sg:classifiers":[
        {
            "category":"Wholesale",
            "subcategory":"Motor Vehicles",
            "type":"Manufacturing & Wholesale Goods"
        }
    ],
    "sg:phone":"+1 949 215 4666",
    "sg:postcode":"92677",
    "sg:province":"CA",
    "sg:tags":[
        "automobile"
    ],
    "wof:name":"Jimmy West Auto Co",
    "wof:placetype":"venue"
},
  "geometry": {"coordinates":[-117.710212,33.536491],"type":"Point"}
}