{
  "type": "Feature",
  "properties": {
    "iso:country":"US",
    "sg:address":"2170 Floral Way",
    "sg:city":"Santa Rosa",
    "sg:classifiers":[
        {
            "category":"Personal",
            "type":"Services"
        }
    ],
    "sg:phone":"+1 707 542 6989",
    "sg:postcode":"95403",
    "sg:province":"CA",
    "sg:tags":[
        "therapist",
        "massage"
    ],
    "wof:name":"Holistic Massage & Energy",
    "wof:placetype":"venue"
},
  "geometry": {"coordinates":[-122.75585100000001,38.463854],"type":"Point"}
}