{
  "type": "Feature",
  "properties": {
    "addr:full":"1345 Broadway Ave Stockton CA 95205",
    "addr:housenumber":"1345",
    "addr:postcode":"95205",
    "addr:street":"Broadway Ave",
    "iso:country":"US",
    "sg:address":"1345 Broadway Ave",
    "sg:city":"Stockton",
    "sg:classifiers":[
        {
            "category":"Wholesale",
            "subcategory":"Fruits & Vegetables",
            "type":"Manufacturing & Wholesale Goods"
        }
    ],
    "sg:phone":"+1 209 466 4581",
    "sg:postcode":"95205",
    "sg:province":"CA",
    "wof:name":"Bennys Produce",
    "wof:placetype":"venue"
},
  "geometry": {"coordinates":[-121.252983,37.982103],"type":"Point"}
}