{
  "type": "Feature",
  "properties": {
    "addr:full":"5924 Vanalden Ave Tarzana CA 91356",
    "addr:housenumber":"5924",
    "addr:postcode":"91356",
    "addr:street":"Vanalden Ave",
    "iso:country":"US",
    "sg:address":"5924 Vanalden Ave",
    "sg:city":"Tarzana",
    "sg:classifiers":[
        {
            "category":"Shopping",
            "subcategory":"Clothing, Apparel, & Fashions",
            "type":"Retail Goods"
        }
    ],
    "sg:phone":"+1 818 344 2349",
    "sg:postcode":"91356",
    "sg:province":"CA",
    "wof:name":"Kate Austin Designs",
    "wof:placetype":"venue"
},
  "geometry": {"coordinates":[-118.55021000000001,34.177229],"type":"Point"}
}