{
  "type": "Feature",
  "properties": {
    "iso:country":"US",
    "sg:address":"3205 Larga Ave",
    "sg:city":"Los Angeles",
    "sg:classifiers":[
        {
            "category":"Shopping",
            "subcategory":"Musical Instruments",
            "type":"Retail Goods"
        }
    ],
    "sg:phone":"+1 323 665 7530",
    "sg:postcode":"90039",
    "sg:province":"CA",
    "wof:name":"Atwater School of Guitar",
    "wof:placetype":"venue"
},
  "geometry": {"coordinates":[-118.254236,34.112954],"type":"Point"}
}