{
  "type": "Feature",
  "properties": {
    "iso:country":"US",
    "sg:address":"145 N 2nd St",
    "sg:city":"Chowchilla",
    "sg:classifiers":[
        {
            "category":"Health Services",
            "subcategory":"Optometrist",
            "type":"Services"
        }
    ],
    "sg:phone":"+1 559 665 3797",
    "sg:postcode":"93610",
    "sg:province":"CA",
    "wof:name":"Vision Enhancement",
    "wof:placetype":"venue"
},
  "geometry": {"coordinates":[-120.26066899999999,37.12318],"type":"Point"}
}