{
  "type": "Feature",
  "properties": {
    "iso:country":"US",
    "sg:address":"21706 Talisman St",
    "sg:city":"Torrance",
    "sg:classifiers":[
        {
            "category":"Building & Trades",
            "subcategory":"Construction",
            "type":"Services"
        }
    ],
    "sg:phone":"+1 310 375 0288",
    "sg:postcode":"90503",
    "sg:province":"CA",
    "sg:tags":[
        "roofing",
        "industrial",
        "contractors-commercial",
        "contractor"
    ],
    "wof:name":"Collins Brothers Roofing",
    "wof:placetype":"venue"
},
  "geometry": {"coordinates":[-118.357194,33.83187],"type":"Point"}
}