{
  "type": "Feature",
  "properties": {
    "addr:full":"22549 Hawthorne Blvd Torrance CA 90505",
    "addr:housenumber":"22549",
    "addr:postcode":"90505",
    "addr:street":"Hawthorne Blvd",
    "iso:country":"US",
    "sg:address":"22549 Hawthorne Blvd",
    "sg:city":"Torrance",
    "sg:classifiers":[
        {
            "category":"Restaurant",
            "type":"Food & Drink"
        }
    ],
    "sg:phone":"+1 310 373 7055",
    "sg:postcode":"90505",
    "sg:province":"CA",
    "sg:tags":[
        "korean"
    ],
    "wof:name":"Cho Dang Tofu",
    "wof:placetype":"venue"
},
  "geometry": {"coordinates":[-118.351204,33.823514],"type":"Point"}
}