{
  "type": "Feature",
  "properties": {
    "addr:full":"3351 el Camino Real Palo Alto CA 94306",
    "addr:housenumber":"3351",
    "addr:postcode":"94306",
    "addr:street":"El Camino Real",
    "iso:country":"US",
    "sg:address":"3351 el Camino Real",
    "sg:city":"Palo Alto",
    "sg:classifiers":[
        {
            "category":"Health Services",
            "subcategory":"Doctor",
            "type":"Services"
        }
    ],
    "sg:phone":"+1 650 599 0360",
    "sg:postcode":"94306",
    "sg:province":"CA",
    "sg:tags":[
        "physician",
        "surgeon"
    ],
    "wof:name":"Atherton Neurology Med Ofc",
    "wof:placetype":"venue"
},
  "geometry": {"coordinates":[-122.136983,37.420412],"type":"Point"}
}