{
  "type": "Feature",
  "properties": {
    "addr:full":"140 Lewis Road San Jose CA 95111",
    "addr:housenumber":"140",
    "addr:postcode":"95111",
    "addr:street":"Lewis Road",
    "iso:country":"US",
    "sg:address":"140 Lewis Road",
    "sg:city":"San Jose",
    "sg:classifiers":[
        {
            "category":"Professional",
            "type":"Services"
        }
    ],
    "sg:phone":"+1 408 227 7590",
    "sg:postcode":"95111",
    "sg:province":"CA",
    "wof:name":"A.P. Nigro Woodworking Services",
    "wof:placetype":"venue"
},
  "geometry": {"coordinates":[-121.845327,37.291439],"type":"Point"}
}