{
  "type": "Feature",
  "properties": {
    "addr:full":"14400 Bear Valley Rd Victorville CA 92392",
    "addr:housenumber":"14400",
    "addr:postcode":"92392",
    "addr:street":"Bear Valley Rd",
    "iso:country":"US",
    "sg:address":"14400 Bear Valley Rd",
    "sg:city":"Victorville",
    "sg:classifiers":[
        {
            "category":"Home & Garden",
            "subcategory":"Furniture",
            "type":"Retail Goods"
        }
    ],
    "sg:phone":"+1 760 843 5525",
    "sg:postcode":"92392",
    "sg:province":"CA",
    "sg:tags":[
        "mattress"
    ],
    "wof:name":"Select Comfort Corp",
    "wof:placetype":"venue"
},
  "geometry": {"coordinates":[-117.356047,34.470374],"type":"Point"}
}