{
  "type": "Feature",
  "properties": {
    "iso:country":"US",
    "sg:address":"3201 N Figueroa Street",
    "sg:city":"Los Angeles",
    "sg:classifiers":[
        {
            "category":"Building & Trades",
            "subcategory":"Cleaning & Sanitation",
            "type":"Services"
        }
    ],
    "sg:phone":"+1 323 276 1057",
    "sg:postcode":"90065",
    "sg:province":"CA",
    "sg:tags":[
        "carpet"
    ],
    "wof:name":"Primex Carpet & Blind",
    "wof:placetype":"venue"
},
  "geometry": {"coordinates":[-118.219427,34.086293],"type":"Point"}
}