{
  "type": "Feature",
  "properties": {
    "addr:full":"2000 Broad St San Luis Obispo CA 93401",
    "addr:housenumber":"2000",
    "addr:postcode":"93401",
    "addr:street":"Broad St",
    "iso:country":"US",
    "sg:address":"2000 Broad St",
    "sg:city":"San Luis Obispo",
    "sg:classifiers":[
        {
            "category":"Insurance",
            "subcategory":"Insurance Agent",
            "type":"Services"
        }
    ],
    "sg:phone":"+1 805 544 7212",
    "sg:postcode":"93401",
    "sg:province":"CA",
    "wof:name":"Aaron Corob Insurance",
    "wof:placetype":"venue"
},
  "geometry": {"coordinates":[-120.65845299999999,35.27218],"type":"Point"}
}