{
  "type": "Feature",
  "properties": {
    "addr:full":"880 E Alisal St Salinas CA 93905",
    "addr:housenumber":"880",
    "addr:postcode":"93905",
    "addr:street":"E Alisal St",
    "iso:country":"US",
    "sg:address":"880 E Alisal St",
    "sg:city":"Salinas",
    "sg:classifiers":[
        {
            "category":"Shopping",
            "subcategory":"Clothing, Apparel, & Fashions",
            "type":"Retail Goods"
        }
    ],
    "sg:phone":"+1 831 754 1181",
    "sg:postcode":"93905",
    "sg:province":"CA",
    "sg:tags":[
        "infant",
        "wear"
    ],
    "wof:name":"Carmelitas' Kids",
    "wof:placetype":"venue"
},
  "geometry": {"coordinates":[-121.629885,36.673106],"type":"Point"}
}