{
  "type": "Feature",
  "properties": {
    "iso:country":"US",
    "sg:address":"5034 E Woodwind Ln",
    "sg:city":"Anaheim",
    "sg:classifiers":[
        {
            "category":"Real Estate",
            "subcategory":"Real Estate Agent",
            "type":"Services"
        }
    ],
    "sg:phone":"+1 408 858 9407",
    "sg:postcode":"92807",
    "sg:province":"CA",
    "sg:tags":[
        "property",
        "management",
        "investment"
    ],
    "wof:name":"Rytl Management Corporation",
    "wof:placetype":"venue"
},
  "geometry": {"coordinates":[-117.804375,33.867478],"type":"Point"}
}