{
  "type": "Feature",
  "properties": {
    "addr:full":"31858 Castaic Rd Castaic CA 91384",
    "addr:housenumber":"31858",
    "addr:postcode":"91384",
    "addr:street":"Castaic Rd",
    "iso:country":"US",
    "sg:address":"31858 Castaic Rd",
    "sg:city":"Castaic",
    "sg:classifiers":[
        {
            "category":"Professional",
            "subcategory":"Business Services",
            "type":"Services"
        }
    ],
    "sg:phone":"+1 818 968 7749",
    "sg:postcode":"91384",
    "sg:province":"CA",
    "sg:tags":[
        "organizing",
        "services-household"
    ],
    "wof:name":"Copa Management",
    "wof:placetype":"venue"
},
  "geometry": {"coordinates":[-118.62277400000001,34.496852],"type":"Point"}
}