{
  "type": "Feature",
  "properties": {
    "addr:full":"107 Cll de Andalucia Redondo Beach CA 90277",
    "addr:housenumber":"107",
    "addr:postcode":"90277",
    "addr:street":"Cll De Andalucia",
    "iso:country":"US",
    "sg:address":"107 Cll de Andalucia",
    "sg:city":"Redondo Beach",
    "sg:classifiers":[
        {
            "category":"Recreation",
            "type":"Entertainment"
        }
    ],
    "sg:phone":"+1 310 375 0200",
    "sg:postcode":"90277",
    "sg:province":"CA",
    "sg:tags":[
        "club",
        "membership"
    ],
    "wof:name":"Kansai Club Inc",
    "wof:placetype":"venue"
},
  "geometry": {"coordinates":[-118.38017600000001,33.805456],"type":"Point"}
}