{
  "type": "Feature",
  "properties": {
    "addr:full":"3130 Leonis Blvd Vernon CA 90058",
    "addr:postcode":"3130;90058",
    "addr:street":"Leonis Blvd",
    "iso:country":"US",
    "sg:address":"3130 Leonis Blvd",
    "sg:city":"Vernon",
    "sg:classifiers":[
        {
            "category":"Building & Trades",
            "subcategory":"Cleaning & Sanitation",
            "type":"Services"
        }
    ],
    "sg:phone":"+1 323 277 3222",
    "sg:postcode":"90058",
    "sg:province":"CA",
    "sg:tags":[
        "carpet"
    ],
    "wof:name":"Kingdom",
    "wof:placetype":"venue"
},
  "geometry": {"coordinates":[-118.212377,33.999992],"type":"Point"}
}