{
  "type": "Feature",
  "properties": {
    "addr:full":"1089 57th St Emeryville CA 94608",
    "addr:housenumber":"1089",
    "addr:postcode":"94608",
    "addr:street":"57Th St",
    "iso:country":"US",
    "sg:address":"1089 57th St",
    "sg:city":"Emeryville",
    "sg:classifiers":[
        {
            "category":"Personal",
            "type":"Services"
        }
    ],
    "sg:phone":"+1 510 828 8444",
    "sg:postcode":"94608",
    "sg:province":"CA",
    "sg:tags":[
        "mover"
    ],
    "wof:name":"Alright Moving",
    "wof:placetype":"venue"
},
  "geometry": {"coordinates":[-122.28229899999999,37.840321],"type":"Point"}
}