{
  "type": "Feature",
  "properties": {
    "iso:country":"US",
    "sg:address":"733 N Pastoria Avenue",
    "sg:city":"Sunnyvale",
    "sg:classifiers":[
        {
            "category":"Building & Trades",
            "subcategory":"Pest Control",
            "type":"Services"
        }
    ],
    "sg:phone":"+1 408 522 0100",
    "sg:postcode":"94085",
    "sg:province":"CA",
    "wof:name":"Terminix International",
    "wof:placetype":"venue"
},
  "geometry": {"coordinates":[-122.032895,37.395578],"type":"Point"}
}