{
  "type": "Feature",
  "properties": {
    "addr:full":"2232 Waterloo Rd Stockton CA 95205",
    "addr:housenumber":"2232",
    "addr:postcode":"95205",
    "addr:street":"Waterloo Rd",
    "iso:country":"US",
    "sg:address":"2232 Waterloo Rd",
    "sg:city":"Stockton",
    "sg:classifiers":[
        {
            "category":"Manufacturing",
            "subcategory":"Buildings",
            "type":"Manufacturing & Wholesale Goods"
        },
        {
            "category":"Home & Garden",
            "subcategory":"Building Materials",
            "type":"Retail Goods"
        },
        {
            "category":"Manufacturing",
            "subcategory":"Building Materials",
            "type":"Manufacturing & Wholesale Goods"
        }
    ],
    "sg:phone":"+1 209 942 0270",
    "sg:postcode":"95205",
    "sg:province":"CA",
    "sg:tags":[
        "frames",
        "builder",
        "window",
        "doors",
        "accessory"
    ],
    "wof:name":"Western Door & Molding",
    "wof:placetype":"venue"
},
  "geometry": {"coordinates":[-121.26686599999999,37.973758],"type":"Point"}
}