{
  "type": "Feature",
  "properties": {
    "iso:country":"US",
    "sg:address":"108 Martella St",
    "sg:city":"Salinas",
    "sg:classifiers":[
        {
            "category":"Building & Trades",
            "subcategory":"Cleaning & Sanitation",
            "type":"Services"
        }
    ],
    "sg:phone":"+1 831 796 0328",
    "sg:postcode":"93901",
    "sg:province":"CA",
    "sg:tags":[
        "janitor"
    ],
    "wof:name":"Karus Janitorial Svc",
    "wof:placetype":"venue"
},
  "geometry": {"coordinates":[-121.655064,36.681418],"type":"Point"}
}