{
  "type": "Feature",
  "properties": {
    "addr:full":"107 N Hall Ave Visalia CA 93291",
    "addr:housenumber":"107",
    "addr:postcode":"93291",
    "addr:street":"N Hall Ave",
    "iso:country":"US",
    "sg:address":"107 N Hall Ave",
    "sg:city":"Visalia",
    "sg:classifiers":[
        {
            "category":"Personal",
            "type":"Services"
        }
    ],
    "sg:phone":"+1 559 733 7772",
    "sg:postcode":"93291",
    "sg:province":"CA",
    "sg:tags":[
        "control",
        "weight"
    ],
    "wof:name":"Weight & Health Clinic",
    "wof:placetype":"venue"
},
  "geometry": {"coordinates":[-119.308847,36.330373],"type":"Point"}
}