{
  "type": "Feature",
  "properties": {
    "iso:country":"US",
    "sg:address":"1017 22nd Ave Ste 300",
    "sg:city":"Oakland",
    "sg:classifiers":[
        {
            "category":"Winery",
            "type":"Food & Drink"
        }
    ],
    "sg:phone":"+1 510 915 5463",
    "sg:postcode":"94606",
    "sg:province":"CA",
    "sg:website":"irishmonkey.net",
    "wof:name":"Irish Monkey",
    "wof:placetype":"venue"
},
  "geometry": {"coordinates":[-122.241178,37.781535],"type":"Point"}
}