{
  "type": "Feature",
  "properties": {
    "iso:country":"US",
    "sg:address":"265 E O St",
    "sg:city":"Colton",
    "sg:classifiers":[
        {
            "category":"Food & Beverages",
            "subcategory":"Groceries & Convenience Stores",
            "type":"Retail Goods"
        }
    ],
    "sg:phone":"+1 909 825 8093",
    "sg:postcode":"92324",
    "sg:province":"CA",
    "sg:tags":[
        "grocer"
    ],
    "wof:name":"Toby's Market",
    "wof:placetype":"venue"
},
  "geometry": {"coordinates":[-117.323384,34.059731],"type":"Point"}
}