{
  "type": "Feature",
  "properties": {
    "addr:full":"507 Pacific Ave Long Beach CA 90802",
    "addr:housenumber":"507",
    "addr:postcode":"90802",
    "addr:street":"Pacific Ave",
    "iso:country":"US",
    "sg:address":"507 Pacific Ave",
    "sg:city":"Long Beach",
    "sg:classifiers":[
        {
            "category":"Organizations",
            "subcategory":"Religious Organization",
            "type":"Services"
        }
    ],
    "sg:phone":"+1 562 437 1289",
    "sg:postcode":"90802",
    "sg:province":"CA",
    "wof:name":"Methodist Church of Long Beach",
    "wof:placetype":"venue"
},
  "geometry": {"coordinates":[-118.194,33.773201],"type":"Point"}
}