{
  "type": "Feature",
  "properties": {
    "addr:full":"5100 Cimarron St Bakersfield CA 93308",
    "addr:housenumber":"5100",
    "addr:postcode":"93308",
    "addr:street":"Cimarron St",
    "iso:country":"US",
    "sg:address":"5100 Cimarron St",
    "sg:city":"Bakersfield",
    "sg:classifiers":[
        {
            "category":"Farming",
            "subcategory":"Farm",
            "type":"Manufacturing & Wholesale Goods"
        }
    ],
    "sg:phone":"+1 661 399 9366",
    "sg:postcode":"93308",
    "sg:province":"CA",
    "wof:name":"J&J Ludy Farm",
    "wof:placetype":"venue"
},
  "geometry": {"coordinates":[-119.08215300000001,35.40556],"type":"Point"}
}