{
  "type": "Feature",
  "properties": {
    "addr:full":"204 Orange Ave Long Beach CA 90802",
    "addr:housenumber":"204",
    "addr:postcode":"90802",
    "addr:street":"Orange Ave",
    "iso:country":"US",
    "sg:address":"204 Orange Ave",
    "sg:city":"Long Beach",
    "sg:classifiers":[
        {
            "category":"Restaurant",
            "type":"Food & Drink"
        }
    ],
    "sg:phone":"+1 562 901 3080",
    "sg:postcode":"90802",
    "sg:province":"CA",
    "wof:name":"Sotelo's Cafe",
    "wof:placetype":"venue"
},
  "geometry": {"coordinates":[-118.176762,33.76834],"type":"Point"}
}