{
  "type": "Feature",
  "properties": {
    "addr:full":"400 N Douglas Street El Segundo CA 90245",
    "addr:housenumber":"400",
    "addr:postcode":"90245",
    "addr:street":"N Douglas Street",
    "iso:country":"US",
    "sg:address":"400 N Douglas Street",
    "sg:city":"El Segundo",
    "sg:classifiers":[
        {
            "category":"Professional",
            "type":"Services"
        }
    ],
    "sg:phone":"+1 310 524 9111",
    "sg:postcode":"90245",
    "sg:province":"CA",
    "sg:tags":[
        "caterer"
    ],
    "wof:name":"Erharts Catering",
    "wof:placetype":"venue"
},
  "geometry": {"coordinates":[-118.41122,33.92223],"type":"Point"}
}