{
  "type": "Feature",
  "properties": {
    "iso:country":"US",
    "sg:address":"13110 Adenmoor Ave",
    "sg:city":"Downey",
    "sg:classifiers":[
        {
            "category":"Wholesale",
            "subcategory":"Office Equipment",
            "type":"Manufacturing & Wholesale Goods"
        }
    ],
    "sg:phone":"+1 562 803 8999",
    "sg:postcode":"90242",
    "sg:province":"CA",
    "wof:name":"American Office Machines",
    "wof:placetype":"venue"
},
  "geometry": {"coordinates":[-118.12355599999999,33.912008],"type":"Point"}
}