{
  "type": "Feature",
  "properties": {
    "iso:country":"US",
    "sg:address":"1860 Embarcadero Rd",
    "sg:city":"Palo Alto",
    "sg:classifiers":[
        {
            "category":"Banks & Credit Unions",
            "subcategory":"Investment Brokerage",
            "type":"Services"
        }
    ],
    "sg:phone":"+1 650 320 8200",
    "sg:postcode":"94303",
    "sg:province":"CA",
    "sg:tags":[
        "consultant",
        "planning",
        "financial"
    ],
    "wof:name":"Financial Independence",
    "wof:placetype":"venue"
},
  "geometry": {"coordinates":[-122.115956,37.451902],"type":"Point"}
}