{
  "type": "Feature",
  "properties": {
    "iso:country":"US",
    "sg:address":"1516 Howe Avenue",
    "sg:city":"Sacramento",
    "sg:classifiers":[
        {
            "category":"Sports & Exercise",
            "subcategory":"Gym",
            "type":"Entertainment"
        }
    ],
    "sg:phone":"+1 916 924 8011",
    "sg:postcode":"95825",
    "sg:province":"CA",
    "wof:name":"Volleyball Cafe International",
    "wof:placetype":"venue"
},
  "geometry": {"coordinates":[-121.415075,38.593456],"type":"Point"}
}