{
  "type": "Feature",
  "properties": {
    "addr:full":"22 Encanto Drive Rolling Hills Estate CA 90274",
    "addr:housenumber":"22",
    "addr:postcode":"90274",
    "addr:street":"Encanto Drive",
    "iso:country":"US",
    "sg:address":"22 Encanto Drive",
    "sg:city":"Rolling Hills Estate",
    "sg:classifiers":[
        {
            "category":"Retail",
            "subcategory":"Repair Shop",
            "type":"Services"
        },
        {
            "category":"Home & Garden",
            "subcategory":"Furniture",
            "type":"Retail Goods"
        }
    ],
    "sg:phone":"+1 310 517 9297",
    "sg:postcode":"90274",
    "sg:province":"CA",
    "sg:tags":[
        "reupholstery",
        "store"
    ],
    "wof:name":"Pv Foam Company",
    "wof:placetype":"venue"
},
  "geometry": {"coordinates":[-118.318113,33.776588],"type":"Point"}
}