{
  "type": "Feature",
  "properties": {
    "addr:full":"595 el Camino Real Salinas CA 93907",
    "addr:housenumber":"595",
    "addr:postcode":"93907",
    "addr:street":"El Camino Real",
    "iso:country":"US",
    "sg:address":"595 el Camino Real",
    "sg:city":"Salinas",
    "sg:classifiers":[
        {
            "category":"Real Estate",
            "subcategory":"Real Estate Operator",
            "type":"Services"
        }
    ],
    "sg:phone":"+1 831 449 0632",
    "sg:postcode":"93907",
    "sg:province":"CA",
    "sg:tags":[
        "mobile",
        "home",
        "community"
    ],
    "wof:name":"Village Mobile Home Parks",
    "wof:placetype":"venue"
},
  "geometry": {"coordinates":[-121.65867900000001,36.738808],"type":"Point"}
}