{
  "type": "Feature",
  "properties": {
    "addr:full":"2576 Shattuck Avenue Berkeley CA 94704",
    "addr:housenumber":"2576",
    "addr:postcode":"94704",
    "addr:street":"Shattuck Avenue",
    "iso:country":"US",
    "sg:address":"2576 Shattuck Avenue",
    "sg:city":"Berkeley",
    "sg:classifiers":[
        {
            "category":"Health Services",
            "subcategory":"Clinic",
            "type":"Services"
        }
    ],
    "sg:phone":"+1 510 845 1790",
    "sg:postcode":"94704",
    "sg:province":"CA",
    "sg:tags":[
        "counseling",
        "mental"
    ],
    "wof:name":"Parrish Heather Mst",
    "wof:placetype":"venue"
},
  "geometry": {"coordinates":[-122.266998,37.862598],"type":"Point"}
}