{
  "type": "Feature",
  "properties": {
    "iso:country":"US",
    "sg:address":"3803 E Castro Valley Blvd",
    "sg:city":"Castro Valley",
    "sg:classifiers":[
        {
            "category":"Coffee & Tea",
            "type":"Food & Drink"
        },
        {
            "category":"Restaurant",
            "type":"Food & Drink"
        },
        {
            "category":"Food & Beverages",
            "subcategory":"Bakery",
            "type":"Retail Goods"
        }
    ],
    "sg:phone":"+1 510 581 2634",
    "sg:postcode":"94552",
    "sg:province":"CA",
    "sg:tags":[
        "brunch",
        "sandwich",
        "breakfast"
    ],
    "wof:name":"Bodi's Java Specialty Coffee House",
    "wof:placetype":"venue"
},
  "geometry": {"coordinates":[-122.052002,37.695499],"type":"Point"}
}