{
  "type": "Feature",
  "properties": {
    "addr:full":"2233 Barry Ave Los Angeles CA 90064",
    "addr:housenumber":"2233",
    "addr:postcode":"90064",
    "addr:street":"Barry Ave",
    "iso:country":"US",
    "sg:address":"2233 Barry Ave",
    "sg:city":"Los Angeles",
    "sg:classifiers":[
        {
            "category":"Real Estate",
            "subcategory":"Architect",
            "type":"Services"
        }
    ],
    "sg:phone":"+1 310 477 0515",
    "sg:postcode":"90064",
    "sg:province":"CA",
    "wof:name":"Essick Associates",
    "wof:placetype":"venue"
},
  "geometry": {"coordinates":[-118.445582,34.033291],"type":"Point"}
}