{
  "type": "Feature",
  "properties": {
    "iso:country":"US",
    "sg:address":"930 Florin Rd",
    "sg:city":"Sacramento",
    "sg:classifiers":[
        {
            "category":"Health Services",
            "subcategory":"Doctor",
            "type":"Services"
        }
    ],
    "sg:phone":"+1 916 428 3384",
    "sg:postcode":"95831",
    "sg:province":"CA",
    "sg:tags":[
        "dentist"
    ],
    "wof:name":"Michael R Deanda DDS",
    "wof:placetype":"venue"
},
  "geometry": {"coordinates":[-121.524487,38.496097],"type":"Point"}
}