{
  "type": "Feature",
  "properties": {
    "iso:country":"US",
    "sg:address":"221 E Big Bear Blvd",
    "sg:city":"Big Bear City",
    "sg:classifiers":[
        {
            "category":"Shopping",
            "subcategory":"Used Merchandise",
            "type":"Retail Goods"
        }
    ],
    "sg:phone":"+1 909 585 4011",
    "sg:postcode":"92314",
    "sg:province":"CA",
    "sg:tags":[
        "antique"
    ],
    "wof:name":"Blue Racoon Antiques",
    "wof:placetype":"venue"
},
  "geometry": {"coordinates":[-116.843431,34.261234],"type":"Point"}
}