{
  "type": "Feature",
  "properties": {
    "addr:full":"2101 Fulkerth Rd Turlock CA 95380",
    "addr:housenumber":"2101",
    "addr:postcode":"95380",
    "addr:street":"Fulkerth Rd",
    "iso:country":"US",
    "sg:address":"2101 Fulkerth Rd",
    "sg:city":"Turlock",
    "sg:classifiers":[
        {
            "category":"Real Estate",
            "subcategory":"Real Estate Services",
            "type":"Services"
        },
        {
            "category":"Banks & Credit Unions",
            "subcategory":"Investment Brokerage",
            "type":"Services"
        },
        {
            "category":"Banks & Credit Unions",
            "subcategory":"Bank",
            "type":"Services"
        },
        {
            "category":"Banks & Credit Unions",
            "subcategory":"Financial Services",
            "type":"Services"
        }
    ],
    "sg:phone":"+1 209 656 2362",
    "sg:postcode":"95380",
    "sg:province":"CA",
    "sg:tags":[
        "saving",
        "loan",
        "commercial",
        "security"
    ],
    "sg:website":"http://www.bankofthewest.com",
    "wof:name":"Bank Of The West",
    "wof:placetype":"venue"
},
  "geometry": {"coordinates":[-120.871788,37.507271],"type":"Point"}
}