{
  "type": "Feature",
  "properties": {
    "addr:full":"3167 India Street San Diego CA 92103",
    "addr:housenumber":"3167",
    "addr:postcode":"92103",
    "addr:street":"India Street",
    "iso:country":"US",
    "sg:address":"3167 India Street",
    "sg:city":"San Diego",
    "sg:classifiers":[
        {
            "category":"Shopping",
            "subcategory":"Hobbies, Toys, & Games",
            "type":"Retail Goods"
        }
    ],
    "sg:phone":"+1 619 295 6668",
    "sg:postcode":"92103",
    "sg:province":"CA",
    "sg:tags":[
        "toy",
        "store"
    ],
    "wof:name":"The Collective Vintage Toy Store",
    "wof:placetype":"venue"
},
  "geometry": {"coordinates":[-117.17518,32.736189],"type":"Point"}
}