{
  "type": "Feature",
  "properties": {
    "addr:full":"1223 Fremont Blvd Seaside CA 93955",
    "addr:housenumber":"1223",
    "addr:postcode":"93955",
    "addr:street":"Fremont Blvd",
    "iso:country":"US",
    "sg:address":"1223 Fremont Blvd",
    "sg:city":"Seaside",
    "sg:classifiers":[
        {
            "category":"Retail",
            "subcategory":"Auto Repair",
            "type":"Services"
        }
    ],
    "sg:phone":"+1 831 899 5214",
    "sg:postcode":"93955",
    "sg:province":"CA",
    "sg:tags":[
        "automobile",
        "rustproofing",
        "undercoating"
    ],
    "wof:name":"Coats Auto Body & Paint",
    "wof:placetype":"venue"
},
  "geometry": {"coordinates":[-121.848691,36.60262],"type":"Point"}
}