{
  "type": "Feature",
  "properties": {
    "iso:country":"US",
    "sg:address":"1989 Country Pl",
    "sg:city":"Ojai",
    "sg:classifiers":[
        {
            "category":"Freight",
            "type":"Transportation"
        }
    ],
    "sg:phone":"+1 805 640 1900",
    "sg:postcode":"93023",
    "sg:province":"CA",
    "sg:tags":[
        "operator",
        "local",
        "trucking"
    ],
    "wof:name":"M & C Clark Dump Truck and BAC",
    "wof:placetype":"venue"
},
  "geometry": {"coordinates":[-119.287726,34.423786],"type":"Point"}
}