{
  "type": "Feature",
  "properties": {
    "addr:full":"1941 N Gateway Blvd Fresno CA 93727",
    "addr:housenumber":"1941",
    "addr:postcode":"93727",
    "addr:street":"N Gateway Blvd",
    "iso:country":"US",
    "sg:address":"1941 N Gateway Blvd",
    "sg:city":"Fresno",
    "sg:classifiers":[
        {
            "category":"Organizations",
            "subcategory":"Non-profit Organization",
            "type":"Services"
        }
    ],
    "sg:phone":"+1 559 252 0728",
    "sg:postcode":"93727",
    "sg:province":"CA",
    "wof:name":"Ca Cotton Growers Assn",
    "wof:placetype":"venue"
},
  "geometry": {"coordinates":[-119.726832,36.767328],"type":"Point"}
}