{
  "type": "Feature",
  "properties": {
    "iso:country":"US",
    "sg:address":"681 Powderhorn Ave",
    "sg:city":"Santa Rosa",
    "sg:classifiers":[
        {
            "category":"Building & Trades",
            "subcategory":"Landscaping Services",
            "type":"Services"
        }
    ],
    "sg:phone":"+1 707 591 9357",
    "sg:postcode":"95407",
    "sg:province":"CA",
    "sg:tags":[
        "landscape",
        "contractor"
    ],
    "wof:name":"International Landscaping",
    "wof:placetype":"venue"
},
  "geometry": {"coordinates":[-122.712071,38.402777],"type":"Point"}
}