{
  "type": "Feature",
  "properties": {
    "iso:country":"US",
    "sg:address":"1843 1/2 E 1st St",
    "sg:city":"Los Angeles",
    "sg:classifiers":[
        {
            "category":"Restaurant",
            "type":"Food & Drink"
        }
    ],
    "sg:phone":"+1 323 262 9787",
    "sg:postcode":"90033",
    "sg:province":"CA",
    "sg:tags":[
        "mexican"
    ],
    "wof:name":"Los Apache's Carnes Al Carbon",
    "wof:placetype":"venue"
},
  "geometry": {"coordinates":[-118.218453,34.047005],"type":"Point"}
}