{
  "type": "Feature",
  "properties": {
    "iso:country":"US",
    "sg:address":"1580 Oakland Rd",
    "sg:city":"San Jose",
    "sg:classifiers":[
        {
            "category":"Banks & Credit Unions",
            "subcategory":"Bank",
            "type":"Services"
        }
    ],
    "sg:phone":"+1 408 573 9218",
    "sg:postcode":"95131",
    "sg:province":"CA",
    "sg:tags":[
        "loan",
        "real estate"
    ],
    "wof:name":"K C Capital Mortgage",
    "wof:placetype":"venue"
},
  "geometry": {"coordinates":[-121.895284,37.380589],"type":"Point"}
}