{
  "type": "Feature",
  "properties": {
    "addr:full":"7814 Florence Ave Downey CA 90240",
    "addr:housenumber":"7814",
    "addr:postcode":"90240",
    "addr:street":"Florence Ave",
    "iso:country":"US",
    "sg:address":"7814 Florence Ave",
    "sg:city":"Downey",
    "sg:classifiers":[
        {
            "category":"Shopping",
            "subcategory":"Mobile Phones",
            "type":"Retail Goods"
        }
    ],
    "sg:phone":"+1 562 928 8800",
    "sg:postcode":"90240",
    "sg:province":"CA",
    "wof:name":"MetroPCS",
    "wof:placetype":"venue"
},
  "geometry": {"coordinates":[-118.134034,33.955424],"type":"Point"}
}