{
  "type": "Feature",
  "properties": {
    "iso:country":"US",
    "sg:address":"465 E Palmdale Blvd",
    "sg:city":"Palmdale",
    "sg:classifiers":[
        {
            "category":"Health Services",
            "subcategory":"Doctor",
            "type":"Services"
        }
    ],
    "sg:phone":"+1 661 273 2400",
    "sg:postcode":"93550",
    "sg:province":"CA",
    "sg:tags":[
        "clinic"
    ],
    "wof:name":"Palmdale Urgent Care",
    "wof:placetype":"venue"
},
  "geometry": {"coordinates":[-118.121776,34.579856],"type":"Point"}
}