{
  "type": "Feature",
  "properties": {
    "addr:full":"430 Percy St Oxnard CA 93033",
    "addr:housenumber":"430",
    "addr:postcode":"93033",
    "addr:street":"Percy St",
    "iso:country":"US",
    "sg:address":"430 Percy St",
    "sg:city":"Oxnard",
    "sg:classifiers":[
        {
            "category":"Professional",
            "subcategory":"Secretarial Services",
            "type":"Services"
        }
    ],
    "sg:phone":"+1 805 488 9751",
    "sg:postcode":"93033",
    "sg:province":"CA",
    "sg:tags":[
        "communications",
        "reporting",
        "telephone"
    ],
    "wof:name":"Choice Commication Service",
    "wof:placetype":"venue"
},
  "geometry": {"coordinates":[-119.173365,34.159223],"type":"Point"}
}