{
  "type": "Feature",
  "properties": {
    "addr:full":"910 Saint Vincent Ave Santa Barbara CA 93101",
    "addr:housenumber":"910",
    "addr:postcode":"93101",
    "addr:street":"Saint Vincent Ave",
    "iso:country":"US",
    "sg:address":"910 Saint Vincent Ave",
    "sg:city":"Santa Barbara",
    "sg:classifiers":[
        {
            "category":"Shopping",
            "subcategory":"Used Merchandise",
            "type":"Retail Goods"
        }
    ],
    "sg:phone":"+1 805 966 0111",
    "sg:postcode":"93101",
    "sg:province":"CA",
    "sg:tags":[
        "antique"
    ],
    "wof:name":"George Sampanis",
    "wof:placetype":"venue"
},
  "geometry": {"coordinates":[-119.704555,34.418763],"type":"Point"}
}