{
  "type": "Feature",
  "properties": {
    "iso:country":"US",
    "sg:address":"5079 Brandin Ct",
    "sg:city":"Fremont",
    "sg:classifiers":[
        {
            "category":"Manufacturing",
            "subcategory":"Retail Goods",
            "type":"Manufacturing & Wholesale Goods"
        }
    ],
    "sg:phone":"+1 510 657 7198",
    "sg:postcode":"94538",
    "sg:province":"CA",
    "sg:tags":[
        "assembly",
        "fabricating"
    ],
    "wof:name":"Sparqtron Corp",
    "wof:placetype":"venue"
},
  "geometry": {"coordinates":[-121.965647,37.502843],"type":"Point"}
}