{
  "type": "Feature",
  "properties": {
    "iso:country":"US",
    "sg:address":"13392 Amargosa Rd",
    "sg:city":"Victorville",
    "sg:classifiers":[
        {
            "category":"Freight",
            "type":"Transportation"
        }
    ],
    "sg:phone":"+1 760 952 0238",
    "sg:postcode":"92392",
    "sg:province":"CA",
    "sg:tags":[
        "operator",
        "local",
        "trucking"
    ],
    "wof:name":"M&F Diaz Trucking",
    "wof:placetype":"venue"
},
  "geometry": {"coordinates":[-117.331441,34.492396],"type":"Point"}
}