{
  "type": "Feature",
  "properties": {
    "iso:country":"US",
    "sg:address":"3371 W Mount Whitney Ave",
    "sg:city":"Riverdale",
    "sg:classifiers":[
        {
            "category":"Freight",
            "type":"Transportation"
        }
    ],
    "sg:phone":"+1 559 867 7867",
    "sg:postcode":"93656",
    "sg:province":"CA",
    "sg:tags":[
        "commercial",
        "storage"
    ],
    "wof:name":"Riverdale Mini-Storage",
    "wof:placetype":"venue"
},
  "geometry": {"coordinates":[-119.858878,36.430734],"type":"Point"}
}