{
  "type": "Feature",
  "properties": {
    "addr:full":"146 Amaral Rd Castroville CA 95012",
    "addr:housenumber":"146",
    "addr:postcode":"95012",
    "addr:street":"Amaral Rd",
    "iso:country":"US",
    "sg:address":"146 Amaral Rd",
    "sg:city":"Castroville",
    "sg:classifiers":[
        {
            "category":"Food & Beverages",
            "subcategory":"Farmers Market",
            "type":"Retail Goods"
        },
        {
            "category":"Wholesale",
            "subcategory":"Fruits & Vegetables",
            "type":"Manufacturing & Wholesale Goods"
        }
    ],
    "sg:phone":"+1 831 633 4211",
    "sg:postcode":"95012",
    "sg:province":"CA",
    "sg:tags":[
        "shipper",
        "grower",
        "vegetables-wholesale"
    ],
    "wof:name":"Goro Nursery",
    "wof:placetype":"venue"
},
  "geometry": {"coordinates":[-121.718486,36.802224],"type":"Point"}
}