{
  "type": "Feature",
  "properties": {
    "iso:country":"US",
    "sg:address":"4594 Salem Pl",
    "sg:city":"Carlsbad",
    "sg:classifiers":[
        {
            "category":"Manufacturing",
            "subcategory":"Tools & Machinery",
            "type":"Manufacturing & Wholesale Goods"
        }
    ],
    "sg:phone":"+1 760 720 1153",
    "sg:postcode":"92010",
    "sg:province":"CA",
    "sg:tags":[
        "equipment",
        "calculating",
        "mfg"
    ],
    "wof:name":"Accurate Cash Systems",
    "wof:placetype":"venue"
},
  "geometry": {"coordinates":[-117.296167,33.164038],"type":"Point"}
}