{
  "type": "Feature",
  "properties": {
    "addr:full":"20572 Linda Ln Cottonwood CA 96022",
    "addr:housenumber":"20572",
    "addr:postcode":"96022",
    "addr:street":"Linda Ln",
    "iso:country":"US",
    "sg:address":"20572 Linda Ln",
    "sg:city":"Cottonwood",
    "sg:classifiers":[
        {
            "category":"Professional",
            "subcategory":"Detective & Security Services",
            "type":"Services"
        }
    ],
    "sg:phone":"+1 530 347 6371",
    "sg:postcode":"96022",
    "sg:province":"CA",
    "sg:tags":[
        "information",
        "bureau"
    ],
    "wof:name":"David Adams",
    "wof:placetype":"venue"
},
  "geometry": {"coordinates":[-122.29114300000001,40.395716],"type":"Point"}
}