{
  "type": "Feature",
  "properties": {
    "addr:full":"8916 Winter Gardens Blvd Lakeside CA 92040",
    "addr:housenumber":"8916",
    "addr:postcode":"92040",
    "addr:street":"Winter Gardens Blvd",
    "iso:country":"US",
    "sg:address":"8916 Winter Gardens Blvd",
    "sg:city":"Lakeside",
    "sg:classifiers":[
        {
            "category":"Personal",
            "type":"Services"
        }
    ],
    "sg:phone":"+1 619 846 7868",
    "sg:postcode":"92040",
    "sg:province":"CA",
    "sg:tags":[
        "towing"
    ],
    "wof:name":"San Diego Impound & Towing Inc",
    "wof:placetype":"venue"
},
  "geometry": {"coordinates":[-116.933455,32.838935],"type":"Point"}
}