{
  "type": "Feature",
  "properties": {
    "addr:full":"252 Spring St Pleasanton CA 94566",
    "addr:housenumber":"252",
    "addr:postcode":"94566",
    "addr:street":"Spring St",
    "iso:country":"US",
    "sg:address":"252 Spring St",
    "sg:city":"Pleasanton",
    "sg:classifiers":[
        {
            "category":"Communications",
            "type":"Services"
        },
        {
            "category":"Professional",
            "subcategory":"Computer Services",
            "type":"Services"
        }
    ],
    "sg:phone":"+1 925 931 4600",
    "sg:postcode":"94566",
    "sg:province":"CA",
    "sg:tags":[
        "consultant",
        "telecommunication"
    ],
    "wof:name":"Assist Tel-Com Inc",
    "wof:placetype":"venue"
},
  "geometry": {"coordinates":[-121.87402899999999,37.662698],"type":"Point"}
}