{
  "type": "Feature",
  "properties": {
    "addr:full":"1020 W. Kenneth Road Glendale CA 91011",
    "addr:housenumber":"1020",
    "addr:postcode":"91011",
    "addr:street":"W. Kenneth Road",
    "iso:country":"US",
    "sg:address":"1020 W. Kenneth Road",
    "sg:city":"Glendale",
    "sg:classifiers":[
        {
            "category":"Place Of Worship",
            "subcategory":"Church",
            "type":"Public Place"
        }
    ],
    "sg:phone":"+1 818 242 8801",
    "sg:postcode":"91011",
    "sg:province":"CA",
    "sg:website":"www.nlc2.com",
    "wof:name":"New Life Christian Church",
    "wof:placetype":"venue"
},
  "geometry": {"coordinates":[-118.27843300000001,34.172062],"type":"Point"}
}