{
  "type": "Feature",
  "properties": {
    "iso:country":"US",
    "sg:address":"4743 Yosemite Ave",
    "sg:city":"Sacramento",
    "sg:classifiers":[
        {
            "category":"Building & Trades",
            "subcategory":"Construction",
            "type":"Services"
        }
    ],
    "sg:phone":"+1 916 730 5299",
    "sg:postcode":"95820",
    "sg:province":"CA",
    "sg:tags":[
        "fire",
        "restoration",
        "damage"
    ],
    "wof:name":"Mold Busters",
    "wof:placetype":"venue"
},
  "geometry": {"coordinates":[-121.45063,38.536301],"type":"Point"}
}