{
  "type": "Feature",
  "properties": {
    "addr:full":"Beverly Garland Theatre at the Holiday Inn 4222 Vineland North Hollywood CA 91602",
    "addr:housenumber":"4222",
    "addr:postcode":"91602",
    "addr:street":"Vineland",
    "iso:country":"US",
    "sg:address":"Beverly Garland Theatre at the Holiday Inn 4222 Vineland",
    "sg:city":"North Hollywood",
    "sg:classifiers":[
        {
            "category":"Arts & Performance",
            "subcategory":"Arts Center",
            "type":"Entertainment"
        }
    ],
    "sg:phone":"+1 213 683 3422",
    "sg:postcode":"91602",
    "sg:province":"CA",
    "sg:tags":[
        "performing"
    ],
    "sg:website":"www.cartaudio.org",
    "wof:name":"California Artists Radio Theatre",
    "wof:placetype":"venue"
},
  "geometry": {"coordinates":[-118.369902,34.145564],"type":"Point"}
}