{
  "type": "Feature",
  "properties": {
    "addr:full":"1585 Laurelwood Rd Santa Clara CA 95054",
    "addr:housenumber":"1585",
    "addr:postcode":"95054",
    "addr:street":"Laurelwood Rd",
    "iso:country":"US",
    "sg:address":"1585 Laurelwood Rd",
    "sg:city":"Santa Clara",
    "sg:classifiers":[
        {
            "category":"Professional",
            "subcategory":"Business Services",
            "type":"Services"
        }
    ],
    "sg:phone":"+1 408 980 9934",
    "sg:postcode":"95054",
    "sg:province":"CA",
    "wof:name":"A-1 Recovery",
    "wof:placetype":"venue"
},
  "geometry": {"coordinates":[-121.957421,37.380501],"type":"Point"}
}