{
  "type": "Feature",
  "properties": {
    "iso:country":"US",
    "sg:address":"1398 Solano Ave",
    "sg:city":"Albany",
    "sg:classifiers":[
        {
            "category":"Health Services",
            "subcategory":"Clinic",
            "type":"Services"
        }
    ],
    "sg:phone":"+1 510 528 9852",
    "sg:postcode":"94706",
    "sg:province":"CA",
    "sg:tags":[
        "therapist",
        "biofeedback"
    ],
    "wof:name":"Ortho-Bionomy",
    "wof:placetype":"venue"
},
  "geometry": {"coordinates":[-122.289993,37.890776],"type":"Point"}
}