{
  "type": "Feature",
  "properties": {
    "addr:full":"4200 el Centro Rd Sacramento CA 95834",
    "addr:housenumber":"4200",
    "addr:postcode":"95834",
    "addr:street":"El Centro Rd",
    "iso:country":"US",
    "sg:address":"4200 el Centro Rd",
    "sg:city":"Sacramento",
    "sg:classifiers":[
        {
            "category":"Real Estate",
            "subcategory":"Real Estate Operator",
            "type":"Services"
        }
    ],
    "sg:phone":"+1 916 419 8795",
    "sg:postcode":"95834",
    "sg:province":"CA",
    "sg:tags":[
        "mobile",
        "home",
        "community"
    ],
    "wof:name":"Stadium Club Estates",
    "wof:placetype":"venue"
},
  "geometry": {"coordinates":[-121.539841,38.652341],"type":"Point"}
}