{
  "type": "Feature",
  "properties": {
    "addr:full":"217 E 8th St Ste 1000 Los Angeles CA 90014",
    "addr:housenumber":"217",
    "addr:postcode":"90014",
    "addr:street":"E 8Th St Ste 1000",
    "iso:country":"US",
    "sg:address":"217 E 8th St Ste 1000",
    "sg:city":"Los Angeles",
    "sg:classifiers":[
        {
            "category":"Shopping",
            "subcategory":"Clothing, Apparel, & Fashions",
            "type":"Retail Goods"
        }
    ],
    "sg:phone":"+1 213 627 1166",
    "sg:postcode":"90014",
    "sg:province":"CA",
    "sg:tags":[
        "clothing",
        "women's"
    ],
    "wof:name":"Luri Fashion",
    "wof:placetype":"venue"
},
  "geometry": {"coordinates":[-118.251559,34.041639],"type":"Point"}
}