{
  "type": "Feature",
  "properties": {
    "iso:country":"US",
    "sg:address":"3220 Swetzer Rd",
    "sg:city":"Loomis",
    "sg:classifiers":[
        {
            "category":"Professional",
            "type":"Services"
        }
    ],
    "sg:phone":"+1 916 652 4148",
    "sg:postcode":"95650",
    "sg:province":"CA",
    "wof:name":"Rod Novelli & Custom",
    "wof:placetype":"venue"
},
  "geometry": {"coordinates":[-121.19184,38.83528],"type":"Point"}
}