{
  "type": "Feature",
  "properties": {
    "iso:country":"US",
    "sg:address":"7477 Eigleberry St",
    "sg:city":"Gilroy",
    "sg:classifiers":[
        {
            "category":"Real Estate",
            "subcategory":"Real Estate Agent",
            "type":"Services"
        }
    ],
    "sg:phone":"+1 408 842 8251",
    "sg:postcode":"95020",
    "sg:province":"CA",
    "wof:name":"Starritt Realtors",
    "wof:placetype":"venue"
},
  "geometry": {"coordinates":[-121.57022499999999,37.006781],"type":"Point"}
}