{
  "type": "Feature",
  "properties": {
    "iso:country":"US",
    "sg:address":"4507 Houston Ave",
    "sg:city":"Hanford",
    "sg:classifiers":[
        {
            "category":"Food & Beverages",
            "subcategory":"Dairy",
            "type":"Retail Goods"
        }
    ],
    "sg:phone":"+1 559 582 0804",
    "sg:postcode":"93230",
    "sg:province":"CA",
    "sg:tags":[
        "product"
    ],
    "wof:name":"JVD Dairy",
    "wof:placetype":"venue"
},
  "geometry": {"coordinates":[-119.542714,36.298626],"type":"Point"}
}