{
  "type": "Feature",
  "properties": {
    "addr:full":"11934 Terra Bella St Sylmar CA 91342",
    "addr:housenumber":"11934",
    "addr:postcode":"91342",
    "addr:street":"Terra Bella St",
    "iso:country":"US",
    "sg:address":"11934 Terra Bella St",
    "sg:city":"Sylmar",
    "sg:classifiers":[
        {
            "category":"Personal",
            "subcategory":"Beauty Salon",
            "type":"Services"
        }
    ],
    "sg:phone":"+1 818 896 0885",
    "sg:postcode":"91342",
    "sg:province":"CA",
    "wof:name":"Platinum House Of Style",
    "wof:placetype":"venue"
},
  "geometry": {"coordinates":[-118.39389799999999,34.276033],"type":"Point"}
}