{
  "type": "Feature",
  "properties": {
    "addr:full":"92 Judah St San Francisco CA 94122",
    "addr:housenumber":"92",
    "addr:postcode":"94122",
    "addr:street":"Judah St",
    "iso:country":"US",
    "sg:address":"92 Judah St",
    "sg:city":"San Francisco",
    "sg:classifiers":[
        {
            "category":"Restaurant",
            "type":"Food & Drink"
        }
    ],
    "sg:menulink":"http://www.allmenus.com/ca/san-francisco/44962-pomelo/menu/",
    "sg:phone":"+1 415 731 6175",
    "sg:postcode":"94122",
    "sg:province":"CA",
    "sg:tags":[
        "asian",
        "chinese"
    ],
    "wof:name":"Pomelo",
    "wof:placetype":"venue"
},
  "geometry": {"coordinates":[-122.46209500000001,37.762368],"type":"Point"}
}