{
  "type": "Feature",
  "properties": {
    "iso:country":"US",
    "sg:address":"760 Market St Suite 937",
    "sg:city":"San Francisco",
    "sg:classifiers":[
        {
            "category":"Health Services",
            "subcategory":"Chiropractor",
            "type":"Services"
        }
    ],
    "sg:phone":"+1 415 346 7776",
    "sg:postcode":"94102",
    "sg:province":"CA",
    "sg:website":"www.altmd.com/Specialists/Richar...",
    "wof:name":"Richard E. Hingel, DC",
    "wof:placetype":"venue"
},
  "geometry": {"coordinates":[-122.405463,37.786469],"type":"Point"}
}