{
  "type": "Feature",
  "properties": {
    "iso:country":"US",
    "sg:address":"42156 10th St W",
    "sg:city":"Lancaster",
    "sg:classifiers":[
        {
            "category":"Recreation",
            "type":"Entertainment"
        }
    ],
    "sg:phone":"+1 661 723 1558",
    "sg:postcode":"93534",
    "sg:province":"CA",
    "sg:tags":[
        "club",
        "membership"
    ],
    "wof:name":"Country Club West Real Estate",
    "wof:placetype":"venue"
},
  "geometry": {"coordinates":[-118.147582,34.647994],"type":"Point"}
}