{
  "type": "Feature",
  "properties": {
    "addr:full":"3045 Remington Way San Jose CA 95148",
    "addr:housenumber":"3045",
    "addr:postcode":"95148",
    "addr:street":"Remington Way",
    "iso:country":"US",
    "sg:address":"3045 Remington Way",
    "sg:city":"San Jose",
    "sg:classifiers":[
        {
            "category":"Building & Trades",
            "subcategory":"Cleaning & Sanitation",
            "type":"Services"
        }
    ],
    "sg:phone":"+1 408 238 3931",
    "sg:postcode":"95148",
    "sg:province":"CA",
    "sg:tags":[
        "home"
    ],
    "wof:name":"Linda's House Keeping Service",
    "wof:placetype":"venue"
},
  "geometry": {"coordinates":[-121.78943700000001,37.323457],"type":"Point"}
}