{
  "type": "Feature",
  "properties": {
    "addr:full":"10722 Beverly Blvd Whittier CA 90601",
    "addr:housenumber":"10722",
    "addr:postcode":"90601",
    "addr:street":"Beverly Blvd",
    "iso:country":"US",
    "sg:address":"10722 Beverly Blvd",
    "sg:city":"Whittier",
    "sg:classifiers":[
        {
            "category":"Cinema",
            "subcategory":"Movie Rental",
            "type":"Entertainment"
        }
    ],
    "sg:phone":"+1 562 699 4589",
    "sg:postcode":"90601",
    "sg:province":"CA",
    "sg:tags":[
        "leasing",
        "video",
        "disc",
        "tape"
    ],
    "wof:name":"Video Pavilion",
    "wof:placetype":"venue"
},
  "geometry": {"coordinates":[-118.055819,33.998792],"type":"Point"}
}