{
  "type": "Feature",
  "properties": {
    "iso:country":"US",
    "sg:address":"1645 Princeton Ave",
    "sg:city":"Modesto",
    "sg:classifiers":[
        {
            "category":"Retail",
            "subcategory":"Laundry & Dry Cleaning",
            "type":"Services"
        }
    ],
    "sg:phone":"+1 209 491 2616",
    "sg:postcode":"95350",
    "sg:province":"CA",
    "wof:name":"B & B Laundry Inc",
    "wof:placetype":"venue"
},
  "geometry": {"coordinates":[-121.021114,37.656936],"type":"Point"}
}