{
  "type": "Feature",
  "properties": {
    "addr:full":"1975 Corby Ave Santa Rosa CA 95407",
    "addr:housenumber":"1975",
    "addr:postcode":"95407",
    "addr:street":"Corby Ave",
    "iso:country":"US",
    "sg:address":"1975 Corby Ave",
    "sg:city":"Santa Rosa",
    "sg:classifiers":[
        {
            "category":"Professional",
            "type":"Services"
        }
    ],
    "sg:phone":"+1 707 545 2705",
    "sg:postcode":"95407",
    "sg:province":"CA",
    "wof:name":"Carlos Alcala",
    "wof:placetype":"venue"
},
  "geometry": {"coordinates":[-122.717341,38.420227],"type":"Point"}
}