{
  "type": "Feature",
  "properties": {
    "iso:country":"US",
    "sg:address":"1300 W Optical Dr",
    "sg:city":"Azusa",
    "sg:classifiers":[
        {
            "category":"Manufacturing",
            "subcategory":"Retail Goods",
            "type":"Manufacturing & Wholesale Goods"
        }
    ],
    "sg:phone":"+1 626 815 3100",
    "sg:postcode":"91702",
    "sg:province":"CA",
    "sg:tags":[
        "product",
        "mfg"
    ],
    "wof:name":"Perkin Maner Electronics",
    "wof:placetype":"venue"
},
  "geometry": {"coordinates":[-117.92750599999999,34.128634],"type":"Point"}
}