{
  "type": "Feature",
  "properties": {
    "addr:full":"2391 Placer St Redding CA 96001",
    "addr:housenumber":"2391",
    "addr:postcode":"96001",
    "addr:street":"Placer St",
    "iso:country":"US",
    "sg:address":"2391 Placer St",
    "sg:city":"Redding",
    "sg:classifiers":[
        {
            "category":"Wholesale",
            "subcategory":"Medical Equipment & Supplies",
            "type":"Manufacturing & Wholesale Goods"
        }
    ],
    "sg:phone":"+1 530 242 1598",
    "sg:postcode":"96001",
    "sg:province":"CA",
    "sg:tags":[
        "dental"
    ],
    "wof:name":"Daisy Dental Supply",
    "wof:placetype":"venue"
},
  "geometry": {"coordinates":[-122.402181,40.579255],"type":"Point"}
}