{
  "type": "Feature",
  "properties": {
    "addr:full":"2802 Ocean View Blvd San Diego CA 92113",
    "addr:housenumber":"2802",
    "addr:postcode":"92113",
    "addr:street":"Ocean View Blvd",
    "iso:country":"US",
    "sg:address":"2802 Ocean View Blvd",
    "sg:city":"San Diego",
    "sg:classifiers":[
        {
            "category":"Restaurant",
            "type":"Food & Drink"
        }
    ],
    "sg:postcode":"92113",
    "sg:province":"CA",
    "sg:tags":[
        "seafood",
        "mexican"
    ],
    "wof:name":"Ocean's 28",
    "wof:placetype":"venue"
},
  "geometry": {"coordinates":[-117.13362100000001,32.701451],"type":"Point"}
}