{
  "type": "Feature",
  "properties": {
    "addr:full":"127 E. 3rd ST Los Angeles CA 90013",
    "addr:housenumber":"127",
    "addr:postcode":"90013",
    "addr:street":"E. 3Rd St",
    "iso:country":"US",
    "sg:address":"127 E. 3rd ST",
    "sg:city":"Los Angeles",
    "sg:classifiers":[
        {
            "category":"Autos & Motor Vehicles",
            "subcategory":"Motorcycle Sales",
            "type":"Retail Goods"
        }
    ],
    "sg:phone":"+1 213 808 1231",
    "sg:postcode":"90013",
    "sg:province":"CA",
    "sg:website":"www.scooterimporter.com",
    "wof:name":"Scooter Importer",
    "wof:placetype":"venue"
},
  "geometry": {"coordinates":[-118.245064,34.049194],"type":"Point"}
}