{
  "type": "Feature",
  "properties": {
    "addr:full":"309 Hyde St San Francisco CA 94109",
    "addr:housenumber":"309",
    "addr:postcode":"94109",
    "addr:street":"Hyde St",
    "iso:country":"US",
    "sg:address":"309 Hyde St",
    "sg:city":"San Francisco",
    "sg:classifiers":[
        {
            "category":"Restaurant",
            "type":"Food & Drink"
        }
    ],
    "sg:phone":"+1 415 885 5159",
    "sg:postcode":"94109",
    "sg:province":"CA",
    "sg:tags":[
        "sandwich"
    ],
    "wof:name":"Sing Sing Sandwich Shop",
    "wof:placetype":"venue"
},
  "geometry": {"coordinates":[-122.416134,37.78436],"type":"Point"}
}