{
  "type": "Feature",
  "properties": {
    "iso:country":"US",
    "sg:address":"23839 Bear Valley Rd",
    "sg:city":"Apple Valley",
    "sg:classifiers":[
        {
            "category":"Sports & Exercise",
            "subcategory":"Golf",
            "type":"Entertainment"
        }
    ],
    "sg:phone":"+1 760 240 6497",
    "sg:postcode":"92308",
    "sg:province":"CA",
    "sg:tags":[
        "course"
    ],
    "wof:name":"Bear Valley Golf Range",
    "wof:placetype":"venue"
},
  "geometry": {"coordinates":[-117.142973,34.471834],"type":"Point"}
}