{
  "type": "Feature",
  "properties": {
    "iso:country":"US",
    "sg:address":"120 Christine Lynn Dr",
    "sg:city":"Morgan Hill",
    "sg:classifiers":[
        {
            "category":"Professional",
            "type":"Services"
        }
    ],
    "sg:phone":"+1 408 779 6155",
    "sg:postcode":"95037",
    "sg:province":"CA",
    "sg:tags":[
        "establishment"
    ],
    "wof:name":"Salter & Salter",
    "wof:placetype":"venue"
},
  "geometry": {"coordinates":[-121.66312499999999,37.135177],"type":"Point"}
}