{
  "type": "Feature",
  "properties": {
    "iso:country":"US",
    "sg:address":"107 E Orange Grove Blvd",
    "sg:city":"Pasadena",
    "sg:classifiers":[
        {
            "category":"Personal",
            "subcategory":"Beauty Salon",
            "type":"Services"
        }
    ],
    "sg:phone":"+1 626 792 9155",
    "sg:postcode":"91103",
    "sg:province":"CA",
    "wof:name":"Sanchez Beauty Salon",
    "wof:placetype":"venue"
},
  "geometry": {"coordinates":[-118.14799499999999,34.157898],"type":"Point"}
}