{
  "type": "Feature",
  "properties": {
    "addr:full":"41180 Fremont Blvd Fremont CA 94538",
    "addr:housenumber":"41180",
    "addr:postcode":"94538",
    "addr:street":"Fremont Blvd",
    "iso:country":"US",
    "sg:address":"41180 Fremont Blvd",
    "sg:city":"Fremont",
    "sg:classifiers":[
        {
            "category":"Shopping",
            "subcategory":"Florist",
            "type":"Retail Goods"
        }
    ],
    "sg:phone":"+1 510 656 7300",
    "sg:postcode":"94538",
    "sg:province":"CA",
    "wof:name":"Irvington Flowers",
    "wof:placetype":"venue"
},
  "geometry": {"coordinates":[-121.95859299999999,37.530197],"type":"Point"}
}