{
  "type": "Feature",
  "properties": {
    "addr:full":"1310 Stratford Ct Del Mar CA 92014",
    "addr:housenumber":"1310",
    "addr:postcode":"92014",
    "addr:street":"Stratford Ct",
    "iso:country":"US",
    "sg:address":"1310 Stratford Ct",
    "sg:city":"Del Mar",
    "sg:classifiers":[
        {
            "category":"Real Estate",
            "subcategory":"Developer",
            "type":"Services"
        }
    ],
    "sg:phone":"+1 858 481 1188",
    "sg:postcode":"92014",
    "sg:province":"CA",
    "wof:name":"Linton & Kimura",
    "wof:placetype":"venue"
},
  "geometry": {"coordinates":[-117.266147,32.958751],"type":"Point"}
}