{
  "type": "Feature",
  "properties": {
    "addr:full":"2635 Jensen Ave Sanger CA 93657",
    "addr:housenumber":"2635",
    "addr:postcode":"ca 93657",
    "addr:street":"Jensen Ave",
    "iso:country":"US",
    "sg:address":"2635 Jensen Ave",
    "sg:city":"Sanger",
    "sg:classifiers":[
        {
            "category":"Real Estate",
            "subcategory":"Real Estate Agent",
            "type":"Services"
        }
    ],
    "sg:phone":"+1 559 876 1833",
    "sg:postcode":"93657",
    "sg:province":"CA",
    "wof:name":"Valley Property Investments",
    "wof:placetype":"venue"
},
  "geometry": {"coordinates":[-119.577603,36.706714],"type":"Point"}
}