{
  "type": "Feature",
  "properties": {
    "addr:full":"6776 Ave 416 Dinuba CA 93618",
    "addr:housenumber":"6776",
    "addr:postcode":"416;93618",
    "addr:street":"Ave",
    "iso:country":"US",
    "sg:address":"6776 Ave 416",
    "sg:city":"Dinuba",
    "sg:classifiers":[
        {
            "category":"Building & Trades",
            "subcategory":"Landscaping Services",
            "type":"Services"
        }
    ],
    "sg:phone":"+1 559 284 8556",
    "sg:postcode":"93618",
    "sg:province":"CA",
    "sg:tags":[
        "landscape",
        "contractor"
    ],
    "wof:name":"Rockyard",
    "wof:placetype":"venue"
},
  "geometry": {"coordinates":[-119.422611,36.546261],"type":"Point"}
}