{
  "type": "Feature",
  "properties": {
    "addr:full":"402 Ingalls St #12 Santa Cruz CA 95060",
    "addr:housenumber":"402",
    "addr:postcode":"95060",
    "addr:street":"Ingalls St # 12",
    "iso:country":"US",
    "sg:address":"402 Ingalls St #12",
    "sg:city":"Santa Cruz",
    "sg:classifiers":[
        {
            "category":"Personal",
            "type":"Services"
        },
        {
            "category":"Shopping",
            "subcategory":"Crafts & Fabrics",
            "type":"Retail Goods"
        }
    ],
    "sg:phone":"+1 831 427 9276",
    "sg:postcode":"95060",
    "sg:province":"CA",
    "sg:tags":[
        "sewing",
        "art",
        "alteration"
    ],
    "sg:website":"www.theswiftstitch.com/",
    "wof:name":"The Swift Stitch",
    "wof:placetype":"venue"
},
  "geometry": {"coordinates":[-122.048464,36.958941],"type":"Point"}
}