{
  "type": "Feature",
  "properties": {
    "addr:full":"8240 Garvey Ave Rosemead CA 91770",
    "addr:housenumber":"8240",
    "addr:postcode":"91770",
    "addr:street":"Garvey Ave",
    "iso:country":"US",
    "sg:address":"8240 Garvey Ave",
    "sg:city":"Rosemead",
    "sg:classifiers":[
        {
            "category":"Personal",
            "subcategory":"Beauty Salon",
            "type":"Services"
        }
    ],
    "sg:phone":"+1 626 280 8582",
    "sg:postcode":"91770",
    "sg:province":"CA",
    "wof:name":"Lily's Beauty Salon",
    "wof:placetype":"venue"
},
  "geometry": {"coordinates":[-118.08850099999999,34.062582],"type":"Point"}
}