{
  "type": "Feature",
  "properties": {
    "addr:full":"8726 S Sepulveda Blvd D2021 Los Angeles CA 90045",
    "addr:housenumber":"8726",
    "addr:postcode":"90045",
    "addr:street":"S Sepulveda Blvd D2021",
    "iso:country":"US",
    "sg:address":"8726 S Sepulveda Blvd D2021",
    "sg:city":"Los Angeles",
    "sg:classifiers":[
        {
            "category":"Professional",
            "type":"Services"
        },
        {
            "category":"Professional",
            "subcategory":"Art Services",
            "type":"Services"
        }
    ],
    "sg:phone":"+1 310 645 5766",
    "sg:postcode":"90045",
    "sg:province":"CA",
    "sg:tags":[
        "photographer"
    ],
    "sg:website":"millsphotography.com",
    "wof:name":"John & Max Mills Photography",
    "wof:placetype":"venue"
},
  "geometry": {"coordinates":[-118.396202,33.959217],"type":"Point"}
}