{
  "type": "Feature",
  "properties": {
    "addr:full":"301 Alexander St Crockett CA 94525",
    "addr:housenumber":"301",
    "addr:postcode":"94525",
    "addr:street":"Alexander St",
    "iso:country":"US",
    "sg:address":"301 Alexander St",
    "sg:city":"Crockett",
    "sg:phone":"+1 510 787 3737",
    "sg:postcode":"94525",
    "sg:province":"CA",
    "wof:name":"Cramer-Krasselt",
    "wof:placetype":"venue"
},
  "geometry": {"coordinates":[-122.210069,38.054321],"type":"Point"}
}