{
  "type": "Feature",
  "properties": {
    "iso:country":"US",
    "sg:address":"3835 Foothill Blvd",
    "sg:city":"La Crescenta",
    "sg:classifiers":[
        {
            "category":"Retail",
            "subcategory":"Auto Repair",
            "type":"Services"
        }
    ],
    "sg:phone":"+1 818 248 5882",
    "sg:postcode":"91214",
    "sg:province":"CA",
    "sg:tags":[
        "transmission"
    ],
    "wof:name":"J & L Transmissions",
    "wof:placetype":"venue"
},
  "geometry": {"coordinates":[-118.26327999999999,34.238677],"type":"Point"}
}