{
  "type": "Feature",
  "properties": {
    "addr:full":"902 W 12th St Tracy CA 95376",
    "addr:housenumber":"902",
    "addr:postcode":"95376",
    "addr:street":"W 12Th St",
    "iso:country":"US",
    "sg:address":"902 W 12th St",
    "sg:city":"Tracy",
    "sg:classifiers":[
        {
            "category":"Real Estate",
            "subcategory":"Real Estate Operator",
            "type":"Services"
        }
    ],
    "sg:phone":"+1 209 836 3924",
    "sg:postcode":"95376",
    "sg:province":"CA",
    "sg:tags":[
        "apartment"
    ],
    "wof:name":"Tracy Place Senior Apt",
    "wof:placetype":"venue"
},
  "geometry": {"coordinates":[-121.438001,37.740631],"type":"Point"}
}