{
  "type": "Feature",
  "properties": {
    "iso:country":"US",
    "sg:address":"2612 Crows Landing Rd",
    "sg:city":"Modesto",
    "sg:classifiers":[
        {
            "category":"Professional",
            "type":"Services"
        }
    ],
    "sg:postcode":"95358",
    "sg:province":"CA",
    "sg:website":"www.g3enterprises.com",
    "wof:name":"G3 Enterprises - Label Division",
    "wof:placetype":"venue"
},
  "geometry": {"coordinates":[-120.990407,37.592946],"type":"Point"}
}