{
  "type": "Feature",
  "properties": {
    "addr:full":"902 Fulton Mall Spc M31 Fresno CA 93721",
    "addr:housenumber":"902",
    "addr:postcode":"m31;ca 93721",
    "addr:street":"Fulton Mall",
    "iso:country":"US",
    "sg:address":"902 Fulton Mall Spc M31",
    "sg:city":"Fresno",
    "sg:classifiers":[
        {
            "category":"Manufacturing",
            "subcategory":"Apparel",
            "type":"Manufacturing & Wholesale Goods"
        }
    ],
    "sg:phone":"+1 559 233 0904",
    "sg:postcode":"93721",
    "sg:province":"CA",
    "sg:tags":[
        "clothing-men's-wholesale",
        "manufacturer"
    ],
    "wof:name":"Biva Shoes",
    "wof:placetype":"venue"
},
  "geometry": {"coordinates":[-119.789061,36.73293],"type":"Point"}
}