{
  "type": "Feature",
  "properties": {
    "iso:country":"US",
    "sg:address":"2927 Martha St",
    "sg:city":"Anderson",
    "sg:classifiers":[
        {
            "category":"Sports & Exercise",
            "subcategory":"Gym",
            "type":"Entertainment"
        },
        {
            "category":"Health Services",
            "subcategory":"Health Practitioner",
            "type":"Services"
        },
        {
            "category":"Community Center",
            "subcategory":"Social",
            "type":"Public Place"
        }
    ],
    "sg:phone":"+1 877 905 7900",
    "sg:postcode":"96007",
    "sg:province":"CA",
    "sg:tags":[
        "control",
        "information",
        "stress",
        "management",
        "weight",
        "smoker",
        "treatment",
        "medicine",
        "alternative",
        "prevention",
        "hypnotist"
    ],
    "sg:website":"http://www.stopsmokingandchewing.com",
    "wof:name":"INSPIRE Hypnosis",
    "wof:placetype":"venue"
},
  "geometry": {"coordinates":[-122.296975,40.451729],"type":"Point"}
}