{
  "type": "Feature",
  "properties": {
    "addr:full":"573 E El Camino Real Sunnyvale CA 94085",
    "addr:housenumber":"573",
    "addr:postcode":"94085",
    "addr:street":"E El Camino Real",
    "iso:country":"US",
    "sg:address":"573 E El Camino Real",
    "sg:city":"Sunnyvale",
    "sg:classifiers":[
        {
            "category":"Restaurant",
            "type":"Food & Drink"
        }
    ],
    "sg:phone":"+1 408 524 2662",
    "sg:postcode":"94085",
    "sg:province":"CA",
    "sg:tags":[
        "pakistani",
        "indian"
    ],
    "sg:website":"www.annapoorna.us/",
    "wof:name":"Annapoorna",
    "wof:placetype":"venue"
},
  "geometry": {"coordinates":[-122.025002,37.362499],"type":"Point"}
}