{
  "type": "Feature",
  "properties": {
    "iso:country":"US",
    "sg:address":"27134 Pso Espada",
    "sg:city":"San Juan Cpstrno",
    "sg:classifiers":[
        {
            "category":"Manufacturing",
            "subcategory":"Printing",
            "type":"Manufacturing & Wholesale Goods"
        }
    ],
    "sg:phone":"+1 949 240 0805",
    "sg:postcode":"92675",
    "sg:province":"CA",
    "sg:tags":[
        "printer",
        "offset"
    ],
    "sg:website":"www.americanspeedyprinting.com",
    "wof:name":"American Speedy Printing Ctr",
    "wof:placetype":"venue"
},
  "geometry": {"coordinates":[-117.65461000000001,33.501406],"type":"Point"}
}