{
  "type": "Feature",
  "properties": {
    "addr:full":"2 Embarcadero Center Ste 460 San Francisco CA 94111",
    "addr:housenumber":"2",
    "addr:postcode":"94111",
    "addr:street":"Embarcadero Center Ste 460",
    "iso:country":"US",
    "sg:address":"2 Embarcadero Center Ste 460",
    "sg:city":"San Francisco",
    "sg:classifiers":[
        {
            "category":"Professional",
            "subcategory":"Employment Agencies",
            "type":"Services"
        }
    ],
    "sg:phone":"+1 415 291 8819",
    "sg:postcode":"94111",
    "sg:province":"CA",
    "sg:website":"www.linebeyond.com",
    "wof:name":"LineBeyond, Inc",
    "wof:placetype":"venue"
},
  "geometry": {"coordinates":[-122.398473,37.794799],"type":"Point"}
}