{
  "type": "Feature",
  "properties": {
    "iso:country":"US",
    "sg:address":"3021 Sunrise Blvd",
    "sg:city":"Rancho Cordova",
    "sg:classifiers":[
        {
            "category":"Restaurant",
            "type":"Food & Drink"
        }
    ],
    "sg:phone":"+1 916 638 3388",
    "sg:postcode":"95742",
    "sg:province":"CA",
    "sg:tags":[
        "fusion",
        "asian",
        "buffet"
    ],
    "sg:website":"www.kimsonbuffet.com",
    "wof:name":"Kim Son Super Buffet",
    "wof:placetype":"venue"
},
  "geometry": {"coordinates":[-121.264579,38.594001],"type":"Point"}
}