{
  "type": "Feature",
  "properties": {
    "addr:full":"25460 Medical Center Dr Ste 200 Murrieta CA 92562",
    "addr:housenumber":"25460",
    "addr:postcode":"92562",
    "addr:street":"Medical Center Dr Ste 200",
    "iso:country":"US",
    "sg:address":"25460 Medical Center Dr Ste 200",
    "sg:city":"Murrieta",
    "sg:classifiers":[
        {
            "category":"Health Services",
            "subcategory":"Dentist",
            "type":"Services"
        }
    ],
    "sg:phone":"+1 951 677 7322",
    "sg:postcode":"92562",
    "sg:province":"CA",
    "sg:tags":[
        "dentists-endodontists"
    ],
    "sg:website":"http://www.ranchoendo.com",
    "wof:name":"Pettersen, Eric A, Dds - Rancho Endodontic Assoc",
    "wof:placetype":"venue"
},
  "geometry": {"coordinates":[-117.18692299999999,33.556506],"type":"Point"}
}