{
  "type": "Feature",
  "properties": {
    "iso:country":"US",
    "sg:address":"820 Bay Ave Ste 103",
    "sg:city":"Capitola",
    "sg:classifiers":[
        {
            "category":"Banks & Credit Unions",
            "subcategory":"Bank",
            "type":"Services"
        }
    ],
    "sg:phone":"+1 831 462 1666",
    "sg:postcode":"95010",
    "sg:province":"CA",
    "wof:name":"State Farm Insurance Companies",
    "wof:placetype":"venue"
},
  "geometry": {"coordinates":[-121.953003,36.974098],"type":"Point"}
}