{
  "type": "Feature",
  "properties": {
    "iso:country":"US",
    "sg:address":"3000 N Alameda St",
    "sg:city":"Compton",
    "sg:classifiers":[
        {
            "category":"Retail",
            "subcategory":"Auto Repair",
            "type":"Services"
        }
    ],
    "sg:phone":"+1 310 632 6510",
    "sg:postcode":"90222",
    "sg:province":"CA",
    "sg:tags":[
        "body",
        "repairing",
        "painting",
        "automobile"
    ],
    "wof:name":"Original Auto Paint",
    "wof:placetype":"venue"
},
  "geometry": {"coordinates":[-118.223493,33.918911],"type":"Point"}
}