{
  "type": "Feature",
  "properties": {
    "addr:full":"1242 Santee St Los Angeles CA 90015",
    "addr:housenumber":"1242",
    "addr:postcode":"90015",
    "addr:street":"Santee St",
    "iso:country":"US",
    "sg:address":"1242 Santee St",
    "sg:city":"Los Angeles",
    "sg:classifiers":[
        {
            "category":"Shopping",
            "subcategory":"Crafts & Fabrics",
            "type":"Retail Goods"
        }
    ],
    "sg:phone":"+1 213 748 5600",
    "sg:postcode":"90015",
    "sg:province":"CA",
    "sg:tags":[
        "sewing"
    ],
    "wof:name":"Classic Fabric",
    "wof:placetype":"venue"
},
  "geometry": {"coordinates":[-118.257874,34.035592],"type":"Point"}
}