{
  "type": "Feature",
  "properties": {
    "iso:country":"US",
    "sg:address":"1254 S de Wolf Ave",
    "sg:city":"Fresno",
    "sg:classifiers":[
        {
            "category":"Real Estate",
            "subcategory":"Real Estate Operator",
            "type":"Services"
        }
    ],
    "sg:phone":"+1 559 251 0511",
    "sg:postcode":"93727",
    "sg:province":"CA",
    "sg:tags":[
        "property",
        "lessor"
    ],
    "wof:name":"Taketa Itsuye",
    "wof:placetype":"venue"
},
  "geometry": {"coordinates":[-119.645866,36.718468],"type":"Point"}
}