{
  "type": "Feature",
  "properties": {
    "addr:full":"3131 Foothill Blvd La Crescenta CA 91214",
    "addr:housenumber":"3131",
    "addr:postcode":"91214",
    "addr:street":"Foothill Blvd",
    "iso:country":"US",
    "sg:address":"3131 Foothill Blvd",
    "sg:city":"La Crescenta",
    "sg:classifiers":[
        {
            "category":"Professional",
            "subcategory":"Business Services",
            "type":"Services"
        }
    ],
    "sg:phone":"+1 818 541 1720",
    "sg:postcode":"91214",
    "sg:province":"CA",
    "sg:tags":[
        "recording",
        "studio"
    ],
    "wof:name":"Jay Stevens",
    "wof:placetype":"venue"
},
  "geometry": {"coordinates":[-118.246633,34.228324],"type":"Point"}
}