{
  "type": "Feature",
  "properties": {
    "iso:country":"US",
    "sg:address":"12598 Central Ave",
    "sg:city":"Chino",
    "sg:classifiers":[
        {
            "category":"Banks & Credit Unions",
            "subcategory":"Investment Brokerage",
            "type":"Services"
        }
    ],
    "sg:phone":"+1 909 590 3343",
    "sg:postcode":"91710",
    "sg:province":"CA",
    "sg:tags":[
        "advisory",
        "financial"
    ],
    "wof:name":"H & P Financial Svc Inc",
    "wof:placetype":"venue"
},
  "geometry": {"coordinates":[-117.68947300000001,34.025547],"type":"Point"}
}