{
  "type": "Feature",
  "properties": {
    "addr:full":"449 Melrose Ave San Francisco CA 94127",
    "addr:housenumber":"449",
    "addr:postcode":"94127",
    "addr:street":"Melrose Ave",
    "iso:country":"US",
    "sg:address":"449 Melrose Ave",
    "sg:city":"San Francisco",
    "sg:classifiers":[
        {
            "category":"Retail",
            "subcategory":"Animal Services",
            "type":"Services"
        }
    ],
    "sg:phone":"+1 415 334 5036",
    "sg:postcode":"94127",
    "sg:province":"CA",
    "sg:tags":[
        "pet"
    ],
    "wof:name":"Betty J Carmack",
    "wof:placetype":"venue"
},
  "geometry": {"coordinates":[-122.451988,37.733724],"type":"Point"}
}