{
  "type": "Feature",
  "properties": {
    "iso:country":"US",
    "sg:address":"5150 Candlewood St",
    "sg:city":"Lakewood",
    "sg:classifiers":[
        {
            "category":"Shopping",
            "type":"Retail Goods"
        }
    ],
    "sg:phone":"+1 562 920 7868",
    "sg:postcode":"90712",
    "sg:province":"CA",
    "sg:tags":[
        "chemical"
    ],
    "wof:name":"Coast Water Technologies",
    "wof:placetype":"venue"
},
  "geometry": {"coordinates":[-118.13322100000001,33.85358],"type":"Point"}
}