{
  "type": "Feature",
  "properties": {
    "addr:full":"4205 Montair Ave Long Beach CA 90808",
    "addr:housenumber":"4205",
    "addr:postcode":"90808",
    "addr:street":"Montair Ave",
    "iso:country":"US",
    "sg:address":"4205 Montair Ave",
    "sg:city":"Long Beach",
    "sg:classifiers":[
        {
            "category":"Education",
            "subcategory":"Dance Studio",
            "type":"Public Place"
        },
        {
            "category":"Arts & Performance",
            "subcategory":"Dance",
            "type":"Entertainment"
        }
    ],
    "sg:phone":"+1 562 425 7231",
    "sg:postcode":"90808",
    "sg:province":"CA",
    "sg:tags":[
        "school"
    ],
    "sg:website":"www.thedancecolongbeach.com/",
    "wof:name":"Dance Co the",
    "wof:placetype":"venue"
},
  "geometry": {"coordinates":[-118.126999,33.8339],"type":"Point"}
}