{
  "type": "Feature",
  "properties": {
    "addr:full":"7473 Broadway Lemon Grove CA 91945",
    "addr:housenumber":"7473",
    "addr:postcode":"91945",
    "addr:street":"Broadway",
    "iso:country":"US",
    "sg:address":"7473 Broadway",
    "sg:city":"Lemon Grove",
    "sg:classifiers":[
        {
            "category":"Wholesale",
            "subcategory":"Auto Parts",
            "type":"Manufacturing & Wholesale Goods"
        }
    ],
    "sg:phone":"+1 619 464 4131",
    "sg:postcode":"91945",
    "sg:province":"CA",
    "sg:tags":[
        "body",
        "automobile",
        "shop"
    ],
    "wof:name":"Body Shop Supplies Inc",
    "wof:placetype":"venue"
},
  "geometry": {"coordinates":[-117.036587,32.742554],"type":"Point"}
}