{
  "type": "Feature",
  "properties": {
    "addr:full":"139 Helen Ave Modesto CA 95354",
    "addr:housenumber":"139",
    "addr:postcode":"ca 95354",
    "addr:street":"Helen Ave",
    "iso:country":"US",
    "sg:address":"139 Helen Ave",
    "sg:city":"Modesto",
    "sg:classifiers":[
        {
            "category":"Utilities",
            "subcategory":"Water",
            "type":"Services"
        }
    ],
    "sg:phone":"+1 209 575 0677",
    "sg:postcode":"95354",
    "sg:province":"CA",
    "sg:tags":[
        "bulk",
        "companies-bottled"
    ],
    "wof:name":"Water Treatment Services",
    "wof:placetype":"venue"
},
  "geometry": {"coordinates":[-120.992739,37.654588],"type":"Point"}
}