{
  "type": "Feature",
  "properties": {
    "addr:full":"480 S Ellsworth Ave San Mateo CA 94401",
    "addr:housenumber":"480",
    "addr:postcode":"94401",
    "addr:street":"S Ellsworth Ave",
    "iso:country":"US",
    "sg:address":"480 S Ellsworth Ave",
    "sg:city":"San Mateo",
    "sg:classifiers":[
        {
            "category":"Professional",
            "subcategory":"Employment Agencies",
            "type":"Services"
        }
    ],
    "sg:phone":"+1 650 342 2700",
    "sg:postcode":"94401",
    "sg:province":"CA",
    "sg:website":"us.manpower.com/office?hcmid=FSO...",
    "wof:name":"Manpower",
    "wof:placetype":"venue"
},
  "geometry": {"coordinates":[-122.32199900000001,37.563702],"type":"Point"}
}