{
  "type": "Feature",
  "properties": {
    "iso:country":"US",
    "sg:address":"PO Box 191051",
    "sg:city":"Sacramento",
    "sg:classifiers":[
        {
            "category":"Shopping",
            "subcategory":"Florist",
            "type":"Retail Goods"
        }
    ],
    "sg:phone":"+1 866 717 9921",
    "sg:postcode":"95819",
    "sg:province":"CA",
    "sg:website":"www.justbecausegiftboxes.com",
    "wof:name":"Just Because Gift Boxes",
    "wof:placetype":"venue"
},
  "geometry": {"coordinates":[-121.438327,38.568855],"type":"Point"}
}