{
  "type": "Feature",
  "properties": {
    "addr:full":"2 Harrison St San Francisco CA 94105",
    "addr:housenumber":"2",
    "addr:postcode":"94105",
    "addr:street":"Harrison St",
    "iso:country":"US",
    "sg:address":"2 Harrison St",
    "sg:city":"San Francisco",
    "sg:classifiers":[
        {
            "category":"Professional",
            "subcategory":"Engineering",
            "type":"Services"
        }
    ],
    "sg:phone":"+1 415 291 3700",
    "sg:postcode":"94105",
    "sg:province":"CA",
    "sg:tags":[
        "engineer"
    ],
    "sg:website":"www.tylin.com",
    "wof:name":"T Y Lin Intl",
    "wof:placetype":"venue"
},
  "geometry": {"coordinates":[-122.38942900000001,37.788838],"type":"Point"}
}