{
  "type": "Feature",
  "properties": {
    "addr:full":"2218 Lee Ave South El Monte CA 91733",
    "addr:housenumber":"2218",
    "addr:postcode":"91733",
    "addr:street":"Lee Ave",
    "iso:country":"US",
    "sg:address":"2218 Lee Ave",
    "sg:city":"South El Monte",
    "sg:classifiers":[
        {
            "category":"Manufacturing",
            "subcategory":"Metals",
            "type":"Manufacturing & Wholesale Goods"
        }
    ],
    "sg:phone":"+1 626 444 5454",
    "sg:postcode":"91733",
    "sg:province":"CA",
    "sg:tags":[
        "steel"
    ],
    "wof:name":"M & S Steel Fabrication Inc",
    "wof:placetype":"venue"
},
  "geometry": {"coordinates":[-118.067184,34.052467],"type":"Point"}
}