{
  "type": "Feature",
  "properties": {
    "addr:full":"2394 Walsh Ave Santa Clara CA 95051",
    "addr:housenumber":"2394",
    "addr:postcode":"95051",
    "addr:street":"Walsh Ave",
    "iso:country":"US",
    "sg:address":"2394 Walsh Ave",
    "sg:city":"Santa Clara",
    "sg:classifiers":[
        {
            "category":"Professional",
            "subcategory":"Computer Services",
            "type":"Services"
        }
    ],
    "sg:phone":"+1 408 980 9500",
    "sg:postcode":"95051",
    "sg:province":"CA",
    "sg:tags":[
        "hardware",
        "provider",
        "internet",
        "software"
    ],
    "wof:name":"International Softdevices Corp",
    "wof:placetype":"venue"
},
  "geometry": {"coordinates":[-121.967214,37.369367],"type":"Point"}
}