{
  "type": "Feature",
  "properties": {
    "addr:full":"1203 Main St Morro Bay CA 93442",
    "addr:housenumber":"1203",
    "addr:postcode":"93442",
    "addr:street":"Main St",
    "iso:country":"US",
    "sg:address":"1203 Main St",
    "sg:city":"Morro Bay",
    "sg:classifiers":[
        {
            "category":"Health Services",
            "subcategory":"Health Practitioner",
            "type":"Services"
        }
    ],
    "sg:phone":"+1 805 927 4799",
    "sg:postcode":"93442",
    "sg:province":"CA",
    "sg:tags":[
        "psychologist"
    ],
    "wof:name":"Linda Nedleman PHD",
    "wof:placetype":"venue"
},
  "geometry": {"coordinates":[-120.850348,35.371312],"type":"Point"}
}