{
  "type": "Feature",
  "properties": {
    "addr:full":"3059 W San Gabriel Ave Fresno CA 93722",
    "addr:housenumber":"3059",
    "addr:postcode":"93722",
    "addr:street":"W San Gabriel Ave",
    "iso:country":"US",
    "sg:address":"3059 W San Gabriel Ave",
    "sg:city":"Fresno",
    "sg:classifiers":[
        {
            "category":"Retail",
            "subcategory":"Repair Shop",
            "type":"Services"
        }
    ],
    "sg:phone":"+1 559 824 9562",
    "sg:postcode":"93722",
    "sg:province":"CA",
    "sg:tags":[
        "welding"
    ],
    "wof:name":"Hoffman Welding",
    "wof:placetype":"venue"
},
  "geometry": {"coordinates":[-119.845079,36.80345],"type":"Point"}
}