{
  "type": "Feature",
  "properties": {
    "iso:country":"US",
    "sg:address":"5052 West Ln",
    "sg:city":"Stockton",
    "sg:classifiers":[
        {
            "category":"Restaurant",
            "type":"Food & Drink"
        }
    ],
    "sg:menulink":"http://www.allmenus.com/ca/stockton/90812-wingstop/menu/",
    "sg:phone":"+1 209 477 8207",
    "sg:postcode":"95210",
    "sg:province":"CA",
    "sg:tags":[
        "american",
        "wing"
    ],
    "wof:name":"Wingstop",
    "wof:placetype":"venue"
},
  "geometry": {"coordinates":[-121.288884,38.000566],"type":"Point"}
}