{
  "type": "Feature",
  "properties": {
    "addr:full":"21515 Vanowen St Canoga Park CA 91303",
    "addr:housenumber":"21515",
    "addr:postcode":"91303",
    "addr:street":"Vanowen St",
    "iso:country":"US",
    "sg:address":"21515 Vanowen St",
    "sg:city":"Canoga Park",
    "sg:classifiers":[
        {
            "category":"Professional",
            "subcategory":"Computer Services",
            "type":"Services"
        }
    ],
    "sg:phone":"+1 818 999 4700",
    "sg:postcode":"91303",
    "sg:province":"CA",
    "sg:tags":[
        "programming"
    ],
    "sg:website":"www.abacuscorp.com",
    "wof:name":"Abacus Programming",
    "wof:placetype":"venue"
},
  "geometry": {"coordinates":[-118.600031,34.193832],"type":"Point"}
}