{
  "type": "Feature",
  "properties": {
    "addr:full":"2575 Auto Mall Pkwy Fairfield CA 94533",
    "addr:housenumber":"2575",
    "addr:postcode":"94533",
    "addr:street":"Auto Mall Pkwy",
    "iso:country":"US",
    "sg:address":"2575 Auto Mall Pkwy",
    "sg:city":"Fairfield",
    "sg:classifiers":[
        {
            "category":"Autos & Motor Vehicles",
            "subcategory":"Automobile Sales",
            "type":"Retail Goods"
        },
        {
            "category":"Retail",
            "subcategory":"Auto Repair",
            "type":"Services"
        }
    ],
    "sg:phone":"+1 707 402 3200",
    "sg:postcode":"94533",
    "sg:province":"CA",
    "sg:tags":[
        "used",
        "leasing",
        "car",
        "truck",
        "new"
    ],
    "sg:website":"http://www.fairfieldnissan.com",
    "wof:name":"Momentum Nissan",
    "wof:placetype":"venue"
},
  "geometry": {"coordinates":[-122.081262,38.244274],"type":"Point"}
}