{
  "type": "Feature",
  "properties": {
    "iso:country":"US",
    "sg:address":"24019 Japatul Valley Rd",
    "sg:city":"Alpine",
    "sg:classifiers":[
        {
            "category":"Building & Trades",
            "subcategory":"Construction",
            "type":"Services"
        }
    ],
    "sg:phone":"+1 619 445 2587",
    "sg:postcode":"91901",
    "sg:province":"CA",
    "sg:tags":[
        "water",
        "well",
        "drilling"
    ],
    "wof:name":"Bulter Drilling Co",
    "wof:placetype":"venue"
},
  "geometry": {"coordinates":[-116.62736700000001,32.823716],"type":"Point"}
}