{
  "type": "Feature",
  "properties": {
    "addr:full":"139 W Shasta Ave Chico CA 95973",
    "addr:housenumber":"139",
    "addr:postcode":"95973",
    "addr:street":"W Shasta Ave",
    "iso:country":"US",
    "sg:address":"139 W Shasta Ave",
    "sg:city":"Chico",
    "sg:classifiers":[
        {
            "category":"Professional",
            "type":"Services"
        }
    ],
    "sg:phone":"+1 530 345 4670",
    "sg:postcode":"95973",
    "sg:province":"CA",
    "wof:name":"Dj L Locaso",
    "wof:placetype":"venue"
},
  "geometry": {"coordinates":[-121.87003199999999,39.762921],"type":"Point"}
}