{
  "type": "Feature",
  "properties": {
    "iso:country":"US",
    "sg:address":"903 Cll Amanecer",
    "sg:city":"San Clemente",
    "sg:classifiers":[
        {
            "category":"Banks & Credit Unions",
            "subcategory":"Bank",
            "type":"Services"
        }
    ],
    "sg:phone":"+1 949 940 1824",
    "sg:postcode":"92673",
    "sg:province":"CA",
    "wof:name":"California Bank & Trust",
    "wof:placetype":"venue"
},
  "geometry": {"coordinates":[-117.607498,33.449499],"type":"Point"}
}