{
  "type": "Feature",
  "properties": {
    "iso:country":"US",
    "sg:address":"2699 Monument Blvd",
    "sg:city":"Concord",
    "sg:classifiers":[
        {
            "category":"Restaurant",
            "type":"Food & Drink"
        }
    ],
    "sg:menulink":"http://www.allmenus.com/ca/central-contra-costa/61194-chopan-kabob/menu/",
    "sg:phone":"+1 925 689 5488",
    "sg:postcode":"94520",
    "sg:province":"CA",
    "sg:tags":[
        "afghan"
    ],
    "wof:name":"Chopan Kabob",
    "wof:placetype":"venue"
},
  "geometry": {"coordinates":[-122.03169800000001,37.963942],"type":"Point"}
}