{
  "type": "Feature",
  "properties": {
    "addr:full":"335 Couch St Vallejo CA 94590",
    "addr:housenumber":"335",
    "addr:postcode":"94590",
    "addr:street":"Couch St",
    "iso:country":"US",
    "sg:address":"335 Couch St",
    "sg:city":"Vallejo",
    "sg:classifiers":[
        {
            "category":"Bars & Pubs",
            "type":"Food & Drink"
        }
    ],
    "sg:phone":"+1 707 643 1682",
    "sg:postcode":"94590",
    "sg:province":"CA",
    "sg:tags":[
        "lounge",
        "cocktail"
    ],
    "wof:name":"Papa Joe's",
    "wof:placetype":"venue"
},
  "geometry": {"coordinates":[-122.251892,38.119793],"type":"Point"}
}