{
  "type": "Feature",
  "properties": {
    "addr:full":"505 Industry Rd Imperial CA 92251",
    "addr:housenumber":"505",
    "addr:postcode":"92251",
    "addr:street":"Industry Rd",
    "iso:country":"US",
    "sg:address":"505 Industry Rd",
    "sg:city":"Imperial",
    "sg:classifiers":[
        {
            "category":"Home & Garden",
            "subcategory":"Building Materials",
            "type":"Retail Goods"
        }
    ],
    "sg:phone":"+1 760 355 2433",
    "sg:postcode":"92251",
    "sg:province":"CA",
    "wof:name":"D & R Supply Inc",
    "wof:placetype":"venue"
},
  "geometry": {"coordinates":[-115.58199500000001,32.827636],"type":"Point"}
}