{
  "type": "Feature",
  "properties": {
    "addr:full":"2801 E 10th St Long Beach CA 90806",
    "addr:housenumber":"2801",
    "addr:postcode":"90806",
    "addr:street":"E 10Th St",
    "iso:country":"US",
    "sg:address":"2801 E 10th St",
    "sg:city":"Long Beach",
    "sg:classifiers":[
        {
            "category":"Restaurant",
            "type":"Food & Drink"
        }
    ],
    "sg:phone":"+1 562 342 4581",
    "sg:postcode":"90806",
    "sg:province":"CA",
    "sg:tags":[
        "mexican"
    ],
    "wof:name":"La Briza",
    "wof:placetype":"venue"
},
  "geometry": {"coordinates":[-118.158562,33.779119],"type":"Point"}
}