{
  "type": "Feature",
  "properties": {
    "addr:full":"10709 Merritt St Castroville CA 95012",
    "addr:housenumber":"10709",
    "addr:postcode":"95012",
    "addr:street":"Merritt St",
    "iso:country":"US",
    "sg:address":"10709 Merritt St",
    "sg:city":"Castroville",
    "sg:classifiers":[
        {
            "category":"Personal",
            "subcategory":"Barber",
            "type":"Services"
        }
    ],
    "sg:phone":"+1 831 633 3771",
    "sg:postcode":"95012",
    "sg:province":"CA",
    "wof:name":"Castroville Barber Shop",
    "wof:placetype":"venue"
},
  "geometry": {"coordinates":[-121.758003,36.7659],"type":"Point"}
}