{
  "type": "Feature",
  "properties": {
    "iso:country":"US",
    "sg:address":"1412 S Lorena St",
    "sg:city":"Los Angeles",
    "sg:classifiers":[
        {
            "category":"Restaurant",
            "type":"Food & Drink"
        }
    ],
    "sg:phone":"+1 323 261 1300",
    "sg:postcode":"90023",
    "sg:province":"CA",
    "wof:name":"Ostioneria Colima",
    "wof:placetype":"venue"
},
  "geometry": {"coordinates":[-118.20700100000001,34.018501],"type":"Point"}
}