{
  "type": "Feature",
  "properties": {
    "addr:full":"385 Lincoln Ave San Jose CA 95126",
    "addr:housenumber":"385",
    "addr:postcode":"95126",
    "addr:street":"Lincoln Ave",
    "iso:country":"US",
    "sg:address":"385 Lincoln Ave",
    "sg:city":"San Jose",
    "sg:classifiers":[
        {
            "category":"Autos & Motor Vehicles",
            "subcategory":"Automobile Sales",
            "type":"Retail Goods"
        }
    ],
    "sg:phone":"+1 408 993 1828",
    "sg:postcode":"95126",
    "sg:province":"CA",
    "sg:tags":[
        "snowmobile"
    ],
    "sg:website":"www.fasttrax.com",
    "wof:name":"Fast Trax",
    "wof:placetype":"venue"
},
  "geometry": {"coordinates":[-121.90859500000001,37.321406],"type":"Point"}
}