{
  "type": "Feature",
  "properties": {
    "addr:full":"580 University Ave Sacramento CA 95825",
    "addr:housenumber":"580",
    "addr:postcode":"95825",
    "addr:street":"University Ave",
    "iso:country":"US",
    "sg:address":"580 University Ave",
    "sg:city":"Sacramento",
    "sg:classifiers":[
        {
            "category":"Insurance",
            "subcategory":"Insurance Agent",
            "type":"Services"
        }
    ],
    "sg:phone":"+1 916 921 2110",
    "sg:postcode":"95825",
    "sg:province":"CA",
    "wof:name":"Nancy J Garton Insurance Svc",
    "wof:placetype":"venue"
},
  "geometry": {"coordinates":[-121.41923300000001,38.565636],"type":"Point"}
}