{
  "type": "Feature",
  "properties": {
    "iso:country":"US",
    "sg:address":"20630 Plummer St",
    "sg:city":"Chatsworth",
    "sg:classifiers":[
        {
            "category":"Manufacturing",
            "subcategory":"Electronics",
            "type":"Manufacturing & Wholesale Goods"
        }
    ],
    "sg:phone":"+1 818 701 2750",
    "sg:postcode":"91311",
    "sg:province":"CA",
    "sg:tags":[
        "manufacture",
        "transducer"
    ],
    "wof:name":"Celesco Transducer Pdts Inc",
    "wof:placetype":"venue"
},
  "geometry": {"coordinates":[-118.583618,34.24265],"type":"Point"}
}