{
  "type": "Feature",
  "properties": {
    "iso:country":"US",
    "sg:address":"155 N K St",
    "sg:city":"Dinuba",
    "sg:classifiers":[
        {
            "category":"Insurance",
            "subcategory":"Title Insurance",
            "type":"Services"
        }
    ],
    "sg:phone":"+1 559 591 7410",
    "sg:postcode":"93618",
    "sg:province":"CA",
    "sg:tags":[
        "mortgage"
    ],
    "sg:website":"http://www.goldleaf-tech.com",
    "wof:name":"Fidelity National Information Services, Inc.",
    "wof:placetype":"venue"
},
  "geometry": {"coordinates":[-119.389799,36.542158],"type":"Point"}
}