{
  "type": "Feature",
  "properties": {
    "addr:full":"15253 Hesperian Blvd San Leandro CA 94578",
    "addr:housenumber":"15253",
    "addr:postcode":"94578",
    "addr:street":"Hesperian Blvd",
    "iso:country":"US",
    "sg:address":"15253 Hesperian Blvd",
    "sg:city":"San Leandro",
    "sg:classifiers":[
        {
            "category":"Retail",
            "subcategory":"Self-service Laundry",
            "type":"Services"
        }
    ],
    "sg:phone":"+1 510 317 9274",
    "sg:postcode":"94578",
    "sg:province":"CA",
    "wof:name":"Sun Laundry",
    "wof:placetype":"venue"
},
  "geometry": {"coordinates":[-122.130054,37.698077],"type":"Point"}
}