{
  "type": "Feature",
  "properties": {
    "addr:full":"16795 Lark Avenue Los Gatos CA 95032",
    "addr:housenumber":"16795",
    "addr:postcode":"95032",
    "addr:street":"Lark Avenue",
    "iso:country":"US",
    "sg:address":"16795 Lark Avenue",
    "sg:city":"Los Gatos",
    "sg:classifiers":[
        {
            "category":"Banks & Credit Unions",
            "subcategory":"Financial Services",
            "type":"Services"
        }
    ],
    "sg:phone":"+1 408 354 1866",
    "sg:postcode":"95032",
    "sg:province":"CA",
    "sg:tags":[
        "broker",
        "mortgage"
    ],
    "wof:name":"Direct Mortgage",
    "wof:placetype":"venue"
},
  "geometry": {"coordinates":[-121.966885,37.252971],"type":"Point"}
}