{
  "type": "Feature",
  "properties": {
    "addr:full":"811 John St Manhattan Beach CA 90266",
    "addr:housenumber":"811",
    "addr:postcode":"90266",
    "addr:street":"John St",
    "iso:country":"US",
    "sg:address":"811 John St",
    "sg:city":"Manhattan Beach",
    "sg:classifiers":[
        {
            "category":"Communications",
            "subcategory":"Film & Video Production",
            "type":"Services"
        }
    ],
    "sg:phone":"+1 310 376 1790",
    "sg:postcode":"90266",
    "sg:province":"CA",
    "sg:tags":[
        "taping"
    ],
    "sg:website":"www.eye-on-art.com",
    "wof:name":"Arte Avenue",
    "wof:placetype":"venue"
},
  "geometry": {"coordinates":[-118.402154,33.884619],"type":"Point"}
}