{
  "type": "Feature",
  "properties": {
    "addr:full":"6536 E Spring St Long Beach CA 90815",
    "addr:housenumber":"6536",
    "addr:postcode":"90815",
    "addr:street":"E Spring St",
    "iso:country":"US",
    "sg:address":"6536 E Spring St",
    "sg:city":"Long Beach",
    "sg:classifiers":[
        {
            "category":"Banks & Credit Unions",
            "subcategory":"Bank",
            "type":"Services"
        }
    ],
    "sg:phone":"+1 562 938 6732",
    "sg:postcode":"90815",
    "sg:province":"CA",
    "sg:tags":[
        "mortgage"
    ],
    "wof:name":"Countrywide",
    "wof:placetype":"venue"
},
  "geometry": {"coordinates":[-118.106944,33.810404],"type":"Point"}
}