{
  "type": "Feature",
  "properties": {
    "addr:full":"17040 Slover Ave Fontana CA 92337",
    "addr:housenumber":"17040",
    "addr:postcode":"92337",
    "addr:street":"Slover Ave",
    "iso:country":"US",
    "sg:address":"17040 Slover Ave",
    "sg:city":"Fontana",
    "sg:classifiers":[
        {
            "category":"Food & Beverages",
            "subcategory":"Groceries & Convenience Stores",
            "type":"Retail Goods"
        }
    ],
    "sg:phone":"+1 909 357 3788",
    "sg:postcode":"92337",
    "sg:province":"CA",
    "sg:tags":[
        "grocer"
    ],
    "wof:name":"Viva Bargain",
    "wof:placetype":"venue"
},
  "geometry": {"coordinates":[-117.434234,34.063107],"type":"Point"}
}