{
  "type": "Feature",
  "properties": {
    "addr:full":"8930 Mission Dr Ste 107 Rosemead CA 91770",
    "addr:housenumber":"8930",
    "addr:postcode":"91770",
    "addr:street":"Mission Dr Ste 107",
    "iso:country":"US",
    "sg:address":"8930 Mission Dr Ste 107",
    "sg:city":"Rosemead",
    "sg:classifiers":[
        {
            "category":"Communications",
            "subcategory":"Television Station",
            "type":"Services"
        }
    ],
    "sg:phone":"+1 626 698 1212",
    "sg:postcode":"91770",
    "sg:province":"CA",
    "sg:tags":[
        "network"
    ],
    "wof:name":"Efix Usa",
    "wof:placetype":"venue"
},
  "geometry": {"coordinates":[-118.074455,34.084721],"type":"Point"}
}