{
  "type": "Feature",
  "properties": {
    "iso:country":"US",
    "sg:address":"4515 Pacific Ave",
    "sg:city":"Stockton",
    "sg:classifiers":[
        {
            "category":"Restaurant",
            "type":"Food & Drink"
        }
    ],
    "sg:menulink":"http://www.allmenus.com/ca/stockton/216468-mcdonalds/menu/",
    "sg:postcode":"95207",
    "sg:province":"CA",
    "sg:tags":[
        "burger",
        "american"
    ],
    "wof:name":"McDonald's",
    "wof:placetype":"venue"
},
  "geometry": {"coordinates":[-121.311933,37.989152],"type":"Point"}
}