{
  "type": "Feature",
  "properties": {
    "iso:country":"US",
    "sg:address":"251 Lytton Ave",
    "sg:city":"Palo Alto",
    "sg:classifiers":[
        {
            "category":"Real Estate",
            "subcategory":"Real Estate Services",
            "type":"Services"
        }
    ],
    "sg:phone":"+1 650 617 0510",
    "sg:postcode":"94301",
    "sg:province":"CA",
    "sg:tags":[
        "company",
        "title"
    ],
    "wof:name":"Alliance Title Co",
    "wof:placetype":"venue"
},
  "geometry": {"coordinates":[-122.164028,37.445571],"type":"Point"}
}