{
  "type": "Feature",
  "properties": {
    "addr:full":"14360 Grizzly Hill Rd Nevada City CA 95959",
    "addr:housenumber":"14360",
    "addr:postcode":"95959",
    "addr:street":"Grizzly Hill Rd",
    "iso:country":"US",
    "sg:address":"14360 Grizzly Hill Rd",
    "sg:city":"Nevada City",
    "sg:classifiers":[
        {
            "category":"Farming",
            "subcategory":"Farm",
            "type":"Manufacturing & Wholesale Goods"
        }
    ],
    "sg:phone":"+1 530 478 1905",
    "sg:postcode":"95959",
    "sg:province":"CA",
    "sg:tags":[
        "gen",
        "crop"
    ],
    "wof:name":"Canyon Gardens Organic Farms",
    "wof:placetype":"venue"
},
  "geometry": {"coordinates":[-120.97403199999999,39.346767],"type":"Point"}
}