{
  "type": "Feature",
  "properties": {
    "iso:country":"US",
    "sg:address":"865 Sepulveda Blvd",
    "sg:city":"Torrance",
    "sg:classifiers":[
        {
            "category":"Fast Food",
            "type":"Food & Drink"
        }
    ],
    "sg:phone":"+1 310 539 0180",
    "sg:postcode":"90502",
    "sg:province":"CA",
    "sg:tags":[
        "burger"
    ],
    "sg:website":"www.burgerking.com",
    "wof:name":"Burger King",
    "wof:placetype":"venue"
},
  "geometry": {"coordinates":[-118.290001,33.809898],"type":"Point"}
}