{
  "type": "Feature",
  "properties": {
    "iso:country":"US",
    "sg:address":"1988 3rd St",
    "sg:city":"Livermore",
    "sg:classifiers":[
        {
            "category":"Real Estate",
            "subcategory":"Real Estate Services",
            "type":"Services"
        }
    ],
    "sg:phone":"+1 925 245 1306",
    "sg:postcode":"94550",
    "sg:province":"CA",
    "sg:tags":[
        "company",
        "title"
    ],
    "wof:name":"Alliance Title Co",
    "wof:placetype":"venue"
},
  "geometry": {"coordinates":[-121.77172,37.679161],"type":"Point"}
}