{
  "type": "Feature",
  "properties": {
    "addr:full":"3300 Webster St Oakland CA 94609",
    "addr:housenumber":"3300",
    "addr:postcode":"94609",
    "addr:street":"Webster St",
    "iso:country":"US",
    "sg:address":"3300 Webster St",
    "sg:city":"Oakland",
    "sg:classifiers":[
        {
            "category":"Health Services",
            "subcategory":"Doctor",
            "type":"Services"
        }
    ],
    "sg:phone":"+1 510 451 0996",
    "sg:postcode":"94609",
    "sg:province":"CA",
    "wof:name":"Chen Yvonne MD",
    "wof:placetype":"venue"
},
  "geometry": {"coordinates":[-122.262114,37.821201],"type":"Point"}
}