{
  "type": "Feature",
  "properties": {
    "addr:full":"8975 Chimney Rock Rd Paso Robles CA 93446",
    "addr:housenumber":"8975",
    "addr:postcode":"93446",
    "addr:street":"Chimney Rock Rd",
    "iso:country":"US",
    "sg:address":"8975 Chimney Rock Rd",
    "sg:city":"Paso Robles",
    "sg:classifiers":[
        {
            "category":"Farming",
            "subcategory":"Crops",
            "type":"Manufacturing & Wholesale Goods"
        }
    ],
    "sg:phone":"+1 805 239 0161",
    "sg:postcode":"93446",
    "sg:province":"CA",
    "sg:tags":[
        "grove",
        "nut",
        "tree"
    ],
    "wof:name":"David J Osgood",
    "wof:placetype":"venue"
},
  "geometry": {"coordinates":[-120.858752,35.668586],"type":"Point"}
}