{
  "type": "Feature",
  "properties": {
    "iso:country":"US",
    "sg:address":"19971 Soledad Canyon Rd",
    "sg:city":"Canyon Country",
    "sg:classifiers":[
        {
            "category":"Restaurant",
            "type":"Food & Drink"
        }
    ],
    "sg:phone":"+1 661 251 7760",
    "sg:postcode":"91351",
    "sg:province":"CA",
    "sg:tags":[
        "eating"
    ],
    "wof:name":"Justa Pizza",
    "wof:placetype":"venue"
},
  "geometry": {"coordinates":[-118.484033,34.420395],"type":"Point"}
}