{
  "type": "Feature",
  "properties": {
    "iso:country":"US",
    "sg:address":"757 Beach St Rear Parking Lot",
    "sg:city":"San Francisco",
    "sg:classifiers":[
        {
            "category":"Landmark",
            "subcategory":"Tourist Information",
            "type":"Public Place"
        }
    ],
    "sg:phone":"+1 415 474 3130",
    "sg:postcode":"94109",
    "sg:province":"CA",
    "sg:tags":[
        "tour"
    ],
    "sg:website":"www.sfelectrictour.com",
    "wof:name":"Electric Tour Company - Segway Tours",
    "wof:placetype":"venue"
},
  "geometry": {"coordinates":[-122.421494,37.80657],"type":"Point"}
}