{
  "type": "Feature",
  "properties": {
    "addr:full":"239 E 4th St Los Angeles CA 90013",
    "addr:housenumber":"239",
    "addr:postcode":"90013",
    "addr:street":"E 4Th St",
    "iso:country":"US",
    "sg:address":"239 E 4th St",
    "sg:city":"Los Angeles",
    "sg:classifiers":[
        {
            "category":"Manufacturing",
            "subcategory":"Glass & Minerals",
            "type":"Manufacturing & Wholesale Goods"
        }
    ],
    "sg:phone":"+1 213 617 0328",
    "sg:postcode":"90013",
    "sg:province":"CA",
    "sg:tags":[
        "product",
        "mfg"
    ],
    "wof:name":"Calsun Glass World",
    "wof:placetype":"venue"
},
  "geometry": {"coordinates":[-118.24512799999999,34.046808],"type":"Point"}
}