{
  "type": "Feature",
  "properties": {
    "addr:full":"949 University Ave Sacramento CA 95825",
    "addr:housenumber":"949",
    "addr:postcode":"95825",
    "addr:street":"University Ave",
    "iso:country":"US",
    "sg:address":"949 University Ave",
    "sg:city":"Sacramento",
    "sg:classifiers":[
        {
            "category":"Health Services",
            "subcategory":"Health Practitioner",
            "type":"Services"
        }
    ],
    "sg:phone":"+1 916 564 6248",
    "sg:postcode":"95825",
    "sg:province":"CA",
    "sg:tags":[
        "psychologist"
    ],
    "wof:name":"Advances In Psychotherapy",
    "wof:placetype":"venue"
},
  "geometry": {"coordinates":[-121.41705,38.562624],"type":"Point"}
}