{
  "type": "Feature",
  "properties": {
    "iso:country":"US",
    "sg:address":"5705 Lankershim Blvd",
    "sg:city":"North Hollywood",
    "sg:classifiers":[
        {
            "category":"Autos & Motor Vehicles",
            "subcategory":"Automobile Sales",
            "type":"Retail Goods"
        }
    ],
    "sg:phone":"+1 818 503 5454",
    "sg:postcode":"91601",
    "sg:province":"CA",
    "sg:tags":[
        "car",
        "dealer"
    ],
    "wof:name":"Car Star Motors",
    "wof:placetype":"venue"
},
  "geometry": {"coordinates":[-118.380704,34.174782],"type":"Point"}
}