{
  "type": "Feature",
  "properties": {
    "addr:full":"2361 Ulric St San Diego CA 92111",
    "addr:housenumber":"2361",
    "addr:postcode":"92111",
    "addr:street":"Ulric St",
    "iso:country":"US",
    "sg:address":"2361 Ulric St",
    "sg:city":"San Diego",
    "sg:classifiers":[
        {
            "category":"Shopping",
            "subcategory":"Pharmacy",
            "type":"Retail Goods"
        }
    ],
    "sg:phone":"+1 858 277 6145",
    "sg:postcode":"92111",
    "sg:province":"CA",
    "sg:tags":[
        "drugstore"
    ],
    "wof:name":"Linda Vista Pharmacy",
    "wof:placetype":"venue"
},
  "geometry": {"coordinates":[-117.16999800000001,32.786201],"type":"Point"}
}