{
  "type": "Feature",
  "properties": {
    "iso:country":"US",
    "sg:address":"311 California St. Suite 300",
    "sg:city":"San Francisco",
    "sg:classifiers":[
        {
            "category":"Health Services",
            "subcategory":"Health Practitioner",
            "type":"Services"
        }
    ],
    "sg:phone":"+1 415 860 0698",
    "sg:postcode":"94104",
    "sg:province":"CA",
    "sg:tags":[
        "acupuncture"
    ],
    "sg:website":"www.balancerestored.com/about4.html",
    "wof:name":"Anne Cabrinha, M.S., L.Ac.",
    "wof:placetype":"venue"
},
  "geometry": {"coordinates":[-122.400294,37.793124],"type":"Point"}
}