{
  "type": "Feature",
  "properties": {
    "addr:full":"1001 N San Fernando Blvd #130 Burbank CA 91504",
    "addr:housenumber":"1001",
    "addr:postcode":"91504",
    "addr:street":"N San Fernando Blvd # 130",
    "iso:country":"US",
    "sg:address":"1001 N San Fernando Blvd #130",
    "sg:city":"Burbank",
    "sg:classifiers":[
        {
            "category":"Food & Beverages",
            "subcategory":"Bakery",
            "type":"Retail Goods"
        }
    ],
    "sg:phone":"+1 818 841 0076",
    "sg:postcode":"91504",
    "sg:province":"CA",
    "sg:tags":[
        "sandwich"
    ],
    "sg:website":"www.quiznos.com",
    "wof:name":"Quizno's",
    "wof:placetype":"venue"
},
  "geometry": {"coordinates":[-118.318067,34.18689],"type":"Point"}
}