{
  "type": "Feature",
  "properties": {
    "iso:country":"US",
    "sg:address":"2244 N Indian Hill Blvd",
    "sg:city":"Claremont",
    "sg:classifiers":[
        {
            "category":"Manufacturing",
            "subcategory":"Retail Goods",
            "type":"Manufacturing & Wholesale Goods"
        }
    ],
    "sg:phone":"+1 909 398 4195",
    "sg:postcode":"91711",
    "sg:province":"CA",
    "sg:tags":[
        "mfr",
        "printer",
        "ribbon"
    ],
    "wof:name":"I B E X",
    "wof:placetype":"venue"
},
  "geometry": {"coordinates":[-117.720208,34.124137],"type":"Point"}
}