{
  "type": "Feature",
  "properties": {
    "addr:full":"1193 Yerba Verde Dr El Cajon CA 92020",
    "addr:housenumber":"1193",
    "addr:postcode":"92020",
    "addr:street":"Yerba Verde Dr",
    "iso:country":"US",
    "sg:address":"1193 Yerba Verde Dr",
    "sg:city":"El Cajon",
    "sg:classifiers":[
        {
            "category":"Wholesale",
            "subcategory":"Machinery & Supplies",
            "type":"Manufacturing & Wholesale Goods"
        }
    ],
    "sg:phone":"+1 619 449 5442",
    "sg:postcode":"92020",
    "sg:province":"CA",
    "sg:tags":[
        "equipment",
        "transportation"
    ],
    "wof:name":"Milas Air Supply",
    "wof:placetype":"venue"
},
  "geometry": {"coordinates":[-116.983964,32.809557],"type":"Point"}
}