{
  "type": "Feature",
  "properties": {
    "addr:full":"13928 Ramona Blvd Baldwin Park CA 91706",
    "addr:housenumber":"13928",
    "addr:postcode":"91706",
    "addr:street":"Ramona Blvd",
    "iso:country":"US",
    "sg:address":"13928 Ramona Blvd",
    "sg:city":"Baldwin Park",
    "sg:classifiers":[
        {
            "category":"Personal",
            "subcategory":"Barber",
            "type":"Services"
        }
    ],
    "sg:phone":"+1 626 960 3076",
    "sg:postcode":"91706",
    "sg:province":"CA",
    "wof:name":"Sir Williams Barber Shop",
    "wof:placetype":"venue"
},
  "geometry": {"coordinates":[-117.968435,34.08436],"type":"Point"}
}