{
  "type": "Feature",
  "properties": {
    "iso:country":"US",
    "sg:address":"1813 E Lomita Ave",
    "sg:city":"Orange",
    "sg:classifiers":[
        {
            "category":"Wholesale",
            "subcategory":"Sporting Goods",
            "type":"Manufacturing & Wholesale Goods"
        }
    ],
    "sg:phone":"+1 714 633 9864",
    "sg:postcode":"92867",
    "sg:province":"CA",
    "wof:name":"Orange Billiards Service",
    "wof:placetype":"venue"
},
  "geometry": {"coordinates":[-117.834053,33.800932],"type":"Point"}
}