{
  "type": "Feature",
  "properties": {
    "iso:country":"US",
    "sg:address":"740 Water St",
    "sg:city":"Santa Cruz",
    "sg:classifiers":[
        {
            "category":"Personal",
            "subcategory":"Beauty Salon",
            "type":"Services"
        }
    ],
    "sg:phone":"+1 831 429 2061",
    "sg:postcode":"95060",
    "sg:province":"CA",
    "wof:name":"Hairheaven An Upscale Salon",
    "wof:placetype":"venue"
},
  "geometry": {"coordinates":[-122.014233,36.981307],"type":"Point"}
}