{
  "type": "Feature",
  "properties": {
    "addr:full":"630 N Baylor St Pacific Palisades CA 90272",
    "addr:housenumber":"630",
    "addr:postcode":"90272",
    "addr:street":"N Baylor St",
    "iso:country":"US",
    "sg:address":"630 N Baylor St",
    "sg:city":"Pacific Palisades",
    "sg:classifiers":[
        {
            "category":"Professional",
            "subcategory":"Research",
            "type":"Services"
        }
    ],
    "sg:phone":"+1 310 450 7107",
    "sg:postcode":"90272",
    "sg:province":"CA",
    "sg:tags":[
        "consulting",
        "commercial",
        "business",
        "physical"
    ],
    "wof:name":"Optimal Network Solutions",
    "wof:placetype":"venue"
},
  "geometry": {"coordinates":[-118.54319599999999,34.047468],"type":"Point"}
}