{
  "type": "Feature",
  "properties": {
    "iso:country":"US",
    "sg:address":"5907 Kanan Rd",
    "sg:city":"Agoura Hills",
    "sg:classifiers":[
        {
            "category":"Arts & Performance",
            "subcategory":"Art Gallery",
            "type":"Entertainment"
        }
    ],
    "sg:phone":"+1 818 991 8161",
    "sg:postcode":"91301",
    "sg:province":"CA",
    "sg:website":"www.frameyourart.net",
    "wof:name":"Frame Gallery the",
    "wof:placetype":"venue"
},
  "geometry": {"coordinates":[-118.758003,34.1642],"type":"Point"}
}