{
  "type": "Feature",
  "properties": {
    "addr:full":"453 S Spring St Los Angeles CA 90013",
    "addr:housenumber":"453",
    "addr:postcode":"90013",
    "addr:street":"S Spring St",
    "iso:country":"US",
    "sg:address":"453 S Spring St",
    "sg:city":"Los Angeles",
    "sg:classifiers":[
        {
            "category":"Professional",
            "subcategory":"Lawyer & Legal Services",
            "type":"Services"
        }
    ],
    "sg:phone":"+1 213 489 7559",
    "sg:postcode":"90013",
    "sg:province":"CA",
    "sg:tags":[
        "attorney",
        "bureau"
    ],
    "wof:name":"Emergency Litigation Support",
    "wof:placetype":"venue"
},
  "geometry": {"coordinates":[-118.249099,34.048195],"type":"Point"}
}