{
  "type": "Feature",
  "properties": {
    "iso:country":"US",
    "sg:address":"324 47th St",
    "sg:city":"San Diego",
    "sg:classifiers":[
        {
            "category":"Health Services",
            "subcategory":"Clinic",
            "type":"Services"
        }
    ],
    "sg:phone":"+1 619 264 7351",
    "sg:postcode":"92102",
    "sg:province":"CA",
    "sg:tags":[
        "aids",
        "testing",
        "information"
    ],
    "wof:name":"Forty-Seventh Street Chr-God",
    "wof:placetype":"venue"
},
  "geometry": {"coordinates":[-117.09374200000001,32.708661],"type":"Point"}
}