{
  "type": "Feature",
  "properties": {
    "iso:country":"US",
    "sg:address":"11270 Sanders Dr Ste A",
    "sg:city":"Rancho Cordova",
    "sg:classifiers":[
        {
            "category":"Sports & Exercise",
            "subcategory":"Gym",
            "type":"Entertainment"
        },
        {
            "category":"Recreation",
            "type":"Entertainment"
        }
    ],
    "sg:phone":"+1 916 635 6735",
    "sg:postcode":"95742",
    "sg:province":"CA",
    "sg:tags":[
        "trainer",
        "summer",
        "camp"
    ],
    "sg:website":"www.velocitysp.com/ranchocordova",
    "wof:name":"Velocity Sports Performance",
    "wof:placetype":"venue"
},
  "geometry": {"coordinates":[-121.26342,38.586145],"type":"Point"}
}