{
  "type": "Feature",
  "properties": {
    "addr:full":"1493 Sycamore Canyon Rd Santa Barbara CA 93108",
    "addr:housenumber":"1493",
    "addr:postcode":"93108",
    "addr:street":"Sycamore Canyon Rd",
    "iso:country":"US",
    "sg:address":"1493 Sycamore Canyon Rd",
    "sg:city":"Santa Barbara",
    "sg:classifiers":[
        {
            "category":"Farming",
            "subcategory":"Farm",
            "type":"Manufacturing & Wholesale Goods"
        }
    ],
    "sg:phone":"+1 805 963 3566",
    "sg:postcode":"93108",
    "sg:province":"CA",
    "wof:name":"Figueroa Farms",
    "wof:placetype":"venue"
},
  "geometry": {"coordinates":[-119.67651499999999,34.435353],"type":"Point"}
}