{
  "type": "Feature",
  "properties": {
    "iso:country":"US",
    "sg:address":"2935 Grand Ave",
    "sg:city":"Los Olivos",
    "sg:classifiers":[
        {
            "category":"Shopping",
            "subcategory":"Used Merchandise",
            "type":"Retail Goods"
        }
    ],
    "sg:phone":"+1 805 688 8700",
    "sg:postcode":"93441",
    "sg:province":"CA",
    "sg:tags":[
        "antique"
    ],
    "wof:name":"Pine Trader Antiques",
    "wof:placetype":"venue"
},
  "geometry": {"coordinates":[-120.114999,34.666554],"type":"Point"}
}