{
  "type": "Feature",
  "properties": {
    "addr:full":"2000 Hyde St, San Francisco, CA, USA",
    "addr:housenumber":2000,
    "addr:postcode":"94109",
    "addr:street":"Hyde St",
    "iso:country":"US",
    "name:eng_x_preferred":[
        "Zarzuela"
    ],
    "wof:name":"Zarzuela",
    "wof:placetype":"venue"
},
  "geometry": {"coordinates":[-122.418888,37.799408],"type":"Point"}
}