{
  "type": "Feature",
  "properties": {
    "addr:full":"7296 Atlantic Ave Cudahy CA 90201",
    "addr:housenumber":"7296",
    "addr:postcode":"90201",
    "addr:street":"Atlantic Ave",
    "iso:country":"US",
    "sg:address":"7296 Atlantic Ave",
    "sg:city":"Cudahy",
    "sg:classifiers":[
        {
            "category":"Restaurant",
            "type":"Food & Drink"
        }
    ],
    "sg:phone":"+1 323 773 5755",
    "sg:postcode":"90201",
    "sg:province":"CA",
    "sg:tags":[
        "pizza"
    ],
    "sg:website":"www.lapizzaloca.com",
    "wof:name":"La Pizza Loca",
    "wof:placetype":"venue"
},
  "geometry": {"coordinates":[-118.187719,33.969092],"type":"Point"}
}