{
  "type": "Feature",
  "properties": {
    "addr:full":"6042 Skyfarm Dr Castro Valley CA 94552",
    "addr:housenumber":"6042",
    "addr:postcode":"94552",
    "addr:street":"Skyfarm Dr",
    "iso:country":"US",
    "sg:address":"6042 Skyfarm Dr",
    "sg:city":"Castro Valley",
    "sg:classifiers":[
        {
            "category":"Building & Trades",
            "subcategory":"Plumbing",
            "type":"Services"
        }
    ],
    "sg:phone":"+1 510 727 9790",
    "sg:postcode":"94552",
    "sg:province":"CA",
    "sg:tags":[
        "product",
        "management",
        "energy",
        "system"
    ],
    "wof:name":"Cooper Compression",
    "wof:placetype":"venue"
},
  "geometry": {"coordinates":[-122.059376,37.726359],"type":"Point"}
}