{
  "type": "Feature",
  "properties": {
    "addr:full":"67502 E Palm Canyon Dr Cathedral City CA 92234",
    "addr:housenumber":"67502",
    "addr:postcode":"92234",
    "addr:street":"E Palm Canyon Dr",
    "iso:country":"US",
    "sg:address":"67502 E Palm Canyon Dr",
    "sg:city":"Cathedral City",
    "sg:classifiers":[
        {
            "category":"Shopping",
            "subcategory":"Gifts & Souvenirs",
            "type":"Retail Goods"
        }
    ],
    "sg:phone":"+1 760 324 0888",
    "sg:postcode":"92234",
    "sg:province":"CA",
    "sg:tags":[
        "balloon",
        "artist"
    ],
    "wof:name":"Balloony Tunes Party Center",
    "wof:placetype":"venue"
},
  "geometry": {"coordinates":[-116.48288599999999,33.788777],"type":"Point"}
}