{
  "type": "Feature",
  "properties": {
    "addr:full":"5021 Columbus Ave Sherman Oaks CA 91403",
    "addr:housenumber":"5021",
    "addr:postcode":"91403",
    "addr:street":"Columbus Ave",
    "iso:country":"US",
    "sg:address":"5021 Columbus Ave",
    "sg:city":"Sherman Oaks",
    "sg:classifiers":[
        {
            "category":"Shopping",
            "subcategory":"Musical Instruments",
            "type":"Retail Goods"
        }
    ],
    "sg:phone":"+1 818 501 2051",
    "sg:postcode":"91403",
    "sg:province":"CA",
    "sg:tags":[
        "music",
        "dealer"
    ],
    "wof:name":"Morena Music Inc",
    "wof:placetype":"venue"
},
  "geometry": {"coordinates":[-118.46404699999999,34.161809],"type":"Point"}
}