{
  "type": "Feature",
  "properties": {
    "addr:full":"74711 Dillon Rd Desert Hot Spgs CA 92241",
    "addr:housenumber":"74711",
    "addr:postcode":"92241",
    "addr:street":"Dillon Rd",
    "iso:country":"US",
    "sg:address":"74711 Dillon Rd",
    "sg:city":"Desert Hot Spgs",
    "sg:classifiers":[
        {
            "category":"Banks & Credit Unions",
            "subcategory":"Investment Brokerage",
            "type":"Services"
        }
    ],
    "sg:phone":"+1 760 251 6855",
    "sg:postcode":"92241",
    "sg:province":"CA",
    "sg:tags":[
        "advisory",
        "financial"
    ],
    "wof:name":"Topco Financial Svc Inc",
    "wof:placetype":"venue"
},
  "geometry": {"coordinates":[-116.361543,33.9043],"type":"Point"}
}