{
  "type": "Feature",
  "properties": {
    "addr:full":"5028 Fairfax Ave Oakland CA 94601",
    "addr:housenumber":"5028",
    "addr:postcode":"94601",
    "addr:street":"Fairfax Ave",
    "iso:country":"US",
    "sg:address":"5028 Fairfax Ave",
    "sg:city":"Oakland",
    "sg:classifiers":[
        {
            "category":"Manufacturing",
            "subcategory":"Printing",
            "type":"Manufacturing & Wholesale Goods"
        }
    ],
    "sg:phone":"+1 510 318 0190",
    "sg:postcode":"94601",
    "sg:province":"CA",
    "sg:tags":[
        "magazines-distributors"
    ],
    "wof:name":"Cocoa Magazine",
    "wof:placetype":"venue"
},
  "geometry": {"coordinates":[-122.201291,37.776731],"type":"Point"}
}