{
  "type": "Feature",
  "properties": {
    "addr:full":"100 N Hubbard Ave San Fernando CA 91340",
    "addr:housenumber":"100",
    "addr:postcode":"91340",
    "addr:street":"N Hubbard Ave",
    "iso:country":"US",
    "sg:address":"100 N Hubbard Ave",
    "sg:city":"San Fernando",
    "sg:classifiers":[
        {
            "category":"Retail",
            "subcategory":"Repair Shop",
            "type":"Services"
        }
    ],
    "sg:phone":"+1 818 362 8787",
    "sg:postcode":"91340",
    "sg:province":"CA",
    "sg:tags":[
        "upholsterer"
    ],
    "wof:name":"Padrinos Upholstery",
    "wof:placetype":"venue"
},
  "geometry": {"coordinates":[-118.44751599999999,34.292078],"type":"Point"}
}