{
  "type": "Feature",
  "properties": {
    "iso:country":"US",
    "sg:address":"1133 S 6th St",
    "sg:city":"San Jose",
    "sg:classifiers":[
        {
            "category":"Building & Trades",
            "subcategory":"Cleaning & Sanitation",
            "type":"Services"
        }
    ],
    "sg:phone":"+1 408 287 4821",
    "sg:postcode":"95112",
    "sg:province":"CA",
    "sg:tags":[
        "house"
    ],
    "wof:name":"Maid Finders Personnel",
    "wof:placetype":"venue"
},
  "geometry": {"coordinates":[-121.87231,37.321239],"type":"Point"}
}