{
  "type": "Feature",
  "properties": {
    "iso:country":"US",
    "sg:address":"2001 Piner Rd",
    "sg:city":"Santa Rosa",
    "sg:classifiers":[
        {
            "category":"Professional",
            "subcategory":"Computer Services",
            "type":"Services"
        }
    ],
    "sg:phone":"+1 707 546 2555",
    "sg:postcode":"95403",
    "sg:province":"CA",
    "sg:tags":[
        "related"
    ],
    "wof:name":"Phil Hersh Associates",
    "wof:placetype":"venue"
},
  "geometry": {"coordinates":[-122.754215,38.467134],"type":"Point"}
}