{
  "type": "Feature",
  "properties": {
    "iso:country":"US",
    "sg:address":"1314 James M Wood Blvd",
    "sg:city":"Los Angeles",
    "sg:classifiers":[
        {
            "category":"Wholesale",
            "subcategory":"Medical Equipment & Supplies",
            "type":"Manufacturing & Wholesale Goods"
        }
    ],
    "sg:phone":"+1 213 385 9888",
    "sg:postcode":"90015",
    "sg:province":"CA",
    "sg:tags":[
        "dental"
    ],
    "wof:name":"K W I Dental Supplies",
    "wof:placetype":"venue"
},
  "geometry": {"coordinates":[-118.2693,34.048982],"type":"Point"}
}