{
  "type": "Feature",
  "properties": {
    "addr:full":"7700 Edgewater Dr Oakland CA 94621",
    "addr:housenumber":"7700",
    "addr:postcode":"94621",
    "addr:street":"Edgewater Dr",
    "iso:country":"US",
    "sg:address":"7700 Edgewater Dr",
    "sg:city":"Oakland",
    "sg:classifiers":[
        {
            "category":"Deli",
            "type":"Food & Drink"
        }
    ],
    "sg:phone":"+1 510 638 8003",
    "sg:postcode":"94621",
    "sg:province":"CA",
    "wof:name":"E & L Deli",
    "wof:placetype":"venue"
},
  "geometry": {"coordinates":[-122.183998,37.7575],"type":"Point"}
}