{
  "type": "Feature",
  "properties": {
    "iso:country":"US",
    "sg:address":"3033 Buckminster Dr",
    "sg:city":"Elk Grove",
    "sg:classifiers":[
        {
            "category":"Organizations",
            "subcategory":"Religious Organization",
            "type":"Services"
        }
    ],
    "sg:phone":"+1 916 683 6500",
    "sg:postcode":"95758",
    "sg:province":"CA",
    "sg:tags":[
        "church"
    ],
    "sg:website":"www.livingwater-eg.org",
    "wof:name":"Living Waters Lutheran Church",
    "wof:placetype":"venue"
},
  "geometry": {"coordinates":[-121.471107,38.41896],"type":"Point"}
}