{
  "type": "Feature",
  "properties": {
    "addr:full":"550 Paularino Ave Apt D 203 Costa Mesa CA 92626",
    "addr:housenumber":"550;203",
    "addr:postcode":"92626",
    "addr:street":"Paularino Ave Apt D",
    "iso:country":"US",
    "sg:address":"550 Paularino Ave Apt D 203",
    "sg:city":"Costa Mesa",
    "sg:classifiers":[
        {
            "category":"Home & Garden",
            "subcategory":"Carpets & Floor Coverings",
            "type":"Retail Goods"
        }
    ],
    "sg:phone":"+1 714 235 0276",
    "sg:postcode":"92626",
    "sg:province":"CA",
    "sg:tags":[
        "carpeting"
    ],
    "wof:name":"Dutchman Woodworks",
    "wof:placetype":"venue"
},
  "geometry": {"coordinates":[-117.879052,33.682497],"type":"Point"}
}