{
  "type": "Feature",
  "properties": {
    "addr:full":"42296 Iron Gate Ln Murrieta CA 92562",
    "addr:housenumber":"42296",
    "addr:postcode":"92562",
    "addr:street":"Iron Gate Ln",
    "iso:country":"US",
    "sg:address":"42296 Iron Gate Ln",
    "sg:city":"Murrieta",
    "sg:classifiers":[
        {
            "category":"Shopping",
            "type":"Retail Goods"
        }
    ],
    "sg:phone":"+1 951 698 8500",
    "sg:postcode":"92562",
    "sg:province":"CA",
    "sg:tags":[
        "pet",
        "shop"
    ],
    "wof:name":"Ocean 1",
    "wof:placetype":"venue"
},
  "geometry": {"coordinates":[-117.22436500000001,33.556622],"type":"Point"}
}