{
  "type": "Feature",
  "properties": {
    "addr:full":"1800 24th St Bakersfield CA 93301",
    "addr:housenumber":"1800",
    "addr:postcode":"93301",
    "addr:street":"24Th St",
    "iso:country":"US",
    "sg:address":"1800 24th St",
    "sg:city":"Bakersfield",
    "sg:classifiers":[
        {
            "category":"Retail",
            "subcategory":"Auto Rental",
            "type":"Services"
        }
    ],
    "sg:phone":"+1 661 323 2711",
    "sg:postcode":"93301",
    "sg:province":"CA",
    "sg:tags":[
        "passenger",
        "car"
    ],
    "wof:name":"Enterprise Rent-A-Car",
    "wof:placetype":"venue"
},
  "geometry": {"coordinates":[-119.023493,35.381018],"type":"Point"}
}