{
  "type": "Feature",
  "properties": {
    "addr:full":"612 Linden Avenue South San Francisco CA 94080",
    "addr:housenumber":"612",
    "addr:postcode":"94080",
    "addr:street":"Linden Avenue",
    "iso:country":"US",
    "sg:address":"612 Linden Avenue",
    "sg:city":"South San Francisco",
    "sg:classifiers":[
        {
            "category":"Food & Beverages",
            "subcategory":"Groceries & Convenience Stores",
            "type":"Retail Goods"
        }
    ],
    "sg:phone":"+1 650 871 9121",
    "sg:postcode":"94080",
    "sg:province":"CA",
    "wof:name":"Estrada's Meat Market",
    "wof:placetype":"venue"
},
  "geometry": {"coordinates":[-122.40883700000001,37.658396],"type":"Point"}
}