{
  "type": "Feature",
  "properties": {
    "addr:full":"4424 Pearl Avenue San Jose CA 95136",
    "addr:housenumber":"4424",
    "addr:postcode":"95136",
    "addr:street":"Pearl Avenue",
    "iso:country":"US",
    "sg:address":"4424 Pearl Avenue",
    "sg:city":"San Jose",
    "sg:classifiers":[
        {
            "category":"Real Estate",
            "subcategory":"Real Estate Services",
            "type":"Services"
        }
    ],
    "sg:phone":"+1 408 225 8538",
    "sg:postcode":"95136",
    "sg:province":"CA",
    "wof:name":"Canok Cindy Rl Est Agt",
    "wof:placetype":"venue"
},
  "geometry": {"coordinates":[-121.866664,37.266931],"type":"Point"}
}