{
  "type": "Feature",
  "properties": {
    "iso:country":"US",
    "sg:address":"13300 Brooks Dr",
    "sg:city":"Baldwin Park",
    "sg:classifiers":[
        {
            "category":"Professional",
            "subcategory":"Business Services",
            "type":"Services"
        }
    ],
    "sg:phone":"+1 626 813 6619",
    "sg:postcode":"91706",
    "sg:province":"CA",
    "sg:tags":[
        "interior",
        "consultant",
        "design",
        "decorator"
    ],
    "wof:name":"AMA Design",
    "wof:placetype":"venue"
},
  "geometry": {"coordinates":[-117.983643,34.098691],"type":"Point"}
}