{
  "type": "Feature",
  "properties": {
    "addr:full":"4501 Mirador Dr Pleasanton CA 94566",
    "addr:housenumber":"4501",
    "addr:postcode":"94566",
    "addr:street":"Mirador Dr",
    "iso:country":"US",
    "sg:address":"4501 Mirador Dr",
    "sg:city":"Pleasanton",
    "sg:classifiers":[
        {
            "category":"Wholesale",
            "subcategory":"Medical Equipment & Supplies",
            "type":"Manufacturing & Wholesale Goods"
        }
    ],
    "sg:phone":"+1 925 426 1750",
    "sg:postcode":"94566",
    "sg:province":"CA",
    "sg:tags":[
        "sales"
    ],
    "wof:name":"Norco Orthopedics Inc",
    "wof:placetype":"venue"
},
  "geometry": {"coordinates":[-121.866991,37.653755],"type":"Point"}
}