{
  "type": "Feature",
  "properties": {
    "iso:country":"US",
    "sg:address":"4100 Glencoe Ave",
    "sg:city":"Marina Del Rey",
    "sg:classifiers":[
        {
            "category":"Retail",
            "subcategory":"Auto Repair",
            "type":"Services"
        }
    ],
    "sg:phone":"+1 310 821 6801",
    "sg:postcode":"90292",
    "sg:province":"CA",
    "sg:tags":[
        "repairing",
        "automobile"
    ],
    "wof:name":"Exotic Performance",
    "wof:placetype":"venue"
},
  "geometry": {"coordinates":[-118.441053,33.988342],"type":"Point"}
}