{
  "type": "Feature",
  "properties": {
    "iso:country":"US",
    "sg:address":"1068 Fassler Ave",
    "sg:city":"Pacifica",
    "sg:classifiers":[
        {
            "category":"Recreation",
            "subcategory":"Arcade",
            "type":"Entertainment"
        }
    ],
    "sg:phone":"+1 650 355 8458",
    "sg:postcode":"94044",
    "sg:province":"CA",
    "sg:tags":[
        "amusement",
        "devices"
    ],
    "wof:name":"Pacifica Pinball Plus",
    "wof:placetype":"venue"
},
  "geometry": {"coordinates":[-122.481966,37.598889],"type":"Point"}
}