{
  "type": "Feature",
  "properties": {
    "addr:full":"2700 W Orangethorpe Ave Fullerton CA 92833",
    "addr:housenumber":"2700",
    "addr:postcode":"92833",
    "addr:street":"W Orangethorpe Ave",
    "iso:country":"US",
    "sg:address":"2700 W Orangethorpe Ave",
    "sg:city":"Fullerton",
    "sg:classifiers":[
        {
            "category":"Shopping",
            "subcategory":"Bicycles & Sporting Goods",
            "type":"Retail Goods"
        }
    ],
    "sg:phone":"+1 714 525 1827",
    "sg:postcode":"92833",
    "sg:province":"CA",
    "sg:tags":[
        "tackle",
        "outdoor",
        "gear",
        "fishing"
    ],
    "sg:website":"www.bmfs.net",
    "wof:name":"Bob Marriott's Fly Fishing Store",
    "wof:placetype":"venue"
},
  "geometry": {"coordinates":[-117.974998,33.8592],"type":"Point"}
}