{
  "type": "Feature",
  "properties": {
    "addr:full":"303 E Acequia Ave Visalia CA 93291",
    "addr:housenumber":"303",
    "addr:postcode":"93291",
    "addr:street":"E Acequia Ave",
    "iso:country":"US",
    "sg:address":"303 E Acequia Ave",
    "sg:city":"Visalia",
    "sg:classifiers":[
        {
            "category":"Government",
            "subcategory":"Office",
            "type":"Public Place"
        }
    ],
    "sg:phone":"+1 559 713 4000",
    "sg:postcode":"93291",
    "sg:province":"CA",
    "sg:tags":[
        "village"
    ],
    "sg:website":"www.visalia.org",
    "wof:name":"Visalia Convention Ctr",
    "wof:placetype":"venue"
},
  "geometry": {"coordinates":[-119.288966,36.329188],"type":"Point"}
}