{
  "type": "Feature",
  "properties": {
    "iso:country":"US",
    "sg:address":"100 Spear St",
    "sg:city":"San Francisco",
    "sg:classifiers":[
        {
            "category":"Banks & Credit Unions",
            "subcategory":"Investment Brokerage",
            "type":"Services"
        }
    ],
    "sg:phone":"+1 415 882 4550",
    "sg:postcode":"94105",
    "sg:province":"CA",
    "sg:tags":[
        "management"
    ],
    "sg:website":"www.industrialgrowthpartners.com",
    "wof:name":"Industrial Growth Partners",
    "wof:placetype":"venue"
},
  "geometry": {"coordinates":[-122.392525,37.791311],"type":"Point"}
}