{
  "type": "Feature",
  "properties": {
    "addr:full":"11623 Slater Ave Fountain Valley CA 92708",
    "addr:housenumber":"11623",
    "addr:postcode":"92708",
    "addr:street":"Slater Ave",
    "iso:country":"US",
    "sg:address":"11623 Slater Ave",
    "sg:city":"Fountain Valley",
    "sg:classifiers":[
        {
            "category":"Professional",
            "subcategory":"Accounting & Tax Preparation",
            "type":"Services"
        }
    ],
    "sg:phone":"+1 714 556 4710",
    "sg:postcode":"92708",
    "sg:province":"CA",
    "sg:tags":[
        "accountant"
    ],
    "wof:name":"Iverson James H CPA",
    "wof:placetype":"venue"
},
  "geometry": {"coordinates":[-117.929001,33.709202],"type":"Point"}
}