{
  "type": "Feature",
  "properties": {
    "iso:country":"US",
    "sg:address":"5980 Casitas Pass Rd",
    "sg:city":"Carpinteria",
    "sg:classifiers":[
        {
            "category":"Home & Garden",
            "subcategory":"Garden Supply",
            "type":"Retail Goods"
        }
    ],
    "sg:phone":"+1 805 684 9740",
    "sg:postcode":"93013",
    "sg:province":"CA",
    "sg:tags":[
        "nursery",
        "gardening"
    ],
    "wof:name":"Horticultural Labor Service",
    "wof:placetype":"venue"
},
  "geometry": {"coordinates":[-119.49099699999999,34.4025],"type":"Point"}
}