{
  "type": "Feature",
  "properties": {
    "addr:full":"1357 Healdsburg Ave Healdsburg CA 95448",
    "addr:housenumber":"1357",
    "addr:postcode":"95448",
    "addr:street":"Healdsburg Ave",
    "iso:country":"US",
    "sg:address":"1357 Healdsburg Ave",
    "sg:city":"Healdsburg",
    "sg:classifiers":[
        {
            "category":"Retail",
            "subcategory":"Self-service Laundry",
            "type":"Services"
        }
    ],
    "sg:phone":"+1 707 433 5723",
    "sg:postcode":"95448",
    "sg:province":"CA",
    "wof:name":"Healdsburg Coin Laundry",
    "wof:placetype":"venue"
},
  "geometry": {"coordinates":[-122.87272299999999,38.626972],"type":"Point"}
}