{
  "type": "Feature",
  "properties": {
    "addr:full":"1080 Carolan Ave Burlingame CA 94010",
    "addr:housenumber":"1080",
    "addr:postcode":"94010",
    "addr:street":"Carolan Ave",
    "iso:country":"US",
    "sg:address":"1080 Carolan Ave",
    "sg:city":"Burlingame",
    "sg:classifiers":[
        {
            "category":"Real Estate",
            "subcategory":"Real Estate Operator",
            "type":"Services"
        }
    ],
    "sg:phone":"+1 650 342 2313",
    "sg:postcode":"94010",
    "sg:province":"CA",
    "sg:tags":[
        "apartment"
    ],
    "wof:name":"Northpark Apartments",
    "wof:placetype":"venue"
},
  "geometry": {"coordinates":[-122.361088,37.587246],"type":"Point"}
}