{
  "type": "Feature",
  "properties": {
    "iso:country":"US",
    "sg:address":"881 San Bruno Ave W",
    "sg:city":"San Bruno",
    "sg:classifiers":[
        {
            "category":"Government",
            "subcategory":"Office",
            "type":"Public Place"
        }
    ],
    "sg:phone":"+1 650 877 8689",
    "sg:postcode":"94066",
    "sg:province":"CA",
    "sg:tags":[
        "surgical",
        "executive",
        "appliance",
        "mfg"
    ],
    "wof:name":"Airport Noise Abatement",
    "wof:placetype":"venue"
},
  "geometry": {"coordinates":[-122.41813500000001,37.628209],"type":"Point"}
}