{
  "type": "Feature",
  "properties": {
    "iso:country":"US",
    "sg:address":"16003 Old Valley Blvd",
    "sg:city":"La Puente",
    "sg:classifiers":[
        {
            "category":"Manufacturing",
            "subcategory":"Metals",
            "type":"Manufacturing & Wholesale Goods"
        }
    ],
    "sg:phone":"+1 626 369 3188",
    "sg:postcode":"91744",
    "sg:province":"CA",
    "sg:tags":[
        "stampings",
        "mfg"
    ],
    "wof:name":"Hi Tech Metal Spinning",
    "wof:placetype":"venue"
},
  "geometry": {"coordinates":[-117.950089,34.017027],"type":"Point"}
}