{
  "type": "Feature",
  "properties": {
    "addr:full":"4675 Tecolote Rd San Diego CA 92110",
    "addr:housenumber":"4675",
    "addr:postcode":"92110",
    "addr:street":"Tecolote Rd",
    "iso:country":"US",
    "sg:address":"4675 Tecolote Rd",
    "sg:city":"San Diego",
    "sg:classifiers":[
        {
            "category":"Recreation",
            "type":"Entertainment"
        }
    ],
    "sg:phone":"+1 619 275 3334",
    "sg:postcode":"92110",
    "sg:province":"CA",
    "sg:tags":[
        "club",
        "membership"
    ],
    "wof:name":"Tecolote Youth Baseball",
    "wof:placetype":"venue"
},
  "geometry": {"coordinates":[-117.19895,32.775631],"type":"Point"}
}