{
  "type": "Feature",
  "properties": {
    "iso:country":"US",
    "sg:address":"1101 E Compton Boulevard",
    "sg:city":"Compton",
    "sg:classifiers":[
        {
            "category":"Restaurant",
            "type":"Food & Drink"
        }
    ],
    "sg:phone":"+1 310 635 4876",
    "sg:postcode":"90221",
    "sg:province":"CA",
    "sg:tags":[
        "pizza"
    ],
    "wof:name":"New Millenium Pizza",
    "wof:placetype":"venue"
},
  "geometry": {"coordinates":[-118.21156,33.896073],"type":"Point"}
}