{
  "type": "Feature",
  "properties": {
    "addr:full":"37120 Fremont Blvd Fremont CA 94536",
    "addr:housenumber":"37120",
    "addr:postcode":"94536",
    "addr:street":"Fremont Blvd",
    "iso:country":"US",
    "sg:address":"37120 Fremont Blvd",
    "sg:city":"Fremont",
    "sg:classifiers":[
        {
            "category":"Real Estate",
            "subcategory":"Real Estate Agent",
            "type":"Services"
        }
    ],
    "sg:phone":"+1 510 792 7804",
    "sg:postcode":"94536",
    "sg:province":"CA",
    "wof:name":"Scenario Realty",
    "wof:placetype":"venue"
},
  "geometry": {"coordinates":[-122.01169299999999,37.56059],"type":"Point"}
}