{
  "type": "Feature",
  "properties": {
    "iso:country":"US",
    "sg:address":"351 Highland Dr",
    "sg:city":"Los Osos",
    "sg:classifiers":[
        {
            "category":"Building & Trades",
            "subcategory":"Construction",
            "type":"Services"
        }
    ],
    "sg:phone":"+1 805 543 9165",
    "sg:postcode":"93402",
    "sg:province":"CA",
    "sg:tags":[
        "foundation"
    ],
    "wof:name":"J R Spencer Construction Inc",
    "wof:placetype":"venue"
},
  "geometry": {"coordinates":[-120.849367,35.30877],"type":"Point"}
}