{
  "type": "Feature",
  "properties": {
    "addr:full":"81 Sienna Way San Rafael CA 94901",
    "addr:housenumber":"81",
    "addr:postcode":"94901",
    "addr:street":"Sienna Way",
    "iso:country":"US",
    "sg:address":"81 Sienna Way",
    "sg:city":"San Rafael",
    "sg:classifiers":[
        {
            "category":"Building & Trades",
            "subcategory":"Landscaping Services",
            "type":"Services"
        }
    ],
    "sg:phone":"+1 415 456 6757",
    "sg:postcode":"94901",
    "sg:province":"CA",
    "sg:tags":[
        "designer",
        "landscape"
    ],
    "wof:name":"Zone 17 Landscape Architecture",
    "wof:placetype":"venue"
},
  "geometry": {"coordinates":[-122.515372,37.984809],"type":"Point"}
}