{
  "type": "Feature",
  "properties": {
    "addr:full":"891 Kuhn Dr Chula Vista CA 91914",
    "addr:housenumber":"891",
    "addr:postcode":"91914",
    "addr:street":"Kuhn Dr",
    "iso:country":"US",
    "sg:address":"891 Kuhn Dr",
    "sg:city":"Chula Vista",
    "sg:classifiers":[
        {
            "category":"Health Services",
            "subcategory":"Health Practitioner",
            "type":"Services"
        }
    ],
    "sg:phone":"+1 619 656 5176",
    "sg:postcode":"91914",
    "sg:province":"CA",
    "sg:tags":[
        "therapist",
        "physical"
    ],
    "wof:name":"E & L & Assoc Physical Therapy",
    "wof:placetype":"venue"
},
  "geometry": {"coordinates":[-116.96737,32.65338],"type":"Point"}
}