{
  "type": "Feature",
  "properties": {
    "addr:full":"6285 E Spring St Ste 267 Long Beach CA 90808",
    "addr:housenumber":"6285",
    "addr:postcode":"90808",
    "addr:street":"E Spring St Ste 267",
    "iso:country":"US",
    "sg:address":"6285 E Spring St Ste 267",
    "sg:city":"Long Beach",
    "sg:classifiers":[
        {
            "category":"Building & Trades",
            "subcategory":"Construction",
            "type":"Services"
        }
    ],
    "sg:phone":"+1 562 697 8501",
    "sg:postcode":"90808",
    "sg:province":"CA",
    "sg:tags":[
        "contractor"
    ],
    "sg:website":"www.edgemontgaragedoor.com/",
    "wof:name":"Edgemont Garage Door",
    "wof:placetype":"venue"
},
  "geometry": {"coordinates":[-118.109298,33.810578],"type":"Point"}
}