{
  "type": "Feature",
  "properties": {
    "iso:country":"US",
    "sg:address":"920 E Arques Ave",
    "sg:city":"Sunnyvale",
    "sg:classifiers":[
        {
            "category":"Restaurant",
            "type":"Food & Drink"
        }
    ],
    "sg:phone":"+1 408 720 8004",
    "sg:postcode":"94085",
    "sg:province":"CA",
    "sg:tags":[
        "indian"
    ],
    "wof:name":"Vaigai",
    "wof:placetype":"venue"
},
  "geometry": {"coordinates":[-122.007707,37.380541],"type":"Point"}
}