{
  "type": "Feature",
  "properties": {
    "iso:country":"US",
    "sg:address":"1115 S Main Ave",
    "sg:city":"Fallbrook",
    "sg:classifiers":[
        {
            "category":"Retail",
            "subcategory":"Laundry & Dry Cleaning",
            "type":"Services"
        }
    ],
    "sg:phone":"+1 760 728 4234",
    "sg:postcode":"92028",
    "sg:province":"CA",
    "wof:name":"Fallbrook Cleaners",
    "wof:placetype":"venue"
},
  "geometry": {"coordinates":[-117.25099899999999,33.371498],"type":"Point"}
}