{
  "type": "Feature",
  "properties": {
    "iso:country":"US",
    "sg:address":"414 Bell Ave",
    "sg:city":"Yuba City",
    "sg:classifiers":[
        {
            "category":"Personal",
            "subcategory":"Beauty Salon",
            "type":"Services"
        }
    ],
    "sg:phone":"+1 530 671 1324",
    "sg:postcode":"95991",
    "sg:province":"CA",
    "wof:name":"Elsa's Beauty Salon",
    "wof:placetype":"venue"
},
  "geometry": {"coordinates":[-121.614622,39.121441],"type":"Point"}
}