{
  "type": "Feature",
  "properties": {
    "addr:full":"3305 E Miraloma Ave Anaheim CA 92806",
    "addr:housenumber":"3305",
    "addr:postcode":"92806",
    "addr:street":"E Miraloma Ave",
    "iso:country":"US",
    "sg:address":"3305 E Miraloma Ave",
    "sg:city":"Anaheim",
    "sg:classifiers":[
        {
            "category":"Building & Trades",
            "subcategory":"Cleaning & Sanitation",
            "type":"Services"
        }
    ],
    "sg:phone":"+1 714 854 9650",
    "sg:postcode":"92806",
    "sg:province":"CA",
    "sg:tags":[
        "carpet"
    ],
    "wof:name":"Steve Slawson Carpet Cleaning",
    "wof:placetype":"venue"
},
  "geometry": {"coordinates":[-117.851445,33.860324],"type":"Point"}
}