{
  "type": "Feature",
  "properties": {
    "iso:country":"US",
    "sg:address":"200 Main St Ste 102",
    "sg:city":"Huntington Beach",
    "sg:classifiers":[
        {
            "category":"Insurance",
            "subcategory":"Health Insurance",
            "type":"Services"
        }
    ],
    "sg:phone":"+1 714 374 1359",
    "sg:postcode":"92648",
    "sg:province":"CA",
    "sg:tags":[
        "market"
    ],
    "wof:name":"General Nutrition Centers",
    "wof:placetype":"venue"
},
  "geometry": {"coordinates":[-118.00099899999999,33.658001],"type":"Point"}
}