{
  "type": "Feature",
  "properties": {
    "addr:full":"3451 W Century Blvd Inglewood CA 90303",
    "addr:housenumber":"3451",
    "addr:postcode":"90303",
    "addr:street":"W Century Blvd",
    "iso:country":"US",
    "sg:address":"3451 W Century Blvd",
    "sg:city":"Inglewood",
    "sg:classifiers":[
        {
            "category":"Shopping",
            "subcategory":"Computers & Home Electronics",
            "type":"Retail Goods"
        },
        {
            "category":"Wholesale",
            "subcategory":"Office Equipment",
            "type":"Manufacturing & Wholesale Goods"
        },
        {
            "category":"Professional",
            "subcategory":"Printing & Photocopies",
            "type":"Services"
        },
        {
            "category":"Professional",
            "subcategory":"Computer Services",
            "type":"Services"
        },
        {
            "category":"Shopping",
            "subcategory":"Stationery & Office Supplies",
            "type":"Retail Goods"
        },
        {
            "category":"Wholesale",
            "subcategory":"Computers",
            "type":"Manufacturing & Wholesale Goods"
        }
    ],
    "sg:phone":"+1 866 950 4126",
    "sg:postcode":"90303",
    "sg:province":"CA",
    "sg:tags":[
        "printer",
        "register",
        "autographic",
        "duplicating",
        "hardware",
        "copying",
        "software",
        "furniture"
    ],
    "sg:website":"http://instorespecials.staples.com/staples/default.aspx?action=nuep&adref=yp",
    "wof:name":"STAPLES",
    "wof:placetype":"venue"
},
  "geometry": {"coordinates":[-118.332099,33.945475],"type":"Point"}
}