{
  "type": "Feature",
  "properties": {
    "iso:country":"US",
    "sg:address":"65 Commerce St",
    "sg:city":"Stockton",
    "sg:classifiers":[
        {
            "category":"Health Services",
            "subcategory":"Clinic",
            "type":"Services"
        }
    ],
    "sg:phone":"+1 209 943 3830",
    "sg:postcode":"95202",
    "sg:province":"CA",
    "sg:tags":[
        "banks",
        "blood",
        "center"
    ],
    "wof:name":"Delta Blood Bank",
    "wof:placetype":"venue"
},
  "geometry": {"coordinates":[-121.292577,37.952626],"type":"Point"}
}