{
  "type": "Feature",
  "properties": {
    "addr:full":"12135 Royal Rd El Cajon CA 92021",
    "addr:housenumber":"12135",
    "addr:postcode":"92021",
    "addr:street":"Royal Rd",
    "iso:country":"US",
    "sg:address":"12135 Royal Rd",
    "sg:city":"El Cajon",
    "sg:classifiers":[
        {
            "category":"Real Estate",
            "subcategory":"Real Estate Operator",
            "type":"Services"
        }
    ],
    "sg:phone":"+1 619 938 1890",
    "sg:postcode":"92021",
    "sg:province":"CA",
    "sg:tags":[
        "apartment"
    ],
    "wof:name":"Royal Road Apartments",
    "wof:placetype":"venue"
},
  "geometry": {"coordinates":[-116.931189,32.824022],"type":"Point"}
}