{
  "type": "Feature",
  "properties": {
    "iso:country":"US",
    "sg:address":"1014 E Cooley Dr",
    "sg:city":"Colton",
    "sg:classifiers":[
        {
            "category":"Building & Trades",
            "subcategory":"Construction",
            "type":"Services"
        }
    ],
    "sg:phone":"+1 909 824 6027",
    "sg:postcode":"92324",
    "sg:province":"CA",
    "sg:tags":[
        "contractor"
    ],
    "wof:name":"Caltera Restoration",
    "wof:placetype":"venue"
},
  "geometry": {"coordinates":[-117.309519,34.054676],"type":"Point"}
}