{
  "type": "Feature",
  "properties": {
    "iso:country":"US",
    "sg:address":"3417 W 43rd St",
    "sg:city":"Los Angeles",
    "sg:classifiers":[
        {
            "category":"Personal",
            "subcategory":"Barber",
            "type":"Services"
        }
    ],
    "sg:phone":"+1 323 296 2616",
    "sg:postcode":"90008",
    "sg:province":"CA",
    "wof:name":"Chief Economy Barber Shop",
    "wof:placetype":"venue"
},
  "geometry": {"coordinates":[-118.33200100000001,34.005901],"type":"Point"}
}