{
  "type": "Feature",
  "properties": {
    "addr:full":"2135 Civic Center Dr Side Redding CA 96001",
    "addr:housenumber":"2135",
    "addr:postcode":"96001",
    "addr:street":"Civic Center Dr",
    "iso:country":"US",
    "sg:address":"2135 Civic Center Dr Side",
    "sg:city":"Redding",
    "sg:classifiers":[
        {
            "category":"Professional",
            "subcategory":"Business Services",
            "type":"Services"
        }
    ],
    "sg:phone":"+1 530 225 2130",
    "sg:postcode":"96001",
    "sg:province":"CA",
    "sg:tags":[
        "medical",
        "administration"
    ],
    "sg:website":"http://www.calsurv.org",
    "wof:name":"Vector-Borne Disease Section",
    "wof:placetype":"venue"
},
  "geometry": {"coordinates":[-122.380641,40.575669],"type":"Point"}
}