{
  "type": "Feature",
  "properties": {
    "addr:full":"7090 N Cedar Ave Fresno CA 93720",
    "addr:housenumber":"7090",
    "addr:postcode":"93720",
    "addr:street":"N Cedar Ave",
    "iso:country":"US",
    "sg:address":"7090 N Cedar Ave",
    "sg:city":"Fresno",
    "sg:classifiers":[
        {
            "category":"Insurance",
            "subcategory":"Insurance Agent",
            "type":"Services"
        }
    ],
    "sg:phone":"+1 559 322 6199",
    "sg:postcode":"93720",
    "sg:province":"CA",
    "wof:name":"Farmers Insurance Group",
    "wof:placetype":"venue"
},
  "geometry": {"coordinates":[-119.754525,36.839285],"type":"Point"}
}