{
  "type": "Feature",
  "properties": {
    "iso:country":"US",
    "sg:address":"11772 Betula Cir",
    "sg:city":"Moreno Valley",
    "sg:classifiers":[
        {
            "category":"Education",
            "subcategory":"School",
            "type":"Public Place"
        }
    ],
    "sg:phone":"+1 951 369 7202",
    "sg:postcode":"92557",
    "sg:province":"CA",
    "sg:tags":[
        "theatrical"
    ],
    "wof:name":"Bilingual Ctr For Prfrmg Arts",
    "wof:placetype":"venue"
},
  "geometry": {"coordinates":[-117.296037,33.949148],"type":"Point"}
}