{
  "type": "Feature",
  "properties": {
    "addr:full":"2450 Lozana Rd Del Mar CA 92014",
    "addr:housenumber":"2450",
    "addr:postcode":"92014",
    "addr:street":"Lozana Rd",
    "iso:country":"US",
    "sg:address":"2450 Lozana Rd",
    "sg:city":"Del Mar",
    "sg:classifiers":[
        {
            "category":"Professional",
            "type":"Services"
        }
    ],
    "sg:phone":"+1 858 259 0604",
    "sg:postcode":"92014",
    "sg:province":"CA",
    "wof:name":"Sseb Equities LLC",
    "wof:placetype":"venue"
},
  "geometry": {"coordinates":[-117.24970399999999,32.952898],"type":"Point"}
}