{
  "type": "Feature",
  "properties": {
    "iso:country":"US",
    "sg:address":"12491 San Pablo Ave",
    "sg:city":"Richmond",
    "sg:classifiers":[
        {
            "category":"Home & Garden",
            "subcategory":"Carpets & Floor Coverings",
            "type":"Retail Goods"
        }
    ],
    "sg:phone":"+1 510 233 9097",
    "sg:postcode":"94805",
    "sg:province":"CA",
    "sg:tags":[
        "mattress"
    ],
    "sg:website":"www.americasbestsleep.com",
    "wof:name":"Odds & Ends Water Beds",
    "wof:placetype":"venue"
},
  "geometry": {"coordinates":[-122.327003,37.939602],"type":"Point"}
}