{
  "type": "Feature",
  "properties": {
    "addr:full":"8026 Wentworth St Sunland CA 91040",
    "addr:housenumber":"8026",
    "addr:postcode":"91040",
    "addr:street":"Wentworth St",
    "iso:country":"US",
    "sg:address":"8026 Wentworth St",
    "sg:city":"Sunland",
    "sg:classifiers":[
        {
            "category":"Professional",
            "subcategory":"Computer Services",
            "type":"Services"
        }
    ],
    "sg:phone":"+1 818 352 1168",
    "sg:postcode":"91040",
    "sg:province":"CA",
    "sg:tags":[
        "datum"
    ],
    "wof:name":"Panoramic Web",
    "wof:placetype":"venue"
},
  "geometry": {"coordinates":[-118.307709,34.266872],"type":"Point"}
}