{
  "type": "Feature",
  "properties": {
    "iso:country":"US",
    "sg:address":"22425 Ventura Blvd",
    "sg:city":"Woodland Hills",
    "sg:classifiers":[
        {
            "category":"Professional",
            "subcategory":"Computer Services",
            "type":"Services"
        }
    ],
    "sg:phone":"+1 818 703 7187",
    "sg:postcode":"91364",
    "sg:province":"CA",
    "sg:tags":[
        "consultant",
        "designer"
    ],
    "sg:website":"www.firm-solutions.com",
    "wof:name":"Firm Solutions",
    "wof:placetype":"venue"
},
  "geometry": {"coordinates":[-118.616663,34.168211],"type":"Point"}
}