{
  "type": "Feature",
  "properties": {
    "addr:full":"19131 Dyer Ct Groveland CA 95321",
    "addr:housenumber":"19131",
    "addr:postcode":"95321",
    "addr:street":"Dyer Ct",
    "iso:country":"US",
    "sg:address":"19131 Dyer Ct",
    "sg:city":"Groveland",
    "sg:classifiers":[
        {
            "category":"Transit Center",
            "subcategory":"Freight",
            "type":"Transportation"
        },
        {
            "category":"Freight",
            "type":"Transportation"
        }
    ],
    "sg:phone":"+1 209 479 6801",
    "sg:postcode":"95321",
    "sg:province":"CA",
    "sg:tags":[
        "local",
        "trucking-motor",
        "trucking"
    ],
    "wof:name":"Bolter Trucking",
    "wof:placetype":"venue"
},
  "geometry": {"coordinates":[-120.221754,37.852785],"type":"Point"}
}