{
  "type": "Feature",
  "properties": {
    "iso:country":"US",
    "sg:address":"12 W Market St",
    "sg:city":"Long Beach",
    "sg:classifiers":[
        {
            "category":"Food & Beverages",
            "subcategory":"Groceries & Convenience Stores",
            "type":"Retail Goods"
        }
    ],
    "sg:phone":"+1 562 423 4238",
    "sg:postcode":"90805",
    "sg:province":"CA",
    "sg:tags":[
        "product"
    ],
    "wof:name":"Happy Babies World",
    "wof:placetype":"venue"
},
  "geometry": {"coordinates":[-118.198308,33.854188],"type":"Point"}
}