{
  "type": "Feature",
  "properties": {
    "iso:country":"US",
    "sg:address":"6515 Oakhurst Cir",
    "sg:city":"Huntington Beach",
    "sg:classifiers":[
        {
            "category":"Building & Trades",
            "subcategory":"Landscaping Services",
            "type":"Services"
        }
    ],
    "sg:phone":"+1 714 585 2636",
    "sg:postcode":"92648",
    "sg:province":"CA",
    "wof:name":"Estate Putting Greens",
    "wof:placetype":"venue"
},
  "geometry": {"coordinates":[-118.014109,33.683371],"type":"Point"}
}