{
  "type": "Feature",
  "properties": {
    "iso:country":"US",
    "sg:address":"406 Andrew Ave",
    "sg:city":"Encinitas",
    "sg:classifiers":[
        {
            "category":"Wholesale",
            "subcategory":"Durable Goods & Equipment",
            "type":"Manufacturing & Wholesale Goods"
        }
    ],
    "sg:phone":"+1 760 942 4929",
    "sg:postcode":"92024",
    "sg:province":"CA",
    "sg:tags":[
        "importer"
    ],
    "wof:name":"Blaze International Inc",
    "wof:placetype":"venue"
},
  "geometry": {"coordinates":[-117.301537,33.081979],"type":"Point"}
}