{
  "type": "Feature",
  "properties": {
    "addr:full":"1064 Woodland Ave Modesto CA 95351",
    "addr:housenumber":"1064",
    "addr:postcode":"ca 95351",
    "addr:street":"Woodland Ave",
    "iso:country":"US",
    "sg:address":"1064 Woodland Ave",
    "sg:city":"Modesto",
    "sg:classifiers":[
        {
            "category":"Manufacturing",
            "subcategory":"Tools & Machinery",
            "type":"Manufacturing & Wholesale Goods"
        }
    ],
    "sg:phone":"+1 209 577 3958",
    "sg:postcode":"95351",
    "sg:province":"CA",
    "sg:tags":[
        "mfg"
    ],
    "wof:name":"Dans Machine Shop",
    "wof:placetype":"venue"
},
  "geometry": {"coordinates":[-121.023555,37.653125],"type":"Point"}
}