{
  "type": "Feature",
  "properties": {
    "iso:country":"US",
    "sg:address":"32360 N Harbor Dr",
    "sg:city":"Fort Bragg",
    "sg:classifiers":[
        {
            "category":"Wholesale",
            "subcategory":"Sporting Goods",
            "type":"Manufacturing & Wholesale Goods"
        }
    ],
    "sg:phone":"+1 707 964 2234",
    "sg:postcode":"95437",
    "sg:province":"CA",
    "wof:name":"Westfall Commercial Marine",
    "wof:placetype":"venue"
},
  "geometry": {"coordinates":[-123.803791,39.427404],"type":"Point"}
}