{
  "type": "Feature",
  "properties": {
    "iso:country":"US",
    "sg:address":"2982 Arthur Ct",
    "sg:city":"Hayward",
    "sg:classifiers":[
        {
            "category":"Professional",
            "type":"Services"
        }
    ],
    "sg:phone":"+1 510 247 8885",
    "sg:postcode":"94541",
    "sg:province":"CA",
    "wof:name":"Nasla Inc",
    "wof:placetype":"venue"
},
  "geometry": {"coordinates":[-122.050135,37.670233],"type":"Point"}
}