{
  "type": "Feature",
  "properties": {
    "addr:full":"6325 Sierra Ct Dublin CA 94568",
    "addr:housenumber":"6325",
    "addr:postcode":"94568",
    "addr:street":"Sierra Ct",
    "iso:country":"US",
    "sg:address":"6325 Sierra Ct",
    "sg:city":"Dublin",
    "sg:classifiers":[
        {
            "category":"Education",
            "subcategory":"Special Training",
            "type":"Public Place"
        }
    ],
    "sg:phone":"+1 925 460 3775",
    "sg:postcode":"94568",
    "sg:province":"CA",
    "sg:tags":[
        "tutoring"
    ],
    "wof:name":"Resources For Education",
    "wof:placetype":"venue"
},
  "geometry": {"coordinates":[-121.915907,37.704807],"type":"Point"}
}