{
  "type": "Feature",
  "properties": {
    "iso:country":"US",
    "sg:address":"2094 Palermo Rd",
    "sg:city":"Palermo",
    "sg:classifiers":[
        {
            "category":"Social Services",
            "type":"Services"
        }
    ],
    "sg:phone":"+1 530 534 6565",
    "sg:postcode":"95968",
    "sg:province":"CA",
    "sg:tags":[
        "organization",
        "welfare"
    ],
    "wof:name":"Palermo Community Council",
    "wof:placetype":"venue"
},
  "geometry": {"coordinates":[-121.549172,39.435301],"type":"Point"}
}