{
  "type": "Feature",
  "properties": {
    "iso:country":"US",
    "sg:address":"6001 S Maywood Ave",
    "sg:city":"Huntington Park",
    "sg:classifiers":[
        {
            "category":"Professional",
            "type":"Services"
        }
    ],
    "sg:phone":"+1 323 582 4250",
    "sg:postcode":"90255",
    "sg:province":"CA",
    "sg:tags":[
        "establishment"
    ],
    "wof:name":"Morales Interprises",
    "wof:placetype":"venue"
},
  "geometry": {"coordinates":[-118.20260399999999,33.986136],"type":"Point"}
}