{
  "type": "Feature",
  "properties": {
    "addr:full":"7134 Amigo Ave Reseda CA 91335",
    "addr:housenumber":"7134",
    "addr:postcode":"91335",
    "addr:street":"Amigo Ave",
    "iso:country":"US",
    "sg:address":"7134 Amigo Ave",
    "sg:city":"Reseda",
    "sg:classifiers":[
        {
            "category":"Shopping",
            "subcategory":"Clothing, Apparel, & Fashions",
            "type":"Retail Goods"
        }
    ],
    "sg:phone":"+1 818 996 9927",
    "sg:postcode":"91335",
    "sg:province":"CA",
    "sg:tags":[
        "scarf"
    ],
    "wof:name":"Delta Creaciones",
    "wof:placetype":"venue"
},
  "geometry": {"coordinates":[-118.538518,34.200447],"type":"Point"}
}