{
  "type": "Feature",
  "properties": {
    "iso:country":"US",
    "sg:address":"1139 Calimesa Blvd",
    "sg:city":"Calimesa",
    "sg:classifiers":[
        {
            "category":"Banks & Credit Unions",
            "subcategory":"Bank",
            "type":"Services"
        },
        {
            "category":"Banks & Credit Unions",
            "subcategory":"Financial Services",
            "type":"Services"
        }
    ],
    "sg:phone":"+1 866 248 4937",
    "sg:postcode":"92320",
    "sg:province":"CA",
    "sg:tags":[
        "saving",
        "mortgage",
        "loan",
        "commercial",
        "card"
    ],
    "sg:website":"http://www.citibank.com",
    "wof:name":"Citibank",
    "wof:placetype":"venue"
},
  "geometry": {"coordinates":[-117.058306,33.995707],"type":"Point"}
}