{
  "type": "Feature",
  "properties": {
    "iso:country":"US",
    "sg:address":"111 W Evelyn Ave",
    "sg:city":"Sunnyvale",
    "sg:classifiers":[
        {
            "category":"Professional",
            "subcategory":"Lawyer & Legal Services",
            "type":"Services"
        }
    ],
    "sg:phone":"+1 408 720 7007",
    "sg:postcode":"94086",
    "sg:province":"CA",
    "sg:tags":[
        "attorney"
    ],
    "wof:name":"Wayne Silver Law Office",
    "wof:placetype":"venue"
},
  "geometry": {"coordinates":[-122.030776,37.377973],"type":"Point"}
}