{
  "type": "Feature",
  "properties": {
    "iso:country":"US",
    "sg:address":"731 Chester Ave",
    "sg:city":"Bakersfield",
    "sg:classifiers":[
        {
            "category":"Travel",
            "subcategory":"Travel Agent",
            "type":"Entertainment"
        }
    ],
    "sg:phone":"+1 661 336 0291",
    "sg:postcode":"93301",
    "sg:province":"CA",
    "sg:tags":[
        "operator",
        "tour"
    ],
    "wof:name":"Karinas Tours",
    "wof:placetype":"venue"
},
  "geometry": {"coordinates":[-119.018878,35.363654],"type":"Point"}
}