{
  "type": "Feature",
  "properties": {
    "addr:full":"1002 E Ave Q Palmdale CA 93550",
    "addr:housenumber":"1002",
    "addr:postcode":"ca 93550",
    "addr:street":"E Ave Q",
    "iso:country":"US",
    "sg:address":"1002 E Ave Q",
    "sg:city":"Palmdale",
    "sg:classifiers":[
        {
            "category":"Social Services",
            "type":"Services"
        }
    ],
    "sg:phone":"+1 661 947 3233",
    "sg:postcode":"93550",
    "sg:province":"CA",
    "sg:tags":[
        "organization",
        "welfare"
    ],
    "wof:name":"A V Committee On Aging Life",
    "wof:placetype":"venue"
},
  "geometry": {"coordinates":[-118.11196700000001,34.587239],"type":"Point"}
}