{
  "type": "Feature",
  "properties": {
    "addr:full":"125 University Ave Palo Alto CA 94301",
    "addr:housenumber":"125",
    "addr:postcode":"94301",
    "addr:street":"University Ave",
    "iso:country":"US",
    "sg:address":"125 University Ave",
    "sg:city":"Palo Alto",
    "sg:classifiers":[
        {
            "category":"Banks & Credit Unions",
            "subcategory":"Financial Services",
            "type":"Services"
        }
    ],
    "sg:phone":"+1 650 462 5800",
    "sg:postcode":"94301",
    "sg:province":"CA",
    "sg:tags":[
        "company",
        "venture",
        "capital"
    ],
    "wof:name":"Skyline Ventures LLC",
    "wof:placetype":"venue"
},
  "geometry": {"coordinates":[-122.16350300000001,37.444018],"type":"Point"}
}