{
  "type": "Feature",
  "properties": {
    "addr:full":"719 S Los Angeles St Ste 807 Suite 524 Los Angeles CA 90014",
    "addr:housenumber":"719",
    "addr:postcode":"90014",
    "addr:street":"S Los Angeles St Ste 807 Suite 524",
    "iso:country":"US",
    "sg:address":"719 S Los Angeles St Ste 807 Suite 524",
    "sg:city":"Los Angeles",
    "sg:classifiers":[
        {
            "category":"Shopping",
            "subcategory":"Clothing, Apparel, & Fashions",
            "type":"Retail Goods"
        }
    ],
    "sg:phone":"+1 213 627 7488",
    "sg:postcode":"90014",
    "sg:province":"CA",
    "sg:tags":[
        "accessory",
        "clothing",
        "women's"
    ],
    "sg:website":"www.coreylynncalter.com",
    "wof:name":"Corey Lynn Calter",
    "wof:placetype":"venue"
},
  "geometry": {"coordinates":[-118.25124099999999,34.043019],"type":"Point"}
}