{
  "type": "Feature",
  "properties": {
    "iso:country":"US",
    "sg:address":"16161 San Fernando Mission Blvd",
    "sg:city":"Granada Hills",
    "sg:classifiers":[
        {
            "category":"Restaurant",
            "type":"Food & Drink"
        }
    ],
    "sg:phone":"+1 818 366 6311",
    "sg:postcode":"91344",
    "sg:province":"CA",
    "wof:name":"Casa De Pizza",
    "wof:placetype":"venue"
},
  "geometry": {"coordinates":[-118.481804,34.271969],"type":"Point"}
}