{
  "type": "Feature",
  "properties": {
    "addr:full":"133 S Eucla Ave San Dimas CA 91773",
    "addr:housenumber":"133",
    "addr:postcode":"91773",
    "addr:street":"S Eucla Ave",
    "iso:country":"US",
    "sg:address":"133 S Eucla Ave",
    "sg:city":"San Dimas",
    "sg:classifiers":[
        {
            "category":"Building & Trades",
            "subcategory":"Construction",
            "type":"Services"
        }
    ],
    "sg:phone":"+1 909 394 4849",
    "sg:postcode":"91773",
    "sg:province":"CA",
    "sg:tags":[
        "glazier"
    ],
    "wof:name":"Marc Anthony Glazing Contr",
    "wof:placetype":"venue"
},
  "geometry": {"coordinates":[-117.815899,34.105013],"type":"Point"}
}