{
  "type": "Feature",
  "properties": {
    "iso:country":"US",
    "sg:address":"40820 Fremont Blvd",
    "sg:city":"Fremont",
    "sg:classifiers":[
        {
            "category":"Food & Beverages",
            "subcategory":"Groceries & Convenience Stores",
            "type":"Retail Goods"
        }
    ],
    "sg:phone":"+1 510 651 5515",
    "sg:postcode":"94538",
    "sg:province":"CA",
    "wof:name":"7-Eleven",
    "wof:placetype":"venue"
},
  "geometry": {"coordinates":[-121.961375,37.534204],"type":"Point"}
}