{
  "type": "Feature",
  "properties": {
    "iso:country":"US",
    "sg:address":"1307 S Main St",
    "sg:city":"Santa Ana",
    "sg:classifiers":[
        {
            "category":"Restaurant",
            "type":"Food & Drink"
        }
    ],
    "sg:phone":"+1 714 543 9033",
    "sg:postcode":"92707",
    "sg:province":"CA",
    "wof:name":"La Perla Restaurant",
    "wof:placetype":"venue"
},
  "geometry": {"coordinates":[-117.86799600000001,33.7313],"type":"Point"}
}