{
  "type": "Feature",
  "properties": {
    "iso:country":"US",
    "sg:address":"24375 Southland Dr",
    "sg:city":"Hayward",
    "sg:classifiers":[
        {
            "category":"Cafe",
            "type":"Food & Drink"
        }
    ],
    "sg:menulink":"http://www.allmenus.com/ca/hayward/63117-camilles-sidewalk-cafe/menu/",
    "sg:phone":"+1 510 783 8801",
    "sg:postcode":"94545",
    "sg:province":"CA",
    "sg:tags":[
        "wrap",
        "american",
        "sandwich"
    ],
    "wof:name":"Camille's Sidewalk Cafe",
    "wof:placetype":"venue"
},
  "geometry": {"coordinates":[-122.10590000000001,37.651919],"type":"Point"}
}