{
  "type": "Feature",
  "properties": {
    "iso:country":"US",
    "sg:address":"945 Taraval St",
    "sg:city":"San Francisco",
    "sg:classifiers":[
        {
            "category":"Professional",
            "subcategory":"Computer Services",
            "type":"Services"
        }
    ],
    "sg:phone":"+1 415 221 8488",
    "sg:postcode":"94116",
    "sg:province":"CA",
    "wof:name":"Infinity Solutions",
    "wof:placetype":"venue"
},
  "geometry": {"coordinates":[-122.476363,37.74295],"type":"Point"}
}