{
  "type": "Feature",
  "properties": {
    "iso:country":"US",
    "sg:address":"2101 Troy Ave",
    "sg:city":"South El Monte",
    "sg:phone":"+1 626 452 1870",
    "sg:postcode":"91733",
    "sg:province":"CA",
    "sg:tags":[
        "food",
        "equipment",
        "processing"
    ],
    "wof:name":"FTR Processing Equipment",
    "wof:placetype":"venue"
},
  "geometry": {"coordinates":[-118.065879,34.05371],"type":"Point"}
}