{
  "type": "Feature",
  "properties": {
    "addr:full":"713 Camellia St Escondido CA 92027",
    "addr:housenumber":"713",
    "addr:postcode":"92027",
    "addr:street":"Camellia St",
    "iso:country":"US",
    "sg:address":"713 Camellia St",
    "sg:city":"Escondido",
    "sg:classifiers":[
        {
            "category":"Insurance",
            "subcategory":"Life Insurance",
            "type":"Services"
        }
    ],
    "sg:phone":"+1 760 480 6057",
    "sg:postcode":"92027",
    "sg:province":"CA",
    "sg:tags":[
        "carrier"
    ],
    "wof:name":"Woodman of World Lf Insur Soc",
    "wof:placetype":"venue"
},
  "geometry": {"coordinates":[-117.058544,33.140659],"type":"Point"}
}