{
  "type": "Feature",
  "properties": {
    "iso:country":"US",
    "sg:address":"1750 San Luis St",
    "sg:city":"Los Banos",
    "sg:classifiers":[
        {
            "category":"Education",
            "subcategory":"School",
            "type":"Public Place"
        }
    ],
    "sg:phone":"+1 209 826 0867",
    "sg:postcode":"93635",
    "sg:province":"CA",
    "wof:name":"Los Banos Junior High School",
    "wof:placetype":"venue"
},
  "geometry": {"coordinates":[-120.828476,37.061795],"type":"Point"}
}