{
  "type": "Feature",
  "properties": {
    "addr:full":"4141 E Olympic Boulevard Los Angeles CA 90023",
    "addr:housenumber":"4141",
    "addr:postcode":"90023",
    "addr:street":"E Olympic Boulevard",
    "iso:country":"US",
    "sg:address":"4141 E Olympic Boulevard",
    "sg:city":"Los Angeles",
    "sg:classifiers":[
        {
            "category":"Retail",
            "subcategory":"Auto Repair",
            "type":"Services"
        }
    ],
    "sg:phone":"+1 323 265 3324",
    "sg:postcode":"90023",
    "sg:province":"CA",
    "wof:name":"Marquez Auto Repair",
    "wof:placetype":"venue"
},
  "geometry": {"coordinates":[-118.18464400000001,34.019009],"type":"Point"}
}