{
  "type": "Feature",
  "properties": {
    "addr:full":"10410 Lower Azusa Rd El Monte CA 91731",
    "addr:housenumber":"10410",
    "addr:postcode":"91731",
    "addr:street":"Lower Azusa Rd",
    "iso:country":"US",
    "sg:address":"10410 Lower Azusa Rd",
    "sg:city":"El Monte",
    "sg:classifiers":[
        {
            "category":"Shopping",
            "subcategory":"Pharmacy",
            "type":"Retail Goods"
        }
    ],
    "sg:phone":"+1 626 448 7659",
    "sg:postcode":"91731",
    "sg:province":"CA",
    "sg:tags":[
        "drugstore"
    ],
    "wof:name":"Midway Drugs",
    "wof:placetype":"venue"
},
  "geometry": {"coordinates":[-118.041,34.0919],"type":"Point"}
}