{
  "type": "Feature",
  "properties": {
    "iso:country":"US",
    "sg:address":"357 E Tulare St",
    "sg:city":"Dinuba",
    "sg:classifiers":[
        {
            "category":"Autos & Motor Vehicles",
            "subcategory":"Fuel & Gas Station",
            "type":"Retail Goods"
        },
        {
            "category":"Food & Beverages",
            "subcategory":"Groceries & Convenience Stores",
            "type":"Retail Goods"
        }
    ],
    "sg:phone":"+1 559 591 1097",
    "sg:postcode":"93618",
    "sg:province":"CA",
    "wof:name":"Beacon",
    "wof:placetype":"venue"
},
  "geometry": {"coordinates":[-119.38763400000001,36.542799],"type":"Point"}
}