{
  "type": "Feature",
  "properties": {
    "addr:full":"19851 Isthmus Ln Huntington Beach CA 92646",
    "addr:housenumber":"19851",
    "addr:postcode":"92646",
    "addr:street":"Isthmus Ln",
    "iso:country":"US",
    "sg:address":"19851 Isthmus Ln",
    "sg:city":"Huntington Beach",
    "sg:classifiers":[
        {
            "category":"Building & Trades",
            "subcategory":"Construction",
            "type":"Services"
        }
    ],
    "sg:phone":"+1 714 717 8304",
    "sg:postcode":"92646",
    "sg:province":"CA",
    "sg:tags":[
        "home",
        "builder"
    ],
    "wof:name":"A J Huntington Home Inc",
    "wof:placetype":"venue"
},
  "geometry": {"coordinates":[-117.974433,33.675427],"type":"Point"}
}