{
  "type": "Feature",
  "properties": {
    "addr:full":"85 Conejo Dr Millbrae CA 94030",
    "addr:housenumber":"85",
    "addr:postcode":"94030",
    "addr:street":"Conejo Dr",
    "iso:country":"US",
    "sg:address":"85 Conejo Dr",
    "sg:city":"Millbrae",
    "sg:classifiers":[
        {
            "category":"Professional",
            "type":"Services"
        }
    ],
    "sg:phone":"+1 650 652 4626",
    "sg:postcode":"94030",
    "sg:province":"CA",
    "wof:name":"Tree Green Corp",
    "wof:placetype":"venue"
},
  "geometry": {"coordinates":[-122.40219,37.586733],"type":"Point"}
}