{
  "type": "Feature",
  "properties": {
    "addr:full":"910 University Ave Sacramento CA 95825",
    "addr:housenumber":"910",
    "addr:postcode":"95825",
    "addr:street":"University Ave",
    "iso:country":"US",
    "sg:address":"910 University Ave",
    "sg:city":"Sacramento",
    "sg:phone":"+1 916 565 1281",
    "sg:postcode":"95825",
    "sg:province":"CA",
    "wof:name":"Cobblestone Cafe",
    "wof:placetype":"venue"
},
  "geometry": {"coordinates":[-121.417312,38.562835],"type":"Point"}
}