{
  "type": "Feature",
  "properties": {
    "addr:full":"4377 Adeline St Emeryville CA 94608",
    "addr:housenumber":"4377",
    "addr:postcode":"94608",
    "addr:street":"Adeline St",
    "iso:country":"US",
    "sg:address":"4377 Adeline St",
    "sg:city":"Emeryville",
    "sg:classifiers":[
        {
            "category":"Wholesale",
            "subcategory":"Electrical",
            "type":"Manufacturing & Wholesale Goods"
        }
    ],
    "sg:phone":"+1 510 597 9966",
    "sg:postcode":"94608",
    "sg:province":"CA",
    "sg:tags":[
        "fire",
        "medical",
        "alarm",
        "system"
    ],
    "sg:website":"http://www.intrepidelectronics.com",
    "wof:name":"Intrepid Electronic Systems Inc.",
    "wof:placetype":"venue"
},
  "geometry": {"coordinates":[-122.276824,37.835009],"type":"Point"}
}