{
  "type": "Feature",
  "properties": {
    "addr:full":"37 Hillside Dr Applegate CA 95703",
    "addr:housenumber":"37",
    "addr:postcode":"95703",
    "addr:street":"Hillside Dr Applegate",
    "iso:country":"US",
    "sg:address":"37 Hillside Dr",
    "sg:city":"Applegate",
    "sg:classifiers":[
        {
            "category":"Building & Trades",
            "subcategory":"Construction",
            "type":"Services"
        }
    ],
    "sg:phone":"+1 530 878 8573",
    "sg:postcode":"95703",
    "sg:province":"CA",
    "sg:tags":[
        "concrete",
        "contractor"
    ],
    "wof:name":"A Ecco Inc",
    "wof:placetype":"venue"
},
  "geometry": {"coordinates":[-121.00645400000001,38.98682],"type":"Point"}
}