{
  "type": "Feature",
  "properties": {
    "iso:country":"US",
    "sg:address":"3767 S Golden State Blvd",
    "sg:city":"Fresno",
    "sg:classifiers":[
        {
            "category":"Retail",
            "subcategory":"Car Wash",
            "type":"Services"
        }
    ],
    "sg:phone":"+1 559 237 9274",
    "sg:postcode":"93725",
    "sg:province":"CA",
    "sg:tags":[
        "truck",
        "cleaning"
    ],
    "wof:name":"G & S Truck Wash",
    "wof:placetype":"venue"
},
  "geometry": {"coordinates":[-119.74126800000001,36.684505],"type":"Point"}
}