{
  "type": "Feature",
  "properties": {
    "addr:full":"22 N Jackson Ave San Jose CA 95116",
    "addr:housenumber":"22",
    "addr:postcode":"95116",
    "addr:street":"N Jackson Ave",
    "iso:country":"US",
    "sg:address":"22 N Jackson Ave",
    "sg:city":"San Jose",
    "sg:classifiers":[
        {
            "category":"Restaurant",
            "type":"Food & Drink"
        }
    ],
    "sg:phone":"+1 408 729 4373",
    "sg:postcode":"95116",
    "sg:province":"CA",
    "sg:tags":[
        "chinese"
    ],
    "wof:name":"Chef P's Restaurant",
    "wof:placetype":"venue"
},
  "geometry": {"coordinates":[-121.84406,37.359071],"type":"Point"}
}