{
  "type": "Feature",
  "properties": {
    "iso:country":"US",
    "sg:address":"19752 Sherman Way",
    "sg:city":"Canoga Park",
    "sg:classifiers":[
        {
            "category":"Retail",
            "subcategory":"Laundry & Dry Cleaning",
            "type":"Services"
        }
    ],
    "sg:phone":"+1 818 348 7411",
    "sg:postcode":"91306",
    "sg:province":"CA",
    "wof:name":"Happy Drycleaners",
    "wof:placetype":"venue"
},
  "geometry": {"coordinates":[-118.563428,34.200882],"type":"Point"}
}