{
  "type": "Feature",
  "properties": {
    "iso:country":"US",
    "sg:address":"31929 East St",
    "sg:city":"Raymond",
    "sg:classifiers":[
        {
            "category":"Building & Trades",
            "subcategory":"Construction",
            "type":"Services"
        }
    ],
    "sg:phone":"+1 559 689 3516",
    "sg:postcode":"93653",
    "sg:province":"CA",
    "sg:tags":[
        "contractor"
    ],
    "wof:name":"Rich Scott Construction",
    "wof:placetype":"venue"
},
  "geometry": {"coordinates":[-119.904889,37.214865],"type":"Point"}
}