{
  "type": "Feature",
  "properties": {
    "addr:full":"7840 Walerga Rd Antelope CA 95843",
    "addr:housenumber":"7840",
    "addr:postcode":"95843",
    "addr:street":"Walerga Rd",
    "iso:country":"US",
    "sg:address":"7840 Walerga Rd",
    "sg:city":"Antelope",
    "sg:classifiers":[
        {
            "category":"Real Estate",
            "subcategory":"Real Estate Operator",
            "type":"Services"
        }
    ],
    "sg:phone":"+1 916 725 7385",
    "sg:postcode":"95843",
    "sg:province":"CA",
    "sg:tags":[
        "apartment"
    ],
    "wof:name":"Danbury Park",
    "wof:placetype":"venue"
},
  "geometry": {"coordinates":[-121.36438200000001,38.71311],"type":"Point"}
}