{
  "type": "Feature",
  "properties": {
    "addr:full":"248 S Mills Rd Ventura CA 93003",
    "addr:housenumber":"248",
    "addr:postcode":"93003",
    "addr:street":"S Mills Rd",
    "iso:country":"US",
    "sg:address":"248 S Mills Rd",
    "sg:city":"Ventura",
    "sg:classifiers":[
        {
            "category":"Real Estate",
            "subcategory":"Real Estate Agent",
            "type":"Services"
        }
    ],
    "sg:phone":"+1 805 644 1892",
    "sg:postcode":"93003",
    "sg:province":"CA",
    "sg:tags":[
        "consultant"
    ],
    "wof:name":"HDR/Lca & Sargent",
    "wof:placetype":"venue"
},
  "geometry": {"coordinates":[-119.246965,34.26998],"type":"Point"}
}