{
  "type": "Feature",
  "properties": {
    "addr:full":"1001 G St Ste 100 Sacramento CA 95814",
    "addr:housenumber":"1001",
    "addr:postcode":"95814",
    "addr:street":"G St Ste 100",
    "iso:country":"US",
    "sg:address":"1001 G St Ste 100",
    "sg:city":"Sacramento",
    "sg:classifiers":[
        {
            "category":"Insurance",
            "subcategory":"Title Insurance",
            "type":"Services"
        }
    ],
    "sg:phone":"+1 916 442 4901",
    "sg:postcode":"95814",
    "sg:province":"CA",
    "sg:website":"http://www.permitsetc.com",
    "wof:name":"Greenpro Services, Inc.",
    "wof:placetype":"venue"
},
  "geometry": {"coordinates":[-121.49202699999999,38.58358],"type":"Point"}
}