{
  "type": "Feature",
  "properties": {
    "iso:country":"US",
    "sg:address":"12100 Wilshire Blvd",
    "sg:city":"Los Angeles",
    "sg:classifiers":[
        {
            "category":"Building & Trades",
            "subcategory":"Cleaning & Sanitation",
            "type":"Services"
        }
    ],
    "sg:phone":"+1 310 826 2221",
    "sg:postcode":"90025",
    "sg:province":"CA",
    "sg:tags":[
        "sales",
        "real estate"
    ],
    "wof:name":"Katz Property Services",
    "wof:placetype":"venue"
},
  "geometry": {"coordinates":[-118.46831,34.043422],"type":"Point"}
}