{
  "type": "Feature",
  "properties": {
    "addr:full":"23052 Sonoita Mission Viejo CA 92691",
    "addr:housenumber":"23052",
    "addr:postcode":"92691",
    "addr:street":"Sonoita",
    "iso:country":"US",
    "sg:address":"23052 Sonoita",
    "sg:city":"Mission Viejo",
    "sg:classifiers":[
        {
            "category":"Professional",
            "type":"Services"
        }
    ],
    "sg:phone":"+1 949 462 0340",
    "sg:postcode":"92691",
    "sg:province":"CA",
    "wof:name":"Pure H2o Systems",
    "wof:placetype":"venue"
},
  "geometry": {"coordinates":[-117.655457,33.627474],"type":"Point"}
}