{
  "type": "Feature",
  "properties": {
    "iso:country":"US",
    "sg:address":"2222 Shasta Way",
    "sg:city":"Simi Valley",
    "sg:classifiers":[
        {
            "category":"Manufacturing",
            "subcategory":"Tools & Machinery",
            "type":"Manufacturing & Wholesale Goods"
        }
    ],
    "sg:phone":"+1 805 583 8961",
    "sg:postcode":"93065",
    "sg:province":"CA",
    "sg:tags":[
        "manufacture",
        "industrial",
        "other",
        "general"
    ],
    "wof:name":"Assembly and Mfg Systems",
    "wof:placetype":"venue"
},
  "geometry": {"coordinates":[-118.788594,34.275966],"type":"Point"}
}