{
  "type": "Feature",
  "properties": {
    "addr:full":"2121 N San Fernando Rd Los Angeles CA 90065",
    "addr:housenumber":"2121",
    "addr:postcode":"90065",
    "addr:street":"N San Fernando Rd",
    "iso:country":"US",
    "sg:address":"2121 N San Fernando Rd",
    "sg:city":"Los Angeles",
    "sg:classifiers":[
        {
            "category":"Shopping",
            "subcategory":"Jewelry",
            "type":"Retail Goods"
        }
    ],
    "sg:phone":"+1 323 343 0130",
    "sg:postcode":"90065",
    "sg:province":"CA",
    "sg:tags":[
        "designer"
    ],
    "wof:name":"B-Tang",
    "wof:placetype":"venue"
},
  "geometry": {"coordinates":[-118.237388,34.103139],"type":"Point"}
}