{
  "type": "Feature",
  "properties": {
    "addr:full":"1827 Walnut Grove Blvd Rosemead CA 91770",
    "addr:housenumber":"1827",
    "addr:postcode":"91770",
    "addr:street":"Walnut Grove Blvd",
    "iso:country":"US",
    "sg:address":"1827 Walnut Grove Blvd",
    "sg:city":"Rosemead",
    "sg:classifiers":[
        {
            "category":"Shopping",
            "subcategory":"Department Store",
            "type":"Retail Goods"
        },
        {
            "category":"Shopping",
            "subcategory":"Mobile Phones",
            "type":"Retail Goods"
        },
        {
            "category":"Food & Beverages",
            "subcategory":"Groceries & Convenience Stores",
            "type":"Retail Goods"
        }
    ],
    "sg:phone":"+1 626 307 1010",
    "sg:postcode":"91770",
    "sg:province":"CA",
    "sg:website":"www.walmart.com",
    "wof:name":"Walmart",
    "wof:placetype":"venue"
},
  "geometry": {"coordinates":[-118.08427399999999,34.050333],"type":"Point"}
}