{
  "type": "Feature",
  "properties": {
    "addr:full":"480 Meta St Oxnard CA 93030",
    "addr:housenumber":"480",
    "addr:postcode":"93030",
    "addr:street":"Meta St",
    "iso:country":"US",
    "sg:address":"480 Meta St",
    "sg:city":"Oxnard",
    "sg:classifiers":[
        {
            "category":"Shopping",
            "subcategory":"Clothing, Apparel, & Fashions",
            "type":"Retail Goods"
        }
    ],
    "sg:phone":"+1 805 483 5919",
    "sg:postcode":"93030",
    "sg:province":"CA",
    "sg:tags":[
        "furnishing"
    ],
    "wof:name":"Mike's General Merchandise",
    "wof:placetype":"venue"
},
  "geometry": {"coordinates":[-119.17587899999999,34.197889],"type":"Point"}
}