{
  "type": "Feature",
  "properties": {
    "iso:country":"US",
    "sg:address":"10 Coach Rd",
    "sg:city":"Escondido",
    "sg:classifiers":[
        {
            "category":"Organizations",
            "subcategory":"Non-profit Organization",
            "type":"Services"
        }
    ],
    "sg:phone":"+1 760 740 8759",
    "sg:postcode":"92025",
    "sg:province":"CA",
    "sg:tags":[
        "fund",
        "counselor",
        "raising"
    ],
    "wof:name":"Pathway Lutheran Ministries",
    "wof:placetype":"venue"
},
  "geometry": {"coordinates":[-117.047664,33.063912],"type":"Point"}
}