{
  "type": "Feature",
  "properties": {
    "addr:full":"1442 Cameo Dr Del Mar CA 92026",
    "addr:housenumber":"1442",
    "addr:postcode":"92026",
    "addr:street":"Cameo Dr",
    "iso:country":"US",
    "sg:address":"1442 Cameo Dr",
    "sg:city":"Del Mar",
    "sg:classifiers":[
        {
            "category":"Travel",
            "subcategory":"Travel Agent",
            "type":"Entertainment"
        }
    ],
    "sg:phone":"+1 858 755 5421",
    "sg:postcode":"92026",
    "sg:province":"CA",
    "sg:tags":[
        "agency",
        "bureau"
    ],
    "wof:name":"Aventura Artistica",
    "wof:placetype":"venue"
},
  "geometry": {"coordinates":[-117.086113,33.144895],"type":"Point"}
}