{
  "type": "Feature",
  "properties": {
    "iso:country":"US",
    "sg:address":"9647 Santa Monica Boulevard",
    "sg:city":"Beverly Hills",
    "sg:classifiers":[
        {
            "category":"Shopping",
            "subcategory":"Clothing, Apparel, & Fashions",
            "type":"Retail Goods"
        }
    ],
    "sg:phone":"+1 310 276 7510",
    "sg:postcode":"90210",
    "sg:province":"CA",
    "sg:tags":[
        "accessory",
        "clothing",
        "women's"
    ],
    "sg:website":"www.susannabeverlyhills.com",
    "wof:name":"Susanna Beverly Hills",
    "wof:placetype":"venue"
},
  "geometry": {"coordinates":[-118.40648,34.069645],"type":"Point"}
}