{
  "type": "Feature",
  "properties": {
    "addr:full":"1242 Poplar Dr El Centro CA 92243",
    "addr:housenumber":"1242",
    "addr:postcode":"92243",
    "addr:street":"Poplar Dr",
    "iso:country":"US",
    "sg:address":"1242 Poplar Dr",
    "sg:city":"El Centro",
    "sg:classifiers":[
        {
            "category":"Social Services",
            "subcategory":"Child Care",
            "type":"Services"
        }
    ],
    "sg:phone":"+1 760 339 9921",
    "sg:postcode":"92243",
    "sg:province":"CA",
    "sg:tags":[
        "kindergarten",
        "academic",
        "school"
    ],
    "wof:name":"Precious Little Ones",
    "wof:placetype":"venue"
},
  "geometry": {"coordinates":[-115.56637499999999,32.780541],"type":"Point"}
}