{
  "type": "Feature",
  "properties": {
    "iso:country":"US",
    "sg:address":"800 W Katella Ave",
    "sg:city":"Anaheim",
    "sg:classifiers":[
        {
            "category":"Utilities",
            "subcategory":"Telephone",
            "type":"Services"
        }
    ],
    "sg:phone":"+1 714 765 8600",
    "sg:postcode":"92802",
    "sg:province":"CA",
    "sg:tags":[
        "communications"
    ],
    "wof:name":"Smart City",
    "wof:placetype":"venue"
},
  "geometry": {"coordinates":[-117.918092,33.803242],"type":"Point"}
}