{
  "type": "Feature",
  "properties": {
    "addr:full":"7323 Mica St El Dorado CA 95623",
    "addr:housenumber":"7323",
    "addr:postcode":"95623",
    "addr:street":"Mica St",
    "iso:country":"US",
    "sg:address":"7323 Mica St",
    "sg:city":"El Dorado",
    "sg:classifiers":[
        {
            "category":"Professional",
            "subcategory":"Computer Services",
            "type":"Services"
        }
    ],
    "sg:phone":"+1 530 620 9161",
    "sg:postcode":"95623",
    "sg:province":"CA",
    "sg:tags":[
        "communications",
        "datum",
        "system"
    ],
    "wof:name":"Terralink Communications Inc",
    "wof:placetype":"venue"
},
  "geometry": {"coordinates":[-120.856921,38.590455],"type":"Point"}
}