{
  "type": "Feature",
  "properties": {
    "addr:full":"12767 Ave 416 Orosi CA 93647",
    "addr:housenumber":"12767",
    "addr:postcode":"93647",
    "addr:street":"Ave 416",
    "iso:country":"US",
    "sg:address":"12767 Ave 416",
    "sg:city":"Orosi",
    "sg:classifiers":[
        {
            "category":"Banks & Credit Unions",
            "subcategory":"Bank",
            "type":"Services"
        }
    ],
    "sg:phone":"+1 559 528 6130",
    "sg:postcode":"93647",
    "sg:province":"CA",
    "sg:tags":[
        "money",
        "transfer"
    ],
    "wof:name":"Dolex Dollar Express",
    "wof:placetype":"venue"
},
  "geometry": {"coordinates":[-119.287735,36.544741],"type":"Point"}
}