{
  "type": "Feature",
  "properties": {
    "iso:country":"US",
    "sg:address":"921 The Alameda",
    "sg:city":"Berkeley",
    "sg:classifiers":[
        {
            "category":"Health Services",
            "subcategory":"Doctor",
            "type":"Services"
        }
    ],
    "sg:phone":"+1 510 527 4825",
    "sg:postcode":"94707",
    "sg:province":"CA",
    "sg:tags":[
        "physician",
        "surgeon"
    ],
    "wof:name":"Ronald Spinka Inc",
    "wof:placetype":"venue"
},
  "geometry": {"coordinates":[-122.276965,37.891149],"type":"Point"}
}