{
  "type": "Feature",
  "properties": {
    "iso:country":"US",
    "sg:address":"824 Munras Ave",
    "sg:city":"Monterey",
    "sg:classifiers":[
        {
            "category":"Travel",
            "subcategory":"Travel Agent",
            "type":"Entertainment"
        }
    ],
    "sg:phone":"+1 831 373 0508",
    "sg:postcode":"93940",
    "sg:province":"CA",
    "sg:tags":[
        "destination",
        "management"
    ],
    "wof:name":"Destination Monterey Carmel",
    "wof:placetype":"venue"
},
  "geometry": {"coordinates":[-121.893432,36.594212],"type":"Point"}
}