{
  "type": "Feature",
  "properties": {
    "addr:full":"1652 W Century Blvd Los Angeles CA 90047",
    "addr:housenumber":"1652",
    "addr:postcode":"90047",
    "addr:street":"W Century Blvd",
    "iso:country":"US",
    "sg:address":"1652 W Century Blvd",
    "sg:city":"Los Angeles",
    "sg:classifiers":[
        {
            "category":"Social Services",
            "subcategory":"Child Care",
            "type":"Services"
        }
    ],
    "sg:phone":"+1 323 418 0155",
    "sg:postcode":"90047",
    "sg:province":"CA",
    "sg:tags":[
        "kindergarten",
        "academic",
        "school"
    ],
    "wof:name":"Ruby's Christian Academy",
    "wof:placetype":"venue"
},
  "geometry": {"coordinates":[-118.30676,33.945387],"type":"Point"}
}