{
  "type": "Feature",
  "properties": {
    "iso:country":"US",
    "sg:address":"7446 Rosanna St",
    "sg:city":"Gilroy",
    "sg:classifiers":[
        {
            "category":"Travel",
            "subcategory":"Hotels & Motels",
            "type":"Entertainment"
        },
        {
            "category":"Travel",
            "subcategory":"Bed & Breakfast",
            "type":"Entertainment"
        }
    ],
    "sg:phone":"+1 408 847 6421",
    "sg:postcode":"95020",
    "sg:province":"CA",
    "sg:tags":[
        "inn",
        "lodging"
    ],
    "wof:name":"Gilroy Fitzgerald House",
    "wof:placetype":"venue"
},
  "geometry": {"coordinates":[-121.57263,37.006471],"type":"Point"}
}