{
  "type": "Feature",
  "properties": {
    "iso:country":"US",
    "sg:address":"1234 E Shaw Ave",
    "sg:city":"Fresno",
    "sg:classifiers":[
        {
            "category":"Government",
            "subcategory":"Office",
            "type":"Public Place"
        }
    ],
    "sg:phone":"+1 559 243 4005",
    "sg:postcode":"93710",
    "sg:province":"CA",
    "sg:tags":[
        "management",
        "wildlife",
        "conservation",
        "resource",
        "agency"
    ],
    "wof:name":"San Joaquin Valley 4",
    "wof:placetype":"venue"
},
  "geometry": {"coordinates":[-119.77208,36.808628],"type":"Point"}
}