{
  "type": "Feature",
  "properties": {
    "iso:country":"US",
    "sg:address":"15335 E 14th St",
    "sg:city":"San Leandro",
    "sg:classifiers":[
        {
            "category":"Retail",
            "subcategory":"Repair Shop",
            "type":"Services"
        }
    ],
    "sg:phone":"+1 510 278 9226",
    "sg:postcode":"94578",
    "sg:province":"CA",
    "sg:tags":[
        "vacuum"
    ],
    "wof:name":"Vacuum City",
    "wof:placetype":"venue"
},
  "geometry": {"coordinates":[-122.126155,37.703581],"type":"Point"}
}