{
  "type": "Feature",
  "properties": {
    "iso:country":"US",
    "sg:address":"8560 Walnut Dr",
    "sg:city":"Los Angeles",
    "sg:classifiers":[
        {
            "category":"Shopping",
            "subcategory":"Hobbies, Toys, & Games",
            "type":"Retail Goods"
        }
    ],
    "sg:phone":"+1 323 653 6703",
    "sg:postcode":"90046",
    "sg:province":"CA",
    "sg:tags":[
        "box",
        "music"
    ],
    "wof:name":"Wound & Wound Toy Co",
    "wof:placetype":"venue"
},
  "geometry": {"coordinates":[-118.378142,34.104458],"type":"Point"}
}