{
  "type": "Feature",
  "properties": {
    "addr:full":"1254 Main St Newman CA 95360",
    "addr:housenumber":"1254",
    "addr:postcode":"95360",
    "addr:street":"Main St",
    "iso:country":"US",
    "sg:address":"1254 Main St",
    "sg:city":"Newman",
    "sg:classifiers":[
        {
            "category":"Personal",
            "subcategory":"Beauty Salon",
            "type":"Services"
        }
    ],
    "sg:phone":"+1 209 862 4061",
    "sg:postcode":"95360",
    "sg:province":"CA",
    "wof:name":"Unique By Design",
    "wof:placetype":"venue"
},
  "geometry": {"coordinates":[-121.023015,37.316609],"type":"Point"}
}