{
  "type": "Feature",
  "properties": {
    "addr:full":"1544 S Crenshaw St Visalia CA 93277",
    "addr:housenumber":"1544",
    "addr:postcode":"93277",
    "addr:street":"S Crenshaw St",
    "iso:country":"US",
    "sg:address":"1544 S Crenshaw St",
    "sg:city":"Visalia",
    "sg:classifiers":[
        {
            "category":"Wholesale",
            "subcategory":"Vending Machines",
            "type":"Manufacturing & Wholesale Goods"
        }
    ],
    "sg:phone":"+1 559 734 7312",
    "sg:postcode":"93277",
    "sg:province":"CA",
    "wof:name":"Munch Time Vending",
    "wof:placetype":"venue"
},
  "geometry": {"coordinates":[-119.343999,36.315585],"type":"Point"}
}