{
  "type": "Feature",
  "properties": {
    "iso:country":"US",
    "sg:address":"919 Garden Hwy",
    "sg:city":"Yuba City",
    "sg:classifiers":[
        {
            "category":"Retail",
            "subcategory":"Repair Shop",
            "type":"Services"
        }
    ],
    "sg:phone":"+1 530 751 0354",
    "sg:postcode":"95991",
    "sg:province":"CA",
    "sg:tags":[
        "welding"
    ],
    "wof:name":"Hilo Erectors",
    "wof:placetype":"venue"
},
  "geometry": {"coordinates":[-121.617469,39.114384],"type":"Point"}
}