{
  "type": "Feature",
  "properties": {
    "iso:country":"US",
    "sg:address":"650 Capitol Mall",
    "sg:city":"Sacramento",
    "sg:classifiers":[
        {
            "category":"Building & Trades",
            "subcategory":"Cleaning & Sanitation",
            "type":"Services"
        }
    ],
    "sg:phone":"+1 916 447 3978",
    "sg:postcode":"95814",
    "sg:province":"CA",
    "sg:tags":[
        "property",
        "maintenance"
    ],
    "wof:name":"SMI Intl",
    "wof:placetype":"venue"
},
  "geometry": {"coordinates":[-121.49943500000001,38.578153],"type":"Point"}
}