{
  "type": "Feature",
  "properties": {
    "iso:country":"US",
    "sg:address":"335 Genoa St",
    "sg:city":"Monrovia",
    "sg:classifiers":[
        {
            "category":"Manufacturing",
            "subcategory":"Signs",
            "type":"Manufacturing & Wholesale Goods"
        }
    ],
    "sg:phone":"+1 626 357 3590",
    "sg:postcode":"91016",
    "sg:province":"CA",
    "sg:tags":[
        "advertising",
        "specialty"
    ],
    "wof:name":"Waynes Signs",
    "wof:placetype":"venue"
},
  "geometry": {"coordinates":[-118.006512,34.133204],"type":"Point"}
}