{
  "type": "Feature",
  "properties": {
    "addr:full":"13347 South St Cerritos CA 90703",
    "addr:housenumber":"13347",
    "addr:postcode":"ca 90703",
    "addr:street":"South St",
    "iso:country":"US",
    "sg:address":"13347 South St",
    "sg:city":"Cerritos",
    "sg:classifiers":[
        {
            "category":"Restaurant",
            "type":"Food & Drink"
        }
    ],
    "sg:phone":"+1 562 865 4771",
    "sg:postcode":"90703",
    "sg:province":"CA",
    "wof:name":"Korean Noodle",
    "wof:placetype":"venue"
},
  "geometry": {"coordinates":[-118.046885,33.858751],"type":"Point"}
}