{
  "type": "Feature",
  "properties": {
    "addr:full":"2167 Central Ave Alameda CA 94501",
    "addr:housenumber":"2167",
    "addr:postcode":"94501",
    "addr:street":"Central Ave",
    "iso:country":"US",
    "sg:address":"2167 Central Ave",
    "sg:city":"Alameda",
    "sg:classifiers":[
        {
            "category":"Arts & Performance",
            "subcategory":"Theater",
            "type":"Entertainment"
        }
    ],
    "sg:phone":"+1 510 748 8181",
    "sg:postcode":"94501",
    "sg:province":"CA",
    "wof:name":"Adelphian Center For The Arts",
    "wof:placetype":"venue"
},
  "geometry": {"coordinates":[-122.247075,37.766064],"type":"Point"}
}