{
  "type": "Feature",
  "properties": {
    "addr:full":"35191 Birch Rd Barstow CA 92311",
    "addr:housenumber":"35191",
    "addr:postcode":"92311",
    "addr:street":"Birch Rd",
    "iso:country":"US",
    "sg:address":"35191 Birch Rd",
    "sg:city":"Barstow",
    "sg:classifiers":[
        {
            "category":"Building & Trades",
            "subcategory":"Landscaping Services",
            "type":"Services"
        }
    ],
    "sg:phone":"+1 760 253 2784",
    "sg:postcode":"92311",
    "sg:province":"CA",
    "sg:tags":[
        "lawn",
        "maintenance"
    ],
    "wof:name":"Grahams Superior Lawn Service",
    "wof:placetype":"venue"
},
  "geometry": {"coordinates":[-117.10674899999999,34.890923],"type":"Point"}
}