{
  "type": "Feature",
  "properties": {
    "addr:full":"611 W 17th St Santa Ana CA 92706",
    "addr:housenumber":"611",
    "addr:postcode":"92706",
    "addr:street":"W 17Th St",
    "iso:country":"US",
    "sg:address":"611 W 17th St",
    "sg:city":"Santa Ana",
    "sg:classifiers":[
        {
            "category":"Real Estate",
            "subcategory":"Real Estate Services",
            "type":"Services"
        },
        {
            "category":"Real Estate",
            "subcategory":"Real Estate Operator",
            "type":"Services"
        }
    ],
    "sg:phone":"+1 714 836 1968",
    "sg:postcode":"92706",
    "sg:province":"CA",
    "sg:tags":[
        "apartment",
        "property",
        "management"
    ],
    "sg:website":"www.propertymanagementmeridian.com",
    "wof:name":"Meridian Property Management",
    "wof:placetype":"venue"
},
  "geometry": {"coordinates":[-117.87400100000001,33.759998],"type":"Point"}
}