{
  "type": "Feature",
  "properties": {
    "iso:country":"US",
    "sg:address":"4721 E Palm Canyon Dr",
    "sg:city":"Palm Springs",
    "sg:classifiers":[
        {
            "category":"Real Estate",
            "subcategory":"Real Estate Agent",
            "type":"Services"
        }
    ],
    "sg:phone":"+1 760 969 6400",
    "sg:postcode":"92264",
    "sg:province":"CA",
    "wof:name":"Century 21 Lois Lauer Realty",
    "wof:placetype":"venue"
},
  "geometry": {"coordinates":[-116.495615,33.793411],"type":"Point"}
}