{
  "type": "Feature",
  "properties": {
    "addr:full":"2 del Amo Fashion Sq Torrance CA 90503",
    "addr:housenumber":"2",
    "addr:postcode":"90503",
    "addr:street":"Del Amo Fashion Sq",
    "iso:country":"US",
    "sg:address":"2 del Amo Fashion Sq",
    "sg:city":"Torrance",
    "sg:classifiers":[
        {
            "category":"Shopping",
            "subcategory":"Clothing, Apparel, & Fashions",
            "type":"Retail Goods"
        }
    ],
    "sg:phone":"+1 310 371 7400",
    "sg:postcode":"90503",
    "sg:province":"CA",
    "sg:tags":[
        "infant",
        "wear"
    ],
    "wof:name":"Limited Too",
    "wof:placetype":"venue"
},
  "geometry": {"coordinates":[-118.350672,33.828447],"type":"Point"}
}