{
  "type": "Feature",
  "properties": {
    "iso:country":"US",
    "sg:address":"5629 Monte Vista St",
    "sg:city":"Los Angeles",
    "sg:classifiers":[
        {
            "category":"Shopping",
            "type":"Retail Goods"
        }
    ],
    "sg:phone":"+1 323 256 4016",
    "sg:postcode":"90042",
    "sg:province":"CA",
    "sg:tags":[
        "plant",
        "flower",
        "tree",
        "artificial"
    ],
    "wof:name":"Spring Rose",
    "wof:placetype":"venue"
},
  "geometry": {"coordinates":[-118.19478700000001,34.111652],"type":"Point"}
}