{
  "type": "Feature",
  "properties": {
    "addr:full":"4191 Business Dr Cameron Park CA 95682",
    "addr:housenumber":"4191",
    "addr:postcode":"95682",
    "addr:street":"Business Dr",
    "iso:country":"US",
    "sg:address":"4191 Business Dr",
    "sg:city":"Cameron Park",
    "sg:classifiers":[
        {
            "category":"Building & Trades",
            "subcategory":"Construction",
            "type":"Services"
        }
    ],
    "sg:phone":"+1 530 677 1021",
    "sg:postcode":"95682",
    "sg:province":"CA",
    "sg:tags":[
        "concrete",
        "contractor"
    ],
    "wof:name":"Rescue Concrete Inc",
    "wof:placetype":"venue"
},
  "geometry": {"coordinates":[-120.951796,38.652216],"type":"Point"}
}