{
  "type": "Feature",
  "properties": {
    "addr:full":"1018 Acacia St Stockton CA 95203",
    "addr:housenumber":"1018",
    "addr:postcode":"95203",
    "addr:street":"Acacia St",
    "iso:country":"US",
    "sg:address":"1018 Acacia St",
    "sg:city":"Stockton",
    "sg:classifiers":[
        {
            "category":"Shopping",
            "subcategory":"Hobbies, Toys, & Games",
            "type":"Retail Goods"
        }
    ],
    "sg:phone":"+1 209 462 2555",
    "sg:postcode":"95203",
    "sg:province":"CA",
    "sg:tags":[
        "business"
    ],
    "wof:name":"Expressions",
    "wof:placetype":"venue"
},
  "geometry": {"coordinates":[-121.307863,37.959917],"type":"Point"}
}