{
  "type": "Feature",
  "properties": {
    "addr:full":"3050 Saturn St Brea CA 92821",
    "addr:housenumber":"3050",
    "addr:postcode":"92821",
    "addr:street":"Saturn St",
    "iso:country":"US",
    "sg:address":"3050 Saturn St",
    "sg:city":"Brea",
    "sg:classifiers":[
        {
            "category":"Professional",
            "type":"Services"
        }
    ],
    "sg:phone":"+1 714 577 8758",
    "sg:postcode":"92821",
    "sg:province":"CA",
    "wof:name":"Pacific Advisors Aic",
    "wof:placetype":"venue"
},
  "geometry": {"coordinates":[-117.862824,33.908584],"type":"Point"}
}