{
  "type": "Feature",
  "properties": {
    "iso:country":"US",
    "sg:address":"8490 Hollywood Blvd",
    "sg:city":"West Hollywood",
    "sg:classifiers":[
        {
            "category":"Arts & Performance",
            "subcategory":"Theater",
            "type":"Entertainment"
        }
    ],
    "sg:phone":"+1 310 855 9099",
    "sg:postcode":"90069",
    "sg:province":"CA",
    "sg:tags":[
        "talent",
        "agency",
        "casting"
    ],
    "wof:name":"Inner Focus Talent Management",
    "wof:placetype":"venue"
},
  "geometry": {"coordinates":[-118.374976,34.099434],"type":"Point"}
}