{
  "type": "Feature",
  "properties": {
    "addr:full":"14131 Yorba St 204 Tustin CA 92780",
    "addr:housenumber":"14131;204",
    "addr:postcode":"92780",
    "addr:street":"Yorba St",
    "iso:country":"US",
    "sg:address":"14131 Yorba St 204",
    "sg:city":"Tustin",
    "sg:classifiers":[
        {
            "category":"Professional",
            "subcategory":"Lawyer & Legal Services",
            "type":"Services"
        }
    ],
    "sg:phone":"+1 714 838 9955",
    "sg:postcode":"92780",
    "sg:province":"CA",
    "sg:tags":[
        "attorney",
        "practice"
    ],
    "wof:name":"Dinnebier King & Wertf",
    "wof:placetype":"venue"
},
  "geometry": {"coordinates":[-117.830254,33.75703],"type":"Point"}
}