{
  "type": "Feature",
  "properties": {
    "iso:country":"US",
    "sg:address":"2082 SE Bristol St",
    "sg:city":"Newport Beach",
    "sg:classifiers":[
        {
            "category":"Recreation",
            "type":"Entertainment"
        }
    ],
    "sg:phone":"+1 949 852 9900",
    "sg:postcode":"92660",
    "sg:province":"CA",
    "sg:tags":[
        "ticket"
    ],
    "sg:website":"www.ticket-connection.com",
    "wof:name":"Ticket Connection",
    "wof:placetype":"venue"
},
  "geometry": {"coordinates":[-117.87828399999999,33.663939],"type":"Point"}
}