{
  "type": "Feature",
  "properties": {
    "iso:country":"US",
    "sg:address":"525 Downie St",
    "sg:city":"Yuba City",
    "sg:classifiers":[
        {
            "category":"Real Estate",
            "subcategory":"Real Estate Operator",
            "type":"Services"
        }
    ],
    "sg:phone":"+1 530 673 8593",
    "sg:postcode":"95991",
    "sg:province":"CA",
    "sg:tags":[
        "apartment"
    ],
    "wof:name":"Heather Glen Duplexes",
    "wof:placetype":"venue"
},
  "geometry": {"coordinates":[-121.621144,39.153522],"type":"Point"}
}