{
  "type": "Feature",
  "properties": {
    "iso:country":"US",
    "sg:address":"28378 Encanto Dr",
    "sg:city":"Sun City",
    "sg:classifiers":[
        {
            "category":"Utilities",
            "subcategory":"Telephone",
            "type":"Services"
        }
    ],
    "sg:phone":"+1 951 672 8041",
    "sg:postcode":"92586",
    "sg:province":"CA",
    "sg:tags":[
        "communications"
    ],
    "wof:name":"Guys Cyber",
    "wof:placetype":"venue"
},
  "geometry": {"coordinates":[-117.18511100000001,33.708905],"type":"Point"}
}