{
  "type": "Feature",
  "properties": {
    "iso:country":"US",
    "sg:address":"12749 Norwalk Blvd Ste 100",
    "sg:city":"Norwalk",
    "sg:classifiers":[
        {
            "category":"Professional",
            "subcategory":"Lawyer & Legal Services",
            "type":"Services"
        }
    ],
    "sg:phone":"+1 562 864 0801",
    "sg:postcode":"90650",
    "sg:province":"CA",
    "wof:name":"Balmer Michael R II Attorney At Law",
    "wof:placetype":"venue"
},
  "geometry": {"coordinates":[-118.072998,33.915001],"type":"Point"}
}