{
  "type": "Feature",
  "properties": {
    "iso:country":"US",
    "sg:address":"1252 Airport Park Blvd",
    "sg:city":"Ukiah",
    "sg:classifiers":[
        {
            "category":"Health Services",
            "subcategory":"Clinic",
            "type":"Services"
        },
        {
            "category":"Health Services",
            "subcategory":"Health Practitioner",
            "type":"Services"
        },
        {
            "category":"Community Center",
            "type":"Public Place"
        }
    ],
    "sg:phone":"+1 707 462 4996",
    "sg:postcode":"95482",
    "sg:province":"CA",
    "sg:tags":[
        "medical",
        "therapist",
        "therapy",
        "physical"
    ],
    "sg:website":"http://www.meadowspt.com",
    "wof:name":"Meadows Physical Therapy Inc",
    "wof:placetype":"venue"
},
  "geometry": {"coordinates":[-123.198419,39.130574],"type":"Point"}
}