{
  "type": "Feature",
  "properties": {
    "iso:country":"US",
    "sg:address":"172 W Palm Dr",
    "sg:city":"Arcadia",
    "sg:classifiers":[
        {
            "category":"Professional",
            "type":"Services"
        }
    ],
    "sg:phone":"+1 818 558 2365",
    "sg:postcode":"91007",
    "sg:province":"CA",
    "wof:name":"Teck S Tan",
    "wof:placetype":"venue"
},
  "geometry": {"coordinates":[-118.038028,34.111453],"type":"Point"}
}