{
  "type": "Feature",
  "properties": {
    "addr:full":"120 Birmingham Dr Cardiff By Sea CA 92007",
    "addr:housenumber":"120",
    "addr:postcode":"92007",
    "addr:street":"Birmingham Dr",
    "iso:country":"US",
    "sg:address":"120 Birmingham Dr",
    "sg:city":"Cardiff By Sea",
    "sg:classifiers":[
        {
            "category":"Insurance",
            "subcategory":"Insurance Agent",
            "type":"Services"
        }
    ],
    "sg:phone":"+1 760 871 0770",
    "sg:postcode":"92007",
    "sg:province":"CA",
    "wof:name":"Farmers Insurance Group",
    "wof:placetype":"venue"
},
  "geometry": {"coordinates":[-117.282752,33.02293],"type":"Point"}
}