{
  "type": "Feature",
  "properties": {
    "iso:country":"US",
    "sg:address":"169 S Sierra Way",
    "sg:city":"San Bernardino",
    "sg:classifiers":[
        {
            "category":"Wholesale",
            "subcategory":"Machinery & Supplies",
            "type":"Manufacturing & Wholesale Goods"
        }
    ],
    "sg:phone":"+1 909 889 4084",
    "sg:postcode":"92408",
    "sg:province":"CA",
    "sg:tags":[
        "farm",
        "equipment"
    ],
    "sg:website":"www.cleancutter.com",
    "wof:name":"Clean Cutter Tiller Blades",
    "wof:placetype":"venue"
},
  "geometry": {"coordinates":[-117.28509099999999,34.100278],"type":"Point"}
}