{
  "type": "Feature",
  "properties": {
    "iso:country":"US",
    "sg:address":"910 N Vermont Ave",
    "sg:city":"Los Angeles",
    "sg:classifiers":[
        {
            "category":"Food & Beverages",
            "subcategory":"Groceries & Convenience Stores",
            "type":"Retail Goods"
        }
    ],
    "sg:phone":"+1 323 664 0235",
    "sg:postcode":"90029",
    "sg:province":"CA",
    "wof:name":"Amigo Discount Mini Mart",
    "wof:placetype":"venue"
},
  "geometry": {"coordinates":[-118.292,34.087898],"type":"Point"}
}