{
  "type": "Feature",
  "properties": {
    "addr:full":"870 S Western Ave Los Angeles CA 90005",
    "addr:housenumber":"870",
    "addr:postcode":"90005",
    "addr:street":"S Western Ave",
    "iso:country":"US",
    "sg:address":"870 S Western Ave",
    "sg:city":"Los Angeles",
    "sg:classifiers":[
        {
            "category":"Shopping",
            "subcategory":"Clothing, Apparel, & Fashions",
            "type":"Retail Goods"
        }
    ],
    "sg:phone":"+1 213 383 6451",
    "sg:postcode":"90005",
    "sg:province":"CA",
    "wof:name":"Young Fashion",
    "wof:placetype":"venue"
},
  "geometry": {"coordinates":[-118.309071,34.057658],"type":"Point"}
}