{
  "type": "Feature",
  "properties": {
    "addr:full":"33215 Transit Ave Union City CA 94587",
    "addr:housenumber":"33215",
    "addr:postcode":"94587",
    "addr:street":"Transit Ave",
    "iso:country":"US",
    "sg:address":"33215 Transit Ave",
    "sg:city":"Union City",
    "sg:classifiers":[
        {
            "category":"Professional",
            "subcategory":"Computer Services",
            "type":"Services"
        }
    ],
    "sg:phone":"+1 510 324 7600",
    "sg:postcode":"94587",
    "sg:province":"CA",
    "sg:tags":[
        "repair"
    ],
    "sg:website":"www.alancomputech.com",
    "wof:name":"Alan Computech Intl",
    "wof:placetype":"venue"
},
  "geometry": {"coordinates":[-122.040511,37.59936],"type":"Point"}
}