{
  "type": "Feature",
  "properties": {
    "addr:full":"3110 Hilltop Mall Rd Richmond CA 94806",
    "addr:housenumber":"3110",
    "addr:postcode":"94806",
    "addr:street":"Hilltop Mall Rd",
    "iso:country":"US",
    "sg:address":"3110 Hilltop Mall Rd",
    "sg:city":"Richmond",
    "sg:classifiers":[
        {
            "category":"Arts & Performance",
            "subcategory":"Theater",
            "type":"Entertainment"
        }
    ],
    "sg:phone":"+1 510 223 5321",
    "sg:postcode":"94806",
    "sg:province":"CA",
    "sg:tags":[
        "bureau"
    ],
    "wof:name":"Sparks Entertainment Group",
    "wof:placetype":"venue"
},
  "geometry": {"coordinates":[-122.32444099999999,37.979823],"type":"Point"}
}