{
  "type": "Feature",
  "properties": {
    "iso:country":"US",
    "sg:address":"18075 Ventura Blvd",
    "sg:city":"Encino",
    "sg:classifiers":[
        {
            "category":"Insurance",
            "subcategory":"Insurance Agent",
            "type":"Services"
        }
    ],
    "sg:phone":"+1 818 342 3973",
    "sg:postcode":"91316",
    "sg:province":"CA",
    "sg:tags":[
        "consultant"
    ],
    "wof:name":"John S Murphy",
    "wof:placetype":"venue"
},
  "geometry": {"coordinates":[-118.52513,34.164801],"type":"Point"}
}