{
  "type": "Feature",
  "properties": {
    "iso:country":"US",
    "sg:address":"4250 Holt Blvd",
    "sg:city":"Montclair",
    "sg:classifiers":[
        {
            "category":"Retail",
            "subcategory":"Auto Repair",
            "type":"Services"
        }
    ],
    "sg:phone":"+1 909 670 1900",
    "sg:postcode":"91763",
    "sg:province":"CA",
    "sg:tags":[
        "repairing",
        "automobile"
    ],
    "wof:name":"Magic Auto Repair",
    "wof:placetype":"venue"
},
  "geometry": {"coordinates":[-117.713212,34.062644],"type":"Point"}
}