{
  "type": "Feature",
  "properties": {
    "addr:full":"21130 Union St Wildomar CA 92595",
    "addr:housenumber":"21130",
    "addr:postcode":"92595",
    "addr:street":"Union St",
    "iso:country":"US",
    "sg:address":"21130 Union St",
    "sg:city":"Wildomar",
    "sg:classifiers":[
        {
            "category":"Building & Trades",
            "subcategory":"Electrical",
            "type":"Services"
        }
    ],
    "sg:phone":"+1 909 772 9790",
    "sg:postcode":"92595",
    "sg:province":"CA",
    "sg:tags":[
        "electrician"
    ],
    "wof:name":"Custis Dump Truck & Backhoe Service",
    "wof:placetype":"venue"
},
  "geometry": {"coordinates":[-117.28299699999999,33.605301],"type":"Point"}
}