{
  "type": "Feature",
  "properties": {
    "iso:country":"US",
    "sg:address":"555 Capitol Mall Ste 276",
    "sg:city":"Sacramento",
    "sg:classifiers":[
        {
            "category":"Personal",
            "subcategory":"Massage",
            "type":"Services"
        },
        {
            "category":"Personal",
            "subcategory":"Day Spa",
            "type":"Services"
        },
        {
            "category":"Personal",
            "subcategory":"Skin Care",
            "type":"Services"
        }
    ],
    "sg:phone":"+1 916 482 2772",
    "sg:postcode":"95814",
    "sg:province":"CA",
    "sg:website":"www.mellowmeout.com/locations/do...",
    "wof:name":"Mellow Me Out",
    "wof:placetype":"venue"
},
  "geometry": {"coordinates":[-121.500764,38.578679],"type":"Point"}
}