{
  "type": "Feature",
  "properties": {
    "iso:country":"US",
    "sg:address":"451 Green Valley Rd",
    "sg:city":"Watsonville",
    "sg:classifiers":[
        {
            "category":"Recreation",
            "type":"Entertainment"
        }
    ],
    "sg:phone":"+1 831 768 7074",
    "sg:postcode":"95076",
    "sg:province":"CA",
    "sg:tags":[
        "club",
        "membership"
    ],
    "wof:name":"Watsonville American Little Le",
    "wof:placetype":"venue"
},
  "geometry": {"coordinates":[-121.765536,36.947992],"type":"Point"}
}