{
  "type": "Feature",
  "properties": {
    "addr:full":"11020 S Vermont Ave Los Angeles CA 90044",
    "addr:housenumber":"11020",
    "addr:postcode":"90044",
    "addr:street":"S Vermont Ave",
    "iso:country":"US",
    "sg:address":"11020 S Vermont Ave",
    "sg:city":"Los Angeles",
    "sg:classifiers":[
        {
            "category":"Retail",
            "subcategory":"Auto Rental",
            "type":"Services"
        }
    ],
    "sg:phone":"+1 323 756 8744",
    "sg:postcode":"90044",
    "sg:province":"CA",
    "sg:tags":[
        "renting",
        "truck",
        "leasing"
    ],
    "wof:name":"U-Haul Co",
    "wof:placetype":"venue"
},
  "geometry": {"coordinates":[-118.29154,33.934823],"type":"Point"}
}