{
  "type": "Feature",
  "properties": {
    "iso:country":"US",
    "sg:address":"1800 3rd St",
    "sg:city":"Sacramento",
    "sg:classifiers":[
        {
            "category":"Government",
            "subcategory":"Office",
            "type":"Public Place"
        }
    ],
    "sg:phone":"+1 916 327 4306",
    "sg:postcode":"95811",
    "sg:province":"CA",
    "sg:tags":[
        "administrative",
        "program",
        "health"
    ],
    "wof:name":"Field Operations-Southern Area",
    "wof:placetype":"venue"
},
  "geometry": {"coordinates":[-121.50681299999999,38.573404],"type":"Point"}
}