{
  "type": "Feature",
  "properties": {
    "addr:full":"6507 4th Ave Sacramento CA 95817",
    "addr:housenumber":"6507",
    "addr:postcode":"95817",
    "addr:street":"4Th Ave",
    "iso:country":"US",
    "sg:address":"6507 4th Ave",
    "sg:city":"Sacramento",
    "sg:classifiers":[
        {
            "category":"Banks & Credit Unions",
            "subcategory":"Bank",
            "type":"Services"
        }
    ],
    "sg:phone":"+1 805 466 6070",
    "sg:postcode":"95817",
    "sg:province":"CA",
    "wof:name":"Calif State Employees Credit Union",
    "wof:placetype":"venue"
},
  "geometry": {"coordinates":[-121.427002,38.5485],"type":"Point"}
}