{
  "type": "Feature",
  "properties": {
    "iso:country":"US",
    "sg:address":"2693 Clayton Rd",
    "sg:city":"Concord",
    "sg:classifiers":[
        {
            "category":"Food & Beverages",
            "subcategory":"Bakery",
            "type":"Retail Goods"
        }
    ],
    "sg:phone":"+1 925 689 7220",
    "sg:postcode":"94519",
    "sg:province":"CA",
    "sg:tags":[
        "baker"
    ],
    "wof:name":"Alpine Pastry & Cakes",
    "wof:placetype":"venue"
},
  "geometry": {"coordinates":[-122.02811800000001,37.975381],"type":"Point"}
}