{
  "type": "Feature",
  "properties": {
    "iso:country":"US",
    "sg:address":"6655 Alvarado Rd",
    "sg:city":"San Diego",
    "sg:classifiers":[
        {
            "category":"Health Services",
            "subcategory":"Hospital",
            "type":"Services"
        }
    ],
    "sg:phone":"+1 619 287 3270",
    "sg:postcode":"92120",
    "sg:province":"CA",
    "wof:name":"Alvarado Hospital Medical Ctr",
    "wof:placetype":"venue"
},
  "geometry": {"coordinates":[-117.058631,32.777559],"type":"Point"}
}