{
  "type": "Feature",
  "properties": {
    "iso:country":"US",
    "sg:address":"13071 Central Ave",
    "sg:city":"Chino",
    "sg:classifiers":[
        {
            "category":"Retail",
            "subcategory":"Repair Shop",
            "type":"Services"
        }
    ],
    "sg:phone":"+1 909 590 0044",
    "sg:postcode":"91710",
    "sg:province":"CA",
    "sg:tags":[
        "upholsterer"
    ],
    "wof:name":"Chino Custom Upholstry",
    "wof:placetype":"venue"
},
  "geometry": {"coordinates":[-117.689217,34.016811],"type":"Point"}
}