{
  "type": "Feature",
  "properties": {
    "iso:country":"US",
    "sg:address":"12330 Magnolia Blvd",
    "sg:city":"Valley Village",
    "sg:classifiers":[
        {
            "category":"Professional",
            "subcategory":"Advertising",
            "type":"Services"
        }
    ],
    "sg:phone":"+1 818 508 1700",
    "sg:postcode":"91607",
    "sg:province":"CA",
    "sg:tags":[
        "counselor"
    ],
    "sg:website":"www.rjhaddad.com",
    "wof:name":"Haddad Advertising Inc",
    "wof:placetype":"venue"
},
  "geometry": {"coordinates":[-118.401528,34.164794],"type":"Point"}
}