{
  "type": "Feature",
  "properties": {
    "iso:country":"US",
    "sg:address":"100 Shoreline Hwy",
    "sg:city":"Mill Valley",
    "sg:classifiers":[
        {
            "category":"Social Services",
            "subcategory":"Child Care",
            "type":"Services"
        }
    ],
    "sg:phone":"+1 415 331 7766",
    "sg:postcode":"94941",
    "sg:province":"CA",
    "sg:tags":[
        "kindergarten",
        "academic",
        "school"
    ],
    "wof:name":"Marin Day Schools",
    "wof:placetype":"venue"
},
  "geometry": {"coordinates":[-122.517257,37.880284],"type":"Point"}
}