{
  "type": "Feature",
  "properties": {
    "iso:country":"US",
    "sg:address":"1700 California Street Suite 450",
    "sg:city":"San Francisco",
    "sg:classifiers":[
        {
            "category":"Health Services",
            "subcategory":"Health Practitioner",
            "type":"Services"
        }
    ],
    "sg:phone":"+1 415 359 1444",
    "sg:postcode":"94109",
    "sg:province":"CA",
    "sg:tags":[
        "therapy",
        "physical"
    ],
    "sg:website":"www.gghandtherapy.com",
    "wof:name":"Golden Gate Hand Therapy",
    "wof:placetype":"venue"
},
  "geometry": {"coordinates":[-122.42242299999999,37.790436],"type":"Point"}
}