{
  "type": "Feature",
  "properties": {
    "addr:full":"14349 Victory Blvd Van Nuys CA 91401",
    "addr:housenumber":"14349",
    "addr:postcode":"91401",
    "addr:street":"Victory Blvd",
    "iso:country":"US",
    "sg:address":"14349 Victory Blvd",
    "sg:city":"Van Nuys",
    "sg:classifiers":[
        {
            "category":"Health Services",
            "subcategory":"Doctor",
            "type":"Services"
        }
    ],
    "sg:phone":"+1 818 786 0911",
    "sg:postcode":"91401",
    "sg:province":"CA",
    "sg:tags":[
        "physician",
        "surgeon"
    ],
    "wof:name":"Satamyan Gayk",
    "wof:placetype":"venue"
},
  "geometry": {"coordinates":[-118.44564699999999,34.186737],"type":"Point"}
}