{
  "type": "Feature",
  "properties": {
    "iso:country":"US",
    "sg:address":"353 Kearny Suite 401",
    "sg:city":"San Francisco",
    "sg:classifiers":[
        {
            "category":"Professional",
            "subcategory":"Computer Services",
            "type":"Services"
        }
    ],
    "sg:phone":"+1 85549675872",
    "sg:postcode":"94108",
    "sg:province":"CA",
    "sg:tags":[
        "staffing",
        "construction",
        "online"
    ],
    "sg:website":"http://www.WorkersNow.com",
    "wof:name":"WorkersNow",
    "wof:placetype":"venue"
},
  "geometry": {"coordinates":[-122.40421499999999,37.791185],"type":"Point"}
}