{
  "type": "Feature",
  "properties": {
    "addr:full":"5116 Los Altos Ct San Diego CA 92109",
    "addr:housenumber":"5116",
    "addr:postcode":"92109",
    "addr:street":"Los Altos Ct",
    "iso:country":"US",
    "sg:address":"5116 Los Altos Ct",
    "sg:city":"San Diego",
    "sg:classifiers":[
        {
            "category":"Professional",
            "subcategory":"Management & Consulting",
            "type":"Services"
        }
    ],
    "sg:phone":"+1 858 245 3216",
    "sg:postcode":"92109",
    "sg:province":"CA",
    "sg:tags":[
        "consultant"
    ],
    "wof:name":"Ryan Traffic Counters",
    "wof:placetype":"venue"
},
  "geometry": {"coordinates":[-117.243978,32.811411],"type":"Point"}
}