{
  "type": "Feature",
  "properties": {
    "iso:country":"US",
    "sg:address":"772 Panhandle Dr",
    "sg:city":"Diamond Bar",
    "sg:classifiers":[
        {
            "category":"Shopping",
            "subcategory":"Crafts & Fabrics",
            "type":"Retail Goods"
        }
    ],
    "sg:phone":"+1 909 861 0314",
    "sg:postcode":"91765",
    "sg:province":"CA",
    "sg:tags":[
        "sewing"
    ],
    "wof:name":"Netties Needleworks",
    "wof:placetype":"venue"
},
  "geometry": {"coordinates":[-117.810322,34.013019],"type":"Point"}
}