{
  "type": "Feature",
  "properties": {
    "addr:full":"6445 N Palm Ave Fresno CA 93704",
    "addr:housenumber":"6445",
    "addr:postcode":"93704",
    "addr:street":"N Palm Ave",
    "iso:country":"US",
    "sg:address":"6445 N Palm Ave",
    "sg:city":"Fresno",
    "sg:classifiers":[
        {
            "category":"Health Services",
            "subcategory":"Doctor",
            "type":"Services"
        }
    ],
    "sg:phone":"+1 559 439 0440",
    "sg:postcode":"93704",
    "sg:province":"CA",
    "sg:tags":[
        "physician",
        "surgeon"
    ],
    "wof:name":"Accident Helpline Med Group",
    "wof:placetype":"venue"
},
  "geometry": {"coordinates":[-119.808384,36.830661],"type":"Point"}
}