{
  "type": "Feature",
  "properties": {
    "iso:country":"US",
    "sg:address":"1721 Scott St",
    "sg:city":"San Francisco",
    "sg:classifiers":[
        {
            "category":"Health Services",
            "subcategory":"Health Practitioner",
            "type":"Services"
        }
    ],
    "sg:phone":"+1 415 440 6860",
    "sg:postcode":"94115",
    "sg:province":"CA",
    "sg:tags":[
        "psychotherapist"
    ],
    "wof:name":"Eric Stein",
    "wof:placetype":"venue"
},
  "geometry": {"coordinates":[-122.438438,37.78619],"type":"Point"}
}