{
  "type": "Feature",
  "properties": {
    "addr:full":"1587 French Camp Tpke Stockton CA 95206",
    "addr:housenumber":"1587",
    "addr:postcode":"95206",
    "iso:country":"US",
    "sg:address":"1587 French Camp Tpke",
    "sg:city":"Stockton",
    "sg:classifiers":[
        {
            "category":"Retail",
            "subcategory":"Auto Repair",
            "type":"Services"
        }
    ],
    "sg:phone":"+1 209 986 3352",
    "sg:postcode":"95206",
    "sg:province":"CA",
    "sg:tags":[
        "wrecker"
    ],
    "wof:name":"Sovan's Towing",
    "wof:placetype":"venue"
},
  "geometry": {"coordinates":[-121.290232,37.938046],"type":"Point"}
}