{
  "type": "Feature",
  "properties": {
    "addr:full":"415 Railroad Ave Danville CA 94526",
    "addr:housenumber":"415",
    "addr:postcode":"94526",
    "addr:street":"Railroad Ave",
    "iso:country":"US",
    "sg:address":"415 Railroad Ave",
    "sg:city":"Danville",
    "sg:classifiers":[
        {
            "category":"Personal",
            "subcategory":"Beauty Salon",
            "type":"Services"
        }
    ],
    "sg:phone":"+1 925 837 7876",
    "sg:postcode":"94526",
    "sg:province":"CA",
    "wof:name":"Salon 415",
    "wof:placetype":"venue"
},
  "geometry": {"coordinates":[-121.996681,37.818971],"type":"Point"}
}