{
  "type": "Feature",
  "properties": {
    "addr:full":"28118 Agoura Rd Agoura Hills CA 91301",
    "addr:housenumber":"28118",
    "addr:postcode":"91301",
    "addr:street":"Agoura Rd",
    "iso:country":"US",
    "sg:address":"28118 Agoura Rd",
    "sg:city":"Agoura Hills",
    "sg:classifiers":[
        {
            "category":"Professional",
            "subcategory":"Management & Consulting",
            "type":"Services"
        }
    ],
    "sg:phone":"+1 805 777 7705",
    "sg:postcode":"91301",
    "sg:province":"CA",
    "sg:tags":[
        "consultant",
        "nursing"
    ],
    "sg:website":"www.nipinc.com",
    "wof:name":"Nurses In Partnership Inc",
    "wof:placetype":"venue"
},
  "geometry": {"coordinates":[-118.742329,34.140825],"type":"Point"}
}