{
  "type": "Feature",
  "properties": {
    "iso:country":"US",
    "sg:address":"Glacial Garden Skating Arena 3975 Pixie Ave",
    "sg:city":"Lakewood",
    "sg:classifiers":[
        {
            "category":"Shopping",
            "subcategory":"Bicycles & Sporting Goods",
            "type":"Retail Goods"
        }
    ],
    "sg:phone":"+1 562 425 5117",
    "sg:postcode":"90712",
    "sg:province":"CA",
    "sg:website":"hockeyelement.com",
    "wof:name":"Skating Element Pro Shop",
    "wof:placetype":"venue"
},
  "geometry": {"coordinates":[-118.163259,33.83048],"type":"Point"}
}