{
  "type": "Feature",
  "properties": {
    "addr:full":"46700 Fremont Blvd Fremont CA 94538",
    "addr:housenumber":"46700",
    "addr:postcode":"94538",
    "addr:street":"Fremont Blvd",
    "iso:country":"US",
    "sg:address":"46700 Fremont Blvd",
    "sg:city":"Fremont",
    "sg:classifiers":[
        {
            "category":"Deli",
            "type":"Food & Drink"
        }
    ],
    "sg:phone":"+1 510 657 3287",
    "sg:postcode":"94538",
    "sg:province":"CA",
    "sg:website":"www.vincescafe.com",
    "wof:name":"Vince's Cafe",
    "wof:placetype":"venue"
},
  "geometry": {"coordinates":[-121.94499999999999,37.480999],"type":"Point"}
}