{
  "type": "Feature",
  "properties": {
    "addr:full":"14106 Rondeau St Westminster CA 92683",
    "addr:housenumber":"14106",
    "addr:postcode":"92683",
    "addr:street":"Rondeau St",
    "iso:country":"US",
    "sg:address":"14106 Rondeau St",
    "sg:city":"Westminster",
    "sg:classifiers":[
        {
            "category":"Professional",
            "subcategory":"Detective & Security Services",
            "type":"Services"
        }
    ],
    "sg:phone":"+1 714 421 1826",
    "sg:postcode":"92683",
    "sg:province":"CA",
    "sg:tags":[
        "information",
        "bureau"
    ],
    "wof:name":"Salient Medical Services",
    "wof:placetype":"venue"
},
  "geometry": {"coordinates":[-118.008571,33.758167],"type":"Point"}
}