{
  "type": "Feature",
  "properties": {
    "iso:country":"US",
    "sg:address":"4500 Woodman Ave",
    "sg:city":"Sherman Oaks",
    "sg:classifiers":[
        {
            "category":"Real Estate",
            "subcategory":"Real Estate Operator",
            "type":"Services"
        }
    ],
    "sg:phone":"+1 818 780 7000",
    "sg:postcode":"91423",
    "sg:province":"CA",
    "sg:tags":[
        "apartment"
    ],
    "wof:name":"The Plaza At Sherman Oaks",
    "wof:placetype":"venue"
},
  "geometry": {"coordinates":[-118.431,34.153198],"type":"Point"}
}