{
  "type": "Feature",
  "properties": {
    "addr:full":"2458 Avalon Drive Sacramento CA 95864",
    "addr:housenumber":"2458",
    "addr:postcode":"95864",
    "addr:street":"Avalon Drive",
    "iso:country":"US",
    "sg:address":"2458 Avalon Drive",
    "sg:city":"Sacramento",
    "sg:classifiers":[
        {
            "category":"Retail",
            "subcategory":"Laundry & Dry Cleaning",
            "type":"Services"
        }
    ],
    "sg:phone":"+1 916 488 6628",
    "sg:postcode":"95864",
    "sg:province":"CA",
    "wof:name":"Fashion Cleaners",
    "wof:placetype":"venue"
},
  "geometry": {"coordinates":[-121.368903,38.609551],"type":"Point"}
}