{
  "type": "Feature",
  "properties": {
    "iso:country":"US",
    "sg:address":"502 Las Posas Rd",
    "sg:city":"Camarillo",
    "sg:classifiers":[
        {
            "category":"Banks & Credit Unions",
            "subcategory":"Bank",
            "type":"Services"
        }
    ],
    "sg:phone":"+1 805 384 2100",
    "sg:postcode":"93010",
    "sg:province":"CA",
    "wof:name":"City National Bank",
    "wof:placetype":"venue"
},
  "geometry": {"coordinates":[-119.064003,34.2304],"type":"Point"}
}