{
  "type": "Feature",
  "properties": {
    "iso:country":"US",
    "sg:address":"1221 E Orangeburg Ave",
    "sg:city":"Modesto",
    "sg:classifiers":[
        {
            "category":"Sports & Exercise",
            "subcategory":"Gym",
            "type":"Entertainment"
        }
    ],
    "sg:phone":"+1 209 578 5239",
    "sg:postcode":"95350",
    "sg:province":"CA",
    "sg:tags":[
        "club",
        "health",
        "studio",
        "gymnasium"
    ],
    "wof:name":"Slender Lady Of Modesto",
    "wof:placetype":"venue"
},
  "geometry": {"coordinates":[-120.977739,37.663617],"type":"Point"}
}