{
  "type": "Feature",
  "properties": {
    "iso:country":"US",
    "sg:address":"121 Industrial Way",
    "sg:city":"Belmont",
    "sg:classifiers":[
        {
            "category":"Wholesale",
            "subcategory":"Electrical",
            "type":"Manufacturing & Wholesale Goods"
        }
    ],
    "sg:phone":"+1 650 637 1864",
    "sg:postcode":"94002",
    "sg:province":"CA",
    "sg:tags":[
        "assembler",
        "electronic",
        "parts"
    ],
    "wof:name":"JIV Electronics",
    "wof:placetype":"venue"
},
  "geometry": {"coordinates":[-122.403088,37.657473],"type":"Point"}
}