{
  "type": "Feature",
  "properties": {
    "addr:full":"47 Bay Dr Bay Point CA 94565",
    "addr:housenumber":"47",
    "addr:postcode":"94565",
    "addr:street":"Bay Dr Bay Point",
    "iso:country":"US",
    "sg:address":"47 Bay Dr",
    "sg:city":"Bay Point",
    "sg:classifiers":[
        {
            "category":"Organizations",
            "subcategory":"Religious Organization",
            "type":"Services"
        }
    ],
    "sg:phone":"+1 925 458 2006",
    "sg:postcode":"94565",
    "sg:province":"CA",
    "sg:tags":[
        "church"
    ],
    "wof:name":"Apostolic Assembly Church",
    "wof:placetype":"venue"
},
  "geometry": {"coordinates":[-121.963875,38.036537],"type":"Point"}
}