{
  "type": "Feature",
  "properties": {
    "iso:country":"US",
    "sg:address":"450 1st St",
    "sg:city":"Woodland",
    "sg:classifiers":[
        {
            "category":"Organizations",
            "subcategory":"Religious Organization",
            "type":"Services"
        }
    ],
    "sg:phone":"+1 530 662 7305",
    "sg:postcode":"95695",
    "sg:province":"CA",
    "wof:name":"Seventh Day Adventist Spanish",
    "wof:placetype":"venue"
},
  "geometry": {"coordinates":[-121.773247,38.675791],"type":"Point"}
}