{
  "type": "Feature",
  "properties": {
    "iso:country":"US",
    "sg:address":"1541 Mason Street",
    "sg:city":"San Francisco",
    "sg:classifiers":[
        {
            "category":"Autos & Motor Vehicles",
            "subcategory":"Automobile Sales",
            "type":"Retail Goods"
        }
    ],
    "sg:phone":"+1 415 861 2386",
    "sg:postcode":"94133",
    "sg:province":"CA",
    "sg:tags":[
        "limo"
    ],
    "wof:name":"Corporate Classic",
    "wof:placetype":"venue"
},
  "geometry": {"coordinates":[-122.412003,37.797699],"type":"Point"}
}