{
  "type": "Feature",
  "properties": {
    "addr:full":"Newport Ave and Mitchell Ave Tustin CA 92781",
    "addr:postcode":"92781",
    "addr:street":"Newport Ave And Mitchell Ave",
    "iso:country":"US",
    "sg:address":"Newport Ave and Mitchell Ave",
    "sg:city":"Tustin",
    "sg:classifiers":[
        {
            "category":"Autos & Motor Vehicles",
            "subcategory":"Fuel & Gas Station",
            "type":"Retail Goods"
        }
    ],
    "sg:postcode":"92781",
    "sg:province":"CA",
    "wof:name":"Thrifty",
    "wof:placetype":"venue"
},
  "geometry": {"coordinates":[-117.82490900000001,33.735429],"type":"Point"}
}