{
  "type": "Feature",
  "properties": {
    "addr:full":"400 2nd St Exeter CA 93221",
    "addr:housenumber":"400",
    "addr:postcode":"93221",
    "addr:street":"2Nd St",
    "iso:country":"US",
    "sg:address":"400 2nd St",
    "sg:city":"Exeter",
    "sg:classifiers":[
        {
            "category":"Professional",
            "subcategory":"Business Services",
            "type":"Services"
        }
    ],
    "sg:phone":"+1 559 592 5655",
    "sg:postcode":"93221",
    "sg:province":"CA",
    "sg:tags":[
        "packaging"
    ],
    "sg:website":"www.hobbs-inc.com",
    "wof:name":"Hobbs Container Co",
    "wof:placetype":"venue"
},
  "geometry": {"coordinates":[-119.130765,36.291288],"type":"Point"}
}