{
  "type": "Feature",
  "properties": {
    "addr:full":"3550 Cam del Rio N San Diego CA 92108",
    "addr:housenumber":"3550",
    "addr:postcode":"92108",
    "addr:street":"Cam Del Rio N",
    "iso:country":"US",
    "sg:address":"3550 Cam del Rio N",
    "sg:city":"San Diego",
    "sg:classifiers":[
        {
            "category":"Professional",
            "subcategory":"Business Services",
            "type":"Services"
        }
    ],
    "sg:phone":"+1 619 280 2212",
    "sg:postcode":"92108",
    "sg:province":"CA",
    "sg:tags":[
        "inventory"
    ],
    "wof:name":"RGIS Inventory Specialist",
    "wof:placetype":"venue"
},
  "geometry": {"coordinates":[-117.121363,32.77751],"type":"Point"}
}