{
  "type": "Feature",
  "properties": {
    "addr:full":"7930 Frost St San Diego CA 92123",
    "addr:housenumber":"7930",
    "addr:postcode":"92123",
    "addr:street":"Frost St",
    "iso:country":"US",
    "sg:address":"7930 Frost St",
    "sg:city":"San Diego",
    "sg:classifiers":[
        {
            "category":"Health Services",
            "subcategory":"Doctor",
            "type":"Services"
        }
    ],
    "sg:phone":"+1 858 565 0104",
    "sg:postcode":"92123",
    "sg:province":"CA",
    "sg:tags":[
        "physician",
        "surgeon"
    ],
    "wof:name":"San Diego General Surgery",
    "wof:placetype":"venue"
},
  "geometry": {"coordinates":[-117.15106299999999,32.800244],"type":"Point"}
}