{
  "type": "Feature",
  "properties": {
    "addr:full":"3110 Roosevelt St Carlsbad CA 92008",
    "addr:housenumber":"3110",
    "addr:postcode":"92008",
    "addr:street":"Roosevelt St",
    "iso:country":"US",
    "sg:address":"3110 Roosevelt St",
    "sg:city":"Carlsbad",
    "sg:classifiers":[
        {
            "category":"Food & Beverages",
            "subcategory":"Groceries & Convenience Stores",
            "type":"Retail Goods"
        }
    ],
    "sg:phone":"+1 760 729 5024",
    "sg:postcode":"92008",
    "sg:province":"CA",
    "wof:name":"Circle K Corp",
    "wof:placetype":"venue"
},
  "geometry": {"coordinates":[-117.34699999999999,33.158699],"type":"Point"}
}