{
  "type": "Feature",
  "properties": {
    "iso:country":"US",
    "sg:address":"Smooth Aesthetics Med Spa 1510 West Verdugo Ave Ste E",
    "sg:city":"Burbank",
    "sg:classifiers":[
        {
            "category":"Health Services",
            "subcategory":"Clinic",
            "type":"Services"
        },
        {
            "category":"Personal",
            "subcategory":"Beauty Salon",
            "type":"Services"
        }
    ],
    "sg:phone":"+1 818 954 0510",
    "sg:postcode":"91506",
    "sg:province":"CA",
    "sg:tags":[
        "spa",
        "medical"
    ],
    "sg:website":"www.jentox.com",
    "wof:name":"Jentox Ionic Toxin Release Therapy",
    "wof:placetype":"venue"
},
  "geometry": {"coordinates":[-118.32168,34.168062],"type":"Point"}
}