{
  "type": "Feature",
  "properties": {
    "iso:country":"US",
    "sg:address":"655 Castro St",
    "sg:city":"Mountain View",
    "sg:classifiers":[
        {
            "category":"Banks & Credit Unions",
            "subcategory":"Bank",
            "type":"Services"
        }
    ],
    "sg:phone":"+1 650 961 6328",
    "sg:postcode":"94041",
    "sg:province":"CA",
    "wof:name":"Silverado Federal Credit Union",
    "wof:placetype":"venue"
},
  "geometry": {"coordinates":[-122.082905,37.387324],"type":"Point"}
}