{
  "type": "Feature",
  "properties": {
    "addr:full":"2684 N Tustin St Orange CA 92865",
    "addr:housenumber":"2684",
    "addr:postcode":"92865",
    "addr:street":"N Tustin St",
    "iso:country":"US",
    "sg:address":"2684 N Tustin St",
    "sg:city":"Orange",
    "sg:classifiers":[
        {
            "category":"Food & Beverages",
            "subcategory":"Groceries & Convenience Stores",
            "type":"Retail Goods"
        }
    ],
    "sg:phone":"+1 714 637 6651",
    "sg:postcode":"92865",
    "sg:province":"CA",
    "wof:name":"Vons 2335",
    "wof:placetype":"venue"
},
  "geometry": {"coordinates":[-117.836232,33.830414],"type":"Point"}
}