{
  "type": "Feature",
  "properties": {
    "addr:full":"752 Vine Ave Coachella CA 92236",
    "addr:housenumber":"752",
    "addr:postcode":"92236",
    "addr:street":"Vine Ave",
    "iso:country":"US",
    "sg:address":"752 Vine Ave",
    "sg:city":"Coachella",
    "sg:classifiers":[
        {
            "category":"Organizations",
            "subcategory":"Non-profit Organization",
            "type":"Services"
        },
        {
            "category":"Health Services",
            "subcategory":"Clinic",
            "type":"Services"
        }
    ],
    "sg:phone":"+1 760 398 4499",
    "sg:postcode":"92236",
    "sg:province":"CA",
    "sg:tags":[
        "information",
        "treatment",
        "specialty",
        "alcoholism",
        "outpatient"
    ],
    "wof:name":"Bill & Bob Alcoholics",
    "wof:placetype":"venue"
},
  "geometry": {"coordinates":[-116.176278,33.680617],"type":"Point"}
}