{
  "type": "Feature",
  "properties": {
    "iso:country":"US",
    "sg:address":"901 E Las Tunas Dr",
    "sg:city":"San Gabriel",
    "sg:classifiers":[
        {
            "category":"Insurance",
            "subcategory":"Insurance Agent",
            "type":"Services"
        }
    ],
    "sg:phone":"+1 626 287 8896",
    "sg:postcode":"91776",
    "sg:province":"CA",
    "wof:name":"Insurance Depot Insurance Svc",
    "wof:placetype":"venue"
},
  "geometry": {"coordinates":[-118.087355,34.103418],"type":"Point"}
}