{
  "type": "Feature",
  "properties": {
    "iso:country":"US",
    "sg:address":"1617 Westcliff Drive",
    "sg:city":"Newport Beach",
    "sg:classifiers":[
        {
            "category":"Community Center",
            "type":"Public Place"
        }
    ],
    "sg:phone":"+1 949 515 4111",
    "sg:postcode":"92660",
    "sg:province":"CA",
    "sg:tags":[
        "medical"
    ],
    "wof:name":"Newport Heights Medical Center",
    "wof:placetype":"venue"
},
  "geometry": {"coordinates":[-117.905704,33.625708],"type":"Point"}
}