{
  "type": "Feature",
  "properties": {
    "addr:full":"2449 88th Ave Oakland CA 94605",
    "addr:housenumber":"2449",
    "addr:postcode":"94605",
    "addr:street":"88Th Ave",
    "iso:country":"US",
    "sg:address":"2449 88th Ave",
    "sg:city":"Oakland",
    "sg:classifiers":[
        {
            "category":"Professional",
            "subcategory":"Engineering",
            "type":"Services"
        }
    ],
    "sg:phone":"+1 510 553 0415",
    "sg:postcode":"94605",
    "sg:province":"CA",
    "sg:tags":[
        "general",
        "contractor"
    ],
    "wof:name":"NBC General Contractors",
    "wof:placetype":"venue"
},
  "geometry": {"coordinates":[-122.162757,37.756915],"type":"Point"}
}