{
  "type": "Feature",
  "properties": {
    "iso:country":"US",
    "sg:address":"830 Eubanks Dr",
    "sg:city":"Vacaville",
    "sg:classifiers":[
        {
            "category":"Manufacturing",
            "subcategory":"Food",
            "type":"Manufacturing & Wholesale Goods"
        }
    ],
    "sg:phone":"+1 707 448 5292",
    "sg:postcode":"95688",
    "sg:province":"CA",
    "sg:tags":[
        "vegetable",
        "fruit"
    ],
    "sg:website":"www.vacavillefruit.com",
    "wof:name":"Vacaville Fruit Co",
    "wof:placetype":"venue"
},
  "geometry": {"coordinates":[-121.954446,38.409633],"type":"Point"}
}