{
  "type": "Feature",
  "properties": {
    "addr:full":"3517 Edison Way Menlo Park CA 94025",
    "addr:housenumber":"3517",
    "addr:postcode":"94025",
    "addr:street":"Edison Way",
    "iso:country":"US",
    "sg:address":"3517 Edison Way",
    "sg:city":"Menlo Park",
    "sg:classifiers":[
        {
            "category":"Professional",
            "subcategory":"Management & Consulting",
            "type":"Services"
        }
    ],
    "sg:phone":"+1 650 298 0900",
    "sg:postcode":"94025",
    "sg:province":"CA",
    "sg:tags":[
        "consultant",
        "sport"
    ],
    "wof:name":"Sports Potential Inc",
    "wof:placetype":"venue"
},
  "geometry": {"coordinates":[-122.19729700000001,37.476542],"type":"Point"}
}