{
  "type": "Feature",
  "properties": {
    "iso:country":"US",
    "sg:address":"1291 E Hillsdale Boulevard",
    "sg:city":"Foster City",
    "sg:classifiers":[
        {
            "category":"Health Services",
            "subcategory":"Dentist",
            "type":"Services"
        }
    ],
    "sg:phone":"+1 650 522 8889",
    "sg:postcode":"94404",
    "sg:province":"CA",
    "wof:name":"Lau Kanson Kwok DDS",
    "wof:placetype":"venue"
},
  "geometry": {"coordinates":[-122.26576799999999,37.569613],"type":"Point"}
}