{
  "type": "Feature",
  "properties": {
    "addr:full":"3355 Alma Ave Lynwood CA 90262",
    "addr:housenumber":"3355",
    "addr:postcode":"90262",
    "addr:street":"Alma Ave",
    "iso:country":"US",
    "sg:address":"3355 Alma Ave",
    "sg:city":"Lynwood",
    "sg:classifiers":[
        {
            "category":"Professional",
            "type":"Services"
        }
    ],
    "sg:phone":"+1 310 537 0115",
    "sg:postcode":"90262",
    "sg:province":"CA",
    "wof:name":"A Valentino",
    "wof:placetype":"venue"
},
  "geometry": {"coordinates":[-118.210615,33.935456],"type":"Point"}
}