{
  "type": "Feature",
  "properties": {
    "addr:full":"1004 N San Fernando Rd Los Angeles CA 90065",
    "addr:housenumber":"1004",
    "addr:postcode":"90065",
    "addr:street":"N San Fernando Rd",
    "iso:country":"US",
    "sg:address":"1004 N San Fernando Rd",
    "sg:city":"Los Angeles",
    "sg:classifiers":[
        {
            "category":"Building & Trades",
            "subcategory":"Electrical",
            "type":"Services"
        }
    ],
    "sg:phone":"+1 323 221 2261",
    "sg:postcode":"90065",
    "sg:province":"CA",
    "sg:tags":[
        "electrical",
        "contractor"
    ],
    "wof:name":"DLT Electric",
    "wof:placetype":"venue"
},
  "geometry": {"coordinates":[-118.228317,34.091865],"type":"Point"}
}