{
  "type": "Feature",
  "properties": {
    "addr:full":"837 W Knoll Dr Los Angeles CA 90069",
    "addr:housenumber":"837",
    "addr:postcode":"90069",
    "addr:street":"W Knoll Dr",
    "iso:country":"US",
    "sg:address":"837 W Knoll Dr",
    "sg:city":"Los Angeles",
    "sg:classifiers":[
        {
            "category":"Real Estate",
            "subcategory":"Real Estate Agent",
            "type":"Services"
        }
    ],
    "sg:phone":"+1 310 659 2611",
    "sg:postcode":"90069",
    "sg:province":"CA",
    "sg:tags":[
        "appraiser"
    ],
    "wof:name":"Lipin & Assoc",
    "wof:placetype":"venue"
},
  "geometry": {"coordinates":[-118.377573,34.086843],"type":"Point"}
}