{
  "type": "Feature",
  "properties": {
    "addr:full":"1600 Lincoln Village Cir Larkspur CA 94939",
    "addr:housenumber":"1600",
    "addr:postcode":"94939",
    "addr:street":"Lincoln Village Cir",
    "iso:country":"US",
    "sg:address":"1600 Lincoln Village Cir",
    "sg:city":"Larkspur",
    "sg:classifiers":[
        {
            "category":"Communications",
            "subcategory":"Film & Video Production",
            "type":"Services"
        }
    ],
    "sg:phone":"+1 415 302 4986",
    "sg:postcode":"94939",
    "sg:province":"CA",
    "sg:tags":[
        "audio"
    ],
    "wof:name":"Nzane Productions",
    "wof:placetype":"venue"
},
  "geometry": {"coordinates":[-122.50441499999999,37.948263],"type":"Point"}
}