{
  "type": "Feature",
  "properties": {
    "addr:full":"5500 Campanile Dr San Diego CA 92182",
    "addr:housenumber":"5500",
    "addr:postcode":"92182",
    "addr:street":"Campanile Dr",
    "iso:country":"US",
    "sg:address":"5500 Campanile Dr",
    "sg:city":"San Diego",
    "sg:classifiers":[
        {
            "category":"Fast Food",
            "type":"Food & Drink"
        }
    ],
    "sg:phone":"+1 619 265 0547",
    "sg:postcode":"92182",
    "sg:province":"CA",
    "sg:tags":[
        "burger"
    ],
    "sg:website":"www.mcdonalds.com",
    "wof:name":"McDonald's",
    "wof:placetype":"venue"
},
  "geometry": {"coordinates":[-117.071665,32.772886],"type":"Point"}
}