{
  "type": "Feature",
  "properties": {
    "addr:full":"2655 Seely Ave San Jose CA 95134",
    "addr:housenumber":"2655",
    "addr:postcode":"95134",
    "addr:street":"Seely Ave",
    "iso:country":"US",
    "sg:address":"2655 Seely Ave",
    "sg:city":"San Jose",
    "sg:classifiers":[
        {
            "category":"Professional",
            "subcategory":"Computer Services",
            "type":"Services"
        }
    ],
    "sg:phone":"+1 408 273 5000",
    "sg:postcode":"95134",
    "sg:province":"CA",
    "sg:tags":[
        "internet"
    ],
    "sg:website":"www.cadence.com",
    "wof:name":"Cadence",
    "wof:placetype":"venue"
},
  "geometry": {"coordinates":[-121.919167,37.396721],"type":"Point"}
}