{
  "type": "Feature",
  "properties": {
    "addr:full":"1994 Flores St Hemet CA 92545",
    "addr:housenumber":"1994",
    "addr:postcode":"92545",
    "addr:street":"Flores St",
    "iso:country":"US",
    "sg:address":"1994 Flores St",
    "sg:city":"Hemet",
    "sg:classifiers":[
        {
            "category":"Building & Trades",
            "subcategory":"Landscaping Services",
            "type":"Services"
        }
    ],
    "sg:phone":"+1 951 658 4137",
    "sg:postcode":"92545",
    "sg:province":"CA",
    "wof:name":"D&N Gardening Service",
    "wof:placetype":"venue"
},
  "geometry": {"coordinates":[-116.99209,33.757177],"type":"Point"}
}