{
  "type": "Feature",
  "properties": {
    "iso:country":"US",
    "sg:address":"2027 W Slauson Ave",
    "sg:city":"Los Angeles",
    "sg:classifiers":[
        {
            "category":"Retail",
            "subcategory":"Auto Repair",
            "type":"Services"
        }
    ],
    "sg:phone":"+1 323 294 8032",
    "sg:postcode":"90047",
    "sg:province":"CA",
    "sg:tags":[
        "repairing",
        "automobile"
    ],
    "wof:name":"Garcia Alvaro",
    "wof:placetype":"venue"
},
  "geometry": {"coordinates":[-118.314383,33.98919],"type":"Point"}
}