{
  "type": "Feature",
  "properties": {
    "addr:full":"1550 Industrial Dr Stockton CA 95206",
    "addr:housenumber":"1550",
    "addr:postcode":"95206",
    "addr:street":"Industrial Dr",
    "iso:country":"US",
    "sg:address":"1550 Industrial Dr",
    "sg:city":"Stockton",
    "sg:classifiers":[
        {
            "category":"Manufacturing",
            "subcategory":"Motor Vehicles & Parts",
            "type":"Manufacturing & Wholesale Goods"
        }
    ],
    "sg:phone":"+1 209 983 6100",
    "sg:postcode":"95206",
    "sg:province":"CA",
    "sg:tags":[
        "mfg"
    ],
    "wof:name":"Dana Stockton Frame Assembly P",
    "wof:placetype":"venue"
},
  "geometry": {"coordinates":[-121.26071399999999,37.910345],"type":"Point"}
}