{
  "type": "Feature",
  "properties": {
    "addr:full":"1685 Cordilleras Rd Redwood City CA 94062",
    "addr:housenumber":"1685",
    "addr:postcode":"94062",
    "addr:street":"Cordilleras Rd",
    "iso:country":"US",
    "sg:address":"1685 Cordilleras Rd",
    "sg:city":"Redwood City",
    "sg:classifiers":[
        {
            "category":"Organizations",
            "subcategory":"Religious Organization",
            "type":"Services"
        }
    ],
    "sg:phone":"+1 650 366 9544",
    "sg:postcode":"94062",
    "sg:province":"CA",
    "sg:tags":[
        "church"
    ],
    "sg:website":"www.stmatthiasparish.org",
    "wof:name":"St Matthias Catholic Church",
    "wof:placetype":"venue"
},
  "geometry": {"coordinates":[-122.261183,37.474373],"type":"Point"}
}