{
  "type": "Feature",
  "properties": {
    "addr:full":"23539 Burbank Blvd Woodland Hills CA 91367",
    "addr:housenumber":"23539",
    "addr:postcode":"91367",
    "addr:street":"Burbank Blvd",
    "iso:country":"US",
    "sg:address":"23539 Burbank Blvd",
    "sg:city":"Woodland Hills",
    "sg:classifiers":[
        {
            "category":"Freight",
            "type":"Transportation"
        }
    ],
    "sg:phone":"+1 818 346 6886",
    "sg:postcode":"91367",
    "sg:province":"CA",
    "sg:tags":[
        "arrangement"
    ],
    "wof:name":"Tour Bookie Inc",
    "wof:placetype":"venue"
},
  "geometry": {"coordinates":[-118.638279,34.171969],"type":"Point"}
}