{
  "type": "Feature",
  "properties": {
    "addr:full":"830 Pocahontas Ct Paso Robles CA 93446",
    "addr:housenumber":"830",
    "addr:postcode":"93446",
    "addr:street":"Pocahontas Ct",
    "iso:country":"US",
    "sg:address":"830 Pocahontas Ct",
    "sg:city":"Paso Robles",
    "sg:classifiers":[
        {
            "category":"Building & Trades",
            "subcategory":"Construction",
            "type":"Services"
        }
    ],
    "sg:phone":"+1 805 610 0898",
    "sg:postcode":"93446",
    "sg:province":"CA",
    "sg:tags":[
        "repairing",
        "remodeling",
        "contractor"
    ],
    "wof:name":"Special Construction Svc",
    "wof:placetype":"venue"
},
  "geometry": {"coordinates":[-120.67406099999999,35.622334],"type":"Point"}
}