{
  "type": "Feature",
  "properties": {
    "iso:country":"US",
    "sg:address":"2904 Tam Oshanter Dr",
    "sg:city":"El Dorado Hills",
    "sg:classifiers":[
        {
            "category":"Social Services",
            "subcategory":"Adult Care",
            "type":"Services"
        }
    ],
    "sg:phone":"+1 916 933 1032",
    "sg:postcode":"95762",
    "sg:province":"CA",
    "sg:tags":[
        "home",
        "residential"
    ],
    "wof:name":"El Dorado Hills Senior Care",
    "wof:placetype":"venue"
},
  "geometry": {"coordinates":[-121.07942,38.689186],"type":"Point"}
}