{
  "type": "Feature",
  "properties": {
    "addr:full":"2165 W Gaylord St Long Beach CA 90813",
    "addr:housenumber":"2165",
    "addr:postcode":"90813",
    "addr:street":"W Gaylord St",
    "iso:country":"US",
    "sg:address":"2165 W Gaylord St",
    "sg:city":"Long Beach",
    "sg:classifiers":[
        {
            "category":"Building & Trades",
            "subcategory":"Construction",
            "type":"Services"
        }
    ],
    "sg:phone":"+1 562 590 4825",
    "sg:postcode":"90813",
    "sg:province":"CA",
    "sg:tags":[
        "contractor"
    ],
    "wof:name":"Roberts Construction",
    "wof:placetype":"venue"
},
  "geometry": {"coordinates":[-118.22124599999999,33.786683],"type":"Point"}
}