{
  "type": "Feature",
  "properties": {
    "iso:country":"US",
    "sg:address":"2400 Washington Ave",
    "sg:city":"Redding",
    "sg:classifiers":[
        {
            "category":"Banks & Credit Unions",
            "subcategory":"Investment Brokerage",
            "type":"Services"
        },
        {
            "category":"Banks & Credit Unions",
            "subcategory":"Financial Services",
            "type":"Services"
        }
    ],
    "sg:phone":"+1 530 243 2234",
    "sg:postcode":"96001",
    "sg:province":"CA",
    "sg:tags":[
        "planning",
        "advisory",
        "retirement",
        "planner"
    ],
    "wof:name":"Fisher Financial Solutions",
    "wof:placetype":"venue"
},
  "geometry": {"coordinates":[-122.37144499999999,40.577578],"type":"Point"}
}