{
  "type": "Feature",
  "properties": {
    "iso:country":"US",
    "sg:address":"4915 Cecilia St",
    "sg:city":"Cudahy",
    "sg:classifiers":[
        {
            "category":"Manufacturing",
            "subcategory":"Tools & Machinery",
            "type":"Manufacturing & Wholesale Goods"
        }
    ],
    "sg:phone":"+1 323 773 3469",
    "sg:postcode":"90201",
    "sg:province":"CA",
    "sg:tags":[
        "cutting",
        "wire"
    ],
    "wof:name":"Artsons Manufacturing Co",
    "wof:placetype":"venue"
},
  "geometry": {"coordinates":[-118.180032,33.958057],"type":"Point"}
}