{
  "type": "Feature",
  "properties": {
    "iso:country":"US",
    "sg:address":"3395 E 19th St",
    "sg:city":"Signal Hill",
    "sg:classifiers":[
        {
            "category":"Wholesale",
            "subcategory":"Machinery & Supplies",
            "type":"Manufacturing & Wholesale Goods"
        }
    ],
    "sg:phone":"+1 562 986 5238",
    "sg:postcode":"90755",
    "sg:province":"CA",
    "sg:tags":[
        "glass",
        "tank",
        "plastic"
    ],
    "sg:website":"www.core-rosion.com",
    "wof:name":"Core-Rosion Products",
    "wof:placetype":"venue"
},
  "geometry": {"coordinates":[-118.15133,33.791672],"type":"Point"}
}