{
  "type": "Feature",
  "properties": {
    "addr:full":"3200 E 1st St Los Angeles CA 90063",
    "addr:housenumber":"3200",
    "addr:postcode":"90063",
    "addr:street":"E 1St St",
    "iso:country":"US",
    "sg:address":"3200 E 1st St",
    "sg:city":"Los Angeles",
    "sg:classifiers":[
        {
            "category":"Food & Beverages",
            "subcategory":"Liquor & Beverages",
            "type":"Retail Goods"
        }
    ],
    "sg:phone":"+1 323 266 1300",
    "sg:postcode":"90063",
    "sg:province":"CA",
    "wof:name":"Xocaitls Liquor Store",
    "wof:placetype":"venue"
},
  "geometry": {"coordinates":[-118.196679,34.037887],"type":"Point"}
}