{
  "type": "Feature",
  "properties": {
    "addr:full":"1433 N Central Park Ave W Anaheim CA 92802",
    "addr:housenumber":"1433",
    "addr:postcode":"92802",
    "addr:street":"N Central Park Ave W",
    "iso:country":"US",
    "sg:address":"1433 N Central Park Ave W",
    "sg:city":"Anaheim",
    "sg:classifiers":[
        {
            "category":"Retail",
            "subcategory":"Auto Repair",
            "type":"Services"
        }
    ],
    "sg:phone":"+1 714 772 2040",
    "sg:postcode":"92802",
    "sg:province":"CA",
    "sg:tags":[
        "automobile",
        "top",
        "upholstery"
    ],
    "wof:name":"Barnes Upholstery Inc",
    "wof:placetype":"venue"
},
  "geometry": {"coordinates":[-117.931815,33.827246],"type":"Point"}
}