{
  "type": "Feature",
  "properties": {
    "addr:full":"1013 Monterey St San Luis Obispo CA 93401",
    "addr:housenumber":"1013",
    "addr:postcode":"93401",
    "addr:street":"Monterey St",
    "iso:country":"US",
    "sg:address":"1013 Monterey St",
    "sg:city":"San Luis Obispo",
    "sg:classifiers":[
        {
            "category":"Organizations",
            "subcategory":"Community Association",
            "type":"Services"
        }
    ],
    "sg:phone":"+1 805 781 9932",
    "sg:postcode":"93401",
    "sg:province":"CA",
    "sg:tags":[
        "environmental",
        "org"
    ],
    "wof:name":"Environment In The Public",
    "wof:placetype":"venue"
},
  "geometry": {"coordinates":[-120.660038,35.28242],"type":"Point"}
}