{
  "type": "Feature",
  "properties": {
    "addr:full":"1265 S Bascom Ave San Jose CA 95128",
    "addr:housenumber":"1265",
    "addr:postcode":"95128",
    "addr:street":"S Bascom Ave",
    "iso:country":"US",
    "sg:address":"1265 S Bascom Ave",
    "sg:city":"San Jose",
    "sg:classifiers":[
        {
            "category":"Professional",
            "subcategory":"Research",
            "type":"Services"
        }
    ],
    "sg:phone":"+1 408 732 9507",
    "sg:postcode":"95128",
    "sg:province":"CA",
    "sg:tags":[
        "development",
        "laboratory"
    ],
    "wof:name":"Dzu Technology",
    "wof:placetype":"venue"
},
  "geometry": {"coordinates":[-121.93179600000001,37.303235],"type":"Point"}
}