{
  "type": "Feature",
  "properties": {
    "iso:country":"US",
    "sg:address":"20 Post Street",
    "sg:city":"San Jose",
    "sg:classifiers":[
        {
            "category":"Professional",
            "subcategory":"Printing & Photocopies",
            "type":"Services"
        }
    ],
    "sg:phone":"+1 408 292 2679",
    "sg:postcode":"95113",
    "sg:province":"CA",
    "sg:website":"precisiondocuments.com",
    "wof:name":"Precision Document Services",
    "wof:placetype":"venue"
},
  "geometry": {"coordinates":[-121.89022900000001,37.335113],"type":"Point"}
}