{
  "type": "Feature",
  "properties": {
    "iso:country":"US",
    "sg:address":"2974 S Norfolk St",
    "sg:city":"San Mateo",
    "sg:classifiers":[
        {
            "category":"Food & Beverages",
            "subcategory":"Groceries & Convenience Stores",
            "type":"Retail Goods"
        }
    ],
    "sg:phone":"+1 650 571 8679",
    "sg:postcode":"94403",
    "sg:province":"CA",
    "sg:tags":[
        "mexican"
    ],
    "wof:name":"Taqueria De Amigos",
    "wof:placetype":"venue"
},
  "geometry": {"coordinates":[-122.283997,37.545399],"type":"Point"}
}