{
  "type": "Feature",
  "properties": {
    "iso:country":"US",
    "sg:address":"8925 N Sepulveda Blvd",
    "sg:city":"North Hills",
    "sg:classifiers":[
        {
            "category":"Education",
            "subcategory":"Special Training",
            "type":"Public Place"
        }
    ],
    "sg:phone":"+1 818 892 5534",
    "sg:postcode":"91343",
    "sg:province":"CA",
    "sg:tags":[
        "educational"
    ],
    "wof:name":"A Plus Educational",
    "wof:placetype":"venue"
},
  "geometry": {"coordinates":[-118.467769,34.23501],"type":"Point"}
}