{
  "type": "Feature",
  "properties": {
    "addr:full":"3283 Cessna Dr Shingle Springs CA 95682",
    "addr:housenumber":"3283",
    "addr:postcode":"95682",
    "addr:street":"Cessna Dr",
    "iso:country":"US",
    "sg:address":"3283 Cessna Dr",
    "sg:city":"Shingle Springs",
    "sg:classifiers":[
        {
            "category":"Wholesale",
            "subcategory":"Chemicals & Plastics",
            "type":"Manufacturing & Wholesale Goods"
        }
    ],
    "sg:phone":"+1 530 677 3511",
    "sg:postcode":"95682",
    "sg:province":"CA",
    "wof:name":"Mainey Distributing Inc",
    "wof:placetype":"venue"
},
  "geometry": {"coordinates":[-120.983662,38.677776],"type":"Point"}
}