{
  "type": "Feature",
  "properties": {
    "iso:country":"US",
    "sg:address":"4030 South Land Park Dr.,Suite F",
    "sg:city":"Sacramento",
    "sg:classifiers":[
        {
            "category":"Personal",
            "subcategory":"Massage",
            "type":"Services"
        },
        {
            "category":"Health Services",
            "subcategory":"Nursing And Care Facility",
            "type":"Services"
        },
        {
            "category":"Health Services",
            "subcategory":"Health Practitioner",
            "type":"Services"
        },
        {
            "category":"Personal",
            "subcategory":"Skin Care",
            "type":"Services"
        }
    ],
    "sg:phone":"+1 916 233 9248",
    "sg:postcode":"95822",
    "sg:province":"CA",
    "sg:tags":[
        "management",
        "pain",
        "aromatherapy",
        "therapist",
        "medicine",
        "alternative"
    ],
    "wof:name":"Victoria's Skin Care & Spa",
    "wof:placetype":"venue"
},
  "geometry": {"coordinates":[-121.504043,38.537229],"type":"Point"}
}