{
  "type": "Feature",
  "properties": {
    "iso:country":"US",
    "sg:address":"55 Second Street",
    "sg:city":"San Francisco",
    "sg:classifiers":[
        {
            "category":"Parking",
            "type":"Transportation"
        }
    ],
    "sg:postcode":"94105",
    "sg:province":"CA",
    "sg:website":"www.hines.com/property/detail.as...",
    "wof:name":"KPMG Building",
    "wof:placetype":"venue"
},
  "geometry": {"coordinates":[-122.400538,37.788616],"type":"Point"}
}