{
  "type": "Feature",
  "properties": {
    "addr:full":"637 E Rainier Ave Orange CA 92865",
    "addr:housenumber":"637",
    "addr:postcode":"92865",
    "addr:street":"E Rainier Ave",
    "iso:country":"US",
    "sg:address":"637 E Rainier Ave",
    "sg:city":"Orange",
    "sg:classifiers":[
        {
            "category":"Professional",
            "subcategory":"Lawyer & Legal Services",
            "type":"Services"
        }
    ],
    "sg:phone":"+1 951 808 0004",
    "sg:postcode":"92865",
    "sg:province":"CA",
    "wof:name":"Legal Services",
    "wof:placetype":"venue"
},
  "geometry": {"coordinates":[-117.845793,33.843064],"type":"Point"}
}