{
  "type": "Feature",
  "properties": {
    "addr:full":"4020 E Main St Ventura CA 93003",
    "addr:housenumber":"4020",
    "addr:postcode":"93003",
    "addr:street":"E Main St",
    "iso:country":"US",
    "sg:address":"4020 E Main St",
    "sg:city":"Ventura",
    "sg:classifiers":[
        {
            "category":"Food & Beverages",
            "subcategory":"Bakery",
            "type":"Retail Goods"
        }
    ],
    "sg:phone":"+1 805 642 4524",
    "sg:postcode":"93003",
    "sg:province":"CA",
    "sg:tags":[
        "baker"
    ],
    "wof:name":"Orowheat",
    "wof:placetype":"venue"
},
  "geometry": {"coordinates":[-119.238145,34.263092],"type":"Point"}
}