{
  "type": "Feature",
  "properties": {
    "addr:full":"1707 Fulton St Fresno CA 93721",
    "addr:housenumber":"1707",
    "addr:postcode":"93721",
    "addr:street":"Fulton St",
    "iso:country":"US",
    "sg:address":"1707 Fulton St",
    "sg:city":"Fresno",
    "sg:classifiers":[
        {
            "category":"Arts & Performance",
            "subcategory":"Theater",
            "type":"Entertainment"
        }
    ],
    "sg:phone":"+1 559 237 1399",
    "sg:postcode":"93721",
    "sg:province":"CA",
    "sg:tags":[
        "clown"
    ],
    "wof:name":"Estrellitas's Entertainment",
    "wof:placetype":"venue"
},
  "geometry": {"coordinates":[-119.798852,36.741725],"type":"Point"}
}