{
  "type": "Feature",
  "properties": {
    "iso:country":"US",
    "sg:address":"1112 Cadillac Court",
    "sg:city":"Milpitas",
    "sg:classifiers":[
        {
            "category":"Health Services",
            "subcategory":"Dentist",
            "type":"Services"
        }
    ],
    "sg:phone":"+1 408 586 8847",
    "sg:postcode":"95035",
    "sg:province":"CA",
    "wof:name":"Perlita Tongol Matute DMD Inc.",
    "wof:placetype":"venue"
},
  "geometry": {"coordinates":[-121.918859,37.445355],"type":"Point"}
}