{
  "type": "Feature",
  "properties": {
    "addr:full":"493 Forbes Blvd S San Francisco CA 94080",
    "addr:housenumber":"493",
    "addr:postcode":"94080",
    "addr:street":"Forbes Blvd S",
    "iso:country":"US",
    "sg:address":"493 Forbes Blvd",
    "sg:city":"S San Francisco",
    "sg:classifiers":[
        {
            "category":"Wholesale",
            "subcategory":"Meat",
            "type":"Manufacturing & Wholesale Goods"
        }
    ],
    "sg:phone":"+1 650 745 2360",
    "sg:postcode":"94080",
    "sg:province":"CA",
    "sg:tags":[
        "prod",
        "plant",
        "prepared",
        "packing",
        "mfg"
    ],
    "wof:name":"San Francisco Sausage Co Inc",
    "wof:placetype":"venue"
},
  "geometry": {"coordinates":[-122.39247899999999,37.656773],"type":"Point"}
}