{
  "type": "Feature",
  "properties": {
    "iso:country":"US",
    "sg:address":"1310 Westlyn Pl",
    "sg:city":"Pasadena",
    "sg:classifiers":[
        {
            "category":"Building & Trades",
            "subcategory":"Construction",
            "type":"Services"
        }
    ],
    "sg:phone":"+1 626 797 0432",
    "sg:postcode":"91104",
    "sg:province":"CA",
    "sg:tags":[
        "residential",
        "nonresidential"
    ],
    "wof:name":"A & L Construction",
    "wof:placetype":"venue"
},
  "geometry": {"coordinates":[-118.104589,34.168434],"type":"Point"}
}