{
  "type": "Feature",
  "properties": {
    "iso:country":"US",
    "sg:address":"400 W 7th St",
    "sg:city":"Los Angeles",
    "sg:classifiers":[
        {
            "category":"Wholesale",
            "subcategory":"Jewelry",
            "type":"Manufacturing & Wholesale Goods"
        }
    ],
    "sg:phone":"+1 213 622 2518",
    "sg:postcode":"90014",
    "sg:province":"CA",
    "sg:tags":[
        "jeweler"
    ],
    "wof:name":"Bingo Jewelry Plaza",
    "wof:placetype":"venue"
},
  "geometry": {"coordinates":[-118.254985,34.046254],"type":"Point"}
}