{
  "type": "Feature",
  "properties": {
    "iso:country":"US",
    "sg:address":"17185 Pacato Ct",
    "sg:city":"San Diego",
    "sg:classifiers":[
        {
            "category":"Banks & Credit Unions",
            "subcategory":"Financial Services",
            "type":"Services"
        }
    ],
    "sg:phone":"+1 858 592 7229",
    "sg:postcode":"92128",
    "sg:province":"CA",
    "sg:tags":[
        "trust",
        "management"
    ],
    "wof:name":"Pierce Family Decendents Trust",
    "wof:placetype":"venue"
},
  "geometry": {"coordinates":[-117.056093,33.021826],"type":"Point"}
}