{
  "type": "Feature",
  "properties": {
    "addr:full":"7117 W Manchester Ave Los Angeles CA 90045",
    "addr:housenumber":"7117",
    "addr:postcode":"90045",
    "addr:street":"W Manchester Ave",
    "iso:country":"US",
    "sg:address":"7117 W Manchester Ave",
    "sg:city":"Los Angeles",
    "sg:classifiers":[
        {
            "category":"Shopping",
            "subcategory":"Computers & Home Electronics",
            "type":"Retail Goods"
        },
        {
            "category":"Building & Trades",
            "subcategory":"Construction",
            "type":"Services"
        }
    ],
    "sg:phone":"+1 310 645 7226",
    "sg:postcode":"90045",
    "sg:province":"CA",
    "sg:tags":[
        "installation",
        "theatre",
        "contractor"
    ],
    "wof:name":"The Hunter Group",
    "wof:placetype":"venue"
},
  "geometry": {"coordinates":[-118.417,33.959801],"type":"Point"}
}