{
  "type": "Feature",
  "properties": {
    "iso:country":"US",
    "sg:address":"45459 Industrial Pl",
    "sg:city":"Fremont",
    "sg:classifiers":[
        {
            "category":"Retail",
            "subcategory":"Repair Shop",
            "type":"Services"
        }
    ],
    "sg:phone":"+1 510 657 3001",
    "sg:postcode":"94538",
    "sg:province":"CA",
    "sg:tags":[
        "welding"
    ],
    "wof:name":"Weld Co Engineering",
    "wof:placetype":"venue"
},
  "geometry": {"coordinates":[-121.950321,37.496133],"type":"Point"}
}