{
  "type": "Feature",
  "properties": {
    "addr:full":"2316 Haste St Berkeley CA 94704",
    "addr:postcode":"2316;94704",
    "addr:street":"Haste St",
    "iso:country":"US",
    "sg:address":"2316 Haste St",
    "sg:city":"Berkeley",
    "sg:classifiers":[
        {
            "category":"Real Estate",
            "subcategory":"Real Estate Operator",
            "type":"Services"
        }
    ],
    "sg:phone":"+1 510 549 2094",
    "sg:postcode":"94704",
    "sg:province":"CA",
    "sg:tags":[
        "apartment"
    ],
    "wof:name":"Evans Manor",
    "wof:placetype":"venue"
},
  "geometry": {"coordinates":[-122.262417,37.865546],"type":"Point"}
}