{
  "type": "Feature",
  "properties": {
    "addr:full":"10006 National Blvd Los Angeles CA 90034",
    "addr:housenumber":"10006",
    "addr:postcode":"90034",
    "addr:street":"National Blvd",
    "iso:country":"US",
    "sg:address":"10006 National Blvd",
    "sg:city":"Los Angeles",
    "sg:classifiers":[
        {
            "category":"Restaurant",
            "type":"Food & Drink"
        }
    ],
    "sg:phone":"+1 310 837 4462",
    "sg:postcode":"90034",
    "sg:province":"CA",
    "sg:tags":[
        "pizza"
    ],
    "wof:name":"The Coop Pizza",
    "wof:placetype":"venue"
},
  "geometry": {"coordinates":[-118.403999,34.029202],"type":"Point"}
}