{
  "type": "Feature",
  "properties": {
    "addr:full":"1550 5th St Santa Monica CA 90401",
    "addr:housenumber":"1550",
    "addr:postcode":"90401",
    "addr:street":"5Th St",
    "iso:country":"US",
    "sg:address":"1550 5th St",
    "sg:city":"Santa Monica",
    "sg:classifiers":[
        {
            "category":"Retail",
            "subcategory":"Auto Repair",
            "type":"Services"
        }
    ],
    "sg:phone":"+1 310 451 5773",
    "sg:postcode":"90401",
    "sg:province":"CA",
    "sg:tags":[
        "body",
        "automobile",
        "painting"
    ],
    "wof:name":"Royalty Autobody & Detail",
    "wof:placetype":"venue"
},
  "geometry": {"coordinates":[-118.491924,34.015201],"type":"Point"}
}