{
  "type": "Feature",
  "properties": {
    "addr:full":"6 Tice Valley Ln Walnut Creek CA 94595",
    "addr:housenumber":"6",
    "addr:postcode":"94595",
    "addr:street":"Tice Valley Ln",
    "iso:country":"US",
    "sg:address":"6 Tice Valley Ln",
    "sg:city":"Walnut Creek",
    "sg:classifiers":[
        {
            "category":"Retail",
            "subcategory":"Portrait Studio",
            "type":"Services"
        }
    ],
    "sg:phone":"+1 925 939 1330",
    "sg:postcode":"94595",
    "sg:province":"CA",
    "sg:tags":[
        "photo"
    ],
    "wof:name":"Chris Scott Photography",
    "wof:placetype":"venue"
},
  "geometry": {"coordinates":[-122.06633100000001,37.876585],"type":"Point"}
}