{
  "type": "Feature",
  "properties": {
    "addr:full":"4299 Macarthur Blvd Newport Beach CA 92660",
    "addr:housenumber":"4299",
    "addr:postcode":"92660",
    "addr:street":"Macarthur Blvd",
    "iso:country":"US",
    "sg:address":"4299 Macarthur Blvd",
    "sg:city":"Newport Beach",
    "sg:classifiers":[
        {
            "category":"Banks & Credit Unions",
            "subcategory":"Bank",
            "type":"Services"
        }
    ],
    "sg:phone":"+1 949 222 4444",
    "sg:postcode":"92660",
    "sg:province":"CA",
    "sg:tags":[
        "loan"
    ],
    "sg:website":"www.theallianceportfolio.com",
    "wof:name":"Alliance Portfolio",
    "wof:placetype":"venue"
},
  "geometry": {"coordinates":[-117.863815,33.664246],"type":"Point"}
}