{
  "type": "Feature",
  "properties": {
    "addr:full":"125 Riverview Dr Boulder Creek CA 95006",
    "addr:housenumber":"125",
    "addr:postcode":"95006",
    "addr:street":"Riverview Dr",
    "iso:country":"US",
    "sg:address":"125 Riverview Dr",
    "sg:city":"Boulder Creek",
    "sg:classifiers":[
        {
            "category":"Professional",
            "subcategory":"Art Services",
            "type":"Services"
        }
    ],
    "sg:phone":"+1 831 338 6075",
    "sg:postcode":"95006",
    "sg:province":"CA",
    "sg:tags":[
        "graphic",
        "designer"
    ],
    "wof:name":"Mc Cormick Design",
    "wof:placetype":"venue"
},
  "geometry": {"coordinates":[-122.13352399999999,37.15737],"type":"Point"}
}