{
  "type": "Feature",
  "properties": {
    "addr:full":"5413 Redwood St San Diego CA 92105",
    "addr:housenumber":"5413",
    "addr:postcode":"92105",
    "addr:street":"Redwood St",
    "iso:country":"US",
    "sg:address":"5413 Redwood St",
    "sg:city":"San Diego",
    "sg:classifiers":[
        {
            "category":"Restaurant",
            "type":"Food & Drink"
        }
    ],
    "sg:phone":"+1 619 795 2333",
    "sg:postcode":"92105",
    "sg:province":"CA",
    "sg:tags":[
        "mexican"
    ],
    "wof:name":"Cuco's Taco Shop",
    "wof:placetype":"venue"
},
  "geometry": {"coordinates":[-117.078951,32.737682],"type":"Point"}
}