{
  "type": "Feature",
  "properties": {
    "iso:country":"US",
    "sg:address":"5263 A Claremont Ave",
    "sg:city":"Oakland",
    "sg:classifiers":[
        {
            "category":"Insurance",
            "subcategory":"Hazard Insurance",
            "type":"Services"
        }
    ],
    "sg:phone":"+1 510 228 4449",
    "sg:postcode":"94618",
    "sg:province":"CA",
    "sg:website":"oaklandcainsurances.com?d=040520...",
    "wof:name":"Ozwald & Speakar Insurance Services, Inc",
    "wof:placetype":"venue"
},
  "geometry": {"coordinates":[-122.261349,37.838928],"type":"Point"}
}