{
  "type": "Feature",
  "properties": {
    "iso:country":"US",
    "sg:address":"6105 Pso Delicias",
    "sg:city":"Rancho Santa Fe",
    "sg:classifiers":[
        {
            "category":"Professional",
            "subcategory":"Lawyer & Legal Services",
            "type":"Services"
        }
    ],
    "sg:phone":"+1 858 756 3707",
    "sg:postcode":"92067",
    "sg:province":"CA",
    "sg:tags":[
        "attorney"
    ],
    "wof:name":"Richard Showen Attorney-Law",
    "wof:placetype":"venue"
},
  "geometry": {"coordinates":[-117.201325,33.021352],"type":"Point"}
}