{
  "type": "Feature",
  "properties": {
    "addr:full":"300 S Cedar Ave Rialto CA 92376",
    "addr:housenumber":"300",
    "addr:postcode":"92376",
    "addr:street":"S Cedar Ave",
    "iso:country":"US",
    "sg:address":"300 S Cedar Ave",
    "sg:city":"Rialto",
    "sg:classifiers":[
        {
            "category":"Manufacturing",
            "subcategory":"Metals",
            "type":"Manufacturing & Wholesale Goods"
        }
    ],
    "sg:phone":"+1 909 820 6827",
    "sg:postcode":"92376",
    "sg:province":"CA",
    "sg:tags":[
        "plate",
        "work",
        "fabricated",
        "mfg"
    ],
    "wof:name":"Afab Tech LLC",
    "wof:placetype":"venue"
},
  "geometry": {"coordinates":[-117.39654299999999,34.094246],"type":"Point"}
}