{
  "type": "Feature",
  "properties": {
    "addr:full":"2818 W 5th St Santa Ana CA 92703",
    "addr:housenumber":"2818",
    "addr:postcode":"92703",
    "addr:street":"W 5Th St",
    "iso:country":"US",
    "sg:address":"2818 W 5th St",
    "sg:city":"Santa Ana",
    "sg:classifiers":[
        {
            "category":"Bus Charters",
            "type":"Transportation"
        }
    ],
    "sg:phone":"+1 714 542 8989",
    "sg:postcode":"92703",
    "sg:province":"CA",
    "sg:tags":[
        "rental"
    ],
    "sg:website":"www.durhamschoolservices.com",
    "wof:name":"Durham Transportation",
    "wof:placetype":"venue"
},
  "geometry": {"coordinates":[-117.908023,33.74883],"type":"Point"}
}