{
  "type": "Feature",
  "properties": {
    "iso:country":"US",
    "sg:address":"19503 Red Feather Rd",
    "sg:city":"Apple Valley",
    "sg:classifiers":[
        {
            "category":"Building & Trades",
            "subcategory":"Plumbing",
            "type":"Services"
        }
    ],
    "sg:phone":"+1 760 242 5807",
    "sg:postcode":"92307",
    "sg:province":"CA",
    "sg:tags":[
        "plumbing",
        "contractor"
    ],
    "wof:name":"Flynn's Plumbing",
    "wof:placetype":"venue"
},
  "geometry": {"coordinates":[-117.238932,34.51352],"type":"Point"}
}