{
  "type": "Feature",
  "properties": {
    "addr:full":"27727 Jefferson Ave Temecula CA 92562",
    "addr:housenumber":"27727",
    "addr:postcode":"92562",
    "addr:street":"Jefferson Ave",
    "iso:country":"US",
    "sg:address":"27727 Jefferson Ave",
    "sg:city":"Temecula",
    "sg:classifiers":[
        {
            "category":"Banks & Credit Unions",
            "subcategory":"Bank",
            "type":"Services"
        }
    ],
    "sg:phone":"+1 951 699 7450",
    "sg:postcode":"92562",
    "sg:province":"CA",
    "sg:tags":[
        "loan",
        "real estate"
    ],
    "wof:name":"American Funding Ctr",
    "wof:placetype":"venue"
},
  "geometry": {"coordinates":[-117.157971,33.511113],"type":"Point"}
}