{
  "type": "Feature",
  "properties": {
    "iso:country":"US",
    "sg:address":"686 E Bullard Ave",
    "sg:city":"Fresno",
    "sg:classifiers":[
        {
            "category":"Sports & Exercise",
            "subcategory":"Gym",
            "type":"Entertainment"
        }
    ],
    "sg:phone":"+1 559 431 3600",
    "sg:postcode":"93710",
    "sg:province":"CA",
    "sg:tags":[
        "club",
        "health",
        "studio",
        "gymnasium"
    ],
    "wof:name":"Rhonda's Personal Training",
    "wof:placetype":"venue"
},
  "geometry": {"coordinates":[-119.77242099999999,36.823116],"type":"Point"}
}