{
  "type": "Feature",
  "properties": {
    "iso:country":"US",
    "sg:address":"10410 Dale St",
    "sg:city":"Stanton",
    "sg:classifiers":[
        {
            "category":"Real Estate",
            "subcategory":"Real Estate Operator",
            "type":"Services"
        }
    ],
    "sg:phone":"+1 714 828 3725",
    "sg:postcode":"90680",
    "sg:province":"CA",
    "sg:tags":[
        "apartment",
        "complex"
    ],
    "wof:name":"Dale Village Apartments",
    "wof:placetype":"venue"
},
  "geometry": {"coordinates":[-117.984451,33.810422],"type":"Point"}
}