{
  "type": "Feature",
  "properties": {
    "iso:country":"US",
    "sg:address":"3319 Seldon Ct",
    "sg:city":"Fremont",
    "sg:classifiers":[
        {
            "category":"Building & Trades",
            "subcategory":"Construction",
            "type":"Services"
        }
    ],
    "sg:phone":"+1 510 656 8020",
    "sg:postcode":"94539",
    "sg:province":"CA",
    "sg:tags":[
        "painter"
    ],
    "wof:name":"Satellite Painting Inc",
    "wof:placetype":"venue"
},
  "geometry": {"coordinates":[-121.946302,37.518999],"type":"Point"}
}