{
  "type": "Feature",
  "properties": {
    "addr:full":"2340 Crestmoor Dr San Bruno CA 94066",
    "addr:postcode":"2340;94066",
    "addr:street":"Crestmoor Dr",
    "iso:country":"US",
    "sg:address":"2340 Crestmoor Dr",
    "sg:city":"San Bruno",
    "sg:classifiers":[
        {
            "category":"Building & Trades",
            "subcategory":"Construction",
            "type":"Services"
        }
    ],
    "sg:phone":"+1 650 692 1822",
    "sg:postcode":"94066",
    "sg:province":"CA",
    "sg:tags":[
        "home",
        "improvement"
    ],
    "wof:name":"Michael J Meyer",
    "wof:placetype":"venue"
},
  "geometry": {"coordinates":[-122.432714,37.625013],"type":"Point"}
}