{
  "type": "Feature",
  "properties": {
    "addr:full":"1757 Cecil Ave Delano CA 93215",
    "addr:housenumber":"1757",
    "addr:postcode":"93215",
    "addr:street":"Cecil Ave",
    "iso:country":"US",
    "sg:address":"1757 Cecil Ave",
    "sg:city":"Delano",
    "sg:classifiers":[
        {
            "category":"Restaurant",
            "type":"Food & Drink"
        }
    ],
    "sg:phone":"+1 661 725 0122",
    "sg:postcode":"93215",
    "sg:province":"CA",
    "sg:tags":[
        "delicatessen"
    ],
    "wof:name":"Bans Deli Market",
    "wof:placetype":"venue"
},
  "geometry": {"coordinates":[-119.232533,35.775938],"type":"Point"}
}