{
  "type": "Feature",
  "properties": {
    "iso:country":"US",
    "sg:address":"63 Bluxome St",
    "sg:city":"San Francisco",
    "sg:classifiers":[
        {
            "category":"Professional",
            "type":"Services"
        }
    ],
    "sg:phone":"+1 415 243 8050",
    "sg:postcode":"94107",
    "sg:province":"CA",
    "sg:tags":[
        "arts",
        "artist"
    ],
    "wof:name":"Evri Kwong",
    "wof:placetype":"venue"
},
  "geometry": {"coordinates":[-122.396803,37.776999],"type":"Point"}
}