{
  "type": "Feature",
  "properties": {
    "addr:full":"63 Bluxome St San Francisco CA 94107",
    "addr:housenumber":"63",
    "addr:postcode":"94107",
    "addr:street":"Bluxome St",
    "iso:country":"US",
    "sg:address":"63 Bluxome St",
    "sg:city":"San Francisco",
    "sg:classifiers":[
        {
            "category":"Professional",
            "type":"Services"
        }
    ],
    "sg:phone":"+1 415 243 8050",
    "sg:postcode":"94107",
    "sg:province":"CA",
    "sg:tags":[
        "arts",
        "artist"
    ],
    "wof:name":"Evri Kwong",
    "wof:placetype":"venue"
},
  "geometry": {"coordinates":[-122.39680300000001,37.776999],"type":"Point"}
}