{
  "type": "Feature",
  "properties": {
    "addr:full":"3996 Pony Tail Ln Shingle Springs CA 95682",
    "addr:housenumber":"3996",
    "addr:postcode":"95682",
    "addr:street":"Pony Tail Ln",
    "iso:country":"US",
    "sg:address":"3996 Pony Tail Ln",
    "sg:city":"Shingle Springs",
    "sg:classifiers":[
        {
            "category":"Manufacturing",
            "subcategory":"Printing",
            "type":"Manufacturing & Wholesale Goods"
        }
    ],
    "sg:phone":"+1 530 672 8499",
    "sg:postcode":"95682",
    "sg:province":"CA",
    "sg:tags":[
        "screen"
    ],
    "wof:name":"Key Screen Printing",
    "wof:placetype":"venue"
},
  "geometry": {"coordinates":[-120.94176899999999,38.659303],"type":"Point"}
}