{
  "type": "Feature",
  "properties": {
    "iso:country":"US",
    "sg:address":"1011 W Olive Ave",
    "sg:city":"Burbank",
    "sg:classifiers":[
        {
            "category":"Wholesale",
            "subcategory":"Metals & Minerals",
            "type":"Manufacturing & Wholesale Goods"
        }
    ],
    "sg:phone":"+1 818 840 9765",
    "sg:postcode":"91506",
    "sg:province":"CA",
    "sg:tags":[
        "wire"
    ],
    "wof:name":"Systems Solutions",
    "wof:placetype":"venue"
},
  "geometry": {"coordinates":[-118.318651,34.17156],"type":"Point"}
}