{
  "type": "Feature",
  "properties": {
    "addr:full":"1015 El Camino Real at Westbourough Blvd South San Francisco CA 94080",
    "addr:housenumber":"1015",
    "addr:postcode":"94080",
    "addr:street":"El Camino Real;Blvd",
    "iso:country":"US",
    "sg:address":"1015 El Camino Real at Westbourough Blvd",
    "sg:city":"South San Francisco",
    "sg:classifiers":[
        {
            "category":"Food & Beverages",
            "subcategory":"Groceries & Convenience Stores",
            "type":"Retail Goods"
        }
    ],
    "sg:postcode":"94080",
    "sg:province":"CA",
    "wof:name":"Pacific Market",
    "wof:placetype":"venue"
},
  "geometry": {"coordinates":[-122.43489700000001,37.655436],"type":"Point"}
}