{
  "type": "Feature",
  "properties": {
    "addr:full":"1107 W March Ln Stockton CA 95207",
    "addr:housenumber":"1107",
    "addr:postcode":"95207",
    "addr:street":"W March Ln",
    "iso:country":"US",
    "sg:address":"1107 W March Ln",
    "sg:city":"Stockton",
    "sg:classifiers":[
        {
            "category":"Restaurant",
            "type":"Food & Drink"
        }
    ],
    "sg:menulink":"http://www.allmenus.com/ca/stockton/164111-wienerschnitzel/menu/",
    "sg:phone":"+1 209 473 1686",
    "sg:postcode":"95207",
    "sg:province":"CA",
    "sg:tags":[
        "sandwich",
        "dog",
        "burger",
        "hot",
        "wrap",
        "american"
    ],
    "wof:name":"Wienerschnitzel",
    "wof:placetype":"venue"
},
  "geometry": {"coordinates":[-121.31868,37.9899],"type":"Point"}
}