{
  "type": "Feature",
  "properties": {
    "addr:full":"1875 Arnold Dr Martinez CA 94553",
    "addr:housenumber":"1875",
    "addr:postcode":"94553",
    "addr:street":"Arnold Dr",
    "iso:country":"US",
    "sg:address":"1875 Arnold Dr",
    "sg:city":"Martinez",
    "sg:classifiers":[
        {
            "category":"Banks & Credit Unions",
            "subcategory":"Bank",
            "type":"Services"
        }
    ],
    "sg:phone":"+1 925 370 9200",
    "sg:postcode":"94553",
    "sg:province":"CA",
    "wof:name":"IBEW Members & Credit Union",
    "wof:placetype":"venue"
},
  "geometry": {"coordinates":[-122.088531,37.991552],"type":"Point"}
}