{
  "type": "Feature",
  "properties": {
    "iso:country":"US",
    "sg:address":"1001 N Palm St",
    "sg:city":"Turlock",
    "sg:classifiers":[
        {
            "category":"Health Services",
            "subcategory":"Chiropractor",
            "type":"Services"
        }
    ],
    "sg:phone":"+1 209 668 7100",
    "sg:postcode":"95380",
    "sg:province":"CA",
    "wof:name":"Cornerstone Natrl Health Ctr",
    "wof:placetype":"venue"
},
  "geometry": {"coordinates":[-120.846529,37.502407],"type":"Point"}
}