{
  "type": "Feature",
  "properties": {
    "addr:full":"1287 Lincoln Ave San Diego CA 92103",
    "addr:housenumber":"1287",
    "addr:postcode":"92103",
    "addr:street":"Lincoln Ave",
    "iso:country":"US",
    "sg:address":"1287 Lincoln Ave",
    "sg:city":"San Diego",
    "sg:classifiers":[
        {
            "category":"Arts & Performance",
            "subcategory":"Art Gallery",
            "type":"Entertainment"
        }
    ],
    "sg:phone":"+1 619 992 8666",
    "sg:postcode":"92103",
    "sg:province":"CA",
    "sg:website":"members.cox.net/darbyart/index.html",
    "wof:name":"Darbyart",
    "wof:placetype":"venue"
},
  "geometry": {"coordinates":[-117.151358,32.752094],"type":"Point"}
}