{
  "type": "Feature",
  "properties": {
    "iso:country":"US",
    "sg:address":"25 Stillman St #105",
    "sg:city":"San Francisco ",
    "sg:classifiers":[
        {
            "category":"Professional",
            "subcategory":"Computer Services",
            "type":"Services"
        }
    ],
    "sg:phone":"+1 800 969 6930",
    "sg:postcode":"94107",
    "sg:province":"CA",
    "sg:tags":[
        "intext",
        "in-line",
        "panels",
        "browser-in-browser",
        "targeting",
        "targeting-platform"
    ],
    "sg:website":"http://www.wordnetworks.com/demo",
    "wof:name":"WordNetworks",
    "wof:placetype":"venue"
},
  "geometry": {"coordinates":[-122.39589599999999,37.782126],"type":"Point"}
}