{
  "type": "Feature",
  "properties": {
    "addr:full":"2000 Williams St Palo Alto CA 94306",
    "addr:housenumber":"2000",
    "addr:postcode":"94306",
    "addr:street":"Williams St",
    "iso:country":"US",
    "sg:address":"2000 Williams St",
    "sg:city":"Palo Alto",
    "sg:classifiers":[
        {
            "category":"Social Services",
            "type":"Services"
        }
    ],
    "sg:phone":"+1 650 328 6115",
    "sg:postcode":"94306",
    "sg:province":"CA",
    "sg:tags":[
        "counselor",
        "marriage",
        "family"
    ],
    "wof:name":"Lynne D Henderson PHD",
    "wof:placetype":"venue"
},
  "geometry": {"coordinates":[-122.14905,37.42444],"type":"Point"}
}