{
  "type": "Feature",
  "properties": {
    "iso:country":"US",
    "sg:address":"20614 Pacific Coast Hwy",
    "sg:city":"Malibu",
    "sg:classifiers":[
        {
            "category":"Wholesale",
            "subcategory":"Machinery & Supplies",
            "type":"Manufacturing & Wholesale Goods"
        }
    ],
    "sg:phone":"+1 310 456 5576",
    "sg:postcode":"90265",
    "sg:province":"CA",
    "sg:tags":[
        "product",
        "industrial"
    ],
    "wof:name":"Seacliff Sales Llc",
    "wof:placetype":"venue"
},
  "geometry": {"coordinates":[-118.61876100000001,34.037654],"type":"Point"}
}