{
  "type": "Feature",
  "properties": {
    "iso:country":"US",
    "sg:address":"2580 San Ramon Valley Blvd",
    "sg:city":"San Ramon",
    "sg:classifiers":[
        {
            "category":"Insurance",
            "subcategory":"Insurance Agent",
            "type":"Services"
        }
    ],
    "sg:phone":"+1 925 277 1795",
    "sg:postcode":"94583",
    "sg:province":"CA",
    "wof:name":"Farmers Insurance Group",
    "wof:placetype":"venue"
},
  "geometry": {"coordinates":[-121.972301,37.769602],"type":"Point"}
}