{
  "type": "Feature",
  "properties": {
    "iso:country":"US",
    "sg:address":"3170 US Hwy 50",
    "sg:city":"South Lake Tahoe",
    "sg:classifiers":[
        {
            "category":"Health Services",
            "subcategory":"Doctor",
            "type":"Services"
        }
    ],
    "sg:phone":"+1 530 577 8080",
    "sg:postcode":"96150",
    "sg:province":"CA",
    "sg:tags":[
        "dentist"
    ],
    "wof:name":"Elizabeth Swope DDS",
    "wof:placetype":"venue"
},
  "geometry": {"coordinates":[-119.97666,38.943575],"type":"Point"}
}