{
  "type": "Feature",
  "properties": {
    "addr:full":"2111 Spray St San Diego CA 92107",
    "addr:housenumber":"2111",
    "addr:postcode":"92107",
    "addr:street":"Spray St",
    "iso:country":"US",
    "sg:address":"2111 Spray St",
    "sg:city":"San Diego",
    "sg:classifiers":[
        {
            "category":"Professional",
            "subcategory":"Art Services",
            "type":"Services"
        }
    ],
    "sg:phone":"+1 619 224 1859",
    "sg:postcode":"92107",
    "sg:province":"CA",
    "sg:tags":[
        "graphic",
        "designer"
    ],
    "wof:name":"Peanut Grafix",
    "wof:placetype":"venue"
},
  "geometry": {"coordinates":[-117.251383,32.752516],"type":"Point"}
}