{
  "type": "Feature",
  "properties": {
    "iso:country":"US",
    "sg:address":"1925 Jerrold Ave",
    "sg:city":"San Francisco",
    "sg:classifiers":[
        {
            "category":"Restaurant",
            "type":"Food & Drink"
        }
    ],
    "sg:phone":"+1 415 642 7700",
    "sg:postcode":"94124",
    "sg:province":"CA",
    "sg:tags":[
        "caterer"
    ],
    "wof:name":"Cook Express",
    "wof:placetype":"venue"
},
  "geometry": {"coordinates":[-122.396631,37.742573],"type":"Point"}
}