{
  "type": "Feature",
  "properties": {
    "iso:country":"US",
    "sg:address":"2627 W Ave N",
    "sg:city":"Palmdale",
    "sg:classifiers":[
        {
            "category":"Government",
            "subcategory":"Office",
            "type":"Public Place"
        }
    ],
    "sg:phone":"+1 661 265 0563",
    "sg:postcode":"93551",
    "sg:province":"CA",
    "wof:name":"Gmd Systems",
    "wof:placetype":"venue"
},
  "geometry": {"coordinates":[-118.176497,34.631198],"type":"Point"}
}