{
  "type": "Feature",
  "properties": {
    "iso:country":"US",
    "sg:address":"501 Poli St",
    "sg:city":"Ventura",
    "sg:classifiers":[
        {
            "category":"Government",
            "subcategory":"Office",
            "type":"Public Place"
        }
    ],
    "sg:phone":"+1 805 654 7827",
    "sg:postcode":"93001",
    "sg:province":"CA",
    "sg:tags":[
        "village"
    ],
    "wof:name":"Ventura City Council",
    "wof:placetype":"venue"
},
  "geometry": {"coordinates":[-119.29307799999999,34.282185],"type":"Point"}
}