{
  "type": "Feature",
  "properties": {
    "iso:country":"US",
    "sg:address":"1185 Sutter St",
    "sg:city":"San Francisco",
    "sg:classifiers":[
        {
            "category":"Social Services",
            "type":"Services"
        }
    ],
    "sg:phone":"+1 415 771 3818",
    "sg:postcode":"94109",
    "sg:province":"CA",
    "sg:tags":[
        "organization",
        "welfare"
    ],
    "wof:name":"Salvation Army Thrift Store",
    "wof:placetype":"venue"
},
  "geometry": {"coordinates":[-122.418986,37.787862],"type":"Point"}
}