{
  "type": "Feature",
  "properties": {
    "iso:country":"US",
    "sg:address":"4139 Shera Ln",
    "sg:city":"Carmichael",
    "sg:classifiers":[
        {
            "category":"Shopping",
            "subcategory":"Beauty & Cosmetics",
            "type":"Retail Goods"
        }
    ],
    "sg:phone":"+1 916 350 8731",
    "sg:postcode":"95608",
    "sg:province":"CA",
    "sg:tags":[
        "merchandise"
    ],
    "wof:name":"Susan J Nelson",
    "wof:placetype":"venue"
},
  "geometry": {"coordinates":[-121.324658,38.639564],"type":"Point"}
}