{
  "type": "Feature",
  "properties": {
    "addr:full":"2036 Avignon Pl Half Moon Bay CA 94019",
    "addr:housenumber":"2036",
    "addr:postcode":"94019",
    "addr:street":"Avignon Pl",
    "iso:country":"US",
    "sg:address":"2036 Avignon Pl",
    "sg:city":"Half Moon Bay",
    "sg:classifiers":[
        {
            "category":"Real Estate",
            "subcategory":"Surveying",
            "type":"Services"
        }
    ],
    "sg:phone":"+1 650 726 2968",
    "sg:postcode":"94019",
    "sg:province":"CA",
    "sg:tags":[
        "report",
        "survey"
    ],
    "wof:name":"Management Research",
    "wof:placetype":"venue"
},
  "geometry": {"coordinates":[-122.446444,37.48497],"type":"Point"}
}