{
  "type": "Feature",
  "properties": {
    "iso:country":"US",
    "sg:address":"10243 Macarthur Blvd",
    "sg:city":"Oakland",
    "sg:classifiers":[
        {
            "category":"Personal",
            "subcategory":"Beauty Salon",
            "type":"Services"
        }
    ],
    "sg:phone":"+1 510 382 9884",
    "sg:postcode":"94605",
    "sg:province":"CA",
    "wof:name":"Anointed Touch Beauty Salon",
    "wof:placetype":"venue"
},
  "geometry": {"coordinates":[-122.154242,37.74451],"type":"Point"}
}