{
  "type": "Feature",
  "properties": {
    "addr:full":"61 Washington St Santa Clara CA 95050",
    "addr:housenumber":"61",
    "addr:postcode":"95050",
    "addr:street":"Washington St",
    "iso:country":"US",
    "sg:address":"61 Washington St",
    "sg:city":"Santa Clara",
    "sg:classifiers":[
        {
            "category":"Restaurant",
            "type":"Food & Drink"
        }
    ],
    "sg:phone":"+1 408 984 6688",
    "sg:postcode":"95050",
    "sg:province":"CA",
    "sg:tags":[
        "chinese"
    ],
    "wof:name":"Chef Ming's Chinese Restaurant",
    "wof:placetype":"venue"
},
  "geometry": {"coordinates":[-121.93851100000001,37.339338],"type":"Point"}
}