{
  "type": "Feature",
  "properties": {
    "addr:full":"300 E Arbor St Long Beach CA 90805",
    "addr:housenumber":"300",
    "addr:postcode":"90805",
    "addr:street":"E Arbor St",
    "iso:country":"US",
    "sg:address":"300 E Arbor St",
    "sg:city":"Long Beach",
    "sg:classifiers":[
        {
            "category":"Education",
            "subcategory":"Special Training",
            "type":"Public Place"
        }
    ],
    "sg:phone":"+1 562 428 0056",
    "sg:postcode":"90805",
    "sg:province":"CA",
    "sg:tags":[
        "instruction",
        "music"
    ],
    "wof:name":"Keith Salisbury",
    "wof:placetype":"venue"
},
  "geometry": {"coordinates":[-118.18828499999999,33.84417],"type":"Point"}
}