{
  "type": "Feature",
  "properties": {
    "addr:full":"2417 Acton St Berkeley CA 94702",
    "addr:housenumber":"2417",
    "addr:postcode":"94702",
    "addr:street":"Acton St",
    "iso:country":"US",
    "sg:address":"2417 Acton St",
    "sg:city":"Berkeley",
    "sg:classifiers":[
        {
            "category":"Building & Trades",
            "subcategory":"Construction",
            "type":"Services"
        }
    ],
    "sg:phone":"+1 510 548 7497",
    "sg:postcode":"94702",
    "sg:province":"CA",
    "sg:tags":[
        "contractor"
    ],
    "wof:name":"Mike's Housing Repair",
    "wof:placetype":"venue"
},
  "geometry": {"coordinates":[-122.28294200000001,37.863143],"type":"Point"}
}