{
  "type": "Feature",
  "properties": {
    "addr:full":"2424 W Magnolia Blvd Ste B Burbank CA 91506",
    "addr:housenumber":"2424",
    "addr:postcode":"91506",
    "addr:street":"W Magnolia Blvd Ste B",
    "iso:country":"US",
    "sg:address":"2424 W Magnolia Blvd Ste B",
    "sg:city":"Burbank",
    "sg:classifiers":[
        {
            "category":"Personal",
            "subcategory":"Nail Salon",
            "type":"Services"
        }
    ],
    "sg:phone":"+1 818 842 1522",
    "sg:postcode":"91506",
    "sg:province":"CA",
    "wof:name":"Nail Event the",
    "wof:placetype":"venue"
},
  "geometry": {"coordinates":[-118.334,34.172199],"type":"Point"}
}