{
  "type": "Feature",
  "properties": {
    "iso:country":"US",
    "sg:address":"4444 Magnolia Ave",
    "sg:city":"Riverside",
    "sg:classifiers":[
        {
            "category":"Health Services",
            "subcategory":"Doctor",
            "type":"Services"
        }
    ],
    "sg:phone":"+1 951 682 5661",
    "sg:postcode":"92501",
    "sg:province":"CA",
    "sg:tags":[
        "medical"
    ],
    "wof:name":"Community Med Group of Rvrside",
    "wof:placetype":"venue"
},
  "geometry": {"coordinates":[-117.381767,33.974296],"type":"Point"}
}