{
  "type": "Feature",
  "properties": {
    "iso:country":"US",
    "sg:address":"2372 Shoreside Ct",
    "sg:city":"Santa Clara",
    "sg:classifiers":[
        {
            "category":"Professional",
            "type":"Services"
        }
    ],
    "sg:phone":"+1 408 492 9835",
    "sg:postcode":"95054",
    "sg:province":"CA",
    "wof:name":"Moondog",
    "wof:placetype":"venue"
},
  "geometry": {"coordinates":[-121.966451,37.393516],"type":"Point"}
}