{
  "type": "Feature",
  "properties": {
    "addr:full":"7891 Stockton Blvd Sacramento CA 95823",
    "addr:housenumber":"7891",
    "addr:postcode":"95823",
    "addr:street":"Stockton Blvd",
    "iso:country":"US",
    "sg:address":"7891 Stockton Blvd",
    "sg:city":"Sacramento",
    "sg:classifiers":[
        {
            "category":"Transit Center",
            "subcategory":"Freight",
            "type":"Transportation"
        },
        {
            "category":"Freight",
            "type":"Transportation"
        }
    ],
    "sg:phone":"+1 916 689 1124",
    "sg:postcode":"95823",
    "sg:province":"CA",
    "sg:tags":[
        "trucking-motor",
        "trucking"
    ],
    "wof:name":"Ligon Transportation Inc",
    "wof:placetype":"venue"
},
  "geometry": {"coordinates":[-121.4179,38.472018],"type":"Point"}
}