{
  "type": "Feature",
  "properties": {
    "addr:full":"11363 Victoria Ave Riverside CA 92503",
    "addr:housenumber":"11363",
    "addr:postcode":"92503",
    "addr:street":"Victoria Ave",
    "iso:country":"US",
    "sg:address":"11363 Victoria Ave",
    "sg:city":"Riverside",
    "sg:classifiers":[
        {
            "category":"Real Estate",
            "subcategory":"Real Estate Agent",
            "type":"Services"
        }
    ],
    "sg:phone":"+1 951 353 8140",
    "sg:postcode":"92503",
    "sg:province":"CA",
    "wof:name":"Taylor Woodrow Homes",
    "wof:placetype":"venue"
},
  "geometry": {"coordinates":[-117.46741400000001,33.885731],"type":"Point"}
}