{
  "type": "Feature",
  "properties": {
    "addr:full":"13819 Foothill Blvd Fontana CA 92335",
    "addr:housenumber":"13819",
    "addr:postcode":"92335",
    "addr:street":"Foothill Blvd",
    "iso:country":"US",
    "sg:address":"13819 Foothill Blvd",
    "sg:city":"Fontana",
    "sg:classifiers":[
        {
            "category":"Personal",
            "subcategory":"Beauty Salon",
            "type":"Services"
        }
    ],
    "sg:phone":"+1 909 355 3651",
    "sg:postcode":"92335",
    "sg:province":"CA",
    "sg:tags":[
        "manicuring"
    ],
    "wof:name":"T & M Nails",
    "wof:placetype":"venue"
},
  "geometry": {"coordinates":[-117.503936,34.106362],"type":"Point"}
}