{
  "type": "Feature",
  "properties": {
    "addr:full":"9635 Monte Vista Ave Montclair CA 91763",
    "addr:housenumber":"9635",
    "addr:postcode":"91763",
    "addr:street":"Monte Vista Ave",
    "iso:country":"US",
    "sg:address":"9635 Monte Vista Ave",
    "sg:city":"Montclair",
    "sg:classifiers":[
        {
            "category":"Health Services",
            "subcategory":"Chiropractor",
            "type":"Services"
        }
    ],
    "sg:phone":"+1 909 625 5910",
    "sg:postcode":"91763",
    "sg:province":"CA",
    "sg:tags":[
        "chiropractic"
    ],
    "wof:name":"Jay Jazayeri",
    "wof:placetype":"venue"
},
  "geometry": {"coordinates":[-117.69824199999999,34.079441],"type":"Point"}
}