{
  "type": "Feature",
  "properties": {
    "addr:full":"120 N Montebello Blvd Montebello CA 90640",
    "addr:housenumber":"120",
    "addr:postcode":"90640",
    "addr:street":"N Montebello Blvd",
    "iso:country":"US",
    "sg:address":"120 N Montebello Blvd",
    "sg:city":"Montebello",
    "sg:classifiers":[
        {
            "category":"Health Services",
            "subcategory":"Health Practitioner",
            "type":"Services"
        }
    ],
    "sg:phone":"+1 323 888 0304",
    "sg:postcode":"90640",
    "sg:province":"CA",
    "sg:tags":[
        "acupuncture"
    ],
    "wof:name":"Meditree Acupuncture",
    "wof:placetype":"venue"
},
  "geometry": {"coordinates":[-118.108002,34.010601],"type":"Point"}
}