{
  "type": "Feature",
  "properties": {
    "addr:full":"1150 W Branch St Arroyo Grande CA 93420",
    "addr:housenumber":"1150",
    "addr:postcode":"93420",
    "addr:street":"W Branch St",
    "iso:country":"US",
    "sg:address":"1150 W Branch St",
    "sg:city":"Arroyo Grande",
    "sg:classifiers":[
        {
            "category":"Shopping",
            "subcategory":"Shoes",
            "type":"Retail Goods"
        }
    ],
    "sg:phone":"+1 805 473 3708",
    "sg:postcode":"93420",
    "sg:province":"CA",
    "wof:name":"Payless Shoe Source",
    "wof:placetype":"venue"
},
  "geometry": {"coordinates":[-120.599476,35.127905],"type":"Point"}
}