{
  "type": "Feature",
  "properties": {
    "addr:full":"747 E Francis St Ontario CA 91761",
    "addr:housenumber":"747",
    "addr:postcode":"91761",
    "addr:street":"E Francis St",
    "iso:country":"US",
    "sg:address":"747 E Francis St",
    "sg:city":"Ontario",
    "sg:classifiers":[
        {
            "category":"Manufacturing",
            "subcategory":"Retail Goods",
            "type":"Manufacturing & Wholesale Goods"
        },
        {
            "category":"Wholesale",
            "subcategory":"Sporting Goods",
            "type":"Manufacturing & Wholesale Goods"
        }
    ],
    "sg:phone":"+1 909 923 5521",
    "sg:postcode":"91761",
    "sg:province":"CA",
    "sg:tags":[
        "tub",
        "spa",
        "product",
        "hot",
        "mfg"
    ],
    "sg:website":"www.diamantespas.com",
    "wof:name":"U S Tooling & Spas",
    "wof:placetype":"venue"
},
  "geometry": {"coordinates":[-117.63971100000001,34.041226],"type":"Point"}
}