{
  "type": "Feature",
  "properties": {
    "iso:country":"US",
    "sg:address":"1142 Keith Ave",
    "sg:city":"Berkeley",
    "sg:classifiers":[
        {
            "category":"Social Services",
            "type":"Services"
        },
        {
            "category":"Professional",
            "subcategory":"Employment Agencies",
            "type":"Services"
        }
    ],
    "sg:phone":"+1 510 488 4554",
    "sg:postcode":"94708",
    "sg:province":"CA",
    "sg:tags":[
        "workers'",
        "placement",
        "volunteer"
    ],
    "wof:name":"Pipra Foundation",
    "wof:placetype":"venue"
},
  "geometry": {"coordinates":[-122.26052900000001,37.889069],"type":"Point"}
}