{
  "type": "Feature",
  "properties": {
    "addr:full":"2401 Marconi Ave Sacramento CA 95821",
    "addr:housenumber":"2401",
    "addr:postcode":"95821",
    "addr:street":"Marconi Ave",
    "iso:country":"US",
    "sg:address":"2401 Marconi Ave",
    "sg:city":"Sacramento",
    "sg:phone":"+1 916 482 1020",
    "sg:postcode":"95821",
    "sg:province":"CA",
    "wof:name":"Marconi Apartments",
    "wof:placetype":"venue"
},
  "geometry": {"coordinates":[-121.406021,38.618061],"type":"Point"}
}