{
  "type": "Feature",
  "properties": {
    "addr:full":"905 Padre Dr Salinas CA 93901",
    "addr:housenumber":"905",
    "addr:postcode":"93901",
    "addr:street":"Padre Dr",
    "iso:country":"US",
    "sg:address":"905 Padre Dr",
    "sg:city":"Salinas",
    "sg:classifiers":[
        {
            "category":"Professional",
            "subcategory":"Business Services",
            "type":"Services"
        }
    ],
    "sg:phone":"+1 831 783 1113",
    "sg:postcode":"93901",
    "sg:province":"CA",
    "sg:tags":[
        "notary"
    ],
    "wof:name":"Notaries Ink",
    "wof:placetype":"venue"
},
  "geometry": {"coordinates":[-121.66081,36.661419],"type":"Point"}
}