{
  "type": "Feature",
  "properties": {
    "iso:country":"US",
    "sg:address":"5690 Old Redwood Hwy",
    "sg:city":"Penngrove",
    "sg:classifiers":[
        {
            "category":"Freight",
            "type":"Transportation"
        }
    ],
    "sg:phone":"+1 707 838 7315",
    "sg:postcode":"94951",
    "sg:province":"CA",
    "wof:name":"Rv Storage",
    "wof:placetype":"venue"
},
  "geometry": {"coordinates":[-122.66641799999999,38.289182],"type":"Point"}
}