{
  "type": "Feature",
  "properties": {
    "iso:country":"US",
    "sg:address":"18601 Hatteras St",
    "sg:city":"Tarzana",
    "sg:classifiers":[
        {
            "category":"Real Estate",
            "subcategory":"Real Estate Operator",
            "type":"Services"
        }
    ],
    "sg:phone":"+1 818 344 5200",
    "sg:postcode":"91356",
    "sg:province":"CA",
    "sg:tags":[
        "apartment"
    ],
    "wof:name":"Tarzana Terraces",
    "wof:placetype":"venue"
},
  "geometry": {"coordinates":[-118.539966,34.177201],"type":"Point"}
}