{
  "type": "Feature",
  "properties": {
    "addr:full":"21642 Parvin Dr Santa Clarita CA 91350",
    "addr:housenumber":"21642",
    "addr:postcode":"91350",
    "addr:street":"Parvin Dr",
    "iso:country":"US",
    "sg:address":"21642 Parvin Dr",
    "sg:city":"Santa Clarita",
    "sg:classifiers":[
        {
            "category":"Insurance",
            "subcategory":"Insurance Agent",
            "type":"Services"
        }
    ],
    "sg:phone":"+1 661 291 1010",
    "sg:postcode":"91350",
    "sg:province":"CA",
    "wof:name":"Pete Tutokey Insurance Svc",
    "wof:placetype":"venue"
},
  "geometry": {"coordinates":[-118.516684,34.392341],"type":"Point"}
}