{
  "type": "Feature",
  "properties": {
    "iso:country":"US",
    "sg:address":"21642 Parvin Dr",
    "sg:city":"Santa Clarita",
    "sg:classifiers":[
        {
            "category":"Insurance",
            "subcategory":"Insurance Agent",
            "type":"Services"
        }
    ],
    "sg:phone":"+1 661 291 1010",
    "sg:postcode":"91350",
    "sg:province":"CA",
    "wof:name":"Pete Tutokey Insurance Svc",
    "wof:placetype":"venue"
},
  "geometry": {"coordinates":[-118.516684,34.392341],"type":"Point"}
}