{
  "type": "Feature",
  "properties": {
    "addr:full":"711 Kains Ave San Bruno CA 94066",
    "addr:housenumber":"711",
    "addr:postcode":"94066",
    "addr:street":"Kains Ave",
    "iso:country":"US",
    "sg:address":"711 Kains Ave",
    "sg:city":"San Bruno",
    "sg:classifiers":[
        {
            "category":"Health Services",
            "subcategory":"Optometrist",
            "type":"Services"
        },
        {
            "category":"Shopping",
            "subcategory":"Optician",
            "type":"Retail Goods"
        }
    ],
    "sg:phone":"+1 650 871 1816",
    "sg:postcode":"94066",
    "sg:province":"CA",
    "sg:tags":[
        "eyewear"
    ],
    "sg:website":"www.draller.com",
    "wof:name":"Dr Thomas Aller Optometrist, Inc.",
    "wof:placetype":"venue"
},
  "geometry": {"coordinates":[-122.41601199999999,37.627024],"type":"Point"}
}