{
  "type": "Feature",
  "properties": {
    "iso:country":"US",
    "sg:address":"1503 Columbus St",
    "sg:city":"Bakersfield",
    "sg:classifiers":[
        {
            "category":"Shopping",
            "subcategory":"Discount & Variety Stores",
            "type":"Retail Goods"
        }
    ],
    "sg:phone":"+1 661 872 7734",
    "sg:postcode":"93305",
    "sg:province":"CA",
    "wof:name":"One Dollar Mart & More",
    "wof:placetype":"venue"
},
  "geometry": {"coordinates":[-118.974371,35.39746],"type":"Point"}
}