{
  "type": "Feature",
  "properties": {
    "iso:country":"US",
    "sg:address":"1244 High St",
    "sg:city":"Oakland",
    "sg:classifiers":[
        {
            "category":"Food & Beverages",
            "subcategory":"Ethnic Foods",
            "type":"Retail Goods"
        },
        {
            "category":"Food & Beverages",
            "subcategory":"Groceries & Convenience Stores",
            "type":"Retail Goods"
        }
    ],
    "sg:phone":"+1 510 536 0717",
    "sg:postcode":"94620",
    "sg:province":"CA",
    "wof:name":"Los Mexicanos Market",
    "wof:placetype":"venue"
},
  "geometry": {"coordinates":[-122.215515,37.77185],"type":"Point"}
}