{
  "type": "Feature",
  "properties": {
    "iso:country":"US",
    "sg:address":"1 City Blvd W",
    "sg:city":"Orange",
    "sg:classifiers":[
        {
            "category":"Professional",
            "subcategory":"Lawyer & Legal Services",
            "type":"Services"
        }
    ],
    "sg:phone":"+1 714 978 1061",
    "sg:postcode":"92868",
    "sg:province":"CA",
    "wof:name":"Thomson Ann Ashby Attorney At Law",
    "wof:placetype":"venue"
},
  "geometry": {"coordinates":[-117.89299800000001,33.787601],"type":"Point"}
}