{
  "type": "Feature",
  "properties": {
    "addr:full":"1155 University Dr Menlo Park CA 94025",
    "addr:housenumber":"1155",
    "addr:postcode":"94025",
    "addr:street":"University Dr",
    "iso:country":"US",
    "sg:address":"1155 University Dr",
    "sg:city":"Menlo Park",
    "sg:classifiers":[
        {
            "category":"Health Services",
            "subcategory":"Chiropractor",
            "type":"Services"
        }
    ],
    "sg:phone":"+1 650 326 5927",
    "sg:postcode":"94025",
    "sg:province":"CA",
    "wof:name":"Mid Peninsula Chiropractic",
    "wof:placetype":"venue"
},
  "geometry": {"coordinates":[-122.18688299999999,37.45013],"type":"Point"}
}