{
  "type": "Feature",
  "properties": {
    "addr:full":"23505 Crenshaw Blvd Torrance CA 90505",
    "addr:housenumber":"23505",
    "addr:postcode":"90505",
    "addr:street":"Crenshaw Blvd",
    "iso:country":"US",
    "sg:address":"23505 Crenshaw Blvd",
    "sg:city":"Torrance",
    "sg:classifiers":[
        {
            "category":"Utilities",
            "subcategory":"Telephone",
            "type":"Services"
        }
    ],
    "sg:phone":"+1 310 539 8775",
    "sg:postcode":"90505",
    "sg:province":"CA",
    "sg:tags":[
        "communications",
        "computer",
        "programing",
        "custom"
    ],
    "wof:name":"Dgccccom LLC",
    "wof:placetype":"venue"
},
  "geometry": {"coordinates":[-118.328115,33.811333],"type":"Point"}
}