{
  "type": "Feature",
  "properties": {
    "iso:country":"US",
    "sg:address":"400 Reed St",
    "sg:city":"Santa Clara",
    "sg:classifiers":[
        {
            "category":"Building & Trades",
            "subcategory":"Construction",
            "type":"Services"
        }
    ],
    "sg:phone":"+1 408 988 1110",
    "sg:postcode":"95050",
    "sg:province":"CA",
    "sg:tags":[
        "contractor"
    ],
    "wof:name":"Kal Construction Inc",
    "wof:placetype":"venue"
},
  "geometry": {"coordinates":[-121.94032,37.36072],"type":"Point"}
}