{
  "type": "Feature",
  "properties": {
    "addr:full":"9425 Garvey Ave South El Monte CA 91733",
    "addr:housenumber":"9425",
    "addr:postcode":"91733",
    "addr:street":"Garvey Ave",
    "iso:country":"US",
    "sg:address":"9425 Garvey Ave",
    "sg:city":"South El Monte",
    "sg:classifiers":[
        {
            "category":"Autos & Motor Vehicles",
            "subcategory":"Automobile Sales",
            "type":"Retail Goods"
        }
    ],
    "sg:phone":"+1 626 279 2722",
    "sg:postcode":"91733",
    "sg:province":"CA",
    "sg:tags":[
        "car",
        "dealer"
    ],
    "wof:name":"America Enterprise",
    "wof:placetype":"venue"
},
  "geometry": {"coordinates":[-118.06515400000001,34.062769],"type":"Point"}
}