{
  "type": "Feature",
  "properties": {
    "addr:full":"Bristol Pkwy Culver City CA 90230",
    "addr:postcode":"90230",
    "addr:street":"Bristol Pkwy",
    "iso:country":"US",
    "sg:address":"Bristol Pkwy",
    "sg:city":"Culver City",
    "sg:classifiers":[
        {
            "category":"Restaurant",
            "type":"Food & Drink"
        }
    ],
    "sg:menulink":"http://www.allmenus.com/ca/los-angeles/33472-fine-american-cuisine/menu/",
    "sg:phone":"+1 310 590 2511",
    "sg:postcode":"90230",
    "sg:province":"CA",
    "sg:tags":[
        "american"
    ],
    "wof:name":"Fine American Cuisine",
    "wof:placetype":"venue"
},
  "geometry": {"coordinates":[-118.38711000000001,33.98591],"type":"Point"}
}