{
  "type": "Feature",
  "properties": {
    "iso:country":"US",
    "sg:address":"9540 Magnolia Ave",
    "sg:city":"Riverside",
    "sg:classifiers":[
        {
            "category":"Retail",
            "subcategory":"Auto Repair",
            "type":"Services"
        }
    ],
    "sg:phone":"+1 951 352 0716",
    "sg:postcode":"92503",
    "sg:province":"CA",
    "sg:tags":[
        "automobile",
        "inspection"
    ],
    "wof:name":"All About Smog",
    "wof:placetype":"venue"
},
  "geometry": {"coordinates":[-117.44717300000001,33.919978],"type":"Point"}
}