{
  "type": "Feature",
  "properties": {
    "addr:full":"1641 N Garey Ave Pomona CA 91767",
    "addr:housenumber":"1641",
    "addr:postcode":"91767",
    "addr:street":"N Garey Ave",
    "iso:country":"US",
    "sg:address":"1641 N Garey Ave",
    "sg:city":"Pomona",
    "sg:classifiers":[
        {
            "category":"Personal",
            "type":"Services"
        }
    ],
    "sg:phone":"+1 909 469 1716",
    "sg:postcode":"91767",
    "sg:province":"CA",
    "sg:tags":[
        "wear",
        "formal"
    ],
    "wof:name":"J & L Cleaners & Tuxedo",
    "wof:placetype":"venue"
},
  "geometry": {"coordinates":[-117.752335,34.07549],"type":"Point"}
}