{
  "type": "Feature",
  "properties": {
    "iso:country":"US",
    "sg:address":"1650 Oregon St",
    "sg:city":"Redding",
    "sg:classifiers":[
        {
            "category":"Social Services",
            "subcategory":"Adult Care",
            "type":"Services"
        }
    ],
    "sg:phone":"+1 530 243 8450",
    "sg:postcode":"96001",
    "sg:province":"CA",
    "sg:tags":[
        "foster"
    ],
    "wof:name":"California Youth Connection",
    "wof:placetype":"venue"
},
  "geometry": {"coordinates":[-122.393823,40.581952],"type":"Point"}
}