{
  "type": "Feature",
  "properties": {
    "iso:country":"US",
    "sg:address":"3639 Harbor Blvd",
    "sg:city":"Ventura",
    "sg:classifiers":[
        {
            "category":"Shopping",
            "subcategory":"Computers & Home Electronics",
            "type":"Retail Goods"
        }
    ],
    "sg:phone":"+1 805 644 1144",
    "sg:postcode":"93001",
    "sg:province":"CA",
    "sg:tags":[
        "equipment",
        "dealer"
    ],
    "wof:name":"Data 2000",
    "wof:placetype":"venue"
},
  "geometry": {"coordinates":[-119.25677899999999,34.242398],"type":"Point"}
}