{
  "type": "Feature",
  "properties": {
    "iso:country":"US",
    "sg:address":"600 Scott St",
    "sg:city":"Monterey",
    "sg:classifiers":[
        {
            "category":"Building & Trades",
            "subcategory":"Landscaping Services",
            "type":"Services"
        }
    ],
    "sg:phone":"+1 831 644 2771",
    "sg:postcode":"93940",
    "sg:province":"CA",
    "sg:tags":[
        "lawn",
        "maintenance",
        "grounds"
    ],
    "wof:name":"Botanical Alternatives",
    "wof:placetype":"venue"
},
  "geometry": {"coordinates":[-121.898163,36.603801],"type":"Point"}
}