{
  "type": "Feature",
  "properties": {
    "iso:country":"US",
    "sg:address":"4600 Watt Avenue",
    "sg:city":"North Highlands",
    "sg:classifiers":[
        {
            "category":"Travel",
            "subcategory":"Hotels & Motels",
            "type":"Entertainment"
        }
    ],
    "sg:phone":"+1 916 973 8637",
    "sg:postcode":"95660",
    "sg:province":"CA",
    "wof:name":"Motel 6",
    "wof:placetype":"venue"
},
  "geometry": {"coordinates":[-121.383021,38.646939],"type":"Point"}
}