{
  "type": "Feature",
  "properties": {
    "iso:country":"US",
    "sg:address":"4700 Whittier Blvd",
    "sg:city":"Los Angeles",
    "sg:classifiers":[
        {
            "category":"Travel",
            "subcategory":"Travel Agent",
            "type":"Entertainment"
        }
    ],
    "sg:phone":"+1 323 415 7040",
    "sg:postcode":"90022",
    "sg:province":"CA",
    "sg:tags":[
        "agency",
        "bureau"
    ],
    "wof:name":"Exito Travel",
    "wof:placetype":"venue"
},
  "geometry": {"coordinates":[-118.165733,34.022176],"type":"Point"}
}