{
  "type": "Feature",
  "properties": {
    "iso:country":"US",
    "sg:address":"3687 Las Posas Rd",
    "sg:city":"Camarillo",
    "sg:classifiers":[
        {
            "category":"Health Services",
            "subcategory":"Doctor",
            "type":"Services"
        }
    ],
    "sg:phone":"+1 805 445 4189",
    "sg:postcode":"93010",
    "sg:province":"CA",
    "sg:tags":[
        "physician",
        "surgeon"
    ],
    "wof:name":"Internal Medicine & Pediatrics",
    "wof:placetype":"venue"
},
  "geometry": {"coordinates":[-119.015091,34.242318],"type":"Point"}
}