{
  "type": "Feature",
  "properties": {
    "addr:full":"333 20th St Oakland CA 94612",
    "addr:housenumber":"333",
    "addr:postcode":"94612",
    "addr:street":"20Th St",
    "iso:country":"US",
    "sg:address":"333 20th St",
    "sg:city":"Oakland",
    "sg:classifiers":[
        {
            "category":"Deli",
            "type":"Food & Drink"
        }
    ],
    "sg:phone":"+1 510 839 0513",
    "sg:postcode":"94612",
    "sg:province":"CA",
    "sg:website":"www.speedsterscafe.com",
    "wof:name":"Speedsters",
    "wof:placetype":"venue"
},
  "geometry": {"coordinates":[-122.26552100000001,37.80816],"type":"Point"}
}