{
  "type": "Feature",
  "properties": {
    "iso:country":"US",
    "sg:address":"7200 Garden Hwy",
    "sg:city":"Sacramento",
    "sg:classifiers":[
        {
            "category":"Shopping",
            "subcategory":"Bicycles & Sporting Goods",
            "type":"Retail Goods"
        },
        {
            "category":"Sports & Exercise",
            "subcategory":"Golf",
            "type":"Entertainment"
        },
        {
            "category":"Sports & Exercise",
            "subcategory":"Sports Center",
            "type":"Entertainment"
        },
        {
            "category":"Arena",
            "subcategory":"Sports Club",
            "type":"Entertainment"
        }
    ],
    "sg:phone":"+1 916 922 5209",
    "sg:postcode":"95837",
    "sg:province":"CA",
    "sg:tags":[
        "equipment",
        "courses-private",
        "supply",
        "course"
    ],
    "sg:website":"http://www.remington-gc.com",
    "wof:name":"Teal Bend Golf Club",
    "wof:placetype":"venue"
},
  "geometry": {"coordinates":[-121.623352,38.701111],"type":"Point"}
}