{
  "type": "Feature",
  "properties": {
    "addr:full":"8008 N Cedar Ave Fresno CA 93720",
    "addr:housenumber":"8008",
    "addr:postcode":"93720",
    "addr:street":"N Cedar Ave",
    "iso:country":"US",
    "sg:address":"8008 N Cedar Ave",
    "sg:city":"Fresno",
    "sg:classifiers":[
        {
            "category":"Restaurant",
            "type":"Food & Drink"
        }
    ],
    "sg:menulink":"http://www.allmenus.com/ca/fresno/178327-jack-in-the-box/menu/",
    "sg:phone":"+1 559 325 0205",
    "sg:postcode":"93720",
    "sg:province":"CA",
    "sg:tags":[
        "burger",
        "american"
    ],
    "wof:name":"Jack in the Box",
    "wof:placetype":"venue"
},
  "geometry": {"coordinates":[-119.75650899999999,36.853062],"type":"Point"}
}