{
  "type": "Feature",
  "properties": {
    "iso:country":"US",
    "sg:address":"140 Yellowstone Dr #120",
    "sg:city":"Chico",
    "sg:classifiers":[
        {
            "category":"Professional",
            "subcategory":"Lawyer & Legal Services",
            "type":"Services"
        }
    ],
    "sg:phone":"+1 530 343 4318",
    "sg:postcode":"95973",
    "sg:province":"CA",
    "sg:tags":[
        "attorney",
        "law",
        "estate",
        "family",
        "divorce",
        "wills",
        "planning",
        "trust",
        "probate"
    ],
    "wof:name":"Gilman Brett A Attorney At Law",
    "wof:placetype":"venue"
},
  "geometry": {"coordinates":[-121.875699,39.76979],"type":"Point"}
}