{
  "type": "Feature",
  "properties": {
    "iso:country":"US",
    "sg:address":"620 42nd St",
    "sg:city":"Oakland",
    "sg:classifiers":[
        {
            "category":"Organizations",
            "subcategory":"Religious Organization",
            "type":"Services"
        }
    ],
    "sg:phone":"+1 510 601 7327",
    "sg:postcode":"94609",
    "sg:province":"CA",
    "sg:tags":[
        "church"
    ],
    "wof:name":"Harvest Fellowship Church",
    "wof:placetype":"venue"
},
  "geometry": {"coordinates":[-122.267759,37.831525],"type":"Point"}
}