{
  "type": "Feature",
  "properties": {
    "iso:country":"US",
    "sg:address":"6352 E Nohl Ranch Rd",
    "sg:city":"Anaheim",
    "sg:classifiers":[
        {
            "category":"Recreation",
            "type":"Entertainment"
        }
    ],
    "sg:phone":"+1 714 998 2830",
    "sg:postcode":"92807",
    "sg:province":"CA",
    "sg:tags":[
        "stable"
    ],
    "wof:name":"Anaheim Hills Saddle Club",
    "wof:placetype":"venue"
},
  "geometry": {"coordinates":[-117.766661,33.839666],"type":"Point"}
}