{
  "type": "Feature",
  "properties": {
    "addr:full":"531 Main St Ste 1135 El Segundo CA 90245",
    "addr:housenumber":"531",
    "addr:postcode":"90245",
    "addr:street":"Main St Ste 1135",
    "iso:country":"US",
    "sg:address":"531 Main St Ste 1135",
    "sg:city":"El Segundo",
    "sg:classifiers":[
        {
            "category":"Arts & Performance",
            "subcategory":"Arts Center",
            "type":"Entertainment"
        }
    ],
    "sg:phone":"+1 310 606 0813",
    "sg:postcode":"90245",
    "sg:province":"CA",
    "sg:tags":[
        "performing"
    ],
    "sg:website":"www.actorsworking.com",
    "wof:name":"Actors Working",
    "wof:placetype":"venue"
},
  "geometry": {"coordinates":[-118.415965,33.9232],"type":"Point"}
}