{
  "type": "Feature",
  "properties": {
    "addr:full":"4393 Riverview Dr Riverside CA 92509",
    "addr:housenumber":"4393",
    "addr:postcode":"92509",
    "addr:street":"Riverview Dr",
    "iso:country":"US",
    "sg:address":"4393 Riverview Dr",
    "sg:city":"Riverside",
    "sg:classifiers":[
        {
            "category":"Recreation",
            "type":"Entertainment"
        }
    ],
    "sg:phone":"+1 951 781 4622",
    "sg:postcode":"92509",
    "sg:province":"CA",
    "sg:tags":[
        "pool",
        "swimming"
    ],
    "wof:name":"Memorial Park Pool",
    "wof:placetype":"venue"
},
  "geometry": {"coordinates":[-117.419555,33.995985],"type":"Point"}
}