{
  "type": "Feature",
  "properties": {
    "iso:country":"US",
    "sg:address":"4363 Lincoln Blvd",
    "sg:city":"Marina Del Rey",
    "sg:classifiers":[
        {
            "category":"Retail",
            "subcategory":"Auto Rental",
            "type":"Services"
        }
    ],
    "sg:phone":"+1 310 306 6044",
    "sg:postcode":"90292",
    "sg:province":"CA",
    "sg:tags":[
        "passenger",
        "truck",
        "car"
    ],
    "wof:name":"Sheffield Leasing",
    "wof:placetype":"venue"
},
  "geometry": {"coordinates":[-118.442021,33.983613],"type":"Point"}
}