{
  "type": "Feature",
  "properties": {
    "addr:full":"948 Ventura Dr Pittsburg CA 94565",
    "addr:housenumber":"948",
    "addr:postcode":"94565",
    "addr:street":"Ventura Dr",
    "iso:country":"US",
    "sg:address":"948 Ventura Dr",
    "sg:city":"Pittsburg",
    "sg:classifiers":[
        {
            "category":"Wholesale",
            "subcategory":"Painting Supplies",
            "type":"Manufacturing & Wholesale Goods"
        }
    ],
    "sg:phone":"+1 925 432 4897",
    "sg:postcode":"94565",
    "sg:province":"CA",
    "sg:tags":[
        "goods-wholesale",
        "art",
        "manufacturer"
    ],
    "wof:name":"Portraits By Joeval",
    "wof:placetype":"venue"
},
  "geometry": {"coordinates":[-121.881047,37.999222],"type":"Point"}
}