{
  "type": "Feature",
  "properties": {
    "addr:full":"3260 Lakeshore Avenue, Oakland, CA, USA",
    "iso:country":"US",
    "name:eng_x_preferred":[
        "Proposition Chicken"
    ],
    "wof:name":"Proposition Chicken",
    "wof:placetype":"venue"
},
  "geometry": {"coordinates":[-122.242547,37.811714],"type":"Point"}
}