{
  "type": "Feature",
  "properties": {
    "addr:full":"9110 de Soto Ave Chatsworth CA 91311",
    "addr:housenumber":"9110",
    "addr:postcode":"91311",
    "addr:street":"De Soto Ave",
    "iso:country":"US",
    "sg:address":"9110 de Soto Ave",
    "sg:city":"Chatsworth",
    "sg:phone":"+1 818 882 1877",
    "sg:postcode":"91311",
    "sg:province":"CA",
    "wof:name":"Giamela's Lamplighter Casa De Soria",
    "wof:placetype":"venue"
},
  "geometry": {"coordinates":[-118.58854700000001,34.235836],"type":"Point"}
}