{
  "type": "Feature",
  "properties": {
    "addr:full":"201 Grand Ave Grover Beach CA 93433",
    "addr:housenumber":"201",
    "addr:postcode":"93433",
    "addr:street":"Grand Ave",
    "iso:country":"US",
    "sg:address":"201 Grand Ave",
    "sg:city":"Grover Beach",
    "sg:classifiers":[
        {
            "category":"Wholesale",
            "subcategory":"Fruits & Vegetables",
            "type":"Manufacturing & Wholesale Goods"
        }
    ],
    "sg:phone":"+1 805 473 1320",
    "sg:postcode":"93433",
    "sg:province":"CA",
    "sg:tags":[
        "shipper"
    ],
    "wof:name":"Regatta Tropicals LTD",
    "wof:placetype":"venue"
},
  "geometry": {"coordinates":[-120.628878,35.121936],"type":"Point"}
}