{
  "type": "Feature",
  "properties": {
    "addr:full":"2820 Market St San Diego CA 92102",
    "addr:housenumber":"2820",
    "addr:postcode":"92102",
    "addr:street":"Market St",
    "iso:country":"US",
    "sg:address":"2820 Market St",
    "sg:city":"San Diego",
    "sg:classifiers":[
        {
            "category":"Restaurant",
            "type":"Food & Drink"
        }
    ],
    "sg:phone":"+1 619 702 9309",
    "sg:postcode":"92102",
    "sg:province":"CA",
    "wof:name":"Island Spice Jamaican Restaurant",
    "wof:placetype":"venue"
},
  "geometry": {"coordinates":[-117.133003,32.711498],"type":"Point"}
}