{
  "type": "Feature",
  "properties": {
    "addr:full":"4937 Coronado Ave San Diego CA 92107",
    "addr:housenumber":"4937",
    "addr:postcode":"92107",
    "addr:street":"Coronado Ave",
    "iso:country":"US",
    "sg:address":"4937 Coronado Ave",
    "sg:city":"San Diego",
    "sg:classifiers":[
        {
            "category":"Taxi",
            "type":"Transportation"
        }
    ],
    "sg:phone":"+1 619 223 3016",
    "sg:postcode":"92107",
    "sg:province":"CA",
    "sg:tags":[
        "taxicab"
    ],
    "wof:name":"Stephen Cole",
    "wof:placetype":"venue"
},
  "geometry": {"coordinates":[-117.253665,32.741848],"type":"Point"}
}