{
  "type": "Feature",
  "properties": {
    "addr:full":"1655 Broadway Chula Vista CA 91911",
    "addr:housenumber":"1655",
    "addr:postcode":"91911",
    "addr:street":"Broadway",
    "iso:country":"US",
    "sg:address":"1655 Broadway",
    "sg:city":"Chula Vista",
    "sg:classifiers":[
        {
            "category":"Autos & Motor Vehicles",
            "subcategory":"Auto Supplies",
            "type":"Retail Goods"
        }
    ],
    "sg:phone":"+1 619 420 7372",
    "sg:postcode":"91911",
    "sg:province":"CA",
    "sg:tags":[
        "automobile",
        "stereo",
        "radio"
    ],
    "wof:name":"Mr Sound Audio System",
    "wof:placetype":"venue"
},
  "geometry": {"coordinates":[-117.07620900000001,32.597408],"type":"Point"}
}