{
  "type": "Feature",
  "properties": {
    "iso:country":"US",
    "sg:address":"11306 Sunco Dr, Unit 1",
    "sg:city":"Rancho Cordova",
    "sg:classifiers":[
        {
            "category":"Autos & Motor Vehicles",
            "subcategory":"Automobile Sales",
            "type":"Retail Goods"
        }
    ],
    "sg:phone":"+1 916 369 2509",
    "sg:postcode":"95742",
    "sg:province":"CA",
    "sg:tags":[
        "automotive"
    ],
    "sg:website":"www.motowheels.com",
    "wof:name":"Motowheels",
    "wof:placetype":"venue"
},
  "geometry": {"coordinates":[-121.265112,38.605033],"type":"Point"}
}