{
  "type": "Feature",
  "properties": {
    "iso:country":"US",
    "sg:address":"116 Via Ardilla",
    "sg:city":"Palos Vrds Ests",
    "sg:classifiers":[
        {
            "category":"Insurance",
            "subcategory":"Insurance Agent",
            "type":"Services"
        }
    ],
    "sg:phone":"+1 310 378 2487",
    "sg:postcode":"90274",
    "sg:province":"CA",
    "wof:name":"DLB Enterprises Inc",
    "wof:placetype":"venue"
},
  "geometry": {"coordinates":[-118.365673,33.802924],"type":"Point"}
}