{
  "type": "Feature",
  "properties": {
    "iso:country":"US",
    "sg:address":"1327 E 21st St",
    "sg:city":"Los Angeles",
    "sg:classifiers":[
        {
            "category":"Organizations",
            "subcategory":"Religious Organization",
            "type":"Services"
        }
    ],
    "sg:phone":"+1 213 748 7370",
    "sg:postcode":"90011",
    "sg:province":"CA",
    "sg:tags":[
        "church"
    ],
    "wof:name":"New Deliverance Twenty First",
    "wof:placetype":"venue"
},
  "geometry": {"coordinates":[-118.250321,34.021423],"type":"Point"}
}