{
  "type": "Feature",
  "properties": {
    "addr:full":"442 S Maclay St San Fernando CA 91340",
    "addr:housenumber":"442",
    "addr:postcode":"91340",
    "addr:street":"S Maclay St",
    "iso:country":"US",
    "sg:address":"442 S Maclay St",
    "sg:city":"San Fernando",
    "sg:classifiers":[
        {
            "category":"Wholesale",
            "subcategory":"Apparel",
            "type":"Manufacturing & Wholesale Goods"
        }
    ],
    "sg:phone":"+1 818 365 6515",
    "sg:postcode":"91340",
    "sg:province":"CA",
    "sg:tags":[
        "piece"
    ],
    "wof:name":"Lupes Bridal",
    "wof:placetype":"venue"
},
  "geometry": {"coordinates":[-118.443157,34.281916],"type":"Point"}
}