{
  "type": "Feature",
  "properties": {
    "iso:country":"US",
    "sg:address":"500 Silver Spur Rd",
    "sg:city":"Rolling Hls Ests",
    "sg:classifiers":[
        {
            "category":"Real Estate",
            "subcategory":"Real Estate Agent",
            "type":"Services"
        }
    ],
    "sg:phone":"+1 310 548 5423",
    "sg:postcode":"90275",
    "sg:province":"CA",
    "wof:name":"Palos Verdes Realty",
    "wof:placetype":"venue"
},
  "geometry": {"coordinates":[-118.372837,33.772952],"type":"Point"}
}