{
  "type": "Feature",
  "properties": {
    "addr:full":"309 Pasadena Ave South Pasadena CA 91030",
    "addr:housenumber":"309",
    "addr:postcode":"91030",
    "addr:street":"Pasadena Ave",
    "iso:country":"US",
    "sg:address":"309 Pasadena Ave",
    "sg:city":"South Pasadena",
    "sg:classifiers":[
        {
            "category":"Organizations",
            "subcategory":"Religious Organization",
            "type":"Services"
        }
    ],
    "sg:phone":"+1 323 254 1546",
    "sg:postcode":"91030",
    "sg:province":"CA",
    "wof:name":"Vedanta Society Southern Cal",
    "wof:placetype":"venue"
},
  "geometry": {"coordinates":[-118.167957,34.113563],"type":"Point"}
}