{
  "type": "Feature",
  "properties": {
    "addr:full":"1037 N Lima St Burbank CA 91505",
    "addr:housenumber":"1037",
    "addr:postcode":"91505",
    "addr:street":"N Lima St",
    "iso:country":"US",
    "sg:address":"1037 N Lima St",
    "sg:city":"Burbank",
    "sg:classifiers":[
        {
            "category":"Professional",
            "type":"Services"
        }
    ],
    "sg:phone":"+1 818 566 9890",
    "sg:postcode":"91505",
    "sg:province":"CA",
    "wof:name":"Modern Inkwell",
    "wof:placetype":"venue"
},
  "geometry": {"coordinates":[-118.345545,34.172015],"type":"Point"}
}