{
  "type": "Feature",
  "properties": {
    "addr:full":"8880 East Rd Redwood Valley CA 95470",
    "addr:housenumber":"8880",
    "addr:postcode":"95470",
    "addr:street":"East Rd",
    "iso:country":"US",
    "sg:address":"8880 East Rd",
    "sg:city":"Redwood Valley",
    "sg:classifiers":[
        {
            "category":"Building & Trades",
            "subcategory":"Construction",
            "type":"Services"
        },
        {
            "category":"Manufacturing",
            "subcategory":"Tools & Machinery",
            "type":"Manufacturing & Wholesale Goods"
        }
    ],
    "sg:phone":"+1 707 485 5845",
    "sg:postcode":"95470",
    "sg:province":"CA",
    "sg:tags":[
        "shop",
        "contractor",
        "machine",
        "industrial",
        "mfg"
    ],
    "wof:name":"Kevin's Welding & Machine",
    "wof:placetype":"venue"
},
  "geometry": {"coordinates":[-123.20527199999999,39.269244],"type":"Point"}
}