{
  "type": "Feature",
  "properties": {
    "iso:country":"US",
    "sg:address":"10050 Fern St",
    "sg:city":"El Monte",
    "sg:classifiers":[
        {
            "category":"Manufacturing",
            "subcategory":"Metals",
            "type":"Manufacturing & Wholesale Goods"
        }
    ],
    "sg:phone":"+1 626 575 1300",
    "sg:postcode":"91733",
    "sg:province":"CA",
    "sg:tags":[
        "polishing"
    ],
    "wof:name":"Rainbow Polishing Co",
    "wof:placetype":"venue"
},
  "geometry": {"coordinates":[-118.049374,34.059022],"type":"Point"}
}