{
  "type": "Feature",
  "properties": {
    "iso:country":"US",
    "sg:address":"897 Embarcadero",
    "sg:city":"Morro Bay",
    "sg:classifiers":[
        {
            "category":"Travel",
            "subcategory":"Hotels & Motels",
            "type":"Entertainment"
        }
    ],
    "sg:phone":"+1 805 772 3434",
    "sg:postcode":"93442",
    "sg:province":"CA",
    "sg:website":"www.andersoninnmorrobay.com",
    "wof:name":"Anderson Inn",
    "wof:placetype":"venue"
},
  "geometry": {"coordinates":[-120.853718,35.367882],"type":"Point"}
}