{
  "type": "Feature",
  "properties": {
    "iso:country":"US",
    "sg:address":"6189 el Camino Real",
    "sg:city":"Carlsbad",
    "sg:classifiers":[
        {
            "category":"Shopping",
            "subcategory":"Bicycles & Sporting Goods",
            "type":"Retail Goods"
        }
    ],
    "sg:phone":"+1 760 597 9503",
    "sg:postcode":"92009",
    "sg:province":"CA",
    "sg:website":"www.batabaseball.com",
    "wof:name":"Bata Baseball Machines",
    "wof:placetype":"venue"
},
  "geometry": {"coordinates":[-117.26678200000001,33.122744],"type":"Point"}
}