{
  "type": "Feature",
  "properties": {
    "iso:country":"US",
    "sg:address":"11340 W Olympic Blvd Ste 240",
    "sg:city":"Los Angeles",
    "sg:classifiers":[
        {
            "category":"Health Services",
            "subcategory":"Dentist",
            "type":"Services"
        }
    ],
    "sg:phone":"+1 310 575 8828",
    "sg:postcode":"90064",
    "sg:province":"CA",
    "wof:name":"Premiere Dental Care",
    "wof:placetype":"venue"
},
  "geometry": {"coordinates":[-118.441329,34.037849],"type":"Point"}
}