{
  "type": "Feature",
  "properties": {
    "addr:full":"368 Merchant St Vacaville CA 95688",
    "addr:housenumber":"368",
    "addr:postcode":"95688",
    "addr:street":"Merchant St",
    "iso:country":"US",
    "sg:address":"368 Merchant St",
    "sg:city":"Vacaville",
    "sg:classifiers":[
        {
            "category":"Personal",
            "subcategory":"Beauty Salon",
            "type":"Services"
        }
    ],
    "sg:phone":"+1 707 448 4646",
    "sg:postcode":"95688",
    "sg:province":"CA",
    "wof:name":"Merle Norman Cosmetics",
    "wof:placetype":"venue"
},
  "geometry": {"coordinates":[-121.98928600000001,38.355751],"type":"Point"}
}