{
  "type": "Feature",
  "properties": {
    "addr:full":"4900 Omar St Fremont CA 94538",
    "addr:housenumber":"4900",
    "addr:postcode":"94538",
    "addr:street":"Omar St",
    "iso:country":"US",
    "sg:address":"4900 Omar St",
    "sg:city":"Fremont",
    "sg:classifiers":[
        {
            "category":"Building & Trades",
            "subcategory":"Construction",
            "type":"Services"
        }
    ],
    "sg:phone":"+1 510 656 5709",
    "sg:postcode":"94538",
    "sg:province":"CA",
    "sg:tags":[
        "roofing",
        "contractor"
    ],
    "wof:name":"Agh Roofing Co",
    "wof:placetype":"venue"
},
  "geometry": {"coordinates":[-121.975521,37.52171],"type":"Point"}
}