{
  "type": "Feature",
  "properties": {
    "iso:country":"US",
    "sg:address":"2023 San Elijo Ave",
    "sg:city":"Cardiff By Sea",
    "sg:classifiers":[
        {
            "category":"Home & Garden",
            "subcategory":"Furniture",
            "type":"Retail Goods"
        }
    ],
    "sg:phone":"+1 760 942 5293",
    "sg:postcode":"92007",
    "sg:province":"CA",
    "wof:name":"Domicile Interiors",
    "wof:placetype":"venue"
},
  "geometry": {"coordinates":[-117.282614,33.021446],"type":"Point"}
}