{
  "type": "Feature",
  "properties": {
    "addr:full":"9210 Alondra Blvd Bellflower CA 90706",
    "addr:housenumber":"9210",
    "addr:postcode":"90706",
    "addr:street":"Alondra Blvd",
    "iso:country":"US",
    "sg:address":"9210 Alondra Blvd",
    "sg:city":"Bellflower",
    "sg:classifiers":[
        {
            "category":"Travel",
            "subcategory":"Travel Agent",
            "type":"Entertainment"
        }
    ],
    "sg:phone":"+1 562 866 6430",
    "sg:postcode":"90706",
    "sg:province":"CA",
    "sg:tags":[
        "agency",
        "bureau"
    ],
    "wof:name":"Costa Azul Travel",
    "wof:placetype":"venue"
},
  "geometry": {"coordinates":[-118.13631700000001,33.889232],"type":"Point"}
}