{
  "type": "Feature",
  "properties": {
    "addr:full":"204 Wayne Ave Oakland CA 94606",
    "addr:housenumber":"204",
    "addr:postcode":"94606",
    "addr:street":"Wayne Ave",
    "iso:country":"US",
    "sg:address":"204 Wayne Ave",
    "sg:city":"Oakland",
    "sg:classifiers":[
        {
            "category":"Shopping",
            "subcategory":"Computers & Home Electronics",
            "type":"Retail Goods"
        }
    ],
    "sg:phone":"+1 510 286 0220",
    "sg:postcode":"94606",
    "sg:province":"CA",
    "sg:tags":[
        "publishing"
    ],
    "wof:name":"Expresscious Moments Prod",
    "wof:placetype":"venue"
},
  "geometry": {"coordinates":[-122.25345900000001,37.802546],"type":"Point"}
}