{
  "type": "Feature",
  "properties": {
    "addr:full":"3315 Almaden Expressway Suite 25 San Jose CA 95118",
    "addr:housenumber":"3315;25",
    "addr:postcode":"95118",
    "addr:street":"Almaden Expressway Suite;Jose",
    "iso:country":"US",
    "sg:address":"3315 Almaden Expressway Suite 25",
    "sg:city":"San Jose",
    "sg:classifiers":[
        {
            "category":"Shopping",
            "subcategory":"Optician",
            "type":"Retail Goods"
        }
    ],
    "sg:phone":"+1 408 265 8644",
    "sg:postcode":"95118",
    "sg:province":"CA",
    "sg:tags":[
        "eyewear"
    ],
    "wof:name":"Optical Connection.",
    "wof:placetype":"venue"
},
  "geometry": {"coordinates":[-121.87862699999999,37.267619],"type":"Point"}
}