{
  "type": "Feature",
  "properties": {
    "iso:country":"US",
    "sg:address":"11272 Westminster Ave",
    "sg:city":"Garden Grove",
    "sg:classifiers":[
        {
            "category":"Autos & Motor Vehicles",
            "subcategory":"Auto Supplies",
            "type":"Retail Goods"
        },
        {
            "category":"Retail",
            "subcategory":"Auto Repair",
            "type":"Services"
        }
    ],
    "sg:phone":"+1 714 636 0286",
    "sg:postcode":"92843",
    "sg:province":"CA",
    "sg:tags":[
        "glass",
        "windshield",
        "installation"
    ],
    "sg:website":"www.ad-autoglass.com",
    "wof:name":"AD Express Auto Glass Inc",
    "wof:placetype":"venue"
},
  "geometry": {"coordinates":[-117.932564,33.75952],"type":"Point"}
}