{
  "type": "Feature",
  "properties": {
    "iso:country":"US",
    "sg:address":"1471 N Waterman Ave",
    "sg:city":"San Bernardino",
    "sg:classifiers":[
        {
            "category":"Health Services",
            "subcategory":"Clinic",
            "type":"Services"
        }
    ],
    "sg:phone":"+1 909 388 4660",
    "sg:postcode":"92404",
    "sg:province":"CA",
    "sg:tags":[
        "medical",
        "group"
    ],
    "wof:name":"United Managed Health Ctr",
    "wof:placetype":"venue"
},
  "geometry": {"coordinates":[-117.278728,34.124123],"type":"Point"}
}