{
  "type": "Feature",
  "properties": {
    "addr:full":"10710 Highway 41 Suite 103 Madera CA 93636",
    "addr:housenumber":"10710",
    "addr:postcode":"93636",
    "addr:street":"Highway 41 Suite 103",
    "iso:country":"US",
    "sg:address":"10710 Highway 41 Suite 103",
    "sg:city":"Madera",
    "sg:classifiers":[
        {
            "category":"Insurance",
            "subcategory":"Insurance Agent",
            "type":"Services"
        },
        {
            "category":"Building & Trades",
            "subcategory":"Cleaning & Sanitation",
            "type":"Services"
        },
        {
            "category":"Retail",
            "subcategory":"Event Space",
            "type":"Services"
        },
        {
            "category":"Building & Trades",
            "subcategory":"Construction",
            "type":"Services"
        },
        {
            "category":"Insurance",
            "subcategory":"Title Insurance",
            "type":"Services"
        }
    ],
    "sg:phone":"+1 559 440 9178",
    "sg:postcode":"93636",
    "sg:province":"CA",
    "sg:tags":[
        "water",
        "lead",
        "asbestos",
        "damage",
        "removal",
        "detection",
        "paint",
        "restoration",
        "fire",
        "remediation",
        "adjuster",
        "homeowner",
        "mold"
    ],
    "sg:website":"http://www.MoldSolution.org",
    "wof:name":"Mold Solutions Inc",
    "wof:placetype":"venue"
},
  "geometry": {"coordinates":[-119.79376999999999,36.915476],"type":"Point"}
}