{
  "type": "Feature",
  "properties": {
    "iso:country":"US",
    "sg:address":"8944 Camellia Ct",
    "sg:city":"Alta Loma",
    "sg:classifiers":[
        {
            "category":"Shopping",
            "type":"Retail Goods"
        }
    ],
    "sg:phone":"+1 909 483 1100",
    "sg:postcode":"91737",
    "sg:province":"CA",
    "sg:tags":[
        "candle"
    ],
    "wof:name":"Cucamonga Candle Co",
    "wof:placetype":"venue"
},
  "geometry": {"coordinates":[-117.610247,34.156297],"type":"Point"}
}