{
  "type": "Feature",
  "properties": {
    "iso:country":"US",
    "sg:address":"30527 San Antonio St",
    "sg:city":"Hayward",
    "sg:classifiers":[
        {
            "category":"Freight",
            "type":"Transportation"
        }
    ],
    "sg:phone":"+1 510 487 1119",
    "sg:postcode":"94544",
    "sg:province":"CA",
    "sg:tags":[
        "warehouse",
        "self",
        "storage"
    ],
    "wof:name":"Peppertree Warehouse",
    "wof:placetype":"venue"
},
  "geometry": {"coordinates":[-122.048355,37.615021],"type":"Point"}
}