{
  "type": "Feature",
  "properties": {
    "addr:full":"3625 Ruffin Rd San Diego CA 92123",
    "addr:housenumber":"3625",
    "addr:postcode":"92123",
    "addr:street":"Ruffin Rd",
    "iso:country":"US",
    "sg:address":"3625 Ruffin Rd",
    "sg:city":"San Diego",
    "sg:classifiers":[
        {
            "category":"Professional",
            "subcategory":"Research",
            "type":"Services"
        }
    ],
    "sg:phone":"+1 858 571 1188",
    "sg:postcode":"92123",
    "sg:province":"CA",
    "sg:tags":[
        "foundation",
        "philanthropic"
    ],
    "wof:name":"BMR Healthquest",
    "wof:placetype":"venue"
},
  "geometry": {"coordinates":[-117.119969,32.8118],"type":"Point"}
}