{
  "type": "Feature",
  "properties": {
    "addr:full":"2140 Professional Dr Roseville CA 95661",
    "addr:housenumber":"2140",
    "addr:postcode":"95661",
    "addr:street":"Professional Dr",
    "iso:country":"US",
    "sg:address":"2140 Professional Dr",
    "sg:city":"Roseville",
    "sg:classifiers":[
        {
            "category":"Wholesale",
            "subcategory":"Stationery",
            "type":"Manufacturing & Wholesale Goods"
        }
    ],
    "sg:phone":"+1 916 780 1300",
    "sg:postcode":"95661",
    "sg:province":"CA",
    "sg:tags":[
        "business",
        "form",
        "system"
    ],
    "sg:website":"www.stratacom.ws",
    "wof:name":"Stratacom",
    "wof:placetype":"venue"
},
  "geometry": {"coordinates":[-121.25335699999999,38.742079],"type":"Point"}
}