{
  "type": "Feature",
  "properties": {
    "iso:country":"US",
    "sg:address":"7665 Formula Pl",
    "sg:city":"San Diego",
    "sg:classifiers":[
        {
            "category":"Manufacturing",
            "subcategory":"Tools & Machinery",
            "type":"Manufacturing & Wholesale Goods"
        }
    ],
    "sg:phone":"+1 858 271 4041",
    "sg:postcode":"92121",
    "sg:province":"CA",
    "sg:tags":[
        "machine",
        "shop"
    ],
    "sg:website":"www.clintprecision.com",
    "wof:name":"Clint Precision Mfg",
    "wof:placetype":"venue"
},
  "geometry": {"coordinates":[-117.1558,32.887803],"type":"Point"}
}