{
  "type": "Feature",
  "properties": {
    "iso:country":"US",
    "sg:address":"105 Cooper Ct.",
    "sg:city":"Los Gatos",
    "sg:classifiers":[
        {
            "category":"Health Services",
            "subcategory":"Clinic",
            "type":"Services"
        }
    ],
    "sg:phone":"+1 408 871 2351",
    "sg:postcode":"95032",
    "sg:province":"CA",
    "sg:tags":[
        "medical"
    ],
    "sg:website":"www.beahmdesigns.com",
    "wof:name":"Beahm Designs",
    "wof:placetype":"venue"
},
  "geometry": {"coordinates":[-121.97236599999999,37.239652],"type":"Point"}
}