{
  "type": "Feature",
  "properties": {
    "iso:country":"US",
    "sg:address":"11835 W. Olympic Blvd Suite 855",
    "sg:city":"Los Angeles",
    "sg:classifiers":[
        {
            "category":"Professional",
            "subcategory":"Computer Services",
            "type":"Services"
        }
    ],
    "sg:phone":"+1 310 775 8077",
    "sg:postcode":"90064",
    "sg:province":"CA",
    "sg:website":"http://www.pringo.com/",
    "wof:name":"Pringo",
    "wof:placetype":"venue"
},
  "geometry": {"coordinates":[-118.450453,34.033074],"type":"Point"}
}