{
  "type": "Feature",
  "properties": {
    "iso:country":"US",
    "sg:address":"55 Legend Rd",
    "sg:city":"San Anselmo",
    "sg:classifiers":[
        {
            "category":"Building & Trades",
            "subcategory":"Landscaping Services",
            "type":"Services"
        }
    ],
    "sg:phone":"+1 415 457 1547",
    "sg:postcode":"94960",
    "sg:province":"CA",
    "sg:tags":[
        "tree"
    ],
    "wof:name":"Ross Valley Tree Svc",
    "wof:placetype":"venue"
},
  "geometry": {"coordinates":[-122.579578,38.004757],"type":"Point"}
}