{
  "type": "Feature",
  "properties": {
    "addr:full":"2480 Refugio Valley Rd Hercules CA 94547",
    "addr:housenumber":"2480",
    "addr:postcode":"94547",
    "addr:street":"Refugio Valley Rd",
    "iso:country":"US",
    "sg:address":"2480 Refugio Valley Rd",
    "sg:city":"Hercules",
    "sg:classifiers":[
        {
            "category":"Education",
            "subcategory":"School",
            "type":"Public Place"
        }
    ],
    "sg:phone":"+1 510 245 9902",
    "sg:postcode":"94547",
    "sg:province":"CA",
    "wof:name":"Hanna Ranch Elementary School",
    "wof:placetype":"venue"
},
  "geometry": {"coordinates":[-122.242654,37.995062],"type":"Point"}
}