{
  "type": "Feature",
  "properties": {
    "addr:full":"2157 Murchison Ave Pomona CA 91768",
    "addr:housenumber":"2157",
    "addr:postcode":"91768",
    "addr:street":"Murchison Ave",
    "iso:country":"US",
    "sg:address":"2157 Murchison Ave",
    "sg:city":"Pomona",
    "sg:classifiers":[
        {
            "category":"Freight",
            "type":"Transportation"
        }
    ],
    "sg:phone":"+1 909 620 7508",
    "sg:postcode":"91768",
    "sg:province":"CA",
    "sg:tags":[
        "commercial",
        "self",
        "storage"
    ],
    "wof:name":"Affordable Mini Storage",
    "wof:placetype":"venue"
},
  "geometry": {"coordinates":[-117.792283,34.071071],"type":"Point"}
}