{
  "type": "Feature",
  "properties": {
    "addr:full":"11313 Painter Ave Whittier CA 90605",
    "addr:housenumber":"11313",
    "addr:postcode":"90605",
    "addr:street":"Painter Ave",
    "iso:country":"US",
    "sg:address":"11313 Painter Ave",
    "sg:city":"Whittier",
    "sg:classifiers":[
        {
            "category":"Professional",
            "type":"Services"
        }
    ],
    "sg:phone":"+1 562 941 2029",
    "sg:postcode":"90605",
    "sg:province":"CA",
    "wof:name":"Maria Talavera",
    "wof:placetype":"venue"
},
  "geometry": {"coordinates":[-118.05334000000001,33.928265],"type":"Point"}
}