{
  "type": "Feature",
  "properties": {
    "addr:full":"108 Cassia Dr Walnut Creek CA 94544",
    "addr:housenumber":"108",
    "addr:postcode":"94544",
    "addr:street":"Cassia Dr",
    "iso:country":"US",
    "sg:address":"108 Cassia Dr",
    "sg:city":"Walnut Creek",
    "sg:classifiers":[
        {
            "category":"Health Services",
            "subcategory":"Doctor",
            "type":"Services"
        }
    ],
    "sg:phone":"+1 925 210 8185",
    "sg:postcode":"94544",
    "sg:province":"CA",
    "sg:tags":[
        "clinic"
    ],
    "wof:name":"Walnut Creek Perotineal Dlysis",
    "wof:placetype":"venue"
},
  "geometry": {"coordinates":[-122.06617300000001,37.637729],"type":"Point"}
}