{
  "type": "Feature",
  "properties": {
    "iso:country":"US",
    "sg:address":"10242 Canoga Ave",
    "sg:city":"Chatsworth",
    "sg:classifiers":[
        {
            "category":"Health Services",
            "subcategory":"Doctor",
            "type":"Services"
        }
    ],
    "sg:phone":"+1 818 882 5252",
    "sg:postcode":"91311",
    "sg:province":"CA",
    "sg:tags":[
        "dentist"
    ],
    "wof:name":"Douglas Dill & Assoc",
    "wof:placetype":"venue"
},
  "geometry": {"coordinates":[-118.597233,34.256424],"type":"Point"}
}