{
  "type": "Feature",
  "properties": {
    "addr:full":"1301 3rd Ave San Diego CA 92101",
    "addr:housenumber":"1301",
    "addr:postcode":"92101",
    "addr:street":"3Rd Ave",
    "iso:country":"US",
    "sg:address":"1301 3rd Ave",
    "sg:city":"San Diego",
    "sg:classifiers":[
        {
            "category":"Utilities",
            "subcategory":"Telephone",
            "type":"Services"
        }
    ],
    "sg:phone":"+1 619 645 5282",
    "sg:postcode":"92101",
    "sg:province":"CA",
    "sg:tags":[
        "telecommunication",
        "provides"
    ],
    "wof:name":"Crystel Telecommunications",
    "wof:placetype":"venue"
},
  "geometry": {"coordinates":[-117.162031,32.719898],"type":"Point"}
}