{
  "type": "Feature",
  "properties": {
    "iso:country":"US",
    "sg:address":"601 S Hill Street",
    "sg:city":"Los Angeles",
    "sg:classifiers":[
        {
            "category":"Shopping",
            "subcategory":"Jewelry",
            "type":"Retail Goods"
        }
    ],
    "sg:phone":"+1 213 627 1767",
    "sg:postcode":"90014",
    "sg:province":"CA",
    "wof:name":"Y & M Diamond Setting",
    "wof:placetype":"venue"
},
  "geometry": {"coordinates":[-118.253089,34.047392],"type":"Point"}
}