{
  "type": "Feature",
  "properties": {
    "iso:country":"US",
    "sg:address":"315 Maple Ave",
    "sg:city":"S San Francisco",
    "sg:classifiers":[
        {
            "category":"Government",
            "subcategory":"Office",
            "type":"Public Place"
        }
    ],
    "sg:phone":"+1 650 829 6670",
    "sg:postcode":"94080",
    "sg:province":"CA",
    "sg:tags":[
        "village"
    ],
    "wof:name":"S San Francisco Building Dept",
    "wof:placetype":"venue"
},
  "geometry": {"coordinates":[-122.412212,37.656666],"type":"Point"}
}