{
  "type": "Feature",
  "properties": {
    "iso:country":"US",
    "sg:address":"5832 Calaveras Cir",
    "sg:city":"La Palma",
    "sg:classifiers":[
        {
            "category":"Retail",
            "subcategory":"Repair Shop",
            "type":"Services"
        }
    ],
    "sg:phone":"+1 714 670 6677",
    "sg:postcode":"90623",
    "sg:province":"CA",
    "sg:tags":[
        "lock",
        "locksmith"
    ],
    "wof:name":"Lucky Locksmith",
    "wof:placetype":"venue"
},
  "geometry": {"coordinates":[-118.032357,33.848886],"type":"Point"}
}