{
  "type": "Feature",
  "properties": {
    "addr:full":"4830 Gardena Ave San Diego CA 92110",
    "addr:housenumber":"4830",
    "addr:postcode":"92110",
    "addr:street":"Gardena Ave",
    "iso:country":"US",
    "sg:address":"4830 Gardena Ave",
    "sg:city":"San Diego",
    "sg:classifiers":[
        {
            "category":"Manufacturing",
            "subcategory":"Tools & Machinery",
            "type":"Manufacturing & Wholesale Goods"
        }
    ],
    "sg:phone":"+1 619 276 5001",
    "sg:postcode":"92110",
    "sg:province":"CA",
    "sg:tags":[
        "machine",
        "copying",
        "supply"
    ],
    "wof:name":"Metro Copier Svc",
    "wof:placetype":"venue"
},
  "geometry": {"coordinates":[-117.198432,32.777375],"type":"Point"}
}