{
  "type": "Feature",
  "properties": {
    "addr:full":"15548 Hesperian Blvd San Lorenzo CA 94580",
    "addr:housenumber":"15548",
    "addr:postcode":"94580",
    "addr:street":"Hesperian Blvd",
    "iso:country":"US",
    "sg:address":"15548 Hesperian Blvd",
    "sg:city":"San Lorenzo",
    "sg:classifiers":[
        {
            "category":"Travel",
            "subcategory":"Travel Agent",
            "type":"Entertainment"
        }
    ],
    "sg:phone":"+1 510 481 2775",
    "sg:postcode":"94580",
    "sg:province":"CA",
    "sg:tags":[
        "agency"
    ],
    "wof:name":"Jema Travel",
    "wof:placetype":"venue"
},
  "geometry": {"coordinates":[-122.129986,37.685888],"type":"Point"}
}