{
  "type": "Feature",
  "properties": {
    "iso:country":"US",
    "sg:address":"2550 Peralta Blvd",
    "sg:city":"Fremont",
    "sg:classifiers":[
        {
            "category":"Social Services",
            "subcategory":"Child Care",
            "type":"Services"
        },
        {
            "category":"Education",
            "subcategory":"School",
            "type":"Public Place"
        }
    ],
    "sg:phone":"+1 510 791 5683",
    "sg:postcode":"94536",
    "sg:province":"CA",
    "sg:tags":[
        "k-",
        "private"
    ],
    "sg:website":"http://www.newhorizonsschool.com",
    "wof:name":"New Horizons School",
    "wof:placetype":"venue"
},
  "geometry": {"coordinates":[-121.992493,37.561749],"type":"Point"}
}