{
  "type": "Feature",
  "properties": {
    "iso:country":"US",
    "sg:address":"6830 Crenshaw Blvd",
    "sg:city":"Los Angeles",
    "sg:classifiers":[
        {
            "category":"Retail",
            "subcategory":"Auto Repair",
            "type":"Services"
        }
    ],
    "sg:phone":"+1 323 753 3434",
    "sg:postcode":"90043",
    "sg:province":"CA",
    "sg:tags":[
        "body",
        "automobile",
        "painting"
    ],
    "wof:name":"Wiggand Auto Body",
    "wof:placetype":"venue"
},
  "geometry": {"coordinates":[-118.330798,33.975832],"type":"Point"}
}