{
  "type": "Feature",
  "properties": {
    "addr:full":"1420 W 11th St Los Angeles CA 90015",
    "addr:housenumber":"1420",
    "addr:postcode":"90015",
    "addr:street":"W 11Th St",
    "iso:country":"US",
    "sg:address":"1420 W 11th St",
    "sg:city":"Los Angeles",
    "sg:classifiers":[
        {
            "category":"Shopping",
            "subcategory":"Clothing, Apparel, & Fashions",
            "type":"Retail Goods"
        }
    ],
    "sg:phone":"+1 213 742 8833",
    "sg:postcode":"90015",
    "sg:province":"CA",
    "sg:tags":[
        "designer"
    ],
    "wof:name":"Freeway",
    "wof:placetype":"venue"
},
  "geometry": {"coordinates":[-118.273132,34.046724],"type":"Point"}
}