{
  "type": "Feature",
  "properties": {
    "addr:full":"Mt. Sutro West Face San Francisco CA 94132",
    "addr:postcode":"94132",
    "addr:street":"West",
    "iso:country":"US",
    "sg:address":"Mt. Sutro West Face",
    "sg:city":"San Francisco",
    "sg:classifiers":[
        {
            "category":"Park",
            "type":"Public Place"
        }
    ],
    "sg:postcode":"94132",
    "sg:province":"CA",
    "wof:name":"Oakhurst Lane",
    "wof:placetype":"venue"
},
  "geometry": {"coordinates":[-122.46151,37.756466],"type":"Point"}
}