{
  "type": "Feature",
  "properties": {
    "iso:country":"US",
    "sg:address":"2525 Cherry Ave",
    "sg:city":"Long Beach",
    "sg:classifiers":[
        {
            "category":"Insurance",
            "subcategory":"Insurance Agent",
            "type":"Services"
        }
    ],
    "sg:phone":"+1 562 989 5521",
    "sg:postcode":"90755",
    "sg:province":"CA",
    "wof:name":"Rdc Insurance Agency",
    "wof:placetype":"venue"
},
  "geometry": {"coordinates":[-118.16767,33.803383],"type":"Point"}
}