{
  "type": "Feature",
  "properties": {
    "iso:country":"US",
    "sg:address":"640 Moraga Rd",
    "sg:city":"Moraga",
    "sg:classifiers":[
        {
            "category":"Professional",
            "type":"Services"
        }
    ],
    "sg:phone":"+1 925 377 1405",
    "sg:postcode":"94556",
    "sg:province":"CA",
    "wof:name":"Jeff Aspillera",
    "wof:placetype":"venue"
},
  "geometry": {"coordinates":[-122.125102,37.854097],"type":"Point"}
}