{
  "type": "Feature",
  "properties": {
    "iso:country":"US",
    "sg:address":"5032 Oakleaf Ave",
    "sg:city":"Carmichael",
    "sg:classifiers":[
        {
            "category":"Professional",
            "type":"Services"
        }
    ],
    "sg:phone":"+1 916 485 9201",
    "sg:postcode":"95608",
    "sg:province":"CA",
    "wof:name":"Progressive Motion",
    "wof:placetype":"venue"
},
  "geometry": {"coordinates":[-121.350246,38.602653],"type":"Point"}
}