{
  "type": "Feature",
  "properties": {
    "iso:country":"US",
    "sg:address":"3662 Bel Aire Plz",
    "sg:city":"Napa",
    "sg:classifiers":[
        {
            "category":"Personal",
            "subcategory":"Barber",
            "type":"Services"
        }
    ],
    "sg:phone":"+1 707 255 3788",
    "sg:postcode":"94558",
    "sg:province":"CA",
    "wof:name":"Barber Shop Of Napa Valley",
    "wof:placetype":"venue"
},
  "geometry": {"coordinates":[-122.306452,38.322465],"type":"Point"}
}