{
  "type": "Feature",
  "properties": {
    "addr:full":"5234 S Peach Ave Fresno CA 93725",
    "addr:housenumber":"5234",
    "addr:postcode":"93725",
    "addr:street":"S Peach Ave",
    "iso:country":"US",
    "sg:address":"5234 S Peach Ave",
    "sg:city":"Fresno",
    "sg:classifiers":[
        {
            "category":"Building & Trades",
            "subcategory":"Construction",
            "type":"Services"
        }
    ],
    "sg:phone":"+1 559 834 5514",
    "sg:postcode":"93725",
    "sg:province":"CA",
    "sg:tags":[
        "maker",
        "cabinet"
    ],
    "sg:website":"www.am-gold.com",
    "wof:name":"AM-Gold Corp",
    "wof:placetype":"venue"
},
  "geometry": {"coordinates":[-119.71776699999999,36.661778],"type":"Point"}
}