{
  "type": "Feature",
  "properties": {
    "addr:full":"30041 Milano Rd Temecula CA 92591",
    "addr:postcode":"30041;92591",
    "addr:street":"Milano Rd",
    "iso:country":"US",
    "sg:address":"30041 Milano Rd",
    "sg:city":"Temecula",
    "sg:classifiers":[
        {
            "category":"Taxi",
            "type":"Transportation"
        }
    ],
    "sg:phone":"+1 951 694 6287",
    "sg:postcode":"92591",
    "sg:province":"CA",
    "sg:tags":[
        "delivery"
    ],
    "wof:name":"Edwin R Carey Jr",
    "wof:placetype":"venue"
},
  "geometry": {"coordinates":[-117.13375000000001,33.537159],"type":"Point"}
}