{
  "type": "Feature",
  "properties": {
    "addr:full":"2944 E Frontera St Apt 123 Anaheim CA 92806",
    "addr:housenumber":"2944;123",
    "addr:postcode":"92806",
    "addr:street":"E Frontera St Apt",
    "iso:country":"US",
    "sg:address":"2944 E Frontera St Apt 123",
    "sg:city":"Anaheim",
    "sg:classifiers":[
        {
            "category":"Real Estate",
            "subcategory":"Real Estate Operator",
            "type":"Services"
        }
    ],
    "sg:phone":"+1 714 630 6549",
    "sg:postcode":"92806",
    "sg:province":"CA",
    "sg:tags":[
        "apartment"
    ],
    "wof:name":"Eastwood Apartments",
    "wof:placetype":"venue"
},
  "geometry": {"coordinates":[-117.862999,33.846001],"type":"Point"}
}