{
  "type": "Feature",
  "properties": {
    "iso:country":"US",
    "sg:address":"15032 Baylor Cir",
    "sg:city":"Huntington Beach",
    "sg:classifiers":[
        {
            "category":"Manufacturing",
            "subcategory":"Tools & Machinery",
            "type":"Manufacturing & Wholesale Goods"
        }
    ],
    "sg:phone":"+1 714 891 1198",
    "sg:postcode":"92647",
    "sg:province":"CA",
    "sg:tags":[
        "pattern",
        "industrial",
        "mfg"
    ],
    "wof:name":"Computer Patterns Express",
    "wof:placetype":"venue"
},
  "geometry": {"coordinates":[-118.018591,33.74332],"type":"Point"}
}