{
  "type": "Feature",
  "properties": {
    "addr:full":"1707 Pico Blvd Santa Monica CA 90405",
    "addr:housenumber":"1707",
    "addr:postcode":"90405",
    "addr:street":"Pico Blvd",
    "iso:country":"US",
    "sg:address":"1707 Pico Blvd",
    "sg:city":"Santa Monica",
    "sg:classifiers":[
        {
            "category":"Restaurant",
            "type":"Food & Drink"
        }
    ],
    "sg:phone":"+1 310 450 6494",
    "sg:postcode":"90405",
    "sg:province":"CA",
    "wof:name":"Barbeque Gardens",
    "wof:placetype":"venue"
},
  "geometry": {"coordinates":[-118.47255199999999,34.017883],"type":"Point"}
}