{
  "type": "Feature",
  "properties": {
    "iso:country":"US",
    "sg:address":"2599 Stevenson Blvd",
    "sg:city":"Fremont",
    "sg:classifiers":[
        {
            "category":"Health Services",
            "subcategory":"Hospital",
            "type":"Services"
        }
    ],
    "sg:phone":"+1 510 791 6800",
    "sg:postcode":"94538",
    "sg:province":"CA",
    "sg:tags":[
        "dialysis"
    ],
    "wof:name":"FMC Dialysis Of Fremont",
    "wof:placetype":"venue"
},
  "geometry": {"coordinates":[-121.972267,37.55079],"type":"Point"}
}