{
  "type": "Feature",
  "properties": {
    "addr:full":"2181 Laurelwood Rd Santa Clara CA 95054",
    "addr:housenumber":"2181",
    "addr:postcode":"95054",
    "addr:street":"Laurelwood Rd",
    "iso:country":"US",
    "sg:address":"2181 Laurelwood Rd",
    "sg:city":"Santa Clara",
    "sg:classifiers":[
        {
            "category":"Autos & Motor Vehicles",
            "subcategory":"Fuel & Gas Station",
            "type":"Retail Goods"
        }
    ],
    "sg:phone":"+1 408 988 8038",
    "sg:postcode":"95054",
    "sg:province":"CA",
    "sg:tags":[
        "oil"
    ],
    "wof:name":"Exxon Santa Clara",
    "wof:placetype":"venue"
},
  "geometry": {"coordinates":[-121.96165999999999,37.381936],"type":"Point"}
}