{
  "type": "Feature",
  "properties": {
    "addr:full":"400 Evelyn Ave Albany CA 94706",
    "addr:housenumber":"400",
    "addr:postcode":"94706",
    "addr:street":"Evelyn Ave",
    "iso:country":"US",
    "sg:address":"400 Evelyn Ave",
    "sg:city":"Albany",
    "sg:classifiers":[
        {
            "category":"Professional",
            "type":"Services"
        }
    ],
    "sg:phone":"+1 510 548 8703",
    "sg:postcode":"94706",
    "sg:province":"CA",
    "sg:tags":[
        "establishment"
    ],
    "wof:name":"Say Bill Core Energetics",
    "wof:placetype":"venue"
},
  "geometry": {"coordinates":[-122.296775,37.897544],"type":"Point"}
}