{
  "type": "Feature",
  "properties": {
    "addr:full":"3414 Regional Pkwy Santa Rosa CA 95403",
    "addr:housenumber":"3414",
    "addr:postcode":"95403",
    "addr:street":"Regional Pkwy",
    "iso:country":"US",
    "sg:address":"3414 Regional Pkwy",
    "sg:city":"Santa Rosa",
    "sg:classifiers":[
        {
            "category":"Professional",
            "subcategory":"Testing Lab",
            "type":"Services"
        }
    ],
    "sg:phone":"+1 707 575 1310",
    "sg:postcode":"95403",
    "sg:province":"CA",
    "sg:tags":[
        "laboratory"
    ],
    "sg:website":"www.thermochem.com",
    "wof:name":"Thermochem Inc",
    "wof:placetype":"venue"
},
  "geometry": {"coordinates":[-122.78825500000001,38.505752],"type":"Point"}
}