{
  "type": "Feature",
  "properties": {
    "iso:country":"US",
    "sg:address":"3414 Regional Pkwy",
    "sg:city":"Santa Rosa",
    "sg:classifiers":[
        {
            "category":"Professional",
            "subcategory":"Testing Lab",
            "type":"Services"
        }
    ],
    "sg:phone":"+1 707 575 1310",
    "sg:postcode":"95403",
    "sg:province":"CA",
    "sg:tags":[
        "laboratory"
    ],
    "sg:website":"www.thermochem.com",
    "wof:name":"Thermochem Inc",
    "wof:placetype":"venue"
},
  "geometry": {"coordinates":[-122.788255,38.505752],"type":"Point"}
}