{
  "type": "Feature",
  "properties": {
    "addr:full":"24531 Trabuco Road Suite I Lake Forest CA 92630",
    "addr:housenumber":"24531",
    "addr:postcode":"92630",
    "addr:street":"Trabuco Road Suite I",
    "iso:country":"US",
    "sg:address":"24531 Trabuco Road Suite I",
    "sg:city":"Lake Forest",
    "sg:classifiers":[
        {
            "category":"Retail",
            "subcategory":"Laundry & Dry Cleaning",
            "type":"Services"
        }
    ],
    "sg:phone":"+1 949 951 3022",
    "sg:postcode":"92630",
    "sg:province":"CA",
    "wof:name":"Spectrum Cleaners",
    "wof:placetype":"venue"
},
  "geometry": {"coordinates":[-117.70185499999999,33.65474],"type":"Point"}
}