{
  "type": "Feature",
  "properties": {
    "iso:country":"US",
    "sg:address":"14074 Irish Town Rd",
    "sg:city":"Pine Grove",
    "sg:classifiers":[
        {
            "category":"Wholesale",
            "subcategory":"Machinery & Supplies",
            "type":"Manufacturing & Wholesale Goods"
        }
    ],
    "sg:phone":"+1 209 296 1540",
    "sg:postcode":"95665",
    "sg:province":"CA",
    "sg:tags":[
        "equipment",
        "industrial"
    ],
    "wof:name":"Cal Pac Graphics",
    "wof:placetype":"venue"
},
  "geometry": {"coordinates":[-120.66029899999999,38.410497],"type":"Point"}
}