{
  "type": "Feature",
  "properties": {
    "addr:full":"1919 Dennis Ln Santa Rosa CA 95403",
    "addr:housenumber":"1919",
    "addr:postcode":"95403",
    "addr:street":"Dennis Ln",
    "iso:country":"US",
    "sg:address":"1919 Dennis Ln",
    "sg:city":"Santa Rosa",
    "sg:classifiers":[
        {
            "category":"Wholesale",
            "subcategory":"Plants",
            "type":"Manufacturing & Wholesale Goods"
        }
    ],
    "sg:phone":"+1 707 566 8133",
    "sg:postcode":"95403",
    "sg:province":"CA",
    "sg:tags":[
        "nursery",
        "tree"
    ],
    "wof:name":"Sweetwater Nursery Inc",
    "wof:placetype":"venue"
},
  "geometry": {"coordinates":[-122.750347,38.482737],"type":"Point"}
}