{
  "type": "Feature",
  "properties": {
    "addr:full":"2628 International Blvd Oakland CA 94601",
    "addr:housenumber":"2628",
    "addr:postcode":"94601",
    "addr:street":"International Blvd",
    "iso:country":"US",
    "sg:address":"2628 International Blvd",
    "sg:city":"Oakland",
    "sg:classifiers":[
        {
            "category":"Shopping",
            "subcategory":"Clothing, Apparel, & Fashions",
            "type":"Retail Goods"
        }
    ],
    "sg:phone":"+1 510 261 7136",
    "sg:postcode":"94601",
    "sg:province":"CA",
    "wof:name":"Concept 101",
    "wof:placetype":"venue"
},
  "geometry": {"coordinates":[-122.23173300000001,37.781016],"type":"Point"}
}