{
  "type": "Feature",
  "properties": {
    "addr:full":"1015 Battery St. San Francisco CA 94111",
    "addr:housenumber":"1015",
    "addr:postcode":"94111",
    "addr:street":"Battery St.",
    "iso:country":"US",
    "sg:address":"1015 Battery St.",
    "sg:city":"San Francisco",
    "sg:classifiers":[
        {
            "category":"Retail",
            "subcategory":"Portrait Studio",
            "type":"Services"
        },
        {
            "category":"Professional",
            "subcategory":"Printing & Photocopies",
            "type":"Services"
        }
    ],
    "sg:phone":"+1 415 956 1954",
    "sg:postcode":"94111",
    "sg:province":"CA",
    "sg:tags":[
        "photography",
        "store"
    ],
    "wof:name":"Natural Color Photo Lab",
    "wof:placetype":"venue"
},
  "geometry": {"coordinates":[-122.401605,37.800646],"type":"Point"}
}