{
  "type": "Feature",
  "properties": {
    "addr:full":"9044 Melrose Avenue West Hollywood CA 90069",
    "addr:housenumber":"9044",
    "addr:postcode":"90069",
    "addr:street":"Melrose Avenue",
    "iso:country":"US",
    "sg:address":"9044 Melrose Avenue",
    "sg:city":"West Hollywood",
    "sg:classifiers":[
        {
            "category":"Retail",
            "subcategory":"Auto Rental",
            "type":"Services"
        }
    ],
    "sg:phone":"+1 310 393 9100",
    "sg:postcode":"90069",
    "sg:province":"CA",
    "sg:tags":[
        "car"
    ],
    "wof:name":"Executive Car Leasing",
    "wof:placetype":"venue"
},
  "geometry": {"coordinates":[-118.389152,34.080883],"type":"Point"}
}