{
  "type": "Feature",
  "properties": {
    "addr:full":"13909 Bettencourt St Cerritos CA 90703",
    "addr:housenumber":"13909",
    "addr:postcode":"ca 90703",
    "addr:street":"Bettencourt St",
    "iso:country":"US",
    "sg:address":"13909 Bettencourt St",
    "sg:city":"Cerritos",
    "sg:classifiers":[
        {
            "category":"Manufacturing",
            "subcategory":"Metals",
            "type":"Manufacturing & Wholesale Goods"
        }
    ],
    "sg:phone":"+1 562 926 6682",
    "sg:postcode":"90703",
    "sg:province":"CA",
    "sg:tags":[
        "pipe",
        "fitting",
        "valve"
    ],
    "sg:website":"www.warden.com",
    "wof:name":"Guy L Warden & Sons",
    "wof:placetype":"venue"
},
  "geometry": {"coordinates":[-118.03595900000001,33.876954],"type":"Point"}
}