{
  "type": "Feature",
  "properties": {
    "addr:full":"5361 N Pershing Ave Stockton CA 95207",
    "addr:housenumber":"5361",
    "addr:postcode":"95207",
    "addr:street":"N Pershing Ave",
    "iso:country":"US",
    "sg:address":"5361 N Pershing Ave",
    "sg:city":"Stockton",
    "sg:classifiers":[
        {
            "category":"Professional",
            "type":"Services"
        }
    ],
    "sg:phone":"+1 209 235 5640",
    "sg:postcode":"95207",
    "sg:province":"CA",
    "sg:tags":[
        "establishment"
    ],
    "wof:name":"Lone Ready Com",
    "wof:placetype":"venue"
},
  "geometry": {"coordinates":[-121.32381700000001,37.9931],"type":"Point"}
}