{
  "type": "Feature",
  "properties": {
    "addr:full":"7942 Ney Ave Oakland CA 94605",
    "addr:housenumber":"7942",
    "addr:postcode":"94605",
    "addr:street":"Ney Ave",
    "iso:country":"US",
    "sg:address":"7942 Ney Ave",
    "sg:city":"Oakland",
    "sg:classifiers":[
        {
            "category":"Social Services",
            "subcategory":"Child Care",
            "type":"Services"
        }
    ],
    "sg:phone":"+1 510 568 5100",
    "sg:postcode":"94605",
    "sg:province":"CA",
    "sg:tags":[
        "day"
    ],
    "wof:name":"Williams Child Care Development",
    "wof:placetype":"venue"
},
  "geometry": {"coordinates":[-122.165001,37.7654],"type":"Point"}
}