{
  "type": "Feature",
  "properties": {
    "iso:country":"US",
    "sg:address":"156 W Foothill Blvd",
    "sg:city":"Upland",
    "sg:classifiers":[
        {
            "category":"Restaurant",
            "type":"Food & Drink"
        }
    ],
    "sg:phone":"+1 909 931 9057",
    "sg:postcode":"91786",
    "sg:province":"CA",
    "sg:tags":[
        "eating"
    ],
    "wof:name":"Juan Pollo Store 22",
    "wof:placetype":"venue"
},
  "geometry": {"coordinates":[-117.65334300000001,34.106922],"type":"Point"}
}