{
  "type": "Feature",
  "properties": {
    "addr:full":"2470 Nut Tree Rd Vacaville CA 95687",
    "addr:housenumber":"2470",
    "addr:postcode":"95687",
    "addr:street":"Nut Tree Rd",
    "iso:country":"US",
    "sg:address":"2470 Nut Tree Rd",
    "sg:city":"Vacaville",
    "sg:classifiers":[
        {
            "category":"Government",
            "subcategory":"Office",
            "type":"Public Place"
        }
    ],
    "sg:phone":"+1 707 446 5548",
    "sg:postcode":"95687",
    "sg:province":"CA",
    "sg:tags":[
        "housing",
        "agency"
    ],
    "wof:name":"Senior Vacaville Housing Corp",
    "wof:placetype":"venue"
},
  "geometry": {"coordinates":[-121.953221,38.335653],"type":"Point"}
}