{
  "type": "Feature",
  "properties": {
    "iso:country":"US",
    "sg:address":"328 W 3rd St",
    "sg:city":"Oxnard",
    "sg:classifiers":[
        {
            "category":"Professional",
            "subcategory":"Lawyer & Legal Services",
            "type":"Services"
        }
    ],
    "sg:phone":"+1 805 483 5808",
    "sg:postcode":"93030",
    "sg:province":"CA",
    "sg:tags":[
        "attorney"
    ],
    "wof:name":"Wolff & Kinsler",
    "wof:placetype":"venue"
},
  "geometry": {"coordinates":[-119.180134,34.200246],"type":"Point"}
}