{
  "type": "Feature",
  "properties": {
    "addr:full":"7736 Fay Ave Ste 102 La Jolla CA 92037",
    "addr:housenumber":"7736",
    "addr:postcode":"92037",
    "addr:street":"Fay Ave Ste 102",
    "iso:country":"US",
    "sg:address":"7736 Fay Ave Ste 102",
    "sg:city":"La Jolla",
    "sg:classifiers":[
        {
            "category":"Personal",
            "subcategory":"Day Spa",
            "type":"Services"
        }
    ],
    "sg:phone":"+1 858 459 4965",
    "sg:postcode":"92037",
    "sg:province":"CA",
    "sg:website":"www.birdiedayspa.com",
    "wof:name":"Birdie Day Spa",
    "wof:placetype":"venue"
},
  "geometry": {"coordinates":[-117.275206,32.843936],"type":"Point"}
}