{
  "type": "Feature",
  "properties": {
    "iso:country":"US",
    "sg:address":"918 Tingley Ln",
    "sg:city":"San Diego",
    "sg:classifiers":[
        {
            "category":"Arts & Performance",
            "subcategory":"Arts Center",
            "type":"Entertainment"
        }
    ],
    "sg:phone":"+1 619 523 6296",
    "sg:postcode":"92106",
    "sg:province":"CA",
    "sg:tags":[
        "performing"
    ],
    "sg:website":"www.montesanomusic.com",
    "wof:name":"Montesano Music",
    "wof:placetype":"venue"
},
  "geometry": {"coordinates":[-117.244675,32.721259],"type":"Point"}
}