{
  "type": "Feature",
  "properties": {
    "iso:country":"US",
    "sg:address":"1906 W Garvey Ave S",
    "sg:city":"West Covina",
    "sg:classifiers":[
        {
            "category":"Professional",
            "subcategory":"Lawyer & Legal Services",
            "type":"Services"
        }
    ],
    "sg:phone":"+1 626 472 7346",
    "sg:postcode":"91790",
    "sg:province":"CA",
    "sg:tags":[
        "attorney"
    ],
    "wof:name":"Mc Curdy & Fuller",
    "wof:placetype":"venue"
},
  "geometry": {"coordinates":[-117.947422,34.071156],"type":"Point"}
}