{
  "type": "Feature",
  "properties": {
    "iso:country":"US",
    "sg:address":"10180 California Waters Dr",
    "sg:city":"Spring Valley",
    "sg:classifiers":[
        {
            "category":"Wholesale",
            "subcategory":"Chemicals & Plastics",
            "type":"Manufacturing & Wholesale Goods"
        }
    ],
    "sg:phone":"+1 619 390 0101",
    "sg:postcode":"91977",
    "sg:province":"CA",
    "sg:tags":[
        "grocery",
        "alcoholic"
    ],
    "wof:name":"Beer Kegs Market",
    "wof:placetype":"venue"
},
  "geometry": {"coordinates":[-116.974523,32.727883],"type":"Point"}
}