{
  "type": "Feature",
  "properties": {
    "iso:country":"US",
    "sg:address":"805 Valley Ave",
    "sg:city":"Solana Beach",
    "sg:classifiers":[
        {
            "category":"Taxi",
            "type":"Transportation"
        }
    ],
    "sg:phone":"+1 760 815 3377",
    "sg:postcode":"92075",
    "sg:province":"CA",
    "sg:tags":[
        "taxicab"
    ],
    "wof:name":"Dean's Cab",
    "wof:placetype":"venue"
},
  "geometry": {"coordinates":[-117.258329,32.984447],"type":"Point"}
}