{
  "type": "Feature",
  "properties": {
    "addr:full":"5926 55th St Sacramento CA 95824",
    "addr:housenumber":"5926",
    "addr:postcode":"95824",
    "addr:street":"55Th St",
    "iso:country":"US",
    "sg:address":"5926 55th St",
    "sg:city":"Sacramento",
    "sg:classifiers":[
        {
            "category":"Building & Trades",
            "subcategory":"Landscaping Services",
            "type":"Services"
        }
    ],
    "sg:phone":"+1 916 452 7468",
    "sg:postcode":"95824",
    "sg:province":"CA",
    "wof:name":"Mendozas Landscape Service",
    "wof:placetype":"venue"
},
  "geometry": {"coordinates":[-121.437465,38.517781],"type":"Point"}
}