{
  "type": "Feature",
  "properties": {
    "addr:full":"650 Castro Street Suite 300 Mountain View CA 94041",
    "addr:housenumber":"650",
    "addr:postcode":"94041",
    "addr:street":"Castro Street Suite 300",
    "iso:country":"US",
    "sg:address":"650 Castro Street Suite 300",
    "sg:city":"Mountain View",
    "sg:classifiers":[
        {
            "category":"Personal",
            "type":"Services"
        },
        {
            "category":"Communications",
            "type":"Services"
        }
    ],
    "sg:phone":"+1 650 903 0800",
    "sg:postcode":"94041",
    "sg:province":"CA",
    "sg:tags":[
        "web",
        "design",
        "local"
    ],
    "sg:website":"www.mozilla.com/",
    "wof:name":"Mozilla Corporation",
    "wof:placetype":"venue"
},
  "geometry": {"coordinates":[-122.08275999999999,37.388095],"type":"Point"}
}