{
  "type": "Feature",
  "properties": {
    "addr:full":"10754 Burbank Blvd North Hollywood CA 91601",
    "addr:housenumber":"10754",
    "addr:postcode":"91601",
    "addr:street":"Burbank Blvd",
    "iso:country":"US",
    "sg:address":"10754 Burbank Blvd",
    "sg:city":"North Hollywood",
    "sg:classifiers":[
        {
            "category":"Professional",
            "subcategory":"Employment Agencies",
            "type":"Services"
        }
    ],
    "sg:phone":"+1 818 763 1283",
    "sg:postcode":"91601",
    "sg:province":"CA",
    "wof:name":"Star Employment Agency",
    "wof:placetype":"venue"
},
  "geometry": {"coordinates":[-118.364998,34.172199],"type":"Point"}
}