{
  "type": "Feature",
  "properties": {
    "addr:full":"16830 Kingsbury St Granada Hills CA 91344",
    "addr:housenumber":"16830",
    "addr:postcode":"91344",
    "addr:street":"Kingsbury St",
    "iso:country":"US",
    "sg:address":"16830 Kingsbury St",
    "sg:city":"Granada Hills",
    "sg:classifiers":[
        {
            "category":"Real Estate",
            "subcategory":"Real Estate Operator",
            "type":"Services"
        }
    ],
    "sg:phone":"+1 818 363 4660",
    "sg:postcode":"91344",
    "sg:province":"CA",
    "sg:tags":[
        "apartment"
    ],
    "wof:name":"Casa Granada",
    "wof:placetype":"venue"
},
  "geometry": {"coordinates":[-118.49844400000001,34.263078],"type":"Point"}
}