{
  "type": "Feature",
  "properties": {
    "addr:full":"4763 18th St San Francisco CA 94114",
    "addr:housenumber":"4763",
    "addr:postcode":"94114",
    "addr:street":"18Th St",
    "iso:country":"US",
    "sg:address":"4763 18th St",
    "sg:city":"San Francisco",
    "sg:classifiers":[
        {
            "category":"Professional",
            "type":"Services"
        }
    ],
    "sg:phone":"+1 415 552 6693",
    "sg:postcode":"94114",
    "sg:province":"CA",
    "wof:name":"Fig 3",
    "wof:placetype":"venue"
},
  "geometry": {"coordinates":[-122.443918,37.760013],"type":"Point"}
}