{
  "type": "Feature",
  "properties": {
    "iso:country":"US",
    "sg:address":"2066 W Shaw Ave",
    "sg:city":"Fresno",
    "sg:classifiers":[
        {
            "category":"Restaurant",
            "type":"Food & Drink"
        }
    ],
    "sg:phone":"+1 559 432 6118",
    "sg:postcode":"93711",
    "sg:province":"CA",
    "wof:name":"Tang Dynasty",
    "wof:placetype":"venue"
},
  "geometry": {"coordinates":[-119.828924,36.808343],"type":"Point"}
}