{
  "type": "Feature",
  "properties": {
    "iso:country":"US",
    "sg:address":"783 Jamacha Rd",
    "sg:city":"El Cajon",
    "sg:classifiers":[
        {
            "category":"Professional",
            "subcategory":"Secretarial Services",
            "type":"Services"
        }
    ],
    "sg:phone":"+1 619 440 3214",
    "sg:postcode":"92019",
    "sg:province":"CA",
    "sg:tags":[
        "reporting",
        "court"
    ],
    "wof:name":"Bonnie's Typing",
    "wof:placetype":"venue"
},
  "geometry": {"coordinates":[-116.927916,32.787312],"type":"Point"}
}