{
  "type": "Feature",
  "properties": {
    "acgov:api":"0.0",
    "acgov:type":"K-8",
    "addr:full":"One Estates Drive Piedmont CA",
    "wof:categories":[
        "education_and_religion:education=school"
    ],
    "wof:name":"Corpus Christi Elementary",
    "wof:placetype":"venue"
},
  "geometry": {"coordinates":[-122.21372298912654,37.81387200365263],"type":"Point"}
}