{
  "type": "Feature",
  "properties": {
    "addr:full":"1804 Tribute Rd Ste B Sacramento CA 95815",
    "addr:housenumber":"1804",
    "addr:postcode":"95815",
    "addr:street":"Tribute Rd Ste B",
    "iso:country":"US",
    "sg:address":"1804 Tribute Rd Ste B",
    "sg:city":"Sacramento",
    "sg:classifiers":[
        {
            "category":"Professional",
            "subcategory":"Printing & Photocopies",
            "type":"Services"
        }
    ],
    "sg:phone":"+1 916 564 4712",
    "sg:postcode":"95815",
    "sg:province":"CA",
    "sg:tags":[
        "duplicating",
        "copying"
    ],
    "wof:name":"Superior Photocopy Service",
    "wof:placetype":"venue"
},
  "geometry": {"coordinates":[-121.445328,38.59903],"type":"Point"}
}