{
  "type": "Feature",
  "properties": {
    "iso:country":"US",
    "sg:address":"4450 Rosewood Dr",
    "sg:city":"Pleasanton",
    "sg:classifiers":[
        {
            "category":"Utilities",
            "subcategory":"Telephone",
            "type":"Services"
        }
    ],
    "sg:phone":"+1 925 224 5202",
    "sg:postcode":"94588",
    "sg:province":"CA",
    "sg:tags":[
        "communications"
    ],
    "wof:name":"AT&T",
    "wof:placetype":"venue"
},
  "geometry": {"coordinates":[-121.88164,37.700974],"type":"Point"}
}