{
  "type": "Feature",
  "properties": {
    "addr:full":"175 W 25th Ave San Mateo CA 94403",
    "addr:housenumber":"175",
    "addr:postcode":"94403",
    "addr:street":"W 25Th Ave",
    "iso:country":"US",
    "sg:address":"175 W 25th Ave",
    "sg:city":"San Mateo",
    "sg:classifiers":[
        {
            "category":"Food & Beverages",
            "subcategory":"Groceries & Convenience Stores",
            "type":"Retail Goods"
        }
    ],
    "sg:phone":"+1 650 571 8620",
    "sg:postcode":"94403",
    "sg:province":"CA",
    "sg:tags":[
        "grocer"
    ],
    "wof:name":"W 25th Avenue Food Mart",
    "wof:placetype":"venue"
},
  "geometry": {"coordinates":[-122.307725,37.543623],"type":"Point"}
}