{
  "type": "Feature",
  "properties": {
    "iso:country":"US",
    "sg:address":"522 Woodbury Rd",
    "sg:city":"Glendale",
    "sg:classifiers":[
        {
            "category":"Wholesale",
            "subcategory":"Non-durable Goods",
            "type":"Manufacturing & Wholesale Goods"
        }
    ],
    "sg:phone":"+1 818 244 0981",
    "sg:postcode":"91206",
    "sg:province":"CA",
    "sg:tags":[
        "dry",
        "goods-wholesale"
    ],
    "wof:name":"Trinity Home Medical Supply In",
    "wof:placetype":"venue"
},
  "geometry": {"coordinates":[-118.235511,34.154795],"type":"Point"}
}