{
  "type": "Feature",
  "properties": {
    "addr:full":"13586 Preciado Ave Chino CA 91710",
    "addr:housenumber":"13586",
    "addr:postcode":"91710",
    "addr:street":"Preciado Ave",
    "iso:country":"US",
    "sg:address":"13586 Preciado Ave",
    "sg:city":"Chino",
    "sg:classifiers":[
        {
            "category":"Building & Trades",
            "subcategory":"Construction",
            "type":"Services"
        }
    ],
    "sg:phone":"+1 909 627 9429",
    "sg:postcode":"91710",
    "sg:province":"CA",
    "sg:tags":[
        "coping",
        "plastering",
        "tiling",
        "pool",
        "swimming"
    ],
    "wof:name":"Gary's Pool Svc",
    "wof:placetype":"venue"
},
  "geometry": {"coordinates":[-117.712024,34.006404],"type":"Point"}
}