{
  "type": "Feature",
  "properties": {
    "iso:country":"US",
    "sg:address":"174 Smoketree Dr",
    "sg:city":"El Centro",
    "sg:classifiers":[
        {
            "category":"Wholesale",
            "subcategory":"Fruits & Vegetables",
            "type":"Manufacturing & Wholesale Goods"
        }
    ],
    "sg:phone":"+1 760 337 1271",
    "sg:postcode":"92243",
    "sg:province":"CA",
    "sg:tags":[
        "importer",
        "produce"
    ],
    "wof:name":"Liaison",
    "wof:placetype":"venue"
},
  "geometry": {"coordinates":[-115.545895,32.775595],"type":"Point"}
}