{
  "type": "Feature",
  "properties": {
    "iso:country":"US",
    "sg:address":"1425 Leimert Blvd Ste 403",
    "sg:city":"Oakland",
    "sg:classifiers":[
        {
            "category":"Professional",
            "subcategory":"Lawyer & Legal Services",
            "type":"Services"
        }
    ],
    "sg:phone":"+1 510 336 9500",
    "sg:postcode":"94602",
    "sg:province":"CA",
    "wof:name":"KERSHNER GARY",
    "wof:placetype":"venue"
},
  "geometry": {"coordinates":[-122.21272500000001,37.811668],"type":"Point"}
}