{
  "type": "Feature",
  "properties": {
    "addr:full":"5251 E 2nd St Long Beach CA 90803",
    "addr:housenumber":"5251",
    "addr:postcode":"90803",
    "addr:street":"E 2Nd St",
    "iso:country":"US",
    "sg:address":"5251 E 2nd St",
    "sg:city":"Long Beach",
    "sg:classifiers":[
        {
            "category":"Coffee & Tea",
            "type":"Food & Drink"
        }
    ],
    "sg:menulink":"http://www.allmenus.com/ca/long-beach-lakewood/109497-starbucks-coffee/menu/",
    "sg:phone":"+1 562 987 5043",
    "sg:postcode":"90803",
    "sg:province":"CA",
    "sg:tags":[
        "american"
    ],
    "wof:name":"Starbucks Coffee",
    "wof:placetype":"venue"
},
  "geometry": {"coordinates":[-118.133448,33.759948],"type":"Point"}
}