{
  "type": "Feature",
  "properties": {
    "addr:full":"2068 E Valley Pkwy Escondido CA 92027",
    "addr:housenumber":"2068",
    "addr:postcode":"92027",
    "addr:street":"E Valley Pkwy",
    "iso:country":"US",
    "sg:address":"2068 E Valley Pkwy",
    "sg:city":"Escondido",
    "sg:classifiers":[
        {
            "category":"Shopping",
            "subcategory":"Thrift Store",
            "type":"Retail Goods"
        },
        {
            "category":"Banks & Credit Unions",
            "subcategory":"Bank",
            "type":"Services"
        },
        {
            "category":"Shopping",
            "subcategory":"Used Merchandise",
            "type":"Retail Goods"
        }
    ],
    "sg:phone":"+1 760 746 7532",
    "sg:postcode":"92027",
    "sg:province":"CA",
    "sg:tags":[
        "shop",
        "resale",
        "second",
        "hand"
    ],
    "wof:name":"Assistance League Of Inland North County",
    "wof:placetype":"venue"
},
  "geometry": {"coordinates":[-117.050499,33.138119],"type":"Point"}
}