{
  "type": "Feature",
  "properties": {
    "addr:full":"7630 S Leonard Ave Fowler CA 93625",
    "addr:housenumber":"7630",
    "addr:postcode":"93625",
    "addr:street":"S Leonard Ave",
    "iso:country":"US",
    "sg:address":"7630 S Leonard Ave",
    "sg:city":"Fowler",
    "sg:classifiers":[
        {
            "category":"Farming",
            "subcategory":"Orchard",
            "type":"Manufacturing & Wholesale Goods"
        }
    ],
    "sg:phone":"+1 559 834 3002",
    "sg:postcode":"93625",
    "sg:province":"CA",
    "sg:tags":[
        "fruit",
        "tree"
    ],
    "wof:name":"Oliver Farms Inc",
    "wof:placetype":"venue"
},
  "geometry": {"coordinates":[-119.637135,36.629018],"type":"Point"}
}