{
  "type": "Feature",
  "properties": {
    "iso:country":"US",
    "sg:address":"9773 Sierra Ave",
    "sg:city":"Fontana",
    "sg:classifiers":[
        {
            "category":"Manufacturing",
            "subcategory":"Food",
            "type":"Manufacturing & Wholesale Goods"
        },
        {
            "category":"Food & Beverages",
            "subcategory":"Fruits & Vegetables",
            "type":"Retail Goods"
        }
    ],
    "sg:phone":"+1 909 349 0059",
    "sg:postcode":"92335",
    "sg:province":"CA",
    "sg:tags":[
        "herb",
        "spices-wholesale",
        "manufacturer"
    ],
    "wof:name":"Humberto Perez",
    "wof:placetype":"venue"
},
  "geometry": {"coordinates":[-117.435677,34.076278],"type":"Point"}
}