{
  "type": "Feature",
  "properties": {
    "iso:country":"US",
    "sg:address":"803 Award Dr",
    "sg:city":"Colton",
    "sg:classifiers":[
        {
            "category":"Wholesale",
            "subcategory":"Apparel",
            "type":"Manufacturing & Wholesale Goods"
        }
    ],
    "sg:phone":"+1 909 824 2652",
    "sg:postcode":"92324",
    "sg:province":"CA",
    "sg:tags":[
        "footwear"
    ],
    "wof:name":"K Swiss",
    "wof:placetype":"venue"
},
  "geometry": {"coordinates":[-117.307379,34.072633],"type":"Point"}
}