{
  "type": "Feature",
  "properties": {
    "addr:full":"2900 S Rodeo Gulch Rd Soquel CA 95073",
    "addr:housenumber":"2900",
    "addr:postcode":"95073",
    "addr:street":"S Rodeo Gulch Rd",
    "iso:country":"US",
    "sg:address":"2900 S Rodeo Gulch Rd",
    "sg:city":"Soquel",
    "sg:classifiers":[
        {
            "category":"Building & Trades",
            "subcategory":"Landscaping Services",
            "type":"Services"
        }
    ],
    "sg:phone":"+1 831 476 4486",
    "sg:postcode":"95073",
    "sg:province":"CA",
    "sg:tags":[
        "landscape",
        "contractor"
    ],
    "wof:name":"Manus Landscaping Service",
    "wof:placetype":"venue"
},
  "geometry": {"coordinates":[-121.96949600000001,36.987072],"type":"Point"}
}