{
  "type": "Feature",
  "properties": {
    "addr:full":"1263 McLaughlin Ave San Jose CA 95122",
    "addr:housenumber":"1263",
    "addr:postcode":"95122",
    "addr:street":"Mclaughlin Ave",
    "iso:country":"US",
    "sg:address":"1263 McLaughlin Ave",
    "sg:city":"San Jose",
    "sg:classifiers":[
        {
            "category":"Building & Trades",
            "subcategory":"Landscaping Services",
            "type":"Services"
        }
    ],
    "sg:phone":"+1 408 280 6545",
    "sg:postcode":"95122",
    "sg:province":"CA",
    "sg:tags":[
        "lawn",
        "maintenance",
        "grounds"
    ],
    "wof:name":"Aly's Tree Trimming & Yard",
    "wof:placetype":"venue"
},
  "geometry": {"coordinates":[-121.851699,37.330607],"type":"Point"}
}