{
  "type": "Feature",
  "properties": {
    "addr:full":"3 Civic Center Dr San Marcos CA 92069",
    "addr:housenumber":"3",
    "addr:postcode":"92069",
    "addr:street":"Civic Center Dr",
    "iso:country":"US",
    "sg:address":"3 Civic Center Dr",
    "sg:city":"San Marcos",
    "sg:classifiers":[
        {
            "category":"Government",
            "subcategory":"Office",
            "type":"Public Place"
        }
    ],
    "sg:phone":"+1 760 744 9000",
    "sg:postcode":"92069",
    "sg:province":"CA",
    "sg:tags":[
        "village"
    ],
    "sg:website":"www.san-marcos.net",
    "wof:name":"San Marcos Community Svc",
    "wof:placetype":"venue"
},
  "geometry": {"coordinates":[-117.15902,33.141077],"type":"Point"}
}