{
  "type": "Feature",
  "properties": {
    "addr:full":"3450 Wilshire Blvd Los Angeles CA 90010",
    "addr:housenumber":"3450",
    "addr:postcode":"90010",
    "addr:street":"Wilshire Blvd",
    "iso:country":"US",
    "sg:address":"3450 Wilshire Blvd",
    "sg:city":"Los Angeles",
    "sg:classifiers":[
        {
            "category":"Professional",
            "subcategory":"Lawyer & Legal Services",
            "type":"Services"
        }
    ],
    "sg:phone":"+1 213 387 1400",
    "sg:postcode":"90010",
    "sg:province":"CA",
    "sg:tags":[
        "attorney"
    ],
    "wof:name":"Gerard Fierro Law Office",
    "wof:placetype":"venue"
},
  "geometry": {"coordinates":[-118.30032,34.061668],"type":"Point"}
}