{
  "type": "Feature",
  "properties": {
    "addr:full":"1990 Stenner Creek Rd San Luis Obispo CA 93405",
    "addr:housenumber":"1990",
    "addr:postcode":"93405",
    "addr:street":"Stenner Creek Rd",
    "iso:country":"US",
    "sg:address":"1990 Stenner Creek Rd",
    "sg:city":"San Luis Obispo",
    "sg:classifiers":[
        {
            "category":"Government",
            "subcategory":"Office",
            "type":"Public Place"
        }
    ],
    "sg:phone":"+1 805 781 7270",
    "sg:postcode":"93405",
    "sg:province":"CA",
    "sg:tags":[
        "village"
    ],
    "wof:name":"San Luis Obispo Water Trtmnt",
    "wof:placetype":"venue"
},
  "geometry": {"coordinates":[-120.680806,35.319223],"type":"Point"}
}