{
  "type": "Feature",
  "properties": {
    "addr:full":"1240 Coronado St Upland CA 91786",
    "addr:housenumber":"1240",
    "addr:postcode":"91786",
    "addr:street":"Coronado St",
    "iso:country":"US",
    "sg:address":"1240 Coronado St",
    "sg:city":"Upland",
    "sg:classifiers":[
        {
            "category":"Professional",
            "subcategory":"Engineering",
            "type":"Services"
        },
        {
            "category":"Home & Garden",
            "subcategory":"Building Materials",
            "type":"Retail Goods"
        },
        {
            "category":"Building & Trades",
            "subcategory":"Construction",
            "type":"Services"
        }
    ],
    "sg:phone":"+1 909 920 3700",
    "sg:postcode":"91786",
    "sg:province":"CA",
    "sg:tags":[
        "system",
        "specialty",
        "heating",
        "contractor",
        "equipment",
        "air conditioning"
    ],
    "wof:name":"Eskimo Airconditioning & Heating",
    "wof:placetype":"venue"
},
  "geometry": {"coordinates":[-117.67225500000001,34.119307],"type":"Point"}
}