{
  "type": "Feature",
  "properties": {
    "iso:country":"US",
    "sg:address":"8750 Stanton Ave",
    "sg:city":"Buena Park",
    "sg:classifiers":[
        {
            "category":"Retail",
            "subcategory":"Auto Repair",
            "type":"Services"
        }
    ],
    "sg:phone":"+1 714 952 8913",
    "sg:postcode":"90620",
    "sg:province":"CA",
    "wof:name":"Perfect Auto Shop",
    "wof:placetype":"venue"
},
  "geometry": {"coordinates":[-117.994003,33.837502],"type":"Point"}
}