{
  "type": "Feature",
  "properties": {
    "iso:country":"US",
    "sg:address":"809 S Grand Ave",
    "sg:city":"San Pedro",
    "sg:classifiers":[
        {
            "category":"Restaurant",
            "type":"Food & Drink"
        }
    ],
    "sg:phone":"+1 310 548 1240",
    "sg:postcode":"90731",
    "sg:province":"CA",
    "sg:tags":[
        "banquet",
        "rooms"
    ],
    "wof:name":"Grand Avenue Grill",
    "wof:placetype":"venue"
},
  "geometry": {"coordinates":[-118.29020199999999,33.737841],"type":"Point"}
}