{
  "type": "Feature",
  "properties": {
    "addr:full":"400 S Baldwin Ave Arcadia CA 91007",
    "addr:housenumber":"400",
    "addr:postcode":"91007",
    "addr:street":"S Baldwin Ave",
    "iso:country":"US",
    "sg:address":"400 S Baldwin Ave",
    "sg:city":"Arcadia",
    "sg:classifiers":[
        {
            "category":"Shopping",
            "subcategory":"Photographic Equipment",
            "type":"Retail Goods"
        }
    ],
    "sg:phone":"+1 626 445 6095",
    "sg:postcode":"91007",
    "sg:province":"CA",
    "sg:tags":[
        "supply"
    ],
    "wof:name":"Ritz Camera Ctr",
    "wof:placetype":"venue"
},
  "geometry": {"coordinates":[-118.054255,34.134837],"type":"Point"}
}