{
  "type": "Feature",
  "properties": {
    "iso:country":"US",
    "sg:address":"992 Orangewood Dr",
    "sg:city":"Brea",
    "sg:classifiers":[
        {
            "category":"Professional",
            "type":"Services"
        }
    ],
    "sg:phone":"+1 714 313 0547",
    "sg:postcode":"92821",
    "sg:province":"CA",
    "wof:name":"Viteck",
    "wof:placetype":"venue"
},
  "geometry": {"coordinates":[-117.896133,33.933442],"type":"Point"}
}