{
  "type": "Feature",
  "properties": {
    "iso:country":"US",
    "sg:address":"20459 Yorba Linda Blvd",
    "sg:city":"Yorba Linda",
    "sg:classifiers":[
        {
            "category":"Professional",
            "type":"Services"
        }
    ],
    "sg:phone":"+1 714 998 7800",
    "sg:postcode":"92886",
    "sg:province":"CA",
    "wof:name":"Kathy Hinojos",
    "wof:placetype":"venue"
},
  "geometry": {"coordinates":[-117.779526,33.891032],"type":"Point"}
}