{
  "type": "Feature",
  "properties": {
    "iso:country":"US",
    "sg:address":"8427 Tobias Ave",
    "sg:city":"Panorama City",
    "sg:classifiers":[
        {
            "category":"Government",
            "subcategory":"Office",
            "type":"Public Place"
        }
    ],
    "sg:phone":"+1 213 706 8509",
    "sg:postcode":"91402",
    "sg:province":"CA",
    "sg:tags":[
        "fire",
        "prevention"
    ],
    "wof:name":"Fuego Technologies",
    "wof:placetype":"venue"
},
  "geometry": {"coordinates":[-118.451724,34.222685],"type":"Point"}
}