{
  "type": "Feature",
  "properties": {
    "iso:country":"US",
    "sg:address":"284 E 10th St",
    "sg:city":"Pittsburg",
    "sg:classifiers":[
        {
            "category":"Shopping",
            "subcategory":"Stationery & Office Supplies",
            "type":"Retail Goods"
        }
    ],
    "sg:phone":"+1 925 432 7367",
    "sg:postcode":"94565",
    "sg:province":"CA",
    "wof:name":"Columbia Stationers & Printers",
    "wof:placetype":"venue"
},
  "geometry": {"coordinates":[-121.884143,38.027592],"type":"Point"}
}