{
  "type": "Feature",
  "properties": {
    "addr:full":"751 Pine St Martinez CA 94553",
    "addr:housenumber":"751",
    "addr:postcode":"94553",
    "addr:street":"Pine St",
    "iso:country":"US",
    "sg:address":"751 Pine St",
    "sg:city":"Martinez",
    "sg:classifiers":[
        {
            "category":"Government",
            "subcategory":"Court House",
            "type":"Public Place"
        }
    ],
    "sg:phone":"+1 925 957 7866",
    "sg:postcode":"94553",
    "sg:province":"CA",
    "sg:tags":[
        "county"
    ],
    "wof:name":"Contra Costa Cnty Family Court",
    "wof:placetype":"venue"
},
  "geometry": {"coordinates":[-122.133321,38.018618],"type":"Point"}
}