{
  "type": "Feature",
  "properties": {
    "addr:full":"3271 Toopal Dr Oceanside CA 92058",
    "addr:housenumber":"3271",
    "addr:postcode":"92058",
    "addr:street":"Toopal Dr",
    "iso:country":"US",
    "sg:address":"3271 Toopal Dr",
    "sg:city":"Oceanside",
    "sg:classifiers":[
        {
            "category":"Professional",
            "subcategory":"Engineering",
            "type":"Services"
        }
    ],
    "sg:phone":"+1 760 512 1048",
    "sg:postcode":"92058",
    "sg:province":"CA",
    "sg:tags":[
        "mechanical",
        "consulting",
        "industrial",
        "structural",
        "engineer"
    ],
    "sg:website":"http://www.zmulate.com",
    "wof:name":"Zmulate Engineering",
    "wof:placetype":"venue"
},
  "geometry": {"coordinates":[-117.350703,33.222489],"type":"Point"}
}