{
  "type": "Feature",
  "properties": {
    "iso:country":"US",
    "sg:address":"946 Irving St Ste C",
    "sg:city":"San Francisco",
    "sg:classifiers":[
        {
            "category":"Health Services",
            "subcategory":"Health Practitioner",
            "type":"Services"
        }
    ],
    "sg:phone":"+1 415 637 7487",
    "sg:postcode":"94122",
    "sg:province":"CA",
    "sg:tags":[
        "naturopathic/holistic"
    ],
    "sg:website":"215rx.com",
    "wof:name":"Monte P. Fisher, MD",
    "wof:placetype":"venue"
},
  "geometry": {"coordinates":[-122.468193,37.76408],"type":"Point"}
}