{
  "type": "Feature",
  "properties": {
    "addr:full":"6537 W 2nd St Rio Linda CA 95673",
    "addr:housenumber":"6537",
    "addr:postcode":"95673",
    "addr:street":"W 2Nd St",
    "iso:country":"US",
    "sg:address":"6537 W 2nd St",
    "sg:city":"Rio Linda",
    "sg:classifiers":[
        {
            "category":"Education",
            "subcategory":"School",
            "type":"Public Place"
        }
    ],
    "sg:phone":"+1 916 991 5175",
    "sg:postcode":"95673",
    "sg:province":"CA",
    "wof:name":"Westside School",
    "wof:placetype":"venue"
},
  "geometry": {"coordinates":[-121.466185,38.686852],"type":"Point"}
}