{
  "type": "Feature",
  "properties": {
    "iso:country":"US",
    "sg:address":"1912 St Sebastian Way",
    "sg:city":"Modesto",
    "sg:classifiers":[
        {
            "category":"Building & Trades",
            "subcategory":"Landscaping Services",
            "type":"Services"
        },
        {
            "category":"Professional",
            "type":"Services"
        }
    ],
    "sg:phone":"+1 209 338 8205",
    "sg:postcode":"95358",
    "sg:province":"CA",
    "sg:website":"www.ortegasconst.com",
    "wof:name":"Ortegas Construction",
    "wof:placetype":"venue"
},
  "geometry": {"coordinates":[-121.023177,37.603931],"type":"Point"}
}