{
  "type": "Feature",
  "properties": {
    "iso:country":"US",
    "sg:address":"8251 Monroe Ave",
    "sg:city":"Stanton",
    "sg:classifiers":[
        {
            "category":"Manufacturing",
            "subcategory":"Rubber & Plastics",
            "type":"Manufacturing & Wholesale Goods"
        },
        {
            "category":"Manufacturing",
            "subcategory":"Chemicals & Compounds",
            "type":"Manufacturing & Wholesale Goods"
        }
    ],
    "sg:phone":"+1 714 761 4998",
    "sg:postcode":"90680",
    "sg:province":"CA",
    "sg:tags":[
        "fabricator"
    ],
    "wof:name":"Mill Creek Plastics",
    "wof:placetype":"venue"
},
  "geometry": {"coordinates":[-117.990577,33.805724],"type":"Point"}
}