{
  "type": "Feature",
  "properties": {
    "iso:country":"US",
    "sg:address":"1731 Embarcadero Rd",
    "sg:city":"Palo Alto",
    "sg:classifiers":[
        {
            "category":"Professional",
            "subcategory":"Secretarial Services",
            "type":"Services"
        }
    ],
    "sg:phone":"+1 650 493 1400",
    "sg:postcode":"94303",
    "sg:province":"CA",
    "sg:tags":[
        "information",
        "document",
        "financial"
    ],
    "sg:website":"www.merrillcorp.com",
    "wof:name":"Merrill Corp",
    "wof:placetype":"venue"
},
  "geometry": {"coordinates":[-122.119399,37.449892],"type":"Point"}
}