{
  "type": "Feature",
  "properties": {
    "iso:country":"US",
    "sg:address":"461 Jessie St",
    "sg:city":"San Fernando",
    "sg:classifiers":[
        {
            "category":"Manufacturing",
            "subcategory":"Glass & Minerals",
            "type":"Manufacturing & Wholesale Goods"
        }
    ],
    "sg:phone":"+1 818 361 1330",
    "sg:postcode":"91340",
    "sg:province":"CA",
    "sg:tags":[
        "stone",
        "cutter"
    ],
    "wof:name":"B Y Marble Inc",
    "wof:placetype":"venue"
},
  "geometry": {"coordinates":[-118.4309,34.284727],"type":"Point"}
}