{
  "type": "Feature",
  "properties": {
    "addr:full":"20899 Kelvin Pl Woodland Hills CA 91367",
    "addr:housenumber":"20899",
    "addr:postcode":"91367",
    "addr:street":"Kelvin Pl",
    "iso:country":"US",
    "sg:address":"20899 Kelvin Pl",
    "sg:city":"Woodland Hills",
    "sg:classifiers":[
        {
            "category":"Wholesale",
            "subcategory":"Electrical",
            "type":"Manufacturing & Wholesale Goods"
        }
    ],
    "sg:phone":"+1 818 992 4288",
    "sg:postcode":"91367",
    "sg:province":"CA",
    "sg:tags":[
        "electronic"
    ],
    "wof:name":"J & I Audio Video",
    "wof:placetype":"venue"
},
  "geometry": {"coordinates":[-118.586697,34.174884],"type":"Point"}
}