{
  "type": "Feature",
  "properties": {
    "addr:full":"2904 Otis Street Berkeley CA 94703",
    "addr:housenumber":"2904",
    "addr:postcode":"94703",
    "addr:street":"Otis Street",
    "iso:country":"US",
    "sg:address":"2904 Otis Street",
    "sg:city":"Berkeley",
    "sg:classifiers":[
        {
            "category":"Professional",
            "subcategory":"Lawyer & Legal Services",
            "type":"Services"
        }
    ],
    "sg:phone":"+1 510 845 8737",
    "sg:postcode":"94703",
    "sg:province":"CA",
    "wof:name":"Murphy Kathryn M Atty",
    "wof:placetype":"venue"
},
  "geometry": {"coordinates":[-122.269997,37.856098],"type":"Point"}
}