{
  "type": "Feature",
  "properties": {
    "addr:full":"1549 Hanna St Coalinga CA 93210",
    "addr:housenumber":"1549",
    "addr:postcode":"93210",
    "addr:street":"Hanna St",
    "iso:country":"US",
    "sg:address":"1549 Hanna St",
    "sg:city":"Coalinga",
    "sg:classifiers":[
        {
            "category":"Manufacturing",
            "subcategory":"Motor Vehicles & Parts",
            "type":"Manufacturing & Wholesale Goods"
        }
    ],
    "sg:phone":"+1 559 935 1933",
    "sg:postcode":"93210",
    "sg:province":"CA",
    "sg:tags":[
        "travel",
        "mfg"
    ],
    "wof:name":"Amandako Mobile Home Park",
    "wof:placetype":"venue"
},
  "geometry": {"coordinates":[-120.34330799999999,36.150119],"type":"Point"}
}