{
  "type": "Feature",
  "properties": {
    "addr:full":"15333 Sherman Way Van Nuys CA 91406",
    "addr:housenumber":"15333",
    "addr:postcode":"91406",
    "addr:street":"Sherman Way",
    "iso:country":"US",
    "sg:address":"15333 Sherman Way",
    "sg:city":"Van Nuys",
    "sg:classifiers":[
        {
            "category":"Health Services",
            "subcategory":"Doctor",
            "type":"Services"
        }
    ],
    "sg:phone":"+1 818 909 0200",
    "sg:postcode":"91406",
    "sg:province":"CA",
    "sg:tags":[
        "dentist"
    ],
    "wof:name":"Gohar Hovsepyan DDS",
    "wof:placetype":"venue"
},
  "geometry": {"coordinates":[-118.468503,34.201137],"type":"Point"}
}