{
  "type": "Feature",
  "properties": {
    "addr:full":"42607 Moonridge Rd Big Bear Lake CA 92315",
    "addr:housenumber":"42607",
    "addr:postcode":"92315",
    "addr:street":"Moonridge Rd",
    "iso:country":"US",
    "sg:address":"42607 Moonridge Rd",
    "sg:city":"Big Bear Lake",
    "sg:classifiers":[
        {
            "category":"Professional",
            "subcategory":"Accounting & Tax Preparation",
            "type":"Services"
        }
    ],
    "sg:phone":"+1 909 585 6995",
    "sg:postcode":"92315",
    "sg:province":"CA",
    "sg:tags":[
        "accountant"
    ],
    "sg:website":"www.doucett.com",
    "wof:name":"Doucett & Silfies Inc",
    "wof:placetype":"venue"
},
  "geometry": {"coordinates":[-116.872389,34.240218],"type":"Point"}
}