{
  "type": "Feature",
  "properties": {
    "iso:country":"US",
    "sg:address":"32 Park Ave",
    "sg:city":"Sierra Madre",
    "sg:classifiers":[
        {
            "category":"Building & Trades",
            "subcategory":"Electrical",
            "type":"Services"
        }
    ],
    "sg:phone":"+1 626 355 4424",
    "sg:postcode":"91024",
    "sg:province":"CA",
    "sg:tags":[
        "electrical",
        "contractor"
    ],
    "wof:name":"Ed Clare",
    "wof:placetype":"venue"
},
  "geometry": {"coordinates":[-118.062791,34.161384],"type":"Point"}
}