{
  "type": "Feature",
  "properties": {
    "addr:full":"6731 E Wardlow Long Beach CA 90808",
    "addr:housenumber":"6731",
    "addr:postcode":"90808",
    "addr:street":"E Wardlow",
    "iso:country":"US",
    "sg:address":"6731 E Wardlow",
    "sg:city":"Long Beach",
    "sg:classifiers":[
        {
            "category":"Professional",
            "type":"Services"
        }
    ],
    "sg:phone":"+1 310 918 0439",
    "sg:postcode":"90808",
    "sg:province":"CA",
    "sg:tags":[
        "planning",
        "event"
    ],
    "sg:website":"www.eventmusicmaster.com",
    "wof:name":"Event Music Master",
    "wof:placetype":"venue"
},
  "geometry": {"coordinates":[-118.10153800000001,33.819088],"type":"Point"}
}