{
  "type": "Feature",
  "properties": {
    "iso:country":"US",
    "sg:address":"5256 Aero Dr",
    "sg:city":"Santa Rosa",
    "sg:classifiers":[
        {
            "category":"Utilities",
            "subcategory":"Mobile Phone",
            "type":"Services"
        },
        {
            "category":"Shopping",
            "type":"Retail Goods"
        }
    ],
    "sg:phone":"+1 707 542 1000",
    "sg:postcode":"95403",
    "sg:province":"CA",
    "sg:tags":[
        "repair",
        "paging",
        "telephone",
        "cellular",
        "equipment"
    ],
    "sg:website":"www.procel.com",
    "wof:name":"Professional Cellular & Paging",
    "wof:placetype":"venue"
},
  "geometry": {"coordinates":[-122.76463,38.509951],"type":"Point"}
}