{
  "type": "Feature",
  "properties": {
    "iso:country":"US",
    "sg:address":"2999 S Orange Ave",
    "sg:city":"Fresno",
    "sg:classifiers":[
        {
            "category":"Freight",
            "type":"Transportation"
        }
    ],
    "sg:phone":"+1 559 237 9159",
    "sg:postcode":"93725",
    "sg:province":"CA",
    "sg:tags":[
        "trucking"
    ],
    "wof:name":"Lamona Transport",
    "wof:placetype":"venue"
},
  "geometry": {"coordinates":[-119.763679,36.696335],"type":"Point"}
}