{
  "type": "Feature",
  "properties": {
    "iso:country":"US",
    "sg:address":"226 W 27th St",
    "sg:city":"Los Angeles",
    "sg:classifiers":[
        {
            "category":"Manufacturing",
            "subcategory":"Tools & Machinery",
            "type":"Manufacturing & Wholesale Goods"
        }
    ],
    "sg:phone":"+1 213 744 1143",
    "sg:postcode":"90007",
    "sg:province":"CA",
    "sg:tags":[
        "textile",
        "mfg"
    ],
    "wof:name":"Nam Fashion",
    "wof:placetype":"venue"
},
  "geometry": {"coordinates":[-118.272656,34.025191],"type":"Point"}
}