{
  "type": "Feature",
  "properties": {
    "iso:country":"US",
    "sg:address":"30872 Huntwood Ave Ste 2",
    "sg:city":"Hayward",
    "sg:classifiers":[
        {
            "category":"Professional",
            "subcategory":"Computer Services",
            "type":"Services"
        }
    ],
    "sg:phone":"+1 510 471 9062",
    "sg:postcode":"94544",
    "sg:province":"CA",
    "sg:tags":[
        "stereo",
        "installation"
    ],
    "sg:website":"www.soundinnovations.com",
    "wof:name":"Sound Innovations",
    "wof:placetype":"venue"
},
  "geometry": {"coordinates":[-122.05415600000001,37.614911],"type":"Point"}
}