{
  "type": "Feature",
  "properties": {
    "addr:full":"9401 Norwalk Blvd Santa Fe Springs CA 90670",
    "addr:housenumber":"9401",
    "addr:postcode":"90670",
    "addr:street":"Norwalk Blvd",
    "iso:country":"US",
    "sg:address":"9401 Norwalk Blvd",
    "sg:city":"Santa Fe Springs",
    "sg:classifiers":[
        {
            "category":"Shopping",
            "subcategory":"Discount & Variety Stores",
            "type":"Retail Goods"
        }
    ],
    "sg:phone":"+1 562 908 5000",
    "sg:postcode":"90670",
    "sg:province":"CA",
    "sg:tags":[
        "wholesale"
    ],
    "sg:website":"www.acudepot.com",
    "wof:name":"Marknew Products / Acudepot",
    "wof:placetype":"venue"
},
  "geometry": {"coordinates":[-118.072517,33.954825],"type":"Point"}
}