{
  "type": "Feature",
  "properties": {
    "addr:full":"425 Loumena Ln San Jose CA 95111",
    "addr:housenumber":"425",
    "addr:postcode":"95111",
    "addr:street":"Loumena Ln",
    "iso:country":"US",
    "sg:address":"425 Loumena Ln",
    "sg:city":"San Jose",
    "sg:classifiers":[
        {
            "category":"Building & Trades",
            "subcategory":"Cleaning & Sanitation",
            "type":"Services"
        }
    ],
    "sg:phone":"+1 408 726 8591",
    "sg:postcode":"95111",
    "sg:province":"CA",
    "sg:tags":[
        "home"
    ],
    "sg:website":"www.a-gift-4-u.com",
    "wof:name":"A Gift 4 U House Cleaning Services",
    "wof:placetype":"venue"
},
  "geometry": {"coordinates":[-121.838865,37.293993],"type":"Point"}
}