{
  "type": "Feature",
  "properties": {
    "iso:country":"US",
    "sg:address":"337 Campbell Ln",
    "sg:city":"Lakeport",
    "sg:classifiers":[
        {
            "category":"Manufacturing",
            "subcategory":"Building Materials",
            "type":"Manufacturing & Wholesale Goods"
        }
    ],
    "sg:phone":"+1 707 262 0127",
    "sg:postcode":"95453",
    "sg:province":"CA",
    "sg:tags":[
        "truss"
    ],
    "wof:name":"Interior & Exterior Wood Prods",
    "wof:placetype":"venue"
},
  "geometry": {"coordinates":[-122.9186,39.029364],"type":"Point"}
}