{
  "type": "Feature",
  "properties": {
    "addr:full":"190 Leavesley Rd Gilroy CA 95020",
    "addr:housenumber":"190",
    "addr:postcode":"95020",
    "addr:street":"Leavesley Rd",
    "iso:country":"US",
    "sg:address":"190 Leavesley Rd",
    "sg:city":"Gilroy",
    "sg:classifiers":[
        {
            "category":"Government",
            "subcategory":"Office",
            "type":"Public Place"
        }
    ],
    "sg:phone":"+1 408 842 2165",
    "sg:postcode":"95020",
    "sg:province":"CA",
    "sg:tags":[
        "agency",
        "employment"
    ],
    "wof:name":"Job Service Unemployment Insur",
    "wof:placetype":"venue"
},
  "geometry": {"coordinates":[-121.57437299999999,37.019348],"type":"Point"}
}