{
  "type": "Feature",
  "properties": {
    "iso:country":"US",
    "sg:address":"233 Fox Hills Mall",
    "sg:city":"Culver City",
    "sg:classifiers":[
        {
            "category":"Shopping",
            "subcategory":"Department Store",
            "type":"Retail Goods"
        }
    ],
    "sg:phone":"+1 310 398 9333",
    "sg:postcode":"90230",
    "sg:province":"CA",
    "wof:name":"Rave",
    "wof:placetype":"venue"
},
  "geometry": {"coordinates":[-118.394925,33.984748],"type":"Point"}
}