{
  "type": "Feature",
  "properties": {
    "addr:full":"3515 E Hillcrest Ave Visalia CA 93292",
    "addr:housenumber":"3515",
    "addr:postcode":"93292",
    "addr:street":"E Hillcrest Ave",
    "iso:country":"US",
    "sg:address":"3515 E Hillcrest Ave",
    "sg:city":"Visalia",
    "sg:classifiers":[
        {
            "category":"Professional",
            "type":"Services"
        }
    ],
    "sg:phone":"+1 559 732 1600",
    "sg:postcode":"93292",
    "sg:province":"CA",
    "wof:name":"Ruth D Wood",
    "wof:placetype":"venue"
},
  "geometry": {"coordinates":[-119.254713,36.314339],"type":"Point"}
}