{
  "type": "Feature",
  "properties": {
    "addr:full":"25432 Trabuco Rd # 104 Lake Forest CA 92630",
    "addr:housenumber":"25432",
    "addr:postcode":"92630",
    "addr:street":"Trabuco Rd # 104",
    "iso:country":"US",
    "sg:address":"25432 Trabuco Rd # 104",
    "sg:city":"Lake Forest",
    "sg:classifiers":[
        {
            "category":"Restaurant",
            "type":"Food & Drink"
        }
    ],
    "sg:phone":"+1 949 215 2225",
    "sg:postcode":"92630",
    "sg:province":"CA",
    "wof:name":"Yogurt Shop",
    "wof:placetype":"venue"
},
  "geometry": {"coordinates":[-117.687816,33.648964],"type":"Point"}
}