{
  "type": "Feature",
  "properties": {
    "iso:country":"US",
    "sg:address":"1 Montgomery Street",
    "sg:city":"San Francisco",
    "sg:classifiers":[
        {
            "category":"Banks & Credit Unions",
            "subcategory":"Investment Brokerage",
            "type":"Services"
        }
    ],
    "sg:phone":"+1 415 394 0450",
    "sg:postcode":"94104",
    "sg:province":"CA",
    "sg:tags":[
        "investing"
    ],
    "wof:name":"Fort Point Capital Management",
    "wof:placetype":"venue"
},
  "geometry": {"coordinates":[-122.402,37.789101],"type":"Point"}
}