{
  "type": "Feature",
  "properties": {
    "iso:country":"US",
    "sg:address":"2118 E 4th St",
    "sg:city":"Long Beach",
    "sg:classifiers":[
        {
            "category":"Professional",
            "type":"Services"
        }
    ],
    "sg:phone":"+1 562 434 4043",
    "sg:postcode":"90814",
    "sg:province":"CA",
    "wof:name":"Cine Vidia Inc",
    "wof:placetype":"venue"
},
  "geometry": {"coordinates":[-118.165711,33.77162],"type":"Point"}
}