{
  "type": "Feature",
  "properties": {
    "addr:full":"681 E Foothill Blvd Pomona CA 91767",
    "addr:housenumber":"681",
    "addr:postcode":"91767",
    "addr:street":"E Foothill Blvd",
    "iso:country":"US",
    "sg:address":"681 E Foothill Blvd",
    "sg:city":"Pomona",
    "sg:classifiers":[
        {
            "category":"Manufacturing",
            "subcategory":"Printing",
            "type":"Manufacturing & Wholesale Goods"
        }
    ],
    "sg:phone":"+1 909 624 8979",
    "sg:postcode":"91767",
    "sg:province":"CA",
    "sg:tags":[
        "lithographic",
        "offset"
    ],
    "wof:name":"Printing Works",
    "wof:placetype":"venue"
},
  "geometry": {"coordinates":[-117.738224,34.107191],"type":"Point"}
}