{
  "type": "Feature",
  "properties": {
    "addr:full":"1346 Bush St San Francisco CA 94109",
    "addr:housenumber":"1346",
    "addr:postcode":"94109",
    "addr:street":"Bush St",
    "iso:country":"US",
    "sg:address":"1346 Bush St",
    "sg:city":"San Francisco",
    "sg:classifiers":[
        {
            "category":"Personal",
            "type":"Services"
        }
    ],
    "sg:phone":"+1 415 422 9822",
    "sg:postcode":"94109",
    "sg:province":"CA",
    "sg:tags":[
        "mover"
    ],
    "sg:website":"bit.ly/gRNYtp",
    "wof:name":"Out of State Movers",
    "wof:placetype":"venue"
},
  "geometry": {"coordinates":[-122.419737,37.788787],"type":"Point"}
}