{
  "type": "Feature",
  "properties": {
    "addr:full":"4673 Thornton Ave Ste H Fremont CA 94536",
    "addr:housenumber":"4673",
    "addr:postcode":"94536",
    "addr:street":"Thornton Ave Ste H",
    "iso:country":"US",
    "sg:address":"4673 Thornton Ave Ste H",
    "sg:city":"Fremont",
    "sg:classifiers":[
        {
            "category":"Food & Beverages",
            "subcategory":"Supermarket",
            "type":"Retail Goods"
        },
        {
            "category":"Food & Beverages",
            "subcategory":"Groceries & Convenience Stores",
            "type":"Retail Goods"
        }
    ],
    "sg:phone":"+1 510 742 0900",
    "sg:postcode":"94536",
    "sg:province":"CA",
    "sg:tags":[
        "super"
    ],
    "wof:name":"Valco",
    "wof:placetype":"venue"
},
  "geometry": {"coordinates":[-122.018159,37.552384],"type":"Point"}
}