{
  "type": "Feature",
  "properties": {
    "iso:country":"US",
    "sg:address":"3349 W 43rd Pl",
    "sg:city":"Los Angeles",
    "sg:classifiers":[
        {
            "category":"Restaurant",
            "type":"Food & Drink"
        }
    ],
    "sg:phone":"+1 323 291 4075",
    "sg:postcode":"90008",
    "sg:province":"CA",
    "sg:tags":[
        "shop",
        "coffee"
    ],
    "wof:name":"Sunny's Spott",
    "wof:placetype":"venue"
},
  "geometry": {"coordinates":[-118.331416,34.004303],"type":"Point"}
}