{
  "type": "Feature",
  "properties": {
    "addr:full":"744 Montgomery Street San Francisco CA 94111",
    "addr:housenumber":"744",
    "addr:postcode":"94111",
    "addr:street":"Montgomery Street",
    "iso:country":"US",
    "sg:address":"744 Montgomery Street",
    "sg:city":"San Francisco",
    "sg:classifiers":[
        {
            "category":"Professional",
            "subcategory":"Lawyer & Legal Services",
            "type":"Services"
        }
    ],
    "sg:phone":"+1 415 951 0166",
    "sg:postcode":"94111",
    "sg:province":"CA",
    "wof:name":"Cronin Timothy C the Law Offices of",
    "wof:placetype":"venue"
},
  "geometry": {"coordinates":[-122.40300000000001,37.796101],"type":"Point"}
}