{
  "type": "Feature",
  "properties": {
    "addr:full":"2132 N Tustin Ave Santa Ana CA 92705",
    "addr:housenumber":"2132",
    "addr:postcode":"92705",
    "addr:street":"N Tustin Ave",
    "iso:country":"US",
    "sg:address":"2132 N Tustin Ave",
    "sg:city":"Santa Ana",
    "sg:classifiers":[
        {
            "category":"Personal",
            "subcategory":"Nail Salon",
            "type":"Services"
        }
    ],
    "sg:phone":"+1 714 542 6616",
    "sg:postcode":"92705",
    "sg:province":"CA",
    "wof:name":"Kelly's Nails",
    "wof:placetype":"venue"
},
  "geometry": {"coordinates":[-117.835999,33.765499],"type":"Point"}
}