{
  "type": "Feature",
  "properties": {
    "addr:full":"7259 Fulton Ave North Hollywood CA 91605",
    "addr:housenumber":"7259",
    "addr:postcode":"91605",
    "addr:street":"Fulton Ave",
    "iso:country":"US",
    "sg:address":"7259 Fulton Ave",
    "sg:city":"North Hollywood",
    "sg:classifiers":[
        {
            "category":"Autos & Motor Vehicles",
            "subcategory":"Automobile Sales",
            "type":"Retail Goods"
        }
    ],
    "sg:phone":"+1 818 503 1414",
    "sg:postcode":"91605",
    "sg:province":"CA",
    "sg:tags":[
        "used",
        "mat"
    ],
    "wof:name":"Atlanta Auto Dismantling",
    "wof:placetype":"venue"
},
  "geometry": {"coordinates":[-118.422602,34.205303],"type":"Point"}
}