{
  "type": "Feature",
  "properties": {
    "iso:country":"US",
    "sg:address":"2500 W Magnolia Blvd",
    "sg:city":"Burbank",
    "sg:classifiers":[
        {
            "category":"Autos & Motor Vehicles",
            "subcategory":"Fuel & Gas Station",
            "type":"Retail Goods"
        }
    ],
    "sg:phone":"+1 818 954 8744",
    "sg:postcode":"91505",
    "sg:province":"CA",
    "wof:name":"Shell Gas Station",
    "wof:placetype":"venue"
},
  "geometry": {"coordinates":[-118.33489400000001,34.171594],"type":"Point"}
}