{
  "type": "Feature",
  "properties": {
    "iso:country":"US",
    "sg:address":"5220 W San Joaquin Dr",
    "sg:city":"Visalia",
    "sg:classifiers":[
        {
            "category":"Building & Trades",
            "subcategory":"Cleaning & Sanitation",
            "type":"Services"
        }
    ],
    "sg:phone":"+1 559 635 9909",
    "sg:postcode":"93277",
    "sg:province":"CA",
    "sg:tags":[
        "janitor"
    ],
    "wof:name":"Affordable Cleaning Svc",
    "wof:placetype":"venue"
},
  "geometry": {"coordinates":[-119.34904899999999,36.315047],"type":"Point"}
}