{
  "type": "Feature",
  "properties": {
    "iso:country":"US",
    "sg:address":"1650 Borel Place",
    "sg:city":"San Mateo",
    "sg:classifiers":[
        {
            "category":"Professional",
            "subcategory":"Accounting & Tax Preparation",
            "type":"Services"
        }
    ],
    "sg:phone":"+1 650 571 6791",
    "sg:postcode":"94402",
    "sg:province":"CA",
    "sg:tags":[
        "accountant"
    ],
    "wof:name":"Feakins & Feakins",
    "wof:placetype":"venue"
},
  "geometry": {"coordinates":[-122.31786099999999,37.548897],"type":"Point"}
}