{
  "type": "Feature",
  "properties": {
    "addr:full":"14412 Olive St Baldwin Park CA 91706",
    "addr:housenumber":"14412",
    "addr:postcode":"91706",
    "addr:street":"Olive St",
    "iso:country":"US",
    "sg:address":"14412 Olive St",
    "sg:city":"Baldwin Park",
    "sg:classifiers":[
        {
            "category":"Restaurant",
            "type":"Food & Drink"
        }
    ],
    "sg:phone":"+1 626 337 6090",
    "sg:postcode":"91706",
    "sg:province":"CA",
    "sg:tags":[
        "eating",
        "pizza"
    ],
    "wof:name":"Baldwin Park Pizza Company",
    "wof:placetype":"venue"
},
  "geometry": {"coordinates":[-117.95960100000001,34.099486],"type":"Point"}
}