{
  "type": "Feature",
  "properties": {
    "iso:country":"US",
    "sg:address":"1713 Elizabeth Ave",
    "sg:city":"Modesto",
    "sg:classifiers":[
        {
            "category":"Building & Trades",
            "subcategory":"Electrical",
            "type":"Services"
        }
    ],
    "sg:phone":"+1 209 554 0683",
    "sg:postcode":"95355",
    "sg:province":"CA",
    "sg:tags":[
        "electrical",
        "contractor"
    ],
    "wof:name":"Blaylock Electric",
    "wof:placetype":"venue"
},
  "geometry": {"coordinates":[-120.967686,37.653201],"type":"Point"}
}