{
  "type": "Feature",
  "properties": {
    "addr:full":"1212 N Broadway Santa Ana CA 92701",
    "addr:housenumber":"1212",
    "addr:postcode":"92701",
    "addr:street":"N Broadway",
    "iso:country":"US",
    "sg:address":"1212 N Broadway",
    "sg:city":"Santa Ana",
    "sg:classifiers":[
        {
            "category":"Professional",
            "subcategory":"Printing & Photocopies",
            "type":"Services"
        }
    ],
    "sg:phone":"+1 714 835 0631",
    "sg:postcode":"92701",
    "sg:province":"CA",
    "sg:tags":[
        "duplicating",
        "copying"
    ],
    "wof:name":"Socal Document",
    "wof:placetype":"venue"
},
  "geometry": {"coordinates":[-117.86977400000001,33.7552],"type":"Point"}
}