{
  "type": "Feature",
  "properties": {
    "addr:full":"5550 Lake Murray Blvd La Mesa CA 91942",
    "addr:housenumber":"5550",
    "addr:postcode":"91942",
    "addr:street":"Lake Murray Blvd",
    "iso:country":"US",
    "sg:address":"5550 Lake Murray Blvd",
    "sg:city":"La Mesa",
    "sg:classifiers":[
        {
            "category":"Restaurant",
            "type":"Food & Drink"
        }
    ],
    "sg:phone":"+1 619 464 1372",
    "sg:postcode":"91942",
    "sg:province":"CA",
    "sg:tags":[
        "eating"
    ],
    "wof:name":"Cocos",
    "wof:placetype":"venue"
},
  "geometry": {"coordinates":[-117.03478200000001,32.78072],"type":"Point"}
}