{
  "type": "Feature",
  "properties": {
    "iso:country":"US",
    "sg:address":"13293 Whittram Ave",
    "sg:city":"Etiwanda",
    "sg:classifiers":[
        {
            "category":"Wholesale",
            "subcategory":"Auto Parts",
            "type":"Manufacturing & Wholesale Goods"
        }
    ],
    "sg:phone":"+1 909 899 1333",
    "sg:postcode":"91739",
    "sg:province":"CA",
    "sg:tags":[
        "automobile",
        "wrecking"
    ],
    "wof:name":"King's Auto Wrecking",
    "wof:placetype":"venue"
},
  "geometry": {"coordinates":[-117.518525,34.094447],"type":"Point"}
}