{
  "type": "Feature",
  "properties": {
    "addr:full":"3457 N Main St Soquel CA 95073",
    "addr:housenumber":"3457",
    "addr:postcode":"95073",
    "addr:street":"N Main St",
    "iso:country":"US",
    "sg:address":"3457 N Main St",
    "sg:city":"Soquel",
    "sg:classifiers":[
        {
            "category":"Wholesale",
            "subcategory":"Stationery",
            "type":"Manufacturing & Wholesale Goods"
        }
    ],
    "sg:phone":"+1 831 251 9060",
    "sg:postcode":"95073",
    "sg:province":"CA",
    "sg:tags":[
        "pencil",
        "pen"
    ],
    "wof:name":"Nicholas Asher",
    "wof:placetype":"venue"
},
  "geometry": {"coordinates":[-121.95382600000001,36.9953],"type":"Point"}
}