{
  "type": "Feature",
  "properties": {
    "iso:country":"US",
    "sg:address":"21851 Sherman Way",
    "sg:city":"Canoga Park",
    "sg:classifiers":[
        {
            "category":"Shopping",
            "subcategory":"Crafts & Fabrics",
            "type":"Retail Goods"
        }
    ],
    "sg:phone":"+1 818 887 7606",
    "sg:postcode":"91303",
    "sg:province":"CA",
    "sg:tags":[
        "art",
        "supply"
    ],
    "wof:name":"R E I Crafts",
    "wof:placetype":"venue"
},
  "geometry": {"coordinates":[-118.603996,34.200901],"type":"Point"}
}