{
  "type": "Feature",
  "properties": {
    "iso:country":"US",
    "sg:address":"5592 Honeyman St",
    "sg:city":"Simi Valley",
    "sg:classifiers":[
        {
            "category":"Building & Trades",
            "subcategory":"Plumbing",
            "type":"Services"
        }
    ],
    "sg:phone":"+1 805 522 6128",
    "sg:postcode":"93063",
    "sg:province":"CA",
    "sg:tags":[
        "plumbing",
        "contractor"
    ],
    "wof:name":"Sun West Plumbing Sewer Co",
    "wof:placetype":"venue"
},
  "geometry": {"coordinates":[-118.683334,34.272332],"type":"Point"}
}