{
  "type": "Feature",
  "properties": {
    "iso:country":"US",
    "sg:address":"5150 Candlewood St Ste 20A",
    "sg:city":"Lakewood",
    "sg:classifiers":[
        {
            "category":"Professional",
            "subcategory":"Lawyer & Legal Services",
            "type":"Services"
        }
    ],
    "sg:phone":"+1 562 263 0242",
    "sg:postcode":"90712",
    "sg:province":"CA",
    "sg:tags":[
        "divorce",
        "law",
        "family"
    ],
    "wof:name":"Paralegal Services",
    "wof:placetype":"venue"
},
  "geometry": {"coordinates":[-118.13242200000001,33.853522],"type":"Point"}
}