{
  "type": "Feature",
  "properties": {
    "iso:country":"US",
    "sg:address":"13213 Gladstone Ave",
    "sg:city":"Sylmar",
    "sg:classifiers":[
        {
            "category":"Shopping",
            "subcategory":"Clothing, Apparel, & Fashions",
            "type":"Retail Goods"
        }
    ],
    "sg:phone":"+1 818 833 7775",
    "sg:postcode":"91342",
    "sg:province":"CA",
    "wof:name":"Fashion Sol",
    "wof:placetype":"venue"
},
  "geometry": {"coordinates":[-118.428515,34.311037],"type":"Point"}
}