{
  "type": "Feature",
  "properties": {
    "addr:full":"1350 Stockton St San Francisco CA 94133",
    "addr:housenumber":"1350",
    "addr:postcode":"94133",
    "addr:street":"Stockton St",
    "iso:country":"US",
    "sg:address":"1350 Stockton St",
    "sg:city":"San Francisco",
    "sg:classifiers":[
        {
            "category":"Travel",
            "subcategory":"Hotels & Motels",
            "type":"Entertainment"
        }
    ],
    "sg:phone":"+1 415 986 6050",
    "sg:postcode":"94133",
    "sg:province":"CA",
    "wof:name":"Stockton Hotel",
    "wof:placetype":"venue"
},
  "geometry": {"coordinates":[-122.40880799999999,37.79857],"type":"Point"}
}