{
  "type": "Feature",
  "properties": {
    "iso:country":"US",
    "sg:address":"144 2nd Ave",
    "sg:city":"San Francisco",
    "sg:classifiers":[
        {
            "category":"Banks & Credit Unions",
            "subcategory":"Bank",
            "type":"Services"
        }
    ],
    "sg:phone":"+1 415 896 6890",
    "sg:postcode":"94118",
    "sg:province":"CA",
    "wof:name":"Allied Credit Union",
    "wof:placetype":"venue"
},
  "geometry": {"coordinates":[-122.460277,37.786312],"type":"Point"}
}