{
  "type": "Feature",
  "properties": {
    "addr:full":"144 2nd Ave San Francisco CA 94118",
    "addr:housenumber":"144",
    "addr:postcode":"94118",
    "addr:street":"2Nd Ave",
    "iso:country":"US",
    "sg:address":"144 2nd Ave",
    "sg:city":"San Francisco",
    "sg:classifiers":[
        {
            "category":"Banks & Credit Unions",
            "subcategory":"Bank",
            "type":"Services"
        }
    ],
    "sg:phone":"+1 415 896 6890",
    "sg:postcode":"94118",
    "sg:province":"CA",
    "wof:name":"Allied Credit Union",
    "wof:placetype":"venue"
},
  "geometry": {"coordinates":[-122.460277,37.786312],"type":"Point"}
}