{
  "type": "Feature",
  "properties": {
    "iso:country":"US",
    "sg:address":"12750 Carmel Country Road",
    "sg:city":"San Diego",
    "sg:classifiers":[
        {
            "category":"Health Services",
            "subcategory":"Dentist",
            "type":"Services"
        }
    ],
    "sg:phone":"+1 858 755 7805",
    "sg:postcode":"92130",
    "sg:province":"CA",
    "sg:website":"www.sedationdentistsandiego.com/",
    "wof:name":"Carmel Heights Dentistry",
    "wof:placetype":"venue"
},
  "geometry": {"coordinates":[-117.229062,32.953327],"type":"Point"}
}