{
  "type": "Feature",
  "properties": {
    "addr:full":"4231 W Flower Ave Fullerton CA 92833",
    "addr:housenumber":"4231",
    "addr:postcode":"92833",
    "addr:street":"W Flower Ave",
    "iso:country":"US",
    "sg:address":"4231 W Flower Ave",
    "sg:city":"Fullerton",
    "sg:classifiers":[
        {
            "category":"Professional",
            "type":"Services"
        }
    ],
    "sg:phone":"+1 714 522 8190",
    "sg:postcode":"92833",
    "sg:province":"CA",
    "wof:name":"Erik Fulkerson",
    "wof:placetype":"venue"
},
  "geometry": {"coordinates":[-117.98354399999999,33.862985],"type":"Point"}
}