{
  "type": "Feature",
  "properties": {
    "iso:country":"US",
    "sg:address":"24605 New Clay St",
    "sg:city":"Murrieta",
    "sg:classifiers":[
        {
            "category":"Freight",
            "type":"Transportation"
        }
    ],
    "sg:phone":"+1 951 696 0030",
    "sg:postcode":"92562",
    "sg:province":"CA",
    "sg:tags":[
        "operator",
        "local",
        "trucking"
    ],
    "wof:name":"Bear Canyon Transportation",
    "wof:placetype":"venue"
},
  "geometry": {"coordinates":[-117.219633,33.553454],"type":"Point"}
}