{
  "type": "Feature",
  "properties": {
    "addr:full":"1281 Logan Ave Costa Mesa CA 92626",
    "addr:housenumber":"1281",
    "addr:postcode":"92626",
    "addr:street":"Logan Ave",
    "iso:country":"US",
    "sg:address":"1281 Logan Ave",
    "sg:city":"Costa Mesa",
    "sg:classifiers":[
        {
            "category":"Building & Trades",
            "subcategory":"Electrical",
            "type":"Services"
        }
    ],
    "sg:phone":"+1 714 549 9139",
    "sg:postcode":"92626",
    "sg:province":"CA",
    "sg:tags":[
        "electrical",
        "business",
        "contractor"
    ],
    "wof:name":"S & N Show Services Inc",
    "wof:placetype":"venue"
},
  "geometry": {"coordinates":[-117.916403,33.678678],"type":"Point"}
}