{
  "type": "Feature",
  "properties": {
    "iso:country":"US",
    "sg:address":"1975 Cambrianna Dr",
    "sg:city":"San Jose",
    "sg:classifiers":[
        {
            "category":"Education",
            "subcategory":"Preschool",
            "type":"Public Place"
        }
    ],
    "sg:phone":"+1 408 371 2573",
    "sg:postcode":"95124",
    "sg:province":"CA",
    "wof:name":"A Tyson Loving Care Preschool A T.L.C. Preschool",
    "wof:placetype":"venue"
},
  "geometry": {"coordinates":[-121.93047799999999,37.264564],"type":"Point"}
}