{
  "type": "Feature",
  "properties": {
    "addr:full":"4100 Poplar St San Diego CA 92105",
    "addr:housenumber":"4100",
    "addr:postcode":"92105",
    "addr:street":"Poplar St",
    "iso:country":"US",
    "sg:address":"4100 Poplar St",
    "sg:city":"San Diego",
    "sg:classifiers":[
        {
            "category":"Professional",
            "type":"Services"
        }
    ],
    "sg:phone":"+1 619 563 4776",
    "sg:postcode":"92105",
    "sg:province":"CA",
    "sg:tags":[
        "establishment"
    ],
    "wof:name":"Sdsu Foundation",
    "wof:placetype":"venue"
},
  "geometry": {"coordinates":[-117.106177,32.734009],"type":"Point"}
}