{
  "type": "Feature",
  "properties": {
    "addr:full":"1969B Mountain Blvd Oakland CA 94611",
    "addr:housenumber":"1969b",
    "addr:postcode":"94611",
    "addr:street":"Mountain Blvd",
    "iso:country":"US",
    "sg:address":"1969B Mountain Blvd",
    "sg:city":"Oakland",
    "sg:classifiers":[
        {
            "category":"Retail",
            "subcategory":"Veterinary Services",
            "type":"Services"
        }
    ],
    "sg:phone":"+1 510 339 2600",
    "sg:postcode":"94611",
    "sg:province":"CA",
    "sg:tags":[
        "clinic",
        "hospital",
        "veterinarian",
        "specialty"
    ],
    "sg:website":"www.HolisticVetCare.com",
    "wof:name":"Holistic Veterinary Care",
    "wof:placetype":"venue"
},
  "geometry": {"coordinates":[-122.21068699999999,37.828541],"type":"Point"}
}