{
  "type": "Feature",
  "properties": {
    "iso:country":"US",
    "sg:address":"380 N El Camino Real",
    "sg:city":"Encinitas",
    "sg:classifiers":[
        {
            "category":"Retail",
            "subcategory":"Repair Shop",
            "type":"Services"
        },
        {
            "category":"Shopping",
            "subcategory":"Crafts & Fabrics",
            "type":"Retail Goods"
        },
        {
            "category":"Wholesale",
            "subcategory":"Home Furnishings",
            "type":"Manufacturing & Wholesale Goods"
        }
    ],
    "sg:phone":"+1 760 944 6700",
    "sg:postcode":"92024",
    "sg:province":"CA",
    "sg:tags":[
        "blind",
        "reupholstery",
        "store",
        "shade",
        "furniture"
    ],
    "wof:name":"Decorative Mills",
    "wof:placetype":"venue"
},
  "geometry": {"coordinates":[-117.262001,33.055801],"type":"Point"}
}