{
  "type": "Feature",
  "properties": {
    "addr:full":"2004 Westminster Mall Westminster CA 92683",
    "addr:housenumber":"2004",
    "addr:postcode":"92683",
    "addr:street":"Westminster Mall",
    "iso:country":"US",
    "sg:address":"2004 Westminster Mall",
    "sg:city":"Westminster",
    "sg:classifiers":[
        {
            "category":"Food & Beverages",
            "subcategory":"Groceries & Convenience Stores",
            "type":"Retail Goods"
        }
    ],
    "sg:phone":"+1 714 894 6670",
    "sg:postcode":"92683",
    "sg:province":"CA",
    "wof:name":"Auntie Anne's Soft Pretzels",
    "wof:placetype":"venue"
},
  "geometry": {"coordinates":[-118.010002,33.7481],"type":"Point"}
}