{
  "type": "Feature",
  "properties": {
    "addr:full":"39872 Los Alamos Rd Ste 3B Murrieta CA 92562",
    "addr:housenumber":"39872",
    "addr:postcode":"92562",
    "addr:street":"Los Alamos Rd Ste 3B",
    "iso:country":"US",
    "sg:address":"39872 Los Alamos Rd Ste 3B",
    "sg:city":"Murrieta",
    "sg:classifiers":[
        {
            "category":"Personal",
            "subcategory":"Nail Salon",
            "type":"Services"
        }
    ],
    "sg:phone":"+1 951 698 7191",
    "sg:postcode":"92562",
    "sg:province":"CA",
    "wof:name":"Princess Nails",
    "wof:placetype":"venue"
},
  "geometry": {"coordinates":[-117.18358499999999,33.571413],"type":"Point"}
}