{
  "type": "Feature",
  "properties": {
    "iso:country":"US",
    "sg:address":"4375 Brown Rd",
    "sg:city":"Guadalupe",
    "sg:classifiers":[
        {
            "category":"Building & Trades",
            "subcategory":"Plumbing",
            "type":"Services"
        },
        {
            "category":"Wholesale",
            "subcategory":"Fruits & Vegetables",
            "type":"Manufacturing & Wholesale Goods"
        }
    ],
    "sg:phone":"+1 805 343 5808",
    "sg:postcode":"93455",
    "sg:province":"CA",
    "sg:tags":[
        "shipper",
        "contractor"
    ],
    "wof:name":"Red Diamond Cooling Inc",
    "wof:placetype":"venue"
},
  "geometry": {"coordinates":[-120.557891,34.933814],"type":"Point"}
}