{
  "type": "Feature",
  "properties": {
    "addr:full":"1750 Clay St San Francisco CA 94109",
    "addr:housenumber":"1750",
    "addr:postcode":"94109",
    "addr:street":"Clay St",
    "iso:country":"US",
    "sg:address":"1750 Clay St",
    "sg:city":"San Francisco",
    "sg:classifiers":[
        {
            "category":"Organizations",
            "subcategory":"Community Association",
            "type":"Services"
        }
    ],
    "sg:phone":"+1 415 474 3516",
    "sg:postcode":"94109",
    "sg:province":"CA",
    "sg:tags":[
        "club"
    ],
    "wof:name":"California Club Of California",
    "wof:placetype":"venue"
},
  "geometry": {"coordinates":[-122.422044,37.792355],"type":"Point"}
}