{
  "type": "Feature",
  "properties": {
    "addr:full":"11507 Pso Lago Lakeside CA 92040",
    "addr:housenumber":"11507",
    "addr:postcode":"92040",
    "addr:street":"Pso Lago",
    "iso:country":"US",
    "sg:address":"11507 Pso Lago",
    "sg:city":"Lakeside",
    "sg:classifiers":[
        {
            "category":"Professional",
            "type":"Services"
        }
    ],
    "sg:phone":"+1 619 448 7115",
    "sg:postcode":"92040",
    "sg:province":"CA",
    "wof:name":"A Stork of Luck",
    "wof:placetype":"venue"
},
  "geometry": {"coordinates":[-116.945413,32.862018],"type":"Point"}
}