{
  "type": "Feature",
  "properties": {
    "iso:country":"US",
    "sg:address":"7322 Florin Wood Dr",
    "sg:city":"Sacramento",
    "sg:classifiers":[
        {
            "category":"Arts & Performance",
            "subcategory":"Theater",
            "type":"Entertainment"
        }
    ],
    "sg:phone":"+1 916 396 2058",
    "sg:postcode":"95823",
    "sg:province":"CA",
    "sg:tags":[
        "bureau"
    ],
    "wof:name":"Navtarang Entertainments",
    "wof:placetype":"venue"
},
  "geometry": {"coordinates":[-121.436498,38.491342],"type":"Point"}
}