{
  "type": "Feature",
  "properties": {
    "addr:full":"10377 Mather Ave Sunland CA 91040",
    "addr:housenumber":"10377",
    "addr:postcode":"91040",
    "addr:street":"Mather Ave",
    "iso:country":"US",
    "sg:address":"10377 Mather Ave",
    "sg:city":"Sunland",
    "sg:classifiers":[
        {
            "category":"Building & Trades",
            "subcategory":"Construction",
            "type":"Services"
        }
    ],
    "sg:phone":"+1 818 353 8181",
    "sg:postcode":"91040",
    "sg:province":"CA",
    "sg:tags":[
        "wallcoverings-installation",
        "wallpaper",
        "painting",
        "contractor"
    ],
    "wof:name":"Tom Dumas Painting",
    "wof:placetype":"venue"
},
  "geometry": {"coordinates":[-118.31041,34.257729],"type":"Point"}
}