{
  "type": "Feature",
  "properties": {
    "addr:full":"17608 Caprino Pl Van Nuys CA 91406",
    "addr:postcode":"17608;91406",
    "addr:street":"Caprino Pl",
    "iso:country":"US",
    "sg:address":"17608 Caprino Pl",
    "sg:city":"Van Nuys",
    "sg:classifiers":[
        {
            "category":"Home & Garden",
            "subcategory":"Building Materials",
            "type":"Retail Goods"
        }
    ],
    "sg:phone":"+1 818 705 0611",
    "sg:postcode":"91406",
    "sg:province":"CA",
    "sg:tags":[
        "door"
    ],
    "wof:name":"Triunfo Overhead Door",
    "wof:placetype":"venue"
},
  "geometry": {"coordinates":[-118.517476,34.205381],"type":"Point"}
}