{
  "type": "Feature",
  "properties": {
    "iso:country":"US",
    "sg:address":"111 Pacifica",
    "sg:city":"Irvine",
    "sg:classifiers":[
        {
            "category":"Professional",
            "subcategory":"Management & Consulting",
            "type":"Services"
        }
    ],
    "sg:phone":"+1 949 727 2436",
    "sg:postcode":"92618",
    "sg:province":"CA",
    "sg:tags":[
        "fuel"
    ],
    "wof:name":"Advantage Management Solutions",
    "wof:placetype":"venue"
},
  "geometry": {"coordinates":[-117.753802,33.660676],"type":"Point"}
}