{
  "type": "Feature",
  "properties": {
    "iso:country":"US",
    "sg:address":"718 B St",
    "sg:city":"San Rafael",
    "sg:classifiers":[
        {
            "category":"Manufacturing",
            "subcategory":"Jewelry",
            "type":"Manufacturing & Wholesale Goods"
        },
        {
            "category":"Shopping",
            "subcategory":"Jewelry",
            "type":"Retail Goods"
        }
    ],
    "sg:phone":"+1 415 459 0333",
    "sg:postcode":"94901",
    "sg:province":"CA",
    "sg:tags":[
        "repair"
    ],
    "wof:name":"Benchmark Jewelry Mfg",
    "wof:placetype":"venue"
},
  "geometry": {"coordinates":[-122.52973299999999,37.971213],"type":"Point"}
}