{
  "type": "Feature",
  "properties": {
    "addr:full":"21410 Tussing Ranch Rd Apple Valley CA 92308",
    "addr:postcode":"21410;92308",
    "addr:street":"Tussing Ranch Rd",
    "iso:country":"US",
    "sg:address":"21410 Tussing Ranch Rd",
    "sg:city":"Apple Valley",
    "sg:classifiers":[
        {
            "category":"Retail",
            "subcategory":"Auto Repair",
            "type":"Services"
        }
    ],
    "sg:phone":"+1 760 240 9158",
    "sg:postcode":"92308",
    "sg:province":"CA",
    "sg:tags":[
        "wrecker"
    ],
    "wof:name":"A A & Sons Towing",
    "wof:placetype":"venue"
},
  "geometry": {"coordinates":[-117.197284,34.442631],"type":"Point"}
}