{
  "type": "Feature",
  "properties": {
    "addr:full":"2231 Commerce Ave Concord CA 94520",
    "addr:housenumber":"2231",
    "addr:postcode":"94520",
    "addr:street":"Commerce Ave",
    "iso:country":"US",
    "sg:address":"2231 Commerce Ave",
    "sg:city":"Concord",
    "sg:classifiers":[
        {
            "category":"Shopping",
            "type":"Retail Goods"
        },
        {
            "category":"Shopping",
            "subcategory":"Clothing, Apparel, & Fashions",
            "type":"Retail Goods"
        }
    ],
    "sg:phone":"+1 925 680 6060",
    "sg:postcode":"94520",
    "sg:province":"CA",
    "sg:tags":[
        "equipment",
        "supply"
    ],
    "wof:name":"High End Uniforms",
    "wof:placetype":"venue"
},
  "geometry": {"coordinates":[-122.04501,37.979065],"type":"Point"}
}