{
  "type": "Feature",
  "properties": {
    "addr:full":"751 N Placentia Ave Fullerton CA 92831",
    "addr:housenumber":"751",
    "addr:postcode":"92831",
    "addr:street":"N Placentia Ave",
    "iso:country":"US",
    "sg:address":"751 N Placentia Ave",
    "sg:city":"Fullerton",
    "sg:classifiers":[
        {
            "category":"Fast Food",
            "type":"Food & Drink"
        }
    ],
    "sg:phone":"+1 714 993 3814",
    "sg:postcode":"92831",
    "sg:province":"CA",
    "sg:website":"jackinthebox.com",
    "wof:name":"Jack In the Box",
    "wof:placetype":"venue"
},
  "geometry": {"coordinates":[-117.87860000000001,33.876569],"type":"Point"}
}