{
  "type": "Feature",
  "properties": {
    "iso:country":"US",
    "sg:address":"9730 Wilshire Blvd Ste 207",
    "sg:city":"Beverly Hills",
    "sg:classifiers":[
        {
            "category":"Personal",
            "subcategory":"Massage",
            "type":"Services"
        }
    ],
    "sg:phone":"+1 310 858 7161",
    "sg:postcode":"90212",
    "sg:province":"CA",
    "sg:website":"www.uttabodysculpture.com",
    "wof:name":"Utta Body Sculpture",
    "wof:placetype":"venue"
},
  "geometry": {"coordinates":[-118.40743500000001,34.066748],"type":"Point"}
}