{
  "type": "Feature",
  "properties": {
    "addr:full":"2514 Carnoustie Ct Union City CA 94587",
    "addr:housenumber":"2514",
    "addr:postcode":"94587",
    "addr:street":"Carnoustie Ct",
    "iso:country":"US",
    "sg:address":"2514 Carnoustie Ct",
    "sg:city":"Union City",
    "sg:classifiers":[
        {
            "category":"Building & Trades",
            "subcategory":"Construction",
            "type":"Services"
        }
    ],
    "sg:phone":"+1 510 675 0231",
    "sg:postcode":"94587",
    "sg:province":"CA",
    "sg:tags":[
        "painter"
    ],
    "wof:name":"Pro Touch Painting",
    "wof:placetype":"venue"
},
  "geometry": {"coordinates":[-122.05884,37.603207],"type":"Point"}
}