{
  "type": "Feature",
  "properties": {
    "iso:country":"US",
    "sg:address":"4575 Loma Vista Ave",
    "sg:city":"Los Angeles",
    "sg:classifiers":[
        {
            "category":"Wholesale",
            "subcategory":"Apparel",
            "type":"Manufacturing & Wholesale Goods"
        }
    ],
    "sg:phone":"+1 323 277 9790",
    "sg:postcode":"90058",
    "sg:province":"CA",
    "wof:name":"Fully Fashion",
    "wof:placetype":"venue"
},
  "geometry": {"coordinates":[-118.197243,34.001194],"type":"Point"}
}