{
  "type": "Feature",
  "properties": {
    "addr:full":"27600 Jefferson Ave Temecula CA 92590",
    "addr:housenumber":"27600",
    "addr:postcode":"92590",
    "addr:street":"Jefferson Ave",
    "iso:country":"US",
    "sg:address":"27600 Jefferson Ave",
    "sg:city":"Temecula",
    "sg:classifiers":[
        {
            "category":"Restaurant",
            "type":"Food & Drink"
        }
    ],
    "sg:menulink":"http://www.allmenus.com/ca/murrieta/5256-hungry-hunter-steakhouse/menu/",
    "sg:phone":"+1 951 694 1475",
    "sg:postcode":"92590",
    "sg:province":"CA",
    "sg:tags":[
        "american",
        "steakhouse"
    ],
    "wof:name":"Hungry Hunter Steakhouse",
    "wof:placetype":"venue"
},
  "geometry": {"coordinates":[-117.159862,33.515351],"type":"Point"}
}