{
  "type": "Feature",
  "properties": {
    "iso:country":"US",
    "sg:address":"1213 Ocean Front Walk",
    "sg:city":"Venice",
    "sg:classifiers":[
        {
            "category":"Autos & Motor Vehicles",
            "subcategory":"Boat Sales",
            "type":"Retail Goods"
        }
    ],
    "sg:phone":"+1 310 314 0246",
    "sg:postcode":"90291",
    "sg:province":"CA",
    "sg:tags":[
        "equipment",
        "marine",
        "supply"
    ],
    "wof:name":"Marine Goods",
    "wof:placetype":"venue"
},
  "geometry": {"coordinates":[-118.475174,33.988469],"type":"Point"}
}