{
  "type": "Feature",
  "properties": {
    "addr:full":"14521 Arminta St Van Nuys CA 91402",
    "addr:housenumber":"14521",
    "addr:postcode":"91402",
    "addr:street":"Arminta St",
    "iso:country":"US",
    "sg:address":"14521 Arminta St",
    "sg:city":"Van Nuys",
    "sg:classifiers":[
        {
            "category":"Building & Trades",
            "subcategory":"Plumbing",
            "type":"Services"
        }
    ],
    "sg:phone":"+1 818 997 6949",
    "sg:postcode":"91402",
    "sg:province":"CA",
    "sg:tags":[
        "heating",
        "contractor"
    ],
    "wof:name":"Bmd Technology",
    "wof:placetype":"venue"
},
  "geometry": {"coordinates":[-118.453597,34.213495],"type":"Point"}
}