{
  "type": "Feature",
  "properties": {
    "addr:full":"40527 Pebble Way Palmdale CA 93551",
    "addr:housenumber":"40527",
    "addr:postcode":"ca 93551",
    "addr:street":"Pebble Way",
    "iso:country":"US",
    "sg:address":"40527 Pebble Way",
    "sg:city":"Palmdale",
    "sg:classifiers":[
        {
            "category":"Personal",
            "type":"Services"
        },
        {
            "category":"Sports & Exercise",
            "subcategory":"Gym",
            "type":"Entertainment"
        }
    ],
    "sg:phone":"+1 661 273 9442",
    "sg:postcode":"93551",
    "sg:province":"CA",
    "sg:tags":[
        "trainer",
        "consultant",
        "program",
        "physical",
        "fitness"
    ],
    "wof:name":"Licensed Educational Psych",
    "wof:placetype":"venue"
},
  "geometry": {"coordinates":[-118.189205,34.61892],"type":"Point"}
}