{
  "type": "Feature",
  "properties": {
    "addr:full":"1970 Grande Cir Fairfield CA 94533",
    "addr:housenumber":"1970",
    "addr:postcode":"94533",
    "addr:street":"Grande Cir",
    "iso:country":"US",
    "sg:address":"1970 Grande Cir",
    "sg:city":"Fairfield",
    "sg:classifiers":[
        {
            "category":"Building & Trades",
            "subcategory":"Plumbing",
            "type":"Services"
        }
    ],
    "sg:phone":"+1 707 290 7988",
    "sg:postcode":"94533",
    "sg:province":"CA",
    "sg:tags":[
        "plumbing",
        "contractor"
    ],
    "wof:name":"G & J Plumbing",
    "wof:placetype":"venue"
},
  "geometry": {"coordinates":[-122.010972,38.264294],"type":"Point"}
}