{
  "type": "Feature",
  "properties": {
    "addr:full":"1550 W Mahalo Pl Compton CA 90220",
    "addr:housenumber":"1550",
    "addr:postcode":"90220",
    "addr:street":"W Mahalo Pl",
    "iso:country":"US",
    "sg:address":"1550 W Mahalo Pl",
    "sg:city":"Compton",
    "sg:classifiers":[
        {
            "category":"Shopping",
            "subcategory":"Computers & Home Electronics",
            "type":"Retail Goods"
        }
    ],
    "sg:phone":"+1 310 669 9700",
    "sg:postcode":"90220",
    "sg:province":"CA",
    "wof:name":"ADF INC",
    "wof:placetype":"venue"
},
  "geometry": {"coordinates":[-118.245902,33.871079],"type":"Point"}
}