{
  "type": "Feature",
  "properties": {
    "addr:full":"864 Arroyo St San Fernando CA 91340",
    "addr:housenumber":"864",
    "addr:postcode":"91340",
    "addr:street":"Arroyo St",
    "iso:country":"US",
    "sg:address":"864 Arroyo St",
    "sg:city":"San Fernando",
    "sg:classifiers":[
        {
            "category":"Wholesale",
            "subcategory":"Construction Materials",
            "type":"Manufacturing & Wholesale Goods"
        }
    ],
    "sg:phone":"+1 818 361 3631",
    "sg:postcode":"91340",
    "sg:province":"CA",
    "wof:name":"F & J Marble & Tile",
    "wof:placetype":"venue"
},
  "geometry": {"coordinates":[-118.42309899999999,34.286525],"type":"Point"}
}