{
  "type": "Feature",
  "properties": {
    "iso:country":"US",
    "sg:address":"250 S Ventu Park Rd",
    "sg:city":"Newbury Park",
    "sg:classifiers":[
        {
            "category":"Freight",
            "type":"Transportation"
        }
    ],
    "sg:phone":"+1 805 499 3346",
    "sg:postcode":"91320",
    "sg:province":"CA",
    "wof:name":"Adventure Transport",
    "wof:placetype":"venue"
},
  "geometry": {"coordinates":[-118.908869,34.173153],"type":"Point"}
}