{
  "type": "Feature",
  "properties": {
    "iso:country":"US",
    "sg:address":"1824 W 84th Pl",
    "sg:city":"Los Angeles",
    "sg:classifiers":[
        {
            "category":"Social Services",
            "subcategory":"Adult Care",
            "type":"Services"
        }
    ],
    "sg:phone":"+1 323 758 5251",
    "sg:postcode":"90047",
    "sg:province":"CA",
    "sg:tags":[
        "home",
        "residential"
    ],
    "wof:name":"E & E House Of Care Assisted",
    "wof:placetype":"venue"
},
  "geometry": {"coordinates":[-118.310736,33.961721],"type":"Point"}
}