{
  "type": "Feature",
  "properties": {
    "iso:country":"US",
    "sg:address":"9822 Russell Ave",
    "sg:city":"Garden Grove",
    "sg:classifiers":[
        {
            "category":"Education",
            "subcategory":"School",
            "type":"Public Place"
        }
    ],
    "sg:phone":"+1 714 537 4850",
    "sg:postcode":"92844",
    "sg:province":"CA",
    "sg:tags":[
        "high",
        "middle",
        "elementary"
    ],
    "wof:name":"Cross County Vietnamese Christian Church",
    "wof:placetype":"venue"
},
  "geometry": {"coordinates":[-117.958,33.768501],"type":"Point"}
}