{
  "type": "Feature",
  "properties": {
    "addr:full":"5037 Newport Ave San Diego CA 92107",
    "addr:housenumber":"5037",
    "addr:postcode":"92107",
    "addr:street":"Newport Ave",
    "iso:country":"US",
    "sg:address":"5037 Newport Ave",
    "sg:city":"San Diego",
    "sg:classifiers":[
        {
            "category":"Shopping",
            "subcategory":"Bicycles & Sporting Goods",
            "type":"Retail Goods"
        }
    ],
    "sg:phone":"+1 619 223 8808",
    "sg:postcode":"92107",
    "sg:province":"CA",
    "sg:tags":[
        "surfboard"
    ],
    "wof:name":"South Coast Longboards",
    "wof:placetype":"venue"
},
  "geometry": {"coordinates":[-117.251839,32.747188],"type":"Point"}
}