{
  "type": "Feature",
  "properties": {
    "iso:country":"US",
    "sg:address":"1207 Front St",
    "sg:city":"Sacramento",
    "sg:classifiers":[
        {
            "category":"Professional",
            "subcategory":"Advertising",
            "type":"Services"
        }
    ],
    "sg:phone":"+1 916 455 6677",
    "sg:postcode":"95814",
    "sg:province":"CA",
    "sg:tags":[
        "agency",
        "employment"
    ],
    "sg:website":"www.sacjobs.com",
    "wof:name":"Sacjobs.com",
    "wof:placetype":"venue"
},
  "geometry": {"coordinates":[-121.50637500000001,38.581269],"type":"Point"}
}