{
  "type": "Feature",
  "properties": {
    "addr:full":"24490 Frampton Ave Harbor City CA 90710",
    "addr:postcode":"24490;90710",
    "addr:street":"Frampton Ave",
    "iso:country":"US",
    "sg:address":"24490 Frampton Ave",
    "sg:city":"Harbor City",
    "sg:classifiers":[
        {
            "category":"Retail",
            "subcategory":"Storage",
            "type":"Services"
        }
    ],
    "sg:phone":"+1 310 326 8853",
    "sg:postcode":"90710",
    "sg:province":"CA",
    "sg:tags":[
        "self"
    ],
    "wof:name":"US Storage Centers Harbor City",
    "wof:placetype":"venue"
},
  "geometry": {"coordinates":[-118.299004,33.801899],"type":"Point"}
}