{
  "type": "Feature",
  "properties": {
    "addr:full":"221 Oak St Oakland CA 94607",
    "addr:housenumber":"221",
    "addr:postcode":"94607",
    "addr:street":"Oak St",
    "iso:country":"US",
    "sg:address":"221 Oak St",
    "sg:city":"Oakland",
    "sg:classifiers":[
        {
            "category":"Food & Beverages",
            "subcategory":"Bakery",
            "type":"Retail Goods"
        },
        {
            "category":"Organizations",
            "subcategory":"Non-profit Organization",
            "type":"Services"
        }
    ],
    "sg:phone":"+1 510 444 4133",
    "sg:postcode":"94607",
    "sg:province":"CA",
    "sg:tags":[
        "foundations-educational",
        "philanthropic",
        "research",
        "bank",
        "charity"
    ],
    "wof:name":"Hope",
    "wof:placetype":"venue"
},
  "geometry": {"coordinates":[-122.26795,37.792908],"type":"Point"}
}