{
  "type": "Feature",
  "properties": {
    "addr:full":"31612 Via Coyote Trabuco Canyon CA 92679",
    "addr:housenumber":"31612",
    "addr:postcode":"92679",
    "addr:street":"Via Coyote",
    "iso:country":"US",
    "sg:address":"31612 Via Coyote",
    "sg:city":"Trabuco Canyon",
    "sg:classifiers":[
        {
            "category":"Manufacturing",
            "subcategory":"Aerospace",
            "type":"Manufacturing & Wholesale Goods"
        }
    ],
    "sg:phone":"+1 949 858 9043",
    "sg:postcode":"92679",
    "sg:province":"CA",
    "sg:tags":[
        "aircraft",
        "mfg"
    ],
    "wof:name":"Atlas Aviation",
    "wof:placetype":"venue"
},
  "geometry": {"coordinates":[-117.581073,33.61637],"type":"Point"}
}