{
  "type": "Feature",
  "properties": {
    "addr:full":"1388 Travis Blvd Fairfield CA 94533",
    "addr:housenumber":"1388",
    "addr:postcode":"94533",
    "addr:street":"Travis Blvd",
    "iso:country":"US",
    "sg:address":"1388 Travis Blvd",
    "sg:city":"Fairfield",
    "sg:classifiers":[
        {
            "category":"Shopping",
            "subcategory":"Gifts & Souvenirs",
            "type":"Retail Goods"
        }
    ],
    "sg:phone":"+1 707 426 4100",
    "sg:postcode":"94533",
    "sg:province":"CA",
    "sg:tags":[
        "shop"
    ],
    "wof:name":"Things Remembered",
    "wof:placetype":"venue"
},
  "geometry": {"coordinates":[-122.053251,38.258238],"type":"Point"}
}