{
  "type": "Feature",
  "properties": {
    "iso:country":"US",
    "sg:address":"529 10th St",
    "sg:city":"Paso Robles",
    "sg:classifiers":[
        {
            "category":"Real Estate",
            "subcategory":"Real Estate Operator",
            "type":"Services"
        }
    ],
    "sg:phone":"+1 805 238 5793",
    "sg:postcode":"93446",
    "sg:province":"CA",
    "sg:tags":[
        "apartment"
    ],
    "wof:name":"Hacienda Del Norte Apartments",
    "wof:placetype":"venue"
},
  "geometry": {"coordinates":[-120.693467,35.624522],"type":"Point"}
}