{
  "type": "Feature",
  "properties": {
    "iso:country":"US",
    "sg:address":"15930 Shalom Rd",
    "sg:city":"Ramona",
    "sg:classifiers":[
        {
            "category":"Real Estate",
            "subcategory":"Real Estate Agent",
            "type":"Services"
        }
    ],
    "sg:phone":"+1 760 789 4969",
    "sg:postcode":"92065",
    "sg:province":"CA",
    "sg:tags":[
        "agency",
        "rental"
    ],
    "wof:name":"Just Chillin Rentals",
    "wof:placetype":"venue"
},
  "geometry": {"coordinates":[-116.755503,33.001509],"type":"Point"}
}