{
  "type": "Feature",
  "properties": {
    "addr:full":"22750 Roscoe Blvd West Hills CA 91304",
    "addr:housenumber":"22750",
    "addr:postcode":"91304",
    "addr:street":"Roscoe Blvd",
    "iso:country":"US",
    "sg:address":"22750 Roscoe Blvd",
    "sg:city":"West Hills",
    "sg:classifiers":[
        {
            "category":"Recreation",
            "type":"Entertainment"
        }
    ],
    "sg:phone":"+1 818 999 3680",
    "sg:postcode":"91304",
    "sg:province":"CA",
    "sg:tags":[
        "martial",
        "arts",
        "instruction"
    ],
    "wof:name":"Makoto Karate Academy",
    "wof:placetype":"venue"
},
  "geometry": {"coordinates":[-118.620717,34.219365],"type":"Point"}
}