{
  "type": "Feature",
  "properties": {
    "addr:full":"2111 Union St San Francisco CA 94123",
    "addr:housenumber":"2111",
    "addr:postcode":"94123",
    "addr:street":"Union St",
    "iso:country":"US",
    "sg:address":"2111 Union St",
    "sg:city":"San Francisco",
    "sg:classifiers":[
        {
            "category":"Shopping",
            "subcategory":"Clothing, Apparel, & Fashions",
            "type":"Retail Goods"
        }
    ],
    "sg:phone":"+1 415 922 8040",
    "sg:postcode":"94123",
    "sg:province":"CA",
    "wof:name":"Rin",
    "wof:placetype":"venue"
},
  "geometry": {"coordinates":[-122.435346,37.797036],"type":"Point"}
}