{
  "type": "Feature",
  "properties": {
    "addr:full":"11 Santa Maria Way Orinda CA 94563",
    "addr:housenumber":"11",
    "addr:postcode":"94563",
    "addr:street":"Santa Maria Way",
    "iso:country":"US",
    "sg:address":"11 Santa Maria Way",
    "sg:city":"Orinda",
    "sg:classifiers":[
        {
            "category":"Health Services",
            "subcategory":"Doctor",
            "type":"Services"
        }
    ],
    "sg:phone":"+1 925 254 8380",
    "sg:postcode":"94563",
    "sg:province":"CA",
    "sg:tags":[
        "surgeon",
        "oral"
    ],
    "wof:name":"Morrow Nancy A DDS",
    "wof:placetype":"venue"
},
  "geometry": {"coordinates":[-122.185997,37.881901],"type":"Point"}
}