{
  "type": "Feature",
  "properties": {
    "iso:country":"US",
    "sg:address":"6221 1/2 S Figueroa St",
    "sg:city":"Los Angeles",
    "sg:classifiers":[
        {
            "category":"Retail",
            "subcategory":"Laundry & Dry Cleaning",
            "type":"Services"
        }
    ],
    "sg:phone":"+1 323 752 5206",
    "sg:postcode":"90003",
    "sg:province":"CA",
    "sg:website":"www.monicasdrycleaners.com",
    "wof:name":"Monica's Dry Cleaners",
    "wof:placetype":"venue"
},
  "geometry": {"coordinates":[-118.282689,33.982717],"type":"Point"}
}