{
  "type": "Feature",
  "properties": {
    "addr:full":"1300 Rockefeller Dr Ceres CA 95307",
    "addr:housenumber":"1300",
    "addr:postcode":"95307",
    "addr:street":"Rockefeller Dr",
    "iso:country":"US",
    "sg:address":"1300 Rockefeller Dr",
    "sg:city":"Ceres",
    "sg:classifiers":[
        {
            "category":"Retail",
            "subcategory":"Auto Repair",
            "type":"Services"
        }
    ],
    "sg:phone":"+1 209 537 1967",
    "sg:postcode":"95307",
    "sg:province":"CA",
    "wof:name":"A & A Auto Care",
    "wof:placetype":"venue"
},
  "geometry": {"coordinates":[-120.975239,37.602087],"type":"Point"}
}