{
  "type": "Feature",
  "properties": {
    "addr:full":"28231 Marguerite Pkwy Mission Viejo CA 92692",
    "addr:housenumber":"28231",
    "addr:postcode":"92692",
    "addr:street":"Marguerite Pkwy",
    "iso:country":"US",
    "sg:address":"28231 Marguerite Pkwy",
    "sg:city":"Mission Viejo",
    "sg:classifiers":[
        {
            "category":"Government",
            "subcategory":"Office",
            "type":"Public Place"
        }
    ],
    "sg:phone":"+1 949 347 0290",
    "sg:postcode":"92692",
    "sg:province":"CA",
    "sg:tags":[
        "national",
        "security"
    ],
    "wof:name":"Army  United States Dept of",
    "wof:placetype":"venue"
},
  "geometry": {"coordinates":[-117.670883,33.552844],"type":"Point"}
}