{
  "type": "Feature",
  "properties": {
    "iso:country":"US",
    "sg:address":"2912 Babson Dr",
    "sg:city":"Elk Grove",
    "sg:classifiers":[
        {
            "category":"Home & Garden",
            "subcategory":"Home Furnishings",
            "type":"Retail Goods"
        }
    ],
    "sg:phone":"+1 916 712 2210",
    "sg:postcode":"95758",
    "sg:province":"CA",
    "sg:tags":[
        "quilting"
    ],
    "wof:name":"Top To Bottom Quilting",
    "wof:placetype":"venue"
},
  "geometry": {"coordinates":[-121.473472,38.417104],"type":"Point"}
}