{
  "type": "Feature",
  "properties": {
    "iso:country":"US",
    "sg:address":"1114 Aberdeen Ave",
    "sg:city":"Livermore",
    "sg:classifiers":[
        {
            "category":"Shopping",
            "subcategory":"Clothing, Apparel, & Fashions",
            "type":"Retail Goods"
        }
    ],
    "sg:phone":"+1 209 505 3554",
    "sg:postcode":"94550",
    "sg:province":"CA",
    "sg:tags":[
        "baby",
        "accessory"
    ],
    "wof:name":"Baby Guard-Central Valley",
    "wof:placetype":"venue"
},
  "geometry": {"coordinates":[-121.779716,37.669634],"type":"Point"}
}