{
  "type": "Feature",
  "properties": {
    "iso:country":"US",
    "sg:address":"43723 20th St W",
    "sg:city":"Lancaster",
    "sg:classifiers":[
        {
            "category":"Health Services",
            "subcategory":"Health Practitioner",
            "type":"Services"
        }
    ],
    "sg:phone":"+1 661 948 5086",
    "sg:postcode":"93534",
    "sg:province":"CA",
    "sg:tags":[
        "nurse"
    ],
    "wof:name":"Bernie Mayer",
    "wof:placetype":"venue"
},
  "geometry": {"coordinates":[-118.165686,34.677862],"type":"Point"}
}