{
  "type": "Feature",
  "properties": {
    "addr:full":"19143 S Bloomfield Ave. Cerritos CA 90703",
    "addr:housenumber":"19143",
    "addr:postcode":"ca 90703",
    "addr:street":"S Bloomfield Ave.",
    "iso:country":"US",
    "sg:address":"19143 S Bloomfield Ave.",
    "sg:city":"Cerritos",
    "sg:classifiers":[
        {
            "category":"Restaurant",
            "type":"Food & Drink"
        }
    ],
    "sg:phone":"+1 562 860 3433",
    "sg:postcode":"90703",
    "sg:province":"CA",
    "sg:tags":[
        "korean"
    ],
    "wof:name":"Tofu Village",
    "wof:placetype":"venue"
},
  "geometry": {"coordinates":[-118.064003,33.8573],"type":"Point"}
}