{
  "type": "Feature",
  "properties": {
    "iso:country":"US",
    "sg:address":"2050 Pioneer Ct",
    "sg:city":"San Mateo",
    "sg:classifiers":[
        {
            "category":"Wholesale",
            "subcategory":"Construction Materials",
            "type":"Manufacturing & Wholesale Goods"
        }
    ],
    "sg:phone":"+1 650 574 2007",
    "sg:postcode":"94403",
    "sg:province":"CA",
    "sg:tags":[
        "importing",
        "lumber"
    ],
    "wof:name":"Siberian Crown",
    "wof:placetype":"venue"
},
  "geometry": {"coordinates":[-122.31204700000001,37.546953],"type":"Point"}
}