{
  "type": "Feature",
  "properties": {
    "iso:country":"US",
    "sg:address":"10475 Mountain View Ave",
    "sg:city":"Loma Linda",
    "sg:classifiers":[
        {
            "category":"Restaurant",
            "type":"Food & Drink"
        }
    ],
    "sg:menulink":"http://www.allmenus.com/ca/san-bernardino/147909-farmer-boys/menu/",
    "sg:phone":"+1 909 799 6714",
    "sg:postcode":"92354",
    "sg:province":"CA",
    "sg:tags":[
        "american"
    ],
    "wof:name":"Farmer Boys",
    "wof:placetype":"venue"
},
  "geometry": {"coordinates":[-117.24321,34.063661],"type":"Point"}
}