{
  "type": "Feature",
  "properties": {
    "iso:country":"US",
    "sg:address":"186 Wikiup Dr",
    "sg:city":"Santa Rosa",
    "sg:classifiers":[
        {
            "category":"Personal",
            "subcategory":"Beauty Salon",
            "type":"Services"
        }
    ],
    "sg:phone":"+1 707 545 8449",
    "sg:postcode":"95403",
    "sg:province":"CA",
    "sg:tags":[
        "school"
    ],
    "sg:website":"www.lytles-rebc.com",
    "wof:name":"Redwood Empire Beauty College",
    "wof:placetype":"venue"
},
  "geometry": {"coordinates":[-122.75836700000001,38.508103],"type":"Point"}
}