{
  "type": "Feature",
  "properties": {
    "addr:full":"213 E St Davis CA 95616",
    "addr:housenumber":"213",
    "addr:postcode":"95616",
    "addr:street":"E St",
    "iso:country":"US",
    "sg:address":"213 E St",
    "sg:city":"Davis",
    "sg:classifiers":[
        {
            "category":"Home & Garden",
            "subcategory":"Furniture",
            "type":"Retail Goods"
        }
    ],
    "sg:phone":"+1 530 756 7200",
    "sg:postcode":"95616",
    "sg:province":"CA",
    "sg:tags":[
        "mattress"
    ],
    "wof:name":"Davis Mattress & Futon Outlet",
    "wof:placetype":"venue"
},
  "geometry": {"coordinates":[-121.741468,38.544347],"type":"Point"}
}