{
  "type": "Feature",
  "properties": {
    "iso:country":"US",
    "sg:address":"5004 Lewis Rd",
    "sg:city":"Agoura Hills",
    "sg:classifiers":[
        {
            "category":"Education",
            "subcategory":"Preschool",
            "type":"Public Place"
        }
    ],
    "sg:phone":"+1 818 991 5439",
    "sg:postcode":"91301",
    "sg:province":"CA",
    "sg:website":"cornerstonepreschool.org",
    "wof:name":"Cornerstone Preschool",
    "wof:placetype":"venue"
},
  "geometry": {"coordinates":[-118.742891,34.141043],"type":"Point"}
}