{
  "type": "Feature",
  "properties": {
    "iso:country":"US",
    "sg:address":"666 Bellevue Ave",
    "sg:city":"Oakland",
    "sg:classifiers":[
        {
            "category":"Sports & Exercise",
            "subcategory":"Sports Center",
            "type":"Entertainment"
        }
    ],
    "sg:phone":"+1 510 465 1850",
    "sg:postcode":"94610",
    "sg:province":"CA",
    "sg:tags":[
        "amateur",
        "team"
    ],
    "wof:name":"Friends of Oakland Parks & Recreations",
    "wof:placetype":"venue"
},
  "geometry": {"coordinates":[-122.25900300000001,37.8092],"type":"Point"}
}