{
  "type": "Feature",
  "properties": {
    "iso:country":"US",
    "sg:address":"14325 Astoria St",
    "sg:city":"Sylmar",
    "sg:classifiers":[
        {
            "category":"Education",
            "subcategory":"School",
            "type":"Public Place"
        }
    ],
    "sg:phone":"+1 818 367 5886",
    "sg:postcode":"91342",
    "sg:province":"CA",
    "sg:tags":[
        "elementary"
    ],
    "sg:website":"http://www.bell-jeff.net",
    "wof:name":"St Didacus Elementary School",
    "wof:placetype":"venue"
},
  "geometry": {"coordinates":[-118.445359,34.305653],"type":"Point"}
}