{
  "type": "Feature",
  "properties": {
    "iso:country":"US",
    "sg:address":"5050 Murphy Canyon Rd",
    "sg:city":"San Diego",
    "sg:classifiers":[
        {
            "category":"Communications",
            "subcategory":"Radio Station",
            "type":"Services"
        }
    ],
    "sg:phone":"+1 619 570 1360",
    "sg:postcode":"92123",
    "sg:province":"CA",
    "sg:tags":[
        "company",
        "broadcasting"
    ],
    "wof:name":"K-Pop",
    "wof:placetype":"venue"
},
  "geometry": {"coordinates":[-117.11940800000001,32.825869],"type":"Point"}
}