{
  "type": "Feature",
  "properties": {
    "addr:full":"6542 Greenbush Ave Van Nuys CA 91401",
    "addr:housenumber":"6542",
    "addr:postcode":"91401",
    "addr:street":"Greenbush Ave",
    "iso:country":"US",
    "sg:address":"6542 Greenbush Ave",
    "sg:city":"Van Nuys",
    "sg:classifiers":[
        {
            "category":"Wholesale",
            "subcategory":"Electrical",
            "type":"Manufacturing & Wholesale Goods"
        }
    ],
    "sg:phone":"+1 818 988 5568",
    "sg:postcode":"91401",
    "sg:province":"CA",
    "sg:tags":[
        "wireless",
        "communication",
        "information",
        "equipment"
    ],
    "wof:name":"Luna Imports Inc",
    "wof:placetype":"venue"
},
  "geometry": {"coordinates":[-118.42571100000001,34.18711],"type":"Point"}
}