{
  "type": "Feature",
  "properties": {
    "iso:country":"US",
    "sg:address":"27674 Newhall Ranch Rd",
    "sg:city":"Valencia",
    "sg:classifiers":[
        {
            "category":"Freight",
            "type":"Transportation"
        }
    ],
    "sg:phone":"+1 661 294 1998",
    "sg:postcode":"91355",
    "sg:province":"CA",
    "sg:tags":[
        "delivery"
    ],
    "wof:name":"Vital Express Courier Inc",
    "wof:placetype":"venue"
},
  "geometry": {"coordinates":[-118.574868,34.442653],"type":"Point"}
}