{
  "type": "Feature",
  "properties": {
    "iso:country":"US",
    "sg:address":"1000 River Rock Dr",
    "sg:city":"Folsom",
    "sg:classifiers":[
        {
            "category":"Manufacturing",
            "subcategory":"Tools & Machinery",
            "type":"Manufacturing & Wholesale Goods"
        }
    ],
    "sg:phone":"+1 916 989 5703",
    "sg:postcode":"95630",
    "sg:province":"CA",
    "sg:tags":[
        "adhesive",
        "gluing",
        "equipment"
    ],
    "wof:name":"Henkel Loctite",
    "wof:placetype":"venue"
},
  "geometry": {"coordinates":[-121.195928,38.678712],"type":"Point"}
}