{
  "type": "Feature",
  "properties": {
    "addr:full":"1244 Spring St St Helena CA 94574",
    "addr:housenumber":"1244",
    "addr:postcode":"94574",
    "addr:street":"Spring St",
    "iso:country":"US",
    "sg:address":"1244 Spring St",
    "sg:city":"St Helena",
    "sg:classifiers":[
        {
            "category":"Real Estate",
            "subcategory":"Real Estate Agent",
            "type":"Services"
        }
    ],
    "sg:phone":"+1 707 963 4643",
    "sg:postcode":"94574",
    "sg:province":"CA",
    "wof:name":"Preferred Properties",
    "wof:placetype":"venue"
},
  "geometry": {"coordinates":[-122.46814000000001,38.503801],"type":"Point"}
}