{
  "type": "Feature",
  "properties": {
    "addr:full":"495 Main St Janesville CA 96114",
    "addr:housenumber":"495",
    "addr:postcode":"96114",
    "addr:street":"Main St",
    "iso:country":"US",
    "sg:address":"495 Main St",
    "sg:city":"Janesville",
    "sg:classifiers":[
        {
            "category":"Government",
            "subcategory":"Post Office",
            "type":"Public Place"
        }
    ],
    "sg:phone":"+1 530 253 3666",
    "sg:postcode":"96114",
    "sg:province":"CA",
    "wof:name":"US Post Office",
    "wof:placetype":"venue"
},
  "geometry": {"coordinates":[-120.53932500000001,40.313081],"type":"Point"}
}