{
  "type": "Feature",
  "properties": {
    "iso:country":"US",
    "sg:address":"495 Main St",
    "sg:city":"Janesville",
    "sg:classifiers":[
        {
            "category":"Government",
            "subcategory":"Post Office",
            "type":"Public Place"
        }
    ],
    "sg:phone":"+1 530 253 3666",
    "sg:postcode":"96114",
    "sg:province":"CA",
    "wof:name":"US Post Office",
    "wof:placetype":"venue"
},
  "geometry": {"coordinates":[-120.539325,40.313081],"type":"Point"}
}