{
  "type": "Feature",
  "properties": {
    "iso:country":"US",
    "sg:address":"140 Nova Dr",
    "sg:city":"Piedmont",
    "sg:classifiers":[
        {
            "category":"Building & Trades",
            "subcategory":"Plumbing",
            "type":"Services"
        }
    ],
    "sg:phone":"+1 510 547 8430",
    "sg:postcode":"94610",
    "sg:province":"CA",
    "sg:tags":[
        "product",
        "management",
        "energy",
        "system"
    ],
    "wof:name":"Accelerated Energy Solutions",
    "wof:placetype":"venue"
},
  "geometry": {"coordinates":[-122.23947200000001,37.822456],"type":"Point"}
}