{
  "type": "Feature",
  "properties": {
    "iso:country":"US",
    "sg:address":"2370 Market St #363",
    "sg:city":"San Francisco",
    "sg:classifiers":[
        {
            "category":"Arts & Performance",
            "subcategory":"Arts Center",
            "type":"Entertainment"
        }
    ],
    "sg:postcode":"94114",
    "sg:province":"CA",
    "wof:name":"DerWilly Music Book Collectibles",
    "wof:placetype":"venue"
},
  "geometry": {"coordinates":[-122.434742,37.763321],"type":"Point"}
}