{
  "type": "Feature",
  "properties": {
    "addr:full":"4111 S Centinela Ave Los Angeles CA 90066",
    "addr:housenumber":"4111",
    "addr:postcode":"90066",
    "addr:street":"S Centinela Ave",
    "iso:country":"US",
    "sg:address":"4111 S Centinela Ave",
    "sg:city":"Los Angeles",
    "sg:classifiers":[
        {
            "category":"Shopping",
            "subcategory":"Clothing, Apparel, & Fashions",
            "type":"Retail Goods"
        }
    ],
    "sg:phone":"+1 310 391 5562",
    "sg:postcode":"90066",
    "sg:province":"CA",
    "sg:tags":[
        "accessory",
        "clothing",
        "women's"
    ],
    "wof:name":"Cinderalla Clothing Store",
    "wof:placetype":"venue"
},
  "geometry": {"coordinates":[-118.42800099999999,33.996899],"type":"Point"}
}