{
  "type": "Feature",
  "properties": {
    "iso:country":"US",
    "sg:address":"4212 Division St",
    "sg:city":"Los Angeles",
    "sg:classifiers":[
        {
            "category":"Shopping",
            "subcategory":"Clothing, Apparel, & Fashions",
            "type":"Retail Goods"
        }
    ],
    "sg:phone":"+1 323 256 5040",
    "sg:postcode":"90065",
    "sg:province":"CA",
    "sg:tags":[
        "designer"
    ],
    "wof:name":"Jupe",
    "wof:placetype":"venue"
},
  "geometry": {"coordinates":[-118.22286099999999,34.116606],"type":"Point"}
}