{
  "type": "Feature",
  "properties": {
    "iso:country":"US",
    "sg:address":"706 Pismo Ct",
    "sg:city":"San Diego",
    "sg:classifiers":[
        {
            "category":"Arts & Performance",
            "subcategory":"Arts Center",
            "type":"Entertainment"
        }
    ],
    "sg:phone":"+1 858 488 5950",
    "sg:postcode":"92109",
    "sg:province":"CA",
    "sg:website":"www.taang.com",
    "wof:name":"Taang Records & Retail",
    "wof:placetype":"venue"
},
  "geometry": {"coordinates":[-117.253516,32.783408],"type":"Point"}
}