{
  "type": "Feature",
  "properties": {
    "addr:full":"253 Rickenbacker Cir Livermore CA 94550",
    "addr:housenumber":"253",
    "addr:postcode":"94550",
    "addr:street":"Rickenbacker Cir",
    "iso:country":"US",
    "sg:address":"253 Rickenbacker Cir",
    "sg:city":"Livermore",
    "sg:classifiers":[
        {
            "category":"Building & Trades",
            "subcategory":"Construction",
            "type":"Services"
        }
    ],
    "sg:phone":"+1 925 371 4610",
    "sg:postcode":"94550",
    "sg:province":"CA",
    "sg:tags":[
        "asbestos",
        "removal"
    ],
    "wof:name":"Parc",
    "wof:placetype":"venue"
},
  "geometry": {"coordinates":[-121.802279,37.691963],"type":"Point"}
}