{
  "type": "Feature",
  "properties": {
    "addr:full":"111 N Sunnyvale Ave Sunnyvale CA 94086",
    "addr:housenumber":"111",
    "addr:postcode":"94086",
    "addr:street":"N Sunnyvale Ave",
    "iso:country":"US",
    "sg:address":"111 N Sunnyvale Ave",
    "sg:city":"Sunnyvale",
    "sg:classifiers":[
        {
            "category":"Retail",
            "subcategory":"Auto Repair",
            "type":"Services"
        }
    ],
    "sg:phone":"+1 408 738 1916",
    "sg:postcode":"94086",
    "sg:province":"CA",
    "sg:tags":[
        "brake"
    ],
    "wof:name":"Hendy Auto Repair",
    "wof:placetype":"venue"
},
  "geometry": {"coordinates":[-122.028476,37.378398],"type":"Point"}
}