{
  "type": "Feature",
  "properties": {
    "iso:country":"US",
    "sg:address":"921 Keswick Pl",
    "sg:city":"Glendora",
    "sg:classifiers":[
        {
            "category":"Professional",
            "subcategory":"Business Services",
            "type":"Services"
        }
    ],
    "sg:phone":"+1 626 963 7577",
    "sg:postcode":"91741",
    "sg:province":"CA",
    "sg:tags":[
        "interior",
        "consultant",
        "design",
        "decorator"
    ],
    "wof:name":"Eddie Russel Interiors",
    "wof:placetype":"venue"
},
  "geometry": {"coordinates":[-117.881968,34.136543],"type":"Point"}
}