{
  "type": "Feature",
  "properties": {
    "addr:full":"477 N El Camino Real Ste C304 Encinitas CA 92024",
    "addr:housenumber":"477",
    "addr:postcode":"92024",
    "addr:street":"N El Camino Real Ste C304",
    "iso:country":"US",
    "sg:address":"477 N El Camino Real Ste C304",
    "sg:city":"Encinitas",
    "sg:classifiers":[
        {
            "category":"Health Services",
            "subcategory":"Doctor",
            "type":"Services"
        }
    ],
    "sg:phone":"+1 760 635 3777",
    "sg:postcode":"92024",
    "sg:province":"CA",
    "wof:name":"Makani Samina MD",
    "wof:placetype":"venue"
},
  "geometry": {"coordinates":[-117.262325,33.72087],"type":"Point"}
}