{
  "type": "Feature",
  "properties": {
    "iso:country":"US",
    "sg:address":"391 K St",
    "sg:city":"Parlier",
    "sg:classifiers":[
        {
            "category":"Food & Beverages",
            "subcategory":"Groceries & Convenience Stores",
            "type":"Retail Goods"
        }
    ],
    "sg:phone":"+1 559 646 1707",
    "sg:postcode":"93648",
    "sg:province":"CA",
    "sg:tags":[
        "grocer"
    ],
    "wof:name":"Toby's Market",
    "wof:placetype":"venue"
},
  "geometry": {"coordinates":[-119.527744,36.608433],"type":"Point"}
}