{
  "type": "Feature",
  "properties": {
    "addr:full":"1804 N Broadway Los Angeles CA 90031",
    "addr:housenumber":"1804",
    "addr:postcode":"90031",
    "addr:street":"N Broadway",
    "iso:country":"US",
    "sg:address":"1804 N Broadway",
    "sg:city":"Los Angeles",
    "sg:classifiers":[
        {
            "category":"Personal",
            "subcategory":"Barber",
            "type":"Services"
        }
    ],
    "sg:phone":"+1 323 223 2050",
    "sg:postcode":"90031",
    "sg:province":"CA",
    "sg:website":"www.linasbeautysalon.com",
    "wof:name":"Lina's Beauty Salon",
    "wof:placetype":"venue"
},
  "geometry": {"coordinates":[-118.22217000000001,34.071606],"type":"Point"}
}