{
  "type": "Feature",
  "properties": {
    "iso:country":"US",
    "sg:address":"3525 Old Conejo Rd",
    "sg:city":"Newbury Park",
    "sg:classifiers":[
        {
            "category":"Social Services",
            "type":"Services"
        }
    ],
    "sg:phone":"+1 805 376 9998",
    "sg:postcode":"91320",
    "sg:province":"CA",
    "sg:tags":[
        "counselor",
        "marriage",
        "family"
    ],
    "wof:name":"Relational Consulting",
    "wof:placetype":"venue"
},
  "geometry": {"coordinates":[-118.952065,34.191915],"type":"Point"}
}