{
  "type": "Feature",
  "properties": {
    "addr:full":"526 E Hillcrest Dr Thousand Oaks CA 91360",
    "addr:housenumber":"526",
    "addr:postcode":"91360",
    "addr:street":"E Hillcrest Dr",
    "iso:country":"US",
    "sg:address":"526 E Hillcrest Dr",
    "sg:city":"Thousand Oaks",
    "sg:classifiers":[
        {
            "category":"Professional",
            "type":"Services"
        }
    ],
    "sg:phone":"+1 805 497 3491",
    "sg:postcode":"91360",
    "sg:province":"CA",
    "wof:name":"Metro Park",
    "wof:placetype":"venue"
},
  "geometry": {"coordinates":[-118.867482,34.181358],"type":"Point"}
}