{
  "type": "Feature",
  "properties": {
    "addr:full":"7323 MacArthur Blvd Oakland CA 94605",
    "addr:housenumber":"7323",
    "addr:postcode":"94605",
    "addr:street":"Macarthur Blvd",
    "iso:country":"US",
    "sg:address":"7323 MacArthur Blvd",
    "sg:city":"Oakland",
    "sg:classifiers":[
        {
            "category":"Organizations",
            "subcategory":"Religious Organization",
            "type":"Services"
        }
    ],
    "sg:phone":"+1 510 639 4800",
    "sg:postcode":"94605",
    "sg:province":"CA",
    "wof:name":"Greater Life Community Outreach",
    "wof:placetype":"venue"
},
  "geometry": {"coordinates":[-122.171925,37.768878],"type":"Point"}
}