{
  "type": "Feature",
  "properties": {
    "iso:country":"US",
    "sg:address":"1505 Wilson Ter",
    "sg:city":"Glendale",
    "sg:classifiers":[
        {
            "category":"Health Services",
            "subcategory":"Doctor",
            "type":"Services"
        }
    ],
    "sg:phone":"+1 818 242 6828",
    "sg:postcode":"91206",
    "sg:province":"CA",
    "wof:name":"Tan Matthew S MD",
    "wof:placetype":"venue"
},
  "geometry": {"coordinates":[-118.231003,34.149502],"type":"Point"}
}