{
  "type": "Feature",
  "properties": {
    "iso:country":"US",
    "sg:address":"13015 Claymine Rd",
    "sg:city":"Edwards",
    "sg:classifiers":[
        {
            "category":"Shopping",
            "subcategory":"Discount & Variety Stores",
            "type":"Retail Goods"
        }
    ],
    "sg:phone":"+1 760 769 1143",
    "sg:postcode":"93523",
    "sg:province":"CA",
    "sg:tags":[
        "merchandise",
        "general"
    ],
    "wof:name":"Sun Shine Market",
    "wof:placetype":"venue"
},
  "geometry": {"coordinates":[-117.83655899999999,35.01555],"type":"Point"}
}