{
  "type": "Feature",
  "properties": {
    "iso:country":"US",
    "sg:address":"5660 Atlantic Ave",
    "sg:city":"Long Beach",
    "sg:classifiers":[
        {
            "category":"Restaurant",
            "type":"Food & Drink"
        }
    ],
    "sg:menulink":"http://www.allmenus.com/ca/long-beach-lakewood/28851-super-mex/menu/",
    "sg:phone":"+1 562 428 7144",
    "sg:postcode":"90805",
    "sg:province":"CA",
    "sg:tags":[
        "mexican"
    ],
    "wof:name":"Super Mex",
    "wof:placetype":"venue"
},
  "geometry": {"coordinates":[-118.18491299999999,33.858705],"type":"Point"}
}