{
  "type": "Feature",
  "properties": {
    "iso:country":"US",
    "sg:address":"3430 Sunrise Blvd",
    "sg:city":"Rancho Cordova",
    "sg:classifiers":[
        {
            "category":"Autos & Motor Vehicles",
            "subcategory":"Automobile Sales",
            "type":"Retail Goods"
        }
    ],
    "sg:phone":"+1 916 635 2514",
    "sg:postcode":"95742",
    "sg:province":"CA",
    "sg:tags":[
        "automotive"
    ],
    "wof:name":"Happy Auto Parts Inc",
    "wof:placetype":"venue"
},
  "geometry": {"coordinates":[-121.26599899999999,38.590599],"type":"Point"}
}