{
  "type": "Feature",
  "properties": {
    "iso:country":"US",
    "sg:address":"2857 E Florence Ave",
    "sg:city":"Huntington Park",
    "sg:classifiers":[
        {
            "category":"Food & Beverages",
            "subcategory":"Groceries & Convenience Stores",
            "type":"Retail Goods"
        }
    ],
    "sg:phone":"+1 323 583 5096",
    "sg:postcode":"90255",
    "sg:province":"CA",
    "wof:name":"Latino Market",
    "wof:placetype":"venue"
},
  "geometry": {"coordinates":[-118.218773,33.973687],"type":"Point"}
}