{
  "type": "Feature",
  "properties": {
    "addr:full":"455 Golden Gate Ave San Francisco CA 94102",
    "addr:housenumber":"455",
    "addr:postcode":"94102",
    "addr:street":"Golden Gate Ave",
    "iso:country":"US",
    "sg:address":"455 Golden Gate Ave",
    "sg:city":"San Francisco",
    "sg:classifiers":[
        {
            "category":"Government",
            "subcategory":"Office",
            "type":"Public Place"
        }
    ],
    "sg:phone":"+1 415 557 3000",
    "sg:postcode":"94102",
    "sg:province":"CA",
    "sg:tags":[
        "equalization",
        "housing",
        "employment",
        "board",
        "fair"
    ],
    "wof:name":"San Francisco District Office",
    "wof:placetype":"venue"
},
  "geometry": {"coordinates":[-122.418072,37.781278],"type":"Point"}
}