{
  "type": "Feature",
  "properties": {
    "addr:full":"12232 Witt Rd Poway CA 92064",
    "addr:housenumber":"12232",
    "addr:postcode":"ca 92064",
    "addr:street":"Witt Rd",
    "iso:country":"US",
    "sg:address":"12232 Witt Rd",
    "sg:city":"Poway",
    "sg:classifiers":[
        {
            "category":"Banks & Credit Unions",
            "subcategory":"Financial Services",
            "type":"Services"
        }
    ],
    "sg:phone":"+1 858 748 3742",
    "sg:postcode":"92064",
    "sg:province":"CA",
    "sg:tags":[
        "trust",
        "management"
    ],
    "wof:name":"Crone Family Trust",
    "wof:placetype":"venue"
},
  "geometry": {"coordinates":[-117.063749,32.969179],"type":"Point"}
}