{
  "type": "Feature",
  "properties": {
    "addr:full":"17520 Von Karman Ave. Irvine CA 92614",
    "addr:housenumber":"17520",
    "addr:postcode":"92614",
    "addr:street":"Von Karman Ave.",
    "iso:country":"US",
    "sg:address":"17520 Von Karman Ave.",
    "sg:city":"Irvine",
    "sg:classifiers":[
        {
            "category":"Shopping",
            "subcategory":"Florist",
            "type":"Retail Goods"
        }
    ],
    "sg:phone":"+1 949 752 1780",
    "sg:postcode":"92614",
    "sg:province":"CA",
    "sg:website":"irvineflorist.com",
    "wof:name":"Irvine Florist Ltd",
    "wof:placetype":"venue"
},
  "geometry": {"coordinates":[-117.844182,33.686425],"type":"Point"}
}