{
  "type": "Feature",
  "properties": {
    "iso:country":"US",
    "sg:address":"930 J St",
    "sg:city":"Sanger",
    "sg:classifiers":[
        {
            "category":"Food & Beverages",
            "subcategory":"Groceries & Convenience Stores",
            "type":"Retail Goods"
        }
    ],
    "sg:phone":"+1 559 875 7176",
    "sg:postcode":"93657",
    "sg:province":"CA",
    "sg:tags":[
        "grocer"
    ],
    "wof:name":"Mary Tierra Grocery",
    "wof:placetype":"venue"
},
  "geometry": {"coordinates":[-119.550962,36.703593],"type":"Point"}
}