{
  "type": "Feature",
  "properties": {
    "iso:country":"US",
    "sg:address":"999 Baker Way",
    "sg:city":"San Mateo",
    "sg:classifiers":[
        {
            "category":"Real Estate",
            "subcategory":"Developer",
            "type":"Services"
        }
    ],
    "sg:phone":"+1 650 571 1010",
    "sg:postcode":"94404",
    "sg:province":"CA",
    "wof:name":"Dewey Land Co",
    "wof:placetype":"venue"
},
  "geometry": {"coordinates":[-122.286292,37.560831],"type":"Point"}
}