{
  "type": "Feature",
  "properties": {
    "addr:full":"720 9th St Ramona CA 92065",
    "addr:housenumber":"720",
    "addr:postcode":"92065",
    "addr:street":"9Th St",
    "iso:country":"US",
    "sg:address":"720 9th St",
    "sg:city":"Ramona",
    "sg:classifiers":[
        {
            "category":"Education",
            "subcategory":"School",
            "type":"Public Place"
        }
    ],
    "sg:phone":"+1 760 787 2056",
    "sg:postcode":"92065",
    "sg:province":"CA",
    "wof:name":"Ramona Unified School District",
    "wof:placetype":"venue"
},
  "geometry": {"coordinates":[-116.86414499999999,33.039203],"type":"Point"}
}