{
  "type": "Feature",
  "properties": {
    "iso:country":"US",
    "sg:address":"8639 Lincoln Blvd",
    "sg:city":"Los Angeles",
    "sg:classifiers":[
        {
            "category":"Personal",
            "subcategory":"Beauty Salon",
            "type":"Services"
        }
    ],
    "sg:phone":"+1 310 670 4250",
    "sg:postcode":"90045",
    "sg:province":"CA",
    "sg:tags":[
        "manicuring"
    ],
    "wof:name":"Van Manicurist",
    "wof:placetype":"venue"
},
  "geometry": {"coordinates":[-118.417837,33.958283],"type":"Point"}
}