{
  "type": "Feature",
  "properties": {
    "iso:country":"US",
    "sg:address":"1540 W 152nd St",
    "sg:city":"Gardena",
    "sg:classifiers":[
        {
            "category":"Banks & Credit Unions",
            "subcategory":"Investment Brokerage",
            "type":"Services"
        }
    ],
    "sg:phone":"+1 310 329 2183",
    "sg:postcode":"90247",
    "sg:province":"CA",
    "sg:tags":[
        "information",
        "attorney",
        "referral",
        "security"
    ],
    "wof:name":"R W Enterprises",
    "wof:placetype":"venue"
},
  "geometry": {"coordinates":[-118.303506,33.893698],"type":"Point"}
}