{
  "type": "Feature",
  "properties": {
    "iso:country":"US",
    "sg:address":"601 N Palm St",
    "sg:city":"La Habra",
    "sg:classifiers":[
        {
            "category":"Manufacturing",
            "subcategory":"Metals",
            "type":"Manufacturing & Wholesale Goods"
        }
    ],
    "sg:phone":"+1 562 694 4441",
    "sg:postcode":"90631",
    "sg:province":"CA",
    "sg:tags":[
        "production",
        "grinding"
    ],
    "wof:name":"LA Habra Tool Grinding",
    "wof:placetype":"venue"
},
  "geometry": {"coordinates":[-117.924412,33.937277],"type":"Point"}
}