{
  "type": "Feature",
  "properties": {
    "addr:full":"141 Lower Ter San Francisco CA 94114",
    "addr:housenumber":"141",
    "addr:postcode":"94114",
    "addr:street":"Lower Ter",
    "iso:country":"US",
    "sg:address":"141 Lower Ter",
    "sg:city":"San Francisco",
    "sg:classifiers":[
        {
            "category":"Health Services",
            "subcategory":"Doctor",
            "type":"Services"
        }
    ],
    "sg:phone":"+1 415 431 2141",
    "sg:postcode":"94114",
    "sg:province":"CA",
    "sg:tags":[
        "physician",
        "surgeon"
    ],
    "wof:name":"John D Hensala MD",
    "wof:placetype":"venue"
},
  "geometry": {"coordinates":[-122.443404,37.763209],"type":"Point"}
}