{
  "type": "Feature",
  "properties": {
    "iso:country":"US",
    "sg:address":"17772 Beach Blvd",
    "sg:city":"Huntington Beach",
    "sg:classifiers":[
        {
            "category":"Health Services",
            "subcategory":"Doctor",
            "type":"Services"
        },
        {
            "category":"Health Services",
            "subcategory":"Hospital",
            "type":"Services"
        }
    ],
    "sg:phone":"+1 714 842 1473",
    "sg:postcode":"92647",
    "sg:province":"CA",
    "wof:name":"Children's Behavioral Center",
    "wof:placetype":"venue"
},
  "geometry": {"coordinates":[-117.988998,33.7043],"type":"Point"}
}