{
  "type": "Feature",
  "properties": {
    "iso:country":"US",
    "sg:address":"2605 Cam del Rio S",
    "sg:city":"San Diego",
    "sg:classifiers":[
        {
            "category":"Health Services",
            "subcategory":"Doctor",
            "type":"Services"
        }
    ],
    "sg:phone":"+1 619 291 7100",
    "sg:postcode":"92108",
    "sg:province":"CA",
    "sg:tags":[
        "physician",
        "surgeon"
    ],
    "wof:name":"Philip H Botkiss MD",
    "wof:placetype":"venue"
},
  "geometry": {"coordinates":[-117.137818,32.769349],"type":"Point"}
}