{
  "type": "Feature",
  "properties": {
    "addr:full":"207 N Main St Santa Ana CA 92701",
    "addr:housenumber":"207",
    "addr:postcode":"92701",
    "addr:street":"N Main St",
    "iso:country":"US",
    "sg:address":"207 N Main St",
    "sg:city":"Santa Ana",
    "sg:classifiers":[
        {
            "category":"Shopping",
            "type":"Retail Goods"
        }
    ],
    "sg:phone":"+1 714 973 2329",
    "sg:postcode":"92701",
    "sg:province":"CA",
    "sg:tags":[
        "art",
        "gallery",
        "dealer"
    ],
    "wof:name":"Diseno Art Gallery",
    "wof:placetype":"venue"
},
  "geometry": {"coordinates":[-117.86754500000001,33.747093],"type":"Point"}
}