{
  "type": "Feature",
  "properties": {
    "iso:country":"US",
    "sg:address":"9309 Avalon Blvd",
    "sg:city":"Los Angeles",
    "sg:classifiers":[
        {
            "category":"Personal",
            "subcategory":"Beauty Salon",
            "type":"Services"
        }
    ],
    "sg:phone":"+1 323 777 9219",
    "sg:postcode":"90003",
    "sg:province":"CA",
    "wof:name":"Hudson House Of Beauty",
    "wof:placetype":"venue"
},
  "geometry": {"coordinates":[-118.26522,33.95118],"type":"Point"}
}