{
  "type": "Feature",
  "properties": {
    "iso:country":"US",
    "sg:address":"655 W Main St",
    "sg:city":"Santa Paula",
    "sg:classifiers":[
        {
            "category":"Wholesale",
            "subcategory":"Fruits & Vegetables",
            "type":"Manufacturing & Wholesale Goods"
        }
    ],
    "sg:phone":"+1 805 525 4514",
    "sg:postcode":"93060",
    "sg:province":"CA",
    "sg:tags":[
        "shipper"
    ],
    "wof:name":"Calavo Growers Of California",
    "wof:placetype":"venue"
},
  "geometry": {"coordinates":[-119.084034,34.343906],"type":"Point"}
}