{
  "type": "Feature",
  "properties": {
    "iso:country":"US",
    "sg:address":"30 Hackamore Ln",
    "sg:city":"Bell Canyon",
    "sg:classifiers":[
        {
            "category":"Professional",
            "subcategory":"Management & Consulting",
            "type":"Services"
        }
    ],
    "sg:phone":"+1 818 884 3105",
    "sg:postcode":"91307",
    "sg:province":"CA",
    "sg:tags":[
        "engineer"
    ],
    "wof:name":"Norman Weinhouse Assoc",
    "wof:placetype":"venue"
},
  "geometry": {"coordinates":[-118.68141,34.207883],"type":"Point"}
}