{
  "type": "Feature",
  "properties": {
    "addr:full":"14837 Calvert St Van Nuys CA 91411",
    "addr:housenumber":"14837",
    "addr:postcode":"91411",
    "addr:street":"Calvert St",
    "iso:country":"US",
    "sg:address":"14837 Calvert St",
    "sg:city":"Van Nuys",
    "sg:classifiers":[
        {
            "category":"Manufacturing",
            "subcategory":"Signs",
            "type":"Manufacturing & Wholesale Goods"
        }
    ],
    "sg:phone":"+1 818 376 0688",
    "sg:postcode":"91411",
    "sg:province":"CA",
    "sg:tags":[
        "specialty",
        "mfg"
    ],
    "wof:name":"Hi-Tech Signs",
    "wof:placetype":"venue"
},
  "geometry": {"coordinates":[-118.45496300000001,34.18173],"type":"Point"}
}