{
  "type": "Feature",
  "properties": {
    "addr:full":"6844 Franklin Blvd Sacramento CA 95823",
    "addr:housenumber":"6844",
    "addr:postcode":"95823",
    "addr:street":"Franklin Blvd",
    "iso:country":"US",
    "sg:address":"6844 Franklin Blvd",
    "sg:city":"Sacramento",
    "sg:classifiers":[
        {
            "category":"Retail",
            "subcategory":"Veterinary Services",
            "type":"Services"
        },
        {
            "category":"Retail",
            "subcategory":"Pet Boarding",
            "type":"Services"
        }
    ],
    "sg:phone":"+1 916 428 6298",
    "sg:postcode":"95823",
    "sg:province":"CA",
    "sg:tags":[
        "veterinarian",
        "boarding/pet",
        "sitting"
    ],
    "sg:website":"www.southgatevet.vetsuite.com",
    "wof:name":"Southgate Veterinary Hospital",
    "wof:placetype":"venue"
},
  "geometry": {"coordinates":[-121.46348,38.502131],"type":"Point"}
}