{
  "type": "Feature",
  "properties": {
    "iso:country":"US",
    "sg:address":"3316 Bryan Ave",
    "sg:city":"Simi Valley",
    "sg:classifiers":[
        {
            "category":"Shopping",
            "subcategory":"Gifts & Souvenirs",
            "type":"Retail Goods"
        }
    ],
    "sg:phone":"+1 805 526 2554",
    "sg:postcode":"93063",
    "sg:province":"CA",
    "wof:name":"Kashka Products",
    "wof:placetype":"venue"
},
  "geometry": {"coordinates":[-118.697103,34.294355],"type":"Point"}
}