{
  "type": "Feature",
  "properties": {
    "iso:country":"US",
    "sg:address":"15910 Ventura Blvd",
    "sg:city":"Encino",
    "sg:classifiers":[
        {
            "category":"Banks & Credit Unions",
            "subcategory":"Bank",
            "type":"Services"
        }
    ],
    "sg:phone":"+1 818 981 9407",
    "sg:postcode":"91436",
    "sg:province":"CA",
    "sg:tags":[
        "mortgage",
        "loan",
        "broker",
        "real estate"
    ],
    "wof:name":"Pacific Premiere Inc",
    "wof:placetype":"venue"
},
  "geometry": {"coordinates":[-118.481263,34.155966],"type":"Point"}
}