{
  "type": "Feature",
  "properties": {
    "iso:country":"US",
    "sg:address":"1468 Davril Cir",
    "sg:city":"Corona",
    "sg:classifiers":[
        {
            "category":"Manufacturing",
            "subcategory":"Leather Goods",
            "type":"Manufacturing & Wholesale Goods"
        }
    ],
    "sg:phone":"+1 951 371 4922",
    "sg:postcode":"92880",
    "sg:province":"CA",
    "sg:tags":[
        "mfg",
        "specialty",
        "luggage"
    ],
    "wof:name":"Bates Display & Packaging",
    "wof:placetype":"venue"
},
  "geometry": {"coordinates":[-117.591057,33.892876],"type":"Point"}
}