{
  "type": "Feature",
  "properties": {
    "addr:full":"2051 Mountain Blvd Oakland CA 94611",
    "addr:housenumber":"2051",
    "addr:postcode":"94611",
    "addr:street":"Mountain Blvd",
    "iso:country":"US",
    "sg:address":"2051 Mountain Blvd",
    "sg:city":"Oakland",
    "sg:classifiers":[
        {
            "category":"Banks & Credit Unions",
            "subcategory":"Bank",
            "type":"Services"
        }
    ],
    "sg:phone":"+1 510 339 4352",
    "sg:postcode":"94611",
    "sg:province":"CA",
    "wof:name":"Chase",
    "wof:placetype":"venue"
},
  "geometry": {"coordinates":[-122.20953900000001,37.826476],"type":"Point"}
}