{
  "type": "Feature",
  "properties": {
    "iso:country":"US",
    "sg:address":"2541 State St",
    "sg:city":"Carlsbad",
    "sg:classifiers":[
        {
            "category":"Professional",
            "subcategory":"Secretarial Services",
            "type":"Services"
        }
    ],
    "sg:phone":"+1 760 434 3559",
    "sg:postcode":"92008",
    "sg:province":"CA",
    "sg:tags":[
        "convention",
        "reporting",
        "court",
        "reporter"
    ],
    "wof:name":"Norman Schall & Associates",
    "wof:placetype":"venue"
},
  "geometry": {"coordinates":[-117.354248,33.165757],"type":"Point"}
}