{
  "type": "Feature",
  "properties": {
    "iso:country":"US",
    "sg:address":"10836 Rau Rd",
    "sg:city":"Elk Grove",
    "sg:classifiers":[
        {
            "category":"Freight",
            "type":"Transportation"
        }
    ],
    "sg:phone":"+1 916 712 2302",
    "sg:postcode":"95757",
    "sg:province":"CA",
    "sg:tags":[
        "operator",
        "local",
        "trucking"
    ],
    "wof:name":"Gibbs Family Enterprises Inc",
    "wof:placetype":"venue"
},
  "geometry": {"coordinates":[-122.45062299999999,38.281559],"type":"Point"}
}