{
  "type": "Feature",
  "properties": {
    "addr:full":"1051 Oak Grove Rd Concord CA 94518",
    "addr:housenumber":"1051",
    "addr:postcode":"94518",
    "addr:street":"Oak Grove Rd",
    "iso:country":"US",
    "sg:address":"1051 Oak Grove Rd",
    "sg:city":"Concord",
    "sg:classifiers":[
        {
            "category":"Building & Trades",
            "subcategory":"Construction",
            "type":"Services"
        }
    ],
    "sg:phone":"+1 510 693 5116",
    "sg:postcode":"94518",
    "sg:province":"CA",
    "sg:tags":[
        "plastering",
        "contractor"
    ],
    "wof:name":"Patrick Griffin Plastering",
    "wof:placetype":"venue"
},
  "geometry": {"coordinates":[-122.03774,37.954019],"type":"Point"}
}