{
  "type": "Feature",
  "properties": {
    "iso:country":"US",
    "sg:address":"335 W Broadway Ste B",
    "sg:city":"Glendale",
    "sg:classifiers":[
        {
            "category":"Shopping",
            "subcategory":"Tobacco",
            "type":"Retail Goods"
        }
    ],
    "sg:phone":"+1 818 547 3771",
    "sg:postcode":"91204",
    "sg:province":"CA",
    "sg:tags":[
        "shop"
    ],
    "wof:name":"Planet Tobacco",
    "wof:placetype":"venue"
},
  "geometry": {"coordinates":[-118.259354,34.146976],"type":"Point"}
}