{
  "type": "Feature",
  "properties": {
    "iso:country":"US",
    "sg:address":"520 Oak Tree Ln",
    "sg:city":"Thousand Oaks",
    "sg:classifiers":[
        {
            "category":"Utilities",
            "subcategory":"Telephone",
            "type":"Services"
        }
    ],
    "sg:phone":"+1 805 497 6819",
    "sg:postcode":"91360",
    "sg:province":"CA",
    "sg:tags":[
        "telecommunication"
    ],
    "wof:name":"Hkesher Hisraeli",
    "wof:placetype":"venue"
},
  "geometry": {"coordinates":[-118.871112,34.18425],"type":"Point"}
}