{
  "type": "Feature",
  "properties": {
    "iso:country":"US",
    "sg:address":"133 E Park Ave",
    "sg:city":"El Cajon",
    "sg:classifiers":[
        {
            "category":"Social Services",
            "subcategory":"Child Care",
            "type":"Services"
        }
    ],
    "sg:phone":"+1 619 401 0318",
    "sg:postcode":"92020",
    "sg:province":"CA",
    "sg:tags":[
        "elementary",
        "school"
    ],
    "wof:name":"Dayspring Christian Learning Center",
    "wof:placetype":"venue"
},
  "geometry": {"coordinates":[-116.960999,32.7976],"type":"Point"}
}