{
  "type": "Feature",
  "properties": {
    "addr:full":"200 Portofino Way Redondo Beach CA 90277",
    "addr:housenumber":"200",
    "addr:postcode":"90277",
    "addr:street":"Portofino Way",
    "iso:country":"US",
    "sg:address":"200 Portofino Way",
    "sg:city":"Redondo Beach",
    "sg:classifiers":[
        {
            "category":"Government",
            "subcategory":"Office",
            "type":"Public Place"
        }
    ],
    "sg:phone":"+1 310 318 0681",
    "sg:postcode":"90277",
    "sg:province":"CA",
    "sg:tags":[
        "village"
    ],
    "sg:website":"www.redondo.org",
    "wof:name":"Seaside Lagoon",
    "wof:placetype":"venue"
},
  "geometry": {"coordinates":[-118.394154,33.845399],"type":"Point"}
}