{
  "type": "Feature",
  "properties": {
    "addr:full":"3675 Old Conejo Rd Newbury Park CA 91320",
    "addr:housenumber":"3675",
    "addr:postcode":"91320",
    "addr:street":"Old Conejo Rd",
    "iso:country":"US",
    "sg:address":"3675 Old Conejo Rd",
    "sg:city":"Newbury Park",
    "sg:classifiers":[
        {
            "category":"Building & Trades",
            "subcategory":"Construction",
            "type":"Services"
        }
    ],
    "sg:phone":"+1 805 498 2228",
    "sg:postcode":"91320",
    "sg:province":"CA",
    "sg:tags":[
        "general",
        "contractor"
    ],
    "wof:name":"Jath Construction Corp",
    "wof:placetype":"venue"
},
  "geometry": {"coordinates":[-118.957452,34.192892],"type":"Point"}
}