{
  "type": "Feature",
  "properties": {
    "iso:country":"US",
    "sg:address":"18075 Ventura Blvd",
    "sg:city":"Encino",
    "sg:classifiers":[
        {
            "category":"Professional",
            "subcategory":"Detective & Security Services",
            "type":"Services"
        }
    ],
    "sg:phone":"+1 818 881 3908",
    "sg:postcode":"91316",
    "sg:province":"CA",
    "sg:tags":[
        "investigator"
    ],
    "wof:name":"American Detective",
    "wof:placetype":"venue"
},
  "geometry": {"coordinates":[-118.52513,34.164801],"type":"Point"}
}