{
  "type": "Feature",
  "properties": {
    "addr:full":"7145 Arlington Ave Riverside CA 92503",
    "addr:housenumber":"7145",
    "addr:postcode":"92503",
    "addr:street":"Arlington Ave",
    "iso:country":"US",
    "sg:address":"7145 Arlington Ave",
    "sg:city":"Riverside",
    "sg:classifiers":[
        {
            "category":"Home & Garden",
            "subcategory":"Building Materials",
            "type":"Retail Goods"
        },
        {
            "category":"Manufacturing",
            "subcategory":"Lumber",
            "type":"Manufacturing & Wholesale Goods"
        }
    ],
    "sg:phone":"+1 951 343 3000",
    "sg:postcode":"92503",
    "sg:province":"CA",
    "sg:tags":[
        "lumber-wholesale",
        "lumber-used",
        "sawmill"
    ],
    "wof:name":"Boise Building Solutions",
    "wof:placetype":"venue"
},
  "geometry": {"coordinates":[-117.44961600000001,33.945889],"type":"Point"}
}