{
  "type": "Feature",
  "properties": {
    "addr:full":"3530 Atlantic Ave Ste 202 Long Beach CA 90807",
    "addr:housenumber":"3530",
    "addr:postcode":"90807",
    "addr:street":"Atlantic Ave Ste 202",
    "iso:country":"US",
    "sg:address":"3530 Atlantic Ave Ste 202",
    "sg:city":"Long Beach",
    "sg:classifiers":[
        {
            "category":"Sports & Exercise",
            "subcategory":"Sports Center",
            "type":"Entertainment"
        }
    ],
    "sg:phone":"+1 562 264 2900",
    "sg:postcode":"90807",
    "sg:province":"CA",
    "sg:tags":[
        "amateur",
        "team"
    ],
    "wof:name":"International Recreation",
    "wof:placetype":"venue"
},
  "geometry": {"coordinates":[-118.184853,33.820711],"type":"Point"}
}