{
  "type": "Feature",
  "properties": {
    "iso:country":"US",
    "sg:address":"745 Airport Blvd",
    "sg:city":"Salinas",
    "sg:classifiers":[
        {
            "category":"Freight",
            "type":"Transportation"
        }
    ],
    "sg:phone":"+1 831 784 1510",
    "sg:postcode":"93901",
    "sg:province":"CA",
    "sg:tags":[
        "operator",
        "local",
        "trucking"
    ],
    "wof:name":"Delivery Express Furniture",
    "wof:placetype":"venue"
},
  "geometry": {"coordinates":[-121.626471,36.658231],"type":"Point"}
}