{
  "type": "Feature",
  "properties": {
    "iso:country":"US",
    "sg:address":"550 S Hope St",
    "sg:city":"Los Angeles",
    "sg:classifiers":[
        {
            "category":"Banks & Credit Unions",
            "subcategory":"Investment Brokerage",
            "type":"Services"
        }
    ],
    "sg:phone":"+1 213 688 2100",
    "sg:postcode":"90071",
    "sg:province":"CA",
    "sg:tags":[
        "advisory",
        "financial"
    ],
    "wof:name":"Yaeger Capital Markets",
    "wof:placetype":"venue"
},
  "geometry": {"coordinates":[-118.256001,34.049759],"type":"Point"}
}