{
  "type": "Feature",
  "properties": {
    "iso:country":"US",
    "sg:address":"1034 Summit Ave",
    "sg:city":"Napa",
    "sg:classifiers":[
        {
            "category":"Building & Trades",
            "subcategory":"Pest Control",
            "type":"Services"
        }
    ],
    "sg:phone":"+1 707 224 8260",
    "sg:postcode":"94559",
    "sg:province":"CA",
    "wof:name":"Industrial Process Contrl Inc",
    "wof:placetype":"venue"
},
  "geometry": {"coordinates":[-122.27413900000001,38.308873],"type":"Point"}
}