{
  "type": "Feature",
  "properties": {
    "addr:full":"1507 20th St Santa Monica CA 90404",
    "addr:housenumber":"1507",
    "addr:postcode":"90404",
    "addr:street":"20Th St",
    "iso:country":"US",
    "sg:address":"1507 20th St",
    "sg:city":"Santa Monica",
    "sg:classifiers":[
        {
            "category":"Real Estate",
            "subcategory":"Architect",
            "type":"Services"
        }
    ],
    "sg:phone":"+1 310 453 9611",
    "sg:postcode":"90404",
    "sg:province":"CA",
    "wof:name":"Belzberg Architects",
    "wof:placetype":"venue"
},
  "geometry": {"coordinates":[-118.47689099999999,34.026146],"type":"Point"}
}