{
  "type": "Feature",
  "properties": {
    "addr:full":"21550 Oxnard St Ste 960 Woodland Hills CA 91367",
    "addr:housenumber":"21550",
    "addr:postcode":"91367",
    "addr:street":"Oxnard St Ste 960",
    "iso:country":"US",
    "sg:address":"21550 Oxnard St Ste 960",
    "sg:city":"Woodland Hills",
    "sg:classifiers":[
        {
            "category":"Banks & Credit Unions",
            "subcategory":"Investment Brokerage",
            "type":"Services"
        }
    ],
    "sg:phone":"+1 818 593 7907",
    "sg:postcode":"91367",
    "sg:province":"CA",
    "sg:tags":[
        "investing"
    ],
    "wof:name":"CenterPoint M & A Advisors",
    "wof:placetype":"venue"
},
  "geometry": {"coordinates":[-118.59945,34.179042],"type":"Point"}
}