{
  "type": "Feature",
  "properties": {
    "addr:full":"152 Mississippi St San Francisco CA 94107",
    "addr:housenumber":"152",
    "addr:postcode":"94107",
    "addr:street":"Mississippi St",
    "iso:country":"US",
    "sg:address":"152 Mississippi St",
    "sg:city":"San Francisco",
    "sg:classifiers":[
        {
            "category":"Professional",
            "subcategory":"Art Services",
            "type":"Services"
        }
    ],
    "sg:phone":"+1 415 252 1910",
    "sg:postcode":"94107",
    "sg:province":"CA",
    "sg:tags":[
        "photographer"
    ],
    "sg:website":"www.hunterfreeman.com",
    "wof:name":"Hunter Freeman Studio",
    "wof:placetype":"venue"
},
  "geometry": {"coordinates":[-122.394834,37.76464],"type":"Point"}
}