{
  "type": "Feature",
  "properties": {
    "addr:full":"8762 Amigo Ave Northridge CA 91324",
    "addr:housenumber":"8762",
    "addr:postcode":"91324",
    "addr:street":"Amigo Ave",
    "iso:country":"US",
    "sg:address":"8762 Amigo Ave",
    "sg:city":"Northridge",
    "sg:classifiers":[
        {
            "category":"Professional",
            "type":"Services"
        }
    ],
    "sg:phone":"+1 818 993 9030",
    "sg:postcode":"91324",
    "sg:province":"CA",
    "sg:tags":[
        "establishment"
    ],
    "wof:name":"Lupita Diaz Inc",
    "wof:placetype":"venue"
},
  "geometry": {"coordinates":[-118.538512,34.230214],"type":"Point"}
}