{
  "type": "Feature",
  "properties": {
    "addr:full":"4375 E Mesquite Ave Palm Springs CA 92264",
    "addr:housenumber":"4375",
    "addr:postcode":"92264",
    "addr:street":"E Mesquite Ave",
    "iso:country":"US",
    "sg:address":"4375 E Mesquite Ave",
    "sg:city":"Palm Springs",
    "sg:classifiers":[
        {
            "category":"Government",
            "subcategory":"Office",
            "type":"Public Place"
        }
    ],
    "sg:phone":"+1 760 323 8166",
    "sg:postcode":"92264",
    "sg:province":"CA",
    "sg:tags":[
        "village"
    ],
    "wof:name":"Palm Springs Wastewater Trtmnt",
    "wof:placetype":"venue"
},
  "geometry": {"coordinates":[-116.49884,33.808555],"type":"Point"}
}