{
  "type": "Feature",
  "properties": {
    "addr:full":"2007 W 6th Street Los Angeles CA 90057",
    "addr:housenumber":"2007",
    "addr:postcode":"90057",
    "addr:street":"W 6Th Street",
    "iso:country":"US",
    "sg:address":"2007 W 6th Street",
    "sg:city":"Los Angeles",
    "sg:classifiers":[
        {
            "category":"Restaurant",
            "type":"Food & Drink"
        }
    ],
    "sg:phone":"+1 213 484 9475",
    "sg:postcode":"90057",
    "sg:province":"CA",
    "wof:name":"Quetzaltenango Restaurant",
    "wof:placetype":"venue"
},
  "geometry": {"coordinates":[-118.274113,34.05907],"type":"Point"}
}