{
  "type": "Feature",
  "properties": {
    "addr:full":"101 W Cutting Blvd Richmond CA 94804",
    "addr:housenumber":"101",
    "addr:postcode":"94804",
    "addr:street":"W Cutting Blvd",
    "iso:country":"US",
    "sg:address":"101 W Cutting Blvd",
    "sg:city":"Richmond",
    "sg:classifiers":[
        {
            "category":"Freight",
            "type":"Transportation"
        }
    ],
    "sg:phone":"+1 510 235 4770",
    "sg:postcode":"94804",
    "sg:province":"CA",
    "sg:tags":[
        "general"
    ],
    "wof:name":"Storagepro",
    "wof:placetype":"venue"
},
  "geometry": {"coordinates":[-122.372096,37.925264],"type":"Point"}
}