{
  "type": "Feature",
  "properties": {
    "iso:country":"US",
    "sg:address":"1197 Willow Rd",
    "sg:city":"Menlo Park",
    "sg:classifiers":[
        {
            "category":"Government",
            "subcategory":"Police Station",
            "type":"Public Place"
        }
    ],
    "sg:phone":"+1 650 858 3328",
    "sg:postcode":"94025",
    "sg:province":"CA",
    "sg:tags":[
        "department"
    ],
    "wof:name":"Belle Haven Community Police",
    "wof:placetype":"venue"
},
  "geometry": {"coordinates":[-122.154692,37.47269],"type":"Point"}
}