{
  "type": "Feature",
  "properties": {
    "iso:country":"US",
    "sg:address":"10130 Mason Ave",
    "sg:city":"Chatsworth",
    "sg:classifiers":[
        {
            "category":"Shopping",
            "subcategory":"Gifts & Souvenirs",
            "type":"Retail Goods"
        }
    ],
    "sg:phone":"+1 818 882 7677",
    "sg:postcode":"91311",
    "sg:province":"CA",
    "sg:tags":[
        "shop"
    ],
    "sg:website":"www.tuesdaymorining.com",
    "wof:name":"Tuesday Morning Inc",
    "wof:placetype":"venue"
},
  "geometry": {"coordinates":[-118.579746,34.2567],"type":"Point"}
}