{
  "type": "Feature",
  "properties": {
    "iso:country":"US",
    "sg:address":"270 Barretta St",
    "sg:city":"Sonora",
    "sg:classifiers":[
        {
            "category":"Social Services",
            "type":"Services"
        }
    ],
    "sg:phone":"+1 209 536 1262",
    "sg:postcode":"95370",
    "sg:province":"CA",
    "sg:tags":[
        "counselor",
        "marriage",
        "family"
    ],
    "wof:name":"Christian Counseling Group",
    "wof:placetype":"venue"
},
  "geometry": {"coordinates":[-120.379976,37.981845],"type":"Point"}
}