{
  "type": "Feature",
  "properties": {
    "iso:country":"US",
    "sg:address":"401 Lombard St",
    "sg:city":"Oxnard",
    "sg:classifiers":[
        {
            "category":"Wholesale",
            "subcategory":"Farm Supplies",
            "type":"Manufacturing & Wholesale Goods"
        }
    ],
    "sg:phone":"+1 805 981 4554",
    "sg:postcode":"93030",
    "sg:province":"CA",
    "wof:name":"Santa Clara Seeds",
    "wof:placetype":"venue"
},
  "geometry": {"coordinates":[-119.148848,34.205103],"type":"Point"}
}