{
  "type": "Feature",
  "properties": {
    "iso:country":"US",
    "sg:address":"25876 The Old Rd",
    "sg:city":"Stevenson Ranch",
    "sg:classifiers":[
        {
            "category":"Wholesale",
            "subcategory":"Apparel",
            "type":"Manufacturing & Wholesale Goods"
        }
    ],
    "sg:phone":"+1 661 284 2313",
    "sg:postcode":"91381",
    "sg:province":"CA",
    "sg:tags":[
        "clothing"
    ],
    "wof:name":"Winners Trading Co",
    "wof:placetype":"venue"
},
  "geometry": {"coordinates":[-118.573382,34.390681],"type":"Point"}
}