{
  "type": "Feature",
  "properties": {
    "iso:country":"US",
    "sg:address":"5644 Van Buren Blvd",
    "sg:city":"Riverside",
    "sg:classifiers":[
        {
            "category":"Real Estate",
            "subcategory":"Real Estate Agent",
            "type":"Services"
        }
    ],
    "sg:phone":"+1 951 509 1707",
    "sg:postcode":"92503",
    "sg:province":"CA",
    "sg:tags":[
        "finding",
        "apartment",
        "rental"
    ],
    "wof:name":"G & A Property Management",
    "wof:placetype":"venue"
},
  "geometry": {"coordinates":[-117.45400600000001,33.940982],"type":"Point"}
}