{
  "type": "Feature",
  "properties": {
    "addr:full":"4949 Buckley Way Bakersfield CA 93309",
    "addr:housenumber":"4949",
    "addr:postcode":"93309",
    "addr:street":"Buckley Way",
    "iso:country":"US",
    "sg:address":"4949 Buckley Way",
    "sg:city":"Bakersfield",
    "sg:classifiers":[
        {
            "category":"Professional",
            "subcategory":"Advertising",
            "type":"Services"
        }
    ],
    "sg:phone":"+1 661 835 5812",
    "sg:postcode":"93309",
    "sg:province":"CA",
    "sg:tags":[
        "counselor"
    ],
    "wof:name":"Ace Communications",
    "wof:placetype":"venue"
},
  "geometry": {"coordinates":[-119.053516,35.337821],"type":"Point"}
}