{
  "type": "Feature",
  "properties": {
    "iso:country":"US",
    "sg:address":"7934 W 3rd Street",
    "sg:city":"Los Angeles",
    "sg:classifiers":[
        {
            "category":"Shopping",
            "subcategory":"Antiques",
            "type":"Retail Goods"
        },
        {
            "category":"Building & Trades",
            "subcategory":"Construction",
            "type":"Services"
        }
    ],
    "sg:phone":"+1 323 658 7008",
    "sg:postcode":"90048",
    "sg:province":"CA",
    "sg:tags":[
        "interior",
        "design"
    ],
    "wof:name":"Douglas Refinishing & Restorations",
    "wof:placetype":"venue"
},
  "geometry": {"coordinates":[-118.362651,34.071814],"type":"Point"}
}