{
  "type": "Feature",
  "properties": {
    "addr:full":"13109 Crossdale Ave Norwalk CA 90650",
    "addr:housenumber":"13109",
    "addr:postcode":"90650",
    "addr:street":"Crossdale Ave",
    "iso:country":"US",
    "sg:address":"13109 Crossdale Ave",
    "sg:city":"Norwalk",
    "sg:classifiers":[
        {
            "category":"Building & Trades",
            "subcategory":"Construction",
            "type":"Services"
        }
    ],
    "sg:phone":"+1 562 863 1713",
    "sg:postcode":"90650",
    "sg:province":"CA",
    "sg:tags":[
        "concrete",
        "cutting",
        "breaking",
        "sawing"
    ],
    "wof:name":"United Concrete Cutting",
    "wof:placetype":"venue"
},
  "geometry": {"coordinates":[-118.09751199999999,33.912399],"type":"Point"}
}