{
  "type": "Feature",
  "properties": {
    "addr:full":"5030 J St Sacramento CA 95819",
    "addr:housenumber":"5030",
    "addr:postcode":"95819",
    "addr:street":"J St",
    "iso:country":"US",
    "sg:address":"5030 J St",
    "sg:city":"Sacramento",
    "sg:classifiers":[
        {
            "category":"Health Services",
            "subcategory":"Doctor",
            "type":"Services"
        }
    ],
    "sg:phone":"+1 916 451 8001",
    "sg:postcode":"95819",
    "sg:province":"CA",
    "sg:tags":[
        "physician",
        "surgeon"
    ],
    "wof:name":"Susan Fritz-Zavacki MD",
    "wof:placetype":"venue"
},
  "geometry": {"coordinates":[-121.441917,38.566487],"type":"Point"}
}