{
  "type": "Feature",
  "properties": {
    "iso:country":"US",
    "sg:address":"3325 E Chapman Ave",
    "sg:city":"Orange",
    "sg:classifiers":[
        {
            "category":"Banks & Credit Unions",
            "subcategory":"Bank",
            "type":"Services"
        },
        {
            "category":"Banks & Credit Unions",
            "subcategory":"Financial Services",
            "type":"Services"
        }
    ],
    "sg:phone":"+1 714 997 7125",
    "sg:postcode":"92869",
    "sg:province":"CA",
    "sg:tags":[
        "commercial",
        "loan",
        "saving"
    ],
    "sg:website":"http://www.wellsfargo.com",
    "wof:name":"Wells Fargo Bank",
    "wof:placetype":"venue"
},
  "geometry": {"coordinates":[-117.818001,33.787899],"type":"Point"}
}