{
  "type": "Feature",
  "properties": {
    "iso:country":"US",
    "sg:address":"704 Newmark Mall",
    "sg:city":"Montebello",
    "sg:classifiers":[
        {
            "category":"Building & Trades",
            "subcategory":"Construction",
            "type":"Services"
        }
    ],
    "sg:phone":"+1 323 888 9715",
    "sg:postcode":"90640",
    "sg:province":"CA",
    "sg:tags":[
        "air",
        "heating",
        "conditioning/hvac"
    ],
    "sg:website":"www.fastacservice.com/",
    "wof:name":"Comfort Time Heating & Cooling",
    "wof:placetype":"venue"
},
  "geometry": {"coordinates":[-118.107037,34.010359],"type":"Point"}
}