{
  "type": "Feature",
  "properties": {
    "iso:country":"US",
    "sg:address":"3365 Somis Rd",
    "sg:city":"Somis",
    "sg:classifiers":[
        {
            "category":"Building & Trades",
            "subcategory":"Construction",
            "type":"Services"
        }
    ],
    "sg:phone":"+1 805 386 4000",
    "sg:postcode":"93066",
    "sg:province":"CA",
    "sg:tags":[
        "contractor"
    ],
    "sg:website":"www.forestconstruction.com",
    "wof:name":"Forest Construction Co",
    "wof:placetype":"venue"
},
  "geometry": {"coordinates":[-118.996002,34.256599],"type":"Point"}
}