{
  "type": "Feature",
  "properties": {
    "addr:full":"24457 Sunnymead Blvd Moreno Valley CA 92553",
    "addr:postcode":"24457;92553",
    "addr:street":"Sunnymead Blvd",
    "iso:country":"US",
    "sg:address":"24457 Sunnymead Blvd",
    "sg:city":"Moreno Valley",
    "sg:classifiers":[
        {
            "category":"Organizations",
            "subcategory":"Religious Organization",
            "type":"Services"
        }
    ],
    "sg:phone":"+1 951 243 3283",
    "sg:postcode":"92553",
    "sg:province":"CA",
    "sg:tags":[
        "church"
    ],
    "wof:name":"Life Enrichment Community",
    "wof:placetype":"venue"
},
  "geometry": {"coordinates":[-117.234866,33.939031],"type":"Point"}
}