{
  "type": "Feature",
  "properties": {
    "iso:country":"US",
    "sg:address":"12342 Old Pomerado Rd",
    "sg:city":"Poway",
    "sg:classifiers":[
        {
            "category":"Social Services",
            "type":"Services"
        },
        {
            "category":"Organizations",
            "subcategory":"Membership Organization",
            "type":"Services"
        }
    ],
    "sg:phone":"+1 858 748 7907",
    "sg:postcode":"92064",
    "sg:province":"CA",
    "sg:tags":[
        "military",
        "veteran"
    ],
    "sg:website":"http://www.vfw10454.com",
    "wof:name":"Vfw",
    "wof:placetype":"venue"
},
  "geometry": {"coordinates":[-117.064438,32.944555],"type":"Point"}
}