{
  "type": "Feature",
  "properties": {
    "addr:full":"5403 E Village Rd Long Beach CA 90808",
    "addr:housenumber":"5403",
    "addr:postcode":"90808",
    "addr:street":"E Village Rd",
    "iso:country":"US",
    "sg:address":"5403 E Village Rd",
    "sg:city":"Long Beach",
    "sg:classifiers":[
        {
            "category":"Personal",
            "subcategory":"Beauty Salon",
            "type":"Services"
        }
    ],
    "sg:phone":"+1 562 522 4013",
    "sg:postcode":"90808",
    "sg:province":"CA",
    "wof:name":"Marie Stock Hair Design",
    "wof:placetype":"venue"
},
  "geometry": {"coordinates":[-118.126096,33.833191],"type":"Point"}
}