{
  "type": "Feature",
  "properties": {
    "addr:full":"1100 Coiner Ct Rowland Heights CA 91748",
    "addr:housenumber":"1100",
    "addr:postcode":"91748",
    "addr:street":"Coiner Ct",
    "iso:country":"US",
    "sg:address":"1100 Coiner Ct",
    "sg:city":"Rowland Heights",
    "sg:classifiers":[
        {
            "category":"Manufacturing",
            "subcategory":"Printing",
            "type":"Manufacturing & Wholesale Goods"
        }
    ],
    "sg:phone":"+1 626 810 7769",
    "sg:postcode":"91748",
    "sg:province":"CA",
    "sg:tags":[
        "commercial"
    ],
    "wof:name":"Los Angeles Impac Center",
    "wof:placetype":"venue"
},
  "geometry": {"coordinates":[-117.895307,33.994879],"type":"Point"}
}