{
  "type": "Feature",
  "properties": {
    "iso:country":"US",
    "sg:address":"1002 S Claremont St",
    "sg:city":"San Mateo",
    "sg:classifiers":[
        {
            "category":"Retail",
            "subcategory":"Auto Repair",
            "type":"Services"
        }
    ],
    "sg:phone":"+1 650 525 1886",
    "sg:postcode":"94402",
    "sg:province":"CA",
    "sg:website":"www.sanmateoautoxperts.com",
    "wof:name":"San Mateo Auto Xperts",
    "wof:placetype":"venue"
},
  "geometry": {"coordinates":[-122.315061,37.561324],"type":"Point"}
}