{
  "type": "Feature",
  "properties": {
    "iso:country":"US",
    "sg:address":"209 Emerson Ave",
    "sg:city":"Modesto",
    "sg:classifiers":[
        {
            "category":"Professional",
            "subcategory":"Engineering",
            "type":"Services"
        }
    ],
    "sg:phone":"+1 209 238 9051",
    "sg:postcode":"95350",
    "sg:province":"CA",
    "sg:tags":[
        "engineer"
    ],
    "wof:name":"Hi Side Engineering",
    "wof:placetype":"venue"
},
  "geometry": {"coordinates":[-120.990361,37.680947],"type":"Point"}
}