{
  "type": "Feature",
  "properties": {
    "addr:full":"209 Emerson Ave Modesto CA 95350",
    "addr:housenumber":"209",
    "addr:postcode":"ca 95350",
    "addr:street":"Emerson Ave",
    "iso:country":"US",
    "sg:address":"209 Emerson Ave",
    "sg:city":"Modesto",
    "sg:classifiers":[
        {
            "category":"Professional",
            "subcategory":"Engineering",
            "type":"Services"
        }
    ],
    "sg:phone":"+1 209 238 9051",
    "sg:postcode":"95350",
    "sg:province":"CA",
    "sg:tags":[
        "engineer"
    ],
    "wof:name":"Hi Side Engineering",
    "wof:placetype":"venue"
},
  "geometry": {"coordinates":[-120.99036099999999,37.680947],"type":"Point"}
}