{
  "type": "Feature",
  "properties": {
    "iso:country":"US",
    "sg:address":"18880 Wells Dr",
    "sg:city":"Tarzana",
    "sg:classifiers":[
        {
            "category":"Professional",
            "type":"Services"
        }
    ],
    "sg:phone":"+1 818 705 3221",
    "sg:postcode":"91356",
    "sg:province":"CA",
    "sg:tags":[
        "establishment"
    ],
    "wof:name":"Mejia Blackwell Inc",
    "wof:placetype":"venue"
},
  "geometry": {"coordinates":[-118.54538,34.163202],"type":"Point"}
}