{
  "type": "Feature",
  "properties": {
    "addr:full":"2220 Fillmore St San Francisco CA 94115",
    "addr:housenumber":"2220",
    "addr:postcode":"94115",
    "addr:street":"Fillmore St",
    "iso:country":"US",
    "sg:address":"2220 Fillmore St",
    "sg:city":"San Francisco",
    "sg:classifiers":[
        {
            "category":"Shopping",
            "subcategory":"News",
            "type":"Retail Goods"
        }
    ],
    "sg:phone":"+1 415 929 5177",
    "sg:postcode":"94115",
    "sg:province":"CA",
    "sg:tags":[
        "magazine"
    ],
    "sg:website":"www.citysportsmag.com",
    "wof:name":"Competitor Publishing",
    "wof:placetype":"venue"
},
  "geometry": {"coordinates":[-122.434101,37.790544],"type":"Point"}
}