{
  "type": "Feature",
  "properties": {
    "iso:country":"US",
    "sg:address":"400 S Baldwin Ave",
    "sg:city":"Arcadia",
    "sg:classifiers":[
        {
            "category":"Shopping",
            "type":"Retail Goods"
        }
    ],
    "sg:phone":"+1 626 254 9271",
    "sg:postcode":"91007",
    "sg:province":"CA",
    "sg:tags":[
        "cosmetic",
        "perfume"
    ],
    "wof:name":"Real Outstanding Cosmetics",
    "wof:placetype":"venue"
},
  "geometry": {"coordinates":[-118.054255,34.134837],"type":"Point"}
}