{
  "type": "Feature",
  "properties": {
    "iso:country":"US",
    "sg:address":"12595 Crenshaw Boulevard",
    "sg:city":"Hawthorne",
    "sg:classifiers":[
        {
            "category":"Building & Trades",
            "subcategory":"Construction",
            "type":"Services"
        }
    ],
    "sg:phone":"+1 310 644 2560",
    "sg:postcode":"90250",
    "sg:province":"CA",
    "sg:tags":[
        "contractor"
    ],
    "wof:name":"Hmh Construction Group",
    "wof:placetype":"venue"
},
  "geometry": {"coordinates":[-118.326396,33.918214],"type":"Point"}
}