{
  "type": "Feature",
  "properties": {
    "addr:full":"1747 Sanchez St San Francisco CA 94131",
    "addr:housenumber":"1747",
    "addr:postcode":"94131",
    "addr:street":"Sanchez St",
    "iso:country":"US",
    "sg:address":"1747 Sanchez St",
    "sg:city":"San Francisco",
    "sg:classifiers":[
        {
            "category":"Health Services",
            "subcategory":"Clinic",
            "type":"Services"
        }
    ],
    "sg:phone":"+1 415 647 1980",
    "sg:postcode":"94131",
    "sg:province":"CA",
    "wof:name":"Heart of America Bone Marrow",
    "wof:placetype":"venue"
},
  "geometry": {"coordinates":[-122.428726,37.740987],"type":"Point"}
}