{
  "type": "Feature",
  "properties": {
    "iso:country":"US",
    "sg:address":"2426 Port St",
    "sg:city":"West Sacramento",
    "sg:classifiers":[
        {
            "category":"Wholesale",
            "subcategory":"Hardware",
            "type":"Manufacturing & Wholesale Goods"
        }
    ],
    "sg:phone":"+1 916 373 9912",
    "sg:postcode":"95691",
    "sg:province":"CA",
    "sg:tags":[
        "fastener"
    ],
    "sg:website":"www.constructionfasteners.com",
    "wof:name":"Sfs Intec",
    "wof:placetype":"venue"
},
  "geometry": {"coordinates":[-121.541636,38.572535],"type":"Point"}
}