{
  "type": "Feature",
  "properties": {
    "addr:full":"189 The Grove Drive Los Angeles CA 90036",
    "addr:housenumber":"189",
    "addr:postcode":"90036",
    "addr:street":"The Grove Drive",
    "iso:country":"US",
    "sg:address":"189 The Grove Drive",
    "sg:city":"Los Angeles",
    "sg:classifiers":[
        {
            "category":"Shopping",
            "subcategory":"Clothing, Apparel, & Fashions",
            "type":"Retail Goods"
        }
    ],
    "sg:phone":"+1 323 939 9072",
    "sg:postcode":"90036",
    "sg:province":"CA",
    "sg:tags":[
        "accessory",
        "clothing",
        "women's"
    ],
    "wof:name":"M Fredric Active",
    "wof:placetype":"venue"
},
  "geometry": {"coordinates":[-118.356317,34.070977],"type":"Point"}
}