{
  "type": "Feature",
  "properties": {
    "addr:full":"24410 Robertson Blvd Chowchilla CA 93610",
    "addr:housenumber":"24410",
    "addr:postcode":"93610",
    "addr:street":"Robertson Blvd",
    "iso:country":"US",
    "sg:address":"24410 Robertson Blvd",
    "sg:city":"Chowchilla",
    "sg:classifiers":[
        {
            "category":"Building & Trades",
            "subcategory":"Construction",
            "type":"Services"
        }
    ],
    "sg:phone":"+1 559 665 7696",
    "sg:postcode":"93610",
    "sg:province":"CA",
    "sg:tags":[
        "house"
    ],
    "wof:name":"Compean Construction & Pntg",
    "wof:placetype":"venue"
},
  "geometry": {"coordinates":[-120.280738,37.102688],"type":"Point"}
}