{
  "type": "Feature",
  "properties": {
    "addr:full":"1790 S Main St Willits CA 95490",
    "addr:housenumber":"1790",
    "addr:postcode":"95490",
    "addr:street":"S Main St",
    "iso:country":"US",
    "sg:address":"1790 S Main St",
    "sg:city":"Willits",
    "sg:classifiers":[
        {
            "category":"Retail",
            "subcategory":"Auto Repair",
            "type":"Services"
        }
    ],
    "sg:phone":"+1 707 459 4627",
    "sg:postcode":"95490",
    "sg:province":"CA",
    "sg:tags":[
        "repairing",
        "tire"
    ],
    "wof:name":"Glen's Commercial Tire",
    "wof:placetype":"venue"
},
  "geometry": {"coordinates":[-123.34566599999999,39.388042],"type":"Point"}
}