{
  "type": "Feature",
  "properties": {
    "addr:full":"742 Otay Lakes Rd Chula Vista CA 91910",
    "addr:housenumber":"742",
    "addr:postcode":"91910",
    "addr:street":"Otay Lakes Rd",
    "iso:country":"US",
    "sg:address":"742 Otay Lakes Rd",
    "sg:city":"Chula Vista",
    "sg:classifiers":[
        {
            "category":"Personal",
            "subcategory":"Skin Care",
            "type":"Services"
        }
    ],
    "sg:phone":"+1 619 218 4915",
    "sg:postcode":"91910",
    "sg:province":"CA",
    "sg:website":"www.nbskincare.com",
    "wof:name":"Skincare by Nicole Bronaugh",
    "wof:placetype":"venue"
},
  "geometry": {"coordinates":[-116.999545,32.644998],"type":"Point"}
}