{
  "type": "Feature",
  "properties": {
    "addr:full":"2458 E Marquise Ct Fresno CA 93720",
    "addr:housenumber":"2458",
    "addr:postcode":"93720",
    "addr:street":"E Marquise Ct",
    "iso:country":"US",
    "sg:address":"2458 E Marquise Ct",
    "sg:city":"Fresno",
    "sg:classifiers":[
        {
            "category":"Wholesale",
            "subcategory":"Apparel",
            "type":"Manufacturing & Wholesale Goods"
        }
    ],
    "sg:phone":"+1 559 240 3776",
    "sg:postcode":"93720",
    "sg:province":"CA",
    "sg:tags":[
        "clothing"
    ],
    "wof:name":"Ephraim Clothing Co",
    "wof:placetype":"venue"
},
  "geometry": {"coordinates":[-119.739521,36.860994],"type":"Point"}
}