{
  "type": "Feature",
  "properties": {
    "iso:country":"US",
    "sg:address":"23842 Boeing Ln",
    "sg:city":"Lake Forest",
    "sg:classifiers":[
        {
            "category":"Building & Trades",
            "subcategory":"Construction",
            "type":"Services"
        }
    ],
    "sg:phone":"+1 949 859 7178",
    "sg:postcode":"92630",
    "sg:province":"CA",
    "sg:tags":[
        "contractor"
    ],
    "sg:website":"www.martinmossgc.com",
    "wof:name":"Martin Moss General Contractor",
    "wof:placetype":"venue"
},
  "geometry": {"coordinates":[-117.71381,33.628499],"type":"Point"}
}