{
  "type": "Feature",
  "properties": {
    "iso:country":"US",
    "sg:address":"1600 Mangrove Ave",
    "sg:city":"Chico",
    "sg:classifiers":[
        {
            "category":"Home & Garden",
            "subcategory":"Home Furnishings",
            "type":"Retail Goods"
        }
    ],
    "sg:phone":"+1 530 893 8008",
    "sg:postcode":"95926",
    "sg:province":"CA",
    "sg:tags":[
        "lighting",
        "fixture"
    ],
    "wof:name":"Northern Lights & Accents",
    "wof:placetype":"venue"
},
  "geometry": {"coordinates":[-121.84162499999999,39.746499],"type":"Point"}
}