{
  "type": "Feature",
  "properties": {
    "iso:country":"US",
    "sg:address":"21 Crestwood Dr",
    "sg:city":"Daly City",
    "sg:classifiers":[
        {
            "category":"Taxi",
            "type":"Transportation"
        }
    ],
    "sg:phone":"+1 650 991 3084",
    "sg:postcode":"94015",
    "sg:province":"CA",
    "wof:name":"Daly City Cab",
    "wof:placetype":"venue"
},
  "geometry": {"coordinates":[-122.485726,37.700473],"type":"Point"}
}