{
  "type": "Feature",
  "properties": {
    "iso:country":"US",
    "sg:address":"6604 S Normandie Ave",
    "sg:city":"Los Angeles",
    "sg:classifiers":[
        {
            "category":"Organizations",
            "subcategory":"Religious Organization",
            "type":"Services"
        }
    ],
    "sg:phone":"+1 323 759 9103",
    "sg:postcode":"90044",
    "sg:province":"CA",
    "sg:tags":[
        "church"
    ],
    "wof:name":"Tabernacle Of The Son",
    "wof:placetype":"venue"
},
  "geometry": {"coordinates":[-118.300197,33.97853],"type":"Point"}
}