{
  "type": "Feature",
  "properties": {
    "addr:full":"20975 Woodside Way Groveland CA 95321",
    "addr:housenumber":"20975",
    "addr:postcode":"95321",
    "addr:street":"Woodside Way",
    "iso:country":"US",
    "sg:address":"20975 Woodside Way",
    "sg:city":"Groveland",
    "sg:classifiers":[
        {
            "category":"Utilities",
            "subcategory":"Telephone",
            "type":"Services"
        }
    ],
    "sg:phone":"+1 209 962 5900",
    "sg:postcode":"95321",
    "sg:province":"CA",
    "sg:tags":[
        "telecommunication"
    ],
    "sg:website":"www.amdevcomm.com",
    "wof:name":"AMDEV Communications Corp",
    "wof:placetype":"venue"
},
  "geometry": {"coordinates":[-120.181853,37.864193],"type":"Point"}
}