{
  "type": "Feature",
  "properties": {
    "iso:country":"US",
    "sg:address":"1932 Wildcat Canyon Rd",
    "sg:city":"Lakeside",
    "sg:classifiers":[
        {
            "category":"Restaurant",
            "type":"Food & Drink"
        }
    ],
    "sg:menulink":"http://www.allmenus.com/ca/san-diego/6686-rubios/menu/",
    "sg:phone":"+1 619 938 0272",
    "sg:postcode":"92040",
    "sg:province":"CA",
    "sg:tags":[
        "seafood",
        "mexican",
        "american"
    ],
    "wof:name":"Rubio's",
    "wof:placetype":"venue"
},
  "geometry": {"coordinates":[-116.843373,32.948057],"type":"Point"}
}