{
  "type": "Feature",
  "properties": {
    "addr:full":"3832 Pirate Dr Rancho Palos Verdes CA 90275",
    "addr:housenumber":"3832",
    "addr:postcode":"90275",
    "addr:street":"Pirate Dr",
    "iso:country":"US",
    "sg:address":"3832 Pirate Dr",
    "sg:city":"Rancho Palos Verdes",
    "sg:classifiers":[
        {
            "category":"Travel",
            "subcategory":"Travel Agent",
            "type":"Entertainment"
        }
    ],
    "sg:phone":"+1 310 377 5946",
    "sg:postcode":"90275",
    "sg:province":"CA",
    "sg:tags":[
        "agency"
    ],
    "wof:name":"Industrial Tours",
    "wof:placetype":"venue"
},
  "geometry": {"coordinates":[-118.345825,33.737269],"type":"Point"}
}