{
  "type": "Feature",
  "properties": {
    "iso:country":"US",
    "sg:address":"7841 Valley View St",
    "sg:city":"La Palma",
    "sg:classifiers":[
        {
            "category":"Insurance",
            "subcategory":"Hazard Insurance",
            "type":"Services"
        }
    ],
    "sg:phone":"+1 714 527 8897",
    "sg:postcode":"90623",
    "sg:province":"CA",
    "sg:website":"www.charlenehatakeyama.com",
    "wof:name":"Charlene Hatakeyama, State Farm Insurance",
    "wof:placetype":"venue"
},
  "geometry": {"coordinates":[-118.028479,33.848514],"type":"Point"}
}