{
  "type": "Feature",
  "properties": {
    "addr:full":"1245 Wilshire Boulevard Los Angeles CA 90017",
    "addr:housenumber":"1245",
    "addr:postcode":"90017",
    "addr:street":"Wilshire Boulevard",
    "iso:country":"US",
    "sg:address":"1245 Wilshire Boulevard",
    "sg:city":"Los Angeles",
    "sg:classifiers":[
        {
            "category":"Health Services",
            "subcategory":"Doctor",
            "type":"Services"
        }
    ],
    "sg:phone":"+1 213 481 2677",
    "sg:postcode":"90017",
    "sg:province":"CA",
    "wof:name":"Kriplani Anita MD",
    "wof:placetype":"venue"
},
  "geometry": {"coordinates":[-118.26565600000001,34.053367],"type":"Point"}
}