{
  "type": "Feature",
  "properties": {
    "iso:country":"US",
    "sg:address":"10027 Prospect Ave",
    "sg:city":"Santee",
    "sg:classifiers":[
        {
            "category":"Building & Trades",
            "subcategory":"Construction",
            "type":"Services"
        }
    ],
    "sg:phone":"+1 619 448 0123",
    "sg:postcode":"92071",
    "sg:province":"CA",
    "sg:tags":[
        "painter"
    ],
    "wof:name":"DAN Finishing",
    "wof:placetype":"venue"
},
  "geometry": {"coordinates":[-116.981449,32.831312],"type":"Point"}
}