{
  "type": "Feature",
  "properties": {
    "iso:country":"US",
    "sg:address":"7533 Ave 304",
    "sg:city":"Visalia",
    "sg:classifiers":[
        {
            "category":"Building & Trades",
            "subcategory":"Plumbing",
            "type":"Services"
        }
    ],
    "sg:phone":"+1 559 651 1776",
    "sg:postcode":"93291",
    "sg:province":"CA",
    "sg:tags":[
        "conditioning",
        "air",
        "system",
        "contractor"
    ],
    "wof:name":"American Air Co Inc",
    "wof:placetype":"venue"
},
  "geometry": {"coordinates":[-119.42026199999999,36.341595],"type":"Point"}
}