{
  "type": "Feature",
  "properties": {
    "addr:full":"25600 Chrisman Rd Tracy CA 95304",
    "addr:postcode":"25600;95304",
    "addr:street":"Chrisman Rd",
    "iso:country":"US",
    "sg:address":"25600 Chrisman Rd",
    "sg:city":"Tracy",
    "sg:classifiers":[
        {
            "category":"Airline",
            "type":"Transportation"
        }
    ],
    "sg:phone":"+1 209 830 9352",
    "sg:postcode":"95304",
    "sg:province":"CA",
    "sg:tags":[
        "cargo",
        "air"
    ],
    "wof:name":"Pilot Air Freight Corp",
    "wof:placetype":"venue"
},
  "geometry": {"coordinates":[-121.398055,37.719273],"type":"Point"}
}