{
  "type": "Feature",
  "properties": {
    "addr:full":"333 S Main St Red Bluff CA 96080",
    "addr:housenumber":"333",
    "addr:postcode":"96080",
    "addr:street":"S Main St",
    "iso:country":"US",
    "sg:address":"333 S Main St",
    "sg:city":"Red Bluff",
    "sg:classifiers":[
        {
            "category":"Retail",
            "subcategory":"Animal Services",
            "type":"Services"
        }
    ],
    "sg:phone":"+1 530 527 6759",
    "sg:postcode":"96080",
    "sg:province":"CA",
    "sg:tags":[
        "pet",
        "sales"
    ],
    "wof:name":"Town & Country Grooming & Sup",
    "wof:placetype":"venue"
},
  "geometry": {"coordinates":[-122.22828800000001,40.167404],"type":"Point"}
}