{
  "type": "Feature",
  "properties": {
    "addr:full":"23501 Park Sorrento Calabasas CA 91302",
    "addr:housenumber":"23501",
    "addr:postcode":"91302",
    "addr:street":"Park",
    "iso:country":"US",
    "sg:address":"23501 Park Sorrento",
    "sg:city":"Calabasas",
    "sg:classifiers":[
        {
            "category":"Manufacturing",
            "subcategory":"Printing",
            "type":"Manufacturing & Wholesale Goods"
        }
    ],
    "sg:phone":"+1 818 223 8188",
    "sg:postcode":"91302",
    "sg:province":"CA",
    "sg:tags":[
        "multimedia"
    ],
    "wof:name":"Motion Media",
    "wof:placetype":"venue"
},
  "geometry": {"coordinates":[-118.63977300000001,34.156013],"type":"Point"}
}