{
  "type": "Feature",
  "properties": {
    "addr:full":"701 Central Ave Menlo Park CA 94025",
    "addr:housenumber":"701",
    "addr:postcode":"94025",
    "addr:street":"Central Ave",
    "iso:country":"US",
    "sg:address":"701 Central Ave",
    "sg:city":"Menlo Park",
    "sg:classifiers":[
        {
            "category":"Building & Trades",
            "subcategory":"Cleaning & Sanitation",
            "type":"Services"
        }
    ],
    "sg:phone":"+1 650 322 0294",
    "sg:postcode":"94025",
    "sg:province":"CA",
    "sg:tags":[
        "janitor"
    ],
    "wof:name":"Jose's Janitor Svc",
    "wof:placetype":"venue"
},
  "geometry": {"coordinates":[-122.152614,37.464387],"type":"Point"}
}