{
  "type": "Feature",
  "properties": {
    "addr:full":"809 Center St Santa Cruz CA 95060",
    "addr:housenumber":"809",
    "addr:postcode":"95060",
    "addr:street":"Center St",
    "iso:country":"US",
    "sg:address":"809 Center St",
    "sg:city":"Santa Cruz",
    "sg:classifiers":[
        {
            "category":"Museum",
            "type":"Entertainment"
        }
    ],
    "sg:phone":"+1 831 420 6289",
    "sg:postcode":"95060",
    "sg:province":"CA",
    "sg:tags":[
        "landmark",
        "building",
        "historical"
    ],
    "sg:website":"www.santacruzsurfingmuseum.org/",
    "wof:name":"Surfing Museum Lighthouse Point",
    "wof:placetype":"venue"
},
  "geometry": {"coordinates":[-122.028999,36.974201],"type":"Point"}
}