{
  "type": "Feature",
  "properties": {
    "iso:country":"US",
    "sg:address":"1040 E Valley Pkwy",
    "sg:city":"Escondido",
    "sg:classifiers":[
        {
            "category":"Manufacturing",
            "subcategory":"Printing",
            "type":"Manufacturing & Wholesale Goods"
        }
    ],
    "sg:phone":"+1 760 489 6773",
    "sg:postcode":"92025",
    "sg:province":"CA",
    "sg:tags":[
        "lithographic",
        "commercial"
    ],
    "wof:name":"Print Shack",
    "wof:placetype":"venue"
},
  "geometry": {"coordinates":[-117.068988,33.12963],"type":"Point"}
}