{
  "type": "Feature",
  "properties": {
    "iso:country":"US",
    "sg:address":"200 S Pine Ave",
    "sg:city":"Long Beach",
    "sg:classifiers":[
        {
            "category":"Communications",
            "subcategory":"Film & Video Production",
            "type":"Services"
        }
    ],
    "sg:phone":"+1 562 901 3125",
    "sg:postcode":"90802",
    "sg:province":"CA",
    "sg:tags":[
        "audio"
    ],
    "sg:website":"www.ps-av.com",
    "wof:name":"Presentation Services",
    "wof:placetype":"venue"
},
  "geometry": {"coordinates":[-118.193091,33.762363],"type":"Point"}
}