{
  "type": "Feature",
  "properties": {
    "addr:full":"2295 Jefferson St Torrance CA 90501",
    "addr:housenumber":"2295",
    "addr:postcode":"90501",
    "addr:street":"Jefferson St",
    "iso:country":"US",
    "sg:address":"2295 Jefferson St",
    "sg:city":"Torrance",
    "sg:classifiers":[
        {
            "category":"Manufacturing",
            "subcategory":"Toys & Sporting Goods",
            "type":"Manufacturing & Wholesale Goods"
        }
    ],
    "sg:phone":"+1 310 212 5412",
    "sg:postcode":"90501",
    "sg:province":"CA",
    "wof:name":"Saitek Industries LTD",
    "wof:placetype":"venue"
},
  "geometry": {"coordinates":[-118.325035,33.827734],"type":"Point"}
}