{
  "type": "Feature",
  "properties": {
    "addr:full":"6200 Stoneridge Mall Rd Pleasanton CA 94588",
    "addr:housenumber":"6200",
    "addr:postcode":"94588",
    "addr:street":"Stoneridge Mall Rd",
    "iso:country":"US",
    "sg:address":"6200 Stoneridge Mall Rd",
    "sg:city":"Pleasanton",
    "sg:classifiers":[
        {
            "category":"Structure",
            "subcategory":"Office Building",
            "type":"Public Place"
        },
        {
            "category":"Farming",
            "subcategory":"Livestock Farm",
            "type":"Manufacturing & Wholesale Goods"
        }
    ],
    "sg:phone":"+1 925 399 6000",
    "sg:postcode":"94588",
    "sg:province":"CA",
    "sg:tags":[
        "suite",
        "desk",
        "executive",
        "rental",
        "space"
    ],
    "sg:website":"http://www.hq.com",
    "wof:name":"Regus Business Centre",
    "wof:placetype":"venue"
},
  "geometry": {"coordinates":[-121.92446099999999,37.69405],"type":"Point"}
}