{
  "type": "Feature",
  "properties": {
    "iso:country":"US",
    "sg:address":"3504 Coast View Dr",
    "sg:city":"Malibu",
    "sg:classifiers":[
        {
            "category":"Manufacturing",
            "subcategory":"Buildings",
            "type":"Manufacturing & Wholesale Goods"
        },
        {
            "category":"Building & Trades",
            "subcategory":"Construction",
            "type":"Services"
        }
    ],
    "sg:phone":"+1 310 456 2938",
    "sg:postcode":"90265",
    "sg:province":"CA",
    "sg:tags":[
        "home",
        "builder",
        "contractor"
    ],
    "wof:name":"Us Potter Homes",
    "wof:placetype":"venue"
},
  "geometry": {"coordinates":[-118.696671,34.039033],"type":"Point"}
}