{
  "type": "Feature",
  "properties": {
    "iso:country":"US",
    "sg:address":"17887 Gail Ct",
    "sg:city":"Salinas",
    "sg:classifiers":[
        {
            "category":"Autos & Motor Vehicles",
            "subcategory":"Auto Supplies",
            "type":"Retail Goods"
        }
    ],
    "sg:phone":"+1 831 663 1835",
    "sg:postcode":"93907",
    "sg:province":"CA",
    "sg:tags":[
        "part",
        "trailer",
        "hitch"
    ],
    "wof:name":"Western Trailer",
    "wof:placetype":"venue"
},
  "geometry": {"coordinates":[-121.659982,36.795568],"type":"Point"}
}