{
  "type": "Feature",
  "properties": {
    "iso:country":"US",
    "sg:address":"133 E Commonwealth",
    "sg:city":"Fullerton",
    "sg:classifiers":[
        {
            "category":"Personal",
            "subcategory":"Tattoo Parlor",
            "type":"Services"
        }
    ],
    "sg:phone":"+1 626 692 2774",
    "sg:postcode":"92832",
    "sg:province":"CA",
    "wof:name":"The Forbidden Chamber",
    "wof:placetype":"venue"
},
  "geometry": {"coordinates":[-117.922684,33.870394],"type":"Point"}
}