{
  "type": "Feature",
  "properties": {
    "iso:country":"US",
    "sg:address":"21615 Hesperian Blvd",
    "sg:city":"Hayward",
    "sg:classifiers":[
        {
            "category":"Arena",
            "subcategory":"Sports Club",
            "type":"Entertainment"
        }
    ],
    "sg:phone":"+1 650 218 7601",
    "sg:postcode":"94541",
    "sg:province":"CA",
    "sg:tags":[
        "martial art"
    ],
    "sg:website":"www.capoeira.bz/hayward/",
    "wof:name":"United Capoeira Association - Hayward",
    "wof:placetype":"venue"
},
  "geometry": {"coordinates":[-122.115831,37.660626],"type":"Point"}
}