{
  "type": "Feature",
  "properties": {
    "addr:full":"729 D St Ramona CA 92065",
    "addr:housenumber":"729",
    "addr:postcode":"92065",
    "addr:street":"D St",
    "iso:country":"US",
    "sg:address":"729 D St",
    "sg:city":"Ramona",
    "sg:classifiers":[
        {
            "category":"Retail",
            "subcategory":"Auto Repair",
            "type":"Services"
        }
    ],
    "sg:phone":"+1 760 789 6177",
    "sg:postcode":"92065",
    "sg:province":"CA",
    "sg:tags":[
        "repairing",
        "automobile"
    ],
    "wof:name":"Danny's Truck & Auto",
    "wof:placetype":"venue"
},
  "geometry": {"coordinates":[-116.864322,33.043168],"type":"Point"}
}