{
  "type": "Feature",
  "properties": {
    "iso:country":"US",
    "sg:address":"150 Nut Tree Pkwy",
    "sg:city":"Vacaville",
    "sg:classifiers":[
        {
            "category":"Restaurant",
            "type":"Food & Drink"
        }
    ],
    "sg:menulink":"http://www.allmenus.com/ca/vacaville/151911-baja-fresh-mexican-grill/menu/",
    "sg:phone":"+1 707 446 6736",
    "sg:postcode":"95687",
    "sg:province":"CA",
    "sg:tags":[
        "mexican"
    ],
    "wof:name":"Baja Fresh Mexican Grill",
    "wof:placetype":"venue"
},
  "geometry": {"coordinates":[-121.96011799999999,38.366442],"type":"Point"}
}