{
  "type": "Feature",
  "properties": {
    "addr:full":"27995 Greenfield Drive Laguna Niguel CA 92677",
    "addr:housenumber":"27995",
    "addr:postcode":"92677",
    "addr:street":"Greenfield Drive",
    "iso:country":"US",
    "sg:address":"27995 Greenfield Drive",
    "sg:city":"Laguna Niguel",
    "sg:classifiers":[
        {
            "category":"Health Services",
            "subcategory":"Doctor",
            "type":"Services"
        }
    ],
    "sg:phone":"+1 949 360 4400",
    "sg:postcode":"92677",
    "sg:province":"CA",
    "sg:tags":[
        "dermatologist"
    ],
    "sg:website":"www.wonderfulskin.com",
    "wof:name":"Kramer Edward MD",
    "wof:placetype":"venue"
},
  "geometry": {"coordinates":[-117.685345,33.553759],"type":"Point"}
}