{
  "type": "Feature",
  "properties": {
    "iso:country":"US",
    "sg:address":"1240 Central Blvd",
    "sg:city":"Brentwood",
    "sg:classifiers":[
        {
            "category":"Professional",
            "subcategory":"Accounting & Tax Preparation",
            "type":"Services"
        }
    ],
    "sg:phone":"+1 925 240 2400",
    "sg:postcode":"94513",
    "sg:province":"CA",
    "sg:tags":[
        "payroll"
    ],
    "sg:website":"www.promerio.com",
    "wof:name":"California Payroll",
    "wof:placetype":"venue"
},
  "geometry": {"coordinates":[-121.703299,37.935513],"type":"Point"}
}