{
  "type": "Feature",
  "properties": {
    "iso:country":"US",
    "sg:address":"1639 Peacock Blvd",
    "sg:city":"Oceanside",
    "sg:classifiers":[
        {
            "category":"Banks & Credit Unions",
            "subcategory":"Financial Services",
            "type":"Services"
        }
    ],
    "sg:phone":"+1 760 726 9745",
    "sg:postcode":"92056",
    "sg:province":"CA",
    "sg:tags":[
        "trust",
        "management"
    ],
    "wof:name":"Pfiffner Family Trust",
    "wof:placetype":"venue"
},
  "geometry": {"coordinates":[-117.274793,33.217068],"type":"Point"}
}