{
  "type": "Feature",
  "properties": {
    "iso:country":"US",
    "sg:address":"378 Santana Row Apt 301",
    "sg:city":"San Jose",
    "sg:classifiers":[
        {
            "category":"Shopping",
            "subcategory":"Clothing, Apparel, & Fashions",
            "type":"Retail Goods"
        },
        {
            "category":"Shopping",
            "subcategory":"Optician",
            "type":"Retail Goods"
        }
    ],
    "sg:phone":"+1 408 261 9010",
    "sg:postcode":"95128",
    "sg:province":"CA",
    "sg:tags":[
        "men's",
        "clothing",
        "eyewear",
        "women's"
    ],
    "sg:website":"www.oakley.com",
    "wof:name":"Oakley O Store",
    "wof:placetype":"venue"
},
  "geometry": {"coordinates":[-121.947714,37.319973],"type":"Point"}
}