{
  "type": "Feature",
  "properties": {
    "iso:country":"US",
    "sg:address":"807 Montgomery St",
    "sg:city":"San Francisco",
    "sg:classifiers":[
        {
            "category":"Health Services",
            "subcategory":"Doctor",
            "type":"Services"
        },
        {
            "category":"Health Services",
            "subcategory":"Chiropractor",
            "type":"Services"
        }
    ],
    "sg:phone":"+1 415 986 3271",
    "sg:postcode":"94133",
    "sg:province":"CA",
    "sg:tags":[
        "medicine",
        "sport"
    ],
    "wof:name":"Graham Ross William MD DC",
    "wof:placetype":"venue"
},
  "geometry": {"coordinates":[-122.403719,37.796698],"type":"Point"}
}