{
  "type": "Feature",
  "properties": {
    "addr:full":"545 W Las Tunas Dr San Gabriel CA 91776",
    "addr:housenumber":"545",
    "addr:postcode":"91776",
    "addr:street":"W Las Tunas Dr",
    "iso:country":"US",
    "sg:address":"545 W Las Tunas Dr",
    "sg:city":"San Gabriel",
    "sg:classifiers":[
        {
            "category":"Restaurant",
            "type":"Food & Drink"
        }
    ],
    "sg:phone":"+1 626 308 1896",
    "sg:postcode":"91776",
    "sg:province":"CA",
    "sg:tags":[
        "chinese"
    ],
    "wof:name":"Yunnan Garden",
    "wof:placetype":"venue"
},
  "geometry": {"coordinates":[-118.108013,34.102811],"type":"Point"}
}