{
  "type": "Feature",
  "properties": {
    "iso:country":"US",
    "sg:address":"1234 E Main St",
    "sg:city":"Ventura",
    "sg:classifiers":[
        {
            "category":"Shopping",
            "subcategory":"Used Merchandise",
            "type":"Retail Goods"
        }
    ],
    "sg:phone":"+1 805 648 7225",
    "sg:postcode":"93001",
    "sg:province":"CA",
    "sg:tags":[
        "antique"
    ],
    "wof:name":"Attention To Detail",
    "wof:placetype":"venue"
},
  "geometry": {"coordinates":[-119.281976,34.280776],"type":"Point"}
}