{
  "type": "Feature",
  "properties": {
    "addr:full":"361 Cahuenga Dr Oxnard CA 93035",
    "addr:housenumber":"361",
    "addr:postcode":"93035",
    "addr:street":"Cahuenga Dr",
    "iso:country":"US",
    "sg:address":"361 Cahuenga Dr",
    "sg:city":"Oxnard",
    "sg:classifiers":[
        {
            "category":"Wholesale",
            "subcategory":"Hardware",
            "type":"Manufacturing & Wholesale Goods"
        }
    ],
    "sg:phone":"+1 805 984 6826",
    "sg:postcode":"93035",
    "sg:province":"CA",
    "sg:tags":[
        "hardware-wholesale",
        "manufacturer"
    ],
    "wof:name":"Bradley Construction",
    "wof:placetype":"venue"
},
  "geometry": {"coordinates":[-119.21704800000001,34.15765],"type":"Point"}
}