{
  "type": "Feature",
  "properties": {
    "iso:country":"US",
    "sg:address":"341 Tres Pinos Rd",
    "sg:city":"Hollister",
    "sg:classifiers":[
        {
            "category":"Real Estate",
            "subcategory":"Real Estate Agent",
            "type":"Services"
        }
    ],
    "sg:phone":"+1 831 638 1855",
    "sg:postcode":"95023",
    "sg:province":"CA",
    "wof:name":"Karey Grimsley",
    "wof:placetype":"venue"
},
  "geometry": {"coordinates":[-121.39648200000001,36.839402],"type":"Point"}
}