{
  "type": "Feature",
  "properties": {
    "addr:full":"9405 Flower St Bellflower CA 90706",
    "addr:housenumber":"9405",
    "addr:postcode":"90706",
    "addr:street":"Flower St",
    "iso:country":"US",
    "sg:address":"9405 Flower St",
    "sg:city":"Bellflower",
    "sg:classifiers":[
        {
            "category":"Organizations",
            "subcategory":"Religious Organization",
            "type":"Services"
        }
    ],
    "sg:phone":"+1 562 925 6561",
    "sg:postcode":"90706",
    "sg:province":"CA",
    "sg:tags":[
        "church"
    ],
    "wof:name":"Bellflower Brethren Church",
    "wof:placetype":"venue"
},
  "geometry": {"coordinates":[-118.132592,33.882143],"type":"Point"}
}