{
  "type": "Feature",
  "properties": {
    "iso:country":"US",
    "sg:address":"3865 Almond Ave",
    "sg:city":"Fremont",
    "sg:classifiers":[
        {
            "category":"Travel",
            "subcategory":"Travel Agent",
            "type":"Entertainment"
        }
    ],
    "sg:phone":"+1 510 657 1472",
    "sg:postcode":"94538",
    "sg:province":"CA",
    "sg:tags":[
        "agency"
    ],
    "wof:name":"Wings Travel & Tradelinks",
    "wof:placetype":"venue"
},
  "geometry": {"coordinates":[-121.958601,37.534966],"type":"Point"}
}