{
  "type": "Feature",
  "properties": {
    "iso:country":"US",
    "sg:address":"5765 Christie Ave",
    "sg:city":"Emeryville",
    "sg:classifiers":[
        {
            "category":"Personal",
            "subcategory":"Beauty Salon",
            "type":"Services"
        }
    ],
    "sg:phone":"+1 510 547 8977",
    "sg:postcode":"94608",
    "sg:province":"CA",
    "wof:name":"Kim Tiajuana",
    "wof:placetype":"venue"
},
  "geometry": {"coordinates":[-122.29451899999999,37.837782],"type":"Point"}
}