{
  "type": "Feature",
  "properties": {
    "addr:full":"1444 Burlingame Ave Burlingame CA 94010",
    "addr:housenumber":"1444",
    "addr:postcode":"94010",
    "addr:street":"Burlingame Ave",
    "iso:country":"US",
    "sg:address":"1444 Burlingame Ave",
    "sg:city":"Burlingame",
    "sg:classifiers":[
        {
            "category":"Home & Garden",
            "subcategory":"Furniture",
            "type":"Retail Goods"
        }
    ],
    "sg:phone":"+1 650 343 4400",
    "sg:postcode":"94010",
    "sg:province":"CA",
    "sg:tags":[
        "store"
    ],
    "sg:website":"www.havenburlingame.com",
    "wof:name":"Haven",
    "wof:placetype":"venue"
},
  "geometry": {"coordinates":[-122.34906599999999,37.577199],"type":"Point"}
}