{
  "type": "Feature",
  "properties": {
    "iso:country":"US",
    "sg:address":"4441 Auburn Blvd Ste E",
    "sg:city":"Sacramento",
    "sg:classifiers":[
        {
            "category":"Health Services",
            "subcategory":"Doctor",
            "type":"Services"
        },
        {
            "category":"Health Services",
            "subcategory":"Clinic",
            "type":"Services"
        },
        {
            "category":"Health Services",
            "subcategory":"Health Practitioner",
            "type":"Services"
        }
    ],
    "sg:phone":"+1 916 473 5764",
    "sg:postcode":"95841",
    "sg:province":"CA",
    "sg:tags":[
        "physician",
        "information",
        "surgeons",
        "drug",
        "abuse",
        "treatment",
        "medicine",
        "addiction",
        "alcoholism"
    ],
    "sg:website":"http://www.strategies4change.org",
    "wof:name":"Strategies For Change",
    "wof:placetype":"venue"
},
  "geometry": {"coordinates":[-121.36075200000001,38.64756],"type":"Point"}
}