{
  "type": "Feature",
  "properties": {
    "iso:country":"US",
    "sg:address":"11942 Paramount Blvd # 1",
    "sg:city":"Downey",
    "sg:classifiers":[
        {
            "category":"Health Services",
            "subcategory":"Doctor",
            "type":"Services"
        }
    ],
    "sg:phone":"+1 562 862 8128",
    "sg:postcode":"90242",
    "sg:province":"CA",
    "sg:tags":[
        "surgeon",
        "oral"
    ],
    "wof:name":"Hassanabadi Behzad DDS",
    "wof:placetype":"venue"
},
  "geometry": {"coordinates":[-118.144997,33.9338],"type":"Point"}
}