{
  "type": "Feature",
  "properties": {
    "addr:full":"1401 el Camino Ave Sacramento CA 95815",
    "addr:housenumber":"1401",
    "addr:postcode":"95815",
    "addr:street":"El Camino Ave",
    "iso:country":"US",
    "sg:address":"1401 el Camino Ave",
    "sg:city":"Sacramento",
    "sg:classifiers":[
        {
            "category":"Professional",
            "subcategory":"Management & Consulting",
            "type":"Services"
        }
    ],
    "sg:phone":"+1 916 925 7788",
    "sg:postcode":"95815",
    "sg:province":"CA",
    "sg:tags":[
        "food"
    ],
    "wof:name":"Kitchen Food Svc Management Co",
    "wof:placetype":"venue"
},
  "geometry": {"coordinates":[-121.43377,38.610917],"type":"Point"}
}