{
  "type": "Feature",
  "properties": {
    "iso:country":"US",
    "sg:address":"17853 Santiago Blvd",
    "sg:city":"Villa Park",
    "sg:classifiers":[
        {
            "category":"Restaurant",
            "type":"Food & Drink"
        },
        {
            "category":"Bakery",
            "type":"Food & Drink"
        }
    ],
    "sg:phone":"+1 714 921 0622",
    "sg:postcode":"92861",
    "sg:province":"CA",
    "sg:tags":[
        "traditional",
        "american"
    ],
    "sg:website":"www.rockwellsbakery.com",
    "wof:name":"Rockwell's Cafe & Bakery",
    "wof:placetype":"venue"
},
  "geometry": {"coordinates":[-117.81999999999999,33.814098],"type":"Point"}
}