{
  "type": "Feature",
  "properties": {
    "iso:country":"US",
    "sg:address":"5125 E Fairfield St",
    "sg:city":"Anaheim",
    "sg:classifiers":[
        {
            "category":"Travel",
            "subcategory":"Travel Agent",
            "type":"Entertainment"
        }
    ],
    "sg:phone":"+1 714 288 1286",
    "sg:postcode":"92807",
    "sg:province":"CA",
    "sg:tags":[
        "agency",
        "bureau"
    ],
    "wof:name":"Lucky Travel & Tours Inc",
    "wof:placetype":"venue"
},
  "geometry": {"coordinates":[-117.808949,33.839257],"type":"Point"}
}