{
  "type": "Feature",
  "properties": {
    "iso:country":"US",
    "sg:address":"3907 Waring Rd Ste 1",
    "sg:city":"Oceanside",
    "sg:classifiers":[
        {
            "category":"Health Services",
            "subcategory":"Clinic",
            "type":"Services"
        }
    ],
    "sg:phone":"+1 760 758 6009",
    "sg:postcode":"92056",
    "sg:province":"CA",
    "sg:tags":[
        "medical"
    ],
    "wof:name":"Tubbs Sean MA",
    "wof:placetype":"venue"
},
  "geometry": {"coordinates":[-117.291876,33.187088],"type":"Point"}
}