{
  "type": "Feature",
  "properties": {
    "addr:full":"2225 W Shaw Ave Fresno CA 93711",
    "addr:housenumber":"2225",
    "addr:postcode":"93711",
    "addr:street":"W Shaw Ave",
    "iso:country":"US",
    "sg:address":"2225 W Shaw Ave",
    "sg:city":"Fresno",
    "sg:classifiers":[
        {
            "category":"Personal",
            "subcategory":"Beauty Salon",
            "type":"Services"
        }
    ],
    "sg:phone":"+1 559 435 1188",
    "sg:postcode":"93711",
    "sg:province":"CA",
    "wof:name":"Nails By Gina",
    "wof:placetype":"venue"
},
  "geometry": {"coordinates":[-119.831722,36.808173],"type":"Point"}
}