{
  "type": "Feature",
  "properties": {
    "addr:full":"1141 Laurel St Napa CA 94559",
    "addr:housenumber":"1141",
    "addr:postcode":"94559",
    "addr:street":"Laurel St",
    "iso:country":"US",
    "sg:address":"1141 Laurel St",
    "sg:city":"Napa",
    "sg:classifiers":[
        {
            "category":"Retail",
            "subcategory":"Repair Shop",
            "type":"Services"
        }
    ],
    "sg:phone":"+1 707 224 1245",
    "sg:postcode":"94559",
    "sg:province":"CA",
    "sg:tags":[
        "repairing",
        "piano",
        "refinishing"
    ],
    "wof:name":"Weisman Brooks",
    "wof:placetype":"venue"
},
  "geometry": {"coordinates":[-122.28504700000001,38.291814],"type":"Point"}
}