{
  "type": "Feature",
  "properties": {
    "addr:full":"4722 Admiralty Way Marina Del Rey CA 90292",
    "addr:housenumber":"4722",
    "addr:postcode":"90292",
    "addr:street":"Admiralty Way",
    "iso:country":"US",
    "sg:address":"4722 Admiralty Way",
    "sg:city":"Marina Del Rey",
    "sg:classifiers":[
        {
            "category":"Retail",
            "subcategory":"Animal Services",
            "type":"Services"
        }
    ],
    "sg:phone":"+1 310 301 4554",
    "sg:postcode":"90292",
    "sg:province":"CA",
    "wof:name":"Marina Dog Grooming",
    "wof:placetype":"venue"
},
  "geometry": {"coordinates":[-118.438581,33.977832],"type":"Point"}
}