{
  "type": "Feature",
  "properties": {
    "addr:full":"2000 Novato Blvd Novato CA 94947",
    "addr:housenumber":"2000",
    "addr:postcode":"94947",
    "addr:street":"Novato Blvd",
    "iso:country":"US",
    "sg:address":"2000 Novato Blvd",
    "sg:city":"Novato",
    "sg:classifiers":[
        {
            "category":"Home & Garden",
            "subcategory":"Garden Supply",
            "type":"Retail Goods"
        }
    ],
    "sg:phone":"+1 415 897 2169",
    "sg:postcode":"94947",
    "sg:province":"CA",
    "sg:tags":[
        "nurseryman"
    ],
    "sg:website":"www.sloatgardens.com",
    "wof:name":"Sloat Garden Ctr",
    "wof:placetype":"venue"
},
  "geometry": {"coordinates":[-122.591359,38.111878],"type":"Point"}
}