{
  "type": "Feature",
  "properties": {
    "addr:full":"1745 E Alisal St Salinas CA 93905",
    "addr:housenumber":"1745",
    "addr:postcode":"93905",
    "addr:street":"E Alisal St",
    "iso:country":"US",
    "sg:address":"1745 E Alisal St",
    "sg:city":"Salinas",
    "sg:classifiers":[
        {
            "category":"Professional",
            "type":"Services"
        }
    ],
    "sg:phone":"+1 831 751 9887",
    "sg:postcode":"93905",
    "sg:province":"CA",
    "wof:name":"Fidel Diaz",
    "wof:placetype":"venue"
},
  "geometry": {"coordinates":[-121.604755,36.673247],"type":"Point"}
}