{
  "type": "Feature",
  "properties": {
    "iso:country":"US",
    "sg:address":"1201 Truman St",
    "sg:city":"San Fernando",
    "sg:classifiers":[
        {
            "category":"Health Services",
            "subcategory":"Health Practitioner",
            "type":"Services"
        }
    ],
    "sg:phone":"+1 818 837 6810",
    "sg:postcode":"91340",
    "sg:province":"CA",
    "sg:tags":[
        "medicine",
        "alternative"
    ],
    "wof:name":"Migun San Fernando Valley",
    "wof:placetype":"venue"
},
  "geometry": {"coordinates":[-118.444945,34.286848],"type":"Point"}
}