{
  "type": "Feature",
  "properties": {
    "addr:full":"1012 Santee St Los Angeles CA 90015",
    "addr:housenumber":"1012",
    "addr:postcode":"90015",
    "addr:street":"Santee St",
    "iso:country":"US",
    "sg:address":"1012 Santee St",
    "sg:city":"Los Angeles",
    "sg:classifiers":[
        {
            "category":"Shopping",
            "subcategory":"Shoes",
            "type":"Retail Goods"
        }
    ],
    "sg:phone":"+1 213 749 1909",
    "sg:postcode":"90015",
    "sg:province":"CA",
    "wof:name":"Rebeca's Shoes",
    "wof:placetype":"venue"
},
  "geometry": {"coordinates":[-118.25596,34.037892],"type":"Point"}
}