{
  "type": "Feature",
  "properties": {
    "addr:full":"630 E Alvarado St Fallbrook CA 92028",
    "addr:housenumber":"630",
    "addr:postcode":"92028",
    "addr:street":"E Alvarado St",
    "iso:country":"US",
    "sg:address":"630 E Alvarado St",
    "sg:city":"Fallbrook",
    "sg:classifiers":[
        {
            "category":"Autos & Motor Vehicles",
            "subcategory":"Auto Supplies",
            "type":"Retail Goods"
        },
        {
            "category":"Retail",
            "subcategory":"Auto Repair",
            "type":"Services"
        }
    ],
    "sg:phone":"+1 760 728 6835",
    "sg:postcode":"92028",
    "sg:province":"CA",
    "sg:tags":[
        "tire"
    ],
    "sg:website":"www.westcoasttruckandauto.com",
    "wof:name":"West Coast Truck & Auto",
    "wof:placetype":"venue"
},
  "geometry": {"coordinates":[-117.245003,33.381901],"type":"Point"}
}