{
  "type": "Feature",
  "properties": {
    "addr:full":"9461 Heathman Way Elk Grove CA 95624",
    "addr:housenumber":"9461",
    "addr:postcode":"95624",
    "addr:street":"Heathman Way",
    "iso:country":"US",
    "sg:address":"9461 Heathman Way",
    "sg:city":"Elk Grove",
    "sg:classifiers":[
        {
            "category":"Home & Garden",
            "subcategory":"Home Furnishings",
            "type":"Retail Goods"
        }
    ],
    "sg:phone":"+1 916 505 0854",
    "sg:postcode":"95624",
    "sg:province":"CA",
    "sg:tags":[
        "curtain",
        "made",
        "drapery"
    ],
    "wof:name":"Amer Style Custom Draperies",
    "wof:placetype":"venue"
},
  "geometry": {"coordinates":[-121.342795,38.414618],"type":"Point"}
}