{
  "type": "Feature",
  "properties": {
    "addr:full":"711 W 17th St Ste 1a Costa Mesa CA 92627",
    "addr:housenumber":"711",
    "addr:postcode":"92627",
    "addr:street":"W 17Th St Ste 1A",
    "iso:country":"US",
    "sg:address":"711 W 17th St Ste 1a",
    "sg:city":"Costa Mesa",
    "sg:classifiers":[
        {
            "category":"Personal",
            "type":"Services"
        }
    ],
    "sg:phone":"+1 888 888 8150",
    "sg:postcode":"92627",
    "sg:province":"CA",
    "sg:tags":[
        "home"
    ],
    "sg:website":"www.diversifiedgaragedoors.com",
    "wof:name":"Diversified Garage Doors",
    "wof:placetype":"venue"
},
  "geometry": {"coordinates":[-117.929306,33.635917],"type":"Point"}
}