{
  "type": "Feature",
  "properties": {
    "iso:country":"US",
    "sg:address":"10406 Enterprise St",
    "sg:city":"Rancho Cucamonga",
    "sg:classifiers":[
        {
            "category":"Wholesale",
            "subcategory":"Electrical",
            "type":"Manufacturing & Wholesale Goods"
        }
    ],
    "sg:phone":"+1 909 987 4050",
    "sg:postcode":"91730",
    "sg:province":"CA",
    "sg:tags":[
        "equipment",
        "electronic",
        "supply"
    ],
    "sg:website":"www.preferredelectronics.com",
    "wof:name":"Preferred Elctronics",
    "wof:placetype":"venue"
},
  "geometry": {"coordinates":[-117.57823999999999,34.079537],"type":"Point"}
}