{
  "type": "Feature",
  "properties": {
    "iso:country":"US",
    "sg:address":"24525 Outlook Dr",
    "sg:city":"Carmel",
    "sg:classifiers":[
        {
            "category":"Communications",
            "type":"Services"
        }
    ],
    "sg:phone":"+1 831 620 1227",
    "sg:postcode":"93923",
    "sg:province":"CA",
    "sg:tags":[
        "communication"
    ],
    "wof:name":"Bonnie Brook Communications",
    "wof:placetype":"venue"
},
  "geometry": {"coordinates":[-121.906255,36.565427],"type":"Point"}
}