{
  "type": "Feature",
  "properties": {
    "addr:full":"5006 York Blvd Los Angeles CA 90042",
    "addr:housenumber":"5006",
    "addr:postcode":"90042",
    "addr:street":"York Blvd",
    "iso:country":"US",
    "sg:address":"5006 York Blvd",
    "sg:city":"Los Angeles",
    "sg:classifiers":[
        {
            "category":"Bars & Pubs",
            "type":"Food & Drink"
        }
    ],
    "sg:phone":"+1 323 551 6959",
    "sg:postcode":"90042",
    "sg:province":"CA",
    "sg:website":"www.facebook.com/pages/Los-Angel...",
    "wof:name":"Johnny's Bar",
    "wof:placetype":"venue"
},
  "geometry": {"coordinates":[-118.206664,34.121138],"type":"Point"}
}