{
  "type": "Feature",
  "properties": {
    "addr:full":"18740 Washington Blvd Culver City CA 90230",
    "addr:housenumber":"18740",
    "addr:postcode":"90230",
    "addr:street":"Washington Blvd",
    "iso:country":"US",
    "sg:address":"18740 Washington Blvd",
    "sg:city":"Culver City",
    "sg:classifiers":[
        {
            "category":"Home & Garden",
            "subcategory":"Carpets & Floor Coverings",
            "type":"Retail Goods"
        }
    ],
    "sg:phone":"+1 310 845 9328",
    "sg:postcode":"90230",
    "sg:province":"CA",
    "sg:tags":[
        "mattress"
    ],
    "wof:name":"Ortho Mattress",
    "wof:placetype":"venue"
},
  "geometry": {"coordinates":[-118.397003,33.996899],"type":"Point"}
}