{
  "type": "Feature",
  "properties": {
    "iso:country":"US",
    "sg:address":"21098 S Valentine Ave",
    "sg:city":"Riverdale",
    "sg:classifiers":[
        {
            "category":"Professional",
            "subcategory":"Business Services",
            "type":"Services"
        }
    ],
    "sg:phone":"+1 559 867 3153",
    "sg:postcode":"93656",
    "sg:province":"CA",
    "sg:tags":[
        "environmental",
        "ecological",
        "product"
    ],
    "wof:name":"Kings River Conservation District",
    "wof:placetype":"venue"
},
  "geometry": {"coordinates":[-119.860153,36.429649],"type":"Point"}
}