{
  "type": "Feature",
  "properties": {
    "iso:country":"US",
    "sg:address":"6330 S Verdun Ave",
    "sg:city":"Los Angeles",
    "sg:classifiers":[
        {
            "category":"Social Services",
            "subcategory":"Child Care",
            "type":"Services"
        }
    ],
    "sg:phone":"+1 323 299 3226",
    "sg:postcode":"90043",
    "sg:province":"CA",
    "wof:name":"Harris Family Day Care",
    "wof:placetype":"venue"
},
  "geometry": {"coordinates":[-118.34547000000001,33.982017],"type":"Point"}
}