{
  "type": "Feature",
  "properties": {
    "iso:country":"US",
    "sg:address":"16646 Bernardo Center Dr",
    "sg:city":"San Diego",
    "sg:classifiers":[
        {
            "category":"Professional",
            "type":"Services"
        }
    ],
    "sg:phone":"+1 858 451 8150",
    "sg:postcode":"92128",
    "sg:province":"CA",
    "sg:tags":[
        "establishment"
    ],
    "wof:name":"Conventions In America",
    "wof:placetype":"venue"
},
  "geometry": {"coordinates":[-117.076509,33.015905],"type":"Point"}
}