{
  "type": "Feature",
  "properties": {
    "addr:full":"1407 Foothill Blvd La Verne CA 91750",
    "addr:housenumber":"1407",
    "addr:postcode":"91750",
    "addr:street":"Foothill Blvd",
    "iso:country":"US",
    "sg:address":"1407 Foothill Blvd",
    "sg:city":"La Verne",
    "sg:classifiers":[
        {
            "category":"Wholesale",
            "subcategory":"Computers",
            "type":"Manufacturing & Wholesale Goods"
        }
    ],
    "sg:phone":"+1 909 392 2040",
    "sg:postcode":"91750",
    "sg:province":"CA",
    "sg:tags":[
        "software"
    ],
    "wof:name":"Epic Media Group",
    "wof:placetype":"venue"
},
  "geometry": {"coordinates":[-117.77580500000001,34.116921],"type":"Point"}
}