{
  "type": "Feature",
  "properties": {
    "addr:full":"13600 Marina Pointe Dr Marina Del Rey CA 90292",
    "addr:housenumber":"13600",
    "addr:postcode":"90292",
    "addr:street":"Marina Pointe Dr",
    "iso:country":"US",
    "sg:address":"13600 Marina Pointe Dr",
    "sg:city":"Marina Del Rey",
    "sg:classifiers":[
        {
            "category":"Professional",
            "type":"Services"
        }
    ],
    "sg:phone":"+1 310 318 9212",
    "sg:postcode":"90292",
    "sg:province":"CA",
    "wof:name":"Ceebeehappee",
    "wof:placetype":"venue"
},
  "geometry": {"coordinates":[-118.443674,33.985531],"type":"Point"}
}