{
  "type": "Feature",
  "properties": {
    "addr:full":"823 Linden Ave Apt 101 Long Beach CA 90813",
    "addr:housenumber":"823;101",
    "addr:postcode":"90813",
    "addr:street":"Linden Ave Apt",
    "iso:country":"US",
    "sg:address":"823 Linden Ave Apt 101",
    "sg:city":"Long Beach",
    "sg:classifiers":[
        {
            "category":"Real Estate",
            "subcategory":"Real Estate Operator",
            "type":"Services"
        }
    ],
    "sg:phone":"+1 562 437 4500",
    "sg:postcode":"90813",
    "sg:province":"CA",
    "sg:tags":[
        "apartment"
    ],
    "wof:name":"St.Mary's Arms Apartments",
    "wof:placetype":"venue"
},
  "geometry": {"coordinates":[-118.186521,33.776835],"type":"Point"}
}