{
  "type": "Feature",
  "properties": {
    "iso:country":"US",
    "sg:address":"14831 Burbank Blvd",
    "sg:city":"Van Nuys",
    "sg:classifiers":[
        {
            "category":"Shopping",
            "subcategory":"Florist",
            "type":"Retail Goods"
        }
    ],
    "sg:phone":"+1 818 781 3083",
    "sg:postcode":"91411",
    "sg:province":"CA",
    "wof:name":"House Of Flowers & Designs",
    "wof:placetype":"venue"
},
  "geometry": {"coordinates":[-118.45737,34.172187],"type":"Point"}
}