{
  "type": "Feature",
  "properties": {
    "iso:country":"US",
    "sg:address":"3530 Cam del Rio N",
    "sg:city":"San Diego",
    "sg:classifiers":[
        {
            "category":"Professional",
            "subcategory":"Lawyer & Legal Services",
            "type":"Services"
        }
    ],
    "sg:phone":"+1 619 284 2444",
    "sg:postcode":"92108",
    "sg:province":"CA",
    "sg:tags":[
        "attorney"
    ],
    "sg:website":"www.sandiegoprobate.com",
    "wof:name":"SANDIEGOPROBATE.COM",
    "wof:placetype":"venue"
},
  "geometry": {"coordinates":[-117.12083199999999,32.777771],"type":"Point"}
}