{
  "type": "Feature",
  "properties": {
    "addr:full":"132 French St Willows CA 95988",
    "addr:housenumber":"132",
    "addr:postcode":"95988",
    "addr:street":"French St",
    "iso:country":"US",
    "sg:address":"132 French St",
    "sg:city":"Willows",
    "sg:classifiers":[
        {
            "category":"Building & Trades",
            "subcategory":"Construction",
            "type":"Services"
        }
    ],
    "sg:phone":"+1 530 934 8989",
    "sg:postcode":"95988",
    "sg:province":"CA",
    "sg:tags":[
        "contractor"
    ],
    "wof:name":"William Mc Clure General Contr",
    "wof:placetype":"venue"
},
  "geometry": {"coordinates":[-122.194373,39.526655],"type":"Point"}
}