{
  "type": "Feature",
  "properties": {
    "addr:full":"16 Technology Dr Irvine CA 92618",
    "addr:housenumber":"16",
    "addr:postcode":"92618",
    "addr:street":"Technology Dr",
    "iso:country":"US",
    "sg:address":"16 Technology Dr",
    "sg:city":"Irvine",
    "sg:classifiers":[
        {
            "category":"Professional",
            "type":"Services"
        }
    ],
    "sg:phone":"+1 714 374 8108",
    "sg:postcode":"92618",
    "sg:province":"CA",
    "wof:name":"Transbiotec",
    "wof:placetype":"venue"
},
  "geometry": {"coordinates":[-117.736587,33.649328],"type":"Point"}
}