{
  "type": "Feature",
  "properties": {
    "iso:country":"US",
    "sg:address":"955 Marina Blvd",
    "sg:city":"San Leandro",
    "sg:classifiers":[
        {
            "category":"Personal",
            "type":"Services"
        }
    ],
    "sg:phone":"+1 510 357 6200",
    "sg:postcode":"94577",
    "sg:province":"CA",
    "sg:tags":[
        "local"
    ],
    "wof:name":"Peterson Tractor Co",
    "wof:placetype":"venue"
},
  "geometry": {"coordinates":[-122.160004,37.7132],"type":"Point"}
}