{
  "type": "Feature",
  "properties": {
    "addr:full":"6480 Farley Dr San Diego CA 92122",
    "addr:housenumber":"6480",
    "addr:postcode":"92122",
    "addr:street":"Farley Dr",
    "iso:country":"US",
    "sg:address":"6480 Farley Dr",
    "sg:city":"San Diego",
    "sg:classifiers":[
        {
            "category":"Professional",
            "subcategory":"Management & Consulting",
            "type":"Services"
        }
    ],
    "sg:phone":"+1 858 457 0955",
    "sg:postcode":"92122",
    "sg:province":"CA",
    "sg:tags":[
        "counselor",
        "public",
        "relations"
    ],
    "wof:name":"Frampton & Assoc",
    "wof:placetype":"venue"
},
  "geometry": {"coordinates":[-117.198262,32.855348],"type":"Point"}
}