{
  "type": "Feature",
  "properties": {
    "addr:full":"7460 Gordon Valley Rd Suisun City CA 94585",
    "addr:housenumber":"7460",
    "addr:postcode":"94585",
    "addr:street":"Gordon Valley Rd",
    "iso:country":"US",
    "sg:address":"7460 Gordon Valley Rd",
    "sg:city":"Suisun City",
    "sg:classifiers":[
        {
            "category":"Farming",
            "subcategory":"Livestock Farm",
            "type":"Manufacturing & Wholesale Goods"
        }
    ],
    "sg:phone":"+1 707 425 4193",
    "sg:postcode":"94585",
    "sg:province":"CA",
    "sg:tags":[
        "ranch"
    ],
    "wof:name":"Gordon Valley Ranch Hdqtrs",
    "wof:placetype":"venue"
},
  "geometry": {"coordinates":[-122.128079,38.352595],"type":"Point"}
}