{
  "type": "Feature",
  "properties": {
    "addr:full":"6830 Walerga Rd Ofc Sacramento CA 95842",
    "addr:postcode":"6830;95842",
    "addr:street":"Walerga Rd",
    "iso:country":"US",
    "sg:address":"6830 Walerga Rd Ofc",
    "sg:city":"Sacramento",
    "sg:classifiers":[
        {
            "category":"Real Estate",
            "subcategory":"Real Estate Operator",
            "type":"Services"
        }
    ],
    "sg:phone":"+1 916 348 0400",
    "sg:postcode":"95842",
    "sg:province":"CA",
    "sg:tags":[
        "apartment"
    ],
    "wof:name":"Summertime Apartments",
    "wof:placetype":"venue"
},
  "geometry": {"coordinates":[-121.363998,38.690899],"type":"Point"}
}