{
  "type": "Feature",
  "properties": {
    "addr:full":"17836 Gillette Ave Irvine CA 92614",
    "addr:postcode":"17836;92614",
    "addr:street":"Gillette Ave",
    "iso:country":"US",
    "sg:address":"17836 Gillette Ave",
    "sg:city":"Irvine",
    "sg:classifiers":[
        {
            "category":"Professional",
            "subcategory":"Computer Services",
            "type":"Services"
        }
    ],
    "sg:phone":"+1 949 477 4939",
    "sg:postcode":"92614",
    "sg:province":"CA",
    "sg:tags":[
        "hardware",
        "provider",
        "internet",
        "software"
    ],
    "wof:name":"Right Click LLC",
    "wof:placetype":"venue"
},
  "geometry": {"coordinates":[-117.85301200000001,33.688575],"type":"Point"}
}