{
  "type": "Feature",
  "properties": {
    "iso:country":"US",
    "sg:address":"1101 Pacific Ave",
    "sg:city":"Santa Cruz",
    "sg:classifiers":[
        {
            "category":"Restaurant",
            "type":"Food & Drink"
        }
    ],
    "sg:menulink":"http://www.allmenus.com/ca/santa-cruz/62417-lees-sandwich-shop/menu/",
    "sg:phone":"+1 831 438 0348",
    "sg:postcode":"95060",
    "sg:province":"CA",
    "sg:tags":[
        "wrap",
        "american",
        "sandwich"
    ],
    "wof:name":"Lee's Sandwich Shop",
    "wof:placetype":"venue"
},
  "geometry": {"coordinates":[-122.025431,36.9718],"type":"Point"}
}