{
  "type": "Feature",
  "properties": {
    "iso:country":"US",
    "sg:address":"1820 N Las Palmas Ave",
    "sg:city":"Los Angeles",
    "sg:classifiers":[
        {
            "category":"Social Services",
            "type":"Services"
        }
    ],
    "sg:phone":"+1 323 465 7787",
    "sg:postcode":"90028",
    "sg:province":"CA",
    "wof:name":"Parks & Recreation Dept",
    "wof:placetype":"venue"
},
  "geometry": {"coordinates":[-118.336302,34.104995],"type":"Point"}
}