{
  "type": "Feature",
  "properties": {
    "addr:full":"1465 E Anita St Upland CA 91786",
    "addr:housenumber":"1465",
    "addr:postcode":"91786",
    "addr:street":"E Anita St",
    "iso:country":"US",
    "sg:address":"1465 E Anita St",
    "sg:city":"Upland",
    "sg:classifiers":[
        {
            "category":"Building & Trades",
            "subcategory":"Plumbing",
            "type":"Services"
        }
    ],
    "sg:phone":"+1 951 966 7751",
    "sg:postcode":"91786",
    "sg:province":"CA",
    "sg:tags":[
        "contractor"
    ],
    "wof:name":"Leagons Plumbing Services",
    "wof:placetype":"venue"
},
  "geometry": {"coordinates":[-117.630336,34.109153],"type":"Point"}
}