{
  "type": "Feature",
  "properties": {
    "addr:full":"4036 Morrell St San Diego CA 92109",
    "addr:housenumber":"4036",
    "addr:postcode":"92109",
    "addr:street":"Morrell St",
    "iso:country":"US",
    "sg:address":"4036 Morrell St",
    "sg:city":"San Diego",
    "sg:classifiers":[
        {
            "category":"Professional",
            "subcategory":"Art Services",
            "type":"Services"
        }
    ],
    "sg:phone":"+1 530 514 1549",
    "sg:postcode":"92109",
    "sg:province":"CA",
    "sg:tags":[
        "photographer"
    ],
    "sg:website":"www.lisafitts.com/",
    "wof:name":"Lisa Fitts Photography",
    "wof:placetype":"venue"
},
  "geometry": {"coordinates":[-117.231441,32.794671],"type":"Point"}
}