{
  "type": "Feature",
  "properties": {
    "iso:country":"US",
    "sg:address":"15068 Rosecrans Ave",
    "sg:city":"La Mirada",
    "sg:classifiers":[
        {
            "category":"Professional",
            "subcategory":"Accounting & Tax Preparation",
            "type":"Services"
        }
    ],
    "sg:phone":"+1 562 868 3699",
    "sg:postcode":"90638",
    "sg:province":"CA",
    "sg:tags":[
        "billing"
    ],
    "wof:name":"Pro-Tech Medical Billing Svc",
    "wof:placetype":"venue"
},
  "geometry": {"coordinates":[-118.00981299999999,33.898377],"type":"Point"}
}