{
  "type": "Feature",
  "properties": {
    "iso:country":"US",
    "sg:address":"1020 Bradbourne Ave Spc 8",
    "sg:city":"Duarte",
    "sg:classifiers":[
        {
            "category":"Place Of Worship",
            "type":"Public Place"
        }
    ],
    "sg:phone":"+1 626 532 6748",
    "sg:postcode":"91010",
    "sg:province":"CA",
    "sg:tags":[
        "church"
    ],
    "wof:name":"United Church Fo God La",
    "wof:placetype":"venue"
},
  "geometry": {"coordinates":[-117.960049,34.140803],"type":"Point"}
}