{
  "type": "Feature",
  "properties": {
    "iso:country":"US",
    "sg:address":"15335 Hawthorne Blvd Ste A",
    "sg:city":"Lawndale",
    "sg:classifiers":[
        {
            "category":"Banks & Credit Unions",
            "subcategory":"Bank",
            "type":"Services"
        }
    ],
    "sg:phone":"+1 310 973 6044",
    "sg:postcode":"90260",
    "sg:province":"CA",
    "sg:website":"www.statefarm.com",
    "wof:name":"Tolliver Wanza Insurance",
    "wof:placetype":"venue"
},
  "geometry": {"coordinates":[-118.352997,33.891998],"type":"Point"}
}