{
  "type": "Feature",
  "properties": {
    "iso:country":"US",
    "sg:address":"6762 Eldridge St",
    "sg:city":"San Diego",
    "sg:classifiers":[
        {
            "category":"Building & Trades",
            "subcategory":"Construction",
            "type":"Services"
        }
    ],
    "sg:phone":"+1 619 583 5245",
    "sg:postcode":"92120",
    "sg:province":"CA",
    "sg:tags":[
        "handyman"
    ],
    "wof:name":"Redi-Man",
    "wof:placetype":"venue"
},
  "geometry": {"coordinates":[-117.076572,32.792233],"type":"Point"}
}