{
  "type": "Feature",
  "properties": {
    "iso:country":"US",
    "sg:address":"214 Cristich Ln",
    "sg:city":"Campbell",
    "sg:classifiers":[
        {
            "category":"Wholesale",
            "subcategory":"Electrical",
            "type":"Manufacturing & Wholesale Goods"
        }
    ],
    "sg:phone":"+1 408 369 1493",
    "sg:postcode":"95008",
    "sg:province":"CA",
    "sg:tags":[
        "control",
        "alarm",
        "burglar",
        "security",
        "system"
    ],
    "wof:name":"3m Pacific Security Systems",
    "wof:placetype":"venue"
},
  "geometry": {"coordinates":[-121.945116,37.276836],"type":"Point"}
}