{
  "type": "Feature",
  "properties": {
    "addr:full":"10309 Folsom Blvd Rancho Cordova CA 95670",
    "addr:housenumber":"10309",
    "addr:postcode":"95670",
    "addr:street":"Folsom Blvd",
    "iso:country":"US",
    "sg:address":"10309 Folsom Blvd",
    "sg:city":"Rancho Cordova",
    "sg:classifiers":[
        {
            "category":"Shopping",
            "subcategory":"Used Merchandise",
            "type":"Retail Goods"
        }
    ],
    "sg:phone":"+1 916 362 6296",
    "sg:postcode":"95670",
    "sg:province":"CA",
    "sg:tags":[
        "shop",
        "thrift"
    ],
    "wof:name":"Salvation Army",
    "wof:placetype":"venue"
},
  "geometry": {"coordinates":[-121.303393,38.588893],"type":"Point"}
}