{
  "type": "Feature",
  "properties": {
    "iso:country":"US",
    "sg:address":"8126 Chase Ave",
    "sg:city":"Los Angeles",
    "sg:classifiers":[
        {
            "category":"Shopping",
            "subcategory":"Hobbies, Toys, & Games",
            "type":"Retail Goods"
        }
    ],
    "sg:phone":"+1 310 641 1551",
    "sg:postcode":"90045",
    "sg:province":"CA",
    "sg:tags":[
        "craft"
    ],
    "wof:name":"Scrapeez",
    "wof:placetype":"venue"
},
  "geometry": {"coordinates":[-118.410881,33.964695],"type":"Point"}
}