{
  "type": "Feature",
  "properties": {
    "addr:full":"77 Geary St Mezzanine Level San Francisco CA 94108",
    "addr:housenumber":"77",
    "addr:postcode":"94108",
    "addr:street":"Geary St",
    "iso:country":"US",
    "sg:address":"77 Geary St Mezzanine Level",
    "sg:city":"San Francisco",
    "sg:classifiers":[
        {
            "category":"Arts & Performance",
            "subcategory":"Art Gallery",
            "type":"Entertainment"
        }
    ],
    "sg:phone":"+1 415 788 5126",
    "sg:postcode":"94108",
    "sg:province":"CA",
    "sg:website":"www.patriciasweetowgallery.com",
    "wof:name":"Patricia Sweetow Gallery",
    "wof:placetype":"venue"
},
  "geometry": {"coordinates":[-122.40452399999999,37.787825],"type":"Point"}
}