{
  "type": "Feature",
  "properties": {
    "addr:full":"901 Illinois St San Francisco CA 94107",
    "addr:housenumber":"901",
    "addr:postcode":"94107",
    "addr:street":"Illinois St",
    "iso:country":"US",
    "sg:address":"901 Illinois St",
    "sg:city":"San Francisco",
    "sg:classifiers":[
        {
            "category":"Personal",
            "type":"Services"
        },
        {
            "category":"Arts & Performance",
            "subcategory":"Music",
            "type":"Entertainment"
        }
    ],
    "sg:phone":"+1 800 741 2420",
    "sg:postcode":"94107",
    "sg:province":"CA",
    "sg:tags":[
        "party",
        "planning",
        "dj",
        "event"
    ],
    "sg:website":"www.party-professionals.com",
    "wof:name":"Party Professionals",
    "wof:placetype":"venue"
},
  "geometry": {"coordinates":[-122.387548,37.760526],"type":"Point"}
}