{
  "type": "Feature",
  "properties": {
    "addr:full":"12010 Woodruff Ave Downey CA 90241",
    "addr:housenumber":"12010",
    "addr:postcode":"90241",
    "addr:street":"Woodruff Ave",
    "iso:country":"US",
    "sg:address":"12010 Woodruff Ave",
    "sg:city":"Downey",
    "sg:classifiers":[
        {
            "category":"Retail",
            "subcategory":"Auto Repair",
            "type":"Services"
        }
    ],
    "sg:phone":"+1 562 803 1210",
    "sg:postcode":"90241",
    "sg:province":"CA",
    "wof:name":"A & C Engineering",
    "wof:placetype":"venue"
},
  "geometry": {"coordinates":[-118.116524,33.925927],"type":"Point"}
}