{
  "type": "Feature",
  "properties": {
    "addr:full":"2794 Garden St Oakland CA 94601",
    "addr:housenumber":"2794",
    "addr:postcode":"94601",
    "addr:street":"Garden St",
    "iso:country":"US",
    "sg:address":"2794 Garden St",
    "sg:city":"Oakland",
    "sg:classifiers":[
        {
            "category":"Social Services",
            "type":"Services"
        }
    ],
    "sg:phone":"+1 510 437 9437",
    "sg:postcode":"94601",
    "sg:province":"CA",
    "sg:tags":[
        "program",
        "services-information",
        "referral"
    ],
    "wof:name":"Salvation Army",
    "wof:placetype":"venue"
},
  "geometry": {"coordinates":[-122.222615,37.793162],"type":"Point"}
}