{
  "type": "Feature",
  "properties": {
    "iso:country":"US",
    "sg:address":"1741 E Cypress Ave",
    "sg:city":"Redding",
    "sg:classifiers":[
        {
            "category":"Shopping",
            "subcategory":"Bicycles & Sporting Goods",
            "type":"Retail Goods"
        }
    ],
    "sg:phone":"+1 530 222 6112",
    "sg:postcode":"96002",
    "sg:province":"CA",
    "wof:name":"Sports Gear Locker",
    "wof:placetype":"venue"
},
  "geometry": {"coordinates":[-122.33965000000001,40.570847],"type":"Point"}
}