{
  "type": "Feature",
  "properties": {
    "iso:country":"US",
    "sg:address":"1361 N Emerald Ave",
    "sg:city":"Modesto",
    "sg:classifiers":[
        {
            "category":"Building & Trades",
            "subcategory":"Construction",
            "type":"Services"
        }
    ],
    "sg:phone":"+1 209 522 5338",
    "sg:postcode":"95351",
    "sg:province":"CA",
    "sg:tags":[
        "lathing",
        "contractor"
    ],
    "wof:name":"Modesto Lathing Co",
    "wof:placetype":"venue"
},
  "geometry": {"coordinates":[-121.02728,37.655412],"type":"Point"}
}