{
  "type": "Feature",
  "properties": {
    "iso:country":"US",
    "sg:address":"12167 Arrow Rte",
    "sg:city":"Etiwanda",
    "sg:classifiers":[
        {
            "category":"Insurance",
            "subcategory":"Insurance Agent",
            "type":"Services"
        }
    ],
    "sg:phone":"+1 909 581 3595",
    "sg:postcode":"91739",
    "sg:province":"CA",
    "wof:name":"Copart Inc",
    "wof:placetype":"venue"
},
  "geometry": {"coordinates":[-117.536681,34.099034],"type":"Point"}
}