{
  "type": "Feature",
  "properties": {
    "addr:full":"3614 Porter Gulch Rd Aptos CA 95003",
    "addr:housenumber":"3614",
    "addr:postcode":"ca 95003",
    "addr:street":"Porter Gulch Rd",
    "iso:country":"US",
    "sg:address":"3614 Porter Gulch Rd",
    "sg:city":"Aptos",
    "sg:classifiers":[
        {
            "category":"Personal",
            "type":"Services"
        }
    ],
    "sg:phone":"+1 831 462 3277",
    "sg:postcode":"95003",
    "sg:province":"CA",
    "sg:tags":[
        "counseling"
    ],
    "wof:name":"Bryson Kelly Mft",
    "wof:placetype":"venue"
},
  "geometry": {"coordinates":[-121.923745,36.996102],"type":"Point"}
}