{
  "type": "Feature",
  "properties": {
    "addr:full":"2550 Canyon Springs Pkwy Riverside CA 92507",
    "addr:housenumber":"2550",
    "addr:postcode":"92507",
    "addr:street":"Canyon Springs Pkwy",
    "iso:country":"US",
    "sg:address":"2550 Canyon Springs Pkwy",
    "sg:city":"Riverside",
    "sg:classifiers":[
        {
            "category":"Shopping",
            "subcategory":"Computers & Home Electronics",
            "type":"Retail Goods"
        },
        {
            "category":"Wholesale",
            "subcategory":"Office Equipment",
            "type":"Manufacturing & Wholesale Goods"
        },
        {
            "category":"Professional",
            "subcategory":"Printing & Photocopies",
            "type":"Services"
        },
        {
            "category":"Professional",
            "subcategory":"Computer Services",
            "type":"Services"
        },
        {
            "category":"Shopping",
            "subcategory":"Stationery & Office Supplies",
            "type":"Retail Goods"
        },
        {
            "category":"Wholesale",
            "subcategory":"Computers",
            "type":"Manufacturing & Wholesale Goods"
        }
    ],
    "sg:phone":"+1 951 656 6594",
    "sg:postcode":"92507",
    "sg:province":"CA",
    "sg:tags":[
        "printer",
        "register",
        "autographic",
        "duplicating",
        "hardware",
        "copying",
        "software",
        "furniture"
    ],
    "sg:website":"http://www.staples.com/",
    "wof:name":"Staples",
    "wof:placetype":"venue"
},
  "geometry": {"coordinates":[-117.28665599999999,33.94181],"type":"Point"}
}