{
  "type": "Feature",
  "properties": {
    "iso:country":"US",
    "sg:address":"2255 Morello Ave",
    "sg:city":"Pleasant Hill",
    "sg:classifiers":[
        {
            "category":"Education",
            "subcategory":"Special Training",
            "type":"Public Place"
        }
    ],
    "sg:phone":"+1 925 691 7612",
    "sg:postcode":"94523",
    "sg:province":"CA",
    "sg:tags":[
        "instruction",
        "driving"
    ],
    "wof:name":"Cheap Comedy 4-U",
    "wof:placetype":"venue"
},
  "geometry": {"coordinates":[-122.079029,37.961738],"type":"Point"}
}