{
  "type": "Feature",
  "properties": {
    "addr:full":"154 S 8th St Grover Beach CA 93433",
    "addr:housenumber":"154",
    "addr:postcode":"93433",
    "addr:street":"S 8Th St",
    "iso:country":"US",
    "sg:address":"154 S 8th St",
    "sg:city":"Grover Beach",
    "sg:classifiers":[
        {
            "category":"Government",
            "subcategory":"Office",
            "type":"Public Place"
        }
    ],
    "sg:phone":"+1 805 473 4568",
    "sg:postcode":"93433",
    "sg:province":"CA",
    "sg:tags":[
        "village"
    ],
    "sg:website":"www.grover.org",
    "wof:name":"Grover Beach City Personnel",
    "wof:placetype":"venue"
},
  "geometry": {"coordinates":[-120.621588,35.120983],"type":"Point"}
}