{
  "type": "Feature",
  "properties": {
    "addr:full":"1850 W 169th St Gardena CA 90247",
    "addr:housenumber":"1850",
    "addr:postcode":"90247",
    "addr:street":"W 169Th St",
    "iso:country":"US",
    "sg:address":"1850 W 169th St",
    "sg:city":"Gardena",
    "sg:classifiers":[
        {
            "category":"Wholesale",
            "subcategory":"Groceries",
            "type":"Manufacturing & Wholesale Goods"
        }
    ],
    "sg:phone":"+1 310 366 7612",
    "sg:postcode":"90247",
    "sg:province":"CA",
    "sg:tags":[
        "food",
        "product"
    ],
    "sg:website":"www.authenticfoods.com",
    "wof:name":"Authentic Foods",
    "wof:placetype":"venue"
},
  "geometry": {"coordinates":[-118.312179,33.87824],"type":"Point"}
}