{
  "type": "Feature",
  "properties": {
    "addr:full":"40 4th St Petaluma CA 94952",
    "addr:housenumber":"40",
    "addr:postcode":"94952",
    "addr:street":"4Th St",
    "iso:country":"US",
    "sg:address":"40 4th St",
    "sg:city":"Petaluma",
    "sg:classifiers":[
        {
            "category":"Building & Trades",
            "subcategory":"Construction",
            "type":"Services"
        }
    ],
    "sg:phone":"+1 707 765 6091",
    "sg:postcode":"94952",
    "sg:province":"CA",
    "sg:tags":[
        "contractor"
    ],
    "wof:name":"Roofmart International",
    "wof:placetype":"venue"
},
  "geometry": {"coordinates":[-122.63879,38.232319],"type":"Point"}
}