{
  "type": "Feature",
  "properties": {
    "iso:country":"US",
    "sg:address":"1301 S Main St",
    "sg:city":"Los Angeles",
    "sg:classifiers":[
        {
            "category":"Sports & Exercise",
            "subcategory":"Bicycle Rental",
            "type":"Entertainment"
        }
    ],
    "sg:phone":"+1 213 841 9493",
    "sg:postcode":"90015",
    "sg:province":"CA",
    "sg:tags":[
        "wear"
    ],
    "sg:website":"mastermindhats.com",
    "wof:name":"Mastermind Hat Company",
    "wof:placetype":"venue"
},
  "geometry": {"coordinates":[-118.26077,34.03646],"type":"Point"}
}