{
  "type": "Feature",
  "properties": {
    "iso:country":"US",
    "sg:address":"1825 Hillsdale Ave",
    "sg:city":"San Jose",
    "sg:classifiers":[
        {
            "category":"Shopping",
            "subcategory":"Computers & Home Electronics",
            "type":"Retail Goods"
        }
    ],
    "sg:phone":"+1 408 723 2753",
    "sg:postcode":"95124",
    "sg:province":"CA",
    "sg:tags":[
        "equipment",
        "electronic",
        "supply"
    ],
    "wof:name":"Circuit City",
    "wof:placetype":"venue"
},
  "geometry": {"coordinates":[-121.919931,37.2623],"type":"Point"}
}