{
  "type": "Feature",
  "properties": {
    "iso:country":"US",
    "sg:address":"1595 Berenice Dr",
    "sg:city":"Brea",
    "sg:classifiers":[
        {
            "category":"Organizations",
            "subcategory":"Non-profit Organization",
            "type":"Services"
        }
    ],
    "sg:phone":"+1 714 946 4535",
    "sg:postcode":"92821",
    "sg:province":"CA",
    "sg:tags":[
        "social"
    ],
    "wof:name":"Circle Assoc",
    "wof:placetype":"venue"
},
  "geometry": {"coordinates":[-117.915078,33.94371],"type":"Point"}
}