{
  "type": "Feature",
  "properties": {
    "addr:full":"89780 60th Ave Thermal CA 92274",
    "addr:housenumber":"89780",
    "addr:postcode":"92274",
    "addr:street":"60Th Ave",
    "iso:country":"US",
    "sg:address":"89780 60th Ave",
    "sg:city":"Thermal",
    "sg:classifiers":[
        {
            "category":"Professional",
            "type":"Services"
        }
    ],
    "sg:phone":"+1 760 399 5494",
    "sg:postcode":"92274",
    "sg:province":"CA",
    "sg:tags":[
        "establishment"
    ],
    "wof:name":"Larson Drake Sales",
    "wof:placetype":"venue"
},
  "geometry": {"coordinates":[-116.098162,33.61325],"type":"Point"}
}