{
  "type": "Feature",
  "properties": {
    "iso:country":"US",
    "sg:address":"13111 S San Pedro Street Apt 35",
    "sg:city":"Los Angeles",
    "sg:classifiers":[
        {
            "category":"Real Estate",
            "subcategory":"Real Estate Operator",
            "type":"Services"
        }
    ],
    "sg:phone":"+1 310 516 7325",
    "sg:postcode":"90061",
    "sg:province":"CA",
    "sg:tags":[
        "apartment"
    ],
    "wof:name":"South Bay Villa",
    "wof:placetype":"venue"
},
  "geometry": {"coordinates":[-118.269598,33.913616],"type":"Point"}
}