{
  "type": "Feature",
  "properties": {
    "iso:country":"US",
    "sg:address":"5100 California Ave",
    "sg:city":"Bakersfield",
    "sg:classifiers":[
        {
            "category":"Banks & Credit Unions",
            "subcategory":"Bank",
            "type":"Services"
        }
    ],
    "sg:phone":"+1 661 324 6873",
    "sg:postcode":"93309",
    "sg:province":"CA",
    "sg:tags":[
        "loan",
        "real estate"
    ],
    "wof:name":"Mortgage Tree Lending",
    "wof:placetype":"venue"
},
  "geometry": {"coordinates":[-119.05721800000001,35.363892],"type":"Point"}
}