{
  "type": "Feature",
  "properties": {
    "addr:full":"1037 Bushard Dr Escondido CA 92029",
    "addr:housenumber":"1037",
    "addr:postcode":"92029",
    "addr:street":"Bushard Dr",
    "iso:country":"US",
    "sg:address":"1037 Bushard Dr",
    "sg:city":"Escondido",
    "sg:classifiers":[
        {
            "category":"Building & Trades",
            "subcategory":"Construction",
            "type":"Services"
        }
    ],
    "sg:phone":"+1 760 746 3346",
    "sg:postcode":"92029",
    "sg:province":"CA",
    "sg:tags":[
        "house"
    ],
    "wof:name":"Four Seasons Construction Co",
    "wof:placetype":"venue"
},
  "geometry": {"coordinates":[-117.08836700000001,33.092223],"type":"Point"}
}