{
  "type": "Feature",
  "properties": {
    "iso:country":"US",
    "sg:address":"1680 Silverado Trl S",
    "sg:city":"Saint Helena",
    "sg:classifiers":[
        {
            "category":"Manufacturing",
            "subcategory":"Food",
            "type":"Manufacturing & Wholesale Goods"
        }
    ],
    "sg:phone":"+1 707 963 5253",
    "sg:postcode":"94574",
    "sg:province":"CA",
    "sg:tags":[
        "mfg"
    ],
    "wof:name":"Van Asperen Vineyards",
    "wof:placetype":"venue"
},
  "geometry": {"coordinates":[-122.406783,38.487799],"type":"Point"}
}