{
  "type": "Feature",
  "properties": {
    "iso:country":"US",
    "sg:address":"1836 Canyon Heights Rd",
    "sg:city":"Fallbrook",
    "sg:classifiers":[
        {
            "category":"Building & Trades",
            "subcategory":"Construction",
            "type":"Services"
        }
    ],
    "sg:phone":"+1 760 728 5475",
    "sg:postcode":"92028",
    "sg:province":"CA",
    "sg:tags":[
        "concrete",
        "contractor"
    ],
    "wof:name":"Dereu Concrete",
    "wof:placetype":"venue"
},
  "geometry": {"coordinates":[-117.154055,33.407314],"type":"Point"}
}