{
  "type": "Feature",
  "properties": {
    "iso:country":"US",
    "sg:address":"11721 Westminster Ave",
    "sg:city":"Garden Grove",
    "sg:classifiers":[
        {
            "category":"Retail",
            "subcategory":"Auto Repair",
            "type":"Services"
        }
    ],
    "sg:phone":"+1 714 534 3404",
    "sg:postcode":"92843",
    "sg:province":"CA",
    "wof:name":"Jorge Auto Repair",
    "wof:placetype":"venue"
},
  "geometry": {"coordinates":[-117.925003,33.759899],"type":"Point"}
}