{
  "type": "Feature",
  "properties": {
    "iso:country":"US",
    "sg:address":"1145 10th St",
    "sg:city":"Oakland",
    "sg:classifiers":[
        {
            "category":"Real Estate",
            "subcategory":"Real Estate Operator",
            "type":"Services"
        }
    ],
    "sg:phone":"+1 510 251 0546",
    "sg:postcode":"94607",
    "sg:province":"CA",
    "sg:tags":[
        "apartment"
    ],
    "wof:name":"Acorn Apartments",
    "wof:placetype":"venue"
},
  "geometry": {"coordinates":[-122.287003,37.8064],"type":"Point"}
}