{
  "type": "Feature",
  "properties": {
    "addr:full":"405 Main St Greenville CA 95947",
    "addr:housenumber":"405",
    "addr:postcode":"95947",
    "addr:street":"Main St",
    "iso:country":"US",
    "sg:address":"405 Main St",
    "sg:city":"Greenville",
    "sg:classifiers":[
        {
            "category":"Government",
            "subcategory":"Post Office",
            "type":"Public Place"
        }
    ],
    "sg:phone":"+1 530 284 7615",
    "sg:postcode":"95947",
    "sg:province":"CA",
    "wof:name":"US Post Office",
    "wof:placetype":"venue"
},
  "geometry": {"coordinates":[-120.949961,40.140508],"type":"Point"}
}