{
  "type": "Feature",
  "properties": {
    "addr:full":"337 S Beverly Dr Ste 107 Beverly Hills CA 90212",
    "addr:housenumber":"337",
    "addr:postcode":"90212",
    "addr:street":"S Beverly Dr Ste 107;Hills Ca",
    "iso:country":"US",
    "sg:address":"337 S Beverly Dr Ste 107",
    "sg:city":"Beverly Hills",
    "sg:classifiers":[
        {
            "category":"Health Services",
            "subcategory":"Doctor",
            "type":"Services"
        },
        {
            "category":"Health Services",
            "subcategory":"Clinic",
            "type":"Services"
        }
    ],
    "sg:phone":"+1 310 552 1522",
    "sg:postcode":"90212",
    "sg:province":"CA",
    "sg:tags":[
        "counseling",
        "mental"
    ],
    "wof:name":"Reed Enid J PHD",
    "wof:placetype":"venue"
},
  "geometry": {"coordinates":[-118.399002,34.060799],"type":"Point"}
}