{
  "type": "Feature",
  "properties": {
    "iso:country":"US",
    "sg:address":"2121 W Lambert Rd",
    "sg:city":"La Habra",
    "sg:classifiers":[
        {
            "category":"Banks & Credit Unions",
            "subcategory":"Investment Brokerage",
            "type":"Services"
        }
    ],
    "sg:phone":"+1 562 691 8327",
    "sg:postcode":"90631",
    "sg:province":"CA",
    "sg:tags":[
        "advisory",
        "financial"
    ],
    "wof:name":"Golden State Financial",
    "wof:placetype":"venue"
},
  "geometry": {"coordinates":[-117.96871,33.924682],"type":"Point"}
}