{
  "type": "Feature",
  "properties": {
    "iso:country":"US",
    "sg:address":"523 Grape St",
    "sg:city":"El Cajon",
    "sg:classifiers":[
        {
            "category":"Real Estate",
            "subcategory":"Real Estate Operator",
            "type":"Services"
        }
    ],
    "sg:phone":"+1 619 579 5181",
    "sg:postcode":"92021",
    "sg:province":"CA",
    "sg:tags":[
        "building",
        "apartment"
    ],
    "wof:name":"Woodlawn Manor Apartments",
    "wof:placetype":"venue"
},
  "geometry": {"coordinates":[-116.931231,32.801655],"type":"Point"}
}