{
  "type": "Feature",
  "properties": {
    "iso:country":"US",
    "sg:address":"172 Suburbia Ave",
    "sg:city":"Santa Cruz",
    "sg:classifiers":[
        {
            "category":"Wholesale",
            "subcategory":"Plants",
            "type":"Manufacturing & Wholesale Goods"
        }
    ],
    "sg:phone":"+1 831 426 5112",
    "sg:postcode":"95062",
    "sg:province":"CA",
    "sg:tags":[
        "florist",
        "supply"
    ],
    "wof:name":"B & D Flowers",
    "wof:placetype":"venue"
},
  "geometry": {"coordinates":[-121.999666,36.982583],"type":"Point"}
}