{
  "type": "Feature",
  "properties": {
    "iso:country":"US",
    "sg:address":"8668 Nagle Ave",
    "sg:city":"Van Nuys",
    "sg:classifiers":[
        {
            "category":"Communications",
            "subcategory":"Film & Video Production",
            "type":"Services"
        }
    ],
    "sg:phone":"+1 818 989 1189",
    "sg:postcode":"91402",
    "sg:province":"CA",
    "sg:tags":[
        "editing",
        "tape"
    ],
    "sg:website":"www.kleinmediaservices.com",
    "wof:name":"Klein Media Svc",
    "wof:placetype":"venue"
},
  "geometry": {"coordinates":[-118.42276699999999,34.226582],"type":"Point"}
}