{
  "type": "Feature",
  "properties": {
    "iso:country":"US",
    "sg:address":"385 E Colorado Blvd",
    "sg:city":"Pasadena",
    "sg:classifiers":[
        {
            "category":"Banks & Credit Unions",
            "subcategory":"Investment Brokerage",
            "type":"Services"
        }
    ],
    "sg:phone":"+1 626 529 9200",
    "sg:postcode":"91106",
    "sg:province":"CA",
    "wof:name":"Vantis Capital",
    "wof:placetype":"venue"
},
  "geometry": {"coordinates":[-118.141838,34.145914],"type":"Point"}
}