{
  "type": "Feature",
  "properties": {
    "iso:country":"US",
    "sg:address":"14230 Magnolia Blvd",
    "sg:city":"Sherman Oaks",
    "sg:classifiers":[
        {
            "category":"Recreation",
            "type":"Entertainment"
        }
    ],
    "sg:phone":"+1 818 986 6832",
    "sg:postcode":"91423",
    "sg:province":"CA",
    "sg:tags":[
        "amusement"
    ],
    "wof:name":"West Coast Baseball School",
    "wof:placetype":"venue"
},
  "geometry": {"coordinates":[-118.442992,34.164784],"type":"Point"}
}