{
  "type": "Feature",
  "properties": {
    "addr:full":"2675 Customhouse Ct San Diego CA 92154",
    "addr:housenumber":"2675",
    "addr:postcode":"92154",
    "addr:street":"Customhouse Ct",
    "iso:country":"US",
    "sg:address":"2675 Customhouse Ct",
    "sg:city":"San Diego",
    "sg:classifiers":[
        {
            "category":"Manufacturing",
            "subcategory":"Tools & Machinery",
            "type":"Manufacturing & Wholesale Goods"
        }
    ],
    "sg:phone":"+1 619 661 6688",
    "sg:postcode":"92154",
    "sg:province":"CA",
    "sg:tags":[
        "mfg"
    ],
    "wof:name":"Comair Holdings Corp",
    "wof:placetype":"venue"
},
  "geometry": {"coordinates":[-116.944754,32.551737],"type":"Point"}
}