{
  "type": "Feature",
  "properties": {
    "addr:full":"2645 Maricopa St Torrance CA 90503",
    "addr:housenumber":"2645",
    "addr:postcode":"90503",
    "addr:street":"Maricopa St",
    "iso:country":"US",
    "sg:address":"2645 Maricopa St",
    "sg:city":"Torrance",
    "sg:classifiers":[
        {
            "category":"Manufacturing",
            "subcategory":"Metals",
            "type":"Manufacturing & Wholesale Goods"
        }
    ],
    "sg:phone":"+1 310 787 4530",
    "sg:postcode":"90503",
    "sg:province":"CA",
    "sg:tags":[
        "hardware",
        "hardware-wholesale",
        "manufacturer"
    ],
    "wof:name":"Sigma West Corp",
    "wof:placetype":"venue"
},
  "geometry": {"coordinates":[-118.332624,33.83934],"type":"Point"}
}