{
  "type": "Feature",
  "properties": {
    "iso:country":"US",
    "sg:address":"702 Academy Ave",
    "sg:city":"Sanger",
    "sg:classifiers":[
        {
            "category":"Food & Beverages",
            "subcategory":"Bakery",
            "type":"Retail Goods"
        }
    ],
    "sg:phone":"+1 559 875 3003",
    "sg:postcode":"93657",
    "sg:province":"CA",
    "sg:tags":[
        "baker"
    ],
    "wof:name":"Sanger Donuts",
    "wof:placetype":"venue"
},
  "geometry": {"coordinates":[-119.555612,36.705245],"type":"Point"}
}