{
  "type": "Feature",
  "properties": {
    "iso:country":"US",
    "sg:address":"1221 Abbot Kinney Blvd",
    "sg:city":"Venice",
    "sg:classifiers":[
        {
            "category":"Personal",
            "subcategory":"Beauty Salon",
            "type":"Services"
        }
    ],
    "sg:phone":"+1 310 581 1142",
    "sg:postcode":"90291",
    "sg:province":"CA",
    "wof:name":"Slave Hair Salon",
    "wof:placetype":"venue"
},
  "geometry": {"coordinates":[-118.468276,33.991301],"type":"Point"}
}