{
  "type": "Feature",
  "properties": {
    "iso:country":"US",
    "sg:address":"4305 Hacienda Dr",
    "sg:city":"Pleasanton",
    "sg:classifiers":[
        {
            "category":"Manufacturing",
            "subcategory":"Glass & Minerals",
            "type":"Manufacturing & Wholesale Goods"
        }
    ],
    "sg:phone":"+1 925 225 9130",
    "sg:postcode":"94588",
    "sg:province":"CA",
    "sg:tags":[
        "product",
        "mfg"
    ],
    "wof:name":"Glass House",
    "wof:placetype":"venue"
},
  "geometry": {"coordinates":[-121.894124,37.695149],"type":"Point"}
}