{
  "type": "Feature",
  "properties": {
    "iso:country":"US",
    "sg:address":"4877 Arrow Hwy",
    "sg:city":"Montclair",
    "sg:classifiers":[
        {
            "category":"Shopping",
            "subcategory":"Crafts & Fabrics",
            "type":"Retail Goods"
        }
    ],
    "sg:phone":"+1 909 624 8541",
    "sg:postcode":"91763",
    "sg:province":"CA",
    "sg:tags":[
        "shop"
    ],
    "wof:name":"Big Y Yardage Outlet",
    "wof:placetype":"venue"
},
  "geometry": {"coordinates":[-117.70069700000001,34.09243],"type":"Point"}
}