{
  "type": "Feature",
  "properties": {
    "addr:full":"500 Hotel Cir N San Diego CA 92108",
    "addr:housenumber":"500",
    "addr:postcode":"92108",
    "addr:street":"Hotel Cir N",
    "iso:country":"US",
    "sg:address":"500 Hotel Cir N",
    "sg:city":"San Diego",
    "sg:classifiers":[
        {
            "category":"Restaurant",
            "type":"Food & Drink"
        }
    ],
    "sg:phone":"+1 619 291 7131",
    "sg:postcode":"92108",
    "sg:province":"CA",
    "sg:tags":[
        "new",
        "seafood",
        "american"
    ],
    "sg:website":"www.trellisesgrille.com/",
    "wof:name":"Trellises Garden Grille",
    "wof:placetype":"venue"
},
  "geometry": {"coordinates":[-117.16627099999999,32.763478],"type":"Point"}
}