{
  "type": "Feature",
  "properties": {
    "iso:country":"US",
    "sg:address":"910 S Los Angeles St",
    "sg:city":"Los Angeles",
    "sg:classifiers":[
        {
            "category":"Wholesale",
            "subcategory":"Apparel",
            "type":"Manufacturing & Wholesale Goods"
        },
        {
            "category":"Shopping",
            "subcategory":"Clothing, Apparel, & Fashions",
            "type":"Retail Goods"
        }
    ],
    "sg:phone":"+1 213 896 0006",
    "sg:postcode":"90015",
    "sg:province":"CA",
    "wof:name":"Polo Jeans Co",
    "wof:placetype":"venue"
},
  "geometry": {"coordinates":[-118.25565,34.03963],"type":"Point"}
}