{
  "type": "Feature",
  "properties": {
    "iso:country":"US",
    "sg:address":"1902 Comstock Ave",
    "sg:city":"Los Angeles",
    "sg:classifiers":[
        {
            "category":"Professional",
            "type":"Services"
        }
    ],
    "sg:phone":"+1 310 552 1877",
    "sg:postcode":"90025",
    "sg:province":"CA",
    "sg:tags":[
        "establishment"
    ],
    "wof:name":"Rollercoaster",
    "wof:placetype":"venue"
},
  "geometry": {"coordinates":[-118.421148,34.055436],"type":"Point"}
}