{
  "type": "Feature",
  "properties": {
    "addr:full":"17768 Strawberry Ln Anderson CA 96007",
    "addr:housenumber":"17768",
    "addr:postcode":"96007",
    "addr:street":"Strawberry Ln",
    "iso:country":"US",
    "sg:address":"17768 Strawberry Ln",
    "sg:city":"Anderson",
    "sg:classifiers":[
        {
            "category":"Professional",
            "type":"Services"
        }
    ],
    "sg:phone":"+1 530 365 8859",
    "sg:postcode":"96007",
    "sg:province":"CA",
    "wof:name":"Flynn Paul & Shirley",
    "wof:placetype":"venue"
},
  "geometry": {"coordinates":[-122.395904,40.476316],"type":"Point"}
}