{
  "type": "Feature",
  "properties": {
    "iso:country":"US",
    "sg:address":"11235 Woodrush Ln",
    "sg:city":"San Diego",
    "sg:classifiers":[
        {
            "category":"Professional",
            "type":"Services"
        }
    ],
    "sg:phone":"+1 858 451 5588",
    "sg:postcode":"92128",
    "sg:province":"CA",
    "wof:name":"Rusty Sun",
    "wof:placetype":"venue"
},
  "geometry": {"coordinates":[-117.08527,32.976937],"type":"Point"}
}