{
  "type": "Feature",
  "properties": {
    "addr:full":"11235 Woodrush Ln San Diego CA 92128",
    "addr:housenumber":"11235",
    "addr:postcode":"92128",
    "addr:street":"Woodrush Ln",
    "iso:country":"US",
    "sg:address":"11235 Woodrush Ln",
    "sg:city":"San Diego",
    "sg:classifiers":[
        {
            "category":"Professional",
            "type":"Services"
        }
    ],
    "sg:phone":"+1 858 451 5588",
    "sg:postcode":"92128",
    "sg:province":"CA",
    "wof:name":"Rusty Sun",
    "wof:placetype":"venue"
},
  "geometry": {"coordinates":[-117.08526999999999,32.976937],"type":"Point"}
}