{
  "type": "Feature",
  "properties": {
    "addr:full":"3882 Crenshaw Blvd Los Angeles CA 90008",
    "addr:housenumber":"3882",
    "addr:postcode":"90008",
    "addr:street":"Crenshaw Blvd",
    "iso:country":"US",
    "sg:address":"3882 Crenshaw Blvd",
    "sg:city":"Los Angeles",
    "sg:classifiers":[
        {
            "category":"Shopping",
            "subcategory":"Jewelry",
            "type":"Retail Goods"
        }
    ],
    "sg:phone":"+1 323 293 3351",
    "sg:postcode":"90008",
    "sg:province":"CA",
    "sg:tags":[
        "jeweler"
    ],
    "wof:name":"Nojima Jewelers",
    "wof:placetype":"venue"
},
  "geometry": {"coordinates":[-118.334807,34.015993],"type":"Point"}
}