{
  "type": "Feature",
  "properties": {
    "iso:country":"US",
    "sg:address":"17521 Jersey Ave",
    "sg:city":"Artesia",
    "sg:classifiers":[
        {
            "category":"Building & Trades",
            "subcategory":"Landscaping Services",
            "type":"Services"
        }
    ],
    "sg:phone":"+1 562 860 9771",
    "sg:postcode":"90701",
    "sg:province":"CA",
    "wof:name":"C H Gardening Service",
    "wof:placetype":"venue"
},
  "geometry": {"coordinates":[-118.085297,33.871353],"type":"Point"}
}