{
  "type": "Feature",
  "properties": {
    "addr:full":"388 9th St Oakland CA 94607",
    "addr:housenumber":"388",
    "addr:postcode":"94607",
    "addr:street":"9Th St",
    "iso:country":"US",
    "sg:address":"388 9th St",
    "sg:city":"Oakland",
    "sg:classifiers":[
        {
            "category":"Banks & Credit Unions",
            "subcategory":"Bank",
            "type":"Services"
        }
    ],
    "sg:phone":"+1 510 452 9188",
    "sg:postcode":"94607",
    "sg:province":"CA",
    "sg:tags":[
        "loan",
        "real estate"
    ],
    "wof:name":"Far East Mortgage Co",
    "wof:placetype":"venue"
},
  "geometry": {"coordinates":[-122.271339,37.800113],"type":"Point"}
}