{
  "type": "Feature",
  "properties": {
    "addr:full":"1639 Harbor Crest Cir Corona Del Mar CA 92625",
    "addr:housenumber":"1639",
    "addr:postcode":"92625",
    "addr:street":"Harbor Crest Cir",
    "iso:country":"US",
    "sg:address":"1639 Harbor Crest Cir",
    "sg:city":"Corona Del Mar",
    "sg:classifiers":[
        {
            "category":"Professional",
            "type":"Services"
        }
    ],
    "sg:phone":"+1 949 640 0128",
    "sg:postcode":"92625",
    "sg:province":"CA",
    "wof:name":"Conway Peripherals Inc",
    "wof:placetype":"venue"
},
  "geometry": {"coordinates":[-117.85429499999999,33.606617],"type":"Point"}
}