{
  "type": "Feature",
  "properties": {
    "addr:full":"3978 W 6th Street Los Angeles CA 90020",
    "addr:housenumber":"3978",
    "addr:postcode":"90020",
    "addr:street":"W 6Th Street",
    "iso:country":"US",
    "sg:address":"3978 W 6th Street",
    "sg:city":"Los Angeles",
    "sg:classifiers":[
        {
            "category":"Professional",
            "type":"Services"
        }
    ],
    "sg:phone":"+1 213 738 9100",
    "sg:postcode":"90020",
    "sg:province":"CA",
    "sg:website":"www.lafingerprinting.com",
    "wof:name":"A Authorized Fingerprinting & Photos",
    "wof:placetype":"venue"
},
  "geometry": {"coordinates":[-118.309855,34.063512],"type":"Point"}
}