{
  "type": "Feature",
  "properties": {
    "addr:full":"649 W Mission Ave Escondido CA 92025",
    "addr:housenumber":"649",
    "addr:postcode":"92025",
    "addr:street":"W Mission Ave",
    "iso:country":"US",
    "sg:address":"649 W Mission Ave",
    "sg:city":"Escondido",
    "sg:classifiers":[
        {
            "category":"Insurance",
            "subcategory":"Insurance Agent",
            "type":"Services"
        }
    ],
    "sg:phone":"+1 619 426 2020",
    "sg:postcode":"92025",
    "sg:province":"CA",
    "wof:name":"20/20 Insurance",
    "wof:placetype":"venue"
},
  "geometry": {"coordinates":[-117.096425,33.126834],"type":"Point"}
}