{
  "type": "Feature",
  "properties": {
    "iso:country":"US",
    "sg:address":"365 Van Buren Ave",
    "sg:city":"Oakland",
    "sg:classifiers":[
        {
            "category":"Real Estate",
            "subcategory":"Real Estate Agent",
            "type":"Services"
        }
    ],
    "sg:phone":"+1 510 444 2314",
    "sg:postcode":"94610",
    "sg:province":"CA",
    "sg:website":"http://www.linneagrebmeier.com",
    "wof:name":"Manhattan Real Estate",
    "wof:placetype":"venue"
},
  "geometry": {"coordinates":[-122.25481499999999,37.810615],"type":"Point"}
}