{
  "type": "Feature",
  "properties": {
    "iso:country":"US",
    "sg:address":"22030 Sherman Way Ste 202",
    "sg:city":"Canoga Park",
    "sg:classifiers":[
        {
            "category":"Health Services",
            "subcategory":"Doctor",
            "type":"Services"
        }
    ],
    "sg:phone":"+1 818 887 0260",
    "sg:postcode":"91303",
    "sg:province":"CA",
    "sg:tags":[
        "surgeon",
        "oral"
    ],
    "wof:name":"Boyce James S DDS",
    "wof:placetype":"venue"
},
  "geometry": {"coordinates":[-118.60700199999999,34.201],"type":"Point"}
}