{
  "type": "Feature",
  "properties": {
    "iso:country":"US",
    "sg:address":"10372 Stanford Ave",
    "sg:city":"Garden Grove",
    "sg:classifiers":[
        {
            "category":"Retail",
            "subcategory":"Repair Shop",
            "type":"Services"
        }
    ],
    "sg:phone":"+1 714 590 0157",
    "sg:postcode":"92840",
    "sg:province":"CA",
    "sg:tags":[
        "equipment",
        "printing"
    ],
    "sg:website":"www.goacevac.com",
    "wof:name":"Ace Machinery & Repair",
    "wof:placetype":"venue"
},
  "geometry": {"coordinates":[-117.95108500000001,33.777642],"type":"Point"}
}