{
  "type": "Feature",
  "properties": {
    "addr:full":"42185 Washington St Palm Desert CA 92211",
    "addr:housenumber":"42185",
    "addr:postcode":"92211",
    "addr:street":"Washington St",
    "iso:country":"US",
    "sg:address":"42185 Washington St",
    "sg:city":"Palm Desert",
    "sg:classifiers":[
        {
            "category":"Retail",
            "subcategory":"Car Wash",
            "type":"Services"
        }
    ],
    "sg:phone":"+1 760 360 4990",
    "sg:postcode":"92211",
    "sg:province":"CA",
    "sg:tags":[
        "polishing",
        "washing"
    ],
    "wof:name":"Hand Car Wash Of Palm Desert",
    "wof:placetype":"venue"
},
  "geometry": {"coordinates":[-116.303935,33.741867],"type":"Point"}
}