{
  "type": "Feature",
  "properties": {
    "iso:country":"US",
    "sg:address":"1328 N Sierra Vista Ave Ste B",
    "sg:city":"Fresno",
    "sg:classifiers":[
        {
            "category":"Personal",
            "type":"Services"
        },
        {
            "category":"Professional",
            "subcategory":"Business Services",
            "type":"Services"
        },
        {
            "category":"Shopping",
            "subcategory":"Discount & Variety Stores",
            "type":"Retail Goods"
        }
    ],
    "sg:phone":"+1 559 456 8084",
    "sg:postcode":"93703",
    "sg:province":"CA",
    "sg:tags":[
        "liquidation",
        "liquidator",
        "auction",
        "estates-sales",
        "auctioneer",
        "appraisal",
        "appraiser"
    ],
    "sg:website":"http://www.bairdauctions.com",
    "wof:name":"Baird Auction And Appraisals",
    "wof:placetype":"venue"
},
  "geometry": {"coordinates":[-119.740894,36.760006],"type":"Point"}
}