{
  "type": "Feature",
  "properties": {
    "iso:country":"US",
    "sg:address":"625 E Mission Rd",
    "sg:city":"Fallbrook",
    "sg:classifiers":[
        {
            "category":"Shopping",
            "subcategory":"Computers & Home Electronics",
            "type":"Retail Goods"
        }
    ],
    "sg:phone":"+1 760 451 0010",
    "sg:postcode":"92028",
    "sg:province":"CA",
    "wof:name":"Satellite Source The",
    "wof:placetype":"venue"
},
  "geometry": {"coordinates":[-117.24536500000001,33.384452],"type":"Point"}
}