{
  "type": "Feature",
  "properties": {
    "addr:full":"971 Park Center Dr Rm Equip Vista CA 92081",
    "addr:housenumber":"971",
    "addr:postcode":"92081",
    "addr:street":"Park Center Dr;Equip",
    "iso:country":"US",
    "sg:address":"971 Park Center Dr Rm Equip",
    "sg:city":"Vista",
    "sg:classifiers":[
        {
            "category":"Manufacturing",
            "subcategory":"Wood Products",
            "type":"Manufacturing & Wholesale Goods"
        },
        {
            "category":"Home & Garden",
            "subcategory":"Furniture",
            "type":"Retail Goods"
        },
        {
            "category":"Building & Trades",
            "subcategory":"Construction",
            "type":"Services"
        },
        {
            "category":"Wholesale",
            "subcategory":"Home Furnishings",
            "type":"Manufacturing & Wholesale Goods"
        }
    ],
    "sg:phone":"+1 760 598 3227",
    "sg:postcode":"92081",
    "sg:province":"CA",
    "sg:tags":[
        "equipment-wholesale",
        "kitchen",
        "equipment-household",
        "maker",
        "cabinet",
        "millwork",
        "manufacturer"
    ],
    "sg:website":"http://www.moondesignmfg.com",
    "wof:name":"Moon Design Manufacturing",
    "wof:placetype":"venue"
},
  "geometry": {"coordinates":[-117.228533,33.14403],"type":"Point"}
}