{
  "type": "Feature",
  "properties": {
    "iso:country":"US",
    "sg:address":"22430 Sylvan St",
    "sg:city":"Woodland Hills",
    "sg:classifiers":[
        {
            "category":"Real Estate",
            "subcategory":"Real Estate Agent",
            "type":"Services"
        }
    ],
    "sg:phone":"+1 818 346 1408",
    "sg:postcode":"91367",
    "sg:province":"CA",
    "wof:name":"Staback  Rudolph R & Grace",
    "wof:placetype":"venue"
},
  "geometry": {"coordinates":[-118.617819,34.184527],"type":"Point"}
}