{
  "type": "Feature",
  "properties": {
    "iso:country":"US",
    "sg:address":"375 S Mayfair Ave",
    "sg:city":"Daly City",
    "sg:classifiers":[
        {
            "category":"Professional",
            "subcategory":"Lawyer & Legal Services",
            "type":"Services"
        }
    ],
    "sg:phone":"+1 650 992 9245",
    "sg:postcode":"94015",
    "sg:province":"CA",
    "sg:tags":[
        "attorney"
    ],
    "wof:name":"Andrew Grant",
    "wof:placetype":"venue"
},
  "geometry": {"coordinates":[-122.484063,37.701283],"type":"Point"}
}