{
  "type": "Feature",
  "properties": {
    "iso:country":"US",
    "sg:address":"15736 Los Gatos Blvd",
    "sg:city":"Los Gatos",
    "sg:classifiers":[
        {
            "category":"Home & Garden",
            "subcategory":"Household Appliances",
            "type":"Retail Goods"
        },
        {
            "category":"Building & Trades",
            "subcategory":"Construction",
            "type":"Services"
        }
    ],
    "sg:phone":"+1 408 358 8800",
    "sg:postcode":"95032",
    "sg:province":"CA",
    "sg:tags":[
        "contractor"
    ],
    "sg:website":"www.tradewindspa.com",
    "wof:name":"Tradewind Spas",
    "wof:placetype":"venue"
},
  "geometry": {"coordinates":[-121.96066500000001,37.239771],"type":"Point"}
}