{
  "type": "Feature",
  "properties": {
    "addr:full":"672 S Vermont Ave Los Angeles CA 90005",
    "addr:housenumber":"672",
    "addr:postcode":"90005",
    "addr:street":"S Vermont Ave",
    "iso:country":"US",
    "sg:address":"672 S Vermont Ave",
    "sg:city":"Los Angeles",
    "sg:classifiers":[
        {
            "category":"Restaurant",
            "type":"Food & Drink"
        }
    ],
    "sg:phone":"+1 213 387 0859",
    "sg:postcode":"90005",
    "sg:province":"CA",
    "wof:name":"Jumak 74",
    "wof:placetype":"venue"
},
  "geometry": {"coordinates":[-118.29155900000001,34.060065],"type":"Point"}
}