{
  "type": "Feature",
  "properties": {
    "iso:country":"US",
    "sg:address":"427 N Main St",
    "sg:city":"Sebastopol",
    "sg:classifiers":[
        {
            "category":"Professional",
            "subcategory":"Art Services",
            "type":"Services"
        }
    ],
    "sg:phone":"+1 707 829 9001",
    "sg:postcode":"95472",
    "sg:province":"CA",
    "sg:tags":[
        "graphic",
        "designer"
    ],
    "wof:name":"Wavelength Media Inc",
    "wof:placetype":"venue"
},
  "geometry": {"coordinates":[-122.826883,38.406477],"type":"Point"}
}