{
  "type": "Feature",
  "properties": {
    "iso:country":"US",
    "sg:address":"5300 Beach Blvd Ste 110",
    "sg:city":"Buena Park",
    "sg:classifiers":[
        {
            "category":"Restaurant",
            "type":"Food & Drink"
        }
    ],
    "sg:phone":"+1 714 690 1432",
    "sg:postcode":"90621",
    "sg:province":"CA",
    "sg:tags":[
        "fusion",
        "asian"
    ],
    "sg:website":"www.facebook.com/?sk=ff#!/profil...",
    "wof:name":"Little Prince Kids Cafe",
    "wof:placetype":"venue"
},
  "geometry": {"coordinates":[-117.995039,33.883653],"type":"Point"}
}