{
  "type": "Feature",
  "properties": {
    "iso:country":"US",
    "sg:address":"20677 Corsair Blvd",
    "sg:city":"Hayward",
    "sg:classifiers":[
        {
            "category":"Autos & Motor Vehicles",
            "subcategory":"Automobile Sales",
            "type":"Retail Goods"
        },
        {
            "category":"Communications",
            "subcategory":"Film & Video Production",
            "type":"Services"
        },
        {
            "category":"Personal",
            "type":"Services"
        }
    ],
    "sg:phone":"+1 510 670 1392",
    "sg:postcode":"94545",
    "sg:province":"CA",
    "sg:tags":[
        "towing",
        "video/film",
        "car"
    ],
    "sg:website":"www.InterstateServices.com",
    "wof:name":"Interstate Services - Evidence and Auto Transportation",
    "wof:placetype":"venue"
},
  "geometry": {"coordinates":[-122.127785,37.657686],"type":"Point"}
}