{
  "type": "Feature",
  "properties": {
    "iso:country":"US",
    "sg:address":"1000 Chestnut St",
    "sg:city":"San Francisco",
    "sg:classifiers":[
        {
            "category":"Real Estate",
            "subcategory":"Real Estate Operator",
            "type":"Services"
        }
    ],
    "sg:postcode":"94199",
    "sg:province":"CA",
    "sg:tags":[
        "apartment"
    ],
    "wof:name":"Trinity Management",
    "wof:placetype":"venue"
},
  "geometry": {"coordinates":[-122.42012099999999,37.803133],"type":"Point"}
}