{
  "type": "Feature",
  "properties": {
    "iso:country":"US",
    "sg:address":"10 S Kellogg Ave",
    "sg:city":"Goleta",
    "sg:classifiers":[
        {
            "category":"Professional",
            "subcategory":"Engineering",
            "type":"Services"
        }
    ],
    "sg:phone":"+1 805 683 4692",
    "sg:postcode":"93117",
    "sg:province":"CA",
    "sg:tags":[
        "general",
        "contractor"
    ],
    "wof:name":"Lash Construction",
    "wof:placetype":"venue"
},
  "geometry": {"coordinates":[-119.820385,34.438765],"type":"Point"}
}