{
  "type": "Feature",
  "properties": {
    "addr:full":"4168 Pepper Tree Ln San Jose CA 95127",
    "addr:housenumber":"4168",
    "addr:postcode":"95127",
    "addr:street":"Pepper Tree Ln",
    "iso:country":"US",
    "sg:address":"4168 Pepper Tree Ln",
    "sg:city":"San Jose",
    "sg:classifiers":[
        {
            "category":"Bars & Pubs",
            "type":"Food & Drink"
        }
    ],
    "sg:phone":"+1 408 254 8472",
    "sg:postcode":"95127",
    "sg:province":"CA",
    "wof:name":"Fat Cat Bar & Grill",
    "wof:placetype":"venue"
},
  "geometry": {"coordinates":[-121.82641599999999,37.390734],"type":"Point"}
}