{
  "type": "Feature",
  "properties": {
    "addr:full":"183 E Glenarm St Pasadena CA 91105",
    "addr:housenumber":"183",
    "addr:postcode":"91105",
    "addr:street":"E Glenarm St",
    "iso:country":"US",
    "sg:address":"183 E Glenarm St",
    "sg:city":"Pasadena",
    "sg:classifiers":[
        {
            "category":"Restaurant",
            "type":"Food & Drink"
        }
    ],
    "sg:phone":"+1 626 799 5252",
    "sg:postcode":"91105",
    "sg:province":"CA",
    "wof:name":"Dickenson West Caterers-Derek's Bistro",
    "wof:placetype":"venue"
},
  "geometry": {"coordinates":[-118.146164,34.127565],"type":"Point"}
}