{
  "type": "Feature",
  "properties": {
    "addr:full":"6668 Owens Dr Pleasanton CA 94588",
    "addr:housenumber":"6668",
    "addr:postcode":"94588",
    "addr:street":"Owens Dr",
    "iso:country":"US",
    "sg:address":"6668 Owens Dr",
    "sg:city":"Pleasanton",
    "sg:classifiers":[
        {
            "category":"Health Services",
            "subcategory":"Health Practitioner",
            "type":"Services"
        }
    ],
    "sg:phone":"+1 925 621 2200",
    "sg:postcode":"94588",
    "sg:province":"CA",
    "sg:tags":[
        "therapist",
        "physical"
    ],
    "sg:website":"www.bodymax.net",
    "wof:name":"Bodymax Physical Therapy",
    "wof:placetype":"venue"
},
  "geometry": {"coordinates":[-121.90779999999999,37.697233],"type":"Point"}
}