{
  "type": "Feature",
  "properties": {
    "iso:country":"US",
    "sg:address":"11 Sunrise Ave",
    "sg:city":"Mill Valley",
    "sg:classifiers":[
        {
            "category":"Professional",
            "subcategory":"Business Services",
            "type":"Services"
        }
    ],
    "sg:phone":"+1 415 381 2526",
    "sg:postcode":"94941",
    "sg:province":"CA",
    "sg:tags":[
        "furniture"
    ],
    "wof:name":"Cowan Design Company",
    "wof:placetype":"venue"
},
  "geometry": {"coordinates":[-122.540356,37.898262],"type":"Point"}
}