{
  "type": "Feature",
  "properties": {
    "addr:full":"510 S Ardmore Avenue Los Angeles CA 90020",
    "addr:housenumber":"510",
    "addr:postcode":"90020",
    "addr:street":"S Ardmore Avenue",
    "iso:country":"US",
    "sg:address":"510 S Ardmore Avenue",
    "sg:city":"Los Angeles",
    "sg:classifiers":[
        {
            "category":"Autos & Motor Vehicles",
            "subcategory":"Automobile Sales",
            "type":"Retail Goods"
        }
    ],
    "sg:phone":"+1 323 965 8282",
    "sg:postcode":"90020",
    "sg:province":"CA",
    "sg:tags":[
        "limo"
    ],
    "wof:name":"Gagopa Service",
    "wof:placetype":"venue"
},
  "geometry": {"coordinates":[-118.301582,34.065191],"type":"Point"}
}