{
  "type": "Feature",
  "properties": {
    "addr:full":"617 N 8th St Lompoc CA 93436",
    "addr:housenumber":"617",
    "addr:postcode":"93436",
    "addr:street":"N 8Th St",
    "iso:country":"US",
    "sg:address":"617 N 8th St",
    "sg:city":"Lompoc",
    "sg:classifiers":[
        {
            "category":"Building & Trades",
            "subcategory":"Construction",
            "type":"Services"
        }
    ],
    "sg:phone":"+1 805 735 9797",
    "sg:postcode":"93436",
    "sg:province":"CA",
    "sg:tags":[
        "water",
        "well",
        "drilling"
    ],
    "wof:name":"A & A Pump & Well",
    "wof:placetype":"venue"
},
  "geometry": {"coordinates":[-120.439374,34.647583],"type":"Point"}
}