{
  "type": "Feature",
  "properties": {
    "addr:full":"3300 Webster Street Suite 1202 Oakland CA 94609",
    "addr:housenumber":"3300",
    "addr:postcode":"94609",
    "addr:street":"Webster Street Suite 1202",
    "iso:country":"US",
    "sg:address":"3300 Webster Street Suite 1202",
    "sg:city":"Oakland",
    "sg:classifiers":[
        {
            "category":"Health Services",
            "subcategory":"Doctor",
            "type":"Services"
        }
    ],
    "sg:phone":"+1 510 433 1040",
    "sg:postcode":"94609",
    "sg:province":"CA",
    "wof:name":"Usem Michael Dr",
    "wof:placetype":"venue"
},
  "geometry": {"coordinates":[-122.262114,37.821201],"type":"Point"}
}