{
  "type": "Feature",
  "properties": {
    "addr:full":"335 E Albertoni Carson CA 90746",
    "addr:housenumber":"335",
    "addr:postcode":"90746",
    "addr:street":"E Albertoni",
    "iso:country":"US",
    "sg:address":"335 E Albertoni",
    "sg:city":"Carson",
    "sg:classifiers":[
        {
            "category":"Food & Beverages",
            "subcategory":"Ethnic Foods",
            "type":"Retail Goods"
        }
    ],
    "sg:phone":"+1 310 324 5317",
    "sg:postcode":"90746",
    "sg:province":"CA",
    "sg:tags":[
        "soul"
    ],
    "sg:website":"www.vennimacsmm.com/index.html",
    "wof:name":"M & M Soul Food",
    "wof:placetype":"venue"
},
  "geometry": {"coordinates":[-118.27155,33.871481],"type":"Point"}
}