{
  "type": "Feature",
  "properties": {
    "iso:country":"US",
    "sg:address":"2000 S Grove Ave",
    "sg:city":"Ontario",
    "sg:classifiers":[
        {
            "category":"Wholesale",
            "subcategory":"Auto Parts",
            "type":"Manufacturing & Wholesale Goods"
        }
    ],
    "sg:phone":"+1 909 923 8300",
    "sg:postcode":"91761",
    "sg:province":"CA",
    "sg:tags":[
        "automobile",
        "supply"
    ],
    "sg:website":"www.excaliburwheel.com",
    "wof:name":"Excalibur Wheel",
    "wof:placetype":"venue"
},
  "geometry": {"coordinates":[-117.628599,34.040556],"type":"Point"}
}