{
  "type": "Feature",
  "properties": {
    "addr:full":"417 Central Ave Santa Maria CA 93454",
    "addr:housenumber":"417",
    "addr:postcode":"93454",
    "addr:street":"Central Ave",
    "iso:country":"US",
    "sg:address":"417 Central Ave",
    "sg:city":"Santa Maria",
    "sg:classifiers":[
        {
            "category":"Manufacturing",
            "subcategory":"Textiles",
            "type":"Manufacturing & Wholesale Goods"
        }
    ],
    "sg:phone":"+1 805 922 1295",
    "sg:postcode":"93454",
    "sg:province":"CA",
    "sg:tags":[
        "dyed",
        "yarn"
    ],
    "wof:name":"Drop Spindle",
    "wof:placetype":"venue"
},
  "geometry": {"coordinates":[-120.43025900000001,34.947982],"type":"Point"}
}