{
  "type": "Feature",
  "properties": {
    "addr:full":"1129 Main St Delano CA 93215",
    "addr:housenumber":"1129",
    "addr:postcode":"93215",
    "addr:street":"Main St",
    "iso:country":"US",
    "sg:address":"1129 Main St",
    "sg:city":"Delano",
    "sg:classifiers":[
        {
            "category":"Shopping",
            "subcategory":"Jewelry",
            "type":"Retail Goods"
        }
    ],
    "sg:phone":"+1 661 725 1126",
    "sg:postcode":"93215",
    "sg:province":"CA",
    "sg:tags":[
        "designer"
    ],
    "wof:name":"Katy's Jewelry",
    "wof:placetype":"venue"
},
  "geometry": {"coordinates":[-119.24624799999999,35.771311],"type":"Point"}
}