{
  "type": "Feature",
  "properties": {
    "iso:country":"US",
    "sg:address":"300 Sill Rd",
    "sg:city":"Watsonville",
    "sg:classifiers":[
        {
            "category":"Education",
            "subcategory":"School",
            "type":"Public Place"
        }
    ],
    "sg:phone":"+1 831 728 6371",
    "sg:postcode":"95076",
    "sg:province":"CA",
    "wof:name":"Hall District Elementary Schl",
    "wof:placetype":"venue"
},
  "geometry": {"coordinates":[-121.72255,36.866197],"type":"Point"}
}