{
  "type": "Feature",
  "properties": {
    "addr:full":"1335 Chrysolite Ave Mentone CA 92359",
    "addr:housenumber":"1335",
    "addr:postcode":"92359",
    "addr:street":"Chrysolite Ave",
    "iso:country":"US",
    "sg:address":"1335 Chrysolite Ave",
    "sg:city":"Mentone",
    "sg:classifiers":[
        {
            "category":"Building & Trades",
            "subcategory":"Plumbing",
            "type":"Services"
        }
    ],
    "sg:phone":"+1 909 794 2611",
    "sg:postcode":"92359",
    "sg:province":"CA",
    "wof:name":"AAA Plumbing Heating & Air Conditioning Mntnrdlnds",
    "wof:placetype":"venue"
},
  "geometry": {"coordinates":[-117.13800000000001,34.072498],"type":"Point"}
}