{
  "type": "Feature",
  "properties": {
    "iso:country":"US",
    "sg:address":"521 N Lake Blvd",
    "sg:city":"Tahoe City",
    "sg:classifiers":[
        {
            "category":"Restaurant",
            "type":"Food & Drink"
        }
    ],
    "sg:phone":"+1 530 581 1416",
    "sg:postcode":"96145",
    "sg:province":"CA",
    "sg:tags":[
        "eating"
    ],
    "wof:name":"Fiamma",
    "wof:placetype":"venue"
},
  "geometry": {"coordinates":[-120.142506,39.169792],"type":"Point"}
}