{
  "type": "Feature",
  "properties": {
    "addr:full":"1649 E Valley Pkwy Escondido CA 92027",
    "addr:housenumber":"1649",
    "addr:postcode":"92027",
    "addr:street":"E Valley Pkwy",
    "iso:country":"US",
    "sg:address":"1649 E Valley Pkwy",
    "sg:city":"Escondido",
    "sg:classifiers":[
        {
            "category":"Personal",
            "subcategory":"Beauty Salon",
            "type":"Services"
        }
    ],
    "sg:phone":"+1 760 489 5971",
    "sg:postcode":"92027",
    "sg:province":"CA",
    "wof:name":"Nice Cut",
    "wof:placetype":"venue"
},
  "geometry": {"coordinates":[-117.05783599999999,33.134605],"type":"Point"}
}