{
  "type": "Feature",
  "properties": {
    "addr:full":"11081 Missouri Ave Los Angeles CA 90025",
    "addr:housenumber":"11081",
    "addr:postcode":"90025",
    "addr:street":"Missouri Ave",
    "iso:country":"US",
    "sg:address":"11081 Missouri Ave",
    "sg:city":"Los Angeles",
    "sg:classifiers":[
        {
            "category":"Health Services",
            "subcategory":"Health Practitioner",
            "type":"Services"
        }
    ],
    "sg:phone":"+1 310 473 3855",
    "sg:postcode":"90025",
    "sg:province":"CA",
    "sg:tags":[
        "psychotherapist"
    ],
    "wof:name":"Bodymind Institute",
    "wof:placetype":"venue"
},
  "geometry": {"coordinates":[-118.441243,34.044847],"type":"Point"}
}