{
  "type": "Feature",
  "properties": {
    "iso:country":"US",
    "sg:address":"14364 Ventura Blvd",
    "sg:city":"Sherman Oaks",
    "sg:classifiers":[
        {
            "category":"Personal",
            "subcategory":"Tanning Parlor",
            "type":"Services"
        }
    ],
    "sg:phone":"+1 818 784 8834",
    "sg:postcode":"91423",
    "sg:province":"CA",
    "wof:name":"Le Beach Club",
    "wof:placetype":"venue"
},
  "geometry": {"coordinates":[-118.44549499999999,34.150366],"type":"Point"}
}