{
  "type": "Feature",
  "properties": {
    "iso:country":"US",
    "sg:address":"18368 Grenache Rose Way",
    "sg:city":"Ramona",
    "sg:classifiers":[
        {
            "category":"Retail",
            "subcategory":"Animal Services",
            "type":"Services"
        }
    ],
    "sg:phone":"+1 760 789 3659",
    "sg:postcode":"92065",
    "sg:province":"CA",
    "sg:tags":[
        "horse",
        "training"
    ],
    "wof:name":"Four Lakes Arabians",
    "wof:placetype":"venue"
},
  "geometry": {"coordinates":[-116.935316,33.018425],"type":"Point"}
}