{
  "type": "Feature",
  "properties": {
    "addr:full":"1505 Louisiana St Vallejo CA 94590",
    "addr:housenumber":"1505",
    "addr:postcode":"94590",
    "addr:street":"Louisiana St",
    "iso:country":"US",
    "sg:address":"1505 Louisiana St",
    "sg:city":"Vallejo",
    "sg:classifiers":[
        {
            "category":"Shopping",
            "type":"Retail Goods"
        }
    ],
    "sg:phone":"+1 707 558 0808",
    "sg:postcode":"94590",
    "sg:province":"CA",
    "sg:tags":[
        "metaphysical",
        "supply"
    ],
    "wof:name":"Red Raven",
    "wof:placetype":"venue"
},
  "geometry": {"coordinates":[-122.23818199999999,38.108092],"type":"Point"}
}