{
  "type": "Feature",
  "properties": {
    "addr:full":"4440 W Shaw Ave Fresno CA 93722",
    "addr:housenumber":"4440",
    "addr:postcode":"93722",
    "addr:street":"W Shaw Ave",
    "iso:country":"US",
    "sg:address":"4440 W Shaw Ave",
    "sg:city":"Fresno",
    "sg:classifiers":[
        {
            "category":"Shopping",
            "subcategory":"Crafts & Fabrics",
            "type":"Retail Goods"
        }
    ],
    "sg:phone":"+1 559 436 1810",
    "sg:postcode":"93722",
    "sg:province":"CA",
    "sg:tags":[
        "shop"
    ],
    "sg:website":"www.jo-ann.com",
    "wof:name":"Jo-Ann Fabrics & Crafts",
    "wof:placetype":"venue"
},
  "geometry": {"coordinates":[-119.873516,36.808306],"type":"Point"}
}