{
  "type": "Feature",
  "properties": {
    "addr:full":"861 Wharf St Richmond CA 94804",
    "addr:housenumber":"861",
    "addr:postcode":"94804",
    "addr:street":"Wharf St",
    "iso:country":"US",
    "sg:address":"861 Wharf St",
    "sg:city":"Richmond",
    "sg:classifiers":[
        {
            "category":"Professional",
            "subcategory":"Management & Consulting",
            "type":"Services"
        }
    ],
    "sg:phone":"+1 510 233 8162",
    "sg:postcode":"94804",
    "sg:province":"CA",
    "sg:tags":[
        "passenger",
        "lease",
        "car"
    ],
    "wof:name":"C T Services Inc",
    "wof:placetype":"venue"
},
  "geometry": {"coordinates":[-122.374082,37.919511],"type":"Point"}
}