{
  "type": "Feature",
  "properties": {
    "iso:country":"US",
    "sg:address":"1340 El Camino Real",
    "sg:city":"San Carlos",
    "sg:classifiers":[
        {
            "category":"Restaurant",
            "type":"Food & Drink"
        }
    ],
    "sg:menulink":"http://www.allmenus.com/ca/san-mateo/74219-dominos-pizza/menu/",
    "sg:phone":"+1 650 591 1411",
    "sg:postcode":"94070",
    "sg:province":"CA",
    "sg:tags":[
        "american",
        "wing",
        "pizza"
    ],
    "wof:name":"Domino's Pizza",
    "wof:placetype":"venue"
},
  "geometry": {"coordinates":[-122.24982799999999,37.497875],"type":"Point"}
}