{
  "type": "Feature",
  "properties": {
    "iso:country":"US",
    "sg:address":"25191 Hwy 116",
    "sg:city":"Duncans Mills",
    "sg:classifiers":[
        {
            "category":"Restaurant",
            "type":"Food & Drink"
        }
    ],
    "sg:phone":"+1 707 865 9246",
    "sg:postcode":"95430",
    "sg:province":"CA",
    "wof:name":"Cape Fear Cafe",
    "wof:placetype":"venue"
},
  "geometry": {"coordinates":[-123.053397,38.4598],"type":"Point"}
}