{
  "type": "Feature",
  "properties": {
    "iso:country":"US",
    "sg:address":"12903 Inglewood Ave",
    "sg:city":"Hawthorne",
    "sg:classifiers":[
        {
            "category":"Autos & Motor Vehicles",
            "subcategory":"Automobile Sales",
            "type":"Retail Goods"
        }
    ],
    "sg:phone":"+1 310 219 1890",
    "sg:postcode":"90250",
    "sg:province":"CA",
    "sg:tags":[
        "car",
        "dealer"
    ],
    "wof:name":"Sports Car West",
    "wof:placetype":"venue"
},
  "geometry": {"coordinates":[-118.361254,33.914666],"type":"Point"}
}