{
  "type": "Feature",
  "properties": {
    "iso:country":"US",
    "sg:address":"1821 Wilshire Blvd",
    "sg:city":"Santa Monica",
    "sg:classifiers":[
        {
            "category":"Professional",
            "subcategory":"Accounting & Tax Preparation",
            "type":"Services"
        }
    ],
    "sg:phone":"+1 310 586 7464",
    "sg:postcode":"90403",
    "sg:province":"CA",
    "sg:tags":[
        "accountant"
    ],
    "wof:name":"Fassenfelt Leach & Feist",
    "wof:placetype":"venue"
},
  "geometry": {"coordinates":[-118.48430999999999,34.030522],"type":"Point"}
}