{
  "type": "Feature",
  "properties": {
    "iso:country":"US",
    "sg:address":"2122 9th St",
    "sg:city":"Los Osos",
    "sg:classifiers":[
        {
            "category":"Social Services",
            "type":"Services"
        }
    ],
    "sg:phone":"+1 805 528 6808",
    "sg:postcode":"93402",
    "sg:province":"CA",
    "sg:tags":[
        "counselor",
        "marriage",
        "family"
    ],
    "wof:name":"Sattie Bowman-Blanton",
    "wof:placetype":"venue"
},
  "geometry": {"coordinates":[-120.833174,35.312912],"type":"Point"}
}