{
  "type": "Feature",
  "properties": {
    "addr:full":"1941 Monterey St San Luis Obispo CA 93401",
    "addr:housenumber":"1941",
    "addr:postcode":"93401",
    "addr:street":"Monterey St",
    "iso:country":"US",
    "sg:address":"1941 Monterey St",
    "sg:city":"San Luis Obispo",
    "sg:classifiers":[
        {
            "category":"Travel",
            "subcategory":"Hotels & Motels",
            "type":"Entertainment"
        }
    ],
    "sg:phone":"+1 805 541 1122",
    "sg:postcode":"93401",
    "sg:province":"CA",
    "sg:website":"www.morgansmansions.com",
    "wof:name":"San Luis Creek Lodge",
    "wof:placetype":"venue"
},
  "geometry": {"coordinates":[-120.651341,35.288659],"type":"Point"}
}