{
  "type": "Feature",
  "properties": {
    "iso:country":"US",
    "sg:address":"383 Diablo Rd",
    "sg:city":"Danville",
    "sg:classifiers":[
        {
            "category":"Professional",
            "subcategory":"Lawyer & Legal Services",
            "type":"Services"
        }
    ],
    "sg:phone":"+1 925 838 0884",
    "sg:postcode":"94526",
    "sg:province":"CA",
    "sg:tags":[
        "attorney"
    ],
    "wof:name":"James A Klinkner",
    "wof:placetype":"venue"
},
  "geometry": {"coordinates":[-121.997753,37.822896],"type":"Point"}
}