{
  "type": "Feature",
  "properties": {
    "addr:full":"5630 Boyton Way Sacramento CA 95823",
    "addr:housenumber":"5630",
    "addr:postcode":"95823",
    "addr:street":"Boyton Way",
    "iso:country":"US",
    "sg:address":"5630 Boyton Way",
    "sg:city":"Sacramento",
    "sg:classifiers":[
        {
            "category":"Banks & Credit Unions",
            "subcategory":"Bank",
            "type":"Services"
        }
    ],
    "sg:phone":"+1 916 422 4492",
    "sg:postcode":"95823",
    "sg:province":"CA",
    "sg:tags":[
        "loan",
        "real estate"
    ],
    "wof:name":"United Alpha Mortgage",
    "wof:placetype":"venue"
},
  "geometry": {"coordinates":[-121.43649600000001,38.480699],"type":"Point"}
}