{
  "type": "Feature",
  "properties": {
    "iso:country":"US",
    "sg:address":"2523 California St",
    "sg:city":"San Francisco",
    "sg:classifiers":[
        {
            "category":"Real Estate",
            "subcategory":"Real Estate Agent",
            "type":"Services"
        }
    ],
    "sg:phone":"+1 415 609 3677",
    "sg:postcode":"94115",
    "sg:province":"CA",
    "sg:website":"www.juliereber.com",
    "wof:name":"Julie Reber at Zephyr Real Estate",
    "wof:placetype":"venue"
},
  "geometry": {"coordinates":[-122.435864,37.788671],"type":"Point"}
}