{
  "type": "Feature",
  "properties": {
    "addr:full":"612 National Ave Mountain View CA 94043",
    "addr:housenumber":"612",
    "addr:postcode":"94043",
    "addr:street":"National Ave",
    "iso:country":"US",
    "sg:address":"612 National Ave",
    "sg:city":"Mountain View",
    "sg:classifiers":[
        {
            "category":"Building & Trades",
            "subcategory":"Plumbing",
            "type":"Services"
        }
    ],
    "sg:phone":"+1 650 254 0422",
    "sg:postcode":"94043",
    "sg:province":"CA",
    "sg:tags":[
        "system",
        "radiant",
        "cooling",
        "heating"
    ],
    "sg:website":"www.ecooling.com",
    "wof:name":"Electronic Cooling Solutions",
    "wof:placetype":"venue"
},
  "geometry": {"coordinates":[-122.053603,37.401297],"type":"Point"}
}