{
  "type": "Feature",
  "properties": {
    "addr:full":"1200 C St Galt CA 95632",
    "addr:housenumber":"1200",
    "addr:postcode":"95632",
    "addr:street":"C St",
    "iso:country":"US",
    "sg:address":"1200 C St",
    "sg:city":"Galt",
    "sg:classifiers":[
        {
            "category":"Banks & Credit Unions",
            "subcategory":"Bank",
            "type":"Services"
        }
    ],
    "sg:phone":"+1 209 367 2300",
    "sg:postcode":"95632",
    "sg:province":"CA",
    "wof:name":"F & M Bank",
    "wof:placetype":"venue"
},
  "geometry": {"coordinates":[-121.29701,38.253127],"type":"Point"}
}