{
  "type": "Feature",
  "properties": {
    "addr:full":"3031 W March Ln Stockton CA 95219",
    "addr:housenumber":"3031",
    "addr:postcode":"95219",
    "addr:street":"W March Ln",
    "iso:country":"US",
    "sg:address":"3031 W March Ln",
    "sg:city":"Stockton",
    "sg:classifiers":[
        {
            "category":"Health Services",
            "subcategory":"Doctor",
            "type":"Services"
        }
    ],
    "sg:phone":"+1 209 477 7700",
    "sg:postcode":"95219",
    "sg:province":"CA",
    "sg:tags":[
        "medical"
    ],
    "wof:name":"Laservue Eye Center",
    "wof:placetype":"venue"
},
  "geometry": {"coordinates":[-121.348743,37.984336],"type":"Point"}
}