{
  "type": "Feature",
  "properties": {
    "addr:full":"5015 Birch St Newport Beach CA 92660",
    "addr:housenumber":"5015",
    "addr:postcode":"92660",
    "addr:street":"Birch St",
    "iso:country":"US",
    "sg:address":"5015 Birch St",
    "sg:city":"Newport Beach",
    "sg:classifiers":[
        {
            "category":"Insurance",
            "subcategory":"Hazard Insurance",
            "type":"Services"
        }
    ],
    "sg:phone":"+1 949 757 0270",
    "sg:postcode":"92660",
    "sg:province":"CA",
    "sg:website":"www.rogerstoneinsurance.com",
    "wof:name":"Roger Stone Insurance Agency",
    "wof:placetype":"venue"
},
  "geometry": {"coordinates":[-117.858603,33.666675],"type":"Point"}
}