{
  "type": "Feature",
  "properties": {
    "iso:country":"US",
    "sg:address":"1070 E Cypress St",
    "sg:city":"Covina",
    "sg:classifiers":[
        {
            "category":"Professional",
            "type":"Services"
        }
    ],
    "sg:phone":"+1 626 339 4600",
    "sg:postcode":"91724",
    "sg:province":"CA",
    "wof:name":"Paradise Outdoor Products",
    "wof:placetype":"venue"
},
  "geometry": {"coordinates":[-117.868012,34.095675],"type":"Point"}
}