{
  "type": "Feature",
  "properties": {
    "iso:country":"US",
    "sg:address":"11500 E Mountain View Ave",
    "sg:city":"Selma",
    "sg:classifiers":[
        {
            "category":"Government",
            "subcategory":"Fire Station",
            "type":"Public Place"
        }
    ],
    "sg:phone":"+1 559 896 3378",
    "sg:postcode":"93662",
    "sg:province":"CA",
    "sg:tags":[
        "protection"
    ],
    "wof:name":"Fire Dept",
    "wof:placetype":"venue"
},
  "geometry": {"coordinates":[-119.575144,36.546797],"type":"Point"}
}