{
  "type": "Feature",
  "properties": {
    "addr:full":"530 Ellis St San Francisco CA 94109",
    "addr:housenumber":"530",
    "addr:postcode":"94109",
    "addr:street":"Ellis St",
    "iso:country":"US",
    "sg:address":"530 Ellis St",
    "sg:city":"San Francisco",
    "sg:classifiers":[
        {
            "category":"Food & Beverages",
            "subcategory":"Groceries & Convenience Stores",
            "type":"Retail Goods"
        }
    ],
    "sg:phone":"+1 415 447 8400",
    "sg:postcode":"94109",
    "sg:province":"CA",
    "wof:name":"Macca Halal Market",
    "wof:placetype":"venue"
},
  "geometry": {"coordinates":[-122.414914,37.784741],"type":"Point"}
}