{
  "type": "Feature",
  "properties": {
    "addr:full":"568 E Orangewood Dr Covina CA 91723",
    "addr:housenumber":"568",
    "addr:postcode":"91723",
    "addr:street":"E Orangewood Dr",
    "iso:country":"US",
    "sg:address":"568 E Orangewood Dr",
    "sg:city":"Covina",
    "sg:classifiers":[
        {
            "category":"Real Estate",
            "subcategory":"Real Estate Operator",
            "type":"Services"
        }
    ],
    "sg:phone":"+1 626 332 5472",
    "sg:postcode":"91723",
    "sg:province":"CA",
    "sg:tags":[
        "apartment"
    ],
    "wof:name":"Faris Apts",
    "wof:placetype":"venue"
},
  "geometry": {"coordinates":[-117.88000099999999,34.076679],"type":"Point"}
}