{
  "type": "Feature",
  "properties": {
    "addr:full":"18849 State Rte 65 Bakersfield CA 93308",
    "addr:housenumber":"18849",
    "addr:postcode":"ca 93308",
    "addr:street":"State Rte 65",
    "iso:country":"US",
    "sg:address":"18849 State Rte 65",
    "sg:city":"Bakersfield",
    "sg:classifiers":[
        {
            "category":"Freight",
            "type":"Transportation"
        }
    ],
    "sg:phone":"+1 661 399 8871",
    "sg:postcode":"93308",
    "sg:province":"CA",
    "sg:tags":[
        "trucking"
    ],
    "wof:name":"Pride Transportation",
    "wof:placetype":"venue"
},
  "geometry": {"coordinates":[-119.074654,35.46288],"type":"Point"}
}