{
  "type": "Feature",
  "properties": {
    "addr:full":"14125 Telephone Ave Chino CA 91710",
    "addr:housenumber":"14125",
    "addr:postcode":"91710",
    "addr:street":"Telephone Ave",
    "iso:country":"US",
    "sg:address":"14125 Telephone Ave",
    "sg:city":"Chino",
    "sg:classifiers":[
        {
            "category":"Wholesale",
            "subcategory":"Electrical",
            "type":"Manufacturing & Wholesale Goods"
        }
    ],
    "sg:phone":"+1 951 443 4312",
    "sg:postcode":"91710",
    "sg:province":"CA",
    "sg:tags":[
        "record"
    ],
    "wof:name":"Golden Records",
    "wof:placetype":"venue"
},
  "geometry": {"coordinates":[-117.693243,33.992224],"type":"Point"}
}