{
  "type": "Feature",
  "properties": {
    "addr:full":"4103 N Katy Ave Fresno CA 93722",
    "addr:housenumber":"4103",
    "addr:postcode":"93722",
    "addr:street":"N Katy Ave",
    "iso:country":"US",
    "sg:address":"4103 N Katy Ave",
    "sg:city":"Fresno",
    "sg:classifiers":[
        {
            "category":"Building & Trades",
            "subcategory":"Electrical",
            "type":"Services"
        }
    ],
    "sg:phone":"+1 559 277 2792",
    "sg:postcode":"93722",
    "sg:province":"CA",
    "sg:tags":[
        "electrical",
        "contractor"
    ],
    "wof:name":"Atlanta Networking & Cabling",
    "wof:placetype":"venue"
},
  "geometry": {"coordinates":[-119.874618,36.795304],"type":"Point"}
}