{
  "type": "Feature",
  "properties": {
    "iso:country":"US",
    "sg:address":"4053 Birchgrove Way",
    "sg:city":"Sacramento",
    "sg:classifiers":[
        {
            "category":"Wholesale",
            "subcategory":"Non-durable Goods",
            "type":"Manufacturing & Wholesale Goods"
        }
    ],
    "sg:phone":"+1 916 363 5789",
    "sg:postcode":"95826",
    "sg:province":"CA",
    "sg:tags":[
        "merchandise"
    ],
    "wof:name":"Poffinbarger Map Company",
    "wof:placetype":"venue"
},
  "geometry": {"coordinates":[-121.355932,38.542414],"type":"Point"}
}