{
  "type": "Feature",
  "properties": {
    "addr:full":"550 Front St San Diego CA 92101",
    "addr:housenumber":"550",
    "addr:postcode":"92101",
    "addr:street":"Front St",
    "iso:country":"US",
    "sg:address":"550 Front St",
    "sg:city":"San Diego",
    "sg:classifiers":[
        {
            "category":"Professional",
            "type":"Services"
        }
    ],
    "sg:phone":"+1 619 233 0442",
    "sg:postcode":"92101",
    "sg:province":"CA",
    "wof:name":"Johnson Barnes & Finch",
    "wof:placetype":"venue"
},
  "geometry": {"coordinates":[-117.164754,32.710925],"type":"Point"}
}