{
  "type": "Feature",
  "properties": {
    "addr:full":"5862 Tree Top Ct San Jose CA 95123",
    "addr:housenumber":"5862",
    "addr:postcode":"95123",
    "addr:street":"Tree Top Ct",
    "iso:country":"US",
    "sg:address":"5862 Tree Top Ct",
    "sg:city":"San Jose",
    "sg:classifiers":[
        {
            "category":"Building & Trades",
            "subcategory":"Landscaping Services",
            "type":"Services"
        }
    ],
    "sg:phone":"+1 408 629 9848",
    "sg:postcode":"95123",
    "sg:province":"CA",
    "sg:tags":[
        "landscape",
        "contractor"
    ],
    "wof:name":"Gardening Angels",
    "wof:placetype":"venue"
},
  "geometry": {"coordinates":[-121.815747,37.241061],"type":"Point"}
}