{
  "type": "Feature",
  "properties": {
    "addr:full":"8422 S Gate Ave South Gate CA 90280",
    "addr:housenumber":"8422",
    "addr:postcode":"90280",
    "addr:street":"S Gate Ave;Gate",
    "iso:country":"US",
    "sg:address":"8422 S Gate Ave",
    "sg:city":"South Gate",
    "sg:classifiers":[
        {
            "category":"Food & Beverages",
            "subcategory":"Groceries & Convenience Stores",
            "type":"Retail Goods"
        }
    ],
    "sg:phone":"+1 323 566 0215",
    "sg:postcode":"90280",
    "sg:province":"CA",
    "sg:tags":[
        "grocer"
    ],
    "wof:name":"Lopez Market",
    "wof:placetype":"venue"
},
  "geometry": {"coordinates":[-118.213629,33.960343],"type":"Point"}
}