{
  "type": "Feature",
  "properties": {
    "addr:full":"6663 el Cajon Blvd San Diego CA 92115",
    "addr:housenumber":"6663",
    "addr:postcode":"92115",
    "addr:street":"El Cajon Blvd",
    "iso:country":"US",
    "sg:address":"6663 el Cajon Blvd",
    "sg:city":"San Diego",
    "sg:classifiers":[
        {
            "category":"Food & Beverages",
            "subcategory":"Specialty",
            "type":"Retail Goods"
        }
    ],
    "sg:phone":"+1 619 828 0111",
    "sg:postcode":"92115",
    "sg:province":"CA",
    "sg:tags":[
        "health",
        "diet"
    ],
    "wof:name":"Nutrimart",
    "wof:placetype":"venue"
},
  "geometry": {"coordinates":[-117.05571399999999,32.767482],"type":"Point"}
}