{
  "type": "Feature",
  "properties": {
    "addr:full":"36060 Fremont Blvd Fremont CA 94536",
    "addr:housenumber":"36060",
    "addr:postcode":"94536",
    "addr:street":"Fremont Blvd",
    "iso:country":"US",
    "sg:address":"36060 Fremont Blvd",
    "sg:city":"Fremont",
    "sg:classifiers":[
        {
            "category":"Place Of Worship",
            "subcategory":"Church",
            "type":"Public Place"
        },
        {
            "category":"Place Of Worship",
            "type":"Public Place"
        },
        {
            "category":"Education",
            "subcategory":"School",
            "type":"Public Place"
        }
    ],
    "sg:phone":"+1 510 797 7729",
    "sg:postcode":"94536",
    "sg:province":"CA",
    "sg:tags":[
        "churches-baptist-general",
        "private",
        "high",
        "k-",
        "churches-baptist",
        "elementary"
    ],
    "sg:website":"http://www.gracechurchfremont.org",
    "wof:name":"Grace Church Fremont",
    "wof:placetype":"venue"
},
  "geometry": {"coordinates":[-122.019814,37.564659],"type":"Point"}
}