{
  "type": "Feature",
  "properties": {
    "addr:full":"3612 Mentone Ave Los Angeles CA 90034",
    "addr:housenumber":"3612",
    "addr:postcode":"90034",
    "addr:street":"Mentone Ave",
    "iso:country":"US",
    "sg:address":"3612 Mentone Ave",
    "sg:city":"Los Angeles",
    "sg:classifiers":[
        {
            "category":"Manufacturing",
            "subcategory":"Motor Vehicles & Parts",
            "type":"Manufacturing & Wholesale Goods"
        }
    ],
    "sg:phone":"+1 310 815 1045",
    "sg:postcode":"90034",
    "sg:province":"CA",
    "sg:tags":[
        "mfg",
        "trimming"
    ],
    "wof:name":"Insurgents Net",
    "wof:placetype":"venue"
},
  "geometry": {"coordinates":[-118.406869,34.022445],"type":"Point"}
}