{
  "type": "Feature",
  "properties": {
    "addr:full":"1151 El Centro St Ste A South Pasadena CA 91030",
    "addr:housenumber":"1151",
    "addr:postcode":"91030",
    "addr:street":"El Centro St Ste A",
    "iso:country":"US",
    "sg:address":"1151 El Centro St Ste A",
    "sg:city":"South Pasadena",
    "sg:classifiers":[
        {
            "category":"Health Services",
            "subcategory":"Chiropractor",
            "type":"Services"
        }
    ],
    "sg:phone":"+1 626 799 1423",
    "sg:postcode":"91030",
    "sg:province":"CA",
    "sg:website":"www.BanikChiropractic.com",
    "wof:name":"Banik Chiropractic",
    "wof:placetype":"venue"
},
  "geometry": {"coordinates":[-118.154123,34.114758],"type":"Point"}
}