{
  "type": "Feature",
  "properties": {
    "addr:full":"799 Valencia Dr Milpitas CA 95035",
    "addr:housenumber":"799",
    "addr:postcode":"95035",
    "addr:street":"Valencia Dr",
    "iso:country":"US",
    "sg:address":"799 Valencia Dr",
    "sg:city":"Milpitas",
    "sg:classifiers":[
        {
            "category":"Shopping",
            "subcategory":"Jewelry",
            "type":"Retail Goods"
        }
    ],
    "sg:phone":"+1 408 945 0654",
    "sg:postcode":"95035",
    "sg:province":"CA",
    "sg:tags":[
        "designer"
    ],
    "wof:name":"Creative Flare",
    "wof:placetype":"venue"
},
  "geometry": {"coordinates":[-121.892419,37.437994],"type":"Point"}
}