{
  "type": "Feature",
  "properties": {
    "iso:country":"US",
    "sg:address":"230 W 31st St",
    "sg:city":"Los Angeles",
    "sg:classifiers":[
        {
            "category":"Shopping",
            "subcategory":"Clothing, Apparel, & Fashions",
            "type":"Retail Goods"
        }
    ],
    "sg:phone":"+1 213 748 1669",
    "sg:postcode":"90007",
    "sg:province":"CA",
    "sg:tags":[
        "children's",
        "clothing"
    ],
    "wof:name":"TETE Design Inc",
    "wof:placetype":"venue"
},
  "geometry": {"coordinates":[-118.273869,34.198167],"type":"Point"}
}