{
  "type": "Feature",
  "properties": {
    "addr:full":"800 W 6th St Los Angeles CA 90017",
    "addr:housenumber":"800",
    "addr:postcode":"90017",
    "addr:street":"W 6Th St",
    "iso:country":"US",
    "sg:address":"800 W 6th St",
    "sg:city":"Los Angeles",
    "sg:classifiers":[
        {
            "category":"Real Estate",
            "subcategory":"Real Estate Agent",
            "type":"Services"
        }
    ],
    "sg:phone":"+1 213 996 2600",
    "sg:postcode":"90017",
    "sg:province":"CA",
    "wof:name":"Lincoln Property Co",
    "wof:placetype":"venue"
},
  "geometry": {"coordinates":[-118.257953,34.05048],"type":"Point"}
}