{
  "type": "Feature",
  "properties": {
    "iso:country":"US",
    "sg:address":"1555 Scott Rd Ofc",
    "sg:city":"Burbank",
    "sg:classifiers":[
        {
            "category":"Real Estate",
            "subcategory":"Real Estate Operator",
            "type":"Services"
        }
    ],
    "sg:phone":"+1 818 843 7400",
    "sg:postcode":"91504",
    "sg:province":"CA",
    "sg:tags":[
        "apartment"
    ],
    "wof:name":"Scott Villa Apartments",
    "wof:placetype":"venue"
},
  "geometry": {"coordinates":[-118.322998,34.192402],"type":"Point"}
}