{
  "type": "Feature",
  "properties": {
    "iso:country":"US",
    "sg:address":"2194 Edison Ave",
    "sg:city":"San Leandro",
    "sg:classifiers":[
        {
            "category":"Professional",
            "subcategory":"Advertising",
            "type":"Services"
        }
    ],
    "sg:phone":"+1 510 636 8663",
    "sg:postcode":"94577",
    "sg:province":"CA",
    "sg:tags":[
        "agency"
    ],
    "wof:name":"Rent-A-Center",
    "wof:placetype":"venue"
},
  "geometry": {"coordinates":[-122.187882,37.723473],"type":"Point"}
}