{
  "type": "Feature",
  "properties": {
    "addr:full":"118 Veronica Ct Windsor CA 95492",
    "addr:housenumber":"118",
    "addr:postcode":"95492",
    "addr:street":"Veronica Ct",
    "iso:country":"US",
    "sg:address":"118 Veronica Ct",
    "sg:city":"Windsor",
    "sg:classifiers":[
        {
            "category":"Professional",
            "subcategory":"Engineering",
            "type":"Services"
        }
    ],
    "sg:phone":"+1 707 837 7564",
    "sg:postcode":"95492",
    "sg:province":"CA",
    "sg:tags":[
        "engineer"
    ],
    "wof:name":"Wheeler Engineering Inc",
    "wof:placetype":"venue"
},
  "geometry": {"coordinates":[-122.809134,38.557973],"type":"Point"}
}