{
  "type": "Feature",
  "properties": {
    "addr:full":"4722 Admiralty Way Marina Del Rey CA 90292",
    "addr:housenumber":"4722",
    "addr:postcode":"90292",
    "addr:street":"Admiralty Way",
    "iso:country":"US",
    "sg:address":"4722 Admiralty Way",
    "sg:city":"Marina Del Rey",
    "sg:classifiers":[
        {
            "category":"Shopping",
            "subcategory":"Clothing, Apparel, & Fashions",
            "type":"Retail Goods"
        }
    ],
    "sg:phone":"+1 310 822 6363",
    "sg:postcode":"90292",
    "sg:province":"CA",
    "sg:tags":[
        "accessory",
        "clothing",
        "women's"
    ],
    "wof:name":"Chelie's Accessories",
    "wof:placetype":"venue"
},
  "geometry": {"coordinates":[-118.43946200000001,33.979329],"type":"Point"}
}