{
  "type": "Feature",
  "properties": {
    "iso:country":"US",
    "sg:address":"4121 Riverside Dr",
    "sg:city":"Chino",
    "sg:classifiers":[
        {
            "category":"Personal",
            "subcategory":"Beauty Salon",
            "type":"Services"
        }
    ],
    "sg:phone":"+1 909 465 1155",
    "sg:postcode":"91710",
    "sg:province":"CA",
    "wof:name":"Cut Color & Curl",
    "wof:placetype":"venue"
},
  "geometry": {"coordinates":[-117.713601,34.018837],"type":"Point"}
}