{
  "type": "Feature",
  "properties": {
    "addr:full":"3418 Clark Ave Long Beach CA 90808",
    "addr:housenumber":"3418",
    "addr:postcode":"90808",
    "addr:street":"Clark Ave",
    "iso:country":"US",
    "sg:address":"3418 Clark Ave",
    "sg:city":"Long Beach",
    "sg:classifiers":[
        {
            "category":"Professional",
            "type":"Services"
        }
    ],
    "sg:phone":"+1 562 420 9165",
    "sg:postcode":"90808",
    "sg:province":"CA",
    "wof:name":"Lo Phala Im",
    "wof:placetype":"venue"
},
  "geometry": {"coordinates":[-118.133814,33.8218],"type":"Point"}
}