{
  "type": "Feature",
  "properties": {
    "iso:country":"US",
    "sg:address":"143 Scotia Pines Cir",
    "sg:city":"Grass Valley",
    "sg:classifiers":[
        {
            "category":"Organizations",
            "subcategory":"Religious Organization",
            "type":"Services"
        }
    ],
    "sg:phone":"+1 530 272 1236",
    "sg:postcode":"95945",
    "sg:province":"CA",
    "wof:name":"Gateway Ministry",
    "wof:placetype":"venue"
},
  "geometry": {"coordinates":[-121.07138999999999,39.219482],"type":"Point"}
}