{
  "type": "Feature",
  "properties": {
    "addr:full":"3754 Drais Rd Stockton CA 95215",
    "addr:housenumber":"3754",
    "addr:postcode":"95215",
    "addr:street":"Drais Rd",
    "iso:country":"US",
    "sg:address":"3754 Drais Rd",
    "sg:city":"Stockton",
    "sg:classifiers":[
        {
            "category":"Farming",
            "subcategory":"Dairy Farm",
            "type":"Manufacturing & Wholesale Goods"
        }
    ],
    "sg:phone":"+1 209 462 6052",
    "sg:postcode":"95215",
    "sg:province":"CA",
    "wof:name":"Reis Dairy",
    "wof:placetype":"venue"
},
  "geometry": {"coordinates":[-121.084675,37.949918],"type":"Point"}
}