{
  "type": "Feature",
  "properties": {
    "addr:full":"1665 Hollenbeck Ave Sunnyvale CA 94087",
    "addr:housenumber":"1665",
    "addr:postcode":"94087",
    "addr:street":"Hollenbeck Ave",
    "iso:country":"US",
    "sg:address":"1665 Hollenbeck Ave",
    "sg:city":"Sunnyvale",
    "sg:classifiers":[
        {
            "category":"Retail",
            "subcategory":"Laundry & Dry Cleaning",
            "type":"Services"
        }
    ],
    "sg:phone":"+1 408 736 5066",
    "sg:postcode":"94087",
    "sg:province":"CA",
    "sg:tags":[
        "cleaners"
    ],
    "wof:name":"Terry's Cleaners & Tailors",
    "wof:placetype":"venue"
},
  "geometry": {"coordinates":[-122.04159199999999,37.33814],"type":"Point"}
}