{
  "type": "Feature",
  "properties": {
    "addr:full":"18440 Lakecrest Ct Castro Valley CA 94546",
    "addr:housenumber":"18440",
    "addr:postcode":"94546",
    "addr:street":"Lakecrest Ct",
    "iso:country":"US",
    "sg:address":"18440 Lakecrest Ct",
    "sg:city":"Castro Valley",
    "sg:classifiers":[
        {
            "category":"Shopping",
            "type":"Retail Goods"
        }
    ],
    "sg:phone":"+1 510 581 6800",
    "sg:postcode":"94546",
    "sg:province":"CA",
    "sg:tags":[
        "cosmetic",
        "perfume"
    ],
    "wof:name":"Katie Face & Friends Inc",
    "wof:placetype":"venue"
},
  "geometry": {"coordinates":[-122.095153,37.710612],"type":"Point"}
}