{
  "type": "Feature",
  "properties": {
    "addr:full":"38712 6th St E Palmdale CA 93550",
    "addr:housenumber":"38712",
    "addr:postcode":"ca 93550",
    "addr:street":"6Th St E",
    "iso:country":"US",
    "sg:address":"38712 6th St E",
    "sg:city":"Palmdale",
    "sg:classifiers":[
        {
            "category":"Shopping",
            "subcategory":"Used Merchandise",
            "type":"Retail Goods"
        }
    ],
    "sg:phone":"+1 661 272 5665",
    "sg:postcode":"93550",
    "sg:province":"CA",
    "wof:name":"Antique Asylum",
    "wof:placetype":"venue"
},
  "geometry": {"coordinates":[-118.119134,34.585544],"type":"Point"}
}