{
  "type": "Feature",
  "properties": {
    "iso:country":"US",
    "sg:address":"1850 E 17th St",
    "sg:city":"Santa Ana",
    "sg:classifiers":[
        {
            "category":"Real Estate",
            "subcategory":"Real Estate Operator",
            "type":"Services"
        }
    ],
    "sg:phone":"+1 714 543 4979",
    "sg:postcode":"92705",
    "sg:province":"CA",
    "sg:tags":[
        "building",
        "parks"
    ],
    "wof:name":"Atrium Office Suites",
    "wof:placetype":"venue"
},
  "geometry": {"coordinates":[-117.83946299999999,33.75986],"type":"Point"}
}