{
  "type": "Feature",
  "properties": {
    "addr:full":"249 S. 20th Street San Jose CA 95116",
    "addr:housenumber":"249",
    "addr:postcode":"95116",
    "addr:street":"S. 20Th Street",
    "iso:country":"US",
    "sg:address":"249 S. 20th Street",
    "sg:city":"San Jose",
    "sg:classifiers":[
        {
            "category":"Real Estate",
            "subcategory":"Architect",
            "type":"Services"
        }
    ],
    "sg:phone":"+1 408 370 0730",
    "sg:postcode":"95116",
    "sg:province":"CA",
    "sg:website":"www.paladin-design.net",
    "wof:name":"Paladin Design Group",
    "wof:placetype":"venue"
},
  "geometry": {"coordinates":[-121.86783200000001,37.340997],"type":"Point"}
}