{
  "type": "Feature",
  "properties": {
    "addr:full":"11439 Crenshaw Blvd Inglewood CA 90303",
    "addr:housenumber":"11439",
    "addr:postcode":"90303",
    "addr:street":"Crenshaw Blvd",
    "iso:country":"US",
    "sg:address":"11439 Crenshaw Blvd",
    "sg:city":"Inglewood",
    "sg:classifiers":[
        {
            "category":"Communications",
            "type":"Services"
        }
    ],
    "sg:phone":"+1 310 644 3388",
    "sg:postcode":"90303",
    "sg:province":"CA",
    "sg:tags":[
        "paging",
        "signaling"
    ],
    "wof:name":"Digital Center",
    "wof:placetype":"venue"
},
  "geometry": {"coordinates":[-118.326576,33.930499],"type":"Point"}
}