{
  "type": "Feature",
  "properties": {
    "addr:full":"15721 Texaco Ave Paramount CA 90723",
    "addr:postcode":"15721;90723",
    "addr:street":"Texaco Ave",
    "iso:country":"US",
    "sg:address":"15721 Texaco Ave",
    "sg:city":"Paramount",
    "sg:classifiers":[
        {
            "category":"Professional",
            "type":"Services"
        }
    ],
    "sg:phone":"+1 562 633 0588",
    "sg:postcode":"90723",
    "sg:province":"CA",
    "wof:name":"Kairouz Corporation",
    "wof:placetype":"venue"
},
  "geometry": {"coordinates":[-118.17192300000001,33.890348],"type":"Point"}
}