{
  "type": "Feature",
  "properties": {
    "iso:country":"US",
    "sg:address":"722 Spenser Ln",
    "sg:city":"Ventura",
    "sg:classifiers":[
        {
            "category":"Building & Trades",
            "subcategory":"Construction",
            "type":"Services"
        }
    ],
    "sg:phone":"+1 805 642 3902",
    "sg:postcode":"93003",
    "sg:province":"CA",
    "sg:tags":[
        "concrete",
        "contractor"
    ],
    "wof:name":"Hard Core Concrete Svc",
    "wof:placetype":"venue"
},
  "geometry": {"coordinates":[-119.20235599999999,34.271759],"type":"Point"}
}