{
  "type": "Feature",
  "properties": {
    "iso:country":"US",
    "sg:address":"47655 Monroe St",
    "sg:city":"Indio",
    "sg:classifiers":[
        {
            "category":"Organizations",
            "subcategory":"Religious Organization",
            "type":"Services"
        }
    ],
    "sg:phone":"+1 760 347 0051",
    "sg:postcode":"92201",
    "sg:province":"CA",
    "sg:tags":[
        "church"
    ],
    "wof:name":"Las Palmos Comm The Nazarene",
    "wof:placetype":"venue"
},
  "geometry": {"coordinates":[-116.233944,33.706657],"type":"Point"}
}