{
  "type": "Feature",
  "properties": {
    "iso:country":"US",
    "sg:address":"505 Forest Ave",
    "sg:city":"Laguna Beach",
    "sg:classifiers":[
        {
            "category":"Government",
            "subcategory":"Fire Station",
            "type":"Public Place"
        },
        {
            "category":"Government",
            "subcategory":"Police Station",
            "type":"Public Place"
        }
    ],
    "sg:phone":"+1 949 497 0700",
    "sg:postcode":"92651",
    "sg:province":"CA",
    "sg:tags":[
        "department",
        "protection"
    ],
    "wof:name":"Laguna Beach Finance Dept",
    "wof:placetype":"venue"
},
  "geometry": {"coordinates":[-117.781835,33.546114],"type":"Point"}
}