{
  "type": "Feature",
  "properties": {
    "iso:country":"US",
    "sg:address":"908 Concord Ave",
    "sg:city":"Montebello",
    "sg:classifiers":[
        {
            "category":"Professional",
            "subcategory":"Computer Services",
            "type":"Services"
        }
    ],
    "sg:phone":"+1 323 721 6594",
    "sg:postcode":"90640",
    "sg:province":"CA",
    "sg:tags":[
        "internet"
    ],
    "wof:name":"Weian",
    "wof:placetype":"venue"
},
  "geometry": {"coordinates":[-118.107269,34.025011],"type":"Point"}
}