{
  "type": "Feature",
  "properties": {
    "addr:full":"6 Bayview Irvine CA 92614",
    "addr:housenumber":"6",
    "addr:postcode":"92614",
    "addr:street":"Bayview",
    "iso:country":"US",
    "sg:address":"6 Bayview",
    "sg:city":"Irvine",
    "sg:classifiers":[
        {
            "category":"Recreation",
            "type":"Entertainment"
        }
    ],
    "sg:phone":"+1 949 786 1392",
    "sg:postcode":"92614",
    "sg:province":"CA",
    "wof:name":"Spring Creek Connection",
    "wof:placetype":"venue"
},
  "geometry": {"coordinates":[-117.80452099999999,33.674038],"type":"Point"}
}