{
  "type": "Feature",
  "properties": {
    "addr:full":"20 North Ave San Rafael CA 94903",
    "addr:housenumber":"20",
    "addr:postcode":"94903",
    "addr:street":"North Ave",
    "iso:country":"US",
    "sg:address":"20 North Ave",
    "sg:city":"San Rafael",
    "sg:classifiers":[
        {
            "category":"Real Estate",
            "subcategory":"Real Estate Operator",
            "type":"Services"
        }
    ],
    "sg:phone":"+1 415 491 1125",
    "sg:postcode":"94903",
    "sg:province":"CA",
    "sg:tags":[
        "apartment"
    ],
    "wof:name":"Mc Innis Park Apartments",
    "wof:placetype":"venue"
},
  "geometry": {"coordinates":[-122.528746,38.024597],"type":"Point"}
}