{
  "type": "Feature",
  "properties": {
    "addr:full":"820 Manhattan Avenue Suite 100 Manhattan Beach CA 90266",
    "addr:housenumber":"820",
    "addr:postcode":"90266",
    "addr:street":"Manhattan Avenue Suite 100",
    "iso:country":"US",
    "sg:address":"820 Manhattan Avenue Suite 100",
    "sg:city":"Manhattan Beach",
    "sg:classifiers":[
        {
            "category":"Real Estate",
            "subcategory":"Architect",
            "type":"Services"
        }
    ],
    "sg:phone":"+1 310 372 4555",
    "sg:postcode":"90266",
    "sg:province":"CA",
    "wof:name":"Angelworks",
    "wof:placetype":"venue"
},
  "geometry": {"coordinates":[-118.40949500000001,33.882569],"type":"Point"}
}