{
  "type": "Feature",
  "properties": {
    "iso:country":"US",
    "sg:address":"467 W Main St",
    "sg:city":"El Centro",
    "sg:classifiers":[
        {
            "category":"Recreation",
            "type":"Entertainment"
        }
    ],
    "sg:phone":"+1 760 352 6191",
    "sg:postcode":"92243",
    "sg:province":"CA",
    "sg:tags":[
        "playing",
        "card",
        "rooms"
    ],
    "wof:name":"New Esquire",
    "wof:placetype":"venue"
},
  "geometry": {"coordinates":[-115.553397,32.792761],"type":"Point"}
}