{
  "type": "Feature",
  "properties": {
    "iso:country":"US",
    "sg:address":"2109 Dandelion Ave",
    "sg:city":"Tulare",
    "sg:classifiers":[
        {
            "category":"Shopping",
            "type":"Retail Goods"
        }
    ],
    "sg:phone":"+1 559 688 4939",
    "sg:postcode":"93274",
    "sg:province":"CA",
    "sg:tags":[
        "candle"
    ],
    "wof:name":"Candle Delights",
    "wof:placetype":"venue"
},
  "geometry": {"coordinates":[-119.37561599999999,36.220865],"type":"Point"}
}