{
  "type": "Feature",
  "properties": {
    "addr:full":"36711 96th St E Littlerock CA 93543",
    "addr:housenumber":"36711",
    "addr:postcode":"littlerock ca 93543",
    "addr:street":"96Th St E",
    "iso:country":"US",
    "sg:address":"36711 96th St E",
    "sg:city":"Littlerock",
    "sg:classifiers":[
        {
            "category":"Building & Trades",
            "subcategory":"Landscaping Services",
            "type":"Services"
        }
    ],
    "sg:phone":"+1 661 944 6344",
    "sg:postcode":"93543",
    "sg:province":"CA",
    "wof:name":"Felix Tree",
    "wof:placetype":"venue"
},
  "geometry": {"coordinates":[-117.95820999999999,34.548571],"type":"Point"}
}