{
  "type": "Feature",
  "properties": {
    "addr:full":"2945 The Villages Parkway San Jose CA 95135",
    "addr:housenumber":"2945",
    "addr:postcode":"95135",
    "addr:street":"The Villages Parkway",
    "iso:country":"US",
    "sg:address":"2945 The Villages Parkway",
    "sg:city":"San Jose",
    "sg:classifiers":[
        {
            "category":"Health Services",
            "subcategory":"Doctor",
            "type":"Services"
        }
    ],
    "sg:phone":"+1 408 270 9450",
    "sg:postcode":"95135",
    "sg:province":"CA",
    "sg:tags":[
        "surgeon",
        "oral"
    ],
    "wof:name":"Andrew D Harsany DDS",
    "wof:placetype":"venue"
},
  "geometry": {"coordinates":[-121.759579,37.291203],"type":"Point"}
}