{
  "type": "Feature",
  "properties": {
    "iso:country":"US",
    "sg:address":"2004 N Bend Dr",
    "sg:city":"Sacramento",
    "sg:classifiers":[
        {
            "category":"Professional",
            "subcategory":"Engineering",
            "type":"Services"
        },
        {
            "category":"Manufacturing",
            "subcategory":"Aerospace",
            "type":"Manufacturing & Wholesale Goods"
        }
    ],
    "sg:phone":"+1 415 440 0054",
    "sg:postcode":"95835",
    "sg:province":"CA",
    "sg:tags":[
        "aeronautical",
        "industry",
        "engineer"
    ],
    "wof:name":"Bombardier Aerospace Inc.",
    "wof:placetype":"venue"
},
  "geometry": {"coordinates":[-121.505572,38.659558],"type":"Point"}
}