{
  "type": "Feature",
  "properties": {
    "iso:country":"US",
    "sg:address":"603 S Shields Dr",
    "sg:city":"Anaheim",
    "sg:classifiers":[
        {
            "category":"Retail",
            "subcategory":"Repair Shop",
            "type":"Services"
        }
    ],
    "sg:phone":"+1 714 827 4966",
    "sg:postcode":"92804",
    "sg:province":"CA",
    "sg:tags":[
        "fix-it"
    ],
    "wof:name":"Custom Designs Interiors & Exteriors",
    "wof:placetype":"venue"
},
  "geometry": {"coordinates":[-117.982399,33.824818],"type":"Point"}
}