{
  "type": "Feature",
  "properties": {
    "addr:full":"8289 Halley Rd Winters CA 95694",
    "addr:housenumber":"8289",
    "addr:postcode":"95694",
    "addr:street":"Halley Rd",
    "iso:country":"US",
    "sg:address":"8289 Halley Rd",
    "sg:city":"Winters",
    "sg:classifiers":[
        {
            "category":"Building & Trades",
            "subcategory":"Cleaning & Sanitation",
            "type":"Services"
        }
    ],
    "sg:phone":"+1 530 795 1375",
    "sg:postcode":"95694",
    "sg:province":"CA",
    "sg:tags":[
        "window"
    ],
    "wof:name":"Gem Pro Window Cleaning",
    "wof:placetype":"venue"
},
  "geometry": {"coordinates":[-121.9238,38.471814],"type":"Point"}
}