{
  "type": "Feature",
  "properties": {
    "addr:full":"100 Mission Blvd 2800 Jackson CA 95642",
    "addr:housenumber":"100;2800",
    "addr:postcode":"95642",
    "addr:street":"Mission Blvd",
    "iso:country":"US",
    "sg:address":"100 Mission Blvd 2800",
    "sg:city":"Jackson",
    "sg:classifiers":[
        {
            "category":"Health Services",
            "subcategory":"Clinic",
            "type":"Services"
        }
    ],
    "sg:phone":"+1 209 257 0174",
    "sg:postcode":"95642",
    "sg:province":"CA",
    "sg:tags":[
        "welfare"
    ],
    "wof:name":"Women S Health Of Amador, Inc.",
    "wof:placetype":"venue"
},
  "geometry": {"coordinates":[-120.76711299999999,38.35165],"type":"Point"}
}