{
  "type": "Feature",
  "properties": {
    "addr:full":"630 Azalea Ave Redding CA 96002",
    "addr:housenumber":"630",
    "addr:postcode":"96002",
    "addr:street":"Azalea Ave",
    "iso:country":"US",
    "sg:address":"630 Azalea Ave",
    "sg:city":"Redding",
    "sg:classifiers":[
        {
            "category":"Real Estate",
            "subcategory":"Real Estate Services",
            "type":"Services"
        }
    ],
    "sg:phone":"+1 530 223 6143",
    "sg:postcode":"96002",
    "sg:province":"CA",
    "sg:tags":[
        "loan"
    ],
    "wof:name":"Access Mortgage",
    "wof:placetype":"venue"
},
  "geometry": {"coordinates":[-122.359021,40.577413],"type":"Point"}
}