{
  "type": "Feature",
  "properties": {
    "addr:full":"3368 W 8th Street Los Angeles CA 90005",
    "addr:housenumber":"3368",
    "addr:postcode":"90005",
    "addr:street":"W 8Th Street",
    "iso:country":"US",
    "sg:address":"3368 W 8th Street",
    "sg:city":"Los Angeles",
    "sg:classifiers":[
        {
            "category":"Arena",
            "subcategory":"Sports Club",
            "type":"Entertainment"
        }
    ],
    "sg:phone":"+1 213 380 8108",
    "sg:postcode":"90005",
    "sg:province":"CA",
    "sg:tags":[
        "martial art"
    ],
    "wof:name":"Dae Sung Tae Kwon DO",
    "wof:placetype":"venue"
},
  "geometry": {"coordinates":[-118.302858,34.057789],"type":"Point"}
}