{
  "type": "Feature",
  "properties": {
    "addr:full":"1274 N Fresno St Fresno CA 93703",
    "addr:housenumber":"1274",
    "addr:postcode":"93703",
    "addr:street":"N Fresno",
    "iso:country":"US",
    "sg:address":"1274 N Fresno St",
    "sg:city":"Fresno",
    "sg:classifiers":[
        {
            "category":"Organizations",
            "subcategory":"Religious Organization",
            "type":"Services"
        }
    ],
    "sg:phone":"+1 559 486 3663",
    "sg:postcode":"93703",
    "sg:province":"CA",
    "sg:tags":[
        "church"
    ],
    "wof:name":"Korean Full Gospel Fresno Chr",
    "wof:placetype":"venue"
},
  "geometry": {"coordinates":[-119.781434,36.759102],"type":"Point"}
}