{
  "type": "Feature",
  "properties": {
    "iso:country":"US",
    "sg:address":"11713 Prairie Ave",
    "sg:city":"Hawthorne",
    "sg:classifiers":[
        {
            "category":"Health Services",
            "subcategory":"Medical Lab",
            "type":"Services"
        }
    ],
    "sg:phone":"+1 310 679 6488",
    "sg:postcode":"90250",
    "sg:province":"CA",
    "sg:tags":[
        "laboratory"
    ],
    "wof:name":"P & P Dental Lab",
    "wof:placetype":"venue"
},
  "geometry": {"coordinates":[-118.343952,33.927398],"type":"Point"}
}