{
  "type": "Feature",
  "properties": {
    "iso:country":"US",
    "sg:address":"1294 W 6th St",
    "sg:city":"San Pedro",
    "sg:classifiers":[
        {
            "category":"Health Services",
            "subcategory":"Medical Lab",
            "type":"Services"
        }
    ],
    "sg:phone":"+1 310 547 3662",
    "sg:postcode":"90731",
    "sg:province":"CA",
    "sg:tags":[
        "laboratory"
    ],
    "wof:name":"Unilab Corporation",
    "wof:placetype":"venue"
},
  "geometry": {"coordinates":[-118.305581,33.738419],"type":"Point"}
}