{
  "type": "Feature",
  "properties": {
    "iso:country":"US",
    "sg:address":"1261 Andersen Dr",
    "sg:city":"San Rafael",
    "sg:classifiers":[
        {
            "category":"Professional",
            "subcategory":"Business Services",
            "type":"Services"
        },
        {
            "category":"Manufacturing",
            "subcategory":"Motor Vehicles & Parts",
            "type":"Manufacturing & Wholesale Goods"
        }
    ],
    "sg:phone":"+1 415 459 2004",
    "sg:postcode":"94901",
    "sg:province":"CA",
    "sg:tags":[
        "mfg",
        "embroidery",
        "trimming"
    ],
    "wof:name":"Marshall Arts",
    "wof:placetype":"venue"
},
  "geometry": {"coordinates":[-122.503973,37.955279],"type":"Point"}
}