{
  "type": "Feature",
  "properties": {
    "addr:full":"901 H St Ste 208 Sacramento CA 95814",
    "addr:housenumber":"901",
    "addr:postcode":"95814",
    "addr:street":"H St Ste 208",
    "iso:country":"US",
    "sg:address":"901 H St Ste 208",
    "sg:city":"Sacramento",
    "sg:classifiers":[
        {
            "category":"Professional",
            "subcategory":"Lawyer & Legal Services",
            "type":"Services"
        }
    ],
    "sg:phone":"+1 916 447 1920",
    "sg:postcode":"95814",
    "sg:province":"CA",
    "wof:name":"Long Michael",
    "wof:placetype":"venue"
},
  "geometry": {"coordinates":[-121.493786,38.582992],"type":"Point"}
}