{
  "type": "Feature",
  "properties": {
    "iso:country":"US",
    "sg:address":"9525 Irondale Ave",
    "sg:city":"Chatsworth",
    "sg:classifiers":[
        {
            "category":"Wholesale",
            "subcategory":"Construction Materials",
            "type":"Manufacturing & Wholesale Goods"
        },
        {
            "category":"Home & Garden",
            "subcategory":"Building Materials",
            "type":"Retail Goods"
        },
        {
            "category":"Building & Trades",
            "subcategory":"Construction",
            "type":"Services"
        }
    ],
    "sg:phone":"+1 818 700 7861",
    "sg:postcode":"91311",
    "sg:province":"CA",
    "sg:tags":[
        "breaking",
        "contractor",
        "concrete",
        "cutting",
        "sawing",
        "staining"
    ],
    "wof:name":"Concrete Sawing & Coring Inc.",
    "wof:placetype":"venue"
},
  "geometry": {"coordinates":[-118.58599700000001,34.243154],"type":"Point"}
}