{
  "type": "Feature",
  "properties": {
    "iso:country":"US",
    "sg:address":"998 W 10th St",
    "sg:city":"Azusa",
    "sg:classifiers":[
        {
            "category":"Retail",
            "subcategory":"Repair Shop",
            "type":"Services"
        }
    ],
    "sg:phone":"+1 626 337 9804",
    "sg:postcode":"91702",
    "sg:province":"CA",
    "sg:tags":[
        "fixture",
        "industrial",
        "lighting",
        "electric",
        "contractors-commercial"
    ],
    "sg:website":"http://www.vistau.com",
    "wof:name":"Vista Universal, Inc.",
    "wof:placetype":"venue"
},
  "geometry": {"coordinates":[-117.918567,34.139771],"type":"Point"}
}