{
  "type": "Feature",
  "properties": {
    "iso:country":"US",
    "sg:address":"240 Nice Ln",
    "sg:city":"Newport Beach",
    "sg:classifiers":[
        {
            "category":"Real Estate",
            "subcategory":"Real Estate Operator",
            "type":"Services"
        }
    ],
    "sg:phone":"+1 949 929 0816",
    "sg:postcode":"92663",
    "sg:province":"CA",
    "sg:tags":[
        "building",
        "nonresidential"
    ],
    "wof:name":"J B H Global Properties",
    "wof:placetype":"venue"
},
  "geometry": {"coordinates":[-117.93481300000001,33.624467],"type":"Point"}
}