{
  "type": "Feature",
  "properties": {
    "addr:full":"25461 Ponce Ct Laguna Hills CA 92653",
    "addr:housenumber":"25461",
    "addr:postcode":"92653",
    "addr:street":"Ponce Ct",
    "iso:country":"US",
    "sg:address":"25461 Ponce Ct",
    "sg:city":"Laguna Hills",
    "sg:classifiers":[
        {
            "category":"Shopping",
            "subcategory":"Hobbies, Toys, & Games",
            "type":"Retail Goods"
        }
    ],
    "sg:phone":"+1 949 273 0550",
    "sg:postcode":"92653",
    "sg:province":"CA",
    "sg:tags":[
        "toy",
        "store"
    ],
    "sg:website":"www.puzzlevehicletoys.com",
    "wof:name":"Puzzle Vehicle Toys",
    "wof:placetype":"venue"
},
  "geometry": {"coordinates":[-117.68761499999999,33.59276],"type":"Point"}
}