{
  "type": "Feature",
  "properties": {
    "iso:country":"US",
    "sg:address":"13030 Goldnwest St",
    "sg:city":"Garden Grove",
    "sg:classifiers":[
        {
            "category":"Restaurant",
            "type":"Food & Drink"
        }
    ],
    "sg:phone":"+1 714 636 0442",
    "sg:postcode":"92840",
    "sg:province":"CA",
    "wof:name":"Spire's Restaurants Inc",
    "wof:placetype":"venue"
},
  "geometry": {"coordinates":[-118.00684099999999,33.773284],"type":"Point"}
}