{
  "type": "Feature",
  "properties": {
    "addr:full":"18801 Hawthorne Blvd Torrance CA 90504",
    "addr:housenumber":"18801",
    "addr:postcode":"90504",
    "addr:street":"Hawthorne Blvd",
    "iso:country":"US",
    "sg:address":"18801 Hawthorne Blvd",
    "sg:city":"Torrance",
    "sg:classifiers":[
        {
            "category":"Freight",
            "type":"Transportation"
        }
    ],
    "sg:phone":"+1 310 542 7357",
    "sg:postcode":"90504",
    "sg:province":"CA",
    "sg:tags":[
        "operator",
        "local",
        "trucking"
    ],
    "wof:name":"Jorge Ponce",
    "wof:placetype":"venue"
},
  "geometry": {"coordinates":[-118.35271899999999,33.859227],"type":"Point"}
}