{
  "type": "Feature",
  "properties": {
    "iso:country":"US",
    "sg:address":"12930 Pawnee Rd",
    "sg:city":"Apple Valley",
    "sg:classifiers":[
        {
            "category":"Social Services",
            "subcategory":"Child Care",
            "type":"Services"
        }
    ],
    "sg:phone":"+1 760 247 4914",
    "sg:postcode":"92308",
    "sg:province":"CA",
    "wof:name":"Hairston-Lane Family Child",
    "wof:placetype":"venue"
},
  "geometry": {"coordinates":[-117.185897,34.488202],"type":"Point"}
}