{
  "type": "Feature",
  "properties": {
    "addr:full":"28752 Marguerite Pkwy Mission Viejo CA 92692",
    "addr:housenumber":"28752",
    "addr:postcode":"92692",
    "addr:street":"Marguerite Pkwy",
    "iso:country":"US",
    "sg:address":"28752 Marguerite Pkwy",
    "sg:city":"Mission Viejo",
    "sg:classifiers":[
        {
            "category":"Manufacturing",
            "subcategory":"Printing",
            "type":"Manufacturing & Wholesale Goods"
        }
    ],
    "sg:phone":"+1 949 347 1426",
    "sg:postcode":"92692",
    "sg:province":"CA",
    "sg:tags":[
        "engraver",
        "wood"
    ],
    "wof:name":"Aardvark Industries Inc",
    "wof:placetype":"venue"
},
  "geometry": {"coordinates":[-117.672528,33.54499],"type":"Point"}
}