{
  "type": "Feature",
  "properties": {
    "iso:country":"US",
    "sg:address":"4561 Sutter Gate Ave",
    "sg:city":"Pleasanton",
    "sg:classifiers":[
        {
            "category":"Professional",
            "subcategory":"Accounting & Tax Preparation",
            "type":"Services"
        }
    ],
    "sg:phone":"+1 925 846 7697",
    "sg:postcode":"94566",
    "sg:province":"CA",
    "sg:tags":[
        "bookkeeping",
        "general"
    ],
    "sg:website":"www.zollingerca.com",
    "wof:name":"Zollinger Bookkeeping Svc",
    "wof:placetype":"venue"
},
  "geometry": {"coordinates":[-121.87996800000001,37.684884],"type":"Point"}
}