{
  "type": "Feature",
  "properties": {
    "addr:full":"7043 Commerce Cir Pleasanton CA 94588",
    "addr:housenumber":"7043",
    "addr:postcode":"94588",
    "addr:street":"Commerce Cir",
    "iso:country":"US",
    "sg:address":"7043 Commerce Cir",
    "sg:city":"Pleasanton",
    "sg:classifiers":[
        {
            "category":"Building & Trades",
            "subcategory":"Landscaping Services",
            "type":"Services"
        }
    ],
    "sg:phone":"+1 925 463 1812",
    "sg:postcode":"94588",
    "sg:province":"CA",
    "sg:tags":[
        "landscape"
    ],
    "wof:name":"Valleycrest Companies",
    "wof:placetype":"venue"
},
  "geometry": {"coordinates":[-121.91598,37.698281],"type":"Point"}
}