{
  "type": "Feature",
  "properties": {
    "addr:full":"700 S Spring Street Los Angeles CA 90014",
    "addr:housenumber":"700",
    "addr:postcode":"90014",
    "addr:street":"S Spring Street",
    "iso:country":"US",
    "sg:address":"700 S Spring Street",
    "sg:city":"Los Angeles",
    "sg:classifiers":[
        {
            "category":"Food & Beverages",
            "subcategory":"Groceries & Convenience Stores",
            "type":"Retail Goods"
        }
    ],
    "sg:phone":"+1 213 614 1135",
    "sg:postcode":"90014",
    "sg:province":"CA",
    "wof:name":"Happy Corner",
    "wof:placetype":"venue"
},
  "geometry": {"coordinates":[-118.25260400000001,34.044381],"type":"Point"}
}