{
  "type": "Feature",
  "properties": {
    "addr:full":"11368 Kenyon Way Alta Loma CA 91701",
    "addr:housenumber":"11368",
    "addr:postcode":"91701",
    "addr:street":"Kenyon Way",
    "iso:country":"US",
    "sg:address":"11368 Kenyon Way",
    "sg:city":"Alta Loma",
    "sg:classifiers":[
        {
            "category":"Personal",
            "subcategory":"Beauty Salon",
            "type":"Services"
        }
    ],
    "sg:phone":"+1 909 989 3866",
    "sg:postcode":"91701",
    "sg:province":"CA",
    "wof:name":"Hair Charisma",
    "wof:placetype":"venue"
},
  "geometry": {"coordinates":[-117.5579,34.134229],"type":"Point"}
}