{
  "type": "Feature",
  "properties": {
    "addr:full":"18824 Carlton Ave Castro Valley CA 94546",
    "addr:housenumber":"18824",
    "addr:postcode":"94546",
    "addr:street":"Carlton Ave",
    "iso:country":"US",
    "sg:address":"18824 Carlton Ave",
    "sg:city":"Castro Valley",
    "sg:classifiers":[
        {
            "category":"Shopping",
            "subcategory":"Jewelry",
            "type":"Retail Goods"
        }
    ],
    "sg:phone":"+1 510 881 1120",
    "sg:postcode":"94546",
    "sg:province":"CA",
    "wof:name":"Lori A Waters",
    "wof:placetype":"venue"
},
  "geometry": {"coordinates":[-122.09551,37.707611],"type":"Point"}
}