{
  "type": "Feature",
  "properties": {
    "iso:country":"US",
    "sg:address":"2074 Parker St",
    "sg:city":"San Luis Obispo",
    "sg:classifiers":[
        {
            "category":"Health Services",
            "subcategory":"Medical Lab",
            "type":"Services"
        }
    ],
    "sg:phone":"+1 805 543 0118",
    "sg:postcode":"93401",
    "sg:province":"CA",
    "sg:tags":[
        "laboratory"
    ],
    "wof:name":"Pacific Coast Dental Lab",
    "wof:placetype":"venue"
},
  "geometry": {"coordinates":[-120.669152,35.27117],"type":"Point"}
}