{
  "type": "Feature",
  "properties": {
    "iso:country":"US",
    "sg:address":"1090 W Highland Ave",
    "sg:city":"San Bernardino",
    "sg:classifiers":[
        {
            "category":"Personal",
            "subcategory":"Beauty Salon",
            "type":"Services"
        }
    ],
    "sg:phone":"+1 909 886 6163",
    "sg:postcode":"92405",
    "sg:province":"CA",
    "wof:name":"Artelea Hair Concern Barber",
    "wof:placetype":"venue"
},
  "geometry": {"coordinates":[-117.30567499999999,34.136128],"type":"Point"}
}