{
  "type": "Feature",
  "properties": {
    "addr:full":"8684 Ave de la Fuente San Diego CA 92154",
    "addr:postcode":"92154",
    "addr:street":"8684 Ave De La Fuente",
    "iso:country":"US",
    "sg:address":"8684 Ave de la Fuente",
    "sg:city":"San Diego",
    "sg:classifiers":[
        {
            "category":"Freight",
            "type":"Transportation"
        },
        {
            "category":"Building & Trades",
            "subcategory":"Construction",
            "type":"Services"
        }
    ],
    "sg:phone":"+1 619 661 5508",
    "sg:postcode":"92154",
    "sg:province":"CA",
    "sg:tags":[
        "operator",
        "erectors",
        "machinery",
        "trucking"
    ],
    "wof:name":"Pacific Industrial Transfer",
    "wof:placetype":"venue"
},
  "geometry": {"coordinates":[-116.95961,32.556973],"type":"Point"}
}