{
  "type": "Feature",
  "properties": {
    "iso:country":"US",
    "sg:address":"14313 Moorpark St",
    "sg:city":"Sherman Oaks",
    "sg:classifiers":[
        {
            "category":"Personal",
            "type":"Services"
        }
    ],
    "sg:phone":"+1 213 599 7115",
    "sg:postcode":"91423",
    "sg:province":"CA",
    "sg:tags":[
        "home"
    ],
    "wof:name":"Sherman Oaks Dish Satellite TV",
    "wof:placetype":"venue"
},
  "geometry": {"coordinates":[-118.445019,34.151343],"type":"Point"}
}