{
  "type": "Feature",
  "properties": {
    "iso:country":"US",
    "sg:address":"239 N H St",
    "sg:city":"Lompoc",
    "sg:classifiers":[
        {
            "category":"Autos & Motor Vehicles",
            "subcategory":"Automobile Sales",
            "type":"Retail Goods"
        }
    ],
    "sg:phone":"+1 805 735 8500",
    "sg:postcode":"93436",
    "sg:province":"CA",
    "sg:tags":[
        "car",
        "dealer"
    ],
    "wof:name":"Lompoc Motors",
    "wof:placetype":"venue"
},
  "geometry": {"coordinates":[-120.458011,34.641613],"type":"Point"}
}