{
  "type": "Feature",
  "properties": {
    "addr:full":"5200 Sunrise Blvd Fair Oaks CA 95628",
    "addr:housenumber":"5200",
    "addr:postcode":"95628",
    "addr:street":"Sunrise Blvd",
    "iso:country":"US",
    "sg:address":"5200 Sunrise Blvd",
    "sg:city":"Fair Oaks",
    "sg:classifiers":[
        {
            "category":"Personal",
            "subcategory":"Beauty Salon",
            "type":"Services"
        }
    ],
    "sg:phone":"+1 916 961 4141",
    "sg:postcode":"95628",
    "sg:province":"CA",
    "sg:tags":[
        "manicuring"
    ],
    "wof:name":"Elegant Nails",
    "wof:placetype":"venue"
},
  "geometry": {"coordinates":[-121.272142,38.663906],"type":"Point"}
}