{
  "type": "Feature",
  "properties": {
    "iso:country":"US",
    "sg:address":"1423 E Washington Ave",
    "sg:city":"El Cajon",
    "sg:classifiers":[
        {
            "category":"Building & Trades",
            "subcategory":"Electrical",
            "type":"Services"
        }
    ],
    "sg:phone":"+1 619 579 3262",
    "sg:postcode":"92019",
    "sg:province":"CA",
    "sg:tags":[
        "electrical",
        "contractor"
    ],
    "wof:name":"Kp Electric",
    "wof:placetype":"venue"
},
  "geometry": {"coordinates":[-116.92936400000001,32.787594],"type":"Point"}
}