{
  "type": "Feature",
  "properties": {
    "iso:country":"US",
    "sg:address":"755 Ashbury Street",
    "sg:city":"San Francisco",
    "sg:classifiers":[
        {
            "category":"Education",
            "subcategory":"Preschool",
            "type":"Public Place"
        },
        {
            "category":"Education",
            "subcategory":"School",
            "type":"Public Place"
        }
    ],
    "sg:phone":"+1 415 661 5232",
    "sg:postcode":"94117",
    "sg:province":"CA",
    "sg:tags":[
        "high",
        "middle",
        "elementary"
    ],
    "wof:name":"Lycee Francais La Perouse-French School",
    "wof:placetype":"venue"
},
  "geometry": {"coordinates":[-122.445999,37.767899],"type":"Point"}
}