{
  "type": "Feature",
  "properties": {
    "iso:country":"US",
    "sg:address":"120 Oakcrest Ct",
    "sg:city":"Danville",
    "sg:classifiers":[
        {
            "category":"Farming",
            "subcategory":"Farm",
            "type":"Manufacturing & Wholesale Goods"
        }
    ],
    "sg:phone":"+1 925 735 1298",
    "sg:postcode":"94526",
    "sg:province":"CA",
    "sg:tags":[
        "crop",
        "general"
    ],
    "wof:name":"Robert Huntoon Farm",
    "wof:placetype":"venue"
},
  "geometry": {"coordinates":[-121.96978,37.790031],"type":"Point"}
}