{
  "type": "Feature",
  "properties": {
    "addr:full":"26929 Caddy Ct El Macero CA 95618",
    "addr:housenumber":"26929",
    "addr:postcode":"95618",
    "addr:street":"Caddy Ct",
    "iso:country":"US",
    "sg:address":"26929 Caddy Ct",
    "sg:city":"El Macero",
    "sg:classifiers":[
        {
            "category":"Home & Garden",
            "subcategory":"Mobile Homes",
            "type":"Retail Goods"
        }
    ],
    "sg:phone":"+1 530 758 3134",
    "sg:postcode":"95618",
    "sg:province":"CA",
    "sg:tags":[
        "commercial",
        "unit"
    ],
    "wof:name":"Pacific Valley Equipment Co",
    "wof:placetype":"venue"
},
  "geometry": {"coordinates":[-121.676278,38.547014],"type":"Point"}
}