{
  "type": "Feature",
  "properties": {
    "addr:full":"339 Wall St Los Angeles CA 90013",
    "addr:housenumber":"339",
    "addr:postcode":"90013",
    "addr:street":"Wall St",
    "iso:country":"US",
    "sg:address":"339 Wall St",
    "sg:city":"Los Angeles",
    "sg:classifiers":[
        {
            "category":"Wholesale",
            "subcategory":"Toys & Hobbies",
            "type":"Manufacturing & Wholesale Goods"
        }
    ],
    "sg:phone":"+1 213 620 1021",
    "sg:postcode":"90013",
    "sg:province":"CA",
    "sg:tags":[
        "doll"
    ],
    "wof:name":"Precious Dolls",
    "wof:placetype":"venue"
},
  "geometry": {"coordinates":[-118.244021,34.047808],"type":"Point"}
}