{
  "type": "Feature",
  "properties": {
    "iso:country":"US",
    "sg:address":"3055 Beyer Blvd",
    "sg:city":"San Diego",
    "sg:classifiers":[
        {
            "category":"Freight",
            "type":"Transportation"
        }
    ],
    "sg:phone":"+1 619 247 1839",
    "sg:postcode":"92154",
    "sg:province":"CA",
    "sg:tags":[
        "operator",
        "local",
        "trucking"
    ],
    "wof:name":"Contreras Trucking",
    "wof:placetype":"venue"
},
  "geometry": {"coordinates":[-117.064758,32.571162],"type":"Point"}
}