{
  "type": "Feature",
  "properties": {
    "iso:country":"US",
    "sg:address":"1624 S Main St",
    "sg:city":"Milpitas",
    "sg:classifiers":[
        {
            "category":"Autos & Motor Vehicles",
            "subcategory":"Auto Supplies",
            "type":"Retail Goods"
        }
    ],
    "sg:phone":"+1 408 416 0061",
    "sg:postcode":"95035",
    "sg:province":"CA",
    "sg:tags":[
        "tire"
    ],
    "wof:name":"Exact Motorsports",
    "wof:placetype":"venue"
},
  "geometry": {"coordinates":[-121.90300000000001,37.4067],"type":"Point"}
}