{
  "type": "Feature",
  "properties": {
    "addr:full":"1676 Delta Ct Hayward CA 94544",
    "addr:housenumber":"1676",
    "addr:postcode":"94544",
    "addr:street":"Delta Ct",
    "iso:country":"US",
    "sg:address":"1676 Delta Ct",
    "sg:city":"Hayward",
    "sg:classifiers":[
        {
            "category":"Home & Garden",
            "subcategory":"Furniture",
            "type":"Retail Goods"
        }
    ],
    "sg:phone":"+1 510 441 5689",
    "sg:postcode":"94544",
    "sg:province":"CA",
    "wof:name":"Patioworld",
    "wof:placetype":"venue"
},
  "geometry": {"coordinates":[-122.063642,37.613751],"type":"Point"}
}