{
  "type": "Feature",
  "properties": {
    "addr:full":"745 W Glenoaks Blvd Glendale CA 91202",
    "addr:housenumber":"745",
    "addr:postcode":"91202",
    "addr:street":"W Glenoaks Blvd",
    "iso:country":"US",
    "sg:address":"745 W Glenoaks Blvd",
    "sg:city":"Glendale",
    "sg:classifiers":[
        {
            "category":"Building & Trades",
            "subcategory":"Equipment Rental",
            "type":"Services"
        }
    ],
    "sg:phone":"+1 800 324 0334",
    "sg:postcode":"91202",
    "sg:province":"CA",
    "sg:tags":[
        "moving"
    ],
    "wof:name":"Econo Box",
    "wof:placetype":"venue"
},
  "geometry": {"coordinates":[-118.272565,34.160334],"type":"Point"}
}