{
  "type": "Feature",
  "properties": {
    "addr:full":"5540 Springdale Ave Pleasanton CA 94588",
    "addr:housenumber":"5540",
    "addr:postcode":"94588",
    "addr:street":"Springdale Ave",
    "iso:country":"US",
    "sg:address":"5540 Springdale Ave",
    "sg:city":"Pleasanton",
    "sg:phone":"+1 925 463 9432",
    "sg:postcode":"94588",
    "sg:province":"CA",
    "wof:name":"Sterling Bridal & Tuxedo",
    "wof:placetype":"venue"
},
  "geometry": {"coordinates":[-121.925883,37.691679],"type":"Point"}
}