{
  "type": "Feature",
  "properties": {
    "iso:country":"US",
    "sg:address":"108 Cabrillo Hwy N",
    "sg:city":"Half Moon Bay",
    "sg:classifiers":[
        {
            "category":"Autos & Motor Vehicles",
            "subcategory":"Automobile Sales",
            "type":"Retail Goods"
        }
    ],
    "sg:phone":"+1 650 726 8220",
    "sg:postcode":"94019",
    "sg:province":"CA",
    "sg:tags":[
        "car",
        "dealer"
    ],
    "wof:name":"B K Motors",
    "wof:placetype":"venue"
},
  "geometry": {"coordinates":[-122.43364800000001,37.46753],"type":"Point"}
}