{
  "type": "Feature",
  "properties": {
    "iso:country":"US",
    "sg:address":"3524 Carlsbad Way",
    "sg:city":"Riverside",
    "sg:classifiers":[
        {
            "category":"Wholesale",
            "subcategory":"Chemicals & Plastics",
            "type":"Manufacturing & Wholesale Goods"
        }
    ],
    "sg:phone":"+1 951 682 7460",
    "sg:postcode":"92506",
    "sg:province":"CA",
    "sg:website":"www.qualitysupplyco.com",
    "wof:name":"Quality Supply Co",
    "wof:placetype":"venue"
},
  "geometry": {"coordinates":[-117.388447,33.950147],"type":"Point"}
}