{
  "type": "Feature",
  "properties": {
    "iso:country":"US",
    "sg:address":"7053 Canoga Ave Ste D",
    "sg:city":"Canoga Park",
    "sg:classifiers":[
        {
            "category":"Retail",
            "subcategory":"Auto Repair",
            "type":"Services"
        }
    ],
    "sg:phone":"+1 818 884 6668",
    "sg:postcode":"91303",
    "sg:province":"CA",
    "wof:name":"Albert Auto Transmission",
    "wof:placetype":"venue"
},
  "geometry": {"coordinates":[-118.598,34.1982],"type":"Point"}
}