{
  "type": "Feature",
  "properties": {
    "addr:full":"151 Van Houten Ave El Cajon CA 92020",
    "addr:housenumber":"151",
    "addr:postcode":"92020",
    "addr:street":"Van Houten Ave",
    "iso:country":"US",
    "sg:address":"151 Van Houten Ave",
    "sg:city":"El Cajon",
    "sg:classifiers":[
        {
            "category":"Manufacturing",
            "subcategory":"Tools & Machinery",
            "type":"Manufacturing & Wholesale Goods"
        }
    ],
    "sg:phone":"+1 619 401 6353",
    "sg:postcode":"92020",
    "sg:province":"CA",
    "sg:tags":[
        "industry",
        "aerospace"
    ],
    "wof:name":"Lockheed Martin Corp",
    "wof:placetype":"venue"
},
  "geometry": {"coordinates":[-116.966093,32.794386],"type":"Point"}
}