{
  "type": "Feature",
  "properties": {
    "iso:country":"US",
    "sg:address":"28992 Sean Dr",
    "sg:city":"Laguna Niguel",
    "sg:classifiers":[
        {
            "category":"Professional",
            "type":"Services"
        }
    ],
    "sg:phone":"+1 949 448 0053",
    "sg:postcode":"92677",
    "sg:province":"CA",
    "wof:name":"Alex J Parsa",
    "wof:placetype":"venue"
},
  "geometry": {"coordinates":[-117.715723,33.542102],"type":"Point"}
}