{
  "type": "Feature",
  "properties": {
    "iso:country":"US",
    "sg:address":"1500 W Capitol Ave",
    "sg:city":"West Sacramento",
    "sg:classifiers":[
        {
            "category":"Restaurant",
            "type":"Food & Drink"
        }
    ],
    "sg:phone":"+1 916 371 8131",
    "sg:postcode":"95691",
    "sg:province":"CA",
    "sg:tags":[
        "chinese"
    ],
    "wof:name":"King's Chinese Restaurant",
    "wof:placetype":"venue"
},
  "geometry": {"coordinates":[-121.52800000000001,38.5807],"type":"Point"}
}