{
  "type": "Feature",
  "properties": {
    "iso:country":"US",
    "sg:address":"2500 Shasta View Dr",
    "sg:city":"Redding",
    "sg:classifiers":[
        {
            "category":"Place Of Worship",
            "subcategory":"Church",
            "type":"Public Place"
        },
        {
            "category":"Place Of Worship",
            "type":"Public Place"
        }
    ],
    "sg:phone":"+1 530 221 6474",
    "sg:postcode":"96002",
    "sg:province":"CA",
    "sg:tags":[
        "lutheran",
        "america",
        "churches-lutheran",
        "churches-lutheran-evangelical"
    ],
    "sg:website":"http://www.stjamesca.com",
    "wof:name":"James Saint Lutheran Church",
    "wof:placetype":"venue"
},
  "geometry": {"coordinates":[-122.325638,40.570919],"type":"Point"}
}