{
  "type": "Feature",
  "properties": {
    "addr:full":"450 S Oxford Ave Los Angeles CA 90020",
    "addr:housenumber":"450",
    "addr:postcode":"90020",
    "addr:street":"S Oxford Ave",
    "iso:country":"US",
    "sg:address":"450 S Oxford Ave",
    "sg:city":"Los Angeles",
    "sg:classifiers":[
        {
            "category":"Professional",
            "subcategory":"Business Services",
            "type":"Services"
        }
    ],
    "sg:phone":"+1 213 820 3452",
    "sg:postcode":"90020",
    "sg:province":"CA",
    "wof:name":"M G Telecom",
    "wof:placetype":"venue"
},
  "geometry": {"coordinates":[-118.307777,34.06627],"type":"Point"}
}