{
  "type": "Feature",
  "properties": {
    "addr:full":"518 Octavia Street San Francisco CA 94102",
    "addr:housenumber":"518",
    "addr:postcode":"94102",
    "addr:street":"Octavia Street",
    "iso:country":"US",
    "sg:address":"518 Octavia Street",
    "sg:city":"San Francisco",
    "sg:classifiers":[
        {
            "category":"Landmark",
            "subcategory":"Tourist Information",
            "type":"Public Place"
        }
    ],
    "sg:phone":"+1 415 626 7007",
    "sg:postcode":"94102",
    "sg:province":"CA",
    "sg:tags":[
        "tour"
    ],
    "sg:website":"www.greatpacifictour.com",
    "wof:name":"Tour Transport",
    "wof:placetype":"venue"
},
  "geometry": {"coordinates":[-122.425003,37.777],"type":"Point"}
}