{
  "type": "Feature",
  "properties": {
    "addr:full":"562 S Los Angeles St Los Angeles CA 90013",
    "addr:housenumber":"562",
    "addr:postcode":"90013",
    "addr:street":"S Los Angeles St",
    "iso:country":"US",
    "sg:address":"562 S Los Angeles St",
    "sg:city":"Los Angeles",
    "sg:classifiers":[
        {
            "category":"Shopping",
            "subcategory":"Discount & Variety Stores",
            "type":"Retail Goods"
        }
    ],
    "sg:phone":"+1 213 628 9978",
    "sg:postcode":"90013",
    "sg:province":"CA",
    "sg:tags":[
        "post",
        "trading"
    ],
    "wof:name":"K Trading Co",
    "wof:placetype":"venue"
},
  "geometry": {"coordinates":[-118.24809999999999,34.04547],"type":"Point"}
}