{
  "type": "Feature",
  "properties": {
    "iso:country":"US",
    "sg:address":"9912 Bus Park Dr",
    "sg:city":"Sacramento",
    "sg:classifiers":[
        {
            "category":"Recreation",
            "subcategory":"Arcade",
            "type":"Entertainment"
        }
    ],
    "sg:phone":"+1 916 363 7746",
    "sg:postcode":"95827",
    "sg:province":"CA",
    "sg:tags":[
        "casino"
    ],
    "wof:name":"Inter Casino Prod California",
    "wof:placetype":"venue"
},
  "geometry": {"coordinates":[-121.33356,38.568848],"type":"Point"}
}