{
  "type": "Feature",
  "properties": {
    "addr:full":"25624 Walnut St Lomita CA 90717",
    "addr:housenumber":"25624",
    "addr:postcode":"90717",
    "addr:street":"Walnut St",
    "iso:country":"US",
    "sg:address":"25624 Walnut St",
    "sg:city":"Lomita",
    "sg:classifiers":[
        {
            "category":"Shopping",
            "subcategory":"Computers & Home Electronics",
            "type":"Retail Goods"
        }
    ],
    "sg:phone":"+1 310 602 4051",
    "sg:postcode":"90717",
    "sg:province":"CA",
    "sg:website":"www.directv.com",
    "wof:name":"DIRECTV",
    "wof:placetype":"venue"
},
  "geometry": {"coordinates":[-118.311874,33.791079],"type":"Point"}
}