{
  "type": "Feature",
  "properties": {
    "addr:full":"9698 Pauline Dr Cypress CA 90630",
    "addr:housenumber":"9698",
    "addr:postcode":"90630",
    "addr:street":"Pauline Dr",
    "iso:country":"US",
    "sg:address":"9698 Pauline Dr",
    "sg:city":"Cypress",
    "sg:classifiers":[
        {
            "category":"Personal",
            "subcategory":"Beauty Salon",
            "type":"Services"
        }
    ],
    "sg:phone":"+1 714 851 9156",
    "sg:postcode":"90630",
    "sg:province":"CA",
    "wof:name":"Unseen Beauty",
    "wof:placetype":"venue"
},
  "geometry": {"coordinates":[-118.023078,33.821452],"type":"Point"}
}