{
  "type": "Feature",
  "properties": {
    "addr:full":"3489 Edison Way Menlo Park CA 94025",
    "addr:housenumber":"3489",
    "addr:postcode":"94025",
    "addr:street":"Edison Way",
    "iso:country":"US",
    "sg:address":"3489 Edison Way",
    "sg:city":"Menlo Park",
    "sg:classifiers":[
        {
            "category":"Shopping",
            "subcategory":"Florist",
            "type":"Retail Goods"
        }
    ],
    "sg:phone":"+1 650 363 0313",
    "sg:postcode":"94025",
    "sg:province":"CA",
    "wof:name":"J Floral Art Inc",
    "wof:placetype":"venue"
},
  "geometry": {"coordinates":[-122.197942,37.476553],"type":"Point"}
}