{
  "type": "Feature",
  "properties": {
    "addr:full":"6519 Fairman St Lakewood CA 90713",
    "addr:housenumber":"6519",
    "addr:postcode":"90713",
    "addr:street":"Fairman St",
    "iso:country":"US",
    "sg:address":"6519 Fairman St",
    "sg:city":"Lakewood",
    "sg:classifiers":[
        {
            "category":"Professional",
            "subcategory":"Computer Services",
            "type":"Services"
        }
    ],
    "sg:phone":"+1 562 249 2424",
    "sg:postcode":"90713",
    "sg:province":"CA",
    "sg:tags":[
        "consultant",
        "designer"
    ],
    "wof:name":"Computer Department",
    "wof:placetype":"venue"
},
  "geometry": {"coordinates":[-118.104581,33.838892],"type":"Point"}
}