{
  "type": "Feature",
  "properties": {
    "iso:country":"US",
    "sg:address":"3172 Campus Dr",
    "sg:city":"San Mateo",
    "sg:classifiers":[
        {
            "category":"Personal",
            "subcategory":"Beauty Salon",
            "type":"Services"
        }
    ],
    "sg:phone":"+1 650 573 8355",
    "sg:postcode":"94497",
    "sg:province":"CA",
    "wof:name":"Finishing Touch Hair & Nails",
    "wof:placetype":"venue"
},
  "geometry": {"coordinates":[-122.327778,37.533332],"type":"Point"}
}