{
  "type": "Feature",
  "properties": {
    "iso:country":"US",
    "sg:address":"12116 Sherman Way",
    "sg:city":"North Hollywood",
    "sg:classifiers":[
        {
            "category":"Banks & Credit Unions",
            "subcategory":"Bank",
            "type":"Services"
        }
    ],
    "sg:phone":"+1 877 766 2202",
    "sg:postcode":"91605",
    "sg:province":"CA",
    "wof:name":"Montana Capital",
    "wof:placetype":"venue"
},
  "geometry": {"coordinates":[-118.39698,34.200609],"type":"Point"}
}