{
  "type": "Feature",
  "properties": {
    "addr:full":"101 Industrial Road Belmont CA 94002",
    "addr:housenumber":"101",
    "addr:postcode":"94002",
    "addr:street":"Industrial Road",
    "iso:country":"US",
    "sg:address":"101 Industrial Road",
    "sg:city":"Belmont",
    "sg:classifiers":[
        {
            "category":"Real Estate",
            "subcategory":"Real Estate Services",
            "type":"Services"
        }
    ],
    "sg:phone":"+1 650 631 1151",
    "sg:postcode":"94002",
    "sg:province":"CA",
    "wof:name":"Harbor Business Center",
    "wof:placetype":"venue"
},
  "geometry": {"coordinates":[-122.26641100000001,37.52125],"type":"Point"}
}