{
  "type": "Feature",
  "properties": {
    "iso:country":"US",
    "sg:address":"530 Nelson Ln",
    "sg:city":"Lincoln",
    "sg:classifiers":[
        {
            "category":"Shopping",
            "subcategory":"Bicycles & Sporting Goods",
            "type":"Retail Goods"
        }
    ],
    "sg:phone":"+1 916 645 7152",
    "sg:postcode":"95648",
    "sg:province":"CA",
    "sg:tags":[
        "equipment",
        "archery",
        "supply"
    ],
    "wof:name":"Flatland Archery Mobile",
    "wof:placetype":"venue"
},
  "geometry": {"coordinates":[-121.340148,38.878178],"type":"Point"}
}