{
  "type": "Feature",
  "properties": {
    "iso:country":"US",
    "sg:address":"9643 Cozycroft Ave",
    "sg:city":"Chatsworth",
    "sg:classifiers":[
        {
            "category":"Freight",
            "type":"Transportation"
        }
    ],
    "sg:phone":"+1 818 709 5296",
    "sg:postcode":"91311",
    "sg:province":"CA",
    "sg:tags":[
        "commercial",
        "storage"
    ],
    "wof:name":"Personal Storage Containers",
    "wof:placetype":"venue"
},
  "geometry": {"coordinates":[-118.582058,34.243753],"type":"Point"}
}