{
  "type": "Feature",
  "properties": {
    "addr:full":"5107 Broadway Oakland CA 94611",
    "addr:housenumber":"5107",
    "addr:postcode":"94611",
    "addr:street":"Broadway",
    "iso:country":"US",
    "sg:address":"5107 Broadway",
    "sg:city":"Oakland",
    "sg:classifiers":[
        {
            "category":"Professional",
            "type":"Services"
        }
    ],
    "sg:phone":"+1 510 653 9120",
    "sg:postcode":"94611",
    "sg:province":"CA",
    "sg:tags":[
        "establishment"
    ],
    "wof:name":"Harper Shields & Cosee Shields",
    "wof:placetype":"venue"
},
  "geometry": {"coordinates":[-122.252388,37.834711],"type":"Point"}
}