{
  "type": "Feature",
  "properties": {
    "iso:country":"US",
    "sg:address":"3200 Bayshore Rd",
    "sg:city":"Benicia",
    "sg:classifiers":[
        {
            "category":"Wholesale",
            "subcategory":"Durable Goods & Equipment",
            "type":"Manufacturing & Wholesale Goods"
        }
    ],
    "sg:phone":"+1 707 745 3655",
    "sg:postcode":"94510",
    "sg:province":"CA",
    "sg:tags":[
        "representative",
        "manufacturer"
    ],
    "wof:name":"R V & Assoc",
    "wof:placetype":"venue"
},
  "geometry": {"coordinates":[-122.128221,38.061263],"type":"Point"}
}