{
  "type": "Feature",
  "properties": {
    "addr:full":"28818 Eagleton St Agoura Hills CA 91301",
    "addr:postcode":"28818;91301",
    "addr:street":"Eagleton St",
    "iso:country":"US",
    "sg:address":"28818 Eagleton St",
    "sg:city":"Agoura Hills",
    "sg:classifiers":[
        {
            "category":"Social Services",
            "subcategory":"Child Care",
            "type":"Services"
        }
    ],
    "sg:phone":"+1 818 889 7675",
    "sg:postcode":"91301",
    "sg:province":"CA",
    "wof:name":"Missan Family Daycare",
    "wof:placetype":"venue"
},
  "geometry": {"coordinates":[-118.753845,34.163128],"type":"Point"}
}