{
  "type": "Feature",
  "properties": {
    "addr:full":"6427 Miles Ln Carmichael CA 95608",
    "addr:housenumber":"6427",
    "addr:postcode":"95608",
    "addr:street":"Miles Ln",
    "iso:country":"US",
    "sg:address":"6427 Miles Ln",
    "sg:city":"Carmichael",
    "sg:classifiers":[
        {
            "category":"Manufacturing",
            "subcategory":"Food",
            "type":"Manufacturing & Wholesale Goods"
        },
        {
            "category":"Food & Beverages",
            "subcategory":"Groceries & Convenience Stores",
            "type":"Retail Goods"
        }
    ],
    "sg:phone":"+1 916 944 2829",
    "sg:postcode":"95608",
    "sg:province":"CA",
    "sg:tags":[
        "product"
    ],
    "wof:name":"Mather",
    "wof:placetype":"venue"
},
  "geometry": {"coordinates":[-121.31452400000001,38.637202],"type":"Point"}
}