{
  "type": "Feature",
  "properties": {
    "iso:country":"US",
    "sg:address":"1706 Indian Hill Blvd",
    "sg:city":"Pomona",
    "sg:classifiers":[
        {
            "category":"Banks & Credit Unions",
            "subcategory":"Investment Brokerage",
            "type":"Services"
        }
    ],
    "sg:phone":"+1 909 626 6474",
    "sg:postcode":"91767",
    "sg:province":"CA",
    "sg:tags":[
        "advisory",
        "financial"
    ],
    "wof:name":"State Wide Financial Inc",
    "wof:placetype":"venue"
},
  "geometry": {"coordinates":[-117.719177,34.079087],"type":"Point"}
}