{
  "type": "Feature",
  "properties": {
    "iso:country":"US",
    "sg:address":"1900 E Palm Canyon Dr",
    "sg:city":"Palm Springs",
    "sg:classifiers":[
        {
            "category":"Travel",
            "subcategory":"Hotels & Motels",
            "type":"Entertainment"
        }
    ],
    "sg:phone":"+1 760 327 1161",
    "sg:postcode":"92264",
    "sg:province":"CA",
    "sg:tags":[
        "resort"
    ],
    "wof:name":"Club Trinidad",
    "wof:placetype":"venue"
},
  "geometry": {"coordinates":[-116.525952,33.801567],"type":"Point"}
}