{
  "type": "Feature",
  "properties": {
    "iso:country":"US",
    "sg:address":"7801 Canoga Ave",
    "sg:city":"Canoga Park",
    "sg:classifiers":[
        {
            "category":"Shopping",
            "subcategory":"Stationery & Office Supplies",
            "type":"Retail Goods"
        }
    ],
    "sg:phone":"+1 818 887 5796",
    "sg:postcode":"91304",
    "sg:province":"CA",
    "sg:tags":[
        "professional",
        "equipment"
    ],
    "wof:name":"San Ho School Corporation",
    "wof:placetype":"venue"
},
  "geometry": {"coordinates":[-118.59753000000001,34.215551],"type":"Point"}
}