{
  "type": "Feature",
  "properties": {
    "iso:country":"US",
    "sg:address":"8690 Aero Dr",
    "sg:city":"San Diego",
    "sg:classifiers":[
        {
            "category":"Insurance",
            "subcategory":"Insurance Agent",
            "type":"Services"
        }
    ],
    "sg:phone":"+1 858 268 5767",
    "sg:postcode":"92123",
    "sg:province":"CA",
    "wof:name":"Allen Thomas Insurance Svcs",
    "wof:placetype":"venue"
},
  "geometry": {"coordinates":[-117.143731,32.809724],"type":"Point"}
}