{
  "type": "Feature",
  "properties": {
    "iso:country":"US",
    "sg:address":"5012 S La Brea Ave",
    "sg:city":"Los Angeles",
    "sg:classifiers":[
        {
            "category":"Retail",
            "subcategory":"Laundry & Dry Cleaning",
            "type":"Services"
        }
    ],
    "sg:phone":"+1 323 291 9100",
    "sg:postcode":"90056",
    "sg:province":"CA",
    "wof:name":"Liberty Cleaners",
    "wof:placetype":"venue"
},
  "geometry": {"coordinates":[-118.358002,33.996399],"type":"Point"}
}