{
  "type": "Feature",
  "properties": {
    "addr:full":"3939 Tweedy Blvd Ste A South Gate CA 90280",
    "addr:housenumber":"3939",
    "addr:postcode":"90280",
    "addr:street":"Tweedy Blvd Ste A;Gate",
    "iso:country":"US",
    "sg:address":"3939 Tweedy Blvd Ste A",
    "sg:city":"South Gate",
    "sg:classifiers":[
        {
            "category":"Insurance",
            "subcategory":"Hazard Insurance",
            "type":"Services"
        },
        {
            "category":"Banks & Credit Unions",
            "subcategory":"Financial Services",
            "type":"Services"
        }
    ],
    "sg:phone":"+1 323 249 5999",
    "sg:postcode":"90280",
    "sg:province":"CA",
    "sg:tags":[
        "broker",
        "mortgage"
    ],
    "wof:name":"Colonial Services Group",
    "wof:placetype":"venue"
},
  "geometry": {"coordinates":[-118.20226700000001,33.943854],"type":"Point"}
}