{
  "type": "Feature",
  "properties": {
    "iso:country":"US",
    "sg:address":"3939 Tweedy Blvd Ste A",
    "sg:city":"South Gate",
    "sg:classifiers":[
        {
            "category":"Insurance",
            "subcategory":"Hazard Insurance",
            "type":"Services"
        },
        {
            "category":"Banks & Credit Unions",
            "subcategory":"Financial Services",
            "type":"Services"
        }
    ],
    "sg:phone":"+1 323 249 5999",
    "sg:postcode":"90280",
    "sg:province":"CA",
    "sg:tags":[
        "broker",
        "mortgage"
    ],
    "wof:name":"Colonial Services Group",
    "wof:placetype":"venue"
},
  "geometry": {"coordinates":[-118.202267,33.943854],"type":"Point"}
}