{
  "type": "Feature",
  "properties": {
    "iso:country":"US",
    "sg:address":"1344 Halidon Way",
    "sg:city":"Folsom",
    "sg:classifiers":[
        {
            "category":"Wholesale",
            "subcategory":"Durable Goods & Equipment",
            "type":"Manufacturing & Wholesale Goods"
        }
    ],
    "sg:phone":"+1 916 983 3385",
    "sg:postcode":"95630",
    "sg:province":"CA",
    "sg:tags":[
        "representative",
        "manufacturer"
    ],
    "wof:name":"Bloom Enterprises",
    "wof:placetype":"venue"
},
  "geometry": {"coordinates":[-121.141253,38.657203],"type":"Point"}
}