{
  "type": "Feature",
  "properties": {
    "addr:full":"8753 Broadway La Mesa CA 91941",
    "addr:housenumber":"8753",
    "addr:postcode":"91941",
    "addr:street":"Broadway",
    "iso:country":"US",
    "sg:address":"8753 Broadway",
    "sg:city":"La Mesa",
    "sg:classifiers":[
        {
            "category":"Professional",
            "subcategory":"Accounting & Tax Preparation",
            "type":"Services"
        }
    ],
    "sg:phone":"+1 619 644 9142",
    "sg:postcode":"91941",
    "sg:province":"CA",
    "sg:tags":[
        "accountant"
    ],
    "wof:name":"Green Larry CPA",
    "wof:placetype":"venue"
},
  "geometry": {"coordinates":[-117.011002,32.751999],"type":"Point"}
}