{
  "type": "Feature",
  "properties": {
    "iso:country":"US",
    "sg:address":"PO Box 500",
    "sg:city":"Tahoe Vista",
    "sg:classifiers":[
        {
            "category":"Bakery",
            "type":"Food & Drink"
        }
    ],
    "sg:phone":"+1 530 546 4698",
    "sg:postcode":"96148",
    "sg:province":"CA",
    "wof:name":"Catered Cannoli Bakery",
    "wof:placetype":"venue"
},
  "geometry": {"coordinates":[-120.057999,39.247101],"type":"Point"}
}