{
  "type": "Feature",
  "properties": {
    "addr:full":"70 Skyview Ter San Rafael CA 94903",
    "addr:housenumber":"70",
    "addr:postcode":"94903",
    "addr:street":"Skyview Ter",
    "iso:country":"US",
    "sg:address":"70 Skyview Ter",
    "sg:city":"San Rafael",
    "sg:classifiers":[
        {
            "category":"Social Services",
            "subcategory":"Child Care",
            "type":"Services"
        }
    ],
    "sg:phone":"+1 415 479 6026",
    "sg:postcode":"94903",
    "sg:province":"CA",
    "sg:tags":[
        "kindergarten",
        "academic",
        "school"
    ],
    "sg:website":"www.oakviewkids.org",
    "wof:name":"Oak View Nursery School",
    "wof:placetype":"venue"
},
  "geometry": {"coordinates":[-122.546716,38.019091],"type":"Point"}
}