{
  "type": "Feature",
  "properties": {
    "addr:full":"4335 Beechwood Pl Riverside CA 92506",
    "addr:housenumber":"4335",
    "addr:postcode":"92506",
    "addr:street":"Beechwood Pl",
    "iso:country":"US",
    "sg:address":"4335 Beechwood Pl",
    "sg:city":"Riverside",
    "sg:classifiers":[
        {
            "category":"Real Estate",
            "subcategory":"Real Estate Operator",
            "type":"Services"
        }
    ],
    "sg:phone":"+1 951 684 7055",
    "sg:postcode":"92506",
    "sg:province":"CA",
    "sg:tags":[
        "apartment"
    ],
    "wof:name":"Sunshine Apartments",
    "wof:placetype":"venue"
},
  "geometry": {"coordinates":[-117.393871,33.971277],"type":"Point"}
}