{
  "type": "Feature",
  "properties": {
    "iso:country":"US",
    "sg:address":"1316 Agate Ave Ste E",
    "sg:city":"Mentone",
    "sg:classifiers":[
        {
            "category":"Autos & Motor Vehicles",
            "subcategory":"Auto Supplies",
            "type":"Retail Goods"
        }
    ],
    "sg:phone":"+1 909 389 0444",
    "sg:postcode":"92359",
    "sg:province":"CA",
    "sg:tags":[
        "part"
    ],
    "wof:name":"Bulletproof Suspension",
    "wof:placetype":"venue"
},
  "geometry": {"coordinates":[-117.124899,34.070452],"type":"Point"}
}