{
  "type": "Feature",
  "properties": {
    "addr:full":"2927 Sacramento St. #11 San Francisco CA 94115",
    "addr:housenumber":"2927",
    "addr:postcode":"94115",
    "addr:street":"Sacramento St. # 11",
    "iso:country":"US",
    "sg:address":"2927 Sacramento St. #11",
    "sg:city":"San Francisco",
    "sg:classifiers":[
        {
            "category":"Professional",
            "subcategory":"Art Services",
            "type":"Services"
        },
        {
            "category":"Professional",
            "subcategory":"Printing & Photocopies",
            "type":"Services"
        }
    ],
    "sg:phone":"+1 415 771 9343",
    "sg:postcode":"94115",
    "sg:province":"CA",
    "sg:tags":[
        "graphic",
        "design"
    ],
    "wof:name":"Ladybug Unlimited",
    "wof:placetype":"venue"
},
  "geometry": {"coordinates":[-122.441181,37.788841],"type":"Point"}
}