{
  "type": "Feature",
  "properties": {
    "iso:country":"US",
    "sg:address":"3131 Stone Valley Rd",
    "sg:city":"Danville",
    "sg:classifiers":[
        {
            "category":"Education",
            "subcategory":"School",
            "type":"Public Place"
        }
    ],
    "sg:phone":"+1 925 552 5530",
    "sg:postcode":"94526",
    "sg:province":"CA",
    "wof:name":"San Ramon, Valley Unified School District",
    "wof:placetype":"venue"
},
  "geometry": {"coordinates":[-121.98268899999999,37.844799],"type":"Point"}
}