{
  "type": "Feature",
  "properties": {
    "iso:country":"US",
    "sg:address":"1944 N Tustin St Ste 111",
    "sg:city":"Orange",
    "sg:classifiers":[
        {
            "category":"Home & Garden",
            "subcategory":"Carpets & Floor Coverings",
            "type":"Retail Goods"
        }
    ],
    "sg:phone":"+1 714 974 6900",
    "sg:postcode":"92865",
    "sg:province":"CA",
    "sg:tags":[
        "flooring"
    ],
    "wof:name":"Fantastic Pergo & Carpet Plus",
    "wof:placetype":"venue"
},
  "geometry": {"coordinates":[-117.835999,33.820301],"type":"Point"}
}