{
  "type": "Feature",
  "properties": {
    "iso:country":"US",
    "sg:address":"608 N Atlantic Blvd",
    "sg:city":"Monterey Park",
    "sg:classifiers":[
        {
            "category":"Utilities",
            "subcategory":"Telephone",
            "type":"Services"
        }
    ],
    "sg:phone":"+1 626 458 0888",
    "sg:postcode":"91754",
    "sg:province":"CA",
    "sg:tags":[
        "telecommunication"
    ],
    "wof:name":"Smarttone Telecom",
    "wof:placetype":"venue"
},
  "geometry": {"coordinates":[-118.134256,34.067217],"type":"Point"}
}