{
  "type": "Feature",
  "properties": {
    "addr:full":"608 N Atlantic Blvd Monterey Park CA 91754",
    "addr:housenumber":"608",
    "addr:postcode":"91754",
    "addr:street":"N Atlantic Blvd",
    "iso:country":"US",
    "sg:address":"608 N Atlantic Blvd",
    "sg:city":"Monterey Park",
    "sg:classifiers":[
        {
            "category":"Utilities",
            "subcategory":"Telephone",
            "type":"Services"
        }
    ],
    "sg:phone":"+1 626 458 0888",
    "sg:postcode":"91754",
    "sg:province":"CA",
    "sg:tags":[
        "telecommunication"
    ],
    "wof:name":"Smarttone Telecom",
    "wof:placetype":"venue"
},
  "geometry": {"coordinates":[-118.13425599999999,34.067217],"type":"Point"}
}