{
  "type": "Feature",
  "properties": {
    "iso:country":"US",
    "sg:address":"1330 Broadway",
    "sg:city":"Oakland",
    "sg:classifiers":[
        {
            "category":"Professional",
            "subcategory":"Accounting & Tax Preparation",
            "type":"Services"
        }
    ],
    "sg:phone":"+1 510 465 9718",
    "sg:postcode":"94612",
    "sg:province":"CA",
    "sg:tags":[
        "accountant"
    ],
    "wof:name":"Lee W Wilson CPA",
    "wof:placetype":"venue"
},
  "geometry": {"coordinates":[-122.27135699999999,37.804056],"type":"Point"}
}