{
  "type": "Feature",
  "properties": {
    "addr:full":"2405 Research Dr Livermore CA 94550",
    "addr:housenumber":"2405",
    "addr:postcode":"94550",
    "addr:street":"Research Dr",
    "iso:country":"US",
    "sg:address":"2405 Research Dr",
    "sg:city":"Livermore",
    "sg:classifiers":[
        {
            "category":"Wholesale",
            "subcategory":"Auto Parts",
            "type":"Manufacturing & Wholesale Goods"
        }
    ],
    "sg:phone":"+1 925 449 0503",
    "sg:postcode":"94550",
    "sg:province":"CA",
    "sg:tags":[
        "automobile",
        "supply"
    ],
    "wof:name":"ALO Sales & Marketing Inc",
    "wof:placetype":"venue"
},
  "geometry": {"coordinates":[-121.720724,37.675598],"type":"Point"}
}