{
  "type": "Feature",
  "properties": {
    "addr:full":"1803 S King Rd San Jose CA 95122",
    "addr:housenumber":"1803",
    "addr:postcode":"95122",
    "addr:street":"S King Rd",
    "iso:country":"US",
    "sg:address":"1803 S King Rd",
    "sg:city":"San Jose",
    "sg:classifiers":[
        {
            "category":"Banks & Credit Unions",
            "subcategory":"Financial Services",
            "type":"Services"
        }
    ],
    "sg:phone":"+1 408 347 9385",
    "sg:postcode":"95122",
    "sg:province":"CA",
    "sg:tags":[
        "broker",
        "mortgage"
    ],
    "wof:name":"M G Financial Service",
    "wof:placetype":"venue"
},
  "geometry": {"coordinates":[-121.834,37.331001],"type":"Point"}
}