{
  "type": "Feature",
  "properties": {
    "addr:full":"18775 Colima Rd Rowland Heights CA 91748",
    "addr:housenumber":"18775",
    "addr:postcode":"91748",
    "addr:street":"Colima Rd",
    "iso:country":"US",
    "sg:address":"18775 Colima Rd",
    "sg:city":"Rowland Heights",
    "sg:classifiers":[
        {
            "category":"Cinema",
            "subcategory":"Movie Rental",
            "type":"Entertainment"
        }
    ],
    "sg:phone":"+1 626 965 9808",
    "sg:postcode":"91748",
    "sg:province":"CA",
    "sg:tags":[
        "leasing",
        "video",
        "disc",
        "tape"
    ],
    "wof:name":"Colima Video Ctr",
    "wof:placetype":"venue"
},
  "geometry": {"coordinates":[-117.89368,33.987821],"type":"Point"}
}