{
  "type": "Feature",
  "properties": {
    "iso:country":"US",
    "sg:address":"14391 Spring Crest Dr",
    "sg:city":"Chino Hills",
    "sg:classifiers":[
        {
            "category":"Health Services",
            "subcategory":"Medical Lab",
            "type":"Services"
        }
    ],
    "sg:phone":"+1 909 590 1159",
    "sg:postcode":"91709",
    "sg:province":"CA",
    "sg:tags":[
        "laboratory"
    ],
    "wof:name":"Omni Diagnostic Imaging",
    "wof:placetype":"venue"
},
  "geometry": {"coordinates":[-117.751396,33.991945],"type":"Point"}
}