{
  "type": "Feature",
  "properties": {
    "iso:country":"US",
    "sg:address":"13609 Victory Blvd",
    "sg:city":"Van Nuys",
    "sg:classifiers":[
        {
            "category":"Shopping",
            "subcategory":"Jewelry",
            "type":"Retail Goods"
        }
    ],
    "sg:phone":"+1 818 782 8711",
    "sg:postcode":"91401",
    "sg:province":"CA",
    "wof:name":"Allercheck Jewelry",
    "wof:placetype":"venue"
},
  "geometry": {"coordinates":[-118.430638,34.186742],"type":"Point"}
}