{
  "type": "Feature",
  "properties": {
    "addr:full":"1211 Edinger Ave Tustin CA 92780",
    "addr:housenumber":"1211",
    "addr:postcode":"92780",
    "addr:street":"Edinger Ave",
    "iso:country":"US",
    "sg:address":"1211 Edinger Ave",
    "sg:city":"Tustin",
    "sg:classifiers":[
        {
            "category":"Wholesale",
            "subcategory":"Hardware",
            "type":"Manufacturing & Wholesale Goods"
        }
    ],
    "sg:phone":"+1 714 259 0109",
    "sg:postcode":"92780",
    "sg:province":"CA",
    "sg:tags":[
        "air",
        "parts",
        "conditioning",
        "supply"
    ],
    "wof:name":"Allied Refrigeration Inc",
    "wof:placetype":"venue"
},
  "geometry": {"coordinates":[-117.830815,33.724051],"type":"Point"}
}