{
  "type": "Feature",
  "properties": {
    "addr:full":"9552 Washington Blvd Culver City CA 90232",
    "addr:housenumber":"9552",
    "addr:postcode":"90232",
    "addr:street":"Washington Blvd",
    "iso:country":"US",
    "sg:address":"9552 Washington Blvd",
    "sg:city":"Culver City",
    "sg:classifiers":[
        {
            "category":"Restaurant",
            "type":"Food & Drink"
        }
    ],
    "sg:phone":"+1 310 559 3809",
    "sg:postcode":"90232",
    "sg:province":"CA",
    "wof:name":"Thai Thai Bbq",
    "wof:placetype":"venue"
},
  "geometry": {"coordinates":[-118.394385,34.023419],"type":"Point"}
}