{
  "type": "Feature",
  "properties": {
    "addr:full":"700 21st St Bakersfield CA 93301",
    "addr:housenumber":"700",
    "addr:postcode":"93301",
    "addr:street":"21St St",
    "iso:country":"US",
    "sg:address":"700 21st St",
    "sg:city":"Bakersfield",
    "sg:classifiers":[
        {
            "category":"Restaurant",
            "type":"Food & Drink"
        }
    ],
    "sg:phone":"+1 661 633 0633",
    "sg:postcode":"93301",
    "sg:province":"CA",
    "wof:name":"Hog's Trof Cafe",
    "wof:placetype":"venue"
},
  "geometry": {"coordinates":[-119.010594,35.3781],"type":"Point"}
}