{
  "type": "Feature",
  "properties": {
    "iso:country":"US",
    "sg:address":"512 Brinkerhoff Ave",
    "sg:city":"Santa Barbara",
    "sg:classifiers":[
        {
            "category":"Food & Beverages",
            "subcategory":"Groceries & Convenience Stores",
            "type":"Retail Goods"
        }
    ],
    "sg:phone":"+1 805 564 8875",
    "sg:postcode":"93101",
    "sg:province":"CA",
    "sg:tags":[
        "product"
    ],
    "wof:name":"Taiko Food Inc",
    "wof:placetype":"venue"
},
  "geometry": {"coordinates":[-119.697743,34.415368],"type":"Point"}
}