{
  "type": "Feature",
  "properties": {
    "addr:full":"7766 Maie Ave Los Angeles CA 90001",
    "addr:housenumber":"7766",
    "addr:postcode":"90001",
    "addr:street":"Maie Ave",
    "iso:country":"US",
    "sg:address":"7766 Maie Ave",
    "sg:city":"Los Angeles",
    "sg:classifiers":[
        {
            "category":"Home & Garden",
            "subcategory":"Furniture",
            "type":"Retail Goods"
        }
    ],
    "sg:phone":"+1 323 588 1272",
    "sg:postcode":"90001",
    "sg:province":"CA",
    "sg:tags":[
        "store"
    ],
    "wof:name":"Valley Furniture",
    "wof:placetype":"venue"
},
  "geometry": {"coordinates":[-118.24428399999999,33.969119],"type":"Point"}
}