{
  "type": "Feature",
  "properties": {
    "iso:country":"US",
    "sg:address":"740 13th St",
    "sg:city":"San Diego",
    "sg:classifiers":[
        {
            "category":"Professional",
            "subcategory":"Art Services",
            "type":"Services"
        }
    ],
    "sg:phone":"+1 619 409 1889",
    "sg:postcode":"92101",
    "sg:province":"CA",
    "sg:tags":[
        "photographer"
    ],
    "wof:name":"Digimage",
    "wof:placetype":"venue"
},
  "geometry": {"coordinates":[-117.15293200000001,32.713231],"type":"Point"}
}