{
  "type": "Feature",
  "properties": {
    "addr:full":"913 W Washington Blvd Los Angeles CA 90015",
    "addr:housenumber":"913",
    "addr:postcode":"90015",
    "addr:street":"W Washington Blvd",
    "iso:country":"US",
    "sg:address":"913 W Washington Blvd",
    "sg:city":"Los Angeles",
    "sg:classifiers":[
        {
            "category":"Manufacturing",
            "subcategory":"Printing",
            "type":"Manufacturing & Wholesale Goods"
        }
    ],
    "sg:phone":"+1 213 744 1878",
    "sg:postcode":"90015",
    "sg:province":"CA",
    "sg:tags":[
        "commercial"
    ],
    "wof:name":"Focus Graphics",
    "wof:placetype":"venue"
},
  "geometry": {"coordinates":[-118.27806,34.037186],"type":"Point"}
}