{
  "type": "Feature",
  "properties": {
    "addr:full":"2590 Folsom St San Francisco CA 94110",
    "addr:housenumber":"2590",
    "addr:postcode":"94110",
    "addr:street":"Folsom St",
    "iso:country":"US",
    "sg:address":"2590 Folsom St",
    "sg:city":"San Francisco",
    "sg:classifiers":[
        {
            "category":"Personal",
            "subcategory":"Beauty Salon",
            "type":"Services"
        }
    ],
    "sg:phone":"+1 415 285 0715",
    "sg:postcode":"94110",
    "sg:province":"CA",
    "wof:name":"Nora's Beauty Salon",
    "wof:placetype":"venue"
},
  "geometry": {"coordinates":[-122.414574,37.757162],"type":"Point"}
}