{
  "type": "Feature",
  "properties": {
    "iso:country":"US",
    "sg:address":"201 Laidley St",
    "sg:city":"San Francisco",
    "sg:classifiers":[
        {
            "category":"Building & Trades",
            "subcategory":"Electrical",
            "type":"Services"
        }
    ],
    "sg:phone":"+1 415 647 1817",
    "sg:postcode":"94131",
    "sg:province":"CA",
    "sg:tags":[
        "electrical",
        "contractor"
    ],
    "wof:name":"Mal Rogers Electric",
    "wof:placetype":"venue"
},
  "geometry": {"coordinates":[-122.428256,37.737744],"type":"Point"}
}