{
  "type": "Feature",
  "properties": {
    "iso:country":"US",
    "sg:address":"6515 Trinity Ct",
    "sg:city":"Dublin",
    "sg:classifiers":[
        {
            "category":"Building & Trades",
            "subcategory":"Construction",
            "type":"Services"
        }
    ],
    "sg:phone":"+1 925 803 4111",
    "sg:postcode":"94568",
    "sg:province":"CA",
    "sg:tags":[
        "concrete",
        "management",
        "contractor"
    ],
    "wof:name":"McE Corporation",
    "wof:placetype":"venue"
},
  "geometry": {"coordinates":[-121.912402,37.709901],"type":"Point"}
}