{
  "type": "Feature",
  "properties": {
    "iso:country":"US",
    "sg:address":"1948 Lomita Blvd",
    "sg:city":"Lomita",
    "sg:classifiers":[
        {
            "category":"Building & Trades",
            "subcategory":"Plumbing",
            "type":"Services"
        }
    ],
    "sg:phone":"+1 562 427 3026",
    "sg:postcode":"90717",
    "sg:province":"CA",
    "sg:tags":[
        "sheet",
        "work",
        "metal",
        "contractor"
    ],
    "wof:name":"Signal Hill Sheet Metal",
    "wof:placetype":"venue"
},
  "geometry": {"coordinates":[-118.314088,33.799807],"type":"Point"}
}