{
  "type": "Feature",
  "properties": {
    "iso:country":"US",
    "sg:address":"851 Theodora St",
    "sg:city":"Nipomo",
    "sg:classifiers":[
        {
            "category":"Building & Trades",
            "subcategory":"Construction",
            "type":"Services"
        }
    ],
    "sg:phone":"+1 805 929 8950",
    "sg:postcode":"93444",
    "sg:province":"CA",
    "sg:tags":[
        "contractor"
    ],
    "wof:name":"Del Sol Builders",
    "wof:placetype":"venue"
},
  "geometry": {"coordinates":[-120.492903,35.028566],"type":"Point"}
}