{
  "type": "Feature",
  "properties": {
    "iso:country":"US",
    "sg:address":"2290 Enrico Fermi Dr",
    "sg:city":"San Diego",
    "sg:classifiers":[
        {
            "category":"Freight",
            "type":"Transportation"
        }
    ],
    "sg:phone":"+1 619 661 1136",
    "sg:postcode":"92154",
    "sg:province":"CA",
    "sg:tags":[
        "forwarding",
        "foreign"
    ],
    "wof:name":"Otay Logistics Inc",
    "wof:placetype":"venue"
},
  "geometry": {"coordinates":[-116.927909,32.55694],"type":"Point"}
}