{
  "type": "Feature",
  "properties": {
    "iso:country":"US",
    "sg:address":"2804 Sombrosa St",
    "sg:city":"Carlsbad",
    "sg:classifiers":[
        {
            "category":"Professional",
            "subcategory":"Management & Consulting",
            "type":"Services"
        }
    ],
    "sg:phone":"+1 619 260 8570",
    "sg:postcode":"92009",
    "sg:province":"CA",
    "sg:tags":[
        "business",
        "software"
    ],
    "wof:name":"Sql Associates Inc",
    "wof:placetype":"venue"
},
  "geometry": {"coordinates":[-117.25079599999999,33.069563],"type":"Point"}
}