{
  "type": "Feature",
  "properties": {
    "iso:country":"US",
    "sg:address":"3150 E Olive Ave",
    "sg:city":"Fresno",
    "sg:classifiers":[
        {
            "category":"Restaurant",
            "type":"Food & Drink"
        }
    ],
    "sg:phone":"+1 559 264 0705",
    "sg:postcode":"93702",
    "sg:province":"CA",
    "sg:tags":[
        "eating"
    ],
    "wof:name":"Laojalurn",
    "wof:placetype":"venue"
},
  "geometry": {"coordinates":[-119.770935,36.757618],"type":"Point"}
}