{
  "type": "Feature",
  "properties": {
    "iso:country":"US",
    "sg:address":"24362 Thomas Ave",
    "sg:city":"Hayward",
    "sg:classifiers":[
        {
            "category":"Organizations",
            "subcategory":"Religious Organization",
            "type":"Services"
        }
    ],
    "sg:phone":"+1 510 886 4815",
    "sg:postcode":"94544",
    "sg:province":"CA",
    "sg:tags":[
        "church"
    ],
    "wof:name":"Bay Area Bible Institute",
    "wof:placetype":"venue"
},
  "geometry": {"coordinates":[-122.082045,37.661364],"type":"Point"}
}