{
  "type": "Feature",
  "properties": {
    "iso:country":"US",
    "sg:address":"1195 Morro Rd",
    "sg:city":"San Marcos",
    "sg:classifiers":[
        {
            "category":"Professional",
            "type":"Services"
        }
    ],
    "sg:phone":"+1 760 745 1322",
    "sg:postcode":"92028",
    "sg:province":"CA",
    "sg:tags":[
        "establishment"
    ],
    "wof:name":"Brown & Brown",
    "wof:placetype":"venue"
},
  "geometry": {"coordinates":[-117.240713,33.367628],"type":"Point"}
}