{
  "type": "Feature",
  "properties": {
    "iso:country":"US",
    "sg:address":"7026 Reseda Blvd",
    "sg:city":"Reseda",
    "sg:classifiers":[
        {
            "category":"Bars & Pubs",
            "type":"Food & Drink"
        },
        {
            "category":"Bars & Pubs",
            "subcategory":"Lounge",
            "type":"Food & Drink"
        }
    ],
    "sg:phone":"+1 818 996 2976",
    "sg:postcode":"91335",
    "sg:province":"CA",
    "sg:tags":[
        "cocktail"
    ],
    "wof:name":"C Frenz",
    "wof:placetype":"venue"
},
  "geometry": {"coordinates":[-118.53604900000001,34.197985],"type":"Point"}
}