{
  "type": "Feature",
  "properties": {
    "iso:country":"US",
    "sg:address":"45767 Flower St",
    "sg:city":"Indio",
    "sg:classifiers":[
        {
            "category":"Retail",
            "subcategory":"Repair Shop",
            "type":"Services"
        }
    ],
    "sg:phone":"+1 760 347 5222",
    "sg:postcode":"92201",
    "sg:province":"CA",
    "sg:tags":[
        "upholsterer"
    ],
    "wof:name":"Liera's Auto Upholstery",
    "wof:placetype":"venue"
},
  "geometry": {"coordinates":[-116.211915,33.715903],"type":"Point"}
}