{
  "type": "Feature",
  "properties": {
    "addr:full":"1020 Etheldore St Moss Beach CA 94038",
    "addr:housenumber":"1020",
    "addr:postcode":"94038",
    "addr:street":"Etheldore St",
    "iso:country":"US",
    "sg:address":"1020 Etheldore St",
    "sg:city":"Moss Beach",
    "sg:classifiers":[
        {
            "category":"Wholesale",
            "subcategory":"Machinery & Supplies",
            "type":"Manufacturing & Wholesale Goods"
        },
        {
            "category":"Wholesale",
            "subcategory":"Electrical",
            "type":"Manufacturing & Wholesale Goods"
        }
    ],
    "sg:phone":"+1 650 728 8822",
    "sg:postcode":"94038",
    "sg:province":"CA",
    "sg:tags":[
        "test",
        "equipment",
        "testing",
        "electronic",
        "measure"
    ],
    "wof:name":"Coastside Test Measurement Inc",
    "wof:placetype":"venue"
},
  "geometry": {"coordinates":[-122.508912,37.525243],"type":"Point"}
}