{
  "type": "Feature",
  "properties": {
    "addr:full":"12137 Main St Fort Jones CA 96032",
    "addr:housenumber":"12137",
    "addr:postcode":"96032",
    "addr:street":"Main St",
    "iso:country":"US",
    "sg:address":"12137 Main St",
    "sg:city":"Fort Jones",
    "sg:classifiers":[
        {
            "category":"Manufacturing",
            "subcategory":"Lumber",
            "type":"Manufacturing & Wholesale Goods"
        }
    ],
    "sg:phone":"+1 530 468 2696",
    "sg:postcode":"96032",
    "sg:province":"CA",
    "sg:tags":[
        "government"
    ],
    "wof:name":"Forestry & Fire Protection",
    "wof:placetype":"venue"
},
  "geometry": {"coordinates":[-122.84122600000001,41.608008],"type":"Point"}
}