{
  "type": "Feature",
  "properties": {
    "iso:country":"US",
    "sg:address":"2025 Gateway Pl",
    "sg:city":"San Jose",
    "sg:classifiers":[
        {
            "category":"Insurance",
            "subcategory":"Insurance Agent",
            "type":"Services"
        }
    ],
    "sg:phone":"+1 408 453 2130",
    "sg:postcode":"95110",
    "sg:province":"CA",
    "wof:name":"Great-West Life & Annuity Ins",
    "wof:placetype":"venue"
},
  "geometry": {"coordinates":[-121.922342,37.370649],"type":"Point"}
}