{
  "type": "Feature",
  "properties": {
    "iso:country":"US",
    "sg:address":"318 N Hollywood Way",
    "sg:city":"Burbank",
    "sg:classifiers":[
        {
            "category":"Real Estate",
            "subcategory":"Real Estate Agent",
            "type":"Services"
        }
    ],
    "sg:phone":"+1 818 238 0090",
    "sg:postcode":"91505",
    "sg:province":"CA",
    "sg:tags":[
        "management",
        "property"
    ],
    "wof:name":"T And T Property Management",
    "wof:placetype":"venue"
},
  "geometry": {"coordinates":[-118.34138799999999,34.156669],"type":"Point"}
}