{
  "type": "Feature",
  "properties": {
    "iso:country":"US",
    "sg:address":"647 Tully Rd",
    "sg:city":"San Jose",
    "sg:classifiers":[
        {
            "category":"Home & Garden",
            "subcategory":"Carpets & Floor Coverings",
            "type":"Retail Goods"
        }
    ],
    "sg:phone":"+1 408 298 2515",
    "sg:postcode":"95111",
    "sg:province":"CA",
    "sg:tags":[
        "dealer",
        "rug"
    ],
    "wof:name":"Profess Oriental Rug",
    "wof:placetype":"venue"
},
  "geometry": {"coordinates":[-121.846023,37.309101],"type":"Point"}
}