{
  "type": "Feature",
  "properties": {
    "addr:full":"525 N 21st St San Jose CA 95112",
    "addr:housenumber":"525",
    "addr:postcode":"95112",
    "addr:street":"N 21St St",
    "iso:country":"US",
    "sg:address":"525 N 21st St",
    "sg:city":"San Jose",
    "sg:classifiers":[
        {
            "category":"Arts & Performance",
            "subcategory":"Arts Center",
            "type":"Entertainment"
        }
    ],
    "sg:phone":"+1 510 393 7976",
    "sg:postcode":"95112",
    "sg:province":"CA",
    "sg:tags":[
        "performing"
    ],
    "sg:website":"www.mysteriesforhire.com/index.html",
    "wof:name":"Hit & Run Productions",
    "wof:placetype":"venue"
},
  "geometry": {"coordinates":[-121.87778299999999,37.35464],"type":"Point"}
}