{
  "type": "Feature",
  "properties": {
    "iso:country":"US",
    "sg:address":"6001 Clubhouse Dr",
    "sg:city":"Rancho Santa Fe",
    "sg:classifiers":[
        {
            "category":"Recreation",
            "type":"Entertainment"
        }
    ],
    "sg:phone":"+1 858 759 5500",
    "sg:postcode":"92067",
    "sg:province":"CA",
    "sg:tags":[
        "club",
        "country"
    ],
    "wof:name":"Del Mar Country Club",
    "wof:placetype":"venue"
},
  "geometry": {"coordinates":[-117.193574,32.977897],"type":"Point"}
}