{
  "type": "Feature",
  "properties": {
    "addr:full":"11180 Warner Ave Ste 161 Fountain Valley CA 92708",
    "addr:housenumber":"11180",
    "addr:postcode":"92708",
    "addr:street":"Warner Ave Ste 161",
    "iso:country":"US",
    "sg:address":"11180 Warner Ave Ste 161",
    "sg:city":"Fountain Valley",
    "sg:classifiers":[
        {
            "category":"Health Services",
            "subcategory":"Doctor",
            "type":"Services"
        }
    ],
    "sg:phone":"+1 714 557 2905",
    "sg:postcode":"92708",
    "sg:province":"CA",
    "wof:name":"Duy Andy D MD",
    "wof:placetype":"venue"
},
  "geometry": {"coordinates":[-117.93335999999999,33.715733],"type":"Point"}
}