{
  "type": "Feature",
  "properties": {
    "addr:full":"133 Plaza Dr Vallejo CA 94591",
    "addr:housenumber":"133",
    "addr:postcode":"94591",
    "addr:street":"Plaza Dr",
    "iso:country":"US",
    "sg:address":"133 Plaza Dr",
    "sg:city":"Vallejo",
    "sg:classifiers":[
        {
            "category":"Shopping",
            "subcategory":"Department Store",
            "type":"Retail Goods"
        }
    ],
    "sg:phone":"+1 707 552 9565",
    "sg:postcode":"94591",
    "sg:province":"CA",
    "wof:name":"Ross Dress For Less",
    "wof:placetype":"venue"
},
  "geometry": {"coordinates":[-122.21681,38.132763],"type":"Point"}
}