{
  "type": "Feature",
  "properties": {
    "iso:country":"US",
    "sg:address":"1630 Sierra Ave",
    "sg:city":"Yuba City",
    "sg:classifiers":[
        {
            "category":"Wholesale",
            "subcategory":"Electrical",
            "type":"Manufacturing & Wholesale Goods"
        }
    ],
    "sg:phone":"+1 530 673 7010",
    "sg:postcode":"95993",
    "sg:province":"CA",
    "sg:tags":[
        "equipment",
        "electric",
        "supply"
    ],
    "wof:name":"A Hi Lite Electric Co",
    "wof:placetype":"venue"
},
  "geometry": {"coordinates":[-121.648511,39.14038],"type":"Point"}
}