{
  "type": "Feature",
  "properties": {
    "addr:full":"2578 Rubidoux Blvd Riverside CA 92509",
    "addr:housenumber":"2578",
    "addr:postcode":"92509",
    "addr:street":"Rubidoux Blvd",
    "iso:country":"US",
    "sg:address":"2578 Rubidoux Blvd",
    "sg:city":"Riverside",
    "sg:classifiers":[
        {
            "category":"Building & Trades",
            "subcategory":"Equipment Rental",
            "type":"Services"
        }
    ],
    "sg:phone":"+1 951 683 2598",
    "sg:postcode":"92509",
    "sg:province":"CA",
    "sg:tags":[
        "yard"
    ],
    "wof:name":"Green Brothers Equip Rentals",
    "wof:placetype":"venue"
},
  "geometry": {"coordinates":[-117.39232800000001,34.01355],"type":"Point"}
}