{
  "type": "Feature",
  "properties": {
    "addr:full":"10025 de Soto Ave Apt 241 Chatsworth CA 91311",
    "addr:housenumber":"241",
    "addr:postcode":"10025;91311",
    "addr:street":"De Soto Ave Apt",
    "iso:country":"US",
    "sg:address":"10025 de Soto Ave Apt 241",
    "sg:city":"Chatsworth",
    "sg:classifiers":[
        {
            "category":"Farming",
            "subcategory":"Farm",
            "type":"Manufacturing & Wholesale Goods"
        }
    ],
    "sg:phone":"+1 818 970 6030",
    "sg:postcode":"91311",
    "sg:province":"CA",
    "wof:name":"West Wind Farms",
    "wof:placetype":"venue"
},
  "geometry": {"coordinates":[-118.58856900000001,34.25225],"type":"Point"}
}