{
  "type": "Feature",
  "properties": {
    "addr:full":"424 Mill St Colton CA 92324",
    "addr:housenumber":"424",
    "addr:postcode":"92324",
    "addr:street":"Mill St",
    "iso:country":"US",
    "sg:address":"424 Mill St",
    "sg:city":"Colton",
    "sg:classifiers":[
        {
            "category":"Food & Beverages",
            "subcategory":"Groceries & Convenience Stores",
            "type":"Retail Goods"
        }
    ],
    "sg:phone":"+1 909 888 1188",
    "sg:postcode":"92324",
    "sg:province":"CA",
    "sg:tags":[
        "market"
    ],
    "wof:name":"G & G Liquor",
    "wof:placetype":"venue"
},
  "geometry": {"coordinates":[-117.32867899999999,34.092083],"type":"Point"}
}