{
  "type": "Feature",
  "properties": {
    "iso:country":"US",
    "sg:address":"3233 Yosemite Ave",
    "sg:city":"El Cerrito",
    "sg:classifiers":[
        {
            "category":"Taxi",
            "type":"Transportation"
        }
    ],
    "sg:phone":"+1 510 222 7433",
    "sg:postcode":"94530",
    "sg:province":"CA",
    "sg:tags":[
        "taxicab"
    ],
    "wof:name":"Cab Ride",
    "wof:placetype":"venue"
},
  "geometry": {"coordinates":[-122.30519,37.901047],"type":"Point"}
}