{
  "type": "Feature",
  "properties": {
    "addr:full":"5952 Las Virgenes Rd Calabasas CA 91302",
    "addr:housenumber":"5952",
    "addr:postcode":"91302",
    "addr:street":"Las Virgenes Rd",
    "iso:country":"US",
    "sg:address":"5952 Las Virgenes Rd",
    "sg:city":"Calabasas",
    "sg:classifiers":[
        {
            "category":"Building & Trades",
            "subcategory":"Construction",
            "type":"Services"
        }
    ],
    "sg:phone":"+1 818 991 0527",
    "sg:postcode":"91302",
    "sg:province":"CA",
    "sg:tags":[
        "home",
        "improvement"
    ],
    "wof:name":"First Time",
    "wof:placetype":"venue"
},
  "geometry": {"coordinates":[-118.702675,34.166963],"type":"Point"}
}