{
  "type": "Feature",
  "properties": {
    "iso:country":"US",
    "sg:address":"1031 Barstow Ave",
    "sg:city":"Clovis",
    "sg:classifiers":[
        {
            "category":"Manufacturing",
            "subcategory":"Printing",
            "type":"Manufacturing & Wholesale Goods"
        }
    ],
    "sg:phone":"+1 559 299 7100",
    "sg:postcode":"93612",
    "sg:province":"CA",
    "sg:tags":[
        "commercial",
        "offset"
    ],
    "wof:name":"Clovis Printing Co Inc",
    "wof:placetype":"venue"
},
  "geometry": {"coordinates":[-119.696598,36.815848],"type":"Point"}
}