{
  "type": "Feature",
  "properties": {
    "addr:full":"6758 Eddinghill Dr Rancho Palos Verdes CA 90275",
    "addr:housenumber":"6758",
    "addr:postcode":"90275",
    "addr:street":"Eddinghill Dr",
    "iso:country":"US",
    "sg:address":"6758 Eddinghill Dr",
    "sg:city":"Rancho Palos Verdes",
    "sg:classifiers":[
        {
            "category":"Wholesale",
            "subcategory":"Stationery",
            "type":"Manufacturing & Wholesale Goods"
        }
    ],
    "sg:phone":"+1 310 265 9666",
    "sg:postcode":"90275",
    "sg:province":"CA",
    "sg:tags":[
        "supply"
    ],
    "wof:name":"Schoolmax LLC",
    "wof:placetype":"venue"
},
  "geometry": {"coordinates":[-118.395246,33.773485],"type":"Point"}
}