{
  "type": "Feature",
  "properties": {
    "addr:full":"3338 Elizabeth Ave Lynwood CA 90262",
    "addr:housenumber":"3338",
    "addr:postcode":"90262",
    "addr:street":"Elizabeth Ave",
    "iso:country":"US",
    "sg:address":"3338 Elizabeth Ave",
    "sg:city":"Lynwood",
    "sg:classifiers":[
        {
            "category":"Freight",
            "type":"Transportation"
        }
    ],
    "sg:phone":"+1 310 638 8621",
    "sg:postcode":"90262",
    "sg:province":"CA",
    "sg:tags":[
        "operator",
        "local",
        "trucking"
    ],
    "wof:name":"Hid & Sons Trucking",
    "wof:placetype":"venue"
},
  "geometry": {"coordinates":[-118.210729,33.93417],"type":"Point"}
}