{
  "type": "Feature",
  "properties": {
    "addr:full":"9121 Jurupa Rd Riverside CA 92509",
    "addr:housenumber":"9121",
    "addr:postcode":"92509",
    "addr:street":"Jurupa Rd",
    "iso:country":"US",
    "sg:address":"9121 Jurupa Rd",
    "sg:city":"Riverside",
    "sg:classifiers":[
        {
            "category":"Food & Beverages",
            "subcategory":"Liquor & Beverages",
            "type":"Retail Goods"
        }
    ],
    "sg:phone":"+1 951 681 0400",
    "sg:postcode":"92509",
    "sg:province":"CA",
    "wof:name":"Plaza Liquors",
    "wof:placetype":"venue"
},
  "geometry": {"coordinates":[-117.477152,33.999164],"type":"Point"}
}