{
  "type": "Feature",
  "properties": {
    "addr:full":"1811 N D St San Bernardino CA 92405",
    "addr:housenumber":"1811",
    "addr:postcode":"92405",
    "addr:street":"N D St",
    "iso:country":"US",
    "sg:address":"1811 N D St",
    "sg:city":"San Bernardino",
    "sg:classifiers":[
        {
            "category":"Organizations",
            "subcategory":"Non-profit Organization",
            "type":"Services"
        }
    ],
    "sg:phone":"+1 909 381 5388",
    "sg:postcode":"92405",
    "sg:province":"CA",
    "wof:name":"San Bernardino Symphony",
    "wof:placetype":"venue"
},
  "geometry": {"coordinates":[-117.291847,34.132556],"type":"Point"}
}