{
  "type": "Feature",
  "properties": {
    "addr:full":"1170 Lombardi Ave Petaluma CA 94954",
    "addr:housenumber":"1170",
    "addr:postcode":"94954",
    "addr:street":"Lombardi Ave",
    "iso:country":"US",
    "sg:address":"1170 Lombardi Ave",
    "sg:city":"Petaluma",
    "sg:classifiers":[
        {
            "category":"Professional",
            "subcategory":"Business Services",
            "type":"Services"
        }
    ],
    "sg:phone":"+1 707 769 0911",
    "sg:postcode":"94954",
    "sg:province":"CA",
    "sg:tags":[
        "interior",
        "consultant",
        "design",
        "decorator"
    ],
    "wof:name":"Interior Impressions",
    "wof:placetype":"venue"
},
  "geometry": {"coordinates":[-122.618285,38.238735],"type":"Point"}
}