{
  "type": "Feature",
  "properties": {
    "addr:full":"406 Brannan Street San Francisco CA 94107",
    "addr:housenumber":"406",
    "addr:postcode":"94107",
    "addr:street":"Brannan Street",
    "iso:country":"US",
    "sg:address":"406 Brannan Street",
    "sg:city":"San Francisco",
    "sg:classifiers":[
        {
            "category":"Professional",
            "subcategory":"Art Services",
            "type":"Services"
        }
    ],
    "sg:phone":"+1 415 567 6222",
    "sg:postcode":"94107",
    "sg:province":"CA",
    "sg:tags":[
        "graphic",
        "design"
    ],
    "sg:website":"rise-and-shine.com/",
    "wof:name":"Rise-and-Shine Studio",
    "wof:placetype":"venue"
},
  "geometry": {"coordinates":[-122.39443,37.779986],"type":"Point"}
}