{
  "type": "Feature",
  "properties": {
    "iso:country":"US",
    "sg:address":"760 8th Ave",
    "sg:city":"San Diego",
    "sg:classifiers":[
        {
            "category":"Shopping",
            "subcategory":"Stationery & Office Supplies",
            "type":"Retail Goods"
        }
    ],
    "sg:phone":"+1 619 702 6290",
    "sg:postcode":"92101",
    "sg:province":"CA",
    "sg:tags":[
        "album",
        "scrapbook"
    ],
    "wof:name":"Scrapbook Diva Crop Lounge",
    "wof:placetype":"venue"
},
  "geometry": {"coordinates":[-117.15749,32.712994],"type":"Point"}
}