{
  "type": "Feature",
  "properties": {
    "addr:full":"16127 Foothill Blvd Fontana CA 92335",
    "addr:housenumber":"16127",
    "addr:postcode":"92335",
    "addr:street":"Foothill Blvd",
    "iso:country":"US",
    "sg:address":"16127 Foothill Blvd",
    "sg:city":"Fontana",
    "sg:classifiers":[
        {
            "category":"Health Services",
            "subcategory":"Doctor",
            "type":"Services"
        }
    ],
    "sg:phone":"+1 909 350 8110",
    "sg:postcode":"92335",
    "sg:province":"CA",
    "sg:tags":[
        "clinic"
    ],
    "wof:name":"Benny Guzman",
    "wof:placetype":"venue"
},
  "geometry": {"coordinates":[-117.449433,34.106497],"type":"Point"}
}