{
  "type": "Feature",
  "properties": {
    "addr:full":"314 Columbus Ave San Francisco CA 94133",
    "addr:housenumber":"314",
    "addr:postcode":"94133",
    "addr:street":"Columbus Ave",
    "iso:country":"US",
    "sg:address":"314 Columbus Ave",
    "sg:city":"San Francisco",
    "sg:classifiers":[
        {
            "category":"Restaurant",
            "type":"Food & Drink"
        }
    ],
    "sg:menulink":"http://www.allmenus.com/ca/san-francisco/276465-pizzelle-di-north-beach/menu/",
    "sg:phone":"+1 415 398 3555",
    "sg:postcode":"94133",
    "sg:province":"CA",
    "sg:tags":[
        "american",
        "italian",
        "pizza"
    ],
    "wof:name":"Pizzelle Di North Beach",
    "wof:placetype":"venue"
},
  "geometry": {"coordinates":[-122.406705,37.798103],"type":"Point"}
}