{
  "type": "Feature",
  "properties": {
    "addr:full":"1851 Ximeno Ave Long Beach CA 90815",
    "addr:housenumber":"1851",
    "addr:postcode":"90815",
    "addr:street":"Ximeno Ave",
    "iso:country":"US",
    "sg:address":"1851 Ximeno Ave",
    "sg:city":"Long Beach",
    "sg:classifiers":[
        {
            "category":"Shopping",
            "subcategory":"Bicycles & Sporting Goods",
            "type":"Retail Goods"
        }
    ],
    "sg:phone":"+1 562 985 0668",
    "sg:postcode":"90815",
    "sg:province":"CA",
    "sg:tags":[
        "equipment",
        "skateboard"
    ],
    "wof:name":"United Board Shop",
    "wof:placetype":"venue"
},
  "geometry": {"coordinates":[-118.139231,33.791501],"type":"Point"}
}