{
  "type": "Feature",
  "properties": {
    "addr:full":"716 E 21st St Bakersfield CA 93305",
    "addr:housenumber":"716",
    "addr:postcode":"93305",
    "addr:street":"E 21St St",
    "iso:country":"US",
    "sg:address":"716 E 21st St",
    "sg:city":"Bakersfield",
    "sg:classifiers":[
        {
            "category":"Government",
            "subcategory":"Fire Station",
            "type":"Public Place"
        }
    ],
    "sg:phone":"+1 661 631 8720",
    "sg:postcode":"93305",
    "sg:province":"CA",
    "sg:tags":[
        "department"
    ],
    "wof:name":"Bakersfield Fire Station",
    "wof:placetype":"venue"
},
  "geometry": {"coordinates":[-118.991895,35.375611],"type":"Point"}
}