{
  "type": "Feature",
  "properties": {
    "iso:country":"US",
    "sg:address":"393 Millar Ave",
    "sg:city":"El Cajon",
    "sg:classifiers":[
        {
            "category":"Building & Trades",
            "subcategory":"Landscaping Services",
            "type":"Services"
        }
    ],
    "sg:phone":"+1 619 447 6789",
    "sg:postcode":"92020",
    "sg:province":"CA",
    "wof:name":"Orozco Prof Tree Svc",
    "wof:placetype":"venue"
},
  "geometry": {"coordinates":[-116.9743,32.794872],"type":"Point"}
}