{
  "type": "Feature",
  "properties": {
    "addr:full":"Chess & Burman Salon 9911 W Pico Blvd Ste 200 Los Angeles CA 90015",
    "addr:housenumber":"9911",
    "addr:postcode":"90015",
    "addr:street":"W Pico Blvd Ste 200",
    "iso:country":"US",
    "sg:address":"Chess & Burman Salon 9911 W Pico Blvd Ste 200",
    "sg:city":"Los Angeles",
    "sg:classifiers":[
        {
            "category":"Personal",
            "subcategory":"Beauty Salon",
            "type":"Services"
        }
    ],
    "sg:phone":"+1 310 560 9085",
    "sg:postcode":"90015",
    "sg:province":"CA",
    "sg:tags":[
        "hair"
    ],
    "sg:website":"www.frankbarron.com",
    "wof:name":"Frank Barron",
    "wof:placetype":"venue"
},
  "geometry": {"coordinates":[-118.38846100000001,34.080547],"type":"Point"}
}