{
  "type": "Feature",
  "properties": {
    "addr:full":"1802 E Katella Ave Orange CA 92867",
    "addr:housenumber":"1802",
    "addr:postcode":"92867",
    "addr:street":"E Katella Ave",
    "iso:country":"US",
    "sg:address":"1802 E Katella Ave",
    "sg:city":"Orange",
    "sg:classifiers":[
        {
            "category":"Shopping",
            "subcategory":"Crafts & Fabrics",
            "type":"Retail Goods"
        }
    ],
    "sg:phone":"+1 714 289 8792",
    "sg:postcode":"92867",
    "sg:province":"CA",
    "sg:tags":[
        "art"
    ],
    "sg:website":"www.michaels.com",
    "wof:name":"Michaels Arts & Crafts",
    "wof:placetype":"venue"
},
  "geometry": {"coordinates":[-117.834999,33.809101],"type":"Point"}
}