{
  "type": "Feature",
  "properties": {
    "iso:country":"US",
    "sg:address":"2690 N State St",
    "sg:city":"San Bernardino",
    "sg:classifiers":[
        {
            "category":"Building & Trades",
            "subcategory":"Electrical",
            "type":"Services"
        }
    ],
    "sg:phone":"+1 909 887 9199",
    "sg:postcode":"92407",
    "sg:province":"CA",
    "sg:tags":[
        "electric",
        "contractor"
    ],
    "wof:name":"JME Mechanical Contractors",
    "wof:placetype":"venue"
},
  "geometry": {"coordinates":[-117.33555699999999,34.145291],"type":"Point"}
}