{
  "type": "Feature",
  "properties": {
    "iso:country":"US",
    "sg:address":"46225 Verba Santa Dr",
    "sg:city":"Palm Desert",
    "sg:classifiers":[
        {
            "category":"Wholesale",
            "subcategory":"Office Equipment",
            "type":"Manufacturing & Wholesale Goods"
        }
    ],
    "sg:phone":"+1 760 346 1224",
    "sg:postcode":"92260",
    "sg:province":"CA",
    "wof:name":"Charles Bennett",
    "wof:placetype":"venue"
},
  "geometry": {"coordinates":[-116.39282900000001,33.71237],"type":"Point"}
}