{
  "type": "Feature",
  "properties": {
    "iso:country":"US",
    "sg:address":"4386 Silverberry Dr",
    "sg:city":"San Jose",
    "sg:classifiers":[
        {
            "category":"Building & Trades",
            "subcategory":"Landscaping Services",
            "type":"Services"
        }
    ],
    "sg:phone":"+1 408 281 2818",
    "sg:postcode":"95136",
    "sg:province":"CA",
    "wof:name":"Doans Gardening",
    "wof:placetype":"venue"
},
  "geometry": {"coordinates":[-121.835133,37.270958],"type":"Point"}
}