{
  "type": "Feature",
  "properties": {
    "addr:full":"6215 Topanga Canyon Blvd Woodland Hills CA 91367",
    "addr:housenumber":"6215",
    "addr:postcode":"91367",
    "addr:street":"Topanga Canyon Blvd",
    "iso:country":"US",
    "sg:address":"6215 Topanga Canyon Blvd",
    "sg:city":"Woodland Hills",
    "sg:classifiers":[
        {
            "category":"Retail",
            "subcategory":"Laundry & Dry Cleaning",
            "type":"Services"
        }
    ],
    "sg:phone":"+1 818 713 2658",
    "sg:postcode":"91367",
    "sg:province":"CA",
    "sg:tags":[
        "cleaners"
    ],
    "wof:name":"Tic Toc Cleaners",
    "wof:placetype":"venue"
},
  "geometry": {"coordinates":[-118.605885,34.186668],"type":"Point"}
}