{
  "type": "Feature",
  "properties": {
    "addr:full":"1315 Crestmont Dr Angwin CA 94508",
    "addr:housenumber":"1315",
    "addr:postcode":"94508",
    "addr:street":"Crestmont Dr",
    "iso:country":"US",
    "sg:address":"1315 Crestmont Dr",
    "sg:city":"Angwin",
    "sg:classifiers":[
        {
            "category":"Education",
            "subcategory":"School",
            "type":"Public Place"
        }
    ],
    "sg:phone":"+1 707 965 1371",
    "sg:postcode":"94508",
    "sg:province":"CA",
    "wof:name":"CA Acad Perfrmng Art",
    "wof:placetype":"venue"
},
  "geometry": {"coordinates":[-122.463375,38.554636],"type":"Point"}
}