{
  "type": "Feature",
  "properties": {
    "addr:full":"4300 Sisk Rd Modesto CA 95356",
    "addr:housenumber":"4300",
    "addr:postcode":"ca 95356",
    "addr:street":"Sisk Rd",
    "iso:country":"US",
    "sg:address":"4300 Sisk Rd",
    "sg:city":"Modesto",
    "sg:classifiers":[
        {
            "category":"Building & Trades",
            "subcategory":"Landscaping Services",
            "type":"Services"
        }
    ],
    "sg:phone":"+1 209 572 3771",
    "sg:postcode":"95356",
    "sg:province":"CA",
    "sg:tags":[
        "consultant",
        "designer",
        "landscape"
    ],
    "wof:name":"Westfall Design Studio",
    "wof:placetype":"venue"
},
  "geometry": {"coordinates":[-121.070938,37.70158],"type":"Point"}
}