{
  "type": "Feature",
  "properties": {
    "iso:country":"US",
    "sg:address":"1084 Cannon Rd",
    "sg:city":"Riverside",
    "sg:classifiers":[
        {
            "category":"Personal",
            "subcategory":"Beauty Salon",
            "type":"Services"
        }
    ],
    "sg:phone":"+1 951 215 0655",
    "sg:postcode":"92506",
    "sg:province":"CA",
    "wof:name":"Dazzled",
    "wof:placetype":"venue"
},
  "geometry": {"coordinates":[-117.335831,33.92366],"type":"Point"}
}