{
  "type": "Feature",
  "properties": {
    "addr:full":"1064 Emerald Bay Rd South Lake Tahoe CA 96150",
    "addr:housenumber":"1064",
    "addr:postcode":"96150",
    "addr:street":"Emerald Bay Rd",
    "iso:country":"US",
    "sg:address":"1064 Emerald Bay Rd",
    "sg:city":"South Lake Tahoe",
    "sg:classifiers":[
        {
            "category":"Coffee & Tea",
            "type":"Food & Drink"
        }
    ],
    "sg:menulink":"http://www.allmenus.com/ca/south-lake-tahoe/116517-starbucks-coffee/menu/",
    "sg:phone":"+1 530 544 4490",
    "sg:postcode":"96150",
    "sg:province":"CA",
    "sg:tags":[
        "american"
    ],
    "wof:name":"Starbucks Coffee",
    "wof:placetype":"venue"
},
  "geometry": {"coordinates":[-120.003445,38.911258],"type":"Point"}
}