{
  "type": "Feature",
  "properties": {
    "iso:country":"US",
    "sg:address":"520 Jefferson St",
    "sg:city":"Hayward",
    "sg:classifiers":[
        {
            "category":"Education",
            "subcategory":"School",
            "type":"Public Place"
        }
    ],
    "sg:phone":"+1 510 293 8567",
    "sg:postcode":"94544",
    "sg:province":"CA",
    "wof:name":"Bowman Elementary School",
    "wof:placetype":"venue"
},
  "geometry": {"coordinates":[-122.061961,37.641594],"type":"Point"}
}