{
  "type": "Feature",
  "properties": {
    "iso:country":"US",
    "sg:address":"16124 Koala Rd",
    "sg:city":"Adelanto",
    "sg:classifiers":[
        {
            "category":"Building & Trades",
            "subcategory":"Construction",
            "type":"Services"
        }
    ],
    "sg:phone":"+1 760 246 0011",
    "sg:postcode":"92301",
    "sg:province":"CA",
    "sg:tags":[
        "finishing",
        "wood",
        "refinishing"
    ],
    "wof:name":"Primer Wood Products",
    "wof:placetype":"venue"
},
  "geometry": {"coordinates":[-117.45391600000001,34.543347],"type":"Point"}
}