{
  "type": "Feature",
  "properties": {
    "iso:country":"US",
    "sg:address":"1464 Parallel Dr",
    "sg:city":"Lakeport",
    "sg:classifiers":[
        {
            "category":"Insurance",
            "subcategory":"Insurance Agent",
            "type":"Services"
        }
    ],
    "sg:phone":"+1 707 263 4807",
    "sg:postcode":"95453",
    "sg:province":"CA",
    "sg:website":"www.aaa.com",
    "wof:name":"AAA Insurance",
    "wof:placetype":"venue"
},
  "geometry": {"coordinates":[-122.92412400000001,39.031254],"type":"Point"}
}