{
  "type": "Feature",
  "properties": {
    "iso:country":"US",
    "sg:address":"1308 N Texas St",
    "sg:city":"Fairfield",
    "sg:classifiers":[
        {
            "category":"Food & Beverages",
            "subcategory":"Groceries & Convenience Stores",
            "type":"Retail Goods"
        }
    ],
    "sg:phone":"+1 707 399 9234",
    "sg:postcode":"94533",
    "sg:province":"CA",
    "wof:name":"Pinoy Kabayan",
    "wof:placetype":"venue"
},
  "geometry": {"coordinates":[-122.03420800000001,38.256034],"type":"Point"}
}