{
  "type": "Feature",
  "properties": {
    "addr:full":"412 Orchard St Fillmore CA 93015",
    "addr:housenumber":"412",
    "addr:postcode":"93015",
    "addr:street":"Orchard St",
    "iso:country":"US",
    "sg:address":"412 Orchard St",
    "sg:city":"Fillmore",
    "sg:classifiers":[
        {
            "category":"Professional",
            "subcategory":"Secretarial Services",
            "type":"Services"
        }
    ],
    "sg:phone":"+1 805 524 4577",
    "sg:postcode":"93015",
    "sg:province":"CA",
    "sg:tags":[
        "preparation",
        "document"
    ],
    "wof:name":"C & L Assoc",
    "wof:placetype":"venue"
},
  "geometry": {"coordinates":[-118.916516,34.40076],"type":"Point"}
}