{
  "type": "Feature",
  "properties": {
    "addr:full":"1817 47th Ave Capitola CA 95010",
    "addr:housenumber":"1817",
    "addr:postcode":"95010",
    "addr:street":"47Th Ave",
    "iso:country":"US",
    "sg:address":"1817 47th Ave",
    "sg:city":"Capitola",
    "sg:classifiers":[
        {
            "category":"Professional",
            "type":"Services"
        }
    ],
    "sg:phone":"+1 831 462 6272",
    "sg:postcode":"95010",
    "sg:province":"CA",
    "sg:tags":[
        "establishment"
    ],
    "wof:name":"Marsh Design",
    "wof:placetype":"venue"
},
  "geometry": {"coordinates":[-121.958313,36.974737],"type":"Point"}
}