{
  "type": "Feature",
  "properties": {
    "addr:full":"3229 Los Prados Street San Mateo CA 94403",
    "addr:housenumber":"3229",
    "addr:postcode":"94403",
    "addr:street":"Los Prados Street",
    "iso:country":"US",
    "sg:address":"3229 Los Prados Street",
    "sg:city":"San Mateo",
    "sg:classifiers":[
        {
            "category":"Professional",
            "subcategory":"Lawyer & Legal Services",
            "type":"Services"
        }
    ],
    "sg:phone":"+1 650 341 2155",
    "sg:postcode":"94403",
    "sg:province":"CA",
    "wof:name":"Gilbert Nathan A Atty",
    "wof:placetype":"venue"
},
  "geometry": {"coordinates":[-122.27872600000001,37.543165],"type":"Point"}
}