{
  "type": "Feature",
  "properties": {
    "iso:country":"US",
    "sg:address":"2538 Corralitas Dr",
    "sg:city":"Los Angeles",
    "sg:classifiers":[
        {
            "category":"Real Estate",
            "subcategory":"Real Estate Agent",
            "type":"Services"
        }
    ],
    "sg:phone":"+1 323 665 1005",
    "sg:postcode":"90039",
    "sg:province":"CA",
    "wof:name":"Regal Estates",
    "wof:placetype":"venue"
},
  "geometry": {"coordinates":[-118.251996,34.099327],"type":"Point"}
}