{
  "type": "Feature",
  "properties": {
    "addr:full":"1835 Volti Way Sacramento CA 95833",
    "addr:housenumber":"1835",
    "addr:postcode":"95833",
    "addr:street":"Volti Way",
    "iso:country":"US",
    "sg:address":"1835 Volti Way",
    "sg:city":"Sacramento",
    "sg:classifiers":[
        {
            "category":"Shopping",
            "subcategory":"Pets & Pet Supplies",
            "type":"Retail Goods"
        }
    ],
    "sg:phone":"+1 916 397 3201",
    "sg:postcode":"95833",
    "sg:province":"CA",
    "sg:tags":[
        "furnishing",
        "dog",
        "store",
        "cat"
    ],
    "wof:name":"Peaceful Pets",
    "wof:placetype":"venue"
},
  "geometry": {"coordinates":[-121.503219,38.623361],"type":"Point"}
}