{
  "type": "Feature",
  "properties": {
    "addr:full":"2501 Scaroni Ave Calexico CA 92231",
    "addr:housenumber":"2501",
    "addr:postcode":"92231",
    "addr:street":"Scaroni Ave",
    "iso:country":"US",
    "sg:address":"2501 Scaroni Ave",
    "sg:city":"Calexico",
    "sg:classifiers":[
        {
            "category":"Travel",
            "subcategory":"Hotels & Motels",
            "type":"Entertainment"
        },
        {
            "category":"Retail",
            "subcategory":"Event Space",
            "type":"Services"
        }
    ],
    "sg:phone":"+1 800 345 8082",
    "sg:postcode":"92231",
    "sg:province":"CA",
    "sg:tags":[
        "facility",
        "banquet",
        "reception",
        "lodging",
        "corporate",
        "hall"
    ],
    "sg:website":"http://ad.doubleclick.net/clk;222816988;46581822;v?http://www.hiexpress.com/redirect?path=hd&brandCode=ex&hotelCode=cxlca&_PMID=99601036&cm_mmc=mdpr-_-yellowpages-_-ex-_-cxlca",
    "wof:name":"Holiday Inn Express Calexico",
    "wof:placetype":"venue"
},
  "geometry": {"coordinates":[-115.499674,32.696851],"type":"Point"}
}