{
  "type": "Feature",
  "properties": {
    "iso:country":"US",
    "sg:address":"120 S George Burns Rd",
    "sg:city":"Los Angeles",
    "sg:classifiers":[
        {
            "category":"Health Services",
            "subcategory":"Doctor",
            "type":"Services"
        }
    ],
    "sg:phone":"+1 310 854 1971",
    "sg:postcode":"90048",
    "sg:province":"CA",
    "sg:tags":[
        "physician",
        "surgeon"
    ],
    "wof:name":"Csmg",
    "wof:placetype":"venue"
},
  "geometry": {"coordinates":[-118.381567,34.073749],"type":"Point"}
}