{
  "type": "Feature",
  "properties": {
    "addr:full":"15575 Bittner Rd Occidental CA 95465",
    "addr:housenumber":"15575",
    "addr:postcode":"95465",
    "addr:street":"Bittner Rd",
    "iso:country":"US",
    "sg:address":"15575 Bittner Rd",
    "sg:city":"Occidental",
    "sg:classifiers":[
        {
            "category":"Real Estate",
            "subcategory":"Real Estate Operator",
            "type":"Services"
        }
    ],
    "sg:phone":"+1 707 874 3538",
    "sg:postcode":"95465",
    "sg:province":"CA",
    "sg:tags":[
        "apartment"
    ],
    "wof:name":"Senior Divine Apartment Llp",
    "wof:placetype":"venue"
},
  "geometry": {"coordinates":[-122.95716299999999,38.400199],"type":"Point"}
}