{
  "type": "Feature",
  "properties": {
    "addr:full":"2667 E Colorado Blvd Pasadena CA 91107",
    "addr:housenumber":"2667",
    "addr:postcode":"91107",
    "addr:street":"E Colorado Blvd",
    "iso:country":"US",
    "sg:address":"2667 E Colorado Blvd",
    "sg:city":"Pasadena",
    "sg:classifiers":[
        {
            "category":"Building & Trades",
            "subcategory":"Plumbing",
            "type":"Services"
        },
        {
            "category":"Home & Garden",
            "subcategory":"Building Materials",
            "type":"Retail Goods"
        }
    ],
    "sg:phone":"+1 626 795 5881",
    "sg:postcode":"91107",
    "sg:province":"CA",
    "sg:tags":[
        "equipment",
        "plumber",
        "heating",
        "system"
    ],
    "sg:website":"www.benedictandbenedict.com",
    "wof:name":"Benedict & Benedict Plumbing Company",
    "wof:placetype":"venue"
},
  "geometry": {"coordinates":[-118.095001,34.146198],"type":"Point"}
}