{
  "type": "Feature",
  "properties": {
    "addr:full":"26 Brighton Dr Vallejo CA 94591",
    "addr:housenumber":"26",
    "addr:postcode":"94591",
    "addr:street":"Brighton Dr",
    "iso:country":"US",
    "sg:address":"26 Brighton Dr",
    "sg:city":"Vallejo",
    "sg:classifiers":[
        {
            "category":"Building & Trades",
            "subcategory":"Construction",
            "type":"Services"
        }
    ],
    "sg:phone":"+1 707 554 8521",
    "sg:postcode":"94591",
    "sg:province":"CA",
    "sg:tags":[
        "painter"
    ],
    "wof:name":"Brunson Brothers Painting",
    "wof:placetype":"venue"
},
  "geometry": {"coordinates":[-122.19326599999999,38.107274],"type":"Point"}
}