{
  "type": "Feature",
  "properties": {
    "addr:full":"4300 42nd Ave Sacramento CA 95824",
    "addr:housenumber":"4300",
    "addr:postcode":"95824",
    "addr:street":"42Nd Ave",
    "iso:country":"US",
    "sg:address":"4300 42nd Ave",
    "sg:city":"Sacramento",
    "sg:classifiers":[
        {
            "category":"Building & Trades",
            "subcategory":"Construction",
            "type":"Services"
        }
    ],
    "sg:phone":"+1 916 399 9299",
    "sg:postcode":"95824",
    "sg:province":"CA",
    "sg:tags":[
        "wallcoverings-installation",
        "wallpaper",
        "painting",
        "contractor"
    ],
    "wof:name":"Cassies Painting And Construction",
    "wof:placetype":"venue"
},
  "geometry": {"coordinates":[-121.458472,38.515179],"type":"Point"}
}