{
  "type": "Feature",
  "properties": {
    "iso:country":"US",
    "sg:address":"2443 Ash St",
    "sg:city":"Palo Alto",
    "sg:classifiers":[
        {
            "category":"Professional",
            "subcategory":"Engineering",
            "type":"Services"
        }
    ],
    "sg:phone":"+1 650 327 3900",
    "sg:postcode":"94306",
    "sg:province":"CA",
    "sg:tags":[
        "engineer"
    ],
    "wof:name":"A C & H Civil Engineers",
    "wof:placetype":"venue"
},
  "geometry": {"coordinates":[-122.14456,37.426582],"type":"Point"}
}