{
  "type": "Feature",
  "properties": {
    "addr:full":"2835 San Pablo Ave Berkeley CA 94702",
    "addr:housenumber":"2835",
    "addr:postcode":"94702",
    "addr:street":"San Pablo Ave",
    "iso:country":"US",
    "sg:address":"2835 San Pablo Ave",
    "sg:city":"Berkeley",
    "sg:classifiers":[
        {
            "category":"Organizations",
            "subcategory":"Professional Association",
            "type":"Services"
        }
    ],
    "sg:phone":"+1 510 843 4134",
    "sg:postcode":"94702",
    "sg:province":"CA",
    "sg:tags":[
        "fraternal"
    ],
    "wof:name":"Pearless Lodge Of Elk's",
    "wof:placetype":"venue"
},
  "geometry": {"coordinates":[-122.287494,37.854532],"type":"Point"}
}