{
  "type": "Feature",
  "properties": {
    "addr:full":"2015 W 1st St Santa Ana CA 92703",
    "addr:housenumber":"2015",
    "addr:postcode":"92703",
    "addr:street":"W 1St St",
    "iso:country":"US",
    "sg:address":"2015 W 1st St",
    "sg:city":"Santa Ana",
    "sg:classifiers":[
        {
            "category":"Health Services",
            "subcategory":"Doctor",
            "type":"Services"
        }
    ],
    "sg:phone":"+1 714 547 7745",
    "sg:postcode":"92703",
    "sg:province":"CA",
    "sg:tags":[
        "clinic"
    ],
    "wof:name":"Casa Guadalupe Family Medical",
    "wof:placetype":"venue"
},
  "geometry": {"coordinates":[-117.8985,33.745319],"type":"Point"}
}