{
  "type": "Feature",
  "properties": {
    "iso:country":"US",
    "sg:address":"17049 E Cypress St",
    "sg:city":"Covina",
    "sg:classifiers":[
        {
            "category":"Wholesale",
            "subcategory":"Computers",
            "type":"Manufacturing & Wholesale Goods"
        }
    ],
    "sg:phone":"+1 626 339 2010",
    "sg:postcode":"91722",
    "sg:province":"CA",
    "wof:name":"Superdimensional",
    "wof:placetype":"venue"
},
  "geometry": {"coordinates":[-117.915031,34.095869],"type":"Point"}
}