{
  "type": "Feature",
  "properties": {
    "addr:full":"107 4th St Los Angeles CA 90013",
    "addr:housenumber":"107",
    "addr:postcode":"90013",
    "addr:street":"4Th St",
    "iso:country":"US",
    "sg:address":"107 4th St",
    "sg:city":"Los Angeles",
    "sg:classifiers":[
        {
            "category":"Bars & Pubs",
            "subcategory":"Dive Bar",
            "type":"Food & Drink"
        }
    ],
    "sg:phone":"+1 213 625 7382",
    "sg:postcode":"90013",
    "sg:province":"CA",
    "sg:website":"www.myspace.com/bar107",
    "wof:name":"Bar 107",
    "wof:placetype":"venue"
},
  "geometry": {"coordinates":[-118.246954,34.047971],"type":"Point"}
}