{
  "type": "Feature",
  "properties": {
    "iso:country":"US",
    "sg:address":"4480 Kester Ave",
    "sg:city":"Sherman Oaks",
    "sg:classifiers":[
        {
            "category":"Professional",
            "type":"Services"
        }
    ],
    "sg:phone":"+1 661 702 8730",
    "sg:postcode":"91403",
    "sg:province":"CA",
    "sg:tags":[
        "establishment"
    ],
    "wof:name":"Bonenete Group LLC",
    "wof:placetype":"venue"
},
  "geometry": {"coordinates":[-118.456642,34.151476],"type":"Point"}
}