{
  "type": "Feature",
  "properties": {
    "addr:full":"422 Walnut St Red Bluff CA 96080",
    "addr:housenumber":"422",
    "addr:postcode":"96080",
    "addr:street":"Walnut St",
    "iso:country":"US",
    "sg:address":"422 Walnut St",
    "sg:city":"Red Bluff",
    "sg:classifiers":[
        {
            "category":"Shopping",
            "type":"Retail Goods"
        }
    ],
    "sg:phone":"+1 530 527 8209",
    "sg:postcode":"96080",
    "sg:province":"CA",
    "sg:tags":[
        "spa",
        "hot",
        "tub"
    ],
    "wof:name":"Red Bluff Interiors Spas & Stv",
    "wof:placetype":"venue"
},
  "geometry": {"coordinates":[-122.236937,40.177825],"type":"Point"}
}