{
  "type": "Feature",
  "properties": {
    "addr:full":"8015 Long Beach Blvd South Gate CA 90280",
    "addr:housenumber":"8015",
    "addr:postcode":"90280",
    "addr:street":"Long Beach Blvd;Gate",
    "iso:country":"US",
    "sg:address":"8015 Long Beach Blvd",
    "sg:city":"South Gate",
    "sg:classifiers":[
        {
            "category":"Shopping",
            "subcategory":"Shoes",
            "type":"Retail Goods"
        }
    ],
    "sg:phone":"+1 323 583 0512",
    "sg:postcode":"90280",
    "sg:province":"CA",
    "sg:tags":[
        "store"
    ],
    "wof:name":"House Of Shoes",
    "wof:placetype":"venue"
},
  "geometry": {"coordinates":[-118.225345,33.965735],"type":"Point"}
}