{
  "type": "Feature",
  "properties": {
    "addr:full":"5247 E Beverly Blvd Los Angeles CA 90022",
    "addr:housenumber":"5247",
    "addr:postcode":"90022",
    "addr:street":"E Beverly Blvd",
    "iso:country":"US",
    "sg:address":"5247 E Beverly Blvd",
    "sg:city":"Los Angeles",
    "sg:classifiers":[
        {
            "category":"Real Estate",
            "subcategory":"Real Estate Services",
            "type":"Services"
        }
    ],
    "sg:phone":"+1 323 721 2041",
    "sg:postcode":"90022",
    "sg:province":"CA",
    "sg:tags":[
        "management",
        "property"
    ],
    "wof:name":"Casa Bella Realty",
    "wof:placetype":"venue"
},
  "geometry": {"coordinates":[-118.152247,34.158703],"type":"Point"}
}