{
  "type": "Feature",
  "properties": {
    "addr:full":"11908 Cypress Canyon Rd San Diego CA 92131",
    "addr:housenumber":"11908",
    "addr:postcode":"92131",
    "addr:street":"Cypress Canyon Rd",
    "iso:country":"US",
    "sg:address":"11908 Cypress Canyon Rd",
    "sg:city":"San Diego",
    "sg:classifiers":[
        {
            "category":"Communications",
            "type":"Services"
        }
    ],
    "sg:phone":"+1 858 271 0200",
    "sg:postcode":"92131",
    "sg:province":"CA",
    "sg:tags":[
        "wireless",
        "product"
    ],
    "wof:name":"Field Technologies",
    "wof:placetype":"venue"
},
  "geometry": {"coordinates":[-117.084462,32.934067],"type":"Point"}
}