{
  "type": "Feature",
  "properties": {
    "iso:country":"US",
    "sg:address":"8764 E Washington Blvd",
    "sg:city":"Pico Rivera",
    "sg:classifiers":[
        {
            "category":"Shopping",
            "subcategory":"Computers & Home Electronics",
            "type":"Retail Goods"
        }
    ],
    "sg:phone":"+1 562 222 1800",
    "sg:postcode":"90660",
    "sg:province":"CA",
    "sg:website":"www.gamestop.com",
    "wof:name":"GameStop",
    "wof:placetype":"venue"
},
  "geometry": {"coordinates":[-118.099913,33.98465],"type":"Point"}
}