{
  "type": "Feature",
  "properties": {
    "iso:country":"US",
    "sg:address":"1027 E 42nd St",
    "sg:city":"Los Angeles",
    "sg:classifiers":[
        {
            "category":"Retail",
            "subcategory":"Repair Shop",
            "type":"Services"
        }
    ],
    "sg:phone":"+1 323 234 4200",
    "sg:postcode":"90011",
    "sg:province":"CA",
    "sg:tags":[
        "antique",
        "restoring"
    ],
    "wof:name":"P G Antiques",
    "wof:placetype":"venue"
},
  "geometry": {"coordinates":[-118.25700399999999,34.007599],"type":"Point"}
}