{
  "type": "Feature",
  "properties": {
    "addr:full":"1306 Park Ave Chico CA 95928",
    "addr:housenumber":"1306",
    "addr:postcode":"95928",
    "addr:street":"Park Ave",
    "iso:country":"US",
    "sg:address":"1306 Park Ave",
    "sg:city":"Chico",
    "sg:classifiers":[
        {
            "category":"Retail",
            "subcategory":"Repair Shop",
            "type":"Services"
        }
    ],
    "sg:phone":"+1 530 343 3270",
    "sg:postcode":"95928",
    "sg:province":"CA",
    "sg:tags":[
        "upholsterer"
    ],
    "wof:name":"Park Ave Upholstery Studio",
    "wof:placetype":"venue"
},
  "geometry": {"coordinates":[-121.829261,39.722556],"type":"Point"}
}