{
  "type": "Feature",
  "properties": {
    "iso:country":"US",
    "sg:address":"970 E 11th St",
    "sg:city":"Los Angeles",
    "sg:classifiers":[
        {
            "category":"Wholesale",
            "subcategory":"Electrical",
            "type":"Manufacturing & Wholesale Goods"
        }
    ],
    "sg:phone":"+1 213 612 0398",
    "sg:postcode":"90021",
    "sg:province":"CA",
    "sg:tags":[
        "equipment",
        "electronic",
        "supply"
    ],
    "wof:name":"A & K Electronics Inc",
    "wof:placetype":"venue"
},
  "geometry": {"coordinates":[-118.245486,34.031236],"type":"Point"}
}