{
  "type": "Feature",
  "properties": {
    "iso:country":"US",
    "sg:address":"1550 Bryant St",
    "sg:city":"San Francisco",
    "sg:classifiers":[
        {
            "category":"Professional",
            "type":"Services"
        }
    ],
    "sg:phone":"+1 888 893 2283",
    "sg:postcode":"94115",
    "sg:province":"CA",
    "sg:tags":[
        "caterer"
    ],
    "sg:website":"www.pastapomodoro.com",
    "wof:name":"Pasta Pomodoro Catering",
    "wof:placetype":"venue"
},
  "geometry": {"coordinates":[-122.41082400000001,37.767725],"type":"Point"}
}