{
  "type": "Feature",
  "properties": {
    "iso:country":"US",
    "sg:address":"710 Dubuque Ave",
    "sg:city":"S San Francisco",
    "sg:classifiers":[
        {
            "category":"Manufacturing",
            "subcategory":"Metals",
            "type":"Manufacturing & Wholesale Goods"
        },
        {
            "category":"Shopping",
            "subcategory":"Bicycles & Sporting Goods",
            "type":"Retail Goods"
        }
    ],
    "sg:phone":"+1 650 869 6126",
    "sg:postcode":"94080",
    "sg:province":"CA",
    "sg:tags":[
        "mfg",
        "arms",
        "gunsmith",
        "gun",
        "small",
        "ammunition"
    ],
    "wof:name":"Two Guns Press",
    "wof:placetype":"venue"
},
  "geometry": {"coordinates":[-122.406035,37.655198],"type":"Point"}
}