{
  "type": "Feature",
  "properties": {
    "iso:country":"US",
    "sg:address":"33 W Mission St",
    "sg:city":"Santa Barbara",
    "sg:classifiers":[
        {
            "category":"Professional",
            "subcategory":"Lawyer & Legal Services",
            "type":"Services"
        }
    ],
    "sg:phone":"+1 805 963 2345",
    "sg:postcode":"93101",
    "sg:province":"CA",
    "sg:tags":[
        "attorney"
    ],
    "wof:name":"Nye Peabody & Stirling",
    "wof:placetype":"venue"
},
  "geometry": {"coordinates":[-119.715459,34.43006],"type":"Point"}
}