{
  "type": "Feature",
  "properties": {
    "addr:full":"335 Powell St San Francisco CA 94102",
    "addr:housenumber":"335",
    "addr:postcode":"94102",
    "addr:street":"Powell St",
    "iso:country":"US",
    "sg:address":"335 Powell St",
    "sg:city":"San Francisco",
    "sg:classifiers":[
        {
            "category":"Personal",
            "subcategory":"Beauty Salon",
            "type":"Services"
        }
    ],
    "sg:phone":"+1 415 774 0357",
    "sg:postcode":"94102",
    "sg:province":"CA",
    "sg:tags":[
        "spa"
    ],
    "sg:website":"www.westinstfrancis.com/spa/",
    "wof:name":"Westin St. Francis Spa",
    "wof:placetype":"venue"
},
  "geometry": {"coordinates":[-122.408309,37.787699],"type":"Point"}
}