{
  "type": "Feature",
  "properties": {
    "iso:country":"US",
    "sg:address":"5772 Garden Grove Blvd",
    "sg:city":"Westminster",
    "sg:classifiers":[
        {
            "category":"Freight",
            "type":"Transportation"
        }
    ],
    "sg:phone":"+1 714 713 7236",
    "sg:postcode":"92683",
    "sg:province":"CA",
    "wof:name":"Andre Transport",
    "wof:placetype":"venue"
},
  "geometry": {"coordinates":[-118.035504,33.772889],"type":"Point"}
}