{
  "type": "Feature",
  "properties": {
    "addr:full":"2636 N Argyle Ave Fresno CA 93727",
    "addr:housenumber":"2636",
    "addr:postcode":"93727",
    "addr:street":"N Argyle Ave",
    "iso:country":"US",
    "sg:address":"2636 N Argyle Ave",
    "sg:city":"Fresno",
    "sg:classifiers":[
        {
            "category":"Home & Garden",
            "subcategory":"Building Materials",
            "type":"Retail Goods"
        }
    ],
    "sg:phone":"+1 800 255 9049",
    "sg:postcode":"93727",
    "sg:province":"CA",
    "sg:tags":[
        "granite",
        "top",
        "counter"
    ],
    "wof:name":"Duracite Countertops",
    "wof:placetype":"venue"
},
  "geometry": {"coordinates":[-119.694413,36.777292],"type":"Point"}
}