{
  "type": "Feature",
  "properties": {
    "iso:country":"US",
    "sg:address":"441 N 1st St",
    "sg:city":"San Jose",
    "sg:classifiers":[
        {
            "category":"Banks & Credit Unions",
            "subcategory":"Bank",
            "type":"Services"
        }
    ],
    "sg:phone":"+1 408 287 6570",
    "sg:postcode":"95112",
    "sg:province":"CA",
    "sg:tags":[
        "loan",
        "real estate"
    ],
    "wof:name":"Ameriworld Mortgage",
    "wof:placetype":"venue"
},
  "geometry": {"coordinates":[-121.895121,37.342117],"type":"Point"}
}