{
  "type": "Feature",
  "properties": {
    "iso:country":"US",
    "sg:address":"1071 Redberry Dr",
    "sg:city":"Corona",
    "sg:classifiers":[
        {
            "category":"Professional",
            "subcategory":"Business Services",
            "type":"Services"
        }
    ],
    "sg:phone":"+1 951 278 0677",
    "sg:postcode":"92882",
    "sg:province":"CA",
    "sg:tags":[
        "information",
        "referral"
    ],
    "wof:name":"Pennant Information",
    "wof:placetype":"venue"
},
  "geometry": {"coordinates":[-117.62482199999999,33.874616],"type":"Point"}
}