{
  "type": "Feature",
  "properties": {
    "addr:full":"9089 Clairemont Mesa Blvd San Diego CA 92117",
    "addr:housenumber":"9089",
    "addr:postcode":"92117",
    "addr:street":"Clairemont Mesa Blvd",
    "iso:country":"US",
    "sg:address":"9089 Clairemont Mesa Blvd",
    "sg:city":"San Diego",
    "sg:classifiers":[
        {
            "category":"Freight",
            "type":"Transportation"
        }
    ],
    "sg:phone":"+1 858 560 1690",
    "sg:postcode":"92117",
    "sg:province":"CA",
    "wof:name":"Approved Transportation & Wrhs",
    "wof:placetype":"venue"
},
  "geometry": {"coordinates":[-117.134342,32.831306],"type":"Point"}
}