{
  "type": "Feature",
  "properties": {
    "addr:full":"5200 W Century Blvd Los Angeles CA 90045",
    "addr:housenumber":"5200",
    "addr:postcode":"90045",
    "addr:street":"W Century Blvd",
    "iso:country":"US",
    "sg:address":"5200 W Century Blvd",
    "sg:city":"Los Angeles",
    "sg:classifiers":[
        {
            "category":"Restaurant",
            "type":"Food & Drink"
        }
    ],
    "sg:phone":"+1 310 216 0011",
    "sg:postcode":"90045",
    "sg:province":"CA",
    "sg:website":"www.trimana.com",
    "wof:name":"Trimana",
    "wof:placetype":"venue"
},
  "geometry": {"coordinates":[-118.370158,33.945332],"type":"Point"}
}