{
  "type": "Feature",
  "properties": {
    "iso:country":"US",
    "sg:address":"3712 Main St",
    "sg:city":"Chula Vista",
    "sg:classifiers":[
        {
            "category":"Retail",
            "subcategory":"Storage",
            "type":"Services"
        }
    ],
    "sg:phone":"+1 619 425 2040",
    "sg:postcode":"91911",
    "sg:province":"CA",
    "sg:tags":[
        "self"
    ],
    "wof:name":"A-1 Sav-On Storage-Truck & Ttrailer Rental",
    "wof:placetype":"venue"
},
  "geometry": {"coordinates":[-117.05300099999999,32.594601],"type":"Point"}
}