{
  "type": "Feature",
  "properties": {
    "addr:full":"10275 Tujunga Canyon Blvd Tujunga CA 91042",
    "addr:housenumber":"10275",
    "addr:postcode":"91042",
    "addr:street":"Tujunga Canyon Blvd",
    "iso:country":"US",
    "sg:address":"10275 Tujunga Canyon Blvd",
    "sg:city":"Tujunga",
    "sg:classifiers":[
        {
            "category":"Place Of Worship",
            "type":"Public Place"
        }
    ],
    "sg:phone":"+1 818 353 5478",
    "sg:postcode":"91042",
    "sg:province":"CA",
    "sg:tags":[
        "church"
    ],
    "wof:name":"Our Lady Of Lords Knights",
    "wof:placetype":"venue"
},
  "geometry": {"coordinates":[-118.291056,34.254737],"type":"Point"}
}