{
  "type": "Feature",
  "properties": {
    "iso:country":"US",
    "sg:address":"1219 Wood St",
    "sg:city":"Oakland",
    "sg:classifiers":[
        {
            "category":"Shopping",
            "subcategory":"Pets & Pet Supplies",
            "type":"Retail Goods"
        },
        {
            "category":"Retail",
            "subcategory":"Animal Services",
            "type":"Services"
        }
    ],
    "sg:phone":"+1 510 986 0431",
    "sg:postcode":"94607",
    "sg:province":"CA",
    "sg:tags":[
        "store"
    ],
    "wof:name":"Zephyr Gate",
    "wof:placetype":"venue"
},
  "geometry": {"coordinates":[-122.298951,37.812097],"type":"Point"}
}