{
  "type": "Feature",
  "properties": {
    "addr:full":"1010 Sandhill Ave Carson CA 90746",
    "addr:housenumber":"1010",
    "addr:postcode":"90746",
    "addr:street":"Sandhill Ave",
    "iso:country":"US",
    "sg:address":"1010 Sandhill Ave",
    "sg:city":"Carson",
    "sg:classifiers":[
        {
            "category":"Wholesale",
            "subcategory":"Electrical",
            "type":"Manufacturing & Wholesale Goods"
        }
    ],
    "sg:phone":"+1 602 861 2560",
    "sg:postcode":"90746",
    "sg:province":"CA",
    "sg:tags":[
        "equipment",
        "electronic"
    ],
    "wof:name":"Sager Electrical Supply Co",
    "wof:placetype":"venue"
},
  "geometry": {"coordinates":[-118.258988,33.878476],"type":"Point"}
}