{
  "type": "Feature",
  "properties": {
    "iso:country":"US",
    "sg:address":"532 Oregon St",
    "sg:city":"Vallejo",
    "sg:classifiers":[
        {
            "category":"Social Services",
            "type":"Services"
        }
    ],
    "sg:phone":"+1 707 643 1923",
    "sg:postcode":"94590",
    "sg:province":"CA",
    "sg:tags":[
        "counselor",
        "marriage",
        "family"
    ],
    "wof:name":"Family Guidance & Therapy Ctr",
    "wof:placetype":"venue"
},
  "geometry": {"coordinates":[-122.249664,38.118415],"type":"Point"}
}