{
  "type": "Feature",
  "properties": {
    "iso:country":"US",
    "sg:address":"1015 L St",
    "sg:city":"Sacramento",
    "sg:classifiers":[
        {
            "category":"Wholesale",
            "subcategory":"Stationery",
            "type":"Manufacturing & Wholesale Goods"
        }
    ],
    "sg:phone":"+1 916 208 3703",
    "sg:postcode":"95814",
    "sg:province":"CA",
    "sg:tags":[
        "supply"
    ],
    "wof:name":"Beyond Juice",
    "wof:placetype":"venue"
},
  "geometry": {"coordinates":[-121.493196,38.577868],"type":"Point"}
}