{
  "type": "Feature",
  "properties": {
    "iso:country":"US",
    "sg:address":"3066 Lake Dr",
    "sg:city":"Marina",
    "sg:classifiers":[
        {
            "category":"Education",
            "subcategory":"School",
            "type":"Public Place"
        }
    ],
    "sg:phone":"+1 831 384 0255",
    "sg:postcode":"93933",
    "sg:province":"CA",
    "sg:tags":[
        "high",
        "middle",
        "elementary"
    ],
    "wof:name":"Marina Del Mar Elementary School",
    "wof:placetype":"venue"
},
  "geometry": {"coordinates":[-121.806,36.6847],"type":"Point"}
}