{
  "type": "Feature",
  "properties": {
    "iso:country":"US",
    "sg:address":"9030 Raffia Ln",
    "sg:city":"Fontana",
    "sg:classifiers":[
        {
            "category":"Wholesale",
            "subcategory":"Vending Machines",
            "type":"Manufacturing & Wholesale Goods"
        }
    ],
    "sg:phone":"+1 909 559 1561",
    "sg:postcode":"92335",
    "sg:province":"CA",
    "sg:tags":[
        "merchandise"
    ],
    "wof:name":"Happy Tummy Vending",
    "wof:placetype":"venue"
},
  "geometry": {"coordinates":[-117.48056,34.089106],"type":"Point"}
}