{
  "type": "Feature",
  "properties": {
    "addr:full":"12860 Muscatine St Pacoima CA 91331",
    "addr:housenumber":"12860",
    "addr:postcode":"91331",
    "addr:street":"Muscatine St",
    "iso:country":"US",
    "sg:address":"12860 Muscatine St",
    "sg:city":"Pacoima",
    "sg:classifiers":[
        {
            "category":"Retail",
            "subcategory":"Auto Repair",
            "type":"Services"
        }
    ],
    "sg:phone":"+1 818 897 1491",
    "sg:postcode":"91331",
    "sg:province":"CA",
    "sg:tags":[
        "transmission"
    ],
    "wof:name":"H & H Auto Parts Wholesale",
    "wof:placetype":"venue"
},
  "geometry": {"coordinates":[-118.412502,34.239238],"type":"Point"}
}