{
  "type": "Feature",
  "properties": {
    "iso:country":"US",
    "sg:address":"401 N Brookhurst St Ste 118",
    "sg:city":"Anaheim",
    "sg:classifiers":[
        {
            "category":"Health Services",
            "subcategory":"Doctor",
            "type":"Services"
        }
    ],
    "sg:phone":"+1 714 635 8653",
    "sg:postcode":"92801",
    "sg:province":"CA",
    "sg:tags":[
        "surgeon",
        "oral"
    ],
    "wof:name":"Shimoide Ron DDS",
    "wof:placetype":"venue"
},
  "geometry": {"coordinates":[-117.959,33.838402],"type":"Point"}
}