{
  "type": "Feature",
  "properties": {
    "iso:country":"US",
    "sg:address":"2820 Townsgate Rd",
    "sg:city":"Westlake Village",
    "sg:classifiers":[
        {
            "category":"Wholesale",
            "subcategory":"Electrical",
            "type":"Manufacturing & Wholesale Goods"
        }
    ],
    "sg:phone":"+1 805 230 1963",
    "sg:postcode":"91361",
    "sg:province":"CA",
    "sg:tags":[
        "electronic"
    ],
    "wof:name":"Debut",
    "wof:placetype":"venue"
},
  "geometry": {"coordinates":[-118.821046,34.151132],"type":"Point"}
}