{
  "type": "Feature",
  "properties": {
    "addr:full":"7644 Forrestal Rd San Diego CA 92120",
    "addr:housenumber":"7644",
    "addr:postcode":"92120",
    "addr:street":"Forrestal Rd",
    "iso:country":"US",
    "sg:address":"7644 Forrestal Rd",
    "sg:city":"San Diego",
    "sg:classifiers":[
        {
            "category":"Shopping",
            "subcategory":"Used Merchandise",
            "type":"Retail Goods"
        }
    ],
    "sg:phone":"+1 619 287 0693",
    "sg:postcode":"92120",
    "sg:province":"CA",
    "sg:tags":[
        "book",
        "rare",
        "dealer"
    ],
    "wof:name":"Parmer Books",
    "wof:placetype":"venue"
},
  "geometry": {"coordinates":[-117.049087,32.8054],"type":"Point"}
}