{
  "type": "Feature",
  "properties": {
    "addr:full":"2912 W Main St Visalia CA 93291",
    "addr:housenumber":"2912",
    "addr:postcode":"93291",
    "addr:street":"W Main St",
    "iso:country":"US",
    "sg:address":"2912 W Main St",
    "sg:city":"Visalia",
    "sg:classifiers":[
        {
            "category":"Professional",
            "subcategory":"Accounting & Tax Preparation",
            "type":"Services"
        }
    ],
    "sg:phone":"+1 559 635 3136",
    "sg:postcode":"93291",
    "sg:province":"CA",
    "sg:tags":[
        "accountant"
    ],
    "wof:name":"Paul E Sonier CPA",
    "wof:placetype":"venue"
},
  "geometry": {"coordinates":[-119.322063,36.329616],"type":"Point"}
}