{
  "type": "Feature",
  "properties": {
    "addr:full":"401 E Carrillo St Santa Barbara CA 93101",
    "addr:housenumber":"401",
    "addr:postcode":"93101",
    "addr:street":"E Carrillo St",
    "iso:country":"US",
    "sg:address":"401 E Carrillo St",
    "sg:city":"Santa Barbara",
    "sg:classifiers":[
        {
            "category":"Building & Trades",
            "subcategory":"Construction",
            "type":"Services"
        }
    ],
    "sg:phone":"+1 805 966 2744",
    "sg:postcode":"93101",
    "sg:province":"CA",
    "sg:tags":[
        "contractor"
    ],
    "wof:name":"Homes By Holmes",
    "wof:placetype":"venue"
},
  "geometry": {"coordinates":[-119.696223,34.426773],"type":"Point"}
}