{
  "type": "Feature",
  "properties": {
    "iso:country":"US",
    "sg:address":"10670 Riverside Dr.",
    "sg:city":"North Hollywood",
    "sg:classifiers":[
        {
            "category":"Personal",
            "subcategory":"Nail Salon",
            "type":"Services"
        }
    ],
    "sg:phone":"+1 818 568 7671",
    "sg:postcode":"91602",
    "sg:province":"CA",
    "wof:name":"Himalaya Sen",
    "wof:placetype":"venue"
},
  "geometry": {"coordinates":[-118.363648,34.152197],"type":"Point"}
}