{
  "type": "Feature",
  "properties": {
    "iso:country":"US",
    "sg:address":"849 Almar Ave Ste C-435",
    "sg:city":"Santa Cruz",
    "sg:classifiers":[
        {
            "category":"Building & Trades",
            "subcategory":"Construction",
            "type":"Services"
        },
        {
            "category":"Wholesale",
            "subcategory":"Home Furnishings",
            "type":"Manufacturing & Wholesale Goods"
        }
    ],
    "sg:phone":"+1 831 336 1119",
    "sg:postcode":"95060",
    "sg:province":"CA",
    "sg:tags":[
        "interior",
        "blind",
        "design",
        "shade"
    ],
    "wof:name":"Fine Designs By Coco",
    "wof:placetype":"venue"
},
  "geometry": {"coordinates":[-122.043644,36.961311],"type":"Point"}
}