{
  "type": "Feature",
  "properties": {
    "addr:full":"4045 Foothill Rd Carpinteria CA 93013",
    "addr:housenumber":"4045",
    "addr:postcode":"93013",
    "addr:street":"Foothill Rd",
    "iso:country":"US",
    "sg:address":"4045 Foothill Rd",
    "sg:city":"Carpinteria",
    "sg:classifiers":[
        {
            "category":"Professional",
            "subcategory":"Business Services",
            "type":"Services"
        }
    ],
    "sg:phone":"+1 805 745 1125",
    "sg:postcode":"93013",
    "sg:province":"CA",
    "sg:tags":[
        "plant",
        "design",
        "maintenance"
    ],
    "wof:name":"Village Gardener",
    "wof:placetype":"venue"
},
  "geometry": {"coordinates":[-119.52864099999999,34.413644],"type":"Point"}
}