{
  "type": "Feature",
  "properties": {
    "iso:country":"US",
    "sg:address":"7227 Broadway",
    "sg:city":"Lemon Grove",
    "sg:classifiers":[
        {
            "category":"Wholesale",
            "subcategory":"Office Equipment",
            "type":"Manufacturing & Wholesale Goods"
        }
    ],
    "sg:phone":"+1 619 337 3800",
    "sg:postcode":"91945",
    "sg:province":"CA",
    "sg:tags":[
        "protection",
        "check",
        "mach"
    ],
    "wof:name":"Nationwide Secure Funds Soluti",
    "wof:placetype":"venue"
},
  "geometry": {"coordinates":[-117.041601,32.742494],"type":"Point"}
}