{
  "type": "Feature",
  "properties": {
    "addr:full":"2731 Hawthorne Ct Hayward CA 94545",
    "addr:housenumber":"2731",
    "addr:postcode":"94545",
    "addr:street":"Hawthorne Ct",
    "iso:country":"US",
    "sg:address":"2731 Hawthorne Ct",
    "sg:city":"Hayward",
    "sg:classifiers":[
        {
            "category":"Home & Garden",
            "subcategory":"Carpets & Floor Coverings",
            "type":"Retail Goods"
        }
    ],
    "sg:phone":"+1 510 293 0455",
    "sg:postcode":"94545",
    "sg:province":"CA",
    "sg:tags":[
        "flooring"
    ],
    "wof:name":"Progresso Hardwood Floors",
    "wof:placetype":"venue"
},
  "geometry": {"coordinates":[-122.10825800000001,37.632671],"type":"Point"}
}