{
  "type": "Feature",
  "properties": {
    "addr:full":"1724 Broadway Oakland CA 94612",
    "addr:housenumber":"1724",
    "addr:postcode":"94612",
    "addr:street":"Broadway",
    "iso:country":"US",
    "sg:address":"1724 Broadway",
    "sg:city":"Oakland",
    "sg:classifiers":[
        {
            "category":"Shopping",
            "subcategory":"Clothing, Apparel, & Fashions",
            "type":"Retail Goods"
        }
    ],
    "sg:phone":"+1 510 452 2751",
    "sg:postcode":"94612",
    "sg:province":"CA",
    "sg:tags":[
        "furnishing"
    ],
    "wof:name":"Selix Formalwear",
    "wof:placetype":"venue"
},
  "geometry": {"coordinates":[-122.26911,37.807626],"type":"Point"}
}