{
  "type": "Feature",
  "properties": {
    "iso:country":"US",
    "sg:address":"8128 Madison Ave",
    "sg:city":"Fair Oaks",
    "sg:classifiers":[
        {
            "category":"Sports & Exercise",
            "subcategory":"Bicycle Rental",
            "type":"Entertainment"
        },
        {
            "category":"Shopping",
            "subcategory":"Shoes",
            "type":"Retail Goods"
        }
    ],
    "sg:phone":"+1 916 965 8326",
    "sg:postcode":"95628",
    "sg:province":"CA",
    "sg:tags":[
        "wear",
        "store"
    ],
    "sg:website":"www.fleetfeet-fairoaks.com",
    "wof:name":"Fleet Feet",
    "wof:placetype":"venue"
},
  "geometry": {"coordinates":[-121.260525,38.664036],"type":"Point"}
}