{
  "type": "Feature",
  "properties": {
    "addr:full":"315 S Hunter St Stockton CA 95203",
    "addr:housenumber":"315",
    "addr:postcode":"95203",
    "addr:street":"S Hunter St",
    "iso:country":"US",
    "sg:address":"315 S Hunter St",
    "sg:city":"Stockton",
    "sg:classifiers":[
        {
            "category":"Restaurant",
            "type":"Food & Drink"
        }
    ],
    "sg:phone":"+1 209 942 2221",
    "sg:postcode":"95203",
    "sg:province":"CA",
    "wof:name":"Emerald Chinese Restaurant",
    "wof:placetype":"venue"
},
  "geometry": {"coordinates":[-121.28752,37.949135],"type":"Point"}
}