{
  "type": "Feature",
  "properties": {
    "iso:country":"US",
    "sg:address":"12431 Darkwood Rd",
    "sg:city":"San Diego",
    "sg:classifiers":[
        {
            "category":"Wholesale",
            "subcategory":"Electrical",
            "type":"Manufacturing & Wholesale Goods"
        }
    ],
    "sg:phone":"+1 858 382 5857",
    "sg:postcode":"92129",
    "sg:province":"CA",
    "sg:tags":[
        "security",
        "product"
    ],
    "wof:name":"Image Wonders Enterprises",
    "wof:placetype":"venue"
},
  "geometry": {"coordinates":[-117.143419,32.94686],"type":"Point"}
}