{
  "type": "Feature",
  "properties": {
    "iso:country":"US",
    "sg:address":"905 N Main St",
    "sg:city":"Bishop",
    "sg:classifiers":[
        {
            "category":"Restaurant",
            "type":"Food & Drink"
        }
    ],
    "sg:menulink":"http://www.allmenus.com/ca/bishop/123942-quiznos-sub/menu/",
    "sg:phone":"+1 760 872 9070",
    "sg:postcode":"93514",
    "sg:province":"CA",
    "sg:tags":[
        "wrap",
        "american",
        "sandwich"
    ],
    "wof:name":"Quiznos Sub",
    "wof:placetype":"venue"
},
  "geometry": {"coordinates":[-118.395357,37.370454],"type":"Point"}
}