{
  "type": "Feature",
  "properties": {
    "iso:country":"US",
    "sg:address":"37316 Niles Blvd",
    "sg:city":"Fremont",
    "sg:classifiers":[
        {
            "category":"Building & Trades",
            "subcategory":"Electrical",
            "type":"Services"
        }
    ],
    "sg:phone":"+1 510 797 2500",
    "sg:postcode":"94536",
    "sg:province":"CA",
    "sg:tags":[
        "electric",
        "contractor"
    ],
    "wof:name":"Niles Electric Co Inc",
    "wof:placetype":"venue"
},
  "geometry": {"coordinates":[-121.97940199999999,37.577151],"type":"Point"}
}