{
  "type": "Feature",
  "properties": {
    "iso:country":"US",
    "sg:address":"570 San Andreas Rd",
    "sg:city":"Watsonville",
    "sg:classifiers":[
        {
            "category":"Farming",
            "subcategory":"Nursery",
            "type":"Manufacturing & Wholesale Goods"
        }
    ],
    "sg:phone":"+1 831 724 2929",
    "sg:postcode":"95076",
    "sg:province":"CA",
    "sg:tags":[
        "greenhouse"
    ],
    "wof:name":"Bloom-Rite Flowers Inc",
    "wof:placetype":"venue"
},
  "geometry": {"coordinates":[-121.82077,36.898616],"type":"Point"}
}