{
  "type": "Feature",
  "properties": {
    "addr:full":"756 S 9th Modesto CA 95350",
    "addr:housenumber":"756",
    "addr:postcode":"ca 95350",
    "addr:street":"S 9Th",
    "iso:country":"US",
    "sg:address":"756 S 9th",
    "sg:city":"Modesto",
    "sg:classifiers":[
        {
            "category":"Autos & Motor Vehicles",
            "subcategory":"Auto Supplies",
            "type":"Retail Goods"
        }
    ],
    "sg:phone":"+1 209 526 4090",
    "sg:postcode":"95350",
    "sg:province":"CA",
    "sg:tags":[
        "tire"
    ],
    "wof:name":"Garcia's Tires",
    "wof:placetype":"venue"
},
  "geometry": {"coordinates":[-120.984881,37.619226],"type":"Point"}
}