{
  "type": "Feature",
  "properties": {
    "iso:country":"US",
    "sg:address":"6700 Tarshes Dr",
    "sg:city":"Carmichael",
    "sg:classifiers":[
        {
            "category":"Sports & Exercise",
            "subcategory":"Golf",
            "type":"Entertainment"
        }
    ],
    "sg:phone":"+1 916 368 7888",
    "sg:postcode":"95608",
    "sg:province":"CA",
    "wof:name":"Ancil Hoffman Golf Course",
    "wof:placetype":"venue"
},
  "geometry": {"coordinates":[-121.318001,38.611301],"type":"Point"}
}