{
  "type": "Feature",
  "properties": {
    "addr:full":"421 Blue Ravine Rd Folsom CA 95630",
    "addr:housenumber":"421",
    "addr:postcode":"95630",
    "addr:street":"Blue Ravine Rd",
    "iso:country":"US",
    "sg:address":"421 Blue Ravine Rd",
    "sg:city":"Folsom",
    "sg:classifiers":[
        {
            "category":"Retail",
            "subcategory":"Veterinary Services",
            "type":"Services"
        }
    ],
    "sg:phone":"+1 916 984 0990",
    "sg:postcode":"95630",
    "sg:province":"CA",
    "sg:website":"www.blueravineanimalhospital.com",
    "wof:name":"Blue Ravine Animal Hospital",
    "wof:placetype":"venue"
},
  "geometry": {"coordinates":[-121.151979,38.670355],"type":"Point"}
}