{
  "type": "Feature",
  "properties": {
    "addr:full":"3713 Adams Ave San Diego CA 92116",
    "addr:housenumber":"3713",
    "addr:postcode":"92116",
    "addr:street":"Adams Ave",
    "iso:country":"US",
    "sg:address":"3713 Adams Ave",
    "sg:city":"San Diego",
    "sg:classifiers":[
        {
            "category":"Arts & Performance",
            "subcategory":"Art Gallery",
            "type":"Entertainment"
        }
    ],
    "sg:phone":"+1 619 280 1030",
    "sg:postcode":"92116",
    "sg:province":"CA",
    "wof:name":"Designer Tastes Gallery",
    "wof:placetype":"venue"
},
  "geometry": {"coordinates":[-117.112999,32.763199],"type":"Point"}
}