{
  "type": "Feature",
  "properties": {
    "addr:full":"1128 Morton St Alameda CA 94501",
    "addr:housenumber":"1128",
    "addr:postcode":"94501",
    "addr:street":"Morton St",
    "iso:country":"US",
    "sg:address":"1128 Morton St",
    "sg:city":"Alameda",
    "sg:classifiers":[
        {
            "category":"Retail",
            "subcategory":"Animal Services",
            "type":"Services"
        }
    ],
    "sg:phone":"+1 510 978 3366",
    "sg:postcode":"94501",
    "sg:province":"CA",
    "sg:tags":[
        "boarding",
        "pet",
        "boarding/pet",
        "sitting"
    ],
    "sg:website":"www.maureenspetcare.com",
    "wof:name":"Maureen's Pet Care",
    "wof:placetype":"venue"
},
  "geometry": {"coordinates":[-122.262001,37.7701],"type":"Point"}
}