{
  "type": "Feature",
  "properties": {
    "addr:full":"6025 Pine Ave Maywood CA 90270",
    "addr:housenumber":"6025",
    "addr:postcode":"90270",
    "addr:street":"Pine Ave",
    "iso:country":"US",
    "sg:address":"6025 Pine Ave",
    "sg:city":"Maywood",
    "sg:classifiers":[
        {
            "category":"Health Services",
            "subcategory":"Nursing And Care Facility",
            "type":"Services"
        }
    ],
    "sg:phone":"+1 323 560 0720",
    "sg:postcode":"90270",
    "sg:province":"CA",
    "sg:tags":[
        "home",
        "convalescent"
    ],
    "wof:name":"Pine Crest Convalescent Hosp",
    "wof:placetype":"venue"
},
  "geometry": {"coordinates":[-118.188047,33.985555],"type":"Point"}
}