{
  "type": "Feature",
  "properties": {
    "addr:full":"3270 Keller St Santa Clara CA 95054",
    "addr:housenumber":"3270",
    "addr:postcode":"95054",
    "addr:street":"Keller St",
    "iso:country":"US",
    "sg:address":"3270 Keller St",
    "sg:city":"Santa Clara",
    "sg:classifiers":[
        {
            "category":"Wholesale",
            "subcategory":"Apparel",
            "type":"Manufacturing & Wholesale Goods"
        }
    ],
    "sg:phone":"+1 408 727 4477",
    "sg:postcode":"95054",
    "sg:province":"CA",
    "sg:tags":[
        "trophy",
        "sweatshirt",
        "cap",
        "sport",
        "wear"
    ],
    "sg:website":"www.cacustom.com",
    "wof:name":"California Custom",
    "wof:placetype":"venue"
},
  "geometry": {"coordinates":[-121.948134,37.380386],"type":"Point"}
}