{
  "type": "Feature",
  "properties": {
    "addr:full":"9323 Stevens Rd Santee CA 92071",
    "addr:housenumber":"9323",
    "addr:postcode":"92071",
    "addr:street":"Stevens Rd",
    "iso:country":"US",
    "sg:address":"9323 Stevens Rd",
    "sg:city":"Santee",
    "sg:classifiers":[
        {
            "category":"Personal",
            "type":"Services"
        },
        {
            "category":"Retail",
            "subcategory":"Storage",
            "type":"Services"
        }
    ],
    "sg:phone":"+1 619 562 6111",
    "sg:postcode":"92071",
    "sg:province":"CA",
    "sg:tags":[
        "mover",
        "self"
    ],
    "wof:name":"C & M Transfer",
    "wof:placetype":"venue"
},
  "geometry": {"coordinates":[-116.962997,32.845299],"type":"Point"}
}