{
  "type": "Feature",
  "properties": {
    "iso:country":"US",
    "sg:address":"41 E Huntington Dr",
    "sg:city":"Arcadia",
    "sg:classifiers":[
        {
            "category":"Insurance",
            "subcategory":"Hazard Insurance",
            "type":"Services"
        },
        {
            "category":"Insurance",
            "subcategory":"Insurance Agent",
            "type":"Services"
        },
        {
            "category":"Insurance",
            "subcategory":"Life Insurance",
            "type":"Services"
        },
        {
            "category":"Insurance",
            "subcategory":"Title Insurance",
            "type":"Services"
        }
    ],
    "sg:phone":"+1 626 821 6811",
    "sg:postcode":"91006",
    "sg:province":"CA",
    "sg:tags":[
        "auto",
        "commercial",
        "business",
        "homeowner"
    ],
    "sg:website":"http://www.farmersagent.com/jestrada1/",
    "wof:name":"Jose Estrada - Farmers Insurance",
    "wof:placetype":"venue"
},
  "geometry": {"coordinates":[-118.033124,34.140006],"type":"Point"}
}