{
  "type": "Feature",
  "properties": {
    "iso:country":"US",
    "sg:address":"12028 Venice Blvd",
    "sg:city":"Los Angeles",
    "sg:classifiers":[
        {
            "category":"Shopping",
            "subcategory":"Florist",
            "type":"Retail Goods"
        }
    ],
    "sg:phone":"+1 310 398 5554",
    "sg:postcode":"90066",
    "sg:province":"CA",
    "sg:website":"www.ashleysflower.com",
    "wof:name":"Ashley's Flowers",
    "wof:placetype":"venue"
},
  "geometry": {"coordinates":[-118.429474,34.005387],"type":"Point"}
}