{
  "type": "Feature",
  "properties": {
    "addr:full":"175 Bosstick Blvd San Marcos CA 92069",
    "addr:housenumber":"175",
    "addr:postcode":"92069",
    "addr:street":"Bosstick Blvd",
    "iso:country":"US",
    "sg:address":"175 Bosstick Blvd",
    "sg:city":"San Marcos",
    "sg:classifiers":[
        {
            "category":"Building & Trades",
            "subcategory":"Construction",
            "type":"Services"
        }
    ],
    "sg:phone":"+1 760 535 1878",
    "sg:postcode":"92069",
    "sg:province":"CA",
    "sg:tags":[
        "fence",
        "contractor"
    ],
    "wof:name":"Glass Wall Systems",
    "wof:placetype":"venue"
},
  "geometry": {"coordinates":[-117.203216,33.159451],"type":"Point"}
}