{
  "type": "Feature",
  "properties": {
    "addr:full":"2135 Dale Ave. Sacramento CA 95815",
    "addr:housenumber":"2135",
    "addr:postcode":"95815",
    "addr:street":"Dale Ave.",
    "iso:country":"US",
    "sg:address":"2135 Dale Ave.",
    "sg:city":"Sacramento",
    "sg:classifiers":[
        {
            "category":"Professional",
            "type":"Services"
        }
    ],
    "sg:phone":"+1 916 641 0550",
    "sg:postcode":"95815",
    "sg:province":"CA",
    "sg:tags":[
        "caterer"
    ],
    "sg:website":"www.massapealcatering.com",
    "wof:name":"Massa Peal Catering",
    "wof:placetype":"venue"
},
  "geometry": {"coordinates":[-121.46267,38.605249],"type":"Point"}
}