{
  "type": "Feature",
  "properties": {
    "iso:country":"US",
    "sg:address":"215 Hwy 101",
    "sg:city":"Solana Beach",
    "sg:classifiers":[
        {
            "category":"Banks & Credit Unions",
            "subcategory":"Investment Brokerage",
            "type":"Services"
        }
    ],
    "sg:phone":"+1 858 350 9290",
    "sg:postcode":"92075",
    "sg:province":"CA",
    "sg:tags":[
        "advisory",
        "financial"
    ],
    "wof:name":"Homebuilders Financial Network",
    "wof:placetype":"venue"
},
  "geometry": {"coordinates":[-117.271677,32.991838],"type":"Point"}
}