{
  "type": "Feature",
  "properties": {
    "addr:full":"2360 Garfield Ave Los Angeles CA 90040",
    "addr:housenumber":"2360",
    "addr:postcode":"90040",
    "addr:street":"Garfield Ave",
    "iso:country":"US",
    "sg:address":"2360 Garfield Ave",
    "sg:city":"Los Angeles",
    "sg:classifiers":[
        {
            "category":"Manufacturing",
            "subcategory":"Food",
            "type":"Manufacturing & Wholesale Goods"
        }
    ],
    "sg:phone":"+1 323 728 7159",
    "sg:postcode":"90040",
    "sg:province":"CA",
    "sg:tags":[
        "margarine",
        "oil",
        "shortening"
    ],
    "wof:name":"PAR-Way Co",
    "wof:placetype":"venue"
},
  "geometry": {"coordinates":[-118.133123,33.999765],"type":"Point"}
}