{
  "type": "Feature",
  "properties": {
    "addr:full":"3400 W MacArthur Blvd Ste E Santa Ana CA 92704",
    "addr:housenumber":"3400",
    "addr:postcode":"92704",
    "addr:street":"W Macarthur Blvd Ste E",
    "iso:country":"US",
    "sg:address":"3400 W MacArthur Blvd Ste E",
    "sg:city":"Santa Ana",
    "sg:classifiers":[
        {
            "category":"Wholesale",
            "subcategory":"Computers",
            "type":"Manufacturing & Wholesale Goods"
        },
        {
            "category":"Shopping",
            "subcategory":"Computers & Home Electronics",
            "type":"Retail Goods"
        },
        {
            "category":"Professional",
            "subcategory":"Computer Services",
            "type":"Services"
        }
    ],
    "sg:phone":"+1 714 662 4959",
    "sg:postcode":"92704",
    "sg:province":"CA",
    "sg:tags":[
        "repair"
    ],
    "sg:website":"www.pinnaclemicro.com",
    "wof:name":"Pinnaclemicro",
    "wof:placetype":"venue"
},
  "geometry": {"coordinates":[-117.914852,33.700886],"type":"Point"}
}