{
  "type": "Feature",
  "properties": {
    "addr:full":"2415 Pasadena Ave Ste D Los Angeles CA 90031",
    "addr:housenumber":"2415",
    "addr:postcode":"90031",
    "addr:street":"Pasadena Ave Ste D",
    "iso:country":"US",
    "sg:address":"2415 Pasadena Ave Ste D",
    "sg:city":"Los Angeles",
    "sg:classifiers":[
        {
            "category":"Shopping",
            "subcategory":"Florist",
            "type":"Retail Goods"
        }
    ],
    "sg:phone":"+1 213 689 9999",
    "sg:postcode":"90031",
    "sg:province":"CA",
    "wof:name":"Los Angeles Florist & Gifts",
    "wof:placetype":"venue"
},
  "geometry": {"coordinates":[-118.21700300000001,34.076099],"type":"Point"}
}