{
  "type": "Feature",
  "properties": {
    "addr:full":"6500 Palma Ave Atascadero CA 93422",
    "addr:postcode":"6500;93422",
    "addr:street":"Palma Ave",
    "iso:country":"US",
    "sg:address":"6500 Palma Ave",
    "sg:city":"Atascadero",
    "sg:classifiers":[
        {
            "category":"Government",
            "subcategory":"Office",
            "type":"Public Place"
        }
    ],
    "sg:phone":"+1 805 461 1034",
    "sg:postcode":"93422",
    "sg:province":"CA",
    "wof:name":"Congressman Bill Thomas",
    "wof:placetype":"venue"
},
  "geometry": {"coordinates":[-120.66781400000001,35.489684],"type":"Point"}
}