{
  "type": "Feature",
  "properties": {
    "addr:full":"12440 Oak Knoll Rd Poway CA 92064",
    "addr:housenumber":"12440",
    "addr:postcode":"ca 92064",
    "addr:street":"Oak Knoll Rd",
    "iso:country":"US",
    "sg:address":"12440 Oak Knoll Rd",
    "sg:city":"Poway",
    "sg:classifiers":[
        {
            "category":"Real Estate",
            "subcategory":"Real Estate Operator",
            "type":"Services"
        }
    ],
    "sg:phone":"+1 858 748 3779",
    "sg:postcode":"92064",
    "sg:province":"CA",
    "sg:tags":[
        "apartment"
    ],
    "wof:name":"Oak Manor Apartments",
    "wof:placetype":"venue"
},
  "geometry": {"coordinates":[-117.061136,32.950238],"type":"Point"}
}