{
  "type": "Feature",
  "properties": {
    "addr:full":"18450 Clark St Tarzana CA 91356",
    "addr:housenumber":"18450",
    "addr:postcode":"91356",
    "addr:street":"Clark St",
    "iso:country":"US",
    "sg:address":"18450 Clark St",
    "sg:city":"Tarzana",
    "sg:classifiers":[
        {
            "category":"Food & Beverages",
            "subcategory":"Bakery",
            "type":"Retail Goods"
        }
    ],
    "sg:phone":"+1 818 344 0100",
    "sg:postcode":"91356",
    "sg:province":"CA",
    "sg:tags":[
        "baker"
    ],
    "sg:website":"www.beasbakery.com",
    "wof:name":"Bea's Bakery",
    "wof:placetype":"venue"
},
  "geometry": {"coordinates":[-118.534606,34.169779],"type":"Point"}
}