{
  "type": "Feature",
  "properties": {
    "addr:full":"7231 Boulder Ave Highland CA 92346",
    "addr:housenumber":"7231",
    "addr:postcode":"92346",
    "addr:street":"Boulder Ave",
    "iso:country":"US",
    "sg:address":"7231 Boulder Ave",
    "sg:city":"Highland",
    "sg:classifiers":[
        {
            "category":"Manufacturing",
            "subcategory":"Chemicals & Compounds",
            "type":"Manufacturing & Wholesale Goods"
        }
    ],
    "sg:phone":"+1 951 347 1128",
    "sg:postcode":"92346",
    "sg:province":"CA",
    "sg:tags":[
        "paint",
        "product",
        "industrial",
        "cleaning",
        "mfg"
    ],
    "wof:name":"Diversified Industrial Pdts",
    "wof:placetype":"venue"
},
  "geometry": {"coordinates":[-117.19546699999999,34.124895],"type":"Point"}
}