{
  "type": "Feature",
  "properties": {
    "addr:full":"1933 Laredo Ct Stockton CA 95209",
    "addr:housenumber":"1933",
    "addr:postcode":"95209",
    "addr:street":"Laredo Ct",
    "iso:country":"US",
    "sg:address":"1933 Laredo Ct",
    "sg:city":"Stockton",
    "sg:classifiers":[
        {
            "category":"Manufacturing",
            "subcategory":"Metals",
            "type":"Manufacturing & Wholesale Goods"
        }
    ],
    "sg:phone":"+1 209 474 3434",
    "sg:postcode":"95209",
    "sg:province":"CA",
    "sg:tags":[
        "cap",
        "bottle",
        "seal"
    ],
    "wof:name":"White Cap Inc",
    "wof:placetype":"venue"
},
  "geometry": {"coordinates":[-121.336411,38.04013],"type":"Point"}
}