{
  "type": "Feature",
  "properties": {
    "addr:full":"785 Fulton St San Francisco CA 94102",
    "addr:housenumber":"785",
    "addr:postcode":"94102",
    "addr:street":"Fulton St",
    "iso:country":"US",
    "sg:address":"785 Fulton St",
    "sg:city":"San Francisco",
    "sg:classifiers":[
        {
            "category":"Health Services",
            "subcategory":"Clinic",
            "type":"Services"
        }
    ],
    "sg:phone":"+1 415 864 1007",
    "sg:postcode":"94102",
    "sg:province":"CA",
    "wof:name":"A-1 Health Care Svc",
    "wof:placetype":"venue"
},
  "geometry": {"coordinates":[-122.42949900000001,37.777868],"type":"Point"}
}