{
  "type": "Feature",
  "properties": {
    "iso:country":"US",
    "sg:address":"785 Fulton St",
    "sg:city":"San Francisco",
    "sg:classifiers":[
        {
            "category":"Health Services",
            "subcategory":"Clinic",
            "type":"Services"
        }
    ],
    "sg:phone":"+1 415 864 1007",
    "sg:postcode":"94102",
    "sg:province":"CA",
    "wof:name":"A-1 Health Care Svc",
    "wof:placetype":"venue"
},
  "geometry": {"coordinates":[-122.429499,37.777868],"type":"Point"}
}