{
  "type": "Feature",
  "properties": {
    "addr:full":"4711 Campbell Avenue San Jose CA 95130",
    "addr:housenumber":"4711",
    "addr:postcode":"95130",
    "addr:street":"Campbell Avenue",
    "iso:country":"US",
    "sg:address":"4711 Campbell Avenue",
    "sg:city":"San Jose",
    "sg:classifiers":[
        {
            "category":"Education",
            "subcategory":"School",
            "type":"Public Place"
        }
    ],
    "sg:phone":"+1 408 874 2900",
    "sg:postcode":"95130",
    "sg:province":"CA",
    "wof:name":"Moreland School District",
    "wof:placetype":"venue"
},
  "geometry": {"coordinates":[-121.984488,37.286333],"type":"Point"}
}