{
  "type": "Feature",
  "properties": {
    "addr:full":"2072 E 20th St Chico CA 95928",
    "addr:housenumber":"2072",
    "addr:postcode":"95928",
    "addr:street":"E 20Th St",
    "iso:country":"US",
    "sg:address":"2072 E 20th St",
    "sg:city":"Chico",
    "sg:classifiers":[
        {
            "category":"Restaurant",
            "type":"Food & Drink"
        }
    ],
    "sg:menulink":"http://www.allmenus.com/ca/chico/17566-baja-fresh-mexican-grill/menu/",
    "sg:phone":"+1 530 342 9791",
    "sg:postcode":"95928",
    "sg:province":"CA",
    "sg:tags":[
        "mexican"
    ],
    "wof:name":"Baja Fresh Mexican Grill",
    "wof:placetype":"venue"
},
  "geometry": {"coordinates":[-121.791128,39.726784],"type":"Point"}
}