{
  "type": "Feature",
  "properties": {
    "addr:full":"329 Jefferson St Oakland CA 94607",
    "addr:housenumber":"329",
    "addr:postcode":"94607",
    "addr:street":"Jefferson St",
    "iso:country":"US",
    "sg:address":"329 Jefferson St",
    "sg:city":"Oakland",
    "sg:classifiers":[
        {
            "category":"Utilities",
            "subcategory":"Electric",
            "type":"Services"
        }
    ],
    "sg:phone":"+1 510 625 7900",
    "sg:postcode":"94607",
    "sg:province":"CA",
    "sg:tags":[
        "company"
    ],
    "wof:name":"National Power Co",
    "wof:placetype":"venue"
},
  "geometry": {"coordinates":[-122.27923699999999,37.798787],"type":"Point"}
}