{
  "type": "Feature",
  "properties": {
    "iso:country":"US",
    "sg:address":"1843 262nd St",
    "sg:city":"Lomita",
    "sg:classifiers":[
        {
            "category":"Retail",
            "subcategory":"Auto Repair",
            "type":"Services"
        }
    ],
    "sg:phone":"+1 310 539 8807",
    "sg:postcode":"90717",
    "sg:province":"CA",
    "sg:tags":[
        "body",
        "automobile",
        "painting"
    ],
    "wof:name":"Russ' Custom Car Care",
    "wof:placetype":"venue"
},
  "geometry": {"coordinates":[-118.312493,33.785276],"type":"Point"}
}