{
  "type": "Feature",
  "properties": {
    "iso:country":"US",
    "sg:address":"1264 N Ventura Ave",
    "sg:city":"Ventura",
    "sg:classifiers":[
        {
            "category":"Shopping",
            "subcategory":"Used Merchandise",
            "type":"Retail Goods"
        }
    ],
    "sg:phone":"+1 805 643 6426",
    "sg:postcode":"93001",
    "sg:province":"CA",
    "sg:tags":[
        "shop",
        "thrift"
    ],
    "wof:name":"LA Barata Thrift Store",
    "wof:placetype":"venue"
},
  "geometry": {"coordinates":[-119.296611,34.294907],"type":"Point"}
}