{
  "type": "Feature",
  "properties": {
    "iso:country":"US",
    "sg:address":"25672 Rangewood Rd",
    "sg:city":"Laguna Hills",
    "sg:classifiers":[
        {
            "category":"Professional",
            "type":"Services"
        }
    ],
    "sg:phone":"+1 949 425 9805",
    "sg:postcode":"92653",
    "sg:province":"CA",
    "wof:name":"Ocamp Inc",
    "wof:placetype":"venue"
},
  "geometry": {"coordinates":[-117.682091,33.589354],"type":"Point"}
}