{
  "type": "Feature",
  "properties": {
    "addr:full":"12901 Saticoy St North Hollywood CA 91605",
    "addr:housenumber":"12901",
    "addr:postcode":"91605",
    "addr:street":"Saticoy St",
    "iso:country":"US",
    "sg:address":"12901 Saticoy St",
    "sg:city":"North Hollywood",
    "sg:classifiers":[
        {
            "category":"Shopping",
            "type":"Retail Goods"
        }
    ],
    "sg:phone":"+1 818 765 3770",
    "sg:postcode":"91605",
    "sg:province":"CA",
    "sg:tags":[
        "trophy",
        "medal",
        "award"
    ],
    "wof:name":"Anderson Trophy Co",
    "wof:placetype":"venue"
},
  "geometry": {"coordinates":[-118.41815800000001,34.207356],"type":"Point"}
}