{
  "type": "Feature",
  "properties": {
    "addr:full":"1946 Fillmore St San Francisco CA 94115",
    "addr:housenumber":"1946",
    "addr:postcode":"94115",
    "addr:street":"Fillmore St",
    "iso:country":"US",
    "sg:address":"1946 Fillmore St",
    "sg:city":"San Francisco",
    "sg:classifiers":[
        {
            "category":"Restaurant",
            "type":"Food & Drink"
        }
    ],
    "sg:menulink":"http://www.allmenus.com/ca/san-francisco/45331-johnny-rockets/menu/",
    "sg:phone":"+1 415 776 9878",
    "sg:postcode":"94115",
    "sg:province":"CA",
    "sg:tags":[
        "burger",
        "american"
    ],
    "wof:name":"Johnny Rockets",
    "wof:placetype":"venue"
},
  "geometry": {"coordinates":[-122.43360699999999,37.787688],"type":"Point"}
}