{
  "type": "Feature",
  "properties": {
    "iso:country":"US",
    "sg:address":"2982 W Pico Blvd",
    "sg:city":"Los Angeles",
    "sg:classifiers":[
        {
            "category":"Manufacturing",
            "subcategory":"Tools & Machinery",
            "type":"Manufacturing & Wholesale Goods"
        }
    ],
    "sg:phone":"+1 323 734 7070",
    "sg:postcode":"90006",
    "sg:province":"CA",
    "sg:tags":[
        "industry",
        "mfg"
    ],
    "wof:name":"Olympic Glass",
    "wof:placetype":"venue"
},
  "geometry": {"coordinates":[-118.30592,34.047129],"type":"Point"}
}