{
  "type": "Feature",
  "properties": {
    "addr:full":"329 E Tulare St Dinuba CA 93618",
    "addr:housenumber":"329",
    "addr:postcode":"93618",
    "addr:street":"E Tulare St",
    "iso:country":"US",
    "sg:address":"329 E Tulare St",
    "sg:city":"Dinuba",
    "sg:classifiers":[
        {
            "category":"Shopping",
            "subcategory":"Florist",
            "type":"Retail Goods"
        }
    ],
    "sg:phone":"+1 559 591 3092",
    "sg:postcode":"93618",
    "sg:province":"CA",
    "wof:name":"Angelas Boutique",
    "wof:placetype":"venue"
},
  "geometry": {"coordinates":[-119.388017,36.542602],"type":"Point"}
}