{
  "type": "Feature",
  "properties": {
    "iso:country":"US",
    "sg:address":"555 Broadway Ave",
    "sg:city":"Seaside",
    "sg:classifiers":[
        {
            "category":"Personal",
            "type":"Services"
        }
    ],
    "sg:phone":"+1 831 394 5206",
    "sg:postcode":"93955",
    "sg:province":"CA",
    "sg:tags":[
        "program",
        "physical",
        "exercise",
        "fitness"
    ],
    "wof:name":"All Around Fitness",
    "wof:placetype":"venue"
},
  "geometry": {"coordinates":[-121.85124,36.609344],"type":"Point"}
}