{
  "type": "Feature",
  "properties": {
    "addr:full":"1418 N. Kraemer Blvd. Placentia CA 92870",
    "addr:housenumber":"1418",
    "addr:postcode":"ca 92870",
    "addr:street":"N. Kraemer Blvd.",
    "iso:country":"US",
    "sg:address":"1418 N. Kraemer Blvd.",
    "sg:city":"Placentia",
    "sg:classifiers":[
        {
            "category":"Personal",
            "subcategory":"Day Spa",
            "type":"Services"
        },
        {
            "category":"Personal",
            "subcategory":"Nail Salon",
            "type":"Services"
        }
    ],
    "sg:phone":"+1 866 257 1465",
    "sg:postcode":"92870",
    "sg:province":"CA",
    "sg:website":"www.angelnailsspa.com",
    "wof:name":"Angel Nails & Spa",
    "wof:placetype":"venue"
},
  "geometry": {"coordinates":[-117.863181,33.887049],"type":"Point"}
}