{
  "type": "Feature",
  "properties": {
    "addr:full":"1020 E Washington St Colton CA 92324",
    "addr:housenumber":"1020",
    "addr:postcode":"92324",
    "addr:street":"E Washington St",
    "iso:country":"US",
    "sg:address":"1020 E Washington St",
    "sg:city":"Colton",
    "sg:classifiers":[
        {
            "category":"Education",
            "subcategory":"Vocational School",
            "type":"Public Place"
        }
    ],
    "sg:phone":"+1 909 783 9331",
    "sg:postcode":"92324",
    "sg:province":"CA",
    "sg:tags":[
        "nurse"
    ],
    "wof:name":"Four-D College",
    "wof:placetype":"venue"
},
  "geometry": {"coordinates":[-117.311393,34.048273],"type":"Point"}
}