{
  "type": "Feature",
  "properties": {
    "addr:full":"600 Administration Dr Santa Rosa CA 95403",
    "addr:housenumber":"600",
    "addr:postcode":"95403",
    "addr:street":"Administration Dr",
    "iso:country":"US",
    "sg:address":"600 Administration Dr",
    "sg:city":"Santa Rosa",
    "sg:classifiers":[
        {
            "category":"Government",
            "subcategory":"Office",
            "type":"Public Place"
        }
    ],
    "sg:phone":"+1 707 565 2169",
    "sg:postcode":"95403",
    "sg:province":"CA",
    "wof:name":"Sonoma County Jury Svc",
    "wof:placetype":"venue"
},
  "geometry": {"coordinates":[-122.725858,38.464148],"type":"Point"}
}