{
  "type": "Feature",
  "properties": {
    "addr:full":"1871 E Dakota Ave Fresno CA 93726",
    "addr:housenumber":"1871",
    "addr:postcode":"93726",
    "addr:street":"E Dakota Ave",
    "iso:country":"US",
    "sg:address":"1871 E Dakota Ave",
    "sg:city":"Fresno",
    "sg:classifiers":[
        {
            "category":"Bars & Pubs",
            "type":"Food & Drink"
        }
    ],
    "sg:phone":"+1 559 227 3000",
    "sg:postcode":"93726",
    "sg:province":"CA",
    "sg:tags":[
        "lounge",
        "cocktail"
    ],
    "wof:name":"Club Dakota",
    "wof:placetype":"venue"
},
  "geometry": {"coordinates":[-119.789098,36.786835],"type":"Point"}
}