{
  "type": "Feature",
  "properties": {
    "iso:country":"US",
    "sg:address":"1467 W 178th St",
    "sg:city":"Gardena",
    "sg:classifiers":[
        {
            "category":"Shopping",
            "subcategory":"Computers & Home Electronics",
            "type":"Retail Goods"
        }
    ],
    "sg:phone":"+1 310 715 1809",
    "sg:postcode":"90248",
    "sg:province":"CA",
    "sg:tags":[
        "software"
    ],
    "wof:name":"Full Force Graffics",
    "wof:placetype":"venue"
},
  "geometry": {"coordinates":[-118.300365,33.869297],"type":"Point"}
}