{
  "type": "Feature",
  "properties": {
    "addr:full":"755 San Pablo Ave Albany CA 94706",
    "addr:housenumber":"755",
    "addr:postcode":"94706",
    "addr:street":"San Pablo Ave",
    "iso:country":"US",
    "sg:address":"755 San Pablo Ave",
    "sg:city":"Albany",
    "sg:classifiers":[
        {
            "category":"Restaurant",
            "type":"Food & Drink"
        }
    ],
    "sg:menulink":"http://www.allmenus.com/ca/berkeley/22466-mangia-mangia/menu/",
    "sg:phone":"+1 510 526 9700",
    "sg:postcode":"94706",
    "sg:province":"CA",
    "sg:tags":[
        "italian"
    ],
    "wof:name":"Mangia Mangia",
    "wof:placetype":"venue"
},
  "geometry": {"coordinates":[-122.29955,37.892199],"type":"Point"}
}