{
  "type": "Feature",
  "properties": {
    "addr:full":"12575 Newport Ave Tustin CA 92780",
    "addr:housenumber":"12575",
    "addr:postcode":"92780",
    "addr:street":"Newport Ave",
    "iso:country":"US",
    "sg:address":"12575 Newport Ave",
    "sg:city":"Tustin",
    "sg:classifiers":[
        {
            "category":"Social Services",
            "type":"Services"
        }
    ],
    "sg:phone":"+1 714 730 3400",
    "sg:postcode":"92780",
    "sg:province":"CA",
    "sg:tags":[
        "information",
        "cancer"
    ],
    "wof:name":"American Oral Cancer Fndtn",
    "wof:placetype":"venue"
},
  "geometry": {"coordinates":[-117.80614199999999,33.754297],"type":"Point"}
}