{
  "type": "Feature",
  "properties": {
    "addr:full":"1786 S Hwy 101 San Marcos CA 92007",
    "addr:housenumber":"1786",
    "addr:postcode":"92007",
    "addr:street":"S Hwy 101",
    "iso:country":"US",
    "sg:address":"1786 S Hwy 101",
    "sg:city":"San Marcos",
    "sg:classifiers":[
        {
            "category":"Building & Trades",
            "subcategory":"Construction",
            "type":"Services"
        }
    ],
    "sg:phone":"+1 760 744 7024",
    "sg:postcode":"92007",
    "sg:province":"CA",
    "sg:tags":[
        "maker",
        "cabinet"
    ],
    "sg:website":"www.inner-space-designs.com",
    "wof:name":"Inner Space Designs Inc",
    "wof:placetype":"venue"
},
  "geometry": {"coordinates":[-117.29021299999999,33.03273],"type":"Point"}
}