{
  "type": "Feature",
  "properties": {
    "addr:full":"32302 Alipaz St San Juan Capistrano CA 92675",
    "addr:housenumber":"32302",
    "addr:postcode":"92675",
    "addr:street":"Alipaz St",
    "iso:country":"US",
    "sg:address":"32302 Alipaz St",
    "sg:city":"San Juan Capistrano",
    "sg:classifiers":[
        {
            "category":"Shopping",
            "subcategory":"Gifts & Souvenirs",
            "type":"Retail Goods"
        }
    ],
    "sg:phone":"+1 949 487 2549",
    "sg:postcode":"92675",
    "sg:province":"CA",
    "wof:name":"Discount Gift Ideas",
    "wof:placetype":"venue"
},
  "geometry": {"coordinates":[-117.67143,33.491782],"type":"Point"}
}