{
  "type": "Feature",
  "properties": {
    "iso:country":"US",
    "sg:address":"629 S Thornhill Rd",
    "sg:city":"Palm Springs",
    "sg:classifiers":[
        {
            "category":"Professional",
            "subcategory":"Management & Consulting",
            "type":"Services"
        }
    ],
    "sg:phone":"+1 760 323 1231",
    "sg:postcode":"92264",
    "sg:province":"CA",
    "sg:tags":[
        "business",
        "merchandise"
    ],
    "wof:name":"Flowerist The",
    "wof:placetype":"venue"
},
  "geometry": {"coordinates":[-116.533186,33.812908],"type":"Point"}
}