{
  "type": "Feature",
  "properties": {
    "addr:full":"5841 Crest Rd Rancho Pls Vrds CA 90275",
    "addr:housenumber":"5841",
    "addr:postcode":"90275",
    "addr:street":"Crest Rd",
    "iso:country":"US",
    "sg:address":"5841 Crest Rd",
    "sg:city":"Rancho Pls Vrds",
    "sg:classifiers":[
        {
            "category":"Personal",
            "subcategory":"Beauty Salon",
            "type":"Services"
        }
    ],
    "sg:phone":"+1 310 541 8459",
    "sg:postcode":"90275",
    "sg:province":"CA",
    "wof:name":"Dimond For Hair",
    "wof:placetype":"venue"
},
  "geometry": {"coordinates":[-118.374652,33.76049],"type":"Point"}
}