{
  "type": "Feature",
  "properties": {
    "addr:full":"705 S Long Beach Blvd Compton CA 90221",
    "addr:housenumber":"705",
    "addr:postcode":"90221",
    "addr:street":"S Long Beach Blvd",
    "iso:country":"US",
    "sg:address":"705 S Long Beach Blvd",
    "sg:city":"Compton",
    "sg:classifiers":[
        {
            "category":"Personal",
            "subcategory":"Beauty Salon",
            "type":"Services"
        }
    ],
    "sg:phone":"+1 310 604 9587",
    "sg:postcode":"90221",
    "sg:province":"CA",
    "wof:name":"Creative Images-West",
    "wof:placetype":"venue"
},
  "geometry": {"coordinates":[-118.20751199999999,33.890362],"type":"Point"}
}