{
  "type": "Feature",
  "properties": {
    "iso:country":"US",
    "sg:address":"25332 Misty Rdg",
    "sg:city":"Mission Viejo",
    "sg:classifiers":[
        {
            "category":"Shopping",
            "subcategory":"Clothing, Apparel, & Fashions",
            "type":"Retail Goods"
        }
    ],
    "sg:phone":"+1 949 770 6095",
    "sg:postcode":"92692",
    "sg:province":"CA",
    "sg:tags":[
        "clothing",
        "women's"
    ],
    "wof:name":"Rv Gear Inc",
    "wof:placetype":"venue"
},
  "geometry": {"coordinates":[-117.639999,33.597099],"type":"Point"}
}