{
  "type": "Feature",
  "properties": {
    "addr:full":"72990 El Paseo Palm Desert CA 92260",
    "addr:housenumber":"72990",
    "addr:postcode":"ca 92260",
    "addr:street":"El Paseo",
    "iso:country":"US",
    "sg:address":"72990 El Paseo",
    "sg:city":"Palm Desert",
    "sg:classifiers":[
        {
            "category":"Personal",
            "subcategory":"Tanning Parlor",
            "type":"Services"
        },
        {
            "category":"Personal",
            "subcategory":"Nail Salon",
            "type":"Services"
        }
    ],
    "sg:phone":"+1 760 837 9190",
    "sg:postcode":"92260",
    "sg:province":"CA",
    "wof:name":"Amazing Nailspa & Tanning",
    "wof:placetype":"venue"
},
  "geometry": {"coordinates":[-116.391408,33.719943],"type":"Point"}
}