{
  "type": "Feature",
  "properties": {
    "iso:country":"US",
    "sg:address":"1328 18th St",
    "sg:city":"San Francisco",
    "sg:classifiers":[
        {
            "category":"Bars & Pubs",
            "type":"Food & Drink"
        },
        {
            "category":"Restaurant",
            "type":"Food & Drink"
        }
    ],
    "sg:menulink":"http://www.allmenus.com/ca/san-francisco/61859-san-francisco-thai-bar-b-q/menu/",
    "sg:phone":"+1 415 431 8956",
    "sg:postcode":"94107",
    "sg:province":"CA",
    "sg:tags":[
        "thai",
        "asian"
    ],
    "wof:name":"San Francisco Thai Bar-b-q",
    "wof:placetype":"venue"
},
  "geometry": {"coordinates":[-122.395872,37.762653],"type":"Point"}
}