{
  "type": "Feature",
  "properties": {
    "addr:full":"8747 Sierra College Blvd Roseville CA 95661",
    "addr:housenumber":"8747",
    "addr:postcode":"95661",
    "addr:street":"Sierra College Blvd",
    "iso:country":"US",
    "sg:address":"8747 Sierra College Blvd",
    "sg:city":"Roseville",
    "sg:classifiers":[
        {
            "category":"Social Services",
            "subcategory":"Child Care",
            "type":"Services"
        }
    ],
    "sg:phone":"+1 916 791 2530",
    "sg:postcode":"95661",
    "sg:province":"CA",
    "wof:name":"Childtime Learning Ctr",
    "wof:placetype":"venue"
},
  "geometry": {"coordinates":[-121.22590599999999,38.739199],"type":"Point"}
}