{
  "type": "Feature",
  "properties": {
    "iso:country":"US",
    "sg:address":"1298 W Capitol Ave",
    "sg:city":"West Sacramento",
    "sg:classifiers":[
        {
            "category":"Shopping Center",
            "type":"Public Place"
        }
    ],
    "sg:phone":"+1 916 371 5205",
    "sg:postcode":"95691",
    "sg:province":"CA",
    "sg:website":"www.safeway.com",
    "wof:name":"Safeway",
    "wof:placetype":"venue"
},
  "geometry": {"coordinates":[-121.526157,38.582498],"type":"Point"}
}