{
  "type": "Feature",
  "properties": {
    "iso:country":"US",
    "sg:address":"1050 Northgate Dr",
    "sg:city":"San Rafael",
    "sg:classifiers":[
        {
            "category":"Professional",
            "subcategory":"Lawyer & Legal Services",
            "type":"Services"
        }
    ],
    "sg:phone":"+1 415 924 4250",
    "sg:postcode":"94903",
    "sg:province":"CA",
    "sg:tags":[
        "attorney"
    ],
    "sg:website":"www.rothken.com",
    "wof:name":"Rothken Law Firm  LLP",
    "wof:placetype":"venue"
},
  "geometry": {"coordinates":[-122.545257,38.008527],"type":"Point"}
}