{
  "type": "Feature",
  "properties": {
    "iso:country":"US",
    "sg:address":"3014 Lawrence Expy.",
    "sg:city":"Santa Clara",
    "sg:classifiers":[
        {
            "category":"Education",
            "subcategory":"Music School",
            "type":"Public Place"
        },
        {
            "category":"Communications",
            "type":"Services"
        }
    ],
    "sg:phone":"+1 510 632 2893",
    "sg:postcode":"95051",
    "sg:province":"CA",
    "sg:tags":[
        "rehearsal",
        "teacher",
        "recording",
        "instrument",
        "studio",
        "musical"
    ],
    "sg:website":"BayAreaRecording.com/",
    "wof:name":"Bay Area Recording Studios",
    "wof:placetype":"venue"
},
  "geometry": {"coordinates":[-121.996058,37.376868],"type":"Point"}
}