{
  "type": "Feature",
  "properties": {
    "addr:full":"175 Los Trancos Rd Portola Valley CA 94028",
    "addr:housenumber":"175",
    "addr:postcode":"94028",
    "addr:street":"Los Trancos Rd",
    "iso:country":"US",
    "sg:address":"175 Los Trancos Rd",
    "sg:city":"Portola Valley",
    "sg:classifiers":[
        {
            "category":"Real Estate",
            "subcategory":"Real Estate Agent",
            "type":"Services"
        }
    ],
    "sg:phone":"+1 650 529 1043",
    "sg:postcode":"94028",
    "sg:province":"CA",
    "wof:name":"Ted Luce Real Estate Inc",
    "wof:placetype":"venue"
},
  "geometry": {"coordinates":[-122.201555,37.372395],"type":"Point"}
}