{
  "type": "Feature",
  "properties": {
    "iso:country":"US",
    "sg:address":"919 Hopper Ave",
    "sg:city":"Santa Rosa",
    "sg:classifiers":[
        {
            "category":"Restaurant",
            "type":"Food & Drink"
        }
    ],
    "sg:phone":"+1 707 526 4603",
    "sg:postcode":"95403",
    "sg:province":"CA",
    "wof:name":"Arby's",
    "wof:placetype":"venue"
},
  "geometry": {"coordinates":[-122.736548,38.479781],"type":"Point"}
}