{
  "type": "Feature",
  "properties": {
    "iso:country":"US",
    "sg:address":"4459 Riverside Dr",
    "sg:city":"Chino",
    "sg:classifiers":[
        {
            "category":"Wholesale",
            "subcategory":"Meat",
            "type":"Manufacturing & Wholesale Goods"
        }
    ],
    "sg:phone":"+1 909 464 9488",
    "sg:postcode":"91710",
    "sg:province":"CA",
    "wof:name":"Sunbelt Food Co Inc",
    "wof:placetype":"venue"
},
  "geometry": {"coordinates":[-117.70714,34.018882],"type":"Point"}
}