{
  "type": "Feature",
  "properties": {
    "addr:full":"80 Swan Way Oakland CA 94621",
    "addr:housenumber":"80",
    "addr:postcode":"94621",
    "addr:street":"Swan Way",
    "iso:country":"US",
    "sg:address":"80 Swan Way",
    "sg:city":"Oakland",
    "sg:classifiers":[
        {
            "category":"Professional",
            "subcategory":"Detective & Security Services",
            "type":"Services"
        }
    ],
    "sg:phone":"+1 510 746 5699",
    "sg:postcode":"94621",
    "sg:province":"CA",
    "sg:tags":[
        "private",
        "investigator"
    ],
    "wof:name":"Informed Decision Corp",
    "wof:placetype":"venue"
},
  "geometry": {"coordinates":[-122.206591,37.730985],"type":"Point"}
}