{
  "type": "Feature",
  "properties": {
    "iso:country":"US",
    "sg:address":"4905 Newport Ave",
    "sg:city":"San Diego",
    "sg:classifiers":[
        {
            "category":"Food & Beverages",
            "subcategory":"Meat & Fish",
            "type":"Retail Goods"
        }
    ],
    "sg:postcode":"92107",
    "sg:province":"CA",
    "sg:tags":[
        "hot",
        "dog"
    ],
    "sg:website":"www.facebook.com/#!/pages/Ocean-...",
    "wof:name":"Hot Diggity Dog",
    "wof:placetype":"venue"
},
  "geometry": {"coordinates":[-117.249707,32.74586],"type":"Point"}
}