{
  "type": "Feature",
  "properties": {
    "iso:country":"US",
    "sg:address":"1528 Victoria Dr",
    "sg:city":"Modesto",
    "sg:classifiers":[
        {
            "category":"Freight",
            "type":"Transportation"
        }
    ],
    "sg:phone":"+1 209 526 0788",
    "sg:postcode":"95351",
    "sg:province":"CA",
    "sg:tags":[
        "operator",
        "local",
        "trucking"
    ],
    "wof:name":"Oas Trucking",
    "wof:placetype":"venue"
},
  "geometry": {"coordinates":[-121.029583,37.619853],"type":"Point"}
}