{
  "type": "Feature",
  "properties": {
    "iso:country":"US",
    "sg:address":"10660 Riverside Dr Ste D",
    "sg:city":"Toluca Lake",
    "sg:classifiers":[
        {
            "category":"Personal",
            "subcategory":"Tanning Parlor",
            "type":"Services"
        },
        {
            "category":"Personal",
            "subcategory":"Skin Care",
            "type":"Services"
        }
    ],
    "sg:phone":"+1 818 506 8266",
    "sg:postcode":"91602",
    "sg:province":"CA",
    "sg:website":"onthebeachcenter.com",
    "wof:name":"On The Beach Day Spa & Tanning Center",
    "wof:placetype":"venue"
},
  "geometry": {"coordinates":[-118.36364399999999,34.151922],"type":"Point"}
}