{
  "type": "Feature",
  "properties": {
    "addr:full":"1494 N Beale Rd Marysville CA 95901",
    "addr:housenumber":"1494",
    "addr:postcode":"95901",
    "addr:street":"N Beale Rd",
    "iso:country":"US",
    "sg:address":"1494 N Beale Rd",
    "sg:city":"Marysville",
    "sg:classifiers":[
        {
            "category":"Personal",
            "subcategory":"Barber",
            "type":"Services"
        }
    ],
    "sg:phone":"+1 530 742 6390",
    "sg:postcode":"95901",
    "sg:province":"CA",
    "wof:name":"Nor-Cal Barber Shop",
    "wof:placetype":"venue"
},
  "geometry": {"coordinates":[-121.564533,39.127124],"type":"Point"}
}