{
  "type": "Feature",
  "properties": {
    "iso:country":"US",
    "sg:address":"15430 Hesperian Blvd",
    "sg:city":"San Leandro",
    "sg:classifiers":[
        {
            "category":"Home & Garden",
            "subcategory":"Furniture",
            "type":"Retail Goods"
        }
    ],
    "sg:phone":"+1 510 481 1623",
    "sg:postcode":"94578",
    "sg:province":"CA",
    "sg:tags":[
        "mattress"
    ],
    "wof:name":"New National Mattress Ctr",
    "wof:placetype":"venue"
},
  "geometry": {"coordinates":[-122.130056,37.691397],"type":"Point"}
}