{
  "type": "Feature",
  "properties": {
    "addr:full":"6603 Independence Ave Canoga Park CA 91303",
    "addr:housenumber":"6603",
    "addr:postcode":"91303",
    "addr:street":"Independence Ave",
    "iso:country":"US",
    "sg:address":"6603 Independence Ave",
    "sg:city":"Canoga Park",
    "sg:classifiers":[
        {
            "category":"Restaurant",
            "type":"Food & Drink"
        }
    ],
    "sg:phone":"+1 818 712 0110",
    "sg:postcode":"91303",
    "sg:province":"CA",
    "sg:tags":[
        "pizza"
    ],
    "wof:name":"Ameci Corporate Ofc",
    "wof:placetype":"venue"
},
  "geometry": {"coordinates":[-118.591003,34.190601],"type":"Point"}
}