{
  "type": "Feature",
  "properties": {
    "addr:full":"10200 Venice Blvd Ste 201 Culver City CA 90232",
    "addr:housenumber":"10200",
    "addr:postcode":"90232",
    "addr:street":"Venice Blvd Ste 201",
    "iso:country":"US",
    "sg:address":"10200 Venice Blvd Ste 201",
    "sg:city":"Culver City",
    "sg:classifiers":[
        {
            "category":"Insurance",
            "subcategory":"Hazard Insurance",
            "type":"Services"
        }
    ],
    "sg:phone":"+1 310 425 8000",
    "sg:postcode":"90232",
    "sg:province":"CA",
    "sg:website":"www.bmpinsurance.com",
    "wof:name":"BMP Insurance",
    "wof:placetype":"venue"
},
  "geometry": {"coordinates":[-118.401994,34.021153],"type":"Point"}
}