{
  "type": "Feature",
  "properties": {
    "iso:country":"US",
    "sg:address":"29099 Hospital Rd # 204A",
    "sg:city":"Lake Arrowhead",
    "sg:classifiers":[
        {
            "category":"Health Services",
            "subcategory":"Doctor",
            "type":"Services"
        }
    ],
    "sg:phone":"+1 909 336 3670",
    "sg:postcode":"92352",
    "sg:province":"CA",
    "wof:name":"Dr. Martin Rocha Pediatrician",
    "wof:placetype":"venue"
},
  "geometry": {"coordinates":[-117.167001,34.265829],"type":"Point"}
}