{
  "type": "Feature",
  "properties": {
    "addr:full":"1709 Alcatraz Ave Berkeley CA 94703",
    "addr:housenumber":"1709",
    "addr:postcode":"94703",
    "addr:street":"Alcatraz Ave",
    "iso:country":"US",
    "sg:address":"1709 Alcatraz Ave",
    "sg:city":"Berkeley",
    "sg:classifiers":[
        {
            "category":"Organizations",
            "subcategory":"Religious Organization",
            "type":"Services"
        }
    ],
    "sg:phone":"+1 510 547 9936",
    "sg:postcode":"94703",
    "sg:province":"CA",
    "sg:tags":[
        "church"
    ],
    "wof:name":"Ephesian Church Of God",
    "wof:placetype":"venue"
},
  "geometry": {"coordinates":[-122.273275,37.84854],"type":"Point"}
}