{
  "type": "Feature",
  "properties": {
    "addr:full":"2228 Kenry Way S San Francisco CA 94080",
    "addr:housenumber":"2228",
    "addr:postcode":"94080",
    "addr:street":"Kenry Way S",
    "iso:country":"US",
    "sg:address":"2228 Kenry Way",
    "sg:city":"S San Francisco",
    "sg:classifiers":[
        {
            "category":"Wholesale",
            "subcategory":"Hardware",
            "type":"Manufacturing & Wholesale Goods"
        },
        {
            "category":"Manufacturing",
            "subcategory":"Metals",
            "type":"Manufacturing & Wholesale Goods"
        }
    ],
    "sg:phone":"+1 650 952 7710",
    "sg:postcode":"94080",
    "sg:province":"CA",
    "sg:tags":[
        "mfg",
        "tool",
        "supply",
        "locksmith",
        "equipment",
        "security"
    ],
    "sg:website":"www.strongarmdrills.com",
    "wof:name":"Strong Arm Security Inc",
    "wof:placetype":"venue"
},
  "geometry": {"coordinates":[-122.449365,37.640529],"type":"Point"}
}