{
  "type": "Feature",
  "properties": {
    "iso:country":"US",
    "sg:address":"646 University Ave",
    "sg:city":"San Diego",
    "sg:classifiers":[
        {
            "category":"Professional",
            "type":"Services"
        }
    ],
    "sg:phone":"+1 619 692 0100",
    "sg:postcode":"92103",
    "sg:province":"CA",
    "wof:name":"Capriottis",
    "wof:placetype":"venue"
},
  "geometry": {"coordinates":[-117.158873,32.748434],"type":"Point"}
}