{
  "type": "Feature",
  "properties": {
    "iso:country":"US",
    "sg:address":"273 Bellerose Dr",
    "sg:city":"San Jose",
    "sg:classifiers":[
        {
            "category":"Building & Trades",
            "subcategory":"Construction",
            "type":"Services"
        }
    ],
    "sg:phone":"+1 408 799 7929",
    "sg:postcode":"95128",
    "sg:province":"CA",
    "sg:tags":[
        "roofing"
    ],
    "wof:name":"A & R Roof Experts",
    "wof:placetype":"venue"
},
  "geometry": {"coordinates":[-121.936268,37.32389],"type":"Point"}
}