{
  "type": "Feature",
  "properties": {
    "addr:full":"3 Sandra Cir Chico CA 95926",
    "addr:housenumber":"3",
    "addr:postcode":"95926",
    "addr:street":"Sandra Cir",
    "iso:country":"US",
    "sg:address":"3 Sandra Cir",
    "sg:city":"Chico",
    "sg:classifiers":[
        {
            "category":"Bus Charters",
            "type":"Transportation"
        }
    ],
    "sg:phone":"+1 530 343 1047",
    "sg:postcode":"95926",
    "sg:province":"CA",
    "wof:name":"Charter Bus Service",
    "wof:placetype":"venue"
},
  "geometry": {"coordinates":[-121.832148,39.758326],"type":"Point"}
}