{
  "type": "Feature",
  "properties": {
    "addr:full":"8904 Revelstoke Way San Diego CA 92126",
    "addr:housenumber":"8904",
    "addr:postcode":"92126",
    "addr:street":"Revelstoke Way",
    "iso:country":"US",
    "sg:address":"8904 Revelstoke Way",
    "sg:city":"San Diego",
    "sg:classifiers":[
        {
            "category":"Health Services",
            "subcategory":"Nursing And Care Facility",
            "type":"Services"
        }
    ],
    "sg:phone":"+1 858 271 5353",
    "sg:postcode":"92126",
    "sg:province":"CA",
    "sg:tags":[
        "home",
        "retirement",
        "community"
    ],
    "wof:name":"Mira Mesa Manor",
    "wof:placetype":"venue"
},
  "geometry": {"coordinates":[-117.13128500000001,32.932702],"type":"Point"}
}