{
  "type": "Feature",
  "properties": {
    "iso:country":"US",
    "sg:address":"3248 E Florence Ave",
    "sg:city":"Huntington Park",
    "sg:classifiers":[
        {
            "category":"Insurance",
            "subcategory":"Insurance Agent",
            "type":"Services"
        }
    ],
    "sg:phone":"+1 323 582 0007",
    "sg:postcode":"90255",
    "sg:province":"CA",
    "sg:tags":[
        "consultant"
    ],
    "wof:name":"ANS Registration Svc",
    "wof:placetype":"venue"
},
  "geometry": {"coordinates":[-118.208266,33.972374],"type":"Point"}
}