{
  "type": "Feature",
  "properties": {
    "iso:country":"US",
    "sg:address":"4515 Central Ave",
    "sg:city":"Riverside",
    "sg:classifiers":[
        {
            "category":"Social Services",
            "type":"Services"
        }
    ],
    "sg:phone":"+1 951 682 8837",
    "sg:postcode":"92506",
    "sg:province":"CA",
    "sg:tags":[
        "counselor",
        "marriage",
        "family"
    ],
    "wof:name":"Annette G Compton",
    "wof:placetype":"venue"
},
  "geometry": {"coordinates":[-117.403441,33.953547],"type":"Point"}
}