{
  "type": "Feature",
  "properties": {
    "iso:country":"US",
    "sg:address":"612 W Duarte Rd",
    "sg:city":"Arcadia",
    "sg:classifiers":[
        {
            "category":"Health Services",
            "subcategory":"Doctor",
            "type":"Services"
        }
    ],
    "sg:phone":"+1 626 445 1853",
    "sg:postcode":"91007",
    "sg:province":"CA",
    "sg:tags":[
        "physician",
        "surgeon"
    ],
    "wof:name":"Michael G Perera Inc",
    "wof:placetype":"venue"
},
  "geometry": {"coordinates":[-118.05448,34.126069],"type":"Point"}
}