{
  "type": "Feature",
  "properties": {
    "addr:full":"2006 Dwight Way Berkeley CA 94704",
    "addr:housenumber":"2006",
    "addr:postcode":"94704",
    "addr:street":"Dwight Way",
    "iso:country":"US",
    "sg:address":"2006 Dwight Way",
    "sg:city":"Berkeley",
    "sg:classifiers":[
        {
            "category":"Health Services",
            "subcategory":"Doctor",
            "type":"Services"
        }
    ],
    "sg:phone":"+1 510 848 8700",
    "sg:postcode":"94704",
    "sg:province":"CA",
    "wof:name":"Hartog Joseph MD",
    "wof:placetype":"venue"
},
  "geometry": {"coordinates":[-122.26966299999999,37.863532],"type":"Point"}
}