{
  "type": "Feature",
  "properties": {
    "iso:country":"US",
    "sg:address":"2511 W Via Palma",
    "sg:city":"Anaheim",
    "sg:classifiers":[
        {
            "category":"Manufacturing",
            "subcategory":"Printing",
            "type":"Manufacturing & Wholesale Goods"
        }
    ],
    "sg:phone":"+1 714 827 2288",
    "sg:postcode":"92801",
    "sg:province":"CA",
    "sg:tags":[
        "commercial"
    ],
    "wof:name":"Tony Aco Co",
    "wof:placetype":"venue"
},
  "geometry": {"coordinates":[-117.975842,33.847943],"type":"Point"}
}