{
  "type": "Feature",
  "properties": {
    "iso:country":"US",
    "sg:address":"4745 Geary Boulevard",
    "sg:city":"San Francisco",
    "sg:classifiers":[
        {
            "category":"Real Estate",
            "subcategory":"Real Estate Services",
            "type":"Services"
        },
        {
            "category":"Building & Trades",
            "subcategory":"Construction",
            "type":"Services"
        }
    ],
    "sg:phone":"+1 415 668 5565",
    "sg:postcode":"94118",
    "sg:province":"CA",
    "sg:tags":[
        "management",
        "property",
        "contractor"
    ],
    "wof:name":"Epp Paul",
    "wof:placetype":"venue"
},
  "geometry": {"coordinates":[-122.47036,37.780609],"type":"Point"}
}