{
  "type": "Feature",
  "properties": {
    "addr:full":"501 Laughlin Way Redwood Valley CA 95470",
    "addr:housenumber":"501",
    "addr:postcode":"95470",
    "addr:street":"Laughlin Way",
    "iso:country":"US",
    "sg:address":"501 Laughlin Way",
    "sg:city":"Redwood Valley",
    "sg:classifiers":[
        {
            "category":"Building & Trades",
            "subcategory":"Construction",
            "type":"Services"
        }
    ],
    "sg:phone":"+1 707 485 1128",
    "sg:postcode":"95470",
    "sg:province":"CA",
    "sg:tags":[
        "fence",
        "contractor"
    ],
    "wof:name":"Arrow Fencing",
    "wof:placetype":"venue"
},
  "geometry": {"coordinates":[-123.22431899999999,39.281942],"type":"Point"}
}