{
  "type": "Feature",
  "properties": {
    "addr:full":"2063 Main St PMB 318 Oakley CA 94561",
    "addr:housenumber":"2063;318",
    "addr:postcode":"94561",
    "addr:street":"Main St",
    "iso:country":"US",
    "sg:address":"2063 Main St PMB 318",
    "sg:city":"Oakley",
    "sg:classifiers":[
        {
            "category":"Building & Trades",
            "subcategory":"Pest Control",
            "type":"Services"
        }
    ],
    "sg:phone":"+1 925 679 1210",
    "sg:postcode":"94561",
    "sg:province":"CA",
    "wof:name":"Rock N Roll Pest Control Inc",
    "wof:placetype":"venue"
},
  "geometry": {"coordinates":[-121.732697,38.003862],"type":"Point"}
}