{
  "type": "Feature",
  "properties": {
    "iso:country":"US",
    "sg:address":"7748 Silverado Trl",
    "sg:city":"Napa",
    "sg:classifiers":[
        {
            "category":"Retail",
            "subcategory":"Repair Shop",
            "type":"Services"
        }
    ],
    "sg:phone":"+1 707 944 1651",
    "sg:postcode":"94558",
    "sg:province":"CA",
    "sg:tags":[
        "tractor"
    ],
    "wof:name":"Dave's Repair",
    "wof:placetype":"venue"
},
  "geometry": {"coordinates":[-122.365921,38.458571],"type":"Point"}
}