{
  "type": "Feature",
  "properties": {
    "iso:country":"US",
    "sg:address":"5450 La Cuenta Dr",
    "sg:city":"San Diego",
    "sg:classifiers":[
        {
            "category":"Education",
            "subcategory":"School",
            "type":"Public Place"
        }
    ],
    "sg:phone":"+1 858 496 8255",
    "sg:postcode":"92124",
    "sg:province":"CA",
    "sg:tags":[
        "high",
        "middle",
        "elementary"
    ],
    "wof:name":"Tierrasanta Elementary School",
    "wof:placetype":"venue"
},
  "geometry": {"coordinates":[-117.096001,32.829399],"type":"Point"}
}