{
  "type": "Feature",
  "properties": {
    "addr:full":"9550 Occidental Rd Sebastopol CA 95472",
    "addr:housenumber":"9550",
    "addr:postcode":"95472",
    "addr:street":"Occidental Rd",
    "iso:country":"US",
    "sg:address":"9550 Occidental Rd",
    "sg:city":"Sebastopol",
    "sg:classifiers":[
        {
            "category":"Professional",
            "subcategory":"Engineering",
            "type":"Services"
        }
    ],
    "sg:phone":"+1 707 829 8337",
    "sg:postcode":"95472",
    "sg:province":"CA",
    "sg:tags":[
        "engineer",
        "contractor"
    ],
    "wof:name":"Hillside Specialist",
    "wof:placetype":"venue"
},
  "geometry": {"coordinates":[-122.868523,38.422162],"type":"Point"}
}