{
  "type": "Feature",
  "properties": {
    "addr:full":"16142 Main St Hesperia CA 92345",
    "addr:housenumber":"16142",
    "addr:postcode":"92345",
    "addr:street":"Main St",
    "iso:country":"US",
    "sg:address":"16142 Main St",
    "sg:city":"Hesperia",
    "sg:classifiers":[
        {
            "category":"Building & Trades",
            "subcategory":"Construction",
            "type":"Services"
        }
    ],
    "sg:phone":"+1 760 948 0908",
    "sg:postcode":"92345",
    "sg:province":"CA",
    "sg:tags":[
        "tile",
        "dealer"
    ],
    "wof:name":"New Impression Tile",
    "wof:placetype":"venue"
},
  "geometry": {"coordinates":[-117.310697,34.422979],"type":"Point"}
}