{
  "type": "Feature",
  "properties": {
    "addr:full":"2575 Burton Dr Cambria CA 93428",
    "addr:housenumber":"2575",
    "addr:postcode":"93428",
    "addr:street":"Burton Dr",
    "iso:country":"US",
    "sg:address":"2575 Burton Dr",
    "sg:city":"Cambria",
    "sg:classifiers":[
        {
            "category":"Building & Trades",
            "subcategory":"Construction",
            "type":"Services"
        }
    ],
    "sg:phone":"+1 805 924 1377",
    "sg:postcode":"93428",
    "sg:province":"CA",
    "sg:tags":[
        "handyman"
    ],
    "wof:name":"Garcia Handyman Svc",
    "wof:placetype":"venue"
},
  "geometry": {"coordinates":[-121.081851,35.554345],"type":"Point"}
}