{
  "type": "Feature",
  "properties": {
    "addr:full":"1609 S H St Bakersfield CA 93304",
    "addr:housenumber":"1609",
    "addr:postcode":"93304",
    "addr:street":"S H St",
    "iso:country":"US",
    "sg:address":"1609 S H St",
    "sg:city":"Bakersfield",
    "sg:classifiers":[
        {
            "category":"Shopping",
            "subcategory":"Bicycles & Sporting Goods",
            "type":"Retail Goods"
        }
    ],
    "sg:phone":"+1 661 833 3781",
    "sg:postcode":"93304",
    "sg:province":"CA",
    "sg:tags":[
        "equipment",
        "diver",
        "supply"
    ],
    "wof:name":"Captain Frog",
    "wof:placetype":"venue"
},
  "geometry": {"coordinates":[-119.021271,35.338625],"type":"Point"}
}