{
  "type": "Feature",
  "properties": {
    "addr:full":"11150 Ridge Rd Sutter Creek CA 95685",
    "addr:housenumber":"11150",
    "addr:postcode":"95685",
    "addr:street":"Ridge Rd",
    "iso:country":"US",
    "sg:address":"11150 Ridge Rd",
    "sg:city":"Sutter Creek",
    "sg:classifiers":[
        {
            "category":"Home & Garden",
            "subcategory":"Garden Supply",
            "type":"Retail Goods"
        }
    ],
    "sg:phone":"+1 209 223 2113",
    "sg:postcode":"95685",
    "sg:province":"CA",
    "sg:tags":[
        "nurseryman"
    ],
    "wof:name":"Amador Nursery & Design",
    "wof:placetype":"venue"
},
  "geometry": {"coordinates":[-120.810787,38.372572],"type":"Point"}
}