{
  "type": "Feature",
  "properties": {
    "addr:full":"16692 Cedar Cir Fountain Valley CA 92708",
    "addr:housenumber":"16692",
    "addr:postcode":"92708",
    "addr:street":"Cedar Cir",
    "iso:country":"US",
    "sg:address":"16692 Cedar Cir",
    "sg:city":"Fountain Valley",
    "sg:classifiers":[
        {
            "category":"Building & Trades",
            "subcategory":"Landscaping Services",
            "type":"Services"
        }
    ],
    "sg:phone":"+1 714 928 5882",
    "sg:postcode":"92708",
    "sg:province":"CA",
    "sg:tags":[
        "landscape"
    ],
    "wof:name":"Young & Jills Landscape",
    "wof:placetype":"venue"
},
  "geometry": {"coordinates":[-117.962037,33.720406],"type":"Point"}
}