{
  "type": "Feature",
  "properties": {
    "addr:full":"761 D St Arcata CA 95521",
    "addr:housenumber":"761",
    "addr:postcode":"95521",
    "addr:street":"D St",
    "iso:country":"US",
    "sg:address":"761 D St",
    "sg:city":"Arcata",
    "sg:classifiers":[
        {
            "category":"Food & Beverages",
            "subcategory":"Liquor & Beverages",
            "type":"Retail Goods"
        }
    ],
    "sg:phone":"+1 707 825 7596",
    "sg:postcode":"95521",
    "sg:province":"CA",
    "sg:tags":[
        "wine"
    ],
    "wof:name":"Libation",
    "wof:placetype":"venue"
},
  "geometry": {"coordinates":[-124.08262999999999,40.867547],"type":"Point"}
}