{
  "type": "Feature",
  "properties": {
    "iso:country":"US",
    "sg:address":"5635 Balboa Avenue",
    "sg:city":"San Diego",
    "sg:classifiers":[
        {
            "category":"Personal",
            "subcategory":"Shoe Repair & Shine",
            "type":"Services"
        }
    ],
    "sg:phone":"+1 858 495 0885",
    "sg:postcode":"92111",
    "sg:province":"CA",
    "wof:name":"Pro Shoe Repair",
    "wof:placetype":"venue"
},
  "geometry": {"coordinates":[-117.179326,32.820129],"type":"Point"}
}