{
  "type": "Feature",
  "properties": {
    "addr:full":"14731 Keswick St Van Nuys CA 91405",
    "addr:housenumber":"14731",
    "addr:postcode":"91405",
    "addr:street":"Keswick St",
    "iso:country":"US",
    "sg:address":"14731 Keswick St",
    "sg:city":"Van Nuys",
    "sg:classifiers":[
        {
            "category":"Restaurant",
            "type":"Food & Drink"
        }
    ],
    "sg:phone":"+1 818 909 4949",
    "sg:postcode":"91405",
    "sg:province":"CA",
    "sg:tags":[
        "caterer"
    ],
    "sg:website":"www.outbackcatering.com",
    "wof:name":"Outback Catering",
    "wof:placetype":"venue"
},
  "geometry": {"coordinates":[-118.454334,34.210342],"type":"Point"}
}