{
  "type": "Feature",
  "properties": {
    "addr:full":"1330 Churn Creek Rd Redding CA 96003",
    "addr:housenumber":"1330",
    "addr:postcode":"96003",
    "addr:street":"Churn Creek Rd",
    "iso:country":"US",
    "sg:address":"1330 Churn Creek Rd",
    "sg:city":"Redding",
    "sg:classifiers":[
        {
            "category":"Wholesale",
            "subcategory":"Scrap",
            "type":"Manufacturing & Wholesale Goods"
        }
    ],
    "sg:phone":"+1 530 224 1338",
    "sg:postcode":"96003",
    "sg:province":"CA",
    "sg:tags":[
        "recycling",
        "center"
    ],
    "wof:name":"Big Foot Recycling",
    "wof:placetype":"venue"
},
  "geometry": {"coordinates":[-122.350911,40.587798],"type":"Point"}
}