{
  "type": "Feature",
  "properties": {
    "iso:country":"US",
    "sg:address":"5475 Airport Way",
    "sg:city":"Stockton",
    "sg:classifiers":[
        {
            "category":"Freight",
            "type":"Transportation"
        }
    ],
    "sg:phone":"+1 209 983 8285",
    "sg:postcode":"95206",
    "sg:province":"CA",
    "sg:tags":[
        "trucking"
    ],
    "wof:name":"Con-Way Western Express",
    "wof:placetype":"venue"
},
  "geometry": {"coordinates":[-121.248784,37.886619],"type":"Point"}
}