{
  "type": "Feature",
  "properties": {
    "addr:full":"18646 Main St Hesperia CA 92345",
    "addr:housenumber":"18646",
    "addr:postcode":"92345",
    "addr:street":"Main St",
    "iso:country":"US",
    "sg:address":"18646 Main St",
    "sg:city":"Hesperia",
    "sg:classifiers":[
        {
            "category":"Building & Trades",
            "subcategory":"Construction",
            "type":"Services"
        }
    ],
    "sg:phone":"+1 760 244 8722",
    "sg:postcode":"92345",
    "sg:province":"CA",
    "sg:tags":[
        "home",
        "contractor",
        "general",
        "custom"
    ],
    "wof:name":"Desert Horizons",
    "wof:placetype":"venue"
},
  "geometry": {"coordinates":[-117.25628,34.414388],"type":"Point"}
}