{
  "type": "Feature",
  "properties": {
    "iso:country":"US",
    "sg:address":"23201 Lake Center Dr",
    "sg:city":"Lake Forest",
    "sg:classifiers":[
        {
            "category":"Real Estate",
            "subcategory":"Real Estate Agent",
            "type":"Services"
        }
    ],
    "sg:phone":"+1 949 470 3990",
    "sg:postcode":"92630",
    "sg:province":"CA",
    "wof:name":"California Brokers Network",
    "wof:placetype":"venue"
},
  "geometry": {"coordinates":[-117.71629299999999,33.625783],"type":"Point"}
}