{
  "type": "Feature",
  "properties": {
    "iso:country":"US",
    "sg:address":"3315 Kimber Dr #A",
    "sg:city":"Newbury Park",
    "sg:classifiers":[
        {
            "category":"Shopping",
            "subcategory":"Tobacco",
            "type":"Retail Goods"
        }
    ],
    "sg:phone":"+1 805 498 5059",
    "sg:postcode":"91320",
    "sg:province":"CA",
    "sg:tags":[
        "shop"
    ],
    "wof:name":"Tobacco Prince",
    "wof:placetype":"venue"
},
  "geometry": {"coordinates":[-118.94669500000001,34.176066],"type":"Point"}
}