{
  "type": "Feature",
  "properties": {
    "iso:country":"US",
    "sg:address":"3303 Ladrillo Aisle",
    "sg:city":"Irvine",
    "sg:classifiers":[
        {
            "category":"Communications",
            "type":"Services"
        }
    ],
    "sg:phone":"+1 949 451 6898",
    "sg:postcode":"92606",
    "sg:province":"CA",
    "sg:tags":[
        "communication"
    ],
    "wof:name":"X Precise Communications Corp",
    "wof:placetype":"venue"
},
  "geometry": {"coordinates":[-117.812079,33.687612],"type":"Point"}
}