{
  "type": "Feature",
  "properties": {
    "addr:full":"1038 N. Fairfax Ave. Los Angeles CA 90046",
    "addr:housenumber":"1038",
    "addr:postcode":"90046",
    "addr:street":"N. Fairfax Ave.",
    "iso:country":"US",
    "sg:address":"1038 N. Fairfax Ave.",
    "sg:city":"Los Angeles",
    "sg:classifiers":[
        {
            "category":"Shopping",
            "subcategory":"Thrift Store",
            "type":"Retail Goods"
        }
    ],
    "sg:phone":"+1 323 848 8613",
    "sg:postcode":"90046",
    "sg:province":"CA",
    "sg:website":"www.filthmart.net",
    "wof:name":"Filthmart",
    "wof:placetype":"venue"
},
  "geometry": {"coordinates":[-118.36116199999999,34.089855],"type":"Point"}
}