{
  "type": "Feature",
  "properties": {
    "iso:country":"US",
    "sg:address":"2285 Huntington Dr",
    "sg:city":"San Marino",
    "sg:classifiers":[
        {
            "category":"Real Estate",
            "subcategory":"Architect",
            "type":"Services"
        }
    ],
    "sg:phone":"+1 626 535 0882",
    "sg:postcode":"91108",
    "sg:province":"CA",
    "sg:website":"www.integrateddesigngroupinc.com",
    "wof:name":"Integrated Design Group Inc",
    "wof:placetype":"venue"
},
  "geometry": {"coordinates":[-118.10511099999999,34.122528],"type":"Point"}
}