{
  "type": "Feature",
  "properties": {
    "addr:full":"35745 82nd St E Littlerock CA 93543",
    "addr:housenumber":"35745",
    "addr:postcode":"littlerock ca 93543",
    "addr:street":"82Nd St E",
    "iso:country":"US",
    "sg:address":"35745 82nd St E",
    "sg:city":"Littlerock",
    "sg:classifiers":[
        {
            "category":"Farming",
            "subcategory":"Orchard",
            "type":"Manufacturing & Wholesale Goods"
        }
    ],
    "sg:phone":"+1 661 944 3913",
    "sg:postcode":"93543",
    "sg:province":"CA",
    "sg:tags":[
        "fruit",
        "tree"
    ],
    "wof:name":"Tenerelli Orchards",
    "wof:placetype":"venue"
},
  "geometry": {"coordinates":[-117.98377000000001,34.529537],"type":"Point"}
}