{
  "type": "Feature",
  "properties": {
    "addr:full":"1 Niles St Bakersfield CA 93305",
    "addr:housenumber":"1",
    "addr:postcode":"93305",
    "addr:street":"Niles St",
    "iso:country":"US",
    "sg:address":"1 Niles St",
    "sg:city":"Bakersfield",
    "sg:classifiers":[
        {
            "category":"Organizations",
            "subcategory":"Religious Organization",
            "type":"Services"
        }
    ],
    "sg:phone":"+1 661 634 0109",
    "sg:postcode":"93305",
    "sg:province":"CA",
    "sg:tags":[
        "church"
    ],
    "wof:name":"Iglesia Nuevo Comienso En Crst",
    "wof:placetype":"venue"
},
  "geometry": {"coordinates":[-119.00176,35.383958],"type":"Point"}
}