{
  "type": "Feature",
  "properties": {
    "iso:country":"US",
    "sg:address":"860 E Remington Dr Ste J",
    "sg:city":"Sunnyvale",
    "sg:classifiers":[
        {
            "category":"Health Services",
            "subcategory":"Doctor",
            "type":"Services"
        },
        {
            "category":"Health Services",
            "subcategory":"Dentist",
            "type":"Services"
        }
    ],
    "sg:phone":"+1 408 736 6266",
    "sg:postcode":"94087",
    "sg:province":"CA",
    "wof:name":"Rabanus Jorg-Peter DMD PHD",
    "wof:placetype":"venue"
},
  "geometry": {"coordinates":[-122.025002,37.361],"type":"Point"}
}