{
  "type": "Feature",
  "properties": {
    "addr:full":"5737 Thornhill Dr Ste 207B Oakland CA 94611",
    "addr:housenumber":"5737",
    "addr:postcode":"94611",
    "addr:street":"Thornhill Dr Ste 207B",
    "iso:country":"US",
    "sg:address":"5737 Thornhill Dr Ste 207B",
    "sg:city":"Oakland",
    "sg:classifiers":[
        {
            "category":"Health Services",
            "subcategory":"Clinic",
            "type":"Services"
        }
    ],
    "sg:phone":"+1 510 903 9296",
    "sg:postcode":"94611",
    "sg:province":"CA",
    "sg:tags":[
        "counseling",
        "mental"
    ],
    "wof:name":"Simple Family Health",
    "wof:placetype":"venue"
},
  "geometry": {"coordinates":[-122.21243800000001,37.834646],"type":"Point"}
}