{
  "type": "Feature",
  "properties": {
    "iso:country":"US",
    "sg:address":"1600 Oak Ridge Way",
    "sg:city":"Auburn",
    "sg:classifiers":[
        {
            "category":"Professional",
            "type":"Services"
        }
    ],
    "sg:phone":"+1 530 889 8965",
    "sg:postcode":"95603",
    "sg:province":"CA",
    "wof:name":"Sanle Power Devices Inc",
    "wof:placetype":"venue"
},
  "geometry": {"coordinates":[-121.07468,38.936057],"type":"Point"}
}