{
  "type": "Feature",
  "properties": {
    "iso:country":"US",
    "sg:address":"4001 State St",
    "sg:city":"Santa Barbara",
    "sg:classifiers":[
        {
            "category":"Freight",
            "type":"Transportation"
        }
    ],
    "sg:phone":"+1 805 453 7711",
    "sg:postcode":"93110",
    "sg:province":"CA",
    "sg:tags":[
        "commercial",
        "storage"
    ],
    "wof:name":"Absolute Self Storage",
    "wof:placetype":"venue"
},
  "geometry": {"coordinates":[-119.757115,34.440188],"type":"Point"}
}