{
  "type": "Feature",
  "properties": {
    "iso:country":"US",
    "sg:address":"27887 Holland Rd",
    "sg:city":"Menifee",
    "sg:classifiers":[
        {
            "category":"Retail",
            "subcategory":"Storage",
            "type":"Services"
        }
    ],
    "sg:phone":"+1 951 301 1082",
    "sg:postcode":"92584",
    "sg:province":"CA",
    "sg:tags":[
        "self"
    ],
    "sg:website":"www.stratprop.com",
    "wof:name":"Menifee Self Storage",
    "wof:placetype":"venue"
},
  "geometry": {"coordinates":[-117.174521,33.669561],"type":"Point"}
}