{
  "type": "Feature",
  "properties": {
    "iso:country":"US",
    "sg:address":"7108 Crenshaw Blvd",
    "sg:city":"Los Angeles",
    "sg:classifiers":[
        {
            "category":"Wholesale",
            "subcategory":"Meat",
            "type":"Manufacturing & Wholesale Goods"
        }
    ],
    "sg:phone":"+1 323 751 1327",
    "sg:postcode":"90043",
    "sg:province":"CA",
    "sg:tags":[
        "plant",
        "packing"
    ],
    "wof:name":"Best Buy Meat",
    "wof:placetype":"venue"
},
  "geometry": {"coordinates":[-118.330806,33.974618],"type":"Point"}
}