{
  "type": "Feature",
  "properties": {
    "iso:country":"US",
    "sg:address":"4351 Davis St",
    "sg:city":"Santa Clara",
    "sg:classifiers":[
        {
            "category":"Shopping",
            "subcategory":"Catalog Store",
            "type":"Retail Goods"
        }
    ],
    "sg:phone":"+1 408 988 4527",
    "sg:postcode":"95054",
    "sg:province":"CA",
    "sg:tags":[
        "mail",
        "house"
    ],
    "wof:name":"Capitola Seashells",
    "wof:placetype":"venue"
},
  "geometry": {"coordinates":[-121.960398,37.395043],"type":"Point"}
}