{
  "type": "Feature",
  "properties": {
    "addr:full":"8270 Petaluma Hill Rd Penngrove CA 94951",
    "addr:housenumber":"8270",
    "addr:postcode":"94951",
    "addr:street":"Petaluma Hill Rd",
    "iso:country":"US",
    "sg:address":"8270 Petaluma Hill Rd",
    "sg:city":"Penngrove",
    "sg:classifiers":[
        {
            "category":"Wholesale",
            "subcategory":"Plants",
            "type":"Manufacturing & Wholesale Goods"
        }
    ],
    "sg:phone":"+1 707 792 2674",
    "sg:postcode":"94951",
    "sg:province":"CA",
    "sg:tags":[
        "florist"
    ],
    "wof:name":"Passanisi Nursery",
    "wof:placetype":"venue"
},
  "geometry": {"coordinates":[-122.666473,38.310061],"type":"Point"}
}