{
  "type": "Feature",
  "properties": {
    "iso:country":"US",
    "sg:address":"11516 Oakcrest Ave",
    "sg:city":"Ojai",
    "sg:classifiers":[
        {
            "category":"Personal",
            "subcategory":"Beauty Salon",
            "type":"Services"
        }
    ],
    "sg:phone":"+1 805 649 1189",
    "sg:postcode":"93023",
    "sg:province":"CA",
    "wof:name":"Diane's Studio Of Electrology",
    "wof:placetype":"venue"
},
  "geometry": {"coordinates":[-119.295635,34.41772],"type":"Point"}
}