{
  "type": "Feature",
  "properties": {
    "addr:full":"3775 Northgate Blvd Sacramento CA 95834",
    "addr:housenumber":"3775",
    "addr:postcode":"95834",
    "addr:street":"Northgate Blvd",
    "iso:country":"US",
    "sg:address":"3775 Northgate Blvd",
    "sg:city":"Sacramento",
    "sg:classifiers":[
        {
            "category":"Professional",
            "subcategory":"Computer Services",
            "type":"Services"
        }
    ],
    "sg:phone":"+1 916 567 2165",
    "sg:postcode":"95834",
    "sg:province":"CA",
    "sg:tags":[
        "design",
        "system"
    ],
    "wof:name":"IBM",
    "wof:placetype":"venue"
},
  "geometry": {"coordinates":[-121.47561899999999,38.635299],"type":"Point"}
}