{
  "type": "Feature",
  "properties": {
    "addr:full":"485 N Tustin St Orange CA 92867",
    "addr:housenumber":"485",
    "addr:postcode":"92867",
    "addr:street":"N Tustin St",
    "iso:country":"US",
    "sg:address":"485 N Tustin St",
    "sg:city":"Orange",
    "sg:classifiers":[
        {
            "category":"Shopping",
            "subcategory":"Discount & Variety Stores",
            "type":"Retail Goods"
        },
        {
            "category":"Shopping",
            "subcategory":"Shoes",
            "type":"Retail Goods"
        }
    ],
    "sg:phone":"+1 714 532 3068",
    "sg:postcode":"92867",
    "sg:province":"CA",
    "sg:tags":[
        "outlet"
    ],
    "sg:website":"www.vans.com",
    "wof:name":"Vans Outlet Store",
    "wof:placetype":"venue"
},
  "geometry": {"coordinates":[-117.83565299999999,33.794714],"type":"Point"}
}