{
  "type": "Feature",
  "properties": {
    "iso:country":"US",
    "sg:address":"2901 Nutwood Ave Apt C11",
    "sg:city":"Fullerton",
    "sg:classifiers":[
        {
            "category":"Real Estate",
            "subcategory":"Real Estate Operator",
            "type":"Services"
        }
    ],
    "sg:phone":"+1 714 524 2901",
    "sg:postcode":"92831",
    "sg:province":"CA",
    "sg:tags":[
        "apartment"
    ],
    "wof:name":"Moonraker Apartments",
    "wof:placetype":"venue"
},
  "geometry": {"coordinates":[-117.878998,33.878201],"type":"Point"}
}