{
  "type": "Feature",
  "properties": {
    "addr:full":"24432 Muirlands Blvd Lake Forest CA 92630",
    "addr:housenumber":"24432",
    "addr:postcode":"92630",
    "addr:street":"Muirlands Blvd",
    "iso:country":"US",
    "sg:address":"24432 Muirlands Blvd",
    "sg:city":"Lake Forest",
    "sg:classifiers":[
        {
            "category":"Health Services",
            "subcategory":"Doctor",
            "type":"Services"
        }
    ],
    "sg:phone":"+1 949 770 8115",
    "sg:postcode":"92630",
    "sg:province":"CA",
    "sg:tags":[
        "dermatologist"
    ],
    "wof:name":"KHOURY JANE G MD",
    "wof:placetype":"venue"
},
  "geometry": {"coordinates":[-117.703277,33.627694],"type":"Point"}
}