{
  "type": "Feature",
  "properties": {
    "iso:country":"US",
    "sg:address":"17052 Slover Ave",
    "sg:city":"Fontana",
    "sg:classifiers":[
        {
            "category":"Personal",
            "type":"Services"
        }
    ],
    "sg:phone":"+1 909 349 2000",
    "sg:postcode":"92337",
    "sg:province":"CA",
    "sg:tags":[
        "wear",
        "formal"
    ],
    "wof:name":"Friar Tux Shop",
    "wof:placetype":"venue"
},
  "geometry": {"coordinates":[-117.434417,34.063106],"type":"Point"}
}