{
  "type": "Feature",
  "properties": {
    "iso:country":"US",
    "sg:address":"2420 Grass Valley Hwy",
    "sg:city":"Auburn",
    "sg:classifiers":[
        {
            "category":"Retail",
            "subcategory":"Laundry & Dry Cleaning",
            "type":"Services"
        }
    ],
    "sg:phone":"+1 530 885 8522",
    "sg:postcode":"95603",
    "sg:province":"CA",
    "sg:tags":[
        "cleaners"
    ],
    "wof:name":"One Stop 49 Cleaners",
    "wof:placetype":"venue"
},
  "geometry": {"coordinates":[-121.09462600000001,38.936761],"type":"Point"}
}