{
  "type": "Feature",
  "properties": {
    "iso:country":"US",
    "sg:address":"1901 Watt Ave Ste 2",
    "sg:city":"Sacramento",
    "sg:classifiers":[
        {
            "category":"Health Services",
            "subcategory":"Dentist",
            "type":"Services"
        }
    ],
    "sg:phone":"+1 916 483 5677",
    "sg:postcode":"95825",
    "sg:province":"CA",
    "wof:name":"Varshawsky Brent J DMD Inc",
    "wof:placetype":"venue"
},
  "geometry": {"coordinates":[-121.383003,38.598999],"type":"Point"}
}