{
  "type": "Feature",
  "properties": {
    "addr:full":"1320 Industrial Ave Petaluma CA 94952",
    "addr:housenumber":"1320",
    "addr:postcode":"94952",
    "addr:street":"Industrial Ave",
    "iso:country":"US",
    "sg:address":"1320 Industrial Ave",
    "sg:city":"Petaluma",
    "sg:classifiers":[
        {
            "category":"Building & Trades",
            "subcategory":"Cleaning & Sanitation",
            "type":"Services"
        },
        {
            "category":"Personal",
            "type":"Services"
        }
    ],
    "sg:phone":"+1 707 769 0770",
    "sg:postcode":"94952",
    "sg:province":"CA",
    "sg:tags":[
        "maids'",
        "house",
        "contractor",
        "cleaning-industrial",
        "butlers'",
        "cleaners-interior"
    ],
    "sg:website":"http://www.mollymaid.com/ca/southern-sonoma-county",
    "wof:name":"Molly Maid",
    "wof:placetype":"venue"
},
  "geometry": {"coordinates":[-122.667266,38.267105],"type":"Point"}
}