{
  "type": "Feature",
  "properties": {
    "addr:full":"898 N Sepulveda Blvd El Segundo CA 90245",
    "addr:housenumber":"898",
    "addr:postcode":"90245",
    "addr:street":"N Sepulveda Blvd",
    "iso:country":"US",
    "sg:address":"898 N Sepulveda Blvd",
    "sg:city":"El Segundo",
    "sg:classifiers":[
        {
            "category":"Professional",
            "subcategory":"Advertising",
            "type":"Services"
        }
    ],
    "sg:phone":"+1 310 321 5200",
    "sg:postcode":"90245",
    "sg:province":"CA",
    "sg:tags":[
        "counselor"
    ],
    "sg:website":"www.siltanenpartners.com",
    "wof:name":"Siltanen & Partners",
    "wof:placetype":"venue"
},
  "geometry": {"coordinates":[-118.39627299999999,33.928036],"type":"Point"}
}