{
  "type": "Feature",
  "properties": {
    "addr:full":"2261 Valko Ave Sacramento CA 95822",
    "addr:housenumber":"2261",
    "addr:postcode":"95822",
    "addr:street":"Valko Ave",
    "iso:country":"US",
    "sg:address":"2261 Valko Ave",
    "sg:city":"Sacramento",
    "sg:classifiers":[
        {
            "category":"Building & Trades",
            "subcategory":"Cleaning & Sanitation",
            "type":"Services"
        }
    ],
    "sg:phone":"+1 916 470 3255",
    "sg:postcode":"95822",
    "sg:province":"CA",
    "sg:tags":[
        "janitor"
    ],
    "wof:name":"Ajays Janitorial",
    "wof:placetype":"venue"
},
  "geometry": {"coordinates":[-121.48633,38.485673],"type":"Point"}
}