{
  "type": "Feature",
  "properties": {
    "iso:country":"US",
    "sg:address":"15929 Gard Ave",
    "sg:city":"Norwalk",
    "sg:classifiers":[
        {
            "category":"Real Estate",
            "subcategory":"Real Estate Operator",
            "type":"Services"
        }
    ],
    "sg:phone":"+1 562 865 8500",
    "sg:postcode":"90650",
    "sg:province":"CA",
    "sg:tags":[
        "apartment"
    ],
    "wof:name":"Park Apartments",
    "wof:placetype":"venue"
},
  "geometry": {"coordinates":[-118.08899700000001,33.887299],"type":"Point"}
}