{
  "type": "Feature",
  "properties": {
    "addr:full":"9526 Oak Grove Dr Descanso CA 91916",
    "addr:housenumber":"9526",
    "addr:postcode":"91916",
    "addr:street":"Oak Grove Dr",
    "iso:country":"US",
    "sg:address":"9526 Oak Grove Dr",
    "sg:city":"Descanso",
    "sg:classifiers":[
        {
            "category":"Freight",
            "type":"Transportation"
        }
    ],
    "sg:phone":"+1 619 445 0390",
    "sg:postcode":"91916",
    "sg:province":"CA",
    "sg:tags":[
        "operator",
        "local",
        "trucking"
    ],
    "wof:name":"R Rocking Trucking Inc",
    "wof:placetype":"venue"
},
  "geometry": {"coordinates":[-116.616173,32.857006],"type":"Point"}
}