{
  "type": "Feature",
  "properties": {
    "addr:full":"23422 Mill Creek Dr Laguna Hills CA 92653",
    "addr:housenumber":"23422",
    "addr:postcode":"92653",
    "addr:street":"Mill Creek Dr",
    "iso:country":"US",
    "sg:address":"23422 Mill Creek Dr",
    "sg:city":"Laguna Hills",
    "sg:classifiers":[
        {
            "category":"Professional",
            "subcategory":"Lawyer & Legal Services",
            "type":"Services"
        }
    ],
    "sg:phone":"+1 949 588 5944",
    "sg:postcode":"92653",
    "sg:province":"CA",
    "sg:tags":[
        "attorney"
    ],
    "wof:name":"Jacobs & Jacobs",
    "wof:placetype":"venue"
},
  "geometry": {"coordinates":[-117.73354500000001,33.630253],"type":"Point"}
}