{
  "type": "Feature",
  "properties": {
    "iso:country":"US",
    "sg:address":"3620 American River Dr",
    "sg:city":"Sacramento",
    "sg:classifiers":[
        {
            "category":"Professional",
            "subcategory":"Lawyer & Legal Services",
            "type":"Services"
        }
    ],
    "sg:phone":"+1 916 484 3844",
    "sg:postcode":"95864",
    "sg:province":"CA",
    "sg:tags":[
        "attorney"
    ],
    "sg:website":"www.binnslaw.com",
    "wof:name":"Robert J Binns",
    "wof:placetype":"venue"
},
  "geometry": {"coordinates":[-121.380825,38.570037],"type":"Point"}
}