{
  "type": "Feature",
  "properties": {
    "addr:full":"998 The Alameda San Jose CA 95126",
    "addr:housenumber":"998",
    "addr:postcode":"95126",
    "addr:street":"The Alameda",
    "iso:country":"US",
    "sg:address":"998 The Alameda",
    "sg:city":"San Jose",
    "sg:classifiers":[
        {
            "category":"Personal",
            "subcategory":"Hair Removal",
            "type":"Services"
        },
        {
            "category":"Personal",
            "subcategory":"Nail Salon",
            "type":"Services"
        }
    ],
    "sg:phone":"+1 408 642 1015",
    "sg:postcode":"95126",
    "sg:province":"CA",
    "sg:website":"www.bonvivantnails.com",
    "wof:name":"Bon Vivant Nails",
    "wof:placetype":"venue"
},
  "geometry": {"coordinates":[-121.909156,37.331575],"type":"Point"}
}