{
  "type": "Feature",
  "properties": {
    "addr:full":"2637 Rosemead Blvd South El Monte CA 91733",
    "addr:housenumber":"2637",
    "addr:postcode":"91733",
    "addr:street":"Rosemead Blvd",
    "iso:country":"US",
    "sg:address":"2637 Rosemead Blvd",
    "sg:city":"South El Monte",
    "sg:classifiers":[
        {
            "category":"Retail",
            "subcategory":"Auto Repair",
            "type":"Services"
        }
    ],
    "sg:phone":"+1 626 401 2887",
    "sg:postcode":"91733",
    "sg:province":"CA",
    "sg:tags":[
        "body",
        "shop"
    ],
    "wof:name":"Superior Pv Auto Body Shop",
    "wof:placetype":"venue"
},
  "geometry": {"coordinates":[-118.06500200000001,34.060699],"type":"Point"}
}