{
  "type": "Feature",
  "properties": {
    "addr:full":"1601 Esplanade Chico CA 95926",
    "addr:housenumber":"1601",
    "addr:postcode":"95926",
    "addr:street":"Esplanade Chico",
    "iso:country":"US",
    "sg:address":"1601 Esplanade",
    "sg:city":"Chico",
    "sg:classifiers":[
        {
            "category":"Health Services",
            "subcategory":"Doctor",
            "type":"Services"
        }
    ],
    "sg:phone":"+1 530 343 5006",
    "sg:postcode":"95926",
    "sg:province":"CA",
    "sg:tags":[
        "physician",
        "surgeon"
    ],
    "wof:name":"Cardiovascular Consultants",
    "wof:placetype":"venue"
},
  "geometry": {"coordinates":[-121.850258,39.744138],"type":"Point"}
}