{
  "type": "Feature",
  "properties": {
    "iso:country":"US",
    "sg:address":"310 8th St",
    "sg:city":"Oakland",
    "sg:classifiers":[
        {
            "category":"Health Services",
            "subcategory":"Health Practitioner",
            "type":"Services"
        }
    ],
    "sg:phone":"+1 510 268 0222",
    "sg:postcode":"94607",
    "sg:province":"CA",
    "sg:tags":[
        "therapist",
        "physical"
    ],
    "wof:name":"Asian Network Physical Therapy",
    "wof:placetype":"venue"
},
  "geometry": {"coordinates":[-122.271123,37.79923],"type":"Point"}
}