{
  "type": "Feature",
  "properties": {
    "iso:country":"US",
    "sg:address":"208 N 10th St",
    "sg:city":"Montebello",
    "sg:classifiers":[
        {
            "category":"Wholesale",
            "subcategory":"Non-durable Goods",
            "type":"Manufacturing & Wholesale Goods"
        }
    ],
    "sg:phone":"+1 323 727 9896",
    "sg:postcode":"90640",
    "sg:province":"CA",
    "wof:name":"Yolanda Robles & Co",
    "wof:placetype":"venue"
},
  "geometry": {"coordinates":[-118.109956,34.01311],"type":"Point"}
}