{
  "type": "Feature",
  "properties": {
    "iso:country":"US",
    "sg:address":"4000 Fruitvale Ave",
    "sg:city":"Bakersfield",
    "sg:classifiers":[
        {
            "category":"Building & Trades",
            "subcategory":"Plumbing",
            "type":"Services"
        }
    ],
    "sg:phone":"+1 661 836 3880",
    "sg:postcode":"93308",
    "sg:province":"CA",
    "sg:tags":[
        "system",
        "cooling",
        "contractor",
        "geothermal",
        "heating",
        "air conditioning"
    ],
    "sg:website":"www.blandac.com",
    "wof:name":"Bland Air Conditioning",
    "wof:placetype":"venue"
},
  "geometry": {"coordinates":[-119.074387,35.39653],"type":"Point"}
}