{
  "type": "Feature",
  "properties": {
    "addr:full":"3425 S Bascom Avenue Campbell CA 95008",
    "addr:housenumber":"3425",
    "addr:postcode":"95008",
    "addr:street":"S Bascom Avenue",
    "iso:country":"US",
    "sg:address":"3425 S Bascom Avenue",
    "sg:city":"Campbell",
    "sg:classifiers":[
        {
            "category":"Professional",
            "subcategory":"Lawyer & Legal Services",
            "type":"Services"
        }
    ],
    "sg:phone":"+1 408 356 9200",
    "sg:postcode":"95008",
    "sg:province":"CA",
    "sg:website":"www.attorneyoffice.com",
    "wof:name":"Law Office of Roy Litherland",
    "wof:placetype":"venue"
},
  "geometry": {"coordinates":[-121.943719,37.263357],"type":"Point"}
}