{
  "type": "Feature",
  "properties": {
    "iso:country":"US",
    "sg:address":"1335 N Hulbert Ave",
    "sg:city":"Fresno",
    "sg:classifiers":[
        {
            "category":"Education",
            "subcategory":"Vocational School",
            "type":"Public Place"
        }
    ],
    "sg:phone":"+1 559 266 0273",
    "sg:postcode":"93728",
    "sg:province":"CA",
    "wof:name":"Carpenters 46 Northern Ca",
    "wof:placetype":"venue"
},
  "geometry": {"coordinates":[-119.83381,36.759649],"type":"Point"}
}