{
  "type": "Feature",
  "properties": {
    "iso:country":"US",
    "sg:address":"14365 Pipeline Ave",
    "sg:city":"Chino",
    "sg:classifiers":[
        {
            "category":"Health Services",
            "subcategory":"Doctor",
            "type":"Services"
        }
    ],
    "sg:phone":"+1 909 591 5587",
    "sg:postcode":"91710",
    "sg:province":"CA",
    "sg:tags":[
        "medical",
        "imaging"
    ],
    "wof:name":"Spectrum Mri",
    "wof:placetype":"venue"
},
  "geometry": {"coordinates":[-117.71507,33.995144],"type":"Point"}
}