{
  "type": "Feature",
  "properties": {
    "iso:country":"US",
    "sg:address":"19360 Rinaldi St",
    "sg:city":"Northridge",
    "sg:classifiers":[
        {
            "category":"Banks & Credit Unions",
            "subcategory":"Financial Services",
            "type":"Services"
        }
    ],
    "sg:phone":"+1 310 877 7740",
    "sg:postcode":"91326",
    "sg:province":"CA",
    "sg:tags":[
        "investor"
    ],
    "wof:name":"Axiom Realty & Investments",
    "wof:placetype":"venue"
},
  "geometry": {"coordinates":[-118.555502,34.274795],"type":"Point"}
}