{
  "type": "Feature",
  "properties": {
    "addr:full":"13745 Seminole Dr Chino CA 91710",
    "addr:housenumber":"13745",
    "addr:postcode":"91710",
    "addr:street":"Seminole Dr",
    "iso:country":"US",
    "sg:address":"13745 Seminole Dr",
    "sg:city":"Chino",
    "sg:classifiers":[
        {
            "category":"Building & Trades",
            "subcategory":"Construction",
            "type":"Services"
        }
    ],
    "sg:phone":"+1 909 627 3651",
    "sg:postcode":"91710",
    "sg:province":"CA",
    "sg:tags":[
        "specializing",
        "general",
        "contractor"
    ],
    "wof:name":"Bergman Companies  The",
    "wof:placetype":"venue"
},
  "geometry": {"coordinates":[-117.69999,34.003846],"type":"Point"}
}