{
  "type": "Feature",
  "properties": {
    "addr:full":"2360 University Ave San Diego CA 92104",
    "addr:housenumber":"2360",
    "addr:postcode":"92104",
    "addr:street":"University Ave",
    "iso:country":"US",
    "sg:address":"2360 University Ave",
    "sg:city":"San Diego",
    "sg:classifiers":[
        {
            "category":"Food & Beverages",
            "subcategory":"Bakery",
            "type":"Retail Goods"
        }
    ],
    "sg:phone":"+1 619 298 2352",
    "sg:postcode":"92104",
    "sg:province":"CA",
    "sg:tags":[
        "doughnut"
    ],
    "wof:name":"Golden Donut",
    "wof:placetype":"venue"
},
  "geometry": {"coordinates":[-117.138987,32.748521],"type":"Point"}
}