{
  "type": "Feature",
  "properties": {
    "addr:full":"880 E Fremont Ave Sunnyvale CA 94087",
    "addr:housenumber":"880",
    "addr:postcode":"94087",
    "addr:street":"E Fremont Ave",
    "iso:country":"US",
    "sg:address":"880 E Fremont Ave",
    "sg:city":"Sunnyvale",
    "sg:classifiers":[
        {
            "category":"Professional",
            "type":"Services"
        }
    ],
    "sg:phone":"+1 408 737 1144",
    "sg:postcode":"94087",
    "sg:province":"CA",
    "sg:tags":[
        "establishment"
    ],
    "wof:name":"Flagstone Inc",
    "wof:placetype":"venue"
},
  "geometry": {"coordinates":[-122.014151,37.352015],"type":"Point"}
}