{
  "type": "Feature",
  "properties": {
    "iso:country":"US",
    "sg:address":"2170 Vista Way",
    "sg:city":"Oceanside",
    "sg:classifiers":[
        {
            "category":"Shopping",
            "subcategory":"Pharmacy",
            "type":"Retail Goods"
        }
    ],
    "sg:phone":"+1 760 757 8887",
    "sg:postcode":"92054",
    "sg:province":"CA",
    "sg:tags":[
        "drugstore"
    ],
    "wof:name":"Super Rx Pharmacy",
    "wof:placetype":"venue"
},
  "geometry": {"coordinates":[-117.337997,33.182899],"type":"Point"}
}