{
  "type": "Feature",
  "properties": {
    "addr:full":"88 Tully Rd Ste 107 San Jose CA 95111",
    "addr:housenumber":"88",
    "addr:postcode":"95111",
    "addr:street":"Tully Rd Ste 107",
    "iso:country":"US",
    "sg:address":"88 Tully Rd Ste 107",
    "sg:city":"San Jose",
    "sg:classifiers":[
        {
            "category":"Health Services",
            "subcategory":"Clinic",
            "type":"Services"
        }
    ],
    "sg:phone":"+1 408 409 4422",
    "sg:postcode":"95111",
    "sg:province":"CA",
    "sg:tags":[
        "cannabis"
    ],
    "sg:website":"www.hhccoop.org",
    "wof:name":"Holistic Health Care",
    "wof:placetype":"venue"
},
  "geometry": {"coordinates":[-121.85874,37.303737],"type":"Point"}
}