{
  "type": "Feature",
  "properties": {
    "addr:full":"2820 College Ave Berkeley CA 94705",
    "addr:housenumber":"2820",
    "addr:postcode":"94705",
    "addr:street":"College Ave",
    "iso:country":"US",
    "sg:address":"2820 College Ave",
    "sg:city":"Berkeley",
    "sg:classifiers":[
        {
            "category":"Health Services",
            "subcategory":"Health Practitioner",
            "type":"Services"
        }
    ],
    "sg:phone":"+1 510 883 0776",
    "sg:postcode":"94705",
    "sg:province":"CA",
    "sg:tags":[
        "psychologist"
    ],
    "wof:name":"Roxanne Morse PHD",
    "wof:placetype":"venue"
},
  "geometry": {"coordinates":[-122.253328,37.858768],"type":"Point"}
}