{
  "type": "Feature",
  "properties": {
    "iso:country":"US",
    "sg:address":"694 Pleasant Valley Rd",
    "sg:city":"Diamond Springs",
    "sg:classifiers":[
        {
            "category":"Restaurant",
            "type":"Food & Drink"
        }
    ],
    "sg:phone":"+1 530 295 8356",
    "sg:postcode":"95619",
    "sg:province":"CA",
    "wof:name":"Colina De Oro Mexican Rstrnt",
    "wof:placetype":"venue"
},
  "geometry": {"coordinates":[-120.80899700000001,38.695525],"type":"Point"}
}