{
  "type": "Feature",
  "properties": {
    "addr:full":"610 Tennessee St Redlands CA 92374",
    "addr:housenumber":"610",
    "addr:postcode":"92374",
    "addr:street":"Tennessee St",
    "iso:country":"US",
    "sg:address":"610 Tennessee St",
    "sg:city":"Redlands",
    "sg:classifiers":[
        {
            "category":"Autos & Motor Vehicles",
            "subcategory":"Auto Supplies",
            "type":"Retail Goods"
        }
    ],
    "sg:phone":"+1 909 793 0212",
    "sg:postcode":"92374",
    "sg:province":"CA",
    "sg:tags":[
        "automobile",
        "parts"
    ],
    "wof:name":"Unique Auto Dune Buggy Supply",
    "wof:placetype":"venue"
},
  "geometry": {"coordinates":[-117.200073,34.062523],"type":"Point"}
}