{
  "type": "Feature",
  "properties": {
    "iso:country":"US",
    "sg:address":"2345 N Glassell St",
    "sg:city":"Orange",
    "sg:classifiers":[
        {
            "category":"Wholesale",
            "subcategory":"Furniture",
            "type":"Manufacturing & Wholesale Goods"
        }
    ],
    "sg:phone":"+1 714 282 5722",
    "sg:postcode":"92865",
    "sg:province":"CA",
    "wof:name":"Interior Specialist California",
    "wof:placetype":"venue"
},
  "geometry": {"coordinates":[-117.852942,33.828679],"type":"Point"}
}