{
  "type": "Feature",
  "properties": {
    "addr:full":"529 Center St Manteca CA 95336",
    "addr:housenumber":"529",
    "addr:postcode":"95336",
    "addr:street":"Center St",
    "iso:country":"US",
    "sg:address":"529 Center St",
    "sg:city":"Manteca",
    "sg:classifiers":[
        {
            "category":"Health Services",
            "subcategory":"Doctor",
            "type":"Services"
        }
    ],
    "sg:phone":"+1 209 239 4670",
    "sg:postcode":"95336",
    "sg:province":"CA",
    "sg:tags":[
        "dentist"
    ],
    "wof:name":"Valley Hill Dental Group",
    "wof:placetype":"venue"
},
  "geometry": {"coordinates":[-121.221716,37.799184],"type":"Point"}
}