{
  "type": "Feature",
  "properties": {
    "addr:full":"10 Inverness Way Inverness CA 94937",
    "addr:housenumber":"10",
    "addr:postcode":"94937",
    "addr:street":"Inverness Way",
    "iso:country":"US",
    "sg:address":"10 Inverness Way",
    "sg:city":"Inverness",
    "sg:classifiers":[
        {
            "category":"Travel",
            "subcategory":"Hotels & Motels",
            "type":"Entertainment"
        }
    ],
    "sg:phone":"+1 415 669 1648",
    "sg:postcode":"94937",
    "sg:province":"CA",
    "sg:tags":[
        "breakfast",
        "accommodation",
        "bed"
    ],
    "sg:website":"www.teninvernessway.com",
    "wof:name":"Ten Inverness Way-B & B",
    "wof:placetype":"venue"
},
  "geometry": {"coordinates":[-122.852265,38.097188],"type":"Point"}
}