{
  "type": "Feature",
  "properties": {
    "addr:full":"43405 Peartree Ln Hemet CA 92544",
    "addr:housenumber":"43405",
    "addr:postcode":"92544",
    "addr:street":"Peartree Ln",
    "iso:country":"US",
    "sg:address":"43405 Peartree Ln",
    "sg:city":"Hemet",
    "sg:classifiers":[
        {
            "category":"Shopping",
            "subcategory":"Gifts & Souvenirs",
            "type":"Retail Goods"
        }
    ],
    "sg:phone":"+1 951 927 5675",
    "sg:postcode":"92544",
    "sg:province":"CA",
    "wof:name":"Greatest Gift",
    "wof:placetype":"venue"
},
  "geometry": {"coordinates":[-116.902765,33.741397],"type":"Point"}
}