{
  "type": "Feature",
  "properties": {
    "addr:full":"313 N Lisabeth Cmn Santa Ana CA 92703",
    "addr:housenumber":"313",
    "addr:postcode":"92703",
    "addr:street":"N Lisabeth Cmn",
    "iso:country":"US",
    "sg:address":"313 N Lisabeth Cmn",
    "sg:city":"Santa Ana",
    "sg:classifiers":[
        {
            "category":"Professional",
            "type":"Services"
        }
    ],
    "sg:phone":"+1 714 554 9793",
    "sg:postcode":"92703",
    "sg:province":"CA",
    "wof:name":"Lynh Nguyen",
    "wof:placetype":"venue"
},
  "geometry": {"coordinates":[-117.910267,33.748354],"type":"Point"}
}