{
  "type": "Feature",
  "properties": {
    "iso:country":"US",
    "sg:address":"5928 S Malt Ave",
    "sg:city":"Los Angeles",
    "sg:classifiers":[
        {
            "category":"Professional",
            "subcategory":"Business Services",
            "type":"Services"
        }
    ],
    "sg:phone":"+1 323 721 4300",
    "sg:postcode":"90040",
    "sg:province":"CA",
    "sg:tags":[
        "re",
        "mill",
        "paper",
        "pulp"
    ],
    "wof:name":"JP Resource Co",
    "wof:placetype":"venue"
},
  "geometry": {"coordinates":[-118.145971,33.982589],"type":"Point"}
}