{
  "type": "Feature",
  "properties": {
    "iso:country":"US",
    "sg:address":"1398 University Ave",
    "sg:city":"Berkeley",
    "sg:classifiers":[
        {
            "category":"Restaurant",
            "type":"Food & Drink"
        },
        {
            "category":"Food & Beverages",
            "subcategory":"Bakery",
            "type":"Retail Goods"
        },
        {
            "category":"Bakery",
            "type":"Food & Drink"
        },
        {
            "category":"Professional",
            "type":"Services"
        }
    ],
    "sg:phone":"+1 510 649 9740",
    "sg:postcode":"94702",
    "sg:province":"CA",
    "sg:tags":[
        "brunch",
        "sandwich",
        "breakfast",
        "caterer"
    ],
    "sg:website":"thebreadworkshop.com/",
    "wof:name":"The Bread Workshop",
    "wof:placetype":"venue"
},
  "geometry": {"coordinates":[-122.284384,37.869974],"type":"Point"}
}