{
  "type": "Feature",
  "properties": {
    "iso:country":"US",
    "sg:address":"575 E Main St",
    "sg:city":"El Cajon",
    "sg:classifiers":[
        {
            "category":"Home & Garden",
            "subcategory":"Home Furnishings",
            "type":"Retail Goods"
        }
    ],
    "sg:phone":"+1 619 444 8700",
    "sg:postcode":"92020",
    "sg:province":"CA",
    "sg:tags":[
        "housewares"
    ],
    "wof:name":"Hollywood Shop",
    "wof:placetype":"venue"
},
  "geometry": {"coordinates":[-116.955607,32.794852],"type":"Point"}
}