{
  "type": "Feature",
  "properties": {
    "addr:full":"3186 S Parkway Dr Fresno CA 93725",
    "addr:housenumber":"3186",
    "addr:postcode":"93725",
    "addr:street":"S Parkway Dr",
    "iso:country":"US",
    "sg:address":"3186 S Parkway Dr",
    "sg:city":"Fresno",
    "sg:classifiers":[
        {
            "category":"Autos & Motor Vehicles",
            "subcategory":"Automobile Sales",
            "type":"Retail Goods"
        }
    ],
    "sg:phone":"+1 559 441 7667",
    "sg:postcode":"93725",
    "sg:province":"CA",
    "sg:tags":[
        "trucks-industrial"
    ],
    "wof:name":"Ry-Den Diesel Inc.",
    "wof:placetype":"venue"
},
  "geometry": {"coordinates":[-119.756517,36.688845],"type":"Point"}
}