{
  "type": "Feature",
  "properties": {
    "addr:full":"2001 Bryant St San Francisco CA 94110",
    "addr:housenumber":"2001",
    "addr:postcode":"94110",
    "addr:street":"Bryant St",
    "iso:country":"US",
    "sg:address":"2001 Bryant St",
    "sg:city":"San Francisco",
    "sg:classifiers":[
        {
            "category":"Professional",
            "type":"Services"
        },
        {
            "category":"Retail",
            "subcategory":"Portrait Studio",
            "type":"Services"
        }
    ],
    "sg:phone":"+1 415 643 9275",
    "sg:postcode":"94110",
    "sg:province":"CA",
    "sg:tags":[
        "photography",
        "store"
    ],
    "sg:website":"www.calumetphoto.com",
    "wof:name":"Calumet Photographic",
    "wof:placetype":"venue"
},
  "geometry": {"coordinates":[-122.409789,37.761551],"type":"Point"}
}