{
  "type": "Feature",
  "properties": {
    "iso:country":"US",
    "sg:address":"1916 Martin Luther King Jr Way",
    "sg:city":"Berkeley",
    "sg:classifiers":[
        {
            "category":"Organizations",
            "subcategory":"Religious Organization",
            "type":"Services"
        }
    ],
    "sg:phone":"+1 510 540 0577",
    "sg:postcode":"94704",
    "sg:province":"CA",
    "sg:tags":[
        "church"
    ],
    "wof:name":"Berkely Baptist Church",
    "wof:placetype":"venue"
},
  "geometry": {"coordinates":[-122.273298,37.872984],"type":"Point"}
}