{
  "type": "Feature",
  "properties": {
    "iso:country":"US",
    "sg:address":"3255 Beverly Boulevard",
    "sg:city":"Los Angeles",
    "sg:classifiers":[
        {
            "category":"Food & Beverages",
            "subcategory":"Groceries & Convenience Stores",
            "type":"Retail Goods"
        }
    ],
    "sg:phone":"+1 213 383 5083",
    "sg:postcode":"90057",
    "sg:province":"CA",
    "wof:name":"Beverly Store",
    "wof:placetype":"venue"
},
  "geometry": {"coordinates":[-118.284462,34.072722],"type":"Point"}
}