{
  "type": "Feature",
  "properties": {
    "iso:country":"US",
    "sg:address":"813 Jessie Ave",
    "sg:city":"Sacramento",
    "sg:classifiers":[
        {
            "category":"Freight",
            "type":"Transportation"
        }
    ],
    "sg:phone":"+1 916 568 6263",
    "sg:postcode":"95838",
    "sg:province":"CA",
    "sg:tags":[
        "trucking"
    ],
    "wof:name":"Bo's Trucking",
    "wof:placetype":"venue"
},
  "geometry": {"coordinates":[-121.443083,38.643969],"type":"Point"}
}