{
  "type": "Feature",
  "properties": {
    "iso:country":"US",
    "sg:address":"5700 Foothill Blvd",
    "sg:city":"Oakland",
    "sg:classifiers":[
        {
            "category":"Building & Trades",
            "subcategory":"Landscaping Services",
            "type":"Services"
        }
    ],
    "sg:phone":"+1 510 261 5049",
    "sg:postcode":"94605",
    "sg:province":"CA",
    "sg:tags":[
        "landscape"
    ],
    "wof:name":"Millers Landscape",
    "wof:placetype":"venue"
},
  "geometry": {"coordinates":[-122.193078,37.771828],"type":"Point"}
}