{
  "type": "Feature",
  "properties": {
    "addr:full":"950 Clay Street San Francisco CA 94108",
    "addr:housenumber":"950",
    "addr:postcode":"94108",
    "addr:street":"Clay Street",
    "iso:country":"US",
    "sg:address":"950 Clay Street",
    "sg:city":"San Francisco",
    "sg:classifiers":[
        {
            "category":"Education",
            "subcategory":"School",
            "type":"Public Place"
        }
    ],
    "sg:phone":"+1 415 291 7934",
    "sg:postcode":"94108",
    "sg:province":"CA",
    "wof:name":"Commodore Stockton Pre-K School",
    "wof:placetype":"venue"
},
  "geometry": {"coordinates":[-122.408997,37.794102],"type":"Point"}
}