{
  "type": "Feature",
  "properties": {
    "iso:country":"US",
    "sg:address":"4050 San Dimas St",
    "sg:city":"Bakersfield",
    "sg:classifiers":[
        {
            "category":"Health Services",
            "subcategory":"Doctor",
            "type":"Services"
        }
    ],
    "sg:phone":"+1 661 323 5910",
    "sg:postcode":"93301",
    "sg:province":"CA",
    "sg:tags":[
        "dentist"
    ],
    "wof:name":"Bakersfield Orthodontic Dental",
    "wof:placetype":"venue"
},
  "geometry": {"coordinates":[-119.008095,35.396567],"type":"Point"}
}