{
  "type": "Feature",
  "properties": {
    "addr:full":"28 Helena Irvine CA 92604",
    "addr:housenumber":"28",
    "addr:postcode":"92604",
    "addr:street":"Helena",
    "iso:country":"US",
    "sg:address":"28 Helena",
    "sg:city":"Irvine",
    "sg:classifiers":[
        {
            "category":"Freight",
            "type":"Transportation"
        }
    ],
    "sg:phone":"+1 949 552 0732",
    "sg:postcode":"92604",
    "sg:province":"CA",
    "sg:tags":[
        "operator",
        "trucking"
    ],
    "wof:name":"Mike Russell Transport",
    "wof:placetype":"venue"
},
  "geometry": {"coordinates":[-117.77424999999999,33.698184],"type":"Point"}
}