{
  "type": "Feature",
  "properties": {
    "iso:country":"US",
    "sg:address":"30 E 5th St",
    "sg:city":"Watsonville",
    "sg:classifiers":[
        {
            "category":"Restaurant",
            "type":"Food & Drink"
        }
    ],
    "sg:phone":"+1 831 724 5151",
    "sg:postcode":"95076",
    "sg:province":"CA",
    "sg:tags":[
        "eating"
    ],
    "wof:name":"Pizzamia-We Deliver",
    "wof:placetype":"venue"
},
  "geometry": {"coordinates":[-121.758565,36.913675],"type":"Point"}
}