{
  "type": "Feature",
  "properties": {
    "iso:country":"US",
    "sg:address":"84 Plaza Sq",
    "sg:city":"Orange",
    "sg:classifiers":[
        {
            "category":"Shopping",
            "subcategory":"Used Merchandise",
            "type":"Retail Goods"
        }
    ],
    "sg:phone":"+1 714 538 1762",
    "sg:postcode":"92866",
    "sg:province":"CA",
    "wof:name":"Rubys Antique Jewelry",
    "wof:placetype":"venue"
},
  "geometry": {"coordinates":[-117.852712,33.78812],"type":"Point"}
}