{
  "type": "Feature",
  "properties": {
    "iso:country":"US",
    "sg:address":"1830 W Burbank Blvd",
    "sg:city":"Burbank",
    "sg:classifiers":[
        {
            "category":"Wholesale",
            "subcategory":"Electrical",
            "type":"Manufacturing & Wholesale Goods"
        }
    ],
    "sg:phone":"+1 818 840 9293",
    "sg:postcode":"91506",
    "sg:province":"CA",
    "sg:tags":[
        "sound",
        "equipment",
        "system"
    ],
    "wof:name":"Mayhew & Co",
    "wof:placetype":"venue"
},
  "geometry": {"coordinates":[-118.331447,34.180892],"type":"Point"}
}