{
  "type": "Feature",
  "properties": {
    "addr:full":"17120 Valley View Ave La Mirada CA 90638",
    "addr:housenumber":"17120",
    "addr:postcode":"90638",
    "addr:street":"Valley View Ave",
    "iso:country":"US",
    "sg:address":"17120 Valley View Ave",
    "sg:city":"La Mirada",
    "sg:classifiers":[
        {
            "category":"Freight",
            "type":"Transportation"
        }
    ],
    "sg:phone":"+1 562 921 0939",
    "sg:postcode":"90638",
    "sg:province":"CA",
    "sg:tags":[
        "mover"
    ],
    "wof:name":"Interconex Inc",
    "wof:placetype":"venue"
},
  "geometry": {"coordinates":[-118.02882700000001,33.877342],"type":"Point"}
}