{
  "type": "Feature",
  "properties": {
    "addr:full":"1155 Coast Village Rd Santa Barbara CA 93108",
    "addr:housenumber":"1155",
    "addr:postcode":"93108",
    "addr:street":"Coast Village Rd",
    "iso:country":"US",
    "sg:address":"1155 Coast Village Rd",
    "sg:city":"Santa Barbara",
    "sg:classifiers":[
        {
            "category":"Professional",
            "type":"Services"
        }
    ],
    "sg:phone":"+1 805 565 9097",
    "sg:postcode":"93108",
    "sg:province":"CA",
    "wof:name":"Jon Douglas Co",
    "wof:placetype":"venue"
},
  "geometry": {"coordinates":[-119.646421,34.421167],"type":"Point"}
}