{
  "type": "Feature",
  "properties": {
    "addr:full":"1627 University Ave Berkeley CA 94703",
    "addr:housenumber":"1627",
    "addr:postcode":"94703",
    "addr:street":"University Ave",
    "iso:country":"US",
    "sg:address":"1627 University Ave",
    "sg:city":"Berkeley",
    "sg:classifiers":[
        {
            "category":"Real Estate",
            "subcategory":"Real Estate Operator",
            "type":"Services"
        }
    ],
    "sg:phone":"+1 510 704 1641",
    "sg:postcode":"94703",
    "sg:province":"CA",
    "sg:tags":[
        "apartment"
    ],
    "sg:website":"www.equityapartments.com/califor...",
    "wof:name":"Renaissance Villas",
    "wof:placetype":"venue"
},
  "geometry": {"coordinates":[-122.278701,37.870905],"type":"Point"}
}