{
  "type": "Feature",
  "properties": {
    "addr:full":"830 Maple Ave Los Angeles CA 90014",
    "addr:housenumber":"830",
    "addr:postcode":"90014",
    "addr:street":"Maple Ave",
    "iso:country":"US",
    "sg:address":"830 Maple Ave",
    "sg:city":"Los Angeles",
    "sg:classifiers":[
        {
            "category":"Restaurant",
            "type":"Food & Drink"
        }
    ],
    "sg:phone":"+1 213 623 2226",
    "sg:postcode":"90014",
    "sg:province":"CA",
    "sg:tags":[
        "middle",
        "eastern"
    ],
    "wof:name":"Maple Grill",
    "wof:placetype":"venue"
},
  "geometry": {"coordinates":[-118.252075,34.040042],"type":"Point"}
}