{
  "type": "Feature",
  "properties": {
    "iso:country":"US",
    "sg:address":"449 Stonefield Pl",
    "sg:city":"Moraga",
    "sg:classifiers":[
        {
            "category":"Shopping",
            "subcategory":"Gifts & Souvenirs",
            "type":"Retail Goods"
        }
    ],
    "sg:phone":"+1 925 631 9679",
    "sg:postcode":"94556",
    "sg:province":"CA",
    "wof:name":"Balloontique",
    "wof:placetype":"venue"
},
  "geometry": {"coordinates":[-122.117679,37.814164],"type":"Point"}
}