{
  "type": "Feature",
  "properties": {
    "iso:country":"US",
    "sg:address":"766 Moorpark St",
    "sg:city":"Oakland",
    "sg:classifiers":[
        {
            "category":"Building & Trades",
            "subcategory":"Plumbing",
            "type":"Services"
        }
    ],
    "sg:phone":"+1 510 569 4422",
    "sg:postcode":"94603",
    "sg:province":"CA",
    "sg:tags":[
        "contractor"
    ],
    "wof:name":"Oak Mechanical Inc",
    "wof:placetype":"venue"
},
  "geometry": {"coordinates":[-122.17409600000001,37.73177],"type":"Point"}
}