{
  "type": "Feature",
  "properties": {
    "iso:country":"US",
    "sg:address":"5150 E Pacific Coast Hwy",
    "sg:city":"Long Beach",
    "sg:classifiers":[
        {
            "category":"Professional",
            "subcategory":"Accounting & Tax Preparation",
            "type":"Services"
        }
    ],
    "sg:phone":"+1 562 985 0202",
    "sg:postcode":"90804",
    "sg:province":"CA",
    "sg:tags":[
        "return",
        "filing"
    ],
    "wof:name":"Szabatura & Co",
    "wof:placetype":"venue"
},
  "geometry": {"coordinates":[-118.133311,33.783188],"type":"Point"}
}