{
  "type": "Feature",
  "properties": {
    "iso:country":"US",
    "sg:address":"8428 Melrose Pl",
    "sg:city":"Los Angeles",
    "sg:classifiers":[
        {
            "category":"Arts & Performance",
            "subcategory":"Theater",
            "type":"Entertainment"
        }
    ],
    "sg:phone":"+1 323 822 2793",
    "sg:postcode":"90069",
    "sg:province":"CA",
    "sg:tags":[
        "talent",
        "agency",
        "casting"
    ],
    "wof:name":"Marion Rosenberg Ofc",
    "wof:placetype":"venue"
},
  "geometry": {"coordinates":[-118.375161,34.083532],"type":"Point"}
}