{
  "type": "Feature",
  "properties": {
    "iso:country":"US",
    "sg:address":"581 McCray St",
    "sg:city":"Hollister",
    "sg:classifiers":[
        {
            "category":"Recreation",
            "type":"Entertainment"
        }
    ],
    "sg:phone":"+1 831 636 6662",
    "sg:postcode":"95023",
    "sg:province":"CA",
    "sg:tags":[
        "martial",
        "arts",
        "instruction"
    ],
    "wof:name":"Hollister Martial Arts Academy",
    "wof:placetype":"venue"
},
  "geometry": {"coordinates":[-121.397521,36.850382],"type":"Point"}
}