{
  "type": "Feature",
  "properties": {
    "iso:country":"US",
    "sg:address":"524 S Golden Gate Ave",
    "sg:city":"Stockton",
    "sg:classifiers":[
        {
            "category":"Social Services",
            "type":"Services"
        }
    ],
    "sg:phone":"+1 209 464 9520",
    "sg:postcode":"95205",
    "sg:province":"CA",
    "sg:tags":[
        "organization",
        "welfare"
    ],
    "wof:name":"Berea Apostolic Group Home",
    "wof:placetype":"venue"
},
  "geometry": {"coordinates":[-121.244717,37.955439],"type":"Point"}
}