{
  "type": "Feature",
  "properties": {
    "iso:country":"US",
    "sg:address":"4661 District Blvd",
    "sg:city":"Los Angeles",
    "sg:classifiers":[
        {
            "category":"Wholesale",
            "subcategory":"Sporting Goods",
            "type":"Manufacturing & Wholesale Goods"
        },
        {
            "category":"Manufacturing",
            "subcategory":"Toys & Sporting Goods",
            "type":"Manufacturing & Wholesale Goods"
        }
    ],
    "sg:phone":"+1 323 586 8475",
    "sg:postcode":"90058",
    "sg:province":"CA",
    "sg:tags":[
        "helmet",
        "bicycle",
        "motorcycle"
    ],
    "wof:name":"Trans National Trading Inc",
    "wof:placetype":"venue"
},
  "geometry": {"coordinates":[-118.196043,33.999636],"type":"Point"}
}