{
  "type": "Feature",
  "properties": {
    "addr:full":"1441 3rd Street Promenade Santa Monica CA 90401",
    "addr:housenumber":"1441",
    "addr:postcode":"90401",
    "addr:street":"3Rd Street Promenade",
    "iso:country":"US",
    "sg:address":"1441 3rd Street Promenade",
    "sg:city":"Santa Monica",
    "sg:classifiers":[
        {
            "category":"Cinema",
            "subcategory":"Movie Theater",
            "type":"Entertainment"
        }
    ],
    "sg:phone":"+1 310 458 3924",
    "sg:postcode":"90401",
    "sg:province":"CA",
    "sg:website":"www.enjoytheshow.com",
    "wof:name":"Broadway Cinema",
    "wof:placetype":"venue"
},
  "geometry": {"coordinates":[-118.495616,34.015448],"type":"Point"}
}