{
  "type": "Feature",
  "properties": {
    "addr:full":"2860 Richardson Dr Auburn CA 95603",
    "addr:housenumber":"2860",
    "addr:postcode":"ca 95603",
    "addr:street":"Richardson Dr",
    "iso:country":"US",
    "sg:address":"2860 Richardson Dr",
    "sg:city":"Auburn",
    "sg:classifiers":[
        {
            "category":"Personal",
            "subcategory":"Beauty Salon",
            "type":"Services"
        }
    ],
    "sg:phone":"+1 530 886 8622",
    "sg:postcode":"95603",
    "sg:province":"CA",
    "wof:name":"Backroads Salon",
    "wof:placetype":"venue"
},
  "geometry": {"coordinates":[-121.107967,38.942819],"type":"Point"}
}