{
  "type": "Feature",
  "properties": {
    "addr:full":"23060 Ottawa Rd Apple Valley CA 92308",
    "addr:housenumber":"23060",
    "addr:postcode":"92308",
    "addr:street":"Ottawa Rd",
    "iso:country":"US",
    "sg:address":"23060 Ottawa Rd",
    "sg:city":"Apple Valley",
    "sg:classifiers":[
        {
            "category":"Banks & Credit Unions",
            "subcategory":"Financial Services",
            "type":"Services"
        }
    ],
    "sg:phone":"+1 760 240 3342",
    "sg:postcode":"92308",
    "sg:province":"CA",
    "sg:tags":[
        "trust",
        "management"
    ],
    "wof:name":"Denty Family Trust",
    "wof:placetype":"venue"
},
  "geometry": {"coordinates":[-117.160808,34.493644],"type":"Point"}
}