{
  "type": "Feature",
  "properties": {
    "iso:country":"US",
    "sg:address":"975 S Meridian Ave",
    "sg:city":"Alhambra",
    "sg:classifiers":[
        {
            "category":"Shopping",
            "subcategory":"Clothing, Apparel, & Fashions",
            "type":"Retail Goods"
        }
    ],
    "sg:phone":"+1 626 282 8039",
    "sg:postcode":"91803",
    "sg:province":"CA",
    "sg:tags":[
        "garment"
    ],
    "wof:name":"LA Pacific Apparel Inc",
    "wof:placetype":"venue"
},
  "geometry": {"coordinates":[-118.153919,34.083294],"type":"Point"}
}