{
  "type": "Feature",
  "properties": {
    "iso:country":"US",
    "sg:address":"483 Oak St",
    "sg:city":"San Francisco",
    "sg:classifiers":[
        {
            "category":"Professional",
            "type":"Services"
        }
    ],
    "sg:phone":"+1 415 255 9276",
    "sg:postcode":"94102",
    "sg:province":"CA",
    "wof:name":"Ray Coleman",
    "wof:placetype":"venue"
},
  "geometry": {"coordinates":[-122.426438,37.77449],"type":"Point"}
}