{
  "type": "Feature",
  "properties": {
    "iso:country":"US",
    "sg:address":"23822 Stillwater Ln",
    "sg:city":"Laguna Niguel",
    "sg:classifiers":[
        {
            "category":"Organizations",
            "subcategory":"Non-profit Organization",
            "type":"Services"
        }
    ],
    "sg:phone":"+1 949 916 8979",
    "sg:postcode":"92677",
    "sg:province":"CA",
    "sg:tags":[
        "info",
        "addiction",
        "abuse",
        "treatment",
        "drug"
    ],
    "wof:name":"Hope By The Sea",
    "wof:placetype":"venue"
},
  "geometry": {"coordinates":[-117.712047,33.529236],"type":"Point"}
}