{
  "type": "Feature",
  "properties": {
    "addr:full":"37077 Bodily Ave Fremont CA 94536",
    "addr:postcode":"37077;94536",
    "addr:street":"Bodily Ave",
    "iso:country":"US",
    "sg:address":"37077 Bodily Ave",
    "sg:city":"Fremont",
    "sg:classifiers":[
        {
            "category":"Real Estate",
            "subcategory":"Architect",
            "type":"Services"
        }
    ],
    "sg:phone":"+1 510 745 9318",
    "sg:postcode":"94536",
    "sg:province":"CA",
    "wof:name":"Linda Randolph",
    "wof:placetype":"venue"
},
  "geometry": {"coordinates":[-121.98862099999999,37.575749],"type":"Point"}
}