{
  "type": "Feature",
  "properties": {
    "addr:full":"2241 E Palmyra Orange CA 92869",
    "addr:housenumber":"2241",
    "addr:postcode":"92869",
    "addr:street":"E Palmyra",
    "iso:country":"US",
    "sg:address":"2241 E Palmyra",
    "sg:city":"Orange",
    "sg:classifiers":[
        {
            "category":"Recreation",
            "type":"Entertainment"
        }
    ],
    "sg:postcode":"92869",
    "sg:province":"CA",
    "sg:tags":[
        "active",
        "life"
    ],
    "sg:website":"Orangeybmx.com",
    "wof:name":"Orange Y BMX",
    "wof:placetype":"venue"
},
  "geometry": {"coordinates":[-117.82705799999999,33.784129],"type":"Point"}
}