{
  "type": "Feature",
  "properties": {
    "addr:full":"2201 S B St Stockton CA 95206",
    "addr:housenumber":"2201",
    "addr:postcode":"95206",
    "addr:street":"S B St",
    "iso:country":"US",
    "sg:address":"2201 S B St",
    "sg:city":"Stockton",
    "sg:classifiers":[
        {
            "category":"Banks & Credit Unions",
            "subcategory":"Bank",
            "type":"Services"
        }
    ],
    "sg:phone":"+1 209 463 3711",
    "sg:postcode":"95206",
    "sg:province":"CA",
    "sg:tags":[
        "loan"
    ],
    "wof:name":"Payday Express Check Cashing",
    "wof:placetype":"venue"
},
  "geometry": {"coordinates":[-121.25499499999999,37.932894],"type":"Point"}
}