{
  "type": "Feature",
  "properties": {
    "addr:full":"300 Pier View Way Oceanside CA 92054",
    "addr:housenumber":"300",
    "addr:postcode":"92054",
    "addr:street":"Pier View Way",
    "iso:country":"US",
    "sg:address":"300 Pier View Way",
    "sg:city":"Oceanside",
    "sg:classifiers":[
        {
            "category":"Coffee & Tea",
            "type":"Food & Drink"
        },
        {
            "category":"Restaurant",
            "type":"Food & Drink"
        }
    ],
    "sg:phone":"+1 760 966 1150",
    "sg:postcode":"92054",
    "sg:province":"CA",
    "sg:tags":[
        "traditional",
        "american"
    ],
    "sg:website":"www.pierviewcoffee.com/",
    "wof:name":"Pier View Coffee Company",
    "wof:placetype":"venue"
},
  "geometry": {"coordinates":[-117.38172900000001,33.195848],"type":"Point"}
}