{
  "type": "Feature",
  "properties": {
    "addr:full":"5224 Avalon Blvd Los Angeles CA 90011",
    "addr:housenumber":"5224",
    "addr:postcode":"90011",
    "addr:street":"Avalon Blvd",
    "iso:country":"US",
    "sg:address":"5224 Avalon Blvd",
    "sg:city":"Los Angeles",
    "sg:classifiers":[
        {
            "category":"Organizations",
            "subcategory":"Religious Organization",
            "type":"Services"
        }
    ],
    "sg:phone":"+1 323 231 6455",
    "sg:postcode":"90011",
    "sg:province":"CA",
    "sg:tags":[
        "church"
    ],
    "wof:name":"Sunset Missionary Baptist Chr",
    "wof:placetype":"venue"
},
  "geometry": {"coordinates":[-118.265128,33.995033],"type":"Point"}
}