{
  "type": "Feature",
  "properties": {
    "addr:full":"22101 Cosala Mission Viejo CA 92691",
    "addr:housenumber":"22101",
    "addr:postcode":"92691",
    "addr:street":"Cosala",
    "iso:country":"US",
    "sg:address":"22101 Cosala",
    "sg:city":"Mission Viejo",
    "sg:classifiers":[
        {
            "category":"Wholesale",
            "subcategory":"Machinery & Supplies",
            "type":"Manufacturing & Wholesale Goods"
        }
    ],
    "sg:phone":"+1 949 859 0960",
    "sg:postcode":"92691",
    "sg:province":"CA",
    "wof:name":"Toussiengm Dnnis MA",
    "wof:placetype":"venue"
},
  "geometry": {"coordinates":[-117.64519199999999,33.645111],"type":"Point"}
}