{
  "type": "Feature",
  "properties": {
    "iso:country":"US",
    "sg:address":"1174 Castro St",
    "sg:city":"Mountain View",
    "sg:classifiers":[
        {
            "category":"Health Services",
            "subcategory":"Health Practitioner",
            "type":"Services"
        }
    ],
    "sg:phone":"+1 650 966 0900",
    "sg:postcode":"94040",
    "sg:province":"CA",
    "sg:tags":[
        "surgery",
        "laser"
    ],
    "wof:name":"Laservue Eye Ctr",
    "wof:placetype":"venue"
},
  "geometry": {"coordinates":[-122.086266,37.38201],"type":"Point"}
}