{
  "type": "Feature",
  "properties": {
    "addr:full":"10401 Folsom Blvd Rancho Cordova CA 95670",
    "addr:housenumber":"10401",
    "addr:postcode":"95670",
    "addr:street":"Folsom Blvd",
    "iso:country":"US",
    "sg:address":"10401 Folsom Blvd",
    "sg:city":"Rancho Cordova",
    "sg:classifiers":[
        {
            "category":"Restaurant",
            "type":"Food & Drink"
        }
    ],
    "sg:phone":"+1 916 364 8888",
    "sg:postcode":"95670",
    "sg:province":"CA",
    "wof:name":"Fresh Pizza Delivery",
    "wof:placetype":"venue"
},
  "geometry": {"coordinates":[-121.30139200000001,38.589838],"type":"Point"}
}