{
  "type": "Feature",
  "properties": {
    "addr:full":"4051 Glencoe Ave Marina Del Rey CA 90292",
    "addr:housenumber":"4051",
    "addr:postcode":"90292",
    "addr:street":"Glencoe Ave",
    "iso:country":"US",
    "sg:address":"4051 Glencoe Ave",
    "sg:city":"Marina Del Rey",
    "sg:classifiers":[
        {
            "category":"Home & Garden",
            "subcategory":"Furniture",
            "type":"Retail Goods"
        }
    ],
    "sg:phone":"+1 310 305 8172",
    "sg:postcode":"90292",
    "sg:province":"CA",
    "sg:tags":[
        "store"
    ],
    "wof:name":"ID Inc",
    "wof:placetype":"venue"
},
  "geometry": {"coordinates":[-118.44397499999999,33.990958],"type":"Point"}
}