{
  "type": "Feature",
  "properties": {
    "addr:full":"3800 Finch Rd Modesto CA 95357",
    "addr:housenumber":"3800",
    "addr:postcode":"ca 95357",
    "addr:street":"Finch Rd",
    "iso:country":"US",
    "sg:address":"3800 Finch Rd",
    "sg:city":"Modesto",
    "sg:classifiers":[
        {
            "category":"Home & Garden",
            "subcategory":"Building Materials",
            "type":"Retail Goods"
        }
    ],
    "sg:phone":"+1 209 523 2094",
    "sg:postcode":"95357",
    "sg:province":"CA",
    "sg:tags":[
        "door"
    ],
    "sg:website":"www.wardrobeandbath.com",
    "wof:name":"Wardrobe & Bath Specialties",
    "wof:placetype":"venue"
},
  "geometry": {"coordinates":[-120.927829,37.624822],"type":"Point"}
}