{
  "type": "Feature",
  "properties": {
    "iso:country":"US",
    "sg:address":"1005 N Mollison Ave",
    "sg:city":"El Cajon",
    "sg:classifiers":[
        {
            "category":"Wholesale",
            "subcategory":"Non-durable Goods",
            "type":"Manufacturing & Wholesale Goods"
        }
    ],
    "sg:phone":"+1 619 258 2130",
    "sg:postcode":"92021",
    "sg:province":"CA",
    "sg:tags":[
        "advertising"
    ],
    "wof:name":"Business Promotions",
    "wof:placetype":"venue"
},
  "geometry": {"coordinates":[-116.950979,32.808597],"type":"Point"}
}