{
  "type": "Feature",
  "properties": {
    "addr:full":"505 Maple Ave Torrance CA 90503",
    "addr:housenumber":"505",
    "addr:postcode":"90503",
    "addr:street":"Maple Ave",
    "iso:country":"US",
    "sg:address":"505 Maple Ave",
    "sg:city":"Torrance",
    "sg:classifiers":[
        {
            "category":"Professional",
            "subcategory":"Business Services",
            "type":"Services"
        }
    ],
    "sg:phone":"+1 310 618 3779",
    "sg:postcode":"90503",
    "sg:province":"CA",
    "sg:tags":[
        "customer",
        "center"
    ],
    "wof:name":"South Bay Service Center",
    "wof:placetype":"venue"
},
  "geometry": {"coordinates":[-118.340155,33.842805],"type":"Point"}
}