{
  "type": "Feature",
  "properties": {
    "iso:country":"US",
    "sg:address":"5803 S Main St",
    "sg:city":"Los Angeles",
    "sg:classifiers":[
        {
            "category":"Retail",
            "subcategory":"Repair Shop",
            "type":"Services"
        }
    ],
    "sg:phone":"+1 323 235 5358",
    "sg:postcode":"90003",
    "sg:province":"CA",
    "sg:tags":[
        "upholsterer"
    ],
    "wof:name":"Eduardo's Upholstery",
    "wof:placetype":"venue"
},
  "geometry": {"coordinates":[-118.274003,33.989441],"type":"Point"}
}