{
  "type": "Feature",
  "properties": {
    "addr:full":"201 Old San Francisco Rd Sunnyvale CA 94086",
    "addr:housenumber":"201",
    "addr:postcode":"94086",
    "addr:street":"Old San Francisco Rd",
    "iso:country":"US",
    "sg:address":"201 Old San Francisco Rd",
    "sg:city":"Sunnyvale",
    "sg:classifiers":[
        {
            "category":"Health Services",
            "subcategory":"Doctor",
            "type":"Services"
        }
    ],
    "sg:phone":"+1 408 730 4300",
    "sg:postcode":"94086",
    "sg:province":"CA",
    "sg:tags":[
        "clinic"
    ],
    "wof:name":"Sunnyvale Urgent Care",
    "wof:placetype":"venue"
},
  "geometry": {"coordinates":[-122.03113399999999,37.368207],"type":"Point"}
}