{
  "type": "Feature",
  "properties": {
    "addr:full":"22905 Lockness Ave Torrance CA 90501",
    "addr:postcode":"22905;90501",
    "addr:street":"Lockness Ave",
    "iso:country":"US",
    "sg:address":"22905 Lockness Ave",
    "sg:city":"Torrance",
    "sg:classifiers":[
        {
            "category":"Real Estate",
            "subcategory":"Real Estate Agent",
            "type":"Services"
        }
    ],
    "sg:phone":"+1 310 534 8436",
    "sg:postcode":"90501",
    "sg:province":"CA",
    "sg:tags":[
        "management",
        "property"
    ],
    "sg:website":"www.thomasproperties.com",
    "wof:name":"Thomas Properties",
    "wof:placetype":"venue"
},
  "geometry": {"coordinates":[-118.306,33.817101],"type":"Point"}
}