{
  "type": "Feature",
  "properties": {
    "addr:full":"3100 Edgewood Rd Eureka CA 95501",
    "addr:housenumber":"3100",
    "addr:postcode":"95501",
    "addr:street":"Edgewood Rd",
    "iso:country":"US",
    "sg:address":"3100 Edgewood Rd",
    "sg:city":"Eureka",
    "sg:classifiers":[
        {
            "category":"Health Services",
            "subcategory":"Clinic",
            "type":"Services"
        }
    ],
    "sg:phone":"+1 707 465 0980",
    "sg:postcode":"95501",
    "sg:province":"CA",
    "sg:tags":[
        "physician",
        "surgeon",
        "bureau",
        "information"
    ],
    "wof:name":"Humboldt Del Norte County",
    "wof:placetype":"venue"
},
  "geometry": {"coordinates":[-124.133533,40.789895],"type":"Point"}
}