{
  "type": "Feature",
  "properties": {
    "addr:full":"311 Poinsettia Ave Corona Del Mar CA 92625",
    "addr:housenumber":"311",
    "addr:postcode":"92625",
    "addr:street":"Poinsettia Ave",
    "iso:country":"US",
    "sg:address":"311 Poinsettia Ave",
    "sg:city":"Corona Del Mar",
    "sg:classifiers":[
        {
            "category":"Real Estate",
            "subcategory":"Real Estate Operator",
            "type":"Services"
        }
    ],
    "sg:phone":"+1 949 673 4678",
    "sg:postcode":"92625",
    "sg:province":"CA",
    "sg:tags":[
        "property",
        "lessor"
    ],
    "wof:name":"Kempler 17th St Property LLC",
    "wof:placetype":"venue"
},
  "geometry": {"coordinates":[-117.868331,33.593731],"type":"Point"}
}