{
  "type": "Feature",
  "properties": {
    "iso:country":"US",
    "sg:address":"1804 N Tustin St",
    "sg:city":"Orange",
    "sg:classifiers":[
        {
            "category":"Food & Beverages",
            "subcategory":"Specialty",
            "type":"Retail Goods"
        }
    ],
    "sg:phone":"+1 714 283 0171",
    "sg:postcode":"92865",
    "sg:province":"CA",
    "wof:name":"Natures Way",
    "wof:placetype":"venue"
},
  "geometry": {"coordinates":[-117.836039,33.820546],"type":"Point"}
}