{
  "type": "Feature",
  "properties": {
    "addr:full":"1700 Nevin Ave Richmond CA 94801",
    "addr:housenumber":"1700",
    "addr:postcode":"94801",
    "addr:street":"Nevin Ave",
    "iso:country":"US",
    "sg:address":"1700 Nevin Ave",
    "sg:city":"Richmond",
    "sg:classifiers":[
        {
            "category":"Local Transit",
            "type":"Transportation"
        }
    ],
    "sg:postcode":"94801",
    "sg:province":"CA",
    "sg:tags":[
        "public"
    ],
    "wof:name":"Richmond Amtrak Station",
    "wof:placetype":"venue"
},
  "geometry": {"coordinates":[-122.351473,37.936854],"type":"Point"}
}