{
  "type": "Feature",
  "properties": {
    "iso:country":"US",
    "sg:address":"1301 Marina Village Pkwy # 105",
    "sg:city":"Alameda",
    "sg:classifiers":[
        {
            "category":"Professional",
            "subcategory":"Business Services",
            "type":"Services"
        }
    ],
    "sg:phone":"+1 510 814 8200",
    "sg:postcode":"94501",
    "sg:province":"CA",
    "sg:tags":[
        "organizing",
        "medical",
        "administration",
        "services-household"
    ],
    "sg:website":"http://www.quadramed.com",
    "wof:name":"Quadramed Corporation",
    "wof:placetype":"venue"
},
  "geometry": {"coordinates":[-122.274655,37.786828],"type":"Point"}
}