{
  "type": "Feature",
  "properties": {
    "addr:full":"8500 Wilshire Blvd Ste 818 Beverly Hills CA 90211",
    "addr:housenumber":"8500",
    "addr:postcode":"90211",
    "addr:street":"Wilshire Blvd Ste 818;Hills Ca",
    "iso:country":"US",
    "sg:address":"8500 Wilshire Blvd Ste 818",
    "sg:city":"Beverly Hills",
    "sg:classifiers":[
        {
            "category":"Health Services",
            "subcategory":"Dentist",
            "type":"Services"
        }
    ],
    "sg:phone":"+1 818 761 3230",
    "sg:postcode":"90211",
    "sg:province":"CA",
    "wof:name":"Vafamansouri Behrouz Dentistry",
    "wof:placetype":"venue"
},
  "geometry": {"coordinates":[-118.37624,34.065047],"type":"Point"}
}