{
  "type": "Feature",
  "properties": {
    "iso:country":"US",
    "sg:address":"5755 Valentine Rd",
    "sg:city":"Ventura",
    "sg:classifiers":[
        {
            "category":"Health Services",
            "subcategory":"Health Practitioner",
            "type":"Services"
        }
    ],
    "sg:phone":"+1 805 643 0016",
    "sg:postcode":"93003",
    "sg:province":"CA",
    "sg:tags":[
        "psychologist"
    ],
    "wof:name":"Stephen Mc Eachen PHD",
    "wof:placetype":"venue"
},
  "geometry": {"coordinates":[-119.209966,34.251119],"type":"Point"}
}