{
  "type": "Feature",
  "properties": {
    "addr:full":"218 S del Mar Ave San Gabriel CA 91776",
    "addr:housenumber":"218",
    "addr:postcode":"91776",
    "addr:street":"S Del Mar Ave",
    "iso:country":"US",
    "sg:address":"218 S del Mar Ave",
    "sg:city":"San Gabriel",
    "sg:classifiers":[
        {
            "category":"Professional",
            "type":"Services"
        }
    ],
    "sg:phone":"+1 626 286 3177",
    "sg:postcode":"91776",
    "sg:province":"CA",
    "wof:name":"Holand America Ltd",
    "wof:placetype":"venue"
},
  "geometry": {"coordinates":[-118.09954500000001,34.09928],"type":"Point"}
}