{
  "type": "Feature",
  "properties": {
    "addr:full":"41091 Big Bear Blvd Big Bear Lake CA 92315",
    "addr:housenumber":"41091",
    "addr:postcode":"92315",
    "addr:street":"Big Bear Blvd",
    "iso:country":"US",
    "sg:address":"41091 Big Bear Blvd",
    "sg:city":"Big Bear Lake",
    "sg:classifiers":[
        {
            "category":"Shopping",
            "subcategory":"Gifts & Souvenirs",
            "type":"Retail Goods"
        }
    ],
    "sg:phone":"+1 909 866 2387",
    "sg:postcode":"92315",
    "sg:province":"CA",
    "sg:tags":[
        "collectible"
    ],
    "wof:name":"Sports Collectibles Gallery",
    "wof:placetype":"venue"
},
  "geometry": {"coordinates":[-116.906104,34.243543],"type":"Point"}
}