{
  "type": "Feature",
  "properties": {
    "addr:full":"6060 W Manchester Avenue Los Angeles CA 90045",
    "addr:housenumber":"6060",
    "addr:postcode":"90045",
    "addr:street":"W Manchester Avenue",
    "iso:country":"US",
    "sg:address":"6060 W Manchester Avenue",
    "sg:city":"Los Angeles",
    "sg:classifiers":[
        {
            "category":"Banks & Credit Unions",
            "subcategory":"Financial Services",
            "type":"Services"
        }
    ],
    "sg:phone":"+1 310 410 3973",
    "sg:postcode":"90045",
    "sg:province":"CA",
    "sg:tags":[
        "broker",
        "mortgage"
    ],
    "wof:name":"The Loan Spcialist Group",
    "wof:placetype":"venue"
},
  "geometry": {"coordinates":[-118.39077,33.959905],"type":"Point"}
}