{
  "type": "Feature",
  "properties": {
    "addr:full":"417 W Padre St Goleta CA 93105",
    "addr:housenumber":"417",
    "addr:postcode":"93105",
    "addr:street":"W Padre St",
    "iso:country":"US",
    "sg:address":"417 W Padre St",
    "sg:city":"Goleta",
    "sg:classifiers":[
        {
            "category":"Professional",
            "subcategory":"Art Services",
            "type":"Services"
        }
    ],
    "sg:phone":"+1 805 967 9858",
    "sg:postcode":"93105",
    "sg:province":"CA",
    "sg:tags":[
        "photographer"
    ],
    "wof:name":"I & I Images",
    "wof:placetype":"venue"
},
  "geometry": {"coordinates":[-119.720804,34.427269],"type":"Point"}
}