{
  "type": "Feature",
  "properties": {
    "iso:country":"US",
    "sg:address":"19080 Riverside Dr",
    "sg:city":"Sonoma",
    "sg:classifiers":[
        {
            "category":"Professional",
            "type":"Services"
        }
    ],
    "sg:phone":"+1 707 938 1616",
    "sg:postcode":"95476",
    "sg:province":"CA",
    "sg:tags":[
        "establishment"
    ],
    "wof:name":"Little Switzerland",
    "wof:placetype":"venue"
},
  "geometry": {"coordinates":[-122.4842,38.302146],"type":"Point"}
}