{
  "type": "Feature",
  "properties": {
    "addr:full":"15311 Saticoy St Van Nuys CA 91406",
    "addr:housenumber":"15311",
    "addr:postcode":"91406",
    "addr:street":"Saticoy St",
    "iso:country":"US",
    "sg:address":"15311 Saticoy St",
    "sg:city":"Van Nuys",
    "sg:classifiers":[
        {
            "category":"Retail",
            "subcategory":"Car Wash",
            "type":"Services"
        }
    ],
    "sg:phone":"+1 818 904 9050",
    "sg:postcode":"91406",
    "sg:province":"CA",
    "sg:tags":[
        "polishing",
        "washing"
    ],
    "wof:name":"Saticoy Car Wash",
    "wof:placetype":"venue"
},
  "geometry": {"coordinates":[-118.46696799999999,34.20852],"type":"Point"}
}