{
  "type": "Feature",
  "properties": {
    "addr:full":"6426 Shattuck Ave Oakland CA 94609",
    "addr:housenumber":"6426",
    "addr:postcode":"94609",
    "addr:street":"Shattuck Ave",
    "iso:country":"US",
    "sg:address":"6426 Shattuck Ave",
    "sg:city":"Oakland",
    "sg:classifiers":[
        {
            "category":"Retail",
            "subcategory":"Auto Repair",
            "type":"Services"
        }
    ],
    "sg:phone":"+1 510 653 7393",
    "sg:postcode":"94609",
    "sg:province":"CA",
    "wof:name":"Motter Bob Auto Body Repair Shop",
    "wof:placetype":"venue"
},
  "geometry": {"coordinates":[-122.26549799999999,37.85012],"type":"Point"}
}