{
  "type": "Feature",
  "properties": {
    "addr:full":"1260 Triangle Ct West Sacramento CA 95605",
    "addr:housenumber":"1260",
    "addr:postcode":"95605",
    "addr:street":"Triangle Ct",
    "iso:country":"US",
    "sg:address":"1260 Triangle Ct",
    "sg:city":"West Sacramento",
    "sg:classifiers":[
        {
            "category":"Wholesale",
            "subcategory":"Medical Equipment & Supplies",
            "type":"Manufacturing & Wholesale Goods"
        }
    ],
    "sg:phone":"+1 916 375 8800",
    "sg:postcode":"95605",
    "sg:province":"CA",
    "wof:name":"Valley Home Care",
    "wof:placetype":"venue"
},
  "geometry": {"coordinates":[-121.527631,38.587031],"type":"Point"}
}