{
  "type": "Feature",
  "properties": {
    "addr:full":"11555 Glenoaks Blvd Pacoima CA 91331",
    "addr:housenumber":"11555",
    "addr:postcode":"91331",
    "addr:street":"Glenoaks Blvd",
    "iso:country":"US",
    "sg:address":"11555 Glenoaks Blvd",
    "sg:city":"Pacoima",
    "sg:classifiers":[
        {
            "category":"Autos & Motor Vehicles",
            "subcategory":"Auto Supplies",
            "type":"Retail Goods"
        }
    ],
    "sg:phone":"+1 818 899 0207",
    "sg:postcode":"91331",
    "sg:province":"CA",
    "sg:tags":[
        "automobile",
        "part",
        "accessory"
    ],
    "wof:name":"Apex Auto Parts",
    "wof:placetype":"venue"
},
  "geometry": {"coordinates":[-118.41805600000001,34.279702],"type":"Point"}
}