{
  "type": "Feature",
  "properties": {
    "iso:country":"US",
    "sg:address":"2802 Ave Simi",
    "sg:city":"Simi Valley",
    "sg:classifiers":[
        {
            "category":"Home & Garden",
            "subcategory":"Garden Supply",
            "type":"Retail Goods"
        }
    ],
    "sg:phone":"+1 805 527 8052",
    "sg:postcode":"93065",
    "sg:province":"CA",
    "sg:tags":[
        "sprinkler"
    ],
    "sg:website":"www.ecologylandscape.com",
    "wof:name":"Ecology Landscape",
    "wof:placetype":"venue"
},
  "geometry": {"coordinates":[-118.741093,34.289799],"type":"Point"}
}