{
  "type": "Feature",
  "properties": {
    "addr:full":"18135 Vierra Canyon Rd Salinas CA 93907",
    "addr:housenumber":"18135",
    "addr:postcode":"93907",
    "addr:street":"Vierra Canyon Rd",
    "iso:country":"US",
    "sg:address":"18135 Vierra Canyon Rd",
    "sg:city":"Salinas",
    "sg:classifiers":[
        {
            "category":"Building & Trades",
            "subcategory":"Construction",
            "type":"Services"
        }
    ],
    "sg:phone":"+1 831 444 8383",
    "sg:postcode":"93907",
    "sg:province":"CA",
    "sg:tags":[
        "resurfacing",
        "laying",
        "refinishing",
        "floor"
    ],
    "wof:name":"Villa's Floor Covering",
    "wof:placetype":"venue"
},
  "geometry": {"coordinates":[-121.655486,36.796333],"type":"Point"}
}