{
  "type": "Feature",
  "properties": {
    "addr:full":"8960 Coan Ln Orangevale CA 95662",
    "addr:postcode":"8960;95662",
    "addr:street":"Coan Ln",
    "iso:country":"US",
    "sg:address":"8960 Coan Ln",
    "sg:city":"Orangevale",
    "sg:classifiers":[
        {
            "category":"Professional",
            "subcategory":"Management & Consulting",
            "type":"Services"
        }
    ],
    "sg:phone":"+1 916 988 7212",
    "sg:postcode":"95662",
    "sg:province":"CA",
    "wof:name":"Lews Mobile Collision Repair",
    "wof:placetype":"venue"
},
  "geometry": {"coordinates":[-121.22448,38.683864],"type":"Point"}
}