{
  "type": "Feature",
  "properties": {
    "addr:full":"727 Via Maria Salinas CA 93901",
    "addr:housenumber":"727",
    "addr:postcode":"93901",
    "addr:street":"Via Maria",
    "iso:country":"US",
    "sg:address":"727 Via Maria",
    "sg:city":"Salinas",
    "sg:classifiers":[
        {
            "category":"Professional",
            "subcategory":"Computer Services",
            "type":"Services"
        }
    ],
    "sg:phone":"+1 831 758 8584",
    "sg:postcode":"93901",
    "sg:province":"CA",
    "sg:tags":[
        "isp",
        "provider",
        "internet"
    ],
    "wof:name":"Snp Group",
    "wof:placetype":"venue"
},
  "geometry": {"coordinates":[-121.67106,36.675686],"type":"Point"}
}