{
  "type": "Feature",
  "properties": {
    "addr:full":"211 W Ojai Ave Ojai CA 93023",
    "addr:housenumber":"211",
    "addr:postcode":"93023",
    "addr:street":"W Ojai Ave",
    "iso:country":"US",
    "sg:address":"211 W Ojai Ave",
    "sg:city":"Ojai",
    "sg:classifiers":[
        {
            "category":"Restaurant",
            "type":"Food & Drink"
        }
    ],
    "sg:menulink":"http://www.allmenus.com/ca/meiners-oaks-ojai/152860-carrows/menu/",
    "sg:phone":"+1 805 646 5952",
    "sg:postcode":"93023",
    "sg:province":"CA",
    "sg:tags":[
        "sandwich",
        "salad",
        "burger",
        "dog",
        "soup",
        "hot",
        "wrap",
        "american"
    ],
    "wof:name":"Carrows",
    "wof:placetype":"venue"
},
  "geometry": {"coordinates":[-119.248717,34.447575],"type":"Point"}
}