{
  "type": "Feature",
  "properties": {
    "iso:country":"US",
    "sg:address":"411 Kentucky Ave",
    "sg:city":"Berkeley",
    "sg:classifiers":[
        {
            "category":"Professional",
            "subcategory":"Engineering",
            "type":"Services"
        }
    ],
    "sg:phone":"+1 510 813 2941",
    "sg:postcode":"94707",
    "sg:province":"CA",
    "sg:tags":[
        "consulting",
        "engineer"
    ],
    "sg:website":"http://www.me.berkeley.edu",
    "wof:name":"David M Auslander",
    "wof:placetype":"venue"
},
  "geometry": {"coordinates":[-122.272583,37.903932],"type":"Point"}
}