{
  "type": "Feature",
  "properties": {
    "addr:full":"1495 Colorado Blvd Los Angeles CA 90041",
    "addr:housenumber":"1495",
    "addr:postcode":"90041",
    "addr:street":"Colorado Blvd",
    "iso:country":"US",
    "sg:address":"1495 Colorado Blvd",
    "sg:city":"Los Angeles",
    "sg:classifiers":[
        {
            "category":"Education",
            "subcategory":"School",
            "type":"Public Place"
        }
    ],
    "sg:phone":"+1 323 257 7576",
    "sg:postcode":"90041",
    "sg:province":"CA",
    "sg:website":"www.westminsteracademy.com",
    "wof:name":"Westminster Academy",
    "wof:placetype":"venue"
},
  "geometry": {"coordinates":[-118.19778100000001,34.1393],"type":"Point"}
}