{
  "type": "Feature",
  "properties": {
    "iso:country":"US",
    "sg:address":"1457 Mable Ave",
    "sg:city":"Modesto",
    "sg:classifiers":[
        {
            "category":"Organizations",
            "subcategory":"Religious Organization",
            "type":"Services"
        }
    ],
    "sg:phone":"+1 209 526 2860",
    "sg:postcode":"95355",
    "sg:province":"CA",
    "sg:tags":[
        "church"
    ],
    "wof:name":"St Zaia",
    "wof:placetype":"venue"
},
  "geometry": {"coordinates":[-120.972211,37.696222],"type":"Point"}
}