{
  "type": "Feature",
  "properties": {
    "addr:full":"8001 Reseda Blvd Reseda CA 91335",
    "addr:housenumber":"8001",
    "addr:postcode":"91335",
    "addr:street":"Reseda Blvd",
    "iso:country":"US",
    "sg:address":"8001 Reseda Blvd",
    "sg:city":"Reseda",
    "sg:classifiers":[
        {
            "category":"Home & Garden",
            "subcategory":"Hardware",
            "type":"Retail Goods"
        }
    ],
    "sg:phone":"+1 818 342 1400",
    "sg:postcode":"91335",
    "sg:province":"CA",
    "wof:name":"Tarzana Door Moulding & Hdwr",
    "wof:placetype":"venue"
},
  "geometry": {"coordinates":[-118.536074,34.217459],"type":"Point"}
}