{
  "type": "Feature",
  "properties": {
    "iso:country":"US",
    "sg:address":"312 S Navarra Dr",
    "sg:city":"Scotts Valley",
    "sg:classifiers":[
        {
            "category":"Personal",
            "subcategory":"Beauty Salon",
            "type":"Services"
        }
    ],
    "sg:phone":"+1 831 438 5885",
    "sg:postcode":"95066",
    "sg:province":"CA",
    "wof:name":"Celeste Creations",
    "wof:placetype":"venue"
},
  "geometry": {"coordinates":[-122.004854,37.057569],"type":"Point"}
}