{
  "type": "Feature",
  "properties": {
    "iso:country":"US",
    "sg:address":"240 S Garfield Ave",
    "sg:city":"Alhambra",
    "sg:classifiers":[
        {
            "category":"Professional",
            "subcategory":"Accounting & Tax Preparation",
            "type":"Services"
        }
    ],
    "sg:phone":"+1 626 282 7628",
    "sg:postcode":"91801",
    "sg:province":"CA",
    "sg:tags":[
        "accountant"
    ],
    "wof:name":"Leo K F Lau CPA",
    "wof:placetype":"venue"
},
  "geometry": {"coordinates":[-118.124943,34.092621],"type":"Point"}
}