{
  "type": "Feature",
  "properties": {
    "iso:country":"US",
    "sg:address":"3004 Taraval St",
    "sg:city":"San Francisco",
    "sg:classifiers":[
        {
            "category":"Shopping",
            "subcategory":"Bicycles & Sporting Goods",
            "type":"Retail Goods"
        }
    ],
    "sg:phone":"+1 415 731 3838",
    "sg:postcode":"94116",
    "sg:province":"CA",
    "wof:name":"Bike Nook",
    "wof:placetype":"venue"
},
  "geometry": {"coordinates":[-122.49923200000001,37.742084],"type":"Point"}
}