{
  "type": "Feature",
  "properties": {
    "iso:country":"US",
    "sg:address":"542 W Olive Ave",
    "sg:city":"Porterville",
    "sg:classifiers":[
        {
            "category":"Food & Beverages",
            "subcategory":"Groceries & Convenience Stores",
            "type":"Retail Goods"
        }
    ],
    "sg:phone":"+1 559 781 7669",
    "sg:postcode":"93257",
    "sg:province":"CA",
    "sg:tags":[
        "grocer"
    ],
    "wof:name":"Laos Asian Market",
    "wof:placetype":"venue"
},
  "geometry": {"coordinates":[-119.02899499999999,36.066089],"type":"Point"}
}