{
  "type": "Feature",
  "properties": {
    "iso:country":"US",
    "sg:address":"2632 Millcreek Dr",
    "sg:city":"Sacramento",
    "sg:classifiers":[
        {
            "category":"Building & Trades",
            "subcategory":"Landscaping Services",
            "type":"Services"
        }
    ],
    "sg:phone":"+1 916 564 5738",
    "sg:postcode":"95833",
    "sg:province":"CA",
    "wof:name":"Oasis Landscaping",
    "wof:placetype":"venue"
},
  "geometry": {"coordinates":[-121.50156200000001,38.613389],"type":"Point"}
}