{
  "type": "Feature",
  "properties": {
    "addr:full":"19651 Center St Castro Valley CA 94546",
    "addr:housenumber":"19651",
    "addr:postcode":"94546",
    "addr:street":"Center St",
    "iso:country":"US",
    "sg:address":"19651 Center St",
    "sg:city":"Castro Valley",
    "sg:classifiers":[
        {
            "category":"Shopping",
            "subcategory":"Jewelry",
            "type":"Retail Goods"
        }
    ],
    "sg:phone":"+1 510 537 3678",
    "sg:postcode":"94546",
    "sg:province":"CA",
    "wof:name":"Vortman's Fine Jewelry",
    "wof:placetype":"venue"
},
  "geometry": {"coordinates":[-122.141239,37.700309],"type":"Point"}
}