{
  "type": "Feature",
  "properties": {
    "addr:full":"942 S Harlan Avenue Compton CA 90220",
    "addr:housenumber":"942",
    "addr:postcode":"90220",
    "addr:street":"S Harlan Avenue",
    "iso:country":"US",
    "sg:address":"942 S Harlan Avenue",
    "sg:city":"Compton",
    "sg:classifiers":[
        {
            "category":"Building & Trades",
            "subcategory":"Construction",
            "type":"Services"
        }
    ],
    "sg:phone":"+1 310 637 8765",
    "sg:postcode":"90220",
    "sg:province":"CA",
    "sg:tags":[
        "contractor"
    ],
    "wof:name":"Roman Arch Construction",
    "wof:placetype":"venue"
},
  "geometry": {"coordinates":[-118.24520200000001,33.886719],"type":"Point"}
}