{
  "type": "Feature",
  "properties": {
    "iso:country":"US",
    "sg:address":"14949 Bear Valley Rd",
    "sg:city":"Hesperia",
    "sg:classifiers":[
        {
            "category":"Retail",
            "subcategory":"Car Wash",
            "type":"Services"
        }
    ],
    "sg:phone":"+1 760 947 6084",
    "sg:postcode":"92345",
    "sg:province":"CA",
    "sg:tags":[
        "automobile",
        "detailing"
    ],
    "wof:name":"Bear Valley Hand Car Wash",
    "wof:placetype":"venue"
},
  "geometry": {"coordinates":[-117.337891,34.470498],"type":"Point"}
}