{
  "type": "Feature",
  "properties": {
    "addr:full":"517 Pine Ave Long Beach CA 90802",
    "addr:housenumber":"517",
    "addr:postcode":"90802",
    "addr:street":"Pine Ave",
    "iso:country":"US",
    "sg:address":"517 Pine Ave",
    "sg:city":"Long Beach",
    "sg:classifiers":[
        {
            "category":"Retail",
            "subcategory":"Portrait Studio",
            "type":"Services"
        }
    ],
    "sg:phone":"+1 562 435 3966",
    "sg:postcode":"90802",
    "sg:province":"CA",
    "sg:tags":[
        "photography",
        "store"
    ],
    "wof:name":"Photo Max",
    "wof:placetype":"venue"
},
  "geometry": {"coordinates":[-118.193001,33.7733],"type":"Point"}
}