{
  "type": "Feature",
  "properties": {
    "addr:full":"13750 Arnold Dr Glen Ellen CA 95442",
    "addr:housenumber":"13750",
    "addr:postcode":"95442",
    "addr:street":"Arnold Dr",
    "iso:country":"US",
    "sg:address":"13750 Arnold Dr",
    "sg:city":"Glen Ellen",
    "sg:classifiers":[
        {
            "category":"Professional",
            "type":"Services"
        }
    ],
    "sg:phone":"+1 707 996 6576",
    "sg:postcode":"95442",
    "sg:province":"CA",
    "wof:name":"Sonoma Nalley Prop",
    "wof:placetype":"venue"
},
  "geometry": {"coordinates":[-122.52502,38.362618],"type":"Point"}
}