{
  "type": "Feature",
  "properties": {
    "iso:country":"US",
    "sg:address":"216 E. Olive Ave.",
    "sg:city":"Burbank",
    "sg:classifiers":[
        {
            "category":"Professional",
            "subcategory":"Detective & Security Services",
            "type":"Services"
        },
        {
            "category":"Professional",
            "subcategory":"Lawyer & Legal Services",
            "type":"Services"
        }
    ],
    "sg:phone":"+1 818 691 7037",
    "sg:postcode":"91502",
    "sg:province":"CA",
    "sg:tags":[
        "referral",
        "bail",
        "bond"
    ],
    "sg:website":"http://vannuysbailbonds.org/",
    "wof:name":"24/7 Quick Bail",
    "wof:placetype":"venue"
},
  "geometry": {"coordinates":[-118.308538,34.181074],"type":"Point"}
}