{
  "type": "Feature",
  "properties": {
    "iso:country":"US",
    "sg:address":"4555 Auburn Blvd Ste D",
    "sg:city":"Sacramento",
    "sg:classifiers":[
        {
            "category":"Real Estate",
            "subcategory":"Real Estate Services",
            "type":"Services"
        },
        {
            "category":"Real Estate",
            "subcategory":"Real Estate Agent",
            "type":"Services"
        }
    ],
    "sg:phone":"+1 916 974 7688",
    "sg:postcode":"95841",
    "sg:province":"CA",
    "sg:tags":[
        "buyer",
        "broker"
    ],
    "wof:name":"Cameron Real Estate Services",
    "wof:placetype":"venue"
},
  "geometry": {"coordinates":[-121.35816800000001,38.650142],"type":"Point"}
}