{
  "type": "Feature",
  "properties": {
    "addr:full":"85 Willowood Aliso Viejo CA 92656",
    "addr:housenumber":"85",
    "addr:postcode":"92656",
    "addr:street":"Willowood",
    "iso:country":"US",
    "sg:address":"85 Willowood",
    "sg:city":"Aliso Viejo",
    "sg:classifiers":[
        {
            "category":"Professional",
            "type":"Services"
        }
    ],
    "sg:phone":"+1 949 643 0959",
    "sg:postcode":"92656",
    "sg:province":"CA",
    "wof:name":"William B Braden",
    "wof:placetype":"venue"
},
  "geometry": {"coordinates":[-117.70846400000001,33.578924],"type":"Point"}
}