{
  "type": "Feature",
  "properties": {
    "addr:full":"248 Franciscan Dr Vallejo CA 94589",
    "addr:housenumber":"248",
    "addr:postcode":"94589",
    "addr:street":"Franciscan Dr",
    "iso:country":"US",
    "sg:address":"248 Franciscan Dr",
    "sg:city":"Vallejo",
    "sg:classifiers":[
        {
            "category":"Professional",
            "subcategory":"Management & Consulting",
            "type":"Services"
        }
    ],
    "sg:phone":"+1 707 642 7789",
    "sg:postcode":"94589",
    "sg:province":"CA",
    "sg:tags":[
        "party",
        "planning"
    ],
    "wof:name":"Special Occasions By Kimberly",
    "wof:placetype":"venue"
},
  "geometry": {"coordinates":[-122.233248,38.130206],"type":"Point"}
}