{
  "type": "Feature",
  "properties": {
    "addr:full":"1074 East Ave Chico CA 95926",
    "addr:housenumber":"1074",
    "addr:postcode":"95926",
    "addr:street":"East Ave",
    "iso:country":"US",
    "sg:address":"1074 East Ave",
    "sg:city":"Chico",
    "sg:classifiers":[
        {
            "category":"Professional",
            "subcategory":"Lawyer & Legal Services",
            "type":"Services"
        }
    ],
    "sg:phone":"+1 530 342 1362",
    "sg:postcode":"95926",
    "sg:province":"CA",
    "sg:tags":[
        "attorney"
    ],
    "wof:name":"Norman J Ryker",
    "wof:placetype":"venue"
},
  "geometry": {"coordinates":[-121.83588399999999,39.760903],"type":"Point"}
}