{
  "type": "Feature",
  "properties": {
    "addr:full":"240 Broadway St Chico CA 95928",
    "addr:housenumber":"240",
    "addr:postcode":"95928",
    "addr:street":"Broadway St",
    "iso:country":"US",
    "sg:address":"240 Broadway St",
    "sg:city":"Chico",
    "sg:classifiers":[
        {
            "category":"Shopping",
            "subcategory":"Gifts & Souvenirs",
            "type":"Retail Goods"
        }
    ],
    "sg:phone":"+1 530 342 3131",
    "sg:postcode":"95928",
    "sg:province":"CA",
    "sg:tags":[
        "basket",
        "parcel"
    ],
    "wof:name":"Body & Bath",
    "wof:placetype":"venue"
},
  "geometry": {"coordinates":[-121.84077600000001,39.729262],"type":"Point"}
}