{
  "type": "Feature",
  "properties": {
    "addr:full":"436 Heliotrope Ave Corona Del Mar CA 92625",
    "addr:housenumber":"436",
    "addr:postcode":"92625",
    "addr:street":"Heliotrope Ave",
    "iso:country":"US",
    "sg:address":"436 Heliotrope Ave",
    "sg:city":"Corona Del Mar",
    "sg:classifiers":[
        {
            "category":"Retail",
            "subcategory":"Repair Shop",
            "type":"Services"
        }
    ],
    "sg:phone":"+1 949 673 8900",
    "sg:postcode":"92625",
    "sg:province":"CA",
    "wof:name":"SOStv& Video & Microwave",
    "wof:placetype":"venue"
},
  "geometry": {"coordinates":[-117.873177,33.599041],"type":"Point"}
}