{
  "type": "Feature",
  "properties": {
    "iso:country":"US",
    "sg:address":"10440 Gridley Rd",
    "sg:city":"Santa Fe Springs",
    "sg:classifiers":[
        {
            "category":"Building & Trades",
            "subcategory":"Construction",
            "type":"Services"
        }
    ],
    "sg:phone":"+1 562 868 3681",
    "sg:postcode":"90670",
    "sg:province":"CA",
    "sg:tags":[
        "contractor"
    ],
    "wof:name":"J J & Associates",
    "wof:placetype":"venue"
},
  "geometry": {"coordinates":[-118.091542,33.941867],"type":"Point"}
}