{
  "type": "Feature",
  "properties": {
    "addr:full":"10049 Viewoods Ct Sacramento CA 95827",
    "addr:housenumber":"10049",
    "addr:postcode":"95827",
    "addr:street":"Viewoods Ct",
    "iso:country":"US",
    "sg:address":"10049 Viewoods Ct",
    "sg:city":"Sacramento",
    "sg:classifiers":[
        {
            "category":"Manufacturing",
            "subcategory":"Rubber & Plastics",
            "type":"Manufacturing & Wholesale Goods"
        }
    ],
    "sg:phone":"+1 916 364 0253",
    "sg:postcode":"95827",
    "sg:province":"CA",
    "sg:tags":[
        "product",
        "mfg"
    ],
    "wof:name":"Leos Tile & Molding",
    "wof:placetype":"venue"
},
  "geometry": {"coordinates":[-121.31855899999999,38.572773],"type":"Point"}
}