{
  "type": "Feature",
  "properties": {
    "iso:country":"US",
    "sg:address":"12106 Lakewood Boulevard",
    "sg:city":"Downey",
    "sg:classifiers":[
        {
            "category":"Shopping",
            "subcategory":"Department Store",
            "type":"Retail Goods"
        }
    ],
    "sg:phone":"+1 562 803 4834",
    "sg:postcode":"90242",
    "sg:province":"CA",
    "wof:name":"Marshalls Store 0169",
    "wof:placetype":"venue"
},
  "geometry": {"coordinates":[-118.13108200000001,33.925779],"type":"Point"}
}