{
  "type": "Feature",
  "properties": {
    "addr:full":"18356 Oxnard St Tarzana CA 91356",
    "addr:housenumber":"18356",
    "addr:postcode":"91356",
    "addr:street":"Oxnard St",
    "iso:country":"US",
    "sg:address":"18356 Oxnard St",
    "sg:city":"Tarzana",
    "sg:classifiers":[
        {
            "category":"Personal",
            "type":"Services"
        }
    ],
    "sg:phone":"+1 818 996 9701",
    "sg:postcode":"91356",
    "sg:province":"CA",
    "sg:tags":[
        "hair",
        "replacement"
    ],
    "wof:name":"Hair For Guys Inc",
    "wof:placetype":"venue"
},
  "geometry": {"coordinates":[-118.53479400000001,34.17993],"type":"Point"}
}