{
  "type": "Feature",
  "properties": {
    "addr:full":"1087 Meridian Ave San Jose CA 95125",
    "addr:housenumber":"1087",
    "addr:postcode":"95125",
    "addr:street":"Meridian Ave",
    "iso:country":"US",
    "sg:address":"1087 Meridian Ave",
    "sg:city":"San Jose",
    "sg:classifiers":[
        {
            "category":"Restaurant",
            "type":"Food & Drink"
        }
    ],
    "sg:phone":"+1 408 723 1425",
    "sg:postcode":"95125",
    "sg:province":"CA",
    "sg:tags":[
        "shop",
        "tea",
        "coffee"
    ],
    "sg:website":"www.starbucks.com",
    "wof:name":"Starbucks",
    "wof:placetype":"venue"
},
  "geometry": {"coordinates":[-121.914062,37.304418],"type":"Point"}
}