{
  "type": "Feature",
  "properties": {
    "iso:country":"US",
    "sg:address":"635 Oxford St",
    "sg:city":"Chula Vista",
    "sg:classifiers":[
        {
            "category":"Shopping",
            "subcategory":"Discount & Variety Stores",
            "type":"Retail Goods"
        }
    ],
    "sg:phone":"+1 619 425 7669",
    "sg:postcode":"91911",
    "sg:province":"CA",
    "wof:name":"Dollar Club",
    "wof:placetype":"venue"
},
  "geometry": {"coordinates":[-117.083756,32.605733],"type":"Point"}
}