{
  "type": "Feature",
  "properties": {
    "iso:country":"US",
    "sg:address":"400 E Esplanade Ave",
    "sg:city":"San Jacinto",
    "sg:classifiers":[
        {
            "category":"Restaurant",
            "type":"Food & Drink"
        }
    ],
    "sg:phone":"+1 951 654 5988",
    "sg:postcode":"92583",
    "sg:province":"CA",
    "wof:name":"Buffet City",
    "wof:placetype":"venue"
},
  "geometry": {"coordinates":[-116.95099399999999,33.772323],"type":"Point"}
}