{
  "type": "Feature",
  "properties": {
    "iso:country":"US",
    "sg:address":"355 S Grand Ave",
    "sg:city":"Los Angeles",
    "sg:classifiers":[
        {
            "category":"Professional",
            "subcategory":"Computer Services",
            "type":"Services"
        }
    ],
    "sg:phone":"+1 213 625 7636",
    "sg:postcode":"90071",
    "sg:province":"CA",
    "sg:tags":[
        "graphics"
    ],
    "sg:website":"www.engineeringsys.com",
    "wof:name":"Engineering Systems",
    "wof:placetype":"venue"
},
  "geometry": {"coordinates":[-118.252481,34.051783],"type":"Point"}
}