{
  "type": "Feature",
  "properties": {
    "iso:country":"US",
    "sg:address":"1235 N Harbor Blvd",
    "sg:city":"Fullerton",
    "sg:classifiers":[
        {
            "category":"Health Services",
            "subcategory":"Doctor",
            "type":"Services"
        }
    ],
    "sg:phone":"+1 949 347 6777",
    "sg:postcode":"92832",
    "sg:province":"CA",
    "sg:tags":[
        "medical"
    ],
    "wof:name":"Tiffany U Tran MD Inc",
    "wof:placetype":"venue"
},
  "geometry": {"coordinates":[-117.92468700000001,33.881818],"type":"Point"}
}