{
  "type": "Feature",
  "properties": {
    "addr:full":"8902 Woodman Ave Arleta CA 91331",
    "addr:housenumber":"8902",
    "addr:postcode":"91331",
    "addr:street":"Woodman Ave",
    "iso:country":"US",
    "sg:address":"8902 Woodman Ave",
    "sg:city":"Arleta",
    "sg:classifiers":[
        {
            "category":"Health Services",
            "subcategory":"Doctor",
            "type":"Services"
        }
    ],
    "sg:phone":"+1 818 830 7080",
    "sg:postcode":"91331",
    "sg:province":"CA",
    "sg:tags":[
        "medical",
        "agency",
        "employment"
    ],
    "wof:name":"El Proyecto Del Barrio, Inc",
    "wof:placetype":"venue"
},
  "geometry": {"coordinates":[-118.43758,34.231507],"type":"Point"}
}