{
  "type": "Feature",
  "properties": {
    "iso:country":"US",
    "sg:address":"17100 Pioneer Blvd Ste 300",
    "sg:city":"Artesia",
    "sg:classifiers":[
        {
            "category":"Health Services",
            "subcategory":"Hospital",
            "type":"Services"
        }
    ],
    "sg:phone":"+1 562 916 7487",
    "sg:postcode":"90701",
    "sg:province":"CA",
    "wof:name":"Aspen Youth Services",
    "wof:placetype":"venue"
},
  "geometry": {"coordinates":[-118.080002,33.867199],"type":"Point"}
}