{
  "type": "Feature",
  "properties": {
    "addr:full":"18010 Kimberly Sue Ct Lake Elsinore CA 92532",
    "addr:housenumber":"18010",
    "addr:postcode":"92532",
    "addr:street":"Kimberly Sue Ct",
    "iso:country":"US",
    "sg:address":"18010 Kimberly Sue Ct",
    "sg:city":"Lake Elsinore",
    "sg:classifiers":[
        {
            "category":"Building & Trades",
            "subcategory":"Landscaping Services",
            "type":"Services"
        }
    ],
    "sg:phone":"+1 951 678 6213",
    "sg:postcode":"92532",
    "sg:province":"CA",
    "sg:tags":[
        "landscape",
        "contractor"
    ],
    "wof:name":"Curb Guy Custom Landscape",
    "wof:placetype":"venue"
},
  "geometry": {"coordinates":[-117.34558699999999,33.701546],"type":"Point"}
}