{
  "type": "Feature",
  "properties": {
    "addr:full":"5407 E Olive Ave Fresno CA 93727",
    "addr:housenumber":"5407",
    "addr:postcode":"93727",
    "addr:street":"E Olive Ave",
    "iso:country":"US",
    "sg:address":"5407 E Olive Ave",
    "sg:city":"Fresno",
    "sg:classifiers":[
        {
            "category":"Organizations",
            "subcategory":"Community Association",
            "type":"Services"
        }
    ],
    "sg:phone":"+1 559 251 1991",
    "sg:postcode":"93727",
    "sg:province":"CA",
    "sg:tags":[
        "fraternal"
    ],
    "wof:name":"Tehran Shrine Ctr",
    "wof:placetype":"venue"
},
  "geometry": {"coordinates":[-119.706293,36.757512],"type":"Point"}
}