{
  "type": "Feature",
  "properties": {
    "iso:country":"US",
    "sg:address":"519 Pine Ave",
    "sg:city":"Holtville",
    "sg:classifiers":[
        {
            "category":"Shopping",
            "subcategory":"Used Merchandise",
            "type":"Retail Goods"
        }
    ],
    "sg:phone":"+1 760 356 5994",
    "sg:postcode":"92250",
    "sg:province":"CA",
    "wof:name":"Special Memories",
    "wof:placetype":"venue"
},
  "geometry": {"coordinates":[-115.381486,32.812487],"type":"Point"}
}