{
  "type": "Feature",
  "properties": {
    "addr:full":"1905 Arnold Industrial Way Ste C Concord CA 94520",
    "addr:housenumber":"1905",
    "addr:postcode":"94520",
    "addr:street":"Arnold Industrial Way Ste C",
    "iso:country":"US",
    "sg:address":"1905 Arnold Industrial Way Ste C",
    "sg:city":"Concord",
    "sg:classifiers":[
        {
            "category":"Autos & Motor Vehicles",
            "subcategory":"Motorcycle Sales",
            "type":"Retail Goods"
        },
        {
            "category":"Retail",
            "subcategory":"Auto Repair",
            "type":"Services"
        }
    ],
    "sg:phone":"+1 925 798 4360",
    "sg:postcode":"94520",
    "sg:province":"CA",
    "sg:tags":[
        "scooters-repairing",
        "scooters-parts",
        "supply"
    ],
    "sg:website":"http://www.rm-motorsports.com",
    "wof:name":"R & M Enterprise",
    "wof:placetype":"venue"
},
  "geometry": {"coordinates":[-122.04620300000001,38.00326],"type":"Point"}
}