{
  "type": "Feature",
  "properties": {
    "addr:full":"1237 Linda Mar Blvd Pacifica CA 94044",
    "addr:housenumber":"1237",
    "addr:postcode":"94044",
    "addr:street":"Linda Mar Blvd",
    "iso:country":"US",
    "sg:address":"1237 Linda Mar Blvd",
    "sg:city":"Pacifica",
    "sg:classifiers":[
        {
            "category":"Food & Beverages",
            "subcategory":"Specialty",
            "type":"Retail Goods"
        }
    ],
    "sg:phone":"+1 650 355 5002",
    "sg:postcode":"94044",
    "sg:province":"CA",
    "sg:tags":[
        "health",
        "diet"
    ],
    "wof:name":"General Nutrition Ctr",
    "wof:placetype":"venue"
},
  "geometry": {"coordinates":[-122.486176,37.58415],"type":"Point"}
}