{
  "type": "Feature",
  "properties": {
    "addr:full":"1400 Karenell Ct Ceres CA 95307",
    "addr:housenumber":"1400",
    "addr:postcode":"95307",
    "addr:street":"Karenell Ct",
    "iso:country":"US",
    "sg:address":"1400 Karenell Ct",
    "sg:city":"Ceres",
    "sg:classifiers":[
        {
            "category":"Fast Food",
            "type":"Food & Drink"
        },
        {
            "category":"Restaurant",
            "type":"Food & Drink"
        }
    ],
    "sg:phone":"+1 209 538 6146",
    "sg:postcode":"95307",
    "sg:province":"CA",
    "wof:name":"Bbh Snack Masters",
    "wof:placetype":"venue"
},
  "geometry": {"coordinates":[-120.97165699999999,37.58894],"type":"Point"}
}