{
  "type": "Feature",
  "properties": {
    "iso:country":"US",
    "sg:address":"75 Pelican Way",
    "sg:city":"San Rafael",
    "sg:classifiers":[
        {
            "category":"Shopping",
            "type":"Retail Goods"
        }
    ],
    "sg:phone":"+1 415 215 8844",
    "sg:postcode":"94901",
    "sg:province":"CA",
    "sg:tags":[
        "miscellaneous",
        "store"
    ],
    "wof:name":"Sun Enterprises",
    "wof:placetype":"venue"
},
  "geometry": {"coordinates":[-122.492864,37.949143],"type":"Point"}
}