{
  "type": "Feature",
  "properties": {
    "addr:full":"8131 Atwater Cir Ste 102 Huntington Beach CA 92646",
    "addr:housenumber":"8131",
    "addr:postcode":"92646",
    "addr:street":"Atwater Cir Ste 102",
    "iso:country":"US",
    "sg:address":"8131 Atwater Cir Ste 102",
    "sg:city":"Huntington Beach",
    "sg:classifiers":[
        {
            "category":"Building & Trades",
            "subcategory":"Plumbing",
            "type":"Services"
        }
    ],
    "sg:phone":"+1 714 336 5076",
    "sg:postcode":"92646",
    "sg:province":"CA",
    "wof:name":"Just In Time Plumbing",
    "wof:placetype":"venue"
},
  "geometry": {"coordinates":[-117.984182,33.671914],"type":"Point"}
}