{
  "type": "Feature",
  "properties": {
    "addr:full":"4827 Laguna Park Dr Elk Grove CA 95758",
    "addr:housenumber":"4827",
    "addr:postcode":"95758",
    "addr:street":"Laguna Park Dr",
    "iso:country":"US",
    "sg:address":"4827 Laguna Park Dr",
    "sg:city":"Elk Grove",
    "sg:classifiers":[
        {
            "category":"Health Services",
            "subcategory":"Doctor",
            "type":"Services"
        }
    ],
    "sg:phone":"+1 916 392 1885",
    "sg:postcode":"95758",
    "sg:province":"CA",
    "sg:tags":[
        "dentist"
    ],
    "wof:name":"Mark S Douglas PC",
    "wof:placetype":"venue"
},
  "geometry": {"coordinates":[-121.44701499999999,38.42866],"type":"Point"}
}