{
  "type": "Feature",
  "properties": {
    "addr:full":"200 S Ave 19 Los Angeles CA 90031",
    "addr:housenumber":"200;19",
    "addr:postcode":"90031",
    "addr:street":"S Ave",
    "iso:country":"US",
    "sg:address":"200 S Ave 19",
    "sg:city":"Los Angeles",
    "sg:classifiers":[
        {
            "category":"Restaurant",
            "type":"Food & Drink"
        }
    ],
    "sg:phone":"+1 323 225 2163",
    "sg:postcode":"90031",
    "sg:province":"CA",
    "sg:tags":[
        "american",
        "latin"
    ],
    "wof:name":"Maya's Restaurant",
    "wof:placetype":"venue"
},
  "geometry": {"coordinates":[-118.221261,34.072127],"type":"Point"}
}