{
  "type": "Feature",
  "properties": {
    "addr:full":"1557 4th St Alameda CA 94501",
    "addr:housenumber":"1557",
    "addr:postcode":"94501",
    "addr:street":"4Th St",
    "iso:country":"US",
    "sg:address":"1557 4th St",
    "sg:city":"Alameda",
    "sg:classifiers":[
        {
            "category":"Shopping",
            "subcategory":"Hobbies, Toys, & Games",
            "type":"Retail Goods"
        }
    ],
    "sg:phone":"+1 510 522 2404",
    "sg:postcode":"94501",
    "sg:province":"CA",
    "sg:tags":[
        "toy",
        "store",
        "supply"
    ],
    "wof:name":"Happy Hunting",
    "wof:placetype":"venue"
},
  "geometry": {"coordinates":[-122.28588999999999,37.774825],"type":"Point"}
}