{
  "type": "Feature",
  "properties": {
    "addr:full":"4210 Petaluma Blvd N Petaluma CA 94952",
    "addr:housenumber":"4210",
    "addr:postcode":"94952",
    "addr:street":"Petaluma Blvd N",
    "iso:country":"US",
    "sg:address":"4210 Petaluma Blvd N",
    "sg:city":"Petaluma",
    "sg:classifiers":[
        {
            "category":"Organizations",
            "subcategory":"Labor Organization",
            "type":"Services"
        }
    ],
    "sg:phone":"+1 707 795 0085",
    "sg:postcode":"94952",
    "sg:province":"CA",
    "wof:name":"Machinists Union Intl Assn",
    "wof:placetype":"venue"
},
  "geometry": {"coordinates":[-122.669571,38.265495],"type":"Point"}
}