{
  "type": "Feature",
  "properties": {
    "iso:country":"US",
    "sg:address":"8830 Garfield Ave",
    "sg:city":"South Gate",
    "sg:classifiers":[
        {
            "category":"Shopping",
            "subcategory":"Shoes",
            "type":"Retail Goods"
        }
    ],
    "sg:phone":"+1 562 806 6701",
    "sg:postcode":"90280",
    "sg:province":"CA",
    "sg:tags":[
        "store"
    ],
    "sg:website":"www.warehouseshoesale.com",
    "wof:name":"Warehouse Shoe Sale",
    "wof:placetype":"venue"
},
  "geometry": {"coordinates":[-118.165001,33.9501],"type":"Point"}
}