{
  "type": "Feature",
  "properties": {
    "iso:country":"US",
    "sg:address":"28 Fairway Dr",
    "sg:city":"San Rafael",
    "sg:classifiers":[
        {
            "category":"Professional",
            "subcategory":"Business Services",
            "type":"Services"
        }
    ],
    "sg:phone":"+1 415 453 1133",
    "sg:postcode":"94901",
    "sg:province":"CA",
    "sg:tags":[
        "interior",
        "consultant",
        "design",
        "decorator"
    ],
    "wof:name":"Mari Jon Di Basilio Interior",
    "wof:placetype":"venue"
},
  "geometry": {"coordinates":[-122.50290200000001,37.977816],"type":"Point"}
}