{
  "type": "Feature",
  "properties": {
    "addr:full":"2169a Pacific Coast Hwy Lomita CA 90717",
    "addr:housenumber":"2169a",
    "addr:postcode":"90717",
    "addr:street":"Pacific Coast Hwy",
    "iso:country":"US",
    "sg:address":"2169a Pacific Coast Hwy",
    "sg:city":"Lomita",
    "sg:classifiers":[
        {
            "category":"Restaurant",
            "type":"Food & Drink"
        }
    ],
    "sg:menulink":"http://www.allmenus.com/ca/palos-verdes/123511-quiznos-sub/menu/",
    "sg:phone":"+1 310 530 0441",
    "sg:postcode":"90717",
    "sg:province":"CA",
    "sg:tags":[
        "wrap",
        "american",
        "sandwich"
    ],
    "wof:name":"Quiznos Sub",
    "wof:placetype":"venue"
},
  "geometry": {"coordinates":[-118.319547,33.78952],"type":"Point"}
}