{
  "type": "Feature",
  "properties": {
    "addr:full":"555 Peters Ave Pleasanton CA 94566",
    "addr:housenumber":"555",
    "addr:postcode":"94566",
    "addr:street":"Peters Ave",
    "iso:country":"US",
    "sg:address":"555 Peters Ave",
    "sg:city":"Pleasanton",
    "sg:classifiers":[
        {
            "category":"Building & Trades",
            "subcategory":"Plumbing",
            "type":"Services"
        }
    ],
    "sg:phone":"+1 408 266 5464",
    "sg:postcode":"94566",
    "sg:province":"CA",
    "sg:tags":[
        "conditioning",
        "air",
        "system",
        "contractor"
    ],
    "wof:name":"Flanders Heat & Air Systems",
    "wof:placetype":"venue"
},
  "geometry": {"coordinates":[-121.876808,37.66135],"type":"Point"}
}