{
  "type": "Feature",
  "properties": {
    "addr:full":"1911 Lawton St San Francisco CA 94122",
    "addr:housenumber":"1911",
    "addr:postcode":"94122",
    "addr:street":"Lawton St",
    "iso:country":"US",
    "sg:address":"1911 Lawton St",
    "sg:city":"San Francisco",
    "sg:classifiers":[
        {
            "category":"Personal",
            "subcategory":"Beauty Salon",
            "type":"Services"
        }
    ],
    "sg:phone":"+1 415 664 7568",
    "sg:postcode":"94122",
    "sg:province":"CA",
    "wof:name":"Sunset Beauty Salon",
    "wof:placetype":"venue"
},
  "geometry": {"coordinates":[-122.484143,37.757566],"type":"Point"}
}