{
  "type": "Feature",
  "properties": {
    "addr:full":"47800 Madison St Indio CA 92201",
    "addr:housenumber":"47800",
    "addr:postcode":"92201",
    "addr:street":"Madison St",
    "iso:country":"US",
    "sg:address":"47800 Madison St",
    "sg:city":"Indio",
    "sg:classifiers":[
        {
            "category":"Shopping",
            "subcategory":"Bicycles & Sporting Goods",
            "type":"Retail Goods"
        }
    ],
    "sg:phone":"+1 760 342 4056",
    "sg:postcode":"92201",
    "sg:province":"CA",
    "wof:name":"Paintball Steve",
    "wof:placetype":"venue"
},
  "geometry": {"coordinates":[-116.251283,33.701324],"type":"Point"}
}