{
  "type": "Feature",
  "properties": {
    "addr:full":"13738 Hanford Armona Rd Hanford CA 93230",
    "addr:housenumber":"13738",
    "addr:postcode":"ca 93230",
    "addr:street":"Hanford Armona Rd",
    "iso:country":"US",
    "sg:address":"13738 Hanford Armona Rd",
    "sg:city":"Hanford",
    "sg:classifiers":[
        {
            "category":"Retail",
            "subcategory":"Auto Repair",
            "type":"Services"
        }
    ],
    "sg:phone":"+1 559 582 4181",
    "sg:postcode":"93230",
    "sg:province":"CA",
    "sg:tags":[
        "wrecker"
    ],
    "wof:name":"J & D Joshua's Towing",
    "wof:placetype":"venue"
},
  "geometry": {"coordinates":[-119.704756,36.313554],"type":"Point"}
}