{
  "type": "Feature",
  "properties": {
    "iso:country":"US",
    "sg:address":"255 S San Gabriel Blvd",
    "sg:city":"San Gabriel",
    "sg:classifiers":[
        {
            "category":"Home & Garden",
            "subcategory":"Furniture",
            "type":"Retail Goods"
        }
    ],
    "sg:phone":"+1 626 286 6788",
    "sg:postcode":"91776",
    "sg:province":"CA",
    "wof:name":"House Of Oriental Furniture",
    "wof:placetype":"venue"
},
  "geometry": {"coordinates":[-118.091016,34.099308],"type":"Point"}
}