{
  "type": "Feature",
  "properties": {
    "addr:full":"268 Bush Street San Francisco CA 94104",
    "addr:housenumber":"268",
    "addr:postcode":"94104",
    "addr:street":"Bush Street",
    "iso:country":"US",
    "sg:address":"268 Bush Street",
    "sg:city":"San Francisco",
    "sg:classifiers":[
        {
            "category":"Communications",
            "subcategory":"Newspaper",
            "type":"Services"
        }
    ],
    "sg:postcode":"94104",
    "sg:province":"CA",
    "sg:tags":[
        "print",
        "medium"
    ],
    "sg:website":"www.neubauerandassociates.com/Co...",
    "wof:name":"Neubauer And Associates Plantiff Magazine",
    "wof:placetype":"venue"
},
  "geometry": {"coordinates":[-122.401663,37.791085],"type":"Point"}
}