{
  "type": "Feature",
  "properties": {
    "addr:full":"2138 4th St San Rafael CA 94901",
    "addr:housenumber":"2138",
    "addr:postcode":"94901",
    "addr:street":"4Th St",
    "iso:country":"US",
    "sg:address":"2138 4th St",
    "sg:city":"San Rafael",
    "sg:classifiers":[
        {
            "category":"Food & Beverages",
            "subcategory":"Liquor & Beverages",
            "type":"Retail Goods"
        }
    ],
    "sg:phone":"+1 415 456 9463",
    "sg:postcode":"94901",
    "sg:province":"CA",
    "sg:tags":[
        "wine"
    ],
    "sg:website":"www.marinwinecellar.com",
    "wof:name":"Marin Wine Cellar",
    "wof:placetype":"venue"
},
  "geometry": {"coordinates":[-122.548143,37.975933],"type":"Point"}
}