{
  "type": "Feature",
  "properties": {
    "iso:country":"US",
    "sg:address":"3845 5th Ave",
    "sg:city":"San Diego",
    "sg:classifiers":[
        {
            "category":"Bars & Pubs",
            "type":"Food & Drink"
        }
    ],
    "sg:phone":"+1 619 299 1911",
    "sg:postcode":"92103",
    "sg:province":"CA",
    "sg:tags":[
        "gay"
    ],
    "wof:name":"Number One Fifth Avenue",
    "wof:placetype":"venue"
},
  "geometry": {"coordinates":[-117.16100299999999,32.747398],"type":"Point"}
}