{
  "type": "Feature",
  "properties": {
    "iso:country":"US",
    "sg:address":"1219 17th St",
    "sg:city":"Sacramento",
    "sg:classifiers":[
        {
            "category":"Cinema",
            "subcategory":"Movie Theater",
            "type":"Entertainment"
        }
    ],
    "sg:phone":"+1 916 447 8862",
    "sg:postcode":"95811",
    "sg:province":"CA",
    "sg:tags":[
        "theatrical",
        "consultant"
    ],
    "wof:name":"Fahn & Company Inc",
    "wof:placetype":"venue"
},
  "geometry": {"coordinates":[-121.484922,38.575356],"type":"Point"}
}