{
  "type": "Feature",
  "properties": {
    "addr:full":"8548 Mosquito Rd Placerville CA 95667",
    "addr:housenumber":"8548",
    "addr:postcode":"95667",
    "addr:street":"Mosquito Rd",
    "iso:country":"US",
    "sg:address":"8548 Mosquito Rd",
    "sg:city":"Placerville",
    "sg:classifiers":[
        {
            "category":"Farming",
            "subcategory":"Vineyard",
            "type":"Manufacturing & Wholesale Goods"
        }
    ],
    "sg:phone":"+1 530 622 8315",
    "sg:postcode":"95667",
    "sg:province":"CA",
    "sg:tags":[
        "grape"
    ],
    "wof:name":"Robert Scharpf",
    "wof:placetype":"venue"
},
  "geometry": {"coordinates":[-120.759331,38.766858],"type":"Point"}
}