{
  "type": "Feature",
  "properties": {
    "iso:country":"US",
    "sg:address":"901 P St",
    "sg:city":"Sacramento",
    "sg:classifiers":[
        {
            "category":"Professional",
            "subcategory":"Management & Consulting",
            "type":"Services"
        }
    ],
    "sg:phone":"+1 916 657 2397",
    "sg:postcode":"95814",
    "sg:province":"CA",
    "sg:tags":[
        "testing"
    ],
    "wof:name":"Water Rsurces Ctrl Bd Tstg Off",
    "wof:placetype":"venue"
},
  "geometry": {"coordinates":[-121.496342,38.573671],"type":"Point"}
}