{
  "type": "Feature",
  "properties": {
    "iso:country":"US",
    "sg:address":"2675 Irvine Ave",
    "sg:city":"Costa Mesa",
    "sg:classifiers":[
        {
            "category":"Sports & Exercise",
            "subcategory":"Gym",
            "type":"Entertainment"
        }
    ],
    "sg:phone":"+1 949 378 4280",
    "sg:postcode":"92627",
    "sg:province":"CA",
    "sg:tags":[
        "trainer"
    ],
    "sg:website":"trufkinathletics.com",
    "wof:name":"Trufkin Athletics",
    "wof:placetype":"venue"
},
  "geometry": {"coordinates":[-117.886713,33.656366],"type":"Point"}
}