{
  "type": "Feature",
  "properties": {
    "addr:full":"763 S Main St Ste 200 Orange CA 92868",
    "addr:housenumber":"763",
    "addr:postcode":"92868",
    "addr:street":"S Main St Ste 200",
    "iso:country":"US",
    "sg:address":"763 S Main St Ste 200",
    "sg:city":"Orange",
    "sg:classifiers":[
        {
            "category":"Restaurant",
            "type":"Food & Drink"
        }
    ],
    "sg:phone":"+1 714 836 5500",
    "sg:postcode":"92868",
    "sg:province":"CA",
    "sg:tags":[
        "traditional",
        "american"
    ],
    "sg:website":"www.patandoscars.com",
    "wof:name":"Pat & Oscar's",
    "wof:placetype":"venue"
},
  "geometry": {"coordinates":[-117.86559200000001,33.77563],"type":"Point"}
}