{
  "type": "Feature",
  "properties": {
    "addr:full":"6114 La Salle Ave #724 Oakland CA 94611",
    "addr:housenumber":"6114",
    "addr:postcode":"94611",
    "addr:street":"La Salle Ave # 724",
    "iso:country":"US",
    "sg:address":"6114 La Salle Ave #724",
    "sg:city":"Oakland",
    "sg:classifiers":[
        {
            "category":"Personal",
            "type":"Services"
        }
    ],
    "sg:phone":"+1 510 281 1917",
    "sg:postcode":"94611",
    "sg:province":"CA",
    "sg:tags":[
        "towing"
    ],
    "sg:website":"www.theautotowing.com/Oakland/",
    "wof:name":"Auto Towing",
    "wof:placetype":"venue"
},
  "geometry": {"coordinates":[-122.210071,37.826436],"type":"Point"}
}