{
  "type": "Feature",
  "properties": {
    "iso:country":"US",
    "sg:address":"255 Cerro Dr",
    "sg:city":"Daly City",
    "sg:classifiers":[
        {
            "category":"Real Estate",
            "subcategory":"Real Estate Agent",
            "type":"Services"
        }
    ],
    "sg:phone":"+1 650 755 5870",
    "sg:postcode":"94015",
    "sg:province":"CA",
    "sg:tags":[
        "finding",
        "apartment",
        "rental"
    ],
    "wof:name":"A V Rental Svc",
    "wof:placetype":"venue"
},
  "geometry": {"coordinates":[-122.477221,37.672964],"type":"Point"}
}