{
  "type": "Feature",
  "properties": {
    "addr:full":"10 S Park Ave San Francisco CA 94107",
    "addr:housenumber":"10",
    "addr:postcode":"94107",
    "addr:street":"S Park Ave",
    "iso:country":"US",
    "sg:address":"10 S Park Ave",
    "sg:city":"San Francisco",
    "sg:classifiers":[
        {
            "category":"Building & Trades",
            "subcategory":"Construction",
            "type":"Services"
        }
    ],
    "sg:phone":"+1 415 546 6919",
    "sg:postcode":"94107",
    "sg:province":"CA",
    "sg:tags":[
        "designer"
    ],
    "wof:name":"Summit Id",
    "wof:placetype":"venue"
},
  "geometry": {"coordinates":[-122.393265,37.782225],"type":"Point"}
}