{
  "type": "Feature",
  "properties": {
    "iso:country":"US",
    "sg:address":"1715 E 28th St",
    "sg:city":"Signal Hill",
    "sg:classifiers":[
        {
            "category":"Professional",
            "subcategory":"Testing Lab",
            "type":"Services"
        }
    ],
    "sg:phone":"+1 562 988 9592",
    "sg:postcode":"90755",
    "sg:province":"CA",
    "sg:tags":[
        "calibration"
    ],
    "wof:name":"Accurate Cal Labs",
    "wof:placetype":"venue"
},
  "geometry": {"coordinates":[-118.169945,33.808125],"type":"Point"}
}