{
  "type": "Feature",
  "properties": {
    "addr:full":"1547 W H St Ontario CA 91762",
    "addr:housenumber":"1547",
    "addr:postcode":"91762",
    "addr:street":"W H St",
    "iso:country":"US",
    "sg:address":"1547 W H St",
    "sg:city":"Ontario",
    "sg:classifiers":[
        {
            "category":"Freight",
            "type":"Transportation"
        }
    ],
    "sg:phone":"+1 909 984 0934",
    "sg:postcode":"91762",
    "sg:province":"CA",
    "sg:tags":[
        "trucking"
    ],
    "wof:name":"Ben's Trucking",
    "wof:placetype":"venue"
},
  "geometry": {"coordinates":[-117.68060199999999,34.07267],"type":"Point"}
}