{
  "type": "Feature",
  "properties": {
    "addr:full":"414 South Western Avenue Los Angeles CA 90020",
    "addr:housenumber":"414",
    "addr:postcode":"90020",
    "addr:street":"South Western Avenue",
    "iso:country":"US",
    "sg:address":"414 South Western Avenue",
    "sg:city":"Los Angeles",
    "sg:classifiers":[
        {
            "category":"Coffee & Tea",
            "type":"Food & Drink"
        }
    ],
    "sg:phone":"+1 213 382 0309",
    "sg:postcode":"90020",
    "sg:province":"CA",
    "wof:name":"Anytime Coffee",
    "wof:placetype":"venue"
},
  "geometry": {"coordinates":[-118.308705,34.066604],"type":"Point"}
}