{
  "type": "Feature",
  "properties": {
    "iso:country":"US",
    "sg:address":"10712 Avalon Blvd",
    "sg:city":"Los Angeles",
    "sg:classifiers":[
        {
            "category":"Food & Beverages",
            "subcategory":"Liquor & Beverages",
            "type":"Retail Goods"
        }
    ],
    "sg:phone":"+1 323 757 5341",
    "sg:postcode":"90061",
    "sg:province":"CA",
    "sg:tags":[
        "beer",
        "spirit",
        "wine"
    ],
    "wof:name":"F & C Liquor No 2",
    "wof:placetype":"venue"
},
  "geometry": {"coordinates":[-118.264999,33.9389],"type":"Point"}
}