{
  "type": "Feature",
  "properties": {
    "addr:full":"351 S Hill St Los Angeles CA 90013",
    "addr:housenumber":"351",
    "addr:postcode":"90013",
    "addr:street":"S Hill St",
    "iso:country":"US",
    "sg:address":"351 S Hill St",
    "sg:city":"Los Angeles",
    "sg:classifiers":[
        {
            "category":"Railroad",
            "type":"Transportation"
        }
    ],
    "sg:phone":"+1 213 626 1901",
    "sg:postcode":"90013",
    "sg:province":"CA",
    "sg:tags":[
        "building",
        "landmark",
        "historical"
    ],
    "sg:website":"angelsflight.com/",
    "wof:name":"Angels Flight Railway",
    "wof:placetype":"venue"
},
  "geometry": {"coordinates":[-118.249776,34.050939],"type":"Point"}
}