{
  "type": "Feature",
  "properties": {
    "iso:country":"US",
    "sg:address":"317 S Broadway",
    "sg:city":"Los Angeles",
    "sg:classifiers":[
        {
            "category":"Building & Trades",
            "subcategory":"Construction",
            "type":"Services"
        }
    ],
    "sg:phone":"+1 626 688 3294",
    "sg:postcode":"90013",
    "sg:province":"CA",
    "sg:tags":[
        "painter"
    ],
    "sg:website":"www.thelosangelespainters.com",
    "wof:name":"The Los Angeles Painters",
    "wof:placetype":"venue"
},
  "geometry": {"coordinates":[-118.248494,34.050499],"type":"Point"}
}