{
  "type": "Feature",
  "properties": {
    "addr:full":"173 E College St Covina CA 91723",
    "addr:housenumber":"173",
    "addr:postcode":"91723",
    "addr:street":"E College St",
    "iso:country":"US",
    "sg:address":"173 E College St",
    "sg:city":"Covina",
    "sg:classifiers":[
        {
            "category":"Professional",
            "subcategory":"Secretarial Services",
            "type":"Services"
        }
    ],
    "sg:phone":"+1 626 966 0942",
    "sg:postcode":"91723",
    "sg:province":"CA",
    "sg:tags":[
        "transcription",
        "medical"
    ],
    "wof:name":"Dyviniak Word Processing Svc",
    "wof:placetype":"venue"
},
  "geometry": {"coordinates":[-117.889488,34.087535],"type":"Point"}
}