{
  "type": "Feature",
  "properties": {
    "iso:country":"US",
    "sg:address":"143 W Walnut Ave",
    "sg:city":"Visalia",
    "sg:classifiers":[
        {
            "category":"Professional",
            "subcategory":"Computer Services",
            "type":"Services"
        }
    ],
    "sg:phone":"+1 559 741 0181",
    "sg:postcode":"93277",
    "sg:province":"CA",
    "sg:tags":[
        "repair"
    ],
    "wof:name":"Wow Complete Enterprises",
    "wof:placetype":"venue"
},
  "geometry": {"coordinates":[-119.29252,36.312782],"type":"Point"}
}