{
  "type": "Feature",
  "properties": {
    "addr:full":"4786 County Rd E Orland CA 95963",
    "addr:housenumber":"4786",
    "addr:postcode":"95963",
    "addr:street":"County Rd E",
    "iso:country":"US",
    "sg:address":"4786 County Rd E",
    "sg:city":"Orland",
    "sg:classifiers":[
        {
            "category":"Real Estate",
            "subcategory":"Real Estate Operator",
            "type":"Services"
        }
    ],
    "sg:phone":"+1 530 865 1368",
    "sg:postcode":"95963",
    "sg:province":"CA",
    "sg:tags":[
        "apartment"
    ],
    "wof:name":"Stonecreek Ranch",
    "wof:placetype":"venue"
},
  "geometry": {"coordinates":[-122.238602,39.775931],"type":"Point"}
}