{
  "type": "Feature",
  "properties": {
    "addr:full":"111 W Washington Ave El Cajon CA 92020",
    "addr:housenumber":"111",
    "addr:postcode":"92020",
    "addr:street":"W Washington Ave",
    "iso:country":"US",
    "sg:address":"111 W Washington Ave",
    "sg:city":"El Cajon",
    "sg:classifiers":[
        {
            "category":"Restaurant",
            "type":"Food & Drink"
        }
    ],
    "sg:phone":"+1 619 442 3614",
    "sg:postcode":"92020",
    "sg:province":"CA",
    "sg:tags":[
        "mexican"
    ],
    "wof:name":"Norberto's Taco Shop",
    "wof:placetype":"venue"
},
  "geometry": {"coordinates":[-116.96294,32.787664],"type":"Point"}
}