{
  "type": "Feature",
  "properties": {
    "addr:full":"1000 Lincoln Rd Yuba City CA 95991",
    "addr:housenumber":"1000",
    "addr:postcode":"95991",
    "addr:street":"Lincoln Rd",
    "iso:country":"US",
    "sg:address":"1000 Lincoln Rd",
    "sg:city":"Yuba City",
    "sg:classifiers":[
        {
            "category":"Retail",
            "subcategory":"Laundry & Dry Cleaning",
            "type":"Services"
        }
    ],
    "sg:phone":"+1 530 751 3939",
    "sg:postcode":"95991",
    "sg:province":"CA",
    "sg:tags":[
        "cleaners"
    ],
    "wof:name":"Jilian's Cleaners",
    "wof:placetype":"venue"
},
  "geometry": {"coordinates":[-121.629949,39.1127],"type":"Point"}
}