{
  "type": "Feature",
  "properties": {
    "iso:country":"US",
    "sg:address":"424 Manzanita Ave",
    "sg:city":"Ventura",
    "sg:classifiers":[
        {
            "category":"Professional",
            "subcategory":"Business Services",
            "type":"Services"
        }
    ],
    "sg:phone":"+1 805 653 7206",
    "sg:postcode":"93001",
    "sg:province":"CA",
    "sg:tags":[
        "broker"
    ],
    "wof:name":"Sunbelt Business Brokers",
    "wof:placetype":"venue"
},
  "geometry": {"coordinates":[-119.276122,34.286782],"type":"Point"}
}