{
  "type": "Feature",
  "properties": {
    "iso:country":"US",
    "sg:address":"1317 D St Exn",
    "sg:city":"Petaluma",
    "sg:classifiers":[
        {
            "category":"Building & Trades",
            "subcategory":"Electrical",
            "type":"Services"
        }
    ],
    "sg:phone":"+1 707 763 0815",
    "sg:postcode":"94952",
    "sg:province":"CA",
    "sg:tags":[
        "electrical",
        "contractor"
    ],
    "wof:name":"Anchor Electric",
    "wof:placetype":"venue"
},
  "geometry": {"coordinates":[-122.644316,38.219257],"type":"Point"}
}