{
  "type": "Feature",
  "properties": {
    "iso:country":"US",
    "sg:address":"346 W Portal Ave",
    "sg:city":"San Francisco",
    "sg:classifiers":[
        {
            "category":"Wholesale",
            "subcategory":"Electrical",
            "type":"Manufacturing & Wholesale Goods"
        }
    ],
    "sg:phone":"+1 415 665 9202",
    "sg:postcode":"94127",
    "sg:province":"CA",
    "sg:tags":[
        "equipment"
    ],
    "wof:name":"Home Lighting & Fixs & Sup Co",
    "wof:placetype":"venue"
},
  "geometry": {"coordinates":[-122.470001,37.737344],"type":"Point"}
}