{
  "type": "Feature",
  "properties": {
    "addr:full":"777 Campus Commons Road Sacramento CA 95825",
    "addr:housenumber":"777",
    "addr:postcode":"95825",
    "addr:street":"Campus Commons Road",
    "iso:country":"US",
    "sg:address":"777 Campus Commons Road",
    "sg:city":"Sacramento",
    "sg:classifiers":[
        {
            "category":"Professional",
            "subcategory":"Lawyer & Legal Services",
            "type":"Services"
        }
    ],
    "sg:phone":"+1 916 565 7433",
    "sg:postcode":"95825",
    "sg:province":"CA",
    "wof:name":"Epolite Stephanie Glorioso Law Office of",
    "wof:placetype":"venue"
},
  "geometry": {"coordinates":[-121.41772400000001,38.570466],"type":"Point"}
}