{
  "type": "Feature",
  "properties": {
    "addr:full":"33027 Rd 159 Ivanhoe CA 93235",
    "addr:postcode":"33027;93235",
    "addr:street":"Rd 159",
    "iso:country":"US",
    "sg:address":"33027 Rd 159",
    "sg:city":"Ivanhoe",
    "sg:classifiers":[
        {
            "category":"Food & Beverages",
            "subcategory":"Bakery",
            "type":"Retail Goods"
        }
    ],
    "sg:phone":"+1 559 798 1000",
    "sg:postcode":"93235",
    "sg:province":"CA",
    "sg:tags":[
        "baker"
    ],
    "wof:name":"LA Espigita Bakery",
    "wof:placetype":"venue"
},
  "geometry": {"coordinates":[-119.218053,36.389246],"type":"Point"}
}