{
  "type": "Feature",
  "properties": {
    "addr:full":"4028 Thomas St Oceanside CA 92056",
    "addr:housenumber":"4028",
    "addr:postcode":"92056",
    "addr:street":"Thomas St",
    "iso:country":"US",
    "sg:address":"4028 Thomas St",
    "sg:city":"Oceanside",
    "sg:classifiers":[
        {
            "category":"Building & Trades",
            "subcategory":"Landscaping Services",
            "type":"Services"
        }
    ],
    "sg:phone":"+1 760 630 3147",
    "sg:postcode":"92056",
    "sg:province":"CA",
    "sg:tags":[
        "tree"
    ],
    "wof:name":"Arborist Consulting Svc",
    "wof:placetype":"venue"
},
  "geometry": {"coordinates":[-117.291247,33.195979],"type":"Point"}
}