{
  "type": "Feature",
  "properties": {
    "addr:full":"1313 S Winchester Blvd San Jose CA 95128",
    "addr:housenumber":"1313",
    "addr:postcode":"95128",
    "addr:street":"S Winchester Blvd",
    "iso:country":"US",
    "sg:address":"1313 S Winchester Blvd",
    "sg:city":"San Jose",
    "sg:classifiers":[
        {
            "category":"Personal",
            "subcategory":"Beauty Salon",
            "type":"Services"
        }
    ],
    "sg:phone":"+1 408 378 5720",
    "sg:postcode":"95128",
    "sg:province":"CA",
    "sg:tags":[
        "shop",
        "barber"
    ],
    "sg:website":"www.supercuts.com",
    "wof:name":"Supercuts",
    "wof:placetype":"venue"
},
  "geometry": {"coordinates":[-121.950031,37.298202],"type":"Point"}
}