{
  "type": "Feature",
  "properties": {
    "addr:full":"10866 Wilshire Boulevard Los Angeles CA 90024",
    "addr:housenumber":"10866",
    "addr:postcode":"90024",
    "addr:street":"Wilshire Boulevard",
    "iso:country":"US",
    "sg:address":"10866 Wilshire Boulevard",
    "sg:city":"Los Angeles",
    "sg:classifiers":[
        {
            "category":"Professional",
            "subcategory":"Employment Agencies",
            "type":"Services"
        }
    ],
    "sg:phone":"+1 310 474 1029",
    "sg:postcode":"90024",
    "sg:province":"CA",
    "sg:website":"www.stantonchase.com",
    "wof:name":"Stanton Chase International",
    "wof:placetype":"venue"
},
  "geometry": {"coordinates":[-118.442137,34.059274],"type":"Point"}
}