{
  "type": "Feature",
  "properties": {
    "iso:country":"US",
    "sg:address":"1617 Sepulveda Blvd",
    "sg:city":"Torrance",
    "sg:classifiers":[
        {
            "category":"Utilities",
            "subcategory":"Refuse",
            "type":"Services"
        }
    ],
    "sg:phone":"+1 310 539 2382",
    "sg:postcode":"90501",
    "sg:province":"CA",
    "sg:tags":[
        "system"
    ],
    "wof:name":"Jjk Roll Off & Disposal",
    "wof:placetype":"venue"
},
  "geometry": {"coordinates":[-118.30494,33.815508],"type":"Point"}
}