{
  "type": "Feature",
  "properties": {
    "addr:full":"1427 Long Beach Blvd Ste B Long Beach CA 90813",
    "addr:housenumber":"1427",
    "addr:postcode":"90813",
    "addr:street":"Long Beach Blvd Ste B",
    "iso:country":"US",
    "sg:address":"1427 Long Beach Blvd Ste B",
    "sg:city":"Long Beach",
    "sg:classifiers":[
        {
            "category":"Retail",
            "subcategory":"Auto Repair",
            "type":"Services"
        }
    ],
    "sg:phone":"+1 562 599 0766",
    "sg:postcode":"90813",
    "sg:province":"CA",
    "sg:tags":[
        "body",
        "shop"
    ],
    "sg:website":"qacollision.com",
    "wof:name":"Quality Assured Collision Center",
    "wof:placetype":"venue"
},
  "geometry": {"coordinates":[-118.18982,33.7846],"type":"Point"}
}