{
  "type": "Feature",
  "properties": {
    "addr:full":"26532 Town Center Dr Laguna Hills CA 92653",
    "addr:housenumber":"26532",
    "addr:postcode":"92653",
    "addr:street":"Town Center Dr",
    "iso:country":"US",
    "sg:address":"26532 Town Center Dr",
    "sg:city":"Laguna Hills",
    "sg:classifiers":[
        {
            "category":"Retail",
            "subcategory":"Veterinary Services",
            "type":"Services"
        }
    ],
    "sg:phone":"+1 949 837 4735",
    "sg:postcode":"92653",
    "sg:province":"CA",
    "sg:tags":[
        "veterinarian"
    ],
    "sg:website":"www.banfield.net",
    "wof:name":"Banfield The Pet Hospital",
    "wof:placetype":"venue"
},
  "geometry": {"coordinates":[-117.698854,33.593656],"type":"Point"}
}