{
  "type": "Feature",
  "properties": {
    "iso:country":"US",
    "sg:address":"1550 E Main St",
    "sg:city":"Ventura",
    "sg:classifiers":[
        {
            "category":"Personal",
            "subcategory":"Beauty Salon",
            "type":"Services"
        }
    ],
    "sg:phone":"+1 805 667 2131",
    "sg:postcode":"93001",
    "sg:province":"CA",
    "wof:name":"Pizazz Hair & Nails",
    "wof:placetype":"venue"
},
  "geometry": {"coordinates":[-119.276939,34.279642],"type":"Point"}
}