{
  "type": "Feature",
  "properties": {
    "addr:full":"12 Harkness Ave Pasadena CA 91106",
    "addr:housenumber":"12",
    "addr:postcode":"91106",
    "addr:street":"Harkness Ave",
    "iso:country":"US",
    "sg:address":"12 Harkness Ave",
    "sg:city":"Pasadena",
    "sg:classifiers":[
        {
            "category":"Food & Beverages",
            "subcategory":"Bakery",
            "type":"Retail Goods"
        }
    ],
    "sg:phone":"+1 626 793 0072",
    "sg:postcode":"91106",
    "sg:province":"CA",
    "sg:tags":[
        "sandwich"
    ],
    "wof:name":"Sandwich Story",
    "wof:placetype":"venue"
},
  "geometry": {"coordinates":[-118.11986,34.146173],"type":"Point"}
}