{
  "type": "Feature",
  "properties": {
    "iso:country":"US",
    "sg:address":"8250 Sepulveda Blvd",
    "sg:city":"Panorama City",
    "sg:classifiers":[
        {
            "category":"Autos & Motor Vehicles",
            "subcategory":"Fuel & Gas Station",
            "type":"Retail Goods"
        }
    ],
    "sg:phone":"+1 818 894 6610",
    "sg:postcode":"91402",
    "sg:province":"CA",
    "sg:tags":[
        "oil"
    ],
    "wof:name":"World Oil Corp",
    "wof:placetype":"venue"
},
  "geometry": {"coordinates":[-118.466961,34.219179],"type":"Point"}
}