{
  "type": "Feature",
  "properties": {
    "iso:country":"US",
    "sg:address":"7825 Beverly Blvd",
    "sg:city":"Los Angeles",
    "sg:classifiers":[
        {
            "category":"Retail",
            "subcategory":"Repair Shop",
            "type":"Services"
        }
    ],
    "sg:phone":"+1 323 937 6898",
    "sg:postcode":"90036",
    "sg:province":"CA",
    "sg:tags":[
        "optical",
        "good"
    ],
    "wof:name":"Edging & Mounting Specialists",
    "wof:placetype":"venue"
},
  "geometry": {"coordinates":[-118.361131,34.07618],"type":"Point"}
}