{
  "type": "Feature",
  "properties": {
    "addr:full":"649 Rock Springs Rd Escondido CA 92025",
    "addr:housenumber":"649",
    "addr:postcode":"92025",
    "addr:street":"Rock Springs Rd",
    "iso:country":"US",
    "sg:address":"649 Rock Springs Rd",
    "sg:city":"Escondido",
    "sg:classifiers":[
        {
            "category":"Wholesale",
            "subcategory":"Farm Supplies",
            "type":"Manufacturing & Wholesale Goods"
        },
        {
            "category":"Shopping",
            "type":"Retail Goods"
        }
    ],
    "sg:phone":"+1 760 745 2911",
    "sg:postcode":"92025",
    "sg:province":"CA",
    "sg:tags":[
        "feed",
        "merchandise",
        "crop"
    ],
    "wof:name":"Escondido Feed & Pet Supply",
    "wof:placetype":"venue"
},
  "geometry": {"coordinates":[-117.09669700000001,33.124349],"type":"Point"}
}