{
  "type": "Feature",
  "properties": {
    "iso:country":"US",
    "sg:address":"41529 Big Bear Blvd",
    "sg:city":"Big Bear Lake",
    "sg:classifiers":[
        {
            "category":"Banks & Credit Unions",
            "subcategory":"Bank",
            "type":"Services"
        }
    ],
    "sg:phone":"+1 909 878 2112",
    "sg:postcode":"92315",
    "sg:province":"CA",
    "sg:tags":[
        "loan",
        "real estate"
    ],
    "wof:name":"Alpine Mortgage",
    "wof:placetype":"venue"
},
  "geometry": {"coordinates":[-116.896142,34.243401],"type":"Point"}
}