{
  "type": "Feature",
  "properties": {
    "iso:country":"US",
    "sg:address":"23407 Main St",
    "sg:city":"Carson",
    "sg:classifiers":[
        {
            "category":"Insurance",
            "subcategory":"Insurance Agent",
            "type":"Services"
        }
    ],
    "sg:phone":"+1 310 233 3855",
    "sg:postcode":"90745",
    "sg:province":"CA",
    "wof:name":"State Farm Insurance",
    "wof:placetype":"venue"
},
  "geometry": {"coordinates":[-118.275264,33.81269],"type":"Point"}
}