{
  "type": "Feature",
  "properties": {
    "addr:full":"1444 S Grand St Visalia CA 93292",
    "addr:housenumber":"1444",
    "addr:postcode":"93292",
    "addr:street":"S Grand St",
    "iso:country":"US",
    "sg:address":"1444 S Grand St",
    "sg:city":"Visalia",
    "sg:classifiers":[
        {
            "category":"Wholesale",
            "subcategory":"Machinery & Supplies",
            "type":"Manufacturing & Wholesale Goods"
        }
    ],
    "sg:phone":"+1 559 732 3484",
    "sg:postcode":"93292",
    "sg:province":"CA",
    "sg:tags":[
        "contractor"
    ],
    "wof:name":"Valley Water Trucking",
    "wof:placetype":"venue"
},
  "geometry": {"coordinates":[-119.248312,36.317737],"type":"Point"}
}