{
  "type": "Feature",
  "properties": {
    "addr:full":"8312 Baranca Ct Spring Valley CA 91977",
    "addr:housenumber":"8312",
    "addr:postcode":"91977",
    "addr:street":"Baranca Ct",
    "iso:country":"US",
    "sg:address":"8312 Baranca Ct",
    "sg:city":"Spring Valley",
    "sg:classifiers":[
        {
            "category":"Wholesale",
            "subcategory":"Computers",
            "type":"Manufacturing & Wholesale Goods"
        }
    ],
    "sg:phone":"+1 619 472 1233",
    "sg:postcode":"91977",
    "sg:province":"CA",
    "wof:name":"CD Computer Services",
    "wof:placetype":"venue"
},
  "geometry": {"coordinates":[-117.02110500000001,32.696343],"type":"Point"}
}