{
  "type": "Feature",
  "properties": {
    "addr:full":"1130 Lafayette St San Mateo CA 94403",
    "addr:housenumber":"1130",
    "addr:postcode":"94403",
    "addr:street":"Lafayette St",
    "iso:country":"US",
    "sg:address":"1130 Lafayette St",
    "sg:city":"San Mateo",
    "sg:classifiers":[
        {
            "category":"Professional",
            "type":"Services"
        }
    ],
    "sg:phone":"+1 650 358 9877",
    "sg:postcode":"94403",
    "sg:province":"CA",
    "wof:name":"RCCA Svc",
    "wof:placetype":"venue"
},
  "geometry": {"coordinates":[-122.293606,37.548052],"type":"Point"}
}