{
  "type": "Feature",
  "properties": {
    "addr:full":"11911 San Vicente Blvd Los Angeles CA 90049",
    "addr:housenumber":"11911",
    "addr:postcode":"90049",
    "addr:street":"San Vicente Blvd",
    "iso:country":"US",
    "sg:address":"11911 San Vicente Blvd",
    "sg:city":"Los Angeles",
    "sg:classifiers":[
        {
            "category":"Food & Beverages",
            "subcategory":"Fruits & Vegetables",
            "type":"Retail Goods"
        }
    ],
    "sg:phone":"+1 310 476 5823",
    "sg:postcode":"90049",
    "sg:province":"CA",
    "sg:tags":[
        "juice"
    ],
    "wof:name":"Jamba Juice",
    "wof:placetype":"venue"
},
  "geometry": {"coordinates":[-118.47266,34.052172],"type":"Point"}
}