{
  "type": "Feature",
  "properties": {
    "iso:country":"US",
    "sg:address":"3927 International Blvd",
    "sg:city":"Oakland",
    "sg:classifiers":[
        {
            "category":"Home & Garden",
            "subcategory":"Garden Supply",
            "type":"Retail Goods"
        }
    ],
    "sg:phone":"+1 510 931 8883",
    "sg:postcode":"94601",
    "sg:province":"CA",
    "wof:name":"International Indoor Garden",
    "wof:placetype":"venue"
},
  "geometry": {"coordinates":[-122.218862,37.773683],"type":"Point"}
}