{
  "type": "Feature",
  "properties": {
    "iso:country":"US",
    "sg:address":"2062 N Marter Ave",
    "sg:city":"Simi Valley",
    "sg:classifiers":[
        {
            "category":"Professional",
            "subcategory":"Computer Services",
            "type":"Services"
        }
    ],
    "sg:phone":"+1 805 520 7847",
    "sg:postcode":"93065",
    "sg:province":"CA",
    "sg:tags":[
        "repair"
    ],
    "wof:name":"Citadel America Group Inc",
    "wof:placetype":"venue"
},
  "geometry": {"coordinates":[-118.759884,34.272924],"type":"Point"}
}