{
  "type": "Feature",
  "properties": {
    "addr:full":"28382 Via Mondano San Juan Capistrano CA 92675",
    "addr:housenumber":"28382",
    "addr:postcode":"92675",
    "addr:street":"Via Mondano",
    "iso:country":"US",
    "sg:address":"28382 Via Mondano",
    "sg:city":"San Juan Capistrano",
    "sg:classifiers":[
        {
            "category":"Wholesale",
            "subcategory":"Construction Materials",
            "type":"Manufacturing & Wholesale Goods"
        }
    ],
    "sg:phone":"+1 949 240 7888",
    "sg:postcode":"92675",
    "sg:province":"CA",
    "wof:name":"Indiana Architectural Plywood",
    "wof:placetype":"venue"
},
  "geometry": {"coordinates":[-117.63942900000001,33.48824],"type":"Point"}
}