{
  "type": "Feature",
  "properties": {
    "iso:country":"US",
    "sg:address":"39700 Bob Hope Dr Ste 216",
    "sg:city":"Rancho Mirage",
    "sg:classifiers":[
        {
            "category":"Health Services",
            "subcategory":"Doctor",
            "type":"Services"
        }
    ],
    "sg:phone":"+1 760 779 9353",
    "sg:postcode":"92270",
    "sg:province":"CA",
    "wof:name":"Fausel DO APC Richard E",
    "wof:placetype":"venue"
},
  "geometry": {"coordinates":[-116.407915,33.761512],"type":"Point"}
}