{
  "type": "Feature",
  "properties": {
    "addr:full":"150 Toland St San Francisco CA 94124",
    "addr:housenumber":"150",
    "addr:postcode":"94124",
    "addr:street":"Toland St",
    "iso:country":"US",
    "sg:address":"150 Toland St",
    "sg:city":"San Francisco",
    "sg:classifiers":[
        {
            "category":"Travel",
            "subcategory":"Travel Agent",
            "type":"Entertainment"
        }
    ],
    "sg:phone":"+1 415 401 8748",
    "sg:postcode":"94124",
    "sg:province":"CA",
    "sg:tags":[
        "agency",
        "bureau"
    ],
    "wof:name":"Central Sky Co",
    "wof:placetype":"venue"
},
  "geometry": {"coordinates":[-122.397582,37.745516],"type":"Point"}
}