{
  "type": "Feature",
  "properties": {
    "addr:full":"3111 S Western Ave Los Angeles CA 90018",
    "addr:housenumber":"3111",
    "addr:postcode":"90018",
    "addr:street":"S Western Ave",
    "iso:country":"US",
    "sg:address":"3111 S Western Ave",
    "sg:city":"Los Angeles",
    "sg:classifiers":[
        {
            "category":"Shopping",
            "subcategory":"Gifts & Souvenirs",
            "type":"Retail Goods"
        }
    ],
    "sg:phone":"+1 323 732 2135",
    "sg:postcode":"90018",
    "sg:province":"CA",
    "wof:name":"Thrift & Gift Shoppe",
    "wof:placetype":"venue"
},
  "geometry": {"coordinates":[-118.30896199999999,34.025583],"type":"Point"}
}