{
  "type": "Feature",
  "properties": {
    "addr:full":"19 Ruben Ct Novato CA 94947",
    "addr:housenumber":"19",
    "addr:postcode":"94947",
    "addr:street":"Ruben Ct",
    "iso:country":"US",
    "sg:address":"19 Ruben Ct",
    "sg:city":"Novato",
    "sg:classifiers":[
        {
            "category":"Personal",
            "type":"Services"
        }
    ],
    "sg:phone":"+1 415 246 9381",
    "sg:postcode":"94947",
    "sg:province":"CA",
    "sg:tags":[
        "consultant",
        "program",
        "health",
        "fitness"
    ],
    "wof:name":"Venice Fitness",
    "wof:placetype":"venue"
},
  "geometry": {"coordinates":[-122.614639,38.109911],"type":"Point"}
}