{
  "type": "Feature",
  "properties": {
    "iso:country":"US",
    "sg:address":"22250 Elkwood St",
    "sg:city":"Canoga Park",
    "sg:classifiers":[
        {
            "category":"Education",
            "subcategory":"School",
            "type":"Public Place"
        }
    ],
    "sg:phone":"+1 818 348 5601",
    "sg:postcode":"91304",
    "sg:province":"CA",
    "sg:tags":[
        "high",
        "middle",
        "elementary"
    ],
    "wof:name":"Columbus Jr High School",
    "wof:placetype":"venue"
},
  "geometry": {"coordinates":[-118.61199999999999,34.212898],"type":"Point"}
}