{
  "type": "Feature",
  "properties": {
    "addr:full":"4212 Overland Ave Culver City CA 90230",
    "addr:housenumber":"4212",
    "addr:postcode":"90230",
    "addr:street":"Overland Ave",
    "iso:country":"US",
    "sg:address":"4212 Overland Ave",
    "sg:city":"Culver City",
    "sg:classifiers":[
        {
            "category":"Personal",
            "type":"Services"
        }
    ],
    "sg:phone":"+1 310 204 2574",
    "sg:postcode":"90230",
    "sg:province":"CA",
    "sg:tags":[
        "control",
        "weight"
    ],
    "wof:name":"Jefferson West Medical Group",
    "wof:placetype":"venue"
},
  "geometry": {"coordinates":[-118.400262,34.011626],"type":"Point"}
}