{
  "type": "Feature",
  "properties": {
    "addr:full":"1060 Lorenzo Ct Seaside CA 93955",
    "addr:housenumber":"1060",
    "addr:postcode":"93955",
    "addr:street":"Lorenzo Ct",
    "iso:country":"US",
    "sg:address":"1060 Lorenzo Ct",
    "sg:city":"Seaside",
    "sg:classifiers":[
        {
            "category":"Freight",
            "type":"Transportation"
        }
    ],
    "sg:phone":"+1 831 394 6186",
    "sg:postcode":"93955",
    "sg:province":"CA",
    "sg:tags":[
        "operator",
        "trucking"
    ],
    "wof:name":"Salvadore J Saia Jr",
    "wof:placetype":"venue"
},
  "geometry": {"coordinates":[-121.84765299999999,36.598443],"type":"Point"}
}