{
  "type": "Feature",
  "properties": {
    "addr:full":"1515 R St Sacramento CA 95811",
    "addr:housenumber":"1515",
    "addr:postcode":"95811",
    "addr:street":"R St",
    "iso:country":"US",
    "sg:address":"1515 R St",
    "sg:city":"Sacramento",
    "sg:classifiers":[
        {
            "category":"Restaurant",
            "type":"Food & Drink"
        }
    ],
    "sg:phone":"+1 916 446 5697",
    "sg:postcode":"95811",
    "sg:province":"CA",
    "sg:tags":[
        "cafeteria"
    ],
    "wof:name":"Coffee & More",
    "wof:placetype":"venue"
},
  "geometry": {"coordinates":[-121.489164,38.569401],"type":"Point"}
}