{
  "type": "Feature",
  "properties": {
    "iso:country":"US",
    "sg:address":"2018 E Woodsville Ct",
    "sg:city":"Visalia",
    "sg:classifiers":[
        {
            "category":"Professional",
            "type":"Services"
        }
    ],
    "sg:phone":"+1 559 741 1306",
    "sg:postcode":"93292",
    "sg:province":"CA",
    "sg:tags":[
        "establishment"
    ],
    "wof:name":"Ariels Designs",
    "wof:placetype":"venue"
},
  "geometry": {"coordinates":[-119.270944,36.34673],"type":"Point"}
}