{
  "type": "Feature",
  "properties": {
    "iso:country":"US",
    "sg:address":"1411 Harbor Bay Pkwy. Suite 2008",
    "sg:city":"Alameda",
    "sg:classifiers":[
        {
            "category":"Professional",
            "subcategory":"Research",
            "type":"Services"
        }
    ],
    "sg:phone":"+1 510 865 1979",
    "sg:postcode":"94502",
    "sg:province":"CA",
    "sg:website":"http://www.vapore.com/",
    "wof:name":"Vapore",
    "wof:placetype":"venue"
},
  "geometry": {"coordinates":[-122.23656699999999,37.725534],"type":"Point"}
}