{
  "type": "Feature",
  "properties": {
    "iso:country":"US",
    "sg:address":"40 Main St",
    "sg:city":"Sutter Creek",
    "sg:classifiers":[
        {
            "category":"Shopping",
            "subcategory":"Clothing, Apparel, & Fashions",
            "type":"Retail Goods"
        }
    ],
    "sg:phone":"+1 209 267 1600",
    "sg:postcode":"95685",
    "sg:province":"CA",
    "sg:website":"www.suttercreekboutique.com",
    "wof:name":"Sutter Creek Boutique",
    "wof:placetype":"venue"
},
  "geometry": {"coordinates":[-120.80297299999999,38.393673],"type":"Point"}
}