{
  "type": "Feature",
  "properties": {
    "iso:country":"US",
    "sg:address":"916 Magnolia Dr",
    "sg:city":"Alameda",
    "sg:classifiers":[
        {
            "category":"Travel",
            "subcategory":"Travel Agent",
            "type":"Entertainment"
        }
    ],
    "sg:phone":"+1 510 521 4365",
    "sg:postcode":"94502",
    "sg:province":"CA",
    "sg:tags":[
        "agency",
        "services-commercial"
    ],
    "wof:name":"Abracadabra Cruises",
    "wof:placetype":"venue"
},
  "geometry": {"coordinates":[-122.232152,37.730068],"type":"Point"}
}