{
  "type": "Feature",
  "properties": {
    "iso:country":"US",
    "sg:address":"1008 S Baldwin Ave",
    "sg:city":"Arcadia",
    "sg:classifiers":[
        {
            "category":"Manufacturing",
            "subcategory":"Rubber & Plastics",
            "type":"Manufacturing & Wholesale Goods"
        }
    ],
    "sg:phone":"+1 626 821 3588",
    "sg:postcode":"91007",
    "sg:province":"CA",
    "sg:tags":[
        "finishing",
        "plastics-fabricating",
        "decorating"
    ],
    "wof:name":"Global Boom Incorporation",
    "wof:placetype":"venue"
},
  "geometry": {"coordinates":[-118.054675,34.128725],"type":"Point"}
}