{
  "type": "Feature",
  "properties": {
    "iso:country":"US",
    "sg:address":"610 16th St Ste 508",
    "sg:city":"Oakland",
    "sg:classifiers":[
        {
            "category":"Health Services",
            "subcategory":"Clinic",
            "type":"Services"
        },
        {
            "category":"Health Services",
            "subcategory":"Medical Lab",
            "type":"Services"
        }
    ],
    "sg:phone":"+1 510 451 1273",
    "sg:postcode":"94612",
    "sg:province":"CA",
    "wof:name":"Lifelong Medical Care Shp Clinic",
    "wof:placetype":"venue"
},
  "geometry": {"coordinates":[-122.27419500000001,37.807154],"type":"Point"}
}