{
  "type": "Feature",
  "properties": {
    "iso:country":"US",
    "sg:address":"260 Water St",
    "sg:city":"Petaluma",
    "sg:classifiers":[
        {
            "category":"Manufacturing",
            "subcategory":"Tools & Machinery",
            "type":"Manufacturing & Wholesale Goods"
        }
    ],
    "sg:phone":"+1 707 763 4266",
    "sg:postcode":"94952",
    "sg:province":"CA",
    "sg:tags":[
        "equipment",
        "lighting",
        "mfg"
    ],
    "wof:name":"Twilight Design",
    "wof:placetype":"venue"
},
  "geometry": {"coordinates":[-122.640596,38.237008],"type":"Point"}
}