{
  "type": "Feature",
  "properties": {
    "addr:full":"32083 Alvarado Niles Rd Union City CA 94587",
    "addr:housenumber":"32083",
    "addr:postcode":"94587",
    "addr:street":"Alvarado Niles Rd",
    "iso:country":"US",
    "sg:address":"32083 Alvarado Niles Rd",
    "sg:city":"Union City",
    "sg:classifiers":[
        {
            "category":"Travel",
            "subcategory":"Hotels & Motels",
            "type":"Entertainment"
        }
    ],
    "sg:phone":"+1 510 489 2200",
    "sg:postcode":"94587",
    "sg:province":"CA",
    "wof:name":"Crowne Plaza",
    "wof:placetype":"venue"
},
  "geometry": {"coordinates":[-122.05557399999999,37.59653],"type":"Point"}
}