{
  "type": "Feature",
  "properties": {
    "iso:country":"US",
    "sg:address":"14301 Crenshaw Boulevard",
    "sg:city":"Hawthorne",
    "sg:classifiers":[
        {
            "category":"Retail",
            "subcategory":"Auto Repair",
            "type":"Services"
        }
    ],
    "sg:phone":"+1 310 679 2214",
    "sg:postcode":"90250",
    "sg:province":"CA",
    "sg:website":"www.midas.com",
    "wof:name":"Midas Auto Service",
    "wof:placetype":"venue"
},
  "geometry": {"coordinates":[-118.326626,33.901845],"type":"Point"}
}