{
  "type": "Feature",
  "properties": {
    "iso:country":"US",
    "sg:address":"1555 Riverlake Rd",
    "sg:city":"Discovery Bay",
    "sg:classifiers":[
        {
            "category":"Real Estate",
            "subcategory":"Real Estate Agent",
            "type":"Services"
        }
    ],
    "sg:phone":"+1 925 634 1111",
    "sg:postcode":"94505",
    "sg:province":"CA",
    "sg:website":"www.apr.com",
    "wof:name":"Alain Pinel Realtors",
    "wof:placetype":"venue"
},
  "geometry": {"coordinates":[-121.606297,37.902497],"type":"Point"}
}