{
  "type": "Feature",
  "properties": {
    "iso:country":"US",
    "sg:address":"6662 Mount Holly Dr",
    "sg:city":"San Jose",
    "sg:classifiers":[
        {
            "category":"Wholesale",
            "subcategory":"Sporting Goods",
            "type":"Manufacturing & Wholesale Goods"
        }
    ],
    "sg:phone":"+1 408 268 0945",
    "sg:postcode":"95120",
    "sg:province":"CA",
    "wof:name":"Edina",
    "wof:placetype":"venue"
},
  "geometry": {"coordinates":[-121.853157,37.220194],"type":"Point"}
}