{
  "type": "Feature",
  "properties": {
    "iso:country":"US",
    "sg:address":"1333 N McDowell Blvd",
    "sg:city":"Petaluma",
    "sg:classifiers":[
        {
            "category":"Professional",
            "type":"Services"
        }
    ],
    "sg:phone":"+1 707 283 8000",
    "sg:postcode":"94954",
    "sg:province":"CA",
    "sg:tags":[
        "establishment"
    ],
    "wof:name":"Advanced Projects Intl",
    "wof:placetype":"venue"
},
  "geometry": {"coordinates":[-122.66468,38.272918],"type":"Point"}
}