{
  "type": "Feature",
  "properties": {
    "iso:country":"US",
    "sg:address":"855 el Camino Real",
    "sg:city":"Palo Alto",
    "sg:classifiers":[
        {
            "category":"Food & Beverages",
            "subcategory":"Fruits & Vegetables",
            "type":"Retail Goods"
        }
    ],
    "sg:phone":"+1 650 325 2582",
    "sg:postcode":"94301",
    "sg:province":"CA",
    "sg:tags":[
        "juice"
    ],
    "sg:website":"www.jambajuice.com",
    "wof:name":"Jamba Juice",
    "wof:placetype":"venue"
},
  "geometry": {"coordinates":[-122.16078899999999,37.437917],"type":"Point"}
}