{
  "type": "Feature",
  "properties": {
    "addr:full":"132 Martinelli St Watsonville CA 95076",
    "addr:housenumber":"132",
    "addr:postcode":"95076",
    "addr:street":"Martinelli St",
    "iso:country":"US",
    "sg:address":"132 Martinelli St",
    "sg:city":"Watsonville",
    "sg:classifiers":[
        {
            "category":"Wholesale",
            "subcategory":"Non-durable Goods",
            "type":"Manufacturing & Wholesale Goods"
        }
    ],
    "sg:phone":"+1 831 722 3465",
    "sg:postcode":"95076",
    "sg:province":"CA",
    "wof:name":"Double Eye Distributing",
    "wof:placetype":"venue"
},
  "geometry": {"coordinates":[-121.748836,36.925697],"type":"Point"}
}