{
  "type": "Feature",
  "properties": {
    "addr:full":"11082 Coloma Rd Rancho Cordova CA 95670",
    "addr:housenumber":"11082",
    "addr:postcode":"95670",
    "addr:street":"Coloma Rd",
    "iso:country":"US",
    "sg:address":"11082 Coloma Rd",
    "sg:city":"Rancho Cordova",
    "sg:classifiers":[
        {
            "category":"Shopping",
            "subcategory":"Gifts & Souvenirs",
            "type":"Retail Goods"
        }
    ],
    "sg:phone":"+1 916 858 2300",
    "sg:postcode":"95670",
    "sg:province":"CA",
    "sg:tags":[
        "shop"
    ],
    "wof:name":"Little Armenian Gift Shop",
    "wof:placetype":"venue"
},
  "geometry": {"coordinates":[-121.271648,38.617768],"type":"Point"}
}