{
  "type": "Feature",
  "properties": {
    "addr:full":"3022 F St Sacramento CA 95816",
    "addr:housenumber":"3022",
    "addr:postcode":"95816",
    "addr:street":"F St",
    "iso:country":"US",
    "sg:address":"3022 F St",
    "sg:city":"Sacramento",
    "sg:classifiers":[
        {
            "category":"Organizations",
            "subcategory":"Religious Organization",
            "type":"Services"
        }
    ],
    "sg:phone":"+1 916 443 2033",
    "sg:postcode":"95816",
    "sg:province":"CA",
    "sg:tags":[
        "church"
    ],
    "sg:website":"www.annunciation.ca.goarch.org",
    "wof:name":"Greek Orthodox Church",
    "wof:placetype":"venue"
},
  "geometry": {"coordinates":[-121.463565,38.577153],"type":"Point"}
}