{
  "type": "Feature",
  "properties": {
    "addr:full":"1280 Dana Dr Redding CA 96003",
    "addr:housenumber":"1280",
    "addr:postcode":"96003",
    "addr:street":"Dana Dr",
    "iso:country":"US",
    "sg:address":"1280 Dana Dr",
    "sg:city":"Redding",
    "sg:classifiers":[
        {
            "category":"Shopping",
            "subcategory":"Department Store",
            "type":"Retail Goods"
        }
    ],
    "sg:phone":"+1 530 223 0123",
    "sg:postcode":"96003",
    "sg:province":"CA",
    "wof:name":"Target",
    "wof:placetype":"venue"
},
  "geometry": {"coordinates":[-122.347341,40.585771],"type":"Point"}
}