{
  "type": "Feature",
  "properties": {
    "addr:full":"1731 N Fresno St Fresno CA 93703",
    "addr:housenumber":"1731",
    "addr:postcode":"93703",
    "addr:street":"N Fresno",
    "iso:country":"US",
    "sg:address":"1731 N Fresno St",
    "sg:city":"Fresno",
    "sg:classifiers":[
        {
            "category":"Health Services",
            "subcategory":"Doctor",
            "type":"Services"
        }
    ],
    "sg:phone":"+1 559 268 1079",
    "sg:postcode":"93703",
    "sg:province":"CA",
    "sg:tags":[
        "physician",
        "surgeon"
    ],
    "wof:name":"Luu Van Tuan MD",
    "wof:placetype":"venue"
},
  "geometry": {"coordinates":[-119.781603,36.766549],"type":"Point"}
}