{
  "type": "Feature",
  "properties": {
    "addr:full":"576 Masters Cir Nipomo CA 93444",
    "addr:housenumber":"576",
    "addr:postcode":"93444",
    "addr:street":"Masters Cir",
    "iso:country":"US",
    "sg:address":"576 Masters Cir",
    "sg:city":"Nipomo",
    "sg:classifiers":[
        {
            "category":"Wholesale",
            "subcategory":"Home Furnishings",
            "type":"Manufacturing & Wholesale Goods"
        }
    ],
    "sg:phone":"+1 805 343 2405",
    "sg:postcode":"93444",
    "sg:province":"CA",
    "wof:name":"Geri-Lynn Decor",
    "wof:placetype":"venue"
},
  "geometry": {"coordinates":[-120.54820100000001,35.05161],"type":"Point"}
}