{
  "type": "Feature",
  "properties": {
    "addr:full":"2525 Camino Del Rio S Ste 325 San Diego CA 92108",
    "addr:housenumber":"2525",
    "addr:postcode":"92108",
    "addr:street":"Camino Del Rio S Ste 325",
    "iso:country":"US",
    "sg:address":"2525 Camino Del Rio S Ste 325",
    "sg:city":"San Diego",
    "sg:classifiers":[
        {
            "category":"Travel",
            "subcategory":"Travel Agent",
            "type":"Entertainment"
        },
        {
            "category":"Community Center",
            "type":"Public Place"
        }
    ],
    "sg:phone":"+1 619 293 3963",
    "sg:postcode":"92108",
    "sg:province":"CA",
    "sg:tags":[
        "medical"
    ],
    "sg:website":"www.passporthealthsd.com",
    "wof:name":"Passport Health",
    "wof:placetype":"venue"
},
  "geometry": {"coordinates":[-117.13743700000001,32.76779],"type":"Point"}
}