{
  "type": "Feature",
  "properties": {
    "iso:country":"US",
    "sg:address":"2147 Amorosa Glen",
    "sg:city":"Escondido",
    "sg:classifiers":[
        {
            "category":"Building & Trades",
            "subcategory":"Construction",
            "type":"Services"
        }
    ],
    "sg:phone":"+1 760 213 3703",
    "sg:postcode":"92026",
    "sg:province":"CA",
    "sg:tags":[
        "painter"
    ],
    "wof:name":"Salazar Painting",
    "wof:placetype":"venue"
},
  "geometry": {"coordinates":[-117.105205,33.158016],"type":"Point"}
}