{
  "type": "Feature",
  "properties": {
    "addr:full":"8724 Avalon Blvd Los Angeles CA 90003",
    "addr:housenumber":"8724",
    "addr:postcode":"90003",
    "addr:street":"Avalon Blvd",
    "iso:country":"US",
    "sg:address":"8724 Avalon Blvd",
    "sg:city":"Los Angeles",
    "sg:classifiers":[
        {
            "category":"Organizations",
            "subcategory":"Religious Organization",
            "type":"Services"
        }
    ],
    "sg:phone":"+1 323 753 5763",
    "sg:postcode":"90003",
    "sg:province":"CA",
    "sg:tags":[
        "church"
    ],
    "wof:name":"Grace To You Bible Church",
    "wof:placetype":"venue"
},
  "geometry": {"coordinates":[-118.26504799999999,33.958751],"type":"Point"}
}