{
  "type": "Feature",
  "properties": {
    "addr:full":"5672 E Dayton Ave Fresno CA 93727",
    "addr:housenumber":"5672",
    "addr:postcode":"93727",
    "addr:street":"E Dayton Ave",
    "iso:country":"US",
    "sg:address":"5672 E Dayton Ave",
    "sg:city":"Fresno",
    "sg:classifiers":[
        {
            "category":"Building & Trades",
            "subcategory":"Construction",
            "type":"Services"
        }
    ],
    "sg:phone":"+1 559 292 9104",
    "sg:postcode":"93727",
    "sg:province":"CA",
    "sg:tags":[
        "maker",
        "cabinet"
    ],
    "wof:name":"Architectural Wood Designs Inc",
    "wof:placetype":"venue"
},
  "geometry": {"coordinates":[-119.69479800000001,36.782975],"type":"Point"}
}