{
  "type": "Feature",
  "properties": {
    "addr:full":"5110 Greer Ave Covina CA 91724",
    "addr:housenumber":"5110",
    "addr:postcode":"91724",
    "addr:street":"Greer Ave",
    "iso:country":"US",
    "sg:address":"5110 Greer Ave",
    "sg:city":"Covina",
    "sg:classifiers":[
        {
            "category":"Professional",
            "type":"Services"
        }
    ],
    "sg:phone":"+1 626 974 5215",
    "sg:postcode":"91724",
    "sg:province":"CA",
    "wof:name":"Agron & Asoociates",
    "wof:placetype":"venue"
},
  "geometry": {"coordinates":[-117.848946,34.106243],"type":"Point"}
}