{
  "type": "Feature",
  "properties": {
    "addr:full":"191 Los Gatos Saratoga R Los Gatos CA 95030",
    "addr:housenumber":"191",
    "addr:postcode":"95030",
    "addr:street":"Los Gatos;R",
    "iso:country":"US",
    "sg:address":"191 Los Gatos Saratoga R",
    "sg:city":"Los Gatos",
    "sg:classifiers":[
        {
            "category":"Personal",
            "subcategory":"Nail Salon",
            "type":"Services"
        }
    ],
    "sg:phone":"+1 408 395 1817",
    "sg:postcode":"95030",
    "sg:province":"CA",
    "wof:name":"Natural Nails",
    "wof:placetype":"venue"
},
  "geometry": {"coordinates":[-121.980423,37.228476],"type":"Point"}
}