{
  "type": "Feature",
  "properties": {
    "iso:country":"US",
    "sg:address":"1604 G St",
    "sg:city":"Reedley",
    "sg:classifiers":[
        {
            "category":"Food & Beverages",
            "subcategory":"Groceries & Convenience Stores",
            "type":"Retail Goods"
        }
    ],
    "sg:phone":"+1 559 638 1995",
    "sg:postcode":"93654",
    "sg:province":"CA",
    "wof:name":"Shop KWIK",
    "wof:placetype":"venue"
},
  "geometry": {"coordinates":[-119.444245,36.590276],"type":"Point"}
}