{
  "type": "Feature",
  "properties": {
    "addr:full":"1105 N Sacramento St Stockton CA 95202",
    "addr:housenumber":"1105",
    "addr:postcode":"95202",
    "addr:street":"N Sacramento St",
    "iso:country":"US",
    "sg:address":"1105 N Sacramento St",
    "sg:city":"Stockton",
    "sg:classifiers":[
        {
            "category":"Social Services",
            "subcategory":"Child Care",
            "type":"Services"
        }
    ],
    "sg:phone":"+1 209 939 9270",
    "sg:postcode":"95202",
    "sg:province":"CA",
    "wof:name":"Creative Child Care Inc",
    "wof:placetype":"venue"
},
  "geometry": {"coordinates":[-121.28160099999999,37.966836],"type":"Point"}
}