{
  "type": "Feature",
  "properties": {
    "iso:country":"US",
    "sg:address":"631 Emerald St",
    "sg:city":"Redondo Beach",
    "sg:classifiers":[
        {
            "category":"Building & Trades",
            "subcategory":"Construction",
            "type":"Services"
        }
    ],
    "sg:phone":"+1 310 406 2176",
    "sg:postcode":"90277",
    "sg:province":"CA",
    "sg:tags":[
        "contractor"
    ],
    "sg:website":"www.epicconstruction.com",
    "wof:name":"Epic Construction",
    "wof:placetype":"venue"
},
  "geometry": {"coordinates":[-118.384015,33.842294],"type":"Point"}
}