{
  "type": "Feature",
  "properties": {
    "addr:full":"39055 Hastings St Fremont CA 94538",
    "addr:housenumber":"39055",
    "addr:postcode":"94538",
    "addr:street":"Hastings St",
    "iso:country":"US",
    "sg:address":"39055 Hastings St",
    "sg:city":"Fremont",
    "sg:classifiers":[
        {
            "category":"Professional",
            "subcategory":"Business Services",
            "type":"Services"
        }
    ],
    "sg:phone":"+1 510 505 1700",
    "sg:postcode":"94538",
    "sg:province":"CA",
    "sg:tags":[
        "telemarketing"
    ],
    "wof:name":"Media Promotions",
    "wof:placetype":"venue"
},
  "geometry": {"coordinates":[-121.98335899999999,37.552407],"type":"Point"}
}