{
  "type": "Feature",
  "properties": {
    "addr:full":"43369 10th St W Lancaster CA 93534",
    "addr:housenumber":"43369",
    "addr:postcode":"93534",
    "addr:street":"10Th St W",
    "iso:country":"US",
    "sg:address":"43369 10th St W",
    "sg:city":"Lancaster",
    "sg:classifiers":[
        {
            "category":"Restaurant",
            "type":"Food & Drink"
        }
    ],
    "sg:phone":"+1 661 945 7538",
    "sg:postcode":"93534",
    "sg:province":"CA",
    "wof:name":"Primo Burgers",
    "wof:placetype":"venue"
},
  "geometry": {"coordinates":[-118.14792199999999,34.67152],"type":"Point"}
}