{
  "type": "Feature",
  "properties": {
    "iso:country":"US",
    "sg:address":"7321 Thornton Ave",
    "sg:city":"Newark",
    "sg:classifiers":[
        {
            "category":"Food & Beverages",
            "subcategory":"Groceries & Convenience Stores",
            "type":"Retail Goods"
        }
    ],
    "sg:phone":"+1 510 745 7080",
    "sg:postcode":"94560",
    "sg:province":"CA",
    "sg:tags":[
        "grocer"
    ],
    "wof:name":"LA Esperanza Tricolor",
    "wof:placetype":"venue"
},
  "geometry": {"coordinates":[-122.039999,37.529515],"type":"Point"}
}