{
  "type": "Feature",
  "properties": {
    "iso:country":"US",
    "sg:address":"735 Fathom Drive",
    "sg:city":"San Mateo",
    "sg:classifiers":[
        {
            "category":"Real Estate",
            "subcategory":"Real Estate Operator",
            "type":"Services"
        }
    ],
    "sg:phone":"+1 650 573 7097",
    "sg:postcode":"94404",
    "sg:province":"CA",
    "sg:tags":[
        "apartment"
    ],
    "wof:name":"Mariner's Island West Apartments",
    "wof:placetype":"venue"
},
  "geometry": {"coordinates":[-122.28703299999999,37.563899],"type":"Point"}
}