{
  "type": "Feature",
  "properties": {
    "addr:full":"643 W Broadway Long Beach CA 90802",
    "addr:housenumber":"643",
    "addr:postcode":"90802",
    "addr:street":"W Broadway",
    "iso:country":"US",
    "sg:address":"643 W Broadway",
    "sg:city":"Long Beach",
    "sg:classifiers":[
        {
            "category":"Professional",
            "subcategory":"Art Services",
            "type":"Services"
        }
    ],
    "sg:phone":"+1 562 276 3335",
    "sg:postcode":"90802",
    "sg:province":"CA",
    "sg:tags":[
        "artist"
    ],
    "wof:name":"Joseph Giri Artworks",
    "wof:placetype":"venue"
},
  "geometry": {"coordinates":[-118.200458,33.769355],"type":"Point"}
}