{
  "type": "Feature",
  "properties": {
    "addr:full":"10624 Opal Ave Redlands CA 92374",
    "addr:housenumber":"10624",
    "addr:postcode":"92374",
    "addr:street":"Opal Ave",
    "iso:country":"US",
    "sg:address":"10624 Opal Ave",
    "sg:city":"Redlands",
    "sg:classifiers":[
        {
            "category":"Building & Trades",
            "subcategory":"Construction",
            "type":"Services"
        }
    ],
    "sg:phone":"+1 909 798 4011",
    "sg:postcode":"92374",
    "sg:province":"CA",
    "sg:tags":[
        "coping",
        "plastering",
        "tiling",
        "pool",
        "swimming"
    ],
    "wof:name":"Clean Sweep Pool Svc",
    "wof:placetype":"venue"
},
  "geometry": {"coordinates":[-117.134548,34.059161],"type":"Point"}
}