{
  "type": "Feature",
  "properties": {
    "iso:country":"US",
    "sg:address":"1905 N Marshall Ave",
    "sg:city":"El Cajon",
    "sg:classifiers":[
        {
            "category":"Autos & Motor Vehicles",
            "subcategory":"Automobile Sales",
            "type":"Retail Goods"
        }
    ],
    "sg:phone":"+1 619 448 2360",
    "sg:postcode":"92020",
    "sg:province":"CA",
    "sg:tags":[
        "aircraft"
    ],
    "wof:name":"Mc Dowell Aviation",
    "wof:placetype":"venue"
},
  "geometry": {"coordinates":[-116.975764,32.817972],"type":"Point"}
}