{
  "type": "Feature",
  "properties": {
    "iso:country":"US",
    "sg:address":"1120 14th St Ste 4",
    "sg:city":"Modesto",
    "sg:classifiers":[
        {
            "category":"Real Estate",
            "subcategory":"Architect",
            "type":"Services"
        }
    ],
    "sg:phone":"+1 209 529 5943",
    "sg:postcode":"95354",
    "sg:province":"CA",
    "wof:name":"Holmdahl Paul F Architect",
    "wof:placetype":"venue"
},
  "geometry": {"coordinates":[-120.998001,37.6446],"type":"Point"}
}