{
  "type": "Feature",
  "properties": {
    "iso:country":"US",
    "sg:address":"25675 Potrero Park Dr",
    "sg:city":"Potrero",
    "sg:classifiers":[
        {
            "category":"Shopping",
            "subcategory":"Department Store",
            "type":"Retail Goods"
        }
    ],
    "sg:phone":"+1 619 478 9160",
    "sg:postcode":"91963",
    "sg:province":"CA",
    "sg:tags":[
        "shop"
    ],
    "wof:name":"A & A Discount Septic",
    "wof:placetype":"venue"
},
  "geometry": {"coordinates":[-116.60448599999999,32.615094],"type":"Point"}
}