{
  "type": "Feature",
  "properties": {
    "iso:country":"US",
    "sg:address":"4420 N 1st St",
    "sg:city":"Fresno",
    "sg:classifiers":[
        {
            "category":"Health Services",
            "subcategory":"Clinic",
            "type":"Services"
        }
    ],
    "sg:phone":"+1 559 221 1550",
    "sg:postcode":"93726",
    "sg:province":"CA",
    "sg:tags":[
        "specialty",
        "outpatient"
    ],
    "wof:name":"Spanger Dale Lcsw",
    "wof:placetype":"venue"
},
  "geometry": {"coordinates":[-119.772186,36.7984],"type":"Point"}
}