{
  "type": "Feature",
  "properties": {
    "addr:full":"1919 Williams St Simi Valley CA 93065",
    "addr:housenumber":"1919",
    "addr:postcode":"93065",
    "addr:street":"Williams St",
    "iso:country":"US",
    "sg:address":"1919 Williams St",
    "sg:city":"Simi Valley",
    "sg:classifiers":[
        {
            "category":"Professional",
            "subcategory":"Lawyer & Legal Services",
            "type":"Services"
        }
    ],
    "sg:phone":"+1 805 522 5628",
    "sg:postcode":"93065",
    "sg:province":"CA",
    "sg:tags":[
        "attorney"
    ],
    "sg:website":"www.cramptonlaw.com",
    "wof:name":"Elisabeth Crampton Law Office",
    "wof:placetype":"venue"
},
  "geometry": {"coordinates":[-118.774005,34.271538],"type":"Point"}
}