{
  "type": "Feature",
  "properties": {
    "addr:full":"18488 Prospect Rd Saratoga CA 95129",
    "addr:housenumber":"18488",
    "addr:postcode":"95129",
    "addr:street":"Prospect Rd",
    "iso:country":"US",
    "sg:address":"18488 Prospect Rd",
    "sg:city":"Saratoga",
    "sg:classifiers":[
        {
            "category":"Freight",
            "type":"Transportation"
        }
    ],
    "sg:phone":"+1 408 863 9933",
    "sg:postcode":"95129",
    "sg:province":"CA",
    "sg:tags":[
        "storage"
    ],
    "wof:name":"Building Storage",
    "wof:placetype":"venue"
},
  "geometry": {"coordinates":[-122.002377,37.292961],"type":"Point"}
}