{
  "type": "Feature",
  "properties": {
    "addr:full":"191 S Indian Hill Blvd Claremont CA 91711",
    "addr:housenumber":"191",
    "addr:postcode":"91711",
    "addr:street":"S Indian Hill Blvd",
    "iso:country":"US",
    "sg:address":"191 S Indian Hill Blvd",
    "sg:city":"Claremont",
    "sg:classifiers":[
        {
            "category":"Autos & Motor Vehicles",
            "subcategory":"Automobile Sales",
            "type":"Retail Goods"
        }
    ],
    "sg:phone":"+1 909 624 4541",
    "sg:postcode":"91711",
    "sg:province":"CA",
    "sg:tags":[
        "car",
        "dealer"
    ],
    "sg:website":"www.hibbardchevrolet.com",
    "wof:name":"Richard Hibbard Chevrolet Inc",
    "wof:placetype":"venue"
},
  "geometry": {"coordinates":[-117.71939,34.093114],"type":"Point"}
}