{
  "type": "Feature",
  "properties": {
    "iso:country":"US",
    "sg:address":"1001 E 60th St",
    "sg:city":"Los Angeles",
    "sg:classifiers":[
        {
            "category":"Manufacturing",
            "subcategory":"Furniture",
            "type":"Manufacturing & Wholesale Goods"
        }
    ],
    "sg:phone":"+1 323 231 4275",
    "sg:postcode":"90001",
    "sg:province":"CA",
    "sg:tags":[
        "household",
        "metal",
        "mfg"
    ],
    "wof:name":"Iron Beds of America",
    "wof:placetype":"venue"
},
  "geometry": {"coordinates":[-118.25671699999999,33.985769],"type":"Point"}
}