{
  "type": "Feature",
  "properties": {
    "addr:full":"4322 Sepulveda Blvd Culver City CA 90230",
    "addr:housenumber":"4322",
    "addr:postcode":"90230",
    "addr:street":"Sepulveda Blvd",
    "iso:country":"US",
    "sg:address":"4322 Sepulveda Blvd",
    "sg:city":"Culver City",
    "sg:classifiers":[
        {
            "category":"Shopping",
            "type":"Retail Goods"
        }
    ],
    "sg:phone":"+1 310 915 7644",
    "sg:postcode":"90230",
    "sg:province":"CA",
    "wof:name":"Botanica Lafe",
    "wof:placetype":"venue"
},
  "geometry": {"coordinates":[-118.40909499999999,34.004264],"type":"Point"}
}