{
  "type": "Feature",
  "properties": {
    "addr:full":"1904 E Rosecrans Ave Compton CA 90221",
    "addr:housenumber":"1904",
    "addr:postcode":"90221",
    "addr:street":"E Rosecrans Ave",
    "iso:country":"US",
    "sg:address":"1904 E Rosecrans Ave",
    "sg:city":"Compton",
    "sg:classifiers":[
        {
            "category":"Home & Garden",
            "subcategory":"Carpets & Floor Coverings",
            "type":"Retail Goods"
        }
    ],
    "sg:phone":"+1 310 639 2002",
    "sg:postcode":"90221",
    "sg:province":"CA",
    "sg:tags":[
        "flooring"
    ],
    "wof:name":"Sandy Flooring",
    "wof:placetype":"venue"
},
  "geometry": {"coordinates":[-118.203041,33.903331],"type":"Point"}
}