{
  "type": "Feature",
  "properties": {
    "iso:country":"US",
    "sg:address":"24264 Valencia Blvd",
    "sg:city":"Valencia",
    "sg:classifiers":[
        {
            "category":"Home & Garden",
            "subcategory":"Furniture",
            "type":"Retail Goods"
        }
    ],
    "sg:phone":"+1 661 287 0050",
    "sg:postcode":"91355",
    "sg:province":"CA",
    "sg:tags":[
        "store"
    ],
    "sg:website":"www.fullbloom.net",
    "wof:name":"Full Bloom",
    "wof:placetype":"venue"
},
  "geometry": {"coordinates":[-118.55897299999999,34.413081],"type":"Point"}
}