{
  "type": "Feature",
  "properties": {
    "addr:full":"428 J St Sacramento CA 95814",
    "addr:housenumber":"428",
    "addr:postcode":"95814",
    "addr:street":"J St",
    "iso:country":"US",
    "sg:address":"428 J St",
    "sg:city":"Sacramento",
    "sg:classifiers":[
        {
            "category":"Government",
            "subcategory":"Office",
            "type":"Public Place"
        }
    ],
    "sg:phone":"+1 916 322 5660",
    "sg:postcode":"95814",
    "sg:province":"CA",
    "sg:tags":[
        "state"
    ],
    "sg:website":"www.fppc.ca.gov",
    "wof:name":"Fair Political Practices Comm",
    "wof:placetype":"venue"
},
  "geometry": {"coordinates":[-121.500417,38.582113],"type":"Point"}
}