{
  "type": "Feature",
  "properties": {
    "iso:country":"US",
    "sg:address":"1220 S Diamond Bar Blvd",
    "sg:city":"Diamond Bar",
    "sg:classifiers":[
        {
            "category":"Personal",
            "subcategory":"Beauty Salon",
            "type":"Services"
        }
    ],
    "sg:phone":"+1 909 612 0307",
    "sg:postcode":"91765",
    "sg:province":"CA",
    "wof:name":"Charming",
    "wof:placetype":"venue"
},
  "geometry": {"coordinates":[-117.811429,34.000134],"type":"Point"}
}