{
  "type": "Feature",
  "properties": {
    "addr:full":"1055 Oro Dam Blvd E Oroville CA 95965",
    "addr:housenumber":"1055",
    "addr:postcode":"95965",
    "addr:street":"Oro Dam Blvd E",
    "iso:country":"US",
    "sg:address":"1055 Oro Dam Blvd E",
    "sg:city":"Oroville",
    "sg:classifiers":[
        {
            "category":"Food & Beverages",
            "subcategory":"Liquor & Beverages",
            "type":"Retail Goods"
        }
    ],
    "sg:phone":"+1 530 533 8520",
    "sg:postcode":"95965",
    "sg:province":"CA",
    "wof:name":"Oro Dam Liquor Store",
    "wof:placetype":"venue"
},
  "geometry": {"coordinates":[-121.56223300000001,39.500672],"type":"Point"}
}