{
  "type": "Feature",
  "properties": {
    "addr:full":"611 Berrellessa St Martinez CA 94553",
    "addr:housenumber":"611",
    "addr:postcode":"94553",
    "addr:street":"Berrellessa St",
    "iso:country":"US",
    "sg:address":"611 Berrellessa St",
    "sg:city":"Martinez",
    "sg:classifiers":[
        {
            "category":"Organizations",
            "subcategory":"Labor Organization",
            "type":"Services"
        }
    ],
    "sg:phone":"+1 925 228 0930",
    "sg:postcode":"94553",
    "sg:province":"CA",
    "wof:name":"Laborers International Union",
    "wof:placetype":"venue"
},
  "geometry": {"coordinates":[-122.13884899999999,38.01606],"type":"Point"}
}