{
  "type": "Feature",
  "properties": {
    "iso:country":"US",
    "sg:address":"2894 S Larkfield Ave",
    "sg:city":"Arcadia",
    "sg:classifiers":[
        {
            "category":"Building & Trades",
            "subcategory":"Construction",
            "type":"Services"
        }
    ],
    "sg:phone":"+1 626 574 7267",
    "sg:postcode":"91006",
    "sg:province":"CA",
    "sg:tags":[
        "house",
        "architectural"
    ],
    "wof:name":"Hung Chou & Associates",
    "wof:placetype":"venue"
},
  "geometry": {"coordinates":[-118.00830999999999,34.112789],"type":"Point"}
}