{
  "type": "Feature",
  "properties": {
    "iso:country":"US",
    "sg:address":"663 W 2nd St",
    "sg:city":"San Bernardino",
    "sg:classifiers":[
        {
            "category":"Retail",
            "subcategory":"Laundry & Dry Cleaning",
            "type":"Services"
        }
    ],
    "sg:phone":"+1 909 384 1829",
    "sg:postcode":"92410",
    "sg:province":"CA",
    "sg:tags":[
        "cleaners"
    ],
    "wof:name":"Family Cleaners",
    "wof:placetype":"venue"
},
  "geometry": {"coordinates":[-117.297417,34.102672],"type":"Point"}
}