{
  "type": "Feature",
  "properties": {
    "iso:country":"US",
    "sg:address":"107 E Pico Blvd",
    "sg:city":"Los Angeles",
    "sg:classifiers":[
        {
            "category":"Wholesale",
            "subcategory":"Durable Goods & Equipment",
            "type":"Manufacturing & Wholesale Goods"
        }
    ],
    "sg:phone":"+1 213 746 0721",
    "sg:postcode":"90015",
    "sg:province":"CA",
    "sg:tags":[
        "luggage"
    ],
    "wof:name":"Vigafon Sport",
    "wof:placetype":"venue"
},
  "geometry": {"coordinates":[-118.25935,34.035832],"type":"Point"}
}