{
  "type": "Feature",
  "properties": {
    "addr:full":"2151 Salvio St Concord CA 94519",
    "addr:housenumber":"2151",
    "addr:postcode":"94519",
    "addr:street":"Salvio St",
    "iso:country":"US",
    "sg:address":"2151 Salvio St",
    "sg:city":"Concord",
    "sg:classifiers":[
        {
            "category":"Insurance",
            "subcategory":"Insurance Agent",
            "type":"Services"
        }
    ],
    "sg:phone":"+1 925 363 9919",
    "sg:postcode":"94519",
    "sg:province":"CA",
    "wof:name":"Allstate Insurance",
    "wof:placetype":"venue"
},
  "geometry": {"coordinates":[-122.034113,37.977776],"type":"Point"}
}