{
  "type": "Feature",
  "properties": {
    "iso:country":"US",
    "sg:address":"101 H St",
    "sg:city":"San Rafael",
    "sg:classifiers":[
        {
            "category":"Insurance",
            "subcategory":"Insurance Agent",
            "type":"Services"
        }
    ],
    "sg:phone":"+1 415 459 8890",
    "sg:postcode":"94901",
    "sg:province":"CA",
    "wof:name":"Raymond La Rocca",
    "wof:placetype":"venue"
},
  "geometry": {"coordinates":[-122.538292,37.975498],"type":"Point"}
}