{
  "type": "Feature",
  "properties": {
    "iso:country":"US",
    "sg:address":"522 Merritt Ave Apt A",
    "sg:city":"Oakland",
    "sg:classifiers":[
        {
            "category":"Wholesale",
            "subcategory":"Hardware",
            "type":"Manufacturing & Wholesale Goods"
        }
    ],
    "sg:phone":"+1 510 836 2745",
    "sg:postcode":"94610",
    "sg:province":"CA",
    "sg:tags":[
        "hardware-wholesale",
        "manufacturer"
    ],
    "wof:name":"C Bradley Products",
    "wof:placetype":"venue"
},
  "geometry": {"coordinates":[-122.247558,37.807264],"type":"Point"}
}