{
  "type": "Feature",
  "properties": {
    "addr:full":"5813 Geary Blvd San Francisco CA 94121",
    "addr:housenumber":"5813",
    "addr:postcode":"94121",
    "addr:street":"Geary Blvd",
    "iso:country":"US",
    "sg:address":"5813 Geary Blvd",
    "sg:city":"San Francisco",
    "sg:classifiers":[
        {
            "category":"Travel",
            "subcategory":"Travel Agent",
            "type":"Entertainment"
        }
    ],
    "sg:phone":"+1 888 929 2954",
    "sg:postcode":"94121",
    "sg:province":"CA",
    "sg:website":"wayby.com",
    "wof:name":"Wayby",
    "wof:placetype":"venue"
},
  "geometry": {"coordinates":[-122.48184500000001,37.779915],"type":"Point"}
}