{
  "type": "Feature",
  "properties": {
    "iso:country":"US",
    "sg:address":"6281 Beach Blvd Ste 208",
    "sg:city":"Buena Park",
    "sg:classifiers":[
        {
            "category":"Professional",
            "subcategory":"Lawyer & Legal Services",
            "type":"Services"
        }
    ],
    "sg:phone":"+1 714 670 7100",
    "sg:postcode":"90621",
    "sg:province":"CA",
    "wof:name":"Law Offices Of Jerry Kaufman",
    "wof:placetype":"venue"
},
  "geometry": {"coordinates":[-117.998419,33.869107],"type":"Point"}
}