{
  "type": "Feature",
  "properties": {
    "addr:full":"3011 W Bullard Ave Fresno CA 93711",
    "addr:housenumber":"3011",
    "addr:postcode":"93711",
    "addr:street":"W Bullard Ave",
    "iso:country":"US",
    "sg:address":"3011 W Bullard Ave",
    "sg:city":"Fresno",
    "sg:classifiers":[
        {
            "category":"Personal",
            "subcategory":"Beauty Salon",
            "type":"Services"
        }
    ],
    "sg:phone":"+1 559 436 1736",
    "sg:postcode":"93711",
    "sg:province":"CA",
    "wof:name":"A Golden Touch",
    "wof:placetype":"venue"
},
  "geometry": {"coordinates":[-119.844652,36.822573],"type":"Point"}
}