{
  "type": "Feature",
  "properties": {
    "addr:full":"965 Alamo Dr Vacaville CA 95687",
    "addr:housenumber":"965",
    "addr:postcode":"95687",
    "addr:street":"Alamo Dr",
    "iso:country":"US",
    "sg:address":"965 Alamo Dr",
    "sg:city":"Vacaville",
    "sg:classifiers":[
        {
            "category":"Building & Trades",
            "subcategory":"Construction",
            "type":"Services"
        }
    ],
    "sg:phone":"+1 707 453 0280",
    "sg:postcode":"95687",
    "sg:province":"CA",
    "sg:tags":[
        "general",
        "contractor"
    ],
    "wof:name":"Tri-Valley Builders Group",
    "wof:placetype":"venue"
},
  "geometry": {"coordinates":[-121.995853,38.343875],"type":"Point"}
}