{
  "type": "Feature",
  "properties": {
    "addr:full":"1113 High St Auburn CA 95603",
    "addr:housenumber":"1113",
    "addr:postcode":"ca 95603",
    "addr:street":"High St",
    "iso:country":"US",
    "sg:address":"1113 High St",
    "sg:city":"Auburn",
    "sg:classifiers":[
        {
            "category":"Building & Trades",
            "subcategory":"Construction",
            "type":"Services"
        }
    ],
    "sg:phone":"+1 530 888 6673",
    "sg:postcode":"95603",
    "sg:province":"CA",
    "sg:tags":[
        "concrete",
        "cutting",
        "demolition",
        "breaking",
        "sawing"
    ],
    "wof:name":"Aces Concrete Sawing Breaking",
    "wof:placetype":"venue"
},
  "geometry": {"coordinates":[-121.071364,38.897159],"type":"Point"}
}