{
  "type": "Feature",
  "properties": {
    "addr:full":"333 Blanchard Ln Benicia CA 94510",
    "addr:housenumber":"333",
    "addr:postcode":"94510",
    "addr:street":"Blanchard Ln",
    "iso:country":"US",
    "sg:address":"333 Blanchard Ln",
    "sg:city":"Benicia",
    "sg:classifiers":[
        {
            "category":"Building & Trades",
            "subcategory":"Construction",
            "type":"Services"
        }
    ],
    "sg:phone":"+1 925 513 3691",
    "sg:postcode":"94510",
    "sg:province":"CA",
    "sg:tags":[
        "builder",
        "stair"
    ],
    "wof:name":"Bay Area Stairs",
    "wof:placetype":"venue"
},
  "geometry": {"coordinates":[-122.15638,38.061856],"type":"Point"}
}