{
  "type": "Feature",
  "properties": {
    "addr:full":"3840 Madison Avenue North Highlands CA 95660",
    "addr:housenumber":"3840",
    "addr:postcode":"95660",
    "addr:street":"Madison Avenue",
    "iso:country":"US",
    "sg:address":"3840 Madison Avenue",
    "sg:city":"North Highlands",
    "sg:classifiers":[
        {
            "category":"Food & Beverages",
            "subcategory":"Groceries & Convenience Stores",
            "type":"Retail Goods"
        }
    ],
    "sg:phone":"+1 916 348 6564",
    "sg:postcode":"95660",
    "sg:province":"CA",
    "wof:name":"Discount Grocery Store",
    "wof:placetype":"venue"
},
  "geometry": {"coordinates":[-121.37433299999999,38.661052],"type":"Point"}
}