{
  "type": "Feature",
  "properties": {
    "iso:country":"US",
    "sg:address":"1804 Placentia Ave",
    "sg:city":"Costa Mesa",
    "sg:classifiers":[
        {
            "category":"Shopping",
            "subcategory":"Clothing, Apparel, & Fashions",
            "type":"Retail Goods"
        }
    ],
    "sg:phone":"+1 949 645 8431",
    "sg:postcode":"92627",
    "sg:province":"CA",
    "sg:tags":[
        "item",
        "boutique"
    ],
    "wof:name":"Balboa Blues Boutique",
    "wof:placetype":"venue"
},
  "geometry": {"coordinates":[-117.931866,33.640212],"type":"Point"}
}