{
  "type": "Feature",
  "properties": {
    "addr:full":"968 2nd St Novato CA 94945",
    "addr:housenumber":"968",
    "addr:postcode":"94945",
    "addr:street":"2Nd St",
    "iso:country":"US",
    "sg:address":"968 2nd St",
    "sg:city":"Novato",
    "sg:classifiers":[
        {
            "category":"Professional",
            "type":"Services"
        }
    ],
    "sg:phone":"+1 415 209 6665",
    "sg:postcode":"94945",
    "sg:province":"CA",
    "wof:name":"Other Co",
    "wof:placetype":"venue"
},
  "geometry": {"coordinates":[-122.572686,38.108016],"type":"Point"}
}