{
  "type": "Feature",
  "properties": {
    "addr:full":"18502 Yorba Linda Blvd Yorba Linda CA 92886",
    "addr:housenumber":"18502",
    "addr:postcode":"92886",
    "addr:street":"Yorba Linda Blvd",
    "iso:country":"US",
    "sg:address":"18502 Yorba Linda Blvd",
    "sg:city":"Yorba Linda",
    "sg:classifiers":[
        {
            "category":"Retail",
            "subcategory":"Laundry & Dry Cleaning",
            "type":"Services"
        }
    ],
    "sg:phone":"+1 714 777 8277",
    "sg:postcode":"92886",
    "sg:province":"CA",
    "wof:name":"Lake View Cleaners",
    "wof:placetype":"venue"
},
  "geometry": {"coordinates":[-117.810997,33.888401],"type":"Point"}
}