{
  "type": "Feature",
  "properties": {
    "addr:full":"23922 de Ville Way Malibu CA 90265",
    "addr:postcode":"23922;90265",
    "addr:street":"De Ville Way",
    "iso:country":"US",
    "sg:address":"23922 de Ville Way",
    "sg:city":"Malibu",
    "sg:classifiers":[
        {
            "category":"Real Estate",
            "subcategory":"Real Estate Agent",
            "type":"Services"
        }
    ],
    "sg:phone":"+1 310 456 3878",
    "sg:postcode":"90265",
    "sg:province":"CA",
    "wof:name":"Mac Neil & Co",
    "wof:placetype":"venue"
},
  "geometry": {"coordinates":[-118.696296,34.03673],"type":"Point"}
}