{
  "type": "Feature",
  "properties": {
    "addr:full":"6680 Crescent St Ventura CA 93003",
    "addr:housenumber":"6680",
    "addr:postcode":"93003",
    "addr:street":"Crescent St",
    "iso:country":"US",
    "sg:address":"6680 Crescent St",
    "sg:city":"Ventura",
    "sg:classifiers":[
        {
            "category":"Retail",
            "subcategory":"Auto Repair",
            "type":"Services"
        }
    ],
    "sg:phone":"+1 805 650 9212",
    "sg:postcode":"93003",
    "sg:province":"CA",
    "sg:tags":[
        "body",
        "automobile",
        "painting"
    ],
    "wof:name":"J & C Collision Ctr",
    "wof:placetype":"venue"
},
  "geometry": {"coordinates":[-119.197209,34.250406],"type":"Point"}
}