{
  "type": "Feature",
  "properties": {
    "iso:country":"US",
    "sg:address":"11821 Lamplighter St",
    "sg:city":"Garden Grove",
    "sg:classifiers":[
        {
            "category":"Manufacturing",
            "subcategory":"Metals",
            "type":"Manufacturing & Wholesale Goods"
        }
    ],
    "sg:phone":"+1 714 899 9031",
    "sg:postcode":"92845",
    "sg:province":"CA",
    "sg:tags":[
        "steel",
        "stainless"
    ],
    "sg:website":"www.bodywireco.com",
    "wof:name":"Body Wire Co",
    "wof:placetype":"venue"
},
  "geometry": {"coordinates":[-118.015541,33.789613],"type":"Point"}
}