{
  "type": "Feature",
  "properties": {
    "iso:country":"US",
    "sg:address":"16250 Ventura Blvd",
    "sg:city":"Encino",
    "sg:classifiers":[
        {
            "category":"Wholesale",
            "subcategory":"Durable Goods & Equipment",
            "type":"Manufacturing & Wholesale Goods"
        }
    ],
    "sg:phone":"+1 818 385 0303",
    "sg:postcode":"91436",
    "sg:province":"CA",
    "sg:tags":[
        "professional"
    ],
    "wof:name":"Ortho Enginnering",
    "wof:placetype":"venue"
},
  "geometry": {"coordinates":[-118.485258,34.15644],"type":"Point"}
}