{
  "type": "Feature",
  "properties": {
    "iso:country":"US",
    "sg:address":"6050 Commerce Blvd",
    "sg:city":"Rohnert Park",
    "sg:classifiers":[
        {
            "category":"Organizations",
            "subcategory":"Professional Association",
            "type":"Services"
        }
    ],
    "sg:phone":"+1 707 584 1415",
    "sg:postcode":"94928",
    "sg:province":"CA",
    "sg:tags":[
        "chambers",
        "commerce"
    ],
    "sg:website":"www.rpchamber.org",
    "wof:name":"Rohnert Park Chamber-Commerce",
    "wof:placetype":"venue"
},
  "geometry": {"coordinates":[-122.709553,38.351127],"type":"Point"}
}