{
  "type": "Feature",
  "properties": {
    "addr:full":"8859 Balboa Avenue San Diego CA 92123",
    "addr:housenumber":"8859",
    "addr:postcode":"92123",
    "addr:street":"Balboa Avenue",
    "iso:country":"US",
    "sg:address":"8859 Balboa Avenue",
    "sg:city":"San Diego",
    "sg:classifiers":[
        {
            "category":"Communications",
            "type":"Services"
        }
    ],
    "sg:phone":"+1 858 277 2540",
    "sg:postcode":"92123",
    "sg:province":"CA",
    "sg:tags":[
        "recording",
        "rehearsal",
        "studio"
    ],
    "wof:name":"Advance Recording Products",
    "wof:placetype":"venue"
},
  "geometry": {"coordinates":[-117.13780300000001,32.820583],"type":"Point"}
}