{
  "type": "Feature",
  "properties": {
    "iso:country":"US",
    "sg:address":"5753 W Las Positas Blvd",
    "sg:city":"Pleasanton",
    "sg:classifiers":[
        {
            "category":"Manufacturing",
            "subcategory":"Printing",
            "type":"Manufacturing & Wholesale Goods"
        }
    ],
    "sg:phone":"+1 925 251 0640",
    "sg:postcode":"94588",
    "sg:province":"CA",
    "sg:tags":[
        "publisher",
        "software"
    ],
    "wof:name":"Trapeze Network",
    "wof:placetype":"venue"
},
  "geometry": {"coordinates":[-121.893308,37.685572],"type":"Point"}
}