{
  "type": "Feature",
  "properties": {
    "addr:full":"950 Rio Vista Dr Pacifica CA 94044",
    "addr:housenumber":"950",
    "addr:postcode":"94044",
    "addr:street":"Rio Vista Dr",
    "iso:country":"US",
    "sg:address":"950 Rio Vista Dr",
    "sg:city":"Pacifica",
    "sg:classifiers":[
        {
            "category":"Manufacturing",
            "subcategory":"Apparel",
            "type":"Manufacturing & Wholesale Goods"
        }
    ],
    "sg:phone":"+1 650 738 0456",
    "sg:postcode":"94044",
    "sg:province":"CA",
    "sg:tags":[
        "accessory"
    ],
    "wof:name":"Vince's Tight Access",
    "wof:placetype":"venue"
},
  "geometry": {"coordinates":[-122.492924,37.584579],"type":"Point"}
}