{
  "type": "Feature",
  "properties": {
    "iso:country":"US",
    "sg:address":"342 W Napa St",
    "sg:city":"Sonoma",
    "sg:classifiers":[
        {
            "category":"Education",
            "subcategory":"School",
            "type":"Public Place"
        }
    ],
    "sg:phone":"+1 707 996 4994",
    "sg:postcode":"95476",
    "sg:province":"CA",
    "wof:name":"St Francis Solano School",
    "wof:placetype":"venue"
},
  "geometry": {"coordinates":[-122.464851,38.292667],"type":"Point"}
}