{
  "type": "Feature",
  "properties": {
    "iso:country":"US",
    "sg:address":"2001 E Gladstone St",
    "sg:city":"Glendora",
    "sg:classifiers":[
        {
            "category":"Wholesale",
            "subcategory":"Durable Goods & Equipment",
            "type":"Manufacturing & Wholesale Goods"
        }
    ],
    "sg:phone":"+1 626 806 3047",
    "sg:postcode":"91740",
    "sg:province":"CA",
    "sg:tags":[
        "dist",
        "mfg"
    ],
    "wof:name":"Four Season Manufacturing Co",
    "wof:placetype":"venue"
},
  "geometry": {"coordinates":[-117.83956000000001,34.113985],"type":"Point"}
}