{
  "type": "Feature",
  "properties": {
    "iso:country":"US",
    "sg:address":"1635 Muller Dr",
    "sg:city":"Napa",
    "sg:classifiers":[
        {
            "category":"Professional",
            "type":"Services"
        }
    ],
    "sg:phone":"+1 707 257 0905",
    "sg:postcode":"94559",
    "sg:province":"CA",
    "wof:name":"Nevaeh",
    "wof:placetype":"venue"
},
  "geometry": {"coordinates":[-122.297697,38.300147],"type":"Point"}
}