{
  "type": "Feature",
  "properties": {
    "iso:country":"US",
    "sg:address":"8547 Westminster Ave",
    "sg:city":"Garden Grove",
    "sg:classifiers":[
        {
            "category":"Restaurant",
            "type":"Food & Drink"
        }
    ],
    "sg:phone":"+1 714 895 7964",
    "sg:postcode":"92844",
    "sg:province":"CA",
    "sg:tags":[
        "seafood",
        "chinese"
    ],
    "sg:website":"www.seafoodcove.com",
    "wof:name":"Seafood Cove",
    "wof:placetype":"venue"
},
  "geometry": {"coordinates":[-117.981003,33.759499],"type":"Point"}
}