{
  "type": "Feature",
  "properties": {
    "iso:country":"US",
    "sg:address":"430 Center St",
    "sg:city":"Manteca",
    "sg:classifiers":[
        {
            "category":"Utilities",
            "subcategory":"Electric",
            "type":"Services"
        }
    ],
    "sg:phone":"+1 209 239 0226",
    "sg:postcode":"95337",
    "sg:province":"CA",
    "sg:tags":[
        "communications",
        "telephone"
    ],
    "wof:name":"Verizon",
    "wof:placetype":"venue"
},
  "geometry": {"coordinates":[-121.220457,37.799037],"type":"Point"}
}