{
  "type": "Feature",
  "properties": {
    "iso:country":"US",
    "sg:address":"455 S Union Ave",
    "sg:city":"Los Angeles",
    "sg:classifiers":[
        {
            "category":"Real Estate",
            "subcategory":"Real Estate Agent",
            "type":"Services"
        }
    ],
    "sg:phone":"+1 213 483 7535",
    "sg:postcode":"90017",
    "sg:province":"CA",
    "sg:tags":[
        "authorities",
        "housing"
    ],
    "wof:name":"Housing Authority-The City",
    "wof:placetype":"venue"
},
  "geometry": {"coordinates":[-118.26987699999999,34.057441],"type":"Point"}
}