{
  "type": "Feature",
  "properties": {
    "addr:full":"35512 Avenue H Yucaipa CA 92399",
    "addr:housenumber":"35512",
    "addr:postcode":"92399",
    "addr:street":"Avenue H",
    "iso:country":"US",
    "sg:address":"35512 Avenue H",
    "sg:city":"Yucaipa",
    "sg:classifiers":[
        {
            "category":"Building & Trades",
            "subcategory":"Electrical",
            "type":"Services"
        }
    ],
    "sg:phone":"+1 909 446 0606",
    "sg:postcode":"92399",
    "sg:province":"CA",
    "sg:tags":[
        "electrician"
    ],
    "wof:name":"Working Electric & Air Conditioning Inc",
    "wof:placetype":"venue"
},
  "geometry": {"coordinates":[-117.029999,34.010201],"type":"Point"}
}