{
  "type": "Feature",
  "properties": {
    "iso:country":"US",
    "sg:address":"651 Division St",
    "sg:city":"Campbell",
    "sg:classifiers":[
        {
            "category":"Professional",
            "subcategory":"Employment Agencies",
            "type":"Services"
        }
    ],
    "sg:phone":"+1 408 871 9680",
    "sg:postcode":"95008",
    "sg:province":"CA",
    "sg:tags":[
        "opportunity"
    ],
    "wof:name":"Community Integrated Work Prog",
    "wof:placetype":"venue"
},
  "geometry": {"coordinates":[-121.958217,37.262581],"type":"Point"}
}