{
  "type": "Feature",
  "properties": {
    "addr:full":"10001 Venice Blvd. #107 Los Angeles CA 90034",
    "addr:housenumber":"10001",
    "addr:postcode":"90034",
    "addr:street":"Venice Blvd. # 107",
    "iso:country":"US",
    "sg:address":"10001 Venice Blvd. #107",
    "sg:city":"Los Angeles",
    "sg:classifiers":[
        {
            "category":"Professional",
            "subcategory":"Lawyer & Legal Services",
            "type":"Services"
        }
    ],
    "sg:phone":"+1 818 961 7739",
    "sg:postcode":"90034",
    "sg:province":"CA",
    "sg:website":"icentralagency.com#cid=yelp",
    "wof:name":"Central Investigations",
    "wof:placetype":"venue"
},
  "geometry": {"coordinates":[-118.39960600000001,34.022988],"type":"Point"}
}