{
  "type": "Feature",
  "properties": {
    "iso:country":"US",
    "sg:address":"256 Kearney Exd",
    "sg:city":"Watsonville",
    "sg:classifiers":[
        {
            "category":"Wholesale",
            "subcategory":"Motor Vehicles",
            "type":"Manufacturing & Wholesale Goods"
        }
    ],
    "sg:phone":"+1 831 761 6440",
    "sg:postcode":"95076",
    "sg:province":"CA",
    "sg:tags":[
        "automobile",
        "truck",
        "broker"
    ],
    "sg:website":"www.a1autotransport.com",
    "wof:name":"A 1 Auto Wholesale",
    "wof:placetype":"venue"
},
  "geometry": {"coordinates":[-121.765665,36.908469],"type":"Point"}
}