{
  "type": "Feature",
  "properties": {
    "addr:full":"9673 Baseline Rd Rancho Cucamonga CA 91730",
    "addr:housenumber":"9673",
    "addr:postcode":"91730",
    "addr:street":"Baseline Rd",
    "iso:country":"US",
    "sg:address":"9673 Baseline Rd",
    "sg:city":"Rancho Cucamonga",
    "sg:classifiers":[
        {
            "category":"Real Estate",
            "subcategory":"Real Estate Agent",
            "type":"Services"
        }
    ],
    "sg:phone":"+1 909 945 8899",
    "sg:postcode":"91730",
    "sg:province":"CA",
    "wof:name":"Era New Star Realty & Invest",
    "wof:placetype":"venue"
},
  "geometry": {"coordinates":[-117.59491300000001,34.121458],"type":"Point"}
}