{
  "type": "Feature",
  "properties": {
    "iso:country":"US",
    "sg:address":"9673 Baseline Rd",
    "sg:city":"Rancho Cucamonga",
    "sg:classifiers":[
        {
            "category":"Real Estate",
            "subcategory":"Real Estate Agent",
            "type":"Services"
        }
    ],
    "sg:phone":"+1 909 945 8899",
    "sg:postcode":"91730",
    "sg:province":"CA",
    "wof:name":"Era New Star Realty & Invest",
    "wof:placetype":"venue"
},
  "geometry": {"coordinates":[-117.594913,34.121458],"type":"Point"}
}