{
  "type": "Feature",
  "properties": {
    "addr:full":"14831 Chalk Hill Rd Healdsburg CA 95448",
    "addr:housenumber":"14831",
    "addr:postcode":"95448",
    "addr:street":"Chalk Hill Rd",
    "iso:country":"US",
    "sg:address":"14831 Chalk Hill Rd",
    "sg:city":"Healdsburg",
    "sg:classifiers":[
        {
            "category":"Farming",
            "subcategory":"Livestock Farm",
            "type":"Manufacturing & Wholesale Goods"
        }
    ],
    "sg:phone":"+1 707 433 7185",
    "sg:postcode":"95448",
    "sg:province":"CA",
    "sg:tags":[
        "ranch"
    ],
    "wof:name":"Burnett, S T Vineyard Co",
    "wof:placetype":"venue"
},
  "geometry": {"coordinates":[-122.77396,38.622553],"type":"Point"}
}