{
  "type": "Feature",
  "properties": {
    "iso:country":"US",
    "sg:address":"1930 Wilshire Blvd Ste 400",
    "sg:city":"Los Angeles",
    "sg:classifiers":[
        {
            "category":"Banks & Credit Unions",
            "subcategory":"Financial Services",
            "type":"Services"
        }
    ],
    "sg:phone":"+1 877 637 3361",
    "sg:postcode":"90057",
    "sg:province":"CA",
    "wof:name":"Solomon Finance",
    "wof:placetype":"venue"
},
  "geometry": {"coordinates":[-118.274378,34.057148],"type":"Point"}
}