{
  "type": "Feature",
  "properties": {
    "addr:full":"3594 National Ave San Diego CA 92113",
    "addr:housenumber":"3594",
    "addr:postcode":"92113",
    "addr:street":"National Ave",
    "iso:country":"US",
    "sg:address":"3594 National Ave",
    "sg:city":"San Diego",
    "sg:classifiers":[
        {
            "category":"Restaurant",
            "type":"Food & Drink"
        }
    ],
    "sg:phone":"+1 619 262 2003",
    "sg:postcode":"92113",
    "sg:province":"CA",
    "wof:name":"El Taco Rico",
    "wof:placetype":"venue"
},
  "geometry": {"coordinates":[-117.11682399999999,32.69603],"type":"Point"}
}