{
  "type": "Feature",
  "properties": {
    "addr:full":"2819 Darwin St Hayward CA 94545",
    "addr:housenumber":"2819",
    "addr:postcode":"94545",
    "addr:street":"Darwin St",
    "iso:country":"US",
    "sg:address":"2819 Darwin St",
    "sg:city":"Hayward",
    "sg:classifiers":[
        {
            "category":"Building & Trades",
            "subcategory":"Construction",
            "type":"Services"
        }
    ],
    "sg:phone":"+1 510 293 9323",
    "sg:postcode":"94545",
    "sg:province":"CA",
    "sg:tags":[
        "concrete",
        "contractor"
    ],
    "wof:name":"Paumau Concrete",
    "wof:placetype":"venue"
},
  "geometry": {"coordinates":[-122.10782,37.629195],"type":"Point"}
}