{
  "type": "Feature",
  "properties": {
    "addr:full":"111 W St. John St Ste 300 San Jose CA 95113",
    "addr:housenumber":"111",
    "addr:postcode":"95113",
    "addr:street":"W St. John St Ste 300",
    "iso:country":"US",
    "sg:address":"111 W St. John St Ste 300",
    "sg:city":"San Jose",
    "sg:classifiers":[
        {
            "category":"Professional",
            "subcategory":"Lawyer & Legal Services",
            "type":"Services"
        }
    ],
    "sg:phone":"+1 408 294 9544",
    "sg:postcode":"95113",
    "sg:province":"CA",
    "sg:tags":[
        "divorce",
        "law",
        "family"
    ],
    "wof:name":"Yates-Carter Lynne Atty",
    "wof:placetype":"venue"
},
  "geometry": {"coordinates":[-121.88870900000001,37.329006],"type":"Point"}
}