{
  "type": "Feature",
  "properties": {
    "iso:country":"US",
    "sg:address":"605 Cambridge Ave",
    "sg:city":"Menlo Park",
    "sg:classifiers":[
        {
            "category":"Personal",
            "subcategory":"Beauty Salon",
            "type":"Services"
        }
    ],
    "sg:phone":"+1 650 327 7877",
    "sg:postcode":"94025",
    "sg:province":"CA",
    "sg:tags":[
        "manicuring"
    ],
    "wof:name":"Jodie For Nails",
    "wof:placetype":"venue"
},
  "geometry": {"coordinates":[-122.175816,37.446224],"type":"Point"}
}