{
  "type": "Feature",
  "properties": {
    "addr:full":"520 Masefield Dr Pleasant Hill CA 94523",
    "addr:housenumber":"520",
    "addr:postcode":"94523",
    "addr:street":"Masefield Dr",
    "iso:country":"US",
    "sg:address":"520 Masefield Dr",
    "sg:city":"Pleasant Hill",
    "sg:classifiers":[
        {
            "category":"Building & Trades",
            "subcategory":"Landscaping Services",
            "type":"Services"
        }
    ],
    "sg:phone":"+1 925 935 8174",
    "sg:postcode":"94523",
    "sg:province":"CA",
    "sg:tags":[
        "landscape"
    ],
    "wof:name":"Mark Low Landscape",
    "wof:placetype":"venue"
},
  "geometry": {"coordinates":[-122.072287,37.937333],"type":"Point"}
}