{
  "type": "Feature",
  "properties": {
    "iso:country":"US",
    "sg:address":"2221 Martin Luther King Jr Way",
    "sg:city":"Oakland",
    "sg:classifiers":[
        {
            "category":"Government",
            "subcategory":"Office",
            "type":"Public Place"
        }
    ],
    "sg:phone":"+1 510 267 7820",
    "sg:postcode":"94612",
    "sg:province":"CA",
    "sg:tags":[
        "medical",
        "clinic"
    ],
    "wof:name":"Oakland V A Outpatient Clinic",
    "wof:placetype":"venue"
},
  "geometry": {"coordinates":[-122.272917,37.812169],"type":"Point"}
}