{
  "type": "Feature",
  "properties": {
    "addr:full":"559 Union Avenue Campbell CA 95008",
    "addr:housenumber":"559",
    "addr:postcode":"95008",
    "addr:street":"Union Avenue",
    "iso:country":"US",
    "sg:address":"559 Union Avenue",
    "sg:city":"Campbell",
    "sg:classifiers":[
        {
            "category":"Home & Garden",
            "subcategory":"Carpets & Floor Coverings",
            "type":"Retail Goods"
        }
    ],
    "sg:phone":"+1 408 371 7585",
    "sg:postcode":"95008",
    "sg:province":"CA",
    "sg:tags":[
        "carpeting"
    ],
    "wof:name":"Eddie's Carpets",
    "wof:placetype":"venue"
},
  "geometry": {"coordinates":[-121.93547,37.27902],"type":"Point"}
}