{
  "type": "Feature",
  "properties": {
    "iso:country":"US",
    "sg:address":"1915 Jackson St",
    "sg:city":"Burbank",
    "sg:classifiers":[
        {
            "category":"Professional",
            "type":"Services"
        }
    ],
    "sg:phone":"+1 818 567 2869",
    "sg:postcode":"91504",
    "sg:province":"CA",
    "wof:name":"Castillo De Ceramica",
    "wof:placetype":"venue"
},
  "geometry": {"coordinates":[-118.329837,34.195439],"type":"Point"}
}