{
  "type": "Feature",
  "properties": {
    "addr:full":"16540 Harbor Blvd Fountain Valley CA 92708",
    "addr:housenumber":"16540",
    "addr:postcode":"92708",
    "addr:street":"Harbor Blvd",
    "iso:country":"US",
    "sg:address":"16540 Harbor Blvd",
    "sg:city":"Fountain Valley",
    "sg:classifiers":[
        {
            "category":"Personal",
            "subcategory":"Beauty Salon",
            "type":"Services"
        }
    ],
    "sg:phone":"+1 714 839 9485",
    "sg:postcode":"92708",
    "sg:province":"CA",
    "wof:name":"Argentinas Beauty Salon Supply",
    "wof:placetype":"venue"
},
  "geometry": {"coordinates":[-117.920845,33.719728],"type":"Point"}
}