{
  "type": "Feature",
  "properties": {
    "iso:country":"US",
    "sg:address":"28873 Selfridge Dr",
    "sg:city":"Malibu",
    "sg:classifiers":[
        {
            "category":"Professional",
            "type":"Services"
        }
    ],
    "sg:phone":"+1 310 457 7397",
    "sg:postcode":"90265",
    "sg:province":"CA",
    "wof:name":"Sento Corp",
    "wof:placetype":"venue"
},
  "geometry": {"coordinates":[-118.8014,34.018574],"type":"Point"}
}