{
  "type": "Feature",
  "properties": {
    "iso:country":"US",
    "sg:address":"1893 Obispo Ave",
    "sg:city":"Signal Hill",
    "sg:classifiers":[
        {
            "category":"Autos & Motor Vehicles",
            "subcategory":"Motorcycle Sales",
            "type":"Retail Goods"
        }
    ],
    "sg:phone":"+1 562 498 1819",
    "sg:postcode":"90755",
    "sg:province":"CA",
    "wof:name":"Bennett's Performance V Twin",
    "wof:placetype":"venue"
},
  "geometry": {"coordinates":[-118.154999,33.792999],"type":"Point"}
}