{
  "type": "Feature",
  "properties": {
    "iso:country":"US",
    "sg:address":"2615 Bechelli Ln",
    "sg:city":"Redding",
    "sg:classifiers":[
        {
            "category":"Sports & Exercise",
            "subcategory":"Bowling",
            "type":"Entertainment"
        }
    ],
    "sg:phone":"+1 530 223 1080",
    "sg:postcode":"96002",
    "sg:province":"CA",
    "sg:tags":[
        "center"
    ],
    "wof:name":"Country Bowl",
    "wof:placetype":"venue"
},
  "geometry": {"coordinates":[-122.362538,40.570518],"type":"Point"}
}