{
  "type": "Feature",
  "properties": {
    "iso:country":"US",
    "sg:address":"3211 del Mar Way",
    "sg:city":"Sacramento",
    "sg:classifiers":[
        {
            "category":"Communications",
            "subcategory":"News Services",
            "type":"Services"
        }
    ],
    "sg:phone":"+1 916 924 8112",
    "sg:postcode":"95815",
    "sg:province":"CA",
    "wof:name":"Waynes Typemagic",
    "wof:placetype":"venue"
},
  "geometry": {"coordinates":[-121.43525099999999,38.62641],"type":"Point"}
}