{
  "type": "Feature",
  "properties": {
    "iso:country":"US",
    "sg:address":"4427 Candlewood St",
    "sg:city":"Lakewood",
    "sg:classifiers":[
        {
            "category":"Professional",
            "subcategory":"Lawyer & Legal Services",
            "type":"Services"
        }
    ],
    "sg:phone":"+1 562 602 0607",
    "sg:postcode":"90712",
    "sg:province":"CA",
    "sg:tags":[
        "notary"
    ],
    "sg:website":"www.postnet.com",
    "wof:name":"Post Net",
    "wof:placetype":"venue"
},
  "geometry": {"coordinates":[-118.140999,33.853901],"type":"Point"}
}