{
  "type": "Feature",
  "properties": {
    "iso:country":"US",
    "sg:address":"21925 Lyons Bald Mountain Rd",
    "sg:city":"Sonora",
    "sg:classifiers":[
        {
            "category":"Education",
            "subcategory":"School",
            "type":"Public Place"
        }
    ],
    "sg:phone":"+1 209 532 6673",
    "sg:postcode":"95370",
    "sg:province":"CA",
    "wof:name":"Foothill Horizons",
    "wof:placetype":"venue"
},
  "geometry": {"coordinates":[-120.327275,38.020081],"type":"Point"}
}