{
  "type": "Feature",
  "properties": {
    "addr:full":"3853 7 Trees Boulevard San Jose CA 95111",
    "addr:housenumber":"3853 7",
    "addr:postcode":"95111",
    "addr:street":"Trees Boulevard",
    "iso:country":"US",
    "sg:address":"3853 7 Trees Boulevard",
    "sg:city":"San Jose",
    "sg:classifiers":[
        {
            "category":"Restaurant",
            "type":"Food & Drink"
        }
    ],
    "sg:phone":"+1 408 578 3030",
    "sg:postcode":"95111",
    "sg:province":"CA",
    "sg:tags":[
        "pizza"
    ],
    "wof:name":"Domino's Pizza",
    "wof:placetype":"venue"
},
  "geometry": {"coordinates":[-121.833343,37.283951],"type":"Point"}
}