{
  "type": "Feature",
  "properties": {
    "addr:full":"77 S Knoll Rd Mill Valley CA 94941",
    "addr:housenumber":"77",
    "addr:postcode":"94941",
    "addr:street":"S Knoll Rd",
    "iso:country":"US",
    "sg:address":"77 S Knoll Rd",
    "sg:city":"Mill Valley",
    "sg:classifiers":[
        {
            "category":"Professional",
            "type":"Services"
        }
    ],
    "sg:phone":"+1 415 383 5915",
    "sg:postcode":"94941",
    "sg:province":"CA",
    "wof:name":"Fainbarg & Friedman",
    "wof:placetype":"venue"
},
  "geometry": {"coordinates":[-122.51101800000001,37.900711],"type":"Point"}
}