{
  "type": "Feature",
  "properties": {
    "iso:country":"US",
    "sg:address":"1815 Williams St",
    "sg:city":"San Leandro",
    "sg:classifiers":[
        {
            "category":"Wholesale",
            "subcategory":"Plants",
            "type":"Manufacturing & Wholesale Goods"
        }
    ],
    "sg:phone":"+1 510 614 7330",
    "sg:postcode":"94577",
    "sg:province":"CA",
    "sg:tags":[
        "florist"
    ],
    "wof:name":"Flower King",
    "wof:placetype":"venue"
},
  "geometry": {"coordinates":[-122.171153,37.712891],"type":"Point"}
}