{
  "type": "Feature",
  "properties": {
    "addr:full":"74945 Hwy 111 Indian Wells CA 92210",
    "addr:housenumber":"74945",
    "addr:postcode":"92210",
    "addr:street":"Hwy 111",
    "iso:country":"US",
    "sg:address":"74945 Hwy 111",
    "sg:city":"Indian Wells",
    "sg:classifiers":[
        {
            "category":"Professional",
            "subcategory":"Business Services",
            "type":"Services"
        }
    ],
    "sg:phone":"+1 760 773 9926",
    "sg:postcode":"92210",
    "sg:province":"CA",
    "sg:tags":[
        "interior",
        "consultant",
        "design",
        "decorator"
    ],
    "wof:name":"Donna Schuler Design Studio",
    "wof:placetype":"venue"
},
  "geometry": {"coordinates":[-116.35746,33.721319],"type":"Point"}
}