{
  "type": "Feature",
  "properties": {
    "iso:country":"US",
    "sg:address":"8678 Melrose Avenue",
    "sg:city":"West Hollywood",
    "sg:classifiers":[
        {
            "category":"Arts & Performance",
            "subcategory":"Art Gallery",
            "type":"Entertainment"
        }
    ],
    "sg:phone":"+1 626 792 8336",
    "sg:postcode":"90069",
    "sg:province":"CA",
    "wof:name":"Lizardi-Harp Gallery",
    "wof:placetype":"venue"
},
  "geometry": {"coordinates":[-118.38201599999999,34.081814],"type":"Point"}
}