{
  "type": "Feature",
  "properties": {
    "iso:country":"US",
    "sg:address":"4066 Pso Poco",
    "sg:city":"Santa Ynez",
    "sg:classifiers":[
        {
            "category":"Farming",
            "subcategory":"Livestock Farm",
            "type":"Manufacturing & Wholesale Goods"
        }
    ],
    "sg:phone":"+1 805 688 5342",
    "sg:postcode":"93460",
    "sg:province":"CA",
    "sg:tags":[
        "animal",
        "general"
    ],
    "wof:name":"Big M Ranches",
    "wof:placetype":"venue"
},
  "geometry": {"coordinates":[-120.07010099999999,34.591399],"type":"Point"}
}