{
  "type": "Feature",
  "properties": {
    "addr:full":"704 San Ramon Valley Blvd Danville CA 94583",
    "addr:housenumber":"704",
    "addr:postcode":"94583",
    "addr:street":"San Ramon Valley Blvd",
    "iso:country":"US",
    "sg:address":"704 San Ramon Valley Blvd",
    "sg:city":"Danville",
    "sg:classifiers":[
        {
            "category":"Education",
            "subcategory":"Special Training",
            "type":"Public Place"
        }
    ],
    "sg:phone":"+1 925 314 9450",
    "sg:postcode":"94583",
    "sg:province":"CA",
    "sg:tags":[
        "school",
        "instruction",
        "art"
    ],
    "wof:name":"Artragous",
    "wof:placetype":"venue"
},
  "geometry": {"coordinates":[-121.99521900000001,37.811524],"type":"Point"}
}