{
  "type": "Feature",
  "properties": {
    "addr:full":"17011 Beach Boulevard Suite 1500 Huntington Beach CA 92647-5995",
    "addr:housenumber":"17011",
    "addr:postcode":"92647-5995",
    "addr:street":"Beach Boulevard Suite 1500",
    "iso:country":"US",
    "sg:address":"17011 Beach Boulevard Suite 1500",
    "sg:city":"Huntington Beach",
    "sg:classifiers":[
        {
            "category":"Professional",
            "subcategory":"Computer Services",
            "type":"Services"
        }
    ],
    "sg:phone":"+1 714 766 8700",
    "sg:postcode":"92647-5995",
    "sg:province":"CA",
    "sg:website":"http://www.foldera.com",
    "wof:name":"Foldera",
    "wof:placetype":"venue"
},
  "geometry": {"coordinates":[-117.989065,33.713947],"type":"Point"}
}