{
  "type": "Feature",
  "properties": {
    "iso:country":"US",
    "sg:address":"180 S Lake St",
    "sg:city":"Burbank",
    "sg:classifiers":[
        {
            "category":"Education",
            "subcategory":"School",
            "type":"Public Place"
        }
    ],
    "sg:phone":"+1 818 899 8946",
    "sg:postcode":"91502",
    "sg:province":"CA",
    "wof:name":"Education Management Systems",
    "wof:placetype":"venue"
},
  "geometry": {"coordinates":[-118.313644,34.175232],"type":"Point"}
}