{
  "type": "Feature",
  "properties": {
    "addr:full":"5190 Caspar Ave Los Angeles CA 90041",
    "addr:housenumber":"5190",
    "addr:postcode":"90041",
    "addr:street":"Caspar Ave",
    "iso:country":"US",
    "sg:address":"5190 Caspar Ave",
    "sg:city":"Los Angeles",
    "sg:classifiers":[
        {
            "category":"Building & Trades",
            "subcategory":"Electrical",
            "type":"Services"
        }
    ],
    "sg:phone":"+1 323 256 4034",
    "sg:postcode":"90041",
    "sg:province":"CA",
    "sg:tags":[
        "electrical",
        "contractor"
    ],
    "wof:name":"Johnson Electric",
    "wof:placetype":"venue"
},
  "geometry": {"coordinates":[-118.21289299999999,34.13942],"type":"Point"}
}