{
  "type": "Feature",
  "properties": {
    "iso:country":"US",
    "sg:address":"640 S Grand Ave Ste 109",
    "sg:city":"Santa Ana",
    "sg:classifiers":[
        {
            "category":"Autos & Motor Vehicles",
            "subcategory":"Auto Supplies",
            "type":"Retail Goods"
        }
    ],
    "sg:phone":"+1 714 550 7111",
    "sg:postcode":"92705",
    "sg:province":"CA",
    "sg:tags":[
        "part"
    ],
    "wof:name":"Tube Technology",
    "wof:placetype":"venue"
},
  "geometry": {"coordinates":[-117.85027599999999,33.739995],"type":"Point"}
}