{
  "type": "Feature",
  "properties": {
    "iso:country":"US",
    "sg:address":"1013 N Pacific Ave",
    "sg:city":"Glendale",
    "sg:classifiers":[
        {
            "category":"Personal",
            "subcategory":"Beauty Salon",
            "type":"Services"
        }
    ],
    "sg:phone":"+1 818 240 1057",
    "sg:postcode":"91202",
    "sg:province":"CA",
    "sg:tags":[
        "hair"
    ],
    "wof:name":"Edo Hair Cut & Style",
    "wof:placetype":"venue"
},
  "geometry": {"coordinates":[-118.264376,34.159962],"type":"Point"}
}