{
  "type": "Feature",
  "properties": {
    "iso:country":"US",
    "sg:address":"3925 Freedom Cir",
    "sg:city":"Santa Clara",
    "sg:classifiers":[
        {
            "category":"Building & Trades",
            "subcategory":"Construction",
            "type":"Services"
        }
    ],
    "sg:phone":"+1 408 654 9064",
    "sg:postcode":"95054",
    "sg:province":"CA",
    "sg:tags":[
        "contractor"
    ],
    "wof:name":"Performace Contracting",
    "wof:placetype":"venue"
},
  "geometry": {"coordinates":[-121.970189,37.387047],"type":"Point"}
}