{
  "type": "Feature",
  "properties": {
    "addr:full":"5433 el Cajon Blvd San Diego CA 92115",
    "addr:housenumber":"5433",
    "addr:postcode":"92115",
    "addr:street":"El Cajon Blvd",
    "iso:country":"US",
    "sg:address":"5433 el Cajon Blvd",
    "sg:city":"San Diego",
    "sg:classifiers":[
        {
            "category":"Organizations",
            "subcategory":"Religious Organization",
            "type":"Services"
        }
    ],
    "sg:phone":"+1 619 229 9629",
    "sg:postcode":"92115",
    "sg:province":"CA",
    "sg:tags":[
        "church"
    ],
    "wof:name":"Escuela De Minieperios",
    "wof:placetype":"venue"
},
  "geometry": {"coordinates":[-117.078064,32.757935],"type":"Point"}
}