{
  "type": "Feature",
  "properties": {
    "addr:full":"241 Oneida Ave San Francisco CA 94112",
    "addr:housenumber":"241",
    "addr:postcode":"94112",
    "addr:street":"Oneida Ave",
    "iso:country":"US",
    "sg:address":"241 Oneida Ave",
    "sg:city":"San Francisco",
    "sg:classifiers":[
        {
            "category":"Professional",
            "type":"Services"
        }
    ],
    "sg:phone":"+1 415 452 4632",
    "sg:postcode":"94112",
    "sg:province":"CA",
    "sg:tags":[
        "establishment"
    ],
    "wof:name":"Records",
    "wof:placetype":"venue"
},
  "geometry": {"coordinates":[-122.443291,37.721906],"type":"Point"}
}