{
  "type": "Feature",
  "properties": {
    "addr:full":"2233 Central Ave Alameda CA 94501",
    "addr:housenumber":"2233",
    "addr:postcode":"94501",
    "addr:street":"Central Ave",
    "iso:country":"US",
    "sg:address":"2233 Central Ave",
    "sg:city":"Alameda",
    "sg:classifiers":[
        {
            "category":"Building & Trades",
            "subcategory":"Electrical",
            "type":"Services"
        }
    ],
    "sg:phone":"+1 510 748 0632",
    "sg:postcode":"94501",
    "sg:province":"CA",
    "sg:tags":[
        "electrical",
        "contractor"
    ],
    "wof:name":"Rmd Electric",
    "wof:placetype":"venue"
},
  "geometry": {"coordinates":[-122.245017,37.765205],"type":"Point"}
}