{
  "type": "Feature",
  "properties": {
    "addr:full":"1662 Hillhurst Ave Los Angeles CA 90027",
    "addr:housenumber":"1662",
    "addr:postcode":"90027",
    "addr:street":"Hillhurst Ave",
    "iso:country":"US",
    "sg:address":"1662 Hillhurst Ave",
    "sg:city":"Los Angeles",
    "sg:classifiers":[
        {
            "category":"Insurance",
            "subcategory":"Insurance Agent",
            "type":"Services"
        }
    ],
    "sg:phone":"+1 323 665 1700",
    "sg:postcode":"90027",
    "sg:province":"CA",
    "wof:name":"Dalton Brown & Long Inc",
    "wof:placetype":"venue"
},
  "geometry": {"coordinates":[-118.287327,34.101411],"type":"Point"}
}