{
  "type": "Feature",
  "properties": {
    "addr:full":"17400 High School Rd Jamestown CA 95327",
    "addr:housenumber":"17400",
    "addr:postcode":"95327",
    "addr:street":"High School Rd",
    "iso:country":"US",
    "sg:address":"17400 High School Rd",
    "sg:city":"Jamestown",
    "sg:classifiers":[
        {
            "category":"Utilities",
            "subcategory":"Mobile Phone",
            "type":"Services"
        }
    ],
    "sg:phone":"+1 209 533 8844",
    "sg:postcode":"95327",
    "sg:province":"CA",
    "sg:tags":[
        "communication",
        "radiotelephone"
    ],
    "wof:name":"Golden State Cellular",
    "wof:placetype":"venue"
},
  "geometry": {"coordinates":[-120.439492,37.940606],"type":"Point"}
}