{
  "type": "Feature",
  "properties": {
    "addr:full":"156 Estabrook St San Leandro CA 94577",
    "addr:housenumber":"156",
    "addr:postcode":"94577",
    "addr:street":"Estabrook St",
    "iso:country":"US",
    "sg:address":"156 Estabrook St",
    "sg:city":"San Leandro",
    "sg:classifiers":[
        {
            "category":"Real Estate",
            "subcategory":"Real Estate Operator",
            "type":"Services"
        }
    ],
    "sg:phone":"+1 510 357 8288",
    "sg:postcode":"94577",
    "sg:province":"CA",
    "sg:tags":[
        "apartment"
    ],
    "wof:name":"Regency Apartments",
    "wof:placetype":"venue"
},
  "geometry": {"coordinates":[-122.15100099999999,37.717999],"type":"Point"}
}