{
  "type": "Feature",
  "properties": {
    "iso:country":"US",
    "sg:address":"8605 Camino Media",
    "sg:city":"Bakersfield",
    "sg:classifiers":[
        {
            "category":"Health Services",
            "subcategory":"Doctor",
            "type":"Services"
        }
    ],
    "sg:phone":"+1 661 664 1682",
    "sg:postcode":"93311",
    "sg:province":"CA",
    "sg:tags":[
        "medicine",
        "physician",
        "practice",
        "surgeons",
        "family"
    ],
    "wof:name":"Premier Family Health Care",
    "wof:placetype":"venue"
},
  "geometry": {"coordinates":[-119.096388,35.342863],"type":"Point"}
}