{
  "type": "Feature",
  "properties": {
    "iso:country":"US",
    "sg:address":"3640 Lone Tree Way",
    "sg:city":"Antioch",
    "sg:classifiers":[
        {
            "category":"Shopping",
            "subcategory":"Used Merchandise",
            "type":"Retail Goods"
        }
    ],
    "sg:phone":"+1 925 779 1100",
    "sg:postcode":"94509",
    "sg:province":"CA",
    "sg:tags":[
        "shop",
        "consignment"
    ],
    "wof:name":"Interiors-Consignments On Lone",
    "wof:placetype":"venue"
},
  "geometry": {"coordinates":[-121.787367,37.968517],"type":"Point"}
}