{
  "type": "Feature",
  "properties": {
    "iso:country":"US",
    "sg:address":"8684 Ave de la Fuente",
    "sg:city":"San Diego",
    "sg:classifiers":[
        {
            "category":"Banks & Credit Unions",
            "subcategory":"Bank",
            "type":"Services"
        }
    ],
    "sg:phone":"+1 619 661 5232",
    "sg:postcode":"92154",
    "sg:province":"CA",
    "sg:tags":[
        "money",
        "transfer"
    ],
    "wof:name":"JOM Corp",
    "wof:placetype":"venue"
},
  "geometry": {"coordinates":[-116.95961,32.556973],"type":"Point"}
}