{
  "type": "Feature",
  "properties": {
    "addr:full":"13540 Larwin Cir Santa Fe Springs CA 90670",
    "addr:housenumber":"13540",
    "addr:postcode":"90670",
    "addr:street":"Larwin Cir",
    "iso:country":"US",
    "sg:address":"13540 Larwin Cir",
    "sg:city":"Santa Fe Springs",
    "sg:classifiers":[
        {
            "category":"Wholesale",
            "subcategory":"Machinery & Supplies",
            "type":"Manufacturing & Wholesale Goods"
        }
    ],
    "sg:phone":"+1 562 623 1133",
    "sg:postcode":"90670",
    "sg:province":"CA",
    "sg:tags":[
        "glass",
        "product",
        "fiber"
    ],
    "sg:website":"www.dorco.com",
    "wof:name":"Dorco Electronics",
    "wof:placetype":"venue"
},
  "geometry": {"coordinates":[-118.039362,33.907965],"type":"Point"}
}