{
  "type": "Feature",
  "properties": {
    "iso:country":"US",
    "sg:address":"345 Middlefield Rd",
    "sg:city":"Menlo Park",
    "sg:classifiers":[
        {
            "category":"Government",
            "subcategory":"Office",
            "type":"Public Place"
        }
    ],
    "sg:phone":"+1 650 329 4309",
    "sg:postcode":"94025",
    "sg:province":"CA",
    "wof:name":"Natural Resource Conservation",
    "wof:placetype":"venue"
},
  "geometry": {"coordinates":[-122.170052,37.457601],"type":"Point"}
}