{
  "type": "Feature",
  "properties": {
    "iso:country":"US",
    "sg:address":"302 8th Ave",
    "sg:city":"San Mateo",
    "sg:classifiers":[
        {
            "category":"Organizations",
            "subcategory":"Labor Organization",
            "type":"Services"
        }
    ],
    "sg:phone":"+1 650 343 1620",
    "sg:postcode":"94401",
    "sg:province":"CA",
    "wof:name":"IBEW",
    "wof:placetype":"venue"
},
  "geometry": {"coordinates":[-122.318164,37.562586],"type":"Point"}
}