{
  "type": "Feature",
  "properties": {
    "iso:country":"US",
    "sg:address":"6994 Broadway",
    "sg:city":"Lemon Grove",
    "sg:classifiers":[
        {
            "category":"Retail",
            "subcategory":"Auto Repair",
            "type":"Services"
        }
    ],
    "sg:phone":"+1 619 698 5410",
    "sg:postcode":"91945",
    "sg:province":"CA",
    "sg:tags":[
        "repairing",
        "automobile"
    ],
    "wof:name":"All Tune & Lube",
    "wof:placetype":"venue"
},
  "geometry": {"coordinates":[-117.043182,32.742616],"type":"Point"}
}