{
  "type": "Feature",
  "properties": {
    "iso:country":"US",
    "sg:address":"810 Main St",
    "sg:city":"Woodland",
    "sg:classifiers":[
        {
            "category":"Shopping",
            "subcategory":"Clothing, Apparel, & Fashions",
            "type":"Retail Goods"
        }
    ],
    "sg:phone":"+1 530 666 7889",
    "sg:postcode":"95695",
    "sg:province":"CA",
    "sg:tags":[
        "western"
    ],
    "wof:name":"Armando's Western Wear",
    "wof:placetype":"venue"
},
  "geometry": {"coordinates":[-121.769508,38.677359],"type":"Point"}
}