{
  "type": "Feature",
  "properties": {
    "iso:country":"US",
    "sg:address":"375 Ignacio Blvd",
    "sg:city":"Novato",
    "sg:classifiers":[
        {
            "category":"Retail",
            "subcategory":"Auto Repair",
            "type":"Services"
        }
    ],
    "sg:phone":"+1 415 883 6441",
    "sg:postcode":"94949",
    "sg:province":"CA",
    "sg:tags":[
        "repairing",
        "automobile"
    ],
    "wof:name":"Novato Unocal",
    "wof:placetype":"venue"
},
  "geometry": {"coordinates":[-122.539663,38.065945],"type":"Point"}
}