{
  "type": "Feature",
  "properties": {
    "iso:country":"US",
    "sg:address":"2107 W Magnolia Blvd",
    "sg:city":"Burbank",
    "sg:classifiers":[
        {
            "category":"Home & Garden",
            "subcategory":"Home Furnishings",
            "type":"Retail Goods"
        }
    ],
    "sg:phone":"+1 818 955 8255",
    "sg:postcode":"91506",
    "sg:province":"CA",
    "sg:tags":[
        "upholstery",
        "fabric"
    ],
    "wof:name":"Cervantes Custom Design",
    "wof:placetype":"venue"
},
  "geometry": {"coordinates":[-118.331609,34.173075],"type":"Point"}
}