{
  "type": "Feature",
  "properties": {
    "iso:country":"US",
    "sg:address":"1725 W Redlands Blvd",
    "sg:city":"Redlands",
    "sg:classifiers":[
        {
            "category":"Home & Garden",
            "subcategory":"Household Appliances",
            "type":"Retail Goods"
        },
        {
            "category":"Home & Garden",
            "subcategory":"Building Materials",
            "type":"Retail Goods"
        },
        {
            "category":"Building & Trades",
            "subcategory":"Construction",
            "type":"Services"
        }
    ],
    "sg:phone":"+1 877 471 9739",
    "sg:postcode":"92373",
    "sg:province":"CA",
    "sg:tags":[
        "repair",
        "major",
        "heater",
        "improvement",
        "water",
        "maintenance"
    ],
    "sg:website":"http://stores.lowes.com/lowes/cgi/index?design=default&lang=en&option=&mapid=US&svv=true&ft=as&cm_mmc=search_yellowpages-_-Business%20Listings-_-Business%20Listings-_-Business%20Listings&semsite=yellowpages&sembrand=n&semcatg=Business+Listings&semsubcatg=Business+Listings&semkeyword=Business+Listings",
    "wof:name":"Lowe's? Home Improvement",
    "wof:placetype":"venue"
},
  "geometry": {"coordinates":[-117.21374299999999,34.062933],"type":"Point"}
}