{
  "type": "Feature",
  "properties": {
    "addr:full":"4525 Sprucewood Ct Sacramento CA 95823",
    "addr:housenumber":"4525",
    "addr:postcode":"95823",
    "addr:street":"Sprucewood Ct",
    "iso:country":"US",
    "sg:address":"4525 Sprucewood Ct",
    "sg:city":"Sacramento",
    "sg:classifiers":[
        {
            "category":"Freight",
            "type":"Transportation"
        }
    ],
    "sg:phone":"+1 916 799 7977",
    "sg:postcode":"95823",
    "sg:province":"CA",
    "sg:tags":[
        "operator",
        "local",
        "trucking"
    ],
    "wof:name":"S King Trucking",
    "wof:placetype":"venue"
},
  "geometry": {"coordinates":[-121.449659,38.503471],"type":"Point"}
}