{
  "type": "Feature",
  "properties": {
    "iso:country":"US",
    "sg:address":"3701 W Oak St",
    "sg:city":"Burbank",
    "sg:classifiers":[
        {
            "category":"Utilities",
            "subcategory":"Cable",
            "type":"Services"
        }
    ],
    "sg:phone":"+1 818 977 3316",
    "sg:postcode":"91505",
    "sg:province":"CA",
    "sg:tags":[
        "television"
    ],
    "wof:name":"Time Warner",
    "wof:placetype":"venue"
},
  "geometry": {"coordinates":[-118.342491,34.157394],"type":"Point"}
}