{
  "type": "Feature",
  "properties": {
    "addr:full":"726 Alfred Nobel Dr Hercules CA 94547",
    "addr:housenumber":"726",
    "addr:postcode":"94547",
    "addr:street":"Alfred Nobel Dr",
    "iso:country":"US",
    "sg:address":"726 Alfred Nobel Dr",
    "sg:city":"Hercules",
    "sg:classifiers":[
        {
            "category":"Real Estate",
            "subcategory":"Real Estate Agent",
            "type":"Services"
        }
    ],
    "sg:phone":"+1 510 724 4445",
    "sg:postcode":"94547",
    "sg:province":"CA",
    "wof:name":"First California Homes",
    "wof:placetype":"venue"
},
  "geometry": {"coordinates":[-122.274394,38.019497],"type":"Point"}
}