{
  "type": "Feature",
  "properties": {
    "iso:country":"US",
    "sg:address":"1381 McMinn Ave",
    "sg:city":"Santa Rosa",
    "sg:classifiers":[
        {
            "category":"Building & Trades",
            "subcategory":"Construction",
            "type":"Services"
        }
    ],
    "sg:phone":"+1 707 546 4153",
    "sg:postcode":"95407",
    "sg:province":"CA",
    "sg:tags":[
        "dry wall",
        "contractor"
    ],
    "wof:name":"ABC Drywall",
    "wof:placetype":"venue"
},
  "geometry": {"coordinates":[-122.73130399999999,38.423164],"type":"Point"}
}