{
  "type": "Feature",
  "properties": {
    "iso:country":"US",
    "sg:address":"230 Winston St",
    "sg:city":"Los Angeles",
    "sg:classifiers":[
        {
            "category":"Professional",
            "type":"Services"
        }
    ],
    "sg:phone":"+1 213 624 6496",
    "sg:postcode":"90013",
    "sg:province":"CA",
    "wof:name":"Bluebeny",
    "wof:placetype":"venue"
},
  "geometry": {"coordinates":[-118.245886,34.045687],"type":"Point"}
}