{
  "type": "Feature",
  "properties": {
    "iso:country":"US",
    "sg:address":"13429 Kiwi Ave",
    "sg:city":"Corona",
    "sg:classifiers":[
        {
            "category":"Building & Trades",
            "subcategory":"Construction",
            "type":"Services"
        }
    ],
    "sg:phone":"+1 951 520 8950",
    "sg:postcode":"92880",
    "sg:province":"CA",
    "sg:tags":[
        "contractor"
    ],
    "sg:website":"www.westernpacifichousing.com",
    "wof:name":"Orchard Western Pacific",
    "wof:placetype":"venue"
},
  "geometry": {"coordinates":[-117.576697,33.973275],"type":"Point"}
}