{
  "type": "Feature",
  "properties": {
    "addr:full":"6337 Dwane Ave San Diego CA 92120",
    "addr:housenumber":"6337",
    "addr:postcode":"92120",
    "addr:street":"Dwane Ave",
    "iso:country":"US",
    "sg:address":"6337 Dwane Ave",
    "sg:city":"San Diego",
    "sg:classifiers":[
        {
            "category":"Professional",
            "type":"Services"
        }
    ],
    "sg:phone":"+1 619 583 8740",
    "sg:postcode":"92120",
    "sg:province":"CA",
    "wof:name":"Carmel Valley 18 LLC",
    "wof:placetype":"venue"
},
  "geometry": {"coordinates":[-117.06085,32.787888],"type":"Point"}
}