{
  "type": "Feature",
  "properties": {
    "addr:full":"1155 Auto Mall Dr Lancaster CA 93534",
    "addr:housenumber":"1155",
    "addr:postcode":"93534",
    "addr:street":"Auto Mall Dr",
    "iso:country":"US",
    "sg:address":"1155 Auto Mall Dr",
    "sg:city":"Lancaster",
    "sg:classifiers":[
        {
            "category":"Autos & Motor Vehicles",
            "subcategory":"Automobile Sales",
            "type":"Retail Goods"
        }
    ],
    "sg:phone":"+1 888 804 6862",
    "sg:postcode":"93534",
    "sg:province":"CA",
    "sg:tags":[
        "car",
        "used"
    ],
    "sg:website":"http://www.avford.com",
    "wof:name":"Antelope Valley Ford",
    "wof:placetype":"venue"
},
  "geometry": {"coordinates":[-118.150964,34.669993],"type":"Point"}
}