{
  "type": "Feature",
  "properties": {
    "addr:full":"1540 Oceanaire Dr San Luis Obispo CA 93405",
    "addr:postcode":"1540;93405",
    "addr:street":"Oceanaire Dr",
    "iso:country":"US",
    "sg:address":"1540 Oceanaire Dr",
    "sg:city":"San Luis Obispo",
    "sg:classifiers":[
        {
            "category":"Professional",
            "subcategory":"Accounting & Tax Preparation",
            "type":"Services"
        }
    ],
    "sg:phone":"+1 805 546 0556",
    "sg:postcode":"93405",
    "sg:province":"CA",
    "sg:tags":[
        "bookkeeping",
        "general"
    ],
    "wof:name":"Kathleen O'Brien",
    "wof:placetype":"venue"
},
  "geometry": {"coordinates":[-120.685076,35.260737],"type":"Point"}
}