{
  "type": "Feature",
  "properties": {
    "addr:full":"2034 Calaveras Ave Davis CA 95616",
    "addr:housenumber":"2034",
    "addr:postcode":"95616",
    "addr:street":"Calaveras Ave",
    "iso:country":"US",
    "sg:address":"2034 Calaveras Ave",
    "sg:city":"Davis",
    "sg:classifiers":[
        {
            "category":"Building & Trades",
            "subcategory":"Construction",
            "type":"Services"
        }
    ],
    "sg:phone":"+1 530 753 6128",
    "sg:postcode":"95616",
    "sg:province":"CA",
    "sg:tags":[
        "resurfacing",
        "laying",
        "refinishing",
        "floor"
    ],
    "wof:name":"SME Restoration & Constr",
    "wof:placetype":"venue"
},
  "geometry": {"coordinates":[-121.775284,38.550484],"type":"Point"}
}