{
  "type": "Feature",
  "properties": {
    "addr:full":"1134 Kenmar Ct San Jose CA 95132",
    "addr:housenumber":"1134",
    "addr:postcode":"95132",
    "addr:street":"Kenmar Ct",
    "iso:country":"US",
    "sg:address":"1134 Kenmar Ct",
    "sg:city":"San Jose",
    "sg:classifiers":[
        {
            "category":"Professional",
            "subcategory":"Computer Services",
            "type":"Services"
        }
    ],
    "sg:phone":"+1 408 568 5813",
    "sg:postcode":"95132",
    "sg:province":"CA",
    "wof:name":"Kano Komputers",
    "wof:placetype":"venue"
},
  "geometry": {"coordinates":[-121.854665,37.39192],"type":"Point"}
}