{
  "type": "Feature",
  "properties": {
    "addr:full":"2785 Claray Dr Los Angeles CA 90077",
    "addr:housenumber":"2785",
    "addr:postcode":"90077",
    "addr:street":"Claray Dr",
    "iso:country":"US",
    "sg:address":"2785 Claray Dr",
    "sg:city":"Los Angeles",
    "sg:classifiers":[
        {
            "category":"Real Estate",
            "subcategory":"Real Estate Agent",
            "type":"Services"
        }
    ],
    "sg:phone":"+1 310 446 1738",
    "sg:postcode":"90077",
    "sg:province":"CA",
    "wof:name":"Alpha Realty",
    "wof:placetype":"venue"
},
  "geometry": {"coordinates":[-118.447913,34.122757],"type":"Point"}
}