{
  "type": "Feature",
  "properties": {
    "addr:full":"3056 W Main St Alhambra CA 91801",
    "addr:housenumber":"3056",
    "addr:postcode":"91801",
    "addr:street":"W Main St",
    "iso:country":"US",
    "sg:address":"3056 W Main St",
    "sg:city":"Alhambra",
    "sg:classifiers":[
        {
            "category":"Arts & Performance",
            "subcategory":"Theater",
            "type":"Entertainment"
        }
    ],
    "sg:phone":"+1 626 458 6233",
    "sg:postcode":"91801",
    "sg:province":"CA",
    "sg:tags":[
        "entertainer",
        "business"
    ],
    "wof:name":"Made Entertainment",
    "wof:placetype":"venue"
},
  "geometry": {"coordinates":[-118.158485,34.094629],"type":"Point"}
}