{
  "type": "Feature",
  "properties": {
    "iso:country":"US",
    "sg:address":"360 Mobil Ave",
    "sg:city":"Camarillo",
    "sg:classifiers":[
        {
            "category":"Professional",
            "subcategory":"Business Services",
            "type":"Services"
        }
    ],
    "sg:phone":"+1 805 388 7975",
    "sg:postcode":"93010",
    "sg:province":"CA",
    "sg:tags":[
        "building",
        "inspection"
    ],
    "wof:name":"Pillar To Post Pro Home",
    "wof:placetype":"venue"
},
  "geometry": {"coordinates":[-119.042935,34.219947],"type":"Point"}
}