{
  "type": "Feature",
  "properties": {
    "iso:country":"US",
    "sg:address":"123 Gates St",
    "sg:city":"San Francisco",
    "sg:classifiers":[
        {
            "category":"Education",
            "subcategory":"Dance Studio",
            "type":"Public Place"
        }
    ],
    "sg:phone":"+1 415 282 6177",
    "sg:postcode":"94110",
    "sg:province":"CA",
    "sg:tags":[
        "instruction",
        "dancing"
    ],
    "wof:name":"Beth Abrams' Dance Classes",
    "wof:placetype":"venue"
},
  "geometry": {"coordinates":[-122.413831,37.740582],"type":"Point"}
}