{
  "type": "Feature",
  "properties": {
    "iso:country":"US",
    "sg:address":"1122 Castleton Way",
    "sg:city":"Sunnyvale",
    "sg:classifiers":[
        {
            "category":"Travel",
            "subcategory":"Travel Agent",
            "type":"Entertainment"
        }
    ],
    "sg:phone":"+1 408 213 2126",
    "sg:postcode":"94087",
    "sg:province":"CA",
    "sg:tags":[
        "ticket",
        "agency",
        "airline"
    ],
    "wof:name":"Venture Travel Center",
    "wof:placetype":"venue"
},
  "geometry": {"coordinates":[-122.001936,37.349015],"type":"Point"}
}