{
  "type": "Feature",
  "properties": {
    "acme:elev":"629",
    "iso:country":"US",
    "name:eng_x_preferred":[
        "SF-51L Milagra Ridge Nike Site"
    ],
    "wof:name":"SF-51L Milagra Ridge Nike Site",
    "wof:placetype":"venue"
},
  "geometry": {"coordinates":[-122.47906999999999,37.63951],"type":"Point"}
}