{
  "type": "Feature",
  "properties": {
    "iso:country":"US",
    "sg:address":"435 N Main St",
    "sg:city":"Lakeport",
    "sg:classifiers":[
        {
            "category":"Insurance",
            "subcategory":"Insurance Agent",
            "type":"Services"
        }
    ],
    "sg:phone":"+1 707 262 0888",
    "sg:postcode":"95453",
    "sg:province":"CA",
    "wof:name":"Tom O'Rourke Insurance",
    "wof:placetype":"venue"
},
  "geometry": {"coordinates":[-122.915203,39.045078],"type":"Point"}
}