{
  "type": "Feature",
  "properties": {
    "iso:country":"US",
    "sg:address":"826 E 9th St",
    "sg:city":"Los Angeles",
    "sg:classifiers":[
        {
            "category":"Wholesale",
            "subcategory":"Apparel",
            "type":"Manufacturing & Wholesale Goods"
        }
    ],
    "sg:phone":"+1 213 622 6363",
    "sg:postcode":"90021",
    "sg:province":"CA",
    "sg:tags":[
        "piece"
    ],
    "wof:name":"Nick Textile",
    "wof:placetype":"venue"
},
  "geometry": {"coordinates":[-118.248042,34.035146],"type":"Point"}
}