{
  "type": "Feature",
  "properties": {
    "addr:full":"14949 State Highway 173 Hesperia CA 92345",
    "addr:housenumber":"14949",
    "addr:postcode":"92345",
    "addr:street":"State Highway 173",
    "iso:country":"US",
    "sg:address":"14949 State Highway 173",
    "sg:city":"Hesperia",
    "sg:classifiers":[
        {
            "category":"Organizations",
            "subcategory":"Religious Organization",
            "type":"Services"
        }
    ],
    "sg:phone":"+1 760 389 2011",
    "sg:postcode":"92345",
    "sg:province":"CA",
    "wof:name":"Grace Christian Church",
    "wof:placetype":"venue"
},
  "geometry": {"coordinates":[-117.328632,34.307366],"type":"Point"}
}