{
  "type": "Feature",
  "properties": {
    "addr:full":"2027 Williams St San Leandro CA 94577",
    "addr:housenumber":"2027",
    "addr:postcode":"94577",
    "addr:street":"Williams St",
    "iso:country":"US",
    "sg:address":"2027 Williams St",
    "sg:city":"San Leandro",
    "sg:classifiers":[
        {
            "category":"Freight",
            "type":"Transportation"
        }
    ],
    "sg:phone":"+1 510 357 0850",
    "sg:postcode":"94577",
    "sg:province":"CA",
    "sg:tags":[
        "local",
        "trucker"
    ],
    "sg:website":"www.expressfreight.com",
    "wof:name":"Express Freight System",
    "wof:placetype":"venue"
},
  "geometry": {"coordinates":[-122.175487,37.711],"type":"Point"}
}