{
  "type": "Feature",
  "properties": {
    "addr:full":"2806 Verde Vista Dr Santa Barbara CA 93105",
    "addr:housenumber":"2806",
    "addr:postcode":"93105",
    "addr:street":"Verde Vista Dr",
    "iso:country":"US",
    "sg:address":"2806 Verde Vista Dr",
    "sg:city":"Santa Barbara",
    "sg:classifiers":[
        {
            "category":"Travel",
            "subcategory":"Travel Agent",
            "type":"Entertainment"
        }
    ],
    "sg:phone":"+1 805 687 0740",
    "sg:postcode":"93105",
    "sg:province":"CA",
    "sg:tags":[
        "agency"
    ],
    "wof:name":"Professional Travel Service",
    "wof:placetype":"venue"
},
  "geometry": {"coordinates":[-119.722013,34.441183],"type":"Point"}
}