{
  "type": "Feature",
  "properties": {
    "addr:full":"7849 Shofner St Bakersfield CA 93308",
    "addr:housenumber":"7849",
    "addr:postcode":"93308",
    "addr:street":"Shofner St",
    "iso:country":"US",
    "sg:address":"7849 Shofner St",
    "sg:city":"Bakersfield",
    "sg:classifiers":[
        {
            "category":"Manufacturing",
            "subcategory":"Tools & Machinery",
            "type":"Manufacturing & Wholesale Goods"
        }
    ],
    "sg:phone":"+1 661 589 3018",
    "sg:postcode":"93308",
    "sg:province":"CA",
    "sg:tags":[
        "machine",
        "shop"
    ],
    "wof:name":"Ingalls Machine",
    "wof:placetype":"venue"
},
  "geometry": {"coordinates":[-119.088877,35.386846],"type":"Point"}
}