{
  "type": "Feature",
  "properties": {
    "addr:full":"55 Meadow Dr San Rafael CA 94903",
    "addr:housenumber":"55",
    "addr:postcode":"94903",
    "addr:street":"Meadow Dr",
    "iso:country":"US",
    "sg:address":"55 Meadow Dr",
    "sg:city":"San Rafael",
    "sg:classifiers":[
        {
            "category":"Building & Trades",
            "subcategory":"Landscaping Services",
            "type":"Services"
        }
    ],
    "sg:phone":"+1 415 472 7686",
    "sg:postcode":"94903",
    "sg:province":"CA",
    "wof:name":"Chris' Rototilling",
    "wof:placetype":"venue"
},
  "geometry": {"coordinates":[-122.52236600000001,38.007599],"type":"Point"}
}