{
  "type": "Feature",
  "properties": {
    "iso:country":"US",
    "sg:address":"8907 Madison Ave",
    "sg:city":"Fair Oaks",
    "sg:classifiers":[
        {
            "category":"Home & Garden",
            "subcategory":"Garden Supply",
            "type":"Retail Goods"
        },
        {
            "category":"Building & Trades",
            "subcategory":"Landscaping Services",
            "type":"Services"
        }
    ],
    "sg:phone":"+1 916 962 3005",
    "sg:postcode":"95628",
    "sg:province":"CA",
    "sg:tags":[
        "lawn",
        "mower"
    ],
    "wof:name":"Fair Oaks Lawn & Garden Equip",
    "wof:placetype":"venue"
},
  "geometry": {"coordinates":[-121.221875,38.664024],"type":"Point"}
}