{
  "type": "Feature",
  "properties": {
    "addr:full":"3440 Wilshire Blvd Ste 1111 Los Angeles CA 90010",
    "addr:housenumber":"3440",
    "addr:postcode":"90010",
    "addr:street":"Wilshire Blvd Ste 1111",
    "iso:country":"US",
    "sg:address":"3440 Wilshire Blvd Ste 1111",
    "sg:city":"Los Angeles",
    "sg:classifiers":[
        {
            "category":"Professional",
            "subcategory":"Employment Agencies",
            "type":"Services"
        }
    ],
    "sg:phone":"+1 213 380 7823",
    "sg:postcode":"90010",
    "sg:province":"CA",
    "wof:name":"California Staffing Service",
    "wof:placetype":"venue"
},
  "geometry": {"coordinates":[-118.298795,34.162067],"type":"Point"}
}