{
  "type": "Feature",
  "properties": {
    "addr:full":"9150 Clairemont Mesa Blvd San Diego CA 92117",
    "addr:housenumber":"9150",
    "addr:postcode":"92117",
    "addr:street":"Clairemont Mesa Blvd",
    "iso:country":"US",
    "sg:address":"9150 Clairemont Mesa Blvd",
    "sg:city":"San Diego",
    "sg:classifiers":[
        {
            "category":"Building & Trades",
            "subcategory":"Equipment Rental",
            "type":"Services"
        }
    ],
    "sg:phone":"+1 858 277 8800",
    "sg:postcode":"92117",
    "sg:province":"CA",
    "sg:tags":[
        "leasing",
        "furniture"
    ],
    "wof:name":"Cort Furniture Clearance Ctr",
    "wof:placetype":"venue"
},
  "geometry": {"coordinates":[-117.13125700000001,32.831488],"type":"Point"}
}