{
  "type": "Feature",
  "properties": {
    "addr:full":"506 Foothill Blvd Oakland CA 94606",
    "addr:housenumber":"506",
    "addr:postcode":"94606",
    "addr:street":"Foothill Blvd",
    "iso:country":"US",
    "sg:address":"506 Foothill Blvd",
    "sg:city":"Oakland",
    "sg:classifiers":[
        {
            "category":"Airline",
            "type":"Transportation"
        }
    ],
    "sg:phone":"+1 510 893 7373",
    "sg:postcode":"94606",
    "sg:province":"CA",
    "sg:tags":[
        "shuttle",
        "airport"
    ],
    "wof:name":"Super Star",
    "wof:placetype":"venue"
},
  "geometry": {"coordinates":[-122.24400300000001,37.795601],"type":"Point"}
}