{
  "type": "Feature",
  "properties": {
    "iso:country":"US",
    "sg:address":"2295 Francisco St",
    "sg:city":"San Francisco",
    "sg:classifiers":[
        {
            "category":"Freight",
            "type":"Transportation"
        }
    ],
    "sg:phone":"+1 415 409 2524",
    "sg:postcode":"94123",
    "sg:province":"CA",
    "sg:tags":[
        "terminal",
        "truck",
        "facility"
    ],
    "wof:name":"Lisa Ligon",
    "wof:placetype":"venue"
},
  "geometry": {"coordinates":[-122.441759,37.801043],"type":"Point"}
}