{
  "type": "Feature",
  "properties": {
    "addr:full":"1600 W 240th St Harbor City CA 90710",
    "addr:housenumber":"1600",
    "addr:postcode":"90710",
    "addr:street":"W 240Th St",
    "iso:country":"US",
    "sg:address":"1600 W 240th St",
    "sg:city":"Harbor City",
    "sg:classifiers":[
        {
            "category":"Professional",
            "subcategory":"Advertising",
            "type":"Services"
        }
    ],
    "sg:phone":"+1 310 539 7200",
    "sg:postcode":"90710",
    "sg:province":"CA",
    "sg:website":"www.industrycloseouts.com",
    "wof:name":"INDUSTRYCLOSEOUTS.COM",
    "wof:placetype":"venue"
},
  "geometry": {"coordinates":[-118.30532100000001,33.807217],"type":"Point"}
}