{
  "type": "Feature",
  "properties": {
    "iso:country":"US",
    "sg:address":"15453 Rowlee Rd",
    "sg:city":"Wasco",
    "sg:classifiers":[
        {
            "category":"Farming",
            "subcategory":"Livestock Farm",
            "type":"Manufacturing & Wholesale Goods"
        }
    ],
    "sg:phone":"+1 661 758 6147",
    "sg:postcode":"93280",
    "sg:province":"CA",
    "sg:tags":[
        "beef",
        "feedlot",
        "cattle"
    ],
    "wof:name":"John Miller Ranch",
    "wof:placetype":"venue"
},
  "geometry": {"coordinates":[-119.473609,35.597255],"type":"Point"}
}