{
  "type": "Feature",
  "properties": {
    "addr:full":"83395 Trona Rd Trona CA 93562",
    "addr:postcode":"83395;93562",
    "addr:street":"Trona Rd",
    "iso:country":"US",
    "sg:address":"83395 Trona Rd",
    "sg:city":"Trona",
    "sg:classifiers":[
        {
            "category":"Organizations",
            "subcategory":"Religious Organization",
            "type":"Services"
        }
    ],
    "sg:phone":"+1 760 372 4717",
    "sg:postcode":"93562",
    "sg:province":"CA",
    "wof:name":"St Madeleine Catholic Church",
    "wof:placetype":"venue"
},
  "geometry": {"coordinates":[-117.36990400000001,35.768135],"type":"Point"}
}