{
  "type": "Feature",
  "properties": {
    "addr:full":"313 E Pine St Santa Ana CA 92701",
    "addr:housenumber":"313",
    "addr:postcode":"92701",
    "addr:street":"E Pine St",
    "iso:country":"US",
    "sg:address":"313 E Pine St",
    "sg:city":"Santa Ana",
    "sg:classifiers":[
        {
            "category":"Real Estate",
            "subcategory":"Real Estate Operator",
            "type":"Services"
        }
    ],
    "sg:phone":"+1 714 550 1151",
    "sg:postcode":"92701",
    "sg:province":"CA",
    "sg:tags":[
        "apartment"
    ],
    "wof:name":"Italia Apartments",
    "wof:placetype":"venue"
},
  "geometry": {"coordinates":[-117.86464599999999,33.743475],"type":"Point"}
}