{
  "type": "Feature",
  "properties": {
    "iso:country":"US",
    "sg:address":"43950 Acacia Ave",
    "sg:city":"Hemet",
    "sg:classifiers":[
        {
            "category":"Government",
            "subcategory":"Police Station",
            "type":"Public Place"
        }
    ],
    "sg:phone":"+1 951 791 3400",
    "sg:postcode":"92544",
    "sg:province":"CA",
    "sg:tags":[
        "sheriff"
    ],
    "wof:name":"Riverside County Sheriff Dept",
    "wof:placetype":"venue"
},
  "geometry": {"coordinates":[-116.894171,33.744284],"type":"Point"}
}