{
  "type": "Feature",
  "properties": {
    "iso:country":"US",
    "sg:address":"741 E Whittier Blvd",
    "sg:city":"La Habra",
    "sg:classifiers":[
        {
            "category":"Retail",
            "subcategory":"Auto Repair",
            "type":"Services"
        }
    ],
    "sg:phone":"+1 562 697 2696",
    "sg:postcode":"90631",
    "sg:province":"CA",
    "sg:tags":[
        "repairing",
        "automobile"
    ],
    "wof:name":"American Gear Shop",
    "wof:placetype":"venue"
},
  "geometry": {"coordinates":[-117.93824600000001,33.939193],"type":"Point"}
}