{
  "type": "Feature",
  "properties": {
    "iso:country":"US",
    "sg:address":"17150 Newhope St",
    "sg:city":"Fountain Valley",
    "sg:classifiers":[
        {
            "category":"Health Services",
            "subcategory":"Doctor",
            "type":"Services"
        },
        {
            "category":"Health Services",
            "subcategory":"Medical Lab",
            "type":"Services"
        }
    ],
    "sg:phone":"+1 714 979 1211",
    "sg:postcode":"92708",
    "sg:province":"CA",
    "sg:tags":[
        "physician",
        "surgeon",
        "laboratory"
    ],
    "wof:name":"Bio Path Medical Group",
    "wof:placetype":"venue"
},
  "geometry": {"coordinates":[-117.928356,33.715923],"type":"Point"}
}