{
  "type": "Feature",
  "properties": {
    "iso:country":"US",
    "sg:address":"980 Grand Ave",
    "sg:city":"San Diego",
    "sg:classifiers":[
        {
            "category":"Restaurant",
            "type":"Food & Drink"
        }
    ],
    "sg:menulink":"http://www.allmenus.com/ca/san-diego/157604-la-salsa/menu/",
    "sg:phone":"+1 858 483 1007",
    "sg:postcode":"92109",
    "sg:province":"CA",
    "sg:tags":[
        "mexican"
    ],
    "wof:name":"La Salsa",
    "wof:placetype":"venue"
},
  "geometry": {"coordinates":[-117.25163000000001,32.795746],"type":"Point"}
}