{
  "type": "Feature",
  "properties": {
    "addr:full":"1900 Seaport Boulevard 2nd Floor Redwood City CA 94063-5587",
    "addr:housenumber":"1900",
    "addr:postcode":"94063-5587",
    "addr:street":"Seaport Boulevard 2Nd Floor",
    "iso:country":"US",
    "sg:address":"1900 Seaport Boulevard 2nd Floor",
    "sg:city":"Redwood City",
    "sg:classifiers":[
        {
            "category":"Professional",
            "subcategory":"Computer Services",
            "type":"Services"
        }
    ],
    "sg:phone":"+1 650 481 3400",
    "sg:postcode":"94063-5587",
    "sg:province":"CA",
    "sg:website":"http://www.serena.com",
    "wof:name":"Serena Software",
    "wof:placetype":"venue"
},
  "geometry": {"coordinates":[-122.207086,37.511231],"type":"Point"}
}