{
  "type": "Feature",
  "properties": {
    "iso:country":"US",
    "sg:address":"12610 Glenoaks Blvd",
    "sg:city":"Sylmar",
    "sg:classifiers":[
        {
            "category":"Professional",
            "subcategory":"Accounting & Tax Preparation",
            "type":"Services"
        }
    ],
    "sg:phone":"+1 818 361 7757",
    "sg:postcode":"91342",
    "sg:province":"CA",
    "sg:tags":[
        "consultant"
    ],
    "wof:name":"Tax Expert",
    "wof:placetype":"venue"
},
  "geometry": {"coordinates":[-118.43901700000001,34.299299],"type":"Point"}
}