{
  "type": "Feature",
  "properties": {
    "iso:country":"US",
    "sg:address":"30510 San Antonio St",
    "sg:city":"Hayward",
    "sg:classifiers":[
        {
            "category":"Manufacturing",
            "subcategory":"Tools & Machinery",
            "type":"Manufacturing & Wholesale Goods"
        }
    ],
    "sg:phone":"+1 510 487 8500",
    "sg:postcode":"94544",
    "sg:province":"CA",
    "sg:tags":[
        "equipment",
        "fixture",
        "lighting",
        "lamp",
        "bulb"
    ],
    "sg:website":"www.westlite.com",
    "wof:name":"West-Lite Supply Co Inc",
    "wof:placetype":"venue"
},
  "geometry": {"coordinates":[-122.05500000000001,37.619301],"type":"Point"}
}