{
  "type": "Feature",
  "properties": {
    "iso:country":"US",
    "sg:address":"4040 San Pablo Dam Rd",
    "sg:city":"El Sobrante",
    "sg:classifiers":[
        {
            "category":"Retail",
            "subcategory":"Auto Repair",
            "type":"Services"
        }
    ],
    "sg:phone":"+1 510 223 9604",
    "sg:postcode":"94803",
    "sg:province":"CA",
    "sg:tags":[
        "brake"
    ],
    "wof:name":"El Sobrante Wheel & Brake",
    "wof:placetype":"venue"
},
  "geometry": {"coordinates":[-122.311412,37.965485],"type":"Point"}
}