{
  "type": "Feature",
  "properties": {
    "addr:full":"777 Mariners Island Boulevard #560 San Mateo CA 94404",
    "addr:housenumber":"777",
    "addr:postcode":"94404",
    "addr:street":"Mariners Island Boulevard # 560",
    "iso:country":"US",
    "sg:address":"777 Mariners Island Boulevard #560",
    "sg:city":"San Mateo",
    "sg:classifiers":[
        {
            "category":"Professional",
            "subcategory":"Employment Agencies",
            "type":"Services"
        }
    ],
    "sg:phone":"+1 650 572 0123",
    "sg:postcode":"94404",
    "sg:province":"CA",
    "sg:website":"www.xcelgroup.com",
    "wof:name":"The Xcel Group, LLC",
    "wof:placetype":"venue"
},
  "geometry": {"coordinates":[-122.286083,37.561994],"type":"Point"}
}