{
  "type": "Feature",
  "properties": {
    "addr:full":"1711 Branham Ln San Jose CA 95124",
    "addr:housenumber":"1711",
    "addr:postcode":"95124",
    "addr:street":"Branham Ln",
    "iso:country":"US",
    "sg:address":"1711 Branham Ln",
    "sg:city":"San Jose",
    "sg:classifiers":[
        {
            "category":"Shopping",
            "subcategory":"Gifts & Souvenirs",
            "type":"Retail Goods"
        }
    ],
    "sg:phone":"+1 408 978 5189",
    "sg:postcode":"95124",
    "sg:province":"CA",
    "wof:name":"Veronicas Cards & Gifts",
    "wof:placetype":"venue"
},
  "geometry": {"coordinates":[-121.916832,37.250933],"type":"Point"}
}