{
  "type": "Feature",
  "properties": {
    "addr:full":"222 E Anapamu St Santa Barbara CA 93101",
    "addr:housenumber":"222",
    "addr:postcode":"93101",
    "addr:street":"E Anapamu St",
    "iso:country":"US",
    "sg:address":"222 E Anapamu St",
    "sg:city":"Santa Barbara",
    "sg:classifiers":[
        {
            "category":"Professional",
            "subcategory":"Lawyer & Legal Services",
            "type":"Services"
        }
    ],
    "sg:phone":"+1 805 963 8777",
    "sg:postcode":"93101",
    "sg:province":"CA",
    "sg:tags":[
        "attorney"
    ],
    "wof:name":"Stanley W Abbott",
    "wof:placetype":"venue"
},
  "geometry": {"coordinates":[-119.70122499999999,34.426248],"type":"Point"}
}