{
  "type": "Feature",
  "properties": {
    "addr:full":"17827 Cherry Court Carson CA 90746",
    "addr:housenumber":"17827",
    "addr:postcode":"90746",
    "addr:street":"Cherry Court",
    "iso:country":"US",
    "sg:address":"17827 Cherry Court",
    "sg:city":"Carson",
    "sg:classifiers":[
        {
            "category":"Personal",
            "type":"Services"
        }
    ],
    "sg:phone":"+1 310 863 9690",
    "sg:postcode":"90746",
    "sg:province":"CA",
    "sg:tags":[
        "party",
        "planning",
        "event"
    ],
    "sg:website":"www.stylishaffairs.com",
    "wof:name":"Stylish Affairs",
    "wof:placetype":"venue"
},
  "geometry": {"coordinates":[-118.252489,33.86857],"type":"Point"}
}