{
  "type": "Feature",
  "properties": {
    "addr:full":"15 Telegraph Hill Blvd San Francisco CA 94133",
    "addr:housenumber":"15",
    "addr:postcode":"94133",
    "addr:street":"Telegraph Hill Blvd",
    "iso:country":"US",
    "sg:address":"15 Telegraph Hill Blvd",
    "sg:city":"San Francisco",
    "sg:classifiers":[
        {
            "category":"Personal",
            "type":"Services"
        }
    ],
    "sg:phone":"+1 510 755 0605",
    "sg:postcode":"94133",
    "sg:province":"CA",
    "sg:tags":[
        "party",
        "planning",
        "event"
    ],
    "wof:name":"San Francisco Tour Bus",
    "wof:placetype":"venue"
},
  "geometry": {"coordinates":[-122.40582499999999,37.80281],"type":"Point"}
}