{
  "type": "Feature",
  "properties": {
    "addr:full":"5943 Co Rd 17 Orland CA 95963",
    "addr:housenumber":"5943;17",
    "addr:postcode":"95963",
    "addr:street":"Co Rd",
    "iso:country":"US",
    "sg:address":"5943 Co Rd 17",
    "sg:city":"Orland",
    "sg:classifiers":[
        {
            "category":"Farming",
            "subcategory":"Dairy Farm",
            "type":"Manufacturing & Wholesale Goods"
        }
    ],
    "sg:phone":"+1 530 865 4875",
    "sg:postcode":"95963",
    "sg:province":"CA",
    "wof:name":"Chris Verboom Dairy Farm",
    "wof:placetype":"venue"
},
  "geometry": {"coordinates":[-122.253362,39.738621],"type":"Point"}
}