{
  "type": "Feature",
  "properties": {
    "addr:full":"3001 Douglas Blvd Roseville CA 95661",
    "addr:housenumber":"3001",
    "addr:postcode":"95661",
    "addr:street":"Douglas Blvd",
    "iso:country":"US",
    "sg:address":"3001 Douglas Blvd",
    "sg:city":"Roseville",
    "sg:classifiers":[
        {
            "category":"Real Estate",
            "subcategory":"Real Estate Agent",
            "type":"Services"
        }
    ],
    "sg:phone":"+1 916 787 2020",
    "sg:postcode":"95661",
    "sg:province":"CA",
    "sg:tags":[
        "consultant"
    ],
    "sg:website":"www.huntleyfinancialgroup.com",
    "wof:name":"Huntley Financial Group",
    "wof:placetype":"venue"
},
  "geometry": {"coordinates":[-121.24070399999999,38.744231],"type":"Point"}
}