{
  "type": "Feature",
  "properties": {
    "addr:full":"1506 Sacramento Ave Broderick CA 95605",
    "addr:housenumber":"1506",
    "addr:postcode":"95605",
    "addr:street":"Sacramento Ave",
    "iso:country":"US",
    "sg:address":"1506 Sacramento Ave",
    "sg:city":"Broderick",
    "sg:classifiers":[
        {
            "category":"Personal",
            "subcategory":"Barber",
            "type":"Services"
        }
    ],
    "sg:phone":"+1 916 371 3031",
    "sg:postcode":"95605",
    "sg:province":"CA",
    "wof:name":"Ray Mata's Barbershop",
    "wof:placetype":"venue"
},
  "geometry": {"coordinates":[-121.53746700000001,38.59074],"type":"Point"}
}