{
  "type": "Feature",
  "properties": {
    "addr:full":"14111 Burbank Blvd Van Nuys CA 91401",
    "addr:housenumber":"14111",
    "addr:postcode":"91401",
    "addr:street":"Burbank Blvd",
    "iso:country":"US",
    "sg:address":"14111 Burbank Blvd",
    "sg:city":"Van Nuys",
    "sg:classifiers":[
        {
            "category":"Wholesale",
            "subcategory":"Apparel",
            "type":"Manufacturing & Wholesale Goods"
        }
    ],
    "sg:phone":"+1 818 997 9412",
    "sg:postcode":"91401",
    "sg:province":"CA",
    "sg:tags":[
        "clothing"
    ],
    "wof:name":"Babies r US",
    "wof:placetype":"venue"
},
  "geometry": {"coordinates":[-118.440765,34.172196],"type":"Point"}
}