{
  "type": "Feature",
  "properties": {
    "addr:full":"403 Edwards St Winters CA 95694",
    "addr:housenumber":"403",
    "addr:postcode":"95694",
    "addr:street":"Edwards St",
    "iso:country":"US",
    "sg:address":"403 Edwards St",
    "sg:city":"Winters",
    "sg:classifiers":[
        {
            "category":"Farming",
            "subcategory":"Farm",
            "type":"Manufacturing & Wholesale Goods"
        }
    ],
    "sg:phone":"+1 530 795 4673",
    "sg:postcode":"95694",
    "sg:province":"CA",
    "sg:tags":[
        "crop",
        "general"
    ],
    "wof:name":"Rap Farms Inc",
    "wof:placetype":"venue"
},
  "geometry": {"coordinates":[-121.975819,38.5213],"type":"Point"}
}