{
  "type": "Feature",
  "properties": {
    "addr:full":"2051 Eel River Dr Fortuna CA 95540",
    "addr:housenumber":"2051",
    "addr:postcode":"95540",
    "addr:street":"Eel River Dr",
    "iso:country":"US",
    "sg:address":"2051 Eel River Dr",
    "sg:city":"Fortuna",
    "sg:classifiers":[
        {
            "category":"Manufacturing",
            "subcategory":"Lumber",
            "type":"Manufacturing & Wholesale Goods"
        }
    ],
    "sg:phone":"+1 707 725 1106",
    "sg:postcode":"95540",
    "sg:province":"CA",
    "wof:name":"C W Wood Products",
    "wof:placetype":"venue"
},
  "geometry": {"coordinates":[-124.146382,40.560068],"type":"Point"}
}