{
  "type": "Feature",
  "properties": {
    "iso:country":"US",
    "sg:address":"2311 Helen Rd",
    "sg:city":"Fallbrook",
    "sg:classifiers":[
        {
            "category":"Professional",
            "subcategory":"Business Services",
            "type":"Services"
        }
    ],
    "sg:phone":"+1 760 723 9933",
    "sg:postcode":"92028",
    "sg:province":"CA",
    "wof:name":"De Luz Direct Distributors",
    "wof:placetype":"venue"
},
  "geometry": {"coordinates":[-117.30194,33.437315],"type":"Point"}
}