{
  "type": "Feature",
  "properties": {
    "addr:full":"3097 E Ana St Compton CA 90221",
    "addr:housenumber":"3097",
    "addr:postcode":"90221",
    "addr:street":"E Ana St",
    "iso:country":"US",
    "sg:address":"3097 E Ana St",
    "sg:city":"Compton",
    "sg:classifiers":[
        {
            "category":"Manufacturing",
            "subcategory":"Textiles",
            "type":"Manufacturing & Wholesale Goods"
        }
    ],
    "sg:phone":"+1 310 667 9030",
    "sg:postcode":"90221",
    "sg:province":"CA",
    "sg:tags":[
        "textiles-manufacturers"
    ],
    "wof:name":"B Green",
    "wof:placetype":"venue"
},
  "geometry": {"coordinates":[-118.206661,33.861609],"type":"Point"}
}