{
  "type": "Feature",
  "properties": {
    "addr:full":"200-219 Jibboom St Sacramento CA 95814",
    "addr:postcode":"200-219;95814",
    "addr:street":"Jibboom St",
    "iso:country":"US",
    "sg:address":"200-219 Jibboom St",
    "sg:city":"Sacramento",
    "sg:classifiers":[
        {
            "category":"Park",
            "type":"Public Place"
        }
    ],
    "sg:postcode":"95814",
    "sg:province":"CA",
    "sg:website":"www.cityofsacramento.org/parksan...",
    "wof:name":"Robert T. Matsui Waterfront Park",
    "wof:placetype":"venue"
},
  "geometry": {"coordinates":[-121.504932,38.589605],"type":"Point"}
}