{
  "type": "Feature",
  "properties": {
    "iso:country":"US",
    "sg:address":"220 Church St",
    "sg:city":"Jackson",
    "sg:classifiers":[
        {
            "category":"Organizations",
            "subcategory":"Non-profit Organization",
            "type":"Services"
        },
        {
            "category":"Building & Trades",
            "subcategory":"Equipment Rental",
            "type":"Services"
        }
    ],
    "sg:phone":"+1 209 223 4500",
    "sg:postcode":"95642",
    "sg:province":"CA",
    "sg:tags":[
        "disabled",
        "person",
        "social",
        "supply"
    ],
    "wof:name":"California Children's Svc Med",
    "wof:placetype":"venue"
},
  "geometry": {"coordinates":[-120.773187,38.350515],"type":"Point"}
}