{
  "type": "Feature",
  "properties": {
    "iso:country":"US",
    "sg:address":"548 N 13th Ave",
    "sg:city":"Upland",
    "sg:classifiers":[
        {
            "category":"Health Services",
            "subcategory":"Health Practitioner",
            "type":"Services"
        }
    ],
    "sg:phone":"+1 909 931 1620",
    "sg:postcode":"91786",
    "sg:province":"CA",
    "sg:tags":[
        "therapist",
        "physical"
    ],
    "wof:name":"Walters Physical Therapy",
    "wof:placetype":"venue"
},
  "geometry": {"coordinates":[-117.633827,34.102048],"type":"Point"}
}