{
  "type": "Feature",
  "properties": {
    "iso:country":"US",
    "sg:address":"2809 S Mission Road",
    "sg:city":"Fallbrook",
    "sg:classifiers":[
        {
            "category":"Real Estate",
            "subcategory":"Real Estate Agent",
            "type":"Services"
        }
    ],
    "sg:phone":"+1 619 252 7031",
    "sg:postcode":"92028",
    "sg:province":"CA",
    "wof:name":"North County Realtor",
    "wof:placetype":"venue"
},
  "geometry": {"coordinates":[-117.23944899999999,33.341175],"type":"Point"}
}