{
  "type": "Feature",
  "properties": {
    "addr:full":"752 18th St Arcata CA 95521",
    "addr:housenumber":"752",
    "addr:postcode":"95521",
    "addr:street":"18Th St",
    "iso:country":"US",
    "sg:address":"752 18th St",
    "sg:city":"Arcata",
    "sg:classifiers":[
        {
            "category":"Restaurant",
            "type":"Food & Drink"
        }
    ],
    "sg:phone":"+1 707 822 0277",
    "sg:postcode":"95521",
    "sg:province":"CA",
    "wof:name":"Hunan Village Restaurant",
    "wof:placetype":"venue"
},
  "geometry": {"coordinates":[-124.08372900000001,40.876137],"type":"Point"}
}