{
  "type": "Feature",
  "properties": {
    "iso:country":"US",
    "sg:address":"550 Deep Valley Dr Ste 267",
    "sg:city":"Rllng Hls Est",
    "sg:classifiers":[
        {
            "category":"Shopping",
            "subcategory":"Clothing, Apparel, & Fashions",
            "type":"Retail Goods"
        }
    ],
    "sg:phone":"+1 310 265 5241",
    "sg:postcode":"90274",
    "sg:province":"CA",
    "sg:tags":[
        "accessory",
        "clothing",
        "women's"
    ],
    "wof:name":"White House Black Market",
    "wof:placetype":"venue"
},
  "geometry": {"coordinates":[-118.37400100000001,33.772099],"type":"Point"}
}