{
  "type": "Feature",
  "properties": {
    "addr:full":"2552 W Woodland Dr Anaheim CA 92801",
    "addr:housenumber":"2552",
    "addr:postcode":"92801",
    "addr:street":"W Woodland Dr",
    "iso:country":"US",
    "sg:address":"2552 W Woodland Dr",
    "sg:city":"Anaheim",
    "sg:classifiers":[
        {
            "category":"Professional",
            "subcategory":"Lawyer & Legal Services",
            "type":"Services"
        }
    ],
    "sg:phone":"+1 714 229 0108",
    "sg:postcode":"92801",
    "sg:province":"CA",
    "sg:tags":[
        "divorce",
        "law",
        "family"
    ],
    "wof:name":"Delorenzo Kenneth Attorney At Law",
    "wof:placetype":"venue"
},
  "geometry": {"coordinates":[-117.97399900000001,33.849499],"type":"Point"}
}