{
  "type": "Feature",
  "properties": {
    "addr:full":"122 W Neal St Pleasanton CA 94566",
    "addr:housenumber":"122",
    "addr:postcode":"94566",
    "addr:street":"W Neal St",
    "iso:country":"US",
    "sg:address":"122 W Neal St",
    "sg:city":"Pleasanton",
    "sg:classifiers":[
        {
            "category":"Restaurant",
            "type":"Food & Drink"
        }
    ],
    "sg:menulink":"http://www.allmenus.com/ca/livermore-pleasanton/50955-haps-original/menu/",
    "sg:phone":"+1 925 600 9200",
    "sg:postcode":"94566",
    "sg:province":"CA",
    "sg:tags":[
        "american",
        "steakhouse"
    ],
    "wof:name":"Hap's Original",
    "wof:placetype":"venue"
},
  "geometry": {"coordinates":[-121.87526800000001,37.660138],"type":"Point"}
}