{
  "type": "Feature",
  "properties": {
    "addr:full":"68421 Commercial Rd Cathedral City CA 92234",
    "addr:housenumber":"68421",
    "addr:postcode":"92234",
    "addr:street":"Commercial Rd",
    "iso:country":"US",
    "sg:address":"68421 Commercial Rd",
    "sg:city":"Cathedral City",
    "sg:classifiers":[
        {
            "category":"Retail",
            "subcategory":"Auto Repair",
            "type":"Services"
        }
    ],
    "sg:phone":"+1 760 324 9626",
    "sg:postcode":"92234",
    "sg:province":"CA",
    "wof:name":"Hyundai Specialist",
    "wof:placetype":"venue"
},
  "geometry": {"coordinates":[-116.468002,33.781898],"type":"Point"}
}