{
  "type": "Feature",
  "properties": {
    "addr:full":"8214 Polo Crosse Ave Sacramento CA 95829",
    "addr:housenumber":"8214",
    "addr:postcode":"95829",
    "addr:street":"Polo Crosse Ave",
    "iso:country":"US",
    "sg:address":"8214 Polo Crosse Ave",
    "sg:city":"Sacramento",
    "sg:classifiers":[
        {
            "category":"Wholesale",
            "subcategory":"Machinery & Supplies",
            "type":"Manufacturing & Wholesale Goods"
        }
    ],
    "sg:phone":"+1 916 849 6779",
    "sg:postcode":"95829",
    "sg:province":"CA",
    "sg:tags":[
        "truck"
    ],
    "wof:name":"M & J Lift Truck Repair & Rntl",
    "wof:placetype":"venue"
},
  "geometry": {"coordinates":[-121.307242,38.457752],"type":"Point"}
}