{
  "type": "Feature",
  "properties": {
    "addr:full":"5977 Marlin Cir Carmichael CA 95608",
    "addr:housenumber":"5977",
    "addr:postcode":"95608",
    "addr:street":"Marlin Cir",
    "iso:country":"US",
    "sg:address":"5977 Marlin Cir",
    "sg:city":"Carmichael",
    "sg:classifiers":[
        {
            "category":"Shopping",
            "subcategory":"Catalog Store",
            "type":"Retail Goods"
        }
    ],
    "sg:phone":"+1 916 863 6915",
    "sg:postcode":"95608",
    "sg:province":"CA",
    "sg:tags":[
        "mail",
        "order"
    ],
    "wof:name":"Select Gifts",
    "wof:placetype":"venue"
},
  "geometry": {"coordinates":[-121.321274,38.672789],"type":"Point"}
}