{
  "type": "Feature",
  "properties": {
    "iso:country":"US",
    "sg:address":"459 Brunswick Dr",
    "sg:city":"Vallejo",
    "sg:classifiers":[
        {
            "category":"Professional",
            "type":"Services"
        }
    ],
    "sg:phone":"+1 707 647 2395",
    "sg:postcode":"94591",
    "sg:province":"CA",
    "wof:name":"Bizword LLC",
    "wof:placetype":"venue"
},
  "geometry": {"coordinates":[-122.192391,38.095672],"type":"Point"}
}