{
  "type": "Feature",
  "properties": {
    "addr:full":"434 Kuehnis Dr Campbell CA 95008",
    "addr:housenumber":"434",
    "addr:postcode":"95008",
    "addr:street":"Kuehnis Dr",
    "iso:country":"US",
    "sg:address":"434 Kuehnis Dr",
    "sg:city":"Campbell",
    "sg:classifiers":[
        {
            "category":"Professional",
            "type":"Services"
        }
    ],
    "sg:phone":"+1 408 377 2779",
    "sg:postcode":"95008",
    "sg:province":"CA",
    "wof:name":"C Collection",
    "wof:placetype":"venue"
},
  "geometry": {"coordinates":[-121.92945,37.292118],"type":"Point"}
}