{
  "type": "Feature",
  "properties": {
    "iso:country":"US",
    "sg:address":"4511 Finley Ave",
    "sg:city":"Los Angeles",
    "sg:classifiers":[
        {
            "category":"Shopping",
            "subcategory":"Clothing, Apparel, & Fashions",
            "type":"Retail Goods"
        }
    ],
    "sg:phone":"+1 510 282 7581",
    "sg:postcode":"90027",
    "sg:province":"CA",
    "sg:tags":[
        "lifestyle"
    ],
    "wof:name":"Wwwmaterial-Labcom",
    "wof:placetype":"venue"
},
  "geometry": {"coordinates":[-118.288522,34.10776],"type":"Point"}
}