{
  "type": "Feature",
  "properties": {
    "iso:country":"US",
    "sg:address":"1616 Niles St",
    "sg:city":"Bakersfield",
    "sg:classifiers":[
        {
            "category":"Shopping",
            "subcategory":"Used Merchandise",
            "type":"Retail Goods"
        }
    ],
    "sg:phone":"+1 661 323 2480",
    "sg:postcode":"93305",
    "sg:province":"CA",
    "sg:tags":[
        "shop",
        "thrift"
    ],
    "wof:name":"Best Value Thrift Store",
    "wof:placetype":"venue"
},
  "geometry": {"coordinates":[-118.975778,35.378451],"type":"Point"}
}