{
  "type": "Feature",
  "properties": {
    "addr:full":"374 S 1st St San Jose CA 95113",
    "addr:housenumber":"374",
    "addr:postcode":"95113",
    "addr:street":"S 1St St",
    "iso:country":"US",
    "sg:address":"374 S 1st St",
    "sg:city":"San Jose",
    "sg:classifiers":[
        {
            "category":"Restaurant",
            "type":"Food & Drink"
        }
    ],
    "sg:menulink":"http://www.allmenus.com/ca/san-jose/20267-eulipia-restaurant/menu/",
    "sg:phone":"+1 408 280 6161",
    "sg:postcode":"95113",
    "sg:province":"CA",
    "sg:tags":[
        "american"
    ],
    "wof:name":"Eulipia Restaurant",
    "wof:placetype":"venue"
},
  "geometry": {"coordinates":[-121.88625399999999,37.330429],"type":"Point"}
}