{
  "type": "Feature",
  "properties": {
    "iso:country":"US",
    "sg:address":"75 E 9th St",
    "sg:city":"Upland",
    "sg:classifiers":[
        {
            "category":"Professional",
            "subcategory":"Business Services",
            "type":"Services"
        }
    ],
    "sg:phone":"+1 909 608 0150",
    "sg:postcode":"91786",
    "sg:province":"CA",
    "sg:tags":[
        "paralegal"
    ],
    "wof:name":"Lori Palmer Document Assistanc",
    "wof:placetype":"venue"
},
  "geometry": {"coordinates":[-117.650644,34.096177],"type":"Point"}
}