{
  "type": "Feature",
  "properties": {
    "addr:full":"6100 Melrose Ave Los Angeles CA 90038",
    "addr:housenumber":"6100",
    "addr:postcode":"90038",
    "addr:street":"Melrose Ave",
    "iso:country":"US",
    "sg:address":"6100 Melrose Ave",
    "sg:city":"Los Angeles",
    "sg:classifiers":[
        {
            "category":"Communications",
            "subcategory":"Film & Video Production",
            "type":"Services"
        }
    ],
    "sg:phone":"+1 323 465 3900",
    "sg:postcode":"90038",
    "sg:province":"CA",
    "sg:tags":[
        "motion",
        "picture",
        "studio",
        "producer"
    ],
    "sg:website":"www.realityx.com",
    "wof:name":"Reality Check",
    "wof:placetype":"venue"
},
  "geometry": {"coordinates":[-118.33416699999999,34.083478],"type":"Point"}
}