{
  "type": "Feature",
  "properties": {
    "iso:country":"US",
    "sg:address":"505 Montgomery St",
    "sg:city":"Oroville",
    "sg:classifiers":[
        {
            "category":"Travel",
            "subcategory":"Hotels & Motels",
            "type":"Entertainment"
        }
    ],
    "sg:phone":"+1 530 532 9400",
    "sg:postcode":"95965",
    "sg:province":"CA",
    "wof:name":"Motel 6",
    "wof:placetype":"venue"
},
  "geometry": {"coordinates":[-121.569862,39.509116],"type":"Point"}
}