{
  "type": "Feature",
  "properties": {
    "addr:full":"3395 Orange Ave Signal Hill CA 90755",
    "addr:housenumber":"3395",
    "addr:postcode":"90755",
    "addr:street":"Orange Ave",
    "iso:country":"US",
    "sg:address":"3395 Orange Ave",
    "sg:city":"Signal Hill",
    "sg:classifiers":[
        {
            "category":"Autos & Motor Vehicles",
            "subcategory":"Fuel & Gas Station",
            "type":"Retail Goods"
        }
    ],
    "sg:phone":"+1 562 424 5051",
    "sg:postcode":"90755",
    "sg:province":"CA",
    "sg:tags":[
        "oil"
    ],
    "wof:name":"Chuck's 76",
    "wof:placetype":"venue"
},
  "geometry": {"coordinates":[-118.17639200000001,33.818825],"type":"Point"}
}