{
  "type": "Feature",
  "properties": {
    "addr:full":"598 Parnassus Ave San Francisco CA 94122",
    "addr:housenumber":"598",
    "addr:postcode":"94122",
    "addr:street":"Parnassus Ave",
    "iso:country":"US",
    "sg:address":"598 Parnassus Ave",
    "sg:city":"San Francisco",
    "sg:classifiers":[
        {
            "category":"Cafe",
            "type":"Food & Drink"
        }
    ],
    "sg:menulink":"http://www.allmenus.com/ca/san-francisco/44946-palio-paninoteca-italian-style-cafe/menu/",
    "sg:phone":"+1 415 681 9925",
    "sg:postcode":"94122",
    "sg:province":"CA",
    "sg:tags":[
        "italian"
    ],
    "wof:name":"Palio Paninoteca Italian Style Cafe",
    "wof:placetype":"venue"
},
  "geometry": {"coordinates":[-122.45987,37.763004],"type":"Point"}
}