{
  "type": "Feature",
  "properties": {
    "addr:full":"393 Lake Merced Blvd Daly City CA 94015",
    "addr:housenumber":"393",
    "addr:postcode":"94015",
    "addr:street":"Lake Merced Blvd",
    "iso:country":"US",
    "sg:address":"393 Lake Merced Blvd",
    "sg:city":"Daly City",
    "sg:classifiers":[
        {
            "category":"Food & Beverages",
            "subcategory":"Bakery",
            "type":"Retail Goods"
        }
    ],
    "sg:phone":"+1 650 994 8827",
    "sg:postcode":"94015",
    "sg:province":"CA",
    "sg:tags":[
        "baker"
    ],
    "wof:name":"Granny Eng's Bakers",
    "wof:placetype":"venue"
},
  "geometry": {"coordinates":[-122.483744,37.699257],"type":"Point"}
}