{
  "type": "Feature",
  "properties": {
    "addr:full":"2269 Will Wool Dr San Jose CA 95112",
    "addr:housenumber":"2269",
    "addr:postcode":"95112",
    "addr:street":"Will Wool Dr",
    "iso:country":"US",
    "sg:address":"2269 Will Wool Dr",
    "sg:city":"San Jose",
    "sg:classifiers":[
        {
            "category":"Building & Trades",
            "subcategory":"Construction",
            "type":"Services"
        }
    ],
    "sg:phone":"+1 408 275 9296",
    "sg:postcode":"95112",
    "sg:province":"CA",
    "sg:tags":[
        "company"
    ],
    "wof:name":"Central Construction & Repair",
    "wof:placetype":"venue"
},
  "geometry": {"coordinates":[-121.848089,37.312153],"type":"Point"}
}