{
  "type": "Feature",
  "properties": {
    "addr:full":"11005 Westview Pkwy San Diego CA 92126",
    "addr:housenumber":"11005",
    "addr:postcode":"92126",
    "addr:street":"Westview Pkwy",
    "iso:country":"US",
    "sg:address":"11005 Westview Pkwy",
    "sg:city":"San Diego",
    "sg:classifiers":[
        {
            "category":"Building & Trades",
            "subcategory":"Construction",
            "type":"Services"
        }
    ],
    "sg:phone":"+1 858 536 1663",
    "sg:postcode":"92126",
    "sg:province":"CA",
    "sg:tags":[
        "home",
        "builder"
    ],
    "wof:name":"Archer Western Contractors",
    "wof:placetype":"venue"
},
  "geometry": {"coordinates":[-117.119095,32.924282],"type":"Point"}
}