{
  "type": "Feature",
  "properties": {
    "iso:country":"US",
    "sg:address":"358 S Fairview Ave",
    "sg:city":"Goleta",
    "sg:classifiers":[
        {
            "category":"Recreation",
            "type":"Entertainment"
        }
    ],
    "sg:phone":"+1 805 681 0604",
    "sg:postcode":"93117",
    "sg:province":"CA",
    "sg:tags":[
        "amusement"
    ],
    "wof:name":"Seedwings Manufacturing",
    "wof:placetype":"venue"
},
  "geometry": {"coordinates":[-119.830236,34.426243],"type":"Point"}
}