{
  "type": "Feature",
  "properties": {
    "iso:country":"US",
    "sg:address":"5351 Cedars Rd",
    "sg:city":"Redding",
    "sg:classifiers":[
        {
            "category":"Organizations",
            "subcategory":"Religious Organization",
            "type":"Services"
        }
    ],
    "sg:phone":"+1 530 244 6350",
    "sg:postcode":"96001",
    "sg:province":"CA",
    "sg:tags":[
        "church"
    ],
    "wof:name":"Jehovah's Witnesses",
    "wof:placetype":"venue"
},
  "geometry": {"coordinates":[-122.389109,40.54297],"type":"Point"}
}