{
  "type": "Feature",
  "properties": {
    "iso:country":"US",
    "sg:address":"418 W Lennox St",
    "sg:city":"Yreka",
    "sg:classifiers":[
        {
            "category":"Shopping",
            "type":"Retail Goods"
        }
    ],
    "sg:phone":"+1 530 842 4370",
    "sg:postcode":"96097",
    "sg:province":"CA",
    "sg:tags":[
        "merchandise"
    ],
    "wof:name":"Fairy Hill Enchanted Gardens",
    "wof:placetype":"venue"
},
  "geometry": {"coordinates":[-122.637808,41.73685],"type":"Point"}
}