{
  "type": "Feature",
  "properties": {
    "addr:full":"5259 State Highway 49 N Mariposa CA 95338",
    "addr:housenumber":"5259",
    "addr:postcode":"95338",
    "addr:street":"State Highway 49 N",
    "iso:country":"US",
    "sg:address":"5259 State Highway 49 N",
    "sg:city":"Mariposa",
    "sg:classifiers":[
        {
            "category":"Place Of Worship",
            "subcategory":"Church",
            "type":"Public Place"
        },
        {
            "category":"Place Of Worship",
            "type":"Public Place"
        }
    ],
    "sg:phone":"+1 209 966 2156",
    "sg:postcode":"95338",
    "sg:province":"CA",
    "sg:tags":[
        "testament",
        "christ-new",
        "churches-church",
        "christ"
    ],
    "wof:name":"Church Of Christ",
    "wof:placetype":"venue"
},
  "geometry": {"coordinates":[-119.97690299999999,37.493462],"type":"Point"}
}