{
  "type": "Feature",
  "properties": {
    "iso:country":"US",
    "sg:address":"1635 E Prosperity Ave",
    "sg:city":"Tulare",
    "sg:classifiers":[
        {
            "category":"Banks & Credit Unions",
            "subcategory":"Bank",
            "type":"Services"
        }
    ],
    "sg:phone":"+1 559 687 3350",
    "sg:postcode":"93274",
    "sg:province":"CA",
    "wof:name":"Bank of Visalia",
    "wof:placetype":"venue"
},
  "geometry": {"coordinates":[-119.322867,36.225856],"type":"Point"}
}