{
  "type": "Feature",
  "properties": {
    "iso:country":"US",
    "sg:address":"6261 E Spring St",
    "sg:city":"Long Beach",
    "sg:classifiers":[
        {
            "category":"Real Estate",
            "subcategory":"Real Estate Agent",
            "type":"Services"
        }
    ],
    "sg:phone":"+1 562 366 5150",
    "sg:postcode":"90808",
    "sg:province":"CA",
    "sg:website":"www.erawestcoast.com",
    "wof:name":"ERA West Coast",
    "wof:placetype":"venue"
},
  "geometry": {"coordinates":[-118.10832499999999,33.810556],"type":"Point"}
}