{
  "type": "Feature",
  "properties": {
    "addr:full":"2627 N Hollywood Way Burbank CA 91503",
    "addr:housenumber":"2627",
    "addr:postcode":"91503",
    "addr:street":"N Hollywood Way",
    "iso:country":"US",
    "sg:address":"2627 N Hollywood Way",
    "sg:city":"Burbank",
    "sg:classifiers":[
        {
            "category":"Fast Food",
            "type":"Food & Drink"
        }
    ],
    "sg:postcode":"91503",
    "sg:province":"CA",
    "sg:website":"www.mcdonalds.com",
    "wof:name":"McDonald's",
    "wof:placetype":"venue"
},
  "geometry": {"coordinates":[-118.348899,34.196077],"type":"Point"}
}