{
  "type": "Feature",
  "properties": {
    "addr:full":"3601 Overland Ave Los Angeles CA 90034",
    "addr:housenumber":"3601",
    "addr:postcode":"90034",
    "addr:street":"Overland Ave",
    "iso:country":"US",
    "sg:address":"3601 Overland Ave",
    "sg:city":"Los Angeles",
    "sg:classifiers":[
        {
            "category":"Restaurant",
            "type":"Food & Drink"
        }
    ],
    "sg:phone":"+1 310 559 9999",
    "sg:postcode":"90034",
    "sg:province":"CA",
    "sg:tags":[
        "new",
        "american"
    ],
    "sg:website":"overlandcafe.com",
    "wof:name":"Overland Caf?",
    "wof:placetype":"venue"
},
  "geometry": {"coordinates":[-118.410004,34.022499],"type":"Point"}
}