{
  "type": "Feature",
  "properties": {
    "addr:full":"861 Sutter St. San Francisco CA 94109",
    "addr:housenumber":"861",
    "addr:postcode":"94109",
    "addr:street":"Sutter St.",
    "iso:country":"US",
    "sg:address":"861 Sutter St.",
    "sg:city":"San Francisco",
    "sg:classifiers":[
        {
            "category":"Building & Trades",
            "subcategory":"Construction",
            "type":"Services"
        }
    ],
    "sg:phone":"+1 415 368 5176",
    "sg:postcode":"94109",
    "sg:province":"CA",
    "sg:tags":[
        "interior",
        "design"
    ],
    "wof:name":"J. Allen Associates",
    "wof:placetype":"venue"
},
  "geometry": {"coordinates":[-122.414423,37.788198],"type":"Point"}
}