{
  "type": "Feature",
  "properties": {
    "addr:full":"11256 Whittier Blvd Whittier CA 90606",
    "addr:housenumber":"11256",
    "addr:postcode":"90606",
    "addr:street":"Whittier Blvd",
    "iso:country":"US",
    "sg:address":"11256 Whittier Blvd",
    "sg:city":"Whittier",
    "sg:classifiers":[
        {
            "category":"Shopping",
            "subcategory":"Clothing, Apparel, & Fashions",
            "type":"Retail Goods"
        }
    ],
    "sg:phone":"+1 562 692 7780",
    "sg:postcode":"90606",
    "sg:province":"CA",
    "wof:name":"MADE",
    "wof:placetype":"venue"
},
  "geometry": {"coordinates":[-118.05738599999999,33.985379],"type":"Point"}
}