{
  "type": "Feature",
  "properties": {
    "addr:full":"235 S Hacienda Blvd Hacienda Heights CA 91745",
    "addr:housenumber":"235",
    "addr:postcode":"91745",
    "addr:street":"S Hacienda Blvd",
    "iso:country":"US",
    "sg:address":"235 S Hacienda Blvd",
    "sg:city":"Hacienda Heights",
    "sg:classifiers":[
        {
            "category":"Wholesale",
            "subcategory":"Groceries",
            "type":"Manufacturing & Wholesale Goods"
        }
    ],
    "sg:phone":"+1 626 855 4711",
    "sg:postcode":"91745",
    "sg:province":"CA",
    "sg:tags":[
        "eating"
    ],
    "wof:name":"Industry Wholesale",
    "wof:placetype":"venue"
},
  "geometry": {"coordinates":[-117.95928499999999,34.018268],"type":"Point"}
}