{
  "type": "Feature",
  "properties": {
    "addr:full":"650 Robinson Ave San Diego CA 92103",
    "addr:housenumber":"650",
    "addr:postcode":"92103",
    "addr:street":"Robinson Ave",
    "iso:country":"US",
    "sg:address":"650 Robinson Ave",
    "sg:city":"San Diego",
    "sg:classifiers":[
        {
            "category":"Organizations",
            "subcategory":"Membership Organization",
            "type":"Services"
        },
        {
            "category":"Recreation",
            "type":"Entertainment"
        }
    ],
    "sg:phone":"+1 858 679 1995",
    "sg:postcode":"92103",
    "sg:province":"CA",
    "sg:tags":[
        "club",
        "athletic"
    ],
    "wof:name":"Poway Girls Softball League In",
    "wof:placetype":"venue"
},
  "geometry": {"coordinates":[-117.15890400000001,32.747044],"type":"Point"}
}