{
  "type": "Feature",
  "properties": {
    "addr:full":"315 California St San Francisco CA 94104",
    "addr:housenumber":"315",
    "addr:postcode":"94104",
    "addr:street":"California St",
    "iso:country":"US",
    "sg:address":"315 California St",
    "sg:city":"San Francisco",
    "sg:classifiers":[
        {
            "category":"Restaurant",
            "type":"Food & Drink"
        }
    ],
    "sg:menulink":"http://www.allmenus.com/ca/san-francisco/64958-san-francisco-soup-company/menu/",
    "sg:phone":"+1 415 989 7687",
    "sg:postcode":"94104",
    "sg:province":"CA",
    "sg:tags":[
        "soup",
        "american",
        "salad"
    ],
    "wof:name":"San Francisco Soup Company",
    "wof:placetype":"venue"
},
  "geometry": {"coordinates":[-122.400251,37.793222],"type":"Point"}
}