{
  "type": "Feature",
  "properties": {
    "iso:country":"US",
    "sg:address":"4400 Central Ave",
    "sg:city":"Fremont",
    "sg:classifiers":[
        {
            "category":"Real Estate",
            "subcategory":"Real Estate Operator",
            "type":"Services"
        }
    ],
    "sg:phone":"+1 510 795 9024",
    "sg:postcode":"94536",
    "sg:province":"CA",
    "sg:tags":[
        "apartment"
    ],
    "wof:name":"Glenview Apartments",
    "wof:placetype":"venue"
},
  "geometry": {"coordinates":[-122.008628,37.550415],"type":"Point"}
}