{
  "type": "Feature",
  "properties": {
    "addr:full":"1923 Cabernet Way Salinas CA 93906",
    "addr:housenumber":"1923",
    "addr:postcode":"93906",
    "addr:street":"Cabernet Way",
    "iso:country":"US",
    "sg:address":"1923 Cabernet Way",
    "sg:city":"Salinas",
    "sg:classifiers":[
        {
            "category":"Retail",
            "subcategory":"Laundry & Dry Cleaning",
            "type":"Services"
        }
    ],
    "sg:phone":"+1 831 442 2090",
    "sg:postcode":"93906",
    "sg:province":"CA",
    "sg:tags":[
        "cleaners",
        "rug",
        "carpet"
    ],
    "wof:name":"Clean Tech",
    "wof:placetype":"venue"
},
  "geometry": {"coordinates":[-121.640181,36.716006],"type":"Point"}
}