{
  "type": "Feature",
  "properties": {
    "iso:country":"US",
    "sg:address":"801 S Broadway",
    "sg:city":"Santa Maria",
    "sg:classifiers":[
        {
            "category":"Professional",
            "subcategory":"Lawyer & Legal Services",
            "type":"Services"
        }
    ],
    "sg:phone":"+1 805 922 3432",
    "sg:postcode":"93454",
    "sg:province":"CA",
    "sg:tags":[
        "attorney"
    ],
    "wof:name":"Kristofer Kallman",
    "wof:placetype":"venue"
},
  "geometry": {"coordinates":[-120.436053,34.9445],"type":"Point"}
}