{
  "type": "Feature",
  "properties": {
    "iso:country":"US",
    "sg:address":"175 S el Molino Ave",
    "sg:city":"Pasadena",
    "sg:classifiers":[
        {
            "category":"Health Services",
            "subcategory":"Doctor",
            "type":"Services"
        }
    ],
    "sg:phone":"+1 626 792 0448",
    "sg:postcode":"91101",
    "sg:province":"CA",
    "sg:tags":[
        "dentist"
    ],
    "wof:name":"Lee A Grund DDS",
    "wof:placetype":"venue"
},
  "geometry": {"coordinates":[-118.136929,34.14328],"type":"Point"}
}