{
  "type": "Feature",
  "properties": {
    "addr:full":"10771 N Wolfe Rd Cupertino CA 95014",
    "addr:housenumber":"10771",
    "addr:postcode":"95014",
    "addr:street":"N Wolfe Rd",
    "iso:country":"US",
    "sg:address":"10771 N Wolfe Rd",
    "sg:city":"Cupertino",
    "sg:classifiers":[
        {
            "category":"Education",
            "subcategory":"Special Training",
            "type":"Public Place"
        }
    ],
    "sg:phone":"+1 408 873 8869",
    "sg:postcode":"95014",
    "sg:province":"CA",
    "sg:tags":[
        "tutoring"
    ],
    "wof:name":"Brainchild Education Ctr",
    "wof:placetype":"venue"
},
  "geometry": {"coordinates":[-122.014251,37.33378],"type":"Point"}
}