{
  "type": "Feature",
  "properties": {
    "addr:full":"1104 S State St Ste B Ukiah CA 95482",
    "addr:housenumber":"1104",
    "addr:postcode":"ca 95482",
    "addr:street":"S State St Ste B",
    "iso:country":"US",
    "sg:address":"1104 S State St Ste B",
    "sg:city":"Ukiah",
    "sg:classifiers":[
        {
            "category":"Personal",
            "subcategory":"Beauty Salon",
            "type":"Services"
        },
        {
            "category":"Personal",
            "subcategory":"Nail Salon",
            "type":"Services"
        }
    ],
    "sg:phone":"+1 707 462 9283",
    "sg:postcode":"95482",
    "sg:province":"CA",
    "wof:name":"Trendsetters",
    "wof:placetype":"venue"
},
  "geometry": {"coordinates":[-123.20526099999999,39.135712],"type":"Point"}
}