{
  "type": "Feature",
  "properties": {
    "iso:country":"US",
    "sg:address":"2703 W 8th St",
    "sg:city":"Los Angeles",
    "sg:classifiers":[
        {
            "category":"Utilities",
            "subcategory":"Telephone",
            "type":"Services"
        }
    ],
    "sg:phone":"+1 213 385 0797",
    "sg:postcode":"90005",
    "sg:province":"CA",
    "sg:tags":[
        "company"
    ],
    "wof:name":"Ardon Communication",
    "wof:placetype":"venue"
},
  "geometry": {"coordinates":[-118.286824,34.057804],"type":"Point"}
}