{
  "type": "Feature",
  "properties": {
    "addr:full":"1120 W Linden St Riverside CA 92507",
    "addr:housenumber":"1120",
    "addr:postcode":"92507",
    "addr:street":"W Linden St",
    "iso:country":"US",
    "sg:address":"1120 W Linden St",
    "sg:city":"Riverside",
    "sg:classifiers":[
        {
            "category":"Real Estate",
            "subcategory":"Real Estate Operator",
            "type":"Services"
        }
    ],
    "sg:phone":"+1 951 787 6263",
    "sg:postcode":"92507",
    "sg:province":"CA",
    "sg:tags":[
        "apartment"
    ],
    "wof:name":"Windwood Apartments",
    "wof:placetype":"venue"
},
  "geometry": {"coordinates":[-117.337553,33.979375],"type":"Point"}
}