{
  "type": "Feature",
  "properties": {
    "iso:country":"US",
    "sg:address":"17127 Pioneer Blvd",
    "sg:city":"Artesia",
    "sg:classifiers":[
        {
            "category":"Professional",
            "subcategory":"Accounting & Tax Preparation",
            "type":"Services"
        }
    ],
    "sg:phone":"+1 562 403 7345",
    "sg:postcode":"90701",
    "sg:province":"CA",
    "sg:tags":[
        "accountant"
    ],
    "wof:name":"Lee Jai & Co",
    "wof:placetype":"venue"
},
  "geometry": {"coordinates":[-118.082001,33.874599],"type":"Point"}
}