{
  "type": "Feature",
  "properties": {
    "addr:full":"3830 U St Sacramento CA 95817",
    "addr:housenumber":"3830",
    "addr:postcode":"95817",
    "addr:street":"U St",
    "iso:country":"US",
    "sg:address":"3830 U St",
    "sg:city":"Sacramento",
    "sg:classifiers":[
        {
            "category":"Education",
            "subcategory":"College",
            "type":"Public Place"
        },
        {
            "category":"Organizations",
            "subcategory":"Membership Organization",
            "type":"Services"
        }
    ],
    "sg:phone":"+1 916 454 5805",
    "sg:postcode":"95817",
    "sg:province":"CA",
    "sg:tags":[
        "student",
        "housing",
        "fraternity",
        "sorority",
        "fraternal"
    ],
    "sg:website":"http://www.californiagrange.org",
    "wof:name":"Calif. State Grange",
    "wof:placetype":"venue"
},
  "geometry": {"coordinates":[-121.45994399999999,38.557989],"type":"Point"}
}