{
  "type": "Feature",
  "properties": {
    "iso:country":"US",
    "sg:address":"910 S McGlincey Ln",
    "sg:city":"Campbell",
    "sg:classifiers":[
        {
            "category":"Building & Trades",
            "subcategory":"Construction",
            "type":"Services"
        }
    ],
    "sg:phone":"+1 408 292 0865",
    "sg:postcode":"95008",
    "sg:province":"CA",
    "sg:tags":[
        "contractor"
    ],
    "wof:name":"Anthony Roof Service Co Inc",
    "wof:placetype":"venue"
},
  "geometry": {"coordinates":[-121.94506,37.274128],"type":"Point"}
}