{
  "type": "Feature",
  "properties": {
    "addr:full":"8439 White Oak Ave Rancho Cucamonga CA 91730",
    "addr:housenumber":"8439",
    "addr:postcode":"91730",
    "addr:street":"White Oak Ave",
    "iso:country":"US",
    "sg:address":"8439 White Oak Ave",
    "sg:city":"Rancho Cucamonga",
    "sg:classifiers":[
        {
            "category":"Professional",
            "subcategory":"Employment Agencies",
            "type":"Services"
        }
    ],
    "sg:phone":"+1 909 466 4211",
    "sg:postcode":"91730",
    "sg:province":"CA",
    "sg:tags":[
        "help",
        "contractor"
    ],
    "wof:name":"Monarch Staffing",
    "wof:placetype":"venue"
},
  "geometry": {"coordinates":[-117.564036,34.102208],"type":"Point"}
}