{
  "type": "Feature",
  "properties": {
    "addr:full":"800 E Cotati Ave Cotati CA 94931",
    "addr:housenumber":"800",
    "addr:postcode":"94931",
    "addr:street":"E Cotati Ave",
    "iso:country":"US",
    "sg:address":"800 E Cotati Ave",
    "sg:city":"Cotati",
    "sg:classifiers":[
        {
            "category":"Arts & Performance",
            "subcategory":"Music",
            "type":"Entertainment"
        }
    ],
    "sg:phone":"+1 707 664 9383",
    "sg:postcode":"94931",
    "sg:province":"CA",
    "sg:tags":[
        "jockey",
        "disc"
    ],
    "sg:website":"http://www.fiznikrick.com",
    "wof:name":"Rick Minervini",
    "wof:placetype":"venue"
},
  "geometry": {"coordinates":[-122.69407699999999,38.33086],"type":"Point"}
}