{
  "type": "Feature",
  "properties": {
    "iso:country":"US",
    "sg:address":"25 Mason St",
    "sg:city":"San Francisco",
    "sg:classifiers":[
        {
            "category":"Restaurant",
            "type":"Food & Drink"
        }
    ],
    "sg:phone":"+1 415 771 5503",
    "sg:postcode":"94102",
    "sg:province":"CA",
    "sg:website":"www.lazeezrestaurant.com",
    "wof:name":"LA Zeez",
    "wof:placetype":"venue"
},
  "geometry": {"coordinates":[-122.409153,37.783302],"type":"Point"}
}