{
  "type": "Feature",
  "properties": {
    "addr:full":"461 Pacific Ave San Francisco CA 94133",
    "addr:housenumber":"461",
    "addr:postcode":"94133",
    "addr:street":"Pacific Ave",
    "iso:country":"US",
    "sg:address":"461 Pacific Ave",
    "sg:city":"San Francisco",
    "sg:classifiers":[
        {
            "category":"Wholesale",
            "subcategory":"Furniture",
            "type":"Manufacturing & Wholesale Goods"
        }
    ],
    "sg:phone":"+1 415 421 7911",
    "sg:postcode":"94133",
    "sg:province":"CA",
    "wof:name":"Sibbitt & Associates I N C",
    "wof:placetype":"venue"
},
  "geometry": {"coordinates":[-122.40353399999999,37.797244],"type":"Point"}
}