{
  "type": "Feature",
  "properties": {
    "addr:full":"7401 Redwood Blvd Novato CA 94945",
    "addr:housenumber":"7401",
    "addr:postcode":"94945",
    "addr:street":"Redwood Blvd",
    "iso:country":"US",
    "sg:address":"7401 Redwood Blvd",
    "sg:city":"Novato",
    "sg:classifiers":[
        {
            "category":"Retail",
            "subcategory":"Auto Repair",
            "type":"Services"
        }
    ],
    "sg:phone":"+1 415 898 4842",
    "sg:postcode":"94945",
    "sg:province":"CA",
    "sg:tags":[
        "repairing",
        "automobile"
    ],
    "wof:name":"Bacon's Auto Svc",
    "wof:placetype":"venue"
},
  "geometry": {"coordinates":[-122.56965700000001,38.109044],"type":"Point"}
}