{
  "type": "Feature",
  "properties": {
    "iso:country":"US",
    "sg:address":"28631 S Western Ave",
    "sg:city":"Rancho Pls Vrds",
    "sg:classifiers":[
        {
            "category":"Communications",
            "subcategory":"Film & Video Production",
            "type":"Services"
        }
    ],
    "sg:phone":"+1 310 831 6227",
    "sg:postcode":"90275",
    "sg:province":"CA",
    "sg:tags":[
        "audio"
    ],
    "sg:website":"www.livewireprod.com",
    "wof:name":"Live Wire Productions & Visual",
    "wof:placetype":"venue"
},
  "geometry": {"coordinates":[-118.312543,33.759788],"type":"Point"}
}