{
  "type": "Feature",
  "properties": {
    "addr:full":"115 5th St Colusa CA 95932",
    "addr:housenumber":"115",
    "addr:postcode":"95932",
    "addr:street":"5Th St",
    "iso:country":"US",
    "sg:address":"115 5th St",
    "sg:city":"Colusa",
    "sg:classifiers":[
        {
            "category":"Autos & Motor Vehicles",
            "subcategory":"Auto Supplies",
            "type":"Retail Goods"
        }
    ],
    "sg:phone":"+1 530 458 2128",
    "sg:postcode":"95932",
    "sg:province":"CA",
    "sg:tags":[
        "automobile",
        "part",
        "accessory"
    ],
    "wof:name":"Baxter Auto Parts",
    "wof:placetype":"venue"
},
  "geometry": {"coordinates":[-122.00775,39.214408],"type":"Point"}
}