{
  "type": "Feature",
  "properties": {
    "iso:country":"US",
    "sg:address":"24725 San Fernando Rd",
    "sg:city":"Newhall",
    "sg:classifiers":[
        {
            "category":"Retail",
            "subcategory":"Self-service Laundry",
            "type":"Services"
        }
    ],
    "sg:phone":"+1 661 255 1522",
    "sg:postcode":"91321",
    "sg:province":"CA",
    "wof:name":"Just For You Laundromat",
    "wof:placetype":"venue"
},
  "geometry": {"coordinates":[-118.531521,34.38494],"type":"Point"}
}