{
  "type": "Feature",
  "properties": {
    "addr:full":"25315 Howard Dr Hemet CA 92544",
    "addr:housenumber":"25315",
    "addr:postcode":"92544",
    "addr:street":"Howard Dr",
    "iso:country":"US",
    "sg:address":"25315 Howard Dr",
    "sg:city":"Hemet",
    "sg:classifiers":[
        {
            "category":"Building & Trades",
            "subcategory":"Plumbing",
            "type":"Services"
        }
    ],
    "sg:phone":"+1 951 927 5208",
    "sg:postcode":"92544",
    "sg:province":"CA",
    "sg:tags":[
        "plumber",
        "industrial",
        "contractors-commercial"
    ],
    "wof:name":"Vision Plumbing",
    "wof:placetype":"venue"
},
  "geometry": {"coordinates":[-116.9042,33.753477],"type":"Point"}
}