{
  "type": "Feature",
  "properties": {
    "addr:full":"5233 Mission Street San Francisco CA 94112",
    "addr:housenumber":"5233",
    "addr:postcode":"94112",
    "addr:street":"Mission Street",
    "iso:country":"US",
    "sg:address":"5233 Mission Street",
    "sg:city":"San Francisco",
    "sg:classifiers":[
        {
            "category":"Personal",
            "subcategory":"Nail Salon",
            "type":"Services"
        }
    ],
    "sg:phone":"+1 415 334 8660",
    "sg:postcode":"94112",
    "sg:province":"CA",
    "wof:name":"Nelia's Glamourama",
    "wof:placetype":"venue"
},
  "geometry": {"coordinates":[-122.442001,37.715099],"type":"Point"}
}