{
  "type": "Feature",
  "properties": {
    "iso:country":"US",
    "sg:address":"440 Western Ave Ste 201",
    "sg:city":"Glendale",
    "sg:classifiers":[
        {
            "category":"Professional",
            "subcategory":"Accounting & Tax Preparation",
            "type":"Services"
        }
    ],
    "sg:phone":"+1 818 546 1094",
    "sg:postcode":"91201",
    "sg:province":"CA",
    "sg:tags":[
        "accountant"
    ],
    "wof:name":"Nagoshiner & Weisnger CPA",
    "wof:placetype":"venue"
},
  "geometry": {"coordinates":[-118.297997,34.1628],"type":"Point"}
}