{
  "type": "Feature",
  "properties": {
    "iso:country":"US",
    "sg:address":"140 S Palm Canyon Dr",
    "sg:city":"Palm Springs",
    "sg:classifiers":[
        {
            "category":"Shopping",
            "subcategory":"Clothing, Apparel, & Fashions",
            "type":"Retail Goods"
        }
    ],
    "sg:phone":"+1 760 320 4616",
    "sg:postcode":"92262",
    "sg:province":"CA",
    "wof:name":"Resorta",
    "wof:placetype":"venue"
},
  "geometry": {"coordinates":[-116.546724,33.821466],"type":"Point"}
}