{
  "type": "Feature",
  "properties": {
    "addr:full":"7128 English Colony Way Penryn CA 95663",
    "addr:housenumber":"7128",
    "addr:postcode":"95663",
    "addr:street":"English Colony Way",
    "iso:country":"US",
    "sg:address":"7128 English Colony Way",
    "sg:city":"Penryn",
    "sg:classifiers":[
        {
            "category":"Building & Trades",
            "subcategory":"Construction",
            "type":"Services"
        }
    ],
    "sg:phone":"+1 916 663 4475",
    "sg:postcode":"95663",
    "sg:province":"CA",
    "sg:tags":[
        "excavation",
        "contractor"
    ],
    "wof:name":"Nolans Backhoe Service",
    "wof:placetype":"venue"
},
  "geometry": {"coordinates":[-121.170429,38.853099],"type":"Point"}
}