{
  "type": "Feature",
  "properties": {
    "iso:country":"US",
    "sg:address":"464 Alvarado St",
    "sg:city":"Monterey",
    "sg:classifiers":[
        {
            "category":"Home & Garden",
            "subcategory":"Furniture",
            "type":"Retail Goods"
        }
    ],
    "sg:phone":"+1 831 655 3902",
    "sg:postcode":"93940",
    "sg:province":"CA",
    "wof:name":"Hacienda Rustic Furnishing",
    "wof:placetype":"venue"
},
  "geometry": {"coordinates":[-121.894892,36.598432],"type":"Point"}
}