{
  "type": "Feature",
  "properties": {
    "addr:full":"2463 Regent Rd Livermore CA 94550",
    "addr:housenumber":"2463",
    "addr:postcode":"94550",
    "addr:street":"Regent Rd",
    "iso:country":"US",
    "sg:address":"2463 Regent Rd",
    "sg:city":"Livermore",
    "sg:classifiers":[
        {
            "category":"Professional",
            "subcategory":"Accounting & Tax Preparation",
            "type":"Services"
        }
    ],
    "sg:phone":"+1 925 371 8124",
    "sg:postcode":"94550",
    "sg:province":"CA",
    "sg:tags":[
        "bookkeeping",
        "general"
    ],
    "wof:name":"Ann Damelos",
    "wof:placetype":"venue"
},
  "geometry": {"coordinates":[-121.78012200000001,37.650955],"type":"Point"}
}