{
  "type": "Feature",
  "properties": {
    "addr:full":"10963 Whipple St North Hollywood CA 91602",
    "addr:housenumber":"10963",
    "addr:postcode":"91602",
    "addr:street":"Whipple St",
    "iso:country":"US",
    "sg:address":"10963 Whipple St",
    "sg:city":"North Hollywood",
    "sg:classifiers":[
        {
            "category":"Manufacturing",
            "subcategory":"Printing",
            "type":"Manufacturing & Wholesale Goods"
        }
    ],
    "sg:phone":"+1 818 506 3246",
    "sg:postcode":"91602",
    "sg:province":"CA",
    "sg:tags":[
        "publishing"
    ],
    "wof:name":"Rock Summit Publishing",
    "wof:placetype":"venue"
},
  "geometry": {"coordinates":[-118.36868200000001,34.148143],"type":"Point"}
}