{
  "type": "Feature",
  "properties": {
    "addr:full":"135 San Carlos Street, San Jose, CA",
    "iso:country":"US",
    "name:eng_x_preferred":[
        "City National Civic"
    ],
    "wof:name":"City National Civic",
    "wof:placetype":"venue"
},
  "geometry": {"coordinates":[-121.88385844231,37.354560526695],"type":"Point"}
}