{
  "type": "Feature",
  "properties": {
    "iso:country":"US",
    "sg:address":"3316 Governor Dr",
    "sg:city":"San Diego",
    "sg:classifiers":[
        {
            "category":"Sports & Exercise",
            "subcategory":"Gym",
            "type":"Entertainment"
        }
    ],
    "sg:phone":"+1 858 373 2870",
    "sg:postcode":"92122",
    "sg:province":"CA",
    "sg:tags":[
        "club",
        "health",
        "studio",
        "gymnasium"
    ],
    "wof:name":"Curves For Women",
    "wof:placetype":"venue"
},
  "geometry": {"coordinates":[-117.213638,32.85085],"type":"Point"}
}