{
  "type": "Feature",
  "properties": {
    "iso:country":"US",
    "sg:address":"Kaiser Permanente 2238 Geary Blvd. 2nd Floor",
    "sg:city":"San Francisco",
    "sg:classifiers":[
        {
            "category":"Health Services",
            "subcategory":"Doctor",
            "type":"Services"
        }
    ],
    "sg:postcode":"94115",
    "sg:province":"CA",
    "wof:name":"Hootan Roozrokh, MD",
    "wof:placetype":"venue"
},
  "geometry": {"coordinates":[-122.440168,37.783295],"type":"Point"}
}