{
  "type": "Feature",
  "properties": {
    "iso:country":"US",
    "sg:address":"123 N H St",
    "sg:city":"Lompoc",
    "sg:classifiers":[
        {
            "category":"Retail",
            "subcategory":"Laundry & Dry Cleaning",
            "type":"Services"
        }
    ],
    "sg:phone":"+1 805 736 4614",
    "sg:postcode":"93436",
    "sg:province":"CA",
    "sg:tags":[
        "cleaners"
    ],
    "wof:name":"Stillmans Modern Cleaners",
    "wof:placetype":"venue"
},
  "geometry": {"coordinates":[-120.458033,34.640387],"type":"Point"}
}