{
  "type": "Feature",
  "properties": {
    "addr:full":"5300 N Figueroa St Los Angeles CA 90042",
    "addr:housenumber":"5300",
    "addr:postcode":"90042",
    "addr:street":"N Figueroa St",
    "iso:country":"US",
    "sg:address":"5300 N Figueroa St",
    "sg:city":"Los Angeles",
    "sg:classifiers":[
        {
            "category":"Shopping",
            "subcategory":"Gifts & Souvenirs",
            "type":"Retail Goods"
        }
    ],
    "sg:phone":"+1 323 257 9527",
    "sg:postcode":"90042",
    "sg:province":"CA",
    "sg:tags":[
        "shop"
    ],
    "wof:name":"K C Party Store",
    "wof:placetype":"venue"
},
  "geometry": {"coordinates":[-118.198178,34.106938],"type":"Point"}
}