{
  "type": "Feature",
  "properties": {
    "addr:full":"5954 Lankershim Blvd North Hollywood CA 91601",
    "addr:housenumber":"5954",
    "addr:postcode":"91601",
    "addr:street":"Lankershim Blvd",
    "iso:country":"US",
    "sg:address":"5954 Lankershim Blvd",
    "sg:city":"North Hollywood",
    "sg:classifiers":[
        {
            "category":"Restaurant",
            "type":"Food & Drink"
        }
    ],
    "sg:phone":"+1 818 985 9060",
    "sg:postcode":"91601",
    "sg:province":"CA",
    "wof:name":"El Taco Loco",
    "wof:placetype":"venue"
},
  "geometry": {"coordinates":[-118.383003,34.179199],"type":"Point"}
}