{
  "type": "Feature",
  "properties": {
    "addr:full":"395 Broadway St El Centro CA 92243",
    "addr:housenumber":"395",
    "addr:postcode":"92243",
    "addr:street":"Broadway St",
    "iso:country":"US",
    "sg:address":"395 Broadway St",
    "sg:city":"El Centro",
    "sg:classifiers":[
        {
            "category":"Organizations",
            "subcategory":"Non-profit Organization",
            "type":"Services"
        }
    ],
    "sg:phone":"+1 760 352 8888",
    "sg:postcode":"92243",
    "sg:province":"CA",
    "sg:tags":[
        "information",
        "alcoholism",
        "treatment"
    ],
    "wof:name":"Sober Roads",
    "wof:placetype":"venue"
},
  "geometry": {"coordinates":[-115.54894400000001,32.793778],"type":"Point"}
}