{
  "type": "Feature",
  "properties": {
    "iso:country":"US",
    "sg:address":"1611 S Hope St",
    "sg:city":"Los Angeles",
    "sg:classifiers":[
        {
            "category":"Wholesale",
            "subcategory":"Apparel",
            "type":"Manufacturing & Wholesale Goods"
        }
    ],
    "sg:phone":"+1 213 744 1302",
    "sg:postcode":"90015",
    "sg:province":"CA",
    "sg:tags":[
        "lingerie"
    ],
    "wof:name":"Lucy B Inc",
    "wof:placetype":"venue"
},
  "geometry": {"coordinates":[-118.268086,34.035854],"type":"Point"}
}