{
  "type": "Feature",
  "properties": {
    "addr:full":"4236 S Mooney Blvd Visalia CA 93277",
    "addr:housenumber":"4236",
    "addr:postcode":"93277",
    "addr:street":"S Mooney Blvd",
    "iso:country":"US",
    "sg:address":"4236 S Mooney Blvd",
    "sg:city":"Visalia",
    "sg:phone":"+1 559 636 6353",
    "sg:postcode":"93277",
    "sg:province":"CA",
    "sg:website":"http://www.geeksquad.com",
    "wof:name":"Geek Squad",
    "wof:placetype":"venue"
},
  "geometry": {"coordinates":[-119.313532,36.291985],"type":"Point"}
}