{
  "type": "Feature",
  "properties": {
    "iso:country":"US",
    "sg:address":"8360 Paradise Valley Rd",
    "sg:city":"Spring Valley",
    "sg:classifiers":[
        {
            "category":"Retail",
            "subcategory":"Veterinary Services",
            "type":"Services"
        }
    ],
    "sg:phone":"+1 619 342 9454",
    "sg:postcode":"91977",
    "sg:province":"CA",
    "sg:tags":[
        "veterinarian"
    ],
    "sg:website":"www.vcaparadisevalley.com",
    "wof:name":"VCA Paradise Valley Animal Hospital",
    "wof:placetype":"venue"
},
  "geometry": {"coordinates":[-117.019065,32.697541],"type":"Point"}
}