{
  "type": "Feature",
  "properties": {
    "addr:full":"5300 Beach Blvd Ste 101 Buena Park CA 90621",
    "addr:housenumber":"5300",
    "addr:postcode":"90621",
    "addr:street":"Beach Blvd Ste 101",
    "iso:country":"US",
    "sg:address":"5300 Beach Blvd Ste 101",
    "sg:city":"Buena Park",
    "sg:classifiers":[
        {
            "category":"Banks & Credit Unions",
            "subcategory":"Bank",
            "type":"Services"
        }
    ],
    "sg:phone":"+1 714 522 2222",
    "sg:postcode":"90621",
    "sg:province":"CA",
    "sg:website":"www.centerbank.com",
    "wof:name":"Center Bank",
    "wof:placetype":"venue"
},
  "geometry": {"coordinates":[-117.995667,33.884002],"type":"Point"}
}