{
  "type": "Feature",
  "properties": {
    "iso:country":"US",
    "sg:address":"395 31st Ave",
    "sg:city":"San Francisco",
    "sg:classifiers":[
        {
            "category":"Education",
            "subcategory":"Special Training",
            "type":"Public Place"
        }
    ],
    "sg:phone":"+1 415 752 0370",
    "sg:postcode":"94121",
    "sg:province":"CA",
    "sg:tags":[
        "instruction",
        "music"
    ],
    "wof:name":"Kindermusik With Dee Dee",
    "wof:placetype":"venue"
},
  "geometry": {"coordinates":[-122.491478,37.783511],"type":"Point"}
}