{
  "type": "Feature",
  "properties": {
    "addr:full":"1090 N Allen Ave Pasadena CA 91104",
    "addr:housenumber":"1090",
    "addr:postcode":"91104",
    "addr:street":"N Allen Ave",
    "iso:country":"US",
    "sg:address":"1090 N Allen Ave",
    "sg:city":"Pasadena",
    "sg:classifiers":[
        {
            "category":"Professional",
            "type":"Services"
        }
    ],
    "sg:phone":"+1 626 791 0999",
    "sg:postcode":"91104",
    "sg:province":"CA",
    "sg:tags":[
        "caterer"
    ],
    "wof:name":"Marroosh Restaurant",
    "wof:placetype":"venue"
},
  "geometry": {"coordinates":[-118.112999,34.1647],"type":"Point"}
}