{
  "type": "Feature",
  "properties": {
    "addr:full":"12639 San Fernando Rd Sylmar CA 91342",
    "addr:housenumber":"12639",
    "addr:postcode":"91342",
    "addr:street":"San Fernando Rd",
    "iso:country":"US",
    "sg:address":"12639 San Fernando Rd",
    "sg:city":"Sylmar",
    "sg:classifiers":[
        {
            "category":"Shopping",
            "subcategory":"Gifts & Souvenirs",
            "type":"Retail Goods"
        }
    ],
    "sg:phone":"+1 818 362 4933",
    "sg:postcode":"91342",
    "sg:province":"CA",
    "wof:name":"Bearland",
    "wof:placetype":"venue"
},
  "geometry": {"coordinates":[-118.458468,34.29835],"type":"Point"}
}