{
  "type": "Feature",
  "properties": {
    "addr:full":"832 5th Ave San Diego CA 92101",
    "addr:housenumber":"832",
    "addr:postcode":"92101",
    "addr:street":"5Th Ave",
    "iso:country":"US",
    "sg:address":"832 5th Ave",
    "sg:city":"San Diego",
    "sg:classifiers":[
        {
            "category":"Banks & Credit Unions",
            "subcategory":"Investment Brokerage",
            "type":"Services"
        }
    ],
    "sg:phone":"+1 619 702 7585",
    "sg:postcode":"92101",
    "sg:province":"CA",
    "sg:tags":[
        "management"
    ],
    "wof:name":"Mrd Inc",
    "wof:placetype":"venue"
},
  "geometry": {"coordinates":[-117.160225,32.714315],"type":"Point"}
}