{
  "type": "Feature",
  "properties": {
    "iso:country":"US",
    "sg:address":"4352 Cordero Dr",
    "sg:city":"El Dorado Hills",
    "sg:classifiers":[
        {
            "category":"Building & Trades",
            "subcategory":"Construction",
            "type":"Services"
        }
    ],
    "sg:phone":"+1 916 933 6599",
    "sg:postcode":"95762",
    "sg:province":"CA",
    "sg:tags":[
        "plastering",
        "contractor"
    ],
    "wof:name":"Cornerstone Plaster",
    "wof:placetype":"venue"
},
  "geometry": {"coordinates":[-121.05457199999999,38.6896],"type":"Point"}
}