{
  "type": "Feature",
  "properties": {
    "addr:full":"444 W C St Ste 380 San Diego CA 92101",
    "addr:housenumber":"444",
    "addr:postcode":"92101",
    "addr:street":"W C St Ste 380",
    "iso:country":"US",
    "sg:address":"444 W C St Ste 380",
    "sg:city":"San Diego",
    "sg:classifiers":[
        {
            "category":"Professional",
            "subcategory":"Lawyer & Legal Services",
            "type":"Services"
        }
    ],
    "sg:phone":"+1 619 685 5300",
    "sg:postcode":"92101",
    "sg:province":"CA",
    "wof:name":"Salim Khwaja Attorney At Law",
    "wof:placetype":"venue"
},
  "geometry": {"coordinates":[-117.167,32.716702],"type":"Point"}
}