{
  "type": "Feature",
  "properties": {
    "addr:full":"1640 S Bascom Ave Campbell CA 95008",
    "addr:housenumber":"1640",
    "addr:postcode":"95008",
    "addr:street":"S Bascom Ave",
    "iso:country":"US",
    "sg:address":"1640 S Bascom Ave",
    "sg:city":"Campbell",
    "sg:classifiers":[
        {
            "category":"Restaurant",
            "type":"Food & Drink"
        }
    ],
    "sg:menulink":"http://www.allmenus.com/ca/san-jose/45723-unamas!/menu/",
    "sg:phone":"+1 408 559 4490",
    "sg:postcode":"95008",
    "sg:province":"CA",
    "sg:tags":[
        "mexican"
    ],
    "wof:name":"Unamas!",
    "wof:placetype":"venue"
},
  "geometry": {"coordinates":[-121.931583,37.293535],"type":"Point"}
}