{
  "type": "Feature",
  "properties": {
    "addr:full":"16494 Foothill Blvd Fontana CA 92335",
    "addr:housenumber":"16494",
    "addr:postcode":"92335",
    "addr:street":"Foothill Blvd",
    "iso:country":"US",
    "sg:address":"16494 Foothill Blvd",
    "sg:city":"Fontana",
    "sg:classifiers":[
        {
            "category":"Autos & Motor Vehicles",
            "subcategory":"Auto Supplies",
            "type":"Retail Goods"
        }
    ],
    "sg:phone":"+1 909 429 2858",
    "sg:postcode":"92335",
    "sg:province":"CA",
    "sg:tags":[
        "tire"
    ],
    "wof:name":"A C Tire Svc",
    "wof:placetype":"venue"
},
  "geometry": {"coordinates":[-117.44661000000001,34.106662],"type":"Point"}
}