{
  "type": "Feature",
  "properties": {
    "addr:full":"4071 39th Street San Diego CA 92105",
    "addr:housenumber":"4071",
    "addr:postcode":"92105",
    "addr:street":"39Th Street",
    "iso:country":"US",
    "sg:address":"4071 39th Street",
    "sg:city":"San Diego",
    "sg:classifiers":[
        {
            "category":"Real Estate",
            "subcategory":"Real Estate Operator",
            "type":"Services"
        }
    ],
    "sg:phone":"+1 619 546 7552",
    "sg:postcode":"92105",
    "sg:province":"CA",
    "sg:tags":[
        "apartment"
    ],
    "wof:name":"Metro Villa Apartments",
    "wof:placetype":"venue"
},
  "geometry": {"coordinates":[-117.11075099999999,32.751064],"type":"Point"}
}