{
  "type": "Feature",
  "properties": {
    "iso:country":"US",
    "sg:address":"890 Glen Annie Rd",
    "sg:city":"Goleta",
    "sg:classifiers":[
        {
            "category":"Building & Trades",
            "subcategory":"Construction",
            "type":"Services"
        }
    ],
    "sg:phone":"+1 805 968 8994",
    "sg:postcode":"93117",
    "sg:province":"CA",
    "sg:tags":[
        "contractor"
    ],
    "wof:name":"Merrill Construction",
    "wof:placetype":"venue"
},
  "geometry": {"coordinates":[-119.874925,34.444433],"type":"Point"}
}