{
  "type": "Feature",
  "properties": {
    "addr:full":"4250 Pacific Hwy San Diego CA 92110",
    "addr:housenumber":"4250",
    "addr:postcode":"92110",
    "addr:street":"Pacific Hwy",
    "iso:country":"US",
    "sg:address":"4250 Pacific Hwy",
    "sg:city":"San Diego",
    "sg:classifiers":[
        {
            "category":"Professional",
            "subcategory":"Research",
            "type":"Services"
        }
    ],
    "sg:phone":"+1 619 221 6800",
    "sg:postcode":"92110",
    "sg:province":"CA",
    "sg:tags":[
        "development",
        "marketing",
        "product"
    ],
    "sg:website":"www.titan.com",
    "wof:name":"Program Support Assoc",
    "wof:placetype":"venue"
},
  "geometry": {"coordinates":[-117.19586099999999,32.745793],"type":"Point"}
}