{
  "type": "Feature",
  "properties": {
    "addr:full":"4685 N Cedar Ave Fresno CA 93726",
    "addr:housenumber":"4685",
    "addr:postcode":"93726",
    "addr:street":"N Cedar Ave",
    "iso:country":"US",
    "sg:address":"4685 N Cedar Ave",
    "sg:city":"Fresno",
    "sg:classifiers":[
        {
            "category":"Professional",
            "subcategory":"Engineering",
            "type":"Services"
        }
    ],
    "sg:phone":"+1 559 225 3633",
    "sg:postcode":"93726",
    "sg:province":"CA",
    "sg:tags":[
        "engineer"
    ],
    "wof:name":"Wood-Wiley & Assoc",
    "wof:placetype":"venue"
},
  "geometry": {"coordinates":[-119.75429099999999,36.8016],"type":"Point"}
}