{
  "type": "Feature",
  "properties": {
    "addr:full":"9621 Canoga Ave Chatsworth CA 91311",
    "addr:housenumber":"9621",
    "addr:postcode":"91311",
    "addr:street":"Canoga Ave",
    "iso:country":"US",
    "sg:address":"9621 Canoga Ave",
    "sg:city":"Chatsworth",
    "sg:classifiers":[
        {
            "category":"Wholesale",
            "subcategory":"Machinery & Supplies",
            "type":"Manufacturing & Wholesale Goods"
        }
    ],
    "sg:phone":"+1 818 780 7600",
    "sg:postcode":"91311",
    "sg:province":"CA",
    "sg:tags":[
        "car"
    ],
    "wof:name":"Automotive Marketing Advantage",
    "wof:placetype":"venue"
},
  "geometry": {"coordinates":[-118.598895,34.245608],"type":"Point"}
}