{
  "type": "Feature",
  "properties": {
    "addr:full":"931 Hamilton Ave Menlo Park CA 94025",
    "addr:housenumber":"931",
    "addr:postcode":"94025",
    "addr:street":"Hamilton Ave",
    "iso:country":"US",
    "sg:address":"931 Hamilton Ave",
    "sg:city":"Menlo Park",
    "sg:classifiers":[
        {
            "category":"Building & Trades",
            "subcategory":"Construction",
            "type":"Services"
        }
    ],
    "sg:phone":"+1 650 838 0469",
    "sg:postcode":"94025",
    "sg:province":"CA",
    "sg:tags":[
        "contractor"
    ],
    "wof:name":"Pedestal Designs Inc",
    "wof:placetype":"venue"
},
  "geometry": {"coordinates":[-122.149237,37.479486],"type":"Point"}
}