{
  "type": "Feature",
  "properties": {
    "addr:full":"1037 W Ave N Palmdale CA 93551",
    "addr:housenumber":"1037",
    "addr:postcode":"ca 93551",
    "addr:street":"W Ave N",
    "iso:country":"US",
    "sg:address":"1037 W Ave N",
    "sg:city":"Palmdale",
    "sg:classifiers":[
        {
            "category":"Banks & Credit Unions",
            "subcategory":"Bank",
            "type":"Services"
        }
    ],
    "sg:phone":"+1 661 273 0200",
    "sg:postcode":"93551",
    "sg:province":"CA",
    "sg:tags":[
        "escrow"
    ],
    "wof:name":"Titan Escrow Corp",
    "wof:placetype":"venue"
},
  "geometry": {"coordinates":[-118.14805699999999,34.631276],"type":"Point"}
}