{
  "type": "Feature",
  "properties": {
    "addr:full":"10050 Bridge St Truckee CA 96161",
    "addr:housenumber":"10050",
    "addr:postcode":"96161",
    "addr:street":"Bridge St",
    "iso:country":"US",
    "sg:address":"10050 Bridge St",
    "sg:city":"Truckee",
    "sg:classifiers":[
        {
            "category":"Government",
            "subcategory":"Post Office",
            "type":"Public Place"
        }
    ],
    "sg:phone":"+1 530 587 7158",
    "sg:postcode":"96161",
    "sg:province":"CA",
    "wof:name":"US Post Office",
    "wof:placetype":"venue"
},
  "geometry": {"coordinates":[-120.18438999999999,39.328747],"type":"Point"}
}