{
  "type": "Feature",
  "properties": {
    "addr:full":"722 Windsong Ln Nipomo CA 93444",
    "addr:housenumber":"722",
    "addr:postcode":"93444",
    "addr:street":"Windsong Ln",
    "iso:country":"US",
    "sg:address":"722 Windsong Ln",
    "sg:city":"Nipomo",
    "sg:classifiers":[
        {
            "category":"Shopping",
            "subcategory":"Gifts & Souvenirs",
            "type":"Retail Goods"
        }
    ],
    "sg:phone":"+1 805 546 2680",
    "sg:postcode":"93444",
    "sg:province":"CA",
    "sg:tags":[
        "party",
        "supply"
    ],
    "wof:name":"Spider Bike Rentals",
    "wof:placetype":"venue"
},
  "geometry": {"coordinates":[-120.48429,35.027014],"type":"Point"}
}