{
  "type": "Feature",
  "properties": {
    "iso:country":"US",
    "sg:address":"7365 Carnelian St",
    "sg:city":"Rancho Cucamonga",
    "sg:classifiers":[
        {
            "category":"Professional",
            "subcategory":"Detective & Security Services",
            "type":"Services"
        }
    ],
    "sg:phone":"+1 909 483 0440",
    "sg:postcode":"91730",
    "sg:province":"CA",
    "sg:tags":[
        "investigator"
    ],
    "wof:name":"Garland Investigations",
    "wof:placetype":"venue"
},
  "geometry": {"coordinates":[-117.61597500000001,34.119594],"type":"Point"}
}