{
  "type": "Feature",
  "properties": {
    "addr:full":"9130 Harbour Point Dr Elk Grove CA 95758",
    "addr:housenumber":"9130",
    "addr:postcode":"95758",
    "addr:street":"Harbour Point Dr",
    "iso:country":"US",
    "sg:address":"9130 Harbour Point Dr",
    "sg:city":"Elk Grove",
    "sg:classifiers":[
        {
            "category":"Retail",
            "subcategory":"Auto Repair",
            "type":"Services"
        }
    ],
    "sg:phone":"+1 916 665 1111",
    "sg:postcode":"95758",
    "sg:province":"CA",
    "sg:tags":[
        "repairing",
        "automobile"
    ],
    "wof:name":"Laguna Creek Auto Svc",
    "wof:placetype":"venue"
},
  "geometry": {"coordinates":[-121.480666,38.426928],"type":"Point"}
}