{
  "type": "Feature",
  "properties": {
    "iso:country":"US",
    "sg:address":"4811 S Western Avenue",
    "sg:city":"Los Angeles",
    "sg:classifiers":[
        {
            "category":"Food & Beverages",
            "subcategory":"Groceries & Convenience Stores",
            "type":"Retail Goods"
        }
    ],
    "sg:phone":"+1 323 292 7954",
    "sg:postcode":"90062",
    "sg:province":"CA",
    "wof:name":"El Paso Mini Market",
    "wof:placetype":"venue"
},
  "geometry": {"coordinates":[-118.308795,33.999615],"type":"Point"}
}