{
  "type": "Feature",
  "properties": {
    "iso:country":"US",
    "sg:address":"27013 Langside Ave",
    "sg:city":"Canyon Country",
    "sg:classifiers":[
        {
            "category":"Wholesale",
            "subcategory":"Medical Equipment & Supplies",
            "type":"Manufacturing & Wholesale Goods"
        }
    ],
    "sg:phone":"+1 661 424 0952",
    "sg:postcode":"91351",
    "sg:province":"CA",
    "sg:tags":[
        "physician",
        "surgeon"
    ],
    "wof:name":"Primecare Medical Supply",
    "wof:placetype":"venue"
},
  "geometry": {"coordinates":[-118.484978,34.423967],"type":"Point"}
}