{
  "type": "Feature",
  "properties": {
    "iso:country":"US",
    "sg:address":"1111 Mateo Street",
    "sg:city":"Los Angeles",
    "sg:classifiers":[
        {
            "category":"Bakery",
            "type":"Food & Drink"
        }
    ],
    "sg:phone":"+1 213 627 9860",
    "sg:postcode":"90021",
    "sg:province":"CA",
    "sg:website":"www.pegasusfoodsinc.com",
    "wof:name":"Pegasus Foods",
    "wof:placetype":"venue"
},
  "geometry": {"coordinates":[-118.23209900000001,34.030232],"type":"Point"}
}