{
  "type": "Feature",
  "properties": {
    "addr:full":"5034 W Wooley Rd Oxnard CA 93035",
    "addr:housenumber":"5034",
    "addr:postcode":"93035",
    "addr:street":"W Wooley Rd",
    "iso:country":"US",
    "sg:address":"5034 W Wooley Rd",
    "sg:city":"Oxnard",
    "sg:classifiers":[
        {
            "category":"Professional",
            "subcategory":"Engineering",
            "type":"Services"
        }
    ],
    "sg:phone":"+1 805 984 6399",
    "sg:postcode":"93035",
    "sg:province":"CA",
    "sg:tags":[
        "engineer"
    ],
    "wof:name":"Associated Civil & Structural",
    "wof:placetype":"venue"
},
  "geometry": {"coordinates":[-119.24203799999999,34.189925],"type":"Point"}
}