{
  "type": "Feature",
  "properties": {
    "addr:full":"19717 Spruce St Castro Valley CA 94546",
    "addr:housenumber":"19717",
    "addr:postcode":"94546",
    "addr:street":"Spruce St",
    "iso:country":"US",
    "sg:address":"19717 Spruce St",
    "sg:city":"Castro Valley",
    "sg:classifiers":[
        {
            "category":"Building & Trades",
            "subcategory":"Construction",
            "type":"Services"
        }
    ],
    "sg:phone":"+1 510 727 0547",
    "sg:postcode":"94546",
    "sg:province":"CA",
    "sg:tags":[
        "painter"
    ],
    "wof:name":"All Star Painting Co",
    "wof:placetype":"venue"
},
  "geometry": {"coordinates":[-122.06500200000001,37.700802],"type":"Point"}
}