{
  "type": "Feature",
  "properties": {
    "addr:full":"8048 Sheehan Way Antelope CA 95843",
    "addr:housenumber":"8048",
    "addr:postcode":"95843",
    "addr:street":"Sheehan Way",
    "iso:country":"US",
    "sg:address":"8048 Sheehan Way",
    "sg:city":"Antelope",
    "sg:classifiers":[
        {
            "category":"Professional",
            "subcategory":"Computer Services",
            "type":"Services"
        }
    ],
    "sg:phone":"+1 916 488 2591",
    "sg:postcode":"95843",
    "sg:province":"CA",
    "sg:tags":[
        "repair"
    ],
    "wof:name":"Robertson's Computer Svc",
    "wof:placetype":"venue"
},
  "geometry": {"coordinates":[-121.383573,38.715873],"type":"Point"}
}