{
  "type": "Feature",
  "properties": {
    "addr:full":"11621 Range View Rd Mira Loma CA 91752",
    "addr:housenumber":"11621",
    "addr:postcode":"91752",
    "addr:street":"Range View Rd",
    "iso:country":"US",
    "sg:address":"11621 Range View Rd",
    "sg:city":"Mira Loma",
    "sg:classifiers":[
        {
            "category":"Food & Beverages",
            "subcategory":"Specialty",
            "type":"Retail Goods"
        }
    ],
    "sg:phone":"+1 951 681 5650",
    "sg:postcode":"91752",
    "sg:province":"CA",
    "sg:tags":[
        "herb"
    ],
    "wof:name":"Herbalife Distributor",
    "wof:placetype":"venue"
},
  "geometry": {"coordinates":[-117.536123,33.97758],"type":"Point"}
}