{
  "type": "Feature",
  "properties": {
    "iso:country":"US",
    "sg:address":"1222 C St",
    "sg:city":"Sacramento",
    "sg:classifiers":[
        {
            "category":"Building & Trades",
            "subcategory":"Plumbing",
            "type":"Services"
        }
    ],
    "sg:phone":"+1 916 448 1760",
    "sg:postcode":"95814",
    "sg:province":"CA",
    "sg:tags":[
        "conditioning",
        "air",
        "system",
        "contractor"
    ],
    "wof:name":"Action HVAC",
    "wof:placetype":"venue"
},
  "geometry": {"coordinates":[-121.48618399999999,38.586856],"type":"Point"}
}