{
  "type": "Feature",
  "properties": {
    "iso:country":"US",
    "sg:address":"2805 Abbot Kinney Blvd",
    "sg:city":"Venice",
    "sg:classifiers":[
        {
            "category":"Restaurant",
            "type":"Food & Drink"
        }
    ],
    "sg:phone":"+1 310 306 1500",
    "sg:postcode":"90291",
    "sg:province":"CA",
    "wof:name":"Taste Of India",
    "wof:placetype":"venue"
},
  "geometry": {"coordinates":[-118.45252499999999,33.988504],"type":"Point"}
}