{
  "type": "Feature",
  "properties": {
    "iso:country":"US",
    "sg:address":"3031 Willow Bend Dr",
    "sg:city":"Chico",
    "sg:classifiers":[
        {
            "category":"Farming",
            "subcategory":"Farm",
            "type":"Manufacturing & Wholesale Goods"
        }
    ],
    "sg:phone":"+1 530 342 9108",
    "sg:postcode":"95973",
    "sg:province":"CA",
    "sg:tags":[
        "crop",
        "general"
    ],
    "wof:name":"Tct Enterprises",
    "wof:placetype":"venue"
},
  "geometry": {"coordinates":[-121.880938,39.760385],"type":"Point"}
}