{
  "type": "Feature",
  "properties": {
    "iso:country":"US",
    "sg:address":"201 Wilshire Blvd",
    "sg:city":"Santa Monica",
    "sg:classifiers":[
        {
            "category":"Communications",
            "subcategory":"Film & Video Production",
            "type":"Services"
        }
    ],
    "sg:phone":"+1 310 826 1026",
    "sg:postcode":"90401",
    "sg:province":"CA",
    "sg:tags":[
        "motion",
        "picture",
        "studio",
        "producer"
    ],
    "wof:name":"Unity Pictures",
    "wof:placetype":"venue"
},
  "geometry": {"coordinates":[-118.499234,34.018353],"type":"Point"}
}