{
  "type": "Feature",
  "properties": {
    "addr:full":"30993 Huntwood Ave Hayward CA 94544",
    "addr:postcode":"30993;94544",
    "addr:street":"Huntwood Ave",
    "iso:country":"US",
    "sg:address":"30993 Huntwood Ave",
    "sg:city":"Hayward",
    "sg:classifiers":[
        {
            "category":"Manufacturing",
            "subcategory":"Tools & Machinery",
            "type":"Manufacturing & Wholesale Goods"
        }
    ],
    "sg:phone":"+1 510 471 4470",
    "sg:postcode":"94544",
    "sg:province":"CA",
    "sg:tags":[
        "cylinder"
    ],
    "sg:website":"www.airconcepts.net",
    "wof:name":"Air Concepts & Controls",
    "wof:placetype":"venue"
},
  "geometry": {"coordinates":[-122.054922,37.616797],"type":"Point"}
}