{
  "type": "Feature",
  "properties": {
    "addr:full":"401 Belle Ave Bakersfield CA 93308",
    "addr:housenumber":"401",
    "addr:postcode":"93308",
    "addr:street":"Belle Ave",
    "iso:country":"US",
    "sg:address":"401 Belle Ave",
    "sg:city":"Bakersfield",
    "sg:classifiers":[
        {
            "category":"Professional",
            "subcategory":"Art Services",
            "type":"Services"
        }
    ],
    "sg:phone":"+1 661 387 0868",
    "sg:postcode":"93308",
    "sg:province":"CA",
    "sg:tags":[
        "graphic",
        "designer"
    ],
    "wof:name":"Lerma New Media",
    "wof:placetype":"venue"
},
  "geometry": {"coordinates":[-119.029985,35.410472],"type":"Point"}
}