{
  "type": "Feature",
  "properties": {
    "iso:country":"US",
    "sg:address":"2110 Artesia Blvd Ste 808",
    "sg:city":"Redondo Beach",
    "sg:classifiers":[
        {
            "category":"Building & Trades",
            "subcategory":"Plumbing",
            "type":"Services"
        }
    ],
    "sg:phone":"+1 310 947 6267",
    "sg:postcode":"90278",
    "sg:province":"CA",
    "sg:website":"www.plumberredondobeach.com",
    "wof:name":"Wc Plumbing Inc.",
    "wof:placetype":"venue"
},
  "geometry": {"coordinates":[-118.373852,33.872521],"type":"Point"}
}