{
  "type": "Feature",
  "properties": {
    "addr:full":"5451 La Palma Ave La Palma CA 90623",
    "addr:housenumber":"5451",
    "addr:postcode":"90623",
    "addr:street":"La Palma Ave",
    "iso:country":"US",
    "sg:address":"5451 La Palma Ave",
    "sg:city":"La Palma",
    "sg:classifiers":[
        {
            "category":"Health Services",
            "subcategory":"Doctor",
            "type":"Services"
        }
    ],
    "sg:phone":"+1 714 523 9493",
    "sg:postcode":"90623",
    "sg:province":"CA",
    "wof:name":"Alamitos Dermatological Medical Clinic Inc",
    "wof:placetype":"venue"
},
  "geometry": {"coordinates":[-118.03800200000001,33.846401],"type":"Point"}
}