{
  "type": "Feature",
  "properties": {
    "iso:country":"US",
    "sg:address":"3427 Sequoia Dr",
    "sg:city":"San Luis Obispo",
    "sg:classifiers":[
        {
            "category":"Health Services",
            "subcategory":"Health Practitioner",
            "type":"Services"
        }
    ],
    "sg:phone":"+1 805 546 0442",
    "sg:postcode":"93401",
    "sg:province":"CA",
    "sg:tags":[
        "pathologist",
        "speech"
    ],
    "wof:name":"Mary Kleeman",
    "wof:placetype":"venue"
},
  "geometry": {"coordinates":[-120.631469,35.264433],"type":"Point"}
}