{
  "type": "Feature",
  "properties": {
    "addr:full":"1501 Herndon Rd Ceres CA 95307",
    "addr:housenumber":"1501",
    "addr:postcode":"95307",
    "addr:street":"Herndon Rd",
    "iso:country":"US",
    "sg:address":"1501 Herndon Rd",
    "sg:city":"Ceres",
    "sg:classifiers":[
        {
            "category":"Autos & Motor Vehicles",
            "subcategory":"Fuel & Gas Station",
            "type":"Retail Goods"
        }
    ],
    "sg:phone":"+1 209 537 0131",
    "sg:postcode":"95307",
    "sg:province":"CA",
    "sg:tags":[
        "oil"
    ],
    "wof:name":"Chevron Station Inc",
    "wof:placetype":"venue"
},
  "geometry": {"coordinates":[-120.973828,37.606899],"type":"Point"}
}