{
  "type": "Feature",
  "properties": {
    "addr:full":"4816 Country Hills Dr Antioch CA 94531",
    "addr:housenumber":"4816",
    "addr:postcode":"ca 94531",
    "addr:street":"Country Hills Dr",
    "iso:country":"US",
    "sg:address":"4816 Country Hills Dr",
    "sg:city":"Antioch",
    "sg:classifiers":[
        {
            "category":"Food & Beverages",
            "subcategory":"Specialty",
            "type":"Retail Goods"
        },
        {
            "category":"Food & Beverages",
            "subcategory":"Groceries & Convenience Stores",
            "type":"Retail Goods"
        }
    ],
    "sg:phone":"+1 925 634 6412",
    "sg:postcode":"94531",
    "sg:province":"CA",
    "sg:tags":[
        "grocers-specialty"
    ],
    "wof:name":"Los Mexicanos Market",
    "wof:placetype":"venue"
},
  "geometry": {"coordinates":[-121.767157,37.966808],"type":"Point"}
}