{
  "type": "Feature",
  "properties": {
    "addr:full":"4065 Nelson Ave Concord CA 94520",
    "addr:housenumber":"4065",
    "addr:postcode":"94520",
    "addr:street":"Nelson Ave",
    "iso:country":"US",
    "sg:address":"4065 Nelson Ave",
    "sg:city":"Concord",
    "sg:classifiers":[
        {
            "category":"Arena",
            "subcategory":"Indoor Arena",
            "type":"Entertainment"
        }
    ],
    "sg:phone":"+1 925 689 4696",
    "sg:postcode":"94520",
    "sg:province":"CA",
    "sg:tags":[
        "bingo",
        "hall"
    ],
    "sg:website":"http://www.bdbingo.org",
    "wof:name":"Blue Devils Bingo Hall",
    "wof:placetype":"venue"
},
  "geometry": {"coordinates":[-122.04395,38.009304],"type":"Point"}
}