{
  "type": "Feature",
  "properties": {
    "iso:country":"US",
    "sg:address":"95 Linden St",
    "sg:city":"Oakland",
    "sg:classifiers":[
        {
            "category":"Building & Trades",
            "subcategory":"Construction",
            "type":"Services"
        }
    ],
    "sg:phone":"+1 510 444 4725",
    "sg:postcode":"94607",
    "sg:province":"CA",
    "sg:tags":[
        "contractor"
    ],
    "wof:name":"B N Builders Inc",
    "wof:placetype":"venue"
},
  "geometry": {"coordinates":[-122.28721,37.800157],"type":"Point"}
}