{
  "type": "Feature",
  "properties": {
    "addr:full":"523 International Blvd Oakland CA 94606",
    "addr:housenumber":"523",
    "addr:postcode":"94606",
    "addr:street":"International Blvd",
    "iso:country":"US",
    "sg:address":"523 International Blvd",
    "sg:city":"Oakland",
    "sg:classifiers":[
        {
            "category":"Professional",
            "type":"Services"
        }
    ],
    "sg:phone":"+1 510 836 1955",
    "sg:postcode":"94606",
    "sg:province":"CA",
    "sg:tags":[
        "service/non-profit",
        "community"
    ],
    "wof:name":"Intertribal Friendship House",
    "wof:placetype":"venue"
},
  "geometry": {"coordinates":[-122.25371800000001,37.795182],"type":"Point"}
}