{
  "type": "Feature",
  "properties": {
    "addr:city":"Oakland",
    "addr:full":"523 International Blvd Oakland, Ca 94606-2909",
    "addr:house_number":"523",
    "addr:housenumber":"523",
    "addr:phone":"+1 510-836-1955",
    "addr:postcode":"94606-2909",
    "addr:road":"International Blvd",
    "addr:state":"CA",
    "addr:street":"International Blvd",
    "iso:country":"US",
    "sg:address":"523 International Blvd",
    "sg:city":"Oakland",
    "sg:classifiers":[
        {
            "category":"Professional",
            "type":"Services"
        }
    ],
    "sg:phone":"+1 510 836 1955",
    "sg:postcode":"94606",
    "sg:province":"CA",
    "sg:tags":[
        "service/non-profit",
        "community"
    ],
    "wof:airports":[
        102527513,
        102531041,
        102532543
    ],
    "wof:name":"Intertribal Friendship House",
    "wof:placetype":"venue"
},
  "geometry": {"coordinates":[-122.25381,37.79562],"type":"Point"}
}