{
  "type": "Feature",
  "properties": {
    "iso:country":"US",
    "sg:address":"1866 Laurinda Dr",
    "sg:city":"San Jose",
    "sg:classifiers":[
        {
            "category":"Building & Trades",
            "subcategory":"Construction",
            "type":"Services"
        }
    ],
    "sg:phone":"+1 408 266 3110",
    "sg:postcode":"95124",
    "sg:province":"CA",
    "sg:tags":[
        "contractor"
    ],
    "wof:name":"Van Go Tile",
    "wof:placetype":"venue"
},
  "geometry": {"coordinates":[-121.922487,37.247012],"type":"Point"}
}