{
  "type": "Feature",
  "properties": {
    "iso:country":"US",
    "sg:address":"1721 Artesia Blvd",
    "sg:city":"Manhattan Beach",
    "sg:classifiers":[
        {
            "category":"Shopping",
            "subcategory":"Bicycles & Sporting Goods",
            "type":"Retail Goods"
        }
    ],
    "sg:phone":"+1 310 376 3940",
    "sg:postcode":"90266",
    "sg:province":"CA",
    "wof:name":"Dream Seeker",
    "wof:placetype":"venue"
},
  "geometry": {"coordinates":[-118.38234199999999,33.873022],"type":"Point"}
}