{
  "type": "Feature",
  "properties": {
    "addr:full":"1439 S Herbert Ave Los Angeles CA 90023",
    "addr:housenumber":"1439",
    "addr:postcode":"90023",
    "addr:street":"S Herbert Ave",
    "iso:country":"US",
    "sg:address":"1439 S Herbert Ave",
    "sg:city":"Los Angeles",
    "sg:classifiers":[
        {
            "category":"Manufacturing",
            "subcategory":"Apparel",
            "type":"Manufacturing & Wholesale Goods"
        }
    ],
    "sg:phone":"+1 323 980 1400",
    "sg:postcode":"90023",
    "sg:province":"CA",
    "wof:name":"Chere Amie Inc",
    "wof:placetype":"venue"
},
  "geometry": {"coordinates":[-118.183781,34.014143],"type":"Point"}
}