{
  "type": "Feature",
  "properties": {
    "iso:country":"US",
    "sg:address":"12660 Old Campo Rd",
    "sg:city":"Spring Valley",
    "sg:classifiers":[
        {
            "category":"Building & Trades",
            "subcategory":"Construction",
            "type":"Services"
        }
    ],
    "sg:phone":"+1 619 660 1115",
    "sg:postcode":"91978",
    "sg:province":"CA",
    "sg:tags":[
        "contractor"
    ],
    "wof:name":"Noel Novack Construction",
    "wof:placetype":"venue"
},
  "geometry": {"coordinates":[-116.91839299999999,32.72828],"type":"Point"}
}