{
  "type": "Feature",
  "properties": {
    "addr:full":"7038 Village Pkwy Dublin CA 94568",
    "addr:housenumber":"7038",
    "addr:postcode":"94568",
    "addr:street":"Village Pkwy",
    "iso:country":"US",
    "sg:address":"7038 Village Pkwy",
    "sg:city":"Dublin",
    "sg:classifiers":[
        {
            "category":"Retail",
            "subcategory":"Repair Shop",
            "type":"Services"
        }
    ],
    "sg:phone":"+1 925 829 4777",
    "sg:postcode":"94568",
    "sg:province":"CA",
    "sg:tags":[
        "picture",
        "framing",
        "merchandise"
    ],
    "sg:website":"http://www.framecompany.com",
    "wof:name":"Frame Company & Art Gallery The",
    "wof:placetype":"venue"
},
  "geometry": {"coordinates":[-121.925586,37.708322],"type":"Point"}
}