{
  "type": "Feature",
  "properties": {
    "addr:full":"4250 Pacific Hwy Suite 111 San Diego CA 92110",
    "addr:housenumber":"4250",
    "addr:postcode":"92110",
    "addr:street":"Pacific Hwy Suite 111",
    "iso:country":"US",
    "sg:address":"4250 Pacific Hwy Suite 111",
    "sg:city":"San Diego",
    "sg:classifiers":[
        {
            "category":"Wholesale",
            "subcategory":"Computers",
            "type":"Manufacturing & Wholesale Goods"
        }
    ],
    "sg:phone":"+1 619 321 6000",
    "sg:postcode":"92110",
    "sg:province":"CA",
    "wof:name":"Comglobal Systems",
    "wof:placetype":"venue"
},
  "geometry": {"coordinates":[-117.197333,32.746784],"type":"Point"}
}