{
  "type": "Feature",
  "properties": {
    "addr:full":"5968 S Land Park Dr Sacramento CA 95822",
    "addr:housenumber":"5968",
    "addr:postcode":"95822",
    "addr:street":"S Land Park Dr",
    "iso:country":"US",
    "sg:address":"5968 S Land Park Dr",
    "sg:city":"Sacramento",
    "sg:classifiers":[
        {
            "category":"Shopping",
            "subcategory":"Hobbies, Toys, & Games",
            "type":"Retail Goods"
        }
    ],
    "sg:phone":"+1 916 391 8750",
    "sg:postcode":"95822",
    "sg:province":"CA",
    "sg:tags":[
        "sport",
        "card",
        "memorabilia"
    ],
    "wof:name":"D & P Cards",
    "wof:placetype":"venue"
},
  "geometry": {"coordinates":[-121.512821,38.518684],"type":"Point"}
}