{
  "type": "Feature",
  "properties": {
    "iso:country":"US",
    "sg:address":"680 Sonoma Mountain Pkwy",
    "sg:city":"Petaluma",
    "sg:classifiers":[
        {
            "category":"Social Services",
            "subcategory":"Job Training",
            "type":"Services"
        }
    ],
    "sg:phone":"+1 707 778 2440",
    "sg:postcode":"94954",
    "sg:province":"CA",
    "sg:tags":[
        "rehab",
        "government"
    ],
    "wof:name":"Job Service",
    "wof:placetype":"venue"
},
  "geometry": {"coordinates":[-122.635685,38.266012],"type":"Point"}
}