{
  "type": "Feature",
  "properties": {
    "iso:country":"US",
    "sg:address":"11445 Commercial Pkwy",
    "sg:city":"Castroville",
    "sg:classifiers":[
        {
            "category":"Organizations",
            "subcategory":"Labor Organization",
            "type":"Services"
        }
    ],
    "sg:phone":"+1 831 633 6312",
    "sg:postcode":"95012",
    "sg:province":"CA",
    "wof:name":"MCBIDS Plan Room",
    "wof:placetype":"venue"
},
  "geometry": {"coordinates":[-121.738605,36.757524],"type":"Point"}
}