{
  "type": "Feature",
  "properties": {
    "addr:full":"1651 Albany Ave Chula Vista CA 91911",
    "addr:housenumber":"1651",
    "addr:postcode":"91911",
    "addr:street":"Albany Ave",
    "iso:country":"US",
    "sg:address":"1651 Albany Ave",
    "sg:city":"Chula Vista",
    "sg:classifiers":[
        {
            "category":"Education",
            "subcategory":"School",
            "type":"Public Place"
        }
    ],
    "sg:phone":"+1 619 425 4311",
    "sg:postcode":"91911",
    "sg:province":"CA",
    "sg:tags":[
        "elementary"
    ],
    "sg:website":"www.cvesd.k12.ca.us",
    "wof:name":"Otay Elementary School",
    "wof:placetype":"venue"
},
  "geometry": {"coordinates":[-117.057999,32.596001],"type":"Point"}
}