{
  "type": "Feature",
  "properties": {
    "addr:full":"2223 W 111th St Inglewood CA 90303",
    "addr:housenumber":"2223",
    "addr:postcode":"90303",
    "addr:street":"W 111Th St",
    "iso:country":"US",
    "sg:address":"2223 W 111th St",
    "sg:city":"Inglewood",
    "sg:classifiers":[
        {
            "category":"Manufacturing",
            "subcategory":"Printing",
            "type":"Manufacturing & Wholesale Goods"
        }
    ],
    "sg:phone":"+1 323 754 3327",
    "sg:postcode":"90303",
    "sg:province":"CA",
    "sg:tags":[
        "publishing"
    ],
    "wof:name":"Urban Street Management",
    "wof:placetype":"venue"
},
  "geometry": {"coordinates":[-118.31809800000001,33.933564],"type":"Point"}
}