{
  "type": "Feature",
  "properties": {
    "iso:country":"US",
    "sg:address":"1919 S Academy Ave",
    "sg:city":"Sanger",
    "sg:classifiers":[
        {
            "category":"Organizations",
            "subcategory":"Religious Organization",
            "type":"Services"
        }
    ],
    "sg:phone":"+1 559 876 2213",
    "sg:postcode":"93657",
    "sg:province":"CA",
    "sg:tags":[
        "church"
    ],
    "wof:name":"Tabernacle Of Praise",
    "wof:placetype":"venue"
},
  "geometry": {"coordinates":[-119.55421,36.693319],"type":"Point"}
}