{
  "type": "Feature",
  "properties": {
    "addr:full":"15015 E 14th St San Leandro CA 94578",
    "addr:housenumber":"15015",
    "addr:postcode":"94578",
    "addr:street":"E 14Th St",
    "iso:country":"US",
    "sg:address":"15015 E 14th St",
    "sg:city":"San Leandro",
    "sg:classifiers":[
        {
            "category":"Restaurant",
            "type":"Food & Drink"
        }
    ],
    "sg:menulink":"http://www.allmenus.com/ca/hayward/54350-la-bella-italia/menu/",
    "sg:phone":"+1 510 278 5899",
    "sg:postcode":"94578",
    "sg:province":"CA",
    "sg:tags":[
        "italian"
    ],
    "wof:name":"La Bella Italia",
    "wof:placetype":"venue"
},
  "geometry": {"coordinates":[-122.12905499999999,37.705517],"type":"Point"}
}