{
  "type": "Feature",
  "properties": {
    "iso:country":"US",
    "sg:address":"438 E Katella Ave",
    "sg:city":"Orange",
    "sg:classifiers":[
        {
            "category":"Banks & Credit Unions",
            "subcategory":"Bank",
            "type":"Services"
        }
    ],
    "sg:phone":"+1 714 621 0964",
    "sg:postcode":"92867",
    "sg:province":"CA",
    "sg:tags":[
        "loan",
        "real estate"
    ],
    "wof:name":"All State Capital Mortgage",
    "wof:placetype":"venue"
},
  "geometry": {"coordinates":[-117.852325,33.809013],"type":"Point"}
}