{
  "type": "Feature",
  "properties": {
    "addr:full":"509 Elmhurst Cir Sacramento CA 95825",
    "addr:housenumber":"509",
    "addr:postcode":"95825",
    "addr:street":"Elmhurst Cir",
    "iso:country":"US",
    "sg:address":"509 Elmhurst Cir",
    "sg:city":"Sacramento",
    "sg:classifiers":[
        {
            "category":"Professional",
            "subcategory":"Art Services",
            "type":"Services"
        }
    ],
    "sg:phone":"+1 916 922 9929",
    "sg:postcode":"95825",
    "sg:province":"CA",
    "sg:tags":[
        "interior",
        "designer",
        "decorator"
    ],
    "wof:name":"Brewington Judith",
    "wof:placetype":"venue"
},
  "geometry": {"coordinates":[-121.415819,38.562672],"type":"Point"}
}