{
  "type": "Feature",
  "properties": {
    "iso:country":"US",
    "sg:address":"301 Beech St",
    "sg:city":"El Cajon",
    "sg:classifiers":[
        {
            "category":"Building & Trades",
            "subcategory":"Plumbing",
            "type":"Services"
        }
    ],
    "sg:phone":"+1 619 590 1109",
    "sg:postcode":"92020",
    "sg:province":"CA",
    "sg:tags":[
        "plumbing",
        "contractor"
    ],
    "wof:name":"J & J Plumbing Inc",
    "wof:placetype":"venue"
},
  "geometry": {"coordinates":[-116.959119,32.802605],"type":"Point"}
}