{
  "type": "Feature",
  "properties": {
    "iso:country":"US",
    "sg:address":"2814 Mariposa St",
    "sg:city":"Fresno",
    "sg:classifiers":[
        {
            "category":"Organizations",
            "subcategory":"Religious Organization",
            "type":"Services"
        }
    ],
    "sg:phone":"+1 559 485 6210",
    "sg:postcode":"93721",
    "sg:province":"CA",
    "sg:tags":[
        "church"
    ],
    "wof:name":"St John's Cathedral",
    "wof:placetype":"venue"
},
  "geometry": {"coordinates":[-119.782067,36.741271],"type":"Point"}
}