{
  "type": "Feature",
  "properties": {
    "iso:country":"US",
    "sg:address":"11135 Rush St",
    "sg:city":"South El Monte",
    "sg:classifiers":[
        {
            "category":"Wholesale",
            "subcategory":"Non-durable Goods",
            "type":"Manufacturing & Wholesale Goods"
        }
    ],
    "sg:phone":"+1 626 401 3297",
    "sg:postcode":"91733",
    "sg:province":"CA",
    "wof:name":"Eastern Falcon Corporation",
    "wof:placetype":"venue"
},
  "geometry": {"coordinates":[-118.034159,34.049497],"type":"Point"}
}