{
  "type": "Feature",
  "properties": {
    "addr:full":"592 Vallejo St San Francisco CA 94133",
    "addr:housenumber":"592",
    "addr:postcode":"94133",
    "addr:street":"Vallejo St",
    "iso:country":"US",
    "sg:address":"592 Vallejo St",
    "sg:city":"San Francisco",
    "sg:classifiers":[
        {
            "category":"Banks & Credit Unions",
            "subcategory":"Investment Brokerage",
            "type":"Services"
        }
    ],
    "sg:phone":"+1 415 982 8073",
    "sg:postcode":"94133",
    "sg:province":"CA",
    "sg:tags":[
        "advisory",
        "financial"
    ],
    "wof:name":"Hung's International Inc",
    "wof:placetype":"venue"
},
  "geometry": {"coordinates":[-122.40699499999999,37.798885],"type":"Point"}
}