{
  "type": "Feature",
  "properties": {
    "iso:country":"US",
    "sg:address":"1536 Ponderosa Ave",
    "sg:city":"Fullerton",
    "sg:classifiers":[
        {
            "category":"Building & Trades",
            "subcategory":"Construction",
            "type":"Services"
        }
    ],
    "sg:phone":"+1 714 990 5930",
    "sg:postcode":"92835",
    "sg:province":"CA",
    "sg:tags":[
        "coping",
        "plastering",
        "tiling",
        "pool",
        "swimming"
    ],
    "wof:name":"Randy's Pool Maintenance",
    "wof:placetype":"venue"
},
  "geometry": {"coordinates":[-117.898942,33.90541],"type":"Point"}
}