{
  "type": "Feature",
  "properties": {
    "iso:country":"US",
    "sg:address":"1649 Newport Ct",
    "sg:city":"Salinas",
    "sg:classifiers":[
        {
            "category":"Professional",
            "subcategory":"Business Services",
            "type":"Services"
        }
    ],
    "sg:phone":"+1 408 623 8833",
    "sg:postcode":"93906",
    "sg:province":"CA",
    "sg:tags":[
        "inspection"
    ],
    "wof:name":"Mega Test Solutions",
    "wof:placetype":"venue"
},
  "geometry": {"coordinates":[-121.620234,36.70187],"type":"Point"}
}