{
  "type": "Feature",
  "properties": {
    "addr:full":"4441 Plantation Dr Fair Oaks CA 95628",
    "addr:housenumber":"4441",
    "addr:postcode":"95628",
    "addr:street":"Plantation Dr",
    "iso:country":"US",
    "sg:address":"4441 Plantation Dr",
    "sg:city":"Fair Oaks",
    "sg:classifiers":[
        {
            "category":"Professional",
            "subcategory":"Management & Consulting",
            "type":"Services"
        }
    ],
    "sg:phone":"+1 916 965 3690",
    "sg:postcode":"95628",
    "sg:province":"CA",
    "sg:tags":[
        "consultant"
    ],
    "wof:name":"Huff Consulting",
    "wof:placetype":"venue"
},
  "geometry": {"coordinates":[-121.29283100000001,38.647231],"type":"Point"}
}