{
  "type": "Feature",
  "properties": {
    "addr:full":"2104 Eilene Dr Pleasanton CA 94588",
    "addr:housenumber":"2104",
    "addr:postcode":"94588",
    "addr:street":"Eilene Dr",
    "iso:country":"US",
    "sg:address":"2104 Eilene Dr",
    "sg:city":"Pleasanton",
    "sg:classifiers":[
        {
            "category":"Manufacturing",
            "subcategory":"Printing",
            "type":"Manufacturing & Wholesale Goods"
        }
    ],
    "sg:phone":"+1 925 485 1259",
    "sg:postcode":"94588",
    "sg:province":"CA",
    "sg:tags":[
        "publisher",
        "software"
    ],
    "wof:name":"KAIO Systems Software",
    "wof:placetype":"venue"
},
  "geometry": {"coordinates":[-121.870002,37.685996],"type":"Point"}
}