{
  "type": "Feature",
  "properties": {
    "iso:country":"US",
    "sg:address":"1420 E Plaza Blvd Ste B5",
    "sg:city":"National City",
    "sg:classifiers":[
        {
            "category":"Shopping",
            "subcategory":"Party Supplies",
            "type":"Retail Goods"
        }
    ],
    "sg:phone":"+1 619 474 5115",
    "sg:postcode":"91950",
    "sg:province":"CA",
    "wof:name":"Ico Party Supplies Rentals & Flowers",
    "wof:placetype":"venue"
},
  "geometry": {"coordinates":[-117.09200300000001,32.6768],"type":"Point"}
}