{
  "type": "Feature",
  "properties": {
    "iso:country":"US",
    "sg:address":"2719 Penitencia Creek Rd",
    "sg:city":"San Jose",
    "sg:classifiers":[
        {
            "category":"Professional",
            "subcategory":"Accounting & Tax Preparation",
            "type":"Services"
        }
    ],
    "sg:phone":"+1 408 422 9007",
    "sg:postcode":"95132",
    "sg:province":"CA",
    "sg:tags":[
        "return",
        "filing"
    ],
    "wof:name":"H P Financial Svc",
    "wof:placetype":"venue"
},
  "geometry": {"coordinates":[-121.852802,37.385686],"type":"Point"}
}