{
  "type": "Feature",
  "properties": {
    "iso:country":"US",
    "sg:address":"3602 N Blackstone Ave",
    "sg:city":"Fresno",
    "sg:classifiers":[
        {
            "category":"Shopping",
            "subcategory":"Gifts & Souvenirs",
            "type":"Retail Goods"
        }
    ],
    "sg:phone":"+1 559 227 1755",
    "sg:postcode":"93726",
    "sg:province":"CA",
    "sg:tags":[
        "shop"
    ],
    "wof:name":"Small World Gifts",
    "wof:placetype":"venue"
},
  "geometry": {"coordinates":[-119.79045499999999,36.784002],"type":"Point"}
}