{
  "type": "Feature",
  "properties": {
    "iso:country":"US",
    "sg:address":"23241 Ventura Blvd",
    "sg:city":"Woodland Hills",
    "sg:classifiers":[
        {
            "category":"Insurance",
            "subcategory":"Insurance Agent",
            "type":"Services"
        }
    ],
    "sg:phone":"+1 818 225 7022",
    "sg:postcode":"91364",
    "sg:province":"CA",
    "wof:name":"Larry Patrick Ins Agcy",
    "wof:placetype":"venue"
},
  "geometry": {"coordinates":[-118.632514,34.161765],"type":"Point"}
}