{
  "type": "Feature",
  "properties": {
    "addr:full":"16462 Gothard St Huntington Beach CA 92647",
    "addr:housenumber":"16462",
    "addr:postcode":"92647",
    "addr:street":"Gothard St",
    "iso:country":"US",
    "sg:address":"16462 Gothard St",
    "sg:city":"Huntington Beach",
    "sg:classifiers":[
        {
            "category":"Professional",
            "subcategory":"Business Services",
            "type":"Services"
        }
    ],
    "sg:phone":"+1 714 427 0596",
    "sg:postcode":"92647",
    "sg:province":"CA",
    "sg:tags":[
        "printing",
        "broker"
    ],
    "wof:name":"Parallel Printing",
    "wof:placetype":"venue"
},
  "geometry": {"coordinates":[-118.000145,33.724054],"type":"Point"}
}