{
  "type": "Feature",
  "properties": {
    "iso:country":"US",
    "sg:address":"15311 Pioneer Blvd",
    "sg:city":"Norwalk",
    "sg:classifiers":[
        {
            "category":"Organizations",
            "subcategory":"Religious Organization",
            "type":"Services"
        }
    ],
    "sg:phone":"+1 562 868 8727",
    "sg:postcode":"90650",
    "sg:province":"CA",
    "wof:name":"Corporation of President of Th",
    "wof:placetype":"venue"
},
  "geometry": {"coordinates":[-118.08247,33.892077],"type":"Point"}
}