{
  "type": "Feature",
  "properties": {
    "iso:country":"US",
    "sg:address":"1751 Torrance Blvd",
    "sg:city":"Torrance",
    "sg:classifiers":[
        {
            "category":"Professional",
            "subcategory":"Testing Lab",
            "type":"Services"
        },
        {
            "category":"Health Services",
            "subcategory":"Medical Lab",
            "type":"Services"
        }
    ],
    "sg:phone":"+1 310 533 0600",
    "sg:postcode":"90501",
    "sg:province":"CA",
    "sg:tags":[
        "laboratory",
        "dental"
    ],
    "wof:name":"Horident Inc",
    "wof:placetype":"venue"
},
  "geometry": {"coordinates":[-118.311397,33.837791],"type":"Point"}
}