{
  "type": "Feature",
  "properties": {
    "iso:country":"US",
    "sg:address":"7050 Friars Rd",
    "sg:city":"San Diego",
    "sg:classifiers":[
        {
            "category":"Professional",
            "subcategory":"Accounting & Tax Preparation",
            "type":"Services"
        }
    ],
    "sg:phone":"+1 858 499 8959",
    "sg:postcode":"92108",
    "sg:province":"CA",
    "sg:tags":[
        "accountant",
        "referral"
    ],
    "wof:name":"NFP Accounting Technologies",
    "wof:placetype":"venue"
},
  "geometry": {"coordinates":[-117.166083,32.769927],"type":"Point"}
}