{
  "type": "Feature",
  "properties": {
    "addr:full":"3107 Pico Blvd Santa Monica CA 90405",
    "addr:housenumber":"3107",
    "addr:postcode":"90405",
    "addr:street":"Pico Blvd",
    "iso:country":"US",
    "sg:address":"3107 Pico Blvd",
    "sg:city":"Santa Monica",
    "sg:classifiers":[
        {
            "category":"Professional",
            "subcategory":"Computer Services",
            "type":"Services"
        },
        {
            "category":"Shopping",
            "subcategory":"Computers & Home Electronics",
            "type":"Retail Goods"
        }
    ],
    "sg:phone":"+1 310 453 0933",
    "sg:postcode":"90405",
    "sg:province":"CA",
    "sg:tags":[
        "software",
        "programing",
        "custom"
    ],
    "sg:website":"www.rtgsoftware.com",
    "wof:name":"R T G Data Systems",
    "wof:placetype":"venue"
},
  "geometry": {"coordinates":[-118.456434,34.026358],"type":"Point"}
}