{
  "type": "Feature",
  "properties": {
    "addr:full":"19710 Ventura Blvd Woodland Hills CA 91364",
    "addr:housenumber":"19710",
    "addr:postcode":"91364",
    "addr:street":"Ventura Blvd",
    "iso:country":"US",
    "sg:address":"19710 Ventura Blvd",
    "sg:city":"Woodland Hills",
    "sg:classifiers":[
        {
            "category":"Retail",
            "subcategory":"Portrait Studio",
            "type":"Services"
        }
    ],
    "sg:phone":"+1 818 999 1179",
    "sg:postcode":"91364",
    "sg:province":"CA",
    "sg:tags":[
        "photography",
        "store"
    ],
    "sg:website":"none",
    "wof:name":"Superior Camera Repair and Exchange",
    "wof:placetype":"venue"
},
  "geometry": {"coordinates":[-118.562698,34.172563],"type":"Point"}
}