{
  "type": "Feature",
  "properties": {
    "addr:full":"720 S. Grand Ave Glendora CA 91740",
    "addr:housenumber":"720",
    "addr:postcode":"91740",
    "addr:street":"S. Grand Ave",
    "iso:country":"US",
    "sg:address":"720 S. Grand Ave",
    "sg:city":"Glendora",
    "sg:classifiers":[
        {
            "category":"Utilities",
            "subcategory":"Mobile Phone",
            "type":"Services"
        },
        {
            "category":"Shopping",
            "subcategory":"Mobile Phones",
            "type":"Retail Goods"
        },
        {
            "category":"Professional",
            "subcategory":"Computer Services",
            "type":"Services"
        }
    ],
    "sg:phone":"+1 626 759 1900",
    "sg:postcode":"91740",
    "sg:province":"CA",
    "sg:tags":[
        "supply",
        "technical",
        "communication",
        "assistance",
        "telephone",
        "wireless",
        "equipment",
        "cellular",
        "support"
    ],
    "sg:website":"http://www.glendorawireless.com",
    "wof:name":"Executive Wireless Communications",
    "wof:placetype":"venue"
},
  "geometry": {"coordinates":[-117.87258300000001,34.126379],"type":"Point"}
}