{
  "type": "Feature",
  "properties": {
    "iso:country":"US",
    "sg:address":"2716 Surrey Ave",
    "sg:city":"Modesto",
    "sg:classifiers":[
        {
            "category":"Farming",
            "subcategory":"Crops",
            "type":"Manufacturing & Wholesale Goods"
        }
    ],
    "sg:phone":"+1 209 522 9130",
    "sg:postcode":"95355",
    "sg:province":"CA",
    "sg:tags":[
        "grove",
        "nut",
        "tree"
    ],
    "wof:name":"Pete Verdegaal",
    "wof:placetype":"venue"
},
  "geometry": {"coordinates":[-120.944295,37.657012],"type":"Point"}
}