{
  "type": "Feature",
  "properties": {
    "addr:full":"1850 E 61st St Los Angeles CA 90001",
    "addr:housenumber":"1850",
    "addr:postcode":"90001",
    "addr:street":"E 61St St",
    "iso:country":"US",
    "sg:address":"1850 E 61st St",
    "sg:city":"Los Angeles",
    "sg:classifiers":[
        {
            "category":"Wholesale",
            "subcategory":"Metals & Minerals",
            "type":"Manufacturing & Wholesale Goods"
        }
    ],
    "sg:phone":"+1 310 973 9100",
    "sg:postcode":"90001",
    "sg:province":"CA",
    "sg:tags":[
        "center"
    ],
    "wof:name":"Mas Iron Company",
    "wof:placetype":"venue"
},
  "geometry": {"coordinates":[-118.239904,33.984664],"type":"Point"}
}