{
  "type": "Feature",
  "properties": {
    "addr:full":"121 W Duarte Rd Monrovia CA 91016",
    "addr:housenumber":"121",
    "addr:postcode":"91016",
    "addr:street":"W Duarte Rd",
    "iso:country":"US",
    "sg:address":"121 W Duarte Rd",
    "sg:city":"Monrovia",
    "sg:phone":"+1 626 303 3848",
    "sg:postcode":"91016",
    "sg:province":"CA",
    "wof:name":"Los Chiles Locos",
    "wof:placetype":"venue"
},
  "geometry": {"coordinates":[-118.001617,34.132191],"type":"Point"}
}