{
  "type": "Feature",
  "properties": {
    "iso:country":"US",
    "sg:address":"67 Bay Rd",
    "sg:city":"Menlo Park",
    "sg:classifiers":[
        {
            "category":"Organizations",
            "subcategory":"Religious Organization",
            "type":"Services"
        }
    ],
    "sg:phone":"+1 650 323 5550",
    "sg:postcode":"94025",
    "sg:province":"CA",
    "sg:tags":[
        "church"
    ],
    "sg:website":"www.hoc.org",
    "wof:name":"Home Of Christ",
    "wof:placetype":"venue"
},
  "geometry": {"coordinates":[-122.181892,37.476597],"type":"Point"}
}