{
  "type": "Feature",
  "properties": {
    "addr:full":"22483 Pacific Coast Hwy Malibu CA 90265",
    "addr:housenumber":"22483",
    "addr:postcode":"90265",
    "addr:street":"Pacific Coast Hwy",
    "iso:country":"US",
    "sg:address":"22483 Pacific Coast Hwy",
    "sg:city":"Malibu",
    "sg:classifiers":[
        {
            "category":"Professional",
            "subcategory":"Lawyer & Legal Services",
            "type":"Services"
        }
    ],
    "sg:phone":"+1 310 456 3024",
    "sg:postcode":"90265",
    "sg:province":"CA",
    "sg:tags":[
        "attorney"
    ],
    "wof:name":"Robert J Allan Law Office",
    "wof:placetype":"venue"
},
  "geometry": {"coordinates":[-118.664327,34.039752],"type":"Point"}
}