{
  "type": "Feature",
  "properties": {
    "iso:country":"US",
    "sg:address":"11737 Clarkman St",
    "sg:city":"Santa Fe Springs",
    "sg:classifiers":[
        {
            "category":"Building & Trades",
            "subcategory":"Plumbing",
            "type":"Services"
        }
    ],
    "sg:phone":"+1 562 863 1001",
    "sg:postcode":"90670",
    "sg:province":"CA",
    "sg:tags":[
        "plumbing",
        "contractor"
    ],
    "wof:name":"Santa Fe Plumbing Inc",
    "wof:placetype":"venue"
},
  "geometry": {"coordinates":[-118.083214,33.939012],"type":"Point"}
}