{
  "type": "Feature",
  "properties": {
    "iso:country":"US",
    "sg:address":"2379 Telegraph Avenue",
    "sg:city":"Berkeley",
    "sg:classifiers":[
        {
            "category":"Restaurant",
            "type":"Food & Drink"
        }
    ],
    "sg:phone":"+1 510 665 8000",
    "sg:postcode":"94704",
    "sg:province":"CA",
    "sg:tags":[
        "sushi",
        "bar",
        "japanese"
    ],
    "sg:website":"www.takosushi.com/",
    "wof:name":"Tako Sushi",
    "wof:placetype":"venue"
},
  "geometry": {"coordinates":[-122.25900300000001,37.867298],"type":"Point"}
}