{
  "type": "Feature",
  "properties": {
    "iso:country":"US",
    "sg:address":"1034 17th St",
    "sg:city":"Paso Robles",
    "sg:classifiers":[
        {
            "category":"Farming",
            "subcategory":"Farm",
            "type":"Manufacturing & Wholesale Goods"
        }
    ],
    "sg:phone":"+1 805 238 1029",
    "sg:postcode":"93446",
    "sg:province":"CA",
    "wof:name":"In Bio-Tec",
    "wof:placetype":"venue"
},
  "geometry": {"coordinates":[-120.687612,35.632029],"type":"Point"}
}