{
  "type": "Feature",
  "properties": {
    "iso:country":"US",
    "sg:address":"12 Golf Ave",
    "sg:city":"San Rafael",
    "sg:classifiers":[
        {
            "category":"Professional",
            "type":"Services"
        }
    ],
    "sg:phone":"+1 415 499 1112",
    "sg:postcode":"94903",
    "sg:province":"CA",
    "wof:name":"Buckmeister LLC",
    "wof:placetype":"venue"
},
  "geometry": {"coordinates":[-122.528627,37.998168],"type":"Point"}
}