{
  "type": "Feature",
  "properties": {
    "iso:country":"US",
    "sg:address":"1127 Fee Dr # B",
    "sg:city":"Sacramento",
    "sg:classifiers":[
        {
            "category":"Shopping",
            "subcategory":"Gifts & Souvenirs",
            "type":"Retail Goods"
        },
        {
            "category":"Shopping",
            "subcategory":"Discount & Variety Stores",
            "type":"Retail Goods"
        }
    ],
    "sg:phone":"+1 916 649 9593",
    "sg:postcode":"95815",
    "sg:province":"CA",
    "sg:tags":[
        "wholesale",
        "flower"
    ],
    "sg:website":"www.fss.com",
    "wof:name":"Floral Supply Syndicate",
    "wof:placetype":"venue"
},
  "geometry": {"coordinates":[-121.445999,38.600498],"type":"Point"}
}