{
  "type": "Feature",
  "properties": {
    "iso:country":"US",
    "sg:address":"912 W Kensington Rd",
    "sg:city":"Los Angeles",
    "sg:classifiers":[
        {
            "category":"Professional",
            "subcategory":"Business Services",
            "type":"Services"
        }
    ],
    "sg:phone":"+1 213 975 9220",
    "sg:postcode":"90026",
    "sg:province":"CA",
    "sg:tags":[
        "notary"
    ],
    "wof:name":"Dalshah Enterprise",
    "wof:placetype":"venue"
},
  "geometry": {"coordinates":[-118.254274,34.07308],"type":"Point"}
}