{
  "type": "Feature",
  "properties": {
    "iso:country":"US",
    "sg:address":"246 E Main St",
    "sg:city":"Stockton",
    "sg:classifiers":[
        {
            "category":"Real Estate",
            "subcategory":"Architect",
            "type":"Services"
        }
    ],
    "sg:phone":"+1 209 944 9110",
    "sg:postcode":"95202",
    "sg:province":"CA",
    "sg:website":"www.wmbarchitects.com",
    "wof:name":"Wenell Mattheis & Bowe",
    "wof:placetype":"venue"
},
  "geometry": {"coordinates":[-121.287613,37.952972],"type":"Point"}
}