{
  "type": "Feature",
  "properties": {
    "iso:country":"US",
    "sg:address":"3935 Harney St",
    "sg:city":"San Diego",
    "sg:classifiers":[
        {
            "category":"Social Services",
            "type":"Services"
        }
    ],
    "sg:phone":"+1 619 295 1918",
    "sg:postcode":"92110",
    "sg:province":"CA",
    "sg:tags":[
        "counselor",
        "marriage",
        "family"
    ],
    "wof:name":"Fran Crawford",
    "wof:placetype":"venue"
},
  "geometry": {"coordinates":[-117.195956,32.751373],"type":"Point"}
}