{
  "type": "Feature",
  "properties": {
    "addr:full":"932 Blossom Hill Rd San Jose CA 95123",
    "addr:housenumber":"932",
    "addr:postcode":"95123",
    "addr:street":"Blossom Hill Rd",
    "iso:country":"US",
    "sg:address":"932 Blossom Hill Rd",
    "sg:city":"San Jose",
    "sg:classifiers":[
        {
            "category":"Shopping",
            "subcategory":"Stationery & Office Supplies",
            "type":"Retail Goods"
        },
        {
            "category":"Wholesale",
            "subcategory":"Computers",
            "type":"Manufacturing & Wholesale Goods"
        }
    ],
    "sg:phone":"+1 408 363 8002",
    "sg:postcode":"95123",
    "sg:province":"CA",
    "sg:tags":[
        "equipment"
    ],
    "wof:name":"Office Depot",
    "wof:placetype":"venue"
},
  "geometry": {"coordinates":[-121.86199999999999,37.250401],"type":"Point"}
}