{
  "type": "Feature",
  "properties": {
    "iso:country":"US",
    "sg:address":"1638 W Capitol Ave",
    "sg:city":"West Sacramento",
    "sg:classifiers":[
        {
            "category":"Food & Beverages",
            "subcategory":"Groceries & Convenience Stores",
            "type":"Retail Goods"
        }
    ],
    "sg:phone":"+1 916 375 8919",
    "sg:postcode":"95691",
    "sg:province":"CA",
    "wof:name":"Ariana Food Mart",
    "wof:placetype":"venue"
},
  "geometry": {"coordinates":[-121.529999,38.580601],"type":"Point"}
}