{
  "type": "Feature",
  "properties": {
    "addr:full":"8071 Luxor Ave Niland CA 92257",
    "addr:postcode":"8071;92257",
    "addr:street":"Luxor Ave",
    "iso:country":"US",
    "sg:address":"8071 Luxor Ave",
    "sg:city":"Niland",
    "sg:classifiers":[
        {
            "category":"Government",
            "subcategory":"Fire Station",
            "type":"Public Place"
        }
    ],
    "sg:phone":"+1 760 359 0410",
    "sg:postcode":"92257",
    "sg:province":"CA",
    "sg:tags":[
        "department"
    ],
    "wof:name":"Niland Fire Dept",
    "wof:placetype":"venue"
},
  "geometry": {"coordinates":[-115.512745,33.238355],"type":"Point"}
}