{
  "type": "Feature",
  "properties": {
    "addr:full":"63 Powell St San Francisco CA 94102",
    "addr:housenumber":"63",
    "addr:postcode":"94102",
    "addr:street":"Powell St",
    "iso:country":"US",
    "sg:address":"63 Powell St",
    "sg:city":"San Francisco",
    "sg:classifiers":[
        {
            "category":"Restaurant",
            "type":"Food & Drink"
        }
    ],
    "sg:phone":"+1 415 982 6168",
    "sg:postcode":"94102",
    "sg:province":"CA",
    "wof:name":"Blondies Pizza",
    "wof:placetype":"venue"
},
  "geometry": {"coordinates":[-122.40785,37.784978],"type":"Point"}
}