{
  "type": "Feature",
  "properties": {
    "iso:country":"US",
    "sg:address":"1074 Kiely Blvd",
    "sg:city":"Santa Clara",
    "sg:classifiers":[
        {
            "category":"Restaurant",
            "type":"Food & Drink"
        }
    ],
    "sg:phone":"+1 408 260 2058",
    "sg:postcode":"95051",
    "sg:province":"CA",
    "sg:tags":[
        "creperies"
    ],
    "wof:name":"Spot Cafe CLOSED",
    "wof:placetype":"venue"
},
  "geometry": {"coordinates":[-121.977681,37.345891],"type":"Point"}
}