{
  "type": "Feature",
  "properties": {
    "addr:full":"3590 Placer St Redding CA 96001",
    "addr:housenumber":"3590",
    "addr:postcode":"96001",
    "addr:street":"Placer St",
    "iso:country":"US",
    "sg:address":"3590 Placer St",
    "sg:city":"Redding",
    "sg:classifiers":[
        {
            "category":"Organizations",
            "subcategory":"Religious Organization",
            "type":"Services"
        }
    ],
    "sg:phone":"+1 530 242 1589",
    "sg:postcode":"96001",
    "sg:province":"CA",
    "sg:tags":[
        "church"
    ],
    "wof:name":"First Christian Church",
    "wof:placetype":"venue"
},
  "geometry": {"coordinates":[-122.41574,40.575079],"type":"Point"}
}