{
  "type": "Feature",
  "properties": {
    "addr:full":"378 W Charter Way Stockton CA 95206",
    "addr:housenumber":"378",
    "addr:postcode":"95206",
    "addr:street":"W Charter Way",
    "iso:country":"US",
    "sg:address":"378 W Charter Way",
    "sg:city":"Stockton",
    "sg:classifiers":[
        {
            "category":"Wholesale",
            "subcategory":"Groceries",
            "type":"Manufacturing & Wholesale Goods"
        }
    ],
    "sg:phone":"+1 209 941 2758",
    "sg:postcode":"95206",
    "sg:province":"CA",
    "sg:tags":[
        "tortilla"
    ],
    "wof:name":"Aranda's Market",
    "wof:placetype":"venue"
},
  "geometry": {"coordinates":[-121.29168799999999,37.937829],"type":"Point"}
}