{
  "type": "Feature",
  "properties": {
    "addr:full":"370 N Beverly Dr Beverly Hills CA 90210",
    "addr:housenumber":"370",
    "addr:postcode":"90210",
    "addr:street":"N Beverly Dr",
    "iso:country":"US",
    "sg:address":"370 N Beverly Dr",
    "sg:city":"Beverly Hills",
    "sg:classifiers":[
        {
            "category":"Sports & Exercise",
            "subcategory":"Bicycle Rental",
            "type":"Entertainment"
        }
    ],
    "sg:phone":"+1 310 274 0461",
    "sg:postcode":"90210",
    "sg:province":"CA",
    "sg:tags":[
        "wear"
    ],
    "wof:name":"Gap the",
    "wof:placetype":"venue"
},
  "geometry": {"coordinates":[-118.402,34.069901],"type":"Point"}
}