{
  "type": "Feature",
  "properties": {
    "iso:country":"US",
    "sg:address":"22491 Rio Aliso",
    "sg:city":"Lake Forest",
    "sg:classifiers":[
        {
            "category":"Professional",
            "subcategory":"Employment Agencies",
            "type":"Services"
        }
    ],
    "sg:phone":"+1 949 215 5107",
    "sg:postcode":"92630",
    "sg:province":"CA",
    "wof:name":"Executive Career Placement",
    "wof:placetype":"venue"
},
  "geometry": {"coordinates":[-117.6743,33.636176],"type":"Point"}
}