{
  "type": "Feature",
  "properties": {
    "addr:full":"1620 Via Montemar Palos Verdes Peninsula CA 90274",
    "addr:housenumber":"1620",
    "addr:postcode":"verdes;90274",
    "addr:street":"Via Montemar",
    "iso:country":"US",
    "sg:address":"1620 Via Montemar",
    "sg:city":"Palos Verdes Peninsula",
    "sg:classifiers":[
        {
            "category":"Banks & Credit Unions",
            "subcategory":"Financial Services",
            "type":"Services"
        }
    ],
    "sg:phone":"+1 310 375 8445",
    "sg:postcode":"90274",
    "sg:province":"CA",
    "sg:tags":[
        "investment",
        "closed"
    ],
    "wof:name":"James Dimitriou",
    "wof:placetype":"venue"
},
  "geometry": {"coordinates":[-118.401393,33.796148],"type":"Point"}
}