{
  "type": "Feature",
  "properties": {
    "addr:full":"2922 Las Flores Ave Riverside CA 92503",
    "addr:housenumber":"2922",
    "addr:postcode":"92503",
    "addr:street":"Las Flores Ave",
    "iso:country":"US",
    "sg:address":"2922 Las Flores Ave",
    "sg:city":"Riverside",
    "sg:classifiers":[
        {
            "category":"Mining & Drilling",
            "type":"Manufacturing & Wholesale Goods"
        }
    ],
    "sg:phone":"+1 951 359 4001",
    "sg:postcode":"92503",
    "sg:province":"CA",
    "sg:tags":[
        "construction"
    ],
    "wof:name":"CWC Construction Systems Inc",
    "wof:placetype":"venue"
},
  "geometry": {"coordinates":[-117.44653599999999,33.900924],"type":"Point"}
}