{
  "type": "Feature",
  "properties": {
    "addr:full":"2525 el Camino Real Carlsbad CA 92008",
    "addr:housenumber":"2525",
    "addr:postcode":"92008",
    "addr:street":"El Camino Real",
    "iso:country":"US",
    "sg:address":"2525 el Camino Real",
    "sg:city":"Carlsbad",
    "sg:classifiers":[
        {
            "category":"Professional",
            "type":"Services"
        }
    ],
    "sg:phone":"+1 760 434 7593",
    "sg:postcode":"92008",
    "sg:province":"CA",
    "sg:tags":[
        "establishment"
    ],
    "wof:name":"Harris Original Of New York",
    "wof:placetype":"venue"
},
  "geometry": {"coordinates":[-117.32684500000001,33.179488],"type":"Point"}
}