{
  "type": "Feature",
  "properties": {
    "addr:full":"2217 Maryal Dr Sacramento CA 95864",
    "addr:housenumber":"2217",
    "addr:postcode":"95864",
    "addr:street":"Maryal Dr",
    "iso:country":"US",
    "sg:address":"2217 Maryal Dr",
    "sg:city":"Sacramento",
    "sg:classifiers":[
        {
            "category":"Food & Beverages",
            "subcategory":"Specialty",
            "type":"Retail Goods"
        }
    ],
    "sg:phone":"+1 916 972 1363",
    "sg:postcode":"95864",
    "sg:province":"CA",
    "sg:tags":[
        "health",
        "diet"
    ],
    "wof:name":"Herbalife Distributor",
    "wof:placetype":"venue"
},
  "geometry": {"coordinates":[-121.369575,38.605499],"type":"Point"}
}