{
  "type": "Feature",
  "properties": {
    "addr:full":"3940 Kimsue Way San Diego CA 92154",
    "addr:housenumber":"3940",
    "addr:postcode":"92154",
    "addr:street":"Kimsue Way",
    "iso:country":"US",
    "sg:address":"3940 Kimsue Way",
    "sg:city":"San Diego",
    "sg:classifiers":[
        {
            "category":"Manufacturing",
            "subcategory":"Printing",
            "type":"Manufacturing & Wholesale Goods"
        }
    ],
    "sg:phone":"+1 619 428 1472",
    "sg:postcode":"92154",
    "sg:province":"CA",
    "sg:tags":[
        "printer"
    ],
    "wof:name":"Affordable Printing Svc",
    "wof:placetype":"venue"
},
  "geometry": {"coordinates":[-117.049965,32.576079],"type":"Point"}
}