{
  "type": "Feature",
  "properties": {
    "iso:country":"US",
    "sg:address":"1000 Elysian Park Ave",
    "sg:city":"Los Angeles",
    "sg:classifiers":[
        {
            "category":"Restaurant",
            "type":"Food & Drink"
        }
    ],
    "sg:phone":"+1 323 441 2130",
    "sg:postcode":"90012",
    "sg:province":"CA",
    "wof:name":"Levy Restaurants",
    "wof:placetype":"venue"
},
  "geometry": {"coordinates":[-118.236773,34.073546],"type":"Point"}
}