{
  "type": "Feature",
  "properties": {
    "addr:full":"9453 Exeter Ave Montclair CA 91763",
    "addr:housenumber":"9453",
    "addr:postcode":"91763",
    "addr:street":"Exeter Ave",
    "iso:country":"US",
    "sg:address":"9453 Exeter Ave",
    "sg:city":"Montclair",
    "sg:classifiers":[
        {
            "category":"Building & Trades",
            "subcategory":"Construction",
            "type":"Services"
        }
    ],
    "sg:phone":"+1 909 986 3031",
    "sg:postcode":"91763",
    "sg:province":"CA",
    "sg:tags":[
        "concrete",
        "contractor"
    ],
    "wof:name":"Famis Concrete",
    "wof:placetype":"venue"
},
  "geometry": {"coordinates":[-117.68734499999999,34.083572],"type":"Point"}
}