{
  "type": "Feature",
  "properties": {
    "iso:country":"US",
    "sg:address":"304 N 6th St",
    "sg:city":"San Jose",
    "sg:classifiers":[
        {
            "category":"Government",
            "subcategory":"City Hall",
            "type":"Public Place"
        }
    ],
    "sg:phone":"+1 408 295 3394",
    "sg:postcode":"95112",
    "sg:province":"CA",
    "wof:name":"NAACP",
    "wof:placetype":"venue"
},
  "geometry": {"coordinates":[-121.889,37.343399],"type":"Point"}
}