{
  "type": "Feature",
  "properties": {
    "iso:country":"US",
    "sg:address":"158 Oakvale Rd",
    "sg:city":"Walnut Creek",
    "sg:classifiers":[
        {
            "category":"Building & Trades",
            "subcategory":"Construction",
            "type":"Services"
        }
    ],
    "sg:phone":"+1 925 932 4822",
    "sg:postcode":"94597",
    "sg:province":"CA",
    "sg:tags":[
        "contractor"
    ],
    "wof:name":"Commercial Sndblst Wtrproofing",
    "wof:placetype":"venue"
},
  "geometry": {"coordinates":[-122.07825,37.903954],"type":"Point"}
}