{
  "type": "Feature",
  "properties": {
    "addr:full":"27576 Commerce Center Dr Temecula CA 92590",
    "addr:housenumber":"27576",
    "addr:postcode":"92590",
    "addr:street":"Commerce Center Dr",
    "iso:country":"US",
    "sg:address":"27576 Commerce Center Dr",
    "sg:city":"Temecula",
    "sg:classifiers":[
        {
            "category":"Organizations",
            "subcategory":"Religious Organization",
            "type":"Services"
        }
    ],
    "sg:phone":"+1 951 506 4372",
    "sg:postcode":"92590",
    "sg:province":"CA",
    "wof:name":"Nu-Way Christian Ministries",
    "wof:placetype":"venue"
},
  "geometry": {"coordinates":[-117.160511,33.511642],"type":"Point"}
}