{
  "type": "Feature",
  "properties": {
    "addr:full":"3934 Cochran St Simi Valley CA 93063",
    "addr:housenumber":"3934",
    "addr:postcode":"93063",
    "addr:street":"Cochran St",
    "iso:country":"US",
    "sg:address":"3934 Cochran St",
    "sg:city":"Simi Valley",
    "sg:classifiers":[
        {
            "category":"Manufacturing",
            "subcategory":"Glass & Minerals",
            "type":"Manufacturing & Wholesale Goods"
        }
    ],
    "sg:phone":"+1 805 582 2329",
    "sg:postcode":"93063",
    "sg:province":"CA",
    "sg:tags":[
        "ready",
        "concrete",
        "mfg"
    ],
    "wof:name":"Ru Ready 2 Party",
    "wof:placetype":"venue"
},
  "geometry": {"coordinates":[-118.71789200000001,34.278959],"type":"Point"}
}