{
  "type": "Feature",
  "properties": {
    "addr:full":"2429 11th Ave Los Angeles CA 90018",
    "addr:housenumber":"2429",
    "addr:postcode":"90018",
    "addr:street":"11Th Ave",
    "iso:country":"US",
    "sg:address":"2429 11th Ave",
    "sg:city":"Los Angeles",
    "sg:classifiers":[
        {
            "category":"Wholesale",
            "subcategory":"Non-durable Goods",
            "type":"Manufacturing & Wholesale Goods"
        }
    ],
    "sg:phone":"+1 323 734 0844",
    "sg:postcode":"90018",
    "sg:province":"CA",
    "wof:name":"Worthy Import Export Company",
    "wof:placetype":"venue"
},
  "geometry": {"coordinates":[-118.329644,34.034472],"type":"Point"}
}