{
  "type": "Feature",
  "properties": {
    "addr:full":"10700 Norwalk Blvd Santa Fe Springs CA 90670",
    "addr:housenumber":"10700",
    "addr:postcode":"90670",
    "addr:street":"Norwalk Blvd",
    "iso:country":"US",
    "sg:address":"10700 Norwalk Blvd",
    "sg:city":"Santa Fe Springs",
    "sg:classifiers":[
        {
            "category":"Banks & Credit Unions",
            "subcategory":"Investment Brokerage",
            "type":"Services"
        }
    ],
    "sg:phone":"+1 562 903 1237",
    "sg:postcode":"90670",
    "sg:province":"CA",
    "sg:tags":[
        "advisory",
        "financial"
    ],
    "sg:website":"www.primericaonline.com",
    "wof:name":"Garcia Primitivo Doing Bus As",
    "wof:placetype":"venue"
},
  "geometry": {"coordinates":[-118.072759,33.936502],"type":"Point"}
}