{
  "type": "Feature",
  "properties": {
    "addr:full":"15016 Espola Rd Poway CA 92064",
    "addr:housenumber":"15016",
    "addr:postcode":"ca 92064",
    "addr:street":"Espola Rd",
    "iso:country":"US",
    "sg:address":"15016 Espola Rd",
    "sg:city":"Poway",
    "sg:classifiers":[
        {
            "category":"Professional",
            "type":"Services"
        }
    ],
    "sg:phone":"+1 858 679 4946",
    "sg:postcode":"92064",
    "sg:province":"CA",
    "sg:tags":[
        "establishment"
    ],
    "wof:name":"Morgan Polymer Seals",
    "wof:placetype":"venue"
},
  "geometry": {"coordinates":[-117.02345800000001,32.985744],"type":"Point"}
}