{
  "type": "Feature",
  "properties": {
    "iso:country":"US",
    "sg:address":"15016 Espola Rd",
    "sg:city":"Poway",
    "sg:classifiers":[
        {
            "category":"Professional",
            "type":"Services"
        }
    ],
    "sg:phone":"+1 858 679 4946",
    "sg:postcode":"92064",
    "sg:province":"CA",
    "sg:tags":[
        "establishment"
    ],
    "wof:name":"Morgan Polymer Seals",
    "wof:placetype":"venue"
},
  "geometry": {"coordinates":[-117.023458,32.985744],"type":"Point"}
}