{
  "type": "Feature",
  "properties": {
    "addr:full":"16915 Van Ness Ave Torrance CA 90504",
    "addr:housenumber":"16915",
    "addr:postcode":"90504",
    "addr:street":"Van Ness Ave",
    "iso:country":"US",
    "sg:address":"16915 Van Ness Ave",
    "sg:city":"Torrance",
    "sg:classifiers":[
        {
            "category":"Building & Trades",
            "subcategory":"Construction",
            "type":"Services"
        }
    ],
    "sg:phone":"+1 310 323 2858",
    "sg:postcode":"90504",
    "sg:province":"CA",
    "sg:tags":[
        "waterproofing",
        "contractor"
    ],
    "wof:name":"South Bay Shower Pans",
    "wof:placetype":"venue"
},
  "geometry": {"coordinates":[-118.31786700000001,33.87652],"type":"Point"}
}