{
  "type": "Feature",
  "properties": {
    "addr:full":"11205 Paramount Blvd Downey CA 90241",
    "addr:housenumber":"11205",
    "addr:postcode":"90241",
    "addr:street":"Paramount Blvd",
    "iso:country":"US",
    "sg:address":"11205 Paramount Blvd",
    "sg:city":"Downey",
    "sg:classifiers":[
        {
            "category":"Retail",
            "subcategory":"Auto Repair",
            "type":"Services"
        }
    ],
    "sg:phone":"+1 562 923 0884",
    "sg:postcode":"90241",
    "sg:province":"CA",
    "sg:tags":[
        "body",
        "shop"
    ],
    "sg:website":"www.onedaypaint.com",
    "wof:name":"1-Day Paint & Body Centers",
    "wof:placetype":"venue"
},
  "geometry": {"coordinates":[-118.13800000000001,33.942402],"type":"Point"}
}