{
  "type": "Feature",
  "properties": {
    "addr:full":"6905 Magnolia Ave Riverside CA 92506",
    "addr:housenumber":"6905",
    "addr:postcode":"92506",
    "addr:street":"Magnolia Ave",
    "iso:country":"US",
    "sg:address":"6905 Magnolia Ave",
    "sg:city":"Riverside",
    "sg:classifiers":[
        {
            "category":"Retail",
            "subcategory":"Portrait Studio",
            "type":"Services"
        }
    ],
    "sg:phone":"+1 951 682 3686",
    "sg:postcode":"92506",
    "sg:province":"CA",
    "sg:tags":[
        "photographer"
    ],
    "wof:name":"Countryside At The Cottage",
    "wof:placetype":"venue"
},
  "geometry": {"coordinates":[-117.39943100000001,33.948943],"type":"Point"}
}