{
  "type": "Feature",
  "properties": {
    "iso:country":"US",
    "sg:address":"877 Ygnacio Valley Rd",
    "sg:city":"Walnut Creek",
    "sg:classifiers":[
        {
            "category":"Personal",
            "type":"Services"
        }
    ],
    "sg:phone":"+1 925 934 6020",
    "sg:postcode":"94596",
    "sg:province":"CA",
    "sg:tags":[
        "make",
        "permanent"
    ],
    "sg:website":"www.lemormpi.com",
    "wof:name":"Lemor Permanent Cosmetics",
    "wof:placetype":"venue"
},
  "geometry": {"coordinates":[-122.057129,37.907241],"type":"Point"}
}