{
  "type": "Feature",
  "properties": {
    "addr:full":"226 E Blithedale Ave Mill Valley CA 94941",
    "addr:housenumber":"226",
    "addr:postcode":"94941",
    "addr:street":"E Blithedale Ave",
    "iso:country":"US",
    "sg:address":"226 E Blithedale Ave",
    "sg:city":"Mill Valley",
    "sg:classifiers":[
        {
            "category":"Personal",
            "subcategory":"Beauty Salon",
            "type":"Services"
        }
    ],
    "sg:phone":"+1 415 383 7534",
    "sg:postcode":"94941",
    "sg:province":"CA",
    "sg:tags":[
        "manicuring"
    ],
    "wof:name":"Shiny Nail Salon",
    "wof:placetype":"venue"
},
  "geometry": {"coordinates":[-122.54237500000001,37.904321],"type":"Point"}
}