{
  "type": "Feature",
  "properties": {
    "iso:country":"US",
    "sg:address":"954 Mission St",
    "sg:city":"South Pasadena",
    "sg:classifiers":[
        {
            "category":"Food & Beverages",
            "subcategory":"Candy",
            "type":"Retail Goods"
        }
    ],
    "sg:phone":"+1 626 441 4010",
    "sg:postcode":"91030",
    "sg:province":"CA",
    "sg:tags":[
        "dessert"
    ],
    "wof:name":"My Sweet Cupcake",
    "wof:placetype":"venue"
},
  "geometry": {"coordinates":[-118.157427,34.11576],"type":"Point"}
}