{
  "type": "Feature",
  "properties": {
    "iso:country":"US",
    "sg:address":"450 W Citrus St",
    "sg:city":"Colton",
    "sg:classifiers":[
        {
            "category":"Organizations",
            "subcategory":"Religious Organization",
            "type":"Services"
        }
    ],
    "sg:phone":"+1 909 825 8901",
    "sg:postcode":"92324",
    "sg:province":"CA",
    "sg:tags":[
        "church"
    ],
    "wof:name":"Assembly Of God Church",
    "wof:placetype":"venue"
},
  "geometry": {"coordinates":[-117.328642,34.08481],"type":"Point"}
}