{
  "type": "Feature",
  "properties": {
    "addr:full":"2100 N Sepulveda Boulevard Manhattan Beach CA 90266",
    "addr:housenumber":"2100",
    "addr:postcode":"90266",
    "addr:street":"N Sepulveda Boulevard",
    "iso:country":"US",
    "sg:address":"2100 N Sepulveda Boulevard",
    "sg:city":"Manhattan Beach",
    "sg:classifiers":[
        {
            "category":"Personal",
            "subcategory":"Beauty Salon",
            "type":"Services"
        },
        {
            "category":"Personal",
            "subcategory":"Day Spa",
            "type":"Services"
        }
    ],
    "sg:phone":"+1 310 546 4459",
    "sg:postcode":"90266",
    "sg:province":"CA",
    "sg:tags":[
        "hair"
    ],
    "sg:website":"www.illusionsofbeauty.com",
    "wof:name":"Illusion's Beauty Salon",
    "wof:placetype":"venue"
},
  "geometry": {"coordinates":[-118.395928,33.892901],"type":"Point"}
}