{
  "type": "Feature",
  "properties": {
    "addr:full":"1332 Bison Ave Newport Beach CA 92660",
    "addr:housenumber":"1332",
    "addr:postcode":"92660",
    "addr:street":"Bison Ave",
    "iso:country":"US",
    "sg:address":"1332 Bison Ave",
    "sg:city":"Newport Beach",
    "sg:classifiers":[
        {
            "category":"Restaurant",
            "type":"Food & Drink"
        }
    ],
    "sg:phone":"+1 949 335 0200",
    "sg:postcode":"92660",
    "sg:province":"CA",
    "wof:name":"Pasta Bravo Restaurant",
    "wof:placetype":"venue"
},
  "geometry": {"coordinates":[-117.862999,33.637699],"type":"Point"}
}