{
  "type": "Feature",
  "properties": {
    "addr:full":"3580 Wilshire Boulevard Los Angeles CA 90010",
    "addr:housenumber":"3580",
    "addr:postcode":"90010",
    "addr:street":"Wilshire Boulevard",
    "iso:country":"US",
    "sg:address":"3580 Wilshire Boulevard",
    "sg:city":"Los Angeles",
    "sg:classifiers":[
        {
            "category":"Professional",
            "subcategory":"Lawyer & Legal Services",
            "type":"Services"
        }
    ],
    "sg:phone":"+1 213 385 2009",
    "sg:postcode":"90010",
    "sg:province":"CA",
    "wof:name":"Law Offices of David B Bloom",
    "wof:placetype":"venue"
},
  "geometry": {"coordinates":[-118.302921,34.0617],"type":"Point"}
}