{
  "type": "Feature",
  "properties": {
    "addr:full":"7173 Saranac St San Diego CA 92115",
    "addr:housenumber":"7173",
    "addr:postcode":"92115",
    "addr:street":"Saranac St",
    "iso:country":"US",
    "sg:address":"7173 Saranac St",
    "sg:city":"San Diego",
    "sg:classifiers":[
        {
            "category":"Organizations",
            "subcategory":"Religious Organization",
            "type":"Services"
        }
    ],
    "sg:phone":"+1 619 589 6200",
    "sg:postcode":"92115",
    "sg:province":"CA",
    "sg:website":"www.alrribat.org",
    "wof:name":"Masjid Al Ribat Al Islami",
    "wof:placetype":"venue"
},
  "geometry": {"coordinates":[-117.043289,32.770893],"type":"Point"}
}