{
  "type": "Feature",
  "properties": {
    "addr:full":"970 S Petit Ave Ventura CA 93004",
    "addr:housenumber":"970",
    "addr:postcode":"93004",
    "addr:street":"S Petit Ave",
    "iso:country":"US",
    "sg:address":"970 S Petit Ave",
    "sg:city":"Ventura",
    "sg:classifiers":[
        {
            "category":"Sports & Exercise",
            "subcategory":"Gym",
            "type":"Entertainment"
        }
    ],
    "sg:phone":"+1 805 672 2888",
    "sg:postcode":"93004",
    "sg:province":"CA",
    "sg:tags":[
        "club",
        "health",
        "studio",
        "gymnasium"
    ],
    "wof:name":"East End Pilates",
    "wof:placetype":"venue"
},
  "geometry": {"coordinates":[-119.17236800000001,34.273297],"type":"Point"}
}