{
  "type": "Feature",
  "properties": {
    "addr:full":"10655 Folsom Blvd Rancho Cordova CA 95670",
    "addr:housenumber":"10655",
    "addr:postcode":"95670",
    "addr:street":"Folsom Blvd",
    "iso:country":"US",
    "sg:address":"10655 Folsom Blvd",
    "sg:city":"Rancho Cordova",
    "sg:classifiers":[
        {
            "category":"Professional",
            "subcategory":"Accounting & Tax Preparation",
            "type":"Services"
        }
    ],
    "sg:phone":"+1 916 363 6786",
    "sg:postcode":"95670",
    "sg:province":"CA",
    "sg:tags":[
        "return",
        "filing"
    ],
    "wof:name":"H & R Block Tax Svc",
    "wof:placetype":"venue"
},
  "geometry": {"coordinates":[-121.29038,38.595157],"type":"Point"}
}