{
  "type": "Feature",
  "properties": {
    "addr:full":"9310 Topanga Canyon Blvd Chatsworth CA 91311",
    "addr:postcode":"9310;91311",
    "addr:street":"Topanga Canyon Blvd",
    "iso:country":"US",
    "sg:address":"9310 Topanga Canyon Blvd",
    "sg:city":"Chatsworth",
    "sg:classifiers":[
        {
            "category":"Professional",
            "subcategory":"Accounting & Tax Preparation",
            "type":"Services"
        }
    ],
    "sg:phone":"+1 818 341 5606",
    "sg:postcode":"91311",
    "sg:province":"CA",
    "sg:tags":[
        "accountant"
    ],
    "wof:name":"Harpster Kurtz & Cox",
    "wof:placetype":"venue"
},
  "geometry": {"coordinates":[-118.605936,34.240782],"type":"Point"}
}