{
  "type": "Feature",
  "properties": {
    "addr:full":"1681 Noe St San Francisco CA 94131",
    "addr:housenumber":"1681",
    "addr:postcode":"94131",
    "addr:street":"Noe St",
    "iso:country":"US",
    "sg:address":"1681 Noe St",
    "sg:city":"San Francisco",
    "sg:classifiers":[
        {
            "category":"Building & Trades",
            "subcategory":"Cleaning & Sanitation",
            "type":"Services"
        }
    ],
    "sg:phone":"+1 415 642 9300",
    "sg:postcode":"94131",
    "sg:province":"CA",
    "sg:tags":[
        "janitor"
    ],
    "wof:name":"Bay Vista Building Mntnc",
    "wof:placetype":"venue"
},
  "geometry": {"coordinates":[-122.43091,37.742332],"type":"Point"}
}