{
  "type": "Feature",
  "properties": {
    "addr:full":"2645 S Cherry Ave Fresno CA 93706",
    "addr:housenumber":"2645",
    "addr:postcode":"93706",
    "addr:street":"S Cherry Ave",
    "iso:country":"US",
    "sg:address":"2645 S Cherry Ave",
    "sg:city":"Fresno",
    "sg:classifiers":[
        {
            "category":"Manufacturing",
            "subcategory":"Tools & Machinery",
            "type":"Manufacturing & Wholesale Goods"
        }
    ],
    "sg:phone":"+1 559 233 8434",
    "sg:postcode":"93706",
    "sg:province":"CA",
    "sg:tags":[
        "filter"
    ],
    "wof:name":"Hall Distributing Co",
    "wof:placetype":"venue"
},
  "geometry": {"coordinates":[-119.7818,36.705816],"type":"Point"}
}