{
  "type": "Feature",
  "properties": {
    "addr:full":"2210 Jenni Ln Tracy CA 95377",
    "addr:housenumber":"2210",
    "addr:postcode":"95377",
    "addr:street":"Jenni Ln",
    "iso:country":"US",
    "sg:address":"2210 Jenni Ln",
    "sg:city":"Tracy",
    "sg:classifiers":[
        {
            "category":"Professional",
            "subcategory":"Management & Consulting",
            "type":"Services"
        }
    ],
    "sg:phone":"+1 209 832 0800",
    "sg:postcode":"95377",
    "sg:province":"CA",
    "sg:tags":[
        "international",
        "business"
    ],
    "wof:name":"Gerhard Group Intl",
    "wof:placetype":"venue"
},
  "geometry": {"coordinates":[-121.458029,37.749027],"type":"Point"}
}