{
  "type": "Feature",
  "properties": {
    "iso:country":"US",
    "sg:address":"583 Crows Landing Rd",
    "sg:city":"Modesto",
    "sg:classifiers":[
        {
            "category":"Autos & Motor Vehicles",
            "subcategory":"Automobile Sales",
            "type":"Retail Goods"
        }
    ],
    "sg:phone":"+1 209 575 9952",
    "sg:postcode":"95351",
    "sg:province":"CA",
    "sg:tags":[
        "car",
        "used",
        "dealer"
    ],
    "wof:name":"Los Compadres Auto Sales",
    "wof:placetype":"venue"
},
  "geometry": {"coordinates":[-120.993396,37.624259],"type":"Point"}
}