{
  "type": "Feature",
  "properties": {
    "addr:full":"1470 Dale Way Costa Mesa CA 92626",
    "addr:housenumber":"1470",
    "addr:postcode":"92626",
    "addr:street":"Dale Way",
    "iso:country":"US",
    "sg:address":"1470 Dale Way",
    "sg:city":"Costa Mesa",
    "sg:classifiers":[
        {
            "category":"Professional",
            "subcategory":"Computer Services",
            "type":"Services"
        }
    ],
    "sg:phone":"+1 877 663 9043",
    "sg:postcode":"92626",
    "sg:province":"CA",
    "sg:tags":[
        "government-opportunity-management",
        "federal-opportunities",
        "fedbizopps",
        "find-government-deals",
        "bids",
        "government-contracting"
    ],
    "sg:website":"http://www.fedbidspeed.com",
    "wof:name":"Bidspeed",
    "wof:placetype":"venue"
},
  "geometry": {"coordinates":[-117.91941199999999,33.679184],"type":"Point"}
}