{
  "type": "Feature",
  "properties": {
    "addr:full":"599 S 4th St San Jose CA 95112",
    "addr:housenumber":"599",
    "addr:postcode":"95112",
    "addr:street":"S 4Th St",
    "iso:country":"US",
    "sg:address":"599 S 4th St",
    "sg:city":"San Jose",
    "sg:classifiers":[
        {
            "category":"Shopping",
            "subcategory":"Florist",
            "type":"Retail Goods"
        }
    ],
    "sg:phone":"+1 408 280 6610",
    "sg:postcode":"95112",
    "sg:province":"CA",
    "wof:name":"Jc Flowers",
    "wof:placetype":"venue"
},
  "geometry": {"coordinates":[-121.88099,37.328675],"type":"Point"}
}