{
  "type": "Feature",
  "properties": {
    "iso:country":"US",
    "sg:address":"827 W Stevens Ave",
    "sg:city":"Santa Ana",
    "sg:classifiers":[
        {
            "category":"Education",
            "subcategory":"Preschool",
            "type":"Public Place"
        },
        {
            "category":"Education",
            "subcategory":"School",
            "type":"Public Place"
        }
    ],
    "sg:phone":"+1 714 549 0086",
    "sg:postcode":"92707",
    "sg:province":"CA",
    "sg:tags":[
        "elementary"
    ],
    "wof:name":"South Coast Preschool Academy",
    "wof:placetype":"venue"
},
  "geometry": {"coordinates":[-117.88099699999999,33.694401],"type":"Point"}
}