{
  "type": "Feature",
  "properties": {
    "addr:full":"27190 Alicia Pkwy Laguna Niguel CA 92677",
    "addr:housenumber":"27190",
    "addr:postcode":"92677",
    "addr:street":"Alicia Pkwy",
    "iso:country":"US",
    "sg:address":"27190 Alicia Pkwy",
    "sg:city":"Laguna Niguel",
    "sg:classifiers":[
        {
            "category":"Home & Garden",
            "subcategory":"Carpets & Floor Coverings",
            "type":"Retail Goods"
        }
    ],
    "sg:phone":"+1 949 362 9659",
    "sg:postcode":"92677",
    "sg:province":"CA",
    "sg:tags":[
        "dealer",
        "rug"
    ],
    "wof:name":"Econo Carpet & Flooring",
    "wof:placetype":"venue"
},
  "geometry": {"coordinates":[-117.715411,33.565844],"type":"Point"}
}