{
  "type": "Feature",
  "properties": {
    "addr:full":"5939 2nd Ave Los Angeles CA 90043",
    "addr:housenumber":"5939",
    "addr:postcode":"90043",
    "addr:street":"2Nd Ave",
    "iso:country":"US",
    "sg:address":"5939 2nd Ave",
    "sg:city":"Los Angeles",
    "sg:classifiers":[
        {
            "category":"Social Services",
            "subcategory":"Child Care",
            "type":"Services"
        }
    ],
    "sg:phone":"+1 323 294 9547",
    "sg:postcode":"90043",
    "sg:province":"CA",
    "sg:tags":[
        "day"
    ],
    "wof:name":"YMCA 59th St School Child Care Center",
    "wof:placetype":"venue"
},
  "geometry": {"coordinates":[-118.319,33.986801],"type":"Point"}
}