{
  "type": "Feature",
  "properties": {
    "iso:country":"US",
    "sg:address":"2004 Chambers Cir",
    "sg:city":"Brentwood",
    "sg:classifiers":[
        {
            "category":"Professional",
            "type":"Services"
        }
    ],
    "sg:phone":"+1 925 516 3717",
    "sg:postcode":"94513",
    "sg:province":"CA",
    "wof:name":"Stiglich Lucier & Company",
    "wof:placetype":"venue"
},
  "geometry": {"coordinates":[-121.732268,37.937976],"type":"Point"}
}