{
  "type": "Feature",
  "properties": {
    "addr:full":"3105 E Harcourt St Compton CA 90221",
    "addr:housenumber":"3105",
    "addr:postcode":"90221",
    "addr:street":"E Harcourt St",
    "iso:country":"US",
    "sg:address":"3105 E Harcourt St",
    "sg:city":"Compton",
    "sg:classifiers":[
        {
            "category":"Professional",
            "subcategory":"Employment Agencies",
            "type":"Services"
        }
    ],
    "sg:phone":"+1 310 223 1726",
    "sg:postcode":"90221",
    "sg:province":"CA",
    "wof:name":"Diamond Staffing Inc",
    "wof:placetype":"venue"
},
  "geometry": {"coordinates":[-118.20702199999999,33.867522],"type":"Point"}
}