{
  "type": "Feature",
  "properties": {
    "iso:country":"US",
    "sg:address":"817 Bancroft Way",
    "sg:city":"Berkeley",
    "sg:classifiers":[
        {
            "category":"Communications",
            "subcategory":"Newspaper",
            "type":"Services"
        },
        {
            "category":"Wholesale",
            "subcategory":"Books, Periodicals, & Newspapers",
            "type":"Manufacturing & Wholesale Goods"
        }
    ],
    "sg:phone":"+1 510 549 6400",
    "sg:postcode":"94710",
    "sg:province":"CA",
    "sg:tags":[
        "print",
        "magazine",
        "medium"
    ],
    "sg:website":"www.readymademag.com/",
    "wof:name":"ReadyMade Magazine",
    "wof:placetype":"venue"
},
  "geometry": {"coordinates":[-122.296768,37.8634],"type":"Point"}
}