{
  "type": "Feature",
  "properties": {
    "iso:country":"US",
    "sg:address":"1611 Montana Ave",
    "sg:city":"Santa Monica",
    "sg:classifiers":[
        {
            "category":"Health Services",
            "subcategory":"Health Practitioner",
            "type":"Services"
        }
    ],
    "sg:phone":"+1 310 451 0868",
    "sg:postcode":"90403",
    "sg:province":"CA",
    "sg:tags":[
        "acupuncture"
    ],
    "wof:name":"Anne R Saldo",
    "wof:placetype":"venue"
},
  "geometry": {"coordinates":[-118.492453,34.034478],"type":"Point"}
}