{
  "type": "Feature",
  "properties": {
    "addr:full":"685 Market Street Suite 560 San Francisco CA 94105",
    "addr:housenumber":"685",
    "addr:postcode":"94105",
    "addr:street":"Market Street Suite 560",
    "iso:country":"US",
    "sg:address":"685 Market Street Suite 560",
    "sg:city":"San Francisco",
    "sg:classifiers":[
        {
            "category":"Professional",
            "subcategory":"Computer Services",
            "type":"Services"
        }
    ],
    "sg:phone":"+1 212 607 8007",
    "sg:postcode":"94105",
    "sg:province":"CA",
    "sg:tags":[
        "games",
        "videogames",
        "games-on-demand",
        "video-games"
    ],
    "sg:website":"http://www.exent.com",
    "wof:name":"Exent",
    "wof:placetype":"venue"
},
  "geometry": {"coordinates":[-122.403431,37.787642],"type":"Point"}
}