{
  "type": "Feature",
  "properties": {
    "addr:full":"208 Brabo Ter Mill Valley CA 94941",
    "addr:housenumber":"208",
    "addr:postcode":"94941",
    "addr:street":"Brabo Ter",
    "iso:country":"US",
    "sg:address":"208 Brabo Ter",
    "sg:city":"Mill Valley",
    "sg:classifiers":[
        {
            "category":"Professional",
            "subcategory":"Business Services",
            "type":"Services"
        }
    ],
    "sg:phone":"+1 415 388 9436",
    "sg:postcode":"94941",
    "sg:province":"CA",
    "sg:tags":[
        "architectural"
    ],
    "sg:website":"www.changinteriors.com",
    "wof:name":"Chang Interiors",
    "wof:placetype":"venue"
},
  "geometry": {"coordinates":[-122.54132300000001,37.893253],"type":"Point"}
}