{
  "type": "Feature",
  "properties": {
    "iso:country":"US",
    "sg:address":"140 Harbor Blvd",
    "sg:city":"Belmont",
    "sg:classifiers":[
        {
            "category":"Autos & Motor Vehicles",
            "subcategory":"Auto Supplies",
            "type":"Retail Goods"
        }
    ],
    "sg:phone":"+1 650 592 1131",
    "sg:postcode":"94002",
    "sg:province":"CA",
    "sg:tags":[
        "automobile",
        "parts"
    ],
    "sg:website":"www.donscofuncar.com",
    "wof:name":"Donsco",
    "wof:placetype":"venue"
},
  "geometry": {"coordinates":[-122.267173,37.521276],"type":"Point"}
}