{
  "type": "Feature",
  "properties": {
    "iso:country":"US",
    "sg:address":"521 Hannon Ave",
    "sg:city":"Monterey",
    "sg:classifiers":[
        {
            "category":"Retail",
            "subcategory":"Portrait Studio",
            "type":"Services"
        }
    ],
    "sg:phone":"+1 831 372 7690",
    "sg:postcode":"93940",
    "sg:province":"CA",
    "sg:tags":[
        "photographer"
    ],
    "wof:name":"Underwater Thrills Inc",
    "wof:placetype":"venue"
},
  "geometry": {"coordinates":[-121.856431,36.599352],"type":"Point"}
}