{
  "type": "Feature",
  "properties": {
    "addr:full":"39848 State Hwy 36 Bridgeville CA 95526",
    "addr:housenumber":"39848",
    "addr:postcode":"95526",
    "addr:street":"State Hwy 36",
    "iso:country":"US",
    "sg:address":"39848 State Hwy 36",
    "sg:city":"Bridgeville",
    "sg:classifiers":[
        {
            "category":"Home & Garden",
            "subcategory":"Home Furnishings",
            "type":"Retail Goods"
        }
    ],
    "sg:phone":"+1 707 777 1752",
    "sg:postcode":"95526",
    "sg:province":"CA",
    "sg:tags":[
        "glassware",
        "chinaware"
    ],
    "wof:name":"Crystal Climax Corp",
    "wof:placetype":"venue"
},
  "geometry": {"coordinates":[-123.65294,40.479494],"type":"Point"}
}