{
  "type": "Feature",
  "properties": {
    "addr:full":"945 W Hyde Park Blvd Inglewood CA 90302",
    "addr:housenumber":"945",
    "addr:postcode":"90302",
    "addr:street":"W Hyde Park Blvd",
    "iso:country":"US",
    "sg:address":"945 W Hyde Park Blvd",
    "sg:city":"Inglewood",
    "sg:classifiers":[
        {
            "category":"Wholesale",
            "subcategory":"Photographic Equipment",
            "type":"Manufacturing & Wholesale Goods"
        }
    ],
    "sg:phone":"+1 310 559 9090",
    "sg:postcode":"90302",
    "sg:province":"CA",
    "sg:tags":[
        "supply"
    ],
    "sg:website":"www.4wedcam.com",
    "wof:name":"International Supplies Corp",
    "wof:placetype":"venue"
},
  "geometry": {"coordinates":[-118.368837,33.96461],"type":"Point"}
}