{
  "type": "Feature",
  "properties": {
    "iso:country":"US",
    "sg:address":"4567 N Bendel Ave",
    "sg:city":"Fresno",
    "sg:classifiers":[
        {
            "category":"Retail",
            "subcategory":"Auto Repair",
            "type":"Services"
        }
    ],
    "sg:phone":"+1 559 225 2633",
    "sg:postcode":"93722",
    "sg:province":"CA",
    "sg:tags":[
        "repairing",
        "automobile"
    ],
    "wof:name":"United Service Automotive",
    "wof:placetype":"venue"
},
  "geometry": {"coordinates":[-119.870411,36.804037],"type":"Point"}
}