{
  "type": "Feature",
  "properties": {
    "iso:country":"US",
    "sg:address":"18225 State Hwy 18",
    "sg:city":"Apple Valley",
    "sg:classifiers":[
        {
            "category":"Health Services",
            "subcategory":"Podiatrist",
            "type":"Services"
        }
    ],
    "sg:phone":"+1 760 242 5096",
    "sg:postcode":"92307",
    "sg:province":"CA",
    "sg:website":"www.foot911.com",
    "wof:name":"Loma Linda Foot Clinic",
    "wof:placetype":"venue"
},
  "geometry": {"coordinates":[-117.266352,34.54054],"type":"Point"}
}