{
  "type": "Feature",
  "properties": {
    "addr:full":"560 Crestfield Cir Roseville CA 95678",
    "addr:housenumber":"560",
    "addr:postcode":"95678",
    "addr:street":"Crestfield Cir",
    "iso:country":"US",
    "sg:address":"560 Crestfield Cir",
    "sg:city":"Roseville",
    "sg:classifiers":[
        {
            "category":"Building & Trades",
            "subcategory":"Construction",
            "type":"Services"
        }
    ],
    "sg:phone":"+1 916 791 1974",
    "sg:postcode":"95678",
    "sg:province":"CA",
    "sg:tags":[
        "residential"
    ],
    "wof:name":"William Mc Broom Construction",
    "wof:placetype":"venue"
},
  "geometry": {"coordinates":[-121.293094,38.778613],"type":"Point"}
}