{
  "type": "Feature",
  "properties": {
    "iso:country":"US",
    "sg:address":"12900 Saratoga Ave.",
    "sg:city":"Saratoga",
    "sg:classifiers":[
        {
            "category":"Real Estate",
            "subcategory":"Real Estate Agent",
            "type":"Services"
        }
    ],
    "sg:phone":"+1 408 390 3897",
    "sg:postcode":"95070",
    "sg:province":"CA",
    "wof:name":"Janet Witkin - Saratoga Real Estate Agent",
    "wof:placetype":"venue"
},
  "geometry": {"coordinates":[-122.002284,37.279934],"type":"Point"}
}