{
  "type": "Feature",
  "properties": {
    "iso:country":"US",
    "sg:address":"39571 Buena Vista Ter",
    "sg:city":"Fremont",
    "sg:classifiers":[
        {
            "category":"Manufacturing",
            "subcategory":"Printing",
            "type":"Manufacturing & Wholesale Goods"
        }
    ],
    "sg:phone":"+1 510 445 0672",
    "sg:postcode":"94538",
    "sg:province":"CA",
    "sg:tags":[
        "publishing"
    ],
    "wof:name":"Lifetouch Church Directories",
    "wof:placetype":"venue"
},
  "geometry": {"coordinates":[-121.98040899999999,37.542818],"type":"Point"}
}