{
  "type": "Feature",
  "properties": {
    "addr:full":"10388 Sheldon Rd Elk Grove CA 95624",
    "addr:housenumber":"10388",
    "addr:postcode":"95624",
    "addr:street":"Sheldon Rd",
    "iso:country":"US",
    "sg:address":"10388 Sheldon Rd",
    "sg:city":"Elk Grove",
    "sg:classifiers":[
        {
            "category":"Shopping",
            "subcategory":"Hobbies, Toys, & Games",
            "type":"Retail Goods"
        }
    ],
    "sg:phone":"+1 916 682 4113",
    "sg:postcode":"95624",
    "sg:province":"CA",
    "sg:tags":[
        "craft"
    ],
    "wof:name":"Gourds 'n More",
    "wof:placetype":"venue"
},
  "geometry": {"coordinates":[-121.303377,38.438024],"type":"Point"}
}