{
  "type": "Feature",
  "properties": {
    "addr:full":"306 Lomitas Ln Santa Rosa CA 95404",
    "addr:housenumber":"306",
    "addr:postcode":"95404",
    "addr:street":"Lomitas Ln",
    "iso:country":"US",
    "sg:address":"306 Lomitas Ln",
    "sg:city":"Santa Rosa",
    "sg:classifiers":[
        {
            "category":"Professional",
            "subcategory":"Business Services",
            "type":"Services"
        }
    ],
    "sg:phone":"+1 707 527 1771",
    "sg:postcode":"95404",
    "sg:province":"CA",
    "wof:name":"Great 6 Products",
    "wof:placetype":"venue"
},
  "geometry": {"coordinates":[-122.71756499999999,38.466476],"type":"Point"}
}