{
  "type": "Feature",
  "properties": {
    "addr:full":"820 Sugar Pine Rd Tahoe City CA 96145",
    "addr:housenumber":"820",
    "addr:postcode":"96145",
    "addr:street":"Sugar Pine Rd",
    "iso:country":"US",
    "sg:address":"820 Sugar Pine Rd",
    "sg:city":"Tahoe City",
    "sg:classifiers":[
        {
            "category":"Professional",
            "type":"Services"
        }
    ],
    "sg:phone":"+1 530 583 9420",
    "sg:postcode":"96145",
    "sg:province":"CA",
    "sg:tags":[
        "establishment"
    ],
    "wof:name":"Clauss Enterprises",
    "wof:placetype":"venue"
},
  "geometry": {"coordinates":[-120.16864700000001,39.128205],"type":"Point"}
}