{
  "type": "Feature",
  "properties": {
    "addr:full":"2448 Country Club Ln Selma CA 93662",
    "addr:housenumber":"2448",
    "addr:postcode":"93662",
    "addr:street":"Country Club Ln",
    "iso:country":"US",
    "sg:address":"2448 Country Club Ln",
    "sg:city":"Selma",
    "sg:classifiers":[
        {
            "category":"Building & Trades",
            "subcategory":"Construction",
            "type":"Services"
        }
    ],
    "sg:phone":"+1 559 896 4313",
    "sg:postcode":"93662",
    "sg:province":"CA",
    "sg:tags":[
        "paving",
        "contractor"
    ],
    "wof:name":"Don Berry Construction",
    "wof:placetype":"venue"
},
  "geometry": {"coordinates":[-119.597784,36.570357],"type":"Point"}
}