{
  "type": "Feature",
  "properties": {
    "iso:country":"US",
    "sg:address":"11377 W Olympic Blvd",
    "sg:city":"Los Angeles",
    "sg:classifiers":[
        {
            "category":"Professional",
            "subcategory":"Lawyer & Legal Services",
            "type":"Services"
        }
    ],
    "sg:phone":"+1 310 312 3164",
    "sg:postcode":"90064",
    "sg:province":"CA",
    "wof:name":"Glassman Jacey",
    "wof:placetype":"venue"
},
  "geometry": {"coordinates":[-118.442829,34.037325],"type":"Point"}
}