{
  "type": "Feature",
  "properties": {
    "addr:full":"2648 Fir Park Way Santa Rosa CA 95404",
    "addr:housenumber":"2648",
    "addr:postcode":"95404",
    "addr:street":"Fir Park Way",
    "iso:country":"US",
    "sg:address":"2648 Fir Park Way",
    "sg:city":"Santa Rosa",
    "sg:classifiers":[
        {
            "category":"Real Estate",
            "subcategory":"Architect",
            "type":"Services"
        }
    ],
    "sg:phone":"+1 707 578 8152",
    "sg:postcode":"95404",
    "sg:province":"CA",
    "wof:name":"Robert Moore",
    "wof:placetype":"venue"
},
  "geometry": {"coordinates":[-122.69397600000001,38.470179],"type":"Point"}
}