{
  "type": "Feature",
  "properties": {
    "addr:full":"2261 W Shaw Ave Fresno CA 93711",
    "addr:housenumber":"2261",
    "addr:postcode":"93711",
    "addr:street":"W Shaw Ave",
    "iso:country":"US",
    "sg:address":"2261 W Shaw Ave",
    "sg:city":"Fresno",
    "sg:classifiers":[
        {
            "category":"Personal",
            "subcategory":"Shoe Repair & Shine",
            "type":"Services"
        }
    ],
    "sg:phone":"+1 559 225 2259",
    "sg:postcode":"93711",
    "sg:province":"CA",
    "sg:tags":[
        "shining"
    ],
    "wof:name":"Selly's Shoe Shine",
    "wof:placetype":"venue"
},
  "geometry": {"coordinates":[-119.83157199999999,36.808195],"type":"Point"}
}