{
  "type": "Feature",
  "properties": {
    "addr:full":"4149 Sepulveda Boulevard Culver City CA 90230",
    "addr:housenumber":"4149",
    "addr:postcode":"90230",
    "addr:street":"Sepulveda Boulevard",
    "iso:country":"US",
    "sg:address":"4149 Sepulveda Boulevard",
    "sg:city":"Culver City",
    "sg:classifiers":[
        {
            "category":"Shopping",
            "subcategory":"Hobbies, Toys, & Games",
            "type":"Retail Goods"
        }
    ],
    "sg:phone":"+1 310 391 4081",
    "sg:postcode":"90230",
    "sg:province":"CA",
    "sg:tags":[
        "toy",
        "store"
    ],
    "wof:name":"Noveltoy",
    "wof:placetype":"venue"
},
  "geometry": {"coordinates":[-118.411653,34.005881],"type":"Point"}
}