{
  "type": "Feature",
  "properties": {
    "addr:full":"26130 N Broadway Escondido CA 92026",
    "addr:housenumber":"26130",
    "addr:postcode":"92026",
    "addr:street":"N Broadway",
    "iso:country":"US",
    "sg:address":"26130 N Broadway",
    "sg:city":"Escondido",
    "sg:classifiers":[
        {
            "category":"Home & Garden",
            "subcategory":"Garden Supply",
            "type":"Retail Goods"
        },
        {
            "category":"Shopping",
            "subcategory":"Crafts & Fabrics",
            "type":"Retail Goods"
        },
        {
            "category":"Manufacturing",
            "subcategory":"Paper Products",
            "type":"Manufacturing & Wholesale Goods"
        },
        {
            "category":"Farming",
            "subcategory":"Nursery",
            "type":"Manufacturing & Wholesale Goods"
        }
    ],
    "sg:phone":"+1 760 745 2733",
    "sg:postcode":"92026",
    "sg:province":"CA",
    "sg:tags":[
        "florists'",
        "equipment",
        "seed",
        "florist",
        "bulb",
        "bamboo",
        "supplies-wholesale",
        "growers'",
        "manufacturer"
    ],
    "wof:name":"Ty Nursery",
    "wof:placetype":"venue"
},
  "geometry": {"coordinates":[-117.09256000000001,33.183552],"type":"Point"}
}