{
  "type": "Feature",
  "properties": {
    "addr:full":"4000 W Metropolitan Dr Orange CA 92868",
    "addr:housenumber":"4000",
    "addr:postcode":"92868",
    "addr:street":"W Metropolitan Dr",
    "iso:country":"US",
    "sg:address":"4000 W Metropolitan Dr",
    "sg:city":"Orange",
    "sg:classifiers":[
        {
            "category":"Wholesale",
            "subcategory":"Drugs",
            "type":"Manufacturing & Wholesale Goods"
        }
    ],
    "sg:phone":"+1 714 385 6545",
    "sg:postcode":"92868",
    "sg:province":"CA",
    "wof:name":"Merisource Inc",
    "wof:placetype":"venue"
},
  "geometry": {"coordinates":[-117.89505800000001,33.779742],"type":"Point"}
}