{
  "type": "Feature",
  "properties": {
    "iso:country":"US",
    "sg:address":"4400 MacArthur Boulevard",
    "sg:city":"Newport Beach",
    "sg:classifiers":[
        {
            "category":"Professional",
            "subcategory":"Lawyer & Legal Services",
            "type":"Services"
        }
    ],
    "sg:phone":"+1 949 470 0690",
    "sg:postcode":"92660",
    "sg:province":"CA",
    "wof:name":"Jack Smart Atty At Law",
    "wof:placetype":"venue"
},
  "geometry": {"coordinates":[-117.86393700000001,33.665755],"type":"Point"}
}