{
  "type": "Feature",
  "properties": {
    "iso:country":"US",
    "sg:address":"14673 Mono Way",
    "sg:city":"Sonora",
    "sg:classifiers":[
        {
            "category":"Education",
            "subcategory":"School",
            "type":"Public Place"
        }
    ],
    "sg:phone":"+1 209 533 8644",
    "sg:postcode":"95370",
    "sg:province":"CA",
    "sg:tags":[
        "high",
        "middle",
        "elementary"
    ],
    "wof:name":"Gold Rush Home Study Charter School",
    "wof:placetype":"venue"
},
  "geometry": {"coordinates":[-120.304001,37.984299],"type":"Point"}
}