{
  "type": "Feature",
  "properties": {
    "iso:country":"US",
    "sg:address":"126 Baker St",
    "sg:city":"San Francisco",
    "sg:classifiers":[
        {
            "category":"Professional",
            "type":"Services"
        }
    ],
    "sg:phone":"+1 415 861 3545",
    "sg:postcode":"94117",
    "sg:province":"CA",
    "wof:name":"Doodlezoo LLC",
    "wof:placetype":"venue"
},
  "geometry": {"coordinates":[-122.44062099999999,37.772476],"type":"Point"}
}