{
  "type": "Feature",
  "properties": {
    "addr:full":"2012 West St Oakland CA 94612",
    "addr:housenumber":"2012",
    "addr:postcode":"94612",
    "addr:street":"West St",
    "iso:country":"US",
    "sg:address":"2012 West St",
    "sg:city":"Oakland",
    "sg:phone":"+1 510 898 8070",
    "sg:postcode":"94612",
    "sg:province":"CA",
    "wof:name":"Josh Thomas",
    "wof:placetype":"venue"
},
  "geometry": {"coordinates":[-122.27699699999999,37.811627],"type":"Point"}
}