{
  "type": "Feature",
  "properties": {
    "addr:full":"200 E Oak St Lodi CA 95240",
    "addr:housenumber":"200",
    "addr:postcode":"95240",
    "addr:street":"E Oak St",
    "iso:country":"US",
    "sg:address":"200 E Oak St",
    "sg:city":"Lodi",
    "sg:classifiers":[
        {
            "category":"Social Services",
            "type":"Services"
        }
    ],
    "sg:phone":"+1 209 368 6938",
    "sg:postcode":"95240",
    "sg:province":"CA",
    "sg:tags":[
        "organization",
        "welfare"
    ],
    "wof:name":"Goodwill Industries",
    "wof:placetype":"venue"
},
  "geometry": {"coordinates":[-121.26811499999999,38.132742],"type":"Point"}
}