{
  "type": "Feature",
  "properties": {
    "iso:country":"US",
    "sg:address":"3170 de la Cruz Blvd",
    "sg:city":"Santa Clara",
    "sg:classifiers":[
        {
            "category":"Restaurant",
            "type":"Food & Drink"
        }
    ],
    "sg:phone":"+1 408 492 1818",
    "sg:postcode":"95054",
    "sg:province":"CA",
    "wof:name":"Royal Garden Chinese Rstrnt",
    "wof:placetype":"venue"
},
  "geometry": {"coordinates":[-121.940242,37.380342],"type":"Point"}
}