{
  "type": "Feature",
  "properties": {
    "iso:country":"US",
    "sg:address":"765 E Cypress Ave",
    "sg:city":"Redding",
    "sg:classifiers":[
        {
            "category":"Autos & Motor Vehicles",
            "subcategory":"Fuel & Gas Station",
            "type":"Retail Goods"
        }
    ],
    "sg:phone":"+1 530 223 2876",
    "sg:postcode":"96002",
    "sg:province":"CA",
    "sg:tags":[
        "oil"
    ],
    "wof:name":"Cypress Chevron",
    "wof:placetype":"venue"
},
  "geometry": {"coordinates":[-122.35543,40.570941],"type":"Point"}
}