{
  "type": "Feature",
  "properties": {
    "addr:full":"13307 Artesia Blvd Cerritos CA 90703",
    "addr:housenumber":"13307",
    "addr:postcode":"ca 90703",
    "addr:street":"Artesia Blvd",
    "iso:country":"US",
    "sg:address":"13307 Artesia Blvd",
    "sg:city":"Cerritos",
    "sg:classifiers":[
        {
            "category":"Real Estate",
            "subcategory":"Real Estate Agent",
            "type":"Services"
        }
    ],
    "sg:phone":"+1 562 404 3510",
    "sg:postcode":"90703",
    "sg:province":"CA",
    "wof:name":"Sunny Estates",
    "wof:placetype":"venue"
},
  "geometry": {"coordinates":[-118.046452,33.873252],"type":"Point"}
}