{
  "type": "Feature",
  "properties": {
    "iso:country":"US",
    "sg:address":"125 Cambon Dr",
    "sg:city":"San Francisco",
    "sg:classifiers":[
        {
            "category":"Wholesale",
            "subcategory":"Non-durable Goods",
            "type":"Manufacturing & Wholesale Goods"
        }
    ],
    "sg:phone":"+1 415 469 7208",
    "sg:postcode":"94132",
    "sg:province":"CA",
    "wof:name":"Mirtsev Global Trading Network",
    "wof:placetype":"venue"
},
  "geometry": {"coordinates":[-122.474338,37.715916],"type":"Point"}
}