{
  "type": "Feature",
  "properties": {
    "addr:full":"7393 Jackson Drive San Diego CA 92119",
    "addr:housenumber":"7393",
    "addr:postcode":"92119",
    "addr:street":"Jackson Drive",
    "iso:country":"US",
    "sg:address":"7393 Jackson Drive",
    "sg:city":"San Diego",
    "sg:classifiers":[
        {
            "category":"Shopping",
            "subcategory":"Pharmacy",
            "type":"Retail Goods"
        },
        {
            "category":"Food & Beverages",
            "subcategory":"Groceries & Convenience Stores",
            "type":"Retail Goods"
        }
    ],
    "sg:phone":"+1 619 465 6800",
    "sg:postcode":"92119",
    "sg:province":"CA",
    "sg:tags":[
        "drugstore"
    ],
    "sg:website":"www.cvs.com",
    "wof:name":"CVS Pharmacy",
    "wof:placetype":"venue"
},
  "geometry": {"coordinates":[-117.043972,32.803266],"type":"Point"}
}