{
  "type": "Feature",
  "properties": {
    "addr:full":"4304 MacArthur Blvd Oakland CA 94619",
    "addr:housenumber":"4304",
    "addr:postcode":"94619",
    "addr:street":"Macarthur Blvd",
    "iso:country":"US",
    "sg:address":"4304 MacArthur Blvd",
    "sg:city":"Oakland",
    "sg:classifiers":[
        {
            "category":"Cinema",
            "subcategory":"Movie Rental",
            "type":"Entertainment"
        }
    ],
    "sg:phone":"+1 510 531 9547",
    "sg:postcode":"94619",
    "sg:province":"CA",
    "sg:tags":[
        "game",
        "video"
    ],
    "wof:name":"Video Factory",
    "wof:placetype":"venue"
},
  "geometry": {"coordinates":[-122.194,37.7868],"type":"Point"}
}