{
  "type": "Feature",
  "properties": {
    "iso:country":"US",
    "sg:address":"600 Montgomery Street",
    "sg:city":"San Francisco",
    "sg:classifiers":[
        {
            "category":"Professional",
            "subcategory":"Lawyer & Legal Services",
            "type":"Services"
        }
    ],
    "sg:phone":"+1 415 981 0550",
    "sg:postcode":"94111",
    "sg:province":"CA",
    "sg:website":"www.steinlubin.com",
    "wof:name":"Rogerson K Bradley",
    "wof:placetype":"venue"
},
  "geometry": {"coordinates":[-122.40300000000001,37.794701],"type":"Point"}
}