{
  "type": "Feature",
  "properties": {
    "addr:full":"7850 Macy Plaza Dr Citrus Heights CA 95610",
    "addr:postcode":"7850;95610",
    "addr:street":"Plaza Dr",
    "iso:country":"US",
    "sg:address":"7850 Macy Plaza Dr",
    "sg:city":"Citrus Heights",
    "sg:classifiers":[
        {
            "category":"Wholesale",
            "subcategory":"Machinery & Supplies",
            "type":"Manufacturing & Wholesale Goods"
        },
        {
            "category":"Shopping",
            "type":"Retail Goods"
        }
    ],
    "sg:phone":"+1 916 966 3299",
    "sg:postcode":"95610",
    "sg:province":"CA",
    "sg:tags":[
        "equipment",
        "establishment",
        "cosmetic",
        "perfume"
    ],
    "wof:name":"Beauty Essentials",
    "wof:placetype":"venue"
},
  "geometry": {"coordinates":[-121.273475,38.671782],"type":"Point"}
}