{
  "type": "Feature",
  "properties": {
    "iso:country":"US",
    "sg:address":"801 Virginia St",
    "sg:city":"Berkeley",
    "sg:classifiers":[
        {
            "category":"Building & Trades",
            "subcategory":"Construction",
            "type":"Services"
        }
    ],
    "sg:phone":"+1 510 526 8886",
    "sg:postcode":"94710",
    "sg:province":"CA",
    "sg:tags":[
        "roofing",
        "industrial",
        "waterproofing",
        "contractor",
        "contractors-commercial"
    ],
    "wof:name":"Malott & Peterson Roofing Co",
    "wof:placetype":"venue"
},
  "geometry": {"coordinates":[-122.300209,37.872089],"type":"Point"}
}