{
  "type": "Feature",
  "properties": {
    "addr:full":"706 S Long Beach Blvd Compton CA 90221",
    "addr:housenumber":"706",
    "addr:postcode":"90221",
    "addr:street":"S Long Beach Blvd",
    "iso:country":"US",
    "sg:address":"706 S Long Beach Blvd",
    "sg:city":"Compton",
    "sg:classifiers":[
        {
            "category":"Personal",
            "type":"Services"
        }
    ],
    "sg:phone":"+1 310 763 7494",
    "sg:postcode":"90221",
    "sg:province":"CA",
    "sg:tags":[
        "mail",
        "receiving"
    ],
    "wof:name":"Mid-Cities Mailbox Rental",
    "wof:placetype":"venue"
},
  "geometry": {"coordinates":[-118.20699399999999,33.888766],"type":"Point"}
}