{
  "type": "Feature",
  "properties": {
    "addr:full":"25002 Moulton Parkway Laguna Hills CA 92637",
    "addr:housenumber":"25002",
    "addr:postcode":"92637",
    "addr:street":"Moulton Parkway",
    "iso:country":"US",
    "sg:address":"25002 Moulton Parkway",
    "sg:city":"Laguna Hills",
    "sg:classifiers":[
        {
            "category":"Professional",
            "subcategory":"Lawyer & Legal Services",
            "type":"Services"
        }
    ],
    "sg:phone":"+1 949 768 0933",
    "sg:postcode":"92637",
    "sg:province":"CA",
    "sg:tags":[
        "notary"
    ],
    "wof:name":"McCormick & Son",
    "wof:placetype":"venue"
},
  "geometry": {"coordinates":[-117.716607,33.5996],"type":"Point"}
}