{
  "type": "Feature",
  "properties": {
    "addr:full":"3550 Alden Way #7 San Jose CA 95117",
    "addr:housenumber":"3550",
    "addr:postcode":"95117",
    "addr:street":"Alden Way # 7",
    "iso:country":"US",
    "sg:address":"3550 Alden Way #7",
    "sg:city":"San Jose",
    "sg:classifiers":[
        {
            "category":"Building & Trades",
            "subcategory":"Cleaning & Sanitation",
            "type":"Services"
        }
    ],
    "sg:phone":"+1 408 497 2502",
    "sg:postcode":"95117",
    "sg:province":"CA",
    "sg:tags":[
        "home"
    ],
    "sg:website":"www.cleantrashcans.com",
    "wof:name":"Clean Trash Cans",
    "wof:placetype":"venue"
},
  "geometry": {"coordinates":[-121.961054,37.321703],"type":"Point"}
}