{
  "type": "Feature",
  "properties": {
    "addr:full":"22612 Foothill Blvd Hayward CA 94541",
    "addr:housenumber":"22612",
    "addr:postcode":"94541",
    "addr:street":"Foothill Blvd",
    "iso:country":"US",
    "sg:address":"22612 Foothill Blvd",
    "sg:city":"Hayward",
    "sg:classifiers":[
        {
            "category":"Education",
            "subcategory":"Special Training",
            "type":"Public Place"
        }
    ],
    "sg:phone":"+1 510 574 0911",
    "sg:postcode":"94541",
    "sg:province":"CA",
    "sg:tags":[
        "instruction",
        "driving"
    ],
    "wof:name":"Bobby's Driving School",
    "wof:placetype":"venue"
},
  "geometry": {"coordinates":[-122.080287,37.673194],"type":"Point"}
}