{
  "type": "Feature",
  "properties": {
    "addr:full":"454 E Hedding St San Jose CA 95112",
    "addr:housenumber":"454",
    "addr:postcode":"95112",
    "addr:street":"E Hedding St",
    "iso:country":"US",
    "sg:address":"454 E Hedding St",
    "sg:city":"San Jose",
    "sg:classifiers":[
        {
            "category":"Insurance",
            "subcategory":"Hazard Insurance",
            "type":"Services"
        }
    ],
    "sg:phone":"+1 408 299 0770",
    "sg:postcode":"95112",
    "sg:province":"CA",
    "sg:tags":[
        "financial",
        "bond"
    ],
    "wof:name":"Amigo Bail Bonds",
    "wof:placetype":"venue"
},
  "geometry": {"coordinates":[-121.893559,37.357935],"type":"Point"}
}