{
  "type": "Feature",
  "properties": {
    "addr:full":"217 4th St Hollister CA 95023",
    "addr:housenumber":"217",
    "addr:postcode":"hollister ca 95023",
    "addr:street":"4Th St",
    "iso:country":"US",
    "sg:address":"217 4th St",
    "sg:city":"Hollister",
    "sg:classifiers":[
        {
            "category":"Building & Trades",
            "subcategory":"Construction",
            "type":"Services"
        }
    ],
    "sg:phone":"+1 831 637 5651",
    "sg:postcode":"95023",
    "sg:province":"CA",
    "sg:tags":[
        "picture",
        "art",
        "jewelry",
        "contractor",
        "glass",
        "framing"
    ],
    "wof:name":"San Benito Glass",
    "wof:placetype":"venue"
},
  "geometry": {"coordinates":[-121.40190699999999,36.852377],"type":"Point"}
}