{
  "type": "Feature",
  "properties": {
    "iso:country":"US",
    "sg:address":"9131 Jurupa Rd",
    "sg:city":"Riverside",
    "sg:classifiers":[
        {
            "category":"Food & Beverages",
            "subcategory":"Bakery",
            "type":"Retail Goods"
        }
    ],
    "sg:phone":"+1 951 685 9599",
    "sg:postcode":"92509",
    "sg:province":"CA",
    "sg:tags":[
        "product",
        "mfg"
    ],
    "wof:name":"Donut Tyme",
    "wof:placetype":"venue"
},
  "geometry": {"coordinates":[-117.47697100000001,33.999215],"type":"Point"}
}