{
  "type": "Feature",
  "properties": {
    "addr:full":"2914 Player Ln Tustin CA 92782",
    "addr:housenumber":"2914",
    "addr:postcode":"92782",
    "addr:street":"Player Ln",
    "iso:country":"US",
    "sg:address":"2914 Player Ln",
    "sg:city":"Tustin",
    "sg:classifiers":[
        {
            "category":"Professional",
            "subcategory":"Management & Consulting",
            "type":"Services"
        }
    ],
    "sg:phone":"+1 714 669 5796",
    "sg:postcode":"92782",
    "sg:province":"CA",
    "sg:tags":[
        "consultant"
    ],
    "wof:name":"A Higher Level",
    "wof:placetype":"venue"
},
  "geometry": {"coordinates":[-117.78185000000001,33.735738],"type":"Point"}
}