{
  "type": "Feature",
  "properties": {
    "addr:full":"1500 S Oxnard Blvd Oxnard CA 93030",
    "addr:housenumber":"1500",
    "addr:postcode":"93030",
    "addr:street":"S Oxnard Blvd",
    "iso:country":"US",
    "sg:address":"1500 S Oxnard Blvd",
    "sg:city":"Oxnard",
    "sg:classifiers":[
        {
            "category":"Travel",
            "subcategory":"Hotels & Motels",
            "type":"Entertainment"
        }
    ],
    "sg:phone":"+1 805 483 1257",
    "sg:postcode":"93030",
    "sg:province":"CA",
    "wof:name":"Budget Gardens",
    "wof:placetype":"venue"
},
  "geometry": {"coordinates":[-119.171673,34.185235],"type":"Point"}
}