{
  "type": "Feature",
  "properties": {
    "addr:full":"750 W Bullard Ave Fresno CA 93704",
    "addr:housenumber":"750",
    "addr:postcode":"93704",
    "addr:street":"W Bullard Ave",
    "iso:country":"US",
    "sg:address":"750 W Bullard Ave",
    "sg:city":"Fresno",
    "sg:classifiers":[
        {
            "category":"Shopping",
            "subcategory":"Pharmacy",
            "type":"Retail Goods"
        }
    ],
    "sg:phone":"+1 559 437 0590",
    "sg:postcode":"93704",
    "sg:province":"CA",
    "wof:name":"Rite Aid Pharmacy",
    "wof:placetype":"venue"
},
  "geometry": {"coordinates":[-119.805887,36.822925],"type":"Point"}
}