{
  "type": "Feature",
  "properties": {
    "addr:full":"2619 Maze Blvd Modesto CA 95358",
    "addr:postcode":"2619;ca 95358",
    "addr:street":"Maze Blvd",
    "iso:country":"US",
    "sg:address":"2619 Maze Blvd",
    "sg:city":"Modesto",
    "sg:classifiers":[
        {
            "category":"Farming",
            "subcategory":"Crops",
            "type":"Manufacturing & Wholesale Goods"
        }
    ],
    "sg:phone":"+1 209 522 0379",
    "sg:postcode":"95358",
    "sg:province":"CA",
    "sg:tags":[
        "grove",
        "nut",
        "tree"
    ],
    "wof:name":"Frank E Hart",
    "wof:placetype":"venue"
},
  "geometry": {"coordinates":[-121.04889300000001,37.638538],"type":"Point"}
}