{
  "type": "Feature",
  "properties": {
    "iso:country":"US",
    "sg:address":"486 E Campbell Ave",
    "sg:city":"Campbell",
    "sg:classifiers":[
        {
            "category":"Utilities",
            "subcategory":"Telephone",
            "type":"Services"
        }
    ],
    "sg:phone":"+1 408 866 0188",
    "sg:postcode":"95008",
    "sg:province":"CA",
    "sg:tags":[
        "communication",
        "radio",
        "except"
    ],
    "wof:name":"Healthhighwaycom Inc",
    "wof:placetype":"venue"
},
  "geometry": {"coordinates":[-121.941142,37.287009],"type":"Point"}
}