{
  "type": "Feature",
  "properties": {
    "addr:full":"734 S Alameda St Los Angeles CA 90021",
    "addr:housenumber":"734",
    "addr:postcode":"90021",
    "addr:street":"S Alameda St",
    "iso:country":"US",
    "sg:address":"734 S Alameda St",
    "sg:city":"Los Angeles",
    "sg:classifiers":[
        {
            "category":"Wholesale",
            "subcategory":"Fruits & Vegetables",
            "type":"Manufacturing & Wholesale Goods"
        }
    ],
    "sg:phone":"+1 213 622 2361",
    "sg:postcode":"90021",
    "sg:province":"CA",
    "sg:tags":[
        "veggie"
    ],
    "wof:name":"Colton & Wood",
    "wof:placetype":"venue"
},
  "geometry": {"coordinates":[-118.238998,34.033199],"type":"Point"}
}