{
  "type": "Feature",
  "properties": {
    "addr:full":"9012 Hemlock Ave Fontana CA 92335",
    "addr:housenumber":"9012",
    "addr:postcode":"92335",
    "addr:street":"Hemlock Ave",
    "iso:country":"US",
    "sg:address":"9012 Hemlock Ave",
    "sg:city":"Fontana",
    "sg:classifiers":[
        {
            "category":"Professional",
            "type":"Services"
        }
    ],
    "sg:phone":"+1 909 829 0628",
    "sg:postcode":"92335",
    "sg:province":"CA",
    "wof:name":"Julio E Serna",
    "wof:placetype":"venue"
},
  "geometry": {"coordinates":[-117.47559800000001,34.090358],"type":"Point"}
}