{
  "type": "Feature",
  "properties": {
    "addr:full":"1175 Saratoga Ave San Jose CA 95129",
    "addr:housenumber":"1175",
    "addr:postcode":"95129",
    "addr:street":"Saratoga Ave",
    "iso:country":"US",
    "sg:address":"1175 Saratoga Ave",
    "sg:city":"San Jose",
    "sg:classifiers":[
        {
            "category":"Health Services",
            "subcategory":"Chiropractor",
            "type":"Services"
        }
    ],
    "sg:phone":"+1 408 261 1320",
    "sg:postcode":"95129",
    "sg:province":"CA",
    "wof:name":"Samuel Jamieson Dc",
    "wof:placetype":"venue"
},
  "geometry": {"coordinates":[-121.97983000000001,37.303299],"type":"Point"}
}