{
  "type": "Feature",
  "properties": {
    "iso:country":"US",
    "sg:address":"2981 Manchester Cir",
    "sg:city":"Corona",
    "sg:classifiers":[
        {
            "category":"Utilities",
            "subcategory":"Telephone",
            "type":"Services"
        }
    ],
    "sg:phone":"+1 951 272 9542",
    "sg:postcode":"92879",
    "sg:province":"CA",
    "sg:tags":[
        "communications"
    ],
    "wof:name":"Amera Com LLC",
    "wof:placetype":"venue"
},
  "geometry": {"coordinates":[-117.506253,33.896398],"type":"Point"}
}