{
  "type": "Feature",
  "properties": {
    "iso:country":"US",
    "sg:address":"9009 Wimbley Ct",
    "sg:city":"Elk Grove",
    "sg:classifiers":[
        {
            "category":"Professional",
            "type":"Services"
        }
    ],
    "sg:phone":"+1 916 686 1603",
    "sg:postcode":"95624",
    "sg:province":"CA",
    "sg:tags":[
        "establishment"
    ],
    "wof:name":"Niemann Technology Inc Nti",
    "wof:placetype":"venue"
},
  "geometry": {"coordinates":[-121.375571,38.429922],"type":"Point"}
}