{
  "type": "Feature",
  "properties": {
    "iso:country":"US",
    "sg:address":"4106 Oceanside Blvd",
    "sg:city":"Oceanside",
    "sg:classifiers":[
        {
            "category":"Autos & Motor Vehicles",
            "subcategory":"Automobile Sales",
            "type":"Retail Goods"
        }
    ],
    "sg:phone":"+1 760 643 9268",
    "sg:postcode":"92056",
    "sg:province":"CA",
    "sg:tags":[
        "automotive"
    ],
    "wof:name":"Jiffy Lube",
    "wof:placetype":"venue"
},
  "geometry": {"coordinates":[-117.28925700000001,33.206686],"type":"Point"}
}