{
  "type": "Feature",
  "properties": {
    "addr:full":"515 N Sycamore St Santa Ana CA 92701",
    "addr:housenumber":"515",
    "addr:postcode":"92701",
    "addr:street":"N Sycamore St",
    "iso:country":"US",
    "sg:address":"515 N Sycamore St",
    "sg:city":"Santa Ana",
    "sg:classifiers":[
        {
            "category":"Government",
            "subcategory":"Office",
            "type":"Public Place"
        }
    ],
    "sg:phone":"+1 714 834 5904",
    "sg:postcode":"92701",
    "sg:province":"CA",
    "sg:tags":[
        "health",
        "mental"
    ],
    "wof:name":"Integrated Services For Homele",
    "wof:placetype":"venue"
},
  "geometry": {"coordinates":[-117.86860299999999,33.74962],"type":"Point"}
}