{
  "type": "Feature",
  "properties": {
    "addr:full":"634 York St Vallejo CA 94590",
    "addr:housenumber":"634",
    "addr:postcode":"94590",
    "addr:street":"York St",
    "iso:country":"US",
    "sg:address":"634 York St",
    "sg:city":"Vallejo",
    "sg:classifiers":[
        {
            "category":"Building & Trades",
            "subcategory":"Electrical",
            "type":"Services"
        }
    ],
    "sg:phone":"+1 707 642 0330",
    "sg:postcode":"94590",
    "sg:province":"CA",
    "sg:tags":[
        "electrical",
        "contractor"
    ],
    "wof:name":"Super Electric",
    "wof:placetype":"venue"
},
  "geometry": {"coordinates":[-122.252105,38.100145],"type":"Point"}
}