{
  "type": "Feature",
  "properties": {
    "addr:full":"1850 Union St San Francisco CA 94123",
    "addr:housenumber":"1850",
    "addr:postcode":"94123",
    "addr:street":"Union St",
    "iso:country":"US",
    "sg:address":"1850 Union St",
    "sg:city":"San Francisco",
    "sg:classifiers":[
        {
            "category":"Manufacturing",
            "subcategory":"Printing",
            "type":"Manufacturing & Wholesale Goods"
        }
    ],
    "sg:phone":"+1 415 614 0005",
    "sg:postcode":"94123",
    "sg:province":"CA",
    "sg:tags":[
        "commercial"
    ],
    "wof:name":"A Day In May Design",
    "wof:placetype":"venue"
},
  "geometry": {"coordinates":[-122.429907,37.797897],"type":"Point"}
}