{
  "type": "Feature",
  "properties": {
    "iso:country":"US",
    "sg:address":"4104 E Belmont Ave",
    "sg:city":"Fresno",
    "sg:classifiers":[
        {
            "category":"Recreation",
            "type":"Entertainment"
        }
    ],
    "sg:phone":"+1 559 442 0939",
    "sg:postcode":"93702",
    "sg:province":"CA",
    "sg:tags":[
        "parlor",
        "billiard"
    ],
    "wof:name":"Billar El Cora",
    "wof:placetype":"venue"
},
  "geometry": {"coordinates":[-119.754498,36.750409],"type":"Point"}
}