{
  "type": "Feature",
  "properties": {
    "iso:country":"US",
    "sg:address":"14831 Bessemer St",
    "sg:city":"Van Nuys",
    "sg:classifiers":[
        {
            "category":"Shopping",
            "subcategory":"Bicycles & Sporting Goods",
            "type":"Retail Goods"
        }
    ],
    "sg:phone":"+1 818 787 6460",
    "sg:postcode":"91411",
    "sg:province":"CA",
    "sg:tags":[
        "equipment",
        "exercise"
    ],
    "wof:name":"Four Minute Workout",
    "wof:placetype":"venue"
},
  "geometry": {"coordinates":[-118.455072,34.180874],"type":"Point"}
}