{
  "type": "Feature",
  "properties": {
    "iso:country":"US",
    "sg:address":"2565 Sand Creek Rd",
    "sg:city":"Brentwood",
    "sg:classifiers":[
        {
            "category":"Shopping Center",
            "type":"Public Place"
        }
    ],
    "sg:phone":"+1 925 516 8500",
    "sg:postcode":"94513",
    "sg:province":"CA",
    "sg:website":"www.streetsofbrentwoodca.com",
    "wof:name":"The Streets of Brentwood",
    "wof:placetype":"venue"
},
  "geometry": {"coordinates":[-121.73600399999999,37.946194],"type":"Point"}
}