{
  "type": "Feature",
  "properties": {
    "addr:full":"7531 Convoy Ct San Diego CA 92111",
    "addr:housenumber":"7531",
    "addr:postcode":"92111",
    "addr:street":"Convoy Ct",
    "iso:country":"US",
    "sg:address":"7531 Convoy Ct",
    "sg:city":"San Diego",
    "sg:classifiers":[
        {
            "category":"Manufacturing",
            "subcategory":"Tools & Machinery",
            "type":"Manufacturing & Wholesale Goods"
        }
    ],
    "sg:phone":"+1 858 279 4300",
    "sg:postcode":"92111",
    "sg:province":"CA",
    "sg:tags":[
        "machine",
        "mfg"
    ],
    "wof:name":"Sigma 6 Inc",
    "wof:placetype":"venue"
},
  "geometry": {"coordinates":[-117.154771,32.834668],"type":"Point"}
}