{
  "type": "Feature",
  "properties": {
    "addr:full":"142 Nadine St Livermore CA 94550",
    "addr:housenumber":"142",
    "addr:postcode":"94550",
    "addr:street":"Nadine St",
    "iso:country":"US",
    "sg:address":"142 Nadine St",
    "sg:city":"Livermore",
    "sg:classifiers":[
        {
            "category":"Professional",
            "subcategory":"Art Services",
            "type":"Services"
        }
    ],
    "sg:phone":"+1 925 768 1929",
    "sg:postcode":"94550",
    "sg:province":"CA",
    "sg:tags":[
        "graphic",
        "designer"
    ],
    "wof:name":"Cyber Designs",
    "wof:placetype":"venue"
},
  "geometry": {"coordinates":[-121.791856,37.67434],"type":"Point"}
}