{
  "type": "Feature",
  "properties": {
    "iso:country":"US",
    "sg:address":"1717 4th St #B",
    "sg:city":"Berkeley",
    "sg:classifiers":[
        {
            "category":"Home & Garden",
            "subcategory":"Building Materials",
            "type":"Retail Goods"
        },
        {
            "category":"Building & Trades",
            "subcategory":"Construction",
            "type":"Services"
        }
    ],
    "sg:phone":"+1 866 870 9258",
    "sg:postcode":"94710",
    "sg:province":"CA",
    "sg:tags":[
        "windows-repair",
        "window",
        "replacement",
        "installation",
        "doors-vinyl"
    ],
    "sg:website":"http://redirect.searchignite.com/si/cm/tracking/DGTrackingRedirect.aspx?siclientid=3825&siredirect=http%3A%2F%2Fwww%2Epella%2Ecom%2Flocation%2Fwhere%2Dto%2Dbuy%2Fdefault%2Easpx&sisearchengine=155&siproduct=705%5FTL&clearppc=1",
    "wof:name":"Pella Windows & Doors of Berkeley",
    "wof:placetype":"venue"
},
  "geometry": {"coordinates":[-122.30116099999999,37.871623],"type":"Point"}
}