{
  "type": "Feature",
  "properties": {
    "addr:full":"7420 Co Rd 19 Orland CA 95963",
    "addr:housenumber":"7420;19",
    "addr:postcode":"95963",
    "addr:street":"Co Rd",
    "iso:country":"US",
    "sg:address":"7420 Co Rd 19",
    "sg:city":"Orland",
    "sg:phone":"+1 530 865 2815",
    "sg:postcode":"95963",
    "sg:province":"CA",
    "sg:tags":[
        "farm",
        "field",
        "crop"
    ],
    "wof:name":"William Schroer",
    "wof:placetype":"venue"
},
  "geometry": {"coordinates":[-122.10173899999999,39.728392],"type":"Point"}
}