{
  "type": "Feature",
  "properties": {
    "addr:full":"14089 Foothill Blvd Sylmar CA 91342",
    "addr:housenumber":"14089",
    "addr:postcode":"91342",
    "addr:street":"Foothill Blvd",
    "iso:country":"US",
    "sg:address":"14089 Foothill Blvd",
    "sg:city":"Sylmar",
    "sg:classifiers":[
        {
            "category":"Autos & Motor Vehicles",
            "subcategory":"Fuel & Gas Station",
            "type":"Retail Goods"
        }
    ],
    "sg:phone":"+1 818 367 4915",
    "sg:postcode":"91342",
    "sg:province":"CA",
    "sg:tags":[
        "oil"
    ],
    "wof:name":"Foothill Chevron",
    "wof:placetype":"venue"
},
  "geometry": {"coordinates":[-118.43802700000001,34.31308],"type":"Point"}
}