{
  "type": "Feature",
  "properties": {
    "iso:country":"US",
    "sg:address":"2472 Eastman Ave",
    "sg:city":"Ventura",
    "sg:classifiers":[
        {
            "category":"Building & Trades",
            "subcategory":"Construction",
            "type":"Services"
        }
    ],
    "sg:phone":"+1 805 643 4043",
    "sg:postcode":"93003",
    "sg:province":"CA",
    "sg:tags":[
        "consultant",
        "contractor"
    ],
    "sg:website":"http://johndonaldson.us/",
    "wof:name":"John Donaldson Construction",
    "wof:placetype":"venue"
},
  "geometry": {"coordinates":[-119.22984,34.251473],"type":"Point"}
}