{
  "type": "Feature",
  "properties": {
    "addr:full":"3033 Amigos Dr Burbank CA 91504",
    "addr:housenumber":"3033",
    "addr:postcode":"91504",
    "addr:street":"Amigos Dr",
    "iso:country":"US",
    "sg:address":"3033 Amigos Dr",
    "sg:city":"Burbank",
    "sg:classifiers":[
        {
            "category":"Banks & Credit Unions",
            "subcategory":"Bank",
            "type":"Services"
        }
    ],
    "sg:phone":"+1 818 731 9432",
    "sg:postcode":"91504",
    "sg:province":"CA",
    "wof:name":"Peter Szucs Industrial De",
    "wof:placetype":"venue"
},
  "geometry": {"coordinates":[-118.327927,34.209009],"type":"Point"}
}