{
  "type": "Feature",
  "properties": {
    "addr:full":"24953 Pso de Valencia Laguna Hills CA 92653",
    "addr:housenumber":"24953",
    "addr:postcode":"92653",
    "addr:street":"Pso De Valencia",
    "iso:country":"US",
    "sg:address":"24953 Pso de Valencia",
    "sg:city":"Laguna Hills",
    "sg:classifiers":[
        {
            "category":"Health Services",
            "subcategory":"Health Practitioner",
            "type":"Services"
        }
    ],
    "sg:phone":"+1 949 462 0195",
    "sg:postcode":"92653",
    "sg:province":"CA",
    "sg:tags":[
        "psychotherapist"
    ],
    "wof:name":"Pamela Esau",
    "wof:placetype":"venue"
},
  "geometry": {"coordinates":[-117.700293,33.593519],"type":"Point"}
}