{
  "type": "Feature",
  "properties": {
    "addr:full":"2635 N 1st Street San Jose CA 95134",
    "addr:housenumber":"2635",
    "addr:postcode":"95134",
    "addr:street":"N 1St Street",
    "iso:country":"US",
    "sg:address":"2635 N 1st Street",
    "sg:city":"San Jose",
    "sg:classifiers":[
        {
            "category":"Professional",
            "subcategory":"Employment Agencies",
            "type":"Services"
        }
    ],
    "sg:phone":"+1 408 570 0750",
    "sg:postcode":"95134",
    "sg:province":"CA",
    "wof:name":"Superior Staffing Services",
    "wof:placetype":"venue"
},
  "geometry": {"coordinates":[-121.928605,37.386931],"type":"Point"}
}