{
  "type": "Feature",
  "properties": {
    "addr:full":"500 Genesee Indian Creek Rd Taylorsville CA 95983",
    "addr:housenumber":"500",
    "addr:postcode":"95983",
    "addr:street":"Genesee Indian Creek Rd",
    "iso:country":"US",
    "sg:address":"500 Genesee Indian Creek Rd",
    "sg:city":"Taylorsville",
    "sg:classifiers":[
        {
            "category":"Building & Trades",
            "subcategory":"Landscaping Services",
            "type":"Services"
        }
    ],
    "sg:phone":"+1 530 284 4848",
    "sg:postcode":"95983",
    "sg:province":"CA",
    "sg:tags":[
        "lawn"
    ],
    "wof:name":"Rock Hound Landscaping",
    "wof:placetype":"venue"
},
  "geometry": {"coordinates":[-120.645867,40.09274],"type":"Point"}
}