{
  "type": "Feature",
  "properties": {
    "addr:full":"27753 Ruisenor Mission Viejo CA 92692",
    "addr:postcode":"27753;92692",
    "addr:street":"Ruisenor",
    "iso:country":"US",
    "sg:address":"27753 Ruisenor",
    "sg:city":"Mission Viejo",
    "sg:classifiers":[
        {
            "category":"Professional",
            "type":"Services"
        }
    ],
    "sg:phone":"+1 949 699 2579",
    "sg:postcode":"92692",
    "sg:province":"CA",
    "wof:name":"Ameriscapes",
    "wof:placetype":"venue"
},
  "geometry": {"coordinates":[-117.646795,33.600251],"type":"Point"}
}