{
  "type": "Feature",
  "properties": {
    "iso:country":"US",
    "sg:address":"2222 S Chester Ave",
    "sg:city":"Bakersfield",
    "sg:classifiers":[
        {
            "category":"Health Services",
            "subcategory":"Chiropractor",
            "type":"Services"
        }
    ],
    "sg:phone":"+1 661 397 5256",
    "sg:postcode":"93304",
    "sg:province":"CA",
    "wof:name":"Safari Chiropractic Inc",
    "wof:placetype":"venue"
},
  "geometry": {"coordinates":[-119.015551,35.334732],"type":"Point"}
}