{
  "type": "Feature",
  "properties": {
    "iso:country":"US",
    "sg:address":"10959 Rochester Ave",
    "sg:city":"Los Angeles",
    "sg:classifiers":[
        {
            "category":"Real Estate",
            "subcategory":"Real Estate Operator",
            "type":"Services"
        }
    ],
    "sg:phone":"+1 310 312 9082",
    "sg:postcode":"90024",
    "sg:province":"CA",
    "sg:tags":[
        "apartment"
    ],
    "wof:name":"Rochester Apartments",
    "wof:placetype":"venue"
},
  "geometry": {"coordinates":[-118.445459,34.055426],"type":"Point"}
}