{
  "type": "Feature",
  "properties": {
    "addr:full":"965 W Macarthur Blvd Oakland CA 94608",
    "addr:housenumber":"965",
    "addr:postcode":"94608",
    "addr:street":"W Macarthur Blvd",
    "iso:country":"US",
    "sg:address":"965 W Macarthur Blvd",
    "sg:city":"Oakland",
    "sg:classifiers":[
        {
            "category":"Autos & Motor Vehicles",
            "subcategory":"Automobile Sales",
            "type":"Retail Goods"
        },
        {
            "category":"Taxi",
            "type":"Transportation"
        }
    ],
    "sg:phone":"+1 510 355 5555",
    "sg:postcode":"94608",
    "sg:province":"CA",
    "sg:tags":[
        "limo"
    ],
    "wof:name":"Yellow Taxi",
    "wof:placetype":"venue"
},
  "geometry": {"coordinates":[-122.27758,37.828316],"type":"Point"}
}