{
  "type": "Feature",
  "properties": {
    "addr:full":"37 E 3rd Ave San Mateo CA 94401",
    "addr:housenumber":"37",
    "addr:postcode":"94401",
    "addr:street":"E 3Rd Ave",
    "iso:country":"US",
    "sg:address":"37 E 3rd Ave",
    "sg:city":"San Mateo",
    "sg:classifiers":[
        {
            "category":"Personal",
            "subcategory":"Skin Care",
            "type":"Services"
        }
    ],
    "sg:phone":"+1 650 867 1108",
    "sg:postcode":"94401",
    "sg:province":"CA",
    "wof:name":"Yan's Skin Care",
    "wof:placetype":"venue"
},
  "geometry": {"coordinates":[-122.325293,37.563522],"type":"Point"}
}