{
  "type": "Feature",
  "properties": {
    "iso:country":"US",
    "sg:address":"16065 Surprise Ln",
    "sg:city":"Huntington Beach",
    "sg:classifiers":[
        {
            "category":"Professional",
            "type":"Services"
        }
    ],
    "sg:phone":"+1 714 305 4824",
    "sg:postcode":"92649",
    "sg:province":"CA",
    "wof:name":"Ghoward",
    "wof:placetype":"venue"
},
  "geometry": {"coordinates":[-118.068792,33.729384],"type":"Point"}
}