{
  "type": "Feature",
  "properties": {
    "addr:full":"4820 S Eastern Ave Ste M Commerce CA 90040",
    "addr:housenumber":"4820",
    "addr:postcode":"90040",
    "addr:street":"S Eastern Ave Ste M",
    "iso:country":"US",
    "sg:address":"4820 S Eastern Ave Ste M",
    "sg:city":"Commerce",
    "sg:classifiers":[
        {
            "category":"Shopping",
            "subcategory":"Florist",
            "type":"Retail Goods"
        }
    ],
    "sg:phone":"+1 323 888 8686",
    "sg:postcode":"90040",
    "sg:province":"CA",
    "sg:website":"www.robinsonsflowershop.com",
    "wof:name":"Robinson's Flower Shop",
    "wof:placetype":"venue"
},
  "geometry": {"coordinates":[-118.160752,33.990441],"type":"Point"}
}