{
  "type": "Feature",
  "properties": {
    "iso:country":"US",
    "sg:address":"14946 Crenshw Blvd",
    "sg:city":"Gardena",
    "sg:classifiers":[
        {
            "category":"Personal",
            "subcategory":"Beauty Salon",
            "type":"Services"
        }
    ],
    "sg:phone":"+1 310 324 9100",
    "sg:postcode":"90249",
    "sg:province":"CA",
    "sg:tags":[
        "hair"
    ],
    "wof:name":"Diva Style Hair Weaving",
    "wof:placetype":"venue"
},
  "geometry": {"coordinates":[-118.32607299999999,33.896115],"type":"Point"}
}