{
  "type": "Feature",
  "properties": {
    "iso:country":"US",
    "sg:address":"1679 Centurion Dr",
    "sg:city":"Santa Rosa",
    "sg:classifiers":[
        {
            "category":"Insurance",
            "subcategory":"Insurance Agent",
            "type":"Services"
        }
    ],
    "sg:phone":"+1 707 578 4549",
    "sg:postcode":"95403",
    "sg:province":"CA",
    "wof:name":"Joyce Distributing Co",
    "wof:placetype":"venue"
},
  "geometry": {"coordinates":[-122.76303,38.450978],"type":"Point"}
}