{
  "type": "Feature",
  "properties": {
    "addr:full":"100 California St San Francisco CA 94111",
    "addr:housenumber":"100",
    "addr:postcode":"94111",
    "addr:street":"California St",
    "iso:country":"US",
    "sg:address":"100 California St",
    "sg:city":"San Francisco",
    "sg:classifiers":[
        {
            "category":"Education",
            "subcategory":"Special Training",
            "type":"Public Place"
        }
    ],
    "sg:phone":"+1 415 986 6356",
    "sg:postcode":"94111",
    "sg:province":"CA",
    "sg:tags":[
        "school",
        "specialty"
    ],
    "sg:website":"www.ieatraining.com",
    "wof:name":"Insurance Educational Association",
    "wof:placetype":"venue"
},
  "geometry": {"coordinates":[-122.39758,37.793525],"type":"Point"}
}