{
  "type": "Feature",
  "properties": {
    "addr:full":"109 S Alisos St Santa Barbara CA 93103",
    "addr:housenumber":"109",
    "addr:postcode":"93103",
    "addr:street":"S Alisos St",
    "iso:country":"US",
    "sg:address":"109 S Alisos St",
    "sg:city":"Santa Barbara",
    "sg:classifiers":[
        {
            "category":"Building & Trades",
            "subcategory":"Landscaping Services",
            "type":"Services"
        }
    ],
    "sg:phone":"+1 805 963 2899",
    "sg:postcode":"93103",
    "sg:province":"CA",
    "sg:tags":[
        "lawn",
        "maintenance",
        "grounds"
    ],
    "wof:name":"Gabriel's Gardening",
    "wof:placetype":"venue"
},
  "geometry": {"coordinates":[-119.675251,34.420926],"type":"Point"}
}