{
  "type": "Feature",
  "properties": {
    "addr:full":"3075 Woods Way San Jose CA 95148",
    "addr:housenumber":"3075",
    "addr:postcode":"95148",
    "addr:street":"Woods Way",
    "iso:country":"US",
    "sg:address":"3075 Woods Way",
    "sg:city":"San Jose",
    "sg:classifiers":[
        {
            "category":"Communications",
            "type":"Services"
        }
    ],
    "sg:phone":"+1 408 238 6049",
    "sg:postcode":"95148",
    "sg:province":"CA",
    "sg:tags":[
        "communication"
    ],
    "wof:name":"Malto Media",
    "wof:placetype":"venue"
},
  "geometry": {"coordinates":[-121.794607,37.327391],"type":"Point"}
}