{
  "type": "Feature",
  "properties": {
    "addr:full":"470 Bell St East Palo Alto CA 94303",
    "addr:housenumber":"470",
    "addr:postcode":"94303",
    "addr:street":"Bell St",
    "iso:country":"US",
    "sg:address":"470 Bell St",
    "sg:city":"East Palo Alto",
    "sg:classifiers":[
        {
            "category":"Professional",
            "subcategory":"Management & Consulting",
            "type":"Services"
        }
    ],
    "sg:phone":"+1 650 323 4477",
    "sg:postcode":"94303",
    "sg:province":"CA",
    "sg:tags":[
        "party",
        "planning"
    ],
    "wof:name":"Jatelo Productions",
    "wof:placetype":"venue"
},
  "geometry": {"coordinates":[-122.144901,37.4658],"type":"Point"}
}