{
  "type": "Feature",
  "properties": {
    "addr:full":"2500 Sycamore Dr Antioch CA 94509",
    "addr:housenumber":"2500",
    "addr:postcode":"ca 94509",
    "addr:street":"Sycamore Dr",
    "iso:country":"US",
    "sg:address":"2500 Sycamore Dr",
    "sg:city":"Antioch",
    "sg:classifiers":[
        {
            "category":"Health Services",
            "subcategory":"Dentist",
            "type":"Services"
        }
    ],
    "sg:phone":"+1 866 937 9556",
    "sg:postcode":"94509",
    "sg:province":"CA",
    "sg:tags":[
        "dentists-endodontists",
        "dentists-cosmetic",
        "dentists-pediatric",
        "dentistry"
    ],
    "sg:website":"http://www-westerndental-com.netsolads.com/?_nsag=34839",
    "wof:name":"Western Dental Centers",
    "wof:placetype":"venue"
},
  "geometry": {"coordinates":[-121.83399300000001,38.006329],"type":"Point"}
}