{
  "type": "Feature",
  "properties": {
    "iso:country":"US",
    "sg:address":"20488 Stevens Creek Blvd",
    "sg:city":"Cupertino",
    "sg:classifiers":[
        {
            "category":"Real Estate",
            "subcategory":"Architect",
            "type":"Services"
        }
    ],
    "sg:phone":"+1 408 255 5851",
    "sg:postcode":"95014",
    "sg:province":"CA",
    "sg:tags":[
        "estimate",
        "construction"
    ],
    "wof:name":"Daniel Silverie III Inc",
    "wof:placetype":"venue"
},
  "geometry": {"coordinates":[-122.027869,37.322764],"type":"Point"}
}