{
  "type": "Feature",
  "properties": {
    "iso:country":"US",
    "sg:address":"1801 Tully Rd Ste A1",
    "sg:city":"Modesto",
    "sg:classifiers":[
        {
            "category":"Real Estate",
            "subcategory":"Real Estate Agent",
            "type":"Services"
        }
    ],
    "sg:phone":"+1 209 524 2200",
    "sg:postcode":"95350",
    "sg:province":"CA",
    "wof:name":"Royal Realty",
    "wof:placetype":"venue"
},
  "geometry": {"coordinates":[-121.012253,37.670471],"type":"Point"}
}