{
  "type": "Feature",
  "properties": {
    "addr:full":"4370 Gill Village Way San Diego CA 92108",
    "addr:housenumber":"4370",
    "addr:postcode":"92108",
    "addr:street":"Gill Village Way",
    "iso:country":"US",
    "sg:address":"4370 Gill Village Way",
    "sg:city":"San Diego",
    "sg:classifiers":[
        {
            "category":"Manufacturing",
            "subcategory":"Tools & Machinery",
            "type":"Manufacturing & Wholesale Goods"
        }
    ],
    "sg:phone":"+1 858 546 4717",
    "sg:postcode":"92108",
    "sg:province":"CA",
    "sg:tags":[
        "mfg",
        "care",
        "eye",
        "supply"
    ],
    "wof:name":"Eyedx Inc",
    "wof:placetype":"venue"
},
  "geometry": {"coordinates":[-117.147019,32.774971],"type":"Point"}
}