{
  "type": "Feature",
  "properties": {
    "addr:full":"1677 Coraltree Pl San Jose CA 95131",
    "addr:housenumber":"1677",
    "addr:postcode":"95131",
    "addr:street":"Coraltree Pl",
    "iso:country":"US",
    "sg:address":"1677 Coraltree Pl",
    "sg:city":"San Jose",
    "sg:classifiers":[
        {
            "category":"Organizations",
            "subcategory":"Membership Organization",
            "type":"Services"
        }
    ],
    "sg:phone":"+1 408 926 6520",
    "sg:postcode":"95131",
    "sg:province":"CA",
    "wof:name":"National Council-Negro Women",
    "wof:placetype":"venue"
},
  "geometry": {"coordinates":[-121.87844699999999,37.393864],"type":"Point"}
}