{
  "type": "Feature",
  "properties": {
    "addr:full":"482 Pier T Ave Long Beach CA 90802",
    "addr:housenumber":"482",
    "addr:postcode":"90802",
    "addr:street":"Pier T Ave",
    "iso:country":"US",
    "sg:address":"482 Pier T Ave",
    "sg:city":"Long Beach",
    "sg:classifiers":[
        {
            "category":"Wholesale",
            "subcategory":"Scrap",
            "type":"Manufacturing & Wholesale Goods"
        },
        {
            "category":"Wholesale",
            "subcategory":"Metals & Minerals",
            "type":"Manufacturing & Wholesale Goods"
        }
    ],
    "sg:phone":"+1 562 628 8132",
    "sg:postcode":"90802",
    "sg:province":"CA",
    "sg:tags":[
        "a",
        "distributor",
        "operate",
        "ex"
    ],
    "sg:website":"www.pacificr.com",
    "wof:name":"Pacific Coast Recycling LLC",
    "wof:placetype":"venue"
},
  "geometry": {"coordinates":[-118.22362,33.757575],"type":"Point"}
}