{
  "type": "Feature",
  "properties": {
    "iso:country":"US",
    "sg:address":"979 Olympic Way",
    "sg:city":"Nipomo",
    "sg:classifiers":[
        {
            "category":"Wholesale",
            "subcategory":"Electrical",
            "type":"Manufacturing & Wholesale Goods"
        }
    ],
    "sg:phone":"+1 805 929 2318",
    "sg:postcode":"93444",
    "sg:province":"CA",
    "sg:tags":[
        "circuit"
    ],
    "wof:name":"Logic Art PC Design",
    "wof:placetype":"venue"
},
  "geometry": {"coordinates":[-120.51452999999999,35.036849],"type":"Point"}
}