{
  "type": "Feature",
  "properties": {
    "addr:full":"472 Main St Murphys CA 95247",
    "addr:housenumber":"472",
    "addr:postcode":"95247",
    "addr:street":"Main St",
    "iso:country":"US",
    "sg:address":"472 Main St",
    "sg:city":"Murphys",
    "sg:classifiers":[
        {
            "category":"Professional",
            "type":"Services"
        }
    ],
    "sg:phone":"+1 209 728 8039",
    "sg:postcode":"95247",
    "sg:province":"CA",
    "sg:tags":[
        "arts",
        "artist"
    ],
    "wof:name":"B R Garvin Artist Studio",
    "wof:placetype":"venue"
},
  "geometry": {"coordinates":[-120.467653,38.13798],"type":"Point"}
}