{
  "type": "Feature",
  "properties": {
    "addr:full":"1664 Main St Ramona CA 92065",
    "addr:housenumber":"1664",
    "addr:postcode":"92065",
    "addr:street":"Main St",
    "iso:country":"US",
    "sg:address":"1664 Main St",
    "sg:city":"Ramona",
    "sg:classifiers":[
        {
            "category":"Restaurant",
            "type":"Food & Drink"
        }
    ],
    "sg:menulink":"http://www.allmenus.com/ca/ramona/7264-rubios/menu/",
    "sg:phone":"+1 760 788 9004",
    "sg:postcode":"92065",
    "sg:province":"CA",
    "sg:tags":[
        "seafood",
        "mexican",
        "american"
    ],
    "wof:name":"Rubio's",
    "wof:placetype":"venue"
},
  "geometry": {"coordinates":[-116.878681,33.036203],"type":"Point"}
}