{
  "type": "Feature",
  "properties": {
    "addr:full":"1543 E Palmdale Blvd Palmdale CA 93550",
    "addr:housenumber":"1543",
    "addr:postcode":"ca 93550",
    "addr:street":"E Palmdale Blvd",
    "iso:country":"US",
    "sg:address":"1543 E Palmdale Blvd",
    "sg:city":"Palmdale",
    "sg:classifiers":[
        {
            "category":"Local Transit",
            "type":"Transportation"
        }
    ],
    "sg:phone":"+1 661 265 8537",
    "sg:postcode":"93550",
    "sg:province":"CA",
    "sg:tags":[
        "bus",
        "line"
    ],
    "wof:name":"Coach USA-Southern Ca",
    "wof:placetype":"venue"
},
  "geometry": {"coordinates":[-118.10229099999999,34.579706],"type":"Point"}
}