{
  "type": "Feature",
  "properties": {
    "addr:full":"1127 W Eucalyptus Ct Ontario CA 91762",
    "addr:housenumber":"1127",
    "addr:postcode":"91762",
    "addr:street":"W Eucalyptus Ct",
    "iso:country":"US",
    "sg:address":"1127 W Eucalyptus Ct",
    "sg:city":"Ontario",
    "sg:classifiers":[
        {
            "category":"Building & Trades",
            "subcategory":"Cleaning & Sanitation",
            "type":"Services"
        }
    ],
    "sg:phone":"+1 909 732 7195",
    "sg:postcode":"91762",
    "sg:province":"CA",
    "sg:tags":[
        "window"
    ],
    "wof:name":"English Window Cleaner",
    "wof:placetype":"venue"
},
  "geometry": {"coordinates":[-117.67100000000001,34.045754],"type":"Point"}
}