{
  "type": "Feature",
  "properties": {
    "addr:full":"4058 51st St San Diego CA 92105",
    "addr:housenumber":"4058",
    "addr:postcode":"92105",
    "addr:street":"51St St",
    "iso:country":"US",
    "sg:address":"4058 51st St",
    "sg:city":"San Diego",
    "sg:classifiers":[
        {
            "category":"Real Estate",
            "subcategory":"Real Estate Operator",
            "type":"Services"
        }
    ],
    "sg:phone":"+1 619 584 4584",
    "sg:postcode":"92105",
    "sg:province":"CA",
    "sg:tags":[
        "apartment"
    ],
    "wof:name":"51st Apartments",
    "wof:placetype":"venue"
},
  "geometry": {"coordinates":[-117.08457900000001,32.750578],"type":"Point"}
}