{
  "type": "Feature",
  "properties": {
    "addr:full":"310 W 1st St Tustin CA 92780",
    "addr:housenumber":"310",
    "addr:postcode":"92780",
    "addr:street":"W 1St St",
    "iso:country":"US",
    "sg:address":"310 W 1st St",
    "sg:city":"Tustin",
    "sg:classifiers":[
        {
            "category":"Professional",
            "subcategory":"Lawyer & Legal Services",
            "type":"Services"
        }
    ],
    "sg:phone":"+1 714 505 0200",
    "sg:postcode":"92780",
    "sg:province":"CA",
    "wof:name":"Gray Danil P Wtts Gry & Mtchll Wlr Llp Lw Offcs of",
    "wof:placetype":"venue"
},
  "geometry": {"coordinates":[-117.825996,33.7458],"type":"Point"}
}