{
  "type": "Feature",
  "properties": {
    "addr:full":"3725 Old Conejo Rd Newbury Park CA 91320",
    "addr:housenumber":"3725",
    "addr:postcode":"91320",
    "addr:street":"Old Conejo Rd",
    "iso:country":"US",
    "sg:address":"3725 Old Conejo Rd",
    "sg:city":"Newbury Park",
    "sg:classifiers":[
        {
            "category":"Wholesale",
            "subcategory":"Durable Goods & Equipment",
            "type":"Manufacturing & Wholesale Goods"
        }
    ],
    "sg:phone":"+1 805 480 1188",
    "sg:postcode":"91320",
    "sg:province":"CA",
    "sg:tags":[
        "importer"
    ],
    "wof:name":"Birchfield Design Group",
    "wof:placetype":"venue"
},
  "geometry": {"coordinates":[-118.95662400000001,34.192589],"type":"Point"}
}