{
  "type": "Feature",
  "properties": {
    "iso:country":"US",
    "sg:address":"31 Buena Vis",
    "sg:city":"Benicia",
    "sg:classifiers":[
        {
            "category":"Building & Trades",
            "subcategory":"Landscaping Services",
            "type":"Services"
        },
        {
            "category":"Manufacturing",
            "subcategory":"Paper Products",
            "type":"Manufacturing & Wholesale Goods"
        }
    ],
    "sg:phone":"+1 707 748 7591",
    "sg:postcode":"94510",
    "sg:province":"CA",
    "sg:tags":[
        "lawn",
        "bamboo"
    ],
    "wof:name":"Greenprints Landscape",
    "wof:placetype":"venue"
},
  "geometry": {"coordinates":[-122.165875,38.061157],"type":"Point"}
}