{
  "type": "Feature",
  "properties": {
    "iso:country":"US",
    "sg:address":"2635 S Western Avenue",
    "sg:city":"Los Angeles",
    "sg:classifiers":[
        {
            "category":"Real Estate",
            "subcategory":"Real Estate Operator",
            "type":"Services"
        }
    ],
    "sg:phone":"+1 323 734 9986",
    "sg:postcode":"90018",
    "sg:province":"CA",
    "sg:tags":[
        "apartment"
    ],
    "wof:name":"Adams West Senior Citizens Apartments",
    "wof:placetype":"venue"
},
  "geometry": {"coordinates":[-118.308978,34.031454],"type":"Point"}
}