{
  "type": "Feature",
  "properties": {
    "iso:country":"US",
    "sg:address":"5440 Fig Rd",
    "sg:city":"Manteca",
    "sg:classifiers":[
        {
            "category":"Building & Trades",
            "subcategory":"Construction",
            "type":"Services"
        }
    ],
    "sg:phone":"+1 209 824 2485",
    "sg:postcode":"95337",
    "sg:province":"CA",
    "sg:tags":[
        "heavy"
    ],
    "wof:name":"Wadco Trenching Service",
    "wof:placetype":"venue"
},
  "geometry": {"coordinates":[-121.236489,37.762123],"type":"Point"}
}