{
  "type": "Feature",
  "properties": {
    "iso:country":"US",
    "sg:address":"12 S 1st Street",
    "sg:city":"San Jose",
    "sg:classifiers":[
        {
            "category":"Professional",
            "subcategory":"Computer Services",
            "type":"Services"
        }
    ],
    "sg:phone":"+1 408 297 7772",
    "sg:postcode":"95113",
    "sg:province":"CA",
    "sg:tags":[
        "repair"
    ],
    "wof:name":"Computer Services Group",
    "wof:placetype":"venue"
},
  "geometry": {"coordinates":[-121.890342,37.335978],"type":"Point"}
}