{
  "type": "Feature",
  "properties": {
    "addr:full":"3140 Alpine Rd Portola Valley CA 94028",
    "addr:housenumber":"3140",
    "addr:postcode":"94028",
    "addr:street":"Alpine Rd",
    "iso:country":"US",
    "sg:address":"3140 Alpine Rd",
    "sg:city":"Portola Valley",
    "sg:classifiers":[
        {
            "category":"Personal",
            "subcategory":"Beauty Salon",
            "type":"Services"
        }
    ],
    "sg:phone":"+1 650 851 2726",
    "sg:postcode":"94028",
    "sg:province":"CA",
    "wof:name":"Razor's Edge",
    "wof:placetype":"venue"
},
  "geometry": {"coordinates":[-122.192672,37.402338],"type":"Point"}
}