{
  "type": "Feature",
  "properties": {
    "addr:full":"6931 Olive Grove Dr Orangevale CA 95662",
    "addr:housenumber":"6931",
    "addr:postcode":"95662",
    "addr:street":"Olive Grove Dr",
    "iso:country":"US",
    "sg:address":"6931 Olive Grove Dr",
    "sg:city":"Orangevale",
    "sg:classifiers":[
        {
            "category":"Restaurant",
            "type":"Food & Drink"
        }
    ],
    "sg:phone":"+1 916 987 8679",
    "sg:postcode":"95662",
    "sg:province":"CA",
    "wof:name":"Jack In The Box",
    "wof:placetype":"venue"
},
  "geometry": {"coordinates":[-121.212762,38.69218],"type":"Point"}
}