{
  "type": "Feature",
  "properties": {
    "addr:full":"3008 Dow Ave Redondo Beach CA 90278",
    "addr:housenumber":"3008",
    "addr:postcode":"90278",
    "addr:street":"Dow Ave",
    "iso:country":"US",
    "sg:address":"3008 Dow Ave",
    "sg:city":"Redondo Beach",
    "sg:classifiers":[
        {
            "category":"Shopping",
            "subcategory":"Bicycles & Sporting Goods",
            "type":"Retail Goods"
        }
    ],
    "sg:phone":"+1 310 371 7726",
    "sg:postcode":"90278",
    "sg:province":"CA",
    "wof:name":"West Coast Guns",
    "wof:placetype":"venue"
},
  "geometry": {"coordinates":[-118.366178,33.882822],"type":"Point"}
}