{
  "type": "Feature",
  "properties": {
    "iso:country":"US",
    "sg:address":"2658 1/2 Montrose Ave",
    "sg:city":"Montrose",
    "sg:classifiers":[
        {
            "category":"Local Transit",
            "type":"Transportation"
        }
    ],
    "sg:phone":"+1 818 248 9897",
    "sg:postcode":"91020",
    "sg:province":"CA",
    "sg:tags":[
        "shuttle"
    ],
    "wof:name":"Bhls",
    "wof:placetype":"venue"
},
  "geometry": {"coordinates":[-118.23656699999999,34.213871],"type":"Point"}
}