{
  "type": "Feature",
  "properties": {
    "iso:country":"US",
    "sg:address":"3284 Sweet Dr",
    "sg:city":"Lafayette",
    "sg:classifiers":[
        {
            "category":"Building & Trades",
            "subcategory":"Landscaping Services",
            "type":"Services"
        }
    ],
    "sg:phone":"+1 925 937 7240",
    "sg:postcode":"94549",
    "sg:province":"CA",
    "sg:tags":[
        "stump",
        "grinding"
    ],
    "wof:name":"Eager Beaver Stump Service",
    "wof:placetype":"venue"
},
  "geometry": {"coordinates":[-122.104761,37.876369],"type":"Point"}
}