{
  "type": "Feature",
  "properties": {
    "iso:country":"US",
    "sg:address":"2028 Leafwood Pl",
    "sg:city":"Encinitas",
    "sg:classifiers":[
        {
            "category":"Shopping",
            "type":"Retail Goods"
        }
    ],
    "sg:phone":"+1 760 944 1720",
    "sg:postcode":"92024",
    "sg:province":"CA",
    "sg:tags":[
        "merchandise"
    ],
    "wof:name":"Pet Steps",
    "wof:placetype":"venue"
},
  "geometry": {"coordinates":[-117.24193,33.05281],"type":"Point"}
}