{
  "type": "Feature",
  "properties": {
    "addr:full":"1715 Lundy Avenue San Jose CA 95131",
    "addr:housenumber":"1715",
    "addr:postcode":"95131",
    "addr:street":"Lundy Avenue",
    "iso:country":"US",
    "sg:address":"1715 Lundy Avenue",
    "sg:city":"San Jose",
    "sg:classifiers":[
        {
            "category":"Banks & Credit Unions",
            "subcategory":"Investment Brokerage",
            "type":"Services"
        }
    ],
    "sg:phone":"+1 408 441 1888",
    "sg:postcode":"95131",
    "sg:province":"CA",
    "sg:tags":[
        "investing"
    ],
    "wof:name":"Ucb Investment Services",
    "wof:placetype":"venue"
},
  "geometry": {"coordinates":[-121.88813399999999,37.389673],"type":"Point"}
}