{
  "type": "Feature",
  "properties": {
    "iso:country":"US",
    "sg:address":"12812 Garden Grove Blvd",
    "sg:city":"Garden Grove",
    "sg:classifiers":[
        {
            "category":"Arts & Performance",
            "subcategory":"Arts Center",
            "type":"Entertainment"
        }
    ],
    "sg:phone":"+1 714 638 0058",
    "sg:postcode":"92843",
    "sg:province":"CA",
    "sg:tags":[
        "performing"
    ],
    "wof:name":"Cedarbrook Dance Center",
    "wof:placetype":"venue"
},
  "geometry": {"coordinates":[-117.909351,33.774212],"type":"Point"}
}