{
  "type": "Feature",
  "properties": {
    "addr:full":"301 E 4th St Los Angeles CA 90013",
    "addr:housenumber":"301",
    "addr:postcode":"90013",
    "addr:street":"E 4Th St",
    "iso:country":"US",
    "sg:address":"301 E 4th St",
    "sg:city":"Los Angeles",
    "sg:classifiers":[
        {
            "category":"Wholesale",
            "subcategory":"Apparel",
            "type":"Manufacturing & Wholesale Goods"
        },
        {
            "category":"Wholesale",
            "subcategory":"Non-durable Goods",
            "type":"Manufacturing & Wholesale Goods"
        }
    ],
    "sg:phone":"+1 213 928 0818",
    "sg:postcode":"90013",
    "sg:province":"CA",
    "sg:tags":[
        "cap"
    ],
    "wof:name":"Cap World",
    "wof:placetype":"venue"
},
  "geometry": {"coordinates":[-118.243002,34.045843],"type":"Point"}
}