{
  "type": "Feature",
  "properties": {
    "addr:full":"2529 S Valencia Ave Ontario CA 91761",
    "addr:housenumber":"2529",
    "addr:postcode":"91761",
    "addr:street":"S Valencia Ave",
    "iso:country":"US",
    "sg:address":"2529 S Valencia Ave",
    "sg:city":"Ontario",
    "sg:classifiers":[
        {
            "category":"Professional",
            "subcategory":"Management & Consulting",
            "type":"Services"
        }
    ],
    "sg:phone":"+1 909 947 8403",
    "sg:postcode":"91761",
    "sg:province":"CA",
    "sg:tags":[
        "consultant"
    ],
    "wof:name":"Advantage Consulting",
    "wof:placetype":"venue"
},
  "geometry": {"coordinates":[-117.609787,34.027561],"type":"Point"}
}