{
  "type": "Feature",
  "properties": {
    "iso:country":"US",
    "sg:address":"1426 Saint Kitts Ln",
    "sg:city":"San Mateo",
    "sg:classifiers":[
        {
            "category":"Wholesale",
            "subcategory":"Groceries",
            "type":"Manufacturing & Wholesale Goods"
        }
    ],
    "sg:phone":"+1 650 341 4314",
    "sg:postcode":"94404",
    "sg:province":"CA",
    "wof:name":"Barbara Rosenberg Dist Ba",
    "wof:placetype":"venue"
},
  "geometry": {"coordinates":[-122.262764,37.537761],"type":"Point"}
}