{
  "type": "Feature",
  "properties": {
    "iso:country":"US",
    "sg:address":"2355 Tapo St",
    "sg:city":"Simi Valley",
    "sg:classifiers":[
        {
            "category":"Shopping",
            "type":"Retail Goods"
        }
    ],
    "sg:phone":"+1 805 520 3555",
    "sg:postcode":"93063",
    "sg:province":"CA",
    "sg:tags":[
        "equipment",
        "care",
        "health",
        "home"
    ],
    "wof:name":"Hi Med Supply Co Inc",
    "wof:placetype":"venue"
},
  "geometry": {"coordinates":[-118.70901600000001,34.277101],"type":"Point"}
}