{
  "type": "Feature",
  "properties": {
    "iso:country":"US",
    "sg:address":"14623 E 14th St",
    "sg:city":"San Leandro",
    "sg:classifiers":[
        {
            "category":"Personal",
            "subcategory":"Beauty Salon",
            "type":"Services"
        }
    ],
    "sg:phone":"+1 510 351 4272",
    "sg:postcode":"94578",
    "sg:province":"CA",
    "sg:tags":[
        "hair"
    ],
    "wof:name":"Effie's & Maria's Hair Design",
    "wof:placetype":"venue"
},
  "geometry": {"coordinates":[-122.135002,37.709599],"type":"Point"}
}