{
  "type": "Feature",
  "properties": {
    "addr:full":"1106 South St Corning CA 96021",
    "addr:housenumber":"1106",
    "addr:postcode":"96021",
    "addr:street":"South St",
    "iso:country":"US",
    "sg:address":"1106 South St",
    "sg:city":"Corning",
    "sg:classifiers":[
        {
            "category":"Retail",
            "subcategory":"Animal Services",
            "type":"Services"
        }
    ],
    "sg:phone":"+1 530 824 8186",
    "sg:postcode":"96021",
    "sg:province":"CA",
    "wof:name":"Pretty Paws Dog Grooming",
    "wof:placetype":"venue"
},
  "geometry": {"coordinates":[-122.17966800000001,39.925907],"type":"Point"}
}