{
  "type": "Feature",
  "properties": {
    "addr:full":"20315 Nordhoff St Chatsworth CA 91311",
    "addr:housenumber":"20315",
    "addr:postcode":"91311",
    "addr:street":"Nordhoff St",
    "iso:country":"US",
    "sg:address":"20315 Nordhoff St",
    "sg:city":"Chatsworth",
    "sg:classifiers":[
        {
            "category":"Professional",
            "subcategory":"Accounting & Tax Preparation",
            "type":"Services"
        }
    ],
    "sg:phone":"+1 818 772 5550",
    "sg:postcode":"91311",
    "sg:province":"CA",
    "sg:tags":[
        "return",
        "filing"
    ],
    "wof:name":"Professional Tax Consultant",
    "wof:placetype":"venue"
},
  "geometry": {"coordinates":[-118.576307,34.231915],"type":"Point"}
}