{
  "type": "Feature",
  "properties": {
    "iso:country":"US",
    "sg:address":"8523 Jasper St",
    "sg:city":"Rancho Cucamonga",
    "sg:classifiers":[
        {
            "category":"Communications",
            "type":"Services"
        }
    ],
    "sg:phone":"+1 909 981 7832",
    "sg:postcode":"91730",
    "sg:province":"CA",
    "sg:tags":[
        "communication"
    ],
    "wof:name":"Igm Communications",
    "wof:placetype":"venue"
},
  "geometry": {"coordinates":[-117.62078,34.098897],"type":"Point"}
}