{
  "type": "Feature",
  "properties": {
    "iso:country":"US",
    "sg:address":"9457 Firestone Blvd",
    "sg:city":"Downey",
    "sg:classifiers":[
        {
            "category":"Home & Garden",
            "subcategory":"Furniture",
            "type":"Retail Goods"
        }
    ],
    "sg:phone":"+1 562 622 7020",
    "sg:postcode":"90241",
    "sg:province":"CA",
    "sg:tags":[
        "store"
    ],
    "wof:name":"A To Z Furniture Outlet",
    "wof:placetype":"venue"
},
  "geometry": {"coordinates":[-118.113998,33.930901],"type":"Point"}
}