{
  "type": "Feature",
  "properties": {
    "addr:full":"6120 S Figueroa St Los Angeles CA 90003",
    "addr:housenumber":"6120",
    "addr:postcode":"90003",
    "addr:street":"S Figueroa St",
    "iso:country":"US",
    "sg:address":"6120 S Figueroa St",
    "sg:city":"Los Angeles",
    "sg:classifiers":[
        {
            "category":"Shopping",
            "subcategory":"Gifts & Souvenirs",
            "type":"Retail Goods"
        }
    ],
    "sg:phone":"+1 323 752 5781",
    "sg:postcode":"90003",
    "sg:province":"CA",
    "sg:tags":[
        "party",
        "supply"
    ],
    "wof:name":"ISA Party Supplies",
    "wof:placetype":"venue"
},
  "geometry": {"coordinates":[-118.282589,33.983354],"type":"Point"}
}