{
  "type": "Feature",
  "properties": {
    "addr:full":"218 Castilian Ave Newbury Park CA 91320",
    "addr:housenumber":"218",
    "addr:postcode":"91320",
    "addr:street":"Castilian Ave",
    "iso:country":"US",
    "sg:address":"218 Castilian Ave",
    "sg:city":"Newbury Park",
    "sg:classifiers":[
        {
            "category":"Shopping",
            "subcategory":"Catalog Store",
            "type":"Retail Goods"
        }
    ],
    "sg:phone":"+1 805 499 1227",
    "sg:postcode":"91320",
    "sg:province":"CA",
    "sg:tags":[
        "mail",
        "house"
    ],
    "wof:name":"Minimus",
    "wof:placetype":"venue"
},
  "geometry": {"coordinates":[-118.902868,34.180637],"type":"Point"}
}