{
  "type": "Feature",
  "properties": {
    "iso:country":"US",
    "sg:address":"3465 Saviers Rd",
    "sg:city":"Oxnard",
    "sg:classifiers":[
        {
            "category":"Personal",
            "subcategory":"Beauty Salon",
            "type":"Services"
        }
    ],
    "sg:phone":"+1 805 483 4716",
    "sg:postcode":"93033",
    "sg:province":"CA",
    "wof:name":"Delia's Hair Design",
    "wof:placetype":"venue"
},
  "geometry": {"coordinates":[-119.177706,34.167667],"type":"Point"}
}