{
  "type": "Feature",
  "properties": {
    "addr:full":"1301 Clay St Oakland CA 94612",
    "addr:housenumber":"1301",
    "addr:postcode":"94612",
    "addr:street":"Clay St",
    "iso:country":"US",
    "sg:address":"1301 Clay St",
    "sg:city":"Oakland",
    "sg:classifiers":[
        {
            "category":"Government",
            "subcategory":"Post Office",
            "type":"Public Place"
        }
    ],
    "sg:phone":"+1 510 637 4347",
    "sg:postcode":"94612",
    "sg:province":"CA",
    "sg:website":"www.usps.gov",
    "wof:name":"US Post Office - Byron Rumford Station",
    "wof:placetype":"venue"
},
  "geometry": {"coordinates":[-122.27404199999999,37.804603],"type":"Point"}
}