{
  "type": "Feature",
  "properties": {
    "addr:full":"410 W Pico Blvd Los Angeles CA 90015",
    "addr:housenumber":"410",
    "addr:postcode":"90015",
    "addr:street":"W Pico Blvd",
    "iso:country":"US",
    "sg:address":"410 W Pico Blvd",
    "sg:city":"Los Angeles",
    "sg:classifiers":[
        {
            "category":"Manufacturing",
            "subcategory":"Apparel",
            "type":"Manufacturing & Wholesale Goods"
        }
    ],
    "sg:phone":"+1 213 746 6604",
    "sg:postcode":"90015",
    "sg:province":"CA",
    "sg:tags":[
        "clothing",
        "outerwear",
        "mfg"
    ],
    "wof:name":"KMC",
    "wof:placetype":"venue"
},
  "geometry": {"coordinates":[-118.265546,34.039363],"type":"Point"}
}