{
  "type": "Feature",
  "properties": {
    "iso:country":"US",
    "sg:address":"1917 S Vineyard Ave",
    "sg:city":"Ontario",
    "sg:classifiers":[
        {
            "category":"Shopping",
            "subcategory":"Gifts & Souvenirs",
            "type":"Retail Goods"
        },
        {
            "category":"Manufacturing",
            "subcategory":"Retail Goods",
            "type":"Manufacturing & Wholesale Goods"
        }
    ],
    "sg:phone":"+1 909 923 3885",
    "sg:postcode":"91761",
    "sg:province":"CA",
    "sg:tags":[
        "shop",
        "giftware's-wholesale",
        "manufacturer"
    ],
    "wof:name":"Annwin Corp",
    "wof:placetype":"venue"
},
  "geometry": {"coordinates":[-117.611013,34.039167],"type":"Point"}
}