{
  "type": "Feature",
  "properties": {
    "addr:full":"1325 Tehama St Redding CA 96001",
    "addr:housenumber":"1325",
    "addr:postcode":"96001",
    "addr:street":"Tehama St",
    "iso:country":"US",
    "sg:address":"1325 Tehama St",
    "sg:city":"Redding",
    "sg:classifiers":[
        {
            "category":"Recreation",
            "type":"Entertainment"
        }
    ],
    "sg:phone":"+1 530 246 7256",
    "sg:postcode":"96001",
    "sg:province":"CA",
    "sg:tags":[
        "instruction",
        "yoga"
    ],
    "sg:website":"www.nshouseofyoga.com",
    "wof:name":"Yoga Nancy Sutton's House",
    "wof:placetype":"venue"
},
  "geometry": {"coordinates":[-122.390342,40.585461],"type":"Point"}
}