{
  "type": "Feature",
  "properties": {
    "addr:full":"651 3rd Ave Chula Vista CA 91910",
    "addr:housenumber":"651",
    "addr:postcode":"91910",
    "addr:street":"3Rd Ave",
    "iso:country":"US",
    "sg:address":"651 3rd Ave",
    "sg:city":"Chula Vista",
    "sg:classifiers":[
        {
            "category":"Social Services",
            "type":"Services"
        }
    ],
    "sg:phone":"+1 619 422 0671",
    "sg:postcode":"91910",
    "sg:province":"CA",
    "sg:tags":[
        "senior",
        "citizen"
    ],
    "wof:name":"Angels At Work Inc",
    "wof:placetype":"venue"
},
  "geometry": {"coordinates":[-117.075064,32.629282],"type":"Point"}
}