{
  "type": "Feature",
  "properties": {
    "addr:full":"5621 Thornhill Drive Oakland CA 94611",
    "addr:housenumber":"5621",
    "addr:postcode":"ca 94611",
    "addr:street":"Thornhill Drive",
    "iso:country":"US",
    "sg:address":"5621 Thornhill Drive",
    "sg:city":"Oakland",
    "sg:classifiers":[
        {
            "category":"Real Estate",
            "subcategory":"Real Estate Services",
            "type":"Services"
        }
    ],
    "sg:phone":"+1 510 339 2010",
    "sg:postcode":"94611",
    "sg:province":"CA",
    "sg:website":"www.homecorealtors.com/index.html",
    "wof:name":"The Home Co. Realtors",
    "wof:placetype":"venue"
},
  "geometry": {"coordinates":[-122.214315,37.83328],"type":"Point"}
}