{
  "type": "Feature",
  "properties": {
    "addr:full":"3185 College Ave Berkeley CA 94705",
    "addr:housenumber":"3185",
    "addr:postcode":"94705",
    "addr:street":"College Ave",
    "iso:country":"US",
    "sg:address":"3185 College Ave",
    "sg:city":"Berkeley",
    "sg:classifiers":[
        {
            "category":"Food & Beverages",
            "subcategory":"Liquor & Beverages",
            "type":"Retail Goods"
        }
    ],
    "sg:phone":"+1 510 655 8584",
    "sg:postcode":"94705",
    "sg:province":"CA",
    "sg:tags":[
        "beer",
        "spirit",
        "wine"
    ],
    "wof:name":"College Avenue Wines, Spirits",
    "wof:placetype":"venue"
},
  "geometry": {"coordinates":[-122.2525,37.851657],"type":"Point"}
}