{
  "type": "Feature",
  "properties": {
    "addr:full":"40101 Monterey Ave Rancho Mirage CA 92270",
    "addr:housenumber":"40101",
    "addr:postcode":"92270",
    "addr:street":"Monterey Ave",
    "iso:country":"US",
    "sg:address":"40101 Monterey Ave",
    "sg:city":"Rancho Mirage",
    "sg:classifiers":[
        {
            "category":"Ice Cream",
            "type":"Food & Drink"
        }
    ],
    "sg:phone":"+1 760 340 0402",
    "sg:postcode":"92270",
    "sg:province":"CA",
    "sg:tags":[
        "frozen",
        "yogurt"
    ],
    "sg:website":"www.goldenspoon.com",
    "wof:name":"Golden Spoon",
    "wof:placetype":"venue"
},
  "geometry": {"coordinates":[-116.39264799999999,33.756294],"type":"Point"}
}