{
  "type": "Feature",
  "properties": {
    "addr:full":"1038 N Western Avenue Los Angeles CA 90029",
    "addr:housenumber":"1038",
    "addr:postcode":"90029",
    "addr:street":"N Western Avenue",
    "iso:country":"US",
    "sg:address":"1038 N Western Avenue",
    "sg:city":"Los Angeles",
    "sg:classifiers":[
        {
            "category":"Shopping",
            "subcategory":"Clothing, Apparel, & Fashions",
            "type":"Retail Goods"
        }
    ],
    "sg:phone":"+1 323 962 8277",
    "sg:postcode":"90029",
    "sg:province":"CA",
    "sg:tags":[
        "accessory",
        "clothing",
        "women's"
    ],
    "wof:name":"Agasi Fashions",
    "wof:placetype":"venue"
},
  "geometry": {"coordinates":[-118.309039,34.08958],"type":"Point"}
}