{
  "type": "Feature",
  "properties": {
    "addr:full":"1114 Fontes Ln Salinas CA 93907",
    "addr:housenumber":"1114",
    "addr:postcode":"93907",
    "addr:street":"Fontes Ln",
    "iso:country":"US",
    "sg:address":"1114 Fontes Ln",
    "sg:city":"Salinas",
    "sg:classifiers":[
        {
            "category":"Education",
            "subcategory":"School",
            "type":"Public Place"
        }
    ],
    "sg:phone":"+1 831 753 5615",
    "sg:postcode":"93907",
    "sg:province":"CA",
    "wof:name":"Boronda Elementary School",
    "wof:placetype":"venue"
},
  "geometry": {"coordinates":[-121.67654899999999,36.697381],"type":"Point"}
}