{
  "type": "Feature",
  "properties": {
    "iso:country":"US",
    "sg:address":"40712 Village Dr",
    "sg:city":"Big Bear Lake",
    "sg:classifiers":[
        {
            "category":"Insurance",
            "subcategory":"Insurance Agent",
            "type":"Services"
        }
    ],
    "sg:phone":"+1 909 878 4898",
    "sg:postcode":"92314",
    "sg:province":"CA",
    "wof:name":"Basic Health & Life",
    "wof:placetype":"venue"
},
  "geometry": {"coordinates":[-116.913673,34.239877],"type":"Point"}
}