{
  "type": "Feature",
  "properties": {
    "addr:full":"957 S Jenifer Ave Glendora CA 91740",
    "addr:housenumber":"957",
    "addr:postcode":"91740",
    "addr:street":"S Jenifer Ave",
    "iso:country":"US",
    "sg:address":"957 S Jenifer Ave",
    "sg:city":"Glendora",
    "sg:classifiers":[
        {
            "category":"Health Services",
            "subcategory":"Medical Lab",
            "type":"Services"
        }
    ],
    "sg:phone":"+1 626 914 0460",
    "sg:postcode":"91740",
    "sg:province":"CA",
    "sg:tags":[
        "laboratory"
    ],
    "wof:name":"Dallal Dental Laboratories",
    "wof:placetype":"venue"
},
  "geometry": {"coordinates":[-117.867695,34.122752],"type":"Point"}
}