{
  "type": "Feature",
  "properties": {
    "iso:country":"US",
    "sg:address":"14721 Magnolia Blvd",
    "sg:city":"Sherman Oaks",
    "sg:classifiers":[
        {
            "category":"Shopping",
            "subcategory":"Luggage & Leather Goods",
            "type":"Retail Goods"
        }
    ],
    "sg:phone":"+1 818 907 9484",
    "sg:postcode":"91403",
    "sg:province":"CA",
    "sg:tags":[
        "travel",
        "accessory"
    ],
    "wof:name":"Northstar Worldwide",
    "wof:placetype":"venue"
},
  "geometry": {"coordinates":[-118.45487799999999,34.164928],"type":"Point"}
}