{
  "type": "Feature",
  "properties": {
    "addr:full":"7171 N Cedar Ave Fresno CA 93720",
    "addr:housenumber":"7171",
    "addr:postcode":"93720",
    "addr:street":"N Cedar Ave",
    "iso:country":"US",
    "sg:address":"7171 N Cedar Ave",
    "sg:city":"Fresno",
    "sg:classifiers":[
        {
            "category":"Health Services",
            "subcategory":"Hospital",
            "type":"Services"
        }
    ],
    "sg:phone":"+1 559 435 7669",
    "sg:postcode":"93720",
    "sg:province":"CA",
    "sg:tags":[
        "mental"
    ],
    "wof:name":"Help Now-24 Hours",
    "wof:placetype":"venue"
},
  "geometry": {"coordinates":[-119.756503,36.840508],"type":"Point"}
}