{
  "type": "Feature",
  "properties": {
    "iso:country":"US",
    "sg:address":"539 S Brea Blvd",
    "sg:city":"Brea",
    "sg:classifiers":[
        {
            "category":"Health Services",
            "subcategory":"Doctor",
            "type":"Services"
        }
    ],
    "sg:phone":"+1 714 671 2936",
    "sg:postcode":"92821",
    "sg:province":"CA",
    "sg:tags":[
        "physician",
        "family",
        "practice",
        "surgeons",
        "medicine",
        "surgeon"
    ],
    "wof:name":"Kristine Percy Md & Lauren Ste",
    "wof:placetype":"venue"
},
  "geometry": {"coordinates":[-117.90248200000001,33.91259],"type":"Point"}
}