{
  "type": "Feature",
  "properties": {
    "addr:full":"2673 N Arrowhead Ave San Bernardino CA 92405",
    "addr:housenumber":"2673",
    "addr:postcode":"92405",
    "addr:street":"N Arrowhead Ave",
    "iso:country":"US",
    "sg:address":"2673 N Arrowhead Ave",
    "sg:city":"San Bernardino",
    "sg:classifiers":[
        {
            "category":"Manufacturing",
            "subcategory":"Printing",
            "type":"Manufacturing & Wholesale Goods"
        }
    ],
    "sg:phone":"+1 909 881 5730",
    "sg:postcode":"92405",
    "sg:province":"CA",
    "sg:tags":[
        "lithographic",
        "commercial"
    ],
    "wof:name":"Epic Print Media",
    "wof:placetype":"venue"
},
  "geometry": {"coordinates":[-117.28959,34.139961],"type":"Point"}
}