{
  "type": "Feature",
  "properties": {
    "iso:country":"US",
    "sg:address":"1550 Escalon Bellota Rd",
    "sg:city":"Farmington",
    "sg:classifiers":[
        {
            "category":"Farming",
            "subcategory":"Poultry Farm",
            "type":"Manufacturing & Wholesale Goods"
        }
    ],
    "sg:phone":"+1 209 886 5359",
    "sg:postcode":"95230",
    "sg:province":"CA",
    "wof:name":"Foster Turkey Farms",
    "wof:placetype":"venue"
},
  "geometry": {"coordinates":[-121.000047,37.958715],"type":"Point"}
}