{
  "type": "Feature",
  "properties": {
    "iso:country":"US",
    "sg:address":"12456 Ventura Blvd",
    "sg:city":"Studio City",
    "sg:classifiers":[
        {
            "category":"Health Services",
            "subcategory":"Health Practitioner",
            "type":"Services"
        }
    ],
    "sg:phone":"+1 818 980 1762",
    "sg:postcode":"91604",
    "sg:province":"CA",
    "sg:tags":[
        "psychologist"
    ],
    "wof:name":"Southern California Psychtrpy",
    "wof:placetype":"venue"
},
  "geometry": {"coordinates":[-118.404111,34.14287],"type":"Point"}
}