{
  "type": "Feature",
  "properties": {
    "addr:full":"11870 Santa Monica Blvd Los Angeles CA 90025",
    "addr:housenumber":"11870",
    "addr:postcode":"90025",
    "addr:street":"Santa Monica Blvd",
    "iso:country":"US",
    "sg:address":"11870 Santa Monica Blvd",
    "sg:city":"Los Angeles",
    "sg:classifiers":[
        {
            "category":"Restaurant",
            "type":"Food & Drink"
        }
    ],
    "sg:menulink":"http://www.allmenus.com/ca/los-angeles/168868-el-pollo-loco/menu/",
    "sg:phone":"+1 310 820 7924",
    "sg:postcode":"90025",
    "sg:province":"CA",
    "sg:tags":[
        "american",
        "mexican",
        "tex-mex"
    ],
    "wof:name":"El Pollo Loco",
    "wof:placetype":"venue"
},
  "geometry": {"coordinates":[-118.459391,34.041717],"type":"Point"}
}