{
  "type": "Feature",
  "properties": {
    "addr:full":"13908 Seal Beach Blvd Seal Beach CA 90740",
    "addr:housenumber":"13908",
    "addr:postcode":"90740",
    "addr:street":"Seal Beach Blvd",
    "iso:country":"US",
    "sg:address":"13908 Seal Beach Blvd",
    "sg:city":"Seal Beach",
    "sg:classifiers":[
        {
            "category":"Wholesale",
            "subcategory":"Medical Equipment & Supplies",
            "type":"Manufacturing & Wholesale Goods"
        }
    ],
    "sg:phone":"+1 562 493 3910",
    "sg:postcode":"90740",
    "sg:province":"CA",
    "sg:tags":[
        "physician",
        "surgeon"
    ],
    "wof:name":"Alpine Home Medical",
    "wof:placetype":"venue"
},
  "geometry": {"coordinates":[-118.077465,33.761141],"type":"Point"}
}