{
  "type": "Feature",
  "properties": {
    "iso:country":"US",
    "sg:address":"9082 Bolsa Ave",
    "sg:city":"Westminster",
    "sg:classifiers":[
        {
            "category":"Restaurant",
            "type":"Food & Drink"
        }
    ],
    "sg:phone":"+1 714 901 8108",
    "sg:postcode":"92683",
    "sg:province":"CA",
    "sg:tags":[
        "vietnamese"
    ],
    "wof:name":"Ha Noi Restaurant",
    "wof:placetype":"venue"
},
  "geometry": {"coordinates":[-117.971001,33.744701],"type":"Point"}
}