{
  "type": "Feature",
  "properties": {
    "iso:country":"US",
    "sg:address":"36 N Euclid Ave",
    "sg:city":"National City",
    "sg:classifiers":[
        {
            "category":"Food & Beverages",
            "subcategory":"Bakery",
            "type":"Retail Goods"
        }
    ],
    "sg:phone":"+1 619 266 8529",
    "sg:postcode":"91950",
    "sg:province":"CA",
    "sg:tags":[
        "doughnut"
    ],
    "wof:name":"Golden Donuts",
    "wof:placetype":"venue"
},
  "geometry": {"coordinates":[-117.085205,32.69045],"type":"Point"}
}