{
  "type": "Feature",
  "properties": {
    "iso:country":"US",
    "sg:address":"8471 Melrose Ave",
    "sg:city":"West Hollywood",
    "sg:classifiers":[
        {
            "category":"Home & Garden",
            "subcategory":"Furniture",
            "type":"Retail Goods"
        }
    ],
    "sg:phone":"+1 323 951 1200",
    "sg:postcode":"90069",
    "sg:province":"CA",
    "sg:tags":[
        "builder",
        "custom"
    ],
    "wof:name":"Charles Fradin Showroom",
    "wof:placetype":"venue"
},
  "geometry": {"coordinates":[-118.375173,34.082717],"type":"Point"}
}