{
  "type": "Feature",
  "properties": {
    "iso:country":"US",
    "sg:address":"1155 S Milliken Ave",
    "sg:city":"Ontario",
    "sg:classifiers":[
        {
            "category":"Government",
            "subcategory":"Office",
            "type":"Public Place"
        }
    ],
    "sg:phone":"+1 909 390 7788",
    "sg:postcode":"91761",
    "sg:province":"CA",
    "sg:tags":[
        "agency"
    ],
    "wof:name":"Carf Print Shop",
    "wof:placetype":"venue"
},
  "geometry": {"coordinates":[-117.55816,34.050603],"type":"Point"}
}