{
  "type": "Feature",
  "properties": {
    "addr:full":"475 Pine St San Francisco CA 94104",
    "addr:housenumber":"475",
    "addr:postcode":"94104",
    "addr:street":"Pine St",
    "iso:country":"US",
    "sg:address":"475 Pine St",
    "sg:city":"San Francisco",
    "sg:classifiers":[
        {
            "category":"Cafe",
            "type":"Food & Drink"
        }
    ],
    "sg:menulink":"http://www.allmenus.com/ca/san-francisco/62928-krivaar-cafe/menu/",
    "sg:phone":"+1 415 781 0894",
    "sg:postcode":"94104",
    "sg:province":"CA",
    "sg:tags":[
        "mediterranean"
    ],
    "wof:name":"Krivaar Cafe",
    "wof:placetype":"venue"
},
  "geometry": {"coordinates":[-122.40363000000001,37.791801],"type":"Point"}
}