{
  "type": "Feature",
  "properties": {
    "addr:full":"19091 State Rte 33 Mc Kittrick CA 93251",
    "addr:housenumber":"19091",
    "addr:postcode":"93251",
    "addr:street":"State Rte 33 Mc Kittrick",
    "iso:country":"US",
    "sg:address":"19091 State Rte 33",
    "sg:city":"Mc Kittrick",
    "sg:classifiers":[
        {
            "category":"Building & Trades",
            "subcategory":"Equipment Rental",
            "type":"Services"
        }
    ],
    "sg:phone":"+1 661 762 9156",
    "sg:postcode":"93251",
    "sg:province":"CA",
    "sg:tags":[
        "yard"
    ],
    "wof:name":"Atlas Copco Rental Svc Corp",
    "wof:placetype":"venue"
},
  "geometry": {"coordinates":[-119.688473,35.435793],"type":"Point"}
}