{
  "type": "Feature",
  "properties": {
    "addr:full":"901 Fulton Ave Sacramento CA 95825",
    "addr:housenumber":"901",
    "addr:postcode":"95825",
    "addr:street":"Fulton Ave",
    "iso:country":"US",
    "sg:address":"901 Fulton Ave",
    "sg:city":"Sacramento",
    "sg:classifiers":[
        {
            "category":"Professional",
            "type":"Services"
        }
    ],
    "sg:phone":"+1 916 482 6735",
    "sg:postcode":"95825",
    "sg:province":"CA",
    "sg:tags":[
        "establishment"
    ],
    "wof:name":"Bengs & Larson",
    "wof:placetype":"venue"
},
  "geometry": {"coordinates":[-121.401483,38.582513],"type":"Point"}
}