{
  "type": "Feature",
  "properties": {
    "addr:full":"5227 Stevens Creek Blvd Santa Clara CA 95051",
    "addr:housenumber":"5227",
    "addr:postcode":"95051",
    "addr:street":"Stevens Creek Blvd",
    "iso:country":"US",
    "sg:address":"5227 Stevens Creek Blvd",
    "sg:city":"Santa Clara",
    "sg:classifiers":[
        {
            "category":"Personal",
            "subcategory":"Skin Care",
            "type":"Services"
        }
    ],
    "sg:phone":"+1 408 296 6999",
    "sg:postcode":"95051",
    "sg:province":"CA",
    "wof:name":"Angela Beauty Center",
    "wof:placetype":"venue"
},
  "geometry": {"coordinates":[-121.993818,37.32312],"type":"Point"}
}