{
  "type": "Feature",
  "properties": {
    "addr:full":"1300 Clay St Oakland CA 94612",
    "addr:housenumber":"1300",
    "addr:postcode":"94612",
    "addr:street":"Clay St",
    "iso:country":"US",
    "sg:address":"1300 Clay St",
    "sg:city":"Oakland",
    "sg:classifiers":[
        {
            "category":"Insurance",
            "subcategory":"Hazard Insurance",
            "type":"Services"
        }
    ],
    "sg:phone":"+1 510 464 8075",
    "sg:postcode":"94612",
    "sg:province":"CA",
    "sg:tags":[
        "commercial",
        "business"
    ],
    "sg:website":"http://www.bankerslife.com",
    "wof:name":"Banker's Life & Casualty",
    "wof:placetype":"venue"
},
  "geometry": {"coordinates":[-122.274036,37.804586],"type":"Point"}
}