{
  "type": "Feature",
  "properties": {
    "addr:full":"4500 Whittier Blvd Los Angeles CA 90022",
    "addr:housenumber":"4500",
    "addr:postcode":"90022",
    "addr:street":"Whittier Blvd",
    "iso:country":"US",
    "sg:address":"4500 Whittier Blvd",
    "sg:city":"Los Angeles",
    "sg:classifiers":[
        {
            "category":"Professional",
            "subcategory":"Accounting & Tax Preparation",
            "type":"Services"
        }
    ],
    "sg:phone":"+1 323 780 8037",
    "sg:postcode":"90022",
    "sg:province":"CA",
    "sg:tags":[
        "return",
        "filing"
    ],
    "wof:name":"Franco Tax Svc",
    "wof:placetype":"venue"
},
  "geometry": {"coordinates":[-118.17,34.023087],"type":"Point"}
}