{
  "type": "Feature",
  "properties": {
    "iso:country":"US",
    "sg:address":"7906 Fallbrook Ave",
    "sg:city":"Canoga Park",
    "sg:classifiers":[
        {
            "category":"Building & Trades",
            "subcategory":"Construction",
            "type":"Services"
        }
    ],
    "sg:phone":"+1 818 992 8172",
    "sg:postcode":"91304",
    "sg:province":"CA",
    "sg:tags":[
        "general",
        "contractor"
    ],
    "wof:name":"SIA Farahmand Constr Co",
    "wof:placetype":"venue"
},
  "geometry": {"coordinates":[-118.623364,34.213562],"type":"Point"}
}