{
  "type": "Feature",
  "properties": {
    "addr:full":"511 Airport Way Manteca CA 95337",
    "addr:housenumber":"511",
    "addr:postcode":"95337",
    "addr:street":"Airport Way",
    "iso:country":"US",
    "sg:address":"511 Airport Way",
    "sg:city":"Manteca",
    "sg:classifiers":[
        {
            "category":"Wholesale",
            "subcategory":"Farm Supplies",
            "type":"Manufacturing & Wholesale Goods"
        }
    ],
    "sg:phone":"+1 209 239 2401",
    "sg:postcode":"95337",
    "sg:province":"CA",
    "sg:tags":[
        "alfalfa",
        "hay"
    ],
    "wof:name":"John Rossi Hay Co",
    "wof:placetype":"venue"
},
  "geometry": {"coordinates":[-121.25219,37.796248],"type":"Point"}
}