{
  "type": "Feature",
  "properties": {
    "addr:full":"736 S Madera Ave Kerman CA 93630",
    "addr:housenumber":"736",
    "addr:postcode":"93630",
    "addr:street":"S Madera Ave",
    "iso:country":"US",
    "sg:address":"736 S Madera Ave",
    "sg:city":"Kerman",
    "sg:classifiers":[
        {
            "category":"Retail",
            "subcategory":"Auto Repair",
            "type":"Services"
        }
    ],
    "sg:phone":"+1 559 846 5784",
    "sg:postcode":"93630",
    "sg:province":"CA",
    "sg:tags":[
        "wrecker"
    ],
    "wof:name":"J S Towing",
    "wof:placetype":"venue"
},
  "geometry": {"coordinates":[-120.060175,36.72395],"type":"Point"}
}