{
  "type": "Feature",
  "properties": {
    "addr:full":"3660 W San Jose Ave Fresno CA 93711",
    "addr:housenumber":"3660",
    "addr:postcode":"93711",
    "addr:street":"W San Jose Ave",
    "iso:country":"US",
    "sg:address":"3660 W San Jose Ave",
    "sg:city":"Fresno",
    "sg:classifiers":[
        {
            "category":"Personal",
            "type":"Services"
        }
    ],
    "sg:phone":"+1 559 917 8008",
    "sg:postcode":"93711",
    "sg:province":"CA",
    "sg:tags":[
        "therapist",
        "massage"
    ],
    "wof:name":"One Touch Therapy",
    "wof:placetype":"venue"
},
  "geometry": {"coordinates":[-119.859346,36.811907],"type":"Point"}
}