{
  "type": "Feature",
  "properties": {
    "iso:country":"US",
    "sg:address":"13326 Elliot Ave",
    "sg:city":"Chino",
    "sg:classifiers":[
        {
            "category":"Manufacturing",
            "subcategory":"Retail Goods",
            "type":"Manufacturing & Wholesale Goods"
        }
    ],
    "sg:phone":"+1 909 464 1222",
    "sg:postcode":"91710",
    "sg:province":"CA",
    "sg:tags":[
        "plant",
        "flower",
        "tree",
        "artificial"
    ],
    "sg:website":"www.dalmarko.com",
    "wof:name":"Dalmarko Inc",
    "wof:placetype":"venue"
},
  "geometry": {"coordinates":[-117.678997,34.010889],"type":"Point"}
}