{
  "type": "Feature",
  "properties": {
    "iso:country":"US",
    "sg:address":"405 Gay St",
    "sg:city":"Corona",
    "sg:classifiers":[
        {
            "category":"Manufacturing",
            "subcategory":"Metals",
            "type":"Manufacturing & Wholesale Goods"
        }
    ],
    "sg:phone":"+1 951 735 9955",
    "sg:postcode":"92879",
    "sg:province":"CA",
    "sg:tags":[
        "engraver"
    ],
    "wof:name":"Custom Awards & Engraving",
    "wof:placetype":"venue"
},
  "geometry": {"coordinates":[-117.56305,33.864939],"type":"Point"}
}