{
  "type": "Feature",
  "properties": {
    "iso:country":"US",
    "sg:address":"9730 Garvey Ave",
    "sg:city":"El Monte",
    "sg:classifiers":[
        {
            "category":"Manufacturing",
            "subcategory":"Apparel",
            "type":"Manufacturing & Wholesale Goods"
        }
    ],
    "sg:phone":"+1 626 582 8300",
    "sg:postcode":"91733",
    "sg:province":"CA",
    "sg:tags":[
        "sewing",
        "contractor"
    ],
    "wof:name":"Classic Tees",
    "wof:placetype":"venue"
},
  "geometry": {"coordinates":[-118.056176,34.062639],"type":"Point"}
}