{
  "type": "Feature",
  "properties": {
    "iso:country":"US",
    "sg:address":"116 N Maryland Ave",
    "sg:city":"Glendale",
    "sg:classifiers":[
        {
            "category":"Real Estate",
            "subcategory":"Real Estate Agent",
            "type":"Services"
        }
    ],
    "sg:phone":"+1 818 244 3000",
    "sg:postcode":"91206",
    "sg:province":"CA",
    "sg:website":"www.pacwestonline.com",
    "wof:name":"Pacific West Commercial & Ind",
    "wof:placetype":"venue"
},
  "geometry": {"coordinates":[-118.253843,34.147798],"type":"Point"}
}