{
  "type": "Feature",
  "properties": {
    "iso:country":"US",
    "sg:address":"3305 Renner Dr",
    "sg:city":"Fortuna",
    "sg:classifiers":[
        {
            "category":"Health Services",
            "subcategory":"Doctor",
            "type":"Services"
        }
    ],
    "sg:phone":"+1 707 725 9355",
    "sg:postcode":"95540",
    "sg:province":"CA",
    "sg:tags":[
        "physician",
        "surgeon"
    ],
    "wof:name":"Redwood Pediatric Group",
    "wof:placetype":"venue"
},
  "geometry": {"coordinates":[-124.130898,40.582517],"type":"Point"}
}