{
  "type": "Feature",
  "properties": {
    "addr:full":"16700 Roscoe Blvd Van Nuys CA 91402",
    "addr:housenumber":"16700",
    "addr:postcode":"91402",
    "addr:street":"Roscoe Blvd",
    "iso:country":"US",
    "sg:address":"16700 Roscoe Blvd",
    "sg:city":"Van Nuys",
    "sg:classifiers":[
        {
            "category":"Airline",
            "type":"Transportation"
        }
    ],
    "sg:phone":"+1 818 988 6532",
    "sg:postcode":"91402",
    "sg:province":"CA",
    "sg:tags":[
        "equipment",
        "nonscheduled",
        "air"
    ],
    "wof:name":"Tours-Training-Photography",
    "wof:placetype":"venue"
},
  "geometry": {"coordinates":[-118.49426699999999,34.220649],"type":"Point"}
}