{
  "type": "Feature",
  "properties": {
    "iso:country":"US",
    "sg:address":"7342 Orangethorpe Ave Ste A102",
    "sg:city":"Buena Park",
    "sg:classifiers":[
        {
            "category":"Wholesale",
            "subcategory":"Computers",
            "type":"Manufacturing & Wholesale Goods"
        }
    ],
    "sg:phone":"+1 714 670 6321",
    "sg:postcode":"90621",
    "sg:province":"CA",
    "wof:name":"Advanced Computer",
    "wof:placetype":"venue"
},
  "geometry": {"coordinates":[-118.004997,33.859001],"type":"Point"}
}