{
  "type": "Feature",
  "properties": {
    "iso:country":"US",
    "sg:address":"24404 S Vermont Ave",
    "sg:city":"Harbor City",
    "sg:classifiers":[
        {
            "category":"Recreation",
            "type":"Entertainment"
        }
    ],
    "sg:phone":"+1 310 257 1707",
    "sg:postcode":"90710",
    "sg:province":"CA",
    "sg:tags":[
        "instruction",
        "golf"
    ],
    "sg:website":"www.lagolfcollege.com",
    "wof:name":"Los Angeles Golf College",
    "wof:placetype":"venue"
},
  "geometry": {"coordinates":[-118.290241,33.803413],"type":"Point"}
}