{
  "type": "Feature",
  "properties": {
    "iso:country":"US",
    "sg:address":"860 E Florence Ave",
    "sg:city":"Los Angeles",
    "sg:classifiers":[
        {
            "category":"Autos & Motor Vehicles",
            "subcategory":"Automobile Sales",
            "type":"Retail Goods"
        }
    ],
    "sg:phone":"+1 323 588 7171",
    "sg:postcode":"90001",
    "sg:province":"CA",
    "sg:tags":[
        "car",
        "dealer"
    ],
    "wof:name":"Esquina Auto Sales",
    "wof:placetype":"venue"
},
  "geometry": {"coordinates":[-118.259059,33.974689],"type":"Point"}
}