{
  "type": "Feature",
  "properties": {
    "iso:country":"US",
    "sg:address":"500 Domingo Pl",
    "sg:city":"Fullerton",
    "sg:classifiers":[
        {
            "category":"Professional",
            "type":"Services"
        }
    ],
    "sg:phone":"+1 714 447 0097",
    "sg:postcode":"92835",
    "sg:province":"CA",
    "wof:name":"La Mere LLC",
    "wof:placetype":"venue"
},
  "geometry": {"coordinates":[-117.93304000000001,33.90318],"type":"Point"}
}