{
  "type": "Feature",
  "properties": {
    "addr:full":"111 Japanese Village Plaza Los Angeles CA 90012",
    "addr:housenumber":"111",
    "addr:postcode":"90012",
    "addr:street":"Japanese Village Plaza",
    "iso:country":"US",
    "sg:address":"111 Japanese Village Plaza",
    "sg:city":"Los Angeles",
    "sg:classifiers":[
        {
            "category":"Retail",
            "subcategory":"Portrait Studio",
            "type":"Services"
        },
        {
            "category":"Shopping",
            "subcategory":"Computers & Home Electronics",
            "type":"Retail Goods"
        }
    ],
    "sg:phone":"+1 213 680 3288",
    "sg:postcode":"90012",
    "sg:province":"CA",
    "sg:tags":[
        "photography",
        "store"
    ],
    "wof:name":"Plaza Gift Center",
    "wof:placetype":"venue"
},
  "geometry": {"coordinates":[-118.239619,34.0493],"type":"Point"}
}