{
  "type": "Feature",
  "properties": {
    "addr:full":"785 Travis St Folsom CA 95630",
    "addr:housenumber":"785",
    "addr:postcode":"95630",
    "addr:street":"Travis St",
    "iso:country":"US",
    "sg:address":"785 Travis St",
    "sg:city":"Folsom",
    "sg:classifiers":[
        {
            "category":"Shopping",
            "type":"Retail Goods"
        }
    ],
    "sg:phone":"+1 916 817 8960",
    "sg:postcode":"95630",
    "sg:province":"CA",
    "sg:tags":[
        "merchandise"
    ],
    "sg:website":"http://www.samsclub.com",
    "wof:name":"Sam's Club",
    "wof:placetype":"venue"
},
  "geometry": {"coordinates":[-121.15733899999999,38.658006],"type":"Point"}
}