{
  "type": "Feature",
  "properties": {
    "addr:full":"3041 E Gage Ave Huntington Park CA 90255",
    "addr:housenumber":"3041",
    "addr:postcode":"90255",
    "addr:street":"E Gage Ave;Park",
    "iso:country":"US",
    "sg:address":"3041 E Gage Ave",
    "sg:city":"Huntington Park",
    "sg:classifiers":[
        {
            "category":"Shopping",
            "subcategory":"Bicycles & Sporting Goods",
            "type":"Retail Goods"
        }
    ],
    "sg:phone":"+1 323 584 1084",
    "sg:postcode":"90255",
    "sg:province":"CA",
    "wof:name":"Eu Bike Shop",
    "wof:placetype":"venue"
},
  "geometry": {"coordinates":[-118.214056,33.980978],"type":"Point"}
}