{
  "type": "Feature",
  "properties": {
    "addr:full":"143 Lain Dr Vallejo CA 94591",
    "addr:housenumber":"143",
    "addr:postcode":"94591",
    "addr:street":"Lain Dr",
    "iso:country":"US",
    "sg:address":"143 Lain Dr",
    "sg:city":"Vallejo",
    "sg:classifiers":[
        {
            "category":"Professional",
            "type":"Services"
        }
    ],
    "sg:phone":"+1 707 332 1103",
    "sg:postcode":"94591",
    "sg:province":"CA",
    "wof:name":"Leo Jj International",
    "wof:placetype":"venue"
},
  "geometry": {"coordinates":[-122.215264,38.108632],"type":"Point"}
}