{
  "type": "Feature",
  "properties": {
    "addr:full":"3861 Mission Ave Oceanside CA 92058",
    "addr:housenumber":"3861",
    "addr:postcode":"92058",
    "addr:street":"Mission Ave",
    "iso:country":"US",
    "sg:address":"3861 Mission Ave",
    "sg:city":"Oceanside",
    "sg:classifiers":[
        {
            "category":"Banks & Credit Unions",
            "subcategory":"Financial Services",
            "type":"Services"
        }
    ],
    "sg:phone":"+1 760 439 2234",
    "sg:postcode":"92058",
    "sg:province":"CA",
    "sg:tags":[
        "broker",
        "mortgage"
    ],
    "wof:name":"Charger Mortgage",
    "wof:placetype":"venue"
},
  "geometry": {"coordinates":[-117.328216,33.226818],"type":"Point"}
}