{
  "type": "Feature",
  "properties": {
    "iso:country":"US",
    "sg:address":"1616 Baker St",
    "sg:city":"Bakersfield",
    "sg:classifiers":[
        {
            "category":"Professional",
            "subcategory":"Lawyer & Legal Services",
            "type":"Services"
        }
    ],
    "sg:phone":"+1 661 852 0417",
    "sg:postcode":"93305",
    "sg:province":"CA",
    "sg:tags":[
        "attorney"
    ],
    "wof:name":"Michelle Trujillo Law Office",
    "wof:placetype":"venue"
},
  "geometry": {"coordinates":[-118.990067,35.384971],"type":"Point"}
}