{
  "type": "Feature",
  "properties": {
    "addr:full":"5801 Sundale Ave Bakersfield CA 93309",
    "addr:housenumber":"5801",
    "addr:postcode":"93309",
    "addr:street":"Sundale Ave",
    "iso:country":"US",
    "sg:address":"5801 Sundale Ave",
    "sg:city":"Bakersfield",
    "sg:classifiers":[
        {
            "category":"Education",
            "subcategory":"School",
            "type":"Public Place"
        }
    ],
    "sg:phone":"+1 661 827 3158",
    "sg:postcode":"93309",
    "sg:province":"CA",
    "sg:tags":[
        "district"
    ],
    "sg:website":"www.khsd.org",
    "wof:name":"KERN High School District",
    "wof:placetype":"venue"
},
  "geometry": {"coordinates":[-119.064789,35.344017],"type":"Point"}
}