{
  "type": "Feature",
  "properties": {
    "addr:full":"3626 W St Eureka CA 95503",
    "addr:housenumber":"3626",
    "addr:postcode":"95503",
    "addr:street":"W St",
    "iso:country":"US",
    "sg:address":"3626 W St",
    "sg:city":"Eureka",
    "sg:classifiers":[
        {
            "category":"Communications",
            "type":"Services"
        }
    ],
    "sg:phone":"+1 707 497 6886",
    "sg:postcode":"95503",
    "sg:province":"CA",
    "wof:name":"Suddenlink Communications",
    "wof:placetype":"venue"
},
  "geometry": {"coordinates":[-124.14449,40.773495],"type":"Point"}
}