{
  "type": "Feature",
  "properties": {
    "addr:full":"2050 S 10th St San Jose CA 95112",
    "addr:housenumber":"2050",
    "addr:postcode":"95112",
    "addr:street":"S 10Th St",
    "iso:country":"US",
    "sg:address":"2050 S 10th St",
    "sg:city":"San Jose",
    "sg:classifiers":[
        {
            "category":"Manufacturing",
            "subcategory":"Printing",
            "type":"Manufacturing & Wholesale Goods"
        }
    ],
    "sg:phone":"+1 408 995 5514",
    "sg:postcode":"95112",
    "sg:province":"CA",
    "sg:tags":[
        "packaging",
        "lamination"
    ],
    "wof:name":"Savoye Packaging Corporation",
    "wof:placetype":"venue"
},
  "geometry": {"coordinates":[-121.85672700000001,37.310596],"type":"Point"}
}