{
  "type": "Feature",
  "properties": {
    "iso:country":"US",
    "sg:address":"2410 Cades Way",
    "sg:city":"Vista",
    "sg:classifiers":[
        {
            "category":"Wholesale",
            "subcategory":"Medical Equipment & Supplies",
            "type":"Manufacturing & Wholesale Goods"
        }
    ],
    "sg:phone":"+1 760 599 9496",
    "sg:postcode":"92081",
    "sg:province":"CA",
    "sg:tags":[
        "physician",
        "surgeon"
    ],
    "sg:website":"www.gosdme.com",
    "wof:name":"SDME Inc",
    "wof:placetype":"venue"
},
  "geometry": {"coordinates":[-117.221591,33.153669],"type":"Point"}
}