{
  "type": "Feature",
  "properties": {
    "addr:full":"659 S Broadway Los Angeles CA 90014",
    "addr:housenumber":"659",
    "addr:postcode":"90014",
    "addr:street":"S Broadway",
    "iso:country":"US",
    "sg:address":"659 S Broadway",
    "sg:city":"Los Angeles",
    "sg:classifiers":[
        {
            "category":"Shopping",
            "subcategory":"Jewelry",
            "type":"Retail Goods"
        }
    ],
    "sg:phone":"+1 213 683 9764",
    "sg:postcode":"90014",
    "sg:province":"CA",
    "sg:tags":[
        "jeweler"
    ],
    "wof:name":"Querubin Jewelry",
    "wof:placetype":"venue"
},
  "geometry": {"coordinates":[-118.25291,34.045751],"type":"Point"}
}