{
  "type": "Feature",
  "properties": {
    "addr:full":"8261 Garden Grove Blvd Garden Grove CA 92844",
    "addr:housenumber":"8261",
    "addr:postcode":"92844",
    "addr:street":"Garden Grove Blvd",
    "iso:country":"US",
    "sg:address":"8261 Garden Grove Blvd",
    "sg:city":"Garden Grove",
    "sg:classifiers":[
        {
            "category":"Utilities",
            "subcategory":"Mobile Phone",
            "type":"Services"
        }
    ],
    "sg:phone":"+1 714 334 5353",
    "sg:postcode":"92844",
    "sg:province":"CA",
    "sg:tags":[
        "communication",
        "radiotelephone"
    ],
    "wof:name":"Jun Wireless",
    "wof:placetype":"venue"
},
  "geometry": {"coordinates":[-117.988899,33.773892],"type":"Point"}
}