{
  "type": "Feature",
  "properties": {
    "addr:full":"7523 Santa Fe Ave Huntington Park CA 90255",
    "addr:housenumber":"7523",
    "addr:postcode":"90255",
    "addr:street":"Santa Fe Ave;Park",
    "iso:country":"US",
    "sg:address":"7523 Santa Fe Ave",
    "sg:city":"Huntington Park",
    "sg:classifiers":[
        {
            "category":"Personal",
            "subcategory":"Beauty Salon",
            "type":"Services"
        }
    ],
    "sg:phone":"+1 323 588 8380",
    "sg:postcode":"90255",
    "sg:province":"CA",
    "wof:name":"Laura's Barbers Beauty Salon",
    "wof:placetype":"venue"
},
  "geometry": {"coordinates":[-118.230284,33.970579],"type":"Point"}
}