{
  "type": "Feature",
  "properties": {
    "addr:full":"4524 Rosemead Blvd Pico Rivera CA 90660",
    "addr:housenumber":"4524",
    "addr:postcode":"90660",
    "addr:street":"Rosemead Blvd",
    "iso:country":"US",
    "sg:address":"4524 Rosemead Blvd",
    "sg:city":"Pico Rivera",
    "sg:classifiers":[
        {
            "category":"Personal",
            "subcategory":"Beauty Salon",
            "type":"Services"
        }
    ],
    "sg:phone":"+1 562 699 2241",
    "sg:postcode":"90660",
    "sg:province":"CA",
    "wof:name":"Glamorama Unisex Salon",
    "wof:placetype":"venue"
},
  "geometry": {"coordinates":[-118.081755,34.007652],"type":"Point"}
}