{
  "type": "Feature",
  "properties": {
    "addr:full":"365 Cloverleaf Dr Baldwin Park CA 91706",
    "addr:housenumber":"365",
    "addr:postcode":"91706",
    "addr:street":"Cloverleaf Dr",
    "iso:country":"US",
    "sg:address":"365 Cloverleaf Dr",
    "sg:city":"Baldwin Park",
    "sg:classifiers":[
        {
            "category":"Wholesale",
            "subcategory":"Durable Goods & Equipment",
            "type":"Manufacturing & Wholesale Goods"
        }
    ],
    "sg:phone":"+1 626 820 5881",
    "sg:postcode":"91706",
    "sg:province":"CA",
    "sg:tags":[
        "importer"
    ],
    "wof:name":"Summit Overseas Co LTD",
    "wof:placetype":"venue"
},
  "geometry": {"coordinates":[-118.00241800000001,34.061281],"type":"Point"}
}