{
  "type": "Feature",
  "properties": {
    "addr:full":"221 E 6th St Corona CA 92879",
    "addr:housenumber":"221",
    "addr:postcode":"92879",
    "addr:street":"E 6Th St",
    "iso:country":"US",
    "sg:address":"221 E 6th St",
    "sg:city":"Corona",
    "sg:classifiers":[
        {
            "category":"Banks & Credit Unions",
            "subcategory":"Bank",
            "type":"Services"
        }
    ],
    "sg:phone":"+1 951 817 1092",
    "sg:postcode":"92879",
    "sg:province":"CA",
    "sg:tags":[
        "money",
        "order"
    ],
    "wof:name":"Dolex Dollar Express",
    "wof:placetype":"venue"
},
  "geometry": {"coordinates":[-117.564138,33.875256],"type":"Point"}
}