{
  "type": "Feature",
  "properties": {
    "iso:country":"US",
    "sg:address":"435 Genoa St Apt B",
    "sg:city":"Monrovia",
    "sg:classifiers":[
        {
            "category":"Building & Trades",
            "subcategory":"Plumbing",
            "type":"Services"
        }
    ],
    "sg:phone":"+1 626 357 5313",
    "sg:postcode":"91016",
    "sg:province":"CA",
    "wof:name":"Drains 4 Less",
    "wof:placetype":"venue"
},
  "geometry": {"coordinates":[-118.058807,34.133],"type":"Point"}
}