{
  "type": "Feature",
  "properties": {
    "addr:full":"1155 E Julian Street San Jose CA 95116",
    "addr:housenumber":"1155",
    "addr:postcode":"95116",
    "addr:street":"E Julian Street",
    "iso:country":"US",
    "sg:address":"1155 E Julian Street",
    "sg:city":"San Jose",
    "sg:classifiers":[
        {
            "category":"Education",
            "subcategory":"School",
            "type":"Public Place"
        }
    ],
    "sg:phone":"+1 408 279 2550",
    "sg:postcode":"95116",
    "sg:province":"CA",
    "wof:name":"San Jose Unified School District",
    "wof:placetype":"venue"
},
  "geometry": {"coordinates":[-121.871071,37.350936],"type":"Point"}
}