{
  "type": "Feature",
  "properties": {
    "addr:full":"3833 Abbey Ct Campbell CA 95008",
    "addr:housenumber":"3833",
    "addr:postcode":"95008",
    "addr:street":"Abbey Ct",
    "iso:country":"US",
    "sg:address":"3833 Abbey Ct",
    "sg:city":"Campbell",
    "sg:classifiers":[
        {
            "category":"Real Estate",
            "subcategory":"Real Estate Agent",
            "type":"Services"
        }
    ],
    "sg:phone":"+1 408 379 9039",
    "sg:postcode":"95008",
    "sg:province":"CA",
    "sg:tags":[
        "management"
    ],
    "wof:name":"Mike Segal Properties",
    "wof:placetype":"venue"
},
  "geometry": {"coordinates":[-121.966959,37.28485],"type":"Point"}
}