{
  "type": "Feature",
  "properties": {
    "addr:full":"2651 S C St Oxnard CA 93033",
    "addr:housenumber":"2651",
    "addr:postcode":"93033",
    "addr:street":"S C St",
    "iso:country":"US",
    "sg:address":"2651 S C St",
    "sg:city":"Oxnard",
    "sg:classifiers":[
        {
            "category":"Health Services",
            "subcategory":"Clinic",
            "type":"Services"
        }
    ],
    "sg:phone":"+1 805 385 1885",
    "sg:postcode":"93033",
    "sg:province":"CA",
    "sg:tags":[
        "information",
        "alcoholism",
        "treatment"
    ],
    "wof:name":"Ventura Cnty Behavrl Hlth Alch",
    "wof:placetype":"venue"
},
  "geometry": {"coordinates":[-119.181228,34.175652],"type":"Point"}
}