{
  "type": "Feature",
  "properties": {
    "addr:full":"871 Via de la Paz Pacific Plsds CA 90272",
    "addr:housenumber":"871",
    "addr:postcode":"90272",
    "addr:street":"Via De La Paz",
    "iso:country":"US",
    "sg:address":"871 Via de la Paz",
    "sg:city":"Pacific Plsds",
    "sg:classifiers":[
        {
            "category":"Retail",
            "subcategory":"Repair Shop",
            "type":"Services"
        },
        {
            "category":"Shopping",
            "subcategory":"Bicycles & Sporting Goods",
            "type":"Retail Goods"
        }
    ],
    "sg:phone":"+1 310 454 2128",
    "sg:postcode":"90272",
    "sg:province":"CA",
    "wof:name":"Teds Palisades Bicycles",
    "wof:placetype":"venue"
},
  "geometry": {"coordinates":[-118.52745400000001,34.045835],"type":"Point"}
}