{
  "type": "Feature",
  "properties": {
    "iso:country":"US",
    "sg:address":"7755 Center Ave",
    "sg:city":"Huntington Beach",
    "sg:classifiers":[
        {
            "category":"Professional",
            "subcategory":"Lawyer & Legal Services",
            "type":"Services"
        }
    ],
    "sg:phone":"+1 714 372 2202",
    "sg:postcode":"92647",
    "sg:province":"CA",
    "wof:name":"Law Office of Christa M Hill",
    "wof:placetype":"venue"
},
  "geometry": {"coordinates":[-117.99700199999999,33.734001],"type":"Point"}
}