{
  "type": "Feature",
  "properties": {
    "iso:country":"US",
    "sg:address":"122 Rancho Del Mar",
    "sg:city":"Aptos",
    "sg:classifiers":[
        {
            "category":"Cinema",
            "subcategory":"Movie Theater",
            "type":"Entertainment"
        }
    ],
    "sg:phone":"+1 831 688 6541",
    "sg:postcode":"95003",
    "sg:province":"CA",
    "wof:name":"Aptos Cinemas",
    "wof:placetype":"venue"
},
  "geometry": {"coordinates":[-121.903999,36.979801],"type":"Point"}
}