{
  "type": "Feature",
  "properties": {
    "iso:country":"US",
    "sg:address":"833 S Main Ave",
    "sg:city":"Fallbrook",
    "sg:classifiers":[
        {
            "category":"Building & Trades",
            "subcategory":"Landscaping Services",
            "type":"Services"
        }
    ],
    "sg:phone":"+1 760 723 6570",
    "sg:postcode":"92028",
    "sg:province":"CA",
    "sg:tags":[
        "designer",
        "landscape"
    ],
    "wof:name":"Environmental Design Group",
    "wof:placetype":"venue"
},
  "geometry": {"coordinates":[-117.25153400000001,33.375115],"type":"Point"}
}