{
  "type": "Feature",
  "properties": {
    "addr:full":"777 Alamo Ln Ofc Vacaville CA 95687",
    "addr:housenumber":"777",
    "addr:postcode":"95687",
    "addr:street":"Alamo Ln",
    "iso:country":"US",
    "sg:address":"777 Alamo Ln Ofc",
    "sg:city":"Vacaville",
    "sg:classifiers":[
        {
            "category":"Building & Trades",
            "subcategory":"Construction",
            "type":"Services"
        },
        {
            "category":"Home & Garden",
            "subcategory":"Mobile Homes",
            "type":"Retail Goods"
        }
    ],
    "sg:phone":"+1 707 448 9320",
    "sg:postcode":"95687",
    "sg:province":"CA",
    "sg:tags":[
        "manufactured",
        "housing-communities",
        "park"
    ],
    "wof:name":"El Matador Mobile Home Park",
    "wof:placetype":"venue"
},
  "geometry": {"coordinates":[-121.98522199999999,38.33448],"type":"Point"}
}