{
  "type": "Feature",
  "properties": {
    "addr:full":"1620 W Huntington Dr Apt B Alhambra CA 91801",
    "addr:housenumber":"1620",
    "addr:postcode":"91801",
    "addr:street":"W Huntington Dr Apt B",
    "iso:country":"US",
    "sg:address":"1620 W Huntington Dr Apt B",
    "sg:city":"Alhambra",
    "sg:classifiers":[
        {
            "category":"Real Estate",
            "subcategory":"Real Estate Services",
            "type":"Services"
        },
        {
            "category":"Real Estate",
            "subcategory":"Real Estate Operator",
            "type":"Services"
        }
    ],
    "sg:phone":"+1 626 576 1906",
    "sg:postcode":"91801",
    "sg:province":"CA",
    "sg:tags":[
        "vacancy",
        "apartment",
        "rental",
        "listing"
    ],
    "wof:name":"Huntington Oaks Apartments",
    "wof:placetype":"venue"
},
  "geometry": {"coordinates":[-118.139999,34.104198],"type":"Point"}
}