{
  "type": "Feature",
  "properties": {
    "addr:full":"1031 Central Ave Duarte CA 91010",
    "addr:housenumber":"1031",
    "addr:postcode":"91010",
    "addr:street":"Central Ave",
    "iso:country":"US",
    "sg:address":"1031 Central Ave",
    "sg:city":"Duarte",
    "sg:classifiers":[
        {
            "category":"Autos & Motor Vehicles",
            "subcategory":"Automobile Sales",
            "type":"Retail Goods"
        }
    ],
    "sg:phone":"+1 626 359 9689",
    "sg:postcode":"91010",
    "sg:province":"CA",
    "sg:tags":[
        "body",
        "car",
        "dealer"
    ],
    "sg:website":"www.advantagefordmail.com",
    "wof:name":"Advantage Ford",
    "wof:placetype":"venue"
},
  "geometry": {"coordinates":[-117.97791700000001,34.135993],"type":"Point"}
}