{
  "type": "Feature",
  "properties": {
    "addr:full":"343 South St Orland CA 95963",
    "addr:housenumber":"343",
    "addr:postcode":"95963",
    "addr:street":"South St",
    "iso:country":"US",
    "sg:address":"343 South St",
    "sg:city":"Orland",
    "sg:classifiers":[
        {
            "category":"Building & Trades",
            "subcategory":"Construction",
            "type":"Services"
        }
    ],
    "sg:phone":"+1 530 865 8444",
    "sg:postcode":"95963",
    "sg:province":"CA",
    "sg:tags":[
        "steel",
        "erectors"
    ],
    "wof:name":"Sanco Steel Erector",
    "wof:placetype":"venue"
},
  "geometry": {"coordinates":[-122.192166,39.740156],"type":"Point"}
}