{
  "type": "Feature",
  "properties": {
    "iso:country":"US",
    "sg:address":"140 San Felipe Rd",
    "sg:city":"Hollister",
    "sg:classifiers":[
        {
            "category":"Shopping",
            "subcategory":"Clothing, Apparel, & Fashions",
            "type":"Retail Goods"
        }
    ],
    "sg:phone":"+1 831 638 0923",
    "sg:postcode":"95023",
    "sg:province":"CA",
    "sg:tags":[
        "alteration"
    ],
    "wof:name":"Alterations Repair & More",
    "wof:placetype":"venue"
},
  "geometry": {"coordinates":[-121.402048,36.856778],"type":"Point"}
}