{
  "type": "Feature",
  "properties": {
    "addr:full":"44380 W Sundown Crest Dr La Quinta CA 92253",
    "addr:housenumber":"44380",
    "addr:postcode":"92253",
    "addr:street":"W Sundown Crest Dr",
    "iso:country":"US",
    "sg:address":"44380 W Sundown Crest Dr",
    "sg:city":"La Quinta",
    "sg:classifiers":[
        {
            "category":"Farming",
            "subcategory":"Nursery",
            "type":"Manufacturing & Wholesale Goods"
        }
    ],
    "sg:phone":"+1 760 345 7955",
    "sg:postcode":"92253",
    "sg:province":"CA",
    "sg:tags":[
        "ornamental"
    ],
    "wof:name":"Happy Plants",
    "wof:placetype":"venue"
},
  "geometry": {"coordinates":[-116.28021699999999,33.726243],"type":"Point"}
}