{
  "type": "Feature",
  "properties": {
    "iso:country":"US",
    "sg:address":"1920 Cordell Ct",
    "sg:city":"El Cajon",
    "sg:classifiers":[
        {
            "category":"Health Services",
            "subcategory":"Clinic",
            "type":"Services"
        }
    ],
    "sg:phone":"+1 619 258 7497",
    "sg:postcode":"92020",
    "sg:province":"CA",
    "sg:tags":[
        "specialty",
        "outpatient"
    ],
    "wof:name":"Bb & B Occptnal Physcl Therapy",
    "wof:placetype":"venue"
},
  "geometry": {"coordinates":[-116.983473,32.821879],"type":"Point"}
}