{
  "type": "Feature",
  "properties": {
    "addr:full":"2008 Mount Diablo Blvd Walnut Creek CA 94596",
    "addr:housenumber":"2008",
    "addr:postcode":"94596",
    "addr:street":"Mount Diablo Blvd",
    "iso:country":"US",
    "sg:address":"2008 Mount Diablo Blvd",
    "sg:city":"Walnut Creek",
    "sg:classifiers":[
        {
            "category":"Autos & Motor Vehicles",
            "subcategory":"Automobile Sales",
            "type":"Retail Goods"
        }
    ],
    "sg:phone":"+1 925 274 0713",
    "sg:postcode":"94596",
    "sg:province":"CA",
    "sg:tags":[
        "car",
        "dealer"
    ],
    "wof:name":"Grand Prix Motors Of Walnut",
    "wof:placetype":"venue"
},
  "geometry": {"coordinates":[-122.06793500000001,37.89723],"type":"Point"}
}