{
  "type": "Feature",
  "properties": {
    "addr:full":"16816 Lime Kiln Rd Sonora CA 95370",
    "addr:housenumber":"16816",
    "addr:postcode":"95370",
    "addr:street":"Lime Kiln Rd",
    "iso:country":"US",
    "sg:address":"16816 Lime Kiln Rd",
    "sg:city":"Sonora",
    "sg:classifiers":[
        {
            "category":"Real Estate",
            "subcategory":"Developer",
            "type":"Services"
        }
    ],
    "sg:phone":"+1 209 588 2755",
    "sg:postcode":"95370",
    "sg:province":"CA",
    "wof:name":"Sharp Development Inc",
    "wof:placetype":"venue"
},
  "geometry": {"coordinates":[-120.368532,37.953743],"type":"Point"}
}