{
  "type": "Feature",
  "properties": {
    "addr:full":"10615 West Pico Blvd. Cheviot Hills CA 90064",
    "addr:housenumber":"10615",
    "addr:postcode":"90064",
    "addr:street":"West Pico Blvd. Cheviot",
    "iso:country":"US",
    "sg:address":"10615 West Pico Blvd.",
    "sg:city":"Cheviot Hills",
    "sg:classifiers":[
        {
            "category":"Personal",
            "type":"Services"
        }
    ],
    "sg:phone":"+1 310 470 5020",
    "sg:postcode":"90064",
    "sg:province":"CA",
    "sg:tags":[
        "sewing",
        "alteration"
    ],
    "wof:name":"Murat European Tailoring",
    "wof:placetype":"venue"
},
  "geometry": {"coordinates":[-118.422997,34.0434],"type":"Point"}
}