{
  "type": "Feature",
  "properties": {
    "addr:full":"21309 Bloomfield Ave Lakewood CA 90715",
    "addr:housenumber":"21309",
    "addr:postcode":"90715",
    "addr:street":"Bloomfield Ave",
    "iso:country":"US",
    "sg:address":"21309 Bloomfield Ave",
    "sg:city":"Lakewood",
    "sg:classifiers":[
        {
            "category":"Real Estate",
            "subcategory":"Real Estate Operator",
            "type":"Services"
        }
    ],
    "sg:phone":"+1 562 809 3456",
    "sg:postcode":"90715",
    "sg:province":"CA",
    "sg:tags":[
        "apartment"
    ],
    "wof:name":"Seasons 2 Senior Apartments",
    "wof:placetype":"venue"
},
  "geometry": {"coordinates":[-118.06300400000001,33.835602],"type":"Point"}
}