{
  "type": "Feature",
  "properties": {
    "iso:country":"US",
    "sg:address":"3783 20th St",
    "sg:city":"San Francisco",
    "sg:classifiers":[
        {
            "category":"Real Estate",
            "subcategory":"Real Estate Services",
            "type":"Services"
        }
    ],
    "sg:phone":"+1 415 824 1538",
    "sg:postcode":"94110",
    "sg:province":"CA",
    "sg:tags":[
        "management",
        "property"
    ],
    "wof:name":"Trophy Properties",
    "wof:placetype":"venue"
},
  "geometry": {"coordinates":[-122.425316,37.758124],"type":"Point"}
}