{
  "type": "Feature",
  "properties": {
    "addr:full":"960 Vine Street Los Angeles CA 90038",
    "addr:housenumber":"960",
    "addr:postcode":"90038",
    "addr:street":"Vine Street",
    "iso:country":"US",
    "sg:address":"960 Vine Street",
    "sg:city":"Los Angeles",
    "sg:classifiers":[
        {
            "category":"Food & Beverages",
            "subcategory":"Groceries & Convenience Stores",
            "type":"Retail Goods"
        }
    ],
    "sg:phone":"+1 323 469 3975",
    "sg:postcode":"90038",
    "sg:province":"CA",
    "wof:name":"El Rancho Super Market",
    "wof:placetype":"venue"
},
  "geometry": {"coordinates":[-118.326491,34.088468],"type":"Point"}
}