{
  "type": "Feature",
  "properties": {
    "iso:country":"US",
    "sg:address":"2050 1st St",
    "sg:city":"Simi Valley",
    "sg:classifiers":[
        {
            "category":"Personal",
            "subcategory":"Beauty Salon",
            "type":"Services"
        }
    ],
    "sg:phone":"+1 805 579 7942",
    "sg:postcode":"93065",
    "sg:province":"CA",
    "sg:tags":[
        "shop",
        "equipment",
        "establishment"
    ],
    "wof:name":"Pro Beauty Center 3",
    "wof:placetype":"venue"
},
  "geometry": {"coordinates":[-118.778821,34.275372],"type":"Point"}
}