{
  "type": "Feature",
  "properties": {
    "addr:full":"15243 Vanowen St Van Nuys CA 91405",
    "addr:housenumber":"15243",
    "addr:postcode":"91405",
    "addr:street":"Vanowen St",
    "iso:country":"US",
    "sg:address":"15243 Vanowen St",
    "sg:city":"Van Nuys",
    "sg:classifiers":[
        {
            "category":"Health Services",
            "subcategory":"Doctor",
            "type":"Services"
        }
    ],
    "sg:phone":"+1 818 785 7777",
    "sg:postcode":"91405",
    "sg:province":"CA",
    "sg:tags":[
        "physician",
        "surgeon"
    ],
    "wof:name":"Ludmila Elgourt MD",
    "wof:placetype":"venue"
},
  "geometry": {"coordinates":[-118.465504,34.193992],"type":"Point"}
}