{
  "type": "Feature",
  "properties": {
    "iso:country":"US",
    "sg:address":"13744 S Milliken Ave",
    "sg:city":"Ontario",
    "sg:classifiers":[
        {
            "category":"Farming",
            "subcategory":"Dairy Farm",
            "type":"Manufacturing & Wholesale Goods"
        }
    ],
    "sg:phone":"+1 909 947 0609",
    "sg:postcode":"91761",
    "sg:province":"CA",
    "wof:name":"Heritage Dairy",
    "wof:placetype":"venue"
},
  "geometry": {"coordinates":[-117.558443,33.990551],"type":"Point"}
}