{
  "type": "Feature",
  "properties": {
    "addr:full":"6501 Hollywood Blvd Los Angeles CA 90028",
    "addr:housenumber":"6501",
    "addr:postcode":"90028",
    "addr:street":"Hollywood Blvd",
    "iso:country":"US",
    "sg:address":"6501 Hollywood Blvd",
    "sg:city":"Los Angeles",
    "sg:classifiers":[
        {
            "category":"Shopping",
            "subcategory":"Clothing, Apparel, & Fashions",
            "type":"Retail Goods"
        }
    ],
    "sg:phone":"+1 323 463 8098",
    "sg:postcode":"90028",
    "sg:province":"CA",
    "sg:tags":[
        "men's",
        "clothing"
    ],
    "wof:name":"Designer Suit Outlet",
    "wof:placetype":"venue"
},
  "geometry": {"coordinates":[-118.331226,34.101863],"type":"Point"}
}