{
  "type": "Feature",
  "properties": {
    "addr:full":"1246 E Main St El Cajon CA 92021",
    "addr:housenumber":"1246",
    "addr:postcode":"92021",
    "addr:street":"E Main St",
    "iso:country":"US",
    "sg:address":"1246 E Main St",
    "sg:city":"El Cajon",
    "sg:classifiers":[
        {
            "category":"Professional",
            "subcategory":"Business Services",
            "type":"Services"
        }
    ],
    "sg:phone":"+1 619 447 1120",
    "sg:postcode":"92021",
    "sg:province":"CA",
    "wof:name":"San Diego Phone Cards",
    "wof:placetype":"venue"
},
  "geometry": {"coordinates":[-116.939852,32.794994],"type":"Point"}
}