{
  "type": "Feature",
  "properties": {
    "addr:full":"2335 Mountain Ave Duarte CA 91010",
    "addr:housenumber":"2335",
    "addr:postcode":"91010",
    "addr:street":"Mountain Ave",
    "iso:country":"US",
    "sg:address":"2335 Mountain Ave",
    "sg:city":"Duarte",
    "sg:classifiers":[
        {
            "category":"Health Services",
            "subcategory":"Nursing And Care Facility",
            "type":"Services"
        }
    ],
    "sg:phone":"+1 626 357 3207",
    "sg:postcode":"91010",
    "sg:province":"CA",
    "sg:tags":[
        "residential"
    ],
    "wof:name":"Community Care Center Inc",
    "wof:placetype":"venue"
},
  "geometry": {"coordinates":[-117.990454,34.12265],"type":"Point"}
}