{
  "type": "Feature",
  "properties": {
    "iso:country":"US",
    "sg:address":"11057 Balboa Blvd",
    "sg:city":"Granada Hills",
    "sg:classifiers":[
        {
            "category":"Banks & Credit Unions",
            "subcategory":"Bank",
            "type":"Services"
        }
    ],
    "sg:phone":"+1 818 887 5033",
    "sg:postcode":"91344",
    "sg:province":"CA",
    "sg:tags":[
        "cashing",
        "check"
    ],
    "wof:name":"E Z Check Advance",
    "wof:placetype":"venue"
},
  "geometry": {"coordinates":[-118.502297,34.269184],"type":"Point"}
}