{
  "type": "Feature",
  "properties": {
    "iso:country":"US",
    "sg:address":"69 Market St",
    "sg:city":"Venice",
    "sg:classifiers":[
        {
            "category":"Building & Trades",
            "subcategory":"Construction",
            "type":"Services"
        }
    ],
    "sg:phone":"+1 310 664 0900",
    "sg:postcode":"90291",
    "sg:province":"CA",
    "sg:tags":[
        "contractor"
    ],
    "sg:website":"www.sealevelvenice.com",
    "wof:name":"Sea Level",
    "wof:placetype":"venue"
},
  "geometry": {"coordinates":[-118.47336199999999,33.987948],"type":"Point"}
}