{
  "type": "Feature",
  "properties": {
    "iso:country":"US",
    "sg:address":"40228 Banyan St",
    "sg:city":"Murrieta",
    "sg:classifiers":[
        {
            "category":"Manufacturing",
            "subcategory":"Printing",
            "type":"Manufacturing & Wholesale Goods"
        }
    ],
    "sg:phone":"+1 951 461 6677",
    "sg:postcode":"92563",
    "sg:province":"CA",
    "sg:tags":[
        "commercial"
    ],
    "wof:name":"One Eye Graphics",
    "wof:placetype":"venue"
},
  "geometry": {"coordinates":[-117.164516,33.545362],"type":"Point"}
}