{
  "type": "Feature",
  "properties": {
    "addr:full":"4174 Lanai Rd Encino CA 91436",
    "addr:housenumber":"4174",
    "addr:postcode":"91436",
    "addr:street":"Lanai Rd",
    "iso:country":"US",
    "sg:address":"4174 Lanai Rd",
    "sg:city":"Encino",
    "sg:classifiers":[
        {
            "category":"Professional",
            "subcategory":"Business Services",
            "type":"Services"
        }
    ],
    "sg:phone":"+1 818 905 0700",
    "sg:postcode":"91436",
    "sg:province":"CA",
    "wof:name":"Business Products Group",
    "wof:placetype":"venue"
},
  "geometry": {"coordinates":[-118.493078,34.146638],"type":"Point"}
}