{
  "type": "Feature",
  "properties": {
    "addr:full":"4901 Topanga Canyon Blvd Woodland Hills CA 91364",
    "addr:housenumber":"4901",
    "addr:postcode":"91364",
    "addr:street":"Topanga Canyon Blvd",
    "iso:country":"US",
    "sg:address":"4901 Topanga Canyon Blvd",
    "sg:city":"Woodland Hills",
    "sg:classifiers":[
        {
            "category":"Wholesale",
            "subcategory":"Apparel",
            "type":"Manufacturing & Wholesale Goods"
        }
    ],
    "sg:phone":"+1 818 227 8022",
    "sg:postcode":"91364",
    "sg:province":"CA",
    "wof:name":"Boku Mangos",
    "wof:placetype":"venue"
},
  "geometry": {"coordinates":[-118.605814,34.157726],"type":"Point"}
}