{
  "type": "Feature",
  "properties": {
    "addr:full":"979 N Grand Ave Covina CA 91724",
    "addr:housenumber":"979",
    "addr:postcode":"91724",
    "addr:street":"N Grand Ave",
    "iso:country":"US",
    "sg:address":"979 N Grand Ave",
    "sg:city":"Covina",
    "sg:classifiers":[
        {
            "category":"Health Services",
            "subcategory":"Clinic",
            "type":"Services"
        },
        {
            "category":"Health Services",
            "subcategory":"Nursing And Care Facility",
            "type":"Services"
        },
        {
            "category":"Health Services",
            "subcategory":"Hospital",
            "type":"Services"
        }
    ],
    "sg:phone":"+1 626 938 0344",
    "sg:postcode":"91724",
    "sg:province":"CA",
    "sg:tags":[
        "nurses-advanced",
        "medical",
        "registry",
        "practice-arnp",
        "nurse"
    ],
    "wof:name":"Interlink Health Care",
    "wof:placetype":"venue"
},
  "geometry": {"coordinates":[-117.872649,34.094622],"type":"Point"}
}