{
  "type": "Feature",
  "properties": {
    "addr:full":"3007 W Temple Street Los Angeles CA 90026",
    "addr:housenumber":"3007",
    "addr:postcode":"90026",
    "addr:street":"W Temple Street",
    "iso:country":"US",
    "sg:address":"3007 W Temple Street",
    "sg:city":"Los Angeles",
    "sg:classifiers":[
        {
            "category":"Building & Trades",
            "subcategory":"Cleaning & Sanitation",
            "type":"Services"
        }
    ],
    "sg:phone":"+1 213 388 0148",
    "sg:postcode":"90026",
    "sg:province":"CA",
    "sg:tags":[
        "carpet"
    ],
    "wof:name":"Monarch Carpet & Upholstery Cleaners",
    "wof:placetype":"venue"
},
  "geometry": {"coordinates":[-118.279532,34.074444],"type":"Point"}
}