{
  "type": "Feature",
  "properties": {
    "addr:full":"2201 S Carmelina Ave Los Angeles CA 90064",
    "addr:housenumber":"2201",
    "addr:postcode":"90064",
    "addr:street":"S Carmelina Ave",
    "iso:country":"US",
    "sg:address":"2201 S Carmelina Ave",
    "sg:city":"Los Angeles",
    "sg:classifiers":[
        {
            "category":"Communications",
            "subcategory":"Film & Video Production",
            "type":"Services"
        }
    ],
    "sg:phone":"+1 310 826 6200",
    "sg:postcode":"90064",
    "sg:province":"CA",
    "sg:tags":[
        "television",
        "commercial"
    ],
    "sg:website":"www.mjz.com",
    "wof:name":"MJZ",
    "wof:placetype":"venue"
},
  "geometry": {"coordinates":[-118.454033,34.028983],"type":"Point"}
}