{
  "type": "Feature",
  "properties": {
    "iso:country":"US",
    "sg:address":"953 W El Camino Real",
    "sg:city":"Sunnyvale",
    "sg:classifiers":[
        {
            "category":"Autos & Motor Vehicles",
            "subcategory":"Automobile Sales",
            "type":"Retail Goods"
        }
    ],
    "sg:phone":"+1 408 660 3669",
    "sg:postcode":"94087",
    "sg:province":"CA",
    "sg:tags":[
        "car"
    ],
    "sg:website":"www.aagcars.com",
    "wof:name":"Axiom Auto Group",
    "wof:placetype":"venue"
},
  "geometry": {"coordinates":[-122.04650100000001,37.371893],"type":"Point"}
}