{
  "type": "Feature",
  "properties": {
    "iso:country":"US",
    "sg:address":"1556 Halford Ave",
    "sg:city":"Santa Clara",
    "sg:classifiers":[
        {
            "category":"Freight",
            "type":"Transportation"
        }
    ],
    "sg:phone":"+1 408 244 8553",
    "sg:postcode":"95051",
    "sg:province":"CA",
    "sg:tags":[
        "delivery",
        "courier"
    ],
    "wof:name":"One in A Million Delivery Service",
    "wof:placetype":"venue"
},
  "geometry": {"coordinates":[-121.999286,37.354022],"type":"Point"}
}