{
  "type": "Feature",
  "properties": {
    "iso:country":"US",
    "sg:address":"1525 Tahoe Ct",
    "sg:city":"Redding",
    "sg:classifiers":[
        {
            "category":"Building & Trades",
            "subcategory":"Construction",
            "type":"Services"
        }
    ],
    "sg:phone":"+1 530 241 2992",
    "sg:postcode":"96003",
    "sg:province":"CA",
    "sg:tags":[
        "pipe",
        "line",
        "contractor"
    ],
    "wof:name":"N & T Digmore Inc",
    "wof:placetype":"venue"
},
  "geometry": {"coordinates":[-122.384323,40.631685],"type":"Point"}
}