{
  "type": "Feature",
  "properties": {
    "iso:country":"US",
    "sg:address":"3555 El Camino Ave",
    "sg:city":"Sacramento",
    "sg:classifiers":[
        {
            "category":"Home & Garden",
            "subcategory":"Garden Supply",
            "type":"Retail Goods"
        },
        {
            "category":"Home & Garden",
            "subcategory":"Hardware",
            "type":"Retail Goods"
        }
    ],
    "sg:phone":"+1 916 482 1900",
    "sg:postcode":"95821",
    "sg:province":"CA",
    "sg:tags":[
        "nursery",
        "gardening",
        "store"
    ],
    "sg:website":"www.emigh.com",
    "wof:name":"Emigh Hardware",
    "wof:placetype":"venue"
},
  "geometry": {"coordinates":[-121.381011,38.61047],"type":"Point"}
}