{
  "type": "Feature",
  "properties": {
    "addr:full":"11250 Los Alamitos Blvd Los Alamitos CA 90720",
    "addr:housenumber":"11250",
    "addr:postcode":"90720",
    "addr:street":"Los Alamitos Blvd",
    "iso:country":"US",
    "sg:address":"11250 Los Alamitos Blvd",
    "sg:city":"Los Alamitos",
    "sg:classifiers":[
        {
            "category":"Fast Food",
            "type":"Food & Drink"
        }
    ],
    "sg:phone":"+1 562 598 6302",
    "sg:postcode":"90720",
    "sg:province":"CA",
    "sg:tags":[
        "burger"
    ],
    "sg:website":"www.jackinthebox.com",
    "wof:name":"Jack In The Box",
    "wof:placetype":"venue"
},
  "geometry": {"coordinates":[-118.07182299999999,33.799387],"type":"Point"}
}