{
  "type": "Feature",
  "properties": {
    "addr:full":"634 E Lockeford St Lodi CA 95240",
    "addr:housenumber":"634",
    "addr:postcode":"95240",
    "addr:street":"E Lockeford St",
    "iso:country":"US",
    "sg:address":"634 E Lockeford St",
    "sg:city":"Lodi",
    "sg:classifiers":[
        {
            "category":"Autos & Motor Vehicles",
            "subcategory":"Automobile Sales",
            "type":"Retail Goods"
        }
    ],
    "sg:phone":"+1 209 365 6315",
    "sg:postcode":"95240",
    "sg:province":"CA",
    "sg:tags":[
        "classic"
    ],
    "wof:name":"Galvin's AMC Rambler Parts",
    "wof:placetype":"venue"
},
  "geometry": {"coordinates":[-121.259731,38.138258],"type":"Point"}
}