{
  "type": "Feature",
  "properties": {
    "addr:full":"840 Guadalupe Pkwy San Jose CA 95110",
    "addr:housenumber":"840",
    "addr:postcode":"95110",
    "addr:street":"Guadalupe Pkwy",
    "iso:country":"US",
    "sg:address":"840 Guadalupe Pkwy",
    "sg:city":"San Jose",
    "sg:classifiers":[
        {
            "category":"Government",
            "subcategory":"Office",
            "type":"Public Place"
        }
    ],
    "sg:phone":"+1 408 808 6200",
    "sg:postcode":"95110",
    "sg:province":"CA",
    "wof:name":"Santa Clara Juvenile Dlnqncy",
    "wof:placetype":"venue"
},
  "geometry": {"coordinates":[-121.90848699999999,37.34933],"type":"Point"}
}