{
  "type": "Feature",
  "properties": {
    "iso:country":"US",
    "sg:address":"9053 Nemo Street",
    "sg:city":"West Hollywood",
    "sg:classifiers":[
        {
            "category":"Shopping",
            "subcategory":"Beauty & Cosmetics",
            "type":"Retail Goods"
        },
        {
            "category":"Personal",
            "subcategory":"Skin Care",
            "type":"Services"
        }
    ],
    "sg:phone":"+1 310 275 6453",
    "sg:postcode":"90069",
    "sg:province":"CA",
    "sg:tags":[
        "supply"
    ],
    "sg:website":"www.myspanetwork.com/thenileinst...",
    "wof:name":"The Nile Institute",
    "wof:placetype":"venue"
},
  "geometry": {"coordinates":[-118.388559,34.082146],"type":"Point"}
}