{
  "type": "Feature",
  "properties": {
    "addr:full":"419 Main St Huntington Beach CA 92648",
    "addr:housenumber":"419",
    "addr:postcode":"92648",
    "addr:street":"Main St",
    "iso:country":"US",
    "sg:address":"419 Main St",
    "sg:city":"Huntington Beach",
    "sg:classifiers":[
        {
            "category":"Wholesale",
            "subcategory":"Machinery & Supplies",
            "type":"Manufacturing & Wholesale Goods"
        }
    ],
    "sg:phone":"+1 714 960 7725",
    "sg:postcode":"92648",
    "sg:province":"CA",
    "sg:tags":[
        "industrial"
    ],
    "wof:name":"Automotive Parts Marketing",
    "wof:placetype":"venue"
},
  "geometry": {"coordinates":[-117.99897799999999,33.660304],"type":"Point"}
}