{
  "type": "Feature",
  "properties": {
    "addr:full":"664 Azalea Ave Redding CA 96002",
    "addr:housenumber":"664",
    "addr:postcode":"96002",
    "addr:street":"Azalea Ave",
    "iso:country":"US",
    "sg:address":"664 Azalea Ave",
    "sg:city":"Redding",
    "sg:classifiers":[
        {
            "category":"Health Services",
            "subcategory":"Chiropractor",
            "type":"Services"
        }
    ],
    "sg:phone":"+1 530 221 8750",
    "sg:postcode":"96002",
    "sg:province":"CA",
    "wof:name":"Susan P Bailey DC",
    "wof:placetype":"venue"
},
  "geometry": {"coordinates":[-122.35941099999999,40.57748],"type":"Point"}
}