{
  "type": "Feature",
  "properties": {
    "addr:full":"18418 Vanowen St Reseda CA 91335",
    "addr:postcode":"18418;91335",
    "addr:street":"Vanowen St",
    "iso:country":"US",
    "sg:address":"18418 Vanowen St",
    "sg:city":"Reseda",
    "sg:classifiers":[
        {
            "category":"Retail",
            "subcategory":"Auto Repair",
            "type":"Services"
        }
    ],
    "sg:phone":"+1 818 345 7664",
    "sg:postcode":"91335",
    "sg:province":"CA",
    "sg:tags":[
        "automobile",
        "smog"
    ],
    "wof:name":"Vanowen Test-Only Ctr",
    "wof:placetype":"venue"
},
  "geometry": {"coordinates":[-118.53435399999999,34.19378],"type":"Point"}
}