{
  "type": "Feature",
  "properties": {
    "iso:country":"US",
    "sg:address":"13212 Magnolia St Ofc",
    "sg:city":"Garden Grove",
    "sg:classifiers":[
        {
            "category":"Real Estate",
            "subcategory":"Real Estate Operator",
            "type":"Services"
        }
    ],
    "sg:phone":"+1 714 537 8500",
    "sg:postcode":"92844",
    "sg:province":"CA",
    "sg:tags":[
        "apartment"
    ],
    "sg:website":"www.ranchomonterey.com",
    "wof:name":"Rancho Monterey Apartments",
    "wof:placetype":"venue"
},
  "geometry": {"coordinates":[-117.97199999999999,33.770699],"type":"Point"}
}