{
  "type": "Feature",
  "properties": {
    "addr:full":"420 Taylor St San Francisco CA 94102",
    "addr:housenumber":"420",
    "addr:postcode":"94102",
    "addr:street":"Taylor St",
    "iso:country":"US",
    "sg:address":"420 Taylor St",
    "sg:city":"San Francisco",
    "sg:classifiers":[
        {
            "category":"Parking",
            "type":"Transportation"
        }
    ],
    "sg:postcode":"94102",
    "sg:province":"CA",
    "wof:name":"Ampco System Parking",
    "wof:placetype":"venue"
},
  "geometry": {"coordinates":[-122.41103099999999,37.786332],"type":"Point"}
}