{
  "type": "Feature",
  "properties": {
    "addr:full":"2602 Portola Dr Santa Cruz CA 95062",
    "addr:housenumber":"2602",
    "addr:postcode":"95062",
    "addr:street":"Portola Dr",
    "iso:country":"US",
    "sg:address":"2602 Portola Dr",
    "sg:city":"Santa Cruz",
    "sg:classifiers":[
        {
            "category":"Building & Trades",
            "subcategory":"Equipment Rental",
            "type":"Services"
        }
    ],
    "sg:phone":"+1 831 462 9141",
    "sg:postcode":"95062",
    "sg:province":"CA",
    "sg:tags":[
        "instrument",
        "musical"
    ],
    "wof:name":"Piano Studio",
    "wof:placetype":"venue"
},
  "geometry": {"coordinates":[-121.974097,36.963379],"type":"Point"}
}