{
  "type": "Feature",
  "properties": {
    "addr:full":"2106 Chestnut St San Francisco CA 94123",
    "addr:housenumber":"2106",
    "addr:postcode":"94123",
    "addr:street":"Chestnut St",
    "iso:country":"US",
    "sg:address":"2106 Chestnut St",
    "sg:city":"San Francisco",
    "sg:classifiers":[
        {
            "category":"Shopping",
            "subcategory":"Beauty & Cosmetics",
            "type":"Retail Goods"
        }
    ],
    "sg:phone":"+1 415 292 9970",
    "sg:postcode":"94123",
    "sg:province":"CA",
    "sg:tags":[
        "supply"
    ],
    "sg:website":"www.lalineusa.com",
    "wof:name":"Laline",
    "wof:placetype":"venue"
},
  "geometry": {"coordinates":[-122.43788600000001,37.800625],"type":"Point"}
}