{
  "type": "Feature",
  "properties": {
    "addr:full":"2120 Professional Dr Roseville CA 95661",
    "addr:housenumber":"2120",
    "addr:postcode":"95661",
    "addr:street":"Professional Dr",
    "iso:country":"US",
    "sg:address":"2120 Professional Dr",
    "sg:city":"Roseville",
    "sg:classifiers":[
        {
            "category":"Insurance",
            "subcategory":"Health Insurance",
            "type":"Services"
        }
    ],
    "sg:phone":"+1 916 771 6680",
    "sg:postcode":"95661",
    "sg:province":"CA",
    "sg:tags":[
        "maintenance"
    ],
    "sg:website":"http://www.kaiserpermanente.org",
    "wof:name":"Kaiser Permanente Health Care",
    "wof:placetype":"venue"
},
  "geometry": {"coordinates":[-121.252967,38.742156],"type":"Point"}
}