{
  "type": "Feature",
  "properties": {
    "iso:country":"US",
    "sg:address":"1501 5th Ave",
    "sg:city":"San Diego",
    "sg:classifiers":[
        {
            "category":"Professional",
            "subcategory":"Accounting & Tax Preparation",
            "type":"Services"
        }
    ],
    "sg:phone":"+1 619 615 3800",
    "sg:postcode":"92101",
    "sg:province":"CA",
    "sg:tags":[
        "accountant"
    ],
    "sg:website":"www.cccpa.com",
    "wof:name":"Considine & Considine",
    "wof:placetype":"venue"
},
  "geometry": {"coordinates":[-117.160213,32.721987],"type":"Point"}
}