{
  "type": "Feature",
  "properties": {
    "addr:full":"9562 Garden Grove Blvd Garden Grove CA 92844",
    "addr:housenumber":"9562",
    "addr:postcode":"92844",
    "addr:street":"Garden Grove Blvd",
    "iso:country":"US",
    "sg:address":"9562 Garden Grove Blvd",
    "sg:city":"Garden Grove",
    "sg:classifiers":[
        {
            "category":"Wholesale",
            "subcategory":"Computers",
            "type":"Manufacturing & Wholesale Goods"
        }
    ],
    "sg:phone":"+1 714 590 9504",
    "sg:postcode":"92844",
    "sg:province":"CA",
    "wof:name":"Cybertech",
    "wof:placetype":"venue"
},
  "geometry": {"coordinates":[-117.966003,33.773899],"type":"Point"}
}