{
  "type": "Feature",
  "properties": {
    "iso:country":"US",
    "sg:address":"1735 Le Roy Ave",
    "sg:city":"Berkeley",
    "sg:classifiers":[
        {
            "category":"Education",
            "subcategory":"University",
            "type":"Public Place"
        }
    ],
    "sg:phone":"+1 510 549 5000",
    "sg:postcode":"94709",
    "sg:province":"CA",
    "sg:tags":[
        "college"
    ],
    "wof:name":"Jesuit School of Theology",
    "wof:placetype":"venue"
},
  "geometry": {"coordinates":[-122.25846900000001,37.879089],"type":"Point"}
}