{
  "type": "Feature",
  "properties": {
    "addr:full":"144 E 2nd St Calexico CA 92231",
    "addr:housenumber":"144",
    "addr:postcode":"92231",
    "addr:street":"E 2Nd St",
    "iso:country":"US",
    "sg:address":"144 E 2nd St",
    "sg:city":"Calexico",
    "sg:classifiers":[
        {
            "category":"Restaurant",
            "type":"Food & Drink"
        }
    ],
    "sg:phone":"+1 760 357 4595",
    "sg:postcode":"92231",
    "sg:province":"CA",
    "wof:name":"Fiesta Restaurant",
    "wof:placetype":"venue"
},
  "geometry": {"coordinates":[-115.497,32.666616],"type":"Point"}
}