{
  "type": "Feature",
  "properties": {
    "addr:full":"109 N Main Ave Fallbrook CA 92028",
    "addr:housenumber":"109",
    "addr:postcode":"92028",
    "addr:street":"N Main Ave",
    "iso:country":"US",
    "sg:address":"109 N Main Ave",
    "sg:city":"Fallbrook",
    "sg:classifiers":[
        {
            "category":"Shopping",
            "subcategory":"Florist",
            "type":"Retail Goods"
        }
    ],
    "sg:phone":"+1 760 723 0334",
    "sg:postcode":"92028",
    "sg:province":"CA",
    "wof:name":"Chubby Chix",
    "wof:placetype":"venue"
},
  "geometry": {"coordinates":[-117.251293,33.382753],"type":"Point"}
}