{
  "type": "Feature",
  "properties": {
    "iso:country":"US",
    "sg:address":"916 J Street",
    "sg:city":"Sacramento",
    "sg:classifiers":[
        {
            "category":"Shopping",
            "subcategory":"Jewelry",
            "type":"Retail Goods"
        },
        {
            "category":"Shopping",
            "subcategory":"Pawn Shop",
            "type":"Retail Goods"
        }
    ],
    "sg:phone":"+1 916 446 6175",
    "sg:postcode":"95814",
    "sg:province":"CA",
    "wof:name":"New York Loan Company",
    "wof:placetype":"venue"
},
  "geometry": {"coordinates":[-121.49381700000001,38.58028],"type":"Point"}
}