{
  "type": "Feature",
  "properties": {
    "iso:country":"US",
    "sg:address":"1626 Mount Silliman Way",
    "sg:city":"Antioch",
    "sg:classifiers":[
        {
            "category":"Professional",
            "type":"Services"
        }
    ],
    "sg:phone":"+1 925 754 4337",
    "sg:postcode":"94531",
    "sg:province":"CA",
    "wof:name":"Antenna Cross Co",
    "wof:placetype":"venue"
},
  "geometry": {"coordinates":[-121.795663,37.968112],"type":"Point"}
}