{
  "type": "Feature",
  "properties": {
    "addr:full":"6105 Stockton Blvd Sacramento CA 95824",
    "addr:housenumber":"6105",
    "addr:postcode":"95824",
    "addr:street":"Stockton Blvd",
    "iso:country":"US",
    "sg:address":"6105 Stockton Blvd",
    "sg:city":"Sacramento",
    "sg:classifiers":[
        {
            "category":"Deli",
            "type":"Food & Drink"
        },
        {
            "category":"Food & Beverages",
            "subcategory":"Ethnic Foods",
            "type":"Retail Goods"
        },
        {
            "category":"Food & Beverages",
            "subcategory":"Groceries & Convenience Stores",
            "type":"Retail Goods"
        }
    ],
    "sg:phone":"+1 916 424 8613",
    "sg:postcode":"95824",
    "sg:province":"CA",
    "wof:name":"Vinh Phat Market",
    "wof:placetype":"venue"
},
  "geometry": {"coordinates":[-121.43800400000001,38.515301],"type":"Point"}
}