{
  "type": "Feature",
  "properties": {
    "addr:full":"1117 Parkview Ave Redding CA 96001",
    "addr:housenumber":"1117",
    "addr:postcode":"96001",
    "addr:street":"Parkview Ave",
    "iso:country":"US",
    "sg:address":"1117 Parkview Ave",
    "sg:city":"Redding",
    "sg:classifiers":[
        {
            "category":"Wholesale",
            "subcategory":"Auto Parts",
            "type":"Manufacturing & Wholesale Goods"
        }
    ],
    "sg:phone":"+1 530 246 4264",
    "sg:postcode":"96001",
    "sg:province":"CA",
    "sg:tags":[
        "automobile",
        "supply"
    ],
    "sg:website":"www.wolfgangint.com",
    "wof:name":"Wolfgang International",
    "wof:placetype":"venue"
},
  "geometry": {"coordinates":[-122.38596699999999,40.573106],"type":"Point"}
}