{
  "type": "Feature",
  "properties": {
    "iso:country":"US",
    "sg:address":"764 Grayson Rd",
    "sg:city":"Pleasant Hill",
    "sg:classifiers":[
        {
            "category":"Health Services",
            "subcategory":"Doctor",
            "type":"Services"
        }
    ],
    "sg:phone":"+1 925 939 6100",
    "sg:postcode":"94523",
    "sg:province":"CA",
    "sg:tags":[
        "dentist"
    ],
    "wof:name":"Robert P Rogers DDS",
    "wof:placetype":"venue"
},
  "geometry": {"coordinates":[-122.087249,37.947796],"type":"Point"}
}