{
  "type": "Feature",
  "properties": {
    "iso:country":"US",
    "sg:address":"3780 Wallace Creek Rd",
    "sg:city":"Healdsburg",
    "sg:classifiers":[
        {
            "category":"Professional",
            "type":"Services"
        }
    ],
    "sg:phone":"+1 707 431 8790",
    "sg:postcode":"95448",
    "sg:province":"CA",
    "wof:name":"Peter Cole",
    "wof:placetype":"venue"
},
  "geometry": {"coordinates":[-122.938393,38.612943],"type":"Point"}
}