{
  "type": "Feature",
  "properties": {
    "iso:country":"US",
    "sg:address":"175 E Vineyard Ave",
    "sg:city":"Livermore",
    "sg:classifiers":[
        {
            "category":"Restaurant",
            "type":"Food & Drink"
        },
        {
            "category":"Retail",
            "subcategory":"Event Space",
            "type":"Services"
        }
    ],
    "sg:phone":"+1 925 249 9800",
    "sg:postcode":"94550",
    "sg:province":"CA",
    "sg:tags":[
        "facility",
        "hall",
        "planning",
        "reception",
        "meeting",
        "banquet",
        "italian"
    ],
    "sg:website":"http://www.campodibocce.com",
    "wof:name":"Campo Di Bocce Of Livermore",
    "wof:placetype":"venue"
},
  "geometry": {"coordinates":[-121.802443,37.650929],"type":"Point"}
}