{
  "type": "Feature",
  "properties": {
    "iso:country":"US",
    "sg:address":"23042 Mill Creek Dr",
    "sg:city":"Laguna Hills",
    "sg:classifiers":[
        {
            "category":"Insurance",
            "subcategory":"Insurance Agent",
            "type":"Services"
        }
    ],
    "sg:phone":"+1 949 768 1180",
    "sg:postcode":"92653",
    "sg:province":"CA",
    "sg:website":"www.suncoastinsurance.com",
    "wof:name":"Sun Coast General Insurance",
    "wof:placetype":"venue"
},
  "geometry": {"coordinates":[-117.734281,33.624917],"type":"Point"}
}