{
  "type": "Feature",
  "properties": {
    "addr:full":"44740 Ranchwood Ave Lancaster CA 93536",
    "addr:postcode":"44740;93536",
    "addr:street":"Ranchwood Ave",
    "iso:country":"US",
    "sg:address":"44740 Ranchwood Ave",
    "sg:city":"Lancaster",
    "sg:classifiers":[
        {
            "category":"Shopping",
            "subcategory":"Jewelry",
            "type":"Retail Goods"
        },
        {
            "category":"Manufacturing",
            "subcategory":"Jewelry",
            "type":"Manufacturing & Wholesale Goods"
        }
    ],
    "sg:phone":"+1 661 917 4285",
    "sg:postcode":"93536",
    "sg:province":"CA",
    "sg:tags":[
        "designer",
        "jeweler"
    ],
    "wof:name":"The Midas Touch",
    "wof:placetype":"venue"
},
  "geometry": {"coordinates":[-118.183144,34.695442],"type":"Point"}
}