{
  "type": "Feature",
  "properties": {
    "addr:full":"21370 Homestead Rd Cupertino CA 95014",
    "addr:housenumber":"21370",
    "addr:postcode":"95014",
    "addr:street":"Homestead Rd",
    "iso:country":"US",
    "sg:address":"21370 Homestead Rd",
    "sg:city":"Cupertino",
    "sg:classifiers":[
        {
            "category":"Education",
            "subcategory":"School",
            "type":"Public Place"
        }
    ],
    "sg:phone":"+1 408 522 2500",
    "sg:postcode":"95014",
    "sg:province":"CA",
    "sg:tags":[
        "high",
        "middle"
    ],
    "sg:website":"www.hhs.fuhsd.org/",
    "wof:name":"Homestead High School",
    "wof:placetype":"venue"
},
  "geometry": {"coordinates":[-122.048574,37.337505],"type":"Point"}
}