{
  "type": "Feature",
  "properties": {
    "addr:full":"6205 Engel Way Gilroy CA 95020",
    "addr:housenumber":"6205",
    "addr:postcode":"95020",
    "addr:street":"Engel Way",
    "iso:country":"US",
    "sg:address":"6205 Engel Way",
    "sg:city":"Gilroy",
    "sg:classifiers":[
        {
            "category":"Sports & Exercise",
            "subcategory":"Race Track",
            "type":"Entertainment"
        }
    ],
    "sg:phone":"+1 408 842 9290",
    "sg:postcode":"95020",
    "sg:province":"CA",
    "wof:name":"Fox Racing",
    "wof:placetype":"venue"
},
  "geometry": {"coordinates":[-121.554991,36.990108],"type":"Point"}
}