{
  "type": "Feature",
  "properties": {
    "iso:country":"US",
    "sfac:artist":"Frey, Viola",
    "sfac:created_at":"01/01/1970 12:33:19 AM +0000",
    "sfac:credit_line":"Commissioned for the San Francisco International Airport; Collection of the City and County of San Francisco.",
    "sfac:display_dimensions":"180\" H X 240\" W",
    "sfac:location_description":"Airport : IT : Boarding Area A : Departures, A4",
    "sfac:medium":"Ceramic tile",
    "sfac:revision":"2-555fd99e2c3f7bc4e4e59792aea675fd",
    "sfac:title":"World Civilization",
    "wof:name":"World Civilization",
    "wof:placetype":"venue"
},
  "geometry": {"coordinates":[-122.389979,37.615223],"type":"Point"}
}