{
  "type": "Feature",
  "properties": {
    "iso:country":"US",
    "sg:address":"4227 University Ave",
    "sg:city":"San Diego",
    "sg:classifiers":[
        {
            "category":"Shopping",
            "subcategory":"Jewelry",
            "type":"Retail Goods"
        }
    ],
    "sg:phone":"+1 619 640 6616",
    "sg:postcode":"92105",
    "sg:province":"CA",
    "wof:name":"Joyeria Garcia's",
    "wof:placetype":"venue"
},
  "geometry": {"coordinates":[-117.10373800000001,32.749511],"type":"Point"}
}