{
  "type": "Feature",
  "properties": {
    "iso:country":"US",
    "sg:address":"5476 Willow Woods Ln",
    "sg:city":"Anaheim",
    "sg:classifiers":[
        {
            "category":"Autos & Motor Vehicles",
            "subcategory":"Automobile Sales",
            "type":"Retail Goods"
        }
    ],
    "sg:phone":"+1 714 336 0423",
    "sg:postcode":"92807",
    "sg:province":"CA",
    "sg:tags":[
        "car",
        "dealer"
    ],
    "wof:name":"Fernandez Auto Sales",
    "wof:placetype":"venue"
},
  "geometry": {"coordinates":[-117.794426,33.865059],"type":"Point"}
}