{
  "type": "Feature",
  "properties": {
    "addr:full":"50 California St Fl 15 San Francisco CA 94111",
    "addr:housenumber":"50;15",
    "addr:postcode":"94111",
    "addr:street":"California St Fl",
    "iso:country":"US",
    "sg:address":"50 California St Fl 15",
    "sg:city":"San Francisco",
    "sg:classifiers":[
        {
            "category":"Professional",
            "subcategory":"Advertising",
            "type":"Services"
        }
    ],
    "sg:phone":"+1 415 986 1743",
    "sg:postcode":"94111",
    "sg:province":"CA",
    "sg:tags":[
        "marketing"
    ],
    "sg:website":"www.waldenresearch.com/index.htm",
    "wof:name":"Walden Research",
    "wof:placetype":"venue"
},
  "geometry": {"coordinates":[-122.39734799999999,37.794053],"type":"Point"}
}