{
  "type": "Feature",
  "properties": {
    "addr:full":"1400 E Arrow Hwy Upland CA 91786",
    "addr:housenumber":"1400",
    "addr:postcode":"91786",
    "addr:street":"E Arrow Hwy",
    "iso:country":"US",
    "sg:address":"1400 E Arrow Hwy",
    "sg:city":"Upland",
    "sg:classifiers":[
        {
            "category":"Wholesale",
            "subcategory":"Construction Materials",
            "type":"Manufacturing & Wholesale Goods"
        }
    ],
    "sg:phone":"+1 909 946 3300",
    "sg:postcode":"91786",
    "sg:province":"CA",
    "wof:name":"Idaho Lumber Co",
    "wof:placetype":"venue"
},
  "geometry": {"coordinates":[-117.629676,34.09944],"type":"Point"}
}