{
  "type": "Feature",
  "properties": {
    "iso:country":"US",
    "sg:address":"962 Sebastopol Rd",
    "sg:city":"Santa Rosa",
    "sg:classifiers":[
        {
            "category":"Health Services",
            "subcategory":"Doctor",
            "type":"Services"
        }
    ],
    "sg:phone":"+1 707 578 2005",
    "sg:postcode":"95407",
    "sg:province":"CA",
    "sg:tags":[
        "clinic"
    ],
    "wof:name":"Roseland Children's Health Cen",
    "wof:placetype":"venue"
},
  "geometry": {"coordinates":[-122.731481,38.42906],"type":"Point"}
}