{
  "type": "Feature",
  "properties": {
    "iso:country":"US",
    "sg:address":"18 N East St",
    "sg:city":"Woodland",
    "sg:classifiers":[
        {
            "category":"Home & Garden",
            "subcategory":"Building Materials",
            "type":"Retail Goods"
        }
    ],
    "sg:phone":"+1 530 662 5494",
    "sg:postcode":"95776",
    "sg:province":"CA",
    "sg:tags":[
        "door"
    ],
    "sg:website":"www.eliasoncorp.com",
    "wof:name":"Eliason Corp",
    "wof:placetype":"venue"
},
  "geometry": {"coordinates":[-121.76522199999999,38.686903],"type":"Point"}
}