{
  "type": "Feature",
  "properties": {
    "iso:country":"US",
    "sg:address":"491 Seaport Ct",
    "sg:city":"Redwood City",
    "sg:classifiers":[
        {
            "category":"Real Estate",
            "subcategory":"Architect",
            "type":"Services"
        }
    ],
    "sg:phone":"+1 650 369 6400",
    "sg:postcode":"94063",
    "sg:province":"CA",
    "wof:name":"Morton Frank FAIA",
    "wof:placetype":"venue"
},
  "geometry": {"coordinates":[-122.21129999999999,37.503142],"type":"Point"}
}