{
  "type": "Feature",
  "properties": {
    "addr:full":"12076 Eagle Peak Dr Waterford CA 95386",
    "addr:housenumber":"12076",
    "addr:postcode":"95386",
    "addr:street":"Eagle Peak Dr",
    "iso:country":"US",
    "sg:address":"12076 Eagle Peak Dr",
    "sg:city":"Waterford",
    "sg:classifiers":[
        {
            "category":"Banks & Credit Unions",
            "subcategory":"Bank",
            "type":"Services"
        }
    ],
    "sg:phone":"+1 209 874 5547",
    "sg:postcode":"95386",
    "sg:province":"CA",
    "sg:tags":[
        "loan"
    ],
    "wof:name":"America's Choice Mortgage",
    "wof:placetype":"venue"
},
  "geometry": {"coordinates":[-120.771732,37.632975],"type":"Point"}
}