{
  "type": "Feature",
  "properties": {
    "iso:country":"US",
    "sg:address":"251 S Lenore Ave",
    "sg:city":"Willits",
    "sg:classifiers":[
        {
            "category":"Real Estate",
            "subcategory":"Real Estate Operator",
            "type":"Services"
        }
    ],
    "sg:phone":"+1 707 456 0552",
    "sg:postcode":"95490",
    "sg:province":"CA",
    "sg:tags":[
        "apartment"
    ],
    "wof:name":"Lenore Street Senior Housing",
    "wof:placetype":"venue"
},
  "geometry": {"coordinates":[-123.347066,39.41034],"type":"Point"}
}