{
  "type": "Feature",
  "properties": {
    "iso:country":"US",
    "sg:address":"1102 Camino Real",
    "sg:city":"Redondo Beach",
    "sg:classifiers":[
        {
            "category":"Park",
            "type":"Public Place"
        }
    ],
    "sg:phone":"+1 310 318 0668",
    "sg:postcode":"90277",
    "sg:province":"CA",
    "wof:name":"Wilderness Park",
    "wof:placetype":"venue"
},
  "geometry": {"coordinates":[-118.375,33.828999],"type":"Point"}
}