{
  "type": "Feature",
  "properties": {
    "addr:full":"11809 Del AMO Blvd Cerritos CA 90703",
    "addr:housenumber":"11809",
    "addr:postcode":"ca 90703",
    "addr:street":"Del Amo Blvd",
    "iso:country":"US",
    "sg:address":"11809 Del AMO Blvd",
    "sg:city":"Cerritos",
    "sg:classifiers":[
        {
            "category":"Shopping",
            "subcategory":"Clothing, Apparel, & Fashions",
            "type":"Retail Goods"
        }
    ],
    "sg:phone":"+1 562 809 9476",
    "sg:postcode":"90703",
    "sg:province":"CA",
    "sg:tags":[
        "accessory",
        "clothing",
        "women's"
    ],
    "wof:name":"Uni Fashion Outlet",
    "wof:placetype":"venue"
},
  "geometry": {"coordinates":[-118.08200100000001,33.846199],"type":"Point"}
}