{
  "type": "Feature",
  "properties": {
    "addr:full":"1191 Magnolia Ave Corona CA 92879",
    "addr:housenumber":"1191",
    "addr:postcode":"92879",
    "addr:street":"Magnolia Ave",
    "iso:country":"US",
    "sg:address":"1191 Magnolia Ave",
    "sg:city":"Corona",
    "sg:classifiers":[
        {
            "category":"Shopping",
            "subcategory":"Crafts & Fabrics",
            "type":"Retail Goods"
        }
    ],
    "sg:phone":"+1 951 270 0686",
    "sg:postcode":"92879",
    "sg:province":"CA",
    "sg:tags":[
        "yarn"
    ],
    "wof:name":"Kelly's Trading Co",
    "wof:placetype":"venue"
},
  "geometry": {"coordinates":[-117.54704099999999,33.863218],"type":"Point"}
}