{
  "type": "Feature",
  "properties": {
    "addr:full":"5822 Southview Dr San Jose CA 95138",
    "addr:housenumber":"5822",
    "addr:postcode":"95138",
    "addr:street":"Southview Dr",
    "iso:country":"US",
    "sg:address":"5822 Southview Dr",
    "sg:city":"San Jose",
    "sg:classifiers":[
        {
            "category":"Autos & Motor Vehicles",
            "subcategory":"Auto Supplies",
            "type":"Retail Goods"
        }
    ],
    "sg:phone":"+1 408 375 4256",
    "sg:postcode":"95138",
    "sg:province":"CA",
    "wof:name":"CHI RHO Tuning",
    "wof:placetype":"venue"
},
  "geometry": {"coordinates":[-121.782588,37.24646],"type":"Point"}
}