{
  "type": "Feature",
  "properties": {
    "addr:full":"18436 Bandilier Cir Fountain Valley CA 92708",
    "addr:postcode":"18436;92708",
    "addr:street":"Bandilier Cir",
    "iso:country":"US",
    "sg:address":"18436 Bandilier Cir",
    "sg:city":"Fountain Valley",
    "sg:classifiers":[
        {
            "category":"Wholesale",
            "subcategory":"Machinery & Supplies",
            "type":"Manufacturing & Wholesale Goods"
        }
    ],
    "sg:phone":"+1 714 965 6400",
    "sg:postcode":"92708",
    "sg:province":"CA",
    "sg:tags":[
        "equipment",
        "industrial"
    ],
    "wof:name":"Ovalstrapping Incorporated",
    "wof:placetype":"venue"
},
  "geometry": {"coordinates":[-117.94039600000001,33.694888],"type":"Point"}
}