{
  "type": "Feature",
  "properties": {
    "addr:full":"5600 H St Sacramento CA 95819",
    "addr:housenumber":"5600",
    "addr:postcode":"95819",
    "addr:street":"H St",
    "iso:country":"US",
    "sg:address":"5600 H St",
    "sg:city":"Sacramento",
    "sg:classifiers":[
        {
            "category":"Social Services",
            "subcategory":"Adult Care",
            "type":"Services"
        }
    ],
    "sg:phone":"+1 916 949 5539",
    "sg:postcode":"95819",
    "sg:province":"CA",
    "sg:tags":[
        "nurses-home"
    ],
    "wof:name":"Delfin Spa Services",
    "wof:placetype":"venue"
},
  "geometry": {"coordinates":[-121.434059,38.567379],"type":"Point"}
}