{
  "type": "Feature",
  "properties": {
    "iso:country":"US",
    "sg:address":"8550 Firestone Blvd",
    "sg:city":"Downey",
    "sg:classifiers":[
        {
            "category":"Real Estate",
            "subcategory":"Real Estate Operator",
            "type":"Services"
        }
    ],
    "sg:phone":"+1 562 904 6450",
    "sg:postcode":"90241",
    "sg:province":"CA",
    "sg:tags":[
        "building",
        "parks"
    ],
    "wof:name":"Cal Select Buildings Inc",
    "wof:placetype":"venue"
},
  "geometry": {"coordinates":[-118.128573,33.937761],"type":"Point"}
}