{
  "type": "Feature",
  "properties": {
    "addr:full":"3400 Buck Owens Blvd Bakersfield CA 93308",
    "addr:housenumber":"3400",
    "addr:postcode":"93308",
    "addr:street":"Buck Owens Blvd",
    "iso:country":"US",
    "sg:address":"3400 Buck Owens Blvd",
    "sg:city":"Bakersfield",
    "sg:classifiers":[
        {
            "category":"Building & Trades",
            "subcategory":"Cleaning & Sanitation",
            "type":"Services"
        }
    ],
    "sg:phone":"+1 661 331 5103",
    "sg:postcode":"93308",
    "sg:province":"CA",
    "sg:tags":[
        "janitor"
    ],
    "wof:name":"Bagg Lady's Janitorial",
    "wof:placetype":"venue"
},
  "geometry": {"coordinates":[-119.0431,35.390761],"type":"Point"}
}