{
  "type": "Feature",
  "properties": {
    "iso:country":"US",
    "sg:address":"1188 Yulupa Ave",
    "sg:city":"Santa Rosa",
    "sg:classifiers":[
        {
            "category":"Health Services",
            "subcategory":"Doctor",
            "type":"Services"
        }
    ],
    "sg:phone":"+1 707 528 7817",
    "sg:postcode":"95405",
    "sg:province":"CA",
    "sg:tags":[
        "physician",
        "surgeon"
    ],
    "wof:name":"Alice Chiang MD",
    "wof:placetype":"venue"
},
  "geometry": {"coordinates":[-122.674375,38.443283],"type":"Point"}
}