{
  "type": "Feature",
  "properties": {
    "addr:full":"On Board the Endeavor Yacht in Newport Beach 2901 W. Pacific Coast Highway Newport Beach CA 92663",
    "addr:housenumber":"2901",
    "addr:postcode":"92663",
    "addr:street":"W. Pacific Coast Highway",
    "iso:country":"US",
    "sg:address":"On Board the Endeavor Yacht in Newport Beach 2901 W. Pacific Coast Highway",
    "sg:city":"Newport Beach",
    "sg:classifiers":[
        {
            "category":"Bars & Pubs",
            "subcategory":"Nightclub",
            "type":"Food & Drink"
        }
    ],
    "sg:phone":"+1 949 280 7647",
    "sg:postcode":"92663",
    "sg:province":"CA",
    "sg:tags":[
        "nightlife"
    ],
    "sg:website":"www.facebook.com/boatwednesdays",
    "wof:name":"I'm on a Boat Wednesdays",
    "wof:placetype":"venue"
},
  "geometry": {"coordinates":[-117.92551899999999,33.620409],"type":"Point"}
}