{
  "type": "Feature",
  "properties": {
    "addr:full":"19005 Parthenia St Northridge CA 91324",
    "addr:housenumber":"19005",
    "addr:postcode":"91324",
    "addr:street":"Parthenia St",
    "iso:country":"US",
    "sg:address":"19005 Parthenia St",
    "sg:city":"Northridge",
    "sg:classifiers":[
        {
            "category":"Professional",
            "subcategory":"Engineering",
            "type":"Services"
        },
        {
            "category":"Wholesale",
            "subcategory":"Electrical",
            "type":"Manufacturing & Wholesale Goods"
        }
    ],
    "sg:phone":"+1 818 701 6951",
    "sg:postcode":"91324",
    "sg:province":"CA",
    "sg:tags":[
        "system",
        "systems-wholesale",
        "equipment",
        "air conditioning",
        "manufacturer"
    ],
    "wof:name":"Penex, Ltd.",
    "wof:placetype":"venue"
},
  "geometry": {"coordinates":[-118.54713099999999,34.228245],"type":"Point"}
}