{
  "type": "Feature",
  "properties": {
    "addr:full":"235 E Colorado Blvd Ste B Arcadia CA 91006",
    "addr:housenumber":"235",
    "addr:postcode":"91006",
    "addr:street":"E Colorado Blvd Ste B",
    "iso:country":"US",
    "sg:address":"235 E Colorado Blvd Ste B",
    "sg:city":"Arcadia",
    "sg:classifiers":[
        {
            "category":"Building & Trades",
            "subcategory":"Construction",
            "type":"Services"
        }
    ],
    "sg:phone":"+1 626 284 7167",
    "sg:postcode":"91006",
    "sg:province":"CA",
    "sg:tags":[
        "roofing",
        "industrial",
        "contractors-commercial",
        "contractor"
    ],
    "wof:name":"Jn Davis Roofing Co",
    "wof:placetype":"venue"
},
  "geometry": {"coordinates":[-118.024151,34.145595],"type":"Point"}
}