{
  "type": "Feature",
  "properties": {
    "iso:country":"US",
    "sg:address":"7007 Friars Rd",
    "sg:city":"San Diego",
    "sg:classifiers":[
        {
            "category":"Bakery",
            "type":"Food & Drink"
        }
    ],
    "sg:menulink":"http://www.allmenus.com/ca/san-diego/19761-boudin-bakery/menu/",
    "sg:phone":"+1 619 683 3962",
    "sg:postcode":"92108",
    "sg:province":"CA",
    "sg:tags":[
        "american",
        "pastry"
    ],
    "wof:name":"Boudin Bakery",
    "wof:placetype":"venue"
},
  "geometry": {"coordinates":[-117.16901900000001,32.769417],"type":"Point"}
}