{
  "type": "Feature",
  "properties": {
    "addr:full":"330 Wall St Los Angeles CA 90013",
    "addr:housenumber":"330",
    "addr:postcode":"90013",
    "addr:street":"Wall St",
    "iso:country":"US",
    "sg:address":"330 Wall St",
    "sg:city":"Los Angeles",
    "sg:classifiers":[
        {
            "category":"Shopping",
            "type":"Retail Goods"
        }
    ],
    "sg:phone":"+1 213 617 8328",
    "sg:postcode":"90013",
    "sg:province":"CA",
    "sg:tags":[
        "plant",
        "flower",
        "tree",
        "artificial"
    ],
    "wof:name":"P D Silk Flower",
    "wof:placetype":"venue"
},
  "geometry": {"coordinates":[-118.24394599999999,34.04762],"type":"Point"}
}