{
  "type": "Feature",
  "properties": {
    "addr:full":"1817 Polk St San Francisco CA 94109",
    "addr:housenumber":"1817",
    "addr:postcode":"94109",
    "addr:street":"Polk St",
    "iso:country":"US",
    "sg:address":"1817 Polk St",
    "sg:city":"San Francisco",
    "sg:classifiers":[
        {
            "category":"Shopping",
            "subcategory":"Used Merchandise",
            "type":"Retail Goods"
        }
    ],
    "sg:phone":"+1 415 775 1207",
    "sg:postcode":"94109",
    "sg:province":"CA",
    "sg:tags":[
        "antique"
    ],
    "wof:name":"Naomi's Antiques To Go",
    "wof:placetype":"venue"
},
  "geometry": {"coordinates":[-122.42145600000001,37.793987],"type":"Point"}
}