{
  "type": "Feature",
  "properties": {
    "addr:full":"3803 Oceanic Dr Oceanside CA 92056",
    "addr:housenumber":"3803",
    "addr:postcode":"92056",
    "addr:street":"Oceanic Dr",
    "iso:country":"US",
    "sg:address":"3803 Oceanic Dr",
    "sg:city":"Oceanside",
    "sg:classifiers":[
        {
            "category":"Shopping",
            "type":"Retail Goods"
        }
    ],
    "sg:phone":"+1 760 842 8300",
    "sg:postcode":"92056",
    "sg:province":"CA",
    "sg:website":"electrosport.com",
    "wof:name":"Electrosport Industries",
    "wof:placetype":"venue"
},
  "geometry": {"coordinates":[-117.30474100000001,33.204813],"type":"Point"}
}