{
  "type": "Feature",
  "properties": {
    "addr:full":"4390 Cll Real Santa Barbara CA 93110",
    "addr:postcode":"4390;93110",
    "addr:street":"Cll Real",
    "iso:country":"US",
    "sg:address":"4390 Cll Real",
    "sg:city":"Santa Barbara",
    "sg:classifiers":[
        {
            "category":"Health Services",
            "subcategory":"Doctor",
            "type":"Services"
        }
    ],
    "sg:phone":"+1 805 964 8710",
    "sg:postcode":"93110",
    "sg:province":"CA",
    "sg:tags":[
        "physician",
        "surgeon"
    ],
    "wof:name":"Kind Heart Institute",
    "wof:placetype":"venue"
},
  "geometry": {"coordinates":[-119.768953,34.44144],"type":"Point"}
}