{
  "type": "Feature",
  "properties": {
    "iso:country":"US",
    "sg:address":"12112 Sherman Way",
    "sg:city":"North Hollywood",
    "sg:classifiers":[
        {
            "category":"Wholesale",
            "subcategory":"Auto Parts",
            "type":"Manufacturing & Wholesale Goods"
        }
    ],
    "sg:phone":"+1 818 982 3606",
    "sg:postcode":"91605",
    "sg:province":"CA",
    "sg:tags":[
        "automobile"
    ],
    "wof:name":"C K Enterprises",
    "wof:placetype":"venue"
},
  "geometry": {"coordinates":[-118.401483,34.20112],"type":"Point"}
}