{
  "type": "Feature",
  "properties": {
    "addr:full":"2101 Wilshire Blvd Santa Monica CA 90403",
    "addr:housenumber":"2101",
    "addr:postcode":"90403",
    "addr:street":"Wilshire Blvd",
    "iso:country":"US",
    "sg:address":"2101 Wilshire Blvd",
    "sg:city":"Santa Monica",
    "sg:classifiers":[
        {
            "category":"Professional",
            "subcategory":"Research",
            "type":"Services"
        },
        {
            "category":"Social Services",
            "type":"Services"
        }
    ],
    "sg:phone":"+1 310 829 7857",
    "sg:postcode":"90403",
    "sg:province":"CA",
    "sg:tags":[
        "foundation",
        "philanthropic"
    ],
    "sg:website":"www.heartfelt.org",
    "wof:name":"Heartfelt Foundation",
    "wof:placetype":"venue"
},
  "geometry": {"coordinates":[-118.48144600000001,34.032748],"type":"Point"}
}