{
  "type": "Feature",
  "properties": {
    "iso:country":"US",
    "sg:address":"14167 Amador Rd",
    "sg:city":"Sutter Creek",
    "sg:classifiers":[
        {
            "category":"Shopping",
            "subcategory":"Used Merchandise",
            "type":"Retail Goods"
        }
    ],
    "sg:phone":"+1 209 267 9310",
    "sg:postcode":"95685",
    "sg:province":"CA",
    "sg:tags":[
        "antique"
    ],
    "wof:name":"Keystone Alley Kitchen-Hearth",
    "wof:placetype":"venue"
},
  "geometry": {"coordinates":[-120.805937,38.40598],"type":"Point"}
}