{
  "type": "Feature",
  "properties": {
    "addr:full":"512 E Haley St Santa Barbara CA 93103",
    "addr:housenumber":"512",
    "addr:postcode":"93103",
    "addr:street":"E Haley St",
    "iso:country":"US",
    "sg:address":"512 E Haley St",
    "sg:city":"Santa Barbara",
    "sg:classifiers":[
        {
            "category":"Food & Beverages",
            "subcategory":"Meat & Fish",
            "type":"Retail Goods"
        }
    ],
    "sg:phone":"+1 805 966 7971",
    "sg:postcode":"93103",
    "sg:province":"CA",
    "wof:name":"Carniceria LA Bodeguita",
    "wof:placetype":"venue"
},
  "geometry": {"coordinates":[-119.688779,34.422982],"type":"Point"}
}