{
  "type": "Feature",
  "properties": {
    "iso:country":"US",
    "sg:address":"1225 Grand Central Ave",
    "sg:city":"Glendale",
    "sg:classifiers":[
        {
            "category":"Professional",
            "subcategory":"Computer Services",
            "type":"Services"
        }
    ],
    "sg:phone":"+1 818 550 2780",
    "sg:postcode":"91201",
    "sg:province":"CA",
    "sg:tags":[
        "information",
        "consulting",
        "technology",
        "it",
        "software"
    ],
    "sg:website":"www.hi-tech.com",
    "wof:name":"High-Tech Business Solutions",
    "wof:placetype":"venue"
},
  "geometry": {"coordinates":[-118.288451,34.162923],"type":"Point"}
}