{
  "type": "Feature",
  "properties": {
    "addr:full":"727 9th Ave City Of Industry CA 91745",
    "addr:housenumber":"727",
    "addr:postcode":"91745",
    "addr:street":"9Th Ave",
    "iso:country":"US",
    "sg:address":"727 9th Ave",
    "sg:city":"City Of Industry",
    "sg:classifiers":[
        {
            "category":"Building & Trades",
            "subcategory":"Construction",
            "type":"Services"
        }
    ],
    "sg:phone":"+1 626 968 1829",
    "sg:postcode":"91745",
    "sg:province":"CA",
    "sg:tags":[
        "insulation",
        "heat",
        "contractor"
    ],
    "wof:name":"Consolidated Western Contrs",
    "wof:placetype":"venue"
},
  "geometry": {"coordinates":[-117.97786000000001,34.020036],"type":"Point"}
}