{
  "type": "Feature",
  "properties": {
    "iso:country":"US",
    "sg:address":"2201 Pine St",
    "sg:city":"Napa",
    "sg:classifiers":[
        {
            "category":"Education",
            "subcategory":"School",
            "type":"Public Place"
        }
    ],
    "sg:phone":"+1 707 255 5233",
    "sg:postcode":"94559",
    "sg:province":"CA",
    "sg:website":"www.najasda.com",
    "wof:name":"Napa Adventist Junior Academy",
    "wof:placetype":"venue"
},
  "geometry": {"coordinates":[-122.299601,38.291117],"type":"Point"}
}