{
  "type": "Feature",
  "properties": {
    "addr:full":"2658 Bridgeway Sausalito CA 94965",
    "addr:housenumber":"2658",
    "addr:postcode":"94965",
    "addr:street":"Bridgeway",
    "iso:country":"US",
    "sg:address":"2658 Bridgeway",
    "sg:city":"Sausalito",
    "sg:classifiers":[
        {
            "category":"Building & Trades",
            "subcategory":"Construction",
            "type":"Services"
        }
    ],
    "sg:phone":"+1 415 381 4620",
    "sg:postcode":"94965",
    "sg:province":"CA",
    "sg:tags":[
        "concrete",
        "contractor"
    ],
    "wof:name":"Design Interlock",
    "wof:placetype":"venue"
},
  "geometry": {"coordinates":[-122.502003,37.868018],"type":"Point"}
}