{
  "type": "Feature",
  "properties": {
    "iso:country":"US",
    "sg:address":"2466 Fender Ave",
    "sg:city":"Fullerton",
    "sg:classifiers":[
        {
            "category":"Wholesale",
            "subcategory":"Durable Goods & Equipment",
            "type":"Manufacturing & Wholesale Goods"
        }
    ],
    "sg:phone":"+1 714 525 8491",
    "sg:postcode":"92831",
    "sg:province":"CA",
    "wof:name":"B and N Distributing",
    "wof:placetype":"venue"
},
  "geometry": {"coordinates":[-117.885923,33.868055],"type":"Point"}
}