{
  "type": "Feature",
  "properties": {
    "addr:full":"7971 State Hwy 99 Los Molinos CA 96055",
    "addr:housenumber":"7971",
    "addr:postcode":"96055",
    "addr:street":"State Hwy 99",
    "iso:country":"US",
    "sg:address":"7971 State Hwy 99",
    "sg:city":"Los Molinos",
    "sg:classifiers":[
        {
            "category":"Personal",
            "subcategory":"Beauty Salon",
            "type":"Services"
        }
    ],
    "sg:phone":"+1 530 384 1133",
    "sg:postcode":"96055",
    "sg:province":"CA",
    "wof:name":"Best Little Hair House",
    "wof:placetype":"venue"
},
  "geometry": {"coordinates":[-122.10002799999999,40.02549],"type":"Point"}
}