{
  "type": "Feature",
  "properties": {
    "iso:country":"US",
    "sg:address":"141 Foster Rd",
    "sg:city":"Salinas",
    "sg:classifiers":[
        {
            "category":"Farming",
            "subcategory":"Farm",
            "type":"Manufacturing & Wholesale Goods"
        }
    ],
    "sg:phone":"+1 831 770 1104",
    "sg:postcode":"93908",
    "sg:province":"CA",
    "wof:name":"Alex Camany Farms",
    "wof:placetype":"venue"
},
  "geometry": {"coordinates":[-121.688649,36.646708],"type":"Point"}
}