{
  "type": "Feature",
  "properties": {
    "iso:country":"US",
    "sg:address":"150 Lombard St",
    "sg:city":"San Francisco",
    "sg:classifiers":[
        {
            "category":"Professional",
            "subcategory":"Business Services",
            "type":"Services"
        }
    ],
    "sg:phone":"+1 415 982 7172",
    "sg:postcode":"94111",
    "sg:province":"CA",
    "sg:tags":[
        "arbitration"
    ],
    "wof:name":"Norman Brand",
    "wof:placetype":"venue"
},
  "geometry": {"coordinates":[-122.404337,37.804008],"type":"Point"}
}