{
  "type": "Feature",
  "properties": {
    "addr:full":"916 N Diamond Bar Blvd Diamond Bar CA 91765",
    "addr:housenumber":"916",
    "addr:postcode":"91765",
    "addr:street":"N Diamond Bar Blvd",
    "iso:country":"US",
    "sg:address":"916 N Diamond Bar Blvd",
    "sg:city":"Diamond Bar",
    "sg:classifiers":[
        {
            "category":"Retail",
            "subcategory":"Laundry & Dry Cleaning",
            "type":"Services"
        }
    ],
    "sg:phone":"+1 909 861 2969",
    "sg:postcode":"91765",
    "sg:province":"CA",
    "sg:tags":[
        "cleaners"
    ],
    "wof:name":"K S Custom Cleaner",
    "wof:placetype":"venue"
},
  "geometry": {"coordinates":[-117.805825,34.036123],"type":"Point"}
}