{
  "type": "Feature",
  "properties": {
    "iso:country":"US",
    "sg:address":"4427 Freeport Blvd",
    "sg:city":"Sacramento",
    "sg:classifiers":[
        {
            "category":"Real Estate",
            "subcategory":"Real Estate Services",
            "type":"Services"
        }
    ],
    "sg:phone":"+1 916 452 5000",
    "sg:postcode":"95822",
    "sg:province":"CA",
    "sg:tags":[
        "management",
        "property"
    ],
    "sg:website":"www.rpmsacmetro.com/",
    "wof:name":"Real Property Management",
    "wof:placetype":"venue"
},
  "geometry": {"coordinates":[-121.493785,38.534851],"type":"Point"}
}