{
  "type": "Feature",
  "properties": {
    "addr:full":"608 Shaw Ave Clovis CA 93612",
    "addr:housenumber":"608",
    "addr:postcode":"93612",
    "addr:street":"Shaw Ave",
    "iso:country":"US",
    "sg:address":"608 Shaw Ave",
    "sg:city":"Clovis",
    "sg:classifiers":[
        {
            "category":"Autos & Motor Vehicles",
            "subcategory":"Auto Supplies",
            "type":"Retail Goods"
        },
        {
            "category":"Wholesale",
            "subcategory":"Auto Parts",
            "type":"Manufacturing & Wholesale Goods"
        }
    ],
    "sg:phone":"+1 559 299 7261",
    "sg:postcode":"93612",
    "sg:province":"CA",
    "sg:tags":[
        "body",
        "automobile",
        "truck",
        "equipment",
        "accessory"
    ],
    "sg:website":"http://www.oreillyauto.com?utm_source=yellowpages&utm_medium=iyp&utm_campaign=2562",
    "wof:name":"Kragen O'ReillyAuto Parts",
    "wof:placetype":"venue"
},
  "geometry": {"coordinates":[-119.70222699999999,36.808437],"type":"Point"}
}