{
  "type": "Feature",
  "properties": {
    "iso:country":"US",
    "sg:address":"715 Hearst Ave",
    "sg:city":"Berkeley",
    "sg:classifiers":[
        {
            "category":"Professional",
            "subcategory":"Advertising",
            "type":"Services"
        }
    ],
    "sg:phone":"+1 510 644 0550",
    "sg:postcode":"94710",
    "sg:province":"CA",
    "sg:tags":[
        "counselor"
    ],
    "wof:name":"Ackerman Mc Queen Inc",
    "wof:placetype":"venue"
},
  "geometry": {"coordinates":[-122.301298,37.868769],"type":"Point"}
}