{
  "type": "Feature",
  "properties": {
    "addr:full":"5248 Tunson Rd Modesto CA 95356",
    "addr:housenumber":"5248",
    "addr:postcode":"ca 95356",
    "addr:street":"Tunson Rd",
    "iso:country":"US",
    "sg:address":"5248 Tunson Rd",
    "sg:city":"Modesto",
    "sg:classifiers":[
        {
            "category":"Building & Trades",
            "subcategory":"Landscaping Services",
            "type":"Services"
        }
    ],
    "sg:phone":"+1 209 545 4455",
    "sg:postcode":"95356",
    "sg:province":"CA",
    "sg:tags":[
        "garden",
        "landscape",
        "contractor"
    ],
    "wof:name":"Continental Landscape Inc",
    "wof:placetype":"venue"
},
  "geometry": {"coordinates":[-121.00623,37.711882],"type":"Point"}
}