{
  "type": "Feature",
  "properties": {
    "addr:full":"810 E Colorado St Glendale CA 91205",
    "addr:housenumber":"810",
    "addr:postcode":"91205",
    "addr:street":"E Colorado St",
    "iso:country":"US",
    "sg:address":"810 E Colorado St",
    "sg:city":"Glendale",
    "sg:classifiers":[
        {
            "category":"Food & Beverages",
            "subcategory":"Liquor & Beverages",
            "type":"Retail Goods"
        }
    ],
    "sg:phone":"+1 818 548 0199",
    "sg:postcode":"91205",
    "sg:province":"CA",
    "sg:tags":[
        "beer",
        "spirit",
        "wine"
    ],
    "wof:name":"Colorado Liquor",
    "wof:placetype":"venue"
},
  "geometry": {"coordinates":[-118.24538699999999,34.142512],"type":"Point"}
}