{
  "type": "Feature",
  "properties": {
    "addr:full":"350 Showers Dr Mountain View CA 94040",
    "addr:housenumber":"350",
    "addr:postcode":"94040",
    "addr:street":"Showers Dr",
    "iso:country":"US",
    "sg:address":"350 Showers Dr",
    "sg:city":"Mountain View",
    "sg:classifiers":[
        {
            "category":"Shopping",
            "subcategory":"Department Store",
            "type":"Retail Goods"
        }
    ],
    "sg:phone":"+1 650 949 3500",
    "sg:postcode":"94040",
    "sg:province":"CA",
    "sg:tags":[
        "dept"
    ],
    "wof:name":"Mervyns",
    "wof:placetype":"venue"
},
  "geometry": {"coordinates":[-122.10866,37.400539],"type":"Point"}
}