{
  "type": "Feature",
  "properties": {
    "iso:country":"US",
    "sg:address":"4243 Maine Ave",
    "sg:city":"Baldwin Park",
    "sg:classifiers":[
        {
            "category":"Social Services",
            "type":"Services"
        }
    ],
    "sg:phone":"+1 626 337 7669",
    "sg:postcode":"91706",
    "sg:province":"CA",
    "sg:tags":[
        "organization",
        "welfare"
    ],
    "wof:name":"Mother's Nutritional",
    "wof:placetype":"venue"
},
  "geometry": {"coordinates":[-117.96048500000001,34.090076],"type":"Point"}
}