{
  "type": "Feature",
  "properties": {
    "iso:country":"US",
    "sg:address":"125 Primrose Rd",
    "sg:city":"Burlingame",
    "sg:classifiers":[
        {
            "category":"Communications",
            "subcategory":"Film & Video Production",
            "type":"Services"
        }
    ],
    "sg:phone":"+1 650 579 1313",
    "sg:postcode":"94010",
    "sg:province":"CA",
    "sg:tags":[
        "motion",
        "picture",
        "studio",
        "producer"
    ],
    "sg:website":"www.bassettproductions.com",
    "wof:name":"Bassett Productions",
    "wof:placetype":"venue"
},
  "geometry": {"coordinates":[-122.346364,37.576177],"type":"Point"}
}