{
  "type": "Feature",
  "properties": {
    "addr:full":"1122 Branham Ln San Jose CA 95118",
    "addr:housenumber":"1122",
    "addr:postcode":"95118",
    "addr:street":"Branham Ln",
    "iso:country":"US",
    "sg:address":"1122 Branham Ln",
    "sg:city":"San Jose",
    "sg:classifiers":[
        {
            "category":"Professional",
            "subcategory":"Printing & Photocopies",
            "type":"Services"
        }
    ],
    "sg:phone":"+1 408 448 2679",
    "sg:postcode":"95118",
    "sg:province":"CA",
    "wof:name":"Digicopy",
    "wof:placetype":"venue"
},
  "geometry": {"coordinates":[-121.878998,37.262501],"type":"Point"}
}