{
  "type": "Feature",
  "properties": {
    "addr:full":"3444 Cam del Rio N San Diego CA 92108",
    "addr:housenumber":"3444",
    "addr:postcode":"92108",
    "addr:street":"Cam Del Rio N",
    "iso:country":"US",
    "sg:address":"3444 Cam del Rio N",
    "sg:city":"San Diego",
    "sg:classifiers":[
        {
            "category":"Banks & Credit Unions",
            "subcategory":"Bank",
            "type":"Services"
        }
    ],
    "sg:phone":"+1 619 624 0049",
    "sg:postcode":"92108",
    "sg:province":"CA",
    "sg:tags":[
        "loan",
        "real estate"
    ],
    "sg:website":"www.aphomeloans.com",
    "wof:name":"Atlantic Pacific Home Loans",
    "wof:placetype":"venue"
},
  "geometry": {"coordinates":[-117.118616,32.778627],"type":"Point"}
}