{
  "type": "Feature",
  "properties": {
    "addr:full":"4400 Macarthur Blvd Newport Beach CA 92660",
    "addr:housenumber":"4400",
    "addr:postcode":"92660",
    "addr:street":"Macarthur Blvd",
    "iso:country":"US",
    "sg:address":"4400 Macarthur Blvd",
    "sg:city":"Newport Beach",
    "sg:classifiers":[
        {
            "category":"Real Estate",
            "subcategory":"Real Estate Agent",
            "type":"Services"
        }
    ],
    "sg:phone":"+1 949 365 1800",
    "sg:postcode":"92660",
    "sg:province":"CA",
    "sg:website":"www.blackrock.com",
    "wof:name":"Blackrock Metric Property Mgmt",
    "wof:placetype":"venue"
},
  "geometry": {"coordinates":[-117.86437100000001,33.667937],"type":"Point"}
}