{
  "type": "Feature",
  "properties": {
    "addr:full":"1919 Davis St San Leandro CA 94577",
    "addr:housenumber":"1919",
    "addr:postcode":"94577",
    "addr:street":"Davis St",
    "iso:country":"US",
    "sg:address":"1919 Davis St",
    "sg:city":"San Leandro",
    "sg:classifiers":[
        {
            "category":"Utilities",
            "subcategory":"Mobile Phone",
            "type":"Services"
        },
        {
            "category":"Shopping",
            "type":"Retail Goods"
        }
    ],
    "sg:phone":"+1 510 635 6135",
    "sg:postcode":"94577",
    "sg:province":"CA",
    "sg:tags":[
        "comm",
        "telephone",
        "cellular"
    ],
    "wof:name":"Cellular Warehouse Inc",
    "wof:placetype":"venue"
},
  "geometry": {"coordinates":[-122.182574,37.71702],"type":"Point"}
}