{
  "type": "Feature",
  "properties": {
    "addr:full":"11300 Sanders Ave Ste 25 Rancho Cordova CA 95742",
    "addr:housenumber":"11300",
    "addr:postcode":"95742",
    "addr:street":"Sanders Ave Ste 25",
    "iso:country":"US",
    "sg:address":"11300 Sanders Ave Ste 25",
    "sg:city":"Rancho Cordova",
    "sg:classifiers":[
        {
            "category":"Health Services",
            "subcategory":"Clinic",
            "type":"Services"
        }
    ],
    "sg:phone":"+1 916 207 7500",
    "sg:postcode":"95742",
    "sg:province":"CA",
    "sg:tags":[
        "medical"
    ],
    "wof:name":"CrossFit Centurion",
    "wof:placetype":"venue"
},
  "geometry": {"coordinates":[-121.261657,38.586123],"type":"Point"}
}