{
  "type": "Feature",
  "properties": {
    "addr:full":"855 Civic Center Dr Santa Clara CA 95050",
    "addr:housenumber":"855",
    "addr:postcode":"95050",
    "addr:street":"Civic Center Dr",
    "iso:country":"US",
    "sg:address":"855 Civic Center Dr",
    "sg:city":"Santa Clara",
    "sg:classifiers":[
        {
            "category":"Professional",
            "subcategory":"Detective & Security Services",
            "type":"Services"
        }
    ],
    "sg:phone":"+1 408 241 0910",
    "sg:postcode":"95050",
    "sg:province":"CA",
    "sg:tags":[
        "car",
        "armored"
    ],
    "wof:name":"Armed Courier Svc",
    "wof:placetype":"venue"
},
  "geometry": {"coordinates":[-121.945661,37.356196],"type":"Point"}
}