{
  "type": "Feature",
  "properties": {
    "addr:full":"523 Southgate Rd Sacramento CA 95815",
    "addr:housenumber":"523",
    "addr:postcode":"95815",
    "addr:street":"Southgate Rd",
    "iso:country":"US",
    "sg:address":"523 Southgate Rd",
    "sg:city":"Sacramento",
    "sg:classifiers":[
        {
            "category":"Insurance",
            "subcategory":"Life Insurance",
            "type":"Services"
        }
    ],
    "sg:phone":"+1 916 925 2327",
    "sg:postcode":"95815",
    "sg:province":"CA",
    "sg:tags":[
        "carrier"
    ],
    "wof:name":"Portuguese American Club",
    "wof:placetype":"venue"
},
  "geometry": {"coordinates":[-121.455152,38.603022],"type":"Point"}
}