{
  "type": "Feature",
  "properties": {
    "addr:full":"1045 Monroe St Santa Clara CA 95050",
    "addr:housenumber":"1045",
    "addr:postcode":"95050",
    "addr:street":"Monroe St",
    "iso:country":"US",
    "sg:address":"1045 Monroe St",
    "sg:city":"Santa Clara",
    "sg:classifiers":[
        {
            "category":"Restaurant",
            "type":"Food & Drink"
        }
    ],
    "sg:menulink":"http://www.allmenus.com/ca/san-jose/89130-thai-pepper/menu/",
    "sg:phone":"+1 408 984 1931",
    "sg:postcode":"95050",
    "sg:province":"CA",
    "sg:tags":[
        "thai",
        "asian"
    ],
    "wof:name":"Thai Pepper",
    "wof:placetype":"venue"
},
  "geometry": {"coordinates":[-121.94835,37.348972],"type":"Point"}
}