{
  "type": "Feature",
  "properties": {
    "iso:country":"US",
    "sg:address":"200 Culver Blvd",
    "sg:city":"Playa Del Rey",
    "sg:classifiers":[
        {
            "category":"Manufacturing",
            "subcategory":"Apparel",
            "type":"Manufacturing & Wholesale Goods"
        }
    ],
    "sg:phone":"+1 310 827 6022",
    "sg:postcode":"90293",
    "sg:province":"CA",
    "sg:tags":[
        "lingerie"
    ],
    "wof:name":"Saville 1300",
    "wof:placetype":"venue"
},
  "geometry": {"coordinates":[-118.447982,33.959098],"type":"Point"}
}