{
  "type": "Feature",
  "properties": {
    "addr:full":"5638 Lake Murray Blvd La Mesa CA 91942",
    "addr:housenumber":"5638",
    "addr:postcode":"91942",
    "addr:street":"Lake Murray Blvd",
    "iso:country":"US",
    "sg:address":"5638 Lake Murray Blvd",
    "sg:city":"La Mesa",
    "sg:classifiers":[
        {
            "category":"Communications",
            "subcategory":"Film & Video Production",
            "type":"Services"
        }
    ],
    "sg:phone":"+1 619 444 8899",
    "sg:postcode":"91942",
    "sg:province":"CA",
    "sg:tags":[
        "taping"
    ],
    "wof:name":"Massage Mastery",
    "wof:placetype":"venue"
},
  "geometry": {"coordinates":[-117.032489,32.781141],"type":"Point"}
}