{
  "type": "Feature",
  "properties": {
    "addr:full":"1250 Montgomery St San Francisco CA 94133",
    "addr:housenumber":"1250",
    "addr:postcode":"94133",
    "addr:street":"Montgomery St",
    "iso:country":"US",
    "sg:address":"1250 Montgomery St",
    "sg:city":"San Francisco",
    "sg:classifiers":[
        {
            "category":"Real Estate",
            "subcategory":"Real Estate Agent",
            "type":"Services"
        }
    ],
    "sg:phone":"+1 415 989 9904",
    "sg:postcode":"94133",
    "sg:province":"CA",
    "wof:name":"Margarie Strough & Properties",
    "wof:placetype":"venue"
},
  "geometry": {"coordinates":[-122.404336,37.800933],"type":"Point"}
}