{
  "type": "Feature",
  "properties": {
    "addr:full":"1824 9th St Oakland CA 94607",
    "addr:housenumber":"1824",
    "addr:postcode":"94607",
    "addr:street":"9Th St",
    "iso:country":"US",
    "sg:address":"1824 9th St",
    "sg:city":"Oakland",
    "sg:classifiers":[
        {
            "category":"Manufacturing",
            "subcategory":"Tools & Machinery",
            "type":"Manufacturing & Wholesale Goods"
        }
    ],
    "sg:phone":"+1 510 693 9336",
    "sg:postcode":"94607",
    "sg:province":"CA",
    "sg:tags":[
        "fasteners-industrial"
    ],
    "wof:name":"Apollo Fasteners",
    "wof:placetype":"venue"
},
  "geometry": {"coordinates":[-122.30168999999999,37.810028],"type":"Point"}
}