{
  "type": "Feature",
  "properties": {
    "addr:full":"207 E Alameda Ave Burbank CA 91502",
    "addr:housenumber":"207",
    "addr:postcode":"91502",
    "addr:street":"E Alameda Ave",
    "iso:country":"US",
    "sg:address":"207 E Alameda Ave",
    "sg:city":"Burbank",
    "sg:classifiers":[
        {
            "category":"Restaurant",
            "type":"Food & Drink"
        }
    ],
    "sg:phone":"+1 818 841 0848",
    "sg:postcode":"91502",
    "sg:province":"CA",
    "sg:tags":[
        "mexican"
    ],
    "wof:name":"Don Diego Mexican Restaurant",
    "wof:placetype":"venue"
},
  "geometry": {"coordinates":[-118.300003,34.174599],"type":"Point"}
}