{
  "type": "Feature",
  "properties": {
    "iso:country":"US",
    "sg:address":"22100 Harmony Ln",
    "sg:city":"Sonora",
    "sg:classifiers":[
        {
            "category":"Building & Trades",
            "subcategory":"Landscaping Services",
            "type":"Services"
        }
    ],
    "sg:phone":"+1 209 533 4758",
    "sg:postcode":"95370",
    "sg:province":"CA",
    "wof:name":"T R Jones Landscaping",
    "wof:placetype":"venue"
},
  "geometry": {"coordinates":[-120.280356,38.022001],"type":"Point"}
}