{
  "type": "Feature",
  "properties": {
    "iso:country":"US",
    "sg:address":"63822 State Rte 96",
    "sg:city":"Happy Camp",
    "sg:classifiers":[
        {
            "category":"Manufacturing",
            "subcategory":"Lumber",
            "type":"Manufacturing & Wholesale Goods"
        }
    ],
    "sg:phone":"+1 530 493 2243",
    "sg:postcode":"96039",
    "sg:province":"CA",
    "sg:tags":[
        "government"
    ],
    "wof:name":"US Forestry Dept",
    "wof:placetype":"venue"
},
  "geometry": {"coordinates":[-123.375244,41.796842],"type":"Point"}
}