{
  "type": "Feature",
  "properties": {
    "addr:full":"2173 Francisco Blvd E San Rafael CA 94901",
    "addr:housenumber":"2173",
    "addr:postcode":"94901",
    "addr:street":"Francisco Blvd E",
    "iso:country":"US",
    "sg:address":"2173 Francisco Blvd E",
    "sg:city":"San Rafael",
    "sg:classifiers":[
        {
            "category":"Professional",
            "subcategory":"Accounting & Tax Preparation",
            "type":"Services"
        }
    ],
    "sg:phone":"+1 415 456 2920",
    "sg:postcode":"94901",
    "sg:province":"CA",
    "sg:tags":[
        "return",
        "filing"
    ],
    "wof:name":"A Counting House",
    "wof:placetype":"venue"
},
  "geometry": {"coordinates":[-122.479748,37.943646],"type":"Point"}
}