{
  "type": "Feature",
  "properties": {
    "addr:full":"4018 Broadway Pl Los Angeles CA 90037",
    "addr:housenumber":"4018",
    "addr:postcode":"90037",
    "addr:street":"Broadway Pl",
    "iso:country":"US",
    "sg:address":"4018 Broadway Pl",
    "sg:city":"Los Angeles",
    "sg:classifiers":[
        {
            "category":"Freight",
            "type":"Transportation"
        },
        {
            "category":"Autos & Motor Vehicles",
            "subcategory":"Auto Supplies",
            "type":"Retail Goods"
        }
    ],
    "sg:phone":"+1 323 232 7103",
    "sg:postcode":"90037",
    "sg:province":"CA",
    "sg:tags":[
        "automobile",
        "parts",
        "general"
    ],
    "wof:name":"M C Warehouse",
    "wof:placetype":"venue"
},
  "geometry": {"coordinates":[-118.277804,34.010415],"type":"Point"}
}