{
  "type": "Feature",
  "properties": {
    "iso:country":"US",
    "sg:address":"24833 Ave 16",
    "sg:city":"Madera",
    "sg:classifiers":[
        {
            "category":"Professional",
            "subcategory":"Computer Services",
            "type":"Services"
        }
    ],
    "sg:phone":"+1 559 675 8521",
    "sg:postcode":"93637",
    "sg:province":"CA",
    "sg:tags":[
        "consulting",
        "management",
        "related"
    ],
    "wof:name":"Bates Web Consulting",
    "wof:placetype":"venue"
},
  "geometry": {"coordinates":[-120.096919,36.981948],"type":"Point"}
}