{
  "type": "Feature",
  "properties": {
    "addr:full":"201 E Magnolia Blvd Burbank Town Center Burbank CA 91506",
    "addr:housenumber":"201",
    "addr:postcode":"91506",
    "addr:street":"E Magnolia Blvd",
    "iso:country":"US",
    "sg:address":"201 E Magnolia Blvd Burbank Town Center",
    "sg:city":"Burbank",
    "sg:classifiers":[
        {
            "category":"Shopping",
            "subcategory":"Bridal",
            "type":"Retail Goods"
        }
    ],
    "sg:phone":"+1 818 567 2626",
    "sg:postcode":"91506",
    "sg:province":"CA",
    "sg:website":"www.tuxedojunction.com/",
    "wof:name":"Tuxedo Junction",
    "wof:placetype":"venue"
},
  "geometry": {"coordinates":[-118.312247,34.183478],"type":"Point"}
}