{
  "type": "Feature",
  "properties": {
    "iso:country":"US",
    "sg:address":"16311 Piuma Ave",
    "sg:city":"Cerritos",
    "sg:classifiers":[
        {
            "category":"Communications",
            "type":"Services"
        }
    ],
    "sg:phone":"+1 562 402 1013",
    "sg:postcode":"90703",
    "sg:province":"CA",
    "wof:name":"Broad Net Inc",
    "wof:placetype":"venue"
},
  "geometry": {"coordinates":[-118.105915,33.886787],"type":"Point"}
}