{
  "type": "Feature",
  "properties": {
    "addr:full":"6145 Joaquin St Chino CA 91710",
    "addr:postcode":"6145;91710",
    "addr:street":"Joaquin St",
    "iso:country":"US",
    "sg:address":"6145 Joaquin St",
    "sg:city":"Chino",
    "sg:classifiers":[
        {
            "category":"Building & Trades",
            "subcategory":"Construction",
            "type":"Services"
        }
    ],
    "sg:phone":"+1 909 590 2903",
    "sg:postcode":"91710",
    "sg:province":"CA",
    "sg:tags":[
        "plastering",
        "contractor"
    ],
    "wof:name":"Smith Plastering Contractors",
    "wof:placetype":"venue"
},
  "geometry": {"coordinates":[-117.669421,34.010651],"type":"Point"}
}