{
  "type": "Feature",
  "properties": {
    "addr:full":"138 Arena St El Segundo CA 90245",
    "addr:housenumber":"138",
    "addr:postcode":"90245",
    "addr:street":"Arena St",
    "iso:country":"US",
    "sg:address":"138 Arena St",
    "sg:city":"El Segundo",
    "sg:classifiers":[
        {
            "category":"Manufacturing",
            "subcategory":"Metals",
            "type":"Manufacturing & Wholesale Goods"
        }
    ],
    "sg:phone":"+1 310 322 8320",
    "sg:postcode":"90245",
    "sg:province":"CA",
    "sg:tags":[
        "engraver"
    ],
    "wof:name":"Universal Engravers",
    "wof:placetype":"venue"
},
  "geometry": {"coordinates":[-118.412266,33.917284],"type":"Point"}
}