{
  "type": "Feature",
  "properties": {
    "iso:country":"US",
    "sg:address":"325 Rancheria St",
    "sg:city":"Santa Barbara",
    "sg:classifiers":[
        {
            "category":"Professional",
            "subcategory":"Computer Services",
            "type":"Services"
        }
    ],
    "sg:phone":"+1 805 962 6320",
    "sg:postcode":"93101",
    "sg:province":"CA",
    "sg:tags":[
        "consultant",
        "designer"
    ],
    "wof:name":"Intelligent Design",
    "wof:placetype":"venue"
},
  "geometry": {"coordinates":[-119.69963,34.410269],"type":"Point"}
}