{
  "type": "Feature",
  "properties": {
    "iso:country":"US",
    "sg:address":"15103 Graystone Ave",
    "sg:city":"Norwalk",
    "sg:classifiers":[
        {
            "category":"Professional",
            "type":"Services"
        }
    ],
    "sg:phone":"+1 562 864 3508",
    "sg:postcode":"90650",
    "sg:province":"CA",
    "sg:tags":[
        "cards",
        "greeting",
        "mfg"
    ],
    "wof:name":"Shirley Holland Illustration",
    "wof:placetype":"venue"
},
  "geometry": {"coordinates":[-118.093475,33.893041],"type":"Point"}
}