{
  "type": "Feature",
  "properties": {
    "addr:full":"36963 S Lassen Ave Huron CA 93234",
    "addr:housenumber":"36963",
    "addr:postcode":"93234",
    "addr:street":"S Lassen Ave",
    "iso:country":"US",
    "sg:address":"36963 S Lassen Ave",
    "sg:city":"Huron",
    "sg:classifiers":[
        {
            "category":"Food & Beverages",
            "subcategory":"Groceries & Convenience Stores",
            "type":"Retail Goods"
        }
    ],
    "sg:phone":"+1 559 945 2775",
    "sg:postcode":"93234",
    "sg:province":"CA",
    "sg:tags":[
        "grocer"
    ],
    "wof:name":"U-Save Market",
    "wof:placetype":"venue"
},
  "geometry": {"coordinates":[-120.103455,36.195991],"type":"Point"}
}