{
  "type": "Feature",
  "properties": {
    "addr:full":"11023 Olinda St Sun Valley CA 91352",
    "addr:housenumber":"11023",
    "addr:postcode":"91352",
    "addr:street":"Olinda St",
    "iso:country":"US",
    "sg:address":"11023 Olinda St",
    "sg:city":"Sun Valley",
    "sg:classifiers":[
        {
            "category":"Retail",
            "subcategory":"Auto Repair",
            "type":"Services"
        }
    ],
    "sg:phone":"+1 818 504 2091",
    "sg:postcode":"91352",
    "sg:province":"CA",
    "sg:tags":[
        "wrecker"
    ],
    "wof:name":"Tom John's Towing",
    "wof:placetype":"venue"
},
  "geometry": {"coordinates":[-118.370496,34.224731],"type":"Point"}
}