{
  "type": "Feature",
  "properties": {
    "addr:full":"5532 Woodruff Ave Lakewood CA 90713",
    "addr:housenumber":"5532",
    "addr:postcode":"90713",
    "addr:street":"Woodruff Ave",
    "iso:country":"US",
    "sg:address":"5532 Woodruff Ave",
    "sg:city":"Lakewood",
    "sg:classifiers":[
        {
            "category":"Professional",
            "subcategory":"Art Services",
            "type":"Services"
        }
    ],
    "sg:phone":"+1 562 866 7662",
    "sg:postcode":"90713",
    "sg:province":"CA",
    "sg:tags":[
        "photographer"
    ],
    "wof:name":"Mazell Images/Los Angeles",
    "wof:placetype":"venue"
},
  "geometry": {"coordinates":[-118.116972,33.857079],"type":"Point"}
}