{
  "type": "Feature",
  "properties": {
    "iso:country":"US",
    "sg:address":"37 Wentworth Street",
    "sg:city":"San Francisco",
    "sg:classifiers":[
        {
            "category":"Professional",
            "subcategory":"Printing & Photocopies",
            "type":"Services"
        }
    ],
    "sg:phone":"+1 415 986 3888",
    "sg:postcode":"94108",
    "sg:province":"CA",
    "wof:name":"Duxwell Printing Co., Inc.",
    "wof:placetype":"venue"
},
  "geometry": {"coordinates":[-122.40615200000001,37.795634],"type":"Point"}
}