{
  "type": "Feature",
  "properties": {
    "iso:country":"US",
    "sg:address":"16416 Nesselwood Ct",
    "sg:city":"Chino Hills",
    "sg:classifiers":[
        {
            "category":"Manufacturing",
            "subcategory":"Jewelry",
            "type":"Manufacturing & Wholesale Goods"
        }
    ],
    "sg:phone":"+1 909 606 9816",
    "sg:postcode":"91709",
    "sg:province":"CA",
    "sg:tags":[
        "costume",
        "mfg"
    ],
    "wof:name":"Poker Luck Charms",
    "wof:placetype":"venue"
},
  "geometry": {"coordinates":[-117.709881,33.955113],"type":"Point"}
}