{
  "type": "Feature",
  "properties": {
    "addr:full":"2610 Ridgeland Rd Torrance CA 90505",
    "addr:housenumber":"2610",
    "addr:postcode":"90505",
    "addr:street":"Ridgeland Rd",
    "iso:country":"US",
    "sg:address":"2610 Ridgeland Rd",
    "sg:city":"Torrance",
    "sg:classifiers":[
        {
            "category":"Shopping",
            "type":"Retail Goods"
        },
        {
            "category":"Professional",
            "subcategory":"Advertising",
            "type":"Services"
        }
    ],
    "sg:phone":"+1 310 539 2235",
    "sg:postcode":"90505",
    "sg:province":"CA",
    "sg:tags":[
        "mail",
        "direct",
        "merchandise"
    ],
    "wof:name":"Crest Services",
    "wof:placetype":"venue"
},
  "geometry": {"coordinates":[-118.336403,33.785189],"type":"Point"}
}