{
  "type": "Feature",
  "properties": {
    "iso:country":"US",
    "sg:address":"7171 Jurupa Ave",
    "sg:city":"Riverside",
    "sg:classifiers":[
        {
            "category":"Retail",
            "subcategory":"Auto Repair",
            "type":"Services"
        }
    ],
    "sg:phone":"+1 951 688 5955",
    "sg:postcode":"92504",
    "sg:province":"CA",
    "sg:tags":[
        "body",
        "automobile",
        "painting"
    ],
    "wof:name":"United Auto Body",
    "wof:placetype":"venue"
},
  "geometry": {"coordinates":[-117.449332,33.960362],"type":"Point"}
}