{
  "type": "Feature",
  "properties": {
    "addr:full":"80 W Bullard Ave Clovis CA 93612",
    "addr:housenumber":"80",
    "addr:postcode":"93612",
    "addr:street":"W Bullard Ave",
    "iso:country":"US",
    "sg:address":"80 W Bullard Ave",
    "sg:city":"Clovis",
    "sg:classifiers":[
        {
            "category":"Professional",
            "type":"Services"
        }
    ],
    "sg:phone":"+1 559 299 8291",
    "sg:postcode":"93612",
    "sg:province":"CA",
    "wof:name":"Winning Edge",
    "wof:placetype":"venue"
},
  "geometry": {"coordinates":[-119.710804,36.82293],"type":"Point"}
}