{
  "type": "Feature",
  "properties": {
    "addr:full":"842 Matagual Dr Vista CA 92081",
    "addr:housenumber":"842",
    "addr:postcode":"92081",
    "addr:street":"Matagual Dr",
    "iso:country":"US",
    "sg:address":"842 Matagual Dr",
    "sg:city":"Vista",
    "sg:classifiers":[
        {
            "category":"Building & Trades",
            "subcategory":"Cleaning & Sanitation",
            "type":"Services"
        }
    ],
    "sg:phone":"+1 760 941 3601",
    "sg:postcode":"92081",
    "sg:province":"CA",
    "sg:tags":[
        "janitor"
    ],
    "wof:name":"Blanco's Janitoral Svc Sptl",
    "wof:placetype":"venue"
},
  "geometry": {"coordinates":[-117.25189399999999,33.188107],"type":"Point"}
}