{
  "type": "Feature",
  "properties": {
    "addr:full":"340 W Grant Line Rd Tracy CA 95376",
    "addr:housenumber":"340",
    "addr:postcode":"95376",
    "addr:street":"W Grant Line Rd",
    "iso:country":"US",
    "sg:address":"340 W Grant Line Rd",
    "sg:city":"Tracy",
    "sg:classifiers":[
        {
            "category":"Home & Garden",
            "subcategory":"Furniture",
            "type":"Retail Goods"
        }
    ],
    "sg:phone":"+1 209 839 9206",
    "sg:postcode":"95376",
    "sg:province":"CA",
    "wof:name":"Century Furniture",
    "wof:placetype":"venue"
},
  "geometry": {"coordinates":[-121.431736,37.754164],"type":"Point"}
}