{
  "type": "Feature",
  "properties": {
    "addr:full":"4741 Laurel Canyon Blvd Valley Village CA 91607",
    "addr:housenumber":"4741",
    "addr:postcode":"91607",
    "addr:street":"Laurel Canyon Blvd",
    "iso:country":"US",
    "sg:address":"4741 Laurel Canyon Blvd",
    "sg:city":"Valley Village",
    "sg:classifiers":[
        {
            "category":"Professional",
            "subcategory":"Accounting & Tax Preparation",
            "type":"Services"
        }
    ],
    "sg:phone":"+1 818 509 9809",
    "sg:postcode":"91607",
    "sg:province":"CA",
    "sg:tags":[
        "accountant"
    ],
    "wof:name":"Harry Edelstein CPA",
    "wof:placetype":"venue"
},
  "geometry": {"coordinates":[-118.396557,34.156443],"type":"Point"}
}