{
  "type": "Feature",
  "properties": {
    "iso:country":"US",
    "sg:address":"3909 Marysville Blvd",
    "sg:city":"Sacramento",
    "sg:classifiers":[
        {
            "category":"Autos & Motor Vehicles",
            "subcategory":"Auto Supplies",
            "type":"Retail Goods"
        },
        {
            "category":"Retail",
            "subcategory":"Auto Repair",
            "type":"Services"
        }
    ],
    "sg:phone":"+1 916 920 9456",
    "sg:postcode":"95838",
    "sg:province":"CA",
    "sg:tags":[
        "body",
        "shop",
        "glass"
    ],
    "wof:name":"Dynamic Auto Glass",
    "wof:placetype":"venue"
},
  "geometry": {"coordinates":[-121.429001,38.638699],"type":"Point"}
}