{
  "type": "Feature",
  "properties": {
    "addr:full":"116 Oak St Maxwell Maxwell CA 95955",
    "addr:housenumber":"116",
    "addr:postcode":"95955",
    "addr:street":"Oak St",
    "iso:country":"US",
    "sg:address":"116 Oak St Maxwell",
    "sg:city":"Maxwell",
    "sg:classifiers":[
        {
            "category":"Deli",
            "type":"Food & Drink"
        },
        {
            "category":"Restaurant",
            "type":"Food & Drink"
        }
    ],
    "sg:phone":"+1 530 438 2288",
    "sg:postcode":"95955",
    "sg:province":"CA",
    "sg:tags":[
        "delicatessen"
    ],
    "wof:name":"Kims Main St Deli & Meats",
    "wof:placetype":"venue"
},
  "geometry": {"coordinates":[-122.19293,39.276248],"type":"Point"}
}