{
  "type": "Feature",
  "properties": {
    "addr:full":"3195 Athens Ave Lincoln CA 95648",
    "addr:housenumber":"3195",
    "addr:postcode":"95648",
    "addr:street":"Athens Ave",
    "iso:country":"US",
    "sg:address":"3195 Athens Ave",
    "sg:city":"Lincoln",
    "sg:classifiers":[
        {
            "category":"Utilities",
            "subcategory":"Refuse",
            "type":"Services"
        }
    ],
    "sg:phone":"+1 916 645 4603",
    "sg:postcode":"95648",
    "sg:province":"CA",
    "sg:tags":[
        "landfill",
        "system"
    ],
    "wof:name":"Western Regional Landfill",
    "wof:placetype":"venue"
},
  "geometry": {"coordinates":[-121.34917900000001,38.838804],"type":"Point"}
}