{
  "type": "Feature",
  "properties": {
    "addr:full":"1822 Angela Street San Jose CA 95125",
    "addr:housenumber":"1822",
    "addr:postcode":"95125",
    "addr:street":"Angela Street",
    "iso:country":"US",
    "sg:address":"1822 Angela Street",
    "sg:city":"San Jose",
    "sg:classifiers":[
        {
            "category":"Retail",
            "subcategory":"Auto Rental",
            "type":"Services"
        }
    ],
    "sg:phone":"+1 408 537 0580",
    "sg:postcode":"95125",
    "sg:province":"CA",
    "sg:tags":[
        "car"
    ],
    "sg:website":"www.enterprise.com",
    "wof:name":"Enterprise Rent-A-Car",
    "wof:placetype":"venue"
},
  "geometry": {"coordinates":[-121.87721000000001,37.304379],"type":"Point"}
}