{
  "type": "Feature",
  "properties": {
    "addr:full":"906 S Main St Lakeport CA 95453",
    "addr:housenumber":"906",
    "addr:postcode":"95453",
    "addr:street":"S Main St",
    "iso:country":"US",
    "sg:address":"906 S Main St",
    "sg:city":"Lakeport",
    "sg:classifiers":[
        {
            "category":"Shopping",
            "subcategory":"Hobbies, Toys, & Games",
            "type":"Retail Goods"
        }
    ],
    "sg:phone":"+1 707 263 1339",
    "sg:postcode":"95453",
    "sg:province":"CA",
    "sg:tags":[
        "craft",
        "supply"
    ],
    "wof:name":"X Stitch Things",
    "wof:placetype":"venue"
},
  "geometry": {"coordinates":[-122.91552799999999,39.035802],"type":"Point"}
}