{
  "type": "Feature",
  "properties": {
    "iso:country":"US",
    "sg:address":"32045 Yucaipa Blvd",
    "sg:city":"Yucaipa",
    "sg:classifiers":[
        {
            "category":"Retail",
            "subcategory":"Auto Rental",
            "type":"Services"
        }
    ],
    "sg:phone":"+1 800 468 4285",
    "sg:postcode":"92399",
    "sg:province":"CA",
    "sg:tags":[
        "renting",
        "truck",
        "leasing"
    ],
    "wof:name":"U-Haul Co.",
    "wof:placetype":"venue"
},
  "geometry": {"coordinates":[-117.105914,34.03159],"type":"Point"}
}