{
  "type": "Feature",
  "properties": {
    "addr:full":"1400 Churchill Downs Ave Woodland CA 95776",
    "addr:housenumber":"1400",
    "addr:postcode":"95776",
    "addr:street":"Churchill Downs Ave",
    "iso:country":"US",
    "sg:address":"1400 Churchill Downs Ave",
    "sg:city":"Woodland",
    "sg:classifiers":[
        {
            "category":"Freight",
            "type":"Transportation"
        }
    ],
    "sg:phone":"+1 530 666 2700",
    "sg:postcode":"95776",
    "sg:province":"CA",
    "sg:tags":[
        "general"
    ],
    "wof:name":"Service Craft Corp",
    "wof:placetype":"venue"
},
  "geometry": {"coordinates":[-121.753016,38.69862],"type":"Point"}
}