{
  "type": "Feature",
  "properties": {
    "iso:country":"US",
    "sg:address":"3384 S Hunt Rd",
    "sg:city":"Gustine",
    "sg:classifiers":[
        {
            "category":"Farming",
            "subcategory":"Livestock Farm",
            "type":"Manufacturing & Wholesale Goods"
        }
    ],
    "sg:phone":"+1 209 854 6729",
    "sg:postcode":"95322",
    "sg:province":"CA",
    "sg:tags":[
        "beef",
        "feedlot",
        "cattle"
    ],
    "wof:name":"Rocken Nine",
    "wof:placetype":"venue"
},
  "geometry": {"coordinates":[-120.994282,37.241013],"type":"Point"}
}