{
  "type": "Feature",
  "properties": {
    "addr:full":"2761 Evergreen Ave West Sacramento CA 95691",
    "addr:housenumber":"2761",
    "addr:postcode":"95691",
    "addr:street":"Evergreen Ave",
    "iso:country":"US",
    "sg:address":"2761 Evergreen Ave",
    "sg:city":"West Sacramento",
    "sg:classifiers":[
        {
            "category":"Travel",
            "subcategory":"Hotels & Motels",
            "type":"Entertainment"
        },
        {
            "category":"Retail",
            "subcategory":"Event Space",
            "type":"Services"
        }
    ],
    "sg:phone":"+1 916 372 6900",
    "sg:postcode":"95691",
    "sg:province":"CA",
    "sg:tags":[
        "venue"
    ],
    "sg:website":"www.holidayinnexpress.com",
    "wof:name":"Holiday Inn Express Hotel West Sacramento",
    "wof:placetype":"venue"
},
  "geometry": {"coordinates":[-121.547375,38.576577],"type":"Point"}
}