{
  "type": "Feature",
  "properties": {
    "iso:country":"US",
    "sg:address":"1344 Park St",
    "sg:city":"Paso Robles",
    "sg:classifiers":[
        {
            "category":"Restaurant",
            "type":"Food & Drink"
        }
    ],
    "sg:phone":"+1 805 239 3366",
    "sg:postcode":"93446",
    "sg:province":"CA",
    "wof:name":"Panolivo Restaurant",
    "wof:placetype":"venue"
},
  "geometry": {"coordinates":[-120.690184,35.628407],"type":"Point"}
}