{
  "type": "Feature",
  "properties": {
    "iso:country":"US",
    "sg:address":"2800 N Main St",
    "sg:city":"Santa Ana",
    "sg:classifiers":[
        {
            "category":"Shopping",
            "subcategory":"Jewelry",
            "type":"Retail Goods"
        }
    ],
    "sg:phone":"+1 714 541 6295",
    "sg:postcode":"92705",
    "sg:province":"CA",
    "wof:name":"Sirilak Jewelry",
    "wof:placetype":"venue"
},
  "geometry": {"coordinates":[-117.866997,33.7747],"type":"Point"}
}