{
  "type": "Feature",
  "properties": {
    "iso:country":"US",
    "sg:address":"5541 Santa Monica Blvd",
    "sg:city":"Los Angeles",
    "sg:classifiers":[
        {
            "category":"Retail",
            "subcategory":"Repair Shop",
            "type":"Services"
        }
    ],
    "sg:phone":"+1 323 962 3068",
    "sg:postcode":"90038",
    "sg:province":"CA",
    "sg:tags":[
        "equipment",
        "electronic",
        "supply"
    ],
    "wof:name":"Palms Electronic Inc",
    "wof:placetype":"venue"
},
  "geometry": {"coordinates":[-118.31031299999999,34.090843],"type":"Point"}
}