{
  "type": "Feature",
  "properties": {
    "addr:full":"1420 Dixon St Glendale CA 91205",
    "addr:housenumber":"1420",
    "addr:postcode":"91205",
    "addr:street":"Dixon St",
    "iso:country":"US",
    "sg:address":"1420 Dixon St",
    "sg:city":"Glendale",
    "sg:classifiers":[
        {
            "category":"Real Estate",
            "subcategory":"Real Estate Agent",
            "type":"Services"
        }
    ],
    "sg:phone":"+1 818 246 9500",
    "sg:postcode":"91205",
    "sg:province":"CA",
    "wof:name":"Greatland Realty",
    "wof:placetype":"venue"
},
  "geometry": {"coordinates":[-118.231908,34.141421],"type":"Point"}
}