{
  "type": "Feature",
  "properties": {
    "iso:country":"US",
    "sg:address":"1302 Butte St",
    "sg:city":"Corning",
    "sg:classifiers":[
        {
            "category":"Professional",
            "type":"Services"
        }
    ],
    "sg:phone":"+1 530 934 6247",
    "sg:postcode":"96021",
    "sg:province":"CA",
    "wof:name":"Susan M Cleland",
    "wof:placetype":"venue"
},
  "geometry": {"coordinates":[-122.183453,39.929962],"type":"Point"}
}