{
  "type": "Feature",
  "properties": {
    "addr:full":"212 Lucas Avenue Los Angeles CA 90026",
    "addr:housenumber":"212",
    "addr:postcode":"90026",
    "addr:street":"Lucas Avenue",
    "iso:country":"US",
    "sg:address":"212 Lucas Avenue",
    "sg:city":"Los Angeles",
    "sg:classifiers":[
        {
            "category":"Real Estate",
            "subcategory":"Real Estate Operator",
            "type":"Services"
        }
    ],
    "sg:phone":"+1 213 482 4566",
    "sg:postcode":"90026",
    "sg:province":"CA",
    "sg:tags":[
        "apartment"
    ],
    "wof:name":"Emerald Park Apartments",
    "wof:placetype":"venue"
},
  "geometry": {"coordinates":[-118.26054999999999,34.060028],"type":"Point"}
}