{
  "type": "Feature",
  "properties": {
    "addr:full":"2705 College Ave Berkeley CA 94705",
    "addr:housenumber":"2705",
    "addr:postcode":"94705",
    "addr:street":"College Ave",
    "iso:country":"US",
    "sg:address":"2705 College Ave",
    "sg:city":"Berkeley",
    "sg:classifiers":[
        {
            "category":"Retail",
            "subcategory":"Laundry & Dry Cleaning",
            "type":"Services"
        }
    ],
    "sg:postcode":"94705",
    "sg:province":"CA",
    "wof:name":"Cal Suds",
    "wof:placetype":"venue"
},
  "geometry": {"coordinates":[-122.25299800000001,37.861599],"type":"Point"}
}