{
  "type": "Feature",
  "properties": {
    "iso:country":"US",
    "sg:address":"9200 Slauson Ave",
    "sg:city":"Pico Rivera",
    "sg:classifiers":[
        {
            "category":"Banks & Credit Unions",
            "subcategory":"Bank",
            "type":"Services"
        }
    ],
    "sg:phone":"+1 562 949 6622",
    "sg:postcode":"90660",
    "sg:province":"CA",
    "sg:website":"www.chase.com",
    "wof:name":"Chase",
    "wof:placetype":"venue"
},
  "geometry": {"coordinates":[-118.101019,33.969549],"type":"Point"}
}