{
  "type": "Feature",
  "properties": {
    "iso:country":"US",
    "sg:address":"809 Calico Trl",
    "sg:city":"Vacaville",
    "sg:classifiers":[
        {
            "category":"Freight",
            "type":"Transportation"
        }
    ],
    "sg:phone":"+1 707 452 0237",
    "sg:postcode":"95687",
    "sg:province":"CA",
    "sg:tags":[
        "personal"
    ],
    "wof:name":"Operation Handup",
    "wof:placetype":"venue"
},
  "geometry": {"coordinates":[-121.962329,38.319333],"type":"Point"}
}