{
  "type": "Feature",
  "properties": {
    "addr:full":"1807 Divisadero St San Francisco CA 94102",
    "addr:housenumber":"1807",
    "addr:postcode":"94102",
    "addr:street":"Divisadero St",
    "iso:country":"US",
    "sg:address":"1807 Divisadero St",
    "sg:city":"San Francisco",
    "sg:classifiers":[
        {
            "category":"Shopping",
            "subcategory":"Clothing, Apparel, & Fashions",
            "type":"Retail Goods"
        },
        {
            "category":"Personal",
            "type":"Services"
        }
    ],
    "sg:phone":"+1 415 345 9200",
    "sg:postcode":"94102",
    "sg:province":"CA",
    "sg:tags":[
        "children's",
        "sewing",
        "clothing",
        "alteration"
    ],
    "sg:website":"www.weescotty.com",
    "wof:name":"Wee Scotty",
    "wof:placetype":"venue"
},
  "geometry": {"coordinates":[-122.440128,37.786245],"type":"Point"}
}