{
  "type": "Feature",
  "properties": {
    "addr:full":"22553 Main St Hayward CA 94541",
    "addr:housenumber":"22553",
    "addr:postcode":"94541",
    "addr:street":"Main St",
    "iso:country":"US",
    "sg:address":"22553 Main St",
    "sg:city":"Hayward",
    "sg:classifiers":[
        {
            "category":"Shopping",
            "subcategory":"Books",
            "type":"Retail Goods"
        }
    ],
    "sg:phone":"+1 510 886 7777",
    "sg:postcode":"94541",
    "sg:province":"CA",
    "sg:tags":[
        "adult"
    ],
    "wof:name":"L'amour Shoppe",
    "wof:placetype":"venue"
},
  "geometry": {"coordinates":[-122.083,37.6731],"type":"Point"}
}