{
  "type": "Feature",
  "properties": {
    "iso:country":"US",
    "sg:address":"27190 State Highway 189",
    "sg:city":"Blue Jay",
    "sg:classifiers":[
        {
            "category":"Sports & Exercise",
            "subcategory":"Gym",
            "type":"Entertainment"
        },
        {
            "category":"Insurance",
            "subcategory":"Health Insurance",
            "type":"Services"
        }
    ],
    "sg:phone":"+1 909 337 2344",
    "sg:postcode":"92317",
    "sg:province":"CA",
    "sg:tags":[
        "trainer",
        "market"
    ],
    "wof:name":"Health Habitat the",
    "wof:placetype":"venue"
},
  "geometry": {"coordinates":[-117.212997,34.250599],"type":"Point"}
}