{
  "type": "Feature",
  "properties": {
    "iso:country":"US",
    "sg:address":"8030 Remmet Ave",
    "sg:city":"Canoga Park",
    "sg:classifiers":[
        {
            "category":"Professional",
            "subcategory":"Testing Lab",
            "type":"Services"
        }
    ],
    "sg:phone":"+1 818 703 1208",
    "sg:postcode":"91304",
    "sg:province":"CA",
    "sg:tags":[
        "laboratory"
    ],
    "wof:name":"Columbia Analytical Inc",
    "wof:placetype":"venue"
},
  "geometry": {"coordinates":[-118.600223,34.219324],"type":"Point"}
}