{
  "type": "Feature",
  "properties": {
    "iso:country":"US",
    "sg:address":"447 N Main St",
    "sg:city":"Manteca",
    "sg:classifiers":[
        {
            "category":"Recreation",
            "type":"Entertainment"
        }
    ],
    "sg:phone":"+1 209 825 5564",
    "sg:postcode":"95336",
    "sg:province":"CA",
    "sg:tags":[
        "instruction",
        "gymnastic"
    ],
    "wof:name":"Funtastic Gymnastics",
    "wof:placetype":"venue"
},
  "geometry": {"coordinates":[-121.216846,37.803508],"type":"Point"}
}