{
  "type": "Feature",
  "properties": {
    "iso:country":"US",
    "sg:address":"7760 Fay Ave Ste T",
    "sg:city":"La Jolla",
    "sg:classifiers":[
        {
            "category":"Personal",
            "subcategory":"Barber",
            "type":"Services"
        }
    ],
    "sg:phone":"+1 858 459 5792",
    "sg:postcode":"92037",
    "sg:province":"CA",
    "wof:name":"La Jolla Barber Shop",
    "wof:placetype":"venue"
},
  "geometry": {"coordinates":[-117.27521900000001,32.844342],"type":"Point"}
}