{
  "type": "Feature",
  "properties": {
    "addr:full":"19 Sheldon Ter San Francisco CA 94122",
    "addr:housenumber":"19",
    "addr:postcode":"94122",
    "addr:street":"Sheldon Ter",
    "iso:country":"US",
    "sg:address":"19 Sheldon Ter",
    "sg:city":"San Francisco",
    "sg:classifiers":[
        {
            "category":"Shopping",
            "type":"Retail Goods"
        }
    ],
    "sg:phone":"+1 415 682 9969",
    "sg:postcode":"94122",
    "sg:province":"CA",
    "sg:tags":[
        "equipment",
        "care",
        "health",
        "home"
    ],
    "sg:website":"www.citywheelchairs.com",
    "wof:name":"CITYWHEELCHAIRS.COM",
    "wof:placetype":"venue"
},
  "geometry": {"coordinates":[-122.471575,37.754948],"type":"Point"}
}