{
  "type": "Feature",
  "properties": {
    "iso:country":"US",
    "sg:address":"529 W 2nd St",
    "sg:city":"Rialto",
    "sg:classifiers":[
        {
            "category":"Professional",
            "subcategory":"Secretarial Services",
            "type":"Services"
        }
    ],
    "sg:phone":"+1 909 820 4773",
    "sg:postcode":"92376",
    "sg:province":"CA",
    "sg:tags":[
        "resume"
    ],
    "wof:name":"Computerease",
    "wof:placetype":"venue"
},
  "geometry": {"coordinates":[-117.379487,34.101851],"type":"Point"}
}