{
  "type": "Feature",
  "properties": {
    "addr:full":"900 Hillview Dr Dixon CA 95620",
    "addr:housenumber":"900",
    "addr:postcode":"95620",
    "addr:street":"Hillview Dr",
    "iso:country":"US",
    "sg:address":"900 Hillview Dr",
    "sg:city":"Dixon",
    "sg:phone":"+1 707 678 4458",
    "sg:postcode":"95620",
    "sg:province":"CA",
    "sg:tags":[
        "farm",
        "ornamental",
        "nursery"
    ],
    "wof:name":"A & A Investments",
    "wof:placetype":"venue"
},
  "geometry": {"coordinates":[-121.833944,38.442658],"type":"Point"}
}