{
  "type": "Feature",
  "properties": {
    "addr:full":"7090 Johnson Dr Pleasanton CA 94588",
    "addr:housenumber":"7090",
    "addr:postcode":"94588",
    "addr:street":"Johnson Dr",
    "iso:country":"US",
    "sg:address":"7090 Johnson Dr",
    "sg:city":"Pleasanton",
    "sg:classifiers":[
        {
            "category":"Retail",
            "subcategory":"Car Wash",
            "type":"Services"
        }
    ],
    "sg:phone":"+1 925 734 6644",
    "sg:postcode":"94588",
    "sg:province":"CA",
    "sg:tags":[
        "automobile",
        "detail",
        "clean"
    ],
    "wof:name":"California Shine Co",
    "wof:placetype":"venue"
},
  "geometry": {"coordinates":[-121.908056,37.700283],"type":"Point"}
}