{
  "type": "Feature",
  "properties": {
    "addr:full":"242 E Main St Ventura CA 93001",
    "addr:housenumber":"242",
    "addr:postcode":"93001",
    "addr:street":"E Main St",
    "iso:country":"US",
    "sg:address":"242 E Main St",
    "sg:city":"Ventura",
    "sg:classifiers":[
        {
            "category":"Retail",
            "subcategory":"Repair Shop",
            "type":"Services"
        }
    ],
    "sg:phone":"+1 805 641 0677",
    "sg:postcode":"93001",
    "sg:province":"CA",
    "sg:tags":[
        "equipment",
        "electronic",
        "supply"
    ],
    "wof:name":"Treasure Island",
    "wof:placetype":"venue"
},
  "geometry": {"coordinates":[-119.296725,34.280731],"type":"Point"}
}