{
  "type": "Feature",
  "properties": {
    "addr:full":"19 Digital Dr Novato CA 94949",
    "addr:housenumber":"19",
    "addr:postcode":"94949",
    "addr:street":"Digital Dr",
    "iso:country":"US",
    "sg:address":"19 Digital Dr",
    "sg:city":"Novato",
    "sg:classifiers":[
        {
            "category":"Restaurant",
            "type":"Food & Drink"
        }
    ],
    "sg:phone":"+1 415 382 8156",
    "sg:postcode":"94949",
    "sg:province":"CA",
    "sg:tags":[
        "delicatessen"
    ],
    "wof:name":"Bell Marin Deli",
    "wof:placetype":"venue"
},
  "geometry": {"coordinates":[-122.53204700000001,38.070631],"type":"Point"}
}