{
  "type": "Feature",
  "properties": {
    "iso:country":"US",
    "sg:address":"139 Kifer Ct",
    "sg:city":"Sunnyvale",
    "sg:classifiers":[
        {
            "category":"Health Services",
            "subcategory":"Doctor",
            "type":"Services"
        }
    ],
    "sg:phone":"+1 408 864 0660",
    "sg:postcode":"94086",
    "sg:province":"CA",
    "wof:name":"Clinical Monitoring Center",
    "wof:placetype":"venue"
},
  "geometry": {"coordinates":[-122.015424,37.374262],"type":"Point"}
}