{
  "type": "Feature",
  "properties": {
    "addr:full":"5015 Van Nuys Blvd Sherman Oaks CA 91403",
    "addr:housenumber":"5015",
    "addr:postcode":"91403",
    "addr:street":"Van Nuys Blvd",
    "iso:country":"US",
    "sg:address":"5015 Van Nuys Blvd",
    "sg:city":"Sherman Oaks",
    "sg:classifiers":[
        {
            "category":"Retail",
            "subcategory":"Auto Repair",
            "type":"Services"
        }
    ],
    "sg:phone":"+1 818 789 1894",
    "sg:postcode":"91403",
    "sg:province":"CA",
    "sg:tags":[
        "repairing",
        "automobile"
    ],
    "wof:name":"Abe's Plaza Motors",
    "wof:placetype":"venue"
},
  "geometry": {"coordinates":[-118.44899700000001,34.1614],"type":"Point"}
}