{
  "type": "Feature",
  "properties": {
    "addr:full":"60 W Easy St Simi Valley CA 93065",
    "addr:housenumber":"60",
    "addr:postcode":"93065",
    "addr:street":"W Easy St",
    "iso:country":"US",
    "sg:address":"60 W Easy St",
    "sg:city":"Simi Valley",
    "sg:classifiers":[
        {
            "category":"Autos & Motor Vehicles",
            "subcategory":"Auto Supplies",
            "type":"Retail Goods"
        }
    ],
    "sg:phone":"+1 805 527 2712",
    "sg:postcode":"93065",
    "sg:province":"CA",
    "sg:tags":[
        "automobile",
        "stereo",
        "radio"
    ],
    "wof:name":"T & R Performance Solutions",
    "wof:placetype":"venue"
},
  "geometry": {"coordinates":[-118.798998,34.278692],"type":"Point"}
}