{
  "type": "Feature",
  "properties": {
    "addr:full":"16325 Old Valley Blvd La Puente CA 91744",
    "addr:housenumber":"16325",
    "addr:postcode":"91744",
    "addr:street":"Old Valley Blvd",
    "iso:country":"US",
    "sg:address":"16325 Old Valley Blvd",
    "sg:city":"La Puente",
    "sg:classifiers":[
        {
            "category":"Wholesale",
            "subcategory":"Petroleum",
            "type":"Manufacturing & Wholesale Goods"
        }
    ],
    "sg:phone":"+1 626 961 0061",
    "sg:postcode":"91744",
    "sg:province":"CA",
    "sg:tags":[
        "bulk",
        "oil",
        "gasoline"
    ],
    "wof:name":"Cox Oil Co",
    "wof:placetype":"venue"
},
  "geometry": {"coordinates":[-117.946305,34.014341],"type":"Point"}
}