{
  "type": "Feature",
  "properties": {
    "addr:full":"764 S Lowry St Orange CA 92869",
    "addr:housenumber":"764",
    "addr:postcode":"92869",
    "addr:street":"S Lowry St",
    "iso:country":"US",
    "sg:address":"764 S Lowry St",
    "sg:city":"Orange",
    "sg:classifiers":[
        {
            "category":"Shopping",
            "subcategory":"Clothing, Apparel, & Fashions",
            "type":"Retail Goods"
        }
    ],
    "sg:phone":"+1 714 633 3619",
    "sg:postcode":"92869",
    "sg:province":"CA",
    "sg:tags":[
        "family"
    ],
    "wof:name":"Bamboozle",
    "wof:placetype":"venue"
},
  "geometry": {"coordinates":[-117.82887700000001,33.776231],"type":"Point"}
}