{
  "type": "Feature",
  "properties": {
    "iso:country":"US",
    "sg:address":"15531 Begonia St",
    "sg:city":"Westminster",
    "sg:classifiers":[
        {
            "category":"Building & Trades",
            "subcategory":"Construction",
            "type":"Services"
        }
    ],
    "sg:phone":"+1 714 839 3591",
    "sg:postcode":"92683",
    "sg:province":"CA",
    "sg:tags":[
        "welder"
    ],
    "wof:name":"Villigan's Portable Welding",
    "wof:placetype":"venue"
},
  "geometry": {"coordinates":[-117.962878,33.737114],"type":"Point"}
}