{
  "type": "Feature",
  "properties": {
    "iso:country":"US",
    "sg:address":"2205 Lee Ave",
    "sg:city":"South El Monte",
    "sg:classifiers":[
        {
            "category":"Manufacturing",
            "subcategory":"Food",
            "type":"Manufacturing & Wholesale Goods"
        }
    ],
    "sg:phone":"+1 626 452 8073",
    "sg:postcode":"91733",
    "sg:province":"CA",
    "sg:tags":[
        "preparation",
        "grocery",
        "noodle",
        "mfg"
    ],
    "wof:name":"Kang Fuk Inc",
    "wof:placetype":"venue"
},
  "geometry": {"coordinates":[-118.067334,34.052596],"type":"Point"}
}