{
  "type": "Feature",
  "properties": {
    "addr:full":"971 N Harbor Blvd La Habra CA 90631",
    "addr:housenumber":"971",
    "addr:postcode":"90631",
    "addr:street":"N Harbor Blvd",
    "iso:country":"US",
    "sg:address":"971 N Harbor Blvd",
    "sg:city":"La Habra",
    "sg:classifiers":[
        {
            "category":"Health Services",
            "subcategory":"Doctor",
            "type":"Services"
        }
    ],
    "sg:phone":"+1 562 690 3551",
    "sg:postcode":"90631",
    "sg:province":"CA",
    "sg:tags":[
        "dentist"
    ],
    "wof:name":"Harbor Dental",
    "wof:placetype":"venue"
},
  "geometry": {"coordinates":[-117.933119,33.941322],"type":"Point"}
}