{
  "type": "Feature",
  "properties": {
    "iso:country":"US",
    "sg:address":"533 E Palmdale Blvd",
    "sg:city":"Palmdale",
    "sg:classifiers":[
        {
            "category":"Freight",
            "type":"Transportation"
        }
    ],
    "sg:phone":"+1 661 538 9900",
    "sg:postcode":"93550",
    "sg:province":"CA",
    "wof:name":"Diamond Transportation",
    "wof:placetype":"venue"
},
  "geometry": {"coordinates":[-118.119998,34.579715],"type":"Point"}
}