{
  "type": "Feature",
  "properties": {
    "iso:country":"US",
    "sg:address":"636 Hindfell Way",
    "sg:city":"Solvang",
    "sg:classifiers":[
        {
            "category":"Professional",
            "subcategory":"Engineering",
            "type":"Services"
        }
    ],
    "sg:phone":"+1 805 686 0218",
    "sg:postcode":"93463",
    "sg:province":"CA",
    "sg:tags":[
        "engineer"
    ],
    "wof:name":"Russell A Holland & Co",
    "wof:placetype":"venue"
},
  "geometry": {"coordinates":[-120.135057,34.599898],"type":"Point"}
}