{
  "type": "Feature",
  "properties": {
    "addr:full":"12042 Gay Rio Dr Lakeside CA 92040",
    "addr:housenumber":"12042",
    "addr:postcode":"92040",
    "addr:street":"Gay Rio Dr",
    "iso:country":"US",
    "sg:address":"12042 Gay Rio Dr",
    "sg:city":"Lakeside",
    "sg:classifiers":[
        {
            "category":"Shopping",
            "subcategory":"Bicycles & Sporting Goods",
            "type":"Retail Goods"
        }
    ],
    "sg:phone":"+1 619 443 1206",
    "sg:postcode":"92040",
    "sg:province":"CA",
    "sg:tags":[
        "equipment",
        "golf",
        "supply"
    ],
    "wof:name":"Golfer's Custom Clubs",
    "wof:placetype":"venue"
},
  "geometry": {"coordinates":[-116.932552,32.838871],"type":"Point"}
}