{
  "type": "Feature",
  "properties": {
    "addr:full":"1314 Lincoln Ave Ste 1C San Jose CA 95125",
    "addr:housenumber":"1314",
    "addr:postcode":"95125",
    "addr:street":"Lincoln Ave Ste 1C",
    "iso:country":"US",
    "sg:address":"1314 Lincoln Ave Ste 1C",
    "sg:city":"San Jose",
    "sg:classifiers":[
        {
            "category":"Personal",
            "subcategory":"Beauty Salon",
            "type":"Services"
        }
    ],
    "sg:phone":"+1 408 292 9221",
    "sg:postcode":"95125",
    "sg:province":"CA",
    "sg:tags":[
        "hair"
    ],
    "sg:website":"eliteimagehair.com/",
    "wof:name":"Elite Image",
    "wof:placetype":"venue"
},
  "geometry": {"coordinates":[-121.898301,37.304717],"type":"Point"}
}