{
  "type": "Feature",
  "properties": {
    "addr:full":"6360 Bennett Valley Rd Santa Rosa CA 95404",
    "addr:housenumber":"6360",
    "addr:postcode":"95404",
    "addr:street":"Bennett Valley Rd",
    "iso:country":"US",
    "sg:address":"6360 Bennett Valley Rd",
    "sg:city":"Santa Rosa",
    "sg:classifiers":[
        {
            "category":"Shopping",
            "subcategory":"Used Merchandise",
            "type":"Retail Goods"
        }
    ],
    "sg:phone":"+1 707 545 5050",
    "sg:postcode":"95404",
    "sg:province":"CA",
    "wof:name":"B&D Antiques",
    "wof:placetype":"venue"
},
  "geometry": {"coordinates":[-122.609211,38.395478],"type":"Point"}
}