{
  "type": "Feature",
  "properties": {
    "iso:country":"US",
    "sg:address":"7719 Somerset Blvd",
    "sg:city":"Paramount",
    "sg:classifiers":[
        {
            "category":"Manufacturing",
            "subcategory":"Leather Goods",
            "type":"Manufacturing & Wholesale Goods"
        }
    ],
    "sg:phone":"+1 562 220 1520",
    "sg:postcode":"90723",
    "sg:province":"CA",
    "sg:tags":[
        "shoes"
    ],
    "wof:name":"Mundo Exotico",
    "wof:placetype":"venue"
},
  "geometry": {"coordinates":[-118.164891,33.896414],"type":"Point"}
}