{
  "type": "Feature",
  "properties": {
    "iso:country":"US",
    "sg:address":"4001 N Freeway Blvd Bl",
    "sg:city":"Sacramento",
    "sg:classifiers":[
        {
            "category":"Professional",
            "subcategory":"Business Services",
            "type":"Services"
        }
    ],
    "sg:phone":"+1 916 923 3497",
    "sg:postcode":"95834",
    "sg:province":"CA",
    "sg:tags":[
        "management"
    ],
    "wof:name":"Jp Management Lp",
    "wof:placetype":"venue"
},
  "geometry": {"coordinates":[-121.47879500000001,38.641563],"type":"Point"}
}