{
  "type": "Feature",
  "properties": {
    "iso:country":"US",
    "sg:address":"5285 el Cajon Blvd",
    "sg:city":"San Diego",
    "sg:classifiers":[
        {
            "category":"Retail",
            "subcategory":"Repair Shop",
            "type":"Services"
        }
    ],
    "sg:phone":"+1 619 229 1220",
    "sg:postcode":"92115",
    "sg:province":"CA",
    "sg:tags":[
        "jewelry"
    ],
    "wof:name":"Mark Chen Watch & Jewelry",
    "wof:placetype":"venue"
},
  "geometry": {"coordinates":[-117.08222600000001,32.757336],"type":"Point"}
}