{
  "type": "Feature",
  "properties": {
    "addr:full":"333 N Lewis Rd Camarillo CA 93012",
    "addr:housenumber":"333",
    "addr:postcode":"93012",
    "addr:street":"N Lewis Rd",
    "iso:country":"US",
    "sg:address":"333 N Lewis Rd",
    "sg:city":"Camarillo",
    "sg:classifiers":[
        {
            "category":"Restaurant",
            "type":"Food & Drink"
        }
    ],
    "sg:phone":"+1 805 482 4318",
    "sg:postcode":"93012",
    "sg:province":"CA",
    "sg:website":"www.eltecolote.com",
    "wof:name":"El Tecolote Restaurant",
    "wof:placetype":"venue"
},
  "geometry": {"coordinates":[-119.023003,34.2281],"type":"Point"}
}