{
  "type": "Feature",
  "properties": {
    "iso:country":"US",
    "sg:address":"132 W Nees Ave",
    "sg:city":"Fresno",
    "sg:classifiers":[
        {
            "category":"Restaurant",
            "type":"Food & Drink"
        }
    ],
    "sg:menulink":"http://www.allmenus.com/ca/fresno/162777-port-of-subs/menu/",
    "sg:phone":"+1 559 431 1980",
    "sg:postcode":"93711",
    "sg:province":"CA",
    "sg:tags":[
        "wrap",
        "american",
        "sandwich"
    ],
    "wof:name":"Port of Subs",
    "wof:placetype":"venue"
},
  "geometry": {"coordinates":[-119.791912,36.851916],"type":"Point"}
}