{
  "type": "Feature",
  "properties": {
    "iso:country":"US",
    "sg:address":"5025 Paradise Dr",
    "sg:city":"Belvedere Tibrn",
    "sg:classifiers":[
        {
            "category":"Professional",
            "subcategory":"Employment Agencies",
            "type":"Services"
        }
    ],
    "sg:phone":"+1 415 789 5627",
    "sg:postcode":"94920",
    "sg:province":"CA",
    "sg:tags":[
        "opportunity"
    ],
    "sg:website":"www.cssjobs.com",
    "wof:name":"Office Concepts",
    "wof:placetype":"venue"
},
  "geometry": {"coordinates":[-122.484965,37.919323],"type":"Point"}
}