{
  "type": "Feature",
  "properties": {
    "iso:country":"US",
    "sg:address":"70 S Lake Ave",
    "sg:city":"Pasadena",
    "sg:classifiers":[
        {
            "category":"Professional",
            "subcategory":"Computer Services",
            "type":"Services"
        }
    ],
    "sg:phone":"+1 626 432 4830",
    "sg:postcode":"91106",
    "sg:province":"CA",
    "sg:tags":[
        "hardware",
        "provider",
        "internet",
        "software"
    ],
    "wof:name":"Creation Point System Corp",
    "wof:placetype":"venue"
},
  "geometry": {"coordinates":[-118.132275,34.145791],"type":"Point"}
}