{
  "type": "Feature",
  "properties": {
    "iso:country":"US",
    "sg:address":"4643 Griffith Ave",
    "sg:city":"Fremont",
    "sg:classifiers":[
        {
            "category":"Home & Garden",
            "subcategory":"Hardware",
            "type":"Retail Goods"
        }
    ],
    "sg:phone":"+1 510 490 6022",
    "sg:postcode":"94538",
    "sg:province":"CA",
    "sg:tags":[
        "equipment",
        "industrial"
    ],
    "wof:name":"Welding & Soldering Eqp Co",
    "wof:placetype":"venue"
},
  "geometry": {"coordinates":[-121.973142,37.525254],"type":"Point"}
}