{
  "type": "Feature",
  "properties": {
    "addr:full":"207 Nijmegen Rd Seaside CA 93955",
    "addr:housenumber":"207",
    "addr:postcode":"93955",
    "addr:street":"Nijmegen Rd",
    "iso:country":"US",
    "sg:address":"207 Nijmegen Rd",
    "sg:city":"Seaside",
    "sg:classifiers":[
        {
            "category":"Shopping",
            "type":"Retail Goods"
        }
    ],
    "sg:phone":"+1 831 583 9581",
    "sg:postcode":"93955",
    "sg:province":"CA",
    "sg:tags":[
        "pet",
        "food",
        "supply"
    ],
    "wof:name":"Natures Paws",
    "wof:placetype":"venue"
},
  "geometry": {"coordinates":[-121.799689,36.639776],"type":"Point"}
}