{
  "type": "Feature",
  "properties": {
    "addr:full":"938 Webster St Oakland CA 94607",
    "addr:housenumber":"938",
    "addr:postcode":"94607",
    "addr:street":"Webster St",
    "iso:country":"US",
    "sg:address":"938 Webster St",
    "sg:city":"Oakland",
    "sg:classifiers":[
        {
            "category":"Shopping",
            "subcategory":"Florist",
            "type":"Retail Goods"
        }
    ],
    "sg:phone":"+1 510 893 5442",
    "sg:postcode":"94607",
    "sg:province":"CA",
    "wof:name":"Mei Wo Florist",
    "wof:placetype":"venue"
},
  "geometry": {"coordinates":[-122.271004,37.8004],"type":"Point"}
}