{
  "type": "Feature",
  "properties": {
    "iso:country":"US",
    "sg:address":"3030 Bonita Rd",
    "sg:city":"National City",
    "sg:classifiers":[
        {
            "category":"Utilities",
            "subcategory":"Mobile Phone",
            "type":"Services"
        }
    ],
    "sg:phone":"+1 619 479 8700",
    "sg:postcode":"91910",
    "sg:province":"CA",
    "sg:tags":[
        "telephone",
        "cellular"
    ],
    "wof:name":"Snap Wireless",
    "wof:placetype":"venue"
},
  "geometry": {"coordinates":[-117.057897,32.647711],"type":"Point"}
}