{
  "type": "Feature",
  "properties": {
    "addr:full":"914 Minnesota Ave San Jose CA 95125",
    "addr:housenumber":"914",
    "addr:postcode":"95125",
    "addr:street":"Minnesota Ave",
    "iso:country":"US",
    "sg:address":"914 Minnesota Ave",
    "sg:city":"San Jose",
    "sg:classifiers":[
        {
            "category":"Food & Beverages",
            "subcategory":"Candy",
            "type":"Retail Goods"
        },
        {
            "category":"Shopping",
            "subcategory":"Florist",
            "type":"Retail Goods"
        }
    ],
    "sg:phone":"+1 650 968 0141",
    "sg:postcode":"95125",
    "sg:province":"CA",
    "sg:tags":[
        "store"
    ],
    "sg:website":"www.floratiquefloral.com",
    "wof:name":"Floratique Flowers, Chocolate & Gift Baskets",
    "wof:placetype":"venue"
},
  "geometry": {"coordinates":[-121.89352100000001,37.305598],"type":"Point"}
}