{
  "type": "Feature",
  "properties": {
    "addr:full":"334 Five Cities Dr Pismo Beach CA 93449",
    "addr:housenumber":"334",
    "addr:postcode":"93449",
    "addr:street":"Five Cities Dr",
    "iso:country":"US",
    "sg:address":"334 Five Cities Dr",
    "sg:city":"Pismo Beach",
    "sg:classifiers":[
        {
            "category":"Restaurant",
            "type":"Food & Drink"
        }
    ],
    "sg:menulink":"http://www.allmenus.com/ca/arroyo-grande/178010-jack-in-the-box/menu/",
    "sg:phone":"+1 805 556 0580",
    "sg:postcode":"93449",
    "sg:province":"CA",
    "sg:tags":[
        "burger",
        "american"
    ],
    "wof:name":"Jack in the Box",
    "wof:placetype":"venue"
},
  "geometry": {"coordinates":[-120.629503,35.136921],"type":"Point"}
}