{
  "type": "Feature",
  "properties": {
    "iso:country":"US",
    "sg:address":"398 Main St",
    "sg:city":"Placerville",
    "sg:classifiers":[
        {
            "category":"Wholesale",
            "subcategory":"Home Furnishings",
            "type":"Manufacturing & Wholesale Goods"
        }
    ],
    "sg:phone":"+1 530 344 0660",
    "sg:postcode":"95667",
    "sg:province":"CA",
    "sg:tags":[
        "retail"
    ],
    "wof:name":"Sierra Country Home",
    "wof:placetype":"venue"
},
  "geometry": {"coordinates":[-120.799858,38.729513],"type":"Point"}
}