{
  "type": "Feature",
  "properties": {
    "iso:country":"US",
    "sg:address":"1118 Rockwood Rd",
    "sg:city":"Heber",
    "sg:classifiers":[
        {
            "category":"Farming",
            "subcategory":"Farm & Veterinary Services",
            "type":"Manufacturing & Wholesale Goods"
        }
    ],
    "sg:phone":"+1 760 336 0727",
    "sg:postcode":"92249",
    "sg:province":"CA",
    "sg:tags":[
        "harvesting"
    ],
    "wof:name":"Boss Har-PAK LLC",
    "wof:placetype":"venue"
},
  "geometry": {"coordinates":[-115.52499400000001,32.731237],"type":"Point"}
}