{
  "type": "Feature",
  "properties": {
    "iso:country":"US",
    "sg:address":"19475 Cheshire St",
    "sg:city":"Rialto",
    "sg:classifiers":[
        {
            "category":"Building & Trades",
            "subcategory":"Cleaning & Sanitation",
            "type":"Services"
        }
    ],
    "sg:phone":"+1 909 877 9376",
    "sg:postcode":"92377",
    "sg:province":"CA",
    "sg:tags":[
        "butler",
        "maid"
    ],
    "wof:name":"Sunshine Professional Maid",
    "wof:placetype":"venue"
},
  "geometry": {"coordinates":[-117.379178,34.138945],"type":"Point"}
}