{
  "type": "Feature",
  "properties": {
    "iso:country":"US",
    "sg:address":"925 Cadiz St",
    "sg:city":"Corona",
    "sg:classifiers":[
        {
            "category":"Wholesale",
            "subcategory":"Electrical",
            "type":"Manufacturing & Wholesale Goods"
        }
    ],
    "sg:phone":"+1 951 739 6306",
    "sg:postcode":"92882",
    "sg:province":"CA",
    "sg:tags":[
        "equipment"
    ],
    "wof:name":"Lakewood Central Station",
    "wof:placetype":"venue"
},
  "geometry": {"coordinates":[-117.582516,33.851676],"type":"Point"}
}