{
  "type": "Feature",
  "properties": {
    "iso:country":"US",
    "sg:address":"1471 E Philadelphia St",
    "sg:city":"Ontario",
    "sg:classifiers":[
        {
            "category":"Manufacturing",
            "subcategory":"Metals",
            "type":"Manufacturing & Wholesale Goods"
        }
    ],
    "sg:phone":"+1 909 947 5223",
    "sg:postcode":"91761",
    "sg:province":"CA",
    "sg:tags":[
        "polishing"
    ],
    "wof:name":"R & T Metal Finish",
    "wof:placetype":"venue"
},
  "geometry": {"coordinates":[-117.622224,34.03408],"type":"Point"}
}