{
  "type": "Feature",
  "properties": {
    "iso:country":"US",
    "sg:address":"165 Rowland Way Ste 212",
    "sg:city":"Novato",
    "sg:classifiers":[
        {
            "category":"Health Services",
            "subcategory":"Doctor",
            "type":"Services"
        },
        {
            "category":"Personal",
            "subcategory":"Skin Care",
            "type":"Services"
        }
    ],
    "sg:phone":"+1 415 892 9550",
    "sg:postcode":"94945",
    "sg:province":"CA",
    "sg:tags":[
        "physician",
        "surgeons",
        "laser",
        "surgery",
        "vascular"
    ],
    "sg:website":"http://www.laserlight.org",
    "wof:name":"Laser Light Treatment Center",
    "wof:placetype":"venue"
},
  "geometry": {"coordinates":[-122.559037,38.095313],"type":"Point"}
}