{
  "type": "Feature",
  "properties": {
    "iso:country":"US",
    "sg:address":"1309 61st St",
    "sg:city":"Emeryville",
    "sg:classifiers":[
        {
            "category":"Food & Beverages",
            "subcategory":"Groceries & Convenience Stores",
            "type":"Retail Goods"
        }
    ],
    "sg:phone":"+1 510 653 8022",
    "sg:postcode":"94608",
    "sg:province":"CA",
    "wof:name":"Kangaroo Kitchen",
    "wof:placetype":"venue"
},
  "geometry": {"coordinates":[-122.28859799999999,37.843022],"type":"Point"}
}