{
  "type": "Feature",
  "properties": {
    "addr:full":"45 Creek Rd Fairfax CA 94930",
    "addr:housenumber":"45",
    "addr:postcode":"94930",
    "addr:street":"Creek Rd",
    "iso:country":"US",
    "sg:address":"45 Creek Rd",
    "sg:city":"Fairfax",
    "sg:classifiers":[
        {
            "category":"Health Services",
            "subcategory":"Health Practitioner",
            "type":"Services"
        }
    ],
    "sg:phone":"+1 415 479 2505",
    "sg:postcode":"94930",
    "sg:province":"CA",
    "sg:tags":[
        "nutritionist"
    ],
    "wof:name":"Marin Health Educators",
    "wof:placetype":"venue"
},
  "geometry": {"coordinates":[-122.59088800000001,37.983283],"type":"Point"}
}