{
  "type": "Feature",
  "properties": {
    "addr:full":"9432 Laurel Ave Fontana CA 92335",
    "addr:housenumber":"9432",
    "addr:postcode":"92335",
    "addr:street":"Laurel Ave",
    "iso:country":"US",
    "sg:address":"9432 Laurel Ave",
    "sg:city":"Fontana",
    "sg:classifiers":[
        {
            "category":"Professional",
            "type":"Services"
        }
    ],
    "sg:phone":"+1 909 350 6029",
    "sg:postcode":"92335",
    "sg:province":"CA",
    "wof:name":"Darlene Uphold",
    "wof:placetype":"venue"
},
  "geometry": {"coordinates":[-117.413366,34.083741],"type":"Point"}
}