{
  "type": "Feature",
  "properties": {
    "iso:country":"US",
    "sg:address":"2211 S Shore Ctr",
    "sg:city":"Alameda",
    "sg:classifiers":[
        {
            "category":"Shopping",
            "subcategory":"Clothing, Apparel, & Fashions",
            "type":"Retail Goods"
        }
    ],
    "sg:phone":"+1 510 337 1013",
    "sg:postcode":"94501",
    "sg:province":"CA",
    "sg:tags":[
        "children's",
        "clothing"
    ],
    "wof:name":"The Children's Place",
    "wof:placetype":"venue"
},
  "geometry": {"coordinates":[-122.253539,37.757334],"type":"Point"}
}