{
  "type": "Feature",
  "properties": {
    "iso:country":"US",
    "sg:address":"1519 Bayshore Hwy",
    "sg:city":"Burlingame",
    "sg:classifiers":[
        {
            "category":"Professional",
            "subcategory":"Advertising",
            "type":"Services"
        }
    ],
    "sg:phone":"+1 650 692 5105",
    "sg:postcode":"94010",
    "sg:province":"CA",
    "wof:name":"J Crawford & Assoc",
    "wof:placetype":"venue"
},
  "geometry": {"coordinates":[-122.367085,37.599088],"type":"Point"}
}