{
  "type": "Feature",
  "properties": {
    "addr:full":"9130 Valley View Dr Newcastle CA 95658",
    "addr:housenumber":"9130",
    "addr:postcode":"95658",
    "addr:street":"Valley View Dr",
    "iso:country":"US",
    "sg:address":"9130 Valley View Dr",
    "sg:city":"Newcastle",
    "sg:classifiers":[
        {
            "category":"Social Services",
            "subcategory":"Child Care",
            "type":"Services"
        }
    ],
    "sg:phone":"+1 916 663 4673",
    "sg:postcode":"95658",
    "sg:province":"CA",
    "wof:name":"4h After School Program",
    "wof:placetype":"venue"
},
  "geometry": {"coordinates":[-121.134152,38.87195],"type":"Point"}
}