{
  "type": "Feature",
  "properties": {
    "iso:country":"US",
    "sg:address":"4061 Lake Tahoe Blvd",
    "sg:city":"South Lake Tahoe",
    "sg:classifiers":[
        {
            "category":"Travel",
            "subcategory":"Hotels & Motels",
            "type":"Entertainment"
        }
    ],
    "sg:phone":"+1 530 544 5211",
    "sg:postcode":"96150",
    "sg:province":"CA",
    "sg:tags":[
        "resort"
    ],
    "sg:website":"www.stardust-tahoe.com",
    "wof:name":"Stardust Lodge",
    "wof:placetype":"venue"
},
  "geometry": {"coordinates":[-119.94401499999999,38.956275],"type":"Point"}
}