{
  "type": "Feature",
  "properties": {
    "iso:country":"US",
    "sg:address":"4075 Avalon Blvd",
    "sg:city":"Los Angeles",
    "sg:classifiers":[
        {
            "category":"Home & Garden",
            "subcategory":"Carpets & Floor Coverings",
            "type":"Retail Goods"
        }
    ],
    "sg:phone":"+1 323 233 0542",
    "sg:postcode":"90011",
    "sg:province":"CA",
    "sg:tags":[
        "equipment",
        "carpeting"
    ],
    "wof:name":"Rose Carpet",
    "wof:placetype":"venue"
},
  "geometry": {"coordinates":[-118.264999,34.009399],"type":"Point"}
}