{
  "type": "Feature",
  "properties": {
    "addr:full":"1616 Park Ave Chico CA 95928",
    "addr:housenumber":"1616",
    "addr:postcode":"95928",
    "addr:street":"Park Ave",
    "iso:country":"US",
    "sg:address":"1616 Park Ave",
    "sg:city":"Chico",
    "sg:classifiers":[
        {
            "category":"Retail",
            "subcategory":"Auto Repair",
            "type":"Services"
        }
    ],
    "sg:phone":"+1 530 342 5381",
    "sg:postcode":"95928",
    "sg:province":"CA",
    "sg:tags":[
        "recreational",
        "trailers-repair",
        "campers-repair",
        "vehicle"
    ],
    "wof:name":"Wiecks Auto Repair Service",
    "wof:placetype":"venue"
},
  "geometry": {"coordinates":[-121.827022,39.721381],"type":"Point"}
}