{
  "type": "Feature",
  "properties": {
    "iso:country":"US",
    "sg:address":"31316 Via Colinas",
    "sg:city":"Thousand Oaks",
    "sg:classifiers":[
        {
            "category":"Manufacturing",
            "subcategory":"Electronics",
            "type":"Manufacturing & Wholesale Goods"
        },
        {
            "category":"Wholesale",
            "subcategory":"Electrical",
            "type":"Manufacturing & Wholesale Goods"
        }
    ],
    "sg:phone":"+1 818 707 9093",
    "sg:postcode":"91362",
    "sg:province":"CA",
    "sg:tags":[
        "electronic",
        "assembler",
        "component",
        "parts",
        "mfg"
    ],
    "wof:name":"Alcove Electronics",
    "wof:placetype":"venue"
},
  "geometry": {"coordinates":[-118.806305,34.156099],"type":"Point"}
}