{
  "type": "Feature",
  "properties": {
    "iso:country":"US",
    "sg:address":"731 Beacon Ave",
    "sg:city":"Los Angeles",
    "sg:classifiers":[
        {
            "category":"Social Services",
            "subcategory":"Child Care",
            "type":"Services"
        }
    ],
    "sg:phone":"+1 213 484 9530",
    "sg:postcode":"90017",
    "sg:province":"CA",
    "sg:tags":[
        "elementary",
        "kindergarten",
        "school",
        "academic"
    ],
    "wof:name":"Kedren Beacon",
    "wof:placetype":"venue"
},
  "geometry": {"coordinates":[-118.273003,34.053902],"type":"Point"}
}