{
  "type": "Feature",
  "properties": {
    "addr:full":"187 Kreuzer Ln Napa CA 94559",
    "addr:housenumber":"187",
    "addr:postcode":"94559",
    "addr:street":"Kreuzer Ln",
    "iso:country":"US",
    "sg:address":"187 Kreuzer Ln",
    "sg:city":"Napa",
    "sg:classifiers":[
        {
            "category":"Retail",
            "subcategory":"Portrait Studio",
            "type":"Services"
        }
    ],
    "sg:phone":"+1 707 253 8540",
    "sg:postcode":"94559",
    "sg:province":"CA",
    "sg:tags":[
        "photographer"
    ],
    "wof:name":"Photos By Marissa",
    "wof:placetype":"venue"
},
  "geometry": {"coordinates":[-122.23017400000001,38.282611],"type":"Point"}
}