{
  "type": "Feature",
  "properties": {
    "iso:country":"US",
    "sg:address":"509 S Westlake Avenue Ofc",
    "sg:city":"Los Angeles",
    "sg:classifiers":[
        {
            "category":"Real Estate",
            "subcategory":"Real Estate Operator",
            "type":"Services"
        }
    ],
    "sg:phone":"+1 213 483 2881",
    "sg:postcode":"90057",
    "sg:province":"CA",
    "sg:tags":[
        "apartment"
    ],
    "wof:name":"Westlake City Lights Apt",
    "wof:placetype":"venue"
},
  "geometry": {"coordinates":[-118.27315,34.059786],"type":"Point"}
}