{
  "type": "Feature",
  "properties": {
    "addr:full":"3305 Motor Ave Los Angeles CA 90034",
    "addr:housenumber":"3305",
    "addr:postcode":"90034",
    "addr:street":"Motor Ave",
    "iso:country":"US",
    "sg:address":"3305 Motor Ave",
    "sg:city":"Los Angeles",
    "sg:classifiers":[
        {
            "category":"Shopping",
            "subcategory":"Clothing, Apparel, & Fashions",
            "type":"Retail Goods"
        }
    ],
    "sg:phone":"+1 310 280 1080",
    "sg:postcode":"90034",
    "sg:province":"CA",
    "sg:tags":[
        "sewing"
    ],
    "wof:name":"Bed Head",
    "wof:placetype":"venue"
},
  "geometry": {"coordinates":[-118.40961799999999,34.027715],"type":"Point"}
}