{
  "type": "Feature",
  "properties": {
    "iso:country":"US",
    "sg:address":"24795 Alicia Pkwy",
    "sg:city":"Laguna Hills",
    "sg:classifiers":[
        {
            "category":"Retail",
            "subcategory":"Car Wash",
            "type":"Services"
        }
    ],
    "sg:phone":"+1 949 859 5851",
    "sg:postcode":"92653",
    "sg:province":"CA",
    "wof:name":"Laguna Hills Car Wash",
    "wof:placetype":"venue"
},
  "geometry": {"coordinates":[-117.691652,33.602366],"type":"Point"}
}