{
  "type": "Feature",
  "properties": {
    "addr:full":"1564 Holly Ave Rohnert Park CA 94928",
    "addr:housenumber":"1564",
    "addr:postcode":"94928",
    "addr:street":"Holly Ave",
    "iso:country":"US",
    "sg:address":"1564 Holly Ave",
    "sg:city":"Rohnert Park",
    "sg:classifiers":[
        {
            "category":"Insurance",
            "subcategory":"Insurance Agent",
            "type":"Services"
        }
    ],
    "sg:phone":"+1 707 584 4500",
    "sg:postcode":"94928",
    "sg:province":"CA",
    "wof:name":"Mutual Boiler",
    "wof:placetype":"venue"
},
  "geometry": {"coordinates":[-122.677136,38.371369],"type":"Point"}
}