{
  "type": "Feature",
  "properties": {
    "addr:full":"10170 Reseda Blvd Northridge CA 91324",
    "addr:housenumber":"10170",
    "addr:postcode":"91324",
    "addr:street":"Reseda Blvd",
    "iso:country":"US",
    "sg:address":"10170 Reseda Blvd",
    "sg:city":"Northridge",
    "sg:classifiers":[
        {
            "category":"Shopping",
            "subcategory":"Used Merchandise",
            "type":"Retail Goods"
        }
    ],
    "sg:phone":"+1 818 773 8712",
    "sg:postcode":"91324",
    "sg:province":"CA",
    "wof:name":"Goodwill Inds Suthern Californ",
    "wof:placetype":"venue"
},
  "geometry": {"coordinates":[-118.536096,34.257266],"type":"Point"}
}