{
  "type": "Feature",
  "properties": {
    "iso:country":"US",
    "sg:address":"1776 W March Ln",
    "sg:city":"Stockton",
    "sg:classifiers":[
        {
            "category":"Utilities",
            "subcategory":"Telephone",
            "type":"Services"
        }
    ],
    "sg:phone":"+1 209 926 3300",
    "sg:postcode":"95207",
    "sg:province":"CA",
    "sg:tags":[
        "company",
        "telecommunication",
        "provider"
    ],
    "sg:website":"www.pacwest.com",
    "wof:name":"Pac-West Telecomm Inc",
    "wof:placetype":"venue"
},
  "geometry": {"coordinates":[-121.327641,37.987634],"type":"Point"}
}