{
  "type": "Feature",
  "properties": {
    "addr:full":"1920 Shadow Ridge Dr Vista CA 92081",
    "addr:housenumber":"1920",
    "addr:postcode":"92081",
    "addr:street":"Shadow Ridge Dr",
    "iso:country":"US",
    "sg:address":"1920 Shadow Ridge Dr",
    "sg:city":"Vista",
    "sg:classifiers":[
        {
            "category":"Real Estate",
            "subcategory":"Real Estate Agent",
            "type":"Services"
        }
    ],
    "sg:phone":"+1 760 727 8242",
    "sg:postcode":"92081",
    "sg:province":"CA",
    "wof:name":"Shadowhill Plaza",
    "wof:placetype":"venue"
},
  "geometry": {"coordinates":[-117.262688,33.1811],"type":"Point"}
}