{
  "type": "Feature",
  "properties": {
    "iso:country":"US",
    "sg:address":"5232 Bolsa Ave",
    "sg:city":"Huntington Beach",
    "sg:classifiers":[
        {
            "category":"Building & Trades",
            "subcategory":"Equipment Rental",
            "type":"Services"
        }
    ],
    "sg:phone":"+1 714 373 9901",
    "sg:postcode":"92649",
    "sg:province":"CA",
    "sg:tags":[
        "industrial"
    ],
    "wof:name":"Mr Breeze",
    "wof:placetype":"venue"
},
  "geometry": {"coordinates":[-118.03773700000001,33.744258],"type":"Point"}
}