{
  "type": "Feature",
  "properties": {
    "addr:full":"23142 Alcalde Dr Laguna Hills CA 92653",
    "addr:housenumber":"23142",
    "addr:postcode":"92653",
    "addr:street":"Alcalde Dr",
    "iso:country":"US",
    "sg:address":"23142 Alcalde Dr",
    "sg:city":"Laguna Hills",
    "sg:classifiers":[
        {
            "category":"Professional",
            "subcategory":"Advertising",
            "type":"Services"
        }
    ],
    "sg:phone":"+1 949 859 1488",
    "sg:postcode":"92653",
    "sg:province":"CA",
    "wof:name":"Mc Vicker & Assoc",
    "wof:placetype":"venue"
},
  "geometry": {"coordinates":[-117.724885,33.62289],"type":"Point"}
}