{
  "type": "Feature",
  "properties": {
    "iso:country":"US",
    "sg:address":"22910 Twain Harte Dr",
    "sg:city":"Twain Harte",
    "sg:classifiers":[
        {
            "category":"Insurance",
            "subcategory":"Title Insurance",
            "type":"Services"
        }
    ],
    "sg:phone":"+1 209 586 3206",
    "sg:postcode":"95383",
    "sg:province":"CA",
    "wof:name":"First American Title Ins Co",
    "wof:placetype":"venue"
},
  "geometry": {"coordinates":[-120.228042,38.038406],"type":"Point"}
}