{
  "type": "Feature",
  "properties": {
    "addr:full":"931 Washington Blvd Roseville CA 95678",
    "addr:housenumber":"931",
    "addr:postcode":"95678",
    "addr:street":"Washington Blvd",
    "iso:country":"US",
    "sg:address":"931 Washington Blvd",
    "sg:city":"Roseville",
    "sg:classifiers":[
        {
            "category":"Recreation",
            "type":"Entertainment"
        }
    ],
    "sg:phone":"+1 916 782 9093",
    "sg:postcode":"95678",
    "sg:province":"CA",
    "sg:tags":[
        "martial",
        "arts",
        "instruction"
    ],
    "wof:name":"Lisa Vierra Martial Arts Trng",
    "wof:placetype":"venue"
},
  "geometry": {"coordinates":[-121.293271,38.760658],"type":"Point"}
}