{
  "type": "Feature",
  "properties": {
    "iso:country":"US",
    "sg:address":"935 Spiva Ave",
    "sg:city":"Yuba City",
    "sg:classifiers":[
        {
            "category":"Freight",
            "type":"Transportation"
        }
    ],
    "sg:phone":"+1 530 673 1986",
    "sg:postcode":"95991",
    "sg:province":"CA",
    "sg:tags":[
        "mover"
    ],
    "wof:name":"T-Bow Moving & Storage",
    "wof:placetype":"venue"
},
  "geometry": {"coordinates":[-121.629985,39.135442],"type":"Point"}
}