{
  "type": "Feature",
  "properties": {
    "iso:country":"US",
    "sg:address":"458 S Hill St",
    "sg:city":"Los Angeles",
    "sg:classifiers":[
        {
            "category":"Fast Food",
            "type":"Food & Drink"
        },
        {
            "category":"Food & Beverages",
            "subcategory":"Bakery",
            "type":"Retail Goods"
        }
    ],
    "sg:phone":"+1 213 629 1304",
    "sg:postcode":"90013",
    "sg:province":"CA",
    "sg:tags":[
        "sandwich"
    ],
    "sg:website":"www.subway.com",
    "wof:name":"Subway",
    "wof:placetype":"venue"
},
  "geometry": {"coordinates":[-118.251611,34.048956],"type":"Point"}
}