{
  "type": "Feature",
  "properties": {
    "iso:country":"US",
    "sg:address":"3031 Alhambra Dr",
    "sg:city":"Cameron Park",
    "sg:classifiers":[
        {
            "category":"Building & Trades",
            "subcategory":"Landscaping Services",
            "type":"Services"
        }
    ],
    "sg:phone":"+1 530 677 3774",
    "sg:postcode":"95682",
    "sg:province":"CA",
    "sg:tags":[
        "landscape",
        "contractor"
    ],
    "wof:name":"Ponderosa Landscaping",
    "wof:placetype":"venue"
},
  "geometry": {"coordinates":[-120.99019800000001,38.687738],"type":"Point"}
}