{
  "type": "Feature",
  "properties": {
    "addr:full":"4270 Rosewood Dr Pleasanton CA 94588",
    "addr:housenumber":"4270",
    "addr:postcode":"94588",
    "addr:street":"Rosewood Dr",
    "iso:country":"US",
    "sg:address":"4270 Rosewood Dr",
    "sg:city":"Pleasanton",
    "sg:classifiers":[
        {
            "category":"Home & Garden",
            "subcategory":"Furniture",
            "type":"Retail Goods"
        }
    ],
    "sg:phone":"+1 925 416 0611",
    "sg:postcode":"94588",
    "sg:province":"CA",
    "wof:name":"Wood A'Faire",
    "wof:placetype":"venue"
},
  "geometry": {"coordinates":[-121.875722,37.698937],"type":"Point"}
}