{
  "type": "Feature",
  "properties": {
    "addr:full":"2614 Telegraph Ave Berkeley CA 94704",
    "addr:housenumber":"2614",
    "addr:postcode":"94704",
    "addr:street":"Telegraph Ave",
    "iso:country":"US",
    "sg:address":"2614 Telegraph Ave",
    "sg:city":"Berkeley",
    "sg:classifiers":[
        {
            "category":"Social Services",
            "subcategory":"Adult Care",
            "type":"Services"
        }
    ],
    "sg:phone":"+1 510 548 6600",
    "sg:postcode":"94704",
    "sg:province":"CA",
    "sg:tags":[
        "home",
        "residential"
    ],
    "wof:name":"Agemark Corp",
    "wof:placetype":"venue"
},
  "geometry": {"coordinates":[-122.25897000000001,37.862409],"type":"Point"}
}