{
  "type": "Feature",
  "properties": {
    "addr:full":"399 Guadalupe Ter Fremont CA 94539",
    "addr:housenumber":"399",
    "addr:postcode":"94539",
    "addr:street":"Guadalupe Ter",
    "iso:country":"US",
    "sg:address":"399 Guadalupe Ter",
    "sg:city":"Fremont",
    "sg:classifiers":[
        {
            "category":"Retail",
            "subcategory":"Repair Shop",
            "type":"Services"
        }
    ],
    "sg:phone":"+1 510 651 6467",
    "sg:postcode":"94539",
    "sg:province":"CA",
    "sg:tags":[
        "equipment",
        "electronic",
        "supply"
    ],
    "wof:name":"ALM Corp",
    "wof:placetype":"venue"
},
  "geometry": {"coordinates":[-121.918747,37.537211],"type":"Point"}
}