{
  "type": "Feature",
  "properties": {
    "iso:country":"US",
    "sg:address":"12392 Beach Blvd",
    "sg:city":"Stanton",
    "sg:classifiers":[
        {
            "category":"Autos & Motor Vehicles",
            "subcategory":"Boat Sales",
            "type":"Retail Goods"
        }
    ],
    "sg:phone":"+1 714 901 1300",
    "sg:postcode":"90680",
    "sg:province":"CA",
    "sg:tags":[
        "dealer",
        "sales"
    ],
    "wof:name":"Derrick Yacht Sales",
    "wof:placetype":"venue"
},
  "geometry": {"coordinates":[-117.99279199999999,33.782373],"type":"Point"}
}