{
  "type": "Feature",
  "properties": {
    "iso:country":"US",
    "sg:address":"149 Reed Ct",
    "sg:city":"Chula Vista",
    "sg:classifiers":[
        {
            "category":"Building & Trades",
            "subcategory":"Construction",
            "type":"Services"
        }
    ],
    "sg:phone":"+1 858 571 4755",
    "sg:postcode":"91911",
    "sg:province":"CA",
    "sg:tags":[
        "demolition",
        "contractor"
    ],
    "wof:name":"Dr Demo Demolition Svc",
    "wof:placetype":"venue"
},
  "geometry": {"coordinates":[-117.055872,32.591932],"type":"Point"}
}