{
  "type": "Feature",
  "properties": {
    "addr:full":"3397 Watt Ave Sacramento CA 95821",
    "addr:housenumber":"3397",
    "addr:postcode":"95821",
    "addr:street":"Watt Ave",
    "iso:country":"US",
    "sg:address":"3397 Watt Ave",
    "sg:city":"Sacramento",
    "sg:classifiers":[
        {
            "category":"Restaurant",
            "type":"Food & Drink"
        }
    ],
    "sg:phone":"+1 916 971 9898",
    "sg:postcode":"95821",
    "sg:province":"CA",
    "sg:tags":[
        "out"
    ],
    "wof:name":"Gordy's Taqueria",
    "wof:placetype":"venue"
},
  "geometry": {"coordinates":[-121.383016,38.627696],"type":"Point"}
}