{
  "type": "Feature",
  "properties": {
    "iso:country":"US",
    "sg:address":"6033 Bridgeview Dr",
    "sg:city":"Ventura",
    "sg:classifiers":[
        {
            "category":"Professional",
            "subcategory":"Management & Consulting",
            "type":"Services"
        }
    ],
    "sg:phone":"+1 805 642 2672",
    "sg:postcode":"93003",
    "sg:province":"CA",
    "sg:tags":[
        "consultant"
    ],
    "wof:name":"Donald M Atwater Inc",
    "wof:placetype":"venue"
},
  "geometry": {"coordinates":[-119.21502700000001,34.297031],"type":"Point"}
}