{
  "type": "Feature",
  "properties": {
    "addr:full":"349 Main St Pleasanton CA 94566",
    "addr:housenumber":"349",
    "addr:postcode":"94566",
    "addr:street":"Main St",
    "iso:country":"US",
    "sg:address":"349 Main St",
    "sg:city":"Pleasanton",
    "sg:classifiers":[
        {
            "category":"Food & Beverages",
            "subcategory":"Bakery",
            "type":"Retail Goods"
        }
    ],
    "sg:phone":"+1 925 426 1616",
    "sg:postcode":"94566",
    "sg:province":"CA",
    "sg:tags":[
        "baker"
    ],
    "sg:website":"www.tortabella.com",
    "wof:name":"Torta Bella Bake Shop",
    "wof:placetype":"venue"
},
  "geometry": {"coordinates":[-121.876667,37.65917],"type":"Point"}
}