{
  "type": "Feature",
  "properties": {
    "iso:country":"US",
    "sg:address":"2499 Cerritos Ave",
    "sg:city":"Signal Hill",
    "sg:classifiers":[
        {
            "category":"Freight",
            "type":"Transportation"
        }
    ],
    "sg:phone":"+1 562 492 9744",
    "sg:postcode":"90755",
    "sg:province":"CA",
    "sg:tags":[
        "delivery"
    ],
    "wof:name":"Mail Delivery Svc",
    "wof:placetype":"venue"
},
  "geometry": {"coordinates":[-118.1774,33.801395],"type":"Point"}
}