{
  "type": "Feature",
  "properties": {
    "addr:full":"2499 Cerritos Ave Signal Hill CA 90755",
    "addr:housenumber":"2499",
    "addr:postcode":"90755",
    "addr:street":"Cerritos Ave",
    "iso:country":"US",
    "sg:address":"2499 Cerritos Ave",
    "sg:city":"Signal Hill",
    "sg:classifiers":[
        {
            "category":"Freight",
            "type":"Transportation"
        }
    ],
    "sg:phone":"+1 562 492 9744",
    "sg:postcode":"90755",
    "sg:province":"CA",
    "sg:tags":[
        "delivery"
    ],
    "wof:name":"Mail Delivery Svc",
    "wof:placetype":"venue"
},
  "geometry": {"coordinates":[-118.17740000000001,33.801395],"type":"Point"}
}