{
  "type": "Feature",
  "properties": {
    "iso:country":"US",
    "sg:address":"9710 Garden Grove Blvd",
    "sg:city":"Garden Grove",
    "sg:classifiers":[
        {
            "category":"Shopping",
            "type":"Retail Goods"
        }
    ],
    "sg:phone":"+1 714 590 2700",
    "sg:postcode":"92844",
    "sg:province":"CA",
    "sg:tags":[
        "merchandise"
    ],
    "wof:name":"Teen Wireless",
    "wof:placetype":"venue"
},
  "geometry": {"coordinates":[-117.959082,33.773944],"type":"Point"}
}