{
  "type": "Feature",
  "properties": {
    "addr:full":"1007 7th St Ste 200A Sacramento CA 95814",
    "addr:housenumber":"1007",
    "addr:postcode":"95814",
    "addr:street":"7Th St Ste 200A",
    "iso:country":"US",
    "sg:address":"1007 7th St Ste 200A",
    "sg:city":"Sacramento",
    "sg:classifiers":[
        {
            "category":"Manufacturing",
            "subcategory":"Buildings",
            "type":"Manufacturing & Wholesale Goods"
        },
        {
            "category":"Building & Trades",
            "subcategory":"Construction",
            "type":"Services"
        }
    ],
    "sg:phone":"+1 916 489 6843",
    "sg:postcode":"95814",
    "sg:province":"CA",
    "sg:tags":[
        "home",
        "builder",
        "industrial",
        "contractors-commercial",
        "contractor"
    ],
    "wof:name":"Rod Read & Sons, Inc.",
    "wof:placetype":"venue"
},
  "geometry": {"coordinates":[-121.497483,38.5813],"type":"Point"}
}