{
  "type": "Feature",
  "properties": {
    "addr:full":"922 Central Ave Upland CA 91786",
    "addr:housenumber":"922",
    "addr:postcode":"91786",
    "addr:street":"Central Ave",
    "iso:country":"US",
    "sg:address":"922 Central Ave",
    "sg:city":"Upland",
    "sg:classifiers":[
        {
            "category":"Restaurant",
            "type":"Food & Drink"
        }
    ],
    "sg:phone":"+1 909 946 6548",
    "sg:postcode":"91786",
    "sg:province":"CA",
    "wof:name":"Dezaras Italinan Restaurant",
    "wof:placetype":"venue"
},
  "geometry": {"coordinates":[-117.689607,34.104575],"type":"Point"}
}