{
  "type": "Feature",
  "properties": {
    "iso:country":"US",
    "sg:address":"3908 Woodruff Ave",
    "sg:city":"Long Beach",
    "sg:classifiers":[
        {
            "category":"Education",
            "subcategory":"School",
            "type":"Public Place"
        }
    ],
    "sg:phone":"+1 562 377 3450",
    "sg:postcode":"90808",
    "sg:province":"CA",
    "sg:tags":[
        "elementary"
    ],
    "wof:name":"Montessori Academy of Long Beach",
    "wof:placetype":"venue"
},
  "geometry": {"coordinates":[-118.11599699999999,33.829399],"type":"Point"}
}