{
  "type": "Feature",
  "properties": {
    "iso:country":"US",
    "sg:address":"303 Northaven Dr",
    "sg:city":"Daly City",
    "sg:classifiers":[
        {
            "category":"Travel",
            "subcategory":"Travel Agent",
            "type":"Entertainment"
        }
    ],
    "sg:phone":"+1 650 992 6013",
    "sg:postcode":"94015",
    "sg:province":"CA",
    "sg:tags":[
        "agency"
    ],
    "wof:name":"There N Back Travel",
    "wof:placetype":"venue"
},
  "geometry": {"coordinates":[-122.484174,37.674039],"type":"Point"}
}