{
  "type": "Feature",
  "properties": {
    "iso:country":"US",
    "sg:address":"527 15th St",
    "sg:city":"Modesto",
    "sg:classifiers":[
        {
            "category":"Professional",
            "subcategory":"Accounting & Tax Preparation",
            "type":"Services"
        }
    ],
    "sg:phone":"+1 209 571 1024",
    "sg:postcode":"95354",
    "sg:province":"CA",
    "sg:tags":[
        "accountant"
    ],
    "wof:name":"Dufort & Co",
    "wof:placetype":"venue"
},
  "geometry": {"coordinates":[-120.990761,37.639924],"type":"Point"}
}