{
  "type": "Feature",
  "properties": {
    "iso:country":"US",
    "sg:address":"1310 N Crystal Ave",
    "sg:city":"Fresno",
    "sg:classifiers":[
        {
            "category":"Wholesale",
            "subcategory":"Sporting Goods",
            "type":"Manufacturing & Wholesale Goods"
        }
    ],
    "sg:phone":"+1 559 264 3614",
    "sg:postcode":"93728",
    "sg:province":"CA",
    "sg:tags":[
        "course",
        "golf",
        "equipment"
    ],
    "wof:name":"Reed Equipment Co",
    "wof:placetype":"venue"
},
  "geometry": {"coordinates":[-119.832215,36.759354],"type":"Point"}
}