{
  "type": "Feature",
  "properties": {
    "iso:country":"US",
    "sg:address":"8536 Shawnee Ave",
    "sg:city":"Fair Oaks",
    "sg:classifiers":[
        {
            "category":"Professional",
            "subcategory":"Management & Consulting",
            "type":"Services"
        }
    ],
    "sg:phone":"+1 916 966 8666",
    "sg:postcode":"95628",
    "sg:province":"CA",
    "sg:tags":[
        "consultant",
        "business"
    ],
    "wof:name":"Bos Co",
    "wof:placetype":"venue"
},
  "geometry": {"coordinates":[-121.24130599999999,38.649005],"type":"Point"}
}