{
  "type": "Feature",
  "properties": {
    "iso:country":"US",
    "sg:address":"2481 Oak Creek Rd",
    "sg:city":"Mojave",
    "sg:classifiers":[
        {
            "category":"Wholesale",
            "subcategory":"Petroleum",
            "type":"Manufacturing & Wholesale Goods"
        }
    ],
    "sg:phone":"+1 760 446 4774",
    "sg:postcode":"93501",
    "sg:province":"CA",
    "sg:tags":[
        "bulk",
        "oil",
        "gasoline"
    ],
    "wof:name":"Ramos/Strong Inc-Chevron",
    "wof:placetype":"venue"
},
  "geometry": {"coordinates":[-118.182082,35.05667],"type":"Point"}
}