{
  "type": "Feature",
  "properties": {
    "iso:country":"US",
    "sg:address":"20111 Hillside Dr",
    "sg:city":"Orange",
    "sg:classifiers":[
        {
            "category":"Banks & Credit Unions",
            "subcategory":"Financial Services",
            "type":"Services"
        }
    ],
    "sg:phone":"+1 714 633 7412",
    "sg:postcode":"92869",
    "sg:province":"CA",
    "sg:tags":[
        "investor",
        "real estate"
    ],
    "wof:name":"Tiy Inc",
    "wof:placetype":"venue"
},
  "geometry": {"coordinates":[-117.779849,33.806844],"type":"Point"}
}