{
  "type": "Feature",
  "properties": {
    "addr:full":"10436 N Blaney Ave Cupertino CA 95014",
    "addr:housenumber":"10436",
    "addr:postcode":"95014",
    "addr:street":"N Blaney Ave",
    "iso:country":"US",
    "sg:address":"10436 N Blaney Ave",
    "sg:city":"Cupertino",
    "sg:classifiers":[
        {
            "category":"Utilities",
            "subcategory":"Telephone",
            "type":"Services"
        }
    ],
    "sg:phone":"+1 408 446 9922",
    "sg:postcode":"95014",
    "sg:province":"CA",
    "sg:tags":[
        "communications"
    ],
    "wof:name":"Nortel Networks Inc",
    "wof:placetype":"venue"
},
  "geometry": {"coordinates":[-122.02310900000001,37.329194],"type":"Point"}
}