{
  "type": "Feature",
  "properties": {
    "iso:country":"US",
    "sg:address":"430 Broadway",
    "sg:city":"San Francisco",
    "sg:classifiers":[
        {
            "category":"Restaurant",
            "type":"Food & Drink"
        }
    ],
    "sg:phone":"+1 415 362 0641",
    "sg:postcode":"94133",
    "sg:province":"CA",
    "wof:name":"Helmand Restaurant",
    "wof:placetype":"venue"
},
  "geometry": {"coordinates":[-122.405404,37.798104],"type":"Point"}
}