{
  "type": "Feature",
  "properties": {
    "addr:full":"7060 N Winton Way Winton CA 95388",
    "addr:housenumber":"7060",
    "addr:postcode":"95388",
    "addr:street":"N Winton Way",
    "iso:country":"US",
    "sg:address":"7060 N Winton Way",
    "sg:city":"Winton",
    "sg:classifiers":[
        {
            "category":"Retail",
            "subcategory":"Self-service Laundry",
            "type":"Services"
        }
    ],
    "sg:phone":"+1 209 357 3151",
    "sg:postcode":"95388",
    "sg:province":"CA",
    "wof:name":"Winton Wash & Dry",
    "wof:placetype":"venue"
},
  "geometry": {"coordinates":[-120.613362,37.389884],"type":"Point"}
}