{
  "type": "Feature",
  "properties": {
    "iso:country":"US",
    "sg:address":"2355 Tapo St",
    "sg:city":"Simi Valley",
    "sg:classifiers":[
        {
            "category":"Food & Beverages",
            "subcategory":"Meat & Fish",
            "type":"Retail Goods"
        }
    ],
    "sg:phone":"+1 805 520 9564",
    "sg:postcode":"93063",
    "sg:province":"CA",
    "wof:name":"Tapatia Market",
    "wof:placetype":"venue"
},
  "geometry": {"coordinates":[-118.709016,34.277101],"type":"Point"}
}