{
  "type": "Feature",
  "properties": {
    "iso:country":"US",
    "sg:address":"1647 Alvarado St",
    "sg:city":"San Leandro",
    "sg:classifiers":[
        {
            "category":"Shopping",
            "subcategory":"Jewelry",
            "type":"Retail Goods"
        }
    ],
    "sg:phone":"+1 510 614 1919",
    "sg:postcode":"94577",
    "sg:province":"CA",
    "wof:name":"Gent Jay Co",
    "wof:placetype":"venue"
},
  "geometry": {"coordinates":[-122.16100299999999,37.718899],"type":"Point"}
}