{
  "type": "Feature",
  "properties": {
    "addr:full":"1 Buchanan St Albany CA 94706",
    "addr:housenumber":"1",
    "addr:postcode":"94706",
    "addr:street":"Buchanan St",
    "iso:country":"US",
    "sg:address":"1 Buchanan St",
    "sg:city":"Albany",
    "sg:classifiers":[
        {
            "category":"Recreation",
            "subcategory":"Dog Park",
            "type":"Entertainment"
        }
    ],
    "sg:postcode":"94706",
    "sg:province":"CA",
    "sg:website":"www.albanybulb.com",
    "wof:name":"Albany Bulb",
    "wof:placetype":"venue"
},
  "geometry": {"coordinates":[-122.31532199999999,37.889454],"type":"Point"}
}