{
  "type": "Feature",
  "properties": {
    "iso:country":"US",
    "sg:address":"Pereira Dr West of E Peltason Dr, Bldg 234",
    "sg:city":"Irvine",
    "sg:classifiers":[
        {
            "category":"Education",
            "subcategory":"Special Training",
            "type":"Public Place"
        }
    ],
    "sg:phone":"+1 949 824 5414",
    "sg:postcode":"92697",
    "sg:province":"CA",
    "sg:tags":[
        "adult"
    ],
    "sg:website":"unex.uci.edu",
    "wof:name":"UC Irvine Extension",
    "wof:placetype":"venue"
},
  "geometry": {"coordinates":[-117.839432,33.647823],"type":"Point"}
}