{
  "type": "Feature",
  "properties": {
    "addr:full":"976 S Boyle Avenue Los Angeles CA 90023",
    "addr:housenumber":"976",
    "addr:postcode":"90023",
    "addr:street":"S Boyle Avenue",
    "iso:country":"US",
    "sg:address":"976 S Boyle Avenue",
    "sg:city":"Los Angeles",
    "sg:classifiers":[
        {
            "category":"Autos & Motor Vehicles",
            "subcategory":"Auto Supplies",
            "type":"Retail Goods"
        }
    ],
    "sg:phone":"+1 323 267 0643",
    "sg:postcode":"90023",
    "sg:province":"CA",
    "sg:tags":[
        "tire"
    ],
    "wof:name":"Llantera Soto",
    "wof:placetype":"venue"
},
  "geometry": {"coordinates":[-118.219582,34.033792],"type":"Point"}
}