{
  "type": "Feature",
  "properties": {
    "iso:country":"US",
    "sg:address":"3873 Piedmont Ave Ste 6",
    "sg:city":"Oakland",
    "sg:classifiers":[
        {
            "category":"Building & Trades",
            "subcategory":"Construction",
            "type":"Services"
        }
    ],
    "sg:phone":"+1 510 655 9616",
    "sg:postcode":"94611",
    "sg:province":"CA",
    "sg:tags":[
        "painter"
    ],
    "wof:name":"Peterson Painting",
    "wof:placetype":"venue"
},
  "geometry": {"coordinates":[-122.25599699999999,37.823898],"type":"Point"}
}