{
  "type": "Feature",
  "properties": {
    "addr:full":"400 S Baldwin Ave Arcadia CA 91007",
    "addr:housenumber":"400",
    "addr:postcode":"91007",
    "addr:street":"S Baldwin Ave",
    "iso:country":"US",
    "sg:address":"400 S Baldwin Ave",
    "sg:city":"Arcadia",
    "sg:classifiers":[
        {
            "category":"Professional",
            "subcategory":"Lawyer & Legal Services",
            "type":"Services"
        }
    ],
    "sg:phone":"+1 626 447 3047",
    "sg:postcode":"91007",
    "sg:province":"CA",
    "wof:name":"Sun Scrub",
    "wof:placetype":"venue"
},
  "geometry": {"coordinates":[-118.39592,34.135981],"type":"Point"}
}