{
  "type": "Feature",
  "properties": {
    "addr:full":"12433 Monterey Hwy San Martin CA 95046",
    "addr:housenumber":"12433",
    "addr:postcode":"95046",
    "addr:street":"Monterey Hwy",
    "iso:country":"US",
    "sg:address":"12433 Monterey Hwy",
    "sg:city":"San Martin",
    "sg:classifiers":[
        {
            "category":"Government",
            "subcategory":"Court House",
            "type":"Public Place"
        }
    ],
    "sg:phone":"+1 408 686 3600",
    "sg:postcode":"95046",
    "sg:province":"CA",
    "sg:tags":[
        "legal"
    ],
    "wof:name":"Santa Clara  County of",
    "wof:placetype":"venue"
},
  "geometry": {"coordinates":[-121.61481000000001,37.09259],"type":"Point"}
}