{
  "type": "Feature",
  "properties": {
    "iso:country":"US",
    "sg:address":"75 Big Trees Rd",
    "sg:city":"Murphys",
    "sg:classifiers":[
        {
            "category":"Bars & Pubs",
            "type":"Food & Drink"
        }
    ],
    "sg:phone":"+1 209 728 3661",
    "sg:postcode":"95247",
    "sg:province":"CA",
    "sg:tags":[
        "lounge",
        "cocktail"
    ],
    "wof:name":"Nugget Bar",
    "wof:placetype":"venue"
},
  "geometry": {"coordinates":[-120.458167,38.13829],"type":"Point"}
}