{
  "type": "Feature",
  "properties": {
    "addr:full":"11717 Eastside Rd Fort Jones CA 96032",
    "addr:housenumber":"11717",
    "addr:postcode":"96032",
    "addr:street":"Eastside Rd",
    "iso:country":"US",
    "sg:address":"11717 Eastside Rd",
    "sg:city":"Fort Jones",
    "sg:classifiers":[
        {
            "category":"Building & Trades",
            "subcategory":"Plumbing",
            "type":"Services"
        }
    ],
    "sg:phone":"+1 530 468 2457",
    "sg:postcode":"96032",
    "sg:province":"CA",
    "sg:tags":[
        "septic"
    ],
    "wof:name":"Duane's Drain Cleaning",
    "wof:placetype":"venue"
},
  "geometry": {"coordinates":[-122.8429,41.596149],"type":"Point"}
}