{
  "type": "Feature",
  "properties": {
    "addr:full":"511 Highland Ave National City CA 91950",
    "addr:housenumber":"511",
    "addr:postcode":"91950",
    "addr:street":"Highland Ave",
    "iso:country":"US",
    "sg:address":"511 Highland Ave",
    "sg:city":"National City",
    "sg:classifiers":[
        {
            "category":"Real Estate",
            "subcategory":"Real Estate Agent",
            "type":"Services"
        }
    ],
    "sg:phone":"+1 619 474 4609",
    "sg:postcode":"91950",
    "sg:province":"CA",
    "wof:name":"Highland Realty & Loans",
    "wof:placetype":"venue"
},
  "geometry": {"coordinates":[-117.099351,32.679979],"type":"Point"}
}