{
  "type": "Feature",
  "properties": {
    "iso:country":"US",
    "sg:address":"8050 Elk Trl",
    "sg:city":"Yucca Valley",
    "sg:classifiers":[
        {
            "category":"Shopping",
            "subcategory":"Computers & Home Electronics",
            "type":"Retail Goods"
        }
    ],
    "sg:phone":"+1 760 369 9533",
    "sg:postcode":"92284",
    "sg:province":"CA",
    "wof:name":"Satellite Systems By Bob",
    "wof:placetype":"venue"
},
  "geometry": {"coordinates":[-116.44692499999999,34.105193],"type":"Point"}
}