{
  "type": "Feature",
  "properties": {
    "addr:full":"971 Chung King Rd Los Angeles CA 90012",
    "addr:housenumber":"971",
    "addr:postcode":"90012",
    "addr:street":"Chung King Rd",
    "iso:country":"US",
    "sg:address":"971 Chung King Rd",
    "sg:city":"Los Angeles",
    "sg:classifiers":[
        {
            "category":"Organizations",
            "subcategory":"Professional Association",
            "type":"Services"
        }
    ],
    "sg:phone":"+1 213 617 8618",
    "sg:postcode":"90012",
    "sg:province":"CA",
    "wof:name":"BNH Senior Assn",
    "wof:placetype":"venue"
},
  "geometry": {"coordinates":[-118.238156,34.06673],"type":"Point"}
}