{
  "type": "Feature",
  "properties": {
    "iso:country":"US",
    "sg:address":"2000 Norris Rd",
    "sg:city":"Bakersfield",
    "sg:classifiers":[
        {
            "category":"Shopping",
            "subcategory":"Books",
            "type":"Retail Goods"
        }
    ],
    "sg:phone":"+1 661 393 6252",
    "sg:postcode":"93308",
    "sg:province":"CA",
    "sg:tags":[
        "dealer"
    ],
    "wof:name":"Books By Sandy",
    "wof:placetype":"venue"
},
  "geometry": {"coordinates":[-119.057964,35.420206],"type":"Point"}
}