{
  "type": "Feature",
  "properties": {
    "iso:country":"US",
    "sg:address":"25146 Tower Ave",
    "sg:city":"Barstow",
    "sg:classifiers":[
        {
            "category":"Retail",
            "subcategory":"Laundry & Dry Cleaning",
            "type":"Services"
        }
    ],
    "sg:phone":"+1 760 252 3006",
    "sg:postcode":"92311",
    "sg:province":"CA",
    "sg:tags":[
        "cleaners",
        "rug",
        "carpet"
    ],
    "wof:name":"Advanced Carpet Care",
    "wof:placetype":"venue"
},
  "geometry": {"coordinates":[-117.112756,34.871742],"type":"Point"}
}