{
  "type": "Feature",
  "properties": {
    "iso:country":"US",
    "sg:address":"159 E F St",
    "sg:city":"Benicia",
    "sg:classifiers":[
        {
            "category":"Retail",
            "subcategory":"Animal Services",
            "type":"Services"
        }
    ],
    "sg:phone":"+1 707 745 3420",
    "sg:postcode":"94510",
    "sg:province":"CA",
    "sg:tags":[
        "pet"
    ],
    "wof:name":"I Care Pet & Home Sitting",
    "wof:placetype":"venue"
},
  "geometry": {"coordinates":[-122.158084,38.048648],"type":"Point"}
}