{
  "type": "Feature",
  "properties": {
    "addr:full":"2332 Chalcedony St San Diego CA 92109",
    "addr:housenumber":"2332",
    "addr:postcode":"92109",
    "addr:street":"Chalcedony St",
    "iso:country":"US",
    "sg:address":"2332 Chalcedony St",
    "sg:city":"San Diego",
    "sg:classifiers":[
        {
            "category":"Professional",
            "type":"Services"
        }
    ],
    "sg:phone":"+1 619 274 6633",
    "sg:postcode":"92109",
    "sg:province":"CA",
    "wof:name":"N Beach Bay Tel",
    "wof:placetype":"venue"
},
  "geometry": {"coordinates":[-117.22831600000001,32.807596],"type":"Point"}
}