{
  "type": "Feature",
  "properties": {
    "addr:full":"5855 Century Boulevard South Gate CA 90280",
    "addr:housenumber":"5855",
    "addr:postcode":"90280",
    "addr:street":"Century Boulevard;Gate",
    "iso:country":"US",
    "sg:address":"5855 Century Boulevard",
    "sg:city":"South Gate",
    "sg:classifiers":[
        {
            "category":"Retail",
            "subcategory":"Auto Rental",
            "type":"Services"
        }
    ],
    "sg:phone":"+1 310 645 7001",
    "sg:postcode":"90280",
    "sg:province":"CA",
    "sg:tags":[
        "car"
    ],
    "wof:name":"Hertz Rent A Car",
    "wof:placetype":"venue"
},
  "geometry": {"coordinates":[-118.202071,33.943336],"type":"Point"}
}