{
  "type": "Feature",
  "properties": {
    "addr:full":"16249 Paramount Blvd Paramount CA 90723",
    "addr:housenumber":"16249",
    "addr:postcode":"90723",
    "addr:street":"Paramount Blvd",
    "iso:country":"US",
    "sg:address":"16249 Paramount Blvd",
    "sg:city":"Paramount",
    "sg:classifiers":[
        {
            "category":"Retail",
            "subcategory":"Laundry & Dry Cleaning",
            "type":"Services"
        }
    ],
    "sg:phone":"+1 562 633 2332",
    "sg:postcode":"90723",
    "sg:province":"CA",
    "sg:tags":[
        "garment",
        "agent"
    ],
    "wof:name":"City Cleaners",
    "wof:placetype":"venue"
},
  "geometry": {"coordinates":[-118.16006299999999,33.886849],"type":"Point"}
}