{
  "type": "Feature",
  "properties": {
    "addr:full":"11082 Coloma Rd Rancho Cordova CA 95670",
    "addr:housenumber":"11082",
    "addr:postcode":"95670",
    "addr:street":"Coloma Rd",
    "iso:country":"US",
    "sg:address":"11082 Coloma Rd",
    "sg:city":"Rancho Cordova",
    "sg:classifiers":[
        {
            "category":"Professional",
            "type":"Services"
        },
        {
            "category":"Shopping",
            "subcategory":"Bridal",
            "type":"Retail Goods"
        }
    ],
    "sg:phone":"+1 916 853 1078",
    "sg:postcode":"95670",
    "sg:province":"CA",
    "sg:website":"alterationsbyp.thenetmark.com",
    "wof:name":"Alteration by Patina",
    "wof:placetype":"venue"
},
  "geometry": {"coordinates":[-121.272946,38.616935],"type":"Point"}
}