{
  "type": "Feature",
  "properties": {
    "addr:full":"5993 Shaker Dr Riverside CA 92506",
    "addr:housenumber":"5993",
    "addr:postcode":"92506",
    "addr:street":"Shaker Dr",
    "iso:country":"US",
    "sg:address":"5993 Shaker Dr",
    "sg:city":"Riverside",
    "sg:classifiers":[
        {
            "category":"Professional",
            "subcategory":"Management & Consulting",
            "type":"Services"
        }
    ],
    "sg:phone":"+1 951 683 0934",
    "sg:postcode":"92506",
    "sg:province":"CA",
    "sg:tags":[
        "consultant"
    ],
    "wof:name":"Human Resource Consulting",
    "wof:placetype":"venue"
},
  "geometry": {"coordinates":[-117.344639,33.943266],"type":"Point"}
}