{
  "type": "Feature",
  "properties": {
    "addr:full":"6150 Lusk Blvd. Suite B202 San Diego CA 92121",
    "addr:housenumber":"6150",
    "addr:postcode":"92121",
    "addr:street":"Lusk Blvd. Suite B202",
    "iso:country":"US",
    "sg:address":"6150 Lusk Blvd. Suite B202",
    "sg:city":"San Diego",
    "sg:classifiers":[
        {
            "category":"Professional",
            "subcategory":"Computer Services",
            "type":"Services"
        }
    ],
    "sg:phone":"+1 858 848 5128",
    "sg:postcode":"92121",
    "sg:province":"CA",
    "sg:tags":[
        "self-operating-networks",
        "self-operated-networking",
        "son",
        "small-cell-networks"
    ],
    "sg:website":"http://www.airhopcomm.com",
    "wof:name":"AirHop Communications",
    "wof:placetype":"venue"
},
  "geometry": {"coordinates":[-117.19582,32.89875],"type":"Point"}
}