{
  "type": "Feature",
  "properties": {
    "iso:country":"US",
    "sg:address":"519 Telegraph Canyon Rd",
    "sg:city":"Chula Vista",
    "sg:classifiers":[
        {
            "category":"Personal",
            "subcategory":"Nail Salon",
            "type":"Services"
        }
    ],
    "sg:phone":"+1 619 482 4447",
    "sg:postcode":"91910",
    "sg:province":"CA",
    "wof:name":"Matty's Salon",
    "wof:placetype":"venue"
},
  "geometry": {"coordinates":[-117.119838,32.628721],"type":"Point"}
}