{
  "type": "Feature",
  "properties": {
    "addr:full":"16707 San Luis Way Morgan Hill CA 95037",
    "addr:housenumber":"16707",
    "addr:postcode":"95037",
    "addr:street":"San Luis Way",
    "iso:country":"US",
    "sg:address":"16707 San Luis Way",
    "sg:city":"Morgan Hill",
    "sg:classifiers":[
        {
            "category":"Building & Trades",
            "subcategory":"Construction",
            "type":"Services"
        }
    ],
    "sg:phone":"+1 408 778 6771",
    "sg:postcode":"95037",
    "sg:province":"CA",
    "sg:tags":[
        "painter"
    ],
    "wof:name":"David Duran Painting",
    "wof:placetype":"venue"
},
  "geometry": {"coordinates":[-121.64009,37.125131],"type":"Point"}
}