{
  "type": "Feature",
  "properties": {
    "addr:full":"1663 12th Ave San Francisco CA 94122",
    "addr:housenumber":"1663",
    "addr:postcode":"94122",
    "addr:street":"12Th Ave",
    "iso:country":"US",
    "sg:address":"1663 12th Ave",
    "sg:city":"San Francisco",
    "sg:classifiers":[
        {
            "category":"Building & Trades",
            "subcategory":"Plumbing",
            "type":"Services"
        }
    ],
    "sg:phone":"+1 415 664 9282",
    "sg:postcode":"94122",
    "sg:province":"CA",
    "sg:tags":[
        "contractor"
    ],
    "wof:name":"Sberlo Plumbing",
    "wof:placetype":"venue"
},
  "geometry": {"coordinates":[-122.46914200000001,37.757613],"type":"Point"}
}