{
  "type": "Feature",
  "properties": {
    "addr:full":"815 N La Brea Avenue Inglewood CA 90302",
    "addr:housenumber":"815",
    "addr:postcode":"90302",
    "addr:street":"N La Brea Avenue",
    "iso:country":"US",
    "sg:address":"815 N La Brea Avenue",
    "sg:city":"Inglewood",
    "sg:classifiers":[
        {
            "category":"Professional",
            "subcategory":"Lawyer & Legal Services",
            "type":"Services"
        }
    ],
    "sg:phone":"+1 323 753 5383",
    "sg:postcode":"90302",
    "sg:province":"CA",
    "sg:tags":[
        "notary"
    ],
    "sg:website":"bailbonds4jail.com",
    "wof:name":"Aaron's Bail Bonds & Notary Public",
    "wof:placetype":"venue"
},
  "geometry": {"coordinates":[-118.357744,33.973329],"type":"Point"}
}