{
  "type": "Feature",
  "properties": {
    "iso:country":"US",
    "sg:address":"2948 Yorba Linda Blvd",
    "sg:city":"Fullerton",
    "sg:classifiers":[
        {
            "category":"Retail",
            "subcategory":"Laundry & Dry Cleaning",
            "type":"Services"
        }
    ],
    "sg:phone":"+1 714 993 0370",
    "sg:postcode":"92886",
    "sg:province":"CA",
    "sg:tags":[
        "cleaners"
    ],
    "wof:name":"Albert's Cleaners",
    "wof:placetype":"venue"
},
  "geometry": {"coordinates":[-117.875451,33.889075],"type":"Point"}
}