{
  "type": "Feature",
  "properties": {
    "iso:country":"US",
    "sg:address":"716 Jackson St",
    "sg:city":"San Francisco",
    "sg:classifiers":[
        {
            "category":"Utilities",
            "subcategory":"Telephone",
            "type":"Services"
        }
    ],
    "sg:phone":"+1 415 788 1688",
    "sg:postcode":"94133",
    "sg:province":"CA",
    "sg:tags":[
        "telecommunication"
    ],
    "wof:name":"Infinitel",
    "wof:placetype":"venue"
},
  "geometry": {"coordinates":[-122.406901,37.796076],"type":"Point"}
}