{
  "type": "Feature",
  "properties": {
    "iso:country":"US",
    "sg:address":"600 Yosemite Blvd",
    "sg:city":"Modesto",
    "sg:classifiers":[
        {
            "category":"Winery",
            "type":"Food & Drink"
        }
    ],
    "sg:phone":"+1 209 556 9274",
    "sg:postcode":"95326",
    "sg:province":"CA",
    "wof:name":"Gallo E & J Winery",
    "wof:placetype":"venue"
},
  "geometry": {"coordinates":[-120.98227900000001,37.634545],"type":"Point"}
}