{
  "type": "Feature",
  "properties": {
    "addr:full":"19719 Yorba Linda Blvd Yorba Linda CA 92886",
    "addr:housenumber":"19719",
    "addr:postcode":"92886",
    "addr:street":"Yorba Linda Blvd",
    "iso:country":"US",
    "sg:address":"19719 Yorba Linda Blvd",
    "sg:city":"Yorba Linda",
    "sg:classifiers":[
        {
            "category":"Manufacturing",
            "subcategory":"Food",
            "type":"Manufacturing & Wholesale Goods"
        },
        {
            "category":"Food & Beverages",
            "subcategory":"Bakery",
            "type":"Retail Goods"
        }
    ],
    "sg:phone":"+1 714 693 3645",
    "sg:postcode":"92886",
    "sg:province":"CA",
    "sg:tags":[
        "product",
        "doughnut",
        "mfg"
    ],
    "wof:name":"Al's Donuts",
    "wof:placetype":"venue"
},
  "geometry": {"coordinates":[-117.78825399999999,33.889607],"type":"Point"}
}