{
  "type": "Feature",
  "properties": {
    "iso:country":"US",
    "sg:address":"636 Blossom Hill Rd",
    "sg:city":"Los Gatos",
    "sg:classifiers":[
        {
            "category":"Shopping",
            "subcategory":"Department Store",
            "type":"Retail Goods"
        }
    ],
    "sg:phone":"+1 408 358 3977",
    "sg:postcode":"95032",
    "sg:province":"CA",
    "sg:tags":[
        "shop"
    ],
    "sg:website":"www.pier1.com",
    "wof:name":"Pier 1 Imports",
    "wof:placetype":"venue"
},
  "geometry": {"coordinates":[-121.96399700000001,37.235699],"type":"Point"}
}