{
  "type": "Feature",
  "properties": {
    "iso:country":"US",
    "sg:address":"81730 US Hwy 111",
    "sg:city":"Indio",
    "sg:classifiers":[
        {
            "category":"Education",
            "subcategory":"Vocational School",
            "type":"Public Place"
        }
    ],
    "sg:phone":"+1 760 775 1623",
    "sg:postcode":"92201",
    "sg:province":"CA",
    "wof:name":"Universal Technical Institute",
    "wof:placetype":"venue"
},
  "geometry": {"coordinates":[-116.242287,33.707758],"type":"Point"}
}