{
  "type": "Feature",
  "properties": {
    "addr:full":"6313 University Ave San Diego CA 92115",
    "addr:housenumber":"6313",
    "addr:postcode":"92115",
    "addr:street":"University Ave",
    "iso:country":"US",
    "sg:address":"6313 University Ave",
    "sg:city":"San Diego",
    "sg:classifiers":[
        {
            "category":"Wholesale",
            "subcategory":"Groceries",
            "type":"Manufacturing & Wholesale Goods"
        }
    ],
    "sg:phone":"+1 619 286 2446",
    "sg:postcode":"92115",
    "sg:province":"CA",
    "sg:tags":[
        "general"
    ],
    "wof:name":"Freeland Foods",
    "wof:placetype":"venue"
},
  "geometry": {"coordinates":[-117.05846699999999,32.754544],"type":"Point"}
}