{
  "type": "Feature",
  "properties": {
    "addr:full":"500 S Center St Turlock CA 95380",
    "addr:housenumber":"500",
    "addr:postcode":"95380",
    "addr:street":"S Center St",
    "iso:country":"US",
    "sg:address":"500 S Center St",
    "sg:city":"Turlock",
    "sg:classifiers":[
        {
            "category":"Arena",
            "subcategory":"Sports Club",
            "type":"Entertainment"
        }
    ],
    "sg:phone":"+1 209 634 5181",
    "sg:postcode":"95380",
    "sg:province":"CA",
    "sg:tags":[
        "soccer"
    ],
    "wof:name":"Turlock Indoor Soccer",
    "wof:placetype":"venue"
},
  "geometry": {"coordinates":[-120.838646,37.489579],"type":"Point"}
}