{
  "type": "Feature",
  "properties": {
    "addr:full":"98 Battery St San Francisco CA 94111",
    "addr:housenumber":"98",
    "addr:postcode":"94111",
    "addr:street":"Battery St",
    "iso:country":"US",
    "sg:address":"98 Battery St",
    "sg:city":"San Francisco",
    "sg:classifiers":[
        {
            "category":"Manufacturing",
            "subcategory":"Printing",
            "type":"Manufacturing & Wholesale Goods"
        }
    ],
    "sg:phone":"+1 415 821 2700",
    "sg:postcode":"94111",
    "sg:province":"CA",
    "sg:tags":[
        "equipment",
        "loose",
        "leaf"
    ],
    "wof:name":"Corporate Express Bindery Sys",
    "wof:placetype":"venue"
},
  "geometry": {"coordinates":[-122.39957200000001,37.791326],"type":"Point"}
}