{
  "type": "Feature",
  "properties": {
    "iso:country":"US",
    "sg:address":"5020 Imperial Ave",
    "sg:city":"San Diego",
    "sg:classifiers":[
        {
            "category":"Retail",
            "subcategory":"Auto Repair",
            "type":"Services"
        }
    ],
    "sg:phone":"+1 619 263 1600",
    "sg:postcode":"92113",
    "sg:province":"CA",
    "sg:tags":[
        "repairing",
        "automobile"
    ],
    "wof:name":"Imperial Auto Svc Ctr",
    "wof:placetype":"venue"
},
  "geometry": {"coordinates":[-117.085141,32.704551],"type":"Point"}
}