{
  "type": "Feature",
  "properties": {
    "addr:full":"1361 Laurel St San Carlos CA 94070",
    "addr:housenumber":"1361",
    "addr:postcode":"94070",
    "addr:street":"Laurel St",
    "iso:country":"US",
    "sg:address":"1361 Laurel St",
    "sg:city":"San Carlos",
    "sg:classifiers":[
        {
            "category":"Taxi",
            "type":"Transportation"
        }
    ],
    "sg:phone":"+1 650 591 5900",
    "sg:postcode":"94070",
    "sg:province":"CA",
    "sg:tags":[
        "taxicab"
    ],
    "wof:name":"Yellow Cab Co",
    "wof:placetype":"venue"
},
  "geometry": {"coordinates":[-122.250405,37.497685],"type":"Point"}
}