{
  "type": "Feature",
  "properties": {
    "addr:full":"1300 W 14th St Long Beach CA 90813",
    "addr:housenumber":"1300",
    "addr:postcode":"90813",
    "addr:street":"W 14Th St",
    "iso:country":"US",
    "sg:address":"1300 W 14th St",
    "sg:city":"Long Beach",
    "sg:classifiers":[
        {
            "category":"Autos & Motor Vehicles",
            "subcategory":"Boat Sales",
            "type":"Retail Goods"
        }
    ],
    "sg:phone":"+1 562 597 4439",
    "sg:postcode":"90813",
    "sg:province":"CA",
    "sg:tags":[
        "dealer",
        "sales"
    ],
    "wof:name":"Avaion Yacht & Boat Sales",
    "wof:placetype":"venue"
},
  "geometry": {"coordinates":[-118.210469,33.783766],"type":"Point"}
}