{
  "type": "Feature",
  "properties": {
    "addr:full":"17802 Irvine Blvd Tustin CA 92780",
    "addr:housenumber":"17802",
    "addr:postcode":"92780",
    "addr:street":"Irvine Blvd",
    "iso:country":"US",
    "sg:address":"17802 Irvine Blvd",
    "sg:city":"Tustin",
    "sg:classifiers":[
        {
            "category":"Building & Trades",
            "subcategory":"Electrical",
            "type":"Services"
        }
    ],
    "sg:phone":"+1 714 544 9600",
    "sg:postcode":"92780",
    "sg:province":"CA",
    "sg:tags":[
        "retail",
        "telephone",
        "install",
        "system"
    ],
    "wof:name":"McMahon Telecommunications",
    "wof:placetype":"venue"
},
  "geometry": {"coordinates":[-117.819689,33.74838],"type":"Point"}
}