{
  "type": "Feature",
  "properties": {
    "iso:country":"US",
    "sg:address":"5154 Waring Rd",
    "sg:city":"San Diego",
    "sg:classifiers":[
        {
            "category":"Sports & Exercise",
            "subcategory":"Gym",
            "type":"Entertainment"
        }
    ],
    "sg:phone":"+1 619 287 0596",
    "sg:postcode":"92120",
    "sg:province":"CA",
    "sg:tags":[
        "club",
        "health",
        "studio",
        "gymnasium"
    ],
    "wof:name":"Contours Express",
    "wof:placetype":"venue"
},
  "geometry": {"coordinates":[-117.08172999999999,32.791662],"type":"Point"}
}