{
  "type": "Feature",
  "properties": {
    "addr:full":"537 Santa Ynez San Leandro CA 94579",
    "addr:housenumber":"537",
    "addr:postcode":"94579",
    "addr:street":"Santa",
    "iso:country":"US",
    "sg:address":"537 Santa Ynez",
    "sg:city":"San Leandro",
    "sg:classifiers":[
        {
            "category":"Real Estate",
            "subcategory":"Developer",
            "type":"Services"
        }
    ],
    "sg:phone":"+1 510 352 7887",
    "sg:postcode":"94579",
    "sg:province":"CA",
    "wof:name":"Mayer Development Co",
    "wof:placetype":"venue"
},
  "geometry": {"coordinates":[-122.16194400000001,37.683265],"type":"Point"}
}