{
  "type": "Feature",
  "properties": {
    "iso:country":"US",
    "sg:address":"6780 Miramar Rd",
    "sg:city":"San Diego",
    "sg:classifiers":[
        {
            "category":"Shopping",
            "subcategory":"Florist",
            "type":"Retail Goods"
        }
    ],
    "sg:phone":"+1 858 549 9112",
    "sg:postcode":"92121",
    "sg:province":"CA",
    "wof:name":"Queen Roses",
    "wof:placetype":"venue"
},
  "geometry": {"coordinates":[-117.168544,32.878172],"type":"Point"}
}