{
  "type": "Feature",
  "properties": {
    "iso:country":"US",
    "sg:address":"6252 Moonstone Beach Dr",
    "sg:city":"Cambria",
    "sg:classifiers":[
        {
            "category":"Travel",
            "subcategory":"Hotels & Motels",
            "type":"Entertainment"
        }
    ],
    "sg:phone":"+1 800 222 9970",
    "sg:postcode":"93428",
    "sg:province":"CA",
    "sg:website":"www.cambriainns.com",
    "wof:name":"Sand Pebbles Inn",
    "wof:placetype":"venue"
},
  "geometry": {"coordinates":[-121.112999,35.5732],"type":"Point"}
}