{
  "type": "Feature",
  "properties": {
    "addr:full":"7508 Windbridge Dr Sacramento CA 95831",
    "addr:housenumber":"7508",
    "addr:postcode":"95831",
    "addr:street":"Windbridge Dr",
    "iso:country":"US",
    "sg:address":"7508 Windbridge Dr",
    "sg:city":"Sacramento",
    "sg:classifiers":[
        {
            "category":"Shopping",
            "subcategory":"Computers & Home Electronics",
            "type":"Retail Goods"
        }
    ],
    "sg:phone":"+1 916 421 6770",
    "sg:postcode":"95831",
    "sg:province":"CA",
    "sg:tags":[
        "software"
    ],
    "wof:name":"New Models",
    "wof:placetype":"venue"
},
  "geometry": {"coordinates":[-121.53257000000001,38.486643],"type":"Point"}
}