{
  "type": "Feature",
  "properties": {
    "iso:country":"US",
    "sg:address":"1504 W 228th St",
    "sg:city":"Torrance",
    "sg:classifiers":[
        {
            "category":"Manufacturing",
            "subcategory":"Metals",
            "type":"Manufacturing & Wholesale Goods"
        }
    ],
    "sg:phone":"+1 310 517 8770",
    "sg:postcode":"90501",
    "sg:province":"CA",
    "sg:tags":[
        "fabrication",
        "industrial",
        "structural",
        "machinery",
        "mfg"
    ],
    "wof:name":"D & M Engineering",
    "wof:placetype":"venue"
},
  "geometry": {"coordinates":[-118.306214,33.818949],"type":"Point"}
}