{
  "type": "Feature",
  "properties": {
    "iso:country":"US",
    "sg:address":"2625 Garnet Ave",
    "sg:city":"San Diego",
    "sg:classifiers":[
        {
            "category":"Travel",
            "subcategory":"Travel Agent",
            "type":"Entertainment"
        }
    ],
    "sg:phone":"+1 858 581 3311",
    "sg:postcode":"92109",
    "sg:province":"CA",
    "sg:tags":[
        "tours",
        "promoter"
    ],
    "sg:website":"www.bajaex.com",
    "wof:name":"Baja Expeditions",
    "wof:placetype":"venue"
},
  "geometry": {"coordinates":[-117.224102,32.804716],"type":"Point"}
}