{
  "type": "Feature",
  "properties": {
    "addr:full":"9204 Piccadilly Cir Windsor CA 95492",
    "addr:housenumber":"9204",
    "addr:postcode":"95492",
    "addr:street":"Piccadilly Cir",
    "iso:country":"US",
    "sg:address":"9204 Piccadilly Cir",
    "sg:city":"Windsor",
    "sg:classifiers":[
        {
            "category":"Building & Trades",
            "subcategory":"Construction",
            "type":"Services"
        }
    ],
    "sg:phone":"+1 707 838 2200",
    "sg:postcode":"95492",
    "sg:province":"CA",
    "sg:tags":[
        "repairing",
        "remodeling",
        "contractor"
    ],
    "wof:name":"GOW Construction",
    "wof:placetype":"venue"
},
  "geometry": {"coordinates":[-122.793808,38.553304],"type":"Point"}
}