{
  "type": "Feature",
  "properties": {
    "addr:full":"7106 Golf Course Ln San Jose CA 95139",
    "addr:housenumber":"7106",
    "addr:postcode":"95139",
    "addr:street":"Golf Course Ln",
    "iso:country":"US",
    "sg:address":"7106 Golf Course Ln",
    "sg:city":"San Jose",
    "sg:classifiers":[
        {
            "category":"Professional",
            "subcategory":"Management & Consulting",
            "type":"Services"
        }
    ],
    "sg:phone":"+1 408 224 5080",
    "sg:postcode":"95139",
    "sg:province":"CA",
    "sg:tags":[
        "party",
        "planning"
    ],
    "wof:name":"Heart Filled Weddings",
    "wof:placetype":"venue"
},
  "geometry": {"coordinates":[-121.77816300000001,37.22436],"type":"Point"}
}