{
  "type": "Feature",
  "properties": {
    "iso:country":"US",
    "sg:address":"9062 Adams Ave",
    "sg:city":"Huntington Beach",
    "sg:classifiers":[
        {
            "category":"Building & Trades",
            "subcategory":"Plumbing",
            "type":"Services"
        }
    ],
    "sg:phone":"+1 714 538 3811",
    "sg:postcode":"92646",
    "sg:province":"CA",
    "wof:name":"Zebco Drain & Plumbing",
    "wof:placetype":"venue"
},
  "geometry": {"coordinates":[-117.969002,33.6721],"type":"Point"}
}