{
  "type": "Feature",
  "properties": {
    "addr:full":"602 N Coast Hwy Oceanside CA 92054",
    "addr:housenumber":"602",
    "addr:postcode":"92054",
    "addr:street":"N Coast Hwy",
    "iso:country":"US",
    "sg:address":"602 N Coast Hwy",
    "sg:city":"Oceanside",
    "sg:classifiers":[
        {
            "category":"Restaurant",
            "type":"Food & Drink"
        }
    ],
    "sg:phone":"+1 760 433 3504",
    "sg:postcode":"92054",
    "sg:province":"CA",
    "sg:tags":[
        "mexican"
    ],
    "sg:website":"www.alfredosmexfood.com",
    "wof:name":"Alfredo's Mexican Food",
    "wof:placetype":"venue"
},
  "geometry": {"coordinates":[-117.382259,33.199626],"type":"Point"}
}