{
  "type": "Feature",
  "properties": {
    "iso:country":"US",
    "sg:address":"2003 16th Street",
    "sg:city":"San Francisco",
    "sg:classifiers":[
        {
            "category":"Professional",
            "subcategory":"Accounting & Tax Preparation",
            "type":"Services"
        }
    ],
    "sg:phone":"+1 415 864 1142",
    "sg:postcode":"94103",
    "sg:province":"CA",
    "sg:tags":[
        "accountant"
    ],
    "wof:name":"Shapiro, Bardin & Garcia",
    "wof:placetype":"venue"
},
  "geometry": {"coordinates":[-122.406876,37.765834],"type":"Point"}
}