{
  "type": "Feature",
  "properties": {
    "addr:full":"249 S Union Ave Bakersfield CA 93307",
    "addr:housenumber":"249",
    "addr:postcode":"93307",
    "addr:street":"S Union Ave",
    "iso:country":"US",
    "sg:address":"249 S Union Ave",
    "sg:city":"Bakersfield",
    "sg:classifiers":[
        {
            "category":"Autos & Motor Vehicles",
            "subcategory":"Auto Supplies",
            "type":"Retail Goods"
        }
    ],
    "sg:phone":"+1 661 323 4645",
    "sg:postcode":"93307",
    "sg:province":"CA",
    "sg:tags":[
        "automobile",
        "parts"
    ],
    "wof:name":"Al's Radiator & Automotive Svc",
    "wof:placetype":"venue"
},
  "geometry": {"coordinates":[-119.00307599999999,35.350656],"type":"Point"}
}