{
  "type": "Feature",
  "properties": {
    "addr:full":"591 E Palm Ave El Segundo CA 90245",
    "addr:housenumber":"591",
    "addr:postcode":"90245",
    "addr:street":"E Palm Ave",
    "iso:country":"US",
    "sg:address":"591 E Palm Ave",
    "sg:city":"El Segundo",
    "sg:classifiers":[
        {
            "category":"Education",
            "subcategory":"Preschool",
            "type":"Public Place"
        },
        {
            "category":"Education",
            "subcategory":"School",
            "type":"Public Place"
        }
    ],
    "sg:phone":"+1 310 322 2719",
    "sg:postcode":"90245",
    "sg:province":"CA",
    "sg:tags":[
        "elementary"
    ],
    "wof:name":"First Baptist Church of El Segundo",
    "wof:placetype":"venue"
},
  "geometry": {"coordinates":[-118.41100299999999,33.925201],"type":"Point"}
}