{
  "type": "Feature",
  "properties": {
    "addr:full":"18783 Stanton Ave Castro Valley CA 94546",
    "addr:housenumber":"18783",
    "addr:postcode":"94546",
    "addr:street":"Stanton Ave",
    "iso:country":"US",
    "sg:address":"18783 Stanton Ave",
    "sg:city":"Castro Valley",
    "sg:classifiers":[
        {
            "category":"Building & Trades",
            "subcategory":"Construction",
            "type":"Services"
        }
    ],
    "sg:phone":"+1 510 886 9554",
    "sg:postcode":"94546",
    "sg:province":"CA",
    "sg:tags":[
        "repairing",
        "remodeling",
        "contractor"
    ],
    "wof:name":"Bierly's Construction",
    "wof:placetype":"venue"
},
  "geometry": {"coordinates":[-122.10038299999999,37.705639],"type":"Point"}
}