{
  "type": "Feature",
  "properties": {
    "addr:full":"2173 Salk Ave. Ste. 250 Carlsbad CA 92008",
    "addr:housenumber":"2173",
    "addr:postcode":"92008",
    "addr:street":"Salk Ave. Ste. 250",
    "iso:country":"US",
    "sg:address":"2173 Salk Ave. Ste. 250",
    "sg:city":"Carlsbad",
    "sg:classifiers":[
        {
            "category":"Real Estate",
            "subcategory":"Real Estate Services",
            "type":"Services"
        },
        {
            "category":"Professional",
            "subcategory":"Employment Agencies",
            "type":"Services"
        }
    ],
    "sg:phone":"+1 760 579 7364",
    "sg:postcode":"92008",
    "sg:province":"CA",
    "sg:website":"www.knowledgeocity.com",
    "wof:name":"Knowledge City",
    "wof:placetype":"venue"
},
  "geometry": {"coordinates":[-117.27599499999999,33.138903],"type":"Point"}
}