{
  "type": "Feature",
  "properties": {
    "addr:full":"1730 Colby Ave Los Angeles CA 90025",
    "addr:housenumber":"1730",
    "addr:postcode":"90025",
    "addr:street":"Colby Ave",
    "iso:country":"US",
    "sg:address":"1730 Colby Ave",
    "sg:city":"Los Angeles",
    "sg:classifiers":[
        {
            "category":"Real Estate",
            "subcategory":"Developer",
            "type":"Services"
        }
    ],
    "sg:phone":"+1 310 445 9711",
    "sg:postcode":"90025",
    "sg:province":"CA",
    "wof:name":"D & S Enterprises",
    "wof:placetype":"venue"
},
  "geometry": {"coordinates":[-118.450461,34.042499],"type":"Point"}
}