{
  "type": "Feature",
  "properties": {
    "addr:full":"1211 Kona Dr Compton CA 90220",
    "addr:housenumber":"1211",
    "addr:postcode":"90220",
    "addr:street":"Kona Dr",
    "iso:country":"US",
    "sg:address":"1211 Kona Dr",
    "sg:city":"Compton",
    "sg:classifiers":[
        {
            "category":"Professional",
            "subcategory":"Testing Lab",
            "type":"Services"
        },
        {
            "category":"Professional",
            "subcategory":"Business Services",
            "type":"Services"
        }
    ],
    "sg:phone":"+1 310 635 2700",
    "sg:postcode":"90220",
    "sg:province":"CA",
    "sg:tags":[
        "analytical",
        "laboratory",
        "inspection"
    ],
    "sg:website":"http://www.getransportation.com",
    "wof:name":"Ge Inspection Svc",
    "wof:placetype":"venue"
},
  "geometry": {"coordinates":[-118.243921,33.870552],"type":"Point"}
}