{
  "type": "Feature",
  "properties": {
    "addr:full":"123 E Artesia Blvd Compton CA 90220",
    "addr:housenumber":"123",
    "addr:postcode":"90220",
    "addr:street":"E Artesia Blvd",
    "iso:country":"US",
    "sg:address":"123 E Artesia Blvd",
    "sg:city":"Compton",
    "sg:classifiers":[
        {
            "category":"Travel",
            "subcategory":"Hotels & Motels",
            "type":"Entertainment"
        },
        {
            "category":"Casinos & Gambling",
            "type":"Entertainment"
        }
    ],
    "sg:phone":"+1 310 631 3838",
    "sg:postcode":"90220",
    "sg:province":"CA",
    "sg:website":"www.thecrystalcasino.com",
    "wof:name":"Crystal Park Casino & Hotel",
    "wof:placetype":"venue"
},
  "geometry": {"coordinates":[-118.22094300000001,33.874385],"type":"Point"}
}