{
  "type": "Feature",
  "properties": {
    "addr:full":"2450 Summit Dr Santa Rosa CA 95404",
    "addr:housenumber":"2450",
    "addr:postcode":"95404",
    "addr:street":"Summit Dr",
    "iso:country":"US",
    "sg:address":"2450 Summit Dr",
    "sg:city":"Santa Rosa",
    "sg:classifiers":[
        {
            "category":"Professional",
            "subcategory":"Engineering",
            "type":"Services"
        }
    ],
    "sg:phone":"+1 707 578 1680",
    "sg:postcode":"95404",
    "sg:province":"CA",
    "sg:tags":[
        "civil",
        "general",
        "engineer",
        "contractor"
    ],
    "wof:name":"Bartholow Engineering",
    "wof:placetype":"venue"
},
  "geometry": {"coordinates":[-122.712316,38.465532],"type":"Point"}
}