{
  "type": "Feature",
  "properties": {
    "iso:country":"US",
    "sg:address":"5026 Calmview Ave",
    "sg:city":"Baldwin Park",
    "sg:classifiers":[
        {
            "category":"Manufacturing",
            "subcategory":"Metals",
            "type":"Manufacturing & Wholesale Goods"
        }
    ],
    "sg:phone":"+1 626 962 3293",
    "sg:postcode":"91706",
    "sg:province":"CA",
    "sg:tags":[
        "fabricator",
        "sheet"
    ],
    "wof:name":"Fabtronics",
    "wof:placetype":"venue"
},
  "geometry": {"coordinates":[-117.947843,34.106217],"type":"Point"}
}