{
  "type": "Feature",
  "properties": {
    "iso:country":"US",
    "sg:address":"1337 E Thousand Oaks Blvd",
    "sg:city":"Thousand Oaks",
    "sg:classifiers":[
        {
            "category":"Health Services",
            "subcategory":"Health Practitioner",
            "type":"Services"
        }
    ],
    "sg:phone":"+1 805 557 0807",
    "sg:postcode":"91362",
    "sg:province":"CA",
    "sg:tags":[
        "acupuncture"
    ],
    "wof:name":"Acupuncture",
    "wof:placetype":"venue"
},
  "geometry": {"coordinates":[-118.855553,34.178155],"type":"Point"}
}