{
  "type": "Feature",
  "properties": {
    "addr:full":"2933 Coronado Avenue San Diego CA 92154",
    "addr:housenumber":"2933",
    "addr:postcode":"92154",
    "addr:street":"Coronado Avenue",
    "iso:country":"US",
    "sg:address":"2933 Coronado Avenue",
    "sg:city":"San Diego",
    "sg:classifiers":[
        {
            "category":"Personal",
            "subcategory":"Nail Salon",
            "type":"Services"
        }
    ],
    "sg:phone":"+1 619 423 8680",
    "sg:postcode":"92154",
    "sg:province":"CA",
    "wof:name":"Ramon's Hairstyling No 2",
    "wof:placetype":"venue"
},
  "geometry": {"coordinates":[-117.070583,32.576568],"type":"Point"}
}