{
  "type": "Feature",
  "properties": {
    "addr:full":"288 W Valley Blvd Ste 208 Alhambra CA 91801",
    "addr:housenumber":"288",
    "addr:postcode":"91801",
    "addr:street":"W Valley Blvd Ste 208",
    "iso:country":"US",
    "sg:address":"288 W Valley Blvd Ste 208",
    "sg:city":"Alhambra",
    "sg:classifiers":[
        {
            "category":"Professional",
            "subcategory":"Lawyer & Legal Services",
            "type":"Services"
        }
    ],
    "sg:phone":"+1 626 284 6320",
    "sg:postcode":"91801",
    "sg:province":"CA",
    "wof:name":"Law Offices of Ray Hellwig",
    "wof:placetype":"venue"
},
  "geometry": {"coordinates":[-118.125443,34.078423],"type":"Point"}
}