{
  "type": "Feature",
  "properties": {
    "iso:country":"US",
    "sg:address":"325 Canham Rd",
    "sg:city":"Scotts Valley",
    "sg:classifiers":[
        {
            "category":"Building & Trades",
            "subcategory":"Construction",
            "type":"Services"
        }
    ],
    "sg:phone":"+1 831 439 8990",
    "sg:postcode":"95066",
    "sg:province":"CA",
    "sg:tags":[
        "contractor"
    ],
    "wof:name":"Hochler Construction",
    "wof:placetype":"venue"
},
  "geometry": {"coordinates":[-121.994452,37.082518],"type":"Point"}
}