{
  "type": "Feature",
  "properties": {
    "iso:country":"US",
    "sg:address":"23822 Valencia Blvd",
    "sg:city":"Valencia",
    "sg:classifiers":[
        {
            "category":"Professional",
            "subcategory":"Lawyer & Legal Services",
            "type":"Services"
        }
    ],
    "sg:phone":"+1 661 257 3725",
    "sg:postcode":"91355",
    "sg:province":"CA",
    "wof:name":"A Adoption Atty John A Giffen",
    "wof:placetype":"venue"
},
  "geometry": {"coordinates":[-118.549878,34.415206],"type":"Point"}
}