{
  "type": "Feature",
  "properties": {
    "iso:country":"US",
    "sg:address":"73231 Broadmoor Dr",
    "sg:city":"Thousand Palms",
    "sg:classifiers":[
        {
            "category":"Manufacturing",
            "subcategory":"Paper Products",
            "type":"Manufacturing & Wholesale Goods"
        }
    ],
    "sg:phone":"+1 907 783 2968",
    "sg:postcode":"92276",
    "sg:province":"CA",
    "sg:tags":[
        "universal",
        "bottle",
        "clip"
    ],
    "wof:name":"Univeral Bottle Clip Co",
    "wof:placetype":"venue"
},
  "geometry": {"coordinates":[-116.38434,33.809841],"type":"Point"}
}