{
  "type": "Feature",
  "properties": {
    "iso:country":"US",
    "sg:address":"4303 Temescal Ave",
    "sg:city":"Norco",
    "sg:classifiers":[
        {
            "category":"Retail",
            "subcategory":"Repair Shop",
            "type":"Services"
        }
    ],
    "sg:phone":"+1 951 273 9822",
    "sg:postcode":"92860",
    "sg:province":"CA",
    "sg:tags":[
        "plumbing",
        "drain",
        "cleaning",
        "sewer"
    ],
    "wof:name":"Western Plumbing & Drain Clng",
    "wof:placetype":"venue"
},
  "geometry": {"coordinates":[-117.541171,33.942915],"type":"Point"}
}