{
  "type": "Feature",
  "properties": {
    "addr:full":"3811 E Castro Valley Blvd Castro Valley CA 94552",
    "addr:housenumber":"3811",
    "addr:postcode":"94552",
    "addr:street":"E Castro Valley Blvd",
    "iso:country":"US",
    "sg:address":"3811 E Castro Valley Blvd",
    "sg:city":"Castro Valley",
    "sg:classifiers":[
        {
            "category":"Real Estate",
            "subcategory":"Real Estate Agent",
            "type":"Services"
        }
    ],
    "sg:phone":"+1 510 755 2666",
    "sg:postcode":"94552",
    "sg:province":"CA",
    "wof:name":"Leslie Drury - Windermere Welcome Home",
    "wof:placetype":"venue"
},
  "geometry": {"coordinates":[-122.053499,37.694831],"type":"Point"}
}