{
  "type": "Feature",
  "properties": {
    "addr:full":"212 Benham Dr Martinez CA 94553",
    "addr:housenumber":"212",
    "addr:postcode":"94553",
    "addr:street":"Benham Dr",
    "iso:country":"US",
    "sg:address":"212 Benham Dr",
    "sg:city":"Martinez",
    "sg:classifiers":[
        {
            "category":"Professional",
            "type":"Services"
        }
    ],
    "sg:phone":"+1 925 229 1883",
    "sg:postcode":"94553",
    "sg:province":"CA",
    "wof:name":"Jeffrey Kosta Studios Inc",
    "wof:placetype":"venue"
},
  "geometry": {"coordinates":[-122.10022600000001,37.965532],"type":"Point"}
}