{
  "type": "Feature",
  "properties": {
    "addr:full":"122 Calistoga Rd Santa Rosa CA 95409",
    "addr:housenumber":"122",
    "addr:postcode":"95409",
    "addr:street":"Calistoga Rd",
    "iso:country":"US",
    "sg:address":"122 Calistoga Rd",
    "sg:city":"Santa Rosa",
    "sg:classifiers":[
        {
            "category":"Professional",
            "subcategory":"Lawyer & Legal Services",
            "type":"Services"
        }
    ],
    "sg:phone":"+1 707 578 7714",
    "sg:postcode":"95409",
    "sg:province":"CA",
    "sg:tags":[
        "attorney"
    ],
    "wof:name":"John F Shields",
    "wof:placetype":"venue"
},
  "geometry": {"coordinates":[-122.653389,38.4658],"type":"Point"}
}