{
  "type": "Feature",
  "properties": {
    "addr:full":"8626 Atlas View Dr Santee CA 92071",
    "addr:housenumber":"8626",
    "addr:postcode":"92071",
    "addr:street":"Atlas View Dr",
    "iso:country":"US",
    "sg:address":"8626 Atlas View Dr",
    "sg:city":"Santee",
    "sg:classifiers":[
        {
            "category":"Professional",
            "type":"Services"
        }
    ],
    "sg:phone":"+1 619 562 5714",
    "sg:postcode":"92071",
    "sg:province":"CA",
    "wof:name":"Jeries & Co",
    "wof:placetype":"venue"
},
  "geometry": {"coordinates":[-116.99301699999999,32.83096],"type":"Point"}
}