{
  "type": "Feature",
  "properties": {
    "addr:full":"14045 Ramona Ave Chino CA 91710",
    "addr:housenumber":"14045",
    "addr:postcode":"91710",
    "addr:street":"Ramona Ave",
    "iso:country":"US",
    "sg:address":"14045 Ramona Ave",
    "sg:city":"Chino",
    "sg:classifiers":[
        {
            "category":"Freight",
            "type":"Transportation"
        }
    ],
    "sg:phone":"+1 909 628 2861",
    "sg:postcode":"91710",
    "sg:province":"CA",
    "sg:tags":[
        "warehouse",
        "general"
    ],
    "wof:name":"Grossfillex Distribution Ctr",
    "wof:placetype":"venue"
},
  "geometry": {"coordinates":[-117.706461,34.001928],"type":"Point"}
}