{
  "type": "Feature",
  "properties": {
    "addr:full":"9000 Reseda Blvd Northridge CA 91324",
    "addr:housenumber":"9000",
    "addr:postcode":"91324",
    "addr:street":"Reseda Blvd",
    "iso:country":"US",
    "sg:address":"9000 Reseda Blvd",
    "sg:city":"Northridge",
    "sg:classifiers":[
        {
            "category":"Shopping",
            "type":"Retail Goods"
        }
    ],
    "sg:phone":"+1 818 701 7039",
    "sg:postcode":"91324",
    "sg:province":"CA",
    "sg:tags":[
        "trophy",
        "medal",
        "award"
    ],
    "wof:name":"Trophy Plus",
    "wof:placetype":"venue"
},
  "geometry": {"coordinates":[-118.53601,34.233658],"type":"Point"}
}