{
  "type": "Feature",
  "properties": {
    "addr:full":"266 E Java Dr Sunnyvale CA 94089",
    "addr:housenumber":"266",
    "addr:postcode":"94089",
    "addr:street":"E Java Dr",
    "iso:country":"US",
    "sg:address":"266 E Java Dr",
    "sg:city":"Sunnyvale",
    "sg:classifiers":[
        {
            "category":"Manufacturing",
            "subcategory":"Printing",
            "type":"Manufacturing & Wholesale Goods"
        }
    ],
    "sg:phone":"+1 408 734 1000",
    "sg:postcode":"94089",
    "sg:province":"CA",
    "sg:tags":[
        "lithographic",
        "commercial"
    ],
    "wof:name":"Print Innovations Inc",
    "wof:placetype":"venue"
},
  "geometry": {"coordinates":[-122.01665800000001,37.41139],"type":"Point"}
}