{
  "type": "Feature",
  "properties": {
    "iso:country":"US",
    "sg:address":"11930 Heritage Oak Pl",
    "sg:city":"Auburn",
    "sg:classifiers":[
        {
            "category":"Health Services",
            "subcategory":"Health Practitioner",
            "type":"Services"
        }
    ],
    "sg:phone":"+1 530 888 7158",
    "sg:postcode":"95603",
    "sg:province":"CA",
    "sg:tags":[
        "therapist",
        "physical"
    ],
    "wof:name":"Rebound Therapy Svc",
    "wof:placetype":"venue"
},
  "geometry": {"coordinates":[-121.098715,38.941157],"type":"Point"}
}