{
  "type": "Feature",
  "properties": {
    "iso:country":"US",
    "sg:address":"1625 Culpepper Ave",
    "sg:city":"Modesto",
    "sg:classifiers":[
        {
            "category":"Home & Garden",
            "subcategory":"Garden Supply",
            "type":"Retail Goods"
        }
    ],
    "sg:phone":"+1 209 522 3899",
    "sg:postcode":"95351",
    "sg:province":"CA",
    "sg:tags":[
        "landscaping",
        "equipment"
    ],
    "wof:name":"Vintage Co",
    "wof:placetype":"venue"
},
  "geometry": {"coordinates":[-121.027715,37.660295],"type":"Point"}
}