{
  "type": "Feature",
  "properties": {
    "addr:full":"9443 Victoria Ln Windsor CA 95492",
    "addr:housenumber":"9443",
    "addr:postcode":"95492",
    "addr:street":"Victoria Ln",
    "iso:country":"US",
    "sg:address":"9443 Victoria Ln",
    "sg:city":"Windsor",
    "sg:classifiers":[
        {
            "category":"Insurance",
            "subcategory":"Insurance Agent",
            "type":"Services"
        }
    ],
    "sg:phone":"+1 707 570 0290",
    "sg:postcode":"95492",
    "sg:province":"CA",
    "wof:name":"Laiks Ins/Financial",
    "wof:placetype":"venue"
},
  "geometry": {"coordinates":[-122.792669,38.555034],"type":"Point"}
}