{
  "type": "Feature",
  "properties": {
    "addr:full":"1785 Rogers Ave San Jose CA 95112",
    "addr:housenumber":"1785",
    "addr:postcode":"95112",
    "addr:street":"Rogers Ave",
    "iso:country":"US",
    "sg:address":"1785 Rogers Ave",
    "sg:city":"San Jose",
    "sg:classifiers":[
        {
            "category":"Building & Trades",
            "subcategory":"Construction",
            "type":"Services"
        }
    ],
    "sg:phone":"+1 408 452 0100",
    "sg:postcode":"95112",
    "sg:province":"CA",
    "sg:tags":[
        "contractor"
    ],
    "wof:name":"Otto Marble",
    "wof:placetype":"venue"
},
  "geometry": {"coordinates":[-121.91075600000001,37.377427],"type":"Point"}
}