{
  "type": "Feature",
  "properties": {
    "iso:country":"US",
    "sg:address":"10219 Cozycroft Ave",
    "sg:city":"Chatsworth",
    "sg:classifiers":[
        {
            "category":"Building & Trades",
            "subcategory":"Construction",
            "type":"Services"
        }
    ],
    "sg:phone":"+1 818 882 4222",
    "sg:postcode":"91311",
    "sg:province":"CA",
    "sg:tags":[
        "contractor"
    ],
    "wof:name":"Dynamic Fence Inc",
    "wof:placetype":"venue"
},
  "geometry": {"coordinates":[-118.581878,34.255707],"type":"Point"}
}