{
  "type": "Feature",
  "properties": {
    "addr:full":"11401 Heacock St Moreno Valley CA 92557",
    "addr:housenumber":"11401",
    "addr:postcode":"92557",
    "addr:street":"Heacock St",
    "iso:country":"US",
    "sg:address":"11401 Heacock St",
    "sg:city":"Moreno Valley",
    "sg:classifiers":[
        {
            "category":"Health Services",
            "subcategory":"Doctor",
            "type":"Services"
        }
    ],
    "sg:phone":"+1 951 247 7228",
    "sg:postcode":"92557",
    "sg:province":"CA",
    "sg:tags":[
        "dentist"
    ],
    "wof:name":"Smile Island Orthodontics",
    "wof:placetype":"venue"
},
  "geometry": {"coordinates":[-117.243989,33.959118],"type":"Point"}
}