{
  "type": "Feature",
  "properties": {
    "addr:full":"15959 Piuma Ave Cerritos CA 90703",
    "addr:housenumber":"15959",
    "addr:postcode":"ca 90703",
    "addr:street":"Piuma Ave",
    "iso:country":"US",
    "sg:address":"15959 Piuma Ave",
    "sg:city":"Cerritos",
    "sg:classifiers":[
        {
            "category":"Manufacturing",
            "subcategory":"Paper Products",
            "type":"Manufacturing & Wholesale Goods"
        }
    ],
    "sg:phone":"+1 562 809 0300",
    "sg:postcode":"90703",
    "sg:province":"CA",
    "sg:tags":[
        "products-wholesale",
        "manufacturer"
    ],
    "wof:name":"R3 Papercraft",
    "wof:placetype":"venue"
},
  "geometry": {"coordinates":[-118.105822,33.886721],"type":"Point"}
}