{
  "type": "Feature",
  "properties": {
    "addr:full":"3645 Lawton St San Francisco CA 94122",
    "addr:housenumber":"3645",
    "addr:postcode":"94122",
    "addr:street":"Lawton St",
    "iso:country":"US",
    "sg:address":"3645 Lawton St",
    "sg:city":"San Francisco",
    "sg:classifiers":[
        {
            "category":"Food & Beverages",
            "subcategory":"Liquor & Beverages",
            "type":"Retail Goods"
        }
    ],
    "sg:phone":"+1 415 564 0737",
    "sg:postcode":"94122",
    "sg:province":"CA",
    "wof:name":"Lawton Liquors",
    "wof:placetype":"venue"
},
  "geometry": {"coordinates":[-122.502064,37.756781],"type":"Point"}
}