{
  "type": "Feature",
  "properties": {
    "iso:country":"US",
    "sg:address":"39252 Winchester Rd # 107",
    "sg:city":"Murrieta",
    "sg:classifiers":[
        {
            "category":"Professional",
            "subcategory":"Detective & Security Services",
            "type":"Services"
        }
    ],
    "sg:phone":"+1 888 788 5558",
    "sg:postcode":"92563",
    "sg:province":"CA",
    "sg:tags":[
        "private",
        "investigator"
    ],
    "wof:name":"J. Banks Detective Agency, Inc.",
    "wof:placetype":"venue"
},
  "geometry": {"coordinates":[-117.141424,33.549153],"type":"Point"}
}