{
  "type": "Feature",
  "properties": {
    "addr:full":"1705 S Mountain Ave Monrovia CA 91016",
    "addr:housenumber":"1705",
    "addr:postcode":"91016",
    "addr:street":"S Mountain Ave",
    "iso:country":"US",
    "sg:address":"1705 S Mountain Ave",
    "sg:city":"Monrovia",
    "sg:classifiers":[
        {
            "category":"Real Estate",
            "subcategory":"Real Estate Services",
            "type":"Services"
        },
        {
            "category":"Real Estate",
            "subcategory":"Real Estate Agent",
            "type":"Services"
        }
    ],
    "sg:phone":"+1 626 303 5454",
    "sg:postcode":"91016",
    "sg:province":"CA",
    "sg:tags":[
        "buyer",
        "broker"
    ],
    "wof:name":"Lenders Marketing Group",
    "wof:placetype":"venue"
},
  "geometry": {"coordinates":[-117.98632000000001,34.133308],"type":"Point"}
}