{
  "type": "Feature",
  "properties": {
    "addr:full":"1657 N California Blvd Walnut Creek CA 94596",
    "addr:housenumber":"1657",
    "addr:postcode":"94596",
    "addr:street":"N California Blvd",
    "iso:country":"US",
    "sg:address":"1657 N California Blvd",
    "sg:city":"Walnut Creek",
    "sg:classifiers":[
        {
            "category":"Real Estate",
            "subcategory":"Real Estate Agent",
            "type":"Services"
        }
    ],
    "sg:phone":"+1 925 472 5850",
    "sg:postcode":"94596",
    "sg:province":"CA",
    "sg:tags":[
        "appraiser"
    ],
    "wof:name":"Dunn & Assoc",
    "wof:placetype":"venue"
},
  "geometry": {"coordinates":[-122.06492,37.903133],"type":"Point"}
}