{
  "type": "Feature",
  "properties": {
    "iso:country":"US",
    "sg:address":"46101 Warm Springs Blvd",
    "sg:city":"Fremont",
    "sg:classifiers":[
        {
            "category":"Travel",
            "subcategory":"Hotels & Motels",
            "type":"Entertainment"
        }
    ],
    "sg:phone":"+1 510 656 2800",
    "sg:postcode":"94539",
    "sg:province":"CA",
    "sg:website":"www.choicehotels.com/ires/en-US/...",
    "wof:name":"Days Inn-Fremont",
    "wof:placetype":"venue"
},
  "geometry": {"coordinates":[-121.93159900000001,37.493322],"type":"Point"}
}