{
  "type": "Feature",
  "properties": {
    "iso:country":"US",
    "sg:address":"4859 Telegraph Rd",
    "sg:city":"Los Angeles",
    "sg:classifiers":[
        {
            "category":"Wholesale",
            "subcategory":"Machinery & Supplies",
            "type":"Manufacturing & Wholesale Goods"
        }
    ],
    "sg:phone":"+1 323 263 4261",
    "sg:postcode":"90022",
    "sg:province":"CA",
    "sg:tags":[
        "equipment",
        "industrial"
    ],
    "wof:name":"American Forklift Services",
    "wof:placetype":"venue"
},
  "geometry": {"coordinates":[-118.166246,34.014064],"type":"Point"}
}