{
  "type": "Feature",
  "properties": {
    "addr:full":"8520 Paramount Blvd Downey CA 90240",
    "addr:housenumber":"8520",
    "addr:postcode":"90240",
    "addr:street":"Paramount Blvd",
    "iso:country":"US",
    "sg:address":"8520 Paramount Blvd",
    "sg:city":"Downey",
    "sg:classifiers":[
        {
            "category":"Insurance",
            "subcategory":"Insurance Agent",
            "type":"Services"
        }
    ],
    "sg:phone":"+1 562 776 5333",
    "sg:postcode":"90240",
    "sg:province":"CA",
    "wof:name":"Estrada Insurance",
    "wof:placetype":"venue"
},
  "geometry": {"coordinates":[-118.11636799999999,33.966598],"type":"Point"}
}