{
  "type": "Feature",
  "properties": {
    "addr:full":"500 N Victory Blvd Burbank CA 91502",
    "addr:housenumber":"500",
    "addr:postcode":"91502",
    "addr:street":"N Victory Blvd",
    "iso:country":"US",
    "sg:address":"500 N Victory Blvd",
    "sg:city":"Burbank",
    "sg:classifiers":[
        {
            "category":"Shopping",
            "subcategory":"Thrift Store",
            "type":"Retail Goods"
        },
        {
            "category":"Shopping",
            "type":"Retail Goods"
        }
    ],
    "sg:phone":"+1 818 841 2969",
    "sg:postcode":"91502",
    "sg:province":"CA",
    "sg:website":"discoveryshop-burbank.org/",
    "wof:name":"American Cancer Society Discovery Shop",
    "wof:placetype":"venue"
},
  "geometry": {"coordinates":[-118.319,34.178799],"type":"Point"}
}