{
  "type": "Feature",
  "properties": {
    "addr:full":"1240 Logan Ave Ste M Costa Mesa CA 92626",
    "addr:housenumber":"1240",
    "addr:postcode":"92626",
    "addr:street":"Logan Ave Ste M Costa",
    "iso:country":"US",
    "sg:address":"1240 Logan Ave Ste M",
    "sg:city":"Costa Mesa",
    "sg:classifiers":[
        {
            "category":"Professional",
            "subcategory":"Printing & Photocopies",
            "type":"Services"
        }
    ],
    "sg:phone":"+1 714 751 2679",
    "sg:postcode":"92626",
    "sg:province":"CA",
    "wof:name":"Coast Business Systems",
    "wof:placetype":"venue"
},
  "geometry": {"coordinates":[-117.91100299999999,33.678799],"type":"Point"}
}