{
  "type": "Feature",
  "properties": {
    "addr:full":"14545 Whittier Blvd Whittier CA 90605",
    "addr:housenumber":"14545",
    "addr:postcode":"90605",
    "addr:street":"Whittier Blvd",
    "iso:country":"US",
    "sg:address":"14545 Whittier Blvd",
    "sg:city":"Whittier",
    "sg:classifiers":[
        {
            "category":"Retail",
            "subcategory":"Funeral Services",
            "type":"Services"
        }
    ],
    "sg:phone":"+1 562 945 2001",
    "sg:postcode":"90605",
    "sg:province":"CA",
    "sg:tags":[
        "director"
    ],
    "wof:name":"Dignity Memorial Funeral",
    "wof:placetype":"venue"
},
  "geometry": {"coordinates":[-118.013018,33.952098],"type":"Point"}
}