{
  "type": "Feature",
  "properties": {
    "addr:full":"30423 Canwood St Agoura Hills CA 91301",
    "addr:housenumber":"30423",
    "addr:postcode":"91301",
    "addr:street":"Canwood St",
    "iso:country":"US",
    "sg:address":"30423 Canwood St",
    "sg:city":"Agoura Hills",
    "sg:classifiers":[
        {
            "category":"Professional",
            "subcategory":"Accounting & Tax Preparation",
            "type":"Services"
        }
    ],
    "sg:phone":"+1 818 889 5302",
    "sg:postcode":"91301",
    "sg:province":"CA",
    "sg:tags":[
        "return",
        "filing"
    ],
    "wof:name":"Walter Kelley Income Tax Svc",
    "wof:placetype":"venue"
},
  "geometry": {"coordinates":[-118.78228900000001,34.147569],"type":"Point"}
}