{
  "type": "Feature",
  "properties": {
    "iso:country":"US",
    "sg:address":"142 N Grand Ave",
    "sg:city":"Glendora",
    "sg:phone":"+1 626 914 1235",
    "sg:postcode":"91741",
    "sg:province":"CA",
    "wof:name":"Modern Nail Spa",
    "wof:placetype":"venue"
},
  "geometry": {"coordinates":[-117.872552,34.137331],"type":"Point"}
}