{
  "type": "Feature",
  "properties": {
    "addr:full":"2827 Smith Grade Santa Cruz CA 95060",
    "addr:housenumber":"2827",
    "addr:postcode":"95060",
    "addr:street":"Smith Grade",
    "iso:country":"US",
    "sg:address":"2827 Smith Grade",
    "sg:city":"Santa Cruz",
    "sg:classifiers":[
        {
            "category":"Building & Trades",
            "subcategory":"Construction",
            "type":"Services"
        }
    ],
    "sg:phone":"+1 831 423 7577",
    "sg:postcode":"95060",
    "sg:province":"CA",
    "sg:tags":[
        "contractor"
    ],
    "wof:name":"Del Mar Builders",
    "wof:placetype":"venue"
},
  "geometry": {"coordinates":[-122.125165,37.017075],"type":"Point"}
}