{
  "type": "Feature",
  "properties": {
    "addr:full":"404 E Commercial St Pomona CA 91767",
    "addr:housenumber":"404",
    "addr:postcode":"91767",
    "addr:street":"E Commercial St",
    "iso:country":"US",
    "sg:address":"404 E Commercial St",
    "sg:city":"Pomona",
    "sg:phone":"+1 909 623 0533",
    "sg:postcode":"91767",
    "sg:province":"CA",
    "sg:tags":[
        "product",
        "petroleum"
    ],
    "sg:website":"www.orangelineoil.com",
    "wof:name":"Orange Line Oil Co Inc",
    "wof:placetype":"venue"
},
  "geometry": {"coordinates":[-117.742222,34.059775],"type":"Point"}
}