{
  "type": "Feature",
  "properties": {
    "iso:country":"US",
    "sg:address":"115 N 6th St",
    "sg:city":"El Centro",
    "sg:classifiers":[
        {
            "category":"Shopping",
            "subcategory":"Florist",
            "type":"Retail Goods"
        }
    ],
    "sg:phone":"+1 760 353 3887",
    "sg:postcode":"92243",
    "sg:province":"CA",
    "wof:name":"Kountry Krafts & Flowers",
    "wof:placetype":"venue"
},
  "geometry": {"coordinates":[-115.55686300000001,32.793731],"type":"Point"}
}