{
  "type": "Feature",
  "properties": {
    "iso:country":"US",
    "sg:address":"3703 Motor Ave",
    "sg:city":"Los Angeles",
    "sg:classifiers":[
        {
            "category":"Retail",
            "subcategory":"Auto Repair",
            "type":"Services"
        }
    ],
    "sg:phone":"+1 310 559 2233",
    "sg:postcode":"90034",
    "sg:province":"CA",
    "sg:tags":[
        "body",
        "shop"
    ],
    "wof:name":"Jim's Body Shop",
    "wof:placetype":"venue"
},
  "geometry": {"coordinates":[-118.404999,34.022598],"type":"Point"}
}