{
  "type": "Feature",
  "properties": {
    "addr:full":"11670 Gateway Blvd Los Angeles CA 90064",
    "addr:housenumber":"11670",
    "addr:postcode":"90064",
    "addr:street":"Gateway Blvd",
    "iso:country":"US",
    "sg:address":"11670 Gateway Blvd",
    "sg:city":"Los Angeles",
    "sg:classifiers":[
        {
            "category":"Restaurant",
            "type":"Food & Drink"
        }
    ],
    "sg:phone":"+1 310 478 8991",
    "sg:postcode":"90064",
    "sg:province":"CA",
    "sg:tags":[
        "korean"
    ],
    "sg:website":"www.ilovegushi.com",
    "wof:name":"Gushi",
    "wof:placetype":"venue"
},
  "geometry": {"coordinates":[-118.442986,34.029038],"type":"Point"}
}