{
  "type": "Feature",
  "properties": {
    "addr:full":"129 J St Sacramento CA 95814",
    "addr:housenumber":"129",
    "addr:postcode":"95814",
    "addr:street":"J St",
    "iso:country":"US",
    "sg:address":"129 J St",
    "sg:city":"Sacramento",
    "sg:classifiers":[
        {
            "category":"Real Estate",
            "subcategory":"Real Estate Agent",
            "type":"Services"
        }
    ],
    "sg:phone":"+1 916 444 6900",
    "sg:postcode":"95814",
    "sg:province":"CA",
    "wof:name":"Realty First Financial",
    "wof:placetype":"venue"
},
  "geometry": {"coordinates":[-121.504628,38.583282],"type":"Point"}
}