{
  "type": "Feature",
  "properties": {
    "iso:country":"US",
    "sg:address":"890 Brockhurst St",
    "sg:city":"Oakland",
    "sg:classifiers":[
        {
            "category":"Education",
            "subcategory":"School",
            "type":"Public Place"
        }
    ],
    "sg:phone":"+1 510 879 1700",
    "sg:postcode":"94608",
    "sg:province":"CA",
    "sg:tags":[
        "high",
        "middle",
        "elementary"
    ],
    "sg:website":"www.ousd.k12.ca.us",
    "wof:name":"Oakland Public Schools",
    "wof:placetype":"venue"
},
  "geometry": {"coordinates":[-122.27548400000001,37.823337],"type":"Point"}
}