{
  "type": "Feature",
  "properties": {
    "iso:country":"US",
    "sg:address":"4375 Rustic Way",
    "sg:city":"San Luis Obispo",
    "sg:classifiers":[
        {
            "category":"Shopping",
            "type":"Retail Goods"
        }
    ],
    "sg:phone":"+1 805 782 0839",
    "sg:postcode":"93401",
    "sg:province":"CA",
    "sg:tags":[
        "flagpole",
        "flag",
        "sales"
    ],
    "wof:name":"Drake Flags & Poles Etc",
    "wof:placetype":"venue"
},
  "geometry": {"coordinates":[-120.65715299999999,35.237135],"type":"Point"}
}