{
  "type": "Feature",
  "properties": {
    "addr:full":"9045 Adams Avenue Huntington Beach CA 92646",
    "addr:housenumber":"9045",
    "addr:postcode":"92646",
    "addr:street":"Adams Avenue",
    "iso:country":"US",
    "sg:address":"9045 Adams Avenue",
    "sg:city":"Huntington Beach",
    "sg:classifiers":[
        {
            "category":"Home & Garden",
            "subcategory":"Hardware",
            "type":"Retail Goods"
        }
    ],
    "sg:phone":"+1 714 962 4160",
    "sg:postcode":"92646",
    "sg:province":"CA",
    "sg:tags":[
        "store"
    ],
    "wof:name":"Crown Hardware Corporation Ofc",
    "wof:placetype":"venue"
},
  "geometry": {"coordinates":[-117.969435,33.672447],"type":"Point"}
}