{
  "type": "Feature",
  "properties": {
    "iso:country":"US",
    "sg:address":"1249 E Kentucky Ave",
    "sg:city":"Woodland",
    "sg:classifiers":[
        {
            "category":"Wholesale",
            "subcategory":"Machinery & Supplies",
            "type":"Manufacturing & Wholesale Goods"
        }
    ],
    "sg:phone":"+1 530 666 3646",
    "sg:postcode":"95776",
    "sg:province":"CA",
    "sg:tags":[
        "equipment",
        "hydraulic"
    ],
    "wof:name":"Valley Hydraulics & Machine",
    "wof:placetype":"venue"
},
  "geometry": {"coordinates":[-121.762645,38.691944],"type":"Point"}
}