{
  "type": "Feature",
  "properties": {
    "addr:full":"2780 34th Ave San Francisco CA 94116",
    "addr:housenumber":"2780",
    "addr:postcode":"94116",
    "addr:street":"34Th Ave",
    "iso:country":"US",
    "sg:address":"2780 34th Ave",
    "sg:city":"San Francisco",
    "sg:classifiers":[
        {
            "category":"Building & Trades",
            "subcategory":"Electrical",
            "type":"Services"
        }
    ],
    "sg:phone":"+1 415 760 9338",
    "sg:postcode":"94116",
    "sg:province":"CA",
    "sg:tags":[
        "electrical",
        "contractor"
    ],
    "wof:name":"Wl Electrical Inc",
    "wof:placetype":"venue"
},
  "geometry": {"coordinates":[-122.491338,37.736962],"type":"Point"}
}