{
  "type": "Feature",
  "properties": {
    "addr:full":"535 W Broadway Glendale CA 91204",
    "addr:housenumber":"535",
    "addr:postcode":"91204",
    "addr:street":"W Broadway",
    "iso:country":"US",
    "sg:address":"535 W Broadway",
    "sg:city":"Glendale",
    "sg:classifiers":[
        {
            "category":"Health Services",
            "subcategory":"Doctor",
            "type":"Services"
        }
    ],
    "sg:phone":"+1 818 244 9141",
    "sg:postcode":"91204",
    "sg:province":"CA",
    "sg:tags":[
        "physician",
        "surgeon"
    ],
    "wof:name":"Dale J Brent MD",
    "wof:placetype":"venue"
},
  "geometry": {"coordinates":[-118.27112099999999,34.146766],"type":"Point"}
}