{
  "type": "Feature",
  "properties": {
    "addr:full":"4921 E Lansing Way Fresno CA 93727",
    "addr:housenumber":"4921",
    "addr:postcode":"93727",
    "addr:street":"E Lansing Way",
    "iso:country":"US",
    "sg:address":"4921 E Lansing Way",
    "sg:city":"Fresno",
    "sg:classifiers":[
        {
            "category":"Home & Garden",
            "subcategory":"Building Materials",
            "type":"Retail Goods"
        }
    ],
    "sg:phone":"+1 559 627 0423",
    "sg:postcode":"93727",
    "sg:province":"CA",
    "sg:tags":[
        "door"
    ],
    "wof:name":"Windsor Door Co",
    "wof:placetype":"venue"
},
  "geometry": {"coordinates":[-119.730723,36.788091],"type":"Point"}
}