{
  "type": "Feature",
  "properties": {
    "iso:country":"US",
    "sg:address":"3479 Union Pacific Ave",
    "sg:city":"Los Angeles",
    "sg:classifiers":[
        {
            "category":"Building & Trades",
            "subcategory":"Electrical",
            "type":"Services"
        }
    ],
    "sg:phone":"+1 323 268 9311",
    "sg:postcode":"90023",
    "sg:province":"CA",
    "sg:tags":[
        "electric",
        "contractor"
    ],
    "sg:website":"www.anthonyelectric.com",
    "wof:name":"Anthony Electric Inc",
    "wof:placetype":"venue"
},
  "geometry": {"coordinates":[-118.20307099999999,34.01663],"type":"Point"}
}