{
  "type": "Feature",
  "properties": {
    "addr:full":"525 N Sepulveda Boulevard El Segundo CA 90245",
    "addr:housenumber":"525",
    "addr:postcode":"90245",
    "addr:street":"N Sepulveda Boulevard",
    "iso:country":"US",
    "sg:address":"525 N Sepulveda Boulevard",
    "sg:city":"El Segundo",
    "sg:classifiers":[
        {
            "category":"Retail",
            "subcategory":"Auto Rental",
            "type":"Services"
        }
    ],
    "sg:phone":"+1 310 640 1560",
    "sg:postcode":"90245",
    "sg:province":"CA",
    "sg:tags":[
        "car"
    ],
    "wof:name":"Discovery Rent A Car",
    "wof:placetype":"venue"
},
  "geometry": {"coordinates":[-118.396461,33.922388],"type":"Point"}
}