{
  "type": "Feature",
  "properties": {
    "iso:country":"US",
    "sg:address":"2855 Telegraph Ave Ste 203",
    "sg:city":"Berkeley",
    "sg:classifiers":[
        {
            "category":"Professional",
            "subcategory":"Lawyer & Legal Services",
            "type":"Services"
        }
    ],
    "sg:phone":"+1 510 473 7373",
    "sg:postcode":"94705",
    "sg:province":"CA",
    "sg:website":"www.smartwills.us",
    "wof:name":"SmartWills",
    "wof:placetype":"venue"
},
  "geometry": {"coordinates":[-122.25881,37.858205],"type":"Point"}
}