{
  "type": "Feature",
  "properties": {
    "iso:country":"US",
    "sg:address":"18054 Saticoy St",
    "sg:city":"Reseda",
    "sg:classifiers":[
        {
            "category":"Restaurant",
            "type":"Food & Drink"
        }
    ],
    "sg:phone":"+1 818 881 4744",
    "sg:postcode":"91335",
    "sg:province":"CA",
    "wof:name":"H Salt Fish & Chips",
    "wof:placetype":"venue"
},
  "geometry": {"coordinates":[-118.52701,34.208319],"type":"Point"}
}