{
  "type": "Feature",
  "properties": {
    "addr:full":"2060 Morlan Dr Napa CA 94558",
    "addr:housenumber":"2060",
    "addr:postcode":"94558",
    "addr:street":"Morlan Dr",
    "iso:country":"US",
    "sg:address":"2060 Morlan Dr",
    "sg:city":"Napa",
    "sg:classifiers":[
        {
            "category":"Communications",
            "subcategory":"Film & Video Production",
            "type":"Services"
        }
    ],
    "sg:phone":"+1 707 257 1472",
    "sg:postcode":"94558",
    "sg:province":"CA",
    "sg:tags":[
        "photographer",
        "aerial"
    ],
    "wof:name":"Quality Aerial Photography",
    "wof:placetype":"venue"
},
  "geometry": {"coordinates":[-122.308978,38.312383],"type":"Point"}
}