{
  "type": "Feature",
  "properties": {
    "addr:full":"14090 State Rte 88 Lockeford CA 95237",
    "addr:housenumber":"14090",
    "addr:postcode":"95237",
    "addr:street":"State Rte 88",
    "iso:country":"US",
    "sg:address":"14090 State Rte 88",
    "sg:city":"Lockeford",
    "sg:classifiers":[
        {
            "category":"Freight",
            "type":"Transportation"
        }
    ],
    "sg:phone":"+1 209 727 0378",
    "sg:postcode":"95237",
    "sg:province":"CA",
    "sg:tags":[
        "trucking"
    ],
    "wof:name":"Mercer Transportation Co",
    "wof:placetype":"venue"
},
  "geometry": {"coordinates":[-121.144862,38.166764],"type":"Point"}
}