{
  "type": "Feature",
  "properties": {
    "addr:full":"149 2nd St San Francisco CA 94105",
    "addr:housenumber":"149",
    "addr:postcode":"94105",
    "addr:street":"2Nd St",
    "iso:country":"US",
    "sg:address":"149 2nd St",
    "sg:city":"San Francisco",
    "sg:classifiers":[
        {
            "category":"Real Estate",
            "subcategory":"Real Estate Agent",
            "type":"Services"
        }
    ],
    "sg:phone":"+1 415 543 3560",
    "sg:postcode":"94105",
    "sg:province":"CA",
    "wof:name":"Malcolm Properties Inc",
    "wof:placetype":"venue"
},
  "geometry": {"coordinates":[-122.398943,37.787467],"type":"Point"}
}