{
  "type": "Feature",
  "properties": {
    "iso:country":"US",
    "sg:address":"293 El Camino Real",
    "sg:city":"Millbrae",
    "sg:classifiers":[
        {
            "category":"Fast Food",
            "type":"Food & Drink"
        },
        {
            "category":"Restaurant",
            "type":"Food & Drink"
        },
        {
            "category":"Food & Beverages",
            "subcategory":"Meat & Fish",
            "type":"Retail Goods"
        }
    ],
    "sg:phone":"+1 650 697 7444",
    "sg:postcode":"94030",
    "sg:province":"CA",
    "sg:tags":[
        "hot",
        "hamburger",
        "dog",
        "british"
    ],
    "wof:name":"Famous Frankfurter",
    "wof:placetype":"venue"
},
  "geometry": {"coordinates":[-122.39099899999999,37.601299],"type":"Point"}
}