{
  "type": "Feature",
  "properties": {
    "addr:full":"21029 Yucca Loma Rd Apple Valley CA 92307",
    "addr:housenumber":"21029",
    "addr:postcode":"92307",
    "addr:street":"Yucca Loma Rd",
    "iso:country":"US",
    "sg:address":"21029 Yucca Loma Rd",
    "sg:city":"Apple Valley",
    "sg:classifiers":[
        {
            "category":"Wholesale",
            "subcategory":"Vending Machines",
            "type":"Manufacturing & Wholesale Goods"
        }
    ],
    "sg:phone":"+1 760 247 6657",
    "sg:postcode":"92307",
    "sg:province":"CA",
    "wof:name":"CNJ Vending",
    "wof:placetype":"venue"
},
  "geometry": {"coordinates":[-117.205023,34.500427],"type":"Point"}
}