{
  "type": "Feature",
  "properties": {
    "addr:full":"15885 Main St Hesperia CA 92345",
    "addr:housenumber":"15885",
    "addr:postcode":"92345",
    "addr:street":"Main St",
    "iso:country":"US",
    "sg:address":"15885 Main St",
    "sg:city":"Hesperia",
    "sg:classifiers":[
        {
            "category":"Building & Trades",
            "subcategory":"Construction",
            "type":"Services"
        }
    ],
    "sg:phone":"+1 760 947 1258",
    "sg:postcode":"92345",
    "sg:province":"CA",
    "sg:tags":[
        "general",
        "contractor"
    ],
    "wof:name":"Fasttrack Construction",
    "wof:placetype":"venue"
},
  "geometry": {"coordinates":[-117.316028,34.423614],"type":"Point"}
}