{
  "type": "Feature",
  "properties": {
    "iso:country":"US",
    "sg:address":"17870 Castleton St",
    "sg:city":"City Of Industry",
    "sg:classifiers":[
        {
            "category":"Professional",
            "subcategory":"Accounting & Tax Preparation",
            "type":"Services"
        }
    ],
    "sg:phone":"+1 626 854 6500",
    "sg:postcode":"91748",
    "sg:province":"CA",
    "sg:tags":[
        "accountant"
    ],
    "wof:name":"Simon Yuan Accountancy Corp",
    "wof:placetype":"venue"
},
  "geometry": {"coordinates":[-117.91935,33.993613],"type":"Point"}
}