{
  "type": "Feature",
  "properties": {
    "iso:country":"US",
    "sg:address":"389 Grove St",
    "sg:city":"San Francisco",
    "sg:classifiers":[
        {
            "category":"Sports & Exercise",
            "subcategory":"Gym",
            "type":"Entertainment"
        }
    ],
    "sg:phone":"+1 619 254 2603",
    "sg:postcode":"94102",
    "sg:province":"CA",
    "sg:tags":[
        "pilate"
    ],
    "sg:website":"pilatesgeek.blogspot.com/",
    "wof:name":"Pilates Geek",
    "wof:placetype":"venue"
},
  "geometry": {"coordinates":[-122.42280700000001,37.777845],"type":"Point"}
}