{
  "type": "Feature",
  "properties": {
    "iso:country":"US",
    "sg:address":"1143 Keith Ave",
    "sg:city":"Berkeley",
    "sg:classifiers":[
        {
            "category":"Professional",
            "subcategory":"Art Services",
            "type":"Services"
        }
    ],
    "sg:phone":"+1 415 252 8644",
    "sg:postcode":"94708",
    "sg:province":"CA",
    "sg:tags":[
        "interior",
        "designer",
        "decorator"
    ],
    "wof:name":"Cristoff Painting & Decorating",
    "wof:placetype":"venue"
},
  "geometry": {"coordinates":[-122.26052900000001,37.889069],"type":"Point"}
}