{
  "type": "Feature",
  "properties": {
    "addr:full":"3133 Fulham Ct Palmdale CA 93551",
    "addr:housenumber":"3133",
    "addr:postcode":"ca 93551",
    "addr:street":"Fulham Ct",
    "iso:country":"US",
    "sg:address":"3133 Fulham Ct",
    "sg:city":"Palmdale",
    "sg:classifiers":[
        {
            "category":"Professional",
            "subcategory":"Advertising",
            "type":"Services"
        }
    ],
    "sg:phone":"+1 661 267 0570",
    "sg:postcode":"93551",
    "sg:province":"CA",
    "sg:tags":[
        "promotion",
        "sale"
    ],
    "wof:name":"Turner Promotions",
    "wof:placetype":"venue"
},
  "geometry": {"coordinates":[-118.186008,34.61587],"type":"Point"}
}