{
  "type": "Feature",
  "properties": {
    "iso:country":"US",
    "sg:address":"1208 N Handy St",
    "sg:city":"Orange",
    "sg:classifiers":[
        {
            "category":"Building & Trades",
            "subcategory":"Construction",
            "type":"Services"
        }
    ],
    "sg:phone":"+1 714 283 4917",
    "sg:postcode":"92867",
    "sg:province":"CA",
    "sg:tags":[
        "contractor"
    ],
    "wof:name":"Koenig Construction",
    "wof:placetype":"venue"
},
  "geometry": {"coordinates":[-117.827073,33.806709],"type":"Point"}
}