{
  "type": "Feature",
  "properties": {
    "iso:country":"US",
    "sg:address":"614 S Main St",
    "sg:city":"Yreka",
    "sg:classifiers":[
        {
            "category":"Shopping",
            "subcategory":"Bicycles & Sporting Goods",
            "type":"Retail Goods"
        }
    ],
    "sg:phone":"+1 530 841 1901",
    "sg:postcode":"96097",
    "sg:province":"CA",
    "wof:name":"Tackle Shop",
    "wof:placetype":"venue"
},
  "geometry": {"coordinates":[-122.63794300000001,41.726472],"type":"Point"}
}