{
  "type": "Feature",
  "properties": {
    "addr:full":"400 34th St Oakland CA 94609",
    "addr:housenumber":"400",
    "addr:postcode":"94609",
    "addr:street":"34Th St",
    "iso:country":"US",
    "sg:address":"400 34th St",
    "sg:city":"Oakland",
    "sg:classifiers":[
        {
            "category":"Shopping",
            "subcategory":"Clothing, Apparel, & Fashions",
            "type":"Retail Goods"
        }
    ],
    "sg:phone":"+1 510 869 8336",
    "sg:postcode":"94609",
    "sg:province":"CA",
    "sg:tags":[
        "work",
        "uniform",
        "clothes"
    ],
    "wof:name":"Volunteers In Uniform",
    "wof:placetype":"venue"
},
  "geometry": {"coordinates":[-122.26299400000001,37.82228],"type":"Point"}
}