{
  "type": "Feature",
  "properties": {
    "iso:country":"US",
    "sg:address":"193 N Moorpark Rd",
    "sg:city":"Thousand Oaks",
    "sg:classifiers":[
        {
            "category":"Home & Garden",
            "subcategory":"Home Furnishings",
            "type":"Retail Goods"
        }
    ],
    "sg:phone":"+1 805 381 1668",
    "sg:postcode":"91360",
    "sg:province":"CA",
    "sg:tags":[
        "linen"
    ],
    "sg:website":"www.lnt.com",
    "wof:name":"Linens 'n Things",
    "wof:placetype":"venue"
},
  "geometry": {"coordinates":[-118.876074,34.180144],"type":"Point"}
}