{
  "type": "Feature",
  "properties": {
    "addr:full":"2600 Ridge Rd Berkeley CA 94709",
    "addr:housenumber":"2600",
    "addr:postcode":"94709",
    "addr:street":"Ridge Rd",
    "iso:country":"US",
    "sg:address":"2600 Ridge Rd",
    "sg:city":"Berkeley",
    "sg:classifiers":[
        {
            "category":"Real Estate",
            "subcategory":"Real Estate Operator",
            "type":"Services"
        },
        {
            "category":"Education",
            "subcategory":"University",
            "type":"Public Place"
        }
    ],
    "sg:phone":"+1 510 849 2480",
    "sg:postcode":"94709",
    "sg:province":"CA",
    "sg:tags":[
        "apartment",
        "college"
    ],
    "sg:website":"www.usca.org/coops/clo.php",
    "wof:name":"Cloyne Court",
    "wof:placetype":"venue"
},
  "geometry": {"coordinates":[-122.258466,37.876253],"type":"Point"}
}