{
  "type": "Feature",
  "properties": {
    "addr:full":"500 Casa del Noyo Fort Bragg CA 95437",
    "addr:housenumber":"500",
    "addr:postcode":"95437",
    "addr:street":"Casa Del Noyo",
    "iso:country":"US",
    "sg:address":"500 Casa del Noyo",
    "sg:city":"Fort Bragg",
    "sg:classifiers":[
        {
            "category":"Travel",
            "subcategory":"Hotels & Motels",
            "type":"Entertainment"
        }
    ],
    "sg:phone":"+1 707 964 8045",
    "sg:postcode":"95437",
    "sg:province":"CA",
    "sg:tags":[
        "breakfast",
        "accommodation",
        "bed"
    ],
    "sg:website":"www.noyolodge.com",
    "wof:name":"Lodge At Noyo River",
    "wof:placetype":"venue"
},
  "geometry": {"coordinates":[-123.802505,39.425104],"type":"Point"}
}