{
  "type": "Feature",
  "properties": {
    "iso:country":"US",
    "sg:address":"1201 W. Lincoln Ave.",
    "sg:city":"Anaheim",
    "sg:classifiers":[
        {
            "category":"Restaurant",
            "type":"Food & Drink"
        }
    ],
    "sg:phone":"+1 714 999 0088",
    "sg:postcode":"92805",
    "sg:province":"CA",
    "sg:tags":[
        "breakfast",
        "mexican",
        "brunch",
        "tex-mex"
    ],
    "sg:website":"lacasagarcia.com/index.htm",
    "wof:name":"La Casa Garcia",
    "wof:placetype":"venue"
},
  "geometry": {"coordinates":[-117.92920100000001,33.832863],"type":"Point"}
}