{
  "type": "Feature",
  "properties": {
    "addr:full":"7784 Magnolia Ave Fair Oaks CA 95628",
    "addr:housenumber":"7784",
    "addr:postcode":"95628",
    "addr:street":"Magnolia Ave",
    "iso:country":"US",
    "sg:address":"7784 Magnolia Ave",
    "sg:city":"Fair Oaks",
    "sg:classifiers":[
        {
            "category":"Professional",
            "subcategory":"Management & Consulting",
            "type":"Services"
        }
    ],
    "sg:phone":"+1 916 961 6150",
    "sg:postcode":"95628",
    "sg:province":"CA",
    "sg:tags":[
        "consultant",
        "wine"
    ],
    "wof:name":"Wine Educators LTD-Pooch",
    "wof:placetype":"venue"
},
  "geometry": {"coordinates":[-121.281041,38.636502],"type":"Point"}
}