{
  "type": "Feature",
  "properties": {
    "addr:full":"1703 Mission Street Santa Cruz CA 95060",
    "addr:housenumber":"1703",
    "addr:postcode":"95060",
    "addr:street":"Mission Street",
    "iso:country":"US",
    "sg:address":"1703 Mission Street",
    "sg:city":"Santa Cruz",
    "sg:classifiers":[
        {
            "category":"Personal",
            "subcategory":"Barber",
            "type":"Services"
        }
    ],
    "sg:phone":"+1 831 426 5579",
    "sg:postcode":"95060",
    "sg:province":"CA",
    "wof:name":"Esquire II Barber Shop",
    "wof:placetype":"venue"
},
  "geometry": {"coordinates":[-122.041348,36.965217],"type":"Point"}
}