{
  "type": "Feature",
  "properties": {
    "iso:country":"US",
    "sg:address":"745 Railroad Ave",
    "sg:city":"Pittsburg",
    "sg:classifiers":[
        {
            "category":"Restaurant",
            "type":"Food & Drink"
        }
    ],
    "sg:phone":"+1 925 473 1245",
    "sg:postcode":"94565",
    "sg:province":"CA",
    "wof:name":"Reynita Restaurant & Taqueria",
    "wof:placetype":"venue"
},
  "geometry": {"coordinates":[-121.884261,38.03004],"type":"Point"}
}