{
  "type": "Feature",
  "properties": {
    "iso:country":"US",
    "sg:address":"1227 Woodrow Ave",
    "sg:city":"Bakersfield",
    "sg:classifiers":[
        {
            "category":"Building & Trades",
            "subcategory":"Plumbing",
            "type":"Services"
        }
    ],
    "sg:phone":"+1 661 393 1926",
    "sg:postcode":"93308",
    "sg:province":"CA",
    "sg:tags":[
        "tank",
        "septic"
    ],
    "wof:name":"KERN County Sewer Plumbing",
    "wof:placetype":"venue"
},
  "geometry": {"coordinates":[-119.04865599999999,35.416291],"type":"Point"}
}