{
  "type": "Feature",
  "properties": {
    "iso:country":"US",
    "sg:address":"731 Central Ave",
    "sg:city":"Alameda",
    "sg:classifiers":[
        {
            "category":"Autos & Motor Vehicles",
            "subcategory":"Boat Sales",
            "type":"Retail Goods"
        }
    ],
    "sg:phone":"+1 510 206 9152",
    "sg:postcode":"94501",
    "sg:province":"CA",
    "sg:tags":[
        "distributor",
        "manufacturer"
    ],
    "sg:website":"http://www.killip.com",
    "wof:name":"Jonathan Killip Co",
    "wof:placetype":"venue"
},
  "geometry": {"coordinates":[-122.275385,37.771393],"type":"Point"}
}