{
  "type": "Feature",
  "properties": {
    "iso:country":"US",
    "sg:address":"1625 Olympic Blvd",
    "sg:city":"Santa Monica",
    "sg:classifiers":[
        {
            "category":"Real Estate",
            "subcategory":"Developer",
            "type":"Services"
        }
    ],
    "sg:phone":"+1 310 399 8990",
    "sg:postcode":"90404",
    "sg:province":"CA",
    "wof:name":"Crescent Bay Land Co",
    "wof:placetype":"venue"
},
  "geometry": {"coordinates":[-118.477604,34.021934],"type":"Point"}
}