{
  "type": "Feature",
  "properties": {
    "addr:full":"3580 California Street Suite 205 San Francisco CA 94118",
    "addr:housenumber":"3580",
    "addr:postcode":"94118",
    "addr:street":"California Street Suite 205",
    "iso:country":"US",
    "sg:address":"3580 California Street Suite 205",
    "sg:city":"San Francisco",
    "sg:classifiers":[
        {
            "category":"Health Services",
            "subcategory":"Health Practitioner",
            "type":"Services"
        }
    ],
    "sg:phone":"+1 415 695 4835",
    "sg:postcode":"94118",
    "sg:province":"CA",
    "sg:tags":[
        "acupuncture"
    ],
    "sg:website":"www.blossominglotusacupuncture.com/",
    "wof:name":"Blossoming Lotus Acupuncture",
    "wof:placetype":"venue"
},
  "geometry": {"coordinates":[-122.453112,37.786863],"type":"Point"}
}