{
  "type": "Feature",
  "properties": {
    "iso:country":"US",
    "sg:address":"3600 16th St",
    "sg:city":"San Francisco",
    "sg:classifiers":[
        {
            "category":"Bars & Pubs",
            "type":"Food & Drink"
        },
        {
            "category":"Restaurant",
            "type":"Food & Drink"
        }
    ],
    "sg:phone":"+1 415 431 3111",
    "sg:postcode":"94114",
    "sg:province":"CA",
    "sg:tags":[
        "pizza"
    ],
    "sg:website":"www.lookoutsf.com",
    "wof:name":"Thick and Thin Pizza",
    "wof:placetype":"venue"
},
  "geometry": {"coordinates":[-122.433199,37.764232],"type":"Point"}
}