{
  "type": "Feature",
  "properties": {
    "addr:full":"14358 Ipava Dr Poway CA 92064",
    "addr:housenumber":"14358",
    "addr:postcode":"ca 92064",
    "addr:street":"Ipava Dr",
    "iso:country":"US",
    "sg:address":"14358 Ipava Dr",
    "sg:city":"Poway",
    "sg:classifiers":[
        {
            "category":"Wholesale",
            "subcategory":"Vending Machines",
            "type":"Manufacturing & Wholesale Goods"
        }
    ],
    "sg:phone":"+1 858 748 5297",
    "sg:postcode":"92064",
    "sg:province":"CA",
    "sg:tags":[
        "operator"
    ],
    "wof:name":"Nelson Vending",
    "wof:placetype":"venue"
},
  "geometry": {"coordinates":[-117.022735,32.965017],"type":"Point"}
}