{
  "type": "Feature",
  "properties": {
    "addr:full":"505 14th St Ste 950 Oakland CA 94612",
    "addr:housenumber":"505",
    "addr:postcode":"94612",
    "addr:street":"14Th St Ste 950",
    "iso:country":"US",
    "sg:address":"505 14th St Ste 950",
    "sg:city":"Oakland",
    "sg:classifiers":[
        {
            "category":"Professional",
            "subcategory":"Accounting & Tax Preparation",
            "type":"Services"
        }
    ],
    "sg:phone":"+1 510 832 0257",
    "sg:postcode":"94612",
    "sg:province":"CA",
    "sg:tags":[
        "accountant"
    ],
    "wof:name":"Grant & Smith Llp",
    "wof:placetype":"venue"
},
  "geometry": {"coordinates":[-122.273003,37.804901],"type":"Point"}
}