{
  "type": "Feature",
  "properties": {
    "addr:full":"2121 Market Street San Francisco CA 94114",
    "addr:housenumber":"2121",
    "addr:postcode":"94114",
    "addr:street":"Market Street",
    "iso:country":"US",
    "sg:address":"2121 Market Street",
    "sg:city":"San Francisco",
    "sg:classifiers":[
        {
            "category":"Arts & Performance",
            "subcategory":"Arts Center",
            "type":"Entertainment"
        },
        {
            "category":"Sports & Exercise",
            "subcategory":"Playing Field",
            "type":"Entertainment"
        }
    ],
    "sg:phone":"+1 415 552 1166",
    "sg:postcode":"94114",
    "sg:province":"CA",
    "sg:tags":[
        "performing",
        "instruction",
        "fitness"
    ],
    "sg:website":"www.chamberdancesf.org/academy/",
    "wof:name":"Academy of Ballet",
    "wof:placetype":"venue"
},
  "geometry": {"coordinates":[-122.429001,37.766899],"type":"Point"}
}