{
  "type": "Feature",
  "properties": {
    "iso:country":"US",
    "sg:address":"3562 Broadway St",
    "sg:city":"Eureka",
    "sg:classifiers":[
        {
            "category":"Real Estate",
            "subcategory":"Real Estate Agent",
            "type":"Services"
        }
    ],
    "sg:phone":"+1 707 476 9474",
    "sg:postcode":"95503",
    "sg:province":"CA",
    "wof:name":"Help U Sell Eureka Properties",
    "wof:placetype":"venue"
},
  "geometry": {"coordinates":[-124.190659,40.774544],"type":"Point"}
}