{
  "type": "Feature",
  "properties": {
    "addr:full":"10842 S Harlan Rd French Camp CA 95231",
    "addr:housenumber":"10842",
    "addr:postcode":"95231",
    "addr:street":"S Harlan Rd",
    "iso:country":"US",
    "sg:address":"10842 S Harlan Rd",
    "sg:city":"French Camp",
    "sg:classifiers":[
        {
            "category":"Freight",
            "type":"Transportation"
        }
    ],
    "sg:phone":"+1 209 858 4138",
    "sg:postcode":"95231",
    "sg:province":"CA",
    "sg:tags":[
        "specializing",
        "int",
        "storage",
        "trucking",
        "without",
        "interstate"
    ],
    "wof:name":"Devine Intermodal",
    "wof:placetype":"venue"
},
  "geometry": {"coordinates":[-121.27982,37.861945],"type":"Point"}
}