{
  "type": "Feature",
  "properties": {
    "addr:full":"6831 Hollister Ave Goleta CA 93117",
    "addr:housenumber":"6831",
    "addr:postcode":"93117",
    "addr:street":"Hollister Ave",
    "iso:country":"US",
    "sg:address":"6831 Hollister Ave",
    "sg:city":"Goleta",
    "sg:classifiers":[
        {
            "category":"Food & Beverages",
            "subcategory":"Groceries & Convenience Stores",
            "type":"Retail Goods"
        }
    ],
    "sg:phone":"+1 805 968 3353",
    "sg:postcode":"93117",
    "sg:province":"CA",
    "sg:tags":[
        "market"
    ],
    "wof:name":"Indo-China Market",
    "wof:placetype":"venue"
},
  "geometry": {"coordinates":[-119.862776,34.430162],"type":"Point"}
}