{
  "type": "Feature",
  "properties": {
    "iso:country":"US",
    "sg:address":"1001 Page Street",
    "sg:city":"San Francisco",
    "sg:classifiers":[
        {
            "category":"Food & Beverages",
            "subcategory":"Groceries & Convenience Stores",
            "type":"Retail Goods"
        }
    ],
    "sg:phone":"+1 415 864 6811",
    "sg:postcode":"94117",
    "sg:province":"CA",
    "wof:name":"Michael's Pit Stop",
    "wof:placetype":"venue"
},
  "geometry": {"coordinates":[-122.43699599999999,37.772301],"type":"Point"}
}