{
  "type": "Feature",
  "properties": {
    "addr:full":"714 E Magnolia Blvd Ste C Burbank CA 91501",
    "addr:housenumber":"714",
    "addr:postcode":"91501",
    "addr:street":"E Magnolia Blvd Ste C",
    "iso:country":"US",
    "sg:address":"714 E Magnolia Blvd Ste C",
    "sg:city":"Burbank",
    "sg:classifiers":[
        {
            "category":"Building & Trades",
            "subcategory":"Cleaning & Sanitation",
            "type":"Services"
        }
    ],
    "sg:phone":"+1 818 843 5526",
    "sg:postcode":"91501",
    "sg:province":"CA",
    "sg:tags":[
        "cleaner",
        "pool"
    ],
    "sg:website":"www.poolexpertsofca.com",
    "wof:name":"Dale's Pool Service",
    "wof:placetype":"venue"
},
  "geometry": {"coordinates":[-118.30483,34.18907],"type":"Point"}
}