{
  "type": "Feature",
  "properties": {
    "iso:country":"US",
    "sg:address":"1000 Broadway",
    "sg:city":"Oakland",
    "sg:classifiers":[
        {
            "category":"Building & Trades",
            "subcategory":"Construction",
            "type":"Services"
        }
    ],
    "sg:phone":"+1 510 465 9138",
    "sg:postcode":"94607",
    "sg:province":"CA",
    "sg:tags":[
        "nonresidential"
    ],
    "wof:name":"Centex",
    "wof:placetype":"venue"
},
  "geometry": {"coordinates":[-122.272535,37.802292],"type":"Point"}
}