{
  "type": "Feature",
  "properties": {
    "addr:full":"4800 W 120th Street Hawthorne CA 90250",
    "addr:housenumber":"4800",
    "addr:postcode":"90250",
    "addr:street":"W 120Th Street",
    "iso:country":"US",
    "sg:address":"4800 W 120th Street",
    "sg:city":"Hawthorne",
    "sg:classifiers":[
        {
            "category":"Food & Beverages",
            "subcategory":"Groceries & Convenience Stores",
            "type":"Retail Goods"
        }
    ],
    "sg:phone":"+1 310 675 4779",
    "sg:postcode":"90250",
    "sg:province":"CA",
    "wof:name":"7-Eleven Food Stores",
    "wof:placetype":"venue"
},
  "geometry": {"coordinates":[-118.361367,33.923807],"type":"Point"}
}