{
  "type": "Feature",
  "properties": {
    "addr:full":"5953 Penfield Ave Woodland Hills CA 91367",
    "addr:housenumber":"5953",
    "addr:postcode":"91367",
    "addr:street":"Penfield Ave",
    "iso:country":"US",
    "sg:address":"5953 Penfield Ave",
    "sg:city":"Woodland Hills",
    "sg:classifiers":[
        {
            "category":"Professional",
            "subcategory":"Lawyer & Legal Services",
            "type":"Services"
        }
    ],
    "sg:phone":"+1 818 884 3778",
    "sg:postcode":"91367",
    "sg:province":"CA",
    "wof:name":"Esperanza Interpreters",
    "wof:placetype":"venue"
},
  "geometry": {"coordinates":[-118.56910000000001,34.179095],"type":"Point"}
}