{
  "type": "Feature",
  "properties": {
    "iso:country":"US",
    "sg:address":"1221 E 1st St Ste A",
    "sg:city":"Santa Ana",
    "sg:classifiers":[
        {
            "category":"Health Services",
            "subcategory":"Dentist",
            "type":"Services"
        }
    ],
    "sg:phone":"+1 714 285 1221",
    "sg:postcode":"92701",
    "sg:province":"CA",
    "sg:tags":[
        "orthodontist"
    ],
    "wof:name":"Beauchamp Dr-Western Dental Centers",
    "wof:placetype":"venue"
},
  "geometry": {"coordinates":[-117.852997,33.745499],"type":"Point"}
}