{
  "type": "Feature",
  "properties": {
    "iso:country":"US",
    "sg:address":"937 Lincoln St",
    "sg:city":"Watsonville",
    "sg:classifiers":[
        {
            "category":"Personal",
            "subcategory":"Beauty Salon",
            "type":"Services"
        }
    ],
    "sg:phone":"+1 831 722 6212",
    "sg:postcode":"95076",
    "sg:province":"CA",
    "wof:name":"Luna Beauty Salon",
    "wof:placetype":"venue"
},
  "geometry": {"coordinates":[-121.75767500000001,36.919376],"type":"Point"}
}