{
  "type": "Feature",
  "properties": {
    "iso:country":"US",
    "sg:address":"1000 N 10th Ave",
    "sg:city":"Hanford",
    "sg:classifiers":[
        {
            "category":"Food & Beverages",
            "subcategory":"Bakery",
            "type":"Retail Goods"
        }
    ],
    "sg:phone":"+1 559 584 9020",
    "sg:postcode":"93230",
    "sg:province":"CA",
    "sg:tags":[
        "doughnut"
    ],
    "wof:name":"Donut King",
    "wof:placetype":"venue"
},
  "geometry": {"coordinates":[-119.637003,36.334928],"type":"Point"}
}