{
  "type": "Feature",
  "properties": {
    "iso:country":"US",
    "sg:address":"11109 Emelita St",
    "sg:city":"North Hollywood",
    "sg:classifiers":[
        {
            "category":"Education",
            "subcategory":"Special Training",
            "type":"Public Place"
        }
    ],
    "sg:phone":"+1 818 508 6843",
    "sg:postcode":"91601",
    "sg:province":"CA",
    "sg:tags":[
        "school",
        "language"
    ],
    "wof:name":"Language Unlimited",
    "wof:placetype":"venue"
},
  "geometry": {"coordinates":[-118.37315099999999,34.176828],"type":"Point"}
}