{
  "type": "Feature",
  "properties": {
    "addr:full":"12137 Industrial Blvd Victorville CA 92395",
    "addr:housenumber":"12137",
    "addr:postcode":"92395",
    "addr:street":"Industrial Blvd",
    "iso:country":"US",
    "sg:address":"12137 Industrial Blvd",
    "sg:city":"Victorville",
    "sg:classifiers":[
        {
            "category":"Manufacturing",
            "subcategory":"Tools & Machinery",
            "type":"Manufacturing & Wholesale Goods"
        },
        {
            "category":"Wholesale",
            "subcategory":"Electrical",
            "type":"Manufacturing & Wholesale Goods"
        }
    ],
    "sg:phone":"+1 760 241 7443",
    "sg:postcode":"92395",
    "sg:province":"CA",
    "sg:tags":[
        "equipment",
        "manufacturer",
        "supplies-wholesale",
        "electric",
        "supply"
    ],
    "sg:website":"http://www.ced-aec.com",
    "wof:name":"C E D",
    "wof:placetype":"venue"
},
  "geometry": {"coordinates":[-117.282894,34.471764],"type":"Point"}
}