{
  "type": "Feature",
  "properties": {
    "addr:full":"18657 Boulder Dr Redding CA 96003",
    "addr:housenumber":"18657",
    "addr:postcode":"96003",
    "addr:street":"Boulder Dr",
    "iso:country":"US",
    "sg:address":"18657 Boulder Dr",
    "sg:city":"Redding",
    "sg:classifiers":[
        {
            "category":"Freight",
            "type":"Transportation"
        }
    ],
    "sg:phone":"+1 530 245 9141",
    "sg:postcode":"96003",
    "sg:province":"CA",
    "sg:tags":[
        "commercial",
        "storage"
    ],
    "wof:name":"A-1 Stor-It Ctr",
    "wof:placetype":"venue"
},
  "geometry": {"coordinates":[-122.369955,40.610707],"type":"Point"}
}