{
  "type": "Feature",
  "properties": {
    "addr:full":"5685 Riverside Dr Ste E Chino CA 91710",
    "addr:housenumber":"5685",
    "addr:postcode":"91710",
    "addr:street":"Riverside Dr Ste E",
    "iso:country":"US",
    "sg:address":"5685 Riverside Dr Ste E",
    "sg:city":"Chino",
    "sg:classifiers":[
        {
            "category":"Personal",
            "subcategory":"Beauty Salon",
            "type":"Services"
        }
    ],
    "sg:phone":"+1 909 628 0292",
    "sg:postcode":"91710",
    "sg:province":"CA",
    "sg:tags":[
        "hair",
        "stylist"
    ],
    "wof:name":"Blowout Beauty Salon",
    "wof:placetype":"venue"
},
  "geometry": {"coordinates":[-117.680941,34.019127],"type":"Point"}
}