{
  "type": "Feature",
  "properties": {
    "iso:country":"US",
    "sg:address":"900 Laguna St",
    "sg:city":"San Francisco",
    "sg:classifiers":[
        {
            "category":"Banks & Credit Unions",
            "subcategory":"Bank",
            "type":"Services"
        }
    ],
    "sg:phone":"+1 415 354 5665",
    "sg:postcode":"94115",
    "sg:province":"CA",
    "wof:name":"United Trust & Savings",
    "wof:placetype":"venue"
},
  "geometry": {"coordinates":[-122.42665,37.779289],"type":"Point"}
}