{
  "type": "Feature",
  "properties": {
    "addr:full":"4152 Puente Ave Baldwin Park CA 91706",
    "addr:housenumber":"4152",
    "addr:postcode":"91706",
    "addr:street":"Puente Ave",
    "iso:country":"US",
    "sg:address":"4152 Puente Ave",
    "sg:city":"Baldwin Park",
    "sg:classifiers":[
        {
            "category":"Retail",
            "subcategory":"Auto Repair",
            "type":"Services"
        }
    ],
    "sg:phone":"+1 626 337 4614",
    "sg:postcode":"91706",
    "sg:province":"CA",
    "sg:tags":[
        "repairing",
        "automobile"
    ],
    "wof:name":"Engine Dynamics",
    "wof:placetype":"venue"
},
  "geometry": {"coordinates":[-117.949291,34.088988],"type":"Point"}
}