{
  "type": "Feature",
  "properties": {
    "addr:full":"2089 Touraine Ln Half Moon Bay CA 94019",
    "addr:housenumber":"2089",
    "addr:postcode":"94019",
    "addr:street":"Touraine Ln",
    "iso:country":"US",
    "sg:address":"2089 Touraine Ln",
    "sg:city":"Half Moon Bay",
    "sg:classifiers":[
        {
            "category":"Professional",
            "subcategory":"Detective & Security Services",
            "type":"Services"
        }
    ],
    "sg:phone":"+1 650 712 1302",
    "sg:postcode":"94019",
    "sg:province":"CA",
    "sg:tags":[
        "sensor"
    ],
    "wof:name":"RF Trax Inc",
    "wof:placetype":"venue"
},
  "geometry": {"coordinates":[-122.44204999999999,37.485324],"type":"Point"}
}