{
  "type": "Feature",
  "properties": {
    "iso:country":"US",
    "sg:address":"1955 Landings Drive",
    "sg:city":"Mountain View",
    "sg:classifiers":[
        {
            "category":"Professional",
            "subcategory":"Computer Services",
            "type":"Services"
        }
    ],
    "sg:postcode":"94043",
    "sg:province":"CA",
    "sg:tags":[
        "online-market-research",
        "audience-demographics",
        "online-ad-campaign-effectiveness",
        "free-online-tools"
    ],
    "sg:website":"http://www.crowdscience.com/",
    "wof:name":"Crowd Science",
    "wof:placetype":"venue"
},
  "geometry": {"coordinates":[-122.091183,37.421152],"type":"Point"}
}