{
  "type": "Feature",
  "properties": {
    "iso:country":"US",
    "sg:address":"6545 Mission Gorge Rd",
    "sg:city":"San Diego",
    "sg:classifiers":[
        {
            "category":"Personal",
            "subcategory":"Beauty Salon",
            "type":"Services"
        }
    ],
    "sg:phone":"+1 619 624 0212",
    "sg:postcode":"92120",
    "sg:province":"CA",
    "sg:tags":[
        "manicuring"
    ],
    "wof:name":"Lily's Nails",
    "wof:placetype":"venue"
},
  "geometry": {"coordinates":[-117.09767,32.791097],"type":"Point"}
}