{
  "type": "Feature",
  "properties": {
    "iso:country":"US",
    "sg:address":"104 Bronson St",
    "sg:city":"Santa Cruz",
    "sg:classifiers":[
        {
            "category":"Professional",
            "type":"Services"
        }
    ],
    "sg:phone":"+1 831 423 2296",
    "sg:postcode":"95062",
    "sg:province":"CA",
    "sg:tags":[
        "establishment"
    ],
    "wof:name":"Parts Drop",
    "wof:placetype":"venue"
},
  "geometry": {"coordinates":[-122.006685,36.96878],"type":"Point"}
}