{
  "type": "Feature",
  "properties": {
    "iso:country":"US",
    "sg:address":"9279 D St",
    "sg:city":"Oakland",
    "sg:classifiers":[
        {
            "category":"Retail",
            "subcategory":"Auto Repair",
            "type":"Services"
        }
    ],
    "sg:phone":"+1 510 430 8968",
    "sg:postcode":"94603",
    "sg:province":"CA",
    "sg:tags":[
        "wrecker"
    ],
    "wof:name":"Ruiz Towing",
    "wof:placetype":"venue"
},
  "geometry": {"coordinates":[-122.177265,37.744023],"type":"Point"}
}