{
  "type": "Feature",
  "properties": {
    "iso:country":"US",
    "sg:address":"451 S Main Street",
    "sg:city":"Los Angeles",
    "sg:classifiers":[
        {
            "category":"Travel",
            "subcategory":"Hotels & Motels",
            "type":"Entertainment"
        },
        {
            "category":"Real Estate",
            "subcategory":"Real Estate Operator",
            "type":"Services"
        }
    ],
    "sg:phone":"+1 213 503 6171",
    "sg:postcode":"90013",
    "sg:province":"CA",
    "sg:tags":[
        "house",
        "apartment",
        "guest"
    ],
    "sg:website":"www.rosslynlofts.net",
    "wof:name":"Rosslyn Lofts",
    "wof:placetype":"venue"
},
  "geometry": {"coordinates":[-118.248238,34.047042],"type":"Point"}
}