{
  "type": "Feature",
  "properties": {
    "iso:country":"US",
    "sg:address":"2523 Foothill Blvd",
    "sg:city":"La Crescenta",
    "sg:classifiers":[
        {
            "category":"Shopping",
            "subcategory":"Florist",
            "type":"Retail Goods"
        }
    ],
    "sg:phone":"+1 818 248 2599",
    "sg:postcode":"91214",
    "sg:province":"CA",
    "wof:name":"Jasmine's Flowers & Gifts",
    "wof:placetype":"venue"
},
  "geometry": {"coordinates":[-118.233227,34.220103],"type":"Point"}
}