{
  "type": "Feature",
  "properties": {
    "addr:full":"413 Miramontes Ave Half Moon Bay CA 94019",
    "addr:housenumber":"413",
    "addr:postcode":"94019",
    "addr:street":"Miramontes Ave",
    "iso:country":"US",
    "sg:address":"413 Miramontes Ave",
    "sg:city":"Half Moon Bay",
    "sg:classifiers":[
        {
            "category":"Social Services",
            "subcategory":"Child Care",
            "type":"Services"
        }
    ],
    "sg:phone":"+1 650 726 8170",
    "sg:postcode":"94019",
    "sg:province":"CA",
    "sg:tags":[
        "kindergarten",
        "academic",
        "school"
    ],
    "wof:name":"Mommy & Me Nontessori",
    "wof:placetype":"venue"
},
  "geometry": {"coordinates":[-122.436509,37.463428],"type":"Point"}
}