{
  "type": "Feature",
  "properties": {
    "addr:full":"4263 Taylor St San Diego CA 92110",
    "addr:housenumber":"4263",
    "addr:postcode":"92110",
    "addr:street":"Taylor St",
    "iso:country":"US",
    "sg:address":"4263 Taylor St",
    "sg:city":"San Diego",
    "sg:classifiers":[
        {
            "category":"Building & Trades",
            "subcategory":"Plumbing",
            "type":"Services"
        }
    ],
    "sg:phone":"+1 619 295 7200",
    "sg:postcode":"92110",
    "sg:province":"CA",
    "sg:tags":[
        "plumbing",
        "contractor"
    ],
    "wof:name":"M R Aron Co Inc",
    "wof:placetype":"venue"
},
  "geometry": {"coordinates":[-117.198497,32.756755],"type":"Point"}
}