{
  "type": "Feature",
  "properties": {
    "iso:country":"US",
    "sg:address":"1 Scripps Dr",
    "sg:city":"Sacramento",
    "sg:classifiers":[
        {
            "category":"Health Services",
            "subcategory":"Doctor",
            "type":"Services"
        }
    ],
    "sg:phone":"+1 916 920 0871",
    "sg:postcode":"95825",
    "sg:province":"CA",
    "sg:tags":[
        "physician",
        "surgeon"
    ],
    "wof:name":"Silverstein & Braunstein",
    "wof:placetype":"venue"
},
  "geometry": {"coordinates":[-121.41172299999999,38.572792],"type":"Point"}
}