{
  "type": "Feature",
  "properties": {
    "iso:country":"US",
    "sg:address":"1260 Alice St",
    "sg:city":"Woodland",
    "sg:classifiers":[
        {
            "category":"Wholesale",
            "subcategory":"Construction Materials",
            "type":"Manufacturing & Wholesale Goods"
        }
    ],
    "sg:phone":"+1 530 666 0309",
    "sg:postcode":"95776",
    "sg:province":"CA",
    "sg:tags":[
        "special",
        "g"
    ],
    "wof:name":"Woodland Mini Storage",
    "wof:placetype":"venue"
},
  "geometry": {"coordinates":[-121.763909,38.675243],"type":"Point"}
}