{
  "type": "Feature",
  "properties": {
    "iso:country":"US",
    "sg:address":"24881 State Highway 74",
    "sg:city":"Perris",
    "sg:classifiers":[
        {
            "category":"Food & Beverages",
            "subcategory":"Groceries & Convenience Stores",
            "type":"Retail Goods"
        }
    ],
    "sg:phone":"+1 951 657 0622",
    "sg:postcode":"92570",
    "sg:province":"CA",
    "wof:name":"Caesar Liquor Market",
    "wof:placetype":"venue"
},
  "geometry": {"coordinates":[-117.266998,33.761101],"type":"Point"}
}