{
  "type": "Feature",
  "properties": {
    "addr:full":"9701 Artesia Blvd Bellflower CA 90706",
    "addr:housenumber":"9701",
    "addr:postcode":"90706",
    "addr:street":"Artesia Blvd",
    "iso:country":"US",
    "sg:address":"9701 Artesia Blvd",
    "sg:city":"Bellflower",
    "sg:classifiers":[
        {
            "category":"Personal",
            "subcategory":"Beauty Salon",
            "type":"Services"
        }
    ],
    "sg:phone":"+1 562 867 6936",
    "sg:postcode":"90706",
    "sg:province":"CA",
    "sg:tags":[
        "hair",
        "stylist"
    ],
    "sg:website":"http://mercuryhairsalon.com",
    "wof:name":"Mercuryhairsalon",
    "wof:placetype":"venue"
},
  "geometry": {"coordinates":[-118.125902,33.874888],"type":"Point"}
}