{
  "type": "Feature",
  "properties": {
    "iso:country":"US",
    "sg:address":"1705 San Miguelito Rd",
    "sg:city":"Lompoc",
    "sg:classifiers":[
        {
            "category":"Wholesale",
            "subcategory":"Machinery & Supplies",
            "type":"Manufacturing & Wholesale Goods"
        }
    ],
    "sg:phone":"+1 805 934 0404",
    "sg:postcode":"93436",
    "sg:province":"CA",
    "sg:tags":[
        "carpet",
        "cleaning",
        "rug"
    ],
    "sg:website":"www.centralcoastmold.com",
    "wof:name":"Central Coast Mold Inspection",
    "wof:placetype":"venue"
},
  "geometry": {"coordinates":[-120.464114,34.608373],"type":"Point"}
}