{
  "type": "Feature",
  "properties": {
    "iso:country":"US",
    "sg:address":"20460 Carrey Rd",
    "sg:city":"Walnut",
    "sg:classifiers":[
        {
            "category":"Shopping",
            "subcategory":"Stationery & Office Supplies",
            "type":"Retail Goods"
        }
    ],
    "sg:phone":"+1 909 468 0132",
    "sg:postcode":"91789",
    "sg:province":"CA",
    "sg:tags":[
        "stationer"
    ],
    "sg:website":"www.buyoverseas.net",
    "wof:name":"Idea International Inc",
    "wof:placetype":"venue"
},
  "geometry": {"coordinates":[-117.858563,34.015261],"type":"Point"}
}