{
  "type": "Feature",
  "properties": {
    "addr:full":"9676 Las Tunas Dr Temple City CA 91780",
    "addr:housenumber":"9676",
    "addr:postcode":"91780",
    "addr:street":"Las Tunas Dr",
    "iso:country":"US",
    "sg:address":"9676 Las Tunas Dr",
    "sg:city":"Temple City",
    "sg:classifiers":[
        {
            "category":"Health Services",
            "subcategory":"Doctor",
            "type":"Services"
        }
    ],
    "sg:phone":"+1 626 286 6680",
    "sg:postcode":"91780",
    "sg:province":"CA",
    "sg:tags":[
        "surgeon",
        "oral"
    ],
    "wof:name":"Cuccia Brandon DDS",
    "wof:placetype":"venue"
},
  "geometry": {"coordinates":[-118.057999,34.106998],"type":"Point"}
}