{
  "type": "Feature",
  "properties": {
    "addr:full":"1870 Bali Way Santa Cruz CA 95062",
    "addr:housenumber":"1870",
    "addr:postcode":"95062",
    "addr:street":"Bali Way",
    "iso:country":"US",
    "sg:address":"1870 Bali Way",
    "sg:city":"Santa Cruz",
    "sg:classifiers":[
        {
            "category":"Communications",
            "subcategory":"Film & Video Production",
            "type":"Services"
        }
    ],
    "sg:phone":"+1 831 234 7111",
    "sg:postcode":"95062",
    "sg:province":"CA",
    "sg:tags":[
        "taping"
    ],
    "wof:name":"Newtype Productions",
    "wof:placetype":"venue"
},
  "geometry": {"coordinates":[-121.979508,36.982273],"type":"Point"}
}