{
  "type": "Feature",
  "properties": {
    "addr:full":"104 W 6th St Hanford CA 93230",
    "addr:housenumber":"104",
    "addr:postcode":"ca 93230",
    "addr:street":"W 6Th St",
    "iso:country":"US",
    "sg:address":"104 W 6th St",
    "sg:city":"Hanford",
    "sg:classifiers":[
        {
            "category":"Bars & Pubs",
            "type":"Food & Drink"
        }
    ],
    "sg:phone":"+1 559 583 6588",
    "sg:postcode":"93230",
    "sg:province":"CA",
    "sg:tags":[
        "club",
        "night"
    ],
    "wof:name":"California Club",
    "wof:placetype":"venue"
},
  "geometry": {"coordinates":[-119.645499,36.325594],"type":"Point"}
}