{
  "type": "Feature",
  "properties": {
    "addr:full":"5678 Bandini Blvd Bell CA 90201",
    "addr:housenumber":"5678",
    "addr:postcode":"90201",
    "addr:street":"Bandini Blvd",
    "iso:country":"US",
    "sg:address":"5678 Bandini Blvd",
    "sg:city":"Bell",
    "sg:classifiers":[
        {
            "category":"Wholesale",
            "subcategory":"Durable Goods & Equipment",
            "type":"Manufacturing & Wholesale Goods"
        }
    ],
    "sg:phone":"+1 323 780 3224",
    "sg:postcode":"90201",
    "sg:province":"CA",
    "sg:tags":[
        "importer"
    ],
    "sg:website":"www.wingar.com",
    "wof:name":"Wingar Industrial Inc",
    "wof:placetype":"venue"
},
  "geometry": {"coordinates":[-118.16182000000001,33.992658],"type":"Point"}
}