{
  "type": "Feature",
  "properties": {
    "addr:full":"13 Jolley Way Scotts Valley CA 95066",
    "addr:housenumber":"13",
    "addr:postcode":"95066",
    "addr:street":"Jolley Way",
    "iso:country":"US",
    "sg:address":"13 Jolley Way",
    "sg:city":"Scotts Valley",
    "sg:classifiers":[
        {
            "category":"Professional",
            "type":"Services"
        }
    ],
    "sg:phone":"+1 831 438 7630",
    "sg:postcode":"95066",
    "sg:province":"CA",
    "wof:name":"Birds Eye View",
    "wof:placetype":"venue"
},
  "geometry": {"coordinates":[-122.022246,37.046503],"type":"Point"}
}