{
  "type": "Feature",
  "properties": {
    "iso:country":"US",
    "sg:address":"753 S Saint John Ave",
    "sg:city":"Pasadena",
    "sg:classifiers":[
        {
            "category":"Building & Trades",
            "subcategory":"Construction",
            "type":"Services"
        }
    ],
    "sg:phone":"+1 626 799 4448",
    "sg:postcode":"91105",
    "sg:province":"CA",
    "sg:tags":[
        "contractor"
    ],
    "wof:name":"Key Enterprises",
    "wof:placetype":"venue"
},
  "geometry": {"coordinates":[-118.155576,34.131871],"type":"Point"}
}