{
  "type": "Feature",
  "properties": {
    "addr:full":"5929 Nina Ct Riverside CA 92509",
    "addr:housenumber":"5929",
    "addr:postcode":"92509",
    "addr:street":"Nina Ct",
    "iso:country":"US",
    "sg:address":"5929 Nina Ct",
    "sg:city":"Riverside",
    "sg:classifiers":[
        {
            "category":"Manufacturing",
            "subcategory":"Chemicals & Compounds",
            "type":"Manufacturing & Wholesale Goods"
        }
    ],
    "sg:phone":"+1 951 681 0977",
    "sg:postcode":"92509",
    "sg:province":"CA",
    "sg:tags":[
        "pesticide",
        "ag"
    ],
    "wof:name":"Earth Products",
    "wof:placetype":"venue"
},
  "geometry": {"coordinates":[-117.456416,33.979873],"type":"Point"}
}