{
  "type": "Feature",
  "properties": {
    "iso:country":"US",
    "sg:address":"6555 Balboa Ave",
    "sg:city":"San Diego",
    "sg:classifiers":[
        {
            "category":"Organizations",
            "subcategory":"Religious Organization",
            "type":"Services"
        }
    ],
    "sg:phone":"+1 858 278 6266",
    "sg:postcode":"92117",
    "sg:province":"CA",
    "sg:tags":[
        "church"
    ],
    "wof:name":"Balboa Community Church",
    "wof:placetype":"venue"
},
  "geometry": {"coordinates":[-117.171512,32.820289],"type":"Point"}
}