{
  "type": "Feature",
  "properties": {
    "addr:full":"4811 Myrtle Avenue suite 300 Sacramento CA 95841",
    "addr:housenumber":"4811",
    "addr:postcode":"95841",
    "addr:street":"Myrtle Avenue Suite 300",
    "iso:country":"US",
    "sg:address":"4811 Myrtle Avenue suite 300",
    "sg:city":"Sacramento",
    "sg:classifiers":[
        {
            "category":"Professional",
            "subcategory":"Business Services",
            "type":"Services"
        }
    ],
    "sg:phone":"+1 800 306 4032",
    "sg:postcode":"95841",
    "sg:province":"CA",
    "sg:tags":[
        "delivery",
        "courier"
    ],
    "sg:website":"www.dimensionmoving.com",
    "wof:name":"Dimension Moving",
    "wof:placetype":"venue"
},
  "geometry": {"coordinates":[-121.35250499999999,38.653901],"type":"Point"}
}