{
  "type": "Feature",
  "properties": {
    "addr:full":"1417 Foxworthy Avenue San Jose CA 95118",
    "addr:housenumber":"1417",
    "addr:postcode":"95118",
    "addr:street":"Foxworthy Avenue",
    "iso:country":"US",
    "sg:address":"1417 Foxworthy Avenue",
    "sg:city":"San Jose",
    "sg:classifiers":[
        {
            "category":"Food & Beverages",
            "subcategory":"Liquor & Beverages",
            "type":"Retail Goods"
        }
    ],
    "sg:phone":"+1 408 266 9700",
    "sg:postcode":"95118",
    "sg:province":"CA",
    "sg:tags":[
        "beer",
        "spirit",
        "wine"
    ],
    "wof:name":"Foxworthy Liquors",
    "wof:placetype":"venue"
},
  "geometry": {"coordinates":[-121.89165800000001,37.271023],"type":"Point"}
}