{
  "type": "Feature",
  "properties": {
    "iso:country":"US",
    "sg:address":"816 Chicago Ave",
    "sg:city":"Modesto",
    "sg:classifiers":[
        {
            "category":"Building & Trades",
            "subcategory":"Cleaning & Sanitation",
            "type":"Services"
        }
    ],
    "sg:phone":"+1 209 551 4609",
    "sg:postcode":"95351",
    "sg:province":"CA",
    "sg:tags":[
        "window"
    ],
    "wof:name":"Carson's Window Cleaning",
    "wof:placetype":"venue"
},
  "geometry": {"coordinates":[-121.018062,37.625903],"type":"Point"}
}