{
  "type": "Feature",
  "properties": {
    "addr:full":"940 Ramona Ave Grover Beach CA 93433",
    "addr:housenumber":"940",
    "addr:postcode":"93433",
    "addr:street":"Ramona Ave",
    "iso:country":"US",
    "sg:address":"940 Ramona Ave",
    "sg:city":"Grover Beach",
    "sg:classifiers":[
        {
            "category":"Professional",
            "subcategory":"Lawyer & Legal Services",
            "type":"Services"
        }
    ],
    "sg:phone":"+1 805 481 2050",
    "sg:postcode":"93433",
    "sg:province":"CA",
    "sg:tags":[
        "attorney"
    ],
    "wof:name":"James P Harvey",
    "wof:placetype":"venue"
},
  "geometry": {"coordinates":[-120.61976300000001,35.122432],"type":"Point"}
}