{
  "type": "Feature",
  "properties": {
    "iso:country":"US",
    "sg:address":"3595 Sunset Dr",
    "sg:city":"Redding",
    "sg:classifiers":[
        {
            "category":"Professional",
            "subcategory":"Management & Consulting",
            "type":"Services"
        }
    ],
    "sg:phone":"+1 530 246 9005",
    "sg:postcode":"96001",
    "sg:province":"CA",
    "sg:tags":[
        "consultant",
        "business"
    ],
    "wof:name":"Tri-Counties Management Co",
    "wof:placetype":"venue"
},
  "geometry": {"coordinates":[-122.423757,40.585815],"type":"Point"}
}