{
  "type": "Feature",
  "properties": {
    "addr:full":"3621 Granby Dr Sacramento CA 95827",
    "addr:housenumber":"3621",
    "addr:postcode":"95827",
    "addr:street":"Granby Dr",
    "iso:country":"US",
    "sg:address":"3621 Granby Dr",
    "sg:city":"Sacramento",
    "sg:classifiers":[
        {
            "category":"Retail",
            "subcategory":"Repair Shop",
            "type":"Services"
        }
    ],
    "sg:phone":"+1 916 368 7821",
    "sg:postcode":"95827",
    "sg:province":"CA",
    "sg:tags":[
        "household",
        "appliance"
    ],
    "wof:name":"1 Service Appliance & Repair",
    "wof:placetype":"venue"
},
  "geometry": {"coordinates":[-121.330727,38.558734],"type":"Point"}
}