{
  "type": "Feature",
  "properties": {
    "addr:full":"7043 Cam Maquiladora San Diego CA 92154",
    "addr:housenumber":"7043",
    "addr:postcode":"92154",
    "addr:street":"Cam Maquiladora",
    "iso:country":"US",
    "sg:address":"7043 Cam Maquiladora",
    "sg:city":"San Diego",
    "sg:classifiers":[
        {
            "category":"Wholesale",
            "subcategory":"Fruits & Vegetables",
            "type":"Manufacturing & Wholesale Goods"
        }
    ],
    "sg:phone":"+1 619 661 7440",
    "sg:postcode":"92154",
    "sg:province":"CA",
    "wof:name":"H Baza Farm",
    "wof:placetype":"venue"
},
  "geometry": {"coordinates":[-116.987909,32.566763],"type":"Point"}
}