{
  "type": "Feature",
  "properties": {
    "addr:full":"862 Folsom St. San Francisco CA 94103",
    "addr:housenumber":"862",
    "addr:postcode":"94103",
    "addr:street":"Folsom St.",
    "iso:country":"US",
    "sg:address":"862 Folsom St.",
    "sg:city":"San Francisco",
    "sg:classifiers":[
        {
            "category":"Health Services",
            "subcategory":"Health Practitioner",
            "type":"Services"
        }
    ],
    "sg:phone":"+1 415 819 5352",
    "sg:postcode":"94103",
    "sg:province":"CA",
    "sg:tags":[
        "acupuncture"
    ],
    "sg:website":"www.allisoncrawford.com",
    "wof:name":"Allison Crawford, MS, L.Ac.",
    "wof:placetype":"venue"
},
  "geometry": {"coordinates":[-122.40300000000001,37.781101],"type":"Point"}
}