{
  "type": "Feature",
  "properties": {
    "addr:full":"569 3rd Ave Chula Vista CA 91910",
    "addr:housenumber":"569",
    "addr:postcode":"91910",
    "addr:street":"3Rd Ave",
    "iso:country":"US",
    "sg:address":"569 3rd Ave",
    "sg:city":"Chula Vista",
    "sg:classifiers":[
        {
            "category":"Banks & Credit Unions",
            "subcategory":"Bank",
            "type":"Services"
        }
    ],
    "sg:phone":"+1 619 827 1701",
    "sg:postcode":"91910",
    "sg:province":"CA",
    "sg:tags":[
        "loan",
        "real estate"
    ],
    "wof:name":"Quick Stop Mortgage",
    "wof:placetype":"venue"
},
  "geometry": {"coordinates":[-117.075997,32.631512],"type":"Point"}
}