{
  "type": "Feature",
  "properties": {
    "addr:full":"500 E Calaveras Blvd Ste 202 Milpitas CA 95035",
    "addr:housenumber":"500",
    "addr:postcode":"95035",
    "addr:street":"E Calaveras Blvd Ste 202",
    "iso:country":"US",
    "sg:address":"500 E Calaveras Blvd Ste 202",
    "sg:city":"Milpitas",
    "sg:classifiers":[
        {
            "category":"Education",
            "subcategory":"Special Training",
            "type":"Public Place"
        }
    ],
    "sg:phone":"+1 800 566 4043",
    "sg:postcode":"95035",
    "sg:province":"CA",
    "sg:tags":[
        "tutoring"
    ],
    "sg:website":"www.gurome.com",
    "wof:name":"Gurome",
    "wof:placetype":"venue"
},
  "geometry": {"coordinates":[-121.89654,37.432264],"type":"Point"}
}