{
  "type": "Feature",
  "properties": {
    "iso:country":"US",
    "sg:address":"909 California St",
    "sg:city":"Woodland",
    "sg:phone":"+1 530 661 7476",
    "sg:postcode":"95695",
    "sg:province":"CA",
    "sg:tags":[
        "leather",
        "industry",
        "machinery",
        "mfg"
    ],
    "wof:name":"Snaketan",
    "wof:placetype":"venue"
},
  "geometry": {"coordinates":[-121.789233,38.667248],"type":"Point"}
}