{
  "type": "Feature",
  "properties": {
    "iso:country":"US",
    "sg:address":"5501 Freeport Blvd",
    "sg:city":"Sacramento",
    "sg:classifiers":[
        {
            "category":"Restaurant",
            "type":"Food & Drink"
        }
    ],
    "sg:menulink":"http://www.allmenus.com/ca/sacramento/171266-carls-jr/menu/",
    "sg:phone":"+1 916 334 2831",
    "sg:postcode":"95822",
    "sg:province":"CA",
    "sg:tags":[
        "burger",
        "american"
    ],
    "wof:name":"Carl's Jr.",
    "wof:placetype":"venue"
},
  "geometry": {"coordinates":[-121.496498,38.525346],"type":"Point"}
}