{
  "type": "Feature",
  "properties": {
    "addr:full":"5520 Cahuenga Blvd North Hollywood CA 91601",
    "addr:housenumber":"5520",
    "addr:postcode":"91601",
    "addr:street":"Cahuenga Blvd",
    "iso:country":"US",
    "sg:address":"5520 Cahuenga Blvd",
    "sg:city":"North Hollywood",
    "sg:classifiers":[
        {
            "category":"Wholesale",
            "subcategory":"Motor Vehicles",
            "type":"Manufacturing & Wholesale Goods"
        }
    ],
    "sg:phone":"+1 818 508 1398",
    "sg:postcode":"91601",
    "sg:province":"CA",
    "sg:tags":[
        "automobile"
    ],
    "wof:name":"Property Management Cons",
    "wof:placetype":"venue"
},
  "geometry": {"coordinates":[-118.361479,34.171715],"type":"Point"}
}