{
  "type": "Feature",
  "properties": {
    "iso:country":"US",
    "sg:address":"501 14th St",
    "sg:city":"Oakland",
    "sg:classifiers":[
        {
            "category":"Restaurant",
            "type":"Food & Drink"
        }
    ],
    "sg:menulink":"http://www.allmenus.com/ca/oakland/157579-la-salsa/menu/",
    "sg:phone":"+1 510 834 3422",
    "sg:postcode":"94612",
    "sg:province":"CA",
    "sg:tags":[
        "mexican"
    ],
    "wof:name":"La Salsa",
    "wof:placetype":"venue"
},
  "geometry": {"coordinates":[-122.273622,37.805311],"type":"Point"}
}