{
  "type": "Feature",
  "properties": {
    "addr:full":"347 Mobil Ave Camarillo CA 93010",
    "addr:postcode":"93010",
    "addr:street":"Ave",
    "iso:country":"US",
    "sg:address":"347 Mobil Ave",
    "sg:city":"Camarillo",
    "sg:classifiers":[
        {
            "category":"Personal",
            "type":"Services"
        }
    ],
    "sg:phone":"+1 805 383 9229",
    "sg:postcode":"93010",
    "sg:province":"CA",
    "sg:tags":[
        "sewing",
        "alteration"
    ],
    "wof:name":"Flavio's Tailoring",
    "wof:placetype":"venue"
},
  "geometry": {"coordinates":[-119.04325799999999,34.220025],"type":"Point"}
}