{
  "type": "Feature",
  "properties": {
    "addr:full":"624 Cardoso Dr Galt CA 95632",
    "addr:housenumber":"624",
    "addr:postcode":"95632",
    "addr:street":"Cardoso Dr",
    "iso:country":"US",
    "sg:address":"624 Cardoso Dr",
    "sg:city":"Galt",
    "sg:classifiers":[
        {
            "category":"Utilities",
            "subcategory":"Cable",
            "type":"Services"
        }
    ],
    "sg:phone":"+1 209 744 0108",
    "sg:postcode":"95632",
    "sg:province":"CA",
    "sg:tags":[
        "television"
    ],
    "wof:name":"EVSC Inc",
    "wof:placetype":"venue"
},
  "geometry": {"coordinates":[-121.30655,38.244058],"type":"Point"}
}