{
  "type": "Feature",
  "properties": {
    "addr:full":"3333 E Spring St Long Beach CA 90806",
    "addr:housenumber":"3333",
    "addr:postcode":"90806",
    "addr:street":"E Spring St",
    "iso:country":"US",
    "sg:address":"3333 E Spring St",
    "sg:city":"Long Beach",
    "sg:classifiers":[
        {
            "category":"Insurance",
            "subcategory":"Insurance Agent",
            "type":"Services"
        }
    ],
    "sg:phone":"+1 562 492 1217",
    "sg:postcode":"90806",
    "sg:province":"CA",
    "wof:name":"Cfm Aviation Insurance",
    "wof:placetype":"venue"
},
  "geometry": {"coordinates":[-118.152957,33.810688],"type":"Point"}
}