{
  "type": "Feature",
  "properties": {
    "iso:country":"US",
    "sg:address":"2917 Shamrock Ave",
    "sg:city":"Brea",
    "sg:classifiers":[
        {
            "category":"Insurance",
            "subcategory":"Insurance Agent",
            "type":"Services"
        }
    ],
    "sg:phone":"+1 714 572 8210",
    "sg:postcode":"92821",
    "sg:province":"CA",
    "wof:name":"Ruhe Claims Services",
    "wof:placetype":"venue"
},
  "geometry": {"coordinates":[-117.860186,33.922492],"type":"Point"}
}