{
  "type": "Feature",
  "properties": {
    "addr:full":"4212 Orange Grove Ave Sacramento CA 95841",
    "addr:housenumber":"4212",
    "addr:postcode":"95841",
    "addr:street":"Orange Grove Ave",
    "iso:country":"US",
    "sg:address":"4212 Orange Grove Ave",
    "sg:city":"Sacramento",
    "sg:classifiers":[
        {
            "category":"Building & Trades",
            "subcategory":"Landscaping Services",
            "type":"Services"
        }
    ],
    "sg:phone":"+1 916 484 0570",
    "sg:postcode":"95841",
    "sg:province":"CA",
    "sg:tags":[
        "lawn",
        "tree"
    ],
    "wof:name":"Conserve Arboculture Care",
    "wof:placetype":"venue"
},
  "geometry": {"coordinates":[-121.363474,38.648132],"type":"Point"}
}