{
  "type": "Feature",
  "properties": {
    "addr:full":"673 Villa Way Arcata CA 95521",
    "addr:housenumber":"673",
    "addr:postcode":"95521",
    "addr:street":"Villa Way",
    "iso:country":"US",
    "sg:address":"673 Villa Way",
    "sg:city":"Arcata",
    "sg:classifiers":[
        {
            "category":"Building & Trades",
            "subcategory":"Landscaping Services",
            "type":"Services"
        }
    ],
    "sg:phone":"+1 707 825 8990",
    "sg:postcode":"95521",
    "sg:province":"CA",
    "sg:tags":[
        "landscape",
        "contractor"
    ],
    "wof:name":"Bumblebee Landscape",
    "wof:placetype":"venue"
},
  "geometry": {"coordinates":[-124.100008,40.872164],"type":"Point"}
}