{
  "type": "Feature",
  "properties": {
    "iso:country":"US",
    "sg:address":"1343 Rollins Rd",
    "sg:city":"Burlingame",
    "sg:classifiers":[
        {
            "category":"Professional",
            "type":"Services"
        }
    ],
    "sg:phone":"+1 650 579 7198",
    "sg:postcode":"94010",
    "sg:province":"CA",
    "sg:tags":[
        "establishment"
    ],
    "wof:name":"Eurofront USA",
    "wof:placetype":"venue"
},
  "geometry": {"coordinates":[-122.367258,37.591153],"type":"Point"}
}