{
  "type": "Feature",
  "properties": {
    "iso:country":"US",
    "sg:address":"1153 Sierra Vista Way",
    "sg:city":"Lafayette",
    "sg:classifiers":[
        {
            "category":"Recreation",
            "type":"Entertainment"
        }
    ],
    "sg:phone":"+1 925 284 1890",
    "sg:postcode":"94549",
    "sg:province":"CA",
    "sg:tags":[
        "safety",
        "instruction",
        "marksmanship",
        "gun"
    ],
    "wof:name":"Great Guns Shooting Tours",
    "wof:placetype":"venue"
},
  "geometry": {"coordinates":[-122.11524799999999,37.898139],"type":"Point"}
}