{
  "type": "Feature",
  "properties": {
    "addr:full":"California State University Fullerton 800 N State College Blvd Fullerton CA 92831",
    "addr:housenumber":"800",
    "addr:postcode":"92831",
    "addr:street":"N State College Blvd",
    "iso:country":"US",
    "sg:address":"California State University Fullerton 800 N State College Blvd",
    "sg:city":"Fullerton",
    "sg:classifiers":[
        {
            "category":"Arts & Performance",
            "subcategory":"Festival",
            "type":"Entertainment"
        }
    ],
    "sg:postcode":"92831",
    "sg:province":"CA",
    "wof:name":"Donate a life: Run/Walk & Family Festival",
    "wof:placetype":"venue"
},
  "geometry": {"coordinates":[-117.887807,33.881924],"type":"Point"}
}