{
  "type": "Feature",
  "properties": {
    "addr:full":"2300 W Victory Blvd Burbank CA 91506",
    "addr:housenumber":"2300",
    "addr:postcode":"91506",
    "addr:street":"W Victory Blvd",
    "iso:country":"US",
    "sg:address":"2300 W Victory Blvd",
    "sg:city":"Burbank",
    "sg:classifiers":[
        {
            "category":"Professional",
            "subcategory":"Computer Services",
            "type":"Services"
        }
    ],
    "sg:phone":"+1 818 352 2244",
    "sg:postcode":"91506",
    "sg:province":"CA",
    "sg:tags":[
        "internet"
    ],
    "wof:name":"A Internet Marketing Group",
    "wof:placetype":"venue"
},
  "geometry": {"coordinates":[-118.337118,34.184565],"type":"Point"}
}