{
  "type": "Feature",
  "properties": {
    "iso:country":"US",
    "sg:address":"7966 Cranford Ln",
    "sg:city":"Dublin",
    "sg:classifiers":[
        {
            "category":"Real Estate",
            "subcategory":"Real Estate Services",
            "type":"Services"
        },
        {
            "category":"Retail",
            "subcategory":"Laundry & Dry Cleaning",
            "type":"Services"
        },
        {
            "category":"Building & Trades",
            "subcategory":"Cleaning & Sanitation",
            "type":"Services"
        }
    ],
    "sg:phone":"+1 925 413 9572",
    "sg:postcode":"94568",
    "sg:province":"CA",
    "sg:tags":[
        "cleaner",
        "upholstery",
        "house",
        "rug",
        "window",
        "maintenance",
        "carpet"
    ],
    "wof:name":"Rougeau Janitorial Services",
    "wof:placetype":"venue"
},
  "geometry": {"coordinates":[-121.92817100000001,37.717981],"type":"Point"}
}