{
  "type": "Feature",
  "properties": {
    "iso:country":"US",
    "sg:address":"3720 Oceanic Way Ste 204",
    "sg:city":"Oceanside",
    "sg:classifiers":[
        {
            "category":"Building & Trades",
            "subcategory":"Construction",
            "type":"Services"
        }
    ],
    "sg:phone":"+1 760 672 1053",
    "sg:postcode":"92056",
    "sg:province":"CA",
    "sg:tags":[
        "system",
        "contractor",
        "air conditioning"
    ],
    "sg:website":"http://www.coastalairinc.com",
    "wof:name":"Coastal Heating & Ac",
    "wof:placetype":"venue"
},
  "geometry": {"coordinates":[-117.30757699999999,33.204402],"type":"Point"}
}