{
  "type": "Feature",
  "properties": {
    "addr:full":"10926 Painter Ave Santa Fe Springs CA 90670",
    "addr:housenumber":"10926",
    "addr:postcode":"90670",
    "addr:street":"Painter Ave",
    "iso:country":"US",
    "sg:address":"10926 Painter Ave",
    "sg:city":"Santa Fe Springs",
    "sg:classifiers":[
        {
            "category":"Autos & Motor Vehicles",
            "subcategory":"Auto Supplies",
            "type":"Retail Goods"
        },
        {
            "category":"Wholesale",
            "subcategory":"Auto Parts",
            "type":"Manufacturing & Wholesale Goods"
        }
    ],
    "sg:phone":"+1 562 777 7717",
    "sg:postcode":"90670",
    "sg:province":"CA",
    "sg:tags":[
        "wheel",
        "rim",
        "cover"
    ],
    "wof:name":"Atlantic Wholesalers West Inc",
    "wof:placetype":"venue"
},
  "geometry": {"coordinates":[-118.051277,33.934457],"type":"Point"}
}