{
  "type": "Feature",
  "properties": {
    "addr:full":"5512 Wilsey Way Carmichael CA 95608",
    "addr:housenumber":"5512",
    "addr:postcode":"95608",
    "addr:street":"Wilsey Way",
    "iso:country":"US",
    "sg:address":"5512 Wilsey Way",
    "sg:city":"Carmichael",
    "sg:classifiers":[
        {
            "category":"Professional",
            "subcategory":"Secretarial Services",
            "type":"Services"
        }
    ],
    "sg:phone":"+1 916 967 7701",
    "sg:postcode":"95608",
    "sg:province":"CA",
    "sg:tags":[
        "reporting",
        "court"
    ],
    "wof:name":"Word Processing By Dee",
    "wof:placetype":"venue"
},
  "geometry": {"coordinates":[-121.320409,38.666462],"type":"Point"}
}