{
  "type": "Feature",
  "properties": {
    "iso:country":"US",
    "sg:address":"1710 Via Lobos",
    "sg:city":"San Lorenzo",
    "sg:classifiers":[
        {
            "category":"Professional",
            "subcategory":"Computer Services",
            "type":"Services"
        }
    ],
    "sg:phone":"+1 510 276 1613",
    "sg:postcode":"94580",
    "sg:province":"CA",
    "sg:tags":[
        "added",
        "value",
        "reseller",
        "system"
    ],
    "wof:name":"Micro Data Communications",
    "wof:placetype":"venue"
},
  "geometry": {"coordinates":[-122.146847,37.677375],"type":"Point"}
}