{
  "type": "Feature",
  "properties": {
    "iso:country":"US",
    "sg:address":"6037 Snell Ave",
    "sg:city":"San Jose",
    "sg:classifiers":[
        {
            "category":"Personal",
            "subcategory":"Barber",
            "type":"Services"
        }
    ],
    "sg:phone":"+1 408 224 8855",
    "sg:postcode":"95123",
    "sg:province":"CA",
    "wof:name":"A Plus Barber",
    "wof:placetype":"venue"
},
  "geometry": {"coordinates":[-121.831879,37.238205],"type":"Point"}
}