{
  "type": "Feature",
  "properties": {
    "iso:country":"US",
    "sg:address":"1993 E Bayshore Rd",
    "sg:city":"Redwood City",
    "sg:classifiers":[
        {
            "category":"Building & Trades",
            "subcategory":"Landscaping Services",
            "type":"Services"
        }
    ],
    "sg:phone":"+1 650 365 5653",
    "sg:postcode":"94063",
    "sg:province":"CA",
    "wof:name":"Wilson Landscape Construction",
    "wof:placetype":"venue"
},
  "geometry": {"coordinates":[-122.208456,37.488455],"type":"Point"}
}