{
  "type": "Feature",
  "properties": {
    "addr:full":"2912 129th St Gardena CA 90249",
    "addr:housenumber":"2912",
    "addr:postcode":"90249",
    "addr:street":"129Th St",
    "iso:country":"US",
    "sg:address":"2912 129th St",
    "sg:city":"Gardena",
    "sg:classifiers":[
        {
            "category":"Shopping",
            "subcategory":"Clothing, Apparel, & Fashions",
            "type":"Retail Goods"
        }
    ],
    "sg:phone":"+1 310 324 0427",
    "sg:postcode":"90249",
    "sg:province":"CA",
    "wof:name":"T W Remarketing",
    "wof:placetype":"venue"
},
  "geometry": {"coordinates":[-118.32498099999999,33.915326],"type":"Point"}
}