{
  "type": "Feature",
  "properties": {
    "iso:country":"US",
    "sg:address":"2097 US Hwy 199",
    "sg:city":"Crescent City",
    "sg:classifiers":[
        {
            "category":"Building & Trades",
            "subcategory":"Construction",
            "type":"Services"
        }
    ],
    "sg:phone":"+1 707 458 3549",
    "sg:postcode":"95531",
    "sg:province":"CA",
    "sg:tags":[
        "contractor"
    ],
    "wof:name":"Norman Storm Construction",
    "wof:placetype":"venue"
},
  "geometry": {"coordinates":[-124.081239,41.805647],"type":"Point"}
}