{
  "type": "Feature",
  "properties": {
    "addr:full":"4733 Loma Vista Ave Vernon CA 90058",
    "addr:housenumber":"4733",
    "addr:postcode":"90058",
    "addr:street":"Loma Vista Ave",
    "iso:country":"US",
    "sg:address":"4733 Loma Vista Ave",
    "sg:city":"Vernon",
    "sg:classifiers":[
        {
            "category":"Wholesale",
            "subcategory":"Chemicals & Plastics",
            "type":"Manufacturing & Wholesale Goods"
        }
    ],
    "sg:phone":"+1 323 268 3535",
    "sg:postcode":"90058",
    "sg:province":"CA",
    "wof:name":"U S Cosmo Plastics",
    "wof:placetype":"venue"
},
  "geometry": {"coordinates":[-118.197076,33.999266],"type":"Point"}
}