{
  "type": "Feature",
  "properties": {
    "iso:country":"US",
    "sg:address":"7837 Olive St",
    "sg:city":"Fair Oaks",
    "sg:classifiers":[
        {
            "category":"Shopping",
            "subcategory":"Catalog Store",
            "type":"Retail Goods"
        }
    ],
    "sg:phone":"+1 916 967 3997",
    "sg:postcode":"95628",
    "sg:province":"CA",
    "sg:tags":[
        "mail",
        "house"
    ],
    "wof:name":"Zone 9 Plants",
    "wof:placetype":"venue"
},
  "geometry": {"coordinates":[-121.274826,38.650131],"type":"Point"}
}