{
  "type": "Feature",
  "properties": {
    "iso:country":"US",
    "sg:address":"2222 M St",
    "sg:city":"Merced",
    "sg:classifiers":[
        {
            "category":"Government",
            "subcategory":"Office",
            "type":"Public Place"
        }
    ],
    "sg:phone":"+1 209 385 7356",
    "sg:postcode":"95340",
    "sg:province":"CA",
    "wof:name":"Merced County Risk Management",
    "wof:placetype":"venue"
},
  "geometry": {"coordinates":[-120.48141699999999,37.307712],"type":"Point"}
}