{
  "type": "Feature",
  "properties": {
    "addr:full":"4211 Market St San Diego CA 92102",
    "addr:housenumber":"4211",
    "addr:postcode":"92102",
    "addr:street":"Market St",
    "iso:country":"US",
    "sg:address":"4211 Market St",
    "sg:city":"San Diego",
    "sg:classifiers":[
        {
            "category":"Restaurant",
            "type":"Food & Drink"
        }
    ],
    "sg:phone":"+1 619 264 5099",
    "sg:postcode":"92102",
    "sg:province":"CA",
    "wof:name":"Nancy's Taco Shop",
    "wof:placetype":"venue"
},
  "geometry": {"coordinates":[-117.103945,32.711402],"type":"Point"}
}