{
  "type": "Feature",
  "properties": {
    "iso:country":"US",
    "sg:address":"855 Oak Grove Ave",
    "sg:city":"Menlo Park",
    "sg:classifiers":[
        {
            "category":"Professional",
            "type":"Services"
        }
    ],
    "sg:phone":"+1 650 323 0348",
    "sg:postcode":"94025",
    "sg:province":"CA",
    "sg:tags":[
        "establishment"
    ],
    "wof:name":"Oak Grove Assoc",
    "wof:placetype":"venue"
},
  "geometry": {"coordinates":[-122.186917,37.451217],"type":"Point"}
}