{
  "type": "Feature",
  "properties": {
    "addr:full":"3140 Lemitar Way Sacramento CA 95833",
    "addr:housenumber":"3140",
    "addr:postcode":"95833",
    "addr:street":"Lemitar Way",
    "iso:country":"US",
    "sg:address":"3140 Lemitar Way",
    "sg:city":"Sacramento",
    "sg:classifiers":[
        {
            "category":"Building & Trades",
            "subcategory":"Construction",
            "type":"Services"
        }
    ],
    "sg:phone":"+1 916 806 3091",
    "sg:postcode":"95833",
    "sg:province":"CA",
    "sg:tags":[
        "dry wall",
        "contractor"
    ],
    "wof:name":"B B Dry Wall",
    "wof:placetype":"venue"
},
  "geometry": {"coordinates":[-121.508573,38.62356],"type":"Point"}
}