{
  "type": "Feature",
  "properties": {
    "iso:country":"US",
    "sg:address":"1340 Tully Rd",
    "sg:city":"San Jose",
    "sg:classifiers":[
        {
            "category":"Building & Trades",
            "subcategory":"Construction",
            "type":"Services"
        }
    ],
    "sg:phone":"+1 408 298 8383",
    "sg:postcode":"95111",
    "sg:province":"CA",
    "sg:tags":[
        "general",
        "contractor"
    ],
    "wof:name":"A Z General Contractor",
    "wof:placetype":"venue"
},
  "geometry": {"coordinates":[-121.832459,37.317915],"type":"Point"}
}