{
  "type": "Feature",
  "properties": {
    "addr:full":"1072 Buttercup Pl Manteca CA 95336",
    "addr:housenumber":"1072",
    "addr:postcode":"95336",
    "addr:street":"Buttercup Pl",
    "iso:country":"US",
    "sg:address":"1072 Buttercup Pl",
    "sg:city":"Manteca",
    "sg:classifiers":[
        {
            "category":"Freight",
            "type":"Transportation"
        }
    ],
    "sg:phone":"+1 209 823 5026",
    "sg:postcode":"95336",
    "sg:province":"CA",
    "sg:tags":[
        "broker"
    ],
    "wof:name":"Delta Traffic Svc",
    "wof:placetype":"venue"
},
  "geometry": {"coordinates":[-121.193568,37.810763],"type":"Point"}
}