{
  "type": "Feature",
  "properties": {
    "iso:country":"US",
    "sg:address":"2560 El Camino Real",
    "sg:city":"Redwood City",
    "sg:classifiers":[
        {
            "category":"Restaurant",
            "type":"Food & Drink"
        }
    ],
    "sg:menulink":"http://www.allmenus.com/ca/san-mateo/51903-pronto-wood-fried-pizzeria/menu/",
    "sg:phone":"+1 650 365 9978",
    "sg:postcode":"94061",
    "sg:province":"CA",
    "sg:tags":[
        "american",
        "pizza"
    ],
    "wof:name":"Pronto Wood Fried Pizzeria",
    "wof:placetype":"venue"
},
  "geometry": {"coordinates":[-122.217039,37.472904],"type":"Point"}
}