{
  "type": "Feature",
  "properties": {
    "iso:country":"US",
    "sg:address":"7040 Deering Ave",
    "sg:city":"Canoga Park",
    "sg:classifiers":[
        {
            "category":"Building & Trades",
            "subcategory":"Construction",
            "type":"Services"
        }
    ],
    "sg:phone":"+1 818 884 2527",
    "sg:postcode":"91303",
    "sg:province":"CA",
    "sg:tags":[
        "contractor"
    ],
    "wof:name":"West Coast Restoration",
    "wof:placetype":"venue"
},
  "geometry": {"coordinates":[-118.59699999999999,34.1987],"type":"Point"}
}