{
  "type": "Feature",
  "properties": {
    "addr:full":"317 N El Camino Real, Suite 406 Encinitas CA 92024",
    "addr:housenumber":"317",
    "addr:postcode":"92024",
    "addr:street":"N El Camino Real Suite 406",
    "iso:country":"US",
    "sg:address":"317 N El Camino Real, Suite 406",
    "sg:city":"Encinitas",
    "sg:classifiers":[
        {
            "category":"Health Services",
            "subcategory":"Health Practitioner",
            "type":"Services"
        }
    ],
    "sg:phone":"+1 760 634 1884",
    "sg:postcode":"92024",
    "sg:province":"CA",
    "sg:tags":[
        "acupuncture",
        "therapy",
        "physical"
    ],
    "sg:website":"www.ISAtherapy.com",
    "wof:name":"Integrative Sports Acupuncture",
    "wof:placetype":"venue"
},
  "geometry": {"coordinates":[-117.260683,33.054539],"type":"Point"}
}