{
  "type": "Feature",
  "properties": {
    "addr:full":"3711 National Ave San Diego CA 92113",
    "addr:housenumber":"3711",
    "addr:postcode":"92113",
    "addr:street":"National Ave",
    "iso:country":"US",
    "sg:address":"3711 National Ave",
    "sg:city":"San Diego",
    "sg:classifiers":[
        {
            "category":"Professional",
            "type":"Services"
        }
    ],
    "sg:phone":"+1 619 527 1195",
    "sg:postcode":"92113",
    "sg:province":"CA",
    "sg:tags":[
        "establishment"
    ],
    "wof:name":"Nation's Best Fish & Fish",
    "wof:placetype":"venue"
},
  "geometry": {"coordinates":[-117.112645,32.695958],"type":"Point"}
}