{
  "type": "Feature",
  "properties": {
    "addr:full":"6095 Rickenbacker Rd Los Angeles CA 90040",
    "addr:housenumber":"6095",
    "addr:postcode":"90040",
    "addr:street":"Rickenbacker Rd",
    "iso:country":"US",
    "sg:address":"6095 Rickenbacker Rd",
    "sg:city":"Los Angeles",
    "sg:classifiers":[
        {
            "category":"Wholesale",
            "subcategory":"Durable Goods & Equipment",
            "type":"Manufacturing & Wholesale Goods"
        }
    ],
    "sg:phone":"+1 323 728 1413",
    "sg:postcode":"90040",
    "sg:province":"CA",
    "sg:tags":[
        "importer"
    ],
    "wof:name":"Starus Trading Inc",
    "wof:placetype":"venue"
},
  "geometry": {"coordinates":[-118.156543,33.988931],"type":"Point"}
}