{
  "type": "Feature",
  "properties": {
    "addr:full":"17024 Van Buren Blvd Riverside CA 92504",
    "addr:housenumber":"17024",
    "addr:postcode":"92504",
    "addr:street":"Van Buren Blvd",
    "iso:country":"US",
    "sg:address":"17024 Van Buren Blvd",
    "sg:city":"Riverside",
    "sg:classifiers":[
        {
            "category":"Food & Beverages",
            "subcategory":"Specialty",
            "type":"Retail Goods"
        }
    ],
    "sg:phone":"+1 951 789 2901",
    "sg:postcode":"92504",
    "sg:province":"CA",
    "sg:tags":[
        "health",
        "diet"
    ],
    "wof:name":"Health-Max",
    "wof:placetype":"venue"
},
  "geometry": {"coordinates":[-117.362138,33.882465],"type":"Point"}
}