{
  "type": "Feature",
  "properties": {
    "iso:country":"US",
    "sg:address":"44 Water Lily Way",
    "sg:city":"Trabuco Canyon",
    "sg:classifiers":[
        {
            "category":"Professional",
            "subcategory":"Business Services",
            "type":"Services"
        }
    ],
    "sg:phone":"+1 949 888 3139",
    "sg:postcode":"92679",
    "sg:province":"CA",
    "sg:tags":[
        "lithographic",
        "printing",
        "commercial"
    ],
    "wof:name":"Value Source Group Inc",
    "wof:placetype":"venue"
},
  "geometry": {"coordinates":[-117.588332,33.57336],"type":"Point"}
}