{
  "type": "Feature",
  "properties": {
    "iso:country":"US",
    "sg:address":"330 N Hayworth Ave",
    "sg:city":"Los Angeles",
    "sg:classifiers":[
        {
            "category":"Social Services",
            "subcategory":"Retirement Home",
            "type":"Services"
        }
    ],
    "sg:phone":"+1 323 244 4341",
    "sg:postcode":"90048",
    "sg:province":"CA",
    "sg:website":"www.silveradosenior.com/memory_c...",
    "wof:name":"Silverado Senior Living - Beverly Place",
    "wof:placetype":"venue"
},
  "geometry": {"coordinates":[-118.362288,34.077021],"type":"Point"}
}