{
  "type": "Feature",
  "properties": {
    "iso:country":"US",
    "sg:address":"3635 Newton St",
    "sg:city":"Torrance",
    "sg:classifiers":[
        {
            "category":"Personal",
            "type":"Services"
        }
    ],
    "sg:phone":"+1 310 373 6163",
    "sg:postcode":"90505",
    "sg:province":"CA",
    "sg:tags":[
        "genealogist"
    ],
    "wof:name":"Site Yourself",
    "wof:placetype":"venue"
},
  "geometry": {"coordinates":[-118.347782,33.799152],"type":"Point"}
}