{
  "type": "Feature",
  "properties": {
    "iso:country":"US",
    "sg:address":"2131 G St",
    "sg:city":"Bakersfield",
    "sg:classifiers":[
        {
            "category":"Real Estate",
            "subcategory":"Real Estate Agent",
            "type":"Services"
        }
    ],
    "sg:phone":"+1 661 327 0440",
    "sg:postcode":"93301",
    "sg:province":"CA",
    "sg:tags":[
        "management"
    ],
    "wof:name":"Pacific Management Co",
    "wof:placetype":"venue"
},
  "geometry": {"coordinates":[-119.022414,35.378819],"type":"Point"}
}