{
  "type": "Feature",
  "properties": {
    "addr:full":"81 Gregory Ln Brentwood CA 94513",
    "addr:housenumber":"81",
    "addr:postcode":"94513",
    "addr:street":"Gregory Ln",
    "iso:country":"US",
    "sg:address":"81 Gregory Ln",
    "sg:city":"Brentwood",
    "sg:classifiers":[
        {
            "category":"Home & Garden",
            "subcategory":"Building Materials",
            "type":"Retail Goods"
        }
    ],
    "sg:phone":"+1 925 513 4019",
    "sg:postcode":"94513",
    "sg:province":"CA",
    "sg:tags":[
        "stone"
    ],
    "wof:name":"Brentwood Decorative Rock",
    "wof:placetype":"venue"
},
  "geometry": {"coordinates":[-121.69868700000001,37.95853],"type":"Point"}
}