{
  "type": "Feature",
  "properties": {
    "addr:full":"4009 Marconi Ave Ofc Sacramento CA 95821",
    "addr:housenumber":"4009",
    "addr:postcode":"95821",
    "addr:street":"Marconi Ave",
    "iso:country":"US",
    "sg:address":"4009 Marconi Ave Ofc",
    "sg:city":"Sacramento",
    "sg:classifiers":[
        {
            "category":"Real Estate",
            "subcategory":"Real Estate Operator",
            "type":"Services"
        }
    ],
    "sg:phone":"+1 916 971 0859",
    "sg:postcode":"95821",
    "sg:province":"CA",
    "sg:tags":[
        "apartment"
    ],
    "wof:name":"Amber Grove Apartments",
    "wof:placetype":"venue"
},
  "geometry": {"coordinates":[-121.371002,38.617699],"type":"Point"}
}