{
  "type": "Feature",
  "properties": {
    "iso:country":"US",
    "sg:address":"1894 6 Mile Rd",
    "sg:city":"Murphys",
    "sg:phone":"+1 209 728 1251",
    "sg:postcode":"95247",
    "sg:province":"CA",
    "sg:website":"http://www.ironstonevineyards.com",
    "wof:name":"Ironstone Vineyards",
    "wof:placetype":"venue"
},
  "geometry": {"coordinates":[-120.487334,38.106212],"type":"Point"}
}