{
  "type": "Feature",
  "properties": {
    "addr:full":"598 Elliott Rd Paradise CA 95969",
    "addr:housenumber":"598",
    "addr:postcode":"95969",
    "addr:street":"Elliott Rd",
    "iso:country":"US",
    "sg:address":"598 Elliott Rd",
    "sg:city":"Paradise",
    "sg:classifiers":[
        {
            "category":"Real Estate",
            "subcategory":"Real Estate Operator",
            "type":"Services"
        }
    ],
    "sg:phone":"+1 530 877 6164",
    "sg:postcode":"95969",
    "sg:province":"CA",
    "sg:tags":[
        "mobile",
        "home",
        "site"
    ],
    "wof:name":"Environmental Housing Solution",
    "wof:placetype":"venue"
},
  "geometry": {"coordinates":[-121.629092,39.75948],"type":"Point"}
}