{
  "type": "Feature",
  "properties": {
    "addr:full":"17267 Ventura Blvd Encino CA 91316",
    "addr:housenumber":"17267",
    "addr:postcode":"91316",
    "addr:street":"Ventura Blvd",
    "iso:country":"US",
    "sg:address":"17267 Ventura Blvd",
    "sg:city":"Encino",
    "sg:classifiers":[
        {
            "category":"Professional",
            "type":"Services"
        },
        {
            "category":"Restaurant",
            "type":"Food & Drink"
        }
    ],
    "sg:phone":"+1 818 501 0088",
    "sg:postcode":"91316",
    "sg:province":"CA",
    "sg:tags":[
        "bar",
        "chinese",
        "sushi",
        "japanese",
        "asian",
        "caterer",
        "pan"
    ],
    "wof:name":"Sushi Wok",
    "wof:placetype":"venue"
},
  "geometry": {"coordinates":[-118.508864,34.160709],"type":"Point"}
}