{
  "type": "Feature",
  "properties": {
    "iso:country":"US",
    "sg:address":"4900 Dartford Pl",
    "sg:city":"Granite Bay",
    "sg:classifiers":[
        {
            "category":"Professional",
            "type":"Services"
        }
    ],
    "sg:phone":"+1 916 791 6370",
    "sg:postcode":"95746",
    "sg:province":"CA",
    "wof:name":"Pharmascriptscom LLC",
    "wof:placetype":"venue"
},
  "geometry": {"coordinates":[-121.210823,38.722618],"type":"Point"}
}