{
  "type": "Feature",
  "properties": {
    "iso:country":"US",
    "sg:address":"225 Santa Monica Blvd",
    "sg:city":"Santa Monica",
    "sg:classifiers":[
        {
            "category":"Restaurant",
            "type":"Food & Drink"
        }
    ],
    "sg:menulink":"http://www.allmenus.com/ca/santa-monica/278919-anisette-brasserie/menu/",
    "sg:phone":"+1 310 395 3200",
    "sg:postcode":"90401",
    "sg:province":"CA",
    "sg:tags":[
        "french"
    ],
    "wof:name":"Anisette Brasserie",
    "wof:placetype":"venue"
},
  "geometry": {"coordinates":[-118.496905,34.015209],"type":"Point"}
}