{
  "type": "Feature",
  "properties": {
    "iso:country":"US",
    "sg:address":"14919 Dickens St",
    "sg:city":"Sherman Oaks",
    "sg:classifiers":[
        {
            "category":"Wholesale",
            "subcategory":"Computers",
            "type":"Manufacturing & Wholesale Goods"
        }
    ],
    "sg:phone":"+1 818 788 3573",
    "sg:postcode":"91403",
    "sg:province":"CA",
    "wof:name":"Sensor Design Association",
    "wof:placetype":"venue"
},
  "geometry": {"coordinates":[-118.46063700000001,34.151678],"type":"Point"}
}