{
  "type": "Feature",
  "properties": {
    "addr:full":"1466 S Main St Willits CA 95490",
    "addr:housenumber":"1466",
    "addr:postcode":"95490",
    "addr:street":"S Main St",
    "iso:country":"US",
    "sg:address":"1466 S Main St",
    "sg:city":"Willits",
    "sg:classifiers":[
        {
            "category":"Banks & Credit Unions",
            "subcategory":"Bank",
            "type":"Services"
        }
    ],
    "sg:phone":"+1 707 456 0339",
    "sg:postcode":"95490",
    "sg:province":"CA",
    "sg:tags":[
        "cashing",
        "check"
    ],
    "wof:name":"Ace Payday Advance",
    "wof:placetype":"venue"
},
  "geometry": {"coordinates":[-123.349322,39.39539],"type":"Point"}
}