{
  "type": "Feature",
  "properties": {
    "addr:full":"38594 Friendly Ave Palmdale CA 93550",
    "addr:postcode":"38594;ca 93550",
    "addr:street":"Friendly Ave",
    "iso:country":"US",
    "sg:address":"38594 Friendly Ave",
    "sg:city":"Palmdale",
    "sg:classifiers":[
        {
            "category":"Manufacturing",
            "subcategory":"Signs",
            "type":"Manufacturing & Wholesale Goods"
        }
    ],
    "sg:phone":"+1 661 265 9305",
    "sg:postcode":"93550",
    "sg:province":"CA",
    "wof:name":"Sign Graphics",
    "wof:placetype":"venue"
},
  "geometry": {"coordinates":[-118.115218,34.583845],"type":"Point"}
}