{
  "type": "Feature",
  "properties": {
    "iso:country":"US",
    "sg:address":"2370 Bryant Street",
    "sg:city":"San Francisco",
    "sg:classifiers":[
        {
            "category":"Building & Trades",
            "subcategory":"Construction",
            "type":"Services"
        }
    ],
    "sg:phone":"+1 415 282 1016",
    "sg:postcode":"94110",
    "sg:province":"CA",
    "sg:tags":[
        "painter"
    ],
    "wof:name":"Estrada's Painting & Decorating",
    "wof:placetype":"venue"
},
  "geometry": {"coordinates":[-122.410004,37.7565],"type":"Point"}
}