{
  "type": "Feature",
  "properties": {
    "addr:full":"3650 Industrial Blvd West Sacramento CA 95691",
    "addr:housenumber":"3650",
    "addr:postcode":"95691",
    "addr:street":"Industrial Blvd",
    "iso:country":"US",
    "sg:address":"3650 Industrial Blvd",
    "sg:city":"West Sacramento",
    "sg:classifiers":[
        {
            "category":"Government",
            "subcategory":"Office",
            "type":"Public Place"
        }
    ],
    "sg:phone":"+1 916 375 8370",
    "sg:postcode":"95691",
    "sg:province":"CA",
    "sg:tags":[
        "administrative",
        "program",
        "health"
    ],
    "wof:name":"Cid/Mass Mail",
    "wof:placetype":"venue"
},
  "geometry": {"coordinates":[-121.56273899999999,38.573456],"type":"Point"}
}