{
  "type": "Feature",
  "properties": {
    "iso:country":"US",
    "sg:address":"315 South Coast Hwy 101 Suite u78",
    "sg:city":"Encinitas",
    "sg:classifiers":[
        {
            "category":"Shopping",
            "subcategory":"Clothing, Apparel, & Fashions",
            "type":"Retail Goods"
        }
    ],
    "sg:phone":"+1 760 846 0169",
    "sg:postcode":"92024",
    "sg:province":"CA",
    "sg:tags":[
        "clothing",
        "women's"
    ],
    "sg:website":"www.ccchic.com",
    "wof:name":"CC Chic",
    "wof:placetype":"venue"
},
  "geometry": {"coordinates":[-117.293693,33.048358],"type":"Point"}
}