{
  "type": "Feature",
  "properties": {
    "addr:full":"19400 Tuolumne Rd Tuolumne CA 95379",
    "addr:housenumber":"19400",
    "addr:postcode":"95379",
    "addr:street":"Tuolumne Rd",
    "iso:country":"US",
    "sg:address":"19400 Tuolumne Rd",
    "sg:city":"Tuolumne",
    "sg:classifiers":[
        {
            "category":"Recreation",
            "subcategory":"Arcade",
            "type":"Entertainment"
        }
    ],
    "sg:phone":"+1 209 928 9300",
    "sg:postcode":"95379",
    "sg:province":"CA",
    "sg:tags":[
        "casino"
    ],
    "sg:website":"www.blackoakcasino.com",
    "wof:name":"Black Oak Casino",
    "wof:placetype":"venue"
},
  "geometry": {"coordinates":[-120.239937,37.974852],"type":"Point"}
}