{
  "type": "Feature",
  "properties": {
    "iso:country":"US",
    "sg:address":"20122 Imperial Cove Ln",
    "sg:city":"Huntington Beach",
    "sg:classifiers":[
        {
            "category":"Food & Beverages",
            "subcategory":"Candy",
            "type":"Retail Goods"
        }
    ],
    "sg:phone":"+1 714 968 3681",
    "sg:postcode":"92646",
    "sg:province":"CA",
    "sg:tags":[
        "gourmet",
        "basket",
        "gift"
    ],
    "wof:name":"Grand Gourmet",
    "wof:placetype":"venue"
},
  "geometry": {"coordinates":[-117.977225,33.6692],"type":"Point"}
}