{
  "type": "Feature",
  "properties": {
    "iso:country":"US",
    "sg:address":"41111 Mission Blvd",
    "sg:city":"Fremont",
    "sg:classifiers":[
        {
            "category":"Real Estate",
            "subcategory":"Real Estate Services",
            "type":"Services"
        },
        {
            "category":"Insurance",
            "subcategory":"Title Insurance",
            "type":"Services"
        },
        {
            "category":"Banks & Credit Unions",
            "subcategory":"Financial Services",
            "type":"Services"
        }
    ],
    "sg:phone":"+1 510 979 1952",
    "sg:postcode":"94539",
    "sg:province":"CA",
    "sg:tags":[
        "mortgage",
        "escrow"
    ],
    "wof:name":"Chicago Title",
    "wof:placetype":"venue"
},
  "geometry": {"coordinates":[-121.93923700000001,37.549341],"type":"Point"}
}