{
  "type": "Feature",
  "properties": {
    "addr:full":"12121 Seal Beach Blvd Seal Beach CA 90740",
    "addr:housenumber":"12121",
    "addr:postcode":"90740",
    "addr:street":"Seal Beach Blvd",
    "iso:country":"US",
    "sg:address":"12121 Seal Beach Blvd",
    "sg:city":"Seal Beach",
    "sg:classifiers":[
        {
            "category":"Shopping Center",
            "type":"Public Place"
        }
    ],
    "sg:phone":"+1 562 430 0211",
    "sg:postcode":"90740",
    "sg:province":"CA",
    "wof:name":"Rossmoor Business Center",
    "wof:placetype":"venue"
},
  "geometry": {"coordinates":[-118.07199900000001,33.785999],"type":"Point"}
}