{
  "type": "Feature",
  "properties": {
    "addr:full":"1939 Harrison St Oakland CA 94612",
    "addr:housenumber":"1939",
    "addr:postcode":"94612",
    "addr:street":"Harrison St",
    "iso:country":"US",
    "sg:address":"1939 Harrison St",
    "sg:city":"Oakland",
    "sg:classifiers":[
        {
            "category":"Professional",
            "subcategory":"Management & Consulting",
            "type":"Services"
        }
    ],
    "sg:phone":"+1 510 832 1415",
    "sg:postcode":"94612",
    "sg:province":"CA",
    "sg:tags":[
        "food",
        "facility"
    ],
    "wof:name":"Scientific Certification Systs",
    "wof:placetype":"venue"
},
  "geometry": {"coordinates":[-122.264605,37.808071],"type":"Point"}
}