{
  "type": "Feature",
  "properties": {
    "addr:full":"1900 E 21st St Signal Hill CA 90755",
    "addr:housenumber":"1900",
    "addr:postcode":"90755",
    "addr:street":"E 21St St",
    "iso:country":"US",
    "sg:address":"1900 E 21st St",
    "sg:city":"Signal Hill",
    "sg:classifiers":[
        {
            "category":"Education",
            "subcategory":"School",
            "type":"Public Place"
        }
    ],
    "sg:phone":"+1 562 985 0019",
    "sg:postcode":"90755",
    "sg:province":"CA",
    "wof:name":"Alvarado Elementary School",
    "wof:placetype":"venue"
},
  "geometry": {"coordinates":[-118.169882,33.795035],"type":"Point"}
}