{
  "type": "Feature",
  "properties": {
    "addr:full":"135 Post St San Francisco CA 94108",
    "addr:housenumber":"135",
    "addr:postcode":"94108",
    "addr:street":"Post St",
    "iso:country":"US",
    "sg:address":"135 Post St",
    "sg:city":"San Francisco",
    "sg:classifiers":[
        {
            "category":"Shopping",
            "subcategory":"Department Store",
            "type":"Retail Goods"
        }
    ],
    "sg:phone":"+1 415 982 1616",
    "sg:postcode":"94108",
    "sg:province":"CA",
    "sg:tags":[
        "shop"
    ],
    "sg:website":"www.gumps.com",
    "wof:name":"Gump's San Francisco Inc",
    "wof:placetype":"venue"
},
  "geometry": {"coordinates":[-122.405044,37.788647],"type":"Point"}
}