{
  "type": "Feature",
  "properties": {
    "addr:full":"12611 Vanowen St North Hollywood CA 91605",
    "addr:housenumber":"12611",
    "addr:postcode":"91605",
    "addr:street":"Vanowen St",
    "iso:country":"US",
    "sg:address":"12611 Vanowen St",
    "sg:city":"North Hollywood",
    "sg:classifiers":[
        {
            "category":"Building & Trades",
            "subcategory":"Construction",
            "type":"Services"
        }
    ],
    "sg:phone":"+1 818 255 2229",
    "sg:postcode":"91605",
    "sg:province":"CA",
    "sg:tags":[
        "general",
        "contractor"
    ],
    "wof:name":"Benlain Brothers Construction",
    "wof:placetype":"venue"
},
  "geometry": {"coordinates":[-118.409237,34.194015],"type":"Point"}
}