{
  "type": "Feature",
  "properties": {
    "iso:country":"US",
    "sg:address":"7354 Stoney Creek Dr #C",
    "sg:city":"Highland",
    "sg:classifiers":[
        {
            "category":"Retail",
            "subcategory":"Auto Rental",
            "type":"Services"
        },
        {
            "category":"Retail",
            "subcategory":"Storage",
            "type":"Services"
        }
    ],
    "sg:phone":"+1 909 425 9188",
    "sg:postcode":"92346",
    "sg:province":"CA",
    "sg:tags":[
        "moving-self",
        "truck"
    ],
    "sg:website":"http://www.uhaul.com/Locations/Rentals-near-Highland-CA-92346/003493",
    "wof:name":"U-Haul Neighborhood Dealer - Fastlane Highland",
    "wof:placetype":"venue"
},
  "geometry": {"coordinates":[-117.196747,34.12101],"type":"Point"}
}