{
  "type": "Feature",
  "properties": {
    "addr:full":"740 Front Street Santa Cruz CA 95060",
    "addr:housenumber":"740",
    "addr:postcode":"95060",
    "addr:street":"Front Street",
    "iso:country":"US",
    "sg:address":"740 Front Street",
    "sg:city":"Santa Cruz",
    "sg:classifiers":[
        {
            "category":"Health Services",
            "subcategory":"Chiropractor",
            "type":"Services"
        }
    ],
    "sg:phone":"+1 831 458 1188",
    "sg:postcode":"95060",
    "sg:province":"CA",
    "wof:name":"Abend Richard M DC",
    "wof:placetype":"venue"
},
  "geometry": {"coordinates":[-122.025409,36.975226],"type":"Point"}
}