{
  "type": "Feature",
  "properties": {
    "addr:full":"1700 W Victoria Ave Montebello CA 90640",
    "addr:housenumber":"1700",
    "addr:postcode":"90640",
    "addr:street":"W Victoria Ave",
    "iso:country":"US",
    "sg:address":"1700 W Victoria Ave",
    "sg:city":"Montebello",
    "sg:classifiers":[
        {
            "category":"Government",
            "subcategory":"Office",
            "type":"Public Place"
        }
    ],
    "sg:phone":"+1 323 887 4544",
    "sg:postcode":"90640",
    "sg:province":"CA",
    "sg:tags":[
        "department",
        "recreation",
        "parks"
    ],
    "wof:name":"Parks and Recreation",
    "wof:placetype":"venue"
},
  "geometry": {"coordinates":[-118.115194,34.021069],"type":"Point"}
}