{
  "type": "Feature",
  "properties": {
    "addr:full":"4830 E Kings Canyon Rd Fresno CA 93727",
    "addr:housenumber":"4830",
    "addr:postcode":"93727",
    "addr:street":"E Kings Canyon Rd",
    "iso:country":"US",
    "sg:address":"4830 E Kings Canyon Rd",
    "sg:city":"Fresno",
    "sg:classifiers":[
        {
            "category":"Autos & Motor Vehicles",
            "subcategory":"Auto Supplies",
            "type":"Retail Goods"
        }
    ],
    "sg:phone":"+1 559 252 3771",
    "sg:postcode":"93727",
    "sg:province":"CA",
    "sg:tags":[
        "tire"
    ],
    "wof:name":"Goodguys Tire Ctr",
    "wof:placetype":"venue"
},
  "geometry": {"coordinates":[-119.73533999999999,36.735846],"type":"Point"}
}