{
  "type": "Feature",
  "properties": {
    "iso:country":"US",
    "sg:address":"1150 N Vermont Ave",
    "sg:city":"Los Angeles",
    "sg:classifiers":[
        {
            "category":"Shopping",
            "subcategory":"Used Merchandise",
            "type":"Retail Goods"
        }
    ],
    "sg:phone":"+1 323 663 2066",
    "sg:postcode":"90029",
    "sg:province":"CA",
    "sg:tags":[
        "shop",
        "thrift"
    ],
    "wof:name":"Out Of The Closet Thrift Store",
    "wof:placetype":"venue"
},
  "geometry": {"coordinates":[-118.291743,34.093444],"type":"Point"}
}