{
  "type": "Feature",
  "properties": {
    "iso:country":"US",
    "sg:address":"1195 S Main St",
    "sg:city":"Angels Camp",
    "sg:phone":"+1 209 736 0449",
    "sg:postcode":"95222",
    "sg:province":"CA",
    "sg:tags":[
        "gas"
    ],
    "wof:name":"Campora Propane Svc",
    "wof:placetype":"venue"
},
  "geometry": {"coordinates":[-120.540468,38.069912],"type":"Point"}
}