{
  "type": "Feature",
  "properties": {
    "iso:country":"US",
    "sg:address":"8310 Alpine Rd",
    "sg:city":"La Honda",
    "sg:classifiers":[
        {
            "category":"Retail",
            "subcategory":"Auto Repair",
            "type":"Services"
        }
    ],
    "sg:phone":"+1 650 747 0900",
    "sg:postcode":"94020",
    "sg:province":"CA",
    "sg:tags":[
        "truck"
    ],
    "wof:name":"Roy's Repair Svc",
    "wof:placetype":"venue"
},
  "geometry": {"coordinates":[-122.26516100000001,37.299437],"type":"Point"}
}