{
  "type": "Feature",
  "properties": {
    "addr:full":"3510 Fruitvale Ave Oakland CA 94602",
    "addr:housenumber":"3510",
    "addr:postcode":"94602",
    "addr:street":"Fruitvale Ave",
    "iso:country":"US",
    "sg:address":"3510 Fruitvale Ave",
    "sg:city":"Oakland",
    "sg:classifiers":[
        {
            "category":"Professional",
            "type":"Services"
        }
    ],
    "sg:phone":"+1 510 482 2288",
    "sg:postcode":"94602",
    "sg:province":"CA",
    "wof:name":"Housewares Etc",
    "wof:placetype":"venue"
},
  "geometry": {"coordinates":[-122.21545399999999,37.801907],"type":"Point"}
}