{
  "type": "Feature",
  "properties": {
    "addr:full":"8301 Utica Ave Rancho Cucamonga CA 91730",
    "addr:housenumber":"8301",
    "addr:postcode":"91730",
    "addr:street":"Utica Ave",
    "iso:country":"US",
    "sg:address":"8301 Utica Ave",
    "sg:city":"Rancho Cucamonga",
    "sg:classifiers":[
        {
            "category":"Health Services",
            "subcategory":"Clinic",
            "type":"Services"
        }
    ],
    "sg:phone":"+1 909 980 5341",
    "sg:postcode":"91730",
    "sg:province":"CA",
    "sg:tags":[
        "home"
    ],
    "wof:name":"American Companion & Homemaker",
    "wof:placetype":"venue"
},
  "geometry": {"coordinates":[-117.57054100000001,34.103218],"type":"Point"}
}