{
  "type": "Feature",
  "properties": {
    "iso:country":"US",
    "sg:address":"1265 Jonas Ave",
    "sg:city":"Sacramento",
    "sg:classifiers":[
        {
            "category":"Organizations",
            "subcategory":"Religious Organization",
            "type":"Services"
        }
    ],
    "sg:phone":"+1 916 485 2090",
    "sg:postcode":"95864",
    "sg:province":"CA",
    "sg:tags":[
        "church"
    ],
    "wof:name":"Jehovah Witnesses-Arden",
    "wof:placetype":"venue"
},
  "geometry": {"coordinates":[-121.396939,38.587534],"type":"Point"}
}