{
  "type": "Feature",
  "properties": {
    "addr:full":"19601 Gas Point Rd Cottonwood CA 96022",
    "addr:housenumber":"19601",
    "addr:postcode":"96022",
    "addr:street":"Gas Point Rd",
    "iso:country":"US",
    "sg:address":"19601 Gas Point Rd",
    "sg:city":"Cottonwood",
    "sg:classifiers":[
        {
            "category":"Farming",
            "subcategory":"Farm",
            "type":"Manufacturing & Wholesale Goods"
        }
    ],
    "sg:phone":"+1 530 347 0468",
    "sg:postcode":"96022",
    "sg:province":"CA",
    "wof:name":"Gas Point Worm Farm",
    "wof:placetype":"venue"
},
  "geometry": {"coordinates":[-122.327974,40.38908],"type":"Point"}
}