{
  "type": "Feature",
  "properties": {
    "addr:full":"1328 S Concord Ln Glendora CA 91740",
    "addr:housenumber":"1328",
    "addr:postcode":"91740",
    "addr:street":"S Concord Ln",
    "iso:country":"US",
    "sg:address":"1328 S Concord Ln",
    "sg:city":"Glendora",
    "sg:classifiers":[
        {
            "category":"Manufacturing",
            "subcategory":"Tools & Machinery",
            "type":"Manufacturing & Wholesale Goods"
        }
    ],
    "sg:phone":"+1 626 674 7247",
    "sg:postcode":"91740",
    "sg:province":"CA",
    "sg:tags":[
        "industrial",
        "mfg"
    ],
    "wof:name":"Markarian Markar",
    "wof:placetype":"venue"
},
  "geometry": {"coordinates":[-117.858818,34.113956],"type":"Point"}
}