{
  "type": "Feature",
  "properties": {
    "iso:country":"US",
    "sg:address":"13156 Mindanao Way",
    "sg:city":"Marina del Rey",
    "sg:classifiers":[
        {
            "category":"Building & Trades",
            "subcategory":"Cleaning & Sanitation",
            "type":"Services"
        }
    ],
    "sg:phone":"+1 310 974 8425",
    "sg:postcode":"90292",
    "sg:province":"CA",
    "sg:tags":[
        "home",
        "carpet"
    ],
    "sg:website":"www.no-odor-cleaning.com",
    "wof:name":"No Odor Cleaning",
    "wof:placetype":"venue"
},
  "geometry": {"coordinates":[-118.437511,33.984763],"type":"Point"}
}