{
  "type": "Feature",
  "properties": {
    "iso:country":"US",
    "sg:address":"1045 E Imperial Hwy",
    "sg:city":"Placentia",
    "sg:phone":"+1 714 223 7878",
    "sg:postcode":"92870",
    "sg:province":"CA",
    "wof:name":"Oishi Restaurant",
    "wof:placetype":"venue"
},
  "geometry": {"coordinates":[-117.84559400000001,33.905899],"type":"Point"}
}