{
  "type": "Feature",
  "properties": {
    "addr:full":"1410 Elmwood St Redding CA 96001",
    "addr:housenumber":"1410",
    "addr:postcode":"96001",
    "addr:street":"Elmwood St",
    "iso:country":"US",
    "sg:address":"1410 Elmwood St",
    "sg:city":"Redding",
    "sg:classifiers":[
        {
            "category":"Building & Trades",
            "subcategory":"Construction",
            "type":"Services"
        }
    ],
    "sg:phone":"+1 530 244 3074",
    "sg:postcode":"96001",
    "sg:province":"CA",
    "sg:tags":[
        "fire",
        "restoration",
        "damage"
    ],
    "wof:name":"AAAA Truck Mount Steam Crpt",
    "wof:placetype":"venue"
},
  "geometry": {"coordinates":[-122.389895,40.57053],"type":"Point"}
}