{
  "type": "Feature",
  "properties": {
    "iso:country":"US",
    "sg:address":"1750 El Camino Real",
    "sg:city":"Burlingame",
    "sg:classifiers":[
        {
            "category":"Health Services",
            "subcategory":"Doctor",
            "type":"Services"
        }
    ],
    "sg:phone":"+1 650 697 6632",
    "sg:postcode":"94010",
    "sg:province":"CA",
    "wof:name":"Telfer Robt B MD",
    "wof:placetype":"venue"
},
  "geometry": {"coordinates":[-122.38200399999999,37.593601],"type":"Point"}
}