{
  "type": "Feature",
  "properties": {
    "iso:country":"US",
    "sg:address":"4032 E Acequia Ave",
    "sg:city":"Visalia",
    "sg:classifiers":[
        {
            "category":"Real Estate",
            "subcategory":"Developer",
            "type":"Services"
        }
    ],
    "sg:phone":"+1 559 733 4663",
    "sg:postcode":"93292",
    "sg:province":"CA",
    "wof:name":"Buyers Choice",
    "wof:placetype":"venue"
},
  "geometry": {"coordinates":[-119.247844,36.329219],"type":"Point"}
}