{
  "type": "Feature",
  "properties": {
    "addr:full":"1905 Union St San Francisco CA 94123",
    "addr:housenumber":"1905",
    "addr:postcode":"94123",
    "addr:street":"Union St",
    "iso:country":"US",
    "sg:address":"1905 Union St",
    "sg:city":"San Francisco",
    "sg:classifiers":[
        {
            "category":"Personal",
            "subcategory":"Massage",
            "type":"Services"
        }
    ],
    "sg:phone":"+1 415 722 1491",
    "sg:postcode":"94123",
    "sg:province":"CA",
    "sg:website":"elementbodywork.com",
    "wof:name":"Element Bodywork",
    "wof:placetype":"venue"
},
  "geometry": {"coordinates":[-122.43070899999999,37.797535],"type":"Point"}
}