{
  "type": "Feature",
  "properties": {
    "addr:full":"1017 Eleanor Ln Manteca CA 95337",
    "addr:housenumber":"1017",
    "addr:postcode":"95337",
    "addr:street":"Eleanor Ln",
    "iso:country":"US",
    "sg:address":"1017 Eleanor Ln",
    "sg:city":"Manteca",
    "sg:classifiers":[
        {
            "category":"Shopping",
            "subcategory":"Crafts & Fabrics",
            "type":"Retail Goods"
        }
    ],
    "sg:phone":"+1 209 825 5956",
    "sg:postcode":"95337",
    "sg:province":"CA",
    "sg:tags":[
        "sewing"
    ],
    "wof:name":"Cindys Kids Can Sew",
    "wof:placetype":"venue"
},
  "geometry": {"coordinates":[-121.243116,37.789634],"type":"Point"}
}