{
  "type": "Feature",
  "properties": {
    "addr:full":"10721 54th St Mira Loma CA 91752",
    "addr:housenumber":"10721",
    "addr:postcode":"91752",
    "addr:street":"54Th St",
    "iso:country":"US",
    "sg:address":"10721 54th St",
    "sg:city":"Mira Loma",
    "sg:phone":"+1 951 685 8216",
    "sg:postcode":"91752",
    "sg:province":"CA",
    "sg:tags":[
        "farm",
        "field",
        "livestock",
        "crop",
        "general"
    ],
    "wof:name":"Marshall Leach",
    "wof:placetype":"venue"
},
  "geometry": {"coordinates":[-117.51978099999999,33.990077],"type":"Point"}
}