{
  "type": "Feature",
  "properties": {
    "iso:country":"US",
    "sg:address":"3527 Mt Diablo Blvd",
    "sg:city":"Lafayette",
    "sg:classifiers":[
        {
            "category":"Professional",
            "subcategory":"Advertising",
            "type":"Services"
        },
        {
            "category":"Restaurant",
            "type":"Food & Drink"
        },
        {
            "category":"Shopping",
            "type":"Retail Goods"
        },
        {
            "category":"Building & Trades",
            "subcategory":"Construction",
            "type":"Services"
        }
    ],
    "sg:phone":"+1 925 284 7168",
    "sg:postcode":"94549",
    "sg:province":"CA",
    "sg:tags":[
        "repair",
        "coupon",
        "maintenance",
        "home",
        "merchandise"
    ],
    "sg:website":"http://www.yellowpagescoupons.net",
    "wof:name":"YELLOW PAGES COUPONS",
    "wof:placetype":"venue"
},
  "geometry": {"coordinates":[-122.118864,37.891995],"type":"Point"}
}