{
  "type": "Feature",
  "properties": {
    "iso:country":"US",
    "sg:address":"6354 Tami Way",
    "sg:city":"Carmichael",
    "sg:classifiers":[
        {
            "category":"Health Services",
            "subcategory":"Clinic",
            "type":"Services"
        }
    ],
    "sg:phone":"+1 916 595 4958",
    "sg:postcode":"95608",
    "sg:province":"CA",
    "sg:tags":[
        "welfare"
    ],
    "wof:name":"Nu Health",
    "wof:placetype":"venue"
},
  "geometry": {"coordinates":[-121.316643,38.639164],"type":"Point"}
}