{
  "type": "Feature",
  "properties": {
    "iso:country":"US",
    "sg:address":"9611 Magnolia Ave",
    "sg:city":"Riverside",
    "sg:classifiers":[
        {
            "category":"Manufacturing",
            "subcategory":"Glass & Minerals",
            "type":"Manufacturing & Wholesale Goods"
        },
        {
            "category":"Retail",
            "subcategory":"Auto Repair",
            "type":"Services"
        }
    ],
    "sg:phone":"+1 877 298 6055",
    "sg:postcode":"92503",
    "sg:province":"CA",
    "sg:tags":[
        "plate",
        "window",
        "windshield",
        "glass-auto"
    ],
    "sg:website":"http://local.ingenio.com/Listings/Details.aspx?NUM=a%3a10300654%3a13%3a4859924%3a14%3a0%3a7",
    "wof:name":"Auto Glass 4 Less",
    "wof:placetype":"venue"
},
  "geometry": {"coordinates":[-117.448626,33.919249],"type":"Point"}
}