{
  "type": "Feature",
  "properties": {
    "iso:country":"US",
    "sg:address":"7001 W Imperial Hwy",
    "sg:city":"Los Angeles",
    "sg:classifiers":[
        {
            "category":"Airport",
            "type":"Transportation"
        }
    ],
    "sg:phone":"+1 310 338 0063",
    "sg:postcode":"90045",
    "sg:province":"CA",
    "sg:tags":[
        "aircraft",
        "maintenance"
    ],
    "wof:name":"F & E Aircraft Maintenance",
    "wof:placetype":"venue"
},
  "geometry": {"coordinates":[-118.418443,33.931454],"type":"Point"}
}