{
  "type": "Feature",
  "properties": {
    "addr:full":"1351 W Clayton Ave Fresno CA 93706",
    "addr:housenumber":"1351",
    "addr:postcode":"93706",
    "addr:street":"W Clayton Ave",
    "iso:country":"US",
    "sg:address":"1351 W Clayton Ave",
    "sg:city":"Fresno",
    "sg:classifiers":[
        {
            "category":"Farming",
            "subcategory":"Vineyard",
            "type":"Manufacturing & Wholesale Goods"
        }
    ],
    "sg:phone":"+1 559 441 1601",
    "sg:postcode":"93706",
    "sg:province":"CA",
    "sg:tags":[
        "grape"
    ],
    "wof:name":"Donald Steinhauer",
    "wof:placetype":"venue"
},
  "geometry": {"coordinates":[-119.812395,36.641338],"type":"Point"}
}