{
  "type": "Feature",
  "properties": {
    "addr:full":"1035 S Winchester Blvd San Jose CA 95128",
    "addr:housenumber":"1035",
    "addr:postcode":"95128",
    "addr:street":"S Winchester Blvd",
    "iso:country":"US",
    "sg:address":"1035 S Winchester Blvd",
    "sg:city":"San Jose",
    "sg:classifiers":[
        {
            "category":"Restaurant",
            "type":"Food & Drink"
        }
    ],
    "sg:phone":"+1 408 260 0255",
    "sg:postcode":"95128",
    "sg:province":"CA",
    "wof:name":"Niko Japanese Restaurant",
    "wof:placetype":"venue"
},
  "geometry": {"coordinates":[-121.95009899999999,37.307907],"type":"Point"}
}