{
  "type": "Feature",
  "properties": {
    "addr:full":"12780 Pierce St Pacoima CA 91331",
    "addr:housenumber":"12780",
    "addr:postcode":"91331",
    "addr:street":"Pierce St",
    "iso:country":"US",
    "sg:address":"12780 Pierce St",
    "sg:city":"Pacoima",
    "sg:classifiers":[
        {
            "category":"Professional",
            "subcategory":"Engineering",
            "type":"Services"
        }
    ],
    "sg:phone":"+1 818 834 2699",
    "sg:postcode":"91331",
    "sg:province":"CA",
    "sg:tags":[
        "engineer"
    ],
    "wof:name":"CSI",
    "wof:placetype":"venue"
},
  "geometry": {"coordinates":[-118.41141,34.26857],"type":"Point"}
}