{
  "type": "Feature",
  "properties": {
    "iso:country":"US",
    "sg:address":"1003 Eye St",
    "sg:city":"Bakersfield",
    "sg:classifiers":[
        {
            "category":"Communications",
            "subcategory":"Television Station",
            "type":"Services"
        }
    ],
    "sg:phone":"+1 661 631 2901",
    "sg:postcode":"93304",
    "sg:province":"CA",
    "wof:name":"Ihr Educational Broadcasting",
    "wof:placetype":"venue"
},
  "geometry": {"coordinates":[-119.020132,35.367457],"type":"Point"}
}