{
  "type": "Feature",
  "properties": {
    "addr:full":"1008 E 49th Pl Los Angeles CA 90011",
    "addr:housenumber":"1008",
    "addr:postcode":"90011",
    "addr:street":"E 49Th Pl",
    "iso:country":"US",
    "sg:address":"1008 E 49th Pl",
    "sg:city":"Los Angeles",
    "sg:classifiers":[
        {
            "category":"Professional",
            "type":"Services"
        }
    ],
    "sg:phone":"+1 323 232 3948",
    "sg:postcode":"90011",
    "sg:province":"CA",
    "wof:name":"Emeldo Mercado",
    "wof:placetype":"venue"
},
  "geometry": {"coordinates":[-118.256607,33.998389],"type":"Point"}
}