{
  "type": "Feature",
  "properties": {
    "iso:country":"US",
    "sg:address":"2707 S Diamond Bar Blvd",
    "sg:city":"Diamond Bar",
    "sg:classifiers":[
        {
            "category":"Real Estate",
            "subcategory":"Architect",
            "type":"Services"
        }
    ],
    "sg:phone":"+1 909 869 6191",
    "sg:postcode":"91765",
    "sg:province":"CA",
    "sg:tags":[
        "estimate",
        "construction"
    ],
    "wof:name":"Horizon Pacific Inc",
    "wof:placetype":"venue"
},
  "geometry": {"coordinates":[-117.836791,33.9751],"type":"Point"}
}