{
  "type": "Feature",
  "properties": {
    "addr:full":"14337 Pioneer Blvd Norwalk CA 90650",
    "addr:housenumber":"14337",
    "addr:postcode":"90650",
    "addr:street":"Pioneer Blvd",
    "iso:country":"US",
    "sg:address":"14337 Pioneer Blvd",
    "sg:city":"Norwalk",
    "sg:classifiers":[
        {
            "category":"Shopping",
            "subcategory":"Optician",
            "type":"Retail Goods"
        }
    ],
    "sg:phone":"+1 562 865 5355",
    "sg:postcode":"90650",
    "sg:province":"CA",
    "sg:tags":[
        "eyewear"
    ],
    "wof:name":"Best Optical",
    "wof:placetype":"venue"
},
  "geometry": {"coordinates":[-118.08259200000001,33.901068],"type":"Point"}
}