{
  "type": "Feature",
  "properties": {
    "iso:country":"US",
    "sg:address":"3525 Del Mar Heights Rd",
    "sg:city":"San Diego",
    "sg:classifiers":[
        {
            "category":"Real Estate",
            "subcategory":"Real Estate Services",
            "type":"Services"
        }
    ],
    "sg:phone":"+1 800 788 4128",
    "sg:postcode":"92121",
    "sg:province":"CA",
    "sg:website":"legalloanaudits.com",
    "wof:name":"Legal Loan Audits",
    "wof:placetype":"venue"
},
  "geometry": {"coordinates":[-117.230732,32.953441],"type":"Point"}
}