{
  "type": "Feature",
  "properties": {
    "addr:full":"400 Montgomery St San Francisco CA 94104",
    "addr:housenumber":"400",
    "addr:postcode":"94104",
    "addr:street":"Montgomery St",
    "iso:country":"US",
    "sg:address":"400 Montgomery St",
    "sg:city":"San Francisco",
    "sg:classifiers":[
        {
            "category":"Professional",
            "subcategory":"Lawyer & Legal Services",
            "type":"Services"
        }
    ],
    "sg:phone":"+1 415 433 2250",
    "sg:postcode":"94104",
    "sg:province":"CA",
    "sg:tags":[
        "attorney"
    ],
    "wof:name":"Girard & Equitz",
    "wof:placetype":"venue"
},
  "geometry": {"coordinates":[-122.402957,37.79378],"type":"Point"}
}