{
  "type": "Feature",
  "properties": {
    "iso:country":"US",
    "sg:address":"1190 Pacific Coast Hwy",
    "sg:city":"Seal Beach",
    "sg:classifiers":[
        {
            "category":"Wholesale",
            "subcategory":"Medical Equipment & Supplies",
            "type":"Manufacturing & Wholesale Goods"
        }
    ],
    "sg:phone":"+1 562 430 5322",
    "sg:postcode":"90740",
    "sg:province":"CA",
    "wof:name":"Ron Pelton Certified Hypnothe",
    "wof:placetype":"venue"
},
  "geometry": {"coordinates":[-118.10162,33.744029],"type":"Point"}
}