{
  "type": "Feature",
  "properties": {
    "addr:full":"2312 Lander Ave Turlock CA 95380",
    "addr:housenumber":"2312",
    "addr:postcode":"95380",
    "addr:street":"Lander Ave",
    "iso:country":"US",
    "sg:address":"2312 Lander Ave",
    "sg:city":"Turlock",
    "sg:classifiers":[
        {
            "category":"Building & Trades",
            "subcategory":"Construction",
            "type":"Services"
        }
    ],
    "sg:phone":"+1 209 634 0019",
    "sg:postcode":"95380",
    "sg:province":"CA",
    "sg:tags":[
        "tile",
        "dealer"
    ],
    "wof:name":"Turlock Tile & Stone Co",
    "wof:placetype":"venue"
},
  "geometry": {"coordinates":[-120.848912,37.471699],"type":"Point"}
}