{
  "type": "Feature",
  "properties": {
    "addr:full":"2736 Madison St Carlsbad CA 92008",
    "addr:housenumber":"2736",
    "addr:postcode":"92008",
    "addr:street":"Madison St",
    "iso:country":"US",
    "sg:address":"2736 Madison St",
    "sg:city":"Carlsbad",
    "sg:classifiers":[
        {
            "category":"Personal",
            "subcategory":"Skin Care",
            "type":"Services"
        }
    ],
    "sg:phone":"+1 760 434 5663",
    "sg:postcode":"92008",
    "sg:province":"CA",
    "wof:name":"The Works",
    "wof:placetype":"venue"
},
  "geometry": {"coordinates":[-117.34899900000001,33.1633],"type":"Point"}
}