{
  "type": "Feature",
  "properties": {
    "iso:country":"US",
    "sg:address":"9027 W Pico Blvd",
    "sg:city":"Los Angeles",
    "sg:classifiers":[
        {
            "category":"Real Estate",
            "subcategory":"Architect",
            "type":"Services"
        }
    ],
    "sg:phone":"+1 310 859 2995",
    "sg:postcode":"90035",
    "sg:province":"CA",
    "wof:name":"Keith Sidley Architectural",
    "wof:placetype":"venue"
},
  "geometry": {"coordinates":[-118.3884,34.055342],"type":"Point"}
}