{
  "type": "Feature",
  "properties": {
    "addr:full":"2160 Newbury Rd Newbury Park CA 91320",
    "addr:housenumber":"2160",
    "addr:postcode":"91320",
    "addr:street":"Newbury Rd",
    "iso:country":"US",
    "sg:address":"2160 Newbury Rd",
    "sg:city":"Newbury Park",
    "sg:classifiers":[
        {
            "category":"Restaurant",
            "type":"Food & Drink"
        }
    ],
    "sg:phone":"+1 805 499 9588",
    "sg:postcode":"91320",
    "sg:province":"CA",
    "wof:name":"Hunan Yuan",
    "wof:placetype":"venue"
},
  "geometry": {"coordinates":[-118.92186700000001,34.183865],"type":"Point"}
}