{
  "type": "Feature",
  "properties": {
    "iso:country":"US",
    "sg:address":"7400 San Ramon Rd",
    "sg:city":"Dublin",
    "sg:classifiers":[
        {
            "category":"Restaurant",
            "type":"Food & Drink"
        }
    ],
    "sg:phone":"+1 925 833 0995",
    "sg:postcode":"94568",
    "sg:province":"CA",
    "sg:website":"http://mcnamarasrestaurant.com/dublin.html",
    "wof:name":"Mc Namara's Steak & Chophouse",
    "wof:placetype":"venue"
},
  "geometry": {"coordinates":[-121.93708100000001,37.706709],"type":"Point"}
}