{
  "type": "Feature",
  "properties": {
    "iso:country":"US",
    "sg:address":"49 Hazel Ave",
    "sg:city":"Redwood City",
    "sg:classifiers":[
        {
            "category":"Home & Garden",
            "subcategory":"Garden Supply",
            "type":"Retail Goods"
        }
    ],
    "sg:phone":"+1 650 322 0421",
    "sg:postcode":"94061",
    "sg:province":"CA",
    "sg:tags":[
        "sprinkler"
    ],
    "sg:website":"www.peninsulairrigation.com",
    "wof:name":"Peninsula Irrigation Co",
    "wof:placetype":"venue"
},
  "geometry": {"coordinates":[-122.22070600000001,37.475021],"type":"Point"}
}