{
  "type": "Feature",
  "properties": {
    "addr:full":"9939 Via Pasar San Diego CA 92126",
    "addr:housenumber":"9939",
    "addr:postcode":"92126",
    "addr:street":"Via Pasar",
    "iso:country":"US",
    "sg:address":"9939 Via Pasar",
    "sg:city":"San Diego",
    "sg:classifiers":[
        {
            "category":"Manufacturing",
            "subcategory":"Electronics",
            "type":"Manufacturing & Wholesale Goods"
        }
    ],
    "sg:phone":"+1 858 621 2700",
    "sg:postcode":"92126",
    "sg:province":"CA",
    "sg:tags":[
        "measuring",
        "mfg",
        "component",
        "electrical",
        "inst",
        "electronic"
    ],
    "wof:name":"Z Communications Inc",
    "wof:placetype":"venue"
},
  "geometry": {"coordinates":[-117.12022399999999,32.899499],"type":"Point"}
}