{
  "type": "Feature",
  "properties": {
    "addr:full":"3911 Firestone Blvd South Gate CA 90280",
    "addr:housenumber":"3911",
    "addr:postcode":"90280",
    "addr:street":"Firestone Blvd;Gate",
    "iso:country":"US",
    "sg:address":"3911 Firestone Blvd",
    "sg:city":"South Gate",
    "sg:classifiers":[
        {
            "category":"Travel",
            "subcategory":"Hotels & Motels",
            "type":"Entertainment"
        }
    ],
    "sg:phone":"+1 323 567 1642",
    "sg:postcode":"90280",
    "sg:province":"CA",
    "wof:name":"El Grande Motel",
    "wof:placetype":"venue"
},
  "geometry": {"coordinates":[-118.200996,33.9538],"type":"Point"}
}