{
  "type": "Feature",
  "properties": {
    "addr:full":"8249 Meeks Bay Ave Tahoma CA 96142",
    "addr:housenumber":"8249",
    "addr:postcode":"96142",
    "addr:street":"Meeks Bay Ave",
    "iso:country":"US",
    "sg:address":"8249 Meeks Bay Ave",
    "sg:city":"Tahoma",
    "sg:classifiers":[
        {
            "category":"Manufacturing",
            "subcategory":"Tools & Machinery",
            "type":"Manufacturing & Wholesale Goods"
        }
    ],
    "sg:phone":"+1 530 525 0347",
    "sg:postcode":"96142",
    "sg:province":"CA",
    "sg:tags":[
        "measuring",
        "instrument",
        "electrical",
        "mfg"
    ],
    "wof:name":"Alternate Energy Inst",
    "wof:placetype":"venue"
},
  "geometry": {"coordinates":[-120.117943,39.034978],"type":"Point"}
}