{
  "type": "Feature",
  "properties": {
    "addr:full":"2356 Sutter Street San Francisco CA 94115",
    "addr:housenumber":"2356",
    "addr:postcode":"94115",
    "addr:street":"Sutter Street",
    "iso:country":"US",
    "sg:address":"2356 Sutter Street",
    "sg:city":"San Francisco",
    "sg:classifiers":[
        {
            "category":"Health Services",
            "subcategory":"Doctor",
            "type":"Services"
        }
    ],
    "sg:phone":"+1 415 885 7788",
    "sg:postcode":"94115",
    "sg:province":"CA",
    "wof:name":"Domush Robert MD",
    "wof:placetype":"venue"
},
  "geometry": {"coordinates":[-122.43820599999999,37.785478],"type":"Point"}
}