{
  "type": "Feature",
  "properties": {
    "addr:full":"17 N Slope Ln Pomona CA 91766",
    "addr:housenumber":"17",
    "addr:postcode":"91766",
    "addr:street":"N Slope Ln",
    "iso:country":"US",
    "sg:address":"17 N Slope Ln",
    "sg:city":"Pomona",
    "sg:classifiers":[
        {
            "category":"Wholesale",
            "subcategory":"Machinery & Supplies",
            "type":"Manufacturing & Wholesale Goods"
        }
    ],
    "sg:phone":"+1 909 620 5992",
    "sg:postcode":"91766",
    "sg:province":"CA",
    "sg:tags":[
        "tool",
        "industrial",
        "machining"
    ],
    "wof:name":"SD Manufacturing Sollutions",
    "wof:placetype":"venue"
},
  "geometry": {"coordinates":[-117.76415799999999,34.032619],"type":"Point"}
}