{
  "type": "Feature",
  "properties": {
    "addr:full":"3211 Scott Blvd. Suite 103 Santa Clara CA 95054",
    "addr:housenumber":"3211",
    "addr:postcode":"95054",
    "addr:street":"Scott Blvd. Suite 103",
    "iso:country":"US",
    "sg:address":"3211 Scott Blvd. Suite 103",
    "sg:city":"Santa Clara",
    "sg:classifiers":[
        {
            "category":"Manufacturing",
            "subcategory":"Electronics",
            "type":"Manufacturing & Wholesale Goods"
        }
    ],
    "sg:phone":"+1 408 689 0303",
    "sg:postcode":"95054",
    "sg:province":"CA",
    "sg:tags":[
        "quad-hd",
        "4k",
        "ultra-high-resolution",
        "consumer-electronics",
        "hdtv",
        "display",
        "rapid-prototyping",
        "virtual-silicon"
    ],
    "sg:website":"http://www.marseilleinc.com/marseille/",
    "wof:name":"Marseille Networks",
    "wof:placetype":"venue"
},
  "geometry": {"coordinates":[-121.96487999999999,37.39673],"type":"Point"}
}