{
  "type": "Feature",
  "properties": {
    "iso:country":"US",
    "sg:address":"700 W el Camino Real",
    "sg:city":"Mountain View",
    "sg:classifiers":[
        {
            "category":"Building & Trades",
            "subcategory":"Electrical",
            "type":"Services"
        }
    ],
    "sg:phone":"+1 650 934 8268",
    "sg:postcode":"94040",
    "sg:province":"CA",
    "sg:tags":[
        "electrical",
        "contractor"
    ],
    "wof:name":"I H I Company",
    "wof:placetype":"venue"
},
  "geometry": {"coordinates":[-122.081891,37.384674],"type":"Point"}
}