{
  "type": "Feature",
  "properties": {
    "addr:full":"822 Citron St Corona CA 92882",
    "addr:housenumber":"822",
    "addr:postcode":"92882",
    "addr:street":"Citron St",
    "iso:country":"US",
    "sg:address":"822 Citron St",
    "sg:city":"Corona",
    "sg:classifiers":[
        {
            "category":"Home & Garden",
            "subcategory":"Home Furnishings",
            "type":"Retail Goods"
        }
    ],
    "sg:phone":"+1 951 735 3397",
    "sg:postcode":"92882",
    "sg:province":"CA",
    "sg:tags":[
        "bedspread"
    ],
    "wof:name":"Doris' Home Apparel",
    "wof:placetype":"venue"
},
  "geometry": {"coordinates":[-117.578163,33.86306],"type":"Point"}
}