{
  "type": "Feature",
  "properties": {
    "iso:country":"US",
    "sg:address":"1411 W 8th St",
    "sg:city":"San Pedro",
    "sg:classifiers":[
        {
            "category":"Health Services",
            "subcategory":"Doctor",
            "type":"Services"
        }
    ],
    "sg:phone":"+1 310 832 5559",
    "sg:postcode":"90732",
    "sg:province":"CA",
    "sg:tags":[
        "dentist"
    ],
    "wof:name":"Peter Spennato Jr DDS",
    "wof:placetype":"venue"
},
  "geometry": {"coordinates":[-118.309674,33.737017],"type":"Point"}
}