{
  "type": "Feature",
  "properties": {
    "iso:country":"US",
    "sg:address":"691 Lomas Santa Fe Dr Ste A",
    "sg:city":"Solana Beach",
    "sg:classifiers":[
        {
            "category":"Restaurant",
            "type":"Food & Drink"
        }
    ],
    "sg:phone":"+1 858 259 5644",
    "sg:postcode":"92075",
    "sg:province":"CA",
    "wof:name":"Togo's Eatery",
    "wof:placetype":"venue"
},
  "geometry": {"coordinates":[-117.261002,32.996101],"type":"Point"}
}