{
  "type": "Feature",
  "properties": {
    "iso:country":"US",
    "sg:address":"3791 Crowell Rd",
    "sg:city":"Turlock",
    "sg:classifiers":[
        {
            "category":"Social Services",
            "subcategory":"Adult Care",
            "type":"Services"
        }
    ],
    "sg:phone":"+1 209 664 9500",
    "sg:postcode":"95382",
    "sg:province":"CA",
    "sg:tags":[
        "home",
        "residential"
    ],
    "sg:website":"www.paramountassistedliving.com",
    "wof:name":"Paramount Parks At Turlock",
    "wof:placetype":"venue"
},
  "geometry": {"coordinates":[-120.862586,37.526073],"type":"Point"}
}