{
  "type": "Feature",
  "properties": {
    "addr:full":"25900 Pso de Los Robles Salinas CA 93908",
    "addr:postcode":"25900;93908",
    "addr:street":"Los Robles",
    "iso:country":"US",
    "sg:address":"25900 Pso de Los Robles",
    "sg:city":"Salinas",
    "sg:classifiers":[
        {
            "category":"Real Estate",
            "subcategory":"Developer",
            "type":"Services"
        }
    ],
    "sg:phone":"+1 831 484 6959",
    "sg:postcode":"93908",
    "sg:province":"CA",
    "wof:name":"KWG Development Inc",
    "wof:placetype":"venue"
},
  "geometry": {"coordinates":[-121.73272299999999,36.552439],"type":"Point"}
}