{
  "type": "Feature",
  "properties": {
    "addr:full":"1325 N Red Gum St Anaheim CA 92806",
    "addr:housenumber":"1325",
    "addr:postcode":"92806",
    "addr:street":"N Red Gum St",
    "iso:country":"US",
    "sg:address":"1325 N Red Gum St",
    "sg:city":"Anaheim",
    "sg:classifiers":[
        {
            "category":"Building & Trades",
            "subcategory":"Construction",
            "type":"Services"
        }
    ],
    "sg:phone":"+1 714 998 3430",
    "sg:postcode":"92806",
    "sg:province":"CA",
    "sg:tags":[
        "window",
        "door",
        "product"
    ],
    "wof:name":"Orange Galleon",
    "wof:placetype":"venue"
},
  "geometry": {"coordinates":[-117.867063,33.859077],"type":"Point"}
}