{
  "type": "Feature",
  "properties": {
    "iso:country":"US",
    "sg:address":"4050 3rd Ave #104",
    "sg:city":"San Diego",
    "sg:classifiers":[
        {
            "category":"Professional",
            "subcategory":"Lawyer & Legal Services",
            "type":"Services"
        }
    ],
    "sg:phone":"+1 619 866 4529",
    "sg:postcode":"92103",
    "sg:province":"CA",
    "sg:website":"www.92103law.com/?page_id=8",
    "wof:name":"Maria Helena Chaves",
    "wof:placetype":"venue"
},
  "geometry": {"coordinates":[-117.162807,32.751078],"type":"Point"}
}