{
  "type": "Feature",
  "properties": {
    "addr:full":"11040 Brookshire Ave Downey CA 90241",
    "addr:housenumber":"11040",
    "addr:postcode":"90241",
    "addr:street":"Brookshire Ave",
    "iso:country":"US",
    "sg:address":"11040 Brookshire Ave",
    "sg:city":"Downey",
    "sg:phone":"+1 562 869 7301",
    "sg:postcode":"90241",
    "sg:province":"CA",
    "sg:website":"http://www.dusd.net",
    "wof:name":"Downey High School",
    "wof:placetype":"venue"
},
  "geometry": {"coordinates":[-118.128112,33.940199],"type":"Point"}
}