{
  "type": "Feature",
  "properties": {
    "iso:country":"US",
    "sg:address":"1839 S Lake Pl",
    "sg:city":"Ontario",
    "sg:classifiers":[
        {
            "category":"Manufacturing",
            "subcategory":"Printing",
            "type":"Manufacturing & Wholesale Goods"
        }
    ],
    "sg:phone":"+1 909 947 0447",
    "sg:postcode":"91761",
    "sg:province":"CA",
    "sg:tags":[
        "printer"
    ],
    "wof:name":"Iga Printing",
    "wof:placetype":"venue"
},
  "geometry": {"coordinates":[-117.62131599999999,34.040416],"type":"Point"}
}