{
  "type": "Feature",
  "properties": {
    "addr:full":"7332 Florence Ave Downey CA 90240",
    "addr:housenumber":"7332",
    "addr:postcode":"90240",
    "addr:street":"Florence Ave",
    "iso:country":"US",
    "sg:address":"7332 Florence Ave",
    "sg:city":"Downey",
    "sg:classifiers":[
        {
            "category":"Travel",
            "subcategory":"Travel Agent",
            "type":"Entertainment"
        }
    ],
    "sg:phone":"+1 562 927 0606",
    "sg:postcode":"90240",
    "sg:province":"CA",
    "sg:tags":[
        "agency",
        "bureau"
    ],
    "wof:name":"Salinas Travel & Multiservice",
    "wof:placetype":"venue"
},
  "geometry": {"coordinates":[-118.142549,33.959829],"type":"Point"}
}