{
  "type": "Feature",
  "properties": {
    "addr:full":"2225 E Tahquitz Canyon Way Ste 6 Palm Springs CA 92262",
    "addr:housenumber":"2225",
    "addr:postcode":"92262",
    "addr:street":"E Tahquitz Canyon Way Ste 6",
    "iso:country":"US",
    "sg:address":"2225 E Tahquitz Canyon Way Ste 6",
    "sg:city":"Palm Springs",
    "sg:classifiers":[
        {
            "category":"Personal",
            "subcategory":"Massage",
            "type":"Services"
        },
        {
            "category":"Health Services",
            "subcategory":"Clinic",
            "type":"Services"
        },
        {
            "category":"Health Services",
            "subcategory":"Health Practitioner",
            "type":"Services"
        },
        {
            "category":"Personal",
            "subcategory":"Day Spa",
            "type":"Services"
        }
    ],
    "sg:phone":"+1 760 408 7661",
    "sg:postcode":"92262",
    "sg:province":"CA",
    "sg:tags":[
        "medical",
        "therapy",
        "physical"
    ],
    "sg:website":"www.MLDTherapist.com",
    "wof:name":"Lisa Ross HHP,CMT",
    "wof:placetype":"venue"
},
  "geometry": {"coordinates":[-116.522043,33.823067],"type":"Point"}
}