{
  "type": "Feature",
  "properties": {
    "addr:full":"3001 Evergreen Ave Ste B West Sacramento CA 95691",
    "addr:housenumber":"3001",
    "addr:postcode":"95691",
    "addr:street":"Evergreen Ave Ste B",
    "iso:country":"US",
    "sg:address":"3001 Evergreen Ave Ste B",
    "sg:city":"West Sacramento",
    "sg:classifiers":[
        {
            "category":"Autos & Motor Vehicles",
            "subcategory":"Auto Supplies",
            "type":"Retail Goods"
        }
    ],
    "sg:phone":"+1 916 372 6666",
    "sg:postcode":"95691",
    "sg:province":"CA",
    "sg:tags":[
        "tire"
    ],
    "sg:website":"www.tirestogo.com",
    "wof:name":"Tires To Go",
    "wof:placetype":"venue"
},
  "geometry": {"coordinates":[-121.549263,38.576656],"type":"Point"}
}