{
  "type": "Feature",
  "properties": {
    "addr:full":"960 E Green St Pasadena CA 91106",
    "addr:housenumber":"960",
    "addr:postcode":"91106",
    "addr:street":"E Green St",
    "iso:country":"US",
    "sg:address":"960 E Green St",
    "sg:city":"Pasadena",
    "sg:classifiers":[
        {
            "category":"Health Services",
            "subcategory":"Doctor",
            "type":"Services"
        }
    ],
    "sg:phone":"+1 626 449 4207",
    "sg:postcode":"91106",
    "sg:province":"CA",
    "sg:tags":[
        "dermatologist"
    ],
    "wof:name":"Kim Leonard H MD",
    "wof:placetype":"venue"
},
  "geometry": {"coordinates":[-118.130354,34.144428],"type":"Point"}
}