{
  "type": "Feature",
  "properties": {
    "addr:full":"6565 Catamaran St San Jose CA 95119",
    "addr:housenumber":"6565",
    "addr:postcode":"95119",
    "addr:street":"Catamaran St",
    "iso:country":"US",
    "sg:address":"6565 Catamaran St",
    "sg:city":"San Jose",
    "sg:classifiers":[
        {
            "category":"Wholesale",
            "subcategory":"Machinery & Supplies",
            "type":"Manufacturing & Wholesale Goods"
        }
    ],
    "sg:phone":"+1 408 629 3535",
    "sg:postcode":"95119",
    "sg:province":"CA",
    "sg:tags":[
        "bearing"
    ],
    "wof:name":"Busak Plus Shamban",
    "wof:placetype":"venue"
},
  "geometry": {"coordinates":[-121.791461,37.231956],"type":"Point"}
}