{
  "type": "Feature",
  "properties": {
    "iso:country":"US",
    "sg:address":"440 N. Wolfe Road",
    "sg:city":"Sunnyvale",
    "sg:classifiers":[
        {
            "category":"Shopping",
            "subcategory":"Mobile Phones",
            "type":"Retail Goods"
        }
    ],
    "sg:phone":"+1 510 579 8526",
    "sg:postcode":"95606",
    "sg:province":"CA",
    "wof:name":"Micello, Inc.",
    "wof:placetype":"venue"
},
  "geometry": {"coordinates":[-122.014911,37.383867],"type":"Point"}
}