{
  "type": "Feature",
  "properties": {
    "iso:country":"US",
    "sg:address":"12126 Sherman Way",
    "sg:city":"North Hollywood",
    "sg:classifiers":[
        {
            "category":"Shopping",
            "subcategory":"Computers & Home Electronics",
            "type":"Retail Goods"
        }
    ],
    "sg:phone":"+1 818 764 3722",
    "sg:postcode":"91605",
    "sg:province":"CA",
    "wof:name":"Chapman Av Systems",
    "wof:placetype":"venue"
},
  "geometry": {"coordinates":[-118.39720699999999,34.200648],"type":"Point"}
}