{
  "type": "Feature",
  "properties": {
    "addr:full":"2170 Pinot Cir Upland CA 91784",
    "addr:housenumber":"2170",
    "addr:postcode":"91784",
    "addr:street":"Pinot Cir",
    "iso:country":"US",
    "sg:address":"2170 Pinot Cir",
    "sg:city":"Upland",
    "sg:classifiers":[
        {
            "category":"Professional",
            "subcategory":"Business Services",
            "type":"Services"
        }
    ],
    "sg:phone":"+1 909 981 3663",
    "sg:postcode":"91784",
    "sg:province":"CA",
    "sg:tags":[
        "interior",
        "consultant",
        "design",
        "decorator"
    ],
    "wof:name":"Creative Interiors",
    "wof:placetype":"venue"
},
  "geometry": {"coordinates":[-117.674233,34.141975],"type":"Point"}
}