{
  "type": "Feature",
  "properties": {
    "addr:full":"4243 Bonita Rd Apt 29 Bonita CA 91902",
    "addr:housenumber":"4243;29",
    "addr:postcode":"91902",
    "addr:street":"Bonita Rd Apt",
    "iso:country":"US",
    "sg:address":"4243 Bonita Rd Apt 29",
    "sg:city":"Bonita",
    "sg:classifiers":[
        {
            "category":"Real Estate",
            "subcategory":"Real Estate Operator",
            "type":"Services"
        }
    ],
    "sg:phone":"+1 619 479 1824",
    "sg:postcode":"91902",
    "sg:province":"CA",
    "sg:tags":[
        "apartment"
    ],
    "wof:name":"Vista Bonita Apartments",
    "wof:placetype":"venue"
},
  "geometry": {"coordinates":[-117.035004,32.660702],"type":"Point"}
}