{
  "type": "Feature",
  "properties": {
    "addr:full":"9728 Variel Ave Chatsworth CA 91311",
    "addr:housenumber":"9728",
    "addr:postcode":"91311",
    "addr:street":"Variel Ave",
    "iso:country":"US",
    "sg:address":"9728 Variel Ave",
    "sg:city":"Chatsworth",
    "sg:classifiers":[
        {
            "category":"Wholesale",
            "subcategory":"Machinery & Supplies",
            "type":"Manufacturing & Wholesale Goods"
        }
    ],
    "sg:phone":"+1 818 727 0957",
    "sg:postcode":"91311",
    "sg:province":"CA",
    "sg:tags":[
        "industrial",
        "equipment",
        "used",
        "machinery-new",
        "supplies-wholesale"
    ],
    "sg:website":"http://www.candomachinery.com",
    "wof:name":"Can-Do Machinery Sales",
    "wof:placetype":"venue"
},
  "geometry": {"coordinates":[-118.592949,34.246514],"type":"Point"}
}