{
  "type": "Feature",
  "properties": {
    "addr:full":"475 Walker Rd San Dimas CA 91773",
    "addr:housenumber":"475",
    "addr:postcode":"91773",
    "addr:street":"Walker Rd",
    "iso:country":"US",
    "sg:address":"475 Walker Rd",
    "sg:city":"San Dimas",
    "sg:classifiers":[
        {
            "category":"Professional",
            "subcategory":"Employment Agencies",
            "type":"Services"
        }
    ],
    "sg:phone":"+1 909 592 7227",
    "sg:postcode":"91773",
    "sg:province":"CA",
    "sg:tags":[
        "consultant",
        "search",
        "executive"
    ],
    "wof:name":"Adept Search",
    "wof:placetype":"venue"
},
  "geometry": {"coordinates":[-117.81535599999999,34.112375],"type":"Point"}
}