{
  "type": "Feature",
  "properties": {
    "addr:full":"9340 W. Pico Blvd Los Angeles CA 90035",
    "addr:housenumber":"9340",
    "addr:postcode":"90035",
    "addr:street":"W. Pico Blvd",
    "iso:country":"US",
    "sg:address":"9340 W. Pico Blvd",
    "sg:city":"Los Angeles",
    "sg:classifiers":[
        {
            "category":"Restaurant",
            "type":"Food & Drink"
        }
    ],
    "sg:phone":"+1 310 274 3474",
    "sg:postcode":"90035",
    "sg:province":"CA",
    "sg:tags":[
        "sushi",
        "bar"
    ],
    "sg:website":"sushikola.com/",
    "wof:name":"Sushiko",
    "wof:placetype":"venue"
},
  "geometry": {"coordinates":[-118.394047,34.054874],"type":"Point"}
}