{
  "type": "Feature",
  "properties": {
    "addr:full":"2820 N Main St Santa Ana CA 92705",
    "addr:housenumber":"2820",
    "addr:postcode":"92705",
    "addr:street":"N Main St",
    "iso:country":"US",
    "sg:address":"2820 N Main St",
    "sg:city":"Santa Ana",
    "sg:classifiers":[
        {
            "category":"Shopping",
            "subcategory":"Clothing, Apparel, & Fashions",
            "type":"Retail Goods"
        }
    ],
    "sg:phone":"+1 714 972 2020",
    "sg:postcode":"92705",
    "sg:province":"CA",
    "sg:tags":[
        "department",
        "store",
        "shoe",
        "family"
    ],
    "wof:name":"Nordstrom",
    "wof:placetype":"venue"
},
  "geometry": {"coordinates":[-117.866997,33.775299],"type":"Point"}
}