{
  "type": "Feature",
  "properties": {
    "addr:full":"30019 Madloy St Castaic CA 91384",
    "addr:postcode":"30019;91384",
    "addr:street":"Madloy St",
    "iso:country":"US",
    "sg:address":"30019 Madloy St",
    "sg:city":"Castaic",
    "sg:classifiers":[
        {
            "category":"Retail",
            "subcategory":"Animal Services",
            "type":"Services"
        }
    ],
    "sg:phone":"+1 661 257 2627",
    "sg:postcode":"91384",
    "sg:province":"CA",
    "wof:name":"Long Hall Ranch",
    "wof:placetype":"venue"
},
  "geometry": {"coordinates":[-118.66137999999999,34.472766],"type":"Point"}
}