{
  "type": "Feature",
  "properties": {
    "addr:full":"224 Magnolia St Costa Mesa CA 92627",
    "addr:housenumber":"224",
    "addr:postcode":"92627",
    "addr:street":"Magnolia St",
    "iso:country":"US",
    "sg:address":"224 Magnolia St",
    "sg:city":"Costa Mesa",
    "sg:classifiers":[
        {
            "category":"Professional",
            "type":"Services"
        }
    ],
    "sg:phone":"+1 949 645 5305",
    "sg:postcode":"92627",
    "sg:province":"CA",
    "wof:name":"Nelson Marine",
    "wof:placetype":"venue"
},
  "geometry": {"coordinates":[-117.914294,33.638383],"type":"Point"}
}