{
  "type": "Feature",
  "properties": {
    "addr:full":"4330 N Pershing Ave Stockton CA 95207",
    "addr:housenumber":"4330",
    "addr:postcode":"95207",
    "addr:street":"N Pershing Ave",
    "iso:country":"US",
    "sg:address":"4330 N Pershing Ave",
    "sg:city":"Stockton",
    "sg:classifiers":[
        {
            "category":"Real Estate",
            "subcategory":"Real Estate Agent",
            "type":"Services"
        },
        {
            "category":"Real Estate",
            "subcategory":"Real Estate Operator",
            "type":"Services"
        }
    ],
    "sg:phone":"+1 209 474 1800",
    "sg:postcode":"95207",
    "sg:province":"CA",
    "sg:tags":[
        "building",
        "parks"
    ],
    "wof:name":"Hacienda Office Complex",
    "wof:placetype":"venue"
},
  "geometry": {"coordinates":[-121.320329,37.985467],"type":"Point"}
}