{
  "type": "Feature",
  "properties": {
    "addr:full":"18560 Via Princessa Ste 130 Santa Clarita CA 91387",
    "addr:housenumber":"18560",
    "addr:postcode":"91387",
    "addr:street":"Via Princessa Ste 130",
    "iso:country":"US",
    "sg:address":"18560 Via Princessa Ste 130",
    "sg:city":"Santa Clarita",
    "sg:classifiers":[
        {
            "category":"Insurance",
            "subcategory":"Health Insurance",
            "type":"Services"
        }
    ],
    "sg:phone":"+1 661 299 9101",
    "sg:postcode":"91387",
    "sg:province":"CA",
    "sg:tags":[
        "market"
    ],
    "sg:website":"www.vip-nutrition.com",
    "wof:name":"VIP Nutrition",
    "wof:placetype":"venue"
},
  "geometry": {"coordinates":[-118.460336,34.403157],"type":"Point"}
}