{
  "type": "Feature",
  "properties": {
    "iso:country":"US",
    "sg:address":"2006 A St",
    "sg:city":"Antioch",
    "sg:classifiers":[
        {
            "category":"Professional",
            "type":"Services"
        }
    ],
    "sg:phone":"+1 925 522 0454",
    "sg:postcode":"94509",
    "sg:province":"CA",
    "sg:tags":[
        "establishment"
    ],
    "wof:name":"Top Gun Productions",
    "wof:placetype":"venue"
},
  "geometry": {"coordinates":[-121.806096,38.003147],"type":"Point"}
}