{
  "type": "Feature",
  "properties": {
    "iso:country":"US",
    "sg:address":"983 S Glendora Ave",
    "sg:city":"West Covina",
    "sg:classifiers":[
        {
            "category":"Personal",
            "subcategory":"Beauty Salon",
            "type":"Services"
        }
    ],
    "sg:phone":"+1 626 960 9630",
    "sg:postcode":"91790",
    "sg:province":"CA",
    "sg:tags":[
        "manicuring"
    ],
    "wof:name":"Queen Nail",
    "wof:placetype":"venue"
},
  "geometry": {"coordinates":[-117.935563,34.058191],"type":"Point"}
}