{
  "type": "Feature",
  "properties": {
    "iso:country":"US",
    "sg:address":"6290 Irvine Blvd",
    "sg:city":"Irvine",
    "sg:classifiers":[
        {
            "category":"Retail",
            "subcategory":"Laundry & Dry Cleaning",
            "type":"Services"
        }
    ],
    "sg:phone":"+1 949 451 0057",
    "sg:postcode":"92620",
    "sg:province":"CA",
    "wof:name":"Pialago Cleaners",
    "wof:placetype":"venue"
},
  "geometry": {"coordinates":[-117.74083,33.700274],"type":"Point"}
}