{
  "type": "Feature",
  "properties": {
    "addr:full":"839 Quintana Rd Morro Bay CA 93442",
    "addr:housenumber":"839",
    "addr:postcode":"93442",
    "addr:street":"Quintana Rd",
    "iso:country":"US",
    "sg:address":"839 Quintana Rd",
    "sg:city":"Morro Bay",
    "sg:classifiers":[
        {
            "category":"Retail",
            "subcategory":"Auto Repair",
            "type":"Services"
        }
    ],
    "sg:phone":"+1 805 771 9811",
    "sg:postcode":"93442",
    "sg:province":"CA",
    "sg:tags":[
        "muffler",
        "exhaust",
        "system"
    ],
    "wof:name":"Nick's Morro Muffler",
    "wof:placetype":"venue"
},
  "geometry": {"coordinates":[-120.84184,35.367105],"type":"Point"}
}