{
  "type": "Feature",
  "properties": {
    "addr:full":"126 W Norberry St Lancaster CA 93534",
    "addr:housenumber":"126",
    "addr:postcode":"93534",
    "addr:street":"W Norberry St",
    "iso:country":"US",
    "sg:address":"126 W Norberry St",
    "sg:city":"Lancaster",
    "sg:classifiers":[
        {
            "category":"Autos & Motor Vehicles",
            "subcategory":"Auto Supplies",
            "type":"Retail Goods"
        }
    ],
    "sg:phone":"+1 661 945 5188",
    "sg:postcode":"93534",
    "sg:province":"CA",
    "sg:tags":[
        "battery"
    ],
    "wof:name":"Interstate Battery System",
    "wof:placetype":"venue"
},
  "geometry": {"coordinates":[-118.130577,34.69376],"type":"Point"}
}