{
  "type": "Feature",
  "properties": {
    "addr:full":"2111 S Bronson Ave Los Angeles CA 90018",
    "addr:housenumber":"2111",
    "addr:postcode":"90018",
    "addr:street":"S Bronson Ave",
    "iso:country":"US",
    "sg:address":"2111 S Bronson Ave",
    "sg:city":"Los Angeles",
    "sg:classifiers":[
        {
            "category":"Manufacturing",
            "subcategory":"Printing",
            "type":"Manufacturing & Wholesale Goods"
        }
    ],
    "sg:phone":"+1 323 734 1151",
    "sg:postcode":"90018",
    "sg:province":"CA",
    "sg:tags":[
        "printer"
    ],
    "wof:name":"4-M Printing Co",
    "wof:placetype":"venue"
},
  "geometry": {"coordinates":[-118.33106600000001,34.037618],"type":"Point"}
}