{
  "type": "Feature",
  "properties": {
    "iso:country":"US",
    "sg:address":"925 Broadbeck Dr Ste 103",
    "sg:city":"Newbury Park",
    "sg:classifiers":[
        {
            "category":"Banks & Credit Unions",
            "subcategory":"Bank",
            "type":"Services"
        }
    ],
    "sg:phone":"+1 805 376 1760",
    "sg:postcode":"91320",
    "sg:province":"CA",
    "wof:name":"Wells Fargo",
    "wof:placetype":"venue"
},
  "geometry": {"coordinates":[-118.936345,34.191093],"type":"Point"}
}