{
  "type": "Feature",
  "properties": {
    "iso:country":"US",
    "sg:address":"2937 S La Brea Avenue",
    "sg:city":"Los Angeles",
    "sg:classifiers":[
        {
            "category":"Banks & Credit Unions",
            "subcategory":"Investment Brokerage",
            "type":"Services"
        }
    ],
    "sg:phone":"+1 323 938 9131",
    "sg:postcode":"90016",
    "sg:province":"CA",
    "sg:tags":[
        "investing"
    ],
    "wof:name":"Descartes Financial Corporation",
    "wof:placetype":"venue"
},
  "geometry": {"coordinates":[-118.353171,34.027713],"type":"Point"}
}