{
  "type": "Feature",
  "properties": {
    "iso:country":"US",
    "sg:address":"9505 York Rd",
    "sg:city":"Monterey",
    "sg:classifiers":[
        {
            "category":"Building & Trades",
            "subcategory":"Construction",
            "type":"Services"
        }
    ],
    "sg:phone":"+1 831 373 0944",
    "sg:postcode":"93940",
    "sg:province":"CA",
    "sg:tags":[
        "contractor",
        "general"
    ],
    "wof:name":"Bethel Construction Co Inc",
    "wof:placetype":"venue"
},
  "geometry": {"coordinates":[-121.78919,36.575333],"type":"Point"}
}