{
  "type": "Feature",
  "properties": {
    "iso:country":"US",
    "sg:address":"6802 Westminster Boulevard",
    "sg:city":"Westminster",
    "sg:classifiers":[
        {
            "category":"Communications",
            "subcategory":"Newspaper",
            "type":"Services"
        }
    ],
    "sg:phone":"+1 714 894 2500",
    "sg:postcode":"92683",
    "sg:province":"CA",
    "sg:tags":[
        "print",
        "medium"
    ],
    "wof:name":"Viet Bao Kinh Te",
    "wof:placetype":"venue"
},
  "geometry": {"coordinates":[-118.00935200000001,33.758986],"type":"Point"}
}