{
  "type": "Feature",
  "properties": {
    "iso:country":"US",
    "sg:address":"9549 Gidley St",
    "sg:city":"Temple City",
    "sg:classifiers":[
        {
            "category":"Building & Trades",
            "subcategory":"Landscaping Services",
            "type":"Services"
        }
    ],
    "sg:phone":"+1 626 284 0769",
    "sg:postcode":"91780",
    "sg:province":"CA",
    "wof:name":"Harnisch Tree Care",
    "wof:placetype":"venue"
},
  "geometry": {"coordinates":[-118.05924899999999,34.087523],"type":"Point"}
}