{
  "type": "Feature",
  "properties": {
    "addr:full":"841 N K St Livermore CA 94551",
    "addr:housenumber":"841",
    "addr:postcode":"94551",
    "addr:street":"N K St",
    "iso:country":"US",
    "sg:address":"841 N K St",
    "sg:city":"Livermore",
    "sg:classifiers":[
        {
            "category":"Building & Trades",
            "subcategory":"Landscaping Services",
            "type":"Services"
        }
    ],
    "sg:phone":"+1 925 443 4408",
    "sg:postcode":"94551",
    "sg:province":"CA",
    "sg:tags":[
        "landscape",
        "contractor"
    ],
    "wof:name":"Kerri Landscape Svc",
    "wof:placetype":"venue"
},
  "geometry": {"coordinates":[-121.774281,37.690177],"type":"Point"}
}