{
  "type": "Feature",
  "properties": {
    "iso:country":"US",
    "sg:address":"2431 W March Ln",
    "sg:city":"Stockton",
    "sg:classifiers":[
        {
            "category":"Real Estate",
            "subcategory":"Real Estate Agent",
            "type":"Services"
        }
    ],
    "sg:phone":"+1 209 473 1000",
    "sg:postcode":"95207",
    "sg:province":"CA",
    "sg:tags":[
        "management"
    ],
    "sg:website":"www.association-services.net",
    "wof:name":"Association Services Inc",
    "wof:placetype":"venue"
},
  "geometry": {"coordinates":[-121.337706,37.985107],"type":"Point"}
}