{
  "type": "Feature",
  "properties": {
    "iso:country":"US",
    "sg:address":"5512 Monterey Hwy",
    "sg:city":"San Jose",
    "sg:classifiers":[
        {
            "category":"Restaurant",
            "type":"Food & Drink"
        }
    ],
    "sg:phone":"+1 408 629 5966",
    "sg:postcode":"95138",
    "sg:province":"CA",
    "sg:tags":[
        "family"
    ],
    "wof:name":"Lyons Restaurant 447",
    "wof:placetype":"venue"
},
  "geometry": {"coordinates":[-121.794141,37.25081],"type":"Point"}
}