{
  "type": "Feature",
  "properties": {
    "iso:country":"US",
    "sg:address":"4605 W Walnut St",
    "sg:city":"Soquel",
    "sg:classifiers":[
        {
            "category":"Professional",
            "subcategory":"Engineering",
            "type":"Services"
        }
    ],
    "sg:phone":"+1 831 464 4320",
    "sg:postcode":"95073",
    "sg:province":"CA",
    "sg:tags":[
        "engineer"
    ],
    "wof:name":"Axiom Engineers",
    "wof:placetype":"venue"
},
  "geometry": {"coordinates":[-121.957378,36.98595],"type":"Point"}
}