{
  "type": "Feature",
  "properties": {
    "iso:country":"US",
    "sg:address":"27001 La Paz Road",
    "sg:city":"Mission Viejo",
    "sg:classifiers":[
        {
            "category":"Professional",
            "subcategory":"Lawyer & Legal Services",
            "type":"Services"
        }
    ],
    "sg:phone":"+1 949 452 9446",
    "sg:postcode":"92691",
    "sg:province":"CA",
    "wof:name":"Abt Gregory D Law Offices of",
    "wof:placetype":"venue"
},
  "geometry": {"coordinates":[-117.658708,33.597148],"type":"Point"}
}