{
  "type": "Feature",
  "properties": {
    "addr:full":"15230 Lakeshore Dr Clearlake CA 95422",
    "addr:housenumber":"15230",
    "addr:postcode":"95422",
    "addr:street":"Lakeshore Dr",
    "iso:country":"US",
    "sg:address":"15230 Lakeshore Dr",
    "sg:city":"Clearlake",
    "sg:classifiers":[
        {
            "category":"Health Services",
            "subcategory":"Doctor",
            "type":"Services"
        }
    ],
    "sg:phone":"+1 707 995 5034",
    "sg:postcode":"95422",
    "sg:province":"CA",
    "sg:tags":[
        "physician",
        "surgeon"
    ],
    "wof:name":"Arthur W Bikangaga MD",
    "wof:placetype":"venue"
},
  "geometry": {"coordinates":[-122.626773,38.949968],"type":"Point"}
}