{
  "type": "Feature",
  "properties": {
    "iso:country":"US",
    "sg:address":"2162 Roosevelt Ave",
    "sg:city":"Altadena",
    "sg:classifiers":[
        {
            "category":"Professional",
            "subcategory":"Business Services",
            "type":"Services"
        }
    ],
    "sg:phone":"+1 626 791 5789",
    "sg:postcode":"91001",
    "sg:province":"CA",
    "sg:tags":[
        "holding"
    ],
    "wof:name":"Mpb Holdings",
    "wof:placetype":"venue"
},
  "geometry": {"coordinates":[-118.101695,34.182207],"type":"Point"}
}