{
  "type": "Feature",
  "properties": {
    "addr:full":"1247 N Lakeview Ave Ste F Anaheim CA 92807",
    "addr:housenumber":"1247",
    "addr:postcode":"92807",
    "addr:street":"N Lakeview Ave Ste F",
    "iso:country":"US",
    "sg:address":"1247 N Lakeview Ave Ste F",
    "sg:city":"Anaheim",
    "sg:classifiers":[
        {
            "category":"Shopping",
            "subcategory":"Stationery & Office Supplies",
            "type":"Retail Goods"
        }
    ],
    "sg:phone":"+1 714 777 1493",
    "sg:postcode":"92807",
    "sg:province":"CA",
    "sg:tags":[
        "equipment"
    ],
    "wof:name":"Precision Office Machines & Stationers",
    "wof:placetype":"venue"
},
  "geometry": {"coordinates":[-117.78299699999999,33.853802],"type":"Point"}
}