{
  "type": "Feature",
  "properties": {
    "iso:country":"US",
    "sg:address":"7105 Martin Ln",
    "sg:city":"Ione",
    "sg:classifiers":[
        {
            "category":"Retail",
            "subcategory":"Animal Services",
            "type":"Services"
        }
    ],
    "sg:phone":"+1 209 274 2624",
    "sg:postcode":"95640",
    "sg:province":"CA",
    "wof:name":"Boyle Performance Horses",
    "wof:placetype":"venue"
},
  "geometry": {"coordinates":[-120.945609,38.307158],"type":"Point"}
}