{
  "type": "Feature",
  "properties": {
    "iso:country":"US",
    "sg:address":"53 N San Mateo Dr",
    "sg:city":"San Mateo",
    "sg:classifiers":[
        {
            "category":"Personal",
            "subcategory":"Beauty Salon",
            "type":"Services"
        }
    ],
    "sg:phone":"+1 650 344 1401",
    "sg:postcode":"94401",
    "sg:province":"CA",
    "wof:name":"Skin Concepts",
    "wof:placetype":"venue"
},
  "geometry": {"coordinates":[-122.32747,37.567557],"type":"Point"}
}