{
  "type": "Feature",
  "properties": {
    "iso:country":"US",
    "sg:address":"1321 Howe Ave",
    "sg:city":"Sacramento",
    "sg:classifiers":[
        {
            "category":"Professional",
            "subcategory":"Business Services",
            "type":"Services"
        }
    ],
    "sg:phone":"+1 916 568 8220",
    "sg:postcode":"95825",
    "sg:province":"CA",
    "sg:tags":[
        "convention",
        "meeting",
        "facility"
    ],
    "wof:name":"Intergovernmental Technology",
    "wof:placetype":"venue"
},
  "geometry": {"coordinates":[-121.415384,38.591307],"type":"Point"}
}