{
  "type": "Feature",
  "properties": {
    "addr:full":"699 N Atlantic Blvd Alhambra CA 91801",
    "addr:housenumber":"699",
    "addr:postcode":"91801",
    "addr:street":"N Atlantic Blvd",
    "iso:country":"US",
    "sg:address":"699 N Atlantic Blvd",
    "sg:city":"Alhambra",
    "sg:classifiers":[
        {
            "category":"Recreation",
            "type":"Entertainment"
        }
    ],
    "sg:phone":"+1 626 282 7222",
    "sg:postcode":"91801",
    "sg:province":"CA",
    "sg:tags":[
        "psychic",
        "medium"
    ],
    "wof:name":"Mrs Lin Psychic Readings",
    "wof:placetype":"venue"
},
  "geometry": {"coordinates":[-118.13474600000001,34.09966],"type":"Point"}
}