{
  "type": "Feature",
  "properties": {
    "addr:full":"1901 westcliff dr. ste#6 Newport Beach CA 92660",
    "addr:housenumber":"1901",
    "addr:postcode":"92660",
    "addr:street":"Westcliff Dr. Ste # 6",
    "iso:country":"US",
    "sg:address":"1901 westcliff dr. ste#6",
    "sg:city":"Newport Beach",
    "sg:classifiers":[
        {
            "category":"Health Services",
            "subcategory":"Dentist",
            "type":"Services"
        }
    ],
    "sg:phone":"+1 949 646 2481",
    "sg:postcode":"92660",
    "sg:province":"CA",
    "sg:website":"thenewportbeachdentist.com",
    "wof:name":"omid haroonian dds",
    "wof:placetype":"venue"
},
  "geometry": {"coordinates":[-117.907291,33.626795],"type":"Point"}
}