{
  "type": "Feature",
  "properties": {
    "addr:full":"17273 Cerritos St Fontana CA 92336",
    "addr:housenumber":"17273",
    "addr:postcode":"92336",
    "addr:street":"Cerritos St",
    "iso:country":"US",
    "sg:address":"17273 Cerritos St",
    "sg:city":"Fontana",
    "sg:classifiers":[
        {
            "category":"Freight",
            "type":"Transportation"
        }
    ],
    "sg:phone":"+1 951 212 8312",
    "sg:postcode":"92336",
    "sg:province":"CA",
    "sg:tags":[
        "operator",
        "local",
        "trucking"
    ],
    "wof:name":"J L Olivares Trucking",
    "wof:placetype":"venue"
},
  "geometry": {"coordinates":[-117.428302,34.127683],"type":"Point"}
}