{
  "type": "Feature",
  "properties": {
    "addr:full":"6811 Embarcadero Ln Carlsbad CA 92009",
    "addr:housenumber":"6811",
    "addr:postcode":"92009",
    "addr:street":"Embarcadero Ln",
    "iso:country":"US",
    "sg:address":"6811 Embarcadero Ln",
    "sg:city":"Carlsbad",
    "sg:classifiers":[
        {
            "category":"Real Estate",
            "subcategory":"Real Estate Operator",
            "type":"Services"
        }
    ],
    "sg:phone":"+1 760 438 8839",
    "sg:postcode":"92009",
    "sg:province":"CA",
    "sg:tags":[
        "apartment"
    ],
    "wof:name":"Poinsetti Station Apartments",
    "wof:placetype":"venue"
},
  "geometry": {"coordinates":[-117.317001,33.109402],"type":"Point"}
}