{
  "type": "Feature",
  "properties": {
    "iso:country":"US",
    "sg:address":"2627 Hollywood Way",
    "sg:city":"Burbank",
    "sg:classifiers":[
        {
            "category":"Retail",
            "subcategory":"Auto Rental",
            "type":"Services"
        }
    ],
    "sg:phone":"+1 818 840 8045",
    "sg:postcode":"91505",
    "sg:province":"CA",
    "sg:tags":[
        "car"
    ],
    "sg:website":"www.alamo.com",
    "wof:name":"Alamo Rent A Car",
    "wof:placetype":"venue"
},
  "geometry": {"coordinates":[-118.348992,34.196536],"type":"Point"}
}