{
  "type": "Feature",
  "properties": {
    "addr:full":"4770 Soquel Dr Soquel CA 95073",
    "addr:housenumber":"4770",
    "addr:postcode":"95073",
    "addr:street":"Soquel Dr",
    "iso:country":"US",
    "sg:address":"4770 Soquel Dr",
    "sg:city":"Soquel",
    "sg:classifiers":[
        {
            "category":"Shopping",
            "subcategory":"Bicycles & Sporting Goods",
            "type":"Retail Goods"
        }
    ],
    "sg:phone":"+1 831 475 1988",
    "sg:postcode":"95073",
    "sg:province":"CA",
    "wof:name":"Play It Again Sports",
    "wof:placetype":"venue"
},
  "geometry": {"coordinates":[-121.956748,36.988338],"type":"Point"}
}