{
  "type": "Feature",
  "properties": {
    "iso:country":"US",
    "sg:address":"1489 E Warner Ave",
    "sg:city":"Santa Ana",
    "sg:classifiers":[
        {
            "category":"Manufacturing",
            "subcategory":"Tools & Machinery",
            "type":"Manufacturing & Wholesale Goods"
        }
    ],
    "sg:phone":"+1 714 549 9700",
    "sg:postcode":"92707",
    "sg:province":"CA",
    "sg:tags":[
        "industrial",
        "mfg"
    ],
    "wof:name":"KMC Precision Maching",
    "wof:placetype":"venue"
},
  "geometry": {"coordinates":[-117.847888,33.715971],"type":"Point"}
}