{
  "type": "Feature",
  "properties": {
    "iso:country":"US",
    "sg:address":"3072 N Lima St",
    "sg:city":"Burbank",
    "sg:classifiers":[
        {
            "category":"Manufacturing",
            "subcategory":"Tools & Machinery",
            "type":"Manufacturing & Wholesale Goods"
        }
    ],
    "sg:phone":"+1 818 845 1997",
    "sg:postcode":"91504",
    "sg:province":"CA",
    "wof:name":"Steven's Grinding Co",
    "wof:placetype":"venue"
},
  "geometry": {"coordinates":[-118.346436,34.206376],"type":"Point"}
}