{
  "type": "Feature",
  "properties": {
    "iso:country":"US",
    "sg:address":"12 Cam Encinas",
    "sg:city":"Orinda",
    "sg:classifiers":[
        {
            "category":"Health Services",
            "subcategory":"Doctor",
            "type":"Services"
        }
    ],
    "sg:phone":"+1 925 253 1300",
    "sg:postcode":"94563",
    "sg:province":"CA",
    "sg:tags":[
        "physician",
        "surgeon"
    ],
    "wof:name":"Eye Physicians Of The East Bay",
    "wof:placetype":"venue"
},
  "geometry": {"coordinates":[-122.18023700000001,37.876042],"type":"Point"}
}