{
  "type": "Feature",
  "properties": {
    "addr:full":"5157 11th Ave Los Angeles CA 90043",
    "addr:housenumber":"5157",
    "addr:postcode":"90043",
    "addr:street":"11Th Ave",
    "iso:country":"US",
    "sg:address":"5157 11th Ave",
    "sg:city":"Los Angeles",
    "sg:classifiers":[
        {
            "category":"Professional",
            "type":"Services"
        }
    ],
    "sg:phone":"+1 323 296 7526",
    "sg:postcode":"90043",
    "sg:province":"CA",
    "wof:name":"E-M Fashn and Jwlry",
    "wof:placetype":"venue"
},
  "geometry": {"coordinates":[-118.32944500000001,33.997106],"type":"Point"}
}