{
  "type": "Feature",
  "properties": {
    "iso:country":"US",
    "sg:address":"11935 Charnock Rd",
    "sg:city":"Los Angeles",
    "sg:classifiers":[
        {
            "category":"Real Estate",
            "subcategory":"Architect",
            "type":"Services"
        }
    ],
    "sg:phone":"+1 310 467 8792",
    "sg:postcode":"90066",
    "sg:province":"CA",
    "wof:name":"Torabi Systems",
    "wof:placetype":"venue"
},
  "geometry": {"coordinates":[-118.431118,34.010907],"type":"Point"}
}