{
  "type": "Feature",
  "properties": {
    "addr:full":"9882 Harvest Ln Anaheim CA 92804",
    "addr:housenumber":"9882",
    "addr:postcode":"92804",
    "addr:street":"Harvest Ln",
    "iso:country":"US",
    "sg:address":"9882 Harvest Ln",
    "sg:city":"Anaheim",
    "sg:classifiers":[
        {
            "category":"Travel",
            "subcategory":"Travel Agent",
            "type":"Entertainment"
        }
    ],
    "sg:phone":"+1 714 535 3737",
    "sg:postcode":"92804",
    "sg:province":"CA",
    "sg:tags":[
        "agency"
    ],
    "wof:name":"Ideal Travel Concepts",
    "wof:placetype":"venue"
},
  "geometry": {"coordinates":[-117.965795,33.820032],"type":"Point"}
}