{
  "type": "Feature",
  "properties": {
    "addr:full":"46710 County Road 32B Davis CA 95618",
    "addr:housenumber":"46710",
    "addr:postcode":"95618",
    "addr:street":"County Road 32B",
    "iso:country":"US",
    "sg:address":"46710 County Road 32B",
    "sg:city":"Davis",
    "sg:classifiers":[
        {
            "category":"Food & Beverages",
            "subcategory":"Farmers Market",
            "type":"Retail Goods"
        }
    ],
    "sg:phone":"+1 530 753 7579",
    "sg:postcode":"95618",
    "sg:province":"CA",
    "sg:tags":[
        "vegetable",
        "fruit"
    ],
    "wof:name":"Yolo Fruit Stand",
    "wof:placetype":"venue"
},
  "geometry": {"coordinates":[-121.647102,38.561501],"type":"Point"}
}