{
  "type": "Feature",
  "properties": {
    "iso:country":"US",
    "sg:address":"3587 1st St",
    "sg:city":"Livermore",
    "sg:classifiers":[
        {
            "category":"Home & Garden",
            "subcategory":"Building Materials",
            "type":"Retail Goods"
        }
    ],
    "sg:phone":"+1 925 443 3258",
    "sg:postcode":"94551",
    "sg:province":"CA",
    "sg:tags":[
        "glass",
        "window",
        "plate"
    ],
    "wof:name":"Elite Auto Glass",
    "wof:placetype":"venue"
},
  "geometry": {"coordinates":[-121.75725,37.688363],"type":"Point"}
}