{
  "type": "Feature",
  "properties": {
    "iso:country":"US",
    "sg:address":"1034 E Ave K",
    "sg:city":"Lancaster",
    "sg:classifiers":[
        {
            "category":"Home & Garden",
            "subcategory":"Home Furnishings",
            "type":"Retail Goods"
        }
    ],
    "sg:phone":"+1 661 940 6280",
    "sg:postcode":"93535",
    "sg:province":"CA",
    "sg:tags":[
        "linen"
    ],
    "wof:name":"Shelia's Linens & More",
    "wof:placetype":"venue"
},
  "geometry": {"coordinates":[-118.111841,34.674974],"type":"Point"}
}