{
  "type": "Feature",
  "properties": {
    "iso:country":"US",
    "sg:address":"2136 Eureka Way",
    "sg:city":"Redding",
    "sg:classifiers":[
        {
            "category":"Professional",
            "subcategory":"Accounting & Tax Preparation",
            "type":"Services"
        }
    ],
    "sg:phone":"+1 530 244 4846",
    "sg:postcode":"96001",
    "sg:province":"CA",
    "sg:tags":[
        "bookkeeping",
        "general"
    ],
    "wof:name":"Tim Riley & Assoc",
    "wof:placetype":"venue"
},
  "geometry": {"coordinates":[-122.402841,40.586697],"type":"Point"}
}