{
  "type": "Feature",
  "properties": {
    "addr:full":"316 Magnolia Ave Larkspur CA 94939",
    "addr:housenumber":"316",
    "addr:postcode":"94939",
    "addr:street":"Magnolia Ave",
    "iso:country":"US",
    "sg:address":"316 Magnolia Ave",
    "sg:city":"Larkspur",
    "sg:classifiers":[
        {
            "category":"Restaurant",
            "type":"Food & Drink"
        }
    ],
    "sg:menulink":"http://www.allmenus.com/ca/ross-valley/48277-pizzeria-picco/menu/",
    "sg:phone":"+1 415 945 8900",
    "sg:postcode":"94939",
    "sg:province":"CA",
    "sg:tags":[
        "american",
        "pizza"
    ],
    "wof:name":"Pizzeria Picco",
    "wof:placetype":"venue"
},
  "geometry": {"coordinates":[-122.535999,37.932593],"type":"Point"}
}