{
  "type": "Feature",
  "properties": {
    "addr:full":"3290 Fairway Dr Soquel CA 95073",
    "addr:housenumber":"3290",
    "addr:postcode":"95073",
    "addr:street":"Fairway Dr",
    "iso:country":"US",
    "sg:address":"3290 Fairway Dr",
    "sg:city":"Soquel",
    "sg:classifiers":[
        {
            "category":"Retail",
            "subcategory":"Portrait Studio",
            "type":"Services"
        }
    ],
    "sg:phone":"+1 831 464 1244",
    "sg:postcode":"95073",
    "sg:province":"CA",
    "sg:tags":[
        "photographer"
    ],
    "sg:website":"www.dquijanophoto.com",
    "wof:name":"Camerawork",
    "wof:placetype":"venue"
},
  "geometry": {"coordinates":[-121.94691899999999,36.989121],"type":"Point"}
}