{
  "type": "Feature",
  "properties": {
    "addr:full":"805 Espee St Bakersfield CA 93301",
    "addr:housenumber":"805",
    "addr:postcode":"93301",
    "addr:street":"Espee St",
    "iso:country":"US",
    "sg:address":"805 Espee St",
    "sg:city":"Bakersfield",
    "sg:classifiers":[
        {
            "category":"Wholesale",
            "subcategory":"Machinery & Supplies",
            "type":"Manufacturing & Wholesale Goods"
        }
    ],
    "sg:phone":"+1 661 325 4710",
    "sg:postcode":"93301",
    "sg:province":"CA",
    "sg:tags":[
        "water",
        "well",
        "drilling"
    ],
    "wof:name":"Sub Surface Sales & Ffbrctrs",
    "wof:placetype":"venue"
},
  "geometry": {"coordinates":[-119.01178899999999,35.38502],"type":"Point"}
}