{
  "type": "Feature",
  "properties": {
    "iso:country":"US",
    "sg:address":"1718 Tecalote Dr",
    "sg:city":"Fallbrook",
    "sg:classifiers":[
        {
            "category":"Manufacturing",
            "subcategory":"Retail Goods",
            "type":"Manufacturing & Wholesale Goods"
        }
    ],
    "sg:phone":"+1 760 728 3282",
    "sg:postcode":"92028",
    "sg:province":"CA",
    "sg:tags":[
        "product",
        "mfg"
    ],
    "wof:name":"JDC Industries",
    "wof:placetype":"venue"
},
  "geometry": {"coordinates":[-117.169503,33.363997],"type":"Point"}
}