{
  "type": "Feature",
  "properties": {
    "addr:full":"11031 Downey Ave Downey CA 90241",
    "addr:housenumber":"11031",
    "addr:postcode":"90241",
    "addr:street":"Downey Ave",
    "iso:country":"US",
    "sg:address":"11031 Downey Ave",
    "sg:city":"Downey",
    "sg:classifiers":[
        {
            "category":"Personal",
            "subcategory":"Beauty Salon",
            "type":"Services"
        }
    ],
    "sg:phone":"+1 562 923 3010",
    "sg:postcode":"90241",
    "sg:province":"CA",
    "sg:tags":[
        "hair"
    ],
    "sg:website":"www.downeyhairstudio.com",
    "wof:name":"Downey Hair Studio",
    "wof:placetype":"venue"
},
  "geometry": {"coordinates":[-118.13229800000001,33.94135],"type":"Point"}
}