{
  "type": "Feature",
  "properties": {
    "iso:country":"US",
    "sg:address":"11675 Sheldon St",
    "sg:city":"Sun Valley",
    "sg:classifiers":[
        {
            "category":"Home & Garden",
            "subcategory":"Home Furnishings",
            "type":"Retail Goods"
        }
    ],
    "sg:phone":"+1 818 897 3535",
    "sg:postcode":"91352",
    "sg:province":"CA",
    "sg:tags":[
        "pillow"
    ],
    "wof:name":"Michelle's Feather & Down Co",
    "wof:placetype":"venue"
},
  "geometry": {"coordinates":[-118.391094,34.241662],"type":"Point"}
}