{
  "type": "Feature",
  "properties": {
    "addr:full":"4190 Roseville Rd North Highlands CA 95660",
    "addr:housenumber":"4190",
    "addr:postcode":"95660",
    "addr:street":"Roseville Rd",
    "iso:country":"US",
    "sg:address":"4190 Roseville Rd",
    "sg:city":"North Highlands",
    "sg:classifiers":[
        {
            "category":"Autos & Motor Vehicles",
            "subcategory":"Automobile Sales",
            "type":"Retail Goods"
        }
    ],
    "sg:phone":"+1 916 487 4483",
    "sg:postcode":"95660",
    "sg:province":"CA",
    "sg:tags":[
        "sport",
        "trailer",
        "utility"
    ],
    "sg:website":"www.pacwesttrailers.com",
    "wof:name":"Pac West Trailers",
    "wof:placetype":"venue"
},
  "geometry": {"coordinates":[-121.402507,38.640592],"type":"Point"}
}