{
  "type": "Feature",
  "properties": {
    "addr:full":"7101 Rosecrans Ave Paramount CA 90723",
    "addr:housenumber":"7101",
    "addr:postcode":"90723",
    "addr:street":"Rosecrans Ave",
    "iso:country":"US",
    "sg:address":"7101 Rosecrans Ave",
    "sg:city":"Paramount",
    "sg:classifiers":[
        {
            "category":"Manufacturing",
            "subcategory":"Apparel",
            "type":"Manufacturing & Wholesale Goods"
        }
    ],
    "sg:phone":"+1 562 930 1273",
    "sg:postcode":"90723",
    "sg:province":"CA",
    "sg:tags":[
        "outerwear",
        "mfg"
    ],
    "wof:name":"Mitchell Tywon",
    "wof:placetype":"venue"
},
  "geometry": {"coordinates":[-118.17973499999999,33.903608],"type":"Point"}
}