{
  "type": "Feature",
  "properties": {
    "addr:full":"7226 Lankershim Blvd North Hollywood CA 91605",
    "addr:housenumber":"7226",
    "addr:postcode":"91605",
    "addr:street":"Lankershim Blvd",
    "iso:country":"US",
    "sg:address":"7226 Lankershim Blvd",
    "sg:city":"North Hollywood",
    "sg:classifiers":[
        {
            "category":"Food & Beverages",
            "subcategory":"Groceries & Convenience Stores",
            "type":"Retail Goods"
        }
    ],
    "sg:phone":"+1 818 765 4598",
    "sg:postcode":"91605",
    "sg:province":"CA",
    "wof:name":"99c & Party Supplies",
    "wof:placetype":"venue"
},
  "geometry": {"coordinates":[-118.387604,34.201656],"type":"Point"}
}