{
  "type": "Feature",
  "properties": {
    "iso:country":"US",
    "sg:address":"1931 Arnold Industrial Way",
    "sg:city":"Concord",
    "sg:classifiers":[
        {
            "category":"Organizations",
            "subcategory":"Non-profit Organization",
            "type":"Services"
        }
    ],
    "sg:phone":"+1 925 827 1709",
    "sg:postcode":"94520",
    "sg:province":"CA",
    "sg:tags":[
        "charitable",
        "institution"
    ],
    "wof:name":"ABC Charity Cars",
    "wof:placetype":"venue"
},
  "geometry": {"coordinates":[-122.046158,38.003184],"type":"Point"}
}