{
  "type": "Feature",
  "properties": {
    "addr:full":"1101 S Robertson Blvd Los Angeles CA 90035",
    "addr:housenumber":"1101",
    "addr:postcode":"90035",
    "addr:street":"S Robertson Blvd",
    "iso:country":"US",
    "sg:address":"1101 S Robertson Blvd",
    "sg:city":"Los Angeles",
    "sg:classifiers":[
        {
            "category":"Banks & Credit Unions",
            "subcategory":"Bank",
            "type":"Services"
        }
    ],
    "sg:phone":"+1 310 278 7759",
    "sg:postcode":"90035",
    "sg:province":"CA",
    "sg:tags":[
        "loan"
    ],
    "wof:name":"Car Cash Leasing",
    "wof:placetype":"venue"
},
  "geometry": {"coordinates":[-118.38370399999999,34.054766],"type":"Point"}
}