{
  "type": "Feature",
  "properties": {
    "addr:full":"1515 W Glenoaks Blvd Glendale CA 91201",
    "addr:housenumber":"1515",
    "addr:postcode":"91201",
    "addr:street":"W Glenoaks Blvd",
    "iso:country":"US",
    "sg:address":"1515 W Glenoaks Blvd",
    "sg:city":"Glendale",
    "sg:classifiers":[
        {
            "category":"Wholesale",
            "subcategory":"Computers",
            "type":"Manufacturing & Wholesale Goods"
        }
    ],
    "sg:phone":"+1 818 244 6242",
    "sg:postcode":"91201",
    "sg:province":"CA",
    "wof:name":"Eritech Internatl",
    "wof:placetype":"venue"
},
  "geometry": {"coordinates":[-118.28600299999999,34.168499],"type":"Point"}
}