{
  "type": "Feature",
  "properties": {
    "iso:country":"US",
    "sg:address":"7725 Manet Pkwy",
    "sg:city":"Sacramento",
    "sg:classifiers":[
        {
            "category":"Building & Trades",
            "subcategory":"Construction",
            "type":"Services"
        }
    ],
    "sg:phone":"+1 916 392 5297",
    "sg:postcode":"95823",
    "sg:province":"CA",
    "sg:tags":[
        "roofing",
        "contractor"
    ],
    "wof:name":"Jay B C Roofing Company Inc",
    "wof:placetype":"venue"
},
  "geometry": {"coordinates":[-121.44841,38.486492],"type":"Point"}
}