{
  "type": "Feature",
  "properties": {
    "addr:full":"825 N McCadden Pl Los Angeles CA 90038",
    "addr:housenumber":"825",
    "addr:postcode":"90038",
    "addr:street":"N Mccadden Pl",
    "iso:country":"US",
    "sg:address":"825 N McCadden Pl",
    "sg:city":"Los Angeles",
    "sg:classifiers":[
        {
            "category":"Building & Trades",
            "subcategory":"Electrical",
            "type":"Services"
        }
    ],
    "sg:phone":"+1 323 463 1598",
    "sg:postcode":"90038",
    "sg:province":"CA",
    "sg:tags":[
        "electric",
        "contractor"
    ],
    "wof:name":"J & S Electric Co",
    "wof:placetype":"venue"
},
  "geometry": {"coordinates":[-118.337492,34.086649],"type":"Point"}
}