{
  "type": "Feature",
  "properties": {
    "addr:full":"4640 Admiralty Way Marina Del Rey CA 90292",
    "addr:housenumber":"4640",
    "addr:postcode":"90292",
    "addr:street":"Admiralty Way",
    "iso:country":"US",
    "sg:address":"4640 Admiralty Way",
    "sg:city":"Marina Del Rey",
    "sg:classifiers":[
        {
            "category":"Banks & Credit Unions",
            "subcategory":"Financial Services",
            "type":"Services"
        }
    ],
    "sg:phone":"+1 310 740 8158",
    "sg:postcode":"90292",
    "sg:province":"CA",
    "sg:tags":[
        "broker",
        "mortgage"
    ],
    "wof:name":"A American Funding Source Inc",
    "wof:placetype":"venue"
},
  "geometry": {"coordinates":[-118.440853,33.981347],"type":"Point"}
}