{
  "type": "Feature",
  "properties": {
    "addr:full":"159 Cakebread Cir Sacramento CA 95834",
    "addr:housenumber":"159",
    "addr:postcode":"95834",
    "addr:street":"Cakebread Cir",
    "iso:country":"US",
    "sg:address":"159 Cakebread Cir",
    "sg:city":"Sacramento",
    "sg:classifiers":[
        {
            "category":"Communications",
            "type":"Services"
        }
    ],
    "sg:phone":"+1 916 419 7326",
    "sg:postcode":"95834",
    "sg:province":"CA",
    "wof:name":"Communications Group",
    "wof:placetype":"venue"
},
  "geometry": {"coordinates":[-121.534875,38.637313],"type":"Point"}
}