{
  "type": "Feature",
  "properties": {
    "iso:country":"US",
    "sg:address":"619 C St",
    "sg:city":"Lemoore",
    "sg:classifiers":[
        {
            "category":"Building & Trades",
            "subcategory":"Electrical",
            "type":"Services"
        }
    ],
    "sg:phone":"+1 559 925 9404",
    "sg:postcode":"93245",
    "sg:province":"CA",
    "sg:tags":[
        "electric",
        "contractor"
    ],
    "wof:name":"Villa Electric Inc",
    "wof:placetype":"venue"
},
  "geometry": {"coordinates":[-119.790872,36.299827],"type":"Point"}
}