{
  "type": "Feature",
  "properties": {
    "iso:country":"US",
    "sg:address":"1218 Llano St",
    "sg:city":"San Clemente",
    "sg:classifiers":[
        {
            "category":"Wholesale",
            "subcategory":"Non-durable Goods",
            "type":"Manufacturing & Wholesale Goods"
        }
    ],
    "sg:phone":"+1 949 361 2700",
    "sg:postcode":"92673",
    "sg:province":"CA",
    "sg:tags":[
        "distribution",
        "package"
    ],
    "wof:name":"About Shamies",
    "wof:placetype":"venue"
},
  "geometry": {"coordinates":[-117.62867,33.467331],"type":"Point"}
}