{
  "type": "Feature",
  "properties": {
    "iso:country":"US",
    "sg:address":"6615 Jamieson Ave",
    "sg:city":"Reseda",
    "sg:classifiers":[
        {
            "category":"Professional",
            "subcategory":"Detective & Security Services",
            "type":"Services"
        }
    ],
    "sg:phone":"+1 818 881 1625",
    "sg:postcode":"91335",
    "sg:province":"CA",
    "sg:tags":[
        "information",
        "bureau"
    ],
    "wof:name":"Urban Services",
    "wof:placetype":"venue"
},
  "geometry": {"coordinates":[-118.52155999999999,34.190443],"type":"Point"}
}