{
  "type": "Feature",
  "properties": {
    "iso:country":"US",
    "sg:address":"26 Brookmont",
    "sg:city":"Irvine",
    "sg:classifiers":[
        {
            "category":"Shopping",
            "type":"Retail Goods"
        }
    ],
    "sg:phone":"+1 949 551 6496",
    "sg:postcode":"92604",
    "sg:province":"CA",
    "sg:tags":[
        "material",
        "artist",
        "supply"
    ],
    "wof:name":"Ashbrook Art Supplies",
    "wof:placetype":"venue"
},
  "geometry": {"coordinates":[-117.784007,33.67707],"type":"Point"}
}