{
  "type": "Feature",
  "properties": {
    "iso:country":"US",
    "sg:address":"1750 Montgomery St",
    "sg:city":"San Francisco",
    "sg:classifiers":[
        {
            "category":"Professional",
            "type":"Services"
        }
    ],
    "sg:phone":"+1 415 773 5324",
    "sg:postcode":"94111",
    "sg:province":"CA",
    "sg:tags":[
        "establishment"
    ],
    "wof:name":"Mountain States",
    "wof:placetype":"venue"
},
  "geometry": {"coordinates":[-122.405209,37.805231],"type":"Point"}
}