{
  "type": "Feature",
  "properties": {
    "iso:country":"US",
    "sg:address":"4257 Tanbark St",
    "sg:city":"San Jose",
    "sg:classifiers":[
        {
            "category":"Building & Trades",
            "subcategory":"Construction",
            "type":"Services"
        }
    ],
    "sg:phone":"+1 650 280 9178",
    "sg:postcode":"95129",
    "sg:province":"CA",
    "sg:tags":[
        "air",
        "heating",
        "conditioning/hvac"
    ],
    "sg:website":"www.innerair.com",
    "wof:name":"Inner Air Heating and Air Conditioning",
    "wof:placetype":"venue"
},
  "geometry": {"coordinates":[-121.97793299999999,37.313814],"type":"Point"}
}