{
  "type": "Feature",
  "properties": {
    "addr:full":"7318 Winding Way Fair Oaks CA 95628",
    "addr:housenumber":"7318",
    "addr:postcode":"95628",
    "addr:street":"Winding Way",
    "iso:country":"US",
    "sg:address":"7318 Winding Way",
    "sg:city":"Fair Oaks",
    "sg:classifiers":[
        {
            "category":"Restaurant",
            "type":"Food & Drink"
        }
    ],
    "sg:phone":"+1 916 962 0740",
    "sg:postcode":"95628",
    "sg:province":"CA",
    "wof:name":"Camino Real Restaurant",
    "wof:placetype":"venue"
},
  "geometry": {"coordinates":[-121.293342,38.649107],"type":"Point"}
}