{
  "type": "Feature",
  "properties": {
    "iso:country":"US",
    "sg:address":"8505 Rosecrans Ave",
    "sg:city":"Paramount",
    "sg:classifiers":[
        {
            "category":"Utilities",
            "subcategory":"Mobile Phone",
            "type":"Services"
        }
    ],
    "sg:phone":"+1 562 220 2818",
    "sg:postcode":"90723",
    "sg:province":"CA",
    "sg:tags":[
        "communication",
        "electronic",
        "radiotelephone"
    ],
    "wof:name":"Pager Shack",
    "wof:placetype":"venue"
},
  "geometry": {"coordinates":[-118.148714,33.903766],"type":"Point"}
}