{
  "type": "Feature",
  "properties": {
    "addr:full":"2862 Arden Way Ste 100 Sacramento CA 95825",
    "addr:housenumber":"2862",
    "addr:postcode":"95825",
    "addr:street":"Arden Way Ste 100",
    "iso:country":"US",
    "sg:address":"2862 Arden Way Ste 100",
    "sg:city":"Sacramento",
    "sg:classifiers":[
        {
            "category":"Building & Trades",
            "subcategory":"Landscaping Services",
            "type":"Services"
        }
    ],
    "sg:phone":"+1 916 481 2328",
    "sg:postcode":"95825",
    "sg:province":"CA",
    "sg:tags":[
        "aged",
        "homes-institutional"
    ],
    "wof:name":"Transitional Support Svcs - N",
    "wof:placetype":"venue"
},
  "geometry": {"coordinates":[-121.39704399999999,38.595951],"type":"Point"}
}