{
  "type": "Feature",
  "properties": {
    "addr:full":"2472 Encinal Dr Walnut Creek CA 94597",
    "addr:housenumber":"2472",
    "addr:postcode":"94597",
    "addr:street":"Encinal Dr",
    "iso:country":"US",
    "sg:address":"2472 Encinal Dr",
    "sg:city":"Walnut Creek",
    "sg:classifiers":[
        {
            "category":"Building & Trades",
            "subcategory":"Electrical",
            "type":"Services"
        }
    ],
    "sg:phone":"+1 925 937 0618",
    "sg:postcode":"94597",
    "sg:province":"CA",
    "sg:tags":[
        "electric",
        "contractor"
    ],
    "wof:name":"County Electric",
    "wof:placetype":"venue"
},
  "geometry": {"coordinates":[-122.06896999999999,37.916568],"type":"Point"}
}