{
  "type": "Feature",
  "properties": {
    "addr:full":"1750 El Camino Real Burlingame CA 94010",
    "addr:housenumber":"1750",
    "addr:postcode":"94010",
    "addr:street":"El Camino Real",
    "iso:country":"US",
    "sg:address":"1750 El Camino Real",
    "sg:city":"Burlingame",
    "sg:classifiers":[
        {
            "category":"Shopping",
            "subcategory":"Pharmacy",
            "type":"Retail Goods"
        }
    ],
    "sg:phone":"+1 650 692 1686",
    "sg:postcode":"94010",
    "sg:province":"CA",
    "sg:tags":[
        "drugstore"
    ],
    "wof:name":"Seventeen Fifty Medical Center Pharmacy",
    "wof:placetype":"venue"
},
  "geometry": {"coordinates":[-122.38200399999999,37.593601],"type":"Point"}
}