{
  "type": "Feature",
  "properties": {
    "iso:country":"US",
    "sg:address":"10734 Jefferson Boulevard",
    "sg:city":"Culver City",
    "sg:classifiers":[
        {
            "category":"Shopping",
            "subcategory":"Tobacco",
            "type":"Retail Goods"
        }
    ],
    "sg:phone":"+1 310 558 8010",
    "sg:postcode":"90230",
    "sg:province":"CA",
    "sg:tags":[
        "shop"
    ],
    "wof:name":"Cc Smoke Shop",
    "wof:placetype":"venue"
},
  "geometry": {"coordinates":[-118.394171,34.003043],"type":"Point"}
}