{
  "type": "Feature",
  "properties": {
    "addr:full":"2373 Oakland Rd San Jose CA 95131",
    "addr:housenumber":"2373",
    "addr:postcode":"95131",
    "addr:street":"Oakland Rd",
    "iso:country":"US",
    "sg:address":"2373 Oakland Rd",
    "sg:city":"San Jose",
    "sg:classifiers":[
        {
            "category":"Manufacturing",
            "subcategory":"Metals",
            "type":"Manufacturing & Wholesale Goods"
        }
    ],
    "sg:phone":"+1 408 433 0696",
    "sg:postcode":"95131",
    "sg:province":"CA",
    "sg:tags":[
        "machine",
        "screw",
        "product"
    ],
    "wof:name":"Swiss Automatic Products",
    "wof:placetype":"venue"
},
  "geometry": {"coordinates":[-121.902928,37.40364],"type":"Point"}
}