{
  "type": "Feature",
  "properties": {
    "iso:country":"US",
    "sg:address":"466 Wilson Ave",
    "sg:city":"Sunnyvale",
    "sg:classifiers":[
        {
            "category":"Professional",
            "subcategory":"Business Services",
            "type":"Services"
        }
    ],
    "sg:phone":"+1 408 738 3266",
    "sg:postcode":"94086",
    "sg:province":"CA",
    "sg:tags":[
        "interior",
        "consultant",
        "design",
        "decorator"
    ],
    "wof:name":"Dasha Interior Designs",
    "wof:placetype":"venue"
},
  "geometry": {"coordinates":[-122.02292799999999,37.370794],"type":"Point"}
}