{
  "type": "Feature",
  "properties": {
    "iso:country":"US",
    "sg:address":"425 E 6th St",
    "sg:city":"Corona",
    "sg:classifiers":[
        {
            "category":"Professional",
            "subcategory":"Advertising",
            "type":"Services"
        }
    ],
    "sg:phone":"+1 951 734 0201",
    "sg:postcode":"92879",
    "sg:province":"CA",
    "sg:tags":[
        "guide"
    ],
    "wof:name":"Little Yellow Pages",
    "wof:placetype":"venue"
},
  "geometry": {"coordinates":[-117.561717,33.875013],"type":"Point"}
}