{
  "type": "Feature",
  "properties": {
    "iso:country":"US",
    "sg:address":"15342 Crenshaw Blvd",
    "sg:city":"Gardena",
    "sg:classifiers":[
        {
            "category":"Fast Food",
            "type":"Food & Drink"
        }
    ],
    "sg:phone":"+1 310 515 1259",
    "sg:postcode":"90249",
    "sg:province":"CA",
    "sg:tags":[
        "burger"
    ],
    "wof:name":"Classic Burger",
    "wof:placetype":"venue"
},
  "geometry": {"coordinates":[-118.327003,33.891201],"type":"Point"}
}