{
  "type": "Feature",
  "properties": {
    "iso:country":"US",
    "sg:address":"2061 Coliseum Ct",
    "sg:city":"Los Banos",
    "sg:classifiers":[
        {
            "category":"Building & Trades",
            "subcategory":"Construction",
            "type":"Services"
        }
    ],
    "sg:phone":"+1 209 826 6564",
    "sg:postcode":"93635",
    "sg:province":"CA",
    "sg:tags":[
        "home",
        "builder"
    ],
    "wof:name":"Woodside Homes Mission Estates",
    "wof:placetype":"venue"
},
  "geometry": {"coordinates":[-120.825226,37.067039],"type":"Point"}
}