{
  "type": "Feature",
  "properties": {
    "addr:full":"411 S Fairfax Ave Los Angeles CA 90036",
    "addr:housenumber":"411",
    "addr:postcode":"90036",
    "addr:street":"S Fairfax Ave",
    "iso:country":"US",
    "sg:address":"411 S Fairfax Ave",
    "sg:city":"Los Angeles",
    "sg:classifiers":[
        {
            "category":"Manufacturing",
            "subcategory":"Tools & Machinery",
            "type":"Manufacturing & Wholesale Goods"
        }
    ],
    "sg:phone":"+1 323 932 1077",
    "sg:postcode":"90036",
    "sg:province":"CA",
    "sg:tags":[
        "lighting",
        "system",
        "mfg"
    ],
    "wof:name":"Digital Xposure",
    "wof:placetype":"venue"
},
  "geometry": {"coordinates":[-118.36147699999999,34.069357],"type":"Point"}
}