{
  "type": "Feature",
  "properties": {
    "acgov:api":"0.0",
    "acgov:type":"K-12",
    "addr:full":"750 Fargo Avenue San Lorenzo CA",
    "wof:categories":[
        "education_and_religion:education=school"
    ],
    "wof:name":"Chinese Christian Schools\u0096San Leandro",
    "wof:placetype":"venue"
},
  "geometry": {"coordinates":[-122.14161977855883,37.68778634427055],"type":"Point"}
}