{
  "type": "Feature",
  "properties": {
    "addr:full":"2021 N Fresno St Fresno CA 93703",
    "addr:housenumber":"2021",
    "addr:postcode":"93703",
    "addr:street":"N Fresno",
    "iso:country":"US",
    "sg:address":"2021 N Fresno St",
    "sg:city":"Fresno",
    "sg:classifiers":[
        {
            "category":"Health Services",
            "subcategory":"Doctor",
            "type":"Services"
        }
    ],
    "sg:phone":"+1 559 222 5759",
    "sg:postcode":"93703",
    "sg:province":"CA",
    "sg:tags":[
        "physician",
        "surgeon"
    ],
    "wof:name":"Fresno Medical Clinic",
    "wof:placetype":"venue"
},
  "geometry": {"coordinates":[-119.781605,36.769172],"type":"Point"}
}