{
  "type": "Feature",
  "properties": {
    "addr:full":"611 Ocean St Santa Cruz CA 95060",
    "addr:housenumber":"611",
    "addr:postcode":"95060",
    "addr:street":"Ocean St",
    "iso:country":"US",
    "sg:address":"611 Ocean St",
    "sg:city":"Santa Cruz",
    "sg:classifiers":[
        {
            "category":"Organizations",
            "subcategory":"Professional Association",
            "type":"Services"
        }
    ],
    "sg:phone":"+1 831 457 3713",
    "sg:postcode":"95060",
    "sg:province":"CA",
    "sg:tags":[
        "chambers",
        "commerce"
    ],
    "wof:name":"Santa Cruz Chamber Of Commerce",
    "wof:placetype":"venue"
},
  "geometry": {"coordinates":[-122.02073900000001,36.977952],"type":"Point"}
}