{
  "type": "Feature",
  "properties": {
    "addr:full":"184 Talmadge Ave San Jose CA 95127",
    "addr:housenumber":"184",
    "addr:postcode":"95127",
    "addr:street":"Talmadge Ave",
    "iso:country":"US",
    "sg:address":"184 Talmadge Ave",
    "sg:city":"San Jose",
    "sg:classifiers":[
        {
            "category":"Building & Trades",
            "subcategory":"Construction",
            "type":"Services"
        }
    ],
    "sg:phone":"+1 408 921 5068",
    "sg:postcode":"95127",
    "sg:province":"CA",
    "sg:tags":[
        "roofing"
    ],
    "wof:name":"AMK Roofing",
    "wof:placetype":"venue"
},
  "geometry": {"coordinates":[-121.829908,37.369916],"type":"Point"}
}