{
  "type": "Feature",
  "properties": {
    "addr:full":"116 N Wetherly Dr Los Angeles CA 90048",
    "addr:housenumber":"116",
    "addr:postcode":"90048",
    "addr:street":"N Wetherly Dr",
    "iso:country":"US",
    "sg:address":"116 N Wetherly Dr",
    "sg:city":"Los Angeles",
    "sg:classifiers":[
        {
            "category":"Professional",
            "subcategory":"Management & Consulting",
            "type":"Services"
        }
    ],
    "sg:phone":"+1 310 247 9454",
    "sg:postcode":"90048",
    "sg:province":"CA",
    "sg:tags":[
        "counselor",
        "public",
        "relations"
    ],
    "wof:name":"LA Hollywood Agency",
    "wof:placetype":"venue"
},
  "geometry": {"coordinates":[-118.38866299999999,34.075906],"type":"Point"}
}