{
  "type": "Feature",
  "properties": {
    "iso:country":"US",
    "sg:address":"1875 S Grant St",
    "sg:city":"San Mateo",
    "sg:classifiers":[
        {
            "category":"Professional",
            "type":"Services"
        }
    ],
    "sg:phone":"+1 650 931 2660",
    "sg:postcode":"94402",
    "sg:province":"CA",
    "wof:name":"Cardiff Ventures",
    "wof:placetype":"venue"
},
  "geometry": {"coordinates":[-122.302091,37.554463],"type":"Point"}
}