{
  "type": "Feature",
  "properties": {
    "addr:full":"231 Kennebec Ave Long Beach CA 90803",
    "addr:housenumber":"231",
    "addr:postcode":"90803",
    "addr:street":"Kennebec Ave",
    "iso:country":"US",
    "sg:address":"231 Kennebec Ave",
    "sg:city":"Long Beach",
    "sg:classifiers":[
        {
            "category":"Travel",
            "subcategory":"Hotels & Motels",
            "type":"Entertainment"
        }
    ],
    "sg:phone":"+1 562 856 0202",
    "sg:postcode":"90803",
    "sg:province":"CA",
    "wof:name":"Beachrunners Inn",
    "wof:placetype":"venue"
},
  "geometry": {"coordinates":[-118.163929,33.767992],"type":"Point"}
}