{
  "type": "Feature",
  "properties": {
    "addr:full":"2213 Artesia Blvd Redondo Beach CA 90278",
    "addr:housenumber":"2213",
    "addr:postcode":"90278",
    "addr:street":"Artesia Blvd",
    "iso:country":"US",
    "sg:address":"2213 Artesia Blvd",
    "sg:city":"Redondo Beach",
    "sg:classifiers":[
        {
            "category":"Building & Trades",
            "subcategory":"Locksmith",
            "type":"Services"
        },
        {
            "category":"Building & Trades",
            "subcategory":"Construction",
            "type":"Services"
        }
    ],
    "sg:phone":"+1 310 376 9066",
    "sg:postcode":"90278",
    "sg:province":"CA",
    "sg:tags":[
        "key",
        "contractor"
    ],
    "sg:website":"redmondlock.com/",
    "wof:name":"Redmond's Key Service",
    "wof:placetype":"venue"
},
  "geometry": {"coordinates":[-118.37200199999999,33.873001],"type":"Point"}
}