{
  "type": "Feature",
  "properties": {
    "addr:full":"5927 W Imperial Hwy Los Angeles CA 90045",
    "addr:housenumber":"5927",
    "addr:postcode":"90045",
    "addr:street":"W Imperial Hwy",
    "iso:country":"US",
    "sg:address":"5927 W Imperial Hwy",
    "sg:city":"Los Angeles",
    "sg:classifiers":[
        {
            "category":"Airline",
            "type":"Transportation"
        }
    ],
    "sg:phone":"+1 310 338 0364",
    "sg:postcode":"90045",
    "sg:province":"CA",
    "sg:tags":[
        "courier",
        "air"
    ],
    "wof:name":"Federal Express Corporation",
    "wof:placetype":"venue"
},
  "geometry": {"coordinates":[-118.42350999999999,33.931435],"type":"Point"}
}