{
  "type": "Feature",
  "properties": {
    "addr:full":"500 del Monte Ave Monterey CA 93940",
    "addr:housenumber":"500",
    "addr:postcode":"93940",
    "addr:street":"Del Monte Ave",
    "iso:country":"US",
    "sg:address":"500 del Monte Ave",
    "sg:city":"Monterey",
    "sg:classifiers":[
        {
            "category":"Food & Beverages",
            "subcategory":"Liquor & Beverages",
            "type":"Retail Goods"
        }
    ],
    "sg:phone":"+1 831 655 3222",
    "sg:postcode":"93940",
    "sg:province":"CA",
    "sg:tags":[
        "wine"
    ],
    "wof:name":"LA Casa Bodega",
    "wof:placetype":"venue"
},
  "geometry": {"coordinates":[-121.888824,36.600153],"type":"Point"}
}