{
  "type": "Feature",
  "properties": {
    "addr:full":"2220 Atlantic Ave Long Beach CA 90806",
    "addr:housenumber":"2220",
    "addr:postcode":"90806",
    "addr:street":"Atlantic Ave",
    "iso:country":"US",
    "sg:address":"2220 Atlantic Ave",
    "sg:city":"Long Beach",
    "sg:classifiers":[
        {
            "category":"Health Services",
            "subcategory":"Doctor",
            "type":"Services"
        }
    ],
    "sg:phone":"+1 562 283 0378",
    "sg:postcode":"90806",
    "sg:province":"CA",
    "wof:name":"For Ever I DO",
    "wof:placetype":"venue"
},
  "geometry": {"coordinates":[-118.18499799999999,33.797401],"type":"Point"}
}