{
  "type": "Feature",
  "properties": {
    "addr:full":"377 Hyacinth Way San Rafael CA 94903",
    "addr:housenumber":"377",
    "addr:postcode":"94903",
    "addr:street":"Hyacinth Way",
    "iso:country":"US",
    "sg:address":"377 Hyacinth Way",
    "sg:city":"San Rafael",
    "sg:classifiers":[
        {
            "category":"Social Services",
            "subcategory":"Child Care",
            "type":"Services"
        }
    ],
    "sg:phone":"+1 415 479 5885",
    "sg:postcode":"94903",
    "sg:province":"CA",
    "wof:name":"Tender Years Preschool Daycare",
    "wof:placetype":"venue"
},
  "geometry": {"coordinates":[-122.550648,38.01015],"type":"Point"}
}