{
  "type": "Feature",
  "properties": {
    "addr:full":"2476 Santa Fe Ave Long Beach CA 90810",
    "addr:housenumber":"2476",
    "addr:postcode":"90810",
    "addr:street":"Santa Fe Ave",
    "iso:country":"US",
    "sg:address":"2476 Santa Fe Ave",
    "sg:city":"Long Beach",
    "sg:classifiers":[
        {
            "category":"Restaurant",
            "type":"Food & Drink"
        }
    ],
    "sg:phone":"+1 562 981 9773",
    "sg:postcode":"90810",
    "sg:province":"CA",
    "wof:name":"Ms Whis Fiesta Mexicana",
    "wof:placetype":"venue"
},
  "geometry": {"coordinates":[-118.214996,33.8022],"type":"Point"}
}