{
  "type": "Feature",
  "properties": {
    "iso:country":"US",
    "sg:address":"444 W Ocean Blvd",
    "sg:city":"Long Beach",
    "sg:classifiers":[
        {
            "category":"Banks & Credit Unions",
            "subcategory":"Bank",
            "type":"Services"
        }
    ],
    "sg:phone":"+1 562 432 0931",
    "sg:postcode":"90802",
    "sg:province":"CA",
    "sg:tags":[
        "loan"
    ],
    "sg:website":"www.calbanktrust.com",
    "wof:name":"California Bank and Trust",
    "wof:placetype":"venue"
},
  "geometry": {"coordinates":[-118.19699900000001,33.7672],"type":"Point"}
}