{
  "type": "Feature",
  "properties": {
    "iso:country":"US",
    "sg:address":"444 De Haro St Ste 101",
    "sg:city":"San Francisco",
    "sg:classifiers":[
        {
            "category":"Winery",
            "type":"Food & Drink"
        },
        {
            "category":"Food & Beverages",
            "subcategory":"Liquor & Beverages",
            "type":"Retail Goods"
        }
    ],
    "sg:phone":"+1 415 495 1350",
    "sg:postcode":"94107",
    "sg:province":"CA",
    "sg:tags":[
        "beer",
        "spirit",
        "wine"
    ],
    "sg:website":"store.chwine.com/shared/StoreFro...",
    "wof:name":"Cameron Hughes Wine",
    "wof:placetype":"venue"
},
  "geometry": {"coordinates":[-122.402021,37.764169],"type":"Point"}
}