{
  "type": "Feature",
  "properties": {
    "iso:country":"US",
    "sg:address":"19529 Bus Center Dr",
    "sg:city":"Northridge",
    "sg:classifiers":[
        {
            "category":"Home & Garden",
            "subcategory":"Furniture",
            "type":"Retail Goods"
        }
    ],
    "sg:phone":"+1 818 727 1080",
    "sg:postcode":"91324",
    "sg:province":"CA",
    "sg:tags":[
        "bed"
    ],
    "wof:name":"Brass Bed Factory",
    "wof:placetype":"venue"
},
  "geometry": {"coordinates":[-118.55457699999999,34.231105],"type":"Point"}
}