{
  "type": "Feature",
  "properties": {
    "iso:country":"US",
    "sg:address":"20906 Warnowood Ln",
    "sg:city":"Anderson",
    "sg:classifiers":[
        {
            "category":"Building & Trades",
            "subcategory":"Construction",
            "type":"Services"
        }
    ],
    "sg:phone":"+1 530 355 4248",
    "sg:postcode":"96007",
    "sg:province":"CA",
    "sg:tags":[
        "tile",
        "dealer"
    ],
    "wof:name":"Franklyn Tile Co",
    "wof:placetype":"venue"
},
  "geometry": {"coordinates":[-122.28265399999999,40.456663],"type":"Point"}
}