{
  "type": "Feature",
  "properties": {
    "iso:country":"US",
    "sg:address":"2248 Townsgate Rd",
    "sg:city":"Westlake Village",
    "sg:classifiers":[
        {
            "category":"Building & Trades",
            "subcategory":"Construction",
            "type":"Services"
        }
    ],
    "sg:phone":"+1 805 496 5050",
    "sg:postcode":"91361",
    "sg:province":"CA",
    "sg:tags":[
        "designer"
    ],
    "sg:website":"www.edgeid.com",
    "wof:name":"Edge Industrial Design Group",
    "wof:placetype":"venue"
},
  "geometry": {"coordinates":[-118.83418,34.160986],"type":"Point"}
}