{
  "type": "Feature",
  "properties": {
    "addr:full":"3301 E 12th St Bldg B, Ste 141 Oakland CA 94620",
    "addr:housenumber":"3301",
    "addr:postcode":"94620",
    "addr:street":"E 12Th St;B Ste 141",
    "iso:country":"US",
    "sg:address":"3301 E 12th St Bldg B, Ste 141",
    "sg:city":"Oakland",
    "sg:classifiers":[
        {
            "category":"Retail",
            "subcategory":"Auto Repair",
            "type":"Services"
        }
    ],
    "sg:phone":"+1 510 536 2200",
    "sg:postcode":"94620",
    "sg:province":"CA",
    "sg:tags":[
        "motorcycle"
    ],
    "wof:name":"Fruitvale Village Bike Station",
    "wof:placetype":"venue"
},
  "geometry": {"coordinates":[-122.225146,37.776208],"type":"Point"}
}