{
  "type": "Feature",
  "properties": {
    "addr:full":"21801 Oxnard Street, Woodland Hills located in the Westfield Promenade Mall Los Angeles CA 91367",
    "addr:housenumber":"21801",
    "addr:postcode":"91367",
    "addr:street":"Oxnard Street;Promenade Mall",
    "iso:country":"US",
    "sg:address":"21801 Oxnard Street, Woodland Hills located in the Westfield Promenade Mall",
    "sg:city":"Los Angeles",
    "sg:classifiers":[
        {
            "category":"Restaurant",
            "type":"Food & Drink"
        }
    ],
    "sg:postcode":"91367",
    "sg:province":"CA",
    "sg:website":"www.mcdonalds.com",
    "wof:name":"McDonald's",
    "wof:placetype":"venue"
},
  "geometry": {"coordinates":[-118.602603,34.180104],"type":"Point"}
}