{
  "type": "Feature",
  "properties": {
    "addr:full":"45 W Dannenberg Rd El Centro CA 92243",
    "addr:housenumber":"45",
    "addr:postcode":"92243",
    "addr:street":"W Dannenberg Rd",
    "iso:country":"US",
    "sg:address":"45 W Dannenberg Rd",
    "sg:city":"El Centro",
    "sg:classifiers":[
        {
            "category":"Wholesale",
            "subcategory":"Farm Supplies",
            "type":"Manufacturing & Wholesale Goods"
        }
    ],
    "sg:phone":"+1 760 352 2847",
    "sg:postcode":"92243",
    "sg:province":"CA",
    "sg:tags":[
        "alfalfa",
        "hay"
    ],
    "wof:name":"Wilbur Ellis Co",
    "wof:placetype":"venue"
},
  "geometry": {"coordinates":[-115.541628,32.766867],"type":"Point"}
}