{
  "type": "Feature",
  "properties": {
    "iso:country":"US",
    "sg:address":"49970 US Hwy 111",
    "sg:city":"Coachella",
    "sg:classifiers":[
        {
            "category":"Wholesale",
            "subcategory":"Fruits & Vegetables",
            "type":"Manufacturing & Wholesale Goods"
        }
    ],
    "sg:phone":"+1 760 391 5300",
    "sg:postcode":"92236",
    "sg:province":"CA",
    "wof:name":"Golden Valley Produce LLC",
    "wof:placetype":"venue"
},
  "geometry": {"coordinates":[-116.169172,33.674552],"type":"Point"}
}