{
  "type": "Feature",
  "properties": {
    "addr:full":"103 Santa Felicia Dr Goleta CA 93117",
    "addr:housenumber":"103",
    "addr:postcode":"93117",
    "addr:street":"Santa Felicia Dr",
    "iso:country":"US",
    "sg:address":"103 Santa Felicia Dr",
    "sg:city":"Goleta",
    "sg:classifiers":[
        {
            "category":"Manufacturing",
            "subcategory":"Food",
            "type":"Manufacturing & Wholesale Goods"
        }
    ],
    "sg:phone":"+1 805 968 2410",
    "sg:postcode":"93117",
    "sg:province":"CA",
    "sg:tags":[
        "bakery",
        "prod",
        "cookie"
    ],
    "wof:name":"Santa Barbara Biscotti Co",
    "wof:placetype":"venue"
},
  "geometry": {"coordinates":[-119.87595,34.4311],"type":"Point"}
}