{
  "type": "Feature",
  "properties": {
    "iso:country":"US",
    "sg:address":"4750 Gosford Rd",
    "sg:city":"Bakersfield",
    "sg:classifiers":[
        {
            "category":"Fast Food",
            "type":"Food & Drink"
        },
        {
            "category":"Restaurant",
            "type":"Food & Drink"
        }
    ],
    "sg:phone":"+1 661 834 0190",
    "sg:postcode":"93313",
    "sg:province":"CA",
    "sg:tags":[
        "american",
        "hot",
        "hamburger",
        "dog"
    ],
    "sg:website":"http://www.jackinthebox.com",
    "wof:name":"Jack in the Box",
    "wof:placetype":"venue"
},
  "geometry": {"coordinates":[-119.092079,35.311361],"type":"Point"}
}