{
  "type": "Feature",
  "properties": {
    "iso:country":"US",
    "sg:address":"11434 Markab Dr",
    "sg:city":"San Diego",
    "sg:classifiers":[
        {
            "category":"Health Services",
            "subcategory":"Clinic",
            "type":"Services"
        }
    ],
    "sg:phone":"+1 858 578 4834",
    "sg:postcode":"92126",
    "sg:province":"CA",
    "wof:name":"A Care Full Life",
    "wof:placetype":"venue"
},
  "geometry": {"coordinates":[-117.140575,32.930512],"type":"Point"}
}