{
  "type": "Feature",
  "properties": {
    "iso:country":"US",
    "sg:address":"8775 Beverly Blvd",
    "sg:city":"Los Angeles",
    "sg:classifiers":[
        {
            "category":"Personal",
            "type":"Services"
        }
    ],
    "sg:phone":"+1 310 855 9331",
    "sg:postcode":"90048",
    "sg:province":"CA",
    "sg:tags":[
        "party",
        "planning",
        "event"
    ],
    "sg:website":"modernevents.com",
    "wof:name":"Modern Events",
    "wof:placetype":"venue"
},
  "geometry": {"coordinates":[-118.382803,34.077228],"type":"Point"}
}