{
  "type": "Feature",
  "properties": {
    "addr:full":"532 5th St Clovis CA 93612",
    "addr:housenumber":"532",
    "addr:postcode":"93612",
    "addr:street":"5Th St",
    "iso:country":"US",
    "sg:address":"532 5th St",
    "sg:city":"Clovis",
    "sg:classifiers":[
        {
            "category":"Shopping",
            "subcategory":"Used Merchandise",
            "type":"Retail Goods"
        }
    ],
    "sg:phone":"+1 559 227 7437",
    "sg:postcode":"93612",
    "sg:province":"CA",
    "sg:tags":[
        "antique"
    ],
    "wof:name":"Unburied Treasures",
    "wof:placetype":"venue"
},
  "geometry": {"coordinates":[-119.702405,36.823856],"type":"Point"}
}