{
  "type": "Feature",
  "properties": {
    "addr:full":"2829 S D St Stockton CA 95206",
    "addr:housenumber":"2829",
    "addr:postcode":"95206",
    "addr:street":"S D St",
    "iso:country":"US",
    "sg:address":"2829 S D St",
    "sg:city":"Stockton",
    "sg:classifiers":[
        {
            "category":"Social Services",
            "subcategory":"Adult Care",
            "type":"Services"
        }
    ],
    "sg:phone":"+1 209 463 7555",
    "sg:postcode":"95206",
    "sg:province":"CA",
    "sg:tags":[
        "home",
        "residential"
    ],
    "wof:name":"Town & Country Guest Home",
    "wof:placetype":"venue"
},
  "geometry": {"coordinates":[-121.248999,37.928397],"type":"Point"}
}