{
  "type": "Feature",
  "properties": {
    "iso:country":"US",
    "sg:address":"1 H St",
    "sg:city":"Chula Vista",
    "sg:classifiers":[
        {
            "category":"Government",
            "subcategory":"Office",
            "type":"Public Place"
        }
    ],
    "sg:phone":"+1 619 691 2195",
    "sg:postcode":"91910",
    "sg:province":"CA",
    "sg:tags":[
        "state",
        "program",
        "health"
    ],
    "wof:name":"Health Care",
    "wof:placetype":"venue"
},
  "geometry": {"coordinates":[-117.066655,32.637349],"type":"Point"}
}