{
  "type": "Feature",
  "properties": {
    "iso:country":"US",
    "sg:address":"1445 5th St",
    "sg:city":"Santa Monica",
    "sg:classifiers":[
        {
            "category":"Freight",
            "type":"Transportation"
        }
    ],
    "sg:phone":"+1 310 393 6947",
    "sg:postcode":"90401",
    "sg:province":"CA",
    "sg:tags":[
        "general"
    ],
    "wof:name":"Storquest Self Storage",
    "wof:placetype":"venue"
},
  "geometry": {"coordinates":[-118.493228,34.016494],"type":"Point"}
}