{
  "type": "Feature",
  "properties": {
    "addr:full":"22251 Welby Way Woodland Hills CA 91303",
    "addr:postcode":"22251;91303",
    "addr:street":"Welby Way",
    "iso:country":"US",
    "sg:address":"22251 Welby Way",
    "sg:city":"Woodland Hills",
    "sg:classifiers":[
        {
            "category":"Building & Trades",
            "subcategory":"Plumbing",
            "type":"Services"
        }
    ],
    "sg:phone":"+1 818 887 9484",
    "sg:postcode":"91303",
    "sg:province":"CA",
    "wof:name":"Hunt Heating & Air Conditioning",
    "wof:placetype":"venue"
},
  "geometry": {"coordinates":[-118.61197199999999,34.193074],"type":"Point"}
}