{
  "type": "Feature",
  "properties": {
    "addr:full":"4142 Verdugo Road Los Angeles CA 90065",
    "addr:housenumber":"4142",
    "addr:postcode":"90065",
    "addr:street":"Verdugo Road",
    "iso:country":"US",
    "sg:address":"4142 Verdugo Road",
    "sg:city":"Los Angeles",
    "sg:classifiers":[
        {
            "category":"Health Services",
            "subcategory":"Dentist",
            "type":"Services"
        }
    ],
    "sg:phone":"+1 818 781 2255",
    "sg:postcode":"90065",
    "sg:province":"CA",
    "wof:name":"Boyadzhyan Gevorak DDS",
    "wof:placetype":"venue"
},
  "geometry": {"coordinates":[-118.23188500000001,34.126586],"type":"Point"}
}