{
  "type": "Feature",
  "properties": {
    "iso:country":"US",
    "sg:address":"15430 Roscoe Blvd",
    "sg:city":"Van Nuys",
    "sg:classifiers":[
        {
            "category":"Autos & Motor Vehicles",
            "subcategory":"Automobile Sales",
            "type":"Retail Goods"
        }
    ],
    "sg:phone":"+1 818 894 3800",
    "sg:postcode":"91402",
    "sg:province":"CA",
    "sg:tags":[
        "car",
        "dealer"
    ],
    "wof:name":"Galpin Aston Martin",
    "wof:placetype":"venue"
},
  "geometry": {"coordinates":[-118.469356,34.221333],"type":"Point"}
}