{
  "type": "Feature",
  "properties": {
    "addr:full":"1680 el Camino Real Santa Clara CA 95050",
    "addr:housenumber":"1680",
    "addr:postcode":"95050",
    "addr:street":"El Camino Real",
    "iso:country":"US",
    "sg:address":"1680 el Camino Real",
    "sg:city":"Santa Clara",
    "sg:classifiers":[
        {
            "category":"Restaurant",
            "type":"Food & Drink"
        }
    ],
    "sg:phone":"+1 408 241 8025",
    "sg:postcode":"95050",
    "sg:province":"CA",
    "wof:name":"Taco Bell",
    "wof:placetype":"venue"
},
  "geometry": {"coordinates":[-121.956767,37.352209],"type":"Point"}
}