{
  "type": "Feature",
  "properties": {
    "addr:full":"5404 Walnut Avenue Suite C Irvine CA 92604",
    "addr:housenumber":"5404",
    "addr:postcode":"92604",
    "addr:street":"Walnut Avenue Suite C",
    "iso:country":"US",
    "sg:address":"5404 Walnut Avenue Suite C",
    "sg:city":"Irvine",
    "sg:classifiers":[
        {
            "category":"Shopping",
            "subcategory":"Gifts & Souvenirs",
            "type":"Retail Goods"
        }
    ],
    "sg:postcode":"92604",
    "sg:province":"CA",
    "sg:tags":[
        "flower"
    ],
    "wof:name":"Takashima",
    "wof:placetype":"venue"
},
  "geometry": {"coordinates":[-117.770538,33.689205],"type":"Point"}
}