{
  "type": "Feature",
  "properties": {
    "addr:full":"5390 Long Beach Blvd Long Beach CA 90805",
    "addr:housenumber":"5390",
    "addr:postcode":"90805",
    "addr:street":"Long Beach Blvd",
    "iso:country":"US",
    "sg:address":"5390 Long Beach Blvd",
    "sg:city":"Long Beach",
    "sg:classifiers":[
        {
            "category":"Home & Garden",
            "subcategory":"Furniture",
            "type":"Retail Goods"
        }
    ],
    "sg:phone":"+1 562 423 7247",
    "sg:postcode":"90805",
    "sg:province":"CA",
    "sg:tags":[
        "store"
    ],
    "wof:name":"Furniture Warehouse",
    "wof:placetype":"venue"
},
  "geometry": {"coordinates":[-118.195999,33.854198],"type":"Point"}
}