{
  "type": "Feature",
  "properties": {
    "addr:full":"1143 E Washington Blvd #330 Pasadena CA 91104",
    "addr:housenumber":"1143",
    "addr:postcode":"91104",
    "addr:street":"E Washington Blvd # 330",
    "iso:country":"US",
    "sg:address":"1143 E Washington Blvd #330",
    "sg:city":"Pasadena",
    "sg:classifiers":[
        {
            "category":"Building & Trades",
            "subcategory":"Construction",
            "type":"Services"
        }
    ],
    "sg:phone":"+1 626 255 0334",
    "sg:postcode":"91104",
    "sg:province":"CA",
    "sg:tags":[
        "contractor"
    ],
    "sg:website":"www.rosecityconstruction.com",
    "wof:name":"Rose City Construction",
    "wof:placetype":"venue"
},
  "geometry": {"coordinates":[-118.126942,34.169031],"type":"Point"}
}