{
  "type": "Feature",
  "properties": {
    "iso:country":"US",
    "sg:address":"427 S Garfield Ave",
    "sg:city":"Alhambra",
    "sg:classifiers":[
        {
            "category":"Wholesale",
            "subcategory":"Groceries",
            "type":"Manufacturing & Wholesale Goods"
        }
    ],
    "sg:phone":"+1 626 281 3328",
    "sg:postcode":"91801",
    "sg:province":"CA",
    "sg:tags":[
        "food",
        "product",
        "health"
    ],
    "wof:name":"Young America Inc",
    "wof:placetype":"venue"
},
  "geometry": {"coordinates":[-118.123198,34.089808],"type":"Point"}
}