{
  "type": "Feature",
  "properties": {
    "addr:full":"2000 Curtis St Berkeley CA 94702",
    "addr:housenumber":"2000",
    "addr:postcode":"94702",
    "addr:street":"Curtis St",
    "iso:country":"US",
    "sg:address":"2000 Curtis St",
    "sg:city":"Berkeley",
    "sg:classifiers":[
        {
            "category":"Professional",
            "type":"Services"
        }
    ],
    "sg:phone":"+1 510 548 7070",
    "sg:postcode":"94702",
    "sg:province":"CA",
    "wof:name":"Alexander Berkey Williams",
    "wof:placetype":"venue"
},
  "geometry": {"coordinates":[-122.2894,37.868497],"type":"Point"}
}