{
  "type": "Feature",
  "properties": {
    "addr:full":"376 Cordova St Pasadena CA 91101",
    "addr:housenumber":"376",
    "addr:postcode":"91101",
    "addr:street":"Cordova St",
    "iso:country":"US",
    "sg:address":"376 Cordova St",
    "sg:city":"Pasadena",
    "sg:classifiers":[
        {
            "category":"Restaurant",
            "type":"Food & Drink"
        }
    ],
    "sg:phone":"+1 626 795 5711",
    "sg:postcode":"91101",
    "sg:province":"CA",
    "sg:tags":[
        "mexican"
    ],
    "wof:name":"Cafe Cordova",
    "wof:placetype":"venue"
},
  "geometry": {"coordinates":[-118.141998,34.1422],"type":"Point"}
}