{
  "type": "Feature",
  "properties": {
    "iso:country":"US",
    "sg:address":"700 Glencrag Way",
    "sg:city":"Woodside",
    "sg:classifiers":[
        {
            "category":"Building & Trades",
            "subcategory":"Electrical",
            "type":"Services"
        }
    ],
    "sg:phone":"+1 650 368 8200",
    "sg:postcode":"94062",
    "sg:province":"CA",
    "sg:tags":[
        "electric",
        "contractor"
    ],
    "wof:name":"Mid Peninsula Electric",
    "wof:placetype":"venue"
},
  "geometry": {"coordinates":[-122.276716,37.452431],"type":"Point"}
}