{
  "type": "Feature",
  "properties": {
    "iso:country":"US",
    "sg:address":"566 Arroyo Seco Dr",
    "sg:city":"San Diego",
    "sg:classifiers":[
        {
            "category":"Building & Trades",
            "subcategory":"Cleaning & Sanitation",
            "type":"Services"
        }
    ],
    "sg:phone":"+1 619 262 3412",
    "sg:postcode":"92114",
    "sg:province":"CA",
    "sg:tags":[
        "janitor"
    ],
    "wof:name":"Rikki Jan Svc",
    "wof:placetype":"venue"
},
  "geometry": {"coordinates":[-117.05334499999999,32.699743],"type":"Point"}
}