{
  "type": "Feature",
  "properties": {
    "addr:full":"222 S Glenoaks Blvd Burbank CA 91502",
    "addr:housenumber":"222",
    "addr:postcode":"91502",
    "addr:street":"S Glenoaks Blvd",
    "iso:country":"US",
    "sg:address":"222 S Glenoaks Blvd",
    "sg:city":"Burbank",
    "sg:classifiers":[
        {
            "category":"Restaurant",
            "type":"Food & Drink"
        }
    ],
    "sg:phone":"+1 818 558 3985",
    "sg:postcode":"91502",
    "sg:province":"CA",
    "sg:tags":[
        "american",
        "latin"
    ],
    "sg:website":"www.elcafecolombia.com",
    "wof:name":"Cafe Colombia",
    "wof:placetype":"venue"
},
  "geometry": {"coordinates":[-118.30500000000001,34.182301],"type":"Point"}
}