{
  "type": "Feature",
  "properties": {
    "addr:full":"2051 Balboa Ave Del Mar CA 92014",
    "addr:housenumber":"2051",
    "addr:postcode":"92014",
    "addr:street":"Balboa Ave",
    "iso:country":"US",
    "sg:address":"2051 Balboa Ave",
    "sg:city":"Del Mar",
    "sg:classifiers":[
        {
            "category":"Building & Trades",
            "subcategory":"Construction",
            "type":"Services"
        }
    ],
    "sg:phone":"+1 858 793 3456",
    "sg:postcode":"92014",
    "sg:province":"CA",
    "sg:tags":[
        "contractor"
    ],
    "wof:name":"Del Mar Restoration Inc",
    "wof:placetype":"venue"
},
  "geometry": {"coordinates":[-117.26226699999999,32.966671],"type":"Point"}
}