{
  "type": "Feature",
  "properties": {
    "addr:full":"1940 Zinfandel Dr Rancho Cordova CA 95670",
    "addr:housenumber":"1940",
    "addr:postcode":"95670",
    "addr:street":"Zinfandel Dr",
    "iso:country":"US",
    "sg:address":"1940 Zinfandel Dr",
    "sg:city":"Rancho Cordova",
    "sg:classifiers":[
        {
            "category":"Autos & Motor Vehicles",
            "subcategory":"Automobile Sales",
            "type":"Retail Goods"
        }
    ],
    "sg:phone":"+1 916 412 0835",
    "sg:postcode":"95670",
    "sg:province":"CA",
    "sg:tags":[
        "car",
        "dealer"
    ],
    "wof:name":"American Dream Rv",
    "wof:placetype":"venue"
},
  "geometry": {"coordinates":[-121.27076,38.615151],"type":"Point"}
}