{
  "type": "Feature",
  "properties": {
    "iso:country":"US",
    "sg:address":"2512 S San Pedro St",
    "sg:city":"Los Angeles",
    "sg:classifiers":[
        {
            "category":"Shopping",
            "subcategory":"Mobile Phones",
            "type":"Retail Goods"
        }
    ],
    "sg:phone":"+1 213 745 2353",
    "sg:postcode":"90011",
    "sg:province":"CA",
    "wof:name":"Wireless Source",
    "wof:placetype":"venue"
},
  "geometry": {"coordinates":[-118.260834,34.20424],"type":"Point"}
}