{
  "type": "Feature",
  "properties": {
    "iso:country":"US",
    "sg:address":"365 N Fortuna Blvd",
    "sg:city":"Fortuna",
    "sg:classifiers":[
        {
            "category":"Real Estate",
            "subcategory":"Real Estate Operator",
            "type":"Services"
        }
    ],
    "sg:phone":"+1 707 725 3041",
    "sg:postcode":"95540",
    "sg:province":"CA",
    "sg:tags":[
        "mobile",
        "home",
        "community"
    ],
    "wof:name":"Fortuna Trailer Village",
    "wof:placetype":"venue"
},
  "geometry": {"coordinates":[-124.14655,40.595174],"type":"Point"}
}