{
  "type": "Feature",
  "properties": {
    "addr:full":"1123 E Las Tunas Dr San Gabriel CA 91776",
    "addr:housenumber":"1123",
    "addr:postcode":"91776",
    "addr:street":"E Las Tunas Dr",
    "iso:country":"US",
    "sg:address":"1123 E Las Tunas Dr",
    "sg:city":"San Gabriel",
    "sg:classifiers":[
        {
            "category":"Personal",
            "subcategory":"Beauty Salon",
            "type":"Services"
        }
    ],
    "sg:phone":"+1 626 291 5045",
    "sg:postcode":"91776",
    "sg:province":"CA",
    "wof:name":"Michaels Beauty Salon",
    "wof:placetype":"venue"
},
  "geometry": {"coordinates":[-118.08378500000001,34.103439],"type":"Point"}
}