{
  "type": "Feature",
  "properties": {
    "addr:full":"9472 Firestone Boulevard Downey CA 90241",
    "addr:housenumber":"9472",
    "addr:postcode":"90241",
    "addr:street":"Firestone Boulevard",
    "iso:country":"US",
    "sg:address":"9472 Firestone Boulevard",
    "sg:city":"Downey",
    "sg:classifiers":[
        {
            "category":"Personal",
            "subcategory":"Massage",
            "type":"Services"
        }
    ],
    "sg:phone":"+1 562 803 1803",
    "sg:postcode":"90241",
    "sg:province":"CA",
    "wof:name":"M & A Day Spa",
    "wof:placetype":"venue"
},
  "geometry": {"coordinates":[-118.11395899999999,33.930384],"type":"Point"}
}