{
  "type": "Feature",
  "properties": {
    "addr:full":"1174 Nevada St Ste 201 Redlands CA 92374",
    "addr:housenumber":"1174",
    "addr:postcode":"92374",
    "addr:street":"Nevada St Ste 201",
    "iso:country":"US",
    "sg:address":"1174 Nevada St Ste 201",
    "sg:city":"Redlands",
    "sg:classifiers":[
        {
            "category":"Professional",
            "subcategory":"Lawyer & Legal Services",
            "type":"Services"
        }
    ],
    "sg:phone":"+1 909 307 6282",
    "sg:postcode":"92374",
    "sg:province":"CA",
    "sg:tags":[
        "plan"
    ],
    "wof:name":"Ismile Inland Empire Inc.",
    "wof:placetype":"venue"
},
  "geometry": {"coordinates":[-117.217466,34.067009],"type":"Point"}
}