{
  "type": "Feature",
  "properties": {
    "iso:country":"US",
    "sg:address":"1624 W Sunset Blvd",
    "sg:city":"Los Angeles",
    "sg:classifiers":[
        {
            "category":"Food & Beverages",
            "subcategory":"Groceries & Convenience Stores",
            "type":"Retail Goods"
        }
    ],
    "sg:phone":"+1 213 250 2445",
    "sg:postcode":"90026",
    "sg:province":"CA",
    "wof:name":"La Guadalupana Mkt",
    "wof:placetype":"venue"
},
  "geometry": {"coordinates":[-118.258003,34.077202],"type":"Point"}
}