{
  "type": "Feature",
  "properties": {
    "addr:full":"2535 el Sutton Ln Sacramento CA 95821",
    "addr:postcode":"2535;95821",
    "addr:street":"El Sutton Ln",
    "iso:country":"US",
    "sg:address":"2535 el Sutton Ln",
    "sg:city":"Sacramento",
    "sg:classifiers":[
        {
            "category":"Government",
            "subcategory":"Police Station",
            "type":"Public Place"
        }
    ],
    "sg:phone":"+1 916 876 5770",
    "sg:postcode":"95821",
    "sg:province":"CA",
    "sg:tags":[
        "protection"
    ],
    "wof:name":"Sheriffs Dept",
    "wof:placetype":"venue"
},
  "geometry": {"coordinates":[-121.402602,38.616689],"type":"Point"}
}