{
  "type": "Feature",
  "properties": {
    "addr:full":"305 Trinity Ave Chowchilla CA 93610",
    "addr:housenumber":"305",
    "addr:postcode":"93610",
    "addr:street":"Trinity Ave",
    "iso:country":"US",
    "sg:address":"305 Trinity Ave",
    "sg:city":"Chowchilla",
    "sg:classifiers":[
        {
            "category":"Banks & Credit Unions",
            "subcategory":"Bank",
            "type":"Services"
        }
    ],
    "sg:phone":"+1 559 665 4868",
    "sg:postcode":"93610",
    "sg:province":"CA",
    "wof:name":"Tri Counties Bank",
    "wof:placetype":"venue"
},
  "geometry": {"coordinates":[-120.25996499999999,37.121276],"type":"Point"}
}