{
  "type": "Feature",
  "properties": {
    "addr:full":"12965 Sandoval St Santa Fe Springs CA 90670",
    "addr:housenumber":"12965",
    "addr:postcode":"90670",
    "addr:street":"Sandoval St",
    "iso:country":"US",
    "sg:address":"12965 Sandoval St",
    "sg:city":"Santa Fe Springs",
    "sg:classifiers":[
        {
            "category":"Manufacturing",
            "subcategory":"Chemicals & Compounds",
            "type":"Manufacturing & Wholesale Goods"
        }
    ],
    "sg:phone":"+1 562 906 0423",
    "sg:postcode":"90670",
    "sg:province":"CA",
    "sg:tags":[
        "gas"
    ],
    "sg:website":"www.airproducts.com",
    "wof:name":"Air Products & Chemicals Inc",
    "wof:placetype":"venue"
},
  "geometry": {"coordinates":[-118.056392,33.938552],"type":"Point"}
}