{
  "type": "Feature",
  "properties": {
    "iso:country":"US",
    "sg:address":"1964 54th St",
    "sg:city":"San Diego",
    "sg:classifiers":[
        {
            "category":"Restaurant",
            "type":"Food & Drink"
        }
    ],
    "sg:phone":"+1 619 262 8854",
    "sg:postcode":"92105",
    "sg:province":"CA",
    "sg:tags":[
        "soul"
    ],
    "sg:website":"www.bonniejeanssoulfood.com/",
    "wof:name":"Bonnie Jean's Soul Food Caf?",
    "wof:placetype":"venue"
},
  "geometry": {"coordinates":[-117.083,32.725498],"type":"Point"}
}