{
  "type": "Feature",
  "properties": {
    "addr:full":"8836 Lookout Mountain Ave Los Angeles CA 90046",
    "addr:housenumber":"8836",
    "addr:postcode":"90046",
    "addr:street":"Lookout Mountain Ave",
    "iso:country":"US",
    "sg:address":"8836 Lookout Mountain Ave",
    "sg:city":"Los Angeles",
    "sg:classifiers":[
        {
            "category":"Professional",
            "type":"Services"
        }
    ],
    "sg:phone":"+1 323 650 1905",
    "sg:postcode":"90046",
    "sg:province":"CA",
    "wof:name":"Tantrum Boy Llc",
    "wof:placetype":"venue"
},
  "geometry": {"coordinates":[-118.384939,34.106996],"type":"Point"}
}