{
  "type": "Feature",
  "properties": {
    "iso:country":"US",
    "sg:address":"10519 Troon Ave",
    "sg:city":"Los Angeles",
    "sg:classifiers":[
        {
            "category":"Health Services",
            "subcategory":"Doctor",
            "type":"Services"
        }
    ],
    "sg:phone":"+1 310 842 8442",
    "sg:postcode":"90064",
    "sg:province":"CA",
    "sg:tags":[
        "physician",
        "surgeon"
    ],
    "wof:name":"Network",
    "wof:placetype":"venue"
},
  "geometry": {"coordinates":[-118.41446999999999,34.038106],"type":"Point"}
}