{
  "type": "Feature",
  "properties": {
    "addr:full":"1837 N Shattuck Pl Orange CA 92865",
    "addr:housenumber":"1837",
    "addr:postcode":"92865",
    "addr:street":"N Shattuck Pl",
    "iso:country":"US",
    "sg:address":"1837 N Shattuck Pl",
    "sg:city":"Orange",
    "sg:classifiers":[
        {
            "category":"Real Estate",
            "subcategory":"Real Estate Agent",
            "type":"Services"
        }
    ],
    "sg:phone":"+1 714 637 7683",
    "sg:postcode":"92865",
    "sg:province":"CA",
    "wof:name":"Nelson Enterprises",
    "wof:placetype":"venue"
},
  "geometry": {"coordinates":[-117.837037,33.81911],"type":"Point"}
}