{
  "type": "Feature",
  "properties": {
    "addr:full":"1023 E 17th St National City CA 91950",
    "addr:housenumber":"1023",
    "addr:postcode":"91950",
    "addr:street":"E 17Th St",
    "iso:country":"US",
    "sg:address":"1023 E 17th St",
    "sg:city":"National City",
    "sg:classifiers":[
        {
            "category":"Banks & Credit Unions",
            "subcategory":"Financial Services",
            "type":"Services"
        }
    ],
    "sg:phone":"+1 619 474 2382",
    "sg:postcode":"91950",
    "sg:province":"CA",
    "sg:tags":[
        "trust",
        "management"
    ],
    "wof:name":"Banashak Family Trust",
    "wof:placetype":"venue"
},
  "geometry": {"coordinates":[-117.092941,32.671196],"type":"Point"}
}