{
  "type": "Feature",
  "properties": {
    "addr:full":"1077 W Foothill Blvd Claremont CA 91711",
    "addr:housenumber":"1077",
    "addr:postcode":"91711",
    "addr:street":"W Foothill Blvd",
    "iso:country":"US",
    "sg:address":"1077 W Foothill Blvd",
    "sg:city":"Claremont",
    "sg:classifiers":[
        {
            "category":"Restaurant",
            "type":"Food & Drink"
        }
    ],
    "sg:phone":"+1 909 626 4426",
    "sg:postcode":"91711",
    "sg:province":"CA",
    "wof:name":"Inka Trails",
    "wof:placetype":"venue"
},
  "geometry": {"coordinates":[-117.73642700000001,34.107165],"type":"Point"}
}