{
  "type": "Feature",
  "properties": {
    "addr:full":"137 Cedar Rock Cir Sacramento CA 95823",
    "addr:housenumber":"137",
    "addr:postcode":"95823",
    "addr:street":"Cedar Rock Cir",
    "iso:country":"US",
    "sg:address":"137 Cedar Rock Cir",
    "sg:city":"Sacramento",
    "sg:classifiers":[
        {
            "category":"Professional",
            "subcategory":"Business Services",
            "type":"Services"
        }
    ],
    "sg:phone":"+1 916 427 2282",
    "sg:postcode":"95823",
    "sg:province":"CA",
    "sg:tags":[
        "process",
        "server"
    ],
    "wof:name":"Access Attorney Svc",
    "wof:placetype":"venue"
},
  "geometry": {"coordinates":[-121.458708,38.481164],"type":"Point"}
}