{
  "type": "Feature",
  "properties": {
    "addr:full":"8314-16 W 3rd St Los Angeles CA 90048",
    "addr:housenumber":"8314-16",
    "addr:postcode":"90048",
    "addr:street":"W 3Rd St",
    "iso:country":"US",
    "sg:address":"8314-16 W 3rd St",
    "sg:city":"Los Angeles",
    "sg:classifiers":[
        {
            "category":"Coffee & Tea",
            "type":"Food & Drink"
        },
        {
            "category":"Restaurant",
            "type":"Food & Drink"
        }
    ],
    "sg:phone":"+1 323 424 3482",
    "sg:postcode":"90048",
    "sg:province":"CA",
    "sg:website":"www.marcelitalartetlethe.com",
    "wof:name":"Marcelita L'art et le Th?",
    "wof:placetype":"venue"
},
  "geometry": {"coordinates":[-118.37063499999999,34.07247],"type":"Point"}
}