{
  "type": "Feature",
  "properties": {
    "addr:full":"15717 Amar Rd La Puente CA 91744",
    "addr:housenumber":"15717",
    "addr:postcode":"91744",
    "addr:street":"Amar Rd",
    "iso:country":"US",
    "sg:address":"15717 Amar Rd",
    "sg:city":"La Puente",
    "sg:classifiers":[
        {
            "category":"Shopping",
            "subcategory":"Computers & Home Electronics",
            "type":"Retail Goods"
        }
    ],
    "sg:phone":"+1 626 968 3486",
    "sg:postcode":"91744",
    "sg:province":"CA",
    "sg:tags":[
        "television",
        "radio"
    ],
    "wof:name":"Ponce Electronics Inc",
    "wof:placetype":"venue"
},
  "geometry": {"coordinates":[-117.941152,34.036579],"type":"Point"}
}