{
  "type": "Feature",
  "properties": {
    "iso:country":"US",
    "sg:address":"5537 Santa Monica Blvd",
    "sg:city":"Los Angeles",
    "sg:classifiers":[
        {
            "category":"Shopping",
            "subcategory":"Gifts & Souvenirs",
            "type":"Retail Goods"
        }
    ],
    "sg:phone":"+1 323 464 5361",
    "sg:postcode":"90038",
    "sg:province":"CA",
    "wof:name":"Ss Gift Shop",
    "wof:placetype":"venue"
},
  "geometry": {"coordinates":[-118.310371,34.090843],"type":"Point"}
}