{
  "type": "Feature",
  "properties": {
    "iso:country":"US",
    "sg:address":"500 Vallejo St",
    "sg:city":"Petaluma",
    "sg:classifiers":[
        {
            "category":"Education",
            "subcategory":"School",
            "type":"Public Place"
        }
    ],
    "sg:phone":"+1 707 778 4758",
    "sg:postcode":"94952",
    "sg:province":"CA",
    "wof:name":"San Antonio High School",
    "wof:placetype":"venue"
},
  "geometry": {"coordinates":[-122.626928,38.238151],"type":"Point"}
}