{
  "type": "Feature",
  "properties": {
    "iso:country":"US",
    "sg:address":"23495 Oat Hill Rd",
    "sg:city":"Middletown",
    "sg:classifiers":[
        {
            "category":"Professional",
            "subcategory":"Accounting & Tax Preparation",
            "type":"Services"
        }
    ],
    "sg:phone":"+1 707 987 9452",
    "sg:postcode":"95461",
    "sg:province":"CA",
    "sg:tags":[
        "bookkeeping",
        "general"
    ],
    "wof:name":"Sternberg Bookkeeping",
    "wof:placetype":"venue"
},
  "geometry": {"coordinates":[-122.533983,38.708635],"type":"Point"}
}