{
  "type": "Feature",
  "properties": {
    "addr:full":"23495 Oat Hill Rd Middletown CA 95461",
    "addr:housenumber":"23495",
    "addr:postcode":"95461",
    "addr:street":"Oat Hill Rd",
    "iso:country":"US",
    "sg:address":"23495 Oat Hill Rd",
    "sg:city":"Middletown",
    "sg:classifiers":[
        {
            "category":"Professional",
            "subcategory":"Accounting & Tax Preparation",
            "type":"Services"
        }
    ],
    "sg:phone":"+1 707 987 9452",
    "sg:postcode":"95461",
    "sg:province":"CA",
    "sg:tags":[
        "bookkeeping",
        "general"
    ],
    "wof:name":"Sternberg Bookkeeping",
    "wof:placetype":"venue"
},
  "geometry": {"coordinates":[-122.53398300000001,38.708635],"type":"Point"}
}