{
  "type": "Feature",
  "properties": {
    "iso:country":"US",
    "sg:address":"2499 Pacific Hwy",
    "sg:city":"San Diego",
    "sg:classifiers":[
        {
            "category":"Retail",
            "subcategory":"Auto Rental",
            "type":"Services"
        }
    ],
    "sg:phone":"+1 866 434 2226",
    "sg:postcode":"92101",
    "sg:province":"CA",
    "sg:tags":[
        "car"
    ],
    "sg:website":"www.dollar.com",
    "wof:name":"Dollar Rent A Car",
    "wof:placetype":"venue"
},
  "geometry": {"coordinates":[-117.17311100000001,32.729412],"type":"Point"}
}