{
  "type": "Feature",
  "properties": {
    "iso:country":"US",
    "sg:address":"9501 Folsom Blvd",
    "sg:city":"Sacramento",
    "sg:classifiers":[
        {
            "category":"Organizations",
            "subcategory":"Religious Organization",
            "type":"Services"
        }
    ],
    "sg:phone":"+1 916 364 0991",
    "sg:postcode":"95827",
    "sg:province":"CA",
    "sg:tags":[
        "church"
    ],
    "wof:name":"Sacramento Zion Presbyterian",
    "wof:placetype":"venue"
},
  "geometry": {"coordinates":[-121.347758,38.566455],"type":"Point"}
}