{
  "type": "Feature",
  "properties": {
    "iso:country":"US",
    "sg:address":"29282 Oakmont Ct",
    "sg:city":"Murrieta",
    "sg:classifiers":[
        {
            "category":"Wholesale",
            "subcategory":"Home Furnishings",
            "type":"Manufacturing & Wholesale Goods"
        }
    ],
    "sg:phone":"+1 951 696 1105",
    "sg:postcode":"92563",
    "sg:province":"CA",
    "wof:name":"Temecula Home Design",
    "wof:placetype":"venue"
},
  "geometry": {"coordinates":[-117.146637,33.567424],"type":"Point"}
}