{
  "type": "Feature",
  "properties": {
    "addr:full":"13345 Johnson Rd Los Banos CA 93635",
    "addr:housenumber":"13345",
    "addr:postcode":"93635",
    "addr:street":"Johnson Rd",
    "iso:country":"US",
    "sg:address":"13345 Johnson Rd",
    "sg:city":"Los Banos",
    "sg:classifiers":[
        {
            "category":"Wholesale",
            "subcategory":"Farm Supplies",
            "type":"Manufacturing & Wholesale Goods"
        }
    ],
    "sg:phone":"+1 209 827 3939",
    "sg:postcode":"93635",
    "sg:province":"CA",
    "sg:tags":[
        "alfalfa",
        "hay"
    ],
    "wof:name":"Nunes & Nunes Hay Sales Inc",
    "wof:placetype":"venue"
},
  "geometry": {"coordinates":[-120.865115,37.094545],"type":"Point"}
}