{
  "type": "Feature",
  "properties": {
    "iso:country":"US",
    "sg:address":"1151 Dove St Ste 245",
    "sg:city":"Newport Beach",
    "sg:classifiers":[
        {
            "category":"Health Services",
            "subcategory":"Clinic",
            "type":"Services"
        },
        {
            "category":"Professional",
            "subcategory":"Management & Consulting",
            "type":"Services"
        }
    ],
    "sg:phone":"+1 949 922 7800",
    "sg:postcode":"92660",
    "sg:province":"CA",
    "sg:tags":[
        "counseling",
        "life",
        "coach",
        "mental"
    ],
    "sg:website":"www.shelleywilson.com",
    "wof:name":"Shelley Wilson, MFT",
    "wof:placetype":"venue"
},
  "geometry": {"coordinates":[-117.86590099999999,33.660517],"type":"Point"}
}