{
  "type": "Feature",
  "properties": {
    "addr:full":"14950 Delano St Van Nuys CA 91411",
    "addr:housenumber":"14950",
    "addr:postcode":"91411",
    "addr:street":"Delano St",
    "iso:country":"US",
    "sg:address":"14950 Delano St",
    "sg:city":"Van Nuys",
    "sg:classifiers":[
        {
            "category":"Building & Trades",
            "subcategory":"Plumbing",
            "type":"Services"
        }
    ],
    "sg:phone":"+1 818 787 6110",
    "sg:postcode":"91411",
    "sg:province":"CA",
    "sg:tags":[
        "plumbing",
        "contractor"
    ],
    "wof:name":"C L Skelton Plumbing Contr",
    "wof:placetype":"venue"
},
  "geometry": {"coordinates":[-118.458707,34.182498],"type":"Point"}
}