{
  "type": "Feature",
  "properties": {
    "addr:full":"202 Capitola Ave Capitola CA 95010",
    "addr:housenumber":"202",
    "addr:postcode":"95010",
    "addr:street":"Capitola Ave",
    "iso:country":"US",
    "sg:address":"202 Capitola Ave",
    "sg:city":"Capitola",
    "sg:classifiers":[
        {
            "category":"Shopping",
            "subcategory":"Optician",
            "type":"Retail Goods"
        }
    ],
    "sg:phone":"+1 831 464 9600",
    "sg:postcode":"95010",
    "sg:province":"CA",
    "sg:tags":[
        "eyewear"
    ],
    "wof:name":"Sunglass Hut",
    "wof:placetype":"venue"
},
  "geometry": {"coordinates":[-121.951307,36.973097],"type":"Point"}
}