{
  "type": "Feature",
  "properties": {
    "addr:full":"6216 Kettlerock Mtn Ct Bakersfield CA 93313",
    "addr:housenumber":"6216",
    "addr:postcode":"93313",
    "addr:street":"Kettlerock Mtn Ct",
    "iso:country":"US",
    "sg:address":"6216 Kettlerock Mtn Ct",
    "sg:city":"Bakersfield",
    "sg:classifiers":[
        {
            "category":"Manufacturing",
            "subcategory":"Metals",
            "type":"Manufacturing & Wholesale Goods"
        }
    ],
    "sg:phone":"+1 661 665 1222",
    "sg:postcode":"93313",
    "sg:province":"CA",
    "sg:tags":[
        "engraver"
    ],
    "wof:name":"Teeter's Tags",
    "wof:placetype":"venue"
},
  "geometry": {"coordinates":[-119.083567,35.301075],"type":"Point"}
}