{
  "type": "Feature",
  "properties": {
    "addr:full":"22466 Paragon Dr Santa Clarita CA 91350",
    "addr:housenumber":"22466",
    "addr:postcode":"91350",
    "addr:street":"Paragon Dr",
    "iso:country":"US",
    "sg:address":"22466 Paragon Dr",
    "sg:city":"Santa Clarita",
    "sg:classifiers":[
        {
            "category":"Retail",
            "subcategory":"Repair Shop",
            "type":"Services"
        }
    ],
    "sg:phone":"+1 661 288 7806",
    "sg:postcode":"91350",
    "sg:province":"CA",
    "sg:tags":[
        "appliance"
    ],
    "wof:name":"L-&-A Heating & Air",
    "wof:placetype":"venue"
},
  "geometry": {"coordinates":[-118.528385,34.457435],"type":"Point"}
}