{
  "type": "Feature",
  "properties": {
    "iso:country":"US",
    "sg:address":"20613 Scofield Dr",
    "sg:city":"Cupertino",
    "sg:classifiers":[
        {
            "category":"Place Of Worship",
            "subcategory":"Church",
            "type":"Public Place"
        },
        {
            "category":"Place Of Worship",
            "type":"Public Place"
        }
    ],
    "sg:phone":"+1 408 253 0957",
    "sg:postcode":"95014",
    "sg:province":"CA",
    "sg:tags":[
        "churches-interdenominational",
        "churches-various",
        "denomination"
    ],
    "wof:name":"Universal Life Rhythms",
    "wof:placetype":"venue"
},
  "geometry": {"coordinates":[-122.034076,37.321063],"type":"Point"}
}