{
  "type": "Feature",
  "properties": {
    "iso:country":"US",
    "sg:address":"2640 Faivre St",
    "sg:city":"Chula Vista",
    "sg:classifiers":[
        {
            "category":"Home & Garden",
            "subcategory":"Furniture",
            "type":"Retail Goods"
        }
    ],
    "sg:phone":"+1 619 628 8016",
    "sg:postcode":"91911",
    "sg:province":"CA",
    "sg:tags":[
        "cabinet"
    ],
    "wof:name":"Mahogany Cabinets",
    "wof:placetype":"venue"
},
  "geometry": {"coordinates":[-117.078459,32.593045],"type":"Point"}
}