{
  "type": "Feature",
  "properties": {
    "addr:full":"13300 Davos Dr Truckee CA 96161",
    "addr:postcode":"13300;96161",
    "addr:street":"Davos Dr",
    "iso:country":"US",
    "sg:address":"13300 Davos Dr",
    "sg:city":"Truckee",
    "sg:classifiers":[
        {
            "category":"Wholesale",
            "subcategory":"Sporting Goods",
            "type":"Manufacturing & Wholesale Goods"
        }
    ],
    "sg:phone":"+1 530 587 8345",
    "sg:postcode":"96161",
    "sg:province":"CA",
    "wof:name":"Corvid Construction",
    "wof:placetype":"venue"
},
  "geometry": {"coordinates":[-120.23056,39.339824],"type":"Point"}
}