{
  "type": "Feature",
  "properties": {
    "iso:country":"US",
    "sg:address":"7777 Edinger Ave Ste 120",
    "sg:city":"Huntington Beach",
    "sg:classifiers":[
        {
            "category":"Restaurant",
            "type":"Food & Drink"
        }
    ],
    "sg:phone":"+1 714 893 1863",
    "sg:postcode":"92647",
    "sg:province":"CA",
    "sg:tags":[
        "new",
        "american"
    ],
    "sg:website":"www.tacone.com",
    "wof:name":"Tacone Flavor Grill",
    "wof:placetype":"venue"
},
  "geometry": {"coordinates":[-117.99444099999999,33.731549],"type":"Point"}
}