{
  "type": "Feature",
  "properties": {
    "iso:country":"US",
    "sg:address":"500 E Esplanade Dr",
    "sg:city":"Oxnard",
    "sg:classifiers":[
        {
            "category":"Professional",
            "type":"Services"
        }
    ],
    "sg:phone":"+1 805 604 7077",
    "sg:postcode":"93036",
    "sg:province":"CA",
    "sg:tags":[
        "establishment"
    ],
    "wof:name":"Golden State Developers",
    "wof:placetype":"venue"
},
  "geometry": {"coordinates":[-119.171211,34.229069],"type":"Point"}
}