{
  "type": "Feature",
  "properties": {
    "addr:full":"1821 N Helm Ave Fresno CA 93727",
    "addr:housenumber":"1821",
    "addr:postcode":"93727",
    "addr:street":"N Helm Ave",
    "iso:country":"US",
    "sg:address":"1821 N Helm Ave",
    "sg:city":"Fresno",
    "sg:classifiers":[
        {
            "category":"Shopping",
            "type":"Retail Goods"
        },
        {
            "category":"Organizations",
            "subcategory":"Non-profit Organization",
            "type":"Services"
        }
    ],
    "sg:phone":"+1 559 255 4500",
    "sg:postcode":"93727",
    "sg:province":"CA",
    "sg:tags":[
        "fund",
        "games",
        "raising",
        "merchandise",
        "supply"
    ],
    "wof:name":"Profit Specialties",
    "wof:placetype":"venue"
},
  "geometry": {"coordinates":[-119.72376800000001,36.767932],"type":"Point"}
}