{
  "type": "Feature",
  "properties": {
    "iso:country":"US",
    "sg:address":"13633 Foothill Blvd",
    "sg:city":"Sylmar",
    "sg:classifiers":[
        {
            "category":"Banks & Credit Unions",
            "subcategory":"Bank",
            "type":"Services"
        }
    ],
    "sg:phone":"+1 818 367 1552",
    "sg:postcode":"91342",
    "sg:province":"CA",
    "sg:tags":[
        "depository",
        "banking"
    ],
    "wof:name":"Check By Check",
    "wof:placetype":"venue"
},
  "geometry": {"coordinates":[-118.433689,34.310157],"type":"Point"}
}