{
  "type": "Feature",
  "properties": {
    "iso:country":"US",
    "sg:address":"777 Corporate Dr Ste 250",
    "sg:city":"Ladera Ranch",
    "sg:classifiers":[
        {
            "category":"Health Services",
            "subcategory":"Doctor",
            "type":"Services"
        }
    ],
    "sg:phone":"+1 949 388 1798",
    "sg:postcode":"92694",
    "sg:province":"CA",
    "sg:tags":[
        "pediatrician"
    ],
    "sg:website":"www.socpa.com",
    "wof:name":"Southern Orange County Pediatric Associates",
    "wof:placetype":"venue"
},
  "geometry": {"coordinates":[-117.629254,33.557424],"type":"Point"}
}