{
  "type": "Feature",
  "properties": {
    "iso:country":"US",
    "sg:address":"3239 Imjin Rd",
    "sg:city":"Marina",
    "sg:classifiers":[
        {
            "category":"Professional",
            "type":"Services"
        }
    ],
    "sg:phone":"+1 831 384 7164",
    "sg:postcode":"93933",
    "sg:province":"CA",
    "sg:tags":[
        "establishment"
    ],
    "wof:name":"Thomas R Bennett & Assoc",
    "wof:placetype":"venue"
},
  "geometry": {"coordinates":[-121.795615,36.659403],"type":"Point"}
}