{
  "type": "Feature",
  "properties": {
    "iso:country":"US",
    "sg:address":"1733 Abbot Kinney Blvd",
    "sg:city":"Venice",
    "sg:classifiers":[
        {
            "category":"Sports & Exercise",
            "subcategory":"Gym",
            "type":"Entertainment"
        }
    ],
    "sg:phone":"+1 310 301 9933",
    "sg:postcode":"90291",
    "sg:province":"CA",
    "sg:tags":[
        "club",
        "health",
        "studio",
        "gymnasium"
    ],
    "wof:name":"Curves For Women",
    "wof:placetype":"venue"
},
  "geometry": {"coordinates":[-118.459873,33.988027],"type":"Point"}
}