{
  "type": "Feature",
  "properties": {
    "iso:country":"US",
    "sg:address":"7246 Sharon Dr",
    "sg:city":"San Jose",
    "sg:classifiers":[
        {
            "category":"Retail",
            "subcategory":"Portrait Studio",
            "type":"Services"
        }
    ],
    "sg:phone":"+1 408 252 5988",
    "sg:postcode":"95129",
    "sg:province":"CA",
    "sg:tags":[
        "photography",
        "store"
    ],
    "wof:name":"Sat Writing Classroom",
    "wof:placetype":"venue"
},
  "geometry": {"coordinates":[-122.031182,37.296728],"type":"Point"}
}