{
  "type": "Feature",
  "properties": {
    "addr:full":"222 E Anapamu St Santa Barbara CA 93101",
    "addr:housenumber":"222",
    "addr:postcode":"93101",
    "addr:street":"E Anapamu St",
    "iso:country":"US",
    "sg:address":"222 E Anapamu St",
    "sg:city":"Santa Barbara",
    "sg:classifiers":[
        {
            "category":"Government",
            "subcategory":"Office",
            "type":"Public Place"
        }
    ],
    "sg:phone":"+1 805 568 2546",
    "sg:postcode":"93101",
    "sg:province":"CA",
    "wof:name":"Santa Barbara Assn-Governments",
    "wof:placetype":"venue"
},
  "geometry": {"coordinates":[-119.70122499999999,34.426248],"type":"Point"}
}