{
  "type": "Feature",
  "properties": {
    "addr:full":"9618 Whittier Blvd Pico Rivera CA 90660",
    "addr:housenumber":"9618",
    "addr:postcode":"90660",
    "addr:street":"Whittier Blvd",
    "iso:country":"US",
    "sg:address":"9618 Whittier Blvd",
    "sg:city":"Pico Rivera",
    "sg:classifiers":[
        {
            "category":"Building & Trades",
            "subcategory":"Construction",
            "type":"Services"
        }
    ],
    "sg:phone":"+1 562 948 2024",
    "sg:postcode":"90660",
    "sg:province":"CA",
    "sg:tags":[
        "contractor"
    ],
    "wof:name":"Sully-Miller Contracting Company",
    "wof:placetype":"venue"
},
  "geometry": {"coordinates":[-118.405638,33.996706],"type":"Point"}
}