{
  "type": "Feature",
  "properties": {
    "addr:full":"2580 Santa Fe Ave Redondo Beach CA 90278",
    "addr:housenumber":"2580",
    "addr:postcode":"90278",
    "addr:street":"Santa Fe Ave",
    "iso:country":"US",
    "sg:address":"2580 Santa Fe Ave",
    "sg:city":"Redondo Beach",
    "sg:classifiers":[
        {
            "category":"Freight",
            "type":"Transportation"
        }
    ],
    "sg:phone":"+1 310 727 1700",
    "sg:postcode":"90278",
    "sg:province":"CA",
    "sg:tags":[
        "air",
        "forwarders"
    ],
    "wof:name":"K A T Import Brokers",
    "wof:placetype":"venue"
},
  "geometry": {"coordinates":[-118.368201,33.889742],"type":"Point"}
}