{
  "type": "Feature",
  "properties": {
    "addr:full":"100 W Bonita Ave San Dimas CA 91773",
    "addr:housenumber":"100",
    "addr:postcode":"91773",
    "addr:street":"W Bonita Ave",
    "iso:country":"US",
    "sg:address":"100 W Bonita Ave",
    "sg:city":"San Dimas",
    "sg:classifiers":[
        {
            "category":"Autos & Motor Vehicles",
            "subcategory":"Auto Supplies",
            "type":"Retail Goods"
        }
    ],
    "sg:phone":"+1 909 599 6872",
    "sg:postcode":"91773",
    "sg:province":"CA",
    "sg:tags":[
        "tire"
    ],
    "wof:name":"People's Tire",
    "wof:placetype":"venue"
},
  "geometry": {"coordinates":[-117.80840000000001,34.106657],"type":"Point"}
}