{
  "type": "Feature",
  "properties": {
    "addr:full":"12925 Riverside Dr Sherman Oaks CA 91423",
    "addr:housenumber":"12925",
    "addr:postcode":"91423",
    "addr:street":"Riverside Dr",
    "iso:country":"US",
    "sg:address":"12925 Riverside Dr",
    "sg:city":"Sherman Oaks",
    "sg:classifiers":[
        {
            "category":"Professional",
            "subcategory":"Lawyer & Legal Services",
            "type":"Services"
        }
    ],
    "sg:phone":"+1 818 990 8863",
    "sg:postcode":"91423",
    "sg:province":"CA",
    "wof:name":"Childs Carol E Atty",
    "wof:placetype":"venue"
},
  "geometry": {"coordinates":[-118.415001,34.1576],"type":"Point"}
}