{
  "type": "Feature",
  "properties": {
    "addr:full":"14300 San Cristobal Dr La Mirada CA 90638",
    "addr:housenumber":"14300",
    "addr:postcode":"90638",
    "addr:street":"San Cristobal Dr",
    "iso:country":"US",
    "sg:address":"14300 San Cristobal Dr",
    "sg:city":"La Mirada",
    "sg:classifiers":[
        {
            "category":"Landmark",
            "subcategory":"Historic",
            "type":"Public Place"
        }
    ],
    "sg:phone":"+1 714 521 7812",
    "sg:postcode":"90638",
    "sg:province":"CA",
    "sg:tags":[
        "building",
        "historical"
    ],
    "wof:name":"Neff Historical House",
    "wof:placetype":"venue"
},
  "geometry": {"coordinates":[-118.027,33.899101],"type":"Point"}
}