{
  "type": "Feature",
  "properties": {
    "iso:country":"US",
    "sg:address":"26691 Oak Trail Rd",
    "sg:city":"Valley Center",
    "sg:classifiers":[
        {
            "category":"Building & Trades",
            "subcategory":"Construction",
            "type":"Services"
        }
    ],
    "sg:phone":"+1 760 749 9426",
    "sg:postcode":"92082",
    "sg:province":"CA",
    "sg:tags":[
        "designer",
        "dealer",
        "pool",
        "swimming"
    ],
    "wof:name":"San Juan Fiberglass Pools",
    "wof:placetype":"venue"
},
  "geometry": {"coordinates":[-116.942716,33.192906],"type":"Point"}
}