{
  "type": "Feature",
  "properties": {
    "addr:full":"19909 Valley Blvd Walnut CA 91789",
    "addr:housenumber":"19909",
    "addr:postcode":"91789",
    "addr:street":"Valley Blvd",
    "iso:country":"US",
    "sg:address":"19909 Valley Blvd",
    "sg:city":"Walnut",
    "sg:classifiers":[
        {
            "category":"Retail",
            "subcategory":"Auto Repair",
            "type":"Services"
        }
    ],
    "sg:phone":"+1 909 594 0066",
    "sg:postcode":"91789",
    "sg:province":"CA",
    "sg:tags":[
        "body",
        "automobile",
        "painting"
    ],
    "wof:name":"Coach & Colors",
    "wof:placetype":"venue"
},
  "geometry": {"coordinates":[-117.86769200000001,34.004866],"type":"Point"}
}