{
  "type": "Feature",
  "properties": {
    "iso:country":"US",
    "sg:address":"19909 Valley Blvd",
    "sg:city":"Walnut",
    "sg:classifiers":[
        {
            "category":"Retail",
            "subcategory":"Auto Repair",
            "type":"Services"
        }
    ],
    "sg:phone":"+1 909 594 0066",
    "sg:postcode":"91789",
    "sg:province":"CA",
    "sg:tags":[
        "body",
        "automobile",
        "painting"
    ],
    "wof:name":"Coach & Colors",
    "wof:placetype":"venue"
},
  "geometry": {"coordinates":[-117.867692,34.004866],"type":"Point"}
}