{
  "type": "Feature",
  "properties": {
    "addr:full":"1851 Lexington Avenue San Mateo CA 94402",
    "addr:housenumber":"1851",
    "addr:postcode":"94402",
    "addr:street":"Lexington Avenue",
    "iso:country":"US",
    "sg:address":"1851 Lexington Avenue",
    "sg:city":"San Mateo",
    "sg:classifiers":[
        {
            "category":"Social Services",
            "subcategory":"Child Care",
            "type":"Services"
        },
        {
            "category":"Sports & Exercise",
            "subcategory":"Sports Center",
            "type":"Entertainment"
        }
    ],
    "sg:phone":"+1 650 341 4251",
    "sg:postcode":"94402",
    "sg:province":"CA",
    "sg:tags":[
        "amateur",
        "day",
        "team"
    ],
    "wof:name":"Highlands Recreation District",
    "wof:placetype":"venue"
},
  "geometry": {"coordinates":[-122.346609,37.518756],"type":"Point"}
}