{
  "type": "Feature",
  "properties": {
    "addr:full":"29613 Mission Blvd Hayward CA 94544",
    "addr:housenumber":"29613",
    "addr:postcode":"94544",
    "addr:street":"Mission Blvd",
    "iso:country":"US",
    "sg:address":"29613 Mission Blvd",
    "sg:city":"Hayward",
    "sg:classifiers":[
        {
            "category":"Professional",
            "subcategory":"Business Services",
            "type":"Services"
        }
    ],
    "sg:phone":"+1 510 888 1398",
    "sg:postcode":"94544",
    "sg:province":"CA",
    "sg:tags":[
        "hardware"
    ],
    "wof:name":"Laundromat J & J",
    "wof:placetype":"venue"
},
  "geometry": {"coordinates":[-122.04774500000001,37.630396],"type":"Point"}
}