{
  "type": "Feature",
  "properties": {
    "iso:country":"US",
    "sg:address":"221 Lathrop Way",
    "sg:city":"Sacramento",
    "sg:classifiers":[
        {
            "category":"Professional",
            "subcategory":"Computer Services",
            "type":"Services"
        }
    ],
    "sg:phone":"+1 408 367 6666",
    "sg:postcode":"95815",
    "sg:province":"CA",
    "sg:tags":[
        "internet"
    ],
    "wof:name":"Metromedia Fiber Network",
    "wof:placetype":"venue"
},
  "geometry": {"coordinates":[-121.45930799999999,38.597276],"type":"Point"}
}