{
  "type": "Feature",
  "properties": {
    "addr:full":"4515 W Adams Blvd Los Angeles CA 90016",
    "addr:housenumber":"4515",
    "addr:postcode":"90016",
    "addr:street":"W Adams Blvd",
    "iso:country":"US",
    "sg:address":"4515 W Adams Blvd",
    "sg:city":"Los Angeles",
    "sg:classifiers":[
        {
            "category":"Manufacturing",
            "subcategory":"Wood Products",
            "type":"Manufacturing & Wholesale Goods"
        }
    ],
    "sg:phone":"+1 323 731 6789",
    "sg:postcode":"90016",
    "sg:province":"CA",
    "wof:name":"Juhasz Inc",
    "wof:placetype":"venue"
},
  "geometry": {"coordinates":[-118.33929000000001,34.032637],"type":"Point"}
}