{
  "type": "Feature",
  "properties": {
    "iso:country":"US",
    "sg:address":"829 N Salsipuedes St",
    "sg:city":"Santa Barbara",
    "sg:classifiers":[
        {
            "category":"Shopping",
            "subcategory":"Clothing, Apparel, & Fashions",
            "type":"Retail Goods"
        }
    ],
    "sg:phone":"+1 805 899 4733",
    "sg:postcode":"93103",
    "sg:province":"CA",
    "sg:tags":[
        "baby",
        "accessory"
    ],
    "wof:name":"Mama Gaia",
    "wof:placetype":"venue"
},
  "geometry": {"coordinates":[-119.693561,34.426552],"type":"Point"}
}