{
  "type": "Feature",
  "properties": {
    "iso:country":"US",
    "sg:address":"3450 Auto Plaza Way",
    "sg:city":"Tracy",
    "sg:classifiers":[
        {
            "category":"Autos & Motor Vehicles",
            "subcategory":"Automobile Sales",
            "type":"Retail Goods"
        }
    ],
    "sg:phone":"+1 877 369 7470",
    "sg:postcode":"95304",
    "sg:province":"CA",
    "sg:tags":[
        "car"
    ],
    "sg:website":"http://www.tracyhonda.com",
    "wof:name":"Tracy Honda",
    "wof:placetype":"venue"
},
  "geometry": {"coordinates":[-121.46416499999999,37.761646],"type":"Point"}
}