{
  "type": "Feature",
  "properties": {
    "addr:full":"3040 Montgomery Rd Red Bluff CA 96080",
    "addr:housenumber":"3040",
    "addr:postcode":"96080",
    "addr:street":"Montgomery Rd",
    "iso:country":"US",
    "sg:address":"3040 Montgomery Rd",
    "sg:city":"Red Bluff",
    "sg:classifiers":[
        {
            "category":"Shopping",
            "subcategory":"Bicycles & Sporting Goods",
            "type":"Retail Goods"
        }
    ],
    "sg:phone":"+1 530 529 9910",
    "sg:postcode":"96080",
    "sg:province":"CA",
    "sg:tags":[
        "equipment",
        "archery",
        "supply"
    ],
    "wof:name":"Raglin 3-D's",
    "wof:placetype":"venue"
},
  "geometry": {"coordinates":[-122.223427,40.141919],"type":"Point"}
}