{
  "type": "Feature",
  "properties": {
    "addr:full":"3186 Adams Ave San Diego CA 92116",
    "addr:housenumber":"3186",
    "addr:postcode":"92116",
    "addr:street":"Adams Ave",
    "iso:country":"US",
    "sg:address":"3186 Adams Ave",
    "sg:city":"San Diego",
    "sg:classifiers":[
        {
            "category":"Shopping",
            "subcategory":"Used Merchandise",
            "type":"Retail Goods"
        }
    ],
    "sg:phone":"+1 619 528 0026",
    "sg:postcode":"92116",
    "sg:province":"CA",
    "sg:tags":[
        "shop",
        "thrift"
    ],
    "wof:name":"Mission Outreach Thrift Store",
    "wof:placetype":"venue"
},
  "geometry": {"coordinates":[-117.125513,32.763454],"type":"Point"}
}