{
  "type": "Feature",
  "properties": {
    "addr:full":"8606 Commerce Ave San Diego CA 92121",
    "addr:housenumber":"8606",
    "addr:postcode":"92121",
    "addr:street":"Commerce Ave",
    "iso:country":"US",
    "sg:address":"8606 Commerce Ave",
    "sg:city":"San Diego",
    "sg:classifiers":[
        {
            "category":"Wholesale",
            "subcategory":"Machinery & Supplies",
            "type":"Manufacturing & Wholesale Goods"
        },
        {
            "category":"Wholesale",
            "subcategory":"Electrical",
            "type":"Manufacturing & Wholesale Goods"
        }
    ],
    "sg:phone":"+1 858 689 0333",
    "sg:postcode":"92121",
    "sg:province":"CA",
    "sg:tags":[
        "equipment",
        "industrial",
        "electronic"
    ],
    "wof:name":"Hi Tech Sources",
    "wof:placetype":"venue"
},
  "geometry": {"coordinates":[-117.167736,32.881279],"type":"Point"}
}