{
  "type": "Feature",
  "properties": {
    "iso:country":"US",
    "sg:address":"3417 W Slauson Ave",
    "sg:city":"Los Angeles",
    "sg:classifiers":[
        {
            "category":"Wholesale",
            "subcategory":"Machinery & Supplies",
            "type":"Manufacturing & Wholesale Goods"
        }
    ],
    "sg:phone":"+1 323 294 2600",
    "sg:postcode":"90043",
    "sg:province":"CA",
    "sg:tags":[
        "dyer",
        "cleaners"
    ],
    "wof:name":"Hi-Tech Cleaners 4",
    "wof:placetype":"venue"
},
  "geometry": {"coordinates":[-118.332094,33.989075],"type":"Point"}
}