{
  "type": "Feature",
  "properties": {
    "iso:country":"US",
    "sg:address":"4175 Adams Ave",
    "sg:city":"San Diego",
    "sg:classifiers":[
        {
            "category":"Personal",
            "subcategory":"Skin Care",
            "type":"Services"
        }
    ],
    "sg:phone":"+1 858 344 4641",
    "sg:postcode":"92116",
    "sg:province":"CA",
    "wof:name":"The Brow Bar at Clip Art Salon",
    "wof:placetype":"venue"
},
  "geometry": {"coordinates":[-117.10538,32.763235],"type":"Point"}
}