{
  "type": "Feature",
  "properties": {
    "iso:country":"US",
    "sg:address":"3021 Cll Juarez",
    "sg:city":"San Clemente",
    "sg:classifiers":[
        {
            "category":"Shopping",
            "type":"Retail Goods"
        }
    ],
    "sg:phone":"+1 949 366 0783",
    "sg:postcode":"92673",
    "sg:province":"CA",
    "sg:tags":[
        "plaque"
    ],
    "wof:name":"In His Image",
    "wof:placetype":"venue"
},
  "geometry": {"coordinates":[-117.640528,33.451911],"type":"Point"}
}