{
  "type": "Feature",
  "properties": {
    "addr:full":"10441 S Vermont Ave Los Angeles CA 90044",
    "addr:housenumber":"10441",
    "addr:postcode":"90044",
    "addr:street":"S Vermont Ave",
    "iso:country":"US",
    "sg:address":"10441 S Vermont Ave",
    "sg:city":"Los Angeles",
    "sg:classifiers":[
        {
            "category":"Social Services",
            "subcategory":"Child Care",
            "type":"Services"
        }
    ],
    "sg:phone":"+1 323 757 1225",
    "sg:postcode":"90044",
    "sg:province":"CA",
    "sg:tags":[
        "elementary",
        "kindergarten",
        "school",
        "academic"
    ],
    "wof:name":"L A Urban League Headstart State",
    "wof:placetype":"venue"
},
  "geometry": {"coordinates":[-118.292,33.941502],"type":"Point"}
}