{
  "type": "Feature",
  "properties": {
    "iso:country":"US",
    "sg:address":"4 Dorman Ave",
    "sg:city":"San Francisco",
    "sg:classifiers":[
        {
            "category":"Professional",
            "subcategory":"Advertising",
            "type":"Services"
        }
    ],
    "sg:phone":"+1 415 648 7200",
    "sg:postcode":"94124",
    "sg:province":"CA",
    "sg:tags":[
        "mailing",
        "shipping"
    ],
    "sg:website":"www.clymerdirect.com",
    "wof:name":"Clymer Direct",
    "wof:placetype":"venue"
},
  "geometry": {"coordinates":[-122.404366,37.739338],"type":"Point"}
}