{
  "type": "Feature",
  "properties": {
    "iso:country":"US",
    "sg:address":"3425 Cam Largo",
    "sg:city":"Carlsbad",
    "sg:classifiers":[
        {
            "category":"Communications",
            "subcategory":"Film & Video Production",
            "type":"Services"
        }
    ],
    "sg:phone":"+1 760 436 0193",
    "sg:postcode":"92009",
    "sg:province":"CA",
    "sg:tags":[
        "motion",
        "picture",
        "studio",
        "producer"
    ],
    "wof:name":"Odonata Studio",
    "wof:placetype":"venue"
},
  "geometry": {"coordinates":[-117.23513,33.063912],"type":"Point"}
}