{
  "type": "Feature",
  "properties": {
    "addr:full":"1405 Market Ln Dixon CA 95620",
    "addr:housenumber":"1405",
    "addr:postcode":"95620",
    "addr:street":"Market Ln",
    "iso:country":"US",
    "sg:address":"1405 Market Ln",
    "sg:city":"Dixon",
    "sg:classifiers":[
        {
            "category":"Autos & Motor Vehicles",
            "subcategory":"Auto Supplies",
            "type":"Retail Goods"
        },
        {
            "category":"Wholesale",
            "subcategory":"Auto Parts",
            "type":"Manufacturing & Wholesale Goods"
        }
    ],
    "sg:phone":"+1 707 693 1200",
    "sg:postcode":"95620",
    "sg:province":"CA",
    "sg:tags":[
        "body",
        "automobile",
        "truck",
        "equipment",
        "accessory"
    ],
    "sg:website":"http://www.oreillyauto.com?utm_source=yellowpages&utm_medium=iyp&utm_campaign=3533",
    "wof:name":"Kragen O'ReillyAuto Parts",
    "wof:placetype":"venue"
},
  "geometry": {"coordinates":[-121.84105,38.455442],"type":"Point"}
}