{
  "type": "Feature",
  "properties": {
    "iso:country":"US",
    "sg:address":"1209 Solano Ave",
    "sg:city":"Albany",
    "sg:classifiers":[
        {
            "category":"Manufacturing",
            "subcategory":"Printing",
            "type":"Manufacturing & Wholesale Goods"
        }
    ],
    "sg:phone":"+1 510 526 3388",
    "sg:postcode":"94706",
    "sg:province":"CA",
    "sg:tags":[
        "publisher",
        "guide"
    ],
    "sg:website":"www.nevadacityca.com",
    "wof:name":"Bay Sports Publishing",
    "wof:placetype":"venue"
},
  "geometry": {"coordinates":[-122.295739,37.890513],"type":"Point"}
}