{
  "type": "Feature",
  "properties": {
    "addr:full":"1048 E Avenue K J Lancaster CA 93535",
    "addr:housenumber":"1048",
    "addr:postcode":"93535",
    "addr:street":"E Avenue K J",
    "iso:country":"US",
    "sg:address":"1048 E Avenue K J",
    "sg:city":"Lancaster",
    "sg:classifiers":[
        {
            "category":"Personal",
            "subcategory":"Beauty Salon",
            "type":"Services"
        }
    ],
    "sg:phone":"+1 661 942 6160",
    "sg:postcode":"93535",
    "sg:province":"CA",
    "wof:name":"Cuts N More",
    "wof:placetype":"venue"
},
  "geometry": {"coordinates":[-118.111315,34.675011],"type":"Point"}
}