{
  "type": "Feature",
  "properties": {
    "addr:full":"7575 Skyline Dr San Diego CA 92114",
    "addr:housenumber":"7575",
    "addr:postcode":"92114",
    "addr:street":"Skyline Dr",
    "iso:country":"US",
    "sg:address":"7575 Skyline Dr",
    "sg:city":"San Diego",
    "sg:classifiers":[
        {
            "category":"Organizations",
            "subcategory":"Religious Organization",
            "type":"Services"
        }
    ],
    "sg:phone":"+1 619 267 2720",
    "sg:postcode":"92114",
    "sg:province":"CA",
    "sg:tags":[
        "church"
    ],
    "wof:name":"Good Samaritan Church Of Sd",
    "wof:placetype":"venue"
},
  "geometry": {"coordinates":[-117.030851,32.702479],"type":"Point"}
}