{
  "type": "Feature",
  "properties": {
    "addr:full":"1177 Norwegian Ave Modesto CA 95350",
    "addr:housenumber":"1177",
    "addr:postcode":"ca 95350",
    "addr:street":"Norwegian Ave",
    "iso:country":"US",
    "sg:address":"1177 Norwegian Ave",
    "sg:city":"Modesto",
    "sg:classifiers":[
        {
            "category":"Wholesale",
            "subcategory":"Auto Parts",
            "type":"Manufacturing & Wholesale Goods"
        }
    ],
    "sg:phone":"+1 209 521 6155",
    "sg:postcode":"95350",
    "sg:province":"CA",
    "wof:name":"Cosgrove Racing and Wholesale",
    "wof:placetype":"venue"
},
  "geometry": {"coordinates":[-120.977003,37.671102],"type":"Point"}
}