{
  "type": "Feature",
  "properties": {
    "addr:full":"13263 Ventura Blvd Ste 6 Studio City CA 91604",
    "addr:housenumber":"13263",
    "addr:postcode":"91604",
    "addr:street":"Ventura Blvd Ste",
    "iso:country":"US",
    "sg:address":"13263 Ventura Blvd Ste 6",
    "sg:city":"Studio City",
    "sg:classifiers":[
        {
            "category":"Professional",
            "subcategory":"Lawyer & Legal Services",
            "type":"Services"
        }
    ],
    "sg:phone":"+1 818 997 6666",
    "sg:postcode":"91604",
    "sg:province":"CA",
    "sg:tags":[
        "divorce",
        "law",
        "family"
    ],
    "wof:name":"California Divorce Council",
    "wof:placetype":"venue"
},
  "geometry": {"coordinates":[-118.421997,34.1465],"type":"Point"}
}