{
  "type": "Feature",
  "properties": {
    "addr:full":"7740 Hollywood Blvd West Hollywood CA 90046",
    "addr:housenumber":"7740",
    "addr:postcode":"90046",
    "addr:street":"Hollywood Blvd",
    "iso:country":"US",
    "sg:address":"7740 Hollywood Blvd",
    "sg:city":"West Hollywood",
    "sg:classifiers":[
        {
            "category":"Wholesale",
            "subcategory":"Groceries",
            "type":"Manufacturing & Wholesale Goods"
        }
    ],
    "sg:phone":"+1 323 654 8776",
    "sg:postcode":"90046",
    "sg:province":"CA",
    "sg:tags":[
        "delicatessen"
    ],
    "wof:name":"Svetlana Deli",
    "wof:placetype":"venue"
},
  "geometry": {"coordinates":[-118.35767,34.101604],"type":"Point"}
}