{
  "type": "Feature",
  "properties": {
    "addr:full":"83810 Vin Deo Cir Indio CA 92201",
    "addr:postcode":"83810;92201",
    "addr:street":"Deo Cir",
    "iso:country":"US",
    "sg:address":"83810 Vin Deo Cir",
    "sg:city":"Indio",
    "sg:classifiers":[
        {
            "category":"Professional",
            "type":"Services"
        }
    ],
    "sg:phone":"+1 760 775 2295",
    "sg:postcode":"92201",
    "sg:province":"CA",
    "sg:tags":[
        "arts",
        "artist"
    ],
    "wof:name":"John Weidenhamer Artist",
    "wof:placetype":"venue"
},
  "geometry": {"coordinates":[-116.20247000000001,33.716911],"type":"Point"}
}