{
  "type": "Feature",
  "properties": {
    "addr:full":"10531 Humbolt Street Los Alamitos CA 90720",
    "addr:housenumber":"10531",
    "addr:postcode":"90720",
    "addr:street":"Humbolt Street",
    "iso:country":"US",
    "sg:address":"10531 Humbolt Street",
    "sg:city":"Los Alamitos",
    "sg:classifiers":[
        {
            "category":"Professional",
            "subcategory":"Computer Services",
            "type":"Services"
        }
    ],
    "sg:phone":"+1 714 369 8197",
    "sg:postcode":"90720",
    "sg:province":"CA",
    "sg:tags":[
        "repair"
    ],
    "sg:website":"www.shiftcs.com",
    "wof:name":"Shift Computer Services",
    "wof:placetype":"venue"
},
  "geometry": {"coordinates":[-118.065821,33.808913],"type":"Point"}
}