{
  "type": "Feature",
  "properties": {
    "iso:country":"US",
    "sg:address":"309 Drake Ave",
    "sg:city":"Sausalito",
    "sg:classifiers":[
        {
            "category":"Personal",
            "subcategory":"Beauty Salon",
            "type":"Services"
        }
    ],
    "sg:phone":"+1 415 331 6753",
    "sg:postcode":"94965",
    "sg:province":"CA",
    "wof:name":"Debz",
    "wof:placetype":"venue"
},
  "geometry": {"coordinates":[-122.509018,37.869176],"type":"Point"}
}