{
  "type": "Feature",
  "properties": {
    "addr:full":"215 Williams Ave Red Bluff CA 96080",
    "addr:housenumber":"215",
    "addr:postcode":"96080",
    "addr:street":"Williams Ave",
    "iso:country":"US",
    "sg:address":"215 Williams Ave",
    "sg:city":"Red Bluff",
    "sg:classifiers":[
        {
            "category":"Building & Trades",
            "subcategory":"Plumbing",
            "type":"Services"
        }
    ],
    "sg:phone":"+1 530 529 0948",
    "sg:postcode":"96080",
    "sg:province":"CA",
    "sg:tags":[
        "plumbing",
        "contractor"
    ],
    "wof:name":"Roach's Plumbing",
    "wof:placetype":"venue"
},
  "geometry": {"coordinates":[-122.216436,40.180233],"type":"Point"}
}