{
  "type": "Feature",
  "properties": {
    "addr:full":"165 41st St Oakland CA 94611",
    "addr:housenumber":"165",
    "addr:postcode":"94611",
    "addr:street":"41St St",
    "iso:country":"US",
    "sg:address":"165 41st St",
    "sg:city":"Oakland",
    "sg:classifiers":[
        {
            "category":"Restaurant",
            "type":"Food & Drink"
        }
    ],
    "sg:postcode":"94611",
    "sg:province":"CA",
    "wof:name":"Suruki's",
    "wof:placetype":"venue"
},
  "geometry": {"coordinates":[-122.25299800000001,37.8265],"type":"Point"}
}