{
  "type": "Feature",
  "properties": {
    "iso:country":"US",
    "sg:address":"1392 Whittingham Dr",
    "sg:city":"Tracy",
    "sg:classifiers":[
        {
            "category":"Home & Garden",
            "subcategory":"Building Materials",
            "type":"Retail Goods"
        }
    ],
    "sg:phone":"+1 209 830 6227",
    "sg:postcode":"95377",
    "sg:province":"CA",
    "wof:name":"Universal Glassworks",
    "wof:placetype":"venue"
},
  "geometry": {"coordinates":[-121.441942,37.703489],"type":"Point"}
}