{
  "type": "Feature",
  "properties": {
    "iso:country":"US",
    "sg:address":"6 Mclaren",
    "sg:city":"Irvine",
    "sg:classifiers":[
        {
            "category":"Manufacturing",
            "subcategory":"Glass & Minerals",
            "type":"Manufacturing & Wholesale Goods"
        }
    ],
    "sg:phone":"+1 949 215 5800",
    "sg:postcode":"92618",
    "sg:province":"CA",
    "sg:tags":[
        "plate",
        "shape",
        "glass-wholesale",
        "window",
        "special",
        "circle",
        "glass-auto",
        "manufacturer"
    ],
    "wof:name":"Z Glass",
    "wof:placetype":"venue"
},
  "geometry": {"coordinates":[-117.71901699999999,33.633869],"type":"Point"}
}