{
  "type": "Feature",
  "properties": {
    "addr:full":"421 Old Chittenden Rd Watsonville CA 95076",
    "addr:housenumber":"421",
    "addr:postcode":"95076",
    "addr:street":"Old Chittenden Rd",
    "iso:country":"US",
    "sg:address":"421 Old Chittenden Rd",
    "sg:city":"Watsonville",
    "sg:classifiers":[
        {
            "category":"Farming",
            "subcategory":"Orchard",
            "type":"Manufacturing & Wholesale Goods"
        }
    ],
    "sg:phone":"+1 831 726 3118",
    "sg:postcode":"95076",
    "sg:province":"CA",
    "sg:tags":[
        "fruit",
        "tree"
    ],
    "wof:name":"Lattimore Rentals",
    "wof:placetype":"venue"
},
  "geometry": {"coordinates":[-121.60842100000001,36.903088],"type":"Point"}
}