{
  "type": "Feature",
  "properties": {
    "addr:full":"704 E Bidwell St Folsom CA 95630",
    "addr:housenumber":"704",
    "addr:postcode":"95630",
    "addr:street":"E Bidwell St",
    "iso:country":"US",
    "sg:address":"704 E Bidwell St",
    "sg:city":"Folsom",
    "sg:classifiers":[
        {
            "category":"Retail",
            "subcategory":"Laundry & Dry Cleaning",
            "type":"Services"
        }
    ],
    "sg:phone":"+1 916 983 1020",
    "sg:postcode":"95630",
    "sg:province":"CA",
    "sg:tags":[
        "cleaners"
    ],
    "sg:website":"www.1800dryclean.com",
    "wof:name":"One 800 Dry Clean",
    "wof:placetype":"venue"
},
  "geometry": {"coordinates":[-121.15433299999999,38.669398],"type":"Point"}
}