{
  "type": "Feature",
  "properties": {
    "addr:full":"333 Jones St San Francisco CA 94102",
    "addr:housenumber":"333",
    "addr:postcode":"94102",
    "addr:street":"Jones St",
    "iso:country":"US",
    "sg:address":"333 Jones St",
    "sg:city":"San Francisco",
    "sg:classifiers":[
        {
            "category":"Retail",
            "subcategory":"Auto Repair",
            "type":"Services"
        }
    ],
    "sg:phone":"+1 415 292 6619",
    "sg:postcode":"94102",
    "sg:province":"CA",
    "sg:tags":[
        "repairing",
        "automobile"
    ],
    "wof:name":"Cooper & Robinon Automotive",
    "wof:placetype":"venue"
},
  "geometry": {"coordinates":[-122.41272499999999,37.784136],"type":"Point"}
}