{
  "type": "Feature",
  "properties": {
    "addr:full":"25500 Rancho Niguel Rd Laguna Niguel CA 92677",
    "addr:housenumber":"25500",
    "addr:postcode":"92677",
    "addr:street":"Rancho Niguel Rd",
    "iso:country":"US",
    "sg:address":"25500 Rancho Niguel Rd",
    "sg:city":"Laguna Niguel",
    "sg:classifiers":[
        {
            "category":"Health Services",
            "subcategory":"Doctor",
            "type":"Services"
        }
    ],
    "sg:phone":"+1 949 425 0005",
    "sg:postcode":"92677",
    "sg:province":"CA",
    "sg:tags":[
        "dentist"
    ],
    "wof:name":"Laura Immel-Sprague Inc",
    "wof:placetype":"venue"
},
  "geometry": {"coordinates":[-117.68817300000001,33.554649],"type":"Point"}
}