{
  "type": "Feature",
  "properties": {
    "addr:full":"200 S Western Ave Los Angeles CA 90004",
    "addr:housenumber":"200",
    "addr:postcode":"90004",
    "addr:street":"S Western Ave",
    "iso:country":"US",
    "sg:address":"200 S Western Ave",
    "sg:city":"Los Angeles",
    "sg:classifiers":[
        {
            "category":"Wholesale",
            "subcategory":"Sporting Goods",
            "type":"Manufacturing & Wholesale Goods"
        }
    ],
    "sg:phone":"+1 213 388 6655",
    "sg:postcode":"90004",
    "sg:province":"CA",
    "sg:tags":[
        "martial",
        "arts",
        "equipment"
    ],
    "wof:name":"Kens Trading Co Inc",
    "wof:placetype":"venue"
},
  "geometry": {"coordinates":[-118.30911399999999,34.068961],"type":"Point"}
}