{
  "type": "Feature",
  "properties": {
    "iso:country":"US",
    "sg:address":"2680 Tarmac Rd",
    "sg:city":"Redding",
    "sg:classifiers":[
        {
            "category":"Freight",
            "type":"Transportation"
        }
    ],
    "sg:phone":"+1 530 221 8500",
    "sg:postcode":"96003",
    "sg:province":"CA",
    "sg:tags":[
        "commercial",
        "storage",
        "general"
    ],
    "wof:name":"AAA Mini & Rv Storage",
    "wof:placetype":"venue"
},
  "geometry": {"coordinates":[-122.320054,40.571054],"type":"Point"}
}