{
  "type": "Feature",
  "properties": {
    "iso:country":"US",
    "sg:address":"4815 E Kings Canyon Rd",
    "sg:city":"Fresno",
    "sg:classifiers":[
        {
            "category":"Autos & Motor Vehicles",
            "subcategory":"Auto Supplies",
            "type":"Retail Goods"
        },
        {
            "category":"Retail",
            "subcategory":"Auto Repair",
            "type":"Services"
        }
    ],
    "sg:phone":"+1 559 458 0793",
    "sg:postcode":"93727",
    "sg:province":"CA",
    "sg:tags":[
        "lube",
        "oil"
    ],
    "wof:name":"Shell Rapid Lube.",
    "wof:placetype":"venue"
},
  "geometry": {"coordinates":[-119.73573,36.736],"type":"Point"}
}