{
  "type": "Feature",
  "properties": {
    "addr:full":"14673 San Pablo Ave Richmond CA 94806",
    "addr:housenumber":"14673",
    "addr:postcode":"94806",
    "addr:street":"San Pablo Ave",
    "iso:country":"US",
    "sg:address":"14673 San Pablo Ave",
    "sg:city":"Richmond",
    "sg:classifiers":[
        {
            "category":"Retail",
            "subcategory":"Auto Repair",
            "type":"Services"
        }
    ],
    "sg:phone":"+1 510 234 0687",
    "sg:postcode":"94806",
    "sg:province":"CA",
    "sg:tags":[
        "automobile",
        "electric"
    ],
    "wof:name":"D C Auto Repair",
    "wof:placetype":"venue"
},
  "geometry": {"coordinates":[-122.34373600000001,37.969537],"type":"Point"}
}