{
  "type": "Feature",
  "properties": {
    "addr:full":"10435 Monterey Rd Gilroy CA 95020",
    "addr:housenumber":"10435",
    "addr:postcode":"95020",
    "addr:street":"Monterey Rd",
    "iso:country":"US",
    "sg:address":"10435 Monterey Rd",
    "sg:city":"Gilroy",
    "sg:classifiers":[
        {
            "category":"Sports & Exercise",
            "subcategory":"Swimming Pool",
            "type":"Entertainment"
        }
    ],
    "sg:phone":"+1 408 847 8182",
    "sg:postcode":"95020",
    "sg:province":"CA",
    "wof:name":"J Sheets Pool Contruction",
    "wof:placetype":"venue"
},
  "geometry": {"coordinates":[-121.590318,37.917215],"type":"Point"}
}