{
  "type": "Feature",
  "properties": {
    "iso:country":"US",
    "sg:address":"1 De Frst",
    "sg:city":"Irvine",
    "sg:classifiers":[
        {
            "category":"Real Estate",
            "subcategory":"Architect",
            "type":"Services"
        }
    ],
    "sg:phone":"+1 949 262 1102",
    "sg:postcode":"92620",
    "sg:province":"CA",
    "wof:name":"Bosz Architecture",
    "wof:placetype":"venue"
},
  "geometry": {"coordinates":[-117.764999,33.701302],"type":"Point"}
}