{
  "type": "Feature",
  "properties": {
    "iso:country":"US",
    "sg:address":"633 Folsom St",
    "sg:city":"San Francisco",
    "sg:classifiers":[
        {
            "category":"Restaurant",
            "type":"Food & Drink"
        }
    ],
    "sg:phone":"+1 415 974 6468",
    "sg:postcode":"94107",
    "sg:province":"CA",
    "wof:name":"Mint Cafe",
    "wof:placetype":"venue"
},
  "geometry": {"coordinates":[-122.397092,37.785281],"type":"Point"}
}