{
  "type": "Feature",
  "properties": {
    "addr:full":"1419 Banks Ave Napa CA 94559",
    "addr:housenumber":"1419",
    "addr:postcode":"94559",
    "addr:street":"Banks Ave",
    "iso:country":"US",
    "sg:address":"1419 Banks Ave",
    "sg:city":"Napa",
    "sg:classifiers":[
        {
            "category":"Building & Trades",
            "subcategory":"Construction",
            "type":"Services"
        }
    ],
    "sg:phone":"+1 707 258 1163",
    "sg:postcode":"94559",
    "sg:province":"CA",
    "sg:tags":[
        "road",
        "contractor"
    ],
    "wof:name":"J D Hurd Construction",
    "wof:placetype":"venue"
},
  "geometry": {"coordinates":[-122.272594,38.305943],"type":"Point"}
}