{
  "type": "Feature",
  "properties": {
    "iso:country":"US",
    "sg:address":"614 Pennsylvania Ave",
    "sg:city":"San Diego",
    "sg:classifiers":[
        {
            "category":"Wholesale",
            "subcategory":"Medical Equipment & Supplies",
            "type":"Manufacturing & Wholesale Goods"
        },
        {
            "category":"Wholesale",
            "subcategory":"Chemicals & Plastics",
            "type":"Manufacturing & Wholesale Goods"
        }
    ],
    "sg:phone":"+1 619 296 9945",
    "sg:postcode":"92103",
    "sg:province":"CA",
    "sg:tags":[
        "physician",
        "surgeon"
    ],
    "wof:name":"Accurate Chemical & Scientific",
    "wof:placetype":"venue"
},
  "geometry": {"coordinates":[-117.159113,32.745219],"type":"Point"}
}