{
  "type": "Feature",
  "properties": {
    "iso:country":"US",
    "sg:address":"5800 Hamner Ave",
    "sg:city":"Mira Loma",
    "sg:classifiers":[
        {
            "category":"Home & Garden",
            "subcategory":"Mobile Homes",
            "type":"Retail Goods"
        }
    ],
    "sg:phone":"+1 909 944 7444",
    "sg:postcode":"91752",
    "sg:province":"CA",
    "wof:name":"Classic Homes",
    "wof:placetype":"venue"
},
  "geometry": {"coordinates":[-117.558285,33.983247],"type":"Point"}
}