{
  "type": "Feature",
  "properties": {
    "iso:country":"US",
    "sg:address":"1248 E Artesia Blvd",
    "sg:city":"Long Beach",
    "sg:classifiers":[
        {
            "category":"Personal",
            "subcategory":"Barber",
            "type":"Services"
        }
    ],
    "sg:phone":"+1 562 256 9988",
    "sg:postcode":"90805",
    "sg:province":"CA",
    "wof:name":"Ortiz Barber Shop",
    "wof:placetype":"venue"
},
  "geometry": {"coordinates":[-118.176592,33.874535],"type":"Point"}
}