{
  "type": "Feature",
  "properties": {
    "addr:full":"920 Allen Ave Glendale CA 91201",
    "addr:housenumber":"920",
    "addr:postcode":"91201",
    "addr:street":"Allen Ave",
    "iso:country":"US",
    "sg:address":"920 Allen Ave",
    "sg:city":"Glendale",
    "sg:classifiers":[
        {
            "category":"Communications",
            "subcategory":"Film & Video Production",
            "type":"Services"
        }
    ],
    "sg:phone":"+1 818 242 3839",
    "sg:postcode":"91201",
    "sg:province":"CA",
    "sg:tags":[
        "motion",
        "picture",
        "studio",
        "producer"
    ],
    "sg:website":"www.icsfilm.com",
    "wof:name":"Ics Svc",
    "wof:placetype":"venue"
},
  "geometry": {"coordinates":[-118.29653500000001,34.17096],"type":"Point"}
}