{
  "type": "Feature",
  "properties": {
    "iso:country":"US",
    "sg:address":"2001 Broadway",
    "sg:city":"Oakland",
    "sg:classifiers":[
        {
            "category":"Organizations",
            "subcategory":"Labor Organization",
            "type":"Services"
        }
    ],
    "sg:phone":"+1 510 844 1170",
    "sg:postcode":"94612",
    "sg:province":"CA",
    "wof:name":"AFSCME3299",
    "wof:placetype":"venue"
},
  "geometry": {"coordinates":[-122.268227,37.809052],"type":"Point"}
}