{
  "type": "Feature",
  "properties": {
    "iso:country":"US",
    "sg:address":"1611 Crenshaw Blvd",
    "sg:city":"Torrance",
    "sg:classifiers":[
        {
            "category":"Building & Trades",
            "subcategory":"Cleaning & Sanitation",
            "type":"Services"
        }
    ],
    "sg:phone":"+1 310 532 6625",
    "sg:postcode":"90501",
    "sg:province":"CA",
    "sg:tags":[
        "window"
    ],
    "wof:name":"Ediorans Window Washing",
    "wof:placetype":"venue"
},
  "geometry": {"coordinates":[-118.32865700000001,33.83199],"type":"Point"}
}