{
  "type": "Feature",
  "properties": {
    "addr:full":"1689 Arden Way Ste 1065 Sacramento CA 95815",
    "addr:housenumber":"1689",
    "addr:postcode":"95815",
    "addr:street":"Arden Way Ste 1065",
    "iso:country":"US",
    "sg:address":"1689 Arden Way Ste 1065",
    "sg:city":"Sacramento",
    "sg:classifiers":[
        {
            "category":"Restaurant",
            "type":"Food & Drink"
        }
    ],
    "sg:phone":"+1 916 649 3839",
    "sg:postcode":"95815",
    "sg:province":"CA",
    "wof:name":"Fresh Choice Restaurants",
    "wof:placetype":"venue"
},
  "geometry": {"coordinates":[-121.425003,38.598999],"type":"Point"}
}