{
  "type": "Feature",
  "properties": {
    "addr:full":"1785 W Arrow Rte Upland CA 91786",
    "addr:housenumber":"1785",
    "addr:postcode":"91786",
    "addr:street":"W Arrow Rte",
    "iso:country":"US",
    "sg:address":"1785 W Arrow Rte",
    "sg:city":"Upland",
    "sg:classifiers":[
        {
            "category":"Autos & Motor Vehicles",
            "subcategory":"Auto Supplies",
            "type":"Retail Goods"
        },
        {
            "category":"Retail",
            "subcategory":"Auto Repair",
            "type":"Services"
        }
    ],
    "sg:phone":"+1 909 931 0351",
    "sg:postcode":"91786",
    "sg:province":"CA",
    "sg:tags":[
        "lettering",
        "automobile",
        "body",
        "truck",
        "painting",
        "repairing"
    ],
    "wof:name":"Upland Collision Craft",
    "wof:placetype":"venue"
},
  "geometry": {"coordinates":[-117.685514,34.099617],"type":"Point"}
}