{
  "type": "Feature",
  "properties": {
    "addr:full":"18701 Sherman Way Ste 4 Reseda CA 91335",
    "addr:housenumber":"18701",
    "addr:postcode":"91335",
    "addr:street":"Sherman Way Ste 4",
    "iso:country":"US",
    "sg:address":"18701 Sherman Way Ste 4",
    "sg:city":"Reseda",
    "sg:classifiers":[
        {
            "category":"Health Services",
            "subcategory":"Chiropractor",
            "type":"Services"
        }
    ],
    "sg:phone":"+1 818 609 7844",
    "sg:postcode":"91335",
    "sg:province":"CA",
    "sg:tags":[
        "chiropractic"
    ],
    "wof:name":"Shayam, Payam",
    "wof:placetype":"venue"
},
  "geometry": {"coordinates":[-118.54039,34.20118],"type":"Point"}
}