{
  "type": "Feature",
  "properties": {
    "iso:country":"US",
    "sg:address":"5801 Power Inn Rd",
    "sg:city":"Sacramento",
    "sg:classifiers":[
        {
            "category":"Home & Garden",
            "subcategory":"Carpets & Floor Coverings",
            "type":"Retail Goods"
        }
    ],
    "sg:phone":"+1 916 381 7777",
    "sg:postcode":"95824",
    "sg:province":"CA",
    "wof:name":"Floor Depot",
    "wof:placetype":"venue"
},
  "geometry": {"coordinates":[-121.40911800000001,38.521313],"type":"Point"}
}