{
  "type": "Feature",
  "properties": {
    "addr:full":"7952 Collins Ln La Palma CA 90623",
    "addr:housenumber":"7952",
    "addr:postcode":"90623",
    "addr:street":"Collins Ln",
    "iso:country":"US",
    "sg:address":"7952 Collins Ln",
    "sg:city":"La Palma",
    "sg:classifiers":[
        {
            "category":"Professional",
            "subcategory":"Business Services",
            "type":"Services"
        }
    ],
    "sg:phone":"+1 714 670 7642",
    "sg:postcode":"90623",
    "sg:province":"CA",
    "sg:tags":[
        "interior",
        "consultant",
        "design",
        "decorator"
    ],
    "wof:name":"Marinos Designs",
    "wof:placetype":"venue"
},
  "geometry": {"coordinates":[-118.04058000000001,33.847121],"type":"Point"}
}