{
  "type": "Feature",
  "properties": {
    "iso:country":"US",
    "sg:address":"12440 Firestone Blvd",
    "sg:city":"Norwalk",
    "sg:classifiers":[
        {
            "category":"Education",
            "subcategory":"College",
            "type":"Public Place"
        }
    ],
    "sg:phone":"+1 562 929 2300",
    "sg:postcode":"90650",
    "sg:province":"CA",
    "sg:tags":[
        "academic",
        "school"
    ],
    "wof:name":"Dia University",
    "wof:placetype":"venue"
},
  "geometry": {"coordinates":[-118.067517,33.905045],"type":"Point"}
}