{
  "type": "Feature",
  "properties": {
    "addr:full":"411 Helen Dr Millbrae CA 94030",
    "addr:housenumber":"411",
    "addr:postcode":"94030",
    "addr:street":"Helen Dr",
    "iso:country":"US",
    "sg:address":"411 Helen Dr",
    "sg:city":"Millbrae",
    "sg:classifiers":[
        {
            "category":"Professional",
            "type":"Services"
        }
    ],
    "sg:phone":"+1 650 697 8298",
    "sg:postcode":"94030",
    "sg:province":"CA",
    "wof:name":"Airworthy Products Inc",
    "wof:placetype":"venue"
},
  "geometry": {"coordinates":[-122.40245299999999,37.603357],"type":"Point"}
}