{
  "type": "Feature",
  "properties": {
    "addr:full":"3052 E Richert Ave Fresno CA 93726",
    "addr:housenumber":"3052",
    "addr:postcode":"93726",
    "addr:street":"E Richert Ave",
    "iso:country":"US",
    "sg:address":"3052 E Richert Ave",
    "sg:city":"Fresno",
    "sg:classifiers":[
        {
            "category":"Building & Trades",
            "subcategory":"Pest Control",
            "type":"Services"
        }
    ],
    "sg:phone":"+1 559 230 2473",
    "sg:postcode":"93726",
    "sg:province":"CA",
    "wof:name":"Early Bird Pest Control",
    "wof:placetype":"venue"
},
  "geometry": {"coordinates":[-119.775265,36.796909],"type":"Point"}
}