{
  "type": "Feature",
  "properties": {
    "iso:country":"US",
    "sg:address":"9201 W Sunset Blvd",
    "sg:city":"Los Angeles",
    "sg:classifiers":[
        {
            "category":"Health Services",
            "subcategory":"Doctor",
            "type":"Services"
        }
    ],
    "sg:phone":"+1 310 247 1445",
    "sg:postcode":"90069",
    "sg:province":"CA",
    "sg:tags":[
        "dentist"
    ],
    "wof:name":"John W Gerace DDS",
    "wof:placetype":"venue"
},
  "geometry": {"coordinates":[-118.393689,34.089724],"type":"Point"}
}