{
  "type": "Feature",
  "properties": {
    "addr:full":"21241 Ventura Blvd Woodland Hills CA 91364",
    "addr:housenumber":"21241",
    "addr:postcode":"91364",
    "addr:street":"Ventura Blvd",
    "iso:country":"US",
    "sg:address":"21241 Ventura Blvd",
    "sg:city":"Woodland Hills",
    "sg:classifiers":[
        {
            "category":"Insurance",
            "subcategory":"Insurance Agent",
            "type":"Services"
        }
    ],
    "sg:phone":"+1 818 887 1700",
    "sg:postcode":"91364",
    "sg:province":"CA",
    "sg:website":"www.farmersdm.com",
    "wof:name":"Farmers Insurance Group",
    "wof:placetype":"venue"
},
  "geometry": {"coordinates":[-118.59522699999999,34.167466],"type":"Point"}
}