{
  "type": "Feature",
  "properties": {
    "addr:full":"2057 Divisadero St. San Francisco CA 94115",
    "addr:housenumber":"2057",
    "addr:postcode":"94115",
    "addr:street":"Divisadero St.",
    "iso:country":"US",
    "sg:address":"2057 Divisadero St.",
    "sg:city":"San Francisco",
    "sg:classifiers":[
        {
            "category":"Health Services",
            "subcategory":"Clinic",
            "type":"Services"
        }
    ],
    "sg:phone":"+1 415 431 2900",
    "sg:postcode":"94115",
    "sg:province":"CA",
    "sg:tags":[
        "counseling",
        "mental"
    ],
    "sg:website":"www.communityhealingcenters.org/",
    "wof:name":"Amelia Pryor, PHD MFT",
    "wof:placetype":"venue"
},
  "geometry": {"coordinates":[-122.44093100000001,37.788824],"type":"Point"}
}