{
  "type": "Feature",
  "properties": {
    "addr:full":"120 S Topanga Canyon Blvd Ste 110 Topanga CA 90290",
    "addr:housenumber":"120",
    "addr:postcode":"90290",
    "addr:street":"S Topanga Canyon Blvd Ste 110",
    "iso:country":"US",
    "sg:address":"120 S Topanga Canyon Blvd Ste 110",
    "sg:city":"Topanga",
    "sg:classifiers":[
        {
            "category":"Food & Beverages",
            "subcategory":"Cheese",
            "type":"Retail Goods"
        },
        {
            "category":"Food & Beverages",
            "subcategory":"Groceries & Convenience Stores",
            "type":"Retail Goods"
        }
    ],
    "sg:phone":"+1 310 455 4200",
    "sg:postcode":"90290",
    "sg:province":"CA",
    "sg:tags":[
        "shop"
    ],
    "sg:website":"www.canyongourmet.com",
    "wof:name":"Canyon Gourmet",
    "wof:placetype":"venue"
},
  "geometry": {"coordinates":[-118.604196,34.089342],"type":"Point"}
}