{
  "type": "Feature",
  "properties": {
    "iso:country":"US",
    "sg:address":"337 W Colorado Blvd",
    "sg:city":"Pasadena",
    "sg:classifiers":[
        {
            "category":"Autos & Motor Vehicles",
            "subcategory":"Automobile Sales",
            "type":"Retail Goods"
        }
    ],
    "sg:phone":"+1 626 449 0770",
    "sg:postcode":"91105",
    "sg:province":"CA",
    "sg:tags":[
        "car",
        "dealer"
    ],
    "wof:name":"Rusnak-Pasadena",
    "wof:placetype":"venue"
},
  "geometry": {"coordinates":[-118.15642200000001,34.145828],"type":"Point"}
}