{
  "type": "Feature",
  "properties": {
    "iso:country":"US",
    "sg:address":"500 12th St",
    "sg:city":"Oakland",
    "sg:classifiers":[
        {
            "category":"Professional",
            "subcategory":"Management & Consulting",
            "type":"Services"
        }
    ],
    "sg:phone":"+1 510 452 1200",
    "sg:postcode":"94607",
    "sg:province":"CA",
    "sg:tags":[
        "association"
    ],
    "wof:name":"Pacific Maritime Assn",
    "wof:placetype":"venue"
},
  "geometry": {"coordinates":[-122.27211,37.802965],"type":"Point"}
}