{
  "type": "Feature",
  "properties": {
    "addr:full":"1820 Monterey St Fresno CA 93721",
    "addr:housenumber":"1820",
    "addr:postcode":"93721",
    "addr:street":"Monterey St",
    "iso:country":"US",
    "sg:address":"1820 Monterey St",
    "sg:city":"Fresno",
    "sg:classifiers":[
        {
            "category":"Building & Trades",
            "subcategory":"Construction",
            "type":"Services"
        }
    ],
    "sg:phone":"+1 559 268 8877",
    "sg:postcode":"93721",
    "sg:province":"CA",
    "sg:tags":[
        "woodworker"
    ],
    "wof:name":"Anderson Woodworking",
    "wof:placetype":"venue"
},
  "geometry": {"coordinates":[-119.783699,36.725993],"type":"Point"}
}