{
  "type": "Feature",
  "properties": {
    "iso:country":"US",
    "sg:address":"448 W Market Street",
    "sg:city":"San Diego",
    "sg:classifiers":[
        {
            "category":"Shopping",
            "subcategory":"Antiques",
            "type":"Retail Goods"
        }
    ],
    "sg:phone":"+1 619 239 6255",
    "sg:postcode":"92101",
    "sg:province":"CA",
    "wof:name":"Antiques Grab Bag",
    "wof:placetype":"venue"
},
  "geometry": {"coordinates":[-117.16679000000001,32.711629],"type":"Point"}
}