{
  "type": "Feature",
  "properties": {
    "addr:full":"2121 E Coast Hwy Ste 200 Corona del Mar CA 92625",
    "addr:housenumber":"2121",
    "addr:postcode":"92625",
    "addr:street":"E Coast Hwy Ste 200",
    "iso:country":"US",
    "sg:address":"2121 E Coast Hwy Ste 200",
    "sg:city":"Corona del Mar",
    "sg:classifiers":[
        {
            "category":"Health Services",
            "subcategory":"Clinic",
            "type":"Services"
        }
    ],
    "sg:phone":"+1 949 600 4668",
    "sg:postcode":"92625",
    "sg:province":"CA",
    "sg:tags":[
        "medical"
    ],
    "wof:name":"ClearSight Laser Center",
    "wof:placetype":"venue"
},
  "geometry": {"coordinates":[-117.876586,33.605501],"type":"Point"}
}