{
  "type": "Feature",
  "properties": {
    "addr:full":"16046 Cambrian Dr San Leandro CA 94578",
    "addr:housenumber":"16046",
    "addr:postcode":"94578",
    "addr:street":"Cambrian Dr",
    "iso:country":"US",
    "sg:address":"16046 Cambrian Dr",
    "sg:city":"San Leandro",
    "sg:classifiers":[
        {
            "category":"Professional",
            "subcategory":"Computer Services",
            "type":"Services"
        }
    ],
    "sg:phone":"+1 510 278 0300",
    "sg:postcode":"94578",
    "sg:province":"CA",
    "wof:name":"Cathey Moses & Assoc",
    "wof:placetype":"venue"
},
  "geometry": {"coordinates":[-122.108327,37.707576],"type":"Point"}
}