{
  "type": "Feature",
  "properties": {
    "addr:full":"8550 Hollywood Blvd West Hollywood CA 90069",
    "addr:housenumber":"8550",
    "addr:postcode":"90069",
    "addr:street":"Hollywood Blvd",
    "iso:country":"US",
    "sg:address":"8550 Hollywood Blvd",
    "sg:city":"West Hollywood",
    "sg:classifiers":[
        {
            "category":"Home & Garden",
            "subcategory":"Home Furnishings",
            "type":"Retail Goods"
        }
    ],
    "sg:phone":"+1 310 659 2519",
    "sg:postcode":"90069",
    "sg:province":"CA",
    "sg:tags":[
        "housewares"
    ],
    "wof:name":"Nad Accessories",
    "wof:placetype":"venue"
},
  "geometry": {"coordinates":[-118.37527799999999,34.098062],"type":"Point"}
}