{
  "type": "Feature",
  "properties": {
    "addr:full":"255 N Forbes St Lakeport CA 95453",
    "addr:housenumber":"255",
    "addr:postcode":"95453",
    "addr:street":"N Forbes St",
    "iso:country":"US",
    "sg:address":"255 N Forbes St",
    "sg:city":"Lakeport",
    "sg:classifiers":[
        {
            "category":"Government",
            "subcategory":"Office",
            "type":"Public Place"
        }
    ],
    "sg:phone":"+1 707 263 2580",
    "sg:postcode":"95453",
    "sg:province":"CA",
    "wof:name":"Lake County Administrative Dir",
    "wof:placetype":"venue"
},
  "geometry": {"coordinates":[-122.91620899999999,39.043491],"type":"Point"}
}