{
  "type": "Feature",
  "properties": {
    "iso:country":"US",
    "sg:address":"1019 E Acequia Ave",
    "sg:city":"Visalia",
    "sg:classifiers":[
        {
            "category":"Retail",
            "subcategory":"Auto Repair",
            "type":"Services"
        }
    ],
    "sg:phone":"+1 559 733 2000",
    "sg:postcode":"93292",
    "sg:province":"CA",
    "sg:tags":[
        "wrecker"
    ],
    "wof:name":"Extreme Towing",
    "wof:placetype":"venue"
},
  "geometry": {"coordinates":[-119.28152799999999,36.329221],"type":"Point"}
}