{
  "type": "Feature",
  "properties": {
    "addr:full":"545 H St Chula Vista CA 91910",
    "addr:housenumber":"545",
    "addr:postcode":"91910",
    "addr:street":"H St",
    "iso:country":"US",
    "sg:address":"545 H St",
    "sg:city":"Chula Vista",
    "sg:classifiers":[
        {
            "category":"Utilities",
            "subcategory":"Mobile Phone",
            "type":"Services"
        }
    ],
    "sg:phone":"+1 619 691 1485",
    "sg:postcode":"91910",
    "sg:province":"CA",
    "sg:tags":[
        "telephone",
        "cellular"
    ],
    "wof:name":"New Generation Intl",
    "wof:placetype":"venue"
},
  "geometry": {"coordinates":[-117.085599,32.632111],"type":"Point"}
}