{
  "type": "Feature",
  "properties": {
    "iso:country":"US",
    "sg:address":"818 Martin St",
    "sg:city":"Monterey",
    "sg:classifiers":[
        {
            "category":"Education",
            "subcategory":"Special Training",
            "type":"Public Place"
        }
    ],
    "sg:phone":"+1 831 372 2056",
    "sg:postcode":"93940",
    "sg:province":"CA",
    "sg:tags":[
        "instruction",
        "music"
    ],
    "wof:name":"Flute Studio-Ursi Frei",
    "wof:placetype":"venue"
},
  "geometry": {"coordinates":[-121.902494,36.592911],"type":"Point"}
}