{
  "type": "Feature",
  "properties": {
    "iso:country":"US",
    "sg:address":"4049 Ball Rd",
    "sg:city":"Cypress",
    "sg:phone":"+1 714 828 0600",
    "sg:postcode":"90630",
    "sg:province":"CA",
    "wof:name":"Nakabayashi Joy DR",
    "wof:placetype":"venue"
},
  "geometry": {"coordinates":[-118.063075,33.81761],"type":"Point"}
}