{
  "type": "Feature",
  "properties": {
    "addr:full":"44545 Date Ave Lancaster CA 93534",
    "addr:housenumber":"44545",
    "addr:postcode":"93534",
    "addr:street":"Date Ave",
    "iso:country":"US",
    "sg:address":"44545 Date Ave",
    "sg:city":"Lancaster",
    "sg:classifiers":[
        {
            "category":"Manufacturing",
            "subcategory":"Motor Vehicles & Parts",
            "type":"Manufacturing & Wholesale Goods"
        }
    ],
    "sg:phone":"+1 661 940 1748",
    "sg:postcode":"93534",
    "sg:province":"CA",
    "sg:tags":[
        "motorcycle"
    ],
    "wof:name":"Citsvagon Werks",
    "wof:placetype":"venue"
},
  "geometry": {"coordinates":[-118.139775,34.691424],"type":"Point"}
}