{
  "type": "Feature",
  "properties": {
    "addr:full":"821 E Anaheim St Long Beach CA 90813",
    "addr:housenumber":"821",
    "addr:postcode":"90813",
    "addr:street":"E Anaheim St",
    "iso:country":"US",
    "sg:address":"821 E Anaheim St",
    "sg:city":"Long Beach",
    "sg:classifiers":[
        {
            "category":"Professional",
            "subcategory":"Business Services",
            "type":"Services"
        }
    ],
    "sg:phone":"+1 562 612 4604",
    "sg:postcode":"90813",
    "sg:province":"CA",
    "sg:tags":[
        "delivery",
        "courier"
    ],
    "wof:name":"California Express",
    "wof:placetype":"venue"
},
  "geometry": {"coordinates":[-118.182497,33.782621],"type":"Point"}
}