{
  "type": "Feature",
  "properties": {
    "addr:full":"4230 S Figueroa St Los Angeles CA 90037",
    "addr:housenumber":"4230",
    "addr:postcode":"90037",
    "addr:street":"S Figueroa St",
    "iso:country":"US",
    "sg:address":"4230 S Figueroa St",
    "sg:city":"Los Angeles",
    "sg:classifiers":[
        {
            "category":"Building & Trades",
            "subcategory":"Plumbing",
            "type":"Services"
        }
    ],
    "sg:phone":"+1 323 846 8391",
    "sg:postcode":"90037",
    "sg:province":"CA",
    "sg:tags":[
        "plumbing",
        "contractor"
    ],
    "wof:name":"Sealey's Plumbing",
    "wof:placetype":"venue"
},
  "geometry": {"coordinates":[-118.282639,34.006493],"type":"Point"}
}