{
  "type": "Feature",
  "properties": {
    "addr:full":"1400 Doolittle Dr San Leandro CA 94577",
    "addr:housenumber":"1400",
    "addr:postcode":"94577",
    "addr:street":"Doolittle Dr",
    "iso:country":"US",
    "sg:address":"1400 Doolittle Dr",
    "sg:city":"San Leandro",
    "sg:classifiers":[
        {
            "category":"Autos & Motor Vehicles",
            "subcategory":"Automobile Sales",
            "type":"Retail Goods"
        }
    ],
    "sg:phone":"+1 510 638 4790",
    "sg:postcode":"94577",
    "sg:province":"CA",
    "sg:tags":[
        "automotive"
    ],
    "wof:name":"Hertz Rent A Car",
    "wof:placetype":"venue"
},
  "geometry": {"coordinates":[-122.185997,37.7131],"type":"Point"}
}