{
  "type": "Feature",
  "properties": {
    "addr:full":"641 Mimosa Ave Vista CA 92081",
    "addr:housenumber":"641",
    "addr:postcode":"92081",
    "addr:street":"Mimosa Ave",
    "iso:country":"US",
    "sg:address":"641 Mimosa Ave",
    "sg:city":"Vista",
    "sg:classifiers":[
        {
            "category":"Building & Trades",
            "subcategory":"Landscaping Services",
            "type":"Services"
        }
    ],
    "sg:phone":"+1 760 945 9494",
    "sg:postcode":"92081",
    "sg:province":"CA",
    "sg:tags":[
        "landscape",
        "contractor"
    ],
    "wof:name":"Knight Landscape",
    "wof:placetype":"venue"
},
  "geometry": {"coordinates":[-117.215261,33.156439],"type":"Point"}
}