{
  "type": "Feature",
  "properties": {
    "iso:country":"US",
    "sg:address":"3890 Valley Centre Dr",
    "sg:city":"San Diego",
    "sg:classifiers":[
        {
            "category":"Insurance",
            "subcategory":"Insurance Agent",
            "type":"Services"
        }
    ],
    "sg:phone":"+1 858 259 4205",
    "sg:postcode":"92130",
    "sg:province":"CA",
    "wof:name":"Farmers Insurance Group",
    "wof:placetype":"venue"
},
  "geometry": {"coordinates":[-117.232969,32.937799],"type":"Point"}
}