{
  "type": "Feature",
  "properties": {
    "iso:country":"US",
    "sg:address":"1200 S Woodland St",
    "sg:city":"Visalia",
    "sg:classifiers":[
        {
            "category":"Professional",
            "subcategory":"Lawyer & Legal Services",
            "type":"Services"
        }
    ],
    "sg:phone":"+1 559 635 3040",
    "sg:postcode":"93277",
    "sg:province":"CA",
    "sg:tags":[
        "attorney"
    ],
    "wof:name":"Advocates Long & Romaine",
    "wof:placetype":"venue"
},
  "geometry": {"coordinates":[-119.318366,36.319265],"type":"Point"}
}