{
  "type": "Feature",
  "properties": {
    "iso:country":"US",
    "sg:address":"12121 Cherrylee Dr",
    "sg:city":"El Monte",
    "sg:classifiers":[
        {
            "category":"Shopping",
            "subcategory":"Party Supplies",
            "type":"Retail Goods"
        },
        {
            "category":"Personal",
            "type":"Services"
        }
    ],
    "sg:phone":"+1 626 350 3049",
    "sg:postcode":"91732",
    "sg:province":"CA",
    "sg:tags":[
        "planning",
        "event"
    ],
    "wof:name":"Ponies For Parties",
    "wof:placetype":"venue"
},
  "geometry": {"coordinates":[-118.953553,34.180886],"type":"Point"}
}