{
  "type": "Feature",
  "properties": {
    "iso:country":"US",
    "sg:address":"254 S B St",
    "sg:city":"San Mateo",
    "sg:classifiers":[
        {
            "category":"Restaurant",
            "type":"Food & Drink"
        }
    ],
    "sg:menulink":"http://www.allmenus.com/ca/san-mateo/158211-las-americas/menu/",
    "sg:phone":"+1 650 340 1327",
    "sg:postcode":"94401",
    "sg:province":"CA",
    "sg:tags":[
        "caribbean"
    ],
    "wof:name":"Las Americas",
    "wof:placetype":"venue"
},
  "geometry": {"coordinates":[-122.32273499999999,37.565922],"type":"Point"}
}