{
  "type": "Feature",
  "properties": {
    "addr:full":"1225 Wall Street Los Angeles CA 90015",
    "addr:housenumber":"1225",
    "addr:postcode":"90015",
    "addr:street":"Wall Street",
    "iso:country":"US",
    "sg:address":"1225 Wall Street",
    "sg:city":"Los Angeles",
    "sg:classifiers":[
        {
            "category":"Shopping",
            "subcategory":"Clothing, Apparel, & Fashions",
            "type":"Retail Goods"
        }
    ],
    "sg:phone":"+1 213 749 2341",
    "sg:postcode":"90015",
    "sg:province":"CA",
    "sg:tags":[
        "children's",
        "clothing"
    ],
    "wof:name":"Ceci Kids",
    "wof:placetype":"venue"
},
  "geometry": {"coordinates":[-118.25576599999999,34.034266],"type":"Point"}
}