{
  "type": "Feature",
  "properties": {
    "addr:full":"4404 Stern Ave Sherman Oaks CA 91423",
    "addr:housenumber":"4404",
    "addr:postcode":"91423",
    "addr:street":"Stern Ave",
    "iso:country":"US",
    "sg:address":"4404 Stern Ave",
    "sg:city":"Sherman Oaks",
    "sg:classifiers":[
        {
            "category":"Personal",
            "subcategory":"Beauty Salon",
            "type":"Services"
        }
    ],
    "sg:phone":"+1 323 877 1926",
    "sg:postcode":"91423",
    "sg:province":"CA",
    "sg:tags":[
        "spa"
    ],
    "sg:website":"www.permalocs.com",
    "wof:name":"PeRMaLoCS Healthy Hair Extensions",
    "wof:placetype":"venue"
},
  "geometry": {"coordinates":[-118.435243,34.150547],"type":"Point"}
}