{
  "type": "Feature",
  "properties": {
    "iso:country":"US",
    "sg:address":"750 Cll Naranjo",
    "sg:city":"Thousand Oaks",
    "sg:classifiers":[
        {
            "category":"Food & Beverages",
            "subcategory":"Meat & Fish",
            "type":"Retail Goods"
        }
    ],
    "sg:phone":"+1 805 498 6000",
    "sg:postcode":"91360",
    "sg:province":"CA",
    "sg:tags":[
        "cutting"
    ],
    "wof:name":"Newbury Park Meat Market",
    "wof:placetype":"venue"
},
  "geometry": {"coordinates":[-118.86492800000001,34.216333],"type":"Point"}
}