{
  "type": "Feature",
  "properties": {
    "iso:country":"US",
    "sg:address":"1654 India St",
    "sg:city":"San Diego",
    "sg:classifiers":[
        {
            "category":"Wholesale",
            "subcategory":"Construction Materials",
            "type":"Manufacturing & Wholesale Goods"
        }
    ],
    "sg:phone":"+1 619 232 7381",
    "sg:postcode":"92101",
    "sg:province":"CA",
    "sg:tags":[
        "gates"
    ],
    "wof:name":"Ironside Co",
    "wof:placetype":"venue"
},
  "geometry": {"coordinates":[-117.168364,32.722414],"type":"Point"}
}