{
  "type": "Feature",
  "properties": {
    "iso:country":"US",
    "sg:address":"406 N. San Mateo Drive Ste# B",
    "sg:city":"San Mateo",
    "sg:classifiers":[
        {
            "category":"Health Services",
            "subcategory":"Dentist",
            "type":"Services"
        }
    ],
    "sg:phone":"+1 650 342 8874",
    "sg:postcode":"94401",
    "sg:province":"CA",
    "wof:name":"Bay Star Dental",
    "wof:placetype":"venue"
},
  "geometry": {"coordinates":[-122.33279,37.572454],"type":"Point"}
}