{
  "type": "Feature",
  "properties": {
    "addr:full":"22290 Cass Ave Woodland Hills CA 91364",
    "addr:housenumber":"22290",
    "addr:postcode":"91364",
    "addr:street":"Cass Ave",
    "iso:country":"US",
    "sg:address":"22290 Cass Ave",
    "sg:city":"Woodland Hills",
    "sg:classifiers":[
        {
            "category":"Professional",
            "subcategory":"Art Services",
            "type":"Services"
        }
    ],
    "sg:phone":"+1 818 888 2328",
    "sg:postcode":"91364",
    "sg:province":"CA",
    "sg:tags":[
        "graphic",
        "designer"
    ],
    "wof:name":"Advance Design Concepts",
    "wof:placetype":"venue"
},
  "geometry": {"coordinates":[-118.611789,34.16283],"type":"Point"}
}