{
  "type": "Feature",
  "properties": {
    "iso:country":"US",
    "sg:address":"180 N Mirage Ave",
    "sg:city":"Lindsay",
    "sg:classifiers":[
        {
            "category":"Professional",
            "subcategory":"Management & Consulting",
            "type":"Services"
        }
    ],
    "sg:phone":"+1 559 562 0000",
    "sg:postcode":"93247",
    "sg:province":"CA",
    "sg:tags":[
        "telecommunication"
    ],
    "wof:name":"Verizon",
    "wof:placetype":"venue"
},
  "geometry": {"coordinates":[-119.088876,36.203264],"type":"Point"}
}