{
  "type": "Feature",
  "properties": {
    "iso:country":"US",
    "sg:address":"6742 Grimes-Arbuckle Rd",
    "sg:city":"Arbuckle",
    "sg:classifiers":[
        {
            "category":"Social Services",
            "subcategory":"Child Care",
            "type":"Services"
        }
    ],
    "sg:phone":"+1 530 476 2847",
    "sg:postcode":"95912",
    "sg:province":"CA",
    "wof:name":"Growing Children",
    "wof:placetype":"venue"
},
  "geometry": {"coordinates":[-122.026364,39.012878],"type":"Point"}
}