{
  "type": "Feature",
  "properties": {
    "addr:full":"25590 Avenue Stanford Valencia CA 91355",
    "addr:housenumber":"25590",
    "addr:postcode":"91355",
    "addr:street":"Avenue",
    "iso:country":"US",
    "sg:address":"25590 Avenue Stanford",
    "sg:city":"Valencia",
    "sg:classifiers":[
        {
            "category":"Retail",
            "subcategory":"Auto Repair",
            "type":"Services"
        }
    ],
    "sg:phone":"+1 661 244 6920",
    "sg:postcode":"91355",
    "sg:province":"CA",
    "sg:tags":[
        "body",
        "automobile",
        "painting",
        "repairing"
    ],
    "wof:name":"Telesis Collision Auto",
    "wof:placetype":"venue"
},
  "geometry": {"coordinates":[-118.58427500000001,34.431565],"type":"Point"}
}