{
  "type": "Feature",
  "properties": {
    "addr:full":"1565 W Ventura St Fillmore CA 93015",
    "addr:housenumber":"1565",
    "addr:postcode":"93015",
    "addr:street":"W Ventura St",
    "iso:country":"US",
    "sg:address":"1565 W Ventura St",
    "sg:city":"Fillmore",
    "sg:classifiers":[
        {
            "category":"Freight",
            "type":"Transportation"
        }
    ],
    "sg:phone":"+1 805 524 1104",
    "sg:postcode":"93015",
    "sg:province":"CA",
    "sg:tags":[
        "operator",
        "local",
        "trucking"
    ],
    "wof:name":"MMI Trucking",
    "wof:placetype":"venue"
},
  "geometry": {"coordinates":[-118.937124,34.393606],"type":"Point"}
}