{
  "type": "Feature",
  "properties": {
    "addr:full":"28404 Felix Valdez Ave Temecula CA 92590",
    "addr:housenumber":"28404",
    "addr:postcode":"92590",
    "addr:street":"Felix Valdez Ave",
    "iso:country":"US",
    "sg:address":"28404 Felix Valdez Ave",
    "sg:city":"Temecula",
    "sg:classifiers":[
        {
            "category":"Sports & Exercise",
            "subcategory":"Gym",
            "type":"Entertainment"
        }
    ],
    "sg:phone":"+1 951 699 9952",
    "sg:postcode":"92590",
    "sg:province":"CA",
    "sg:tags":[
        "club",
        "health",
        "studio",
        "gymnasium"
    ],
    "sg:website":"www.temeculafitness.com",
    "wof:name":"Club",
    "wof:placetype":"venue"
},
  "geometry": {"coordinates":[-117.155579,33.497423],"type":"Point"}
}