{
  "type": "Feature",
  "properties": {
    "iso:country":"US",
    "sg:address":"10956 Golden Hills Dr",
    "sg:city":"Yucaipa",
    "sg:classifiers":[
        {
            "category":"Professional",
            "subcategory":"Management & Consulting",
            "type":"Services"
        }
    ],
    "sg:phone":"+1 909 797 9340",
    "sg:postcode":"92399",
    "sg:province":"CA",
    "sg:tags":[
        "consultant",
        "business"
    ],
    "wof:name":"W & B Systems",
    "wof:placetype":"venue"
},
  "geometry": {"coordinates":[-117.043667,34.054625],"type":"Point"}
}