{
  "type": "Feature",
  "properties": {
    "addr:full":"7314 Marbrisa Ave Huntington Park CA 90255",
    "addr:housenumber":"7314",
    "addr:postcode":"90255",
    "addr:street":"Marbrisa Ave;Park",
    "iso:country":"US",
    "sg:address":"7314 Marbrisa Ave",
    "sg:city":"Huntington Park",
    "sg:classifiers":[
        {
            "category":"Wholesale",
            "subcategory":"Hardware",
            "type":"Manufacturing & Wholesale Goods"
        },
        {
            "category":"Professional",
            "subcategory":"Business Services",
            "type":"Services"
        }
    ],
    "sg:phone":"+1 323 587 7784",
    "sg:postcode":"90255",
    "sg:province":"CA",
    "sg:tags":[
        "plumbing",
        "water",
        "treatment"
    ],
    "wof:name":"Everlasting Health Products",
    "wof:placetype":"venue"
},
  "geometry": {"coordinates":[-118.231347,33.973132],"type":"Point"}
}