{
  "type": "Feature",
  "properties": {
    "addr:full":"1306 Montana Ave Santa Monica CA 90403",
    "addr:housenumber":"1306",
    "addr:postcode":"90403",
    "addr:street":"Montana Ave",
    "iso:country":"US",
    "sg:address":"1306 Montana Ave",
    "sg:city":"Santa Monica",
    "sg:classifiers":[
        {
            "category":"Shopping",
            "subcategory":"Clothing, Apparel, & Fashions",
            "type":"Retail Goods"
        }
    ],
    "sg:phone":"+1 310 451 2140",
    "sg:postcode":"90403",
    "sg:province":"CA",
    "wof:name":"Giselle",
    "wof:placetype":"venue"
},
  "geometry": {"coordinates":[-118.49563000000001,34.031716],"type":"Point"}
}