{
  "type": "Feature",
  "properties": {
    "addr:full":"162 S Polk St Lakeport CA 95453",
    "addr:housenumber":"162",
    "addr:postcode":"95453",
    "addr:street":"S Polk St",
    "iso:country":"US",
    "sg:address":"162 S Polk St",
    "sg:city":"Lakeport",
    "sg:classifiers":[
        {
            "category":"Building & Trades",
            "subcategory":"Construction",
            "type":"Services"
        }
    ],
    "sg:phone":"+1 707 263 6141",
    "sg:postcode":"95453",
    "sg:province":"CA",
    "sg:tags":[
        "roofing",
        "contractor"
    ],
    "wof:name":"Nichols Roofing",
    "wof:placetype":"venue"
},
  "geometry": {"coordinates":[-122.921646,39.04167],"type":"Point"}
}