{
  "type": "Feature",
  "properties": {
    "addr:full":"3260 Blume Dr Richmond CA 94806",
    "addr:postcode":"3260;94806",
    "addr:street":"Blume Dr",
    "iso:country":"US",
    "sg:address":"3260 Blume Dr",
    "sg:city":"Richmond",
    "sg:classifiers":[
        {
            "category":"Professional",
            "subcategory":"Lawyer & Legal Services",
            "type":"Services"
        }
    ],
    "sg:phone":"+1 510 758 5100",
    "sg:postcode":"94806",
    "sg:province":"CA",
    "sg:tags":[
        "attorney"
    ],
    "wof:name":"Richard H Bartke Law Offices",
    "wof:placetype":"venue"
},
  "geometry": {"coordinates":[-122.32083799999999,37.983906],"type":"Point"}
}