{
  "type": "Feature",
  "properties": {
    "addr:full":"50 Narcissa Drive Rancho Palos Verdes CA 90275",
    "addr:housenumber":"50",
    "addr:postcode":"90275",
    "addr:street":"Narcissa Drive",
    "iso:country":"US",
    "sg:address":"50 Narcissa Drive",
    "sg:city":"Rancho Palos Verdes",
    "sg:classifiers":[
        {
            "category":"Organizations",
            "subcategory":"Religious Organization",
            "type":"Services"
        }
    ],
    "sg:phone":"+1 310 541 4201",
    "sg:postcode":"90275",
    "sg:province":"CA",
    "sg:website":"www.ridetofly.com",
    "wof:name":"Ride To Fly",
    "wof:placetype":"venue"
},
  "geometry": {"coordinates":[-118.374745,33.748833],"type":"Point"}
}