{
  "type": "Feature",
  "properties": {
    "iso:country":"US",
    "sg:address":"8500 Steller Dr",
    "sg:city":"Culver City",
    "sg:classifiers":[
        {
            "category":"Wholesale",
            "subcategory":"Chemicals & Plastics",
            "type":"Manufacturing & Wholesale Goods"
        }
    ],
    "sg:phone":"+1 310 204 6159",
    "sg:postcode":"90232",
    "sg:province":"CA",
    "sg:tags":[
        "adhesive",
        "glue"
    ],
    "sg:website":"www.resinformulators.com",
    "wof:name":"E V Roberts & Assoc",
    "wof:placetype":"venue"
},
  "geometry": {"coordinates":[-118.37994,34.024647],"type":"Point"}
}