{
  "type": "Feature",
  "properties": {
    "addr:full":"611 Washington St Bakersfield CA 93307",
    "addr:housenumber":"611",
    "addr:postcode":"93307",
    "addr:street":"Washington St",
    "iso:country":"US",
    "sg:address":"611 Washington St",
    "sg:city":"Bakersfield",
    "sg:classifiers":[
        {
            "category":"Organizations",
            "subcategory":"Religious Organization",
            "type":"Services"
        }
    ],
    "sg:phone":"+1 661 366 5774",
    "sg:postcode":"93307",
    "sg:province":"CA",
    "sg:tags":[
        "church"
    ],
    "wof:name":"Jehovah's Witnesses",
    "wof:placetype":"venue"
},
  "geometry": {"coordinates":[-118.976303,35.364828],"type":"Point"}
}