{
  "type": "Feature",
  "properties": {
    "addr:full":"7065 Benson Ave San Diego CA 92114",
    "addr:housenumber":"7065",
    "addr:postcode":"92114",
    "addr:street":"Benson Ave",
    "iso:country":"US",
    "sg:address":"7065 Benson Ave",
    "sg:city":"San Diego",
    "sg:classifiers":[
        {
            "category":"Professional",
            "type":"Services"
        }
    ],
    "sg:phone":"+1 619 263 0656",
    "sg:postcode":"92114",
    "sg:province":"CA",
    "wof:name":"James Braggs",
    "wof:placetype":"venue"
},
  "geometry": {"coordinates":[-117.045526,32.704565],"type":"Point"}
}