{
  "type": "Feature",
  "properties": {
    "addr:full":"11856 Mississippi Ave Los Angeles CA 90025",
    "addr:housenumber":"11856",
    "addr:postcode":"90025",
    "addr:street":"Mississippi Ave",
    "iso:country":"US",
    "sg:address":"11856 Mississippi Ave",
    "sg:city":"Los Angeles",
    "sg:classifiers":[
        {
            "category":"Manufacturing",
            "subcategory":"Tools & Machinery",
            "type":"Manufacturing & Wholesale Goods"
        }
    ],
    "sg:phone":"+1 310 479 6770",
    "sg:postcode":"90025",
    "sg:province":"CA",
    "sg:tags":[
        "devices"
    ],
    "sg:website":"www.webstertesters.com",
    "wof:name":"Webster Instrument Inc",
    "wof:placetype":"venue"
},
  "geometry": {"coordinates":[-118.452478,34.033508],"type":"Point"}
}