{
  "type": "Feature",
  "properties": {
    "addr:full":"31 N 2nd Street Suite 300 San Jose CA 95113",
    "addr:housenumber":"31",
    "addr:postcode":"95113",
    "addr:street":"N 2Nd Street Suite 300",
    "iso:country":"US",
    "sg:address":"31 N 2nd Street Suite 300",
    "sg:city":"San Jose",
    "sg:classifiers":[
        {
            "category":"Professional",
            "subcategory":"Lawyer & Legal Services",
            "type":"Services"
        }
    ],
    "sg:phone":"+1 408 993 1120",
    "sg:postcode":"95113",
    "sg:province":"CA",
    "sg:tags":[
        "divorce",
        "law",
        "family"
    ],
    "sg:website":"www.kidlaw.com",
    "wof:name":"Schlepphorst & Emede, P.C.",
    "wof:placetype":"venue"
},
  "geometry": {"coordinates":[-121.889808,37.337112],"type":"Point"}
}