{
  "type": "Feature",
  "properties": {
    "addr:full":"1127 E Green St Pasadena CA 91105",
    "addr:housenumber":"1127",
    "addr:postcode":"91105",
    "addr:street":"E Green St",
    "iso:country":"US",
    "sg:address":"1127 E Green St",
    "sg:city":"Pasadena",
    "sg:classifiers":[
        {
            "category":"Building & Trades",
            "subcategory":"Construction",
            "type":"Services"
        }
    ],
    "sg:phone":"+1 626 584 1212",
    "sg:postcode":"91105",
    "sg:province":"CA",
    "sg:tags":[
        "commercial",
        "remodeling",
        "contractor"
    ],
    "wof:name":"Starlings Construction Company",
    "wof:placetype":"venue"
},
  "geometry": {"coordinates":[-118.12665,34.144668],"type":"Point"}
}