{
  "type": "Feature",
  "properties": {
    "addr:full":"44836 S Grimmer Blvd Fremont CA 94538",
    "addr:housenumber":"44836",
    "addr:postcode":"94538",
    "addr:street":"S Grimmer Blvd",
    "iso:country":"US",
    "sg:address":"44836 S Grimmer Blvd",
    "sg:city":"Fremont",
    "sg:classifiers":[
        {
            "category":"Home & Garden",
            "subcategory":"Furniture",
            "type":"Retail Goods"
        }
    ],
    "sg:phone":"+1 510 490 5556",
    "sg:postcode":"94538",
    "sg:province":"CA",
    "wof:name":"Samie's Furniture",
    "wof:placetype":"venue"
},
  "geometry": {"coordinates":[-121.947953,37.502841],"type":"Point"}
}