{
  "type": "Feature",
  "properties": {
    "iso:country":"US",
    "sg:address":"4698 Alvarado Canyon Rd",
    "sg:city":"San Diego",
    "sg:classifiers":[
        {
            "category":"Manufacturing",
            "subcategory":"Wood Products",
            "type":"Manufacturing & Wholesale Goods"
        }
    ],
    "sg:phone":"+1 619 286 0963",
    "sg:postcode":"92120",
    "sg:province":"CA",
    "sg:tags":[
        "mfg"
    ],
    "wof:name":"R L Neal Woodworking",
    "wof:placetype":"venue"
},
  "geometry": {"coordinates":[-117.097703,32.780087],"type":"Point"}
}