{
  "type": "Feature",
  "properties": {
    "addr:full":"6045 Rosedale Hwy Bakersfield CA 93308",
    "addr:housenumber":"6045",
    "addr:postcode":"93308",
    "addr:street":"Rosedale Hwy",
    "iso:country":"US",
    "sg:address":"6045 Rosedale Hwy",
    "sg:city":"Bakersfield",
    "sg:classifiers":[
        {
            "category":"Building & Trades",
            "subcategory":"Equipment Rental",
            "type":"Services"
        }
    ],
    "sg:phone":"+1 661 631 2900",
    "sg:postcode":"93308",
    "sg:province":"CA",
    "sg:tags":[
        "contractor"
    ],
    "sg:website":"www.unitedrentals.com",
    "wof:name":"United Rentals",
    "wof:placetype":"venue"
},
  "geometry": {"coordinates":[-119.0719,35.383265],"type":"Point"}
}