{
  "type": "Feature",
  "properties": {
    "iso:country":"US",
    "sg:address":"1586 Howe Avenue",
    "sg:city":"Sacramento",
    "sg:classifiers":[
        {
            "category":"Health Services",
            "subcategory":"Optometrist",
            "type":"Services"
        }
    ],
    "sg:phone":"+1 916 646 9155",
    "sg:postcode":"95825",
    "sg:province":"CA",
    "sg:website":"www.douglasclarkeod.com",
    "wof:name":"Clarke Douglas OD",
    "wof:placetype":"venue"
},
  "geometry": {"coordinates":[-121.415077,38.594738],"type":"Point"}
}