{
  "type": "Feature",
  "properties": {
    "addr:full":"3180 18th St 2nd Fl San Francisco CA 94110",
    "addr:housenumber":"3180",
    "addr:postcode":"94110",
    "addr:street":"18Th St",
    "iso:country":"US",
    "sg:address":"3180 18th St 2nd Fl",
    "sg:city":"San Francisco",
    "sg:classifiers":[
        {
            "category":"Community Center",
            "type":"Public Place"
        }
    ],
    "sg:phone":"+1 415 502 7223",
    "sg:postcode":"94110",
    "sg:province":"CA",
    "sg:tags":[
        "medical"
    ],
    "sg:website":"www.buprenorphine-doctors.com/ph...",
    "wof:name":"OBOT Buprenorphine Induction Clinic",
    "wof:placetype":"venue"
},
  "geometry": {"coordinates":[-122.414601,37.762132],"type":"Point"}
}