{
  "type": "Feature",
  "properties": {
    "iso:country":"US",
    "sg:address":"4112 S Main St",
    "sg:city":"Los Angeles",
    "sg:classifiers":[
        {
            "category":"Professional",
            "subcategory":"Business Services",
            "type":"Services"
        }
    ],
    "sg:phone":"+1 323 231 9553",
    "sg:postcode":"90037",
    "sg:province":"CA",
    "sg:tags":[
        "embroidery"
    ],
    "wof:name":"A & A Embroidery",
    "wof:placetype":"venue"
},
  "geometry": {"coordinates":[-118.273919,34.008446],"type":"Point"}
}