{
  "type": "Feature",
  "properties": {
    "addr:full":"2256 Santa Ana N Los Angeles CA 90059",
    "addr:housenumber":"2256",
    "addr:postcode":"90059",
    "addr:street":"Santa Ana N",
    "iso:country":"US",
    "sg:address":"2256 Santa Ana N",
    "sg:city":"Los Angeles",
    "sg:classifiers":[
        {
            "category":"Real Estate",
            "subcategory":"Real Estate Services",
            "type":"Services"
        }
    ],
    "sg:phone":"+1 323 566 5924",
    "sg:postcode":"90059",
    "sg:province":"CA",
    "sg:tags":[
        "management",
        "property"
    ],
    "wof:name":"The Lee Group Inc.",
    "wof:placetype":"venue"
},
  "geometry": {"coordinates":[-118.232658,33.935315],"type":"Point"}
}