{
  "type": "Feature",
  "properties": {
    "addr:full":"20433 Lander Dr Woodland Hills CA 91364",
    "addr:postcode":"20433;91364",
    "addr:street":"Lander Dr",
    "iso:country":"US",
    "sg:address":"20433 Lander Dr",
    "sg:city":"Woodland Hills",
    "sg:classifiers":[
        {
            "category":"Wholesale",
            "subcategory":"Non-durable Goods",
            "type":"Manufacturing & Wholesale Goods"
        }
    ],
    "sg:phone":"+1 818 346 3026",
    "sg:postcode":"91364",
    "sg:province":"CA",
    "wof:name":"Ls Distribution LLC",
    "wof:placetype":"venue"
},
  "geometry": {"coordinates":[-118.576801,34.155282],"type":"Point"}
}