{
  "type": "Feature",
  "properties": {
    "iso:country":"US",
    "sg:address":"2705 Lee Ave",
    "sg:city":"South El Monte",
    "sg:classifiers":[
        {
            "category":"Manufacturing",
            "subcategory":"Apparel",
            "type":"Manufacturing & Wholesale Goods"
        }
    ],
    "sg:phone":"+1 626 279 1628",
    "sg:postcode":"91733",
    "sg:province":"CA",
    "sg:tags":[
        "sewing",
        "contractor"
    ],
    "wof:name":"KTM Fashions",
    "wof:placetype":"venue"
},
  "geometry": {"coordinates":[-118.067362,34.061205],"type":"Point"}
}