{
  "type": "Feature",
  "properties": {
    "addr:full":"300 Amador Ave. San Bruno, Ca 94066",
    "wof:categories":[
        "education_and_religion:education=school"
    ],
    "wof:name":"Portola Elementary School",
    "wof:placetype":"venue"
},
  "geometry": {"coordinates":[-122.45251380024878,37.62403770074122],"type":"Point"}
}