{
  "type": "Feature",
  "properties": {
    "addr:full":"2456 Rio Linda Blvd Sacramento CA 95815",
    "addr:housenumber":"2456",
    "addr:postcode":"95815",
    "addr:street":"Rio Linda Blvd",
    "iso:country":"US",
    "sg:address":"2456 Rio Linda Blvd",
    "sg:city":"Sacramento",
    "sg:classifiers":[
        {
            "category":"Coffee & Tea",
            "type":"Food & Drink"
        }
    ],
    "sg:menulink":"http://www.allmenus.com/ca/sacramento/108889-starbucks-coffee/menu/",
    "sg:phone":"+1 916 925 2232",
    "sg:postcode":"95815",
    "sg:province":"CA",
    "sg:tags":[
        "american"
    ],
    "wof:name":"Starbucks Coffee",
    "wof:placetype":"venue"
},
  "geometry": {"coordinates":[-121.44945,38.611769],"type":"Point"}
}