{
  "type": "Feature",
  "properties": {
    "iso:country":"US",
    "sg:address":"4505 Woodmont Ct",
    "sg:city":"Fair Oaks",
    "sg:classifiers":[
        {
            "category":"Professional",
            "subcategory":"Management & Consulting",
            "type":"Services"
        }
    ],
    "sg:phone":"+1 916 966 1730",
    "sg:postcode":"95628",
    "sg:province":"CA",
    "sg:tags":[
        "consultant",
        "business"
    ],
    "wof:name":"President's Resource Org",
    "wof:placetype":"venue"
},
  "geometry": {"coordinates":[-121.28031300000001,38.647212],"type":"Point"}
}