{
  "type": "Feature",
  "properties": {
    "iso:country":"US",
    "sg:address":"2227 Mendocino Ave",
    "sg:city":"Santa Rosa",
    "sg:classifiers":[
        {
            "category":"Restaurant",
            "type":"Food & Drink"
        }
    ],
    "sg:menulink":"http://www.allmenus.com/ca/santa-rosa/52793-vip/menu/",
    "sg:phone":"+1 707 527 5430",
    "sg:postcode":"95403",
    "sg:province":"CA",
    "sg:tags":[
        "mexican"
    ],
    "wof:name":"Vip",
    "wof:placetype":"venue"
},
  "geometry": {"coordinates":[-122.71780800000001,38.461654],"type":"Point"}
}