{
  "type": "Feature",
  "properties": {
    "iso:country":"US",
    "sg:address":"2525 W Olive Ave",
    "sg:city":"Fullerton",
    "sg:classifiers":[
        {
            "category":"Building & Trades",
            "subcategory":"Construction",
            "type":"Services"
        }
    ],
    "sg:phone":"+1 714 578 0543",
    "sg:postcode":"92833",
    "sg:province":"CA",
    "sg:tags":[
        "contractor"
    ],
    "wof:name":"Lt General Contracting Inc",
    "wof:placetype":"venue"
},
  "geometry": {"coordinates":[-117.971547,33.862467],"type":"Point"}
}