{
  "type": "Feature",
  "properties": {
    "addr:full":"381 Airport Blvd S San Francisco CA 94080",
    "addr:housenumber":"381",
    "addr:postcode":"94080",
    "addr:street":"Airport Blvd S",
    "iso:country":"US",
    "sg:address":"381 Airport Blvd",
    "sg:city":"S San Francisco",
    "sg:classifiers":[
        {
            "category":"Restaurant",
            "type":"Food & Drink"
        }
    ],
    "sg:phone":"+1 650 871 6018",
    "sg:postcode":"94080",
    "sg:province":"CA",
    "wof:name":"Mc Donald's",
    "wof:placetype":"venue"
},
  "geometry": {"coordinates":[-122.407799,37.654869],"type":"Point"}
}