{
  "type": "Feature",
  "properties": {
    "addr:full":"202 S Park Victoria Dr Milpitas CA 95035",
    "addr:housenumber":"202",
    "addr:postcode":"95035",
    "addr:street":"S Park Victoria Dr",
    "iso:country":"US",
    "sg:address":"202 S Park Victoria Dr",
    "sg:city":"Milpitas",
    "sg:classifiers":[
        {
            "category":"Building & Trades",
            "subcategory":"Electrical",
            "type":"Services"
        }
    ],
    "sg:phone":"+1 408 934 9838",
    "sg:postcode":"95035",
    "sg:province":"CA",
    "sg:tags":[
        "electrical",
        "contractor"
    ],
    "wof:name":"American Alarm Services",
    "wof:placetype":"venue"
},
  "geometry": {"coordinates":[-121.88285399999999,37.431722],"type":"Point"}
}