{
  "type": "Feature",
  "properties": {
    "iso:country":"US",
    "sg:address":"32954 Rd 159",
    "sg:city":"Ivanhoe",
    "sg:classifiers":[
        {
            "category":"Bars & Pubs",
            "type":"Food & Drink"
        }
    ],
    "sg:phone":"+1 559 798 0822",
    "sg:postcode":"93235",
    "sg:province":"CA",
    "sg:tags":[
        "club",
        "night"
    ],
    "wof:name":"Navegante El Bar",
    "wof:placetype":"venue"
},
  "geometry": {"coordinates":[-119.21792600000001,36.388108],"type":"Point"}
}