{
  "type": "Feature",
  "properties": {
    "addr:full":"13921 Tustin East Dr Tustin CA 92780",
    "addr:housenumber":"13921",
    "addr:postcode":"92780",
    "addr:street":"Tustin East Dr",
    "iso:country":"US",
    "sg:address":"13921 Tustin East Dr",
    "sg:city":"Tustin",
    "sg:classifiers":[
        {
            "category":"Real Estate",
            "subcategory":"Real Estate Operator",
            "type":"Services"
        }
    ],
    "sg:phone":"+1 714 544 3303",
    "sg:postcode":"92780",
    "sg:province":"CA",
    "sg:tags":[
        "apartment"
    ],
    "sg:website":"www.creeksidemeadowsapts.com/",
    "wof:name":"Creekside Meadows Apartments",
    "wof:placetype":"venue"
},
  "geometry": {"coordinates":[-117.81099399999999,33.733745],"type":"Point"}
}