{
  "type": "Feature",
  "properties": {
    "addr:full":"2744 Belrose Avenue Berkeley CA 94701",
    "addr:housenumber":"2744",
    "addr:postcode":"94701",
    "addr:street":"Belrose Avenue",
    "iso:country":"US",
    "sg:address":"2744 Belrose Avenue",
    "sg:city":"Berkeley",
    "sg:classifiers":[
        {
            "category":"Travel",
            "subcategory":"Bed & Breakfast",
            "type":"Entertainment"
        }
    ],
    "sg:phone":"+1 510 845 7454",
    "sg:postcode":"94701",
    "sg:province":"CA",
    "sg:website":"www.bbonline.com/ca/belrose/inde...",
    "wof:name":"Belrose Bed & Breakfast",
    "wof:placetype":"venue"
},
  "geometry": {"coordinates":[-122.246172,37.861009],"type":"Point"}
}