{
  "type": "Feature",
  "properties": {
    "addr:full":"3043 Oak St Santa Ana CA 92707",
    "addr:housenumber":"3043",
    "addr:postcode":"92707",
    "addr:street":"Oak St",
    "iso:country":"US",
    "sg:address":"3043 Oak St",
    "sg:city":"Santa Ana",
    "sg:classifiers":[
        {
            "category":"Professional",
            "subcategory":"Testing Lab",
            "type":"Services"
        }
    ],
    "sg:phone":"+1 714 957 1215",
    "sg:postcode":"92707",
    "sg:province":"CA",
    "sg:tags":[
        "ultrasonic",
        "inspection"
    ],
    "wof:name":"Critical Operations",
    "wof:placetype":"venue"
},
  "geometry": {"coordinates":[-117.863052,33.706754],"type":"Point"}
}