{
  "type": "Feature",
  "properties": {
    "iso:country":"US",
    "sg:address":"6205 Van Nuys Blvd",
    "sg:city":"Van Nuys",
    "sg:classifiers":[
        {
            "category":"Home & Garden",
            "subcategory":"Carpets & Floor Coverings",
            "type":"Retail Goods"
        }
    ],
    "sg:phone":"+1 818 786 0681",
    "sg:postcode":"91401",
    "sg:province":"CA",
    "sg:tags":[
        "rug",
        "carpeting"
    ],
    "sg:website":"www.dwinteriorsinc.com",
    "wof:name":"D W Interiors",
    "wof:placetype":"venue"
},
  "geometry": {"coordinates":[-118.44899700000001,34.182899],"type":"Point"}
}