{
  "type": "Feature",
  "properties": {
    "addr:full":"1120 Nye St San Rafael CA 94901",
    "addr:housenumber":"1120",
    "addr:postcode":"94901",
    "addr:street":"Nye St",
    "iso:country":"US",
    "sg:address":"1120 Nye St",
    "sg:city":"San Rafael",
    "sg:classifiers":[
        {
            "category":"Professional",
            "subcategory":"Lawyer & Legal Services",
            "type":"Services"
        }
    ],
    "sg:phone":"+1 415 485 6060",
    "sg:postcode":"94901",
    "sg:province":"CA",
    "sg:tags":[
        "attorney"
    ],
    "wof:name":"Owen Mayer",
    "wof:placetype":"venue"
},
  "geometry": {"coordinates":[-122.52505600000001,37.974358],"type":"Point"}
}