{
  "type": "Feature",
  "properties": {
    "iso:country":"US",
    "sg:address":"3555 Voyager St",
    "sg:city":"Torrance",
    "sg:classifiers":[
        {
            "category":"Wholesale",
            "subcategory":"Electrical",
            "type":"Manufacturing & Wholesale Goods"
        }
    ],
    "sg:phone":"+1 310 371 5626",
    "sg:postcode":"90503",
    "sg:province":"CA",
    "sg:tags":[
        "electronic"
    ],
    "wof:name":"Alternative Retail Solutions",
    "wof:placetype":"venue"
},
  "geometry": {"coordinates":[-118.350115,33.852777],"type":"Point"}
}