{
  "type": "Feature",
  "properties": {
    "iso:country":"US",
    "sg:address":"1460 Thunderbird Dr",
    "sg:city":"Modesto",
    "sg:classifiers":[
        {
            "category":"Farming",
            "subcategory":"Livestock Farm",
            "type":"Manufacturing & Wholesale Goods"
        }
    ],
    "sg:phone":"+1 209 341 3106",
    "sg:postcode":"95356",
    "sg:province":"CA",
    "sg:tags":[
        "beef",
        "feedlot",
        "cattle"
    ],
    "wof:name":"Sierra Ranch",
    "wof:placetype":"venue"
},
  "geometry": {"coordinates":[-121.017881,37.742215],"type":"Point"}
}