{
  "type": "Feature",
  "properties": {
    "iso:country":"US",
    "sg:address":"9420 Reseda Blvd",
    "sg:city":"Northridge",
    "sg:classifiers":[
        {
            "category":"Manufacturing",
            "subcategory":"Textiles",
            "type":"Manufacturing & Wholesale Goods"
        }
    ],
    "sg:phone":"+1 818 886 3823",
    "sg:postcode":"91324",
    "sg:province":"CA",
    "wof:name":"Ideas and Images",
    "wof:placetype":"venue"
},
  "geometry": {"coordinates":[-118.536014,34.242381],"type":"Point"}
}