{
  "type": "Feature",
  "properties": {
    "addr:full":"708 W Ponderosa Ave Reedley CA 93654",
    "addr:housenumber":"708",
    "addr:postcode":"93654",
    "addr:street":"W Ponderosa Ave",
    "iso:country":"US",
    "sg:address":"708 W Ponderosa Ave",
    "sg:city":"Reedley",
    "sg:classifiers":[
        {
            "category":"Building & Trades",
            "subcategory":"Electrical",
            "type":"Services"
        },
        {
            "category":"Manufacturing",
            "subcategory":"Signs",
            "type":"Manufacturing & Wholesale Goods"
        }
    ],
    "sg:phone":"+1 559 638 9894",
    "sg:postcode":"93654",
    "sg:province":"CA",
    "sg:tags":[
        "contractor",
        "electrical",
        "specialty",
        "mfg"
    ],
    "wof:name":"Wolff's Sign",
    "wof:placetype":"venue"
},
  "geometry": {"coordinates":[-119.457618,36.606096],"type":"Point"}
}