{
  "type": "Feature",
  "properties": {
    "iso:country":"US",
    "sg:address":"11012 Main St",
    "sg:city":"Lamont",
    "sg:classifiers":[
        {
            "category":"Shopping",
            "subcategory":"Gifts & Souvenirs",
            "type":"Retail Goods"
        }
    ],
    "sg:phone":"+1 661 845 8207",
    "sg:postcode":"93241",
    "sg:province":"CA",
    "sg:tags":[
        "shop"
    ],
    "wof:name":"Poblanita",
    "wof:placetype":"venue"
},
  "geometry": {"coordinates":[-118.91448200000001,35.254813],"type":"Point"}
}