{
  "type": "Feature",
  "properties": {
    "addr:full":"747 Roth Rd French Camp CA 95231",
    "addr:housenumber":"747",
    "addr:postcode":"95231",
    "addr:street":"Roth Rd",
    "iso:country":"US",
    "sg:address":"747 Roth Rd",
    "sg:city":"French Camp",
    "sg:classifiers":[
        {
            "category":"Manufacturing",
            "subcategory":"Tools & Machinery",
            "type":"Manufacturing & Wholesale Goods"
        }
    ],
    "sg:phone":"+1 209 983 0278",
    "sg:postcode":"95231",
    "sg:province":"CA",
    "sg:tags":[
        "machine",
        "shop"
    ],
    "wof:name":"San Joaquin Grinding Inc",
    "wof:placetype":"venue"
},
  "geometry": {"coordinates":[-121.26993899999999,37.855602],"type":"Point"}
}