{
  "type": "Feature",
  "properties": {
    "iso:country":"US",
    "sg:address":"4130 Citrus Ave",
    "sg:city":"Rocklin",
    "sg:classifiers":[
        {
            "category":"Manufacturing",
            "subcategory":"Electronics",
            "type":"Manufacturing & Wholesale Goods"
        }
    ],
    "sg:phone":"+1 916 630 9483",
    "sg:postcode":"95677",
    "sg:province":"CA",
    "sg:tags":[
        "equipment",
        "mfg"
    ],
    "wof:name":"Constant Velocity Transm Lines",
    "wof:placetype":"venue"
},
  "geometry": {"coordinates":[-121.21784599999999,38.807543],"type":"Point"}
}