{
  "type": "Feature",
  "properties": {
    "addr:full":"1425 N Montebello Blvd Montebello CA 90640",
    "addr:housenumber":"1425",
    "addr:postcode":"90640",
    "addr:street":"N Montebello Blvd",
    "iso:country":"US",
    "sg:address":"1425 N Montebello Blvd",
    "sg:city":"Montebello",
    "sg:classifiers":[
        {
            "category":"Shopping",
            "subcategory":"Pets & Pet Supplies",
            "type":"Retail Goods"
        }
    ],
    "sg:phone":"+1 323 724 3194",
    "sg:postcode":"90640",
    "sg:province":"CA",
    "sg:tags":[
        "store"
    ],
    "wof:name":"Petco",
    "wof:placetype":"venue"
},
  "geometry": {"coordinates":[-118.089996,34.034901],"type":"Point"}
}