{
  "type": "Feature",
  "properties": {
    "iso:country":"US",
    "sg:address":"1340 E Covell Blvd",
    "sg:city":"Davis",
    "sg:classifiers":[
        {
            "category":"Banks & Credit Unions",
            "subcategory":"Bank",
            "type":"Services"
        }
    ],
    "sg:phone":"+1 530 753 9244",
    "sg:postcode":"95616",
    "sg:province":"CA",
    "sg:tags":[
        "bond",
        "broker",
        "stock"
    ],
    "wof:name":"Belenis, Jim",
    "wof:placetype":"venue"
},
  "geometry": {"coordinates":[-121.735083,38.561095],"type":"Point"}
}