{
  "type": "Feature",
  "properties": {
    "iso:country":"US",
    "sg:address":"2587 Chino Hills Pkwy",
    "sg:city":"Chino Hills",
    "sg:classifiers":[
        {
            "category":"Education",
            "subcategory":"Dance Studio",
            "type":"Public Place"
        }
    ],
    "sg:phone":"+1 909 597 3800",
    "sg:postcode":"91709",
    "sg:province":"CA",
    "sg:tags":[
        "instruction",
        "dancing"
    ],
    "wof:name":"All That Dance Academy",
    "wof:placetype":"venue"
},
  "geometry": {"coordinates":[-117.746209,33.984467],"type":"Point"}
}