{
  "type": "Feature",
  "properties": {
    "addr:full":"424 N San Mateo Drive San Mateo CA 94401",
    "addr:housenumber":"424",
    "addr:postcode":"94401",
    "addr:street":"N San Mateo Drive",
    "iso:country":"US",
    "sg:address":"424 N San Mateo Drive",
    "sg:city":"San Mateo",
    "sg:classifiers":[
        {
            "category":"Health Services",
            "subcategory":"Health Practitioner",
            "type":"Services"
        }
    ],
    "sg:phone":"+1 650 348 5112",
    "sg:postcode":"94401",
    "sg:province":"CA",
    "sg:tags":[
        "therapy",
        "physical"
    ],
    "wof:name":"Peninsula Spine Education & Treatment Center",
    "wof:placetype":"venue"
},
  "geometry": {"coordinates":[-122.333292,37.572918],"type":"Point"}
}