{
  "type": "Feature",
  "properties": {
    "addr:full":"6540 Stockton Blvd Ste 2 Sacramento CA 95823",
    "addr:housenumber":"6540",
    "addr:postcode":"95823",
    "addr:street":"Stockton Blvd Ste 2",
    "iso:country":"US",
    "sg:address":"6540 Stockton Blvd Ste 2",
    "sg:city":"Sacramento",
    "sg:classifiers":[
        {
            "category":"Banks & Credit Unions",
            "subcategory":"Financial Services",
            "type":"Services"
        }
    ],
    "sg:phone":"+1 916 392 6816",
    "sg:postcode":"95823",
    "sg:province":"CA",
    "sg:tags":[
        "mortgage"
    ],
    "wof:name":"Alliance Realty & Mortgage",
    "wof:placetype":"venue"
},
  "geometry": {"coordinates":[-121.434181,38.50679],"type":"Point"}
}