{
  "type": "Feature",
  "properties": {
    "addr:full":"1261 Ryan Ln Placentia CA 92882",
    "addr:housenumber":"1261",
    "addr:postcode":"ca 92882",
    "addr:street":"Ryan Ln",
    "iso:country":"US",
    "sg:address":"1261 Ryan Ln",
    "sg:city":"Placentia",
    "sg:classifiers":[
        {
            "category":"Manufacturing",
            "subcategory":"Tools & Machinery",
            "type":"Manufacturing & Wholesale Goods"
        }
    ],
    "sg:phone":"+1 714 528 9343",
    "sg:postcode":"92882",
    "sg:province":"CA",
    "sg:tags":[
        "farm",
        "mfg"
    ],
    "wof:name":"Crystal Cave Development Co",
    "wof:placetype":"venue"
},
  "geometry": {"coordinates":[-117.586467,33.874818],"type":"Point"}
}