{
  "type": "Feature",
  "properties": {
    "iso:country":"US",
    "sg:address":"13658 Hawthorne Blvd. #213",
    "sg:city":"Hawthorne",
    "sg:classifiers":[
        {
            "category":"Personal",
            "type":"Services"
        }
    ],
    "sg:phone":"+1 310 219 0999",
    "sg:postcode":"90250",
    "sg:province":"CA",
    "sg:tags":[
        "local"
    ],
    "wof:name":"Live Scan",
    "wof:placetype":"venue"
},
  "geometry": {"coordinates":[-118.352356,33.907923],"type":"Point"}
}