{
  "type": "Feature",
  "properties": {
    "iso:country":"US",
    "sg:address":"303 Hegenberger Rd",
    "sg:city":"Oakland",
    "sg:classifiers":[
        {
            "category":"Social Services",
            "subcategory":"Job Training",
            "type":"Services"
        }
    ],
    "sg:phone":"+1 510 632 6712",
    "sg:postcode":"94621",
    "sg:province":"CA",
    "sg:tags":[
        "nursing",
        "homes-skilled",
        "facility"
    ],
    "wof:name":"Nba Diciples Of The Greater Ks, Mo, Inc",
    "wof:placetype":"venue"
},
  "geometry": {"coordinates":[-122.19784900000001,37.734564],"type":"Point"}
}