{
  "type": "Feature",
  "properties": {
    "addr:full":"1060 Fresno St Fresno CA 93706",
    "addr:housenumber":"1060",
    "addr:postcode":"93706",
    "addr:street":"Fresno St",
    "iso:country":"US",
    "sg:address":"1060 Fresno St",
    "sg:city":"Fresno",
    "sg:classifiers":[
        {
            "category":"Utilities",
            "subcategory":"Mobile Phone",
            "type":"Services"
        },
        {
            "category":"Shopping",
            "subcategory":"Mobile Phones",
            "type":"Retail Goods"
        },
        {
            "category":"Utilities",
            "subcategory":"Telephone",
            "type":"Services"
        },
        {
            "category":"Professional",
            "subcategory":"Computer Services",
            "type":"Services"
        }
    ],
    "sg:phone":"+1 559 485 8196",
    "sg:postcode":"93706",
    "sg:province":"CA",
    "sg:tags":[
        "telecommunication",
        "supply",
        "communication",
        "system",
        "wireless",
        "equipment",
        "cellular"
    ],
    "sg:website":"http://clickserve.dartsearch.net/link/click?lid=43000000308049899",
    "wof:name":"T-Mobile",
    "wof:placetype":"venue"
},
  "geometry": {"coordinates":[-119.80156700000001,36.729236],"type":"Point"}
}