{
  "type": "Feature",
  "properties": {
    "iso:country":"US",
    "sg:address":"251 E Redondo Beach Blvd",
    "sg:city":"Gardena",
    "sg:classifiers":[
        {
            "category":"Wholesale",
            "subcategory":"Durable Goods & Equipment",
            "type":"Manufacturing & Wholesale Goods"
        }
    ],
    "sg:phone":"+1 310 715 6952",
    "sg:postcode":"90248",
    "sg:province":"CA",
    "sg:tags":[
        "importer"
    ],
    "wof:name":"Beaumar International LTD",
    "wof:placetype":"venue"
},
  "geometry": {"coordinates":[-118.268083,33.893232],"type":"Point"}
}