{
  "type": "Feature",
  "properties": {
    "iso:country":"US",
    "sg:address":"3411 E Ventura Ave",
    "sg:city":"Fresno",
    "sg:classifiers":[
        {
            "category":"Personal",
            "subcategory":"Barber",
            "type":"Services"
        }
    ],
    "sg:phone":"+1 559 824 5377",
    "sg:postcode":"93702",
    "sg:province":"CA",
    "wof:name":"Ramirez Barber & Beauty Shop",
    "wof:placetype":"venue"
},
  "geometry": {"coordinates":[-119.765985,36.735941],"type":"Point"}
}