{
  "type": "Feature",
  "properties": {
    "iso:country":"US",
    "sg:address":"2290 N Bellflower Blvd",
    "sg:city":"Long Beach",
    "sg:classifiers":[
        {
            "category":"Fast Food",
            "type":"Food & Drink"
        }
    ],
    "sg:phone":"+1 562 430 3500",
    "sg:postcode":"90815",
    "sg:province":"CA",
    "sg:tags":[
        "burger"
    ],
    "sg:website":"www.mcdonalds.com",
    "wof:name":"McDonald's",
    "wof:placetype":"venue"
},
  "geometry": {"coordinates":[-118.125,33.798599],"type":"Point"}
}