{
  "type": "Feature",
  "properties": {
    "addr:full":"1083 Barona Rd Lakeside CA 92040",
    "addr:housenumber":"1083",
    "addr:postcode":"92040",
    "addr:street":"Barona Rd",
    "iso:country":"US",
    "sg:address":"1083 Barona Rd",
    "sg:city":"Lakeside",
    "sg:classifiers":[
        {
            "category":"Building & Trades",
            "subcategory":"Construction",
            "type":"Services"
        }
    ],
    "sg:phone":"+1 619 390 8755",
    "sg:postcode":"92040",
    "sg:province":"CA",
    "sg:tags":[
        "dry wall",
        "contractor"
    ],
    "wof:name":"Featherstone Drywall Svc",
    "wof:placetype":"venue"
},
  "geometry": {"coordinates":[-116.875821,32.932684],"type":"Point"}
}