{
  "type": "Feature",
  "properties": {
    "iso:country":"US",
    "sg:address":"2355 E Washington Blvd",
    "sg:city":"Pasadena",
    "sg:classifiers":[
        {
            "category":"Organizations",
            "subcategory":"Religious Organization",
            "type":"Services"
        }
    ],
    "sg:phone":"+1 626 797 0359",
    "sg:postcode":"91104",
    "sg:province":"CA",
    "sg:tags":[
        "church"
    ],
    "sg:website":"www.biblelandmission.org",
    "wof:name":"Bible Land Mission Salem Ctr",
    "wof:placetype":"venue"
},
  "geometry": {"coordinates":[-118.102543,34.169207],"type":"Point"}
}