{
  "type": "Feature",
  "properties": {
    "iso:country":"US",
    "sg:address":"418 Truxtun Ave",
    "sg:city":"Bakersfield",
    "sg:classifiers":[
        {
            "category":"Health Services",
            "subcategory":"Health Practitioner",
            "type":"Services"
        }
    ],
    "sg:phone":"+1 661 323 1839",
    "sg:postcode":"93301",
    "sg:province":"CA",
    "sg:tags":[
        "pathologist",
        "speech"
    ],
    "wof:name":"Speech Pathology Assoc",
    "wof:placetype":"venue"
},
  "geometry": {"coordinates":[-119.005034,35.373362],"type":"Point"}
}