{
  "type": "Feature",
  "properties": {
    "addr:full":"18275 Meadow Song Way Salinas CA 93908",
    "addr:housenumber":"18275",
    "addr:postcode":"93908",
    "addr:street":"Meadow Song Way",
    "iso:country":"US",
    "sg:address":"18275 Meadow Song Way",
    "sg:city":"Salinas",
    "sg:classifiers":[
        {
            "category":"Real Estate",
            "subcategory":"Real Estate Agent",
            "type":"Services"
        }
    ],
    "sg:phone":"+1 831 455 2110",
    "sg:postcode":"93908",
    "sg:province":"CA",
    "wof:name":"Mariner Real Estate Inc",
    "wof:placetype":"venue"
},
  "geometry": {"coordinates":[-121.64391500000001,36.604865],"type":"Point"}
}