{
  "type": "Feature",
  "properties": {
    "addr:full":"3317 W Beverly Blvd Ste 102 Montebello CA 90640",
    "addr:housenumber":"3317",
    "addr:postcode":"90640",
    "addr:street":"W Beverly Blvd Ste 102",
    "iso:country":"US",
    "sg:address":"3317 W Beverly Blvd Ste 102",
    "sg:city":"Montebello",
    "sg:classifiers":[
        {
            "category":"Professional",
            "subcategory":"Lawyer & Legal Services",
            "type":"Services"
        }
    ],
    "sg:phone":"+1 323 887 9844",
    "sg:postcode":"90640",
    "sg:province":"CA",
    "wof:name":"Tony Luna Attorney At Law",
    "wof:placetype":"venue"
},
  "geometry": {"coordinates":[-118.139762,34.02395],"type":"Point"}
}