{
  "type": "Feature",
  "properties": {
    "iso:country":"US",
    "sg:address":"4003 Goldfinch St",
    "sg:city":"San Diego",
    "sg:classifiers":[
        {
            "category":"Banks & Credit Unions",
            "subcategory":"Investment Brokerage",
            "type":"Services"
        }
    ],
    "sg:phone":"+1 619 294 4449",
    "sg:postcode":"92103",
    "sg:province":"CA",
    "sg:tags":[
        "security"
    ],
    "wof:name":"Robin Ballard",
    "wof:placetype":"venue"
},
  "geometry": {"coordinates":[-117.17131500000001,32.75082],"type":"Point"}
}