{
  "type": "Feature",
  "properties": {
    "addr:full":"639 N Larchmont Blvd Los Angeles CA 90004",
    "addr:housenumber":"639",
    "addr:postcode":"90004",
    "addr:street":"N Larchmont Blvd",
    "iso:country":"US",
    "sg:address":"639 N Larchmont Blvd",
    "sg:city":"Los Angeles",
    "sg:classifiers":[
        {
            "category":"Communications",
            "subcategory":"Film & Video Production",
            "type":"Services"
        }
    ],
    "sg:phone":"+1 323 463 2200",
    "sg:postcode":"90004",
    "sg:province":"CA",
    "sg:tags":[
        "taping"
    ],
    "wof:name":"Silas Entertainment",
    "wof:placetype":"venue"
},
  "geometry": {"coordinates":[-118.32373800000001,34.08279],"type":"Point"}
}