{
  "type": "Feature",
  "properties": {
    "addr:full":"28 6th St San Francisco CA 94103",
    "addr:housenumber":"28",
    "addr:postcode":"94103",
    "addr:street":"6Th St",
    "iso:country":"US",
    "sg:address":"28 6th St",
    "sg:city":"San Francisco",
    "sg:classifiers":[
        {
            "category":"Shopping",
            "subcategory":"Used Merchandise",
            "type":"Retail Goods"
        }
    ],
    "sg:phone":"+1 415 522 1732",
    "sg:postcode":"94103",
    "sg:province":"CA",
    "wof:name":"Can B Loans",
    "wof:placetype":"venue"
},
  "geometry": {"coordinates":[-122.409402,37.781448],"type":"Point"}
}