{
  "type": "Feature",
  "properties": {
    "iso:country":"US",
    "sg:address":"3220 W Magnolia Blvd",
    "sg:city":"Burbank",
    "sg:classifiers":[
        {
            "category":"Shopping",
            "subcategory":"Used Merchandise",
            "type":"Retail Goods"
        }
    ],
    "sg:phone":"+1 818 845 0636",
    "sg:postcode":"91505",
    "sg:province":"CA",
    "sg:tags":[
        "vintage",
        "clothing",
        "period",
        "consignment"
    ],
    "wof:name":"Hubba Hubba",
    "wof:placetype":"venue"
},
  "geometry": {"coordinates":[-118.343002,34.169399],"type":"Point"}
}