{
  "type": "Feature",
  "properties": {
    "iso:country":"US",
    "sg:address":"8380 Farralone Ave",
    "sg:city":"Canoga Park",
    "sg:classifiers":[
        {
            "category":"Professional",
            "type":"Services"
        }
    ],
    "sg:phone":"+1 818 887 5949",
    "sg:postcode":"91304",
    "sg:province":"CA",
    "wof:name":"John M Tesoriero Ensign Limi",
    "wof:placetype":"venue"
},
  "geometry": {"coordinates":[-118.610845,34.22162],"type":"Point"}
}