{
  "type": "Feature",
  "properties": {
    "addr:full":"2880 Sunrise Blvd Ste 220 Rncho Cordova CA 95742",
    "addr:housenumber":"2880",
    "addr:postcode":"95742",
    "addr:street":"Sunrise Blvd Ste 220 Rncho",
    "iso:country":"US",
    "sg:address":"2880 Sunrise Blvd Ste 220",
    "sg:city":"Rncho Cordova",
    "sg:classifiers":[
        {
            "category":"Banks & Credit Unions",
            "subcategory":"Financial Services",
            "type":"Services"
        }
    ],
    "sg:phone":"+1 916 635 8799",
    "sg:postcode":"95742",
    "sg:province":"CA",
    "sg:tags":[
        "broker",
        "mortgage"
    ],
    "wof:name":"Pacific National Lending",
    "wof:placetype":"venue"
},
  "geometry": {"coordinates":[-121.265925,38.599734],"type":"Point"}
}