{
  "type": "Feature",
  "properties": {
    "addr:full":"28741 Cole Grade Rd Valley Center CA 92082",
    "addr:housenumber":"28741",
    "addr:postcode":"92082",
    "addr:street":"Cole Grade Rd",
    "iso:country":"US",
    "sg:address":"28741 Cole Grade Rd",
    "sg:city":"Valley Center",
    "sg:classifiers":[
        {
            "category":"Manufacturing",
            "subcategory":"Lumber",
            "type":"Manufacturing & Wholesale Goods"
        }
    ],
    "sg:phone":"+1 760 749 1702",
    "sg:postcode":"92082",
    "sg:province":"CA",
    "sg:tags":[
        "government"
    ],
    "wof:name":"Forestry & Fire Protection",
    "wof:placetype":"venue"
},
  "geometry": {"coordinates":[-117.023954,33.234891],"type":"Point"}
}