{
  "type": "Feature",
  "properties": {
    "addr:full":"14241 Ventura Blvd Sherman Oaks CA 91423",
    "addr:housenumber":"14241",
    "addr:postcode":"91423",
    "addr:street":"Ventura Blvd",
    "iso:country":"US",
    "sg:address":"14241 Ventura Blvd",
    "sg:city":"Sherman Oaks",
    "sg:classifiers":[
        {
            "category":"Real Estate",
            "subcategory":"Real Estate Agent",
            "type":"Services"
        }
    ],
    "sg:phone":"+1 818 981 9074",
    "sg:postcode":"91423",
    "sg:province":"CA",
    "sg:tags":[
        "management"
    ],
    "wof:name":"Bell Diversified Development",
    "wof:placetype":"venue"
},
  "geometry": {"coordinates":[-118.445234,34.150397],"type":"Point"}
}