{
  "type": "Feature",
  "properties": {
    "iso:country":"US",
    "sg:address":"1421 Hilltop Dr",
    "sg:city":"Chula Vista",
    "sg:classifiers":[
        {
            "category":"Home & Garden",
            "subcategory":"Furniture",
            "type":"Retail Goods"
        }
    ],
    "sg:phone":"+1 619 420 0600",
    "sg:postcode":"91911",
    "sg:province":"CA",
    "wof:name":"Ceja Furniture Warehouse",
    "wof:placetype":"venue"
},
  "geometry": {"coordinates":[-117.05140900000001,32.602395],"type":"Point"}
}