{
  "type": "Feature",
  "properties": {
    "iso:country":"US",
    "sg:address":"27881 Robinson Canyon Rd",
    "sg:city":"Carmel",
    "sg:classifiers":[
        {
            "category":"Professional",
            "type":"Services"
        },
        {
            "category":"Professional",
            "subcategory":"Art Services",
            "type":"Services"
        }
    ],
    "sg:phone":"+1 831 625 3112",
    "sg:postcode":"93923",
    "sg:province":"CA",
    "sg:tags":[
        "mineral",
        "mfg",
        "commercial",
        "p",
        "design",
        "nonmetallic",
        "sculptor"
    ],
    "wof:name":"Paul Wilson Sculpture Studio",
    "wof:placetype":"venue"
},
  "geometry": {"coordinates":[-121.806876,36.519622],"type":"Point"}
}