{
  "type": "Feature",
  "properties": {
    "iso:country":"US",
    "sg:address":"29397 Agoura Rd",
    "sg:city":"Agoura Hills",
    "sg:classifiers":[
        {
            "category":"Professional",
            "subcategory":"Computer Services",
            "type":"Services"
        }
    ],
    "sg:phone":"+1 818 706 3282",
    "sg:postcode":"91301",
    "sg:province":"CA",
    "sg:tags":[
        "processing",
        "datum"
    ],
    "wof:name":"Postal Data Svc Inc",
    "wof:placetype":"venue"
},
  "geometry": {"coordinates":[-118.771299,34.145136],"type":"Point"}
}