{
  "type": "Feature",
  "properties": {
    "iso:country":"US",
    "sg:address":"12947 Newton St",
    "sg:city":"Sylmar",
    "sg:classifiers":[
        {
            "category":"Building & Trades",
            "subcategory":"Plumbing",
            "type":"Services"
        }
    ],
    "sg:phone":"+1 818 361 2285",
    "sg:postcode":"91342",
    "sg:province":"CA",
    "sg:tags":[
        "contractor"
    ],
    "wof:name":"Thomas Isaac Valenzuela & AC",
    "wof:placetype":"venue"
},
  "geometry": {"coordinates":[-118.414166,34.300146],"type":"Point"}
}