{
  "type": "Feature",
  "properties": {
    "addr:full":"948 9th St Santa Monica CA 90403",
    "addr:housenumber":"948",
    "addr:postcode":"90403",
    "addr:street":"9Th St",
    "iso:country":"US",
    "sg:address":"948 9th St",
    "sg:city":"Santa Monica",
    "sg:classifiers":[
        {
            "category":"Shopping",
            "subcategory":"Catalog Store",
            "type":"Retail Goods"
        }
    ],
    "sg:phone":"+1 310 393 4593",
    "sg:postcode":"90403",
    "sg:province":"CA",
    "sg:tags":[
        "house",
        "mail"
    ],
    "wof:name":"Waverley Books",
    "wof:placetype":"venue"
},
  "geometry": {"coordinates":[-118.497491,34.02628],"type":"Point"}
}