{
  "type": "Feature",
  "properties": {
    "addr:full":"4761 N Star Way Modesto CA 95356",
    "addr:housenumber":"4761",
    "addr:postcode":"ca 95356",
    "addr:street":"N Star Way",
    "iso:country":"US",
    "sg:address":"4761 N Star Way",
    "sg:city":"Modesto",
    "sg:classifiers":[
        {
            "category":"Wholesale",
            "subcategory":"Machinery & Supplies",
            "type":"Manufacturing & Wholesale Goods"
        },
        {
            "category":"Professional",
            "type":"Services"
        }
    ],
    "sg:phone":"+1 209 578 1500",
    "sg:postcode":"95356",
    "sg:province":"CA",
    "sg:tags":[
        "equipment",
        "material",
        "handling"
    ],
    "wof:name":"Wharehouse Operation Inc",
    "wof:placetype":"venue"
},
  "geometry": {"coordinates":[-121.002499,37.705874],"type":"Point"}
}