{
  "type": "Feature",
  "properties": {
    "addr:full":"901 Battery Street Suite 220 San Francisco CA 94111",
    "addr:housenumber":"901",
    "addr:postcode":"94111",
    "addr:street":"Battery Street Suite 220",
    "iso:country":"US",
    "sg:address":"901 Battery Street Suite 220",
    "sg:city":"San Francisco",
    "sg:classifiers":[
        {
            "category":"Professional",
            "type":"Services"
        },
        {
            "category":"Communications",
            "type":"Services"
        }
    ],
    "sg:phone":"+1 415 262 4222",
    "sg:postcode":"94111",
    "sg:province":"CA",
    "sg:tags":[
        "medium",
        "mass"
    ],
    "sg:website":"www.m1sf.com",
    "wof:name":"Media One Services",
    "wof:placetype":"venue"
},
  "geometry": {"coordinates":[-122.401652,37.799766],"type":"Point"}
}