{
  "type": "Feature",
  "properties": {
    "addr:full":"676 S Ave 21 Los Angeles CA 90031",
    "addr:housenumber":"676;21",
    "addr:postcode":"90031",
    "addr:street":"S Ave",
    "iso:country":"US",
    "sg:address":"676 S Ave 21",
    "sg:city":"Los Angeles",
    "sg:classifiers":[
        {
            "category":"Shopping",
            "type":"Retail Goods"
        }
    ],
    "sg:phone":"+1 323 225 1214",
    "sg:postcode":"90031",
    "sg:province":"CA",
    "sg:tags":[
        "merchandise"
    ],
    "wof:name":"Handpress International",
    "wof:placetype":"venue"
},
  "geometry": {"coordinates":[-118.216741,34.065577],"type":"Point"}
}