{
  "type": "Feature",
  "properties": {
    "addr:full":"3221 Fruitvale Ave Oakland CA 94602",
    "addr:housenumber":"3221",
    "addr:postcode":"94602",
    "addr:street":"Fruitvale Ave",
    "iso:country":"US",
    "sg:address":"3221 Fruitvale Ave",
    "sg:city":"Oakland",
    "sg:classifiers":[
        {
            "category":"Health Services",
            "subcategory":"Doctor",
            "type":"Services"
        }
    ],
    "sg:phone":"+1 510 532 1777",
    "sg:postcode":"94602",
    "sg:province":"CA",
    "sg:tags":[
        "surgeon",
        "oral"
    ],
    "wof:name":"Patino Jose A DDS",
    "wof:placetype":"venue"
},
  "geometry": {"coordinates":[-122.21700300000001,37.7976],"type":"Point"}
}