{
  "type": "Feature",
  "properties": {
    "iso:country":"US",
    "sg:address":"33341 Cameo Ln",
    "sg:city":"Wildomar",
    "sg:classifiers":[
        {
            "category":"Place Of Worship",
            "subcategory":"Church",
            "type":"Public Place"
        },
        {
            "category":"Place Of Worship",
            "type":"Public Place"
        }
    ],
    "sg:phone":"+1 951 678 7394",
    "sg:postcode":"92595",
    "sg:province":"CA",
    "sg:tags":[
        "churches-non-denominational"
    ],
    "wof:name":"Calvary Chapel Bear Creek Inc",
    "wof:placetype":"venue"
},
  "geometry": {"coordinates":[-117.282208,33.594862],"type":"Point"}
}