{
  "type": "Feature",
  "properties": {
    "iso:country":"US",
    "sg:address":"381 Lovell Ave",
    "sg:city":"Mill Valley",
    "sg:classifiers":[
        {
            "category":"Professional",
            "subcategory":"Management & Consulting",
            "type":"Services"
        }
    ],
    "sg:phone":"+1 415 388 1681",
    "sg:postcode":"94941",
    "sg:province":"CA",
    "sg:tags":[
        "marketing",
        "consultant"
    ],
    "wof:name":"Alexander L Biel & Assoc",
    "wof:placetype":"venue"
},
  "geometry": {"coordinates":[-122.558704,37.911029],"type":"Point"}
}