{
  "type": "Feature",
  "properties": {
    "iso:country":"US",
    "sg:address":"18226 W McDurmott",
    "sg:city":"Irvine",
    "sg:classifiers":[
        {
            "category":"Shopping",
            "subcategory":"Computers & Home Electronics",
            "type":"Retail Goods"
        }
    ],
    "sg:phone":"+1 949 851 8531",
    "sg:postcode":"92614",
    "sg:province":"CA",
    "sg:tags":[
        "equipment",
        "electronic",
        "supply"
    ],
    "sg:website":"www.torikocorp.com",
    "wof:name":"Toriko Corp",
    "wof:placetype":"venue"
},
  "geometry": {"coordinates":[-117.867561,33.690256],"type":"Point"}
}