{
  "type": "Feature",
  "properties": {
    "iso:country":"US",
    "sg:address":"2211 S Hacienda Blvd",
    "sg:city":"Hacienda Heights",
    "sg:classifiers":[
        {
            "category":"Wholesale",
            "subcategory":"Electrical",
            "type":"Manufacturing & Wholesale Goods"
        }
    ],
    "sg:phone":"+1 626 968 6980",
    "sg:postcode":"91745",
    "sg:province":"CA",
    "sg:tags":[
        "equipment",
        "testing",
        "electronic"
    ],
    "wof:name":"THT Intl",
    "wof:placetype":"venue"
},
  "geometry": {"coordinates":[-117.968692,33.993613],"type":"Point"}
}