{
  "type": "Feature",
  "properties": {
    "iso:country":"US",
    "sg:address":"26612 Towne Centre Drive",
    "sg:city":"Foothill Ranch",
    "sg:classifiers":[
        {
            "category":"Food & Beverages",
            "subcategory":"Candy",
            "type":"Retail Goods"
        }
    ],
    "sg:phone":"+1 949 588 1767",
    "sg:postcode":"92610",
    "sg:province":"CA",
    "sg:tags":[
        "store"
    ],
    "wof:name":"Bon Bon Candy",
    "wof:placetype":"venue"
},
  "geometry": {"coordinates":[-117.66613599999999,33.676961],"type":"Point"}
}