{
  "type": "Feature",
  "properties": {
    "iso:country":"US",
    "sg:address":"961 1st St",
    "sg:city":"Lafayette",
    "sg:classifiers":[
        {
            "category":"Social Services",
            "subcategory":"Child Care",
            "type":"Services"
        }
    ],
    "sg:phone":"+1 925 283 4500",
    "sg:postcode":"94549",
    "sg:province":"CA",
    "wof:name":"Center-Arts Technology & Sci",
    "wof:placetype":"venue"
},
  "geometry": {"coordinates":[-122.116607,37.891349],"type":"Point"}
}