{
  "type": "Feature",
  "properties": {
    "addr:full":"858 N Cherry St Tulare CA 93274",
    "addr:housenumber":"858",
    "addr:postcode":"93274",
    "addr:street":"N Cherry St",
    "iso:country":"US",
    "sg:address":"858 N Cherry St",
    "sg:city":"Tulare",
    "sg:classifiers":[
        {
            "category":"Wholesale",
            "subcategory":"Medical Equipment & Supplies",
            "type":"Manufacturing & Wholesale Goods"
        }
    ],
    "sg:phone":"+1 559 686 9000",
    "sg:postcode":"93274",
    "sg:province":"CA",
    "wof:name":"Valley Import Export",
    "wof:placetype":"venue"
},
  "geometry": {"coordinates":[-119.33752,36.21919],"type":"Point"}
}