{
  "type": "Feature",
  "properties": {
    "addr:full":"7727 Calle Maria Winnetka CA 91306",
    "addr:housenumber":"7727",
    "addr:postcode":"91306",
    "addr:street":"Calle Maria",
    "iso:country":"US",
    "sg:address":"7727 Calle Maria",
    "sg:city":"Winnetka",
    "sg:classifiers":[
        {
            "category":"Retail",
            "subcategory":"Car Wash",
            "type":"Services"
        }
    ],
    "sg:phone":"+1 818 772 1582",
    "sg:postcode":"91306",
    "sg:province":"CA",
    "wof:name":"Arthur Bennish",
    "wof:placetype":"venue"
},
  "geometry": {"coordinates":[-118.562771,34.211112],"type":"Point"}
}