{
  "type": "Feature",
  "properties": {
    "iso:country":"US",
    "sg:address":"1600 Wyatt Dr",
    "sg:city":"Santa Clara",
    "sg:classifiers":[
        {
            "category":"Wholesale",
            "subcategory":"Durable Goods & Equipment",
            "type":"Manufacturing & Wholesale Goods"
        }
    ],
    "sg:phone":"+1 408 969 0221",
    "sg:postcode":"95054",
    "sg:province":"CA",
    "sg:tags":[
        "audiovisual"
    ],
    "wof:name":"Globalpresentercom",
    "wof:placetype":"venue"
},
  "geometry": {"coordinates":[-121.956613,37.389997],"type":"Point"}
}