{
  "type": "Feature",
  "properties": {
    "iso:country":"US",
    "sg:address":"14170 Crenshaw Boulevard",
    "sg:city":"Gardena",
    "sg:classifiers":[
        {
            "category":"Restaurant",
            "type":"Food & Drink"
        }
    ],
    "sg:phone":"+1 310 327 9931",
    "sg:postcode":"90249",
    "sg:province":"CA",
    "sg:tags":[
        "mexican"
    ],
    "wof:name":"Lucky Star Cafe Mexican Grill",
    "wof:placetype":"venue"
},
  "geometry": {"coordinates":[-118.326587,33.902396],"type":"Point"}
}