{
  "type": "Feature",
  "properties": {
    "addr:full":"92 Caselli Ave San Francisco CA 94114",
    "addr:housenumber":"92",
    "addr:postcode":"94114",
    "addr:street":"Caselli Ave",
    "iso:country":"US",
    "sg:address":"92 Caselli Ave",
    "sg:city":"San Francisco",
    "sg:classifiers":[
        {
            "category":"Travel",
            "subcategory":"Hotels & Motels",
            "type":"Entertainment"
        }
    ],
    "sg:phone":"+1 415 861 3162",
    "sg:postcode":"94114",
    "sg:province":"CA",
    "sg:tags":[
        "operation"
    ],
    "wof:name":"The Albion House Inn",
    "wof:placetype":"venue"
},
  "geometry": {"coordinates":[-122.44130800000001,37.759755],"type":"Point"}
}