{
  "type": "Feature",
  "properties": {
    "iso:country":"US",
    "sg:address":"1820 E Garry Ave",
    "sg:city":"Santa Ana",
    "sg:classifiers":[
        {
            "category":"Health Services",
            "subcategory":"Doctor",
            "type":"Services"
        }
    ],
    "sg:phone":"+1 949 660 1399",
    "sg:postcode":"92705",
    "sg:province":"CA",
    "sg:tags":[
        "physician",
        "surgeon"
    ],
    "wof:name":"Catherine Arvantely MD",
    "wof:placetype":"venue"
},
  "geometry": {"coordinates":[-117.852143,33.70429],"type":"Point"}
}