{
  "type": "Feature",
  "properties": {
    "iso:country":"US",
    "sg:address":"3695 Reflections Dr",
    "sg:city":"Pleasanton",
    "sg:classifiers":[
        {
            "category":"Professional",
            "subcategory":"Management & Consulting",
            "type":"Services"
        }
    ],
    "sg:phone":"+1 925 462 6590",
    "sg:postcode":"94566",
    "sg:province":"CA",
    "sg:tags":[
        "consultant",
        "automation"
    ],
    "wof:name":"Powerdox Inc",
    "wof:placetype":"venue"
},
  "geometry": {"coordinates":[-121.86414000000001,37.668549],"type":"Point"}
}