{
  "type": "Feature",
  "properties": {
    "addr:full":"17045 Main St Hesperia CA 92345",
    "addr:housenumber":"17045",
    "addr:postcode":"92345",
    "addr:street":"Main St",
    "iso:country":"US",
    "sg:address":"17045 Main St",
    "sg:city":"Hesperia",
    "sg:classifiers":[
        {
            "category":"Manufacturing",
            "subcategory":"Printing",
            "type":"Manufacturing & Wholesale Goods"
        }
    ],
    "sg:phone":"+1 760 956 7827",
    "sg:postcode":"92345",
    "sg:province":"CA",
    "sg:tags":[
        "newspaper"
    ],
    "wof:name":"Hesperia Star",
    "wof:placetype":"venue"
},
  "geometry": {"coordinates":[-117.290965,34.419905],"type":"Point"}
}