{
  "type": "Feature",
  "properties": {
    "addr:full":"833 Island Dr #A Alameda CA 94502",
    "addr:housenumber":"833",
    "addr:postcode":"94502",
    "addr:street":"Island Dr # A Alameda",
    "iso:country":"US",
    "sg:address":"833 Island Dr #A",
    "sg:city":"Alameda",
    "sg:classifiers":[
        {
            "category":"Banks & Credit Unions",
            "subcategory":"Bank",
            "type":"Services"
        }
    ],
    "sg:phone":"+1 510 748 8435",
    "sg:postcode":"94502",
    "sg:province":"CA",
    "sg:website":"www.bankofalameda.com",
    "wof:name":"Bank of Alameda",
    "wof:placetype":"venue"
},
  "geometry": {"coordinates":[-122.23857700000001,37.738324],"type":"Point"}
}