{
  "type": "Feature",
  "properties": {
    "iso:country":"US",
    "sg:address":"3408 Via Oporto Suite 204",
    "sg:city":"Newport Beach",
    "sg:classifiers":[
        {
            "category":"Arts & Performance",
            "subcategory":"Art Gallery",
            "type":"Entertainment"
        }
    ],
    "sg:phone":"+1 949 673 2555",
    "sg:postcode":"92663",
    "sg:province":"CA",
    "wof:name":"Envirovision",
    "wof:placetype":"venue"
},
  "geometry": {"coordinates":[-117.92826599999999,33.618104],"type":"Point"}
}