{
  "type": "Feature",
  "properties": {
    "iso:country":"US",
    "sg:address":"766 W Franklin St",
    "sg:city":"Monterey",
    "sg:classifiers":[
        {
            "category":"Wholesale",
            "subcategory":"Apparel",
            "type":"Manufacturing & Wholesale Goods"
        }
    ],
    "sg:phone":"+1 831 373 3985",
    "sg:postcode":"93940",
    "sg:province":"CA",
    "sg:tags":[
        "piece"
    ],
    "wof:name":"First Shirt",
    "wof:placetype":"venue"
},
  "geometry": {"coordinates":[-121.90084,36.601441],"type":"Point"}
}