{
  "type": "Feature",
  "properties": {
    "addr:full":"269 Solar View Dr San Marcos CA 92069",
    "addr:housenumber":"269",
    "addr:postcode":"92069",
    "addr:street":"Solar View Dr",
    "iso:country":"US",
    "sg:address":"269 Solar View Dr",
    "sg:city":"San Marcos",
    "sg:classifiers":[
        {
            "category":"Wholesale",
            "subcategory":"Machinery & Supplies",
            "type":"Manufacturing & Wholesale Goods"
        }
    ],
    "sg:phone":"+1 760 471 7963",
    "sg:postcode":"92069",
    "sg:province":"CA",
    "sg:tags":[
        "equipment",
        "industrial"
    ],
    "wof:name":"Twin Oaks Engineering",
    "wof:placetype":"venue"
},
  "geometry": {"coordinates":[-117.159201,33.199202],"type":"Point"}
}