{
  "type": "Feature",
  "properties": {
    "iso:country":"US",
    "sg:address":"12152 N Lower Sacramento Rd",
    "sg:city":"Lodi",
    "sg:classifiers":[
        {
            "category":"Farming",
            "subcategory":"Farm",
            "type":"Manufacturing & Wholesale Goods"
        }
    ],
    "sg:phone":"+1 209 368 4748",
    "sg:postcode":"95242",
    "sg:province":"CA",
    "sg:tags":[
        "crop",
        "general"
    ],
    "wof:name":"Ruby H Fujinaka",
    "wof:placetype":"venue"
},
  "geometry": {"coordinates":[-121.310363,38.093299],"type":"Point"}
}