{
  "type": "Feature",
  "properties": {
    "addr:full":"20725 Sasia Rd Tehachapi CA 93561",
    "addr:housenumber":"20725",
    "addr:postcode":"93561",
    "addr:street":"Sasia Rd",
    "iso:country":"US",
    "sg:address":"20725 Sasia Rd",
    "sg:city":"Tehachapi",
    "sg:classifiers":[
        {
            "category":"Freight",
            "type":"Transportation"
        }
    ],
    "sg:phone":"+1 909 908 9001",
    "sg:postcode":"93561",
    "sg:province":"CA",
    "sg:tags":[
        "operator",
        "local",
        "trucking"
    ],
    "wof:name":"Valencia Trucking Inc",
    "wof:placetype":"venue"
},
  "geometry": {"coordinates":[-118.628274,35.116405],"type":"Point"}
}