{
  "type": "Feature",
  "properties": {
    "addr:full":"504 S Bay Front Newport Beach CA 92662",
    "addr:housenumber":"504",
    "addr:postcode":"92662",
    "addr:street":"S Bay Front",
    "iso:country":"US",
    "sg:address":"504 S Bay Front",
    "sg:city":"Newport Beach",
    "sg:classifiers":[
        {
            "category":"Shopping",
            "subcategory":"Jewelry",
            "type":"Retail Goods"
        }
    ],
    "sg:phone":"+1 949 675 7904",
    "sg:postcode":"92662",
    "sg:province":"CA",
    "wof:name":"Tahiti Nui",
    "wof:placetype":"venue"
},
  "geometry": {"coordinates":[-117.897437,33.605274],"type":"Point"}
}