{
  "type": "Feature",
  "properties": {
    "addr:full":"305 San Anselmo Ave San Anselmo CA 94960",
    "addr:housenumber":"305",
    "addr:postcode":"94960",
    "addr:street":"San Anselmo Ave",
    "iso:country":"US",
    "sg:address":"305 San Anselmo Ave",
    "sg:city":"San Anselmo",
    "sg:classifiers":[
        {
            "category":"Social Services",
            "type":"Services"
        }
    ],
    "sg:phone":"+1 415 256 1580",
    "sg:postcode":"94960",
    "sg:province":"CA",
    "sg:tags":[
        "organization",
        "welfare"
    ],
    "wof:name":"Sunny Hills Childrens Garden",
    "wof:placetype":"venue"
},
  "geometry": {"coordinates":[-122.562133,37.972799],"type":"Point"}
}