{
  "type": "Feature",
  "properties": {
    "addr:full":"1200 Elm Ave Modesto CA 95351",
    "addr:housenumber":"1200",
    "addr:postcode":"ca 95351",
    "addr:street":"Elm Ave",
    "iso:country":"US",
    "sg:address":"1200 Elm Ave",
    "sg:city":"Modesto",
    "sg:classifiers":[
        {
            "category":"Home & Garden",
            "subcategory":"Building Materials",
            "type":"Retail Goods"
        }
    ],
    "sg:phone":"+1 209 522 7923",
    "sg:postcode":"95351",
    "sg:province":"CA",
    "sg:tags":[
        "door"
    ],
    "wof:name":"Ichord Overhead Doors",
    "wof:placetype":"venue"
},
  "geometry": {"coordinates":[-121.02607399999999,37.643172],"type":"Point"}
}