{
  "type": "Feature",
  "properties": {
    "iso:country":"US",
    "sg:address":"7325 Pontoosuc Ave",
    "sg:city":"Riverside",
    "sg:classifiers":[
        {
            "category":"Building & Trades",
            "subcategory":"Construction",
            "type":"Services"
        }
    ],
    "sg:phone":"+1 951 780 1658",
    "sg:postcode":"92504",
    "sg:province":"CA",
    "sg:tags":[
        "concrete",
        "contractor"
    ],
    "wof:name":"Andrew E Yoakam",
    "wof:placetype":"venue"
},
  "geometry": {"coordinates":[-117.39009,33.920718],"type":"Point"}
}