{
  "type": "Feature",
  "properties": {
    "addr:full":"253 E Mesquite Ave Palm Springs CA 92264",
    "addr:housenumber":"253",
    "addr:postcode":"92264",
    "addr:street":"E Mesquite Ave",
    "iso:country":"US",
    "sg:address":"253 E Mesquite Ave",
    "sg:city":"Palm Springs",
    "sg:classifiers":[
        {
            "category":"Shopping",
            "subcategory":"Clothing, Apparel, & Fashions",
            "type":"Retail Goods"
        }
    ],
    "sg:phone":"+1 760 778 6732",
    "sg:postcode":"92264",
    "sg:province":"CA",
    "sg:tags":[
        "salvage",
        "surplus",
        "merchandise"
    ],
    "wof:name":"Ron Dale Co",
    "wof:placetype":"venue"
},
  "geometry": {"coordinates":[-116.543858,33.808518],"type":"Point"}
}