{
  "type": "Feature",
  "properties": {
    "addr:full":"4952 Charter Rd Rocklin CA 95765",
    "addr:housenumber":"4952",
    "addr:postcode":"95765",
    "addr:street":"Charter Rd",
    "iso:country":"US",
    "sg:address":"4952 Charter Rd",
    "sg:city":"Rocklin",
    "sg:classifiers":[
        {
            "category":"Professional",
            "subcategory":"Accounting & Tax Preparation",
            "type":"Services"
        }
    ],
    "sg:phone":"+1 916 768 6398",
    "sg:postcode":"95765",
    "sg:province":"CA",
    "sg:tags":[
        "accountant"
    ],
    "wof:name":"Robert A Fitzpatrick CPA",
    "wof:placetype":"venue"
},
  "geometry": {"coordinates":[-121.254828,38.825545],"type":"Point"}
}