{
  "type": "Feature",
  "properties": {
    "addr:full":"6233 Santa Teresa Blvd San Jose CA 95119",
    "addr:housenumber":"6233",
    "addr:postcode":"95119",
    "addr:street":"Santa Teresa Blvd",
    "iso:country":"US",
    "sg:address":"6233 Santa Teresa Blvd",
    "sg:city":"San Jose",
    "sg:classifiers":[
        {
            "category":"Food & Beverages",
            "subcategory":"Bakery",
            "type":"Retail Goods"
        }
    ],
    "sg:phone":"+1 408 226 6395",
    "sg:postcode":"95119",
    "sg:province":"CA",
    "sg:tags":[
        "doughnut"
    ],
    "wof:name":"Daily Donuts 2",
    "wof:placetype":"venue"
},
  "geometry": {"coordinates":[-121.803389,37.236921],"type":"Point"}
}