{
  "type": "Feature",
  "properties": {
    "iso:country":"US",
    "sg:address":"455 Brea Canyon Rd",
    "sg:city":"Walnut",
    "sg:classifiers":[
        {
            "category":"Freight",
            "type":"Transportation"
        }
    ],
    "sg:phone":"+1 909 594 0610",
    "sg:postcode":"91789",
    "sg:province":"CA",
    "sg:tags":[
        "operator",
        "local",
        "trucking"
    ],
    "wof:name":"Dependable Delivery",
    "wof:placetype":"venue"
},
  "geometry": {"coordinates":[-117.843391,34.014337],"type":"Point"}
}