{
  "type": "Feature",
  "properties": {
    "iso:country":"US",
    "sg:address":"5011 Wilson Landing Rd",
    "sg:city":"Chico",
    "sg:classifiers":[
        {
            "category":"Farming",
            "subcategory":"Livestock Farm",
            "type":"Manufacturing & Wholesale Goods"
        }
    ],
    "sg:phone":"+1 530 342 0577",
    "sg:postcode":"95973",
    "sg:province":"CA",
    "sg:tags":[
        "animal",
        "general"
    ],
    "wof:name":"Frank Steel Ranch Corp",
    "wof:placetype":"venue"
},
  "geometry": {"coordinates":[-121.944278,39.796745],"type":"Point"}
}