{
  "type": "Feature",
  "properties": {
    "addr:full":"4630 Song Ln Santa Maria CA 93455",
    "addr:housenumber":"4630",
    "addr:postcode":"93455",
    "addr:street":"Song Ln",
    "iso:country":"US",
    "sg:address":"4630 Song Ln",
    "sg:city":"Santa Maria",
    "sg:classifiers":[
        {
            "category":"Building & Trades",
            "subcategory":"Construction",
            "type":"Services"
        }
    ],
    "sg:phone":"+1 805 937 3233",
    "sg:postcode":"93455",
    "sg:province":"CA",
    "sg:tags":[
        "contractor"
    ],
    "wof:name":"Halsell Builders",
    "wof:placetype":"venue"
},
  "geometry": {"coordinates":[-120.46096199999999,34.871879],"type":"Point"}
}