{
  "type": "Feature",
  "properties": {
    "addr:full":"4564 E Los Angeles Ave Simi Valley CA 93063",
    "addr:housenumber":"4564",
    "addr:postcode":"93063",
    "addr:street":"E Los Angeles Ave",
    "iso:country":"US",
    "sg:address":"4564 E Los Angeles Ave",
    "sg:city":"Simi Valley",
    "sg:classifiers":[
        {
            "category":"Manufacturing",
            "subcategory":"Tools & Machinery",
            "type":"Manufacturing & Wholesale Goods"
        }
    ],
    "sg:phone":"+1 805 526 7808",
    "sg:postcode":"93063",
    "sg:province":"CA",
    "sg:tags":[
        "industrial",
        "mfg"
    ],
    "wof:name":"Metal Tech",
    "wof:placetype":"venue"
},
  "geometry": {"coordinates":[-118.705422,34.271601],"type":"Point"}
}