{
  "type": "Feature",
  "properties": {
    "addr:full":"2246 Caminito Preciosa Sur La Jolla CA 92037",
    "addr:housenumber":"2246",
    "addr:postcode":"92037",
    "addr:street":"Caminito Preciosa Sur",
    "iso:country":"US",
    "sg:address":"2246 Caminito Preciosa Sur",
    "sg:city":"La Jolla",
    "sg:classifiers":[
        {
            "category":"Real Estate",
            "subcategory":"Real Estate Operator",
            "type":"Services"
        }
    ],
    "sg:phone":"+1 858 459 4845",
    "sg:postcode":"92037",
    "sg:province":"CA",
    "sg:tags":[
        "apartment"
    ],
    "sg:website":"www.treetops.com",
    "wof:name":"Treetops",
    "wof:placetype":"venue"
},
  "geometry": {"coordinates":[-117.234177,32.818689],"type":"Point"}
}