{
  "type": "Feature",
  "properties": {
    "addr:full":"14501 S Bascom Avenue Los Gatos CA 95032",
    "addr:housenumber":"14501",
    "addr:postcode":"95032",
    "addr:street":"S Bascom Avenue",
    "iso:country":"US",
    "sg:address":"14501 S Bascom Avenue",
    "sg:city":"Los Gatos",
    "sg:classifiers":[
        {
            "category":"Health Services",
            "subcategory":"Dentist",
            "type":"Services"
        }
    ],
    "sg:phone":"+1 408 371 4050",
    "sg:postcode":"95032",
    "sg:province":"CA",
    "wof:name":"Childs John R DDS",
    "wof:placetype":"venue"
},
  "geometry": {"coordinates":[-121.948545,37.257738],"type":"Point"}
}