{
  "type": "Feature",
  "properties": {
    "addr:full":"6138 W Pico Blvd Los Angeles CA 90035",
    "addr:housenumber":"6138",
    "addr:postcode":"90035",
    "addr:street":"W Pico Blvd",
    "iso:country":"US",
    "sg:address":"6138 W Pico Blvd",
    "sg:city":"Los Angeles",
    "sg:classifiers":[
        {
            "category":"Organizations",
            "subcategory":"Professional Association",
            "type":"Services"
        }
    ],
    "sg:phone":"+1 323 852 4723",
    "sg:postcode":"90035",
    "sg:province":"CA",
    "wof:name":"Custom Upholsterers & Dcrtrs",
    "wof:placetype":"venue"
},
  "geometry": {"coordinates":[-118.374562,34.052919],"type":"Point"}
}