{
  "type": "Feature",
  "properties": {
    "iso:country":"US",
    "sg:address":"4882 W 145th St",
    "sg:city":"Hawthorne",
    "sg:classifiers":[
        {
            "category":"Freight",
            "type":"Transportation"
        }
    ],
    "sg:phone":"+1 310 676 6233",
    "sg:postcode":"90250",
    "sg:province":"CA",
    "wof:name":"A M Freight Logistics Inc",
    "wof:placetype":"venue"
},
  "geometry": {"coordinates":[-118.363608,33.899583],"type":"Point"}
}