{
  "type": "Feature",
  "properties": {
    "iso:country":"US",
    "sg:address":"3663 W 6th St",
    "sg:city":"Los Angeles",
    "sg:classifiers":[
        {
            "category":"Health Services",
            "subcategory":"Chiropractor",
            "type":"Services"
        }
    ],
    "sg:phone":"+1 213 383 9771",
    "sg:postcode":"90020",
    "sg:province":"CA",
    "wof:name":"Christopher Kim DC",
    "wof:placetype":"venue"
},
  "geometry": {"coordinates":[-118.302593,34.063629],"type":"Point"}
}