{
  "type": "Feature",
  "properties": {
    "iso:country":"US",
    "sg:address":"951 Martin Luther King Jr Ave",
    "sg:city":"Long Beach",
    "sg:classifiers":[
        {
            "category":"Retail",
            "subcategory":"Auto Repair",
            "type":"Services"
        }
    ],
    "sg:phone":"+1 562 901 9201",
    "sg:postcode":"90813",
    "sg:province":"CA",
    "wof:name":"D R Auto Repair",
    "wof:placetype":"venue"
},
  "geometry": {"coordinates":[-118.18084399999999,33.778538],"type":"Point"}
}