{
  "type": "Feature",
  "properties": {
    "iso:country":"US",
    "sg:address":"3416 Farmington Rd",
    "sg:city":"Stockton",
    "sg:classifiers":[
        {
            "category":"Travel",
            "subcategory":"Hotels & Motels",
            "type":"Entertainment"
        }
    ],
    "sg:phone":"+1 209 941 9000",
    "sg:postcode":"95205",
    "sg:province":"CA",
    "wof:name":"Sierra Motel",
    "wof:placetype":"venue"
},
  "geometry": {"coordinates":[-121.235953,37.939969],"type":"Point"}
}