{
  "type": "Feature",
  "properties": {
    "addr:full":"6 Valley View Dr Orinda CA 94563",
    "addr:housenumber":"6",
    "addr:postcode":"94563",
    "addr:street":"Valley View Dr",
    "iso:country":"US",
    "sg:address":"6 Valley View Dr",
    "sg:city":"Orinda",
    "sg:classifiers":[
        {
            "category":"Manufacturing",
            "subcategory":"Printing",
            "type":"Manufacturing & Wholesale Goods"
        }
    ],
    "sg:phone":"+1 925 253 1123",
    "sg:postcode":"94563",
    "sg:province":"CA",
    "sg:tags":[
        "publisher",
        "software"
    ],
    "wof:name":"Berkeley Transportation System",
    "wof:placetype":"venue"
},
  "geometry": {"coordinates":[-122.158001,37.857115],"type":"Point"}
}