{
  "type": "Feature",
  "properties": {
    "iso:country":"US",
    "sg:address":"661 S Harvard Blvd # 166",
    "sg:city":"Los Angeles",
    "sg:classifiers":[
        {
            "category":"Bars & Pubs",
            "subcategory":"Sports Bar",
            "type":"Food & Drink"
        }
    ],
    "sg:phone":"+1 213 383 4789",
    "sg:postcode":"90005",
    "sg:province":"CA",
    "sg:tags":[
        "hall",
        "pool"
    ],
    "wof:name":"Q Sports Bar",
    "wof:placetype":"venue"
},
  "geometry": {"coordinates":[-118.304192,34.061226],"type":"Point"}
}