{
  "type": "Feature",
  "properties": {
    "addr:full":"5108 Holt Blvd Montclair CA 91763",
    "addr:housenumber":"5108",
    "addr:postcode":"91763",
    "addr:street":"Holt Blvd",
    "iso:country":"US",
    "sg:address":"5108 Holt Blvd",
    "sg:city":"Montclair",
    "sg:classifiers":[
        {
            "category":"Insurance",
            "subcategory":"Insurance Agent",
            "type":"Services"
        }
    ],
    "sg:phone":"+1 909 621 9500",
    "sg:postcode":"91763",
    "sg:province":"CA",
    "wof:name":"Livingwell Insurance Svc",
    "wof:placetype":"venue"
},
  "geometry": {"coordinates":[-117.693674,34.06328],"type":"Point"}
}