{
  "type": "Feature",
  "properties": {
    "addr:full":"1422 Mendocino Ave Santa Rosa CA 95401",
    "addr:housenumber":"1422",
    "addr:postcode":"95401",
    "addr:street":"Mendocino Ave",
    "iso:country":"US",
    "sg:address":"1422 Mendocino Ave",
    "sg:city":"Santa Rosa",
    "sg:classifiers":[
        {
            "category":"Wholesale",
            "subcategory":"Non-durable Goods",
            "type":"Manufacturing & Wholesale Goods"
        }
    ],
    "sg:phone":"+1 707 545 7009",
    "sg:postcode":"95401",
    "sg:province":"CA",
    "wof:name":"Music Biz",
    "wof:placetype":"venue"
},
  "geometry": {"coordinates":[-122.717293,38.454443],"type":"Point"}
}