{
  "type": "Feature",
  "properties": {
    "addr:full":"3751 4th Ave Glendale CA 91214",
    "addr:housenumber":"3751",
    "addr:postcode":"91214",
    "addr:street":"4Th Ave",
    "iso:country":"US",
    "sg:address":"3751 4th Ave",
    "sg:city":"Glendale",
    "sg:classifiers":[
        {
            "category":"Communications",
            "subcategory":"Film & Video Production",
            "type":"Services"
        }
    ],
    "sg:phone":"+1 818 541 0019",
    "sg:postcode":"91214",
    "sg:province":"CA",
    "sg:tags":[
        "taping"
    ],
    "wof:name":"Digifine Video Svc",
    "wof:placetype":"venue"
},
  "geometry": {"coordinates":[-118.260622,34.234341],"type":"Point"}
}