{
  "type": "Feature",
  "properties": {
    "addr:full":"4033 W Chapman Ave Orange CA 92868",
    "addr:housenumber":"4033",
    "addr:postcode":"92868",
    "addr:street":"W Chapman Ave",
    "iso:country":"US",
    "sg:address":"4033 W Chapman Ave",
    "sg:city":"Orange",
    "sg:classifiers":[
        {
            "category":"Banks & Credit Unions",
            "subcategory":"Investment Brokerage",
            "type":"Services"
        },
        {
            "category":"Cinema",
            "subcategory":"Movie Rental",
            "type":"Entertainment"
        },
        {
            "category":"Shopping",
            "subcategory":"Computers & Home Electronics",
            "type":"Retail Goods"
        }
    ],
    "sg:phone":"+1 714 938 1437",
    "sg:postcode":"92868",
    "sg:province":"CA",
    "sg:tags":[
        "dvd",
        "sale",
        "dvds-rental",
        "game",
        "tape",
        "video"
    ],
    "wof:name":"House Of Dvds",
    "wof:placetype":"venue"
},
  "geometry": {"coordinates":[-117.896969,33.789117],"type":"Point"}
}