{
  "type": "Feature",
  "properties": {
    "iso:country":"US",
    "sg:address":"1835 el Cajon Blvd",
    "sg:city":"San Diego",
    "sg:classifiers":[
        {
            "category":"Social Services",
            "type":"Services"
        }
    ],
    "sg:phone":"+1 619 297 0012",
    "sg:postcode":"92103",
    "sg:province":"CA",
    "sg:tags":[
        "worker"
    ],
    "wof:name":"Chris Diani",
    "wof:placetype":"venue"
},
  "geometry": {"coordinates":[-117.14595,32.755169],"type":"Point"}
}