{
  "type": "Feature",
  "properties": {
    "addr:full":"1214 Oak St Alameda CA 94502",
    "addr:housenumber":"1214",
    "addr:postcode":"94502",
    "addr:street":"Oak St",
    "iso:country":"US",
    "sg:address":"1214 Oak St",
    "sg:city":"Alameda",
    "sg:classifiers":[
        {
            "category":"Shopping",
            "subcategory":"Jewelry",
            "type":"Retail Goods"
        }
    ],
    "sg:phone":"+1 510 814 6542",
    "sg:postcode":"94502",
    "sg:province":"CA",
    "wof:name":"To Herb With Love",
    "wof:placetype":"venue"
},
  "geometry": {"coordinates":[-122.24527,37.763252],"type":"Point"}
}