{
  "type": "Feature",
  "properties": {
    "iso:country":"US",
    "sg:address":"5837 Gibson Pl",
    "sg:city":"Granite Bay",
    "sg:classifiers":[
        {
            "category":"Wholesale",
            "subcategory":"Machinery & Supplies",
            "type":"Manufacturing & Wholesale Goods"
        }
    ],
    "sg:phone":"+1 916 791 2708",
    "sg:postcode":"95746",
    "sg:province":"CA",
    "sg:tags":[
        "abrasive"
    ],
    "wof:name":"Paul Rizzo Sales Co",
    "wof:placetype":"venue"
},
  "geometry": {"coordinates":[-121.195271,38.756034],"type":"Point"}
}