{
  "type": "Feature",
  "properties": {
    "iso:country":"US",
    "sg:address":"822 Campus Ave",
    "sg:city":"Redlands",
    "sg:classifiers":[
        {
            "category":"Building & Trades",
            "subcategory":"Construction",
            "type":"Services"
        }
    ],
    "sg:phone":"+1 909 798 0755",
    "sg:postcode":"92374",
    "sg:province":"CA",
    "sg:tags":[
        "contractor"
    ],
    "wof:name":"E E Shirtcliff",
    "wof:placetype":"venue"
},
  "geometry": {"coordinates":[-117.171761,34.065165],"type":"Point"}
}