{
  "type": "Feature",
  "properties": {
    "addr:full":"2438 E 11th St Los Angeles CA 90021",
    "addr:housenumber":"2438",
    "addr:postcode":"90021",
    "addr:street":"E 11Th St",
    "iso:country":"US",
    "sg:address":"2438 E 11th St",
    "sg:city":"Los Angeles",
    "sg:classifiers":[
        {
            "category":"Shopping",
            "type":"Retail Goods"
        }
    ],
    "sg:phone":"+1 323 623 6676",
    "sg:postcode":"90021",
    "sg:province":"CA",
    "sg:tags":[
        "picture"
    ],
    "wof:name":"Dogwood Publishing Inc",
    "wof:placetype":"venue"
},
  "geometry": {"coordinates":[-118.22906500000001,34.023585],"type":"Point"}
}