{
  "type": "Feature",
  "properties": {
    "iso:country":"US",
    "sg:address":"2438 E 11th St",
    "sg:city":"Los Angeles",
    "sg:classifiers":[
        {
            "category":"Shopping",
            "type":"Retail Goods"
        }
    ],
    "sg:phone":"+1 323 623 6676",
    "sg:postcode":"90021",
    "sg:province":"CA",
    "sg:tags":[
        "picture"
    ],
    "wof:name":"Dogwood Publishing Inc",
    "wof:placetype":"venue"
},
  "geometry": {"coordinates":[-118.229065,34.023585],"type":"Point"}
}