{
  "type": "Feature",
  "properties": {
    "addr:full":"900 W. James M. Wood Blvd. Los Angeles CA 90015",
    "addr:housenumber":"900",
    "addr:postcode":"90015",
    "addr:street":"W. James M. Wood Blvd.",
    "iso:country":"US",
    "sg:address":"900 W. James M. Wood Blvd.",
    "sg:city":"Los Angeles",
    "sg:classifiers":[
        {
            "category":"Organizations",
            "subcategory":"Religious Organization",
            "type":"Services"
        }
    ],
    "sg:phone":"+1 213 553 3273",
    "sg:postcode":"90015",
    "sg:province":"CA",
    "sg:website":"salvationarmysocal.org",
    "wof:name":"The Salvation Army",
    "wof:placetype":"venue"
},
  "geometry": {"coordinates":[-118.265263,34.046793],"type":"Point"}
}