{
  "type": "Feature",
  "properties": {
    "addr:full":"860 W Olive Ave Merced CA 95348",
    "addr:housenumber":"860",
    "addr:postcode":"95348",
    "addr:street":"W Olive Ave",
    "iso:country":"US",
    "sg:address":"860 W Olive Ave",
    "sg:city":"Merced",
    "sg:classifiers":[
        {
            "category":"Banks & Credit Unions",
            "subcategory":"Investment Brokerage",
            "type":"Services"
        }
    ],
    "sg:phone":"+1 209 723 3911",
    "sg:postcode":"95348",
    "sg:province":"CA",
    "sg:tags":[
        "stock",
        "bond"
    ],
    "wof:name":"UBS Financial Svc",
    "wof:placetype":"venue"
},
  "geometry": {"coordinates":[-120.48326900000001,37.31917],"type":"Point"}
}