{
  "type": "Feature",
  "properties": {
    "iso:country":"US",
    "sg:address":"1709 Freedom Blvd",
    "sg:city":"Freedom",
    "sg:classifiers":[
        {
            "category":"Retail",
            "subcategory":"Auto Repair",
            "type":"Services"
        }
    ],
    "sg:phone":"+1 831 728 3751",
    "sg:postcode":"95019",
    "sg:province":"CA",
    "sg:tags":[
        "machine",
        "automobile",
        "shop"
    ],
    "wof:name":"Marino's Automotive Mach Shop",
    "wof:placetype":"venue"
},
  "geometry": {"coordinates":[-121.77209999999999,36.933825],"type":"Point"}
}