{
  "type": "Feature",
  "properties": {
    "addr:full":"555 W Tefft St Ste 2 Nipomo CA 93444",
    "addr:housenumber":"555",
    "addr:postcode":"93444",
    "addr:street":"W Tefft St Ste 2",
    "iso:country":"US",
    "sg:address":"555 W Tefft St Ste 2",
    "sg:city":"Nipomo",
    "sg:classifiers":[
        {
            "category":"Health Services",
            "subcategory":"Chiropractor",
            "type":"Services"
        }
    ],
    "sg:phone":"+1 805 931 0300",
    "sg:postcode":"93444",
    "sg:province":"CA",
    "sg:tags":[
        "chiropractic"
    ],
    "wof:name":"California Chiropractic",
    "wof:placetype":"venue"
},
  "geometry": {"coordinates":[-120.485874,35.036157],"type":"Point"}
}