{
  "type": "Feature",
  "properties": {
    "addr:full":"2607 W Pomona Blvd Pomona CA 91768",
    "addr:housenumber":"2607",
    "addr:postcode":"91768",
    "addr:street":"W Pomona Blvd",
    "iso:country":"US",
    "sg:address":"2607 W Pomona Blvd",
    "sg:city":"Pomona",
    "sg:classifiers":[
        {
            "category":"Professional",
            "subcategory":"Engineering",
            "type":"Services"
        }
    ],
    "sg:phone":"+1 909 869 6316",
    "sg:postcode":"91768",
    "sg:province":"CA",
    "sg:tags":[
        "engineer"
    ],
    "wof:name":"Ap Engineers",
    "wof:placetype":"venue"
},
  "geometry": {"coordinates":[-117.79903,34.055282],"type":"Point"}
}