{
  "type": "Feature",
  "properties": {
    "addr:full":"3910 Long Beach Blvd Long Beach CA 90807",
    "addr:housenumber":"3910",
    "addr:postcode":"90807",
    "addr:street":"Long Beach Blvd",
    "iso:country":"US",
    "sg:address":"3910 Long Beach Blvd",
    "sg:city":"Long Beach",
    "sg:classifiers":[
        {
            "category":"Restaurant",
            "type":"Food & Drink"
        }
    ],
    "sg:phone":"+1 562 427 5000",
    "sg:postcode":"90807",
    "sg:province":"CA",
    "sg:tags":[
        "pizza"
    ],
    "wof:name":"Papa Johns Pizza",
    "wof:placetype":"venue"
},
  "geometry": {"coordinates":[-118.189003,33.829498],"type":"Point"}
}