{
  "type": "Feature",
  "properties": {
    "iso:country":"US",
    "sg:address":"2171 Junipero Serra Blvd Ste 590",
    "sg:city":"Daly City",
    "sg:classifiers":[
        {
            "category":"Health Services",
            "subcategory":"Chiropractor",
            "type":"Services"
        }
    ],
    "sg:phone":"+1 650 756 9003",
    "sg:postcode":"94014",
    "sg:province":"CA",
    "sg:website":"drdanchan.com",
    "wof:name":"Danny K L Chan, DC",
    "wof:placetype":"venue"
},
  "geometry": {"coordinates":[-122.47041299999999,37.698347],"type":"Point"}
}