{
  "type": "Feature",
  "properties": {
    "addr:full":"7761 College Town Dr Sacramento CA 95826",
    "addr:housenumber":"7761",
    "addr:postcode":"95826",
    "addr:street":"College Town Dr",
    "iso:country":"US",
    "sg:address":"7761 College Town Dr",
    "sg:city":"Sacramento",
    "sg:classifiers":[
        {
            "category":"Real Estate",
            "subcategory":"Real Estate Services",
            "type":"Services"
        },
        {
            "category":"Building & Trades",
            "subcategory":"Cleaning & Sanitation",
            "type":"Services"
        }
    ],
    "sg:phone":"+1 916 383 3650",
    "sg:postcode":"95826",
    "sg:province":"CA",
    "sg:tags":[
        "maintenance",
        "cleaners-interior"
    ],
    "wof:name":"E BMC Maintainance Director",
    "wof:placetype":"venue"
},
  "geometry": {"coordinates":[-121.41162300000001,38.554233],"type":"Point"}
}