{
  "type": "Feature",
  "properties": {
    "addr:full":"257 Kent Pl San Ramon CA 94583",
    "addr:housenumber":"257",
    "addr:postcode":"94583",
    "addr:street":"Kent Pl",
    "iso:country":"US",
    "sg:address":"257 Kent Pl",
    "sg:city":"San Ramon",
    "sg:classifiers":[
        {
            "category":"Building & Trades",
            "subcategory":"Landscaping Services",
            "type":"Services"
        }
    ],
    "sg:phone":"+1 925 875 9183",
    "sg:postcode":"94583",
    "sg:province":"CA",
    "sg:tags":[
        "designer",
        "landscape"
    ],
    "wof:name":"Daryl G Morrow Co",
    "wof:placetype":"venue"
},
  "geometry": {"coordinates":[-121.942008,37.727112],"type":"Point"}
}