{
  "type": "Feature",
  "properties": {
    "addr:full":"11580 W Pico Boulevard Los Angeles CA 90064",
    "addr:housenumber":"11580",
    "addr:postcode":"90064",
    "addr:street":"W Pico Boulevard",
    "iso:country":"US",
    "sg:address":"11580 W Pico Boulevard",
    "sg:city":"Los Angeles",
    "sg:classifiers":[
        {
            "category":"Retail",
            "subcategory":"Auto Repair",
            "type":"Services"
        }
    ],
    "sg:phone":"+1 310 312 6740",
    "sg:postcode":"90064",
    "sg:province":"CA",
    "wof:name":"First Class Auto Service &",
    "wof:placetype":"venue"
},
  "geometry": {"coordinates":[-118.443832,34.032665],"type":"Point"}
}