{
  "type": "Feature",
  "properties": {
    "iso:country":"US",
    "sg:address":"2030 Chestnut St",
    "sg:city":"San Francisco",
    "sg:classifiers":[
        {
            "category":"Shopping",
            "subcategory":"Shoes",
            "type":"Retail Goods"
        }
    ],
    "sg:phone":"+1 415 673 4736",
    "sg:postcode":"94123",
    "sg:province":"CA",
    "wof:name":"Smash Shoes",
    "wof:placetype":"venue"
},
  "geometry": {"coordinates":[-122.43678300000001,37.800842],"type":"Point"}
}