{
  "type": "Feature",
  "properties": {
    "iso:country":"US",
    "sg:address":"517 S Broadway",
    "sg:city":"Santa Ana",
    "sg:classifiers":[
        {
            "category":"Real Estate",
            "subcategory":"Real Estate Agent",
            "type":"Services"
        }
    ],
    "sg:phone":"+1 714 836 1700",
    "sg:postcode":"92701",
    "sg:province":"CA",
    "sg:tags":[
        "house",
        "motel",
        "apartment",
        "broker"
    ],
    "wof:name":"Apartments OC",
    "wof:placetype":"venue"
},
  "geometry": {"coordinates":[-117.869705,33.739654],"type":"Point"}
}