{
  "type": "Feature",
  "properties": {
    "addr:full":"4747 Viewridge Avenue San Diego CA 92123",
    "addr:housenumber":"4747",
    "addr:postcode":"92123",
    "addr:street":"Viewridge Avenue",
    "iso:country":"US",
    "sg:address":"4747 Viewridge Avenue",
    "sg:city":"San Diego",
    "sg:classifiers":[
        {
            "category":"Professional",
            "subcategory":"Employment Agencies",
            "type":"Services"
        }
    ],
    "sg:phone":"+1 858 571 7881",
    "sg:postcode":"92123",
    "sg:province":"CA",
    "wof:name":"General Ledger Resourses",
    "wof:placetype":"venue"
},
  "geometry": {"coordinates":[-117.133892,32.802479],"type":"Point"}
}