{
  "type": "Feature",
  "properties": {
    "addr:full":"5519 Mission Rd Bonsall CA 92003",
    "addr:housenumber":"5519",
    "addr:postcode":"92003",
    "addr:street":"Mission Rd",
    "iso:country":"US",
    "sg:address":"5519 Mission Rd",
    "sg:city":"Bonsall",
    "sg:classifiers":[
        {
            "category":"Real Estate",
            "subcategory":"Real Estate Agent",
            "type":"Services"
        }
    ],
    "sg:phone":"+1 760 732 3355",
    "sg:postcode":"92003",
    "sg:province":"CA",
    "wof:name":"Maverick Real Estate Company",
    "wof:placetype":"venue"
},
  "geometry": {"coordinates":[-117.225668,33.289435],"type":"Point"}
}