{
  "type": "Feature",
  "properties": {
    "iso:country":"US",
    "sg:address":"13 Glenwood Dr",
    "sg:city":"Napa",
    "sg:classifiers":[
        {
            "category":"Education",
            "subcategory":"Dance Studio",
            "type":"Public Place"
        }
    ],
    "sg:phone":"+1 707 251 9200",
    "sg:postcode":"94559",
    "sg:province":"CA",
    "sg:tags":[
        "instruction",
        "dancing"
    ],
    "wof:name":"Tami Nixon's Childrens Dance",
    "wof:placetype":"venue"
},
  "geometry": {"coordinates":[-122.298209,38.302842],"type":"Point"}
}