{
  "type": "Feature",
  "properties": {
    "iso:country":"US",
    "sg:address":"3133 W March Ln",
    "sg:city":"Stockton",
    "sg:classifiers":[
        {
            "category":"Insurance",
            "subcategory":"Insurance Agent",
            "type":"Services"
        }
    ],
    "sg:phone":"+1 209 957 9551",
    "sg:postcode":"95219",
    "sg:province":"CA",
    "wof:name":"Met Life",
    "wof:placetype":"venue"
},
  "geometry": {"coordinates":[-121.351793,37.984101],"type":"Point"}
}