{
  "type": "Feature",
  "properties": {
    "addr:full":"4397 Tujunga Ave Ste H Studio City CA 91604",
    "addr:housenumber":"4397",
    "addr:postcode":"91604",
    "addr:street":"Tujunga Ave Ste H",
    "iso:country":"US",
    "sg:address":"4397 Tujunga Ave Ste H",
    "sg:city":"Studio City",
    "sg:classifiers":[
        {
            "category":"Donuts",
            "subcategory":"None",
            "type":"Food & Drink"
        }
    ],
    "sg:phone":"+1 818 760 7279",
    "sg:postcode":"91604",
    "sg:province":"CA",
    "wof:name":"Holly Donut Shop",
    "wof:placetype":"venue"
},
  "geometry": {"coordinates":[-118.378998,34.1502],"type":"Point"}
}