{
  "type": "Feature",
  "properties": {
    "iso:country":"US",
    "sg:address":"11564 Rosecrans Ave",
    "sg:city":"Norwalk",
    "sg:classifiers":[
        {
            "category":"Personal",
            "type":"Services"
        }
    ],
    "sg:phone":"+1 562 929 4880",
    "sg:postcode":"90650",
    "sg:province":"CA",
    "sg:tags":[
        "wear",
        "formal"
    ],
    "wof:name":"Gabriel's Norwalk Tuxedos",
    "wof:placetype":"venue"
},
  "geometry": {"coordinates":[-118.086759,33.902047],"type":"Point"}
}