{
  "type": "Feature",
  "properties": {
    "addr:full":"2462 Atlas Peak Rd Napa CA 94558",
    "addr:housenumber":"2462",
    "addr:postcode":"94558",
    "addr:street":"Atlas Peak Rd",
    "iso:country":"US",
    "sg:address":"2462 Atlas Peak Rd",
    "sg:city":"Napa",
    "sg:classifiers":[
        {
            "category":"Retail",
            "subcategory":"Animal Services",
            "type":"Services"
        }
    ],
    "sg:phone":"+1 707 258 0315",
    "sg:postcode":"94558",
    "sg:province":"CA",
    "wof:name":"Waste Abatement Resources",
    "wof:placetype":"venue"
},
  "geometry": {"coordinates":[-122.241387,38.382498],"type":"Point"}
}