{
  "type": "Feature",
  "properties": {
    "iso:country":"US",
    "sg:address":"433 Mason St",
    "sg:city":"San Francisco",
    "sg:classifiers":[
        {
            "category":"Sports & Exercise",
            "subcategory":"Bicycle Rental",
            "type":"Entertainment"
        }
    ],
    "sg:phone":"+1 415 202 8888",
    "sg:postcode":"94102",
    "sg:province":"CA",
    "sg:tags":[
        "bike"
    ],
    "sg:website":"blazingsaddles.com",
    "wof:name":"Blazing Saddles Bike Rentals",
    "wof:placetype":"venue"
},
  "geometry": {"coordinates":[-122.41014,37.787522],"type":"Point"}
}