{
  "type": "Feature",
  "properties": {
    "iso:country":"US",
    "sg:address":"3035 Pacific Coast Hwy",
    "sg:city":"Torrance",
    "sg:classifiers":[
        {
            "category":"Autos & Motor Vehicles",
            "subcategory":"Automobile Sales",
            "type":"Retail Goods"
        }
    ],
    "sg:phone":"+1 310 325 5555",
    "sg:postcode":"90505",
    "sg:province":"CA",
    "sg:tags":[
        "car"
    ],
    "sg:website":"www.infinitiofsouthbay.com",
    "wof:name":"Infiniti Southbay",
    "wof:placetype":"venue"
},
  "geometry": {"coordinates":[-118.339175,33.796657],"type":"Point"}
}