{
  "type": "Feature",
  "properties": {
    "addr:full":"7795 Gabor St Valley Springs CA 95252",
    "addr:housenumber":"7795",
    "addr:postcode":"95252",
    "addr:street":"Gabor St",
    "iso:country":"US",
    "sg:address":"7795 Gabor St",
    "sg:city":"Valley Springs",
    "sg:classifiers":[
        {
            "category":"Building & Trades",
            "subcategory":"Pest Control",
            "type":"Services"
        }
    ],
    "sg:phone":"+1 209 786 3549",
    "sg:postcode":"95252",
    "sg:province":"CA",
    "wof:name":"Curt Bibb Pest Control",
    "wof:placetype":"venue"
},
  "geometry": {"coordinates":[-120.8683,38.11157],"type":"Point"}
}