{
  "type": "Feature",
  "properties": {
    "iso:country":"US",
    "sg:address":"9237 Mapleview Way",
    "sg:city":"Elk Grove",
    "sg:classifiers":[
        {
            "category":"Shopping",
            "subcategory":"Musical Instruments",
            "type":"Retail Goods"
        }
    ],
    "sg:phone":"+1 916 716 7070",
    "sg:postcode":"95758",
    "sg:province":"CA",
    "wof:name":"Vicki Cromwell",
    "wof:placetype":"venue"
},
  "geometry": {"coordinates":[-121.422797,38.420821],"type":"Point"}
}