{
  "type": "Feature",
  "properties": {
    "iso:country":"US",
    "sg:address":"240 Bonnywood Way",
    "sg:city":"Santa Cruz",
    "sg:classifiers":[
        {
            "category":"Building & Trades",
            "subcategory":"Cleaning & Sanitation",
            "type":"Services"
        }
    ],
    "sg:phone":"+1 831 688 9770",
    "sg:postcode":"95060",
    "sg:province":"CA",
    "sg:tags":[
        "janitor"
    ],
    "wof:name":"Handy Helpers",
    "wof:placetype":"venue"
},
  "geometry": {"coordinates":[-122.104604,37.04202],"type":"Point"}
}