{
  "type": "Feature",
  "properties": {
    "addr:full":"7101 Jurupa Ave Ste 12 Riverside CA 92504",
    "addr:housenumber":"7101",
    "addr:postcode":"92504",
    "addr:street":"Jurupa Ave Ste 12",
    "iso:country":"US",
    "sg:address":"7101 Jurupa Ave Ste 12",
    "sg:city":"Riverside",
    "sg:classifiers":[
        {
            "category":"Health Services",
            "subcategory":"Doctor",
            "type":"Services"
        }
    ],
    "sg:phone":"+1 951 283 6915",
    "sg:postcode":"92504",
    "sg:province":"CA",
    "sg:tags":[
        "medicine",
        "physician",
        "forensic",
        "surgeons"
    ],
    "wof:name":"Gruning Precision",
    "wof:placetype":"venue"
},
  "geometry": {"coordinates":[-117.44944099999999,33.960233],"type":"Point"}
}