{
  "type": "Feature",
  "properties": {
    "iso:country":"US",
    "sg:address":"1020 W 164th St",
    "sg:city":"Gardena",
    "sg:classifiers":[
        {
            "category":"Home & Garden",
            "subcategory":"Household Appliances",
            "type":"Retail Goods"
        },
        {
            "category":"Home & Garden",
            "subcategory":"Furniture",
            "type":"Retail Goods"
        }
    ],
    "sg:phone":"+1 310 715 1069",
    "sg:postcode":"90247",
    "sg:province":"CA",
    "sg:tags":[
        "repair",
        "store"
    ],
    "sg:website":"www.kingscredit.com",
    "wof:name":"Kings of Credit",
    "wof:placetype":"venue"
},
  "geometry": {"coordinates":[-118.292213,33.882227],"type":"Point"}
}