{
  "type": "Feature",
  "properties": {
    "addr:full":"923 Berryessa Rd San Jose CA 95133",
    "addr:housenumber":"923",
    "addr:postcode":"95133",
    "addr:street":"Berryessa Rd",
    "iso:country":"US",
    "sg:address":"923 Berryessa Rd",
    "sg:city":"San Jose",
    "sg:classifiers":[
        {
            "category":"Manufacturing",
            "subcategory":"Electronics",
            "type":"Manufacturing & Wholesale Goods"
        }
    ],
    "sg:phone":"+1 408 727 9770",
    "sg:postcode":"95133",
    "sg:province":"CA",
    "sg:tags":[
        "printed",
        "circuit",
        "etched"
    ],
    "sg:website":"www.hytekservices.com",
    "wof:name":"Hytek",
    "wof:placetype":"venue"
},
  "geometry": {"coordinates":[-121.886683,37.363248],"type":"Point"}
}