{
  "type": "Feature",
  "properties": {
    "iso:country":"US",
    "sg:address":"37425 Sycamore St",
    "sg:city":"Newark",
    "sg:classifiers":[
        {
            "category":"Railroad",
            "type":"Transportation"
        }
    ],
    "sg:phone":"+1 510 797 2430",
    "sg:postcode":"94560",
    "sg:province":"CA",
    "sg:tags":[
        "rail"
    ],
    "wof:name":"Union Pacific Railroad",
    "wof:placetype":"venue"
},
  "geometry": {"coordinates":[-122.032217,37.526853],"type":"Point"}
}