{
  "type": "Feature",
  "properties": {
    "iso:country":"US",
    "sg:address":"2841 Canon St",
    "sg:city":"San Diego",
    "sg:classifiers":[
        {
            "category":"Professional",
            "subcategory":"Business Services",
            "type":"Services"
        }
    ],
    "sg:phone":"+1 619 226 4565",
    "sg:postcode":"92106",
    "sg:province":"CA",
    "sg:tags":[
        "interior",
        "consultant",
        "design",
        "decorator"
    ],
    "sg:website":"www.lindamedinainteriordesign.com",
    "wof:name":"Linda Medina Interior Design",
    "wof:placetype":"venue"
},
  "geometry": {"coordinates":[-117.230498,32.720567],"type":"Point"}
}