{
  "type": "Feature",
  "properties": {
    "addr:full":"440 Locksley Ct Paradise CA 95969",
    "addr:housenumber":"440",
    "addr:postcode":"95969",
    "addr:street":"Locksley Ct",
    "iso:country":"US",
    "sg:address":"440 Locksley Ct",
    "sg:city":"Paradise",
    "sg:classifiers":[
        {
            "category":"Professional",
            "subcategory":"Business Services",
            "type":"Services"
        }
    ],
    "sg:phone":"+1 530 872 1841",
    "sg:postcode":"95969",
    "sg:province":"CA",
    "sg:tags":[
        "interior",
        "consultant",
        "design",
        "decorator"
    ],
    "wof:name":"Absolute Interiors",
    "wof:placetype":"venue"
},
  "geometry": {"coordinates":[-121.636883,39.761016],"type":"Point"}
}