{
  "type": "Feature",
  "properties": {
    "addr:full":"2348 30th St San Diego CA 92104",
    "addr:housenumber":"2348",
    "addr:postcode":"92104",
    "addr:street":"30Th St",
    "iso:country":"US",
    "sg:address":"2348 30th St",
    "sg:city":"San Diego",
    "sg:classifiers":[
        {
            "category":"Building & Trades",
            "subcategory":"Plumbing",
            "type":"Services"
        }
    ],
    "sg:phone":"+1 619 282 9242",
    "sg:postcode":"92104",
    "sg:province":"CA",
    "sg:tags":[
        "plumbing",
        "contractor"
    ],
    "wof:name":"Goforth Plumbing & Drain Svc",
    "wof:placetype":"venue"
},
  "geometry": {"coordinates":[-117.12962,32.730572],"type":"Point"}
}