{
  "type": "Feature",
  "properties": {
    "addr:full":"4286 Old Railroad Grade Rd Mckinleyville CA 95519",
    "addr:housenumber":"4286",
    "addr:postcode":"95519",
    "addr:street":"Old Railroad Grade Rd",
    "iso:country":"US",
    "sg:address":"4286 Old Railroad Grade Rd",
    "sg:city":"Mckinleyville",
    "sg:classifiers":[
        {
            "category":"Building & Trades",
            "subcategory":"Construction",
            "type":"Services"
        }
    ],
    "sg:phone":"+1 707 839 5409",
    "sg:postcode":"95519",
    "sg:province":"CA",
    "sg:tags":[
        "water",
        "well",
        "drilling"
    ],
    "wof:name":"Lake's Well Drilling",
    "wof:placetype":"venue"
},
  "geometry": {"coordinates":[-124.044431,40.956143],"type":"Point"}
}