{
  "type": "Feature",
  "properties": {
    "iso:country":"US",
    "sg:address":"38 Josiah Ave",
    "sg:city":"San Francisco",
    "sg:classifiers":[
        {
            "category":"Professional",
            "subcategory":"Computer Services",
            "type":"Services"
        }
    ],
    "sg:phone":"+1 415 452 9092",
    "sg:postcode":"94112",
    "sg:province":"CA",
    "sg:tags":[
        "consultant",
        "designer"
    ],
    "sg:website":"www.jumpdigital.com",
    "wof:name":"Jump Digital Svc",
    "wof:placetype":"venue"
},
  "geometry": {"coordinates":[-122.453194,37.718168],"type":"Point"}
}