{
  "type": "Feature",
  "properties": {
    "addr:full":"5111 Santa Fe Street San Diego CA 92109",
    "addr:housenumber":"5111",
    "addr:postcode":"92109",
    "addr:street":"Santa Fe Street",
    "iso:country":"US",
    "sg:address":"5111 Santa Fe Street",
    "sg:city":"San Diego",
    "sg:classifiers":[
        {
            "category":"Wholesale",
            "subcategory":"Computers",
            "type":"Manufacturing & Wholesale Goods"
        }
    ],
    "sg:phone":"+1 858 483 9883",
    "sg:postcode":"92109",
    "sg:province":"CA",
    "wof:name":"Terabyte Supply",
    "wof:placetype":"venue"
},
  "geometry": {"coordinates":[-117.224182,32.817844],"type":"Point"}
}