{
  "type": "Feature",
  "properties": {
    "addr:full":"2050 Oakland Rd San Jose CA 95131",
    "addr:housenumber":"2050",
    "addr:postcode":"95131",
    "addr:street":"Oakland Rd",
    "iso:country":"US",
    "sg:address":"2050 Oakland Rd",
    "sg:city":"San Jose",
    "sg:classifiers":[
        {
            "category":"Home & Garden",
            "subcategory":"Building Materials",
            "type":"Retail Goods"
        }
    ],
    "sg:phone":"+1 408 432 3383",
    "sg:postcode":"95131",
    "sg:province":"CA",
    "sg:tags":[
        "door"
    ],
    "wof:name":"Commercial Mill & Builders",
    "wof:placetype":"venue"
},
  "geometry": {"coordinates":[-121.901296,37.392687],"type":"Point"}
}