{
  "type": "Feature",
  "properties": {
    "addr:full":"1911 Edison Hwy Bakersfield CA 93305",
    "addr:housenumber":"1911",
    "addr:postcode":"93305",
    "addr:street":"Edison Hwy",
    "iso:country":"US",
    "sg:address":"1911 Edison Hwy",
    "sg:city":"Bakersfield",
    "sg:classifiers":[
        {
            "category":"Autos & Motor Vehicles",
            "subcategory":"Automobile Sales",
            "type":"Retail Goods"
        }
    ],
    "sg:phone":"+1 661 322 6764",
    "sg:postcode":"93305",
    "sg:province":"CA",
    "sg:tags":[
        "car",
        "dealer"
    ],
    "wof:name":"Universal Auto",
    "wof:placetype":"venue"
},
  "geometry": {"coordinates":[-118.97237,35.3722],"type":"Point"}
}