{
  "type": "Feature",
  "properties": {
    "addr:full":"2083 Old Middlefield Way Suite 206 Mountain View CA 94043",
    "addr:housenumber":"2083",
    "addr:postcode":"94043",
    "addr:street":"Old Middlefield Way Suite 206",
    "iso:country":"US",
    "sg:address":"2083 Old Middlefield Way Suite 206",
    "sg:city":"Mountain View",
    "sg:classifiers":[
        {
            "category":"Professional",
            "subcategory":"Computer Services",
            "type":"Services"
        }
    ],
    "sg:postcode":"94043",
    "sg:province":"CA",
    "sg:tags":[
        "security",
        "software",
        "phone",
        "mobile",
        "fraud"
    ],
    "sg:website":"http://www.victrio.com",
    "wof:name":"Victrio",
    "wof:placetype":"venue"
},
  "geometry": {"coordinates":[-122.089697,37.414207],"type":"Point"}
}