{
  "type": "Feature",
  "properties": {
    "addr:full":"10071 Grant Line Rd Elk Grove CA 95624",
    "addr:housenumber":"10071",
    "addr:postcode":"95624",
    "addr:street":"Grant Line Rd",
    "iso:country":"US",
    "sg:address":"10071 Grant Line Rd",
    "sg:city":"Elk Grove",
    "sg:classifiers":[
        {
            "category":"Shopping",
            "subcategory":"Gifts & Souvenirs",
            "type":"Retail Goods"
        }
    ],
    "sg:phone":"+1 916 684 0377",
    "sg:postcode":"95624",
    "sg:province":"CA",
    "wof:name":"Big Os Collectibles",
    "wof:placetype":"venue"
},
  "geometry": {"coordinates":[-121.34154700000001,38.392882],"type":"Point"}
}