{
  "type": "Feature",
  "properties": {
    "addr:full":"463 S California Ave Palo Alto CA 94306",
    "addr:housenumber":"463",
    "addr:postcode":"94306",
    "addr:street":"S California Ave",
    "iso:country":"US",
    "sg:address":"463 S California Ave",
    "sg:city":"Palo Alto",
    "sg:classifiers":[
        {
            "category":"Restaurant",
            "type":"Food & Drink"
        }
    ],
    "sg:menulink":"http://www.allmenus.com/ca/san-jose/48915-la-bodeguita-del-medio/menu/",
    "sg:phone":"+1 650 326 7762",
    "sg:postcode":"94306",
    "sg:province":"CA",
    "sg:tags":[
        "cuban"
    ],
    "wof:name":"La Bodeguita Del Medio",
    "wof:placetype":"venue"
},
  "geometry": {"coordinates":[-122.145432,37.425557],"type":"Point"}
}