{
  "type": "Feature",
  "properties": {
    "addr:full":"36470 Nickel St Palmdale CA 93550",
    "addr:housenumber":"36470",
    "addr:postcode":"ca 93550",
    "addr:street":"Nickel St",
    "iso:country":"US",
    "sg:address":"36470 Nickel St",
    "sg:city":"Palmdale",
    "sg:classifiers":[
        {
            "category":"Professional",
            "subcategory":"Business Services",
            "type":"Services"
        }
    ],
    "sg:phone":"+1 661 265 1703",
    "sg:postcode":"93550",
    "sg:province":"CA",
    "sg:tags":[
        "organizing",
        "services-household"
    ],
    "wof:name":"Hills Property Mgt",
    "wof:placetype":"venue"
},
  "geometry": {"coordinates":[-118.071253,34.5429],"type":"Point"}
}