{
  "type": "Feature",
  "properties": {
    "addr:full":"2148 S Bristol St Ste D Santa Ana CA 92704",
    "addr:housenumber":"2148",
    "addr:postcode":"92704",
    "addr:street":"S Bristol St Ste D",
    "iso:country":"US",
    "sg:address":"2148 S Bristol St Ste D",
    "sg:city":"Santa Ana",
    "sg:classifiers":[
        {
            "category":"Retail",
            "subcategory":"Laundry & Dry Cleaning",
            "type":"Services"
        }
    ],
    "sg:phone":"+1 714 545 2322",
    "sg:postcode":"92704",
    "sg:province":"CA",
    "wof:name":"Kent Cleaners",
    "wof:placetype":"venue"
},
  "geometry": {"coordinates":[-117.885002,33.719898],"type":"Point"}
}