{
  "type": "Feature",
  "properties": {
    "iso:country":"US",
    "sg:address":"1819 Union St",
    "sg:city":"San Francisco",
    "sg:classifiers":[
        {
            "category":"Health Services",
            "subcategory":"Doctor",
            "type":"Services"
        }
    ],
    "sg:phone":"+1 415 346 7025",
    "sg:postcode":"94123",
    "sg:province":"CA",
    "sg:tags":[
        "psychiatrist"
    ],
    "wof:name":"Bruce S Victor, MD",
    "wof:placetype":"venue"
},
  "geometry": {"coordinates":[-122.429363,37.797856],"type":"Point"}
}