{
  "type": "Feature",
  "properties": {
    "iso:country":"US",
    "sg:address":"20681 Shadow Rock Ln",
    "sg:city":"Trabuco Canyon",
    "sg:classifiers":[
        {
            "category":"Manufacturing",
            "subcategory":"Signs",
            "type":"Manufacturing & Wholesale Goods"
        }
    ],
    "sg:phone":"+1 949 858 0690",
    "sg:postcode":"92679",
    "sg:province":"CA",
    "sg:tags":[
        "specialty",
        "mfg"
    ],
    "wof:name":"Media Center & Graphic Support",
    "wof:placetype":"venue"
},
  "geometry": {"coordinates":[-117.56294,33.662965],"type":"Point"}
}