{
  "type": "Feature",
  "properties": {
    "addr:full":"12767 Saticoy St North Hollywood CA 91605",
    "addr:housenumber":"12767",
    "addr:postcode":"91605",
    "addr:street":"Saticoy St",
    "iso:country":"US",
    "sg:address":"12767 Saticoy St",
    "sg:city":"North Hollywood",
    "sg:classifiers":[
        {
            "category":"Wholesale",
            "subcategory":"Photographic Equipment",
            "type":"Manufacturing & Wholesale Goods"
        }
    ],
    "sg:phone":"+1 818 982 2510",
    "sg:postcode":"91605",
    "sg:province":"CA",
    "sg:tags":[
        "motion",
        "picture",
        "supply"
    ],
    "wof:name":"Grip Trix",
    "wof:placetype":"venue"
},
  "geometry": {"coordinates":[-118.410589,34.206553],"type":"Point"}
}