{
  "type": "Feature",
  "properties": {
    "iso:country":"US",
    "sg:address":"36555 Cook St",
    "sg:city":"Palm Desert",
    "sg:classifiers":[
        {
            "category":"Restaurant",
            "type":"Food & Drink"
        }
    ],
    "sg:menulink":"http://www.allmenus.com/ca/cathedral-city-palm-desert/178042-jack-in-the-box/menu/",
    "sg:phone":"+1 760 773 3025",
    "sg:postcode":"92211",
    "sg:province":"CA",
    "sg:tags":[
        "burger",
        "american"
    ],
    "wof:name":"Jack in the Box",
    "wof:placetype":"venue"
},
  "geometry": {"coordinates":[-116.35521300000001,33.785345],"type":"Point"}
}