{
  "type": "Feature",
  "properties": {
    "addr:full":"575 Anton Blvd Ste 300 Costa Mesa CA 92626",
    "addr:housenumber":"575",
    "addr:postcode":"92626",
    "addr:street":"Anton Blvd Ste 300",
    "iso:country":"US",
    "sg:address":"575 Anton Blvd Ste 300",
    "sg:city":"Costa Mesa",
    "sg:classifiers":[
        {
            "category":"Professional",
            "subcategory":"Lawyer & Legal Services",
            "type":"Services"
        }
    ],
    "sg:phone":"+1 714 432 6470",
    "sg:postcode":"92626",
    "sg:province":"CA",
    "wof:name":"Chapman Glucksman & Dean Law Offices of",
    "wof:placetype":"venue"
},
  "geometry": {"coordinates":[-117.88099699999999,33.690102],"type":"Point"}
}