{
  "type": "Feature",
  "properties": {
    "addr:full":"129 Harvard Ln Seal Beach CA 90740",
    "addr:housenumber":"129",
    "addr:postcode":"90740",
    "addr:street":"Harvard Ln",
    "iso:country":"US",
    "sg:address":"129 Harvard Ln",
    "sg:city":"Seal Beach",
    "sg:classifiers":[
        {
            "category":"Professional",
            "type":"Services"
        }
    ],
    "sg:phone":"+1 562 598 9443",
    "sg:postcode":"90740",
    "sg:province":"CA",
    "wof:name":"Medically Brief",
    "wof:placetype":"venue"
},
  "geometry": {"coordinates":[-118.09508599999999,33.777273],"type":"Point"}
}