{
  "type": "Feature",
  "properties": {
    "addr:full":"1132 S Main St Los Angeles CA 90015",
    "addr:housenumber":"1132",
    "addr:postcode":"90015",
    "addr:street":"S Main St",
    "iso:country":"US",
    "sg:address":"1132 S Main St",
    "sg:city":"Los Angeles",
    "sg:classifiers":[
        {
            "category":"Wholesale",
            "subcategory":"Toys & Hobbies",
            "type":"Manufacturing & Wholesale Goods"
        }
    ],
    "sg:phone":"+1 213 746 2640",
    "sg:postcode":"90015",
    "sg:province":"CA",
    "sg:tags":[
        "bag",
        "clocks"
    ],
    "wof:name":"B J Trading",
    "wof:placetype":"venue"
},
  "geometry": {"coordinates":[-118.258959,34.038037],"type":"Point"}
}