{
  "type": "Feature",
  "properties": {
    "iso:country":"US",
    "sg:address":"635 Barberry Way",
    "sg:city":"Nipomo",
    "sg:classifiers":[
        {
            "category":"Mining & Drilling",
            "type":"Manufacturing & Wholesale Goods"
        }
    ],
    "sg:phone":"+1 805 343 4448",
    "sg:postcode":"93444",
    "sg:province":"CA",
    "sg:tags":[
        "field"
    ],
    "wof:name":"Rob Isakson & Associates",
    "wof:placetype":"venue"
},
  "geometry": {"coordinates":[-120.53636899999999,35.050565],"type":"Point"}
}