{
  "type": "Feature",
  "properties": {
    "addr:full":"21 Pso del Sol Rancho Santa Margarita CA 92688",
    "addr:housenumber":"21",
    "addr:postcode":"92688",
    "addr:street":"Pso Del Sol",
    "iso:country":"US",
    "sg:address":"21 Pso del Sol",
    "sg:city":"Rancho Santa Margarita",
    "sg:classifiers":[
        {
            "category":"Professional",
            "type":"Services"
        }
    ],
    "sg:phone":"+1 949 766 1356",
    "sg:postcode":"92688",
    "sg:province":"CA",
    "wof:name":"Team Work Title",
    "wof:placetype":"venue"
},
  "geometry": {"coordinates":[-117.61894599999999,33.655222],"type":"Point"}
}