{
  "type": "Feature",
  "properties": {
    "addr:full":"7210 S Land Park Dr Sacramento CA 95831",
    "addr:housenumber":"7210",
    "addr:postcode":"95831",
    "addr:street":"S Land Park Dr",
    "iso:country":"US",
    "sg:address":"7210 S Land Park Dr",
    "sg:city":"Sacramento",
    "sg:classifiers":[
        {
            "category":"Health Services",
            "subcategory":"Doctor",
            "type":"Services"
        }
    ],
    "sg:phone":"+1 916 427 2555",
    "sg:postcode":"95831",
    "sg:province":"CA",
    "sg:tags":[
        "dentist"
    ],
    "wof:name":"Timothy A Wong DDS",
    "wof:placetype":"venue"
},
  "geometry": {"coordinates":[-121.511821,38.494532],"type":"Point"}
}