{
  "type": "Feature",
  "properties": {
    "iso:country":"US",
    "sg:address":"12665 N Tully Rd",
    "sg:city":"Lodi",
    "sg:classifiers":[
        {
            "category":"Professional",
            "type":"Services"
        }
    ],
    "sg:phone":"+1 209 931 5211",
    "sg:postcode":"95240",
    "sg:province":"CA",
    "wof:name":"Carl Hickman",
    "wof:placetype":"venue"
},
  "geometry": {"coordinates":[-121.12414200000001,38.088546],"type":"Point"}
}