{
  "type": "Feature",
  "properties": {
    "iso:country":"US",
    "sg:address":"950 Maidu Ave",
    "sg:city":"Nevada City",
    "sg:classifiers":[
        {
            "category":"Government",
            "subcategory":"Office",
            "type":"Public Place"
        }
    ],
    "sg:phone":"+1 530 265 7040",
    "sg:postcode":"95959",
    "sg:province":"CA",
    "wof:name":"Nevada County Administrator",
    "wof:placetype":"venue"
},
  "geometry": {"coordinates":[-121.02495500000001,39.269538],"type":"Point"}
}