{
  "type": "Feature",
  "properties": {
    "addr:full":"1130 Post St San Francisco CA 94109",
    "addr:housenumber":"1130",
    "addr:postcode":"94109",
    "addr:street":"Post St",
    "iso:country":"US",
    "sg:address":"1130 Post St",
    "sg:city":"San Francisco",
    "sg:classifiers":[
        {
            "category":"Personal",
            "subcategory":"Beauty Salon",
            "type":"Services"
        }
    ],
    "sg:phone":"+1 415 563 2316",
    "sg:postcode":"94109",
    "sg:province":"CA",
    "sg:website":"www.refreshdayspa.com",
    "wof:name":"Re-Fresh-A Day Spa",
    "wof:placetype":"venue"
},
  "geometry": {"coordinates":[-122.42118499999999,37.786757],"type":"Point"}
}