{
  "type": "Feature",
  "properties": {
    "iso:country":"US",
    "sg:address":"12000 Washington Blvd C",
    "sg:city":"Whittier",
    "sg:classifiers":[
        {
            "category":"Shopping",
            "subcategory":"Discount & Variety Stores",
            "type":"Retail Goods"
        }
    ],
    "sg:phone":"+1 562 693 8491",
    "sg:postcode":"90606",
    "sg:province":"CA",
    "sg:tags":[
        "wholesale"
    ],
    "wof:name":"La Colmena Candy",
    "wof:placetype":"venue"
},
  "geometry": {"coordinates":[-118.05542199999999,33.967451],"type":"Point"}
}