{
  "type": "Feature",
  "properties": {
    "addr:full":"21 T St Bakersfield CA 93304",
    "addr:housenumber":"21",
    "addr:postcode":"93304",
    "addr:street":"T St",
    "iso:country":"US",
    "sg:address":"21 T St",
    "sg:city":"Bakersfield",
    "sg:classifiers":[
        {
            "category":"Autos & Motor Vehicles",
            "subcategory":"Automobile Sales",
            "type":"Retail Goods"
        },
        {
            "category":"Retail",
            "subcategory":"Auto Repair",
            "type":"Services"
        }
    ],
    "sg:phone":"+1 661 325 6007",
    "sg:postcode":"93304",
    "sg:province":"CA",
    "sg:tags":[
        "dealers-used",
        "car",
        "used",
        "cars-wholesale"
    ],
    "wof:name":"Independence Auto Repair",
    "wof:placetype":"venue"
},
  "geometry": {"coordinates":[-119.008528,35.354124],"type":"Point"}
}