{
  "type": "Feature",
  "properties": {
    "addr:full":"1111 W Inyokern Rd Ridgecrest CA 93555",
    "addr:housenumber":"1111",
    "addr:postcode":"93555",
    "addr:street":"W Inyokern Rd",
    "iso:country":"US",
    "sg:address":"1111 W Inyokern Rd",
    "sg:city":"Ridgecrest",
    "sg:classifiers":[
        {
            "category":"Health Services",
            "subcategory":"Hospital",
            "type":"Services"
        }
    ],
    "sg:phone":"+1 760 446 4644",
    "sg:postcode":"93555",
    "sg:province":"CA",
    "wof:name":"Chiropractic Health Institute",
    "wof:placetype":"venue"
},
  "geometry": {"coordinates":[-117.692182,35.651655],"type":"Point"}
}