{
  "type": "Feature",
  "properties": {
    "iso:country":"US",
    "sg:address":"1203 N Dresden Pl",
    "sg:city":"Anaheim",
    "sg:classifiers":[
        {
            "category":"Real Estate",
            "subcategory":"Real Estate Operator",
            "type":"Services"
        }
    ],
    "sg:phone":"+1 714 520 9133",
    "sg:postcode":"92801",
    "sg:province":"CA",
    "sg:tags":[
        "apartment"
    ],
    "wof:name":"Dresdon Palms",
    "wof:placetype":"venue"
},
  "geometry": {"coordinates":[-117.940105,33.850754],"type":"Point"}
}