{
  "type": "Feature",
  "properties": {
    "iso:country":"US",
    "sg:address":"8824 Shirley Ave",
    "sg:city":"Northridge",
    "sg:classifiers":[
        {
            "category":"Shopping",
            "subcategory":"Clothing, Apparel, & Fashions",
            "type":"Retail Goods"
        },
        {
            "category":"Shopping",
            "subcategory":"Bridal",
            "type":"Retail Goods"
        }
    ],
    "sg:phone":"+1 818 701 5111",
    "sg:postcode":"91324",
    "sg:province":"CA",
    "sg:tags":[
        "shop",
        "alterations-clothing"
    ],
    "wof:name":"Unique Bridal",
    "wof:placetype":"venue"
},
  "geometry": {"coordinates":[-118.55793,34.230198],"type":"Point"}
}