{
  "type": "Feature",
  "properties": {
    "addr:full":"1514 S Carlos Ave Ontario CA 91761",
    "addr:housenumber":"1514",
    "addr:postcode":"91761",
    "addr:street":"S Carlos Ave",
    "iso:country":"US",
    "sg:address":"1514 S Carlos Ave",
    "sg:city":"Ontario",
    "sg:classifiers":[
        {
            "category":"Building & Trades",
            "subcategory":"Electrical",
            "type":"Services"
        }
    ],
    "sg:phone":"+1 909 930 0664",
    "sg:postcode":"91761",
    "sg:province":"CA",
    "sg:tags":[
        "electric",
        "contractor"
    ],
    "wof:name":"Jonny Socket Electrical Svc",
    "wof:placetype":"venue"
},
  "geometry": {"coordinates":[-117.60659099999999,34.046516],"type":"Point"}
}