{
  "type": "Feature",
  "properties": {
    "iso:country":"US",
    "sg:address":"1535 N Hobart Blvd",
    "sg:city":"Los Angeles",
    "sg:classifiers":[
        {
            "category":"Real Estate",
            "subcategory":"Real Estate Operator",
            "type":"Services"
        }
    ],
    "sg:phone":"+1 323 962 4945",
    "sg:postcode":"90027",
    "sg:province":"CA",
    "sg:tags":[
        "apartment"
    ],
    "wof:name":"Rosewood Corp",
    "wof:placetype":"venue"
},
  "geometry": {"coordinates":[-118.305713,34.10112],"type":"Point"}
}