{
  "type": "Feature",
  "properties": {
    "addr:full":"22762 Pacific Coast Hwy Malibu CA 90265",
    "addr:housenumber":"22762",
    "addr:postcode":"90265",
    "addr:street":"Pacific Coast Hwy",
    "iso:country":"US",
    "sg:address":"22762 Pacific Coast Hwy",
    "sg:city":"Malibu",
    "sg:classifiers":[
        {
            "category":"Professional",
            "subcategory":"Art Services",
            "type":"Services"
        }
    ],
    "sg:phone":"+1 310 317 0275",
    "sg:postcode":"90265",
    "sg:province":"CA",
    "sg:tags":[
        "graphic",
        "designer"
    ],
    "sg:website":"www.8edge.com",
    "wof:name":"Creativedge",
    "wof:placetype":"venue"
},
  "geometry": {"coordinates":[-118.669865,34.03935],"type":"Point"}
}