{
  "type": "Feature",
  "properties": {
    "addr:full":"11215 Hatteras St North Hollywood CA 91601",
    "addr:housenumber":"11215",
    "addr:postcode":"91601",
    "addr:street":"Hatteras St",
    "iso:country":"US",
    "sg:address":"11215 Hatteras St",
    "sg:city":"North Hollywood",
    "sg:classifiers":[
        {
            "category":"Home & Garden",
            "subcategory":"Building Materials",
            "type":"Retail Goods"
        }
    ],
    "sg:phone":"+1 818 623 7910",
    "sg:postcode":"91601",
    "sg:province":"CA",
    "sg:tags":[
        "paint"
    ],
    "wof:name":"Alex Painting",
    "wof:placetype":"venue"
},
  "geometry": {"coordinates":[-118.37629699999999,34.175789],"type":"Point"}
}