{
  "type": "Feature",
  "properties": {
    "iso:country":"US",
    "sg:address":"3563 Golden State Dr",
    "sg:city":"Santa Clara",
    "sg:classifiers":[
        {
            "category":"Arts & Performance",
            "subcategory":"Music",
            "type":"Entertainment"
        }
    ],
    "sg:phone":"+1 510 739 1862",
    "sg:postcode":"95051",
    "sg:province":"CA",
    "sg:tags":[
        "dj"
    ],
    "wof:name":"Bass Record Fremont",
    "wof:placetype":"venue"
},
  "geometry": {"coordinates":[-121.99426,37.343718],"type":"Point"}
}