{
  "type": "Feature",
  "properties": {
    "addr:full":"18530 Hatteras St Tarzana CA 91356",
    "addr:housenumber":"18530",
    "addr:postcode":"91356",
    "addr:street":"Hatteras St",
    "iso:country":"US",
    "sg:address":"18530 Hatteras St",
    "sg:city":"Tarzana",
    "sg:classifiers":[
        {
            "category":"Wholesale",
            "subcategory":"Stationery",
            "type":"Manufacturing & Wholesale Goods"
        }
    ],
    "sg:phone":"+1 818 708 8450",
    "sg:postcode":"91356",
    "sg:province":"CA",
    "sg:tags":[
        "school",
        "supply"
    ],
    "wof:name":"Schoolmaster Educational Svc",
    "wof:placetype":"venue"
},
  "geometry": {"coordinates":[-118.53688699999999,34.177388],"type":"Point"}
}