{
  "type": "Feature",
  "properties": {
    "addr:full":"228 N el Molino Ave Pasadena CA 91101",
    "addr:housenumber":"228",
    "addr:postcode":"91101",
    "addr:street":"N El Molino Ave",
    "iso:country":"US",
    "sg:address":"228 N el Molino Ave",
    "sg:city":"Pasadena",
    "sg:classifiers":[
        {
            "category":"Organizations",
            "subcategory":"Religious Organization",
            "type":"Services"
        }
    ],
    "sg:phone":"+1 626 584 0547",
    "sg:postcode":"91101",
    "sg:province":"CA",
    "wof:name":"Word Of Truth Ministry",
    "wof:placetype":"venue"
},
  "geometry": {"coordinates":[-118.136841,34.150092],"type":"Point"}
}