{
  "type": "Feature",
  "properties": {
    "addr:full":"27225 Camp Plenty Rd Ste 3 Canyon Cntry CA 91351",
    "addr:housenumber":"27225",
    "addr:postcode":"91351",
    "addr:street":"Camp Plenty Rd Ste 3 Canyon Cntry",
    "iso:country":"US",
    "sg:address":"27225 Camp Plenty Rd Ste 3",
    "sg:city":"Canyon Cntry",
    "sg:classifiers":[
        {
            "category":"Health Services",
            "subcategory":"Chiropractor",
            "type":"Services"
        }
    ],
    "sg:phone":"+1 661 252 8802",
    "sg:postcode":"91351",
    "sg:province":"CA",
    "wof:name":"Canyon Chiropractic",
    "wof:placetype":"venue"
},
  "geometry": {"coordinates":[-118.475998,34.416199],"type":"Point"}
}