{
  "type": "Feature",
  "properties": {
    "addr:full":"1308 Wilshire Blvd Los Angeles CA 90017",
    "addr:housenumber":"1308",
    "addr:postcode":"90017",
    "addr:street":"Wilshire Blvd",
    "iso:country":"US",
    "sg:address":"1308 Wilshire Blvd",
    "sg:city":"Los Angeles",
    "sg:classifiers":[
        {
            "category":"Professional",
            "type":"Services"
        }
    ],
    "sg:phone":"+1 323 467 2990",
    "sg:postcode":"90017",
    "sg:province":"CA",
    "sg:tags":[
        "establishment"
    ],
    "wof:name":"Encomiendas Internacionales",
    "wof:placetype":"venue"
},
  "geometry": {"coordinates":[-118.268348,34.054484],"type":"Point"}
}