{
  "type": "Feature",
  "properties": {
    "iso:country":"US",
    "sg:address":"2356 Moore St Ste 201",
    "sg:city":"San Diego",
    "sg:classifiers":[
        {
            "category":"Banks & Credit Unions",
            "subcategory":"Financial Services",
            "type":"Services"
        }
    ],
    "sg:phone":"+1 619 293 3919",
    "sg:postcode":"92110",
    "sg:province":"CA",
    "sg:tags":[
        "broker",
        "mortgage"
    ],
    "sg:website":"www.cmlv.net",
    "wof:name":"Cornerstone Commercial Mortgage",
    "wof:placetype":"venue"
},
  "geometry": {"coordinates":[-117.194197,32.7489],"type":"Point"}
}