{
  "type": "Feature",
  "properties": {
    "addr:full":"1377 Vancouver Ave Burlingame CA 94010",
    "addr:housenumber":"1377",
    "addr:postcode":"94010",
    "addr:street":"Vancouver Ave",
    "iso:country":"US",
    "sg:address":"1377 Vancouver Ave",
    "sg:city":"Burlingame",
    "sg:classifiers":[
        {
            "category":"Professional",
            "type":"Services"
        },
        {
            "category":"Shopping",
            "subcategory":"Florist",
            "type":"Retail Goods"
        }
    ],
    "sg:phone":"+1 650 302 1812",
    "sg:postcode":"94010",
    "sg:province":"CA",
    "sg:tags":[
        "planning",
        "event"
    ],
    "sg:website":"www.anniesiu.com",
    "wof:name":"Annie Siu Floral & Events",
    "wof:placetype":"venue"
},
  "geometry": {"coordinates":[-122.375061,37.582763],"type":"Point"}
}