{
  "type": "Feature",
  "properties": {
    "iso:country":"US",
    "sg:address":"520 Contra Costa Blvd",
    "sg:city":"Pleasant Hill",
    "sg:classifiers":[
        {
            "category":"Autos & Motor Vehicles",
            "subcategory":"Auto Supplies",
            "type":"Retail Goods"
        }
    ],
    "sg:phone":"+1 925 691 0178",
    "sg:postcode":"94523",
    "sg:province":"CA",
    "sg:tags":[
        "automobile",
        "parts"
    ],
    "sg:website":"www.pepboys.com",
    "wof:name":"Pep Boys Supercenter",
    "wof:placetype":"venue"
},
  "geometry": {"coordinates":[-122.06620700000001,37.97883],"type":"Point"}
}