{
  "type": "Feature",
  "properties": {
    "iso:country":"US",
    "sg:address":"505 Sansome St",
    "sg:city":"San Francisco",
    "sg:classifiers":[
        {
            "category":"Banks & Credit Unions",
            "subcategory":"Investment Brokerage",
            "type":"Services"
        }
    ],
    "sg:phone":"+1 415 981 3455",
    "sg:postcode":"94111",
    "sg:province":"CA",
    "sg:tags":[
        "advisory",
        "financial"
    ],
    "wof:name":"Van Strum & Towne Inc",
    "wof:placetype":"venue"
},
  "geometry": {"coordinates":[-122.401649,37.795255],"type":"Point"}
}