{
  "type": "Feature",
  "properties": {
    "addr:full":"750 W Route 66 Glendora CA 91740",
    "addr:housenumber":"750",
    "addr:postcode":"91740",
    "addr:street":"W Route 66",
    "iso:country":"US",
    "sg:address":"750 W Route 66",
    "sg:city":"Glendora",
    "sg:classifiers":[
        {
            "category":"Health Services",
            "subcategory":"Chiropractor",
            "type":"Services"
        }
    ],
    "sg:phone":"+1 626 857 1901",
    "sg:postcode":"91740",
    "sg:province":"CA",
    "sg:tags":[
        "chiropractic"
    ],
    "wof:name":"Physique Envy",
    "wof:placetype":"venue"
},
  "geometry": {"coordinates":[-117.87867799999999,34.128675],"type":"Point"}
}