{
  "type": "Feature",
  "properties": {
    "addr:full":"1625 Richland Ave Ceres CA 95307",
    "addr:housenumber":"1625",
    "addr:postcode":"95307",
    "addr:street":"Richland Ave",
    "iso:country":"US",
    "sg:address":"1625 Richland Ave",
    "sg:city":"Ceres",
    "sg:classifiers":[
        {
            "category":"Building & Trades",
            "subcategory":"Landscaping Services",
            "type":"Services"
        }
    ],
    "sg:phone":"+1 209 496 0338",
    "sg:postcode":"95307",
    "sg:province":"CA",
    "wof:name":"Valley Lawncare",
    "wof:placetype":"venue"
},
  "geometry": {"coordinates":[-120.96622600000001,37.607201],"type":"Point"}
}