{
  "type": "Feature",
  "properties": {
    "iso:country":"US",
    "sg:address":"526 E Holt Blvd",
    "sg:city":"Ontario",
    "sg:classifiers":[
        {
            "category":"Shopping",
            "subcategory":"Gifts & Souvenirs",
            "type":"Retail Goods"
        }
    ],
    "sg:phone":"+1 909 391 1229",
    "sg:postcode":"91761",
    "sg:province":"CA",
    "sg:tags":[
        "party",
        "supply"
    ],
    "wof:name":"Hueras Party Supply",
    "wof:placetype":"venue"
},
  "geometry": {"coordinates":[-117.64561,34.063301],"type":"Point"}
}