{
  "type": "Feature",
  "properties": {
    "addr:full":"440 Elm Ave Long Beach CA 90802",
    "addr:housenumber":"440",
    "addr:postcode":"90802",
    "addr:street":"Elm Ave",
    "iso:country":"US",
    "sg:address":"440 Elm Ave",
    "sg:city":"Long Beach",
    "sg:classifiers":[
        {
            "category":"Organizations",
            "subcategory":"Religious Organization",
            "type":"Services"
        }
    ],
    "sg:phone":"+1 562 435 8941",
    "sg:postcode":"90802",
    "sg:province":"CA",
    "sg:tags":[
        "church"
    ],
    "wof:name":"First Christian Church",
    "wof:placetype":"venue"
},
  "geometry": {"coordinates":[-118.187595,33.772793],"type":"Point"}
}