{
  "type": "Feature",
  "properties": {
    "addr:full":"10250 Santa Monica Blvd Los Angeles CA 90067",
    "addr:housenumber":"10250",
    "addr:postcode":"90067",
    "addr:street":"Santa Monica Blvd",
    "iso:country":"US",
    "sg:address":"10250 Santa Monica Blvd",
    "sg:city":"Los Angeles",
    "sg:classifiers":[
        {
            "category":"Health Services",
            "subcategory":"Optometrist",
            "type":"Services"
        }
    ],
    "sg:phone":"+1 310 277 3032",
    "sg:postcode":"90067",
    "sg:province":"CA",
    "wof:name":"Century City Optometry",
    "wof:placetype":"venue"
},
  "geometry": {"coordinates":[-118.421042,34.059196],"type":"Point"}
}