{
  "type": "Feature",
  "properties": {
    "addr:full":"947 Sun Mun Way Los Angeles CA 90012",
    "addr:housenumber":"947",
    "addr:postcode":"90012",
    "addr:street":"Sun Mun Way",
    "iso:country":"US",
    "sg:address":"947 Sun Mun Way",
    "sg:city":"Los Angeles",
    "sg:classifiers":[
        {
            "category":"Wholesale",
            "subcategory":"Non-durable Goods",
            "type":"Manufacturing & Wholesale Goods"
        }
    ],
    "sg:phone":"+1 213 620 7907",
    "sg:postcode":"90012",
    "sg:province":"CA",
    "wof:name":"Hongkong Association",
    "wof:placetype":"venue"
},
  "geometry": {"coordinates":[-118.23689299999999,34.065996],"type":"Point"}
}