{
  "type": "Feature",
  "properties": {
    "addr:full":"1515 32nd Ave San Francisco CA 94122",
    "addr:housenumber":"1515",
    "addr:postcode":"94122",
    "addr:street":"32Nd Ave",
    "iso:country":"US",
    "sg:address":"1515 32nd Ave",
    "sg:city":"San Francisco",
    "sg:classifiers":[
        {
            "category":"Health Services",
            "subcategory":"Clinic",
            "type":"Services"
        }
    ],
    "sg:phone":"+1 415 250 1295",
    "sg:postcode":"94122",
    "sg:province":"CA",
    "sg:tags":[
        "medical"
    ],
    "wof:name":"JigalinFitness",
    "wof:placetype":"venue"
},
  "geometry": {"coordinates":[-122.49105400000001,37.758861],"type":"Point"}
}