{
  "type": "Feature",
  "properties": {
    "iso:country":"US",
    "sg:address":"505 N Arrowhead Ave",
    "sg:city":"San Bernardino",
    "sg:classifiers":[
        {
            "category":"Professional",
            "subcategory":"Business Services",
            "type":"Services"
        }
    ],
    "sg:phone":"+1 909 388 9105",
    "sg:postcode":"92401",
    "sg:province":"CA",
    "wof:name":"Dunham Hernandez Legal Svc",
    "wof:placetype":"venue"
},
  "geometry": {"coordinates":[-117.289606,34.110124],"type":"Point"}
}