{
  "type": "Feature",
  "properties": {
    "addr:full":"50 Post St San Francisco CA 94104",
    "addr:housenumber":"50",
    "addr:postcode":"94104",
    "addr:street":"Post St",
    "iso:country":"US",
    "sg:address":"50 Post St",
    "sg:city":"San Francisco",
    "sg:classifiers":[
        {
            "category":"Restaurant",
            "type":"Food & Drink"
        }
    ],
    "sg:menulink":"http://www.allmenus.com/ca/san-francisco/62905-chipotle/menu/",
    "sg:phone":"+1 415 956 3392",
    "sg:postcode":"94104",
    "sg:province":"CA",
    "sg:tags":[
        "mexican",
        "asian",
        "chinese"
    ],
    "wof:name":"Chipotle",
    "wof:placetype":"venue"
},
  "geometry": {"coordinates":[-122.40267799999999,37.789066],"type":"Point"}
}