{
  "type": "Feature",
  "properties": {
    "addr:full":"14560 Nordhoff St Panorama City CA 91402",
    "addr:housenumber":"14560",
    "addr:postcode":"91402",
    "addr:street":"Nordhoff St",
    "iso:country":"US",
    "sg:address":"14560 Nordhoff St",
    "sg:city":"Panorama City",
    "sg:classifiers":[
        {
            "category":"Restaurant",
            "type":"Food & Drink"
        }
    ],
    "sg:phone":"+1 818 893 3329",
    "sg:postcode":"91402",
    "sg:province":"CA",
    "sg:tags":[
        "out"
    ],
    "wof:name":"Sizzling Wok",
    "wof:placetype":"venue"
},
  "geometry": {"coordinates":[-118.450121,34.235334],"type":"Point"}
}