{
  "type": "Feature",
  "properties": {
    "iso:country":"US",
    "sg:address":"8338 Beverly Blvd 2nd Floor",
    "sg:city":"Los Angeles",
    "sg:classifiers":[
        {
            "category":"Personal",
            "subcategory":"Beauty Salon",
            "type":"Services"
        },
        {
            "category":"Sports & Exercise",
            "subcategory":"Gym",
            "type":"Entertainment"
        }
    ],
    "sg:phone":"+1 626 393 6283",
    "sg:postcode":"90048",
    "sg:province":"CA",
    "sg:tags":[
        "spa",
        "pilate"
    ],
    "sg:website":"www.coreartscenter.com",
    "wof:name":"Core Arts Pilates",
    "wof:placetype":"venue"
},
  "geometry": {"coordinates":[-118.371493,34.076022],"type":"Point"}
}