{
  "type": "Feature",
  "properties": {
    "addr:full":"214 Estates Dr Roseville CA 95678",
    "addr:housenumber":"214",
    "addr:postcode":"95678",
    "addr:street":"Estates Dr",
    "iso:country":"US",
    "sg:address":"214 Estates Dr",
    "sg:city":"Roseville",
    "sg:classifiers":[
        {
            "category":"Professional",
            "subcategory":"Secretarial Services",
            "type":"Services"
        }
    ],
    "sg:phone":"+1 916 783 5363",
    "sg:postcode":"95678",
    "sg:province":"CA",
    "sg:tags":[
        "reporting",
        "court"
    ],
    "wof:name":"Typing Place",
    "wof:placetype":"venue"
},
  "geometry": {"coordinates":[-121.272189,38.747162],"type":"Point"}
}