{
  "type": "Feature",
  "properties": {
    "iso:country":"US",
    "sg:address":"14526 Galleon Ln",
    "sg:city":"Helendale",
    "sg:classifiers":[
        {
            "category":"Home & Garden",
            "subcategory":"Home Furnishings",
            "type":"Retail Goods"
        }
    ],
    "sg:phone":"+1 760 245 8375",
    "sg:postcode":"92342",
    "sg:province":"CA",
    "sg:tags":[
        "curtain",
        "made",
        "drapery"
    ],
    "wof:name":"J & J Interiors",
    "wof:placetype":"venue"
},
  "geometry": {"coordinates":[-117.352305,34.740445],"type":"Point"}
}