{
  "type": "Feature",
  "properties": {
    "iso:country":"US",
    "sg:address":"3168 Airway Ave",
    "sg:city":"Costa Mesa",
    "sg:classifiers":[
        {
            "category":"Wholesale",
            "subcategory":"Auto Parts",
            "type":"Manufacturing & Wholesale Goods"
        }
    ],
    "sg:phone":"+1 714 662 7547",
    "sg:postcode":"92626",
    "sg:province":"CA",
    "wof:name":"Worldpac",
    "wof:placetype":"venue"
},
  "geometry": {"coordinates":[-117.87125899999999,33.67894],"type":"Point"}
}