{
  "type": "Feature",
  "properties": {
    "iso:country":"US",
    "sg:address":"1008 Brucker Ave",
    "sg:city":"Spring Valley",
    "sg:classifiers":[
        {
            "category":"Retail",
            "subcategory":"Repair Shop",
            "type":"Services"
        }
    ],
    "sg:phone":"+1 619 460 8241",
    "sg:postcode":"91977",
    "sg:province":"CA",
    "sg:tags":[
        "taxidermist"
    ],
    "wof:name":"Moydell's Taxidermy",
    "wof:placetype":"venue"
},
  "geometry": {"coordinates":[-117.009288,32.712736],"type":"Point"}
}