{
  "type": "Feature",
  "properties": {
    "addr:full":"850 S Robertson Blvd Los Angeles CA 90035",
    "addr:housenumber":"850",
    "addr:postcode":"90035",
    "addr:street":"S Robertson Blvd",
    "iso:country":"US",
    "sg:address":"850 S Robertson Blvd",
    "sg:city":"Los Angeles",
    "sg:classifiers":[
        {
            "category":"Professional",
            "type":"Services"
        }
    ],
    "sg:phone":"+1 310 360 7979",
    "sg:postcode":"90035",
    "sg:province":"CA",
    "wof:name":"Brite Dental",
    "wof:placetype":"venue"
},
  "geometry": {"coordinates":[-118.38349599999999,34.061369],"type":"Point"}
}