{
  "type": "Feature",
  "properties": {
    "addr:full":"15061 Glass Cir Irvine CA 92604",
    "addr:housenumber":"15061",
    "addr:postcode":"92604",
    "addr:street":"Glass Cir",
    "iso:country":"US",
    "sg:address":"15061 Glass Cir",
    "sg:city":"Irvine",
    "sg:classifiers":[
        {
            "category":"Wholesale",
            "subcategory":"Jewelry",
            "type":"Manufacturing & Wholesale Goods"
        }
    ],
    "sg:phone":"+1 949 552 5839",
    "sg:postcode":"92604",
    "sg:province":"CA",
    "sg:tags":[
        "tools-wholesale",
        "tool",
        "manufacturer"
    ],
    "wof:name":"Mac's Findings & Tools",
    "wof:placetype":"venue"
},
  "geometry": {"coordinates":[-117.782111,33.690113],"type":"Point"}
}