{
  "type": "Feature",
  "properties": {
    "addr:full":"1069 57th St Emeryville CA 94608",
    "addr:housenumber":"1069",
    "addr:postcode":"94608",
    "addr:street":"57Th St",
    "iso:country":"US",
    "sg:address":"1069 57th St",
    "sg:city":"Emeryville",
    "sg:classifiers":[
        {
            "category":"Professional",
            "subcategory":"Business Services",
            "type":"Services"
        },
        {
            "category":"Restaurant",
            "type":"Food & Drink"
        }
    ],
    "sg:phone":"+1 510 452 5225",
    "sg:postcode":"94608",
    "sg:province":"CA",
    "sg:tags":[
        "product",
        "nonmetallic",
        "eating",
        "mineral",
        "mfg"
    ],
    "wof:name":"Ice Art-Ice Sculpture",
    "wof:placetype":"venue"
},
  "geometry": {"coordinates":[-122.282062,37.84046],"type":"Point"}
}