{
  "type": "Feature",
  "properties": {
    "iso:country":"US",
    "sg:address":"3726 Arlen Ct",
    "sg:city":"San Jose",
    "sg:classifiers":[
        {
            "category":"Building & Trades",
            "subcategory":"Cleaning & Sanitation",
            "type":"Services"
        }
    ],
    "sg:phone":"+1 408 263 1352",
    "sg:postcode":"95132",
    "sg:province":"CA",
    "sg:tags":[
        "janitor"
    ],
    "wof:name":"Clear Line",
    "wof:placetype":"venue"
},
  "geometry": {"coordinates":[-121.855251,37.420289],"type":"Point"}
}