{
  "type": "Feature",
  "properties": {
    "addr:full":"11027 Lower Azusa Rd El Monte CA 91731",
    "addr:housenumber":"11027",
    "addr:postcode":"91731",
    "addr:street":"Lower Azusa Rd",
    "iso:country":"US",
    "sg:address":"11027 Lower Azusa Rd",
    "sg:city":"El Monte",
    "sg:classifiers":[
        {
            "category":"Retail",
            "subcategory":"Repair Shop",
            "type":"Services"
        }
    ],
    "sg:phone":"+1 626 579 7833",
    "sg:postcode":"91731",
    "sg:province":"CA",
    "wof:name":"Sorensens Custom Metal Polsg",
    "wof:placetype":"venue"
},
  "geometry": {"coordinates":[-118.024732,34.091995],"type":"Point"}
}