{
  "type": "Feature",
  "properties": {
    "iso:country":"US",
    "sg:address":"7840 Alabama Ave",
    "sg:city":"Canoga Park",
    "sg:classifiers":[
        {
            "category":"Home & Garden",
            "subcategory":"Building Materials",
            "type":"Retail Goods"
        }
    ],
    "sg:phone":"+1 818 704 7490",
    "sg:postcode":"91304",
    "sg:province":"CA",
    "sg:tags":[
        "lumber"
    ],
    "sg:website":"www.integritymantels.com",
    "wof:name":"Integrity Wood Products Inc",
    "wof:placetype":"venue"
},
  "geometry": {"coordinates":[-118.599343,34.213399],"type":"Point"}
}