{
  "type": "Feature",
  "properties": {
    "iso:country":"US",
    "sg:address":"24172 Falconer Dr",
    "sg:city":"Murrieta",
    "sg:classifiers":[
        {
            "category":"Manufacturing",
            "subcategory":"Tools & Machinery",
            "type":"Manufacturing & Wholesale Goods"
        }
    ],
    "sg:phone":"+1 951 677 2438",
    "sg:postcode":"92562",
    "sg:province":"CA",
    "sg:tags":[
        "dental",
        "mfg"
    ],
    "wof:name":"Pearly White Study Models",
    "wof:placetype":"venue"
},
  "geometry": {"coordinates":[-117.199344,33.590558],"type":"Point"}
}