{
  "type": "Feature",
  "properties": {
    "addr:full":"2885 E Gage Ave Huntington Park CA 90255",
    "addr:housenumber":"2885",
    "addr:postcode":"90255",
    "addr:street":"E Gage Ave;Park",
    "iso:country":"US",
    "sg:address":"2885 E Gage Ave",
    "sg:city":"Huntington Park",
    "sg:classifiers":[
        {
            "category":"Restaurant",
            "type":"Food & Drink"
        }
    ],
    "sg:phone":"+1 323 584 8194",
    "sg:postcode":"90255",
    "sg:province":"CA",
    "wof:name":"Mariscos LA Quebrada De Acplco",
    "wof:placetype":"venue"
},
  "geometry": {"coordinates":[-118.218333,33.981517],"type":"Point"}
}