{
  "type": "Feature",
  "properties": {
    "iso:country":"US",
    "sg:address":"305 3rd St",
    "sg:city":"Sausalito",
    "sg:classifiers":[
        {
            "category":"Retail",
            "subcategory":"Portrait Studio",
            "type":"Services"
        }
    ],
    "sg:phone":"+1 415 332 6800",
    "sg:postcode":"94965",
    "sg:province":"CA",
    "sg:tags":[
        "photo"
    ],
    "wof:name":"Lynda Niemeier Photography",
    "wof:placetype":"venue"
},
  "geometry": {"coordinates":[-122.481698,37.850796],"type":"Point"}
}