{
  "type": "Feature",
  "properties": {
    "iso:country":"US",
    "sg:address":"5664 Selmaraine Dr",
    "sg:city":"Culver City",
    "sg:classifiers":[
        {
            "category":"Building & Trades",
            "subcategory":"Cleaning & Sanitation",
            "type":"Services"
        }
    ],
    "sg:phone":"+1 310 390 3552",
    "sg:postcode":"90230",
    "sg:province":"CA",
    "sg:tags":[
        "property",
        "maintenance"
    ],
    "wof:name":"CAM Services",
    "wof:placetype":"venue"
},
  "geometry": {"coordinates":[-118.397399,33.988081],"type":"Point"}
}