{
  "type": "Feature",
  "properties": {
    "iso:country":"US",
    "sg:address":"27023 McBean Pkwy",
    "sg:city":"Valencia",
    "sg:classifiers":[
        {
            "category":"Building & Trades",
            "subcategory":"Plumbing",
            "type":"Services"
        }
    ],
    "sg:phone":"+1 661 257 2029",
    "sg:postcode":"91355",
    "sg:province":"CA",
    "sg:tags":[
        "air",
        "heating",
        "warm",
        "conditioning",
        "contractor"
    ],
    "wof:name":"Heavens Air Conditioning & Htg",
    "wof:placetype":"venue"
},
  "geometry": {"coordinates":[-118.562123,34.425368],"type":"Point"}
}