{
  "type": "Feature",
  "properties": {
    "addr:full":"2551 Harbor St Pittsburg CA 94565",
    "addr:housenumber":"2551",
    "addr:postcode":"94565",
    "addr:street":"Harbor St",
    "iso:country":"US",
    "sg:address":"2551 Harbor St",
    "sg:city":"Pittsburg",
    "sg:classifiers":[
        {
            "category":"Recreation",
            "type":"Entertainment"
        }
    ],
    "sg:phone":"+1 925 439 4879",
    "sg:postcode":"94565",
    "sg:province":"CA",
    "sg:tags":[
        "parks"
    ],
    "wof:name":"Small World Park",
    "wof:placetype":"venue"
},
  "geometry": {"coordinates":[-121.883123,38.014906],"type":"Point"}
}