{
  "type": "Feature",
  "properties": {
    "addr:full":"27200 Embassy St Sun City CA 92586",
    "addr:housenumber":"27200",
    "addr:postcode":"92586",
    "addr:street":"Embassy St",
    "iso:country":"US",
    "sg:address":"27200 Embassy St",
    "sg:city":"Sun City",
    "sg:classifiers":[
        {
            "category":"Building & Trades",
            "subcategory":"Construction",
            "type":"Services"
        }
    ],
    "sg:phone":"+1 951 679 6025",
    "sg:postcode":"92586",
    "sg:province":"CA",
    "sg:tags":[
        "contractor"
    ],
    "wof:name":"R & J Co",
    "wof:placetype":"venue"
},
  "geometry": {"coordinates":[-117.19011999999999,33.724785],"type":"Point"}
}