{
  "type": "Feature",
  "properties": {
    "iso:country":"US",
    "sg:address":"752 Glen Canyon Rd",
    "sg:city":"Santa Cruz",
    "sg:classifiers":[
        {
            "category":"Professional",
            "type":"Services"
        }
    ],
    "sg:phone":"+1 831 426 2633",
    "sg:postcode":"95060",
    "sg:province":"CA",
    "wof:name":"Machine Arts Inc",
    "wof:placetype":"venue"
},
  "geometry": {"coordinates":[-122.009332,37.008033],"type":"Point"}
}