{
  "type": "Feature",
  "properties": {
    "addr:full":"10500 San Marcos Rd Atascadero CA 93422",
    "addr:housenumber":"10500",
    "addr:postcode":"93422",
    "addr:street":"San Marcos Rd",
    "iso:country":"US",
    "sg:address":"10500 San Marcos Rd",
    "sg:city":"Atascadero",
    "sg:classifiers":[
        {
            "category":"Building & Trades",
            "subcategory":"Landscaping Services",
            "type":"Services"
        }
    ],
    "sg:phone":"+1 805 461 1657",
    "sg:postcode":"93422",
    "sg:province":"CA",
    "sg:tags":[
        "contractor"
    ],
    "wof:name":"Tomascapes",
    "wof:placetype":"venue"
},
  "geometry": {"coordinates":[-120.698318,35.468289],"type":"Point"}
}