{
  "type": "Feature",
  "properties": {
    "iso:country":"US",
    "sg:address":"211 E 3rd Ave",
    "sg:city":"San Mateo",
    "sg:classifiers":[
        {
            "category":"Shopping",
            "type":"Retail Goods"
        }
    ],
    "sg:phone":"+1 650 344 8988",
    "sg:postcode":"94401",
    "sg:province":"CA",
    "sg:tags":[
        "mobile",
        "phone",
        "telephone",
        "cellular"
    ],
    "wof:name":"Wireless Pcs",
    "wof:placetype":"venue"
},
  "geometry": {"coordinates":[-122.322998,37.565201],"type":"Point"}
}