{
  "type": "Feature",
  "properties": {
    "addr:full":"4919 Ledge Ave North Hollywood CA 91601",
    "addr:housenumber":"4919",
    "addr:postcode":"91601",
    "addr:street":"Ledge Ave",
    "iso:country":"US",
    "sg:address":"4919 Ledge Ave",
    "sg:city":"North Hollywood",
    "sg:classifiers":[
        {
            "category":"Professional",
            "subcategory":"Lawyer & Legal Services",
            "type":"Services"
        }
    ],
    "sg:phone":"+1 818 760 3386",
    "sg:postcode":"91601",
    "sg:province":"CA",
    "sg:tags":[
        "attorney"
    ],
    "wof:name":"Greg Alexanian Law Offices",
    "wof:placetype":"venue"
},
  "geometry": {"coordinates":[-118.357225,34.160954],"type":"Point"}
}