{
  "type": "Feature",
  "properties": {
    "addr:full":"3410 Clairemont Dr San Diego CA 92117",
    "addr:housenumber":"3410",
    "addr:postcode":"92117",
    "addr:street":"Clairemont Dr",
    "iso:country":"US",
    "sg:address":"3410 Clairemont Dr",
    "sg:city":"San Diego",
    "sg:classifiers":[
        {
            "category":"Organizations",
            "subcategory":"Religious Organization",
            "type":"Services"
        }
    ],
    "sg:phone":"+1 619 276 0603",
    "sg:postcode":"92117",
    "sg:province":"CA",
    "sg:tags":[
        "church"
    ],
    "wof:name":"Christian Science-Church",
    "wof:placetype":"venue"
},
  "geometry": {"coordinates":[-117.200041,32.804548],"type":"Point"}
}