{
  "type": "Feature",
  "properties": {
    "addr:full":"4643 W Washington Blvd Los Angeles CA 90016",
    "addr:housenumber":"4643",
    "addr:postcode":"90016",
    "addr:street":"W Washington Blvd",
    "iso:country":"US",
    "sg:address":"4643 W Washington Blvd",
    "sg:city":"Los Angeles",
    "sg:classifiers":[
        {
            "category":"Building & Trades",
            "subcategory":"Construction",
            "type":"Services"
        }
    ],
    "sg:phone":"+1 323 933 9165",
    "sg:postcode":"90016",
    "sg:province":"CA",
    "sg:tags":[
        "carpenter"
    ],
    "wof:name":"Flores Carpenter",
    "wof:placetype":"venue"
},
  "geometry": {"coordinates":[-118.34117500000001,34.039908],"type":"Point"}
}