{
  "type": "Feature",
  "properties": {
    "addr:full":"19530 Van Buren Blvd Riverside CA 92508",
    "addr:housenumber":"19530",
    "addr:postcode":"92508",
    "addr:street":"Van Buren Blvd",
    "iso:country":"US",
    "sg:address":"19530 Van Buren Blvd",
    "sg:city":"Riverside",
    "sg:classifiers":[
        {
            "category":"Restaurant",
            "type":"Food & Drink"
        }
    ],
    "sg:phone":"+1 951 656 0304",
    "sg:postcode":"92508",
    "sg:province":"CA",
    "wof:name":"Roberto's Taco Shop",
    "wof:placetype":"venue"
},
  "geometry": {"coordinates":[-117.320846,33.889116],"type":"Point"}
}