{
  "type": "Feature",
  "properties": {
    "iso:country":"US",
    "sg:address":"555 E Palmer Ave",
    "sg:city":"Glendale",
    "sg:classifiers":[
        {
            "category":"Social Services",
            "subcategory":"Adult Care",
            "type":"Services"
        }
    ],
    "sg:phone":"+1 818 551 1330",
    "sg:postcode":"91205",
    "sg:province":"CA",
    "sg:tags":[
        "home",
        "residential"
    ],
    "wof:name":"Palmer House",
    "wof:placetype":"venue"
},
  "geometry": {"coordinates":[-118.248389,34.132722],"type":"Point"}
}