{
  "type": "Feature",
  "properties": {
    "addr:full":"902 K St Sacramento CA 95814",
    "addr:housenumber":"902",
    "addr:postcode":"95814",
    "addr:street":"K St",
    "iso:country":"US",
    "sg:address":"902 K St",
    "sg:city":"Sacramento",
    "sg:classifiers":[
        {
            "category":"Restaurant",
            "type":"Food & Drink"
        }
    ],
    "sg:menulink":"http://www.allmenus.com/ca/sacramento/123940-quiznos-sub/menu/",
    "sg:phone":"+1 916 329 7373",
    "sg:postcode":"95814",
    "sg:province":"CA",
    "sg:tags":[
        "wrap",
        "american",
        "sandwich"
    ],
    "wof:name":"Quiznos Sub",
    "wof:placetype":"venue"
},
  "geometry": {"coordinates":[-121.495133,38.579511],"type":"Point"}
}