{
  "type": "Feature",
  "properties": {
    "addr:full":"632 Jacobs Way Happy Camp CA 96039",
    "addr:housenumber":"632",
    "addr:postcode":"96039",
    "addr:street":"Jacobs Way",
    "iso:country":"US",
    "sg:address":"632 Jacobs Way",
    "sg:city":"Happy Camp",
    "sg:classifiers":[
        {
            "category":"Real Estate",
            "subcategory":"Real Estate Agent",
            "type":"Services"
        }
    ],
    "sg:phone":"+1 530 493 5434",
    "sg:postcode":"96039",
    "sg:province":"CA",
    "sg:tags":[
        "authorities",
        "housing"
    ],
    "wof:name":"Karuk Tribe Housing Authority",
    "wof:placetype":"venue"
},
  "geometry": {"coordinates":[-123.378083,41.802235],"type":"Point"}
}