{
  "type": "Feature",
  "properties": {
    "addr:full":"40 N Mentor Ave Pasadena CA 91106",
    "addr:housenumber":"40",
    "addr:postcode":"91106",
    "addr:street":"N Mentor Ave",
    "iso:country":"US",
    "sg:address":"40 N Mentor Ave",
    "sg:city":"Pasadena",
    "sg:classifiers":[
        {
            "category":"Bars & Pubs",
            "type":"Food & Drink"
        },
        {
            "category":"Restaurant",
            "type":"Food & Drink"
        }
    ],
    "sg:phone":"+1 626 795 7199",
    "sg:postcode":"91106",
    "sg:province":"CA",
    "sg:tags":[
        "tapa",
        "new",
        "american"
    ],
    "sg:website":"www.noirfoodandwine.com",
    "wof:name":"Noir Food & Wine",
    "wof:placetype":"venue"
},
  "geometry": {"coordinates":[-118.13041800000001,34.146595],"type":"Point"}
}