{
  "type": "Feature",
  "properties": {
    "iso:country":"US",
    "sg:address":"9 W Woodward Ave",
    "sg:city":"Alhambra",
    "sg:classifiers":[
        {
            "category":"Organizations",
            "subcategory":"Community Association",
            "type":"Services"
        }
    ],
    "sg:phone":"+1 626 281 7950",
    "sg:postcode":"91801",
    "sg:province":"CA",
    "sg:tags":[
        "fraternal"
    ],
    "wof:name":"Masonic Lodge",
    "wof:placetype":"venue"
},
  "geometry": {"coordinates":[-118.129572,34.097213],"type":"Point"}
}