{
  "type": "Feature",
  "properties": {
    "iso:country":"US",
    "sg:address":"1262 N College Ave",
    "sg:city":"Fresno",
    "sg:classifiers":[
        {
            "category":"Professional",
            "type":"Services"
        }
    ],
    "sg:phone":"+1 559 268 2771",
    "sg:postcode":"93728",
    "sg:province":"CA",
    "wof:name":"RE Visions Inc",
    "wof:placetype":"venue"
},
  "geometry": {"coordinates":[-119.797774,36.758348],"type":"Point"}
}