{
  "type": "Feature",
  "properties": {
    "iso:country":"US",
    "sg:address":"3801 E Willow St",
    "sg:city":"Long Beach",
    "sg:classifiers":[
        {
            "category":"Organizations",
            "subcategory":"Non-profit Organization",
            "type":"Services"
        }
    ],
    "sg:phone":"+1 562 427 7916",
    "sg:postcode":"90815",
    "sg:province":"CA",
    "sg:tags":[
        "service/non-profit",
        "community"
    ],
    "wof:name":"Jewish Family and Childrens Service",
    "wof:placetype":"venue"
},
  "geometry": {"coordinates":[-118.148003,33.804298],"type":"Point"}
}