{
  "type": "Feature",
  "properties": {
    "iso:country":"US",
    "sg:address":"3869 Ave del Sol",
    "sg:city":"Studio City",
    "sg:classifiers":[
        {
            "category":"Wholesale",
            "subcategory":"Apparel",
            "type":"Manufacturing & Wholesale Goods"
        }
    ],
    "sg:phone":"+1 818 769 1242",
    "sg:postcode":"91604",
    "sg:province":"CA",
    "sg:tags":[
        "mfg"
    ],
    "wof:name":"Commet Clothing Co",
    "wof:placetype":"venue"
},
  "geometry": {"coordinates":[-118.411604,34.138265],"type":"Point"}
}