{
  "type": "Feature",
  "properties": {
    "iso:country":"US",
    "sg:address":"950 S Fairmont Ave",
    "sg:city":"Lodi",
    "sg:classifiers":[
        {
            "category":"Health Services",
            "subcategory":"Nursing And Care Facility",
            "type":"Services"
        }
    ],
    "sg:phone":"+1 209 368 0693",
    "sg:postcode":"95240",
    "sg:province":"CA",
    "sg:tags":[
        "home",
        "convalescent"
    ],
    "wof:name":"Fairmont Rehabilitation Hosp",
    "wof:placetype":"venue"
},
  "geometry": {"coordinates":[-121.28568199999999,38.121386],"type":"Point"}
}