{
  "type": "Feature",
  "properties": {
    "addr:full":"100 Whitney Young Cir San Francisco CA 94124",
    "addr:housenumber":"100",
    "addr:postcode":"94124",
    "addr:street":"Whitney Young Cir",
    "iso:country":"US",
    "sg:address":"100 Whitney Young Cir",
    "sg:city":"San Francisco",
    "sg:classifiers":[
        {
            "category":"Education",
            "subcategory":"School",
            "type":"Public Place"
        }
    ],
    "sg:phone":"+1 415 824 4107",
    "sg:postcode":"94124",
    "sg:province":"CA",
    "sg:tags":[
        "academic",
        "special"
    ],
    "wof:name":"Joshua Marie Cameron Academy",
    "wof:placetype":"venue"
},
  "geometry": {"coordinates":[-122.382279,37.733632],"type":"Point"}
}