{
  "type": "Feature",
  "properties": {
    "iso:country":"US",
    "sg:address":"922 San Leandro Ave Ste F",
    "sg:city":"Mountain View",
    "sg:classifiers":[
        {
            "category":"Wholesale",
            "subcategory":"Computers",
            "type":"Manufacturing & Wholesale Goods"
        }
    ],
    "sg:phone":"+1 650 318 0156",
    "sg:postcode":"94043",
    "sg:province":"CA",
    "wof:name":"Ameris Corp",
    "wof:placetype":"venue"
},
  "geometry": {"coordinates":[-122.06999999999999,37.406601],"type":"Point"}
}