{
  "type": "Feature",
  "properties": {
    "addr:full":"287 Lawrence St Quincy CA 95971",
    "addr:housenumber":"287",
    "addr:postcode":"95971",
    "addr:street":"Lawrence St",
    "iso:country":"US",
    "sg:address":"287 Lawrence St",
    "sg:city":"Quincy",
    "sg:classifiers":[
        {
            "category":"Professional",
            "subcategory":"Advertising",
            "type":"Services"
        },
        {
            "category":"Wholesale",
            "subcategory":"Books, Periodicals, & Newspapers",
            "type":"Manufacturing & Wholesale Goods"
        }
    ],
    "sg:phone":"+1 530 283 0800",
    "sg:postcode":"95971",
    "sg:province":"CA",
    "sg:tags":[
        "print",
        "news",
        "dealers-wholesale"
    ],
    "sg:website":"http://www.plumasnews.com",
    "wof:name":"Feather River Bulletin",
    "wof:placetype":"venue"
},
  "geometry": {"coordinates":[-120.94197800000001,39.937729],"type":"Point"}
}