{
  "type": "Feature",
  "properties": {
    "iso:country":"US",
    "sg:address":"868 S Havenwood Cir",
    "sg:city":"Orange",
    "sg:classifiers":[
        {
            "category":"Organizations",
            "subcategory":"Non-profit Organization",
            "type":"Services"
        }
    ],
    "sg:phone":"+1 714 538 6400",
    "sg:postcode":"92869",
    "sg:province":"CA",
    "sg:tags":[
        "medical",
        "management"
    ],
    "wof:name":"Adaptive Technologies Group",
    "wof:placetype":"venue"
},
  "geometry": {"coordinates":[-117.808564,33.773793],"type":"Point"}
}