{
  "type": "Feature",
  "properties": {
    "addr:full":"9853 Smokey Ct Stockton CA 95209",
    "addr:housenumber":"9853",
    "addr:postcode":"95209",
    "addr:street":"Smokey Ct",
    "iso:country":"US",
    "sg:address":"9853 Smokey Ct",
    "sg:city":"Stockton",
    "sg:classifiers":[
        {
            "category":"Banks & Credit Unions",
            "subcategory":"Bank",
            "type":"Services"
        }
    ],
    "sg:phone":"+1 209 478 0701",
    "sg:postcode":"95209",
    "sg:province":"CA",
    "sg:tags":[
        "loan",
        "mortgage",
        "real estate"
    ],
    "wof:name":"Ambeck Mortgage Associates",
    "wof:placetype":"venue"
},
  "geometry": {"coordinates":[-121.32699599999999,38.041623],"type":"Point"}
}