{
  "type": "Feature",
  "properties": {
    "addr:full":"321 W Covina Blvd San Dimas CA 91773",
    "addr:housenumber":"321",
    "addr:postcode":"91773",
    "addr:street":"W Covina Blvd",
    "iso:country":"US",
    "sg:address":"321 W Covina Blvd",
    "sg:city":"San Dimas",
    "sg:classifiers":[
        {
            "category":"Manufacturing",
            "subcategory":"Retail Goods",
            "type":"Manufacturing & Wholesale Goods"
        }
    ],
    "sg:phone":"+1 909 599 2411",
    "sg:postcode":"91773",
    "sg:province":"CA",
    "sg:tags":[
        "manufacturer"
    ],
    "sg:website":"www.vuitton.com",
    "wof:name":"Louis Vuitton Mfg",
    "wof:placetype":"venue"
},
  "geometry": {"coordinates":[-117.812984,34.099587],"type":"Point"}
}