{
  "type": "Feature",
  "properties": {
    "iso:country":"US",
    "sg:address":"5330 Silverado Trl",
    "sg:city":"Napa",
    "sg:classifiers":[
        {
            "category":"Manufacturing",
            "subcategory":"Food",
            "type":"Manufacturing & Wholesale Goods"
        }
    ],
    "sg:phone":"+1 707 259 2200",
    "sg:postcode":"94558",
    "sg:province":"CA",
    "sg:tags":[
        "winery"
    ],
    "sg:website":"www.closduval.com",
    "wof:name":"Clos Du Val Winery",
    "wof:placetype":"venue"
},
  "geometry": {"coordinates":[-122.319529,38.391446],"type":"Point"}
}