{
  "type": "Feature",
  "properties": {
    "iso:country":"US",
    "sg:address":"7006 Coldwater Canyon Ave",
    "sg:city":"North Hollywood",
    "sg:classifiers":[
        {
            "category":"Bus Charters",
            "type":"Transportation"
        }
    ],
    "sg:phone":"+1 818 367 8330",
    "sg:postcode":"91605",
    "sg:province":"CA",
    "sg:tags":[
        "rental"
    ],
    "wof:name":"Riders Express",
    "wof:placetype":"venue"
},
  "geometry": {"coordinates":[-118.413714,34.196175],"type":"Point"}
}