{
  "type": "Feature",
  "properties": {
    "iso:country":"US",
    "sg:address":"2450 Crystal St",
    "sg:city":"Los Angeles",
    "sg:classifiers":[
        {
            "category":"Wholesale",
            "subcategory":"Durable Goods & Equipment",
            "type":"Manufacturing & Wholesale Goods"
        }
    ],
    "sg:phone":"+1 323 664 8956",
    "sg:postcode":"90039",
    "sg:province":"CA",
    "sg:tags":[
        "importer"
    ],
    "wof:name":"Karabetian Import & Export",
    "wof:placetype":"venue"
},
  "geometry": {"coordinates":[-118.255067,34.107777],"type":"Point"}
}