{
  "type": "Feature",
  "properties": {
    "addr:full":"12937 Rosecrans Ave Norwalk CA 90650",
    "addr:housenumber":"12937",
    "addr:postcode":"90650",
    "addr:street":"Rosecrans Ave",
    "iso:country":"US",
    "sg:address":"12937 Rosecrans Ave",
    "sg:city":"Norwalk",
    "sg:classifiers":[
        {
            "category":"Autos & Motor Vehicles",
            "subcategory":"Auto Supplies",
            "type":"Retail Goods"
        }
    ],
    "sg:phone":"+1 562 802 3161",
    "sg:postcode":"90650",
    "sg:province":"CA",
    "sg:tags":[
        "equipment",
        "racing",
        "car",
        "automobile"
    ],
    "wof:name":"Trendsetters Motor Sports",
    "wof:placetype":"venue"
},
  "geometry": {"coordinates":[-118.056173,33.902385],"type":"Point"}
}