{
  "type": "Feature",
  "properties": {
    "iso:country":"US",
    "sg:address":"19602 Gilmore St",
    "sg:city":"Reseda",
    "sg:classifiers":[
        {
            "category":"Building & Trades",
            "subcategory":"Landscaping Services",
            "type":"Services"
        }
    ],
    "sg:phone":"+1 818 708 1762",
    "sg:postcode":"91335",
    "sg:province":"CA",
    "wof:name":"Orozcos Gardening",
    "wof:placetype":"venue"
},
  "geometry": {"coordinates":[-118.559911,34.187391],"type":"Point"}
}