{
  "type": "Feature",
  "properties": {
    "iso:country":"US",
    "sg:address":"13191 Crossroads Pkwy N",
    "sg:city":"City Of Industry",
    "sg:classifiers":[
        {
            "category":"Professional",
            "subcategory":"Engineering",
            "type":"Services"
        }
    ],
    "sg:phone":"+1 562 695 0551",
    "sg:postcode":"91746",
    "sg:province":"CA",
    "sg:tags":[
        "engineer"
    ],
    "wof:name":"Willdan",
    "wof:placetype":"venue"
},
  "geometry": {"coordinates":[-118.015454,34.029683],"type":"Point"}
}