{
  "type": "Feature",
  "properties": {
    "addr:full":"22000 Rd 28 Tulare CA 93274",
    "addr:housenumber":"22000",
    "addr:postcode":"93274",
    "addr:street":"Rd 28",
    "iso:country":"US",
    "sg:address":"22000 Rd 28",
    "sg:city":"Tulare",
    "sg:classifiers":[
        {
            "category":"Food & Beverages",
            "subcategory":"Dairy",
            "type":"Retail Goods"
        }
    ],
    "sg:phone":"+1 559 686 7535",
    "sg:postcode":"93274",
    "sg:province":"CA",
    "sg:tags":[
        "farm",
        "field",
        "product",
        "crop"
    ],
    "wof:name":"Jacques Dairy & Farming",
    "wof:placetype":"venue"
},
  "geometry": {"coordinates":[-119.510688,36.191991],"type":"Point"}
}