{
  "type": "Feature",
  "properties": {
    "iso:country":"US",
    "sg:address":"5756 Pacific Ave",
    "sg:city":"Stockton",
    "sg:classifiers":[
        {
            "category":"Shopping",
            "subcategory":"Department Store",
            "type":"Retail Goods"
        }
    ],
    "sg:phone":"+1 209 957 0614",
    "sg:postcode":"95207",
    "sg:province":"CA",
    "wof:name":"Ross Dress For Less",
    "wof:placetype":"venue"
},
  "geometry": {"coordinates":[-121.316979,38.001983],"type":"Point"}
}