{
  "type": "Feature",
  "properties": {
    "addr:full":"4346 Slauson Ave Maywood CA 90270",
    "addr:postcode":"4346;90270",
    "addr:street":"Slauson Ave",
    "iso:country":"US",
    "sg:address":"4346 Slauson Ave",
    "sg:city":"Maywood",
    "sg:classifiers":[
        {
            "category":"Shopping",
            "subcategory":"Mobile Phones",
            "type":"Retail Goods"
        }
    ],
    "sg:phone":"+1 323 560 4026",
    "sg:postcode":"90270",
    "sg:province":"CA",
    "wof:name":"Big Cellular",
    "wof:placetype":"venue"
},
  "geometry": {"coordinates":[-118.188311,33.987146],"type":"Point"}
}