{
  "type": "Feature",
  "properties": {
    "iso:country":"US",
    "sg:address":"607 E Washington St",
    "sg:city":"Petaluma",
    "sg:classifiers":[
        {
            "category":"Restaurant",
            "type":"Food & Drink"
        }
    ],
    "sg:phone":"+1 707 773 3885",
    "sg:postcode":"94952",
    "sg:province":"CA",
    "wof:name":"Teriyaki House",
    "wof:placetype":"venue"
},
  "geometry": {"coordinates":[-122.634303,38.240141],"type":"Point"}
}