{
  "type": "Feature",
  "properties": {
    "iso:country":"US",
    "sg:address":"3 37th Ave Ste 10",
    "sg:city":"San Mateo",
    "sg:classifiers":[
        {
            "category":"Real Estate",
            "subcategory":"Architect",
            "type":"Services"
        }
    ],
    "sg:phone":"+1 650 286 1996",
    "sg:postcode":"94403",
    "sg:province":"CA",
    "wof:name":"Burns & Nettle Architects",
    "wof:placetype":"venue"
},
  "geometry": {"coordinates":[-122.294645,37.534277],"type":"Point"}
}