{
  "type": "Feature",
  "properties": {
    "iso:country":"US",
    "sg:address":"6812 Fruitridge Rd",
    "sg:city":"Sacramento",
    "sg:classifiers":[
        {
            "category":"Building & Trades",
            "subcategory":"Landscaping Services",
            "type":"Services"
        }
    ],
    "sg:phone":"+1 916 383 1530",
    "sg:postcode":"95820",
    "sg:province":"CA",
    "sg:tags":[
        "landscape",
        "contractor"
    ],
    "wof:name":"Cutting Edge Landscaping",
    "wof:placetype":"venue"
},
  "geometry": {"coordinates":[-121.423967,38.524996],"type":"Point"}
}