{
  "type": "Feature",
  "properties": {
    "addr:full":"7809 Hollywood Blvd Los Angeles CA 90046",
    "addr:housenumber":"7809",
    "addr:postcode":"90046",
    "addr:street":"Hollywood Blvd",
    "iso:country":"US",
    "sg:address":"7809 Hollywood Blvd",
    "sg:city":"Los Angeles",
    "sg:classifiers":[
        {
            "category":"Communications",
            "subcategory":"Film & Video Production",
            "type":"Services"
        }
    ],
    "sg:phone":"+1 323 465 5800",
    "sg:postcode":"90046",
    "sg:province":"CA",
    "sg:tags":[
        "television"
    ],
    "wof:name":"Televentures",
    "wof:placetype":"venue"
},
  "geometry": {"coordinates":[-118.36034600000001,34.101648],"type":"Point"}
}