{
  "type": "Feature",
  "properties": {
    "addr:full":"11875 Palm Dr Desert Hot Spgs CA 92240",
    "addr:housenumber":"11875",
    "addr:postcode":"92240",
    "addr:street":"Palm Dr;Spgs",
    "iso:country":"US",
    "sg:address":"11875 Palm Dr",
    "sg:city":"Desert Hot Spgs",
    "sg:classifiers":[
        {
            "category":"Retail",
            "subcategory":"Auto Repair",
            "type":"Services"
        }
    ],
    "sg:phone":"+1 760 251 3452",
    "sg:postcode":"92240",
    "sg:province":"CA",
    "sg:tags":[
        "repairing",
        "automobile"
    ],
    "wof:name":"Grandpa Bills Automotive",
    "wof:placetype":"venue"
},
  "geometry": {"coordinates":[-116.50144,33.962641],"type":"Point"}
}