{
  "type": "Feature",
  "properties": {
    "iso:country":"US",
    "sg:address":"1088 W Base Line St",
    "sg:city":"San Bernardino",
    "sg:classifiers":[
        {
            "category":"Wholesale",
            "subcategory":"Auto Parts",
            "type":"Manufacturing & Wholesale Goods"
        }
    ],
    "sg:phone":"+1 909 884 5118",
    "sg:postcode":"92411",
    "sg:province":"CA",
    "sg:tags":[
        "tire"
    ],
    "wof:name":"San Roberto Tire Shop",
    "wof:placetype":"venue"
},
  "geometry": {"coordinates":[-117.308371,34.12142],"type":"Point"}
}