{
  "type": "Feature",
  "properties": {
    "addr:full":"5010 Ravelle Ct Paradise CA 95969",
    "addr:housenumber":"5010",
    "addr:postcode":"95969",
    "addr:street":"Ravelle Ct",
    "iso:country":"US",
    "sg:address":"5010 Ravelle Ct",
    "sg:city":"Paradise",
    "sg:classifiers":[
        {
            "category":"Professional",
            "subcategory":"Printing & Photocopies",
            "type":"Services"
        }
    ],
    "sg:phone":"+1 530 877 0510",
    "sg:postcode":"95969",
    "sg:province":"CA",
    "sg:tags":[
        "lithographer"
    ],
    "wof:name":"Leaving Prints",
    "wof:placetype":"venue"
},
  "geometry": {"coordinates":[-121.575109,39.726411],"type":"Point"}
}