{
  "type": "Feature",
  "properties": {
    "addr:full":"23232 Peralta Dr Laguna Hills CA 92653",
    "addr:housenumber":"23232",
    "addr:postcode":"92653",
    "addr:street":"Peralta Dr",
    "iso:country":"US",
    "sg:address":"23232 Peralta Dr",
    "sg:city":"Laguna Hills",
    "sg:classifiers":[
        {
            "category":"Insurance",
            "subcategory":"Insurance Agent",
            "type":"Services"
        }
    ],
    "sg:phone":"+1 949 586 3604",
    "sg:postcode":"92653",
    "sg:province":"CA",
    "wof:name":"Modern Woodmen of America",
    "wof:placetype":"venue"
},
  "geometry": {"coordinates":[-117.72517499999999,33.624856],"type":"Point"}
}