{
  "type": "Feature",
  "properties": {
    "addr:full":"1913 W Magnolia Blvd Burbank CA 91506",
    "addr:housenumber":"1913",
    "addr:postcode":"91506",
    "addr:street":"W Magnolia Blvd",
    "iso:country":"US",
    "sg:address":"1913 W Magnolia Blvd",
    "sg:city":"Burbank",
    "sg:classifiers":[
        {
            "category":"Building & Trades",
            "subcategory":"Construction",
            "type":"Services"
        }
    ],
    "sg:phone":"+1 818 841 2011",
    "sg:postcode":"91506",
    "sg:province":"CA",
    "sg:tags":[
        "equipment",
        "contractor",
        "drywall",
        "supply"
    ],
    "wof:name":"Rudy Carrillo Drywall Inc",
    "wof:placetype":"venue"
},
  "geometry": {"coordinates":[-118.32874,34.174016],"type":"Point"}
}