{
  "type": "Feature",
  "properties": {
    "addr:full":"4375 Genesee Ave San Diego CA 92117",
    "addr:housenumber":"4375",
    "addr:postcode":"92117",
    "addr:street":"Genesee Ave",
    "iso:country":"US",
    "sg:address":"4375 Genesee Ave",
    "sg:city":"San Diego",
    "sg:classifiers":[
        {
            "category":"Fast Food",
            "type":"Food & Drink"
        }
    ],
    "sg:phone":"+1 858 627 9738",
    "sg:postcode":"92117",
    "sg:province":"CA",
    "sg:tags":[
        "burger"
    ],
    "sg:website":"www.jackinthebox.com",
    "wof:name":"Jack in the Box",
    "wof:placetype":"venue"
},
  "geometry": {"coordinates":[-117.18347300000001,32.822976],"type":"Point"}
}