{
  "type": "Feature",
  "properties": {
    "addr:full":"4310 San Fernando Rd Glendale CA 91204",
    "addr:housenumber":"4310",
    "addr:postcode":"91204",
    "addr:street":"San Fernando Rd",
    "iso:country":"US",
    "sg:address":"4310 San Fernando Rd",
    "sg:city":"Glendale",
    "sg:classifiers":[
        {
            "category":"Home & Garden",
            "subcategory":"Carpets & Floor Coverings",
            "type":"Retail Goods"
        }
    ],
    "sg:phone":"+1 818 265 1900",
    "sg:postcode":"91204",
    "sg:province":"CA",
    "sg:tags":[
        "dealer",
        "rug"
    ],
    "sg:website":"www.famefloor.com",
    "wof:name":"Fame Floor Covering Inc",
    "wof:placetype":"venue"
},
  "geometry": {"coordinates":[-118.26106299999999,34.130823],"type":"Point"}
}