{
  "type": "Feature",
  "properties": {
    "addr:full":"568 W Grand Ave Oakland CA 94612",
    "addr:housenumber":"568",
    "addr:postcode":"94612",
    "addr:street":"W Grand Ave",
    "iso:country":"US",
    "sg:address":"568 W Grand Ave",
    "sg:city":"Oakland",
    "sg:classifiers":[
        {
            "category":"Government",
            "subcategory":"Office",
            "type":"Public Place"
        }
    ],
    "sg:phone":"+1 510 268 7940",
    "sg:postcode":"94612",
    "sg:province":"CA",
    "sg:tags":[
        "county",
        "program",
        "health"
    ],
    "wof:name":"Alameda County Public Health",
    "wof:placetype":"venue"
},
  "geometry": {"coordinates":[-122.269876,37.812158],"type":"Point"}
}