{
  "type": "Feature",
  "properties": {
    "addr:full":"5252 Orange Avenue Ste 108 Cypress CA 90630",
    "addr:housenumber":"5252",
    "addr:postcode":"90630",
    "addr:street":"Orange Avenue Ste 108",
    "iso:country":"US",
    "sg:address":"5252 Orange Avenue Ste 108",
    "sg:city":"Cypress",
    "sg:classifiers":[
        {
            "category":"Real Estate",
            "subcategory":"Real Estate Services",
            "type":"Services"
        }
    ],
    "sg:phone":"+1 714 828 2121",
    "sg:postcode":"90630",
    "sg:province":"CA",
    "wof:name":"Sueno Financial",
    "wof:placetype":"venue"
},
  "geometry": {"coordinates":[-118.040677,33.823785],"type":"Point"}
}