{
  "type": "Feature",
  "properties": {
    "addr:full":"17490 S Westlawn Ave Riverdale CA 93656",
    "addr:housenumber":"17490",
    "addr:postcode":"93656",
    "addr:street":"S Westlawn Ave",
    "iso:country":"US",
    "sg:address":"17490 S Westlawn Ave",
    "sg:city":"Riverdale",
    "sg:classifiers":[
        {
            "category":"Farming",
            "subcategory":"Orchard",
            "type":"Manufacturing & Wholesale Goods"
        }
    ],
    "sg:phone":"+1 559 866 5464",
    "sg:postcode":"93656",
    "sg:province":"CA",
    "wof:name":"Leoni Farms",
    "wof:placetype":"venue"
},
  "geometry": {"coordinates":[-119.95926,36.478442],"type":"Point"}
}