{
  "type": "Feature",
  "properties": {
    "iso:country":"US",
    "sg:address":"26387 E 9th St",
    "sg:city":"Highland",
    "sg:classifiers":[
        {
            "category":"Shopping",
            "subcategory":"Used Merchandise",
            "type":"Retail Goods"
        }
    ],
    "sg:phone":"+1 909 862 2837",
    "sg:postcode":"92346",
    "sg:province":"CA",
    "wof:name":"Red Cottage Antique Shop The",
    "wof:placetype":"venue"
},
  "geometry": {"coordinates":[-117.227266,34.115651],"type":"Point"}
}