{
  "type": "Feature",
  "properties": {
    "addr:full":"333 Hegenberger Rd Suite 700 Oakland CA 94621",
    "addr:housenumber":"333",
    "addr:postcode":"94621",
    "addr:street":"Hegenberger Rd Suite 700",
    "iso:country":"US",
    "sg:address":"333 Hegenberger Rd Suite 700",
    "sg:city":"Oakland",
    "sg:classifiers":[
        {
            "category":"Health Services",
            "subcategory":"Nursing And Care Facility",
            "type":"Services"
        },
        {
            "category":"Health Services",
            "subcategory":"Health Practitioner",
            "type":"Services"
        }
    ],
    "sg:phone":"+1 510 893 2273",
    "sg:postcode":"94621",
    "sg:province":"CA",
    "sg:tags":[
        "home",
        "physician",
        "nurse",
        "eldercare-home",
        "assistant"
    ],
    "wof:name":"Pathways Private Duty",
    "wof:placetype":"venue"
},
  "geometry": {"coordinates":[-122.197616,37.735088],"type":"Point"}
}