{
  "type": "Feature",
  "properties": {
    "addr:full":"987 Colmore Way Galt CA 95632",
    "addr:housenumber":"987",
    "addr:postcode":"95632",
    "addr:street":"Colmore Way",
    "iso:country":"US",
    "sg:address":"987 Colmore Way",
    "sg:city":"Galt",
    "sg:classifiers":[
        {
            "category":"Shopping",
            "subcategory":"Musical Instruments",
            "type":"Retail Goods"
        }
    ],
    "sg:phone":"+1 209 745 3735",
    "sg:postcode":"95632",
    "sg:province":"CA",
    "sg:tags":[
        "vintage",
        "used",
        "records",
        "tapes",
        "cd's"
    ],
    "wof:name":"Jebby And The Trees",
    "wof:placetype":"venue"
},
  "geometry": {"coordinates":[-121.290637,38.273254],"type":"Point"}
}