{
  "type": "Feature",
  "properties": {
    "addr:full":"1100 J St Sacramento CA 95814",
    "addr:housenumber":"1100",
    "addr:postcode":"95814",
    "addr:street":"J St",
    "iso:country":"US",
    "sg:address":"1100 J St",
    "sg:city":"Sacramento",
    "sg:classifiers":[
        {
            "category":"Government",
            "subcategory":"Office",
            "type":"Public Place"
        }
    ],
    "sg:phone":"+1 916 327 5640",
    "sg:postcode":"95814",
    "sg:province":"CA",
    "sg:tags":[
        "program",
        "nonprofit",
        "trust",
        "administrative"
    ],
    "wof:name":"Employment Training Panel",
    "wof:placetype":"venue"
},
  "geometry": {"coordinates":[-121.490799,38.579603],"type":"Point"}
}