{
  "type": "Feature",
  "properties": {
    "iso:country":"US",
    "sg:address":"450 E Alessandro Blvd",
    "sg:city":"Riverside",
    "sg:classifiers":[
        {
            "category":"Utilities",
            "subcategory":"Water",
            "type":"Services"
        }
    ],
    "sg:phone":"+1 951 789 5000",
    "sg:postcode":"92508",
    "sg:province":"CA",
    "sg:tags":[
        "company",
        "sewage"
    ],
    "wof:name":"Western Municipal Water Dist",
    "wof:placetype":"venue"
},
  "geometry": {"coordinates":[-117.32118800000001,33.916516],"type":"Point"}
}