{
  "type": "Feature",
  "properties": {
    "addr:full":"3134 Shoemaker Pl Marina CA 93933",
    "addr:housenumber":"3134",
    "addr:postcode":"93933",
    "addr:street":"Shoemaker Pl",
    "iso:country":"US",
    "sg:address":"3134 Shoemaker Pl",
    "sg:city":"Marina",
    "sg:classifiers":[
        {
            "category":"Communications",
            "subcategory":"Film & Video Production",
            "type":"Services"
        }
    ],
    "sg:phone":"+1 831 582 9500",
    "sg:postcode":"93933",
    "sg:province":"CA",
    "sg:tags":[
        "motion",
        "picture",
        "studio",
        "producer"
    ],
    "wof:name":"Cortee Mijo Film Invest",
    "wof:placetype":"venue"
},
  "geometry": {"coordinates":[-121.806656,36.689092],"type":"Point"}
}