{
  "type": "Feature",
  "properties": {
    "addr:full":"250 Conejo Ridge Ave Thousand Oaks CA 91361",
    "addr:housenumber":"250",
    "addr:postcode":"91361",
    "addr:street":"Conejo Ridge Ave",
    "iso:country":"US",
    "sg:address":"250 Conejo Ridge Ave",
    "sg:city":"Thousand Oaks",
    "sg:classifiers":[
        {
            "category":"Home & Garden",
            "subcategory":"Furniture",
            "type":"Retail Goods"
        }
    ],
    "sg:phone":"+1 805 496 4804",
    "sg:postcode":"91361",
    "sg:province":"CA",
    "wof:name":"PTS Home & Office Furniture",
    "wof:placetype":"venue"
},
  "geometry": {"coordinates":[-118.84635,34.170219],"type":"Point"}
}