{
  "type": "Feature",
  "properties": {
    "iso:country":"US",
    "sg:address":"27529 Ynez Rd",
    "sg:city":"Temecula",
    "sg:classifiers":[
        {
            "category":"Ice Cream",
            "type":"Food & Drink"
        }
    ],
    "sg:menulink":"http://www.allmenus.com/ca/murrieta/217596-ben--jerrys/menu/",
    "sg:postcode":"92591",
    "sg:province":"CA",
    "sg:tags":[
        "american"
    ],
    "wof:name":"Ben & Jerry's",
    "wof:placetype":"venue"
},
  "geometry": {"coordinates":[-117.149755,33.504545],"type":"Point"}
}