{
  "type": "Feature",
  "properties": {
    "iso:country":"US",
    "sg:address":"13147 Lamplite Ln",
    "sg:city":"Lakeside",
    "sg:classifiers":[
        {
            "category":"Professional",
            "type":"Services"
        }
    ],
    "sg:phone":"+1 619 938 0536",
    "sg:postcode":"92040",
    "sg:province":"CA",
    "wof:name":"James R Waters",
    "wof:placetype":"venue"
},
  "geometry": {"coordinates":[-116.90884800000001,32.835517],"type":"Point"}
}