{
  "type": "Feature",
  "properties": {
    "iso:country":"US",
    "sg:address":"1380 Bancroft Ave",
    "sg:city":"San Leandro",
    "sg:classifiers":[
        {
            "category":"Shopping",
            "subcategory":"Beauty & Cosmetics",
            "type":"Retail Goods"
        }
    ],
    "sg:phone":"+1 510 357 5124",
    "sg:postcode":"94577",
    "sg:province":"CA",
    "sg:tags":[
        "merchandise"
    ],
    "wof:name":"Skin Essence",
    "wof:placetype":"venue"
},
  "geometry": {"coordinates":[-122.147747,37.727021],"type":"Point"}
}