{
  "type": "Feature",
  "properties": {
    "addr:full":"5465 Valley Ridge Ave Los Angeles CA 90043",
    "addr:housenumber":"5465",
    "addr:postcode":"90043",
    "addr:street":"Valley Ridge Ave",
    "iso:country":"US",
    "sg:address":"5465 Valley Ridge Ave",
    "sg:city":"Los Angeles",
    "sg:classifiers":[
        {
            "category":"Arts & Performance",
            "subcategory":"Theater",
            "type":"Entertainment"
        }
    ],
    "sg:phone":"+1 323 290 1403",
    "sg:postcode":"90043",
    "sg:province":"CA",
    "sg:tags":[
        "talent",
        "agency",
        "casting"
    ],
    "wof:name":"Creative Artists Zone",
    "wof:placetype":"venue"
},
  "geometry": {"coordinates":[-118.344883,33.992404],"type":"Point"}
}