{
  "type": "Feature",
  "properties": {
    "iso:country":"US",
    "sg:address":"510 Civic Center Dr. Ste A",
    "sg:city":"Vista",
    "sg:classifiers":[
        {
            "category":"Professional",
            "subcategory":"Computer Services",
            "type":"Services"
        }
    ],
    "sg:phone":"+1 877 720 8670",
    "sg:postcode":"92084",
    "sg:province":"CA",
    "sg:tags":[
        "website-design",
        "online-marketing",
        "seo",
        "search-engine-optimazation",
        "programming",
        "creative-design",
        "marketing"
    ],
    "sg:website":"http://www.newwavemktg.com",
    "wof:name":"New Wave Enterprises",
    "wof:placetype":"venue"
},
  "geometry": {"coordinates":[-117.182081,33.192779],"type":"Point"}
}