{
  "type": "Feature",
  "properties": {
    "iso:country":"US",
    "sg:address":"340 W Caldwell Ave",
    "sg:city":"Visalia",
    "sg:classifiers":[
        {
            "category":"Building & Trades",
            "subcategory":"Construction",
            "type":"Services"
        }
    ],
    "sg:phone":"+1 559 732 1230",
    "sg:postcode":"93277",
    "sg:province":"CA",
    "wof:name":"Atlantis Pools & Design Inc",
    "wof:placetype":"venue"
},
  "geometry": {"coordinates":[-119.293758,36.298245],"type":"Point"}
}