{
  "type": "Feature",
  "properties": {
    "addr:full":"251 W Channel Rd Benicia CA 94510",
    "addr:housenumber":"251",
    "addr:postcode":"94510",
    "addr:street":"W Channel Rd",
    "iso:country":"US",
    "sg:address":"251 W Channel Rd",
    "sg:city":"Benicia",
    "sg:classifiers":[
        {
            "category":"Manufacturing",
            "subcategory":"Tools & Machinery",
            "type":"Manufacturing & Wholesale Goods"
        }
    ],
    "sg:phone":"+1 707 747 7585",
    "sg:postcode":"94510",
    "sg:province":"CA",
    "sg:tags":[
        "pump"
    ],
    "sg:website":"www.kroghpump.com",
    "wof:name":"Krogh Pump Co",
    "wof:placetype":"venue"
},
  "geometry": {"coordinates":[-122.139914,38.08264],"type":"Point"}
}