{
  "type": "Feature",
  "properties": {
    "iso:country":"US",
    "sg:address":"501 Vernon St",
    "sg:city":"Roseville",
    "sg:classifiers":[
        {
            "category":"Retail",
            "subcategory":"Laundry & Dry Cleaning",
            "type":"Services"
        },
        {
            "category":"Building & Trades",
            "subcategory":"Construction",
            "type":"Services"
        },
        {
            "category":"Home & Garden",
            "subcategory":"Carpets & Floor Coverings",
            "type":"Retail Goods"
        }
    ],
    "sg:phone":"+1 916 782 1303",
    "sg:postcode":"95678",
    "sg:province":"CA",
    "sg:tags":[
        "cleaner",
        "installation",
        "rug",
        "tile-contractors"
    ],
    "wof:name":"Abbey Carpet",
    "wof:placetype":"venue"
},
  "geometry": {"coordinates":[-121.28634599999999,38.747169],"type":"Point"}
}