{
  "type": "Feature",
  "properties": {
    "addr:full":"362 Cam Manzanas Thousand Oaks CA 91360",
    "addr:housenumber":"362",
    "addr:postcode":"91360",
    "addr:street":"Cam Manzanas",
    "iso:country":"US",
    "sg:address":"362 Cam Manzanas",
    "sg:city":"Thousand Oaks",
    "sg:classifiers":[
        {
            "category":"Health Services",
            "subcategory":"Clinic",
            "type":"Services"
        }
    ],
    "sg:phone":"+1 805 446 6172",
    "sg:postcode":"91360",
    "sg:province":"CA",
    "sg:tags":[
        "home"
    ],
    "wof:name":"Hillside In-Home Svc",
    "wof:placetype":"venue"
},
  "geometry": {"coordinates":[-118.88402600000001,34.196327],"type":"Point"}
}