{
  "type": "Feature",
  "properties": {
    "addr:full":"5701 Redwood Dr Rohnert Park CA 94928",
    "addr:housenumber":"5701",
    "addr:postcode":"94928",
    "addr:street":"Redwood Dr",
    "iso:country":"US",
    "sg:address":"5701 Redwood Dr",
    "sg:city":"Rohnert Park",
    "sg:classifiers":[
        {
            "category":"Wholesale",
            "subcategory":"Office Equipment",
            "type":"Manufacturing & Wholesale Goods"
        }
    ],
    "sg:phone":"+1 707 778 9000",
    "sg:postcode":"94928",
    "sg:province":"CA",
    "sg:tags":[
        "machine",
        "duplicating",
        "copying"
    ],
    "wof:name":"MBA Of California",
    "wof:placetype":"venue"
},
  "geometry": {"coordinates":[-122.713652,38.353829],"type":"Point"}
}