{
  "type": "Feature",
  "properties": {
    "addr:full":"4901 Auburn Boulevard Sacramento CA 95841",
    "addr:housenumber":"4901",
    "addr:postcode":"95841",
    "addr:street":"Auburn Boulevard",
    "iso:country":"US",
    "sg:address":"4901 Auburn Boulevard",
    "sg:city":"Sacramento",
    "sg:classifiers":[
        {
            "category":"Restaurant",
            "type":"Food & Drink"
        }
    ],
    "sg:phone":"+1 916 338 4444",
    "sg:postcode":"95841",
    "sg:province":"CA",
    "wof:name":"East Meets West Super Market",
    "wof:placetype":"venue"
},
  "geometry": {"coordinates":[-121.349998,38.657902],"type":"Point"}
}