{
  "type": "Feature",
  "properties": {
    "iso:country":"US",
    "sg:address":"6125 Imperial Ave",
    "sg:city":"San Diego",
    "sg:classifiers":[
        {
            "category":"Building & Trades",
            "subcategory":"Construction",
            "type":"Services"
        }
    ],
    "sg:phone":"+1 619 263 9791",
    "sg:postcode":"92114",
    "sg:province":"CA",
    "sg:tags":[
        "contractor"
    ],
    "sg:website":"www.bcasd.org",
    "wof:name":"Black Contractors-San Diego",
    "wof:placetype":"venue"
},
  "geometry": {"coordinates":[-117.064571,32.709672],"type":"Point"}
}