{
  "type": "Feature",
  "properties": {
    "addr:full":"2220 S Beverly Glen Blvd Los Angeles CA 90064",
    "addr:housenumber":"2220",
    "addr:postcode":"90064",
    "addr:street":"S Beverly Glen Blvd",
    "iso:country":"US",
    "sg:address":"2220 S Beverly Glen Blvd",
    "sg:city":"Los Angeles",
    "sg:classifiers":[
        {
            "category":"Professional",
            "type":"Services"
        }
    ],
    "sg:phone":"+1 310 556 3115",
    "sg:postcode":"90064",
    "sg:province":"CA",
    "wof:name":"Jimmys 411 Classics",
    "wof:placetype":"venue"
},
  "geometry": {"coordinates":[-118.41986900000001,34.049755],"type":"Point"}
}