{
  "type": "Feature",
  "properties": {
    "iso:country":"US",
    "sg:address":"22345 Meekland Ave",
    "sg:city":"Hayward",
    "sg:classifiers":[
        {
            "category":"Building & Trades",
            "subcategory":"Construction",
            "type":"Services"
        }
    ],
    "sg:phone":"+1 510 733 5540",
    "sg:postcode":"94541",
    "sg:province":"CA",
    "sg:tags":[
        "painter"
    ],
    "wof:name":"United Pro Painting",
    "wof:placetype":"venue"
},
  "geometry": {"coordinates":[-122.100998,37.668598],"type":"Point"}
}