{
  "type": "Feature",
  "properties": {
    "addr:full":"1703 Howard Rd Madera CA 93637",
    "addr:housenumber":"1703",
    "addr:postcode":"93637",
    "addr:street":"Howard Rd",
    "iso:country":"US",
    "sg:address":"1703 Howard Rd",
    "sg:city":"Madera",
    "sg:classifiers":[
        {
            "category":"Banks & Credit Unions",
            "subcategory":"Bank",
            "type":"Services"
        }
    ],
    "sg:phone":"+1 559 674 3200",
    "sg:postcode":"93637",
    "sg:province":"CA",
    "sg:tags":[
        "loan",
        "real estate"
    ],
    "wof:name":"Santa Fe Mortgage",
    "wof:placetype":"venue"
},
  "geometry": {"coordinates":[-120.07780200000001,36.952828],"type":"Point"}
}