{
  "type": "Feature",
  "properties": {
    "addr:full":"355 N Lantana St Camarillo CA 93010",
    "addr:housenumber":"355",
    "addr:postcode":"93010",
    "addr:street":"N Lantana St",
    "iso:country":"US",
    "sg:address":"355 N Lantana St",
    "sg:city":"Camarillo",
    "sg:classifiers":[
        {
            "category":"Retail",
            "subcategory":"Auto Repair",
            "type":"Services"
        }
    ],
    "sg:phone":"+1 805 383 2660",
    "sg:postcode":"93010",
    "sg:province":"CA",
    "sg:tags":[
        "repairing",
        "tire"
    ],
    "wof:name":"Dill's Tire Svc",
    "wof:placetype":"venue"
},
  "geometry": {"coordinates":[-119.055184,34.21974],"type":"Point"}
}