{
  "type": "Feature",
  "properties": {
    "addr:full":"1900 North Highway 101 Encinitas CA 92024",
    "addr:housenumber":"1900",
    "addr:postcode":"92024",
    "addr:street":"North Highway 101",
    "iso:country":"US",
    "sg:address":"1900 North Highway 101",
    "sg:city":"Encinitas",
    "sg:classifiers":[
        {
            "category":"Restaurant",
            "type":"Food & Drink"
        },
        {
            "category":"Home & Garden",
            "subcategory":"Building Materials",
            "type":"Retail Goods"
        }
    ],
    "sg:phone":"+1 760 633 3100",
    "sg:postcode":"92024",
    "sg:province":"CA",
    "sg:tags":[
        "flavor",
        "local",
        "supply"
    ],
    "sg:website":"www.rebelrents.com/locations/enc...",
    "wof:name":"Rebel Rents",
    "wof:placetype":"venue"
},
  "geometry": {"coordinates":[-117.308189,33.081242],"type":"Point"}
}