{
  "type": "Feature",
  "properties": {
    "addr:full":"1134 Shotwell St San Francisco CA 94110",
    "addr:housenumber":"1134",
    "addr:postcode":"94110",
    "addr:street":"Shotwell St",
    "iso:country":"US",
    "sg:address":"1134 Shotwell St",
    "sg:city":"San Francisco",
    "sg:classifiers":[
        {
            "category":"Building & Trades",
            "subcategory":"Cleaning & Sanitation",
            "type":"Services"
        }
    ],
    "sg:phone":"+1 510 625 8090",
    "sg:postcode":"94110",
    "sg:province":"CA",
    "sg:tags":[
        "house"
    ],
    "wof:name":"A & J Heavy Duty House Clean",
    "wof:placetype":"venue"
},
  "geometry": {"coordinates":[-122.414978,37.749787],"type":"Point"}
}