{
  "type": "Feature",
  "properties": {
    "iso:country":"US",
    "sg:address":"3878 W 6th St",
    "sg:city":"Los Angeles",
    "sg:classifiers":[
        {
            "category":"Shopping",
            "subcategory":"Clothing, Apparel, & Fashions",
            "type":"Retail Goods"
        }
    ],
    "sg:phone":"+1 213 252 0119",
    "sg:postcode":"90020",
    "sg:province":"CA",
    "wof:name":"Prime Collection Inc",
    "wof:placetype":"venue"
},
  "geometry": {"coordinates":[-118.30724,34.063452],"type":"Point"}
}