{
  "type": "Feature",
  "properties": {
    "iso:country":"US",
    "sg:address":"2631 E 124th St",
    "sg:city":"Compton",
    "sg:classifiers":[
        {
            "category":"Manufacturing",
            "subcategory":"Metals",
            "type":"Manufacturing & Wholesale Goods"
        }
    ],
    "sg:phone":"+1 310 638 6907",
    "sg:postcode":"90222",
    "sg:province":"CA",
    "sg:tags":[
        "metalwork",
        "center",
        "architectural",
        "mfg"
    ],
    "wof:name":"Three Bros Pipe",
    "wof:placetype":"venue"
},
  "geometry": {"coordinates":[-118.226238,33.919896],"type":"Point"}
}