{
  "type": "Feature",
  "properties": {
    "addr:full":"607 W 77th St Los Angeles CA 90044",
    "addr:housenumber":"607",
    "addr:postcode":"90044",
    "addr:street":"W 77Th St",
    "iso:country":"US",
    "sg:address":"607 W 77th St",
    "sg:city":"Los Angeles",
    "sg:classifiers":[
        {
            "category":"Freight",
            "type":"Transportation"
        }
    ],
    "sg:phone":"+1 323 778 4270",
    "sg:postcode":"90044",
    "sg:province":"CA",
    "sg:tags":[
        "operator",
        "local",
        "trucking"
    ],
    "wof:name":"Marota Trucking Inc",
    "wof:placetype":"venue"
},
  "geometry": {"coordinates":[-118.285791,33.969853],"type":"Point"}
}