{
  "type": "Feature",
  "properties": {
    "addr:full":"1101 W Valley Blvd Alhambra CA 91803",
    "addr:housenumber":"1101",
    "addr:postcode":"91803",
    "addr:street":"W Valley Blvd",
    "iso:country":"US",
    "sg:address":"1101 W Valley Blvd",
    "sg:city":"Alhambra",
    "sg:classifiers":[
        {
            "category":"Banks & Credit Unions",
            "subcategory":"Bank",
            "type":"Services"
        }
    ],
    "sg:phone":"+1 626 943 1138",
    "sg:postcode":"91803",
    "sg:province":"CA",
    "wof:name":"First United Bank",
    "wof:placetype":"venue"
},
  "geometry": {"coordinates":[-118.13596699999999,34.077822],"type":"Point"}
}