{
  "type": "Feature",
  "properties": {
    "addr:full":"6655 Hollywood Blvd Los Angeles CA 90028",
    "addr:housenumber":"6655",
    "addr:postcode":"90028",
    "addr:street":"Hollywood Blvd",
    "iso:country":"US",
    "sg:address":"6655 Hollywood Blvd",
    "sg:city":"Los Angeles",
    "sg:classifiers":[
        {
            "category":"Shopping",
            "subcategory":"Tobacco",
            "type":"Retail Goods"
        }
    ],
    "sg:phone":"+1 323 467 7006",
    "sg:postcode":"90028",
    "sg:province":"CA",
    "sg:tags":[
        "shop"
    ],
    "wof:name":"Third I Smoke Shop",
    "wof:placetype":"venue"
},
  "geometry": {"coordinates":[-118.334986,34.101776],"type":"Point"}
}