{
  "type": "Feature",
  "properties": {
    "iso:country":"US",
    "sg:address":"608 Monterey Pass Rd",
    "sg:city":"Monterey Park",
    "sg:classifiers":[
        {
            "category":"Manufacturing",
            "subcategory":"Food",
            "type":"Manufacturing & Wholesale Goods"
        }
    ],
    "sg:phone":"+1 626 289 5054",
    "sg:postcode":"91754",
    "sg:province":"CA",
    "sg:tags":[
        "frozen",
        "preparation",
        "specialty",
        "mfg"
    ],
    "wof:name":"Sierra Madre Foods Inc",
    "wof:placetype":"venue"
},
  "geometry": {"coordinates":[-118.147049,34.055796],"type":"Point"}
}