{
  "type": "Feature",
  "properties": {
    "addr:full":"23842 el Toro Rd Lake Forest CA 92630",
    "addr:housenumber":"23842",
    "addr:postcode":"92630",
    "addr:street":"El Toro Rd",
    "iso:country":"US",
    "sg:address":"23842 el Toro Rd",
    "sg:city":"Lake Forest",
    "sg:classifiers":[
        {
            "category":"Wholesale",
            "subcategory":"Groceries",
            "type":"Manufacturing & Wholesale Goods"
        }
    ],
    "sg:phone":"+1 949 462 0690",
    "sg:postcode":"92630",
    "sg:province":"CA",
    "sg:tags":[
        "food",
        "product"
    ],
    "wof:name":"Kill Devils",
    "wof:placetype":"venue"
},
  "geometry": {"coordinates":[-117.705338,33.616569],"type":"Point"}
}