{
  "type": "Feature",
  "properties": {
    "iso:country":"US",
    "sg:address":"4000 Alhambra Ave",
    "sg:city":"Martinez",
    "sg:classifiers":[
        {
            "category":"Retail",
            "subcategory":"Funeral Services",
            "type":"Services"
        }
    ],
    "sg:phone":"+1 925 228 4700",
    "sg:postcode":"94553",
    "sg:province":"CA",
    "sg:tags":[
        "director"
    ],
    "wof:name":"Connolly & Taylor Chapel",
    "wof:placetype":"venue"
},
  "geometry": {"coordinates":[-122.132067,37.995098],"type":"Point"}
}