{
  "type": "Feature",
  "properties": {
    "addr:full":"72 Yolanda Dr San Anselmo CA 94960",
    "addr:housenumber":"72",
    "addr:postcode":"94960",
    "addr:street":"Yolanda Dr",
    "iso:country":"US",
    "sg:address":"72 Yolanda Dr",
    "sg:city":"San Anselmo",
    "sg:classifiers":[
        {
            "category":"Professional",
            "subcategory":"Management & Consulting",
            "type":"Services"
        }
    ],
    "sg:phone":"+1 415 453 6029",
    "sg:postcode":"94960",
    "sg:province":"CA",
    "sg:tags":[
        "consultant",
        "hospital"
    ],
    "wof:name":"SNAP Inc",
    "wof:placetype":"venue"
},
  "geometry": {"coordinates":[-122.572908,37.980593],"type":"Point"}
}