{
  "type": "Feature",
  "properties": {
    "addr:full":"615 Alhambra Ave Martinez CA 94553",
    "addr:housenumber":"615",
    "addr:postcode":"94553",
    "addr:street":"Alhambra Ave",
    "iso:country":"US",
    "sg:address":"615 Alhambra Ave",
    "sg:city":"Martinez",
    "sg:classifiers":[
        {
            "category":"Retail",
            "subcategory":"Auto Repair",
            "type":"Services"
        }
    ],
    "sg:phone":"+1 925 228 3689",
    "sg:postcode":"94553",
    "sg:province":"CA",
    "sg:tags":[
        "body",
        "automobile",
        "painting"
    ],
    "wof:name":"Martinez Auto Body Shop",
    "wof:placetype":"venue"
},
  "geometry": {"coordinates":[-122.138155,38.016517],"type":"Point"}
}