{
  "type": "Feature",
  "properties": {
    "addr:full":"4144 Glencoe Ave Marina Del Rey CA 90292",
    "addr:housenumber":"4144",
    "addr:postcode":"90292",
    "addr:street":"Glencoe Ave",
    "iso:country":"US",
    "sg:address":"4144 Glencoe Ave",
    "sg:city":"Marina Del Rey",
    "sg:classifiers":[
        {
            "category":"Health Services",
            "subcategory":"Chiropractor",
            "type":"Services"
        }
    ],
    "sg:phone":"+1 310 301 4045",
    "sg:postcode":"90292",
    "sg:province":"CA",
    "wof:name":"Hearn Eileen DC",
    "wof:placetype":"venue"
},
  "geometry": {"coordinates":[-118.44237200000001,33.98969],"type":"Point"}
}