{
  "type": "Feature",
  "properties": {
    "iso:country":"US",
    "sg:address":"1113 N Shaw Rd",
    "sg:city":"Stockton",
    "sg:classifiers":[
        {
            "category":"Utilities",
            "type":"Services"
        }
    ],
    "sg:phone":"+1 209 931 7848",
    "sg:postcode":"95215",
    "sg:province":"CA",
    "sg:tags":[
        "sweeper"
    ],
    "wof:name":"Contract Sweeping Svc",
    "wof:placetype":"venue"
},
  "geometry": {"coordinates":[-121.24547,37.972798],"type":"Point"}
}