{
  "type": "Feature",
  "properties": {
    "iso:country":"US",
    "sg:address":"3465 Victor St",
    "sg:city":"Santa Clara",
    "sg:classifiers":[
        {
            "category":"Manufacturing",
            "subcategory":"Metals",
            "type":"Manufacturing & Wholesale Goods"
        },
        {
            "category":"Building & Trades",
            "subcategory":"Plumbing",
            "type":"Services"
        }
    ],
    "sg:phone":"+1 408 988 8877",
    "sg:postcode":"95054",
    "sg:province":"CA",
    "sg:tags":[
        "fabricator",
        "work",
        "sheet",
        "contractor"
    ],
    "wof:name":"Dallas Sheet Metal Mfg Inc",
    "wof:placetype":"venue"
},
  "geometry": {"coordinates":[-121.94266,37.38774],"type":"Point"}
}