{
  "type": "Feature",
  "properties": {
    "iso:country":"US",
    "sg:address":"278 Santa Monica Blvd",
    "sg:city":"Santa Monica",
    "sg:classifiers":[
        {
            "category":"Shopping",
            "subcategory":"Clothing, Apparel, & Fashions",
            "type":"Retail Goods"
        }
    ],
    "sg:phone":"+1 310 458 2884",
    "sg:postcode":"90401",
    "sg:province":"CA",
    "sg:tags":[
        "leather"
    ],
    "wof:name":"Leather Expo",
    "wof:placetype":"venue"
},
  "geometry": {"coordinates":[-118.496765,34.015006],"type":"Point"}
}