{
  "type": "Feature",
  "properties": {
    "addr:full":"3784 Mission Ave Oceanside CA 92054",
    "addr:housenumber":"3784",
    "addr:postcode":"92054",
    "addr:street":"Mission Ave",
    "iso:country":"US",
    "sg:address":"3784 Mission Ave",
    "sg:city":"Oceanside",
    "sg:classifiers":[
        {
            "category":"Building & Trades",
            "subcategory":"Construction",
            "type":"Services"
        }
    ],
    "sg:phone":"+1 760 458 7838",
    "sg:postcode":"92054",
    "sg:province":"CA",
    "sg:tags":[
        "memorial",
        "restoration",
        "preservation"
    ],
    "wof:name":"Cornerstone Stone & Tile Care",
    "wof:placetype":"venue"
},
  "geometry": {"coordinates":[-117.331209,33.225787],"type":"Point"}
}