{
  "type": "Feature",
  "properties": {
    "iso:country":"US",
    "sg:address":"4905 9th St",
    "sg:city":"Carpinteria",
    "sg:classifiers":[
        {
            "category":"Organizations",
            "subcategory":"Religious Organization",
            "type":"Services"
        }
    ],
    "sg:phone":"+1 805 684 8018",
    "sg:postcode":"93013",
    "sg:province":"CA",
    "sg:tags":[
        "church"
    ],
    "wof:name":"Church Of Christ",
    "wof:placetype":"venue"
},
  "geometry": {"coordinates":[-119.519667,34.398588],"type":"Point"}
}