{
  "type": "Feature",
  "properties": {
    "addr:full":"3072 Oldwood Ct San Jose CA 95148",
    "addr:housenumber":"3072",
    "addr:postcode":"95148",
    "addr:street":"Oldwood Ct",
    "iso:country":"US",
    "sg:address":"3072 Oldwood Ct",
    "sg:city":"San Jose",
    "sg:classifiers":[
        {
            "category":"Professional",
            "type":"Services"
        }
    ],
    "sg:phone":"+1 408 238 5529",
    "sg:postcode":"95148",
    "sg:province":"CA",
    "wof:name":"Jj Mountain Inc",
    "wof:placetype":"venue"
},
  "geometry": {"coordinates":[-121.783862,37.326116],"type":"Point"}
}