{
  "type": "Feature",
  "properties": {
    "addr:full":"1863 Lillian Ave Paradise CA 95969",
    "addr:housenumber":"1863",
    "addr:postcode":"95969",
    "addr:street":"Lillian Ave",
    "iso:country":"US",
    "sg:address":"1863 Lillian Ave",
    "sg:city":"Paradise",
    "sg:classifiers":[
        {
            "category":"Shopping",
            "subcategory":"Crafts & Fabrics",
            "type":"Retail Goods"
        }
    ],
    "sg:phone":"+1 530 872 3357",
    "sg:postcode":"95969",
    "sg:province":"CA",
    "sg:tags":[
        "material",
        "needlework",
        "sewing"
    ],
    "wof:name":"Zel's Stitchery",
    "wof:placetype":"venue"
},
  "geometry": {"coordinates":[-121.573049,39.745335],"type":"Point"}
}