{
  "type": "Feature",
  "properties": {
    "addr:full":"2239 Michael Dr Newbury Park CA 91320",
    "addr:housenumber":"2239",
    "addr:postcode":"91320",
    "addr:street":"Michael Dr",
    "iso:country":"US",
    "sg:address":"2239 Michael Dr",
    "sg:city":"Newbury Park",
    "sg:classifiers":[
        {
            "category":"Health Services",
            "subcategory":"Optometrist",
            "type":"Services"
        }
    ],
    "sg:phone":"+1 805 499 2676",
    "sg:postcode":"91320",
    "sg:province":"CA",
    "sg:tags":[
        "optical",
        "good"
    ],
    "wof:name":"Newbury Park Optometric Ctr",
    "wof:placetype":"venue"
},
  "geometry": {"coordinates":[-118.927026,34.181744],"type":"Point"}
}