{
  "type": "Feature",
  "properties": {
    "addr:full":"24th St and Mission St San Francisco CA 94110",
    "addr:postcode":"94110",
    "addr:street":"24Th St;St",
    "iso:country":"US",
    "sg:address":"24th St and Mission St",
    "sg:city":"San Francisco",
    "sg:classifiers":[
        {
            "category":"Government",
            "subcategory":"City Hall",
            "type":"Public Place"
        }
    ],
    "sg:postcode":"94110",
    "sg:province":"CA",
    "sg:website":"www.bart.gov",
    "wof:name":"24th St BART Station",
    "wof:placetype":"venue"
},
  "geometry": {"coordinates":[-122.418482,37.752228],"type":"Point"}
}