{
  "type": "Feature",
  "properties": {
    "addr:full":"11450 South St Cerritos CA 90703",
    "addr:housenumber":"11450",
    "addr:postcode":"ca 90703",
    "addr:street":"South St",
    "iso:country":"US",
    "sg:address":"11450 South St",
    "sg:city":"Cerritos",
    "sg:classifiers":[
        {
            "category":"Retail",
            "subcategory":"Laundry & Dry Cleaning",
            "type":"Services"
        }
    ],
    "sg:phone":"+1 562 860 6465",
    "sg:postcode":"90703",
    "sg:province":"CA",
    "wof:name":"Continental Cleaners",
    "wof:placetype":"venue"
},
  "geometry": {"coordinates":[-118.09200300000001,33.8582],"type":"Point"}
}