{
  "type": "Feature",
  "properties": {
    "iso:country":"US",
    "sg:address":"26900 Newport Rd",
    "sg:city":"Menifee",
    "sg:classifiers":[
        {
            "category":"Shopping",
            "subcategory":"Bicycles & Sporting Goods",
            "type":"Retail Goods"
        }
    ],
    "sg:phone":"+1 951 679 7377",
    "sg:postcode":"92584",
    "sg:province":"CA",
    "sg:tags":[
        "equipment",
        "skateboard",
        "skateboarding"
    ],
    "wof:name":"Newport Ride Shop",
    "wof:placetype":"venue"
},
  "geometry": {"coordinates":[-117.18895000000001,33.685111],"type":"Point"}
}