{
  "type": "Feature",
  "properties": {
    "addr:full":"722 S Main St Santa Ana CA 92701",
    "addr:housenumber":"722",
    "addr:postcode":"92701",
    "addr:street":"S Main St",
    "iso:country":"US",
    "sg:address":"722 S Main St",
    "sg:city":"Santa Ana",
    "sg:classifiers":[
        {
            "category":"Shopping",
            "subcategory":"Gifts & Souvenirs",
            "type":"Retail Goods"
        }
    ],
    "sg:phone":"+1 714 835 0051",
    "sg:postcode":"92701",
    "sg:province":"CA",
    "sg:tags":[
        "party",
        "supply"
    ],
    "wof:name":"LA Chona Party Supply",
    "wof:placetype":"venue"
},
  "geometry": {"coordinates":[-117.867785,33.7386],"type":"Point"}
}