{
  "type": "Feature",
  "properties": {
    "iso:country":"US",
    "sg:address":"351 Atwater Blvd",
    "sg:city":"Atwater",
    "sg:classifiers":[
        {
            "category":"Restaurant",
            "type":"Food & Drink"
        }
    ],
    "sg:phone":"+1 209 358 4103",
    "sg:postcode":"95301",
    "sg:province":"CA",
    "wof:name":"Tary Boscolo's Pizzeria",
    "wof:placetype":"venue"
},
  "geometry": {"coordinates":[-120.596889,37.341352],"type":"Point"}
}