{
  "type": "Feature",
  "properties": {
    "iso:country":"US",
    "sg:address":"800 W el Camino Real",
    "sg:city":"Mountain View",
    "sg:classifiers":[
        {
            "category":"Professional",
            "subcategory":"Computer Services",
            "type":"Services"
        }
    ],
    "sg:phone":"+1 650 237 4400",
    "sg:postcode":"94040",
    "sg:province":"CA",
    "sg:tags":[
        "hardware",
        "provider",
        "internet",
        "software"
    ],
    "sg:website":"www.mobilearia.com",
    "wof:name":"Mobilearia",
    "wof:placetype":"venue"
},
  "geometry": {"coordinates":[-122.082551,37.385036],"type":"Point"}
}