{
  "type": "Feature",
  "properties": {
    "addr:full":"11260 Overland Ave Culver City CA 90230",
    "addr:housenumber":"11260",
    "addr:postcode":"90230",
    "addr:street":"Overland Ave",
    "iso:country":"US",
    "sg:address":"11260 Overland Ave",
    "sg:city":"Culver City",
    "sg:classifiers":[
        {
            "category":"Professional",
            "subcategory":"Business Services",
            "type":"Services"
        }
    ],
    "sg:phone":"+1 310 815 8755",
    "sg:postcode":"90230",
    "sg:province":"CA",
    "wof:name":"Electra Color",
    "wof:placetype":"venue"
},
  "geometry": {"coordinates":[-118.390331,33.993489],"type":"Point"}
}