{
  "type": "Feature",
  "properties": {
    "addr:full":"638 Mount Olivet Ct Clayton CA 94517",
    "addr:housenumber":"638",
    "addr:postcode":"94517",
    "addr:street":"Mount Olivet Ct",
    "iso:country":"US",
    "sg:address":"638 Mount Olivet Ct",
    "sg:city":"Clayton",
    "sg:classifiers":[
        {
            "category":"Shopping",
            "subcategory":"Used Merchandise",
            "type":"Retail Goods"
        }
    ],
    "sg:phone":"+1 925 673 7123",
    "sg:postcode":"94517",
    "sg:province":"CA",
    "wof:name":"Consignment Treasures",
    "wof:placetype":"venue"
},
  "geometry": {"coordinates":[-121.931707,37.92633],"type":"Point"}
}