{
  "type": "Feature",
  "properties": {
    "addr:full":"340 Crest Lake Dr Palm Desert CA 92211",
    "addr:housenumber":"340",
    "addr:postcode":"ca 92211",
    "addr:street":"Crest Lake Dr",
    "iso:country":"US",
    "sg:address":"340 Crest Lake Dr",
    "sg:city":"Palm Desert",
    "sg:classifiers":[
        {
            "category":"Wholesale",
            "subcategory":"Metals & Minerals",
            "type":"Manufacturing & Wholesale Goods"
        }
    ],
    "sg:phone":"+1 760 674 0955",
    "sg:postcode":"92211",
    "sg:province":"CA",
    "sg:tags":[
        "aluminum"
    ],
    "wof:name":"Desert Metals",
    "wof:placetype":"venue"
},
  "geometry": {"coordinates":[-116.353735,33.764234],"type":"Point"}
}