{
  "type": "Feature",
  "properties": {
    "iso:country":"US",
    "sg:address":"1100 Lucretia Avenue",
    "sg:city":"San Jose",
    "sg:classifiers":[
        {
            "category":"Autos & Motor Vehicles",
            "subcategory":"Fuel & Gas Station",
            "type":"Retail Goods"
        }
    ],
    "sg:phone":"+1 408 279 3277",
    "sg:postcode":"95122",
    "sg:province":"CA",
    "sg:website":"www.quikstop.com",
    "wof:name":"Quik Stop #86",
    "wof:placetype":"venue"
},
  "geometry": {"coordinates":[-121.856916,37.330025],"type":"Point"}
}