{
  "type": "Feature",
  "properties": {
    "iso:country":"US",
    "sg:address":"26520 Cactus Ave",
    "sg:city":"Moreno Valley",
    "sg:classifiers":[
        {
            "category":"Wholesale",
            "subcategory":"Groceries",
            "type":"Manufacturing & Wholesale Goods"
        }
    ],
    "sg:phone":"+1 951 486 4338",
    "sg:postcode":"92555",
    "sg:province":"CA",
    "sg:tags":[
        "tea",
        "coffee"
    ],
    "wof:name":"Peabodys Coffee Inc",
    "wof:placetype":"venue"
},
  "geometry": {"coordinates":[-117.196882,33.910194],"type":"Point"}
}