{
  "type": "Feature",
  "properties": {
    "addr:full":"4121 MacDonald Ave Richmond CA 94805",
    "addr:housenumber":"4121",
    "addr:postcode":"94805",
    "addr:street":"Macdonald Ave",
    "iso:country":"US",
    "sg:address":"4121 MacDonald Ave",
    "sg:city":"Richmond",
    "sg:classifiers":[
        {
            "category":"Health Services",
            "subcategory":"Chiropractor",
            "type":"Services"
        }
    ],
    "sg:phone":"+1 510 232 0877",
    "sg:postcode":"94805",
    "sg:province":"CA",
    "wof:name":"Thongvichit Chiropractic Center",
    "wof:placetype":"venue"
},
  "geometry": {"coordinates":[-122.331001,37.933399],"type":"Point"}
}