{
  "type": "Feature",
  "properties": {
    "iso:country":"US",
    "sg:address":"3823 Williams Rd",
    "sg:city":"San Jose",
    "sg:classifiers":[
        {
            "category":"Wholesale",
            "subcategory":"Non-durable Goods",
            "type":"Manufacturing & Wholesale Goods"
        }
    ],
    "sg:phone":"+1 408 243 5761",
    "sg:postcode":"95117",
    "sg:province":"CA",
    "wof:name":"Comcent Trading & Contrac",
    "wof:placetype":"venue"
},
  "geometry": {"coordinates":[-121.968575,37.308409],"type":"Point"}
}