{
  "type": "Feature",
  "properties": {
    "addr:full":"1312 Barham Dr San Marcos CA 92078",
    "addr:housenumber":"1312",
    "addr:postcode":"92078",
    "addr:street":"Barham Dr",
    "iso:country":"US",
    "sg:address":"1312 Barham Dr",
    "sg:city":"San Marcos",
    "sg:classifiers":[
        {
            "category":"Wholesale",
            "subcategory":"Machinery & Supplies",
            "type":"Manufacturing & Wholesale Goods"
        }
    ],
    "sg:phone":"+1 760 735 9793",
    "sg:postcode":"92078",
    "sg:province":"CA",
    "sg:tags":[
        "equipment",
        "industrial",
        "hydraulic"
    ],
    "wof:name":"Mobile Hydraulic Eguipment Inc",
    "wof:placetype":"venue"
},
  "geometry": {"coordinates":[-117.133025,33.134904],"type":"Point"}
}