{
  "type": "Feature",
  "properties": {
    "addr:full":"585 Juana Ave San Leandro CA 94577",
    "addr:housenumber":"585",
    "addr:postcode":"94577",
    "addr:street":"Juana Ave",
    "iso:country":"US",
    "sg:address":"585 Juana Ave",
    "sg:city":"San Leandro",
    "sg:classifiers":[
        {
            "category":"Building & Trades",
            "subcategory":"Construction",
            "type":"Services"
        }
    ],
    "sg:phone":"+1 510 708 7307",
    "sg:postcode":"94577",
    "sg:province":"CA",
    "sg:tags":[
        "general",
        "contractor"
    ],
    "wof:name":"Metrobuilt",
    "wof:placetype":"venue"
},
  "geometry": {"coordinates":[-122.148905,37.724823],"type":"Point"}
}