{
  "type": "Feature",
  "properties": {
    "addr:full":"112 N Avenue 58 Los Angeles CA 90042",
    "addr:housenumber":"112;58",
    "addr:postcode":"90042",
    "addr:street":"N Avenue",
    "iso:country":"US",
    "sg:address":"112 N Avenue 58",
    "sg:city":"Los Angeles",
    "sg:classifiers":[
        {
            "category":"Food & Beverages",
            "subcategory":"Specialty",
            "type":"Retail Goods"
        }
    ],
    "sg:phone":"+1 323 349 0563",
    "sg:postcode":"90042",
    "sg:province":"CA",
    "wof:name":"Botanica Nueva Era",
    "wof:placetype":"venue"
},
  "geometry": {"coordinates":[-118.192033,34.110554],"type":"Point"}
}