{
  "type": "Feature",
  "properties": {
    "addr:full":"43 Grassy Knoll Rancho Santa Margarita CA 92688",
    "addr:housenumber":"43",
    "addr:postcode":"92688",
    "addr:street":"Grassy Knoll",
    "iso:country":"US",
    "sg:address":"43 Grassy Knoll",
    "sg:city":"Rancho Santa Margarita",
    "sg:classifiers":[
        {
            "category":"Building & Trades",
            "subcategory":"Plumbing",
            "type":"Services"
        }
    ],
    "sg:phone":"+1 949 379 9834",
    "sg:postcode":"92688",
    "sg:province":"CA",
    "wof:name":"Ironwood Plumbing",
    "wof:placetype":"venue"
},
  "geometry": {"coordinates":[-117.626554,33.58614],"type":"Point"}
}