{
  "type": "Feature",
  "properties": {
    "iso:country":"US",
    "sg:address":"2650 Zoe Ave Fl 3",
    "sg:city":"Huntington Park",
    "sg:classifiers":[
        {
            "category":"Education",
            "subcategory":"Preschool",
            "type":"Public Place"
        },
        {
            "category":"Education",
            "subcategory":"School",
            "type":"Public Place"
        }
    ],
    "sg:phone":"+1 323 588 7320",
    "sg:postcode":"90255",
    "sg:province":"CA",
    "sg:tags":[
        "elementary"
    ],
    "wof:name":"Mexican American Opportunity Foundation-Head Start",
    "wof:placetype":"venue"
},
  "geometry": {"coordinates":[-118.223999,33.979301],"type":"Point"}
}