{
  "type": "Feature",
  "properties": {
    "iso:country":"US",
    "sg:address":"26880 Cherry Hills Blvd",
    "sg:city":"Sun City",
    "sg:classifiers":[
        {
            "category":"Real Estate",
            "subcategory":"Real Estate Services",
            "type":"Services"
        }
    ],
    "sg:phone":"+1 951 679 5858",
    "sg:postcode":"92586",
    "sg:province":"CA",
    "sg:website":"www.c21caloaks.com/",
    "wof:name":"C21 Cal Oaks",
    "wof:placetype":"venue"
},
  "geometry": {"coordinates":[-117.19049699999999,33.710704],"type":"Point"}
}