{
  "type": "Feature",
  "properties": {
    "addr:full":"285 Hamilton Ave Palo Alto CA 94301",
    "addr:housenumber":"285",
    "addr:postcode":"94301",
    "addr:street":"Hamilton Ave",
    "iso:country":"US",
    "sg:address":"285 Hamilton Ave",
    "sg:city":"Palo Alto",
    "sg:classifiers":[
        {
            "category":"Professional",
            "subcategory":"Management & Consulting",
            "type":"Services"
        }
    ],
    "sg:phone":"+1 650 847 2200",
    "sg:postcode":"94301",
    "sg:province":"CA",
    "sg:tags":[
        "consultant",
        "business"
    ],
    "wof:name":"Charles River Assoc",
    "wof:placetype":"venue"
},
  "geometry": {"coordinates":[-122.160735,37.444701],"type":"Point"}
}