{
  "type": "Feature",
  "properties": {
    "addr:full":"27127 Cll Arroyo San Juan Capistrano CA 92675",
    "addr:postcode":"27127;92675",
    "addr:street":"Cll Arroyo",
    "iso:country":"US",
    "sg:address":"27127 Cll Arroyo",
    "sg:city":"San Juan Capistrano",
    "sg:classifiers":[
        {
            "category":"Professional",
            "subcategory":"Business Services",
            "type":"Services"
        }
    ],
    "sg:phone":"+1 949 661 6695",
    "sg:postcode":"92675",
    "sg:province":"CA",
    "wof:name":"Charles Hartman & Assoc",
    "wof:placetype":"venue"
},
  "geometry": {"coordinates":[-117.65659599999999,33.49912],"type":"Point"}
}