{
  "type": "Feature",
  "properties": {
    "addr:full":"2005 W Bullard Ave Fresno CA 93711",
    "addr:housenumber":"2005",
    "addr:postcode":"93711",
    "addr:street":"W Bullard Ave",
    "iso:country":"US",
    "sg:address":"2005 W Bullard Ave",
    "sg:city":"Fresno",
    "sg:classifiers":[
        {
            "category":"Retail",
            "subcategory":"Laundry & Dry Cleaning",
            "type":"Services"
        }
    ],
    "sg:phone":"+1 559 439 0779",
    "sg:postcode":"93711",
    "sg:province":"CA",
    "sg:tags":[
        "cleaners"
    ],
    "wof:name":"Comet Cleaners",
    "wof:placetype":"venue"
},
  "geometry": {"coordinates":[-119.83073400000001,36.822662],"type":"Point"}
}