{
  "type": "Feature",
  "properties": {
    "iso:country":"US",
    "sg:address":"19722 Center St",
    "sg:city":"Castro Valley",
    "sg:classifiers":[
        {
            "category":"Social Services",
            "subcategory":"Child Care",
            "type":"Services"
        }
    ],
    "sg:phone":"+1 510 583 6383",
    "sg:postcode":"94546",
    "sg:province":"CA",
    "sg:tags":[
        "day"
    ],
    "sg:website":"www.ymca.net",
    "wof:name":"YMCA",
    "wof:placetype":"venue"
},
  "geometry": {"coordinates":[-122.11265899999999,37.699915],"type":"Point"}
}