{
  "type": "Feature",
  "properties": {
    "addr:full":"810 Brown St Napa CA 94559",
    "addr:housenumber":"810",
    "addr:postcode":"94559",
    "addr:street":"Brown St",
    "iso:country":"US",
    "sg:address":"810 Brown St",
    "sg:city":"Napa",
    "sg:classifiers":[
        {
            "category":"Insurance",
            "subcategory":"Hazard Insurance",
            "type":"Services"
        }
    ],
    "sg:phone":"+1 707 255 7820",
    "sg:postcode":"94559",
    "sg:province":"CA",
    "sg:tags":[
        "bond"
    ],
    "wof:name":"Joanne's Bail Bonds",
    "wof:placetype":"venue"
},
  "geometry": {"coordinates":[-122.285281,38.298198],"type":"Point"}
}