{
  "type": "Feature",
  "properties": {
    "iso:country":"US",
    "sg:address":"4250 Avalon Blvd",
    "sg:city":"Los Angeles",
    "sg:classifiers":[
        {
            "category":"Autos & Motor Vehicles",
            "subcategory":"Auto Supplies",
            "type":"Retail Goods"
        }
    ],
    "sg:phone":"+1 323 231 2218",
    "sg:postcode":"90011",
    "sg:province":"CA",
    "sg:tags":[
        "alternator",
        "generator"
    ],
    "wof:name":"Main Alternators",
    "wof:placetype":"venue"
},
  "geometry": {"coordinates":[-118.265236,34.005697],"type":"Point"}
}