{
  "type": "Feature",
  "properties": {
    "addr:full":"76220 Commercial St Covelo CA 95428",
    "addr:housenumber":"76220",
    "addr:postcode":"95428",
    "addr:street":"Commercial St",
    "iso:country":"US",
    "sg:address":"76220 Commercial St",
    "sg:city":"Covelo",
    "sg:classifiers":[
        {
            "category":"Wholesale",
            "subcategory":"Petroleum",
            "type":"Manufacturing & Wholesale Goods"
        }
    ],
    "sg:phone":"+1 707 983 6444",
    "sg:postcode":"95428",
    "sg:province":"CA",
    "sg:tags":[
        "bulk",
        "oil",
        "gasoline"
    ],
    "wof:name":"Redwood Oil Co Inc",
    "wof:placetype":"venue"
},
  "geometry": {"coordinates":[-123.248203,39.787986],"type":"Point"}
}