{
  "type": "Feature",
  "properties": {
    "iso:country":"US",
    "sg:address":"3585 Sunset Dr",
    "sg:city":"Redding",
    "sg:classifiers":[
        {
            "category":"Professional",
            "subcategory":"Accounting & Tax Preparation",
            "type":"Services"
        }
    ],
    "sg:phone":"+1 530 246 2220",
    "sg:postcode":"96001",
    "sg:province":"CA",
    "sg:tags":[
        "accountant"
    ],
    "wof:name":"Bruce W Hirst CPA",
    "wof:placetype":"venue"
},
  "geometry": {"coordinates":[-122.423796,40.585708],"type":"Point"}
}