{
  "type": "Feature",
  "properties": {
    "addr:full":"2040 Brown St Napa CA 94559",
    "addr:housenumber":"2040",
    "addr:postcode":"94559",
    "addr:street":"Brown St",
    "iso:country":"US",
    "sg:address":"2040 Brown St",
    "sg:city":"Napa",
    "sg:classifiers":[
        {
            "category":"Farming",
            "subcategory":"Vineyard",
            "type":"Manufacturing & Wholesale Goods"
        }
    ],
    "sg:phone":"+1 707 257 7555",
    "sg:postcode":"94559",
    "sg:province":"CA",
    "sg:tags":[
        "grape"
    ],
    "wof:name":"Robert Biale Vineyards",
    "wof:placetype":"venue"
},
  "geometry": {"coordinates":[-122.293329,38.307344],"type":"Point"}
}