{
  "type": "Feature",
  "properties": {
    "iso:country":"US",
    "sg:address":"1100 Fulton Ave",
    "sg:city":"San Leandro",
    "sg:classifiers":[
        {
            "category":"Education",
            "subcategory":"School",
            "type":"Public Place"
        }
    ],
    "sg:phone":"+1 510 357 8772",
    "sg:postcode":"94577",
    "sg:province":"CA",
    "sg:tags":[
        "high",
        "middle",
        "elementary"
    ],
    "wof:name":"Assumption School of San Leandro the",
    "wof:placetype":"venue"
},
  "geometry": {"coordinates":[-122.137001,37.721001],"type":"Point"}
}