{
  "type": "Feature",
  "properties": {
    "iso:country":"US",
    "sg:address":"1036 2nd St",
    "sg:city":"Encinitas",
    "sg:classifiers":[
        {
            "category":"Insurance",
            "subcategory":"Hazard Insurance",
            "type":"Services"
        }
    ],
    "sg:phone":"+1 760 436 5015",
    "sg:postcode":"92024",
    "sg:province":"CA",
    "sg:website":"www.schulteinsurance.com",
    "wof:name":"Schulte Insurance Agency",
    "wof:placetype":"venue"
},
  "geometry": {"coordinates":[-117.293999,33.0383],"type":"Point"}
}