{
  "type": "Feature",
  "properties": {
    "addr:full":"9749 Independence Ave Chatsworth CA 91311",
    "addr:housenumber":"9749",
    "addr:postcode":"91311",
    "addr:street":"Independence Ave",
    "iso:country":"US",
    "sg:address":"9749 Independence Ave",
    "sg:city":"Chatsworth",
    "sg:classifiers":[
        {
            "category":"Shopping",
            "subcategory":"Stationery & Office Supplies",
            "type":"Retail Goods"
        }
    ],
    "sg:phone":"+1 818 709 9550",
    "sg:postcode":"91311",
    "sg:province":"CA",
    "sg:tags":[
        "stationer"
    ],
    "sg:website":"www.stationers.com",
    "wof:name":"Catalogue Stationers",
    "wof:placetype":"venue"
},
  "geometry": {"coordinates":[-118.590813,34.249099],"type":"Point"}
}