{
  "type": "Feature",
  "properties": {
    "addr:full":"1220 H St Modesto CA 95354",
    "addr:housenumber":"1220",
    "addr:postcode":"ca 95354",
    "addr:street":"H St",
    "iso:country":"US",
    "sg:address":"1220 H St",
    "sg:city":"Modesto",
    "sg:classifiers":[
        {
            "category":"Restaurant",
            "type":"Food & Drink"
        }
    ],
    "sg:phone":"+1 209 544 6433",
    "sg:postcode":"95354",
    "sg:province":"CA",
    "wof:name":"Mediterranean Market & Grill",
    "wof:placetype":"venue"
},
  "geometry": {"coordinates":[-120.995003,37.640301],"type":"Point"}
}