{
  "type": "Feature",
  "properties": {
    "iso:country":"US",
    "sg:address":"430 Peninsula Ave",
    "sg:city":"San Mateo",
    "sg:classifiers":[
        {
            "category":"Real Estate",
            "subcategory":"Real Estate Agent",
            "type":"Services"
        }
    ],
    "sg:phone":"+1 650 343 4550",
    "sg:postcode":"94401",
    "sg:province":"CA",
    "sg:tags":[
        "appraiser"
    ],
    "wof:name":"Bruin Realty",
    "wof:placetype":"venue"
},
  "geometry": {"coordinates":[-122.333803,37.580918],"type":"Point"}
}