{
  "type": "Feature",
  "properties": {
    "iso:country":"US",
    "sg:address":"12100 Wilshire Blvd",
    "sg:city":"Los Angeles",
    "sg:classifiers":[
        {
            "category":"Professional",
            "subcategory":"Lawyer & Legal Services",
            "type":"Services"
        }
    ],
    "sg:phone":"+1 310 826 2848",
    "sg:postcode":"90025",
    "sg:province":"CA",
    "sg:tags":[
        "attorney"
    ],
    "wof:name":"Sheldon M Jaffe",
    "wof:placetype":"venue"
},
  "geometry": {"coordinates":[-118.46831,34.043422],"type":"Point"}
}