{
  "type": "Feature",
  "properties": {
    "addr:full":"11334 Moorpark St Studio City CA 91602",
    "addr:housenumber":"11334",
    "addr:postcode":"91602",
    "addr:street":"Moorpark St",
    "iso:country":"US",
    "sg:address":"11334 Moorpark St",
    "sg:city":"Studio City",
    "sg:classifiers":[
        {
            "category":"Bars & Pubs",
            "type":"Food & Drink"
        },
        {
            "category":"Restaurant",
            "type":"Food & Drink"
        }
    ],
    "sg:phone":"+1 818 308 1100",
    "sg:postcode":"91602",
    "sg:province":"CA",
    "sg:tags":[
        "italian"
    ],
    "sg:website":"www.8andahalf.com",
    "wof:name":"8 1/2 Taverna",
    "wof:placetype":"venue"
},
  "geometry": {"coordinates":[-118.3781,34.150096],"type":"Point"}
}