{
  "type": "Feature",
  "properties": {
    "iso:country":"US",
    "sg:address":"463 Rincon Rd",
    "sg:city":"El Sobrante",
    "sg:classifiers":[
        {
            "category":"Building & Trades",
            "subcategory":"Construction",
            "type":"Services"
        }
    ],
    "sg:phone":"+1 510 223 5783",
    "sg:postcode":"94803",
    "sg:province":"CA",
    "sg:tags":[
        "roofing",
        "contractor"
    ],
    "wof:name":"K S Roofing",
    "wof:placetype":"venue"
},
  "geometry": {"coordinates":[-122.297528,37.978038],"type":"Point"}
}