{
  "type": "Feature",
  "properties": {
    "addr:full":"24000 Alicia Pkwy Mission Viejo CA 92691",
    "addr:housenumber":"24000",
    "addr:postcode":"92691",
    "addr:street":"Alicia Pkwy",
    "iso:country":"US",
    "sg:address":"24000 Alicia Pkwy",
    "sg:city":"Mission Viejo",
    "sg:classifiers":[
        {
            "category":"Personal",
            "subcategory":"Tanning Parlor",
            "type":"Services"
        }
    ],
    "sg:phone":"+1 949 458 8266",
    "sg:postcode":"92691",
    "sg:province":"CA",
    "wof:name":"Havana Tanning Company",
    "wof:placetype":"venue"
},
  "geometry": {"coordinates":[-117.689409,33.607709],"type":"Point"}
}