{
  "type": "Feature",
  "properties": {
    "iso:country":"US",
    "sg:address":"24610 2nd St",
    "sg:city":"Murrieta",
    "sg:classifiers":[
        {
            "category":"Retail",
            "subcategory":"Animal Services",
            "type":"Services"
        }
    ],
    "sg:phone":"+1 951 698 0600",
    "sg:postcode":"92562",
    "sg:province":"CA",
    "sg:tags":[
        "pet",
        "grooming",
        "washing"
    ],
    "wof:name":"Barkin' Barber",
    "wof:placetype":"venue"
},
  "geometry": {"coordinates":[-117.21877499999999,33.554914],"type":"Point"}
}