{
  "type": "Feature",
  "properties": {
    "iso:country":"US",
    "sg:address":"41 Throckmorton Ave",
    "sg:city":"Mill Valley",
    "sg:classifiers":[
        {
            "category":"Restaurant",
            "type":"Food & Drink"
        }
    ],
    "sg:menulink":"http://www.allmenus.com/ca/southeast-marin/48994-champagne/menu/",
    "sg:phone":"+1 415 380 0410",
    "sg:postcode":"94941",
    "sg:province":"CA",
    "sg:tags":[
        "french"
    ],
    "wof:name":"Champagne",
    "wof:placetype":"venue"
},
  "geometry": {"coordinates":[-122.547183,37.906617],"type":"Point"}
}