{
  "type": "Feature",
  "properties": {
    "iso:country":"US",
    "sg:address":"956 Huntington Dr",
    "sg:city":"San Marino",
    "sg:classifiers":[
        {
            "category":"Shopping",
            "subcategory":"Baby Store",
            "type":"Retail Goods"
        },
        {
            "category":"Shopping",
            "subcategory":"Clothing, Apparel, & Fashions",
            "type":"Retail Goods"
        }
    ],
    "sg:phone":"+1 626 588 2810",
    "sg:postcode":"91108",
    "sg:province":"CA",
    "sg:tags":[
        "children's",
        "clothing",
        "gear",
        "furniture"
    ],
    "sg:website":"www.mylittlebebe.com",
    "wof:name":"mylittlebebe",
    "wof:placetype":"venue"
},
  "geometry": {"coordinates":[-118.125694,34.112524],"type":"Point"}
}