{
  "type": "Feature",
  "properties": {
    "addr:full":"933 Treat Ave San Francisco CA 94110",
    "addr:housenumber":"933",
    "addr:postcode":"94110",
    "addr:street":"Treat Ave",
    "iso:country":"US",
    "sg:address":"933 Treat Ave",
    "sg:city":"San Francisco",
    "sg:classifiers":[
        {
            "category":"Wholesale",
            "subcategory":"Durable Goods & Equipment",
            "type":"Manufacturing & Wholesale Goods"
        }
    ],
    "sg:phone":"+1 415 647 7600",
    "sg:postcode":"94110",
    "sg:province":"CA",
    "sg:tags":[
        "professional"
    ],
    "wof:name":"Scotech",
    "wof:placetype":"venue"
},
  "geometry": {"coordinates":[-122.413106,37.754693],"type":"Point"}
}