{
  "type": "Feature",
  "properties": {
    "iso:country":"US",
    "sg:address":"870 Butler Ave",
    "sg:city":"Santa Rosa",
    "sg:classifiers":[
        {
            "category":"Farming",
            "subcategory":"Vineyard",
            "type":"Manufacturing & Wholesale Goods"
        }
    ],
    "sg:phone":"+1 707 573 9496",
    "sg:postcode":"95407",
    "sg:province":"CA",
    "sg:tags":[
        "grape"
    ],
    "wof:name":"Screaming Eagle Vineyards",
    "wof:placetype":"venue"
},
  "geometry": {"coordinates":[-122.741726,38.399155],"type":"Point"}
}