{
  "type": "Feature",
  "properties": {
    "iso:country":"US",
    "sg:address":"764 N Mount Vernon Ave",
    "sg:city":"San Bernardino",
    "sg:classifiers":[
        {
            "category":"Professional",
            "type":"Services"
        }
    ],
    "sg:phone":"+1 909 381 4272",
    "sg:postcode":"92411",
    "sg:province":"CA",
    "wof:name":"Revolution Racing",
    "wof:placetype":"venue"
},
  "geometry": {"coordinates":[-117.313928,34.113663],"type":"Point"}
}