{
  "type": "Feature",
  "properties": {
    "addr:full":"4000 Middlefield Rd Palo Alto CA 94303",
    "addr:housenumber":"4000",
    "addr:postcode":"94303",
    "addr:street":"Middlefield Rd",
    "iso:country":"US",
    "sg:address":"4000 Middlefield Rd",
    "sg:city":"Palo Alto",
    "sg:classifiers":[
        {
            "category":"Social Services",
            "subcategory":"Child Care",
            "type":"Services"
        }
    ],
    "sg:phone":"+1 650 493 2777",
    "sg:postcode":"94303",
    "sg:province":"CA",
    "wof:name":"Good Neighbor Montessori",
    "wof:placetype":"venue"
},
  "geometry": {"coordinates":[-122.106881,37.417917],"type":"Point"}
}