{
  "type": "Feature",
  "properties": {
    "addr:full":"2297 Arnold Industrial Way Concord CA 94520",
    "addr:housenumber":"2297",
    "addr:postcode":"94520",
    "addr:street":"Arnold Industrial Way",
    "iso:country":"US",
    "sg:address":"2297 Arnold Industrial Way",
    "sg:city":"Concord",
    "sg:classifiers":[
        {
            "category":"Autos & Motor Vehicles",
            "subcategory":"Automobile Sales",
            "type":"Retail Goods"
        },
        {
            "category":"Personal",
            "type":"Services"
        },
        {
            "category":"Wholesale",
            "subcategory":"Scrap",
            "type":"Manufacturing & Wholesale Goods"
        },
        {
            "category":"Retail",
            "subcategory":"Auto Repair",
            "type":"Services"
        }
    ],
    "sg:phone":"+1 925 676 1311",
    "sg:postcode":"94520",
    "sg:province":"CA",
    "sg:tags":[
        "truck",
        "towing",
        "wrecking",
        "salvage"
    ],
    "sg:website":"http://www.mchughautowrecking.com",
    "wof:name":"McHugh's Towing",
    "wof:placetype":"venue"
},
  "geometry": {"coordinates":[-122.033845,38.008266],"type":"Point"}
}