{
  "type": "Feature",
  "properties": {
    "addr:full":"18719 Deer Hill Rd Hidden Valley Lk CA 95467",
    "addr:housenumber":"18719",
    "addr:postcode":"95467",
    "addr:street":"Deer Hill Rd",
    "iso:country":"US",
    "sg:address":"18719 Deer Hill Rd",
    "sg:city":"Hidden Valley Lk",
    "sg:classifiers":[
        {
            "category":"Education",
            "subcategory":"Special Training",
            "type":"Public Place"
        }
    ],
    "sg:phone":"+1 707 987 4630",
    "sg:postcode":"95467",
    "sg:province":"CA",
    "sg:tags":[
        "instruction",
        "driving"
    ],
    "wof:name":"Auto Bee Driving School",
    "wof:placetype":"venue"
},
  "geometry": {"coordinates":[-122.561356,38.814571],"type":"Point"}
}