{
  "type": "Feature",
  "properties": {
    "iso:country":"US",
    "sg:address":"120 Howard St",
    "sg:city":"San Francisco",
    "sg:classifiers":[
        {
            "category":"Professional",
            "subcategory":"Printing & Photocopies",
            "type":"Services"
        }
    ],
    "sg:phone":"+1 415 957 1700",
    "sg:postcode":"94105",
    "sg:province":"CA",
    "wof:name":"Copymat",
    "wof:placetype":"venue"
},
  "geometry": {"coordinates":[-122.39310999999999,37.791352],"type":"Point"}
}