{
  "type": "Feature",
  "properties": {
    "addr:full":"5200 Whittier Boulevard Los Angeles CA 90022",
    "addr:housenumber":"5200",
    "addr:postcode":"90022",
    "addr:street":"Whittier Boulevard",
    "iso:country":"US",
    "sg:address":"5200 Whittier Boulevard",
    "sg:city":"Los Angeles",
    "sg:classifiers":[
        {
            "category":"Government",
            "subcategory":"Office",
            "type":"Public Place"
        }
    ],
    "sg:phone":"+1 323 265 4797",
    "sg:postcode":"90022",
    "sg:province":"CA",
    "sg:tags":[
        "smog",
        "check"
    ],
    "wof:name":"Smog Pros",
    "wof:placetype":"venue"
},
  "geometry": {"coordinates":[-118.15714199999999,34.020278],"type":"Point"}
}