{
  "type": "Feature",
  "properties": {
    "iso:country":"US",
    "sg:address":"1640 E Highland Ave",
    "sg:city":"San Bernardino",
    "sg:classifiers":[
        {
            "category":"Professional",
            "type":"Services"
        }
    ],
    "sg:phone":"+1 909 881 7777",
    "sg:postcode":"92404",
    "sg:province":"CA",
    "wof:name":"El Patito Nutritional Center",
    "wof:placetype":"venue"
},
  "geometry": {"coordinates":[-117.251625,34.135936],"type":"Point"}
}