{
  "type": "Feature",
  "properties": {
    "addr:full":"21192 Hesperian Blvd Hayward CA 94541",
    "addr:housenumber":"21192",
    "addr:postcode":"94541",
    "addr:street":"Hesperian Blvd",
    "iso:country":"US",
    "sg:address":"21192 Hesperian Blvd",
    "sg:city":"Hayward",
    "sg:classifiers":[
        {
            "category":"Shopping",
            "subcategory":"Jewelry",
            "type":"Retail Goods"
        }
    ],
    "sg:phone":"+1 510 732 6878",
    "sg:postcode":"94541",
    "sg:province":"CA",
    "wof:name":"Joyeria Jocelyn",
    "wof:placetype":"venue"
},
  "geometry": {"coordinates":[-122.116399,37.663344],"type":"Point"}
}