{
  "type": "Feature",
  "properties": {
    "acgov:api":"788.0",
    "acgov:type":"ES",
    "addr:full":"1700 28th Avenue Oakland CA",
    "wof:categories":[
        "education_and_religion:education=school"
    ],
    "wof:name":"Achieve Academy",
    "wof:placetype":"venue"
},
  "geometry": {"coordinates":[-122.22732211857898,37.782319625991],"type":"Point"}
}