{
  "type": "Feature",
  "properties": {
    "addr:full":"2931 S Alameda St Vernon CA 90058",
    "addr:housenumber":"2931",
    "addr:postcode":"90058",
    "addr:street":"S Alameda St",
    "iso:country":"US",
    "sg:address":"2931 S Alameda St",
    "sg:city":"Vernon",
    "sg:classifiers":[
        {
            "category":"Manufacturing",
            "subcategory":"Textiles",
            "type":"Manufacturing & Wholesale Goods"
        },
        {
            "category":"Shopping",
            "subcategory":"Crafts & Fabrics",
            "type":"Retail Goods"
        }
    ],
    "sg:phone":"+1 323 233 4500",
    "sg:postcode":"90058",
    "sg:province":"CA",
    "sg:tags":[
        "canvas",
        "cotton"
    ],
    "wof:name":"Hot Cotton Inc",
    "wof:placetype":"venue"
},
  "geometry": {"coordinates":[-118.239681,34.010728],"type":"Point"}
}