{
  "type": "Feature",
  "properties": {
    "addr:full":"1118 Hingham Ln Ventura CA 93001",
    "addr:housenumber":"1118",
    "addr:postcode":"93001",
    "addr:street":"Hingham Ln",
    "iso:country":"US",
    "sg:address":"1118 Hingham Ln",
    "sg:city":"Ventura",
    "sg:classifiers":[
        {
            "category":"Real Estate",
            "subcategory":"Real Estate Agent",
            "type":"Services"
        }
    ],
    "sg:phone":"+1 805 643 0100",
    "sg:postcode":"93001",
    "sg:province":"CA",
    "wof:name":"Walter Stein Property Man",
    "wof:placetype":"venue"
},
  "geometry": {"coordinates":[-119.27264099999999,34.263365],"type":"Point"}
}