{
  "type": "Feature",
  "properties": {
    "addr:full":"90 N Baldwin Ave Sierra Madre CA 91024",
    "addr:housenumber":"90",
    "addr:postcode":"91024",
    "addr:street":"N Baldwin Ave",
    "iso:country":"US",
    "sg:address":"90 N Baldwin Ave",
    "sg:city":"Sierra Madre",
    "sg:classifiers":[
        {
            "category":"Professional",
            "type":"Services"
        }
    ],
    "sg:phone":"+1 626 355 2100",
    "sg:postcode":"91024",
    "sg:province":"CA",
    "wof:name":"Sierra Cstm Ktchens Bath Dsign",
    "wof:placetype":"venue"
},
  "geometry": {"coordinates":[-118.052459,34.164298],"type":"Point"}
}