{
  "type": "Feature",
  "properties": {
    "iso:country":"US",
    "sg:address":"5554 Rayo del Sol",
    "sg:city":"Laguna Hills",
    "sg:classifiers":[
        {
            "category":"Insurance",
            "subcategory":"Insurance Agent",
            "type":"Services"
        }
    ],
    "sg:phone":"+1 949 699 3356",
    "sg:postcode":"92637",
    "sg:province":"CA",
    "wof:name":"William G Selwyn Insuranc",
    "wof:placetype":"venue"
},
  "geometry": {"coordinates":[-117.747551,33.602616],"type":"Point"}
}