{
  "type": "Feature",
  "properties": {
    "iso:country":"US",
    "sg:address":"2499 Martin Rd",
    "sg:city":"Fairfield",
    "sg:classifiers":[
        {
            "category":"Home & Garden",
            "subcategory":"Building Materials",
            "type":"Retail Goods"
        }
    ],
    "sg:phone":"+1 707 422 3626",
    "sg:postcode":"94534",
    "sg:province":"CA",
    "sg:tags":[
        "glass",
        "window",
        "plate"
    ],
    "wof:name":"Acme Glass & Tinting",
    "wof:placetype":"venue"
},
  "geometry": {"coordinates":[-122.049692,38.283673],"type":"Point"}
}