{
  "type": "Feature",
  "properties": {
    "addr:full":"814 S Bascom Ave San Jose CA 95128",
    "addr:housenumber":"814",
    "addr:postcode":"95128",
    "addr:street":"S Bascom Ave",
    "iso:country":"US",
    "sg:address":"814 S Bascom Ave",
    "sg:city":"San Jose",
    "sg:classifiers":[
        {
            "category":"Restaurant",
            "type":"Food & Drink"
        }
    ],
    "sg:phone":"+1 408 293 2600",
    "sg:postcode":"95128",
    "sg:province":"CA",
    "sg:tags":[
        "sushi",
        "bar",
        "japanese",
        "hawaiian"
    ],
    "sg:website":"www.konawavesushi.com",
    "wof:name":"Kona Wave",
    "wof:placetype":"venue"
},
  "geometry": {"coordinates":[-121.931712,37.312454],"type":"Point"}
}