{
  "type": "Feature",
  "properties": {
    "iso:country":"US",
    "sg:address":"8660 Reseda Blvd",
    "sg:city":"Northridge",
    "sg:classifiers":[
        {
            "category":"Home & Garden",
            "subcategory":"Furniture",
            "type":"Retail Goods"
        }
    ],
    "sg:phone":"+1 818 727 7580",
    "sg:postcode":"91324",
    "sg:province":"CA",
    "sg:tags":[
        "mattress"
    ],
    "wof:name":"America's Mattress",
    "wof:placetype":"venue"
},
  "geometry": {"coordinates":[-118.536007,34.227835],"type":"Point"}
}