{
  "type": "Feature",
  "properties": {
    "addr:full":"1217 Grant Ave Novato CA 94945",
    "addr:housenumber":"1217",
    "addr:postcode":"94945",
    "addr:street":"Grant Ave",
    "iso:country":"US",
    "sg:address":"1217 Grant Ave",
    "sg:city":"Novato",
    "sg:classifiers":[
        {
            "category":"Shopping",
            "subcategory":"Computers & Home Electronics",
            "type":"Retail Goods"
        }
    ],
    "sg:phone":"+1 415 897 6217",
    "sg:postcode":"94945",
    "sg:province":"CA",
    "sg:tags":[
        "television",
        "radio"
    ],
    "wof:name":"Novato TV Sales & Svc",
    "wof:placetype":"venue"
},
  "geometry": {"coordinates":[-122.573489,38.108098],"type":"Point"}
}