{
  "type": "Feature",
  "properties": {
    "addr:full":"10971 Chapman Ave Garden Grove CA 92840",
    "addr:housenumber":"10971",
    "addr:postcode":"92840",
    "addr:street":"Chapman Ave",
    "iso:country":"US",
    "sg:address":"10971 Chapman Ave",
    "sg:city":"Garden Grove",
    "sg:classifiers":[
        {
            "category":"Shopping",
            "subcategory":"Computers & Home Electronics",
            "type":"Retail Goods"
        }
    ],
    "sg:phone":"+1 714 786 8420",
    "sg:postcode":"92840",
    "sg:province":"CA",
    "wof:name":"DISH Network",
    "wof:placetype":"venue"
},
  "geometry": {"coordinates":[-117.94173600000001,33.78886],"type":"Point"}
}