{
  "type": "Feature",
  "properties": {
    "addr:full":"26833 Bouquet Canyon Rd Santa Clarita CA 91350",
    "addr:housenumber":"26833",
    "addr:postcode":"91350",
    "addr:street":"Bouquet Canyon Rd",
    "iso:country":"US",
    "sg:address":"26833 Bouquet Canyon Rd",
    "sg:city":"Santa Clarita",
    "sg:classifiers":[
        {
            "category":"Coffee & Tea",
            "type":"Food & Drink"
        }
    ],
    "sg:phone":"+1 661 263 0663",
    "sg:postcode":"91350",
    "sg:province":"CA",
    "wof:name":"Coffee Kiosk",
    "wof:placetype":"venue"
},
  "geometry": {"coordinates":[-118.529999,34.433701],"type":"Point"}
}