{
  "type": "Feature",
  "properties": {
    "addr:full":"1107 Investment Blvd El Dorado Hills CA 95762",
    "addr:housenumber":"1107",
    "addr:postcode":"95762",
    "addr:street":"Investment Blvd",
    "iso:country":"US",
    "sg:address":"1107 Investment Blvd",
    "sg:city":"El Dorado Hills",
    "sg:classifiers":[
        {
            "category":"Professional",
            "subcategory":"Lawyer & Legal Services",
            "type":"Services"
        }
    ],
    "sg:phone":"+1 916 939 3939",
    "sg:postcode":"95762",
    "sg:province":"CA",
    "wof:name":"Clemons Timothy C Attorney At Law",
    "wof:placetype":"venue"
},
  "geometry": {"coordinates":[-121.321021,38.620663],"type":"Point"}
}