{
  "type": "Feature",
  "properties": {
    "iso:country":"US",
    "sg:address":"26940 Baseline St",
    "sg:city":"Highland",
    "sg:classifiers":[
        {
            "category":"Real Estate",
            "subcategory":"Real Estate Agent",
            "type":"Services"
        }
    ],
    "sg:phone":"+1 909 862 6850",
    "sg:postcode":"92346",
    "sg:province":"CA",
    "sg:tags":[
        "buyer",
        "broker"
    ],
    "wof:name":"Prudental Signature",
    "wof:placetype":"venue"
},
  "geometry": {"coordinates":[-117.215574,34.12134],"type":"Point"}
}