{
  "type": "Feature",
  "properties": {
    "iso:country":"US",
    "sg:address":"575 Brookside Dr",
    "sg:city":"Richmond",
    "sg:classifiers":[
        {
            "category":"Wholesale",
            "subcategory":"Machinery & Supplies",
            "type":"Manufacturing & Wholesale Goods"
        }
    ],
    "sg:phone":"+1 510 237 0817",
    "sg:postcode":"94801",
    "sg:province":"CA",
    "sg:tags":[
        "box"
    ],
    "wof:name":"D M Box Co",
    "wof:placetype":"venue"
},
  "geometry": {"coordinates":[-122.359732,37.965804],"type":"Point"}
}