{
  "type": "Feature",
  "properties": {
    "addr:full":"31011 Agoura Rd Westlake Village CA 91361",
    "addr:housenumber":"31011",
    "addr:postcode":"91361",
    "addr:street":"Agoura Rd",
    "iso:country":"US",
    "sg:address":"31011 Agoura Rd",
    "sg:city":"Westlake Village",
    "sg:classifiers":[
        {
            "category":"Travel",
            "subcategory":"Travel Agent",
            "type":"Entertainment"
        }
    ],
    "sg:phone":"+1 818 879 8747",
    "sg:postcode":"91361",
    "sg:province":"CA",
    "sg:tags":[
        "agency",
        "bureau"
    ],
    "wof:name":"Promenade Travel",
    "wof:placetype":"venue"
},
  "geometry": {"coordinates":[-118.799378,34.145085],"type":"Point"}
}