{
  "type": "Feature",
  "properties": {
    "iso:country":"US",
    "sg:address":"5460 Limerick Ct",
    "sg:city":"San Diego",
    "sg:classifiers":[
        {
            "category":"Building & Trades",
            "subcategory":"Construction",
            "type":"Services"
        }
    ],
    "sg:phone":"+1 858 277 1625",
    "sg:postcode":"92117",
    "sg:province":"CA",
    "sg:tags":[
        "home",
        "improvement"
    ],
    "wof:name":"DNR Home Handyman Hauling",
    "wof:placetype":"venue"
},
  "geometry": {"coordinates":[-117.179839,32.841867],"type":"Point"}
}