{
  "type": "Feature",
  "properties": {
    "addr:full":"350 Ignacio Blvd Novato CA 94949",
    "addr:housenumber":"350",
    "addr:postcode":"94949",
    "addr:street":"Ignacio Blvd",
    "iso:country":"US",
    "sg:address":"350 Ignacio Blvd",
    "sg:city":"Novato",
    "sg:classifiers":[
        {
            "category":"Banks & Credit Unions",
            "subcategory":"Bank",
            "type":"Services"
        }
    ],
    "sg:phone":"+1 415 382 0200",
    "sg:postcode":"94949",
    "sg:province":"CA",
    "sg:tags":[
        "loan",
        "real estate"
    ],
    "wof:name":"Andrew Olmsted Pacific Capital",
    "wof:placetype":"venue"
},
  "geometry": {"coordinates":[-122.53998799999999,38.066084],"type":"Point"}
}