{
  "type": "Feature",
  "properties": {
    "iso:country":"US",
    "sg:address":"10840 Talbert Ave",
    "sg:city":"Fountain Valley",
    "sg:classifiers":[
        {
            "category":"Building & Trades",
            "subcategory":"Construction",
            "type":"Services"
        }
    ],
    "sg:phone":"+1 714 965 7900",
    "sg:postcode":"92708",
    "sg:province":"CA",
    "sg:tags":[
        "contractor"
    ],
    "sg:website":"www.bartwood.com",
    "wof:name":"Bartwood Construction",
    "wof:placetype":"venue"
},
  "geometry": {"coordinates":[-117.94000200000001,33.701698],"type":"Point"}
}