{
  "type": "Feature",
  "properties": {
    "iso:country":"US",
    "sg:address":"1750 W 6th St",
    "sg:city":"Corona",
    "sg:classifiers":[
        {
            "category":"Banks & Credit Unions",
            "subcategory":"Investment Brokerage",
            "type":"Services"
        }
    ],
    "sg:phone":"+1 951 735 1593",
    "sg:postcode":"92882",
    "sg:province":"CA",
    "sg:tags":[
        "firm"
    ],
    "wof:name":"LDS 3 Group Inc",
    "wof:placetype":"venue"
},
  "geometry": {"coordinates":[-117.599895,33.878903],"type":"Point"}
}