{
  "type": "Feature",
  "properties": {
    "iso:country":"US",
    "sg:address":"17510 Pioneer Blvd Ste 212",
    "sg:city":"Artesia",
    "sg:classifiers":[
        {
            "category":"Personal",
            "subcategory":"Beauty Salon",
            "type":"Services"
        }
    ],
    "sg:phone":"+1 562 860 5086",
    "sg:postcode":"90701",
    "sg:province":"CA",
    "sg:tags":[
        "hair"
    ],
    "wof:name":"Dylux Beauty Salon",
    "wof:placetype":"venue"
},
  "geometry": {"coordinates":[-118.08219800000001,33.871957],"type":"Point"}
}