{
  "type": "Feature",
  "properties": {
    "addr:full":"41 Sutter St San Francisco CA 94104",
    "addr:housenumber":"41",
    "addr:postcode":"94104",
    "addr:street":"Sutter St",
    "iso:country":"US",
    "sg:address":"41 Sutter St",
    "sg:city":"San Francisco",
    "sg:classifiers":[
        {
            "category":"Professional",
            "subcategory":"Secretarial Services",
            "type":"Services"
        }
    ],
    "sg:phone":"+1 415 781 6669",
    "sg:postcode":"94104",
    "sg:province":"CA",
    "sg:tags":[
        "reporting",
        "court"
    ],
    "wof:name":"Able & Bright",
    "wof:placetype":"venue"
},
  "geometry": {"coordinates":[-122.401737,37.790036],"type":"Point"}
}