{
  "type": "Feature",
  "properties": {
    "addr:full":"40047 State Hwy 41 Oakhurst CA 93644",
    "addr:housenumber":"40047",
    "addr:postcode":"93644",
    "addr:street":"State Hwy 41",
    "iso:country":"US",
    "sg:address":"40047 State Hwy 41",
    "sg:city":"Oakhurst",
    "sg:classifiers":[
        {
            "category":"Wholesale",
            "subcategory":"Machinery & Supplies",
            "type":"Manufacturing & Wholesale Goods"
        }
    ],
    "sg:phone":"+1 559 683 6100",
    "sg:postcode":"93644",
    "sg:province":"CA",
    "sg:tags":[
        "salon",
        "beauty"
    ],
    "wof:name":"Mountain Beauty Supply & Salon",
    "wof:placetype":"venue"
},
  "geometry": {"coordinates":[-119.656548,37.329974],"type":"Point"}
}