{
  "type": "Feature",
  "properties": {
    "iso:country":"US",
    "sg:address":"10750 Hemlock Ave",
    "sg:city":"Fontana",
    "sg:classifiers":[
        {
            "category":"Professional",
            "type":"Services"
        }
    ],
    "sg:phone":"+1 909 854 6241",
    "sg:postcode":"92337",
    "sg:province":"CA",
    "sg:tags":[
        "establishment"
    ],
    "wof:name":"Dealer's Prep",
    "wof:placetype":"venue"
},
  "geometry": {"coordinates":[-117.475697,34.061577],"type":"Point"}
}