{
  "type": "Feature",
  "properties": {
    "iso:country":"US",
    "sg:address":"117 E Providencia Ave",
    "sg:city":"Burbank",
    "sg:classifiers":[
        {
            "category":"Airport",
            "type":"Transportation"
        }
    ],
    "sg:phone":"+1 323 849 3961",
    "sg:postcode":"91502",
    "sg:province":"CA",
    "sg:tags":[
        "repair",
        "aircraft",
        "aerospace",
        "accessory"
    ],
    "wof:name":"Honeywell",
    "wof:placetype":"venue"
},
  "geometry": {"coordinates":[-118.304101,34.177091],"type":"Point"}
}