{
  "type": "Feature",
  "properties": {
    "addr:full":"11041 Millpond Ln Nevada City CA 95959",
    "addr:housenumber":"11041",
    "addr:postcode":"95959",
    "addr:street":"Millpond Ln",
    "iso:country":"US",
    "sg:address":"11041 Millpond Ln",
    "sg:city":"Nevada City",
    "sg:classifiers":[
        {
            "category":"Building & Trades",
            "subcategory":"Construction",
            "type":"Services"
        }
    ],
    "sg:phone":"+1 530 265 4419",
    "sg:postcode":"95959",
    "sg:province":"CA",
    "sg:tags":[
        "excavating",
        "contractor"
    ],
    "wof:name":"Steico",
    "wof:placetype":"venue"
},
  "geometry": {"coordinates":[-121.005017,39.260361],"type":"Point"}
}