{
  "type": "Feature",
  "properties": {
    "iso:country":"US",
    "sg:address":"7727 Lankershim Blvd Apt 134",
    "sg:city":"North Hollywood",
    "sg:classifiers":[
        {
            "category":"Real Estate",
            "subcategory":"Real Estate Operator",
            "type":"Services"
        }
    ],
    "sg:phone":"+1 818 982 0527",
    "sg:postcode":"91605",
    "sg:province":"CA",
    "sg:tags":[
        "apartment"
    ],
    "wof:name":"Academy Point",
    "wof:placetype":"venue"
},
  "geometry": {"coordinates":[-118.38800000000001,34.2108],"type":"Point"}
}