{
  "type": "Feature",
  "properties": {
    "iso:country":"US",
    "sg:address":"15000 Vista Vw",
    "sg:city":"Lake Elsinore",
    "sg:classifiers":[
        {
            "category":"Banks & Credit Unions",
            "subcategory":"Bank",
            "type":"Services"
        }
    ],
    "sg:phone":"+1 951 245 7335",
    "sg:postcode":"92530",
    "sg:province":"CA",
    "sg:tags":[
        "loan",
        "mortgage",
        "real estate"
    ],
    "wof:name":"Mortgage Lending Specialists",
    "wof:placetype":"venue"
},
  "geometry": {"coordinates":[-117.392898,33.69589],"type":"Point"}
}