{
  "type": "Feature",
  "properties": {
    "iso:country":"US",
    "sg:address":"3800 Oakes Dr",
    "sg:city":"Martinez",
    "sg:classifiers":[
        {
            "category":"Insurance",
            "subcategory":"Insurance Agent",
            "type":"Services"
        }
    ],
    "sg:phone":"+1 925 372 4860",
    "sg:postcode":"94542",
    "sg:province":"CA",
    "wof:name":"G F Capital Insurance Svc",
    "wof:placetype":"venue"
},
  "geometry": {"coordinates":[-122.03093699999999,37.662115],"type":"Point"}
}