{
  "type": "Feature",
  "properties": {
    "iso:country":"US",
    "sg:address":"8974 Trautwein Rd Ste B4",
    "sg:city":"Riverside",
    "sg:classifiers":[
        {
            "category":"Personal",
            "subcategory":"Beauty Salon",
            "type":"Services"
        }
    ],
    "sg:phone":"+1 951 653 1212",
    "sg:postcode":"92508",
    "sg:province":"CA",
    "wof:name":"Beauty Town",
    "wof:placetype":"venue"
},
  "geometry": {"coordinates":[-117.32409199999999,33.888559],"type":"Point"}
}