{
  "type": "Feature",
  "properties": {
    "addr:full":"120 Westbluff Ct Bakersfield CA 93305",
    "addr:housenumber":"120",
    "addr:postcode":"93305",
    "addr:street":"Westbluff Ct",
    "iso:country":"US",
    "sg:address":"120 Westbluff Ct",
    "sg:city":"Bakersfield",
    "sg:classifiers":[
        {
            "category":"Health Services",
            "subcategory":"Health Practitioner",
            "type":"Services"
        }
    ],
    "sg:phone":"+1 661 395 1919",
    "sg:postcode":"93305",
    "sg:province":"CA",
    "sg:tags":[
        "psychologist"
    ],
    "wof:name":"Action Therapy",
    "wof:placetype":"venue"
},
  "geometry": {"coordinates":[-119.002377,35.402825],"type":"Point"}
}