{
  "type": "Feature",
  "properties": {
    "iso:country":"US",
    "sg:address":"762 Sunnyvale Saratoga Rd",
    "sg:city":"Sunnyvale",
    "sg:classifiers":[
        {
            "category":"Food & Beverages",
            "subcategory":"Groceries & Convenience Stores",
            "type":"Retail Goods"
        }
    ],
    "sg:phone":"+1 408 720 0244",
    "sg:postcode":"94087",
    "sg:province":"CA",
    "sg:tags":[
        "grocer"
    ],
    "sg:website":"www.safeway.com",
    "wof:name":"Pak 'n Save Foods",
    "wof:placetype":"venue"
},
  "geometry": {"coordinates":[-122.032196,37.367177],"type":"Point"}
}