{
  "type": "Feature",
  "properties": {
    "iso:country":"US",
    "sg:address":"3712 Claremont Dr",
    "sg:city":"Bakersfield",
    "sg:classifiers":[
        {
            "category":"Farming",
            "subcategory":"Livestock Farm",
            "type":"Manufacturing & Wholesale Goods"
        }
    ],
    "sg:phone":"+1 661 871 1322",
    "sg:postcode":"93306",
    "sg:province":"CA",
    "sg:tags":[
        "beef",
        "feedlot",
        "cattle"
    ],
    "wof:name":"David L Moore Farms",
    "wof:placetype":"venue"
},
  "geometry": {"coordinates":[-118.943024,35.386345],"type":"Point"}
}