{
  "type": "Feature",
  "properties": {
    "addr:full":"309 Bryant St Ojai CA 93023",
    "addr:housenumber":"309",
    "addr:postcode":"93023",
    "addr:street":"Bryant St",
    "iso:country":"US",
    "sg:address":"309 Bryant St",
    "sg:city":"Ojai",
    "sg:classifiers":[
        {
            "category":"Freight",
            "type":"Transportation"
        }
    ],
    "sg:phone":"+1 805 646 1234",
    "sg:postcode":"93023",
    "sg:province":"CA",
    "sg:tags":[
        "material",
        "storage",
        "trucking",
        "moving",
        "services-labor",
        "local"
    ],
    "sg:website":"http://www.mayflower.com",
    "wof:name":"Mayflower Moving Service",
    "wof:placetype":"venue"
},
  "geometry": {"coordinates":[-119.23729899999999,34.446182],"type":"Point"}
}