{
  "type": "Feature",
  "properties": {
    "addr:full":"6083 N Figarden Dr Fresno CA 93722",
    "addr:housenumber":"6083",
    "addr:postcode":"93722",
    "addr:street":"N Figarden Dr",
    "iso:country":"US",
    "sg:address":"6083 N Figarden Dr",
    "sg:city":"Fresno",
    "sg:classifiers":[
        {
            "category":"Professional",
            "type":"Services"
        }
    ],
    "sg:phone":"+1 559 271 2077",
    "sg:postcode":"93722",
    "sg:province":"CA",
    "wof:name":"All For Fun Inc",
    "wof:placetype":"venue"
},
  "geometry": {"coordinates":[-119.870439,36.824868],"type":"Point"}
}