{
  "type": "Feature",
  "properties": {
    "iso:country":"US",
    "sg:address":"1236 McKinley Ave",
    "sg:city":"Woodland",
    "sg:classifiers":[
        {
            "category":"Shopping",
            "type":"Retail Goods"
        }
    ],
    "sg:phone":"+1 530 662 2757",
    "sg:postcode":"95695",
    "sg:province":"CA",
    "sg:tags":[
        "merchandise"
    ],
    "wof:name":"D Moriconi D Landscape Design",
    "wof:placetype":"venue"
},
  "geometry": {"coordinates":[-121.781838,38.663722],"type":"Point"}
}