{
  "type": "Feature",
  "properties": {
    "iso:country":"US",
    "sg:address":"9500 Gilman Dr",
    "sg:city":"La Jolla",
    "sg:classifiers":[
        {
            "category":"Shopping",
            "subcategory":"Bicycles & Sporting Goods",
            "type":"Retail Goods"
        }
    ],
    "sg:phone":"+1 858 534 8141",
    "sg:postcode":"92093",
    "sg:province":"CA",
    "sg:tags":[
        "outdoor",
        "gear"
    ],
    "sg:website":"recreation.ucsd.edu/outb/index.h...",
    "wof:name":"Outback Surf Shop",
    "wof:placetype":"venue"
},
  "geometry": {"coordinates":[-117.23609999999999,32.876186],"type":"Point"}
}