{
  "type": "Feature",
  "properties": {
    "iso:country":"US",
    "sg:address":"2968 Del Paso Blvd Ste A",
    "sg:city":"Sacramento",
    "sg:classifiers":[
        {
            "category":"Personal",
            "subcategory":"Barber",
            "type":"Services"
        }
    ],
    "sg:phone":"+1 916 920 2142",
    "sg:postcode":"95815",
    "sg:province":"CA",
    "wof:name":"Capitol Barber Shop",
    "wof:placetype":"venue"
},
  "geometry": {"coordinates":[-121.43360300000001,38.619784],"type":"Point"}
}