{
  "type": "Feature",
  "properties": {
    "iso:country":"US",
    "sg:address":"4615 San Vicente Ave",
    "sg:city":"Atascadero",
    "sg:classifiers":[
        {
            "category":"Freight",
            "type":"Transportation"
        }
    ],
    "sg:phone":"+1 805 462 9112",
    "sg:postcode":"93422",
    "sg:province":"CA",
    "sg:tags":[
        "trucking"
    ],
    "sg:website":"www.gap-logistics.com",
    "wof:name":"Landstar Ligon Inc",
    "wof:placetype":"venue"
},
  "geometry": {"coordinates":[-120.670682,35.505889],"type":"Point"}
}