{
  "type": "Feature",
  "properties": {
    "iso:country":"US",
    "sg:address":"7016 Primrose Ln",
    "sg:city":"Redding",
    "sg:classifiers":[
        {
            "category":"Professional",
            "type":"Services"
        }
    ],
    "sg:phone":"+1 530 365 4704",
    "sg:postcode":"96002",
    "sg:province":"CA",
    "wof:name":"All American D V S",
    "wof:placetype":"venue"
},
  "geometry": {"coordinates":[-122.278418,40.492914],"type":"Point"}
}