{
  "type": "Feature",
  "properties": {
    "iso:country":"US",
    "sg:address":"11935 Woodside Ave",
    "sg:city":"Lakeside",
    "sg:classifiers":[
        {
            "category":"Wholesale",
            "subcategory":"Motor Vehicles",
            "type":"Manufacturing & Wholesale Goods"
        }
    ],
    "sg:phone":"+1 619 390 3666",
    "sg:postcode":"92040",
    "sg:province":"CA",
    "wof:name":"Truck King",
    "wof:placetype":"venue"
},
  "geometry": {"coordinates":[-116.936172,32.855278],"type":"Point"}
}