{
  "type": "Feature",
  "properties": {
    "addr:full":"1965 Zehndner Ave Arcata CA 95521",
    "addr:housenumber":"1965",
    "addr:postcode":"95521",
    "addr:street":"Zehndner Ave",
    "iso:country":"US",
    "sg:address":"1965 Zehndner Ave",
    "sg:city":"Arcata",
    "sg:classifiers":[
        {
            "category":"Building & Trades",
            "subcategory":"Landscaping Services",
            "type":"Services"
        }
    ],
    "sg:phone":"+1 707 822 4191",
    "sg:postcode":"95521",
    "sg:province":"CA",
    "wof:name":"Jantzhoffman Gardening Service",
    "wof:placetype":"venue"
},
  "geometry": {"coordinates":[-124.100022,40.875833],"type":"Point"}
}