{
  "type": "Feature",
  "properties": {
    "iso:country":"US",
    "sg:address":"Yerba Buena Gardens 3rd and Mission St",
    "sg:city":"San Francisco",
    "sg:classifiers":[
        {
            "category":"Restaurant",
            "type":"Food & Drink"
        },
        {
            "category":"Arena",
            "subcategory":"Sports Club",
            "type":"Entertainment"
        }
    ],
    "sg:postcode":"94103",
    "sg:province":"CA",
    "sg:tags":[
        "flavor",
        "martial art",
        "local"
    ],
    "wof:name":"Tai Chi Practice at Yerba Buena Gardens",
    "wof:placetype":"venue"
},
  "geometry": {"coordinates":[-122.401979,37.786234],"type":"Point"}
}