{
  "type": "Feature",
  "properties": {
    "iso:country":"US",
    "sg:address":"14141 Covello St",
    "sg:city":"Van Nuys",
    "sg:classifiers":[
        {
            "category":"Organizations",
            "subcategory":"Non-profit Organization",
            "type":"Services"
        }
    ],
    "sg:phone":"+1 818 997 8688",
    "sg:postcode":"91405",
    "sg:province":"CA",
    "sg:tags":[
        "medical",
        "management"
    ],
    "sg:website":"www.nationwidemedical.net",
    "wof:name":"Nationwide Medical Surgical",
    "wof:placetype":"venue"
},
  "geometry": {"coordinates":[-118.443633,34.207056],"type":"Point"}
}