{
  "type": "Feature",
  "properties": {
    "iso:country":"US",
    "sg:address":"19469 Via del Caballo",
    "sg:city":"Yorba Linda",
    "sg:classifiers":[
        {
            "category":"Professional",
            "type":"Services"
        }
    ],
    "sg:phone":"+1 714 979 1573",
    "sg:postcode":"92886",
    "sg:province":"CA",
    "wof:name":"Morr Is Tested Inc",
    "wof:placetype":"venue"
},
  "geometry": {"coordinates":[-117.797229,33.895791],"type":"Point"}
}