{
  "type": "Feature",
  "properties": {
    "addr:full":"4805 Surrey Ln Bakersfield CA 93309",
    "addr:housenumber":"4805",
    "addr:postcode":"93309",
    "addr:street":"Surrey Ln",
    "iso:country":"US",
    "sg:address":"4805 Surrey Ln",
    "sg:city":"Bakersfield",
    "sg:classifiers":[
        {
            "category":"Mining & Drilling",
            "type":"Manufacturing & Wholesale Goods"
        }
    ],
    "sg:phone":"+1 661 831 0615",
    "sg:postcode":"93309",
    "sg:province":"CA",
    "sg:tags":[
        "field"
    ],
    "wof:name":"Acsi Thermal Recovery Group",
    "wof:placetype":"venue"
},
  "geometry": {"coordinates":[-119.056145,35.335892],"type":"Point"}
}