{
  "type": "Feature",
  "properties": {
    "iso:country":"US",
    "sg:address":"23846 Humiston Way",
    "sg:city":"Ramona",
    "sg:classifiers":[
        {
            "category":"Personal",
            "type":"Services"
        },
        {
            "category":"Retail",
            "subcategory":"Animal Services",
            "type":"Services"
        }
    ],
    "sg:phone":"+1 760 788 5494",
    "sg:postcode":"92065",
    "sg:province":"CA",
    "sg:tags":[
        "pet",
        "boarding",
        "sitting"
    ],
    "sg:website":"www.karenscrittercare.com",
    "wof:name":"Karens' Critter Care",
    "wof:placetype":"venue"
},
  "geometry": {"coordinates":[-116.813608,33.017332],"type":"Point"}
}