{
  "type": "Feature",
  "properties": {
    "addr:full":"40951 Grimmer Blvd Fremont CA 94538",
    "addr:postcode":"40951;94538",
    "addr:street":"Grimmer Blvd",
    "iso:country":"US",
    "sg:address":"40951 Grimmer Blvd",
    "sg:city":"Fremont",
    "sg:classifiers":[
        {
            "category":"Retail",
            "subcategory":"Veterinary Services",
            "type":"Services"
        }
    ],
    "sg:phone":"+1 510 651 0707",
    "sg:postcode":"94538",
    "sg:province":"CA",
    "sg:tags":[
        "hospital",
        "animal"
    ],
    "wof:name":"Grimmer Boulevard Veterinary",
    "wof:placetype":"venue"
},
  "geometry": {"coordinates":[-121.968208,37.533129],"type":"Point"}
}