{
  "type": "Feature",
  "properties": {
    "iso:country":"US",
    "sg:address":"1821 E Dakota Ave",
    "sg:city":"Fresno",
    "sg:classifiers":[
        {
            "category":"Building & Trades",
            "subcategory":"Landscaping Services",
            "type":"Services"
        }
    ],
    "sg:phone":"+1 559 244 0419",
    "sg:postcode":"93726",
    "sg:province":"CA",
    "sg:tags":[
        "tree"
    ],
    "wof:name":"Central Tree Care",
    "wof:placetype":"venue"
},
  "geometry": {"coordinates":[-119.788133,36.78686],"type":"Point"}
}