{
  "type": "Feature",
  "properties": {
    "addr:full":"6285 Zumirez Dr Malibu CA 90265",
    "addr:housenumber":"6285",
    "addr:postcode":"90265",
    "addr:street":"Zumirez Dr",
    "iso:country":"US",
    "sg:address":"6285 Zumirez Dr",
    "sg:city":"Malibu",
    "sg:classifiers":[
        {
            "category":"Building & Trades",
            "subcategory":"Landscaping Services",
            "type":"Services"
        }
    ],
    "sg:phone":"+1 310 457 1011",
    "sg:postcode":"90265",
    "sg:province":"CA",
    "sg:tags":[
        "contractor"
    ],
    "wof:name":"Baja Landscape",
    "wof:placetype":"venue"
},
  "geometry": {"coordinates":[-118.795877,34.024793],"type":"Point"}
}