{
  "type": "Feature",
  "properties": {
    "addr:full":"6161 Ocotillo Ave Twentynine Palms CA 92277",
    "addr:housenumber":"6161",
    "addr:postcode":"92277",
    "addr:street":"Ocotillo Ave",
    "iso:country":"US",
    "sg:address":"6161 Ocotillo Ave",
    "sg:city":"Twentynine Palms",
    "sg:classifiers":[
        {
            "category":"Building & Trades",
            "subcategory":"Construction",
            "type":"Services"
        },
        {
            "category":"Real Estate",
            "subcategory":"Real Estate Operator",
            "type":"Services"
        }
    ],
    "sg:phone":"+1 760 367 9901",
    "sg:postcode":"92277",
    "sg:province":"CA",
    "sg:tags":[
        "mobile",
        "home",
        "apartment",
        "park"
    ],
    "wof:name":"Casitas Cientos Mobile Home Pk",
    "wof:placetype":"venue"
},
  "geometry": {"coordinates":[-116.05309200000001,34.140724],"type":"Point"}
}