{
  "type": "Feature",
  "properties": {
    "iso:country":"US",
    "sg:address":"5209 E 2nd St",
    "sg:city":"Long Beach",
    "sg:classifiers":[
        {
            "category":"Shopping",
            "subcategory":"Gifts & Souvenirs",
            "type":"Retail Goods"
        }
    ],
    "sg:phone":"+1 562 439 5372",
    "sg:postcode":"90803",
    "sg:province":"CA",
    "wof:name":"Romance Etc",
    "wof:placetype":"venue"
},
  "geometry": {"coordinates":[-118.13469,33.760292],"type":"Point"}
}