{
  "type": "Feature",
  "properties": {
    "iso:country":"US",
    "sg:address":"135 E Live Oak Ave",
    "sg:city":"Arcadia",
    "sg:classifiers":[
        {
            "category":"Manufacturing",
            "subcategory":"Printing",
            "type":"Manufacturing & Wholesale Goods"
        }
    ],
    "sg:phone":"+1 626 446 6122",
    "sg:postcode":"91006",
    "sg:province":"CA",
    "wof:name":"New Coast Marketing Inc",
    "wof:placetype":"venue"
},
  "geometry": {"coordinates":[-118.025149,34.108184],"type":"Point"}
}