{
  "type": "Feature",
  "properties": {
    "addr:full":"21611 Lemon St Wildomar CA 92595",
    "addr:housenumber":"21611",
    "addr:postcode":"92595",
    "addr:street":"Lemon St",
    "iso:country":"US",
    "sg:address":"21611 Lemon St",
    "sg:city":"Wildomar",
    "sg:classifiers":[
        {
            "category":"Organizations",
            "subcategory":"Religious Organization",
            "type":"Services"
        }
    ],
    "sg:phone":"+1 951 674 6881",
    "sg:postcode":"92595",
    "sg:province":"CA",
    "wof:name":"St Frances of Rome",
    "wof:placetype":"venue"
},
  "geometry": {"coordinates":[-117.28192300000001,33.633951],"type":"Point"}
}