{
  "type": "Feature",
  "properties": {
    "iso:country":"US",
    "sg:address":"275 N Clovis Ave",
    "sg:city":"Clovis",
    "sg:classifiers":[
        {
            "category":"Professional",
            "type":"Services"
        }
    ],
    "sg:phone":"+1 559 297 1758",
    "sg:postcode":"93612",
    "sg:province":"CA",
    "wof:name":"Wallace Kyle",
    "wof:placetype":"venue"
},
  "geometry": {"coordinates":[-119.699979,36.833912],"type":"Point"}
}