{
  "type": "Feature",
  "properties": {
    "addr:full":"33415 Shay Ln Wildomar CA 92595",
    "addr:postcode":"33415;92595",
    "addr:street":"Shay Ln",
    "iso:country":"US",
    "sg:address":"33415 Shay Ln",
    "sg:city":"Wildomar",
    "sg:classifiers":[
        {
            "category":"Building & Trades",
            "subcategory":"Construction",
            "type":"Services"
        }
    ],
    "sg:phone":"+1 951 674 5163",
    "sg:postcode":"92595",
    "sg:province":"CA",
    "sg:tags":[
        "system",
        "contractor",
        "air conditioning"
    ],
    "wof:name":"Stein Heating And Air",
    "wof:placetype":"venue"
},
  "geometry": {"coordinates":[-117.288134,33.613347],"type":"Point"}
}