{
  "type": "Feature",
  "properties": {
    "iso:country":"US",
    "sg:address":"119 Stockdale Cir",
    "sg:city":"Bakersfield",
    "sg:classifiers":[
        {
            "category":"Manufacturing",
            "subcategory":"Furniture",
            "type":"Manufacturing & Wholesale Goods"
        }
    ],
    "sg:phone":"+1 661 834 3556",
    "sg:postcode":"93309",
    "sg:province":"CA",
    "wof:name":"Judys Interiors",
    "wof:placetype":"venue"
},
  "geometry": {"coordinates":[-119.07804299999999,35.355287],"type":"Point"}
}