{
  "type": "Feature",
  "properties": {
    "addr:full":"5130 International Blvd Oakland CA 94601",
    "addr:housenumber":"5130",
    "addr:postcode":"94601",
    "addr:street":"International Blvd",
    "iso:country":"US",
    "sg:address":"5130 International Blvd",
    "sg:city":"Oakland",
    "sg:classifiers":[
        {
            "category":"Government",
            "subcategory":"Office",
            "type":"Public Place"
        }
    ],
    "sg:phone":"+1 510 536 3989",
    "sg:postcode":"94601",
    "sg:province":"CA",
    "sg:tags":[
        "smog",
        "check"
    ],
    "wof:name":"Q Smog Check Test Only",
    "wof:placetype":"venue"
},
  "geometry": {"coordinates":[-122.207519,37.769028],"type":"Point"}
}