{
  "type": "Feature",
  "properties": {
    "iso:country":"US",
    "sg:address":"10956 Weyburn Ave",
    "sg:city":"Los Angeles",
    "sg:classifiers":[
        {
            "category":"Real Estate",
            "subcategory":"Architect",
            "type":"Services"
        }
    ],
    "sg:phone":"+1 310 396 1157",
    "sg:postcode":"90024",
    "sg:province":"CA",
    "wof:name":"Ward Jewell and Associates Architect Aia",
    "wof:placetype":"venue"
},
  "geometry": {"coordinates":[-118.447998,34.062199],"type":"Point"}
}