{
  "type": "Feature",
  "properties": {
    "addr:full":"21171 Western Ave Ste 260 Torrance CA 90501",
    "addr:housenumber":"21171",
    "addr:postcode":"90501",
    "addr:street":"Western Ave Ste 260",
    "iso:country":"US",
    "sg:address":"21171 Western Ave Ste 260",
    "sg:city":"Torrance",
    "sg:classifiers":[
        {
            "category":"Professional",
            "type":"Services"
        },
        {
            "category":"Communications",
            "subcategory":"Newspaper",
            "type":"Services"
        }
    ],
    "sg:phone":"+1 310 212 5727",
    "sg:postcode":"90501",
    "sg:province":"CA",
    "sg:tags":[
        "print",
        "medium"
    ],
    "sg:website":"www.cdmginc.com",
    "wof:name":"CDMG, Inc.",
    "wof:placetype":"venue"
},
  "geometry": {"coordinates":[-118.309242,33.836921],"type":"Point"}
}