{
  "type": "Feature",
  "properties": {
    "addr:full":"11462 Telegraph Rd Santa Fe Springs CA 90670",
    "addr:housenumber":"11462",
    "addr:postcode":"90670",
    "addr:street":"Telegraph Rd",
    "iso:country":"US",
    "sg:address":"11462 Telegraph Rd",
    "sg:city":"Santa Fe Springs",
    "sg:classifiers":[
        {
            "category":"Professional",
            "subcategory":"Art Services",
            "type":"Services"
        },
        {
            "category":"Professional",
            "subcategory":"Printing & Photocopies",
            "type":"Services"
        }
    ],
    "sg:phone":"+1 562 207 2655",
    "sg:postcode":"90670",
    "sg:province":"CA",
    "sg:tags":[
        "graphic",
        "design"
    ],
    "wof:name":"The Copy Center",
    "wof:placetype":"venue"
},
  "geometry": {"coordinates":[-118.089089,33.948494],"type":"Point"}
}