{
  "type": "Feature",
  "properties": {
    "iso:country":"US",
    "sg:address":"1224 E Edinger Ave",
    "sg:city":"Santa Ana",
    "sg:classifiers":[
        {
            "category":"Wholesale",
            "subcategory":"Machinery & Supplies",
            "type":"Manufacturing & Wholesale Goods"
        }
    ],
    "sg:phone":"+1 714 543 5422",
    "sg:postcode":"92707",
    "sg:province":"CA",
    "wof:name":"Advance Irrigation Supply",
    "wof:placetype":"venue"
},
  "geometry": {"coordinates":[-117.85622100000001,33.726813],"type":"Point"}
}