{
  "type": "Feature",
  "properties": {
    "addr:full":"114 18th St Bakersfield CA 93301",
    "addr:housenumber":"114",
    "addr:postcode":"93301",
    "addr:street":"18Th St",
    "iso:country":"US",
    "sg:address":"114 18th St",
    "sg:city":"Bakersfield",
    "sg:classifiers":[
        {
            "category":"Professional",
            "subcategory":"Computer Services",
            "type":"Services"
        }
    ],
    "sg:phone":"+1 661 631 9432",
    "sg:postcode":"93301",
    "sg:province":"CA",
    "sg:tags":[
        "repair"
    ],
    "wof:name":"On-Site Computer Svc",
    "wof:placetype":"venue"
},
  "geometry": {"coordinates":[-119.004677,35.375311],"type":"Point"}
}