{
  "type": "Feature",
  "properties": {
    "addr:full":"9164 Magnolia Ave Riverside CA 92503",
    "addr:housenumber":"9164",
    "addr:postcode":"92503",
    "addr:street":"Magnolia Ave",
    "iso:country":"US",
    "sg:address":"9164 Magnolia Ave",
    "sg:city":"Riverside",
    "sg:classifiers":[
        {
            "category":"Restaurant",
            "type":"Food & Drink"
        }
    ],
    "sg:phone":"+1 951 688 8868",
    "sg:postcode":"92503",
    "sg:province":"CA",
    "wof:name":"El Chilango",
    "wof:placetype":"venue"
},
  "geometry": {"coordinates":[-117.439875,33.924162],"type":"Point"}
}