{
  "type": "Feature",
  "properties": {
    "iso:country":"US",
    "sg:address":"3684 Virgin Islands Ct",
    "sg:city":"Pleasanton",
    "sg:classifiers":[
        {
            "category":"Real Estate",
            "subcategory":"Real Estate Services",
            "type":"Services"
        },
        {
            "category":"Building & Trades",
            "subcategory":"Cleaning & Sanitation",
            "type":"Services"
        }
    ],
    "sg:phone":"+1 925 846 9318",
    "sg:postcode":"94588",
    "sg:province":"CA",
    "sg:tags":[
        "maintenance",
        "cleaners-interior"
    ],
    "wof:name":"Shirleys Housekeeping",
    "wof:placetype":"venue"
},
  "geometry": {"coordinates":[-121.90902699999999,37.674581],"type":"Point"}
}