{
  "type": "Feature",
  "properties": {
    "addr:full":"1431 E Beamer St Woodland CA 95776",
    "addr:housenumber":"1431",
    "addr:postcode":"95776",
    "addr:street":"E Beamer St",
    "iso:country":"US",
    "sg:address":"1431 E Beamer St",
    "sg:city":"Woodland",
    "sg:classifiers":[
        {
            "category":"Winery",
            "type":"Food & Drink"
        },
        {
            "category":"Food & Beverages",
            "subcategory":"Farmers Market",
            "type":"Retail Goods"
        }
    ],
    "sg:phone":"+1 530 662 2145",
    "sg:postcode":"95776",
    "sg:province":"CA",
    "sg:tags":[
        "vegetable",
        "fruit",
        "shipper",
        "grower"
    ],
    "wof:name":"Phillips R H Vineyard",
    "wof:placetype":"venue"
},
  "geometry": {"coordinates":[-121.754526,38.684573],"type":"Point"}
}