{
  "type": "Feature",
  "properties": {
    "iso:country":"US",
    "sg:address":"10256 Coralwood Ct",
    "sg:city":"Alta Loma",
    "sg:classifiers":[
        {
            "category":"Professional",
            "type":"Services"
        }
    ],
    "sg:phone":"+1 909 996 2070",
    "sg:postcode":"91737",
    "sg:province":"CA",
    "wof:name":"R & C American Trust Recovery",
    "wof:placetype":"venue"
},
  "geometry": {"coordinates":[-117.58035,34.147786],"type":"Point"}
}