{
  "type": "Feature",
  "properties": {
    "iso:country":"US",
    "sg:address":"470 Landsdown Cir",
    "sg:city":"Rohnert Park",
    "sg:classifiers":[
        {
            "category":"Retail",
            "subcategory":"Repair Shop",
            "type":"Services"
        }
    ],
    "sg:phone":"+1 707 792 9600",
    "sg:postcode":"94928",
    "sg:province":"CA",
    "sg:tags":[
        "repairing",
        "piano",
        "refinishing"
    ],
    "wof:name":"Seth's Piano Svc",
    "wof:placetype":"venue"
},
  "geometry": {"coordinates":[-122.691512,38.322458],"type":"Point"}
}