{
  "type": "Feature",
  "properties": {
    "iso:country":"US",
    "sg:address":"4432 Cardinal Ct",
    "sg:city":"Napa",
    "sg:classifiers":[
        {
            "category":"Professional",
            "type":"Services"
        }
    ],
    "sg:phone":"+1 707 224 6803",
    "sg:postcode":"94558",
    "sg:province":"CA",
    "wof:name":"Craig & Lori Co",
    "wof:placetype":"venue"
},
  "geometry": {"coordinates":[-122.314924,38.346035],"type":"Point"}
}