{
  "type": "Feature",
  "properties": {
    "iso:country":"US",
    "sg:address":"14822 Beach Blvd",
    "sg:city":"La Mirada",
    "sg:classifiers":[
        {
            "category":"Restaurant",
            "type":"Food & Drink"
        }
    ],
    "sg:phone":"+1 714 670 6701",
    "sg:postcode":"90638",
    "sg:province":"CA",
    "sg:tags":[
        "sandwich"
    ],
    "wof:name":"Kwik Pick",
    "wof:placetype":"venue"
},
  "geometry": {"coordinates":[-117.98699999999999,33.897499],"type":"Point"}
}