{
  "type": "Feature",
  "properties": {
    "iso:country":"US",
    "sg:address":"1001 Camelia St",
    "sg:city":"Berkeley",
    "sg:classifiers":[
        {
            "category":"Home & Garden",
            "subcategory":"Home Furnishings",
            "type":"Retail Goods"
        },
        {
            "category":"Home & Garden",
            "subcategory":"Furniture",
            "type":"Retail Goods"
        }
    ],
    "sg:phone":"+1 510 526 1241",
    "sg:postcode":"94710",
    "sg:province":"CA",
    "sg:tags":[
        "decor",
        "store"
    ],
    "sg:website":"www.easternclassics.net",
    "wof:name":"Eastern Classics",
    "wof:placetype":"venue"
},
  "geometry": {"coordinates":[-122.297101,37.878899],"type":"Point"}
}