{
  "type": "Feature",
  "properties": {
    "iso:country":"US",
    "sg:address":"116 W 2nd St",
    "sg:city":"Chico",
    "sg:classifiers":[
        {
            "category":"Professional",
            "subcategory":"Printing & Photocopies",
            "type":"Services"
        }
    ],
    "sg:phone":"+1 530 895 0232",
    "sg:postcode":"95928",
    "sg:province":"CA",
    "sg:tags":[
        "duplicating",
        "copying"
    ],
    "wof:name":"Prompt Copy Svc",
    "wof:placetype":"venue"
},
  "geometry": {"coordinates":[-121.84123,39.729898],"type":"Point"}
}