{
  "type": "Feature",
  "properties": {
    "iso:country":"US",
    "sg:address":"1333 Willow Pass Rd # 102",
    "sg:city":"Concord",
    "sg:classifiers":[
        {
            "category":"Health Services",
            "subcategory":"Clinic",
            "type":"Services"
        }
    ],
    "sg:phone":"+1 925 825 1793",
    "sg:postcode":"94520",
    "sg:province":"CA",
    "sg:tags":[
        "information",
        "mental"
    ],
    "wof:name":"Portia Bell Hume Center",
    "wof:placetype":"venue"
},
  "geometry": {"coordinates":[-122.051952,37.968847],"type":"Point"}
}