{
  "type": "Feature",
  "properties": {
    "addr:full":"3575 San Pablo Dam Rd El Sobrante CA 94803",
    "addr:housenumber":"3575",
    "addr:postcode":"94803",
    "addr:street":"San Pablo Dam Rd",
    "iso:country":"US",
    "sg:address":"3575 San Pablo Dam Rd",
    "sg:city":"El Sobrante",
    "sg:classifiers":[
        {
            "category":"Real Estate",
            "subcategory":"Real Estate Agent",
            "type":"Services"
        }
    ],
    "sg:phone":"+1 510 758 5637",
    "sg:postcode":"94803",
    "sg:province":"CA",
    "wof:name":"Prudential",
    "wof:placetype":"venue"
},
  "geometry": {"coordinates":[-122.319388,37.964023],"type":"Point"}
}