{
  "type": "Feature",
  "properties": {
    "iso:country":"US",
    "sg:address":"10501 Valley Blvd",
    "sg:city":"El Monte",
    "sg:classifiers":[
        {
            "category":"Banks & Credit Unions",
            "subcategory":"Investment Brokerage",
            "type":"Services"
        }
    ],
    "sg:phone":"+1 626 279 7136",
    "sg:postcode":"91731",
    "sg:province":"CA",
    "sg:tags":[
        "investing"
    ],
    "wof:name":"Af Pacific Inc",
    "wof:placetype":"venue"
},
  "geometry": {"coordinates":[-118.042,34.076302],"type":"Point"}
}