{
  "type": "Feature",
  "properties": {
    "iso:country":"US",
    "sg:address":"8788 Elk Grove Blvd",
    "sg:city":"Elk Grove",
    "sg:classifiers":[
        {
            "category":"Professional",
            "subcategory":"Lawyer & Legal Services",
            "type":"Services"
        }
    ],
    "sg:phone":"+1 916 685 7878",
    "sg:postcode":"95624",
    "sg:province":"CA",
    "sg:tags":[
        "attorney"
    ],
    "wof:name":"Michael L English Law Office",
    "wof:placetype":"venue"
},
  "geometry": {"coordinates":[-121.378443,38.408989],"type":"Point"}
}