{
  "type": "Feature",
  "properties": {
    "iso:country":"US",
    "sg:address":"10004 Rush St",
    "sg:city":"South El Monte",
    "sg:classifiers":[
        {
            "category":"Professional",
            "type":"Services"
        }
    ],
    "sg:phone":"+1 626 582 1802",
    "sg:postcode":"91733",
    "sg:province":"CA",
    "sg:tags":[
        "establishment"
    ],
    "wof:name":"DMI Co",
    "wof:placetype":"venue"
},
  "geometry": {"coordinates":[-118.049882,34.051764],"type":"Point"}
}