{
  "type": "Feature",
  "properties": {
    "addr:full":"222 E Carrillo St Santa Barbara CA 93101",
    "addr:housenumber":"222",
    "addr:postcode":"93101",
    "addr:street":"E Carrillo St",
    "iso:country":"US",
    "sg:address":"222 E Carrillo St",
    "sg:city":"Santa Barbara",
    "sg:classifiers":[
        {
            "category":"Real Estate",
            "subcategory":"Real Estate Agent",
            "type":"Services"
        }
    ],
    "sg:phone":"+1 805 899 2400",
    "sg:postcode":"93101",
    "sg:province":"CA",
    "wof:name":"Pacifica Real Estate Group",
    "wof:placetype":"venue"
},
  "geometry": {"coordinates":[-119.698623,34.424377],"type":"Point"}
}