{
  "type": "Feature",
  "properties": {
    "iso:country":"US",
    "sg:address":"16610 S Normandie Ave",
    "sg:city":"Gardena",
    "sg:classifiers":[
        {
            "category":"Retail",
            "subcategory":"Auto Repair",
            "type":"Services"
        }
    ],
    "sg:phone":"+1 310 630 0150",
    "sg:postcode":"90247",
    "sg:province":"CA",
    "sg:tags":[
        "body",
        "automobile",
        "painting"
    ],
    "wof:name":"A Universal Auto Body & Paint",
    "wof:placetype":"venue"
},
  "geometry": {"coordinates":[-118.299755,33.879594],"type":"Point"}
}