{
  "type": "Feature",
  "properties": {
    "addr:full":"7297 Ronson Road San Diego CA 92111",
    "addr:housenumber":"7297",
    "addr:postcode":"92111",
    "addr:street":"Ronson Road",
    "iso:country":"US",
    "sg:address":"7297 Ronson Road",
    "sg:city":"San Diego",
    "sg:classifiers":[
        {
            "category":"Professional",
            "subcategory":"Computer Services",
            "type":"Services"
        }
    ],
    "sg:phone":"+1 858 495 7300",
    "sg:postcode":"92111",
    "sg:province":"CA",
    "sg:tags":[
        "repair"
    ],
    "wof:name":"Apcom Computer Consultants",
    "wof:placetype":"venue"
},
  "geometry": {"coordinates":[-117.15987800000001,32.828971],"type":"Point"}
}