{
  "type": "Feature",
  "properties": {
    "iso:country":"US",
    "sg:address":"2061 S Garey Ave",
    "sg:city":"Pomona",
    "sg:classifiers":[
        {
            "category":"Shopping",
            "subcategory":"Department Store",
            "type":"Retail Goods"
        }
    ],
    "sg:phone":"+1 909 364 8483",
    "sg:postcode":"91766",
    "sg:province":"CA",
    "sg:tags":[
        "shop"
    ],
    "wof:name":"99 Cost Bargain",
    "wof:placetype":"venue"
},
  "geometry": {"coordinates":[-117.749416,34.036366],"type":"Point"}
}