{
  "type": "Feature",
  "properties": {
    "iso:country":"US",
    "sg:address":"525 Pine Ave",
    "sg:city":"Holtville",
    "sg:classifiers":[
        {
            "category":"Coffee & Tea",
            "type":"Food & Drink"
        },
        {
            "category":"Restaurant",
            "type":"Food & Drink"
        }
    ],
    "sg:phone":"+1 760 356 4624",
    "sg:postcode":"92250",
    "sg:province":"CA",
    "sg:tags":[
        "espresso"
    ],
    "wof:name":"Nana's Cafe",
    "wof:placetype":"venue"
},
  "geometry": {"coordinates":[-115.381382,32.811408],"type":"Point"}
}