{
  "type": "Feature",
  "properties": {
    "addr:full":"100 Glacier Dr Martinez CA 94553",
    "addr:housenumber":"100",
    "addr:postcode":"94553",
    "addr:street":"Glacier Dr",
    "iso:country":"US",
    "sg:address":"100 Glacier Dr",
    "sg:city":"Martinez",
    "sg:classifiers":[
        {
            "category":"Government",
            "subcategory":"Office",
            "type":"Public Place"
        }
    ],
    "sg:phone":"+1 925 646 2474",
    "sg:postcode":"94553",
    "sg:province":"CA",
    "wof:name":"Contra Costa Cnty Victim Wtnss",
    "wof:placetype":"venue"
},
  "geometry": {"coordinates":[-122.087441,37.987788],"type":"Point"}
}