{
  "type": "Feature",
  "properties": {
    "iso:country":"US",
    "sg:address":"4401 Fruitvale Ave",
    "sg:city":"Bakersfield",
    "sg:classifiers":[
        {
            "category":"Building & Trades",
            "subcategory":"Construction",
            "type":"Services"
        }
    ],
    "sg:phone":"+1 661 829 2792",
    "sg:postcode":"93308",
    "sg:province":"CA",
    "sg:tags":[
        "general",
        "contractor"
    ],
    "wof:name":"Ashwood Construction",
    "wof:placetype":"venue"
},
  "geometry": {"coordinates":[-119.074423,35.405073],"type":"Point"}
}