{
  "type": "Feature",
  "properties": {
    "iso:country":"US",
    "sg:address":"42 Billington Ln",
    "sg:city":"Windsor",
    "sg:classifiers":[
        {
            "category":"Building & Trades",
            "subcategory":"Construction",
            "type":"Services"
        }
    ],
    "sg:phone":"+1 707 836 9616",
    "sg:postcode":"95492",
    "sg:province":"CA",
    "sg:tags":[
        "hanging",
        "contractor"
    ],
    "wof:name":"DBS Painting Co",
    "wof:placetype":"venue"
},
  "geometry": {"coordinates":[-122.789473,38.535209],"type":"Point"}
}