{
  "type": "Feature",
  "properties": {
    "addr:full":"197 Pomeroy Ave Pismo Beach CA 93449",
    "addr:housenumber":"197",
    "addr:postcode":"93449",
    "addr:street":"Pomeroy Ave",
    "iso:country":"US",
    "sg:address":"197 Pomeroy Ave",
    "sg:city":"Pismo Beach",
    "sg:classifiers":[
        {
            "category":"Restaurant",
            "type":"Food & Drink"
        }
    ],
    "sg:phone":"+1 805 773 4653",
    "sg:postcode":"93449",
    "sg:province":"CA",
    "sg:website":"www.splashcafe.com",
    "wof:name":"Splash Cafe",
    "wof:placetype":"venue"
},
  "geometry": {"coordinates":[-120.642791,35.139565],"type":"Point"}
}