{
  "type": "Feature",
  "properties": {
    "addr:full":"375 Blackstone Dr San Rafael CA 94903",
    "addr:housenumber":"375",
    "addr:postcode":"94903",
    "addr:street":"Blackstone Dr",
    "iso:country":"US",
    "sg:address":"375 Blackstone Dr",
    "sg:city":"San Rafael",
    "sg:classifiers":[
        {
            "category":"Education",
            "subcategory":"School",
            "type":"Public Place"
        }
    ],
    "sg:phone":"+1 415 492 3741",
    "sg:postcode":"94903",
    "sg:province":"CA",
    "wof:name":"Mary E Silveira School",
    "wof:placetype":"venue"
},
  "geometry": {"coordinates":[-122.542479,38.038375],"type":"Point"}
}