{
  "type": "Feature",
  "properties": {
    "iso:country":"US",
    "sg:address":"120 E 8th St",
    "sg:city":"Los Angeles",
    "sg:classifiers":[
        {
            "category":"Manufacturing",
            "subcategory":"Apparel",
            "type":"Manufacturing & Wholesale Goods"
        }
    ],
    "sg:phone":"+1 213 623 6786",
    "sg:postcode":"90014",
    "sg:province":"CA",
    "sg:tags":[
        "sewing",
        "contractor"
    ],
    "wof:name":"Two Young Fashion",
    "wof:placetype":"venue"
},
  "geometry": {"coordinates":[-118.252376,34.041881],"type":"Point"}
}