{
  "type": "Feature",
  "properties": {
    "iso:country":"US",
    "sg:address":"6970 Central Ave",
    "sg:city":"Lemon Grove",
    "sg:classifiers":[
        {
            "category":"Health Services",
            "subcategory":"Clinic",
            "type":"Services"
        }
    ],
    "sg:phone":"+1 619 463 7923",
    "sg:postcode":"91945",
    "sg:province":"CA",
    "wof:name":"Rogers Evangeline",
    "wof:placetype":"venue"
},
  "geometry": {"coordinates":[-117.045143,32.738909],"type":"Point"}
}