{
  "type": "Feature",
  "properties": {
    "addr:full":"4841 Jackson St Riverside CA 92503",
    "addr:housenumber":"4841",
    "addr:postcode":"92503",
    "addr:street":"Jackson St",
    "iso:country":"US",
    "sg:address":"4841 Jackson St",
    "sg:city":"Riverside",
    "sg:classifiers":[
        {
            "category":"Professional",
            "type":"Services"
        }
    ],
    "sg:phone":"+1 951 689 5501",
    "sg:postcode":"92503",
    "sg:province":"CA",
    "wof:name":"Henry A Banks",
    "wof:placetype":"venue"
},
  "geometry": {"coordinates":[-117.44973299999999,33.937552],"type":"Point"}
}