{
  "type": "Feature",
  "properties": {
    "iso:country":"US",
    "sg:address":"1506 Bank St",
    "sg:city":"South Pasadena",
    "sg:classifiers":[
        {
            "category":"Building & Trades",
            "subcategory":"Construction",
            "type":"Services"
        }
    ],
    "sg:phone":"+1 626 799 2672",
    "sg:postcode":"91030",
    "sg:province":"CA",
    "sg:tags":[
        "painter"
    ],
    "wof:name":"Ryan Painting Svc",
    "wof:placetype":"venue"
},
  "geometry": {"coordinates":[-118.151175,34.110015],"type":"Point"}
}