{
  "type": "Feature",
  "properties": {
    "iso:country":"US",
    "sg:address":"1123 N Market Blvd",
    "sg:city":"Sacramento",
    "sg:classifiers":[
        {
            "category":"Professional",
            "subcategory":"Business Services",
            "type":"Services"
        }
    ],
    "sg:phone":"+1 916 928 7400",
    "sg:postcode":"95834",
    "sg:province":"CA",
    "sg:tags":[
        "messenger"
    ],
    "wof:name":"CFC Network",
    "wof:placetype":"venue"
},
  "geometry": {"coordinates":[-121.48460300000001,38.647268],"type":"Point"}
}