{
  "type": "Feature",
  "properties": {
    "iso:country":"US",
    "sg:address":"1421 N Harbor Blvd",
    "sg:city":"Santa Ana",
    "sg:classifiers":[
        {
            "category":"Retail",
            "subcategory":"Auto Repair",
            "type":"Services"
        }
    ],
    "sg:phone":"+1 714 554 1515",
    "sg:postcode":"92703",
    "sg:province":"CA",
    "sg:tags":[
        "automobile",
        "electric"
    ],
    "wof:name":"Auto Electric Rebuilder",
    "wof:placetype":"venue"
},
  "geometry": {"coordinates":[-117.92024600000001,33.758145],"type":"Point"}
}