{
  "type": "Feature",
  "properties": {
    "iso:country":"US",
    "sg:address":"6917 Lincoln Oaks Dr",
    "sg:city":"Fair Oaks",
    "sg:classifiers":[
        {
            "category":"Wholesale",
            "subcategory":"Electrical",
            "type":"Manufacturing & Wholesale Goods"
        }
    ],
    "sg:phone":"+1 916 961 9554",
    "sg:postcode":"95628",
    "sg:province":"CA",
    "sg:tags":[
        "intercommunication"
    ],
    "wof:name":"M Electronics",
    "wof:placetype":"venue"
},
  "geometry": {"coordinates":[-121.30151499999999,38.665834],"type":"Point"}
}