{
  "type": "Feature",
  "properties": {
    "addr:full":"1220 Parkridge Ave Norco CA 92860",
    "addr:housenumber":"1220",
    "addr:postcode":"92860",
    "addr:street":"Parkridge Ave",
    "iso:country":"US",
    "sg:address":"1220 Parkridge Ave",
    "sg:city":"Norco",
    "sg:classifiers":[
        {
            "category":"Education",
            "subcategory":"School",
            "type":"Public Place"
        }
    ],
    "sg:phone":"+1 951 736 3326",
    "sg:postcode":"92860",
    "sg:province":"CA",
    "wof:name":"Washington Elementary School",
    "wof:placetype":"venue"
},
  "geometry": {"coordinates":[-117.570123,33.900347],"type":"Point"}
}