{
  "type": "Feature",
  "properties": {
    "iso:country":"US",
    "sg:address":"636 E Valley St",
    "sg:city":"Coalinga",
    "sg:classifiers":[
        {
            "category":"Utilities",
            "subcategory":"Refuse",
            "type":"Services"
        }
    ],
    "sg:phone":"+1 559 935 3772",
    "sg:postcode":"93210",
    "sg:province":"CA",
    "sg:tags":[
        "operator",
        "local",
        "system",
        "trucking"
    ],
    "wof:name":"Du Cycle Inc",
    "wof:placetype":"venue"
},
  "geometry": {"coordinates":[-120.35063,36.135641],"type":"Point"}
}