{
  "type": "Feature",
  "properties": {
    "addr:full":"9470 W Heaney Cir Santee CA 92071",
    "addr:housenumber":"9470",
    "addr:postcode":"92071",
    "addr:street":"W Heaney Cir",
    "iso:country":"US",
    "sg:address":"9470 W Heaney Cir",
    "sg:city":"Santee",
    "sg:classifiers":[
        {
            "category":"Autos & Motor Vehicles",
            "subcategory":"Auto Supplies",
            "type":"Retail Goods"
        }
    ],
    "sg:phone":"+1 619 449 8670",
    "sg:postcode":"92071",
    "sg:province":"CA",
    "wof:name":"Bug Patch",
    "wof:placetype":"venue"
},
  "geometry": {"coordinates":[-117.002379,32.849158],"type":"Point"}
}