{
  "type": "Feature",
  "properties": {
    "addr:full":"777 Cuesta Drive Suite 140 Mountain View CA 94040",
    "addr:housenumber":"777",
    "addr:postcode":"94040",
    "addr:street":"Cuesta Drive Suite 140",
    "iso:country":"US",
    "sg:address":"777 Cuesta Drive Suite 140",
    "sg:city":"Mountain View",
    "sg:classifiers":[
        {
            "category":"Health Services",
            "subcategory":"Dentist",
            "type":"Services"
        }
    ],
    "sg:phone":"+1 650 254 1596",
    "sg:postcode":"94040",
    "sg:province":"CA",
    "wof:name":"Benyammi Fella DDS Inc",
    "wof:placetype":"venue"
},
  "geometry": {"coordinates":[-122.086197,37.373688],"type":"Point"}
}