{
  "type": "Feature",
  "properties": {
    "addr:full":"1600 McHenry Ave Modesto CA 95350",
    "addr:housenumber":"1600",
    "addr:postcode":"ca 95350",
    "addr:street":"Mchenry Ave",
    "iso:country":"US",
    "sg:address":"1600 McHenry Ave",
    "sg:city":"Modesto",
    "sg:classifiers":[
        {
            "category":"Shopping",
            "subcategory":"Mobile Phones",
            "type":"Retail Goods"
        }
    ],
    "sg:phone":"+1 209 557 9725",
    "sg:postcode":"95350",
    "sg:province":"CA",
    "sg:website":"www.bellsouth.com",
    "wof:name":"AT&T",
    "wof:placetype":"venue"
},
  "geometry": {"coordinates":[-120.99380600000001,37.667291],"type":"Point"}
}