{
  "type": "Feature",
  "properties": {
    "iso:country":"US",
    "sg:address":"12442 Brookhurst St",
    "sg:city":"Garden Grove",
    "sg:classifiers":[
        {
            "category":"Arts & Performance",
            "subcategory":"Arts Center",
            "type":"Entertainment"
        },
        {
            "category":"Shopping",
            "type":"Retail Goods"
        }
    ],
    "sg:phone":"+1 714 786 5561",
    "sg:postcode":"92840",
    "sg:province":"CA",
    "wof:name":"Sheet Music Mart",
    "wof:placetype":"venue"
},
  "geometry": {"coordinates":[-117.95845300000001,33.781208],"type":"Point"}
}