{
  "type": "Feature",
  "properties": {
    "iso:country":"US",
    "sg:address":"233 Harter Ave",
    "sg:city":"Woodland",
    "sg:classifiers":[
        {
            "category":"Wholesale",
            "subcategory":"Electrical",
            "type":"Manufacturing & Wholesale Goods"
        }
    ],
    "sg:phone":"+1 530 662 1777",
    "sg:postcode":"95776",
    "sg:province":"CA",
    "sg:tags":[
        "fire",
        "equipment",
        "protection"
    ],
    "wof:name":"Pacific Fire Safety",
    "wof:placetype":"venue"
},
  "geometry": {"coordinates":[-121.760679,38.68889],"type":"Point"}
}