{
  "type": "Feature",
  "properties": {
    "addr:full":"1761 Devonshire Dr Benicia CA 94510",
    "addr:housenumber":"1761",
    "addr:postcode":"94510",
    "addr:street":"Devonshire Dr",
    "iso:country":"US",
    "sg:address":"1761 Devonshire Dr",
    "sg:city":"Benicia",
    "sg:classifiers":[
        {
            "category":"Manufacturing",
            "subcategory":"Watercraft",
            "type":"Manufacturing & Wholesale Goods"
        }
    ],
    "sg:phone":"+1 707 745 0197",
    "sg:postcode":"94510",
    "sg:province":"CA",
    "wof:name":"Play N Hooky Sport Fishin",
    "wof:placetype":"venue"
},
  "geometry": {"coordinates":[-122.1799,38.071746],"type":"Point"}
}