{
  "type": "Feature",
  "properties": {
    "iso:country":"US",
    "sg:address":"324 E Haley St",
    "sg:city":"Santa Barbara",
    "sg:classifiers":[
        {
            "category":"Retail",
            "subcategory":"Auto Repair",
            "type":"Services"
        }
    ],
    "sg:phone":"+1 805 564 1033",
    "sg:postcode":"93101",
    "sg:province":"CA",
    "sg:tags":[
        "muffler",
        "exhaust",
        "system"
    ],
    "wof:name":"Higgins Muffler & Brake",
    "wof:placetype":"venue"
},
  "geometry": {"coordinates":[-119.690952,34.420965],"type":"Point"}
}