{
  "type": "Feature",
  "properties": {
    "iso:country":"US",
    "sg:address":"201 Main St",
    "sg:city":"Suisun City",
    "sg:classifiers":[
        {
            "category":"Shopping",
            "subcategory":"Bicycles & Sporting Goods",
            "type":"Retail Goods"
        }
    ],
    "sg:phone":"+1 707 425 5518",
    "sg:postcode":"94585",
    "sg:province":"CA",
    "sg:tags":[
        "bait",
        "fishing"
    ],
    "wof:name":"Virgil's Bait Shop & Ice House",
    "wof:placetype":"venue"
},
  "geometry": {"coordinates":[-122.040487,38.244165],"type":"Point"}
}