{
  "type": "Feature",
  "properties": {
    "iso:country":"US",
    "sg:address":"3910 Princeton Dr",
    "sg:city":"Santa Rosa",
    "sg:classifiers":[
        {
            "category":"Health Services",
            "subcategory":"Doctor",
            "type":"Services"
        }
    ],
    "sg:phone":"+1 707 546 9882",
    "sg:postcode":"95405",
    "sg:province":"CA",
    "sg:tags":[
        "dentist"
    ],
    "wof:name":"Lorraine Gock DDS",
    "wof:placetype":"venue"
},
  "geometry": {"coordinates":[-122.673417,38.443416],"type":"Point"}
}