{
  "type": "Feature",
  "properties": {
    "iso:country":"US",
    "sg:address":"3858 E Ventura Ave",
    "sg:city":"Fresno",
    "sg:classifiers":[
        {
            "category":"Restaurant",
            "type":"Food & Drink"
        }
    ],
    "sg:phone":"+1 559 266 4884",
    "sg:postcode":"93702",
    "sg:province":"CA",
    "wof:name":"Foster's Freeze",
    "wof:placetype":"venue"
},
  "geometry": {"coordinates":[-119.759655,36.735783],"type":"Point"}
}