{
  "type": "Feature",
  "properties": {
    "addr:full":"1709 Butters Rd Carlsbad CA 92008",
    "addr:housenumber":"1709",
    "addr:postcode":"92008",
    "addr:street":"Butters Rd",
    "iso:country":"US",
    "sg:address":"1709 Butters Rd",
    "sg:city":"Carlsbad",
    "sg:classifiers":[
        {
            "category":"Health Services",
            "subcategory":"Health Practitioner",
            "type":"Services"
        }
    ],
    "sg:phone":"+1 760 729 6939",
    "sg:postcode":"92008",
    "sg:province":"CA",
    "sg:tags":[
        "psychologist"
    ],
    "wof:name":"Devora Lockton",
    "wof:placetype":"venue"
},
  "geometry": {"coordinates":[-117.340237,33.173145],"type":"Point"}
}