{
  "type": "Feature",
  "properties": {
    "iso:country":"US",
    "sg:address":"624 Armstrong Way",
    "sg:city":"Oakdale",
    "sg:classifiers":[
        {
            "category":"Retail",
            "subcategory":"Auto Repair",
            "type":"Services"
        }
    ],
    "sg:phone":"+1 209 847 8252",
    "sg:postcode":"95361",
    "sg:province":"CA",
    "sg:tags":[
        "truck"
    ],
    "wof:name":"D Hooks & Sons",
    "wof:placetype":"venue"
},
  "geometry": {"coordinates":[-120.834211,37.753266],"type":"Point"}
}