{
  "type": "Feature",
  "properties": {
    "addr:full":"139 E Tulare Ave Tulare CA 93274",
    "addr:housenumber":"139",
    "addr:postcode":"93274",
    "addr:street":"E Tulare Ave",
    "iso:country":"US",
    "sg:address":"139 E Tulare Ave",
    "sg:city":"Tulare",
    "sg:classifiers":[
        {
            "category":"Wholesale",
            "subcategory":"Electrical",
            "type":"Manufacturing & Wholesale Goods"
        }
    ],
    "sg:phone":"+1 559 686 8635",
    "sg:postcode":"93274",
    "sg:province":"CA",
    "sg:tags":[
        "electronic"
    ],
    "wof:name":"Wrap N Sind Postal Service",
    "wof:placetype":"venue"
},
  "geometry": {"coordinates":[-119.34691100000001,36.207872],"type":"Point"}
}