{
  "type": "Feature",
  "properties": {
    "addr:full":"1270 Michigan Ave Beaumont CA 92223",
    "addr:housenumber":"1270",
    "addr:postcode":"92223",
    "addr:street":"Michigan Ave",
    "iso:country":"US",
    "sg:address":"1270 Michigan Ave",
    "sg:city":"Beaumont",
    "sg:classifiers":[
        {
            "category":"Personal",
            "type":"Services"
        }
    ],
    "sg:phone":"+1 951 769 5297",
    "sg:postcode":"92223",
    "sg:province":"CA",
    "sg:tags":[
        "towing"
    ],
    "sg:website":"www.kiddstowing.net",
    "wof:name":"Kidd's Towing Service",
    "wof:placetype":"venue"
},
  "geometry": {"coordinates":[-116.96850000000001,33.942987],"type":"Point"}
}