{
  "type": "Feature",
  "properties": {
    "iso:country":"US",
    "sg:address":"3902 Middlefield Rd",
    "sg:city":"Palo Alto",
    "sg:classifiers":[
        {
            "category":"Personal",
            "subcategory":"Beauty Salon",
            "type":"Services"
        }
    ],
    "sg:phone":"+1 650 493 2100",
    "sg:postcode":"94303",
    "sg:province":"CA",
    "wof:name":"Great Clips",
    "wof:placetype":"venue"
},
  "geometry": {"coordinates":[-122.108592,37.418757],"type":"Point"}
}