{
  "type": "Feature",
  "properties": {
    "addr:full":"521 Leucadia Village Ct Encinitas CA 92024",
    "addr:housenumber":"521",
    "addr:postcode":"92024",
    "addr:street":"Leucadia Village Ct",
    "iso:country":"US",
    "sg:address":"521 Leucadia Village Ct",
    "sg:city":"Encinitas",
    "sg:classifiers":[
        {
            "category":"Building & Trades",
            "subcategory":"Construction",
            "type":"Services"
        }
    ],
    "sg:phone":"+1 760 944 9121",
    "sg:postcode":"92024",
    "sg:province":"CA",
    "sg:tags":[
        "consultant"
    ],
    "wof:name":"Kallisti Group",
    "wof:placetype":"venue"
},
  "geometry": {"coordinates":[-117.298028,33.08102],"type":"Point"}
}