{
  "type": "Feature",
  "properties": {
    "addr:full":"215 Lemon Creek Dr Walnut CA 91789",
    "addr:housenumber":"215",
    "addr:postcode":"91789",
    "addr:street":"Lemon Creek Dr",
    "iso:country":"US",
    "sg:address":"215 Lemon Creek Dr",
    "sg:city":"Walnut",
    "sg:classifiers":[
        {
            "category":"Professional",
            "type":"Services"
        }
    ],
    "sg:phone":"+1 909 598 0027",
    "sg:postcode":"91789",
    "sg:province":"CA",
    "sg:tags":[
        "establishment"
    ],
    "wof:name":"Micro-50 Inc",
    "wof:placetype":"venue"
},
  "geometry": {"coordinates":[-117.862927,34.010455],"type":"Point"}
}