{
  "type": "Feature",
  "properties": {
    "iso:country":"US",
    "sg:address":"605 Standiford Ave",
    "sg:city":"Modesto",
    "sg:classifiers":[
        {
            "category":"Real Estate",
            "subcategory":"Real Estate Agent",
            "type":"Services"
        }
    ],
    "sg:phone":"+1 209 549 8300",
    "sg:postcode":"95350",
    "sg:province":"CA",
    "wof:name":"Century 21",
    "wof:placetype":"venue"
},
  "geometry": {"coordinates":[-121.000111,37.689175],"type":"Point"}
}