{
  "type": "Feature",
  "properties": {
    "addr:full":"339 Maitland Dr Alameda CA 94502",
    "addr:housenumber":"339",
    "addr:postcode":"94502",
    "addr:street":"Maitland Dr",
    "iso:country":"US",
    "sg:address":"339 Maitland Dr",
    "sg:city":"Alameda",
    "sg:classifiers":[
        {
            "category":"Professional",
            "subcategory":"Computer Services",
            "type":"Services"
        }
    ],
    "sg:phone":"+1 510 865 6276",
    "sg:postcode":"94502",
    "sg:province":"CA",
    "sg:tags":[
        "consultant",
        "designer"
    ],
    "wof:name":"Words & Figures",
    "wof:placetype":"venue"
},
  "geometry": {"coordinates":[-122.233082,37.732903],"type":"Point"}
}