{
  "type": "Feature",
  "properties": {
    "addr:full":"25366 Crenshaw Blvd Torrance CA 90505",
    "addr:housenumber":"25366",
    "addr:postcode":"90505",
    "addr:street":"Crenshaw Blvd",
    "iso:country":"US",
    "sg:address":"25366 Crenshaw Blvd",
    "sg:city":"Torrance",
    "sg:classifiers":[
        {
            "category":"Restaurant",
            "type":"Food & Drink"
        }
    ],
    "sg:menulink":"http://www.allmenus.com/ca/torrance/7402-rubios/menu/",
    "sg:phone":"+1 310 891 1811",
    "sg:postcode":"90505",
    "sg:province":"CA",
    "sg:tags":[
        "seafood",
        "mexican",
        "american"
    ],
    "wof:name":"Rubio's",
    "wof:placetype":"venue"
},
  "geometry": {"coordinates":[-118.332784,33.792383],"type":"Point"}
}