{
  "type": "Feature",
  "properties": {
    "addr:full":"10266 Truckee Airport Rd Truckee CA 96161",
    "addr:housenumber":"10266",
    "addr:postcode":"96161",
    "addr:street":"Truckee Airport Rd",
    "iso:country":"US",
    "sg:address":"10266 Truckee Airport Rd",
    "sg:city":"Truckee",
    "sg:classifiers":[
        {
            "category":"Local Transit",
            "type":"Transportation"
        }
    ],
    "sg:phone":"+1 530 587 7451",
    "sg:postcode":"96161",
    "sg:province":"CA",
    "sg:tags":[
        "line"
    ],
    "wof:name":"Aztec Trasportation Svc",
    "wof:placetype":"venue"
},
  "geometry": {"coordinates":[-120.14148400000001,39.356432],"type":"Point"}
}