{
  "type": "Feature",
  "properties": {
    "iso:country":"US",
    "sg:address":"45554 Industrial Pl",
    "sg:city":"Fremont",
    "sg:classifiers":[
        {
            "category":"Manufacturing",
            "subcategory":"Tools & Machinery",
            "type":"Manufacturing & Wholesale Goods"
        }
    ],
    "sg:phone":"+1 510 657 9509",
    "sg:postcode":"94538",
    "sg:province":"CA",
    "sg:tags":[
        "machine",
        "shop"
    ],
    "wof:name":"American Tooling & Machining",
    "wof:placetype":"venue"
},
  "geometry": {"coordinates":[-121.950283,37.496605],"type":"Point"}
}