{
  "type": "Feature",
  "properties": {
    "iso:country":"US",
    "sg:address":"15143 Maricopa Rd",
    "sg:city":"Victorville",
    "sg:classifiers":[
        {
            "category":"Building & Trades",
            "subcategory":"Construction",
            "type":"Services"
        }
    ],
    "sg:phone":"+1 760 243 7393",
    "sg:postcode":"92392",
    "sg:province":"CA",
    "sg:tags":[
        "repair",
        "system",
        "contractor",
        "air conditioning"
    ],
    "sg:website":"http://www.yourheatingandair.com",
    "wof:name":"Air Repair",
    "wof:placetype":"venue"
},
  "geometry": {"coordinates":[-117.33340699999999,34.496031],"type":"Point"}
}