{
  "type": "Feature",
  "properties": {
    "addr:full":"1601 E Olympic Blvd Los Angeles CA 90021",
    "addr:housenumber":"1601",
    "addr:postcode":"90021",
    "addr:street":"E Olympic Blvd",
    "iso:country":"US",
    "sg:address":"1601 E Olympic Blvd",
    "sg:city":"Los Angeles",
    "sg:classifiers":[
        {
            "category":"Wholesale",
            "subcategory":"Fruits & Vegetables",
            "type":"Manufacturing & Wholesale Goods"
        }
    ],
    "sg:phone":"+1 213 384 4612",
    "sg:postcode":"90021",
    "sg:province":"CA",
    "wof:name":"Valle Los Niches LLC",
    "wof:placetype":"venue"
},
  "geometry": {"coordinates":[-118.24109799999999,34.029433],"type":"Point"}
}