{
  "type": "Feature",
  "properties": {
    "iso:country":"US",
    "sg:address":"420 Hindry Ave",
    "sg:city":"Inglewood",
    "sg:classifiers":[
        {
            "category":"Real Estate",
            "subcategory":"Real Estate Operator",
            "type":"Services"
        }
    ],
    "sg:phone":"+1 310 645 6077",
    "sg:postcode":"90301",
    "sg:province":"CA",
    "sg:tags":[
        "building",
        "nonresidential"
    ],
    "wof:name":"This Property",
    "wof:placetype":"venue"
},
  "geometry": {"coordinates":[-118.37348,33.956723],"type":"Point"}
}