{
  "type": "Feature",
  "properties": {
    "iso:country":"US",
    "sg:address":"818 Civic Center Drive",
    "sg:city":"Oceanside",
    "sg:classifiers":[
        {
            "category":"Health Services",
            "subcategory":"Dentist",
            "type":"Services"
        }
    ],
    "sg:phone":"+1 760 722 4765",
    "sg:postcode":"92054",
    "sg:province":"CA",
    "sg:website":"www.calcoastdental.com",
    "wof:name":"California Coast Dental Arts",
    "wof:placetype":"venue"
},
  "geometry": {"coordinates":[-117.378293,33.199436],"type":"Point"}
}