{
  "type": "Feature",
  "properties": {
    "iso:country":"US",
    "sg:address":"3378 Myers St",
    "sg:city":"Oroville",
    "sg:classifiers":[
        {
            "category":"Insurance",
            "subcategory":"Insurance Agent",
            "type":"Services"
        }
    ],
    "sg:phone":"+1 530 534 5075",
    "sg:postcode":"95966",
    "sg:province":"CA",
    "wof:name":"Leany Insurance Svc",
    "wof:placetype":"venue"
},
  "geometry": {"coordinates":[-121.548929,39.498122],"type":"Point"}
}