{
  "type": "Feature",
  "properties": {
    "iso:country":"US",
    "sg:address":"6425 S Van Ness Ave",
    "sg:city":"Los Angeles",
    "sg:classifiers":[
        {
            "category":"Building & Trades",
            "subcategory":"Cleaning & Sanitation",
            "type":"Services"
        }
    ],
    "sg:phone":"+1 323 758 8826",
    "sg:postcode":"90047",
    "sg:province":"CA",
    "sg:tags":[
        "janitor"
    ],
    "wof:name":"Molly's Highrise Cleaning Svc",
    "wof:placetype":"venue"
},
  "geometry": {"coordinates":[-118.317785,33.980305],"type":"Point"}
}