{
  "type": "Feature",
  "properties": {
    "addr:full":"5816 W 3rd St Los Angeles CA 90036",
    "addr:housenumber":"5816",
    "addr:postcode":"90036",
    "addr:street":"W 3Rd St",
    "iso:country":"US",
    "sg:address":"5816 W 3rd St",
    "sg:city":"Los Angeles",
    "sg:classifiers":[
        {
            "category":"Personal",
            "subcategory":"Beauty Salon",
            "type":"Services"
        }
    ],
    "sg:phone":"+1 323 936 0109",
    "sg:postcode":"90036",
    "sg:province":"CA",
    "sg:tags":[
        "manicuring"
    ],
    "wof:name":"Sandra Beauty Studio",
    "wof:placetype":"venue"
},
  "geometry": {"coordinates":[-118.34688199999999,34.069025],"type":"Point"}
}