{
  "type": "Feature",
  "properties": {
    "iso:country":"US",
    "sg:address":"2503 Seaman Ave",
    "sg:city":"South El Monte",
    "sg:classifiers":[
        {
            "category":"Autos & Motor Vehicles",
            "subcategory":"Auto Supplies",
            "type":"Retail Goods"
        }
    ],
    "sg:phone":"+1 626 453 0493",
    "sg:postcode":"91733",
    "sg:province":"CA",
    "sg:tags":[
        "tire"
    ],
    "wof:name":"K&E Tires Warehouse",
    "wof:placetype":"venue"
},
  "geometry": {"coordinates":[-118.053169,34.057466],"type":"Point"}
}