{
  "type": "Feature",
  "properties": {
    "addr:full":"111 N Sepulveda Blvd Manhattan Beach CA 90266",
    "addr:housenumber":"111",
    "addr:postcode":"90266",
    "addr:street":"N Sepulveda Blvd",
    "iso:country":"US",
    "sg:address":"111 N Sepulveda Blvd",
    "sg:city":"Manhattan Beach",
    "sg:classifiers":[
        {
            "category":"Professional",
            "subcategory":"Accounting & Tax Preparation",
            "type":"Services"
        }
    ],
    "sg:phone":"+1 310 372 4671",
    "sg:postcode":"90266",
    "sg:province":"CA",
    "sg:tags":[
        "return",
        "filing"
    ],
    "wof:name":"Robert H Reinhardt",
    "wof:placetype":"venue"
},
  "geometry": {"coordinates":[-118.396045,33.880887],"type":"Point"}
}