{
  "type": "Feature",
  "properties": {
    "iso:country":"US",
    "sg:address":"961 E Baseline St",
    "sg:city":"San Bernardino",
    "sg:classifiers":[
        {
            "category":"Autos & Motor Vehicles",
            "subcategory":"Automobile Sales",
            "type":"Retail Goods"
        }
    ],
    "sg:phone":"+1 909 885 6436",
    "sg:postcode":"92410",
    "sg:province":"CA",
    "sg:tags":[
        "car",
        "dealer"
    ],
    "wof:name":"Charlies Car Sales",
    "wof:placetype":"venue"
},
  "geometry": {"coordinates":[-117.266534,34.121251],"type":"Point"}
}