{
  "type": "Feature",
  "properties": {
    "addr:full":"451 Waller St San Francisco CA 94117",
    "addr:housenumber":"451",
    "addr:postcode":"94117",
    "addr:street":"Waller St",
    "iso:country":"US",
    "sg:address":"451 Waller St",
    "sg:city":"San Francisco",
    "sg:classifiers":[
        {
            "category":"Social Services",
            "type":"Services"
        }
    ],
    "sg:phone":"+1 415 558 8501",
    "sg:postcode":"94117",
    "sg:province":"CA",
    "sg:tags":[
        "organization",
        "welfare"
    ],
    "wof:name":"License Vocational Nurses",
    "wof:placetype":"venue"
},
  "geometry": {"coordinates":[-122.431229,37.770997],"type":"Point"}
}