{
  "type": "Feature",
  "properties": {
    "addr:full":"3921 E Bayshore Rd Palo Alto CA 94303",
    "addr:housenumber":"3921",
    "addr:postcode":"94303",
    "addr:street":"E Bayshore Rd",
    "iso:country":"US",
    "sg:address":"3921 E Bayshore Rd",
    "sg:city":"Palo Alto",
    "sg:classifiers":[
        {
            "category":"Organizations",
            "subcategory":"Community Association",
            "type":"Services"
        }
    ],
    "sg:phone":"+1 650 390 8411",
    "sg:postcode":"94303",
    "sg:province":"CA",
    "sg:tags":[
        "environmental",
        "org"
    ],
    "wof:name":"Sierra Club Loma Prieta Chptr",
    "wof:placetype":"venue"
},
  "geometry": {"coordinates":[-122.104482,37.431757],"type":"Point"}
}