{
  "type": "Feature",
  "properties": {
    "addr:full":"3748 S Grand Ave Los Angeles CA 90007",
    "addr:housenumber":"3748",
    "addr:postcode":"90007",
    "addr:street":"S Grand Ave",
    "iso:country":"US",
    "sg:address":"3748 S Grand Ave",
    "sg:city":"Los Angeles",
    "sg:classifiers":[
        {
            "category":"Wholesale",
            "subcategory":"Apparel",
            "type":"Manufacturing & Wholesale Goods"
        }
    ],
    "sg:phone":"+1 213 746 1912",
    "sg:postcode":"90007",
    "sg:province":"CA",
    "wof:name":"Parco USA",
    "wof:placetype":"venue"
},
  "geometry": {"coordinates":[-118.278959,34.015706],"type":"Point"}
}