{
  "type": "Feature",
  "properties": {
    "addr:full":"643 Burnell St Napa CA 94559",
    "addr:housenumber":"643",
    "addr:postcode":"94559",
    "addr:street":"Burnell St",
    "iso:country":"US",
    "sg:address":"643 Burnell St",
    "sg:city":"Napa",
    "sg:classifiers":[
        {
            "category":"Building & Trades",
            "subcategory":"Construction",
            "type":"Services"
        }
    ],
    "sg:phone":"+1 707 255 6211",
    "sg:postcode":"94559",
    "sg:province":"CA",
    "sg:tags":[
        "maker",
        "cabinet"
    ],
    "wof:name":"Gibson's Wood Products",
    "wof:placetype":"venue"
},
  "geometry": {"coordinates":[-122.279785,38.29686],"type":"Point"}
}