{
  "type": "Feature",
  "properties": {
    "iso:country":"US",
    "sg:address":"10825 Robinwood Ln",
    "sg:city":"Sonora",
    "sg:classifiers":[
        {
            "category":"Organizations",
            "subcategory":"Religious Organization",
            "type":"Services"
        }
    ],
    "sg:phone":"+1 209 536 0701",
    "sg:postcode":"95370",
    "sg:province":"CA",
    "sg:tags":[
        "church"
    ],
    "wof:name":"St Susanna Orthodox Church",
    "wof:placetype":"venue"
},
  "geometry": {"coordinates":[-120.408117,37.995162],"type":"Point"}
}