{
  "type": "Feature",
  "properties": {
    "addr:full":"6500 Broadway Oakland CA 94618",
    "addr:housenumber":"6500",
    "addr:postcode":"94618",
    "addr:street":"Broadway",
    "iso:country":"US",
    "sg:address":"6500 Broadway",
    "sg:city":"Oakland",
    "sg:classifiers":[
        {
            "category":"Recreation",
            "type":"Entertainment"
        }
    ],
    "sg:phone":"+1 510 418 8599",
    "sg:postcode":"94618",
    "sg:province":"CA",
    "sg:tags":[
        "active",
        "life"
    ],
    "sg:website":"www.babybootcamp.com",
    "wof:name":"Baby Boot Camp Oakland",
    "wof:placetype":"venue"
},
  "geometry": {"coordinates":[-122.233779,37.848207],"type":"Point"}
}