{
  "type": "Feature",
  "properties": {
    "addr:full":"414 11th St Ramona CA 92065",
    "addr:housenumber":"414",
    "addr:postcode":"92065",
    "addr:street":"11Th St",
    "iso:country":"US",
    "sg:address":"414 11th St",
    "sg:city":"Ramona",
    "sg:classifiers":[
        {
            "category":"Health Services",
            "subcategory":"Chiropractor",
            "type":"Services"
        }
    ],
    "sg:phone":"+1 760 789 3864",
    "sg:postcode":"92065",
    "sg:province":"CA",
    "wof:name":"Richard V Austin DC",
    "wof:placetype":"venue"
},
  "geometry": {"coordinates":[-116.86814699999999,33.038676],"type":"Point"}
}