{
  "type": "Feature",
  "properties": {
    "iso:country":"US",
    "sg:address":"1321 7th St",
    "sg:city":"Santa Monica",
    "sg:classifiers":[
        {
            "category":"Health Services",
            "subcategory":"Nursing And Care Facility",
            "type":"Services"
        }
    ],
    "sg:phone":"+1 310 395 7396",
    "sg:postcode":"90401",
    "sg:province":"CA",
    "sg:tags":[
        "adult"
    ],
    "wof:name":"Total Adult Day Health Care",
    "wof:placetype":"venue"
},
  "geometry": {"coordinates":[-118.492558,34.019031],"type":"Point"}
}