{
  "type": "Feature",
  "properties": {
    "iso:country":"US",
    "sg:address":"9832 Campo Rd",
    "sg:city":"Spring Valley",
    "sg:classifiers":[
        {
            "category":"Banks & Credit Unions",
            "subcategory":"Bank",
            "type":"Services"
        }
    ],
    "sg:phone":"+1 619 667 7700",
    "sg:postcode":"91977",
    "sg:province":"CA",
    "sg:website":"www.communityfirst.com",
    "wof:name":"Bank Of The West",
    "wof:placetype":"venue"
},
  "geometry": {"coordinates":[-116.98571699999999,32.748054],"type":"Point"}
}