{
  "type": "Feature",
  "properties": {
    "addr:full":"4242 Camino Del Rio N #18 San Diego CA 92108",
    "addr:housenumber":"4242",
    "addr:postcode":"92108",
    "addr:street":"Camino Del Rio N # 18",
    "iso:country":"US",
    "sg:address":"4242 Camino Del Rio N #18",
    "sg:city":"San Diego",
    "sg:classifiers":[
        {
            "category":"Personal",
            "subcategory":"Nail Salon",
            "type":"Services"
        }
    ],
    "sg:phone":"+1 619 528 8170",
    "sg:postcode":"92108",
    "sg:province":"CA",
    "wof:name":"Beauty Nails & Hair",
    "wof:placetype":"venue"
},
  "geometry": {"coordinates":[-117.103086,32.779463],"type":"Point"}
}