{
  "type": "Feature",
  "properties": {
    "iso:country":"US",
    "sg:address":"2340 E Pacific Coast Hwy",
    "sg:city":"Long Beach",
    "sg:classifiers":[
        {
            "category":"Food & Beverages",
            "subcategory":"Liquor & Beverages",
            "type":"Retail Goods"
        }
    ],
    "sg:phone":"+1 562 597 7033",
    "sg:postcode":"90804",
    "sg:province":"CA",
    "wof:name":"Eddies Liquor",
    "wof:placetype":"venue"
},
  "geometry": {"coordinates":[-118.163676,33.789781],"type":"Point"}
}