{
  "type": "Feature",
  "properties": {
    "iso:country":"US",
    "sg:address":"915 Saturn Blvd",
    "sg:city":"San Diego",
    "sg:classifiers":[
        {
            "category":"Organizations",
            "subcategory":"Religious Organization",
            "type":"Services"
        }
    ],
    "sg:phone":"+1 619 691 8752",
    "sg:postcode":"92154",
    "sg:province":"CA",
    "sg:tags":[
        "church"
    ],
    "wof:name":"First Landmark Baptist Church",
    "wof:placetype":"venue"
},
  "geometry": {"coordinates":[-117.092624,32.578753],"type":"Point"}
}