{
  "type": "Feature",
  "properties": {
    "iso:country":"US",
    "sg:address":"2313 Moore Ave",
    "sg:city":"Fullerton",
    "sg:classifiers":[
        {
            "category":"Wholesale",
            "subcategory":"Electrical",
            "type":"Manufacturing & Wholesale Goods"
        }
    ],
    "sg:phone":"+1 714 879 4192",
    "sg:postcode":"92833",
    "sg:province":"CA",
    "sg:tags":[
        "equipment"
    ],
    "wof:name":"Fullerton Moore",
    "wof:placetype":"venue"
},
  "geometry": {"coordinates":[-117.969863,33.875973],"type":"Point"}
}