{
  "type": "Feature",
  "properties": {
    "addr:full":"37473 Briarwood Dr Fremont CA 94536",
    "addr:housenumber":"37473",
    "addr:postcode":"94536",
    "addr:street":"Briarwood Dr",
    "iso:country":"US",
    "sg:address":"37473 Briarwood Dr",
    "sg:city":"Fremont",
    "sg:classifiers":[
        {
            "category":"Wholesale",
            "subcategory":"Machinery & Supplies",
            "type":"Manufacturing & Wholesale Goods"
        }
    ],
    "sg:phone":"+1 510 793 6398",
    "sg:postcode":"94536",
    "sg:province":"CA",
    "sg:tags":[
        "industrial",
        "equipment",
        "optical"
    ],
    "wof:name":"W & W Technologies",
    "wof:placetype":"venue"
},
  "geometry": {"coordinates":[-122.01400099999999,37.547844],"type":"Point"}
}