{
  "type": "Feature",
  "properties": {
    "addr:full":"950 W Pine St Santa Ana CA 92703",
    "addr:housenumber":"950",
    "addr:postcode":"92703",
    "addr:street":"W Pine St",
    "iso:country":"US",
    "sg:address":"950 W Pine St",
    "sg:city":"Santa Ana",
    "sg:classifiers":[
        {
            "category":"Building & Trades",
            "subcategory":"Landscaping Services",
            "type":"Services"
        }
    ],
    "sg:phone":"+1 714 558 8393",
    "sg:postcode":"92703",
    "sg:province":"CA",
    "wof:name":"Salvador Vargas Landscaping",
    "wof:placetype":"venue"
},
  "geometry": {"coordinates":[-117.878018,33.743495],"type":"Point"}
}