{
  "type": "Feature",
  "properties": {
    "iso:country":"US",
    "sg:address":"2190 Meridian Park Blvd",
    "sg:city":"Concord",
    "sg:classifiers":[
        {
            "category":"Home & Garden",
            "subcategory":"Building Materials",
            "type":"Retail Goods"
        }
    ],
    "sg:phone":"+1 925 691 1501",
    "sg:postcode":"94520",
    "sg:province":"CA",
    "sg:tags":[
        "windows"
    ],
    "sg:website":"www.thewindowoutlet.com",
    "wof:name":"Window Outlet Inc",
    "wof:placetype":"venue"
},
  "geometry": {"coordinates":[-122.055102,37.9746],"type":"Point"}
}