{
  "type": "Feature",
  "properties": {
    "addr:full":"4215 Geary Blvd San Francisco CA 94118",
    "addr:housenumber":"4215",
    "addr:postcode":"94118",
    "addr:street":"Geary Blvd",
    "iso:country":"US",
    "sg:address":"4215 Geary Blvd",
    "sg:city":"San Francisco",
    "sg:classifiers":[
        {
            "category":"Insurance",
            "subcategory":"Insurance Agent",
            "type":"Services"
        }
    ],
    "sg:phone":"+1 415 831 3090",
    "sg:postcode":"94118",
    "sg:province":"CA",
    "wof:name":"Allstate Insurance",
    "wof:placetype":"venue"
},
  "geometry": {"coordinates":[-122.465214,37.780828],"type":"Point"}
}