{
  "type": "Feature",
  "properties": {
    "addr:full":"2627 Taylor St San Francisco CA 94133",
    "addr:housenumber":"2627",
    "addr:postcode":"94133",
    "addr:street":"Taylor St",
    "iso:country":"US",
    "sg:address":"2627 Taylor St",
    "sg:city":"San Francisco",
    "sg:classifiers":[
        {
            "category":"Travel",
            "subcategory":"Travel Agent",
            "type":"Entertainment"
        }
    ],
    "sg:phone":"+1 415 353 5310",
    "sg:postcode":"94133",
    "sg:province":"CA",
    "sg:tags":[
        "tours",
        "promoter"
    ],
    "wof:name":"Super Site Seeing Tours",
    "wof:placetype":"venue"
},
  "geometry": {"coordinates":[-122.41565199999999,37.807017],"type":"Point"}
}