{
  "type": "Feature",
  "properties": {
    "iso:country":"US",
    "sg:address":"3550 Logan Avenue",
    "sg:city":"San Diego",
    "sg:classifiers":[
        {
            "category":"Education",
            "subcategory":"School",
            "type":"Public Place"
        }
    ],
    "sg:phone":"+1 619 525 7360",
    "sg:postcode":"92113",
    "sg:province":"CA",
    "sg:tags":[
        "high",
        "middle",
        "elementary"
    ],
    "wof:name":"San Diego Unified School District",
    "wof:placetype":"venue"
},
  "geometry": {"coordinates":[-117.11873799999999,32.697421],"type":"Point"}
}