{
  "type": "Feature",
  "properties": {
    "addr:full":"1422 Ward Rd Los Banos CA 93635",
    "addr:housenumber":"1422",
    "addr:postcode":"93635",
    "addr:street":"Ward Rd",
    "iso:country":"US",
    "sg:address":"1422 Ward Rd",
    "sg:city":"Los Banos",
    "sg:classifiers":[
        {
            "category":"Retail",
            "subcategory":"Auto Repair",
            "type":"Services"
        }
    ],
    "sg:phone":"+1 209 826 1605",
    "sg:postcode":"93635",
    "sg:province":"CA",
    "sg:tags":[
        "wrecker"
    ],
    "wof:name":"Romero's Towing",
    "wof:placetype":"venue"
},
  "geometry": {"coordinates":[-120.817718,37.056767],"type":"Point"}
}