{
  "type": "Feature",
  "properties": {
    "iso:country":"US",
    "sg:address":"4708 Winding Creek Ave",
    "sg:city":"Santa Rosa",
    "sg:classifiers":[
        {
            "category":"Arts & Performance",
            "subcategory":"Theater",
            "type":"Entertainment"
        }
    ],
    "sg:phone":"+1 707 537 2174",
    "sg:postcode":"95409",
    "sg:province":"CA",
    "sg:tags":[
        "music"
    ],
    "wof:name":"Sound Arts Studios",
    "wof:placetype":"venue"
},
  "geometry": {"coordinates":[-122.669479,38.464964],"type":"Point"}
}