{
  "type": "Feature",
  "properties": {
    "addr:full":"1115 Stockton St San Francisco CA 94133",
    "addr:housenumber":"1115",
    "addr:postcode":"94133",
    "addr:street":"Stockton St",
    "iso:country":"US",
    "sg:address":"1115 Stockton St",
    "sg:city":"San Francisco",
    "sg:classifiers":[
        {
            "category":"Taxi",
            "type":"Transportation"
        }
    ],
    "sg:phone":"+1 415 986 7220",
    "sg:postcode":"94133",
    "sg:province":"CA",
    "sg:tags":[
        "taxicab"
    ],
    "wof:name":"Pacific Cab Co",
    "wof:placetype":"venue"
},
  "geometry": {"coordinates":[-122.408485,37.796566],"type":"Point"}
}