{
  "type": "Feature",
  "properties": {
    "addr:full":"568 Howard St San Francisco CA 94105",
    "addr:housenumber":"568",
    "addr:postcode":"94105",
    "addr:street":"Howard St",
    "iso:country":"US",
    "sg:address":"568 Howard St",
    "sg:city":"San Francisco",
    "sg:classifiers":[
        {
            "category":"Wholesale",
            "subcategory":"Non-durable Goods",
            "type":"Manufacturing & Wholesale Goods"
        }
    ],
    "sg:phone":"+1 415 546 6069",
    "sg:postcode":"94105",
    "sg:province":"CA",
    "wof:name":"Tri-H Brothers Inv Dev I",
    "wof:placetype":"venue"
},
  "geometry": {"coordinates":[-122.39765199999999,37.787422],"type":"Point"}
}