{
  "type": "Feature",
  "properties": {
    "addr:full":"1921 N Gaffey St San Pedro CA 90731",
    "addr:housenumber":"1921",
    "addr:postcode":"90731",
    "addr:street":"N Gaffey St",
    "iso:country":"US",
    "sg:address":"1921 N Gaffey St",
    "sg:city":"San Pedro",
    "sg:classifiers":[
        {
            "category":"Health Services",
            "subcategory":"Health Practitioner",
            "type":"Services"
        }
    ],
    "sg:phone":"+1 310 833 0300",
    "sg:postcode":"90731",
    "sg:province":"CA",
    "sg:tags":[
        "therapy",
        "physical"
    ],
    "wof:name":"Balance Rehabilitation Inc",
    "wof:placetype":"venue"
},
  "geometry": {"coordinates":[-118.29332100000001,33.762493],"type":"Point"}
}