{
  "type": "Feature",
  "properties": {
    "iso:country":"US",
    "sg:address":"730 Lombard St",
    "sg:city":"San Francisco",
    "sg:classifiers":[
        {
            "category":"Building & Trades",
            "subcategory":"Construction",
            "type":"Services"
        }
    ],
    "sg:phone":"+1 415 441 8165",
    "sg:postcode":"94133",
    "sg:province":"CA",
    "sg:tags":[
        "general",
        "contractor"
    ],
    "wof:name":"Alac Dean Construction",
    "wof:placetype":"venue"
},
  "geometry": {"coordinates":[-122.413224,37.802894],"type":"Point"}
}