{
  "type": "Feature",
  "properties": {
    "iso:country":"US",
    "sg:address":"27537 Commerce Center Dr Ste 201",
    "sg:city":"Temecula",
    "sg:classifiers":[
        {
            "category":"Building & Trades",
            "subcategory":"Landscaping Services",
            "type":"Services"
        }
    ],
    "sg:phone":"+1 951 694 1416",
    "sg:postcode":"92590",
    "sg:province":"CA",
    "sg:tags":[
        "consultant",
        "lawn",
        "designer",
        "landscape",
        "contractor"
    ],
    "sg:website":"http://www.southwestlandscapeca.com/",
    "wof:name":"Southwest Landscape & Designs",
    "wof:placetype":"venue"
},
  "geometry": {"coordinates":[-117.16081699999999,33.511751],"type":"Point"}
}