{
  "type": "Feature",
  "properties": {
    "iso:country":"US",
    "sg:address":"2233 Brigden Rd",
    "sg:city":"Pasadena",
    "sg:classifiers":[
        {
            "category":"Professional",
            "subcategory":"Advertising",
            "type":"Services"
        }
    ],
    "sg:phone":"+1 626 797 1212",
    "sg:postcode":"91104",
    "sg:province":"CA",
    "sg:tags":[
        "counselor"
    ],
    "wof:name":"Dufford Marketing",
    "wof:placetype":"venue"
},
  "geometry": {"coordinates":[-118.103971,34.166094],"type":"Point"}
}