{
  "type": "Feature",
  "properties": {
    "iso:country":"US",
    "sg:address":"6129 Henrilee St",
    "sg:city":"Lakewood",
    "sg:classifiers":[
        {
            "category":"Manufacturing",
            "subcategory":"Tools & Machinery",
            "type":"Manufacturing & Wholesale Goods"
        },
        {
            "category":"Industrial Area",
            "type":"Public Place"
        }
    ],
    "sg:phone":"+1 562 425 0161",
    "sg:postcode":"90713",
    "sg:province":"CA",
    "sg:tags":[
        "repair",
        "equipment-repairing",
        "machinery-rebuild"
    ],
    "wof:name":"H S C Machine Werks",
    "wof:placetype":"venue"
},
  "geometry": {"coordinates":[-118.112719,33.840938],"type":"Point"}
}