{
  "type": "Feature",
  "properties": {
    "addr:full":"11932 Mayes Dr La Mirada CA 90638",
    "addr:housenumber":"11932",
    "addr:postcode":"90638",
    "addr:street":"Mayes Dr",
    "iso:country":"US",
    "sg:address":"11932 Mayes Dr",
    "sg:city":"La Mirada",
    "sg:classifiers":[
        {
            "category":"Building & Trades",
            "subcategory":"Electrical",
            "type":"Services"
        }
    ],
    "sg:phone":"+1 626 826 4548",
    "sg:postcode":"90638",
    "sg:province":"CA",
    "sg:tags":[
        "electrical",
        "contractor"
    ],
    "wof:name":"Marshall Albright",
    "wof:placetype":"venue"
},
  "geometry": {"coordinates":[-117.996527,33.922016],"type":"Point"}
}