{
  "type": "Feature",
  "properties": {
    "addr:full":"268 Bush St # 3631 San Francisco CA 94104",
    "addr:housenumber":"268",
    "addr:postcode":"94104",
    "addr:street":"Bush St # 3631",
    "iso:country":"US",
    "sg:address":"268 Bush St # 3631",
    "sg:city":"San Francisco",
    "sg:classifiers":[
        {
            "category":"Banks & Credit Unions",
            "subcategory":"Investment Brokerage",
            "type":"Services"
        },
        {
            "category":"Professional",
            "subcategory":"Lawyer & Legal Services",
            "type":"Services"
        }
    ],
    "sg:phone":"+1 415 845 7829",
    "sg:postcode":"94104",
    "sg:province":"CA",
    "sg:tags":[
        "investing",
        "litigation"
    ],
    "sg:website":"www.isacm.com",
    "wof:name":"Investment Strategy & Analysis, LLC",
    "wof:placetype":"venue"
},
  "geometry": {"coordinates":[-122.40194200000001,37.791068],"type":"Point"}
}