{
  "type": "Feature",
  "properties": {
    "iso:country":"US",
    "sg:address":"1600 Shattuck Ave Ste 112",
    "sg:city":"Berkeley",
    "sg:classifiers":[
        {
            "category":"Fast Food",
            "type":"Food & Drink"
        }
    ],
    "sg:phone":"+1 510 849 2827",
    "sg:postcode":"94709",
    "sg:province":"CA",
    "sg:tags":[
        "burger",
        "hot",
        "hamburger",
        "dog"
    ],
    "sg:website":"www.barneyshamburgers.com/",
    "wof:name":"Barney's Gourmet Hamburger",
    "wof:placetype":"venue"
},
  "geometry": {"coordinates":[-122.269211,37.878058],"type":"Point"}
}