{
  "type": "Feature",
  "properties": {
    "iso:country":"US",
    "sg:address":"1244 7th St",
    "sg:city":"Santa Monica",
    "sg:classifiers":[
        {
            "category":"Health Services",
            "subcategory":"Doctor",
            "type":"Services"
        }
    ],
    "sg:phone":"+1 310 393 9664",
    "sg:postcode":"90401",
    "sg:province":"CA",
    "sg:tags":[
        "dentist"
    ],
    "wof:name":"Bobak Morshed DDS",
    "wof:placetype":"venue"
},
  "geometry": {"coordinates":[-118.494523,34.02061],"type":"Point"}
}