{
  "type": "Feature",
  "properties": {
    "addr:full":"223 Bothun Rd Turlock CA 95380",
    "addr:housenumber":"223",
    "addr:postcode":"95380",
    "addr:street":"Bothun Rd",
    "iso:country":"US",
    "sg:address":"223 Bothun Rd",
    "sg:city":"Turlock",
    "sg:classifiers":[
        {
            "category":"Real Estate",
            "subcategory":"Real Estate Operator",
            "type":"Services"
        }
    ],
    "sg:phone":"+1 209 667 7850",
    "sg:postcode":"95380",
    "sg:province":"CA",
    "sg:tags":[
        "apartment"
    ],
    "wof:name":"Alpha-Bothun Manor",
    "wof:placetype":"venue"
},
  "geometry": {"coordinates":[-120.831868,37.491506],"type":"Point"}
}