{
  "type": "Feature",
  "properties": {
    "iso:country":"US",
    "sg:address":"625 Bayshore Blvd",
    "sg:city":"San Francisco",
    "sg:classifiers":[
        {
            "category":"Building & Trades",
            "subcategory":"Plumbing",
            "type":"Services"
        },
        {
            "category":"Home & Garden",
            "subcategory":"Home Furnishings",
            "type":"Retail Goods"
        },
        {
            "category":"Home & Garden",
            "subcategory":"Hardware",
            "type":"Retail Goods"
        }
    ],
    "sg:phone":"+1 415 467 8563",
    "sg:postcode":"94124",
    "sg:province":"CA",
    "sg:tags":[
        "kitchen",
        "store",
        "bath"
    ],
    "sg:website":"www.besttilesf.com/",
    "wof:name":"Best Tile",
    "wof:placetype":"venue"
},
  "geometry": {"coordinates":[-122.40624099999999,37.736976],"type":"Point"}
}