{
  "type": "Feature",
  "properties": {
    "iso:country":"US",
    "sg:address":"708 S Industrial Dr",
    "sg:city":"Yuba City",
    "sg:classifiers":[
        {
            "category":"Manufacturing",
            "subcategory":"Tools & Machinery",
            "type":"Manufacturing & Wholesale Goods"
        }
    ],
    "sg:phone":"+1 530 673 6318",
    "sg:postcode":"95993",
    "sg:province":"CA",
    "sg:tags":[
        "equipment",
        "material",
        "handling"
    ],
    "sg:website":"www.escalera.com",
    "wof:name":"Escalera Inc",
    "wof:placetype":"venue"
},
  "geometry": {"coordinates":[-121.674603,39.137969],"type":"Point"}
}