{
  "type": "Feature",
  "properties": {
    "addr:full":"23622 Calabasas Rd Calabasas CA 91302",
    "addr:housenumber":"23622",
    "addr:postcode":"91302",
    "addr:street":"Calabasas Rd",
    "iso:country":"US",
    "sg:address":"23622 Calabasas Rd",
    "sg:city":"Calabasas",
    "sg:classifiers":[
        {
            "category":"Professional",
            "subcategory":"Art Services",
            "type":"Services"
        }
    ],
    "sg:phone":"+1 818 222 4216",
    "sg:postcode":"91302",
    "sg:province":"CA",
    "sg:tags":[
        "graphic",
        "designer"
    ],
    "sg:website":"www.multivisiondesign.com",
    "wof:name":"Multi Vision Design",
    "wof:placetype":"venue"
},
  "geometry": {"coordinates":[-118.643176,34.155701],"type":"Point"}
}