{
  "type": "Feature",
  "properties": {
    "addr:full":"8477 Telegraph Rd Pico Rivera CA 90660",
    "addr:housenumber":"8477",
    "addr:postcode":"90660",
    "addr:street":"Telegraph Rd",
    "iso:country":"US",
    "sg:address":"8477 Telegraph Rd",
    "sg:city":"Pico Rivera",
    "sg:classifiers":[
        {
            "category":"Travel",
            "subcategory":"Hotels & Motels",
            "type":"Entertainment"
        }
    ],
    "sg:phone":"+1 562 869 9588",
    "sg:postcode":"90660",
    "sg:province":"CA",
    "wof:name":"Paco Hotel",
    "wof:placetype":"venue"
},
  "geometry": {"coordinates":[-118.111,33.962399],"type":"Point"}
}