{
  "type": "Feature",
  "properties": {
    "addr:full":"1501 Clement Street San Francisco CA 94118",
    "addr:housenumber":"1501",
    "addr:postcode":"94118",
    "addr:street":"Clement Street",
    "iso:country":"US",
    "sg:address":"1501 Clement Street",
    "sg:city":"San Francisco",
    "sg:classifiers":[
        {
            "category":"Professional",
            "subcategory":"Lawyer & Legal Services",
            "type":"Services"
        }
    ],
    "sg:phone":"+1 415 752 9937",
    "sg:postcode":"94118",
    "sg:province":"CA",
    "wof:name":"Law Offices of Howard Eric Specter",
    "wof:placetype":"venue"
},
  "geometry": {"coordinates":[-122.475245,37.782441],"type":"Point"}
}