{
  "type": "Feature",
  "properties": {
    "addr:full":"145 Valle Vista Ave Vallejo CA 94590",
    "addr:housenumber":"145",
    "addr:postcode":"94590",
    "addr:street":"Valle Vista Ave",
    "iso:country":"US",
    "sg:address":"145 Valle Vista Ave",
    "sg:city":"Vallejo",
    "sg:classifiers":[
        {
            "category":"Education",
            "subcategory":"Dance Studio",
            "type":"Public Place"
        }
    ],
    "sg:phone":"+1 707 554 4403",
    "sg:postcode":"94590",
    "sg:province":"CA",
    "sg:tags":[
        "instruction",
        "dancing"
    ],
    "wof:name":"Dance Shop",
    "wof:placetype":"venue"
},
  "geometry": {"coordinates":[-122.253598,38.119756],"type":"Point"}
}