{
  "type": "Feature",
  "properties": {
    "addr:full":"401 Old San Jose Road Soquel CA 95073",
    "addr:housenumber":"401",
    "addr:postcode":"95073",
    "addr:street":"Old San Jose Road",
    "iso:country":"US",
    "sg:address":"401 Old San Jose Road",
    "sg:city":"Soquel",
    "sg:classifiers":[
        {
            "category":"Education",
            "subcategory":"School",
            "type":"Public Place"
        }
    ],
    "sg:phone":"+1 831 429 3909",
    "sg:postcode":"95073",
    "sg:province":"CA",
    "wof:name":"Santa Cruz City Schools",
    "wof:placetype":"venue"
},
  "geometry": {"coordinates":[-121.957094,36.990748],"type":"Point"}
}