{
  "type": "Feature",
  "properties": {
    "iso:country":"US",
    "sg:address":"18430 Brookhurst St",
    "sg:city":"Fountain Valley",
    "sg:classifiers":[
        {
            "category":"Banks & Credit Unions",
            "subcategory":"Financial Services",
            "type":"Services"
        }
    ],
    "sg:phone":"+1 714 968 3920",
    "sg:postcode":"92708",
    "sg:province":"CA",
    "sg:tags":[
        "broker",
        "mortgage"
    ],
    "wof:name":"Allstate Funding",
    "wof:placetype":"venue"
},
  "geometry": {"coordinates":[-117.953925,33.694872],"type":"Point"}
}