{
  "type": "Feature",
  "properties": {
    "iso:country":"US",
    "sg:address":"2301 Orchard Ave",
    "sg:city":"El Cajon",
    "sg:classifiers":[
        {
            "category":"Arts & Performance",
            "subcategory":"Theater",
            "type":"Entertainment"
        }
    ],
    "sg:phone":"+1 619 442 8583",
    "sg:postcode":"92019",
    "sg:province":"CA",
    "sg:tags":[
        "music"
    ],
    "sg:website":"www.sandiegosophisticats.com",
    "wof:name":"Sophisticats",
    "wof:placetype":"venue"
},
  "geometry": {"coordinates":[-116.898134,32.796193],"type":"Point"}
}