{
  "type": "Feature",
  "properties": {
    "iso:country":"US",
    "sg:address":"330 E Oberlin Rd",
    "sg:city":"Yreka",
    "sg:classifiers":[
        {
            "category":"Retail",
            "subcategory":"Auto Repair",
            "type":"Services"
        }
    ],
    "sg:phone":"+1 530 842 4454",
    "sg:postcode":"96097",
    "sg:province":"CA",
    "sg:tags":[
        "repairing",
        "automobile"
    ],
    "wof:name":"Dunn Automotive",
    "wof:placetype":"venue"
},
  "geometry": {"coordinates":[-122.634771,41.715718],"type":"Point"}
}