{
  "type": "Feature",
  "properties": {
    "iso:country":"US",
    "sg:address":"404 Sun Valley Mall",
    "sg:city":"Concord",
    "sg:classifiers":[
        {
            "category":"Restaurant",
            "type":"Food & Drink"
        }
    ],
    "sg:menulink":"http://www.allmenus.com/ca/central-contra-costa/8485-red-robin/menu/",
    "sg:phone":"+1 925 671 9315",
    "sg:postcode":"94520",
    "sg:province":"CA",
    "sg:tags":[
        "american"
    ],
    "wof:name":"Red Robin",
    "wof:placetype":"venue"
},
  "geometry": {"coordinates":[-122.06182699999999,37.9672],"type":"Point"}
}