{
  "type": "Feature",
  "properties": {
    "iso:country":"US",
    "sg:address":"70740 Hope Cir",
    "sg:city":"Rancho Mirage",
    "sg:classifiers":[
        {
            "category":"Wholesale",
            "subcategory":"Apparel",
            "type":"Manufacturing & Wholesale Goods"
        }
    ],
    "sg:phone":"+1 760 324 3213",
    "sg:postcode":"92270",
    "sg:province":"CA",
    "sg:tags":[
        "piece"
    ],
    "wof:name":"Dispensa Matic",
    "wof:placetype":"venue"
},
  "geometry": {"coordinates":[-116.42780999999999,33.780754],"type":"Point"}
}