{
  "type": "Feature",
  "properties": {
    "addr:full":"908 Jackson St Albany CA 94706",
    "addr:housenumber":"908",
    "addr:postcode":"94706",
    "addr:street":"Jackson St",
    "iso:country":"US",
    "sg:address":"908 Jackson St",
    "sg:city":"Albany",
    "sg:classifiers":[
        {
            "category":"Arts & Performance",
            "subcategory":"Music",
            "type":"Entertainment"
        }
    ],
    "sg:phone":"+1 510 388 9066",
    "sg:postcode":"94706",
    "sg:province":"CA",
    "sg:tags":[
        "musician"
    ],
    "wof:name":"Freelance Musician",
    "wof:placetype":"venue"
},
  "geometry": {"coordinates":[-122.301513,37.889626],"type":"Point"}
}