{
  "type": "Feature",
  "properties": {
    "iso:country":"US",
    "sg:address":"2901 Meadowlark Dr",
    "sg:city":"San Diego",
    "sg:classifiers":[
        {
            "category":"Government",
            "subcategory":"Jail",
            "type":"Public Place"
        }
    ],
    "sg:phone":"+1 858 694 4600",
    "sg:postcode":"92123",
    "sg:province":"CA",
    "sg:tags":[
        "correctional",
        "institution"
    ],
    "wof:name":"Probation Dept",
    "wof:placetype":"venue"
},
  "geometry": {"coordinates":[-117.154362,32.796113],"type":"Point"}
}