{
  "type": "Feature",
  "properties": {
    "addr:full":"2901 Meadowlark Dr San Diego CA 92123",
    "addr:housenumber":"2901",
    "addr:postcode":"92123",
    "addr:street":"Meadowlark Dr",
    "iso:country":"US",
    "sg:address":"2901 Meadowlark Dr",
    "sg:city":"San Diego",
    "sg:classifiers":[
        {
            "category":"Government",
            "subcategory":"Jail",
            "type":"Public Place"
        }
    ],
    "sg:phone":"+1 858 694 4600",
    "sg:postcode":"92123",
    "sg:province":"CA",
    "sg:tags":[
        "correctional",
        "institution"
    ],
    "wof:name":"Probation Dept",
    "wof:placetype":"venue"
},
  "geometry": {"coordinates":[-117.15436200000001,32.796113],"type":"Point"}
}