{
  "type": "Feature",
  "properties": {
    "iso:country":"US",
    "sg:address":"3225 N Harbor Dr San Diego Airport",
    "sg:city":"San Diego",
    "sg:classifiers":[
        {
            "category":"Bars & Pubs",
            "type":"Food & Drink"
        }
    ],
    "sg:postcode":"92103",
    "sg:province":"CA",
    "wof:name":"Karl Strauss Brewery",
    "wof:placetype":"venue"
},
  "geometry": {"coordinates":[-117.189656,32.733577],"type":"Point"}
}