{
  "type": "Feature",
  "properties": {
    "addr:full":"1106 Darlene Dr Santa Cruz CA 95062",
    "addr:housenumber":"1106",
    "addr:postcode":"95062",
    "addr:street":"Darlene Dr",
    "iso:country":"US",
    "sg:address":"1106 Darlene Dr",
    "sg:city":"Santa Cruz",
    "sg:classifiers":[
        {
            "category":"Social Services",
            "subcategory":"Adult Care",
            "type":"Services"
        }
    ],
    "sg:phone":"+1 831 476 2501",
    "sg:postcode":"95062",
    "sg:province":"CA",
    "sg:tags":[
        "home",
        "residential"
    ],
    "wof:name":"Flor's Guest Homes",
    "wof:placetype":"venue"
},
  "geometry": {"coordinates":[-121.977858,36.969917],"type":"Point"}
}