{
  "type": "Feature",
  "properties": {
    "addr:full":"3917 Lyman Rd Oakland CA 94602",
    "addr:housenumber":"3917",
    "addr:postcode":"94602",
    "addr:street":"Lyman Rd",
    "iso:country":"US",
    "sg:address":"3917 Lyman Rd",
    "sg:city":"Oakland",
    "sg:classifiers":[
        {
            "category":"Social Services",
            "subcategory":"Child Care",
            "type":"Services"
        },
        {
            "category":"Education",
            "subcategory":"Preschool",
            "type":"Public Place"
        }
    ],
    "sg:phone":"+1 510 531 3121",
    "sg:postcode":"94602",
    "sg:province":"CA",
    "wof:name":"Cottage In the Woods Pre-School",
    "wof:placetype":"venue"
},
  "geometry": {"coordinates":[-122.21399700000001,37.806599],"type":"Point"}
}