{
  "type": "Feature",
  "properties": {
    "addr:full":"160 N La Brea Ave Los Angeles CA 90036",
    "addr:housenumber":"160",
    "addr:postcode":"90036",
    "addr:street":"N La Brea Ave",
    "iso:country":"US",
    "sg:address":"160 N La Brea Ave",
    "sg:city":"Los Angeles",
    "sg:classifiers":[
        {
            "category":"Shopping",
            "subcategory":"Antiques",
            "type":"Retail Goods"
        }
    ],
    "sg:phone":"+1 323 931 0500",
    "sg:postcode":"90036",
    "sg:province":"CA",
    "wof:name":"East Meets West Antique Quilts & Americana",
    "wof:placetype":"venue"
},
  "geometry": {"coordinates":[-118.344002,34.0756],"type":"Point"}
}