{
  "type": "Feature",
  "properties": {
    "addr:full":"6801 Coldwater Canyon Ave North Hollywood CA 91605",
    "addr:housenumber":"6801",
    "addr:postcode":"91605",
    "addr:street":"Coldwater Canyon Ave",
    "iso:country":"US",
    "sg:address":"6801 Coldwater Canyon Ave",
    "sg:city":"North Hollywood",
    "sg:classifiers":[
        {
            "category":"Health Services",
            "subcategory":"Doctor",
            "type":"Services"
        }
    ],
    "sg:phone":"+1 818 765 6260",
    "sg:postcode":"91605",
    "sg:province":"CA",
    "wof:name":"Hollywood Liposculpture",
    "wof:placetype":"venue"
},
  "geometry": {"coordinates":[-118.413955,34.193941],"type":"Point"}
}