{
  "type": "Feature",
  "properties": {
    "addr:full":"1345 Silica Ave Ste A Sacramento CA 95815",
    "addr:housenumber":"1345",
    "addr:postcode":"95815",
    "addr:street":"Silica Ave Ste A",
    "iso:country":"US",
    "sg:address":"1345 Silica Ave Ste A",
    "sg:city":"Sacramento",
    "sg:classifiers":[
        {
            "category":"Building & Trades",
            "subcategory":"Construction",
            "type":"Services"
        }
    ],
    "sg:phone":"+1 916 925 2577",
    "sg:postcode":"95815",
    "sg:province":"CA",
    "sg:tags":[
        "contractor"
    ],
    "sg:website":"www.djkitchen.com",
    "wof:name":"D & J Kitchens & Baths, Inc.",
    "wof:placetype":"venue"
},
  "geometry": {"coordinates":[-121.43561,38.608668],"type":"Point"}
}