{
  "type": "Feature",
  "properties": {
    "iso:country":"US",
    "sg:address":"109 Daisy Ct",
    "sg:city":"Hercules",
    "sg:classifiers":[
        {
            "category":"Manufacturing",
            "subcategory":"Printing",
            "type":"Manufacturing & Wholesale Goods"
        }
    ],
    "sg:phone":"+1 510 245 3253",
    "sg:postcode":"94547",
    "sg:province":"CA",
    "sg:tags":[
        "lithographic",
        "commercial"
    ],
    "wof:name":"Williford Trace",
    "wof:placetype":"venue"
},
  "geometry": {"coordinates":[-122.255326,38.008021],"type":"Point"}
}