{
  "type": "Feature",
  "properties": {
    "iso:country":"US",
    "sg:address":"1601 Lone Oak Rd",
    "sg:city":"Brentwood",
    "sg:classifiers":[
        {
            "category":"Retail",
            "subcategory":"Animal Services",
            "type":"Services"
        }
    ],
    "sg:phone":"+1 925 240 1082",
    "sg:postcode":"94513",
    "sg:province":"CA",
    "sg:tags":[
        "re",
        "training",
        "dog",
        "contractor"
    ],
    "wof:name":"Lori Lee's Family Dog Training",
    "wof:placetype":"venue"
},
  "geometry": {"coordinates":[-121.70273899999999,37.949789],"type":"Point"}
}