{
  "type": "Feature",
  "properties": {
    "addr:full":"251 S Robertson Blvd #108 Beverly Hills CA 90211",
    "addr:housenumber":"251",
    "addr:postcode":"90211",
    "addr:street":"S Robertson Blvd # 108;Hills Ca",
    "iso:country":"US",
    "sg:address":"251 S Robertson Blvd #108",
    "sg:city":"Beverly Hills",
    "sg:classifiers":[
        {
            "category":"Shopping",
            "subcategory":"Beauty & Cosmetics",
            "type":"Retail Goods"
        },
        {
            "category":"Personal",
            "subcategory":"Hair Removal",
            "type":"Services"
        },
        {
            "category":"Personal",
            "subcategory":"Skin Care",
            "type":"Services"
        }
    ],
    "sg:phone":"+1 310 657 8081",
    "sg:postcode":"90211",
    "sg:province":"CA",
    "sg:tags":[
        "laser",
        "supply"
    ],
    "wof:name":"Marcelle's Skin Care Salon",
    "wof:placetype":"venue"
},
  "geometry": {"coordinates":[-118.38383399999999,34.063451],"type":"Point"}
}