{
  "type": "Feature",
  "properties": {
    "iso:country":"US",
    "sg:address":"3513 W 6th St",
    "sg:city":"Los Angeles",
    "sg:classifiers":[
        {
            "category":"Building & Trades",
            "subcategory":"Construction",
            "type":"Services"
        }
    ],
    "sg:phone":"+1 213 252 8500",
    "sg:postcode":"90020",
    "sg:province":"CA",
    "sg:tags":[
        "interior",
        "design"
    ],
    "wof:name":"Aqua Vitae Design",
    "wof:placetype":"venue"
},
  "geometry": {"coordinates":[-118.29843200000001,34.063589],"type":"Point"}
}