{
  "type": "Feature",
  "properties": {
    "addr:full":"1025 Chapala St Santa Barbara CA 93101",
    "addr:housenumber":"1025",
    "addr:postcode":"93101",
    "addr:street":"Chapala St",
    "iso:country":"US",
    "sg:address":"1025 Chapala St",
    "sg:city":"Santa Barbara",
    "sg:classifiers":[
        {
            "category":"Insurance",
            "subcategory":"Insurance Agent",
            "type":"Services"
        }
    ],
    "sg:phone":"+1 805 965 0071",
    "sg:postcode":"93101",
    "sg:province":"CA",
    "wof:name":"MFC & V Insurance",
    "wof:placetype":"venue"
},
  "geometry": {"coordinates":[-119.70409600000001,34.42105],"type":"Point"}
}