{
  "type": "Feature",
  "properties": {
    "iso:country":"US",
    "sg:address":"2055 Westminster Mall",
    "sg:city":"Westminster",
    "sg:classifiers":[
        {
            "category":"Fast Food",
            "type":"Food & Drink"
        }
    ],
    "sg:phone":"+1 714 891 9367",
    "sg:postcode":"92683",
    "sg:province":"CA",
    "sg:tags":[
        "burger"
    ],
    "sg:website":"www.wendys.com",
    "wof:name":"Wendy's",
    "wof:placetype":"venue"
},
  "geometry": {"coordinates":[-118.009174,33.747561],"type":"Point"}
}