{
  "type": "Feature",
  "properties": {
    "addr:full":"8811 Hollywood Blvd West Hollywood CA 90069",
    "addr:housenumber":"8811",
    "addr:postcode":"90069",
    "addr:street":"Hollywood Blvd",
    "iso:country":"US",
    "sg:address":"8811 Hollywood Blvd",
    "sg:city":"West Hollywood",
    "sg:classifiers":[
        {
            "category":"Professional",
            "subcategory":"Business Services",
            "type":"Services"
        }
    ],
    "sg:phone":"+1 310 657 6750",
    "sg:postcode":"90069",
    "sg:province":"CA",
    "sg:tags":[
        "recording",
        "studio"
    ],
    "sg:website":"www.larrabeestudios.com",
    "wof:name":"Larrabee Sound Studios",
    "wof:placetype":"venue"
},
  "geometry": {"coordinates":[-118.379492,34.101249],"type":"Point"}
}