{
  "type": "Feature",
  "properties": {
    "iso:country":"US",
    "sg:address":"8525 Gibbs Dr",
    "sg:city":"San Diego",
    "sg:classifiers":[
        {
            "category":"Government",
            "subcategory":"Court House",
            "type":"Public Place"
        }
    ],
    "sg:phone":"+1 858 974 5757",
    "sg:postcode":"92123",
    "sg:province":"CA",
    "sg:tags":[
        "county",
        "counsel"
    ],
    "wof:name":"San Diego Cnty Public Defender",
    "wof:placetype":"venue"
},
  "geometry": {"coordinates":[-117.140583,32.810399],"type":"Point"}
}