{
  "type": "Feature",
  "properties": {
    "addr:full":"3838 del Amo Blvd Torrance CA 90503",
    "addr:housenumber":"3838",
    "addr:postcode":"90503",
    "addr:street":"Del Amo Blvd",
    "iso:country":"US",
    "sg:address":"3838 del Amo Blvd",
    "sg:city":"Torrance",
    "sg:classifiers":[
        {
            "category":"Professional",
            "subcategory":"Engineering",
            "type":"Services"
        }
    ],
    "sg:phone":"+1 310 793 8880",
    "sg:postcode":"90503",
    "sg:province":"CA",
    "sg:tags":[
        "engineer"
    ],
    "sg:website":"www.timapower.com",
    "wof:name":"Tima Power Systems",
    "wof:placetype":"venue"
},
  "geometry": {"coordinates":[-118.35503,33.848542],"type":"Point"}
}