{
  "type": "Feature",
  "properties": {
    "addr:full":"911 K St Ste B Sacramento CA 95814",
    "addr:housenumber":"911",
    "addr:postcode":"95814",
    "addr:street":"K St Ste B",
    "iso:country":"US",
    "sg:address":"911 K St Ste B",
    "sg:city":"Sacramento",
    "sg:classifiers":[
        {
            "category":"Travel",
            "subcategory":"Hotels & Motels",
            "type":"Entertainment"
        }
    ],
    "sg:phone":"+1 916 442 8973",
    "sg:postcode":"95814",
    "sg:province":"CA",
    "sg:tags":[
        "lodging"
    ],
    "wof:name":"Sequoia Hotel",
    "wof:placetype":"venue"
},
  "geometry": {"coordinates":[-121.494691,38.579754],"type":"Point"}
}