{
  "type": "Feature",
  "properties": {
    "iso:country":"US",
    "sg:address":"4457 Alameda Dr",
    "sg:city":"Fremont",
    "sg:classifiers":[
        {
            "category":"Building & Trades",
            "subcategory":"Construction",
            "type":"Services"
        }
    ],
    "sg:phone":"+1 510 793 0962",
    "sg:postcode":"94536",
    "sg:province":"CA",
    "sg:tags":[
        "house"
    ],
    "wof:name":"Scott Dennis Enjaian Cnstr",
    "wof:placetype":"venue"
},
  "geometry": {"coordinates":[-122.013419,37.554052],"type":"Point"}
}