{
  "type": "Feature",
  "properties": {
    "addr:full":"10425 Enterprise Dr Redlands CA 92374",
    "addr:housenumber":"10425",
    "addr:postcode":"92374",
    "addr:street":"Enterprise Dr",
    "iso:country":"US",
    "sg:address":"10425 Enterprise Dr",
    "sg:city":"Redlands",
    "sg:classifiers":[
        {
            "category":"Recreation",
            "type":"Entertainment"
        }
    ],
    "sg:phone":"+1 909 796 7200",
    "sg:postcode":"92374",
    "sg:province":"CA",
    "sg:tags":[
        "range",
        "baseball",
        "batting"
    ],
    "wof:name":"Inland Empire Batting Cages",
    "wof:placetype":"venue"
},
  "geometry": {"coordinates":[-117.23765899999999,34.064776],"type":"Point"}
}