{
  "type": "Feature",
  "properties": {
    "iso:country":"US",
    "sg:address":"2017 Lazzini Ave",
    "sg:city":"Santa Rosa",
    "sg:classifiers":[
        {
            "category":"Building & Trades",
            "subcategory":"Construction",
            "type":"Services"
        }
    ],
    "sg:phone":"+1 707 525 8197",
    "sg:postcode":"95407",
    "sg:province":"CA",
    "sg:tags":[
        "legal"
    ],
    "wof:name":"Donna Becchetti",
    "wof:placetype":"venue"
},
  "geometry": {"coordinates":[-122.741041,38.421994],"type":"Point"}
}