{
  "type": "Feature",
  "properties": {
    "iso:country":"US",
    "sg:address":"1471 Silver Lake Blvd",
    "sg:city":"Los Angeles",
    "sg:classifiers":[
        {
            "category":"Shopping",
            "subcategory":"Musical Instruments",
            "type":"Retail Goods"
        }
    ],
    "sg:phone":"+1 323 666 1707",
    "sg:postcode":"90026",
    "sg:province":"CA",
    "sg:tags":[
        "repair",
        "equipment"
    ],
    "wof:name":"Wes Velkov",
    "wof:placetype":"venue"
},
  "geometry": {"coordinates":[-118.270448,34.086017],"type":"Point"}
}