{
  "type": "Feature",
  "properties": {
    "addr:full":"1811 Old Sonoma Rd Napa CA 94559",
    "addr:housenumber":"1811",
    "addr:postcode":"94559",
    "addr:street":"Old Sonoma Rd",
    "iso:country":"US",
    "sg:address":"1811 Old Sonoma Rd",
    "sg:city":"Napa",
    "sg:classifiers":[
        {
            "category":"Shopping",
            "subcategory":"Gifts & Souvenirs",
            "type":"Retail Goods"
        }
    ],
    "sg:phone":"+1 707 226 7652",
    "sg:postcode":"94559",
    "sg:province":"CA",
    "sg:tags":[
        "a",
        "specializing",
        "no",
        "operates",
        "as",
        "store"
    ],
    "wof:name":"Doc Of Rock",
    "wof:placetype":"venue"
},
  "geometry": {"coordinates":[-122.295446,38.287656],"type":"Point"}
}