{
  "type": "Feature",
  "properties": {
    "iso:country":"US",
    "sg:address":"27232 Arena Ln",
    "sg:city":"Mission Viejo",
    "sg:classifiers":[
        {
            "category":"Banks & Credit Unions",
            "subcategory":"Bank",
            "type":"Services"
        }
    ],
    "sg:phone":"+1 949 588 0852",
    "sg:postcode":"92691",
    "sg:province":"CA",
    "sg:tags":[
        "broker",
        "mortgage"
    ],
    "wof:name":"West Coast Mortgage Services",
    "wof:placetype":"venue"
},
  "geometry": {"coordinates":[-117.65637,33.611715],"type":"Point"}
}