{
  "type": "Feature",
  "properties": {
    "addr:full":"1248 Aslan Way Kingsburg CA 93631",
    "addr:housenumber":"1248",
    "addr:postcode":"93631",
    "addr:street":"Aslan Way",
    "iso:country":"US",
    "sg:address":"1248 Aslan Way",
    "sg:city":"Kingsburg",
    "sg:classifiers":[
        {
            "category":"Building & Trades",
            "subcategory":"Construction",
            "type":"Services"
        }
    ],
    "sg:phone":"+1 559 733 9788",
    "sg:postcode":"93631",
    "sg:province":"CA",
    "sg:tags":[
        "downspouts",
        "gutter"
    ],
    "wof:name":"Continous Roof Gutters",
    "wof:placetype":"venue"
},
  "geometry": {"coordinates":[-119.553962,36.526456],"type":"Point"}
}