{
  "type": "Feature",
  "properties": {
    "iso:country":"US",
    "sg:address":"2419 S Driftwood Pl",
    "sg:city":"Ontario",
    "sg:classifiers":[
        {
            "category":"Building & Trades",
            "subcategory":"Electrical",
            "type":"Services"
        }
    ],
    "sg:phone":"+1 909 947 7328",
    "sg:postcode":"91761",
    "sg:province":"CA",
    "sg:tags":[
        "electric",
        "contractor"
    ],
    "wof:name":"Nichols Electric",
    "wof:placetype":"venue"
},
  "geometry": {"coordinates":[-117.587172,34.029608],"type":"Point"}
}