{
  "type": "Feature",
  "properties": {
    "iso:country":"US",
    "sg:address":"12738 Colfax Hwy",
    "sg:city":"Grass Valley",
    "sg:classifiers":[
        {
            "category":"Food & Beverages",
            "subcategory":"Groceries & Convenience Stores",
            "type":"Retail Goods"
        }
    ],
    "sg:phone":"+1 530 273 6964",
    "sg:postcode":"95945",
    "sg:province":"CA",
    "sg:tags":[
        "grocer"
    ],
    "wof:name":"Fredd's Country Store",
    "wof:placetype":"venue"
},
  "geometry": {"coordinates":[-121.026661,39.198523],"type":"Point"}
}