{
  "type": "Feature",
  "properties": {
    "addr:full":"11481 Heacock St Moreno Valley CA 92557",
    "addr:housenumber":"11481",
    "addr:postcode":"92557",
    "addr:street":"Heacock St",
    "iso:country":"US",
    "sg:address":"11481 Heacock St",
    "sg:city":"Moreno Valley",
    "sg:classifiers":[
        {
            "category":"Health Services",
            "subcategory":"Doctor",
            "type":"Services"
        }
    ],
    "sg:phone":"+1 951 242 5470",
    "sg:postcode":"92557",
    "sg:province":"CA",
    "sg:tags":[
        "dentist"
    ],
    "wof:name":"Family Dentistry",
    "wof:placetype":"venue"
},
  "geometry": {"coordinates":[-117.243988,33.959503],"type":"Point"}
}