{
  "type": "Feature",
  "properties": {
    "iso:country":"US",
    "sg:address":"1541 Corporate Way",
    "sg:city":"Sacramento",
    "sg:classifiers":[
        {
            "category":"Real Estate",
            "subcategory":"Real Estate Services",
            "type":"Services"
        },
        {
            "category":"Real Estate",
            "subcategory":"Real Estate Agent",
            "type":"Services"
        }
    ],
    "sg:phone":"+1 916 391 0481",
    "sg:postcode":"95831",
    "sg:province":"CA",
    "sg:tags":[
        "buyer",
        "broker"
    ],
    "wof:name":"Kikumoto Real Estate",
    "wof:placetype":"venue"
},
  "geometry": {"coordinates":[-121.521604,38.492114],"type":"Point"}
}