{
  "type": "Feature",
  "properties": {
    "iso:country":"US",
    "sg:address":"995 Market Street",
    "sg:city":"San Francisco",
    "sg:classifiers":[
        {
            "category":"Professional",
            "subcategory":"Lawyer & Legal Services",
            "type":"Services"
        }
    ],
    "sg:phone":"+1 415 538 3333",
    "sg:postcode":"94103",
    "sg:province":"CA",
    "wof:name":"Legal Assistance To the Elderly",
    "wof:placetype":"venue"
},
  "geometry": {"coordinates":[-122.410099,37.782339],"type":"Point"}
}