{
  "type": "Feature",
  "properties": {
    "addr:full":"4850 Jackson St Riverside CA 92503",
    "addr:housenumber":"4850",
    "addr:postcode":"92503",
    "addr:street":"Jackson St",
    "iso:country":"US",
    "sg:address":"4850 Jackson St",
    "sg:city":"Riverside",
    "sg:classifiers":[
        {
            "category":"Retail",
            "subcategory":"Self-service Laundry",
            "type":"Services"
        }
    ],
    "sg:phone":"+1 951 352 1618",
    "sg:postcode":"92503",
    "sg:province":"CA",
    "wof:name":"Sudz Coin Laundry",
    "wof:placetype":"venue"
},
  "geometry": {"coordinates":[-117.45289,33.942091],"type":"Point"}
}