{
  "type": "Feature",
  "properties": {
    "addr:full":"8083 Lexus Way Sacramento CA 95828",
    "addr:housenumber":"8083",
    "addr:postcode":"95828",
    "addr:street":"Lexus Way",
    "iso:country":"US",
    "sg:address":"8083 Lexus Way",
    "sg:city":"Sacramento",
    "sg:classifiers":[
        {
            "category":"Freight",
            "type":"Transportation"
        }
    ],
    "sg:phone":"+1 916 689 9025",
    "sg:postcode":"95828",
    "sg:province":"CA",
    "sg:tags":[
        "trucking"
    ],
    "wof:name":"R & R Trucking",
    "wof:placetype":"venue"
},
  "geometry": {"coordinates":[-121.40055,38.464212],"type":"Point"}
}