{
  "type": "Feature",
  "properties": {
    "addr:full":"1341 Old County Road Belmont CA 94002",
    "addr:housenumber":"1341",
    "addr:postcode":"94002",
    "addr:street":"Old County Road",
    "iso:country":"US",
    "sg:address":"1341 Old County Road",
    "sg:city":"Belmont",
    "sg:classifiers":[
        {
            "category":"Home & Garden",
            "subcategory":"Carpets & Floor Coverings",
            "type":"Retail Goods"
        }
    ],
    "sg:phone":"+1 650 593 3700",
    "sg:postcode":"94002",
    "sg:province":"CA",
    "sg:tags":[
        "flooring"
    ],
    "sg:website":"www.slaterfloors.com",
    "wof:name":"Slater Floors",
    "wof:placetype":"venue"
},
  "geometry": {"coordinates":[-122.271828,37.518241],"type":"Point"}
}