{
  "type": "Feature",
  "properties": {
    "addr:full":"3174 Luyung Dr Rancho Cordova CA 95742",
    "addr:housenumber":"3174",
    "addr:postcode":"95742",
    "addr:street":"Luyung Dr",
    "iso:country":"US",
    "sg:address":"3174 Luyung Dr",
    "sg:city":"Rancho Cordova",
    "sg:classifiers":[
        {
            "category":"Farming",
            "subcategory":"Farm & Veterinary Services",
            "type":"Manufacturing & Wholesale Goods"
        }
    ],
    "sg:phone":"+1 916 861 0504",
    "sg:postcode":"95742",
    "sg:province":"CA",
    "sg:tags":[
        "control",
        "weed"
    ],
    "wof:name":"A Plus Green Thumb Pro Turf",
    "wof:placetype":"venue"
},
  "geometry": {"coordinates":[-121.255698,38.585499],"type":"Point"}
}