{
  "type": "Feature",
  "properties": {
    "addr:full":"11043 Balboa Blvd Granada Hills CA 91344",
    "addr:housenumber":"11043",
    "addr:postcode":"91344",
    "addr:street":"Balboa Blvd",
    "iso:country":"US",
    "sg:address":"11043 Balboa Blvd",
    "sg:city":"Granada Hills",
    "sg:classifiers":[
        {
            "category":"Retail",
            "subcategory":"Laundry & Dry Cleaning",
            "type":"Services"
        }
    ],
    "sg:phone":"+1 818 360 4197",
    "sg:postcode":"91344",
    "sg:province":"CA",
    "sg:tags":[
        "cleaners"
    ],
    "wof:name":"Quality Cleaners",
    "wof:placetype":"venue"
},
  "geometry": {"coordinates":[-118.502296,34.26944],"type":"Point"}
}