{
  "type": "Feature",
  "properties": {
    "iso:country":"US",
    "sg:address":"400 N Tustin Ave",
    "sg:city":"Santa Ana",
    "sg:classifiers":[
        {
            "category":"Professional",
            "type":"Services"
        }
    ],
    "sg:phone":"+1 714 542 3567",
    "sg:postcode":"92705",
    "sg:province":"CA",
    "sg:tags":[
        "establishment"
    ],
    "wof:name":"Desnoo & Desnoo",
    "wof:placetype":"venue"
},
  "geometry": {"coordinates":[-117.83416,33.74932],"type":"Point"}
}