{
  "type": "Feature",
  "properties": {
    "addr:full":"128 Russell Dr Walnut Creek CA 94598",
    "addr:housenumber":"128",
    "addr:postcode":"94598",
    "addr:street":"Russell Dr",
    "iso:country":"US",
    "sg:address":"128 Russell Dr",
    "sg:city":"Walnut Creek",
    "sg:classifiers":[
        {
            "category":"Communications",
            "subcategory":"Film & Video Production",
            "type":"Services"
        }
    ],
    "sg:phone":"+1 925 945 4900",
    "sg:postcode":"94598",
    "sg:province":"CA",
    "sg:tags":[
        "consultant",
        "audio"
    ],
    "wof:name":"Star Media Consultants",
    "wof:placetype":"venue"
},
  "geometry": {"coordinates":[-122.037302,37.901852],"type":"Point"}
}