{
  "type": "Feature",
  "properties": {
    "iso:country":"US",
    "sg:address":"1801 Old Sonoma Rd",
    "sg:city":"Napa",
    "sg:classifiers":[
        {
            "category":"Insurance",
            "subcategory":"Hazard Insurance",
            "type":"Services"
        }
    ],
    "sg:phone":"+1 707 224 9400",
    "sg:postcode":"94559",
    "sg:province":"CA",
    "sg:tags":[
        "bond"
    ],
    "wof:name":"Aldridge Bail Bonds",
    "wof:placetype":"venue"
},
  "geometry": {"coordinates":[-122.29554899999999,38.287731],"type":"Point"}
}