{
  "type": "Feature",
  "properties": {
    "addr:full":"1930 E Hatch Rd # A Modesto CA 95351",
    "addr:housenumber":"1930",
    "addr:postcode":"ca 95351",
    "addr:street":"E Hatch Rd # A",
    "iso:country":"US",
    "sg:address":"1930 E Hatch Rd # A",
    "sg:city":"Modesto",
    "sg:classifiers":[
        {
            "category":"Health Services",
            "subcategory":"Doctor",
            "type":"Services"
        }
    ],
    "sg:phone":"+1 209 531 0552",
    "sg:postcode":"95351",
    "sg:province":"CA",
    "sg:tags":[
        "medicine",
        "practice",
        "internal",
        "family"
    ],
    "wof:name":"Rai Meetinder MD",
    "wof:placetype":"venue"
},
  "geometry": {"coordinates":[-120.959,37.6091],"type":"Point"}
}