{
  "type": "Feature",
  "properties": {
    "iso:country":"US",
    "sg:address":"222 N Mountain Ave 110A",
    "sg:city":"Upland",
    "sg:classifiers":[
        {
            "category":"Banks & Credit Unions",
            "subcategory":"Financial Services",
            "type":"Services"
        }
    ],
    "sg:phone":"+1 909 608 1144",
    "sg:postcode":"91786",
    "sg:province":"CA",
    "sg:tags":[
        "financing"
    ],
    "wof:name":"United Providence Funding Inc",
    "wof:placetype":"venue"
},
  "geometry": {"coordinates":[-117.670091,34.096279],"type":"Point"}
}