{
  "type": "Feature",
  "properties": {
    "addr:full":"10815 Julius St Oakland CA 94605",
    "addr:housenumber":"10815",
    "addr:postcode":"94605",
    "addr:street":"Julius St",
    "iso:country":"US",
    "sg:address":"10815 Julius St",
    "sg:city":"Oakland",
    "sg:classifiers":[
        {
            "category":"Professional",
            "type":"Services"
        }
    ],
    "sg:phone":"+1 510 632 2606",
    "sg:postcode":"94605",
    "sg:province":"CA",
    "wof:name":"L Reece & Co",
    "wof:placetype":"venue"
},
  "geometry": {"coordinates":[-122.147092,37.741814],"type":"Point"}
}