{
  "type": "Feature",
  "properties": {
    "iso:country":"US",
    "sg:address":"39750 Old Stage Rd",
    "sg:city":"Gualala",
    "sg:classifiers":[
        {
            "category":"Health Services",
            "subcategory":"Chiropractor",
            "type":"Services"
        }
    ],
    "sg:phone":"+1 707 884 4805",
    "sg:postcode":"95445",
    "sg:province":"CA",
    "wof:name":"East West Healing Arts & Sci",
    "wof:placetype":"venue"
},
  "geometry": {"coordinates":[-123.51484600000001,38.780833],"type":"Point"}
}