{
  "type": "Feature",
  "properties": {
    "addr:full":"1050 W Olive Ave Fresno CA 93728",
    "addr:housenumber":"1050",
    "addr:postcode":"93728",
    "addr:street":"W Olive Ave",
    "iso:country":"US",
    "sg:address":"1050 W Olive Ave",
    "sg:city":"Fresno",
    "sg:classifiers":[
        {
            "category":"Shopping",
            "subcategory":"Clothing, Apparel, & Fashions",
            "type":"Retail Goods"
        }
    ],
    "sg:phone":"+1 559 264 5464",
    "sg:postcode":"93728",
    "sg:province":"CA",
    "sg:tags":[
        "clothing",
        "store"
    ],
    "wof:name":"King Solomon's Mine Imports",
    "wof:placetype":"venue"
},
  "geometry": {"coordinates":[-119.82436,36.757504],"type":"Point"}
}