{
  "type": "Feature",
  "properties": {
    "addr:full":"Ashby and Shattuck Berkeley CA 94705",
    "addr:postcode":"94705",
    "iso:country":"US",
    "sg:address":"Ashby and Shattuck",
    "sg:city":"Berkeley",
    "sg:classifiers":[
        {
            "category":"Education",
            "subcategory":"Special Training",
            "type":"Public Place"
        }
    ],
    "sg:postcode":"94705",
    "sg:province":"CA",
    "sg:tags":[
        "tutor",
        "private"
    ],
    "sg:website":"www.EastBayESL.com",
    "wof:name":"East Bay ESL",
    "wof:placetype":"venue"
},
  "geometry": {"coordinates":[-122.266497,37.855295],"type":"Point"}
}