{
  "type": "Feature",
  "properties": {
    "addr:full":"1140 W Mission Rd San Marcos CA 92069",
    "addr:housenumber":"1140",
    "addr:postcode":"92069",
    "addr:street":"W Mission Rd",
    "iso:country":"US",
    "sg:address":"1140 W Mission Rd",
    "sg:city":"San Marcos",
    "sg:classifiers":[
        {
            "category":"Education",
            "subcategory":"Junior College",
            "type":"Public Place"
        }
    ],
    "sg:phone":"+1 760 744 1150",
    "sg:postcode":"92069",
    "sg:province":"CA",
    "wof:name":"PALOMAR COMMUNITY COLLEGE",
    "wof:placetype":"venue"
},
  "geometry": {"coordinates":[-117.183919,33.146934],"type":"Point"}
}