{
  "type": "Feature",
  "properties": {
    "iso:country":"US",
    "sg:address":"20 School St",
    "sg:city":"Point Arena",
    "sg:classifiers":[
        {
            "category":"Education",
            "subcategory":"School",
            "type":"Public Place"
        }
    ],
    "sg:phone":"+1 707 882 2371",
    "sg:postcode":"95468",
    "sg:province":"CA",
    "wof:name":"Arena Union Elementary School",
    "wof:placetype":"venue"
},
  "geometry": {"coordinates":[-123.699411,38.913395],"type":"Point"}
}