{
  "type": "Feature",
  "properties": {
    "addr:full":"1179 Redmond Ave San Jose CA 95120",
    "addr:housenumber":"1179",
    "addr:postcode":"95120",
    "addr:street":"Redmond Ave",
    "iso:country":"US",
    "sg:address":"1179 Redmond Ave",
    "sg:city":"San Jose",
    "sg:classifiers":[
        {
            "category":"Food & Beverages",
            "subcategory":"Bakery",
            "type":"Retail Goods"
        }
    ],
    "sg:phone":"+1 408 268 4555",
    "sg:postcode":"95120",
    "sg:province":"CA",
    "sg:tags":[
        "dessert",
        "baker"
    ],
    "sg:website":"www.charliescheesecakeworks.com",
    "wof:name":"Charlie's Cheesecake Works",
    "wof:placetype":"venue"
},
  "geometry": {"coordinates":[-121.873001,37.229099],"type":"Point"}
}