{
  "type": "Feature",
  "properties": {
    "iso:country":"US",
    "sg:address":"3000 Alum Rock Avenue",
    "sg:city":"San Jose",
    "sg:classifiers":[
        {
            "category":"Home & Garden",
            "subcategory":"Garden Supply",
            "type":"Retail Goods"
        }
    ],
    "sg:phone":"+1 408 259 5470",
    "sg:postcode":"95127",
    "sg:province":"CA",
    "sg:tags":[
        "nursery",
        "gardening"
    ],
    "wof:name":"Orchard Supply Hardware",
    "wof:placetype":"venue"
},
  "geometry": {"coordinates":[-121.82953000000001,37.364886],"type":"Point"}
}