{
  "type": "Feature",
  "properties": {
    "iso:country":"US",
    "sg:address":"15204 Stagg St",
    "sg:city":"Van Nuys",
    "sg:classifiers":[
        {
            "category":"Manufacturing",
            "subcategory":"Pet Food",
            "type":"Manufacturing & Wholesale Goods"
        }
    ],
    "sg:phone":"+1 818 786 3618",
    "sg:postcode":"91406",
    "sg:province":"CA",
    "sg:tags":[
        "mfg"
    ],
    "wof:name":"Artemis Pet Food Co Inc",
    "wof:placetype":"venue"
},
  "geometry": {"coordinates":[-118.46478,34.211999],"type":"Point"}
}