{
  "type": "Feature",
  "properties": {
    "addr:full":"2468 Historic Decatur Rd San Diego CA 92106",
    "addr:housenumber":"2468",
    "addr:postcode":"92106",
    "addr:street":"Historic Decatur Rd",
    "iso:country":"US",
    "sg:address":"2468 Historic Decatur Rd",
    "sg:city":"San Diego",
    "sg:classifiers":[
        {
            "category":"Real Estate",
            "subcategory":"Real Estate Agent",
            "type":"Services"
        }
    ],
    "sg:phone":"+1 619 417 5234",
    "sg:postcode":"92106",
    "sg:province":"CA",
    "wof:name":"Liz Rincon- Ascent Real Estate",
    "wof:placetype":"venue"
},
  "geometry": {"coordinates":[-117.215301,32.736296],"type":"Point"}
}