{
  "type": "Feature",
  "properties": {
    "iso:country":"US",
    "sg:address":"306 Leveland Ln",
    "sg:city":"Modesto",
    "sg:classifiers":[
        {
            "category":"Insurance",
            "subcategory":"Insurance Agent",
            "type":"Services"
        }
    ],
    "sg:phone":"+1 209 575 4746",
    "sg:postcode":"95350",
    "sg:province":"CA",
    "wof:name":"Dadasovich Insurance Svc",
    "wof:placetype":"venue"
},
  "geometry": {"coordinates":[-120.997361,37.679063],"type":"Point"}
}