{
  "type": "Feature",
  "properties": {
    "addr:full":"930 Huber St Grover Beach CA 93433",
    "addr:housenumber":"930",
    "addr:postcode":"93433",
    "addr:street":"Huber St",
    "iso:country":"US",
    "sg:address":"930 Huber St",
    "sg:city":"Grover Beach",
    "sg:classifiers":[
        {
            "category":"Wholesale",
            "subcategory":"Hardware",
            "type":"Manufacturing & Wholesale Goods"
        }
    ],
    "sg:phone":"+1 805 489 4290",
    "sg:postcode":"93433",
    "sg:province":"CA",
    "sg:tags":[
        "nut",
        "bolt"
    ],
    "wof:name":"Coast Nut & Bolt",
    "wof:placetype":"venue"
},
  "geometry": {"coordinates":[-120.622376,35.112733],"type":"Point"}
}