{
  "type": "Feature",
  "properties": {
    "addr:full":"9308 Sawtooth Way San Diego CA 92129",
    "addr:housenumber":"9308",
    "addr:postcode":"92129",
    "addr:street":"Sawtooth Way",
    "iso:country":"US",
    "sg:address":"9308 Sawtooth Way",
    "sg:city":"San Diego",
    "sg:classifiers":[
        {
            "category":"Professional",
            "type":"Services"
        }
    ],
    "sg:phone":"+1 858 484 6289",
    "sg:postcode":"92129",
    "sg:province":"CA",
    "wof:name":"Young K Seo",
    "wof:placetype":"venue"
},
  "geometry": {"coordinates":[-117.125353,32.963335],"type":"Point"}
}