{
  "type": "Feature",
  "properties": {
    "iso:country":"US",
    "sg:address":"3542 E Cesar E Chavez Ave",
    "sg:city":"Los Angeles",
    "sg:classifiers":[
        {
            "category":"Personal",
            "subcategory":"Beauty Salon",
            "type":"Services"
        }
    ],
    "sg:phone":"+1 323 263 2303",
    "sg:postcode":"90063",
    "sg:province":"CA",
    "wof:name":"Luisa's Beauty Salon",
    "wof:placetype":"venue"
},
  "geometry": {"coordinates":[-118.187091,34.040448],"type":"Point"}
}