{
  "type": "Feature",
  "properties": {
    "iso:country":"US",
    "sg:address":"11900 W Olympic Blvd",
    "sg:city":"Los Angeles",
    "sg:classifiers":[
        {
            "category":"Real Estate",
            "subcategory":"Real Estate Agent",
            "type":"Services"
        }
    ],
    "sg:phone":"+1 310 477 3535",
    "sg:postcode":"90064",
    "sg:province":"CA",
    "wof:name":"Bud Petrick & Assoc",
    "wof:placetype":"venue"
},
  "geometry": {"coordinates":[-118.45261,34.032537],"type":"Point"}
}