{
  "type": "Feature",
  "properties": {
    "iso:country":"US",
    "sg:address":"5716 East 7th St., Ste. B-6",
    "sg:city":"Long Beach",
    "sg:classifiers":[
        {
            "category":"Fast Food",
            "type":"Food & Drink"
        },
        {
            "category":"Restaurant",
            "type":"Food & Drink"
        }
    ],
    "sg:phone":"+1 562 985 0483",
    "sg:postcode":"90803",
    "sg:province":"CA",
    "sg:tags":[
        "hawaiian"
    ],
    "sg:website":"www.hawaiianbarbecue.com/index.html",
    "wof:name":"L&L Hawaiian Barbecue",
    "wof:placetype":"venue"
},
  "geometry": {"coordinates":[-118.120272,33.775228],"type":"Point"}
}