{
  "type": "Feature",
  "properties": {
    "iso:country":"US",
    "sg:address":"312 N Russell Ave",
    "sg:city":"Santa Maria",
    "sg:classifiers":[
        {
            "category":"Retail",
            "subcategory":"Auto Repair",
            "type":"Services"
        }
    ],
    "sg:phone":"+1 805 922 8696",
    "sg:postcode":"93458",
    "sg:province":"CA",
    "sg:tags":[
        "repairing",
        "automobile"
    ],
    "wof:name":"Foster Engine Svc",
    "wof:placetype":"venue"
},
  "geometry": {"coordinates":[-120.451419,34.956016],"type":"Point"}
}