{
  "type": "Feature",
  "properties": {
    "addr:full":"2221 Kern St Fresno CA 93721",
    "addr:housenumber":"2221",
    "addr:postcode":"93721",
    "addr:street":"Kern St",
    "iso:country":"US",
    "sg:address":"2221 Kern St",
    "sg:city":"Fresno",
    "sg:classifiers":[
        {
            "category":"Government",
            "subcategory":"Court House",
            "type":"Public Place"
        }
    ],
    "sg:phone":"+1 559 488 3343",
    "sg:postcode":"93721",
    "sg:province":"CA",
    "sg:tags":[
        "voter",
        "registration"
    ],
    "wof:name":"County Clerk-Registar Voters",
    "wof:placetype":"venue"
},
  "geometry": {"coordinates":[-119.786224,36.734987],"type":"Point"}
}