{
  "type": "Feature",
  "properties": {
    "iso:country":"US",
    "sg:address":"879 Newport Center Dr",
    "sg:city":"Newport Beach",
    "sg:classifiers":[
        {
            "category":"Shopping",
            "subcategory":"Hobbies, Toys, & Games",
            "type":"Retail Goods"
        }
    ],
    "sg:phone":"+1 949 729 9800",
    "sg:postcode":"92660",
    "sg:province":"CA",
    "wof:name":"Toy Boat Toy Boat Toy Boat",
    "wof:placetype":"venue"
},
  "geometry": {"coordinates":[-117.87794,33.614158],"type":"Point"}
}