{
  "type": "Feature",
  "properties": {
    "addr:full":"2541 S Rodeo Gulch Rd Soquel CA 95073",
    "addr:housenumber":"2541",
    "addr:postcode":"95073",
    "addr:street":"S Rodeo Gulch Rd",
    "iso:country":"US",
    "sg:address":"2541 S Rodeo Gulch Rd",
    "sg:city":"Soquel",
    "sg:classifiers":[
        {
            "category":"Building & Trades",
            "subcategory":"Plumbing",
            "type":"Services"
        }
    ],
    "sg:phone":"+1 831 477 0845",
    "sg:postcode":"95073",
    "sg:province":"CA",
    "sg:tags":[
        "conditioning",
        "air",
        "system",
        "contractor"
    ],
    "wof:name":"Santa Cruz Mechanical",
    "wof:placetype":"venue"
},
  "geometry": {"coordinates":[-121.969593,36.983954],"type":"Point"}
}