{
  "type": "Feature",
  "properties": {
    "iso:country":"US",
    "sg:address":"33583 Vino Way",
    "sg:city":"Temecula",
    "sg:classifiers":[
        {
            "category":"Home & Garden",
            "subcategory":"Garden Supply",
            "type":"Retail Goods"
        }
    ],
    "sg:phone":"+1 951 694 5309",
    "sg:postcode":"92591",
    "sg:province":"CA",
    "sg:tags":[
        "center"
    ],
    "wof:name":"Wild Rose Farms",
    "wof:placetype":"venue"
},
  "geometry": {"coordinates":[-117.068147,33.541171],"type":"Point"}
}