{
  "type": "Feature",
  "properties": {
    "iso:country":"US",
    "sg:address":"3645 Wintun Dr",
    "sg:city":"Carmichael",
    "sg:classifiers":[
        {
            "category":"Manufacturing",
            "subcategory":"Food",
            "type":"Manufacturing & Wholesale Goods"
        }
    ],
    "sg:phone":"+1 916 876 0421",
    "sg:postcode":"95608",
    "sg:province":"CA",
    "sg:tags":[
        "product"
    ],
    "wof:name":"Amroot Inc",
    "wof:placetype":"venue"
},
  "geometry": {"coordinates":[-121.323078,38.630181],"type":"Point"}
}