{
  "type": "Feature",
  "properties": {
    "addr:full":"1429 N Hacienda Blvd La Puente CA 91744",
    "addr:housenumber":"1429",
    "addr:postcode":"91744",
    "addr:street":"N Hacienda Blvd",
    "iso:country":"US",
    "sg:address":"1429 N Hacienda Blvd",
    "sg:city":"La Puente",
    "sg:classifiers":[
        {
            "category":"Restaurant",
            "type":"Food & Drink"
        }
    ],
    "sg:phone":"+1 626 919 0889",
    "sg:postcode":"91744",
    "sg:province":"CA",
    "wof:name":"Q Home Chinese Food",
    "wof:placetype":"venue"
},
  "geometry": {"coordinates":[-117.948395,34.046526],"type":"Point"}
}