{
  "type": "Feature",
  "properties": {
    "iso:country":"US",
    "sg:address":"2615 West Ln",
    "sg:city":"Stockton",
    "sg:classifiers":[
        {
            "category":"Retail",
            "subcategory":"Auto Repair",
            "type":"Services"
        }
    ],
    "sg:phone":"+1 209 474 9465",
    "sg:postcode":"95205",
    "sg:province":"CA",
    "sg:tags":[
        "body",
        "painting",
        "repairing",
        "automobile"
    ],
    "sg:website":"http://www.fabianscollision.com",
    "wof:name":"Fabian's Collision Center",
    "wof:placetype":"venue"
},
  "geometry": {"coordinates":[-121.282004,37.979368],"type":"Point"}
}