{
  "type": "Feature",
  "properties": {
    "addr:full":"8539 W Sunset Blvd West Hollywood CA 90069",
    "addr:housenumber":"8539",
    "addr:postcode":"90069",
    "addr:street":"W Sunset Blvd",
    "iso:country":"US",
    "sg:address":"8539 W Sunset Blvd",
    "sg:city":"West Hollywood",
    "sg:classifiers":[
        {
            "category":"Restaurant",
            "type":"Food & Drink"
        }
    ],
    "sg:menulink":"http://www.allmenus.com/ca/los-angeles/102776-the-pita-pit/menu/",
    "sg:phone":"+1 310 657 7482",
    "sg:postcode":"90069",
    "sg:province":"CA",
    "sg:tags":[
        "salad",
        "soup",
        "eastern",
        "mediterranean",
        "middle",
        "american",
        "greek"
    ],
    "wof:name":"The Pita Pit",
    "wof:placetype":"venue"
},
  "geometry": {"coordinates":[-118.377917,34.093789],"type":"Point"}
}