{
  "type": "Feature",
  "properties": {
    "addr:full":"425 E Foothill Blvd Azusa CA 91702",
    "addr:housenumber":"425",
    "addr:postcode":"91702",
    "addr:street":"E Foothill Blvd",
    "iso:country":"US",
    "sg:address":"425 E Foothill Blvd",
    "sg:city":"Azusa",
    "sg:classifiers":[
        {
            "category":"Restaurant",
            "type":"Food & Drink"
        }
    ],
    "sg:phone":"+1 626 969 7779",
    "sg:postcode":"91702",
    "sg:province":"CA",
    "wof:name":"Taco Taco",
    "wof:placetype":"venue"
},
  "geometry": {"coordinates":[-117.90268,34.133524],"type":"Point"}
}