{
  "type": "Feature",
  "properties": {
    "iso:country":"US",
    "sg:address":"516 Villa Ave",
    "sg:city":"Clovis",
    "sg:classifiers":[
        {
            "category":"Wholesale",
            "subcategory":"Farm Supplies",
            "type":"Manufacturing & Wholesale Goods"
        }
    ],
    "sg:phone":"+1 559 297 6020",
    "sg:postcode":"93612",
    "sg:province":"CA",
    "wof:name":"Micro Flo Company",
    "wof:placetype":"venue"
},
  "geometry": {"coordinates":[-119.71347299999999,36.824333],"type":"Point"}
}