{
  "type": "Feature",
  "properties": {
    "iso:country":"US",
    "sg:address":"133 E Elm Ave",
    "sg:city":"Coalinga",
    "sg:classifiers":[
        {
            "category":"Shopping",
            "subcategory":"Used Merchandise",
            "type":"Retail Goods"
        },
        {
            "category":"Shopping",
            "subcategory":"Music",
            "type":"Retail Goods"
        }
    ],
    "sg:phone":"+1 559 935 3075",
    "sg:postcode":"93210",
    "sg:province":"CA",
    "sg:tags":[
        "record",
        "rare"
    ],
    "wof:name":"Fauria Musical",
    "wof:placetype":"venue"
},
  "geometry": {"coordinates":[-120.359651,36.140487],"type":"Point"}
}