{
  "type": "Feature",
  "properties": {
    "iso:country":"US",
    "sg:address":"37925 6th St E",
    "sg:city":"Palmdale",
    "sg:classifiers":[
        {
            "category":"Professional",
            "type":"Services"
        }
    ],
    "sg:phone":"+1 661 273 2000",
    "sg:postcode":"93550",
    "sg:province":"CA",
    "sg:tags":[
        "establishment"
    ],
    "wof:name":"C S & G Specialties",
    "wof:placetype":"venue"
},
  "geometry": {"coordinates":[-118.117968,34.571168],"type":"Point"}
}