{
  "type": "Feature",
  "properties": {
    "iso:country":"US",
    "sg:address":"90 Corte Arriba",
    "sg:city":"Novato",
    "sg:classifiers":[
        {
            "category":"Building & Trades",
            "subcategory":"Construction",
            "type":"Services"
        }
    ],
    "sg:phone":"+1 415 884 9573",
    "sg:postcode":"94949",
    "sg:province":"CA",
    "sg:tags":[
        "repairing",
        "remodeling",
        "contractor"
    ],
    "sg:website":"www.pottenger.com",
    "wof:name":"Pottenger Construction & Desig",
    "wof:placetype":"venue"
},
  "geometry": {"coordinates":[-122.54292599999999,38.064376],"type":"Point"}
}