{
  "type": "Feature",
  "properties": {
    "iso:country":"US",
    "sg:address":"1400 Hill St",
    "sg:city":"El Cajon",
    "sg:classifiers":[
        {
            "category":"Professional",
            "subcategory":"Computer Services",
            "type":"Services"
        }
    ],
    "sg:phone":"+1 619 590 9175",
    "sg:postcode":"92020",
    "sg:province":"CA",
    "sg:tags":[
        "repair"
    ],
    "sg:website":"www.cts4u.com",
    "wof:name":"Certified Technology Solutions Llc",
    "wof:placetype":"venue"
},
  "geometry": {"coordinates":[-116.978996,32.784199],"type":"Point"}
}