{
  "type": "Feature",
  "properties": {
    "addr:full":"1048 Irvine Ave Newport Beach CA 92660",
    "addr:housenumber":"1048",
    "addr:postcode":"92660",
    "addr:street":"Irvine Ave",
    "iso:country":"US",
    "sg:address":"1048 Irvine Ave",
    "sg:city":"Newport Beach",
    "sg:classifiers":[
        {
            "category":"Professional",
            "type":"Services"
        }
    ],
    "sg:phone":"+1 949 660 9222",
    "sg:postcode":"92660",
    "sg:province":"CA",
    "wof:name":"Cybervault Inc",
    "wof:placetype":"venue"
},
  "geometry": {"coordinates":[-117.907651,33.629481],"type":"Point"}
}