{
  "type": "Feature",
  "properties": {
    "addr:full":"1939 Harrison St Ste 300 Oakland CA 94612",
    "addr:housenumber":"1939",
    "addr:postcode":"94612",
    "addr:street":"Harrison St Ste 300",
    "iso:country":"US",
    "sg:address":"1939 Harrison St Ste 300",
    "sg:city":"Oakland",
    "sg:classifiers":[
        {
            "category":"Professional",
            "subcategory":"Accounting & Tax Preparation",
            "type":"Services"
        }
    ],
    "sg:phone":"+1 510 433 1440",
    "sg:postcode":"94612",
    "sg:province":"CA",
    "sg:tags":[
        "accountant"
    ],
    "wof:name":"Crawford Scott M CPA",
    "wof:placetype":"venue"
},
  "geometry": {"coordinates":[-122.264999,37.806999],"type":"Point"}
}