{
  "type": "Feature",
  "properties": {
    "iso:country":"US",
    "sg:address":"10512 Longfellow Ave",
    "sg:city":"Oakland",
    "sg:classifiers":[
        {
            "category":"Professional",
            "subcategory":"Business Services",
            "type":"Services"
        }
    ],
    "sg:phone":"+1 510 431 1257",
    "sg:postcode":"94603",
    "sg:province":"CA",
    "sg:tags":[
        "holding"
    ],
    "wof:name":"Blue Sky Investments",
    "wof:placetype":"venue"
},
  "geometry": {"coordinates":[-122.155672,37.742586],"type":"Point"}
}