{
  "type": "Feature",
  "properties": {
    "addr:full":"3152 E la Palma Ave Ste H Anaheim CA 92806",
    "addr:housenumber":"3152",
    "addr:postcode":"92806",
    "addr:street":"E La Palma Ave Ste H",
    "iso:country":"US",
    "sg:address":"3152 E la Palma Ave Ste H",
    "sg:city":"Anaheim",
    "sg:classifiers":[
        {
            "category":"Wholesale",
            "subcategory":"Medical Equipment & Supplies",
            "type":"Manufacturing & Wholesale Goods"
        }
    ],
    "sg:phone":"+1 714 630 2549",
    "sg:postcode":"92806",
    "sg:province":"CA",
    "sg:tags":[
        "hospital",
        "supplies-wholesale",
        "manufacturer"
    ],
    "wof:name":"Medspec, Inc",
    "wof:placetype":"venue"
},
  "geometry": {"coordinates":[-117.855036,33.851713],"type":"Point"}
}