{
  "type": "Feature",
  "properties": {
    "addr:full":"9020 Slauson Ave Pico Rivera CA 90660",
    "addr:postcode":"9020;90660",
    "addr:street":"Slauson Ave",
    "iso:country":"US",
    "sg:address":"9020 Slauson Ave",
    "sg:city":"Pico Rivera",
    "sg:classifiers":[
        {
            "category":"Professional",
            "subcategory":"Lawyer & Legal Services",
            "type":"Services"
        }
    ],
    "sg:phone":"+1 562 949 5329",
    "sg:postcode":"90660",
    "sg:province":"CA",
    "wof:name":"Camilo Estrada",
    "wof:placetype":"venue"
},
  "geometry": {"coordinates":[-118.104589,33.970648],"type":"Point"}
}