{
  "type": "Feature",
  "properties": {
    "iso:country":"US",
    "sg:address":"1052 Melody Ln",
    "sg:city":"Roseville",
    "sg:classifiers":[
        {
            "category":"Banks & Credit Unions",
            "subcategory":"Bank",
            "type":"Services"
        }
    ],
    "sg:phone":"+1 916 966 2980",
    "sg:postcode":"95678",
    "sg:province":"CA",
    "sg:tags":[
        "loan",
        "real estate"
    ],
    "sg:website":"www.fundyourloan.com",
    "wof:name":"Atlas Funding Group",
    "wof:placetype":"venue"
},
  "geometry": {"coordinates":[-121.290927,38.72661],"type":"Point"}
}