{
  "type": "Feature",
  "properties": {
    "addr:full":"4811 Chippendale Dr Sacramento CA 95841",
    "addr:housenumber":"4811",
    "addr:postcode":"95841",
    "addr:street":"Chippendale Dr",
    "iso:country":"US",
    "sg:address":"4811 Chippendale Dr",
    "sg:city":"Sacramento",
    "sg:classifiers":[
        {
            "category":"Personal",
            "type":"Services"
        }
    ],
    "sg:phone":"+1 916 331 7761",
    "sg:postcode":"95841",
    "sg:province":"CA",
    "sg:tags":[
        "therapist",
        "massage"
    ],
    "wof:name":"Olga Ptitsyn",
    "wof:placetype":"venue"
},
  "geometry": {"coordinates":[-121.351867,38.662872],"type":"Point"}
}