{
  "type": "Feature",
  "properties": {
    "iso:country":"US",
    "sg:address":"559 E Pico Blvd",
    "sg:city":"Los Angeles",
    "sg:classifiers":[
        {
            "category":"Shopping",
            "subcategory":"Hobbies, Toys, & Games",
            "type":"Retail Goods"
        }
    ],
    "sg:phone":"+1 213 749 8026",
    "sg:postcode":"90015",
    "sg:province":"CA",
    "sg:tags":[
        "doll",
        "clothing",
        "accessory"
    ],
    "wof:name":"Beautiful Kid",
    "wof:placetype":"venue"
},
  "geometry": {"coordinates":[-118.255353,34.033642],"type":"Point"}
}