{
  "type": "Feature",
  "properties": {
    "iso:country":"US",
    "sg:address":"1133 S San Gabriel Blvd",
    "sg:city":"San Gabriel",
    "sg:classifiers":[
        {
            "category":"Health Services",
            "subcategory":"Doctor",
            "type":"Services"
        }
    ],
    "sg:phone":"+1 626 286 7666",
    "sg:postcode":"91776",
    "sg:province":"CA",
    "wof:name":"Yeh Sunny MD",
    "wof:placetype":"venue"
},
  "geometry": {"coordinates":[-118.091003,34.087101],"type":"Point"}
}