{
  "type": "Feature",
  "properties": {
    "addr:full":"22551 Foothill Blvd Hayward CA 94541",
    "addr:housenumber":"22551",
    "addr:postcode":"94541",
    "addr:street":"Foothill Blvd",
    "iso:country":"US",
    "sg:address":"22551 Foothill Blvd",
    "sg:city":"Hayward",
    "sg:classifiers":[
        {
            "category":"Professional",
            "subcategory":"Lawyer & Legal Services",
            "type":"Services"
        }
    ],
    "sg:phone":"+1 510 728 7600",
    "sg:postcode":"94541",
    "sg:province":"CA",
    "sg:tags":[
        "divorce",
        "assistance",
        "law",
        "family"
    ],
    "sg:website":"www.wethepeople-bayarea.com",
    "wof:name":"We the People",
    "wof:placetype":"venue"
},
  "geometry": {"coordinates":[-122.081001,37.6744],"type":"Point"}
}