{
  "type": "Feature",
  "properties": {
    "addr:full":"152 Coop Ct Encinitas CA 92024",
    "addr:housenumber":"152",
    "addr:postcode":"92024",
    "addr:street":"Coop Ct",
    "iso:country":"US",
    "sg:address":"152 Coop Ct",
    "sg:city":"Encinitas",
    "sg:classifiers":[
        {
            "category":"Building & Trades",
            "subcategory":"Construction",
            "type":"Services"
        }
    ],
    "sg:phone":"+1 760 753 2111",
    "sg:postcode":"92024",
    "sg:province":"CA",
    "sg:tags":[
        "painter"
    ],
    "wof:name":"Beemer Coatings",
    "wof:placetype":"venue"
},
  "geometry": {"coordinates":[-117.306704,33.073252],"type":"Point"}
}