{
  "type": "Feature",
  "properties": {
    "addr:full":"1424 Detroit Ave Concord CA 94520",
    "addr:housenumber":"1424",
    "addr:postcode":"94520",
    "addr:street":"Detroit Ave",
    "iso:country":"US",
    "sg:address":"1424 Detroit Ave",
    "sg:city":"Concord",
    "sg:classifiers":[
        {
            "category":"Retail",
            "subcategory":"Animal Services",
            "type":"Services"
        }
    ],
    "sg:phone":"+1 925 890 5072",
    "sg:postcode":"94520",
    "sg:province":"CA",
    "sg:tags":[
        "pet"
    ],
    "wof:name":"Friends Of Bill Pet Home Care",
    "wof:placetype":"venue"
},
  "geometry": {"coordinates":[-122.03912699999999,37.96609],"type":"Point"}
}