{
  "type": "Feature",
  "properties": {
    "iso:country":"US",
    "sg:address":"1215 K St",
    "sg:city":"Sacramento",
    "sg:classifiers":[
        {
            "category":"Professional",
            "subcategory":"Management & Consulting",
            "type":"Services"
        }
    ],
    "sg:phone":"+1 916 650 2000",
    "sg:postcode":"95814",
    "sg:province":"CA",
    "sg:tags":[
        "consultant",
        "business"
    ],
    "sg:website":"www.accenture.com",
    "wof:name":"Accenture LTD",
    "wof:placetype":"venue"
},
  "geometry": {"coordinates":[-121.48984400000001,38.578204],"type":"Point"}
}