{
  "type": "Feature",
  "properties": {
    "iso:country":"US",
    "sg:address":"1117 Geary Blvd",
    "sg:city":"San Francisco",
    "sg:classifiers":[
        {
            "category":"Communications",
            "subcategory":"Radio Station",
            "type":"Services"
        }
    ],
    "sg:phone":"+1 415 474 4774",
    "sg:postcode":"94109",
    "sg:province":"CA",
    "sg:tags":[
        "broadcast"
    ],
    "wof:name":"Kwde Radio",
    "wof:placetype":"venue"
},
  "geometry": {"coordinates":[-122.422805,37.785441],"type":"Point"}
}