{
  "type": "Feature",
  "properties": {
    "addr:full":"12766 W Washington Blvd Los Angeles CA 90066",
    "addr:housenumber":"12766",
    "addr:postcode":"90066",
    "addr:street":"W Washington Blvd",
    "iso:country":"US",
    "sg:address":"12766 W Washington Blvd",
    "sg:city":"Los Angeles",
    "sg:classifiers":[
        {
            "category":"Travel",
            "subcategory":"Travel Agent",
            "type":"Entertainment"
        }
    ],
    "sg:phone":"+1 310 305 0285",
    "sg:postcode":"90066",
    "sg:province":"CA",
    "sg:tags":[
        "agency",
        "bureau"
    ],
    "wof:name":"Herman Viajes Travel",
    "wof:placetype":"venue"
},
  "geometry": {"coordinates":[-118.436166,33.996233],"type":"Point"}
}