{
  "type": "Feature",
  "properties": {
    "iso:country":"US",
    "sg:address":"2198 E Anderson St",
    "sg:city":"Vernon",
    "sg:classifiers":[
        {
            "category":"Wholesale",
            "subcategory":"Stationery",
            "type":"Manufacturing & Wholesale Goods"
        }
    ],
    "sg:phone":"+1 323 581 9850",
    "sg:postcode":"90058",
    "sg:province":"CA",
    "sg:tags":[
        "card"
    ],
    "wof:name":"Focus Distributors Inc",
    "wof:placetype":"venue"
},
  "geometry": {"coordinates":[-118.233902,33.989779],"type":"Point"}
}