{
  "type": "Feature",
  "properties": {
    "addr:full":"1010 Lakeville St Petaluma CA 94952",
    "addr:housenumber":"1010",
    "addr:postcode":"94952",
    "addr:street":"Lakeville St",
    "iso:country":"US",
    "sg:address":"1010 Lakeville St",
    "sg:city":"Petaluma",
    "sg:classifiers":[
        {
            "category":"Home & Garden",
            "subcategory":"Building Materials",
            "type":"Retail Goods"
        }
    ],
    "sg:phone":"+1 707 762 0055",
    "sg:postcode":"94952",
    "sg:province":"CA",
    "sg:tags":[
        "glass",
        "window",
        "plate"
    ],
    "wof:name":"Golden West Glass Co Inc",
    "wof:placetype":"venue"
},
  "geometry": {"coordinates":[-122.621751,38.235227],"type":"Point"}
}