{
  "type": "Feature",
  "properties": {
    "addr:full":"1520 E Covell Blvd Davis CA 95616",
    "addr:housenumber":"1520",
    "addr:postcode":"95616",
    "addr:street":"E Covell Blvd",
    "iso:country":"US",
    "sg:address":"1520 E Covell Blvd",
    "sg:city":"Davis",
    "sg:classifiers":[
        {
            "category":"Personal",
            "subcategory":"Beauty Salon",
            "type":"Services"
        }
    ],
    "sg:phone":"+1 530 753 3450",
    "sg:postcode":"95616",
    "sg:province":"CA",
    "wof:name":"Creative Hair",
    "wof:placetype":"venue"
},
  "geometry": {"coordinates":[-121.732907,38.562052],"type":"Point"}
}