{
  "type": "Feature",
  "properties": {
    "addr:full":"6300 Wilshire Boulevard Los Angeles CA 90048",
    "addr:housenumber":"6300",
    "addr:postcode":"90048",
    "addr:street":"Wilshire Boulevard",
    "iso:country":"US",
    "sg:address":"6300 Wilshire Boulevard",
    "sg:city":"Los Angeles",
    "sg:classifiers":[
        {
            "category":"Professional",
            "subcategory":"Lawyer & Legal Services",
            "type":"Services"
        }
    ],
    "sg:phone":"+1 323 852 6135",
    "sg:postcode":"90048",
    "sg:province":"CA",
    "wof:name":"Law Offices of Adam Green",
    "wof:placetype":"venue"
},
  "geometry": {"coordinates":[-118.365403,34.063418],"type":"Point"}
}