{
  "type": "Feature",
  "properties": {
    "addr:full":"4682 Charnock Dr Irvine CA 92604",
    "addr:housenumber":"4682",
    "addr:postcode":"92604",
    "addr:street":"Charnock Dr",
    "iso:country":"US",
    "sg:address":"4682 Charnock Dr",
    "sg:city":"Irvine",
    "sg:classifiers":[
        {
            "category":"Professional",
            "type":"Services"
        }
    ],
    "sg:phone":"+1 949 551 3521",
    "sg:postcode":"92604",
    "sg:province":"CA",
    "wof:name":"Body Perfect Personal Training",
    "wof:placetype":"venue"
},
  "geometry": {"coordinates":[-117.780811,33.695892],"type":"Point"}
}