{
  "type": "Feature",
  "properties": {
    "iso:country":"US",
    "sg:address":"1400 N Brea Blvd",
    "sg:city":"Fullerton",
    "sg:classifiers":[
        {
            "category":"Professional",
            "subcategory":"Lawyer & Legal Services",
            "type":"Services"
        }
    ],
    "sg:phone":"+1 714 578 8838",
    "sg:postcode":"92835",
    "sg:province":"CA",
    "sg:tags":[
        "attorney"
    ],
    "wof:name":"Andrew V Arczynski",
    "wof:placetype":"venue"
},
  "geometry": {"coordinates":[-117.924408,33.883616],"type":"Point"}
}