{
  "type": "Feature",
  "properties": {
    "iso:country":"US",
    "sg:address":"2959 Blue Spruce Cir",
    "sg:city":"Thousand Oaks",
    "sg:classifiers":[
        {
            "category":"Building & Trades",
            "subcategory":"Plumbing",
            "type":"Services"
        }
    ],
    "sg:phone":"+1 805 498 3000",
    "sg:postcode":"91360",
    "sg:province":"CA",
    "sg:tags":[
        "plumbing",
        "contractor"
    ],
    "wof:name":"Bob Roberts Plumbing",
    "wof:placetype":"venue"
},
  "geometry": {"coordinates":[-118.853071,34.219756],"type":"Point"}
}