{
  "type": "Feature",
  "properties": {
    "addr:full":"136 8th Ave La Puente CA 91746",
    "addr:housenumber":"136",
    "addr:postcode":"91746",
    "addr:street":"8Th Ave",
    "iso:country":"US",
    "sg:address":"136 8th Ave",
    "sg:city":"La Puente",
    "sg:classifiers":[
        {
            "category":"Professional",
            "subcategory":"Management & Consulting",
            "type":"Services"
        }
    ],
    "sg:phone":"+1 626 961 4480",
    "sg:postcode":"91746",
    "sg:province":"CA",
    "sg:tags":[
        "marketing",
        "consultant"
    ],
    "wof:name":"K & L Marketing Inc",
    "wof:placetype":"venue"
},
  "geometry": {"coordinates":[-117.971585,34.032072],"type":"Point"}
}