{
  "type": "Feature",
  "properties": {
    "iso:country":"US",
    "sg:address":"159 Taft Ave",
    "sg:city":"Ventura",
    "sg:classifiers":[
        {
            "category":"Professional",
            "subcategory":"Engineering",
            "type":"Services"
        }
    ],
    "sg:phone":"+1 805 647 1617",
    "sg:postcode":"93003",
    "sg:province":"CA",
    "sg:tags":[
        "refrigeration",
        "engineer"
    ],
    "wof:name":"Ventura Refrigeration Sales & Service",
    "wof:placetype":"venue"
},
  "geometry": {"coordinates":[-119.197596,34.279203],"type":"Point"}
}