{
  "type": "Feature",
  "properties": {
    "addr:full":"1320 Ivy Way Manteca CA 95336",
    "addr:housenumber":"1320",
    "addr:postcode":"95336",
    "addr:street":"Ivy Way",
    "iso:country":"US",
    "sg:address":"1320 Ivy Way",
    "sg:city":"Manteca",
    "sg:classifiers":[
        {
            "category":"Professional",
            "type":"Services"
        }
    ],
    "sg:phone":"+1 209 825 5948",
    "sg:postcode":"95336",
    "sg:province":"CA",
    "sg:website":"www.speed-concepts.com",
    "wof:name":"Speed Concepts",
    "wof:placetype":"venue"
},
  "geometry": {"coordinates":[-121.23848599999999,37.823757],"type":"Point"}
}