{
  "type": "Feature",
  "properties": {
    "iso:country":"US",
    "sg:address":"1730 Daggett Way",
    "sg:city":"Sacramento",
    "sg:classifiers":[
        {
            "category":"Professional",
            "subcategory":"Business Services",
            "type":"Services"
        }
    ],
    "sg:phone":"+1 916 419 0625",
    "sg:postcode":"95835",
    "sg:province":"CA",
    "sg:tags":[
        "equipment",
        "microfilming"
    ],
    "wof:name":"Filmdex",
    "wof:placetype":"venue"
},
  "geometry": {"coordinates":[-121.499814,38.682748],"type":"Point"}
}