{
  "type": "Feature",
  "properties": {
    "iso:country":"US",
    "sg:address":"3719 S Meyler St",
    "sg:city":"San Pedro",
    "sg:classifiers":[
        {
            "category":"Building & Trades",
            "subcategory":"Construction",
            "type":"Services"
        }
    ],
    "sg:phone":"+1 310 548 7220",
    "sg:postcode":"90731",
    "sg:province":"CA",
    "sg:tags":[
        "painter"
    ],
    "wof:name":"Chang's Painting",
    "wof:placetype":"venue"
},
  "geometry": {"coordinates":[-118.301441,33.711554],"type":"Point"}
}