{
  "type": "Feature",
  "properties": {
    "iso:country":"US",
    "sg:address":"11879 Kemper Rd",
    "sg:city":"Auburn",
    "sg:classifiers":[
        {
            "category":"Building & Trades",
            "subcategory":"Construction",
            "type":"Services"
        }
    ],
    "sg:phone":"+1 530 823 7074",
    "sg:postcode":"95603",
    "sg:province":"CA",
    "sg:tags":[
        "marking",
        "maintenance",
        "parking"
    ],
    "wof:name":"TDT Inc",
    "wof:placetype":"venue"
},
  "geometry": {"coordinates":[-121.091657,38.931409],"type":"Point"}
}