{
  "type": "Feature",
  "properties": {
    "addr:full":"5920 West Mall Atascadero CA 93422",
    "addr:housenumber":"5920",
    "addr:postcode":"93422",
    "addr:street":"West Mall",
    "iso:country":"US",
    "sg:address":"5920 West Mall",
    "sg:city":"Atascadero",
    "sg:classifiers":[
        {
            "category":"Health Services",
            "subcategory":"Doctor",
            "type":"Services"
        }
    ],
    "sg:phone":"+1 805 466 0676",
    "sg:postcode":"93422",
    "sg:province":"CA",
    "sg:tags":[
        "physician",
        "surgeon"
    ],
    "wof:name":"Warren Lyle H MD",
    "wof:placetype":"venue"
},
  "geometry": {"coordinates":[-120.66797200000001,35.489436],"type":"Point"}
}