{
  "type": "Feature",
  "properties": {
    "addr:full":"4445 Estate Dr Fallbrook CA 92028",
    "addr:housenumber":"4445",
    "addr:postcode":"92028",
    "addr:street":"Estate Dr",
    "iso:country":"US",
    "sg:address":"4445 Estate Dr",
    "sg:city":"Fallbrook",
    "sg:classifiers":[
        {
            "category":"Building & Trades",
            "subcategory":"Construction",
            "type":"Services"
        }
    ],
    "sg:phone":"+1 760 758 4313",
    "sg:postcode":"92028",
    "sg:province":"CA",
    "sg:tags":[
        "contractor"
    ],
    "wof:name":"T W M Roofing",
    "wof:placetype":"venue"
},
  "geometry": {"coordinates":[-117.20928000000001,33.307173],"type":"Point"}
}