{
  "type": "Feature",
  "properties": {
    "addr:full":"65 3rd St Point Reyes Sta CA 94956",
    "addr:housenumber":"65",
    "addr:postcode":"94956",
    "addr:street":"3Rd St;Reyes Sta",
    "iso:country":"US",
    "sg:address":"65 3rd St",
    "sg:city":"Point Reyes Sta",
    "sg:classifiers":[
        {
            "category":"Organizations",
            "subcategory":"Community Association",
            "type":"Services"
        }
    ],
    "sg:phone":"+1 415 663 9312",
    "sg:postcode":"94956",
    "sg:province":"CA",
    "sg:tags":[
        "environmental",
        "org"
    ],
    "wof:name":"Environmental Action Committee",
    "wof:placetype":"venue"
},
  "geometry": {"coordinates":[-122.806145,38.068205],"type":"Point"}
}