{
  "type": "Feature",
  "properties": {
    "iso:country":"US",
    "sg:address":"17171 S Central Ave",
    "sg:city":"Carson",
    "sg:classifiers":[
        {
            "category":"Utilities",
            "subcategory":"Electric",
            "type":"Services"
        }
    ],
    "sg:phone":"+1 310 635 9827",
    "sg:postcode":"90746",
    "sg:province":"CA",
    "sg:tags":[
        "plant",
        "company",
        "power"
    ],
    "wof:name":"Carson Cogeneration Company",
    "wof:placetype":"venue"
},
  "geometry": {"coordinates":[-118.248695,33.874764],"type":"Point"}
}