{
  "type": "Feature",
  "properties": {
    "iso:country":"US",
    "sg:address":"821 S Wilton Pl",
    "sg:city":"Los Angeles",
    "sg:classifiers":[
        {
            "category":"Shopping",
            "subcategory":"Beauty & Cosmetics",
            "type":"Retail Goods"
        },
        {
            "category":"Personal",
            "subcategory":"Beauty Salon",
            "type":"Services"
        }
    ],
    "sg:phone":"+1 424 245 6525",
    "sg:postcode":"90005",
    "sg:province":"CA",
    "sg:tags":[
        "makeup",
        "artist",
        "supply"
    ],
    "sg:website":"www.eugeneconde.com/",
    "wof:name":"Eugene Conde ?Make-up Artist Hairstylist",
    "wof:placetype":"venue"
},
  "geometry": {"coordinates":[-118.314616,34.057366],"type":"Point"}
}