{
  "type": "Feature",
  "properties": {
    "iso:country":"US",
    "sg:address":"8850 Corbin Ave",
    "sg:city":"Northridge",
    "sg:classifiers":[
        {
            "category":"Personal",
            "subcategory":"Beauty Salon",
            "type":"Services"
        }
    ],
    "sg:phone":"+1 818 701 5640",
    "sg:postcode":"91324",
    "sg:province":"CA",
    "wof:name":"Lisa Marie Hair Designs",
    "wof:placetype":"venue"
},
  "geometry": {"coordinates":[-118.56223,34.231944],"type":"Point"}
}