{
  "type": "Feature",
  "properties": {
    "iso:country":"US",
    "sg:address":"4700 Stockdale Hwy",
    "sg:city":"Bakersfield",
    "sg:classifiers":[
        {
            "category":"Insurance",
            "subcategory":"Insurance Agent",
            "type":"Services"
        }
    ],
    "sg:phone":"+1 661 326 6330",
    "sg:postcode":"93309",
    "sg:province":"CA",
    "wof:name":"Millennium Advantage Insurance",
    "wof:placetype":"venue"
},
  "geometry": {"coordinates":[-119.056557,35.354217],"type":"Point"}
}