{
  "type": "Feature",
  "properties": {
    "addr:full":"2098 N Belle St San Bernardino CA 92404",
    "addr:housenumber":"2098",
    "addr:postcode":"92404",
    "addr:street":"N Belle St",
    "iso:country":"US",
    "sg:address":"2098 N Belle St",
    "sg:city":"San Bernardino",
    "sg:classifiers":[
        {
            "category":"Professional",
            "type":"Services"
        }
    ],
    "sg:phone":"+1 909 883 9648",
    "sg:postcode":"92404",
    "sg:province":"CA",
    "wof:name":"Accxel 1",
    "wof:placetype":"venue"
},
  "geometry": {"coordinates":[-117.280114,34.132471],"type":"Point"}
}