{
  "type": "Feature",
  "properties": {
    "addr:full":"25607 Mont Pointe Lake Forest CA 92630",
    "addr:postcode":"25607;92630",
    "addr:street":"Mont Pointe",
    "iso:country":"US",
    "sg:address":"25607 Mont Pointe",
    "sg:city":"Lake Forest",
    "sg:classifiers":[
        {
            "category":"Freight",
            "type":"Transportation"
        }
    ],
    "sg:phone":"+1 949 770 2980",
    "sg:postcode":"92630",
    "sg:province":"CA",
    "sg:tags":[
        "arrangement"
    ],
    "wof:name":"Sch Enterprises",
    "wof:placetype":"venue"
},
  "geometry": {"coordinates":[-117.681217,33.640011],"type":"Point"}
}