{
  "type": "Feature",
  "properties": {
    "addr:full":"9234 Hickory Ave Hesperia CA 92345",
    "addr:housenumber":"9234",
    "addr:postcode":"92345",
    "addr:street":"Hickory Ave",
    "iso:country":"US",
    "sg:address":"9234 Hickory Ave",
    "sg:city":"Hesperia",
    "sg:classifiers":[
        {
            "category":"Building & Trades",
            "subcategory":"Construction",
            "type":"Services"
        }
    ],
    "sg:phone":"+1 760 948 6010",
    "sg:postcode":"92345",
    "sg:province":"CA",
    "sg:tags":[
        "concrete",
        "contractor"
    ],
    "wof:name":"Competitive Flooring",
    "wof:placetype":"venue"
},
  "geometry": {"coordinates":[-117.32778500000001,34.423144],"type":"Point"}
}