{
  "type": "Feature",
  "properties": {
    "addr:full":"1 State St Santa Barbara CA 93101",
    "addr:housenumber":"1",
    "addr:postcode":"93101",
    "addr:street":"State St",
    "iso:country":"US",
    "sg:address":"1 State St",
    "sg:city":"Santa Barbara",
    "sg:classifiers":[
        {
            "category":"Real Estate",
            "subcategory":"Architect",
            "type":"Services"
        }
    ],
    "sg:phone":"+1 805 963 8077",
    "sg:postcode":"93101",
    "sg:province":"CA",
    "sg:website":"www.cearnal.com",
    "wof:name":"Cearnal Architects Inc",
    "wof:placetype":"venue"
},
  "geometry": {"coordinates":[-119.689559,34.412448],"type":"Point"}
}