{
  "type": "Feature",
  "properties": {
    "addr:full":"5021 Cordoba Cir La Palma CA 90623",
    "addr:housenumber":"5021",
    "addr:postcode":"90623",
    "addr:street":"Cordoba Cir",
    "iso:country":"US",
    "sg:address":"5021 Cordoba Cir",
    "sg:city":"La Palma",
    "sg:classifiers":[
        {
            "category":"Building & Trades",
            "subcategory":"Landscaping Services",
            "type":"Services"
        }
    ],
    "sg:phone":"+1 714 827 0559",
    "sg:postcode":"90623",
    "sg:province":"CA",
    "sg:tags":[
        "designer",
        "landscape"
    ],
    "wof:name":"Matsui & Associates",
    "wof:placetype":"venue"
},
  "geometry": {"coordinates":[-118.044455,33.84092],"type":"Point"}
}