{
  "type": "Feature",
  "properties": {
    "addr:full":"243 S Vermont Ave Glendora CA 91741",
    "addr:housenumber":"243",
    "addr:postcode":"91741",
    "addr:street":"S Vermont Ave",
    "iso:country":"US",
    "sg:address":"243 S Vermont Ave",
    "sg:city":"Glendora",
    "sg:classifiers":[
        {
            "category":"Building & Trades",
            "subcategory":"Plumbing",
            "type":"Services"
        }
    ],
    "sg:phone":"+1 626 963 1552",
    "sg:postcode":"91741",
    "sg:province":"CA",
    "sg:tags":[
        "conditioning",
        "air",
        "system",
        "contractor"
    ],
    "wof:name":"J C Heating & Air Cond",
    "wof:placetype":"venue"
},
  "geometry": {"coordinates":[-117.86682999999999,34.133023],"type":"Point"}
}