{
  "type": "Feature",
  "properties": {
    "addr:full":"1748 Newcomb Ave San Francisco CA 94124",
    "addr:housenumber":"1748",
    "addr:postcode":"94124",
    "addr:street":"Newcomb Ave",
    "iso:country":"US",
    "sg:address":"1748 Newcomb Ave",
    "sg:city":"San Francisco",
    "sg:classifiers":[
        {
            "category":"Real Estate",
            "subcategory":"Real Estate Operator",
            "type":"Services"
        }
    ],
    "sg:phone":"+1 415 821 6272",
    "sg:postcode":"94124",
    "sg:province":"CA",
    "sg:tags":[
        "boarding",
        "house"
    ],
    "wof:name":"Alderson's Board & Care Home",
    "wof:placetype":"venue"
},
  "geometry": {"coordinates":[-122.392754,37.736891],"type":"Point"}
}