{
  "type": "Feature",
  "properties": {
    "iso:country":"US",
    "sg:address":"18549 Yorba Linda Blvd",
    "sg:city":"Yorba Linda",
    "sg:classifiers":[
        {
            "category":"Wholesale",
            "subcategory":"Jewelry",
            "type":"Manufacturing & Wholesale Goods"
        },
        {
            "category":"Shopping",
            "subcategory":"Gifts & Souvenirs",
            "type":"Retail Goods"
        }
    ],
    "sg:phone":"+1 714 779 8688",
    "sg:postcode":"92886",
    "sg:province":"CA",
    "sg:tags":[
        "beads"
    ],
    "wof:name":"Beads & Crafts",
    "wof:placetype":"venue"
},
  "geometry": {"coordinates":[-117.809142,33.888714],"type":"Point"}
}