{
  "type": "Feature",
  "properties": {
    "iso:country":"US",
    "sg:address":"933 Valley Dr",
    "sg:city":"Vista",
    "sg:classifiers":[
        {
            "category":"Health Services",
            "subcategory":"Doctor",
            "type":"Services"
        }
    ],
    "sg:phone":"+1 760 724 1011",
    "sg:postcode":"92084",
    "sg:province":"CA",
    "sg:tags":[
        "dentist"
    ],
    "wof:name":"Steve M Nave DDS",
    "wof:placetype":"venue"
},
  "geometry": {"coordinates":[-117.214074,33.192048],"type":"Point"}
}