{
  "type": "Feature",
  "properties": {
    "iso:country":"US",
    "sg:address":"1570 Market St",
    "sg:city":"San Francisco",
    "sg:classifiers":[
        {
            "category":"Health Services",
            "subcategory":"Hospital",
            "type":"Services"
        }
    ],
    "sg:phone":"+1 415 567 8304",
    "sg:postcode":"94102",
    "sg:province":"CA",
    "sg:tags":[
        "center",
        "birth"
    ],
    "wof:name":"Making Waves Education Program",
    "wof:placetype":"venue"
},
  "geometry": {"coordinates":[-122.41895700000001,37.775595],"type":"Point"}
}