{
  "type": "Feature",
  "properties": {
    "iso:country":"US",
    "sg:address":"711 W Poplar Ave",
    "sg:city":"Porterville",
    "sg:classifiers":[
        {
            "category":"Organizations",
            "subcategory":"Religious Organization",
            "type":"Services"
        }
    ],
    "sg:phone":"+1 559 782 1165",
    "sg:postcode":"93257",
    "sg:province":"CA",
    "sg:tags":[
        "church"
    ],
    "wof:name":"Trinity Southern Baptist Chr",
    "wof:placetype":"venue"
},
  "geometry": {"coordinates":[-119.032538,36.051703],"type":"Point"}
}