{
  "type": "Feature",
  "properties": {
    "iso:country":"US",
    "sg:address":"1545 Pioneer Way",
    "sg:city":"El Cajon",
    "sg:classifiers":[
        {
            "category":"Organizations",
            "subcategory":"Membership Organization",
            "type":"Services"
        }
    ],
    "sg:phone":"+1 619 588 4901",
    "sg:postcode":"92020",
    "sg:province":"CA",
    "wof:name":"Mt Helix Park Foundation",
    "wof:placetype":"venue"
},
  "geometry": {"coordinates":[-116.967679,32.813675],"type":"Point"}
}