{
  "type": "Feature",
  "properties": {
    "addr:full":"1301 N Rose Dr Placentia CA 92870",
    "addr:housenumber":"1301",
    "addr:postcode":"ca 92870",
    "addr:street":"N Rose Dr",
    "iso:country":"US",
    "sg:address":"1301 N Rose Dr",
    "sg:city":"Placentia",
    "sg:classifiers":[
        {
            "category":"Health Services",
            "subcategory":"Doctor",
            "type":"Services"
        }
    ],
    "sg:phone":"+1 866 396 2717",
    "sg:postcode":"92870",
    "sg:province":"CA",
    "sg:tags":[
        "physician",
        "stomach",
        "intestines",
        "gastroenterology",
        "surgeons"
    ],
    "sg:website":"http://placentialinda.reachlocal.com/?scid=1736231",
    "wof:name":"Gastroenterology Services",
    "wof:placetype":"venue"
},
  "geometry": {"coordinates":[-117.842146,33.886508],"type":"Point"}
}