{
  "type": "Feature",
  "properties": {
    "addr:full":"1160 Sonora Ave Glendale CA 91201",
    "addr:housenumber":"1160",
    "addr:postcode":"91201",
    "addr:street":"Sonora Ave",
    "iso:country":"US",
    "sg:address":"1160 Sonora Ave",
    "sg:city":"Glendale",
    "sg:classifiers":[
        {
            "category":"Shopping",
            "subcategory":"Gifts & Souvenirs",
            "type":"Retail Goods"
        }
    ],
    "sg:phone":"+1 818 243 2946",
    "sg:postcode":"91201",
    "sg:province":"CA",
    "sg:tags":[
        "party",
        "supply"
    ],
    "wof:name":"Pioneer Trading Co",
    "wof:placetype":"venue"
},
  "geometry": {"coordinates":[-118.283742,34.170075],"type":"Point"}
}