{
  "type": "Feature",
  "properties": {
    "iso:country":"US",
    "sg:address":"3731 Stocker St",
    "sg:city":"Los Angeles",
    "sg:classifiers":[
        {
            "category":"Health Services",
            "subcategory":"Doctor",
            "type":"Services"
        }
    ],
    "sg:phone":"+1 323 294 5216",
    "sg:postcode":"90008",
    "sg:province":"CA",
    "wof:name":"Waldron David MD",
    "wof:placetype":"venue"
},
  "geometry": {"coordinates":[-118.337997,34.0065],"type":"Point"}
}