{
  "type": "Feature",
  "properties": {
    "addr:full":"1014 Fruitvale Ave Oakland CA 94601",
    "addr:housenumber":"1014",
    "addr:postcode":"94601",
    "addr:street":"Fruitvale Ave",
    "iso:country":"US",
    "sg:address":"1014 Fruitvale Ave",
    "sg:city":"Oakland",
    "sg:classifiers":[
        {
            "category":"Retail",
            "subcategory":"Auto Repair",
            "type":"Services"
        }
    ],
    "sg:phone":"+1 510 434 9430",
    "sg:postcode":"94601",
    "sg:province":"CA",
    "sg:tags":[
        "body",
        "automobile",
        "painting"
    ],
    "wof:name":"Alexis Body Shop",
    "wof:placetype":"venue"
},
  "geometry": {"coordinates":[-122.226782,37.775241],"type":"Point"}
}