{
  "type": "Feature",
  "properties": {
    "addr:full":"20703 Santa Clara St Canyon Country CA 91351",
    "addr:housenumber":"20703",
    "addr:postcode":"91351",
    "addr:street":"Santa Clara St",
    "iso:country":"US",
    "sg:address":"20703 Santa Clara St",
    "sg:city":"Canyon Country",
    "sg:classifiers":[
        {
            "category":"Building & Trades",
            "subcategory":"Construction",
            "type":"Services"
        }
    ],
    "sg:phone":"+1 661 299 5539",
    "sg:postcode":"91351",
    "sg:province":"CA",
    "sg:tags":[
        "masonry",
        "contractor"
    ],
    "wof:name":"Design Masonry Inc",
    "wof:placetype":"venue"
},
  "geometry": {"coordinates":[-118.498442,34.425314],"type":"Point"}
}