{
  "type": "Feature",
  "properties": {
    "iso:country":"US",
    "sg:address":"1720 N Termino Ave",
    "sg:city":"Long Beach",
    "sg:classifiers":[
        {
            "category":"Health Services",
            "subcategory":"Hospital",
            "type":"Services"
        }
    ],
    "sg:phone":"+1 562 498 1000",
    "sg:postcode":"90804",
    "sg:province":"CA",
    "wof:name":"Community Hospital Of Long Bch",
    "wof:placetype":"venue"
},
  "geometry": {"coordinates":[-118.14581,33.787847],"type":"Point"}
}