{
  "type": "Feature",
  "properties": {
    "iso:country":"US",
    "sg:address":"11815 Horton Ave",
    "sg:city":"Downey",
    "sg:phone":"+1 562 923 9918",
    "sg:postcode":"90241",
    "sg:province":"CA",
    "sg:tags":[
        "oil"
    ],
    "wof:name":"Futura Fuels",
    "wof:placetype":"venue"
},
  "geometry": {"coordinates":[-118.149877,33.940028],"type":"Point"}
}