{
  "type": "Feature",
  "properties": {
    "iso:country":"US",
    "sg:address":"250 Douglass St.",
    "sg:city":"San Francisco",
    "sg:classifiers":[
        {
            "category":"Landmark",
            "subcategory":"Historic",
            "type":"Public Place"
        }
    ],
    "sg:postcode":"94114",
    "sg:province":"CA",
    "sg:tags":[
        "building",
        "historical"
    ],
    "wof:name":"Alfred 'Nobby' Clarke's Mansion",
    "wof:placetype":"venue"
},
  "geometry": {"coordinates":[-122.439527,37.759614],"type":"Point"}
}