{
  "type": "Feature",
  "properties": {
    "addr:full":"3223 Bagley Ave Los Angeles CA 90034",
    "addr:housenumber":"3223",
    "addr:postcode":"90034",
    "addr:street":"Bagley Ave",
    "iso:country":"US",
    "sg:address":"3223 Bagley Ave",
    "sg:city":"Los Angeles",
    "sg:classifiers":[
        {
            "category":"Travel",
            "subcategory":"Travel Agent",
            "type":"Entertainment"
        }
    ],
    "sg:phone":"+1 310 839 4354",
    "sg:postcode":"90034",
    "sg:province":"CA",
    "sg:tags":[
        "agency"
    ],
    "wof:name":"Mighty Travels",
    "wof:placetype":"venue"
},
  "geometry": {"coordinates":[-118.39514,34.033909],"type":"Point"}
}