{
  "type": "Feature",
  "properties": {
    "iso:country":"US",
    "sg:address":"2518 Lee Ave",
    "sg:city":"South El Monte",
    "sg:classifiers":[
        {
            "category":"Professional",
            "type":"Services"
        }
    ],
    "sg:phone":"+1 626 350 2124",
    "sg:postcode":"91733",
    "sg:province":"CA",
    "wof:name":"Ruben Vidal",
    "wof:placetype":"venue"
},
  "geometry": {"coordinates":[-118.067216,34.056888],"type":"Point"}
}