{
  "type": "Feature",
  "properties": {
    "iso:country":"US",
    "sg:address":"231 1st St",
    "sg:city":"Gilroy",
    "sg:classifiers":[
        {
            "category":"Professional",
            "subcategory":"Management & Consulting",
            "type":"Services"
        }
    ],
    "sg:phone":"+1 408 848 0007",
    "sg:postcode":"95020",
    "sg:province":"CA",
    "sg:tags":[
        "party",
        "planning"
    ],
    "wof:name":"LA Mejor Dulceria",
    "wof:placetype":"venue"
},
  "geometry": {"coordinates":[-121.575104,37.013911],"type":"Point"}
}