{
  "type": "Feature",
  "properties": {
    "iso:country":"US",
    "sg:address":"5213 W Sunset Blvd",
    "sg:city":"Los Angeles",
    "sg:classifiers":[
        {
            "category":"Retail",
            "subcategory":"Laundry & Dry Cleaning",
            "type":"Services"
        }
    ],
    "sg:phone":"+1 323 664 4037",
    "sg:postcode":"90027",
    "sg:province":"CA",
    "sg:tags":[
        "cleaner"
    ],
    "sg:website":"www.coast1hr.com",
    "wof:name":"Coast 1 Hr Cleaners",
    "wof:placetype":"venue"
},
  "geometry": {"coordinates":[-118.303543,34.098117],"type":"Point"}
}