{
  "type": "Feature",
  "properties": {
    "iso:country":"US",
    "sg:address":"800 Colusa Ave",
    "sg:city":"Yuba City",
    "sg:classifiers":[
        {
            "category":"Restaurant",
            "type":"Food & Drink"
        }
    ],
    "sg:menulink":"http://www.allmenus.com/ca/yuba-city/200737-long-john-silvers/menu/",
    "sg:phone":"+1 530 673 0951",
    "sg:postcode":"95991",
    "sg:province":"CA",
    "sg:tags":[
        "seafood",
        "american"
    ],
    "wof:name":"Long John Silver's",
    "wof:placetype":"venue"
},
  "geometry": {"coordinates":[-121.627752,39.141647],"type":"Point"}
}