{
  "type": "Feature",
  "properties": {
    "addr:full":"630 Fairway Dr Galt CA 95632",
    "addr:housenumber":"630",
    "addr:postcode":"95632",
    "addr:street":"Fairway Dr",
    "iso:country":"US",
    "sg:address":"630 Fairway Dr",
    "sg:city":"Galt",
    "sg:classifiers":[
        {
            "category":"Retail",
            "subcategory":"Auto Repair",
            "type":"Services"
        }
    ],
    "sg:phone":"+1 209 745 7576",
    "sg:postcode":"95632",
    "sg:province":"CA",
    "sg:tags":[
        "wrecker"
    ],
    "wof:name":"Mach 1 Towing",
    "wof:placetype":"venue"
},
  "geometry": {"coordinates":[-121.29143000000001,38.250007],"type":"Point"}
}