{
  "type": "Feature",
  "properties": {
    "addr:full":"1900 Union St San Francisco CA 94123",
    "addr:housenumber":"1900",
    "addr:postcode":"94123",
    "addr:street":"Union St",
    "iso:country":"US",
    "sg:address":"1900 Union St",
    "sg:city":"San Francisco",
    "sg:classifiers":[
        {
            "category":"Banks & Credit Unions",
            "subcategory":"Bank",
            "type":"Services"
        }
    ],
    "sg:phone":"+1 415 396 4890",
    "sg:postcode":"94123",
    "sg:province":"CA",
    "sg:website":"www.wellsfargo.com",
    "wof:name":"Wells Fargo",
    "wof:placetype":"venue"
},
  "geometry": {"coordinates":[-122.430593,37.79775],"type":"Point"}
}