{
  "type": "Feature",
  "properties": {
    "addr:full":"2751 Green River Rd Corona CA 92882",
    "addr:housenumber":"2751",
    "addr:postcode":"92882",
    "addr:street":"Green River Rd",
    "iso:country":"US",
    "sg:address":"2751 Green River Rd",
    "sg:city":"Corona",
    "sg:classifiers":[
        {
            "category":"Recreation",
            "type":"Entertainment"
        }
    ],
    "sg:phone":"+1 951 734 1888",
    "sg:postcode":"92882",
    "sg:province":"CA",
    "sg:tags":[
        "instruction",
        "gymnastic"
    ],
    "sg:website":"www.kipsgymnastics.com",
    "wof:name":"Kips Gymnastics",
    "wof:placetype":"venue"
},
  "geometry": {"coordinates":[-117.623304,33.871285],"type":"Point"}
}