{
  "type": "Feature",
  "properties": {
    "iso:country":"US",
    "sg:address":"3538 Santa Maria St",
    "sg:city":"Oceanside",
    "sg:classifiers":[
        {
            "category":"Banks & Credit Unions",
            "subcategory":"Financial Services",
            "type":"Services"
        }
    ],
    "sg:phone":"+1 760 433 5017",
    "sg:postcode":"92056",
    "sg:province":"CA",
    "sg:tags":[
        "trust",
        "management"
    ],
    "wof:name":"Worsencroft Family Trust",
    "wof:placetype":"venue"
},
  "geometry": {"coordinates":[-117.30908,33.183917],"type":"Point"}
}