{
  "type": "Feature",
  "properties": {
    "addr:full":"1472 Ave Arriba El Cajon CA 92020",
    "addr:housenumber":"1472",
    "addr:postcode":"92020",
    "addr:street":"Ave Arriba",
    "iso:country":"US",
    "sg:address":"1472 Ave Arriba",
    "sg:city":"El Cajon",
    "sg:classifiers":[
        {
            "category":"Professional",
            "type":"Services"
        }
    ],
    "sg:phone":"+1 619 588 5353",
    "sg:postcode":"92020",
    "sg:province":"CA",
    "sg:tags":[
        "writer"
    ],
    "wof:name":"Curriculum Construction",
    "wof:placetype":"venue"
},
  "geometry": {"coordinates":[-116.956824,32.775121],"type":"Point"}
}