{
  "type": "Feature",
  "properties": {
    "iso:country":"US",
    "sg:address":"1439 34th St",
    "sg:city":"Sacramento",
    "sg:classifiers":[
        {
            "category":"Real Estate",
            "subcategory":"Real Estate Agent",
            "type":"Services"
        }
    ],
    "sg:phone":"+1 916 452 4557",
    "sg:postcode":"95819",
    "sg:province":"CA",
    "wof:name":"Enterprise Real Estate",
    "wof:placetype":"venue"
},
  "geometry": {"coordinates":[-121.46313499999999,38.567455],"type":"Point"}
}