{
  "type": "Feature",
  "properties": {
    "iso:country":"US",
    "sg:address":"300 West St",
    "sg:city":"Hollister",
    "sg:classifiers":[
        {
            "category":"Social Services",
            "subcategory":"Adult Care",
            "type":"Services"
        }
    ],
    "sg:phone":"+1 831 637 9275",
    "sg:postcode":"95023",
    "sg:province":"CA",
    "sg:tags":[
        "counseling",
        "senior",
        "citizen"
    ],
    "wof:name":"Jovenes De Antano",
    "wof:placetype":"venue"
},
  "geometry": {"coordinates":[-121.405579,36.85358],"type":"Point"}
}