{
  "type": "Feature",
  "properties": {
    "addr:full":"1788 45th Ave San Francisco CA 94122",
    "addr:housenumber":"1788",
    "addr:postcode":"94122",
    "addr:street":"45Th Ave",
    "iso:country":"US",
    "sg:address":"1788 45th Ave",
    "sg:city":"San Francisco",
    "sg:classifiers":[
        {
            "category":"Building & Trades",
            "subcategory":"Construction",
            "type":"Services"
        }
    ],
    "sg:phone":"+1 415 725 3250",
    "sg:postcode":"94122",
    "sg:province":"CA",
    "sg:tags":[
        "floor",
        "laying",
        "contractor"
    ],
    "wof:name":"Delta Hardwood Floors",
    "wof:placetype":"venue"
},
  "geometry": {"coordinates":[-122.50435,37.754692],"type":"Point"}
}