{
  "type": "Feature",
  "properties": {
    "iso:country":"US",
    "sg:address":"72840 Hwy 111",
    "sg:city":"Palm Desert",
    "sg:classifiers":[
        {
            "category":"Professional",
            "type":"Services"
        }
    ],
    "sg:phone":"+1 760 773 0973",
    "sg:postcode":"92260",
    "sg:province":"CA",
    "sg:tags":[
        "establishment"
    ],
    "wof:name":"Structure",
    "wof:placetype":"venue"
},
  "geometry": {"coordinates":[-116.392351,33.721574],"type":"Point"}
}