{
  "type": "Feature",
  "properties": {
    "iso:country":"US",
    "sg:address":"29655 Strawberry Hill Dr",
    "sg:city":"Agoura Hills",
    "sg:classifiers":[
        {
            "category":"Professional",
            "subcategory":"Business Services",
            "type":"Services"
        }
    ],
    "sg:phone":"+1 818 707 0680",
    "sg:postcode":"91301",
    "sg:province":"CA",
    "wof:name":"Denson & Denson Design Assoc",
    "wof:placetype":"venue"
},
  "geometry": {"coordinates":[-118.770377,34.148673],"type":"Point"}
}