{
  "type": "Feature",
  "properties": {
    "iso:country":"US",
    "sg:address":"3330 Lomita Blvd",
    "sg:city":"Torrance",
    "sg:classifiers":[
        {
            "category":"Health Services",
            "subcategory":"Doctor",
            "type":"Services"
        }
    ],
    "sg:phone":"+1 310 784 6300",
    "sg:postcode":"90505",
    "sg:province":"CA",
    "wof:name":"Torrance Family Practice",
    "wof:placetype":"venue"
},
  "geometry": {"coordinates":[-118.344002,33.812801],"type":"Point"}
}