{
  "type": "Feature",
  "properties": {
    "addr:full":"676 S Orchard Ave Ukiah CA 95482",
    "addr:housenumber":"676",
    "addr:postcode":"ca 95482",
    "addr:street":"S Orchard Ave",
    "iso:country":"US",
    "sg:address":"676 S Orchard Ave",
    "sg:city":"Ukiah",
    "sg:classifiers":[
        {
            "category":"Social Services",
            "subcategory":"Adult Care",
            "type":"Services"
        }
    ],
    "sg:phone":"+1 707 463 1100",
    "sg:postcode":"95482",
    "sg:province":"CA",
    "sg:tags":[
        "foster"
    ],
    "wof:name":"True To Life Childrens Svc",
    "wof:placetype":"venue"
},
  "geometry": {"coordinates":[-123.19867000000001,39.145528],"type":"Point"}
}