{
  "type": "Feature",
  "properties": {
    "addr:full":"917 77th Ave Oakland CA 94621",
    "addr:housenumber":"917",
    "addr:postcode":"94621",
    "addr:street":"77Th Ave",
    "iso:country":"US",
    "sg:address":"917 77th Ave",
    "sg:city":"Oakland",
    "sg:classifiers":[
        {
            "category":"Wholesale",
            "subcategory":"Home Furnishings",
            "type":"Manufacturing & Wholesale Goods"
        }
    ],
    "sg:phone":"+1 510 569 2333",
    "sg:postcode":"94621",
    "sg:province":"CA",
    "sg:tags":[
        "mfr",
        "representative"
    ],
    "wof:name":"Metropolitan Sales Inc",
    "wof:placetype":"venue"
},
  "geometry": {"coordinates":[-122.190707,37.753533],"type":"Point"}
}