{
  "type": "Feature",
  "properties": {
    "iso:country":"US",
    "sg:address":"501 Primrose Rd",
    "sg:city":"Burlingame",
    "sg:classifiers":[
        {
            "category":"Government",
            "subcategory":"Office",
            "type":"Public Place"
        }
    ],
    "sg:phone":"+1 650 558 7203",
    "sg:postcode":"94010",
    "sg:province":"CA",
    "sg:tags":[
        "city"
    ],
    "sg:website":"www.burlingame.org",
    "wof:name":"Burlingame City Clerk",
    "wof:placetype":"venue"
},
  "geometry": {"coordinates":[-122.35107600000001,37.580467],"type":"Point"}
}