{
  "type": "Feature",
  "properties": {
    "iso:country":"US",
    "sg:address":"19655 Sherman Way",
    "sg:city":"Reseda",
    "sg:classifiers":[
        {
            "category":"Restaurant",
            "type":"Food & Drink"
        },
        {
            "category":"Bars & Pubs",
            "subcategory":"Nightclub",
            "type":"Food & Drink"
        }
    ],
    "sg:phone":"+1 818 998 8464",
    "sg:postcode":"91335",
    "sg:province":"CA",
    "sg:tags":[
        "nightlife"
    ],
    "wof:name":"Coco Bongo",
    "wof:placetype":"venue"
},
  "geometry": {"coordinates":[-118.560997,34.201],"type":"Point"}
}