{
  "type": "Feature",
  "properties": {
    "addr:full":"935 Grand Ave Grover Beach CA 93433",
    "addr:housenumber":"935",
    "addr:postcode":"93433",
    "addr:street":"Grand Ave",
    "iso:country":"US",
    "sg:address":"935 Grand Ave",
    "sg:city":"Grover Beach",
    "sg:classifiers":[
        {
            "category":"Travel",
            "subcategory":"Hotels & Motels",
            "type":"Entertainment"
        }
    ],
    "sg:phone":"+1 805 773 9702",
    "sg:postcode":"93433",
    "sg:province":"CA",
    "sg:tags":[
        "operation"
    ],
    "wof:name":"Pismo Beach Vacation Rentals",
    "wof:placetype":"venue"
},
  "geometry": {"coordinates":[-120.61987999999999,35.121574],"type":"Point"}
}