{
  "type": "Feature",
  "properties": {
    "addr:full":"21232 San Miguel Lake Forest CA 92630",
    "addr:housenumber":"21232",
    "addr:postcode":"92630",
    "addr:street":"San Miguel",
    "iso:country":"US",
    "sg:address":"21232 San Miguel",
    "sg:city":"Lake Forest",
    "sg:classifiers":[
        {
            "category":"Wholesale",
            "subcategory":"Construction Materials",
            "type":"Manufacturing & Wholesale Goods"
        }
    ],
    "sg:phone":"+1 949 837 4461",
    "sg:postcode":"92630",
    "sg:province":"CA",
    "sg:tags":[
        "marble"
    ],
    "wof:name":"Stonecliff Marble & Granite",
    "wof:placetype":"venue"
},
  "geometry": {"coordinates":[-117.68859999999999,33.654849],"type":"Point"}
}