{
  "type": "Feature",
  "properties": {
    "iso:country":"US",
    "sg:address":"4365 Executive Dr",
    "sg:city":"San Diego",
    "sg:classifiers":[
        {
            "category":"Real Estate",
            "subcategory":"Real Estate Agent",
            "type":"Services"
        }
    ],
    "sg:phone":"+1 858 546 4600",
    "sg:postcode":"92121",
    "sg:province":"CA",
    "wof:name":"C B Richard Ellis",
    "wof:placetype":"venue"
},
  "geometry": {"coordinates":[-117.211248,32.875009],"type":"Point"}
}