{
  "type": "Feature",
  "properties": {
    "addr:full":"24418 Main St Carson CA 90745",
    "addr:housenumber":"24418",
    "addr:postcode":"90745",
    "addr:street":"Main St",
    "iso:country":"US",
    "sg:address":"24418 Main St",
    "sg:city":"Carson",
    "sg:classifiers":[
        {
            "category":"Retail",
            "subcategory":"Auto Repair",
            "type":"Services"
        }
    ],
    "sg:phone":"+1 310 549 3203",
    "sg:postcode":"90745",
    "sg:province":"CA",
    "sg:tags":[
        "repairing",
        "automobile"
    ],
    "wof:name":"Southbay Pump Svc",
    "wof:placetype":"venue"
},
  "geometry": {"coordinates":[-118.27542,33.812404],"type":"Point"}
}