{
  "type": "Feature",
  "properties": {
    "iso:country":"US",
    "sg:address":"1231 Highland Ave",
    "sg:city":"National City",
    "sg:classifiers":[
        {
            "category":"Restaurant",
            "type":"Food & Drink"
        }
    ],
    "sg:phone":"+1 619 477 7080",
    "sg:postcode":"91950",
    "sg:province":"CA",
    "sg:tags":[
        "mexican"
    ],
    "wof:name":"Mariscos Choy's",
    "wof:placetype":"venue"
},
  "geometry": {"coordinates":[-117.09675,32.674012],"type":"Point"}
}