{
  "type": "Feature",
  "properties": {
    "addr:full":"17683 San Bernardino Ave Fontana CA 92335",
    "addr:housenumber":"17683",
    "addr:postcode":"92335",
    "addr:street":"San Bernardino Ave",
    "iso:country":"US",
    "sg:address":"17683 San Bernardino Ave",
    "sg:city":"Fontana",
    "sg:classifiers":[
        {
            "category":"Freight",
            "type":"Transportation"
        }
    ],
    "sg:phone":"+1 909 820 4480",
    "sg:postcode":"92335",
    "sg:province":"CA",
    "wof:name":"Elite Transportation",
    "wof:placetype":"venue"
},
  "geometry": {"coordinates":[-117.41880999999999,34.07758],"type":"Point"}
}