{
  "type": "Feature",
  "properties": {
    "addr:full":"4505 Las Virgenes Rd Ste 205 Calabasas CA 91302",
    "addr:housenumber":"4505",
    "addr:postcode":"91302",
    "addr:street":"Las Virgenes Rd Ste 205",
    "iso:country":"US",
    "sg:address":"4505 Las Virgenes Rd Ste 205",
    "sg:city":"Calabasas",
    "sg:classifiers":[
        {
            "category":"Banks & Credit Unions",
            "subcategory":"Bank",
            "type":"Services"
        }
    ],
    "sg:phone":"+1 818 878 0279",
    "sg:postcode":"91302",
    "sg:province":"CA",
    "sg:website":"www.rescuemyloan.com",
    "wof:name":"RES Advisors",
    "wof:placetype":"venue"
},
  "geometry": {"coordinates":[-118.700345,34.14003],"type":"Point"}
}