{
  "type": "Feature",
  "properties": {
    "addr:full":"12182 Maypole Dr Garden Grove CA 92840",
    "addr:postcode":"12182;92840",
    "addr:street":"Maypole Dr",
    "iso:country":"US",
    "sg:address":"12182 Maypole Dr",
    "sg:city":"Garden Grove",
    "sg:classifiers":[
        {
            "category":"Retail",
            "subcategory":"Car Wash",
            "type":"Services"
        }
    ],
    "sg:phone":"+1 714 394 6884",
    "sg:postcode":"92840",
    "sg:province":"CA",
    "sg:tags":[
        "automobile",
        "detail",
        "clean"
    ],
    "wof:name":"A1 Professional Detailing Prod",
    "wof:placetype":"venue"
},
  "geometry": {"coordinates":[-117.918245,33.784745],"type":"Point"}
}