{
  "type": "Feature",
  "properties": {
    "addr:full":"1221 E 3rd St Santa Ana CA 92701",
    "addr:housenumber":"1221",
    "addr:postcode":"92701",
    "addr:street":"E 3Rd St",
    "iso:country":"US",
    "sg:address":"1221 E 3rd St",
    "sg:city":"Santa Ana",
    "sg:classifiers":[
        {
            "category":"Autos & Motor Vehicles",
            "subcategory":"Auto Supplies",
            "type":"Retail Goods"
        }
    ],
    "sg:phone":"+1 714 953 1022",
    "sg:postcode":"92701",
    "sg:province":"CA",
    "sg:tags":[
        "tire"
    ],
    "wof:name":"7 Day Grand Tire Corp",
    "wof:placetype":"venue"
},
  "geometry": {"coordinates":[-117.851997,33.747299],"type":"Point"}
}