{
  "type": "Feature",
  "properties": {
    "iso:country":"US",
    "sg:address":"100 N Sepulveda Blvd",
    "sg:city":"El Segundo",
    "sg:classifiers":[
        {
            "category":"Professional",
            "subcategory":"Business Services",
            "type":"Services"
        }
    ],
    "sg:phone":"+1 310 426 7300",
    "sg:postcode":"90245",
    "sg:province":"CA",
    "sg:tags":[
        "interior",
        "consultant",
        "design",
        "decorator"
    ],
    "sg:website":"www.aref.com",
    "wof:name":"Aref & Assoc",
    "wof:placetype":"venue"
},
  "geometry": {"coordinates":[-118.39599200000001,33.917983],"type":"Point"}
}