{
  "type": "Feature",
  "properties": {
    "addr:full":"233 N Vermont Ave Los Angeles CA 90004",
    "addr:housenumber":"233",
    "addr:postcode":"90004",
    "addr:street":"N Vermont Ave",
    "iso:country":"US",
    "sg:address":"233 N Vermont Ave",
    "sg:city":"Los Angeles",
    "sg:classifiers":[
        {
            "category":"Autos & Motor Vehicles",
            "subcategory":"Automobile Sales",
            "type":"Retail Goods"
        }
    ],
    "sg:phone":"+1 213 251 1414",
    "sg:postcode":"90004",
    "sg:province":"CA",
    "sg:tags":[
        "car",
        "dealer"
    ],
    "sg:website":"www.vchevy.com",
    "wof:name":"Vermont Chevrolet Used",
    "wof:placetype":"venue"
},
  "geometry": {"coordinates":[-118.291758,34.075728],"type":"Point"}
}