{
  "type": "Feature",
  "properties": {
    "iso:country":"US",
    "sg:address":"12880 Beach Blvd",
    "sg:city":"Stanton",
    "sg:classifiers":[
        {
            "category":"Cinema",
            "subcategory":"Movie Rental",
            "type":"Entertainment"
        }
    ],
    "sg:phone":"+1 714 895 3878",
    "sg:postcode":"90680",
    "sg:province":"CA",
    "sg:tags":[
        "leasing",
        "video",
        "disc",
        "tape"
    ],
    "wof:name":"Video Town",
    "wof:placetype":"venue"
},
  "geometry": {"coordinates":[-117.992722,33.775483],"type":"Point"}
}