{
  "type": "Feature",
  "properties": {
    "addr:full":"815 Almar Ave Ste 3 Santa Cruz CA 95060",
    "addr:housenumber":"815",
    "addr:postcode":"95060",
    "addr:street":"Almar Ave Ste 3",
    "iso:country":"US",
    "sg:address":"815 Almar Ave Ste 3",
    "sg:city":"Santa Cruz",
    "sg:classifiers":[
        {
            "category":"Retail",
            "subcategory":"Auto Repair",
            "type":"Services"
        }
    ],
    "sg:phone":"+1 831 429 8711",
    "sg:postcode":"95060",
    "sg:province":"CA",
    "sg:website":"www.evolutionautomotive.net",
    "wof:name":"Evolution Automotive",
    "wof:placetype":"venue"
},
  "geometry": {"coordinates":[-122.044175,36.959663],"type":"Point"}
}