{
  "type": "Feature",
  "properties": {
    "addr:full":"95 Scripps Drive Sacramento CA 95825",
    "addr:housenumber":"95",
    "addr:postcode":"95825",
    "addr:street":"Scripps Drive",
    "iso:country":"US",
    "sg:address":"95 Scripps Drive",
    "sg:city":"Sacramento",
    "sg:classifiers":[
        {
            "category":"Health Services",
            "subcategory":"Doctor",
            "type":"Services"
        },
        {
            "category":"Personal",
            "subcategory":"Hair Removal",
            "type":"Services"
        }
    ],
    "sg:phone":"+1 916 929 1833",
    "sg:postcode":"95825",
    "sg:province":"CA",
    "sg:website":"www.anuyu.com",
    "wof:name":"Bruner Jack G MD",
    "wof:placetype":"venue"
},
  "geometry": {"coordinates":[-121.409727,38.571758],"type":"Point"}
}