{
  "type": "Feature",
  "properties": {
    "addr:full":"1660 Portola Ave Livermore CA 94551",
    "addr:housenumber":"1660",
    "addr:postcode":"94551",
    "addr:street":"Portola Ave",
    "iso:country":"US",
    "sg:address":"1660 Portola Ave",
    "sg:city":"Livermore",
    "sg:classifiers":[
        {
            "category":"Organizations",
            "subcategory":"Religious Organization",
            "type":"Services"
        }
    ],
    "sg:phone":"+1 925 443 4283",
    "sg:postcode":"94551",
    "sg:province":"CA",
    "wof:name":"Shepherd's Gate",
    "wof:placetype":"venue"
},
  "geometry": {"coordinates":[-121.778723,37.692687],"type":"Point"}
}