{
  "type": "Feature",
  "properties": {
    "iso:country":"US",
    "sg:address":"14922 Moran St Ste B",
    "sg:city":"Westminster",
    "sg:classifiers":[
        {
            "category":"Communications",
            "subcategory":"Film & Video Production",
            "type":"Services"
        }
    ],
    "sg:phone":"+1 714 891 5665",
    "sg:postcode":"92683",
    "sg:province":"CA",
    "sg:tags":[
        "tv",
        "radio",
        "services-commercial",
        "companies-film"
    ],
    "wof:name":"Art D'orient",
    "wof:placetype":"venue"
},
  "geometry": {"coordinates":[-117.96739700000001,33.74669],"type":"Point"}
}