{
  "type": "Feature",
  "properties": {
    "addr:full":"7001 Stockton Ave El Cerrito CA 94530",
    "addr:housenumber":"7001",
    "addr:postcode":"94530",
    "addr:street":"Stockton Ave",
    "iso:country":"US",
    "sg:address":"7001 Stockton Ave",
    "sg:city":"El Cerrito",
    "sg:classifiers":[
        {
            "category":"Health Services",
            "subcategory":"Doctor",
            "type":"Services"
        }
    ],
    "sg:phone":"+1 510 524 4633",
    "sg:postcode":"94530",
    "sg:province":"CA",
    "sg:tags":[
        "dentist"
    ],
    "wof:name":"Edward M Matsuishi Inc",
    "wof:placetype":"venue"
},
  "geometry": {"coordinates":[-122.299412,37.910598],"type":"Point"}
}