{
  "type": "Feature",
  "properties": {
    "addr:full":"15627 Brookhurst St Westminster CA 92683",
    "addr:housenumber":"15627",
    "addr:postcode":"92683",
    "addr:street":"Brookhurst St",
    "iso:country":"US",
    "sg:address":"15627 Brookhurst St",
    "sg:city":"Westminster",
    "sg:classifiers":[
        {
            "category":"Health Services",
            "subcategory":"Optometrist",
            "type":"Services"
        }
    ],
    "sg:phone":"+1 714 418 0190",
    "sg:postcode":"92683",
    "sg:province":"CA",
    "sg:tags":[
        "ophthalmologist"
    ],
    "wof:name":"Chau Nguyen OD",
    "wof:placetype":"venue"
},
  "geometry": {"coordinates":[-117.95500199999999,33.736],"type":"Point"}
}