{
  "type": "Feature",
  "properties": {
    "addr:full":"398 E Santa Clara St San Jose CA 95113",
    "addr:housenumber":"398",
    "addr:postcode":"95113",
    "addr:street":"E Santa Clara St",
    "iso:country":"US",
    "sg:address":"398 E Santa Clara St",
    "sg:city":"San Jose",
    "sg:classifiers":[
        {
            "category":"Professional",
            "type":"Services"
        }
    ],
    "sg:phone":"+1 408 971 1333",
    "sg:postcode":"95113",
    "sg:province":"CA",
    "sg:tags":[
        "establishment"
    ],
    "wof:name":"VMAUSA",
    "wof:placetype":"venue"
},
  "geometry": {"coordinates":[-121.883145,37.339695],"type":"Point"}
}