{
  "type": "Feature",
  "properties": {
    "addr:full":"269 N Main St Willits CA 95490",
    "addr:housenumber":"269",
    "addr:postcode":"95490",
    "addr:street":"N Main St",
    "iso:country":"US",
    "sg:address":"269 N Main St",
    "sg:city":"Willits",
    "sg:classifiers":[
        {
            "category":"Organizations",
            "subcategory":"Community Association",
            "type":"Services"
        }
    ],
    "sg:phone":"+1 707 459 0151",
    "sg:postcode":"95490",
    "sg:province":"CA",
    "sg:tags":[
        "fraternal"
    ],
    "wof:name":"Odd Fellows Little Lake Lodge",
    "wof:placetype":"venue"
},
  "geometry": {"coordinates":[-123.354495,39.416155],"type":"Point"}
}