{
  "type": "Feature",
  "properties": {
    "addr:full":"5423 Cmt Borde San Diego CA 92108",
    "addr:postcode":"5423;92108",
    "addr:street":"Cmt Borde",
    "iso:country":"US",
    "sg:address":"5423 Cmt Borde",
    "sg:city":"San Diego",
    "sg:classifiers":[
        {
            "category":"Professional",
            "subcategory":"Management & Consulting",
            "type":"Services"
        }
    ],
    "sg:phone":"+1 619 464 2584",
    "sg:postcode":"92108",
    "sg:province":"CA",
    "sg:tags":[
        "training",
        "sales"
    ],
    "sg:website":"www.gehegan.com",
    "wof:name":"Gehegan & Assoc",
    "wof:placetype":"venue"
},
  "geometry": {"coordinates":[-117.10088500000001,32.776105],"type":"Point"}
}