{
  "type": "Feature",
  "properties": {
    "addr:full":"969 Edgewater Blvd Foster City CA 94404",
    "addr:housenumber":"969",
    "addr:postcode":"94404",
    "addr:street":"Edgewater Blvd",
    "iso:country":"US",
    "sg:address":"969 Edgewater Blvd",
    "sg:city":"Foster City",
    "sg:classifiers":[
        {
            "category":"Professional",
            "subcategory":"Detective & Security Services",
            "type":"Services"
        }
    ],
    "sg:phone":"+1 650 572 1641",
    "sg:postcode":"94404",
    "sg:province":"CA",
    "sg:tags":[
        "guard",
        "patrol"
    ],
    "wof:name":"Scott Security Svc",
    "wof:placetype":"venue"
},
  "geometry": {"coordinates":[-122.272463,37.545535],"type":"Point"}
}