{
  "type": "Feature",
  "properties": {
    "iso:country":"US",
    "sg:address":"2187 Newcastle Ave",
    "sg:city":"Cardiff By The Sea",
    "sg:classifiers":[
        {
            "category":"Professional",
            "subcategory":"Management & Consulting",
            "type":"Services"
        }
    ],
    "sg:phone":"+1 760 753 8000",
    "sg:postcode":"92007",
    "sg:province":"CA",
    "sg:tags":[
        "business"
    ],
    "wof:name":"SPS Associates",
    "wof:placetype":"venue"
},
  "geometry": {"coordinates":[-117.280407,33.020288],"type":"Point"}
}