{
  "type": "Feature",
  "properties": {
    "iso:country":"US",
    "sg:address":"3375 Scott Blvd",
    "sg:city":"Santa Clara",
    "sg:classifiers":[
        {
            "category":"Professional",
            "subcategory":"Computer Services",
            "type":"Services"
        }
    ],
    "sg:phone":"+1 408 980 0090",
    "sg:postcode":"95050",
    "sg:province":"CA",
    "sg:tags":[
        "hardware",
        "provider",
        "internet",
        "software"
    ],
    "wof:name":"Quantum Intelligence",
    "wof:placetype":"venue"
},
  "geometry": {"coordinates":[-121.98421399999999,37.380669],"type":"Point"}
}