{
  "type": "Feature",
  "properties": {
    "addr:full":"777 Encina Ave Imperial Beach CA 91932",
    "addr:housenumber":"777",
    "addr:postcode":"91932",
    "addr:street":"Encina Ave",
    "iso:country":"US",
    "sg:address":"777 Encina Ave",
    "sg:city":"Imperial Beach",
    "sg:classifiers":[
        {
            "category":"Building & Trades",
            "subcategory":"Electrical",
            "type":"Services"
        }
    ],
    "sg:phone":"+1 619 424 3014",
    "sg:postcode":"91932",
    "sg:province":"CA",
    "sg:tags":[
        "communications",
        "contractor"
    ],
    "wof:name":"American Wireless",
    "wof:placetype":"venue"
},
  "geometry": {"coordinates":[-117.116579,32.580123],"type":"Point"}
}