{
  "type": "Feature",
  "properties": {
    "iso:country":"US",
    "sg:address":"4119 Overend Ave",
    "sg:city":"Richmond",
    "sg:classifiers":[
        {
            "category":"Professional",
            "type":"Services"
        }
    ],
    "sg:phone":"+1 510 233 2467",
    "sg:postcode":"94804",
    "sg:province":"CA",
    "wof:name":"Pham",
    "wof:placetype":"venue"
},
  "geometry": {"coordinates":[-122.329883,37.926412],"type":"Point"}
}