{
  "type": "Feature",
  "properties": {
    "iso:country":"US",
    "sg:address":"300 W Manchester Blvd",
    "sg:city":"Inglewood",
    "sg:classifiers":[
        {
            "category":"Shopping",
            "subcategory":"Department Store",
            "type":"Retail Goods"
        }
    ],
    "sg:phone":"+1 310 671 7030",
    "sg:postcode":"90301",
    "sg:province":"CA",
    "sg:tags":[
        "shop"
    ],
    "wof:name":"Delta Discounts",
    "wof:placetype":"venue"
},
  "geometry": {"coordinates":[-118.361183,33.961676],"type":"Point"}
}