{
  "type": "Feature",
  "properties": {
    "iso:country":"US",
    "sg:address":"4105 Atlantic Ave",
    "sg:city":"Long Beach",
    "sg:classifiers":[
        {
            "category":"Shopping",
            "subcategory":"Mobile Phones",
            "type":"Retail Goods"
        }
    ],
    "sg:phone":"+1 562 989 1333",
    "sg:postcode":"90807",
    "sg:province":"CA",
    "wof:name":"Affordable Portables",
    "wof:placetype":"venue"
},
  "geometry": {"coordinates":[-118.184998,33.831799],"type":"Point"}
}