{
  "type": "Feature",
  "properties": {
    "addr:full":"121 E Arrow Hwy San Dimas CA 91773",
    "addr:housenumber":"121",
    "addr:postcode":"91773",
    "addr:street":"E Arrow Hwy",
    "iso:country":"US",
    "sg:address":"121 E Arrow Hwy",
    "sg:city":"San Dimas",
    "sg:classifiers":[
        {
            "category":"Building & Trades",
            "subcategory":"Pest Control",
            "type":"Services"
        }
    ],
    "sg:phone":"+1 626 331 0032",
    "sg:postcode":"91773",
    "sg:province":"CA",
    "wof:name":"Gaston Termite Control",
    "wof:placetype":"venue"
},
  "geometry": {"coordinates":[-117.803111,34.103033],"type":"Point"}
}