{
  "type": "Feature",
  "properties": {
    "addr:full":"121 Tunstead Ave San Anselmo CA 94960",
    "addr:housenumber":"121",
    "addr:postcode":"94960",
    "addr:street":"Tunstead Ave",
    "iso:country":"US",
    "sg:address":"121 Tunstead Ave",
    "sg:city":"San Anselmo",
    "sg:classifiers":[
        {
            "category":"Shopping",
            "subcategory":"Computers & Home Electronics",
            "type":"Retail Goods"
        }
    ],
    "sg:phone":"+1 415 454 1532",
    "sg:postcode":"94960",
    "sg:province":"CA",
    "sg:tags":[
        "equipment",
        "metal",
        "locating"
    ],
    "wof:name":"Jack's Drug Store-Metal Detect",
    "wof:placetype":"venue"
},
  "geometry": {"coordinates":[-122.56517599999999,37.973553],"type":"Point"}
}