{
  "type": "Feature",
  "properties": {
    "iso:country":"US",
    "sg:address":"121 Tunstead Ave",
    "sg:city":"San Anselmo",
    "sg:classifiers":[
        {
            "category":"Shopping",
            "subcategory":"Computers & Home Electronics",
            "type":"Retail Goods"
        }
    ],
    "sg:phone":"+1 415 454 1532",
    "sg:postcode":"94960",
    "sg:province":"CA",
    "sg:tags":[
        "equipment",
        "metal",
        "locating"
    ],
    "wof:name":"Jack's Drug Store-Metal Detect",
    "wof:placetype":"venue"
},
  "geometry": {"coordinates":[-122.565176,37.973553],"type":"Point"}
}