{
  "type": "Feature",
  "properties": {
    "addr:full":"1756 Manhattan Beach Blvd Manhattan Beach CA 90266",
    "addr:housenumber":"1756",
    "addr:postcode":"90266",
    "addr:street":"Manhattan Beach Blvd",
    "iso:country":"US",
    "sg:address":"1756 Manhattan Beach Blvd",
    "sg:city":"Manhattan Beach",
    "sg:classifiers":[
        {
            "category":"Wholesale",
            "subcategory":"Home Furnishings",
            "type":"Manufacturing & Wholesale Goods"
        }
    ],
    "sg:phone":"+1 310 372 5357",
    "sg:postcode":"90266",
    "sg:province":"CA",
    "sg:tags":[
        "blind",
        "shade"
    ],
    "sg:website":"www.clearviewsun.com",
    "wof:name":"Clearview Sun Control",
    "wof:placetype":"venue"
},
  "geometry": {"coordinates":[-118.381766,33.887284],"type":"Point"}
}