{
  "type": "Feature",
  "properties": {
    "iso:country":"US",
    "sg:address":"5851 Thille St",
    "sg:city":"Ventura",
    "sg:classifiers":[
        {
            "category":"Insurance",
            "subcategory":"Insurance Agent",
            "type":"Services"
        }
    ],
    "sg:phone":"+1 805 654 6820",
    "sg:postcode":"93003",
    "sg:province":"CA",
    "sg:website":"www.fickewirth.com",
    "wof:name":"Fickewirth & Assoc",
    "wof:placetype":"venue"
},
  "geometry": {"coordinates":[-119.21414900000001,34.267955],"type":"Point"}
}