{
  "type": "Feature",
  "properties": {
    "addr:full":"7532 Sunset Ave Fair Oaks CA 95628",
    "addr:housenumber":"7532",
    "addr:postcode":"95628",
    "addr:street":"Sunset Ave",
    "iso:country":"US",
    "sg:address":"7532 Sunset Ave",
    "sg:city":"Fair Oaks",
    "sg:classifiers":[
        {
            "category":"Building & Trades",
            "subcategory":"Landscaping Services",
            "type":"Services"
        }
    ],
    "sg:phone":"+1 916 536 1005",
    "sg:postcode":"95628",
    "sg:province":"CA",
    "sg:tags":[
        "landscape"
    ],
    "wof:name":"Hortus Landscape Architect",
    "wof:placetype":"venue"
},
  "geometry": {"coordinates":[-121.288121,38.652615],"type":"Point"}
}