{
  "type": "Feature",
  "properties": {
    "addr:full":"14365 E 14th St San Leandro CA 94578",
    "addr:housenumber":"14365",
    "addr:postcode":"94578",
    "addr:street":"E 14Th St",
    "iso:country":"US",
    "sg:address":"14365 E 14th St",
    "sg:city":"San Leandro",
    "sg:classifiers":[
        {
            "category":"Professional",
            "subcategory":"Accounting & Tax Preparation",
            "type":"Services"
        }
    ],
    "sg:phone":"+1 510 351 2334",
    "sg:postcode":"94578",
    "sg:province":"CA",
    "sg:tags":[
        "return",
        "filing"
    ],
    "wof:name":"Joyeria Rochcitas",
    "wof:placetype":"venue"
},
  "geometry": {"coordinates":[-122.13656400000001,37.710935],"type":"Point"}
}