{
  "type": "Feature",
  "properties": {
    "iso:country":"US",
    "sg:address":"14365 E 14th St",
    "sg:city":"San Leandro",
    "sg:classifiers":[
        {
            "category":"Professional",
            "subcategory":"Accounting & Tax Preparation",
            "type":"Services"
        }
    ],
    "sg:phone":"+1 510 351 2334",
    "sg:postcode":"94578",
    "sg:province":"CA",
    "sg:tags":[
        "return",
        "filing"
    ],
    "wof:name":"Joyeria Rochcitas",
    "wof:placetype":"venue"
},
  "geometry": {"coordinates":[-122.136564,37.710935],"type":"Point"}
}