{
  "type": "Feature",
  "properties": {
    "addr:full":"2000 Powell St Ste 1286 Emeryville CA 94608",
    "addr:housenumber":"2000",
    "addr:postcode":"94608",
    "addr:street":"Powell St Ste 1286",
    "iso:country":"US",
    "sg:address":"2000 Powell St Ste 1286",
    "sg:city":"Emeryville",
    "sg:classifiers":[
        {
            "category":"Professional",
            "subcategory":"Lawyer & Legal Services",
            "type":"Services"
        }
    ],
    "sg:phone":"+1 510 597 1775",
    "sg:postcode":"94608",
    "sg:province":"CA",
    "wof:name":"Schwartz Amitai Law Offices of",
    "wof:placetype":"venue"
},
  "geometry": {"coordinates":[-122.285004,37.838001],"type":"Point"}
}