{
  "type": "Feature",
  "properties": {
    "addr:full":"520 San Ramon Valley Blvd Danville CA 94583",
    "addr:housenumber":"520",
    "addr:postcode":"94583",
    "addr:street":"San Ramon Valley Blvd",
    "iso:country":"US",
    "sg:address":"520 San Ramon Valley Blvd",
    "sg:city":"Danville",
    "sg:classifiers":[
        {
            "category":"Personal",
            "subcategory":"Beauty Salon",
            "type":"Services"
        }
    ],
    "sg:phone":"+1 925 362 9912",
    "sg:postcode":"94583",
    "sg:province":"CA",
    "wof:name":"Nina Yegany",
    "wof:placetype":"venue"
},
  "geometry": {"coordinates":[-121.99653499999999,37.818864],"type":"Point"}
}