{
  "type": "Feature",
  "properties": {
    "addr:full":"46 Geary St San Francisco CA 94108",
    "addr:housenumber":"46",
    "addr:postcode":"94108",
    "addr:street":"Geary St",
    "iso:country":"US",
    "sg:address":"46 Geary St",
    "sg:city":"San Francisco",
    "sg:classifiers":[
        {
            "category":"Recreation",
            "subcategory":"Dance Hall",
            "type":"Entertainment"
        }
    ],
    "sg:postcode":"94108",
    "sg:province":"CA",
    "sg:tags":[
        "club"
    ],
    "wof:name":"Loft 46",
    "wof:placetype":"venue"
},
  "geometry": {"coordinates":[-122.40429899999999,37.788123],"type":"Point"}
}