{
  "type": "Feature",
  "properties": {
    "addr:full":"1020 3rd St Santa Rosa CA 95404",
    "addr:housenumber":"1020",
    "addr:postcode":"ca 95404",
    "addr:street":"3Rd St",
    "iso:country":"US",
    "sg:address":"1020 3rd St",
    "sg:city":"Santa Rosa",
    "sg:classifiers":[
        {
            "category":"Social Services",
            "type":"Services"
        }
    ],
    "sg:phone":"+1 707 578 3924",
    "sg:postcode":"95404",
    "sg:province":"CA",
    "sg:tags":[
        "organization",
        "welfare"
    ],
    "wof:name":"Salvation Army",
    "wof:placetype":"venue"
},
  "geometry": {"coordinates":[-122.70617900000001,38.442849],"type":"Point"}
}