{
  "type": "Feature",
  "properties": {
    "iso:country":"US",
    "sg:address":"17890 Castleton St",
    "sg:city":"City Of Industry",
    "sg:classifiers":[
        {
            "category":"Professional",
            "subcategory":"Lawyer & Legal Services",
            "type":"Services"
        }
    ],
    "sg:phone":"+1 626 810 7572",
    "sg:postcode":"91748",
    "sg:province":"CA",
    "sg:tags":[
        "attorney"
    ],
    "sg:website":"www.mjzhanglaw.com",
    "wof:name":"Michael J Zhang Law Office",
    "wof:placetype":"venue"
},
  "geometry": {"coordinates":[-117.91953599999999,33.993726],"type":"Point"}
}