{
  "type": "Feature",
  "properties": {
    "addr:full":"3880 Old Santa Rita Rd Pleasanton CA 94588",
    "addr:housenumber":"3880",
    "addr:postcode":"94588",
    "addr:street":"Old Santa Rita Rd",
    "iso:country":"US",
    "sg:address":"3880 Old Santa Rita Rd",
    "sg:city":"Pleasanton",
    "sg:classifiers":[
        {
            "category":"Autos & Motor Vehicles",
            "subcategory":"Fuel & Gas Station",
            "type":"Retail Goods"
        },
        {
            "category":"Retail",
            "subcategory":"Auto Repair",
            "type":"Services"
        }
    ],
    "sg:phone":"+1 925 463 1622",
    "sg:postcode":"94588",
    "sg:province":"CA",
    "sg:tags":[
        "automotive",
        "sale",
        "radiator"
    ],
    "wof:name":"Pleasanton Auto Service And Repair",
    "wof:placetype":"venue"
},
  "geometry": {"coordinates":[-121.878798,37.699444],"type":"Point"}
}