{
  "type": "Feature",
  "properties": {
    "addr:full":"10618 S Inglewood Ave Inglewood CA 90304",
    "addr:housenumber":"10618",
    "addr:postcode":"90304",
    "addr:street":"S Inglewood Ave",
    "iso:country":"US",
    "sg:address":"10618 S Inglewood Ave",
    "sg:city":"Inglewood",
    "sg:classifiers":[
        {
            "category":"Professional",
            "subcategory":"Lawyer & Legal Services",
            "type":"Services"
        }
    ],
    "sg:phone":"+1 310 677 1000",
    "sg:postcode":"90304",
    "sg:province":"CA",
    "sg:tags":[
        "notary"
    ],
    "wof:name":"La Frontera Corp",
    "wof:placetype":"venue"
},
  "geometry": {"coordinates":[-118.361,33.9398],"type":"Point"}
}