{
  "type": "Feature",
  "properties": {
    "iso:country":"US",
    "sg:address":"160 E Broadway Ave",
    "sg:city":"Atwater",
    "sg:classifiers":[
        {
            "category":"Home & Garden",
            "subcategory":"Building Materials",
            "type":"Retail Goods"
        }
    ],
    "sg:phone":"+1 209 357 2679",
    "sg:postcode":"95301",
    "sg:province":"CA",
    "sg:tags":[
        "windows"
    ],
    "wof:name":"Alliance Building Products",
    "wof:placetype":"venue"
},
  "geometry": {"coordinates":[-120.595571,37.342233],"type":"Point"}
}