{
  "type": "Feature",
  "properties": {
    "addr:full":"6212 Claremont Ave Oakland CA 94618",
    "addr:housenumber":"6212",
    "addr:postcode":"94618",
    "addr:street":"Claremont Ave",
    "iso:country":"US",
    "sg:address":"6212 Claremont Ave",
    "sg:city":"Oakland",
    "sg:classifiers":[
        {
            "category":"Taxi",
            "type":"Transportation"
        }
    ],
    "sg:phone":"+1 510 547 0211",
    "sg:postcode":"94618",
    "sg:province":"CA",
    "wof:name":"A1 Airport Express Taxi",
    "wof:placetype":"venue"
},
  "geometry": {"coordinates":[-122.25212000000001,37.849635],"type":"Point"}
}