{
  "type": "Feature",
  "properties": {
    "addr:full":"1283 W El Camino Real Sunnyvale CA 94087",
    "addr:housenumber":"1283",
    "addr:postcode":"94087",
    "addr:street":"W El Camino Real",
    "iso:country":"US",
    "sg:address":"1283 W El Camino Real",
    "sg:city":"Sunnyvale",
    "sg:classifiers":[
        {
            "category":"Personal",
            "subcategory":"Beauty Salon",
            "type":"Services"
        }
    ],
    "sg:phone":"+1 650 968 0767",
    "sg:postcode":"94087",
    "sg:province":"CA",
    "sg:tags":[
        "hair"
    ],
    "wof:name":"Lisa's Perfect Cuts",
    "wof:placetype":"venue"
},
  "geometry": {"coordinates":[-122.059352,37.375156],"type":"Point"}
}