{
  "type": "Feature",
  "properties": {
    "iso:country":"US",
    "sg:address":"6885 Palm Ave",
    "sg:city":"San Bernardino",
    "sg:classifiers":[
        {
            "category":"Home & Garden",
            "subcategory":"Building Materials",
            "type":"Retail Goods"
        },
        {
            "category":"Professional",
            "type":"Services"
        }
    ],
    "sg:phone":"+1 909 880 2480",
    "sg:postcode":"92407",
    "sg:province":"CA",
    "sg:tags":[
        "lumber"
    ],
    "wof:name":"Hardwood Homes Skyline Project",
    "wof:placetype":"venue"
},
  "geometry": {"coordinates":[-117.352977,34.204255],"type":"Point"}
}