{
  "type": "Feature",
  "properties": {
    "addr:full":"1513 San Jose St Oceanside CA 92058",
    "addr:housenumber":"1513",
    "addr:postcode":"92058",
    "addr:street":"San Jose St",
    "iso:country":"US",
    "sg:address":"1513 San Jose St",
    "sg:city":"Oceanside",
    "sg:classifiers":[
        {
            "category":"Organizations",
            "subcategory":"Political Organization",
            "type":"Services"
        }
    ],
    "sg:phone":"+1 760 721 3555",
    "sg:postcode":"92058",
    "sg:province":"CA",
    "wof:name":"Citizens For-Better Oceanside",
    "wof:placetype":"venue"
},
  "geometry": {"coordinates":[-117.37985999999999,33.212559],"type":"Point"}
}