{
  "type": "Feature",
  "properties": {
    "iso:country":"US",
    "sg:address":"4301 Industrial Way",
    "sg:city":"Benicia",
    "sg:classifiers":[
        {
            "category":"Wholesale",
            "subcategory":"Wine & Distilled Alcoholic Beverages",
            "type":"Manufacturing & Wholesale Goods"
        }
    ],
    "sg:phone":"+1 707 745 8500",
    "sg:postcode":"94510",
    "sg:province":"CA",
    "sg:website":"www.henrywinegroup.com",
    "wof:name":"Henry Wine Group",
    "wof:placetype":"venue"
},
  "geometry": {"coordinates":[-122.118506,38.074596],"type":"Point"}
}