{
  "type": "Feature",
  "properties": {
    "addr:full":"1417 W Whittier Blvd La Habra CA 90631",
    "addr:housenumber":"1417",
    "addr:postcode":"90631",
    "addr:street":"W Whittier Blvd",
    "iso:country":"US",
    "sg:address":"1417 W Whittier Blvd",
    "sg:city":"La Habra",
    "sg:classifiers":[
        {
            "category":"Wholesale",
            "subcategory":"Sporting Goods",
            "type":"Manufacturing & Wholesale Goods"
        }
    ],
    "sg:phone":"+1 562 690 6238",
    "sg:postcode":"90631",
    "sg:province":"CA",
    "wof:name":"Diversion Board Shop",
    "wof:placetype":"venue"
},
  "geometry": {"coordinates":[-117.96071600000001,33.939237],"type":"Point"}
}