{
  "type": "Feature",
  "properties": {
    "iso:country":"US",
    "sg:address":"15435 Jeffrey Rd Ste 124",
    "sg:city":"Irvine",
    "sg:classifiers":[
        {
            "category":"Personal",
            "subcategory":"Beauty Salon",
            "type":"Services"
        }
    ],
    "sg:phone":"+1 949 786 5678",
    "sg:postcode":"92618",
    "sg:province":"CA",
    "sg:tags":[
        "hair"
    ],
    "sg:website":"salontm2.com",
    "wof:name":"Salon TM:2",
    "wof:placetype":"venue"
},
  "geometry": {"coordinates":[-117.777922,33.680381],"type":"Point"}
}