{
  "type": "Feature",
  "properties": {
    "iso:country":"US",
    "sg:address":"304 N Palm Canyon Dr",
    "sg:city":"Palm Springs",
    "sg:classifiers":[
        {
            "category":"Shopping",
            "subcategory":"Clothing, Apparel, & Fashions",
            "type":"Retail Goods"
        }
    ],
    "sg:phone":"+1 760 864 8755",
    "sg:postcode":"92262",
    "sg:province":"CA",
    "sg:tags":[
        "men's",
        "clothing",
        "women's"
    ],
    "wof:name":"Tashana Boutique",
    "wof:placetype":"venue"
},
  "geometry": {"coordinates":[-116.546836,33.826973],"type":"Point"}
}