{
  "type": "Feature",
  "properties": {
    "iso:country":"US",
    "sg:address":"1221 Post Rd",
    "sg:city":"Oakdale",
    "sg:classifiers":[
        {
            "category":"Building & Trades",
            "subcategory":"Landscaping Services",
            "type":"Services"
        }
    ],
    "sg:phone":"+1 209 845 9914",
    "sg:postcode":"95361",
    "sg:province":"CA",
    "sg:tags":[
        "landscape"
    ],
    "wof:name":"Hamilton Landscape",
    "wof:placetype":"venue"
},
  "geometry": {"coordinates":[-120.83198899999999,37.753074],"type":"Point"}
}