{
  "type": "Feature",
  "properties": {
    "addr:full":"1150 E 6th St Beaumont CA 92223",
    "addr:housenumber":"1150",
    "addr:postcode":"92223",
    "addr:street":"E 6Th St",
    "iso:country":"US",
    "sg:address":"1150 E 6th St",
    "sg:city":"Beaumont",
    "sg:classifiers":[
        {
            "category":"Food & Beverages",
            "subcategory":"Groceries & Convenience Stores",
            "type":"Retail Goods"
        }
    ],
    "sg:phone":"+1 909 991 1421",
    "sg:postcode":"92223",
    "sg:province":"CA",
    "wof:name":"Dollar Power",
    "wof:placetype":"venue"
},
  "geometry": {"coordinates":[-116.966718,33.929409],"type":"Point"}
}