{
  "type": "Feature",
  "properties": {
    "addr:full":"37 Bayview Road Castroville CA 95012",
    "addr:housenumber":"37",
    "addr:postcode":"95012",
    "addr:street":"Bayview Road",
    "iso:country":"US",
    "sg:address":"37 Bayview Road",
    "sg:city":"Castroville",
    "sg:classifiers":[
        {
            "category":"Retail",
            "subcategory":"Auto Repair",
            "type":"Services"
        }
    ],
    "sg:phone":"+1 831 632 2502",
    "sg:postcode":"95012",
    "sg:province":"CA",
    "wof:name":"The Shop",
    "wof:placetype":"venue"
},
  "geometry": {"coordinates":[-121.720294,36.807081],"type":"Point"}
}