{
  "type": "Feature",
  "properties": {
    "addr:full":"4160 S Broadway Los Angeles CA 90037",
    "addr:housenumber":"4160",
    "addr:postcode":"90037",
    "addr:street":"S Broadway",
    "iso:country":"US",
    "sg:address":"4160 S Broadway",
    "sg:city":"Los Angeles",
    "sg:classifiers":[
        {
            "category":"Shopping",
            "subcategory":"Shoes",
            "type":"Retail Goods"
        }
    ],
    "sg:phone":"+1 323 235 0799",
    "sg:postcode":"90037",
    "sg:province":"CA",
    "wof:name":"King David Shoes",
    "wof:placetype":"venue"
},
  "geometry": {"coordinates":[-118.27827499999999,34.007583],"type":"Point"}
}