{
  "type": "Feature",
  "properties": {
    "addr:full":"1650 E Daily Dr Camarillo CA 93010",
    "addr:housenumber":"1650",
    "addr:postcode":"93010",
    "addr:street":"E Daily Dr",
    "iso:country":"US",
    "sg:address":"1650 E Daily Dr",
    "sg:city":"Camarillo",
    "sg:classifiers":[
        {
            "category":"Restaurant",
            "type":"Food & Drink"
        }
    ],
    "sg:menulink":"http://www.allmenus.com/ca/camarillo/178636-jack-in-the-box/menu/",
    "sg:phone":"+1 805 484 9443",
    "sg:postcode":"93010",
    "sg:province":"CA",
    "sg:tags":[
        "burger",
        "american"
    ],
    "wof:name":"Jack in the Box",
    "wof:placetype":"venue"
},
  "geometry": {"coordinates":[-119.049139,34.218175],"type":"Point"}
}