{
  "type": "Feature",
  "properties": {
    "iso:country":"US",
    "sg:address":"13310 Pine Gulch Ct",
    "sg:city":"Sutter Creek",
    "sg:classifiers":[
        {
            "category":"Shopping",
            "type":"Retail Goods"
        }
    ],
    "sg:phone":"+1 209 267 5085",
    "sg:postcode":"95685",
    "sg:province":"CA",
    "sg:tags":[
        "merchandise"
    ],
    "wof:name":"Fortune Alley",
    "wof:placetype":"venue"
},
  "geometry": {"coordinates":[-120.764331,38.403416],"type":"Point"}
}