{
  "type": "Feature",
  "properties": {
    "iso:country":"US",
    "sg:address":"19075 Moroni Ln",
    "sg:city":"Grass Valley",
    "sg:classifiers":[
        {
            "category":"Building & Trades",
            "subcategory":"Construction",
            "type":"Services"
        }
    ],
    "sg:phone":"+1 530 268 9945",
    "sg:postcode":"95949",
    "sg:province":"CA",
    "sg:tags":[
        "excavating",
        "contractor"
    ],
    "wof:name":"Sta-Bull Fence Co",
    "wof:placetype":"venue"
},
  "geometry": {"coordinates":[-121.035254,39.094756],"type":"Point"}
}