{
  "type": "Feature",
  "properties": {
    "iso:country":"US",
    "sg:address":"26800 Mulholland Hwy",
    "sg:city":"Calabasas",
    "sg:classifiers":[
        {
            "category":"Organizations",
            "subcategory":"Religious Organization",
            "type":"Services"
        }
    ],
    "sg:phone":"+1 310 880 5300",
    "sg:postcode":"91302",
    "sg:province":"CA",
    "sg:tags":[
        "church"
    ],
    "wof:name":"Chr Universal & Truimphant",
    "wof:placetype":"venue"
},
  "geometry": {"coordinates":[-118.70908900000001,34.104774],"type":"Point"}
}