{
  "type": "Feature",
  "properties": {
    "iso:country":"US",
    "sg:address":"954 W el Camino Real",
    "sg:city":"Sunnyvale",
    "sg:classifiers":[
        {
            "category":"Shopping",
            "subcategory":"Clothing, Apparel, & Fashions",
            "type":"Retail Goods"
        }
    ],
    "sg:phone":"+1 408 245 8720",
    "sg:postcode":"94087",
    "sg:province":"CA",
    "sg:tags":[
        "theatrical",
        "costume"
    ],
    "wof:name":"Debbie Lyn's Costumes",
    "wof:placetype":"venue"
},
  "geometry": {"coordinates":[-122.042942,37.370367],"type":"Point"}
}