{
  "type": "Feature",
  "properties": {
    "addr:full":"3234 Grand Ave Oakland CA 94610",
    "addr:housenumber":"3234",
    "addr:postcode":"94610",
    "addr:street":"Grand Ave",
    "iso:country":"US",
    "sg:address":"3234 Grand Ave",
    "sg:city":"Oakland",
    "sg:classifiers":[
        {
            "category":"Sports & Exercise",
            "subcategory":"Gym",
            "type":"Entertainment"
        }
    ],
    "sg:phone":"+1 510 546 0978",
    "sg:postcode":"94610",
    "sg:province":"CA",
    "sg:tags":[
        "personal",
        "trainer"
    ],
    "wof:name":"Pigott Abu",
    "wof:placetype":"venue"
},
  "geometry": {"coordinates":[-122.246864,37.813256],"type":"Point"}
}