{
  "type": "Feature",
  "properties": {
    "iso:country":"US",
    "sg:address":"1302 Jordan St",
    "sg:city":"Crescent City",
    "sg:classifiers":[
        {
            "category":"Retail",
            "subcategory":"Auto Repair",
            "type":"Services"
        }
    ],
    "sg:phone":"+1 707 464 4400",
    "sg:postcode":"95531",
    "sg:province":"CA",
    "sg:tags":[
        "wrecker"
    ],
    "wof:name":"American Towing & Svc Ctr",
    "wof:placetype":"venue"
},
  "geometry": {"coordinates":[-124.198484,41.770895],"type":"Point"}
}