{
  "type": "Feature",
  "properties": {
    "iso:country":"US",
    "sg:address":"20750 Ventura Blvd",
    "sg:city":"Woodland Hills",
    "sg:classifiers":[
        {
            "category":"Professional",
            "subcategory":"Lawyer & Legal Services",
            "type":"Services"
        }
    ],
    "sg:phone":"+1 818 702 7000",
    "sg:postcode":"91364",
    "sg:province":"CA",
    "sg:tags":[
        "attorney"
    ],
    "sg:website":"www.attorneyrobertbrenner.com",
    "wof:name":"Robert A Brenner Law Office",
    "wof:placetype":"venue"
},
  "geometry": {"coordinates":[-118.58420099999999,34.16682],"type":"Point"}
}