{
  "type": "Feature",
  "properties": {
    "addr:full":"100 W El Camino Real Suite #63A Mountain View CA 94041",
    "addr:housenumber":"100;63a",
    "addr:postcode":"94041",
    "addr:street":"W El Camino Real Suite #",
    "iso:country":"US",
    "sg:address":"100 W El Camino Real Suite #63A",
    "sg:city":"Mountain View",
    "sg:classifiers":[
        {
            "category":"Health Services",
            "subcategory":"Dentist",
            "type":"Services"
        }
    ],
    "sg:phone":"+1 650 964 2207",
    "sg:postcode":"94041",
    "sg:province":"CA",
    "sg:tags":[
        "orthodontist"
    ],
    "sg:website":"www.boschkenorthodontics.com",
    "wof:name":"Boschken Orthodontics",
    "wof:placetype":"venue"
},
  "geometry": {"coordinates":[-122.07711500000001,37.382792],"type":"Point"}
}