{
  "type": "Feature",
  "properties": {
    "addr:full":"13024 Halldale Ave Gardena CA 90249",
    "addr:housenumber":"13024",
    "addr:postcode":"90249",
    "addr:street":"Halldale Ave",
    "iso:country":"US",
    "sg:address":"13024 Halldale Ave",
    "sg:city":"Gardena",
    "sg:classifiers":[
        {
            "category":"Retail",
            "subcategory":"Auto Repair",
            "type":"Services"
        }
    ],
    "sg:phone":"+1 310 516 0410",
    "sg:postcode":"90249",
    "sg:province":"CA",
    "sg:tags":[
        "body",
        "automobile",
        "painting"
    ],
    "wof:name":"Ziggy's Auto Body",
    "wof:placetype":"venue"
},
  "geometry": {"coordinates":[-118.302215,33.91287],"type":"Point"}
}