{
  "type": "Feature",
  "properties": {
    "iso:country":"US",
    "sg:address":"2451 Eastman Ave",
    "sg:city":"Oxnard",
    "sg:classifiers":[
        {
            "category":"Professional",
            "type":"Services"
        }
    ],
    "sg:phone":"+1 805 485 9595",
    "sg:postcode":"93030",
    "sg:province":"CA",
    "wof:name":"Hatch Work Inc",
    "wof:placetype":"venue"
},
  "geometry": {"coordinates":[-119.142977,34.199035],"type":"Point"}
}