{
  "type": "Feature",
  "properties": {
    "iso:country":"US",
    "sg:address":"1274 Thurston Ave",
    "sg:city":"Los Altos",
    "sg:classifiers":[
        {
            "category":"Professional",
            "subcategory":"Research",
            "type":"Services"
        }
    ],
    "sg:phone":"+1 650 428 0409",
    "sg:postcode":"94024",
    "sg:province":"CA",
    "sg:tags":[
        "development",
        "marketing",
        "product"
    ],
    "sg:website":"www.pacificphotonics.com",
    "wof:name":"Pacific Photonics Inc",
    "wof:placetype":"venue"
},
  "geometry": {"coordinates":[-122.080819,37.34828],"type":"Point"}
}