{
  "type": "Feature",
  "properties": {
    "iso:country":"US",
    "sg:address":"10538 Bradbury Rd",
    "sg:city":"Los Angeles",
    "sg:classifiers":[
        {
            "category":"Professional",
            "subcategory":"Business Services",
            "type":"Services"
        }
    ],
    "sg:phone":"+1 310 288 0144",
    "sg:postcode":"90064",
    "sg:province":"CA",
    "sg:tags":[
        "interior",
        "consultant",
        "design",
        "decorator"
    ],
    "wof:name":"Frost Design",
    "wof:placetype":"venue"
},
  "geometry": {"coordinates":[-118.417486,34.038201],"type":"Point"}
}