{
  "type": "Feature",
  "properties": {
    "addr:full":"1725 4th Ave Chula Vista CA 91911",
    "addr:housenumber":"1725",
    "addr:postcode":"91911",
    "addr:street":"4Th Ave",
    "iso:country":"US",
    "sg:address":"1725 4th Ave",
    "sg:city":"Chula Vista",
    "sg:classifiers":[
        {
            "category":"Shopping",
            "subcategory":"Stationery & Office Supplies",
            "type":"Retail Goods"
        }
    ],
    "sg:phone":"+1 619 691 0574",
    "sg:postcode":"91911",
    "sg:province":"CA",
    "sg:tags":[
        "equipment"
    ],
    "wof:name":"GM Office Supplies",
    "wof:placetype":"venue"
},
  "geometry": {"coordinates":[-117.069,32.594299],"type":"Point"}
}