{
  "type": "Feature",
  "properties": {
    "addr:full":"2241 Bunker Hill Dr San Mateo CA 94402",
    "addr:housenumber":"2241",
    "addr:postcode":"94402",
    "addr:street":"Bunker Hill Dr",
    "iso:country":"US",
    "sg:address":"2241 Bunker Hill Dr",
    "sg:city":"San Mateo",
    "sg:classifiers":[
        {
            "category":"Professional",
            "subcategory":"Engineering",
            "type":"Services"
        }
    ],
    "sg:phone":"+1 650 574 7472",
    "sg:postcode":"94402",
    "sg:province":"CA",
    "sg:tags":[
        "engineer"
    ],
    "wof:name":"Rivera Lanthier & Assoc",
    "wof:placetype":"venue"
},
  "geometry": {"coordinates":[-122.34454700000001,37.525288],"type":"Point"}
}