{
  "type": "Feature",
  "properties": {
    "addr:full":"3855 Pacific Coast Hwy Torrance CA 90505",
    "addr:housenumber":"3855",
    "addr:postcode":"90505",
    "addr:street":"Pacific Coast Hwy",
    "iso:country":"US",
    "sg:address":"3855 Pacific Coast Hwy",
    "sg:city":"Torrance",
    "sg:classifiers":[
        {
            "category":"Freight",
            "type":"Transportation"
        }
    ],
    "sg:phone":"+1 310 791 2277",
    "sg:postcode":"90505",
    "sg:province":"CA",
    "sg:tags":[
        "clearing",
        "trade",
        "exchange"
    ],
    "wof:name":"Hoybesar Inc",
    "wof:placetype":"venue"
},
  "geometry": {"coordinates":[-118.35265099999999,33.805752],"type":"Point"}
}