{
  "type": "Feature",
  "properties": {
    "addr:full":"747 Alvina Ct Los Altos CA 94024",
    "addr:housenumber":"747",
    "addr:postcode":"94024",
    "addr:street":"Alvina Ct",
    "iso:country":"US",
    "sg:address":"747 Alvina Ct",
    "sg:city":"Los Altos",
    "sg:classifiers":[
        {
            "category":"Wholesale",
            "subcategory":"Computers",
            "type":"Manufacturing & Wholesale Goods"
        },
        {
            "category":"Wholesale",
            "subcategory":"Electrical",
            "type":"Manufacturing & Wholesale Goods"
        }
    ],
    "sg:phone":"+1 650 960 3933",
    "sg:postcode":"94024",
    "sg:province":"CA",
    "sg:tags":[
        "electronic",
        "representative"
    ],
    "wof:name":"Heidmiller Group",
    "wof:placetype":"venue"
},
  "geometry": {"coordinates":[-122.093924,37.362],"type":"Point"}
}