{
  "type": "Feature",
  "properties": {
    "iso:country":"US",
    "sg:address":"27756 Santa Margarita Parkway",
    "sg:city":"Mission Viejo",
    "sg:classifiers":[
        {
            "category":"Shopping",
            "subcategory":"Hobbies, Toys, & Games",
            "type":"Retail Goods"
        },
        {
            "category":"Personal",
            "type":"Services"
        },
        {
            "category":"Personal",
            "subcategory":"Shoe Repair & Shine",
            "type":"Services"
        }
    ],
    "sg:phone":"+1 949 586 3968",
    "sg:postcode":"92691",
    "sg:province":"CA",
    "sg:tags":[
        "shop",
        "hobby",
        "local"
    ],
    "wof:name":"Portola Shoe & Luggage Repair Center",
    "wof:placetype":"venue"
},
  "geometry": {"coordinates":[-117.646225,33.652627],"type":"Point"}
}