{
  "type": "Feature",
  "properties": {
    "addr:full":"4263 Alta Mira Dr La Mesa CA 91941",
    "addr:housenumber":"4263",
    "addr:postcode":"91941",
    "addr:street":"Alta Mira Dr",
    "iso:country":"US",
    "sg:address":"4263 Alta Mira Dr",
    "sg:city":"La Mesa",
    "sg:classifiers":[
        {
            "category":"Manufacturing",
            "subcategory":"Tools & Machinery",
            "type":"Manufacturing & Wholesale Goods"
        }
    ],
    "sg:phone":"+1 619 660 6172",
    "sg:postcode":"91941",
    "sg:province":"CA",
    "sg:tags":[
        "electrical",
        "mfg"
    ],
    "wof:name":"Visualize It Prod",
    "wof:placetype":"venue"
},
  "geometry": {"coordinates":[-116.970922,32.755615],"type":"Point"}
}