{
  "type": "Feature",
  "properties": {
    "iso:country":"US",
    "sg:address":"915 S 26th St",
    "sg:city":"San Diego",
    "sg:classifiers":[
        {
            "category":"Wholesale",
            "subcategory":"Fruits & Vegetables",
            "type":"Manufacturing & Wholesale Goods"
        }
    ],
    "sg:phone":"+1 619 702 4645",
    "sg:postcode":"92113",
    "sg:province":"CA",
    "wof:name":"Fruteria Nayarit",
    "wof:placetype":"venue"
},
  "geometry": {"coordinates":[-117.138016,32.696736],"type":"Point"}
}