{
  "type": "Feature",
  "properties": {
    "iso:country":"US",
    "sg:address":"845 E Santa Barbara St",
    "sg:city":"Santa Paula",
    "sg:classifiers":[
        {
            "category":"Government",
            "subcategory":"Office",
            "type":"Public Place"
        }
    ],
    "sg:phone":"+1 805 654 4889",
    "sg:postcode":"93060",
    "sg:province":"CA",
    "sg:tags":[
        "state",
        "inspection"
    ],
    "wof:name":"Pesticide Regulation Dept",
    "wof:placetype":"venue"
},
  "geometry": {"coordinates":[-119.063882,34.354707],"type":"Point"}
}