{
  "type": "Feature",
  "properties": {
    "addr:full":"4050 W.Metropolitan Dr. Orange CA 92868",
    "addr:housenumber":"4050",
    "addr:postcode":"92868",
    "addr:street":"W.Metropolitan Dr.",
    "iso:country":"US",
    "sg:address":"4050 W.Metropolitan Dr.",
    "sg:city":"Orange",
    "sg:classifiers":[
        {
            "category":"Banks & Credit Unions",
            "subcategory":"Bank",
            "type":"Services"
        }
    ],
    "sg:phone":"+1 714 283 8688",
    "sg:postcode":"92868",
    "sg:province":"CA",
    "sg:website":"www.citibank.com",
    "wof:name":"Citibank",
    "wof:placetype":"venue"
},
  "geometry": {"coordinates":[-117.89707799999999,33.781343],"type":"Point"}
}