{
  "type": "Feature",
  "properties": {
    "addr:full":"5359 Claremont Ave Oakland CA 94618",
    "addr:housenumber":"5359",
    "addr:postcode":"94618",
    "addr:street":"Claremont Ave",
    "iso:country":"US",
    "sg:address":"5359 Claremont Ave",
    "sg:city":"Oakland",
    "sg:classifiers":[
        {
            "category":"Personal",
            "subcategory":"Barber",
            "type":"Services"
        }
    ],
    "sg:phone":"+1 510 654 8929",
    "sg:postcode":"94618",
    "sg:province":"CA",
    "wof:name":"Sportmans Barber Shop",
    "wof:placetype":"venue"
},
  "geometry": {"coordinates":[-122.261002,37.8395],"type":"Point"}
}