{
  "type": "Feature",
  "properties": {
    "addr:full":"335 Dartmouth Rd Santa Paula CA 93060",
    "addr:housenumber":"335",
    "addr:postcode":"93060",
    "addr:street":"Dartmouth Rd",
    "iso:country":"US",
    "sg:address":"335 Dartmouth Rd",
    "sg:city":"Santa Paula",
    "sg:classifiers":[
        {
            "category":"Freight",
            "type":"Transportation"
        }
    ],
    "sg:phone":"+1 805 525 1196",
    "sg:postcode":"93060",
    "sg:province":"CA",
    "sg:tags":[
        "operator",
        "local",
        "trucking"
    ],
    "wof:name":"W&M Covarrubias Trucking",
    "wof:placetype":"venue"
},
  "geometry": {"coordinates":[-119.08197699999999,34.340776],"type":"Point"}
}