{
  "type": "Feature",
  "properties": {
    "addr:full":"15000 Bolsa Chica St Huntington Beach CA 92649",
    "addr:postcode":"15000;92649",
    "addr:street":"Bolsa Chica St",
    "iso:country":"US",
    "sg:address":"15000 Bolsa Chica St",
    "sg:city":"Huntington Beach",
    "sg:classifiers":[
        {
            "category":"Manufacturing",
            "subcategory":"Tools & Machinery",
            "type":"Manufacturing & Wholesale Goods"
        }
    ],
    "sg:phone":"+1 714 891 7855",
    "sg:postcode":"92649",
    "sg:province":"CA",
    "sg:tags":[
        "machine",
        "shop",
        "printing",
        "mfg"
    ],
    "wof:name":"A-1 Precision Machine",
    "wof:placetype":"venue"
},
  "geometry": {"coordinates":[-118.04189,33.74108],"type":"Point"}
}