{
  "type": "Feature",
  "properties": {
    "iso:country":"US",
    "sg:address":"1520 James M Wood Blvd",
    "sg:city":"Los Angeles",
    "sg:classifiers":[
        {
            "category":"Organizations",
            "subcategory":"Religious Organization",
            "type":"Services"
        }
    ],
    "sg:phone":"+1 213 381 6870",
    "sg:postcode":"90015",
    "sg:province":"CA",
    "wof:name":"Klesis Mission",
    "wof:placetype":"venue"
},
  "geometry": {"coordinates":[-118.272003,34.050499],"type":"Point"}
}