{
  "type": "Feature",
  "properties": {
    "iso:country":"US",
    "sg:address":"2525 Mandela Pkwy",
    "sg:city":"Oakland",
    "sg:classifiers":[
        {
            "category":"Wholesale",
            "subcategory":"Machinery & Supplies",
            "type":"Manufacturing & Wholesale Goods"
        }
    ],
    "sg:phone":"+1 510 832 4404",
    "sg:postcode":"94607",
    "sg:province":"CA",
    "sg:tags":[
        "equipment",
        "printing"
    ],
    "wof:name":"General Graphic Co",
    "wof:placetype":"venue"
},
  "geometry": {"coordinates":[-122.289057,37.820407],"type":"Point"}
}