{
  "type": "Feature",
  "properties": {
    "addr:full":"300 Moraga Rd Moraga CA 94556",
    "addr:housenumber":"300",
    "addr:postcode":"94556",
    "addr:street":"Moraga Rd",
    "iso:country":"US",
    "sg:address":"300 Moraga Rd",
    "sg:city":"Moraga",
    "sg:classifiers":[
        {
            "category":"Education",
            "subcategory":"School",
            "type":"Public Place"
        }
    ],
    "sg:phone":"+1 925 280 3950",
    "sg:postcode":"94556",
    "sg:province":"CA",
    "sg:tags":[
        "high"
    ],
    "sg:website":"http://campolindo.acalanes.k12.ca.us/",
    "wof:name":"Campolindo High School",
    "wof:placetype":"venue"
},
  "geometry": {"coordinates":[-122.12522199999999,37.867882],"type":"Point"}
}