{
  "type": "Feature",
  "properties": {
    "iso:country":"US",
    "sg:address":"7177 Brockton Ave",
    "sg:city":"Riverside",
    "sg:classifiers":[
        {
            "category":"Building & Trades",
            "subcategory":"Landscaping Services",
            "type":"Services"
        }
    ],
    "sg:phone":"+1 951 787 1180",
    "sg:postcode":"92506",
    "sg:province":"CA",
    "sg:tags":[
        "landscape",
        "contractor"
    ],
    "wof:name":"Reyco Smith & Reynolds",
    "wof:placetype":"venue"
},
  "geometry": {"coordinates":[-117.39502899999999,33.943798],"type":"Point"}
}