{
  "type": "Feature",
  "properties": {
    "addr:full":"206 W Ridgecrest Blvd Ridgecrest CA 93555",
    "addr:housenumber":"206",
    "addr:postcode":"93555",
    "addr:street":"W Ridgecrest Blvd",
    "iso:country":"US",
    "sg:address":"206 W Ridgecrest Blvd",
    "sg:city":"Ridgecrest",
    "sg:classifiers":[
        {
            "category":"Building & Trades",
            "subcategory":"Construction",
            "type":"Services"
        }
    ],
    "sg:phone":"+1 760 375 5315",
    "sg:postcode":"93555",
    "sg:province":"CA",
    "sg:tags":[
        "contractor"
    ],
    "wof:name":"Clarks Pools",
    "wof:placetype":"venue"
},
  "geometry": {"coordinates":[-117.67249700000001,35.622598],"type":"Point"}
}