{
  "type": "Feature",
  "properties": {
    "iso:country":"US",
    "sg:address":"17046 Devonshire St",
    "sg:city":"Northridge",
    "sg:classifiers":[
        {
            "category":"Manufacturing",
            "subcategory":"Signs",
            "type":"Manufacturing & Wholesale Goods"
        }
    ],
    "sg:phone":"+1 818 832 7979",
    "sg:postcode":"91325",
    "sg:province":"CA",
    "sg:website":"www.alohasigns.com",
    "wof:name":"Aloha Signs & Graphics",
    "wof:placetype":"venue"
},
  "geometry": {"coordinates":[-118.505465,34.257458],"type":"Point"}
}