{
  "type": "Feature",
  "properties": {
    "iso:country":"US",
    "sg:address":"1300 N Kellogg Dr Ste B",
    "sg:city":"Anaheim",
    "sg:classifiers":[
        {
            "category":"Real Estate",
            "subcategory":"Real Estate Services",
            "type":"Services"
        }
    ],
    "sg:phone":"+1 714 777 3700",
    "sg:postcode":"92807",
    "sg:province":"CA",
    "sg:tags":[
        "management",
        "property"
    ],
    "sg:website":"www.tricommanagement.com",
    "wof:name":"Tricom Management Inc",
    "wof:placetype":"venue"
},
  "geometry": {"coordinates":[-117.806999,33.860901],"type":"Point"}
}