{
  "type": "Feature",
  "properties": {
    "addr:full":"3408 30th San Diego CA 92104",
    "addr:housenumber":"3408",
    "addr:postcode":"92104",
    "addr:street":"30Th",
    "iso:country":"US",
    "sg:address":"3408 30th",
    "sg:city":"San Diego",
    "sg:classifiers":[
        {
            "category":"Restaurant",
            "type":"Food & Drink"
        }
    ],
    "sg:phone":"+1 619 955 5295",
    "sg:postcode":"92104",
    "sg:province":"CA",
    "sg:tags":[
        "new",
        "american"
    ],
    "sg:website":"www.thesmokinggoatrestaurant.com/",
    "wof:name":"The Smoking Goat",
    "wof:placetype":"venue"
},
  "geometry": {"coordinates":[-117.13012999999999,32.74127],"type":"Point"}
}