{
  "type": "Feature",
  "properties": {
    "addr:full":"711 N Spring St Los Angeles CA 90012",
    "addr:housenumber":"711",
    "addr:postcode":"90012",
    "addr:street":"N Spring St",
    "iso:country":"US",
    "sg:address":"711 N Spring St",
    "sg:city":"Los Angeles",
    "sg:classifiers":[
        {
            "category":"Farming",
            "subcategory":"Farm & Veterinary Services",
            "type":"Manufacturing & Wholesale Goods"
        }
    ],
    "sg:phone":"+1 213 617 2635",
    "sg:postcode":"90012",
    "sg:province":"CA",
    "sg:tags":[
        "livestock"
    ],
    "wof:name":"Shang Lee Poultry Inc",
    "wof:placetype":"venue"
},
  "geometry": {"coordinates":[-118.237077,34.061683],"type":"Point"}
}