{
  "type": "Feature",
  "properties": {
    "iso:country":"US",
    "sg:address":"5200 Coe Ave",
    "sg:city":"Seaside",
    "sg:classifiers":[
        {
            "category":"Real Estate",
            "subcategory":"Real Estate Operator",
            "type":"Services"
        }
    ],
    "sg:phone":"+1 831 394 2515",
    "sg:postcode":"93955",
    "sg:province":"CA",
    "sg:tags":[
        "apartment"
    ],
    "wof:name":"Sun Bay Suites & Apartments",
    "wof:placetype":"venue"
},
  "geometry": {"coordinates":[-121.827628,36.623236],"type":"Point"}
}