{
  "type": "Feature",
  "properties": {
    "iso:country":"US",
    "sg:address":"5169 Douglas Fir Rd Ste 5",
    "sg:city":"Calabasas",
    "sg:classifiers":[
        {
            "category":"Real Estate",
            "subcategory":"Real Estate Services",
            "type":"Services"
        }
    ],
    "sg:phone":"+1 818 222 2252",
    "sg:postcode":"91302",
    "sg:province":"CA",
    "sg:tags":[
        "management",
        "property"
    ],
    "wof:name":"Calabasas Industrial Center",
    "wof:placetype":"venue"
},
  "geometry": {"coordinates":[-118.649002,34.1581],"type":"Point"}
}