{
  "type": "Feature",
  "properties": {
    "addr:full":"9255 Euthalia Ct Elk Grove CA 95758",
    "addr:housenumber":"9255",
    "addr:postcode":"95758",
    "addr:street":"Euthalia Ct",
    "iso:country":"US",
    "sg:address":"9255 Euthalia Ct",
    "sg:city":"Elk Grove",
    "sg:classifiers":[
        {
            "category":"Shopping",
            "subcategory":"Optical Goods",
            "type":"Retail Goods"
        }
    ],
    "sg:phone":"+1 916 853 9636",
    "sg:postcode":"95758",
    "sg:province":"CA",
    "wof:name":"Cynthia Woo OD",
    "wof:placetype":"venue"
},
  "geometry": {"coordinates":[-121.479483,38.421225],"type":"Point"}
}