{
  "type": "Feature",
  "properties": {
    "addr:full":"1011 Murre Way Suisun City CA 94585",
    "addr:housenumber":"1011",
    "addr:postcode":"94585",
    "addr:street":"Murre Way",
    "iso:country":"US",
    "sg:address":"1011 Murre Way",
    "sg:city":"Suisun City",
    "sg:classifiers":[
        {
            "category":"Professional",
            "type":"Services"
        }
    ],
    "sg:phone":"+1 707 432 5594",
    "sg:postcode":"94585",
    "sg:province":"CA",
    "wof:name":"Cameron Executive Svc",
    "wof:placetype":"venue"
},
  "geometry": {"coordinates":[-121.99933799999999,38.252783],"type":"Point"}
}