{
  "type": "Feature",
  "properties": {
    "addr:full":"3049 E 4th St Los Angeles CA 90063",
    "addr:housenumber":"3049",
    "addr:postcode":"90063",
    "addr:street":"E 4Th St",
    "iso:country":"US",
    "sg:address":"3049 E 4th St",
    "sg:city":"Los Angeles",
    "sg:classifiers":[
        {
            "category":"Restaurant",
            "type":"Food & Drink"
        }
    ],
    "sg:phone":"+1 323 262 3620",
    "sg:postcode":"90063",
    "sg:province":"CA",
    "wof:name":"Tacos Clarita",
    "wof:placetype":"venue"
},
  "geometry": {"coordinates":[-118.20141599999999,34.036098],"type":"Point"}
}