{
  "type": "Feature",
  "properties": {
    "addr:full":"25991 Brodiaea Ave Moreno Valley CA 92553",
    "addr:housenumber":"25991",
    "addr:postcode":"92553",
    "addr:street":"Brodiaea Ave",
    "iso:country":"US",
    "sg:address":"25991 Brodiaea Ave",
    "sg:city":"Moreno Valley",
    "sg:classifiers":[
        {
            "category":"Professional",
            "subcategory":"Business Services",
            "type":"Services"
        }
    ],
    "sg:phone":"+1 951 485 8185",
    "sg:postcode":"92553",
    "sg:province":"CA",
    "sg:tags":[
        "good"
    ],
    "wof:name":"Springcrest Pool Service",
    "wof:placetype":"venue"
},
  "geometry": {"coordinates":[-117.20895899999999,33.913709],"type":"Point"}
}