{
  "type": "Feature",
  "properties": {
    "addr:full":"9120 Center Ave Rancho Cucamonga CA 91730",
    "addr:housenumber":"9120",
    "addr:postcode":"91730",
    "addr:street":"Center Ave",
    "iso:country":"US",
    "sg:address":"9120 Center Ave",
    "sg:city":"Rancho Cucamonga",
    "sg:classifiers":[
        {
            "category":"Wholesale",
            "subcategory":"Furniture",
            "type":"Manufacturing & Wholesale Goods"
        }
    ],
    "sg:phone":"+1 909 944 1980",
    "sg:postcode":"91730",
    "sg:province":"CA",
    "wof:name":"4 D Concepts",
    "wof:placetype":"venue"
},
  "geometry": {"coordinates":[-117.580299,34.085085],"type":"Point"}
}