{
  "type": "Feature",
  "properties": {
    "iso:country":"US",
    "sg:address":"25426 Plz Escovar",
    "sg:city":"Valencia",
    "sg:classifiers":[
        {
            "category":"Home & Garden",
            "subcategory":"Hardware",
            "type":"Retail Goods"
        }
    ],
    "sg:phone":"+1 661 255 8525",
    "sg:postcode":"91355",
    "sg:province":"CA",
    "wof:name":"Metal Resources",
    "wof:placetype":"venue"
},
  "geometry": {"coordinates":[-118.552398,34.383704],"type":"Point"}
}