{
  "type": "Feature",
  "properties": {
    "addr:full":"519 Vernon St Roseville CA 95678",
    "addr:housenumber":"519",
    "addr:postcode":"95678",
    "addr:street":"Vernon St",
    "iso:country":"US",
    "sg:address":"519 Vernon St",
    "sg:city":"Roseville",
    "sg:classifiers":[
        {
            "category":"Personal",
            "subcategory":"Barber",
            "type":"Services"
        }
    ],
    "sg:phone":"+1 916 652 5370",
    "sg:postcode":"95678",
    "sg:province":"CA",
    "wof:name":"Enzo's Barber Shop",
    "wof:placetype":"venue"
},
  "geometry": {"coordinates":[-121.287316,38.74637],"type":"Point"}
}