{
  "type": "Feature",
  "properties": {
    "addr:full":"701 S Broadway Los Angeles CA 90014",
    "addr:housenumber":"701",
    "addr:postcode":"90014",
    "addr:street":"S Broadway",
    "iso:country":"US",
    "sg:address":"701 S Broadway",
    "sg:city":"Los Angeles",
    "sg:classifiers":[
        {
            "category":"Coffee & Tea",
            "type":"Food & Drink"
        }
    ],
    "sg:phone":"+1 213 688 7362",
    "sg:postcode":"90014",
    "sg:province":"CA",
    "wof:name":"Seven Star Coffee 2",
    "wof:placetype":"venue"
},
  "geometry": {"coordinates":[-118.253286,34.04511],"type":"Point"}
}