{
  "type": "Feature",
  "properties": {
    "iso:country":"US",
    "sg:address":"532 W Monte Vista Ave",
    "sg:city":"Vacaville",
    "sg:classifiers":[
        {
            "category":"Health Services",
            "subcategory":"Doctor",
            "type":"Services"
        }
    ],
    "sg:phone":"+1 707 446 4677",
    "sg:postcode":"95688",
    "sg:province":"CA",
    "sg:tags":[
        "dentist"
    ],
    "wof:name":"Robert A Hekking DDS",
    "wof:placetype":"venue"
},
  "geometry": {"coordinates":[-122.006103,38.359348],"type":"Point"}
}