{
  "type": "Feature",
  "properties": {
    "iso:country":"US",
    "sg:address":"500 D St",
    "sg:city":"Antioch",
    "sg:classifiers":[
        {
            "category":"Building & Trades",
            "subcategory":"Landscaping Services",
            "type":"Services"
        }
    ],
    "sg:phone":"+1 925 755 3447",
    "sg:postcode":"94509",
    "sg:province":"CA",
    "sg:tags":[
        "aged",
        "homes-institutional"
    ],
    "wof:name":"Antioch Icf Inc",
    "wof:placetype":"venue"
},
  "geometry": {"coordinates":[-121.81001999999999,38.014759],"type":"Point"}
}