{
  "type": "Feature",
  "properties": {
    "addr:full":"14121 S Western Ave Gardena CA 90249",
    "addr:housenumber":"14121",
    "addr:postcode":"90249",
    "addr:street":"S Western Ave",
    "iso:country":"US",
    "sg:address":"14121 S Western Ave",
    "sg:city":"Gardena",
    "sg:classifiers":[
        {
            "category":"Wholesale",
            "subcategory":"Medical Equipment & Supplies",
            "type":"Manufacturing & Wholesale Goods"
        }
    ],
    "sg:phone":"+1 310 527 5228",
    "sg:postcode":"90249",
    "sg:province":"CA",
    "sg:tags":[
        "physician",
        "surgeon"
    ],
    "wof:name":"C & B Medical Supply",
    "wof:placetype":"venue"
},
  "geometry": {"coordinates":[-118.309196,33.902105],"type":"Point"}
}