{
  "type": "Feature",
  "properties": {
    "addr:full":"10519 Colorado Rd Atascadero CA 93422",
    "addr:housenumber":"10519",
    "addr:postcode":"93422",
    "addr:street":"Colorado Rd",
    "iso:country":"US",
    "sg:address":"10519 Colorado Rd",
    "sg:city":"Atascadero",
    "sg:classifiers":[
        {
            "category":"Manufacturing",
            "subcategory":"Tools & Machinery",
            "type":"Manufacturing & Wholesale Goods"
        }
    ],
    "sg:phone":"+1 805 466 4987",
    "sg:postcode":"93422",
    "sg:province":"CA",
    "sg:tags":[
        "fire",
        "equipment",
        "emergency",
        "for",
        "fighting"
    ],
    "wof:name":"Heidi Monson",
    "wof:placetype":"venue"
},
  "geometry": {"coordinates":[-120.65091700000001,35.45472],"type":"Point"}
}