{
  "type": "Feature",
  "properties": {
    "iso:country":"US",
    "sg:address":"11608 Ventura Blvd",
    "sg:city":"Studio City",
    "sg:classifiers":[
        {
            "category":"Arts & Performance",
            "subcategory":"Music",
            "type":"Entertainment"
        },
        {
            "category":"Recreation",
            "subcategory":"Dance Hall",
            "type":"Entertainment"
        }
    ],
    "sg:phone":"+1 818 755 9548",
    "sg:postcode":"91604",
    "sg:province":"CA",
    "sg:tags":[
        "club",
        "venue"
    ],
    "sg:website":"www.rlounge.us",
    "wof:name":"R Lounge",
    "wof:placetype":"venue"
},
  "geometry": {"coordinates":[-118.385002,34.140335],"type":"Point"}
}