{
  "type": "Feature",
  "properties": {
    "addr:full":"806 4th St Napa CA 94559",
    "addr:housenumber":"806",
    "addr:postcode":"94559",
    "addr:street":"4Th St",
    "iso:country":"US",
    "sg:address":"806 4th St",
    "sg:city":"Napa",
    "sg:classifiers":[
        {
            "category":"Restaurant",
            "type":"Food & Drink"
        }
    ],
    "sg:phone":"+1 707 252 4477",
    "sg:postcode":"94559",
    "sg:province":"CA",
    "wof:name":"Depot Restaurant-Rainbow Room",
    "wof:placetype":"venue"
},
  "geometry": {"coordinates":[-122.280483,38.298058],"type":"Point"}
}