{
  "type": "Feature",
  "properties": {
    "iso:country":"US",
    "sg:address":"950 N Waterman Ct",
    "sg:city":"El Centro",
    "sg:classifiers":[
        {
            "category":"Social Services",
            "type":"Services"
        }
    ],
    "sg:phone":"+1 760 353 2620",
    "sg:postcode":"92243",
    "sg:province":"CA",
    "sg:tags":[
        "organization",
        "welfare"
    ],
    "wof:name":"Senior Citizen's Emergency",
    "wof:placetype":"venue"
},
  "geometry": {"coordinates":[-115.574257,32.801103],"type":"Point"}
}