{
  "type": "Feature",
  "properties": {
    "iso:country":"US",
    "sg:address":"1367 Grand Ave",
    "sg:city":"Grover Beach",
    "sg:classifiers":[
        {
            "category":"Shopping",
            "subcategory":"Hobbies, Toys, & Games",
            "type":"Retail Goods"
        }
    ],
    "sg:phone":"+1 805 481 8017",
    "sg:postcode":"93433",
    "sg:province":"CA",
    "sg:tags":[
        "craft",
        "supply"
    ],
    "wof:name":"Warner's House Of Color",
    "wof:placetype":"venue"
},
  "geometry": {"coordinates":[-120.614625,35.121313],"type":"Point"}
}