{
  "type": "Feature",
  "properties": {
    "iso:country":"US",
    "sg:address":"855 Stanton Rd",
    "sg:city":"Burlingame",
    "sg:classifiers":[
        {
            "category":"Restaurant",
            "type":"Food & Drink"
        }
    ],
    "sg:phone":"+1 650 876 3015",
    "sg:postcode":"94010",
    "sg:province":"CA",
    "sg:tags":[
        "eating"
    ],
    "wof:name":"Debobbs",
    "wof:placetype":"venue"
},
  "geometry": {"coordinates":[-122.370622,37.599303],"type":"Point"}
}