{
  "type": "Feature",
  "properties": {
    "iso:country":"US",
    "sg:address":"401 Hayes St",
    "sg:city":"San Francisco",
    "sg:classifiers":[
        {
            "category":"Food & Beverages",
            "subcategory":"Candy",
            "type":"Retail Goods"
        },
        {
            "category":"Food & Beverages",
            "subcategory":"Chocolate",
            "type":"Retail Goods"
        }
    ],
    "sg:phone":"+1 415 355 1105",
    "sg:postcode":"94102",
    "sg:province":"CA",
    "sg:tags":[
        "shop",
        "dessert",
        "chocolatiers"
    ],
    "sg:website":"www.elbowchocolates.com/",
    "wof:name":"Christopher Elbow Artisanal Chocolates",
    "wof:placetype":"venue"
},
  "geometry": {"coordinates":[-122.42315600000001,37.776597],"type":"Point"}
}