{
  "type": "Feature",
  "properties": {
    "addr:full":"668 Barber Lane Milpitas CA 95035",
    "addr:housenumber":"668",
    "addr:postcode":"95035",
    "addr:street":"Barber Lane",
    "iso:country":"US",
    "sg:address":"668 Barber Lane",
    "sg:city":"Milpitas",
    "sg:classifiers":[
        {
            "category":"Home & Garden",
            "subcategory":"Furniture",
            "type":"Retail Goods"
        }
    ],
    "sg:phone":"+1 408 432 8833",
    "sg:postcode":"95035",
    "sg:province":"CA",
    "sg:tags":[
        "store"
    ],
    "sg:website":"www.ulferts.com",
    "wof:name":"Ulferts Furniture",
    "wof:placetype":"venue"
},
  "geometry": {"coordinates":[-121.916646,37.419576],"type":"Point"}
}