{
  "type": "Feature",
  "properties": {
    "addr:full":"9728 6th St Rancho Cucamonga CA 91730",
    "addr:housenumber":"9728",
    "addr:postcode":"91730",
    "addr:street":"6Th St",
    "iso:country":"US",
    "sg:address":"9728 6th St",
    "sg:city":"Rancho Cucamonga",
    "sg:classifiers":[
        {
            "category":"Wholesale",
            "subcategory":"Chemicals & Plastics",
            "type":"Manufacturing & Wholesale Goods"
        }
    ],
    "sg:phone":"+1 909 987 4554",
    "sg:postcode":"91730",
    "sg:province":"CA",
    "wof:name":"DSR & Co",
    "wof:placetype":"venue"
},
  "geometry": {"coordinates":[-117.587198,34.084799],"type":"Point"}
}