{
  "type": "Feature",
  "properties": {
    "addr:full":"1302 95th Ave Oakland CA 94603",
    "addr:housenumber":"1302",
    "addr:postcode":"94603",
    "addr:street":"95Th Ave",
    "iso:country":"US",
    "sg:address":"1302 95th Ave",
    "sg:city":"Oakland",
    "sg:classifiers":[
        {
            "category":"Freight",
            "type":"Transportation"
        }
    ],
    "sg:phone":"+1 510 917 3644",
    "sg:postcode":"94603",
    "sg:province":"CA",
    "sg:tags":[
        "local",
        "trucking"
    ],
    "wof:name":"Melgar Trucking",
    "wof:placetype":"venue"
},
  "geometry": {"coordinates":[-122.172118,37.746361],"type":"Point"}
}