{
  "type": "Feature",
  "properties": {
    "addr:full":"4370 La Jolla Village Dr San Diego CA 92122",
    "addr:housenumber":"4370",
    "addr:postcode":"92122",
    "addr:street":"La Jolla Village Dr",
    "iso:country":"US",
    "sg:address":"4370 La Jolla Village Dr",
    "sg:city":"San Diego",
    "sg:classifiers":[
        {
            "category":"Professional",
            "subcategory":"Lawyer & Legal Services",
            "type":"Services"
        }
    ],
    "sg:phone":"+1 858 535 9001",
    "sg:postcode":"92122",
    "sg:province":"CA",
    "wof:name":"Campbell Cathryn Atty",
    "wof:placetype":"venue"
},
  "geometry": {"coordinates":[-117.21199799999999,32.873001],"type":"Point"}
}