{
  "type": "Feature",
  "properties": {
    "addr:full":"4221 Wilshire Blvd Los Angeles CA 90010",
    "addr:housenumber":"4221",
    "addr:postcode":"90010",
    "addr:street":"Wilshire Blvd",
    "iso:country":"US",
    "sg:address":"4221 Wilshire Blvd",
    "sg:city":"Los Angeles",
    "sg:classifiers":[
        {
            "category":"Professional",
            "subcategory":"Lawyer & Legal Services",
            "type":"Services"
        }
    ],
    "sg:phone":"+1 310 556 8133",
    "sg:postcode":"90010",
    "sg:province":"CA",
    "wof:name":"Cohen Michael A Business Seminar",
    "wof:placetype":"venue"
},
  "geometry": {"coordinates":[-118.31999999999999,34.061798],"type":"Point"}
}