{
  "type": "Feature",
  "properties": {
    "addr:full":"11755 Wilshire Blvd Los Angeles CA 90025",
    "addr:housenumber":"11755",
    "addr:postcode":"90025",
    "addr:street":"Wilshire Blvd",
    "iso:country":"US",
    "sg:address":"11755 Wilshire Blvd",
    "sg:city":"Los Angeles",
    "sg:classifiers":[
        {
            "category":"Professional",
            "subcategory":"Lawyer & Legal Services",
            "type":"Services"
        }
    ],
    "sg:phone":"+1 310 273 0904",
    "sg:postcode":"90025",
    "sg:province":"CA",
    "sg:tags":[
        "attorney"
    ],
    "wof:name":"En Gage Mediation",
    "wof:placetype":"venue"
},
  "geometry": {"coordinates":[-118.462287,34.048416],"type":"Point"}
}