{
  "type": "Feature",
  "properties": {
    "addr:full":"7809 Lincoln Ave Riverside CA 92504",
    "addr:housenumber":"7809",
    "addr:postcode":"92504",
    "addr:street":"Lincoln Ave",
    "iso:country":"US",
    "sg:address":"7809 Lincoln Ave",
    "sg:city":"Riverside",
    "sg:classifiers":[
        {
            "category":"Manufacturing",
            "subcategory":"Rubber & Plastics",
            "type":"Manufacturing & Wholesale Goods"
        }
    ],
    "sg:phone":"+1 951 354 7550",
    "sg:postcode":"92504",
    "sg:province":"CA",
    "wof:name":"E R Carpenter Co",
    "wof:placetype":"venue"
},
  "geometry": {"coordinates":[-117.40494700000001,33.926025],"type":"Point"}
}