{
  "type": "Feature",
  "properties": {
    "addr:full":"7005 Hollywood Blvd Los Angeles CA 90028",
    "addr:housenumber":"7005",
    "addr:postcode":"90028",
    "addr:street":"Hollywood Blvd",
    "iso:country":"US",
    "sg:address":"7005 Hollywood Blvd",
    "sg:city":"Los Angeles",
    "sg:classifiers":[
        {
            "category":"Shopping",
            "subcategory":"Optical Goods",
            "type":"Retail Goods"
        }
    ],
    "sg:phone":"+1 323 467 7117",
    "sg:postcode":"90028",
    "sg:province":"CA",
    "sg:tags":[
        "sun",
        "goggles",
        "sunglasses"
    ],
    "wof:name":"Designer Alternative Shades",
    "wof:placetype":"venue"
},
  "geometry": {"coordinates":[-118.343215,34.101609],"type":"Point"}
}