{
  "type": "Feature",
  "properties": {
    "iso:country":"US",
    "sg:address":"131 S Kellogg Ave Ofc",
    "sg:city":"Goleta",
    "sg:classifiers":[
        {
            "category":"Real Estate",
            "subcategory":"Real Estate Operator",
            "type":"Services"
        }
    ],
    "sg:phone":"+1 626 403 1788",
    "sg:postcode":"93117",
    "sg:province":"CA",
    "sg:tags":[
        "apartment"
    ],
    "wof:name":"Villa La Esperanza",
    "wof:placetype":"venue"
},
  "geometry": {"coordinates":[-119.820571,34.436713],"type":"Point"}
}