{
  "type": "Feature",
  "properties": {
    "addr:full":"13217 Whittier Blvd Whittier CA 90602",
    "addr:housenumber":"13217",
    "addr:postcode":"90602",
    "addr:street":"Whittier Blvd",
    "iso:country":"US",
    "sg:address":"13217 Whittier Blvd",
    "sg:city":"Whittier",
    "sg:classifiers":[
        {
            "category":"Personal",
            "subcategory":"Shoe Repair & Shine",
            "type":"Services"
        }
    ],
    "sg:phone":"+1 562 698 9029",
    "sg:postcode":"90602",
    "sg:province":"CA",
    "sg:tags":[
        "repairing",
        "boot"
    ],
    "wof:name":"Park Center Shoe Repair",
    "wof:placetype":"venue"
},
  "geometry": {"coordinates":[-118.034921,33.964451],"type":"Point"}
}