{
  "type": "Feature",
  "properties": {
    "addr:full":"21381 Cajalco Rd Perris CA 92570",
    "addr:postcode":"21381;92570",
    "addr:street":"Cajalco Rd",
    "iso:country":"US",
    "sg:address":"21381 Cajalco Rd",
    "sg:city":"Perris",
    "sg:classifiers":[
        {
            "category":"Professional",
            "subcategory":"Computer Services",
            "type":"Services"
        }
    ],
    "sg:phone":"+1 951 940 5430",
    "sg:postcode":"92570",
    "sg:province":"CA",
    "sg:tags":[
        "repair"
    ],
    "wof:name":"Expressway Computers",
    "wof:placetype":"venue"
},
  "geometry": {"coordinates":[-117.289379,33.837133],"type":"Point"}
}