{
  "type": "Feature",
  "properties": {
    "addr:full":"712 Maryland Dr Vista CA 92083",
    "addr:housenumber":"712",
    "addr:postcode":"92083",
    "addr:street":"Maryland Dr",
    "iso:country":"US",
    "sg:address":"712 Maryland Dr",
    "sg:city":"Vista",
    "sg:classifiers":[
        {
            "category":"Building & Trades",
            "subcategory":"Landscaping Services",
            "type":"Services"
        }
    ],
    "sg:phone":"+1 760 758 6134",
    "sg:postcode":"92083",
    "sg:province":"CA",
    "sg:tags":[
        "gardener"
    ],
    "wof:name":"Gomez W Landscape",
    "wof:placetype":"venue"
},
  "geometry": {"coordinates":[-117.25900300000001,33.205502],"type":"Point"}
}