{
  "type": "Feature",
  "properties": {
    "iso:country":"US",
    "sg:address":"6949 El Camino Real",
    "sg:city":"Carlsbad",
    "sg:classifiers":[
        {
            "category":"Insurance",
            "subcategory":"Health Insurance",
            "type":"Services"
        }
    ],
    "sg:phone":"+1 760 603 0506",
    "sg:postcode":"92009",
    "sg:province":"CA",
    "sg:tags":[
        "market"
    ],
    "wof:name":"General Nutrition Centers",
    "wof:placetype":"venue"
},
  "geometry": {"coordinates":[-117.266998,33.1031],"type":"Point"}
}