{
  "type": "Feature",
  "properties": {
    "addr:full":"5100 N 6th St Fresno CA 93710",
    "addr:housenumber":"5100",
    "addr:postcode":"93710",
    "addr:street":"N 6Th St",
    "iso:country":"US",
    "sg:address":"5100 N 6th St",
    "sg:city":"Fresno",
    "sg:classifiers":[
        {
            "category":"Real Estate",
            "subcategory":"Real Estate Agent",
            "type":"Services"
        }
    ],
    "sg:phone":"+1 559 228 0606",
    "sg:postcode":"93710",
    "sg:province":"CA",
    "sg:tags":[
        "management"
    ],
    "sg:website":"www.iipm.com",
    "wof:name":"I & I Property Management",
    "wof:placetype":"venue"
},
  "geometry": {"coordinates":[-119.763159,36.810405],"type":"Point"}
}