{
  "type": "Feature",
  "properties": {
    "iso:country":"US",
    "sg:address":"512 4th St",
    "sg:city":"Wheatland",
    "sg:classifiers":[
        {
            "category":"Wholesale",
            "subcategory":"Groceries",
            "type":"Manufacturing & Wholesale Goods"
        }
    ],
    "sg:phone":"+1 530 633 4956",
    "sg:postcode":"95692",
    "sg:province":"CA",
    "sg:tags":[
        "rice"
    ],
    "wof:name":"Burt Haughey",
    "wof:placetype":"venue"
},
  "geometry": {"coordinates":[-121.423906,39.010292],"type":"Point"}
}