{
  "type": "Feature",
  "properties": {
    "iso:country":"US",
    "sg:address":"5669 W. Pico Blvd.",
    "sg:city":"Los Angeles",
    "sg:classifiers":[
        {
            "category":"Health Services",
            "subcategory":"Clinic",
            "type":"Services"
        },
        {
            "category":"Community Center",
            "type":"Public Place"
        }
    ],
    "sg:phone":"+1 323 938 9800",
    "sg:postcode":"90019",
    "sg:province":"CA",
    "sg:tags":[
        "cannabis",
        "medical"
    ],
    "wof:name":"TRC The Relief Collective",
    "wof:placetype":"venue"
},
  "geometry": {"coordinates":[-118.361809,34.050481],"type":"Point"}
}