{
  "type": "Feature",
  "properties": {
    "iso:country":"US",
    "sg:address":"8669 Baseline Rd",
    "sg:city":"Rancho Cucamonga",
    "sg:classifiers":[
        {
            "category":"Food & Beverages",
            "subcategory":"Bakery",
            "type":"Retail Goods"
        }
    ],
    "sg:phone":"+1 909 944 3808",
    "sg:postcode":"91730",
    "sg:province":"CA",
    "sg:tags":[
        "doughnut"
    ],
    "wof:name":"Freds Donuts",
    "wof:placetype":"venue"
},
  "geometry": {"coordinates":[-117.618416,34.121565],"type":"Point"}
}