{
  "type": "Feature",
  "properties": {
    "addr:full":"Main St Between A and B Hayward CA 94543",
    "addr:postcode":"94543",
    "addr:street":"Main St",
    "iso:country":"US",
    "sg:address":"Main St Between A and B",
    "sg:city":"Hayward",
    "sg:classifiers":[
        {
            "category":"Food & Beverages",
            "subcategory":"Farmers Market",
            "type":"Retail Goods"
        }
    ],
    "sg:phone":"+1 415 472 6100",
    "sg:postcode":"94543",
    "sg:province":"CA",
    "sg:website":"www.marincountyfarmersmarkets.or...",
    "wof:name":"Hayward Farmers' Market",
    "wof:placetype":"venue"
},
  "geometry": {"coordinates":[-122.08473600000001,37.675038],"type":"Point"}
}