{
  "type": "Feature",
  "properties": {
    "addr:full":"3732 Mt Diablo Blvd Ste 170 Lafayette CA 94549",
    "addr:housenumber":"3732",
    "addr:postcode":"94549",
    "addr:street":"Mt Diablo Blvd Ste 170",
    "iso:country":"US",
    "sg:address":"3732 Mt Diablo Blvd Ste 170",
    "sg:city":"Lafayette",
    "sg:classifiers":[
        {
            "category":"Coffee & Tea",
            "type":"Food & Drink"
        },
        {
            "category":"Restaurant",
            "type":"Food & Drink"
        }
    ],
    "sg:phone":"+1 925 283 6720",
    "sg:postcode":"94549",
    "sg:province":"CA",
    "sg:tags":[
        "cafeteria",
        "espresso"
    ],
    "wof:name":"Express Cafe",
    "wof:placetype":"venue"
},
  "geometry": {"coordinates":[-122.130563,37.88987],"type":"Point"}
}