{
  "type": "Feature",
  "properties": {
    "iso:country":"US",
    "sg:address":"1119 Chantilly Rd",
    "sg:city":"Los Angeles",
    "sg:classifiers":[
        {
            "category":"Building & Trades",
            "subcategory":"Construction",
            "type":"Services"
        }
    ],
    "sg:phone":"+1 310 472 6711",
    "sg:postcode":"90077",
    "sg:province":"CA",
    "sg:tags":[
        "contractor"
    ],
    "wof:name":"Woloz Construction",
    "wof:placetype":"venue"
},
  "geometry": {"coordinates":[-118.454567,34.085623],"type":"Point"}
}