{
  "type": "Feature",
  "properties": {
    "iso:country":"US",
    "sg:address":"2010 Bahia Dr",
    "sg:city":"Oxnard",
    "sg:classifiers":[
        {
            "category":"Shopping",
            "subcategory":"Florist",
            "type":"Retail Goods"
        }
    ],
    "sg:phone":"+1 805 485 6218",
    "sg:postcode":"93036",
    "sg:province":"CA",
    "wof:name":"Rlf Flowers",
    "wof:placetype":"venue"
},
  "geometry": {"coordinates":[-119.17492799999999,34.221368],"type":"Point"}
}