{
  "type": "Feature",
  "properties": {
    "addr:full":"6349 Markley Way Carmichael CA 95608",
    "addr:housenumber":"6349",
    "addr:postcode":"95608",
    "addr:street":"Markley Way",
    "iso:country":"US",
    "sg:address":"6349 Markley Way",
    "sg:city":"Carmichael",
    "sg:classifiers":[
        {
            "category":"Building & Trades",
            "subcategory":"Cleaning & Sanitation",
            "type":"Services"
        }
    ],
    "sg:phone":"+1 916 536 9242",
    "sg:postcode":"95608",
    "sg:province":"CA",
    "sg:tags":[
        "house"
    ],
    "wof:name":"Michele M Kimball",
    "wof:placetype":"venue"
},
  "geometry": {"coordinates":[-121.316185,38.664484],"type":"Point"}
}