{
  "type": "Feature",
  "properties": {
    "addr:full":"1649 Watt Ave Sacramento CA 95864",
    "addr:housenumber":"1649",
    "addr:postcode":"95864",
    "addr:street":"Watt Ave",
    "iso:country":"US",
    "sg:address":"1649 Watt Ave",
    "sg:city":"Sacramento",
    "sg:classifiers":[
        {
            "category":"Restaurant",
            "type":"Food & Drink"
        }
    ],
    "sg:menulink":"http://www.allmenus.com/ca/sacramento/59992-subway/menu/",
    "sg:phone":"+1 916 489 9288",
    "sg:postcode":"95864",
    "sg:province":"CA",
    "sg:tags":[
        "american",
        "sandwich"
    ],
    "wof:name":"Subway",
    "wof:placetype":"venue"
},
  "geometry": {"coordinates":[-121.383481,38.595288],"type":"Point"}
}