{
  "type": "Feature",
  "properties": {
    "iso:country":"US",
    "sg:address":"261 Carlisle Way",
    "sg:city":"Benicia",
    "sg:classifiers":[
        {
            "category":"Personal",
            "type":"Services"
        }
    ],
    "sg:phone":"+1 707 747 6703",
    "sg:postcode":"94510",
    "sg:province":"CA",
    "sg:tags":[
        "department",
        "motor",
        "vehicle"
    ],
    "wof:name":"Kelly's Auto Registration Svc",
    "wof:placetype":"venue"
},
  "geometry": {"coordinates":[-122.16518,38.072456],"type":"Point"}
}