{
  "type": "Feature",
  "properties": {
    "addr:full":"21221 Quail Springs Rd Tehachapi CA 93561",
    "addr:housenumber":"21221",
    "addr:postcode":"93561",
    "addr:street":"Quail Springs Rd",
    "iso:country":"US",
    "sg:address":"21221 Quail Springs Rd",
    "sg:city":"Tehachapi",
    "sg:classifiers":[
        {
            "category":"Building & Trades",
            "subcategory":"Construction",
            "type":"Services"
        }
    ],
    "sg:phone":"+1 661 822 5906",
    "sg:postcode":"93561",
    "sg:province":"CA",
    "sg:tags":[
        "contractor"
    ],
    "wof:name":"Oak Creek Construction",
    "wof:placetype":"venue"
},
  "geometry": {"coordinates":[-118.508925,35.149746],"type":"Point"}
}