{
  "type": "Feature",
  "properties": {
    "iso:country":"US",
    "sg:address":"192 Beacon St",
    "sg:city":"S San Francisco",
    "sg:classifiers":[
        {
            "category":"Health Services",
            "subcategory":"Doctor",
            "type":"Services"
        }
    ],
    "sg:phone":"+1 650 589 6500",
    "sg:postcode":"94080",
    "sg:province":"CA",
    "sg:tags":[
        "physician",
        "surgeon"
    ],
    "sg:website":"www.ushealthworks.com",
    "wof:name":"U.S. Health Works Medical Group",
    "wof:placetype":"venue"
},
  "geometry": {"coordinates":[-122.401979,37.639708],"type":"Point"}
}