{
  "type": "Feature",
  "properties": {
    "addr:full":"81100 Airport Blvd La Quinta CA 92274",
    "addr:housenumber":"81100",
    "addr:postcode":"92274",
    "addr:street":"Airport Blvd",
    "iso:country":"US",
    "sg:address":"81100 Airport Blvd",
    "sg:city":"La Quinta",
    "sg:classifiers":[
        {
            "category":"Professional",
            "type":"Services"
        }
    ],
    "sg:phone":"+1 760 777 7279",
    "sg:postcode":"92274",
    "sg:province":"CA",
    "sg:tags":[
        "establishment"
    ],
    "wof:name":"Village At The Palms Hm Owner",
    "wof:placetype":"venue"
},
  "geometry": {"coordinates":[-116.244305,33.642223],"type":"Point"}
}