{
  "type": "Feature",
  "properties": {
    "addr:full":"201 Lathrop Way Ste L Sacramento CA 95815",
    "addr:housenumber":"201",
    "addr:postcode":"95815",
    "addr:street":"Lathrop Way Ste L",
    "iso:country":"US",
    "sg:address":"201 Lathrop Way Ste L",
    "sg:city":"Sacramento",
    "sg:classifiers":[
        {
            "category":"Communications",
            "subcategory":"Film & Video Production",
            "type":"Services"
        },
        {
            "category":"Professional",
            "subcategory":"Art Services",
            "type":"Services"
        }
    ],
    "sg:phone":"+1 916 641 1253",
    "sg:postcode":"95815",
    "sg:province":"CA",
    "sg:tags":[
        "video/film",
        "graphic",
        "design"
    ],
    "sg:website":"www.rhinodesignstudio.com",
    "wof:name":"Rhino Design",
    "wof:placetype":"venue"
},
  "geometry": {"coordinates":[-121.463048,38.595544],"type":"Point"}
}