{
  "type": "Feature",
  "properties": {
    "addr:full":"12200 Venice Blvd Los Angeles CA 90066",
    "addr:housenumber":"12200",
    "addr:postcode":"90066",
    "addr:street":"Venice Blvd",
    "iso:country":"US",
    "sg:address":"12200 Venice Blvd",
    "sg:city":"Los Angeles",
    "sg:classifiers":[
        {
            "category":"Personal",
            "subcategory":"Beauty Salon",
            "type":"Services"
        }
    ],
    "sg:phone":"+1 310 391 2800",
    "sg:postcode":"90066",
    "sg:province":"CA",
    "sg:tags":[
        "hair"
    ],
    "sg:website":"www.floydsbarbershop.com/index.p...",
    "wof:name":"Floyd's 99 Barbershop",
    "wof:placetype":"venue"
},
  "geometry": {"coordinates":[-118.43125999999999,34.004751],"type":"Point"}
}