{
  "type": "Feature",
  "properties": {
    "addr:full":"12017 Calabash Ave Fontana CA 92337",
    "addr:housenumber":"12017",
    "addr:postcode":"92337",
    "addr:street":"Calabash Ave",
    "iso:country":"US",
    "sg:address":"12017 Calabash Ave",
    "sg:city":"Fontana",
    "sg:classifiers":[
        {
            "category":"Freight",
            "type":"Transportation"
        }
    ],
    "sg:phone":"+1 909 356 0627",
    "sg:postcode":"92337",
    "sg:province":"CA",
    "sg:tags":[
        "trucking"
    ],
    "wof:name":"Five R's Trucking",
    "wof:placetype":"venue"
},
  "geometry": {"coordinates":[-117.50251799999999,34.034188],"type":"Point"}
}