{
  "type": "Feature",
  "properties": {
    "iso:country":"US",
    "sg:address":"11836 Downey Ave",
    "sg:city":"Downey",
    "sg:classifiers":[
        {
            "category":"Personal",
            "subcategory":"Beauty Salon",
            "type":"Services"
        }
    ],
    "sg:phone":"+1 562 862 5495",
    "sg:postcode":"90241",
    "sg:province":"CA",
    "wof:name":"EVO Hair Design",
    "wof:placetype":"venue"
},
  "geometry": {"coordinates":[-118.138592,33.932081],"type":"Point"}
}