{
  "type": "Feature",
  "properties": {
    "iso:country":"US",
    "sg:address":"2353 N Hobart Blvd",
    "sg:city":"Los Angeles",
    "sg:classifiers":[
        {
            "category":"Real Estate",
            "subcategory":"Real Estate Operator",
            "type":"Services"
        }
    ],
    "sg:phone":"+1 323 463 6097",
    "sg:postcode":"90027",
    "sg:province":"CA",
    "sg:tags":[
        "building",
        "apartment"
    ],
    "wof:name":"Garcia Investments",
    "wof:placetype":"venue"
},
  "geometry": {"coordinates":[-118.302865,34.113904],"type":"Point"}
}