{
  "type": "Feature",
  "properties": {
    "addr:full":"118 McHenry Ave Modesto CA 95354",
    "addr:housenumber":"118",
    "addr:postcode":"ca 95354",
    "addr:street":"Mchenry Ave",
    "iso:country":"US",
    "sg:address":"118 McHenry Ave",
    "sg:city":"Modesto",
    "sg:classifiers":[
        {
            "category":"Insurance",
            "subcategory":"Insurance Agent",
            "type":"Services"
        }
    ],
    "sg:phone":"+1 209 567 1111",
    "sg:postcode":"95354",
    "sg:province":"CA",
    "sg:website":"www.lowcostquote.com",
    "wof:name":"Gladiator Insurance",
    "wof:placetype":"venue"
},
  "geometry": {"coordinates":[-120.99363200000001,37.645771],"type":"Point"}
}