{
  "type": "Feature",
  "properties": {
    "addr:full":"9175 Eton Ave Chatsworth CA 91311",
    "addr:housenumber":"9175",
    "addr:postcode":"91311",
    "addr:street":"Eton Ave",
    "iso:country":"US",
    "sg:address":"9175 Eton Ave",
    "sg:city":"Chatsworth",
    "sg:classifiers":[
        {
            "category":"Manufacturing",
            "subcategory":"Chemicals & Compounds",
            "type":"Manufacturing & Wholesale Goods"
        }
    ],
    "sg:phone":"+1 818 764 8700",
    "sg:postcode":"91311",
    "sg:province":"CA",
    "sg:tags":[
        "agricultural",
        "mfg"
    ],
    "wof:name":"Brooker Chemical Inc",
    "wof:placetype":"venue"
},
  "geometry": {"coordinates":[-118.594779,34.238997],"type":"Point"}
}