{
  "type": "Feature",
  "properties": {
    "addr:full":"1609 Oaktree Pl Glendora CA 91741",
    "addr:housenumber":"1609",
    "addr:postcode":"91741",
    "addr:street":"Oaktree Pl",
    "iso:country":"US",
    "sg:address":"1609 Oaktree Pl",
    "sg:city":"Glendora",
    "sg:classifiers":[
        {
            "category":"Building & Trades",
            "subcategory":"Landscaping Services",
            "type":"Services"
        }
    ],
    "sg:phone":"+1 626 450 6763",
    "sg:postcode":"91741",
    "sg:province":"CA",
    "sg:tags":[
        "tree"
    ],
    "wof:name":"David's Tree Svc",
    "wof:placetype":"venue"
},
  "geometry": {"coordinates":[-117.834694,34.139728],"type":"Point"}
}