{
  "type": "Feature",
  "properties": {
    "addr:full":"1835 N Blackstone Ave Fresno CA 93703",
    "addr:housenumber":"1835",
    "addr:postcode":"93703",
    "addr:street":"N Blackstone Ave",
    "iso:country":"US",
    "sg:address":"1835 N Blackstone Ave",
    "sg:city":"Fresno",
    "sg:classifiers":[
        {
            "category":"Personal",
            "subcategory":"Beauty Salon",
            "type":"Services"
        }
    ],
    "sg:phone":"+1 559 264 2774",
    "sg:postcode":"93703",
    "sg:province":"CA",
    "sg:tags":[
        "hair",
        "stylist"
    ],
    "wof:name":"Cuts & Beyond",
    "wof:placetype":"venue"
},
  "geometry": {"coordinates":[-119.790656,36.76714],"type":"Point"}
}