{
  "type": "Feature",
  "properties": {
    "addr:full":"2809 Middlefield Rd Redwood City CA 94063",
    "addr:housenumber":"2809",
    "addr:postcode":"94063",
    "addr:street":"Middlefield Rd",
    "iso:country":"US",
    "sg:address":"2809 Middlefield Rd",
    "sg:city":"Redwood City",
    "sg:classifiers":[
        {
            "category":"Restaurant",
            "type":"Food & Drink"
        }
    ],
    "sg:phone":"+1 650 368 6444",
    "sg:postcode":"94063",
    "sg:province":"CA",
    "wof:name":"7 Mares",
    "wof:placetype":"venue"
},
  "geometry": {"coordinates":[-122.209177,37.475318],"type":"Point"}
}