{
  "type": "Feature",
  "properties": {
    "addr:full":"12832 Garden Grove Blvd Garden Grove CA 92843",
    "addr:housenumber":"12832",
    "addr:postcode":"92843",
    "addr:street":"Garden Grove Blvd",
    "iso:country":"US",
    "sg:address":"12832 Garden Grove Blvd",
    "sg:city":"Garden Grove",
    "sg:classifiers":[
        {
            "category":"Professional",
            "type":"Services"
        }
    ],
    "sg:phone":"+1 714 530 0389",
    "sg:postcode":"92843",
    "sg:province":"CA",
    "wof:name":"Virlouise",
    "wof:placetype":"venue"
},
  "geometry": {"coordinates":[-117.90647800000001,33.774355],"type":"Point"}
}