{
  "type": "Feature",
  "properties": {
    "iso:country":"US",
    "sg:address":"2044 Sunset Dr",
    "sg:city":"Pacific Grove",
    "sg:classifiers":[
        {
            "category":"Building & Trades",
            "subcategory":"Construction",
            "type":"Services"
        }
    ],
    "sg:phone":"+1 831 657 9947",
    "sg:postcode":"93950",
    "sg:province":"CA",
    "sg:tags":[
        "contractor"
    ],
    "wof:name":"H & M Construction",
    "wof:placetype":"venue"
},
  "geometry": {"coordinates":[-121.93437400000001,36.615882],"type":"Point"}
}