{
  "type": "Feature",
  "properties": {
    "iso:country":"US",
    "sg:address":"6021 N Figueroa St Ste C",
    "sg:city":"Los Angeles",
    "sg:classifiers":[
        {
            "category":"Bakery",
            "type":"Food & Drink"
        }
    ],
    "sg:phone":"+1 323 256 0980",
    "sg:postcode":"90042",
    "sg:province":"CA",
    "wof:name":"Andy's Bakery",
    "wof:placetype":"venue"
},
  "geometry": {"coordinates":[-118.189003,34.1115],"type":"Point"}
}