{
  "type": "Feature",
  "properties": {
    "addr:full":"101 Howard Street Suite B San Francisco CA 94105",
    "addr:housenumber":"101",
    "addr:postcode":"94105",
    "addr:street":"Howard Street Suite B",
    "iso:country":"US",
    "sg:address":"101 Howard Street Suite B",
    "sg:city":"San Francisco",
    "sg:classifiers":[
        {
            "category":"Health Services",
            "subcategory":"Chiropractor",
            "type":"Services"
        }
    ],
    "sg:phone":"+1 415 896 2225",
    "sg:postcode":"94105",
    "sg:province":"CA",
    "wof:name":"Palmer Alumni Chiropractic Referral Service",
    "wof:placetype":"venue"
},
  "geometry": {"coordinates":[-122.39299800000001,37.791302],"type":"Point"}
}