{
  "type": "Feature",
  "properties": {
    "iso:country":"US",
    "sg:address":"801 E Palmdale Blvd",
    "sg:city":"Palmdale",
    "sg:classifiers":[
        {
            "category":"Insurance",
            "subcategory":"Insurance Agent",
            "type":"Services"
        }
    ],
    "sg:phone":"+1 661 947 5936",
    "sg:postcode":"93550",
    "sg:province":"CA",
    "wof:name":"Latinowide",
    "wof:placetype":"venue"
},
  "geometry": {"coordinates":[-118.11583899999999,34.579521],"type":"Point"}
}