{
  "type": "Feature",
  "properties": {
    "addr:full":"2575 N San Fernando Rd Los Angeles CA 90065",
    "addr:housenumber":"2575",
    "addr:postcode":"90065",
    "addr:street":"N San Fernando Rd",
    "iso:country":"US",
    "sg:address":"2575 N San Fernando Rd",
    "sg:city":"Los Angeles",
    "sg:classifiers":[
        {
            "category":"Professional",
            "type":"Services"
        }
    ],
    "sg:phone":"+1 323 227 1514",
    "sg:postcode":"90065",
    "sg:province":"CA",
    "sg:tags":[
        "establishment"
    ],
    "wof:name":"El Chente",
    "wof:placetype":"venue"
},
  "geometry": {"coordinates":[-118.238795,34.10512],"type":"Point"}
}