{
  "type": "Feature",
  "properties": {
    "iso:country":"US",
    "sg:address":"3960 Studebaker Rd Ste 109",
    "sg:city":"Long Beach",
    "sg:classifiers":[
        {
            "category":"Personal",
            "subcategory":"Tanning Parlor",
            "type":"Services"
        },
        {
            "category":"Personal",
            "subcategory":"Skin Care",
            "type":"Services"
        }
    ],
    "sg:phone":"+1 562 429 3400",
    "sg:postcode":"90808",
    "sg:province":"CA",
    "sg:website":"www.tanninginlongbeach.com/",
    "wof:name":"BronzRepublic Tanning Spa",
    "wof:placetype":"venue"
},
  "geometry": {"coordinates":[-118.098972,33.829711],"type":"Point"}
}