{
  "type": "Feature",
  "properties": {
    "addr:full":"9051 Soquel Dr Aptos CA 95003",
    "addr:housenumber":"9051",
    "addr:postcode":"ca 95003",
    "addr:street":"Soquel Dr",
    "iso:country":"US",
    "sg:address":"9051 Soquel Dr",
    "sg:city":"Aptos",
    "sg:classifiers":[
        {
            "category":"Personal",
            "subcategory":"Beauty Salon",
            "type":"Services"
        }
    ],
    "sg:phone":"+1 831 662 1300",
    "sg:postcode":"95003",
    "sg:province":"CA",
    "sg:tags":[
        "hair"
    ],
    "sg:website":"www.aptosblisssalon.com",
    "wof:name":"Bliss",
    "wof:placetype":"venue"
},
  "geometry": {"coordinates":[-121.89093800000001,36.975654],"type":"Point"}
}