{
  "type": "Feature",
  "properties": {
    "addr:full":"8416 Florence Ave Downey CA 90240",
    "addr:housenumber":"8416",
    "addr:postcode":"90240",
    "addr:street":"Florence Ave",
    "iso:country":"US",
    "sg:address":"8416 Florence Ave",
    "sg:city":"Downey",
    "sg:classifiers":[
        {
            "category":"Professional",
            "subcategory":"Testing Lab",
            "type":"Services"
        }
    ],
    "sg:phone":"+1 562 923 1837",
    "sg:postcode":"90240",
    "sg:province":"CA",
    "sg:tags":[
        "laboratory"
    ],
    "wof:name":"ICS Radiation Technologies",
    "wof:placetype":"venue"
},
  "geometry": {"coordinates":[-118.12406,33.95071],"type":"Point"}
}