{
  "type": "Feature",
  "properties": {
    "iso:country":"US",
    "sg:address":"1948 Washington St",
    "sg:city":"Lemon Grove",
    "sg:classifiers":[
        {
            "category":"Wholesale",
            "subcategory":"Non-durable Goods",
            "type":"Manufacturing & Wholesale Goods"
        }
    ],
    "sg:phone":"+1 619 462 0380",
    "sg:postcode":"91945",
    "sg:province":"CA",
    "wof:name":"Avenday Ventures Trading Co",
    "wof:placetype":"venue"
},
  "geometry": {"coordinates":[-117.02337799999999,32.726148],"type":"Point"}
}