{
  "type": "Feature",
  "properties": {
    "addr:full":"1644 Radnor Ave Ventura CA 93004",
    "addr:housenumber":"1644",
    "addr:postcode":"93004",
    "addr:street":"Radnor Ave",
    "iso:country":"US",
    "sg:address":"1644 Radnor Ave",
    "sg:city":"Ventura",
    "sg:classifiers":[
        {
            "category":"Food & Beverages",
            "subcategory":"Specialty",
            "type":"Retail Goods"
        }
    ],
    "sg:phone":"+1 805 647 2266",
    "sg:postcode":"93004",
    "sg:province":"CA",
    "sg:tags":[
        "health",
        "diet"
    ],
    "sg:website":"www.btrim4life.com",
    "wof:name":"Herbalife Distributor",
    "wof:placetype":"venue"
},
  "geometry": {"coordinates":[-119.175915,34.265663],"type":"Point"}
}