{
  "type": "Feature",
  "properties": {
    "addr:full":"5241 Saint Helena Rd Santa Rosa CA 95404",
    "addr:housenumber":"5241",
    "addr:postcode":"95404",
    "addr:street":"Saint Helena Rd",
    "iso:country":"US",
    "sg:address":"5241 Saint Helena Rd",
    "sg:city":"Santa Rosa",
    "sg:classifiers":[
        {
            "category":"Autos & Motor Vehicles",
            "subcategory":"Automobile Sales",
            "type":"Retail Goods"
        }
    ],
    "sg:phone":"+1 707 526 9680",
    "sg:postcode":"95404",
    "sg:province":"CA",
    "sg:tags":[
        "used"
    ],
    "wof:name":"Usedcarfinder",
    "wof:placetype":"venue"
},
  "geometry": {"coordinates":[-122.647752,38.505536],"type":"Point"}
}