{
  "type": "Feature",
  "properties": {
    "iso:country":"US",
    "sg:address":"3811 Schaefer Ave",
    "sg:city":"Chino",
    "sg:classifiers":[
        {
            "category":"Organizations",
            "subcategory":"Religious Organization",
            "type":"Services"
        }
    ],
    "sg:phone":"+1 909 464 1554",
    "sg:postcode":"91710",
    "sg:province":"CA",
    "sg:tags":[
        "church"
    ],
    "wof:name":"Lionheart Christian Fellowship",
    "wof:placetype":"venue"
},
  "geometry": {"coordinates":[-117.719775,34.004301],"type":"Point"}
}