{
  "type": "Feature",
  "properties": {
    "addr:full":"1254 N Everett St Glendale CA 91207",
    "addr:housenumber":"1254",
    "addr:postcode":"91207",
    "addr:street":"N Everett St",
    "iso:country":"US",
    "sg:address":"1254 N Everett St",
    "sg:city":"Glendale",
    "sg:classifiers":[
        {
            "category":"Health Services",
            "subcategory":"Clinic",
            "type":"Services"
        }
    ],
    "sg:phone":"+1 818 545 3709",
    "sg:postcode":"91207",
    "sg:province":"CA",
    "sg:tags":[
        "information",
        "alcoholism",
        "treatment"
    ],
    "wof:name":"Bravo Rehab Services Inc",
    "wof:placetype":"venue"
},
  "geometry": {"coordinates":[-118.24508400000001,34.164051],"type":"Point"}
}