{
  "type": "Feature",
  "properties": {
    "addr:full":"1600 S Union Ave Bakersfield CA 93307",
    "addr:housenumber":"1600",
    "addr:postcode":"93307",
    "addr:street":"S Union Ave",
    "iso:country":"US",
    "sg:address":"1600 S Union Ave",
    "sg:city":"Bakersfield",
    "sg:classifiers":[
        {
            "category":"Manufacturing",
            "subcategory":"Tools & Machinery",
            "type":"Manufacturing & Wholesale Goods"
        }
    ],
    "sg:phone":"+1 661 397 4987",
    "sg:postcode":"93307",
    "sg:province":"CA",
    "sg:tags":[
        "machine",
        "shop"
    ],
    "wof:name":"Farley Machines Inc",
    "wof:placetype":"venue"
},
  "geometry": {"coordinates":[-119.00294599999999,35.337143],"type":"Point"}
}