{
  "type": "Feature",
  "properties": {
    "iso:country":"US",
    "sg:address":"4311 W Sunset Blvd",
    "sg:city":"Los Angeles",
    "sg:classifiers":[
        {
            "category":"Retail",
            "subcategory":"Auto Repair",
            "type":"Services"
        }
    ],
    "sg:phone":"+1 323 665 4420",
    "sg:postcode":"90029",
    "sg:province":"CA",
    "sg:tags":[
        "automobile",
        "electric"
    ],
    "wof:name":"Mario & Bro's Auto Electric",
    "wof:placetype":"venue"
},
  "geometry": {"coordinates":[-118.28385299999999,34.095627],"type":"Point"}
}