{
  "type": "Feature",
  "properties": {
    "addr:full":"530 W 27th Street Los Angeles CA 90007",
    "addr:housenumber":"530",
    "addr:postcode":"90007",
    "addr:street":"W 27Th Street",
    "iso:country":"US",
    "sg:address":"530 W 27th Street",
    "sg:city":"Los Angeles",
    "sg:classifiers":[
        {
            "category":"Building & Trades",
            "subcategory":"Plumbing",
            "type":"Services"
        }
    ],
    "sg:phone":"+1 213 747 0001",
    "sg:postcode":"90007",
    "sg:province":"CA",
    "wof:name":"Aqualife Water",
    "wof:placetype":"venue"
},
  "geometry": {"coordinates":[-118.287434,34.030788],"type":"Point"}
}