{
  "type": "Feature",
  "properties": {
    "addr:full":"1998 E Valley Pkwy Escondido CA 92027",
    "addr:housenumber":"1998",
    "addr:postcode":"92027",
    "addr:street":"E Valley Pkwy",
    "iso:country":"US",
    "sg:address":"1998 E Valley Pkwy",
    "sg:city":"Escondido",
    "sg:classifiers":[
        {
            "category":"Autos & Motor Vehicles",
            "subcategory":"Auto Supplies",
            "type":"Retail Goods"
        },
        {
            "category":"Manufacturing",
            "subcategory":"Petroleum Products",
            "type":"Manufacturing & Wholesale Goods"
        }
    ],
    "sg:phone":"+1 760 466 1624",
    "sg:postcode":"92027",
    "sg:province":"CA",
    "sg:tags":[
        "lubricating",
        "lube",
        "oil"
    ],
    "wof:name":"Ez Lube Llc Num106",
    "wof:placetype":"venue"
},
  "geometry": {"coordinates":[-117.051811,33.137508],"type":"Point"}
}