{
  "type": "Feature",
  "properties": {
    "iso:country":"US",
    "sg:address":"10175 Joerschke Dr",
    "sg:city":"Grass Valley",
    "sg:classifiers":[
        {
            "category":"Real Estate",
            "subcategory":"Real Estate Agent",
            "type":"Services"
        }
    ],
    "sg:phone":"+1 530 272 8657",
    "sg:postcode":"95945",
    "sg:province":"CA",
    "sg:tags":[
        "management"
    ],
    "wof:name":"ACM Properties",
    "wof:placetype":"venue"
},
  "geometry": {"coordinates":[-121.040789,39.231902],"type":"Point"}
}