{
  "type": "Feature",
  "properties": {
    "iso:country":"US",
    "sg:address":"535 W Valley Blvd",
    "sg:city":"San Gabriel",
    "sg:classifiers":[
        {
            "category":"Restaurant",
            "type":"Food & Drink"
        }
    ],
    "sg:phone":"+1 626 281 1226",
    "sg:postcode":"91776",
    "sg:province":"CA",
    "sg:tags":[
        "chinese"
    ],
    "sg:website":"bamboodlesrestaurant.com",
    "wof:name":"Bamboodles",
    "wof:placetype":"venue"
},
  "geometry": {"coordinates":[-118.10782399999999,34.079383],"type":"Point"}
}