{
  "type": "Feature",
  "properties": {
    "iso:country":"US",
    "sg:address":"591 S Fortuna Blvd",
    "sg:city":"Fortuna",
    "sg:classifiers":[
        {
            "category":"Real Estate",
            "subcategory":"Real Estate Agent",
            "type":"Services"
        }
    ],
    "sg:phone":"+1 707 725 4456",
    "sg:postcode":"95540",
    "sg:province":"CA",
    "wof:name":"Debets & Assoc Realtors",
    "wof:placetype":"venue"
},
  "geometry": {"coordinates":[-124.14658300000001,40.586053],"type":"Point"}
}