{
  "type": "Feature",
  "properties": {
    "addr:full":"2511 N Long Beach Blvd Long Beach CA 90806",
    "addr:housenumber":"2511",
    "addr:postcode":"90806",
    "addr:street":"N Long Beach Blvd",
    "iso:country":"US",
    "sg:address":"2511 N Long Beach Blvd",
    "sg:city":"Long Beach",
    "sg:classifiers":[
        {
            "category":"Health Services",
            "subcategory":"Doctor",
            "type":"Services"
        }
    ],
    "sg:phone":"+1 562 981 1501",
    "sg:postcode":"90806",
    "sg:province":"CA",
    "sg:tags":[
        "clinic"
    ],
    "wof:name":"Total Family Support Clinic",
    "wof:placetype":"venue"
},
  "geometry": {"coordinates":[-118.189431,33.803273],"type":"Point"}
}