{
  "type": "Feature",
  "properties": {
    "addr:full":"17210 Oak St Fountain Valley CA 92708",
    "addr:housenumber":"17210",
    "addr:postcode":"92708",
    "addr:street":"Oak St",
    "iso:country":"US",
    "sg:address":"17210 Oak St",
    "sg:city":"Fountain Valley",
    "sg:classifiers":[
        {
            "category":"Professional",
            "subcategory":"Management & Consulting",
            "type":"Services"
        }
    ],
    "sg:phone":"+1 714 847 8203",
    "sg:postcode":"92708",
    "sg:province":"CA",
    "sg:tags":[
        "employment",
        "screening"
    ],
    "sg:website":"www.codesp.com",
    "wof:name":"CODESP",
    "wof:placetype":"venue"
},
  "geometry": {"coordinates":[-117.966937,33.712099],"type":"Point"}
}