{
  "type": "Feature",
  "properties": {
    "iso:country":"US",
    "sg:address":"1911 Commercenter Ct",
    "sg:city":"San Bernardino",
    "sg:classifiers":[
        {
            "category":"Banks & Credit Unions",
            "subcategory":"Bank",
            "type":"Services"
        }
    ],
    "sg:phone":"+1 909 890 0550",
    "sg:postcode":"92408",
    "sg:province":"CA",
    "sg:tags":[
        "loan",
        "real estate"
    ],
    "wof:name":"Independent Home Loans",
    "wof:placetype":"venue"
},
  "geometry": {"coordinates":[-117.28222599999999,34.066179],"type":"Point"}
}