{
  "type": "Feature",
  "properties": {
    "iso:country":"US",
    "sg:address":"2966 College Ave",
    "sg:city":"Berkeley",
    "sg:classifiers":[
        {
            "category":"Cinema",
            "subcategory":"Movie Theater",
            "type":"Entertainment"
        }
    ],
    "sg:phone":"+1 510 433 9730",
    "sg:postcode":"94705",
    "sg:province":"CA",
    "sg:website":"www.rialtocinemas.com/elmwood",
    "wof:name":"Rialto Cinemas Elmwood",
    "wof:placetype":"venue"
},
  "geometry": {"coordinates":[-122.253293,37.856681],"type":"Point"}
}