{
  "type": "Feature",
  "properties": {
    "addr:full":"2540 Venture Oaks Way Sacramento CA 95833",
    "addr:housenumber":"2540",
    "addr:postcode":"95833",
    "addr:street":"Venture Oaks Way",
    "iso:country":"US",
    "sg:address":"2540 Venture Oaks Way",
    "sg:city":"Sacramento",
    "sg:classifiers":[
        {
            "category":"Restaurant",
            "type":"Food & Drink"
        }
    ],
    "sg:phone":"+1 916 568 5400",
    "sg:postcode":"95833",
    "sg:province":"CA",
    "sg:website":"hiltongardeninn.hilton.com/en/gi...",
    "wof:name":"Great American Grill",
    "wof:placetype":"venue"
},
  "geometry": {"coordinates":[-121.51464,38.611388],"type":"Point"}
}