{
  "type": "Feature",
  "properties": {
    "iso:country":"US",
    "sg:address":"1971 American River Trl",
    "sg:city":"Cool",
    "sg:classifiers":[
        {
            "category":"Retail",
            "subcategory":"Veterinary Services",
            "type":"Services"
        }
    ],
    "sg:phone":"+1 530 885 6113",
    "sg:postcode":"95614",
    "sg:province":"CA",
    "sg:tags":[
        "veterinarian",
        "specialty"
    ],
    "wof:name":"Rma",
    "wof:placetype":"venue"
},
  "geometry": {"coordinates":[-120.988477,38.905783],"type":"Point"}
}