{
  "type": "Feature",
  "properties": {
    "addr:full":"13548 Magnolia Ave Corona CA 92879",
    "addr:housenumber":"13548",
    "addr:postcode":"92879",
    "addr:street":"Magnolia Ave",
    "iso:country":"US",
    "sg:address":"13548 Magnolia Ave",
    "sg:city":"Corona",
    "sg:classifiers":[
        {
            "category":"Retail",
            "subcategory":"Auto Repair",
            "type":"Services"
        }
    ],
    "sg:phone":"+1 951 272 1763",
    "sg:postcode":"92879",
    "sg:province":"CA",
    "sg:tags":[
        "repairing",
        "automobile"
    ],
    "wof:name":"Barbosa Carburadores",
    "wof:placetype":"venue"
},
  "geometry": {"coordinates":[-117.52083,33.878218],"type":"Point"}
}