{
  "type": "Feature",
  "properties": {
    "addr:full":"3520 Jenny Lind Ave North Highlands CA 95660",
    "addr:housenumber":"3520",
    "addr:postcode":"95660",
    "addr:street":"Jenny Lind Ave",
    "iso:country":"US",
    "sg:address":"3520 Jenny Lind Ave",
    "sg:city":"North Highlands",
    "sg:classifiers":[
        {
            "category":"Freight",
            "type":"Transportation"
        }
    ],
    "sg:phone":"+1 916 487 9785",
    "sg:postcode":"95660",
    "sg:province":"CA",
    "sg:tags":[
        "operator",
        "local",
        "trucking"
    ],
    "wof:name":"Heinz Dairy Delivery",
    "wof:placetype":"venue"
},
  "geometry": {"coordinates":[-121.382002,38.647611],"type":"Point"}
}