{
  "type": "Feature",
  "properties": {
    "iso:country":"US",
    "sg:address":"206 N Santa Cruz Ave",
    "sg:city":"Los Gatos",
    "sg:classifiers":[
        {
            "category":"Restaurant",
            "type":"Food & Drink"
        }
    ],
    "sg:phone":"+1 408 395 6434",
    "sg:postcode":"95030",
    "sg:province":"CA",
    "sg:tags":[
        "seafood",
        "steakhouse"
    ],
    "sg:website":"www.forbesmillsteakhouse.com",
    "wof:name":"Forbes Mill Steakhouse",
    "wof:placetype":"venue"
},
  "geometry": {"coordinates":[-121.981897,37.226016],"type":"Point"}
}