{
  "type": "Feature",
  "properties": {
    "addr:full":"110 W Tehachapi Blvd Tehachapi CA 93561",
    "addr:housenumber":"110",
    "addr:postcode":"93561",
    "addr:street":"W Tehachapi Blvd",
    "iso:country":"US",
    "sg:address":"110 W Tehachapi Blvd",
    "sg:city":"Tehachapi",
    "sg:classifiers":[
        {
            "category":"Restaurant",
            "type":"Food & Drink"
        }
    ],
    "sg:phone":"+1 661 822 4207",
    "sg:postcode":"93561",
    "sg:province":"CA",
    "wof:name":"Kelcy's Restaurant",
    "wof:placetype":"venue"
},
  "geometry": {"coordinates":[-118.448965,35.132225],"type":"Point"}
}