{
  "type": "Feature",
  "properties": {
    "addr:full":"219 Dorado Ter San Francisco CA 94112",
    "addr:housenumber":"219",
    "addr:postcode":"94112",
    "addr:street":"Dorado Ter",
    "iso:country":"US",
    "sg:address":"219 Dorado Ter",
    "sg:city":"San Francisco",
    "sg:classifiers":[
        {
            "category":"Freight",
            "type":"Transportation"
        }
    ],
    "sg:phone":"+1 415 391 7681",
    "sg:postcode":"94112",
    "sg:province":"CA",
    "sg:tags":[
        "arrangement"
    ],
    "wof:name":"Jenken Freight Services",
    "wof:placetype":"venue"
},
  "geometry": {"coordinates":[-122.46099700000001,37.725706],"type":"Point"}
}