{
  "type": "Feature",
  "properties": {
    "addr:full":"630 N Sepulveda Blvd Ste 14A El Segundo CA 90245",
    "addr:housenumber":"630;14a",
    "addr:postcode":"90245",
    "addr:street":"N Sepulveda Blvd Ste",
    "iso:country":"US",
    "sg:address":"630 N Sepulveda Blvd Ste 14A",
    "sg:city":"El Segundo",
    "sg:classifiers":[
        {
            "category":"Shopping",
            "subcategory":"Pets & Pet Supplies",
            "type":"Retail Goods"
        }
    ],
    "sg:phone":"+1 310 322 3474",
    "sg:postcode":"90245",
    "sg:province":"CA",
    "sg:tags":[
        "store"
    ],
    "sg:website":"www.jimsexoticfish.com",
    "wof:name":"Jim's Exotic Fish",
    "wof:placetype":"venue"
},
  "geometry": {"coordinates":[-118.39619999999999,33.924127],"type":"Point"}
}