{
  "type": "Feature",
  "properties": {
    "iso:country":"US",
    "sg:address":"360 San Miguel Dr",
    "sg:city":"Newport Beach",
    "sg:classifiers":[
        {
            "category":"Health Services",
            "subcategory":"Dentist",
            "type":"Services"
        }
    ],
    "sg:phone":"+1 949 640 0300",
    "sg:postcode":"92660",
    "sg:province":"CA",
    "wof:name":"Kimberly Johnson, DDS",
    "wof:placetype":"venue"
},
  "geometry": {"coordinates":[-117.871681,33.613358],"type":"Point"}
}