{
  "type": "Feature",
  "properties": {
    "addr:full":"31 Wildflower Ct Danville CA 94526",
    "addr:housenumber":"31",
    "addr:postcode":"94526",
    "addr:street":"Wildflower Ct",
    "iso:country":"US",
    "sg:address":"31 Wildflower Ct",
    "sg:city":"Danville",
    "sg:classifiers":[
        {
            "category":"Professional",
            "subcategory":"Management & Consulting",
            "type":"Services"
        }
    ],
    "sg:phone":"+1 925 837 2782",
    "sg:postcode":"94526",
    "sg:province":"CA",
    "sg:tags":[
        "consultant",
        "business"
    ],
    "wof:name":"Quick Plan Svc",
    "wof:placetype":"venue"
},
  "geometry": {"coordinates":[-121.957205,37.81263],"type":"Point"}
}