{
  "type": "Feature",
  "properties": {
    "iso:country":"US",
    "sg:address":"4 Las Aromas",
    "sg:city":"Orinda",
    "sg:classifiers":[
        {
            "category":"Building & Trades",
            "subcategory":"Construction",
            "type":"Services"
        }
    ],
    "sg:phone":"+1 925 254 6785",
    "sg:postcode":"94563",
    "sg:province":"CA",
    "sg:tags":[
        "roofing",
        "contractor"
    ],
    "wof:name":"Robertson & Co",
    "wof:placetype":"venue"
},
  "geometry": {"coordinates":[-122.179643,37.894349],"type":"Point"}
}