{
  "type": "Feature",
  "properties": {
    "addr:full":"1399 Broadway Burlingame CA 94010",
    "addr:housenumber":"1399",
    "addr:postcode":"94010",
    "addr:street":"Broadway",
    "iso:country":"US",
    "sg:address":"1399 Broadway",
    "sg:city":"Burlingame",
    "sg:classifiers":[
        {
            "category":"Insurance",
            "subcategory":"Health Insurance",
            "type":"Services"
        }
    ],
    "sg:phone":"+1 650 347 2058",
    "sg:postcode":"94010",
    "sg:province":"CA",
    "sg:tags":[
        "market"
    ],
    "sg:website":"www.earthbeamfoods.com",
    "wof:name":"Earthbeam Natural Foods",
    "wof:placetype":"venue"
},
  "geometry": {"coordinates":[-122.36599699999999,37.5849],"type":"Point"}
}