{
  "type": "Feature",
  "properties": {
    "iso:country":"US",
    "sg:address":"2619 International Blvd",
    "sg:city":"Oakland",
    "sg:classifiers":[
        {
            "category":"Shopping",
            "subcategory":"Music",
            "type":"Retail Goods"
        }
    ],
    "sg:phone":"+1 510 536 6257",
    "sg:postcode":"94601",
    "sg:province":"CA",
    "sg:tags":[
        "video",
        "disc",
        "tape",
        "cassette"
    ],
    "wof:name":"May's Video",
    "wof:placetype":"venue"
},
  "geometry": {"coordinates":[-122.23168699999999,37.780829],"type":"Point"}
}