{
  "type": "Feature",
  "properties": {
    "addr:full":"600 Deep Valley Dr Rolling Hls Ests CA 90274",
    "addr:housenumber":"600",
    "addr:postcode":"90274",
    "addr:street":"Deep Valley Dr Rolling",
    "iso:country":"US",
    "sg:address":"600 Deep Valley Dr",
    "sg:city":"Rolling Hls Ests",
    "sg:classifiers":[
        {
            "category":"Personal",
            "subcategory":"Beauty Salon",
            "type":"Services"
        }
    ],
    "sg:phone":"+1 310 266 5835",
    "sg:postcode":"90274",
    "sg:province":"CA",
    "wof:name":"Charlene Stipech's Hair Salon",
    "wof:placetype":"venue"
},
  "geometry": {"coordinates":[-118.368646,33.769503],"type":"Point"}
}