{
  "type": "Feature",
  "properties": {
    "addr:full":"2110 N Blackstone Ave Fresno CA 93704",
    "addr:housenumber":"2110",
    "addr:postcode":"93704",
    "addr:street":"N Blackstone Ave",
    "iso:country":"US",
    "sg:address":"2110 N Blackstone Ave",
    "sg:city":"Fresno",
    "sg:classifiers":[
        {
            "category":"Personal",
            "subcategory":"Barber",
            "type":"Services"
        }
    ],
    "sg:phone":"+1 559 224 9963",
    "sg:postcode":"93704",
    "sg:province":"CA",
    "wof:name":"All Eyes On Me Barber Shop 2",
    "wof:placetype":"venue"
},
  "geometry": {"coordinates":[-119.790458,36.77036],"type":"Point"}
}