{
  "type": "Feature",
  "properties": {
    "addr:full":"222 Keyes St San Jose CA 95112",
    "addr:housenumber":"222",
    "addr:postcode":"95112",
    "addr:street":"Keyes St",
    "iso:country":"US",
    "sg:address":"222 Keyes St",
    "sg:city":"San Jose",
    "sg:classifiers":[
        {
            "category":"Retail",
            "subcategory":"Auto Repair",
            "type":"Services"
        }
    ],
    "sg:phone":"+1 408 280 7340",
    "sg:postcode":"95112",
    "sg:province":"CA",
    "sg:tags":[
        "automobile",
        "diagnostic"
    ],
    "wof:name":"Pacific Autoworks",
    "wof:placetype":"venue"
},
  "geometry": {"coordinates":[-121.873374,37.321924],"type":"Point"}
}