{
  "type": "Feature",
  "properties": {
    "addr:full":"225 Berrywood Ct Vacaville CA 95688",
    "addr:housenumber":"225",
    "addr:postcode":"95688",
    "addr:street":"Berrywood Ct",
    "iso:country":"US",
    "sg:address":"225 Berrywood Ct",
    "sg:city":"Vacaville",
    "sg:classifiers":[
        {
            "category":"Recreation",
            "type":"Entertainment"
        }
    ],
    "sg:phone":"+1 707 446 6312",
    "sg:postcode":"95688",
    "sg:province":"CA",
    "sg:tags":[
        "club",
        "membership"
    ],
    "wof:name":"Little League Baseball In",
    "wof:placetype":"venue"
},
  "geometry": {"coordinates":[-121.978962,38.39369],"type":"Point"}
}