{
  "type": "Feature",
  "properties": {
    "iso:country":"US",
    "sg:address":"2511 E Lamona Ave",
    "sg:city":"Fresno",
    "sg:classifiers":[
        {
            "category":"Health Services",
            "subcategory":"Health Practitioner",
            "type":"Services"
        }
    ],
    "sg:phone":"+1 559 412 3636",
    "sg:postcode":"93703",
    "sg:province":"CA",
    "sg:tags":[
        "aromatherapy"
    ],
    "wof:name":"Peaceful Healing",
    "wof:placetype":"venue"
},
  "geometry": {"coordinates":[-119.781367,36.76043],"type":"Point"}
}