{
  "type": "Feature",
  "properties": {
    "iso:country":"US",
    "sg:address":"424 O St",
    "sg:city":"Antioch",
    "sg:classifiers":[
        {
            "category":"Wholesale",
            "subcategory":"Durable Goods & Equipment",
            "type":"Manufacturing & Wholesale Goods"
        },
        {
            "category":"Wholesale",
            "subcategory":"Electrical",
            "type":"Manufacturing & Wholesale Goods"
        }
    ],
    "sg:phone":"+1 925 755 8326",
    "sg:postcode":"94509",
    "sg:province":"CA",
    "sg:tags":[
        "alarm",
        "burglar",
        "system"
    ],
    "wof:name":"Global Marine Distribution Inc",
    "wof:placetype":"venue"
},
  "geometry": {"coordinates":[-121.823495,38.014958],"type":"Point"}
}