{
  "type": "Feature",
  "properties": {
    "addr:full":"20415 Via Paviso Cupertino CA 95014",
    "addr:housenumber":"20415",
    "addr:postcode":"95014",
    "addr:street":"Via Paviso",
    "iso:country":"US",
    "sg:address":"20415 Via Paviso",
    "sg:city":"Cupertino",
    "sg:classifiers":[
        {
            "category":"Real Estate",
            "subcategory":"Real Estate Agent",
            "type":"Services"
        }
    ],
    "sg:phone":"+1 408 257 4488",
    "sg:postcode":"95014",
    "sg:province":"CA",
    "sg:tags":[
        "apartment",
        "management"
    ],
    "wof:name":"Aviara Apartments",
    "wof:placetype":"venue"
},
  "geometry": {"coordinates":[-122.030998,37.336899],"type":"Point"}
}