{
  "type": "Feature",
  "properties": {
    "addr:full":"1210 Ortega St San Francisco CA 94122",
    "addr:housenumber":"1210",
    "addr:postcode":"94122",
    "addr:street":"Ortega St",
    "iso:country":"US",
    "sg:address":"1210 Ortega St",
    "sg:city":"San Francisco",
    "sg:classifiers":[
        {
            "category":"Taxi",
            "type":"Transportation"
        }
    ],
    "sg:phone":"+1 415 564 5693",
    "sg:postcode":"94122",
    "sg:province":"CA",
    "sg:tags":[
        "taxicab"
    ],
    "wof:name":"Royal Taxie Cab",
    "wof:placetype":"venue"
},
  "geometry": {"coordinates":[-122.477329,37.752408],"type":"Point"}
}