{
  "type": "Feature",
  "properties": {
    "addr:full":"8059 Targa Cir Ofc Citrus Heights CA 95610",
    "addr:housenumber":"8059",
    "addr:postcode":"95610",
    "addr:street":"Targa Cir",
    "iso:country":"US",
    "sg:address":"8059 Targa Cir Ofc",
    "sg:city":"Citrus Heights",
    "sg:classifiers":[
        {
            "category":"Real Estate",
            "subcategory":"Real Estate Operator",
            "type":"Services"
        }
    ],
    "sg:phone":"+1 916 961 0606",
    "sg:postcode":"95610",
    "sg:province":"CA",
    "sg:tags":[
        "apartment"
    ],
    "wof:name":"Woodmore Manor Apartments",
    "wof:placetype":"venue"
},
  "geometry": {"coordinates":[-121.271491,38.688939],"type":"Point"}
}