{
  "type": "Feature",
  "properties": {
    "addr:full":"1400 Braeridge Dr Beverly Hills CA 90210",
    "addr:housenumber":"1400",
    "addr:postcode":"90210",
    "addr:street":"Braeridge Dr",
    "iso:country":"US",
    "sg:address":"1400 Braeridge Dr",
    "sg:city":"Beverly Hills",
    "sg:classifiers":[
        {
            "category":"Arts & Performance",
            "subcategory":"Theater",
            "type":"Entertainment"
        }
    ],
    "sg:phone":"+1 310 278 4574",
    "sg:postcode":"90210",
    "sg:province":"CA",
    "sg:tags":[
        "music"
    ],
    "wof:name":"Wallach Entertainment",
    "wof:placetype":"venue"
},
  "geometry": {"coordinates":[-118.421035,34.097114],"type":"Point"}
}