{
  "type": "Feature",
  "properties": {
    "addr:full":"111 Lucky Dr Corte Madera CA 94925",
    "addr:housenumber":"111",
    "addr:postcode":"94925",
    "addr:street":"Lucky Dr",
    "iso:country":"US",
    "sg:address":"111 Lucky Dr",
    "sg:city":"Corte Madera",
    "sg:classifiers":[
        {
            "category":"Shopping",
            "subcategory":"Clothing, Apparel, & Fashions",
            "type":"Retail Goods"
        }
    ],
    "sg:phone":"+1 415 927 7779",
    "sg:postcode":"94925",
    "sg:province":"CA",
    "sg:tags":[
        "furnishing"
    ],
    "sg:website":"www.barcelino.com",
    "wof:name":"Barcelino Continental Corp",
    "wof:placetype":"venue"
},
  "geometry": {"coordinates":[-122.519969,37.938238],"type":"Point"}
}