{
  "type": "Feature",
  "properties": {
    "iso:country":"US",
    "sg:address":"1351 E Las Tunas Dr",
    "sg:city":"San Gabriel",
    "sg:classifiers":[
        {
            "category":"Real Estate",
            "subcategory":"Real Estate Agent",
            "type":"Services"
        }
    ],
    "sg:phone":"+1 626 285 9888",
    "sg:postcode":"91776",
    "sg:province":"CA",
    "wof:name":"East Valley Financial Group",
    "wof:placetype":"venue"
},
  "geometry": {"coordinates":[-118.07889,34.103541],"type":"Point"}
}