{
  "type": "Feature",
  "properties": {
    "iso:country":"US",
    "sg:address":"20 Barber Ln",
    "sg:city":"Martinez",
    "sg:classifiers":[
        {
            "category":"Professional",
            "subcategory":"Art Services",
            "type":"Services"
        }
    ],
    "sg:phone":"+1 925 370 6014",
    "sg:postcode":"94553",
    "sg:province":"CA",
    "sg:tags":[
        "photographer"
    ],
    "wof:name":"Jim Baylor",
    "wof:placetype":"venue"
},
  "geometry": {"coordinates":[-122.12294300000001,37.988608],"type":"Point"}
}