{
  "type": "Feature",
  "properties": {
    "addr:full":"26836 Co Rd 12A Esparto CA 95627",
    "addr:housenumber":"26836;12a",
    "addr:postcode":"95627",
    "addr:street":"Co Rd",
    "iso:country":"US",
    "sg:address":"26836 Co Rd 12A",
    "sg:city":"Esparto",
    "sg:classifiers":[
        {
            "category":"Farming",
            "subcategory":"Vineyard",
            "type":"Manufacturing & Wholesale Goods"
        }
    ],
    "sg:phone":"+1 530 662 3215",
    "sg:postcode":"95627",
    "sg:province":"CA",
    "sg:tags":[
        "grape",
        "mfg"
    ],
    "wof:name":"R H Phillips Vineyard",
    "wof:placetype":"venue"
},
  "geometry": {"coordinates":[-122.01190200000001,38.803177],"type":"Point"}
}