{
  "type": "Feature",
  "properties": {
    "addr:full":"15959 Piuma Ave Cerritos CA 90703",
    "addr:housenumber":"15959",
    "addr:postcode":"ca 90703",
    "addr:street":"Piuma Ave",
    "iso:country":"US",
    "sg:address":"15959 Piuma Ave",
    "sg:city":"Cerritos",
    "sg:classifiers":[
        {
            "category":"Home & Garden",
            "subcategory":"Carpets & Floor Coverings",
            "type":"Retail Goods"
        }
    ],
    "sg:phone":"+1 562 865 4210",
    "sg:postcode":"90703",
    "sg:province":"CA",
    "sg:tags":[
        "material"
    ],
    "wof:name":"Professional Sample Co",
    "wof:placetype":"venue"
},
  "geometry": {"coordinates":[-118.10475,33.884326],"type":"Point"}
}