{
  "type": "Feature",
  "properties": {
    "addr:full":"13120 Casimir Ave Gardena CA 90249",
    "addr:postcode":"13120;90249",
    "addr:street":"Casimir Ave",
    "iso:country":"US",
    "sg:address":"13120 Casimir Ave",
    "sg:city":"Gardena",
    "sg:classifiers":[
        {
            "category":"Building & Trades",
            "subcategory":"Landscaping Services",
            "type":"Services"
        }
    ],
    "sg:phone":"+1 310 366 5883",
    "sg:postcode":"90249",
    "sg:province":"CA",
    "sg:tags":[
        "aged",
        "homes-institutional"
    ],
    "wof:name":"Crisp Residential Care Homes",
    "wof:placetype":"venue"
},
  "geometry": {"coordinates":[-118.32214399999999,33.91335],"type":"Point"}
}