{
  "type": "Feature",
  "properties": {
    "addr:full":"200 S San Pedro St Los Angeles CA 90012",
    "addr:housenumber":"200",
    "addr:postcode":"90012",
    "addr:street":"S San Pedro St",
    "iso:country":"US",
    "sg:address":"200 S San Pedro St",
    "sg:city":"Los Angeles",
    "sg:classifiers":[
        {
            "category":"Professional",
            "subcategory":"Computer Services",
            "type":"Services"
        }
    ],
    "sg:phone":"+1 213 830 9950",
    "sg:postcode":"90012",
    "sg:province":"CA",
    "sg:tags":[
        "design",
        "integrated",
        "system"
    ],
    "sg:website":"www.la911.com",
    "wof:name":"TRWLAPDECCCS",
    "wof:placetype":"venue"
},
  "geometry": {"coordinates":[-118.24208,34.048484],"type":"Point"}
}