{
  "type": "Feature",
  "properties": {
    "iso:country":"US",
    "sg:address":"32395 Clinton Keith Rd",
    "sg:city":"Wildomar",
    "sg:classifiers":[
        {
            "category":"Retail",
            "subcategory":"Animal Services",
            "type":"Services"
        }
    ],
    "sg:phone":"+1 951 678 1145",
    "sg:postcode":"92595",
    "sg:province":"CA",
    "sg:tags":[
        "pet",
        "grooming",
        "washing",
        "merchandise"
    ],
    "wof:name":"Shaggy Dog Grooming & Supplies",
    "wof:placetype":"venue"
},
  "geometry": {"coordinates":[-117.247605,33.593907],"type":"Point"}
}