{
  "type": "Feature",
  "properties": {
    "addr:full":"2478 Euclid Pl Fremont CA 94539",
    "addr:housenumber":"2478",
    "addr:postcode":"94539",
    "addr:street":"Euclid Pl",
    "iso:country":"US",
    "sg:address":"2478 Euclid Pl",
    "sg:city":"Fremont",
    "sg:classifiers":[
        {
            "category":"Education",
            "subcategory":"Vocational School",
            "type":"Public Place"
        }
    ],
    "sg:phone":"+1 510 573 5769",
    "sg:postcode":"94539",
    "sg:province":"CA",
    "sg:tags":[
        "travel",
        "agency"
    ],
    "wof:name":"Journease Inc",
    "wof:placetype":"venue"
},
  "geometry": {"coordinates":[-121.93927600000001,37.521514],"type":"Point"}
}