{
  "type": "Feature",
  "properties": {
    "iso:country":"US",
    "sg:address":"2115 Julian Ave",
    "sg:city":"Bakersfield",
    "sg:classifiers":[
        {
            "category":"Autos & Motor Vehicles",
            "subcategory":"Automobile Sales",
            "type":"Retail Goods"
        }
    ],
    "sg:phone":"+1 661 831 8983",
    "sg:postcode":"93304",
    "sg:province":"CA",
    "sg:tags":[
        "dealers-used",
        "car",
        "used",
        "cars-wholesale"
    ],
    "wof:name":"Premier Auto Sales",
    "wof:placetype":"venue"
},
  "geometry": {"coordinates":[-119.026196,35.323444],"type":"Point"}
}