{
  "type": "Feature",
  "properties": {
    "iso:country":"US",
    "sg:address":"250 E Hackett Rd",
    "sg:city":"Modesto",
    "sg:classifiers":[
        {
            "category":"Government",
            "subcategory":"Police Station",
            "type":"Public Place"
        }
    ],
    "sg:phone":"+1 209 525 7112",
    "sg:postcode":"95358",
    "sg:province":"CA",
    "sg:tags":[
        "department"
    ],
    "wof:name":"Staniflaus Cnty Sheriffs Dept",
    "wof:placetype":"venue"
},
  "geometry": {"coordinates":[-120.98744,37.587546],"type":"Point"}
}