{
  "type": "Feature",
  "properties": {
    "iso:country":"US",
    "sg:address":"100 Los Gatos Saratoga Rd Ste D",
    "sg:city":"Los Gatos",
    "sg:classifiers":[
        {
            "category":"Building & Trades",
            "subcategory":"Construction",
            "type":"Services"
        }
    ],
    "sg:phone":"+1 408 399 7720",
    "sg:postcode":"95032",
    "sg:province":"CA",
    "sg:tags":[
        "interior",
        "design"
    ],
    "sg:website":"www.chelseacourtdesigns.com",
    "wof:name":"Chelsea Court Designs",
    "wof:placetype":"venue"
},
  "geometry": {"coordinates":[-121.97898600000001,37.228183],"type":"Point"}
}