{
  "type": "Feature",
  "properties": {
    "addr:full":"1174 Castro St Mountain View CA 94040",
    "addr:housenumber":"1174",
    "addr:postcode":"94040",
    "addr:street":"Castro St",
    "iso:country":"US",
    "sg:address":"1174 Castro St",
    "sg:city":"Mountain View",
    "sg:classifiers":[
        {
            "category":"Health Services",
            "subcategory":"Doctor",
            "type":"Services"
        }
    ],
    "sg:phone":"+1 650 934 7000",
    "sg:postcode":"94040",
    "sg:province":"CA",
    "sg:tags":[
        "physician",
        "surgeon"
    ],
    "wof:name":"Kim Yeun MD Camino Med Group",
    "wof:placetype":"venue"
},
  "geometry": {"coordinates":[-122.08626599999999,37.38201],"type":"Point"}
}