{
  "type": "Feature",
  "properties": {
    "iso:country":"US",
    "sg:address":"538 Lewelling Blvd",
    "sg:city":"San Leandro",
    "sg:classifiers":[
        {
            "category":"Building & Trades",
            "subcategory":"Construction",
            "type":"Services"
        }
    ],
    "sg:phone":"+1 510 352 1870",
    "sg:postcode":"94579",
    "sg:province":"CA",
    "sg:tags":[
        "contractor"
    ],
    "sg:website":"www.centurypatiovillage.com",
    "wof:name":"Century Patio Village",
    "wof:placetype":"venue"
},
  "geometry": {"coordinates":[-122.13400300000001,37.686699],"type":"Point"}
}