{
  "type": "Feature",
  "properties": {
    "iso:country":"US",
    "sg:address":"48 S Stewart St",
    "sg:city":"Sonora",
    "sg:classifiers":[
        {
            "category":"Health Services",
            "subcategory":"Optometrist",
            "type":"Services"
        }
    ],
    "sg:phone":"+1 209 532 5421",
    "sg:postcode":"95370",
    "sg:province":"CA",
    "wof:name":"Wallace T Stuart OD",
    "wof:placetype":"venue"
},
  "geometry": {"coordinates":[-120.382217,37.984637],"type":"Point"}
}