{
  "type": "Feature",
  "properties": {
    "addr:full":"2412 W Century Blvd Inglewood CA 90303",
    "addr:housenumber":"2412",
    "addr:postcode":"90303",
    "addr:street":"W Century Blvd",
    "iso:country":"US",
    "sg:address":"2412 W Century Blvd",
    "sg:city":"Inglewood",
    "sg:classifiers":[
        {
            "category":"Banks & Credit Unions",
            "subcategory":"Bank",
            "type":"Services"
        }
    ],
    "sg:phone":"+1 323 754 3450",
    "sg:postcode":"90303",
    "sg:province":"CA",
    "sg:tags":[
        "broker",
        "mortgage"
    ],
    "wof:name":"Equity Investment Network",
    "wof:placetype":"venue"
},
  "geometry": {"coordinates":[-118.320863,33.945397],"type":"Point"}
}