{
  "type": "Feature",
  "properties": {
    "iso:country":"US",
    "sg:address":"11200 Donner Pass Rd",
    "sg:city":"Truckee",
    "sg:classifiers":[
        {
            "category":"Building & Trades",
            "subcategory":"Construction",
            "type":"Services"
        }
    ],
    "sg:phone":"+1 530 582 5791",
    "sg:postcode":"96161",
    "sg:province":"CA",
    "sg:tags":[
        "project"
    ],
    "wof:name":"Abyss Construction",
    "wof:placetype":"venue"
},
  "geometry": {"coordinates":[-120.207538,39.32608],"type":"Point"}
}