{
  "type": "Feature",
  "properties": {
    "addr:full":"11711 Sterling Ave Riverside CA 92503",
    "addr:housenumber":"11711",
    "addr:postcode":"92503",
    "addr:street":"Sterling Ave",
    "iso:country":"US",
    "sg:address":"11711 Sterling Ave",
    "sg:city":"Riverside",
    "sg:classifiers":[
        {
            "category":"Retail",
            "subcategory":"Laundry & Dry Cleaning",
            "type":"Services"
        }
    ],
    "sg:phone":"+1 951 352 4000",
    "sg:postcode":"92503",
    "sg:province":"CA",
    "sg:tags":[
        "cleaners",
        "rug",
        "carpet"
    ],
    "wof:name":"Ameristar Restoration",
    "wof:placetype":"venue"
},
  "geometry": {"coordinates":[-117.485884,33.895361],"type":"Point"}
}