{
  "type": "Feature",
  "properties": {
    "iso:country":"US",
    "sg:address":"11874 1st St",
    "sg:city":"Yucaipa",
    "sg:classifiers":[
        {
            "category":"Real Estate",
            "subcategory":"Real Estate Agent",
            "type":"Services"
        }
    ],
    "sg:phone":"+1 951 255 3058",
    "sg:postcode":"92399",
    "sg:province":"CA",
    "sg:tags":[
        "consultant"
    ],
    "wof:name":"ITC",
    "wof:placetype":"venue"
},
  "geometry": {"coordinates":[-117.041561,34.038482],"type":"Point"}
}