{
  "type": "Feature",
  "properties": {
    "addr:full":"13833 Ventura Blvd Sherman Oaks CA 91423",
    "addr:housenumber":"13833",
    "addr:postcode":"91423",
    "addr:street":"Ventura Blvd",
    "iso:country":"US",
    "sg:address":"13833 Ventura Blvd",
    "sg:city":"Sherman Oaks",
    "sg:classifiers":[
        {
            "category":"Shopping",
            "subcategory":"Clothing, Apparel, & Fashions",
            "type":"Retail Goods"
        }
    ],
    "sg:phone":"+1 818 282 1151",
    "sg:postcode":"91423",
    "sg:province":"CA",
    "sg:tags":[
        "tailor",
        "alteration",
        "sewing"
    ],
    "wof:name":"VICTOR'S TAILOR SHOP",
    "wof:placetype":"venue"
},
  "geometry": {"coordinates":[-118.43420999999999,34.148665],"type":"Point"}
}