{
  "type": "Feature",
  "properties": {
    "addr:full":"13426 Woodruff Ave Bellflower CA 90706",
    "addr:housenumber":"13426",
    "addr:postcode":"90706",
    "addr:street":"Woodruff Ave",
    "iso:country":"US",
    "sg:address":"13426 Woodruff Ave",
    "sg:city":"Bellflower",
    "sg:classifiers":[
        {
            "category":"Banks & Credit Unions",
            "subcategory":"Investment Brokerage",
            "type":"Services"
        },
        {
            "category":"Shopping",
            "subcategory":"Computers & Home Electronics",
            "type":"Retail Goods"
        }
    ],
    "sg:phone":"+1 562 866 8224",
    "sg:postcode":"90706",
    "sg:province":"CA",
    "sg:tags":[
        "dvd",
        "video",
        "tape",
        "sale",
        "dvds-rental"
    ],
    "wof:name":"Aa Video",
    "wof:placetype":"venue"
},
  "geometry": {"coordinates":[-118.116669,33.909077],"type":"Point"}
}