{
  "type": "Feature",
  "properties": {
    "iso:country":"US",
    "sg:address":"458 W College Ave",
    "sg:city":"Santa Rosa",
    "sg:classifiers":[
        {
            "category":"Building & Trades",
            "subcategory":"Equipment Rental",
            "type":"Services"
        }
    ],
    "sg:phone":"+1 707 542 3742",
    "sg:postcode":"95401",
    "sg:province":"CA",
    "sg:tags":[
        "yard",
        "leasing",
        "store"
    ],
    "wof:name":"Nationsrent Inc",
    "wof:placetype":"venue"
},
  "geometry": {"coordinates":[-122.729744,38.445834],"type":"Point"}
}