{
  "type": "Feature",
  "properties": {
    "iso:country":"US",
    "sg:address":"6308 Landfair Dr",
    "sg:city":"Bakersfield",
    "sg:classifiers":[
        {
            "category":"Insurance",
            "subcategory":"Insurance Agent",
            "type":"Services"
        }
    ],
    "sg:phone":"+1 661 833 0300",
    "sg:postcode":"93309",
    "sg:province":"CA",
    "wof:name":"MCA Insurance",
    "wof:placetype":"venue"
},
  "geometry": {"coordinates":[-119.071183,35.336758],"type":"Point"}
}