{
  "type": "Feature",
  "properties": {
    "iso:country":"US",
    "sg:address":"21267 Stevens Creek Blvd Ste 311",
    "sg:city":"Cupertino",
    "sg:classifiers":[
        {
            "category":"Shopping",
            "subcategory":"Bicycles & Sporting Goods",
            "type":"Retail Goods"
        },
        {
            "category":"Shopping",
            "subcategory":"Shoes",
            "type":"Retail Goods"
        }
    ],
    "sg:phone":"+1 408 446 5511",
    "sg:postcode":"95014",
    "sg:province":"CA",
    "sg:tags":[
        "store"
    ],
    "wof:name":"Metrosport",
    "wof:placetype":"venue"
},
  "geometry": {"coordinates":[-122.049004,37.322899],"type":"Point"}
}