{
  "type": "Feature",
  "properties": {
    "addr:full":"1768 Crestmont Pl Costa Mesa CA 92627",
    "addr:housenumber":"1768",
    "addr:postcode":"92627",
    "addr:street":"Crestmont Pl",
    "iso:country":"US",
    "sg:address":"1768 Crestmont Pl",
    "sg:city":"Costa Mesa",
    "sg:classifiers":[
        {
            "category":"Professional",
            "type":"Services"
        }
    ],
    "sg:phone":"+1 949 650 8717",
    "sg:postcode":"92627",
    "sg:province":"CA",
    "wof:name":"Battle Inc",
    "wof:placetype":"venue"
},
  "geometry": {"coordinates":[-117.924905,33.6384],"type":"Point"}
}