{
  "type": "Feature",
  "properties": {
    "addr:full":"152 del Rey Ct Fairfield CA 94533",
    "addr:housenumber":"152",
    "addr:postcode":"94533",
    "addr:street":"Del Rey Ct",
    "iso:country":"US",
    "sg:address":"152 del Rey Ct",
    "sg:city":"Fairfield",
    "sg:classifiers":[
        {
            "category":"Freight",
            "type":"Transportation"
        }
    ],
    "sg:phone":"+1 707 426 1542",
    "sg:postcode":"94533",
    "sg:province":"CA",
    "sg:tags":[
        "operator",
        "local",
        "trucking"
    ],
    "wof:name":"Transport /Delivery",
    "wof:placetype":"venue"
},
  "geometry": {"coordinates":[-122.021305,38.271779],"type":"Point"}
}