{
  "type": "Feature",
  "properties": {
    "addr:full":"1416 Mipaty Ln Carmichael CA 95608",
    "addr:housenumber":"1416",
    "addr:postcode":"95608",
    "addr:street":"Mipaty Ln",
    "iso:country":"US",
    "sg:address":"1416 Mipaty Ln",
    "sg:city":"Carmichael",
    "sg:classifiers":[
        {
            "category":"Shopping",
            "subcategory":"Pets & Pet Supplies",
            "type":"Retail Goods"
        }
    ],
    "sg:phone":"+1 916 979 9836",
    "sg:postcode":"95608",
    "sg:province":"CA",
    "sg:tags":[
        "furnishing",
        "dog",
        "store",
        "cat"
    ],
    "wof:name":"Michi P Petite Pet Couture",
    "wof:placetype":"venue"
},
  "geometry": {"coordinates":[-121.349155,38.589379],"type":"Point"}
}