{
  "type": "Feature",
  "properties": {
    "iso:country":"US",
    "sg:address":"16551 Victory Blvd",
    "sg:city":"Van Nuys",
    "sg:classifiers":[
        {
            "category":"Professional",
            "subcategory":"Management & Consulting",
            "type":"Services"
        }
    ],
    "sg:phone":"+1 818 781 2272",
    "sg:postcode":"91406",
    "sg:province":"CA",
    "sg:tags":[
        "consultant",
        "training"
    ],
    "wof:name":"Kimbur Group Inc",
    "wof:placetype":"venue"
},
  "geometry": {"coordinates":[-118.49614800000001,34.186706],"type":"Point"}
}