{
  "type": "Feature",
  "properties": {
    "addr:full":"550 Montgomery St San Francisco CA 94111",
    "addr:housenumber":"550",
    "addr:postcode":"94111",
    "addr:street":"Montgomery St",
    "iso:country":"US",
    "sg:address":"550 Montgomery St",
    "sg:city":"San Francisco",
    "sg:classifiers":[
        {
            "category":"Professional",
            "subcategory":"Research",
            "type":"Services"
        }
    ],
    "sg:phone":"+1 415 397 5700",
    "sg:postcode":"94111",
    "sg:province":"CA",
    "sg:tags":[
        "foundation",
        "philanthropic"
    ],
    "wof:name":"Campaign Against Child Explttn",
    "wof:placetype":"venue"
},
  "geometry": {"coordinates":[-122.40304500000001,37.794555],"type":"Point"}
}