{
  "type": "Feature",
  "properties": {
    "addr:full":"Cupertino Square Food Court 10123 N Wolfe Rd Cupertino CA 95014",
    "addr:housenumber":"10123",
    "addr:postcode":"95014",
    "addr:street":"Cupertino;N Wolfe Rd",
    "iso:country":"US",
    "sg:address":"Cupertino Square Food Court 10123 N Wolfe Rd",
    "sg:city":"Cupertino",
    "sg:classifiers":[
        {
            "category":"Ice Cream",
            "type":"Food & Drink"
        }
    ],
    "sg:postcode":"95014",
    "sg:province":"CA",
    "sg:tags":[
        "frozen",
        "yogurt"
    ],
    "sg:website":"www.tfyogurt.com",
    "wof:name":"Tutti Frutti",
    "wof:placetype":"venue"
},
  "geometry": {"coordinates":[-122.012778,37.325032],"type":"Point"}
}