{
  "type": "Feature",
  "properties": {
    "addr:full":"5301 Laurel Canyon Blvd Valley Village CA 91607",
    "addr:housenumber":"5301",
    "addr:postcode":"91607",
    "addr:street":"Laurel Canyon Blvd",
    "iso:country":"US",
    "sg:address":"5301 Laurel Canyon Blvd",
    "sg:city":"Valley Village",
    "sg:classifiers":[
        {
            "category":"Professional",
            "subcategory":"Secretarial Services",
            "type":"Services"
        }
    ],
    "sg:phone":"+1 818 487 0672",
    "sg:postcode":"91607",
    "sg:province":"CA",
    "sg:tags":[
        "information",
        "document",
        "financial"
    ],
    "sg:website":"www.superpaycard.com",
    "wof:name":"Edebitpay LLC",
    "wof:placetype":"venue"
},
  "geometry": {"coordinates":[-118.396501,34.168357],"type":"Point"}
}