{
  "type": "Feature",
  "properties": {
    "addr:full":"3732 W Shields Ave Fresno CA 93722",
    "addr:housenumber":"3732",
    "addr:postcode":"93722",
    "addr:street":"W Shields Ave",
    "iso:country":"US",
    "sg:address":"3732 W Shields Ave",
    "sg:city":"Fresno",
    "sg:classifiers":[
        {
            "category":"Shopping",
            "subcategory":"Music",
            "type":"Retail Goods"
        }
    ],
    "sg:phone":"+1 559 271 7314",
    "sg:postcode":"93722",
    "sg:province":"CA",
    "sg:tags":[
        "video",
        "disc",
        "tape",
        "cassette"
    ],
    "wof:name":"Us Star Video",
    "wof:placetype":"venue"
},
  "geometry": {"coordinates":[-119.86070100000001,36.779205],"type":"Point"}
}