{
  "type": "Feature",
  "properties": {
    "iso:country":"US",
    "sg:address":"2657 Fruitland Ave",
    "sg:city":"Los Angeles",
    "sg:classifiers":[
        {
            "category":"Freight",
            "type":"Transportation"
        }
    ],
    "sg:phone":"+1 323 277 5825",
    "sg:postcode":"90058",
    "sg:province":"CA",
    "sg:tags":[
        "operator",
        "local",
        "trucking"
    ],
    "wof:name":"Ancon Transportation",
    "wof:placetype":"venue"
},
  "geometry": {"coordinates":[-118.222617,33.996442],"type":"Point"}
}