{
  "type": "Feature",
  "properties": {
    "addr:full":"5300 Lindbergh Ln Bell CA 90201",
    "addr:housenumber":"5300",
    "addr:postcode":"90201",
    "addr:street":"Lindbergh Ln",
    "iso:country":"US",
    "sg:address":"5300 Lindbergh Ln",
    "sg:city":"Bell",
    "sg:classifiers":[
        {
            "category":"Manufacturing",
            "subcategory":"Printing",
            "type":"Manufacturing & Wholesale Goods"
        }
    ],
    "sg:phone":"+1 323 261 5257",
    "sg:postcode":"90201",
    "sg:province":"CA",
    "sg:tags":[
        "commercial"
    ],
    "wof:name":"Crestline Thermogravers",
    "wof:placetype":"venue"
},
  "geometry": {"coordinates":[-118.169343,33.99481],"type":"Point"}
}