{
  "type": "Feature",
  "properties": {
    "addr:full":"2862 Telegraph Ave Oakland CA 94609",
    "addr:housenumber":"2862",
    "addr:postcode":"94609",
    "addr:street":"Telegraph Ave",
    "iso:country":"US",
    "sg:address":"2862 Telegraph Ave",
    "sg:city":"Oakland",
    "sg:classifiers":[
        {
            "category":"Manufacturing",
            "subcategory":"Signs",
            "type":"Manufacturing & Wholesale Goods"
        }
    ],
    "sg:phone":"+1 510 496 0415",
    "sg:postcode":"94609",
    "sg:province":"CA",
    "sg:tags":[
        "specialty",
        "mfg"
    ],
    "wof:name":"Graphics 2000",
    "wof:placetype":"venue"
},
  "geometry": {"coordinates":[-122.267493,37.818239],"type":"Point"}
}