{
  "type": "Feature",
  "properties": {
    "addr:full":"4198 Union Ave Bakersfield CA 93305",
    "addr:housenumber":"4198",
    "addr:postcode":"93305",
    "addr:street":"Union Ave",
    "iso:country":"US",
    "sg:address":"4198 Union Ave",
    "sg:city":"Bakersfield",
    "sg:classifiers":[
        {
            "category":"Food & Beverages",
            "subcategory":"Groceries & Convenience Stores",
            "type":"Retail Goods"
        }
    ],
    "sg:phone":"+1 661 328 9578",
    "sg:postcode":"93305",
    "sg:province":"CA",
    "sg:tags":[
        "grocer"
    ],
    "wof:name":"Lucky Seven Store 18",
    "wof:placetype":"venue"
},
  "geometry": {"coordinates":[-119.002864,35.396443],"type":"Point"}
}