{
  "type": "Feature",
  "properties": {
    "iso:country":"US",
    "sg:address":"10439 Prospect Ave",
    "sg:city":"Santee",
    "sg:classifiers":[
        {
            "category":"Autos & Motor Vehicles",
            "subcategory":"Auto Supplies",
            "type":"Retail Goods"
        }
    ],
    "sg:phone":"+1 619 448 5083",
    "sg:postcode":"92071",
    "sg:province":"CA",
    "wof:name":"Victory Auto Supply",
    "wof:placetype":"venue"
},
  "geometry": {"coordinates":[-116.969463,32.831071],"type":"Point"}
}