{
  "type": "Feature",
  "properties": {
    "iso:country":"US",
    "sg:address":"318 N Kenwood St",
    "sg:city":"Glendale",
    "sg:classifiers":[
        {
            "category":"Home & Garden",
            "subcategory":"Home Furnishings",
            "type":"Retail Goods"
        }
    ],
    "sg:phone":"+1 818 956 1858",
    "sg:postcode":"91206",
    "sg:province":"CA",
    "wof:name":"California Window Coverings",
    "wof:placetype":"venue"
},
  "geometry": {"coordinates":[-118.251312,34.151431],"type":"Point"}
}