{
  "type": "Feature",
  "properties": {
    "iso:country":"US",
    "sg:address":"920 Northgate Dr",
    "sg:city":"San Rafael",
    "sg:classifiers":[
        {
            "category":"Health Services",
            "subcategory":"Doctor",
            "type":"Services"
        }
    ],
    "sg:phone":"+1 415 479 1022",
    "sg:postcode":"94903",
    "sg:province":"CA",
    "sg:tags":[
        "physician",
        "surgeon"
    ],
    "wof:name":"Terra Linda Medical Group",
    "wof:placetype":"venue"
},
  "geometry": {"coordinates":[-122.545507,38.006895],"type":"Point"}
}