{
  "type": "Feature",
  "properties": {
    "addr:full":"29050 S Western Ave Rancho Pls Vrds CA 90275",
    "addr:housenumber":"29050",
    "addr:postcode":"90275",
    "addr:street":"S Western Ave",
    "iso:country":"US",
    "sg:address":"29050 S Western Ave",
    "sg:city":"Rancho Pls Vrds",
    "sg:classifiers":[
        {
            "category":"Insurance",
            "subcategory":"Insurance Agent",
            "type":"Services"
        }
    ],
    "sg:phone":"+1 310 548 0348",
    "sg:postcode":"90275",
    "sg:province":"CA",
    "sg:website":"www.gloverinsuranceagency.com",
    "wof:name":"Allstate Insurance",
    "wof:placetype":"venue"
},
  "geometry": {"coordinates":[-118.30896799999999,33.753847],"type":"Point"}
}