{
  "type": "Feature",
  "properties": {
    "iso:country":"US",
    "sg:address":"525 Henrietta St",
    "sg:city":"Martinez",
    "sg:classifiers":[
        {
            "category":"Government",
            "subcategory":"Office",
            "type":"Public Place"
        }
    ],
    "sg:phone":"+1 925 372 3505",
    "sg:postcode":"94553",
    "sg:province":"CA",
    "sg:tags":[
        "executive"
    ],
    "wof:name":"City Council",
    "wof:placetype":"venue"
},
  "geometry": {"coordinates":[-122.13500500000001,38.014001],"type":"Point"}
}