{
  "type": "Feature",
  "properties": {
    "iso:country":"US",
    "sg:address":"747 10th St",
    "sg:city":"Los Angeles",
    "sg:classifiers":[
        {
            "category":"Shopping",
            "subcategory":"Clothing, Apparel, & Fashions",
            "type":"Retail Goods"
        }
    ],
    "sg:phone":"+1 213 748 3315",
    "sg:postcode":"90021",
    "sg:province":"CA",
    "sg:tags":[
        "clothing",
        "women's"
    ],
    "wof:name":"Poetry Company",
    "wof:placetype":"venue"
},
  "geometry": {"coordinates":[-118.250403,34.034949],"type":"Point"}
}