{
  "type": "Feature",
  "properties": {
    "addr:full":"380 S Mathilda Ave Sunnyvale CA 94086",
    "addr:housenumber":"380",
    "addr:postcode":"94086",
    "addr:street":"S Mathilda Ave",
    "iso:country":"US",
    "sg:address":"380 S Mathilda Ave",
    "sg:city":"Sunnyvale",
    "sg:classifiers":[
        {
            "category":"Banks & Credit Unions",
            "subcategory":"Bank",
            "type":"Services"
        }
    ],
    "sg:phone":"+1 408 245 4540",
    "sg:postcode":"94086",
    "sg:province":"CA",
    "wof:name":"Bank of the West",
    "wof:placetype":"venue"
},
  "geometry": {"coordinates":[-122.035004,37.373798],"type":"Point"}
}