{
  "type": "Feature",
  "properties": {
    "iso:country":"US",
    "sg:address":"19425 Soledad Canyon Rd",
    "sg:city":"Canyon Country",
    "sg:classifiers":[
        {
            "category":"Wholesale",
            "subcategory":"Electrical",
            "type":"Manufacturing & Wholesale Goods"
        }
    ],
    "sg:phone":"+1 805 524 9746",
    "sg:postcode":"91351",
    "sg:province":"CA",
    "sg:tags":[
        "alarm",
        "burglar",
        "system"
    ],
    "wof:name":"Continental Security",
    "wof:placetype":"venue"
},
  "geometry": {"coordinates":[-118.474575,34.415716],"type":"Point"}
}