{
  "type": "Feature",
  "properties": {
    "iso:country":"US",
    "sg:address":"205 W 4th St",
    "sg:city":"Madera",
    "sg:classifiers":[
        {
            "category":"Government",
            "subcategory":"Office",
            "type":"Public Place"
        }
    ],
    "sg:phone":"+1 559 661 5400",
    "sg:postcode":"93637",
    "sg:province":"CA",
    "sg:tags":[
        "legislative",
        "body"
    ],
    "wof:name":"City of Madera",
    "wof:placetype":"venue"
},
  "geometry": {"coordinates":[-120.063562,36.962399],"type":"Point"}
}