{
  "type": "Feature",
  "properties": {
    "addr:full":"2147 Edison St Santa Ynez CA 93460",
    "addr:housenumber":"2147",
    "addr:postcode":"93460",
    "addr:street":"Edison St",
    "iso:country":"US",
    "sg:address":"2147 Edison St",
    "sg:city":"Santa Ynez",
    "sg:classifiers":[
        {
            "category":"Farming",
            "subcategory":"Livestock Farm",
            "type":"Manufacturing & Wholesale Goods"
        }
    ],
    "sg:phone":"+1 805 688 2851",
    "sg:postcode":"93460",
    "sg:province":"CA",
    "sg:tags":[
        "equine"
    ],
    "wof:name":"Fair Oak Farm",
    "wof:placetype":"venue"
},
  "geometry": {"coordinates":[-120.08032900000001,34.649108],"type":"Point"}
}