{
  "type": "Feature",
  "properties": {
    "iso:country":"US",
    "sg:address":"132 E Mission Ave",
    "sg:city":"Escondido",
    "sg:classifiers":[
        {
            "category":"Food & Beverages",
            "subcategory":"Liquor & Beverages",
            "type":"Retail Goods"
        }
    ],
    "sg:phone":"+1 760 746 1809",
    "sg:postcode":"92025",
    "sg:province":"CA",
    "wof:name":"Ken's Liquor",
    "wof:placetype":"venue"
},
  "geometry": {"coordinates":[-117.083562,33.130979],"type":"Point"}
}