{
  "type": "Feature",
  "properties": {
    "iso:country":"US",
    "sg:address":"2134 Wimbledon Cir",
    "sg:city":"Westlake Village",
    "sg:classifiers":[
        {
            "category":"Organizations",
            "subcategory":"Community Association",
            "type":"Services"
        }
    ],
    "sg:phone":"+1 818 889 2266",
    "sg:postcode":"91361",
    "sg:province":"CA",
    "wof:name":"Post 123",
    "wof:placetype":"venue"
},
  "geometry": {"coordinates":[-118.836973,34.147729],"type":"Point"}
}