{
  "type": "Feature",
  "properties": {
    "iso:country":"US",
    "sg:address":"200 N Grand Ave",
    "sg:city":"West Covina",
    "sg:classifiers":[
        {
            "category":"Professional",
            "subcategory":"Management & Consulting",
            "type":"Services"
        }
    ],
    "sg:phone":"+1 626 332 1066",
    "sg:postcode":"91791",
    "sg:province":"CA",
    "sg:tags":[
        "consultant",
        "educational"
    ],
    "wof:name":"Academic Management Services",
    "wof:placetype":"venue"
},
  "geometry": {"coordinates":[-117.872432,34.073001],"type":"Point"}
}