{
  "type": "Feature",
  "properties": {
    "iso:country":"US",
    "sg:address":"23296 Rd 24",
    "sg:city":"Chowchilla",
    "sg:classifiers":[
        {
            "category":"Wholesale",
            "subcategory":"Plants",
            "type":"Manufacturing & Wholesale Goods"
        }
    ],
    "sg:phone":"+1 559 674 6062",
    "sg:postcode":"93610",
    "sg:province":"CA",
    "sg:tags":[
        "nursery",
        "tree"
    ],
    "wof:name":"Hines Color",
    "wof:placetype":"venue"
},
  "geometry": {"coordinates":[-120.11086899999999,37.071342],"type":"Point"}
}