{
  "type": "Feature",
  "properties": {
    "iso:country":"US",
    "sg:address":"601 Sacramento St",
    "sg:city":"Vallejo",
    "sg:classifiers":[
        {
            "category":"Wholesale",
            "subcategory":"Computers",
            "type":"Manufacturing & Wholesale Goods"
        }
    ],
    "sg:phone":"+1 707 554 3123",
    "sg:postcode":"94590",
    "sg:province":"CA",
    "wof:name":"Custom PC Inc",
    "wof:placetype":"venue"
},
  "geometry": {"coordinates":[-122.258269,38.102635],"type":"Point"}
}