{
  "type": "Feature",
  "properties": {
    "addr:full":"21512 Midcrest Dr Lake Forest CA 92630",
    "addr:housenumber":"21512",
    "addr:postcode":"92630",
    "addr:street":"Midcrest Dr",
    "iso:country":"US",
    "sg:address":"21512 Midcrest Dr",
    "sg:city":"Lake Forest",
    "sg:classifiers":[
        {
            "category":"Building & Trades",
            "subcategory":"Electrical",
            "type":"Services"
        }
    ],
    "sg:phone":"+1 949 770 0102",
    "sg:postcode":"92630",
    "sg:province":"CA",
    "sg:tags":[
        "electrician",
        "electric",
        "contractor"
    ],
    "sg:website":"www.baysideelectric.net",
    "wof:name":"Bayside Electric",
    "wof:placetype":"venue"
},
  "geometry": {"coordinates":[-117.671997,33.6497],"type":"Point"}
}