{
  "type": "Feature",
  "properties": {
    "addr:full":"1739 S Union St Stockton CA 95206",
    "addr:housenumber":"1739",
    "addr:postcode":"95206",
    "addr:street":"S Union St",
    "iso:country":"US",
    "sg:address":"1739 S Union St",
    "sg:city":"Stockton",
    "sg:classifiers":[
        {
            "category":"Organizations",
            "subcategory":"Religious Organization",
            "type":"Services"
        }
    ],
    "sg:phone":"+1 209 464 1622",
    "sg:postcode":"95206",
    "sg:province":"CA",
    "sg:tags":[
        "church"
    ],
    "wof:name":"Stockton Word Of Faith",
    "wof:placetype":"venue"
},
  "geometry": {"coordinates":[-121.271838,37.939192],"type":"Point"}
}