{
  "type": "Feature",
  "properties": {
    "addr:full":"20802 Plummer St Chatsworth CA 91311",
    "addr:housenumber":"20802",
    "addr:postcode":"91311",
    "addr:street":"Plummer St",
    "iso:country":"US",
    "sg:address":"20802 Plummer St",
    "sg:city":"Chatsworth",
    "sg:classifiers":[
        {
            "category":"Manufacturing",
            "subcategory":"Metals",
            "type":"Manufacturing & Wholesale Goods"
        }
    ],
    "sg:phone":"+1 818 886 4653",
    "sg:postcode":"91311",
    "sg:province":"CA",
    "sg:tags":[
        "metals-base"
    ],
    "wof:name":"Ntr Metals",
    "wof:placetype":"venue"
},
  "geometry": {"coordinates":[-118.586563,34.24271],"type":"Point"}
}