{
  "type": "Feature",
  "properties": {
    "iso:country":"US",
    "sg:address":"330 N Brand Blvd",
    "sg:city":"Glendale",
    "sg:classifiers":[
        {
            "category":"Real Estate",
            "subcategory":"Real Estate Agent",
            "type":"Services"
        }
    ],
    "sg:phone":"+1 818 240 7840",
    "sg:postcode":"91203",
    "sg:province":"CA",
    "sg:website":"www.righthome.com",
    "wof:name":"Right Home",
    "wof:placetype":"venue"
},
  "geometry": {"coordinates":[-118.254992,34.151181],"type":"Point"}
}