{
  "type": "Feature",
  "properties": {
    "addr:full":"2703 7th St Berkeley CA 94710",
    "addr:housenumber":"2703",
    "addr:postcode":"94710",
    "addr:street":"7Th St",
    "iso:country":"US",
    "sg:address":"2703 7th St",
    "sg:city":"Berkeley",
    "sg:classifiers":[
        {
            "category":"Communications",
            "subcategory":"Film & Video Production",
            "type":"Services"
        }
    ],
    "sg:phone":"+1 510 665 4091",
    "sg:postcode":"94710",
    "sg:province":"CA",
    "sg:tags":[
        "motion",
        "picture",
        "studio",
        "producer"
    ],
    "wof:name":"Small Change",
    "wof:placetype":"venue"
},
  "geometry": {"coordinates":[-122.292731,37.856154],"type":"Point"}
}