{
  "type": "Feature",
  "properties": {
    "iso:country":"US",
    "sg:address":"801 Folger Ave",
    "sg:city":"Berkeley",
    "sg:classifiers":[
        {
            "category":"Professional",
            "subcategory":"Advertising",
            "type":"Services"
        },
        {
            "category":"Professional",
            "subcategory":"Art Services",
            "type":"Services"
        }
    ],
    "sg:phone":"+1 510 859 0200",
    "sg:postcode":"94710",
    "sg:province":"CA",
    "sg:tags":[
        "graphic",
        "artist",
        "agency",
        "commercial",
        "specialty",
        "designer"
    ],
    "sg:website":"http://www.formativegroup.com",
    "wof:name":"Formative",
    "wof:placetype":"venue"
},
  "geometry": {"coordinates":[-122.29219500000001,37.849723],"type":"Point"}
}