{
  "type": "Feature",
  "properties": {
    "addr:full":"9228 Chablis Way Elk Grove CA 95624",
    "addr:housenumber":"9228",
    "addr:postcode":"95624",
    "addr:street":"Chablis Way",
    "iso:country":"US",
    "sg:address":"9228 Chablis Way",
    "sg:city":"Elk Grove",
    "sg:classifiers":[
        {
            "category":"Insurance",
            "subcategory":"Health Insurance",
            "type":"Services"
        }
    ],
    "sg:phone":"+1 916 685 2563",
    "sg:postcode":"95624",
    "sg:province":"CA",
    "sg:tags":[
        "plan"
    ],
    "wof:name":"Blue Cross Janitorial Empire",
    "wof:placetype":"venue"
},
  "geometry": {"coordinates":[-121.354553,38.403794],"type":"Point"}
}