{
  "type": "Feature",
  "properties": {
    "iso:country":"US",
    "sg:address":"1114 20th St",
    "sg:city":"Santa Monica",
    "sg:classifiers":[
        {
            "category":"Professional",
            "type":"Services"
        }
    ],
    "sg:phone":"+1 310 546 3676",
    "sg:postcode":"90403",
    "sg:province":"CA",
    "wof:name":"Clear Point",
    "wof:placetype":"venue"
},
  "geometry": {"coordinates":[-118.484146,34.032173],"type":"Point"}
}