{
  "type": "Feature",
  "properties": {
    "addr:full":"1260 1st St Gilroy CA 95020",
    "addr:housenumber":"1260",
    "addr:postcode":"95020",
    "addr:street":"1St St",
    "iso:country":"US",
    "sg:address":"1260 1st St",
    "sg:city":"Gilroy",
    "sg:classifiers":[
        {
            "category":"Home & Garden",
            "subcategory":"Hardware",
            "type":"Retail Goods"
        }
    ],
    "sg:phone":"+1 408 847 5890",
    "sg:postcode":"95020",
    "sg:province":"CA",
    "wof:name":"Ace Hardware",
    "wof:placetype":"venue"
},
  "geometry": {"coordinates":[-121.596278,37.013405],"type":"Point"}
}