{
  "type": "Feature",
  "properties": {
    "addr:full":"712 State Rte 66 Glendora CA 91740",
    "addr:housenumber":"712",
    "addr:postcode":"91740",
    "addr:street":"State Rte 66",
    "iso:country":"US",
    "sg:address":"712 State Rte 66",
    "sg:city":"Glendora",
    "sg:classifiers":[
        {
            "category":"Home & Garden",
            "subcategory":"Building Materials",
            "type":"Retail Goods"
        },
        {
            "category":"Building & Trades",
            "subcategory":"Construction",
            "type":"Services"
        }
    ],
    "sg:phone":"+1 626 335 3699",
    "sg:postcode":"91740",
    "sg:province":"CA",
    "sg:tags":[
        "glass",
        "window",
        "contractor",
        "plate"
    ],
    "wof:name":"Glendora Glass & Mirror",
    "wof:placetype":"venue"
},
  "geometry": {"coordinates":[-117.879289,34.128651],"type":"Point"}
}