{
  "type": "Feature",
  "properties": {
    "iso:country":"US",
    "sg:address":"27726 Blossom Hill Rd",
    "sg:city":"Laguna Niguel",
    "sg:classifiers":[
        {
            "category":"Building & Trades",
            "subcategory":"Plumbing",
            "type":"Services"
        }
    ],
    "sg:phone":"+1 949 831 3260",
    "sg:postcode":"92677",
    "sg:province":"CA",
    "sg:tags":[
        "conditioning",
        "air",
        "system",
        "contractor"
    ],
    "wof:name":"Air Treatment Corp",
    "wof:placetype":"venue"
},
  "geometry": {"coordinates":[-117.69418,33.560088],"type":"Point"}
}