{
  "type": "Feature",
  "properties": {
    "iso:country":"US",
    "sg:address":"5149 Ming Ave",
    "sg:city":"Bakersfield",
    "sg:classifiers":[
        {
            "category":"Professional",
            "subcategory":"Accounting & Tax Preparation",
            "type":"Services"
        }
    ],
    "sg:phone":"+1 866 871 1040",
    "sg:postcode":"93309",
    "sg:province":"CA",
    "sg:tags":[
        "return",
        "preparation-business"
    ],
    "sg:website":"http://www.libertytax.com/",
    "wof:name":"Liberty Tax Service",
    "wof:placetype":"venue"
},
  "geometry": {"coordinates":[-119.05909800000001,35.338718],"type":"Point"}
}