{
  "type": "Feature",
  "properties": {
    "addr:full":"5993 Lindhurst Ave Marysville CA 95901",
    "addr:postcode":"5993;95901",
    "addr:street":"Lindhurst Ave",
    "iso:country":"US",
    "sg:address":"5993 Lindhurst Ave",
    "sg:city":"Marysville",
    "sg:classifiers":[
        {
            "category":"Shopping",
            "subcategory":"Pharmacy",
            "type":"Retail Goods"
        }
    ],
    "sg:phone":"+1 530 742 8808",
    "sg:postcode":"95901",
    "sg:province":"CA",
    "wof:name":"Medi Mart Pharmacy",
    "wof:placetype":"venue"
},
  "geometry": {"coordinates":[-121.56864899999999,39.12369],"type":"Point"}
}