{
  "type": "Feature",
  "properties": {
    "iso:country":"US",
    "sg:address":"32451 E Trimmer Springs Rd",
    "sg:city":"Sanger",
    "sg:classifiers":[
        {
            "category":"Recreation",
            "subcategory":"Marina",
            "type":"Entertainment"
        }
    ],
    "sg:phone":"+1 559 787 2207",
    "sg:postcode":"93657",
    "sg:province":"CA",
    "sg:tags":[
        "grocery",
        "bar",
        "motel",
        "court",
        "cafe",
        "trailer"
    ],
    "wof:name":"Pineflat Lake Resort",
    "wof:placetype":"venue"
},
  "geometry": {"coordinates":[-119.312111,36.868843],"type":"Point"}
}