{
  "type": "Feature",
  "properties": {
    "iso:country":"US",
    "sg:address":"14222 Oxnard St",
    "sg:city":"Van Nuys",
    "sg:classifiers":[
        {
            "category":"Retail",
            "subcategory":"Auto Repair",
            "type":"Services"
        }
    ],
    "sg:phone":"+1 818 908 9499",
    "sg:postcode":"91401",
    "sg:province":"CA",
    "wof:name":"ZBest Autobody",
    "wof:placetype":"venue"
},
  "geometry": {"coordinates":[-118.442656,34.17926],"type":"Point"}
}