{
  "type": "Feature",
  "properties": {
    "addr:full":"100 Professional Center Dr Rohnert Park CA 94928",
    "addr:housenumber":"100",
    "addr:postcode":"94928",
    "addr:street":"Center Dr",
    "iso:country":"US",
    "sg:address":"100 Professional Center Dr",
    "sg:city":"Rohnert Park",
    "sg:classifiers":[
        {
            "category":"Wholesale",
            "subcategory":"Office Equipment",
            "type":"Manufacturing & Wholesale Goods"
        }
    ],
    "sg:phone":"+1 707 584 3995",
    "sg:postcode":"94928",
    "sg:province":"CA",
    "sg:tags":[
        "machine",
        "duplicating",
        "copying"
    ],
    "sg:website":"www.scottsoffice.com",
    "wof:name":"Scott's Office Equipment",
    "wof:placetype":"venue"
},
  "geometry": {"coordinates":[-122.71003899999999,38.353755],"type":"Point"}
}