{
  "type": "Feature",
  "properties": {
    "addr:full":"2808 E Cesar E Chavez Ave Los Angeles CA 90033",
    "addr:housenumber":"2808",
    "addr:postcode":"90033",
    "addr:street":"E Cesar E Chavez Ave",
    "iso:country":"US",
    "sg:address":"2808 E Cesar E Chavez Ave",
    "sg:city":"Los Angeles",
    "sg:classifiers":[
        {
            "category":"Home & Garden",
            "subcategory":"Carpets & Floor Coverings",
            "type":"Retail Goods"
        }
    ],
    "sg:phone":"+1 323 265 9081",
    "sg:postcode":"90033",
    "sg:province":"CA",
    "sg:tags":[
        "dealer",
        "rug"
    ],
    "wof:name":"Lissett's Carpet",
    "wof:placetype":"venue"
},
  "geometry": {"coordinates":[-118.202724,34.044509],"type":"Point"}
}