{
  "type": "Feature",
  "properties": {
    "addr:full":"18081 Ventura Blvd Encino CA 91316",
    "addr:housenumber":"18081",
    "addr:postcode":"91316",
    "addr:street":"Ventura Blvd",
    "iso:country":"US",
    "sg:address":"18081 Ventura Blvd",
    "sg:city":"Encino",
    "sg:classifiers":[
        {
            "category":"Autos & Motor Vehicles",
            "subcategory":"Fuel & Gas Station",
            "type":"Retail Goods"
        }
    ],
    "sg:phone":"+1 818 996 4844",
    "sg:postcode":"91316",
    "sg:province":"CA",
    "sg:tags":[
        "oil"
    ],
    "wof:name":"Encino Chevron Car Wash",
    "wof:placetype":"venue"
},
  "geometry": {"coordinates":[-118.52498900000001,34.164735],"type":"Point"}
}