{
  "type": "Feature",
  "properties": {
    "addr:full":"1758 Lincoln Blvd Santa Monica CA 90404",
    "addr:housenumber":"1758",
    "addr:postcode":"90404",
    "addr:street":"Lincoln Blvd",
    "iso:country":"US",
    "sg:address":"1758 Lincoln Blvd",
    "sg:city":"Santa Monica",
    "sg:classifiers":[
        {
            "category":"Home & Garden",
            "subcategory":"Building Materials",
            "type":"Retail Goods"
        }
    ],
    "sg:phone":"+1 310 393 9422",
    "sg:postcode":"90404",
    "sg:province":"CA",
    "sg:tags":[
        "wallpaper"
    ],
    "wof:name":"Wallpaper City",
    "wof:placetype":"venue"
},
  "geometry": {"coordinates":[-118.48489600000001,34.0139],"type":"Point"}
}