{
  "type": "Feature",
  "properties": {
    "addr:full":"18102 Burbank Blvd Tarzana CA 91356",
    "addr:housenumber":"18102",
    "addr:postcode":"91356",
    "addr:street":"Burbank Blvd",
    "iso:country":"US",
    "sg:address":"18102 Burbank Blvd",
    "sg:city":"Tarzana",
    "sg:classifiers":[
        {
            "category":"Travel",
            "subcategory":"Travel Agent",
            "type":"Entertainment"
        }
    ],
    "sg:phone":"+1 818 345 8519",
    "sg:postcode":"91356",
    "sg:province":"CA",
    "sg:tags":[
        "agency"
    ],
    "wof:name":"Cruises Worldwide",
    "wof:placetype":"venue"
},
  "geometry": {"coordinates":[-118.530494,34.172251],"type":"Point"}
}