{
  "type": "Feature",
  "properties": {
    "iso:country":"US",
    "sg:address":"8024 Sacramento St",
    "sg:city":"Fair Oaks",
    "sg:classifiers":[
        {
            "category":"Autos & Motor Vehicles",
            "subcategory":"Fuel & Gas Station",
            "type":"Retail Goods"
        },
        {
            "category":"Personal",
            "type":"Services"
        },
        {
            "category":"Retail",
            "subcategory":"Auto Repair",
            "type":"Services"
        }
    ],
    "sg:phone":"+1 916 967 7602",
    "sg:postcode":"95628",
    "sg:province":"CA",
    "sg:tags":[
        "towing"
    ],
    "wof:name":"Fair Oaks Auto Repair",
    "wof:placetype":"venue"
},
  "geometry": {"coordinates":[-121.266998,38.643398],"type":"Point"}
}