{
  "type": "Feature",
  "properties": {
    "addr:full":"4897 Main St Yorba Linda CA 92886",
    "addr:housenumber":"4897",
    "addr:postcode":"92886",
    "addr:street":"Main St",
    "iso:country":"US",
    "sg:address":"4897 Main St",
    "sg:city":"Yorba Linda",
    "sg:classifiers":[
        {
            "category":"Professional",
            "subcategory":"Lawyer & Legal Services",
            "type":"Services"
        }
    ],
    "sg:phone":"+1 714 777 4477",
    "sg:postcode":"92886",
    "sg:province":"CA",
    "sg:tags":[
        "attorney"
    ],
    "wof:name":"Bigonger & Bigonger",
    "wof:placetype":"venue"
},
  "geometry": {"coordinates":[-117.814069,33.890382],"type":"Point"}
}