{
  "type": "Feature",
  "properties": {
    "iso:country":"US",
    "sg:address":"65 Dorman Ave",
    "sg:city":"San Francisco",
    "sg:classifiers":[
        {
            "category":"Airline",
            "type":"Transportation"
        }
    ],
    "sg:phone":"+1 415 864 7736",
    "sg:postcode":"94124",
    "sg:province":"CA",
    "sg:tags":[
        "ope",
        "air",
        "local",
        "courier",
        "trucking"
    ],
    "sg:website":"www.netcour.com",
    "wof:name":"Network Courier Svc",
    "wof:placetype":"venue"
},
  "geometry": {"coordinates":[-122.40278000000001,37.739741],"type":"Point"}
}