{
  "type": "Feature",
  "properties": {
    "addr:full":"2535 Norfolk St National City CA 91950",
    "addr:housenumber":"2535",
    "addr:postcode":"91950",
    "addr:street":"Norfolk St",
    "iso:country":"US",
    "sg:address":"2535 Norfolk St",
    "sg:city":"National City",
    "sg:classifiers":[
        {
            "category":"Building & Trades",
            "subcategory":"Construction",
            "type":"Services"
        }
    ],
    "sg:phone":"+1 619 262 0998",
    "sg:postcode":"91950",
    "sg:province":"CA",
    "sg:tags":[
        "hanging"
    ],
    "wof:name":"Myco Painting",
    "wof:placetype":"venue"
},
  "geometry": {"coordinates":[-117.084858,32.691963],"type":"Point"}
}