{
  "type": "Feature",
  "properties": {
    "addr:full":"1325 Dyer Rd Santa Ana CA 92705",
    "addr:housenumber":"1325",
    "addr:postcode":"92705",
    "addr:street":"Dyer Rd",
    "iso:country":"US",
    "sg:address":"1325 Dyer Rd",
    "sg:city":"Santa Ana",
    "sg:classifiers":[
        {
            "category":"Personal",
            "type":"Services"
        },
        {
            "category":"Shopping",
            "subcategory":"Florist",
            "type":"Retail Goods"
        }
    ],
    "sg:phone":"+1 949 307 1918",
    "sg:postcode":"92705",
    "sg:province":"CA",
    "sg:tags":[
        "planning",
        "wedding"
    ],
    "sg:website":"petalsbyxavi.com",
    "wof:name":"Petals by Xavi",
    "wof:placetype":"venue"
},
  "geometry": {"coordinates":[-117.85356,33.708937],"type":"Point"}
}