{
  "type": "Feature",
  "properties": {
    "iso:country":"US",
    "sg:address":"1150 Bayhill Dr",
    "sg:city":"Montara",
    "sg:classifiers":[
        {
            "category":"Banks & Credit Unions",
            "subcategory":"Investment Brokerage",
            "type":"Services"
        },
        {
            "category":"Professional",
            "type":"Services"
        },
        {
            "category":"Professional",
            "subcategory":"Management & Consulting",
            "type":"Services"
        }
    ],
    "sg:phone":"+1 650 553 0000",
    "sg:postcode":"94066",
    "sg:province":"CA",
    "sg:tags":[
        "consultant",
        "financial",
        "advisory"
    ],
    "wof:name":"Coastside",
    "wof:placetype":"venue"
},
  "geometry": {"coordinates":[-122.4225,37.628108],"type":"Point"}
}