{
  "type": "Feature",
  "properties": {
    "iso:country":"US",
    "sg:address":"8225 N Fresno St",
    "sg:city":"Fresno",
    "sg:classifiers":[
        {
            "category":"Professional",
            "subcategory":"Management & Consulting",
            "type":"Services"
        }
    ],
    "sg:phone":"+1 559 261 9891",
    "sg:postcode":"93710",
    "sg:province":"CA",
    "wof:name":"Primavera Marketing",
    "wof:placetype":"venue"
},
  "geometry": {"coordinates":[-119.78507,36.857402],"type":"Point"}
}