{
  "type": "Feature",
  "properties": {
    "iso:country":"US",
    "sg:address":"4564 W Telephone Rd",
    "sg:city":"Ventura",
    "sg:classifiers":[
        {
            "category":"Insurance",
            "subcategory":"Insurance Agent",
            "type":"Services"
        }
    ],
    "sg:phone":"+1 805 604 2158",
    "sg:postcode":"93003",
    "sg:province":"CA",
    "wof:name":"New York Life Insurance",
    "wof:placetype":"venue"
},
  "geometry": {"coordinates":[-119.225769,34.263345],"type":"Point"}
}