{
  "type": "Feature",
  "properties": {
    "iso:country":"US",
    "sg:address":"1510 S Orange Dr",
    "sg:city":"Los Angeles",
    "sg:classifiers":[
        {
            "category":"Building & Trades",
            "subcategory":"Construction",
            "type":"Services"
        }
    ],
    "sg:phone":"+1 323 938 7551",
    "sg:postcode":"90019",
    "sg:province":"CA",
    "sg:tags":[
        "hanging",
        "contractor"
    ],
    "wof:name":"Perez Bros Painting",
    "wof:placetype":"venue"
},
  "geometry": {"coordinates":[-118.347333,34.046982],"type":"Point"}
}