{
  "type": "Feature",
  "properties": {
    "iso:country":"US",
    "sg:address":"10835 Wescott Ave",
    "sg:city":"Sunland",
    "sg:classifiers":[
        {
            "category":"Building & Trades",
            "subcategory":"Equipment Rental",
            "type":"Services"
        }
    ],
    "sg:phone":"+1 818 951 0685",
    "sg:postcode":"91040",
    "sg:province":"CA",
    "sg:tags":[
        "leasing",
        "forklift",
        "cranes-renting",
        "trucks-rental"
    ],
    "wof:name":"Select Crane Inc",
    "wof:placetype":"venue"
},
  "geometry": {"coordinates":[-118.317388,34.265684],"type":"Point"}
}