{
  "type": "Feature",
  "properties": {
    "addr:full":"4907 Longview Way El Cajon CA 92020",
    "addr:housenumber":"4907",
    "addr:postcode":"92020",
    "addr:street":"Longview Way",
    "iso:country":"US",
    "sg:address":"4907 Longview Way",
    "sg:city":"El Cajon",
    "sg:classifiers":[
        {
            "category":"Professional",
            "subcategory":"Business Services",
            "type":"Services"
        }
    ],
    "sg:phone":"+1 619 334 2922",
    "sg:postcode":"92020",
    "sg:province":"CA",
    "sg:tags":[
        "lecture",
        "bureau",
        "seminar"
    ],
    "wof:name":"Achievers Institute",
    "wof:placetype":"venue"
},
  "geometry": {"coordinates":[-116.950514,32.771684],"type":"Point"}
}