{
  "type": "Feature",
  "properties": {
    "iso:country":"US",
    "sg:address":"401 Cherokee Ln",
    "sg:city":"Lodi",
    "sg:classifiers":[
        {
            "category":"Food & Beverages",
            "subcategory":"Liquor & Beverages",
            "type":"Retail Goods"
        }
    ],
    "sg:phone":"+1 209 368 3818",
    "sg:postcode":"95240",
    "sg:province":"CA",
    "wof:name":"Cherokee Mini Mart & Liquors",
    "wof:placetype":"venue"
},
  "geometry": {"coordinates":[-121.26046,38.128977],"type":"Point"}
}