{
  "type": "Feature",
  "properties": {
    "iso:country":"US",
    "sg:address":"18 Mirabel Ave",
    "sg:city":"Mill Valley",
    "sg:classifiers":[
        {
            "category":"Professional",
            "subcategory":"Business Services",
            "type":"Services"
        }
    ],
    "sg:phone":"+1 415 381 2659",
    "sg:postcode":"94941",
    "sg:province":"CA",
    "sg:tags":[
        "interior",
        "consultant",
        "design",
        "decorator"
    ],
    "wof:name":"G G Green Interior Design",
    "wof:placetype":"venue"
},
  "geometry": {"coordinates":[-122.544522,37.901538],"type":"Point"}
}