{
  "type": "Feature",
  "properties": {
    "iso:country":"US",
    "sg:address":"3030 W Olympic Blvd Suite 208",
    "sg:city":"Los Angeles",
    "sg:classifiers":[
        {
            "category":"Health Services",
            "subcategory":"Chiropractor",
            "type":"Services"
        }
    ],
    "sg:phone":"+1 213 251 7700",
    "sg:postcode":"90006",
    "sg:province":"CA",
    "wof:name":"Stephanie J Kim",
    "wof:placetype":"venue"
},
  "geometry": {"coordinates":[-118.305283,34.048799],"type":"Point"}
}