{
  "type": "Feature",
  "properties": {
    "iso:country":"US",
    "sg:address":"5407 W Pico Blvd",
    "sg:city":"Los Angeles",
    "sg:classifiers":[
        {
            "category":"Wholesale",
            "subcategory":"Drugs",
            "type":"Manufacturing & Wholesale Goods"
        }
    ],
    "sg:phone":"+1 323 938 6980",
    "sg:postcode":"90019",
    "sg:province":"CA",
    "wof:name":"New Generation Buty Sup Salon",
    "wof:placetype":"venue"
},
  "geometry": {"coordinates":[-118.356656,34.048689],"type":"Point"}
}