{
  "type": "Feature",
  "properties": {
    "iso:country":"US",
    "sg:address":"5775 Scarborough Dr",
    "sg:city":"Oakland",
    "sg:classifiers":[
        {
            "category":"Professional",
            "subcategory":"Printing & Photocopies",
            "type":"Services"
        }
    ],
    "sg:phone":"+1 510 336 0269",
    "sg:postcode":"94611",
    "sg:province":"CA",
    "sg:tags":[
        "lithographer"
    ],
    "wof:name":"Fsa Print Finishing Services",
    "wof:placetype":"venue"
},
  "geometry": {"coordinates":[-122.200637,37.823872],"type":"Point"}
}