{
  "type": "Feature",
  "properties": {
    "iso:country":"US",
    "sg:address":"2202 Stevens Creek Blvd",
    "sg:city":"San Jose",
    "sg:classifiers":[
        {
            "category":"Banks & Credit Unions",
            "subcategory":"Bank",
            "type":"Services"
        }
    ],
    "sg:phone":"+1 408 287 5340",
    "sg:postcode":"95128",
    "sg:province":"CA",
    "sg:tags":[
        "financing"
    ],
    "wof:name":"Western Funding",
    "wof:placetype":"venue"
},
  "geometry": {"coordinates":[-121.93281399999999,37.323314],"type":"Point"}
}