{
  "type": "Feature",
  "properties": {
    "addr:full":"8460 Mira Mesa Blvd San Diego CA 92126",
    "addr:housenumber":"8460",
    "addr:postcode":"92126",
    "addr:street":"Mira Mesa Blvd",
    "iso:country":"US",
    "sg:address":"8460 Mira Mesa Blvd",
    "sg:city":"San Diego",
    "sg:classifiers":[
        {
            "category":"Organizations",
            "subcategory":"Religious Organization",
            "type":"Services"
        }
    ],
    "sg:phone":"+1 858 549 4557",
    "sg:postcode":"92126",
    "sg:province":"CA",
    "sg:tags":[
        "church"
    ],
    "wof:name":"Praise Fellowship Family",
    "wof:placetype":"venue"
},
  "geometry": {"coordinates":[-117.140547,32.91286],"type":"Point"}
}