{
  "type": "Feature",
  "properties": {
    "addr:full":"7447 Skyline Dr Stanton CA 90680",
    "addr:housenumber":"7447",
    "addr:postcode":"ca 90680",
    "addr:street":"Skyline Dr",
    "iso:country":"US",
    "sg:address":"7447 Skyline Dr",
    "sg:city":"Stanton",
    "sg:classifiers":[
        {
            "category":"Building & Trades",
            "subcategory":"Construction",
            "type":"Services"
        }
    ],
    "sg:phone":"+1 714 527 6280",
    "sg:postcode":"90680",
    "sg:province":"CA",
    "sg:tags":[
        "wallcoverings-installation",
        "wallpaper",
        "painting",
        "contractor"
    ],
    "wof:name":"Orange Coast Painting Co",
    "wof:placetype":"venue"
},
  "geometry": {"coordinates":[-118.00312700000001,33.803893],"type":"Point"}
}