{
  "type": "Feature",
  "properties": {
    "iso:country":"US",
    "sg:address":"1343 N Helen Ave",
    "sg:city":"Ontario",
    "sg:classifiers":[
        {
            "category":"Manufacturing",
            "subcategory":"Signs",
            "type":"Manufacturing & Wholesale Goods"
        }
    ],
    "sg:phone":"+1 909 988 6615",
    "sg:postcode":"91762",
    "sg:province":"CA",
    "sg:tags":[
        "specialty",
        "mfg"
    ],
    "wof:name":"Pacific Banner & Sign",
    "wof:placetype":"venue"
},
  "geometry": {"coordinates":[-117.67811,34.082727],"type":"Point"}
}