{
  "type": "Feature",
  "properties": {
    "iso:country":"US",
    "sg:address":"2195 Sepulveda Blvd",
    "sg:city":"Torrance",
    "sg:classifiers":[
        {
            "category":"Restaurant",
            "type":"Food & Drink"
        }
    ],
    "sg:phone":"+1 310 328 6080",
    "sg:postcode":"90501",
    "sg:province":"CA",
    "wof:name":"Carl's Jr Restaurants",
    "wof:placetype":"venue"
},
  "geometry": {"coordinates":[-118.319,33.819901],"type":"Point"}
}