{
  "type": "Feature",
  "properties": {
    "addr:full":"2733 Lake Tahoe Blvd South Lake Tahoe CA 96150",
    "addr:housenumber":"2733",
    "addr:postcode":"96150",
    "addr:street":"Lake Tahoe Blvd",
    "iso:country":"US",
    "sg:address":"2733 Lake Tahoe Blvd",
    "sg:city":"South Lake Tahoe",
    "sg:classifiers":[
        {
            "category":"Organizations",
            "subcategory":"Religious Organization",
            "type":"Services"
        }
    ],
    "sg:phone":"+1 530 544 3757",
    "sg:postcode":"96150",
    "sg:province":"CA",
    "sg:tags":[
        "church"
    ],
    "wof:name":"Lake Tahoe Community Presby",
    "wof:placetype":"venue"
},
  "geometry": {"coordinates":[-119.97976199999999,38.930538],"type":"Point"}
}