{
  "type": "Feature",
  "properties": {
    "iso:country":"US",
    "sg:address":"251 Stonewood St",
    "sg:city":"Downey",
    "sg:classifiers":[
        {
            "category":"Home & Garden",
            "subcategory":"Furniture",
            "type":"Retail Goods"
        }
    ],
    "sg:phone":"+1 562 923 3000",
    "sg:postcode":"90241",
    "sg:province":"CA",
    "sg:tags":[
        "store"
    ],
    "wof:name":"Corioliss",
    "wof:placetype":"venue"
},
  "geometry": {"coordinates":[-118.121552,33.937906],"type":"Point"}
}