{
  "type": "Feature",
  "properties": {
    "addr:full":"10990 Lower Azusa Rd El Monte CA 91731",
    "addr:housenumber":"10990",
    "addr:postcode":"91731",
    "addr:street":"Lower Azusa Rd",
    "iso:country":"US",
    "sg:address":"10990 Lower Azusa Rd",
    "sg:city":"El Monte",
    "sg:classifiers":[
        {
            "category":"Food & Beverages",
            "subcategory":"Bakery",
            "type":"Retail Goods"
        }
    ],
    "sg:phone":"+1 626 443 5555",
    "sg:postcode":"91731",
    "sg:province":"CA",
    "sg:tags":[
        "product",
        "mfg"
    ],
    "wof:name":"Top Donut & Sandwich Shop",
    "wof:placetype":"venue"
},
  "geometry": {"coordinates":[-118.02773500000001,34.092234],"type":"Point"}
}