{
  "type": "Feature",
  "properties": {
    "addr:full":"11267 Coloma Rd Rancho Cordova CA 95670",
    "addr:housenumber":"11267",
    "addr:postcode":"95670",
    "addr:street":"Coloma Rd",
    "iso:country":"US",
    "sg:address":"11267 Coloma Rd",
    "sg:city":"Rancho Cordova",
    "sg:classifiers":[
        {
            "category":"Building & Trades",
            "subcategory":"Construction",
            "type":"Services"
        }
    ],
    "sg:phone":"+1 916 638 8889",
    "sg:postcode":"95670",
    "sg:province":"CA",
    "sg:tags":[
        "contractor"
    ],
    "wof:name":"Steel-Roof Supply",
    "wof:placetype":"venue"
},
  "geometry": {"coordinates":[-121.266285,38.61867],"type":"Point"}
}