{
  "type": "Feature",
  "properties": {
    "iso:country":"US",
    "sg:address":"3944 Murphy Canyon Rd",
    "sg:city":"San Diego",
    "sg:classifiers":[
        {
            "category":"Utilities",
            "subcategory":"Mobile Phone",
            "type":"Services"
        }
    ],
    "sg:phone":"+1 858 874 7700",
    "sg:postcode":"92123",
    "sg:province":"CA",
    "sg:tags":[
        "telephone",
        "cellular"
    ],
    "wof:name":"Celluphone",
    "wof:placetype":"venue"
},
  "geometry": {"coordinates":[-117.117086,32.82093],"type":"Point"}
}