{
  "type": "Feature",
  "properties": {
    "addr:full":"2635 Farwell Avenue Los Angeles CA 90039",
    "addr:housenumber":"2635",
    "addr:postcode":"90039",
    "addr:street":"Farwell Avenue",
    "iso:country":"US",
    "sg:address":"2635 Farwell Avenue",
    "sg:city":"Los Angeles",
    "sg:classifiers":[
        {
            "category":"Real Estate",
            "subcategory":"Real Estate Services",
            "type":"Services"
        }
    ],
    "sg:phone":"+1 323 665 5896",
    "sg:postcode":"90039",
    "sg:province":"CA",
    "sg:tags":[
        "management",
        "property"
    ],
    "wof:name":"Wolff Realty Company",
    "wof:placetype":"venue"
},
  "geometry": {"coordinates":[-118.25992599999999,34.105974],"type":"Point"}
}