{
  "type": "Feature",
  "properties": {
    "iso:country":"US",
    "sg:address":"4505 W 5th Street",
    "sg:city":"Los Angeles",
    "sg:classifiers":[
        {
            "category":"Building & Trades",
            "subcategory":"Construction",
            "type":"Services"
        }
    ],
    "sg:phone":"+1 323 549 0010",
    "sg:postcode":"90020",
    "sg:province":"CA",
    "sg:tags":[
        "painter",
        "contractor"
    ],
    "wof:name":"Clover Contracting",
    "wof:placetype":"venue"
},
  "geometry": {"coordinates":[-118.317403,34.065352],"type":"Point"}
}