{
  "type": "Feature",
  "properties": {
    "addr:full":"7404 Jackson Drive San Diego CA 92119",
    "addr:housenumber":"7404",
    "addr:postcode":"92119",
    "addr:street":"Jackson Drive",
    "iso:country":"US",
    "sg:address":"7404 Jackson Drive",
    "sg:city":"San Diego",
    "sg:classifiers":[
        {
            "category":"Banks & Credit Unions",
            "subcategory":"Bank",
            "type":"Services"
        },
        {
            "category":"Banks & Credit Unions",
            "subcategory":"Financial Services",
            "type":"Services"
        }
    ],
    "sg:phone":"+1 619 667 3220",
    "sg:postcode":"92119",
    "sg:province":"CA",
    "sg:tags":[
        "broker",
        "mortgage"
    ],
    "wof:name":"Bank of America",
    "wof:placetype":"venue"
},
  "geometry": {"coordinates":[-117.044961,32.802685],"type":"Point"}
}