{
  "type": "Feature",
  "properties": {
    "iso:country":"US",
    "sg:address":"1147 Osuna Pl",
    "sg:city":"San Jose",
    "sg:classifiers":[
        {
            "category":"Professional",
            "type":"Services"
        }
    ],
    "sg:phone":"+1 408 446 0255",
    "sg:postcode":"95129",
    "sg:province":"CA",
    "wof:name":"Kaelin Clan",
    "wof:placetype":"venue"
},
  "geometry": {"coordinates":[-121.989477,37.30408],"type":"Point"}
}