{
  "type": "Feature",
  "properties": {
    "addr:full":"3155 Rutledge Way Stockton CA 95219",
    "addr:housenumber":"3155",
    "addr:postcode":"95219",
    "addr:street":"Rutledge Way",
    "iso:country":"US",
    "sg:address":"3155 Rutledge Way",
    "sg:city":"Stockton",
    "sg:classifiers":[
        {
            "category":"Wholesale",
            "subcategory":"Durable Goods & Equipment",
            "type":"Manufacturing & Wholesale Goods"
        }
    ],
    "sg:phone":"+1 209 478 1897",
    "sg:postcode":"95219",
    "sg:province":"CA",
    "wof:name":"R Koon & Associates",
    "wof:placetype":"venue"
},
  "geometry": {"coordinates":[-121.35547800000001,38.003055],"type":"Point"}
}