{
  "type": "Feature",
  "properties": {
    "addr:full":"10040 Garvey Ave El Monte CA 91733",
    "addr:housenumber":"10040",
    "addr:postcode":"91733",
    "addr:street":"Garvey Ave",
    "iso:country":"US",
    "sg:address":"10040 Garvey Ave",
    "sg:city":"El Monte",
    "sg:classifiers":[
        {
            "category":"Food & Beverages",
            "subcategory":"Bakery",
            "type":"Retail Goods"
        }
    ],
    "sg:phone":"+1 626 452 8687",
    "sg:postcode":"91733",
    "sg:province":"CA",
    "sg:tags":[
        "baker"
    ],
    "wof:name":"Serina Bakery & Food Inc",
    "wof:placetype":"venue"
},
  "geometry": {"coordinates":[-118.051136,34.062632],"type":"Point"}
}