{
  "type": "Feature",
  "properties": {
    "addr:full":"275 Durley Ave Camarillo CA 93010",
    "addr:housenumber":"275",
    "addr:postcode":"93010",
    "addr:street":"Durley Ave",
    "iso:country":"US",
    "sg:address":"275 Durley Ave",
    "sg:city":"Camarillo",
    "sg:classifiers":[
        {
            "category":"Airport",
            "type":"Transportation"
        }
    ],
    "sg:phone":"+1 805 484 0556",
    "sg:postcode":"93010",
    "sg:province":"CA",
    "sg:tags":[
        "helicopter",
        "aircraft",
        "including",
        "maintenance",
        "repair"
    ],
    "wof:name":"Ro-Wing Aviation Inc",
    "wof:placetype":"venue"
},
  "geometry": {"coordinates":[-119.076537,34.208735],"type":"Point"}
}