{
  "type": "Feature",
  "properties": {
    "iso:country":"US",
    "sg:address":"1985 Bronson Way",
    "sg:city":"Riverside",
    "sg:classifiers":[
        {
            "category":"Shopping",
            "subcategory":"Bicycles & Sporting Goods",
            "type":"Retail Goods"
        }
    ],
    "sg:phone":"+1 951 787 8338",
    "sg:postcode":"92506",
    "sg:province":"CA",
    "wof:name":"White Wave Snowboards",
    "wof:placetype":"venue"
},
  "geometry": {"coordinates":[-117.353669,33.953714],"type":"Point"}
}