{
  "type": "Feature",
  "properties": {
    "iso:country":"US",
    "sg:address":"807 Marina Village Pkwy",
    "sg:city":"Alameda",
    "sg:classifiers":[
        {
            "category":"Restaurant",
            "type":"Food & Drink"
        }
    ],
    "sg:phone":"+1 510 522 5822",
    "sg:postcode":"94501",
    "sg:province":"CA",
    "sg:website":"www.angelasrestaurant.com",
    "wof:name":"Angela's Restaurant",
    "wof:placetype":"venue"
},
  "geometry": {"coordinates":[-122.275002,37.7827],"type":"Point"}
}