{
  "type": "Feature",
  "properties": {
    "addr:full":"350 Blomquist St Redwood City CA 94063",
    "addr:housenumber":"350",
    "addr:postcode":"94063",
    "addr:street":"Blomquist St",
    "iso:country":"US",
    "sg:address":"350 Blomquist St",
    "sg:city":"Redwood City",
    "sg:classifiers":[
        {
            "category":"Wholesale",
            "subcategory":"Machinery & Supplies",
            "type":"Manufacturing & Wholesale Goods"
        }
    ],
    "sg:phone":"+1 650 366 3732",
    "sg:postcode":"94063",
    "sg:province":"CA",
    "sg:tags":[
        "dry wall",
        "contractor"
    ],
    "wof:name":"T & H Building Supply",
    "wof:placetype":"venue"
},
  "geometry": {"coordinates":[-122.216257,37.492894],"type":"Point"}
}