{
  "type": "Feature",
  "properties": {
    "iso:country":"US",
    "sg:address":"2116 S Hacienda Blvd",
    "sg:city":"Hacienda Heights",
    "sg:classifiers":[
        {
            "category":"Shopping",
            "subcategory":"Hobbies, Toys, & Games",
            "type":"Retail Goods"
        }
    ],
    "sg:phone":"+1 626 968 4409",
    "sg:postcode":"91745",
    "sg:province":"CA",
    "wof:name":"G I Toys",
    "wof:placetype":"venue"
},
  "geometry": {"coordinates":[-117.96830300000001,33.994945],"type":"Point"}
}