{
  "type": "Feature",
  "properties": {
    "addr:full":"115 E Yosemite Ave Madera CA 93638",
    "addr:housenumber":"115",
    "addr:postcode":"93638",
    "addr:street":"E Yosemite Ave",
    "iso:country":"US",
    "sg:address":"115 E Yosemite Ave",
    "sg:city":"Madera",
    "sg:classifiers":[
        {
            "category":"Travel",
            "subcategory":"Travel Agent",
            "type":"Entertainment"
        }
    ],
    "sg:phone":"+1 559 661 3008",
    "sg:postcode":"93638",
    "sg:province":"CA",
    "sg:tags":[
        "agency"
    ],
    "wof:name":"Mundo Travel",
    "wof:placetype":"venue"
},
  "geometry": {"coordinates":[-120.058646,36.962576],"type":"Point"}
}