{
  "type": "Feature",
  "properties": {
    "iso:country":"US",
    "sg:address":"322 W D St",
    "sg:city":"Ontario",
    "sg:classifiers":[
        {
            "category":"Education",
            "subcategory":"School",
            "type":"Public Place"
        }
    ],
    "sg:phone":"+1 909 984 9123",
    "sg:postcode":"91762",
    "sg:province":"CA",
    "wof:name":"St George School",
    "wof:placetype":"venue"
},
  "geometry": {"coordinates":[-117.654511,34.067087],"type":"Point"}
}