{
  "type": "Feature",
  "properties": {
    "addr:full":"225 S Sepulveda Blvd Manhattan Beach CA 90266",
    "addr:housenumber":"225",
    "addr:postcode":"90266",
    "addr:street":"S Sepulveda Blvd",
    "iso:country":"US",
    "sg:address":"225 S Sepulveda Blvd",
    "sg:city":"Manhattan Beach",
    "sg:classifiers":[
        {
            "category":"Banks & Credit Unions",
            "subcategory":"Investment Brokerage",
            "type":"Services"
        }
    ],
    "sg:phone":"+1 310 937 8155",
    "sg:postcode":"90266",
    "sg:province":"CA",
    "sg:tags":[
        "stock",
        "bond"
    ],
    "wof:name":"Piper Jaffray Co",
    "wof:placetype":"venue"
},
  "geometry": {"coordinates":[-118.396045,33.878053],"type":"Point"}
}