{
  "type": "Feature",
  "properties": {
    "addr:full":"1776 Erringer Rd Simi Valley CA 93065",
    "addr:housenumber":"1776",
    "addr:postcode":"93065",
    "addr:street":"Erringer Rd",
    "iso:country":"US",
    "sg:address":"1776 Erringer Rd",
    "sg:city":"Simi Valley",
    "sg:classifiers":[
        {
            "category":"Health Services",
            "subcategory":"Doctor",
            "type":"Services"
        }
    ],
    "sg:phone":"+1 805 527 9300",
    "sg:postcode":"93065",
    "sg:province":"CA",
    "sg:tags":[
        "dentist"
    ],
    "wof:name":"Guss & Rahimi",
    "wof:placetype":"venue"
},
  "geometry": {"coordinates":[-118.761285,34.269175],"type":"Point"}
}