{
  "type": "Feature",
  "properties": {
    "iso:country":"US",
    "sg:address":"707 N Tustin St",
    "sg:city":"Orange",
    "sg:classifiers":[
        {
            "category":"Restaurant",
            "type":"Food & Drink"
        }
    ],
    "sg:menulink":"http://www.allmenus.com/ca/anaheim-santa-ana-garden-grove/97058-ihop/menu/",
    "sg:phone":"+1 714 639 1533",
    "sg:postcode":"92867",
    "sg:province":"CA",
    "sg:tags":[
        "sandwich",
        "salad",
        "burger",
        "soup",
        "american",
        "steakhouse",
        "wrap"
    ],
    "wof:name":"IHOP",
    "wof:placetype":"venue"
},
  "geometry": {"coordinates":[-117.835285,33.798904],"type":"Point"}
}