{
  "type": "Feature",
  "properties": {
    "iso:country":"US",
    "sg:address":"2941 N Gainsborough Dr",
    "sg:city":"San Marino",
    "sg:classifiers":[
        {
            "category":"Banks & Credit Unions",
            "subcategory":"Financial Services",
            "type":"Services"
        }
    ],
    "sg:phone":"+1 626 577 2144",
    "sg:postcode":"91108",
    "sg:province":"CA",
    "sg:tags":[
        "investor"
    ],
    "wof:name":"Kirimis Investments",
    "wof:placetype":"venue"
},
  "geometry": {"coordinates":[-118.093299,34.128612],"type":"Point"}
}