{
  "type": "Feature",
  "properties": {
    "iso:country":"US",
    "sg:address":"119 Park Blvd",
    "sg:city":"Millbrae",
    "sg:classifiers":[
        {
            "category":"Health Services",
            "subcategory":"Chiropractor",
            "type":"Services"
        }
    ],
    "sg:phone":"+1 650 952 7246",
    "sg:postcode":"94030",
    "sg:province":"CA",
    "wof:name":"Linford Chiropractic",
    "wof:placetype":"venue"
},
  "geometry": {"coordinates":[-122.40383799999999,37.612441],"type":"Point"}
}