{
  "type": "Feature",
  "properties": {
    "addr:full":"4703 Hazeltine Ave. Sherman Oaks CA 91423",
    "addr:housenumber":"4703",
    "addr:postcode":"91423",
    "addr:street":"Hazeltine Ave.",
    "iso:country":"US",
    "sg:address":"4703 Hazeltine Ave.",
    "sg:city":"Sherman Oaks",
    "sg:classifiers":[
        {
            "category":"Personal",
            "type":"Services"
        }
    ],
    "sg:phone":"+1 818 995 1453",
    "sg:postcode":"91423",
    "sg:province":"CA",
    "sg:tags":[
        "towing"
    ],
    "wof:name":"Sherman Oaks Club Service, Inc.",
    "wof:placetype":"venue"
},
  "geometry": {"coordinates":[-118.439982,34.15724],"type":"Point"}
}