{
  "type": "Feature",
  "properties": {
    "addr:full":"660 Sanitarium Rd Deer Park CA 94576",
    "addr:housenumber":"660",
    "addr:postcode":"94576",
    "addr:street":"Sanitarium Rd",
    "iso:country":"US",
    "sg:address":"660 Sanitarium Rd",
    "sg:city":"Deer Park",
    "sg:classifiers":[
        {
            "category":"Health Services",
            "subcategory":"Health Practitioner",
            "type":"Services"
        }
    ],
    "sg:phone":"+1 707 963 1493",
    "sg:postcode":"94576",
    "sg:province":"CA",
    "sg:tags":[
        "psychologist"
    ],
    "wof:name":"Pacifica Pain Management Svc",
    "wof:placetype":"venue"
},
  "geometry": {"coordinates":[-122.476023,38.544105],"type":"Point"}
}