{
  "type": "Feature",
  "properties": {
    "iso:country":"US",
    "sg:address":"9107 W Olympic Blvd",
    "sg:city":"Beverly Hills",
    "sg:classifiers":[
        {
            "category":"Shopping",
            "subcategory":"Clothing, Apparel, & Fashions",
            "type":"Retail Goods"
        }
    ],
    "sg:phone":"+1 310 273 6266",
    "sg:postcode":"90212",
    "sg:province":"CA",
    "sg:tags":[
        "tailor"
    ],
    "wof:name":"Le Roy Cleaners",
    "wof:placetype":"venue"
},
  "geometry": {"coordinates":[-118.390084,34.059462],"type":"Point"}
}