{
  "type": "Feature",
  "properties": {
    "addr:full":"348 E Ave K Lancaster CA 93535",
    "addr:housenumber":"348",
    "addr:postcode":"93535",
    "addr:street":"E Ave K",
    "iso:country":"US",
    "sg:address":"348 E Ave K",
    "sg:city":"Lancaster",
    "sg:classifiers":[
        {
            "category":"Communications",
            "subcategory":"Radio Station",
            "type":"Services"
        }
    ],
    "sg:phone":"+1 661 940 9487",
    "sg:postcode":"93535",
    "sg:province":"CA",
    "sg:tags":[
        "company",
        "broadcasting"
    ],
    "wof:name":"Fox Sports 610 AM",
    "wof:placetype":"venue"
},
  "geometry": {"coordinates":[-118.12381999999999,34.674914],"type":"Point"}
}