{
  "type": "Feature",
  "properties": {
    "addr:full":"11610 Iberia Pl San Diego CA 92128",
    "addr:housenumber":"11610",
    "addr:postcode":"92128",
    "addr:street":"Iberia Pl",
    "iso:country":"US",
    "sg:address":"11610 Iberia Pl",
    "sg:city":"San Diego",
    "sg:classifiers":[
        {
            "category":"Insurance",
            "subcategory":"Insurance Agent",
            "type":"Services"
        }
    ],
    "sg:phone":"+1 858 485 8852",
    "sg:postcode":"92128",
    "sg:province":"CA",
    "wof:name":"Executive & Employee Benefit",
    "wof:placetype":"venue"
},
  "geometry": {"coordinates":[-117.07684399999999,33.015326],"type":"Point"}
}