{
  "type": "Feature",
  "properties": {
    "iso:country":"US",
    "sg:address":"260 Dondero Way",
    "sg:city":"San Jose",
    "sg:classifiers":[
        {
            "category":"Building & Trades",
            "subcategory":"Cleaning & Sanitation",
            "type":"Services"
        }
    ],
    "sg:phone":"+1 408 229 1567",
    "sg:postcode":"95119",
    "sg:province":"CA",
    "sg:tags":[
        "maintenance"
    ],
    "wof:name":"Details Cleaning Services",
    "wof:placetype":"venue"
},
  "geometry": {"coordinates":[-121.79805,37.232799],"type":"Point"}
}