{
  "type": "Feature",
  "properties": {
    "addr:full":"2435 E Colorado Blvd Pasadena CA 91107",
    "addr:housenumber":"2435",
    "addr:postcode":"91107",
    "addr:street":"E Colorado Blvd",
    "iso:country":"US",
    "sg:address":"2435 E Colorado Blvd",
    "sg:city":"Pasadena",
    "sg:classifiers":[
        {
            "category":"Building & Trades",
            "subcategory":"Electrical",
            "type":"Services"
        }
    ],
    "sg:phone":"+1 626 564 1955",
    "sg:postcode":"91107",
    "sg:province":"CA",
    "sg:tags":[
        "electrician"
    ],
    "wof:name":"Faultless Electric",
    "wof:placetype":"venue"
},
  "geometry": {"coordinates":[-118.100082,34.146408],"type":"Point"}
}