{
  "type": "Feature",
  "properties": {
    "addr:full":"10442 Nora Dr Redding CA 96003",
    "addr:housenumber":"10442",
    "addr:postcode":"96003",
    "addr:street":"Nora Dr",
    "iso:country":"US",
    "sg:address":"10442 Nora Dr",
    "sg:city":"Redding",
    "sg:classifiers":[
        {
            "category":"Building & Trades",
            "subcategory":"Landscaping Services",
            "type":"Services"
        }
    ],
    "sg:phone":"+1 530 223 2077",
    "sg:postcode":"96003",
    "sg:province":"CA",
    "wof:name":"Dennis Tree Service",
    "wof:placetype":"venue"
},
  "geometry": {"coordinates":[-122.304705,40.589031],"type":"Point"}
}