{
  "type": "Feature",
  "properties": {
    "iso:country":"US",
    "sg:address":"10919 Vanowen St",
    "sg:city":"North Hollywood",
    "sg:classifiers":[
        {
            "category":"Shopping",
            "subcategory":"Jewelry",
            "type":"Retail Goods"
        }
    ],
    "sg:phone":"+1 818 769 7135",
    "sg:postcode":"91605",
    "sg:province":"CA",
    "sg:tags":[
        "jeweler"
    ],
    "wof:name":"Mimitrinka Jewelry & Gifts",
    "wof:placetype":"venue"
},
  "geometry": {"coordinates":[-118.369981,34.194018],"type":"Point"}
}