{
  "type": "Feature",
  "properties": {
    "iso:country":"US",
    "sg:address":"39207 Sundale Dr",
    "sg:city":"Fremont",
    "sg:classifiers":[
        {
            "category":"Education",
            "subcategory":"Special Training",
            "type":"Public Place"
        },
        {
            "category":"Social Services",
            "subcategory":"Child Care",
            "type":"Services"
        },
        {
            "category":"Education",
            "subcategory":"Preschool",
            "type":"Public Place"
        },
        {
            "category":"Education",
            "subcategory":"School",
            "type":"Public Place"
        }
    ],
    "sg:phone":"+1 510 651 1190",
    "sg:postcode":"94538",
    "sg:province":"CA",
    "sg:tags":[
        "educational",
        "private",
        "kindergarten",
        "nursery",
        "k-",
        "day"
    ],
    "sg:website":"http://www.fremont.k12.ca.us",
    "wof:name":"Fusd Glankler State Preschool",
    "wof:placetype":"venue"
},
  "geometry": {"coordinates":[-121.98488999999999,37.539393],"type":"Point"}
}