{
  "type": "Feature",
  "properties": {
    "iso:country":"US",
    "sg:address":"1610 Blossom Hill Rd",
    "sg:city":"San Jose",
    "sg:classifiers":[
        {
            "category":"Wholesale",
            "subcategory":"Stationery",
            "type":"Manufacturing & Wholesale Goods"
        }
    ],
    "sg:phone":"+1 408 996 3676",
    "sg:postcode":"95124",
    "sg:province":"CA",
    "sg:tags":[
        "business",
        "form",
        "system"
    ],
    "wof:name":"Design Rite Business Forms",
    "wof:placetype":"venue"
},
  "geometry": {"coordinates":[-121.904365,37.236282],"type":"Point"}
}