{
  "type": "Feature",
  "properties": {
    "iso:country":"US",
    "sg:address":"1036 86th Ave",
    "sg:city":"Oakland",
    "sg:classifiers":[
        {
            "category":"Building & Trades",
            "subcategory":"Construction",
            "type":"Services"
        }
    ],
    "sg:phone":"+1 415 260 7009",
    "sg:postcode":"94621",
    "sg:province":"CA",
    "sg:tags":[
        "contractor"
    ],
    "wof:name":"JBE Construction",
    "wof:placetype":"venue"
},
  "geometry": {"coordinates":[-122.18250999999999,37.749776],"type":"Point"}
}