{
  "type": "Feature",
  "properties": {
    "addr:full":"4665 Beacon Rd Paso Robles CA 93446",
    "addr:housenumber":"4665",
    "addr:postcode":"93446",
    "addr:street":"Beacon Rd",
    "iso:country":"US",
    "sg:address":"4665 Beacon Rd",
    "sg:city":"Paso Robles",
    "sg:classifiers":[
        {
            "category":"Organizations",
            "subcategory":"Religious Organization",
            "type":"Services"
        }
    ],
    "sg:phone":"+1 805 226 7350",
    "sg:postcode":"93446",
    "sg:province":"CA",
    "sg:tags":[
        "church"
    ],
    "wof:name":"Midstate Baptist",
    "wof:placetype":"venue"
},
  "geometry": {"coordinates":[-120.612111,35.674104],"type":"Point"}
}