{
  "type": "Feature",
  "properties": {
    "iso:country":"US",
    "sg:address":"2222 Atlantic Ave",
    "sg:city":"Long Beach",
    "sg:classifiers":[
        {
            "category":"Food & Beverages",
            "subcategory":"Bakery",
            "type":"Retail Goods"
        }
    ],
    "sg:phone":"+1 562 595 1004",
    "sg:postcode":"90806",
    "sg:province":"CA",
    "sg:tags":[
        "baker"
    ],
    "wof:name":"El Buen Sabor",
    "wof:placetype":"venue"
},
  "geometry": {"coordinates":[-118.18493700000001,33.798525],"type":"Point"}
}