{
  "type": "Feature",
  "properties": {
    "addr:full":"211 S Beach Blvd Spc 2 Anaheim CA 92804",
    "addr:housenumber":"211;2",
    "addr:postcode":"92804",
    "addr:street":"S Beach Blvd Spc",
    "iso:country":"US",
    "sg:address":"211 S Beach Blvd Spc 2",
    "sg:city":"Anaheim",
    "sg:classifiers":[
        {
            "category":"Building & Trades",
            "subcategory":"Construction",
            "type":"Services"
        }
    ],
    "sg:phone":"+1 714 236 0355",
    "sg:postcode":"92804",
    "sg:province":"CA",
    "sg:tags":[
        "air",
        "heating",
        "conditioning/hvac"
    ],
    "wof:name":"McCurley's Hvac Service",
    "wof:placetype":"venue"
},
  "geometry": {"coordinates":[-117.994613,33.829063],"type":"Point"}
}