{
  "type": "Feature",
  "properties": {
    "iso:country":"US",
    "sg:address":"10924 Rincon Dr",
    "sg:city":"Whittier",
    "sg:classifiers":[
        {
            "category":"Professional",
            "type":"Services"
        }
    ],
    "sg:phone":"+1 562 908 8288",
    "sg:postcode":"90606",
    "sg:province":"CA",
    "wof:name":"Molino",
    "wof:placetype":"venue"
},
  "geometry": {"coordinates":[-118.063261,33.987483],"type":"Point"}
}