{
  "type": "Feature",
  "properties": {
    "iso:country":"US",
    "sg:address":"365 Revere St",
    "sg:city":"Upland",
    "sg:classifiers":[
        {
            "category":"Home & Garden",
            "subcategory":"Building Materials",
            "type":"Retail Goods"
        },
        {
            "category":"Building & Trades",
            "subcategory":"Construction",
            "type":"Services"
        }
    ],
    "sg:phone":"+1 909 838 7936",
    "sg:postcode":"91784",
    "sg:province":"CA",
    "sg:tags":[
        "concrete",
        "staining",
        "contractor"
    ],
    "wof:name":"G & M Quality Concrete Inc",
    "wof:placetype":"venue"
},
  "geometry": {"coordinates":[-117.64681899999999,34.145773],"type":"Point"}
}