{
  "type": "Feature",
  "properties": {
    "addr:full":"6015 York Blvd Los Angeles CA 90042",
    "addr:housenumber":"6015",
    "addr:postcode":"90042",
    "addr:street":"York Blvd",
    "iso:country":"US",
    "sg:address":"6015 York Blvd",
    "sg:city":"Los Angeles",
    "sg:classifiers":[
        {
            "category":"Home & Garden",
            "subcategory":"Garden Supply",
            "type":"Retail Goods"
        }
    ],
    "sg:phone":"+1 323 257 7400",
    "sg:postcode":"90042",
    "sg:province":"CA",
    "sg:tags":[
        "nursery",
        "gardening"
    ],
    "wof:name":"York Blvd Nursery",
    "wof:placetype":"venue"
},
  "geometry": {"coordinates":[-118.189003,34.118099],"type":"Point"}
}