{
  "type": "Feature",
  "properties": {
    "iso:country":"US",
    "sg:address":"614 Crystal Springs Dr",
    "sg:city":"Woodland",
    "sg:classifiers":[
        {
            "category":"Building & Trades",
            "subcategory":"Construction",
            "type":"Services"
        }
    ],
    "sg:phone":"+1 530 662 5735",
    "sg:postcode":"95776",
    "sg:province":"CA",
    "sg:tags":[
        "concrete",
        "contractor"
    ],
    "wof:name":"Bbb Custom Poured Baits",
    "wof:placetype":"venue"
},
  "geometry": {"coordinates":[-121.752184,38.672559],"type":"Point"}
}