{
  "type": "Feature",
  "properties": {
    "iso:country":"US",
    "sg:address":"2417 W Olive Ave",
    "sg:city":"Fullerton",
    "sg:classifiers":[
        {
            "category":"Building & Trades",
            "subcategory":"Construction",
            "type":"Services"
        }
    ],
    "sg:phone":"+1 714 525 3327",
    "sg:postcode":"92833",
    "sg:province":"CA",
    "sg:tags":[
        "wallcoverings-installation",
        "wallpaper",
        "painting",
        "contractor"
    ],
    "wof:name":"Home Painting",
    "wof:placetype":"venue"
},
  "geometry": {"coordinates":[-117.969413,33.862341],"type":"Point"}
}