{
  "type": "Feature",
  "properties": {
    "iso:country":"US",
    "sg:address":"141 Daniel Dr",
    "sg:city":"Alamo",
    "sg:classifiers":[
        {
            "category":"Real Estate",
            "subcategory":"Real Estate Services",
            "type":"Services"
        }
    ],
    "sg:phone":"+1 925 837 7363",
    "sg:postcode":"94507",
    "sg:province":"CA",
    "sg:tags":[
        "home",
        "inspector"
    ],
    "wof:name":"Western Home Inspection",
    "wof:placetype":"venue"
},
  "geometry": {"coordinates":[-122.243278,37.837889],"type":"Point"}
}