{
  "type": "Feature",
  "properties": {
    "addr:full":"3744 Pheasant Ln Brea CA 92823",
    "addr:housenumber":"3744",
    "addr:postcode":"92823",
    "addr:street":"Pheasant Ln",
    "iso:country":"US",
    "sg:address":"3744 Pheasant Ln",
    "sg:city":"Brea",
    "sg:classifiers":[
        {
            "category":"Personal",
            "subcategory":"Beauty Salon",
            "type":"Services"
        }
    ],
    "sg:phone":"+1 714 572 4375",
    "sg:postcode":"92823",
    "sg:province":"CA",
    "wof:name":"Gina's Skin Care",
    "wof:placetype":"venue"
},
  "geometry": {"coordinates":[-117.844751,33.924702],"type":"Point"}
}