{
  "type": "Feature",
  "properties": {
    "iso:country":"US",
    "sg:address":"18034 Ventura Blvd",
    "sg:city":"Encino",
    "sg:classifiers":[
        {
            "category":"Shopping",
            "subcategory":"Gifts & Souvenirs",
            "type":"Retail Goods"
        }
    ],
    "sg:phone":"+1 818 708 8870",
    "sg:postcode":"91316",
    "sg:province":"CA",
    "sg:tags":[
        "shop"
    ],
    "wof:name":"Silver Sentiments Intl",
    "wof:placetype":"venue"
},
  "geometry": {"coordinates":[-118.526466,34.165054],"type":"Point"}
}