{
  "type": "Feature",
  "properties": {
    "addr:full":"39884 Rd 425B Oakhurst CA 93644",
    "addr:housenumber":"39884;425b",
    "addr:postcode":"93644",
    "addr:street":"Rd",
    "iso:country":"US",
    "sg:address":"39884 Rd 425B",
    "sg:city":"Oakhurst",
    "sg:classifiers":[
        {
            "category":"Social Services",
            "type":"Services"
        }
    ],
    "sg:phone":"+1 559 642 2111",
    "sg:postcode":"93644",
    "sg:province":"CA",
    "sg:tags":[
        "probation"
    ],
    "wof:name":"Madera County Probation Dept",
    "wof:placetype":"venue"
},
  "geometry": {"coordinates":[-119.649531,37.326921],"type":"Point"}
}