{
  "type": "Feature",
  "properties": {
    "iso:country":"US",
    "sg:address":"5930 Holway St",
    "sg:city":"Oakland",
    "sg:classifiers":[
        {
            "category":"Professional",
            "type":"Services"
        }
    ],
    "sg:phone":"+1 510 639 0568",
    "sg:postcode":"94621",
    "sg:province":"CA",
    "wof:name":"The Valrey Co",
    "wof:placetype":"venue"
},
  "geometry": {"coordinates":[-122.19407200000001,37.766451],"type":"Point"}
}