{
  "type": "Feature",
  "properties": {
    "addr:full":"7715 Burnet Ave Van Nuys CA 91405",
    "addr:housenumber":"7715",
    "addr:postcode":"91405",
    "addr:street":"Burnet Ave",
    "iso:country":"US",
    "sg:address":"7715 Burnet Ave",
    "sg:city":"Van Nuys",
    "sg:classifiers":[
        {
            "category":"Professional",
            "subcategory":"Detective & Security Services",
            "type":"Services"
        }
    ],
    "sg:phone":"+1 818 785 0085",
    "sg:postcode":"91405",
    "sg:province":"CA",
    "sg:tags":[
        "guard",
        "patrol"
    ],
    "wof:name":"S K Security Licensing",
    "wof:placetype":"venue"
},
  "geometry": {"coordinates":[-118.46300100000001,34.211108],"type":"Point"}
}