{
  "type": "Feature",
  "properties": {
    "iso:country":"US",
    "sg:address":"9310 Topanga Canyon Blvd",
    "sg:city":"Chatsworth",
    "sg:classifiers":[
        {
            "category":"Professional",
            "subcategory":"Accounting & Tax Preparation",
            "type":"Services"
        }
    ],
    "sg:phone":"+1 818 998 8484",
    "sg:postcode":"91311",
    "sg:province":"CA",
    "sg:tags":[
        "return",
        "filing"
    ],
    "wof:name":"Elam & Assoc",
    "wof:placetype":"venue"
},
  "geometry": {"coordinates":[-118.605936,34.240782],"type":"Point"}
}