{
  "type": "Feature",
  "properties": {
    "iso:country":"US",
    "sg:address":"966 S Western Ave Ste 207",
    "sg:city":"Los Angeles",
    "sg:classifiers":[
        {
            "category":"Health Services",
            "subcategory":"Dentist",
            "type":"Services"
        }
    ],
    "sg:phone":"+1 323 734 3710",
    "sg:postcode":"90006",
    "sg:province":"CA",
    "sg:website":"www.osmiledentistry.com",
    "wof:name":"O Smile Dentistry",
    "wof:placetype":"venue"
},
  "geometry": {"coordinates":[-118.308998,34.053501],"type":"Point"}
}