{
  "type": "Feature",
  "properties": {
    "addr:full":"73819 Masson St Palm Desert CA 92260",
    "addr:housenumber":"73819",
    "addr:postcode":"92260",
    "addr:street":"Masson St",
    "iso:country":"US",
    "sg:address":"73819 Masson St",
    "sg:city":"Palm Desert",
    "sg:classifiers":[
        {
            "category":"Banks & Credit Unions",
            "subcategory":"Investment Brokerage",
            "type":"Services"
        }
    ],
    "sg:phone":"+1 760 423 4212",
    "sg:postcode":"92260",
    "sg:province":"CA",
    "sg:tags":[
        "advisory",
        "financial"
    ],
    "wof:name":"Ram Financial Securities",
    "wof:placetype":"venue"
},
  "geometry": {"coordinates":[-116.376425,33.732542],"type":"Point"}
}