{
  "type": "Feature",
  "properties": {
    "iso:country":"US",
    "sg:address":"12034 Riverside Dr",
    "sg:city":"Valley Village",
    "sg:classifiers":[
        {
            "category":"Professional",
            "subcategory":"Lawyer & Legal Services",
            "type":"Services"
        }
    ],
    "sg:phone":"+1 818 509 0980",
    "sg:postcode":"91607",
    "sg:province":"CA",
    "wof:name":"Jackson & Sutor Attorneys At Law",
    "wof:placetype":"venue"
},
  "geometry": {"coordinates":[-118.394997,34.1576],"type":"Point"}
}