{
  "type": "Feature",
  "properties": {
    "addr:full":"631 Abrego St Monterey CA 93940",
    "addr:housenumber":"631",
    "addr:postcode":"93940",
    "addr:street":"Abrego St",
    "iso:country":"US",
    "sg:address":"631 Abrego St",
    "sg:city":"Monterey",
    "sg:classifiers":[
        {
            "category":"Organizations",
            "subcategory":"Religious Organization",
            "type":"Services"
        }
    ],
    "sg:phone":"+1 831 373 4345",
    "sg:postcode":"93940",
    "sg:province":"CA",
    "sg:tags":[
        "church"
    ],
    "wof:name":"Diocese Of Monterey-Cemeteries",
    "wof:placetype":"venue"
},
  "geometry": {"coordinates":[-121.892048,36.59536],"type":"Point"}
}