{
  "type": "Feature",
  "properties": {
    "iso:country":"US",
    "sg:address":"1930 E Carson St",
    "sg:city":"Carson",
    "sg:classifiers":[
        {
            "category":"Wholesale",
            "subcategory":"Durable Goods & Equipment",
            "type":"Manufacturing & Wholesale Goods"
        }
    ],
    "sg:phone":"+1 310 764 4880",
    "sg:postcode":"90810",
    "sg:province":"CA",
    "sg:tags":[
        "importer"
    ],
    "wof:name":"Smart Cargo Svc",
    "wof:placetype":"venue"
},
  "geometry": {"coordinates":[-118.238845,33.831647],"type":"Point"}
}