{
  "type": "Feature",
  "properties": {
    "iso:country":"US",
    "sg:address":"181 Industry Ave",
    "sg:city":"La Habra",
    "sg:classifiers":[
        {
            "category":"Real Estate",
            "subcategory":"Real Estate Agent",
            "type":"Services"
        }
    ],
    "sg:phone":"+1 714 449 9656",
    "sg:postcode":"90631",
    "sg:province":"CA",
    "wof:name":"Sekhon Properties",
    "wof:placetype":"venue"
},
  "geometry": {"coordinates":[-117.944605,33.917984],"type":"Point"}
}