{
  "type": "Feature",
  "properties": {
    "iso:country":"US",
    "sg:address":"2140 S Hacienda Blvd",
    "sg:city":"Hacienda Heights",
    "sg:classifiers":[
        {
            "category":"Education",
            "subcategory":"Special Training",
            "type":"Public Place"
        }
    ],
    "sg:phone":"+1 626 961 8880",
    "sg:postcode":"91745",
    "sg:province":"CA",
    "sg:tags":[
        "tutoring"
    ],
    "wof:name":"JEI Learning Ctr",
    "wof:placetype":"venue"
},
  "geometry": {"coordinates":[-117.968197,33.99525],"type":"Point"}
}