{
  "type": "Feature",
  "properties": {
    "addr:full":"2812 Lincoln Ave Alameda CA 94501",
    "addr:housenumber":"2812",
    "addr:postcode":"94501",
    "addr:street":"Lincoln Ave",
    "iso:country":"US",
    "sg:address":"2812 Lincoln Ave",
    "sg:city":"Alameda",
    "sg:classifiers":[
        {
            "category":"Professional",
            "subcategory":"Computer Services",
            "type":"Services"
        }
    ],
    "sg:phone":"+1 510 522 6071",
    "sg:postcode":"94501",
    "sg:province":"CA",
    "sg:website":"www.compuprosystems.com",
    "wof:name":"Compupro Systems",
    "wof:placetype":"venue"
},
  "geometry": {"coordinates":[-122.234824,37.763392],"type":"Point"}
}