{
  "type": "Feature",
  "properties": {
    "iso:country":"US",
    "sg:address":"346 N Tehama St",
    "sg:city":"Willows",
    "sg:classifiers":[
        {
            "category":"Organizations",
            "subcategory":"Religious Organization",
            "type":"Services"
        }
    ],
    "sg:phone":"+1 530 934 9673",
    "sg:postcode":"95988",
    "sg:province":"CA",
    "sg:tags":[
        "church"
    ],
    "wof:name":"Promised Land World Outreach",
    "wof:placetype":"venue"
},
  "geometry": {"coordinates":[-122.193788,39.523724],"type":"Point"}
}