{
  "type": "Feature",
  "properties": {
    "addr:full":"518 Needham St Modesto CA 95354",
    "addr:housenumber":"518",
    "addr:postcode":"ca 95354",
    "addr:street":"Needham St",
    "iso:country":"US",
    "sg:address":"518 Needham St",
    "sg:city":"Modesto",
    "sg:classifiers":[
        {
            "category":"Professional",
            "subcategory":"Lawyer & Legal Services",
            "type":"Services"
        }
    ],
    "sg:phone":"+1 209 523 2001",
    "sg:postcode":"95354",
    "sg:province":"CA",
    "sg:tags":[
        "attorney"
    ],
    "wof:name":"Drivers Defense Law Office",
    "wof:placetype":"venue"
},
  "geometry": {"coordinates":[-121.00018300000001,37.64579],"type":"Point"}
}