{
  "type": "Feature",
  "properties": {
    "addr:full":"20240 Avalon Blvd Carson CA 90746",
    "addr:housenumber":"20240",
    "addr:postcode":"90746",
    "addr:street":"Avalon Blvd",
    "iso:country":"US",
    "sg:address":"20240 Avalon Blvd",
    "sg:city":"Carson",
    "sg:classifiers":[
        {
            "category":"Coffee & Tea",
            "type":"Food & Drink"
        }
    ],
    "sg:phone":"+1 310 324 4012",
    "sg:postcode":"90746",
    "sg:province":"CA",
    "sg:website":"www.starbucks.com/store/17360",
    "wof:name":"Starbucks",
    "wof:placetype":"venue"
},
  "geometry": {"coordinates":[-118.264304,33.847894],"type":"Point"}
}