{
  "type": "Feature",
  "properties": {
    "iso:country":"US",
    "sg:address":"1112 Meadow Ln",
    "sg:city":"Concord",
    "sg:classifiers":[
        {
            "category":"Food & Beverages",
            "subcategory":"Groceries & Convenience Stores",
            "type":"Retail Goods"
        }
    ],
    "sg:phone":"+1 925 825 1500",
    "sg:postcode":"94520",
    "sg:province":"CA",
    "wof:name":"Afghan Bread Market",
    "wof:placetype":"venue"
},
  "geometry": {"coordinates":[-122.040384,37.958041],"type":"Point"}
}