{
  "type": "Feature",
  "properties": {
    "iso:country":"US",
    "sg:address":"1025 Laurel Fig Dr",
    "sg:city":"Simi Valley",
    "sg:classifiers":[
        {
            "category":"Building & Trades",
            "subcategory":"Construction",
            "type":"Services"
        }
    ],
    "sg:phone":"+1 805 581 5883",
    "sg:postcode":"93065",
    "sg:province":"CA",
    "sg:tags":[
        "contractor"
    ],
    "wof:name":"Mark Lubin Contractor",
    "wof:placetype":"venue"
},
  "geometry": {"coordinates":[-118.73621900000001,34.258202],"type":"Point"}
}