{
  "type": "Feature",
  "properties": {
    "iso:country":"US",
    "sg:address":"2120 El Camino Real",
    "sg:city":"Santa Clara",
    "sg:classifiers":[
        {
            "category":"Banks & Credit Unions",
            "subcategory":"Bank",
            "type":"Services"
        }
    ],
    "sg:phone":"+1 408 423 8500",
    "sg:postcode":"95050",
    "sg:province":"CA",
    "wof:name":"Bridge Bank of Silicon Valley",
    "wof:placetype":"venue"
},
  "geometry": {"coordinates":[-121.962997,37.352299],"type":"Point"}
}