{
  "type": "Feature",
  "properties": {
    "addr:full":"37363 Main St Burney CA 96013",
    "addr:housenumber":"37363",
    "addr:postcode":"96013",
    "addr:street":"Main St",
    "iso:country":"US",
    "sg:address":"37363 Main St",
    "sg:city":"Burney",
    "sg:classifiers":[
        {
            "category":"Travel",
            "subcategory":"Hotels & Motels",
            "type":"Entertainment"
        }
    ],
    "sg:phone":"+1 530 335 2254",
    "sg:postcode":"96013",
    "sg:province":"CA",
    "wof:name":"Charm Motel",
    "wof:placetype":"venue"
},
  "geometry": {"coordinates":[-121.657043,40.885169],"type":"Point"}
}