{
  "type": "Feature",
  "properties": {
    "addr:full":"42859 Rd 52 Reedley CA 93654",
    "addr:postcode":"42859;93654",
    "addr:street":"Rd 52",
    "iso:country":"US",
    "sg:address":"42859 Rd 52",
    "sg:city":"Reedley",
    "sg:classifiers":[
        {
            "category":"Building & Trades",
            "subcategory":"Landscaping Services",
            "type":"Services"
        }
    ],
    "sg:phone":"+1 559 638 1124",
    "sg:postcode":"93654",
    "sg:province":"CA",
    "sg:tags":[
        "tree"
    ],
    "wof:name":"Penner Enterprises Inc",
    "wof:placetype":"venue"
},
  "geometry": {"coordinates":[-119.457786,36.566937],"type":"Point"}
}