{
  "type": "Feature",
  "properties": {
    "iso:country":"US",
    "sg:address":"744 Mcewen Rd",
    "sg:city":"Waterford",
    "sg:classifiers":[
        {
            "category":"Food & Beverages",
            "subcategory":"Dairy",
            "type":"Retail Goods"
        }
    ],
    "sg:phone":"+1 209 524 1363",
    "sg:postcode":"95386",
    "sg:province":"CA",
    "sg:tags":[
        "product"
    ],
    "wof:name":"Michael Ag Best",
    "wof:placetype":"venue"
},
  "geometry": {"coordinates":[-120.811043,37.62594],"type":"Point"}
}