{
  "type": "Feature",
  "properties": {
    "iso:country":"US",
    "sg:address":"760 N Brookhurst St",
    "sg:city":"Anaheim",
    "sg:classifiers":[
        {
            "category":"Sports & Exercise",
            "subcategory":"Gym",
            "type":"Entertainment"
        }
    ],
    "sg:phone":"+1 714 991 1066",
    "sg:postcode":"92801",
    "sg:province":"CA",
    "sg:website":"www.curves.com",
    "wof:name":"Curves",
    "wof:placetype":"venue"
},
  "geometry": {"coordinates":[-117.958794,33.840692],"type":"Point"}
}