{
  "type": "Feature",
  "properties": {
    "addr:full":"2565 Franklin Blvd Sacramento CA 95817",
    "addr:housenumber":"2565",
    "addr:postcode":"95817",
    "addr:street":"Franklin Blvd",
    "iso:country":"US",
    "sg:address":"2565 Franklin Blvd",
    "sg:city":"Sacramento",
    "sg:classifiers":[
        {
            "category":"Bars & Pubs",
            "type":"Food & Drink"
        }
    ],
    "sg:phone":"+1 916 455 1331",
    "sg:postcode":"95817",
    "sg:province":"CA",
    "sg:website":"www.facebook.com/pages",
    "wof:name":"Hideaway Bar & Grill",
    "wof:placetype":"venue"
},
  "geometry": {"coordinates":[-121.47545599999999,38.555918],"type":"Point"}
}