{
  "type": "Feature",
  "properties": {
    "addr:full":"1615 J St Sacramento CA 95814",
    "addr:housenumber":"1615",
    "addr:postcode":"95814",
    "addr:street":"J St",
    "iso:country":"US",
    "sg:address":"1615 J St",
    "sg:city":"Sacramento",
    "sg:classifiers":[
        {
            "category":"Restaurant",
            "type":"Food & Drink"
        }
    ],
    "sg:phone":"+1 916 669 5300",
    "sg:postcode":"95814",
    "sg:province":"CA",
    "sg:tags":[
        "new",
        "american",
        "mediterranean"
    ],
    "sg:website":"www.luccarestaurant.com",
    "wof:name":"Lucca Restaurant & Bar",
    "wof:placetype":"venue"
},
  "geometry": {"coordinates":[-121.485001,38.578201],"type":"Point"}
}