{
  "type": "Feature",
  "properties": {
    "iso:country":"US",
    "sg:address":"7155 Hwy 9",
    "sg:city":"Felton",
    "sg:classifiers":[
        {
            "category":"Education",
            "subcategory":"School",
            "type":"Public Place"
        }
    ],
    "sg:phone":"+1 831 335 4475",
    "sg:postcode":"95018",
    "sg:province":"CA",
    "wof:name":"San Lorenzo Valley Elementary",
    "wof:placetype":"venue"
},
  "geometry": {"coordinates":[-122.080122,37.061976],"type":"Point"}
}