{
  "type": "Feature",
  "properties": {
    "iso:country":"US",
    "sg:address":"23540 Lyons Ave",
    "sg:city":"Newhall",
    "sg:classifiers":[
        {
            "category":"Home & Garden",
            "subcategory":"Building Materials",
            "type":"Retail Goods"
        }
    ],
    "sg:phone":"+1 805 288 1221",
    "sg:postcode":"91321",
    "sg:province":"CA",
    "sg:tags":[
        "screen",
        "window"
    ],
    "wof:name":"First Choice Screen Embroidery",
    "wof:placetype":"venue"
},
  "geometry": {"coordinates":[-118.546256,34.379298],"type":"Point"}
}