{
  "type": "Feature",
  "properties": {
    "addr:full":"7935 Greenleaf Ave Whittier CA 90602",
    "addr:housenumber":"7935",
    "addr:postcode":"90602",
    "addr:street":"Greenleaf Ave",
    "iso:country":"US",
    "sg:address":"7935 Greenleaf Ave",
    "sg:city":"Whittier",
    "sg:classifiers":[
        {
            "category":"Retail",
            "subcategory":"Repair Shop",
            "type":"Services"
        }
    ],
    "sg:phone":"+1 562 693 5705",
    "sg:postcode":"90602",
    "sg:province":"CA",
    "sg:tags":[
        "repairing",
        "lawn",
        "mower"
    ],
    "wof:name":"Aki's Lawn Mower Shop",
    "wof:placetype":"venue"
},
  "geometry": {"coordinates":[-118.037443,33.971049],"type":"Point"}
}