{
  "type": "Feature",
  "properties": {
    "addr:full":"10323 Lorenzo Dr Los Angeles CA 90064",
    "addr:housenumber":"10323",
    "addr:postcode":"90064",
    "addr:street":"Lorenzo Dr",
    "iso:country":"US",
    "sg:address":"10323 Lorenzo Dr",
    "sg:city":"Los Angeles",
    "sg:classifiers":[
        {
            "category":"Professional",
            "subcategory":"Advertising",
            "type":"Services"
        }
    ],
    "sg:phone":"+1 213 383 6915",
    "sg:postcode":"90064",
    "sg:province":"CA",
    "sg:tags":[
        "counselor"
    ],
    "sg:website":"www.yuguchi.com",
    "wof:name":"Yuguchi Group",
    "wof:placetype":"venue"
},
  "geometry": {"coordinates":[-118.40759,34.040412],"type":"Point"}
}