{
  "type": "Feature",
  "properties": {
    "iso:country":"US",
    "sg:address":"1104 Stone St",
    "sg:city":"Los Angeles",
    "sg:classifiers":[
        {
            "category":"Restaurant",
            "type":"Food & Drink"
        }
    ],
    "sg:phone":"+1 213 384 7696",
    "sg:postcode":"90063",
    "sg:province":"CA",
    "wof:name":"Rincon Taurino",
    "wof:placetype":"venue"
},
  "geometry": {"coordinates":[-118.19367,34.052048],"type":"Point"}
}