{
  "type": "Feature",
  "properties": {
    "addr:full":"334 Shaw Ave Clovis CA 93612",
    "addr:housenumber":"334",
    "addr:postcode":"93612",
    "addr:street":"Shaw Ave",
    "iso:country":"US",
    "sg:address":"334 Shaw Ave",
    "sg:city":"Clovis",
    "sg:classifiers":[
        {
            "category":"Health Services",
            "subcategory":"Chiropractor",
            "type":"Services"
        }
    ],
    "sg:phone":"+1 559 299 2090",
    "sg:postcode":"93612",
    "sg:province":"CA",
    "wof:name":"Knudsen Chiropractic Offices",
    "wof:placetype":"venue"
},
  "geometry": {"coordinates":[-119.70472700000001,36.808425],"type":"Point"}
}