{
  "type": "Feature",
  "properties": {
    "iso:country":"US",
    "sg:address":"6131 Jarvis Ave",
    "sg:city":"Newark",
    "sg:classifiers":[
        {
            "category":"Food & Beverages",
            "subcategory":"Specialty",
            "type":"Retail Goods"
        }
    ],
    "sg:phone":"+1 510 797 5282",
    "sg:postcode":"94560",
    "sg:province":"CA",
    "sg:tags":[
        "tea",
        "coffee"
    ],
    "wof:name":"Newark Java",
    "wof:placetype":"venue"
},
  "geometry": {"coordinates":[-122.050631,37.549009],"type":"Point"}
}