{
  "type": "Feature",
  "properties": {
    "iso:country":"US",
    "sg:address":"175 E Dana St",
    "sg:city":"Mountain View",
    "sg:classifiers":[
        {
            "category":"Organizations",
            "subcategory":"Religious Organization",
            "type":"Services"
        }
    ],
    "sg:phone":"+1 650 964 1591",
    "sg:postcode":"94041",
    "sg:province":"CA",
    "sg:website":"www.mvccc.org/",
    "wof:name":"Mountain View Chinese Christian Church",
    "wof:placetype":"venue"
},
  "geometry": {"coordinates":[-122.06500200000001,37.386501],"type":"Point"}
}