{
  "type": "Feature",
  "properties": {
    "addr:full":"650 Trade Way Turlock CA 95380",
    "addr:housenumber":"650",
    "addr:postcode":"95380",
    "addr:street":"Trade Way",
    "iso:country":"US",
    "sg:address":"650 Trade Way",
    "sg:city":"Turlock",
    "sg:phone":"+1 209 668 1331",
    "sg:postcode":"95380",
    "sg:province":"CA",
    "sg:tags":[
        "tanner"
    ],
    "wof:name":"Golden State Tannery",
    "wof:placetype":"venue"
},
  "geometry": {"coordinates":[-120.881608,37.48543],"type":"Point"}
}