{
  "type": "Feature",
  "properties": {
    "iso:country":"US",
    "sg:address":"1104 N Pacific Ave",
    "sg:city":"Glendale",
    "sg:classifiers":[
        {
            "category":"Wholesale",
            "subcategory":"Stationery",
            "type":"Manufacturing & Wholesale Goods"
        }
    ],
    "sg:phone":"+1 818 247 7660",
    "sg:postcode":"91202",
    "sg:province":"CA",
    "sg:tags":[
        "card"
    ],
    "wof:name":"Baron's Gifts & Cards",
    "wof:placetype":"venue"
},
  "geometry": {"coordinates":[-118.264,34.160999],"type":"Point"}
}