{
  "type": "Feature",
  "properties": {
    "iso:country":"US",
    "sg:address":"24218 Mission Blvd",
    "sg:city":"Hayward",
    "sg:classifiers":[
        {
            "category":"Personal",
            "subcategory":"Barber",
            "type":"Services"
        }
    ],
    "sg:postcode":"94543",
    "sg:province":"CA",
    "wof:name":"Stay Groomed",
    "wof:placetype":"venue"
},
  "geometry": {"coordinates":[-122.07763,37.665039],"type":"Point"}
}