{
  "type": "Feature",
  "properties": {
    "iso:country":"US",
    "sg:address":"590 W Putnam Ave",
    "sg:city":"Porterville",
    "sg:classifiers":[
        {
            "category":"Health Services",
            "subcategory":"Doctor",
            "type":"Services"
        }
    ],
    "sg:phone":"+1 559 783 8943",
    "sg:postcode":"93257",
    "sg:province":"CA",
    "sg:tags":[
        "physician",
        "surgeon"
    ],
    "wof:name":"Mohsen T Thomas MD",
    "wof:placetype":"venue"
},
  "geometry": {"coordinates":[-119.029093,36.069621],"type":"Point"}
}