{
  "type": "Feature",
  "properties": {
    "iso:country":"US",
    "sg:address":"1630 E G St",
    "sg:city":"Ontario",
    "sg:classifiers":[
        {
            "category":"Autos & Motor Vehicles",
            "subcategory":"Automobile Sales",
            "type":"Retail Goods"
        }
    ],
    "sg:phone":"+1 909 821 3904",
    "sg:postcode":"91764",
    "sg:province":"CA",
    "sg:tags":[
        "car",
        "dealer"
    ],
    "wof:name":"Jordan Auto Sale",
    "wof:placetype":"venue"
},
  "geometry": {"coordinates":[-117.617133,34.070639],"type":"Point"}
}