{
  "type": "Feature",
  "properties": {
    "iso:country":"US",
    "sg:address":"15826 Ventura Blvd",
    "sg:city":"Encino",
    "sg:classifiers":[
        {
            "category":"Restaurant",
            "type":"Food & Drink"
        }
    ],
    "sg:phone":"+1 818 783 6713",
    "sg:postcode":"91436",
    "sg:province":"CA",
    "wof:name":"B B's Coffee & Deli",
    "wof:placetype":"venue"
},
  "geometry": {"coordinates":[-118.478882,34.155635],"type":"Point"}
}