{
  "type": "Feature",
  "properties": {
    "addr:full":"1332 4th St Berkeley CA 94710",
    "addr:housenumber":"1332",
    "addr:postcode":"94710",
    "addr:street":"4Th St",
    "iso:country":"US",
    "sg:address":"1332 4th St",
    "sg:city":"Berkeley",
    "sg:classifiers":[
        {
            "category":"Manufacturing",
            "subcategory":"Food",
            "type":"Manufacturing & Wholesale Goods"
        }
    ],
    "sg:phone":"+1 510 526 4294",
    "sg:postcode":"94710",
    "sg:province":"CA",
    "sg:tags":[
        "winery"
    ],
    "wof:name":"Allyance Wine Cellars",
    "wof:placetype":"venue"
},
  "geometry": {"coordinates":[-122.303241,37.877686],"type":"Point"}
}