{
  "type": "Feature",
  "properties": {
    "addr:full":"5652 Mulberry Ridge Dr Camarillo CA 93012",
    "addr:housenumber":"5652",
    "addr:postcode":"93012",
    "addr:street":"Mulberry Ridge Dr",
    "iso:country":"US",
    "sg:address":"5652 Mulberry Ridge Dr",
    "sg:city":"Camarillo",
    "sg:classifiers":[
        {
            "category":"Retail",
            "subcategory":"Laundry & Dry Cleaning",
            "type":"Services"
        }
    ],
    "sg:phone":"+1 805 482 1332",
    "sg:postcode":"93012",
    "sg:province":"CA",
    "sg:tags":[
        "cleaners"
    ],
    "wof:name":"Executive On-Site Drapery",
    "wof:placetype":"venue"
},
  "geometry": {"coordinates":[-118.989614,34.226744],"type":"Point"}
}