{
  "type": "Feature",
  "properties": {
    "iso:country":"US",
    "sg:address":"114 Olinda Dr",
    "sg:city":"Brea",
    "sg:classifiers":[
        {
            "category":"Professional",
            "subcategory":"Computer Services",
            "type":"Services"
        }
    ],
    "sg:phone":"+1 714 579 0500",
    "sg:postcode":"92821",
    "sg:province":"CA",
    "sg:tags":[
        "electronics"
    ],
    "sg:website":"www.celectronics.com",
    "wof:name":"Compatible Electronics",
    "wof:placetype":"venue"
},
  "geometry": {"coordinates":[-117.802355,33.927505],"type":"Point"}
}