{
  "type": "Feature",
  "properties": {
    "iso:country":"US",
    "sg:address":"1348 Market St",
    "sg:city":"Redding",
    "sg:classifiers":[
        {
            "category":"Real Estate",
            "subcategory":"Real Estate Operator",
            "type":"Services"
        },
        {
            "category":"Social Services",
            "type":"Services"
        }
    ],
    "sg:phone":"+1 530 244 2305",
    "sg:postcode":"96001",
    "sg:province":"CA",
    "sg:tags":[
        "organization",
        "apartment",
        "complex",
        "welfare"
    ],
    "wof:name":"Redding Rhf Housing Inc",
    "wof:placetype":"venue"
},
  "geometry": {"coordinates":[-122.391523,40.585786],"type":"Point"}
}