{
  "type": "Feature",
  "properties": {
    "iso:country":"US",
    "sg:address":"917 E Ridgecrest Blvd",
    "sg:city":"Ridgecrest",
    "sg:classifiers":[
        {
            "category":"Wholesale",
            "subcategory":"Machinery & Supplies",
            "type":"Manufacturing & Wholesale Goods"
        }
    ],
    "sg:phone":"+1 760 384 4754",
    "sg:postcode":"93555",
    "sg:province":"CA",
    "sg:tags":[
        "rep",
        "industrial",
        "mobil"
    ],
    "wof:name":"Meinerts Industrial Supplies",
    "wof:placetype":"venue"
},
  "geometry": {"coordinates":[-117.650312,35.622377],"type":"Point"}
}