{
  "type": "Feature",
  "properties": {
    "addr:full":"75 Phelan Ave Ste 2 San Jose CA 95112",
    "addr:housenumber":"75",
    "addr:postcode":"95112",
    "addr:street":"Phelan Ave Ste 2",
    "iso:country":"US",
    "sg:address":"75 Phelan Ave Ste 2",
    "sg:city":"San Jose",
    "sg:classifiers":[
        {
            "category":"Autos & Motor Vehicles",
            "subcategory":"Auto Supplies",
            "type":"Retail Goods"
        },
        {
            "category":"Autos & Motor Vehicles",
            "subcategory":"Motorcycle Sales",
            "type":"Retail Goods"
        },
        {
            "category":"Retail",
            "subcategory":"Auto Repair",
            "type":"Services"
        }
    ],
    "sg:phone":"+1 408 298 6800",
    "sg:postcode":"95112",
    "sg:province":"CA",
    "sg:tags":[
        "part"
    ],
    "sg:website":"www.ramcycles.com",
    "wof:name":"RAM Products Real American Motorcycle Repair & Rental",
    "wof:placetype":"venue"
},
  "geometry": {"coordinates":[-121.867788,37.312102],"type":"Point"}
}