{
  "type": "Feature",
  "properties": {
    "iso:country":"US",
    "sg:address":"11035 Osborne St",
    "sg:city":"Lake View Ter",
    "sg:classifiers":[
        {
            "category":"Recreation",
            "type":"Entertainment"
        },
        {
            "category":"Retail",
            "subcategory":"Animal Services",
            "type":"Services"
        }
    ],
    "sg:phone":"+1 818 896 6967",
    "sg:postcode":"91342",
    "sg:province":"CA",
    "sg:tags":[
        "stable"
    ],
    "wof:name":"California Polo Club",
    "wof:placetype":"venue"
},
  "geometry": {"coordinates":[-118.376623,34.278229],"type":"Point"}
}