{
  "type": "Feature",
  "properties": {
    "iso:country":"US",
    "sg:address":"44726 10th St W",
    "sg:city":"Lancaster",
    "sg:classifiers":[
        {
            "category":"Real Estate",
            "subcategory":"Real Estate Services",
            "type":"Services"
        },
        {
            "category":"Structure",
            "subcategory":"Office Building",
            "type":"Public Place"
        }
    ],
    "sg:phone":"+1 661 949 1444",
    "sg:postcode":"93534",
    "sg:province":"CA",
    "sg:tags":[
        "consultant",
        "park"
    ],
    "sg:website":"http://www.wainwrightrealestate.com",
    "wof:name":"Wainwright Real Estate, Inc",
    "wof:placetype":"venue"
},
  "geometry": {"coordinates":[-118.14807399999999,34.696218],"type":"Point"}
}