{
  "type": "Feature",
  "properties": {
    "addr:full":"9960 Glenoaks Blvd Sun Valley CA 91352",
    "addr:housenumber":"9960",
    "addr:postcode":"91352",
    "addr:street":"Glenoaks Blvd",
    "iso:country":"US",
    "sg:address":"9960 Glenoaks Blvd",
    "sg:city":"Sun Valley",
    "sg:classifiers":[
        {
            "category":"Manufacturing",
            "subcategory":"Apparel",
            "type":"Manufacturing & Wholesale Goods"
        }
    ],
    "sg:phone":"+1 818 767 8090",
    "sg:postcode":"91352",
    "sg:province":"CA",
    "sg:tags":[
        "clothes",
        "accessory"
    ],
    "wof:name":"Agabang USA Inc",
    "wof:placetype":"venue"
},
  "geometry": {"coordinates":[-118.38827999999999,34.250295],"type":"Point"}
}