{
  "type": "Feature",
  "properties": {
    "addr:full":"2855 Hyannis Way Sacramento CA 95827",
    "addr:housenumber":"2855",
    "addr:postcode":"95827",
    "addr:street":"Hyannis Way",
    "iso:country":"US",
    "sg:address":"2855 Hyannis Way",
    "sg:city":"Sacramento",
    "sg:classifiers":[
        {
            "category":"Utilities",
            "type":"Services"
        }
    ],
    "sg:phone":"+1 916 366 1670",
    "sg:postcode":"95827",
    "sg:province":"CA",
    "sg:tags":[
        "sweeping",
        "company"
    ],
    "wof:name":"Baggett Sweeping",
    "wof:placetype":"venue"
},
  "geometry": {"coordinates":[-121.336218,38.576172],"type":"Point"}
}