{
  "type": "Feature",
  "properties": {
    "iso:country":"US",
    "sg:address":"1180 S Beverly Dr",
    "sg:city":"Los Angeles",
    "sg:classifiers":[
        {
            "category":"Professional",
            "subcategory":"Lawyer & Legal Services",
            "type":"Services"
        }
    ],
    "sg:phone":"+1 310 890 7353",
    "sg:postcode":"90035",
    "sg:province":"CA",
    "sg:website":"thegklawfirm.com",
    "wof:name":"GK Law Firm",
    "wof:placetype":"venue"
},
  "geometry": {"coordinates":[-118.395261,34.05572],"type":"Point"}
}