{
  "type": "Feature",
  "properties": {
    "addr:full":"31340 Cll Joya Bonsall CA 92003",
    "addr:postcode":"31340;92003",
    "iso:country":"US",
    "sg:address":"31340 Cll Joya",
    "sg:city":"Bonsall",
    "sg:classifiers":[
        {
            "category":"Farming",
            "subcategory":"Crops",
            "type":"Manufacturing & Wholesale Goods"
        }
    ],
    "sg:phone":"+1 760 749 8086",
    "sg:postcode":"92003",
    "sg:province":"CA",
    "sg:tags":[
        "farm"
    ],
    "wof:name":"Rancho Tuckahoe II",
    "wof:placetype":"venue"
},
  "geometry": {"coordinates":[-117.163256,33.276143],"type":"Point"}
}