{
  "type": "Feature",
  "properties": {
    "iso:country":"US",
    "sg:address":"620 Windham St",
    "sg:city":"Santa Cruz",
    "sg:classifiers":[
        {
            "category":"Professional",
            "type":"Services"
        }
    ],
    "sg:phone":"+1 831 425 0420",
    "sg:postcode":"95062",
    "sg:province":"CA",
    "wof:name":"Kazel Halpern and Robson Ptr",
    "wof:placetype":"venue"
},
  "geometry": {"coordinates":[-122.007608,36.973159],"type":"Point"}
}