{
  "type": "Feature",
  "properties": {
    "iso:country":"US",
    "sg:address":"7860 Girard St",
    "sg:city":"La Jolla",
    "sg:classifiers":[
        {
            "category":"Shopping",
            "subcategory":"Jewelry",
            "type":"Retail Goods"
        }
    ],
    "sg:phone":"+1 858 459 3678",
    "sg:postcode":"92037",
    "sg:province":"CA",
    "wof:name":"Bowers Jewelry",
    "wof:placetype":"venue"
},
  "geometry": {"coordinates":[-117.27441399999999,32.845974],"type":"Point"}
}