{
  "type": "Feature",
  "properties": {
    "addr:full":"29260 Lakeview Ln Highland CA 92346",
    "addr:housenumber":"29260",
    "addr:postcode":"92346",
    "addr:street":"Lakeview Ln",
    "iso:country":"US",
    "sg:address":"29260 Lakeview Ln",
    "sg:city":"Highland",
    "sg:classifiers":[
        {
            "category":"Autos & Motor Vehicles",
            "subcategory":"Automobile Sales",
            "type":"Retail Goods"
        }
    ],
    "sg:phone":"+1 951 906 5636",
    "sg:postcode":"92346",
    "sg:province":"CA",
    "sg:tags":[
        "leasing"
    ],
    "wof:name":"Gar Elite Inc.",
    "wof:placetype":"venue"
},
  "geometry": {"coordinates":[-117.16364900000001,34.254267],"type":"Point"}
}