{
  "type": "Feature",
  "properties": {
    "addr:full":"1153 Glendale Galleria Glendale CA 91210",
    "addr:housenumber":"1153",
    "addr:postcode":"91210",
    "addr:street":"Glendale Galleria",
    "iso:country":"US",
    "sg:address":"1153 Glendale Galleria",
    "sg:city":"Glendale",
    "sg:classifiers":[
        {
            "category":"Coffee & Tea",
            "type":"Food & Drink"
        },
        {
            "category":"Shopping",
            "type":"Retail Goods"
        }
    ],
    "sg:phone":"+1 818 956 1063",
    "sg:postcode":"91210",
    "sg:province":"CA",
    "sg:website":"www.teavana.com/",
    "wof:name":"Teavana",
    "wof:placetype":"venue"
},
  "geometry": {"coordinates":[-118.25939200000001,34.146664],"type":"Point"}
}