{
  "type": "Feature",
  "properties": {
    "iso:country":"US",
    "sg:address":"1911 N Gaffey St",
    "sg:city":"San Pedro",
    "sg:classifiers":[
        {
            "category":"Autos & Motor Vehicles",
            "subcategory":"Automobile Sales",
            "type":"Retail Goods"
        }
    ],
    "sg:phone":"+1 310 514 0305",
    "sg:postcode":"90731",
    "sg:province":"CA",
    "sg:tags":[
        "car",
        "dealer"
    ],
    "wof:name":"Cardinale Auto",
    "wof:placetype":"venue"
},
  "geometry": {"coordinates":[-118.29293699999999,33.760174],"type":"Point"}
}