{
  "type": "Feature",
  "properties": {
    "addr:full":"8375 Entreken Way San Diego CA 92129",
    "addr:housenumber":"8375",
    "addr:postcode":"92129",
    "addr:street":"Entreken Way",
    "iso:country":"US",
    "sg:address":"8375 Entreken Way",
    "sg:city":"San Diego",
    "sg:classifiers":[
        {
            "category":"Education",
            "subcategory":"School",
            "type":"Public Place"
        }
    ],
    "sg:phone":"+1 858 538 5478",
    "sg:postcode":"92129",
    "sg:province":"CA",
    "wof:name":"Mesa Verde Middle School",
    "wof:placetype":"venue"
},
  "geometry": {"coordinates":[-117.144614,32.962722],"type":"Point"}
}