{
  "type": "Feature",
  "properties": {
    "iso:country":"US",
    "sg:address":"2121 Rosecrans Avenue",
    "sg:city":"El Segundo",
    "sg:classifiers":[
        {
            "category":"Banks & Credit Unions",
            "subcategory":"Financial Services",
            "type":"Services"
        }
    ],
    "sg:phone":"+1 310 252 7200",
    "sg:postcode":"90245",
    "sg:province":"CA",
    "sg:tags":[
        "broker",
        "mortgage"
    ],
    "wof:name":"Akt Dba American Capitol Corporation",
    "wof:placetype":"venue"
},
  "geometry": {"coordinates":[-118.387844,33.901978],"type":"Point"}
}