{
  "type": "Feature",
  "properties": {
    "iso:country":"US",
    "sg:address":"1035 Sutter St",
    "sg:city":"Redding",
    "sg:classifiers":[
        {
            "category":"Retail",
            "subcategory":"Auto Repair",
            "type":"Services"
        }
    ],
    "sg:phone":"+1 530 242 0674",
    "sg:postcode":"96001",
    "sg:province":"CA",
    "sg:tags":[
        "truck"
    ],
    "wof:name":"E S May",
    "wof:placetype":"venue"
},
  "geometry": {"coordinates":[-122.384627,40.563427],"type":"Point"}
}