{
  "type": "Feature",
  "properties": {
    "addr:full":"5850 Republic St Riverside CA 92504",
    "addr:housenumber":"5850",
    "addr:postcode":"92504",
    "addr:street":"Republic St",
    "iso:country":"US",
    "sg:address":"5850 Republic St",
    "sg:city":"Riverside",
    "sg:classifiers":[
        {
            "category":"Manufacturing",
            "subcategory":"Tools & Machinery",
            "type":"Manufacturing & Wholesale Goods"
        }
    ],
    "sg:phone":"+1 951 637 5755",
    "sg:postcode":"92504",
    "sg:province":"CA",
    "sg:tags":[
        "machine",
        "repair"
    ],
    "wof:name":"Protech Equipment Service",
    "wof:placetype":"venue"
},
  "geometry": {"coordinates":[-117.438309,33.965055],"type":"Point"}
}