{
  "type": "Feature",
  "properties": {
    "iso:country":"US",
    "sg:address":"369 S Doheny Dr",
    "sg:city":"Beverly Hills",
    "sg:classifiers":[
        {
            "category":"Professional",
            "subcategory":"Lawyer & Legal Services",
            "type":"Services"
        }
    ],
    "sg:phone":"+1 310 275 3520",
    "sg:postcode":"90211",
    "sg:province":"CA",
    "sg:tags":[
        "attorney"
    ],
    "wof:name":"Dina Chernick",
    "wof:placetype":"venue"
},
  "geometry": {"coordinates":[-118.389799,34.061347],"type":"Point"}
}