{
  "type": "Feature",
  "properties": {
    "addr:full":"2099 N Bellflower Blvd Long Beach CA 90815",
    "addr:housenumber":"2099",
    "addr:postcode":"90815",
    "addr:street":"N Bellflower Blvd",
    "iso:country":"US",
    "sg:address":"2099 N Bellflower Blvd",
    "sg:city":"Long Beach",
    "sg:classifiers":[
        {
            "category":"Restaurant",
            "type":"Food & Drink"
        }
    ],
    "sg:phone":"+1 562 985 3053",
    "sg:postcode":"90815",
    "sg:province":"CA",
    "sg:tags":[
        "traditional",
        "american",
        "cafe"
    ],
    "wof:name":"Best Place Cafe",
    "wof:placetype":"venue"
},
  "geometry": {"coordinates":[-118.12599899999999,33.793598],"type":"Point"}
}