{
  "type": "Feature",
  "properties": {
    "iso:country":"US",
    "sg:address":"25422 Trabuco Rd",
    "sg:city":"Lake Forest",
    "sg:classifiers":[
        {
            "category":"Shopping",
            "subcategory":"Used Merchandise",
            "type":"Retail Goods"
        }
    ],
    "sg:phone":"+1 949 588 9035",
    "sg:postcode":"92630",
    "sg:province":"CA",
    "sg:tags":[
        "shop",
        "consignment"
    ],
    "wof:name":"Copitone",
    "wof:placetype":"venue"
},
  "geometry": {"coordinates":[-117.68738500000001,33.648758],"type":"Point"}
}