{
  "type": "Feature",
  "properties": {
    "addr:full":"901 Brunswick St Daly City CA 94014",
    "addr:housenumber":"901",
    "addr:postcode":"94014",
    "addr:street":"Brunswick St",
    "iso:country":"US",
    "sg:address":"901 Brunswick St",
    "sg:city":"Daly City",
    "sg:classifiers":[
        {
            "category":"Recreation",
            "subcategory":"Playground",
            "type":"Entertainment"
        }
    ],
    "sg:phone":"+1 650 991 8018",
    "sg:postcode":"94014",
    "sg:province":"CA",
    "sg:website":"www.ci.daly-city.ca.us/city_serv...",
    "wof:name":"Lincoln Park",
    "wof:placetype":"venue"
},
  "geometry": {"coordinates":[-122.452315,37.707106],"type":"Point"}
}