{
  "type": "Feature",
  "properties": {
    "iso:country":"US",
    "sg:address":"930 Dena Way",
    "sg:city":"Santa Barbara",
    "sg:classifiers":[
        {
            "category":"Building & Trades",
            "subcategory":"Plumbing",
            "type":"Services"
        }
    ],
    "sg:phone":"+1 805 964 6811",
    "sg:postcode":"93111",
    "sg:province":"CA",
    "sg:tags":[
        "plumbing",
        "contractor"
    ],
    "wof:name":"F Lindblom Inc",
    "wof:placetype":"venue"
},
  "geometry": {"coordinates":[-119.813073,34.457006],"type":"Point"}
}