{
  "type": "Feature",
  "properties": {
    "iso:country":"US",
    "sg:address":"1370 Mission St",
    "sg:city":"San Francisco",
    "sg:classifiers":[
        {
            "category":"Professional",
            "subcategory":"Management & Consulting",
            "type":"Services"
        }
    ],
    "sg:phone":"+1 415 865 5400",
    "sg:postcode":"94103",
    "sg:province":"CA",
    "sg:tags":[
        "consultant",
        "educational"
    ],
    "wof:name":"SMART",
    "wof:placetype":"venue"
},
  "geometry": {"coordinates":[-122.415902,37.775384],"type":"Point"}
}