{
  "type": "Feature",
  "properties": {
    "iso:country":"US",
    "sg:address":"2250 W Beverly Blvd",
    "sg:city":"Montebello",
    "sg:classifiers":[
        {
            "category":"Health Services",
            "subcategory":"Health Practitioner",
            "type":"Services"
        }
    ],
    "sg:phone":"+1 323 725 0194",
    "sg:postcode":"90640",
    "sg:province":"CA",
    "sg:tags":[
        "therapy",
        "physical"
    ],
    "wof:name":"Bay Rehabilitation",
    "wof:placetype":"venue"
},
  "geometry": {"coordinates":[-118.125,34.021301],"type":"Point"}
}