{
  "type": "Feature",
  "properties": {
    "addr:full":"6930 S Land Park Dr Sacramento CA 95831",
    "addr:housenumber":"6930",
    "addr:postcode":"95831",
    "addr:street":"S Land Park Dr",
    "iso:country":"US",
    "sg:address":"6930 S Land Park Dr",
    "sg:city":"Sacramento",
    "sg:classifiers":[
        {
            "category":"Building & Trades",
            "subcategory":"Cleaning & Sanitation",
            "type":"Services"
        }
    ],
    "sg:phone":"+1 916 429 0520",
    "sg:postcode":"95831",
    "sg:province":"CA",
    "sg:tags":[
        "cleaning-industrial",
        "contractor"
    ],
    "wof:name":"Housecleaners....And More , Ll",
    "wof:placetype":"venue"
},
  "geometry": {"coordinates":[-121.510289,38.499875],"type":"Point"}
}