{
  "type": "Feature",
  "properties": {
    "iso:country":"US",
    "sg:address":"132 9th St # 100",
    "sg:city":"Oakland",
    "sg:classifiers":[
        {
            "category":"Organizations",
            "subcategory":"Labor Organization",
            "type":"Services"
        }
    ],
    "sg:phone":"+1 510 763 1555",
    "sg:postcode":"94607",
    "sg:province":"CA",
    "wof:name":"Amalgamated Transit Union",
    "wof:placetype":"venue"
},
  "geometry": {"coordinates":[-122.265789,37.797907],"type":"Point"}
}