{
  "type": "Feature",
  "properties": {
    "iso:country":"US",
    "sg:address":"5334 Las Positas Cir",
    "sg:city":"Stockton",
    "sg:classifiers":[
        {
            "category":"Professional",
            "subcategory":"Accounting & Tax Preparation",
            "type":"Services"
        }
    ],
    "sg:phone":"+1 209 476 1269",
    "sg:postcode":"95212",
    "sg:province":"CA",
    "sg:tags":[
        "return",
        "preparation-business"
    ],
    "wof:name":"Chandra's Accounting & Income Tax S",
    "wof:placetype":"venue"
},
  "geometry": {"coordinates":[-121.24651,38.054002],"type":"Point"}
}