{
  "type": "Feature",
  "properties": {
    "addr:full":"3727 Carol St Pinole CA 94564",
    "addr:housenumber":"3727",
    "addr:postcode":"94564",
    "addr:street":"Carol St",
    "iso:country":"US",
    "sg:address":"3727 Carol St",
    "sg:city":"Pinole",
    "sg:classifiers":[
        {
            "category":"Arts & Performance",
            "subcategory":"Theater",
            "type":"Entertainment"
        }
    ],
    "sg:phone":"+1 510 243 1122",
    "sg:postcode":"94564",
    "sg:province":"CA",
    "sg:tags":[
        "musician"
    ],
    "sg:website":"www.folkloric.net",
    "wof:name":"A Folkloric Production",
    "wof:placetype":"venue"
},
  "geometry": {"coordinates":[-122.26473300000001,37.982278],"type":"Point"}
}