{
  "type": "Feature",
  "properties": {
    "iso:country":"US",
    "sg:address":"2946 Honolulu Ave",
    "sg:city":"La Crescenta",
    "sg:classifiers":[
        {
            "category":"Professional",
            "subcategory":"Art Services",
            "type":"Services"
        },
        {
            "category":"Communications",
            "type":"Services"
        }
    ],
    "sg:phone":"+1 818 957 4488",
    "sg:postcode":"91214",
    "sg:province":"CA",
    "sg:tags":[
        "web",
        "graphic",
        "design"
    ],
    "sg:website":"www.caspianservices.net/",
    "wof:name":"Caspian Services, Inc.",
    "wof:placetype":"venue"
},
  "geometry": {"coordinates":[-118.24319,34.213449],"type":"Point"}
}