{
  "type": "Feature",
  "properties": {
    "iso:country":"US",
    "sg:address":"1592 Union St",
    "sg:city":"San Francisco",
    "sg:classifiers":[
        {
            "category":"Retail",
            "subcategory":"Repair Shop",
            "type":"Services"
        }
    ],
    "sg:phone":"+1 415 775 3466",
    "sg:postcode":"94123",
    "sg:province":"CA",
    "sg:tags":[
        "lock",
        "locksmith"
    ],
    "wof:name":"Locksmith",
    "wof:placetype":"venue"
},
  "geometry": {"coordinates":[-122.424418,37.798613],"type":"Point"}
}