{
  "type": "Feature",
  "properties": {
    "addr:full":"624 Delta Way Watsonville CA 95076",
    "addr:housenumber":"624",
    "addr:postcode":"95076",
    "addr:street":"Delta Way",
    "iso:country":"US",
    "sg:address":"624 Delta Way",
    "sg:city":"Watsonville",
    "sg:classifiers":[
        {
            "category":"Wholesale",
            "subcategory":"Hardware",
            "type":"Manufacturing & Wholesale Goods"
        }
    ],
    "sg:phone":"+1 831 724 2727",
    "sg:postcode":"95076",
    "sg:province":"CA",
    "sg:tags":[
        "heater"
    ],
    "wof:name":"Heater Specialist",
    "wof:placetype":"venue"
},
  "geometry": {"coordinates":[-121.740995,36.917349],"type":"Point"}
}