{
  "type": "Feature",
  "properties": {
    "iso:country":"US",
    "sg:address":"3 Corporate Plaza Dr Ste 230",
    "sg:city":"Newport Beach",
    "sg:classifiers":[
        {
            "category":"Professional",
            "subcategory":"Lawyer & Legal Services",
            "type":"Services"
        }
    ],
    "sg:phone":"+1 949 718 3920",
    "sg:postcode":"92660",
    "sg:province":"CA",
    "wof:name":"Gagliardino Vivian Law Office Of",
    "wof:placetype":"venue"
},
  "geometry": {"coordinates":[-117.877009,33.607654],"type":"Point"}
}