{
  "type": "Feature",
  "properties": {
    "iso:country":"US",
    "sg:address":"1504 B Fillmore Street Above Aarang Korean Restaurant",
    "sg:city":"San Francisco",
    "sg:classifiers":[
        {
            "category":"Bars & Pubs",
            "subcategory":"Lounge",
            "type":"Food & Drink"
        }
    ],
    "sg:phone":"+1 415 922 9636",
    "sg:postcode":"94101",
    "sg:province":"CA",
    "sg:tags":[
        "karaoke"
    ],
    "wof:name":"Safety Zone Karaoke Box",
    "wof:placetype":"venue"
},
  "geometry": {"coordinates":[-122.432785,37.783443],"type":"Point"}
}