{
  "type": "Feature",
  "properties": {
    "iso:country":"US",
    "sg:address":"3275 Peachwillow Ln",
    "sg:city":"Walnut Creek",
    "sg:classifiers":[
        {
            "category":"Education",
            "subcategory":"School",
            "type":"Public Place"
        }
    ],
    "sg:phone":"+1 925 939 5700",
    "sg:postcode":"94598",
    "sg:province":"CA",
    "sg:tags":[
        "elementary"
    ],
    "wof:name":"Valle Verde Elementary School",
    "wof:placetype":"venue"
},
  "geometry": {"coordinates":[-122.014668,37.934337],"type":"Point"}
}