{
  "type": "Feature",
  "properties": {
    "addr:full":"1200 Sonoma Ave Santa Rosa CA 95405",
    "addr:housenumber":"1200",
    "addr:postcode":"95405",
    "addr:street":"Sonoma Ave",
    "iso:country":"US",
    "sg:address":"1200 Sonoma Ave",
    "sg:city":"Santa Rosa",
    "sg:classifiers":[
        {
            "category":"Health Services",
            "subcategory":"Doctor",
            "type":"Services"
        }
    ],
    "sg:phone":"+1 707 545 2545",
    "sg:postcode":"95405",
    "sg:province":"CA",
    "sg:tags":[
        "physician",
        "surgeon"
    ],
    "wof:name":"Pediatric Associates",
    "wof:placetype":"venue"
},
  "geometry": {"coordinates":[-122.699124,38.44126],"type":"Point"}
}