{
  "type": "Feature",
  "properties": {
    "addr:full":"261 Pollard Ct Windsor CA 95492",
    "addr:housenumber":"261",
    "addr:postcode":"95492",
    "addr:street":"Pollard Ct",
    "iso:country":"US",
    "sg:address":"261 Pollard Ct",
    "sg:city":"Windsor",
    "sg:classifiers":[
        {
            "category":"Building & Trades",
            "subcategory":"Construction",
            "type":"Services"
        }
    ],
    "sg:phone":"+1 707 837 9007",
    "sg:postcode":"95492",
    "sg:province":"CA",
    "sg:tags":[
        "tile-contractors"
    ],
    "wof:name":"Stonetastic Tile",
    "wof:placetype":"venue"
},
  "geometry": {"coordinates":[-122.81966300000001,38.559702],"type":"Point"}
}