{
  "type": "Feature",
  "properties": {
    "iso:country":"US",
    "sg:address":"2008 India St",
    "sg:city":"San Diego",
    "sg:classifiers":[
        {
            "category":"Recreation",
            "type":"Entertainment"
        }
    ],
    "sg:phone":"+1 619 804 7208",
    "sg:postcode":"92101",
    "sg:province":"CA",
    "sg:tags":[
        "psychic",
        "medium"
    ],
    "wof:name":"Psychic Crstal Healer",
    "wof:placetype":"venue"
},
  "geometry": {"coordinates":[-117.169472,32.726282],"type":"Point"}
}