{
  "type": "Feature",
  "properties": {
    "iso:country":"US",
    "sg:address":"15520 Strebor Dr",
    "sg:city":"Bakersfield",
    "sg:classifiers":[
        {
            "category":"Social Services",
            "type":"Services"
        }
    ],
    "sg:phone":"+1 661 588 4102",
    "sg:postcode":"93314",
    "sg:province":"CA",
    "sg:tags":[
        "guidance",
        "child"
    ],
    "wof:name":"Child Training Resources",
    "wof:placetype":"venue"
},
  "geometry": {"coordinates":[-119.174737,35.364436],"type":"Point"}
}