{
  "type": "Feature",
  "properties": {
    "iso:country":"US",
    "sg:address":"2181 Greenwich Street",
    "sg:city":"San Francisco",
    "sg:classifiers":[
        {
            "category":"Professional",
            "type":"Services"
        }
    ],
    "sg:postcode":"94123",
    "sg:province":"CA",
    "sg:tags":[
        "planning",
        "event"
    ],
    "sg:website":"www.sfcitydish.com",
    "wof:name":"The City Dish",
    "wof:placetype":"venue"
},
  "geometry": {"coordinates":[-122.43553900000001,37.799034],"type":"Point"}
}