{
  "type": "Feature",
  "properties": {
    "addr:full":"27800 Medical Center Rd Ste 208 Mission Viejo CA 92691",
    "addr:housenumber":"27800",
    "addr:postcode":"92691",
    "addr:street":"Medical Center Rd Ste 208",
    "iso:country":"US",
    "sg:address":"27800 Medical Center Rd Ste 208",
    "sg:city":"Mission Viejo",
    "sg:classifiers":[
        {
            "category":"Health Services",
            "subcategory":"Dentist",
            "type":"Services"
        }
    ],
    "sg:phone":"+1 949 364 0223",
    "sg:postcode":"92691",
    "sg:province":"CA",
    "sg:tags":[
        "periodontist",
        "orthodontist",
        "cosmetic"
    ],
    "sg:website":"www.exceldentalonline.com",
    "wof:name":"Excel Dental",
    "wof:placetype":"venue"
},
  "geometry": {"coordinates":[-117.66395900000001,33.56123],"type":"Point"}
}