{
  "type": "Feature",
  "properties": {
    "addr:full":"80 Huntington St Huntington Beach CA 92648",
    "addr:housenumber":"80",
    "addr:postcode":"92648",
    "addr:street":"Huntington St",
    "iso:country":"US",
    "sg:address":"80 Huntington St",
    "sg:city":"Huntington Beach",
    "sg:classifiers":[
        {
            "category":"Building & Trades",
            "subcategory":"Construction",
            "type":"Services"
        }
    ],
    "sg:phone":"+1 714 375 5350",
    "sg:postcode":"92648",
    "sg:province":"CA",
    "sg:tags":[
        "resurfacing",
        "laying",
        "refinishing",
        "floor"
    ],
    "wof:name":"Beach Flooring",
    "wof:placetype":"venue"
},
  "geometry": {"coordinates":[-117.99493,33.65761],"type":"Point"}
}