{
  "type": "Feature",
  "properties": {
    "addr:full":"5920 Balboa Ave San Diego CA 92117",
    "addr:housenumber":"5920",
    "addr:postcode":"92117",
    "addr:street":"Balboa Ave",
    "iso:country":"US",
    "sg:address":"5920 Balboa Ave",
    "sg:city":"San Diego",
    "sg:classifiers":[
        {
            "category":"Fast Food",
            "type":"Food & Drink"
        }
    ],
    "sg:phone":"+1 858 569 5928",
    "sg:postcode":"92117",
    "sg:province":"CA",
    "sg:website":"www.mcdonalds.com",
    "wof:name":"McDonald's",
    "wof:placetype":"venue"
},
  "geometry": {"coordinates":[-117.177987,32.820482],"type":"Point"}
}