{
  "type": "Feature",
  "properties": {
    "addr:full":"1125 Ocean Ave San Francisco CA 94112",
    "addr:housenumber":"1125",
    "addr:postcode":"94112",
    "addr:street":"Ocean Ave",
    "iso:country":"US",
    "sg:address":"1125 Ocean Ave",
    "sg:city":"San Francisco",
    "sg:classifiers":[
        {
            "category":"Coffee & Tea",
            "type":"Food & Drink"
        },
        {
            "category":"Food & Beverages",
            "subcategory":"Bakery",
            "type":"Retail Goods"
        }
    ],
    "sg:phone":"+1 415 333 3771",
    "sg:postcode":"94112",
    "sg:province":"CA",
    "sg:tags":[
        "sandwich"
    ],
    "wof:name":"Java Jitters",
    "wof:placetype":"venue"
},
  "geometry": {"coordinates":[-122.454711,37.723322],"type":"Point"}
}