{
  "type": "Feature",
  "properties": {
    "iso:country":"US",
    "sg:address":"3212 April Ct",
    "sg:city":"Modesto",
    "sg:classifiers":[
        {
            "category":"Building & Trades",
            "subcategory":"Cleaning & Sanitation",
            "type":"Services"
        }
    ],
    "sg:phone":"+1 209 548 9846",
    "sg:postcode":"95354",
    "sg:province":"CA",
    "sg:tags":[
        "janitor"
    ],
    "wof:name":"A Better Cleaning Svc",
    "wof:placetype":"venue"
},
  "geometry": {"coordinates":[-120.933588,37.640467],"type":"Point"}
}