{
  "type": "Feature",
  "properties": {
    "addr:full":"317 W Inyokern Rd Ridgecrest CA 93555",
    "addr:housenumber":"317",
    "addr:postcode":"93555",
    "addr:street":"W Inyokern Rd",
    "iso:country":"US",
    "sg:address":"317 W Inyokern Rd",
    "sg:city":"Ridgecrest",
    "sg:classifiers":[
        {
            "category":"Autos & Motor Vehicles",
            "subcategory":"Auto Supplies",
            "type":"Retail Goods"
        }
    ],
    "sg:phone":"+1 760 499 6453",
    "sg:postcode":"93555",
    "sg:province":"CA",
    "sg:tags":[
        "tire"
    ],
    "sg:website":"www.aandltire.com",
    "wof:name":"A & L Tire Co",
    "wof:placetype":"venue"
},
  "geometry": {"coordinates":[-117.67671199999999,35.651529],"type":"Point"}
}