{
  "type": "Feature",
  "properties": {
    "iso:country":"US",
    "sg:address":"13918 Saticoy St",
    "sg:city":"Panorama City",
    "sg:classifiers":[
        {
            "category":"Building & Trades",
            "subcategory":"Construction",
            "type":"Services"
        }
    ],
    "sg:phone":"+1 818 718 9780",
    "sg:postcode":"91402",
    "sg:province":"CA",
    "sg:tags":[
        "air",
        "heating",
        "conditioning/hvac"
    ],
    "wof:name":"RA Air Conditioning",
    "wof:placetype":"venue"
},
  "geometry": {"coordinates":[-118.436256,34.210066],"type":"Point"}
}