{
  "type": "Feature",
  "properties": {
    "addr:full":"328 Stowell Ave Sunnyvale CA 94085",
    "addr:housenumber":"328",
    "addr:postcode":"94085",
    "addr:street":"Stowell Ave",
    "iso:country":"US",
    "sg:address":"328 Stowell Ave",
    "sg:city":"Sunnyvale",
    "sg:classifiers":[
        {
            "category":"Professional",
            "subcategory":"Computer Services",
            "type":"Services"
        }
    ],
    "sg:phone":"+1 408 733 1429",
    "sg:postcode":"94085",
    "sg:province":"CA",
    "sg:tags":[
        "internet"
    ],
    "wof:name":"Virtually There",
    "wof:placetype":"venue"
},
  "geometry": {"coordinates":[-122.02710999999999,37.38783],"type":"Point"}
}