{
  "type": "Feature",
  "properties": {
    "addr:full":"278 E Alisal St Salinas CA 93901",
    "addr:housenumber":"278",
    "addr:postcode":"93901",
    "addr:street":"E Alisal St",
    "iso:country":"US",
    "sg:address":"278 E Alisal St",
    "sg:city":"Salinas",
    "sg:classifiers":[
        {
            "category":"Autos & Motor Vehicles",
            "subcategory":"Auto Supplies",
            "type":"Retail Goods"
        }
    ],
    "sg:phone":"+1 831 772 9560",
    "sg:postcode":"93901",
    "sg:province":"CA",
    "sg:tags":[
        "automobile",
        "stereo",
        "radio"
    ],
    "wof:name":"Audio Express Inc",
    "wof:placetype":"venue"
},
  "geometry": {"coordinates":[-121.64706200000001,36.674726],"type":"Point"}
}