{
  "type": "Feature",
  "properties": {
    "iso:country":"US",
    "sg:address":"41941 Rd 222",
    "sg:city":"Oakhurst",
    "sg:classifiers":[
        {
            "category":"Retail",
            "subcategory":"Repair Shop",
            "type":"Services"
        }
    ],
    "sg:phone":"+1 559 683 3232",
    "sg:postcode":"93644",
    "sg:province":"CA",
    "wof:name":"Van Aman Stereo & TV Repair",
    "wof:placetype":"venue"
},
  "geometry": {"coordinates":[-119.609152,37.358241],"type":"Point"}
}