{
  "type": "Feature",
  "properties": {
    "addr:full":"749 N Main St Orange CA 92868",
    "addr:housenumber":"749",
    "addr:postcode":"92868",
    "addr:street":"N Main St",
    "iso:country":"US",
    "sg:address":"749 N Main St",
    "sg:city":"Orange",
    "sg:classifiers":[
        {
            "category":"Manufacturing",
            "subcategory":"Rubber & Plastics",
            "type":"Manufacturing & Wholesale Goods"
        }
    ],
    "sg:phone":"+1 714 639 3326",
    "sg:postcode":"92868",
    "sg:province":"CA",
    "sg:website":"www.decotechgroup.com",
    "wof:name":"Deco Tech Systems",
    "wof:placetype":"venue"
},
  "geometry": {"coordinates":[-117.86647499999999,33.798686],"type":"Point"}
}