{
  "type": "Feature",
  "properties": {
    "addr:full":"2610 Sierra Meadows Dr Rocklin CA 95677",
    "addr:housenumber":"2610",
    "addr:postcode":"95677",
    "addr:street":"Sierra Meadows Dr",
    "iso:country":"US",
    "sg:address":"2610 Sierra Meadows Dr",
    "sg:city":"Rocklin",
    "sg:classifiers":[
        {
            "category":"Organizations",
            "subcategory":"Religious Organization",
            "type":"Services"
        }
    ],
    "sg:phone":"+1 916 632 2613",
    "sg:postcode":"95677",
    "sg:province":"CA",
    "wof:name":"Corporation of President of Th",
    "wof:placetype":"venue"
},
  "geometry": {"coordinates":[-121.22239500000001,38.791503],"type":"Point"}
}