{
  "type": "Feature",
  "properties": {
    "addr:full":"1895 W Elm Ave Coalinga CA 93210",
    "addr:housenumber":"1895",
    "addr:postcode":"93210",
    "addr:street":"W Elm Ave",
    "iso:country":"US",
    "sg:address":"1895 W Elm Ave",
    "sg:city":"Coalinga",
    "sg:classifiers":[
        {
            "category":"Retail",
            "subcategory":"Auto Rental",
            "type":"Services"
        }
    ],
    "sg:phone":"+1 559 935 3680",
    "sg:postcode":"93210",
    "sg:province":"CA",
    "sg:tags":[
        "renting",
        "truck",
        "leasing"
    ],
    "wof:name":"Valley Produce & Trucking Inc",
    "wof:placetype":"venue"
},
  "geometry": {"coordinates":[-120.373322,36.123704],"type":"Point"}
}