{
  "type": "Feature",
  "properties": {
    "addr:full":"1859 Greenwich St San Francisco CA 94123",
    "addr:housenumber":"1859",
    "addr:postcode":"94123",
    "addr:street":"Greenwich St",
    "iso:country":"US",
    "sg:address":"1859 Greenwich St",
    "sg:city":"San Francisco",
    "sg:classifiers":[
        {
            "category":"Professional",
            "type":"Services"
        }
    ],
    "sg:phone":"+1 415 922 2226",
    "sg:postcode":"94123",
    "sg:province":"CA",
    "wof:name":"Gkl Tecon Inc",
    "wof:placetype":"venue"
},
  "geometry": {"coordinates":[-122.430154,37.799629],"type":"Point"}
}