{
  "type": "Feature",
  "properties": {
    "iso:country":"US",
    "sg:address":"2148 Larkin Street",
    "sg:city":"San Francisco",
    "sg:classifiers":[
        {
            "category":"Real Estate",
            "subcategory":"Architect",
            "type":"Services"
        }
    ],
    "sg:phone":"+1 415 474 6723",
    "sg:postcode":"94109",
    "sg:province":"CA",
    "wof:name":"Ogrydziak Prillinger Architects",
    "wof:placetype":"venue"
},
  "geometry": {"coordinates":[-122.41999800000001,37.797798],"type":"Point"}
}