{
  "type": "Feature",
  "properties": {
    "addr:full":"326 Encinitas Blvd Encinitas CA 92024",
    "addr:housenumber":"326",
    "addr:postcode":"92024",
    "addr:street":"Encinitas Blvd",
    "iso:country":"US",
    "sg:address":"326 Encinitas Blvd",
    "sg:city":"Encinitas",
    "sg:classifiers":[
        {
            "category":"Insurance",
            "subcategory":"Insurance Agent",
            "type":"Services"
        }
    ],
    "sg:phone":"+1 760 753 7255",
    "sg:postcode":"92024",
    "sg:province":"CA",
    "wof:name":"Behrens-Taylor & Assoc",
    "wof:placetype":"venue"
},
  "geometry": {"coordinates":[-117.284786,33.048264],"type":"Point"}
}