{
  "type": "Feature",
  "properties": {
    "addr:full":"2000 Mowry Ave Fremont CA 94538",
    "addr:housenumber":"2000",
    "addr:postcode":"94538",
    "addr:street":"Mowry Ave",
    "iso:country":"US",
    "sg:address":"2000 Mowry Ave",
    "sg:city":"Fremont",
    "sg:classifiers":[
        {
            "category":"Health Services",
            "subcategory":"Hospital",
            "type":"Services"
        }
    ],
    "sg:phone":"+1 510 794 4671",
    "sg:postcode":"94538",
    "sg:province":"CA",
    "sg:tags":[
        "general"
    ],
    "wof:name":"Sports Medicine Center At Wash",
    "wof:placetype":"venue"
},
  "geometry": {"coordinates":[-121.981652,37.557002],"type":"Point"}
}