{
  "type": "Feature",
  "properties": {
    "addr:full":"535 Las Animas Ave Gilroy CA 95020",
    "addr:housenumber":"535",
    "addr:postcode":"95020",
    "addr:street":"Las Animas Ave",
    "iso:country":"US",
    "sg:address":"535 Las Animas Ave",
    "sg:city":"Gilroy",
    "sg:classifiers":[
        {
            "category":"Professional",
            "type":"Services"
        }
    ],
    "sg:phone":"+1 408 293 8418",
    "sg:postcode":"95020",
    "sg:province":"CA",
    "wof:name":"Leblanc",
    "wof:placetype":"venue"
},
  "geometry": {"coordinates":[-121.574428,37.031496],"type":"Point"}
}