{
  "type": "Feature",
  "properties": {
    "iso:country":"US",
    "sg:address":"245 2nd St",
    "sg:city":"Oakland",
    "sg:classifiers":[
        {
            "category":"Real Estate",
            "subcategory":"Real Estate Services",
            "type":"Services"
        }
    ],
    "sg:phone":"+1 510 238 8222",
    "sg:postcode":"94607",
    "sg:province":"CA",
    "sg:tags":[
        "management",
        "property"
    ],
    "wof:name":"CAC Real Estate Mgt",
    "wof:placetype":"venue"
},
  "geometry": {"coordinates":[-122.271556,37.794034],"type":"Point"}
}