{
  "type": "Feature",
  "properties": {
    "iso:country":"US",
    "sg:address":"320 Wilshire Blvd",
    "sg:city":"Santa Monica",
    "sg:classifiers":[
        {
            "category":"Professional",
            "subcategory":"Accounting & Tax Preparation",
            "type":"Services"
        }
    ],
    "sg:phone":"+1 310 451 8871",
    "sg:postcode":"90401",
    "sg:province":"CA",
    "sg:tags":[
        "accountant"
    ],
    "wof:name":"Lopez & Jackson",
    "wof:placetype":"venue"
},
  "geometry": {"coordinates":[-118.498879,34.018513],"type":"Point"}
}