{
  "type": "Feature",
  "properties": {
    "addr:full":"1001 E 17th St Santa Ana CA 92701",
    "addr:housenumber":"1001",
    "addr:postcode":"92701",
    "addr:street":"E 17Th St",
    "iso:country":"US",
    "sg:address":"1001 E 17th St",
    "sg:city":"Santa Ana",
    "sg:classifiers":[
        {
            "category":"Restaurant",
            "type":"Food & Drink"
        }
    ],
    "sg:menulink":"http://www.allmenus.com/ca/anaheim-santa-ana-garden-grove/35564-ihop/menu/",
    "sg:phone":"+1 714 953 7515",
    "sg:postcode":"92701",
    "sg:province":"CA",
    "sg:tags":[
        "sandwich",
        "salad",
        "burger",
        "soup",
        "american",
        "steakhouse",
        "wrap"
    ],
    "wof:name":"IHOP",
    "wof:placetype":"venue"
},
  "geometry": {"coordinates":[-117.857083,33.760027],"type":"Point"}
}