{
  "type": "Feature",
  "properties": {
    "iso:country":"US",
    "sg:address":"14501 Ave 7",
    "sg:city":"Madera",
    "sg:classifiers":[
        {
            "category":"Farming",
            "subcategory":"Crops",
            "type":"Manufacturing & Wholesale Goods"
        }
    ],
    "sg:phone":"+1 559 673 4073",
    "sg:postcode":"93637",
    "sg:province":"CA",
    "sg:tags":[
        "grove",
        "nut",
        "tree"
    ],
    "wof:name":"Chester and Theresa Andrew",
    "wof:placetype":"venue"
},
  "geometry": {"coordinates":[-120.282258,36.851024],"type":"Point"}
}