{
  "type": "Feature",
  "properties": {
    "addr:full":"2465 E 23rd Street Los Angeles CA 90058",
    "addr:housenumber":"2465",
    "addr:postcode":"90058",
    "addr:street":"E 23Rd Street",
    "iso:country":"US",
    "sg:address":"2465 E 23rd Street",
    "sg:city":"Los Angeles",
    "sg:classifiers":[
        {
            "category":"Shopping",
            "subcategory":"Clothing, Apparel, & Fashions",
            "type":"Retail Goods"
        }
    ],
    "sg:phone":"+1 323 587 0007",
    "sg:postcode":"90058",
    "sg:province":"CA",
    "sg:tags":[
        "accessory",
        "clothing",
        "women's"
    ],
    "wof:name":"Ambiance USA",
    "wof:placetype":"venue"
},
  "geometry": {"coordinates":[-118.230048,34.017254],"type":"Point"}
}