{
  "type": "Feature",
  "properties": {
    "iso:country":"US",
    "sg:address":"900 Atlantic St",
    "sg:city":"Roseville",
    "sg:classifiers":[
        {
            "category":"Retail",
            "subcategory":"Auto Repair",
            "type":"Services"
        }
    ],
    "sg:phone":"+1 916 782 5511",
    "sg:postcode":"95678",
    "sg:province":"CA",
    "sg:tags":[
        "repairing",
        "automobile"
    ],
    "wof:name":"Atlantic Auto Repair",
    "wof:placetype":"venue"
},
  "geometry": {"coordinates":[-121.26702,38.758058],"type":"Point"}
}