{
  "type": "Feature",
  "properties": {
    "addr:full":"7400 Redwood Blvd Ste 101 Novato CA 94945",
    "addr:housenumber":"7400",
    "addr:postcode":"94945",
    "addr:street":"Redwood Blvd Ste 101",
    "iso:country":"US",
    "sg:address":"7400 Redwood Blvd Ste 101",
    "sg:city":"Novato",
    "sg:classifiers":[
        {
            "category":"Building & Trades",
            "subcategory":"Electrical",
            "type":"Services"
        }
    ],
    "sg:phone":"+1 415 897 1105",
    "sg:postcode":"94945",
    "sg:province":"CA",
    "sg:tags":[
        "electrician"
    ],
    "wof:name":"Electrical Design Center",
    "wof:placetype":"venue"
},
  "geometry": {"coordinates":[-122.569453,38.108937],"type":"Point"}
}