{
  "type": "Feature",
  "properties": {
    "addr:full":"466 Primero Ct Cotati CA 94931",
    "addr:housenumber":"466",
    "addr:postcode":"94931",
    "addr:street":"Primero Ct",
    "iso:country":"US",
    "sg:address":"466 Primero Ct",
    "sg:city":"Cotati",
    "sg:classifiers":[
        {
            "category":"Manufacturing",
            "subcategory":"Signs",
            "type":"Manufacturing & Wholesale Goods"
        }
    ],
    "sg:phone":"+1 707 795 3929",
    "sg:postcode":"94931",
    "sg:province":"CA",
    "wof:name":"Bayside Signs",
    "wof:placetype":"venue"
},
  "geometry": {"coordinates":[-122.715729,38.342101],"type":"Point"}
}