{
  "type": "Feature",
  "properties": {
    "iso:country":"US",
    "sg:address":"25349 Wayne Mills Pl",
    "sg:city":"Valencia",
    "sg:classifiers":[
        {
            "category":"Utilities",
            "subcategory":"Mobile Phone",
            "type":"Services"
        },
        {
            "category":"Coffee & Tea",
            "type":"Food & Drink"
        }
    ],
    "sg:phone":"+1 661 260 0844",
    "sg:postcode":"91355",
    "sg:province":"CA",
    "sg:tags":[
        "shop",
        "restaurant",
        "espresso",
        "hotspot",
        "wi-fi"
    ],
    "sg:website":"http://www.starbuckscoffee.com",
    "wof:name":"Starbucks Coffee",
    "wof:placetype":"venue"
},
  "geometry": {"coordinates":[-118.579016,34.423002],"type":"Point"}
}