{
  "type": "Feature",
  "properties": {
    "iso:country":"US",
    "sg:address":"208 S Beverly Dr",
    "sg:city":"Beverly Hills",
    "sg:classifiers":[
        {
            "category":"Professional",
            "subcategory":"Business Services",
            "type":"Services"
        }
    ],
    "sg:phone":"+1 310 550 5533",
    "sg:postcode":"90212",
    "sg:province":"CA",
    "wof:name":"Elite Business Svc",
    "wof:placetype":"venue"
},
  "geometry": {"coordinates":[-118.39899800000001,34.062441],"type":"Point"}
}