{
  "type": "Feature",
  "properties": {
    "iso:country":"US",
    "sg:address":"5030 Campus Drive",
    "sg:city":"Newport Beach",
    "sg:classifiers":[
        {
            "category":"Professional",
            "subcategory":"Lawyer & Legal Services",
            "type":"Services"
        }
    ],
    "sg:phone":"+1 949 863 9682",
    "sg:postcode":"92660",
    "sg:province":"CA",
    "wof:name":"Law Offices of Brewer & Cadzow",
    "wof:placetype":"venue"
},
  "geometry": {"coordinates":[-117.857027,33.667868],"type":"Point"}
}