{
  "type": "Feature",
  "properties": {
    "addr:full":"1513 Robertson Rd Modesto CA 95351",
    "addr:housenumber":"1513",
    "addr:postcode":"ca 95351",
    "addr:street":"Robertson Rd",
    "iso:country":"US",
    "sg:address":"1513 Robertson Rd",
    "sg:city":"Modesto",
    "sg:classifiers":[
        {
            "category":"Real Estate",
            "subcategory":"Real Estate Operator",
            "type":"Services"
        }
    ],
    "sg:phone":"+1 209 526 4627",
    "sg:postcode":"95351",
    "sg:province":"CA",
    "sg:tags":[
        "apartment"
    ],
    "wof:name":"El Casa Verde Apartments",
    "wof:placetype":"venue"
},
  "geometry": {"coordinates":[-121.01193000000001,37.613332],"type":"Point"}
}