{
  "type": "Feature",
  "properties": {
    "iso:country":"US",
    "sg:address":"450 10th St",
    "sg:city":"San Francisco",
    "sg:classifiers":[
        {
            "category":"Health Services",
            "subcategory":"Optometrist",
            "type":"Services"
        }
    ],
    "sg:phone":"+1 415 437 0136",
    "sg:postcode":"94103",
    "sg:province":"CA",
    "wof:name":"Stephen Woo, OD",
    "wof:placetype":"venue"
},
  "geometry": {"coordinates":[-122.411106,37.770488],"type":"Point"}
}