{
  "type": "Feature",
  "properties": {
    "iso:country":"US",
    "sg:address":"16311 Ventura Blvd",
    "sg:city":"Encino",
    "sg:classifiers":[
        {
            "category":"Banks & Credit Unions",
            "subcategory":"Bank",
            "type":"Services"
        }
    ],
    "sg:phone":"+1 818 386 1500",
    "sg:postcode":"91436",
    "sg:province":"CA",
    "sg:tags":[
        "national",
        "commercial"
    ],
    "wof:name":"H S B C Bank USA",
    "wof:placetype":"venue"
},
  "geometry": {"coordinates":[-118.489954,34.157308],"type":"Point"}
}