{
  "type": "Feature",
  "properties": {
    "addr:full":"1531 E Woodbury Rd Pasadena CA 91104",
    "addr:housenumber":"1531",
    "addr:postcode":"91104",
    "addr:street":"E Woodbury Rd",
    "iso:country":"US",
    "sg:address":"1531 E Woodbury Rd",
    "sg:city":"Pasadena",
    "sg:classifiers":[
        {
            "category":"Real Estate",
            "subcategory":"Real Estate Operator",
            "type":"Services"
        }
    ],
    "sg:phone":"+1 626 791 7647",
    "sg:postcode":"91104",
    "sg:province":"CA",
    "sg:tags":[
        "building",
        "nonresidential"
    ],
    "wof:name":"Baseball Reliquary Inc",
    "wof:placetype":"venue"
},
  "geometry": {"coordinates":[-118.120532,34.177252],"type":"Point"}
}