{
  "type": "Feature",
  "properties": {
    "addr:full":"2020 E Route 66 Glendora CA 91740",
    "addr:housenumber":"2020",
    "addr:postcode":"91740",
    "addr:street":"E Route 66",
    "iso:country":"US",
    "sg:address":"2020 E Route 66",
    "sg:city":"Glendora",
    "sg:phone":"+1 626 335 6605",
    "sg:postcode":"91740",
    "sg:province":"CA",
    "wof:name":"Decor Water Fountains",
    "wof:placetype":"venue"
},
  "geometry": {"coordinates":[-117.82622499999999,34.127984],"type":"Point"}
}