{
  "type": "Feature",
  "properties": {
    "addr:full":"2126 Mad River Rd Arcata CA 95521",
    "addr:housenumber":"2126",
    "addr:postcode":"95521",
    "addr:street":"Mad River Rd",
    "iso:country":"US",
    "sg:address":"2126 Mad River Rd",
    "sg:city":"Arcata",
    "sg:classifiers":[
        {
            "category":"Farming",
            "subcategory":"Dairy Farm",
            "type":"Manufacturing & Wholesale Goods"
        },
        {
            "category":"Farming",
            "subcategory":"Farm",
            "type":"Manufacturing & Wholesale Goods"
        }
    ],
    "sg:phone":"+1 707 822 0140",
    "sg:postcode":"95521",
    "sg:province":"CA",
    "wof:name":"Nicholson Dairy",
    "wof:placetype":"venue"
},
  "geometry": {"coordinates":[-124.105779,40.900899],"type":"Point"}
}