{
  "type": "Feature",
  "properties": {
    "iso:country":"US",
    "sg:address":"2300 Westborough Blvd",
    "sg:city":"South San Francisco",
    "sg:classifiers":[
        {
            "category":"Autos & Motor Vehicles",
            "subcategory":"Fuel & Gas Station",
            "type":"Retail Goods"
        },
        {
            "category":"Government",
            "subcategory":"Office",
            "type":"Public Place"
        }
    ],
    "sg:phone":"+1 650 952 4447",
    "sg:postcode":"94080",
    "sg:province":"CA",
    "sg:tags":[
        "smog",
        "check"
    ],
    "wof:name":"Westborough Arco",
    "wof:placetype":"venue"
},
  "geometry": {"coordinates":[-122.453003,37.643299],"type":"Point"}
}