{
  "type": "Feature",
  "properties": {
    "iso:country":"US",
    "sg:address":"21 Gladstone",
    "sg:city":"Irvine",
    "sg:classifiers":[
        {
            "category":"Professional",
            "subcategory":"Management & Consulting",
            "type":"Services"
        }
    ],
    "sg:phone":"+1 949 552 9663",
    "sg:postcode":"92606",
    "sg:province":"CA",
    "sg:tags":[
        "insurance"
    ],
    "wof:name":"Mod Audit",
    "wof:placetype":"venue"
},
  "geometry": {"coordinates":[-117.798078,33.700287],"type":"Point"}
}