{
  "type": "Feature",
  "properties": {
    "addr:full":"1744 Park Ave San Jose CA 95126",
    "addr:housenumber":"1744",
    "addr:postcode":"95126",
    "addr:street":"Park Ave",
    "iso:country":"US",
    "sg:address":"1744 Park Ave",
    "sg:city":"San Jose",
    "sg:classifiers":[
        {
            "category":"Personal",
            "subcategory":"Beauty Salon",
            "type":"Services"
        }
    ],
    "sg:phone":"+1 408 294 1592",
    "sg:postcode":"95126",
    "sg:province":"CA",
    "wof:name":"Park Avenue Salon",
    "wof:placetype":"venue"
},
  "geometry": {"coordinates":[-121.924102,37.334072],"type":"Point"}
}