{
  "type": "Feature",
  "properties": {
    "iso:country":"US",
    "sg:address":"20685 Sigal Dr",
    "sg:city":"Saratoga",
    "sg:classifiers":[
        {
            "category":"Professional",
            "subcategory":"Business Services",
            "type":"Services"
        }
    ],
    "sg:phone":"+1 408 867 2015",
    "sg:postcode":"95070",
    "sg:province":"CA",
    "sg:tags":[
        "development",
        "product",
        "designers-industrial",
        "marketing",
        "commercial",
        "design"
    ],
    "wof:name":"David W Dolloff",
    "wof:placetype":"venue"
},
  "geometry": {"coordinates":[-122.035639,37.246615],"type":"Point"}
}