{
  "type": "Feature",
  "properties": {
    "addr:full":"1924 Fremont Blvd Seaside CA 93955",
    "addr:housenumber":"1924",
    "addr:postcode":"93955",
    "addr:street":"Fremont Blvd",
    "iso:country":"US",
    "sg:address":"1924 Fremont Blvd",
    "sg:city":"Seaside",
    "sg:classifiers":[
        {
            "category":"Shopping",
            "subcategory":"Used Merchandise",
            "type":"Retail Goods"
        }
    ],
    "sg:phone":"+1 831 899 3928",
    "sg:postcode":"93955",
    "sg:province":"CA",
    "wof:name":"Jenny Thrift Shop",
    "wof:placetype":"venue"
},
  "geometry": {"coordinates":[-121.841223,36.617355],"type":"Point"}
}