{
  "type": "Feature",
  "properties": {
    "iso:country":"US",
    "sg:address":"#4 Camp Evers Ln.",
    "sg:city":"Scotts Valley",
    "sg:classifiers":[
        {
            "category":"Building & Trades",
            "subcategory":"Construction",
            "type":"Services"
        }
    ],
    "sg:phone":"+1 831 566 3213",
    "sg:postcode":"95060",
    "sg:province":"CA",
    "sg:tags":[
        "contractor"
    ],
    "sg:website":"www.servi-crete.com",
    "wof:name":"Servicrete",
    "wof:placetype":"venue"
},
  "geometry": {"coordinates":[-122.02416100000001,37.043985],"type":"Point"}
}