{
  "type": "Feature",
  "properties": {
    "iso:country":"US",
    "sg:address":"2632 San Miguel Dr",
    "sg:city":"Newport Beach",
    "sg:classifiers":[
        {
            "category":"Restaurant",
            "type":"Food & Drink"
        }
    ],
    "sg:phone":"+1 949 720 0980",
    "sg:postcode":"92660",
    "sg:province":"CA",
    "sg:tags":[
        "mexican"
    ],
    "sg:website":"www.tacorosa.com",
    "wof:name":"Taco Rosa",
    "wof:placetype":"venue"
},
  "geometry": {"coordinates":[-117.849951,33.626669],"type":"Point"}
}