{
  "type": "Feature",
  "properties": {
    "addr:full":"2300 Manzanita Ln Big Bear City CA 92314",
    "addr:housenumber":"2300",
    "addr:postcode":"92314",
    "addr:street":"Manzanita Ln",
    "iso:country":"US",
    "sg:address":"2300 Manzanita Ln",
    "sg:city":"Big Bear City",
    "sg:classifiers":[
        {
            "category":"Professional",
            "subcategory":"Secretarial Services",
            "type":"Services"
        }
    ],
    "sg:phone":"+1 909 585 3374",
    "sg:postcode":"92314",
    "sg:province":"CA",
    "sg:tags":[
        "reporting",
        "court"
    ],
    "wof:name":"Mountain Secretarial Relief",
    "wof:placetype":"venue"
},
  "geometry": {"coordinates":[-116.79869100000001,34.24001],"type":"Point"}
}