{
  "type": "Feature",
  "properties": {
    "addr:full":"6 Fig Leaf Ct Sacramento CA 95838",
    "addr:housenumber":"6",
    "addr:postcode":"95838",
    "addr:street":"Fig Leaf Ct",
    "iso:country":"US",
    "sg:address":"6 Fig Leaf Ct",
    "sg:city":"Sacramento",
    "sg:classifiers":[
        {
            "category":"Insurance",
            "subcategory":"Hazard Insurance",
            "type":"Services"
        }
    ],
    "sg:phone":"+1 916 929 4649",
    "sg:postcode":"95838",
    "sg:province":"CA",
    "sg:tags":[
        "employee",
        "benefit",
        "compensation",
        "plan"
    ],
    "wof:name":"Federal Benefit Solutions",
    "wof:placetype":"venue"
},
  "geometry": {"coordinates":[-121.459644,38.659156],"type":"Point"}
}