{
  "type": "Feature",
  "properties": {
    "addr:full":"119 Main St Half Moon Bay CA 94019",
    "addr:housenumber":"119",
    "addr:postcode":"94019",
    "addr:street":"Main St",
    "iso:country":"US",
    "sg:address":"119 Main St",
    "sg:city":"Half Moon Bay",
    "sg:classifiers":[
        {
            "category":"Home & Garden",
            "subcategory":"Building Materials",
            "type":"Retail Goods"
        }
    ],
    "sg:phone":"+1 650 726 6696",
    "sg:postcode":"94019",
    "sg:province":"CA",
    "wof:name":"Half Moon Bay Building & Grdn",
    "wof:placetype":"venue"
},
  "geometry": {"coordinates":[-122.431522,37.469443],"type":"Point"}
}