{
  "type": "Feature",
  "properties": {
    "iso:country":"US",
    "sg:address":"542 Rockcreek Way",
    "sg:city":"Pleasant Hill",
    "sg:classifiers":[
        {
            "category":"Personal",
            "type":"Services"
        }
    ],
    "sg:phone":"+1 925 288 1686",
    "sg:postcode":"94523",
    "sg:province":"CA",
    "wof:name":"Fortune Counsel Co",
    "wof:placetype":"venue"
},
  "geometry": {"coordinates":[-122.055108,37.960605],"type":"Point"}
}