{
  "type": "Feature",
  "properties": {
    "iso:country":"US",
    "sg:address":"650 W Adams Blvd",
    "sg:city":"Los Angeles",
    "sg:classifiers":[
        {
            "category":"Organizations",
            "subcategory":"Non-profit Organization",
            "type":"Services"
        },
        {
            "category":"Social Services",
            "subcategory":"Child Care",
            "type":"Services"
        }
    ],
    "sg:phone":"+1 323 299 8998",
    "sg:postcode":"90007",
    "sg:province":"CA",
    "sg:tags":[
        "center",
        "for",
        "food",
        "an",
        "subsidy",
        "providing"
    ],
    "wof:name":"Crystal Stairs Inc",
    "wof:placetype":"venue"
},
  "geometry": {"coordinates":[-118.277168,34.028467],"type":"Point"}
}