{
  "type": "Feature",
  "properties": {
    "iso:country":"US",
    "sg:address":"246 Sand Hill Cir",
    "sg:city":"Menlo Park",
    "sg:classifiers":[
        {
            "category":"Building & Trades",
            "subcategory":"Construction",
            "type":"Services"
        }
    ],
    "sg:phone":"+1 650 561 9234",
    "sg:postcode":"94025",
    "sg:province":"CA",
    "sg:tags":[
        "general",
        "contractor"
    ],
    "wof:name":"J C Construction",
    "wof:placetype":"venue"
},
  "geometry": {"coordinates":[-122.22285100000001,37.423035],"type":"Point"}
}