{
  "type": "Feature",
  "properties": {
    "addr:full":"14660 W D St Kerman CA 93630",
    "addr:housenumber":"14660",
    "addr:postcode":"93630",
    "addr:street":"W D St",
    "iso:country":"US",
    "sg:address":"14660 W D St",
    "sg:city":"Kerman",
    "sg:classifiers":[
        {
            "category":"Government",
            "subcategory":"Office",
            "type":"Public Place"
        }
    ],
    "sg:phone":"+1 559 846 9855",
    "sg:postcode":"93630",
    "sg:province":"CA",
    "sg:tags":[
        "village"
    ],
    "wof:name":"Kerman Community Food Bank",
    "wof:placetype":"venue"
},
  "geometry": {"coordinates":[-120.05572100000001,36.723672],"type":"Point"}
}