{
  "type": "Feature",
  "properties": {
    "addr:full":"23020 Lake Forest Dr Laguna Hills CA 92653",
    "addr:housenumber":"23020",
    "addr:postcode":"92653",
    "addr:street":"Lake Forest Dr",
    "iso:country":"US",
    "sg:address":"23020 Lake Forest Dr",
    "sg:city":"Laguna Hills",
    "sg:classifiers":[
        {
            "category":"Deli",
            "type":"Food & Drink"
        },
        {
            "category":"Bakery",
            "type":"Food & Drink"
        }
    ],
    "sg:phone":"+1 949 586 4718",
    "sg:postcode":"92653",
    "sg:province":"CA",
    "wof:name":"Solomon's Bakery & Deli",
    "wof:placetype":"venue"
},
  "geometry": {"coordinates":[-117.725247,33.628502],"type":"Point"}
}