{
  "type": "Feature",
  "properties": {
    "iso:country":"US",
    "sg:address":"712 W 23rd St",
    "sg:city":"Merced",
    "sg:classifiers":[
        {
            "category":"Social Services",
            "type":"Services"
        }
    ],
    "sg:phone":"+1 209 384 8557",
    "sg:postcode":"95340",
    "sg:province":"CA",
    "sg:tags":[
        "organization",
        "welfare"
    ],
    "wof:name":"Child Advocate-Merced County",
    "wof:placetype":"venue"
},
  "geometry": {"coordinates":[-120.484315,37.308958],"type":"Point"}
}