{
  "type": "Feature",
  "properties": {
    "iso:country":"US",
    "sg:address":"1589 W 9th St Ste H",
    "sg:city":"Upland",
    "sg:classifiers":[
        {
            "category":"Home & Garden",
            "subcategory":"Hardware",
            "type":"Retail Goods"
        }
    ],
    "sg:phone":"+1 909 291 8411",
    "sg:postcode":"91786",
    "sg:province":"CA",
    "sg:tags":[
        "fire",
        "sprinklers-residential",
        "industrial",
        "commercial",
        "automatic"
    ],
    "wof:name":"Western States Fire Protection Company",
    "wof:placetype":"venue"
},
  "geometry": {"coordinates":[-117.680762,34.095971],"type":"Point"}
}