{
  "type": "Feature",
  "properties": {
    "addr:full":"7356 Trade St San Diego CA 92121",
    "addr:housenumber":"7356",
    "addr:postcode":"92121",
    "addr:street":"Trade St",
    "iso:country":"US",
    "sg:address":"7356 Trade St",
    "sg:city":"San Diego",
    "sg:classifiers":[
        {
            "category":"Building & Trades",
            "subcategory":"Construction",
            "type":"Services"
        }
    ],
    "sg:phone":"+1 858 577 2930",
    "sg:postcode":"92121",
    "sg:province":"CA",
    "sg:tags":[
        "roofing",
        "contractor"
    ],
    "wof:name":"Patriot Roofing",
    "wof:placetype":"venue"
},
  "geometry": {"coordinates":[-117.163838,32.888749],"type":"Point"}
}