{
  "type": "Feature",
  "properties": {
    "addr:full":"5420 W Sunset Blvd Los Angeles CA 90027",
    "addr:housenumber":"5420",
    "addr:postcode":"90027",
    "addr:street":"W Sunset Blvd",
    "iso:country":"US",
    "sg:address":"5420 W Sunset Blvd",
    "sg:city":"Los Angeles",
    "sg:classifiers":[
        {
            "category":"Insurance",
            "subcategory":"Hazard Insurance",
            "type":"Services"
        }
    ],
    "sg:phone":"+1 323 460 5100",
    "sg:postcode":"90027",
    "sg:province":"CA",
    "wof:name":"Hollywood's Auto Insurance Services",
    "wof:placetype":"venue"
},
  "geometry": {"coordinates":[-118.308094,34.097266],"type":"Point"}
}