{
  "type": "Feature",
  "properties": {
    "addr:full":"895 E Fremont Ave Ste 101 Sunnyvale CA 94087",
    "addr:housenumber":"895",
    "addr:postcode":"94087",
    "addr:street":"E Fremont Ave Ste 101",
    "iso:country":"US",
    "sg:address":"895 E Fremont Ave Ste 101",
    "sg:city":"Sunnyvale",
    "sg:classifiers":[
        {
            "category":"Health Services",
            "subcategory":"Dentist",
            "type":"Services"
        }
    ],
    "sg:phone":"+1 408 732 0220",
    "sg:postcode":"94087",
    "sg:province":"CA",
    "sg:website":"www.mysmilestyle.com",
    "wof:name":"Sunnyvale Smile Style",
    "wof:placetype":"venue"
},
  "geometry": {"coordinates":[-122.014692,37.352511],"type":"Point"}
}