{
  "type": "Feature",
  "properties": {
    "addr:full":"15250 Dittmar Dr Whittier CA 90603",
    "addr:housenumber":"15250",
    "addr:postcode":"90603",
    "addr:street":"Dittmar Dr",
    "iso:country":"US",
    "sg:address":"15250 Dittmar Dr",
    "sg:city":"Whittier",
    "sg:classifiers":[
        {
            "category":"Real Estate",
            "subcategory":"Real Estate Agent",
            "type":"Services"
        }
    ],
    "sg:phone":"+1 562 696 7432",
    "sg:postcode":"90603",
    "sg:province":"CA",
    "wof:name":"Calabretta Properties",
    "wof:placetype":"venue"
},
  "geometry": {"coordinates":[-118.003843,33.939579],"type":"Point"}
}