{
  "type": "Feature",
  "properties": {
    "iso:country":"US",
    "sg:address":"13242 Grass Valley Ave",
    "sg:city":"Grass Valley",
    "sg:classifiers":[
        {
            "category":"Building & Trades",
            "subcategory":"Construction",
            "type":"Services"
        }
    ],
    "sg:phone":"+1 530 272 9660",
    "sg:postcode":"95945",
    "sg:province":"CA",
    "sg:tags":[
        "downspouts",
        "gutter"
    ],
    "sg:website":"www.guttertopper.com",
    "wof:name":"Gutter Topper",
    "wof:placetype":"venue"
},
  "geometry": {"coordinates":[-121.01260600000001,39.220333],"type":"Point"}
}