{
  "type": "Feature",
  "properties": {
    "iso:country":"US",
    "sg:address":"7171 Ronson Rd",
    "sg:city":"San Diego",
    "sg:classifiers":[
        {
            "category":"Manufacturing",
            "subcategory":"Tools & Machinery",
            "type":"Manufacturing & Wholesale Goods"
        }
    ],
    "sg:phone":"+1 858 279 5221",
    "sg:postcode":"92111",
    "sg:province":"CA",
    "sg:tags":[
        "industrial",
        "mfg"
    ],
    "wof:name":"R E Lee Welding Inc",
    "wof:placetype":"venue"
},
  "geometry": {"coordinates":[-117.15915200000001,32.828914],"type":"Point"}
}