{
  "type": "Feature",
  "properties": {
    "addr:full":"30755 Auld Rd Murrieta CA 92563",
    "addr:housenumber":"30755",
    "addr:postcode":"92563",
    "addr:street":"Auld Rd",
    "iso:country":"US",
    "sg:address":"30755 Auld Rd",
    "sg:city":"Murrieta",
    "sg:classifiers":[
        {
            "category":"Government",
            "subcategory":"Police Station",
            "type":"Public Place"
        }
    ],
    "sg:phone":"+1 951 696 3131",
    "sg:postcode":"92563",
    "sg:province":"CA",
    "sg:tags":[
        "sheriff"
    ],
    "wof:name":"Sheriff's Dept-Court Svc Div",
    "wof:placetype":"venue"
},
  "geometry": {"coordinates":[-117.125658,33.583401],"type":"Point"}
}