{
  "type": "Feature",
  "properties": {
    "addr:full":"12409 Central Ave Chino CA 91710",
    "addr:housenumber":"12409",
    "addr:postcode":"91710",
    "addr:street":"Central Ave",
    "iso:country":"US",
    "sg:address":"12409 Central Ave",
    "sg:city":"Chino",
    "sg:classifiers":[
        {
            "category":"Travel",
            "subcategory":"Travel Agent",
            "type":"Entertainment"
        }
    ],
    "sg:phone":"+1 909 923 0222",
    "sg:postcode":"91710",
    "sg:province":"CA",
    "sg:tags":[
        "agency"
    ],
    "wof:name":"Select Travel & Cruises",
    "wof:placetype":"venue"
},
  "geometry": {"coordinates":[-117.689308,34.026487],"type":"Point"}
}