{
  "type": "Feature",
  "properties": {
    "iso:country":"US",
    "sg:address":"1546 N Western Ave",
    "sg:city":"Los Angeles",
    "sg:classifiers":[
        {
            "category":"Shopping",
            "subcategory":"Clothing, Apparel, & Fashions",
            "type":"Retail Goods"
        }
    ],
    "sg:phone":"+1 323 461 8744",
    "sg:postcode":"90027",
    "sg:province":"CA",
    "sg:tags":[
        "shop",
        "bridal"
    ],
    "wof:name":"Suenos De Novia Bridal Shop",
    "wof:placetype":"venue"
},
  "geometry": {"coordinates":[-118.309178,34.100445],"type":"Point"}
}