{
  "type": "Feature",
  "properties": {
    "iso:country":"US",
    "sg:address":"15711 Condon Avenue A-7",
    "sg:city":"Lawndale",
    "sg:classifiers":[
        {
            "category":"Shopping",
            "subcategory":"Pets & Pet Supplies",
            "type":"Retail Goods"
        },
        {
            "category":"Retail",
            "subcategory":"Pet Boarding",
            "type":"Services"
        }
    ],
    "sg:phone":"+1 310 322 3649",
    "sg:postcode":"90260",
    "sg:province":"CA",
    "sg:tags":[
        "training",
        "boarding/pet",
        "sitting"
    ],
    "sg:website":"www.k9klass.com",
    "wof:name":"K9 Klass",
    "wof:placetype":"venue"
},
  "geometry": {"coordinates":[-118.359476,33.88857],"type":"Point"}
}