{
  "type": "Feature",
  "properties": {
    "addr:full":"6351 Corte del Abeto Carlsbad CA 92011",
    "addr:housenumber":"6351",
    "addr:postcode":"92011",
    "addr:street":"Corte Del Abeto",
    "iso:country":"US",
    "sg:address":"6351 Corte del Abeto",
    "sg:city":"Carlsbad",
    "sg:classifiers":[
        {
            "category":"Wholesale",
            "subcategory":"Durable Goods & Equipment",
            "type":"Manufacturing & Wholesale Goods"
        }
    ],
    "sg:phone":"+1 760 579 0393",
    "sg:postcode":"92011",
    "sg:province":"CA",
    "sg:tags":[
        "laboratory",
        "biological",
        "supply"
    ],
    "wof:name":"Globozymes",
    "wof:placetype":"venue"
},
  "geometry": {"coordinates":[-117.277709,33.120253],"type":"Point"}
}