{
  "type": "Feature",
  "properties": {
    "addr:full":"7314 Hollywood Blvd West Hollywood CA 90046",
    "addr:housenumber":"7314",
    "addr:postcode":"90046",
    "addr:street":"Hollywood Blvd",
    "iso:country":"US",
    "sg:address":"7314 Hollywood Blvd",
    "sg:city":"West Hollywood",
    "sg:classifiers":[
        {
            "category":"Shopping",
            "subcategory":"Tobacco",
            "type":"Retail Goods"
        }
    ],
    "sg:phone":"+1 323 851 2101",
    "sg:postcode":"90046",
    "sg:province":"CA",
    "sg:tags":[
        "cigarette",
        "cigar",
        "dealer"
    ],
    "wof:name":"W Tobacco Shop",
    "wof:placetype":"venue"
},
  "geometry": {"coordinates":[-118.349434,34.10155],"type":"Point"}
}