{
  "type": "Feature",
  "properties": {
    "iso:country":"US",
    "sg:address":"27462 Portola Parkway",
    "sg:city":"Foothill Ranch",
    "sg:classifiers":[
        {
            "category":"Health Services",
            "subcategory":"Doctor",
            "type":"Services"
        }
    ],
    "sg:phone":"+1 949 727 9099",
    "sg:postcode":"92610",
    "sg:province":"CA",
    "sg:website":"www.hootandaneshmandmd.com",
    "wof:name":"Hootan Daneshmand MD",
    "wof:placetype":"venue"
},
  "geometry": {"coordinates":[-117.665176,33.685135],"type":"Point"}
}