{
  "type": "Feature",
  "properties": {
    "addr:full":"2295 W Cleveland Ave Madera CA 93637",
    "addr:housenumber":"2295",
    "addr:postcode":"93637",
    "addr:street":"W Cleveland Ave",
    "iso:country":"US",
    "sg:address":"2295 W Cleveland Ave",
    "sg:city":"Madera",
    "sg:classifiers":[
        {
            "category":"Restaurant",
            "type":"Food & Drink"
        }
    ],
    "sg:phone":"+1 559 662 1768",
    "sg:postcode":"93637",
    "sg:province":"CA",
    "wof:name":"Fatellos",
    "wof:placetype":"venue"
},
  "geometry": {"coordinates":[-120.084361,36.974681],"type":"Point"}
}