{
  "type": "Feature",
  "properties": {
    "iso:country":"US",
    "sg:address":"1407 N El Dorado St",
    "sg:city":"Stockton",
    "sg:classifiers":[
        {
            "category":"Manufacturing",
            "subcategory":"Glass & Minerals",
            "type":"Manufacturing & Wholesale Goods"
        }
    ],
    "sg:phone":"+1 209 948 5313",
    "sg:postcode":"95202",
    "sg:province":"CA",
    "sg:tags":[
        "leaded-commercial",
        "glass-stained",
        "leaded",
        "stained"
    ],
    "wof:name":"Ram Studios",
    "wof:placetype":"venue"
},
  "geometry": {"coordinates":[-121.29356900000001,37.966573],"type":"Point"}
}