{
  "type": "Feature",
  "properties": {
    "iso:country":"US",
    "sg:address":"68615 Perez Rd",
    "sg:city":"Cathedral City",
    "sg:classifiers":[
        {
            "category":"Organizations",
            "subcategory":"Non-profit Organization",
            "type":"Services"
        }
    ],
    "sg:phone":"+1 760 328 3663",
    "sg:postcode":"92234",
    "sg:province":"CA",
    "sg:website":"www.findfoodbank.com",
    "wof:name":"FIND Inc",
    "wof:placetype":"venue"
},
  "geometry": {"coordinates":[-116.466486,33.784807],"type":"Point"}
}