{
  "type": "Feature",
  "properties": {
    "addr:full":"2900 Routier Rd Sacramento CA 95827",
    "addr:housenumber":"2900",
    "addr:postcode":"95827",
    "addr:street":"Routier Rd",
    "iso:country":"US",
    "sg:address":"2900 Routier Rd",
    "sg:city":"Sacramento",
    "sg:classifiers":[
        {
            "category":"Home & Garden",
            "subcategory":"Building Materials",
            "type":"Retail Goods"
        }
    ],
    "sg:phone":"+1 916 363 4333",
    "sg:postcode":"95827",
    "sg:province":"CA",
    "sg:tags":[
        "doors-closers",
        "check"
    ],
    "wof:name":"Mirror Man",
    "wof:placetype":"venue"
},
  "geometry": {"coordinates":[-121.318687,38.581009],"type":"Point"}
}