{
  "type": "Feature",
  "properties": {
    "addr:full":"4918 N Harbor Dr San Diego CA 92106",
    "addr:housenumber":"4918",
    "addr:postcode":"92106",
    "addr:street":"N Harbor Dr",
    "iso:country":"US",
    "sg:address":"4918 N Harbor Dr",
    "sg:city":"San Diego",
    "sg:classifiers":[
        {
            "category":"Professional",
            "subcategory":"Management & Consulting",
            "type":"Services"
        }
    ],
    "sg:phone":"+1 619 523 4859",
    "sg:postcode":"92106",
    "sg:province":"CA",
    "sg:tags":[
        "consultant",
        "safety"
    ],
    "wof:name":"Quantum Risk Management",
    "wof:placetype":"venue"
},
  "geometry": {"coordinates":[-117.223862,32.72549],"type":"Point"}
}