{
  "type": "Feature",
  "properties": {
    "addr:full":"96 W Foothill Blvd Upland CA 91786",
    "addr:housenumber":"96",
    "addr:postcode":"91786",
    "addr:street":"W Foothill Blvd",
    "iso:country":"US",
    "sg:address":"96 W Foothill Blvd",
    "sg:city":"Upland",
    "sg:classifiers":[
        {
            "category":"Health Services",
            "subcategory":"Doctor",
            "type":"Services"
        }
    ],
    "sg:phone":"+1 909 920 3735",
    "sg:postcode":"91786",
    "sg:province":"CA",
    "sg:tags":[
        "dentist"
    ],
    "wof:name":"Doctor Cruz Dental Office",
    "wof:placetype":"venue"
},
  "geometry": {"coordinates":[-117.65395700000001,34.106924],"type":"Point"}
}