{
  "type": "Feature",
  "properties": {
    "iso:country":"US",
    "sg:address":"1613 W Riggin Ave",
    "sg:city":"Visalia",
    "sg:classifiers":[
        {
            "category":"Building & Trades",
            "subcategory":"Landscaping Services",
            "type":"Services"
        }
    ],
    "sg:phone":"+1 559 635 0898",
    "sg:postcode":"93291",
    "sg:province":"CA",
    "wof:name":"J & S Gardening",
    "wof:placetype":"venue"
},
  "geometry": {"coordinates":[-119.308947,36.356343],"type":"Point"}
}