{
  "type": "Feature",
  "properties": {
    "addr:full":"3200 E South St Long Beach CA 90805",
    "addr:housenumber":"3200 e",
    "addr:postcode":"90805",
    "addr:street":"South St",
    "iso:country":"US",
    "sg:address":"3200 E South St",
    "sg:city":"Long Beach",
    "sg:classifiers":[
        {
            "category":"Manufacturing",
            "subcategory":"Watercraft",
            "type":"Manufacturing & Wholesale Goods"
        }
    ],
    "sg:phone":"+1 562 412 6301",
    "sg:postcode":"90805",
    "sg:province":"CA",
    "wof:name":"Janes Calamity Boat Works",
    "wof:placetype":"venue"
},
  "geometry": {"coordinates":[-118.157099,33.860183],"type":"Point"}
}