{
  "type": "Feature",
  "properties": {
    "addr:full":"221 Water St Petaluma CA 94952",
    "addr:housenumber":"221",
    "addr:postcode":"94952",
    "addr:street":"Water St",
    "iso:country":"US",
    "sg:address":"221 Water St",
    "sg:city":"Petaluma",
    "sg:classifiers":[
        {
            "category":"Recreation",
            "type":"Entertainment"
        },
        {
            "category":"Organizations",
            "subcategory":"Community Association",
            "type":"Services"
        }
    ],
    "sg:phone":"+1 707 769 9999",
    "sg:postcode":"94952",
    "sg:province":"CA",
    "sg:tags":[
        "club",
        "membership"
    ],
    "wof:name":"Alamo Club of Sonoma County",
    "wof:placetype":"venue"
},
  "geometry": {"coordinates":[-122.640714,38.236247],"type":"Point"}
}