{
  "type": "Feature",
  "properties": {
    "addr:full":"1898 Tulip Ave Hayward CA 94545",
    "addr:housenumber":"1898",
    "addr:postcode":"94545",
    "addr:street":"Tulip Ave",
    "iso:country":"US",
    "sg:address":"1898 Tulip Ave",
    "sg:city":"Hayward",
    "sg:classifiers":[
        {
            "category":"Freight",
            "type":"Transportation"
        }
    ],
    "sg:phone":"+1 510 783 0564",
    "sg:postcode":"94545",
    "sg:province":"CA",
    "sg:tags":[
        "operator",
        "local",
        "trucking"
    ],
    "wof:name":"D&B Delivery Inc",
    "wof:placetype":"venue"
},
  "geometry": {"coordinates":[-122.079773,37.623694],"type":"Point"}
}