{
  "type": "Feature",
  "properties": {
    "addr:full":"2949 Randolph Ave Suite C Costa Mesa CA 92626",
    "addr:housenumber":"2949",
    "addr:postcode":"92626",
    "addr:street":"Randolph Ave Suite C",
    "iso:country":"US",
    "sg:address":"2949 Randolph Ave Suite C",
    "sg:city":"Costa Mesa",
    "sg:classifiers":[
        {
            "category":"Shopping",
            "subcategory":"Clothing, Apparel, & Fashions",
            "type":"Retail Goods"
        }
    ],
    "sg:phone":"+1 714 436 1540",
    "sg:postcode":"92626",
    "sg:province":"CA",
    "sg:tags":[
        "clothing",
        "women's"
    ],
    "sg:website":"www.pinkmascara.com",
    "wof:name":"Pink Mascara",
    "wof:placetype":"venue"
},
  "geometry": {"coordinates":[-117.88800000000001,33.677898],"type":"Point"}
}