{
  "type": "Feature",
  "properties": {
    "addr:full":"606 Olive St Santa Barbara CA 93101",
    "addr:housenumber":"606",
    "addr:postcode":"93101",
    "addr:street":"Olive St",
    "iso:country":"US",
    "sg:address":"606 Olive St",
    "sg:city":"Santa Barbara",
    "sg:classifiers":[
        {
            "category":"Home & Garden",
            "subcategory":"Furniture",
            "type":"Retail Goods"
        }
    ],
    "sg:phone":"+1 805 962 1036",
    "sg:postcode":"93101",
    "sg:province":"CA",
    "sg:tags":[
        "equipment",
        "kitchen",
        "cabinet"
    ],
    "wof:name":"Hayward Design Ctr",
    "wof:placetype":"venue"
},
  "geometry": {"coordinates":[-119.692277,34.423967],"type":"Point"}
}