{
  "type": "Feature",
  "properties": {
    "addr:full":"30281 Barcelona Rd Castaic CA 91384",
    "addr:postcode":"30281;91384",
    "addr:street":"Barcelona Rd",
    "iso:country":"US",
    "sg:address":"30281 Barcelona Rd",
    "sg:city":"Castaic",
    "sg:classifiers":[
        {
            "category":"Shopping",
            "subcategory":"Books",
            "type":"Retail Goods"
        }
    ],
    "sg:phone":"+1 661 775 9822",
    "sg:postcode":"91384",
    "sg:province":"CA",
    "wof:name":"Bruce David Charles",
    "wof:placetype":"venue"
},
  "geometry": {"coordinates":[-118.642026,34.47124],"type":"Point"}
}