{
  "type": "Feature",
  "properties": {
    "addr:full":"15025 Innovation Dr San Diego CA 92128",
    "addr:housenumber":"15025",
    "addr:postcode":"92128",
    "addr:street":"Innovation Dr",
    "iso:country":"US",
    "sg:address":"15025 Innovation Dr",
    "sg:city":"San Diego",
    "sg:classifiers":[
        {
            "category":"Health Services",
            "subcategory":"Doctor",
            "type":"Services"
        }
    ],
    "sg:phone":"+1 858 626 7900",
    "sg:postcode":"92128",
    "sg:province":"CA",
    "sg:tags":[
        "physician",
        "surgeon"
    ],
    "wof:name":"David Alan Ingrum MD",
    "wof:placetype":"venue"
},
  "geometry": {"coordinates":[-117.076373,32.990244],"type":"Point"}
}