{
  "type": "Feature",
  "properties": {
    "addr:full":"565 Bryant St Palo Alto CA 94301",
    "addr:housenumber":"565",
    "addr:postcode":"94301",
    "addr:street":"Bryant St",
    "iso:country":"US",
    "sg:address":"565 Bryant St",
    "sg:city":"Palo Alto",
    "sg:classifiers":[
        {
            "category":"Restaurant",
            "type":"Food & Drink"
        }
    ],
    "sg:menulink":"http://www.allmenus.com/ca/san-jose/275216-rangoon-restaurant/menu/",
    "sg:phone":"+1 650 325 8146",
    "sg:postcode":"94301",
    "sg:province":"CA",
    "sg:tags":[
        "burmese",
        "asian",
        "chinese"
    ],
    "wof:name":"Rangoon Restaurant",
    "wof:placetype":"venue"
},
  "geometry": {"coordinates":[-122.160583,37.445415],"type":"Point"}
}