{
  "type": "Feature",
  "properties": {
    "iso:country":"US",
    "sg:address":"2401 Waterman Blvd # 35",
    "sg:city":"Fairfield",
    "sg:classifiers":[
        {
            "category":"Restaurant",
            "type":"Food & Drink"
        }
    ],
    "sg:phone":"+1 707 428 3882",
    "sg:postcode":"94534",
    "sg:province":"CA",
    "sg:tags":[
        "style",
        "family",
        "italian"
    ],
    "wof:name":"Strings Italian Cafe",
    "wof:placetype":"venue"
},
  "geometry": {"coordinates":[-122.05249000000001,38.273312],"type":"Point"}
}