{
  "type": "Feature",
  "properties": {
    "addr:full":"501 Stockton Ave San Jose CA 95126",
    "addr:housenumber":"501",
    "addr:postcode":"95126",
    "addr:street":"Stockton Ave",
    "iso:country":"US",
    "sg:address":"501 Stockton Ave",
    "sg:city":"San Jose",
    "sg:classifiers":[
        {
            "category":"Health Services",
            "subcategory":"Health Practitioner",
            "type":"Services"
        }
    ],
    "sg:phone":"+1 408 499 7564",
    "sg:postcode":"95126",
    "sg:province":"CA",
    "sg:tags":[
        "psychologist"
    ],
    "wof:name":"Christine S Wu",
    "wof:placetype":"venue"
},
  "geometry": {"coordinates":[-121.910886,37.338333],"type":"Point"}
}