{
  "type": "Feature",
  "properties": {
    "iso:country":"US",
    "sg:address":"5255 Pomona Blvd",
    "sg:city":"Los Angeles",
    "sg:classifiers":[
        {
            "category":"Banks & Credit Unions",
            "subcategory":"Bank",
            "type":"Services"
        }
    ],
    "sg:phone":"+1 323 721 3024",
    "sg:postcode":"90022",
    "sg:province":"CA",
    "sg:tags":[
        "loan",
        "real estate"
    ],
    "wof:name":"Xtreme Mortgage",
    "wof:placetype":"venue"
},
  "geometry": {"coordinates":[-118.151793,34.033424],"type":"Point"}
}