{
  "type": "Feature",
  "properties": {
    "addr:full":"543 Encinitas Blvd Ste #117 Encinitas CA 92024",
    "addr:housenumber":"543",
    "addr:postcode":"92024",
    "addr:street":"Encinitas Blvd Ste # 117",
    "iso:country":"US",
    "sg:address":"543 Encinitas Blvd Ste #117",
    "sg:city":"Encinitas",
    "sg:classifiers":[
        {
            "category":"Education",
            "subcategory":"Special Training",
            "type":"Public Place"
        }
    ],
    "sg:phone":"+1 760 632 7577",
    "sg:postcode":"92024",
    "sg:province":"CA",
    "sg:tags":[
        "school",
        "specialty"
    ],
    "sg:website":"CaliforniaMusicStudios.com/",
    "wof:name":"California Music Studios",
    "wof:placetype":"venue"
},
  "geometry": {"coordinates":[-117.280512,33.04595],"type":"Point"}
}