{
  "type": "Feature",
  "properties": {
    "addr:full":"22554 Ventura Blvd Ste 109 Woodland Hills CA 91364",
    "addr:housenumber":"22554",
    "addr:postcode":"91364",
    "addr:street":"Ventura Blvd Ste 109",
    "iso:country":"US",
    "sg:address":"22554 Ventura Blvd Ste 109",
    "sg:city":"Woodland Hills",
    "sg:classifiers":[
        {
            "category":"Health Services",
            "subcategory":"Health Practitioner",
            "type":"Services"
        }
    ],
    "sg:phone":"+1 818 224 2106",
    "sg:postcode":"91364",
    "sg:province":"CA",
    "sg:tags":[
        "acupuncture"
    ],
    "wof:name":"Acupuncture Center For Health",
    "wof:placetype":"venue"
},
  "geometry": {"coordinates":[-118.618138,34.16705],"type":"Point"}
}