{
  "type": "Feature",
  "properties": {
    "addr:full":"720 San Antonio Ave Palo Alto CA 94303",
    "addr:housenumber":"720",
    "addr:postcode":"94303",
    "addr:street":"San Antonio Ave",
    "iso:country":"US",
    "sg:address":"720 San Antonio Ave",
    "sg:city":"Palo Alto",
    "sg:classifiers":[
        {
            "category":"Food & Beverages",
            "subcategory":"Groceries & Convenience Stores",
            "type":"Retail Goods"
        }
    ],
    "sg:phone":"+1 650 858 6910",
    "sg:postcode":"94303",
    "sg:province":"CA",
    "sg:tags":[
        "market"
    ],
    "wof:name":"Crossroads World Market",
    "wof:placetype":"venue"
},
  "geometry": {"coordinates":[-122.10209399999999,37.418796],"type":"Point"}
}