{
  "type": "Feature",
  "properties": {
    "iso:country":"US",
    "sg:address":"720 San Antonio Ave",
    "sg:city":"Palo Alto",
    "sg:classifiers":[
        {
            "category":"Food & Beverages",
            "subcategory":"Groceries & Convenience Stores",
            "type":"Retail Goods"
        }
    ],
    "sg:phone":"+1 650 858 6910",
    "sg:postcode":"94303",
    "sg:province":"CA",
    "sg:tags":[
        "market"
    ],
    "wof:name":"Crossroads World Market",
    "wof:placetype":"venue"
},
  "geometry": {"coordinates":[-122.102094,37.418796],"type":"Point"}
}