{
  "type": "Feature",
  "properties": {
    "iso:country":"US",
    "sg:address":"111 S Maag Ave",
    "sg:city":"Oakdale",
    "sg:classifiers":[
        {
            "category":"Professional",
            "type":"Services"
        }
    ],
    "sg:phone":"+1 209 845 0553",
    "sg:postcode":"95361",
    "sg:province":"CA",
    "wof:name":"Curves",
    "wof:placetype":"venue"
},
  "geometry": {"coordinates":[-120.831053,37.772406],"type":"Point"}
}