{
  "type": "Feature",
  "properties": {
    "addr:full":"1125 Eucalyptus Rd Nipomo CA 93444",
    "addr:housenumber":"1125",
    "addr:postcode":"93444",
    "addr:street":"Eucalyptus Rd",
    "iso:country":"US",
    "sg:address":"1125 Eucalyptus Rd",
    "sg:city":"Nipomo",
    "sg:classifiers":[
        {
            "category":"Shopping",
            "type":"Retail Goods"
        }
    ],
    "sg:phone":"+1 805 260 5327",
    "sg:postcode":"93444",
    "sg:province":"CA",
    "sg:tags":[
        "merchandise"
    ],
    "wof:name":"Babi's 1 Stop Travel Shop",
    "wof:placetype":"venue"
},
  "geometry": {"coordinates":[-120.52950300000001,35.020519],"type":"Point"}
}