{
  "type": "Feature",
  "properties": {
    "addr:full":"2433 Golden Rain Rd Walnut Creek CA 94595",
    "addr:housenumber":"2433",
    "addr:postcode":"94595",
    "addr:street":"Golden Rain Rd",
    "iso:country":"US",
    "sg:address":"2433 Golden Rain Rd",
    "sg:city":"Walnut Creek",
    "sg:classifiers":[
        {
            "category":"Wholesale",
            "subcategory":"Chemicals & Plastics",
            "type":"Manufacturing & Wholesale Goods"
        }
    ],
    "sg:phone":"+1 925 934 1096",
    "sg:postcode":"94595",
    "sg:province":"CA",
    "sg:tags":[
        "cleaning",
        "compound"
    ],
    "wof:name":"Amway Distributors",
    "wof:placetype":"venue"
},
  "geometry": {"coordinates":[-122.07970299999999,37.879943],"type":"Point"}
}