{
  "type": "Feature",
  "properties": {
    "iso:country":"US",
    "sg:address":"51858 Montgomery Dr",
    "sg:city":"Oakhurst",
    "sg:classifiers":[
        {
            "category":"Professional",
            "subcategory":"Art Services",
            "type":"Services"
        }
    ],
    "sg:phone":"+1 559 683 6416",
    "sg:postcode":"93644",
    "sg:province":"CA",
    "sg:tags":[
        "designer",
        "display",
        "producer"
    ],
    "wof:name":"Creative Concepts",
    "wof:placetype":"venue"
},
  "geometry": {"coordinates":[-119.602355,37.357533],"type":"Point"}
}