{
  "type": "Feature",
  "properties": {
    "iso:country":"US",
    "sg:address":"9833 Geyser Ave",
    "sg:city":"Northridge",
    "sg:classifiers":[
        {
            "category":"Autos & Motor Vehicles",
            "subcategory":"Automobile Sales",
            "type":"Retail Goods"
        }
    ],
    "sg:phone":"+1 818 993 9380",
    "sg:postcode":"91324",
    "sg:province":"CA",
    "sg:tags":[
        "car",
        "dealer"
    ],
    "wof:name":"SDG Auto Sales",
    "wof:placetype":"venue"
},
  "geometry": {"coordinates":[-118.542676,34.246878],"type":"Point"}
}