{
  "type": "Feature",
  "properties": {
    "addr:full":"756 N Van Ness Ave Los Angeles CA 90038",
    "addr:housenumber":"756",
    "addr:postcode":"90038",
    "addr:street":"N Van Ness Ave",
    "iso:country":"US",
    "sg:address":"756 N Van Ness Ave",
    "sg:city":"Los Angeles",
    "sg:classifiers":[
        {
            "category":"Professional",
            "subcategory":"Management & Consulting",
            "type":"Services"
        }
    ],
    "sg:phone":"+1 323 871 8054",
    "sg:postcode":"90038",
    "sg:province":"CA",
    "sg:tags":[
        "consultant",
        "educational"
    ],
    "wof:name":"Dubois Foundation Inc",
    "wof:placetype":"venue"
},
  "geometry": {"coordinates":[-118.31563800000001,34.08394],"type":"Point"}
}