{
  "type": "Feature",
  "properties": {
    "addr:full":"5915 Kanan Rd Agoura Hills CA 91301",
    "addr:housenumber":"5915",
    "addr:postcode":"91301",
    "addr:street":"Kanan Rd",
    "iso:country":"US",
    "sg:address":"5915 Kanan Rd",
    "sg:city":"Agoura Hills",
    "sg:classifiers":[
        {
            "category":"Deli",
            "type":"Food & Drink"
        }
    ],
    "sg:phone":"+1 818 889 9113",
    "sg:postcode":"91301",
    "sg:province":"CA",
    "wof:name":"Agoura's Famous Deli & Restaurant",
    "wof:placetype":"venue"
},
  "geometry": {"coordinates":[-118.758003,34.164501],"type":"Point"}
}