{
  "type": "Feature",
  "properties": {
    "addr:full":"4753 E Olive Ave Fresno CA 93702",
    "addr:housenumber":"4753",
    "addr:postcode":"93702",
    "addr:street":"E Olive Ave",
    "iso:country":"US",
    "sg:address":"4753 E Olive Ave",
    "sg:city":"Fresno",
    "sg:classifiers":[
        {
            "category":"Social Services",
            "type":"Services"
        }
    ],
    "sg:phone":"+1 559 252 8782",
    "sg:postcode":"93702",
    "sg:province":"CA",
    "sg:tags":[
        "organization",
        "welfare"
    ],
    "wof:name":"Hmong International New Year",
    "wof:placetype":"venue"
},
  "geometry": {"coordinates":[-119.73639300000001,36.757768],"type":"Point"}
}