{
  "type": "Feature",
  "properties": {
    "addr:full":"Church & Market San Francisco CA 94114",
    "addr:postcode":"94114",
    "iso:country":"US",
    "sg:address":"Church & Market",
    "sg:city":"San Francisco",
    "sg:classifiers":[
        {
            "category":"Restaurant",
            "type":"Food & Drink"
        }
    ],
    "sg:postcode":"94114",
    "sg:province":"CA",
    "sg:tags":[
        "flavor",
        "local"
    ],
    "sg:website":"www.myspace.com/battlehooch",
    "wof:name":"Battlehooch",
    "wof:placetype":"venue"
},
  "geometry": {"coordinates":[-122.428966,37.767419],"type":"Point"}
}