{
  "type": "Feature",
  "properties": {
    "addr:full":"1900 Noriega St San Francisco CA 94122",
    "addr:housenumber":"1900",
    "addr:postcode":"94122",
    "addr:street":"Noriega St",
    "iso:country":"US",
    "sg:address":"1900 Noriega St",
    "sg:city":"San Francisco",
    "sg:classifiers":[
        {
            "category":"Banks & Credit Unions",
            "subcategory":"Bank",
            "type":"Services"
        }
    ],
    "sg:postcode":"94122",
    "sg:province":"CA",
    "wof:name":"Citibank",
    "wof:placetype":"venue"
},
  "geometry": {"coordinates":[-122.484342,37.754153],"type":"Point"}
}