{
  "type": "Feature",
  "properties": {
    "iso:country":"US",
    "sg:address":"7 W 41st Ave",
    "sg:city":"San Mateo",
    "sg:classifiers":[
        {
            "category":"Professional",
            "subcategory":"Business Services",
            "type":"Services"
        }
    ],
    "sg:phone":"+1 650 802 6880",
    "sg:postcode":"94403",
    "sg:province":"CA",
    "sg:tags":[
        "durable",
        "good"
    ],
    "wof:name":"United Supply Inc",
    "wof:placetype":"venue"
},
  "geometry": {"coordinates":[-122.290564,37.530781],"type":"Point"}
}