{
  "type": "Feature",
  "properties": {
    "iso:country":"US",
    "sg:address":"713 Quintana Dr",
    "sg:city":"Bakersfield",
    "sg:classifiers":[
        {
            "category":"Education",
            "subcategory":"School",
            "type":"Public Place"
        }
    ],
    "sg:phone":"+1 661 588 1553",
    "sg:postcode":"93314",
    "sg:province":"CA",
    "wof:name":"A Personalized Gift Shop",
    "wof:placetype":"venue"
},
  "geometry": {"coordinates":[-119.161528,35.347672],"type":"Point"}
}