{
  "type": "Feature",
  "properties": {
    "iso:country":"US",
    "sg:address":"2478 N Sunnyside Ave",
    "sg:city":"Fresno",
    "sg:classifiers":[
        {
            "category":"Wholesale",
            "subcategory":"Farm Supplies",
            "type":"Manufacturing & Wholesale Goods"
        }
    ],
    "sg:phone":"+1 559 291 7740",
    "sg:postcode":"93727",
    "sg:province":"CA",
    "sg:tags":[
        "control",
        "equipment",
        "industrial",
        "services-commercial",
        "pest"
    ],
    "sg:website":"http://www.west-ext.com",
    "wof:name":"Target Specialty Products",
    "wof:placetype":"venue"
},
  "geometry": {"coordinates":[-119.691997,36.772574],"type":"Point"}
}