{
  "type": "Feature",
  "properties": {
    "addr:full":"1941 W el Camino Real Mountain View CA 94040",
    "addr:housenumber":"1941",
    "addr:postcode":"94040",
    "addr:street":"W El Camino Real",
    "iso:country":"US",
    "sg:address":"1941 W el Camino Real",
    "sg:city":"Mountain View",
    "sg:classifiers":[
        {
            "category":"Professional",
            "subcategory":"Accounting & Tax Preparation",
            "type":"Services"
        }
    ],
    "sg:phone":"+1 650 961 9356",
    "sg:postcode":"94040",
    "sg:province":"CA",
    "sg:tags":[
        "return",
        "filing"
    ],
    "wof:name":"H & R Block Tax Svc",
    "wof:placetype":"venue"
},
  "geometry": {"coordinates":[-122.097221,37.393437],"type":"Point"}
}