{
  "type": "Feature",
  "properties": {
    "addr:full":"3761 Van Buren Blvd Riverside CA 92503",
    "addr:housenumber":"3761",
    "addr:postcode":"92503",
    "addr:street":"Van Buren Blvd",
    "iso:country":"US",
    "sg:address":"3761 Van Buren Blvd",
    "sg:city":"Riverside",
    "sg:classifiers":[
        {
            "category":"Travel",
            "subcategory":"Travel Agent",
            "type":"Entertainment"
        }
    ],
    "sg:phone":"+1 951 358 0178",
    "sg:postcode":"92503",
    "sg:province":"CA",
    "sg:tags":[
        "agency",
        "bureau"
    ],
    "wof:name":"ITCC",
    "wof:placetype":"venue"
},
  "geometry": {"coordinates":[-117.444118,33.917461],"type":"Point"}
}