{
  "type": "Feature",
  "properties": {
    "iso:country":"US",
    "sg:address":"901 Columbus Ave",
    "sg:city":"San Francisco",
    "sg:classifiers":[
        {
            "category":"Coffee & Tea",
            "type":"Food & Drink"
        },
        {
            "category":"Restaurant",
            "type":"Food & Drink"
        }
    ],
    "sg:phone":"+1 415 409 9001",
    "sg:postcode":"94133",
    "sg:province":"CA",
    "sg:tags":[
        "mediterranean"
    ],
    "wof:name":"901 Columbus Caffe",
    "wof:placetype":"venue"
},
  "geometry": {"coordinates":[-122.41376,37.802785],"type":"Point"}
}