{
  "type": "Feature",
  "properties": {
    "addr:full":"723 Lincoln Way San Francisco CA 94122",
    "addr:housenumber":"723",
    "addr:postcode":"94122",
    "addr:street":"Lincoln Way",
    "iso:country":"US",
    "sg:address":"723 Lincoln Way",
    "sg:city":"San Francisco",
    "sg:classifiers":[
        {
            "category":"Manufacturing",
            "subcategory":"Wood Products",
            "type":"Manufacturing & Wholesale Goods"
        },
        {
            "category":"Building & Trades",
            "subcategory":"Construction",
            "type":"Services"
        }
    ],
    "sg:phone":"+1 415 664 7452",
    "sg:postcode":"94122",
    "sg:province":"CA",
    "sg:tags":[
        "carpentry",
        "cabinet",
        "co",
        "maker",
        "mfg"
    ],
    "wof:name":"Cuschieri's Cabinet Shop",
    "wof:placetype":"venue"
},
  "geometry": {"coordinates":[-122.466224,37.765813],"type":"Point"}
}