{
  "type": "Feature",
  "properties": {
    "addr:full":"8752 Amigo Ave Northridge CA 91324",
    "addr:housenumber":"8752",
    "addr:postcode":"91324",
    "addr:street":"Amigo Ave",
    "iso:country":"US",
    "sg:address":"8752 Amigo Ave",
    "sg:city":"Northridge",
    "sg:classifiers":[
        {
            "category":"Freight",
            "type":"Transportation"
        }
    ],
    "sg:phone":"+1 818 280 1414",
    "sg:postcode":"91324",
    "sg:province":"CA",
    "sg:tags":[
        "operator",
        "trucking"
    ],
    "sg:website":"www.hollywoodmove.com",
    "wof:name":"Hollywood Moving & Storage",
    "wof:placetype":"venue"
},
  "geometry": {"coordinates":[-118.53851299999999,34.230302],"type":"Point"}
}