{
  "type": "Feature",
  "properties": {
    "addr:full":"6357 Co Rd 48 Willows CA 95988",
    "addr:housenumber":"6357;48",
    "addr:postcode":"95988",
    "addr:street":"Co Rd",
    "iso:country":"US",
    "sg:address":"6357 Co Rd 48",
    "sg:city":"Willows",
    "sg:phone":"+1 530 934 3282",
    "sg:postcode":"95988",
    "sg:province":"CA",
    "sg:tags":[
        "farm",
        "rice",
        "mfg",
        "farming",
        "supply"
    ],
    "wof:name":"Poly Riser & Pipe",
    "wof:placetype":"venue"
},
  "geometry": {"coordinates":[-122.197979,39.538766],"type":"Point"}
}