{
  "type": "Feature",
  "properties": {
    "iso:country":"US",
    "sg:address":"770 W 14th St",
    "sg:city":"Merced",
    "sg:classifiers":[
        {
            "category":"Wholesale",
            "subcategory":"Groceries",
            "type":"Manufacturing & Wholesale Goods"
        }
    ],
    "sg:phone":"+1 209 722 2187",
    "sg:postcode":"95340",
    "sg:province":"CA",
    "sg:tags":[
        "tortilla"
    ],
    "wof:name":"LA Casita",
    "wof:placetype":"venue"
},
  "geometry": {"coordinates":[-120.488956,37.299336],"type":"Point"}
}