{
  "type": "Feature",
  "properties": {
    "iso:country":"US",
    "sg:address":"5301 Hazel Ave",
    "sg:city":"Fair Oaks",
    "sg:classifiers":[
        {
            "category":"Restaurant",
            "type":"Food & Drink"
        }
    ],
    "sg:menulink":"http://www.allmenus.com/ca/sacramento/75100-round-table-pizza/menu/",
    "sg:phone":"+1 916 962 2700",
    "sg:postcode":"95628",
    "sg:province":"CA",
    "sg:tags":[
        "american",
        "pizza"
    ],
    "wof:name":"Round Table Pizza",
    "wof:placetype":"venue"
},
  "geometry": {"coordinates":[-121.22627,38.663086],"type":"Point"}
}