{
  "type": "Feature",
  "properties": {
    "addr:full":"1793 6th St Port Hueneme CA 93041",
    "addr:housenumber":"1793",
    "addr:postcode":"93041",
    "addr:street":"6Th St",
    "iso:country":"US",
    "sg:address":"1793 6th St",
    "sg:city":"Port Hueneme",
    "sg:classifiers":[
        {
            "category":"Freight",
            "type":"Transportation"
        }
    ],
    "sg:phone":"+1 805 483 9268",
    "sg:postcode":"93041",
    "sg:province":"CA",
    "sg:tags":[
        "operator",
        "local",
        "trucking"
    ],
    "wof:name":"Jennings Trucking",
    "wof:placetype":"venue"
},
  "geometry": {"coordinates":[-119.192666,34.167177],"type":"Point"}
}