{
  "type": "Feature",
  "properties": {
    "addr:full":"8570 23rd Ave Sacramento CA 95826",
    "addr:housenumber":"8570",
    "addr:postcode":"95826",
    "addr:street":"23Rd Ave",
    "iso:country":"US",
    "sg:address":"8570 23rd Ave",
    "sg:city":"Sacramento",
    "sg:classifiers":[
        {
            "category":"Wholesale",
            "subcategory":"Electrical",
            "type":"Manufacturing & Wholesale Goods"
        }
    ],
    "sg:phone":"+1 916 387 1336",
    "sg:postcode":"95826",
    "sg:province":"CA",
    "sg:tags":[
        "generator"
    ],
    "sg:website":"www.pacmachine.com",
    "wof:name":"Pac Machine",
    "wof:placetype":"venue"
},
  "geometry": {"coordinates":[-121.383922,38.531571],"type":"Point"}
}