{
  "type": "Feature",
  "properties": {
    "addr:full":"1201 Piner Rd Santa Rosa CA 95403",
    "addr:housenumber":"1201",
    "addr:postcode":"95403",
    "addr:street":"Piner Rd",
    "iso:country":"US",
    "sg:address":"1201 Piner Rd",
    "sg:city":"Santa Rosa",
    "sg:classifiers":[
        {
            "category":"Wholesale",
            "subcategory":"Furniture",
            "type":"Manufacturing & Wholesale Goods"
        }
    ],
    "sg:phone":"+1 707 570 1791",
    "sg:postcode":"95403",
    "sg:province":"CA",
    "wof:name":"Red Tag Furniture",
    "wof:placetype":"venue"
},
  "geometry": {"coordinates":[-122.739237,38.471838],"type":"Point"}
}