{
  "type": "Feature",
  "properties": {
    "iso:country":"US",
    "sg:address":"100 Buckingham Dr",
    "sg:city":"Santa Clara",
    "sg:classifiers":[
        {
            "category":"Communications",
            "subcategory":"Film & Video Production",
            "type":"Services"
        }
    ],
    "sg:phone":"+1 408 244 9692",
    "sg:postcode":"95051",
    "sg:province":"CA",
    "sg:tags":[
        "taping"
    ],
    "wof:name":"Kingsway Productions",
    "wof:placetype":"venue"
},
  "geometry": {"coordinates":[-121.97168000000001,37.32519],"type":"Point"}
}