{
  "type": "Feature",
  "properties": {
    "addr:full":"15 Freeman Ct Oakley CA 94595",
    "addr:housenumber":"15",
    "addr:postcode":"94595",
    "addr:street":"Freeman Ct",
    "iso:country":"US",
    "sg:address":"15 Freeman Ct",
    "sg:city":"Oakley",
    "sg:classifiers":[
        {
            "category":"Retail",
            "subcategory":"Laundry & Dry Cleaning",
            "type":"Services"
        }
    ],
    "sg:phone":"+1 925 625 9625",
    "sg:postcode":"94595",
    "sg:province":"CA",
    "sg:tags":[
        "cleaners",
        "rug",
        "carpet"
    ],
    "wof:name":"Patriot Carpet Cleaners",
    "wof:placetype":"venue"
},
  "geometry": {"coordinates":[-122.081059,37.884007],"type":"Point"}
}