{
  "type": "Feature",
  "properties": {
    "iso:country":"US",
    "sg:address":"2422 Artesia Blvd",
    "sg:city":"Redondo Beach",
    "sg:classifiers":[
        {
            "category":"Bars & Pubs",
            "type":"Food & Drink"
        }
    ],
    "sg:phone":"+1 310 374 7030",
    "sg:postcode":"90278",
    "sg:province":"CA",
    "sg:tags":[
        "nightlife"
    ],
    "wof:name":"Bac Street Lounge",
    "wof:placetype":"venue"
},
  "geometry": {"coordinates":[-118.366997,33.8727],"type":"Point"}
}