{
  "type": "Feature",
  "properties": {
    "iso:country":"US",
    "sg:address":"330 Lincoln Ave Unit B",
    "sg:city":"San Jose",
    "sg:classifiers":[
        {
            "category":"Building & Trades",
            "subcategory":"Construction",
            "type":"Services"
        }
    ],
    "sg:phone":"+1 408 924 0102",
    "sg:postcode":"95126",
    "sg:province":"CA",
    "sg:tags":[
        "interior",
        "design"
    ],
    "wof:name":"Possibility Kitchens Designer Kate Stratton",
    "wof:placetype":"venue"
},
  "geometry": {"coordinates":[-121.908417,37.32322],"type":"Point"}
}