{
  "type": "Feature",
  "properties": {
    "addr:full":"939 McCoy Ln Santa Maria CA 93455",
    "addr:housenumber":"939",
    "addr:postcode":"93455",
    "addr:street":"Mccoy Ln",
    "iso:country":"US",
    "sg:address":"939 McCoy Ln",
    "sg:city":"Santa Maria",
    "sg:classifiers":[
        {
            "category":"Retail",
            "subcategory":"Repair Shop",
            "type":"Services"
        }
    ],
    "sg:phone":"+1 805 345 3300",
    "sg:postcode":"93455",
    "sg:province":"CA",
    "sg:tags":[
        "related"
    ],
    "wof:name":"Ewing Irrigation Golf & Ind",
    "wof:placetype":"venue"
},
  "geometry": {"coordinates":[-120.448398,34.916824],"type":"Point"}
}