{
  "type": "Feature",
  "properties": {
    "addr:full":"3559 Eggers Dr Fremont CA 94536",
    "addr:housenumber":"3559",
    "addr:postcode":"94536",
    "addr:street":"Eggers Dr",
    "iso:country":"US",
    "sg:address":"3559 Eggers Dr",
    "sg:city":"Fremont",
    "sg:classifiers":[
        {
            "category":"Social Services",
            "subcategory":"Child Care",
            "type":"Services"
        }
    ],
    "sg:phone":"+1 510 894 0422",
    "sg:postcode":"94536",
    "sg:province":"CA",
    "wof:name":"Tender Care",
    "wof:placetype":"venue"
},
  "geometry": {"coordinates":[-121.994074,37.555337],"type":"Point"}
}