{
  "type": "Feature",
  "properties": {
    "iso:country":"US",
    "sg:address":"180 Grand Ave",
    "sg:city":"Oakland",
    "sg:classifiers":[
        {
            "category":"Professional",
            "subcategory":"Engineering",
            "type":"Services"
        }
    ],
    "sg:phone":"+1 510 839 1742",
    "sg:postcode":"94612",
    "sg:province":"CA",
    "sg:tags":[
        "transportation",
        "engineer"
    ],
    "sg:website":"www.dowlinginc.com",
    "wof:name":"Dowling Associates",
    "wof:placetype":"venue"
},
  "geometry": {"coordinates":[-122.263648,37.811255],"type":"Point"}
}