{
  "type": "Feature",
  "properties": {
    "addr:full":"7209 Van Nuys Blvd Van Nuys CA 91405",
    "addr:housenumber":"7209",
    "addr:postcode":"91405",
    "addr:street":"Van Nuys Blvd",
    "iso:country":"US",
    "sg:address":"7209 Van Nuys Blvd",
    "sg:city":"Van Nuys",
    "sg:classifiers":[
        {
            "category":"Restaurant",
            "type":"Food & Drink"
        }
    ],
    "sg:phone":"+1 818 988 2853",
    "sg:postcode":"91405",
    "sg:province":"CA",
    "wof:name":"My Trang Restaurant",
    "wof:placetype":"venue"
},
  "geometry": {"coordinates":[-118.44899700000001,34.2015],"type":"Point"}
}