{
  "type": "Feature",
  "properties": {
    "addr:full":"6025 N El Dorado St Stockton CA 95207",
    "addr:housenumber":"6025",
    "addr:postcode":"95207",
    "addr:street":"N El Dorado St",
    "iso:country":"US",
    "sg:address":"6025 N El Dorado St",
    "sg:city":"Stockton",
    "sg:classifiers":[
        {
            "category":"Shopping",
            "subcategory":"Jewelry",
            "type":"Retail Goods"
        },
        {
            "category":"Manufacturing",
            "subcategory":"Jewelry",
            "type":"Manufacturing & Wholesale Goods"
        }
    ],
    "sg:phone":"+1 209 478 2293",
    "sg:postcode":"95207",
    "sg:province":"CA",
    "sg:tags":[
        "designer",
        "jeweler"
    ],
    "sg:website":"http://KingsJewelry.com",
    "wof:name":"King's Jewelry",
    "wof:placetype":"venue"
},
  "geometry": {"coordinates":[-121.308756,38.007774],"type":"Point"}
}