{
  "type": "Feature",
  "properties": {
    "iso:country":"US",
    "sg:address":"5930 Lakeshore Dr",
    "sg:city":"Cypress",
    "sg:classifiers":[
        {
            "category":"Freight",
            "type":"Transportation"
        }
    ],
    "sg:phone":"+1 714 826 3836",
    "sg:postcode":"90630",
    "sg:province":"CA",
    "sg:tags":[
        "forwarding"
    ],
    "wof:name":"Nedrac Incorporated",
    "wof:placetype":"venue"
},
  "geometry": {"coordinates":[-118.029926,33.829507],"type":"Point"}
}