{
  "type": "Feature",
  "properties": {
    "iso:country":"US",
    "sg:address":"433 N Market St",
    "sg:city":"Redding",
    "sg:classifiers":[
        {
            "category":"Food & Beverages",
            "subcategory":"Liquor & Beverages",
            "type":"Retail Goods"
        }
    ],
    "sg:phone":"+1 530 244 4700",
    "sg:postcode":"96003",
    "sg:province":"CA",
    "wof:name":"North Market",
    "wof:placetype":"venue"
},
  "geometry": {"coordinates":[-122.38387,40.599546],"type":"Point"}
}