{
  "type": "Feature",
  "properties": {
    "addr:full":"14145 Danielson St Poway CA 92064",
    "addr:housenumber":"14145",
    "addr:postcode":"ca 92064",
    "addr:street":"Danielson St",
    "iso:country":"US",
    "sg:address":"14145 Danielson St",
    "sg:city":"Poway",
    "sg:classifiers":[
        {
            "category":"Shopping",
            "subcategory":"Bicycles & Sporting Goods",
            "type":"Retail Goods"
        }
    ],
    "sg:phone":"+1 858 513 1064",
    "sg:postcode":"92064",
    "sg:province":"CA",
    "sg:tags":[
        "equipment",
        "diver",
        "supply"
    ],
    "wof:name":"Deep Outdoors",
    "wof:placetype":"venue"
},
  "geometry": {"coordinates":[-117.028886,32.940711],"type":"Point"}
}