{
  "type": "Feature",
  "properties": {
    "iso:country":"US",
    "sg:address":"10500 Pelham Dr",
    "sg:city":"Windsor",
    "sg:classifiers":[
        {
            "category":"Utilities",
            "subcategory":"Water",
            "type":"Services"
        }
    ],
    "sg:phone":"+1 707 838 8301",
    "sg:postcode":"95492",
    "sg:province":"CA",
    "sg:tags":[
        "supply"
    ],
    "wof:name":"Mount Weske Estates Water Co",
    "wof:placetype":"venue"
},
  "geometry": {"coordinates":[-122.79273,38.576558],"type":"Point"}
}