{
  "type": "Feature",
  "properties": {
    "iso:country":"US",
    "sg:address":"3433 American River Dr Ste A",
    "sg:city":"Sacramento",
    "sg:classifiers":[
        {
            "category":"Health Services",
            "subcategory":"Clinic",
            "type":"Services"
        }
    ],
    "sg:phone":"+1 916 972 7831",
    "sg:postcode":"95864",
    "sg:province":"CA",
    "sg:tags":[
        "counseling",
        "mental"
    ],
    "sg:website":"www.hearthealer.net",
    "wof:name":"Linda Paoli LCSW",
    "wof:placetype":"venue"
},
  "geometry": {"coordinates":[-121.400226,38.570235],"type":"Point"}
}