{
  "type": "Feature",
  "properties": {
    "addr:full":"318 Cayuga St Salinas CA 93901",
    "addr:housenumber":"318",
    "addr:postcode":"93901",
    "addr:street":"Cayuga St",
    "iso:country":"US",
    "sg:address":"318 Cayuga St",
    "sg:city":"Salinas",
    "sg:classifiers":[
        {
            "category":"Building & Trades",
            "subcategory":"Construction",
            "type":"Services"
        }
    ],
    "sg:phone":"+1 831 754 2444",
    "sg:postcode":"93901",
    "sg:province":"CA",
    "sg:tags":[
        "contractor",
        "fence-sales"
    ],
    "wof:name":"Rovella A Paul",
    "wof:placetype":"venue"
},
  "geometry": {"coordinates":[-121.658939,36.672886],"type":"Point"}
}