{
  "type": "Feature",
  "properties": {
    "addr:full":"5252 Argosy Ave Huntington Beach CA 92649",
    "addr:housenumber":"5252",
    "addr:postcode":"92649",
    "addr:street":"Argosy Ave",
    "iso:country":"US",
    "sg:address":"5252 Argosy Ave",
    "sg:city":"Huntington Beach",
    "sg:classifiers":[
        {
            "category":"Freight",
            "type":"Transportation"
        }
    ],
    "sg:phone":"+1 714 898 0955",
    "sg:postcode":"92649",
    "sg:province":"CA",
    "sg:tags":[
        "mover"
    ],
    "sg:website":"www.crownrelo.com",
    "wof:name":"Crown Relocations",
    "wof:placetype":"venue"
},
  "geometry": {"coordinates":[-118.03402,33.741036],"type":"Point"}
}