{
  "type": "Feature",
  "properties": {
    "iso:country":"US",
    "sg:address":"165 E High St",
    "sg:city":"Moorpark",
    "sg:classifiers":[
        {
            "category":"Real Estate",
            "subcategory":"Architect",
            "type":"Services"
        }
    ],
    "sg:phone":"+1 805 529 6883",
    "sg:postcode":"93021",
    "sg:province":"CA",
    "wof:name":"Nextects Architects",
    "wof:placetype":"venue"
},
  "geometry": {"coordinates":[-118.88001199999999,34.285444],"type":"Point"}
}