{
  "type": "Feature",
  "properties": {
    "addr:full":"7111 Hwy 128 Healdsburg CA 95448",
    "addr:housenumber":"7111",
    "addr:postcode":"95448",
    "addr:street":"Hwy 128",
    "iso:country":"US",
    "sg:address":"7111 Hwy 128",
    "sg:city":"Healdsburg",
    "sg:classifiers":[
        {
            "category":"Manufacturing",
            "subcategory":"Food",
            "type":"Manufacturing & Wholesale Goods"
        }
    ],
    "sg:phone":"+1 707 433 9463",
    "sg:postcode":"95448",
    "sg:province":"CA",
    "sg:tags":[
        "vineyard",
        "winery"
    ],
    "wof:name":"Stonestreet LLC",
    "wof:placetype":"venue"
},
  "geometry": {"coordinates":[-122.81905,38.667027],"type":"Point"}
}