{
  "type": "Feature",
  "properties": {
    "iso:country":"US",
    "sg:address":"181 3rd St",
    "sg:city":"San Rafael",
    "sg:classifiers":[
        {
            "category":"Insurance",
            "subcategory":"Insurance Agent",
            "type":"Services"
        }
    ],
    "sg:phone":"+1 415 256 1750",
    "sg:postcode":"94901",
    "sg:province":"CA",
    "wof:name":"Tan Gram",
    "wof:placetype":"venue"
},
  "geometry": {"coordinates":[-122.512593,37.968885],"type":"Point"}
}