{
  "type": "Feature",
  "properties": {
    "iso:country":"US",
    "sg:address":"23051 Kilkenny Ln",
    "sg:city":"Red Bluff",
    "sg:classifiers":[
        {
            "category":"Retail",
            "subcategory":"Animal Services",
            "type":"Services"
        }
    ],
    "sg:phone":"+1 530 527 8709",
    "sg:postcode":"96080",
    "sg:province":"CA",
    "sg:tags":[
        "pet",
        "boarding",
        "sitting"
    ],
    "wof:name":"Murphy's Pet Sitting",
    "wof:placetype":"venue"
},
  "geometry": {"coordinates":[-122.17663,40.085642],"type":"Point"}
}