{
  "type": "Feature",
  "properties": {
    "addr:full":"2034 Forest Ave San Jose CA 95128",
    "addr:housenumber":"2034",
    "addr:postcode":"95128",
    "addr:street":"Forest Ave",
    "iso:country":"US",
    "sg:address":"2034 Forest Ave",
    "sg:city":"San Jose",
    "sg:classifiers":[
        {
            "category":"Health Services",
            "subcategory":"Medical Lab",
            "type":"Services"
        }
    ],
    "sg:phone":"+1 408 998 8388",
    "sg:postcode":"95128",
    "sg:province":"CA",
    "sg:tags":[
        "laboratory"
    ],
    "wof:name":"A & T Dental Ceramics",
    "wof:placetype":"venue"
},
  "geometry": {"coordinates":[-121.933767,37.326841],"type":"Point"}
}