{
  "type": "Feature",
  "properties": {
    "iso:country":"US",
    "sg:address":"3136 Bonita Rd Apt 201",
    "sg:city":"Chula Vista",
    "sg:classifiers":[
        {
            "category":"Real Estate",
            "subcategory":"Real Estate Operator",
            "type":"Services"
        }
    ],
    "sg:phone":"+1 619 420 6621",
    "sg:postcode":"91910",
    "sg:province":"CA",
    "sg:tags":[
        "apartment"
    ],
    "wof:name":"Bonita Court Apartments",
    "wof:placetype":"venue"
},
  "geometry": {"coordinates":[-117.056999,32.647598],"type":"Point"}
}