{
  "type": "Feature",
  "properties": {
    "iso:country":"US",
    "sg:address":"3940 California Ave",
    "sg:city":"Norco",
    "sg:classifiers":[
        {
            "category":"Shopping",
            "subcategory":"Gifts & Souvenirs",
            "type":"Retail Goods"
        }
    ],
    "sg:phone":"+1 951 637 0507",
    "sg:postcode":"92860",
    "sg:province":"CA",
    "sg:tags":[
        "party",
        "supply"
    ],
    "wof:name":"J R Party Supply",
    "wof:placetype":"venue"
},
  "geometry": {"coordinates":[-117.52809000000001,33.939513],"type":"Point"}
}