{
  "type": "Feature",
  "properties": {
    "iso:country":"US",
    "sg:address":"5850 Franklin Blvd",
    "sg:city":"Sacramento",
    "sg:classifiers":[
        {
            "category":"Autos & Motor Vehicles",
            "subcategory":"Automobile Sales",
            "type":"Retail Goods"
        }
    ],
    "sg:phone":"+1 916 422 0601",
    "sg:postcode":"95824",
    "sg:province":"CA",
    "sg:tags":[
        "used"
    ],
    "wof:name":"Yias Auto Sale",
    "wof:placetype":"venue"
},
  "geometry": {"coordinates":[-121.47075,38.520441],"type":"Point"}
}