{
  "type": "Feature",
  "properties": {
    "iso:country":"US",
    "sg:address":"176 E Blithedale Ave",
    "sg:city":"Mill Valley",
    "sg:classifiers":[
        {
            "category":"Personal",
            "type":"Services"
        }
    ],
    "sg:phone":"+1 415 384 0242",
    "sg:postcode":"94941",
    "sg:province":"CA",
    "sg:tags":[
        "therapist",
        "massage"
    ],
    "wof:name":"Thai Traditional Med Massage",
    "wof:placetype":"venue"
},
  "geometry": {"coordinates":[-122.5425,37.904453],"type":"Point"}
}