{
  "type": "Feature",
  "properties": {
    "addr:full":"11886 Mariposa Rd Hesperia CA 92345",
    "addr:housenumber":"11886",
    "addr:postcode":"92345",
    "addr:street":"Mariposa Rd",
    "iso:country":"US",
    "sg:address":"11886 Mariposa Rd",
    "sg:city":"Hesperia",
    "sg:classifiers":[
        {
            "category":"Travel",
            "subcategory":"Hotels & Motels",
            "type":"Entertainment"
        }
    ],
    "sg:phone":"+1 760 949 1515",
    "sg:postcode":"92345",
    "sg:province":"CA",
    "wof:name":"Econo Lodge",
    "wof:placetype":"venue"
},
  "geometry": {"coordinates":[-117.349124,34.464323],"type":"Point"}
}