{
  "type": "Feature",
  "properties": {
    "iso:country":"US",
    "sg:address":"4631 Van Nuys Blvd",
    "sg:city":"Sherman Oaks",
    "sg:classifiers":[
        {
            "category":"Personal",
            "subcategory":"Barber",
            "type":"Services"
        }
    ],
    "sg:phone":"+1 818 784 9084",
    "sg:postcode":"91403",
    "sg:province":"CA",
    "wof:name":"At The Hop",
    "wof:placetype":"venue"
},
  "geometry": {"coordinates":[-118.44877,34.155647],"type":"Point"}
}