{
  "type": "Feature",
  "properties": {
    "iso:country":"US",
    "sg:address":"4225 Prado Rd",
    "sg:city":"Corona",
    "sg:classifiers":[
        {
            "category":"Professional",
            "subcategory":"Business Services",
            "type":"Services"
        }
    ],
    "sg:phone":"+1 951 736 5467",
    "sg:postcode":"92880",
    "sg:province":"CA",
    "sg:tags":[
        "automobile",
        "used"
    ],
    "wof:name":"J CS Classic Cars & Antiques",
    "wof:placetype":"venue"
},
  "geometry": {"coordinates":[-117.650634,33.881667],"type":"Point"}
}