{
  "type": "Feature",
  "properties": {
    "iso:country":"US",
    "sg:address":"608 Main St",
    "sg:city":"Pleasanton",
    "sg:classifiers":[
        {
            "category":"Shopping",
            "subcategory":"Gifts & Souvenirs",
            "type":"Retail Goods"
        }
    ],
    "sg:phone":"+1 925 426 9229",
    "sg:postcode":"94566",
    "sg:province":"CA",
    "sg:tags":[
        "indian"
    ],
    "wof:name":"Mesa Trading Co",
    "wof:placetype":"venue"
},
  "geometry": {"coordinates":[-121.874913,37.662388],"type":"Point"}
}