{
  "type": "Feature",
  "properties": {
    "addr:full":"3653 Slopeview Dr San Jose CA 95148",
    "addr:housenumber":"3653",
    "addr:postcode":"95148",
    "addr:street":"Slopeview Dr",
    "iso:country":"US",
    "sg:address":"3653 Slopeview Dr",
    "sg:city":"San Jose",
    "sg:classifiers":[
        {
            "category":"Shopping",
            "subcategory":"Catalog Store",
            "type":"Retail Goods"
        }
    ],
    "sg:phone":"+1 408 238 5610",
    "sg:postcode":"95148",
    "sg:province":"CA",
    "sg:tags":[
        "mail",
        "house"
    ],
    "wof:name":"Ejc Entrprises",
    "wof:placetype":"venue"
},
  "geometry": {"coordinates":[-121.773011,37.33106],"type":"Point"}
}