{
  "type": "Feature",
  "properties": {
    "iso:country":"US",
    "sg:address":"15926 Napa St",
    "sg:city":"North Hills",
    "sg:classifiers":[
        {
            "category":"Professional",
            "subcategory":"Lawyer & Legal Services",
            "type":"Services"
        }
    ],
    "sg:phone":"+1 818 892 5860",
    "sg:postcode":"91343",
    "sg:province":"CA",
    "wof:name":"Metamorphosis",
    "wof:placetype":"venue"
},
  "geometry": {"coordinates":[-118.47930100000001,34.226459],"type":"Point"}
}