{
  "type": "Feature",
  "properties": {
    "addr:full":"1404 Vacation Rd San Diego CA 92109",
    "addr:housenumber":"1404",
    "addr:postcode":"92109",
    "addr:street":"Vacation Rd",
    "iso:country":"US",
    "sg:address":"1404 Vacation Rd",
    "sg:city":"San Diego",
    "sg:classifiers":[
        {
            "category":"Restaurant",
            "type":"Food & Drink"
        }
    ],
    "sg:phone":"+1 858 490 6363",
    "sg:postcode":"92109",
    "sg:province":"CA",
    "sg:website":"www.paradisepoint.com",
    "wof:name":"Baleen",
    "wof:placetype":"venue"
},
  "geometry": {"coordinates":[-117.23591999999999,32.774968],"type":"Point"}
}