{
  "type": "Feature",
  "properties": {
    "addr:full":"1816 N Sepulveda Blvd Manhattan Beach CA 90266",
    "addr:housenumber":"1816",
    "addr:postcode":"90266",
    "addr:street":"N Sepulveda Blvd",
    "iso:country":"US",
    "sg:address":"1816 N Sepulveda Blvd",
    "sg:city":"Manhattan Beach",
    "sg:classifiers":[
        {
            "category":"Shopping",
            "subcategory":"Pets & Pet Supplies",
            "type":"Retail Goods"
        }
    ],
    "sg:phone":"+1 310 546 8090",
    "sg:postcode":"90266",
    "sg:province":"CA",
    "sg:tags":[
        "store"
    ],
    "sg:website":"petfoodsmarket.com",
    "wof:name":"Pet Foods Market",
    "wof:placetype":"venue"
},
  "geometry": {"coordinates":[-118.39595,33.891593],"type":"Point"}
}