{
  "type": "Feature",
  "properties": {
    "iso:country":"US",
    "sg:address":"2546 Bancroft Way",
    "sg:city":"Berkeley",
    "sg:classifiers":[
        {
            "category":"Shopping",
            "type":"Retail Goods"
        }
    ],
    "sg:phone":"+1 510 649 9577",
    "sg:postcode":"94701",
    "sg:province":"CA",
    "wof:name":"Oddball",
    "wof:placetype":"venue"
},
  "geometry": {"coordinates":[-122.258003,37.868698],"type":"Point"}
}