{
  "type": "Feature",
  "properties": {
    "iso:country":"US",
    "sg:address":"3840 Medford St",
    "sg:city":"Los Angeles",
    "sg:classifiers":[
        {
            "category":"Retail",
            "subcategory":"Auto Repair",
            "type":"Services"
        }
    ],
    "sg:phone":"+1 323 269 9094",
    "sg:postcode":"90063",
    "sg:province":"CA",
    "wof:name":"Rocha Auto Service",
    "wof:placetype":"venue"
},
  "geometry": {"coordinates":[-118.183998,34.0597],"type":"Point"}
}