{
  "type": "Feature",
  "properties": {
    "iso:country":"US",
    "sg:address":"4240 Katella Ave",
    "sg:city":"Los Alamitos",
    "sg:classifiers":[
        {
            "category":"Restaurant",
            "type":"Food & Drink"
        }
    ],
    "sg:phone":"+1 562 799 0027",
    "sg:postcode":"90720",
    "sg:province":"CA",
    "wof:name":"Wienerschnitzel",
    "wof:placetype":"venue"
},
  "geometry": {"coordinates":[-118.058998,33.802898],"type":"Point"}
}