{
  "type": "Feature",
  "properties": {
    "addr:full":"11643 Iberia Pl San Diego CA 92128",
    "addr:housenumber":"11643",
    "addr:postcode":"92128",
    "addr:street":"Iberia Pl",
    "iso:country":"US",
    "sg:address":"11643 Iberia Pl",
    "sg:city":"San Diego",
    "sg:classifiers":[
        {
            "category":"Retail",
            "subcategory":"Auto Repair",
            "type":"Services"
        }
    ],
    "sg:phone":"+1 858 487 1250",
    "sg:postcode":"92128",
    "sg:province":"CA",
    "sg:tags":[
        "repairing",
        "automobile"
    ],
    "wof:name":"Secor's GM Svc",
    "wof:placetype":"venue"
},
  "geometry": {"coordinates":[-117.07738000000001,33.015322],"type":"Point"}
}