{
  "type": "Feature",
  "properties": {
    "iso:country":"US",
    "sg:address":"3620 Greenwood Dr",
    "sg:city":"Kelseyville",
    "sg:classifiers":[
        {
            "category":"Manufacturing",
            "subcategory":"Printing",
            "type":"Manufacturing & Wholesale Goods"
        }
    ],
    "sg:phone":"+1 707 279 9621",
    "sg:postcode":"95451",
    "sg:province":"CA",
    "sg:tags":[
        "publisher"
    ],
    "wof:name":"Earthen Vessel Productions Inc",
    "wof:placetype":"venue"
},
  "geometry": {"coordinates":[-122.75443,38.990837],"type":"Point"}
}