{
  "type": "Feature",
  "properties": {
    "addr:full":"334 Santana Row Suite #330 San Jose CA 95128",
    "addr:housenumber":"334",
    "addr:postcode":"95128",
    "addr:street":"Santana Row Suite # 330",
    "iso:country":"US",
    "sg:address":"334 Santana Row Suite #330",
    "sg:city":"San Jose",
    "sg:classifiers":[
        {
            "category":"Professional",
            "subcategory":"Computer Services",
            "type":"Services"
        }
    ],
    "sg:phone":"+1 408 832 8536",
    "sg:postcode":"95128",
    "sg:province":"CA",
    "sg:tags":[
        "travel",
        "adventure",
        "adventure-travel",
        "outdoor",
        "activities"
    ],
    "sg:website":"http://www.adventuredrop.com",
    "wof:name":"AdventureDrop",
    "wof:placetype":"venue"
},
  "geometry": {"coordinates":[-121.94795000000001,37.322938],"type":"Point"}
}