{
  "type": "Feature",
  "properties": {
    "addr:full":"304 Glen Vista St San Diego CA 92114",
    "addr:housenumber":"304",
    "addr:postcode":"92114",
    "addr:street":"Glen Vista St",
    "iso:country":"US",
    "sg:address":"304 Glen Vista St",
    "sg:city":"San Diego",
    "sg:classifiers":[
        {
            "category":"Freight",
            "type":"Transportation"
        }
    ],
    "sg:phone":"+1 619 475 0243",
    "sg:postcode":"92114",
    "sg:province":"CA",
    "sg:tags":[
        "courier"
    ],
    "wof:name":"Mp Courier Service",
    "wof:placetype":"venue"
},
  "geometry": {"coordinates":[-117.02339000000001,32.699261],"type":"Point"}
}