{
  "type": "Feature",
  "properties": {
    "addr:full":"6160 Riverside Ave Riverside CA 92506",
    "addr:housenumber":"6160",
    "addr:postcode":"92506",
    "addr:street":"Riverside Ave",
    "iso:country":"US",
    "sg:address":"6160 Riverside Ave",
    "sg:city":"Riverside",
    "sg:classifiers":[
        {
            "category":"Organizations",
            "subcategory":"Religious Organization",
            "type":"Services"
        }
    ],
    "sg:phone":"+1 951 686 4343",
    "sg:postcode":"92506",
    "sg:province":"CA",
    "sg:tags":[
        "church"
    ],
    "wof:name":"Church Of Christ Magnolia Ctr",
    "wof:placetype":"venue"
},
  "geometry": {"coordinates":[-117.38784099999999,33.957255],"type":"Point"}
}