{
  "type": "Feature",
  "properties": {
    "iso:country":"US",
    "sg:address":"3649 Mitchell Rd",
    "sg:city":"Ceres",
    "sg:classifiers":[
        {
            "category":"Professional",
            "subcategory":"Accounting & Tax Preparation",
            "type":"Services"
        }
    ],
    "sg:phone":"+1 209 556 0408",
    "sg:postcode":"95307",
    "sg:province":"CA",
    "sg:tags":[
        "return",
        "filing"
    ],
    "wof:name":"Cazares Income Tax Svc",
    "wof:placetype":"venue"
},
  "geometry": {"coordinates":[-120.93882000000001,37.585251],"type":"Point"}
}