{
  "type": "Feature",
  "properties": {
    "iso:country":"US",
    "sg:address":"12315 Woodruff Ave",
    "sg:city":"Downey",
    "sg:classifiers":[
        {
            "category":"Wholesale",
            "subcategory":"Construction Materials",
            "type":"Manufacturing & Wholesale Goods"
        }
    ],
    "sg:phone":"+1 562 803 5256",
    "sg:postcode":"90241",
    "sg:province":"CA",
    "sg:tags":[
        "granite"
    ],
    "wof:name":"Granite Tops Etc",
    "wof:placetype":"venue"
},
  "geometry": {"coordinates":[-118.11665600000001,33.919565],"type":"Point"}
}