{
  "type": "Feature",
  "properties": {
    "addr:full":"3150 18th St San Francisco CA 94110",
    "addr:housenumber":"3150",
    "addr:postcode":"94110",
    "addr:street":"18Th St",
    "iso:country":"US",
    "sg:address":"3150 18th St",
    "sg:city":"San Francisco",
    "sg:classifiers":[
        {
            "category":"Professional",
            "subcategory":"Management & Consulting",
            "type":"Services"
        }
    ],
    "sg:phone":"+1 415 260 6758",
    "sg:postcode":"94110",
    "sg:province":"CA",
    "sg:tags":[
        "life",
        "coach"
    ],
    "sg:website":"www.danaclark.net",
    "wof:name":"Dana Clark Coaching",
    "wof:placetype":"venue"
},
  "geometry": {"coordinates":[-122.414259,37.762718],"type":"Point"}
}