{
  "type": "Feature",
  "properties": {
    "addr:full":"891 Laurelwood Rd Ste 108 Santa Clara CA 95054",
    "addr:housenumber":"891",
    "addr:postcode":"95054",
    "addr:street":"Laurelwood Rd Ste 108",
    "iso:country":"US",
    "sg:address":"891 Laurelwood Rd Ste 108",
    "sg:city":"Santa Clara",
    "sg:classifiers":[
        {
            "category":"Shopping",
            "subcategory":"Bicycles & Sporting Goods",
            "type":"Retail Goods"
        }
    ],
    "sg:phone":"+1 408 492 9282",
    "sg:postcode":"95054",
    "sg:province":"CA",
    "sg:website":"www.airsoftextreme.com",
    "wof:name":"Airsoft Extreme",
    "wof:placetype":"venue"
},
  "geometry": {"coordinates":[-121.949513,37.379174],"type":"Point"}
}