{
  "type": "Feature",
  "properties": {
    "iso:country":"US",
    "sg:address":"219 Vis Bonita",
    "sg:city":"Newbury Park",
    "sg:classifiers":[
        {
            "category":"Social Services",
            "type":"Services"
        }
    ],
    "sg:phone":"+1 805 375 4745",
    "sg:postcode":"91320",
    "sg:province":"CA",
    "sg:tags":[
        "counselor",
        "marriage",
        "family"
    ],
    "wof:name":"Suzanne Mills",
    "wof:placetype":"venue"
},
  "geometry": {"coordinates":[-118.961933,34.194659],"type":"Point"}
}