{
  "type": "Feature",
  "properties": {
    "iso:country":"US",
    "sg:address":"205 N Yale Ave",
    "sg:city":"Claremont",
    "sg:classifiers":[
        {
            "category":"Organizations",
            "subcategory":"Professional Association",
            "type":"Services"
        }
    ],
    "sg:phone":"+1 909 624 1681",
    "sg:postcode":"91711",
    "sg:province":"CA",
    "sg:tags":[
        "chambers",
        "commerce"
    ],
    "sg:website":"www.claremontchamber.org",
    "wof:name":"Chamber Of Commerce",
    "wof:placetype":"venue"
},
  "geometry": {"coordinates":[-117.71795899999999,34.096567],"type":"Point"}
}