{
  "type": "Feature",
  "properties": {
    "iso:country":"US",
    "sg:address":"2611 W Florence Ave",
    "sg:city":"Los Angeles",
    "sg:classifiers":[
        {
            "category":"Building & Trades",
            "subcategory":"Construction",
            "type":"Services"
        }
    ],
    "sg:phone":"+1 323 753 3001",
    "sg:postcode":"90043",
    "sg:province":"CA",
    "sg:tags":[
        "downspouts",
        "gutter"
    ],
    "wof:name":"A Millennium Gutter Svc",
    "wof:placetype":"venue"
},
  "geometry": {"coordinates":[-118.322019,33.974644],"type":"Point"}
}