{
  "type": "Feature",
  "properties": {
    "addr:full":"6579 Brissac Pl Alta Loma CA 91737",
    "addr:housenumber":"6579",
    "addr:postcode":"91737",
    "addr:street":"Brissac Pl",
    "iso:country":"US",
    "sg:address":"6579 Brissac Pl",
    "sg:city":"Alta Loma",
    "sg:classifiers":[
        {
            "category":"Manufacturing",
            "subcategory":"Printing",
            "type":"Manufacturing & Wholesale Goods"
        }
    ],
    "sg:phone":"+1 909 477 6653",
    "sg:postcode":"91737",
    "sg:province":"CA",
    "sg:tags":[
        "check"
    ],
    "wof:name":"Safeguard Business Forms",
    "wof:placetype":"venue"
},
  "geometry": {"coordinates":[-117.583139,34.133573],"type":"Point"}
}