{
  "type": "Feature",
  "properties": {
    "iso:country":"US",
    "sg:address":"187 W Orangethorpe Ave",
    "sg:city":"Placentia",
    "sg:classifiers":[
        {
            "category":"Professional",
            "subcategory":"Art Services",
            "type":"Services"
        }
    ],
    "sg:phone":"+1 714 528 8040",
    "sg:postcode":"92870",
    "sg:province":"CA",
    "sg:tags":[
        "graphic",
        "design"
    ],
    "sg:website":"www.eclecticprinting.com/",
    "wof:name":"Eclectic Printing & Design",
    "wof:placetype":"venue"
},
  "geometry": {"coordinates":[-117.87398399999999,33.863397],"type":"Point"}
}