{
  "type": "Feature",
  "properties": {
    "addr:full":"1133 W 17th St Santa Ana CA 92706",
    "addr:housenumber":"1133",
    "addr:postcode":"92706",
    "addr:street":"W 17Th St",
    "iso:country":"US",
    "sg:address":"1133 W 17th St",
    "sg:city":"Santa Ana",
    "sg:classifiers":[
        {
            "category":"Restaurant",
            "type":"Food & Drink"
        }
    ],
    "sg:phone":"+1 714 836 5096",
    "sg:postcode":"92706",
    "sg:province":"CA",
    "sg:tags":[
        "mexican"
    ],
    "wof:name":"El Rincon Chilango",
    "wof:placetype":"venue"
},
  "geometry": {"coordinates":[-117.881681,33.760321],"type":"Point"}
}