{
  "type": "Feature",
  "properties": {
    "addr:full":"11222 S La Cienega Boulevard Inglewood CA 90304",
    "addr:housenumber":"11222",
    "addr:postcode":"90304",
    "addr:street":"S La Cienega Boulevard",
    "iso:country":"US",
    "sg:address":"11222 S La Cienega Boulevard",
    "sg:city":"Inglewood",
    "sg:classifiers":[
        {
            "category":"Wholesale",
            "subcategory":"Computers",
            "type":"Manufacturing & Wholesale Goods"
        }
    ],
    "sg:phone":"+1 310 337 0803",
    "sg:postcode":"90304",
    "sg:province":"CA",
    "sg:website":"www.vinastar.com",
    "wof:name":"Vinastar",
    "wof:placetype":"venue"
},
  "geometry": {"coordinates":[-118.370041,33.932699],"type":"Point"}
}