{
  "type": "Feature",
  "properties": {
    "iso:country":"US",
    "sg:address":"520 Capitol Mall",
    "sg:city":"Sacramento",
    "sg:classifiers":[
        {
            "category":"Professional",
            "subcategory":"Lawyer & Legal Services",
            "type":"Services"
        }
    ],
    "sg:phone":"+1 916 326 5150",
    "sg:postcode":"95814",
    "sg:province":"CA",
    "wof:name":"Valenza D Gregory Atty",
    "wof:placetype":"venue"
},
  "geometry": {"coordinates":[-121.501366,38.578548],"type":"Point"}
}