{
  "type": "Feature",
  "properties": {
    "addr:full":"1502 E Chevy Chase Dr Glendale CA 91206",
    "addr:housenumber":"1502",
    "addr:postcode":"91206",
    "addr:street":"E Chevy Chase Dr",
    "iso:country":"US",
    "sg:address":"1502 E Chevy Chase Dr",
    "sg:city":"Glendale",
    "sg:classifiers":[
        {
            "category":"Insurance",
            "subcategory":"Health Insurance",
            "type":"Services"
        }
    ],
    "sg:phone":"+1 818 546 8610",
    "sg:postcode":"91206",
    "sg:province":"CA",
    "sg:tags":[
        "market"
    ],
    "wof:name":"So-Calif Conference Book & Bible House",
    "wof:placetype":"venue"
},
  "geometry": {"coordinates":[-118.23200199999999,34.151901],"type":"Point"}
}