{
  "type": "Feature",
  "properties": {
    "addr:full":"2635 Park Center Dr Simi Valley CA 93065",
    "addr:housenumber":"2635",
    "addr:postcode":"93065",
    "addr:street":"Park Center Dr",
    "iso:country":"US",
    "sg:address":"2635 Park Center Dr",
    "sg:city":"Simi Valley",
    "sg:classifiers":[
        {
            "category":"Manufacturing",
            "subcategory":"Tools & Machinery",
            "type":"Manufacturing & Wholesale Goods"
        }
    ],
    "sg:phone":"+1 805 578 4000",
    "sg:postcode":"93065",
    "sg:province":"CA",
    "sg:tags":[
        "computer",
        "printer",
        "mfg"
    ],
    "wof:name":"Hitachi Prtg Solutions Amer",
    "wof:placetype":"venue"
},
  "geometry": {"coordinates":[-118.79742,34.283588],"type":"Point"}
}