{
  "type": "Feature",
  "properties": {
    "iso:country":"US",
    "sg:address":"616 N Flores St",
    "sg:city":"West Hollywood",
    "sg:classifiers":[
        {
            "category":"Communications",
            "subcategory":"Film & Video Production",
            "type":"Services"
        }
    ],
    "sg:phone":"+1 323 653 2438",
    "sg:postcode":"90048",
    "sg:province":"CA",
    "sg:tags":[
        "audio"
    ],
    "wof:name":"Red Dot Films",
    "wof:placetype":"venue"
},
  "geometry": {"coordinates":[-118.371154,34.082655],"type":"Point"}
}