{
  "type": "Feature",
  "properties": {
    "addr:full":"8195 Mallard Way Millville CA 96062",
    "addr:housenumber":"8195",
    "addr:postcode":"96062",
    "addr:street":"Mallard Way",
    "iso:country":"US",
    "sg:address":"8195 Mallard Way",
    "sg:city":"Millville",
    "sg:classifiers":[
        {
            "category":"Manufacturing",
            "subcategory":"Chemicals & Compounds",
            "type":"Manufacturing & Wholesale Goods"
        }
    ],
    "sg:phone":"+1 530 547 5493",
    "sg:postcode":"96062",
    "sg:province":"CA",
    "sg:tags":[
        "plastic"
    ],
    "wof:name":"PLG",
    "wof:placetype":"venue"
},
  "geometry": {"coordinates":[-122.204947,40.510332],"type":"Point"}
}