{
  "type": "Feature",
  "properties": {
    "addr:full":"7269 Melrose Ave Los Angeles CA 90046",
    "addr:housenumber":"7269",
    "addr:postcode":"90046",
    "addr:street":"Melrose Ave",
    "iso:country":"US",
    "sg:address":"7269 Melrose Ave",
    "sg:city":"Los Angeles",
    "sg:classifiers":[
        {
            "category":"Sports & Exercise",
            "subcategory":"Gym",
            "type":"Entertainment"
        }
    ],
    "sg:phone":"+1 323 937 2122",
    "sg:postcode":"90046",
    "sg:province":"CA",
    "sg:tags":[
        "club",
        "health",
        "studio",
        "gymnasium"
    ],
    "wof:name":"Melrose Spa",
    "wof:placetype":"venue"
},
  "geometry": {"coordinates":[-118.34827300000001,34.083596],"type":"Point"}
}