{
  "type": "Feature",
  "properties": {
    "iso:country":"US",
    "sg:address":"634 E Colorado St",
    "sg:city":"Glendale",
    "sg:classifiers":[
        {
            "category":"Wholesale",
            "subcategory":"Electrical",
            "type":"Manufacturing & Wholesale Goods"
        }
    ],
    "sg:phone":"+1 818 244 6777",
    "sg:postcode":"91205",
    "sg:province":"CA",
    "sg:tags":[
        "cleaners",
        "vacuum"
    ],
    "wof:name":"Mini-Vac",
    "wof:placetype":"venue"
},
  "geometry": {"coordinates":[-118.247003,34.142598],"type":"Point"}
}