{
  "type": "Feature",
  "properties": {
    "iso:country":"US",
    "sg:address":"660 Pismo St",
    "sg:city":"San Luis Obispo",
    "sg:classifiers":[
        {
            "category":"Professional",
            "type":"Services"
        }
    ],
    "sg:phone":"+1 805 548 0909",
    "sg:postcode":"93401",
    "sg:province":"CA",
    "sg:tags":[
        "establishment"
    ],
    "wof:name":"Project Life Saver",
    "wof:placetype":"venue"
},
  "geometry": {"coordinates":[-120.663076,35.276205],"type":"Point"}
}