{
  "type": "Feature",
  "properties": {
    "iso:country":"US",
    "sg:address":"18630 Collier Ave. Unit E",
    "sg:city":"Lake Elsinore",
    "sg:classifiers":[
        {
            "category":"Professional",
            "subcategory":"Art Services",
            "type":"Services"
        },
        {
            "category":"Professional",
            "subcategory":"Printing & Photocopies",
            "type":"Services"
        }
    ],
    "sg:phone":"+1 951 674 5930",
    "sg:postcode":"92530",
    "sg:province":"CA",
    "sg:tags":[
        "graphic",
        "design"
    ],
    "sg:website":"www.synergygraffix.com",
    "wof:name":"Synergy Graffix",
    "wof:placetype":"venue"
},
  "geometry": {"coordinates":[-117.333235,33.686179],"type":"Point"}
}