{
  "type": "Feature",
  "properties": {
    "iso:country":"US",
    "sg:address":"1908 N Brampton Ave",
    "sg:city":"Rialto",
    "sg:classifiers":[
        {
            "category":"Professional",
            "type":"Services"
        }
    ],
    "sg:phone":"+1 909 875 1688",
    "sg:postcode":"92376",
    "sg:province":"CA",
    "wof:name":"Kathryn Love",
    "wof:placetype":"venue"
},
  "geometry": {"coordinates":[-117.385626,34.135005],"type":"Point"}
}