{
  "type": "Feature",
  "properties": {
    "iso:country":"US",
    "sg:address":"1113 High St",
    "sg:city":"Auburn",
    "sg:classifiers":[
        {
            "category":"Banks & Credit Unions",
            "subcategory":"Investment Brokerage",
            "type":"Services"
        }
    ],
    "sg:phone":"+1 530 889 0400",
    "sg:postcode":"95603",
    "sg:province":"CA",
    "sg:tags":[
        "consultant",
        "planning",
        "financial"
    ],
    "wof:name":"North Brook Management",
    "wof:placetype":"venue"
},
  "geometry": {"coordinates":[-121.071364,38.897159],"type":"Point"}
}