{
  "type": "Feature",
  "properties": {
    "addr:full":"25 Walnut Ave. Los Gatos CA 95030",
    "addr:housenumber":"25",
    "addr:postcode":"95030",
    "addr:street":"Walnut Ave.",
    "iso:country":"US",
    "sg:address":"25 Walnut Ave.",
    "sg:city":"Los Gatos",
    "sg:classifiers":[
        {
            "category":"Building & Trades",
            "subcategory":"Construction",
            "type":"Services"
        }
    ],
    "sg:phone":"+1 415 450 8957",
    "sg:postcode":"95030",
    "sg:province":"CA",
    "sg:tags":[
        "contractor"
    ],
    "sg:website":"tassinconstruction.com",
    "wof:name":"Tassin Terrazzo",
    "wof:placetype":"venue"
},
  "geometry": {"coordinates":[-121.991816,37.22728],"type":"Point"}
}