{
  "type": "Feature",
  "properties": {
    "iso:country":"US",
    "sg:address":"22722 White Lily Cir",
    "sg:city":"Moreno Valley",
    "sg:classifiers":[
        {
            "category":"Shopping",
            "subcategory":"Clothing, Apparel, & Fashions",
            "type":"Retail Goods"
        }
    ],
    "sg:phone":"+1 951 924 9624",
    "sg:postcode":"92557",
    "sg:province":"CA",
    "wof:name":"Suiturself",
    "wof:placetype":"venue"
},
  "geometry": {"coordinates":[-117.26625900000001,33.947221],"type":"Point"}
}