{
  "type": "Feature",
  "properties": {
    "iso:country":"US",
    "sg:address":"2610 Contra Loma Blvd",
    "sg:city":"Antioch",
    "sg:classifiers":[
        {
            "category":"Retail",
            "subcategory":"Auto Repair",
            "type":"Services"
        }
    ],
    "sg:phone":"+1 925 757 5220",
    "sg:postcode":"94509",
    "sg:province":"CA",
    "sg:tags":[
        "automobile",
        "smog"
    ],
    "wof:name":"Bhalla's Gas & Auto Svc",
    "wof:placetype":"venue"
},
  "geometry": {"coordinates":[-121.822256,37.99808],"type":"Point"}
}