{
  "type": "Feature",
  "properties": {
    "iso:country":"US",
    "sg:address":"100 Bayview Dr",
    "sg:city":"San Rafael",
    "sg:classifiers":[
        {
            "category":"Building & Trades",
            "subcategory":"Construction",
            "type":"Services"
        }
    ],
    "sg:phone":"+1 415 456 8833",
    "sg:postcode":"94901",
    "sg:province":"CA",
    "sg:tags":[
        "house",
        "nonresidential"
    ],
    "wof:name":"Bergmark Construction",
    "wof:placetype":"venue"
},
  "geometry": {"coordinates":[-122.478711,37.977723],"type":"Point"}
}