{
  "type": "Feature",
  "properties": {
    "iso:country":"US",
    "sg:address":"7455 Westbrook Ave",
    "sg:city":"San Diego",
    "sg:classifiers":[
        {
            "category":"Manufacturing",
            "subcategory":"Toys & Sporting Goods",
            "type":"Manufacturing & Wholesale Goods"
        }
    ],
    "sg:phone":"+1 619 920 2796",
    "sg:postcode":"92139",
    "sg:province":"CA",
    "sg:tags":[
        "mfg"
    ],
    "wof:name":"Sharp Safety Equipment",
    "wof:placetype":"venue"
},
  "geometry": {"coordinates":[-117.028194,32.684054],"type":"Point"}
}