{
  "type": "Feature",
  "properties": {
    "iso:country":"US",
    "sg:address":"516 N 6th St",
    "sg:city":"Lompoc",
    "sg:classifiers":[
        {
            "category":"Home & Garden",
            "subcategory":"Furniture",
            "type":"Retail Goods"
        }
    ],
    "sg:phone":"+1 805 736 4555",
    "sg:postcode":"93436",
    "sg:province":"CA",
    "sg:tags":[
        "store"
    ],
    "wof:name":"Coast Home Furnishings",
    "wof:placetype":"venue"
},
  "geometry": {"coordinates":[-120.44135900000001,34.645534],"type":"Point"}
}