{
  "type": "Feature",
  "properties": {
    "iso:country":"US",
    "sg:address":"10238 Vassar Ave",
    "sg:city":"Chatsworth",
    "sg:classifiers":[
        {
            "category":"Wholesale",
            "subcategory":"Non-durable Goods",
            "type":"Manufacturing & Wholesale Goods"
        }
    ],
    "sg:phone":"+1 818 341 3361",
    "sg:postcode":"91311",
    "sg:province":"CA",
    "wof:name":"Ini Young Trading",
    "wof:placetype":"venue"
},
  "geometry": {"coordinates":[-118.60490299999999,34.256534],"type":"Point"}
}