{
  "type": "Feature",
  "properties": {
    "addr:full":"19508 Parthenia St Northridge CA 91324",
    "addr:housenumber":"19508",
    "addr:postcode":"91324",
    "addr:street":"Parthenia St",
    "iso:country":"US",
    "sg:address":"19508 Parthenia St",
    "sg:city":"Northridge",
    "sg:classifiers":[
        {
            "category":"Professional",
            "subcategory":"Credit Reporting & Collection",
            "type":"Services"
        }
    ],
    "sg:phone":"+1 818 775 1577",
    "sg:postcode":"91324",
    "sg:province":"CA",
    "sg:tags":[
        "agency"
    ],
    "wof:name":"Balboa Collections",
    "wof:placetype":"venue"
},
  "geometry": {"coordinates":[-118.562156,34.228146],"type":"Point"}
}