{
  "type": "Feature",
  "properties": {
    "iso:country":"US",
    "sg:address":"314 E Rowland St",
    "sg:city":"Covina",
    "sg:classifiers":[
        {
            "category":"Wholesale",
            "subcategory":"Construction Materials",
            "type":"Manufacturing & Wholesale Goods"
        }
    ],
    "sg:phone":"+1 626 859 3464",
    "sg:postcode":"91723",
    "sg:province":"CA",
    "sg:tags":[
        "tile"
    ],
    "wof:name":"Jjj Ceramic Tile",
    "wof:placetype":"venue"
},
  "geometry": {"coordinates":[-117.884392,34.079031],"type":"Point"}
}