{
  "type": "Feature",
  "properties": {
    "iso:country":"US",
    "sg:address":"1638 Bayo Vista Ave",
    "sg:city":"San Pablo",
    "sg:classifiers":[
        {
            "category":"Building & Trades",
            "subcategory":"Landscaping Services",
            "type":"Services"
        }
    ],
    "sg:phone":"+1 510 233 7055",
    "sg:postcode":"94806",
    "sg:province":"CA",
    "sg:tags":[
        "lawn",
        "maintenance",
        "grounds"
    ],
    "wof:name":"Cobb & Sons Gardening",
    "wof:placetype":"venue"
},
  "geometry": {"coordinates":[-122.325447,37.956143],"type":"Point"}
}