{
  "type": "Feature",
  "properties": {
    "iso:country":"US",
    "sg:address":"1753 E Saginaw Way",
    "sg:city":"Fresno",
    "sg:classifiers":[
        {
            "category":"Autos & Motor Vehicles",
            "subcategory":"Automobile Sales",
            "type":"Retail Goods"
        }
    ],
    "sg:phone":"+1 559 229 2100",
    "sg:postcode":"93726",
    "sg:province":"CA",
    "sg:tags":[
        "car",
        "dealer"
    ],
    "wof:name":"Cost Less Auto Sales",
    "wof:placetype":"venue"
},
  "geometry": {"coordinates":[-119.788823,36.788698],"type":"Point"}
}