{
  "type": "Feature",
  "properties": {
    "iso:country":"US",
    "sg:address":"7352 Rosecrans Ave",
    "sg:city":"Paramount",
    "sg:classifiers":[
        {
            "category":"Autos & Motor Vehicles",
            "subcategory":"Fuel & Gas Station",
            "type":"Retail Goods"
        }
    ],
    "sg:phone":"+1 562 602 2651",
    "sg:postcode":"90723",
    "sg:province":"CA",
    "wof:name":"MDA Fuel Inc",
    "wof:placetype":"venue"
},
  "geometry": {"coordinates":[-118.169881,33.903459],"type":"Point"}
}