{
  "type": "Feature",
  "properties": {
    "iso:country":"US",
    "sg:address":"1600 W Whittier Blvd",
    "sg:city":"Montebello",
    "sg:classifiers":[
        {
            "category":"Education",
            "subcategory":"Special Training",
            "type":"Public Place"
        },
        {
            "category":"Education",
            "subcategory":"School",
            "type":"Public Place"
        }
    ],
    "sg:phone":"+1 323 721 5111",
    "sg:postcode":"90640",
    "sg:province":"CA",
    "sg:tags":[
        "high",
        "middle",
        "educational",
        "elementary"
    ],
    "sg:website":"www.montebello.k12.ca.us",
    "wof:name":"Montebello Intermediate School",
    "wof:placetype":"venue"
},
  "geometry": {"coordinates":[-118.11799600000001,34.012299],"type":"Point"}
}