{
  "type": "Feature",
  "properties": {
    "addr:full":"9017 Mandarin Ave Alta Loma CA 91701",
    "addr:postcode":"9017;91701",
    "addr:street":"Mandarin Ave",
    "iso:country":"US",
    "sg:address":"9017 Mandarin Ave",
    "sg:city":"Alta Loma",
    "sg:classifiers":[
        {
            "category":"Wholesale",
            "subcategory":"Non-durable Goods",
            "type":"Manufacturing & Wholesale Goods"
        }
    ],
    "sg:phone":"+1 909 944 0900",
    "sg:postcode":"91701",
    "sg:province":"CA",
    "sg:tags":[
        "advertising"
    ],
    "wof:name":"Golden Source Intl",
    "wof:placetype":"venue"
},
  "geometry": {"coordinates":[-117.60950699999999,34.142227],"type":"Point"}
}