{
  "type": "Feature",
  "properties": {
    "iso:country":"US",
    "sg:address":"727 W 7th Street",
    "sg:city":"Los Angeles",
    "sg:classifiers":[
        {
            "category":"Professional",
            "subcategory":"Lawyer & Legal Services",
            "type":"Services"
        }
    ],
    "sg:phone":"+1 310 203 9933",
    "sg:postcode":"90017",
    "sg:province":"CA",
    "wof:name":"Law Offices of Homan Taghdiri",
    "wof:placetype":"venue"
},
  "geometry": {"coordinates":[-118.257951,34.048176],"type":"Point"}
}