{
  "type": "Feature",
  "properties": {
    "addr:full":"11960 Woodside Ave Lakeside CA 92040",
    "addr:housenumber":"11960",
    "addr:postcode":"92040",
    "addr:street":"Woodside Ave",
    "iso:country":"US",
    "sg:address":"11960 Woodside Ave",
    "sg:city":"Lakeside",
    "sg:classifiers":[
        {
            "category":"Health Services",
            "subcategory":"Doctor",
            "type":"Services"
        }
    ],
    "sg:phone":"+1 619 443 5330",
    "sg:postcode":"92040",
    "sg:province":"CA",
    "sg:tags":[
        "physician",
        "surgeon"
    ],
    "wof:name":"John J Clifford MD",
    "wof:placetype":"venue"
},
  "geometry": {"coordinates":[-116.931533,32.856038],"type":"Point"}
}