{
  "type": "Feature",
  "properties": {
    "iso:country":"US",
    "sg:address":"4088 S Figueroa St",
    "sg:city":"Los Angeles",
    "sg:classifiers":[
        {
            "category":"Retail",
            "subcategory":"Auto Repair",
            "type":"Services"
        }
    ],
    "sg:phone":"+1 323 232 2167",
    "sg:postcode":"90037",
    "sg:province":"CA",
    "sg:tags":[
        "road"
    ],
    "wof:name":"Access Towing",
    "wof:placetype":"venue"
},
  "geometry": {"coordinates":[-118.282652,34.010028],"type":"Point"}
}