{
  "type": "Feature",
  "properties": {
    "addr:full":"4121 Gage Ave Bell CA 90201",
    "addr:housenumber":"4121",
    "addr:postcode":"90201",
    "addr:street":"Gage Ave",
    "iso:country":"US",
    "sg:address":"4121 Gage Ave",
    "sg:city":"Bell",
    "sg:classifiers":[
        {
            "category":"Professional",
            "subcategory":"Accounting & Tax Preparation",
            "type":"Services"
        }
    ],
    "sg:phone":"+1 323 560 4563",
    "sg:postcode":"90201",
    "sg:province":"CA",
    "sg:tags":[
        "return",
        "filing"
    ],
    "wof:name":"A & J Tax Svc",
    "wof:placetype":"venue"
},
  "geometry": {"coordinates":[-118.19261400000001,33.978547],"type":"Point"}
}