{
  "type": "Feature",
  "properties": {
    "iso:country":"US",
    "sg:address":"604 N Noble St",
    "sg:city":"Orange",
    "sg:classifiers":[
        {
            "category":"Shopping",
            "subcategory":"Crafts & Fabrics",
            "type":"Retail Goods"
        }
    ],
    "sg:phone":"+1 714 633 3500",
    "sg:postcode":"92869",
    "sg:province":"CA",
    "sg:tags":[
        "sewing"
    ],
    "wof:name":"Sewing Basket",
    "wof:placetype":"venue"
},
  "geometry": {"coordinates":[-117.802256,33.797774],"type":"Point"}
}