{
  "type": "Feature",
  "properties": {
    "iso:country":"US",
    "sg:address":"1741 Ivar Avenue",
    "sg:city":"Los Angeles",
    "sg:classifiers":[
        {
            "category":"Retail",
            "subcategory":"Portrait Studio",
            "type":"Services"
        }
    ],
    "sg:phone":"+1 323 461 4232",
    "sg:postcode":"90028",
    "sg:province":"CA",
    "sg:tags":[
        "photography",
        "store"
    ],
    "wof:name":"Trailer Park",
    "wof:placetype":"venue"
},
  "geometry": {"coordinates":[-118.32830300000001,34.102538],"type":"Point"}
}