{
  "type": "Feature",
  "properties": {
    "iso:country":"US",
    "sg:address":"18919 Ventura Blvd",
    "sg:city":"Tarzana",
    "sg:classifiers":[
        {
            "category":"Wholesale",
            "subcategory":"Hardware",
            "type":"Manufacturing & Wholesale Goods"
        }
    ],
    "sg:phone":"+1 818 345 5481",
    "sg:postcode":"91356",
    "sg:province":"CA",
    "sg:tags":[
        "builder"
    ],
    "wof:name":"Deco-Brass Inc",
    "wof:placetype":"venue"
},
  "geometry": {"coordinates":[-118.545647,34.172495],"type":"Point"}
}