{
  "type": "Feature",
  "properties": {
    "iso:country":"US",
    "sg:address":"4216 Franklin Blvd",
    "sg:city":"Sacramento",
    "sg:classifiers":[
        {
            "category":"Professional",
            "type":"Services"
        },
        {
            "category":"Restaurant",
            "type":"Food & Drink"
        }
    ],
    "sg:phone":"+1 916 456 4287",
    "sg:postcode":"95820",
    "sg:province":"CA",
    "sg:tags":[
        "mexican",
        "caterer"
    ],
    "sg:website":"elnov.com/",
    "wof:name":"El Novillero",
    "wof:placetype":"venue"
},
  "geometry": {"coordinates":[-121.47507899999999,38.53648],"type":"Point"}
}