{
  "type": "Feature",
  "properties": {
    "iso:country":"US",
    "sg:address":"3201 Fletcher Drive",
    "sg:city":"Los Angeles",
    "sg:classifiers":[
        {
            "category":"Banks & Credit Unions",
            "subcategory":"Financial Services",
            "type":"Services"
        }
    ],
    "sg:phone":"+1 323 258 7364",
    "sg:postcode":"90065",
    "sg:province":"CA",
    "sg:tags":[
        "broker",
        "mortgage"
    ],
    "wof:name":"Star-Cash",
    "wof:placetype":"venue"
},
  "geometry": {"coordinates":[-118.243162,34.116865],"type":"Point"}
}