{
  "type": "Feature",
  "properties": {
    "iso:country":"US",
    "sg:address":"18500 State Hwy 1",
    "sg:city":"Marshall",
    "sg:classifiers":[
        {
            "category":"Professional",
            "subcategory":"Business Services",
            "type":"Services"
        }
    ],
    "sg:phone":"+1 415 663 9020",
    "sg:postcode":"94956",
    "sg:province":"CA",
    "sg:tags":[
        "conference",
        "center"
    ],
    "sg:website":"www.marconiconference.org",
    "wof:name":"Marconi Conference Ctr",
    "wof:placetype":"venue"
},
  "geometry": {"coordinates":[-122.894372,38.15977],"type":"Point"}
}