{
  "type": "Feature",
  "properties": {
    "addr:full":"9467 Cummings Rd Durham CA 95938",
    "addr:housenumber":"9467",
    "addr:postcode":"95938",
    "addr:street":"Cummings Rd",
    "iso:country":"US",
    "sg:address":"9467 Cummings Rd",
    "sg:city":"Durham",
    "sg:classifiers":[
        {
            "category":"Shopping",
            "type":"Retail Goods"
        }
    ],
    "sg:phone":"+1 530 343 8982",
    "sg:postcode":"95938",
    "sg:province":"CA",
    "sg:tags":[
        "material",
        "artist",
        "supply"
    ],
    "wof:name":"Horizon Art",
    "wof:placetype":"venue"
},
  "geometry": {"coordinates":[-121.782138,39.646886],"type":"Point"}
}