{
  "type": "Feature",
  "properties": {
    "addr:full":"707 Dool Ave Calexico CA 92231",
    "addr:housenumber":"707",
    "addr:postcode":"92231",
    "addr:street":"Dool Ave",
    "iso:country":"US",
    "sg:address":"707 Dool Ave",
    "sg:city":"Calexico",
    "sg:classifiers":[
        {
            "category":"Government",
            "subcategory":"Office",
            "type":"Public Place"
        }
    ],
    "sg:phone":"+1 760 357 3191",
    "sg:postcode":"92231",
    "sg:province":"CA",
    "wof:name":"CHDP Program",
    "wof:placetype":"venue"
},
  "geometry": {"coordinates":[-115.48623000000001,32.673654],"type":"Point"}
}