{
  "type": "Feature",
  "properties": {
    "addr:full":"7384 Valaho Dr Tujunga CA 91042",
    "addr:housenumber":"7384",
    "addr:postcode":"91042",
    "addr:street":"Valaho Dr",
    "iso:country":"US",
    "sg:address":"7384 Valaho Dr",
    "sg:city":"Tujunga",
    "sg:classifiers":[
        {
            "category":"Wholesale",
            "subcategory":"Vending Machines",
            "type":"Manufacturing & Wholesale Goods"
        }
    ],
    "sg:phone":"+1 818 352 2720",
    "sg:postcode":"91042",
    "sg:province":"CA",
    "sg:tags":[
        "operator"
    ],
    "wof:name":"All In 1 Vending",
    "wof:placetype":"venue"
},
  "geometry": {"coordinates":[-118.29337700000001,34.250252],"type":"Point"}
}