{
  "type": "Feature",
  "properties": {
    "iso:country":"US",
    "sg:address":"1608 India St. #105",
    "sg:city":"San Diego",
    "sg:classifiers":[
        {
            "category":"Home & Garden",
            "subcategory":"Home Furnishings",
            "type":"Retail Goods"
        }
    ],
    "sg:phone":"+1 619 235 6564",
    "sg:postcode":"92101",
    "sg:province":"CA",
    "sg:tags":[
        "decor"
    ],
    "sg:website":"www.masqueradeartofliving.com",
    "wof:name":"Masquerade",
    "wof:placetype":"venue"
},
  "geometry": {"coordinates":[-117.16799899999999,32.722198],"type":"Point"}
}