{
  "type": "Feature",
  "properties": {
    "iso:country":"US",
    "sg:address":"201 S Lovekin Blvd",
    "sg:city":"Blythe",
    "sg:classifiers":[
        {
            "category":"Professional",
            "type":"Services"
        }
    ],
    "sg:phone":"+1 760 921 8121",
    "sg:postcode":"92225",
    "sg:province":"CA",
    "sg:tags":[
        "establishment"
    ],
    "wof:name":"Wayne Perry Inc",
    "wof:placetype":"venue"
},
  "geometry": {"coordinates":[-114.605474,33.608184],"type":"Point"}
}