{
  "type": "Feature",
  "properties": {
    "addr:full":"12401 Debby St North Hollywood CA 91606",
    "addr:housenumber":"12401",
    "addr:postcode":"91606",
    "addr:street":"Debby St",
    "iso:country":"US",
    "sg:address":"12401 Debby St",
    "sg:city":"North Hollywood",
    "sg:classifiers":[
        {
            "category":"Communications",
            "subcategory":"Film & Video Production",
            "type":"Services"
        },
        {
            "category":"Arts & Performance",
            "subcategory":"Theater",
            "type":"Entertainment"
        }
    ],
    "sg:phone":"+1 818 769 9649",
    "sg:postcode":"91606",
    "sg:province":"CA",
    "sg:tags":[
        "motion",
        "theatrical",
        "television",
        "program",
        "producer"
    ],
    "wof:name":"Goodwood Productions Inc",
    "wof:placetype":"venue"
},
  "geometry": {"coordinates":[-118.40279099999999,34.184062],"type":"Point"}
}