{
  "type": "Feature",
  "properties": {
    "addr:full":"3580 Wilshire Blvd Los Angeles CA 90010",
    "addr:housenumber":"3580",
    "addr:postcode":"90010",
    "addr:street":"Wilshire Blvd",
    "iso:country":"US",
    "sg:address":"3580 Wilshire Blvd",
    "sg:city":"Los Angeles",
    "sg:classifiers":[
        {
            "category":"Professional",
            "subcategory":"Lawyer & Legal Services",
            "type":"Services"
        }
    ],
    "sg:phone":"+1 213 637 9800",
    "sg:postcode":"90010",
    "sg:province":"CA",
    "sg:tags":[
        "attorney"
    ],
    "wof:name":"Sharon Oxborough Law Offices",
    "wof:placetype":"venue"
},
  "geometry": {"coordinates":[-118.30306400000001,34.061652],"type":"Point"}
}