{
  "type": "Feature",
  "properties": {
    "iso:country":"US",
    "sg:address":"45415 28th St E",
    "sg:city":"Lancaster",
    "sg:classifiers":[
        {
            "category":"Real Estate",
            "subcategory":"Real Estate Operator",
            "type":"Services"
        }
    ],
    "sg:phone":"+1 661 946 1877",
    "sg:postcode":"93535",
    "sg:province":"CA",
    "sg:tags":[
        "mobile",
        "home",
        "community"
    ],
    "wof:name":"Sunny Skies Mobile Home Park",
    "wof:placetype":"venue"
},
  "geometry": {"coordinates":[-118.079364,34.708425],"type":"Point"}
}