{
  "type": "Feature",
  "properties": {
    "iso:country":"US",
    "sg:address":"6701 Center Drive W",
    "sg:city":"Los Angeles",
    "sg:classifiers":[
        {
            "category":"Professional",
            "subcategory":"Lawyer & Legal Services",
            "type":"Services"
        }
    ],
    "sg:phone":"+1 310 337 4855",
    "sg:postcode":"90045",
    "sg:province":"CA",
    "wof:name":"Graham Stanley P Atty",
    "wof:placetype":"venue"
},
  "geometry": {"coordinates":[-118.393574,33.978773],"type":"Point"}
}