{
  "type": "Feature",
  "properties": {
    "addr:full":"6120 Madbury Ct San Luis Obispo CA 93401",
    "addr:postcode":"6120;93401",
    "addr:street":"Madbury Ct",
    "iso:country":"US",
    "sg:address":"6120 Madbury Ct",
    "sg:city":"San Luis Obispo",
    "sg:classifiers":[
        {
            "category":"Wholesale",
            "subcategory":"Chemicals & Plastics",
            "type":"Manufacturing & Wholesale Goods"
        }
    ],
    "sg:phone":"+1 805 462 8939",
    "sg:postcode":"93401",
    "sg:province":"CA",
    "sg:tags":[
        "cards",
        "credit",
        "metal"
    ],
    "wof:name":"Electronic Card Acceptance",
    "wof:placetype":"venue"
},
  "geometry": {"coordinates":[-120.624177,35.209216],"type":"Point"}
}