{
  "type": "Feature",
  "properties": {
    "addr:full":"1600 S De Anza Boulevard San Jose CA 95129",
    "addr:housenumber":"1600",
    "addr:postcode":"95129",
    "addr:street":"S De Anza Boulevard",
    "iso:country":"US",
    "sg:address":"1600 S De Anza Boulevard",
    "sg:city":"San Jose",
    "sg:classifiers":[
        {
            "category":"Restaurant",
            "type":"Food & Drink"
        }
    ],
    "sg:phone":"+1 408 996 0889",
    "sg:postcode":"95129",
    "sg:province":"CA",
    "sg:tags":[
        "chinese"
    ],
    "wof:name":"Wonderful Chinese Gourmet",
    "wof:placetype":"venue"
},
  "geometry": {"coordinates":[-122.03212000000001,37.295582],"type":"Point"}
}