{
  "type": "Feature",
  "properties": {
    "addr:full":"555 Williams Rd Palm Springs CA 92264",
    "addr:housenumber":"555",
    "addr:postcode":"92264",
    "addr:street":"Williams Rd",
    "iso:country":"US",
    "sg:address":"555 Williams Rd",
    "sg:city":"Palm Springs",
    "sg:classifiers":[
        {
            "category":"Building & Trades",
            "subcategory":"Construction",
            "type":"Services"
        }
    ],
    "sg:phone":"+1 760 327 2202",
    "sg:postcode":"92264",
    "sg:province":"CA",
    "sg:tags":[
        "coping",
        "plastering",
        "tiling",
        "pool",
        "swimming"
    ],
    "wof:name":"Mark Pool Svc",
    "wof:placetype":"venue"
},
  "geometry": {"coordinates":[-116.495271,33.814803],"type":"Point"}
}