{
  "type": "Feature",
  "properties": {
    "addr:full":"2120 Coolidge Dr Santa Clara CA 95051",
    "addr:housenumber":"2120",
    "addr:postcode":"95051",
    "addr:street":"Coolidge Dr",
    "iso:country":"US",
    "sg:address":"2120 Coolidge Dr",
    "sg:city":"Santa Clara",
    "sg:classifiers":[
        {
            "category":"Building & Trades",
            "subcategory":"Construction",
            "type":"Services"
        }
    ],
    "sg:phone":"+1 408 984 5606",
    "sg:postcode":"95051",
    "sg:province":"CA",
    "sg:tags":[
        "house"
    ],
    "wof:name":"Small Jobs Co",
    "wof:placetype":"venue"
},
  "geometry": {"coordinates":[-121.970922,37.360656],"type":"Point"}
}