{
  "type": "Feature",
  "properties": {
    "addr:full":"7996 Elmhurst Ave Rancho Cucamonga CA 91730",
    "addr:housenumber":"7996",
    "addr:postcode":"91730",
    "addr:street":"Elmhurst Ave",
    "iso:country":"US",
    "sg:address":"7996 Elmhurst Ave",
    "sg:city":"Rancho Cucamonga",
    "sg:classifiers":[
        {
            "category":"Education",
            "subcategory":"School",
            "type":"Public Place"
        }
    ],
    "sg:phone":"+1 909 941 6612",
    "sg:postcode":"91730",
    "sg:province":"CA",
    "wof:name":"National School Supplies",
    "wof:placetype":"venue"
},
  "geometry": {"coordinates":[-117.58565900000001,34.108085],"type":"Point"}
}