{
  "type": "Feature",
  "properties": {
    "addr:full":"30 Baywood Ct Fairfax CA 94930",
    "addr:housenumber":"30",
    "addr:postcode":"94930",
    "addr:street":"Baywood Ct",
    "iso:country":"US",
    "sg:address":"30 Baywood Ct",
    "sg:city":"Fairfax",
    "sg:classifiers":[
        {
            "category":"Restaurant",
            "type":"Food & Drink"
        }
    ],
    "sg:phone":"+1 415 485 5699",
    "sg:postcode":"94930",
    "sg:province":"CA",
    "sg:tags":[
        "caterer"
    ],
    "wof:name":"Pedemonte & Co",
    "wof:placetype":"venue"
},
  "geometry": {"coordinates":[-122.581599,37.984121],"type":"Point"}
}