{
  "type": "Feature",
  "properties": {
    "addr:full":"2154 Macarthur Blvd Oakland CA 94602",
    "addr:housenumber":"2154",
    "addr:postcode":"94602",
    "addr:street":"Macarthur Blvd",
    "iso:country":"US",
    "sg:address":"2154 Macarthur Blvd",
    "sg:city":"Oakland",
    "sg:classifiers":[
        {
            "category":"Banks & Credit Unions",
            "subcategory":"Bank",
            "type":"Services"
        }
    ],
    "sg:phone":"+1 510 649 6600",
    "sg:postcode":"94602",
    "sg:province":"CA",
    "wof:name":"Bank Of America",
    "wof:placetype":"venue"
},
  "geometry": {"coordinates":[-122.216964,37.800631],"type":"Point"}
}