{
  "type": "Feature",
  "properties": {
    "addr:full":"800 Franklin St # 202 Oakland CA 94607",
    "addr:housenumber":"800;202",
    "addr:postcode":"94607",
    "addr:street":"Franklin St #",
    "iso:country":"US",
    "sg:address":"800 Franklin St # 202",
    "sg:city":"Oakland",
    "sg:classifiers":[
        {
            "category":"Health Services",
            "subcategory":"Health Practitioner",
            "type":"Services"
        }
    ],
    "sg:phone":"+1 510 893 3928",
    "sg:postcode":"94607",
    "sg:province":"CA",
    "sg:tags":[
        "acupuncture",
        "medicine",
        "alternative"
    ],
    "wof:name":"Xing Lin Acupuncture & Chinese Medicine Clinic",
    "wof:placetype":"venue"
},
  "geometry": {"coordinates":[-122.272003,37.799801],"type":"Point"}
}