{
  "type": "Feature",
  "properties": {
    "addr:full":"144 N Glendale Ave Ste 202 Glendale CA 91206",
    "addr:housenumber":"144",
    "addr:postcode":"91206",
    "addr:street":"N Glendale Ave Ste 202",
    "iso:country":"US",
    "sg:address":"144 N Glendale Ave Ste 202",
    "sg:city":"Glendale",
    "sg:classifiers":[
        {
            "category":"Professional",
            "subcategory":"Lawyer & Legal Services",
            "type":"Services"
        }
    ],
    "sg:phone":"+1 818 240 1800",
    "sg:postcode":"91206",
    "sg:province":"CA",
    "sg:tags":[
        "personal",
        "injury"
    ],
    "sg:website":"www.bcalegal.com",
    "wof:name":"Benjamin Charchian & Associates",
    "wof:placetype":"venue"
},
  "geometry": {"coordinates":[-118.246375,34.14799],"type":"Point"}
}