{
  "type": "Feature",
  "properties": {
    "addr:full":"950 Northgate Dr San Rafael CA 94903",
    "addr:housenumber":"950",
    "addr:postcode":"94903",
    "addr:street":"Northgate Dr",
    "iso:country":"US",
    "sg:address":"950 Northgate Dr",
    "sg:city":"San Rafael",
    "sg:classifiers":[
        {
            "category":"Manufacturing",
            "subcategory":"Printing",
            "type":"Manufacturing & Wholesale Goods"
        }
    ],
    "sg:phone":"+1 415 491 1442",
    "sg:postcode":"94903",
    "sg:province":"CA",
    "sg:tags":[
        "periodical"
    ],
    "wof:name":"Cellular Business Magazine",
    "wof:placetype":"venue"
},
  "geometry": {"coordinates":[-122.54555000000001,38.007356],"type":"Point"}
}