{
  "type": "Feature",
  "properties": {
    "iso:country":"US",
    "sg:address":"16620 Soledad Canyon Rd",
    "sg:city":"Canyon Cntry",
    "sg:classifiers":[
        {
            "category":"Personal",
            "type":"Services"
        }
    ],
    "sg:phone":"+1 661 251 9391",
    "sg:postcode":"91387",
    "sg:province":"CA",
    "sg:tags":[
        "sewing",
        "alteration"
    ],
    "wof:name":"Rainbow Cleaners",
    "wof:placetype":"venue"
},
  "geometry": {"coordinates":[-118.42600299999999,34.4268],"type":"Point"}
}