{
  "type": "Feature",
  "properties": {
    "addr:full":"208 Buena Vista Dr Freedom CA 95019",
    "addr:housenumber":"208",
    "addr:postcode":"95019",
    "addr:street":"Buena Vista Dr",
    "iso:country":"US",
    "sg:address":"208 Buena Vista Dr",
    "sg:city":"Freedom",
    "sg:classifiers":[
        {
            "category":"Real Estate",
            "subcategory":"Real Estate Operator",
            "type":"Services"
        }
    ],
    "sg:phone":"+1 831 761 8609",
    "sg:postcode":"95019",
    "sg:province":"CA",
    "sg:tags":[
        "apartment"
    ],
    "wof:name":"Pat Barry Construct Prksd Apts",
    "wof:placetype":"venue"
},
  "geometry": {"coordinates":[-121.787823,36.940958],"type":"Point"}
}