{
  "type": "Feature",
  "properties": {
    "addr:full":"1200 Harbor Dr N Oceanside CA 92054",
    "addr:housenumber":"1200",
    "addr:postcode":"92054",
    "addr:street":"Harbor Dr N",
    "iso:country":"US",
    "sg:address":"1200 Harbor Dr N",
    "sg:city":"Oceanside",
    "sg:classifiers":[
        {
            "category":"Professional",
            "subcategory":"Lawyer & Legal Services",
            "type":"Services"
        }
    ],
    "sg:phone":"+1 760 729 5100",
    "sg:postcode":"92054",
    "sg:province":"CA",
    "wof:name":"Henderson Dale Attorney At Law",
    "wof:placetype":"venue"
},
  "geometry": {"coordinates":[-117.39045,33.206732],"type":"Point"}
}