{
  "type": "Feature",
  "properties": {
    "addr:full":"451 N Canon Dr Beverly Hills CA 90210",
    "addr:housenumber":"451",
    "addr:postcode":"90210",
    "addr:street":"N Canon Dr",
    "iso:country":"US",
    "sg:address":"451 N Canon Dr",
    "sg:city":"Beverly Hills",
    "sg:classifiers":[
        {
            "category":"Shopping",
            "subcategory":"Musical Instruments",
            "type":"Retail Goods"
        }
    ],
    "sg:phone":"+1 310 859 7200",
    "sg:postcode":"90210",
    "sg:province":"CA",
    "sg:tags":[
        "music",
        "dealer"
    ],
    "wof:name":"Anderson Scores",
    "wof:placetype":"venue"
},
  "geometry": {"coordinates":[-118.401231,34.070842],"type":"Point"}
}