{
  "type": "Feature",
  "properties": {
    "iso:country":"US",
    "sg:address":"2525 el Camino Real",
    "sg:city":"Carlsbad",
    "sg:classifiers":[
        {
            "category":"Shopping",
            "subcategory":"Tobacco",
            "type":"Retail Goods"
        }
    ],
    "sg:phone":"+1 760 434 2788",
    "sg:postcode":"92008",
    "sg:province":"CA",
    "sg:tags":[
        "shop",
        "smoke",
        "supply"
    ],
    "wof:name":"Hiland Gift & Tobacco",
    "wof:placetype":"venue"
},
  "geometry": {"coordinates":[-117.32684500000001,33.179488],"type":"Point"}
}