{
  "type": "Feature",
  "properties": {
    "addr:full":"13185 Sunlit Ct Moreno Valley CA 92553",
    "addr:housenumber":"13185",
    "addr:postcode":"92553",
    "addr:street":"Sunlit Ct",
    "iso:country":"US",
    "sg:address":"13185 Sunlit Ct",
    "sg:city":"Moreno Valley",
    "sg:classifiers":[
        {
            "category":"Shopping",
            "subcategory":"Musical Instruments",
            "type":"Retail Goods"
        }
    ],
    "sg:phone":"+1 951 653 3653",
    "sg:postcode":"92553",
    "sg:province":"CA",
    "wof:name":"Image West Guitars",
    "wof:placetype":"venue"
},
  "geometry": {"coordinates":[-117.251865,33.92842],"type":"Point"}
}