{
  "type": "Feature",
  "properties": {
    "iso:country":"US",
    "sg:address":"433 F St",
    "sg:city":"Davis",
    "sg:classifiers":[
        {
            "category":"Health Services",
            "subcategory":"Health Practitioner",
            "type":"Services"
        }
    ],
    "sg:phone":"+1 530 756 2502",
    "sg:postcode":"95616",
    "sg:province":"CA",
    "sg:tags":[
        "psychologist"
    ],
    "wof:name":"Hali Rowen PHD",
    "wof:placetype":"venue"
},
  "geometry": {"coordinates":[-121.741043,38.546872],"type":"Point"}
}