{
  "type": "Feature",
  "properties": {
    "addr:full":"11500 Meacham Rd Bakersfield CA 93312",
    "addr:housenumber":"11500",
    "addr:postcode":"93312",
    "addr:street":"Meacham Rd",
    "iso:country":"US",
    "sg:address":"11500 Meacham Rd",
    "sg:city":"Bakersfield",
    "sg:classifiers":[
        {
            "category":"Education",
            "subcategory":"School",
            "type":"Public Place"
        }
    ],
    "sg:phone":"+1 661 588 6040",
    "sg:postcode":"93312",
    "sg:province":"CA",
    "wof:name":"Rosedale North Elem School",
    "wof:placetype":"venue"
},
  "geometry": {"coordinates":[-119.13072099999999,35.390959],"type":"Point"}
}