{
  "type": "Feature",
  "properties": {
    "addr:full":"1645 Market St San Francisco CA 94103",
    "addr:housenumber":"1645",
    "addr:postcode":"94103",
    "addr:street":"Market St",
    "iso:country":"US",
    "sg:address":"1645 Market St",
    "sg:city":"San Francisco",
    "sg:classifiers":[
        {
            "category":"Shopping",
            "subcategory":"Used Merchandise",
            "type":"Retail Goods"
        }
    ],
    "sg:phone":"+1 415 621 6453",
    "sg:postcode":"94103",
    "sg:province":"CA",
    "sg:tags":[
        "antique"
    ],
    "wof:name":"Antiquario",
    "wof:placetype":"venue"
},
  "geometry": {"coordinates":[-122.419256,37.775147],"type":"Point"}
}