{
  "type": "Feature",
  "properties": {
    "addr:full":"2949 Dona Susana Dr Studio City CA 91604",
    "addr:housenumber":"2949",
    "addr:postcode":"91604",
    "addr:street":"Dona Susana Dr",
    "iso:country":"US",
    "sg:address":"2949 Dona Susana Dr",
    "sg:city":"Studio City",
    "sg:classifiers":[
        {
            "category":"Professional",
            "type":"Services"
        }
    ],
    "sg:phone":"+1 323 654 1776",
    "sg:postcode":"91604",
    "sg:province":"CA",
    "sg:tags":[
        "establishment"
    ],
    "wof:name":"Laverne Henebry",
    "wof:placetype":"venue"
},
  "geometry": {"coordinates":[-118.37590299999999,34.125654],"type":"Point"}
}