{
  "type": "Feature",
  "properties": {
    "addr:full":"12006 Gurley Ave Downey CA 90242",
    "addr:housenumber":"12006",
    "addr:postcode":"90242",
    "addr:street":"Gurley Ave",
    "iso:country":"US",
    "sg:address":"12006 Gurley Ave",
    "sg:city":"Downey",
    "sg:classifiers":[
        {
            "category":"Wholesale",
            "subcategory":"Stationery",
            "type":"Manufacturing & Wholesale Goods"
        },
        {
            "category":"Wholesale",
            "subcategory":"Non-durable Goods",
            "type":"Manufacturing & Wholesale Goods"
        }
    ],
    "sg:phone":"+1 562 862 8925",
    "sg:postcode":"90242",
    "sg:province":"CA",
    "sg:tags":[
        "box",
        "paper",
        "fiber"
    ],
    "wof:name":"Robinson Packaging and Display",
    "wof:placetype":"venue"
},
  "geometry": {"coordinates":[-118.14159100000001,33.929751],"type":"Point"}
}