{
  "type": "Feature",
  "properties": {
    "addr:full":"15723 Claretta Ave Norwalk CA 90650",
    "addr:housenumber":"15723",
    "addr:postcode":"90650",
    "addr:street":"Claretta Ave",
    "iso:country":"US",
    "sg:address":"15723 Claretta Ave",
    "sg:city":"Norwalk",
    "sg:classifiers":[
        {
            "category":"Shopping",
            "subcategory":"Computers & Home Electronics",
            "type":"Retail Goods"
        }
    ],
    "sg:phone":"+1 562 229 0955",
    "sg:postcode":"90650",
    "sg:province":"CA",
    "sg:tags":[
        "equipment",
        "electronic",
        "supply"
    ],
    "wof:name":"Rayco Inc",
    "wof:placetype":"venue"
},
  "geometry": {"coordinates":[-118.06864899999999,33.890202],"type":"Point"}
}