{
  "type": "Feature",
  "properties": {
    "addr:full":"569 N Mountain Ave Ste B Upland CA 91786",
    "addr:housenumber":"569",
    "addr:postcode":"91786",
    "addr:street":"N Mountain Ave Ste B",
    "iso:country":"US",
    "sg:address":"569 N Mountain Ave Ste B",
    "sg:city":"Upland",
    "sg:classifiers":[
        {
            "category":"Professional",
            "subcategory":"Business Services",
            "type":"Services"
        }
    ],
    "sg:phone":"+1 888 492 5129",
    "sg:postcode":"91786",
    "sg:province":"CA",
    "sg:tags":[
        "auction"
    ],
    "wof:name":"Orangebidz",
    "wof:placetype":"venue"
},
  "geometry": {"coordinates":[-117.670215,34.101073],"type":"Point"}
}