{
  "type": "Feature",
  "properties": {
    "iso:country":"US",
    "sg:address":"25672 Crown Valley Pkwy",
    "sg:city":"Ladera Ranch",
    "sg:classifiers":[
        {
            "category":"Restaurant",
            "type":"Food & Drink"
        }
    ],
    "sg:phone":"+1 949 347 8999",
    "sg:postcode":"92694",
    "sg:province":"CA",
    "sg:tags":[
        "pizza"
    ],
    "sg:website":"www.zpizza.com",
    "wof:name":"zPizza",
    "wof:placetype":"venue"
},
  "geometry": {"coordinates":[-117.631254,33.565988],"type":"Point"}
}