{
  "type": "Feature",
  "properties": {
    "addr:full":"13432 S Vermont Avenue Gardena CA 90247",
    "addr:housenumber":"13432",
    "addr:postcode":"90247",
    "addr:street":"S Vermont Avenue",
    "iso:country":"US",
    "sg:address":"13432 S Vermont Avenue",
    "sg:city":"Gardena",
    "sg:classifiers":[
        {
            "category":"Real Estate",
            "subcategory":"Real Estate Services",
            "type":"Services"
        },
        {
            "category":"Real Estate",
            "subcategory":"Real Estate Operator",
            "type":"Services"
        }
    ],
    "sg:phone":"+1 310 538 2478",
    "sg:postcode":"90247",
    "sg:province":"CA",
    "sg:tags":[
        "apartment",
        "property",
        "management"
    ],
    "wof:name":"Vermont Ave Apartments",
    "wof:placetype":"venue"
},
  "geometry": {"coordinates":[-118.291546,33.909888],"type":"Point"}
}