{
  "type": "Feature",
  "properties": {
    "iso:country":"US",
    "sg:address":"7546 E Clinton Ave",
    "sg:city":"Fresno",
    "sg:classifiers":[
        {
            "category":"Farming",
            "subcategory":"Livestock Farm",
            "type":"Manufacturing & Wholesale Goods"
        }
    ],
    "sg:phone":"+1 559 291 7238",
    "sg:postcode":"93727",
    "sg:province":"CA",
    "sg:tags":[
        "equine",
        "animal"
    ],
    "wof:name":"Childers Ranch",
    "wof:placetype":"venue"
},
  "geometry": {"coordinates":[-119.66305199999999,36.772209],"type":"Point"}
}