{
  "type": "Feature",
  "properties": {
    "addr:full":"17526 Hawthorne Blvd Torrance CA 90504",
    "addr:housenumber":"17526",
    "addr:postcode":"90504",
    "addr:street":"Hawthorne Blvd",
    "iso:country":"US",
    "sg:address":"17526 Hawthorne Blvd",
    "sg:city":"Torrance",
    "sg:classifiers":[
        {
            "category":"Shopping",
            "subcategory":"Clothing, Apparel, & Fashions",
            "type":"Retail Goods"
        }
    ],
    "sg:phone":"+1 310 214 0050",
    "sg:postcode":"90504",
    "sg:province":"CA",
    "wof:name":"J C Tailor Shop",
    "wof:placetype":"venue"
},
  "geometry": {"coordinates":[-118.352298,33.871413],"type":"Point"}
}