{
  "type": "Feature",
  "properties": {
    "iso:country":"US",
    "sg:address":"4205 Mowry Ave",
    "sg:city":"Fremont",
    "sg:classifiers":[
        {
            "category":"Travel",
            "subcategory":"Hotels & Motels",
            "type":"Entertainment"
        }
    ],
    "sg:phone":"+1 510 574 0632",
    "sg:postcode":"94538",
    "sg:province":"CA",
    "sg:tags":[
        "operation"
    ],
    "wof:name":"Dcm Data Systems Guest House",
    "wof:placetype":"venue"
},
  "geometry": {"coordinates":[-121.989994,37.54692],"type":"Point"}
}