{
  "type": "Feature",
  "properties": {
    "iso:country":"US",
    "sg:address":"34395 Yucaipa Blvd",
    "sg:city":"Yucaipa",
    "sg:classifiers":[
        {
            "category":"Personal",
            "subcategory":"Beauty Salon",
            "type":"Services"
        }
    ],
    "sg:phone":"+1 909 797 8343",
    "sg:postcode":"92399",
    "sg:province":"CA",
    "wof:name":"Ellen's Blvd Of Beauty",
    "wof:placetype":"venue"
},
  "geometry": {"coordinates":[-117.05417199999999,34.033875],"type":"Point"}
}