{
  "type": "Feature",
  "properties": {
    "addr:full":"3949 Bradford St La Verne CA 91750",
    "addr:housenumber":"3949",
    "addr:postcode":"91750",
    "addr:street":"Bradford St",
    "iso:country":"US",
    "sg:address":"3949 Bradford St",
    "sg:city":"La Verne",
    "sg:classifiers":[
        {
            "category":"Professional",
            "type":"Services"
        }
    ],
    "sg:phone":"+1 951 956 4679",
    "sg:postcode":"91750",
    "sg:province":"CA",
    "wof:name":"Sherwood Best",
    "wof:placetype":"venue"
},
  "geometry": {"coordinates":[-117.755143,34.112148],"type":"Point"}
}