{
  "type": "Feature",
  "properties": {
    "iso:country":"US",
    "sg:address":"8527 Elk Grove Blvd",
    "sg:city":"Elk Grove",
    "sg:classifiers":[
        {
            "category":"Restaurant",
            "type":"Food & Drink"
        }
    ],
    "sg:phone":"+1 916 686 4440",
    "sg:postcode":"95624",
    "sg:province":"CA",
    "wof:name":"Hunan Garden Restaurant",
    "wof:placetype":"venue"
},
  "geometry": {"coordinates":[-121.385186,38.40906],"type":"Point"}
}