{
  "type": "Feature",
  "properties": {
    "iso:country":"US",
    "sg:address":"1020 Old County Rd",
    "sg:city":"Belmont",
    "sg:classifiers":[
        {
            "category":"Retail",
            "subcategory":"Auto Repair",
            "type":"Services"
        }
    ],
    "sg:phone":"+1 650 591 8998",
    "sg:postcode":"94002",
    "sg:province":"CA",
    "sg:website":"www.kirbergmotors.com",
    "wof:name":"Kirberg Motors",
    "wof:placetype":"venue"
},
  "geometry": {"coordinates":[-122.275002,37.520699],"type":"Point"}
}