{
  "type": "Feature",
  "properties": {
    "addr:full":"3225 W Floradora Ave Fresno CA 93722",
    "addr:housenumber":"3225",
    "addr:postcode":"93722",
    "addr:street":"W Floradora Ave",
    "iso:country":"US",
    "sg:address":"3225 W Floradora Ave",
    "sg:city":"Fresno",
    "sg:classifiers":[
        {
            "category":"Building & Trades",
            "subcategory":"Landscaping Services",
            "type":"Services"
        }
    ],
    "sg:phone":"+1 559 681 0156",
    "sg:postcode":"93722",
    "sg:province":"CA",
    "sg:tags":[
        "lawn",
        "maintenance",
        "grounds"
    ],
    "wof:name":"Al Gardening Svc",
    "wof:placetype":"venue"
},
  "geometry": {"coordinates":[-119.852887,36.760939],"type":"Point"}
}