{
  "type": "Feature",
  "properties": {
    "iso:country":"US",
    "sg:address":"1575 Marshall St",
    "sg:city":"Redwood City",
    "sg:classifiers":[
        {
            "category":"Organizations",
            "subcategory":"Community Association",
            "type":"Services"
        }
    ],
    "sg:phone":"+1 650 361 9791",
    "sg:postcode":"94063",
    "sg:province":"CA",
    "wof:name":"Foe 418",
    "wof:placetype":"venue"
},
  "geometry": {"coordinates":[-122.220715,37.487766],"type":"Point"}
}