{
  "type": "Feature",
  "properties": {
    "addr:full":"3772 Mission Ave Ste R Oceanside CA 92054",
    "addr:housenumber":"3772",
    "addr:postcode":"92054",
    "addr:street":"Mission Ave Ste R",
    "iso:country":"US",
    "sg:address":"3772 Mission Ave Ste R",
    "sg:city":"Oceanside",
    "sg:classifiers":[
        {
            "category":"Restaurant",
            "type":"Food & Drink"
        }
    ],
    "sg:phone":"+1 760 757 4543",
    "sg:postcode":"92054",
    "sg:province":"CA",
    "wof:name":"Hong Xian Rice Queen",
    "wof:placetype":"venue"
},
  "geometry": {"coordinates":[-117.33200100000001,33.225399],"type":"Point"}
}