{
  "type": "Feature",
  "properties": {
    "iso:country":"US",
    "sg:address":"1633 S La Cienega Boulevard",
    "sg:city":"Los Angeles",
    "sg:classifiers":[
        {
            "category":"Retail",
            "subcategory":"Repair Shop",
            "type":"Services"
        }
    ],
    "sg:phone":"+1 323 655 5605",
    "sg:postcode":"90035",
    "sg:province":"CA",
    "sg:tags":[
        "reupholstery",
        "furniture"
    ],
    "wof:name":"Cosmos Upholstery",
    "wof:placetype":"venue"
},
  "geometry": {"coordinates":[-118.37604399999999,34.04799],"type":"Point"}
}