{
  "type": "Feature",
  "properties": {
    "iso:country":"US",
    "sg:address":"1644 Cerca Blanca Pl",
    "sg:city":"El Cajon",
    "sg:classifiers":[
        {
            "category":"Building & Trades",
            "subcategory":"Construction",
            "type":"Services"
        }
    ],
    "sg:phone":"+1 619 401 0467",
    "sg:postcode":"92019",
    "sg:province":"CA",
    "sg:tags":[
        "roofing",
        "contractor"
    ],
    "wof:name":"All Weather Roofing",
    "wof:placetype":"venue"
},
  "geometry": {"coordinates":[-116.92186,32.794387],"type":"Point"}
}