{
  "type": "Feature",
  "properties": {
    "iso:country":"US",
    "sg:address":"5400 Alcoa Ave",
    "sg:city":"Vernon",
    "sg:classifiers":[
        {
            "category":"Home & Garden",
            "subcategory":"Building Materials",
            "type":"Retail Goods"
        }
    ],
    "sg:phone":"+1 323 587 4173",
    "sg:postcode":"90058",
    "sg:province":"CA",
    "wof:name":"American Pacific Supply",
    "wof:placetype":"venue"
},
  "geometry": {"coordinates":[-118.208496,33.99642],"type":"Point"}
}