{
  "type": "Feature",
  "properties": {
    "addr:full":"99 N Bascom Ave San Jose CA 95128",
    "addr:housenumber":"99",
    "addr:postcode":"95128",
    "addr:street":"N Bascom Ave",
    "iso:country":"US",
    "sg:address":"99 N Bascom Ave",
    "sg:city":"San Jose",
    "sg:classifiers":[
        {
            "category":"Community Center",
            "subcategory":"Social",
            "type":"Public Place"
        },
        {
            "category":"Organizations",
            "subcategory":"Non-profit Organization",
            "type":"Services"
        }
    ],
    "sg:postcode":"95128",
    "sg:province":"CA",
    "sg:tags":[
        "club",
        "service/non-profit"
    ],
    "sg:website":"www.lionsclubs.org",
    "wof:name":"Lions Club",
    "wof:placetype":"venue"
},
  "geometry": {"coordinates":[-121.93301099999999,37.325417],"type":"Point"}
}