{
  "type": "Feature",
  "properties": {
    "addr:full":"7417 Van Nuys Blvd Van Nuys CA 91405",
    "addr:housenumber":"7417",
    "addr:postcode":"91405",
    "addr:street":"Van Nuys Blvd",
    "iso:country":"US",
    "sg:address":"7417 Van Nuys Blvd",
    "sg:city":"Van Nuys",
    "sg:classifiers":[
        {
            "category":"Organizations",
            "subcategory":"Religious Organization",
            "type":"Services"
        }
    ],
    "sg:phone":"+1 818 710 7633",
    "sg:postcode":"91405",
    "sg:province":"CA",
    "sg:tags":[
        "church"
    ],
    "wof:name":"Spiritualist Chapel Of Flowers",
    "wof:placetype":"venue"
},
  "geometry": {"coordinates":[-118.448837,34.205644],"type":"Point"}
}