{
  "type": "Feature",
  "properties": {
    "iso:country":"US",
    "sg:address":"1 Almaden Blvd",
    "sg:city":"San Jose",
    "sg:classifiers":[
        {
            "category":"Banks & Credit Unions",
            "subcategory":"Investment Brokerage",
            "type":"Services"
        }
    ],
    "sg:phone":"+1 408 288 8700",
    "sg:postcode":"95113",
    "sg:province":"CA",
    "sg:tags":[
        "investing"
    ],
    "sg:website":"www.wachoviasec.com",
    "wof:name":"Jarrett Brady, Financial Consultant",
    "wof:placetype":"venue"
},
  "geometry": {"coordinates":[-121.89529,37.333392],"type":"Point"}
}