{
  "type": "Feature",
  "properties": {
    "iso:country":"US",
    "sg:address":"3582 Jomar Dr",
    "sg:city":"Napa",
    "sg:classifiers":[
        {
            "category":"Professional",
            "subcategory":"Business Services",
            "type":"Services"
        }
    ],
    "sg:phone":"+1 707 255 9509",
    "sg:postcode":"94558",
    "sg:province":"CA",
    "sg:tags":[
        "organizing"
    ],
    "wof:name":"Organizing Strategies",
    "wof:placetype":"venue"
},
  "geometry": {"coordinates":[-122.322206,38.321401],"type":"Point"}
}