{
  "type": "Feature",
  "properties": {
    "addr:full":"110 S Rosemead Blvd Pasadena CA 91107",
    "addr:housenumber":"110",
    "addr:postcode":"91107",
    "addr:street":"S Rosemead Blvd",
    "iso:country":"US",
    "sg:address":"110 S Rosemead Blvd",
    "sg:city":"Pasadena",
    "sg:classifiers":[
        {
            "category":"Insurance",
            "subcategory":"Health Insurance",
            "type":"Services"
        }
    ],
    "sg:phone":"+1 626 683 8966",
    "sg:postcode":"91107",
    "sg:province":"CA",
    "sg:tags":[
        "market"
    ],
    "wof:name":"Vicare Group Inc",
    "wof:placetype":"venue"
},
  "geometry": {"coordinates":[-118.308767,34.144386],"type":"Point"}
}