{
  "type": "Feature",
  "properties": {
    "iso:country":"US",
    "sg:address":"383 Diablo Rd",
    "sg:city":"Danville",
    "sg:classifiers":[
        {
            "category":"Professional",
            "subcategory":"Business Services",
            "type":"Services"
        }
    ],
    "sg:phone":"+1 925 314 9700",
    "sg:postcode":"94526",
    "sg:province":"CA",
    "sg:tags":[
        "cashing",
        "protection",
        "check",
        "system"
    ],
    "sg:website":"www.e-paynow.com",
    "wof:name":"E-Paynow.Com",
    "wof:placetype":"venue"
},
  "geometry": {"coordinates":[-121.997753,37.822896],"type":"Point"}
}