{
  "type": "Feature",
  "properties": {
    "iso:country":"US",
    "sg:address":"4636 Geer Rd",
    "sg:city":"Hughson",
    "sg:classifiers":[
        {
            "category":"Manufacturing",
            "subcategory":"Pet Food",
            "type":"Manufacturing & Wholesale Goods"
        }
    ],
    "sg:phone":"+1 209 883 1163",
    "sg:postcode":"95326",
    "sg:province":"CA",
    "sg:tags":[
        "feed"
    ],
    "wof:name":"Nuwest Milling LLC",
    "wof:placetype":"venue"
},
  "geometry": {"coordinates":[-120.846972,37.574194],"type":"Point"}
}