{
  "type": "Feature",
  "properties": {
    "addr:full":"14796 Wicks Blvd San Leandro CA 94579",
    "addr:housenumber":"14796",
    "addr:postcode":"94579",
    "addr:street":"Wicks Blvd",
    "iso:country":"US",
    "sg:address":"14796 Wicks Blvd",
    "sg:city":"San Leandro",
    "sg:classifiers":[
        {
            "category":"Manufacturing",
            "subcategory":"Tools & Machinery",
            "type":"Manufacturing & Wholesale Goods"
        }
    ],
    "sg:phone":"+1 510 614 1151",
    "sg:postcode":"94579",
    "sg:province":"CA",
    "sg:tags":[
        "industrial",
        "parts",
        "mfg"
    ],
    "wof:name":"Cooper Energy Services",
    "wof:placetype":"venue"
},
  "geometry": {"coordinates":[-122.164394,37.696674],"type":"Point"}
}