{
  "type": "Feature",
  "properties": {
    "addr:full":"624 W 4th St San Bernardino CA 92410",
    "addr:housenumber":"624",
    "addr:postcode":"92410",
    "addr:street":"W 4Th St",
    "iso:country":"US",
    "sg:address":"624 W 4th St",
    "sg:city":"San Bernardino",
    "sg:classifiers":[
        {
            "category":"Food & Beverages",
            "subcategory":"Bakery",
            "type":"Retail Goods"
        }
    ],
    "sg:phone":"+1 909 888 6572",
    "sg:postcode":"92410",
    "sg:province":"CA",
    "sg:tags":[
        "baker"
    ],
    "wof:name":"Carousel Bakery",
    "wof:placetype":"venue"
},
  "geometry": {"coordinates":[-117.298143,34.106491],"type":"Point"}
}