{
  "type": "Feature",
  "properties": {
    "iso:country":"US",
    "sg:address":"1933 S Broadway",
    "sg:city":"Los Angeles",
    "sg:classifiers":[
        {
            "category":"Building & Trades",
            "subcategory":"Construction",
            "type":"Services"
        }
    ],
    "sg:phone":"+1 310 270 5301",
    "sg:postcode":"90007",
    "sg:province":"CA",
    "sg:tags":[
        "interior",
        "designer"
    ],
    "wof:name":"Charlie Platero Jr",
    "wof:placetype":"venue"
},
  "geometry": {"coordinates":[-118.266982,34.02979],"type":"Point"}
}