{
  "type": "Feature",
  "properties": {
    "iso:country":"US",
    "sg:address":"25600 Encinal Rd",
    "sg:city":"Salinas",
    "sg:classifiers":[
        {
            "category":"Farming",
            "subcategory":"Nursery",
            "type":"Manufacturing & Wholesale Goods"
        }
    ],
    "sg:phone":"+1 831 758 2827",
    "sg:postcode":"93908",
    "sg:province":"CA",
    "sg:tags":[
        "greenhouse"
    ],
    "wof:name":"Fumi Greenhouse",
    "wof:placetype":"venue"
},
  "geometry": {"coordinates":[-121.509252,36.620047],"type":"Point"}
}