{
  "type": "Feature",
  "properties": {
    "addr:full":"430 Winton Ave Hayward CA 94544",
    "addr:housenumber":"430",
    "addr:postcode":"94544",
    "addr:street":"Winton Ave",
    "iso:country":"US",
    "sg:address":"430 Winton Ave",
    "sg:city":"Hayward",
    "sg:classifiers":[
        {
            "category":"Food & Beverages",
            "subcategory":"Bakery",
            "type":"Retail Goods"
        }
    ],
    "sg:phone":"+1 510 537 0108",
    "sg:postcode":"94544",
    "sg:province":"CA",
    "sg:tags":[
        "donut",
        "doughnut"
    ],
    "sg:website":"510donutexpress.com/",
    "wof:name":"Donut Express",
    "wof:placetype":"venue"
},
  "geometry": {"coordinates":[-122.084,37.662899],"type":"Point"}
}