{
  "type": "Feature",
  "properties": {
    "iso:country":"US",
    "sg:address":"1201 Grove Ave",
    "sg:city":"Atwater",
    "sg:classifiers":[
        {
            "category":"Organizations",
            "subcategory":"Membership Organization",
            "type":"Services"
        }
    ],
    "sg:phone":"+1 209 356 0388",
    "sg:postcode":"95301",
    "sg:province":"CA",
    "wof:name":"Atwater Women's Club",
    "wof:placetype":"venue"
},
  "geometry": {"coordinates":[-120.608123,37.351279],"type":"Point"}
}