{
  "type": "Feature",
  "properties": {
    "addr:full":"4525 Industrial St Simi Valley CA 93063",
    "addr:housenumber":"4525",
    "addr:postcode":"93063",
    "addr:street":"Industrial St",
    "iso:country":"US",
    "sg:address":"4525 Industrial St",
    "sg:city":"Simi Valley",
    "sg:classifiers":[
        {
            "category":"Wholesale",
            "subcategory":"Machinery & Supplies",
            "type":"Manufacturing & Wholesale Goods"
        }
    ],
    "sg:phone":"+1 805 522 9845",
    "sg:postcode":"93063",
    "sg:province":"CA",
    "sg:tags":[
        "equipment",
        "industrial"
    ],
    "wof:name":"Control Enterprises Inc",
    "wof:placetype":"venue"
},
  "geometry": {"coordinates":[-118.703164,34.273336],"type":"Point"}
}