{
  "type": "Feature",
  "properties": {
    "iso:country":"US",
    "sg:address":"24011 Ventura Blvd",
    "sg:city":"Calabasas",
    "sg:classifiers":[
        {
            "category":"Professional",
            "type":"Services"
        }
    ],
    "sg:phone":"+1 310 774 7462",
    "sg:postcode":"91302",
    "sg:province":"CA",
    "sg:tags":[
        "establishment"
    ],
    "wof:name":"Raven Drum Foundation",
    "wof:placetype":"venue"
},
  "geometry": {"coordinates":[-118.65020699999999,34.154858],"type":"Point"}
}