{
  "type": "Feature",
  "properties": {
    "iso:country":"US",
    "sg:address":"1533 S Broadway",
    "sg:city":"Santa Maria",
    "sg:classifiers":[
        {
            "category":"Food & Beverages",
            "subcategory":"Specialty",
            "type":"Retail Goods"
        },
        {
            "category":"Shopping",
            "type":"Retail Goods"
        }
    ],
    "sg:phone":"+1 805 925 1202",
    "sg:postcode":"93454",
    "sg:province":"CA",
    "sg:tags":[
        "bulk",
        "water",
        "company",
        "direct",
        "merchandise"
    ],
    "sg:website":"www.wateroutlet.com",
    "wof:name":"Pure Water Outlet",
    "wof:placetype":"venue"
},
  "geometry": {"coordinates":[-120.436189,34.933262],"type":"Point"}
}