{
  "type": "Feature",
  "properties": {
    "iso:country":"US",
    "sg:address":"9150 W Pico Blvd",
    "sg:city":"Los Angeles",
    "sg:classifiers":[
        {
            "category":"Retail",
            "subcategory":"Laundry & Dry Cleaning",
            "type":"Services"
        }
    ],
    "sg:phone":"+1 213 253 2637",
    "sg:postcode":"90035",
    "sg:province":"CA",
    "wof:name":"Valet Dry Cleaners",
    "wof:placetype":"venue"
},
  "geometry": {"coordinates":[-118.390999,34.055401],"type":"Point"}
}