{
  "type": "Feature",
  "properties": {
    "iso:country":"US",
    "sg:address":"8618 Garfield Ave",
    "sg:city":"South Gate",
    "sg:classifiers":[
        {
            "category":"Fast Food",
            "type":"Food & Drink"
        },
        {
            "category":"Restaurant",
            "type":"Food & Drink"
        }
    ],
    "sg:phone":"+1 562 928 8341",
    "sg:postcode":"90280",
    "sg:province":"CA",
    "sg:tags":[
        "american",
        "latin"
    ],
    "sg:website":"www.campero.com",
    "wof:name":"Pollo Campero",
    "wof:placetype":"venue"
},
  "geometry": {"coordinates":[-118.163895,33.952847],"type":"Point"}
}