{
  "type": "Feature",
  "properties": {
    "addr:full":"1425 Koll Cir San Jose CA 95112",
    "addr:postcode":"1425;95112",
    "addr:street":"Koll Cir",
    "iso:country":"US",
    "sg:address":"1425 Koll Cir",
    "sg:city":"San Jose",
    "sg:classifiers":[
        {
            "category":"Wholesale",
            "subcategory":"Furniture",
            "type":"Manufacturing & Wholesale Goods"
        }
    ],
    "sg:phone":"+1 408 441 0815",
    "sg:postcode":"95112",
    "sg:province":"CA",
    "wof:name":"Modular In Motion",
    "wof:placetype":"venue"
},
  "geometry": {"coordinates":[-121.906909,37.366173],"type":"Point"}
}