{
  "type": "Feature",
  "properties": {
    "addr:full":"350 Brannan St San Francisco CA 94107",
    "addr:housenumber":"350",
    "addr:postcode":"94107",
    "addr:street":"Brannan St",
    "iso:country":"US",
    "sg:address":"350 Brannan St",
    "sg:city":"San Francisco",
    "sg:classifiers":[
        {
            "category":"Professional",
            "subcategory":"Engineering",
            "type":"Services"
        }
    ],
    "sg:phone":"+1 415 764 1675",
    "sg:postcode":"94107",
    "sg:province":"CA",
    "sg:tags":[
        "engineer"
    ],
    "wof:name":"Bell Associates Irrigation",
    "wof:placetype":"venue"
},
  "geometry": {"coordinates":[-122.393607,37.780637],"type":"Point"}
}