{
  "type": "Feature",
  "properties": {
    "iso:country":"US",
    "sg:address":"1450 4th St",
    "sg:city":"Berkeley",
    "sg:classifiers":[
        {
            "category":"Real Estate",
            "subcategory":"Architect",
            "type":"Services"
        }
    ],
    "sg:phone":"+1 415 621 6597",
    "sg:postcode":"94710",
    "sg:province":"CA",
    "sg:website":"www.loomstudio.com",
    "wof:name":"Loom",
    "wof:placetype":"venue"
},
  "geometry": {"coordinates":[-122.302402,37.875152],"type":"Point"}
}