{
  "type": "Feature",
  "properties": {
    "addr:full":"711 N Broadway Los Angeles CA 90012",
    "addr:housenumber":"711",
    "addr:postcode":"90012",
    "addr:street":"N Broadway",
    "iso:country":"US",
    "sg:address":"711 N Broadway",
    "sg:city":"Los Angeles",
    "sg:classifiers":[
        {
            "category":"Shopping",
            "subcategory":"Music",
            "type":"Retail Goods"
        }
    ],
    "sg:phone":"+1 213 621 4434",
    "sg:postcode":"90012",
    "sg:province":"CA",
    "sg:tags":[
        "compact",
        "record",
        "disc",
        "tape"
    ],
    "wof:name":"Hoa Bien",
    "wof:placetype":"venue"
},
  "geometry": {"coordinates":[-118.238463,34.06216],"type":"Point"}
}