{
  "type": "Feature",
  "properties": {
    "addr:full":"166 Geary Street Suite 1207 San Francisco CA 94108",
    "addr:housenumber":"166",
    "addr:postcode":"94108",
    "addr:street":"Geary Street Suite 1207",
    "iso:country":"US",
    "sg:address":"166 Geary Street Suite 1207",
    "sg:city":"San Francisco",
    "sg:classifiers":[
        {
            "category":"Personal",
            "subcategory":"Beauty Salon",
            "type":"Services"
        }
    ],
    "sg:phone":"+1 415 397 5505",
    "sg:postcode":"94108",
    "sg:province":"CA",
    "sg:tags":[
        "hair"
    ],
    "wof:name":"Alex Chases Salon",
    "wof:placetype":"venue"
},
  "geometry": {"coordinates":[-122.405998,37.7878],"type":"Point"}
}