{
  "type": "Feature",
  "properties": {
    "addr:full":"2627 N Blackstone Ave Fresno CA 93704",
    "addr:housenumber":"2627",
    "addr:postcode":"93704",
    "addr:street":"N Blackstone Ave",
    "iso:country":"US",
    "sg:address":"2627 N Blackstone Ave",
    "sg:city":"Fresno",
    "sg:classifiers":[
        {
            "category":"Autos & Motor Vehicles",
            "subcategory":"Automobile Sales",
            "type":"Retail Goods"
        }
    ],
    "sg:phone":"+1 559 237 3700",
    "sg:postcode":"93704",
    "sg:province":"CA",
    "sg:tags":[
        "car",
        "dealer"
    ],
    "wof:name":"Auto Barn",
    "wof:placetype":"venue"
},
  "geometry": {"coordinates":[-119.790609,36.774754],"type":"Point"}
}