{
  "type": "Feature",
  "properties": {
    "iso:country":"US",
    "sg:address":"1653 Nelson Ave",
    "sg:city":"Manhattan Beach",
    "sg:classifiers":[
        {
            "category":"Manufacturing",
            "subcategory":"Chemicals & Compounds",
            "type":"Manufacturing & Wholesale Goods"
        }
    ],
    "sg:phone":"+1 310 376 2121",
    "sg:postcode":"90266",
    "sg:province":"CA",
    "sg:tags":[
        "preparation",
        "pharmaceutical",
        "mfg"
    ],
    "wof:name":"Aaron Industries Inc",
    "wof:placetype":"venue"
},
  "geometry": {"coordinates":[-118.383925,33.874828],"type":"Point"}
}