{
  "type": "Feature",
  "properties": {
    "addr:full":"2223 Market St. San Francisco CA",
    "addr:housenumber":"2223",
    "addr:street":"market st.",
    "iso:country":"US",
    "wof:name":"Nomica",
    "wof:placetype":"venue"
},
  "geometry": {"coordinates":[-122.431409,37.765084],"type":"Point"}
}