{
  "type": "Feature",
  "properties": {
    "addr:full":"361 Ely Rd N Petaluma CA 94954",
    "addr:housenumber":"361",
    "addr:postcode":"94954",
    "addr:street":"Ely Rd N",
    "iso:country":"US",
    "sg:address":"361 Ely Rd N",
    "sg:city":"Petaluma",
    "sg:classifiers":[
        {
            "category":"Professional",
            "subcategory":"Business Services",
            "type":"Services"
        }
    ],
    "sg:phone":"+1 707 778 7735",
    "sg:postcode":"94954",
    "sg:province":"CA",
    "sg:tags":[
        "consultant",
        "coach"
    ],
    "wof:name":"Russell N Morita",
    "wof:placetype":"venue"
},
  "geometry": {"coordinates":[-122.656999,38.277907],"type":"Point"}
}