{
  "type": "Feature",
  "properties": {
    "addr:full":"7247 Rosemead Blvd San Gabriel CA 91775",
    "addr:housenumber":"7247",
    "addr:postcode":"91775",
    "addr:street":"Rosemead Blvd",
    "iso:country":"US",
    "sg:address":"7247 Rosemead Blvd",
    "sg:city":"San Gabriel",
    "sg:classifiers":[
        {
            "category":"Restaurant",
            "type":"Food & Drink"
        }
    ],
    "sg:phone":"+1 626 286 3579",
    "sg:postcode":"91775",
    "sg:province":"CA",
    "sg:tags":[
        "steakhouse"
    ],
    "sg:website":"www.clearmansrestaurants.com/nor...",
    "wof:name":"Clearman's North Woods Inn",
    "wof:placetype":"venue"
},
  "geometry": {"coordinates":[-118.073263,34.128987],"type":"Point"}
}