{
  "type": "Feature",
  "properties": {
    "addr:full":"3001 Macedo Way Sacramento CA 95826",
    "addr:housenumber":"3001",
    "addr:postcode":"95826",
    "addr:street":"Macedo Way",
    "iso:country":"US",
    "sg:address":"3001 Macedo Way",
    "sg:city":"Sacramento",
    "sg:classifiers":[
        {
            "category":"Real Estate",
            "subcategory":"Real Estate Operator",
            "type":"Services"
        }
    ],
    "sg:phone":"+1 916 921 5965",
    "sg:postcode":"95826",
    "sg:province":"CA",
    "sg:tags":[
        "mall",
        "shopping",
        "center"
    ],
    "sg:website":"www.sacramentomarketplace.net",
    "wof:name":"SACRAMENTOMARKETPLACE.NET",
    "wof:placetype":"venue"
},
  "geometry": {"coordinates":[-121.363511,38.558082],"type":"Point"}
}