{
  "type": "Feature",
  "properties": {
    "iso:country":"US",
    "sg:address":"12029 Ranchito St",
    "sg:city":"El Monte",
    "sg:classifiers":[
        {
            "category":"Shopping",
            "subcategory":"Computers & Home Electronics",
            "type":"Retail Goods"
        }
    ],
    "sg:phone":"+1 626 442 8618",
    "sg:postcode":"91732",
    "sg:province":"CA",
    "sg:tags":[
        "audio"
    ],
    "wof:name":"Dreamzs Etc",
    "wof:placetype":"venue"
},
  "geometry": {"coordinates":[-118.007174,34.086249],"type":"Point"}
}