{
  "type": "Feature",
  "properties": {
    "addr:full":"16952 Ventura Blvd Encino CA 91316",
    "addr:housenumber":"16952",
    "addr:postcode":"91316",
    "addr:street":"Ventura Blvd",
    "iso:country":"US",
    "sg:address":"16952 Ventura Blvd",
    "sg:city":"Encino",
    "sg:classifiers":[
        {
            "category":"Communications",
            "subcategory":"Film & Video Production",
            "type":"Services"
        }
    ],
    "sg:phone":"+1 818 981 6556",
    "sg:postcode":"91316",
    "sg:province":"CA",
    "sg:tags":[
        "taping"
    ],
    "sg:website":"www.imageresources.net",
    "wof:name":"Image Resources Film & Video",
    "wof:placetype":"venue"
},
  "geometry": {"coordinates":[-118.502967,34.159605],"type":"Point"}
}