{
  "type": "Feature",
  "properties": {
    "iso:country":"US",
    "sg:address":"39345 10th St W",
    "sg:city":"Palmdale",
    "sg:classifiers":[
        {
            "category":"Health Services",
            "subcategory":"Doctor",
            "type":"Services"
        }
    ],
    "sg:phone":"+1 661 274 8065",
    "sg:postcode":"93551",
    "sg:province":"CA",
    "sg:tags":[
        "dentist"
    ],
    "wof:name":"Bright Now Dental",
    "wof:placetype":"venue"
},
  "geometry": {"coordinates":[-118.147657,34.595882],"type":"Point"}
}