{
  "type": "Feature",
  "properties": {
    "iso:country":"US",
    "sg:address":"2605 W Olympic Blvd",
    "sg:city":"Los Angeles",
    "sg:classifiers":[
        {
            "category":"Building & Trades",
            "subcategory":"Construction",
            "type":"Services"
        }
    ],
    "sg:phone":"+1 310 644 7766",
    "sg:postcode":"90006",
    "sg:province":"CA",
    "sg:tags":[
        "painter"
    ],
    "wof:name":"Southland Construction",
    "wof:placetype":"venue"
},
  "geometry": {"coordinates":[-118.288927,34.052481],"type":"Point"}
}