{
  "type": "Feature",
  "properties": {
    "iso:country":"US",
    "sg:address":"8016 California City Blvd",
    "sg:city":"California City",
    "sg:classifiers":[
        {
            "category":"Health Services",
            "subcategory":"Health Practitioner",
            "type":"Services"
        }
    ],
    "sg:phone":"+1 760 373 2958",
    "sg:postcode":"93505",
    "sg:province":"CA",
    "sg:tags":[
        "nutrition",
        "consultant"
    ],
    "wof:name":"Valley Caregiver Resource",
    "wof:placetype":"venue"
},
  "geometry": {"coordinates":[-117.985378,35.125733],"type":"Point"}
}