{
  "type": "Feature",
  "properties": {
    "iso:country":"US",
    "sg:address":"36523 25th St E",
    "sg:city":"Palmdale",
    "sg:classifiers":[
        {
            "category":"Real Estate",
            "subcategory":"Real Estate Operator",
            "type":"Services"
        }
    ],
    "sg:phone":"+1 661 266 2997",
    "sg:postcode":"93550",
    "sg:province":"CA",
    "sg:tags":[
        "apartment"
    ],
    "wof:name":"Longhorn Pavilion Apartments",
    "wof:placetype":"venue"
},
  "geometry": {"coordinates":[-118.084254,34.545236],"type":"Point"}
}