{
  "type": "Feature",
  "properties": {
    "iso:country":"US",
    "sg:address":"249 Muir Ct",
    "sg:city":"Upland",
    "sg:classifiers":[
        {
            "category":"Manufacturing",
            "subcategory":"Printing",
            "type":"Manufacturing & Wholesale Goods"
        }
    ],
    "sg:phone":"+1 951 440 8807",
    "sg:postcode":"91784",
    "sg:province":"CA",
    "sg:tags":[
        "commercial"
    ],
    "wof:name":"Warren Letter Press",
    "wof:placetype":"venue"
},
  "geometry": {"coordinates":[-117.64751,34.137353],"type":"Point"}
}