{
  "type": "Feature",
  "properties": {
    "addr:full":"8435 Rincon Ave Sun Valley CA 91352",
    "addr:housenumber":"8435",
    "addr:postcode":"91352",
    "addr:street":"Rincon Ave",
    "iso:country":"US",
    "sg:address":"8435 Rincon Ave",
    "sg:city":"Sun Valley",
    "sg:classifiers":[
        {
            "category":"Freight",
            "type":"Transportation"
        }
    ],
    "sg:phone":"+1 818 392 7665",
    "sg:postcode":"91352",
    "sg:province":"CA",
    "sg:tags":[
        "trucking"
    ],
    "wof:name":"Hm Trucking",
    "wof:placetype":"venue"
},
  "geometry": {"coordinates":[-118.392844,34.22304],"type":"Point"}
}