{
  "type": "Feature",
  "properties": {
    "iso:country":"US",
    "sg:address":"10347 Folsom Blvd",
    "sg:city":"Rancho Cordova",
    "sg:classifiers":[
        {
            "category":"Shopping",
            "subcategory":"Department Store",
            "type":"Retail Goods"
        }
    ],
    "sg:phone":"+1 916 361 8312",
    "sg:postcode":"95670",
    "sg:province":"CA",
    "wof:name":"Sears Roebuck & Co",
    "wof:placetype":"venue"
},
  "geometry": {"coordinates":[-121.304801,38.588003],"type":"Point"}
}