{
  "type": "Feature",
  "properties": {
    "addr:full":"84 Fortuna Avenue San Francisco CA 94115",
    "addr:housenumber":"84",
    "addr:postcode":"94115",
    "addr:street":"Fortuna Avenue",
    "iso:country":"US",
    "sg:address":"84 Fortuna Avenue",
    "sg:city":"San Francisco",
    "sg:classifiers":[
        {
            "category":"Professional",
            "subcategory":"Accounting & Tax Preparation",
            "type":"Services"
        }
    ],
    "sg:phone":"+1 415 441 3774",
    "sg:postcode":"94115",
    "sg:province":"CA",
    "sg:tags":[
        "accountant"
    ],
    "wof:name":"Collier David E CPA",
    "wof:placetype":"venue"
},
  "geometry": {"coordinates":[-122.44281599999999,37.781418],"type":"Point"}
}