{
  "type": "Feature",
  "properties": {
    "iso:country":"US",
    "sg:address":"6150 Stevenson Blvd.",
    "sg:city":"Fremont",
    "sg:classifiers":[
        {
            "category":"Professional",
            "subcategory":"Computer Services",
            "type":"Services"
        }
    ],
    "sg:postcode":"94538",
    "sg:province":"CA",
    "sg:tags":[
        "ethernet",
        "copper",
        "eoc",
        "backhaul",
        "access",
        "broadband"
    ],
    "sg:website":"http://www.actelis.com/",
    "wof:name":"Actelis Networks",
    "wof:placetype":"venue"
},
  "geometry": {"coordinates":[-121.99077699999999,37.518972],"type":"Point"}
}