{
  "type": "Feature",
  "properties": {
    "addr:full":"9743 Abilene St Rosemead CA 91770",
    "addr:housenumber":"9743",
    "addr:postcode":"91770",
    "addr:street":"Abilene St",
    "iso:country":"US",
    "sg:address":"9743 Abilene St",
    "sg:city":"Rosemead",
    "sg:classifiers":[
        {
            "category":"Restaurant",
            "type":"Food & Drink"
        }
    ],
    "sg:phone":"+1 626 350 6827",
    "sg:postcode":"91770",
    "sg:province":"CA",
    "sg:tags":[
        "eating"
    ],
    "wof:name":"Piccolo Italiano Rest & Bar",
    "wof:placetype":"venue"
},
  "geometry": {"coordinates":[-118.056641,34.082642],"type":"Point"}
}