{
  "type": "Feature",
  "properties": {
    "addr:full":"650 Mission St San Francisco CA 94105",
    "addr:housenumber":"650",
    "addr:postcode":"94105",
    "addr:street":"Mission St",
    "iso:country":"US",
    "sg:address":"650 Mission St",
    "sg:city":"San Francisco",
    "sg:classifiers":[
        {
            "category":"Personal",
            "type":"Services"
        }
    ],
    "sg:phone":"+1 510 864 1900",
    "sg:postcode":"94105",
    "sg:province":"CA",
    "sg:tags":[
        "mover"
    ],
    "sg:website":"www.tomcatmoving.com",
    "wof:name":"Tomcat Moving and Hauling",
    "wof:placetype":"venue"
},
  "geometry": {"coordinates":[-122.401037,37.787186],"type":"Point"}
}