{
  "type": "Feature",
  "properties": {
    "addr:full":"9522 Palomino Trl Browns Valley CA 95918",
    "addr:housenumber":"9522",
    "addr:postcode":"valley ca 95918",
    "addr:street":"Palomino Trl Browns",
    "iso:country":"US",
    "sg:address":"9522 Palomino Trl",
    "sg:city":"Browns Valley",
    "sg:classifiers":[
        {
            "category":"Professional",
            "type":"Services"
        }
    ],
    "sg:phone":"+1 530 639 0431",
    "sg:postcode":"95918",
    "sg:province":"CA",
    "wof:name":"Timothy J Dierks",
    "wof:placetype":"venue"
},
  "geometry": {"coordinates":[-121.358831,39.234922],"type":"Point"}
}