{
  "type": "Feature",
  "properties": {
    "addr:full":"8756 Gemstone Ct Elk Grove CA 95624",
    "addr:housenumber":"8756",
    "addr:postcode":"95624",
    "addr:street":"Gemstone Ct",
    "iso:country":"US",
    "sg:address":"8756 Gemstone Ct",
    "sg:city":"Elk Grove",
    "sg:classifiers":[
        {
            "category":"Insurance",
            "subcategory":"Insurance Agent",
            "type":"Services"
        }
    ],
    "sg:phone":"+1 916 686 5009",
    "sg:postcode":"95624",
    "sg:province":"CA",
    "wof:name":"Steven Payne",
    "wof:placetype":"venue"
},
  "geometry": {"coordinates":[-121.377291,38.406421],"type":"Point"}
}