{
  "type": "Feature",
  "properties": {
    "addr:full":"223 E Newfield St Gardena CA 90248",
    "addr:housenumber":"223",
    "addr:postcode":"90248",
    "addr:street":"E Newfield St",
    "iso:country":"US",
    "sg:address":"223 E Newfield St",
    "sg:city":"Gardena",
    "sg:classifiers":[
        {
            "category":"Place Of Worship",
            "type":"Public Place"
        }
    ],
    "sg:phone":"+1 310 630 4863",
    "sg:postcode":"90248",
    "sg:province":"CA",
    "sg:tags":[
        "church"
    ],
    "wof:name":"Freddy Iglesias",
    "wof:placetype":"venue"
},
  "geometry": {"coordinates":[-118.27315299999999,33.888641],"type":"Point"}
}