{
  "type": "Feature",
  "properties": {
    "iso:country":"US",
    "sg:address":"43862 15th St W",
    "sg:city":"Lancaster",
    "sg:classifiers":[
        {
            "category":"Restaurant",
            "type":"Food & Drink"
        }
    ],
    "sg:phone":"+1 661 729 6050",
    "sg:postcode":"93534",
    "sg:province":"CA",
    "wof:name":"Hernandez Home Cooking",
    "wof:placetype":"venue"
},
  "geometry": {"coordinates":[-118.156685,34.682123],"type":"Point"}
}