{
  "type": "Feature",
  "properties": {
    "addr:full":"24602 Raymond Way Ste S Lake Forest CA 92630",
    "addr:housenumber":"24602",
    "addr:postcode":"92630",
    "addr:street":"Raymond Way Ste S",
    "iso:country":"US",
    "sg:address":"24602 Raymond Way Ste S",
    "sg:city":"Lake Forest",
    "sg:classifiers":[
        {
            "category":"Food & Beverages",
            "subcategory":"Groceries & Convenience Stores",
            "type":"Retail Goods"
        }
    ],
    "sg:phone":"+1 949 588 0241",
    "sg:postcode":"92630",
    "sg:province":"CA",
    "wof:name":"Hierro's Market",
    "wof:placetype":"venue"
},
  "geometry": {"coordinates":[-117.701714,33.622005],"type":"Point"}
}