{
  "type": "Feature",
  "properties": {
    "addr:full":"202 N Garfield Ave Ste A Monterey Park CA 91754",
    "addr:housenumber":"202",
    "addr:postcode":"91754",
    "addr:street":"N Garfield Ave Ste A",
    "iso:country":"US",
    "sg:address":"202 N Garfield Ave Ste A",
    "sg:city":"Monterey Park",
    "sg:classifiers":[
        {
            "category":"Health Services",
            "subcategory":"Chiropractor",
            "type":"Services"
        }
    ],
    "sg:phone":"+1 626 571 6680",
    "sg:postcode":"91754",
    "sg:province":"CA",
    "wof:name":"Wong Bertram D DC",
    "wof:placetype":"venue"
},
  "geometry": {"coordinates":[-118.122213,34.063727],"type":"Point"}
}