{
  "type": "Feature",
  "properties": {
    "iso:country":"US",
    "sg:address":"13161 Sherman Way Unit C",
    "sg:city":"North Hollywood",
    "sg:classifiers":[
        {
            "category":"Professional",
            "subcategory":"Business Services",
            "type":"Services"
        }
    ],
    "sg:phone":"+1 818 764 8111",
    "sg:postcode":"91605",
    "sg:province":"CA",
    "sg:tags":[
        "delivery",
        "courier"
    ],
    "wof:name":"Delivery Associates Inc",
    "wof:placetype":"venue"
},
  "geometry": {"coordinates":[-118.41982400000001,34.201212],"type":"Point"}
}