{
  "type": "Feature",
  "properties": {
    "addr:full":"1300 S College Dr Santa Maria CA 93454",
    "addr:housenumber":"1300",
    "addr:postcode":"93454",
    "addr:street":"S College Dr",
    "iso:country":"US",
    "sg:address":"1300 S College Dr",
    "sg:city":"Santa Maria",
    "sg:classifiers":[
        {
            "category":"Education",
            "subcategory":"College",
            "type":"Public Place"
        }
    ],
    "sg:phone":"+1 805 928 7731",
    "sg:postcode":"93454",
    "sg:province":"CA",
    "sg:tags":[
        "academic",
        "school"
    ],
    "wof:name":"Allan Hancock College",
    "wof:placetype":"venue"
},
  "geometry": {"coordinates":[-120.424904,34.937478],"type":"Point"}
}