{
  "type": "Feature",
  "properties": {
    "iso:country":"US",
    "sg:address":"110 Main St",
    "sg:city":"Rio Vista",
    "sg:classifiers":[
        {
            "category":"Bars & Pubs",
            "type":"Food & Drink"
        }
    ],
    "sg:phone":"+1 707 374 2473",
    "sg:postcode":"94571",
    "sg:province":"CA",
    "wof:name":"Flamingo Lounge",
    "wof:placetype":"venue"
},
  "geometry": {"coordinates":[-121.691472,38.156529],"type":"Point"}
}