{
  "type": "Feature",
  "properties": {
    "iso:country":"US",
    "sg:address":"13157 Terra Bella St",
    "sg:city":"Pacoima",
    "sg:classifiers":[
        {
            "category":"Shopping",
            "subcategory":"Clothing, Apparel, & Fashions",
            "type":"Retail Goods"
        }
    ],
    "sg:phone":"+1 818 497 3639",
    "sg:postcode":"91331",
    "sg:province":"CA",
    "sg:tags":[
        "handbag"
    ],
    "wof:name":"Stylish Handbags",
    "wof:placetype":"venue"
},
  "geometry": {"coordinates":[-118.41944700000001,34.257473],"type":"Point"}
}