{
  "type": "Feature",
  "properties": {
    "addr:full":"8188 Plumeria Ave Fair Oaks CA 95628",
    "addr:housenumber":"8188",
    "addr:postcode":"95628",
    "addr:street":"Plumeria Ave",
    "iso:country":"US",
    "sg:address":"8188 Plumeria Ave",
    "sg:city":"Fair Oaks",
    "sg:classifiers":[
        {
            "category":"Professional",
            "subcategory":"Computer Services",
            "type":"Services"
        }
    ],
    "sg:phone":"+1 916 965 0704",
    "sg:postcode":"95628",
    "sg:province":"CA",
    "sg:tags":[
        "related"
    ],
    "wof:name":"Jmc Internetworking",
    "wof:placetype":"venue"
},
  "geometry": {"coordinates":[-121.25977899999999,38.650641],"type":"Point"}
}