{
  "type": "Feature",
  "properties": {
    "iso:country":"US",
    "sg:address":"16141 Hart St",
    "sg:city":"Van Nuys",
    "sg:classifiers":[
        {
            "category":"Home & Garden",
            "subcategory":"Household Appliances",
            "type":"Retail Goods"
        }
    ],
    "sg:phone":"+1 818 376 0940",
    "sg:postcode":"91406",
    "sg:province":"CA",
    "sg:tags":[
        "machine"
    ],
    "sg:website":"www.autochlorsystem.com",
    "wof:name":"Auto-Chlor System",
    "wof:placetype":"venue"
},
  "geometry": {"coordinates":[-118.485102,34.197607],"type":"Point"}
}