{
  "type": "Feature",
  "properties": {
    "iso:country":"US",
    "sg:address":"101 The Embarcadero",
    "sg:city":"San Francisco",
    "sg:classifiers":[
        {
            "category":"Wholesale",
            "subcategory":"Durable Goods & Equipment",
            "type":"Manufacturing & Wholesale Goods"
        }
    ],
    "sg:phone":"+1 415 391 3952",
    "sg:postcode":"94105",
    "sg:province":"CA",
    "sg:tags":[
        "mfg"
    ],
    "wof:name":"Mm Manufacturing",
    "wof:placetype":"venue"
},
  "geometry": {"coordinates":[-122.392499,37.793769],"type":"Point"}
}