{
  "type": "Feature",
  "properties": {
    "addr:full":"2812 Effie St Los Angeles CA 90026",
    "addr:housenumber":"2812",
    "addr:postcode":"90026",
    "addr:street":"Effie St",
    "iso:country":"US",
    "sg:address":"2812 Effie St",
    "sg:city":"Los Angeles",
    "sg:classifiers":[
        {
            "category":"Social Services",
            "type":"Services"
        }
    ],
    "sg:phone":"+1 323 663 4001",
    "sg:postcode":"90026",
    "sg:province":"CA",
    "sg:tags":[
        "counselor",
        "marriage",
        "family"
    ],
    "wof:name":"Edmund Cohen PHD",
    "wof:placetype":"venue"
},
  "geometry": {"coordinates":[-118.26643199999999,34.089557],"type":"Point"}
}