{
  "type": "Feature",
  "properties": {
    "addr:full":"1060 S Vail Ave Montebello CA 90640",
    "addr:housenumber":"1060",
    "addr:postcode":"90640",
    "addr:street":"S Vail Ave",
    "iso:country":"US",
    "sg:address":"1060 S Vail Ave",
    "sg:city":"Montebello",
    "sg:classifiers":[
        {
            "category":"Manufacturing",
            "subcategory":"Paper Products",
            "type":"Manufacturing & Wholesale Goods"
        }
    ],
    "sg:phone":"+1 323 869 9133",
    "sg:postcode":"90640",
    "sg:province":"CA",
    "sg:tags":[
        "box"
    ],
    "wof:name":"Royal Paper Box Co",
    "wof:placetype":"venue"
},
  "geometry": {"coordinates":[-118.12748000000001,33.996965],"type":"Point"}
}