{
  "type": "Feature",
  "properties": {
    "addr:full":"1230 Seacoast Dr Imperial Beach CA 91932",
    "addr:housenumber":"1230",
    "addr:postcode":"91932",
    "addr:street":"Seacoast Dr",
    "iso:country":"US",
    "sg:address":"1230 Seacoast Dr",
    "sg:city":"Imperial Beach",
    "sg:classifiers":[
        {
            "category":"Organizations",
            "subcategory":"Professional Association",
            "type":"Services"
        }
    ],
    "sg:phone":"+1 619 423 6861",
    "sg:postcode":"91932",
    "sg:province":"CA",
    "wof:name":"Shearwater Owner Assn",
    "wof:placetype":"venue"
},
  "geometry": {"coordinates":[-117.13179,32.575329],"type":"Point"}
}