{
  "type": "Feature",
  "properties": {
    "addr:full":"155 N 1st St Blythe CA 92225",
    "addr:housenumber":"155",
    "addr:postcode":"92225",
    "addr:street":"N 1St St",
    "iso:country":"US",
    "sg:address":"155 N 1st St",
    "sg:city":"Blythe",
    "sg:classifiers":[
        {
            "category":"Insurance",
            "subcategory":"Insurance Agent",
            "type":"Services"
        }
    ],
    "sg:phone":"+1 760 922 5168",
    "sg:postcode":"92225",
    "sg:province":"CA",
    "wof:name":"Coulson Agency",
    "wof:placetype":"venue"
},
  "geometry": {"coordinates":[-114.595493,33.611426],"type":"Point"}
}