{
  "type": "Feature",
  "properties": {
    "iso:country":"US",
    "sg:address":"15300 Pine Ln",
    "sg:city":"Chino Hills",
    "sg:classifiers":[
        {
            "category":"Freight",
            "type":"Transportation"
        }
    ],
    "sg:phone":"+1 909 597 2641",
    "sg:postcode":"91709",
    "sg:province":"CA",
    "sg:tags":[
        "operator",
        "trucking"
    ],
    "wof:name":"Valdez & Son Trucking",
    "wof:placetype":"venue"
},
  "geometry": {"coordinates":[-117.71807699999999,33.97516],"type":"Point"}
}