{
  "type": "Feature",
  "properties": {
    "iso:country":"US",
    "sg:address":"1035 Chesapeake Dr",
    "sg:city":"Pittsburg",
    "sg:classifiers":[
        {
            "category":"Shopping",
            "subcategory":"Clothing, Apparel, & Fashions",
            "type":"Retail Goods"
        }
    ],
    "sg:phone":"+1 925 439 1692",
    "sg:postcode":"94565",
    "sg:province":"CA",
    "sg:tags":[
        "uniforms-accessories",
        "uniform"
    ],
    "wof:name":"Millennuim Scrubs",
    "wof:placetype":"venue"
},
  "geometry": {"coordinates":[-121.910822,38.027403],"type":"Point"}
}