{
  "type": "Feature",
  "properties": {
    "addr:full":"28181 Haria Mission Viejo CA 92692",
    "addr:postcode":"28181;92692",
    "addr:street":"Haria",
    "iso:country":"US",
    "sg:address":"28181 Haria",
    "sg:city":"Mission Viejo",
    "sg:classifiers":[
        {
            "category":"Freight",
            "type":"Transportation"
        }
    ],
    "sg:phone":"+1 949 388 1577",
    "sg:postcode":"92692",
    "sg:province":"CA",
    "sg:tags":[
        "warehouse",
        "local",
        "trucking"
    ],
    "wof:name":"Indian Creek Trucking Inc",
    "wof:placetype":"venue"
},
  "geometry": {"coordinates":[-117.64029600000001,33.627407],"type":"Point"}
}