{
  "type": "Feature",
  "properties": {
    "iso:country":"US",
    "sg:address":"5008 1/2 Vincent Ave",
    "sg:city":"Los Angeles",
    "sg:classifiers":[
        {
            "category":"Education",
            "subcategory":"Special Training",
            "type":"Public Place"
        }
    ],
    "sg:phone":"+1 310 367 3555",
    "sg:postcode":"90041",
    "sg:province":"CA",
    "sg:tags":[
        "tutor",
        "private"
    ],
    "sg:website":"www.french4every1.com",
    "wof:name":"French For Everyone",
    "wof:placetype":"venue"
},
  "geometry": {"coordinates":[-118.20227800000001,34.137406],"type":"Point"}
}