{
  "type": "Feature",
  "properties": {
    "addr:full":"724 Fox Hollow Way Vacaville CA 95687",
    "addr:housenumber":"724",
    "addr:postcode":"95687",
    "addr:street":"Fox Hollow Way",
    "iso:country":"US",
    "sg:address":"724 Fox Hollow Way",
    "sg:city":"Vacaville",
    "sg:classifiers":[
        {
            "category":"Shopping",
            "type":"Retail Goods"
        }
    ],
    "sg:phone":"+1 707 451 1257",
    "sg:postcode":"95687",
    "sg:province":"CA",
    "sg:tags":[
        "merchandise"
    ],
    "wof:name":"Pts",
    "wof:placetype":"venue"
},
  "geometry": {"coordinates":[-121.935542,38.345006],"type":"Point"}
}