{
  "type": "Feature",
  "properties": {
    "addr:full":"2831 G St Ste 200 Sacramento CA 95816",
    "addr:housenumber":"2831",
    "addr:postcode":"95816",
    "addr:street":"G St Ste 200",
    "iso:country":"US",
    "sg:address":"2831 G St Ste 200",
    "sg:city":"Sacramento",
    "sg:classifiers":[
        {
            "category":"Real Estate",
            "subcategory":"Real Estate Services",
            "type":"Services"
        },
        {
            "category":"Banks & Credit Unions",
            "subcategory":"Bank",
            "type":"Services"
        },
        {
            "category":"Banks & Credit Unions",
            "subcategory":"Financial Services",
            "type":"Services"
        }
    ],
    "sg:phone":"+1 916 732 2340",
    "sg:postcode":"95816",
    "sg:province":"CA",
    "sg:tags":[
        "broker",
        "mortgage"
    ],
    "sg:website":"www.nfcsac.com",
    "wof:name":"Neighbors Financial Corporation",
    "wof:placetype":"venue"
},
  "geometry": {"coordinates":[-121.46651,38.577036],"type":"Point"}
}