{
  "type": "Feature",
  "properties": {
    "iso:country":"US",
    "sg:address":"724 E 1st St",
    "sg:city":"Los Angeles",
    "sg:classifiers":[
        {
            "category":"Professional",
            "subcategory":"Art Services",
            "type":"Services"
        }
    ],
    "sg:phone":"+1 213 617 3062",
    "sg:postcode":"90012",
    "sg:province":"CA",
    "sg:tags":[
        "graphic",
        "designer"
    ],
    "wof:name":"Mike Chan Design",
    "wof:placetype":"venue"
},
  "geometry": {"coordinates":[-118.235355,34.04855],"type":"Point"}
}