{
  "type": "Feature",
  "properties": {
    "iso:country":"US",
    "sg:address":"51 el Charro Rd",
    "sg:city":"Pleasanton",
    "sg:classifiers":[
        {
            "category":"Wholesale",
            "subcategory":"Construction Materials",
            "type":"Manufacturing & Wholesale Goods"
        }
    ],
    "sg:phone":"+1 925 961 8930",
    "sg:postcode":"94588",
    "sg:province":"CA",
    "sg:tags":[
        "concrete",
        "product"
    ],
    "wof:name":"Conco Form Works",
    "wof:placetype":"venue"
},
  "geometry": {"coordinates":[-121.82683,37.67632],"type":"Point"}
}