{
  "type": "Feature",
  "properties": {
    "addr:full":"731 E Ave K Lancaster CA 93535",
    "addr:housenumber":"731",
    "addr:postcode":"93535",
    "addr:street":"E Ave K",
    "iso:country":"US",
    "sg:address":"731 E Ave K",
    "sg:city":"Lancaster",
    "sg:classifiers":[
        {
            "category":"Manufacturing",
            "subcategory":"Printing",
            "type":"Manufacturing & Wholesale Goods"
        }
    ],
    "sg:phone":"+1 661 945 4576",
    "sg:postcode":"93535",
    "sg:province":"CA",
    "sg:tags":[
        "commercial"
    ],
    "wof:name":"Regal Link",
    "wof:placetype":"venue"
},
  "geometry": {"coordinates":[-118.11485500000001,34.675049],"type":"Point"}
}