{
  "type": "Feature",
  "properties": {
    "iso:country":"US",
    "sg:address":"1160 W Betteravia Rd",
    "sg:city":"Santa Maria",
    "sg:classifiers":[
        {
            "category":"Wholesale",
            "subcategory":"Non-durable Goods",
            "type":"Manufacturing & Wholesale Goods"
        }
    ],
    "sg:phone":"+1 805 614 9650",
    "sg:postcode":"93455",
    "sg:province":"CA",
    "wof:name":"LA Azteca Mexican Imports",
    "wof:placetype":"venue"
},
  "geometry": {"coordinates":[-120.452642,34.920502],"type":"Point"}
}