{
  "type": "Feature",
  "properties": {
    "addr:full":"517 N Puente Ave La Puente CA 91746",
    "addr:housenumber":"517",
    "addr:postcode":"91746",
    "addr:street":"N Puente Ave",
    "iso:country":"US",
    "sg:address":"517 N Puente Ave",
    "sg:city":"La Puente",
    "sg:classifiers":[
        {
            "category":"Restaurant",
            "type":"Food & Drink"
        }
    ],
    "sg:phone":"+1 626 968 6946",
    "sg:postcode":"91746",
    "sg:province":"CA",
    "wof:name":"Mr Taco Restaurant",
    "wof:placetype":"venue"
},
  "geometry": {"coordinates":[-117.982465,34.049896],"type":"Point"}
}