{
  "type": "Feature",
  "properties": {
    "addr:full":"650 Howe Ave Sacramento CA 95825",
    "addr:housenumber":"650",
    "addr:postcode":"95825",
    "addr:street":"Howe Ave",
    "iso:country":"US",
    "sg:address":"650 Howe Ave",
    "sg:city":"Sacramento",
    "sg:classifiers":[
        {
            "category":"Professional",
            "subcategory":"Business Services",
            "type":"Services"
        }
    ],
    "sg:phone":"+1 916 569 1740",
    "sg:postcode":"95825",
    "sg:province":"CA",
    "sg:tags":[
        "telemarketing"
    ],
    "wof:name":"Gordon & Schwenkmeyer Tlmrktng",
    "wof:placetype":"venue"
},
  "geometry": {"coordinates":[-121.415262,38.575676],"type":"Point"}
}