{
  "type": "Feature",
  "properties": {
    "iso:country":"US",
    "sg:address":"150 E Olive Ave Ste 114",
    "sg:city":"Burbank",
    "sg:classifiers":[
        {
            "category":"Tea Room",
            "subcategory":"None",
            "type":"Food & Drink"
        },
        {
            "category":"Coffee & Tea",
            "type":"Food & Drink"
        },
        {
            "category":"Restaurant",
            "type":"Food & Drink"
        }
    ],
    "sg:phone":"+1 818 848 7545",
    "sg:postcode":"91502",
    "sg:province":"CA",
    "sg:tags":[
        "espresso"
    ],
    "wof:name":"Cafe Chalet",
    "wof:placetype":"venue"
},
  "geometry": {"coordinates":[-118.30999799999999,34.18],"type":"Point"}
}