{
  "type": "Feature",
  "properties": {
    "addr:full":"310 Larkin Dr Benicia CA 94510",
    "addr:housenumber":"310",
    "addr:postcode":"94510",
    "addr:street":"Larkin Dr",
    "iso:country":"US",
    "sg:address":"310 Larkin Dr",
    "sg:city":"Benicia",
    "sg:classifiers":[
        {
            "category":"Wholesale",
            "subcategory":"Durable Goods & Equipment",
            "type":"Manufacturing & Wholesale Goods"
        }
    ],
    "sg:phone":"+1 707 747 1902",
    "sg:postcode":"94510",
    "sg:province":"CA",
    "sg:tags":[
        "representative",
        "manufacturer"
    ],
    "wof:name":"D S Sales & Marketing",
    "wof:placetype":"venue"
},
  "geometry": {"coordinates":[-122.165373,38.075001],"type":"Point"}
}