{
  "type": "Feature",
  "properties": {
    "iso:country":"US",
    "sg:address":"601 Lincoln Way",
    "sg:city":"Auburn",
    "sg:classifiers":[
        {
            "category":"Organizations",
            "subcategory":"Professional Association",
            "type":"Services"
        }
    ],
    "sg:phone":"+1 530 885 5616",
    "sg:postcode":"95603",
    "sg:province":"CA",
    "sg:tags":[
        "chambers",
        "commerce"
    ],
    "sg:website":"www.auburnarea.com",
    "wof:name":"Chamber Of Commerce",
    "wof:placetype":"venue"
},
  "geometry": {"coordinates":[-121.066593,38.901334],"type":"Point"}
}