{
  "type": "Feature",
  "properties": {
    "iso:country":"US",
    "sg:address":"1523 Commercial Way",
    "sg:city":"Santa Cruz",
    "sg:classifiers":[
        {
            "category":"Freight",
            "type":"Transportation"
        },
        {
            "category":"Retail",
            "subcategory":"Repair Shop",
            "type":"Services"
        }
    ],
    "sg:phone":"+1 831 477 4460",
    "sg:postcode":"95065",
    "sg:province":"CA",
    "sg:tags":[
        "scooter",
        "trucking",
        "motorcycle",
        "motor",
        "operator",
        "local"
    ],
    "sg:website":"www.moesalley.com",
    "wof:name":"Cycle Imagery",
    "wof:placetype":"venue"
},
  "geometry": {"coordinates":[-121.98365200000001,36.98739],"type":"Point"}
}