{
  "type": "Feature",
  "properties": {
    "addr:full":"43 Appian Way S San Francisco CA 94080",
    "addr:housenumber":"43",
    "addr:postcode":"94080",
    "addr:street":"Appian Way S",
    "iso:country":"US",
    "sg:address":"43 Appian Way",
    "sg:city":"S San Francisco",
    "sg:classifiers":[
        {
            "category":"Health Services",
            "subcategory":"Clinic",
            "type":"Services"
        }
    ],
    "sg:phone":"+1 650 589 7293",
    "sg:postcode":"94080",
    "sg:province":"CA",
    "sg:tags":[
        "agency",
        "welfare"
    ],
    "wof:name":"Corinthian Care Ctr",
    "wof:placetype":"venue"
},
  "geometry": {"coordinates":[-122.44867000000001,37.64254],"type":"Point"}
}