{
  "type": "Feature",
  "properties": {
    "iso:country":"US",
    "sg:address":"894 la Mesa Way",
    "sg:city":"Manteca",
    "sg:classifiers":[
        {
            "category":"Home & Garden",
            "subcategory":"Building Materials",
            "type":"Retail Goods"
        },
        {
            "category":"Building & Trades",
            "subcategory":"Construction",
            "type":"Services"
        },
        {
            "category":"Building & Trades",
            "subcategory":"Electrical",
            "type":"Services"
        }
    ],
    "sg:phone":"+1 209 456 1236",
    "sg:postcode":"95336",
    "sg:province":"CA",
    "sg:tags":[
        "industrial",
        "electrician",
        "electric",
        "altering",
        "contractor",
        "contractors-commercial",
        "improvement",
        "remodeling"
    ],
    "wof:name":"Pacific Electric",
    "wof:placetype":"venue"
},
  "geometry": {"coordinates":[-121.230056,37.808681],"type":"Point"}
}