{
  "type": "Feature",
  "properties": {
    "addr:full":"2236 Mitchell Rd Ste B Ceres CA 95307",
    "addr:housenumber":"2236",
    "addr:postcode":"95307",
    "addr:street":"Mitchell Rd Ste B",
    "iso:country":"US",
    "sg:address":"2236 Mitchell Rd Ste B",
    "sg:city":"Ceres",
    "sg:classifiers":[
        {
            "category":"Health Services",
            "subcategory":"Chiropractor",
            "type":"Services"
        }
    ],
    "sg:phone":"+1 209 544 3000",
    "sg:postcode":"95307",
    "sg:province":"CA",
    "wof:name":"SCOTT CHIROPRACTIC OFFICES",
    "wof:placetype":"venue"
},
  "geometry": {"coordinates":[-120.938451,37.597248],"type":"Point"}
}