{
  "type": "Feature",
  "properties": {
    "iso:country":"US",
    "sg:address":"1361 S Mansfield Ave",
    "sg:city":"Los Angeles",
    "sg:classifiers":[
        {
            "category":"Professional",
            "type":"Services"
        }
    ],
    "sg:phone":"+1 323 933 4267",
    "sg:postcode":"90019",
    "sg:province":"CA",
    "wof:name":"Mental Pictures LLC",
    "wof:placetype":"venue"
},
  "geometry": {"coordinates":[-118.34541,34.049349],"type":"Point"}
}