{
  "type": "Feature",
  "properties": {
    "addr:full":"445 Huyler Ln Simi Valley CA 93065",
    "addr:housenumber":"445",
    "addr:postcode":"93065",
    "addr:street":"Huyler Ln",
    "iso:country":"US",
    "sg:address":"445 Huyler Ln",
    "sg:city":"Simi Valley",
    "sg:classifiers":[
        {
            "category":"Retail",
            "subcategory":"Repair Shop",
            "type":"Services"
        },
        {
            "category":"Building & Trades",
            "subcategory":"Plumbing",
            "type":"Services"
        }
    ],
    "sg:phone":"+1 805 527 6474",
    "sg:postcode":"93065",
    "sg:province":"CA",
    "sg:tags":[
        "conditioning",
        "air",
        "refrigeration",
        "system",
        "contractor"
    ],
    "wof:name":"Chase Heating & Air Cond",
    "wof:placetype":"venue"
},
  "geometry": {"coordinates":[-118.808201,34.246492],"type":"Point"}
}