{
  "type": "Feature",
  "properties": {
    "iso:country":"US",
    "sg:address":"3490 Scott St",
    "sg:city":"San Francisco",
    "sg:classifiers":[
        {
            "category":"Professional",
            "subcategory":"Employment Agencies",
            "type":"Services"
        }
    ],
    "sg:phone":"+1 415 359 1046",
    "sg:postcode":"94123",
    "sg:province":"CA",
    "sg:tags":[
        "consultant",
        "search",
        "executive"
    ],
    "wof:name":"Executive Venture Group",
    "wof:placetype":"venue"
},
  "geometry": {"coordinates":[-122.441523,37.80217],"type":"Point"}
}