{
  "type": "Feature",
  "properties": {
    "iso:country":"US",
    "sg:address":"2831 Cam del Rio S",
    "sg:city":"San Diego",
    "sg:classifiers":[
        {
            "category":"Professional",
            "subcategory":"Business Services",
            "type":"Services"
        }
    ],
    "sg:phone":"+1 619 725 0938",
    "sg:postcode":"92108",
    "sg:province":"CA",
    "wof:name":"C C Coupon LLC",
    "wof:placetype":"venue"
},
  "geometry": {"coordinates":[-117.135183,32.770386],"type":"Point"}
}