{
  "type": "Feature",
  "properties": {
    "addr:full":"20850 Leapwood Ave Carson CA 90746",
    "addr:postcode":"20850;90746",
    "addr:street":"Leapwood Ave",
    "iso:country":"US",
    "sg:address":"20850 Leapwood Ave",
    "sg:city":"Carson",
    "sg:classifiers":[
        {
            "category":"Professional",
            "subcategory":"Research",
            "type":"Services"
        }
    ],
    "sg:phone":"+1 310 324 6722",
    "sg:postcode":"90746",
    "sg:province":"CA",
    "sg:tags":[
        "laboratory"
    ],
    "wof:name":"Arnold Laboratories Inc",
    "wof:placetype":"venue"
},
  "geometry": {"coordinates":[-118.258763,33.843661],"type":"Point"}
}