{
  "type": "Feature",
  "properties": {
    "addr:full":"1236 E Houston Ave Visalia CA 93292",
    "addr:housenumber":"1236",
    "addr:postcode":"93292",
    "addr:street":"E Houston Ave",
    "iso:country":"US",
    "sg:address":"1236 E Houston Ave",
    "sg:city":"Visalia",
    "sg:classifiers":[
        {
            "category":"Autos & Motor Vehicles",
            "subcategory":"Fuel & Gas Station",
            "type":"Retail Goods"
        }
    ],
    "sg:phone":"+1 559 627 6844",
    "sg:postcode":"93292",
    "sg:province":"CA",
    "sg:tags":[
        "oil"
    ],
    "wof:name":"Beacon",
    "wof:placetype":"venue"
},
  "geometry": {"coordinates":[-119.28003699999999,36.341917],"type":"Point"}
}