{
  "type": "Feature",
  "properties": {
    "addr:full":"907 Mission Ave San Rafael CA 94901",
    "addr:housenumber":"907",
    "addr:postcode":"94901",
    "addr:street":"Mission Ave",
    "iso:country":"US",
    "sg:address":"907 Mission Ave",
    "sg:city":"San Rafael",
    "sg:classifiers":[
        {
            "category":"Professional",
            "subcategory":"Engineering",
            "type":"Services"
        }
    ],
    "sg:phone":"+1 415 453 4480",
    "sg:postcode":"94901",
    "sg:province":"CA",
    "sg:tags":[
        "engineer"
    ],
    "wof:name":"Nute Engineering",
    "wof:placetype":"venue"
},
  "geometry": {"coordinates":[-122.525998,37.974637],"type":"Point"}
}