{
  "type": "Feature",
  "properties": {
    "addr:full":"1412 S Greenwood Ave Montebello CA 90640",
    "addr:housenumber":"1412",
    "addr:postcode":"90640",
    "addr:street":"S Greenwood Ave",
    "iso:country":"US",
    "sg:address":"1412 S Greenwood Ave",
    "sg:city":"Montebello",
    "sg:classifiers":[
        {
            "category":"Building & Trades",
            "subcategory":"Construction",
            "type":"Services"
        }
    ],
    "sg:phone":"+1 323 728 4267",
    "sg:postcode":"90640",
    "sg:province":"CA",
    "sg:tags":[
        "excavating",
        "contractor"
    ],
    "wof:name":"Gabriel's Dump Truck & Backhoe",
    "wof:placetype":"venue"
},
  "geometry": {"coordinates":[-118.124516,33.986174],"type":"Point"}
}