{
  "type": "Feature",
  "properties": {
    "iso:country":"US",
    "sg:address":"1215 Olive Dr",
    "sg:city":"Bakersfield",
    "sg:classifiers":[
        {
            "category":"Professional",
            "subcategory":"Accounting & Tax Preparation",
            "type":"Services"
        },
        {
            "category":"Banks & Credit Unions",
            "subcategory":"Financial Services",
            "type":"Services"
        }
    ],
    "sg:phone":"+1 661 392 1040",
    "sg:postcode":"93308",
    "sg:province":"CA",
    "sg:tags":[
        "return",
        "preparation-business",
        "taxes-consultants",
        "loan",
        "reporting",
        "representative",
        "alternative",
        "bookkeeping"
    ],
    "sg:website":"http://www.hrblock.com",
    "wof:name":"H&R Block",
    "wof:placetype":"venue"
},
  "geometry": {"coordinates":[-119.045095,35.4123],"type":"Point"}
}