{
  "type": "Feature",
  "properties": {
    "addr:full":"4141 Manzanita Ave Ste 105 Carmichael CA 95608",
    "addr:housenumber":"4141",
    "addr:postcode":"95608",
    "addr:street":"Manzanita Ave Ste 105",
    "iso:country":"US",
    "sg:address":"4141 Manzanita Ave Ste 105",
    "sg:city":"Carmichael",
    "sg:classifiers":[
        {
            "category":"Personal",
            "type":"Services"
        },
        {
            "category":"Sports & Exercise",
            "subcategory":"Gym",
            "type":"Entertainment"
        },
        {
            "category":"Health Services",
            "subcategory":"Health Practitioner",
            "type":"Services"
        },
        {
            "category":"Arena",
            "subcategory":"Sports Club",
            "type":"Entertainment"
        }
    ],
    "sg:phone":"+1 916 973 9900",
    "sg:postcode":"95608",
    "sg:province":"CA",
    "sg:tags":[
        "control",
        "weight",
        "consultant",
        "program",
        "fitness",
        "physical"
    ],
    "sg:website":"http://www.curves.com",
    "wof:name":"Curves",
    "wof:placetype":"venue"
},
  "geometry": {"coordinates":[-121.327968,38.639584],"type":"Point"}
}