{
  "type": "Feature",
  "properties": {
    "addr:full":"6735 N Farris Ave Fresno CA 93711",
    "addr:housenumber":"6735",
    "addr:postcode":"93711",
    "addr:street":"N Farris Ave",
    "iso:country":"US",
    "sg:address":"6735 N Farris Ave",
    "sg:city":"Fresno",
    "sg:classifiers":[
        {
            "category":"Manufacturing",
            "subcategory":"Glass & Minerals",
            "type":"Manufacturing & Wholesale Goods"
        },
        {
            "category":"Building & Trades",
            "subcategory":"Construction",
            "type":"Services"
        }
    ],
    "sg:phone":"+1 559 905 6430",
    "sg:postcode":"93711",
    "sg:province":"CA",
    "sg:tags":[
        "granite",
        "product",
        "contractor"
    ],
    "wof:name":"Kotenkoff's Granite Inc",
    "wof:placetype":"venue"
},
  "geometry": {"coordinates":[-119.812421,36.834573],"type":"Point"}
}