{
  "type": "Feature",
  "properties": {
    "iso:country":"US",
    "sg:address":"805 Aerovista Park",
    "sg:city":"San Luis Obispo",
    "sg:classifiers":[
        {
            "category":"Sports & Exercise",
            "subcategory":"Gym",
            "type":"Entertainment"
        }
    ],
    "sg:phone":"+1 805 546 6070",
    "sg:postcode":"93401",
    "sg:province":"CA",
    "sg:tags":[
        "club",
        "health",
        "studio",
        "gymnasium"
    ],
    "wof:name":"Athlon Health & Fitness",
    "wof:placetype":"venue"
},
  "geometry": {"coordinates":[-120.641465,35.242166],"type":"Point"}
}