{
  "type": "Feature",
  "properties": {
    "addr:full":"9838 Mission Vega Rd Santee CA 92071",
    "addr:housenumber":"9838",
    "addr:postcode":"92071",
    "addr:street":"Mission Vega Rd",
    "iso:country":"US",
    "sg:address":"9838 Mission Vega Rd",
    "sg:city":"Santee",
    "sg:classifiers":[
        {
            "category":"Retail",
            "subcategory":"Laundry & Dry Cleaning",
            "type":"Services"
        }
    ],
    "sg:phone":"+1 858 277 2300",
    "sg:postcode":"92071",
    "sg:province":"CA",
    "sg:tags":[
        "cleaners",
        "rug",
        "carpet"
    ],
    "wof:name":"San Diego Carpet Care",
    "wof:placetype":"venue"
},
  "geometry": {"coordinates":[-116.98173300000001,32.837809],"type":"Point"}
}