{
  "type": "Feature",
  "properties": {
    "addr:full":"813 Ellington St Delano CA 93215",
    "addr:housenumber":"813",
    "addr:postcode":"93215",
    "addr:street":"Ellington St",
    "iso:country":"US",
    "sg:address":"813 Ellington St",
    "sg:city":"Delano",
    "sg:classifiers":[
        {
            "category":"Professional",
            "subcategory":"Secretarial Services",
            "type":"Services"
        }
    ],
    "sg:phone":"+1 661 721 8358",
    "sg:postcode":"93215",
    "sg:province":"CA",
    "sg:tags":[
        "reporting",
        "court"
    ],
    "wof:name":"Socorro's Clerical Svc",
    "wof:placetype":"venue"
},
  "geometry": {"coordinates":[-119.251047,35.766758],"type":"Point"}
}