{
  "type": "Feature",
  "properties": {
    "addr:full":"3550 Moraga St San Francisco CA 94122",
    "addr:housenumber":"3550",
    "addr:postcode":"94122",
    "addr:street":"Moraga St",
    "iso:country":"US",
    "sg:address":"3550 Moraga St",
    "sg:city":"San Francisco",
    "sg:classifiers":[
        {
            "category":"Wholesale",
            "subcategory":"Non-durable Goods",
            "type":"Manufacturing & Wholesale Goods"
        }
    ],
    "sg:phone":"+1 415 753 8342",
    "sg:postcode":"94122",
    "sg:province":"CA",
    "sg:tags":[
        "merchandise",
        "general"
    ],
    "wof:name":"Its",
    "wof:placetype":"venue"
},
  "geometry": {"coordinates":[-122.50081900000001,37.755103],"type":"Point"}
}