{
  "type": "Feature",
  "properties": {
    "addr:full":"4 Red Oak Ct Novato CA 94949",
    "addr:housenumber":"4",
    "addr:postcode":"94949",
    "addr:street":"Red Oak Ct",
    "iso:country":"US",
    "sg:address":"4 Red Oak Ct",
    "sg:city":"Novato",
    "sg:classifiers":[
        {
            "category":"Autos & Motor Vehicles",
            "subcategory":"Auto Supplies",
            "type":"Retail Goods"
        }
    ],
    "sg:phone":"+1 415 899 0703",
    "sg:postcode":"94949",
    "sg:province":"CA",
    "sg:tags":[
        "battery"
    ],
    "sg:website":"www.myocke.com",
    "wof:name":"Celtech Partners",
    "wof:placetype":"venue"
},
  "geometry": {"coordinates":[-122.56129900000001,38.072011],"type":"Point"}
}