{
  "type": "Feature",
  "properties": {
    "iso:country":"US",
    "sg:address":"117 9th St",
    "sg:city":"Manhattan Beach",
    "sg:classifiers":[
        {
            "category":"Professional",
            "type":"Services"
        }
    ],
    "sg:phone":"+1 310 379 7896",
    "sg:postcode":"90266",
    "sg:province":"CA",
    "sg:tags":[
        "establishment"
    ],
    "sg:website":"www.saba-solutions.com",
    "wof:name":"Saba Solutions",
    "wof:placetype":"venue"
},
  "geometry": {"coordinates":[-118.409739,33.882892],"type":"Point"}
}