{
  "type": "Feature",
  "properties": {
    "iso:country":"US",
    "sg:address":"31187 Mission Blvd",
    "sg:city":"Hayward",
    "sg:classifiers":[
        {
            "category":"Restaurant",
            "type":"Food & Drink"
        }
    ],
    "sg:menulink":"http://www.allmenus.com/ca/hayward/159933-arbys/menu/",
    "sg:phone":"+1 510 475 6115",
    "sg:postcode":"94544",
    "sg:province":"CA",
    "sg:tags":[
        "burger",
        "american"
    ],
    "wof:name":"Arby's",
    "wof:placetype":"venue"
},
  "geometry": {"coordinates":[-122.03537900000001,37.619049],"type":"Point"}
}