{
  "type": "Feature",
  "properties": {
    "iso:country":"US",
    "sg:address":"5341 Crow Canyon Rd",
    "sg:city":"Castro Valley",
    "sg:classifiers":[
        {
            "category":"Wholesale",
            "subcategory":"Machinery & Supplies",
            "type":"Manufacturing & Wholesale Goods"
        }
    ],
    "sg:phone":"+1 510 582 4565",
    "sg:postcode":"94552",
    "sg:province":"CA",
    "sg:tags":[
        "trailer"
    ],
    "wof:name":"Jack's Trailer Sales Inc",
    "wof:placetype":"venue"
},
  "geometry": {"coordinates":[-122.04705300000001,37.702472],"type":"Point"}
}