{
  "type": "Feature",
  "properties": {
    "iso:country":"US",
    "sg:address":"608 Jensen Pl",
    "sg:city":"Placentia",
    "sg:classifiers":[
        {
            "category":"Home & Garden",
            "subcategory":"Furniture",
            "type":"Retail Goods"
        }
    ],
    "sg:phone":"+1 714 792 3792",
    "sg:postcode":"92870",
    "sg:province":"CA",
    "sg:tags":[
        "store"
    ],
    "wof:name":"Utopia Furniture Corporation",
    "wof:placetype":"venue"
},
  "geometry": {"coordinates":[-117.846547,33.87625],"type":"Point"}
}