{
  "type": "Feature",
  "properties": {
    "addr:full":"1743 N Cahuenga Blvd Los Angeles CA 90028",
    "addr:housenumber":"1743",
    "addr:postcode":"90028",
    "addr:street":"N Cahuenga Blvd",
    "iso:country":"US",
    "sg:address":"1743 N Cahuenga Blvd",
    "sg:city":"Los Angeles",
    "sg:classifiers":[
        {
            "category":"Recreation",
            "subcategory":"Dance Hall",
            "type":"Entertainment"
        }
    ],
    "sg:phone":"+1 323 525 2450",
    "sg:postcode":"90028",
    "sg:province":"CA",
    "sg:tags":[
        "club"
    ],
    "wof:name":"Colony Night Club",
    "wof:placetype":"venue"
},
  "geometry": {"coordinates":[-118.32957399999999,34.103175],"type":"Point"}
}