{
  "type": "Feature",
  "properties": {
    "iso:country":"US",
    "sg:address":"100 E Cortner St",
    "sg:city":"Hanford",
    "sg:classifiers":[
        {
            "category":"Manufacturing",
            "subcategory":"Printing",
            "type":"Manufacturing & Wholesale Goods"
        }
    ],
    "sg:phone":"+1 559 583 6066",
    "sg:postcode":"93230",
    "sg:province":"CA",
    "sg:tags":[
        "publisher"
    ],
    "wof:name":"Amenta Books",
    "wof:placetype":"venue"
},
  "geometry": {"coordinates":[-119.64607100000001,36.351808],"type":"Point"}
}