{
  "type": "Feature",
  "properties": {
    "iso:country":"US",
    "sg:address":"11775 Shoal Creek Dr",
    "sg:city":"San Diego",
    "sg:classifiers":[
        {
            "category":"Education",
            "subcategory":"School",
            "type":"Public Place"
        }
    ],
    "sg:phone":"+1 858 613 9080",
    "sg:postcode":"92128",
    "sg:province":"CA",
    "wof:name":"Shoal Creek Elementary School",
    "wof:placetype":"venue"
},
  "geometry": {"coordinates":[-117.080263,32.967188],"type":"Point"}
}