{
  "type": "Feature",
  "properties": {
    "iso:country":"US",
    "sg:address":"117 S Western Ave",
    "sg:city":"Anaheim",
    "sg:classifiers":[
        {
            "category":"Restaurant",
            "type":"Food & Drink"
        }
    ],
    "sg:phone":"+1 714 761 5283",
    "sg:postcode":"92804",
    "sg:province":"CA",
    "wof:name":"Mos No 2",
    "wof:placetype":"venue"
},
  "geometry": {"coordinates":[-118.001999,33.831699],"type":"Point"}
}