{
  "type": "Feature",
  "properties": {
    "iso:country":"US",
    "sg:address":"8441 24th Ave",
    "sg:city":"Sacramento",
    "sg:classifiers":[
        {
            "category":"Professional",
            "subcategory":"Business Services",
            "type":"Services"
        }
    ],
    "sg:phone":"+1 916 386 2297",
    "sg:postcode":"95826",
    "sg:province":"CA",
    "sg:tags":[
        "process",
        "server"
    ],
    "wof:name":"Woodstone",
    "wof:placetype":"venue"
},
  "geometry": {"coordinates":[-121.391443,38.530363],"type":"Point"}
}