{
  "type": "Feature",
  "properties": {
    "addr:full":"2001 Ocean Ave Santa Monica CA 90405",
    "addr:housenumber":"2001",
    "addr:postcode":"90405",
    "addr:street":"Ocean Ave",
    "iso:country":"US",
    "sg:address":"2001 Ocean Ave",
    "sg:city":"Santa Monica",
    "sg:classifiers":[
        {
            "category":"Travel",
            "subcategory":"Hotels & Motels",
            "type":"Entertainment"
        }
    ],
    "sg:phone":"+1 310 396 6000",
    "sg:postcode":"90405",
    "sg:province":"CA",
    "wof:name":"Casa Del Ceilo Llc",
    "wof:placetype":"venue"
},
  "geometry": {"coordinates":[-118.48972999999999,34.507321],"type":"Point"}
}