{
  "type": "Feature",
  "properties": {
    "addr:full":"3175 Heather Ridge Dr San Jose CA 95136",
    "addr:housenumber":"3175",
    "addr:postcode":"95136",
    "addr:street":"Heather Ridge Dr",
    "iso:country":"US",
    "sg:address":"3175 Heather Ridge Dr",
    "sg:city":"San Jose",
    "sg:classifiers":[
        {
            "category":"Building & Trades",
            "subcategory":"Cleaning & Sanitation",
            "type":"Services"
        }
    ],
    "sg:phone":"+1 408 227 8292",
    "sg:postcode":"95136",
    "sg:province":"CA",
    "sg:tags":[
        "janitor"
    ],
    "wof:name":"BHC Maintenance Svc",
    "wof:placetype":"venue"
},
  "geometry": {"coordinates":[-121.86187,37.281631],"type":"Point"}
}