{
  "type": "Feature",
  "properties": {
    "addr:full":"4609 S Broadway Los Angeles CA 90037",
    "addr:housenumber":"4609",
    "addr:postcode":"90037",
    "addr:street":"S Broadway",
    "iso:country":"US",
    "sg:address":"4609 S Broadway",
    "sg:city":"Los Angeles",
    "sg:classifiers":[
        {
            "category":"Personal",
            "subcategory":"Tattoo Parlor",
            "type":"Services"
        }
    ],
    "sg:phone":"+1 323 234 8409",
    "sg:postcode":"90037",
    "sg:province":"CA",
    "wof:name":"City of Angels Body Art",
    "wof:placetype":"venue"
},
  "geometry": {"coordinates":[-118.278203,34.001516],"type":"Point"}
}