{
  "type": "Feature",
  "properties": {
    "addr:full":"9051A Soquel Dr Ste A Aptos CA 95003",
    "addr:housenumber":"9051a",
    "addr:postcode":"95003",
    "addr:street":"Soquel Dr Ste A",
    "iso:country":"US",
    "sg:address":"9051A Soquel Dr Ste A",
    "sg:city":"Aptos",
    "sg:classifiers":[
        {
            "category":"Professional",
            "type":"Services"
        },
        {
            "category":"Arts & Performance",
            "subcategory":"Music",
            "type":"Entertainment"
        }
    ],
    "sg:phone":"+1 831 687 0278",
    "sg:postcode":"95003",
    "sg:province":"CA",
    "sg:tags":[
        "record",
        "producer",
        "label"
    ],
    "wof:name":"Kapland Records",
    "wof:placetype":"venue"
},
  "geometry": {"coordinates":[-121.892408,36.97555],"type":"Point"}
}