{
  "type": "Feature",
  "properties": {
    "iso:country":"US",
    "sg:address":"1275 Central Blvd Bldg 10",
    "sg:city":"Brentwood",
    "sg:classifiers":[
        {
            "category":"Real Estate",
            "subcategory":"Real Estate Services",
            "type":"Services"
        },
        {
            "category":"Real Estate",
            "subcategory":"Real Estate Agent",
            "type":"Services"
        }
    ],
    "sg:phone":"+1 925 516 3628",
    "sg:postcode":"94513",
    "sg:province":"CA",
    "sg:tags":[
        "management"
    ],
    "wof:name":"HPH Properties L.P.",
    "wof:placetype":"venue"
},
  "geometry": {"coordinates":[-121.698064,37.939501],"type":"Point"}
}