{
  "type": "Feature",
  "properties": {
    "iso:country":"US",
    "sg:address":"7347 Ethel Ave",
    "sg:city":"North Hollywood",
    "sg:classifiers":[
        {
            "category":"Manufacturing",
            "subcategory":"Tools & Machinery",
            "type":"Manufacturing & Wholesale Goods"
        }
    ],
    "sg:phone":"+1 818 765 4994",
    "sg:postcode":"91605",
    "sg:province":"CA",
    "sg:tags":[
        "equipment",
        "dental",
        "supply"
    ],
    "wof:name":"Davis Dental Supply Co",
    "wof:placetype":"venue"
},
  "geometry": {"coordinates":[-118.418234,34.203823],"type":"Point"}
}