{
  "type": "Feature",
  "properties": {
    "iso:country":"US",
    "sg:address":"3556 Orcutt Rd",
    "sg:city":"Santa Maria",
    "sg:classifiers":[
        {
            "category":"Shopping",
            "subcategory":"Musical Instruments",
            "type":"Retail Goods"
        }
    ],
    "sg:phone":"+1 805 922 3449",
    "sg:postcode":"93455",
    "sg:province":"CA",
    "wof:name":"Maxfield's Happy Music Co",
    "wof:placetype":"venue"
},
  "geometry": {"coordinates":[-120.436221,34.8961],"type":"Point"}
}