{
  "type": "Feature",
  "properties": {
    "addr:full":"7400 Garvey Ave Rosemead CA 91770",
    "addr:housenumber":"7400",
    "addr:postcode":"91770",
    "addr:street":"Garvey Ave",
    "iso:country":"US",
    "sg:address":"7400 Garvey Ave",
    "sg:city":"Rosemead",
    "sg:classifiers":[
        {
            "category":"Food & Beverages",
            "subcategory":"Groceries & Convenience Stores",
            "type":"Retail Goods"
        }
    ],
    "sg:phone":"+1 626 307 1987",
    "sg:postcode":"91770",
    "sg:province":"CA",
    "wof:name":"7-Eleven",
    "wof:placetype":"venue"
},
  "geometry": {"coordinates":[-118.106973,34.062573],"type":"Point"}
}