{
  "type": "Feature",
  "properties": {
    "addr:full":"381 E L St Benicia CA 94510",
    "addr:housenumber":"381",
    "addr:postcode":"94510",
    "addr:street":"E L St",
    "iso:country":"US",
    "sg:address":"381 E L St",
    "sg:city":"Benicia",
    "sg:classifiers":[
        {
            "category":"Manufacturing",
            "subcategory":"Textiles",
            "type":"Manufacturing & Wholesale Goods"
        },
        {
            "category":"Home & Garden",
            "subcategory":"Building Materials",
            "type":"Retail Goods"
        },
        {
            "category":"Building & Trades",
            "subcategory":"Construction",
            "type":"Services"
        },
        {
            "category":"Manufacturing",
            "subcategory":"Building Materials",
            "type":"Manufacturing & Wholesale Goods"
        }
    ],
    "sg:phone":"+1 707 751 1700",
    "sg:postcode":"94510",
    "sg:province":"CA",
    "sg:tags":[
        "solid",
        "top",
        "counter",
        "surface",
        "tile-contractors",
        "tile-wholesale",
        "manufacturer"
    ],
    "wof:name":"Tenret Tile",
    "wof:placetype":"venue"
},
  "geometry": {"coordinates":[-122.149855,38.051163],"type":"Point"}
}