{
  "type": "Feature",
  "properties": {
    "iso:country":"US",
    "sg:address":"385a Aviation Blvd",
    "sg:city":"Santa Rosa",
    "sg:classifiers":[
        {
            "category":"Restaurant",
            "type":"Food & Drink"
        }
    ],
    "sg:menulink":"http://www.allmenus.com/ca/santa-rosa/123688-quiznos-sub/menu/",
    "sg:phone":"+1 707 573 0999",
    "sg:postcode":"95403",
    "sg:province":"CA",
    "sg:tags":[
        "wrap",
        "american",
        "sandwich"
    ],
    "wof:name":"Quiznos Sub",
    "wof:placetype":"venue"
},
  "geometry": {"coordinates":[-122.786216,38.515031],"type":"Point"}
}