{
  "type": "Feature",
  "properties": {
    "addr:full":"4901 Emerson Rd Sacramento CA 95820",
    "addr:housenumber":"4901",
    "addr:postcode":"95820",
    "addr:street":"Emerson Rd",
    "iso:country":"US",
    "sg:address":"4901 Emerson Rd",
    "sg:city":"Sacramento",
    "sg:classifiers":[
        {
            "category":"Building & Trades",
            "subcategory":"Landscaping Services",
            "type":"Services"
        }
    ],
    "sg:phone":"+1 916 383 6031",
    "sg:postcode":"95820",
    "sg:province":"CA",
    "sg:tags":[
        "landscape",
        "contractor"
    ],
    "wof:name":"Greenlawn Maintenance/Landscpg",
    "wof:placetype":"venue"
},
  "geometry": {"coordinates":[-121.42001399999999,38.530296],"type":"Point"}
}