{
  "type": "Feature",
  "properties": {
    "addr:full":"1049 S Westlake Blvd Westlake Village CA 91361",
    "addr:housenumber":"1049",
    "addr:postcode":"91361",
    "addr:street":"S Westlake Blvd",
    "iso:country":"US",
    "sg:address":"1049 S Westlake Blvd",
    "sg:city":"Westlake Village",
    "sg:classifiers":[
        {
            "category":"Social Services",
            "subcategory":"Child Care",
            "type":"Services"
        }
    ],
    "sg:phone":"+1 805 497 7064",
    "sg:postcode":"91361",
    "sg:province":"CA",
    "sg:tags":[
        "kindergarten",
        "academic",
        "school"
    ],
    "wof:name":"Growing Place Preschool",
    "wof:placetype":"venue"
},
  "geometry": {"coordinates":[-118.828726,34.152762],"type":"Point"}
}