{
  "type": "Feature",
  "properties": {
    "addr:full":"331 E 9th St San Bernardino CA 92410",
    "addr:housenumber":"331",
    "addr:postcode":"92410",
    "addr:street":"E 9Th St",
    "iso:country":"US",
    "sg:address":"331 E 9th St",
    "sg:city":"San Bernardino",
    "sg:classifiers":[
        {
            "category":"Cinema",
            "subcategory":"Movie Rental",
            "type":"Entertainment"
        }
    ],
    "sg:phone":"+1 909 884 3780",
    "sg:postcode":"92410",
    "sg:province":"CA",
    "sg:tags":[
        "leasing",
        "video",
        "disc",
        "tape"
    ],
    "wof:name":"Le Hoang Video",
    "wof:placetype":"venue"
},
  "geometry": {"coordinates":[-117.27515,34.115719],"type":"Point"}
}