{
  "type": "Feature",
  "properties": {
    "addr:full":"1232 D St Corona CA 92882",
    "addr:housenumber":"1232",
    "addr:postcode":"92882",
    "addr:street":"D St",
    "iso:country":"US",
    "sg:address":"1232 D St",
    "sg:city":"Corona",
    "sg:classifiers":[
        {
            "category":"Freight",
            "type":"Transportation"
        }
    ],
    "sg:phone":"+1 951 283 4517",
    "sg:postcode":"92882",
    "sg:province":"CA",
    "sg:tags":[
        "operator",
        "trucking"
    ],
    "wof:name":"Peef Transport",
    "wof:placetype":"venue"
},
  "geometry": {"coordinates":[-117.58814700000001,33.880717],"type":"Point"}
}