{
  "type": "Feature",
  "properties": {
    "addr:full":"9093 Elk Grove Blvd Elk Grove CA 95624",
    "addr:housenumber":"9093",
    "addr:postcode":"95624",
    "addr:street":"Elk Grove Blvd",
    "iso:country":"US",
    "sg:address":"9093 Elk Grove Blvd",
    "sg:city":"Elk Grove",
    "sg:classifiers":[
        {
            "category":"Wholesale",
            "subcategory":"Durable Goods & Equipment",
            "type":"Manufacturing & Wholesale Goods"
        }
    ],
    "sg:phone":"+1 916 714 1404",
    "sg:postcode":"95624",
    "sg:province":"CA",
    "sg:tags":[
        "importer"
    ],
    "wof:name":"Mi Casa TU Zasa Imports",
    "wof:placetype":"venue"
},
  "geometry": {"coordinates":[-121.362801,38.40909],"type":"Point"}
}