{
  "type": "Feature",
  "properties": {
    "iso:country":"US",
    "sg:address":"877 Chestnut Street",
    "sg:city":"San Jose",
    "sg:classifiers":[
        {
            "category":"Retail",
            "subcategory":"Auto Repair",
            "type":"Services"
        }
    ],
    "sg:phone":"+1 408 295 8446",
    "sg:postcode":"95110",
    "sg:province":"CA",
    "sg:tags":[
        "body",
        "shop"
    ],
    "wof:name":"Progressive Collision Repair",
    "wof:placetype":"venue"
},
  "geometry": {"coordinates":[-121.916214,37.344639],"type":"Point"}
}