{
  "type": "Feature",
  "properties": {
    "iso:country":"US",
    "sg:address":"3000 W Olympic Boulevard",
    "sg:city":"Los Angeles",
    "sg:classifiers":[
        {
            "category":"Shopping",
            "subcategory":"Pharmacy",
            "type":"Retail Goods"
        }
    ],
    "sg:phone":"+1 213 388 0300",
    "sg:postcode":"90006",
    "sg:province":"CA",
    "sg:tags":[
        "drugstore"
    ],
    "wof:name":"Kim David Pharmacy",
    "wof:placetype":"venue"
},
  "geometry": {"coordinates":[-118.300016,34.052739],"type":"Point"}
}