{
  "type": "Feature",
  "properties": {
    "iso:country":"US",
    "sg:address":"3761 James W Smith Loop",
    "sg:city":"Tracy",
    "sg:classifiers":[
        {
            "category":"Restaurant",
            "type":"Food & Drink"
        }
    ],
    "sg:phone":"+1 209 832 8407",
    "sg:postcode":"95377",
    "sg:province":"CA",
    "sg:tags":[
        "caterer"
    ],
    "wof:name":"Alberta's Soul Food Catering",
    "wof:placetype":"venue"
},
  "geometry": {"coordinates":[-121.423913,37.705281],"type":"Point"}
}