{
  "type": "Feature",
  "properties": {
    "iso:country":"US",
    "sg:address":"3430 El Camino Real",
    "sg:city":"Santa Clara",
    "sg:classifiers":[
        {
            "category":"Restaurant",
            "type":"Food & Drink"
        }
    ],
    "sg:menulink":"http://www.allmenus.com/ca/san-jose/136156-secret-garden/menu/",
    "sg:phone":"+1 408 244 5020",
    "sg:postcode":"95051",
    "sg:province":"CA",
    "sg:tags":[
        "korean",
        "asian"
    ],
    "wof:name":"Secret Garden",
    "wof:placetype":"venue"
},
  "geometry": {"coordinates":[-121.991997,37.352279],"type":"Point"}
}