{
  "type": "Feature",
  "properties": {
    "addr:full":"8200 Brand Ln Penngrove CA 94951",
    "addr:postcode":"8200;94951",
    "addr:street":"Brand Ln",
    "iso:country":"US",
    "sg:address":"8200 Brand Ln",
    "sg:city":"Penngrove",
    "sg:classifiers":[
        {
            "category":"Building & Trades",
            "subcategory":"Plumbing",
            "type":"Services"
        }
    ],
    "sg:phone":"+1 707 793 1015",
    "sg:postcode":"94951",
    "sg:province":"CA",
    "sg:tags":[
        "plumbing",
        "contractor"
    ],
    "wof:name":"Gary Moller Plumbing",
    "wof:placetype":"venue"
},
  "geometry": {"coordinates":[-122.653532,38.311508],"type":"Point"}
}