{
  "type": "Feature",
  "properties": {
    "addr:full":"2730 E Slauson Ave Huntington Park CA 90255",
    "addr:housenumber":"2730",
    "addr:postcode":"90255",
    "addr:street":"E Slauson Ave;Park",
    "iso:country":"US",
    "sg:address":"2730 E Slauson Ave",
    "sg:city":"Huntington Park",
    "sg:classifiers":[
        {
            "category":"Retail",
            "subcategory":"Auto Repair",
            "type":"Services"
        }
    ],
    "sg:phone":"+1 323 589 1886",
    "sg:postcode":"90255",
    "sg:province":"CA",
    "sg:tags":[
        "glass",
        "coating",
        "tinting"
    ],
    "wof:name":"Professional Window Tinting",
    "wof:placetype":"venue"
},
  "geometry": {"coordinates":[-118.221619,33.989131],"type":"Point"}
}