{
  "type": "Feature",
  "properties": {
    "iso:country":"US",
    "sg:address":"362 S Barrington Ave",
    "sg:city":"Los Angeles",
    "sg:classifiers":[
        {
            "category":"Professional",
            "type":"Services"
        }
    ],
    "sg:phone":"+1 310 472 9786",
    "sg:postcode":"90049",
    "sg:province":"CA",
    "wof:name":"Jcs/Monogram Hold",
    "wof:placetype":"venue"
},
  "geometry": {"coordinates":[-118.46838200000001,34.06022],"type":"Point"}
}