{
  "type": "Feature",
  "properties": {
    "addr:full":"834 S Lucerne Blvd Los Angeles CA 90005",
    "addr:housenumber":"834",
    "addr:postcode":"90005",
    "addr:street":"S Lucerne Blvd",
    "iso:country":"US",
    "sg:address":"834 S Lucerne Blvd",
    "sg:city":"Los Angeles",
    "sg:classifiers":[
        {
            "category":"Building & Trades",
            "subcategory":"Electrical",
            "type":"Services"
        }
    ],
    "sg:phone":"+1 323 936 4000",
    "sg:postcode":"90005",
    "sg:province":"CA",
    "sg:tags":[
        "electrician"
    ],
    "wof:name":"Roz'n Roz",
    "wof:placetype":"venue"
},
  "geometry": {"coordinates":[-118.324997,34.059399],"type":"Point"}
}