{
  "type": "Feature",
  "properties": {
    "iso:country":"US",
    "sg:address":"1669 W Arrow Rte",
    "sg:city":"Upland",
    "sg:classifiers":[
        {
            "category":"Personal",
            "type":"Services"
        },
        {
            "category":"Recreation",
            "type":"Entertainment"
        }
    ],
    "sg:phone":"+1 909 579 0511",
    "sg:postcode":"91786",
    "sg:province":"CA",
    "sg:tags":[
        "party",
        "planning",
        "entertainers-family",
        "event",
        "business"
    ],
    "wof:name":"Rk Diversified Entertainment I",
    "wof:placetype":"venue"
},
  "geometry": {"coordinates":[-117.68286500000001,34.099627],"type":"Point"}
}