{
  "type": "Feature",
  "properties": {
    "addr:full":"14111 Sun View Ct Penn Valley CA 95946",
    "addr:housenumber":"14111",
    "addr:postcode":"95946",
    "addr:street":"Sun View Ct",
    "iso:country":"US",
    "sg:address":"14111 Sun View Ct",
    "sg:city":"Penn Valley",
    "sg:classifiers":[
        {
            "category":"Retail",
            "subcategory":"Auto Repair",
            "type":"Services"
        }
    ],
    "sg:phone":"+1 530 477 2215",
    "sg:postcode":"95946",
    "sg:province":"CA",
    "sg:tags":[
        "repairing",
        "automobile"
    ],
    "wof:name":"Wilson's Foreign Cars",
    "wof:placetype":"venue"
},
  "geometry": {"coordinates":[-121.13553400000001,39.16405],"type":"Point"}
}