{
  "type": "Feature",
  "properties": {
    "addr:full":"40829 Winding Way Oakhurst CA 93644",
    "addr:housenumber":"40829",
    "addr:postcode":"93644",
    "addr:street":"Winding Way",
    "iso:country":"US",
    "sg:address":"40829 Winding Way",
    "sg:city":"Oakhurst",
    "sg:classifiers":[
        {
            "category":"Restaurant",
            "type":"Food & Drink"
        }
    ],
    "sg:phone":"+1 559 683 4352",
    "sg:postcode":"93644",
    "sg:province":"CA",
    "sg:tags":[
        "parlor",
        "ice",
        "cream"
    ],
    "wof:name":"Mountain Milk & Cream",
    "wof:placetype":"venue"
},
  "geometry": {"coordinates":[-119.64129,37.341445],"type":"Point"}
}