{
  "type": "Feature",
  "properties": {
    "addr:full":"12601 Pierce St Pacoima CA 91331",
    "addr:housenumber":"12601",
    "addr:postcode":"91331",
    "addr:street":"Pierce St",
    "iso:country":"US",
    "sg:address":"12601 Pierce St",
    "sg:city":"Pacoima",
    "sg:classifiers":[
        {
            "category":"Professional",
            "type":"Services"
        }
    ],
    "sg:phone":"+1 310 391 4880",
    "sg:postcode":"91331",
    "sg:province":"CA",
    "wof:name":"West Coast Rydaz",
    "wof:placetype":"venue"
},
  "geometry": {"coordinates":[-118.40646099999999,34.272634],"type":"Point"}
}