{
  "type": "Feature",
  "properties": {
    "iso:country":"US",
    "sg:address":"2222 Beebee St",
    "sg:city":"San Luis Obispo",
    "sg:classifiers":[
        {
            "category":"Manufacturing",
            "subcategory":"Printing",
            "type":"Manufacturing & Wholesale Goods"
        }
    ],
    "sg:phone":"+1 805 543 6843",
    "sg:postcode":"93401",
    "sg:province":"CA",
    "sg:tags":[
        "offset"
    ],
    "wof:name":"Blake Printery",
    "wof:placetype":"venue"
},
  "geometry": {"coordinates":[-120.667866,35.269357],"type":"Point"}
}