{
  "type": "Feature",
  "properties": {
    "iso:country":"US",
    "sg:address":"1215 S Anaheim Blvd",
    "sg:city":"Anaheim",
    "sg:classifiers":[
        {
            "category":"Restaurant",
            "type":"Food & Drink"
        }
    ],
    "sg:phone":"+1 714 774 0924",
    "sg:postcode":"92805",
    "sg:province":"CA",
    "sg:tags":[
        "pizza"
    ],
    "wof:name":"Miamore",
    "wof:placetype":"venue"
},
  "geometry": {"coordinates":[-117.90799699999999,33.817299],"type":"Point"}
}