{
  "type": "Feature",
  "properties": {
    "iso:country":"US",
    "sg:address":"4154 Voltaire St",
    "sg:city":"San Diego",
    "sg:classifiers":[
        {
            "category":"Shopping",
            "subcategory":"Clothing, Apparel, & Fashions",
            "type":"Retail Goods"
        }
    ],
    "sg:phone":"+1 619 224 1608",
    "sg:postcode":"92107",
    "sg:province":"CA",
    "sg:tags":[
        "building",
        "dressmaker",
        "nonresidential",
        "op"
    ],
    "wof:name":"Connie's Creations",
    "wof:placetype":"venue"
},
  "geometry": {"coordinates":[-117.234104,32.743272],"type":"Point"}
}