{
  "type": "Feature",
  "properties": {
    "addr:full":"10 Refugio Beach Rd Goleta CA 93117",
    "addr:housenumber":"10",
    "addr:postcode":"93117",
    "addr:street":"Refugio Beach Rd",
    "iso:country":"US",
    "sg:address":"10 Refugio Beach Rd",
    "sg:city":"Goleta",
    "sg:classifiers":[
        {
            "category":"Government",
            "subcategory":"Office",
            "type":"Public Place"
        }
    ],
    "sg:phone":"+1 805 968 1033",
    "sg:postcode":"93117",
    "sg:province":"CA",
    "sg:tags":[
        "state",
        "beach"
    ],
    "wof:name":"El Capitan Beach State Park",
    "wof:placetype":"venue"
},
  "geometry": {"coordinates":[-120.065916,34.463981],"type":"Point"}
}