{
  "type": "Feature",
  "properties": {
    "addr:full":"1250 Birchwood Dr Sunnyvale CA 94089",
    "addr:housenumber":"1250",
    "addr:postcode":"94089",
    "addr:street":"Birchwood Dr",
    "iso:country":"US",
    "sg:address":"1250 Birchwood Dr",
    "sg:city":"Sunnyvale",
    "sg:classifiers":[
        {
            "category":"Building & Trades",
            "subcategory":"Construction",
            "type":"Services"
        }
    ],
    "sg:phone":"+1 408 747 5130",
    "sg:postcode":"94089",
    "sg:province":"CA",
    "sg:tags":[
        "contractor"
    ],
    "wof:name":"Summit Ventures I Inc",
    "wof:placetype":"venue"
},
  "geometry": {"coordinates":[-121.992321,37.404922],"type":"Point"}
}