{
  "type": "Feature",
  "properties": {
    "addr:full":"844 Lincoln Blvd Santa Monica CA 90403",
    "addr:housenumber":"844",
    "addr:postcode":"90403",
    "addr:street":"Lincoln Blvd",
    "iso:country":"US",
    "sg:address":"844 Lincoln Blvd",
    "sg:city":"Santa Monica",
    "sg:classifiers":[
        {
            "category":"Communications",
            "type":"Services"
        }
    ],
    "sg:phone":"+1 310 394 7647",
    "sg:postcode":"90403",
    "sg:province":"CA",
    "sg:tags":[
        "communication"
    ],
    "wof:name":"Outside Lines Communications I",
    "wof:placetype":"venue"
},
  "geometry": {"coordinates":[-118.49991799999999,34.0268],"type":"Point"}
}