{
  "type": "Feature",
  "properties": {
    "iso:country":"US",
    "sg:address":"2212 Siesta Ln",
    "sg:city":"Santa Rosa",
    "sg:classifiers":[
        {
            "category":"Real Estate",
            "subcategory":"Real Estate Agent",
            "type":"Services"
        }
    ],
    "sg:phone":"+1 707 575 7088",
    "sg:postcode":"95404",
    "sg:province":"CA",
    "wof:name":"Glenn Pope",
    "wof:placetype":"venue"
},
  "geometry": {"coordinates":[-122.69248,38.451711],"type":"Point"}
}