{
  "type": "Feature",
  "properties": {
    "addr:full":"251 Vineyard Blvd Morgan Hill CA 95037",
    "addr:housenumber":"251",
    "addr:postcode":"95037",
    "addr:street":"Vineyard Blvd",
    "iso:country":"US",
    "sg:address":"251 Vineyard Blvd",
    "sg:city":"Morgan Hill",
    "sg:classifiers":[
        {
            "category":"Restaurant",
            "type":"Food & Drink"
        }
    ],
    "sg:phone":"+1 408 779 8692",
    "sg:postcode":"95037",
    "sg:province":"CA",
    "sg:tags":[
        "shop",
        "coffee"
    ],
    "wof:name":"Starbucks",
    "wof:placetype":"venue"
},
  "geometry": {"coordinates":[-121.641321,37.11013],"type":"Point"}
}