{
  "type": "Feature",
  "properties": {
    "addr:full":"2951 Monterey Rd Suite 40 San Jose CA 95111",
    "addr:housenumber":"2951;40",
    "addr:postcode":"95111",
    "addr:street":"Monterey Rd Suite;Jose",
    "iso:country":"US",
    "sg:address":"2951 Monterey Rd Suite 40",
    "sg:city":"San Jose",
    "sg:classifiers":[
        {
            "category":"Personal",
            "subcategory":"Beauty Salon",
            "type":"Services"
        }
    ],
    "sg:phone":"+1 408 225 5881",
    "sg:postcode":"95111",
    "sg:province":"CA",
    "sg:tags":[
        "spa"
    ],
    "wof:name":"E-Z Nails",
    "wof:placetype":"venue"
},
  "geometry": {"coordinates":[-121.739043,37.216236],"type":"Point"}
}