{
  "type": "Feature",
  "properties": {
    "addr:full":"6607 Holmes Ave Los Angeles CA 90001",
    "addr:housenumber":"6607",
    "addr:postcode":"90001",
    "addr:street":"Holmes Ave",
    "iso:country":"US",
    "sg:address":"6607 Holmes Ave",
    "sg:city":"Los Angeles",
    "sg:classifiers":[
        {
            "category":"Home & Garden",
            "subcategory":"Building Materials",
            "type":"Retail Goods"
        }
    ],
    "sg:phone":"+1 323 583 6434",
    "sg:postcode":"90001",
    "sg:province":"CA",
    "sg:tags":[
        "glass",
        "window",
        "plate"
    ],
    "wof:name":"Rivera Glass",
    "wof:placetype":"venue"
},
  "geometry": {"coordinates":[-118.241215,33.97887],"type":"Point"}
}