{
  "type": "Feature",
  "properties": {
    "addr:full":"1831 Solano Ave Berkeley CA 94707",
    "addr:housenumber":"1831",
    "addr:postcode":"94707",
    "addr:street":"Solano Ave",
    "iso:country":"US",
    "sg:address":"1831 Solano Ave",
    "sg:city":"Berkeley",
    "sg:classifiers":[
        {
            "category":"Government",
            "subcategory":"Post Office",
            "type":"Public Place"
        }
    ],
    "sg:phone":"+1 800 275 8777",
    "sg:postcode":"94707",
    "sg:province":"CA",
    "sg:website":"www.usps.com",
    "wof:name":"US Post Office - Landscape",
    "wof:placetype":"venue"
},
  "geometry": {"coordinates":[-122.27906,37.891368],"type":"Point"}
}