{
  "type": "Feature",
  "properties": {
    "addr:full":"7317 Pacific Blvd Huntington Park CA 90255",
    "addr:housenumber":"7317",
    "addr:postcode":"90255",
    "addr:street":"Pacific Blvd;Park",
    "iso:country":"US",
    "sg:address":"7317 Pacific Blvd",
    "sg:city":"Huntington Park",
    "sg:classifiers":[
        {
            "category":"Restaurant",
            "type":"Food & Drink"
        }
    ],
    "sg:phone":"+1 323 583 3905",
    "sg:postcode":"90255",
    "sg:province":"CA",
    "wof:name":"Taqueria El Mexicano",
    "wof:placetype":"venue"
},
  "geometry": {"coordinates":[-118.224998,33.972599],"type":"Point"}
}