{
  "type": "Feature",
  "properties": {
    "addr:full":"300 A St Hayward CA 94541",
    "addr:housenumber":"300",
    "addr:postcode":"94541",
    "addr:street":"A St",
    "iso:country":"US",
    "sg:address":"300 A St",
    "sg:city":"Hayward",
    "sg:classifiers":[
        {
            "category":"Professional",
            "type":"Services"
        }
    ],
    "sg:phone":"+1 510 728 8464",
    "sg:postcode":"94541",
    "sg:province":"CA",
    "sg:tags":[
        "establishment"
    ],
    "wof:name":"Jessica's Little House",
    "wof:placetype":"venue"
},
  "geometry": {"coordinates":[-122.094002,37.669295],"type":"Point"}
}