{
  "type": "Feature",
  "properties": {
    "iso:country":"US",
    "sg:address":"789 18th Ave",
    "sg:city":"Lemoore",
    "sg:classifiers":[
        {
            "category":"Social Services",
            "type":"Services"
        }
    ],
    "sg:phone":"+1 559 924 7791",
    "sg:postcode":"93245",
    "sg:province":"CA",
    "sg:tags":[
        "senior",
        "citizen"
    ],
    "wof:name":"Lemoore Senior Citizen Ctr",
    "wof:placetype":"venue"
},
  "geometry": {"coordinates":[-119.78093800000001,36.305676],"type":"Point"}
}