{
  "type": "Feature",
  "properties": {
    "iso:country":"US",
    "sg:address":"13630 Atlantis Way",
    "sg:city":"Garden Grove",
    "sg:classifiers":[
        {
            "category":"Park",
            "type":"Public Place"
        },
        {
            "category":"Recreation",
            "subcategory":"Playground",
            "type":"Entertainment"
        }
    ],
    "sg:phone":"+1 714 892 6015",
    "sg:postcode":"92844",
    "sg:province":"CA",
    "sg:website":"www.ci.garden-grove.ca.us/?q=com...",
    "wof:name":"Atlantis Play Center",
    "wof:placetype":"venue"
},
  "geometry": {"coordinates":[-117.96836,33.764494],"type":"Point"}
}