{
  "type": "Feature",
  "properties": {
    "addr:full":"409 Elizabeth St Vacaville CA 95688",
    "addr:housenumber":"409",
    "addr:postcode":"95688",
    "addr:street":"Elizabeth St",
    "iso:country":"US",
    "sg:address":"409 Elizabeth St",
    "sg:city":"Vacaville",
    "sg:classifiers":[
        {
            "category":"Communications",
            "subcategory":"Film & Video Production",
            "type":"Services"
        }
    ],
    "sg:phone":"+1 707 447 1773",
    "sg:postcode":"95688",
    "sg:province":"CA",
    "sg:tags":[
        "taping"
    ],
    "wof:name":"Towne Cryer Pro Video",
    "wof:placetype":"venue"
},
  "geometry": {"coordinates":[-121.98754700000001,38.353992],"type":"Point"}
}