{
  "type": "Feature",
  "properties": {
    "addr:full":"3609 N Long Beach Blvd Long Beach CA 90807",
    "addr:housenumber":"3609",
    "addr:postcode":"90807",
    "addr:street":"N Long Beach Blvd",
    "iso:country":"US",
    "sg:address":"3609 N Long Beach Blvd",
    "sg:city":"Long Beach",
    "sg:classifiers":[
        {
            "category":"Professional",
            "subcategory":"Employment Agencies",
            "type":"Services"
        }
    ],
    "sg:phone":"+1 562 492 1227",
    "sg:postcode":"90807",
    "sg:province":"CA",
    "wof:name":"Accounting Advantage",
    "wof:placetype":"venue"
},
  "geometry": {"coordinates":[-118.189424,33.822871],"type":"Point"}
}