{
  "type": "Feature",
  "properties": {
    "iso:country":"US",
    "sg:address":"9513 Natick Ave",
    "sg:city":"North Hills",
    "sg:classifiers":[
        {
            "category":"Personal",
            "subcategory":"Beauty Salon",
            "type":"Services"
        }
    ],
    "sg:phone":"+1 818 892 9589",
    "sg:postcode":"91343",
    "sg:province":"CA",
    "wof:name":"Vanessa's Beauty Salon",
    "wof:placetype":"venue"
},
  "geometry": {"coordinates":[-118.456396,34.243638],"type":"Point"}
}