{
  "type": "Feature",
  "properties": {
    "addr:full":"17607 Ranchero Rd Hesperia CA 92345",
    "addr:housenumber":"17607",
    "addr:postcode":"92345",
    "addr:street":"Ranchero Rd",
    "iso:country":"US",
    "sg:address":"17607 Ranchero Rd",
    "sg:city":"Hesperia",
    "sg:classifiers":[
        {
            "category":"Education",
            "subcategory":"School",
            "type":"Public Place"
        }
    ],
    "sg:phone":"+1 760 948 0175",
    "sg:postcode":"92345",
    "sg:province":"CA",
    "wof:name":"Ranchero Middle School",
    "wof:placetype":"venue"
},
  "geometry": {"coordinates":[-117.278774,34.383726],"type":"Point"}
}