{
  "type": "Feature",
  "properties": {
    "iso:country":"US",
    "sg:address":"9095 Central Ave",
    "sg:city":"Montclair",
    "sg:classifiers":[
        {
            "category":"Shopping",
            "subcategory":"Shoes",
            "type":"Retail Goods"
        }
    ],
    "sg:phone":"+1 909 624 1718",
    "sg:postcode":"91763",
    "sg:province":"CA",
    "wof:name":"Shoe City Montclair",
    "wof:placetype":"venue"
},
  "geometry": {"coordinates":[-117.689532,34.089168],"type":"Point"}
}