{
  "type": "Feature",
  "properties": {
    "addr:full":"2011 Platform Pl Oxnard CA 93035",
    "addr:housenumber":"2011",
    "addr:postcode":"93035",
    "addr:street":"Platform Pl",
    "iso:country":"US",
    "sg:address":"2011 Platform Pl",
    "sg:city":"Oxnard",
    "sg:classifiers":[
        {
            "category":"Freight",
            "type":"Transportation"
        }
    ],
    "sg:phone":"+1 805 984 5906",
    "sg:postcode":"93035",
    "sg:province":"CA",
    "sg:tags":[
        "operator",
        "local",
        "trucking"
    ],
    "wof:name":"Madrigal Javier",
    "wof:placetype":"venue"
},
  "geometry": {"coordinates":[-119.19990900000001,34.190983],"type":"Point"}
}