{
  "type": "Feature",
  "properties": {
    "iso:country":"US",
    "sg:address":"1440 Ella St",
    "sg:city":"San Luis Obispo",
    "sg:classifiers":[
        {
            "category":"Real Estate",
            "subcategory":"Real Estate Agent",
            "type":"Services"
        }
    ],
    "sg:phone":"+1 805 543 0559",
    "sg:postcode":"93401",
    "sg:province":"CA",
    "sg:tags":[
        "appraiser"
    ],
    "wof:name":"Rick Lewis Appraisals",
    "wof:placetype":"venue"
},
  "geometry": {"coordinates":[-120.64850199999999,35.277718],"type":"Point"}
}