{
  "type": "Feature",
  "properties": {
    "addr:full":"11656 Ventura Blvd Studio City CA 91604",
    "addr:housenumber":"11656",
    "addr:postcode":"91604",
    "addr:street":"Ventura Blvd",
    "iso:country":"US",
    "sg:address":"11656 Ventura Blvd",
    "sg:city":"Studio City",
    "sg:classifiers":[
        {
            "category":"Retail",
            "subcategory":"Auto Rental",
            "type":"Services"
        }
    ],
    "sg:phone":"+1 818 754 1322",
    "sg:postcode":"91604",
    "sg:province":"CA",
    "sg:tags":[
        "car"
    ],
    "sg:website":"avis.com",
    "wof:name":"Avis",
    "wof:placetype":"venue"
},
  "geometry": {"coordinates":[-118.386517,34.14072],"type":"Point"}
}