{
  "type": "Feature",
  "properties": {
    "addr:full":"1212 N San Fernando Blvd Ste J Burbank CA 91504",
    "addr:housenumber":"1212",
    "addr:postcode":"91504",
    "addr:street":"N San Fernando Blvd Ste J",
    "iso:country":"US",
    "sg:address":"1212 N San Fernando Blvd Ste J",
    "sg:city":"Burbank",
    "sg:classifiers":[
        {
            "category":"Personal",
            "subcategory":"Massage",
            "type":"Services"
        },
        {
            "category":"Personal",
            "subcategory":"Day Spa",
            "type":"Services"
        }
    ],
    "sg:phone":"+1 818 557 6261",
    "sg:postcode":"91504",
    "sg:province":"CA",
    "sg:website":"www.chabamassage.com/",
    "wof:name":"Chaba Spa",
    "wof:placetype":"venue"
},
  "geometry": {"coordinates":[-118.319729,34.189388],"type":"Point"}
}