{
  "type": "Feature",
  "properties": {
    "addr:full":"410 7th St Oakland CA 94607",
    "addr:housenumber":"410",
    "addr:postcode":"94607",
    "addr:street":"7Th St",
    "iso:country":"US",
    "sg:address":"410 7th St",
    "sg:city":"Oakland",
    "sg:classifiers":[
        {
            "category":"Food & Beverages",
            "subcategory":"Groceries & Convenience Stores",
            "type":"Retail Goods"
        }
    ],
    "sg:phone":"+1 510 444 1220",
    "sg:postcode":"94607",
    "sg:province":"CA",
    "wof:name":"Orient Market Inc.",
    "wof:placetype":"venue"
},
  "geometry": {"coordinates":[-122.274002,37.7994],"type":"Point"}
}