{
  "type": "Feature",
  "properties": {
    "iso:country":"US",
    "sg:address":"1212 Market Street",
    "sg:city":"San Francisco",
    "sg:classifiers":[
        {
            "category":"Real Estate",
            "subcategory":"Real Estate Services",
            "type":"Services"
        }
    ],
    "sg:phone":"+1 415 861 2581",
    "sg:postcode":"94102",
    "sg:province":"CA",
    "sg:tags":[
        "management",
        "property"
    ],
    "wof:name":"Yully Company",
    "wof:placetype":"venue"
},
  "geometry": {"coordinates":[-122.415001,37.778702],"type":"Point"}
}