{
  "type": "Feature",
  "properties": {
    "iso:country":"US",
    "sg:address":"2600 Industrial Blvd",
    "sg:city":"West Sacramento",
    "sg:classifiers":[
        {
            "category":"Wholesale",
            "subcategory":"Motor Vehicles",
            "type":"Manufacturing & Wholesale Goods"
        }
    ],
    "sg:phone":"+1 916 375 1695",
    "sg:postcode":"95691",
    "sg:province":"CA",
    "sg:tags":[
        "trailer"
    ],
    "sg:website":"www.hddistribution.com",
    "wof:name":"H D Distribution",
    "wof:placetype":"venue"
},
  "geometry": {"coordinates":[-121.548677,38.56877],"type":"Point"}
}