{
  "type": "Feature",
  "properties": {
    "addr:full":"2523 California St San Francisco CA 94115",
    "addr:housenumber":"2523",
    "addr:postcode":"94115",
    "addr:street":"California St",
    "iso:country":"US",
    "sg:address":"2523 California St",
    "sg:city":"San Francisco",
    "sg:classifiers":[
        {
            "category":"Real Estate",
            "subcategory":"Real Estate Agent",
            "type":"Services"
        }
    ],
    "sg:phone":"+1 415 674 6550",
    "sg:postcode":"94115",
    "sg:province":"CA",
    "sg:website":"www.mattlanning.com",
    "wof:name":"Matt Lanning - Zephyr Real Estate",
    "wof:placetype":"venue"
},
  "geometry": {"coordinates":[-122.435864,37.788671],"type":"Point"}
}