{
  "type": "Feature",
  "properties": {
    "iso:country":"US",
    "sg:address":"403 McCormick St",
    "sg:city":"San Leandro",
    "sg:classifiers":[
        {
            "category":"Communications",
            "subcategory":"Television Station",
            "type":"Services"
        }
    ],
    "sg:phone":"+1 510 632 5385",
    "sg:postcode":"94577",
    "sg:province":"CA",
    "wof:name":"Univision Communicatoins",
    "wof:placetype":"venue"
},
  "geometry": {"coordinates":[-122.191831,37.725349],"type":"Point"}
}