{
  "type": "Feature",
  "properties": {
    "addr:full":"1036 Copper Ct Vacaville CA 95687",
    "addr:housenumber":"1036",
    "addr:postcode":"95687",
    "addr:street":"Copper Ct",
    "iso:country":"US",
    "sg:address":"1036 Copper Ct",
    "sg:city":"Vacaville",
    "sg:classifiers":[
        {
            "category":"Freight",
            "type":"Transportation"
        }
    ],
    "sg:phone":"+1 707 448 5984",
    "sg:postcode":"95687",
    "sg:province":"CA",
    "sg:tags":[
        "operator",
        "local",
        "trucking"
    ],
    "wof:name":"D Laws Trucking",
    "wof:placetype":"venue"
},
  "geometry": {"coordinates":[-121.952963,38.324309],"type":"Point"}
}