{
  "type": "Feature",
  "properties": {
    "iso:country":"US",
    "sg:address":"593 Acacia Dr",
    "sg:city":"Crestline",
    "sg:classifiers":[
        {
            "category":"Wholesale",
            "subcategory":"Construction Materials",
            "type":"Manufacturing & Wholesale Goods"
        }
    ],
    "sg:phone":"+1 909 338 8408",
    "sg:postcode":"92325",
    "sg:province":"CA",
    "sg:tags":[
        "timberland",
        "company",
        "timber"
    ],
    "wof:name":"Timber Masters",
    "wof:placetype":"venue"
},
  "geometry": {"coordinates":[-117.256595,34.242222],"type":"Point"}
}