{
  "type": "Feature",
  "properties": {
    "iso:country":"US",
    "sg:address":"2965 East St",
    "sg:city":"Anderson",
    "sg:classifiers":[
        {
            "category":"Home & Garden",
            "subcategory":"Furniture",
            "type":"Retail Goods"
        }
    ],
    "sg:phone":"+1 530 365 1309",
    "sg:postcode":"96007",
    "sg:province":"CA",
    "wof:name":"Epperson's Furniture",
    "wof:placetype":"venue"
},
  "geometry": {"coordinates":[-122.298948,40.451761],"type":"Point"}
}