{
  "type": "Feature",
  "properties": {
    "iso:country":"US",
    "sg:address":"79110 Victoria Dr",
    "sg:city":"La Quinta",
    "sg:classifiers":[
        {
            "category":"Wholesale",
            "subcategory":"Groceries",
            "type":"Manufacturing & Wholesale Goods"
        }
    ],
    "sg:phone":"+1 760 772 9201",
    "sg:postcode":"92253",
    "sg:province":"CA",
    "sg:tags":[
        "food",
        "import",
        "indian"
    ],
    "wof:name":"Shantinath Import Export",
    "wof:placetype":"venue"
},
  "geometry": {"coordinates":[-116.285079,33.718265],"type":"Point"}
}