{
  "type": "Feature",
  "properties": {
    "addr:full":"1891 McCloskey Rd Hollister CA 95023",
    "addr:housenumber":"1891",
    "addr:postcode":"hollister ca 95023",
    "addr:street":"Mccloskey Rd",
    "iso:country":"US",
    "sg:address":"1891 McCloskey Rd",
    "sg:city":"Hollister",
    "sg:classifiers":[
        {
            "category":"Shopping",
            "subcategory":"Bicycles & Sporting Goods",
            "type":"Retail Goods"
        }
    ],
    "sg:phone":"+1 831 637 3307",
    "sg:postcode":"95023",
    "sg:province":"CA",
    "wof:name":"Frank Brown Saddlery",
    "wof:placetype":"venue"
},
  "geometry": {"coordinates":[-121.366112,36.868138],"type":"Point"}
}