{
  "type": "Feature",
  "properties": {
    "addr:full":"1400 Maiden Ln Del Mar CA 92014",
    "addr:housenumber":"1400",
    "addr:postcode":"92014",
    "addr:street":"Maiden Ln",
    "iso:country":"US",
    "sg:address":"1400 Maiden Ln",
    "sg:city":"Del Mar",
    "sg:classifiers":[
        {
            "category":"Organizations",
            "subcategory":"Community Association",
            "type":"Services"
        }
    ],
    "sg:phone":"+1 858 259 0374",
    "sg:postcode":"92014",
    "sg:province":"CA",
    "sg:tags":[
        "environmental",
        "org"
    ],
    "wof:name":"Fundacion Scientificca Sfc",
    "wof:placetype":"venue"
},
  "geometry": {"coordinates":[-117.26452999999999,32.959299],"type":"Point"}
}