{
  "type": "Feature",
  "properties": {
    "addr:full":"8024 W 3rd St Los Angeles CA 90048",
    "addr:housenumber":"8024",
    "addr:postcode":"90048",
    "addr:street":"W 3Rd St",
    "iso:country":"US",
    "sg:address":"8024 W 3rd St",
    "sg:city":"Los Angeles",
    "sg:classifiers":[
        {
            "category":"Professional",
            "type":"Services"
        }
    ],
    "sg:phone":"+1 323 651 2366",
    "sg:postcode":"90048",
    "sg:province":"CA",
    "sg:tags":[
        "establishment"
    ],
    "wof:name":"Neilie Girl",
    "wof:placetype":"venue"
},
  "geometry": {"coordinates":[-118.363997,34.071773],"type":"Point"}
}