{
  "type": "Feature",
  "properties": {
    "iso:country":"US",
    "sg:address":"991 N Tustin St",
    "sg:city":"Orange",
    "sg:classifiers":[
        {
            "category":"Autos & Motor Vehicles",
            "subcategory":"Automobile Sales",
            "type":"Retail Goods"
        }
    ],
    "sg:phone":"+1 714 639 6679",
    "sg:postcode":"92867",
    "sg:province":"CA",
    "sg:tags":[
        "car",
        "dealer"
    ],
    "wof:name":"S & A Auto Sales",
    "wof:placetype":"venue"
},
  "geometry": {"coordinates":[-117.835621,33.802307],"type":"Point"}
}