{
  "type": "Feature",
  "properties": {
    "iso:country":"US",
    "sg:address":"1200 E Hill Rd",
    "sg:city":"Willits",
    "sg:classifiers":[
        {
            "category":"Retail",
            "subcategory":"Veterinary Services",
            "type":"Services"
        }
    ],
    "sg:phone":"+1 707 459 5236",
    "sg:postcode":"95490",
    "sg:province":"CA",
    "sg:tags":[
        "veterinarian"
    ],
    "wof:name":"East Hill Veterinary Clinic",
    "wof:placetype":"venue"
},
  "geometry": {"coordinates":[-123.325924,39.392435],"type":"Point"}
}