{
  "type": "Feature",
  "properties": {
    "iso:country":"US",
    "sg:address":"6601 Santa Monica Blvd",
    "sg:city":"Los Angeles",
    "sg:classifiers":[
        {
            "category":"Wholesale",
            "subcategory":"Durable Goods & Equipment",
            "type":"Manufacturing & Wholesale Goods"
        }
    ],
    "sg:phone":"+1 323 462 7816",
    "sg:postcode":"90038",
    "sg:province":"CA",
    "sg:tags":[
        "representative",
        "manufacturer"
    ],
    "sg:website":"www.lightningstrikes.com",
    "wof:name":"Lightening Strikes Inc",
    "wof:placetype":"venue"
},
  "geometry": {"coordinates":[-118.33628299999999,34.090716],"type":"Point"}
}