{
  "type": "Feature",
  "properties": {
    "addr:full":"7520 El Cajon Blvd La Mesa CA 91941",
    "addr:housenumber":"7520",
    "addr:postcode":"91941",
    "addr:street":"El Cajon Blvd",
    "iso:country":"US",
    "sg:address":"7520 El Cajon Blvd",
    "sg:city":"La Mesa",
    "sg:classifiers":[
        {
            "category":"Restaurant",
            "type":"Food & Drink"
        }
    ],
    "sg:phone":"+1 619 460 1300",
    "sg:postcode":"91941",
    "sg:province":"CA",
    "sg:tags":[
        "mexican"
    ],
    "wof:name":"Tacos & Grill Inc.",
    "wof:placetype":"venue"
},
  "geometry": {"coordinates":[-117.03543999999999,32.768405],"type":"Point"}
}