{
  "type": "Feature",
  "properties": {
    "iso:country":"US",
    "sg:address":"2603 Lee Ave",
    "sg:city":"South El Monte",
    "sg:classifiers":[
        {
            "category":"Manufacturing",
            "subcategory":"Signs",
            "type":"Manufacturing & Wholesale Goods"
        }
    ],
    "sg:phone":"+1 626 444 6819",
    "sg:postcode":"91733",
    "sg:province":"CA",
    "sg:tags":[
        "specialty",
        "mfg"
    ],
    "wof:name":"Wing's Neon Sign Inc",
    "wof:placetype":"venue"
},
  "geometry": {"coordinates":[-118.067366,34.06007],"type":"Point"}
}