{
  "type": "Feature",
  "properties": {
    "iso:country":"US",
    "sg:address":"428 W 6th St",
    "sg:city":"Tustin",
    "sg:classifiers":[
        {
            "category":"Manufacturing",
            "subcategory":"Printing",
            "type":"Manufacturing & Wholesale Goods"
        }
    ],
    "sg:phone":"+1 714 731 2484",
    "sg:postcode":"92780",
    "sg:province":"CA",
    "sg:tags":[
        "lithographic",
        "commercial"
    ],
    "wof:name":"California Kist",
    "wof:placetype":"venue"
},
  "geometry": {"coordinates":[-117.82755299999999,33.739979],"type":"Point"}
}