{
  "type": "Feature",
  "properties": {
    "iso:country":"US",
    "sg:address":"5943 Melvin Ave",
    "sg:city":"Tarzana",
    "sg:classifiers":[
        {
            "category":"Manufacturing",
            "subcategory":"Printing",
            "type":"Manufacturing & Wholesale Goods"
        }
    ],
    "sg:phone":"+1 818 774 1441",
    "sg:postcode":"91356",
    "sg:province":"CA",
    "sg:tags":[
        "publisher",
        "music"
    ],
    "sg:website":"www.hotlatintracks.com",
    "wof:name":"Indart Music",
    "wof:placetype":"venue"
},
  "geometry": {"coordinates":[-118.560015,34.17581],"type":"Point"}
}