{
  "type": "Feature",
  "properties": {
    "addr:full":"1320 Grand Ave San Marcos CA 92078",
    "addr:housenumber":"1320",
    "addr:postcode":"92078",
    "addr:street":"Grand Ave",
    "iso:country":"US",
    "sg:address":"1320 Grand Ave",
    "sg:city":"San Marcos",
    "sg:classifiers":[
        {
            "category":"Wholesale",
            "subcategory":"Apparel",
            "type":"Manufacturing & Wholesale Goods"
        },
        {
            "category":"Manufacturing",
            "subcategory":"Retail Goods",
            "type":"Manufacturing & Wholesale Goods"
        }
    ],
    "sg:phone":"+1 760 510 9600",
    "sg:postcode":"92078",
    "sg:province":"CA",
    "sg:tags":[
        "me",
        "durable",
        "piece",
        "maker",
        "button"
    ],
    "sg:website":"www.rubberstampchamp.com",
    "wof:name":"Rubber Stamp and Button Champ",
    "wof:placetype":"venue"
},
  "geometry": {"coordinates":[-117.193836,33.143732],"type":"Point"}
}