{
  "type": "Feature",
  "properties": {
    "addr:full":"6450 Melrose Dr North Highlands CA 95660",
    "addr:housenumber":"6450",
    "addr:postcode":"95660",
    "addr:street":"Melrose Dr",
    "iso:country":"US",
    "sg:address":"6450 Melrose Dr",
    "sg:city":"North Highlands",
    "sg:classifiers":[
        {
            "category":"Building & Trades",
            "subcategory":"Construction",
            "type":"Services"
        }
    ],
    "sg:phone":"+1 916 275 4119",
    "sg:postcode":"95660",
    "sg:province":"CA",
    "sg:tags":[
        "painter"
    ],
    "wof:name":"A Plus Painting",
    "wof:placetype":"venue"
},
  "geometry": {"coordinates":[-121.376564,38.682529],"type":"Point"}
}