{
  "type": "Feature",
  "properties": {
    "addr:full":"1453 W 8th St San Pedro CA 90732",
    "addr:housenumber":"1453",
    "addr:postcode":"90732",
    "addr:street":"W 8Th St",
    "iso:country":"US",
    "sg:address":"1453 W 8th St",
    "sg:city":"San Pedro",
    "sg:classifiers":[
        {
            "category":"Social Services",
            "type":"Services"
        }
    ],
    "sg:phone":"+1 310 831 5902",
    "sg:postcode":"90732",
    "sg:province":"CA",
    "sg:tags":[
        "organization",
        "welfare"
    ],
    "wof:name":"Easter Seals Southern Ca",
    "wof:placetype":"venue"
},
  "geometry": {"coordinates":[-118.307748,33.73701],"type":"Point"}
}