{
  "type": "Feature",
  "properties": {
    "iso:country":"US",
    "sg:address":"23392 Bolivar",
    "sg:city":"Mission Viejo",
    "sg:classifiers":[
        {
            "category":"Shopping",
            "subcategory":"Bicycles & Sporting Goods",
            "type":"Retail Goods"
        }
    ],
    "sg:phone":"+1 949 587 1431",
    "sg:postcode":"92691",
    "sg:province":"CA",
    "wof:name":"Primm Motorsports",
    "wof:placetype":"venue"
},
  "geometry": {"coordinates":[-117.651928,33.6233],"type":"Point"}
}