{
  "type": "Feature",
  "properties": {
    "addr:full":"22250 Ave 256 Lindsay CA 93247",
    "addr:housenumber":"22250;256",
    "addr:postcode":"93247",
    "addr:street":"Ave",
    "iso:country":"US",
    "sg:address":"22250 Ave 256",
    "sg:city":"Lindsay",
    "sg:classifiers":[
        {
            "category":"Professional",
            "type":"Services"
        }
    ],
    "sg:phone":"+1 559 562 4786",
    "sg:postcode":"93247",
    "sg:province":"CA",
    "wof:name":"Martin Hochi",
    "wof:placetype":"venue"
},
  "geometry": {"coordinates":[-119.07695200000001,36.253701],"type":"Point"}
}