{
  "type": "Feature",
  "properties": {
    "addr:full":"456 S Sierra Way San Bernardino CA 92408",
    "addr:housenumber":"456",
    "addr:postcode":"92408",
    "addr:street":"S Sierra Way",
    "iso:country":"US",
    "sg:address":"456 S Sierra Way",
    "sg:city":"San Bernardino",
    "sg:classifiers":[
        {
            "category":"Wholesale",
            "subcategory":"Auto Parts",
            "type":"Manufacturing & Wholesale Goods"
        }
    ],
    "sg:phone":"+1 909 888 9859",
    "sg:postcode":"92408",
    "sg:province":"CA",
    "sg:tags":[
        "shaft",
        "drive"
    ],
    "wof:name":"Ed Moore Drive Lines",
    "wof:placetype":"venue"
},
  "geometry": {"coordinates":[-117.285229,34.096163],"type":"Point"}
}