{
  "type": "Feature",
  "properties": {
    "addr:full":"3720 N 1st St Ste 10 San Jose CA 95134",
    "addr:housenumber":"3720",
    "addr:postcode":"95134",
    "addr:street":"N 1St St Ste 10 San Jose",
    "iso:country":"US",
    "sg:address":"3720 N 1st St Ste 10",
    "sg:city":"San Jose",
    "sg:classifiers":[
        {
            "category":"Wholesale",
            "subcategory":"Home Furnishings",
            "type":"Manufacturing & Wholesale Goods"
        }
    ],
    "sg:postcode":"95134",
    "sg:province":"CA",
    "sg:tags":[
        "plate",
        "tapas/small"
    ],
    "wof:name":"La Catalana",
    "wof:placetype":"venue"
},
  "geometry": {"coordinates":[-121.945722,37.410436],"type":"Point"}
}