{
  "type": "Feature",
  "properties": {
    "iso:country":"US",
    "sg:address":"250 E Garvey Ave",
    "sg:city":"Monterey Park",
    "sg:classifiers":[
        {
            "category":"Shopping",
            "subcategory":"Jewelry",
            "type":"Retail Goods"
        }
    ],
    "sg:phone":"+1 626 307 4312",
    "sg:postcode":"91755",
    "sg:province":"CA",
    "wof:name":"S H Gold Bullion Inc",
    "wof:placetype":"venue"
},
  "geometry": {"coordinates":[-118.120003,34.062401],"type":"Point"}
}