{
  "type": "Feature",
  "properties": {
    "iso:country":"US",
    "sg:address":"14048 Firestone Blvd",
    "sg:city":"Santa Fe Springs",
    "sg:classifiers":[
        {
            "category":"Autos & Motor Vehicles",
            "subcategory":"Auto Supplies",
            "type":"Retail Goods"
        }
    ],
    "sg:phone":"+1 562 926 9338",
    "sg:postcode":"90670",
    "sg:province":"CA",
    "sg:tags":[
        "wheel",
        "cover"
    ],
    "wof:name":"Wheel N Audio Pro",
    "wof:placetype":"venue"
},
  "geometry": {"coordinates":[-118.032746,33.885959],"type":"Point"}
}