{
  "type": "Feature",
  "properties": {
    "addr:full":"1820 W Orangewood Ave Orange CA 92868",
    "addr:housenumber":"1820",
    "addr:postcode":"92868",
    "addr:street":"W Orangewood Ave",
    "iso:country":"US",
    "sg:address":"1820 W Orangewood Ave",
    "sg:city":"Orange",
    "sg:classifiers":[
        {
            "category":"Banks & Credit Unions",
            "subcategory":"Bank",
            "type":"Services"
        }
    ],
    "sg:phone":"+1 714 935 9595",
    "sg:postcode":"92868",
    "sg:province":"CA",
    "sg:tags":[
        "loan"
    ],
    "wof:name":"Allstate Home Loans",
    "wof:placetype":"venue"
},
  "geometry": {"coordinates":[-117.871454,33.795145],"type":"Point"}
}