{
  "type": "Feature",
  "properties": {
    "iso:country":"US",
    "sg:address":"17800 S Main St Ste 202",
    "sg:city":"Gardena",
    "sg:classifiers":[
        {
            "category":"Professional",
            "subcategory":"Printing & Photocopies",
            "type":"Services"
        }
    ],
    "sg:phone":"+1 310 327 7442",
    "sg:postcode":"90248",
    "sg:province":"CA",
    "sg:tags":[
        "screen"
    ],
    "wof:name":"Bahia South Silkscreen",
    "wof:placetype":"venue"
},
  "geometry": {"coordinates":[-118.275459,33.869038],"type":"Point"}
}