{
  "type": "Feature",
  "properties": {
    "iso:country":"US",
    "sg:address":"14471 Big Basin Way",
    "sg:city":"Saratoga",
    "sg:classifiers":[
        {
            "category":"Professional",
            "subcategory":"Management & Consulting",
            "type":"Services"
        }
    ],
    "sg:phone":"+1 408 872 3102",
    "sg:postcode":"95070",
    "sg:province":"CA",
    "sg:tags":[
        "consultant",
        "training"
    ],
    "wof:name":"Prodex TCR",
    "wof:placetype":"venue"
},
  "geometry": {"coordinates":[-122.03283399999999,37.258619],"type":"Point"}
}