{
  "type": "Feature",
  "properties": {
    "addr:full":"1426 Buena St Oceanside CA 92058",
    "addr:housenumber":"1426",
    "addr:postcode":"92058",
    "addr:street":"Buena St",
    "iso:country":"US",
    "sg:address":"1426 Buena St",
    "sg:city":"Oceanside",
    "sg:classifiers":[
        {
            "category":"Wholesale",
            "subcategory":"Electrical",
            "type":"Manufacturing & Wholesale Goods"
        }
    ],
    "sg:phone":"+1 760 967 2795",
    "sg:postcode":"92058",
    "sg:province":"CA",
    "sg:tags":[
        "equipment"
    ],
    "wof:name":"Saneco",
    "wof:placetype":"venue"
},
  "geometry": {"coordinates":[-117.370216,33.202631],"type":"Point"}
}