{
  "type": "Feature",
  "properties": {
    "iso:country":"US",
    "sg:address":"980 Post St",
    "sg:city":"Alameda",
    "sg:classifiers":[
        {
            "category":"Professional",
            "type":"Services"
        }
    ],
    "sg:phone":"+1 510 749 7596",
    "sg:postcode":"94501",
    "sg:province":"CA",
    "wof:name":"Kondo Inc",
    "wof:placetype":"venue"
},
  "geometry": {"coordinates":[-122.23700599999999,37.752317],"type":"Point"}
}