{
  "type": "Feature",
  "properties": {
    "addr:full":"391 S Lilac Ct Anaheim CA 92808",
    "addr:housenumber":"391",
    "addr:postcode":"92808",
    "addr:street":"S Lilac Ct",
    "iso:country":"US",
    "sg:address":"391 S Lilac Ct",
    "sg:city":"Anaheim",
    "sg:classifiers":[
        {
            "category":"Autos & Motor Vehicles",
            "subcategory":"Auto Supplies",
            "type":"Retail Goods"
        }
    ],
    "sg:phone":"+1 714 637 5651",
    "sg:postcode":"92808",
    "sg:province":"CA",
    "wof:name":"K & S Auto Parts",
    "wof:placetype":"venue"
},
  "geometry": {"coordinates":[-117.735709,33.8642],"type":"Point"}
}