{
  "type": "Feature",
  "properties": {
    "addr:full":"124 Clement St San Francisco CA 94118",
    "addr:housenumber":"124",
    "addr:postcode":"94118",
    "addr:street":"Clement St",
    "iso:country":"US",
    "sg:address":"124 Clement St",
    "sg:city":"San Francisco",
    "sg:classifiers":[
        {
            "category":"Shopping",
            "subcategory":"Clothing, Apparel, & Fashions",
            "type":"Retail Goods"
        }
    ],
    "sg:phone":"+1 415 876 4924",
    "sg:postcode":"94118",
    "sg:province":"CA",
    "wof:name":"Go Figure",
    "wof:placetype":"venue"
},
  "geometry": {"coordinates":[-122.461004,37.783173],"type":"Point"}
}