{
  "type": "Feature",
  "properties": {
    "iso:country":"US",
    "sg:address":"1900 N Grand Avenue #B",
    "sg:city":"Santa Ana",
    "sg:classifiers":[
        {
            "category":"Shopping",
            "type":"Retail Goods"
        }
    ],
    "sg:phone":"+1 714 543 1693",
    "sg:postcode":"92705",
    "sg:province":"CA",
    "sg:website":"www.dollartree.com",
    "wof:name":"Dollar Tree Stores, Inc.",
    "wof:placetype":"venue"
},
  "geometry": {"coordinates":[-117.852659,33.761667],"type":"Point"}
}