{
  "type": "Feature",
  "properties": {
    "iso:country":"US",
    "sg:address":"1733 Abbot Kinney Blvd",
    "sg:city":"Venice",
    "sg:classifiers":[
        {
            "category":"Real Estate",
            "subcategory":"Architect",
            "type":"Services"
        }
    ],
    "sg:phone":"+1 310 305 8122",
    "sg:postcode":"90291",
    "sg:province":"CA",
    "wof:name":"James Cox Architects",
    "wof:placetype":"venue"
},
  "geometry": {"coordinates":[-118.459873,33.988027],"type":"Point"}
}