{
  "type": "Feature",
  "properties": {
    "addr:full":"1130 S Main St Los Angeles CA 90015",
    "addr:housenumber":"1130",
    "addr:postcode":"90015",
    "addr:street":"S Main St",
    "iso:country":"US",
    "sg:address":"1130 S Main St",
    "sg:city":"Los Angeles",
    "sg:classifiers":[
        {
            "category":"Wholesale",
            "subcategory":"Jewelry",
            "type":"Manufacturing & Wholesale Goods"
        }
    ],
    "sg:phone":"+1 213 748 5439",
    "sg:postcode":"90015",
    "sg:province":"CA",
    "sg:tags":[
        "stone"
    ],
    "wof:name":"Main Trading Inc",
    "wof:placetype":"venue"
},
  "geometry": {"coordinates":[-118.25897999999999,34.038006],"type":"Point"}
}