{
  "type": "Feature",
  "properties": {
    "iso:country":"US",
    "sg:address":"35488 Panorama Dr",
    "sg:city":"Yucaipa",
    "sg:classifiers":[
        {
            "category":"Retail",
            "subcategory":"Auto Repair",
            "type":"Services"
        }
    ],
    "sg:phone":"+1 909 633 6857",
    "sg:postcode":"92399",
    "sg:province":"CA",
    "sg:tags":[
        "glass",
        "windshield",
        "installation",
        "automobile"
    ],
    "wof:name":"Dgs Mobile Windshield Repair",
    "wof:placetype":"venue"
},
  "geometry": {"coordinates":[-117.030619,34.042946],"type":"Point"}
}