{
  "type": "Feature",
  "properties": {
    "addr:full":"1215 Gingerwood Dr Milpitas CA 95035",
    "addr:housenumber":"1215",
    "addr:postcode":"95035",
    "addr:street":"Gingerwood Dr",
    "iso:country":"US",
    "sg:address":"1215 Gingerwood Dr",
    "sg:city":"Milpitas",
    "sg:classifiers":[
        {
            "category":"Professional",
            "type":"Services"
        }
    ],
    "sg:phone":"+1 408 262 1812",
    "sg:postcode":"95035",
    "sg:province":"CA",
    "wof:name":"Tuan Tran",
    "wof:placetype":"venue"
},
  "geometry": {"coordinates":[-121.915024,37.448992],"type":"Point"}
}