{
  "type": "Feature",
  "properties": {
    "iso:country":"US",
    "sg:address":"5061 Cadiz Cir",
    "sg:city":"La Palma",
    "sg:classifiers":[
        {
            "category":"Wholesale",
            "subcategory":"Durable Goods & Equipment",
            "type":"Manufacturing & Wholesale Goods"
        }
    ],
    "sg:phone":"+1 714 761 0547",
    "sg:postcode":"90623",
    "sg:province":"CA",
    "sg:tags":[
        "exporter"
    ],
    "wof:name":"Mc Namee Intl Svc",
    "wof:placetype":"venue"
},
  "geometry": {"coordinates":[-118.044464,33.839519],"type":"Point"}
}