{
  "type": "Feature",
  "properties": {
    "addr:full":"5371 Wilshire Blvd Los Angeles CA 90036",
    "addr:housenumber":"5371",
    "addr:postcode":"90036",
    "addr:street":"Wilshire Blvd",
    "iso:country":"US",
    "sg:address":"5371 Wilshire Blvd",
    "sg:city":"Los Angeles",
    "sg:classifiers":[
        {
            "category":"Government",
            "subcategory":"Office",
            "type":"Public Place"
        }
    ],
    "sg:phone":"+1 323 634 0479",
    "sg:postcode":"90036",
    "sg:province":"CA",
    "sg:tags":[
        "international",
        "affairs"
    ],
    "wof:name":"SRI Lanka Consulate General",
    "wof:placetype":"venue"
},
  "geometry": {"coordinates":[-118.345817,34.06228],"type":"Point"}
}