{
  "type": "Feature",
  "properties": {
    "iso:country":"US",
    "sg:address":"1305 Franklin St",
    "sg:city":"Oakland",
    "sg:classifiers":[
        {
            "category":"Professional",
            "subcategory":"Lawyer & Legal Services",
            "type":"Services"
        }
    ],
    "sg:phone":"+1 510 351 3400",
    "sg:postcode":"94612",
    "sg:province":"CA",
    "sg:tags":[
        "attorney"
    ],
    "wof:name":"Abel & Abel",
    "wof:placetype":"venue"
},
  "geometry": {"coordinates":[-122.270086,37.803817],"type":"Point"}
}