{
  "type": "Feature",
  "properties": {
    "iso:country":"US",
    "sg:address":"4090 el Cajon Blvd",
    "sg:city":"San Diego",
    "sg:classifiers":[
        {
            "category":"Banks & Credit Unions",
            "subcategory":"Bank",
            "type":"Services"
        }
    ],
    "sg:phone":"+1 619 563 6543",
    "sg:postcode":"92105",
    "sg:province":"CA",
    "sg:tags":[
        "cashing",
        "check"
    ],
    "wof:name":"Payless Loans",
    "wof:placetype":"venue"
},
  "geometry": {"coordinates":[-117.107507,32.755237],"type":"Point"}
}