{
  "type": "Feature",
  "properties": {
    "iso:country":"US",
    "sg:address":"1031 W Manchester Blvd",
    "sg:city":"Inglewood",
    "sg:classifiers":[
        {
            "category":"Freight",
            "type":"Transportation"
        }
    ],
    "sg:phone":"+1 310 568 0052",
    "sg:postcode":"90301",
    "sg:province":"CA",
    "sg:tags":[
        "broker",
        "customs"
    ],
    "wof:name":"Elizabeth S Lee Customs Broker",
    "wof:placetype":"venue"
},
  "geometry": {"coordinates":[-118.374848,33.959977],"type":"Point"}
}