{
  "type": "Feature",
  "properties": {
    "addr:full":"81 N 1st St San Jose CA 95113",
    "addr:housenumber":"81",
    "addr:postcode":"95113",
    "addr:street":"N 1St St",
    "iso:country":"US",
    "sg:address":"81 N 1st St",
    "sg:city":"San Jose",
    "sg:classifiers":[
        {
            "category":"Organizations",
            "subcategory":"Religious Organization",
            "type":"Services"
        }
    ],
    "sg:phone":"+1 408 370 4908",
    "sg:postcode":"95113",
    "sg:province":"CA",
    "sg:tags":[
        "church"
    ],
    "wof:name":"LA Iglesia De Cristo",
    "wof:placetype":"venue"
},
  "geometry": {"coordinates":[-121.890838,37.336403],"type":"Point"}
}