{
  "type": "Feature",
  "properties": {
    "iso:country":"US",
    "sg:address":"7335 Orchard Dr",
    "sg:city":"Gilroy",
    "sg:classifiers":[
        {
            "category":"Wholesale",
            "subcategory":"Hardware",
            "type":"Manufacturing & Wholesale Goods"
        }
    ],
    "sg:phone":"+1 408 848 3765",
    "sg:postcode":"95020",
    "sg:province":"CA",
    "sg:tags":[
        "used",
        "boiler"
    ],
    "wof:name":"South County Boilers Heating",
    "wof:placetype":"venue"
},
  "geometry": {"coordinates":[-121.579055,37.0015],"type":"Point"}
}