{
  "type": "Feature",
  "properties": {
    "iso:country":"US",
    "sg:address":"1477 E Shaw Ave",
    "sg:city":"Fresno",
    "sg:classifiers":[
        {
            "category":"Building & Trades",
            "subcategory":"Electrical",
            "type":"Services"
        }
    ],
    "sg:phone":"+1 559 221 5003",
    "sg:postcode":"93710",
    "sg:province":"CA",
    "sg:tags":[
        "telecommunication",
        "contractor"
    ],
    "wof:name":"TBS Productions",
    "wof:placetype":"venue"
},
  "geometry": {"coordinates":[-119.761196,36.808515],"type":"Point"}
}