{
  "type": "Feature",
  "properties": {
    "addr:full":"2021 W Compton Blvd Compton CA 90220",
    "addr:housenumber":"2021",
    "addr:postcode":"90220",
    "addr:street":"W Compton Blvd",
    "iso:country":"US",
    "sg:address":"2021 W Compton Blvd",
    "sg:city":"Compton",
    "sg:classifiers":[
        {
            "category":"Professional",
            "type":"Services"
        }
    ],
    "sg:phone":"+1 310 884 6802",
    "sg:postcode":"90220",
    "sg:province":"CA",
    "wof:name":"Just Like Home",
    "wof:placetype":"venue"
},
  "geometry": {"coordinates":[-118.25223099999999,33.895894],"type":"Point"}
}