{
  "type": "Feature",
  "properties": {
    "iso:country":"US",
    "sg:address":"3000 Gibbons Dr",
    "sg:city":"Alameda",
    "sg:classifiers":[
        {
            "category":"Food & Beverages",
            "subcategory":"Groceries & Convenience Stores",
            "type":"Retail Goods"
        }
    ],
    "sg:phone":"+1 510 865 6136",
    "sg:postcode":"94501",
    "sg:province":"CA",
    "wof:name":"Market To Market",
    "wof:placetype":"venue"
},
  "geometry": {"coordinates":[-122.230003,37.76358],"type":"Point"}
}