{
  "type": "Feature",
  "properties": {
    "addr:full":"247 W Glenwood Ave Fullerton CA 92832",
    "addr:housenumber":"247",
    "addr:postcode":"92832",
    "addr:street":"W Glenwood Ave",
    "iso:country":"US",
    "sg:address":"247 W Glenwood Ave",
    "sg:city":"Fullerton",
    "sg:classifiers":[
        {
            "category":"Wholesale",
            "subcategory":"Sporting Goods",
            "type":"Manufacturing & Wholesale Goods"
        }
    ],
    "sg:phone":"+1 714 609 1177",
    "sg:postcode":"92832",
    "sg:province":"CA",
    "wof:name":"Gothem Board Company",
    "wof:placetype":"venue"
},
  "geometry": {"coordinates":[-117.92794600000001,33.879496],"type":"Point"}
}