{
  "type": "Feature",
  "properties": {
    "iso:country":"US",
    "sg:address":"611 W Route 66",
    "sg:city":"Glendora",
    "sg:classifiers":[
        {
            "category":"Fast Food",
            "type":"Food & Drink"
        },
        {
            "category":"Deli",
            "type":"Food & Drink"
        },
        {
            "category":"Restaurant",
            "type":"Food & Drink"
        }
    ],
    "sg:phone":"+1 626 857 0017",
    "sg:postcode":"91740",
    "sg:province":"CA",
    "sg:tags":[
        "hamburger",
        "delicatessen",
        "dog",
        "hot",
        "lunch",
        "american",
        "brunch",
        "breakfast"
    ],
    "sg:website":"http://www.thehat.com",
    "wof:name":"Hat",
    "wof:placetype":"venue"
},
  "geometry": {"coordinates":[-117.873368,34.128817],"type":"Point"}
}