{
  "type": "Feature",
  "properties": {
    "addr:full":"6699 Campus Dr Placerville CA 95667",
    "addr:housenumber":"6699",
    "addr:postcode":"95667",
    "addr:street":"Campus Dr",
    "iso:country":"US",
    "sg:address":"6699 Campus Dr",
    "sg:city":"Placerville",
    "sg:classifiers":[
        {
            "category":"Education",
            "subcategory":"College",
            "type":"Public Place"
        }
    ],
    "sg:phone":"+1 530 642 5644",
    "sg:postcode":"95667",
    "sg:province":"CA",
    "sg:tags":[
        "academic",
        "school"
    ],
    "sg:website":"www.flc.losrios.edu",
    "wof:name":"El Dorado Ctr-Cosumnes River",
    "wof:placetype":"venue"
},
  "geometry": {"coordinates":[-120.86913300000001,38.720297],"type":"Point"}
}