{
  "type": "Feature",
  "properties": {
    "addr:full":"740 Front St Santa Cruz CA 95060",
    "addr:housenumber":"740",
    "addr:postcode":"95060",
    "addr:street":"Front St",
    "iso:country":"US",
    "sg:address":"740 Front St",
    "sg:city":"Santa Cruz",
    "sg:classifiers":[
        {
            "category":"Arts & Performance",
            "subcategory":"Theater",
            "type":"Entertainment"
        }
    ],
    "sg:phone":"+1 831 429 1325",
    "sg:postcode":"95060",
    "sg:province":"CA",
    "sg:tags":[
        "bureau"
    ],
    "wof:name":"Sure Thing Productions",
    "wof:placetype":"venue"
},
  "geometry": {"coordinates":[-122.02541100000001,36.975272],"type":"Point"}
}