{
  "type": "Feature",
  "properties": {
    "addr:full":"1799 El Camino Real San Bruno CA 94066",
    "addr:housenumber":"1799",
    "addr:postcode":"94066",
    "addr:street":"El Camino Real",
    "iso:country":"US",
    "sg:address":"1799 El Camino Real",
    "sg:city":"San Bruno",
    "sg:classifiers":[
        {
            "category":"Food & Beverages",
            "subcategory":"Groceries & Convenience Stores",
            "type":"Retail Goods"
        }
    ],
    "sg:phone":"+1 650 583 5050",
    "sg:postcode":"94066",
    "sg:province":"CA",
    "wof:name":"St Gas",
    "wof:placetype":"venue"
},
  "geometry": {"coordinates":[-122.406583,37.615228],"type":"Point"}
}