{
  "type": "Feature",
  "properties": {
    "addr:full":"5928 Pacific Ave Stockton CA 95207",
    "addr:housenumber":"5928",
    "addr:postcode":"95207",
    "addr:street":"Pacific Ave",
    "iso:country":"US",
    "sg:address":"5928 Pacific Ave",
    "sg:city":"Stockton",
    "sg:classifiers":[
        {
            "category":"Shopping",
            "type":"Retail Goods"
        }
    ],
    "sg:phone":"+1 209 478 0641",
    "sg:postcode":"95207",
    "sg:province":"CA",
    "sg:tags":[
        "telephone",
        "cellular"
    ],
    "wof:name":"Radio Shack",
    "wof:placetype":"venue"
},
  "geometry": {"coordinates":[-121.31782,38.004306],"type":"Point"}
}