{
  "type": "Feature",
  "properties": {
    "addr:full":"605 S Newhope St Santa Ana CA 92704",
    "addr:housenumber":"605",
    "addr:postcode":"92704",
    "addr:street":"S Newhope St",
    "iso:country":"US",
    "sg:address":"605 S Newhope St",
    "sg:city":"Santa Ana",
    "sg:classifiers":[
        {
            "category":"Building & Trades",
            "subcategory":"Landscaping Services",
            "type":"Services"
        }
    ],
    "sg:phone":"+1 714 457 4648",
    "sg:postcode":"92704",
    "sg:province":"CA",
    "wof:name":"Zenteno Eugino",
    "wof:placetype":"venue"
},
  "geometry": {"coordinates":[-117.928635,33.739064],"type":"Point"}
}