{
  "type": "Feature",
  "properties": {
    "addr:full":"350 Oakmead Pkwy Sunnyvale CA 94085",
    "addr:housenumber":"350",
    "addr:postcode":"94085",
    "addr:street":"Oakmead Pkwy",
    "iso:country":"US",
    "sg:address":"350 Oakmead Pkwy",
    "sg:city":"Sunnyvale",
    "sg:classifiers":[
        {
            "category":"Professional",
            "subcategory":"Lawyer & Legal Services",
            "type":"Services"
        }
    ],
    "sg:phone":"+1 408 874 0200",
    "sg:postcode":"94085",
    "sg:province":"CA",
    "sg:tags":[
        "patent",
        "attorney",
        "law",
        "trademark",
        "copyright"
    ],
    "sg:website":"http://www.reinfolink.com",
    "wof:name":"Mlslistings",
    "wof:placetype":"venue"
},
  "geometry": {"coordinates":[-121.98788500000001,37.379157],"type":"Point"}
}