{
  "type": "Feature",
  "properties": {
    "addr:full":"277 S Brookhurst St Anaheim CA 92804",
    "addr:housenumber":"277",
    "addr:postcode":"92804",
    "addr:street":"S Brookhurst St",
    "iso:country":"US",
    "sg:address":"277 S Brookhurst St",
    "sg:city":"Anaheim",
    "sg:classifiers":[
        {
            "category":"Wholesale",
            "subcategory":"Durable Goods & Equipment",
            "type":"Manufacturing & Wholesale Goods"
        }
    ],
    "sg:phone":"+1 714 687 9838",
    "sg:postcode":"92804",
    "sg:province":"CA",
    "wof:name":"Young Kim & Assoc",
    "wof:placetype":"venue"
},
  "geometry": {"coordinates":[-117.958997,33.829215],"type":"Point"}
}