{
  "type": "Feature",
  "properties": {
    "addr:full":"2921 S Main St Ste E Santa Ana CA 92707",
    "addr:housenumber":"2921",
    "addr:postcode":"92707",
    "addr:street":"S Main St Ste E",
    "iso:country":"US",
    "sg:address":"2921 S Main St Ste E",
    "sg:city":"Santa Ana",
    "sg:classifiers":[
        {
            "category":"Retail",
            "subcategory":"Portrait Studio",
            "type":"Services"
        }
    ],
    "sg:phone":"+1 714 549 3520",
    "sg:postcode":"92707",
    "sg:province":"CA",
    "sg:tags":[
        "photography",
        "store"
    ],
    "wof:name":"Display Solutions",
    "wof:placetype":"venue"
},
  "geometry": {"coordinates":[-117.86799600000001,33.7075],"type":"Point"}
}