{
  "type": "Feature",
  "properties": {
    "iso:country":"US",
    "sg:address":"35212 Rd 206",
    "sg:city":"Woodlake",
    "sg:classifiers":[
        {
            "category":"Farming",
            "subcategory":"Orchard",
            "type":"Manufacturing & Wholesale Goods"
        }
    ],
    "sg:phone":"+1 559 564 3197",
    "sg:postcode":"93286",
    "sg:province":"CA",
    "sg:tags":[
        "citrus",
        "grove",
        "fruit"
    ],
    "wof:name":"Ken Vellema",
    "wof:placetype":"venue"
},
  "geometry": {"coordinates":[-119.112206,36.431603],"type":"Point"}
}