{
  "type": "Feature",
  "properties": {
    "iso:country":"US",
    "sg:address":"240 S Market Street",
    "sg:city":"Inglewood",
    "sg:classifiers":[
        {
            "category":"Education",
            "subcategory":"Vocational School",
            "type":"Public Place"
        }
    ],
    "sg:phone":"+1 310 674 8100",
    "sg:postcode":"90301",
    "sg:province":"CA",
    "sg:tags":[
        "cosmetology"
    ],
    "wof:name":"Marinello School of Beauty",
    "wof:placetype":"venue"
},
  "geometry": {"coordinates":[-118.352035,33.960919],"type":"Point"}
}