{
  "type": "Feature",
  "properties": {
    "iso:country":"US",
    "sg:address":"530 Grey Ghost Ct",
    "sg:city":"Morgan Hill",
    "sg:classifiers":[
        {
            "category":"Personal",
            "type":"Services"
        }
    ],
    "sg:phone":"+1 408 778 9222",
    "sg:postcode":"95037",
    "sg:province":"CA",
    "sg:tags":[
        "electrologist"
    ],
    "wof:name":"Debra Chrisman",
    "wof:placetype":"venue"
},
  "geometry": {"coordinates":[-121.630665,37.094879],"type":"Point"}
}