{
  "type": "Feature",
  "properties": {
    "addr:full":"36751 Hafner St Newark CA 94560",
    "addr:postcode":"36751;94560",
    "addr:street":"Hafner St",
    "iso:country":"US",
    "sg:address":"36751 Hafner St",
    "sg:city":"Newark",
    "sg:classifiers":[
        {
            "category":"Farming",
            "subcategory":"Livestock Farm",
            "type":"Manufacturing & Wholesale Goods"
        }
    ],
    "sg:phone":"+1 510 713 1919",
    "sg:postcode":"94560",
    "sg:province":"CA",
    "sg:tags":[
        "specialty",
        "animal"
    ],
    "wof:name":"Homen Apiaries",
    "wof:placetype":"venue"
},
  "geometry": {"coordinates":[-122.032884,37.540349],"type":"Point"}
}