{
  "type": "Feature",
  "properties": {
    "addr:full":"845 Embarcadero Morro Bay CA 93442",
    "addr:housenumber":"845",
    "addr:postcode":"93442",
    "addr:street":"Embarcadero",
    "iso:country":"US",
    "sg:address":"845 Embarcadero",
    "sg:city":"Morro Bay",
    "sg:classifiers":[
        {
            "category":"Food & Beverages",
            "subcategory":"Candy",
            "type":"Retail Goods"
        }
    ],
    "sg:phone":"+1 805 772 1022",
    "sg:postcode":"93442",
    "sg:province":"CA",
    "sg:tags":[
        "confectionery"
    ],
    "wof:name":"Candy Bouquet",
    "wof:placetype":"venue"
},
  "geometry": {"coordinates":[-120.854015,35.367495],"type":"Point"}
}