{
  "type": "Feature",
  "properties": {
    "iso:country":"US",
    "sg:address":"5577 Carli Ct",
    "sg:city":"Paradise",
    "sg:classifiers":[
        {
            "category":"Health Services",
            "subcategory":"Hospital",
            "type":"Services"
        }
    ],
    "sg:phone":"+1 530 872 2296",
    "sg:postcode":"95969",
    "sg:province":"CA",
    "sg:tags":[
        "mental"
    ],
    "wof:name":"Alpine Home III",
    "wof:placetype":"venue"
},
  "geometry": {"coordinates":[-121.620575,39.749342],"type":"Point"}
}