{
  "type": "Feature",
  "properties": {
    "iso:country":"US",
    "sg:address":"2015 Central Ave",
    "sg:city":"Mckinleyville",
    "sg:classifiers":[
        {
            "category":"Restaurant",
            "type":"Food & Drink"
        }
    ],
    "sg:menulink":"http://www.allmenus.com/ca/north-coastal/77853-papa-murphys/menu/",
    "sg:phone":"+1 707 839 8763",
    "sg:postcode":"95519",
    "sg:province":"CA",
    "sg:tags":[
        "american",
        "pizza"
    ],
    "wof:name":"Papa Murphy's",
    "wof:placetype":"venue"
},
  "geometry": {"coordinates":[-124.100943,40.942291],"type":"Point"}
}