{
  "type": "Feature",
  "properties": {
    "addr:full":"5754 Willowcrest Ave North Hollywood CA 91601",
    "addr:housenumber":"5754",
    "addr:postcode":"91601",
    "addr:street":"Willowcrest Ave",
    "iso:country":"US",
    "sg:address":"5754 Willowcrest Ave",
    "sg:city":"North Hollywood",
    "sg:classifiers":[
        {
            "category":"Professional",
            "subcategory":"Printing & Photocopies",
            "type":"Services"
        },
        {
            "category":"Arena",
            "subcategory":"Sports Club",
            "type":"Entertainment"
        }
    ],
    "sg:phone":"+1 818 769 3250",
    "sg:postcode":"91601",
    "sg:province":"CA",
    "sg:tags":[
        "martial art"
    ],
    "sg:website":"www.arcservicesco.com",
    "wof:name":"A R C Services Co",
    "wof:placetype":"venue"
},
  "geometry": {"coordinates":[-118.362999,34.1754],"type":"Point"}
}