{
  "type": "Feature",
  "properties": {
    "addr:full":"625 de Las Flores St Calexico CA 92231",
    "addr:housenumber":"625",
    "addr:postcode":"92231",
    "addr:street":"De Las Flores St",
    "iso:country":"US",
    "sg:address":"625 de Las Flores St",
    "sg:city":"Calexico",
    "sg:classifiers":[
        {
            "category":"Manufacturing",
            "subcategory":"Tools & Machinery",
            "type":"Manufacturing & Wholesale Goods"
        }
    ],
    "sg:phone":"+1 760 357 4759",
    "sg:postcode":"92231",
    "sg:province":"CA",
    "sg:tags":[
        "surgical",
        "mfg"
    ],
    "wof:name":"Hearing Aids",
    "wof:placetype":"venue"
},
  "geometry": {"coordinates":[-115.51078699999999,32.680956],"type":"Point"}
}