{
  "type": "Feature",
  "properties": {
    "iso:country":"US",
    "sg:address":"2255 W Lincoln Ave",
    "sg:city":"Anaheim",
    "sg:classifiers":[
        {
            "category":"Travel",
            "subcategory":"Hotels & Motels",
            "type":"Entertainment"
        }
    ],
    "sg:phone":"+1 714 774 7774",
    "sg:postcode":"92801",
    "sg:province":"CA",
    "wof:name":"Eagle Inn & Suites",
    "wof:placetype":"venue"
},
  "geometry": {"coordinates":[-117.960999,33.832401],"type":"Point"}
}