{
  "type": "Feature",
  "properties": {
    "addr:full":"7857 Sepulveda Blvd Van Nuys CA 91405",
    "addr:housenumber":"7857",
    "addr:postcode":"91405",
    "addr:street":"Sepulveda Blvd",
    "iso:country":"US",
    "sg:address":"7857 Sepulveda Blvd",
    "sg:city":"Van Nuys",
    "sg:classifiers":[
        {
            "category":"Retail",
            "subcategory":"Auto Repair",
            "type":"Services"
        }
    ],
    "sg:phone":"+1 818 988 7200",
    "sg:postcode":"91405",
    "sg:province":"CA",
    "sg:tags":[
        "body",
        "automobile",
        "painting"
    ],
    "sg:website":"www.fordautobody.com",
    "wof:name":"Ford Auto Body Inc",
    "wof:placetype":"venue"
},
  "geometry": {"coordinates":[-118.466278,34.212115],"type":"Point"}
}