{
  "type": "Feature",
  "properties": {
    "addr:full":"15951 Los Gatos Blvd Los Gatos CA 95032",
    "addr:housenumber":"15951",
    "addr:postcode":"95032",
    "addr:street":"Los Gatos Blvd",
    "iso:country":"US",
    "sg:address":"15951 Los Gatos Blvd",
    "sg:city":"Los Gatos",
    "sg:classifiers":[
        {
            "category":"Professional",
            "subcategory":"Employment Agencies",
            "type":"Services"
        }
    ],
    "sg:phone":"+1 408 354 3664",
    "sg:postcode":"95032",
    "sg:province":"CA",
    "sg:tags":[
        "consultant",
        "search",
        "executive"
    ],
    "sg:website":"www.exec-search.com",
    "wof:name":"Splaine & Assoc Inc",
    "wof:placetype":"venue"
},
  "geometry": {"coordinates":[-121.96231,37.23738],"type":"Point"}
}