{
  "type": "Feature",
  "properties": {
    "iso:country":"US",
    "sg:address":"7050 La Presa",
    "sg:city":"Los Angeles",
    "sg:classifiers":[
        {
            "category":"Restaurant",
            "type":"Food & Drink"
        },
        {
            "category":"Food & Beverages",
            "subcategory":"Ethnic Foods",
            "type":"Retail Goods"
        }
    ],
    "sg:phone":"+1 877 206 1550",
    "sg:postcode":"90068",
    "sg:province":"CA",
    "sg:tags":[
        "vegetarian",
        "soul"
    ],
    "sg:website":"soulvegetarian.com",
    "wof:name":"Soul Vegetarian",
    "wof:placetype":"venue"
},
  "geometry": {"coordinates":[-118.342417,34.108849],"type":"Point"}
}