{
  "type": "Feature",
  "properties": {
    "addr:full":"9018 Vernal Ln Descanso CA 91916",
    "addr:housenumber":"9018",
    "addr:postcode":"91916",
    "addr:street":"Vernal Ln",
    "iso:country":"US",
    "sg:address":"9018 Vernal Ln",
    "sg:city":"Descanso",
    "sg:classifiers":[
        {
            "category":"Recreation",
            "type":"Entertainment"
        }
    ],
    "sg:phone":"+1 619 445 1137",
    "sg:postcode":"91916",
    "sg:province":"CA",
    "sg:tags":[
        "stable"
    ],
    "wof:name":"Fracchiolla Ranch",
    "wof:placetype":"venue"
},
  "geometry": {"coordinates":[-116.617307,32.850921],"type":"Point"}
}