{
  "type": "Feature",
  "properties": {
    "iso:country":"US",
    "sg:address":"21155 Uvas Rd",
    "sg:city":"Morgan Hill",
    "sg:classifiers":[
        {
            "category":"Shopping",
            "subcategory":"Bicycles & Sporting Goods",
            "type":"Retail Goods"
        }
    ],
    "sg:phone":"+1 408 268 9619",
    "sg:postcode":"95037",
    "sg:province":"CA",
    "sg:tags":[
        "saddlery",
        "harness"
    ],
    "wof:name":"Tumbleweed Saddlery",
    "wof:placetype":"venue"
},
  "geometry": {"coordinates":[-121.74627099999999,37.150464],"type":"Point"}
}