{
  "type": "Feature",
  "properties": {
    "addr:full":"4222 Lankershim Blvd North Hollywood CA 91602",
    "addr:postcode":"4222;91602",
    "addr:street":"Lankershim Blvd",
    "iso:country":"US",
    "sg:address":"4222 Lankershim Blvd",
    "sg:city":"North Hollywood",
    "sg:classifiers":[
        {
            "category":"Personal",
            "subcategory":"Beauty Salon",
            "type":"Services"
        }
    ],
    "sg:phone":"+1 818 980 3452",
    "sg:postcode":"91602",
    "sg:province":"CA",
    "sg:tags":[
        "hair"
    ],
    "wof:name":"Robert Bachelor Salon",
    "wof:placetype":"venue"
},
  "geometry": {"coordinates":[-118.36343599999999,34.146432],"type":"Point"}
}