{
  "type": "Feature",
  "properties": {
    "addr:full":"909 E Green St Pasadena CA 91106",
    "addr:housenumber":"909",
    "addr:postcode":"91106",
    "addr:street":"E Green St",
    "iso:country":"US",
    "sg:address":"909 E Green St",
    "sg:city":"Pasadena",
    "sg:classifiers":[
        {
            "category":"Professional",
            "subcategory":"Lawyer & Legal Services",
            "type":"Services"
        },
        {
            "category":"Bars & Pubs",
            "subcategory":"Nightclub",
            "type":"Food & Drink"
        }
    ],
    "sg:phone":"+1 626 796 4382",
    "sg:postcode":"91106",
    "sg:province":"CA",
    "sg:tags":[
        "nightlife"
    ],
    "wof:name":"Triange Civil Lawyers",
    "wof:placetype":"venue"
},
  "geometry": {"coordinates":[-118.132003,34.144673],"type":"Point"}
}