{
  "type": "Feature",
  "properties": {
    "iso:country":"US",
    "sg:address":"3661 Walnut Ave",
    "sg:city":"Chino",
    "sg:classifiers":[
        {
            "category":"Professional",
            "type":"Services"
        }
    ],
    "sg:phone":"+1 909 591 8358",
    "sg:postcode":"91710",
    "sg:province":"CA",
    "sg:tags":[
        "establishment"
    ],
    "wof:name":"Instek America Corp",
    "wof:placetype":"venue"
},
  "geometry": {"coordinates":[-117.72583899999999,34.024772],"type":"Point"}
}