{
  "type": "Feature",
  "properties": {
    "addr:full":"3311 E Slauson Ave Vernon CA 90058",
    "addr:housenumber":"3311",
    "addr:postcode":"90058",
    "addr:street":"E Slauson Ave",
    "iso:country":"US",
    "sg:address":"3311 E Slauson Ave",
    "sg:city":"Vernon",
    "sg:classifiers":[
        {
            "category":"Wholesale",
            "subcategory":"Apparel",
            "type":"Manufacturing & Wholesale Goods"
        }
    ],
    "sg:phone":"+1 323 588 2226",
    "sg:postcode":"90058",
    "sg:province":"CA",
    "sg:website":"www.jamesperse.com",
    "wof:name":"James Perse Enterprise Inc",
    "wof:placetype":"venue"
},
  "geometry": {"coordinates":[-118.20840200000001,33.989186],"type":"Point"}
}