{
  "type": "Feature",
  "properties": {
    "addr:full":"15916 State Rte 59 Snelling CA 95369",
    "addr:housenumber":"15916",
    "addr:postcode":"95369",
    "addr:street":"State Rte 59",
    "iso:country":"US",
    "sg:address":"15916 State Rte 59",
    "sg:city":"Snelling",
    "sg:classifiers":[
        {
            "category":"Education",
            "subcategory":"Library",
            "type":"Public Place"
        }
    ],
    "sg:phone":"+1 209 563 6616",
    "sg:postcode":"95369",
    "sg:province":"CA",
    "wof:name":"Snelling Library",
    "wof:placetype":"venue"
},
  "geometry": {"coordinates":[-120.43868399999999,37.51905],"type":"Point"}
}