{
  "type": "Feature",
  "properties": {
    "iso:country":"US",
    "sg:address":"1050 Holly Rd",
    "sg:city":"Tahoe City",
    "sg:classifiers":[
        {
            "category":"Shopping",
            "subcategory":"Clothing, Apparel, & Fashions",
            "type":"Retail Goods"
        }
    ],
    "sg:phone":"+1 530 583 4028",
    "sg:postcode":"96145",
    "sg:province":"CA",
    "sg:tags":[
        "alteration"
    ],
    "wof:name":"Jo L Mc Dougal Seamstress",
    "wof:placetype":"venue"
},
  "geometry": {"coordinates":[-120.14864799999999,39.150808],"type":"Point"}
}