{
  "type": "Feature",
  "properties": {
    "iso:country":"US",
    "sg:address":"68727 State Hwy 111",
    "sg:city":"Cathedral City",
    "sg:classifiers":[
        {
            "category":"Social Services",
            "type":"Services"
        }
    ],
    "sg:phone":"+1 760 324 2477",
    "sg:postcode":"92234",
    "sg:province":"CA",
    "wof:name":"Community Health Agency",
    "wof:placetype":"venue"
},
  "geometry": {"coordinates":[-116.46251700000001,33.779244],"type":"Point"}
}