{
  "type": "Feature",
  "properties": {
    "addr:full":"126 W Fir St San Diego CA 92101",
    "addr:housenumber":"126",
    "addr:postcode":"92101",
    "addr:street":"W Fir St",
    "iso:country":"US",
    "sg:address":"126 W Fir St",
    "sg:city":"San Diego",
    "sg:classifiers":[
        {
            "category":"Retail",
            "subcategory":"Portrait Studio",
            "type":"Services"
        }
    ],
    "sg:phone":"+1 619 237 6178",
    "sg:postcode":"92101",
    "sg:province":"CA",
    "sg:tags":[
        "photographer"
    ],
    "wof:name":"Brooke Durham Photography",
    "wof:placetype":"venue"
},
  "geometry": {"coordinates":[-117.16456100000001,32.725171],"type":"Point"}
}