{
  "type": "Feature",
  "properties": {
    "addr:full":"4201 Stagecoach Rd Willits CA 95490",
    "addr:housenumber":"4201",
    "addr:postcode":"95490",
    "addr:street":"Stagecoach Rd",
    "iso:country":"US",
    "sg:address":"4201 Stagecoach Rd",
    "sg:city":"Willits",
    "sg:classifiers":[
        {
            "category":"Home & Garden",
            "subcategory":"Garden Supply",
            "type":"Retail Goods"
        }
    ],
    "sg:phone":"+1 707 984 8639",
    "sg:postcode":"95490",
    "sg:province":"CA",
    "wof:name":"Strong Supplies",
    "wof:placetype":"venue"
},
  "geometry": {"coordinates":[-123.507717,39.557445],"type":"Point"}
}