{
  "type": "Feature",
  "properties": {
    "iso:country":"US",
    "sg:address":"236 el Medio St",
    "sg:city":"Ventura",
    "sg:classifiers":[
        {
            "category":"Professional",
            "type":"Services"
        }
    ],
    "sg:phone":"+1 805 643 3471",
    "sg:postcode":"93001",
    "sg:province":"CA",
    "wof:name":"Westside Cultural Center",
    "wof:placetype":"venue"
},
  "geometry": {"coordinates":[-119.29295,34.292348],"type":"Point"}
}