{
  "type": "Feature",
  "properties": {
    "iso:country":"US",
    "sg:address":"4514 Franklin Ave",
    "sg:city":"Los Angeles",
    "sg:classifiers":[
        {
            "category":"Shopping",
            "subcategory":"Clothing, Apparel, & Fashions",
            "type":"Retail Goods"
        }
    ],
    "sg:phone":"+1 323 644 9707",
    "sg:postcode":"90027",
    "sg:province":"CA",
    "wof:name":"G M H Clothing",
    "wof:placetype":"venue"
},
  "geometry": {"coordinates":[-118.288518,34.105342],"type":"Point"}
}