{
  "type": "Feature",
  "properties": {
    "iso:country":"US",
    "sg:address":"24765 Fir Ave",
    "sg:city":"Moreno Valley",
    "sg:classifiers":[
        {
            "category":"Organizations",
            "subcategory":"Religious Organization",
            "type":"Services"
        }
    ],
    "sg:phone":"+1 951 242 3421",
    "sg:postcode":"92553",
    "sg:province":"CA",
    "sg:tags":[
        "church"
    ],
    "wof:name":"First Baptist Church",
    "wof:placetype":"venue"
},
  "geometry": {"coordinates":[-117.22647499999999,33.935371],"type":"Point"}
}