{
  "type": "Feature",
  "properties": {
    "iso:country":"US",
    "sg:address":"101 W Canon Perdido St",
    "sg:city":"Santa Barbara",
    "sg:classifiers":[
        {
            "category":"Freight",
            "type":"Transportation"
        }
    ],
    "sg:phone":"+1 805 883 0013",
    "sg:postcode":"93101",
    "sg:province":"CA",
    "sg:tags":[
        "mover"
    ],
    "wof:name":"A-1 Professional Moving",
    "wof:placetype":"venue"
},
  "geometry": {"coordinates":[-119.70285,34.418389],"type":"Point"}
}