{
  "type": "Feature",
  "properties": {
    "iso:country":"US",
    "sg:address":"2412 E Thousand Oaks Blvd",
    "sg:city":"Thousand Oaks",
    "sg:classifiers":[
        {
            "category":"Shopping",
            "subcategory":"Used Merchandise",
            "type":"Retail Goods"
        }
    ],
    "sg:phone":"+1 805 496 6562",
    "sg:postcode":"91362",
    "sg:province":"CA",
    "sg:tags":[
        "shop",
        "thrift"
    ],
    "wof:name":"Hope Chest II",
    "wof:placetype":"venue"
},
  "geometry": {"coordinates":[-118.842015,34.173498],"type":"Point"}
}