{
  "type": "Feature",
  "properties": {
    "addr:full":"1941 E Miraloma Ave Ste B Placentia CA 92870",
    "addr:housenumber":"1941",
    "addr:postcode":"ca 92870",
    "addr:street":"E Miraloma Ave Ste B",
    "iso:country":"US",
    "sg:address":"1941 E Miraloma Ave Ste B",
    "sg:city":"Placentia",
    "sg:classifiers":[
        {
            "category":"Wholesale",
            "subcategory":"Computers",
            "type":"Manufacturing & Wholesale Goods"
        }
    ],
    "sg:phone":"+1 714 572 9889",
    "sg:postcode":"92870",
    "sg:province":"CA",
    "wof:name":"Caldigit Inc",
    "wof:placetype":"venue"
},
  "geometry": {"coordinates":[-117.822395,33.862157],"type":"Point"}
}