{
  "type": "Feature",
  "properties": {
    "addr:full":"5962 La Place Ct Ste 145 Carlsbad CA 92008",
    "addr:housenumber":"5962",
    "addr:postcode":"92008",
    "addr:street":"La Place Ct Ste 145",
    "iso:country":"US",
    "sg:address":"5962 La Place Ct Ste 145",
    "sg:city":"Carlsbad",
    "sg:classifiers":[
        {
            "category":"Shopping",
            "subcategory":"Music",
            "type":"Retail Goods"
        }
    ],
    "sg:phone":"+1 760 607 0130",
    "sg:postcode":"92008",
    "sg:province":"CA",
    "sg:tags":[
        "dvd's"
    ],
    "sg:website":"www.rollingthundersoftware.com",
    "wof:name":"Rolling Thunder Software",
    "wof:placetype":"venue"
},
  "geometry": {"coordinates":[-117.27198199999999,33.13265],"type":"Point"}
}