{
  "type": "Feature",
  "properties": {
    "addr:full":"2315 E 7th St Long Beach CA 90804",
    "addr:housenumber":"2315",
    "addr:postcode":"90804",
    "addr:street":"E 7Th St",
    "iso:country":"US",
    "sg:address":"2315 E 7th St",
    "sg:city":"Long Beach",
    "sg:classifiers":[
        {
            "category":"Shopping",
            "subcategory":"Clothing, Apparel, & Fashions",
            "type":"Retail Goods"
        }
    ],
    "sg:phone":"+1 562 433 1910",
    "sg:postcode":"90804",
    "sg:province":"CA",
    "sg:tags":[
        "department",
        "store"
    ],
    "wof:name":"Cid Fashion & Gear",
    "wof:placetype":"venue"
},
  "geometry": {"coordinates":[-118.164001,33.775398],"type":"Point"}
}