{
  "type": "Feature",
  "properties": {
    "addr:full":"5040 Foothills Blvd Roseville CA 95747",
    "addr:housenumber":"5040",
    "addr:postcode":"95747",
    "addr:street":"Foothills Blvd",
    "iso:country":"US",
    "sg:address":"5040 Foothills Blvd",
    "sg:city":"Roseville",
    "sg:classifiers":[
        {
            "category":"Banks & Credit Unions",
            "subcategory":"Bank",
            "type":"Services"
        }
    ],
    "sg:phone":"+1 916 872 6400",
    "sg:postcode":"95747",
    "sg:province":"CA",
    "sg:website":"http://www.patelco.org",
    "wof:name":"Patelco Credit Union",
    "wof:placetype":"venue"
},
  "geometry": {"coordinates":[-121.30992000000001,38.759959],"type":"Point"}
}