{
  "type": "Feature",
  "properties": {
    "addr:full":"10838 Beverly Blvd Whittier CA 90601",
    "addr:housenumber":"10838",
    "addr:postcode":"90601",
    "addr:street":"Beverly Blvd",
    "iso:country":"US",
    "sg:address":"10838 Beverly Blvd",
    "sg:city":"Whittier",
    "sg:classifiers":[
        {
            "category":"Personal",
            "subcategory":"Beauty Salon",
            "type":"Services"
        }
    ],
    "sg:phone":"+1 562 463 6120",
    "sg:postcode":"90601",
    "sg:province":"CA",
    "wof:name":"Sonia's Nails",
    "wof:placetype":"venue"
},
  "geometry": {"coordinates":[-118.054835,33.997752],"type":"Point"}
}