{
  "type": "Feature",
  "properties": {
    "iso:country":"US",
    "sg:address":"145 Trevino Ave",
    "sg:city":"Manteca",
    "sg:classifiers":[
        {
            "category":"Insurance",
            "subcategory":"Insurance Agent",
            "type":"Services"
        }
    ],
    "sg:phone":"+1 209 239 1252",
    "sg:postcode":"95337",
    "sg:province":"CA",
    "wof:name":"California State Auto Assn",
    "wof:placetype":"venue"
},
  "geometry": {"coordinates":[-121.240527,37.79829],"type":"Point"}
}