{
  "type": "Feature",
  "properties": {
    "addr:full":"200 W Midway Dr Anaheim CA 92805",
    "addr:housenumber":"200",
    "addr:postcode":"92805",
    "addr:street":"W Midway Dr",
    "iso:country":"US",
    "sg:address":"200 W Midway Dr",
    "sg:city":"Anaheim",
    "sg:classifiers":[
        {
            "category":"Building & Trades",
            "subcategory":"Construction",
            "type":"Services"
        }
    ],
    "sg:phone":"+1 714 635 3258",
    "sg:postcode":"92805",
    "sg:province":"CA",
    "sg:tags":[
        "contractor"
    ],
    "wof:name":"Area Builders",
    "wof:placetype":"venue"
},
  "geometry": {"coordinates":[-117.91101399999999,33.812512],"type":"Point"}
}