{
  "type": "Feature",
  "properties": {
    "iso:country":"US",
    "sg:address":"72875 Highway 111",
    "sg:city":"Palm Desert",
    "sg:classifiers":[
        {
            "category":"Retail",
            "subcategory":"Portrait Studio",
            "type":"Services"
        }
    ],
    "sg:phone":"+1 760 346 2618",
    "sg:postcode":"92260",
    "sg:province":"CA",
    "sg:tags":[
        "photography",
        "store"
    ],
    "wof:name":"Rite Aid",
    "wof:placetype":"venue"
},
  "geometry": {"coordinates":[-116.396004,33.722],"type":"Point"}
}