{
  "type": "Feature",
  "properties": {
    "addr:full":"2908 Oregon Ct Torrance CA 90503",
    "addr:housenumber":"2908",
    "addr:postcode":"90503",
    "addr:street":"Oregon Ct",
    "iso:country":"US",
    "sg:address":"2908 Oregon Ct",
    "sg:city":"Torrance",
    "sg:classifiers":[
        {
            "category":"Arts & Performance",
            "subcategory":"Theater",
            "type":"Entertainment"
        }
    ],
    "sg:phone":"+1 949 362 4218",
    "sg:postcode":"90503",
    "sg:province":"CA",
    "sg:tags":[
        "bureau"
    ],
    "wof:name":"Executive Entertainment",
    "wof:placetype":"venue"
},
  "geometry": {"coordinates":[-118.338826,33.846341],"type":"Point"}
}