{
  "type": "Feature",
  "properties": {
    "addr:full":"9458 Thunderbird Pl San Ramon CA 94583",
    "addr:housenumber":"9458",
    "addr:postcode":"94583",
    "addr:street":"Thunderbird Pl",
    "iso:country":"US",
    "sg:address":"9458 Thunderbird Pl",
    "sg:city":"San Ramon",
    "sg:classifiers":[
        {
            "category":"Professional",
            "type":"Services"
        }
    ],
    "sg:phone":"+1 925 829 8118",
    "sg:postcode":"94583",
    "sg:province":"CA",
    "wof:name":"Carol Haney",
    "wof:placetype":"venue"
},
  "geometry": {"coordinates":[-121.93254,37.736331],"type":"Point"}
}