{
  "type": "Feature",
  "properties": {
    "addr:full":"23000 Crenshaw Blvd Torrance CA 90505",
    "addr:housenumber":"23000",
    "addr:postcode":"90505",
    "addr:street":"Crenshaw Blvd",
    "iso:country":"US",
    "sg:address":"23000 Crenshaw Blvd",
    "sg:city":"Torrance",
    "sg:classifiers":[
        {
            "category":"Health Services",
            "subcategory":"Doctor",
            "type":"Services"
        }
    ],
    "sg:phone":"+1 310 534 2469",
    "sg:postcode":"90505",
    "sg:province":"CA",
    "sg:tags":[
        "dentist"
    ],
    "wof:name":"Henry S Lee DDS",
    "wof:placetype":"venue"
},
  "geometry": {"coordinates":[-118.328031,33.816379],"type":"Point"}
}