{
  "type": "Feature",
  "properties": {
    "iso:country":"US",
    "sg:address":"2350 San Diego Avenue",
    "sg:city":"San Diego",
    "sg:classifiers":[
        {
            "category":"Shopping",
            "subcategory":"Jewelry",
            "type":"Retail Goods"
        }
    ],
    "sg:phone":"+1 619 296 3638",
    "sg:postcode":"92110",
    "sg:province":"CA",
    "sg:tags":[
        "watch"
    ],
    "sg:website":"www.sandiegowatchmaker.com",
    "wof:name":"A Gunalp Horologist Watch & Clock Shop",
    "wof:placetype":"venue"
},
  "geometry": {"coordinates":[-117.192712,32.750142],"type":"Point"}
}