{
  "type": "Feature",
  "properties": {
    "addr:full":"5408 Sepulveda Blvd Culver City CA 90230",
    "addr:housenumber":"5408",
    "addr:postcode":"90230",
    "addr:street":"Sepulveda Blvd",
    "iso:country":"US",
    "sg:address":"5408 Sepulveda Blvd",
    "sg:city":"Culver City",
    "sg:classifiers":[
        {
            "category":"Professional",
            "subcategory":"Lawyer & Legal Services",
            "type":"Services"
        }
    ],
    "sg:phone":"+1 310 390 1890",
    "sg:postcode":"90230",
    "sg:province":"CA",
    "sg:tags":[
        "notary"
    ],
    "wof:name":"Green Line Notary",
    "wof:placetype":"venue"
},
  "geometry": {"coordinates":[-118.394997,33.9949],"type":"Point"}
}