{
  "type": "Feature",
  "properties": {
    "addr:full":"3651 Garrison St San Diego CA 92106",
    "addr:housenumber":"3651",
    "addr:postcode":"92106",
    "addr:street":"Garrison St",
    "iso:country":"US",
    "sg:address":"3651 Garrison St",
    "sg:city":"San Diego",
    "sg:classifiers":[
        {
            "category":"Building & Trades",
            "subcategory":"Construction",
            "type":"Services"
        }
    ],
    "sg:phone":"+1 619 224 8397",
    "sg:postcode":"92106",
    "sg:province":"CA",
    "sg:tags":[
        "heavy"
    ],
    "wof:name":"Superior Irrigation & Ldscpg",
    "wof:placetype":"venue"
},
  "geometry": {"coordinates":[-117.235041,32.732182],"type":"Point"}
}