{
  "type": "Feature",
  "properties": {
    "addr:full":"633 Brazos St Ramona CA 92065",
    "addr:housenumber":"633",
    "addr:postcode":"92065",
    "addr:street":"Brazos St",
    "iso:country":"US",
    "sg:address":"633 Brazos St",
    "sg:city":"Ramona",
    "sg:classifiers":[
        {
            "category":"Manufacturing",
            "subcategory":"Buildings",
            "type":"Manufacturing & Wholesale Goods"
        },
        {
            "category":"Building & Trades",
            "subcategory":"Construction",
            "type":"Services"
        },
        {
            "category":"Building & Trades",
            "subcategory":"Electrical",
            "type":"Services"
        }
    ],
    "sg:phone":"+1 760 788 3500",
    "sg:postcode":"92065",
    "sg:province":"CA",
    "sg:tags":[
        "industrial",
        "electrician",
        "electric",
        "builder",
        "contractor",
        "contractors-commercial",
        "home"
    ],
    "sg:website":"http://www.hedgeselectric.com",
    "wof:name":"Hedges Electric & Construction Inc",
    "wof:placetype":"venue"
},
  "geometry": {"coordinates":[-116.87967399999999,33.043877],"type":"Point"}
}