{
  "type": "Feature",
  "properties": {
    "addr:full":"3301 C St Sacramento CA 95816",
    "addr:housenumber":"3301",
    "addr:postcode":"95816",
    "addr:street":"C St",
    "iso:country":"US",
    "sg:address":"3301 C St",
    "sg:city":"Sacramento",
    "sg:classifiers":[
        {
            "category":"Banks & Credit Unions",
            "subcategory":"Bank",
            "type":"Services"
        }
    ],
    "sg:phone":"+1 916 498 0418",
    "sg:postcode":"95816",
    "sg:province":"CA",
    "sg:tags":[
        "loan",
        "real estate"
    ],
    "wof:name":"Deal Pro Financial Svc",
    "wof:placetype":"venue"
},
  "geometry": {"coordinates":[-121.45723700000001,38.579195],"type":"Point"}
}