{
  "type": "Feature",
  "properties": {
    "addr:full":"517 E Gutierrez St Santa Barbara CA 93103",
    "addr:housenumber":"517",
    "addr:postcode":"93103",
    "addr:street":"E Gutierrez St",
    "iso:country":"US",
    "sg:address":"517 E Gutierrez St",
    "sg:city":"Santa Barbara",
    "sg:classifiers":[
        {
            "category":"Retail",
            "subcategory":"Auto Repair",
            "type":"Services"
        }
    ],
    "sg:phone":"+1 805 962 1540",
    "sg:postcode":"93103",
    "sg:province":"CA",
    "sg:tags":[
        "repairing",
        "automobile"
    ],
    "wof:name":"Lexus Independent Lexus",
    "wof:placetype":"venue"
},
  "geometry": {"coordinates":[-119.687634,34.42208],"type":"Point"}
}