{
  "type": "Feature",
  "properties": {
    "iso:country":"US",
    "sg:address":"881 West Baker Street",
    "sg:city":"Costa Mesa",
    "sg:classifiers":[
        {
            "category":"Travel",
            "subcategory":"Hotels & Motels",
            "type":"Entertainment"
        }
    ],
    "sg:phone":"+1 714 241 8800",
    "sg:postcode":"92626",
    "sg:province":"CA",
    "sg:website":"www.marriott.com",
    "wof:name":"Residence Inn Costa Mesa Newport Beach",
    "wof:placetype":"venue"
},
  "geometry": {"coordinates":[-117.892701,33.679067],"type":"Point"}
}