{
  "type": "Feature",
  "properties": {
    "addr:full":"2480 Oak St Napa CA 94559",
    "addr:housenumber":"2480",
    "addr:postcode":"94559",
    "addr:street":"Oak St",
    "iso:country":"US",
    "sg:address":"2480 Oak St",
    "sg:city":"Napa",
    "sg:classifiers":[
        {
            "category":"Shopping",
            "subcategory":"Hobbies, Toys, & Games",
            "type":"Retail Goods"
        }
    ],
    "sg:phone":"+1 707 251 5686",
    "sg:postcode":"94559",
    "sg:province":"CA",
    "wof:name":"W Barton Berg Hobby Shop",
    "wof:placetype":"venue"
},
  "geometry": {"coordinates":[-122.299025,38.295512],"type":"Point"}
}