{
  "type": "Feature",
  "properties": {
    "iso:country":"US",
    "sg:address":"25283 Cabot Rd",
    "sg:city":"Laguna Hills",
    "sg:classifiers":[
        {
            "category":"Banks & Credit Unions",
            "subcategory":"Bank",
            "type":"Services"
        }
    ],
    "sg:phone":"+1 949 460 7799",
    "sg:postcode":"92653",
    "sg:province":"CA",
    "sg:tags":[
        "loan",
        "real estate"
    ],
    "wof:name":"Homequest Mortgage",
    "wof:placetype":"venue"
},
  "geometry": {"coordinates":[-117.674599,33.59174],"type":"Point"}
}