{
  "type": "Feature",
  "properties": {
    "iso:country":"US",
    "sg:address":"69th & University Ave By the Joan Kroc Center",
    "sg:city":"San Diego",
    "sg:classifiers":[
        {
            "category":"Social Services",
            "subcategory":"Child Care",
            "type":"Services"
        }
    ],
    "sg:phone":"+1 619 287 2094",
    "sg:postcode":"92115",
    "sg:province":"CA",
    "sg:tags":[
        "day"
    ],
    "sg:website":"littlepeoplesworld@yahoo.com",
    "wof:name":"Little Peoples Learning Family Childcare",
    "wof:placetype":"venue"
},
  "geometry": {"coordinates":[-117.049136,32.755109],"type":"Point"}
}