{
  "type": "Feature",
  "properties": {
    "addr:full":"13024 Bitney Springs Rd Nevada City CA 95959",
    "addr:housenumber":"13024",
    "addr:postcode":"95959",
    "addr:street":"Bitney Springs Rd",
    "iso:country":"US",
    "sg:address":"13024 Bitney Springs Rd",
    "sg:city":"Nevada City",
    "sg:classifiers":[
        {
            "category":"Manufacturing",
            "subcategory":"Electronics",
            "type":"Manufacturing & Wholesale Goods"
        }
    ],
    "sg:phone":"+1 530 478 3000",
    "sg:postcode":"95959",
    "sg:province":"CA",
    "sg:tags":[
        "equipment",
        "broadcasting",
        "mfg"
    ],
    "wof:name":"Grass Valley Products",
    "wof:placetype":"venue"
},
  "geometry": {"coordinates":[-121.13656400000001,39.25503],"type":"Point"}
}