{
  "type": "Feature",
  "properties": {
    "iso:country":"US",
    "sg:address":"6911 Imperial Ave",
    "sg:city":"San Diego",
    "sg:classifiers":[
        {
            "category":"Restaurant",
            "type":"Food & Drink"
        }
    ],
    "sg:phone":"+1 619 263 3228",
    "sg:postcode":"92114",
    "sg:province":"CA",
    "sg:tags":[
        "mexican"
    ],
    "wof:name":"Vero's Mexican Food",
    "wof:placetype":"venue"
},
  "geometry": {"coordinates":[-117.048686,32.712196],"type":"Point"}
}