{
  "type": "Feature",
  "properties": {
    "addr:full":"401 E Grand Ave Escondido CA 92025",
    "addr:housenumber":"401",
    "addr:postcode":"92025",
    "addr:street":"E Grand Ave",
    "iso:country":"US",
    "sg:address":"401 E Grand Ave",
    "sg:city":"Escondido",
    "sg:classifiers":[
        {
            "category":"Personal",
            "subcategory":"Beauty Salon",
            "type":"Services"
        }
    ],
    "sg:phone":"+1 760 739 9802",
    "sg:postcode":"92025",
    "sg:province":"CA",
    "wof:name":"Sculpture Salon",
    "wof:placetype":"venue"
},
  "geometry": {"coordinates":[-117.07663100000001,33.124066],"type":"Point"}
}