{
  "type": "Feature",
  "properties": {
    "addr:full":"337 Emory Oak Pl Lathrop CA 95330",
    "addr:housenumber":"337",
    "addr:postcode":"95330",
    "addr:street":"Emory Oak Pl",
    "iso:country":"US",
    "sg:address":"337 Emory Oak Pl",
    "sg:city":"Lathrop",
    "sg:classifiers":[
        {
            "category":"Building & Trades",
            "subcategory":"Construction",
            "type":"Services"
        }
    ],
    "sg:phone":"+1 209 982 9920",
    "sg:postcode":"95330",
    "sg:province":"CA",
    "sg:tags":[
        "system",
        "contractor",
        "air conditioning"
    ],
    "wof:name":"Hunt Air Inc.",
    "wof:placetype":"venue"
},
  "geometry": {"coordinates":[-121.30538199999999,37.795424],"type":"Point"}
}