{
  "type": "Feature",
  "properties": {
    "iso:country":"US",
    "sg:address":"3474 Heritage Oaks Dr",
    "sg:city":"San Jose",
    "sg:classifiers":[
        {
            "category":"Food & Beverages",
            "subcategory":"Meat & Fish",
            "type":"Retail Goods"
        }
    ],
    "sg:phone":"+1 408 532 7008",
    "sg:postcode":"95148",
    "sg:province":"CA",
    "sg:tags":[
        "shop"
    ],
    "wof:name":"America's Choice Steak & Seafood",
    "wof:placetype":"venue"
},
  "geometry": {"coordinates":[-121.777,37.3167],"type":"Point"}
}