{
  "type": "Feature",
  "properties": {
    "iso:country":"US",
    "sg:address":"3111 Camino Del Rio N",
    "sg:city":"San Diego",
    "sg:classifiers":[
        {
            "category":"Professional",
            "subcategory":"Lawyer & Legal Services",
            "type":"Services"
        }
    ],
    "sg:phone":"+1 619 398 9390",
    "sg:postcode":"92108",
    "sg:province":"CA",
    "wof:name":"Alan M Anzarouth",
    "wof:placetype":"venue"
},
  "geometry": {"coordinates":[-117.12799800000001,32.774899],"type":"Point"}
}