{
  "type": "Feature",
  "properties": {
    "iso:country":"US",
    "sg:address":"833 E 4th St",
    "sg:city":"Long Beach",
    "sg:classifiers":[
        {
            "category":"Food & Beverages",
            "subcategory":"Specialty",
            "type":"Retail Goods"
        }
    ],
    "sg:phone":"+1 562 432 0760",
    "sg:postcode":"90802",
    "sg:province":"CA",
    "sg:tags":[
        "grocery"
    ],
    "wof:name":"Yanga Mini Market",
    "wof:placetype":"venue"
},
  "geometry": {"coordinates":[-118.181999,33.771801],"type":"Point"}
}