{
  "type": "Feature",
  "properties": {
    "addr:full":"159 Clarendon Rd Pacifica CA 94044",
    "addr:housenumber":"159",
    "addr:postcode":"94044",
    "addr:street":"Clarendon Rd",
    "iso:country":"US",
    "sg:address":"159 Clarendon Rd",
    "sg:city":"Pacifica",
    "sg:classifiers":[
        {
            "category":"Social Services",
            "subcategory":"Adult Care",
            "type":"Services"
        }
    ],
    "sg:phone":"+1 650 355 8554",
    "sg:postcode":"94044",
    "sg:province":"CA",
    "sg:tags":[
        "residential"
    ],
    "wof:name":"Coastal Home Care For Elderly",
    "wof:placetype":"venue"
},
  "geometry": {"coordinates":[-122.490399,37.629964],"type":"Point"}
}