{
  "type": "Feature",
  "properties": {
    "addr:full":"1335 Solomon Rd Apt D Santa Maria CA 93455",
    "addr:housenumber":"1335",
    "addr:postcode":"93455",
    "addr:street":"Solomon Rd Apt D",
    "iso:country":"US",
    "sg:address":"1335 Solomon Rd Apt D",
    "sg:city":"Santa Maria",
    "sg:classifiers":[
        {
            "category":"Retail",
            "subcategory":"Animal Services",
            "type":"Services"
        }
    ],
    "sg:phone":"+1 805 934 1800",
    "sg:postcode":"93455",
    "sg:province":"CA",
    "sg:tags":[
        "pet"
    ],
    "wof:name":"Phodography",
    "wof:placetype":"venue"
},
  "geometry": {"coordinates":[-120.458611,34.872597],"type":"Point"}
}