{
  "type": "Feature",
  "properties": {
    "iso:country":"US",
    "sg:address":"505 S Oaks Ave",
    "sg:city":"Ontario",
    "sg:classifiers":[
        {
            "category":"Wholesale",
            "subcategory":"Metals & Minerals",
            "type":"Manufacturing & Wholesale Goods"
        }
    ],
    "sg:phone":"+1 909 984 7199",
    "sg:postcode":"91762",
    "sg:province":"CA",
    "sg:tags":[
        "concrete",
        "reinforcement"
    ],
    "wof:name":"Pacific Rebar Inc",
    "wof:placetype":"venue"
},
  "geometry": {"coordinates":[-117.676349,34.056997],"type":"Point"}
}