{
  "type": "Feature",
  "properties": {
    "addr:full":"7523 Denrock Ave Los Angeles CA 90045",
    "addr:housenumber":"7523",
    "addr:postcode":"90045",
    "addr:street":"Denrock Ave",
    "iso:country":"US",
    "sg:address":"7523 Denrock Ave",
    "sg:city":"Los Angeles",
    "sg:classifiers":[
        {
            "category":"Wholesale",
            "subcategory":"Electrical",
            "type":"Manufacturing & Wholesale Goods"
        }
    ],
    "sg:phone":"+1 310 641 8304",
    "sg:postcode":"90045",
    "sg:province":"CA",
    "sg:tags":[
        "parts",
        "electronic"
    ],
    "wof:name":"Trebor Electronics",
    "wof:placetype":"venue"
},
  "geometry": {"coordinates":[-118.40846500000001,33.972178],"type":"Point"}
}