{
  "type": "Feature",
  "properties": {
    "addr:full":"1929 Freedom Blvd Freedom CA 95019",
    "addr:housenumber":"1929",
    "addr:postcode":"95019",
    "addr:street":"Freedom Blvd",
    "iso:country":"US",
    "sg:address":"1929 Freedom Blvd",
    "sg:city":"Freedom",
    "sg:classifiers":[
        {
            "category":"Retail",
            "subcategory":"Auto Repair",
            "type":"Services"
        }
    ],
    "sg:phone":"+1 831 728 3032",
    "sg:postcode":"95019",
    "sg:province":"CA",
    "sg:tags":[
        "repairing",
        "automobile"
    ],
    "wof:name":"Tony's Auto Svc",
    "wof:placetype":"venue"
},
  "geometry": {"coordinates":[-121.775699,36.936816],"type":"Point"}
}