{
  "type": "Feature",
  "properties": {
    "addr:full":"1958 Yodel Ln San Diego CA 92154",
    "addr:housenumber":"1958",
    "addr:postcode":"92154",
    "addr:street":"Yodel Ln",
    "iso:country":"US",
    "sg:address":"1958 Yodel Ln",
    "sg:city":"San Diego",
    "sg:classifiers":[
        {
            "category":"Professional",
            "type":"Services"
        }
    ],
    "sg:phone":"+1 619 575 0713",
    "sg:postcode":"92154",
    "sg:province":"CA",
    "wof:name":"Fish Fancy Inc",
    "wof:placetype":"venue"
},
  "geometry": {"coordinates":[-117.090791,32.574361],"type":"Point"}
}