{
  "type": "Feature",
  "properties": {
    "addr:full":"17015 Pacific Coast Hwy Pacific Palisades CA 90272",
    "addr:housenumber":"17015",
    "addr:postcode":"90272",
    "addr:street":"Pacific Coast Hwy",
    "iso:country":"US",
    "sg:address":"17015 Pacific Coast Hwy",
    "sg:city":"Pacific Palisades",
    "sg:classifiers":[
        {
            "category":"Shopping",
            "subcategory":"Clothing, Apparel, & Fashions",
            "type":"Retail Goods"
        }
    ],
    "sg:phone":"+1 310 454 7686",
    "sg:postcode":"90272",
    "sg:province":"CA",
    "wof:name":"Paula Sindoni",
    "wof:placetype":"venue"
},
  "geometry": {"coordinates":[-118.55219,34.03919],"type":"Point"}
}