{
  "type": "Feature",
  "properties": {
    "addr:full":"19763 Sherman Way Canoga Park CA 91306",
    "addr:housenumber":"19763",
    "addr:postcode":"91306",
    "addr:street":"Sherman Way",
    "iso:country":"US",
    "sg:address":"19763 Sherman Way",
    "sg:city":"Canoga Park",
    "sg:classifiers":[
        {
            "category":"Retail",
            "subcategory":"Auto Repair",
            "type":"Services"
        }
    ],
    "sg:phone":"+1 818 882 2565",
    "sg:postcode":"91306",
    "sg:province":"CA",
    "sg:tags":[
        "body",
        "shop",
        "painting",
        "automobile"
    ],
    "sg:website":"www.normsab.com",
    "wof:name":"Norm's Auto Body",
    "wof:placetype":"venue"
},
  "geometry": {"coordinates":[-118.563666,34.201153],"type":"Point"}
}