{
  "type": "Feature",
  "properties": {
    "addr:full":"12427 Alondra Blvd Norwalk CA 90650",
    "addr:housenumber":"12427",
    "addr:postcode":"90650",
    "addr:street":"Alondra Blvd",
    "iso:country":"US",
    "sg:address":"12427 Alondra Blvd",
    "sg:city":"Norwalk",
    "sg:classifiers":[
        {
            "category":"Home & Garden",
            "subcategory":"Household Appliances",
            "type":"Retail Goods"
        }
    ],
    "sg:phone":"+1 562 927 8858",
    "sg:postcode":"90650",
    "sg:province":"CA",
    "sg:tags":[
        "repair"
    ],
    "wof:name":"Larry's Home Appliance Center",
    "wof:placetype":"venue"
},
  "geometry": {"coordinates":[-118.068001,33.888],"type":"Point"}
}