{
  "type": "Feature",
  "properties": {
    "iso:country":"US",
    "sg:address":"230 Longden Ave",
    "sg:city":"Irwindale",
    "sg:classifiers":[
        {
            "category":"Manufacturing",
            "subcategory":"Glass & Minerals",
            "type":"Manufacturing & Wholesale Goods"
        }
    ],
    "sg:phone":"+1 626 445 2125",
    "sg:postcode":"91706",
    "sg:province":"CA",
    "sg:tags":[
        "ready"
    ],
    "sg:website":"www.spraguesreadymix.com",
    "wof:name":"Spragues' Ready Mix",
    "wof:placetype":"venue"
},
  "geometry": {"coordinates":[-118.002556,34.113441],"type":"Point"}
}