{
  "type": "Feature",
  "properties": {
    "addr:full":"4535 McGrath St Ventura CA 93003",
    "addr:housenumber":"4535",
    "addr:postcode":"93003",
    "addr:street":"Mcgrath St",
    "iso:country":"US",
    "sg:address":"4535 McGrath St",
    "sg:city":"Ventura",
    "sg:classifiers":[
        {
            "category":"Manufacturing",
            "subcategory":"Tools & Machinery",
            "type":"Manufacturing & Wholesale Goods"
        }
    ],
    "sg:phone":"+1 805 642 4062",
    "sg:postcode":"93003",
    "sg:province":"CA",
    "sg:tags":[
        "machine",
        "shop"
    ],
    "wof:name":"Accurate Technologies",
    "wof:placetype":"venue"
},
  "geometry": {"coordinates":[-119.23226,34.254347],"type":"Point"}
}