{
  "type": "Feature",
  "properties": {
    "iso:country":"US",
    "sg:address":"125 N Kalmia St",
    "sg:city":"Escondido",
    "sg:classifiers":[
        {
            "category":"Travel",
            "subcategory":"Travel Agent",
            "type":"Entertainment"
        }
    ],
    "sg:phone":"+1 760 745 6140",
    "sg:postcode":"92025",
    "sg:province":"CA",
    "sg:tags":[
        "agency",
        "bureau"
    ],
    "wof:name":"Royal Travel Svc",
    "wof:placetype":"venue"
},
  "geometry": {"coordinates":[-117.080354,33.122562],"type":"Point"}
}