{
  "type": "Feature",
  "properties": {
    "iso:country":"US",
    "sg:address":"1009 3rd Street",
    "sg:city":"Santa Cruz",
    "sg:classifiers":[
        {
            "category":"Health Services",
            "subcategory":"Health Practitioner",
            "type":"Services"
        }
    ],
    "sg:phone":"+1 831 427 1346",
    "sg:postcode":"95060",
    "sg:province":"CA",
    "sg:tags":[
        "acupuncture"
    ],
    "wof:name":"Burton Michael S PHD Lac Green-Eyed Tiger Oriental Medicine",
    "wof:placetype":"venue"
},
  "geometry": {"coordinates":[-122.023741,36.966218],"type":"Point"}
}