{
  "type": "Feature",
  "properties": {
    "iso:country":"US",
    "sg:address":"2277 Valley Rd",
    "sg:city":"Oceanside",
    "sg:classifiers":[
        {
            "category":"Manufacturing",
            "subcategory":"Printing",
            "type":"Manufacturing & Wholesale Goods"
        }
    ],
    "sg:phone":"+1 760 519 5047",
    "sg:postcode":"92056",
    "sg:province":"CA",
    "sg:tags":[
        "printer"
    ],
    "wof:name":"Crowell & Assoc",
    "wof:placetype":"venue"
},
  "geometry": {"coordinates":[-117.323283,33.190873],"type":"Point"}
}