{
  "type": "Feature",
  "properties": {
    "addr:full":"15080 7th St Ste 6 Victorville CA 92395",
    "addr:housenumber":"15080",
    "addr:postcode":"92395",
    "addr:street":"7Th St Ste 6",
    "iso:country":"US",
    "sg:address":"15080 7th St Ste 6",
    "sg:city":"Victorville",
    "sg:classifiers":[
        {
            "category":"Health Services",
            "subcategory":"Doctor",
            "type":"Services"
        }
    ],
    "sg:phone":"+1 760 245 3113",
    "sg:postcode":"92395",
    "sg:province":"CA",
    "sg:tags":[
        "physician",
        "family",
        "practice",
        "surgeons",
        "medicine"
    ],
    "wof:name":"Valley Family Care Center",
    "wof:placetype":"venue"
},
  "geometry": {"coordinates":[-117.303051,34.52558],"type":"Point"}
}