{
  "type": "Feature",
  "properties": {
    "addr:full":"1309 Simpson Way Escondido CA 92029",
    "addr:housenumber":"1309",
    "addr:postcode":"92029",
    "addr:street":"Simpson Way",
    "iso:country":"US",
    "sg:address":"1309 Simpson Way",
    "sg:city":"Escondido",
    "sg:classifiers":[
        {
            "category":"Restaurant",
            "type":"Food & Drink"
        }
    ],
    "sg:phone":"+1 760 737 8594",
    "sg:postcode":"92029",
    "sg:province":"CA",
    "sg:tags":[
        "caterer"
    ],
    "wof:name":"Chuck Wagon Catering",
    "wof:placetype":"venue"
},
  "geometry": {"coordinates":[-117.10201600000001,33.11952],"type":"Point"}
}