{
  "type": "Feature",
  "properties": {
    "addr:full":"3369 Hadley Dr Mira Loma CA 91752",
    "addr:housenumber":"3369",
    "addr:postcode":"91752",
    "addr:street":"Hadley Dr",
    "iso:country":"US",
    "sg:address":"3369 Hadley Dr",
    "sg:city":"Mira Loma",
    "sg:classifiers":[
        {
            "category":"Retail",
            "subcategory":"Repair Shop",
            "type":"Services"
        }
    ],
    "sg:phone":"+1 951 681 7723",
    "sg:postcode":"91752",
    "sg:province":"CA",
    "sg:tags":[
        "welding"
    ],
    "wof:name":"M A P Welding",
    "wof:placetype":"venue"
},
  "geometry": {"coordinates":[-117.51167,34.027904],"type":"Point"}
}