{
  "type": "Feature",
  "properties": {
    "iso:country":"US",
    "sg:address":"6126 Sylvester Way",
    "sg:city":"Carmichael",
    "sg:classifiers":[
        {
            "category":"Professional",
            "subcategory":"Detective & Security Services",
            "type":"Services"
        }
    ],
    "sg:phone":"+1 916 965 8348",
    "sg:postcode":"95608",
    "sg:province":"CA",
    "sg:tags":[
        "information",
        "bureau"
    ],
    "wof:name":"Pauls Pool Service",
    "wof:placetype":"venue"
},
  "geometry": {"coordinates":[-121.32207200000001,38.670386],"type":"Point"}
}