{
  "type": "Feature",
  "properties": {
    "addr:full":"620 Park View Dr Santa Clara CA 95054",
    "addr:housenumber":"620",
    "addr:postcode":"95054",
    "addr:street":"Park View Dr",
    "iso:country":"US",
    "sg:address":"620 Park View Dr",
    "sg:city":"Santa Clara",
    "sg:classifiers":[
        {
            "category":"Professional",
            "type":"Services"
        }
    ],
    "sg:phone":"+1 408 853 2995",
    "sg:postcode":"95054",
    "sg:province":"CA",
    "wof:name":"Hassan Farrukh",
    "wof:placetype":"venue"
},
  "geometry": {"coordinates":[-121.94620399999999,37.400064],"type":"Point"}
}