{
  "type": "Feature",
  "properties": {
    "addr:full":"373 Avenue Of The Flags Buellton CA 93427",
    "addr:housenumber":"373",
    "addr:postcode":"93427",
    "addr:street":"Avenue Of",
    "iso:country":"US",
    "sg:address":"373 Avenue Of The Flags",
    "sg:city":"Buellton",
    "sg:classifiers":[
        {
            "category":"Insurance",
            "subcategory":"Hazard Insurance",
            "type":"Services"
        },
        {
            "category":"Insurance",
            "subcategory":"Insurance Agent",
            "type":"Services"
        },
        {
            "category":"Insurance",
            "subcategory":"Life Insurance",
            "type":"Services"
        },
        {
            "category":"Insurance",
            "subcategory":"Title Insurance",
            "type":"Services"
        }
    ],
    "sg:phone":"+1 805 688 6106",
    "sg:postcode":"93427",
    "sg:province":"CA",
    "sg:tags":[
        "auto",
        "commercial",
        "business",
        "homeowner"
    ],
    "sg:website":"http://www.farmersagent.com/jmehm/",
    "wof:name":"Joseph Mehm - Farmers Insurance",
    "wof:placetype":"venue"
},
  "geometry": {"coordinates":[-120.193307,34.614396],"type":"Point"}
}