{
  "type": "Feature",
  "properties": {
    "iso:country":"US",
    "sg:address":"770 Magnolia Ave",
    "sg:city":"Corona",
    "sg:classifiers":[
        {
            "category":"Health Services",
            "subcategory":"Doctor",
            "type":"Services"
        }
    ],
    "sg:phone":"+1 951 278 9377",
    "sg:postcode":"92879",
    "sg:province":"CA",
    "sg:tags":[
        "physician",
        "surgeon"
    ],
    "wof:name":"Sudarshan Kumar Inc",
    "wof:placetype":"venue"
},
  "geometry": {"coordinates":[-117.552109,33.860121],"type":"Point"}
}