{
  "type": "Feature",
  "properties": {
    "iso:country":"US",
    "sg:address":"859 S Harbor Blvd",
    "sg:city":"Anaheim",
    "sg:classifiers":[
        {
            "category":"Shopping Center",
            "type":"Public Place"
        }
    ],
    "sg:phone":"+1 323 571 2828",
    "sg:postcode":"92805",
    "sg:province":"CA",
    "sg:tags":[
        "mall"
    ],
    "wof:name":"Kf Harbor",
    "wof:placetype":"venue"
},
  "geometry": {"coordinates":[-117.915986,33.823322],"type":"Point"}
}