{
  "type": "Feature",
  "properties": {
    "addr:full":"407 S Highland Ave Fullerton CA 92832",
    "addr:housenumber":"407",
    "addr:postcode":"92832",
    "addr:street":"S Highland Ave",
    "iso:country":"US",
    "sg:address":"407 S Highland Ave",
    "sg:city":"Fullerton",
    "sg:classifiers":[
        {
            "category":"Food & Beverages",
            "subcategory":"Groceries & Convenience Stores",
            "type":"Retail Goods"
        }
    ],
    "sg:phone":"+1 714 447 8980",
    "sg:postcode":"92832",
    "sg:province":"CA",
    "wof:name":"Feliz Market",
    "wof:placetype":"venue"
},
  "geometry": {"coordinates":[-117.92882899999999,33.866933],"type":"Point"}
}