{
  "type": "Feature",
  "properties": {
    "addr:full":"715 N Weatherlow St Susanville CA 96130",
    "addr:housenumber":"715",
    "addr:postcode":"96130",
    "addr:street":"N Weatherlow St",
    "iso:country":"US",
    "sg:address":"715 N Weatherlow St",
    "sg:city":"Susanville",
    "sg:classifiers":[
        {
            "category":"Retail",
            "subcategory":"Repair Shop",
            "type":"Services"
        }
    ],
    "sg:phone":"+1 530 257 7082",
    "sg:postcode":"96130",
    "sg:province":"CA",
    "sg:tags":[
        "welding"
    ],
    "wof:name":"Beter Welding & Fabrication",
    "wof:placetype":"venue"
},
  "geometry": {"coordinates":[-120.65520100000001,40.425813],"type":"Point"}
}