{
  "type": "Feature",
  "properties": {
    "iso:country":"US",
    "sg:address":"24202 Lake Dr.",
    "sg:city":"Crestline",
    "sg:classifiers":[
        {
            "category":"Travel",
            "subcategory":"Hotels & Motels",
            "type":"Entertainment"
        }
    ],
    "sg:phone":"+1 909 338 5230",
    "sg:postcode":"92325",
    "sg:province":"CA",
    "sg:website":"www.thenorthshoreinn.com",
    "wof:name":"The North Shore Inn",
    "wof:placetype":"venue"
},
  "geometry": {"coordinates":[-117.27513999999999,34.243645],"type":"Point"}
}