{
  "type": "Feature",
  "properties": {
    "iso:country":"US",
    "sg:address":"11149 Vanowen St",
    "sg:city":"North Hollywood",
    "sg:classifiers":[
        {
            "category":"Shopping",
            "subcategory":"Clothing, Apparel, & Fashions",
            "type":"Retail Goods"
        }
    ],
    "sg:phone":"+1 818 753 3700",
    "sg:postcode":"91605",
    "sg:province":"CA",
    "sg:tags":[
        "theatrical",
        "costume"
    ],
    "wof:name":"Costume Rentals",
    "wof:placetype":"venue"
},
  "geometry": {"coordinates":[-118.37400100000001,34.193802],"type":"Point"}
}