{
  "type": "Feature",
  "properties": {
    "addr:full":"309 Cll Delicada San Clemente CA 92672",
    "addr:housenumber":"309",
    "addr:postcode":"92672",
    "addr:street":"Cll Delicada",
    "iso:country":"US",
    "sg:address":"309 Cll Delicada",
    "sg:city":"San Clemente",
    "sg:classifiers":[
        {
            "category":"Insurance",
            "subcategory":"Insurance Agent",
            "type":"Services"
        }
    ],
    "sg:phone":"+1 949 369 8512",
    "sg:postcode":"92672",
    "sg:province":"CA",
    "sg:tags":[
        "communications",
        "telephone"
    ],
    "wof:name":"Rollins & Associates",
    "wof:placetype":"venue"
},
  "geometry": {"coordinates":[-117.609537,33.437588],"type":"Point"}
}