{
  "type": "Feature",
  "properties": {
    "addr:full":"2054 Klamath River Dr Rancho Cordova CA 95670",
    "addr:housenumber":"2054",
    "addr:postcode":"95670",
    "addr:street":"Klamath River Dr",
    "iso:country":"US",
    "sg:address":"2054 Klamath River Dr",
    "sg:city":"Rancho Cordova",
    "sg:classifiers":[
        {
            "category":"Building & Trades",
            "subcategory":"Construction",
            "type":"Services"
        }
    ],
    "sg:phone":"+1 916 806 8160",
    "sg:postcode":"95670",
    "sg:province":"CA",
    "sg:tags":[
        "handyman"
    ],
    "wof:name":"Don Wroth Enterprises",
    "wof:placetype":"venue"
},
  "geometry": {"coordinates":[-121.26786199999999,38.627336],"type":"Point"}
}