{
  "type": "Feature",
  "properties": {
    "addr:full":"5164 Bloch St San Diego CA 92122",
    "addr:housenumber":"5164",
    "addr:postcode":"92122",
    "addr:street":"Bloch St",
    "iso:country":"US",
    "sg:address":"5164 Bloch St",
    "sg:city":"San Diego",
    "sg:classifiers":[
        {
            "category":"Professional",
            "subcategory":"Business Services",
            "type":"Services"
        }
    ],
    "sg:phone":"+1 858 458 9171",
    "sg:postcode":"92122",
    "sg:province":"CA",
    "sg:tags":[
        "embroidery"
    ],
    "wof:name":"Normann Designs",
    "wof:placetype":"venue"
},
  "geometry": {"coordinates":[-117.22901,32.839827],"type":"Point"}
}