{
  "type": "Feature",
  "properties": {
    "iso:country":"US",
    "sg:address":"160 W Santa Clara St Ste 1180",
    "sg:city":"San Jose",
    "sg:classifiers":[
        {
            "category":"Professional",
            "subcategory":"Lawyer & Legal Services",
            "type":"Services"
        }
    ],
    "sg:phone":"+1 408 286 1200",
    "sg:postcode":"95113",
    "sg:province":"CA",
    "wof:name":"Tenenbaum & Crowley & Brereton",
    "wof:placetype":"venue"
},
  "geometry": {"coordinates":[-121.892948,37.334551],"type":"Point"}
}