{
  "type": "Feature",
  "properties": {
    "iso:country":"US",
    "sg:address":"4639 Pico St",
    "sg:city":"San Diego",
    "sg:classifiers":[
        {
            "category":"Real Estate",
            "subcategory":"Real Estate Operator",
            "type":"Services"
        }
    ],
    "sg:phone":"+1 858 337 7264",
    "sg:postcode":"92109",
    "sg:province":"CA",
    "sg:tags":[
        "apartment"
    ],
    "wof:name":"Pico Colony Apartments",
    "wof:placetype":"venue"
},
  "geometry": {"coordinates":[-117.223016,32.806683],"type":"Point"}
}