{
  "type": "Feature",
  "properties": {
    "iso:country":"US",
    "sg:address":"4834 Halison St",
    "sg:city":"Torrance",
    "sg:classifiers":[
        {
            "category":"Airline",
            "type":"Transportation"
        }
    ],
    "sg:phone":"+1 310 373 9536",
    "sg:postcode":"90503",
    "sg:province":"CA",
    "sg:tags":[
        "courier",
        "air"
    ],
    "wof:name":"Flying Eagle USA",
    "wof:placetype":"venue"
},
  "geometry": {"coordinates":[-118.36210699999999,33.851215],"type":"Point"}
}