{
  "type": "Feature",
  "properties": {
    "iso:country":"US",
    "sg:address":"1728 Franklin St",
    "sg:city":"Oakland",
    "sg:classifiers":[
        {
            "category":"Education",
            "subcategory":"Vocational School",
            "type":"Public Place"
        }
    ],
    "sg:phone":"+1 510 891 8671",
    "sg:postcode":"94612",
    "sg:province":"CA",
    "wof:name":"Advance Vocational Institute",
    "wof:placetype":"venue"
},
  "geometry": {"coordinates":[-122.267848,37.807105],"type":"Point"}
}