{
  "type": "Feature",
  "properties": {
    "addr:full":"1405 Solana Dr Belmont CA 94002",
    "addr:housenumber":"1405",
    "addr:postcode":"94002",
    "addr:street":"Solana Dr",
    "iso:country":"US",
    "sg:address":"1405 Solana Dr",
    "sg:city":"Belmont",
    "sg:classifiers":[
        {
            "category":"Education",
            "subcategory":"School",
            "type":"Public Place"
        }
    ],
    "sg:phone":"+1 650 592 7570",
    "sg:postcode":"94002",
    "sg:province":"CA",
    "sg:tags":[
        "high",
        "middle",
        "elementary"
    ],
    "wof:name":"Charles Armstrong School",
    "wof:placetype":"venue"
},
  "geometry": {"coordinates":[-122.283997,37.511398],"type":"Point"}
}