{
  "type": "Feature",
  "properties": {
    "iso:country":"US",
    "sg:address":"4610 Laurelwood Dr",
    "sg:city":"Santa Maria",
    "sg:classifiers":[
        {
            "category":"Professional",
            "type":"Services"
        }
    ],
    "sg:phone":"+1 805 938 1454",
    "sg:postcode":"93455",
    "sg:province":"CA",
    "sg:tags":[
        "establishment"
    ],
    "wof:name":"Real Deal Enterprise",
    "wof:placetype":"venue"
},
  "geometry": {"coordinates":[-120.42485600000001,34.869597],"type":"Point"}
}