{
  "type": "Feature",
  "properties": {
    "addr:full":"2348 W Whitendale Ave Visalia CA 93277",
    "addr:housenumber":"2348",
    "addr:postcode":"93277",
    "addr:street":"W Whitendale Ave",
    "iso:country":"US",
    "sg:address":"2348 W Whitendale Ave",
    "sg:city":"Visalia",
    "sg:classifiers":[
        {
            "category":"Real Estate",
            "subcategory":"Real Estate Agent",
            "type":"Services"
        }
    ],
    "sg:phone":"+1 559 734 2320",
    "sg:postcode":"93277",
    "sg:province":"CA",
    "wof:name":"Realty World",
    "wof:placetype":"venue"
},
  "geometry": {"coordinates":[-119.31559900000001,36.305841],"type":"Point"}
}