{
  "type": "Feature",
  "properties": {
    "addr:full":"6098 Silveroak Cir Stockton CA 95219",
    "addr:housenumber":"6098",
    "addr:postcode":"95219",
    "addr:street":"Silveroak Cir",
    "iso:country":"US",
    "sg:address":"6098 Silveroak Cir",
    "sg:city":"Stockton",
    "sg:classifiers":[
        {
            "category":"Social Services",
            "subcategory":"Job Training",
            "type":"Services"
        }
    ],
    "sg:phone":"+1 209 476 9503",
    "sg:postcode":"95219",
    "sg:province":"CA",
    "sg:tags":[
        "nursing",
        "homes-skilled",
        "facility"
    ],
    "wof:name":"California Nursing Solutions",
    "wof:placetype":"venue"
},
  "geometry": {"coordinates":[-121.389974,38.055177],"type":"Point"}
}