{
  "type": "Feature",
  "properties": {
    "iso:country":"US",
    "sg:address":"1341 W Westfield Ave",
    "sg:city":"Porterville",
    "sg:classifiers":[
        {
            "category":"Banks & Credit Unions",
            "subcategory":"Bank",
            "type":"Services"
        }
    ],
    "sg:phone":"+1 559 782 1265",
    "sg:postcode":"93257",
    "sg:province":"CA",
    "sg:tags":[
        "leasing",
        "vehicle"
    ],
    "wof:name":"Gabriel Meneses",
    "wof:placetype":"venue"
},
  "geometry": {"coordinates":[-119.046464,36.087537],"type":"Point"}
}