{
  "type": "Feature",
  "properties": {
    "iso:country":"US",
    "sg:address":"18993 Amberly Pl",
    "sg:city":"Rowland Heights",
    "sg:classifiers":[
        {
            "category":"Professional",
            "type":"Services"
        }
    ],
    "sg:phone":"+1 626 810 0870",
    "sg:postcode":"91748",
    "sg:province":"CA",
    "wof:name":"Calex International LLC",
    "wof:placetype":"venue"
},
  "geometry": {"coordinates":[-117.88815,33.96896],"type":"Point"}
}