{
  "type": "Feature",
  "properties": {
    "addr:full":"1638 Placentia Ave Costa Mesa CA 92627",
    "addr:housenumber":"1638",
    "addr:postcode":"92627",
    "addr:street":"Placentia Ave",
    "iso:country":"US",
    "sg:address":"1638 Placentia Ave",
    "sg:city":"Costa Mesa",
    "sg:classifiers":[
        {
            "category":"Retail",
            "subcategory":"Auto Repair",
            "type":"Services"
        }
    ],
    "sg:phone":"+1 949 722 6388",
    "sg:postcode":"92627",
    "sg:province":"CA",
    "sg:tags":[
        "repairing",
        "automobile"
    ],
    "wof:name":"Clutches Only",
    "wof:placetype":"venue"
},
  "geometry": {"coordinates":[-117.93180099999999,33.634707],"type":"Point"}
}