{
  "type": "Feature",
  "properties": {
    "addr:full":"3198 1/2 W 7th St Los Angeles CA 90005",
    "addr:housenumber":"3198 1 / 2",
    "addr:postcode":"90005",
    "addr:street":"W 7Th St",
    "iso:country":"US",
    "sg:address":"3198 1/2 W 7th St",
    "sg:city":"Los Angeles",
    "sg:classifiers":[
        {
            "category":"Restaurant",
            "type":"Food & Drink"
        }
    ],
    "sg:phone":"+1 213 389 1586",
    "sg:postcode":"90005",
    "sg:province":"CA",
    "wof:name":"Hwang Tae Ja",
    "wof:placetype":"venue"
},
  "geometry": {"coordinates":[-118.29513799999999,34.059593],"type":"Point"}
}