{
  "type": "Feature",
  "properties": {
    "iso:country":"US",
    "sg:address":"2 Chester St",
    "sg:city":"Daly City",
    "sg:classifiers":[
        {
            "category":"Restaurant",
            "type":"Food & Drink"
        }
    ],
    "sg:phone":"+1 650 992 0160",
    "sg:postcode":"94014",
    "sg:province":"CA",
    "wof:name":"LA Pachanga Restaurant",
    "wof:placetype":"venue"
},
  "geometry": {"coordinates":[-122.459216,37.686772],"type":"Point"}
}