{
  "type": "Feature",
  "properties": {
    "iso:country":"US",
    "sg:address":"11714 Canton Pl",
    "sg:city":"Studio City",
    "sg:classifiers":[
        {
            "category":"Communications",
            "subcategory":"Film & Video Production",
            "type":"Services"
        }
    ],
    "sg:phone":"+1 818 972 3600",
    "sg:postcode":"91604",
    "sg:province":"CA",
    "sg:tags":[
        "motion",
        "picture",
        "payroll",
        "casting"
    ],
    "wof:name":"Total Eclipse Productions",
    "wof:placetype":"venue"
},
  "geometry": {"coordinates":[-118.39036400000001,34.133407],"type":"Point"}
}