{
  "type": "Feature",
  "properties": {
    "addr:full":"2458 Butler Ave Los Angeles CA 90064",
    "addr:housenumber":"2458",
    "addr:postcode":"90064",
    "addr:street":"Butler Ave",
    "iso:country":"US",
    "sg:address":"2458 Butler Ave",
    "sg:city":"Los Angeles",
    "sg:classifiers":[
        {
            "category":"Building & Trades",
            "subcategory":"Landscaping Services",
            "type":"Services"
        }
    ],
    "sg:phone":"+1 310 312 6883",
    "sg:postcode":"90064",
    "sg:province":"CA",
    "sg:tags":[
        "planning",
        "designer",
        "design",
        "architecture",
        "landscape"
    ],
    "wof:name":"Laura Saltzman & Associates",
    "wof:placetype":"venue"
},
  "geometry": {"coordinates":[-118.440336,34.032765],"type":"Point"}
}