{
  "type": "Feature",
  "properties": {
    "iso:country":"US",
    "sg:address":"2521 S Rodeo Gulch Rd",
    "sg:city":"Soquel",
    "sg:classifiers":[
        {
            "category":"Wholesale",
            "subcategory":"Durable Goods & Equipment",
            "type":"Manufacturing & Wholesale Goods"
        }
    ],
    "sg:phone":"+1 831 479 0837",
    "sg:postcode":"95073",
    "sg:province":"CA",
    "sg:tags":[
        "laser"
    ],
    "wof:name":"Actinix",
    "wof:placetype":"venue"
},
  "geometry": {"coordinates":[-121.96959699999999,36.983591],"type":"Point"}
}