{
  "type": "Feature",
  "properties": {
    "addr:full":"1000 Adlar Ct Chico CA 95926",
    "addr:housenumber":"1000",
    "addr:postcode":"95926",
    "addr:street":"Adlar Ct",
    "iso:country":"US",
    "sg:address":"1000 Adlar Ct",
    "sg:city":"Chico",
    "sg:classifiers":[
        {
            "category":"Wholesale",
            "subcategory":"Durable Goods & Equipment",
            "type":"Manufacturing & Wholesale Goods"
        }
    ],
    "sg:phone":"+1 530 894 9070",
    "sg:postcode":"95926",
    "sg:province":"CA",
    "sg:tags":[
        "representative",
        "manufacturer"
    ],
    "wof:name":"International Markets Group",
    "wof:placetype":"venue"
},
  "geometry": {"coordinates":[-121.87294199999999,39.73354],"type":"Point"}
}