{
  "type": "Feature",
  "properties": {
    "iso:country":"US",
    "sg:address":"4320 Mills Cir",
    "sg:city":"Ontario",
    "sg:classifiers":[
        {
            "category":"Banks & Credit Unions",
            "subcategory":"Bank",
            "type":"Services"
        }
    ],
    "sg:phone":"+1 909 390 8180",
    "sg:postcode":"91764",
    "sg:province":"CA",
    "sg:tags":[
        "loan",
        "real estate"
    ],
    "wof:name":"Security Pacific Home Loans",
    "wof:placetype":"venue"
},
  "geometry": {"coordinates":[-117.555818,34.076195],"type":"Point"}
}