{
  "type": "Feature",
  "properties": {
    "iso:country":"US",
    "sg:address":"750 E McGlincy Ln Ste 104",
    "sg:city":"Campbell",
    "sg:classifiers":[
        {
            "category":"Shopping",
            "subcategory":"Stationery & Office Supplies",
            "type":"Retail Goods"
        },
        {
            "category":"Personal",
            "type":"Services"
        }
    ],
    "sg:phone":"+1 408 374 0900",
    "sg:postcode":"95008",
    "sg:province":"CA",
    "sg:tags":[
        "equipment",
        "home"
    ],
    "sg:website":"www.gridleycompany.com",
    "wof:name":"Gridley Company",
    "wof:placetype":"venue"
},
  "geometry": {"coordinates":[-121.937246,37.278414],"type":"Point"}
}