{
  "type": "Feature",
  "properties": {
    "iso:country":"US",
    "sg:address":"755 Sunrise Ave",
    "sg:city":"Roseville",
    "sg:classifiers":[
        {
            "category":"Health Services",
            "subcategory":"Medical Lab",
            "type":"Services"
        }
    ],
    "sg:phone":"+1 916 773 4557",
    "sg:postcode":"95661",
    "sg:province":"CA",
    "sg:tags":[
        "laboratory"
    ],
    "wof:name":"Artistic Dental Design Studio",
    "wof:placetype":"venue"
},
  "geometry": {"coordinates":[-121.271967,38.733595],"type":"Point"}
}