{
  "type": "Feature",
  "properties": {
    "iso:country":"US",
    "sg:address":"10722 Arrow Rte",
    "sg:city":"Rancho Cucamonga",
    "sg:classifiers":[
        {
            "category":"Professional",
            "subcategory":"Lawyer & Legal Services",
            "type":"Services"
        }
    ],
    "sg:phone":"+1 909 980 4777",
    "sg:postcode":"91730",
    "sg:province":"CA",
    "sg:tags":[
        "attorney"
    ],
    "wof:name":"Bernstein Law Corp",
    "wof:placetype":"venue"
},
  "geometry": {"coordinates":[-117.569532,34.099213],"type":"Point"}
}