{
  "type": "Feature",
  "properties": {
    "addr:full":"740 E Hill St Long Beach CA 90806",
    "addr:housenumber":"740",
    "addr:postcode":"90806",
    "addr:street":"E Hill St",
    "iso:country":"US",
    "sg:address":"740 E Hill St",
    "sg:city":"Long Beach",
    "sg:classifiers":[
        {
            "category":"Organizations",
            "subcategory":"Religious Organization",
            "type":"Services"
        }
    ],
    "sg:phone":"+1 562 591 0311",
    "sg:postcode":"90806",
    "sg:province":"CA",
    "sg:tags":[
        "church"
    ],
    "wof:name":"Great Deliverance Church-God",
    "wof:placetype":"venue"
},
  "geometry": {"coordinates":[-118.18320799999999,33.797046],"type":"Point"}
}