{
  "type": "Feature",
  "properties": {
    "iso:country":"US",
    "sg:address":"1711 Schaeffer Rd",
    "sg:city":"Sebastopol",
    "sg:classifiers":[
        {
            "category":"Professional",
            "subcategory":"Business Services",
            "type":"Services"
        }
    ],
    "sg:phone":"+1 707 824 1957",
    "sg:postcode":"95472",
    "sg:province":"CA",
    "sg:tags":[
        "appraiser"
    ],
    "wof:name":"Brorsen & Savage Accredited",
    "wof:placetype":"venue"
},
  "geometry": {"coordinates":[-122.814333,38.361021],"type":"Point"}
}