{
  "type": "Feature",
  "properties": {
    "addr:full":"2705 Artesia Boulevard Redondo Beach CA 90278",
    "addr:housenumber":"2705",
    "addr:postcode":"90278",
    "addr:street":"Artesia Boulevard",
    "iso:country":"US",
    "sg:address":"2705 Artesia Boulevard",
    "sg:city":"Redondo Beach",
    "sg:classifiers":[
        {
            "category":"Health Services",
            "subcategory":"Health Practitioner",
            "type":"Services"
        }
    ],
    "sg:phone":"+1 310 371 3717",
    "sg:postcode":"90278",
    "sg:province":"CA",
    "sg:tags":[
        "acupuncture"
    ],
    "wof:name":"Dalmagie",
    "wof:placetype":"venue"
},
  "geometry": {"coordinates":[-118.362199,33.873032],"type":"Point"}
}