{
  "type": "Feature",
  "properties": {
    "addr:full":"350 Kiely Blvd San Jose CA 95129",
    "addr:housenumber":"350",
    "addr:postcode":"95129",
    "addr:street":"Kiely Blvd",
    "iso:country":"US",
    "sg:address":"350 Kiely Blvd",
    "sg:city":"San Jose",
    "sg:classifiers":[
        {
            "category":"Retail",
            "subcategory":"Auto Repair",
            "type":"Services"
        }
    ],
    "sg:phone":"+1 408 244 4540",
    "sg:postcode":"95129",
    "sg:province":"CA",
    "sg:website":"www.kwmuffler.com",
    "wof:name":"Kwik-Way Muffler Service",
    "wof:placetype":"venue"
},
  "geometry": {"coordinates":[-121.975138,37.32174],"type":"Point"}
}