{
  "type": "Feature",
  "properties": {
    "addr:full":"1401 N Chester Ave Bakersfield CA 93308",
    "addr:housenumber":"1401",
    "addr:postcode":"93308",
    "addr:street":"N Chester Ave",
    "iso:country":"US",
    "sg:address":"1401 N Chester Ave",
    "sg:city":"Bakersfield",
    "sg:classifiers":[
        {
            "category":"Restaurant",
            "type":"Food & Drink"
        }
    ],
    "sg:phone":"+1 661 392 1352",
    "sg:postcode":"93308",
    "sg:province":"CA",
    "wof:name":"Tacos LA Villa",
    "wof:placetype":"venue"
},
  "geometry": {"coordinates":[-119.021171,35.419439],"type":"Point"}
}