{
  "type": "Feature",
  "properties": {
    "iso:country":"US",
    "sg:address":"24351 Avenida De La Carlota",
    "sg:city":"Laguna Hills",
    "sg:classifiers":[
        {
            "category":"Restaurant",
            "type":"Food & Drink"
        }
    ],
    "sg:phone":"+1 949 587 9418",
    "sg:postcode":"92653",
    "sg:province":"CA",
    "sg:tags":[
        "breakfast",
        "brunch"
    ],
    "sg:website":"www.breakofdawnrestaurant.com",
    "wof:name":"Break of Dawn",
    "wof:placetype":"venue"
},
  "geometry": {"coordinates":[-117.701178,33.609199],"type":"Point"}
}