{
  "type": "Feature",
  "properties": {
    "addr:full":"2933 W Capitol Ave West Sacramento CA 95605",
    "addr:housenumber":"2933",
    "addr:postcode":"95605",
    "addr:street":"W Capitol Ave",
    "iso:country":"US",
    "sg:address":"2933 W Capitol Ave",
    "sg:city":"West Sacramento",
    "sg:classifiers":[
        {
            "category":"Restaurant",
            "type":"Food & Drink"
        }
    ],
    "sg:phone":"+1 916 371 3322",
    "sg:postcode":"95605",
    "sg:province":"CA",
    "sg:tags":[
        "chinese"
    ],
    "wof:name":"Hings Chinese Cuisine",
    "wof:placetype":"venue"
},
  "geometry": {"coordinates":[-121.549604,38.579195],"type":"Point"}
}