{
  "type": "Feature",
  "properties": {
    "iso:country":"US",
    "sg:address":"5495 Carlson Dr",
    "sg:city":"Sacramento",
    "sg:classifiers":[
        {
            "category":"Arts & Performance",
            "subcategory":"Theater",
            "type":"Entertainment"
        }
    ],
    "sg:phone":"+1 916 451 3352",
    "sg:postcode":"95819",
    "sg:province":"CA",
    "sg:tags":[
        "live",
        "music"
    ],
    "wof:name":"Music To Grow",
    "wof:placetype":"venue"
},
  "geometry": {"coordinates":[-121.43230800000001,38.571604],"type":"Point"}
}