{
  "type": "Feature",
  "properties": {
    "iso:country":"US",
    "sg:address":"1525 Webster St",
    "sg:city":"Fairfield",
    "sg:classifiers":[
        {
            "category":"Health Services",
            "subcategory":"Doctor",
            "type":"Services"
        }
    ],
    "sg:phone":"+1 707 425 3937",
    "sg:postcode":"94533",
    "sg:province":"CA",
    "sg:tags":[
        "physician",
        "surgeon"
    ],
    "wof:name":"Richard Rothman MD",
    "wof:placetype":"venue"
},
  "geometry": {"coordinates":[-122.04599,38.25511],"type":"Point"}
}