{
  "type": "Feature",
  "properties": {
    "addr:full":"2456 Whipple Rd Hayward CA 94544",
    "addr:housenumber":"2456",
    "addr:postcode":"94544",
    "addr:street":"Whipple Rd",
    "iso:country":"US",
    "sg:address":"2456 Whipple Rd",
    "sg:city":"Hayward",
    "sg:classifiers":[
        {
            "category":"Autos & Motor Vehicles",
            "subcategory":"Automobile Sales",
            "type":"Retail Goods"
        }
    ],
    "sg:phone":"+1 510 401 5390",
    "sg:postcode":"94544",
    "sg:province":"CA",
    "sg:tags":[
        "truck"
    ],
    "wof:name":"Bay Area Kenworth Hayward",
    "wof:placetype":"venue"
},
  "geometry": {"coordinates":[-122.06004900000001,37.606176],"type":"Point"}
}