{
  "type": "Feature",
  "properties": {
    "addr:full":"16552 E. Tudor St Covina CA 91722",
    "addr:housenumber":"16552",
    "addr:postcode":"91722",
    "addr:street":"E. Tudor St",
    "iso:country":"US",
    "sg:address":"16552 E. Tudor St",
    "sg:city":"Covina",
    "sg:classifiers":[
        {
            "category":"Building & Trades",
            "subcategory":"Construction",
            "type":"Services"
        }
    ],
    "sg:phone":"+1 626 277 8355",
    "sg:postcode":"91722",
    "sg:province":"CA",
    "sg:tags":[
        "system",
        "contractor",
        "air conditioning"
    ],
    "wof:name":"Total Heat & Cool",
    "wof:placetype":"venue"
},
  "geometry": {"coordinates":[-117.923821,34.101952],"type":"Point"}
}