{
  "type": "Feature",
  "properties": {
    "iso:country":"US",
    "sg:address":"21912 Ventura Blvd",
    "sg:city":"Woodland Hills",
    "sg:classifiers":[
        {
            "category":"Personal",
            "subcategory":"Barber",
            "type":"Services"
        }
    ],
    "sg:phone":"+1 818 348 9224",
    "sg:postcode":"91364",
    "sg:province":"CA",
    "wof:name":"Cut Offs",
    "wof:placetype":"venue"
},
  "geometry": {"coordinates":[-118.603996,34.168598],"type":"Point"}
}