{
  "type": "Feature",
  "properties": {
    "addr:full":"8375 Dover Dr Granite Bay CA 95746",
    "addr:housenumber":"8375",
    "addr:postcode":"95746",
    "addr:street":"Dover Dr",
    "iso:country":"US",
    "sg:address":"8375 Dover Dr",
    "sg:city":"Granite Bay",
    "sg:classifiers":[
        {
            "category":"Manufacturing",
            "subcategory":"Toys & Sporting Goods",
            "type":"Manufacturing & Wholesale Goods"
        }
    ],
    "sg:phone":"+1 916 768 3047",
    "sg:postcode":"95746",
    "sg:province":"CA",
    "sg:tags":[
        "golf",
        "range",
        "electronic",
        "driving",
        "mfg"
    ],
    "wof:name":"Quinnco Enterprises",
    "wof:placetype":"venue"
},
  "geometry": {"coordinates":[-121.177767,38.747884],"type":"Point"}
}