{
  "type": "Feature",
  "properties": {
    "addr:full":"120 Meadowbrook Ct Vallejo CA 94591",
    "addr:housenumber":"120",
    "addr:postcode":"94591",
    "addr:street":"Meadowbrook Ct",
    "iso:country":"US",
    "sg:address":"120 Meadowbrook Ct",
    "sg:city":"Vallejo",
    "sg:classifiers":[
        {
            "category":"Building & Trades",
            "subcategory":"Construction",
            "type":"Services"
        }
    ],
    "sg:phone":"+1 707 645 1566",
    "sg:postcode":"94591",
    "sg:province":"CA",
    "sg:tags":[
        "builder",
        "deck"
    ],
    "wof:name":"Integral Enterprises Inc",
    "wof:placetype":"venue"
},
  "geometry": {"coordinates":[-122.20618399999999,38.103977],"type":"Point"}
}