{
  "type": "Feature",
  "properties": {
    "addr:full":"50 Alessandro Pl Ste 430 Pasadena CA 91105",
    "addr:housenumber":"50",
    "addr:postcode":"91105",
    "addr:street":"Alessandro Pl Ste 430",
    "iso:country":"US",
    "sg:address":"50 Alessandro Pl Ste 430",
    "sg:city":"Pasadena",
    "sg:classifiers":[
        {
            "category":"Health Services",
            "subcategory":"Doctor",
            "type":"Services"
        }
    ],
    "sg:phone":"+1 626 795 2226",
    "sg:postcode":"91105",
    "sg:province":"CA",
    "wof:name":"Edward Merchant, MD",
    "wof:placetype":"venue"
},
  "geometry": {"coordinates":[-118.151971,34.130624],"type":"Point"}
}