{
  "type": "Feature",
  "properties": {
    "iso:country":"US",
    "sg:address":"18800 Amar Rd Ste B11",
    "sg:city":"Walnut",
    "sg:classifiers":[
        {
            "category":"Shopping",
            "subcategory":"Antiques",
            "type":"Retail Goods"
        }
    ],
    "sg:phone":"+1 626 913 1661",
    "sg:postcode":"91789",
    "sg:province":"CA",
    "sg:tags":[
        "dealers-wholesale"
    ],
    "wof:name":"Kaonei International Incorporated",
    "wof:placetype":"venue"
},
  "geometry": {"coordinates":[-117.891808,34.028278],"type":"Point"}
}