{
  "type": "Feature",
  "properties": {
    "addr:full":"410 W Colton Ave Redlands CA 92374",
    "addr:housenumber":"410",
    "addr:postcode":"92374",
    "addr:street":"W Colton Ave",
    "iso:country":"US",
    "sg:address":"410 W Colton Ave",
    "sg:city":"Redlands",
    "sg:classifiers":[
        {
            "category":"Manufacturing",
            "subcategory":"Rubber & Plastics",
            "type":"Manufacturing & Wholesale Goods"
        },
        {
            "category":"Autos & Motor Vehicles",
            "subcategory":"Auto Supplies",
            "type":"Retail Goods"
        },
        {
            "category":"Retail",
            "subcategory":"Auto Repair",
            "type":"Services"
        }
    ],
    "sg:phone":"+1 909 747 0144",
    "sg:postcode":"92374",
    "sg:province":"CA",
    "sg:tags":[
        "tires-wholesale",
        "tire",
        "manufacturer"
    ],
    "sg:website":"http://www.americantiredepot.com",
    "wof:name":"American Tire Depot - Redlands",
    "wof:placetype":"venue"
},
  "geometry": {"coordinates":[-117.18698000000001,34.06284],"type":"Point"}
}