{
  "type": "Feature",
  "properties": {
    "addr:full":"1515 E 1st St Santa Ana CA 92701",
    "addr:housenumber":"1515",
    "addr:postcode":"92701",
    "addr:street":"E 1St St",
    "iso:country":"US",
    "sg:address":"1515 E 1st St",
    "sg:city":"Santa Ana",
    "sg:classifiers":[
        {
            "category":"Restaurant",
            "type":"Food & Drink"
        }
    ],
    "sg:phone":"+1 714 210 8924",
    "sg:postcode":"92701",
    "sg:province":"CA",
    "wof:name":"Premier Restaurant",
    "wof:placetype":"venue"
},
  "geometry": {"coordinates":[-117.848637,33.745517],"type":"Point"}
}