{
  "type": "Feature",
  "properties": {
    "addr:full":"20960 State Hwy 89 Markleeville CA 96120",
    "addr:housenumber":"20960",
    "addr:postcode":"96120",
    "addr:street":"State Hwy 89",
    "iso:country":"US",
    "sg:address":"20960 State Hwy 89",
    "sg:city":"Markleeville",
    "sg:classifiers":[
        {
            "category":"Travel",
            "subcategory":"Hotels & Motels",
            "type":"Entertainment"
        }
    ],
    "sg:phone":"+1 530 694 2410",
    "sg:postcode":"96120",
    "sg:province":"CA",
    "wof:name":"Woodfords Inn",
    "wof:placetype":"venue"
},
  "geometry": {"coordinates":[-119.81928600000001,38.773184],"type":"Point"}
}