{
  "type": "Feature",
  "properties": {
    "iso:country":"US",
    "sg:address":"100 E Huntington Dr",
    "sg:city":"Alhambra",
    "sg:classifiers":[
        {
            "category":"Wholesale",
            "subcategory":"Drugs",
            "type":"Manufacturing & Wholesale Goods"
        }
    ],
    "sg:phone":"+1 626 300 8077",
    "sg:postcode":"91801",
    "sg:province":"CA",
    "sg:tags":[
        "cosmetic"
    ],
    "wof:name":"Wamiles Cosmetics Intl",
    "wof:placetype":"venue"
},
  "geometry": {"coordinates":[-118.13334399999999,34.107631],"type":"Point"}
}