{
  "type": "Feature",
  "properties": {
    "iso:country":"US",
    "sg:address":"1100 Via Verde",
    "sg:city":"San Dimas",
    "sg:classifiers":[
        {
            "category":"Real Estate",
            "subcategory":"Real Estate Agent",
            "type":"Services"
        }
    ],
    "sg:phone":"+1 909 592 8500",
    "sg:postcode":"91773",
    "sg:province":"CA",
    "sg:website":"www.c21citrus.com",
    "wof:name":"Century 21",
    "wof:placetype":"venue"
},
  "geometry": {"coordinates":[-117.828763,34.07409],"type":"Point"}
}