{
  "type": "Feature",
  "properties": {
    "addr:full":"92 McDonald Ln Bayside CA 95524",
    "addr:housenumber":"92",
    "addr:postcode":"95524",
    "addr:street":"Mcdonald Ln",
    "iso:country":"US",
    "sg:address":"92 McDonald Ln",
    "sg:city":"Bayside",
    "sg:classifiers":[
        {
            "category":"Wholesale",
            "subcategory":"Fruits & Vegetables",
            "type":"Manufacturing & Wholesale Goods"
        }
    ],
    "sg:phone":"+1 707 445 1420",
    "sg:postcode":"95524",
    "sg:province":"CA",
    "wof:name":"Sierra Madre Mushrooms Inc",
    "wof:placetype":"venue"
},
  "geometry": {"coordinates":[-124.085595,40.816806],"type":"Point"}
}