{
  "type": "Feature",
  "properties": {
    "iso:country":"US",
    "sg:address":"3128 E Chapman Ave",
    "sg:city":"Orange",
    "sg:classifiers":[
        {
            "category":"Building & Trades",
            "subcategory":"Plumbing",
            "type":"Services"
        }
    ],
    "sg:phone":"+1 714 606 0518",
    "sg:postcode":"92869",
    "sg:province":"CA",
    "sg:tags":[
        "contractor"
    ],
    "wof:name":"Main Stream Mechanical",
    "wof:placetype":"venue"
},
  "geometry": {"coordinates":[-117.81590799999999,33.787703],"type":"Point"}
}