{
  "type": "Feature",
  "properties": {
    "addr:full":"430 Leoni Dr Grover Beach CA 93433",
    "addr:housenumber":"430",
    "addr:postcode":"93433",
    "addr:street":"Leoni Dr",
    "iso:country":"US",
    "sg:address":"430 Leoni Dr",
    "sg:city":"Grover Beach",
    "sg:classifiers":[
        {
            "category":"Professional",
            "subcategory":"Management & Consulting",
            "type":"Services"
        }
    ],
    "sg:phone":"+1 805 481 1774",
    "sg:postcode":"93433",
    "sg:province":"CA",
    "sg:tags":[
        "coffee",
        "brewing",
        "devices"
    ],
    "wof:name":"Mr Espresso Of Central Ca",
    "wof:placetype":"venue"
},
  "geometry": {"coordinates":[-120.623662,35.11323],"type":"Point"}
}