{
  "type": "Feature",
  "properties": {
    "iso:country":"US",
    "sg:address":"22629 Twain Harte Dr Ste B",
    "sg:city":"Twain Harte",
    "sg:classifiers":[
        {
            "category":"Retail",
            "subcategory":"Veterinary Services",
            "type":"Services"
        }
    ],
    "sg:phone":"+1 209 586 3232",
    "sg:postcode":"95383",
    "sg:province":"CA",
    "sg:tags":[
        "veterinarian"
    ],
    "sg:website":"www.twainhartevet.vetsuite.com",
    "wof:name":"Twain Harte Veterinary Hospital",
    "wof:placetype":"venue"
},
  "geometry": {"coordinates":[-120.232804,38.032643],"type":"Point"}
}