{
  "type": "Feature",
  "properties": {
    "addr:full":"102 Healdsburg Ave Healdsburg CA 95448",
    "addr:housenumber":"102",
    "addr:postcode":"95448",
    "addr:street":"Healdsburg Ave",
    "iso:country":"US",
    "sg:address":"102 Healdsburg Ave",
    "sg:city":"Healdsburg",
    "sg:classifiers":[
        {
            "category":"Restaurant",
            "type":"Food & Drink"
        }
    ],
    "sg:phone":"+1 707 433 2102",
    "sg:postcode":"95448",
    "sg:province":"CA",
    "wof:name":"Salvadoris",
    "wof:placetype":"venue"
},
  "geometry": {"coordinates":[-122.868607,38.605019],"type":"Point"}
}