{
  "type": "Feature",
  "properties": {
    "iso:country":"US",
    "sg:address":"9520 Gladbeck Ave",
    "sg:city":"Northridge",
    "sg:classifiers":[
        {
            "category":"Professional",
            "subcategory":"Management & Consulting",
            "type":"Services"
        }
    ],
    "sg:phone":"+1 818 341 9898",
    "sg:postcode":"91324",
    "sg:province":"CA",
    "sg:tags":[
        "consultant"
    ],
    "wof:name":"Concept Health Inc",
    "wof:placetype":"venue"
},
  "geometry": {"coordinates":[-118.53881199999999,34.243022],"type":"Point"}
}