{
  "type": "Feature",
  "properties": {
    "addr:full":"4633 Geary Blvd #161 San Francisco CA 94118",
    "addr:housenumber":"4633",
    "addr:postcode":"94118",
    "addr:street":"Geary Blvd # 161",
    "iso:country":"US",
    "sg:address":"4633 Geary Blvd #161",
    "sg:city":"San Francisco",
    "sg:classifiers":[
        {
            "category":"Building & Trades",
            "subcategory":"Construction",
            "type":"Services"
        }
    ],
    "sg:phone":"+1 415 420 3935",
    "sg:postcode":"94118",
    "sg:province":"CA",
    "sg:tags":[
        "contractor"
    ],
    "wof:name":"Argos Home Remodeling",
    "wof:placetype":"venue"
},
  "geometry": {"coordinates":[-122.469123,37.780709],"type":"Point"}
}