{
  "type": "Feature",
  "properties": {
    "addr:full":"493 Antelope Blvd Red Bluff CA 96080",
    "addr:housenumber":"493",
    "addr:postcode":"96080",
    "addr:street":"Antelope Blvd",
    "iso:country":"US",
    "sg:address":"493 Antelope Blvd",
    "sg:city":"Red Bluff",
    "sg:classifiers":[
        {
            "category":"Social Services",
            "type":"Services"
        }
    ],
    "sg:phone":"+1 530 529 1590",
    "sg:postcode":"96080",
    "sg:province":"CA",
    "sg:tags":[
        "organization",
        "welfare"
    ],
    "wof:name":"Salvation Army Thrift Store",
    "wof:placetype":"venue"
},
  "geometry": {"coordinates":[-122.20960700000001,40.18602],"type":"Point"}
}