{
  "type": "Feature",
  "properties": {
    "iso:country":"US",
    "sg:address":"560 Oxford Ave",
    "sg:city":"Palo Alto",
    "sg:classifiers":[
        {
            "category":"Real Estate",
            "subcategory":"Real Estate Agent",
            "type":"Services"
        }
    ],
    "sg:phone":"+1 650 856 2000",
    "sg:postcode":"94306",
    "sg:province":"CA",
    "wof:name":"Couch Properties",
    "wof:placetype":"venue"
},
  "geometry": {"coordinates":[-122.149444,37.425856],"type":"Point"}
}