{
  "type": "Feature",
  "properties": {
    "iso:country":"US",
    "sg:address":"112 N Main St",
    "sg:city":"Lake Elsinore",
    "sg:classifiers":[
        {
            "category":"Shopping",
            "subcategory":"Florist",
            "type":"Retail Goods"
        }
    ],
    "sg:phone":"+1 951 245 1950",
    "sg:postcode":"92530",
    "sg:province":"CA",
    "sg:website":"www.mainstreetflorist1.com",
    "wof:name":"Main Street Florist, Ice Cream & Fresh Fruit",
    "wof:placetype":"venue"
},
  "geometry": {"coordinates":[-117.327003,33.668701],"type":"Point"}
}