{
  "type": "Feature",
  "properties": {
    "addr:full":"3311 Grayhouse Ln Stockton CA 95206",
    "addr:housenumber":"3311",
    "addr:postcode":"95206",
    "addr:street":"Grayhouse Ln",
    "iso:country":"US",
    "sg:address":"3311 Grayhouse Ln",
    "sg:city":"Stockton",
    "sg:classifiers":[
        {
            "category":"Retail",
            "subcategory":"Laundry & Dry Cleaning",
            "type":"Services"
        }
    ],
    "sg:phone":"+1 209 983 1731",
    "sg:postcode":"95206",
    "sg:province":"CA",
    "sg:tags":[
        "cleaners",
        "rug",
        "carpet"
    ],
    "wof:name":"Fantastic Cleaning",
    "wof:placetype":"venue"
},
  "geometry": {"coordinates":[-121.30625000000001,37.913251],"type":"Point"}
}