{
  "type": "Feature",
  "properties": {
    "iso:country":"US",
    "sg:address":"5 Spring Ln",
    "sg:city":"Fairfield",
    "sg:classifiers":[
        {
            "category":"Communications",
            "type":"Services"
        }
    ],
    "sg:phone":"+1 707 580 0264",
    "sg:postcode":"94534",
    "sg:province":"CA",
    "sg:tags":[
        "consultant",
        "telecommunication"
    ],
    "wof:name":"Peters Underground Construction",
    "wof:placetype":"venue"
},
  "geometry": {"coordinates":[-122.146423,38.252781],"type":"Point"}
}