{
  "type": "Feature",
  "properties": {
    "iso:country":"US",
    "sg:address":"4975 Sandshore Ct",
    "sg:city":"San Diego",
    "sg:classifiers":[
        {
            "category":"Manufacturing",
            "subcategory":"Glass & Minerals",
            "type":"Manufacturing & Wholesale Goods"
        }
    ],
    "sg:phone":"+1 619 517 3124",
    "sg:postcode":"92130",
    "sg:province":"CA",
    "sg:tags":[
        "ready",
        "concrete",
        "mfg"
    ],
    "wof:name":"Ready Money Cash Advance",
    "wof:placetype":"venue"
},
  "geometry": {"coordinates":[-117.209285,32.948451],"type":"Point"}
}