{
  "type": "Feature",
  "properties": {
    "addr:full":"128 E 10th Ave Escondido CA 92025",
    "addr:housenumber":"128",
    "addr:postcode":"92025",
    "addr:street":"E 10Th Ave",
    "iso:country":"US",
    "sg:address":"128 E 10th Ave",
    "sg:city":"Escondido",
    "sg:classifiers":[
        {
            "category":"Building & Trades",
            "subcategory":"Landscaping Services",
            "type":"Services"
        }
    ],
    "sg:phone":"+1 760 746 8660",
    "sg:postcode":"92025",
    "sg:province":"CA",
    "wof:name":"Eddies Landscape Service",
    "wof:placetype":"venue"
},
  "geometry": {"coordinates":[-117.073373,33.114794],"type":"Point"}
}