{
  "type": "Feature",
  "properties": {
    "iso:country":"US",
    "sg:address":"331 Longridge Dr",
    "sg:city":"Vallejo",
    "sg:classifiers":[
        {
            "category":"Building & Trades",
            "subcategory":"Construction",
            "type":"Services"
        }
    ],
    "sg:phone":"+1 707 649 2652",
    "sg:postcode":"94591",
    "sg:province":"CA",
    "sg:tags":[
        "paving",
        "contractor"
    ],
    "wof:name":"R G Carter Co",
    "wof:placetype":"venue"
},
  "geometry": {"coordinates":[-122.204172,38.091355],"type":"Point"}
}