{
  "type": "Feature",
  "properties": {
    "iso:country":"US",
    "sg:address":"17 S San Joaquin St",
    "sg:city":"Stockton",
    "sg:classifiers":[
        {
            "category":"Travel",
            "subcategory":"Travel Agent",
            "type":"Entertainment"
        }
    ],
    "sg:phone":"+1 209 952 6544",
    "sg:postcode":"95202",
    "sg:province":"CA",
    "sg:tags":[
        "agency"
    ],
    "wof:name":"Above & Beyond Travel",
    "wof:placetype":"venue"
},
  "geometry": {"coordinates":[-121.28701700000001,37.952306],"type":"Point"}
}