{
  "type": "Feature",
  "properties": {
    "addr:full":"2420 W Clemenceau Ave Caruthers CA 93609",
    "addr:housenumber":"2420",
    "addr:postcode":"93609",
    "addr:street":"W Clemenceau Ave",
    "iso:country":"US",
    "sg:address":"2420 W Clemenceau Ave",
    "sg:city":"Caruthers",
    "sg:classifiers":[
        {
            "category":"Social Services",
            "subcategory":"Child Care",
            "type":"Services"
        }
    ],
    "sg:phone":"+1 559 864 0322",
    "sg:postcode":"93609",
    "sg:province":"CA",
    "sg:tags":[
        "start",
        "head"
    ],
    "wof:name":"Economic Opportunities Comm",
    "wof:placetype":"venue"
},
  "geometry": {"coordinates":[-119.828391,36.536408],"type":"Point"}
}