{
  "type": "Feature",
  "properties": {
    "iso:country":"US",
    "sg:address":"27000 Crown Valley Pky",
    "sg:city":"Mission Viejo",
    "sg:classifiers":[
        {
            "category":"Restaurant",
            "type":"Food & Drink"
        }
    ],
    "sg:menulink":"http://www.allmenus.com/ca/trabuco/239944-panda-express/menu/",
    "sg:phone":"+1 949 364 6982",
    "sg:postcode":"92691",
    "sg:province":"CA",
    "sg:tags":[
        "asian",
        "chinese"
    ],
    "wof:name":"Panda Express",
    "wof:placetype":"venue"
},
  "geometry": {"coordinates":[-117.667689,33.559703],"type":"Point"}
}