{
  "type": "Feature",
  "properties": {
    "addr:full":"1108 S Diamond Bar Blvd Diamond Bar CA 91765",
    "addr:housenumber":"1108",
    "addr:postcode":"91765",
    "addr:street":"S;Blvd",
    "iso:country":"US",
    "sg:address":"1108 S Diamond Bar Blvd",
    "sg:city":"Diamond Bar",
    "sg:classifiers":[
        {
            "category":"Health Services",
            "subcategory":"Doctor",
            "type":"Services"
        }
    ],
    "sg:phone":"+1 909 861 4444",
    "sg:postcode":"91765",
    "sg:province":"CA",
    "sg:tags":[
        "dentist"
    ],
    "wof:name":"Dr Lee Dentistry",
    "wof:placetype":"venue"
},
  "geometry": {"coordinates":[-117.810197,34.002264],"type":"Point"}
}