{
  "type": "Feature",
  "properties": {
    "iso:country":"US",
    "sg:address":"35 N Lake Ave",
    "sg:city":"Pasadena",
    "sg:classifiers":[
        {
            "category":"Banks & Credit Unions",
            "subcategory":"Bank",
            "type":"Services"
        }
    ],
    "sg:phone":"+1 626 584 0576",
    "sg:postcode":"91101",
    "sg:province":"CA",
    "sg:tags":[
        "company",
        "trust"
    ],
    "wof:name":"Associated Third Party Adms",
    "wof:placetype":"venue"
},
  "geometry": {"coordinates":[-118.132441,34.147088],"type":"Point"}
}