{
  "type": "Feature",
  "properties": {
    "addr:full":"2865 Atlantic Ave Long Beach CA 90806",
    "addr:housenumber":"2865",
    "addr:postcode":"90806",
    "addr:street":"Atlantic Ave",
    "iso:country":"US",
    "sg:address":"2865 Atlantic Ave",
    "sg:city":"Long Beach",
    "sg:classifiers":[
        {
            "category":"Health Services",
            "subcategory":"Doctor",
            "type":"Services"
        }
    ],
    "sg:phone":"+1 562 424 0421",
    "sg:postcode":"90806",
    "sg:province":"CA",
    "sg:website":"www.assocgensurg.com",
    "wof:name":"Grant Steven W MD",
    "wof:placetype":"venue"
},
  "geometry": {"coordinates":[-118.18499799999999,33.809101],"type":"Point"}
}