{
  "type": "Feature",
  "properties": {
    "iso:country":"US",
    "sg:address":"6051 Telegraph Rd",
    "sg:city":"Commerce",
    "sg:classifiers":[
        {
            "category":"Shopping",
            "subcategory":"Discount & Variety Stores",
            "type":"Retail Goods"
        }
    ],
    "sg:phone":"+1 323 837 0025",
    "sg:postcode":"90040",
    "sg:province":"CA",
    "sg:tags":[
        "outlet"
    ],
    "sg:website":"www.kitchenplus.com",
    "wof:name":"Kitchen Plus Inc",
    "wof:placetype":"venue"
},
  "geometry": {"coordinates":[-118.14715099999999,33.999165],"type":"Point"}
}