{
  "type": "Feature",
  "properties": {
    "iso:country":"US",
    "sg:address":"6435 Sandstone Street",
    "sg:city":"Carmichael",
    "sg:classifiers":[
        {
            "category":"Building & Trades",
            "subcategory":"Construction",
            "type":"Services"
        }
    ],
    "sg:phone":"+1 916 965 3030",
    "sg:postcode":"95608",
    "sg:province":"CA",
    "sg:tags":[
        "interior",
        "design"
    ],
    "wof:name":"Designs Unlimited",
    "wof:placetype":"venue"
},
  "geometry": {"coordinates":[-121.314187,38.65989],"type":"Point"}
}