{
  "type": "Feature",
  "properties": {
    "iso:country":"US",
    "sg:address":"3345 M St",
    "sg:city":"Merced",
    "sg:classifiers":[
        {
            "category":"Social Services",
            "type":"Services"
        }
    ],
    "sg:phone":"+1 209 381 6860",
    "sg:postcode":"95348",
    "sg:province":"CA",
    "wof:name":"Mental Health Dept",
    "wof:placetype":"venue"
},
  "geometry": {"coordinates":[-120.478435,37.323129],"type":"Point"}
}