{
  "type": "Feature",
  "properties": {
    "addr:full":"12155 Magnolia Ave Riverside CA 92503",
    "addr:housenumber":"12155",
    "addr:postcode":"92503",
    "addr:street":"Magnolia Ave",
    "iso:country":"US",
    "sg:address":"12155 Magnolia Ave",
    "sg:city":"Riverside",
    "sg:classifiers":[
        {
            "category":"Freight",
            "type":"Transportation"
        }
    ],
    "sg:phone":"+1 909 687 0951",
    "sg:postcode":"92503",
    "sg:province":"CA",
    "sg:tags":[
        "operator",
        "mover",
        "trucking"
    ],
    "wof:name":"V I P Transport Inc",
    "wof:placetype":"venue"
},
  "geometry": {"coordinates":[-117.494562,33.893559],"type":"Point"}
}