{
  "type": "Feature",
  "properties": {
    "iso:country":"US",
    "sg:address":"17490 Monterey St",
    "sg:city":"Morgan Hill",
    "sg:classifiers":[
        {
            "category":"Shopping",
            "subcategory":"Jewelry",
            "type":"Retail Goods"
        }
    ],
    "sg:phone":"+1 408 779 2089",
    "sg:postcode":"95037",
    "sg:province":"CA",
    "sg:tags":[
        "jeweler"
    ],
    "wof:name":"Goddess Bead Shop",
    "wof:placetype":"venue"
},
  "geometry": {"coordinates":[-121.653221,37.128875],"type":"Point"}
}