{
  "type": "Feature",
  "properties": {
    "iso:country":"US",
    "sg:address":"6404 Hollywood Blvd Ste 220",
    "sg:city":"Los Angeles",
    "sg:classifiers":[
        {
            "category":"Communications",
            "type":"Services"
        }
    ],
    "sg:phone":"+1 323 472 8600",
    "sg:postcode":"90028",
    "sg:province":"CA",
    "sg:tags":[
        "web",
        "design"
    ],
    "wof:name":"Starmen",
    "wof:placetype":"venue"
},
  "geometry": {"coordinates":[-118.3296,34.101472],"type":"Point"}
}