{
  "type": "Feature",
  "properties": {
    "addr:full":"327 E Valley Blvd San Gabriel CA 91776",
    "addr:housenumber":"327",
    "addr:postcode":"91776",
    "addr:street":"E Valley Blvd",
    "iso:country":"US",
    "sg:address":"327 E Valley Blvd",
    "sg:city":"San Gabriel",
    "sg:classifiers":[
        {
            "category":"Shopping",
            "subcategory":"Gifts & Souvenirs",
            "type":"Retail Goods"
        }
    ],
    "sg:phone":"+1 626 571 1800",
    "sg:postcode":"91776",
    "sg:province":"CA",
    "sg:tags":[
        "shop"
    ],
    "wof:name":"Stone Age Collection",
    "wof:placetype":"venue"
},
  "geometry": {"coordinates":[-118.096979,34.079856],"type":"Point"}
}