{
  "type": "Feature",
  "properties": {
    "iso:country":"US",
    "sg:address":"2273 Goldcrest Cir",
    "sg:city":"Pleasanton",
    "sg:classifiers":[
        {
            "category":"Professional",
            "subcategory":"Advertising",
            "type":"Services"
        }
    ],
    "sg:phone":"+1 925 600 1248",
    "sg:postcode":"94566",
    "sg:province":"CA",
    "sg:tags":[
        "promotion",
        "sale"
    ],
    "wof:name":"Tina Fujihira",
    "wof:placetype":"venue"
},
  "geometry": {"coordinates":[-121.89218200000001,37.67514],"type":"Point"}
}