{
  "type": "Feature",
  "properties": {
    "iso:country":"US",
    "sg:address":"1247 Harrison St",
    "sg:city":"San Francisco",
    "sg:classifiers":[
        {
            "category":"Arts & Performance",
            "subcategory":"Comedy Club",
            "type":"Entertainment"
        }
    ],
    "sg:phone":"+1 415 503 0016",
    "sg:postcode":"94103",
    "sg:province":"CA",
    "wof:name":"Cantrell Harris & Associates",
    "wof:placetype":"venue"
},
  "geometry": {"coordinates":[-122.40906699999999,37.773188],"type":"Point"}
}