{
  "type": "Feature",
  "properties": {
    "iso:country":"US",
    "sg:address":"50 W San Fernando St",
    "sg:city":"San Jose",
    "sg:classifiers":[
        {
            "category":"Banks & Credit Unions",
            "subcategory":"Financial Services",
            "type":"Services"
        }
    ],
    "sg:phone":"+1 408 318 6305",
    "sg:postcode":"95113",
    "sg:province":"CA",
    "sg:tags":[
        "broker",
        "mortgage"
    ],
    "wof:name":"Ace Mortgage Funding ilc",
    "wof:placetype":"venue"
},
  "geometry": {"coordinates":[-121.889833,37.33385],"type":"Point"}
}