{
  "type": "Feature",
  "properties": {
    "addr:full":"2200 Panama Ln Bakersfield CA 93307",
    "addr:housenumber":"2200",
    "addr:postcode":"93307",
    "addr:street":"Panama Ln",
    "iso:country":"US",
    "sg:address":"2200 Panama Ln",
    "sg:city":"Bakersfield",
    "sg:classifiers":[
        {
            "category":"Coffee & Tea",
            "type":"Food & Drink"
        }
    ],
    "sg:menulink":"http://www.allmenus.com/ca/greenfield-panama/117351-starbucks-coffee/menu/",
    "sg:phone":"+1 661 396 0579",
    "sg:postcode":"93307",
    "sg:province":"CA",
    "sg:tags":[
        "american"
    ],
    "wof:name":"Starbucks Coffee",
    "wof:placetype":"venue"
},
  "geometry": {"coordinates":[-119.02607500000001,35.295861],"type":"Point"}
}