{
  "type": "Feature",
  "properties": {
    "addr:full":"2705 W Mission Ct Visalia CA 93277",
    "addr:housenumber":"2705",
    "addr:postcode":"93277",
    "addr:street":"W Mission Ct",
    "iso:country":"US",
    "sg:address":"2705 W Mission Ct",
    "sg:city":"Visalia",
    "sg:classifiers":[
        {
            "category":"Building & Trades",
            "subcategory":"Landscaping Services",
            "type":"Services"
        }
    ],
    "sg:phone":"+1 559 627 4401",
    "sg:postcode":"93277",
    "sg:province":"CA",
    "wof:name":"Brians Lawn Maintenance",
    "wof:placetype":"venue"
},
  "geometry": {"coordinates":[-119.32256,36.299164],"type":"Point"}
}