{
  "type": "Feature",
  "properties": {
    "iso:country":"US",
    "sg:address":"8801 Research Dr",
    "sg:city":"Irvine",
    "sg:classifiers":[
        {
            "category":"Real Estate",
            "subcategory":"Developer",
            "type":"Services"
        }
    ],
    "sg:phone":"+1 949 729 2211",
    "sg:postcode":"92618",
    "sg:province":"CA",
    "wof:name":"Bacchus Development Co",
    "wof:placetype":"venue"
},
  "geometry": {"coordinates":[-117.73685500000001,33.640485],"type":"Point"}
}