{
  "type": "Feature",
  "properties": {
    "iso:country":"US",
    "sg:address":"24201 Valencia Blvd",
    "sg:city":"Valencia",
    "sg:classifiers":[
        {
            "category":"Shopping",
            "subcategory":"Baby Store",
            "type":"Retail Goods"
        }
    ],
    "sg:phone":"+1 661 255 7332",
    "sg:postcode":"91355",
    "sg:province":"CA",
    "sg:tags":[
        "children's",
        "infant",
        "wear"
    ],
    "wof:name":"Crazy 8",
    "wof:placetype":"venue"
},
  "geometry": {"coordinates":[-118.557388,34.413212],"type":"Point"}
}