{
  "type": "Feature",
  "properties": {
    "iso:country":"US",
    "sg:address":"201 Torrance Blvd",
    "sg:city":"Redondo Beach",
    "sg:classifiers":[
        {
            "category":"Food & Beverages",
            "subcategory":"Liquor & Beverages",
            "type":"Retail Goods"
        }
    ],
    "sg:phone":"+1 310 374 9768",
    "sg:postcode":"90277",
    "sg:province":"CA",
    "sg:tags":[
        "wine"
    ],
    "sg:website":"www.giftsofwine.com",
    "wof:name":"Connoisseur Inc",
    "wof:placetype":"venue"
},
  "geometry": {"coordinates":[-118.385413,33.838241],"type":"Point"}
}