{
  "type": "Feature",
  "properties": {
    "iso:country":"US",
    "sg:address":"218 N Lincoln Ave",
    "sg:city":"Corona",
    "sg:classifiers":[
        {
            "category":"Professional",
            "subcategory":"Accounting & Tax Preparation",
            "type":"Services"
        }
    ],
    "sg:phone":"+1 951 278 8780",
    "sg:postcode":"92882",
    "sg:province":"CA",
    "sg:tags":[
        "return",
        "filing"
    ],
    "wof:name":"Gabe Domenici Tax & Business",
    "wof:placetype":"venue"
},
  "geometry": {"coordinates":[-117.581717,33.887056],"type":"Point"}
}