{
  "type": "Feature",
  "properties": {
    "iso:country":"US",
    "sg:address":"1991 E Ventura Blvd",
    "sg:city":"Oxnard",
    "sg:classifiers":[
        {
            "category":"Shopping",
            "subcategory":"Clothing, Apparel, & Fashions",
            "type":"Retail Goods"
        }
    ],
    "sg:phone":"+1 805 485 1230",
    "sg:postcode":"93036",
    "sg:province":"CA",
    "sg:tags":[
        "furnishing"
    ],
    "wof:name":"Men's Wearhouse",
    "wof:placetype":"venue"
},
  "geometry": {"coordinates":[-119.160788,34.226022],"type":"Point"}
}