{
  "type": "Feature",
  "properties": {
    "iso:country":"US",
    "sg:address":"9840 Indiana Ave",
    "sg:city":"Riverside",
    "sg:classifiers":[
        {
            "category":"Professional",
            "subcategory":"Business Services",
            "type":"Services"
        },
        {
            "category":"Shopping",
            "subcategory":"Clothing, Apparel, & Fashions",
            "type":"Retail Goods"
        }
    ],
    "sg:phone":"+1 951 688 6710",
    "sg:postcode":"92503",
    "sg:province":"CA",
    "sg:tags":[
        "embroidery"
    ],
    "wof:name":"J L Custom Jackets",
    "wof:placetype":"venue"
},
  "geometry": {"coordinates":[-117.44647399999999,33.911352],"type":"Point"}
}