{
  "type": "Feature",
  "properties": {
    "iso:country":"US",
    "sg:address":"5333 Hollister Ave",
    "sg:city":"Santa Barbara",
    "sg:classifiers":[
        {
            "category":"Health Services",
            "subcategory":"Doctor",
            "type":"Services"
        }
    ],
    "sg:phone":"+1 805 964 6926",
    "sg:postcode":"93111",
    "sg:province":"CA",
    "sg:tags":[
        "physician",
        "surgeon"
    ],
    "wof:name":"John D Mc Caffery MD",
    "wof:placetype":"venue"
},
  "geometry": {"coordinates":[-119.810633,34.434993],"type":"Point"}
}