{
  "type": "Feature",
  "properties": {
    "addr:full":"909 E 49th St Los Angeles CA 90011",
    "addr:housenumber":"909",
    "addr:postcode":"90011",
    "addr:street":"E 49Th St",
    "iso:country":"US",
    "sg:address":"909 E 49th St",
    "sg:city":"Los Angeles",
    "sg:classifiers":[
        {
            "category":"Organizations",
            "subcategory":"Religious Organization",
            "type":"Services"
        }
    ],
    "sg:phone":"+1 323 234 5770",
    "sg:postcode":"90011",
    "sg:province":"CA",
    "sg:tags":[
        "church"
    ],
    "wof:name":"Descending Like Dove Minstry",
    "wof:placetype":"venue"
},
  "geometry": {"coordinates":[-118.259725,33.99935],"type":"Point"}
}