{
  "type": "Feature",
  "properties": {
    "iso:country":"US",
    "sg:address":"1400 E Anaheim St",
    "sg:city":"Long Beach",
    "sg:classifiers":[
        {
            "category":"Retail",
            "subcategory":"Auto Repair",
            "type":"Services"
        }
    ],
    "sg:phone":"+1 562 591 0412",
    "sg:postcode":"90813",
    "sg:province":"CA",
    "sg:tags":[
        "automotive",
        "exhaust"
    ],
    "wof:name":"Techs Tire Brake Muffler & Au",
    "wof:placetype":"venue"
},
  "geometry": {"coordinates":[-118.17361099999999,33.782609],"type":"Point"}
}