{
  "type": "Feature",
  "properties": {
    "addr:full":"595 E Hospitality Ln San Bernardino CA 92408",
    "addr:housenumber":"595",
    "addr:postcode":"92408",
    "addr:street":"E Hospitality Ln",
    "iso:country":"US",
    "sg:address":"595 E Hospitality Ln",
    "sg:city":"San Bernardino",
    "sg:classifiers":[
        {
            "category":"Retail",
            "subcategory":"Veterinary Services",
            "type":"Services"
        }
    ],
    "sg:phone":"+1 909 890 9949",
    "sg:postcode":"92408",
    "sg:province":"CA",
    "sg:tags":[
        "hospital",
        "animal"
    ],
    "wof:name":"Banfield The Pet Hospital",
    "wof:placetype":"venue"
},
  "geometry": {"coordinates":[-117.272442,34.065777],"type":"Point"}
}