{
  "type": "Feature",
  "properties": {
    "addr:full":"5029 Calmview Ave Baldwin Park CA 91706",
    "addr:housenumber":"5029",
    "addr:postcode":"91706",
    "addr:street":"Calmview Ave",
    "iso:country":"US",
    "sg:address":"5029 Calmview Ave",
    "sg:city":"Baldwin Park",
    "sg:classifiers":[
        {
            "category":"Wholesale",
            "subcategory":"Machinery & Supplies",
            "type":"Manufacturing & Wholesale Goods"
        }
    ],
    "sg:phone":"+1 626 337 9782",
    "sg:postcode":"91706",
    "sg:province":"CA",
    "sg:tags":[
        "equipment",
        "ride",
        "park",
        "amusement"
    ],
    "wof:name":"P & L Video Games",
    "wof:placetype":"venue"
},
  "geometry": {"coordinates":[-117.947993,34.106179],"type":"Point"}
}