{
  "type": "Feature",
  "properties": {
    "iso:country":"US",
    "sg:address":"300 Ferry St",
    "sg:city":"Martinez",
    "sg:classifiers":[
        {
            "category":"Government",
            "subcategory":"Police Station",
            "type":"Public Place"
        }
    ],
    "sg:phone":"+1 310 514 6030",
    "sg:postcode":"94553",
    "sg:province":"CA",
    "sg:tags":[
        "enforcement",
        "law",
        "agencies-government"
    ],
    "wof:name":"Bureau Of Customs And Border Protection",
    "wof:placetype":"venue"
},
  "geometry": {"coordinates":[-122.140213,38.020481],"type":"Point"}
}