{
  "type": "Feature",
  "properties": {
    "iso:country":"US",
    "sg:address":"1571 S Sunkist St",
    "sg:city":"Anaheim",
    "sg:classifiers":[
        {
            "category":"Wholesale",
            "subcategory":"Home Furnishings",
            "type":"Manufacturing & Wholesale Goods"
        }
    ],
    "sg:phone":"+1 714 978 1275",
    "sg:postcode":"92806",
    "sg:province":"CA",
    "sg:tags":[
        "flooring",
        "covering"
    ],
    "wof:name":"Trinity Group",
    "wof:placetype":"venue"
},
  "geometry": {"coordinates":[-117.883318,33.810229],"type":"Point"}
}