{
  "type": "Feature",
  "properties": {
    "addr:full":"402 E Acacia Ave Glendale CA 91205",
    "addr:housenumber":"402",
    "addr:postcode":"91205",
    "addr:street":"E Acacia Ave",
    "iso:country":"US",
    "sg:address":"402 E Acacia Ave",
    "sg:city":"Glendale",
    "sg:classifiers":[
        {
            "category":"Food & Beverages",
            "subcategory":"Groceries & Convenience Stores",
            "type":"Retail Goods"
        }
    ],
    "sg:phone":"+1 818 240 5066",
    "sg:postcode":"91205",
    "sg:province":"CA",
    "wof:name":"Anush Clothing",
    "wof:placetype":"venue"
},
  "geometry": {"coordinates":[-118.251621,34.134762],"type":"Point"}
}