{
  "type": "Feature",
  "properties": {
    "iso:country":"US",
    "sg:address":"4221 Wilshire Boulevard",
    "sg:city":"Los Angeles",
    "sg:classifiers":[
        {
            "category":"Landmark",
            "subcategory":"Tourist Information",
            "type":"Public Place"
        }
    ],
    "sg:phone":"+1 323 937 8900",
    "sg:postcode":"90010",
    "sg:province":"CA",
    "sg:tags":[
        "tour"
    ],
    "wof:name":"Green World Tour",
    "wof:placetype":"venue"
},
  "geometry": {"coordinates":[-118.320256,34.061775],"type":"Point"}
}