{
  "type": "Feature",
  "properties": {
    "iso:country":"US",
    "sg:address":"1440 Padres Dr",
    "sg:city":"San Jose",
    "sg:classifiers":[
        {
            "category":"Professional",
            "subcategory":"Computer Services",
            "type":"Services"
        }
    ],
    "sg:phone":"+1 408 289 8234",
    "sg:postcode":"95125",
    "sg:province":"CA",
    "sg:tags":[
        "programing",
        "custom"
    ],
    "wof:name":"Objects By Design",
    "wof:placetype":"venue"
},
  "geometry": {"coordinates":[-121.888176,37.306864],"type":"Point"}
}