{
  "type": "Feature",
  "properties": {
    "iso:country":"US",
    "sg:address":"250 Newport Center Dr Ste 102",
    "sg:city":"Newport Beach",
    "sg:classifiers":[
        {
            "category":"Health Services",
            "subcategory":"Health Practitioner",
            "type":"Services"
        },
        {
            "category":"Health Services",
            "subcategory":"Chiropractor",
            "type":"Services"
        }
    ],
    "sg:phone":"+1 949 760 5437",
    "sg:postcode":"92660",
    "sg:province":"CA",
    "sg:tags":[
        "acupuncture",
        "nutritionist"
    ],
    "wof:name":"Angell Chiropractic And Wellness Center",
    "wof:placetype":"venue"
},
  "geometry": {"coordinates":[-117.87361,33.611035],"type":"Point"}
}