{
  "type": "Feature",
  "properties": {
    "iso:country":"US",
    "sg:address":"2400 E Ponderosa Dr",
    "sg:city":"Camarillo",
    "sg:classifiers":[
        {
            "category":"Banks & Credit Unions",
            "subcategory":"Bank",
            "type":"Services"
        },
        {
            "category":"Banks & Credit Unions",
            "subcategory":"Financial Services",
            "type":"Services"
        }
    ],
    "sg:phone":"+1 805 650 2280",
    "sg:postcode":"93010",
    "sg:province":"CA",
    "sg:tags":[
        "broker",
        "mortgage"
    ],
    "wof:name":"Bank of America",
    "wof:placetype":"venue"
},
  "geometry": {"coordinates":[-119.029999,34.230202],"type":"Point"}
}