{
  "type": "Feature",
  "properties": {
    "iso:country":"US",
    "sg:address":"3935 Harney St",
    "sg:city":"San Diego",
    "sg:classifiers":[
        {
            "category":"Building & Trades",
            "subcategory":"Construction",
            "type":"Services"
        },
        {
            "category":"Wholesale",
            "subcategory":"Metals & Minerals",
            "type":"Manufacturing & Wholesale Goods"
        }
    ],
    "sg:phone":"+1 619 298 0620",
    "sg:postcode":"92110",
    "sg:province":"CA",
    "sg:tags":[
        "concrete",
        "special",
        "reinforcement",
        "contractor"
    ],
    "wof:name":"Jem III",
    "wof:placetype":"venue"
},
  "geometry": {"coordinates":[-117.195956,32.751373],"type":"Point"}
}