{
  "type": "Feature",
  "properties": {
    "iso:country":"US",
    "sg:address":"2800 W Olympic Blvd #B",
    "sg:city":"Los Angeles",
    "sg:classifiers":[
        {
            "category":"Shopping",
            "subcategory":"Florist",
            "type":"Retail Goods"
        }
    ],
    "sg:phone":"+1 213 480 3102",
    "sg:postcode":"90006",
    "sg:province":"CA",
    "sg:website":"www.olympictownflowers.com",
    "wof:name":"Olympic Town Flowers",
    "wof:placetype":"venue"
},
  "geometry": {"coordinates":[-118.295108,34.05226],"type":"Point"}
}