{
  "type": "Feature",
  "properties": {
    "addr:full":"2550 Kerner Blvd San Rafael CA 94901",
    "addr:postcode":"2550;94901",
    "addr:street":"Kerner Blvd",
    "iso:country":"US",
    "sg:address":"2550 Kerner Blvd",
    "sg:city":"San Rafael",
    "sg:classifiers":[
        {
            "category":"Wholesale",
            "subcategory":"Sporting Goods",
            "type":"Manufacturing & Wholesale Goods"
        }
    ],
    "sg:phone":"+1 415 256 2410",
    "sg:postcode":"94901",
    "sg:province":"CA",
    "sg:tags":[
        "bicycle"
    ],
    "wof:name":"Dynacraft Industry",
    "wof:placetype":"venue"
},
  "geometry": {"coordinates":[-122.49286600000001,37.950645],"type":"Point"}
}