{
  "type": "Feature",
  "properties": {
    "addr:full":"6310 San Vicente Blvd Ste 402 Los Angeles CA 90048",
    "addr:housenumber":"6310",
    "addr:postcode":"90048",
    "addr:street":"San Vicente Blvd Ste 402",
    "iso:country":"US",
    "sg:address":"6310 San Vicente Blvd Ste 402",
    "sg:city":"Los Angeles",
    "sg:classifiers":[
        {
            "category":"Arts & Performance",
            "subcategory":"Music",
            "type":"Entertainment"
        }
    ],
    "sg:phone":"+1 323 632 2354",
    "sg:postcode":"90048",
    "sg:province":"CA",
    "sg:tags":[
        "therapist",
        "speech"
    ],
    "sg:website":"www.languageladder.com",
    "wof:name":"Language Ladder",
    "wof:placetype":"venue"
},
  "geometry": {"coordinates":[-118.367693,34.060523],"type":"Point"}
}