{
  "type": "Feature",
  "properties": {
    "iso:country":"US",
    "sg:address":"7340 French Rd",
    "sg:city":"Sacramento",
    "sg:classifiers":[
        {
            "category":"Manufacturing",
            "subcategory":"Wood Products",
            "type":"Manufacturing & Wholesale Goods"
        }
    ],
    "sg:phone":"+1 916 387 0983",
    "sg:postcode":"95828",
    "sg:province":"CA",
    "sg:tags":[
        "reconstituted",
        "mfg"
    ],
    "sg:website":"www.sierrapine.com",
    "wof:name":"Sierra Pine Moulding",
    "wof:placetype":"venue"
},
  "geometry": {"coordinates":[-121.390516,38.490852],"type":"Point"}
}