{
  "type": "Feature",
  "properties": {
    "iso:country":"US",
    "sg:address":"6200 S San Pedro Street",
    "sg:city":"Los Angeles",
    "sg:classifiers":[
        {
            "category":"Food & Beverages",
            "subcategory":"Groceries & Convenience Stores",
            "type":"Retail Goods"
        }
    ],
    "sg:phone":"+1 323 232 2555",
    "sg:postcode":"90003",
    "sg:province":"CA",
    "wof:name":"Royalty Market",
    "wof:placetype":"venue"
},
  "geometry": {"coordinates":[-118.269691,33.983154],"type":"Point"}
}