{
  "type": "Feature",
  "properties": {
    "addr:full":"9116 Painter Ave Whittier CA 90602",
    "addr:housenumber":"9116",
    "addr:postcode":"90602",
    "addr:street":"Painter Ave",
    "iso:country":"US",
    "sg:address":"9116 Painter Ave",
    "sg:city":"Whittier",
    "sg:classifiers":[
        {
            "category":"Manufacturing",
            "subcategory":"Electronics",
            "type":"Manufacturing & Wholesale Goods"
        }
    ],
    "sg:phone":"+1 562 945 9140",
    "sg:postcode":"90602",
    "sg:province":"CA",
    "sg:tags":[
        "equipment",
        "mfg",
        "home"
    ],
    "wof:name":"USA Teck",
    "wof:placetype":"venue"
},
  "geometry": {"coordinates":[-118.041909,33.954054],"type":"Point"}
}