{
  "type": "Feature",
  "properties": {
    "iso:country":"US",
    "sg:address":"4715 E Dakota Ave",
    "sg:city":"Fresno",
    "sg:classifiers":[
        {
            "category":"Freight",
            "type":"Transportation"
        }
    ],
    "sg:phone":"+1 559 276 1188",
    "sg:postcode":"93726",
    "sg:province":"CA",
    "sg:tags":[
        "trucking"
    ],
    "wof:name":"Robert Aguiar Trucking",
    "wof:placetype":"venue"
},
  "geometry": {"coordinates":[-119.736474,36.786845],"type":"Point"}
}