{
  "type": "Feature",
  "properties": {
    "iso:country":"US",
    "sg:address":"5305 N Figueroa St",
    "sg:city":"Los Angeles",
    "sg:classifiers":[
        {
            "category":"Restaurant",
            "type":"Food & Drink"
        }
    ],
    "sg:phone":"+1 323 478 8383",
    "sg:postcode":"90042",
    "sg:province":"CA",
    "sg:tags":[
        "mexican"
    ],
    "wof:name":"Metro Balderas",
    "wof:placetype":"venue"
},
  "geometry": {"coordinates":[-118.19793199999999,34.10706],"type":"Point"}
}