{
  "type": "Feature",
  "properties": {
    "addr:full":"166 W Campbell Avenue Campbell CA 95008",
    "addr:housenumber":"166",
    "addr:postcode":"95008",
    "addr:street":"W Campbell Avenue",
    "iso:country":"US",
    "sg:address":"166 W Campbell Avenue",
    "sg:city":"Campbell",
    "sg:classifiers":[
        {
            "category":"Health Services",
            "subcategory":"Dentist",
            "type":"Services"
        }
    ],
    "sg:phone":"+1 408 379 0851",
    "sg:postcode":"95008",
    "sg:province":"CA",
    "sg:website":"www.campbellsmile.com",
    "wof:name":"Campbell Smile",
    "wof:placetype":"venue"
},
  "geometry": {"coordinates":[-121.95094899999999,37.287125],"type":"Point"}
}