{
  "type": "Feature",
  "properties": {
    "addr:full":"38000 Camden St Fremont CA 94536",
    "addr:housenumber":"38000",
    "addr:postcode":"94536",
    "addr:street":"Camden St",
    "iso:country":"US",
    "sg:address":"38000 Camden St",
    "sg:city":"Fremont",
    "sg:classifiers":[
        {
            "category":"Building & Trades",
            "subcategory":"Construction",
            "type":"Services"
        }
    ],
    "sg:phone":"+1 510 742 1470",
    "sg:postcode":"94536",
    "sg:province":"CA",
    "sg:tags":[
        "general",
        "contractor"
    ],
    "wof:name":"R L Pacific Construction",
    "wof:placetype":"venue"
},
  "geometry": {"coordinates":[-121.99526400000001,37.557861],"type":"Point"}
}