{
  "type": "Feature",
  "properties": {
    "addr:full":"2910 S San Pedro St Los Angeles CA 90011",
    "addr:housenumber":"2910",
    "addr:postcode":"90011",
    "addr:street":"S San Pedro St",
    "iso:country":"US",
    "sg:address":"2910 S San Pedro St",
    "sg:city":"Los Angeles",
    "sg:classifiers":[
        {
            "category":"Food & Beverages",
            "subcategory":"Groceries & Convenience Stores",
            "type":"Retail Goods"
        }
    ],
    "sg:phone":"+1 323 232 7964",
    "sg:postcode":"90011",
    "sg:province":"CA",
    "sg:tags":[
        "grocer"
    ],
    "wof:name":"Ofelia's Mini Market",
    "wof:placetype":"venue"
},
  "geometry": {"coordinates":[-118.26300000000001,34.0186],"type":"Point"}
}