{
  "type": "Feature",
  "properties": {
    "iso:country":"US",
    "sg:address":"490 Foothill Rd",
    "sg:city":"Beverly Hills",
    "sg:classifiers":[
        {
            "category":"Building & Trades",
            "subcategory":"Plumbing",
            "type":"Services"
        }
    ],
    "sg:phone":"+1 323 752 3148",
    "sg:postcode":"90210",
    "sg:province":"CA",
    "sg:website":"www.jimmiewest.com",
    "wof:name":"West Plumbing Shop West Jimmie Plumbing Co",
    "wof:placetype":"venue"
},
  "geometry": {"coordinates":[-118.396086,34.076294],"type":"Point"}
}