{
  "type": "Feature",
  "properties": {
    "iso:country":"US",
    "sg:address":"14726 Ramona Ave E9",
    "sg:city":"Chino",
    "sg:classifiers":[
        {
            "category":"Banks & Credit Unions",
            "subcategory":"Financial Services",
            "type":"Services"
        }
    ],
    "sg:phone":"+1 909 597 7373",
    "sg:postcode":"91710",
    "sg:province":"CA",
    "sg:tags":[
        "financing"
    ],
    "wof:name":"Dba Allegro Funding",
    "wof:placetype":"venue"
},
  "geometry": {"coordinates":[-117.706446,33.986266],"type":"Point"}
}