{
  "type": "Feature",
  "properties": {
    "iso:country":"US",
    "sg:address":"4241 Elverta Rd",
    "sg:city":"Antelope",
    "sg:phone":"+1 916 729 0100",
    "sg:postcode":"95843",
    "sg:province":"CA",
    "sg:website":"http://www.baskinrobbins.com",
    "wof:name":"Baskin Robbins",
    "wof:placetype":"venue"
},
  "geometry": {"coordinates":[-121.366246,38.713399],"type":"Point"}
}