{
  "type": "Feature",
  "properties": {
    "iso:country":"US",
    "sg:address":"2435 Galahad Rd",
    "sg:city":"San Diego",
    "sg:classifiers":[
        {
            "category":"Autos & Motor Vehicles",
            "subcategory":"Boat Sales",
            "type":"Retail Goods"
        }
    ],
    "sg:phone":"+1 858 277 4907",
    "sg:postcode":"92123",
    "sg:province":"CA",
    "sg:tags":[
        "dealer",
        "sales"
    ],
    "wof:name":"Pacific Powercat Co",
    "wof:placetype":"venue"
},
  "geometry": {"coordinates":[-117.143059,32.789461],"type":"Point"}
}