{
  "type": "Feature",
  "properties": {
    "addr:full":"13397 Marlay Ave Fontana CA 92337",
    "addr:housenumber":"13397",
    "addr:postcode":"92337",
    "addr:street":"Marlay Ave",
    "iso:country":"US",
    "sg:address":"13397 Marlay Ave",
    "sg:city":"Fontana",
    "sg:classifiers":[
        {
            "category":"Freight",
            "type":"Transportation"
        }
    ],
    "sg:phone":"+1 951 685 7606",
    "sg:postcode":"92337",
    "sg:province":"CA",
    "wof:name":"Kuehne & Nagel",
    "wof:placetype":"venue"
},
  "geometry": {"coordinates":[-117.511635,34.040737],"type":"Point"}
}