{
  "type": "Feature",
  "properties": {
    "addr:full":"1207 13th St Ste 1 Modesto CA 95354",
    "addr:housenumber":"1207",
    "addr:postcode":"ca 95354",
    "addr:street":"13Th St Ste 1",
    "iso:country":"US",
    "sg:address":"1207 13th St Ste 1",
    "sg:city":"Modesto",
    "sg:classifiers":[
        {
            "category":"Banks & Credit Unions",
            "subcategory":"Atm",
            "type":"Services"
        }
    ],
    "sg:phone":"+1 209 492 9335",
    "sg:postcode":"95354",
    "sg:province":"CA",
    "sg:tags":[
        "bankruptcy"
    ],
    "sg:website":"www.tomhoganlaw.com",
    "wof:name":"HOGAN THOMAS ATTORNEY AT LAW",
    "wof:placetype":"venue"
},
  "geometry": {"coordinates":[-120.99992899999999,37.64453],"type":"Point"}
}