{
  "type": "Feature",
  "properties": {
    "iso:country":"US",
    "sg:address":"7334 Topanga Canyon Blvd",
    "sg:city":"Canoga Park",
    "sg:classifiers":[
        {
            "category":"Travel",
            "subcategory":"Travel Agent",
            "type":"Entertainment"
        }
    ],
    "sg:phone":"+1 818 704 0325",
    "sg:postcode":"91303",
    "sg:province":"CA",
    "sg:tags":[
        "agency",
        "bureau"
    ],
    "wof:name":"Patagonia Travel",
    "wof:placetype":"venue"
},
  "geometry": {"coordinates":[-118.605786,34.204594],"type":"Point"}
}