{
  "type": "Feature",
  "properties": {
    "addr:full":"350 S State St San Jacinto CA 92583",
    "addr:housenumber":"350",
    "addr:postcode":"92583",
    "addr:street":"S State St",
    "iso:country":"US",
    "sg:address":"350 S State St",
    "sg:city":"San Jacinto",
    "sg:classifiers":[
        {
            "category":"Real Estate",
            "subcategory":"Real Estate Operator",
            "type":"Services"
        }
    ],
    "sg:phone":"+1 951 654 2323",
    "sg:postcode":"92583",
    "sg:province":"CA",
    "sg:tags":[
        "apartment"
    ],
    "wof:name":"Elms Mobile Park & Apartments",
    "wof:placetype":"venue"
},
  "geometry": {"coordinates":[-116.971988,33.783829],"type":"Point"}
}