{
  "type": "Feature",
  "properties": {
    "addr:full":"820 N Parton St Santa Ana CA 92701",
    "addr:housenumber":"820",
    "addr:postcode":"92701",
    "addr:street":"N Parton St",
    "iso:country":"US",
    "sg:address":"820 N Parton St",
    "sg:city":"Santa Ana",
    "sg:classifiers":[
        {
            "category":"Banks & Credit Unions",
            "subcategory":"Bank",
            "type":"Services"
        }
    ],
    "sg:phone":"+1 714 647 1100",
    "sg:postcode":"92701",
    "sg:province":"CA",
    "sg:tags":[
        "financing"
    ],
    "sg:website":"www.fundamericafinancial.com",
    "wof:name":"Fund America",
    "wof:placetype":"venue"
},
  "geometry": {"coordinates":[-117.874768,33.751871],"type":"Point"}
}