{
  "type": "Feature",
  "properties": {
    "addr:full":"6041 E Montecito Ave Fresno CA 93727",
    "addr:housenumber":"6041",
    "addr:postcode":"93727",
    "addr:street":"E Montecito Ave",
    "iso:country":"US",
    "sg:address":"6041 E Montecito Ave",
    "sg:city":"Fresno",
    "sg:classifiers":[
        {
            "category":"Manufacturing",
            "subcategory":"Retail Goods",
            "type":"Manufacturing & Wholesale Goods"
        }
    ],
    "sg:phone":"+1 559 453 0404",
    "sg:postcode":"93727",
    "sg:province":"CA",
    "sg:tags":[
        "product",
        "mfg"
    ],
    "wof:name":"Poochigian Mfg",
    "wof:placetype":"venue"
},
  "geometry": {"coordinates":[-119.68168799999999,36.734988],"type":"Point"}
}