{
  "type": "Feature",
  "properties": {
    "addr:full":"1518 S Eastern Ave City Of Commerce CA 90040",
    "addr:housenumber":"1518",
    "addr:postcode":"90040",
    "addr:street":"S Eastern Ave",
    "iso:country":"US",
    "sg:address":"1518 S Eastern Ave",
    "sg:city":"City Of Commerce",
    "sg:classifiers":[
        {
            "category":"Wholesale",
            "subcategory":"Non-durable Goods",
            "type":"Manufacturing & Wholesale Goods"
        }
    ],
    "sg:phone":"+1 323 780 6000",
    "sg:postcode":"90040",
    "sg:province":"CA",
    "sg:tags":[
        "charcoal"
    ],
    "wof:name":"California Charcoal & Firewood",
    "wof:placetype":"venue"
},
  "geometry": {"coordinates":[-118.173815,34.011656],"type":"Point"}
}