{
  "type": "Feature",
  "properties": {
    "iso:country":"US",
    "sg:address":"132 N Euclid Ave",
    "sg:city":"Upland",
    "sg:classifiers":[
        {
            "category":"Manufacturing",
            "subcategory":"Tools & Machinery",
            "type":"Manufacturing & Wholesale Goods"
        }
    ],
    "sg:phone":"+1 909 949 3819",
    "sg:postcode":"91786",
    "sg:province":"CA",
    "sg:tags":[
        "terminal",
        "computer",
        "system",
        "install",
        "mfg"
    ],
    "wof:name":"Online Technology Inc",
    "wof:placetype":"venue"
},
  "geometry": {"coordinates":[-117.651068,34.095593],"type":"Point"}
}