{
  "type": "Feature",
  "properties": {
    "iso:country":"US",
    "sg:address":"9221 W Olympic Blvd",
    "sg:city":"Beverly Hills",
    "sg:classifiers":[
        {
            "category":"Retail",
            "subcategory":"Repair Shop",
            "type":"Services"
        }
    ],
    "sg:phone":"+1 323 876 1300",
    "sg:postcode":"90212",
    "sg:province":"CA",
    "sg:tags":[
        "plumbing",
        "drain",
        "cleaning",
        "sewer"
    ],
    "wof:name":"Burt Plumbing",
    "wof:placetype":"venue"
},
  "geometry": {"coordinates":[-118.39216,34.059472],"type":"Point"}
}