{
  "type": "Feature",
  "properties": {
    "iso:country":"US",
    "sg:address":"160 Sansome St",
    "sg:city":"San Francisco",
    "sg:classifiers":[
        {
            "category":"Insurance",
            "subcategory":"Hazard Insurance",
            "type":"Services"
        }
    ],
    "sg:phone":"+1 415 395 9300",
    "sg:postcode":"94104",
    "sg:province":"CA",
    "sg:tags":[
        "profit",
        "sharing",
        "pension",
        "plan"
    ],
    "sg:website":"www.altmancronin.com",
    "wof:name":"Altman & Cronin Benefit Cnsltn",
    "wof:placetype":"venue"
},
  "geometry": {"coordinates":[-122.400768,37.79155],"type":"Point"}
}