{
  "type": "Feature",
  "properties": {
    "addr:full":"1510 Howe Avenue Ste A Sacramento CA 95825",
    "addr:housenumber":"1510",
    "addr:postcode":"95825",
    "addr:street":"Howe Avenue Ste A",
    "iso:country":"US",
    "sg:address":"1510 Howe Avenue Ste A",
    "sg:city":"Sacramento",
    "sg:classifiers":[
        {
            "category":"Arena",
            "subcategory":"Sports Club",
            "type":"Entertainment"
        }
    ],
    "sg:phone":"+1 916 568 9104",
    "sg:postcode":"95825",
    "sg:province":"CA",
    "sg:tags":[
        "martial art"
    ],
    "sg:website":"www.muaythailao.com",
    "wof:name":"Muay Thai Lao Kickboxing Academy",
    "wof:placetype":"venue"
},
  "geometry": {"coordinates":[-121.413674,38.59319],"type":"Point"}
}