{
  "type": "Feature",
  "properties": {
    "iso:country":"US",
    "sg:address":"12046 Jacaranda Ave",
    "sg:city":"Hesperia",
    "sg:classifiers":[
        {
            "category":"Building & Trades",
            "subcategory":"Construction",
            "type":"Services"
        }
    ],
    "sg:phone":"+1 760 956 6755",
    "sg:postcode":"92345",
    "sg:province":"CA",
    "sg:tags":[
        "insulation",
        "heat",
        "contractor"
    ],
    "wof:name":"Apple Valley Insulation",
    "wof:placetype":"venue"
},
  "geometry": {"coordinates":[-117.263356,34.468378],"type":"Point"}
}