{
  "type": "Feature",
  "properties": {
    "addr:full":"1029 E Olive Ave Merced CA 95340",
    "addr:housenumber":"1029",
    "addr:postcode":"95340",
    "addr:street":"E Olive Ave",
    "iso:country":"US",
    "sg:address":"1029 E Olive Ave",
    "sg:city":"Merced",
    "sg:classifiers":[
        {
            "category":"Building & Trades",
            "subcategory":"Construction",
            "type":"Services"
        }
    ],
    "sg:phone":"+1 209 384 2822",
    "sg:postcode":"95340",
    "sg:province":"CA",
    "sg:tags":[
        "concrete",
        "contractor"
    ],
    "wof:name":"Cooper Curbing",
    "wof:placetype":"venue"
},
  "geometry": {"coordinates":[-120.458038,37.318547],"type":"Point"}
}