{
  "type": "Feature",
  "properties": {
    "iso:country":"US",
    "sg:address":"796 S Cloverdale Blvd",
    "sg:city":"Cloverdale",
    "sg:classifiers":[
        {
            "category":"Restaurant",
            "type":"Food & Drink"
        }
    ],
    "sg:phone":"+1 707 894 9444",
    "sg:postcode":"95425",
    "sg:province":"CA",
    "wof:name":"Zini's Diner",
    "wof:placetype":"venue"
},
  "geometry": {"coordinates":[-123.017546,38.791746],"type":"Point"}
}