{
  "type": "Feature",
  "properties": {
    "addr:full":"50 S Gay St Susanville CA 96130",
    "addr:housenumber":"50",
    "addr:postcode":"96130",
    "addr:street":"S Gay St",
    "iso:country":"US",
    "sg:address":"50 S Gay St",
    "sg:city":"Susanville",
    "sg:classifiers":[
        {
            "category":"Real Estate",
            "subcategory":"Real Estate Agent",
            "type":"Services"
        }
    ],
    "sg:phone":"+1 530 257 7936",
    "sg:postcode":"96130",
    "sg:province":"CA",
    "wof:name":"Cascade Realty",
    "wof:placetype":"venue"
},
  "geometry": {"coordinates":[-120.660819,40.417828],"type":"Point"}
}