{
  "type": "Feature",
  "properties": {
    "addr:full":"3705 Gaelic Ct Bakersfield CA 93311",
    "addr:housenumber":"3705",
    "addr:postcode":"93311",
    "addr:street":"Gaelic Ct",
    "iso:country":"US",
    "sg:address":"3705 Gaelic Ct",
    "sg:city":"Bakersfield",
    "sg:classifiers":[
        {
            "category":"Freight",
            "type":"Transportation"
        }
    ],
    "sg:phone":"+1 661 654 8400",
    "sg:postcode":"93311",
    "sg:province":"CA",
    "sg:tags":[
        "trucking"
    ],
    "wof:name":"Premier Freightways Inc",
    "wof:placetype":"venue"
},
  "geometry": {"coordinates":[-119.120327,35.320489],"type":"Point"}
}