{
  "type": "Feature",
  "properties": {
    "iso:country":"US",
    "sg:address":"316 N Westside St",
    "sg:city":"Porterville",
    "sg:classifiers":[
        {
            "category":"Building & Trades",
            "subcategory":"Construction",
            "type":"Services"
        }
    ],
    "sg:phone":"+1 559 783 2220",
    "sg:postcode":"93257",
    "sg:province":"CA",
    "sg:website":"www.mc-construction.com",
    "wof:name":"Metal Craft Construction",
    "wof:placetype":"venue"
},
  "geometry": {"coordinates":[-119.045039,36.071011],"type":"Point"}
}