{
  "type": "Feature",
  "properties": {
    "addr:full":"3150 Contra Loma Blvd Antioch CA 94509",
    "addr:postcode":"3150;ca 94509",
    "addr:street":"Contra Loma Blvd",
    "iso:country":"US",
    "sg:address":"3150 Contra Loma Blvd",
    "sg:city":"Antioch",
    "sg:classifiers":[
        {
            "category":"Shopping",
            "subcategory":"Discount & Variety Stores",
            "type":"Retail Goods"
        }
    ],
    "sg:phone":"+1 925 755 8356",
    "sg:postcode":"94509",
    "sg:province":"CA",
    "wof:name":"Dollar World Inc",
    "wof:placetype":"venue"
},
  "geometry": {"coordinates":[-121.822439,37.991738],"type":"Point"}
}