{
  "type": "Feature",
  "properties": {
    "iso:country":"US",
    "sg:address":"5113 Gordon Dr",
    "sg:city":"Sacramento",
    "sg:classifiers":[
        {
            "category":"Building & Trades",
            "subcategory":"Construction",
            "type":"Services"
        }
    ],
    "sg:phone":"+1 916 393 1561",
    "sg:postcode":"95824",
    "sg:province":"CA",
    "sg:tags":[
        "painter"
    ],
    "wof:name":"John & Tony's Painting Svc",
    "wof:placetype":"venue"
},
  "geometry": {"coordinates":[-121.441439,38.520707],"type":"Point"}
}