{
  "type": "Feature",
  "properties": {
    "addr:full":"83 Morning Dove Cir Sacramento CA 95833",
    "addr:housenumber":"83",
    "addr:postcode":"95833",
    "addr:street":"Morning Dove Cir",
    "iso:country":"US",
    "sg:address":"83 Morning Dove Cir",
    "sg:city":"Sacramento",
    "sg:classifiers":[
        {
            "category":"Autos & Motor Vehicles",
            "subcategory":"Auto Supplies",
            "type":"Retail Goods"
        }
    ],
    "sg:phone":"+1 916 868 2223",
    "sg:postcode":"95833",
    "sg:province":"CA",
    "sg:tags":[
        "tire"
    ],
    "wof:name":"Pacific Tire & Wheels",
    "wof:placetype":"venue"
},
  "geometry": {"coordinates":[-121.49498,38.619301],"type":"Point"}
}