{
  "type": "Feature",
  "properties": {
    "addr:full":"3806 Lesser Dr Newbury Park CA 91320",
    "addr:postcode":"3806;91320",
    "addr:street":"Lesser Dr",
    "iso:country":"US",
    "sg:address":"3806 Lesser Dr",
    "sg:city":"Newbury Park",
    "sg:classifiers":[
        {
            "category":"Insurance",
            "subcategory":"Insurance Agent",
            "type":"Services"
        }
    ],
    "sg:phone":"+1 805 499 6954",
    "sg:postcode":"91320",
    "sg:province":"CA",
    "wof:name":"Laria Insurance",
    "wof:placetype":"venue"
},
  "geometry": {"coordinates":[-118.956273,34.1861],"type":"Point"}
}