{
  "type": "Feature",
  "properties": {
    "addr:full":"40254 Tanager Cir Temecula CA 92591",
    "addr:postcode":"40254;92591",
    "addr:street":"Tanager Cir",
    "iso:country":"US",
    "sg:address":"40254 Tanager Cir",
    "sg:city":"Temecula",
    "sg:classifiers":[
        {
            "category":"Manufacturing",
            "subcategory":"Buildings",
            "type":"Manufacturing & Wholesale Goods"
        },
        {
            "category":"Building & Trades",
            "subcategory":"Construction",
            "type":"Services"
        },
        {
            "category":"Building & Trades",
            "subcategory":"Electrical",
            "type":"Services"
        }
    ],
    "sg:phone":"+1 951 526 7235",
    "sg:postcode":"92591",
    "sg:province":"CA",
    "sg:tags":[
        "industrial",
        "electrician",
        "electric",
        "builder",
        "contractor",
        "contractors-commercial",
        "home"
    ],
    "wof:name":"P & M Electric",
    "wof:placetype":"venue"
},
  "geometry": {"coordinates":[-117.135002,33.537234],"type":"Point"}
}