{
  "type": "Feature",
  "properties": {
    "addr:full":"114 Mitchell Ct Vallejo CA 94589",
    "addr:housenumber":"114",
    "addr:postcode":"94589",
    "addr:street":"Mitchell Ct",
    "iso:country":"US",
    "sg:address":"114 Mitchell Ct",
    "sg:city":"Vallejo",
    "sg:classifiers":[
        {
            "category":"Wholesale",
            "subcategory":"Non-durable Goods",
            "type":"Manufacturing & Wholesale Goods"
        }
    ],
    "sg:phone":"+1 707 642 9054",
    "sg:postcode":"94589",
    "sg:province":"CA",
    "sg:tags":[
        "dry",
        "goods-wholesale"
    ],
    "wof:name":"That's Dat",
    "wof:placetype":"venue"
},
  "geometry": {"coordinates":[-122.244018,38.135769],"type":"Point"}
}