{
  "type": "Feature",
  "properties": {
    "addr:full":"25200 Mission Blvd Hayward CA 94544",
    "addr:housenumber":"25200",
    "addr:postcode":"94544",
    "addr:street":"Mission Blvd",
    "iso:country":"US",
    "sg:address":"25200 Mission Blvd",
    "sg:city":"Hayward",
    "sg:classifiers":[
        {
            "category":"Shopping",
            "subcategory":"Mobile Phones",
            "type":"Retail Goods"
        }
    ],
    "sg:postcode":"94544",
    "sg:province":"CA",
    "wof:name":"Cellular Gopher",
    "wof:placetype":"venue"
},
  "geometry": {"coordinates":[-122.07199900000001,37.6572],"type":"Point"}
}