{
  "type": "Feature",
  "properties": {
    "iso:country":"US",
    "sg:address":"10970 International Blvd",
    "sg:city":"Oakland",
    "sg:classifiers":[
        {
            "category":"Shopping",
            "subcategory":"Jewelry",
            "type":"Retail Goods"
        }
    ],
    "sg:phone":"+1 510 430 8087",
    "sg:postcode":"94603",
    "sg:province":"CA",
    "wof:name":"Tom's Jewelry",
    "wof:placetype":"venue"
},
  "geometry": {"coordinates":[-122.165513,37.737748],"type":"Point"}
}