{
  "type": "Feature",
  "properties": {
    "iso:country":"US",
    "sg:address":"2710 Heinz St",
    "sg:city":"Stockton",
    "sg:classifiers":[
        {
            "category":"Building & Trades",
            "subcategory":"Construction",
            "type":"Services"
        }
    ],
    "sg:phone":"+1 209 943 4710",
    "sg:postcode":"95206",
    "sg:province":"CA",
    "sg:tags":[
        "roof",
        "structure"
    ],
    "wof:name":"Inland Valley Truss",
    "wof:placetype":"venue"
},
  "geometry": {"coordinates":[-121.2771,37.923169],"type":"Point"}
}