{
  "type": "Feature",
  "properties": {
    "addr:full":"225 S Lassen St Susanville CA 96130",
    "addr:housenumber":"225",
    "addr:postcode":"96130",
    "addr:street":"S Lassen St",
    "iso:country":"US",
    "sg:address":"225 S Lassen St",
    "sg:city":"Susanville",
    "sg:classifiers":[
        {
            "category":"Professional",
            "subcategory":"Lawyer & Legal Services",
            "type":"Services"
        }
    ],
    "sg:phone":"+1 530 257 6162",
    "sg:postcode":"96130",
    "sg:province":"CA",
    "sg:tags":[
        "attorney"
    ],
    "wof:name":"Nareau Law Office",
    "wof:placetype":"venue"
},
  "geometry": {"coordinates":[-120.662693,40.41638],"type":"Point"}
}