{
  "type": "Feature",
  "properties": {
    "iso:country":"US",
    "sg:address":"1441 Gingerwood Dr",
    "sg:city":"Milpitas",
    "sg:classifiers":[
        {
            "category":"Wholesale",
            "subcategory":"Chemicals & Plastics",
            "type":"Manufacturing & Wholesale Goods"
        }
    ],
    "sg:phone":"+1 408 942 1643",
    "sg:postcode":"95035",
    "sg:province":"CA",
    "sg:tags":[
        "distribution"
    ],
    "wof:name":"Malti Group USA Corp",
    "wof:placetype":"venue"
},
  "geometry": {"coordinates":[-121.915228,37.451015],"type":"Point"}
}