{
  "type": "Feature",
  "properties": {
    "addr:full":"2830 4th Ave San Diego CA 92103",
    "addr:housenumber":"2830",
    "addr:postcode":"92103",
    "addr:street":"4Th Ave",
    "iso:country":"US",
    "sg:address":"2830 4th Ave",
    "sg:city":"San Diego",
    "sg:classifiers":[
        {
            "category":"Professional",
            "subcategory":"Business Services",
            "type":"Services"
        }
    ],
    "sg:phone":"+1 619 291 6499",
    "sg:postcode":"92103",
    "sg:province":"CA",
    "sg:tags":[
        "telemarketing"
    ],
    "wof:name":"Skycom",
    "wof:placetype":"venue"
},
  "geometry": {"coordinates":[-117.161306,32.735256],"type":"Point"}
}