{
  "type": "Feature",
  "properties": {
    "iso:country":"US",
    "sg:address":"855 Alabama St",
    "sg:city":"Redlands",
    "sg:classifiers":[
        {
            "category":"Restaurant",
            "type":"Food & Drink"
        }
    ],
    "sg:phone":"+1 909 793 7007",
    "sg:postcode":"92374",
    "sg:province":"CA",
    "wof:name":"Zabella's Mexican Restaurant",
    "wof:placetype":"venue"
},
  "geometry": {"coordinates":[-117.208844,34.064387],"type":"Point"}
}