{
  "type": "Feature",
  "properties": {
    "addr:full":"19360 Colima Rd Rowland Heights CA 91748",
    "addr:housenumber":"19360",
    "addr:postcode":"91748",
    "addr:street":"Colima Rd",
    "iso:country":"US",
    "sg:address":"19360 Colima Rd",
    "sg:city":"Rowland Heights",
    "sg:classifiers":[
        {
            "category":"Organizations",
            "subcategory":"Religious Organization",
            "type":"Services"
        }
    ],
    "sg:phone":"+1 626 964 2521",
    "sg:postcode":"91748",
    "sg:province":"CA",
    "sg:tags":[
        "church"
    ],
    "sg:website":"www.redeemerlc.com",
    "wof:name":"Redeemer Lutheran Church",
    "wof:placetype":"venue"
},
  "geometry": {"coordinates":[-117.877898,33.986798],"type":"Point"}
}