{
  "type": "Feature",
  "properties": {
    "iso:country":"US",
    "sg:address":"668 Eugene Rd",
    "sg:city":"Palm Springs",
    "sg:classifiers":[
        {
            "category":"Manufacturing",
            "subcategory":"Metals",
            "type":"Manufacturing & Wholesale Goods"
        },
        {
            "category":"Retail",
            "subcategory":"Repair Shop",
            "type":"Services"
        }
    ],
    "sg:phone":"+1 760 327 1770",
    "sg:postcode":"92264",
    "sg:province":"CA",
    "sg:tags":[
        "steel",
        "ornamental",
        "mfg",
        "work",
        "iron",
        "welding"
    ],
    "wof:name":"Village Blacksmith Inc",
    "wof:placetype":"venue"
},
  "geometry": {"coordinates":[-116.494001,33.81348],"type":"Point"}
}