{
  "type": "Feature",
  "properties": {
    "addr:full":"7232 Van Nuys Blvd Ste 203 Van Nuys CA 91405",
    "addr:housenumber":"7232",
    "addr:postcode":"91405",
    "addr:street":"Van Nuys Blvd Ste 203",
    "iso:country":"US",
    "sg:address":"7232 Van Nuys Blvd Ste 203",
    "sg:city":"Van Nuys",
    "sg:classifiers":[
        {
            "category":"Health Services",
            "subcategory":"Doctor",
            "type":"Services"
        }
    ],
    "sg:phone":"+1 714 687 1737",
    "sg:postcode":"91405",
    "sg:province":"CA",
    "wof:name":"S & L Medical Center",
    "wof:placetype":"venue"
},
  "geometry": {"coordinates":[-118.44875999999999,34.201959],"type":"Point"}
}