{
  "type": "Feature",
  "properties": {
    "iso:country":"US",
    "sg:address":"1350 Arnold Dr",
    "sg:city":"Martinez",
    "sg:classifiers":[
        {
            "category":"Professional",
            "subcategory":"Detective & Security Services",
            "type":"Services"
        }
    ],
    "sg:phone":"+1 925 250 7298",
    "sg:postcode":"94553",
    "sg:province":"CA",
    "sg:tags":[
        "investigator"
    ],
    "wof:name":"R Patterson Investigations",
    "wof:placetype":"venue"
},
  "geometry": {"coordinates":[-122.098716,37.993255],"type":"Point"}
}