{
  "type": "Feature",
  "properties": {
    "addr:full":"312 Capetown Ct Novato CA 94947",
    "addr:housenumber":"312",
    "addr:postcode":"94947",
    "addr:street":"Capetown Ct",
    "iso:country":"US",
    "sg:address":"312 Capetown Ct",
    "sg:city":"Novato",
    "sg:classifiers":[
        {
            "category":"Real Estate",
            "subcategory":"Real Estate Agent",
            "type":"Services"
        }
    ],
    "sg:phone":"+1 415 233 1729",
    "sg:postcode":"94947",
    "sg:province":"CA",
    "sg:tags":[
        "inspection"
    ],
    "wof:name":"Certified Home Inspection Svc",
    "wof:placetype":"venue"
},
  "geometry": {"coordinates":[-122.549564,38.079793],"type":"Point"}
}