{
  "type": "Feature",
  "properties": {
    "iso:country":"US",
    "sg:address":"401 Francisco Street",
    "sg:city":"San Francisco",
    "sg:classifiers":[
        {
            "category":"Professional",
            "subcategory":"Lawyer & Legal Services",
            "type":"Services"
        }
    ],
    "sg:phone":"+1 415 775 1101",
    "sg:postcode":"94133",
    "sg:province":"CA",
    "wof:name":"Dean Martin L Atty",
    "wof:placetype":"venue"
},
  "geometry": {"coordinates":[-122.412003,37.804798],"type":"Point"}
}