{
  "type": "Feature",
  "properties": {
    "iso:country":"US",
    "sg:address":"3490 Stevens Creek Blvd",
    "sg:city":"San Jose",
    "sg:classifiers":[
        {
            "category":"Retail",
            "subcategory":"Auto Rental",
            "type":"Services"
        }
    ],
    "sg:phone":"+1 408 286 6201",
    "sg:postcode":"95117",
    "sg:province":"CA",
    "sg:tags":[
        "car"
    ],
    "wof:name":"1st Nationwide Mortgage Corporation",
    "wof:placetype":"venue"
},
  "geometry": {"coordinates":[-121.959,37.323399],"type":"Point"}
}