{
  "type": "Feature",
  "properties": {
    "addr:full":"4401 Hughes Ln Bakersfield CA 93304",
    "addr:housenumber":"4401",
    "addr:postcode":"93304",
    "addr:street":"Hughes Ln",
    "iso:country":"US",
    "sg:address":"4401 Hughes Ln",
    "sg:city":"Bakersfield",
    "sg:classifiers":[
        {
            "category":"Sports & Exercise",
            "subcategory":"Bowling",
            "type":"Entertainment"
        }
    ],
    "sg:phone":"+1 661 833 9019",
    "sg:postcode":"93304",
    "sg:province":"CA",
    "sg:tags":[
        "center"
    ],
    "wof:name":"Tremblay Norman G DC",
    "wof:placetype":"venue"
},
  "geometry": {"coordinates":[-119.030086,35.316589],"type":"Point"}
}