{
  "type": "Feature",
  "properties": {
    "iso:country":"US",
    "sg:address":"2060 State Rte 66",
    "sg:city":"Glendora",
    "sg:classifiers":[
        {
            "category":"Real Estate",
            "subcategory":"Real Estate Agent",
            "type":"Services"
        }
    ],
    "sg:phone":"+1 626 852 6771",
    "sg:postcode":"91740",
    "sg:province":"CA",
    "wof:name":"Andrade Financial",
    "wof:placetype":"venue"
},
  "geometry": {"coordinates":[-117.825444,34.127819],"type":"Point"}
}