{
  "type": "Feature",
  "properties": {
    "iso:country":"US",
    "sg:address":"2140 Peralta Blvd",
    "sg:city":"Fremont",
    "sg:classifiers":[
        {
            "category":"Professional",
            "type":"Services"
        },
        {
            "category":"Shopping",
            "subcategory":"Computers & Home Electronics",
            "type":"Retail Goods"
        }
    ],
    "sg:phone":"+1 510 796 4416",
    "sg:postcode":"94536",
    "sg:province":"CA",
    "sg:tags":[
        "software"
    ],
    "wof:name":"Eyetee Inc",
    "wof:placetype":"venue"
},
  "geometry": {"coordinates":[-121.989582,37.562286],"type":"Point"}
}