{
  "type": "Feature",
  "properties": {
    "addr:full":"205 S Tustin St Orange CA 92866",
    "addr:housenumber":"205",
    "addr:postcode":"92866",
    "addr:street":"S Tustin St",
    "iso:country":"US",
    "sg:address":"205 S Tustin St",
    "sg:city":"Orange",
    "sg:classifiers":[
        {
            "category":"Restaurant",
            "type":"Food & Drink"
        }
    ],
    "sg:phone":"+1 714 744 1702",
    "sg:postcode":"92866",
    "sg:province":"CA",
    "sg:tags":[
        "mexican"
    ],
    "wof:name":"El Taco",
    "wof:placetype":"venue"
},
  "geometry": {"coordinates":[-117.83575399999999,33.785908],"type":"Point"}
}