{
  "type": "Feature",
  "properties": {
    "addr:full":"2937 Veneman Ave N Modesto CA 95356",
    "addr:housenumber":"2937",
    "addr:postcode":"ca 95356",
    "addr:street":"Veneman Ave N",
    "iso:country":"US",
    "sg:address":"2937 Veneman Ave N",
    "sg:city":"Modesto",
    "sg:classifiers":[
        {
            "category":"Insurance",
            "subcategory":"Insurance Agent",
            "type":"Services"
        }
    ],
    "sg:phone":"+1 209 529 4850",
    "sg:postcode":"95356",
    "sg:province":"CA",
    "wof:name":"Allstate Insurance",
    "wof:placetype":"venue"
},
  "geometry": {"coordinates":[-121.033361,37.691507],"type":"Point"}
}