{
  "type": "Feature",
  "properties": {
    "iso:country":"US",
    "sg:address":"141 Earl St",
    "sg:city":"Crescent City",
    "sg:classifiers":[
        {
            "category":"Manufacturing",
            "subcategory":"Lumber",
            "type":"Manufacturing & Wholesale Goods"
        }
    ],
    "sg:phone":"+1 707 465 9856",
    "sg:postcode":"95531",
    "sg:province":"CA",
    "sg:tags":[
        "forestry"
    ],
    "wof:name":"Dale Fugate",
    "wof:placetype":"venue"
},
  "geometry": {"coordinates":[-124.16149,41.820128],"type":"Point"}
}