{
  "type": "Feature",
  "properties": {
    "addr:full":"1624 E Main St Ventura CA 93001",
    "addr:housenumber":"1624",
    "addr:postcode":"93001",
    "addr:street":"E Main St",
    "iso:country":"US",
    "sg:address":"1624 E Main St",
    "sg:city":"Ventura",
    "sg:classifiers":[
        {
            "category":"Professional",
            "type":"Services"
        }
    ],
    "sg:phone":"+1 805 653 1326",
    "sg:postcode":"93001",
    "sg:province":"CA",
    "wof:name":"Barnes Pierre Doctor",
    "wof:placetype":"venue"
},
  "geometry": {"coordinates":[-119.27493200000001,34.279129],"type":"Point"}
}