{
  "type": "Feature",
  "properties": {
    "iso:country":"US",
    "sg:address":"4701 University Ave",
    "sg:city":"San Diego",
    "sg:classifiers":[
        {
            "category":"Travel",
            "subcategory":"Travel Agent",
            "type":"Entertainment"
        }
    ],
    "sg:phone":"+1 619 284 6898",
    "sg:postcode":"92105",
    "sg:province":"CA",
    "sg:tags":[
        "agency"
    ],
    "wof:name":"Travel World Services LLC",
    "wof:placetype":"venue"
},
  "geometry": {"coordinates":[-117.093368,32.749536],"type":"Point"}
}