{
  "type": "Feature",
  "properties": {
    "addr:full":"2807 Oregon Ct Ste E3 Torrance CA 90503",
    "addr:housenumber":"2807",
    "addr:postcode":"90503",
    "addr:street":"Oregon Ct Ste E3",
    "iso:country":"US",
    "sg:address":"2807 Oregon Ct Ste E3",
    "sg:city":"Torrance",
    "sg:classifiers":[
        {
            "category":"Shopping",
            "subcategory":"Stationery & Office Supplies",
            "type":"Retail Goods"
        },
        {
            "category":"Personal",
            "subcategory":"Tattoo Parlor",
            "type":"Services"
        }
    ],
    "sg:phone":"+1 310 320 4465",
    "sg:postcode":"90503",
    "sg:province":"CA",
    "sg:tags":[
        "equipment"
    ],
    "wof:name":"Ink Works Inc",
    "wof:placetype":"venue"
},
  "geometry": {"coordinates":[-118.337969,33.846633],"type":"Point"}
}