{
  "type": "Feature",
  "properties": {
    "addr:full":"21021 Devonshire St Chatsworth CA 91311",
    "addr:housenumber":"21021",
    "addr:postcode":"91311",
    "addr:street":"Devonshire St",
    "iso:country":"US",
    "sg:address":"21021 Devonshire St",
    "sg:city":"Chatsworth",
    "sg:classifiers":[
        {
            "category":"Professional",
            "subcategory":"Business Services",
            "type":"Services"
        }
    ],
    "sg:phone":"+1 818 993 0300",
    "sg:postcode":"91311",
    "sg:province":"CA",
    "sg:tags":[
        "merchant",
        "credit",
        "card"
    ],
    "wof:name":"C S I",
    "wof:placetype":"venue"
},
  "geometry": {"coordinates":[-118.59256999999999,34.257314],"type":"Point"}
}