{
  "type": "Feature",
  "properties": {
    "iso:country":"US",
    "sg:address":"Empire Center 1501 North Victory Place",
    "sg:city":"Burbank",
    "sg:classifiers":[
        {
            "category":"Shopping",
            "subcategory":"Department Store",
            "type":"Retail Goods"
        }
    ],
    "sg:postcode":"91504",
    "sg:province":"CA",
    "wof:name":"Nordstrom Rack",
    "wof:placetype":"venue"
},
  "geometry": {"coordinates":[-118.330136,34.189968],"type":"Point"}
}