{
  "type": "Feature",
  "properties": {
    "iso:country":"US",
    "sg:address":"1061 E 54th St",
    "sg:city":"Los Angeles",
    "sg:classifiers":[
        {
            "category":"Organizations",
            "subcategory":"Membership Organization",
            "type":"Services"
        }
    ],
    "sg:phone":"+1 323 231 4660",
    "sg:postcode":"90011",
    "sg:province":"CA",
    "wof:name":"Concerned Citizens Of South",
    "wof:placetype":"venue"
},
  "geometry": {"coordinates":[-118.259613,33.993498],"type":"Point"}
}