{
  "type": "Feature",
  "properties": {
    "iso:country":"US",
    "sg:address":"1046 Sierra Dr",
    "sg:city":"Turlock",
    "sg:classifiers":[
        {
            "category":"Professional",
            "subcategory":"Computer Services",
            "type":"Services"
        }
    ],
    "sg:phone":"+1 209 606 0806",
    "sg:postcode":"95380",
    "sg:province":"CA",
    "sg:tags":[
        "consultant",
        "designer"
    ],
    "wof:name":"Central Valley Webworks",
    "wof:placetype":"venue"
},
  "geometry": {"coordinates":[-120.833778,37.502013],"type":"Point"}
}