{
  "type": "Feature",
  "properties": {
    "addr:full":"1 Ocean Park Blvd Santa Monica CA 90405",
    "addr:housenumber":"1",
    "addr:postcode":"90405",
    "addr:street":"Ocean Park Blvd",
    "iso:country":"US",
    "sg:address":"1 Ocean Park Blvd",
    "sg:city":"Santa Monica",
    "sg:classifiers":[
        {
            "category":"Restaurant",
            "type":"Food & Drink"
        }
    ],
    "sg:phone":"+1 310 450 9949",
    "sg:postcode":"90405",
    "sg:province":"CA",
    "wof:name":"Gary's Grill",
    "wof:placetype":"venue"
},
  "geometry": {"coordinates":[-118.48577899999999,34.000906],"type":"Point"}
}