{
  "type": "Feature",
  "properties": {
    "iso:country":"US",
    "sg:address":"11847 Wilshire Blvd",
    "sg:city":"Los Angeles",
    "sg:classifiers":[
        {
            "category":"Health Services",
            "subcategory":"Chiropractor",
            "type":"Services"
        }
    ],
    "sg:phone":"+1 310 477 1443",
    "sg:postcode":"90025",
    "sg:province":"CA",
    "wof:name":"Brentwood Wilshire Chiro Ctr",
    "wof:placetype":"venue"
},
  "geometry": {"coordinates":[-118.463938,34.047064],"type":"Point"}
}