{
  "type": "Feature",
  "properties": {
    "addr:full":"1229 N Sycamore Ave Los Angeles CA 90038",
    "addr:housenumber":"1229",
    "addr:postcode":"90038",
    "addr:street":"N Sycamore Ave",
    "iso:country":"US",
    "sg:address":"1229 N Sycamore Ave",
    "sg:city":"Los Angeles",
    "sg:classifiers":[
        {
            "category":"Real Estate",
            "subcategory":"Real Estate Operator",
            "type":"Services"
        }
    ],
    "sg:phone":"+1 323 461 8050",
    "sg:postcode":"90038",
    "sg:province":"CA",
    "sg:tags":[
        "apartment"
    ],
    "wof:name":"1229 N Sycamore Ave Apartments",
    "wof:placetype":"venue"
},
  "geometry": {"coordinates":[-118.342938,34.093533],"type":"Point"}
}