{
  "type": "Feature",
  "properties": {
    "addr:full":"2244 S Santa Fe Ave Vista CA 92084",
    "addr:housenumber":"2244",
    "addr:postcode":"92084",
    "addr:street":"S Santa Fe Ave",
    "iso:country":"US",
    "sg:address":"2244 S Santa Fe Ave",
    "sg:city":"Vista",
    "sg:classifiers":[
        {
            "category":"Taxi",
            "type":"Transportation"
        }
    ],
    "sg:phone":"+1 760 599 4221",
    "sg:postcode":"92084",
    "sg:province":"CA",
    "sg:tags":[
        "taxicab"
    ],
    "wof:name":"Courtesy Cab",
    "wof:placetype":"venue"
},
  "geometry": {"coordinates":[-117.20649,33.169812],"type":"Point"}
}