{
  "type": "Feature",
  "properties": {
    "iso:country":"US",
    "sg:address":"394 Princeton Ln",
    "sg:city":"Danville",
    "sg:classifiers":[
        {
            "category":"Professional",
            "subcategory":"Computer Services",
            "type":"Services"
        }
    ],
    "sg:phone":"+1 925 837 5903",
    "sg:postcode":"94526",
    "sg:province":"CA",
    "sg:tags":[
        "systems-consultants",
        "designer",
        "data"
    ],
    "wof:name":"Grand Monde Trading Co Inc",
    "wof:placetype":"venue"
},
  "geometry": {"coordinates":[-121.98885199999999,37.812976],"type":"Point"}
}