{
  "type": "Feature",
  "properties": {
    "iso:country":"US",
    "sg:address":"176 Wikiup Dr",
    "sg:city":"Santa Rosa",
    "sg:classifiers":[
        {
            "category":"Social Services",
            "subcategory":"Adult Care",
            "type":"Services"
        }
    ],
    "sg:phone":"+1 707 576 0522",
    "sg:postcode":"95403",
    "sg:province":"CA",
    "sg:tags":[
        "foster"
    ],
    "wof:name":"Foster Family Svc",
    "wof:placetype":"venue"
},
  "geometry": {"coordinates":[-122.75828,38.508154],"type":"Point"}
}