{
  "type": "Feature",
  "properties": {
    "iso:country":"US",
    "sg:address":"1036 E Ave J",
    "sg:city":"Lancaster",
    "sg:classifiers":[
        {
            "category":"Building & Trades",
            "subcategory":"Landscaping Services",
            "type":"Services"
        }
    ],
    "sg:phone":"+1 661 945 8185",
    "sg:postcode":"93535",
    "sg:province":"CA",
    "sg:tags":[
        "lawn",
        "maintenance",
        "grounds"
    ],
    "wof:name":"Superior Gardening & Mntnc",
    "wof:placetype":"venue"
},
  "geometry": {"coordinates":[-118.11150000000001,34.689341],"type":"Point"}
}