{
  "type": "Feature",
  "properties": {
    "iso:country":"US",
    "sg:address":"2151 Airport Blvd",
    "sg:city":"San Jose",
    "sg:classifiers":[
        {
            "category":"Building & Trades",
            "subcategory":"Construction",
            "type":"Services"
        }
    ],
    "sg:phone":"+1 408 998 4915",
    "sg:postcode":"95112",
    "sg:province":"CA",
    "sg:tags":[
        "contractor"
    ],
    "wof:name":"Pinnacle",
    "wof:placetype":"venue"
},
  "geometry": {"coordinates":[-121.932462,37.372411],"type":"Point"}
}