{
  "type": "Feature",
  "properties": {
    "iso:country":"US",
    "sg:address":"2905 Homestead Rd",
    "sg:city":"Santa Clara",
    "sg:classifiers":[
        {
            "category":"Banks & Credit Unions",
            "subcategory":"Bank",
            "type":"Services"
        }
    ],
    "sg:phone":"+1 408 247 4713",
    "sg:postcode":"95051",
    "sg:province":"CA",
    "wof:name":"State Farm Bank",
    "wof:placetype":"venue"
},
  "geometry": {"coordinates":[-121.977997,37.338001],"type":"Point"}
}