{
  "type": "Feature",
  "properties": {
    "addr:full":"8633 Central Ave Orangevale CA 95662",
    "addr:housenumber":"8633",
    "addr:postcode":"95662",
    "addr:street":"Central Ave",
    "iso:country":"US",
    "sg:address":"8633 Central Ave",
    "sg:city":"Orangevale",
    "sg:classifiers":[
        {
            "category":"Building & Trades",
            "subcategory":"Landscaping Services",
            "type":"Services"
        }
    ],
    "sg:phone":"+1 916 955 2448",
    "sg:postcode":"95662",
    "sg:province":"CA",
    "sg:tags":[
        "tree",
        "stump",
        "grinding",
        "removal"
    ],
    "wof:name":"Anderson Tree Safety",
    "wof:placetype":"venue"
},
  "geometry": {"coordinates":[-121.238032,38.685871],"type":"Point"}
}