{
  "type": "Feature",
  "properties": {
    "addr:full":"5862 E Latonia St Laton CA 93242",
    "addr:housenumber":"5862",
    "addr:postcode":"93242",
    "addr:street":"E Latonia St",
    "iso:country":"US",
    "sg:address":"5862 E Latonia St",
    "sg:city":"Laton",
    "sg:classifiers":[
        {
            "category":"Autos & Motor Vehicles",
            "subcategory":"Auto Supplies",
            "type":"Retail Goods"
        }
    ],
    "sg:phone":"+1 559 923 0330",
    "sg:postcode":"93242",
    "sg:province":"CA",
    "sg:tags":[
        "tire"
    ],
    "wof:name":"Laton Tire Svc",
    "wof:placetype":"venue"
},
  "geometry": {"coordinates":[-119.69171799999999,36.431439],"type":"Point"}
}