{
  "type": "Feature",
  "properties": {
    "addr:full":"6474 Patterson Pass Rd Livermore CA 94550",
    "addr:housenumber":"6474",
    "addr:postcode":"94550",
    "addr:street":"Patterson Pass Rd",
    "iso:country":"US",
    "sg:address":"6474 Patterson Pass Rd",
    "sg:city":"Livermore",
    "sg:classifiers":[
        {
            "category":"Freight",
            "type":"Transportation"
        }
    ],
    "sg:phone":"+1 925 373 8200",
    "sg:postcode":"94550",
    "sg:province":"CA",
    "sg:tags":[
        "warehouse",
        "distribution",
        "center"
    ],
    "wof:name":"Castro-Krauses Industries",
    "wof:placetype":"venue"
},
  "geometry": {"coordinates":[-121.710273,37.695858],"type":"Point"}
}