{
  "type": "Feature",
  "properties": {
    "iso:country":"US",
    "sg:address":"9800 Valley Blvd",
    "sg:city":"Rosemead",
    "sg:classifiers":[
        {
            "category":"Professional",
            "subcategory":"Management & Consulting",
            "type":"Services"
        }
    ],
    "sg:phone":"+1 626 443 8488",
    "sg:postcode":"91770",
    "sg:province":"CA",
    "sg:tags":[
        "construction"
    ],
    "wof:name":"Q C Construction & Engineering",
    "wof:placetype":"venue"
},
  "geometry": {"coordinates":[-118.055752,34.080293],"type":"Point"}
}