{
  "type": "Feature",
  "properties": {
    "iso:country":"US",
    "sg:address":"1535 Termino Ave",
    "sg:city":"Long Beach",
    "sg:classifiers":[
        {
            "category":"Real Estate",
            "subcategory":"Real Estate Operator",
            "type":"Services"
        }
    ],
    "sg:phone":"+1 562 597 0830",
    "sg:postcode":"90804",
    "sg:province":"CA",
    "sg:tags":[
        "apartment"
    ],
    "wof:name":"Community Plaza Apartments",
    "wof:placetype":"venue"
},
  "geometry": {"coordinates":[-118.146004,33.786201],"type":"Point"}
}