{
  "type": "Feature",
  "properties": {
    "iso:country":"US",
    "sg:address":"2230 Stockton Blvd",
    "sg:city":"Sacramento",
    "sg:classifiers":[
        {
            "category":"Health Services",
            "subcategory":"Doctor",
            "type":"Services"
        }
    ],
    "sg:phone":"+1 916 734 0870",
    "sg:postcode":"95817",
    "sg:province":"CA",
    "sg:tags":[
        "psychiatrist"
    ],
    "wof:name":"Temporini Humberto MD Psychiatry",
    "wof:placetype":"venue"
},
  "geometry": {"coordinates":[-121.45879100000001,38.555477],"type":"Point"}
}