{
  "type": "Feature",
  "properties": {
    "addr:full":"95 S Market St Ste 300 San Jose CA 95109",
    "addr:housenumber":"95",
    "addr:postcode":"95109",
    "addr:street":"S Market St Ste 300",
    "iso:country":"US",
    "sg:address":"95 S Market St Ste 300",
    "sg:city":"San Jose",
    "sg:classifiers":[
        {
            "category":"Home & Garden",
            "subcategory":"Home Furnishings",
            "type":"Retail Goods"
        }
    ],
    "sg:phone":"+1 877 706 0384",
    "sg:postcode":"95109",
    "sg:province":"CA",
    "sg:tags":[
        "decor"
    ],
    "sg:website":"www.fjorn.com",
    "wof:name":"Fjorn Scandinavian",
    "wof:placetype":"venue"
},
  "geometry": {"coordinates":[-121.89076,37.33372],"type":"Point"}
}