{
  "type": "Feature",
  "properties": {
    "addr:full":"313 W D St Lemoore CA 93245",
    "addr:housenumber":"313",
    "addr:postcode":"93245",
    "addr:street":"W D St",
    "iso:country":"US",
    "sg:address":"313 W D St",
    "sg:city":"Lemoore",
    "sg:classifiers":[
        {
            "category":"Building & Trades",
            "subcategory":"Construction",
            "type":"Services"
        }
    ],
    "sg:phone":"+1 559 924 4202",
    "sg:postcode":"93245",
    "sg:province":"CA",
    "sg:tags":[
        "coping",
        "plastering",
        "tiling",
        "pool",
        "swimming"
    ],
    "wof:name":"All American Pool Co",
    "wof:placetype":"venue"
},
  "geometry": {"coordinates":[-119.785031,36.301687],"type":"Point"}
}