{
  "type": "Feature",
  "properties": {
    "addr:full":"PO Box 924 Los Angeles CA 90078",
    "addr:housenumber":"po",
    "addr:postcode":"90078",
    "addr:street":"Box 924",
    "iso:country":"US",
    "sg:address":"PO Box 924",
    "sg:city":"Los Angeles",
    "sg:classifiers":[
        {
            "category":"Building & Trades",
            "subcategory":"Cleaning & Sanitation",
            "type":"Services"
        }
    ],
    "sg:phone":"+1 310 271 5545",
    "sg:postcode":"90078",
    "sg:province":"CA",
    "sg:tags":[
        "carpet"
    ],
    "wof:name":"Chem-Dry by Calvin & Company",
    "wof:placetype":"venue"
},
  "geometry": {"coordinates":[-118.33123399999999,34.100155],"type":"Point"}
}