{
  "type": "Feature",
  "properties": {
    "addr:full":"534 W Main St El Centro CA 92243",
    "addr:housenumber":"534",
    "addr:postcode":"92243",
    "addr:street":"W Main St",
    "iso:country":"US",
    "sg:address":"534 W Main St",
    "sg:city":"El Centro",
    "sg:classifiers":[
        {
            "category":"Shopping",
            "subcategory":"Musical Instruments",
            "type":"Retail Goods"
        }
    ],
    "sg:phone":"+1 760 352 3363",
    "sg:postcode":"92243",
    "sg:province":"CA",
    "sg:website":"www.musicprime.com",
    "wof:name":"Clark Baker Music",
    "wof:placetype":"venue"
},
  "geometry": {"coordinates":[-115.555432,32.792909],"type":"Point"}
}