{
  "type": "Feature",
  "properties": {
    "iso:country":"US",
    "sg:address":"1625 Van Ness Ave",
    "sg:city":"San Francisco",
    "sg:classifiers":[
        {
            "category":"Community Center",
            "type":"Public Place"
        }
    ],
    "sg:phone":"+1 415 600 6200",
    "sg:postcode":"94109",
    "sg:province":"CA",
    "sg:tags":[
        "medical"
    ],
    "wof:name":"California Pacific Medical Center",
    "wof:placetype":"venue"
},
  "geometry": {"coordinates":[-122.42262599999999,37.790586],"type":"Point"}
}