{
  "type": "Feature",
  "properties": {
    "addr:full":"1155 Montauk Ln Ventura CA 93001",
    "addr:housenumber":"1155",
    "addr:postcode":"93001",
    "addr:street":"Montauk Ln",
    "iso:country":"US",
    "sg:address":"1155 Montauk Ln",
    "sg:city":"Ventura",
    "sg:classifiers":[
        {
            "category":"Building & Trades",
            "subcategory":"Construction",
            "type":"Services"
        }
    ],
    "sg:phone":"+1 805 653 5818",
    "sg:postcode":"93001",
    "sg:province":"CA",
    "sg:tags":[
        "textile",
        "painter"
    ],
    "wof:name":"Ruben's Homewash & Paint",
    "wof:placetype":"venue"
},
  "geometry": {"coordinates":[-119.27422900000001,34.263425],"type":"Point"}
}