{
  "type": "Feature",
  "properties": {
    "addr:full":"420 Miller Ave Mill Valley CA 94941",
    "addr:housenumber":"420",
    "addr:postcode":"94941",
    "addr:street":"Miller Ave",
    "iso:country":"US",
    "sg:address":"420 Miller Ave",
    "sg:city":"Mill Valley",
    "sg:classifiers":[
        {
            "category":"Real Estate",
            "subcategory":"Real Estate Agent",
            "type":"Services"
        }
    ],
    "sg:phone":"+1 415 388 9909",
    "sg:postcode":"94941",
    "sg:province":"CA",
    "wof:name":"House Properties LLC",
    "wof:placetype":"venue"
},
  "geometry": {"coordinates":[-122.535044,37.895644],"type":"Point"}
}