{
  "type": "Feature",
  "properties": {
    "addr:full":"150 Starlite Street South San Francisco CA 94080",
    "addr:housenumber":"150",
    "addr:postcode":"94080",
    "addr:street":"Starlite Street",
    "iso:country":"US",
    "sg:address":"150 Starlite Street",
    "sg:city":"South San Francisco",
    "sg:classifiers":[
        {
            "category":"Banks & Credit Unions",
            "subcategory":"Financial Services",
            "type":"Services"
        }
    ],
    "sg:phone":"+1 650 583 8670",
    "sg:postcode":"94080",
    "sg:province":"CA",
    "wof:name":"Magnum Financial Services",
    "wof:placetype":"venue"
},
  "geometry": {"coordinates":[-122.417017,37.649379],"type":"Point"}
}