{
  "type": "Feature",
  "properties": {
    "iso:country":"US",
    "sg:address":"844 Maple Ave",
    "sg:city":"Los Angeles",
    "sg:classifiers":[
        {
            "category":"Wholesale",
            "subcategory":"Apparel",
            "type":"Manufacturing & Wholesale Goods"
        }
    ],
    "sg:phone":"+1 213 489 7071",
    "sg:postcode":"90014",
    "sg:province":"CA",
    "sg:tags":[
        "fabric"
    ],
    "wof:name":"New York LA Fashion Inc",
    "wof:placetype":"venue"
},
  "geometry": {"coordinates":[-118.252076,34.040035],"type":"Point"}
}