{
  "type": "Feature",
  "properties": {
    "addr:full":"15922 Strathern St Van Nuys CA 91406",
    "addr:housenumber":"15922",
    "addr:postcode":"91406",
    "addr:street":"Strathern St",
    "iso:country":"US",
    "sg:address":"15922 Strathern St",
    "sg:city":"Van Nuys",
    "sg:classifiers":[
        {
            "category":"Wholesale",
            "subcategory":"Stationery",
            "type":"Manufacturing & Wholesale Goods"
        }
    ],
    "sg:phone":"+1 818 781 3288",
    "sg:postcode":"91406",
    "sg:province":"CA",
    "sg:tags":[
        "room",
        "shipping",
        "supply"
    ],
    "sg:website":"www.us-tl.com",
    "wof:name":"Us Tape & Label",
    "wof:placetype":"venue"
},
  "geometry": {"coordinates":[-118.48327399999999,34.215619],"type":"Point"}
}