{
  "type": "Feature",
  "properties": {
    "iso:country":"US",
    "sg:address":"10153 1/2 Riverside Dr. #465",
    "sg:city":"Toluca Lake",
    "sg:classifiers":[
        {
            "category":"Sports & Exercise",
            "subcategory":"Gym",
            "type":"Entertainment"
        }
    ],
    "sg:phone":"+1 818 980 7348",
    "sg:postcode":"91602",
    "sg:province":"CA",
    "sg:tags":[
        "pilate",
        "yoga"
    ],
    "sg:website":"www.balinyoga.com",
    "wof:name":"Balin Yoga",
    "wof:placetype":"venue"
},
  "geometry": {"coordinates":[-118.35253,34.152228],"type":"Point"}
}