{
  "type": "Feature",
  "properties": {
    "iso:country":"US",
    "sg:address":"535 Cashew Place",
    "sg:city":"Brentwood",
    "sg:classifiers":[
        {
            "category":"Education",
            "subcategory":"Preschool",
            "type":"Public Place"
        }
    ],
    "sg:phone":"+1 925 595 1282",
    "sg:postcode":"94513",
    "sg:province":"CA",
    "sg:website":"www.kidscornerpreschool.org",
    "wof:name":"Kids Corner Preschool",
    "wof:placetype":"venue"
},
  "geometry": {"coordinates":[-121.70092200000001,37.920077],"type":"Point"}
}