{
  "type": "Feature",
  "properties": {
    "addr:full":"1800 Monument Blvd Concord CA 94520",
    "addr:housenumber":"1800",
    "addr:postcode":"94520",
    "addr:street":"Monument Blvd",
    "iso:country":"US",
    "sg:address":"1800 Monument Blvd",
    "sg:city":"Concord",
    "sg:classifiers":[
        {
            "category":"Restaurant",
            "type":"Food & Drink"
        }
    ],
    "sg:menulink":"http://www.allmenus.com/ca/central-contra-costa/61260-sushi-momoyama/menu/",
    "sg:phone":"+1 925 686 1888",
    "sg:postcode":"94520",
    "sg:province":"CA",
    "sg:tags":[
        "sushi",
        "asian"
    ],
    "wof:name":"Sushi Momoyama",
    "wof:placetype":"venue"
},
  "geometry": {"coordinates":[-122.040622,37.955128],"type":"Point"}
}