{
  "type": "Feature",
  "properties": {
    "addr:full":"5620 Greens Dr Riverside CA 92509",
    "addr:housenumber":"5620",
    "addr:postcode":"92509",
    "addr:street":"Greens Dr",
    "iso:country":"US",
    "sg:address":"5620 Greens Dr",
    "sg:city":"Riverside",
    "sg:classifiers":[
        {
            "category":"Freight",
            "type":"Transportation"
        }
    ],
    "sg:phone":"+1 951 681 7996",
    "sg:postcode":"92509",
    "sg:province":"CA",
    "sg:tags":[
        "operator",
        "local",
        "trucking"
    ],
    "wof:name":"Irish Malone Trucking Inc",
    "wof:placetype":"venue"
},
  "geometry": {"coordinates":[-117.460528,33.985391],"type":"Point"}
}