{
  "type": "Feature",
  "properties": {
    "iso:country":"US",
    "sg:address":"7561 State Hwy 20",
    "sg:city":"Smartville",
    "sg:classifiers":[
        {
            "category":"Wholesale",
            "subcategory":"Construction Materials",
            "type":"Manufacturing & Wholesale Goods"
        }
    ],
    "sg:phone":"+1 530 639 2408",
    "sg:postcode":"95977",
    "sg:province":"CA",
    "sg:tags":[
        "rock"
    ],
    "wof:name":"Parks Bar Quarry",
    "wof:placetype":"venue"
},
  "geometry": {"coordinates":[-121.332846,39.217938],"type":"Point"}
}