{
  "type": "Feature",
  "properties": {
    "addr:full":"6968 Campus Dr Fullerton CA 92831",
    "addr:housenumber":"6968",
    "addr:postcode":"92831",
    "addr:street":"Campus Dr",
    "iso:country":"US",
    "sg:address":"6968 Campus Dr",
    "sg:city":"Fullerton",
    "sg:classifiers":[
        {
            "category":"Real Estate",
            "subcategory":"Real Estate Operator",
            "type":"Services"
        }
    ],
    "sg:phone":"+1 714 773 0505",
    "sg:postcode":"92831",
    "sg:province":"CA",
    "sg:tags":[
        "apartment"
    ],
    "wof:name":"Castlewood Park Apartments",
    "wof:placetype":"venue"
},
  "geometry": {"coordinates":[-117.889999,33.877701],"type":"Point"}
}