{
  "type": "Feature",
  "properties": {
    "iso:country":"US",
    "sg:address":"3417 Brunswick St",
    "sg:city":"Modesto",
    "sg:classifiers":[
        {
            "category":"Professional",
            "type":"Services"
        }
    ],
    "sg:phone":"+1 209 523 6572",
    "sg:postcode":"95350",
    "sg:province":"CA",
    "wof:name":"Ben W Fugate",
    "wof:placetype":"venue"
},
  "geometry": {"coordinates":[-121.004151,37.687192],"type":"Point"}
}