{
  "type": "Feature",
  "properties": {
    "iso:country":"US",
    "sg:address":"423 Healdsburg Ave",
    "sg:city":"Healdsburg",
    "sg:classifiers":[
        {
            "category":"Shopping",
            "subcategory":"Florist",
            "type":"Retail Goods"
        }
    ],
    "sg:phone":"+1 707 433 6318",
    "sg:postcode":"95448",
    "sg:province":"CA",
    "sg:website":"http://www.healdsburgcountrydaisy.com",
    "wof:name":"Healdsburg Country Daisy",
    "wof:placetype":"venue"
},
  "geometry": {"coordinates":[-122.87146199999999,38.612923],"type":"Point"}
}