{
  "type": "Feature",
  "properties": {
    "addr:full":"114 E Market St Long Beach CA 90805",
    "addr:housenumber":"114",
    "addr:postcode":"90805",
    "addr:street":"E Market St",
    "iso:country":"US",
    "sg:address":"114 E Market St",
    "sg:city":"Long Beach",
    "sg:classifiers":[
        {
            "category":"Food & Beverages",
            "subcategory":"Groceries & Convenience Stores",
            "type":"Retail Goods"
        }
    ],
    "sg:phone":"+1 562 423 6194",
    "sg:postcode":"90805",
    "sg:province":"CA",
    "wof:name":"Best Mini Market",
    "wof:placetype":"venue"
},
  "geometry": {"coordinates":[-118.193001,33.854198],"type":"Point"}
}