{
  "type": "Feature",
  "properties": {
    "iso:country":"US",
    "sg:address":"589 Mendocino Ave",
    "sg:city":"Santa Rosa",
    "sg:classifiers":[
        {
            "category":"Professional",
            "subcategory":"Lawyer & Legal Services",
            "type":"Services"
        }
    ],
    "sg:phone":"+1 707 573 0444",
    "sg:postcode":"95401",
    "sg:province":"CA",
    "sg:tags":[
        "attorney"
    ],
    "wof:name":"Harry J Dowd",
    "wof:placetype":"venue"
},
  "geometry": {"coordinates":[-122.716662,38.443969],"type":"Point"}
}