{
  "type": "Feature",
  "properties": {
    "addr:full":"1550 Bryant St San Francisco CA 94107",
    "addr:housenumber":"1550",
    "addr:postcode":"94107",
    "addr:street":"Bryant St",
    "iso:country":"US",
    "sg:address":"1550 Bryant St",
    "sg:city":"San Francisco",
    "sg:classifiers":[
        {
            "category":"Autos & Motor Vehicles",
            "subcategory":"Automobile Sales",
            "type":"Retail Goods"
        }
    ],
    "sg:phone":"+1 888 464 1919",
    "sg:postcode":"94107",
    "sg:province":"CA",
    "sg:tags":[
        "car"
    ],
    "wof:name":"Cash for Cars",
    "wof:placetype":"venue"
},
  "geometry": {"coordinates":[-122.411142,37.767562],"type":"Point"}
}