{
  "type": "Feature",
  "properties": {
    "addr:full":"6195 University Ave San Diego CA 92115",
    "addr:housenumber":"6195",
    "addr:postcode":"92115",
    "addr:street":"University Ave",
    "iso:country":"US",
    "sg:address":"6195 University Ave",
    "sg:city":"San Diego",
    "sg:classifiers":[
        {
            "category":"Restaurant",
            "type":"Food & Drink"
        },
        {
            "category":"Bars & Pubs",
            "subcategory":"Nightclub",
            "type":"Food & Drink"
        }
    ],
    "sg:phone":"+1 619 544 0807",
    "sg:postcode":"92115",
    "sg:province":"CA",
    "sg:tags":[
        "nightlife"
    ],
    "sg:website":"www.collegerocksbarandgrill.com",
    "wof:name":"College Rocks",
    "wof:placetype":"venue"
},
  "geometry": {"coordinates":[-117.062348,32.752967],"type":"Point"}
}