{
  "type": "Feature",
  "properties": {
    "iso:country":"US",
    "sg:address":"2136 Griffin Dr",
    "sg:city":"Vallejo",
    "sg:classifiers":[
        {
            "category":"Banks & Credit Unions",
            "subcategory":"Bank",
            "type":"Services"
        }
    ],
    "sg:phone":"+1 707 425 5446",
    "sg:postcode":"94589",
    "sg:province":"CA",
    "sg:tags":[
        "loan",
        "processing",
        "mortgage"
    ],
    "wof:name":"Independent Processing",
    "wof:placetype":"venue"
},
  "geometry": {"coordinates":[-122.2339,38.145381],"type":"Point"}
}