{
  "type": "Feature",
  "properties": {
    "iso:country":"US",
    "sg:address":"3319 Julliard Dr",
    "sg:city":"Sacramento",
    "sg:classifiers":[
        {
            "category":"Building & Trades",
            "subcategory":"Construction",
            "type":"Services"
        }
    ],
    "sg:phone":"+1 916 381 6518",
    "sg:postcode":"95826",
    "sg:province":"CA",
    "sg:tags":[
        "repairing",
        "remodeling",
        "contractor"
    ],
    "wof:name":"Eberle Remodeling",
    "wof:placetype":"venue"
},
  "geometry": {"coordinates":[-121.392302,38.547664],"type":"Point"}
}