{
  "type": "Feature",
  "properties": {
    "addr:full":"6640 E Pacific Coast Hwy Long Beach CA 90803",
    "addr:housenumber":"6640",
    "addr:postcode":"90803",
    "addr:street":"E Pacific Coast Hwy",
    "iso:country":"US",
    "sg:address":"6640 E Pacific Coast Hwy",
    "sg:city":"Long Beach",
    "sg:classifiers":[
        {
            "category":"Restaurant",
            "type":"Food & Drink"
        }
    ],
    "sg:phone":"+1 562 795 5889",
    "sg:postcode":"90803",
    "sg:province":"CA",
    "wof:name":"Hanabi Roll & Grill",
    "wof:placetype":"venue"
},
  "geometry": {"coordinates":[-118.107585,33.754186],"type":"Point"}
}