{
  "type": "Feature",
  "properties": {
    "iso:country":"US",
    "sg:address":"1572 Barton Rd",
    "sg:city":"Redlands",
    "sg:classifiers":[
        {
            "category":"Education",
            "subcategory":"School",
            "type":"Public Place"
        }
    ],
    "sg:phone":"+1 909 335 9643",
    "sg:postcode":"92373",
    "sg:province":"CA",
    "sg:tags":[
        "academic",
        "special"
    ],
    "wof:name":"Loma Linda Kumon Math Ctr",
    "wof:placetype":"venue"
},
  "geometry": {"coordinates":[-117.204295,34.046564],"type":"Point"}
}