{
  "type": "Feature",
  "properties": {
    "addr:full":"227 West.Valley Boulevard. #118-B San Gabriel CA 91776",
    "addr:housenumber":"227",
    "addr:postcode":"91776",
    "addr:street":"West.Valley Boulevard. # 118-B",
    "iso:country":"US",
    "sg:address":"227 West.Valley Boulevard. #118-B",
    "sg:city":"San Gabriel",
    "sg:classifiers":[
        {
            "category":"Fast Food",
            "type":"Food & Drink"
        }
    ],
    "sg:phone":"+1 626 289 3550",
    "sg:postcode":"91776",
    "sg:province":"CA",
    "sg:tags":[
        "chicken",
        "wing"
    ],
    "wof:name":"Coo Coo Chicken",
    "wof:placetype":"venue"
},
  "geometry": {"coordinates":[-118.102678,34.07962],"type":"Point"}
}