{
  "type": "Feature",
  "properties": {
    "iso:country":"US",
    "sg:address":"4701 Franklin Blvd",
    "sg:city":"Sacramento",
    "sg:classifiers":[
        {
            "category":"Shopping",
            "type":"Retail Goods"
        }
    ],
    "sg:phone":"+1 916 456 1965",
    "sg:postcode":"95820",
    "sg:province":"CA",
    "sg:tags":[
        "merchandise"
    ],
    "wof:name":"Rahat Buksh",
    "wof:placetype":"venue"
},
  "geometry": {"coordinates":[-121.473747,38.532749],"type":"Point"}
}