{
  "type": "Feature",
  "properties": {
    "addr:full":"1130 N Lincoln Way Galt CA 95632",
    "addr:housenumber":"1130",
    "addr:postcode":"95632",
    "addr:street":"N Lincoln Way",
    "iso:country":"US",
    "sg:address":"1130 N Lincoln Way",
    "sg:city":"Galt",
    "sg:classifiers":[
        {
            "category":"Retail",
            "subcategory":"Auto Repair",
            "type":"Services"
        }
    ],
    "sg:phone":"+1 209 745 2822",
    "sg:postcode":"95632",
    "sg:province":"CA",
    "sg:tags":[
        "repairing",
        "automobile"
    ],
    "wof:name":"Japanese Automotive Svc",
    "wof:placetype":"venue"
},
  "geometry": {"coordinates":[-121.304013,38.274099],"type":"Point"}
}