{
  "type": "Feature",
  "properties": {
    "iso:country":"US",
    "sg:address":"16800 Edwards Rd",
    "sg:city":"Cerritos",
    "sg:classifiers":[
        {
            "category":"Professional",
            "subcategory":"Computer Services",
            "type":"Services"
        }
    ],
    "sg:postcode":"90703",
    "sg:province":"CA",
    "sg:website":"http://www.farfetch.com",
    "wof:name":"Farfetch",
    "wof:placetype":"venue"
},
  "geometry": {"coordinates":[-118.03439,33.879246],"type":"Point"}
}