{
  "type": "Feature",
  "properties": {
    "addr:full":"447 Sutter St San Francisco CA 94108",
    "addr:housenumber":"447",
    "addr:postcode":"94108",
    "addr:street":"Sutter St",
    "iso:country":"US",
    "sg:address":"447 Sutter St",
    "sg:city":"San Francisco",
    "sg:classifiers":[
        {
            "category":"Travel",
            "subcategory":"Travel Agent",
            "type":"Entertainment"
        }
    ],
    "sg:phone":"+1 415 981 0540",
    "sg:postcode":"94108",
    "sg:province":"CA",
    "sg:tags":[
        "agency",
        "bureau"
    ],
    "wof:name":"Pacific Air Leisure Svc",
    "wof:placetype":"venue"
},
  "geometry": {"coordinates":[-122.407184,37.789348],"type":"Point"}
}