{
  "type": "Feature",
  "properties": {
    "iso:country":"US",
    "sg:address":"125 N Tustin St",
    "sg:city":"Orange",
    "sg:classifiers":[
        {
            "category":"Manufacturing",
            "subcategory":"Printing",
            "type":"Manufacturing & Wholesale Goods"
        }
    ],
    "sg:phone":"+1 714 771 6630",
    "sg:postcode":"92867",
    "sg:province":"CA",
    "sg:tags":[
        "printer"
    ],
    "wof:name":"ADS Printing",
    "wof:placetype":"venue"
},
  "geometry": {"coordinates":[-117.835632,33.791288],"type":"Point"}
}