{
  "type": "Feature",
  "properties": {
    "addr:full":"346 Fair Oaks St San Francisco CA 94110",
    "addr:housenumber":"346",
    "addr:postcode":"94110",
    "addr:street":"Fair Oaks St",
    "iso:country":"US",
    "sg:address":"346 Fair Oaks St",
    "sg:city":"San Francisco",
    "sg:classifiers":[
        {
            "category":"Arts & Performance",
            "subcategory":"Arts Center",
            "type":"Entertainment"
        }
    ],
    "sg:phone":"+1 415 285 4526",
    "sg:postcode":"94110",
    "sg:province":"CA",
    "wof:name":"Hell on Wheels (Fear Goes Mobile)",
    "wof:placetype":"venue"
},
  "geometry": {"coordinates":[-122.424227,37.751127],"type":"Point"}
}