{
  "type": "Feature",
  "properties": {
    "iso:country":"US",
    "sg:address":"11117 Hartsook St",
    "sg:city":"North Hollywood",
    "sg:classifiers":[
        {
            "category":"Real Estate",
            "subcategory":"Real Estate Operator",
            "type":"Services"
        }
    ],
    "sg:phone":"+1 818 760 7491",
    "sg:postcode":"91601",
    "sg:province":"CA",
    "sg:tags":[
        "apartment"
    ],
    "wof:name":"Teixeira Juscena",
    "wof:placetype":"venue"
},
  "geometry": {"coordinates":[-118.372394,34.164013],"type":"Point"}
}