{
  "type": "Feature",
  "properties": {
    "addr:full":"2544 Etna St Berkeley CA 94704",
    "addr:housenumber":"2544",
    "addr:postcode":"94704",
    "addr:street":"Etna St",
    "iso:country":"US",
    "sg:address":"2544 Etna St",
    "sg:city":"Berkeley",
    "sg:classifiers":[
        {
            "category":"Real Estate",
            "subcategory":"Developer",
            "type":"Services"
        }
    ],
    "sg:phone":"+1 510 644 4442",
    "sg:postcode":"94704",
    "sg:province":"CA",
    "wof:name":"Daniels Development",
    "wof:placetype":"venue"
},
  "geometry": {"coordinates":[-122.252768,37.864811],"type":"Point"}
}