{
  "type": "Feature",
  "properties": {
    "addr:full":"400 US Hwy 101 Crescent City CA 95531",
    "addr:housenumber":"400",
    "addr:postcode":"95531",
    "addr:street":"Us Hwy 101 Crescent",
    "iso:country":"US",
    "sg:address":"400 US Hwy 101",
    "sg:city":"Crescent City",
    "sg:classifiers":[
        {
            "category":"Restaurant",
            "type":"Food & Drink"
        }
    ],
    "sg:phone":"+1 707 464 5712",
    "sg:postcode":"95531",
    "sg:province":"CA",
    "wof:name":"Toreros Famosos Mexican Rstrnt",
    "wof:placetype":"venue"
},
  "geometry": {"coordinates":[-124.194659,41.75593],"type":"Point"}
}