{
  "type": "Feature",
  "properties": {
    "addr:full":"5497 Claremont Ave Apt A Oakland CA 94618",
    "addr:housenumber":"5497",
    "addr:postcode":"94618",
    "addr:street":"Claremont Ave Apt A",
    "iso:country":"US",
    "sg:address":"5497 Claremont Ave Apt A",
    "sg:city":"Oakland",
    "sg:classifiers":[
        {
            "category":"Personal",
            "type":"Services"
        }
    ],
    "sg:phone":"+1 510 552 1701",
    "sg:postcode":"94618",
    "sg:province":"CA",
    "sg:tags":[
        "home"
    ],
    "wof:name":"Richter Works",
    "wof:placetype":"venue"
},
  "geometry": {"coordinates":[-122.25748299999999,37.843452],"type":"Point"}
}