{
  "type": "Feature",
  "properties": {
    "addr:full":"1749 Bonaire Cir Stockton CA 95210",
    "addr:housenumber":"1749",
    "addr:postcode":"95210",
    "addr:street":"Bonaire Cir",
    "iso:country":"US",
    "sg:address":"1749 Bonaire Cir",
    "sg:city":"Stockton",
    "sg:classifiers":[
        {
            "category":"Professional",
            "type":"Services"
        }
    ],
    "sg:phone":"+1 209 477 5487",
    "sg:postcode":"95210",
    "sg:province":"CA",
    "wof:name":"Cnc Framed Art & Mirrors Inc",
    "wof:placetype":"venue"
},
  "geometry": {"coordinates":[-121.284058,37.99657],"type":"Point"}
}