{
  "type": "Feature",
  "properties": {
    "addr:full":"3450 Wilshire Blvd Los Angeles CA 90010",
    "addr:housenumber":"3450",
    "addr:postcode":"90010",
    "addr:street":"Wilshire Blvd",
    "iso:country":"US",
    "sg:address":"3450 Wilshire Blvd",
    "sg:city":"Los Angeles",
    "sg:classifiers":[
        {
            "category":"Banks & Credit Unions",
            "subcategory":"Financial Services",
            "type":"Services"
        }
    ],
    "sg:phone":"+1 213 632 1860",
    "sg:postcode":"90010",
    "sg:province":"CA",
    "sg:tags":[
        "broker",
        "mortgage"
    ],
    "wof:name":"Ourhouse-Westwind Mortgage",
    "wof:placetype":"venue"
},
  "geometry": {"coordinates":[-118.299004,34.061798],"type":"Point"}
}