{
  "type": "Feature",
  "properties": {
    "addr:full":"1630 E Hatch Rd Modesto CA 95351",
    "addr:housenumber":"1630",
    "addr:postcode":"ca 95351",
    "addr:street":"E Hatch Rd",
    "iso:country":"US",
    "sg:address":"1630 E Hatch Rd",
    "sg:city":"Modesto",
    "sg:classifiers":[
        {
            "category":"Shopping",
            "subcategory":"Music",
            "type":"Retail Goods"
        }
    ],
    "sg:phone":"+1 209 537 2932",
    "sg:postcode":"95351",
    "sg:province":"CA",
    "sg:tags":[
        "video",
        "disc",
        "tape",
        "cassette"
    ],
    "wof:name":"Video King",
    "wof:placetype":"venue"
},
  "geometry": {"coordinates":[-120.968234,37.609164],"type":"Point"}
}