{
  "type": "Feature",
  "properties": {
    "iso:country":"US",
    "sg:address":"650 N Euclid St",
    "sg:city":"Anaheim",
    "sg:classifiers":[
        {
            "category":"Food & Beverages",
            "subcategory":"Groceries & Convenience Stores",
            "type":"Retail Goods"
        }
    ],
    "sg:phone":"+1 714 533 3761",
    "sg:postcode":"92801",
    "sg:province":"CA",
    "wof:name":"El Super",
    "wof:placetype":"venue"
},
  "geometry": {"coordinates":[-117.94156099999999,33.840727],"type":"Point"}
}