{
  "type": "Feature",
  "properties": {
    "iso:country":"US",
    "sg:address":"8601 Greenback Ln",
    "sg:city":"Orangevale",
    "sg:classifiers":[
        {
            "category":"Insurance",
            "subcategory":"Hazard Insurance",
            "type":"Services"
        }
    ],
    "sg:phone":"+1 916 987 8991",
    "sg:postcode":"95662",
    "sg:province":"CA",
    "sg:tags":[
        "commercial",
        "business"
    ],
    "wof:name":"Welk Insurance Agency Inc",
    "wof:placetype":"venue"
},
  "geometry": {"coordinates":[-121.239693,38.678581],"type":"Point"}
}