{
  "type": "Feature",
  "properties": {
    "addr:full":"3519 McDonald Ave Modesto CA 95358",
    "addr:housenumber":"3519",
    "addr:postcode":"ca 95358",
    "addr:street":"Mcdonald Ave",
    "iso:country":"US",
    "sg:address":"3519 McDonald Ave",
    "sg:city":"Modesto",
    "sg:classifiers":[
        {
            "category":"Government",
            "subcategory":"Office",
            "type":"Public Place"
        }
    ],
    "sg:phone":"+1 209 527 4900",
    "sg:postcode":"95358",
    "sg:province":"CA",
    "sg:tags":[
        "city",
        "program"
    ],
    "wof:name":"Modesto Transit Svc",
    "wof:placetype":"venue"
},
  "geometry": {"coordinates":[-121.049691,37.663852],"type":"Point"}
}