{
  "type": "Feature",
  "properties": {
    "addr:full":"10951 W Pico Blvd Los Angeles CA 90064",
    "addr:housenumber":"10951",
    "addr:postcode":"90064",
    "addr:street":"W Pico Blvd",
    "iso:country":"US",
    "sg:address":"10951 W Pico Blvd",
    "sg:city":"Los Angeles",
    "sg:classifiers":[
        {
            "category":"Arts & Performance",
            "subcategory":"Theater",
            "type":"Entertainment"
        }
    ],
    "sg:phone":"+1 310 820 6169",
    "sg:postcode":"90064",
    "sg:province":"CA",
    "sg:tags":[
        "theatrical",
        "manager",
        "producer"
    ],
    "wof:name":"Sheila Manning Casting",
    "wof:placetype":"venue"
},
  "geometry": {"coordinates":[-118.430419,34.039198],"type":"Point"}
}