{
  "type": "Feature",
  "properties": {
    "addr:full":"2785 Teagarden St San Leandro CA 94577",
    "addr:housenumber":"2785",
    "addr:postcode":"94577",
    "addr:street":"Teagarden St",
    "iso:country":"US",
    "sg:address":"2785 Teagarden St",
    "sg:city":"San Leandro",
    "sg:classifiers":[
        {
            "category":"Personal",
            "type":"Services"
        },
        {
            "category":"Shopping",
            "type":"Retail Goods"
        }
    ],
    "sg:phone":"+1 510 841 7577",
    "sg:postcode":"94577",
    "sg:province":"CA",
    "sg:tags":[
        "local"
    ],
    "wof:name":"Builders Source",
    "wof:placetype":"venue"
},
  "geometry": {"coordinates":[-122.157937,37.70565],"type":"Point"}
}