{
  "type": "Feature",
  "properties": {
    "addr:full":"2107 Van Ness Ave San Francisco CA 94109",
    "addr:housenumber":"2107",
    "addr:postcode":"94109",
    "addr:street":"Van Ness Ave",
    "iso:country":"US",
    "sg:address":"2107 Van Ness Ave",
    "sg:city":"San Francisco",
    "sg:classifiers":[
        {
            "category":"Health Services",
            "subcategory":"Health Practitioner",
            "type":"Services"
        }
    ],
    "sg:phone":"+1 415 664 3463",
    "sg:postcode":"94109",
    "sg:province":"CA",
    "sg:tags":[
        "hypnotist"
    ],
    "wof:name":"Finemind Hypnotherapy",
    "wof:placetype":"venue"
},
  "geometry": {"coordinates":[-122.423507,37.795717],"type":"Point"}
}