{
  "type": "Feature",
  "properties": {
    "iso:country":"US",
    "sg:address":"601 W Florinda St",
    "sg:city":"Hanford",
    "sg:classifiers":[
        {
            "category":"Education",
            "subcategory":"School",
            "type":"Public Place"
        }
    ],
    "sg:phone":"+1 559 585 2334",
    "sg:postcode":"93230",
    "sg:province":"CA",
    "sg:website":"www.hesd.k12.ca.us",
    "wof:name":"Wilson Junior High School",
    "wof:placetype":"venue"
},
  "geometry": {"coordinates":[-119.655082,36.334849],"type":"Point"}
}