{
  "type": "Feature",
  "properties": {
    "addr:full":"1393 Solano Ave Albany CA 94706",
    "addr:housenumber":"1393",
    "addr:postcode":"94706",
    "addr:street":"Solano Ave",
    "iso:country":"US",
    "sg:address":"1393 Solano Ave",
    "sg:city":"Albany",
    "sg:classifiers":[
        {
            "category":"Personal",
            "subcategory":"Beauty Salon",
            "type":"Services"
        }
    ],
    "sg:phone":"+1 510 559 1850",
    "sg:postcode":"94706",
    "sg:province":"CA",
    "wof:name":"Marcia Walden Skincare & Make",
    "wof:placetype":"venue"
},
  "geometry": {"coordinates":[-122.290707,37.890783],"type":"Point"}
}