{
  "type": "Feature",
  "properties": {
    "iso:country":"US",
    "sg:address":"810 3rd St",
    "sg:city":"Orland",
    "sg:classifiers":[
        {
            "category":"Building & Trades",
            "subcategory":"Cleaning & Sanitation",
            "type":"Services"
        }
    ],
    "sg:phone":"+1 530 865 2508",
    "sg:postcode":"95963",
    "sg:province":"CA",
    "sg:tags":[
        "window"
    ],
    "wof:name":"Lopez Professional Window",
    "wof:placetype":"venue"
},
  "geometry": {"coordinates":[-122.192919,39.745957],"type":"Point"}
}