{
  "type": "Feature",
  "properties": {
    "addr:full":"313 Central Ave Shafter CA 93263",
    "addr:housenumber":"313",
    "addr:postcode":"93263",
    "addr:street":"Central Ave",
    "iso:country":"US",
    "sg:address":"313 Central Ave",
    "sg:city":"Shafter",
    "sg:classifiers":[
        {
            "category":"Fast Food",
            "type":"Food & Drink"
        },
        {
            "category":"Restaurant",
            "type":"Food & Drink"
        }
    ],
    "sg:phone":"+1 661 746 9135",
    "sg:postcode":"93263",
    "sg:province":"CA",
    "sg:tags":[
        "hot",
        "hamburger",
        "dog"
    ],
    "wof:name":"Burger Factory",
    "wof:placetype":"venue"
},
  "geometry": {"coordinates":[-119.275448,35.502049],"type":"Point"}
}