{
  "type": "Feature",
  "properties": {
    "addr:full":"1281 Palma Vista Ct Escondido CA 92025",
    "addr:housenumber":"1281",
    "addr:postcode":"92025",
    "addr:street":"Palma Vista Ct",
    "iso:country":"US",
    "sg:address":"1281 Palma Vista Ct",
    "sg:city":"Escondido",
    "sg:classifiers":[
        {
            "category":"Building & Trades",
            "subcategory":"Landscaping Services",
            "type":"Services"
        }
    ],
    "sg:phone":"+1 760 741 9763",
    "sg:postcode":"92025",
    "sg:province":"CA",
    "wof:name":"Z & T Kirovski Inc",
    "wof:placetype":"venue"
},
  "geometry": {"coordinates":[-117.04127800000001,33.097773],"type":"Point"}
}