{
  "type": "Feature",
  "properties": {
    "iso:country":"US",
    "sg:address":"150 S 1st",
    "sg:city":"Santa Clara",
    "sg:classifiers":[
        {
            "category":"Utilities",
            "type":"Services"
        }
    ],
    "sg:phone":"+1 408 200 5380",
    "sg:postcode":"95054",
    "sg:province":"CA",
    "sg:tags":[
        "provider",
        "internet"
    ],
    "wof:name":"Pronto Networks",
    "wof:placetype":"venue"
},
  "geometry": {"coordinates":[-121.955727,37.399961],"type":"Point"}
}