{
  "type": "Feature",
  "properties": {
    "iso:country":"US",
    "sg:address":"316 Manzanita Dr",
    "sg:city":"Chester",
    "sg:classifiers":[
        {
            "category":"Communications",
            "subcategory":"Radio Station",
            "type":"Services"
        }
    ],
    "sg:phone":"+1 530 259 4141",
    "sg:postcode":"96020",
    "sg:province":"CA",
    "sg:tags":[
        "broadcast"
    ],
    "wof:name":"Almanor Tv & Fm Association",
    "wof:placetype":"venue"
},
  "geometry": {"coordinates":[-121.202957,40.237167],"type":"Point"}
}