{
  "type": "Feature",
  "properties": {
    "iso:country":"US",
    "sg:address":"10730 Henderson Rd",
    "sg:city":"Ventura",
    "sg:classifiers":[
        {
            "category":"Organizations",
            "subcategory":"Non-profit Organization",
            "type":"Services"
        }
    ],
    "sg:phone":"+1 805 647 1141",
    "sg:postcode":"93004",
    "sg:province":"CA",
    "sg:tags":[
        "social"
    ],
    "wof:name":"Easter Seals Tri-Counties",
    "wof:placetype":"venue"
},
  "geometry": {"coordinates":[-119.159109,34.287427],"type":"Point"}
}