{
  "type": "Feature",
  "properties": {
    "addr:full":"2812 Clayton Rd Concord CA 94519",
    "addr:housenumber":"2812",
    "addr:postcode":"94519",
    "addr:street":"Clayton Rd",
    "iso:country":"US",
    "sg:address":"2812 Clayton Rd",
    "sg:city":"Concord",
    "sg:classifiers":[
        {
            "category":"Wholesale",
            "subcategory":"Hardware",
            "type":"Manufacturing & Wholesale Goods"
        },
        {
            "category":"Building & Trades",
            "subcategory":"Plumbing",
            "type":"Services"
        }
    ],
    "sg:phone":"+1 925 634 0210",
    "sg:postcode":"94519",
    "sg:province":"CA",
    "sg:tags":[
        "household",
        "furnace",
        "contractor"
    ],
    "wof:name":"Rudy's Service",
    "wof:placetype":"venue"
},
  "geometry": {"coordinates":[-122.025142,37.974495],"type":"Point"}
}