{
  "type": "Feature",
  "properties": {
    "iso:country":"US",
    "sg:address":"21916 Moneta Ave",
    "sg:city":"Carson",
    "sg:classifiers":[
        {
            "category":"Organizations",
            "subcategory":"Religious Organization",
            "type":"Services"
        }
    ],
    "sg:phone":"+1 310 835 4465",
    "sg:postcode":"90745",
    "sg:province":"CA",
    "sg:tags":[
        "church"
    ],
    "wof:name":"Keystone Assembly Of God",
    "wof:placetype":"venue"
},
  "geometry": {"coordinates":[-118.281606,33.828241],"type":"Point"}
}