{
  "type": "Feature",
  "properties": {
    "iso:country":"US",
    "sg:address":"309 N Yale Ave",
    "sg:city":"Claremont",
    "sg:classifiers":[
        {
            "category":"Shopping",
            "subcategory":"Clothing, Apparel, & Fashions",
            "type":"Retail Goods"
        }
    ],
    "sg:phone":"+1 909 621 4193",
    "sg:postcode":"91711",
    "sg:province":"CA",
    "sg:tags":[
        "gift"
    ],
    "wof:name":"Tattle Tails",
    "wof:placetype":"venue"
},
  "geometry": {"coordinates":[-117.71795,34.097528],"type":"Point"}
}