{
  "type": "Feature",
  "properties": {
    "iso:country":"US",
    "sg:address":"6280 Clay St",
    "sg:city":"Riverside",
    "sg:classifiers":[
        {
            "category":"Social Services",
            "subcategory":"Adult Care",
            "type":"Services"
        }
    ],
    "sg:phone":"+1 951 332 6079",
    "sg:postcode":"92509",
    "sg:province":"CA",
    "sg:tags":[
        "centers-adult",
        "day"
    ],
    "wof:name":"Eloise Habekost",
    "wof:placetype":"venue"
},
  "geometry": {"coordinates":[-117.46221199999999,33.975284],"type":"Point"}
}