{
  "type": "Feature",
  "properties": {
    "iso:country":"US",
    "sg:address":"4905 E Hunter Ave",
    "sg:city":"Anaheim",
    "sg:classifiers":[
        {
            "category":"Manufacturing",
            "subcategory":"Chemicals & Compounds",
            "type":"Manufacturing & Wholesale Goods"
        }
    ],
    "sg:phone":"+1 714 701 3900",
    "sg:postcode":"92807",
    "sg:province":"CA",
    "sg:tags":[
        "industrial",
        "organic"
    ],
    "sg:website":"www.innovativeorganics.com",
    "wof:name":"Innovative Organics",
    "wof:placetype":"venue"
},
  "geometry": {"coordinates":[-117.80669899999999,33.863423],"type":"Point"}
}