{
  "type": "Feature",
  "properties": {
    "addr:full":"829 N Oakland Ave Pasadena CA 91104",
    "addr:housenumber":"829",
    "addr:postcode":"91104",
    "addr:street":"N Oakland Ave",
    "iso:country":"US",
    "sg:address":"829 N Oakland Ave",
    "sg:city":"Pasadena",
    "sg:classifiers":[
        {
            "category":"Professional",
            "type":"Services"
        }
    ],
    "sg:phone":"+1 626 793 2512",
    "sg:postcode":"91104",
    "sg:province":"CA",
    "wof:name":"Krikor Orjanian",
    "wof:placetype":"venue"
},
  "geometry": {"coordinates":[-118.140377,34.161014],"type":"Point"}
}