{
  "type": "Feature",
  "properties": {
    "addr:full":"20540 Superior St Chatsworth CA 91311",
    "addr:housenumber":"20540",
    "addr:postcode":"91311",
    "addr:street":"Superior St",
    "iso:country":"US",
    "sg:address":"20540 Superior St",
    "sg:city":"Chatsworth",
    "sg:classifiers":[
        {
            "category":"Building & Trades",
            "subcategory":"Construction",
            "type":"Services"
        }
    ],
    "sg:phone":"+1 818 727 7258",
    "sg:postcode":"91311",
    "sg:province":"CA",
    "sg:tags":[
        "fabricator",
        "metal"
    ],
    "wof:name":"LA Quinta Metal Fabrication",
    "wof:placetype":"venue"
},
  "geometry": {"coordinates":[-118.58124599999999,34.246282],"type":"Point"}
}