{
  "type": "Feature",
  "properties": {
    "iso:country":"US",
    "sg:address":"25283 Cabot Road Suite 106",
    "sg:city":"Laguna Hills",
    "sg:classifiers":[
        {
            "category":"Shopping",
            "subcategory":"Jewelry",
            "type":"Retail Goods"
        },
        {
            "category":"Banks & Credit Unions",
            "subcategory":"Financial Services",
            "type":"Services"
        }
    ],
    "sg:phone":"+1 949 837 2311",
    "sg:postcode":"92653",
    "sg:province":"CA",
    "sg:tags":[
        "broker",
        "mortgage"
    ],
    "wof:name":"Pacific Shores Financial",
    "wof:placetype":"venue"
},
  "geometry": {"coordinates":[-117.675084,33.59392],"type":"Point"}
}