{
  "type": "Feature",
  "properties": {
    "addr:full":"3100 W Warner Ave Ste 11 Santa Ana CA 92704",
    "addr:housenumber":"3100",
    "addr:postcode":"92704",
    "addr:street":"W Warner Ave Ste 11",
    "iso:country":"US",
    "sg:address":"3100 W Warner Ave Ste 11",
    "sg:city":"Santa Ana",
    "sg:classifiers":[
        {
            "category":"Personal",
            "subcategory":"Skin Care",
            "type":"Services"
        }
    ],
    "sg:phone":"+1 714 444 1040",
    "sg:postcode":"92704",
    "sg:province":"CA",
    "wof:name":"Spa Girl Corp",
    "wof:placetype":"venue"
},
  "geometry": {"coordinates":[-117.910161,33.715023],"type":"Point"}
}