{
  "type": "Feature",
  "properties": {
    "iso:country":"US",
    "sg:address":"100 State Rte 36",
    "sg:city":"Susanville",
    "sg:classifiers":[
        {
            "category":"Arts & Performance",
            "subcategory":"Theater",
            "type":"Entertainment"
        }
    ],
    "sg:phone":"+1 530 310 1612",
    "sg:postcode":"96130",
    "sg:province":"CA",
    "sg:tags":[
        "live",
        "music"
    ],
    "wof:name":"Marks Mobile DJ",
    "wof:placetype":"venue"
},
  "geometry": {"coordinates":[-120.664597,40.4182],"type":"Point"}
}