{
  "type": "Feature",
  "properties": {
    "addr:full":"32 4th St Gonzales CA 93926",
    "addr:housenumber":"32",
    "addr:postcode":"93926",
    "addr:street":"4Th St",
    "iso:country":"US",
    "sg:address":"32 4th St",
    "sg:city":"Gonzales",
    "sg:classifiers":[
        {
            "category":"Personal",
            "subcategory":"Barber",
            "type":"Services"
        }
    ],
    "sg:phone":"+1 831 675 3672",
    "sg:postcode":"93926",
    "sg:province":"CA",
    "wof:name":"Barber Shop",
    "wof:placetype":"venue"
},
  "geometry": {"coordinates":[-121.444739,36.506748],"type":"Point"}
}