{
  "type": "Feature",
  "properties": {
    "iso:country":"US",
    "sg:address":"55 de Ford Dr",
    "sg:city":"San Rafael",
    "sg:classifiers":[
        {
            "category":"Banks & Credit Unions",
            "subcategory":"Bank",
            "type":"Services"
        }
    ],
    "sg:phone":"+1 415 507 0911",
    "sg:postcode":"94903",
    "sg:province":"CA",
    "sg:tags":[
        "broker",
        "mortgage"
    ],
    "wof:name":"SRI",
    "wof:placetype":"venue"
},
  "geometry": {"coordinates":[-122.560149,38.008341],"type":"Point"}
}