{
  "type": "Feature",
  "properties": {
    "iso:country":"US",
    "sg:address":"2100 Traffic Way",
    "sg:city":"Atascadero",
    "sg:classifiers":[
        {
            "category":"Retail",
            "subcategory":"Animal Services",
            "type":"Services"
        }
    ],
    "sg:phone":"+1 805 461 3549",
    "sg:postcode":"93422",
    "sg:province":"CA",
    "wof:name":"Carousel Farm",
    "wof:placetype":"venue"
},
  "geometry": {"coordinates":[-120.690746,35.521162],"type":"Point"}
}