{
  "type": "Feature",
  "properties": {
    "iso:country":"US",
    "sg:address":"350 Oakmead Parkway Suite 100",
    "sg:city":"Sunnyvale",
    "sg:classifiers":[
        {
            "category":"Manufacturing",
            "subcategory":"Electronics",
            "type":"Manufacturing & Wholesale Goods"
        }
    ],
    "sg:phone":"+1 408 970 3400",
    "sg:postcode":"94085",
    "sg:province":"CA",
    "sg:website":"http://www.mellanox.com",
    "wof:name":"Mellanox Technologies",
    "wof:placetype":"venue"
},
  "geometry": {"coordinates":[-121.98793999999999,37.38057],"type":"Point"}
}