{
  "type": "Feature",
  "properties": {
    "addr:full":"21321 Cold Spring Ln Diamond Bar CA 91765",
    "addr:housenumber":"21321",
    "addr:postcode":"91765",
    "addr:street":"Cold Spring Ln",
    "iso:country":"US",
    "sg:address":"21321 Cold Spring Ln",
    "sg:city":"Diamond Bar",
    "sg:classifiers":[
        {
            "category":"Restaurant",
            "type":"Food & Drink"
        }
    ],
    "sg:phone":"+1 909 598 4208",
    "sg:postcode":"91765",
    "sg:province":"CA",
    "sg:tags":[
        "management"
    ],
    "wof:name":"Card Investments Inc",
    "wof:placetype":"venue"
},
  "geometry": {"coordinates":[-117.839986,33.973363],"type":"Point"}
}