{
  "type": "Feature",
  "properties": {
    "iso:country":"US",
    "sg:address":"4933 Hillsborough Dr",
    "sg:city":"Petaluma",
    "sg:classifiers":[
        {
            "category":"Building & Trades",
            "subcategory":"Electrical",
            "type":"Services"
        }
    ],
    "sg:phone":"+1 707 769 1604",
    "sg:postcode":"94954",
    "sg:province":"CA",
    "sg:tags":[
        "electric",
        "contractor"
    ],
    "wof:name":"King Electric",
    "wof:placetype":"venue"
},
  "geometry": {"coordinates":[-122.609969,38.32012],"type":"Point"}
}