{
  "type": "Feature",
  "properties": {
    "addr:full":"4933 Hillsborough Dr Petaluma CA 94954",
    "addr:housenumber":"4933",
    "addr:postcode":"94954",
    "addr:street":"Hillsborough Dr",
    "iso:country":"US",
    "sg:address":"4933 Hillsborough Dr",
    "sg:city":"Petaluma",
    "sg:classifiers":[
        {
            "category":"Building & Trades",
            "subcategory":"Electrical",
            "type":"Services"
        }
    ],
    "sg:phone":"+1 707 769 1604",
    "sg:postcode":"94954",
    "sg:province":"CA",
    "sg:tags":[
        "electric",
        "contractor"
    ],
    "wof:name":"King Electric",
    "wof:placetype":"venue"
},
  "geometry": {"coordinates":[-122.60996900000001,38.32012],"type":"Point"}
}