{
  "type": "Feature",
  "properties": {
    "iso:country":"US",
    "sg:address":"1176 Chestnut St",
    "sg:city":"Menlo Park",
    "sg:classifiers":[
        {
            "category":"Personal",
            "subcategory":"Beauty Salon",
            "type":"Services"
        }
    ],
    "sg:phone":"+1 650 328 6089",
    "sg:postcode":"94025",
    "sg:province":"CA",
    "wof:name":"Euro Skin Care",
    "wof:placetype":"venue"
},
  "geometry": {"coordinates":[-122.18584300000001,37.452488],"type":"Point"}
}