{
  "type": "Feature",
  "properties": {
    "iso:country":"US",
    "sg:address":"1522 University Ave",
    "sg:city":"Berkeley",
    "sg:classifiers":[
        {
            "category":"Taxi",
            "type":"Transportation"
        }
    ],
    "sg:phone":"+1 510 848 1234",
    "sg:postcode":"94703",
    "sg:province":"CA",
    "sg:tags":[
        "taxicab"
    ],
    "wof:name":"Yellow A-1 Cab",
    "wof:placetype":"venue"
},
  "geometry": {"coordinates":[-122.28164099999999,37.870328],"type":"Point"}
}