{
  "type": "Feature",
  "properties": {
    "iso:country":"US",
    "sg:address":"24190 Alicia Pkwy",
    "sg:city":"Mission Viejo",
    "sg:classifiers":[
        {
            "category":"Restaurant",
            "type":"Food & Drink"
        }
    ],
    "sg:phone":"+1 949 472 4332",
    "sg:postcode":"92691",
    "sg:province":"CA",
    "sg:tags":[
        "italian"
    ],
    "sg:website":"www.antonuccis.net",
    "wof:name":"Antonucci's",
    "wof:placetype":"venue"
},
  "geometry": {"coordinates":[-117.685875,33.610315],"type":"Point"}
}