{
  "type": "Feature",
  "properties": {
    "addr:full":"100 West Broadway Level 2 Glendale CA 91203",
    "addr:housenumber":"100;2",
    "addr:postcode":"91203",
    "addr:street":"West Broadway Level",
    "iso:country":"US",
    "sg:address":"100 West Broadway Level 2",
    "sg:city":"Glendale",
    "sg:classifiers":[
        {
            "category":"Shopping",
            "subcategory":"Clothing, Apparel, & Fashions",
            "type":"Retail Goods"
        }
    ],
    "sg:phone":"+1 818 956 5697",
    "sg:postcode":"91203",
    "sg:province":"CA",
    "sg:website":"www.cottonon.com.au/",
    "wof:name":"Cotton On",
    "wof:placetype":"venue"
},
  "geometry": {"coordinates":[-118.25574400000001,34.146248],"type":"Point"}
}