{
  "type": "Feature",
  "properties": {
    "addr:full":"4151 S Central Ave Los Angeles CA 90011",
    "addr:housenumber":"4151",
    "addr:postcode":"90011",
    "addr:street":"S Central Ave",
    "iso:country":"US",
    "sg:address":"4151 S Central Ave",
    "sg:city":"Los Angeles",
    "sg:classifiers":[
        {
            "category":"Food & Beverages",
            "subcategory":"Groceries & Convenience Stores",
            "type":"Retail Goods"
        }
    ],
    "sg:phone":"+1 323 232 0713",
    "sg:postcode":"90011",
    "sg:province":"CA",
    "wof:name":"Yesenias Market",
    "wof:placetype":"venue"
},
  "geometry": {"coordinates":[-118.25599699999999,34.008301],"type":"Point"}
}