{
  "type": "Feature",
  "properties": {
    "iso:country":"US",
    "sg:address":"5791 Machine Dr",
    "sg:city":"Huntington Beach",
    "sg:classifiers":[
        {
            "category":"Home & Garden",
            "subcategory":"Hardware",
            "type":"Retail Goods"
        }
    ],
    "sg:phone":"+1 714 379 3200",
    "sg:postcode":"92649",
    "sg:province":"CA",
    "sg:tags":[
        "store"
    ],
    "wof:name":"Standard Wire Products",
    "wof:placetype":"venue"
},
  "geometry": {"coordinates":[-118.02800000000001,33.739601],"type":"Point"}
}