{
  "type": "Feature",
  "properties": {
    "addr:full":"1169 Meadowsweet Dr Corte Madera CA 94925",
    "addr:housenumber":"1169",
    "addr:postcode":"94925",
    "addr:street":"Meadowsweet Dr",
    "iso:country":"US",
    "sg:address":"1169 Meadowsweet Dr",
    "sg:city":"Corte Madera",
    "sg:classifiers":[
        {
            "category":"Wholesale",
            "subcategory":"Machinery & Supplies",
            "type":"Manufacturing & Wholesale Goods"
        }
    ],
    "sg:phone":"+1 415 927 2050",
    "sg:postcode":"94925",
    "sg:province":"CA",
    "sg:tags":[
        "compressor",
        "gas"
    ],
    "wof:name":"Shamrock Compressor Svc",
    "wof:placetype":"venue"
},
  "geometry": {"coordinates":[-122.512906,37.912527],"type":"Point"}
}