{
  "type": "Feature",
  "properties": {
    "iso:country":"US",
    "sg:address":"1274 Geneva Dr",
    "sg:city":"Sunnyvale",
    "sg:classifiers":[
        {
            "category":"Wholesale",
            "subcategory":"Computers",
            "type":"Manufacturing & Wholesale Goods"
        }
    ],
    "sg:phone":"+1 408 747 1111",
    "sg:postcode":"94089",
    "sg:province":"CA",
    "wof:name":"Lots Technology Inc",
    "wof:placetype":"venue"
},
  "geometry": {"coordinates":[-122.014367,37.40952],"type":"Point"}
}