{
  "type": "Feature",
  "properties": {
    "addr:full":"4603 Mission Blvd San Diego CA 92109",
    "addr:housenumber":"4603",
    "addr:postcode":"92109",
    "addr:street":"Mission Blvd",
    "iso:country":"US",
    "sg:address":"4603 Mission Blvd",
    "sg:city":"San Diego",
    "sg:classifiers":[
        {
            "category":"Personal",
            "subcategory":"Tattoo Parlor",
            "type":"Services"
        }
    ],
    "sg:phone":"+1 858 483 1542",
    "sg:postcode":"92109",
    "sg:province":"CA",
    "sg:website":"www.blackrosetattoo.com",
    "wof:name":"Black Rose Tattoo",
    "wof:placetype":"venue"
},
  "geometry": {"coordinates":[-117.255566,32.79784],"type":"Point"}
}