{
  "type": "Feature",
  "properties": {
    "addr:full":"850 S Van Ness Ave San Francisco CA 94110",
    "addr:housenumber":"850",
    "addr:postcode":"94110",
    "addr:street":"S Van Ness Ave",
    "iso:country":"US",
    "sg:address":"850 S Van Ness Ave",
    "sg:city":"San Francisco",
    "sg:classifiers":[
        {
            "category":"Building & Trades",
            "subcategory":"Construction",
            "type":"Services"
        }
    ],
    "sg:phone":"+1 415 647 6868",
    "sg:postcode":"94110",
    "sg:province":"CA",
    "sg:tags":[
        "home",
        "waterproofing",
        "contractor"
    ],
    "wof:name":"Cal Coast Waterproofing, Inc.",
    "wof:placetype":"venue"
},
  "geometry": {"coordinates":[-122.41750999999999,37.759534],"type":"Point"}
}