{
  "type": "Feature",
  "properties": {
    "iso:country":"US",
    "sg:address":"8041 Florence Ave",
    "sg:city":"Downey",
    "sg:classifiers":[
        {
            "category":"Building & Trades",
            "subcategory":"Construction",
            "type":"Services"
        }
    ],
    "sg:phone":"+1 562 806 2899",
    "sg:postcode":"90240",
    "sg:province":"CA",
    "sg:tags":[
        "residential",
        "nonresidential"
    ],
    "wof:name":"Mayans Development Inc",
    "wof:placetype":"venue"
},
  "geometry": {"coordinates":[-118.128916,33.953192],"type":"Point"}
}