{
  "type": "Feature",
  "properties": {
    "addr:full":"625 Broadway Ste 700 San Diego CA 92101",
    "addr:housenumber":"625",
    "addr:postcode":"92101",
    "addr:street":"Broadway Ste 700",
    "iso:country":"US",
    "sg:address":"625 Broadway Ste 700",
    "sg:city":"San Diego",
    "sg:classifiers":[
        {
            "category":"Communications",
            "subcategory":"Newspaper",
            "type":"Services"
        }
    ],
    "sg:phone":"+1 619 237 5014",
    "sg:postcode":"92101",
    "sg:province":"CA",
    "sg:tags":[
        "print",
        "medium"
    ],
    "sg:website":"www.thenaughtyamerican.com",
    "wof:name":"Naughty American",
    "wof:placetype":"venue"
},
  "geometry": {"coordinates":[-117.15900999999999,32.7157],"type":"Point"}
}