{
  "type": "Feature",
  "properties": {
    "iso:country":"US",
    "sg:address":"9719 Lincoln Village Dr 409",
    "sg:city":"Sacramento",
    "sg:classifiers":[
        {
            "category":"Insurance",
            "subcategory":"Insurance Agent",
            "type":"Services"
        },
        {
            "category":"Insurance",
            "subcategory":"Hazard Insurance",
            "type":"Services"
        },
        {
            "category":"Insurance",
            "subcategory":"Title Insurance",
            "type":"Services"
        },
        {
            "category":"Insurance",
            "subcategory":"Life Insurance",
            "type":"Services"
        }
    ],
    "sg:phone":"+1 916 596 2683",
    "sg:postcode":"95827",
    "sg:province":"CA",
    "sg:tags":[
        "business",
        "auto",
        "commercial",
        "homeowner",
        "property",
        "casualty"
    ],
    "sg:website":"http://sacramento.citysearch.com/profile/external/602680263/sacramento_ca/asher_styrsky_insurance_agency_inc_farmers_insurance.html?publisher=yellowpages&reference_id=1&placement=ypwebsitemip",
    "wof:name":"Asher Styrsky Insurance Agency Inc - Farmers Insurance",
    "wof:placetype":"venue"
},
  "geometry": {"coordinates":[-121.33361499999999,38.562053],"type":"Point"}
}