{
  "type": "Feature",
  "properties": {
    "iso:country":"US",
    "sg:address":"2055 N Figueroa St #6689",
    "sg:city":"Los Angeles",
    "sg:classifiers":[
        {
            "category":"Home & Garden",
            "subcategory":"Hardware",
            "type":"Retail Goods"
        }
    ],
    "sg:phone":"+1 323 441 1310",
    "sg:postcode":"90065",
    "sg:province":"CA",
    "sg:tags":[
        "store"
    ],
    "sg:website":"www.homedepot.com",
    "wof:name":"Home Depot",
    "wof:placetype":"venue"
},
  "geometry": {"coordinates":[-118.224059,34.08277],"type":"Point"}
}