{
  "type": "Feature",
  "properties": {
    "iso:country":"US",
    "sg:address":"3310 Yorba Linda Blvd",
    "sg:city":"Fullerton",
    "sg:classifiers":[
        {
            "category":"Manufacturing",
            "subcategory":"Paper Products",
            "type":"Manufacturing & Wholesale Goods"
        }
    ],
    "sg:phone":"+1 714 777 8839",
    "sg:postcode":"92886",
    "sg:province":"CA",
    "sg:tags":[
        "manufacture",
        "corrugated",
        "partition",
        "box",
        "item",
        "s",
        "display"
    ],
    "wof:name":"RG Loomis Corporation",
    "wof:placetype":"venue"
},
  "geometry": {"coordinates":[-117.867914,33.888517],"type":"Point"}
}