{
  "type": "Feature",
  "properties": {
    "addr:full":"1525 E Main St Santa Maria CA 93454",
    "addr:housenumber":"1525",
    "addr:postcode":"93454",
    "addr:street":"E Main St",
    "iso:country":"US",
    "sg:address":"1525 E Main St",
    "sg:city":"Santa Maria",
    "sg:classifiers":[
        {
            "category":"Professional",
            "type":"Services"
        }
    ],
    "sg:phone":"+1 805 937 4594",
    "sg:postcode":"93454",
    "sg:province":"CA",
    "wof:name":"Cossa Blanca LLC",
    "wof:placetype":"venue"
},
  "geometry": {"coordinates":[-120.409998,34.952934],"type":"Point"}
}