{
  "type": "Feature",
  "properties": {
    "iso:country":"US",
    "sg:address":"3670 Grand Ave",
    "sg:city":"Claremont",
    "sg:classifiers":[
        {
            "category":"Restaurant",
            "type":"Food & Drink"
        }
    ],
    "sg:phone":"+1 909 364 9098",
    "sg:postcode":"91711",
    "sg:province":"CA",
    "sg:website":"www.chilis.com",
    "wof:name":"Chili's Grill & Bar",
    "wof:placetype":"venue"
},
  "geometry": {"coordinates":[-117.702904,34.133706],"type":"Point"}
}