{
  "type": "Feature",
  "properties": {
    "addr:full":"176 E 7th St Lincoln CA 95648",
    "addr:housenumber":"176",
    "addr:postcode":"95648",
    "addr:street":"E 7Th St",
    "iso:country":"US",
    "sg:address":"176 E 7th St",
    "sg:city":"Lincoln",
    "sg:classifiers":[
        {
            "category":"Manufacturing",
            "subcategory":"Jewelry",
            "type":"Manufacturing & Wholesale Goods"
        }
    ],
    "sg:phone":"+1 916 645 3060",
    "sg:postcode":"95648",
    "sg:province":"CA",
    "sg:tags":[
        "lapidary"
    ],
    "wof:name":"J & I Lapidary",
    "wof:placetype":"venue"
},
  "geometry": {"coordinates":[-121.28322300000001,38.894642],"type":"Point"}
}