{
  "type": "Feature",
  "properties": {
    "addr:full":"1912 W Grant Line Rd Tracy CA 95376",
    "addr:housenumber":"1912",
    "addr:postcode":"95376",
    "addr:street":"W Grant Line Rd",
    "iso:country":"US",
    "sg:address":"1912 W Grant Line Rd",
    "sg:city":"Tracy",
    "sg:classifiers":[
        {
            "category":"Health Services",
            "subcategory":"Chiropractor",
            "type":"Services"
        }
    ],
    "sg:phone":"+1 209 832 2223",
    "sg:postcode":"95376",
    "sg:province":"CA",
    "wof:name":"Chau Chiropractic",
    "wof:placetype":"venue"
},
  "geometry": {"coordinates":[-121.448792,37.754131],"type":"Point"}
}