{
  "type": "Feature",
  "properties": {
    "addr:full":"32842 Kentucky St Yucaipa CA 92399",
    "addr:housenumber":"32842",
    "addr:postcode":"92399",
    "addr:street":"Kentucky St",
    "iso:country":"US",
    "sg:address":"32842 Kentucky St",
    "sg:city":"Yucaipa",
    "sg:classifiers":[
        {
            "category":"Building & Trades",
            "subcategory":"Landscaping Services",
            "type":"Services"
        }
    ],
    "sg:phone":"+1 909 795 1721",
    "sg:postcode":"92399",
    "sg:province":"CA",
    "sg:tags":[
        "tree"
    ],
    "wof:name":"Walt's Stump Removal",
    "wof:placetype":"venue"
},
  "geometry": {"coordinates":[-117.089017,34.0231],"type":"Point"}
}