{
  "type": "Feature",
  "properties": {
    "addr:full":"1118 W 182nd St Gardena CA 90248",
    "addr:housenumber":"1118",
    "addr:postcode":"90248",
    "addr:street":"W 182Nd St",
    "iso:country":"US",
    "sg:address":"1118 W 182nd St",
    "sg:city":"Gardena",
    "sg:classifiers":[
        {
            "category":"Professional",
            "type":"Services"
        }
    ],
    "sg:phone":"+1 310 327 0742",
    "sg:postcode":"90248",
    "sg:province":"CA",
    "wof:name":"Neighbors Care",
    "wof:placetype":"venue"
},
  "geometry": {"coordinates":[-118.293002,33.866287],"type":"Point"}
}