{
  "type": "Feature",
  "properties": {
    "iso:country":"US",
    "sg:address":"2013 Monrovia Ave",
    "sg:city":"Costa Mesa",
    "sg:classifiers":[
        {
            "category":"Shopping",
            "type":"Retail Goods"
        }
    ],
    "sg:phone":"+1 949 646 8105",
    "sg:postcode":"92627",
    "sg:province":"CA",
    "sg:tags":[
        "merchandise"
    ],
    "wof:name":"Robert Shefflette Enterprises",
    "wof:placetype":"venue"
},
  "geometry": {"coordinates":[-117.936072,33.647798],"type":"Point"}
}