{
  "type": "Feature",
  "properties": {
    "iso:country":"US",
    "sg:address":"368 Noren St",
    "sg:city":"La Canada Fltrdg",
    "sg:classifiers":[
        {
            "category":"Building & Trades",
            "subcategory":"Construction",
            "type":"Services"
        }
    ],
    "sg:phone":"+1 818 790 4756",
    "sg:postcode":"91011",
    "sg:province":"CA",
    "sg:tags":[
        "designer"
    ],
    "wof:name":"Smythsonlyun",
    "wof:placetype":"venue"
},
  "geometry": {"coordinates":[-118.18436,34.209903],"type":"Point"}
}