{
  "type": "Feature",
  "properties": {
    "iso:country":"US",
    "sg:address":"8737 Oak Knoll Ct",
    "sg:city":"Stockton",
    "sg:classifiers":[
        {
            "category":"Building & Trades",
            "subcategory":"Construction",
            "type":"Services"
        }
    ],
    "sg:phone":"+1 209 951 6137",
    "sg:postcode":"95209",
    "sg:province":"CA",
    "sg:tags":[
        "wallcoverings-installation",
        "wallpaper",
        "painting",
        "contractor"
    ],
    "wof:name":"Hickman Painting",
    "wof:placetype":"venue"
},
  "geometry": {"coordinates":[-121.324405,38.030342],"type":"Point"}
}