{
  "type": "Feature",
  "properties": {
    "iso:country":"US",
    "sg:address":"1227 O St Ste 105",
    "sg:city":"Sacramento",
    "sg:classifiers":[
        {
            "category":"Government",
            "subcategory":"Office",
            "type":"Public Place"
        }
    ],
    "sg:phone":"+1 916 653 2579",
    "sg:postcode":"95814",
    "sg:province":"CA",
    "sg:tags":[
        "government-state",
        "government-united",
        "state"
    ],
    "sg:website":"http://www.californiachronicle.com",
    "wof:name":"State of California Veterans Affairs",
    "wof:placetype":"venue"
},
  "geometry": {"coordinates":[-121.49279799999999,38.573947],"type":"Point"}
}