{
  "type": "Feature",
  "properties": {
    "iso:country":"US",
    "sg:address":"2604 El Camino Real Ste B",
    "sg:city":"Carlsbad",
    "sg:classifiers":[
        {
            "category":"Real Estate",
            "subcategory":"Real Estate Services",
            "type":"Services"
        }
    ],
    "sg:phone":"+1 760 434 2342",
    "sg:postcode":"92008",
    "sg:province":"CA",
    "sg:tags":[
        "inspection"
    ],
    "wof:name":"Inspectrite",
    "wof:placetype":"venue"
},
  "geometry": {"coordinates":[-117.326373,33.17717],"type":"Point"}
}