{
  "type": "Feature",
  "properties": {
    "iso:country":"US",
    "sg:address":"855 Front St",
    "sg:city":"Needles",
    "sg:classifiers":[
        {
            "category":"Health Services",
            "subcategory":"Chiropractor",
            "type":"Services"
        }
    ],
    "sg:phone":"+1 760 326 6544",
    "sg:postcode":"92363",
    "sg:province":"CA",
    "wof:name":"Martha Merrifield DC",
    "wof:placetype":"venue"
},
  "geometry": {"coordinates":[-114.604664,34.839937],"type":"Point"}
}