{
  "type": "Feature",
  "properties": {
    "addr:full":"2152 Bonita Ave La Verne CA 91750",
    "addr:housenumber":"2152",
    "addr:postcode":"91750",
    "addr:street":"Bonita Ave",
    "iso:country":"US",
    "sg:address":"2152 Bonita Ave",
    "sg:city":"La Verne",
    "sg:classifiers":[
        {
            "category":"Wholesale",
            "subcategory":"Non-durable Goods",
            "type":"Manufacturing & Wholesale Goods"
        }
    ],
    "sg:phone":"+1 909 593 8478",
    "sg:postcode":"91750",
    "sg:province":"CA",
    "sg:tags":[
        "interior"
    ],
    "wof:name":"Gina T Interior Accents",
    "wof:placetype":"venue"
},
  "geometry": {"coordinates":[-117.76879099999999,34.101198],"type":"Point"}
}