{
  "type": "Feature",
  "properties": {
    "iso:country":"US",
    "sg:address":"2510 Gibson St",
    "sg:city":"Riverside",
    "sg:classifiers":[
        {
            "category":"Social Services",
            "subcategory":"Adult Care",
            "type":"Services"
        }
    ],
    "sg:phone":"+1 951 359 5063",
    "sg:postcode":"92503",
    "sg:province":"CA",
    "sg:tags":[
        "residential"
    ],
    "wof:name":"Marca Small Family Home",
    "wof:placetype":"venue"
},
  "geometry": {"coordinates":[-117.43004999999999,33.906639],"type":"Point"}
}