{
  "type": "Feature",
  "properties": {
    "addr:full":"12137 Magnolia Blvd Valley Village CA 91607",
    "addr:housenumber":"12137",
    "addr:postcode":"91607",
    "addr:street":"Magnolia Blvd",
    "iso:country":"US",
    "sg:address":"12137 Magnolia Blvd",
    "sg:city":"Valley Village",
    "sg:classifiers":[
        {
            "category":"Health Services",
            "subcategory":"Dentist",
            "type":"Services"
        }
    ],
    "sg:phone":"+1 818 766 3988",
    "sg:postcode":"91607",
    "sg:province":"CA",
    "wof:name":"Vinarsky Maya DDS",
    "wof:placetype":"venue"
},
  "geometry": {"coordinates":[-118.397003,34.164799],"type":"Point"}
}