{
  "type": "Feature",
  "properties": {
    "iso:country":"US",
    "sg:address":"9966 State Rte 140",
    "sg:city":"El Portal",
    "sg:classifiers":[
        {
            "category":"Travel",
            "subcategory":"Hotels & Motels",
            "type":"Entertainment"
        }
    ],
    "sg:phone":"+1 209 379 2612",
    "sg:postcode":"95318",
    "sg:province":"CA",
    "sg:website":"www.yosemite-motels.com",
    "wof:name":"Cedar Lodge Motel",
    "wof:placetype":"venue"
},
  "geometry": {"coordinates":[-119.887642,37.654401],"type":"Point"}
}