{
  "type": "Feature",
  "properties": {
    "iso:country":"US",
    "sg:address":"1363 E Wilshire Ave",
    "sg:city":"Santa Ana",
    "sg:classifiers":[
        {
            "category":"Professional",
            "subcategory":"Computer Services",
            "type":"Services"
        }
    ],
    "sg:phone":"+1 714 426 1380",
    "sg:postcode":"92705",
    "sg:province":"CA",
    "sg:tags":[
        "repair"
    ],
    "wof:name":"Irvine Enterprises Inc",
    "wof:placetype":"venue"
},
  "geometry": {"coordinates":[-117.851997,33.729198],"type":"Point"}
}