{
  "type": "Feature",
  "properties": {
    "iso:country":"US",
    "sg:address":"2026 Santa Anita Ave",
    "sg:city":"South El Monte",
    "sg:classifiers":[
        {
            "category":"Building & Trades",
            "subcategory":"Construction",
            "type":"Services"
        }
    ],
    "sg:phone":"+1 626 350 8282",
    "sg:postcode":"91733",
    "sg:province":"CA",
    "sg:tags":[
        "general",
        "contractor"
    ],
    "wof:name":"Golden Globe Contractors Inc",
    "wof:placetype":"venue"
},
  "geometry": {"coordinates":[-118.042321,34.053421],"type":"Point"}
}