{
  "type": "Feature",
  "properties": {
    "iso:country":"US",
    "sg:address":"15720 Loma Vista Ave",
    "sg:city":"Los Gatos",
    "sg:classifiers":[
        {
            "category":"Building & Trades",
            "subcategory":"Landscaping Services",
            "type":"Services"
        }
    ],
    "sg:phone":"+1 408 356 2022",
    "sg:postcode":"95032",
    "sg:province":"CA",
    "sg:tags":[
        "designer",
        "landscape"
    ],
    "wof:name":"Garden Design Svc",
    "wof:placetype":"venue"
},
  "geometry": {"coordinates":[-121.950613,37.242237],"type":"Point"}
}