{
  "type": "Feature",
  "properties": {
    "addr:full":"15891 Co Rd 92C Woodland CA 95695",
    "addr:housenumber":"15891;92c",
    "addr:postcode":"95695",
    "addr:street":"Co Rd",
    "iso:country":"US",
    "sg:address":"15891 Co Rd 92C",
    "sg:city":"Woodland",
    "sg:classifiers":[
        {
            "category":"Farming",
            "subcategory":"Farm",
            "type":"Manufacturing & Wholesale Goods"
        }
    ],
    "sg:phone":"+1 530 662 0951",
    "sg:postcode":"95695",
    "sg:province":"CA",
    "sg:tags":[
        "crop",
        "general"
    ],
    "wof:name":"Shelton Farms",
    "wof:placetype":"venue"
},
  "geometry": {"coordinates":[-121.90052799999999,38.708566],"type":"Point"}
}