{
  "type": "Feature",
  "properties": {
    "iso:country":"US",
    "sg:address":"16835 Brookhurst St",
    "sg:city":"Fountain Valley",
    "sg:classifiers":[
        {
            "category":"Organizations",
            "subcategory":"Religious Organization",
            "type":"Services"
        }
    ],
    "sg:phone":"+1 714 964 6899",
    "sg:postcode":"92708",
    "sg:province":"CA",
    "sg:tags":[
        "church"
    ],
    "sg:website":"www.fcbcfv.org",
    "wof:name":"First Chinese Baptist Church",
    "wof:placetype":"venue"
},
  "geometry": {"coordinates":[-117.954002,33.719101],"type":"Point"}
}