{
  "type": "Feature",
  "properties": {
    "addr:full":"1295 Fulton Ave Sacramento CA 95825",
    "addr:housenumber":"1295",
    "addr:postcode":"95825",
    "addr:street":"Fulton Ave",
    "iso:country":"US",
    "sg:address":"1295 Fulton Ave",
    "sg:city":"Sacramento",
    "sg:classifiers":[
        {
            "category":"Food & Beverages",
            "subcategory":"Groceries & Convenience Stores",
            "type":"Retail Goods"
        }
    ],
    "sg:phone":"+1 916 977 0902",
    "sg:postcode":"95825",
    "sg:province":"CA",
    "wof:name":"Quik Stop Market",
    "wof:placetype":"venue"
},
  "geometry": {"coordinates":[-121.402,38.5882],"type":"Point"}
}