{
  "type": "Feature",
  "properties": {
    "addr:full":"5836 Franklin Blvd Sacramento CA 95824",
    "addr:housenumber":"5836",
    "addr:postcode":"95824",
    "addr:street":"Franklin Blvd",
    "iso:country":"US",
    "sg:address":"5836 Franklin Blvd",
    "sg:city":"Sacramento",
    "sg:classifiers":[
        {
            "category":"Personal",
            "subcategory":"Barber",
            "type":"Services"
        }
    ],
    "sg:phone":"+1 916 393 6595",
    "sg:postcode":"95824",
    "sg:province":"CA",
    "wof:name":"Kings Klips",
    "wof:placetype":"venue"
},
  "geometry": {"coordinates":[-121.47071800000001,38.520317],"type":"Point"}
}