{
  "type": "Feature",
  "properties": {
    "iso:country":"US",
    "sg:address":"993 Mission St",
    "sg:city":"San Francisco",
    "sg:classifiers":[
        {
            "category":"Shopping",
            "subcategory":"Used Merchandise",
            "type":"Retail Goods"
        }
    ],
    "sg:phone":"+1 415 957 9917",
    "sg:postcode":"94103",
    "sg:province":"CA",
    "sg:tags":[
        "pawnbroker"
    ],
    "wof:name":"Best Collateral Inc",
    "wof:placetype":"venue"
},
  "geometry": {"coordinates":[-122.407614,37.781958],"type":"Point"}
}