{
  "type": "Feature",
  "properties": {
    "iso:country":"US",
    "sg:address":"11 University Ave",
    "sg:city":"Los Gatos",
    "sg:classifiers":[
        {
            "category":"Shopping",
            "subcategory":"Clothing, Apparel, & Fashions",
            "type":"Retail Goods"
        },
        {
            "category":"Shopping",
            "subcategory":"Bridal",
            "type":"Retail Goods"
        }
    ],
    "sg:phone":"+1 408 354 8003",
    "sg:postcode":"95030",
    "sg:province":"CA",
    "sg:tags":[
        "clothing",
        "women's"
    ],
    "wof:name":"In the Olde Manner",
    "wof:placetype":"venue"
},
  "geometry": {"coordinates":[-121.983002,37.2225],"type":"Point"}
}