{
  "type": "Feature",
  "properties": {
    "addr:full":"14560 Reservoir Pl Chino Hills CA 91709",
    "addr:housenumber":"14560",
    "addr:postcode":"91709",
    "addr:street":"Reservoir Pl",
    "iso:country":"US",
    "sg:address":"14560 Reservoir Pl",
    "sg:city":"Chino Hills",
    "sg:classifiers":[
        {
            "category":"Manufacturing",
            "subcategory":"Paper Products",
            "type":"Manufacturing & Wholesale Goods"
        }
    ],
    "sg:phone":"+1 909 606 3970",
    "sg:postcode":"91709",
    "sg:province":"CA",
    "sg:tags":[
        "mill",
        "paperboard"
    ],
    "wof:name":"Bob Balys Packaging",
    "wof:placetype":"venue"
},
  "geometry": {"coordinates":[-117.73080899999999,33.98903],"type":"Point"}
}