{
  "type": "Feature",
  "properties": {
    "iso:country":"US",
    "sg:address":"3355 E Spring St",
    "sg:city":"Long Beach",
    "sg:classifiers":[
        {
            "category":"Organizations",
            "subcategory":"Religious Organization",
            "type":"Services"
        }
    ],
    "sg:phone":"+1 562 988 8606",
    "sg:postcode":"90806",
    "sg:province":"CA",
    "wof:name":"World Healing Center Church",
    "wof:placetype":"venue"
},
  "geometry": {"coordinates":[-118.153142,33.810807],"type":"Point"}
}