{
  "type": "Feature",
  "properties": {
    "addr:full":"4404 Bond St San Diego CA 92109",
    "addr:housenumber":"4404",
    "addr:postcode":"92109",
    "addr:street":"Bond St",
    "iso:country":"US",
    "sg:address":"4404 Bond St",
    "sg:city":"San Diego",
    "sg:classifiers":[
        {
            "category":"Building & Trades",
            "subcategory":"Electrical",
            "type":"Services"
        }
    ],
    "sg:phone":"+1 858 270 3458",
    "sg:postcode":"92109",
    "sg:province":"CA",
    "sg:tags":[
        "electrical",
        "contractor"
    ],
    "wof:name":"Hopkins Electric",
    "wof:placetype":"venue"
},
  "geometry": {"coordinates":[-117.220403,32.803191],"type":"Point"}
}