{
  "type": "Feature",
  "properties": {
    "iso:country":"US",
    "sg:address":"4636 Schlosser Ct",
    "sg:city":"Castro Valley",
    "sg:classifiers":[
        {
            "category":"Health Services",
            "subcategory":"Clinic",
            "type":"Services"
        }
    ],
    "sg:phone":"+1 510 581 6759",
    "sg:postcode":"94546",
    "sg:province":"CA",
    "sg:tags":[
        "medical"
    ],
    "sg:website":"www.mobility-4u.com",
    "wof:name":"Mobility 4U Stair Lift",
    "wof:placetype":"venue"
},
  "geometry": {"coordinates":[-122.064949,37.704969],"type":"Point"}
}