{
  "type": "Feature",
  "properties": {
    "addr:full":"9601 Slauson Ave Pico Rivera CA 90660",
    "addr:housenumber":"9601",
    "addr:postcode":"90660",
    "addr:street":"Slauson Ave",
    "iso:country":"US",
    "sg:address":"9601 Slauson Ave",
    "sg:city":"Pico Rivera",
    "sg:classifiers":[
        {
            "category":"Retail",
            "subcategory":"Storage",
            "type":"Services"
        }
    ],
    "sg:phone":"+1 562 948 4445",
    "sg:postcode":"90660",
    "sg:province":"CA",
    "sg:tags":[
        "self"
    ],
    "sg:website":"www.extraspace.com/Storage/Facil...",
    "wof:name":"Extra Space Storage",
    "wof:placetype":"venue"
},
  "geometry": {"coordinates":[-118.091877,33.96744],"type":"Point"}
}