{
  "type": "Feature",
  "properties": {
    "iso:country":"US",
    "sg:address":"598 Bosworth Street Suite 2",
    "sg:city":"San Francisco",
    "sg:classifiers":[
        {
            "category":"Health Services",
            "subcategory":"Doctor",
            "type":"Services"
        }
    ],
    "sg:phone":"+1 415 337 9362",
    "sg:postcode":"94131",
    "sg:province":"CA",
    "wof:name":"Leung Martin C MD",
    "wof:placetype":"venue"
},
  "geometry": {"coordinates":[-122.433998,37.733601],"type":"Point"}
}