{
  "type": "Feature",
  "properties": {
    "iso:country":"US",
    "sg:address":"180 Gary Pl",
    "sg:city":"San Rafael",
    "sg:classifiers":[
        {
            "category":"Retail",
            "subcategory":"Auto Repair",
            "type":"Services"
        }
    ],
    "sg:phone":"+1 415 453 5469",
    "sg:postcode":"94901",
    "sg:province":"CA",
    "sg:tags":[
        "body",
        "automobile",
        "painting"
    ],
    "sg:website":"www.prestigeautobody.com",
    "wof:name":"Prestige Autobody",
    "wof:placetype":"venue"
},
  "geometry": {"coordinates":[-122.509056,37.959737],"type":"Point"}
}