{
  "type": "Feature",
  "properties": {
    "iso:country":"US",
    "sg:address":"1620 N Carpenter Rd Bldg B",
    "sg:city":"Modesto",
    "sg:classifiers":[
        {
            "category":"Manufacturing",
            "subcategory":"Buildings",
            "type":"Manufacturing & Wholesale Goods"
        },
        {
            "category":"Building & Trades",
            "subcategory":"Construction",
            "type":"Services"
        }
    ],
    "sg:phone":"+1 209 526 8242",
    "sg:postcode":"95351",
    "sg:province":"CA",
    "sg:tags":[
        "home",
        "builder",
        "contractor"
    ],
    "sg:website":"http://www.bright-homes.com",
    "wof:name":"Bright Development",
    "wof:placetype":"venue"
},
  "geometry": {"coordinates":[-121.031128,37.659288],"type":"Point"}
}