{
  "type": "Feature",
  "properties": {
    "addr:full":"203 N Savona Walk Long Beach CA 90803",
    "addr:housenumber":"203",
    "addr:postcode":"90803",
    "addr:street":"N Savona Walk",
    "iso:country":"US",
    "sg:address":"203 N Savona Walk",
    "sg:city":"Long Beach",
    "sg:classifiers":[
        {
            "category":"Real Estate",
            "subcategory":"Real Estate Agent",
            "type":"Services"
        }
    ],
    "sg:phone":"+1 562 434 9243",
    "sg:postcode":"90803",
    "sg:province":"CA",
    "wof:name":"Robert C McFadden Jr",
    "wof:placetype":"venue"
},
  "geometry": {"coordinates":[-118.11844000000001,33.754624],"type":"Point"}
}