{
  "type": "Feature",
  "properties": {
    "addr:full":"1203 Garnet Ave San Diego CA 92109",
    "addr:housenumber":"1203",
    "addr:postcode":"92109",
    "addr:street":"Garnet Ave",
    "iso:country":"US",
    "sg:address":"1203 Garnet Ave",
    "sg:city":"San Diego",
    "sg:classifiers":[
        {
            "category":"Restaurant",
            "type":"Food & Drink"
        }
    ],
    "sg:menulink":"http://www.allmenus.com/ca/san-diego/28968-pb-sushi/menu/",
    "sg:phone":"+1 858 274 9755",
    "sg:postcode":"92109",
    "sg:province":"CA",
    "sg:tags":[
        "japanese",
        "asian"
    ],
    "wof:name":"PB Sushi",
    "wof:placetype":"venue"
},
  "geometry": {"coordinates":[-117.24812900000001,32.798184],"type":"Point"}
}