{
  "type": "Feature",
  "properties": {
    "addr:full":"8500 Beverly Blvd Los Angeles CA 90048",
    "addr:housenumber":"8500",
    "addr:postcode":"90048",
    "addr:street":"Beverly Blvd",
    "iso:country":"US",
    "sg:address":"8500 Beverly Blvd",
    "sg:city":"Los Angeles",
    "sg:classifiers":[
        {
            "category":"Shopping",
            "subcategory":"Clothing, Apparel, & Fashions",
            "type":"Retail Goods"
        }
    ],
    "sg:phone":"+1 310 657 0011",
    "sg:postcode":"90048",
    "sg:province":"CA",
    "sg:tags":[
        "men's",
        "clothing"
    ],
    "wof:name":"Hugo Boss",
    "wof:placetype":"venue"
},
  "geometry": {"coordinates":[-118.376762,34.075966],"type":"Point"}
}