{
  "type": "Feature",
  "properties": {
    "addr:full":"1302 W 65th St Los Angeles CA 90044",
    "addr:housenumber":"1302",
    "addr:postcode":"90044",
    "addr:street":"W 65Th St",
    "iso:country":"US",
    "sg:address":"1302 W 65th St",
    "sg:city":"Los Angeles",
    "sg:classifiers":[
        {
            "category":"Freight",
            "type":"Transportation"
        }
    ],
    "sg:phone":"+1 323 759 2064",
    "sg:postcode":"90044",
    "sg:province":"CA",
    "wof:name":"Kent Baptist Trucking",
    "wof:placetype":"venue"
},
  "geometry": {"coordinates":[-118.300262,33.980616],"type":"Point"}
}