{
  "type": "Feature",
  "properties": {
    "iso:country":"US",
    "sg:address":"1557 Santa Anita Ave",
    "sg:city":"South El Monte",
    "sg:classifiers":[
        {
            "category":"Wholesale",
            "subcategory":"Office Equipment",
            "type":"Manufacturing & Wholesale Goods"
        }
    ],
    "sg:phone":"+1 626 527 2025",
    "sg:postcode":"91733",
    "sg:province":"CA",
    "wof:name":"Copierman",
    "wof:placetype":"venue"
},
  "geometry": {"coordinates":[-118.04560600000001,34.044582],"type":"Point"}
}