{
  "type": "Feature",
  "properties": {
    "iso:country":"US",
    "sg:address":"2203 E 4th St",
    "sg:city":"Ontario",
    "sg:classifiers":[
        {
            "category":"Retail",
            "subcategory":"Auto Repair",
            "type":"Services"
        }
    ],
    "sg:phone":"+1 909 467 9688",
    "sg:postcode":"91764",
    "sg:province":"CA",
    "sg:tags":[
        "automobile",
        "installation",
        "glass"
    ],
    "wof:name":"Windshield Crack Repair",
    "wof:placetype":"venue"
},
  "geometry": {"coordinates":[-117.605243,34.077643],"type":"Point"}
}