{
  "type": "Feature",
  "properties": {
    "iso:country":"US",
    "sg:address":"2300 Boswell Ct",
    "sg:city":"Chula Vista",
    "sg:classifiers":[
        {
            "category":"Banks & Credit Unions",
            "subcategory":"Bank",
            "type":"Services"
        }
    ],
    "sg:phone":"+1 619 498 0000",
    "sg:postcode":"91914",
    "sg:province":"CA",
    "sg:tags":[
        "loan"
    ],
    "wof:name":"Lending Specialist",
    "wof:placetype":"venue"
},
  "geometry": {"coordinates":[-116.967769,32.655197],"type":"Point"}
}