{
  "type": "Feature",
  "properties": {
    "iso:country":"US",
    "sg:address":"200 E 30th St",
    "sg:city":"San Bernardino",
    "sg:classifiers":[
        {
            "category":"Professional",
            "type":"Services"
        }
    ],
    "sg:phone":"+1 909 883 1192",
    "sg:postcode":"92404",
    "sg:province":"CA",
    "wof:name":"Jeffrey Edwards Handy Man",
    "wof:placetype":"venue"
},
  "geometry": {"coordinates":[-117.281609,34.146054],"type":"Point"}
}