{
  "type": "Feature",
  "properties": {
    "addr:full":"940 N. Sierra Bonita Ave. Unit 9 West Hollywood CA 90046",
    "addr:housenumber":"940",
    "addr:postcode":"90046",
    "addr:street":"N. Sierra Bonita Ave. Unit 9",
    "iso:country":"US",
    "sg:address":"940 N. Sierra Bonita Ave. Unit 9",
    "sg:city":"West Hollywood",
    "sg:classifiers":[
        {
            "category":"Personal",
            "type":"Services"
        }
    ],
    "sg:phone":"+1 800 707 6420",
    "sg:postcode":"90046",
    "sg:province":"CA",
    "sg:tags":[
        "mover"
    ],
    "sg:website":"www.lamoving4u.com",
    "wof:name":"La Moving Inc",
    "wof:placetype":"venue"
},
  "geometry": {"coordinates":[-118.353977,34.088317],"type":"Point"}
}