{
  "type": "Feature",
  "properties": {
    "addr:full":"6993 Dublin Blvd Dublin CA 94568",
    "addr:housenumber":"6993",
    "addr:postcode":"94568",
    "addr:street":"Dublin Blvd",
    "iso:country":"US",
    "sg:address":"6993 Dublin Blvd",
    "sg:city":"Dublin",
    "sg:classifiers":[
        {
            "category":"Personal",
            "subcategory":"Beauty Salon",
            "type":"Services"
        }
    ],
    "sg:phone":"+1 925 829 2515",
    "sg:postcode":"94568",
    "sg:province":"CA",
    "sg:tags":[
        "care",
        "skin"
    ],
    "wof:name":"Hair Emporium",
    "wof:placetype":"venue"
},
  "geometry": {"coordinates":[-121.918677,37.705077],"type":"Point"}
}