{
  "type": "Feature",
  "properties": {
    "addr:full":"15955 Lake Mathews Dr Perris CA 92570",
    "addr:housenumber":"15955",
    "addr:postcode":"92570",
    "addr:street":"Lake Mathews Dr",
    "iso:country":"US",
    "sg:address":"15955 Lake Mathews Dr",
    "sg:city":"Perris",
    "sg:classifiers":[
        {
            "category":"Building & Trades",
            "subcategory":"Construction",
            "type":"Services"
        }
    ],
    "sg:phone":"+1 951 657 9666",
    "sg:postcode":"92570",
    "sg:province":"CA",
    "sg:tags":[
        "sewer",
        "contractor"
    ],
    "wof:name":"Poss & Sons Pipeline",
    "wof:placetype":"venue"
},
  "geometry": {"coordinates":[-117.38445299999999,33.79288],"type":"Point"}
}