{
  "type": "Feature",
  "properties": {
    "iso:country":"US",
    "sg:address":"15955 Lake Mathews Dr",
    "sg:city":"Perris",
    "sg:classifiers":[
        {
            "category":"Building & Trades",
            "subcategory":"Construction",
            "type":"Services"
        }
    ],
    "sg:phone":"+1 951 657 9666",
    "sg:postcode":"92570",
    "sg:province":"CA",
    "sg:tags":[
        "sewer",
        "contractor"
    ],
    "wof:name":"Poss & Sons Pipeline",
    "wof:placetype":"venue"
},
  "geometry": {"coordinates":[-117.384453,33.79288],"type":"Point"}
}