{
  "type": "Feature",
  "properties": {
    "addr:full":"7573 Slater Ave Huntington Beach CA 92647",
    "addr:housenumber":"7573",
    "addr:postcode":"92647",
    "addr:street":"Slater Ave",
    "iso:country":"US",
    "sg:address":"7573 Slater Ave",
    "sg:city":"Huntington Beach",
    "sg:classifiers":[
        {
            "category":"Shopping",
            "subcategory":"Bicycles & Sporting Goods",
            "type":"Retail Goods"
        }
    ],
    "sg:phone":"+1 714 842 8837",
    "sg:postcode":"92647",
    "sg:province":"CA",
    "wof:name":"Chuck Dent Surf Center",
    "wof:placetype":"venue"
},
  "geometry": {"coordinates":[-117.99673300000001,33.708514],"type":"Point"}
}