{
  "type": "Feature",
  "properties": {
    "iso:country":"US",
    "sg:address":"13523 2nd St",
    "sg:city":"Yucaipa",
    "sg:classifiers":[
        {
            "category":"Education",
            "subcategory":"School",
            "type":"Public Place"
        }
    ],
    "sg:phone":"+1 909 790 8570",
    "sg:postcode":"92399",
    "sg:province":"CA",
    "wof:name":"Calimesa Elementary School",
    "wof:placetype":"venue"
},
  "geometry": {"coordinates":[-117.04311800000001,34.007537],"type":"Point"}
}