{
  "type": "Feature",
  "properties": {
    "addr:full":"126 W Branch St Arroyo Grande CA 93420",
    "addr:housenumber":"126",
    "addr:postcode":"93420",
    "addr:street":"W Branch St",
    "iso:country":"US",
    "sg:address":"126 W Branch St",
    "sg:city":"Arroyo Grande",
    "sg:classifiers":[
        {
            "category":"Personal",
            "type":"Services"
        }
    ],
    "sg:phone":"+1 805 235 6199",
    "sg:postcode":"93420",
    "sg:province":"CA",
    "sg:tags":[
        "therapist",
        "massage"
    ],
    "wof:name":"Massage Therapy By Tasha",
    "wof:placetype":"venue"
},
  "geometry": {"coordinates":[-120.58017599999999,35.122878],"type":"Point"}
}