{
  "type": "Feature",
  "properties": {
    "iso:country":"US",
    "sg:address":"1121 Valley Blvd",
    "sg:city":"Tehachapi",
    "sg:classifiers":[
        {
            "category":"Retail",
            "subcategory":"Laundry & Dry Cleaning",
            "type":"Services"
        }
    ],
    "sg:phone":"+1 661 822 3724",
    "sg:postcode":"93561",
    "sg:province":"CA",
    "sg:tags":[
        "cleaners"
    ],
    "wof:name":"Fabricare Cleaners",
    "wof:placetype":"venue"
},
  "geometry": {"coordinates":[-118.46787,35.12423],"type":"Point"}
}