{
  "type": "Feature",
  "properties": {
    "addr:full":"52218 Ave Vallejo La Quinta CA 92253",
    "addr:postcode":"52218;92253",
    "addr:street":"Ave",
    "iso:country":"US",
    "sg:address":"52218 Ave Vallejo",
    "sg:city":"La Quinta",
    "sg:classifiers":[
        {
            "category":"Retail",
            "subcategory":"Laundry & Dry Cleaning",
            "type":"Services"
        }
    ],
    "sg:phone":"+1 760 771 9674",
    "sg:postcode":"92253",
    "sg:province":"CA",
    "sg:tags":[
        "cleaners",
        "rug",
        "carpet"
    ],
    "wof:name":"Victor's Carpet & Upholstery",
    "wof:placetype":"venue"
},
  "geometry": {"coordinates":[-116.310568,33.670503],"type":"Point"}
}