{
  "type": "Feature",
  "properties": {
    "iso:country":"US",
    "sg:address":"417 E 15th St",
    "sg:city":"Los Angeles",
    "sg:classifiers":[
        {
            "category":"Wholesale",
            "subcategory":"Non-durable Goods",
            "type":"Manufacturing & Wholesale Goods"
        }
    ],
    "sg:phone":"+1 213 748 0909",
    "sg:postcode":"90015",
    "sg:province":"CA",
    "wof:name":"Georgiano",
    "wof:placetype":"venue"
},
  "geometry": {"coordinates":[-118.25811400000001,34.032211],"type":"Point"}
}