{
  "type": "Feature",
  "properties": {
    "addr:full":"1600 W Kettleman Ln Lodi CA 95242",
    "addr:housenumber":"1600",
    "addr:postcode":"95242",
    "addr:street":"W Kettleman Ln",
    "iso:country":"US",
    "sg:address":"1600 W Kettleman Ln",
    "sg:city":"Lodi",
    "sg:classifiers":[
        {
            "category":"Insurance",
            "subcategory":"Insurance Agent",
            "type":"Services"
        }
    ],
    "sg:phone":"+1 209 367 3300",
    "sg:postcode":"95242",
    "sg:province":"CA",
    "sg:tags":[
        "claim"
    ],
    "wof:name":"State Farm Insurance",
    "wof:placetype":"venue"
},
  "geometry": {"coordinates":[-121.291889,38.115306],"type":"Point"}
}