{
  "type": "Feature",
  "properties": {
    "addr:full":"330 Tres Pinos Rd Hollister CA 95023",
    "addr:housenumber":"330",
    "addr:postcode":"hollister ca 95023",
    "addr:street":"Tres Pinos Rd",
    "iso:country":"US",
    "sg:address":"330 Tres Pinos Rd",
    "sg:city":"Hollister",
    "sg:classifiers":[
        {
            "category":"Wholesale",
            "subcategory":"Auto Parts",
            "type":"Manufacturing & Wholesale Goods"
        }
    ],
    "sg:phone":"+1 831 638 1365",
    "sg:postcode":"95023",
    "sg:province":"CA",
    "wof:name":"Craps",
    "wof:placetype":"venue"
},
  "geometry": {"coordinates":[-121.396529,36.839644],"type":"Point"}
}