{
  "type": "Feature",
  "properties": {
    "iso:country":"US",
    "sg:address":"3350 W Lincoln Ave",
    "sg:city":"Anaheim",
    "sg:classifiers":[
        {
            "category":"Real Estate",
            "subcategory":"Real Estate Operator",
            "type":"Services"
        }
    ],
    "sg:phone":"+1 714 952 2404",
    "sg:postcode":"92801",
    "sg:province":"CA",
    "sg:tags":[
        "apartment"
    ],
    "wof:name":"Lincoln Heritage Apartments",
    "wof:placetype":"venue"
},
  "geometry": {"coordinates":[-118.004997,33.831902],"type":"Point"}
}