{
  "type": "Feature",
  "properties": {
    "addr:full":"1300 W Shaw Ave Fresno CA 93711",
    "addr:housenumber":"1300",
    "addr:postcode":"93711",
    "addr:street":"W Shaw Ave",
    "iso:country":"US",
    "sg:address":"1300 W Shaw Ave",
    "sg:city":"Fresno",
    "sg:classifiers":[
        {
            "category":"Insurance",
            "subcategory":"Insurance Agent",
            "type":"Services"
        }
    ],
    "sg:phone":"+1 559 224 2023",
    "sg:postcode":"93711",
    "sg:province":"CA",
    "wof:name":"Health Guard",
    "wof:placetype":"venue"
},
  "geometry": {"coordinates":[-119.817403,36.808327],"type":"Point"}
}