{
  "type": "Feature",
  "properties": {
    "addr:full":"2689 1st St Atwater CA 95301",
    "addr:housenumber":"2689",
    "addr:postcode":"95301",
    "addr:street":"1St St",
    "iso:country":"US",
    "sg:address":"2689 1st St",
    "sg:city":"Atwater",
    "sg:classifiers":[
        {
            "category":"Autos & Motor Vehicles",
            "subcategory":"Auto Supplies",
            "type":"Retail Goods"
        },
        {
            "category":"Wholesale",
            "subcategory":"Electrical",
            "type":"Manufacturing & Wholesale Goods"
        }
    ],
    "sg:phone":"+1 209 357 2437",
    "sg:postcode":"95301",
    "sg:province":"CA",
    "sg:tags":[
        "battery",
        "automobile",
        "part",
        "batteries-storage",
        "accessory"
    ],
    "sg:website":"http://www.autozone.com",
    "wof:name":"AutoZone",
    "wof:placetype":"venue"
},
  "geometry": {"coordinates":[-120.595913,37.360368],"type":"Point"}
}