{
  "type": "Feature",
  "properties": {
    "iso:country":"US",
    "sg:address":"6330 Florin Rd",
    "sg:city":"Sacramento",
    "sg:classifiers":[
        {
            "category":"Shopping",
            "subcategory":"Tobacco",
            "type":"Retail Goods"
        }
    ],
    "sg:phone":"+1 916 392 9229",
    "sg:postcode":"95823",
    "sg:province":"CA",
    "sg:tags":[
        "cigarette",
        "product",
        "cigar",
        "dealer"
    ],
    "wof:name":"Cigarette Store The",
    "wof:placetype":"venue"
},
  "geometry": {"coordinates":[-121.429367,38.495976],"type":"Point"}
}