{
  "type": "Feature",
  "properties": {
    "iso:country":"US",
    "sg:address":"30 Monte Cimas Ave",
    "sg:city":"Mill Valley",
    "sg:classifiers":[
        {
            "category":"Professional",
            "subcategory":"Detective & Security Services",
            "type":"Services"
        }
    ],
    "sg:phone":"+1 415 381 9320",
    "sg:postcode":"94941",
    "sg:province":"CA",
    "sg:tags":[
        "investigator"
    ],
    "wof:name":"JGC Investigation",
    "wof:placetype":"venue"
},
  "geometry": {"coordinates":[-122.562915,37.900855],"type":"Point"}
}