{
  "type": "Feature",
  "properties": {
    "addr:full":"222 3rd Ave Chula Vista CA 91910",
    "addr:housenumber":"222",
    "addr:postcode":"91910",
    "addr:street":"3Rd Ave",
    "iso:country":"US",
    "sg:address":"222 3rd Ave",
    "sg:city":"Chula Vista",
    "sg:classifiers":[
        {
            "category":"Insurance",
            "subcategory":"Insurance Agent",
            "type":"Services"
        }
    ],
    "sg:phone":"+1 619 420 1861",
    "sg:postcode":"91910",
    "sg:province":"CA",
    "wof:name":"Kemjoy Corp-Hoffman Hanono",
    "wof:placetype":"venue"
},
  "geometry": {"coordinates":[-117.080915,32.643767],"type":"Point"}
}