{
  "type": "Feature",
  "properties": {
    "iso:country":"US",
    "sg:address":"23236 Lyons Ave",
    "sg:city":"Santa Clarita",
    "sg:classifiers":[
        {
            "category":"Real Estate",
            "subcategory":"Real Estate Agent",
            "type":"Services"
        }
    ],
    "sg:phone":"+1 661 287 1670",
    "sg:postcode":"91321",
    "sg:province":"CA",
    "sg:tags":[
        "appraiser"
    ],
    "wof:name":"Reid Appraisal Svc",
    "wof:placetype":"venue"
},
  "geometry": {"coordinates":[-118.538877,34.379819],"type":"Point"}
}