{
  "type": "Feature",
  "properties": {
    "addr:full":"13710 Studebaker Rd Ste 100 Norwalk CA 90650",
    "addr:housenumber":"13710",
    "addr:postcode":"90650",
    "addr:street":"Studebaker Rd Ste 100",
    "iso:country":"US",
    "sg:address":"13710 Studebaker Rd Ste 100",
    "sg:city":"Norwalk",
    "sg:classifiers":[
        {
            "category":"Health Services",
            "subcategory":"Doctor",
            "type":"Services"
        }
    ],
    "sg:phone":"+1 562 929 9625",
    "sg:postcode":"90650",
    "sg:province":"CA",
    "wof:name":"Lobarbio-Banares Minerva MD",
    "wof:placetype":"venue"
},
  "geometry": {"coordinates":[-118.09899900000001,33.907299],"type":"Point"}
}