{
  "type": "Feature",
  "properties": {
    "iso:country":"US",
    "sg:address":"73140 Hwy 111",
    "sg:city":"Palm Desert",
    "sg:classifiers":[
        {
            "category":"Home & Garden",
            "subcategory":"Home Furnishings",
            "type":"Retail Goods"
        }
    ],
    "sg:phone":"+1 760 568 2681",
    "sg:postcode":"92260",
    "sg:province":"CA",
    "sg:tags":[
        "interior",
        "product"
    ],
    "wof:name":"Walls & More",
    "wof:placetype":"venue"
},
  "geometry": {"coordinates":[-116.388729,33.721508],"type":"Point"}
}