{
  "type": "Feature",
  "properties": {
    "iso:country":"US",
    "sg:address":"4012 Foothills Blvd",
    "sg:city":"Roseville",
    "sg:classifiers":[
        {
            "category":"Shopping",
            "type":"Retail Goods"
        }
    ],
    "sg:phone":"+1 916 789 7892",
    "sg:postcode":"95747",
    "sg:province":"CA",
    "sg:tags":[
        "telephone",
        "cellular"
    ],
    "sg:website":"www.dishmount.com",
    "wof:name":"Factory Direct Cingular Store",
    "wof:placetype":"venue"
},
  "geometry": {"coordinates":[-121.309032,38.743935],"type":"Point"}
}