{
  "type": "Feature",
  "properties": {
    "addr:full":"1615 Bonanza St Walnut Creek CA 94596",
    "addr:housenumber":"1615",
    "addr:postcode":"94596",
    "addr:street":"Bonanza St",
    "iso:country":"US",
    "sg:address":"1615 Bonanza St",
    "sg:city":"Walnut Creek",
    "sg:classifiers":[
        {
            "category":"Professional",
            "subcategory":"Research",
            "type":"Services"
        }
    ],
    "sg:phone":"+1 925 938 9300",
    "sg:postcode":"94596",
    "sg:province":"CA",
    "sg:tags":[
        "foundation",
        "philanthropic"
    ],
    "sg:website":"www.nfxf.org",
    "wof:name":"National Fragile X Foundation",
    "wof:placetype":"venue"
},
  "geometry": {"coordinates":[-122.063345,37.899256],"type":"Point"}
}