{
  "type": "Feature",
  "properties": {
    "addr:full":"1919 3rd St Livermore CA 94550",
    "addr:housenumber":"1919",
    "addr:postcode":"94550",
    "addr:street":"3Rd St",
    "iso:country":"US",
    "sg:address":"1919 3rd St",
    "sg:city":"Livermore",
    "sg:classifiers":[
        {
            "category":"Professional",
            "subcategory":"Lawyer & Legal Services",
            "type":"Services"
        }
    ],
    "sg:phone":"+1 925 454 8580",
    "sg:postcode":"94550",
    "sg:province":"CA",
    "sg:tags":[
        "attorney"
    ],
    "wof:name":"Sidney Alegre Law Office",
    "wof:placetype":"venue"
},
  "geometry": {"coordinates":[-121.770788,37.67929],"type":"Point"}
}