{
  "type": "Feature",
  "properties": {
    "iso:country":"US",
    "sg:address":"2909 Thornton Ave",
    "sg:city":"Burbank",
    "sg:classifiers":[
        {
            "category":"Communications",
            "subcategory":"Film & Video Production",
            "type":"Services"
        }
    ],
    "sg:phone":"+1 818 846 6256",
    "sg:postcode":"91504",
    "sg:province":"CA",
    "sg:tags":[
        "motion",
        "picture",
        "studio",
        "producer"
    ],
    "sg:website":"www.designsetters.com",
    "wof:name":"Design Setters Corp",
    "wof:placetype":"venue"
},
  "geometry": {"coordinates":[-118.340256,34.195625],"type":"Point"}
}