{
  "type": "Feature",
  "properties": {
    "addr:full":"50 Iron Point Cir Ste 200 Folsom CA 95630",
    "addr:housenumber":"50",
    "addr:postcode":"95630",
    "addr:street":"Iron Point Cir Ste 200",
    "iso:country":"US",
    "sg:address":"50 Iron Point Cir Ste 200",
    "sg:city":"Folsom",
    "sg:classifiers":[
        {
            "category":"Banks & Credit Unions",
            "subcategory":"Financial Services",
            "type":"Services"
        }
    ],
    "sg:phone":"+1 916 996 4621",
    "sg:postcode":"95630",
    "sg:province":"CA",
    "sg:tags":[
        "mortgage"
    ],
    "wof:name":"Peak Financial Group",
    "wof:placetype":"venue"
},
  "geometry": {"coordinates":[-121.143168,38.643489],"type":"Point"}
}