{
  "type": "Feature",
  "properties": {
    "iso:country":"US",
    "sg:address":"2730 Middlefield Rd",
    "sg:city":"Palo Alto",
    "sg:classifiers":[
        {
            "category":"Restaurant",
            "type":"Food & Drink"
        }
    ],
    "sg:menulink":"http://www.allmenus.com/ca/san-jose/77799-papa-murphys/menu/",
    "sg:phone":"+1 650 328 5200",
    "sg:postcode":"94306",
    "sg:province":"CA",
    "sg:tags":[
        "american",
        "pizza"
    ],
    "wof:name":"Papa Murphy's",
    "wof:placetype":"venue"
},
  "geometry": {"coordinates":[-122.129561,37.433148],"type":"Point"}
}