{
  "type": "Feature",
  "properties": {
    "iso:country":"US",
    "sg:address":"408 Turner Dr",
    "sg:city":"Benicia",
    "sg:classifiers":[
        {
            "category":"Professional",
            "subcategory":"Accounting & Tax Preparation",
            "type":"Services"
        }
    ],
    "sg:phone":"+1 707 315 6876",
    "sg:postcode":"94510",
    "sg:province":"CA",
    "wof:name":"Thomason Enterprises",
    "wof:placetype":"venue"
},
  "geometry": {"coordinates":[-122.170895,38.070778],"type":"Point"}
}