{
  "type": "Feature",
  "properties": {
    "iso:country":"US",
    "sg:address":"1548 15th St",
    "sg:city":"San Francisco",
    "sg:classifiers":[
        {
            "category":"Wholesale",
            "subcategory":"Photographic Equipment",
            "type":"Manufacturing & Wholesale Goods"
        }
    ],
    "sg:phone":"+1 415 861 4733",
    "sg:postcode":"94103",
    "sg:province":"CA",
    "sg:tags":[
        "audio"
    ],
    "wof:name":"San Francisco Audio Tint",
    "wof:placetype":"venue"
},
  "geometry": {"coordinates":[-122.418403,37.76676],"type":"Point"}
}