{
  "type": "Feature",
  "properties": {
    "addr:full":"2011 Cordoba Pl Carlsbad CA 92008",
    "addr:housenumber":"2011",
    "addr:postcode":"92008",
    "addr:street":"Cordoba Pl",
    "iso:country":"US",
    "sg:address":"2011 Cordoba Pl",
    "sg:city":"Carlsbad",
    "sg:classifiers":[
        {
            "category":"Manufacturing",
            "subcategory":"Motor Vehicles & Parts",
            "type":"Manufacturing & Wholesale Goods"
        }
    ],
    "sg:phone":"+1 760 729 6025",
    "sg:postcode":"92008",
    "sg:province":"CA",
    "sg:tags":[
        "mfg",
        "trimming"
    ],
    "wof:name":"Henry L Peterson Dr",
    "wof:placetype":"venue"
},
  "geometry": {"coordinates":[-117.313652,33.146693],"type":"Point"}
}