{
  "type": "Feature",
  "properties": {
    "addr:full":"12234 Norino Dr Whittier CA 90601",
    "addr:housenumber":"12234",
    "addr:postcode":"90601",
    "addr:street":"Norino Dr",
    "iso:country":"US",
    "sg:address":"12234 Norino Dr",
    "sg:city":"Whittier",
    "sg:classifiers":[
        {
            "category":"Real Estate",
            "subcategory":"Real Estate Agent",
            "type":"Services"
        }
    ],
    "sg:phone":"+1 562 692 9121",
    "sg:postcode":"90601",
    "sg:province":"CA",
    "wof:name":"Amodeo Realty",
    "wof:placetype":"venue"
},
  "geometry": {"coordinates":[-118.04650700000001,33.995207],"type":"Point"}
}