{
  "type": "Feature",
  "properties": {
    "addr:full":"630 Melrose Pl Vista CA 92083",
    "addr:housenumber":"630",
    "addr:postcode":"92083",
    "addr:street":"Melrose Pl",
    "iso:country":"US",
    "sg:address":"630 Melrose Pl",
    "sg:city":"Vista",
    "sg:classifiers":[
        {
            "category":"Health Services",
            "subcategory":"Doctor",
            "type":"Services"
        }
    ],
    "sg:phone":"+1 760 724 2284",
    "sg:postcode":"92083",
    "sg:province":"CA",
    "sg:tags":[
        "dentist"
    ],
    "wof:name":"Robert P Lozuk DDS",
    "wof:placetype":"venue"
},
  "geometry": {"coordinates":[-117.254667,33.209743],"type":"Point"}
}