{
  "type": "Feature",
  "properties": {
    "iso:country":"US",
    "sg:address":"22 College Ter",
    "sg:city":"San Francisco",
    "sg:classifiers":[
        {
            "category":"Manufacturing",
            "subcategory":"Jewelry",
            "type":"Manufacturing & Wholesale Goods"
        }
    ],
    "sg:phone":"+1 415 337 5645",
    "sg:postcode":"94112",
    "sg:province":"CA",
    "sg:tags":[
        "precious",
        "metal",
        "mfg"
    ],
    "wof:name":"Sulipa",
    "wof:placetype":"venue"
},
  "geometry": {"coordinates":[-122.426447,37.734774],"type":"Point"}
}