{
  "type": "Feature",
  "properties": {
    "addr:full":"1600 Pine St Redding CA 96001",
    "addr:housenumber":"1600",
    "addr:postcode":"96001",
    "addr:street":"Pine St",
    "iso:country":"US",
    "sg:address":"1600 Pine St",
    "sg:city":"Redding",
    "sg:classifiers":[
        {
            "category":"Retail",
            "subcategory":"Driving School",
            "type":"Services"
        }
    ],
    "sg:phone":"+1 530 245 0630",
    "sg:postcode":"96001",
    "sg:province":"CA",
    "sg:tags":[
        "instruction",
        "traffic"
    ],
    "wof:name":"California Classic Traffic School",
    "wof:placetype":"venue"
},
  "geometry": {"coordinates":[-122.462086,40.627878],"type":"Point"}
}