{
  "type": "Feature",
  "properties": {
    "addr:full":"111 Technology Drive Irvine CA 92618",
    "addr:housenumber":"111",
    "addr:postcode":"92618",
    "addr:street":"Technology Drive",
    "iso:country":"US",
    "sg:address":"111 Technology Drive",
    "sg:city":"Irvine",
    "sg:classifiers":[
        {
            "category":"Building & Trades",
            "subcategory":"Locksmith",
            "type":"Services"
        }
    ],
    "sg:phone":"+1 949 471 0010",
    "sg:postcode":"92618",
    "sg:province":"CA",
    "sg:tags":[
        "key"
    ],
    "wof:name":"AAA Locksmith",
    "wof:placetype":"venue"
},
  "geometry": {"coordinates":[-117.743128,33.659864],"type":"Point"}
}