{
  "type": "Feature",
  "properties": {
    "addr:full":"986 Kaiser Rd Napa CA 94558",
    "addr:housenumber":"986",
    "addr:postcode":"94558",
    "addr:street":"Kaiser Rd",
    "iso:country":"US",
    "sg:address":"986 Kaiser Rd",
    "sg:city":"Napa",
    "sg:classifiers":[
        {
            "category":"Professional",
            "type":"Services"
        }
    ],
    "sg:phone":"+1 707 258 0553",
    "sg:postcode":"94558",
    "sg:province":"CA",
    "sg:tags":[
        "establishment"
    ],
    "wof:name":"Heritage Systems Inc",
    "wof:placetype":"venue"
},
  "geometry": {"coordinates":[-122.27524099999999,38.257617],"type":"Point"}
}