{
  "type": "Feature",
  "properties": {
    "addr:full":"2708 Foothill Blvd La Crescenta CA 91214",
    "addr:housenumber":"2708",
    "addr:postcode":"91214",
    "addr:street":"Foothill Blvd",
    "iso:country":"US",
    "sg:address":"2708 Foothill Blvd",
    "sg:city":"La Crescenta",
    "sg:classifiers":[
        {
            "category":"Building & Trades",
            "subcategory":"Cleaning & Sanitation",
            "type":"Services"
        }
    ],
    "sg:phone":"+1 818 248 2467",
    "sg:postcode":"91214",
    "sg:province":"CA",
    "sg:tags":[
        "house",
        "window",
        "washing"
    ],
    "wof:name":"Kevin's Professional Window Washing",
    "wof:placetype":"venue"
},
  "geometry": {"coordinates":[-118.237863,34.222687],"type":"Point"}
}