{
  "type": "Feature",
  "properties": {
    "addr:full":"6736 Palm Ave Riverside CA 92506",
    "addr:housenumber":"6736",
    "addr:postcode":"92506",
    "addr:street":"Palm Ave",
    "iso:country":"US",
    "sg:address":"6736 Palm Ave",
    "sg:city":"Riverside",
    "sg:classifiers":[
        {
            "category":"Health Services",
            "subcategory":"Nursing And Care Facility",
            "type":"Services"
        },
        {
            "category":"Health Services",
            "subcategory":"Clinic",
            "type":"Services"
        }
    ],
    "sg:phone":"+1 951 784 1388",
    "sg:postcode":"92506",
    "sg:province":"CA",
    "sg:tags":[
        "skilled"
    ],
    "wof:name":"Chapman Hospice",
    "wof:placetype":"venue"
},
  "geometry": {"coordinates":[-117.401009,33.95007],"type":"Point"}
}