{
  "type": "Feature",
  "properties": {
    "iso:country":"US",
    "sg:address":"14930 Calvert St",
    "sg:city":"Van Nuys",
    "sg:classifiers":[
        {
            "category":"Shopping",
            "type":"Retail Goods"
        }
    ],
    "sg:phone":"+1 818 989 3320",
    "sg:postcode":"91411",
    "sg:province":"CA",
    "sg:tags":[
        "consultant",
        "art"
    ],
    "wof:name":"Saltman Art",
    "wof:placetype":"venue"
},
  "geometry": {"coordinates":[-118.460835,34.18112],"type":"Point"}
}