{
  "type": "Feature",
  "properties": {
    "addr:full":"27383 Pso Sienna San Juan Capistrano CA 92675",
    "addr:postcode":"27383;92675",
    "addr:street":"Sienna",
    "iso:country":"US",
    "sg:address":"27383 Pso Sienna",
    "sg:city":"San Juan Capistrano",
    "sg:classifiers":[
        {
            "category":"Insurance",
            "subcategory":"Insurance Agent",
            "type":"Services"
        }
    ],
    "sg:phone":"+1 949 240 9998",
    "sg:postcode":"92675",
    "sg:province":"CA",
    "wof:name":"K L Woods",
    "wof:placetype":"venue"
},
  "geometry": {"coordinates":[-117.65181200000001,33.491756],"type":"Point"}
}