{
  "type": "Feature",
  "properties": {
    "iso:country":"US",
    "sg:address":"14701 Friar St",
    "sg:city":"Van Nuys",
    "sg:classifiers":[
        {
            "category":"Organizations",
            "subcategory":"Religious Organization",
            "type":"Services"
        }
    ],
    "sg:phone":"+1 818 786 6231",
    "sg:postcode":"91411",
    "sg:province":"CA",
    "sg:tags":[
        "child",
        "day",
        "care"
    ],
    "wof:name":"Iglesia Roca Be Salvacion",
    "wof:placetype":"venue"
},
  "geometry": {"coordinates":[-118.457447,34.185666],"type":"Point"}
}