{
  "type": "Feature",
  "properties": {
    "iso:country":"US",
    "sg:address":"21243 Ventura Blvd",
    "sg:city":"Woodland Hills",
    "sg:classifiers":[
        {
            "category":"Manufacturing",
            "subcategory":"Electronics",
            "type":"Manufacturing & Wholesale Goods"
        }
    ],
    "sg:phone":"+1 818 703 0835",
    "sg:postcode":"91364",
    "sg:province":"CA",
    "sg:tags":[
        "equipment",
        "electronic",
        "supply"
    ],
    "wof:name":"Linear Technology Corp",
    "wof:placetype":"venue"
},
  "geometry": {"coordinates":[-118.595209,34.167462],"type":"Point"}
}