{
  "type": "Feature",
  "properties": {
    "addr:full":"991 Corte Azal Camarillo CA 93010",
    "addr:housenumber":"991",
    "addr:postcode":"93010",
    "addr:street":"Corte Azal",
    "iso:country":"US",
    "sg:address":"991 Corte Azal",
    "sg:city":"Camarillo",
    "sg:classifiers":[
        {
            "category":"Wholesale",
            "subcategory":"Electrical",
            "type":"Manufacturing & Wholesale Goods"
        }
    ],
    "sg:phone":"+1 805 445 1016",
    "sg:postcode":"93010",
    "sg:province":"CA",
    "sg:tags":[
        "equipment"
    ],
    "wof:name":"S&J Sales",
    "wof:placetype":"venue"
},
  "geometry": {"coordinates":[-119.05638399999999,34.234082],"type":"Point"}
}