{
  "type": "Feature",
  "properties": {
    "addr:full":"30732 Via Norte Temecula CA 92591",
    "addr:housenumber":"30732",
    "addr:postcode":"92591",
    "addr:street":"Via Norte",
    "iso:country":"US",
    "sg:address":"30732 Via Norte",
    "sg:city":"Temecula",
    "sg:classifiers":[
        {
            "category":"Building & Trades",
            "subcategory":"Electrical",
            "type":"Services"
        }
    ],
    "sg:phone":"+1 951 676 5763",
    "sg:postcode":"92591",
    "sg:province":"CA",
    "sg:tags":[
        "electrical",
        "contractor"
    ],
    "wof:name":"Ingram Electric of California",
    "wof:placetype":"venue"
},
  "geometry": {"coordinates":[-117.12253,33.532358],"type":"Point"}
}