{
  "type": "Feature",
  "properties": {
    "iso:country":"US",
    "sg:address":"9984 Scripps Ranch Blvd",
    "sg:city":"San Diego",
    "sg:classifiers":[
        {
            "category":"Shopping",
            "subcategory":"Bicycles & Sporting Goods",
            "type":"Retail Goods"
        }
    ],
    "sg:phone":"+1 858 547 9707",
    "sg:postcode":"92131",
    "sg:province":"CA",
    "sg:tags":[
        "equipment",
        "tennis",
        "supply"
    ],
    "wof:name":"Just Tennis",
    "wof:placetype":"venue"
},
  "geometry": {"coordinates":[-117.09843499999999,32.902921],"type":"Point"}
}