{
  "type": "Feature",
  "properties": {
    "iso:country":"US",
    "sg:address":"18551 Von Karman Ave",
    "sg:city":"Irvine",
    "sg:classifiers":[
        {
            "category":"Insurance",
            "subcategory":"Insurance Agent",
            "type":"Services"
        }
    ],
    "sg:phone":"+1 949 253 4062",
    "sg:postcode":"92612",
    "sg:province":"CA",
    "wof:name":"Consolidated Org Cnty",
    "wof:placetype":"venue"
},
  "geometry": {"coordinates":[-117.85485,33.674342],"type":"Point"}
}