{
  "type": "Feature",
  "properties": {
    "addr:full":"1602 State St Santa Barbara CA 93101",
    "addr:housenumber":"1602",
    "addr:postcode":"93101",
    "addr:street":"State St",
    "iso:country":"US",
    "sg:address":"1602 State St",
    "sg:city":"Santa Barbara",
    "sg:classifiers":[
        {
            "category":"Professional",
            "subcategory":"Lawyer & Legal Services",
            "type":"Services"
        }
    ],
    "sg:phone":"+1 805 897 1830",
    "sg:postcode":"93101",
    "sg:province":"CA",
    "sg:tags":[
        "attorney"
    ],
    "wof:name":"Zilinskas & Woosley",
    "wof:placetype":"venue"
},
  "geometry": {"coordinates":[-119.710773,34.428066],"type":"Point"}
}