{
  "type": "Feature",
  "properties": {
    "iso:country":"US",
    "sg:address":"1919 W Redondo Beach Blvd",
    "sg:city":"Gardena",
    "sg:classifiers":[
        {
            "category":"Insurance",
            "subcategory":"Insurance Agent",
            "type":"Services"
        }
    ],
    "sg:phone":"+1 310 515 2125",
    "sg:postcode":"90247",
    "sg:province":"CA",
    "wof:name":"Farmers Insurance",
    "wof:placetype":"venue"
},
  "geometry": {"coordinates":[-118.310611,33.888045],"type":"Point"}
}