{
  "type": "Feature",
  "properties": {
    "addr:full":"4211 Eagle Rock Blvd Los Angeles CA 90065",
    "addr:housenumber":"4211",
    "addr:postcode":"90065",
    "addr:street":"Eagle Rock Blvd",
    "iso:country":"US",
    "sg:address":"4211 Eagle Rock Blvd",
    "sg:city":"Los Angeles",
    "sg:classifiers":[
        {
            "category":"Food & Beverages",
            "subcategory":"Groceries & Convenience Stores",
            "type":"Retail Goods"
        }
    ],
    "sg:phone":"+1 323 255 9993",
    "sg:postcode":"90065",
    "sg:province":"CA",
    "sg:tags":[
        "grocer"
    ],
    "wof:name":"Albertsons",
    "wof:placetype":"venue"
},
  "geometry": {"coordinates":[-118.22469700000001,34.122205],"type":"Point"}
}