{
  "type": "Feature",
  "properties": {
    "addr:full":"703 N Anaheim Blvd Anaheim CA 92805",
    "addr:housenumber":"703",
    "addr:postcode":"92805",
    "addr:street":"N Anaheim Blvd",
    "iso:country":"US",
    "sg:address":"703 N Anaheim Blvd",
    "sg:city":"Anaheim",
    "sg:classifiers":[
        {
            "category":"Manufacturing",
            "subcategory":"Printing",
            "type":"Manufacturing & Wholesale Goods"
        }
    ],
    "sg:phone":"+1 714 774 0555",
    "sg:postcode":"92805",
    "sg:province":"CA",
    "sg:tags":[
        "copying",
        "offset"
    ],
    "wof:name":"All-Star Printers & Copying",
    "wof:placetype":"venue"
},
  "geometry": {"coordinates":[-117.916828,33.844178],"type":"Point"}
}