{
  "type": "Feature",
  "properties": {
    "addr:full":"1998 Broadyway Suite 806 San Francisco CA 94109",
    "addr:housenumber":"1998;suite 806",
    "addr:postcode":"94109",
    "addr:street":"Broadyway",
    "iso:country":"US",
    "sg:address":"1998 Broadyway Suite 806",
    "sg:city":"San Francisco",
    "sg:classifiers":[
        {
            "category":"Professional",
            "subcategory":"Computer Services",
            "type":"Services"
        }
    ],
    "sg:postcode":"94109",
    "sg:province":"CA",
    "sg:tags":[
        "software-development",
        "nearshore-development",
        "experienced-developers"
    ],
    "sg:website":"http://www.openmountain.com",
    "wof:name":"Open Mountain",
    "wof:placetype":"venue"
},
  "geometry": {"coordinates":[-122.428344,37.795106],"type":"Point"}
}