{
  "type": "Feature",
  "properties": {
    "iso:country":"US",
    "sg:address":"2019 W Ave J",
    "sg:city":"Lancaster",
    "sg:classifiers":[
        {
            "category":"Personal",
            "subcategory":"Beauty Salon",
            "type":"Services"
        }
    ],
    "sg:phone":"+1 661 945 4626",
    "sg:postcode":"93536",
    "sg:province":"CA",
    "wof:name":"Sisters Beauty Salon",
    "wof:placetype":"venue"
},
  "geometry": {"coordinates":[-118.165801,34.689405],"type":"Point"}
}