{
  "type": "Feature",
  "properties": {
    "iso:country":"US",
    "sg:address":"21372 High Country Dr",
    "sg:city":"Trabuco Canyon",
    "sg:classifiers":[
        {
            "category":"Organizations",
            "subcategory":"Non-profit Organization",
            "type":"Services"
        }
    ],
    "sg:phone":"+1 949 766 5101",
    "sg:postcode":"92679",
    "sg:province":"CA",
    "sg:tags":[
        "social"
    ],
    "wof:name":"Performance Dynamix",
    "wof:placetype":"venue"
},
  "geometry": {"coordinates":[-117.56883000000001,33.649527],"type":"Point"}
}