{
  "type": "Feature",
  "properties": {
    "addr:full":"22521 Main St Hayward CA 94541",
    "addr:housenumber":"22521",
    "addr:postcode":"94541",
    "addr:street":"Main St",
    "iso:country":"US",
    "sg:address":"22521 Main St",
    "sg:city":"Hayward",
    "sg:classifiers":[
        {
            "category":"Food & Beverages",
            "subcategory":"Candy",
            "type":"Retail Goods"
        },
        {
            "category":"Bakery",
            "type":"Food & Drink"
        }
    ],
    "sg:phone":"+1 510 537 5850",
    "sg:postcode":"94541",
    "sg:province":"CA",
    "sg:tags":[
        "dessert"
    ],
    "sg:website":"www.swissdelices.com",
    "wof:name":"Swiss Delices",
    "wof:placetype":"venue"
},
  "geometry": {"coordinates":[-122.083456,37.673632],"type":"Point"}
}