{
  "type": "Feature",
  "properties": {
    "addr:full":"150 S Auburn St Grass Valley CA 95945",
    "addr:housenumber":"150",
    "addr:postcode":"95945",
    "addr:street":"S Auburn St",
    "iso:country":"US",
    "sg:address":"150 S Auburn St",
    "sg:city":"Grass Valley",
    "sg:classifiers":[
        {
            "category":"Personal",
            "subcategory":"Beauty Salon",
            "type":"Services"
        }
    ],
    "sg:phone":"+1 530 274 0716",
    "sg:postcode":"95945",
    "sg:province":"CA",
    "wof:name":"Cutting Edge Salon",
    "wof:placetype":"venue"
},
  "geometry": {"coordinates":[-121.06196799999999,39.217719],"type":"Point"}
}