{
  "type": "Feature",
  "properties": {
    "addr:full":"2920 Columbia St Torrance CA 90503",
    "addr:housenumber":"2920",
    "addr:postcode":"90503",
    "addr:street":"Columbia St",
    "iso:country":"US",
    "sg:address":"2920 Columbia St",
    "sg:city":"Torrance",
    "sg:classifiers":[
        {
            "category":"Building & Trades",
            "subcategory":"Plumbing",
            "type":"Services"
        }
    ],
    "sg:phone":"+1 310 782 7114",
    "sg:postcode":"90503",
    "sg:province":"CA",
    "sg:tags":[
        "clean",
        "boilers-repair"
    ],
    "wof:name":"Piping & Boiler Specialists",
    "wof:placetype":"venue"
},
  "geometry": {"coordinates":[-118.339567,33.844149],"type":"Point"}
}