{
  "type": "Feature",
  "properties": {
    "iso:country":"US",
    "sg:address":"626 E Alisal St",
    "sg:city":"Salinas",
    "sg:classifiers":[
        {
            "category":"Restaurant",
            "type":"Food & Drink"
        }
    ],
    "sg:phone":"+1 831 771 0425",
    "sg:postcode":"93905",
    "sg:province":"CA",
    "wof:name":"Tacos Y Antojitos Mexicanos",
    "wof:placetype":"venue"
},
  "geometry": {"coordinates":[-121.634775,36.673614],"type":"Point"}
}