{
  "type": "Feature",
  "properties": {
    "iso:country":"US",
    "sg:address":"425 W Broadway",
    "sg:city":"Glendale",
    "sg:classifiers":[
        {
            "category":"Professional",
            "subcategory":"Lawyer & Legal Services",
            "type":"Services"
        }
    ],
    "sg:phone":"+1 818 547 0005",
    "sg:postcode":"91204",
    "sg:province":"CA",
    "wof:name":"Krass Louis Law Office of",
    "wof:placetype":"venue"
},
  "geometry": {"coordinates":[-118.262001,34.146801],"type":"Point"}
}