{
  "type": "Feature",
  "properties": {
    "iso:country":"US",
    "sg:address":"2700 Colorado Boulevard",
    "sg:city":"Los Angeles",
    "sg:classifiers":[
        {
            "category":"Sports & Exercise",
            "subcategory":"Bicycle Rental",
            "type":"Entertainment"
        }
    ],
    "sg:phone":"+1 323 256 7335",
    "sg:postcode":"90041",
    "sg:province":"CA",
    "sg:tags":[
        "wear"
    ],
    "wof:name":"Foot Locker Store",
    "wof:placetype":"venue"
},
  "geometry": {"coordinates":[-118.224585,34.142757],"type":"Point"}
}