{
  "type": "Feature",
  "properties": {
    "addr:full":"440 E Redondo Beach Boulevard Gardena CA 90248",
    "addr:housenumber":"440",
    "addr:postcode":"90248",
    "addr:street":"E Redondo Beach Boulevard",
    "iso:country":"US",
    "sg:address":"440 E Redondo Beach Boulevard",
    "sg:city":"Gardena",
    "sg:classifiers":[
        {
            "category":"Retail",
            "subcategory":"Auto Repair",
            "type":"Services"
        }
    ],
    "sg:phone":"+1 310 327 2950",
    "sg:postcode":"90248",
    "sg:province":"CA",
    "wof:name":"Thomas Auto Salvage",
    "wof:placetype":"venue"
},
  "geometry": {"coordinates":[-118.26895399999999,33.893018],"type":"Point"}
}