{
  "type": "Feature",
  "properties": {
    "iso:country":"US",
    "sg:address":"1100 H St",
    "sg:city":"Modesto",
    "sg:classifiers":[
        {
            "category":"Education",
            "subcategory":"Library",
            "type":"Public Place"
        }
    ],
    "sg:phone":"+1 209 558 7814",
    "sg:postcode":"95354",
    "sg:province":"CA",
    "wof:name":"Modesto Library",
    "wof:placetype":"venue"
},
  "geometry": {"coordinates":[-120.996047,37.640009],"type":"Point"}
}