{
  "type": "Feature",
  "properties": {
    "iso:country":"US",
    "sg:address":"2445 S Watney Way",
    "sg:city":"Fairfield",
    "sg:classifiers":[
        {
            "category":"Manufacturing",
            "subcategory":"Food",
            "type":"Manufacturing & Wholesale Goods"
        }
    ],
    "sg:phone":"+1 707 435 1140",
    "sg:postcode":"94533",
    "sg:province":"CA",
    "sg:tags":[
        "mfg"
    ],
    "wof:name":"Thompson Candy Company LLC",
    "wof:placetype":"venue"
},
  "geometry": {"coordinates":[-122.07719400000001,38.231907],"type":"Point"}
}