{
  "type": "Feature",
  "properties": {
    "addr:full":"4611 Opal St Riverside CA 92509",
    "addr:housenumber":"4611",
    "addr:postcode":"92509",
    "addr:street":"Opal St",
    "iso:country":"US",
    "sg:address":"4611 Opal St",
    "sg:city":"Riverside",
    "sg:classifiers":[
        {
            "category":"Building & Trades",
            "subcategory":"Construction",
            "type":"Services"
        }
    ],
    "sg:phone":"+1 951 369 6117",
    "sg:postcode":"92509",
    "sg:province":"CA",
    "sg:tags":[
        "concrete",
        "contractor"
    ],
    "wof:name":"Pwa Concrete Construction",
    "wof:placetype":"venue"
},
  "geometry": {"coordinates":[-117.42885,33.992979],"type":"Point"}
}