{
  "type": "Feature",
  "properties": {
    "iso:country":"US",
    "sg:address":"917 Dana Dr",
    "sg:city":"Redding",
    "sg:classifiers":[
        {
            "category":"Personal",
            "subcategory":"Beauty Salon",
            "type":"Services"
        }
    ],
    "sg:phone":"+1 530 221 6827",
    "sg:postcode":"96003",
    "sg:province":"CA",
    "wof:name":"Xpert Hair Cuts",
    "wof:placetype":"venue"
},
  "geometry": {"coordinates":[-122.357225,40.58628],"type":"Point"}
}