{
  "type": "Feature",
  "properties": {
    "iso:country":"US",
    "sg:address":"5070 Foothills Blvd",
    "sg:city":"Roseville",
    "sg:classifiers":[
        {
            "category":"Personal",
            "subcategory":"Beauty Salon",
            "type":"Services"
        }
    ],
    "sg:phone":"+1 916 781 7638",
    "sg:postcode":"95747",
    "sg:province":"CA",
    "sg:tags":[
        "manicuring"
    ],
    "wof:name":"Top Ten Nails",
    "wof:placetype":"venue"
},
  "geometry": {"coordinates":[-121.309085,38.752465],"type":"Point"}
}