{
  "type": "Feature",
  "properties": {
    "addr:full":"7747 Yolanda Ave Reseda CA 91335",
    "addr:housenumber":"7747",
    "addr:postcode":"91335",
    "addr:street":"Yolanda Ave",
    "iso:country":"US",
    "sg:address":"7747 Yolanda Ave",
    "sg:city":"Reseda",
    "sg:classifiers":[
        {
            "category":"Personal",
            "subcategory":"Beauty Salon",
            "type":"Services"
        }
    ],
    "sg:phone":"+1 818 343 6874",
    "sg:postcode":"91335",
    "sg:province":"CA",
    "wof:name":"Future Nails",
    "wof:placetype":"venue"
},
  "geometry": {"coordinates":[-118.540504,34.210383],"type":"Point"}
}