{
  "type": "Feature",
  "properties": {
    "addr:full":"2132 S San Pedro Street Los Angeles CA 90011",
    "addr:housenumber":"2132",
    "addr:postcode":"90011",
    "addr:street":"S San Pedro Street",
    "iso:country":"US",
    "sg:address":"2132 S San Pedro Street",
    "sg:city":"Los Angeles",
    "sg:classifiers":[
        {
            "category":"Shopping",
            "subcategory":"Mobile Phones",
            "type":"Retail Goods"
        }
    ],
    "sg:phone":"+1 213 747 9870",
    "sg:postcode":"90011",
    "sg:province":"CA",
    "wof:name":"Pirate Pagers",
    "wof:placetype":"venue"
},
  "geometry": {"coordinates":[-118.259258,34.025038],"type":"Point"}
}