{
  "type": "Feature",
  "properties": {
    "addr:full":"1944 Saviers Rd Oxnard CA 93033",
    "addr:housenumber":"1944",
    "addr:postcode":"93033",
    "addr:street":"Saviers Rd",
    "iso:country":"US",
    "sg:address":"1944 Saviers Rd",
    "sg:city":"Oxnard",
    "sg:classifiers":[
        {
            "category":"Shopping",
            "subcategory":"Musical Instruments",
            "type":"Retail Goods"
        }
    ],
    "sg:phone":"+1 805 487 6515",
    "sg:postcode":"93033",
    "sg:province":"CA",
    "wof:name":"Mario's Guitars",
    "wof:placetype":"venue"
},
  "geometry": {"coordinates":[-119.177403,34.180473],"type":"Point"}
}