{
  "type": "Feature",
  "properties": {
    "iso:country":"US",
    "sg:address":"646 Main St",
    "sg:city":"Colusa",
    "sg:classifiers":[
        {
            "category":"Real Estate",
            "subcategory":"Real Estate Agent",
            "type":"Services"
        }
    ],
    "sg:phone":"+1 530 458 8826",
    "sg:postcode":"95932",
    "sg:province":"CA",
    "wof:name":"West Valley Properties",
    "wof:placetype":"venue"
},
  "geometry": {"coordinates":[-122.00985,39.215524],"type":"Point"}
}