{
  "type": "Feature",
  "properties": {
    "addr:full":"1281 North Ave Sacramento CA 95838",
    "addr:housenumber":"1281",
    "addr:postcode":"95838",
    "addr:street":"North Ave",
    "iso:country":"US",
    "sg:address":"1281 North Ave",
    "sg:city":"Sacramento",
    "sg:classifiers":[
        {
            "category":"Education",
            "subcategory":"School",
            "type":"Public Place"
        }
    ],
    "sg:phone":"+1 916 925 1330",
    "sg:postcode":"95838",
    "sg:province":"CA",
    "wof:name":"North Avenue Elementary",
    "wof:placetype":"venue"
},
  "geometry": {"coordinates":[-121.43675399999999,38.640194],"type":"Point"}
}