{
  "type": "Feature",
  "properties": {
    "iso:country":"US",
    "sg:address":"4305 University Avenue",
    "sg:city":"San Diego",
    "sg:classifiers":[
        {
            "category":"Education",
            "subcategory":"Preschool",
            "type":"Public Place"
        },
        {
            "category":"Education",
            "subcategory":"School",
            "type":"Public Place"
        }
    ],
    "sg:phone":"+1 619 284 5644",
    "sg:postcode":"92105",
    "sg:province":"CA",
    "sg:tags":[
        "elementary"
    ],
    "wof:name":"Urban Village II",
    "wof:placetype":"venue"
},
  "geometry": {"coordinates":[-117.101968,32.749685],"type":"Point"}
}