{
  "type": "Feature",
  "properties": {
    "addr:full":"49 Sailfish Ct Half Moon Bay CA 94019",
    "addr:housenumber":"49",
    "addr:postcode":"94019",
    "addr:street":"Sailfish Ct",
    "iso:country":"US",
    "sg:address":"49 Sailfish Ct",
    "sg:city":"Half Moon Bay",
    "sg:classifiers":[
        {
            "category":"Professional",
            "type":"Services"
        }
    ],
    "sg:phone":"+1 650 726 3082",
    "sg:postcode":"94019",
    "sg:province":"CA",
    "wof:name":"Half Moon Handwovens",
    "wof:placetype":"venue"
},
  "geometry": {"coordinates":[-122.427913,37.428946],"type":"Point"}
}