{
  "type": "Feature",
  "properties": {
    "addr:full":"2739 Manhattan Beach Blvd Redondo Beach CA 90278",
    "addr:housenumber":"2739",
    "addr:postcode":"90278",
    "addr:street":"Manhattan Beach Blvd",
    "iso:country":"US",
    "sg:address":"2739 Manhattan Beach Blvd",
    "sg:city":"Redondo Beach",
    "sg:classifiers":[
        {
            "category":"Shopping",
            "subcategory":"Tobacco",
            "type":"Retail Goods"
        }
    ],
    "sg:phone":"+1 310 643 0320",
    "sg:postcode":"90278",
    "sg:province":"CA",
    "sg:tags":[
        "shop"
    ],
    "wof:name":"Smoke Zone & Heavy Hitter",
    "wof:placetype":"venue"
},
  "geometry": {"coordinates":[-118.362403,33.887463],"type":"Point"}
}