{
  "type": "Feature",
  "properties": {
    "addr:full":"4055 Wilshire Blvd Ste 417 Los Angeles CA 90010",
    "addr:housenumber":"4055",
    "addr:postcode":"90010",
    "addr:street":"Wilshire Blvd Ste 417",
    "iso:country":"US",
    "sg:address":"4055 Wilshire Blvd Ste 417",
    "sg:city":"Los Angeles",
    "sg:classifiers":[
        {
            "category":"Education",
            "subcategory":"School",
            "type":"Public Place"
        }
    ],
    "sg:phone":"+1 213 388 2866",
    "sg:postcode":"90010",
    "sg:province":"CA",
    "sg:tags":[
        "high",
        "middle",
        "elementary"
    ],
    "wof:name":"Geni Kids Inc",
    "wof:placetype":"venue"
},
  "geometry": {"coordinates":[-118.315777,34.183065],"type":"Point"}
}