{
  "type": "Feature",
  "properties": {
    "iso:country":"US",
    "sg:address":"326 S Del Mar Ave",
    "sg:city":"San Gabriel",
    "sg:classifiers":[
        {
            "category":"Retail",
            "subcategory":"Auto Repair",
            "type":"Services"
        }
    ],
    "sg:phone":"+1 626 285 6443",
    "sg:postcode":"91776",
    "sg:province":"CA",
    "wof:name":"Beisser Motorwerks",
    "wof:placetype":"venue"
},
  "geometry": {"coordinates":[-118.099998,34.0979],"type":"Point"}
}