{
  "type": "Feature",
  "properties": {
    "iso:country":"US",
    "sg:address":"328 Wayne Ave",
    "sg:city":"Oakland",
    "sg:classifiers":[
        {
            "category":"Professional",
            "subcategory":"Management & Consulting",
            "type":"Services"
        }
    ],
    "sg:phone":"+1 510 832 4552",
    "sg:postcode":"94606",
    "sg:province":"CA",
    "sg:tags":[
        "consultant",
        "training"
    ],
    "wof:name":"Ability Training Inc",
    "wof:placetype":"venue"
},
  "geometry": {"coordinates":[-122.251675,37.803517],"type":"Point"}
}