{
  "type": "Feature",
  "properties": {
    "addr:full":"328 Wayne Ave Oakland CA 94606",
    "addr:housenumber":"328",
    "addr:postcode":"94606",
    "addr:street":"Wayne Ave",
    "iso:country":"US",
    "sg:address":"328 Wayne Ave",
    "sg:city":"Oakland",
    "sg:classifiers":[
        {
            "category":"Professional",
            "subcategory":"Management & Consulting",
            "type":"Services"
        }
    ],
    "sg:phone":"+1 510 832 4552",
    "sg:postcode":"94606",
    "sg:province":"CA",
    "sg:tags":[
        "consultant",
        "training"
    ],
    "wof:name":"Ability Training Inc",
    "wof:placetype":"venue"
},
  "geometry": {"coordinates":[-122.25167500000001,37.803517],"type":"Point"}
}