{
  "type": "Feature",
  "properties": {
    "addr:full":"30661 Pso del Niguel Laguna Niguel CA 92677",
    "addr:postcode":"30661;92677",
    "addr:street":"Pso Del Niguel",
    "iso:country":"US",
    "sg:address":"30661 Pso del Niguel",
    "sg:city":"Laguna Niguel",
    "sg:classifiers":[
        {
            "category":"Professional",
            "type":"Services"
        }
    ],
    "sg:phone":"+1 949 249 8659",
    "sg:postcode":"92677",
    "sg:province":"CA",
    "wof:name":"Susan Rodgers Ward",
    "wof:placetype":"venue"
},
  "geometry": {"coordinates":[-117.718585,33.51778],"type":"Point"}
}