{
  "type": "Feature",
  "properties": {
    "iso:country":"US",
    "sg:address":"617 S Olive St",
    "sg:city":"Los Angeles",
    "sg:classifiers":[
        {
            "category":"Manufacturing",
            "subcategory":"Jewelry",
            "type":"Manufacturing & Wholesale Goods"
        },
        {
            "category":"Shopping",
            "subcategory":"Jewelry",
            "type":"Retail Goods"
        }
    ],
    "sg:phone":"+1 213 624 8890",
    "sg:postcode":"90014",
    "sg:province":"CA",
    "sg:tags":[
        "mfg",
        "material",
        "diamond",
        "setter"
    ],
    "wof:name":"Aces Diamond Setting",
    "wof:placetype":"venue"
},
  "geometry": {"coordinates":[-118.2554,34.046881],"type":"Point"}
}