{
  "type": "Feature",
  "properties": {
    "iso:country":"US",
    "sg:address":"5463 Carson St",
    "sg:city":"Long Beach",
    "sg:classifiers":[
        {
            "category":"Insurance",
            "subcategory":"Insurance Agent",
            "type":"Services"
        }
    ],
    "sg:phone":"+1 562 425 6473",
    "sg:postcode":"90808",
    "sg:province":"CA",
    "wof:name":"Allstate Insurance",
    "wof:placetype":"venue"
},
  "geometry": {"coordinates":[-118.126328,33.832382],"type":"Point"}
}