{
  "type": "Feature",
  "properties": {
    "addr:full":"1901 Merkley Ave West Sacramento CA 95691",
    "addr:housenumber":"1901",
    "addr:postcode":"95691",
    "addr:street":"Merkley Ave",
    "iso:country":"US",
    "sg:address":"1901 Merkley Ave",
    "sg:city":"West Sacramento",
    "sg:classifiers":[
        {
            "category":"Government",
            "subcategory":"Post Office",
            "type":"Public Place"
        }
    ],
    "sg:phone":"+1 916 000 1111",
    "sg:postcode":"95691",
    "sg:province":"CA",
    "wof:name":"US Post Office",
    "wof:placetype":"venue"
},
  "geometry": {"coordinates":[-121.537021,38.579187],"type":"Point"}
}