{
  "type": "Feature",
  "properties": {
    "addr:full":"1870 Judson Ln Santa Rosa CA 95401",
    "addr:housenumber":"1870",
    "addr:postcode":"95401",
    "addr:street":"Judson Ln",
    "iso:country":"US",
    "sg:address":"1870 Judson Ln",
    "sg:city":"Santa Rosa",
    "sg:classifiers":[
        {
            "category":"Health Services",
            "subcategory":"Chiropractor",
            "type":"Services"
        }
    ],
    "sg:phone":"+1 707 527 7463",
    "sg:postcode":"95401",
    "sg:province":"CA",
    "wof:name":"Accident & Industrial Injury",
    "wof:placetype":"venue"
},
  "geometry": {"coordinates":[-122.780798,38.464476],"type":"Point"}
}