{
  "type": "Feature",
  "properties": {
    "addr:full":"2909 Daimler St Santa Ana CA 92705",
    "addr:housenumber":"2909",
    "addr:postcode":"92705",
    "addr:street":"Daimler St",
    "iso:country":"US",
    "sg:address":"2909 Daimler St",
    "sg:city":"Santa Ana",
    "sg:classifiers":[
        {
            "category":"Manufacturing",
            "subcategory":"Electronics",
            "type":"Manufacturing & Wholesale Goods"
        }
    ],
    "sg:phone":"+1 949 442 1070",
    "sg:postcode":"92705",
    "sg:province":"CA",
    "sg:tags":[
        "semiconductor",
        "related",
        "devices"
    ],
    "wof:name":"Srswowcast Technologies",
    "wof:placetype":"venue"
},
  "geometry": {"coordinates":[-117.85134499999999,33.704465],"type":"Point"}
}