{
  "type": "Feature",
  "properties": {
    "addr:full":"438 S Almont Dr Beverly Hills CA 90211",
    "addr:housenumber":"438",
    "addr:postcode":"90211",
    "addr:street":"S Almont Dr",
    "iso:country":"US",
    "sg:address":"438 S Almont Dr",
    "sg:city":"Beverly Hills",
    "sg:classifiers":[
        {
            "category":"Real Estate",
            "subcategory":"Developer",
            "type":"Services"
        }
    ],
    "sg:phone":"+1 310 278 7772",
    "sg:postcode":"90211",
    "sg:province":"CA",
    "wof:name":"Bravo Construction & Dev Inc",
    "wof:placetype":"venue"
},
  "geometry": {"coordinates":[-118.387699,34.057469],"type":"Point"}
}