{
  "type": "Feature",
  "properties": {
    "iso:country":"US",
    "sg:address":"1818 Noemi Dr",
    "sg:city":"Concord",
    "sg:classifiers":[
        {
            "category":"Professional",
            "subcategory":"Business Services",
            "type":"Services"
        }
    ],
    "sg:phone":"+1 925 691 4348",
    "sg:postcode":"94519",
    "sg:province":"CA",
    "wof:name":"Johnson Family Enterprises",
    "wof:placetype":"venue"
},
  "geometry": {"coordinates":[-122.001767,37.981736],"type":"Point"}
}