{
  "type": "Feature",
  "properties": {
    "addr:full":"15504 W Clinton Ave Kerman CA 93630",
    "addr:housenumber":"15504",
    "addr:postcode":"93630",
    "addr:street":"W Clinton Ave",
    "iso:country":"US",
    "sg:address":"15504 W Clinton Ave",
    "sg:city":"Kerman",
    "sg:classifiers":[
        {
            "category":"Farming",
            "subcategory":"Vineyard",
            "type":"Manufacturing & Wholesale Goods"
        }
    ],
    "sg:phone":"+1 559 846 7162",
    "sg:postcode":"93630",
    "sg:province":"CA",
    "sg:tags":[
        "grape"
    ],
    "wof:name":"James Scharf",
    "wof:placetype":"venue"
},
  "geometry": {"coordinates":[-120.069225,36.771401],"type":"Point"}
}