{
  "type": "Feature",
  "properties": {
    "iso:country":"US",
    "sg:address":"1800 Century Park East Ste 300",
    "sg:city":"Los Angeles",
    "sg:classifiers":[
        {
            "category":"Professional",
            "subcategory":"Lawyer & Legal Services",
            "type":"Services"
        }
    ],
    "sg:phone":"+1 310 598 4155",
    "sg:postcode":"90067",
    "sg:province":"CA",
    "sg:website":"www.foxrothschild.com",
    "wof:name":"Scott Weston",
    "wof:placetype":"venue"
},
  "geometry": {"coordinates":[-118.415263,34.062699],"type":"Point"}
}