{
  "type": "Feature",
  "properties": {
    "addr:full":"3945 Freedom Cir Ste 660 Santa Clara CA 95054",
    "addr:housenumber":"3945",
    "addr:postcode":"95054",
    "addr:street":"Freedom Cir Ste 660",
    "iso:country":"US",
    "sg:address":"3945 Freedom Cir Ste 660",
    "sg:city":"Santa Clara",
    "sg:classifiers":[
        {
            "category":"Professional",
            "subcategory":"Employment Agencies",
            "type":"Services"
        }
    ],
    "sg:phone":"+1 408 496 5450",
    "sg:postcode":"95054",
    "sg:province":"CA",
    "sg:website":"www.staffmark.com",
    "wof:name":"Ann Wells Personnel Services",
    "wof:placetype":"venue"
},
  "geometry": {"coordinates":[-121.973,37.3862],"type":"Point"}
}