{
  "type": "Feature",
  "properties": {
    "addr:full":"21 Buckingham Way San Francisco CA 94132",
    "addr:housenumber":"21",
    "addr:postcode":"94132",
    "addr:street":"Buckingham Way",
    "iso:country":"US",
    "sg:address":"21 Buckingham Way",
    "sg:city":"San Francisco",
    "sg:classifiers":[
        {
            "category":"Real Estate",
            "subcategory":"Real Estate Operator",
            "type":"Services"
        }
    ],
    "sg:postcode":"94132",
    "sg:province":"CA",
    "sg:tags":[
        "apartment"
    ],
    "wof:name":"University Park South",
    "wof:placetype":"venue"
},
  "geometry": {"coordinates":[-122.475272,37.72575],"type":"Point"}
}