{
  "type": "Feature",
  "properties": {
    "iso:country":"US",
    "sg:address":"7606 Saladin Ave",
    "sg:city":"Twentynine Palms",
    "sg:classifiers":[
        {
            "category":"Banks & Credit Unions",
            "subcategory":"Financial Services",
            "type":"Services"
        }
    ],
    "sg:phone":"+1 760 830 4463",
    "sg:postcode":"92277",
    "sg:province":"CA",
    "sg:tags":[
        "education",
        "religious"
    ],
    "wof:name":"Open Hands Services",
    "wof:placetype":"venue"
},
  "geometry": {"coordinates":[-116.031294,34.11599],"type":"Point"}
}