{
  "type": "Feature",
  "properties": {
    "addr:full":"13321 Ventura Blvd Sherman Oaks CA 91423",
    "addr:housenumber":"13321",
    "addr:postcode":"91423",
    "addr:street":"Ventura Blvd",
    "iso:country":"US",
    "sg:address":"13321 Ventura Blvd",
    "sg:city":"Sherman Oaks",
    "sg:classifiers":[
        {
            "category":"Arts & Performance",
            "subcategory":"Theater",
            "type":"Entertainment"
        }
    ],
    "sg:phone":"+1 818 501 8917",
    "sg:postcode":"91423",
    "sg:province":"CA",
    "sg:tags":[
        "talent",
        "agency",
        "casting"
    ],
    "wof:name":"American Artists",
    "wof:placetype":"venue"
},
  "geometry": {"coordinates":[-118.423087,34.146727],"type":"Point"}
}