{
  "type": "Feature",
  "properties": {
    "addr:full":"20249 Blythe St Winnetka CA 91306",
    "addr:housenumber":"20249",
    "addr:postcode":"91306",
    "addr:street":"Blythe St",
    "iso:country":"US",
    "sg:address":"20249 Blythe St",
    "sg:city":"Winnetka",
    "sg:classifiers":[
        {
            "category":"Building & Trades",
            "subcategory":"Construction",
            "type":"Services"
        }
    ],
    "sg:phone":"+1 818 407 0311",
    "sg:postcode":"91306",
    "sg:province":"CA",
    "sg:tags":[
        "general",
        "contractor"
    ],
    "wof:name":"Chapo's Construction Co",
    "wof:placetype":"venue"
},
  "geometry": {"coordinates":[-118.57452600000001,34.214797],"type":"Point"}
}