{
  "type": "Feature",
  "properties": {
    "iso:country":"US",
    "sg:address":"3283 Industry Dr",
    "sg:city":"Signal Hill",
    "sg:classifiers":[
        {
            "category":"Communications",
            "type":"Services"
        }
    ],
    "sg:phone":"+1 562 597 2446",
    "sg:postcode":"90755",
    "sg:province":"CA",
    "sg:website":"www.futuredesigncom.com",
    "wof:name":"Future Design Communications",
    "wof:placetype":"venue"
},
  "geometry": {"coordinates":[-118.15407999999999,33.799565],"type":"Point"}
}