{
  "type": "Feature",
  "properties": {
    "addr:full":"8935 Aqueduct Ave North Hills CA 91343",
    "addr:housenumber":"8935",
    "addr:postcode":"91343",
    "addr:street":"Aqueduct Ave",
    "iso:country":"US",
    "sg:address":"8935 Aqueduct Ave",
    "sg:city":"North Hills",
    "sg:classifiers":[
        {
            "category":"Communications",
            "subcategory":"Film & Video Production",
            "type":"Services"
        }
    ],
    "sg:phone":"+1 818 891 1138",
    "sg:postcode":"91343",
    "sg:province":"CA",
    "sg:tags":[
        "motion",
        "picture",
        "projection"
    ],
    "wof:name":"Tom Ajar Projection Co",
    "wof:placetype":"venue"
},
  "geometry": {"coordinates":[-118.474222,34.234949],"type":"Point"}
}