{
  "type": "Feature",
  "properties": {
    "addr:full":"444 el Camino Real Menlo Park CA 94025",
    "addr:housenumber":"444",
    "addr:postcode":"94025",
    "addr:street":"El Camino Real",
    "iso:country":"US",
    "sg:address":"444 el Camino Real",
    "sg:city":"Menlo Park",
    "sg:classifiers":[
        {
            "category":"Autos & Motor Vehicles",
            "subcategory":"Automobile Sales",
            "type":"Retail Goods"
        }
    ],
    "sg:phone":"+1 650 321 8030",
    "sg:postcode":"94025",
    "sg:province":"CA",
    "sg:tags":[
        "car",
        "dealer"
    ],
    "sg:website":"www.stanfordlm.com",
    "wof:name":"Stanford Lincoln-Mercury",
    "wof:placetype":"venue"
},
  "geometry": {"coordinates":[-122.176723,37.450222],"type":"Point"}
}