{
  "type": "Feature",
  "properties": {
    "addr:full":"393 Hillcrest Ave Ukiah CA 95482",
    "addr:housenumber":"393",
    "addr:postcode":"ca 95482",
    "addr:street":"Hillcrest Ave",
    "iso:country":"US",
    "sg:address":"393 Hillcrest Ave",
    "sg:city":"Ukiah",
    "sg:classifiers":[
        {
            "category":"Health Services",
            "subcategory":"Health Practitioner",
            "type":"Services"
        }
    ],
    "sg:phone":"+1 707 463 3505",
    "sg:postcode":"95482",
    "sg:province":"CA",
    "sg:tags":[
        "therapist",
        "physical"
    ],
    "wof:name":"Karen A Feeney",
    "wof:placetype":"venue"
},
  "geometry": {"coordinates":[-123.21615799999999,39.140929],"type":"Point"}
}