{
  "type": "Feature",
  "properties": {
    "iso:country":"US",
    "sg:address":"3350 Scott Boulevard",
    "sg:city":"Santa Clara",
    "sg:classifiers":[
        {
            "category":"Communications",
            "type":"Services"
        }
    ],
    "sg:phone":"+1 408 727 8444",
    "sg:postcode":"95054",
    "sg:province":"CA",
    "sg:tags":[
        "recording",
        "rehearsal",
        "studio"
    ],
    "wof:name":"Wave Group Sound",
    "wof:placetype":"venue"
},
  "geometry": {"coordinates":[-121.982319,37.380344],"type":"Point"}
}