{
  "type": "Feature",
  "properties": {
    "addr:full":"2041 Railroad Ave Livermore CA 94550",
    "addr:housenumber":"2041",
    "addr:postcode":"94550",
    "addr:street":"Railroad Ave",
    "iso:country":"US",
    "sg:address":"2041 Railroad Ave",
    "sg:city":"Livermore",
    "sg:classifiers":[
        {
            "category":"Restaurant",
            "type":"Food & Drink"
        }
    ],
    "sg:phone":"+1 925 447 0235",
    "sg:postcode":"94550",
    "sg:province":"CA",
    "wof:name":"Railroad Cafe",
    "wof:placetype":"venue"
},
  "geometry": {"coordinates":[-121.77121,37.68287],"type":"Point"}
}