{
  "type": "Feature",
  "properties": {
    "iso:country":"US",
    "sg:address":"74741 Joni Dr",
    "sg:city":"Palm Desert",
    "sg:classifiers":[
        {
            "category":"Home & Garden",
            "subcategory":"Home Furnishings",
            "type":"Retail Goods"
        }
    ],
    "sg:phone":"+1 760 346 2339",
    "sg:postcode":"92260",
    "sg:province":"CA",
    "sg:tags":[
        "fireplace"
    ],
    "wof:name":"Paragon Schmid Building Prods",
    "wof:placetype":"venue"
},
  "geometry": {"coordinates":[-116.35692,33.740954],"type":"Point"}
}