{
  "type": "Feature",
  "properties": {
    "addr:full":"18743 Main St Groveland CA 95321",
    "addr:housenumber":"18743",
    "addr:postcode":"95321",
    "addr:street":"Main St",
    "iso:country":"US",
    "sg:address":"18743 Main St",
    "sg:city":"Groveland",
    "sg:classifiers":[
        {
            "category":"Shopping",
            "type":"Retail Goods"
        }
    ],
    "sg:phone":"+1 209 962 4438",
    "sg:postcode":"95321",
    "sg:province":"CA",
    "sg:tags":[
        "pet",
        "food",
        "supply"
    ],
    "wof:name":"Critter Corner",
    "wof:placetype":"venue"
},
  "geometry": {"coordinates":[-120.230688,37.838637],"type":"Point"}
}