{
  "type": "Feature",
  "properties": {
    "iso:country":"US",
    "sg:address":"3275 C St",
    "sg:city":"San Diego",
    "sg:classifiers":[
        {
            "category":"Real Estate",
            "subcategory":"Real Estate Operator",
            "type":"Services"
        }
    ],
    "sg:postcode":"92102",
    "sg:province":"CA",
    "sg:tags":[
        "apartment"
    ],
    "wof:name":"Golden Glen Apts",
    "wof:placetype":"venue"
},
  "geometry": {"coordinates":[-117.123693,32.716946],"type":"Point"}
}