{
  "type": "Feature",
  "properties": {
    "iso:country":"US",
    "sg:address":"1816 Tully Road Suite 172",
    "sg:city":"San Jose",
    "sg:classifiers":[
        {
            "category":"Personal",
            "type":"Services"
        },
        {
            "category":"Shopping",
            "subcategory":"Bridal",
            "type":"Retail Goods"
        }
    ],
    "sg:phone":"+1 408 532 0968",
    "sg:postcode":"95122",
    "sg:province":"CA",
    "sg:tags":[
        "sewing",
        "alteration"
    ],
    "wof:name":"Icon Tuxedo",
    "wof:placetype":"venue"
},
  "geometry": {"coordinates":[-121.82461000000001,37.32312],"type":"Point"}
}