{
  "type": "Feature",
  "properties": {
    "iso:country":"US",
    "sg:address":"2792 Greer Rd",
    "sg:city":"Palo Alto",
    "sg:classifiers":[
        {
            "category":"Professional",
            "subcategory":"Computer Services",
            "type":"Services"
        }
    ],
    "sg:phone":"+1 650 856 0740",
    "sg:postcode":"94303",
    "sg:province":"CA",
    "wof:name":"Consult Supply Support",
    "wof:placetype":"venue"
},
  "geometry": {"coordinates":[-122.120907,37.440406],"type":"Point"}
}