{
  "type": "Feature",
  "properties": {
    "addr:full":"600 S Eugene Rd Palm Springs CA 92264",
    "addr:housenumber":"600",
    "addr:postcode":"92264",
    "addr:street":"S Eugene Rd",
    "iso:country":"US",
    "sg:address":"600 S Eugene Rd",
    "sg:city":"Palm Springs",
    "sg:classifiers":[
        {
            "category":"Home & Garden",
            "subcategory":"Building Materials",
            "type":"Retail Goods"
        },
        {
            "category":"Building & Trades",
            "subcategory":"Electrical",
            "type":"Services"
        }
    ],
    "sg:phone":"+1 760 320 4429",
    "sg:postcode":"92264",
    "sg:province":"CA",
    "sg:tags":[
        "equipment",
        "lighting",
        "fixture",
        "electrician"
    ],
    "wof:name":"Brudvik Inc Rental Division",
    "wof:placetype":"venue"
},
  "geometry": {"coordinates":[-116.49400300000001,33.813301],"type":"Point"}
}