{
  "type": "Feature",
  "properties": {
    "iso:country":"US",
    "sg:address":"1355 Market St",
    "sg:city":"San Francisco",
    "sg:classifiers":[
        {
            "category":"Manufacturing",
            "subcategory":"Furniture",
            "type":"Manufacturing & Wholesale Goods"
        }
    ],
    "sg:phone":"+1 415 487 1919",
    "sg:postcode":"94103",
    "sg:province":"CA",
    "sg:website":"www.armenart.com",
    "wof:name":"Armen Art Inc",
    "wof:placetype":"venue"
},
  "geometry": {"coordinates":[-122.416865,37.776981],"type":"Point"}
}