{
  "type": "Feature",
  "properties": {
    "iso:country":"US",
    "sg:address":"9025 Wilshire Boulevard",
    "sg:city":"Beverly Hills",
    "sg:classifiers":[
        {
            "category":"Building & Trades",
            "subcategory":"Locksmith",
            "type":"Services"
        }
    ],
    "sg:phone":"+1 310 499 0768",
    "sg:postcode":"90211",
    "sg:province":"CA",
    "sg:tags":[
        "key"
    ],
    "wof:name":"24 Hour All City Locks & Locksmith",
    "wof:placetype":"venue"
},
  "geometry": {"coordinates":[-118.38847,34.067135],"type":"Point"}
}