{
  "type": "Feature",
  "properties": {
    "iso:country":"US",
    "sg:address":"1757 Avenida Vista Labera",
    "sg:city":"Oceanside",
    "sg:classifiers":[
        {
            "category":"Health Services",
            "subcategory":"Medical Lab",
            "type":"Services"
        },
        {
            "category":"Professional",
            "subcategory":"Employment Agencies",
            "type":"Services"
        }
    ],
    "sg:phone":"+1 760 631 1335",
    "sg:postcode":"92056",
    "sg:province":"CA",
    "sg:tags":[
        "transcription",
        "processing",
        "word"
    ],
    "wof:name":"Rj's Word Processing Services",
    "wof:placetype":"venue"
},
  "geometry": {"coordinates":[-117.285453,33.215619],"type":"Point"}
}