{
  "type": "Feature",
  "properties": {
    "iso:country":"US",
    "sg:address":"3120 Pacific Coast Hwy",
    "sg:city":"Torrance",
    "sg:classifiers":[
        {
            "category":"Shopping",
            "type":"Retail Goods"
        }
    ],
    "sg:phone":"+1 310 257 9096",
    "sg:postcode":"90505",
    "sg:province":"CA",
    "wof:name":"JK Emporium",
    "wof:placetype":"venue"
},
  "geometry": {"coordinates":[-118.340576,33.797754],"type":"Point"}
}