{
  "type": "Feature",
  "properties": {
    "addr:full":"360 State St Fairfield CA 94533",
    "addr:housenumber":"360",
    "addr:postcode":"94533",
    "addr:street":"State St",
    "iso:country":"US",
    "sg:address":"360 State St",
    "sg:city":"Fairfield",
    "sg:classifiers":[
        {
            "category":"Retail",
            "subcategory":"Auto Repair",
            "type":"Services"
        }
    ],
    "sg:phone":"+1 707 422 2222",
    "sg:postcode":"94533",
    "sg:province":"CA",
    "sg:tags":[
        "repairing",
        "automobile"
    ],
    "wof:name":"Crown Auto Repair",
    "wof:placetype":"venue"
},
  "geometry": {"coordinates":[-122.036306,38.248746],"type":"Point"}
}