{
  "type": "Feature",
  "properties": {
    "iso:country":"US",
    "sg:address":"505 N Brand Blvd",
    "sg:city":"Glendale",
    "sg:classifiers":[
        {
            "category":"Building & Trades",
            "subcategory":"Construction",
            "type":"Services"
        }
    ],
    "sg:phone":"+1 818 662 7113",
    "sg:postcode":"91203",
    "sg:province":"CA",
    "sg:tags":[
        "carpenter"
    ],
    "wof:name":"Guy Carpenter And Company",
    "wof:placetype":"venue"
},
  "geometry": {"coordinates":[-118.255112,34.15302],"type":"Point"}
}