{
  "type": "Feature",
  "properties": {
    "iso:country":"US",
    "sg:address":"1142 Brunswick Ln",
    "sg:city":"Ventura",
    "sg:classifiers":[
        {
            "category":"Professional",
            "subcategory":"Computer Services",
            "type":"Services"
        }
    ],
    "sg:phone":"+1 805 648 2077",
    "sg:postcode":"93001",
    "sg:province":"CA",
    "sg:tags":[
        "consultant",
        "designer",
        "system"
    ],
    "wof:name":"Catalyst Consulting",
    "wof:placetype":"venue"
},
  "geometry": {"coordinates":[-119.270556,34.260313],"type":"Point"}
}