{
  "type": "Feature",
  "properties": {
    "iso:country":"US",
    "sg:address":"1516 N San Fernando Blvd #207",
    "sg:city":"Burbank",
    "sg:classifiers":[
        {
            "category":"Professional",
            "subcategory":"Computer Services",
            "type":"Services"
        }
    ],
    "sg:phone":"+1 818 478 5139",
    "sg:postcode":"91504",
    "sg:province":"CA",
    "sg:tags":[
        "repair"
    ],
    "sg:website":"www.helixpc.com",
    "wof:name":"HeliX PC",
    "wof:placetype":"venue"
},
  "geometry": {"coordinates":[-118.322524,34.191366],"type":"Point"}
}