{
  "type": "Feature",
  "properties": {
    "addr:full":"2800 Maple Avenue Los Angeles CA 90011",
    "addr:housenumber":"2800",
    "addr:postcode":"90011",
    "addr:street":"Maple Avenue",
    "iso:country":"US",
    "sg:address":"2800 Maple Avenue",
    "sg:city":"Los Angeles",
    "sg:classifiers":[
        {
            "category":"Food & Beverages",
            "subcategory":"Meat & Fish",
            "type":"Retail Goods"
        }
    ],
    "sg:phone":"+1 213 763 6198",
    "sg:postcode":"90011",
    "sg:province":"CA",
    "sg:tags":[
        "shop"
    ],
    "wof:name":"Carniceria El Rinconcito No 1",
    "wof:placetype":"venue"
},
  "geometry": {"coordinates":[-118.266626,34.021785],"type":"Point"}
}