{
  "type": "Feature",
  "properties": {
    "addr:full":"6226 Pacific Ave Stockton CA 95207",
    "addr:housenumber":"6226",
    "addr:postcode":"95207",
    "addr:street":"Pacific Ave",
    "iso:country":"US",
    "sg:address":"6226 Pacific Ave",
    "sg:city":"Stockton",
    "sg:classifiers":[
        {
            "category":"Retail",
            "subcategory":"Auto Repair",
            "type":"Services"
        }
    ],
    "sg:phone":"+1 209 474 9770",
    "sg:postcode":"95207",
    "sg:province":"CA",
    "sg:tags":[
        "automobile",
        "inspection"
    ],
    "wof:name":"Smog First",
    "wof:placetype":"venue"
},
  "geometry": {"coordinates":[-121.318941,38.007027],"type":"Point"}
}