{
  "type": "Feature",
  "properties": {
    "addr:full":"4397 Tujunga Ave Studio City CA 91604",
    "addr:housenumber":"4397",
    "addr:postcode":"91604",
    "addr:street":"Tujunga Ave",
    "iso:country":"US",
    "sg:address":"4397 Tujunga Ave",
    "sg:city":"Studio City",
    "sg:classifiers":[
        {
            "category":"Personal",
            "subcategory":"Nail Salon",
            "type":"Services"
        }
    ],
    "sg:phone":"+1 818 761 0936",
    "sg:postcode":"91604",
    "sg:province":"CA",
    "wof:name":"Vianh's Nail Spa Salon",
    "wof:placetype":"venue"
},
  "geometry": {"coordinates":[-118.379322,34.150118],"type":"Point"}
}