{
  "type": "Feature",
  "properties": {
    "iso:country":"US",
    "sg:address":"101 N Bascom Ave",
    "sg:city":"San Jose",
    "sg:classifiers":[
        {
            "category":"Organizations",
            "subcategory":"Non-profit Organization",
            "type":"Services"
        }
    ],
    "sg:phone":"+1 408 298 4468",
    "sg:postcode":"95128",
    "sg:province":"CA",
    "wof:name":"Braille Transcription Project",
    "wof:placetype":"venue"
},
  "geometry": {"coordinates":[-121.931973,37.325862],"type":"Point"}
}