{
  "type": "Feature",
  "properties": {
    "addr:full":"1147 W Swain Rd Stockton CA 95207",
    "addr:housenumber":"1147",
    "addr:postcode":"95207",
    "addr:street":"W Swain Rd",
    "iso:country":"US",
    "sg:address":"1147 W Swain Rd",
    "sg:city":"Stockton",
    "sg:classifiers":[
        {
            "category":"Health Services",
            "subcategory":"Doctor",
            "type":"Services"
        }
    ],
    "sg:phone":"+1 209 477 6971",
    "sg:postcode":"95207",
    "sg:province":"CA",
    "sg:tags":[
        "dentist"
    ],
    "wof:name":"Karen Trinh DDS",
    "wof:placetype":"venue"
},
  "geometry": {"coordinates":[-121.32427,38.003162],"type":"Point"}
}