{
  "type": "Feature",
  "properties": {
    "addr:full":"11814 160th St Norwalk CA 90650",
    "addr:housenumber":"11814",
    "addr:postcode":"90650",
    "addr:street":"160Th St",
    "iso:country":"US",
    "sg:address":"11814 160th St",
    "sg:city":"Norwalk",
    "sg:classifiers":[
        {
            "category":"Retail",
            "subcategory":"Auto Repair",
            "type":"Services"
        }
    ],
    "sg:phone":"+1 562 802 0905",
    "sg:postcode":"90650",
    "sg:province":"CA",
    "wof:name":"Pioneer Auto Repair",
    "wof:placetype":"venue"
},
  "geometry": {"coordinates":[-118.08200100000001,33.8862],"type":"Point"}
}