{
  "type": "Feature",
  "properties": {
    "iso:country":"US",
    "sg:address":"3400 Lomita Blvd Ste 301",
    "sg:city":"Torrance",
    "sg:classifiers":[
        {
            "category":"Health Services",
            "subcategory":"Doctor",
            "type":"Services"
        }
    ],
    "sg:phone":"+1 310 534 4494",
    "sg:postcode":"90505",
    "sg:province":"CA",
    "sg:tags":[
        "allergist"
    ],
    "sg:website":"www.davidsonallergy.com",
    "wof:name":"Davidson Allergy",
    "wof:placetype":"venue"
},
  "geometry": {"coordinates":[-118.345826,33.811848],"type":"Point"}
}