{
  "type": "Feature",
  "properties": {
    "iso:country":"US",
    "sg:address":"1400 E Cypress St",
    "sg:city":"Covina",
    "sg:classifiers":[
        {
            "category":"Retail",
            "subcategory":"Veterinary Services",
            "type":"Services"
        }
    ],
    "sg:phone":"+1 626 331 0775",
    "sg:postcode":"91724",
    "sg:province":"CA",
    "sg:tags":[
        "clinic",
        "hospital",
        "veterinarian",
        "specialty"
    ],
    "wof:name":"Cypress Avenue Animal Hospital",
    "wof:placetype":"venue"
},
  "geometry": {"coordinates":[-117.86150000000001,34.095791],"type":"Point"}
}