{
  "type": "Feature",
  "properties": {
    "iso:country":"US",
    "sg:address":"224 W Main St",
    "sg:city":"Turlock",
    "sg:classifiers":[
        {
            "category":"Personal",
            "subcategory":"Barber",
            "type":"Services"
        }
    ],
    "sg:phone":"+1 209 668 1768",
    "sg:postcode":"95380",
    "sg:province":"CA",
    "wof:name":"Ron's Razor Edge",
    "wof:placetype":"venue"
},
  "geometry": {"coordinates":[-120.84928,37.492669],"type":"Point"}
}