{
  "type": "Feature",
  "properties": {
    "iso:country":"US",
    "sg:address":"445 Lupine Way",
    "sg:city":"Ventura",
    "sg:classifiers":[
        {
            "category":"Building & Trades",
            "subcategory":"Construction",
            "type":"Services"
        }
    ],
    "sg:phone":"+1 805 648 6551",
    "sg:postcode":"93001",
    "sg:province":"CA",
    "sg:tags":[
        "repairing",
        "remodeling",
        "contractor"
    ],
    "wof:name":"Ventura Coast Construction Inc",
    "wof:placetype":"venue"
},
  "geometry": {"coordinates":[-119.275064,34.28459],"type":"Point"}
}