{
  "type": "Feature",
  "properties": {
    "addr:full":"37 Ringwood Ave Atherton CA 94027",
    "addr:housenumber":"37",
    "addr:postcode":"94027",
    "addr:street":"Ringwood Ave",
    "iso:country":"US",
    "sg:address":"37 Ringwood Ave",
    "sg:city":"Atherton",
    "sg:classifiers":[
        {
            "category":"Shopping",
            "type":"Retail Goods"
        }
    ],
    "sg:phone":"+1 650 208 2580",
    "sg:postcode":"94027",
    "sg:province":"CA",
    "sg:tags":[
        "equipment",
        "clothing",
        "safety"
    ],
    "wof:name":"Powerflare Corporation",
    "wof:placetype":"venue"
},
  "geometry": {"coordinates":[-122.171058,37.46521],"type":"Point"}
}