{
  "type": "Feature",
  "properties": {
    "iso:country":"US",
    "sg:address":"351 E Oberlin Rd",
    "sg:city":"Yreka",
    "sg:classifiers":[
        {
            "category":"Retail",
            "subcategory":"Repair Shop",
            "type":"Services"
        }
    ],
    "sg:phone":"+1 530 842 0842",
    "sg:postcode":"96097",
    "sg:province":"CA",
    "sg:tags":[
        "welding"
    ],
    "wof:name":"J W Nowlin Enterprises",
    "wof:placetype":"venue"
},
  "geometry": {"coordinates":[-122.634491,41.715523],"type":"Point"}
}