{
  "type": "Feature",
  "properties": {
    "addr:full":"1010 National City Blvd National City CA 91950",
    "addr:housenumber":"1010",
    "addr:postcode":"91950",
    "addr:street":"National City Blvd",
    "iso:country":"US",
    "sg:address":"1010 National City Blvd",
    "sg:city":"National City",
    "sg:classifiers":[
        {
            "category":"Autos & Motor Vehicles",
            "subcategory":"Automobile Sales",
            "type":"Retail Goods"
        }
    ],
    "sg:phone":"+1 619 477 2323",
    "sg:postcode":"91950",
    "sg:province":"CA",
    "sg:tags":[
        "car",
        "dealer"
    ],
    "wof:name":"Autobuyers Plus",
    "wof:placetype":"venue"
},
  "geometry": {"coordinates":[-117.106011,32.6733],"type":"Point"}
}