{
  "type": "Feature",
  "properties": {
    "addr:full":"1665 Old Mammoth Rd Mammoth Lakes CA 93546",
    "addr:housenumber":"1665",
    "addr:postcode":"93546",
    "addr:street":"Old Mammoth Rd",
    "iso:country":"US",
    "sg:address":"1665 Old Mammoth Rd",
    "sg:city":"Mammoth Lakes",
    "sg:classifiers":[
        {
            "category":"Shopping",
            "subcategory":"Hobbies, Toys, & Games",
            "type":"Retail Goods"
        }
    ],
    "sg:phone":"+1 760 934 2252",
    "sg:postcode":"93546",
    "sg:province":"CA",
    "sg:tags":[
        "house",
        "doll",
        "accessory"
    ],
    "wof:name":"Doll House Chalet",
    "wof:placetype":"venue"
},
  "geometry": {"coordinates":[-118.979635,37.628983],"type":"Point"}
}