{
  "type": "Feature",
  "properties": {
    "addr:full":"1048 E Burgrove St Carson CA 90746",
    "addr:housenumber":"1048",
    "addr:postcode":"90746",
    "addr:street":"E Burgrove St",
    "iso:country":"US",
    "sg:address":"1048 E Burgrove St",
    "sg:city":"Carson",
    "sg:classifiers":[
        {
            "category":"Wholesale",
            "subcategory":"Electrical",
            "type":"Manufacturing & Wholesale Goods"
        }
    ],
    "sg:phone":"+1 310 898 2011",
    "sg:postcode":"90746",
    "sg:province":"CA",
    "sg:tags":[
        "hardware",
        "equipment",
        "store"
    ],
    "wof:name":"R F C Sales Inc",
    "wof:placetype":"venue"
},
  "geometry": {"coordinates":[-118.25412799999999,33.845061],"type":"Point"}
}