{
  "type": "Feature",
  "properties": {
    "addr:full":"1 Main St Ste X Jackson CA 95642",
    "addr:housenumber":"1",
    "addr:postcode":"95642",
    "addr:street":"Main St Ste X Jackson",
    "iso:country":"US",
    "sg:address":"1 Main St Ste X",
    "sg:city":"Jackson",
    "sg:classifiers":[
        {
            "category":"Shopping",
            "subcategory":"Antiques",
            "type":"Retail Goods"
        }
    ],
    "sg:phone":"+1 209 257 1949",
    "sg:postcode":"95642",
    "sg:province":"CA",
    "wof:name":"Antiques On Main",
    "wof:placetype":"venue"
},
  "geometry": {"coordinates":[-120.773499,38.348251],"type":"Point"}
}