{
  "type": "Feature",
  "properties": {
    "addr:full":"97 South 13th Street San Jose CA 95112",
    "addr:housenumber":"97",
    "addr:postcode":"95112",
    "addr:street":"South 13Th Street",
    "iso:country":"US",
    "sg:address":"97 South 13th Street",
    "sg:city":"San Jose",
    "sg:classifiers":[
        {
            "category":"Real Estate",
            "subcategory":"Real Estate Agent",
            "type":"Services"
        }
    ],
    "sg:phone":"+1 415 370 7919",
    "sg:postcode":"95112",
    "sg:province":"CA",
    "wof:name":"Prime Realty and Financial Services",
    "wof:placetype":"venue"
},
  "geometry": {"coordinates":[-121.877084,37.340308],"type":"Point"}
}