{
  "type": "Feature",
  "properties": {
    "iso:country":"US",
    "sg:address":"12759 Poway Rd #103",
    "sg:city":"Poway",
    "sg:classifiers":[
        {
            "category":"Insurance",
            "subcategory":"Insurance Agent",
            "type":"Services"
        },
        {
            "category":"Insurance",
            "subcategory":"Hazard Insurance",
            "type":"Services"
        },
        {
            "category":"Insurance",
            "subcategory":"Title Insurance",
            "type":"Services"
        },
        {
            "category":"Insurance",
            "subcategory":"Life Insurance",
            "type":"Services"
        }
    ],
    "sg:phone":"+1 858 748 3105",
    "sg:postcode":"92064",
    "sg:province":"CA",
    "sg:tags":[
        "auto",
        "commercial",
        "business",
        "homeowner"
    ],
    "sg:website":"http://www.farmersagent.com/tsnow/",
    "wof:name":"Terry Snow - Farmers Insurance",
    "wof:placetype":"venue"
},
  "geometry": {"coordinates":[-117.054535,32.955986],"type":"Point"}
}