{
  "type": "Feature",
  "properties": {
    "addr:full":"5048 Glenhollow Way Antioch CA 94531",
    "addr:housenumber":"5048",
    "addr:postcode":"ca 94531",
    "addr:street":"Glenhollow Way",
    "iso:country":"US",
    "sg:address":"5048 Glenhollow Way",
    "sg:city":"Antioch",
    "sg:classifiers":[
        {
            "category":"Wholesale",
            "subcategory":"Durable Goods & Equipment",
            "type":"Manufacturing & Wholesale Goods"
        }
    ],
    "sg:phone":"+1 925 777 1639",
    "sg:postcode":"94531",
    "sg:province":"CA",
    "sg:tags":[
        "dry",
        "goods-wholesale"
    ],
    "wof:name":"Quality Wholesale",
    "wof:placetype":"venue"
},
  "geometry": {"coordinates":[-121.800224,37.965006],"type":"Point"}
}