{
  "type": "Feature",
  "properties": {
    "addr:full":"2531 Blanding Ave Alameda CA 94501",
    "addr:housenumber":"2531",
    "addr:postcode":"94501",
    "addr:street":"Blanding Ave",
    "iso:country":"US",
    "sg:address":"2531 Blanding Ave",
    "sg:city":"Alameda",
    "sg:classifiers":[
        {
            "category":"Banks & Credit Unions",
            "subcategory":"Bank",
            "type":"Services"
        }
    ],
    "sg:phone":"+1 510 865 9040",
    "sg:postcode":"94501",
    "sg:province":"CA",
    "sg:website":"www.fcbconnect.com",
    "wof:name":"First Community Bank",
    "wof:placetype":"venue"
},
  "geometry": {"coordinates":[-122.23343800000001,37.768462],"type":"Point"}
}