{
  "type": "Feature",
  "properties": {
    "iso:country":"US",
    "sg:address":"8801 Walker St",
    "sg:city":"Cypress",
    "sg:classifiers":[
        {
            "category":"Professional",
            "subcategory":"Management & Consulting",
            "type":"Services"
        },
        {
            "category":"Shopping",
            "subcategory":"Clothing, Apparel, & Fashions",
            "type":"Retail Goods"
        }
    ],
    "sg:phone":"+1 714 615 1220",
    "sg:postcode":"90630",
    "sg:province":"CA",
    "sg:tags":[
        "direct",
        "sales"
    ],
    "wof:name":"Behind Closed Doors",
    "wof:placetype":"venue"
},
  "geometry": {"coordinates":[-118.03702,33.833929],"type":"Point"}
}