{
  "type": "Feature",
  "properties": {
    "addr:full":"713 Sutter St Folsom CA 95630",
    "addr:housenumber":"713",
    "addr:postcode":"95630",
    "addr:street":"Sutter St",
    "iso:country":"US",
    "sg:address":"713 Sutter St",
    "sg:city":"Folsom",
    "sg:classifiers":[
        {
            "category":"Real Estate",
            "subcategory":"Architect",
            "type":"Services"
        }
    ],
    "sg:phone":"+1 916 353 0833",
    "sg:postcode":"95630",
    "sg:province":"CA",
    "sg:tags":[
        "home",
        "planning",
        "design"
    ],
    "wof:name":"Forget Me Not Home Decor",
    "wof:placetype":"venue"
},
  "geometry": {"coordinates":[-121.177558,38.677039],"type":"Point"}
}