{
  "type": "Feature",
  "properties": {
    "addr:full":"18270 Siskiyou Rd Apple Valley CA 92307",
    "addr:housenumber":"18270",
    "addr:postcode":"92307",
    "addr:street":"Siskiyou Rd",
    "iso:country":"US",
    "sg:address":"18270 Siskiyou Rd",
    "sg:city":"Apple Valley",
    "sg:classifiers":[
        {
            "category":"Health Services",
            "subcategory":"Clinic",
            "type":"Services"
        }
    ],
    "sg:phone":"+1 760 242 3677",
    "sg:postcode":"92307",
    "sg:province":"CA",
    "sg:tags":[
        "physician",
        "surgeon",
        "bureau",
        "information"
    ],
    "wof:name":"High Desert Valley Pediatrics",
    "wof:placetype":"venue"
},
  "geometry": {"coordinates":[-117.265095,34.544551],"type":"Point"}
}