{
  "type": "Feature",
  "properties": {
    "iso:country":"US",
    "sg:address":"1724 Cahuenga Blvd",
    "sg:city":"Los Angeles",
    "sg:classifiers":[
        {
            "category":"Recreation",
            "type":"Entertainment"
        }
    ],
    "sg:phone":"+1 323 461 1096",
    "sg:postcode":"90028",
    "sg:province":"CA",
    "sg:tags":[
        "active",
        "life"
    ],
    "sg:website":"www.bareelegance.com/Bare_Elegan...",
    "wof:name":"Bare Elegance Boutique",
    "wof:placetype":"venue"
},
  "geometry": {"coordinates":[-118.329133,34.102424],"type":"Point"}
}