{
  "type": "Feature",
  "properties": {
    "addr:full":"937 W Ontario Ave Corona CA 92882",
    "addr:housenumber":"937",
    "addr:postcode":"92882",
    "addr:street":"W Ontario Ave",
    "iso:country":"US",
    "sg:address":"937 W Ontario Ave",
    "sg:city":"Corona",
    "sg:classifiers":[
        {
            "category":"Building & Trades",
            "subcategory":"Electrical",
            "type":"Services"
        }
    ],
    "sg:phone":"+1 951 284 0419",
    "sg:postcode":"92882",
    "sg:province":"CA",
    "sg:tags":[
        "booth",
        "equipment",
        "telephone",
        "pay"
    ],
    "wof:name":"Cal-Tel Communications",
    "wof:placetype":"venue"
},
  "geometry": {"coordinates":[-117.582053,33.857814],"type":"Point"}
}