{
  "type": "Feature",
  "properties": {
    "iso:country":"US",
    "sg:address":"690 el Cajon Blvd",
    "sg:city":"El Cajon",
    "sg:classifiers":[
        {
            "category":"Retail",
            "subcategory":"Car Wash",
            "type":"Services"
        }
    ],
    "sg:phone":"+1 619 588 4099",
    "sg:postcode":"92020",
    "sg:province":"CA",
    "sg:tags":[
        "polishing",
        "washing"
    ],
    "wof:name":"Body Beautiful Car Wash Ctr",
    "wof:placetype":"venue"
},
  "geometry": {"coordinates":[-116.97421900000001,32.788527],"type":"Point"}
}