{
  "type": "Feature",
  "properties": {
    "addr:full":"457 Capistrano Dr Oakland CA 94603",
    "addr:housenumber":"457",
    "addr:postcode":"94603",
    "addr:street":"Capistrano Dr",
    "iso:country":"US",
    "sg:address":"457 Capistrano Dr",
    "sg:city":"Oakland",
    "sg:classifiers":[
        {
            "category":"Banks & Credit Unions",
            "subcategory":"Bank",
            "type":"Services"
        }
    ],
    "sg:phone":"+1 510 777 9262",
    "sg:postcode":"94603",
    "sg:province":"CA",
    "sg:tags":[
        "commercial",
        "saving"
    ],
    "wof:name":"Sobrante Park Time Banking",
    "wof:placetype":"venue"
},
  "geometry": {"coordinates":[-122.179351,37.728418],"type":"Point"}
}