{
  "type": "Feature",
  "properties": {
    "addr:full":"1725 Rogers Ave San Jose CA 95112",
    "addr:housenumber":"1725",
    "addr:postcode":"95112",
    "addr:street":"Rogers Ave",
    "iso:country":"US",
    "sg:address":"1725 Rogers Ave",
    "sg:city":"San Jose",
    "sg:classifiers":[
        {
            "category":"Restaurant",
            "type":"Food & Drink"
        }
    ],
    "sg:phone":"+1 408 436 8336",
    "sg:postcode":"95112",
    "sg:province":"CA",
    "sg:tags":[
        "delicatessen"
    ],
    "sg:website":"www.traintrackdeli.com",
    "wof:name":"Train Track Deli",
    "wof:placetype":"venue"
},
  "geometry": {"coordinates":[-121.910444,37.377979],"type":"Point"}
}