{
  "type": "Feature",
  "properties": {
    "iso:country":"US",
    "sg:address":"3650 Hazelwood St",
    "sg:city":"Vallejo",
    "sg:classifiers":[
        {
            "category":"Professional",
            "subcategory":"Accounting & Tax Preparation",
            "type":"Services"
        }
    ],
    "sg:phone":"+1 510 535 0206",
    "sg:postcode":"94591",
    "sg:province":"CA",
    "sg:tags":[
        "accountant"
    ],
    "wof:name":"Adonis Rentoria",
    "wof:placetype":"venue"
},
  "geometry": {"coordinates":[-122.213666,38.099257],"type":"Point"}
}