{
  "type": "Feature",
  "properties": {
    "iso:country":"US",
    "sg:address":"2702 Media Center Dr",
    "sg:city":"Los Angeles",
    "sg:classifiers":[
        {
            "category":"Manufacturing",
            "subcategory":"Tools & Machinery",
            "type":"Manufacturing & Wholesale Goods"
        }
    ],
    "sg:phone":"+1 323 908 1300",
    "sg:postcode":"90065",
    "sg:province":"CA",
    "sg:tags":[
        "measuring",
        "instrument",
        "electrical",
        "mfg"
    ],
    "wof:name":"Altrio Communications Inc",
    "wof:placetype":"venue"
},
  "geometry": {"coordinates":[-118.242795,34.109186],"type":"Point"}
}