{
  "type": "Feature",
  "properties": {
    "addr:full":"1911 Commercenter Ct San Bernardino CA 92408",
    "addr:housenumber":"1911",
    "addr:postcode":"92408",
    "addr:street":"Commercenter Ct",
    "iso:country":"US",
    "sg:address":"1911 Commercenter Ct",
    "sg:city":"San Bernardino",
    "sg:classifiers":[
        {
            "category":"Health Services",
            "subcategory":"Clinic",
            "type":"Services"
        }
    ],
    "sg:phone":"+1 909 890 2668",
    "sg:postcode":"92408",
    "sg:province":"CA",
    "sg:tags":[
        "home"
    ],
    "wof:name":"Visiting Angels",
    "wof:placetype":"venue"
},
  "geometry": {"coordinates":[-117.28222599999999,34.066179],"type":"Point"}
}