{
  "type": "Feature",
  "properties": {
    "iso:country":"US",
    "sg:address":"460 W Taylor Street",
    "sg:city":"San Jose",
    "sg:classifiers":[
        {
            "category":"Communications",
            "subcategory":"Newspaper",
            "type":"Services"
        }
    ],
    "sg:phone":"+1 408 293 0909",
    "sg:postcode":"95110",
    "sg:province":"CA",
    "sg:tags":[
        "magazine"
    ],
    "wof:name":"El Avisador Magazine",
    "wof:placetype":"venue"
},
  "geometry": {"coordinates":[-121.90975299999999,37.3429],"type":"Point"}
}