{
  "type": "Feature",
  "properties": {
    "iso:country":"US",
    "sg:address":"1248 Iroquois Ln",
    "sg:city":"Fawnskin",
    "sg:classifiers":[
        {
            "category":"Wholesale",
            "subcategory":"Machinery & Supplies",
            "type":"Manufacturing & Wholesale Goods"
        }
    ],
    "sg:phone":"+1 909 866 2810",
    "sg:postcode":"92333",
    "sg:province":"CA",
    "sg:tags":[
        "janitor",
        "establishment",
        "equipment"
    ],
    "wof:name":"Mountain Janitorial Supplies",
    "wof:placetype":"venue"
},
  "geometry": {"coordinates":[-116.94654,34.272125],"type":"Point"}
}