{
  "type": "Feature",
  "properties": {
    "iso:country":"US",
    "sg:address":"1730 S Sherbourne Dr",
    "sg:city":"Los Angeles",
    "sg:classifiers":[
        {
            "category":"Food & Beverages",
            "subcategory":"Groceries & Convenience Stores",
            "type":"Retail Goods"
        }
    ],
    "sg:phone":"+1 310 289 6888",
    "sg:postcode":"90035",
    "sg:province":"CA",
    "sg:tags":[
        "grocer"
    ],
    "wof:name":"Glatt Mart",
    "wof:placetype":"venue"
},
  "geometry": {"coordinates":[-118.380791,34.046096],"type":"Point"}
}