{
  "type": "Feature",
  "properties": {
    "iso:country":"US",
    "sg:address":"6950 Cam Maquiladora",
    "sg:city":"San Diego",
    "sg:classifiers":[
        {
            "category":"Freight",
            "type":"Transportation"
        }
    ],
    "sg:phone":"+1 619 671 9917",
    "sg:postcode":"92154",
    "sg:province":"CA",
    "sg:tags":[
        "arrangement"
    ],
    "wof:name":"Border Custom Broker",
    "wof:placetype":"venue"
},
  "geometry": {"coordinates":[-116.992597,32.566899],"type":"Point"}
}