{
  "type": "Feature",
  "properties": {
    "addr:full":"1425 Frazee Rd San Diego CA 92108",
    "addr:housenumber":"1425",
    "addr:postcode":"92108",
    "addr:street":"Frazee Rd",
    "iso:country":"US",
    "sg:address":"1425 Frazee Rd",
    "sg:city":"San Diego",
    "sg:classifiers":[
        {
            "category":"Personal",
            "subcategory":"Beauty Salon",
            "type":"Services"
        },
        {
            "category":"Personal",
            "subcategory":"Skin Care",
            "type":"Services"
        },
        {
            "category":"Personal",
            "subcategory":"Day Spa",
            "type":"Services"
        }
    ],
    "sg:phone":"+1 619 293 7233",
    "sg:postcode":"92108",
    "sg:province":"CA",
    "sg:tags":[
        "hair"
    ],
    "sg:website":"www.revivesalonandspa.com",
    "wof:name":"Revive Salon & Spa",
    "wof:placetype":"venue"
},
  "geometry": {"coordinates":[-117.157678,32.773083],"type":"Point"}
}