{
  "type": "Feature",
  "properties": {
    "iso:country":"US",
    "sg:address":"37631 Oak Hill St",
    "sg:city":"Palmdale",
    "sg:classifiers":[
        {
            "category":"Shopping",
            "subcategory":"Gifts & Souvenirs",
            "type":"Retail Goods"
        }
    ],
    "sg:phone":"+1 661 285 0175",
    "sg:postcode":"93552",
    "sg:province":"CA",
    "wof:name":"Gifts Galore",
    "wof:placetype":"venue"
},
  "geometry": {"coordinates":[-118.048714,34.566155],"type":"Point"}
}