{
  "type": "Feature",
  "properties": {
    "addr:full":"4434 Palomar Dr Fallbrook CA 92028",
    "addr:housenumber":"4434",
    "addr:postcode":"92028",
    "addr:street":"Palomar Dr",
    "iso:country":"US",
    "sg:address":"4434 Palomar Dr",
    "sg:city":"Fallbrook",
    "sg:classifiers":[
        {
            "category":"Real Estate",
            "subcategory":"Real Estate Services",
            "type":"Services"
        },
        {
            "category":"Real Estate",
            "subcategory":"Real Estate Agent",
            "type":"Services"
        }
    ],
    "sg:phone":"+1 760 419 6868",
    "sg:postcode":"92028",
    "sg:province":"CA",
    "sg:tags":[
        "buyer",
        "broker"
    ],
    "wof:name":"California Edge Realty And Mortgage, Inc.",
    "wof:placetype":"venue"
},
  "geometry": {"coordinates":[-117.224344,33.312004],"type":"Point"}
}