{
  "type": "Feature",
  "properties": {
    "addr:full":"1505 W Highland Ave San Bernardino CA 92411",
    "addr:housenumber":"1505",
    "addr:postcode":"92411",
    "addr:street":"W Highland Ave",
    "iso:country":"US",
    "sg:address":"1505 W Highland Ave",
    "sg:city":"San Bernardino",
    "sg:classifiers":[
        {
            "category":"Social Services",
            "type":"Services"
        }
    ],
    "sg:phone":"+1 909 855 0344",
    "sg:postcode":"92411",
    "sg:province":"CA",
    "sg:tags":[
        "organization",
        "welfare"
    ],
    "sg:website":"www.koinoniacharity.org",
    "wof:name":"Koinonia Charitable Foundation",
    "wof:placetype":"venue"
},
  "geometry": {"coordinates":[-117.320336,34.136039],"type":"Point"}
}