{
  "type": "Feature",
  "properties": {
    "iso:country":"US",
    "sg:address":"2323 Via Campo",
    "sg:city":"Montebello",
    "sg:classifiers":[
        {
            "category":"Restaurant",
            "type":"Food & Drink"
        }
    ],
    "sg:phone":"+1 323 726 1668",
    "sg:postcode":"90640",
    "sg:province":"CA",
    "sg:tags":[
        "buffet"
    ],
    "wof:name":"International Buffet",
    "wof:placetype":"venue"
},
  "geometry": {"coordinates":[-118.121364,34.032588],"type":"Point"}
}