{
  "type": "Feature",
  "properties": {
    "addr:full":"29483 The Old Rd Castaic CA 91355",
    "addr:housenumber":"29483",
    "addr:postcode":"91355",
    "addr:street":"The Old Rd",
    "iso:country":"US",
    "sg:address":"29483 The Old Rd",
    "sg:city":"Castaic",
    "sg:classifiers":[
        {
            "category":"Restaurant",
            "type":"Food & Drink"
        }
    ],
    "sg:phone":"+1 661 295 6992",
    "sg:postcode":"91355",
    "sg:province":"CA",
    "sg:tags":[
        "mexican"
    ],
    "wof:name":"Las Delicias",
    "wof:placetype":"venue"
},
  "geometry": {"coordinates":[-118.616444,34.452724],"type":"Point"}
}