{
  "type": "Feature",
  "properties": {
    "addr:full":"444 del Sol Ave Pleasanton CA 94566",
    "addr:housenumber":"444",
    "addr:postcode":"94566",
    "addr:street":"Del Sol Ave",
    "iso:country":"US",
    "sg:address":"444 del Sol Ave",
    "sg:city":"Pleasanton",
    "sg:classifiers":[
        {
            "category":"Professional",
            "type":"Services"
        }
    ],
    "sg:phone":"+1 925 484 4224",
    "sg:postcode":"94566",
    "sg:province":"CA",
    "wof:name":"Fengshui For Western Living",
    "wof:placetype":"venue"
},
  "geometry": {"coordinates":[-121.867485,37.65856],"type":"Point"}
}