{
  "type": "Feature",
  "properties": {
    "iso:country":"US",
    "sg:address":"8510 Costa Verde Blvd",
    "sg:city":"San Diego",
    "sg:classifiers":[
        {
            "category":"Banks & Credit Unions",
            "subcategory":"Bank",
            "type":"Services"
        }
    ],
    "sg:phone":"+1 858 552 0253",
    "sg:postcode":"92122",
    "sg:province":"CA",
    "sg:tags":[
        "loan",
        "real estate"
    ],
    "wof:name":"HSBC Mortgage Corp",
    "wof:placetype":"venue"
},
  "geometry": {"coordinates":[-117.216931,32.869256],"type":"Point"}
}