{
  "type": "Feature",
  "properties": {
    "addr:full":"7020 N Van Ness Blvd Fresno CA 93711",
    "addr:housenumber":"7020",
    "addr:postcode":"93711",
    "addr:street":"N Van Ness Blvd",
    "iso:country":"US",
    "sg:address":"7020 N Van Ness Blvd",
    "sg:city":"Fresno",
    "sg:classifiers":[
        {
            "category":"Real Estate",
            "subcategory":"Real Estate Services",
            "type":"Services"
        }
    ],
    "sg:phone":"+1 559 440 0780",
    "sg:postcode":"93711",
    "sg:province":"CA",
    "sg:tags":[
        "company",
        "title"
    ],
    "wof:name":"Fidelity National Title",
    "wof:placetype":"venue"
},
  "geometry": {"coordinates":[-119.835279,36.83818],"type":"Point"}
}