{
  "type": "Feature",
  "properties": {
    "addr:full":"13337 South St Ste 208 Cerritos CA 90703",
    "addr:housenumber":"13337",
    "addr:postcode":"ca 90703",
    "addr:street":"South St Ste 208",
    "iso:country":"US",
    "sg:address":"13337 South St Ste 208",
    "sg:city":"Cerritos",
    "sg:classifiers":[
        {
            "category":"Travel",
            "subcategory":"Travel Agent",
            "type":"Entertainment"
        }
    ],
    "sg:phone":"+1 562 865 1890",
    "sg:postcode":"90703",
    "sg:province":"CA",
    "sg:website":"www.blissfulgetaways.com/",
    "wof:name":"Blissful Getaways",
    "wof:placetype":"venue"
},
  "geometry": {"coordinates":[-118.047158,33.85876],"type":"Point"}
}