{
  "type": "Feature",
  "properties": {
    "iso:country":"US",
    "sg:address":"23542 Lyons Ave",
    "sg:city":"Newhall",
    "sg:classifiers":[
        {
            "category":"Home & Garden",
            "subcategory":"Building Materials",
            "type":"Retail Goods"
        }
    ],
    "sg:phone":"+1 661 263 2863",
    "sg:postcode":"91321",
    "sg:province":"CA",
    "sg:tags":[
        "glass",
        "leaded"
    ],
    "wof:name":"Stained Glass Overlay",
    "wof:placetype":"venue"
},
  "geometry": {"coordinates":[-118.54627600000001,34.379297],"type":"Point"}
}