{
  "type": "Feature",
  "properties": {
    "addr:full":"350 S Hope Ave Santa Barbara CA 93105",
    "addr:housenumber":"350",
    "addr:postcode":"93105",
    "addr:street":"S Hope Ave",
    "iso:country":"US",
    "sg:address":"350 S Hope Ave",
    "sg:city":"Santa Barbara",
    "sg:classifiers":[
        {
            "category":"Professional",
            "subcategory":"Research",
            "type":"Services"
        }
    ],
    "sg:phone":"+1 805 969 1044",
    "sg:postcode":"93105",
    "sg:province":"CA",
    "sg:website":"www.networkbuyersguide.com",
    "wof:name":"Strategic Research",
    "wof:placetype":"venue"
},
  "geometry": {"coordinates":[-119.74722800000001,34.434899],"type":"Point"}
}