{
  "type": "Feature",
  "properties": {
    "addr:full":"34297 Pacific Coast Hwy Dana Point CA 92629",
    "addr:housenumber":"34297",
    "addr:postcode":"92629",
    "addr:street":"Pacific Coast Hwy",
    "iso:country":"US",
    "sg:address":"34297 Pacific Coast Hwy",
    "sg:city":"Dana Point",
    "sg:classifiers":[
        {
            "category":"Restaurant",
            "type":"Food & Drink"
        }
    ],
    "sg:menulink":"http://www.allmenus.com/ca/south-coast/178019-jack-in-the-box/menu/",
    "sg:phone":"+1 949 443 4054",
    "sg:postcode":"92629",
    "sg:province":"CA",
    "sg:tags":[
        "burger",
        "american"
    ],
    "wof:name":"Jack in the Box",
    "wof:placetype":"venue"
},
  "geometry": {"coordinates":[-117.68839,33.46518],"type":"Point"}
}