{
  "type": "Feature",
  "properties": {
    "iso:country":"US",
    "sg:address":"110 E Lincoln Ave",
    "sg:city":"Orange",
    "sg:classifiers":[
        {
            "category":"Food & Beverages",
            "subcategory":"Liquor & Beverages",
            "type":"Retail Goods"
        }
    ],
    "sg:phone":"+1 714 637 1273",
    "sg:postcode":"92865",
    "sg:province":"CA",
    "sg:tags":[
        "beer",
        "spirit",
        "wine"
    ],
    "wof:name":"Orange Tree Liquor",
    "wof:placetype":"venue"
},
  "geometry": {"coordinates":[-117.852238,33.835476],"type":"Point"}
}