{
  "type": "Feature",
  "properties": {
    "addr:full":"7885 Bell Dr Atwater CA 95301",
    "addr:housenumber":"7885",
    "addr:postcode":"95301",
    "addr:street":"Bell Dr",
    "iso:country":"US",
    "sg:address":"7885 Bell Dr",
    "sg:city":"Atwater",
    "sg:classifiers":[
        {
            "category":"Professional",
            "subcategory":"Engineering",
            "type":"Services"
        }
    ],
    "sg:phone":"+1 209 357 3268",
    "sg:postcode":"95301",
    "sg:province":"CA",
    "sg:tags":[
        "aircraft",
        "maintenance"
    ],
    "wof:name":"Ceels Lock And Key Service",
    "wof:placetype":"venue"
},
  "geometry": {"coordinates":[-120.630837,37.345677],"type":"Point"}
}