{
  "type": "Feature",
  "properties": {
    "iso:country":"US",
    "sg:address":"501 Poli St Ste 218",
    "sg:city":"Ventura",
    "sg:classifiers":[
        {
            "category":"Building & Trades",
            "subcategory":"Construction",
            "type":"Services"
        }
    ],
    "sg:phone":"+1 805 658 4711",
    "sg:postcode":"93001",
    "sg:province":"CA",
    "sg:tags":[
        "repair",
        "altering",
        "contractor",
        "maintenance",
        "home",
        "remodeling"
    ],
    "wof:name":"Inspection Svc Preservation",
    "wof:placetype":"venue"
},
  "geometry": {"coordinates":[-119.292664,34.282131],"type":"Point"}
}