{
  "type": "Feature",
  "properties": {
    "iso:country":"US",
    "sg:address":"815 Sea Spray Ln Ste 306",
    "sg:city":"San Mateo",
    "sg:classifiers":[
        {
            "category":"Professional",
            "subcategory":"Art Services",
            "type":"Services"
        },
        {
            "category":"Communications",
            "type":"Services"
        }
    ],
    "sg:phone":"+1 650 360 1901",
    "sg:postcode":"94404",
    "sg:province":"CA",
    "sg:tags":[
        "web",
        "graphic",
        "design"
    ],
    "sg:website":"www.bayarea-web.com",
    "wof:name":"BayArea-Web",
    "wof:placetype":"venue"
},
  "geometry": {"coordinates":[-122.281415,37.553696],"type":"Point"}
}