{
  "type": "Feature",
  "properties": {
    "iso:country":"US",
    "sg:address":"1967 Spruce St",
    "sg:city":"Riverside",
    "sg:classifiers":[
        {
            "category":"Retail",
            "subcategory":"Auto Repair",
            "type":"Services"
        }
    ],
    "sg:phone":"+1 951 369 4953",
    "sg:postcode":"92507",
    "sg:province":"CA",
    "sg:tags":[
        "body",
        "automobile",
        "painting"
    ],
    "wof:name":"Andy's Paint & Body Shop",
    "wof:placetype":"venue"
},
  "geometry": {"coordinates":[-117.356052,33.990338],"type":"Point"}
}