{
  "type": "Feature",
  "properties": {
    "addr:full":"1046 W Highland Ave San Bernardino CA 92405",
    "addr:housenumber":"1046",
    "addr:postcode":"92405",
    "addr:street":"W Highland Ave",
    "iso:country":"US",
    "sg:address":"1046 W Highland Ave",
    "sg:city":"San Bernardino",
    "sg:classifiers":[
        {
            "category":"Personal",
            "subcategory":"Tattoo Parlor",
            "type":"Services"
        }
    ],
    "sg:phone":"+1 909 886 2000",
    "sg:postcode":"92405",
    "sg:province":"CA",
    "sg:tags":[
        "tattooing"
    ],
    "wof:name":"San Bernardino Tattoo",
    "wof:placetype":"venue"
},
  "geometry": {"coordinates":[-117.30678,34.136132],"type":"Point"}
}