{
  "type": "Feature",
  "properties": {
    "iso:country":"US",
    "sg:address":"1869 Rainbow Terrace Ln",
    "sg:city":"Montebello",
    "sg:classifiers":[
        {
            "category":"Wholesale",
            "subcategory":"Books, Periodicals, & Newspapers",
            "type":"Manufacturing & Wholesale Goods"
        }
    ],
    "sg:phone":"+1 310 629 2364",
    "sg:postcode":"90640",
    "sg:province":"CA",
    "sg:tags":[
        "publisher",
        "book"
    ],
    "wof:name":"Hk Speed Express Inc",
    "wof:placetype":"venue"
},
  "geometry": {"coordinates":[-118.094002,34.042122],"type":"Point"}
}