{
  "type": "Feature",
  "properties": {
    "iso:country":"US",
    "sg:address":"2018 Lombard Street",
    "sg:city":"San Francisco",
    "sg:classifiers":[
        {
            "category":"Building & Trades",
            "subcategory":"Locksmith",
            "type":"Services"
        }
    ],
    "sg:phone":"+1 415 775 3191",
    "sg:postcode":"94123",
    "sg:province":"CA",
    "sg:tags":[
        "key"
    ],
    "wof:name":"24 Hour 1A1 Locks & Locksmith Service",
    "wof:placetype":"venue"
},
  "geometry": {"coordinates":[-122.43499799999999,37.800201],"type":"Point"}
}