{
  "type": "Feature",
  "properties": {
    "addr:full":"2766 W Court St Rialto CA 92376",
    "addr:housenumber":"2766",
    "addr:postcode":"92376",
    "addr:street":"W Court St",
    "iso:country":"US",
    "sg:address":"2766 W Court St",
    "sg:city":"Rialto",
    "sg:classifiers":[
        {
            "category":"Professional",
            "type":"Services"
        }
    ],
    "sg:phone":"+1 909 874 7804",
    "sg:postcode":"92376",
    "sg:province":"CA",
    "wof:name":"Annies Unique Treasures",
    "wof:placetype":"venue"
},
  "geometry": {"coordinates":[-117.348795,34.105486],"type":"Point"}
}