{
  "type": "Feature",
  "properties": {
    "iso:country":"US",
    "sg:address":"1390 Huggins Ave",
    "sg:city":"Chico",
    "sg:classifiers":[
        {
            "category":"Building & Trades",
            "subcategory":"Construction",
            "type":"Services"
        }
    ],
    "sg:phone":"+1 530 891 0488",
    "sg:postcode":"95926",
    "sg:province":"CA",
    "sg:tags":[
        "general",
        "contractor"
    ],
    "wof:name":"Sherwood Construction",
    "wof:placetype":"venue"
},
  "geometry": {"coordinates":[-121.815906,39.74779],"type":"Point"}
}