{
  "type": "Feature",
  "properties": {
    "addr:full":"14704 Hawthorne Blvd Lawndale CA 90260",
    "addr:housenumber":"14704",
    "addr:postcode":"ca 90260",
    "addr:street":"Hawthorne Blvd",
    "iso:country":"US",
    "sg:address":"14704 Hawthorne Blvd",
    "sg:city":"Lawndale",
    "sg:classifiers":[
        {
            "category":"Shopping",
            "subcategory":"Pets & Pet Supplies",
            "type":"Retail Goods"
        }
    ],
    "sg:phone":"+1 310 973 4040",
    "sg:postcode":"90260",
    "sg:province":"CA",
    "sg:tags":[
        "store"
    ],
    "wof:name":"Lotus Aquarium",
    "wof:placetype":"venue"
},
  "geometry": {"coordinates":[-118.352388,33.89811],"type":"Point"}
}