{
  "type": "Feature",
  "properties": {
    "addr:full":"7740 El Camino Real Carlsbad CA 92009",
    "addr:housenumber":"7740",
    "addr:postcode":"92009",
    "addr:street":"El Camino Real",
    "iso:country":"US",
    "sg:address":"7740 El Camino Real",
    "sg:city":"Carlsbad",
    "sg:classifiers":[
        {
            "category":"Arts & Performance",
            "subcategory":"Arts Center",
            "type":"Entertainment"
        }
    ],
    "sg:phone":"+1 760 753 2002",
    "sg:postcode":"92009",
    "sg:province":"CA",
    "sg:tags":[
        "performing"
    ],
    "sg:website":"Evolutiondancecenter.com",
    "wof:name":"Evolution Dance Center",
    "wof:placetype":"venue"
},
  "geometry": {"coordinates":[-117.26699600000001,33.083069],"type":"Point"}
}