{
  "type": "Feature",
  "properties": {
    "iso:country":"US",
    "sg:address":"923 Folsom St",
    "sg:city":"San Francisco",
    "sg:classifiers":[
        {
            "category":"Building & Trades",
            "subcategory":"Cleaning & Sanitation",
            "type":"Services"
        }
    ],
    "sg:phone":"+1 415 822 6210",
    "sg:postcode":"94107",
    "sg:province":"CA",
    "sg:tags":[
        "maintenance"
    ],
    "wof:name":"Augusta Carballo",
    "wof:placetype":"venue"
},
  "geometry": {"coordinates":[-122.403965,37.779799],"type":"Point"}
}