{
  "type": "Feature",
  "properties": {
    "iso:country":"US",
    "sg:address":"1974 Mountain Ave",
    "sg:city":"Duarte",
    "sg:classifiers":[
        {
            "category":"Professional",
            "type":"Services"
        }
    ],
    "sg:phone":"+1 626 303 3910",
    "sg:postcode":"91010",
    "sg:province":"CA",
    "sg:tags":[
        "establishment"
    ],
    "wof:name":"Cinnamon Hollow",
    "wof:placetype":"venue"
},
  "geometry": {"coordinates":[-117.988079,34.128262],"type":"Point"}
}