{
  "type": "Feature",
  "properties": {
    "addr:full":"400 2nd Ave San Francisco CA 94118",
    "addr:housenumber":"400",
    "addr:postcode":"94118",
    "addr:street":"2Nd Ave",
    "iso:country":"US",
    "sg:address":"400 2nd Ave",
    "sg:city":"San Francisco",
    "sg:classifiers":[
        {
            "category":"Professional",
            "subcategory":"Computer Services",
            "type":"Services"
        }
    ],
    "sg:phone":"+1 415 531 6574",
    "sg:postcode":"94118",
    "sg:province":"CA",
    "sg:tags":[
        "plain",
        "great",
        "consulting"
    ],
    "wof:name":"Workopia Inc",
    "wof:placetype":"venue"
},
  "geometry": {"coordinates":[-122.45985899999999,37.779283],"type":"Point"}
}