{
  "type": "Feature",
  "properties": {
    "addr:full":"8272 Moss Landing Road Moss Landing CA 95039",
    "addr:postcode":"8272;95039",
    "addr:street":"Moss Landing Road",
    "iso:country":"US",
    "sg:address":"8272 Moss Landing Road",
    "sg:city":"Moss Landing",
    "sg:classifiers":[
        {
            "category":"Education",
            "subcategory":"University",
            "type":"Public Place"
        }
    ],
    "sg:phone":"+1 831 771 4400",
    "sg:postcode":"95039",
    "sg:province":"CA",
    "sg:tags":[
        "college"
    ],
    "wof:name":"Moss Landing Marine Laboratories",
    "wof:placetype":"venue"
},
  "geometry": {"coordinates":[-121.78559199999999,36.795306],"type":"Point"}
}