{
  "type": "Feature",
  "properties": {
    "addr:full":"1226 W Roderick Ave Oxnard CA 93030",
    "addr:housenumber":"1226",
    "addr:postcode":"93030",
    "addr:street":"W Roderick Ave",
    "iso:country":"US",
    "sg:address":"1226 W Roderick Ave",
    "sg:city":"Oxnard",
    "sg:classifiers":[
        {
            "category":"Building & Trades",
            "subcategory":"Landscaping Services",
            "type":"Services"
        },
        {
            "category":"Health Services",
            "subcategory":"Nursing And Care Facility",
            "type":"Services"
        }
    ],
    "sg:phone":"+1 805 988 4054",
    "sg:postcode":"93030",
    "sg:province":"CA",
    "sg:tags":[
        "personal",
        "home",
        "aged",
        "homes-institutional"
    ],
    "wof:name":"Ballard Support Home",
    "wof:placetype":"venue"
},
  "geometry": {"coordinates":[-119.19116699999999,34.209741],"type":"Point"}
}