{
  "type": "Feature",
  "properties": {
    "iso:country":"US",
    "sg:address":"14103 Winchester Blvd",
    "sg:city":"Los Gatos",
    "sg:classifiers":[
        {
            "category":"Shopping",
            "subcategory":"Gifts & Souvenirs",
            "type":"Retail Goods"
        },
        {
            "category":"Shopping",
            "subcategory":"Antiques",
            "type":"Retail Goods"
        }
    ],
    "sg:phone":"+1 408 370 1818",
    "sg:postcode":"95032",
    "sg:province":"CA",
    "sg:tags":[
        "flower"
    ],
    "sg:website":"www.alefbetjudaica.com",
    "wof:name":"Alef Bet",
    "wof:placetype":"venue"
},
  "geometry": {"coordinates":[-121.960999,37.263],"type":"Point"}
}