{
  "type": "Feature",
  "properties": {
    "addr:full":"1001 Bidwell St Folsom CA 95630",
    "addr:housenumber":"1001",
    "addr:postcode":"95630",
    "addr:street":"Bidwell St",
    "iso:country":"US",
    "sg:address":"1001 Bidwell St",
    "sg:city":"Folsom",
    "sg:classifiers":[
        {
            "category":"Restaurant",
            "type":"Food & Drink"
        }
    ],
    "sg:menulink":"http://www.allmenus.com/ca/folsom/157941-chipotle/menu/",
    "sg:phone":"+1 916 983 9374",
    "sg:postcode":"95630",
    "sg:province":"CA",
    "sg:tags":[
        "mexican"
    ],
    "wof:name":"Chipotle",
    "wof:placetype":"venue"
},
  "geometry": {"coordinates":[-121.176655,38.671378],"type":"Point"}
}