{
  "type": "Feature",
  "properties": {
    "addr:full":"212 Fransil Ln Turlock CA 95380",
    "addr:housenumber":"212",
    "addr:postcode":"95380",
    "addr:street":"Fransil Ln",
    "iso:country":"US",
    "sg:address":"212 Fransil Ln",
    "sg:city":"Turlock",
    "sg:classifiers":[
        {
            "category":"Building & Trades",
            "subcategory":"Landscaping Services",
            "type":"Services"
        }
    ],
    "sg:phone":"+1 209 667 7801",
    "sg:postcode":"95380",
    "sg:province":"CA",
    "sg:tags":[
        "landscape"
    ],
    "wof:name":"Countryside Landscaping",
    "wof:placetype":"venue"
},
  "geometry": {"coordinates":[-120.88987899999999,37.495825],"type":"Point"}
}