{
  "type": "Feature",
  "properties": {
    "iso:country":"US",
    "sg:address":"9665 Jeremy St",
    "sg:city":"Santee",
    "sg:classifiers":[
        {
            "category":"Education",
            "subcategory":"School",
            "type":"Public Place"
        }
    ],
    "sg:phone":"+1 619 956 5000",
    "sg:postcode":"92071",
    "sg:province":"CA",
    "sg:tags":[
        "high",
        "middle",
        "elementary"
    ],
    "wof:name":"Santee Elementary School District",
    "wof:placetype":"venue"
},
  "geometry": {"coordinates":[-116.963162,32.852959],"type":"Point"}
}