{
  "type": "Feature",
  "properties": {
    "iso:country":"US",
    "sg:address":"211 E 1st St",
    "sg:city":"Calexico",
    "sg:classifiers":[
        {
            "category":"Shopping",
            "type":"Retail Goods"
        }
    ],
    "sg:phone":"+1 760 768 0092",
    "sg:postcode":"92231",
    "sg:province":"CA",
    "sg:tags":[
        "miscellaneous",
        "store"
    ],
    "wof:name":"UETA Inc",
    "wof:placetype":"venue"
},
  "geometry": {"coordinates":[-115.495548,32.665691],"type":"Point"}
}