{
  "type": "Feature",
  "properties": {
    "iso:country":"US",
    "sg:address":"1185 Lincoln Ave",
    "sg:city":"San Jose",
    "sg:classifiers":[
        {
            "category":"Restaurant",
            "type":"Food & Drink"
        }
    ],
    "sg:phone":"+1 408 993 8636",
    "sg:postcode":"95125",
    "sg:province":"CA",
    "sg:tags":[
        "middle",
        "eastern",
        "mediterranean",
        "greek"
    ],
    "sg:website":"www.casablancascafe.com",
    "wof:name":"Casablancas Cafe",
    "wof:placetype":"venue"
},
  "geometry": {"coordinates":[-121.900029,37.306957],"type":"Point"}
}