{
  "type": "Feature",
  "properties": {
    "addr:full":"1602 N Susan St Ste B Santa Ana CA 92703",
    "addr:housenumber":"1602",
    "addr:postcode":"92703",
    "addr:street":"N Susan St Ste B",
    "iso:country":"US",
    "sg:address":"1602 N Susan St Ste B",
    "sg:city":"Santa Ana",
    "sg:classifiers":[
        {
            "category":"Retail",
            "subcategory":"Auto Repair",
            "type":"Services"
        }
    ],
    "sg:phone":"+1 714 554 4421",
    "sg:postcode":"92703",
    "sg:province":"CA",
    "wof:name":"Nn Enterprises",
    "wof:placetype":"venue"
},
  "geometry": {"coordinates":[-117.902,33.748699],"type":"Point"}
}