{
  "type": "Feature",
  "properties": {
    "addr:full":"334 S Van Ness Ave San Francisco CA 94103",
    "addr:housenumber":"334",
    "addr:postcode":"94103",
    "addr:street":"S Van Ness Ave",
    "iso:country":"US",
    "sg:address":"334 S Van Ness Ave",
    "sg:city":"San Francisco",
    "sg:classifiers":[
        {
            "category":"Retail",
            "subcategory":"Auto Repair",
            "type":"Services"
        }
    ],
    "sg:phone":"+1 415 626 4843",
    "sg:postcode":"94103",
    "sg:province":"CA",
    "wof:name":"Japan Auto",
    "wof:placetype":"venue"
},
  "geometry": {"coordinates":[-122.41779699999999,37.767871],"type":"Point"}
}