{
  "type": "Feature",
  "properties": {
    "addr:full":"6309 Lankershim Blvd North Hollywood CA 91606",
    "addr:housenumber":"6309",
    "addr:postcode":"91606",
    "addr:street":"Lankershim Blvd",
    "iso:country":"US",
    "sg:address":"6309 Lankershim Blvd",
    "sg:city":"North Hollywood",
    "sg:classifiers":[
        {
            "category":"Fast Food",
            "type":"Food & Drink"
        }
    ],
    "sg:phone":"+1 818 763 7117",
    "sg:postcode":"91606",
    "sg:province":"CA",
    "sg:website":"www.mccalifornia.com/10997",
    "wof:name":"McDonald's",
    "wof:placetype":"venue"
},
  "geometry": {"coordinates":[-118.38728500000001,34.185085],"type":"Point"}
}