{
  "type": "Feature",
  "properties": {
    "iso:country":"US",
    "sg:address":"2150 Pacific Beach Dr",
    "sg:city":"San Diego",
    "sg:classifiers":[
        {
            "category":"Sports & Exercise",
            "subcategory":"Golf",
            "type":"Entertainment"
        }
    ],
    "sg:phone":"+1 858 373 1884",
    "sg:postcode":"92109",
    "sg:province":"CA",
    "sg:tags":[
        "course"
    ],
    "wof:name":"Pacific Beach Golf Club Repair",
    "wof:placetype":"venue"
},
  "geometry": {"coordinates":[-117.228999,32.796471],"type":"Point"}
}