{
  "type": "Feature",
  "properties": {
    "addr:full":"1201 24th St Bakersfield CA 93301",
    "addr:housenumber":"1201",
    "addr:postcode":"93301",
    "addr:street":"24Th St",
    "iso:country":"US",
    "sg:address":"1201 24th St",
    "sg:city":"Bakersfield",
    "sg:classifiers":[
        {
            "category":"Personal",
            "subcategory":"Massage",
            "type":"Services"
        },
        {
            "category":"Shopping",
            "subcategory":"Beauty & Cosmetics",
            "type":"Retail Goods"
        },
        {
            "category":"Personal",
            "subcategory":"Day Spa",
            "type":"Services"
        },
        {
            "category":"Personal",
            "subcategory":"Skin Care",
            "type":"Services"
        },
        {
            "category":"Personal",
            "subcategory":"Beauty Salon",
            "type":"Services"
        }
    ],
    "sg:phone":"+1 661 323 1220",
    "sg:postcode":"93301",
    "sg:province":"CA",
    "sg:tags":[
        "therapist",
        "perfume"
    ],
    "wof:name":"Tru Skin & Body",
    "wof:placetype":"venue"
},
  "geometry": {"coordinates":[-119.01522799999999,35.381191],"type":"Point"}
}