{
  "type": "Feature",
  "properties": {
    "iso:country":"US",
    "sg:address":"7253 el Camino Real",
    "sg:city":"Atascadero",
    "sg:classifiers":[
        {
            "category":"Shopping",
            "subcategory":"Music",
            "type":"Retail Goods"
        }
    ],
    "sg:phone":"+1 805 462 0404",
    "sg:postcode":"93422",
    "sg:province":"CA",
    "sg:tags":[
        "video",
        "disc",
        "tape",
        "cassette"
    ],
    "wof:name":"Diamond Adult World",
    "wof:placetype":"venue"
},
  "geometry": {"coordinates":[-120.664214,35.485737],"type":"Point"}
}