{
  "type": "Feature",
  "properties": {
    "iso:country":"US",
    "sg:address":"5000 Birch St",
    "sg:city":"Newport Beach",
    "sg:classifiers":[
        {
            "category":"Banks & Credit Unions",
            "subcategory":"Bank",
            "type":"Services"
        }
    ],
    "sg:phone":"+1 949 251 9196",
    "sg:postcode":"92660",
    "sg:province":"CA",
    "sg:tags":[
        "loan",
        "real estate"
    ],
    "wof:name":"C W Capital LLC",
    "wof:placetype":"venue"
},
  "geometry": {"coordinates":[-117.858181,33.665774],"type":"Point"}
}