{
  "type": "Feature",
  "properties": {
    "iso:country":"US",
    "sg:address":"16337 Main St",
    "sg:city":"Guerneville",
    "sg:classifiers":[
        {
            "category":"Restaurant",
            "type":"Food & Drink"
        }
    ],
    "sg:phone":"+1 707 869 1665",
    "sg:postcode":"95446",
    "sg:province":"CA",
    "wof:name":"Pasta Boys Cafe & Deli",
    "wof:placetype":"venue"
},
  "geometry": {"coordinates":[-123.001999,38.5019],"type":"Point"}
}