{
  "type": "Feature",
  "properties": {
    "iso:country":"US",
    "sg:address":"3433 64th Avenue Pl",
    "sg:city":"Oakland",
    "sg:classifiers":[
        {
            "category":"Retail",
            "subcategory":"Auto Repair",
            "type":"Services"
        }
    ],
    "sg:phone":"+1 707 648 1587",
    "sg:postcode":"94605",
    "sg:province":"CA",
    "sg:tags":[
        "automobile",
        "customizing"
    ],
    "wof:name":"Playtyme Customs",
    "wof:placetype":"venue"
},
  "geometry": {"coordinates":[-122.178316,37.774306],"type":"Point"}
}