{
  "type": "Feature",
  "properties": {
    "addr:full":"4930 Vanderbilt St Ontario CA 91761",
    "addr:housenumber":"4930",
    "addr:postcode":"91761",
    "addr:street":"Vanderbilt St",
    "iso:country":"US",
    "sg:address":"4930 Vanderbilt St",
    "sg:city":"Ontario",
    "sg:classifiers":[
        {
            "category":"Retail",
            "subcategory":"Auto Rental",
            "type":"Services"
        }
    ],
    "sg:phone":"+1 909 390 2990",
    "sg:postcode":"91761",
    "sg:province":"CA",
    "sg:tags":[
        "renting",
        "automobile"
    ],
    "wof:name":"Hertz Rent A Car",
    "wof:placetype":"venue"
},
  "geometry": {"coordinates":[-117.545339,34.045065],"type":"Point"}
}