{
  "type": "Feature",
  "properties": {
    "addr:full":"1420 Windsor Ct Turlock CA 95380",
    "addr:housenumber":"1420",
    "addr:postcode":"95380",
    "addr:street":"Windsor Ct",
    "iso:country":"US",
    "sg:address":"1420 Windsor Ct",
    "sg:city":"Turlock",
    "sg:classifiers":[
        {
            "category":"Real Estate",
            "subcategory":"Real Estate Agent",
            "type":"Services"
        }
    ],
    "sg:phone":"+1 209 664 9469",
    "sg:postcode":"95380",
    "sg:province":"CA",
    "wof:name":"Anderson Bud Central Vly Rlty",
    "wof:placetype":"venue"
},
  "geometry": {"coordinates":[-120.842488,37.50478],"type":"Point"}
}