{
  "type": "Feature",
  "properties": {
    "iso:country":"US",
    "sg:address":"2200 E California Ave",
    "sg:city":"Bakersfield",
    "sg:classifiers":[
        {
            "category":"Retail",
            "subcategory":"Auto Repair",
            "type":"Services"
        }
    ],
    "sg:phone":"+1 661 336 0981",
    "sg:postcode":"93307",
    "sg:province":"CA",
    "sg:tags":[
        "repairing",
        "automobile"
    ],
    "wof:name":"J V's Auto Repair",
    "wof:placetype":"venue"
},
  "geometry": {"coordinates":[-118.9653,35.368609],"type":"Point"}
}