{
  "type": "Feature",
  "properties": {
    "addr:full":"6161 Amie Dr Windsor CA 95492",
    "addr:housenumber":"6161",
    "addr:postcode":"95492",
    "addr:street":"Amie Dr",
    "iso:country":"US",
    "sg:address":"6161 Amie Dr",
    "sg:city":"Windsor",
    "sg:classifiers":[
        {
            "category":"Insurance",
            "subcategory":"Insurance Agent",
            "type":"Services"
        }
    ],
    "sg:phone":"+1 707 838 3618",
    "sg:postcode":"95492",
    "sg:province":"CA",
    "wof:name":"NEA Valuebuilders",
    "wof:placetype":"venue"
},
  "geometry": {"coordinates":[-122.787926,38.532605],"type":"Point"}
}