{
  "type": "Feature",
  "properties": {
    "iso:country":"US",
    "sg:address":"2225 Southwest Dr",
    "sg:city":"Los Angeles",
    "sg:classifiers":[
        {
            "category":"Manufacturing",
            "subcategory":"Rubber & Plastics",
            "type":"Manufacturing & Wholesale Goods"
        }
    ],
    "sg:phone":"+1 323 750 7332",
    "sg:postcode":"90043",
    "sg:province":"CA",
    "sg:tags":[
        "product"
    ],
    "wof:name":"Little Crafts",
    "wof:placetype":"venue"
},
  "geometry": {"coordinates":[-118.31850900000001,33.983078],"type":"Point"}
}