{
  "type": "Feature",
  "properties": {
    "addr:full":"1835 W Rosecrans Ave Gardena CA 90249",
    "addr:housenumber":"1835",
    "addr:postcode":"90249",
    "addr:street":"W Rosecrans Ave",
    "iso:country":"US",
    "sg:address":"1835 W Rosecrans Ave",
    "sg:city":"Gardena",
    "sg:classifiers":[
        {
            "category":"Autos & Motor Vehicles",
            "subcategory":"Automobile Sales",
            "type":"Retail Goods"
        }
    ],
    "sg:phone":"+1 310 851 5700",
    "sg:postcode":"90249",
    "sg:province":"CA",
    "sg:tags":[
        "equipment",
        "aircraft",
        "parts",
        "supply"
    ],
    "wof:name":"LPJ Metalfab Inc",
    "wof:placetype":"venue"
},
  "geometry": {"coordinates":[-118.309764,33.902002],"type":"Point"}
}