{
  "type": "Feature",
  "properties": {
    "iso:country":"US",
    "sg:address":"1409 Normandy Dr",
    "sg:city":"Modesto",
    "sg:classifiers":[
        {
            "category":"Shopping",
            "type":"Retail Goods"
        }
    ],
    "sg:phone":"+1 209 526 7091",
    "sg:postcode":"95351",
    "sg:province":"CA",
    "sg:tags":[
        "cards",
        "sport",
        "baseball",
        "memorabilia"
    ],
    "wof:name":"Dr Sports Cards & Collectibles",
    "wof:placetype":"venue"
},
  "geometry": {"coordinates":[-121.025271,37.621783],"type":"Point"}
}