{
  "type": "Feature",
  "properties": {
    "iso:country":"US",
    "sg:address":"2815 Chanticleer Ave",
    "sg:city":"Santa Cruz",
    "sg:classifiers":[
        {
            "category":"Real Estate",
            "subcategory":"Real Estate Agent",
            "type":"Services"
        }
    ],
    "sg:phone":"+1 831 479 1901",
    "sg:postcode":"95065",
    "sg:province":"CA",
    "sg:tags":[
        "appraiser"
    ],
    "sg:website":"www.frankmay.com",
    "wof:name":"Frank May & Assoc",
    "wof:placetype":"venue"
},
  "geometry": {"coordinates":[-121.978478,36.986916],"type":"Point"}
}