{
  "type": "Feature",
  "properties": {
    "iso:country":"US",
    "sg:address":"73575 El Paseo Ste C2316",
    "sg:city":"Palm Desert",
    "sg:classifiers":[
        {
            "category":"Building & Trades",
            "subcategory":"Construction",
            "type":"Services"
        }
    ],
    "sg:phone":"+1 760 674 3232",
    "sg:postcode":"92260",
    "sg:province":"CA",
    "sg:tags":[
        "interior",
        "design"
    ],
    "wof:name":"Distinctive Interiors By",
    "wof:placetype":"venue"
},
  "geometry": {"coordinates":[-116.380948,33.71959],"type":"Point"}
}