{
  "type": "Feature",
  "properties": {
    "iso:country":"US",
    "sg:address":"5336 Humboldt Dr",
    "sg:city":"Rocklin",
    "sg:classifiers":[
        {
            "category":"Shopping",
            "subcategory":"Hobbies, Toys, & Games",
            "type":"Retail Goods"
        }
    ],
    "sg:phone":"+1 916 632 2178",
    "sg:postcode":"95765",
    "sg:province":"CA",
    "sg:tags":[
        "shop"
    ],
    "wof:name":"Iron Horse Hobbies",
    "wof:placetype":"venue"
},
  "geometry": {"coordinates":[-121.250113,38.805793],"type":"Point"}
}