{
  "type": "Feature",
  "properties": {
    "addr:full":"4420 Seville Ave Los Angeles CA 90058",
    "addr:housenumber":"4420",
    "addr:postcode":"90058",
    "addr:street":"Seville Ave",
    "iso:country":"US",
    "sg:address":"4420 Seville Ave",
    "sg:city":"Los Angeles",
    "sg:classifiers":[
        {
            "category":"Wholesale",
            "subcategory":"Non-durable Goods",
            "type":"Manufacturing & Wholesale Goods"
        }
    ],
    "sg:phone":"+1 323 584 9792",
    "sg:postcode":"90058",
    "sg:province":"CA",
    "sg:tags":[
        "merchandise",
        "general"
    ],
    "wof:name":"Landmark Enterprises",
    "wof:placetype":"venue"
},
  "geometry": {"coordinates":[-118.22234899999999,34.004729],"type":"Point"}
}