{
  "type": "Feature",
  "properties": {
    "addr:full":"2033 E Fruit St Santa Ana CA 92701",
    "addr:housenumber":"2033",
    "addr:postcode":"92701",
    "addr:street":"E Fruit St",
    "iso:country":"US",
    "sg:address":"2033 E Fruit St",
    "sg:city":"Santa Ana",
    "sg:classifiers":[
        {
            "category":"Manufacturing",
            "subcategory":"Tools & Machinery",
            "type":"Manufacturing & Wholesale Goods"
        }
    ],
    "sg:phone":"+1 714 954 0369",
    "sg:postcode":"92701",
    "sg:province":"CA",
    "sg:tags":[
        "dental",
        "mfg"
    ],
    "wof:name":"Lynne Glauber",
    "wof:placetype":"venue"
},
  "geometry": {"coordinates":[-117.83911000000001,33.752894],"type":"Point"}
}