{
  "type": "Feature",
  "properties": {
    "addr:full":"684 Telegraph Canyon Rd Chula Vista CA 91910",
    "addr:housenumber":"684",
    "addr:postcode":"91910",
    "addr:street":"Telegraph Canyon Rd",
    "iso:country":"US",
    "sg:address":"684 Telegraph Canyon Rd",
    "sg:city":"Chula Vista",
    "sg:classifiers":[
        {
            "category":"Bars & Pubs",
            "subcategory":"Nightclub",
            "type":"Food & Drink"
        }
    ],
    "sg:phone":"+1 619 421 9509",
    "sg:postcode":"91910",
    "sg:province":"CA",
    "sg:tags":[
        "nightlife"
    ],
    "wof:name":"Archway Lounge the",
    "wof:placetype":"venue"
},
  "geometry": {"coordinates":[-117.03299699999999,32.6264],"type":"Point"}
}