{
  "type": "Feature",
  "properties": {
    "addr:full":"208 E Compton Blvd Compton CA 90220",
    "addr:housenumber":"208",
    "addr:postcode":"90220",
    "addr:street":"E Compton Blvd",
    "iso:country":"US",
    "sg:address":"208 E Compton Blvd",
    "sg:city":"Compton",
    "sg:classifiers":[
        {
            "category":"Shopping",
            "subcategory":"Clothing, Apparel, & Fashions",
            "type":"Retail Goods"
        },
        {
            "category":"Shopping",
            "subcategory":"Shoes",
            "type":"Retail Goods"
        }
    ],
    "sg:phone":"+1 310 537 2429",
    "sg:postcode":"90220",
    "sg:province":"CA",
    "sg:tags":[
        "accessory",
        "store",
        "women's"
    ],
    "sg:website":"http://www.paylessshoesource.com",
    "wof:name":"Payless ShoeSource",
    "wof:placetype":"venue"
},
  "geometry": {"coordinates":[-118.22196099999999,33.895971],"type":"Point"}
}