{
  "type": "Feature",
  "properties": {
    "addr:full":"1325 Amethyst Ave Mentone CA 92359",
    "addr:housenumber":"1325",
    "addr:postcode":"92359",
    "addr:street":"Amethyst Ave",
    "iso:country":"US",
    "sg:address":"1325 Amethyst Ave",
    "sg:city":"Mentone",
    "sg:classifiers":[
        {
            "category":"Organizations",
            "subcategory":"Religious Organization",
            "type":"Services"
        }
    ],
    "sg:phone":"+1 909 794 9800",
    "sg:postcode":"92359",
    "sg:province":"CA",
    "sg:website":"www.amethystbible.org",
    "wof:name":"Amethyst Bible Church",
    "wof:placetype":"venue"
},
  "geometry": {"coordinates":[-117.104023,34.179903],"type":"Point"}
}