{
  "type": "Feature",
  "properties": {
    "addr:full":"1024 E US Hwy 98 Calexico CA 92231",
    "addr:housenumber":"1024",
    "addr:postcode":"92231",
    "addr:street":"E Us Hwy 98",
    "iso:country":"US",
    "sg:address":"1024 E US Hwy 98",
    "sg:city":"Calexico",
    "sg:classifiers":[
        {
            "category":"Wholesale",
            "subcategory":"Farm Supplies",
            "type":"Manufacturing & Wholesale Goods"
        }
    ],
    "sg:phone":"+1 760 768 6815",
    "sg:postcode":"92231",
    "sg:province":"CA",
    "sg:tags":[
        "livestock"
    ],
    "wof:name":"Phillips Cattle Co Tamarack",
    "wof:placetype":"venue"
},
  "geometry": {"coordinates":[-115.44793799999999,32.693896],"type":"Point"}
}