{
  "type": "Feature",
  "properties": {
    "addr:full":"2741 McMillan Ave San Luis Obispo CA 93401",
    "addr:housenumber":"2741",
    "addr:postcode":"93401",
    "addr:street":"Mcmillan Ave",
    "iso:country":"US",
    "sg:address":"2741 McMillan Ave",
    "sg:city":"San Luis Obispo",
    "sg:classifiers":[
        {
            "category":"Wholesale",
            "subcategory":"Sporting Goods",
            "type":"Manufacturing & Wholesale Goods"
        },
        {
            "category":"Manufacturing",
            "subcategory":"Toys & Sporting Goods",
            "type":"Manufacturing & Wholesale Goods"
        }
    ],
    "sg:phone":"+1 805 549 9764",
    "sg:postcode":"93401",
    "sg:province":"CA",
    "sg:tags":[
        "athletic"
    ],
    "sg:website":"www.rootamental.com",
    "wof:name":"Rootamental",
    "wof:placetype":"venue"
},
  "geometry": {"coordinates":[-120.648179,35.264589],"type":"Point"}
}