{
  "type": "Feature",
  "properties": {
    "addr:full":"975 Pacific Ave San Jose CA 95126",
    "addr:housenumber":"975",
    "addr:postcode":"95126",
    "addr:street":"Pacific Ave",
    "iso:country":"US",
    "sg:address":"975 Pacific Ave",
    "sg:city":"San Jose",
    "sg:classifiers":[
        {
            "category":"Building & Trades",
            "subcategory":"Landscaping Services",
            "type":"Services"
        }
    ],
    "sg:phone":"+1 408 971 2044",
    "sg:postcode":"95126",
    "sg:province":"CA",
    "sg:tags":[
        "gardener"
    ],
    "wof:name":"Chavez Gardening Service",
    "wof:placetype":"venue"
},
  "geometry": {"coordinates":[-121.909982,37.324685],"type":"Point"}
}