{
  "type": "Feature",
  "properties": {
    "addr:full":"235 N Goodhope Ave San Pedro CA 90732",
    "addr:housenumber":"235",
    "addr:postcode":"90732",
    "addr:street":"N Goodhope Ave",
    "iso:country":"US",
    "sg:address":"235 N Goodhope Ave",
    "sg:city":"San Pedro",
    "sg:classifiers":[
        {
            "category":"Freight",
            "type":"Transportation"
        }
    ],
    "sg:phone":"+1 310 833 0461",
    "sg:postcode":"90732",
    "sg:province":"CA",
    "sg:tags":[
        "arrangement"
    ],
    "wof:name":"V & N Sales",
    "wof:placetype":"venue"
},
  "geometry": {"coordinates":[-118.31623,33.746395],"type":"Point"}
}