{
  "type": "Feature",
  "properties": {
    "addr:full":"328 W Portal Ave San Francisco CA 94127",
    "addr:housenumber":"328",
    "addr:postcode":"94127",
    "addr:street":"W Portal Ave",
    "iso:country":"US",
    "sg:address":"328 W Portal Ave",
    "sg:city":"San Francisco",
    "sg:classifiers":[
        {
            "category":"Bars & Pubs",
            "type":"Food & Drink"
        }
    ],
    "sg:phone":"+1 415 566 9444",
    "sg:postcode":"94127",
    "sg:province":"CA",
    "sg:website":"www.dublinerwp.com",
    "wof:name":"The Dubliner",
    "wof:placetype":"venue"
},
  "geometry": {"coordinates":[-122.469639,37.737595],"type":"Point"}
}