{
  "type": "Feature",
  "properties": {
    "iso:country":"US",
    "sg:address":"36400 Bankside Dr",
    "sg:city":"Cathedral City",
    "sg:classifiers":[
        {
            "category":"Retail",
            "subcategory":"Auto Repair",
            "type":"Services"
        }
    ],
    "sg:phone":"+1 760 324 3454",
    "sg:postcode":"92234",
    "sg:province":"CA",
    "sg:tags":[
        "body",
        "shop"
    ],
    "sg:website":"www.rembrandtspaintandbody.com",
    "wof:name":"Rembrandt's Paint & Body",
    "wof:placetype":"venue"
},
  "geometry": {"coordinates":[-116.468959,33.782975],"type":"Point"}
}