{
  "type": "Feature",
  "properties": {
    "addr:full":"8262 Blandwood Rd Downey CA 90240",
    "addr:housenumber":"8262",
    "addr:postcode":"90240",
    "addr:street":"Blandwood Rd",
    "iso:country":"US",
    "sg:address":"8262 Blandwood Rd",
    "sg:city":"Downey",
    "sg:phone":"+1 562 904 3414",
    "sg:postcode":"90240",
    "sg:province":"CA",
    "wof:name":"Uncle Dennys Critter Sitters",
    "wof:placetype":"venue"
},
  "geometry": {"coordinates":[-118.116192,33.962212],"type":"Point"}
}