{
  "type": "Feature",
  "properties": {
    "acgov:api":"924.0",
    "acgov:type":"ES",
    "addr:full":"4150 Dorman Rd Pleasanton CA",
    "wof:categories":[
        "education_and_religion:education=school"
    ],
    "wof:name":"Donlon Elementary",
    "wof:placetype":"venue"
},
  "geometry": {"coordinates":[-121.90702857784373,37.68463526716844],"type":"Point"}
}