{
  "type": "Feature",
  "properties": {
    "addr:full":"21177 Nandina Rd Apple Valley CA 92308",
    "addr:housenumber":"21177",
    "addr:postcode":"92308",
    "addr:street":"Nandina Rd",
    "iso:country":"US",
    "sg:address":"21177 Nandina Rd",
    "sg:city":"Apple Valley",
    "sg:classifiers":[
        {
            "category":"Real Estate",
            "subcategory":"Real Estate Agent",
            "type":"Services"
        }
    ],
    "sg:phone":"+1 760 403 4068",
    "sg:postcode":"92308",
    "sg:province":"CA",
    "wof:name":"American Landmark Homes Inc",
    "wof:placetype":"venue"
},
  "geometry": {"coordinates":[-117.199566,34.446209],"type":"Point"}
}