{
  "type": "Feature",
  "properties": {
    "addr:full":"1400 W Capitol Ave West Sacramento CA 95691",
    "addr:housenumber":"1400",
    "addr:postcode":"95691",
    "addr:street":"W Capitol Ave",
    "iso:country":"US",
    "sg:address":"1400 W Capitol Ave",
    "sg:city":"West Sacramento",
    "sg:classifiers":[
        {
            "category":"Autos & Motor Vehicles",
            "subcategory":"Auto Supplies",
            "type":"Retail Goods"
        }
    ],
    "sg:phone":"+1 916 372 6386",
    "sg:postcode":"95691",
    "sg:province":"CA",
    "sg:tags":[
        "automobile",
        "parts"
    ],
    "wof:name":"Autozone",
    "wof:placetype":"venue"
},
  "geometry": {"coordinates":[-121.53064000000001,38.580261],"type":"Point"}
}