{
  "type": "Feature",
  "properties": {
    "iso:country":"US",
    "sg:address":"6050 Atlantic Ave",
    "sg:city":"Long Beach",
    "sg:classifiers":[
        {
            "category":"Personal",
            "subcategory":"Barber",
            "type":"Services"
        }
    ],
    "sg:phone":"+1 562 422 2631",
    "sg:postcode":"90805",
    "sg:province":"CA",
    "wof:name":"Cedrics Hair Fashion Barber",
    "wof:placetype":"venue"
},
  "geometry": {"coordinates":[-118.184923,33.864579],"type":"Point"}
}