{
  "type": "Feature",
  "properties": {
    "iso:country":"US",
    "sg:address":"1454 G St",
    "sg:city":"Fresno",
    "sg:phone":"+1 559 442 0525",
    "sg:postcode":"93706",
    "sg:province":"CA",
    "sg:tags":[
        "product",
        "petroleum"
    ],
    "wof:name":"Visa Petroleum Inc",
    "wof:placetype":"venue"
},
  "geometry": {"coordinates":[-119.798751,36.735686],"type":"Point"}
}