{
  "type": "Feature",
  "properties": {
    "addr:full":"592 Manzanita Ave Chico CA 95926",
    "addr:housenumber":"592",
    "addr:postcode":"95926",
    "addr:street":"Manzanita Ave",
    "iso:country":"US",
    "sg:address":"592 Manzanita Ave",
    "sg:city":"Chico",
    "sg:classifiers":[
        {
            "category":"Professional",
            "subcategory":"Lawyer & Legal Services",
            "type":"Services"
        }
    ],
    "sg:phone":"+1 530 893 0131",
    "sg:postcode":"95926",
    "sg:province":"CA",
    "sg:tags":[
        "attorney"
    ],
    "wof:name":"Watkins & Watkins",
    "wof:placetype":"venue"
},
  "geometry": {"coordinates":[-121.843278,39.754686],"type":"Point"}
}