{
  "type": "Feature",
  "properties": {
    "addr:full":"720 N Todd Ave Azusa CA 91702",
    "addr:housenumber":"720",
    "addr:postcode":"91702",
    "addr:street":"N Todd Ave",
    "iso:country":"US",
    "sg:address":"720 N Todd Ave",
    "sg:city":"Azusa",
    "sg:classifiers":[
        {
            "category":"Shopping",
            "subcategory":"Computers & Home Electronics",
            "type":"Retail Goods"
        }
    ],
    "sg:phone":"+1 626 305 8866",
    "sg:postcode":"91702",
    "sg:province":"CA",
    "sg:tags":[
        "equipment",
        "dealer"
    ],
    "wof:name":"P T Computer Work",
    "wof:placetype":"venue"
},
  "geometry": {"coordinates":[-117.924795,34.139484],"type":"Point"}
}