{
  "type": "Feature",
  "properties": {
    "addr:full":"350 Townsend St Ste 426 San Francisco CA 94107",
    "addr:housenumber":"350",
    "addr:postcode":"94107",
    "addr:street":"Townsend St Ste 426",
    "iso:country":"US",
    "sg:address":"350 Townsend St Ste 426",
    "sg:city":"San Francisco",
    "sg:classifiers":[
        {
            "category":"Professional",
            "subcategory":"Art Services",
            "type":"Services"
        },
        {
            "category":"Communications",
            "type":"Services"
        }
    ],
    "sg:phone":"+1 415 254 2748",
    "sg:postcode":"94107",
    "sg:province":"CA",
    "sg:tags":[
        "web",
        "graphic",
        "design"
    ],
    "sg:website":"www.flair-designs.com",
    "wof:name":"Flair Designs",
    "wof:placetype":"venue"
},
  "geometry": {"coordinates":[-122.396506,37.776271],"type":"Point"}
}