{
  "type": "Feature",
  "properties": {
    "addr:full":"2001 Union Street Suite 570 San Francisco CA 94123",
    "addr:housenumber":"2001",
    "addr:postcode":"94123",
    "addr:street":"Union Street Suite 570",
    "iso:country":"US",
    "sg:address":"2001 Union Street Suite 570",
    "sg:city":"San Francisco",
    "sg:classifiers":[
        {
            "category":"Banks & Credit Unions",
            "subcategory":"Financial Services",
            "type":"Services"
        }
    ],
    "sg:phone":"+1 415 775 3500",
    "sg:postcode":"94123",
    "sg:province":"CA",
    "sg:tags":[
        "broker",
        "mortgage"
    ],
    "wof:name":"First Security Loan",
    "wof:placetype":"venue"
},
  "geometry": {"coordinates":[-122.431999,37.797501],"type":"Point"}
}