{
  "type": "Feature",
  "properties": {
    "iso:country":"US",
    "sg:address":"1688 N Perris Blvd",
    "sg:city":"Perris",
    "sg:classifiers":[
        {
            "category":"Personal",
            "subcategory":"Beauty Salon",
            "type":"Services"
        }
    ],
    "sg:phone":"+1 951 943 7770",
    "sg:postcode":"92571",
    "sg:province":"CA",
    "sg:tags":[
        "manicuring"
    ],
    "wof:name":"Exotic Nails",
    "wof:placetype":"venue"
},
  "geometry": {"coordinates":[-117.226026,33.802786],"type":"Point"}
}