{
  "type": "Feature",
  "properties": {
    "addr:full":"11400 Ventura Blvd Studio City CA 91604",
    "addr:housenumber":"11400",
    "addr:postcode":"91604",
    "addr:street":"Ventura Blvd",
    "iso:country":"US",
    "sg:address":"11400 Ventura Blvd",
    "sg:city":"Studio City",
    "sg:classifiers":[
        {
            "category":"Restaurant",
            "type":"Food & Drink"
        }
    ],
    "sg:phone":"+1 818 487 7000",
    "sg:postcode":"91604",
    "sg:province":"CA",
    "wof:name":"Dragon X",
    "wof:placetype":"venue"
},
  "geometry": {"coordinates":[-118.380511,34.139553],"type":"Point"}
}