{
  "type": "Feature",
  "properties": {
    "addr:full":"322 Main St Woodland CA 95695",
    "addr:housenumber":"322",
    "addr:postcode":"95695",
    "addr:street":"Main St",
    "iso:country":"US",
    "sg:address":"322 Main St",
    "sg:city":"Woodland",
    "sg:classifiers":[
        {
            "category":"Cinema",
            "subcategory":"Movie Theater",
            "type":"Entertainment"
        }
    ],
    "sg:phone":"+1 530 666 3444",
    "sg:postcode":"95695",
    "sg:province":"CA",
    "wof:name":"State Theatre",
    "wof:placetype":"venue"
},
  "geometry": {"coordinates":[-121.776718,38.677452],"type":"Point"}
}