{
  "type": "Feature",
  "properties": {
    "addr:full":"42215 Palm Ave Fremont CA 94539",
    "addr:housenumber":"42215",
    "addr:postcode":"94539",
    "addr:street":"Palm Ave",
    "iso:country":"US",
    "sg:address":"42215 Palm Ave",
    "sg:city":"Fremont",
    "sg:classifiers":[
        {
            "category":"Manufacturing",
            "subcategory":"Printing",
            "type":"Manufacturing & Wholesale Goods"
        }
    ],
    "sg:phone":"+1 510 656 2002",
    "sg:postcode":"94539",
    "sg:province":"CA",
    "sg:tags":[
        "book"
    ],
    "wof:name":"Ddc Publishing",
    "wof:placetype":"venue"
},
  "geometry": {"coordinates":[-121.933848,37.537563],"type":"Point"}
}