{
  "type": "Feature",
  "properties": {
    "iso:country":"US",
    "sg:address":"407 W Douglas Ave",
    "sg:city":"El Cajon",
    "sg:classifiers":[
        {
            "category":"Professional",
            "subcategory":"Accounting & Tax Preparation",
            "type":"Services"
        }
    ],
    "sg:phone":"+1 619 447 8297",
    "sg:postcode":"92020",
    "sg:province":"CA",
    "sg:tags":[
        "return",
        "filing"
    ],
    "wof:name":"J & J Personalized Tax Prep",
    "wof:placetype":"venue"
},
  "geometry": {"coordinates":[-116.967922,32.794401],"type":"Point"}
}