{
  "type": "Feature",
  "properties": {
    "addr:full":"6513 Sun Ranch Dr Sacramento CA 95823",
    "addr:housenumber":"6513",
    "addr:postcode":"95823",
    "addr:street":"Sun Ranch Dr",
    "iso:country":"US",
    "sg:address":"6513 Sun Ranch Dr",
    "sg:city":"Sacramento",
    "sg:classifiers":[
        {
            "category":"Freight",
            "type":"Transportation"
        }
    ],
    "sg:phone":"+1 916 821 5939",
    "sg:postcode":"95823",
    "sg:province":"CA",
    "wof:name":"Advanced Crate & Freight",
    "wof:placetype":"venue"
},
  "geometry": {"coordinates":[-121.429851,38.447768],"type":"Point"}
}