{
  "type": "Feature",
  "properties": {
    "addr:full":"706 S Hill St Ste 940 Los Angeles CA 90014",
    "addr:housenumber":"706",
    "addr:postcode":"90014",
    "addr:street":"S Hill St Ste 940",
    "iso:country":"US",
    "sg:address":"706 S Hill St Ste 940",
    "sg:city":"Los Angeles",
    "sg:classifiers":[
        {
            "category":"Shopping",
            "subcategory":"Jewelry",
            "type":"Retail Goods"
        }
    ],
    "sg:phone":"+1 213 627 8309",
    "sg:postcode":"90014",
    "sg:province":"CA",
    "wof:name":"Exclusive Jewelry Designs",
    "wof:placetype":"venue"
},
  "geometry": {"coordinates":[-118.254997,34.045799],"type":"Point"}
}