{
  "type": "Feature",
  "properties": {
    "addr:full":"32 Discovery Ste 250 Irvine CA 92618",
    "addr:housenumber":"32",
    "addr:postcode":"92618",
    "addr:street":"Discovery Ste 250",
    "iso:country":"US",
    "sg:address":"32 Discovery Ste 250",
    "sg:city":"Irvine",
    "sg:classifiers":[
        {
            "category":"Education",
            "subcategory":"University",
            "type":"Public Place"
        }
    ],
    "sg:phone":"+1 949 450 9066",
    "sg:postcode":"92618",
    "sg:province":"CA",
    "sg:tags":[
        "college"
    ],
    "sg:website":"www.webster.edu",
    "wof:name":"Webster University",
    "wof:placetype":"venue"
},
  "geometry": {"coordinates":[-117.75566000000001,33.667052],"type":"Point"}
}