{
  "type": "Feature",
  "properties": {
    "iso:country":"US",
    "sg:address":"370 B St",
    "sg:city":"Fresno",
    "sg:classifiers":[
        {
            "category":"Food & Beverages",
            "subcategory":"Liquor & Beverages",
            "type":"Retail Goods"
        }
    ],
    "sg:phone":"+1 559 485 0688",
    "sg:postcode":"93706",
    "sg:province":"CA",
    "wof:name":"Discount General Merchandise",
    "wof:placetype":"venue"
},
  "geometry": {"coordinates":[-119.79188499999999,36.72106],"type":"Point"}
}