{
  "type": "Feature",
  "properties": {
    "addr:full":"211 Hillcrest Ave Marina CA 93933",
    "addr:housenumber":"211",
    "addr:postcode":"93933",
    "addr:street":"Hillcrest Ave",
    "iso:country":"US",
    "sg:address":"211 Hillcrest Ave",
    "sg:city":"Marina",
    "sg:classifiers":[
        {
            "category":"Government",
            "subcategory":"Police Station",
            "type":"Public Place"
        }
    ],
    "sg:phone":"+1 831 384 5225",
    "sg:postcode":"93933",
    "sg:province":"CA",
    "sg:tags":[
        "department"
    ],
    "wof:name":"Marina City Police Dept",
    "wof:placetype":"venue"
},
  "geometry": {"coordinates":[-121.802654,36.681822],"type":"Point"}
}