{
  "type": "Feature",
  "properties": {
    "addr:full":"2603 W 1st St Santa Ana CA 92703",
    "addr:housenumber":"2603",
    "addr:postcode":"92703",
    "addr:street":"W 1St St",
    "iso:country":"US",
    "sg:address":"2603 W 1st St",
    "sg:city":"Santa Ana",
    "sg:classifiers":[
        {
            "category":"Shopping",
            "subcategory":"Thrift Store",
            "type":"Retail Goods"
        }
    ],
    "sg:phone":"+1 714 541 6726",
    "sg:postcode":"92703",
    "sg:province":"CA",
    "wof:name":"The Salvation Army",
    "wof:placetype":"venue"
},
  "geometry": {"coordinates":[-117.903999,33.745098],"type":"Point"}
}