{
  "type": "Feature",
  "properties": {
    "addr:full":"1000 I St Modesto CA 95354",
    "addr:housenumber":"1000",
    "addr:postcode":"ca 95354",
    "addr:street":"I St",
    "iso:country":"US",
    "sg:address":"1000 I St",
    "sg:city":"Modesto",
    "sg:classifiers":[
        {
            "category":"Building & Trades",
            "subcategory":"Plumbing",
            "type":"Services"
        }
    ],
    "sg:phone":"+1 209 572 3038",
    "sg:postcode":"95354",
    "sg:province":"CA",
    "sg:tags":[
        "contractor"
    ],
    "wof:name":"J W Mc Clenahan Co",
    "wof:placetype":"venue"
},
  "geometry": {"coordinates":[-120.99819599999999,37.640267],"type":"Point"}
}