{
  "type": "Feature",
  "properties": {
    "addr:full":"8629 Auburn Folsom Rd Granite Bay CA 95746",
    "addr:housenumber":"8629",
    "addr:postcode":"95746",
    "addr:street":"Auburn Folsom Rd",
    "iso:country":"US",
    "sg:address":"8629 Auburn Folsom Rd",
    "sg:city":"Granite Bay",
    "sg:classifiers":[
        {
            "category":"Insurance",
            "subcategory":"Insurance Agent",
            "type":"Services"
        }
    ],
    "sg:phone":"+1 916 797 6930",
    "sg:postcode":"95746",
    "sg:province":"CA",
    "wof:name":"Falcon Aviation Insurance",
    "wof:placetype":"venue"
},
  "geometry": {"coordinates":[-121.17049900000001,38.742636],"type":"Point"}
}