{
  "type": "Feature",
  "properties": {
    "addr:full":"7540 Elata Ave Yucca Valley CA 92284",
    "addr:housenumber":"7540",
    "addr:postcode":"92284",
    "addr:street":"Elata Ave",
    "iso:country":"US",
    "sg:address":"7540 Elata Ave",
    "sg:city":"Yucca Valley",
    "sg:classifiers":[
        {
            "category":"Shopping",
            "subcategory":"Gifts & Souvenirs",
            "type":"Retail Goods"
        }
    ],
    "sg:phone":"+1 209 577 6825",
    "sg:postcode":"92284",
    "sg:province":"CA",
    "wof:name":"Crystal Dreams",
    "wof:placetype":"venue"
},
  "geometry": {"coordinates":[-116.41476400000001,34.115359],"type":"Point"}
}