{
  "type": "Feature",
  "properties": {
    "iso:country":"US",
    "sg:address":"7928 State Street",
    "sg:city":"Huntington Park",
    "sg:classifiers":[
        {
            "category":"Food & Beverages",
            "subcategory":"Groceries & Convenience Stores",
            "type":"Retail Goods"
        }
    ],
    "sg:phone":"+1 323 581 7863",
    "sg:postcode":"90255",
    "sg:province":"CA",
    "wof:name":"Morenita Market",
    "wof:placetype":"venue"
},
  "geometry": {"coordinates":[-118.21089499999999,33.964495],"type":"Point"}
}