{
  "type": "Feature",
  "properties": {
    "addr:full":"605 Magazine St Vallejo CA 94590",
    "addr:housenumber":"605",
    "addr:postcode":"94590",
    "addr:street":"Magazine St",
    "iso:country":"US",
    "sg:address":"605 Magazine St",
    "sg:city":"Vallejo",
    "sg:classifiers":[
        {
            "category":"Food & Beverages",
            "subcategory":"Groceries & Convenience Stores",
            "type":"Retail Goods"
        }
    ],
    "sg:phone":"+1 707 554 0160",
    "sg:postcode":"94590",
    "sg:province":"CA",
    "sg:tags":[
        "grocer"
    ],
    "wof:name":"Discount Gas Grocery & Liquor",
    "wof:placetype":"venue"
},
  "geometry": {"coordinates":[-122.237803,38.082807],"type":"Point"}
}