{
  "type": "Feature",
  "properties": {
    "iso:country":"US",
    "sg:address":"12131 Ave 200",
    "sg:city":"Tulare",
    "sg:classifiers":[
        {
            "category":"Farming",
            "subcategory":"Dairy Farm",
            "type":"Manufacturing & Wholesale Goods"
        }
    ],
    "sg:phone":"+1 559 686 9610",
    "sg:postcode":"93274",
    "sg:province":"CA",
    "sg:tags":[
        "livestock"
    ],
    "wof:name":"Bel R Martin & Sons",
    "wof:placetype":"venue"
},
  "geometry": {"coordinates":[-119.313883,36.15273],"type":"Point"}
}