{
  "type": "Feature",
  "properties": {
    "addr:full":"4334 San Pablo Ave Emeryville CA 94608",
    "addr:housenumber":"4334",
    "addr:postcode":"94608",
    "addr:street":"San Pablo Ave",
    "iso:country":"US",
    "sg:address":"4334 San Pablo Ave",
    "sg:city":"Emeryville",
    "sg:classifiers":[
        {
            "category":"Personal",
            "subcategory":"Nail Salon",
            "type":"Services"
        }
    ],
    "sg:phone":"+1 510 654 6948",
    "sg:postcode":"94608",
    "sg:province":"CA",
    "wof:name":"Victoria Nails",
    "wof:placetype":"venue"
},
  "geometry": {"coordinates":[-122.279999,37.8335],"type":"Point"}
}