{
  "type": "Feature",
  "properties": {
    "iso:country":"US",
    "sg:address":"9871 Santa Monica Blvd",
    "sg:city":"Beverly Hills",
    "sg:classifiers":[
        {
            "category":"Personal",
            "subcategory":"Beauty Salon",
            "type":"Services"
        }
    ],
    "sg:phone":"+1 310 277 9005",
    "sg:postcode":"90212",
    "sg:province":"CA",
    "wof:name":"Carrie White Hair",
    "wof:placetype":"venue"
},
  "geometry": {"coordinates":[-118.410154,34.067335],"type":"Point"}
}