{
  "type": "Feature",
  "properties": {
    "addr:full":"7510 Clairemont Mesa Boulevard San Diego CA 92111",
    "addr:housenumber":"7510",
    "addr:postcode":"92111",
    "addr:street":"Clairemont Mesa Boulevard",
    "iso:country":"US",
    "sg:address":"7510 Clairemont Mesa Boulevard",
    "sg:city":"San Diego",
    "sg:classifiers":[
        {
            "category":"Organizations",
            "subcategory":"Non-profit Organization",
            "type":"Services"
        }
    ],
    "sg:phone":"+1 858 268 9888",
    "sg:postcode":"92111",
    "sg:province":"CA",
    "sg:tags":[
        "service/non-profit",
        "community"
    ],
    "wof:name":"Community Campership Council",
    "wof:placetype":"venue"
},
  "geometry": {"coordinates":[-117.157569,32.832776],"type":"Point"}
}