{
  "type": "Feature",
  "properties": {
    "iso:country":"US",
    "sg:address":"4736 J St Unit B",
    "sg:city":"Sacramento",
    "sg:classifiers":[
        {
            "category":"Professional",
            "subcategory":"Art Services",
            "type":"Services"
        }
    ],
    "sg:phone":"+1 916 505 2329",
    "sg:postcode":"95819",
    "sg:province":"CA",
    "sg:tags":[
        "photographer"
    ],
    "sg:website":"www.loveatfirstclickphotography.com",
    "wof:name":"Love At First Click Photography",
    "wof:placetype":"venue"
},
  "geometry": {"coordinates":[-121.444278,38.567186],"type":"Point"}
}