{
  "type": "Feature",
  "properties": {
    "addr:full":"946 E Julian St San Jose CA 95112",
    "addr:housenumber":"946",
    "addr:postcode":"95112",
    "addr:street":"E Julian St",
    "iso:country":"US",
    "sg:address":"946 E Julian St",
    "sg:city":"San Jose",
    "sg:classifiers":[
        {
            "category":"Personal",
            "subcategory":"Beauty Salon",
            "type":"Services"
        }
    ],
    "sg:phone":"+1 408 286 2401",
    "sg:postcode":"95112",
    "sg:province":"CA",
    "wof:name":"Lydia's Hair Stylist",
    "wof:placetype":"venue"
},
  "geometry": {"coordinates":[-121.875642,37.349085],"type":"Point"}
}