{
  "type": "Feature",
  "properties": {
    "addr:full":"500 Auto Center Dr Watsonville CA 95076",
    "addr:housenumber":"500",
    "addr:postcode":"95076",
    "addr:street":"Auto Center Dr",
    "iso:country":"US",
    "sg:address":"500 Auto Center Dr",
    "sg:city":"Watsonville",
    "sg:classifiers":[
        {
            "category":"Autos & Motor Vehicles",
            "subcategory":"Automobile Sales",
            "type":"Retail Goods"
        },
        {
            "category":"Autos & Motor Vehicles",
            "subcategory":"Auto Supplies",
            "type":"Retail Goods"
        },
        {
            "category":"Retail",
            "subcategory":"Auto Repair",
            "type":"Services"
        }
    ],
    "sg:phone":"+1 831 722 3522",
    "sg:postcode":"95076",
    "sg:province":"CA",
    "sg:tags":[
        "car",
        "part",
        "used",
        "truck",
        "new"
    ],
    "sg:website":"http://gmdealerdashboard.com/track/click/1620",
    "wof:name":"Watsonville Cadillac Buick GMC",
    "wof:placetype":"venue"
},
  "geometry": {"coordinates":[-121.768066,36.920391],"type":"Point"}
}