{
  "type": "Feature",
  "properties": {
    "addr:full":"455 Capitol Mall Sacramento CA 95814",
    "addr:housenumber":"455",
    "addr:postcode":"95814",
    "addr:street":"Capitol Mall",
    "iso:country":"US",
    "sg:address":"455 Capitol Mall",
    "sg:city":"Sacramento",
    "sg:classifiers":[
        {
            "category":"Banks & Credit Unions",
            "subcategory":"Investment Brokerage",
            "type":"Services"
        }
    ],
    "sg:phone":"+1 916 498 0001",
    "sg:postcode":"95814",
    "sg:province":"CA",
    "sg:tags":[
        "advisory"
    ],
    "wof:name":"Titus Equity Partners",
    "wof:placetype":"venue"
},
  "geometry": {"coordinates":[-121.50210199999999,38.579032],"type":"Point"}
}