{
  "type": "Feature",
  "properties": {
    "addr:full":"1624 Knollwood Ave San Jose CA 95125",
    "addr:housenumber":"1624",
    "addr:postcode":"95125",
    "addr:street":"Knollwood Ave",
    "iso:country":"US",
    "sg:address":"1624 Knollwood Ave",
    "sg:city":"San Jose",
    "sg:classifiers":[
        {
            "category":"Real Estate",
            "subcategory":"Real Estate Operator",
            "type":"Services"
        }
    ],
    "sg:phone":"+1 408 265 3570",
    "sg:postcode":"95125",
    "sg:province":"CA",
    "sg:tags":[
        "building",
        "apartment"
    ],
    "wof:name":"Goodwin Properties",
    "wof:placetype":"venue"
},
  "geometry": {"coordinates":[-121.902565,37.276942],"type":"Point"}
}