{
  "type": "Feature",
  "properties": {
    "addr:full":"11601 Wilshire Blvd Los Angeles CA 90025",
    "addr:housenumber":"11601",
    "addr:postcode":"90025",
    "addr:street":"Wilshire Blvd",
    "iso:country":"US",
    "sg:address":"11601 Wilshire Blvd",
    "sg:city":"Los Angeles",
    "sg:classifiers":[
        {
            "category":"Professional",
            "subcategory":"Lawyer & Legal Services",
            "type":"Services"
        }
    ],
    "sg:phone":"+1 310 445 0609",
    "sg:postcode":"90025",
    "sg:province":"CA",
    "sg:tags":[
        "attorney"
    ],
    "sg:website":"www.mainstain.com",
    "wof:name":"Morris Mainstain Law Office",
    "wof:placetype":"venue"
},
  "geometry": {"coordinates":[-118.460072,34.050095],"type":"Point"}
}