{
  "type": "Feature",
  "properties": {
    "addr:full":"5655 Arcturus Ave Oxnard CA 93033",
    "addr:housenumber":"5655",
    "addr:postcode":"93033",
    "addr:street":"Arcturus Ave",
    "iso:country":"US",
    "sg:address":"5655 Arcturus Ave",
    "sg:city":"Oxnard",
    "sg:classifiers":[
        {
            "category":"Freight",
            "type":"Transportation"
        }
    ],
    "sg:phone":"+1 805 986 9100",
    "sg:postcode":"93033",
    "sg:province":"CA",
    "sg:tags":[
        "operator",
        "local",
        "trucking"
    ],
    "wof:name":"Super Fresh Produce Sales",
    "wof:placetype":"venue"
},
  "geometry": {"coordinates":[-119.17238500000001,34.140936],"type":"Point"}
}