{
  "type": "Feature",
  "properties": {
    "addr:full":"275 Kearney Exd Watsonville CA 95076",
    "addr:housenumber":"275",
    "addr:postcode":"95076",
    "addr:street":"Kearney Exd",
    "iso:country":"US",
    "sg:address":"275 Kearney Exd",
    "sg:city":"Watsonville",
    "sg:classifiers":[
        {
            "category":"Professional",
            "subcategory":"Accounting & Tax Preparation",
            "type":"Services"
        }
    ],
    "sg:phone":"+1 831 724 1133",
    "sg:postcode":"95076",
    "sg:province":"CA",
    "sg:tags":[
        "bookkeeping",
        "general"
    ],
    "wof:name":"Karen Aliotti Bookkeeping Svc",
    "wof:placetype":"venue"
},
  "geometry": {"coordinates":[-121.76517699999999,36.90851],"type":"Point"}
}