{
  "type": "Feature",
  "properties": {
    "addr:full":"608 E Palm Ave Orange CA 92866",
    "addr:housenumber":"608",
    "addr:postcode":"92866",
    "addr:street":"E Palm Ave",
    "iso:country":"US",
    "sg:address":"608 E Palm Ave",
    "sg:city":"Orange",
    "sg:classifiers":[
        {
            "category":"Food & Beverages",
            "subcategory":"Groceries & Convenience Stores",
            "type":"Retail Goods"
        }
    ],
    "sg:phone":"+1 714 538 8110",
    "sg:postcode":"92866",
    "sg:province":"CA",
    "wof:name":"Palm Market",
    "wof:placetype":"venue"
},
  "geometry": {"coordinates":[-117.84699999999999,33.791401],"type":"Point"}
}