{
  "type": "Feature",
  "properties": {
    "iso:country":"US",
    "sg:address":"233 Granada Dr",
    "sg:city":"San Luis Obispo",
    "sg:classifiers":[
        {
            "category":"Manufacturing",
            "subcategory":"Motor Vehicles & Parts",
            "type":"Manufacturing & Wholesale Goods"
        }
    ],
    "sg:phone":"+1 805 549 0147",
    "sg:postcode":"93401",
    "sg:province":"CA",
    "sg:tags":[
        "equipment",
        "transportation",
        "mfg"
    ],
    "wof:name":"Chuck Grash Enterprises",
    "wof:placetype":"venue"
},
  "geometry": {"coordinates":[-120.66674999999999,35.251052],"type":"Point"}
}