{
  "type": "Feature",
  "properties": {
    "iso:country":"US",
    "sg:address":"101 Fishermans Wharf",
    "sg:city":"Monterey",
    "sg:classifiers":[
        {
            "category":"Restaurant",
            "type":"Food & Drink"
        }
    ],
    "sg:phone":"+1 831 372 7562",
    "sg:postcode":"93940",
    "sg:province":"CA",
    "sg:tags":[
        "seafood",
        "steak"
    ],
    "wof:name":"Rappas Restaurant",
    "wof:placetype":"venue"
},
  "geometry": {"coordinates":[-121.892675,36.604412],"type":"Point"}
}