{
  "type": "Feature",
  "properties": {
    "addr:full":"1419 W F St Oakdale CA 95361",
    "addr:housenumber":"1419",
    "addr:postcode":"95361",
    "addr:street":"W F St",
    "iso:country":"US",
    "sg:address":"1419 W F St",
    "sg:city":"Oakdale",
    "sg:classifiers":[
        {
            "category":"Health Services",
            "subcategory":"Doctor",
            "type":"Services"
        }
    ],
    "sg:phone":"+1 209 847 0309",
    "sg:postcode":"95361",
    "sg:province":"CA",
    "sg:tags":[
        "dentist"
    ],
    "wof:name":"Albertoni & Corso Dentistry",
    "wof:placetype":"venue"
},
  "geometry": {"coordinates":[-120.863229,37.759805],"type":"Point"}
}