{
  "type": "Feature",
  "properties": {
    "addr:full":"29350 Poppy Meadow St Santa Clarita CA 91387",
    "addr:housenumber":"29350",
    "addr:postcode":"91387",
    "addr:street":"Poppy Meadow St",
    "iso:country":"US",
    "sg:address":"29350 Poppy Meadow St",
    "sg:city":"Santa Clarita",
    "sg:classifiers":[
        {
            "category":"Building & Trades",
            "subcategory":"Pest Control",
            "type":"Services"
        }
    ],
    "sg:phone":"+1 661 250 2533",
    "sg:postcode":"91387",
    "sg:province":"CA",
    "wof:name":"Newhall Valencia Exterminating Co",
    "wof:placetype":"venue"
},
  "geometry": {"coordinates":[-118.398325,34.439127],"type":"Point"}
}