{
  "type": "Feature",
  "properties": {
    "addr:full":"200 Main St Redwood City CA 94063",
    "addr:housenumber":"200",
    "addr:postcode":"94063",
    "addr:street":"Main St",
    "iso:country":"US",
    "sg:address":"200 Main St",
    "sg:city":"Redwood City",
    "sg:classifiers":[
        {
            "category":"Professional",
            "subcategory":"Lawyer & Legal Services",
            "type":"Services"
        }
    ],
    "sg:phone":"+1 650 599 9565",
    "sg:postcode":"94063",
    "sg:province":"CA",
    "sg:tags":[
        "attorney"
    ],
    "wof:name":"Legal Answer",
    "wof:placetype":"venue"
},
  "geometry": {"coordinates":[-122.228432,37.49281],"type":"Point"}
}