{
  "type": "Feature",
  "properties": {
    "iso:country":"US",
    "sg:address":"414 Simpson St",
    "sg:city":"Arvin",
    "sg:classifiers":[
        {
            "category":"Personal",
            "type":"Services"
        }
    ],
    "sg:phone":"+1 661 303 2955",
    "sg:postcode":"93203",
    "sg:province":"CA",
    "sg:tags":[
        "towing"
    ],
    "wof:name":"Gonzalez Towing",
    "wof:placetype":"venue"
},
  "geometry": {"coordinates":[-118.82924800000001,35.214128],"type":"Point"}
}