{
  "type": "Feature",
  "properties": {
    "iso:country":"US",
    "sg:address":"100 Civic Dr",
    "sg:city":"Hercules",
    "sg:classifiers":[
        {
            "category":"Real Estate",
            "subcategory":"Real Estate Operator",
            "type":"Services"
        }
    ],
    "sg:phone":"+1 510 799 6000",
    "sg:postcode":"94547",
    "sg:province":"CA",
    "sg:tags":[
        "apartment"
    ],
    "wof:name":"Arbors",
    "wof:placetype":"venue"
},
  "geometry": {"coordinates":[-122.26547100000001,38.00989],"type":"Point"}
}