{
  "type": "Feature",
  "properties": {
    "iso:country":"US",
    "sg:address":"11800 Enterprise Dr",
    "sg:city":"Auburn",
    "sg:classifiers":[
        {
            "category":"Sports & Exercise",
            "subcategory":"Gym",
            "type":"Entertainment"
        }
    ],
    "sg:phone":"+1 530 823 7458",
    "sg:postcode":"95603",
    "sg:province":"CA",
    "sg:tags":[
        "club",
        "health",
        "studio",
        "gymnasium"
    ],
    "sg:website":"www.pacfit.com",
    "wof:name":"Pacific Fitness Ctr",
    "wof:placetype":"venue"
},
  "geometry": {"coordinates":[-121.083946,38.907339],"type":"Point"}
}