{
  "type": "Feature",
  "properties": {
    "addr:full":"201 Ravenswood Ave Menlo Park CA 94025",
    "addr:housenumber":"201",
    "addr:postcode":"94025",
    "addr:street":"Ravenswood Ave",
    "iso:country":"US",
    "sg:address":"201 Ravenswood Ave",
    "sg:city":"Menlo Park",
    "sg:classifiers":[
        {
            "category":"Organizations",
            "subcategory":"Religious Organization",
            "type":"Services"
        }
    ],
    "sg:phone":"+1 650 323 2872",
    "sg:postcode":"94025",
    "sg:province":"CA",
    "sg:tags":[
        "church"
    ],
    "wof:name":"Church Of Christ Scientist",
    "wof:placetype":"venue"
},
  "geometry": {"coordinates":[-122.178461,37.456393],"type":"Point"}
}