{
  "type": "Feature",
  "properties": {
    "iso:country":"US",
    "sg:address":"42872 N Fork Dr",
    "sg:city":"Three Rivers",
    "sg:classifiers":[
        {
            "category":"Building & Trades",
            "subcategory":"Construction",
            "type":"Services"
        }
    ],
    "sg:phone":"+1 559 561 3550",
    "sg:postcode":"93271",
    "sg:province":"CA",
    "sg:tags":[
        "general",
        "contractor"
    ],
    "wof:name":"Speedy Gonzalez Construction",
    "wof:placetype":"venue"
},
  "geometry": {"coordinates":[-118.913337,36.457352],"type":"Point"}
}