{
  "type": "Feature",
  "properties": {
    "iso:country":"US",
    "sg:address":"8350 Wilshire Blvd",
    "sg:city":"Beverly Hills",
    "sg:classifiers":[
        {
            "category":"Professional",
            "subcategory":"Business Services",
            "type":"Services"
        }
    ],
    "sg:phone":"+1 323 658 4466",
    "sg:postcode":"90211",
    "sg:province":"CA",
    "sg:tags":[
        "broker",
        "merchandise"
    ],
    "sg:website":"www.towerasset.com",
    "wof:name":"Tower Assets Management",
    "wof:placetype":"venue"
},
  "geometry": {"coordinates":[-118.373928,34.064548],"type":"Point"}
}