{
  "type": "Feature",
  "properties": {
    "addr:full":"29296 Uller Ln Nuevo CA 92567",
    "addr:postcode":"29296;92567",
    "addr:street":"Uller Ln",
    "iso:country":"US",
    "sg:address":"29296 Uller Ln",
    "sg:city":"Nuevo",
    "sg:classifiers":[
        {
            "category":"Building & Trades",
            "subcategory":"Landscaping Services",
            "type":"Services"
        }
    ],
    "sg:phone":"+1 951 970 9475",
    "sg:postcode":"92567",
    "sg:province":"CA",
    "sg:tags":[
        "lawn",
        "maintenance"
    ],
    "wof:name":"Lawn Maintenance Etc",
    "wof:placetype":"venue"
},
  "geometry": {"coordinates":[-117.15121600000001,33.795765],"type":"Point"}
}