{
  "type": "Feature",
  "properties": {
    "iso:country":"US",
    "sg:address":"937 Enterprise Dr",
    "sg:city":"Sacramento",
    "sg:classifiers":[
        {
            "category":"Building & Trades",
            "subcategory":"Construction",
            "type":"Services"
        }
    ],
    "sg:phone":"+1 800 549 1151",
    "sg:postcode":"95825",
    "sg:province":"CA",
    "sg:tags":[
        "roofing",
        "contractor"
    ],
    "wof:name":"Eberling Paula",
    "wof:placetype":"venue"
},
  "geometry": {"coordinates":[-121.41703699999999,38.582855],"type":"Point"}
}