{
  "type": "Feature",
  "properties": {
    "iso:country":"US",
    "sg:address":"1500 W 96th St",
    "sg:city":"Los Angeles",
    "sg:classifiers":[
        {
            "category":"Health Services",
            "subcategory":"Health Practitioner",
            "type":"Services"
        }
    ],
    "sg:phone":"+1 323 779 3056",
    "sg:postcode":"90047",
    "sg:province":"CA",
    "sg:tags":[
        "nutritionist"
    ],
    "wof:name":"Ann Battle",
    "wof:placetype":"venue"
},
  "geometry": {"coordinates":[-118.304644,33.948664],"type":"Point"}
}