{
  "type": "Feature",
  "properties": {
    "iso:country":"US",
    "sg:address":"2401 W Whittier Blvd",
    "sg:city":"La Habra",
    "sg:classifiers":[
        {
            "category":"Personal",
            "subcategory":"Beauty Salon",
            "type":"Services"
        }
    ],
    "sg:phone":"+1 562 697 2897",
    "sg:postcode":"90631",
    "sg:province":"CA",
    "wof:name":"Tiffany's Beauty Salon",
    "wof:placetype":"venue"
},
  "geometry": {"coordinates":[-117.974334,33.939899],"type":"Point"}
}