{
  "type": "Feature",
  "properties": {
    "acgov:api":"0.0",
    "acgov:type":"Small Schools",
    "addr:full":"285 17TH St Oakland CA",
    "wof:categories":[
        "education_and_religion:education=school"
    ],
    "wof:name":"Oasis High",
    "wof:placetype":"venue"
},
  "geometry": {"coordinates":[-122.26574115567064,37.80506348011202],"type":"Point"}
}