{
  "type": "Feature",
  "properties": {
    "addr:full":"8 Gordon St Sausalito CA 94965",
    "addr:housenumber":"8",
    "addr:postcode":"94965",
    "addr:street":"Gordon St",
    "iso:country":"US",
    "sg:address":"8 Gordon St",
    "sg:city":"Sausalito",
    "sg:classifiers":[
        {
            "category":"Shopping",
            "subcategory":"Shoes",
            "type":"Retail Goods"
        }
    ],
    "sg:phone":"+1 415 331 0355",
    "sg:postcode":"94965",
    "sg:province":"CA",
    "wof:name":"Walk Well",
    "wof:placetype":"venue"
},
  "geometry": {"coordinates":[-122.497544,37.860007],"type":"Point"}
}