{
  "type": "Feature",
  "properties": {
    "addr:full":"154 N Arroyo Seco St Ione CA 95640",
    "addr:housenumber":"154",
    "addr:postcode":"ca 95640",
    "addr:street":"N Arroyo Seco St",
    "iso:country":"US",
    "sg:address":"154 N Arroyo Seco St",
    "sg:city":"Ione",
    "sg:classifiers":[
        {
            "category":"Real Estate",
            "subcategory":"Real Estate Operator",
            "type":"Services"
        }
    ],
    "sg:phone":"+1 209 274 2684",
    "sg:postcode":"95640",
    "sg:province":"CA",
    "sg:tags":[
        "apartment"
    ],
    "wof:name":"Joses Place",
    "wof:placetype":"venue"
},
  "geometry": {"coordinates":[-120.932303,38.354915],"type":"Point"}
}