{
  "type": "Feature",
  "properties": {
    "addr:full":"41500 Monterey Ave Palm Desert CA 92260",
    "addr:housenumber":"41500",
    "addr:postcode":"ca 92260",
    "addr:street":"Monterey Ave",
    "iso:country":"US",
    "sg:address":"41500 Monterey Ave",
    "sg:city":"Palm Desert",
    "sg:classifiers":[
        {
            "category":"Real Estate",
            "subcategory":"Real Estate Agent",
            "type":"Services"
        }
    ],
    "sg:phone":"+1 760 340 2665",
    "sg:postcode":"92260",
    "sg:province":"CA",
    "wof:name":"Becker & Becker Realtors",
    "wof:placetype":"venue"
},
  "geometry": {"coordinates":[-116.391344,33.752455],"type":"Point"}
}