{
  "type": "Feature",
  "properties": {
    "addr:full":"2332 N Batavia Orange CA 92865",
    "addr:housenumber":"2332",
    "addr:postcode":"92865",
    "addr:street":"N Batavia",
    "iso:country":"US",
    "sg:address":"2332 N Batavia",
    "sg:city":"Orange",
    "sg:classifiers":[
        {
            "category":"Building & Trades",
            "subcategory":"Plumbing",
            "type":"Services"
        }
    ],
    "sg:phone":"+1 714 998 9022",
    "sg:postcode":"92865",
    "sg:province":"CA",
    "sg:website":"scottenglishplumbing.net",
    "wof:name":"Scott English Plumbing Inc.",
    "wof:placetype":"venue"
},
  "geometry": {"coordinates":[-117.862092,33.827142],"type":"Point"}
}