{
  "type": "Feature",
  "properties": {
    "addr:full":"19939 Valley Blvd Walnut CA 91789",
    "addr:housenumber":"19939",
    "addr:postcode":"91789",
    "addr:street":"Valley Blvd",
    "iso:country":"US",
    "sg:address":"19939 Valley Blvd",
    "sg:city":"Walnut",
    "sg:classifiers":[
        {
            "category":"Retail",
            "subcategory":"Repair Shop",
            "type":"Services"
        }
    ],
    "sg:phone":"+1 909 595 8329",
    "sg:postcode":"91789",
    "sg:province":"CA",
    "sg:tags":[
        "upholsterer"
    ],
    "wof:name":"Gomez Upholstery",
    "wof:placetype":"venue"
},
  "geometry": {"coordinates":[-117.86812,34.00459],"type":"Point"}
}