{
  "type": "Feature",
  "properties": {
    "addr:full":"1000 Taraval St San Francisco CA 94116",
    "addr:housenumber":"1000",
    "addr:postcode":"94116",
    "addr:street":"Taraval St",
    "iso:country":"US",
    "sg:address":"1000 Taraval St",
    "sg:city":"San Francisco",
    "sg:classifiers":[
        {
            "category":"Banks & Credit Unions",
            "subcategory":"Bank",
            "type":"Services"
        }
    ],
    "sg:phone":"+1 415 661 7070",
    "sg:postcode":"94116",
    "sg:province":"CA",
    "sg:website":"www.firstbanks.com",
    "wof:name":"First Banks",
    "wof:placetype":"venue"
},
  "geometry": {"coordinates":[-122.477046,37.743238],"type":"Point"}
}