{
  "type": "Feature",
  "properties": {
    "iso:country":"US",
    "sg:address":"767 Industrial Rd",
    "sg:city":"San Carlos",
    "sg:classifiers":[
        {
            "category":"Education",
            "subcategory":"Dance Studio",
            "type":"Public Place"
        }
    ],
    "sg:phone":"+1 650 598 0644",
    "sg:postcode":"94070",
    "sg:province":"CA",
    "sg:tags":[
        "instruction",
        "dancing"
    ],
    "wof:name":"Dance Mode Studio",
    "wof:placetype":"venue"
},
  "geometry": {"coordinates":[-122.253157,37.508724],"type":"Point"}
}