{
  "type": "Feature",
  "properties": {
    "addr:full":"27450 Ynez Rd Temecula CA 92591",
    "addr:housenumber":"27450",
    "addr:postcode":"92591",
    "addr:street":"Ynez Rd",
    "iso:country":"US",
    "sg:address":"27450 Ynez Rd",
    "sg:city":"Temecula",
    "sg:classifiers":[
        {
            "category":"Banks & Credit Unions",
            "subcategory":"Investment Brokerage",
            "type":"Services"
        }
    ],
    "sg:phone":"+1 951 693 2520",
    "sg:postcode":"92591",
    "sg:province":"CA",
    "sg:tags":[
        "advisory",
        "financial"
    ],
    "wof:name":"Liberty Financial Solution",
    "wof:placetype":"venue"
},
  "geometry": {"coordinates":[-117.150181,33.507002],"type":"Point"}
}