{
  "type": "Feature",
  "properties": {
    "iso:country":"US",
    "sg:address":"5302 N Fresno St",
    "sg:city":"Fresno",
    "sg:classifiers":[
        {
            "category":"Personal",
            "subcategory":"Beauty Salon",
            "type":"Services"
        }
    ],
    "sg:phone":"+1 559 222 1920",
    "sg:postcode":"93710",
    "sg:province":"CA",
    "wof:name":"Hair Styles By Dora Gonzalez",
    "wof:placetype":"venue"
},
  "geometry": {"coordinates":[-119.781256,36.815702],"type":"Point"}
}