{
  "type": "Feature",
  "properties": {
    "addr:full":"2257 Highland Vista Dr Arcadia CA 91006",
    "addr:housenumber":"2257",
    "addr:postcode":"91006",
    "addr:street":"Highland Vista Dr",
    "iso:country":"US",
    "sg:address":"2257 Highland Vista Dr",
    "sg:city":"Arcadia",
    "sg:classifiers":[
        {
            "category":"Health Services",
            "subcategory":"Doctor",
            "type":"Services"
        }
    ],
    "sg:phone":"+1 626 355 7623",
    "sg:postcode":"91006",
    "sg:province":"CA",
    "sg:tags":[
        "medical"
    ],
    "wof:name":"Susan C Choa MD Inc",
    "wof:placetype":"venue"
},
  "geometry": {"coordinates":[-118.020526,34.177226],"type":"Point"}
}