{
  "type": "Feature",
  "properties": {
    "iso:country":"US",
    "sg:address":"56582 US Hwy 101",
    "sg:city":"Fortuna",
    "sg:classifiers":[
        {
            "category":"Retail",
            "subcategory":"Repair Shop",
            "type":"Services"
        }
    ],
    "sg:phone":"+1 707 725 1887",
    "sg:postcode":"95540",
    "sg:province":"CA",
    "sg:tags":[
        "appliance",
        "household",
        "electrical"
    ],
    "wof:name":"R Ds Repair Service",
    "wof:placetype":"venue"
},
  "geometry": {"coordinates":[-124.12554,40.512084],"type":"Point"}
}