{
  "type": "Feature",
  "properties": {
    "iso:country":"US",
    "sg:address":"363 E McKinley Ave",
    "sg:city":"Sunnyvale",
    "sg:classifiers":[
        {
            "category":"Professional",
            "subcategory":"Business Services",
            "type":"Services"
        }
    ],
    "sg:phone":"+1 408 732 1262",
    "sg:postcode":"94086",
    "sg:province":"CA",
    "sg:tags":[
        "drafting"
    ],
    "wof:name":"Parametric Support Svc",
    "wof:placetype":"venue"
},
  "geometry": {"coordinates":[-122.02700900000001,37.373481],"type":"Point"}
}