{
  "type": "Feature",
  "properties": {
    "addr:full":"363 E McKinley Ave Sunnyvale CA 94086",
    "addr:housenumber":"363",
    "addr:postcode":"94086",
    "addr:street":"E Mckinley Ave",
    "iso:country":"US",
    "sg:address":"363 E McKinley Ave",
    "sg:city":"Sunnyvale",
    "sg:classifiers":[
        {
            "category":"Professional",
            "subcategory":"Business Services",
            "type":"Services"
        }
    ],
    "sg:phone":"+1 408 732 1262",
    "sg:postcode":"94086",
    "sg:province":"CA",
    "sg:tags":[
        "drafting"
    ],
    "wof:name":"Parametric Support Svc",
    "wof:placetype":"venue"
},
  "geometry": {"coordinates":[-122.02700900000001,37.373481],"type":"Point"}
}