{
  "type": "Feature",
  "properties": {
    "addr:full":"324 Avila St San Francisco CA 94123",
    "addr:housenumber":"324",
    "addr:postcode":"94123",
    "addr:street":"Avila St",
    "iso:country":"US",
    "sg:address":"324 Avila St",
    "sg:city":"San Francisco",
    "sg:classifiers":[
        {
            "category":"Health Services",
            "subcategory":"Doctor",
            "type":"Services"
        }
    ],
    "sg:phone":"+1 415 567 3535",
    "sg:postcode":"94123",
    "sg:province":"CA",
    "sg:tags":[
        "physician",
        "surgeon"
    ],
    "wof:name":"Sally Kaufman MD",
    "wof:placetype":"venue"
},
  "geometry": {"coordinates":[-122.441035,37.80414],"type":"Point"}
}