{
  "type": "Feature",
  "properties": {
    "addr:full":"13754 Roscoe Blvd Panorama City CA 91402",
    "addr:housenumber":"13754",
    "addr:postcode":"91402",
    "addr:street":"Roscoe Blvd",
    "iso:country":"US",
    "sg:address":"13754 Roscoe Blvd",
    "sg:city":"Panorama City",
    "sg:classifiers":[
        {
            "category":"Utilities",
            "subcategory":"Mobile Phone",
            "type":"Services"
        }
    ],
    "sg:phone":"+1 818 895 3900",
    "sg:postcode":"91402",
    "sg:province":"CA",
    "sg:tags":[
        "telephone",
        "cellular"
    ],
    "wof:name":"Panorama Wireless",
    "wof:placetype":"venue"
},
  "geometry": {"coordinates":[-118.434029,34.221581],"type":"Point"}
}