{
  "type": "Feature",
  "properties": {
    "addr:full":"23839 Connecticut St Hayward CA 94545",
    "addr:housenumber":"23839",
    "addr:postcode":"94545",
    "addr:street":"Connecticut St",
    "iso:country":"US",
    "sg:address":"23839 Connecticut St",
    "sg:city":"Hayward",
    "sg:classifiers":[
        {
            "category":"Professional",
            "subcategory":"Advertising",
            "type":"Services"
        }
    ],
    "sg:phone":"+1 510 265 1526",
    "sg:postcode":"94545",
    "sg:province":"CA",
    "sg:tags":[
        "counselor"
    ],
    "wof:name":"Arsh Group Inc",
    "wof:placetype":"venue"
},
  "geometry": {"coordinates":[-122.129498,37.640143],"type":"Point"}
}