{
  "type": "Feature",
  "properties": {
    "iso:country":"US",
    "sg:address":"2915 Warwick Ave",
    "sg:city":"Los Angeles",
    "sg:classifiers":[
        {
            "category":"Professional",
            "type":"Services"
        }
    ],
    "sg:phone":"+1 323 352 8839",
    "sg:postcode":"90032",
    "sg:province":"CA",
    "sg:tags":[
        "caterer"
    ],
    "sg:website":"www.twoguyscatering.org",
    "wof:name":"Two Guys Catering",
    "wof:placetype":"venue"
},
  "geometry": {"coordinates":[-118.166654,34.078778],"type":"Point"}
}