{
  "type": "Feature",
  "properties": {
    "iso:country":"US",
    "sg:address":"2220 E Carson St",
    "sg:city":"Long Beach",
    "sg:classifiers":[
        {
            "category":"Manufacturing",
            "subcategory":"Aerospace",
            "type":"Manufacturing & Wholesale Goods"
        }
    ],
    "sg:phone":"+1 310 522 2809",
    "sg:postcode":"90810",
    "sg:province":"CA",
    "sg:tags":[
        "aircraft",
        "receiving",
        "inventory"
    ],
    "wof:name":"Boeing",
    "wof:placetype":"venue"
},
  "geometry": {"coordinates":[-118.237663,33.831652],"type":"Point"}
}