{
  "type": "Feature",
  "properties": {
    "iso:country":"US",
    "sg:address":"3183 Mecartney Rd",
    "sg:city":"Alameda",
    "sg:classifiers":[
        {
            "category":"Place Of Worship",
            "subcategory":"Synagogue",
            "type":"Public Place"
        }
    ],
    "sg:phone":"+1 510 522 9355",
    "sg:postcode":"94502",
    "sg:province":"CA",
    "sg:website":"www.templeisraelalameda.org",
    "wof:name":"Temple Israel",
    "wof:placetype":"venue"
},
  "geometry": {"coordinates":[-122.24299600000001,37.7365],"type":"Point"}
}