{
  "type": "Feature",
  "properties": {
    "addr:full":"322 N Euclid St Fullerton CA 92832",
    "addr:housenumber":"322",
    "addr:postcode":"92832",
    "addr:street":"N Euclid St",
    "iso:country":"US",
    "sg:address":"322 N Euclid St",
    "sg:city":"Fullerton",
    "sg:classifiers":[
        {
            "category":"Retail",
            "subcategory":"Laundry & Dry Cleaning",
            "type":"Services"
        }
    ],
    "sg:phone":"+1 714 680 0820",
    "sg:postcode":"92832",
    "sg:province":"CA",
    "wof:name":"Dryclean Express",
    "wof:placetype":"venue"
},
  "geometry": {"coordinates":[-117.942001,33.873402],"type":"Point"}
}