{
  "type": "Feature",
  "properties": {
    "iso:country":"US",
    "sg:address":"7330 Peacock Way",
    "sg:city":"Sacramento",
    "sg:classifiers":[
        {
            "category":"Building & Trades",
            "subcategory":"Landscaping Services",
            "type":"Services"
        }
    ],
    "sg:phone":"+1 916 381 8803",
    "sg:postcode":"95820",
    "sg:province":"CA",
    "sg:tags":[
        "landscape"
    ],
    "wof:name":"Vista Landscapes",
    "wof:placetype":"venue"
},
  "geometry": {"coordinates":[-121.416925,38.528295],"type":"Point"}
}