{
  "type": "Feature",
  "properties": {
    "iso:country":"US",
    "sg:address":"1424 4th Ave",
    "sg:city":"Santa Monica",
    "sg:classifiers":[
        {
            "category":"Communications",
            "subcategory":"Film & Video Production",
            "type":"Services"
        }
    ],
    "sg:phone":"+1 310 393 7123",
    "sg:postcode":"90401",
    "sg:province":"CA",
    "sg:tags":[
        "taping"
    ],
    "wof:name":"Always Moving Pictures",
    "wof:placetype":"venue"
},
  "geometry": {"coordinates":[-118.493965,34.015352],"type":"Point"}
}