{
  "type": "Feature",
  "properties": {
    "addr:full":"19352 Donkey Hill Rd Hidden Valley Lk CA 95467",
    "addr:postcode":"19352;95467",
    "addr:street":"Donkey Hill Rd",
    "iso:country":"US",
    "sg:address":"19352 Donkey Hill Rd",
    "sg:city":"Hidden Valley Lk",
    "sg:classifiers":[
        {
            "category":"Insurance",
            "subcategory":"Insurance Agent",
            "type":"Services"
        }
    ],
    "sg:phone":"+1 707 987 2650",
    "sg:postcode":"95467",
    "sg:province":"CA",
    "wof:name":"Hidden Valley Lake Insurance",
    "wof:placetype":"venue"
},
  "geometry": {"coordinates":[-122.55393599999999,38.796092],"type":"Point"}
}