{
  "type": "Feature",
  "properties": {
    "iso:country":"US",
    "sg:address":"2720 State Hwy 32",
    "sg:city":"Chico",
    "sg:classifiers":[
        {
            "category":"Farming",
            "subcategory":"Nursery",
            "type":"Manufacturing & Wholesale Goods"
        },
        {
            "category":"Home & Garden",
            "subcategory":"Garden Supply",
            "type":"Retail Goods"
        }
    ],
    "sg:phone":"+1 530 893 4769",
    "sg:postcode":"95973",
    "sg:province":"CA",
    "sg:tags":[
        "nurseryman"
    ],
    "wof:name":"Growing Grounds Nursery",
    "wof:placetype":"venue"
},
  "geometry": {"coordinates":[-121.890801,39.745279],"type":"Point"}
}