{
  "type": "Feature",
  "properties": {
    "addr:full":"190 S Palm Canyon Dr Palm Springs CA 92262",
    "addr:housenumber":"190",
    "addr:postcode":"92262",
    "addr:street":"S Palm Canyon Dr",
    "iso:country":"US",
    "sg:address":"190 S Palm Canyon Dr",
    "sg:city":"Palm Springs",
    "sg:classifiers":[
        {
            "category":"Shopping",
            "subcategory":"Jewelry",
            "type":"Retail Goods"
        }
    ],
    "sg:phone":"+1 760 320 6545",
    "sg:postcode":"92262",
    "sg:province":"CA",
    "wof:name":"Madison Jewelers",
    "wof:placetype":"venue"
},
  "geometry": {"coordinates":[-116.546997,33.821701],"type":"Point"}
}