{
  "type": "Feature",
  "properties": {
    "iso:country":"US",
    "sg:address":"567 Lone Oak Dr",
    "sg:city":"Thousand Oaks",
    "sg:classifiers":[
        {
            "category":"Home & Garden",
            "subcategory":"Building Materials",
            "type":"Retail Goods"
        }
    ],
    "sg:phone":"+1 805 495 7976",
    "sg:postcode":"91362",
    "sg:province":"CA",
    "sg:tags":[
        "glass",
        "window",
        "plate"
    ],
    "wof:name":"Preferred Discount Auto Glass",
    "wof:placetype":"venue"
},
  "geometry": {"coordinates":[-118.845463,34.183903],"type":"Point"}
}