{
  "type": "Feature",
  "properties": {
    "iso:country":"US",
    "sg:address":"2907 The Villages Parkway",
    "sg:city":"San Jose",
    "sg:classifiers":[
        {
            "category":"Food & Beverages",
            "subcategory":"Groceries & Convenience Stores",
            "type":"Retail Goods"
        }
    ],
    "sg:phone":"+1 408 274 5858",
    "sg:postcode":"95135",
    "sg:province":"CA",
    "wof:name":"Bonfare Market",
    "wof:placetype":"venue"
},
  "geometry": {"coordinates":[-121.76028700000001,37.290952],"type":"Point"}
}