{
  "type": "Feature",
  "properties": {
    "addr:full":"1456 E Philadelphia St Ontario CA 91761",
    "addr:housenumber":"1456 e",
    "addr:postcode":"91761",
    "addr:street":"Philadelphia St",
    "iso:country":"US",
    "sg:address":"1456 E Philadelphia St",
    "sg:city":"Ontario",
    "sg:classifiers":[
        {
            "category":"Farming",
            "subcategory":"Farm",
            "type":"Manufacturing & Wholesale Goods"
        }
    ],
    "sg:phone":"+1 909 930 6461",
    "sg:postcode":"91761",
    "sg:province":"CA",
    "wof:name":"Glenn Ranch",
    "wof:placetype":"venue"
},
  "geometry": {"coordinates":[-117.62369,34.033999],"type":"Point"}
}