{
  "type": "Feature",
  "properties": {
    "iso:country":"US",
    "sg:address":"3370 Perlita Ave",
    "sg:city":"Los Angeles",
    "sg:classifiers":[
        {
            "category":"Social Services",
            "type":"Services"
        }
    ],
    "sg:phone":"+1 323 664 6847",
    "sg:postcode":"90039",
    "sg:province":"CA",
    "sg:tags":[
        "organization",
        "welfare"
    ],
    "wof:name":"San Fernando Valley Interfaith",
    "wof:placetype":"venue"
},
  "geometry": {"coordinates":[-118.25535,34.116175],"type":"Point"}
}