{
  "type": "Feature",
  "properties": {
    "addr:full":"12459 Kokomo Cir Victorville CA 92392",
    "addr:postcode":"12459;92392",
    "addr:street":"Cir",
    "iso:country":"US",
    "sg:address":"12459 Kokomo Cir",
    "sg:city":"Victorville",
    "sg:classifiers":[
        {
            "category":"Shopping",
            "subcategory":"Bicycles & Sporting Goods",
            "type":"Retail Goods"
        }
    ],
    "sg:phone":"+1 760 244 8271",
    "sg:postcode":"92392",
    "sg:province":"CA",
    "wof:name":"Pomona Air Guns Manufacturing",
    "wof:placetype":"venue"
},
  "geometry": {"coordinates":[-117.391774,34.474645],"type":"Point"}
}