{
  "type": "Feature",
  "properties": {
    "addr:full":"38 Brannan St Calistoga CA 94515",
    "addr:housenumber":"38",
    "addr:postcode":"94515",
    "addr:street":"Brannan St",
    "iso:country":"US",
    "sg:address":"38 Brannan St",
    "sg:city":"Calistoga",
    "sg:classifiers":[
        {
            "category":"Building & Trades",
            "subcategory":"Construction",
            "type":"Services"
        }
    ],
    "sg:phone":"+1 707 321 6003",
    "sg:postcode":"94515",
    "sg:province":"CA",
    "sg:tags":[
        "general",
        "contractor"
    ],
    "wof:name":"Montanez Construction",
    "wof:placetype":"venue"
},
  "geometry": {"coordinates":[-122.576126,38.583618],"type":"Point"}
}