{
  "type": "Feature",
  "properties": {
    "iso:country":"US",
    "sg:address":"11232 Vanowen St",
    "sg:city":"North Hollywood",
    "sg:classifiers":[
        {
            "category":"Retail",
            "subcategory":"Auto Repair",
            "type":"Services"
        }
    ],
    "sg:phone":"+1 818 505 1321",
    "sg:postcode":"91605",
    "sg:province":"CA",
    "wof:name":"J P Collision & Paint",
    "wof:placetype":"venue"
},
  "geometry": {"coordinates":[-118.375743,34.193802],"type":"Point"}
}