{
  "type": "Feature",
  "properties": {
    "addr:full":"100 S. Robertson Boulevard Los Angeles CA 90048",
    "addr:housenumber":"100",
    "addr:postcode":"90048",
    "addr:street":"S. Robertson Boulevard",
    "iso:country":"US",
    "sg:address":"100 S. Robertson Boulevard",
    "sg:city":"Los Angeles",
    "sg:classifiers":[
        {
            "category":"Shopping",
            "subcategory":"Clothing, Apparel, & Fashions",
            "type":"Retail Goods"
        }
    ],
    "sg:phone":"+1 310 385 9540",
    "sg:postcode":"90048",
    "sg:province":"CA",
    "sg:website":"www.7forallmankind.com/",
    "wof:name":"7 for All Mankind",
    "wof:placetype":"venue"
},
  "geometry": {"coordinates":[-118.383448,34.075116],"type":"Point"}
}