{
  "type": "Feature",
  "properties": {
    "iso:country":"US",
    "sg:address":"3830 Prospect Ave",
    "sg:city":"Yorba Linda",
    "sg:classifiers":[
        {
            "category":"Manufacturing",
            "subcategory":"Metals",
            "type":"Manufacturing & Wholesale Goods"
        }
    ],
    "sg:phone":"+1 714 572 4050",
    "sg:postcode":"92886",
    "sg:province":"CA",
    "sg:tags":[
        "equipment",
        "heating",
        "mfg"
    ],
    "wof:name":"Infrared Dynamics Inc",
    "wof:placetype":"venue"
},
  "geometry": {"coordinates":[-117.837459,33.903994],"type":"Point"}
}