{
  "type": "Feature",
  "properties": {
    "addr:full":"41 Main St Belvedere Tibrn CA 94920",
    "addr:housenumber":"41",
    "addr:postcode":"94920",
    "addr:street":"Main St",
    "iso:country":"US",
    "sg:address":"41 Main St",
    "sg:city":"Belvedere Tibrn",
    "sg:classifiers":[
        {
            "category":"Building & Trades",
            "subcategory":"Construction",
            "type":"Services"
        }
    ],
    "sg:phone":"+1 415 435 4967",
    "sg:postcode":"94920",
    "sg:province":"CA",
    "sg:tags":[
        "contractor"
    ],
    "wof:name":"Caceras Building",
    "wof:placetype":"venue"
},
  "geometry": {"coordinates":[-122.45635799999999,37.873184],"type":"Point"}
}