{
  "type": "Feature",
  "properties": {
    "iso:country":"US",
    "sg:address":"1006 Santee Street",
    "sg:city":"Los Angeles",
    "sg:classifiers":[
        {
            "category":"Shopping",
            "subcategory":"Clothing, Apparel, & Fashions",
            "type":"Retail Goods"
        }
    ],
    "sg:phone":"+1 213 746 2579",
    "sg:postcode":"90015",
    "sg:province":"CA",
    "sg:tags":[
        "clothing",
        "women's"
    ],
    "wof:name":"Bubijou",
    "wof:placetype":"venue"
},
  "geometry": {"coordinates":[-118.255047,34.038975],"type":"Point"}
}