{
  "type": "Feature",
  "properties": {
    "addr:full":"114 Liberty St Santa Cruz CA 95060",
    "addr:housenumber":"114",
    "addr:postcode":"95060",
    "addr:street":"Liberty St",
    "iso:country":"US",
    "sg:address":"114 Liberty St",
    "sg:city":"Santa Cruz",
    "sg:classifiers":[
        {
            "category":"Building & Trades",
            "subcategory":"Landscaping Services",
            "type":"Services"
        }
    ],
    "sg:phone":"+1 831 459 0656",
    "sg:postcode":"95060",
    "sg:province":"CA",
    "sg:tags":[
        "landscape",
        "contractor"
    ],
    "sg:website":"www.centralcoastwilds.com",
    "wof:name":"Central Coast Wilds",
    "wof:placetype":"venue"
},
  "geometry": {"coordinates":[-122.030798,36.955727],"type":"Point"}
}