{
  "type": "Feature",
  "properties": {
    "iso:country":"US",
    "sg:address":"8408 Juniper Ln",
    "sg:city":"Montague",
    "sg:classifiers":[
        {
            "category":"Manufacturing",
            "subcategory":"Buildings",
            "type":"Manufacturing & Wholesale Goods"
        },
        {
            "category":"Building & Trades",
            "subcategory":"Construction",
            "type":"Services"
        }
    ],
    "sg:phone":"+1 530 340 0413",
    "sg:postcode":"96064",
    "sg:province":"CA",
    "sg:tags":[
        "home",
        "builder",
        "contractor"
    ],
    "wof:name":"Quality Home Inspections",
    "wof:placetype":"venue"
},
  "geometry": {"coordinates":[-122.389692,41.616582],"type":"Point"}
}