{
  "type": "Feature",
  "properties": {
    "addr:full":"1735 Technology Dr San Jose CA 95110",
    "addr:housenumber":"1735",
    "addr:postcode":"95110",
    "addr:street":"Technology Dr",
    "iso:country":"US",
    "sg:address":"1735 Technology Dr",
    "sg:city":"San Jose",
    "sg:classifiers":[
        {
            "category":"Professional",
            "subcategory":"Management & Consulting",
            "type":"Services"
        }
    ],
    "sg:phone":"+1 408 436 6200",
    "sg:postcode":"95110",
    "sg:province":"CA",
    "sg:tags":[
        "consultant",
        "business"
    ],
    "wof:name":"Drake Beam Morin Inc",
    "wof:placetype":"venue"
},
  "geometry": {"coordinates":[-121.918924,37.367837],"type":"Point"}
}