{
  "type": "Feature",
  "properties": {
    "iso:country":"US",
    "sg:address":"18114 Manhattan Pl",
    "sg:city":"Torrance",
    "sg:classifiers":[
        {
            "category":"Manufacturing",
            "subcategory":"Food",
            "type":"Manufacturing & Wholesale Goods"
        }
    ],
    "sg:phone":"+1 310 327 9854",
    "sg:postcode":"90504",
    "sg:province":"CA",
    "sg:tags":[
        "preparation",
        "catering"
    ],
    "wof:name":"Professional Culinary Intl LLC",
    "wof:placetype":"venue"
},
  "geometry": {"coordinates":[-118.310126,33.865731],"type":"Point"}
}