{
  "type": "Feature",
  "properties": {
    "addr:full":"2972 W Swain Rd Stockton CA 95219",
    "addr:housenumber":"2972",
    "addr:postcode":"95219",
    "addr:street":"W Swain Rd",
    "iso:country":"US",
    "sg:address":"2972 W Swain Rd",
    "sg:city":"Stockton",
    "sg:classifiers":[
        {
            "category":"Manufacturing",
            "subcategory":"Rubber & Plastics",
            "type":"Manufacturing & Wholesale Goods"
        }
    ],
    "sg:phone":"+1 209 298 4195",
    "sg:postcode":"95219",
    "sg:province":"CA",
    "sg:tags":[
        "product",
        "fabricated",
        "mfg"
    ],
    "wof:name":"Norcal Zodiac",
    "wof:placetype":"venue"
},
  "geometry": {"coordinates":[-121.350553,38.000068],"type":"Point"}
}