{
  "type": "Feature",
  "properties": {
    "addr:full":"20820 Avalon Blvd Gardena CA 90247",
    "addr:housenumber":"20820",
    "addr:postcode":"90247",
    "addr:street":"Avalon Blvd",
    "iso:country":"US",
    "sg:address":"20820 Avalon Blvd",
    "sg:city":"Gardena",
    "sg:classifiers":[
        {
            "category":"Shopping",
            "subcategory":"Mobile Phones",
            "type":"Retail Goods"
        }
    ],
    "sg:phone":"+1 310 329 9325",
    "sg:postcode":"90247",
    "sg:province":"CA",
    "wof:name":"Verizon Wireless",
    "wof:placetype":"venue"
},
  "geometry": {"coordinates":[-118.296997,33.8946],"type":"Point"}
}