{
  "type": "Feature",
  "properties": {
    "addr:full":"2133 Shaw Ave Clovis CA 93611",
    "addr:housenumber":"2133",
    "addr:postcode":"93611",
    "addr:street":"Shaw Ave",
    "iso:country":"US",
    "sg:address":"2133 Shaw Ave",
    "sg:city":"Clovis",
    "sg:classifiers":[
        {
            "category":"Shopping",
            "subcategory":"Bicycles & Sporting Goods",
            "type":"Retail Goods"
        }
    ],
    "sg:phone":"+1 559 323 8693",
    "sg:postcode":"93611",
    "sg:province":"CA",
    "wof:name":"All Pro Hockey & Sports",
    "wof:placetype":"venue"
},
  "geometry": {"coordinates":[-119.673892,36.808628],"type":"Point"}
}