{
  "type": "Feature",
  "properties": {
    "addr:full":"1807 W 5th St Oxnard CA 93030",
    "addr:housenumber":"1807",
    "addr:postcode":"93030",
    "addr:street":"W 5Th St",
    "iso:country":"US",
    "sg:address":"1807 W 5th St",
    "sg:city":"Oxnard",
    "sg:classifiers":[
        {
            "category":"Wholesale",
            "subcategory":"Books, Periodicals, & Newspapers",
            "type":"Manufacturing & Wholesale Goods"
        }
    ],
    "sg:phone":"+1 805 985 2320",
    "sg:postcode":"93030",
    "sg:province":"CA",
    "sg:tags":[
        "publishers-periodical"
    ],
    "wof:name":"Aerospacenews Co",
    "wof:placetype":"venue"
},
  "geometry": {"coordinates":[-119.198812,34.19751],"type":"Point"}
}