{
  "type": "Feature",
  "properties": {
    "iso:country":"US",
    "sg:address":"202 W Valerio St",
    "sg:city":"Santa Barbara",
    "sg:classifiers":[
        {
            "category":"Organizations",
            "subcategory":"Political Organization",
            "type":"Services"
        }
    ],
    "sg:phone":"+1 805 569 3387",
    "sg:postcode":"93101",
    "sg:province":"CA",
    "wof:name":"Right To Life Leaque",
    "wof:placetype":"venue"
},
  "geometry": {"coordinates":[-119.71427199999999,34.42492],"type":"Point"}
}