{
  "type": "Feature",
  "properties": {
    "addr:full":"3822 W Elkhorn Blvd Sacramento CA 95835",
    "addr:housenumber":"3822",
    "addr:postcode":"95835",
    "addr:street":"W Elkhorn Blvd",
    "iso:country":"US",
    "sg:address":"3822 W Elkhorn Blvd",
    "sg:city":"Sacramento",
    "sg:classifiers":[
        {
            "category":"Retail",
            "subcategory":"Animal Services",
            "type":"Services"
        }
    ],
    "sg:phone":"+1 916 487 9797",
    "sg:postcode":"95835",
    "sg:province":"CA",
    "wof:name":"Two Jakes Park",
    "wof:placetype":"venue"
},
  "geometry": {"coordinates":[-121.54178899999999,38.685511],"type":"Point"}
}