{
  "type": "Feature",
  "properties": {
    "addr:full":"770 Mason St Vacaville CA 95688",
    "addr:housenumber":"770",
    "addr:postcode":"95688",
    "addr:street":"Mason St",
    "iso:country":"US",
    "sg:address":"770 Mason St",
    "sg:city":"Vacaville",
    "sg:classifiers":[
        {
            "category":"Manufacturing",
            "subcategory":"Food",
            "type":"Manufacturing & Wholesale Goods"
        }
    ],
    "sg:phone":"+1 800 639 9769",
    "sg:postcode":"95688",
    "sg:province":"CA",
    "sg:tags":[
        "std",
        "testing"
    ],
    "sg:website":"http://www.localstdtesting.com/11",
    "wof:name":"Aar Local Hiv / Std Testing",
    "wof:placetype":"venue"
},
  "geometry": {"coordinates":[-121.984072,38.355069],"type":"Point"}
}