{
  "type": "Feature",
  "properties": {
    "addr:full":"896 N Raymond Ave Pasadena CA 91103",
    "addr:housenumber":"896",
    "addr:postcode":"91103",
    "addr:street":"N Raymond Ave",
    "iso:country":"US",
    "sg:address":"896 N Raymond Ave",
    "sg:city":"Pasadena",
    "sg:classifiers":[
        {
            "category":"Social Services",
            "subcategory":"Child Care",
            "type":"Services"
        }
    ],
    "sg:phone":"+1 626 356 3795",
    "sg:postcode":"91103",
    "sg:province":"CA",
    "wof:name":"Sanford & Kids Family Day Care",
    "wof:placetype":"venue"
},
  "geometry": {"coordinates":[-118.148944,34.159707],"type":"Point"}
}