{
  "type": "Feature",
  "properties": {
    "addr:full":"23805 Stuart Ranch Rd Malibu CA 90265",
    "addr:housenumber":"23805",
    "addr:postcode":"90265",
    "addr:street":"Stuart Ranch Rd",
    "iso:country":"US",
    "sg:address":"23805 Stuart Ranch Rd",
    "sg:city":"Malibu",
    "sg:classifiers":[
        {
            "category":"Health Services",
            "subcategory":"Doctor",
            "type":"Services"
        }
    ],
    "sg:phone":"+1 310 456 0333",
    "sg:postcode":"90265",
    "sg:province":"CA",
    "sg:tags":[
        "medicine",
        "physician",
        "practice",
        "surgeons",
        "family"
    ],
    "wof:name":"Gil L Solomon Md",
    "wof:placetype":"venue"
},
  "geometry": {"coordinates":[-118.692668,34.039485],"type":"Point"}
}