{
  "type": "Feature",
  "properties": {
    "addr:full":"1275 Central Blvd Brentwood CA 94513",
    "addr:housenumber":"1275",
    "addr:postcode":"ca 94513",
    "addr:street":"Central Blvd",
    "iso:country":"US",
    "sg:address":"1275 Central Blvd",
    "sg:city":"Brentwood",
    "sg:classifiers":[
        {
            "category":"Professional",
            "type":"Services"
        }
    ],
    "sg:phone":"+1 925 240 5576",
    "sg:postcode":"94513",
    "sg:province":"CA",
    "wof:name":"J Hargus",
    "wof:placetype":"venue"
},
  "geometry": {"coordinates":[-121.70370200000001,37.935266],"type":"Point"}
}