{
  "type": "Feature",
  "properties": {
    "iso:country":"US",
    "sg:address":"1501 W State St",
    "sg:city":"Ontario",
    "sg:classifiers":[
        {
            "category":"Wholesale",
            "subcategory":"Machinery & Supplies",
            "type":"Manufacturing & Wholesale Goods"
        }
    ],
    "sg:phone":"+1 909 983 4243",
    "sg:postcode":"91762",
    "sg:province":"CA",
    "sg:tags":[
        "equipment",
        "industrial"
    ],
    "wof:name":"Liberty Pallets",
    "wof:placetype":"venue"
},
  "geometry": {"coordinates":[-117.678866,34.059803],"type":"Point"}
}