{
  "type": "Feature",
  "properties": {
    "iso:country":"US",
    "sg:address":"170 Borica St",
    "sg:city":"San Francisco",
    "sg:classifiers":[
        {
            "category":"Building & Trades",
            "subcategory":"Landscaping Services",
            "type":"Services"
        }
    ],
    "sg:phone":"+1 415 584 4656",
    "sg:postcode":"94127",
    "sg:province":"CA",
    "wof:name":"Extravert Landscaper",
    "wof:placetype":"venue"
},
  "geometry": {"coordinates":[-122.46733399999999,37.724093],"type":"Point"}
}