{
  "type": "Feature",
  "properties": {
    "iso:country":"US",
    "sg:address":"1351 Main St",
    "sg:city":"St Helena",
    "sg:classifiers":[
        {
            "category":"Bars & Pubs",
            "type":"Food & Drink"
        }
    ],
    "sg:phone":"+1 707 963 1969",
    "sg:postcode":"94574",
    "sg:province":"CA",
    "wof:name":"1351 Lounge",
    "wof:placetype":"venue"
},
  "geometry": {"coordinates":[-122.46973800000001,38.504723],"type":"Point"}
}