{
  "type": "Feature",
  "properties": {
    "iso:country":"US",
    "sg:address":"9911 W Pico Blvd",
    "sg:city":"Los Angeles",
    "sg:classifiers":[
        {
            "category":"Social Services",
            "subcategory":"Adult Care",
            "type":"Services"
        }
    ],
    "sg:phone":"+1 310 203 0500",
    "sg:postcode":"90035",
    "sg:province":"CA",
    "sg:tags":[
        "foster",
        "day",
        "child"
    ],
    "wof:name":"M Play-Children Uniting Nations",
    "wof:placetype":"venue"
},
  "geometry": {"coordinates":[-118.403999,34.053299],"type":"Point"}
}