{
  "type": "Feature",
  "properties": {
    "iso:country":"US",
    "sg:address":"1100 The Strand",
    "sg:city":"Hermosa Beach",
    "sg:classifiers":[
        {
            "category":"Restaurant",
            "type":"Food & Drink"
        }
    ],
    "sg:phone":"+1 310 318 7152",
    "sg:postcode":"90254",
    "sg:province":"CA",
    "wof:name":"Scotty's Inc",
    "wof:placetype":"venue"
},
  "geometry": {"coordinates":[-118.401664,33.861913],"type":"Point"}
}