{
  "type": "Feature",
  "properties": {
    "iso:country":"US",
    "sg:address":"1776 2nd St",
    "sg:city":"Napa",
    "sg:classifiers":[
        {
            "category":"Farming",
            "subcategory":"Vineyard",
            "type":"Manufacturing & Wholesale Goods"
        }
    ],
    "sg:phone":"+1 707 252 9384",
    "sg:postcode":"94559",
    "sg:province":"CA",
    "sg:tags":[
        "grape"
    ],
    "wof:name":"Big Ranch Vineyards A Cal",
    "wof:placetype":"venue"
},
  "geometry": {"coordinates":[-122.293413,38.29659],"type":"Point"}
}