{
  "type": "Feature",
  "properties": {
    "iso:country":"US",
    "sg:address":"1601 N Tustin Ave",
    "sg:city":"Santa Ana",
    "sg:classifiers":[
        {
            "category":"Shopping",
            "subcategory":"Shoes",
            "type":"Retail Goods"
        }
    ],
    "sg:phone":"+1 714 542 2023",
    "sg:postcode":"92705",
    "sg:province":"CA",
    "sg:tags":[
        "store"
    ],
    "wof:name":"Shoe City",
    "wof:placetype":"venue"
},
  "geometry": {"coordinates":[-117.834,33.758701],"type":"Point"}
}