{
  "type": "Feature",
  "properties": {
    "iso:country":"US",
    "sg:address":"6574 N Mirna Ave",
    "sg:city":"San Bernardino",
    "sg:classifiers":[
        {
            "category":"Health Services",
            "subcategory":"Nursing And Care Facility",
            "type":"Services"
        }
    ],
    "sg:phone":"+1 909 880 6309",
    "sg:postcode":"92407",
    "sg:province":"CA",
    "sg:tags":[
        "home",
        "convalescent"
    ],
    "wof:name":"Mirora Group Home",
    "wof:placetype":"venue"
},
  "geometry": {"coordinates":[-117.360176,34.200461],"type":"Point"}
}