{
  "type": "Feature",
  "properties": {
    "addr:full":"4817 Via Palma La Mesa CA 91941",
    "addr:housenumber":"4817",
    "addr:postcode":"91941",
    "addr:street":"Via Palma",
    "iso:country":"US",
    "sg:address":"4817 Via Palma",
    "sg:city":"La Mesa",
    "sg:classifiers":[
        {
            "category":"Professional",
            "subcategory":"Lawyer & Legal Services",
            "type":"Services"
        }
    ],
    "sg:phone":"+1 619 462 7051",
    "sg:postcode":"91941",
    "sg:province":"CA",
    "sg:tags":[
        "attorney"
    ],
    "wof:name":"Sam J Cerniglia",
    "wof:placetype":"venue"
},
  "geometry": {"coordinates":[-116.953137,32.745787],"type":"Point"}
}