{
  "type": "Feature",
  "properties": {
    "iso:country":"US",
    "sg:address":"1436 Menlo Ave",
    "sg:city":"Clovis",
    "sg:classifiers":[
        {
            "category":"Manufacturing",
            "subcategory":"Buildings",
            "type":"Manufacturing & Wholesale Goods"
        },
        {
            "category":"Home & Garden",
            "subcategory":"Building Materials",
            "type":"Retail Goods"
        },
        {
            "category":"Professional",
            "subcategory":"Printing & Photocopies",
            "type":"Services"
        },
        {
            "category":"Manufacturing",
            "subcategory":"Building Materials",
            "type":"Manufacturing & Wholesale Goods"
        },
        {
            "category":"Building & Trades",
            "subcategory":"Locksmith",
            "type":"Services"
        }
    ],
    "sg:phone":"+1 559 323 6350",
    "sg:postcode":"93611",
    "sg:province":"CA",
    "sg:tags":[
        "repairing",
        "repair",
        "door",
        "accessory",
        "garage",
        "opener",
        "doors",
        "frames",
        "door-overhead",
        "type",
        "garages-building"
    ],
    "sg:website":"http://www.phillipsdoor.com",
    "wof:name":"Phillips Garage Door Co",
    "wof:placetype":"venue"
},
  "geometry": {"coordinates":[-119.690161,36.831236],"type":"Point"}
}