{
  "type": "Feature",
  "properties": {
    "iso:country":"US",
    "sg:address":"720 Arctic Ave",
    "sg:city":"Santa Maria",
    "sg:classifiers":[
        {
            "category":"Building & Trades",
            "subcategory":"Construction",
            "type":"Services"
        }
    ],
    "sg:phone":"+1 805 349 9177",
    "sg:postcode":"93454",
    "sg:province":"CA",
    "sg:tags":[
        "paving",
        "asphalt",
        "contractor"
    ],
    "wof:name":"Arnold Asphalt",
    "wof:placetype":"venue"
},
  "geometry": {"coordinates":[-120.42526100000001,34.946041],"type":"Point"}
}