{
  "type": "Feature",
  "properties": {
    "iso:country":"US",
    "sg:address":"1617 W Rosecrans Ave",
    "sg:city":"Gardena",
    "sg:classifiers":[
        {
            "category":"Autos & Motor Vehicles",
            "subcategory":"Auto Supplies",
            "type":"Retail Goods"
        }
    ],
    "sg:phone":"+1 310 538 3236",
    "sg:postcode":"90249",
    "sg:province":"CA",
    "sg:tags":[
        "tire"
    ],
    "wof:name":"US Tire Company",
    "wof:placetype":"venue"
},
  "geometry": {"coordinates":[-118.305,33.901901],"type":"Point"}
}