{
  "type": "Feature",
  "properties": {
    "addr:full":"1082 San Juan St Apt D Tustin CA 92780",
    "addr:housenumber":"1082",
    "addr:postcode":"92780",
    "addr:street":"San Juan St Apt D",
    "iso:country":"US",
    "sg:address":"1082 San Juan St Apt D",
    "sg:city":"Tustin",
    "sg:classifiers":[
        {
            "category":"Retail",
            "subcategory":"Laundry & Dry Cleaning",
            "type":"Services"
        },
        {
            "category":"Building & Trades",
            "subcategory":"Cleaning & Sanitation",
            "type":"Services"
        }
    ],
    "sg:phone":"+1 714 366 9201",
    "sg:postcode":"92780",
    "sg:province":"CA",
    "sg:tags":[
        "cleaner",
        "house"
    ],
    "wof:name":"Top 2 Bottom Cleaning",
    "wof:placetype":"venue"
},
  "geometry": {"coordinates":[-117.81838,33.740325],"type":"Point"}
}