{
  "type": "Feature",
  "properties": {
    "iso:country":"US",
    "sg:address":"3441 Woodland Dr",
    "sg:city":"Mariposa",
    "sg:classifiers":[
        {
            "category":"Restaurant",
            "type":"Food & Drink"
        }
    ],
    "sg:phone":"+1 209 966 3474",
    "sg:postcode":"95338",
    "sg:province":"CA",
    "wof:name":"Pop's Sportsman Cafe",
    "wof:placetype":"venue"
},
  "geometry": {"coordinates":[-119.846543,37.449894],"type":"Point"}
}