{
  "type": "Feature",
  "properties": {
    "addr:full":"4778 Cll Solimar Oceanside CA 92057",
    "addr:housenumber":"4778",
    "addr:postcode":"92057",
    "addr:street":"Cll Solimar",
    "iso:country":"US",
    "sg:address":"4778 Cll Solimar",
    "sg:city":"Oceanside",
    "sg:classifiers":[
        {
            "category":"Restaurant",
            "type":"Food & Drink"
        }
    ],
    "sg:phone":"+1 760 757 3791",
    "sg:postcode":"92057",
    "sg:province":"CA",
    "sg:tags":[
        "eating"
    ],
    "wof:name":"Juliettes Cafe Cart",
    "wof:placetype":"venue"
},
  "geometry": {"coordinates":[-117.30739800000001,33.24792],"type":"Point"}
}