{
  "type": "Feature",
  "properties": {
    "iso:country":"US",
    "sg:address":"1220 Brickyard Cove Rd Ste 101",
    "sg:city":"Richmond",
    "sg:classifiers":[
        {
            "category":"Health Services",
            "subcategory":"Clinic",
            "type":"Services"
        },
        {
            "category":"Community Center",
            "type":"Public Place"
        }
    ],
    "sg:phone":"+1 510 412 9040",
    "sg:postcode":"94801",
    "sg:province":"CA",
    "sg:tags":[
        "medical"
    ],
    "wof:name":"Hahnemann Medical Clinic Pt Richmond",
    "wof:placetype":"venue"
},
  "geometry": {"coordinates":[-122.37960099999999,37.911368],"type":"Point"}
}