{
  "type": "Feature",
  "properties": {
    "iso:country":"US",
    "sg:address":"5820 Temple City Blvd",
    "sg:city":"Temple City",
    "sg:classifiers":[
        {
            "category":"Personal",
            "subcategory":"Beauty Salon",
            "type":"Services"
        }
    ],
    "sg:phone":"+1 626 286 5931",
    "sg:postcode":"91780",
    "sg:province":"CA",
    "wof:name":"Coe's Coiffures North",
    "wof:placetype":"venue"
},
  "geometry": {"coordinates":[-118.060766,34.106332],"type":"Point"}
}