{
  "type": "Feature",
  "properties": {
    "iso:country":"US",
    "sg:address":"14616 Grevillea Ave",
    "sg:city":"Lawndale",
    "sg:classifiers":[
        {
            "category":"Government",
            "subcategory":"Office",
            "type":"Public Place"
        }
    ],
    "sg:phone":"+1 310 973 3100",
    "sg:postcode":"90260",
    "sg:province":"CA",
    "sg:tags":[
        "administrative",
        "program",
        "health"
    ],
    "wof:name":"Health Services Dept of",
    "wof:placetype":"venue"
},
  "geometry": {"coordinates":[-118.354732,33.899864],"type":"Point"}
}