{
  "type": "Feature",
  "properties": {
    "addr:full":"5331 Eunice St Rohnert Park CA 94928",
    "addr:housenumber":"5331",
    "addr:postcode":"94928",
    "addr:street":"Eunice St",
    "iso:country":"US",
    "sg:address":"5331 Eunice St",
    "sg:city":"Rohnert Park",
    "sg:classifiers":[
        {
            "category":"Professional",
            "subcategory":"Computer Services",
            "type":"Services"
        }
    ],
    "sg:phone":"+1 707 292 7599",
    "sg:postcode":"94928",
    "sg:province":"CA",
    "sg:tags":[
        "internet"
    ],
    "wof:name":"Babbitt Networking",
    "wof:placetype":"venue"
},
  "geometry": {"coordinates":[-122.692919,38.357441],"type":"Point"}
}