{
  "type": "Feature",
  "properties": {
    "addr:full":"12007 Woodruff Ave Downey CA 90241",
    "addr:housenumber":"12007",
    "addr:postcode":"90241",
    "addr:street":"Woodruff Ave",
    "iso:country":"US",
    "sg:address":"12007 Woodruff Ave",
    "sg:city":"Downey",
    "sg:classifiers":[
        {
            "category":"Manufacturing",
            "subcategory":"Rubber & Plastics",
            "type":"Manufacturing & Wholesale Goods"
        }
    ],
    "sg:phone":"+1 562 803 5582",
    "sg:postcode":"90241",
    "sg:province":"CA",
    "sg:website":"www.storopackinc.com",
    "wof:name":"Storopack",
    "wof:placetype":"venue"
},
  "geometry": {"coordinates":[-118.11675,33.925266],"type":"Point"}
}