{
  "type": "Feature",
  "properties": {
    "iso:country":"US",
    "sg:address":"844 Production Pl",
    "sg:city":"Newport Beach",
    "sg:classifiers":[
        {
            "category":"Shopping",
            "subcategory":"Clothing, Apparel, & Fashions",
            "type":"Retail Goods"
        }
    ],
    "sg:phone":"+1 949 650 1222",
    "sg:postcode":"92663",
    "sg:province":"CA",
    "sg:tags":[
        "handbag"
    ],
    "wof:name":"Ameriken Joe Inc",
    "wof:placetype":"venue"
},
  "geometry": {"coordinates":[-117.934401,33.631179],"type":"Point"}
}