{
  "type": "Feature",
  "properties": {
    "addr:full":"315 Rianda St Salinas CA 93901",
    "addr:housenumber":"315",
    "addr:postcode":"93901",
    "addr:street":"Rianda St",
    "iso:country":"US",
    "sg:address":"315 Rianda St",
    "sg:city":"Salinas",
    "sg:classifiers":[
        {
            "category":"Retail",
            "subcategory":"Auto Repair",
            "type":"Services"
        }
    ],
    "sg:phone":"+1 831 757 8868",
    "sg:postcode":"93901",
    "sg:province":"CA",
    "sg:tags":[
        "repairing",
        "automobile"
    ],
    "wof:name":"All City Emissions",
    "wof:placetype":"venue"
},
  "geometry": {"coordinates":[-121.642836,36.67581],"type":"Point"}
}