{
  "type": "Feature",
  "properties": {
    "iso:country":"US",
    "sg:address":"3014 San Pablo Ave",
    "sg:city":"Berkeley",
    "sg:classifiers":[
        {
            "category":"Shopping",
            "subcategory":"Clothing, Apparel, & Fashions",
            "type":"Retail Goods"
        }
    ],
    "sg:phone":"+1 510 649 2990",
    "sg:postcode":"94702",
    "sg:province":"CA",
    "sg:tags":[
        "clothing",
        "boys'"
    ],
    "wof:name":"Dome Apparel Line",
    "wof:placetype":"venue"
},
  "geometry": {"coordinates":[-122.286547,37.85157],"type":"Point"}
}