{
  "type": "Feature",
  "properties": {
    "addr:full":"272 Nut Tree Rd Vacaville CA 95687",
    "addr:housenumber":"272",
    "addr:postcode":"95687",
    "addr:street":"Nut Tree Rd",
    "iso:country":"US",
    "sg:address":"272 Nut Tree Rd",
    "sg:city":"Vacaville",
    "sg:classifiers":[
        {
            "category":"Shopping",
            "subcategory":"Jewelry",
            "type":"Retail Goods"
        }
    ],
    "sg:phone":"+1 707 446 2144",
    "sg:postcode":"95687",
    "sg:province":"CA",
    "sg:tags":[
        "jeweler"
    ],
    "sg:website":"www.diamondsdirectca.com",
    "wof:name":"Diamonds Direct",
    "wof:placetype":"venue"
},
  "geometry": {"coordinates":[-121.954275,38.36579],"type":"Point"}
}