{
  "type": "Feature",
  "properties": {
    "iso:country":"US",
    "sg:address":"8434 Nahoa Way",
    "sg:city":"Phelan",
    "sg:classifiers":[
        {
            "category":"Retail",
            "subcategory":"Animal Services",
            "type":"Services"
        }
    ],
    "sg:phone":"+1 760 956 3504",
    "sg:postcode":"92407",
    "sg:province":"CA",
    "wof:name":"Rtl Paint Horses",
    "wof:placetype":"venue"
},
  "geometry": {"coordinates":[-117.457651,34.403561],"type":"Point"}
}