{
  "type": "Feature",
  "properties": {
    "addr:full":"1669 Chili Bar Ct Placerville CA 95667",
    "addr:housenumber":"1669",
    "addr:postcode":"95667",
    "addr:street":"Bar Ct",
    "iso:country":"US",
    "sg:address":"1669 Chili Bar Ct",
    "sg:city":"Placerville",
    "sg:classifiers":[
        {
            "category":"Recreation",
            "subcategory":"Boat Charter",
            "type":"Entertainment"
        },
        {
            "category":"Landmark",
            "subcategory":"Tourist Information",
            "type":"Public Place"
        },
        {
            "category":"Landmark",
            "subcategory":"Tourist Attraction",
            "type":"Public Place"
        }
    ],
    "sg:phone":"+1 530 642 1667",
    "sg:postcode":"95667",
    "sg:province":"CA",
    "sg:tags":[
        "tour",
        "tours-operators",
        "promoter",
        "sightseeing"
    ],
    "wof:name":"Chili Bar Put In",
    "wof:placetype":"venue"
},
  "geometry": {"coordinates":[-120.821816,38.766746],"type":"Point"}
}