{
  "type": "Feature",
  "properties": {
    "addr:full":"2 Civic Center Plz Irvine CA 92606",
    "addr:housenumber":"2",
    "addr:postcode":"92606",
    "addr:street":"Civic Center Plz",
    "iso:country":"US",
    "sg:address":"2 Civic Center Plz",
    "sg:city":"Irvine",
    "sg:classifiers":[
        {
            "category":"Social Services",
            "subcategory":"Child Care",
            "type":"Services"
        }
    ],
    "sg:phone":"+1 949 724 6700",
    "sg:postcode":"92606",
    "sg:province":"CA",
    "sg:tags":[
        "day"
    ],
    "wof:name":"Irvine Child Development Center",
    "wof:placetype":"venue"
},
  "geometry": {"coordinates":[-117.824997,33.686001],"type":"Point"}
}