{
  "type": "Feature",
  "properties": {
    "addr:full":"6101 Condor Dr Moorpark CA 93021",
    "addr:housenumber":"6101",
    "addr:postcode":"ca 93021",
    "addr:street":"Condor Dr",
    "iso:country":"US",
    "sg:address":"6101 Condor Dr",
    "sg:city":"Moorpark",
    "sg:classifiers":[
        {
            "category":"Wholesale",
            "subcategory":"Office Equipment",
            "type":"Manufacturing & Wholesale Goods"
        },
        {
            "category":"Professional",
            "subcategory":"Business Services",
            "type":"Services"
        }
    ],
    "sg:phone":"+1 805 552 8000",
    "sg:postcode":"93021",
    "sg:province":"CA",
    "sg:tags":[
        "credit",
        "short",
        "system",
        "card"
    ],
    "sg:website":"www.cardservicecincy.com",
    "wof:name":"Cardservice International Inc",
    "wof:placetype":"venue"
},
  "geometry": {"coordinates":[-118.855615,34.28871],"type":"Point"}
}