{
  "type": "Feature",
  "properties": {
    "addr:full":"840 E Parkridge Ave Corona CA 92879",
    "addr:housenumber":"840",
    "addr:postcode":"92879",
    "addr:street":"E Parkridge Ave",
    "iso:country":"US",
    "sg:address":"840 E Parkridge Ave",
    "sg:city":"Corona",
    "sg:classifiers":[
        {
            "category":"Professional",
            "subcategory":"Advertising",
            "type":"Services"
        }
    ],
    "sg:phone":"+1 909 948 7025",
    "sg:postcode":"92879",
    "sg:province":"CA",
    "sg:tags":[
        "commercial",
        "agency",
        "design"
    ],
    "sg:website":"www.designmakers.com",
    "wof:name":"California Coast Advertising",
    "wof:placetype":"venue"
},
  "geometry": {"coordinates":[-117.54953399999999,33.886423],"type":"Point"}
}