{
  "type": "Feature",
  "properties": {
    "iso:country":"US",
    "sg:address":"2727 Pacific St",
    "sg:city":"Highland",
    "sg:classifiers":[
        {
            "category":"Wholesale",
            "subcategory":"Non-durable Goods",
            "type":"Manufacturing & Wholesale Goods"
        },
        {
            "category":"Wholesale",
            "subcategory":"Durable Goods & Equipment",
            "type":"Manufacturing & Wholesale Goods"
        }
    ],
    "sg:phone":"+1 909 856 8817",
    "sg:postcode":"92346",
    "sg:province":"CA",
    "sg:tags":[
        "importer"
    ],
    "wof:name":"Pattama Import Export",
    "wof:placetype":"venue"
},
  "geometry": {"coordinates":[-117.227677,34.128497],"type":"Point"}
}