{
  "type": "Feature",
  "properties": {
    "addr:full":"2600 N Glenoaks Blvd Burbank CA 91504",
    "addr:housenumber":"2600",
    "addr:postcode":"91504",
    "addr:street":"N Glenoaks Blvd",
    "iso:country":"US",
    "sg:address":"2600 N Glenoaks Blvd",
    "sg:city":"Burbank",
    "sg:classifiers":[
        {
            "category":"Restaurant",
            "type":"Food & Drink"
        }
    ],
    "sg:phone":"+1 818 846 3358",
    "sg:postcode":"91504",
    "sg:province":"CA",
    "sg:tags":[
        "cuban"
    ],
    "sg:website":"www.labambarestaurant.us/",
    "wof:name":"La Bamba Island Cuisine",
    "wof:placetype":"venue"
},
  "geometry": {"coordinates":[-118.333,34.202099],"type":"Point"}
}