{
  "type": "Feature",
  "properties": {
    "addr:full":"320 W Ave P Palmdale CA 93551",
    "addr:housenumber":"320",
    "addr:postcode":"93551",
    "addr:street":"W Ave P Palmdale",
    "iso:country":"US",
    "sg:address":"320 W Ave P",
    "sg:city":"Palmdale",
    "sg:classifiers":[
        {
            "category":"Utilities",
            "subcategory":"Mobile Phone",
            "type":"Services"
        }
    ],
    "sg:phone":"+1 661 265 9715",
    "sg:postcode":"93551",
    "sg:province":"CA",
    "sg:tags":[
        "communication",
        "radiotelephone"
    ],
    "wof:name":"AT&T Wireless",
    "wof:placetype":"venue"
},
  "geometry": {"coordinates":[-118.137659,34.601683],"type":"Point"}
}