{
  "type": "Feature",
  "properties": {
    "addr:full":"895 B St Hayward CA 94541",
    "addr:housenumber":"895",
    "addr:postcode":"94541",
    "addr:street":"B St",
    "iso:country":"US",
    "sg:address":"895 B St",
    "sg:city":"Hayward",
    "sg:classifiers":[
        {
            "category":"Retail",
            "subcategory":"Repair Shop",
            "type":"Services"
        }
    ],
    "sg:phone":"+1 510 538 3996",
    "sg:postcode":"94541",
    "sg:province":"CA",
    "sg:tags":[
        "spa",
        "hot",
        "tub"
    ],
    "wof:name":"Spa Surgeon",
    "wof:placetype":"venue"
},
  "geometry": {"coordinates":[-122.083878,37.672061],"type":"Point"}
}