{
  "type": "Feature",
  "properties": {
    "iso:country":"US",
    "sg:address":"608 E 12th Street",
    "sg:city":"Los Angeles",
    "sg:classifiers":[
        {
            "category":"Shopping",
            "subcategory":"Clothing, Apparel, & Fashions",
            "type":"Retail Goods"
        }
    ],
    "sg:phone":"+1 213 745 4568",
    "sg:postcode":"90015",
    "sg:province":"CA",
    "sg:tags":[
        "children's",
        "clothing"
    ],
    "wof:name":"Bijan Kids",
    "wof:placetype":"venue"
},
  "geometry": {"coordinates":[-118.25419100000001,34.034119],"type":"Point"}
}