{
  "type": "Feature",
  "properties": {
    "iso:country":"US",
    "sg:address":"8042 Clairemont Mesa Boulevard",
    "sg:city":"San Diego",
    "sg:classifiers":[
        {
            "category":"Restaurant",
            "type":"Food & Drink"
        }
    ],
    "sg:phone":"+1 858 565 0304",
    "sg:postcode":"92111",
    "sg:province":"CA",
    "sg:tags":[
        "mexican"
    ],
    "wof:name":"Gualberto's Taco Shop No 4",
    "wof:placetype":"venue"
},
  "geometry": {"coordinates":[-117.149722,32.832722],"type":"Point"}
}