{
  "type": "Feature",
  "properties": {
    "iso:country":"US",
    "sg:address":"18608 1/2 Ventura Blvd",
    "sg:city":"Tarzana",
    "sg:phone":"+1 818 343 8800",
    "sg:postcode":"91356",
    "sg:province":"CA",
    "wof:name":"Kosher Chicks",
    "wof:placetype":"venue"
},
  "geometry": {"coordinates":[-118.53872800000001,34.16985],"type":"Point"}
}