{
  "type": "Feature",
  "properties": {
    "addr:full":"2222 W Sunnyside Ave # 2 Visalia CA 93277",
    "addr:housenumber":"2222",
    "addr:postcode":"93277",
    "addr:street":"W Sunnyside Ave # 2",
    "iso:country":"US",
    "sg:address":"2222 W Sunnyside Ave # 2",
    "sg:city":"Visalia",
    "sg:classifiers":[
        {
            "category":"Health Services",
            "subcategory":"Clinic",
            "type":"Services"
        }
    ],
    "sg:phone":"+1 559 625 0360",
    "sg:postcode":"93277",
    "sg:province":"CA",
    "sg:tags":[
        "information",
        "alcoholism",
        "treatment"
    ],
    "wof:name":"A S.T.E.P.",
    "wof:placetype":"venue"
},
  "geometry": {"coordinates":[-119.315091,36.303437],"type":"Point"}
}