{
  "type": "Feature",
  "properties": {
    "addr:full":"23946 Hawthorne Blvd Torrance CA 90505",
    "addr:housenumber":"23946",
    "addr:postcode":"90505",
    "addr:street":"Hawthorne Blvd",
    "iso:country":"US",
    "sg:address":"23946 Hawthorne Blvd",
    "sg:city":"Torrance",
    "sg:classifiers":[
        {
            "category":"Retail",
            "subcategory":"Repair Shop",
            "type":"Services"
        }
    ],
    "sg:phone":"+1 310 375 6175",
    "sg:postcode":"90505",
    "sg:province":"CA",
    "sg:tags":[
        "antique",
        "restoring"
    ],
    "wof:name":"Dunk Antiques & Restoration",
    "wof:placetype":"venue"
},
  "geometry": {"coordinates":[-118.350998,33.807701],"type":"Point"}
}