{
  "type": "Feature",
  "properties": {
    "addr:full":"2026A N Riverside Ave Ste 6-A Rialto CA 92377",
    "addr:housenumber":"2026a",
    "addr:postcode":"92377",
    "addr:street":"N Riverside Ave Ste 6-A",
    "iso:country":"US",
    "sg:address":"2026A N Riverside Ave Ste 6-A",
    "sg:city":"Rialto",
    "sg:classifiers":[
        {
            "category":"Professional",
            "subcategory":"Accounting & Tax Preparation",
            "type":"Services"
        },
        {
            "category":"Banks & Credit Unions",
            "subcategory":"Financial Services",
            "type":"Services"
        }
    ],
    "sg:phone":"+1 909 820 0795",
    "sg:postcode":"92377",
    "sg:province":"CA",
    "sg:tags":[
        "return",
        "preparation-business",
        "taxes-consultants",
        "loan",
        "reporting",
        "representative",
        "alternative",
        "bookkeeping"
    ],
    "sg:website":"http://www.hrblock.com",
    "wof:name":"H&R Block",
    "wof:placetype":"venue"
},
  "geometry": {"coordinates":[-117.37153000000001,34.138891],"type":"Point"}
}