{
  "type": "Feature",
  "properties": {
    "addr:full":"13931 Carroll Way Tustin CA 92780",
    "addr:housenumber":"13931",
    "addr:postcode":"92780",
    "addr:street":"Carroll Way",
    "iso:country":"US",
    "sg:address":"13931 Carroll Way",
    "sg:city":"Tustin",
    "sg:classifiers":[
        {
            "category":"Restaurant",
            "type":"Food & Drink"
        }
    ],
    "sg:phone":"+1 714 505 8922",
    "sg:postcode":"92780",
    "sg:province":"CA",
    "sg:tags":[
        "greek",
        "mediterranean"
    ],
    "wof:name":"Mama Kabob",
    "wof:placetype":"venue"
},
  "geometry": {"coordinates":[-117.829868,33.761],"type":"Point"}
}