{
  "type": "Feature",
  "properties": {
    "addr:full":"4287 E Olympic Blvd Los Angeles CA 90023",
    "addr:housenumber":"4287",
    "addr:postcode":"90023",
    "addr:street":"E Olympic Blvd",
    "iso:country":"US",
    "sg:address":"4287 E Olympic Blvd",
    "sg:city":"Los Angeles",
    "sg:classifiers":[
        {
            "category":"Manufacturing",
            "subcategory":"Metals",
            "type":"Manufacturing & Wholesale Goods"
        }
    ],
    "sg:phone":"+1 323 981 7177",
    "sg:postcode":"90023",
    "sg:province":"CA",
    "sg:tags":[
        "metalwork",
        "architectural",
        "mfg"
    ],
    "wof:name":"Luevanos Iron Works",
    "wof:placetype":"venue"
},
  "geometry": {"coordinates":[-118.180803,34.018971],"type":"Point"}
}