{
  "type": "Feature",
  "properties": {
    "addr:full":"440 Cold Springs Rd Angwin CA 94508",
    "addr:housenumber":"440",
    "addr:postcode":"94508",
    "addr:street":"Cold Springs Rd",
    "iso:country":"US",
    "sg:address":"440 Cold Springs Rd",
    "sg:city":"Angwin",
    "sg:classifiers":[
        {
            "category":"Professional",
            "type":"Services"
        }
    ],
    "sg:phone":"+1 707 965 2331",
    "sg:postcode":"94508",
    "sg:province":"CA",
    "wof:name":"NAPA Vintage Caves",
    "wof:placetype":"venue"
},
  "geometry": {"coordinates":[-122.435118,38.560528],"type":"Point"}
}