{
  "type": "Feature",
  "properties": {
    "iso:country":"US",
    "sg:address":"18850 Ventura Blvd",
    "sg:city":"Tarzana",
    "sg:classifiers":[
        {
            "category":"Wholesale",
            "subcategory":"Drugs",
            "type":"Manufacturing & Wholesale Goods"
        }
    ],
    "sg:phone":"+1 818 345 4346",
    "sg:postcode":"91356",
    "sg:province":"CA",
    "sg:tags":[
        "cosmetic"
    ],
    "sg:website":"www.cleanimals.com",
    "wof:name":"SNS Intl",
    "wof:placetype":"venue"
},
  "geometry": {"coordinates":[-118.54389999999999,34.171819],"type":"Point"}
}