{
  "type": "Feature",
  "properties": {
    "addr:full":"425 S Oleander Avenue Compton CA 90220",
    "addr:housenumber":"425",
    "addr:postcode":"90220",
    "addr:street":"S Oleander Avenue",
    "iso:country":"US",
    "sg:address":"425 S Oleander Avenue",
    "sg:city":"Compton",
    "sg:classifiers":[
        {
            "category":"Real Estate",
            "subcategory":"Real Estate Operator",
            "type":"Services"
        }
    ],
    "sg:phone":"+1 310 638 8251",
    "sg:postcode":"90220",
    "sg:province":"CA",
    "sg:tags":[
        "apartment"
    ],
    "wof:name":"St Timothy's Manor",
    "wof:placetype":"venue"
},
  "geometry": {"coordinates":[-118.228525,33.892923],"type":"Point"}
}