{
  "type": "Feature",
  "properties": {
    "addr:full":"22744 Eastpark Dr Yorba Linda CA 92887",
    "addr:housenumber":"22744",
    "addr:postcode":"92887",
    "addr:street":"Eastpark Dr",
    "iso:country":"US",
    "sg:address":"22744 Eastpark Dr",
    "sg:city":"Yorba Linda",
    "sg:classifiers":[
        {
            "category":"Autos & Motor Vehicles",
            "subcategory":"Automobile Sales",
            "type":"Retail Goods"
        }
    ],
    "sg:phone":"+1 714 283 5400",
    "sg:postcode":"92887",
    "sg:province":"CA",
    "sg:tags":[
        "car"
    ],
    "wof:name":"Yorba Linda Chevrolet Used Cars",
    "wof:placetype":"venue"
},
  "geometry": {"coordinates":[-117.736,33.872898],"type":"Point"}
}