{
  "type": "Feature",
  "properties": {
    "addr:full":"1129 Cypress St Santa Maria CA 93458",
    "addr:housenumber":"1129",
    "addr:postcode":"93458",
    "addr:street":"Cypress St",
    "iso:country":"US",
    "sg:address":"1129 Cypress St",
    "sg:city":"Santa Maria",
    "sg:classifiers":[
        {
            "category":"Retail",
            "subcategory":"Auto Repair",
            "type":"Services"
        }
    ],
    "sg:phone":"+1 805 260 5030",
    "sg:postcode":"93458",
    "sg:province":"CA",
    "sg:tags":[
        "body",
        "automobile",
        "painting"
    ],
    "wof:name":"Precision Auto Body Uphlstry",
    "wof:placetype":"venue"
},
  "geometry": {"coordinates":[-120.452055,34.950899],"type":"Point"}
}