{
  "type": "Feature",
  "properties": {
    "iso:country":"US",
    "sg:address":"1030 Los Osos Valley Rd",
    "sg:city":"Los Osos",
    "sg:classifiers":[
        {
            "category":"Shopping",
            "type":"Retail Goods"
        }
    ],
    "sg:phone":"+1 805 528 5611",
    "sg:postcode":"93402",
    "sg:province":"CA",
    "sg:tags":[
        "pet",
        "food",
        "supply"
    ],
    "wof:name":"J D's Pet House",
    "wof:placetype":"venue"
},
  "geometry": {"coordinates":[-120.83188,35.311077],"type":"Point"}
}