{
  "type": "Feature",
  "properties": {
    "iso:country":"US",
    "sg:address":"338 E Route 66",
    "sg:city":"Glendora",
    "sg:classifiers":[
        {
            "category":"Restaurant",
            "type":"Food & Drink"
        }
    ],
    "sg:phone":"+1 626 335 2615",
    "sg:postcode":"91740",
    "sg:province":"CA",
    "sg:tags":[
        "style",
        "family"
    ],
    "wof:name":"Auline's Restaurant",
    "wof:placetype":"venue"
},
  "geometry": {"coordinates":[-117.860856,34.128689],"type":"Point"}
}