{
  "type": "Feature",
  "properties": {
    "addr:full":"620 Pennsylvania Ave Fairfield CA 94533",
    "addr:housenumber":"620",
    "addr:postcode":"94533",
    "addr:street":"Pennsylvania Ave",
    "iso:country":"US",
    "sg:address":"620 Pennsylvania Ave",
    "sg:city":"Fairfield",
    "sg:classifiers":[
        {
            "category":"Cinema",
            "subcategory":"Movie Rental",
            "type":"Entertainment"
        }
    ],
    "sg:phone":"+1 707 422 9920",
    "sg:postcode":"94533",
    "sg:province":"CA",
    "sg:tags":[
        "video",
        "tape"
    ],
    "wof:name":"Pepes Video Movil",
    "wof:placetype":"venue"
},
  "geometry": {"coordinates":[-122.049747,38.248459],"type":"Point"}
}