{
  "type": "Feature",
  "properties": {
    "iso:country":"US",
    "sg:address":"2547 E Bethel Dr",
    "sg:city":"Anaheim",
    "sg:classifiers":[
        {
            "category":"Freight",
            "type":"Transportation"
        }
    ],
    "sg:phone":"+1 714 956 5744",
    "sg:postcode":"92806",
    "sg:province":"CA",
    "sg:tags":[
        "operator",
        "local",
        "trucking"
    ],
    "wof:name":"Londekes Trucking",
    "wof:placetype":"venue"
},
  "geometry": {"coordinates":[-117.877917,33.831494],"type":"Point"}
}