{
  "type": "Feature",
  "properties": {
    "addr:full":"815 N Magnolia Ave Upland CA 91786",
    "addr:housenumber":"815",
    "addr:postcode":"91786",
    "addr:street":"N Magnolia Ave",
    "iso:country":"US",
    "sg:address":"815 N Magnolia Ave",
    "sg:city":"Upland",
    "sg:classifiers":[
        {
            "category":"Professional",
            "subcategory":"Computer Services",
            "type":"Services"
        }
    ],
    "sg:phone":"+1 909 946 7444",
    "sg:postcode":"91786",
    "sg:province":"CA",
    "sg:tags":[
        "internet"
    ],
    "sg:website":"www.cdahelp.com",
    "wof:name":"Perpetual Preschool",
    "wof:placetype":"venue"
},
  "geometry": {"coordinates":[-117.66386,34.103883],"type":"Point"}
}