{
  "type": "Feature",
  "properties": {
    "iso:country":"US",
    "sg:address":"1011 Pecten Ct",
    "sg:city":"Milpitas",
    "sg:classifiers":[
        {
            "category":"Manufacturing",
            "subcategory":"Tools & Machinery",
            "type":"Manufacturing & Wholesale Goods"
        }
    ],
    "sg:phone":"+1 408 946 5890",
    "sg:postcode":"95035",
    "sg:province":"CA",
    "sg:tags":[
        "machine",
        "shop"
    ],
    "sg:website":"www.allweld.com",
    "wof:name":"All Weld Machine & Fabrication",
    "wof:placetype":"venue"
},
  "geometry": {"coordinates":[-121.88323,37.4131],"type":"Point"}
}