{
  "type": "Feature",
  "properties": {
    "addr:full":"401 W Fallbrook Ave Fresno CA 93711",
    "addr:housenumber":"401",
    "addr:postcode":"93711",
    "addr:street":"W Fallbrook Ave",
    "iso:country":"US",
    "sg:address":"401 W Fallbrook Ave",
    "sg:city":"Fresno",
    "sg:classifiers":[
        {
            "category":"Professional",
            "subcategory":"Lawyer & Legal Services",
            "type":"Services"
        }
    ],
    "sg:phone":"+1 559 266 8604",
    "sg:postcode":"93711",
    "sg:province":"CA",
    "sg:tags":[
        "attorney"
    ],
    "wof:name":"Terry A Wapner",
    "wof:placetype":"venue"
},
  "geometry": {"coordinates":[-119.79950700000001,36.849314],"type":"Point"}
}