{
  "type": "Feature",
  "properties": {
    "addr:full":"4535 Missouri Flat Rd #1B Placerville CA 95667",
    "addr:housenumber":"4535;1b",
    "addr:postcode":"95667",
    "addr:street":"Missouri Flat Rd #",
    "iso:country":"US",
    "sg:address":"4535 Missouri Flat Rd #1B",
    "sg:city":"Placerville",
    "sg:classifiers":[
        {
            "category":"Home & Garden",
            "subcategory":"Garden Supply",
            "type":"Retail Goods"
        },
        {
            "category":"Shopping",
            "subcategory":"Gifts & Souvenirs",
            "type":"Retail Goods"
        },
        {
            "category":"Shopping",
            "subcategory":"Crafts & Fabrics",
            "type":"Retail Goods"
        },
        {
            "category":"Shopping",
            "subcategory":"Florist",
            "type":"Retail Goods"
        }
    ],
    "sg:phone":"+1 530 621 4444",
    "sg:postcode":"95667",
    "sg:province":"CA",
    "sg:tags":[
        "plant",
        "etc-retail",
        "dried",
        "basket",
        "trees-silk",
        "flowers"
    ],
    "sg:website":"http://www.lefleurflorist.com",
    "wof:name":"Le Fleur Florist",
    "wof:placetype":"venue"
},
  "geometry": {"coordinates":[-120.822861,38.699162],"type":"Point"}
}