{
  "type": "Feature",
  "properties": {
    "addr:full":"570 N Shoreline Blvd Mountain View CA 94043",
    "addr:housenumber":"570",
    "addr:postcode":"94043",
    "addr:street":"N Shoreline Blvd",
    "iso:country":"US",
    "sg:address":"570 N Shoreline Blvd",
    "sg:city":"Mountain View",
    "sg:classifiers":[
        {
            "category":"Personal",
            "subcategory":"Beauty Salon",
            "type":"Services"
        }
    ],
    "sg:phone":"+1 650 969 2725",
    "sg:postcode":"94043",
    "sg:province":"CA",
    "wof:name":"Nguyen Sangthi",
    "wof:placetype":"venue"
},
  "geometry": {"coordinates":[-122.07857199999999,37.40205],"type":"Point"}
}