{
  "type": "Feature",
  "properties": {
    "addr:full":"265 N D St San Bernardino CA 92401",
    "addr:housenumber":"265",
    "addr:postcode":"92401",
    "addr:street":"N D St",
    "iso:country":"US",
    "sg:address":"265 N D St",
    "sg:city":"San Bernardino",
    "sg:classifiers":[
        {
            "category":"Social Services",
            "subcategory":"Child Care",
            "type":"Services"
        }
    ],
    "sg:phone":"+1 909 383 8345",
    "sg:postcode":"92401",
    "sg:province":"CA",
    "wof:name":"Civic Circle Preschool",
    "wof:placetype":"venue"
},
  "geometry": {"coordinates":[-117.291836,34.103373],"type":"Point"}
}