{
  "type": "Feature",
  "properties": {
    "iso:country":"US",
    "sg:address":"1516 Oak St",
    "sg:city":"Alameda",
    "sg:classifiers":[
        {
            "category":"Professional",
            "subcategory":"Research",
            "type":"Services"
        }
    ],
    "sg:phone":"+1 510 865 5872",
    "sg:postcode":"94501",
    "sg:province":"CA",
    "sg:tags":[
        "biotechnology",
        "product"
    ],
    "wof:name":"Advanced Bioscience Resources",
    "wof:placetype":"venue"
},
  "geometry": {"coordinates":[-122.24299600000001,37.766293],"type":"Point"}
}