{
  "type": "Feature",
  "properties": {
    "addr:full":"4243 18th St San Francisco CA 94114",
    "addr:housenumber":"4243",
    "addr:postcode":"94114",
    "addr:street":"18Th St",
    "iso:country":"US",
    "sg:address":"4243 18th St",
    "sg:city":"San Francisco",
    "sg:classifiers":[
        {
            "category":"Restaurant",
            "type":"Food & Drink"
        }
    ],
    "sg:phone":"+1 415 626 7864",
    "sg:postcode":"94114",
    "sg:province":"CA",
    "wof:name":"Ma Tante Sumi",
    "wof:placetype":"venue"
},
  "geometry": {"coordinates":[-122.43682,37.760711],"type":"Point"}
}