{
  "type": "Feature",
  "properties": {
    "addr:full":"302 W el Norte Pkwy Escondido CA 92026",
    "addr:housenumber":"302",
    "addr:postcode":"92026",
    "addr:street":"W El Norte Pkwy",
    "iso:country":"US",
    "sg:address":"302 W el Norte Pkwy",
    "sg:city":"Escondido",
    "sg:classifiers":[
        {
            "category":"Retail",
            "subcategory":"Portrait Studio",
            "type":"Services"
        }
    ],
    "sg:phone":"+1 760 233 4100",
    "sg:postcode":"92026",
    "sg:province":"CA",
    "sg:tags":[
        "photographer"
    ],
    "wof:name":"Dig-Dog",
    "wof:placetype":"venue"
},
  "geometry": {"coordinates":[-117.094388,33.14061],"type":"Point"}
}