{
  "type": "Feature",
  "properties": {
    "addr:full":"4324 Redwood Hwy San Rafael CA 94903",
    "addr:housenumber":"4324",
    "addr:postcode":"94903",
    "addr:street":"Redwood Hwy",
    "iso:country":"US",
    "sg:address":"4324 Redwood Hwy",
    "sg:city":"San Rafael",
    "sg:classifiers":[
        {
            "category":"Wholesale",
            "subcategory":"Medical Equipment & Supplies",
            "type":"Manufacturing & Wholesale Goods"
        }
    ],
    "sg:phone":"+1 415 491 4488",
    "sg:postcode":"94903",
    "sg:province":"CA",
    "sg:tags":[
        "dental"
    ],
    "wof:name":"Golden Gate Dental Supply",
    "wof:placetype":"venue"
},
  "geometry": {"coordinates":[-122.541331,38.013151],"type":"Point"}
}