{
  "type": "Feature",
  "properties": {
    "iso:country":"US",
    "sg:address":"2085 E Main St",
    "sg:city":"Quincy",
    "sg:classifiers":[
        {
            "category":"Professional",
            "subcategory":"Computer Services",
            "type":"Services"
        }
    ],
    "sg:phone":"+1 530 283 1875",
    "sg:postcode":"95971",
    "sg:province":"CA",
    "sg:tags":[
        "repair"
    ],
    "wof:name":"Plumos Electronic & Computer",
    "wof:placetype":"venue"
},
  "geometry": {"coordinates":[-120.898922,39.934022],"type":"Point"}
}