{
  "type": "Feature",
  "properties": {
    "addr:full":"3616 Monterey Ave El Monte CA 91731",
    "addr:housenumber":"3616",
    "addr:postcode":"91731",
    "addr:street":"Monterey Ave",
    "iso:country":"US",
    "sg:address":"3616 Monterey Ave",
    "sg:city":"El Monte",
    "sg:classifiers":[
        {
            "category":"Sports & Exercise",
            "subcategory":"Bicycle Rental",
            "type":"Entertainment"
        }
    ],
    "sg:phone":"+1 888 376 2434",
    "sg:postcode":"91731",
    "sg:province":"CA",
    "sg:tags":[
        "wear"
    ],
    "wof:name":"Sports Nation",
    "wof:placetype":"venue"
},
  "geometry": {"coordinates":[-118.038021,34.075589],"type":"Point"}
}