{
  "type": "Feature",
  "properties": {
    "iso:country":"US",
    "sg:address":"4266 Locust Ave",
    "sg:city":"Long Beach",
    "sg:classifiers":[
        {
            "category":"Banks & Credit Unions",
            "subcategory":"Bank",
            "type":"Services"
        }
    ],
    "sg:phone":"+1 562 988 9393",
    "sg:postcode":"90807",
    "sg:province":"CA",
    "sg:tags":[
        "broker",
        "mortgage"
    ],
    "wof:name":"Amen Mortgage Funding",
    "wof:placetype":"venue"
},
  "geometry": {"coordinates":[-118.193191,33.833352],"type":"Point"}
}