{
  "type": "Feature",
  "properties": {
    "addr:full":"4385 Hillcrest Ave Antioch CA 94509",
    "addr:housenumber":"4385",
    "addr:postcode":"ca 94509",
    "addr:street":"Hillcrest Ave",
    "iso:country":"US",
    "sg:address":"4385 Hillcrest Ave",
    "sg:city":"Antioch",
    "sg:classifiers":[
        {
            "category":"Personal",
            "subcategory":"Beauty Salon",
            "type":"Services"
        }
    ],
    "sg:phone":"+1 925 978 2419",
    "sg:postcode":"94509",
    "sg:province":"CA",
    "wof:name":"Cutting Loose Hair Studio",
    "wof:placetype":"venue"
},
  "geometry": {"coordinates":[-121.759213,37.957733],"type":"Point"}
}