{
  "type": "Feature",
  "properties": {
    "addr:full":"801 S Lakeview Ave Ste B Placentia CA 92870",
    "addr:housenumber":"801",
    "addr:postcode":"ca 92870",
    "addr:street":"S Lakeview Ave Ste B",
    "iso:country":"US",
    "sg:address":"801 S Lakeview Ave Ste B",
    "sg:city":"Placentia",
    "sg:classifiers":[
        {
            "category":"Professional",
            "type":"Services"
        }
    ],
    "sg:phone":"+1 714 779 1260",
    "sg:postcode":"92870",
    "sg:province":"CA",
    "sg:tags":[
        "caterer"
    ],
    "sg:website":"www.SallyAnnCatering.com",
    "wof:name":"Sally Ann Catering",
    "wof:placetype":"venue"
},
  "geometry": {"coordinates":[-117.822998,33.863701],"type":"Point"}
}