{
  "type": "Feature",
  "properties": {
    "iso:country":"US",
    "sg:address":"12167 California St",
    "sg:city":"Yucaipa",
    "sg:classifiers":[
        {
            "category":"Organizations",
            "subcategory":"Community Association",
            "type":"Services"
        }
    ],
    "sg:phone":"+1 909 790 4030",
    "sg:postcode":"92399",
    "sg:province":"CA",
    "sg:tags":[
        "military"
    ],
    "wof:name":"American Legion",
    "wof:placetype":"venue"
},
  "geometry": {"coordinates":[-117.038746,34.031844],"type":"Point"}
}