{
  "type": "Feature",
  "properties": {
    "addr:full":"455 Oconnor Dr San Jose CA 95128",
    "addr:housenumber":"455",
    "addr:postcode":"95128",
    "addr:street":"Oconnor Dr",
    "iso:country":"US",
    "sg:address":"455 Oconnor Dr",
    "sg:city":"San Jose",
    "sg:classifiers":[
        {
            "category":"Health Services",
            "subcategory":"Doctor",
            "type":"Services"
        }
    ],
    "sg:phone":"+1 408 297 2833",
    "sg:postcode":"95128",
    "sg:province":"CA",
    "sg:tags":[
        "orthopedist"
    ],
    "wof:name":"Tran M Sherman MD",
    "wof:placetype":"venue"
},
  "geometry": {"coordinates":[-121.94000200000001,37.327301],"type":"Point"}
}