{
  "type": "Feature",
  "properties": {
    "addr:full":"2472 Dolan Way San Pablo CA 94806",
    "addr:housenumber":"2472",
    "addr:postcode":"94806",
    "addr:street":"Dolan Way",
    "iso:country":"US",
    "sg:address":"2472 Dolan Way",
    "sg:city":"San Pablo",
    "sg:classifiers":[
        {
            "category":"Shopping",
            "subcategory":"Clothing, Apparel, & Fashions",
            "type":"Retail Goods"
        }
    ],
    "sg:phone":"+1 510 724 4570",
    "sg:postcode":"94806",
    "sg:province":"CA",
    "sg:tags":[
        "tailor"
    ],
    "wof:name":"Pacita Sews",
    "wof:placetype":"venue"
},
  "geometry": {"coordinates":[-122.321018,37.992171],"type":"Point"}
}