{
  "type": "Feature",
  "properties": {
    "iso:country":"US",
    "sg:address":"26888 County Road 90",
    "sg:city":"Winters",
    "sg:classifiers":[
        {
            "category":"Manufacturing",
            "subcategory":"Pet Food",
            "type":"Manufacturing & Wholesale Goods"
        }
    ],
    "sg:phone":"+1 530 795 5888",
    "sg:postcode":"95694",
    "sg:province":"CA",
    "sg:tags":[
        "hay"
    ],
    "wof:name":"Hay Kingdom Inc",
    "wof:placetype":"venue"
},
  "geometry": {"coordinates":[-121.953369,38.536172],"type":"Point"}
}