{
  "type": "Feature",
  "properties": {
    "addr:full":"4030 Birch St Newport Beach CA 92660",
    "addr:housenumber":"4030",
    "addr:postcode":"92660",
    "addr:street":"Birch St",
    "iso:country":"US",
    "sg:address":"4030 Birch St",
    "sg:city":"Newport Beach",
    "sg:classifiers":[
        {
            "category":"Professional",
            "subcategory":"Computer Services",
            "type":"Services"
        }
    ],
    "sg:phone":"+1 714 540 4430",
    "sg:postcode":"92660",
    "sg:province":"CA",
    "sg:tags":[
        "processing",
        "datum"
    ],
    "wof:name":"M S Data Svc Corp",
    "wof:placetype":"venue"
},
  "geometry": {"coordinates":[-117.86955500000001,33.664679],"type":"Point"}
}