{
  "type": "Feature",
  "properties": {
    "iso:country":"US",
    "sg:address":"1001 Appling Ave",
    "sg:city":"Placentia",
    "sg:classifiers":[
        {
            "category":"Professional",
            "type":"Services"
        }
    ],
    "sg:phone":"+1 714 993 2852",
    "sg:postcode":"92870",
    "sg:province":"CA",
    "wof:name":"P I Elderly",
    "wof:placetype":"venue"
},
  "geometry": {"coordinates":[-117.846756,33.894306],"type":"Point"}
}