{
  "type": "Feature",
  "properties": {
    "addr:full":"21016 White Pine Dr Tehachapi CA 93561",
    "addr:housenumber":"21016",
    "addr:postcode":"93561",
    "addr:street":"White Pine Dr",
    "iso:country":"US",
    "sg:address":"21016 White Pine Dr",
    "sg:city":"Tehachapi",
    "sg:classifiers":[
        {
            "category":"Building & Trades",
            "subcategory":"Construction",
            "type":"Services"
        }
    ],
    "sg:phone":"+1 661 718 2268",
    "sg:postcode":"93561",
    "sg:province":"CA",
    "sg:tags":[
        "resurfacing",
        "laying",
        "refinishing",
        "floor"
    ],
    "wof:name":"Travis Pillar & Sons Hardwood",
    "wof:placetype":"venue"
},
  "geometry": {"coordinates":[-118.50823800000001,35.154616],"type":"Point"}
}