{
  "type": "Feature",
  "properties": {
    "addr:full":"191 Page Mill Dr San Jose CA 95111",
    "addr:housenumber":"191",
    "addr:postcode":"95111",
    "addr:street":"Page Mill Dr",
    "iso:country":"US",
    "sg:address":"191 Page Mill Dr",
    "sg:city":"San Jose",
    "sg:classifiers":[
        {
            "category":"Professional",
            "type":"Services"
        }
    ],
    "sg:phone":"+1 650 697 4210",
    "sg:postcode":"95111",
    "sg:province":"CA",
    "wof:name":"Hoa KY Restaurant",
    "wof:placetype":"venue"
},
  "geometry": {"coordinates":[-121.811592,37.265251],"type":"Point"}
}