{
  "type": "Feature",
  "properties": {
    "addr:full":"20303 Candice Ct Santa Clarita CA 91351",
    "addr:housenumber":"20303",
    "addr:postcode":"91351",
    "addr:street":"Candice Ct",
    "iso:country":"US",
    "sg:address":"20303 Candice Ct",
    "sg:city":"Santa Clarita",
    "sg:classifiers":[
        {
            "category":"Education",
            "subcategory":"Special Training",
            "type":"Public Place"
        }
    ],
    "sg:phone":"+1 661 252 1867",
    "sg:postcode":"91351",
    "sg:province":"CA",
    "sg:tags":[
        "program"
    ],
    "wof:name":"Breath Of Life Cpr Training",
    "wof:placetype":"venue"
},
  "geometry": {"coordinates":[-118.49168899999999,34.410335],"type":"Point"}
}