{
  "type": "Feature",
  "properties": {
    "iso:country":"US",
    "sg:address":"3964 Missouri Flat Rd",
    "sg:city":"Placerville",
    "sg:classifiers":[
        {
            "category":"Banks & Credit Unions",
            "subcategory":"Bank",
            "type":"Services"
        }
    ],
    "sg:phone":"+1 530 621 2301",
    "sg:postcode":"95667",
    "sg:province":"CA",
    "wof:name":"Bank Of America",
    "wof:placetype":"venue"
},
  "geometry": {"coordinates":[-120.841815,38.712972],"type":"Point"}
}