{
  "type": "Feature",
  "properties": {
    "iso:country":"US",
    "sg:address":"3022 G St # 102",
    "sg:city":"Merced",
    "sg:classifiers":[
        {
            "category":"Insurance",
            "subcategory":"Hazard Insurance",
            "type":"Services"
        },
        {
            "category":"Insurance",
            "subcategory":"Insurance Agent",
            "type":"Services"
        },
        {
            "category":"Insurance",
            "subcategory":"Life Insurance",
            "type":"Services"
        },
        {
            "category":"Insurance",
            "subcategory":"Title Insurance",
            "type":"Services"
        }
    ],
    "sg:phone":"+1 209 383 5669",
    "sg:postcode":"95340",
    "sg:province":"CA",
    "sg:tags":[
        "auto",
        "commercial",
        "business",
        "homeowner"
    ],
    "sg:website":"http://www.farmersagent.com/jsapien/",
    "wof:name":"Joe Sapien - Farmers Insurance",
    "wof:placetype":"venue"
},
  "geometry": {"coordinates":[-120.469264,37.31583],"type":"Point"}
}