{
  "type": "Feature",
  "properties": {
    "iso:country":"US",
    "sg:address":"10174 Mason Ave",
    "sg:city":"Chatsworth",
    "sg:classifiers":[
        {
            "category":"Restaurant",
            "type":"Food & Drink"
        }
    ],
    "sg:phone":"+1 818 998 5504",
    "sg:postcode":"91311",
    "sg:province":"CA",
    "wof:name":"Cultured Taste",
    "wof:placetype":"venue"
},
  "geometry": {"coordinates":[-118.579842,34.254968],"type":"Point"}
}