{
  "type": "Feature",
  "properties": {
    "addr:full":"7 Ashley Ave Santa Barbara CA 93103",
    "addr:housenumber":"7",
    "addr:postcode":"93103",
    "addr:street":"Ashley Ave",
    "iso:country":"US",
    "sg:address":"7 Ashley Ave",
    "sg:city":"Santa Barbara",
    "sg:classifiers":[
        {
            "category":"Health Services",
            "subcategory":"Doctor",
            "type":"Services"
        }
    ],
    "sg:phone":"+1 805 962 1237",
    "sg:postcode":"93103",
    "sg:province":"CA",
    "sg:tags":[
        "dentist"
    ],
    "wof:name":"Jeff Peppard DDS",
    "wof:placetype":"venue"
},
  "geometry": {"coordinates":[-119.67876099999999,34.420668],"type":"Point"}
}