{
  "type": "Feature",
  "properties": {
    "addr:full":"5245 Mission Oaks Blvd Camarillo CA 93012",
    "addr:housenumber":"5245",
    "addr:postcode":"93012",
    "addr:street":"Mission Oaks Blvd",
    "iso:country":"US",
    "sg:address":"5245 Mission Oaks Blvd",
    "sg:city":"Camarillo",
    "sg:classifiers":[
        {
            "category":"Personal",
            "subcategory":"Beauty Salon",
            "type":"Services"
        }
    ],
    "sg:phone":"+1 805 389 6748",
    "sg:postcode":"93012",
    "sg:province":"CA",
    "wof:name":"City Cuts",
    "wof:placetype":"venue"
},
  "geometry": {"coordinates":[-118.99729000000001,34.228686],"type":"Point"}
}