{
  "type": "Feature",
  "properties": {
    "iso:country":"US",
    "sg:address":"187 Hillcrest Ln",
    "sg:city":"Ramona",
    "sg:classifiers":[
        {
            "category":"Building & Trades",
            "subcategory":"Plumbing",
            "type":"Services"
        }
    ],
    "sg:phone":"+1 858 486 2590",
    "sg:postcode":"92065",
    "sg:province":"CA",
    "sg:tags":[
        "conditioning",
        "air",
        "system",
        "contractor"
    ],
    "wof:name":"Acuna's Polar Aire",
    "wof:placetype":"venue"
},
  "geometry": {"coordinates":[-116.85179100000001,33.041856],"type":"Point"}
}