{
  "type": "Feature",
  "properties": {
    "addr:full":"101 4th St San Francisco CA 94103",
    "addr:housenumber":"101",
    "addr:postcode":"94103",
    "addr:street":"4Th St",
    "iso:country":"US",
    "sg:address":"101 4th St",
    "sg:city":"San Francisco",
    "sg:classifiers":[
        {
            "category":"Food & Beverages",
            "subcategory":"Farmers Market",
            "type":"Retail Goods"
        }
    ],
    "sg:phone":"+1 510 547 2358",
    "sg:postcode":"94103",
    "sg:province":"CA",
    "sg:website":"www.islandearthfarmersmarket.org/",
    "wof:name":"Island Earth Farmers Market",
    "wof:placetype":"venue"
},
  "geometry": {"coordinates":[-122.40418699999999,37.784436],"type":"Point"}
}