{
  "type": "Feature",
  "properties": {
    "addr:full":"5026 Starfish Way San Diego CA 92154",
    "addr:housenumber":"5026",
    "addr:postcode":"92154",
    "addr:street":"Starfish Way",
    "iso:country":"US",
    "sg:address":"5026 Starfish Way",
    "sg:city":"San Diego",
    "sg:classifiers":[
        {
            "category":"Professional",
            "type":"Services"
        }
    ],
    "sg:phone":"+1 858 586 6432",
    "sg:postcode":"92154",
    "sg:province":"CA",
    "sg:tags":[
        "establishment"
    ],
    "wof:name":"Ocean Crest Sales",
    "wof:placetype":"venue"
},
  "geometry": {"coordinates":[-117.025035,32.578796],"type":"Point"}
}