{
  "type": "Feature",
  "properties": {
    "iso:country":"US",
    "sg:address":"8977 Glenoaks Blvd",
    "sg:city":"Sun Valley",
    "sg:classifiers":[
        {
            "category":"Building & Trades",
            "subcategory":"Construction",
            "type":"Services"
        }
    ],
    "sg:phone":"+1 818 771 1900",
    "sg:postcode":"91352",
    "sg:province":"CA",
    "sg:tags":[
        "marking",
        "maintenance",
        "parking"
    ],
    "sg:website":"www.curcioenterprises.com",
    "wof:name":"Curcio Enterprises Inc",
    "wof:placetype":"venue"
},
  "geometry": {"coordinates":[-118.369091,34.232198],"type":"Point"}
}