{
  "type": "Feature",
  "properties": {
    "addr:full":"541 Jefferson Ave Redwood City CA 94063",
    "addr:housenumber":"541",
    "addr:postcode":"94063",
    "addr:street":"Jefferson Ave",
    "iso:country":"US",
    "sg:address":"541 Jefferson Ave",
    "sg:city":"Redwood City",
    "sg:classifiers":[
        {
            "category":"Professional",
            "subcategory":"Secretarial Services",
            "type":"Services"
        }
    ],
    "sg:phone":"+1 650 366 3008",
    "sg:postcode":"94063",
    "sg:province":"CA",
    "sg:tags":[
        "convention",
        "court",
        "reporter"
    ],
    "sg:website":"www.for-the-record.com",
    "wof:name":"Kelty & Scott",
    "wof:placetype":"venue"
},
  "geometry": {"coordinates":[-122.228272,37.4889],"type":"Point"}
}