{
  "type": "Feature",
  "properties": {
    "sfgov:dept":"7",
    "sfgov:deptname":"SF Unified School District (SFUSD)",
    "sfgov:facility_i":"0000003259",
    "sfgov:school_typ":"Elementary",
    "wof:categories":[
        "education_and_religion:education=school"
    ],
    "wof:name":"Hillcrest Elementary School",
    "wof:placetype":"venue"
},
  "geometry": {"coordinates":[-122.41886225608178,37.72882231144026],"type":"Point"}
}