{
  "type": "Feature",
  "properties": {
    "iso:country":"US",
    "sg:address":"1110 Versailles Dr",
    "sg:city":"Hollister",
    "sg:classifiers":[
        {
            "category":"Banks & Credit Unions",
            "subcategory":"Bank",
            "type":"Services"
        }
    ],
    "sg:phone":"+1 831 636 1770",
    "sg:postcode":"95023",
    "sg:province":"CA",
    "sg:tags":[
        "loan",
        "real estate"
    ],
    "sg:website":"www.southvalleymortgage.com",
    "wof:name":"South Valley Mortgage Group",
    "wof:placetype":"venue"
},
  "geometry": {"coordinates":[-121.387292,36.843712],"type":"Point"}
}