{
  "type": "Feature",
  "properties": {
    "iso:country":"US",
    "sg:address":"733 S Main St",
    "sg:city":"Salinas",
    "sg:classifiers":[
        {
            "category":"Personal",
            "subcategory":"Massage",
            "type":"Services"
        }
    ],
    "sg:phone":"+1 831 754 6709",
    "sg:postcode":"93901",
    "sg:province":"CA",
    "wof:name":"Jing Foot Reflexology",
    "wof:placetype":"venue"
},
  "geometry": {"coordinates":[-121.65628700000001,36.666664],"type":"Point"}
}