{
  "type": "Feature",
  "properties": {
    "addr:full":"555 School St Pittsburg CA 94565",
    "addr:housenumber":"555",
    "addr:postcode":"94565",
    "addr:street":"School St",
    "iso:country":"US",
    "sg:address":"555 School St",
    "sg:city":"Pittsburg",
    "sg:classifiers":[
        {
            "category":"Professional",
            "type":"Services"
        }
    ],
    "sg:phone":"+1 925 432 4118",
    "sg:postcode":"94565",
    "sg:province":"CA",
    "wof:name":"Hume Center",
    "wof:placetype":"venue"
},
  "geometry": {"coordinates":[-121.879429,38.019937],"type":"Point"}
}