{
  "type": "Feature",
  "properties": {
    "addr:full":"370 Grand Ave Ste 1 Oakland CA 94610",
    "addr:housenumber":"370",
    "addr:postcode":"94610",
    "addr:street":"Grand Ave Ste 1",
    "iso:country":"US",
    "sg:address":"370 Grand Ave Ste 1",
    "sg:city":"Oakland",
    "sg:classifiers":[
        {
            "category":"Professional",
            "subcategory":"Lawyer & Legal Services",
            "type":"Services"
        }
    ],
    "sg:phone":"+1 510 465 6363",
    "sg:postcode":"94610",
    "sg:province":"CA",
    "wof:name":"Roberts Dennis-A Professional Corp Atty",
    "wof:placetype":"venue"
},
  "geometry": {"coordinates":[-122.254997,37.808899],"type":"Point"}
}