{
  "type": "Feature",
  "properties": {
    "addr:full":"24411 Ridge Route Dr Laguna Hills CA 92653",
    "addr:housenumber":"24411",
    "addr:postcode":"92653",
    "addr:street":"Ridge Route Dr",
    "iso:country":"US",
    "sg:address":"24411 Ridge Route Dr",
    "sg:city":"Laguna Hills",
    "sg:classifiers":[
        {
            "category":"Professional",
            "subcategory":"Lawyer & Legal Services",
            "type":"Services"
        }
    ],
    "sg:phone":"+1 949 452 0700",
    "sg:postcode":"92653",
    "sg:province":"CA",
    "wof:name":"Namanny Byrne & Owens Law Offices",
    "wof:placetype":"venue"
},
  "geometry": {"coordinates":[-117.734089,33.621238],"type":"Point"}
}