{
  "type": "Feature",
  "properties": {
    "addr:full":"203 E 2nd Ave Escondido CA 92025",
    "addr:housenumber":"203",
    "addr:postcode":"92025",
    "addr:street":"E 2Nd Ave",
    "iso:country":"US",
    "sg:address":"203 E 2nd Ave",
    "sg:city":"Escondido",
    "sg:classifiers":[
        {
            "category":"Health Services",
            "subcategory":"Doctor",
            "type":"Services"
        }
    ],
    "sg:phone":"+1 760 743 4401",
    "sg:postcode":"92025",
    "sg:province":"CA",
    "sg:tags":[
        "clinic"
    ],
    "sg:website":"www.gambro.com",
    "wof:name":"Gambro Healthcare",
    "wof:placetype":"venue"
},
  "geometry": {"coordinates":[-117.078085,33.122031],"type":"Point"}
}