{
  "type": "Feature",
  "properties": {
    "addr:full":"19250 State Hwy 18 Apple Valley CA 92307",
    "addr:housenumber":"19250",
    "addr:postcode":"92307",
    "addr:street":"State Hwy 18",
    "iso:country":"US",
    "sg:address":"19250 State Hwy 18",
    "sg:city":"Apple Valley",
    "sg:classifiers":[
        {
            "category":"Personal",
            "type":"Services"
        }
    ],
    "sg:phone":"+1 760 246 1212",
    "sg:postcode":"92307",
    "sg:province":"CA",
    "sg:tags":[
        "hair",
        "replacement"
    ],
    "wof:name":"Kessee Chargie",
    "wof:placetype":"venue"
},
  "geometry": {"coordinates":[-117.243877,34.536891],"type":"Point"}
}