{
  "type": "Feature",
  "properties": {
    "iso:country":"US",
    "sg:address":"3970 Atlantic Ave",
    "sg:city":"Long Beach",
    "sg:classifiers":[
        {
            "category":"Banks & Credit Unions",
            "subcategory":"Bank",
            "type":"Services"
        }
    ],
    "sg:phone":"+1 562 989 3155",
    "sg:postcode":"90807",
    "sg:province":"CA",
    "sg:tags":[
        "loan",
        "real estate"
    ],
    "sg:website":"www.awfinancial.com",
    "wof:name":"A & W Financial",
    "wof:placetype":"venue"
},
  "geometry": {"coordinates":[-118.184924,33.829465],"type":"Point"}
}