{
  "type": "Feature",
  "properties": {
    "iso:country":"US",
    "sg:address":"619 13th St",
    "sg:city":"Modesto",
    "sg:classifiers":[
        {
            "category":"Social Services",
            "type":"Services"
        }
    ],
    "sg:phone":"+1 209 526 4224",
    "sg:postcode":"95354",
    "sg:province":"CA",
    "sg:tags":[
        "counselor",
        "marriage",
        "family"
    ],
    "wof:name":"Paul B Woodrum",
    "wof:placetype":"venue"
},
  "geometry": {"coordinates":[-120.993863,37.63953],"type":"Point"}
}