{
  "type": "Feature",
  "properties": {
    "addr:full":"1925 Adobe Ave Corona CA 92882",
    "addr:housenumber":"1925",
    "addr:postcode":"92882",
    "addr:street":"Adobe Ave",
    "iso:country":"US",
    "sg:address":"1925 Adobe Ave",
    "sg:city":"Corona",
    "sg:classifiers":[
        {
            "category":"Manufacturing",
            "subcategory":"Wood Products",
            "type":"Manufacturing & Wholesale Goods"
        }
    ],
    "sg:phone":"+1 951 735 4018",
    "sg:postcode":"92882",
    "sg:province":"CA",
    "sg:tags":[
        "mfg"
    ],
    "wof:name":"Wood n Things",
    "wof:placetype":"venue"
},
  "geometry": {"coordinates":[-117.611133,33.860215],"type":"Point"}
}