{
  "type": "Feature",
  "properties": {
    "addr:full":"25881 Pso de Juanita San Juan Capistrano CA 92675",
    "addr:postcode":"25881;92675",
    "iso:country":"US",
    "sg:address":"25881 Pso de Juanita",
    "sg:city":"San Juan Capistrano",
    "sg:classifiers":[
        {
            "category":"Professional",
            "subcategory":"Management & Consulting",
            "type":"Services"
        }
    ],
    "sg:phone":"+1 949 493 1563",
    "sg:postcode":"92675",
    "sg:province":"CA",
    "sg:tags":[
        "retail",
        "direct",
        "sales"
    ],
    "wof:name":"Medical Specialty Technol",
    "wof:placetype":"venue"
},
  "geometry": {"coordinates":[-117.678016,33.497043],"type":"Point"}
}