{
  "type": "Feature",
  "properties": {
    "iso:country":"US",
    "sg:address":"42809 Rd 128",
    "sg:city":"Orosi",
    "sg:classifiers":[
        {
            "category":"Wholesale",
            "subcategory":"Fruits & Vegetables",
            "type":"Manufacturing & Wholesale Goods"
        }
    ],
    "sg:phone":"+1 559 528 9314",
    "sg:postcode":"93647",
    "sg:province":"CA",
    "sg:tags":[
        "shipper"
    ],
    "wof:name":"Rising C Ranches",
    "wof:placetype":"venue"
},
  "geometry": {"coordinates":[-119.28716300000001,36.573307],"type":"Point"}
}