{
  "type": "Feature",
  "properties": {
    "iso:country":"US",
    "sg:address":"77 Otis St",
    "sg:city":"San Francisco",
    "sg:classifiers":[
        {
            "category":"Travel",
            "subcategory":"Travel Agent",
            "type":"Entertainment"
        }
    ],
    "sg:phone":"+1 415 255 6946",
    "sg:postcode":"94103",
    "sg:province":"CA",
    "sg:tags":[
        "tours",
        "promoter"
    ],
    "wof:name":"Tours Are Us",
    "wof:placetype":"venue"
},
  "geometry": {"coordinates":[-122.42000299999999,37.772006],"type":"Point"}
}