{
  "type": "Feature",
  "properties": {
    "addr:full":"860 Brookdale Ave La Habra CA 90631",
    "addr:housenumber":"860",
    "addr:postcode":"90631",
    "addr:street":"Brookdale Ave",
    "iso:country":"US",
    "sg:address":"860 Brookdale Ave",
    "sg:city":"La Habra",
    "sg:classifiers":[
        {
            "category":"Manufacturing",
            "subcategory":"Tools & Machinery",
            "type":"Manufacturing & Wholesale Goods"
        }
    ],
    "sg:phone":"+1 562 945 7717",
    "sg:postcode":"90631",
    "sg:province":"CA",
    "sg:tags":[
        "machine",
        "mfg"
    ],
    "wof:name":"C B S Machinery",
    "wof:placetype":"venue"
},
  "geometry": {"coordinates":[-117.93884,33.943287],"type":"Point"}
}