{
  "type": "Feature",
  "properties": {
    "iso:country":"US",
    "sg:address":"1141 Old Woman Springs Rd",
    "sg:city":"Yucca Valley",
    "sg:classifiers":[
        {
            "category":"Restaurant",
            "type":"Food & Drink"
        }
    ],
    "sg:phone":"+1 760 364 2010",
    "sg:postcode":"92284",
    "sg:province":"CA",
    "wof:name":"Hitching Post Coffee Shop",
    "wof:placetype":"venue"
},
  "geometry": {"coordinates":[-116.439542,34.232658],"type":"Point"}
}