{
  "type": "Feature",
  "properties": {
    "addr:full":"3905 Convoy St San Diego CA 92111",
    "addr:housenumber":"3905",
    "addr:postcode":"92111",
    "addr:street":"Convoy St",
    "iso:country":"US",
    "sg:address":"3905 Convoy St",
    "sg:city":"San Diego",
    "sg:classifiers":[
        {
            "category":"Retail",
            "subcategory":"Auto Repair",
            "type":"Services"
        }
    ],
    "sg:phone":"+1 858 565 8125",
    "sg:postcode":"92111",
    "sg:province":"CA",
    "sg:tags":[
        "transmission"
    ],
    "wof:name":"AAMCO Transmissions",
    "wof:placetype":"venue"
},
  "geometry": {"coordinates":[-117.15473,32.81706],"type":"Point"}
}