{
  "type": "Feature",
  "properties": {
    "addr:full":"517 Taylor Ave Alameda CA 94501",
    "addr:housenumber":"517",
    "addr:postcode":"94501",
    "addr:street":"Taylor Ave",
    "iso:country":"US",
    "sg:address":"517 Taylor Ave",
    "sg:city":"Alameda",
    "sg:classifiers":[
        {
            "category":"Building & Trades",
            "subcategory":"Construction",
            "type":"Services"
        }
    ],
    "sg:phone":"+1 510 865 6510",
    "sg:postcode":"94501",
    "sg:province":"CA",
    "sg:tags":[
        "sanding",
        "floor"
    ],
    "wof:name":"West Side Flooring",
    "wof:placetype":"venue"
},
  "geometry": {"coordinates":[-122.28242,37.772681],"type":"Point"}
}