{
  "type": "Feature",
  "properties": {
    "iso:country":"US",
    "sg:address":"134 Wolfe Grade",
    "sg:city":"Kentfield",
    "sg:classifiers":[
        {
            "category":"Professional",
            "subcategory":"Business Services",
            "type":"Services"
        }
    ],
    "sg:phone":"+1 415 461 4667",
    "sg:postcode":"94904",
    "sg:province":"CA",
    "wof:name":"Joel Chase",
    "wof:placetype":"venue"
},
  "geometry": {"coordinates":[-122.533224,37.959417],"type":"Point"}
}