{
  "type": "Feature",
  "properties": {
    "addr:full":"14928 Larch Ave Lawndale CA 90260",
    "addr:housenumber":"14928",
    "addr:postcode":"ca 90260",
    "addr:street":"Larch Ave",
    "iso:country":"US",
    "sg:address":"14928 Larch Ave",
    "sg:city":"Lawndale",
    "sg:classifiers":[
        {
            "category":"Retail",
            "subcategory":"Animal Services",
            "type":"Services"
        }
    ],
    "sg:phone":"+1 310 970 9663",
    "sg:postcode":"90260",
    "sg:province":"CA",
    "sg:tags":[
        "pet",
        "boarding",
        "sitting"
    ],
    "wof:name":"Danny's Ark",
    "wof:placetype":"venue"
},
  "geometry": {"coordinates":[-118.350177,33.894898],"type":"Point"}
}