{
  "type": "Feature",
  "properties": {
    "addr:full":"3145 Geary Blvd. #112 San Francisco CA 94118",
    "addr:housenumber":"3145",
    "addr:postcode":"94118",
    "addr:street":"Geary Blvd. # 112",
    "iso:country":"US",
    "sg:address":"3145 Geary Blvd. #112",
    "sg:city":"San Francisco",
    "sg:classifiers":[
        {
            "category":"Professional",
            "type":"Services"
        },
        {
            "category":"Personal",
            "type":"Services"
        }
    ],
    "sg:phone":"+1 510 883 9386",
    "sg:postcode":"94118",
    "sg:province":"CA",
    "sg:tags":[
        "party",
        "planning",
        "event",
        "caterer"
    ],
    "sg:website":"chilipepperevents.com/",
    "wof:name":"Chilipepper Events",
    "wof:placetype":"venue"
},
  "geometry": {"coordinates":[-122.452853,37.781452],"type":"Point"}
}