{
  "type": "Feature",
  "properties": {
    "iso:country":"US",
    "sg:address":"1398 East Ave",
    "sg:city":"Chico",
    "sg:classifiers":[
        {
            "category":"Restaurant",
            "type":"Food & Drink"
        }
    ],
    "sg:menulink":"http://www.allmenus.com/ca/chico/149857-subway/menu/",
    "sg:phone":"+1 530 894 8757",
    "sg:postcode":"95926",
    "sg:province":"CA",
    "sg:tags":[
        "american",
        "sandwich"
    ],
    "wof:name":"Subway",
    "wof:placetype":"venue"
},
  "geometry": {"coordinates":[-121.820127,39.761453],"type":"Point"}
}