{
  "type": "Feature",
  "properties": {
    "addr:full":"300 Piedmont Ave San Bruno CA 94066",
    "addr:housenumber":"300",
    "addr:postcode":"94066",
    "addr:street":"Piedmont Ave",
    "iso:country":"US",
    "sg:address":"300 Piedmont Ave",
    "sg:city":"San Bruno",
    "sg:classifiers":[
        {
            "category":"Education",
            "subcategory":"School",
            "type":"Public Place"
        }
    ],
    "sg:phone":"+1 650 877 8377",
    "sg:postcode":"94066",
    "sg:province":"CA",
    "wof:name":"Peninsula High School",
    "wof:placetype":"venue"
},
  "geometry": {"coordinates":[-122.429996,37.609657],"type":"Point"}
}