{
  "type": "Feature",
  "properties": {
    "iso:country":"US",
    "sg:address":"730 S Hoover St",
    "sg:city":"Los Angeles",
    "sg:classifiers":[
        {
            "category":"Freight",
            "type":"Transportation"
        }
    ],
    "sg:phone":"+1 213 637 0327",
    "sg:postcode":"90005",
    "sg:province":"CA",
    "sg:tags":[
        "courier"
    ],
    "wof:name":"El Salvador Express",
    "wof:placetype":"venue"
},
  "geometry": {"coordinates":[-118.284198,34.059792],"type":"Point"}
}