{
  "type": "Feature",
  "properties": {
    "iso:country":"US",
    "sg:address":"845 Kennedy St",
    "sg:city":"Oakland",
    "sg:classifiers":[
        {
            "category":"Utilities",
            "subcategory":"Water",
            "type":"Services"
        },
        {
            "category":"Building & Trades",
            "subcategory":"Plumbing",
            "type":"Services"
        },
        {
            "category":"Home & Garden",
            "subcategory":"Building Materials",
            "type":"Retail Goods"
        },
        {
            "category":"Utilities",
            "subcategory":"Sewage",
            "type":"Services"
        },
        {
            "category":"Building & Trades",
            "subcategory":"Construction",
            "type":"Services"
        }
    ],
    "sg:phone":"+1 510 261 4713",
    "sg:postcode":"94606",
    "sg:province":"CA",
    "sg:tags":[
        "heater",
        "systems-cleaning",
        "tank",
        "septic",
        "excavation",
        "well",
        "plumber",
        "contractor",
        "pump",
        "sewer",
        "cleaning",
        "plumbing-drain",
        "drilling"
    ],
    "sg:website":"http://eastbay.citysearch.com/profile/external/42773738/oakland_ca/roto_rooter_plumbing_drain_service.html?publisher=yellowpages&reference_id=1&placement=ypwebsitemip",
    "wof:name":"Roto-Rooter Plumbing & Drain Service",
    "wof:placetype":"venue"
},
  "geometry": {"coordinates":[-122.237844,37.778288],"type":"Point"}
}