{
  "type": "Feature",
  "properties": {
    "addr:full":"450 S Oxnard Blvd Ste B Oxnard CA 93030",
    "addr:housenumber":"450",
    "addr:postcode":"93030",
    "addr:street":"S Oxnard Blvd Ste B",
    "iso:country":"US",
    "sg:address":"450 S Oxnard Blvd Ste B",
    "sg:city":"Oxnard",
    "sg:phone":"+1 805 486 5209",
    "sg:postcode":"93030",
    "sg:province":"CA",
    "wof:name":"A Good Thai & Peruvian",
    "wof:placetype":"venue"
},
  "geometry": {"coordinates":[-119.17733800000001,34.198153],"type":"Point"}
}