{
  "type": "Feature",
  "properties": {
    "addr:full":"2135 W Brownwood Ave Anaheim CA 92801",
    "addr:housenumber":"2135",
    "addr:postcode":"92801",
    "addr:street":"W Brownwood Ave",
    "iso:country":"US",
    "sg:address":"2135 W Brownwood Ave",
    "sg:city":"Anaheim",
    "sg:classifiers":[
        {
            "category":"Building & Trades",
            "subcategory":"Construction",
            "type":"Services"
        }
    ],
    "sg:phone":"+1 714 402 8337",
    "sg:postcode":"92801",
    "sg:province":"CA",
    "sg:tags":[
        "contractor"
    ],
    "wof:name":"T & A Concrete & Masonry",
    "wof:placetype":"venue"
},
  "geometry": {"coordinates":[-117.95490700000001,33.837176],"type":"Point"}
}