{
  "type": "Feature",
  "properties": {
    "addr:full":"12401 Woodley Ave Granada Hills CA 91344",
    "addr:housenumber":"12401",
    "addr:postcode":"91344",
    "addr:street":"Woodley Ave",
    "iso:country":"US",
    "sg:address":"12401 Woodley Ave",
    "sg:city":"Granada Hills",
    "sg:classifiers":[
        {
            "category":"Professional",
            "type":"Services"
        }
    ],
    "sg:phone":"+1 818 366 8171",
    "sg:postcode":"91344",
    "sg:province":"CA",
    "wof:name":"Jad N Adham",
    "wof:placetype":"venue"
},
  "geometry": {"coordinates":[-118.49570199999999,34.298193],"type":"Point"}
}