{
  "type": "Feature",
  "properties": {
    "iso:country":"US",
    "sg:address":"17721 Merridy St",
    "sg:city":"Northridge",
    "sg:classifiers":[
        {
            "category":"Wholesale",
            "subcategory":"Apparel",
            "type":"Manufacturing & Wholesale Goods"
        }
    ],
    "sg:phone":"+1 818 882 1577",
    "sg:postcode":"91325",
    "sg:province":"CA",
    "sg:tags":[
        "accessory"
    ],
    "wof:name":"PNikki-0",
    "wof:placetype":"venue"
},
  "geometry": {"coordinates":[-118.521646,34.252271],"type":"Point"}
}