{
  "type": "Feature",
  "properties": {
    "addr:full":"740 Ventura Blvd Camarillo CA 93010",
    "addr:housenumber":"740",
    "addr:postcode":"93010",
    "addr:street":"Ventura Blvd",
    "iso:country":"US",
    "sg:address":"740 Ventura Blvd",
    "sg:city":"Camarillo",
    "sg:classifiers":[
        {
            "category":"Shopping",
            "subcategory":"Department Store",
            "type":"Retail Goods"
        },
        {
            "category":"Shopping",
            "subcategory":"Clothing, Apparel, & Fashions",
            "type":"Retail Goods"
        },
        {
            "category":"Manufacturing",
            "subcategory":"Apparel",
            "type":"Manufacturing & Wholesale Goods"
        },
        {
            "category":"Shopping",
            "subcategory":"Baby Store",
            "type":"Retail Goods"
        }
    ],
    "sg:phone":"+1 805 484 5591",
    "sg:postcode":"93010",
    "sg:province":"CA",
    "sg:tags":[
        "apparel-wholesale",
        "infant",
        "clothing-men's-wholesale",
        "women's",
        "children's",
        "wear",
        "clothing",
        "manufacturer"
    ],
    "wof:name":"Diesel Camarillo",
    "wof:placetype":"venue"
},
  "geometry": {"coordinates":[-119.060349,34.21796],"type":"Point"}
}