{
  "type": "Feature",
  "properties": {
    "addr:full":"1625 Sweetwater Rd National City CA 91950",
    "addr:housenumber":"1625",
    "addr:postcode":"91950",
    "addr:street":"Sweetwater Rd",
    "iso:country":"US",
    "sg:address":"1625 Sweetwater Rd",
    "sg:city":"National City",
    "sg:classifiers":[
        {
            "category":"Health Services",
            "subcategory":"Doctor",
            "type":"Services"
        }
    ],
    "sg:phone":"+1 619 336 1588",
    "sg:postcode":"91950",
    "sg:province":"CA",
    "sg:tags":[
        "dentist"
    ],
    "wof:name":"Renato D Reyes DDS",
    "wof:placetype":"venue"
},
  "geometry": {"coordinates":[-117.083772,32.661225],"type":"Point"}
}