{
  "type": "Feature",
  "properties": {
    "addr:full":"345 Cam del Remedio Santa Barbara CA 93110",
    "addr:housenumber":"345",
    "addr:postcode":"93110",
    "addr:street":"Cam Del Remedio",
    "iso:country":"US",
    "sg:address":"345 Cam del Remedio",
    "sg:city":"Santa Barbara",
    "sg:classifiers":[
        {
            "category":"Government",
            "subcategory":"Office",
            "type":"Public Place"
        }
    ],
    "sg:phone":"+1 805 681 5390",
    "sg:postcode":"93110",
    "sg:province":"CA",
    "wof:name":"Santa Barbara Utilization Rvw",
    "wof:placetype":"venue"
},
  "geometry": {"coordinates":[-119.77956399999999,34.446215],"type":"Point"}
}