{
  "type": "Feature",
  "properties": {
    "iso:country":"US",
    "sg:address":"23600 Roscoe Blvd",
    "sg:city":"Canoga Park",
    "sg:classifiers":[
        {
            "category":"Personal",
            "type":"Services"
        }
    ],
    "sg:phone":"+1 818 346 7449",
    "sg:postcode":"91304",
    "sg:province":"CA",
    "sg:tags":[
        "chapel",
        "space",
        "venue",
        "event",
        "wedding"
    ],
    "wof:name":"Orcutt Ranch",
    "wof:placetype":"venue"
},
  "geometry": {"coordinates":[-118.64099899999999,34.219299],"type":"Point"}
}