{
  "type": "Feature",
  "properties": {
    "addr:full":"6630 1st St Forestville CA 95436",
    "addr:housenumber":"6630",
    "addr:postcode":"95436",
    "addr:street":"1St St",
    "iso:country":"US",
    "sg:address":"6630 1st St",
    "sg:city":"Forestville",
    "sg:classifiers":[
        {
            "category":"Building & Trades",
            "subcategory":"Construction",
            "type":"Services"
        }
    ],
    "sg:phone":"+1 707 887 1859",
    "sg:postcode":"95436",
    "sg:province":"CA",
    "sg:tags":[
        "industrial"
    ],
    "wof:name":"Sona Masala",
    "wof:placetype":"venue"
},
  "geometry": {"coordinates":[-122.892363,38.478534],"type":"Point"}
}