{
  "type": "Feature",
  "properties": {
    "iso:country":"US",
    "sg:address":"1324 Marsten Road",
    "sg:city":"Burlingame",
    "sg:classifiers":[
        {
            "category":"Building & Trades",
            "subcategory":"Plumbing",
            "type":"Services"
        }
    ],
    "sg:phone":"+1 650 344 9370",
    "sg:postcode":"94010",
    "sg:province":"CA",
    "wof:name":"Emerald Plumbing & Fire Protection",
    "wof:placetype":"venue"
},
  "geometry": {"coordinates":[-122.36385799999999,37.590633],"type":"Point"}
}