{
  "type": "Feature",
  "properties": {
    "iso:country":"US",
    "sg:address":"1133 Mission St",
    "sg:city":"South Pasadena",
    "sg:classifiers":[
        {
            "category":"Manufacturing",
            "subcategory":"Tools & Machinery",
            "type":"Manufacturing & Wholesale Goods"
        }
    ],
    "sg:phone":"+1 626 799 1178",
    "sg:postcode":"91030",
    "sg:province":"CA",
    "sg:tags":[
        "equipment",
        "electric"
    ],
    "wof:name":"Day Ray Products Inc Elec Mfrs",
    "wof:placetype":"venue"
},
  "geometry": {"coordinates":[-118.153275,34.115704],"type":"Point"}
}