{
  "type": "Feature",
  "properties": {
    "addr:full":"1557 Eugene Ct Yuba City CA 95993",
    "addr:housenumber":"1557",
    "addr:postcode":"95993",
    "addr:street":"Eugene Ct",
    "iso:country":"US",
    "sg:address":"1557 Eugene Ct",
    "sg:city":"Yuba City",
    "sg:classifiers":[
        {
            "category":"Professional",
            "subcategory":"Engineering",
            "type":"Services"
        }
    ],
    "sg:phone":"+1 530 671 1155",
    "sg:postcode":"95993",
    "sg:province":"CA",
    "sg:tags":[
        "engineer"
    ],
    "wof:name":"Altman General Engineering",
    "wof:placetype":"venue"
},
  "geometry": {"coordinates":[-121.69240600000001,39.150215],"type":"Point"}
}