{
  "type": "Feature",
  "properties": {
    "addr:full":"852 E Decatur Ave Fresno CA 93720",
    "addr:housenumber":"852",
    "addr:postcode":"93720",
    "addr:street":"E Decatur Ave",
    "iso:country":"US",
    "sg:address":"852 E Decatur Ave",
    "sg:city":"Fresno",
    "sg:classifiers":[
        {
            "category":"Home & Garden",
            "subcategory":"Building Materials",
            "type":"Retail Goods"
        }
    ],
    "sg:phone":"+1 559 435 6438",
    "sg:postcode":"93720",
    "sg:province":"CA",
    "wof:name":"Good Glass",
    "wof:placetype":"venue"
},
  "geometry": {"coordinates":[-119.767916,36.847698],"type":"Point"}
}