{
  "type": "Feature",
  "properties": {
    "addr:full":"11642 Knott St Ste 4 Garden Grove CA 92841",
    "addr:housenumber":"11642",
    "addr:postcode":"92841",
    "addr:street":"Knott St Ste 4",
    "iso:country":"US",
    "sg:address":"11642 Knott St Ste 4",
    "sg:city":"Garden Grove",
    "sg:classifiers":[
        {
            "category":"Professional",
            "subcategory":"Computer Services",
            "type":"Services"
        }
    ],
    "sg:phone":"+1 714 893 1630",
    "sg:postcode":"92841",
    "sg:province":"CA",
    "sg:tags":[
        "repair"
    ],
    "wof:name":"Versatile N S",
    "wof:placetype":"venue"
},
  "geometry": {"coordinates":[-118.09249800000001,33.792967],"type":"Point"}
}