{
  "type": "Feature",
  "properties": {
    "addr:full":"1901 Wyatt Dr Santa Clara CA 95054",
    "addr:housenumber":"1901",
    "addr:postcode":"95054",
    "addr:street":"Wyatt Dr",
    "iso:country":"US",
    "sg:address":"1901 Wyatt Dr",
    "sg:city":"Santa Clara",
    "sg:classifiers":[
        {
            "category":"Wholesale",
            "subcategory":"Electrical",
            "type":"Manufacturing & Wholesale Goods"
        },
        {
            "category":"Manufacturing",
            "subcategory":"Electronics",
            "type":"Manufacturing & Wholesale Goods"
        }
    ],
    "sg:phone":"+1 408 988 1408",
    "sg:postcode":"95054",
    "sg:province":"CA",
    "sg:tags":[
        "semiconductor",
        "electronic",
        "devices"
    ],
    "sg:website":"www.kingpak.com",
    "wof:name":"Kingpak Technology Inc",
    "wof:placetype":"venue"
},
  "geometry": {"coordinates":[-121.958854,37.388977],"type":"Point"}
}