{
  "type": "Feature",
  "properties": {
    "iso:country":"US",
    "sg:address":"1116 Summer Ave",
    "sg:city":"Burlingame",
    "sg:classifiers":[
        {
            "category":"Professional",
            "subcategory":"Art Services",
            "type":"Services"
        }
    ],
    "sg:phone":"+1 650 344 3643",
    "sg:postcode":"94010",
    "sg:province":"CA",
    "sg:tags":[
        "graphic",
        "designer"
    ],
    "wof:name":"Claudia Steenberg Design",
    "wof:placetype":"venue"
},
  "geometry": {"coordinates":[-122.367686,37.588274],"type":"Point"}
}