{
  "type": "Feature",
  "properties": {
    "iso:country":"US",
    "sg:address":"122 E Main St",
    "sg:city":"Grass Valley",
    "sg:classifiers":[
        {
            "category":"Restaurant",
            "type":"Food & Drink"
        }
    ],
    "sg:phone":"+1 530 273 4622",
    "sg:postcode":"95945",
    "sg:province":"CA",
    "sg:tags":[
        "pizza"
    ],
    "wof:name":"Frank's Pizza Pan",
    "wof:placetype":"venue"
},
  "geometry": {"coordinates":[-121.061712,39.219285],"type":"Point"}
}