{
  "type": "Feature",
  "properties": {
    "addr:full":"447 Hillcrest Rd San Carlos CA 94070",
    "addr:housenumber":"447",
    "addr:postcode":"94070",
    "addr:street":"Hillcrest Rd",
    "iso:country":"US",
    "sg:address":"447 Hillcrest Rd",
    "sg:city":"San Carlos",
    "sg:classifiers":[
        {
            "category":"Banks & Credit Unions",
            "subcategory":"Bank",
            "type":"Services"
        }
    ],
    "sg:phone":"+1 650 598 0384",
    "sg:postcode":"94070",
    "sg:province":"CA",
    "sg:tags":[
        "broker",
        "mortgage"
    ],
    "wof:name":"Expert Financial",
    "wof:placetype":"venue"
},
  "geometry": {"coordinates":[-122.269105,37.50425],"type":"Point"}
}