{
  "type": "Feature",
  "properties": {
    "iso:country":"US",
    "sg:address":"2428 W 54th Street",
    "sg:city":"Los Angeles",
    "sg:classifiers":[
        {
            "category":"Shopping",
            "subcategory":"Computers & Home Electronics",
            "type":"Retail Goods"
        }
    ],
    "sg:phone":"+1 323 291 3838",
    "sg:postcode":"90043",
    "sg:province":"CA",
    "wof:name":"Frankie's T V Service",
    "wof:placetype":"venue"
},
  "geometry": {"coordinates":[-118.320228,33.993312],"type":"Point"}
}