{
  "type": "Feature",
  "properties": {
    "iso:country":"US",
    "sg:address":"5750 Wilshire Blvd",
    "sg:city":"Los Angeles",
    "sg:classifiers":[
        {
            "category":"Education",
            "subcategory":"Library",
            "type":"Public Place"
        }
    ],
    "sg:phone":"+1 323 525 3388",
    "sg:postcode":"90036",
    "sg:province":"CA",
    "sg:website":"www.goethe.de/ins/us/los/enindex...",
    "wof:name":"Goethe Institute of Los Angeles",
    "wof:placetype":"venue"
},
  "geometry": {"coordinates":[-118.35422199999999,34.061557],"type":"Point"}
}