{
  "type": "Feature",
  "properties": {
    "addr:full":"510 N Main St Manteca CA 95336",
    "addr:housenumber":"510",
    "addr:postcode":"95336",
    "addr:street":"N Main St",
    "iso:country":"US",
    "sg:address":"510 N Main St",
    "sg:city":"Manteca",
    "sg:classifiers":[
        {
            "category":"Cinema",
            "subcategory":"Movie Rental",
            "type":"Entertainment"
        }
    ],
    "sg:phone":"+1 209 825 5470",
    "sg:postcode":"95336",
    "sg:province":"CA",
    "sg:tags":[
        "leasing",
        "video",
        "disc",
        "tape"
    ],
    "sg:website":"www.blockbuster.com",
    "wof:name":"Blockbuster Video",
    "wof:placetype":"venue"
},
  "geometry": {"coordinates":[-121.21680499999999,37.806332],"type":"Point"}
}