{
  "type": "Feature",
  "properties": {
    "iso:country":"US",
    "sg:address":"585 Low Gap Rd",
    "sg:city":"Ukiah",
    "sg:classifiers":[
        {
            "category":"Government",
            "subcategory":"Office",
            "type":"Public Place"
        }
    ],
    "sg:phone":"+1 707 463 4434",
    "sg:postcode":"95482",
    "sg:province":"CA",
    "wof:name":"Mendocino County Juvenile Hall",
    "wof:placetype":"venue"
},
  "geometry": {"coordinates":[-123.216764,39.16038],"type":"Point"}
}