{
  "type": "Feature",
  "properties": {
    "addr:full":"5700 Sepulveda Blvd Culver City CA 90230",
    "addr:housenumber":"5700",
    "addr:postcode":"90230",
    "addr:street":"Sepulveda Blvd",
    "iso:country":"US",
    "sg:address":"5700 Sepulveda Blvd",
    "sg:city":"Culver City",
    "sg:classifiers":[
        {
            "category":"Banks & Credit Unions",
            "subcategory":"Bank",
            "type":"Services"
        }
    ],
    "sg:phone":"+1 800 274 6660",
    "sg:postcode":"90230",
    "sg:province":"CA",
    "wof:name":"Citibank West F S B",
    "wof:placetype":"venue"
},
  "geometry": {"coordinates":[-118.394997,33.988602],"type":"Point"}
}