{
  "type": "Feature",
  "properties": {
    "iso:country":"US",
    "sg:address":"35450 W Yermo Rd",
    "sg:city":"Yermo",
    "sg:phone":"+1 760 254 1148",
    "sg:postcode":"92398",
    "sg:province":"CA",
    "wof:name":"Penny's Diner",
    "wof:placetype":"venue"
},
  "geometry": {"coordinates":[-116.892742,34.901241],"type":"Point"}
}