{
  "type": "Feature",
  "properties": {
    "iso:country":"US",
    "sg:address":"23191 Peralta Dr",
    "sg:city":"Laguna Hills",
    "sg:classifiers":[
        {
            "category":"Manufacturing",
            "subcategory":"Rubber & Plastics",
            "type":"Manufacturing & Wholesale Goods"
        }
    ],
    "sg:phone":"+1 949 768 8985",
    "sg:postcode":"92653",
    "sg:province":"CA",
    "sg:tags":[
        "product"
    ],
    "wof:name":"Cooksey Corp",
    "wof:placetype":"venue"
},
  "geometry": {"coordinates":[-117.724993,33.624511],"type":"Point"}
}