{
  "type": "Feature",
  "properties": {
    "addr:full":"610 W 5th St Antioch CA 94509",
    "addr:housenumber":"610",
    "addr:postcode":"ca 94509",
    "addr:street":"W 5Th St",
    "iso:country":"US",
    "sg:address":"610 W 5th St",
    "sg:city":"Antioch",
    "sg:classifiers":[
        {
            "category":"Professional",
            "subcategory":"Accounting & Tax Preparation",
            "type":"Services"
        }
    ],
    "sg:phone":"+1 925 757 4808",
    "sg:postcode":"94509",
    "sg:province":"CA",
    "sg:tags":[
        "accountant"
    ],
    "wof:name":"Millias Accountancy",
    "wof:placetype":"venue"
},
  "geometry": {"coordinates":[-121.814921,38.014838],"type":"Point"}
}