{
  "type": "Feature",
  "properties": {
    "iso:country":"US",
    "sg:address":"640 Las Posas Rd",
    "sg:city":"Camarillo",
    "sg:classifiers":[
        {
            "category":"Retail",
            "subcategory":"Laundry & Dry Cleaning",
            "type":"Services"
        }
    ],
    "sg:phone":"+1 805 388 0352",
    "sg:postcode":"93010",
    "sg:province":"CA",
    "wof:name":"Best Cleaners Camarillo",
    "wof:placetype":"venue"
},
  "geometry": {"coordinates":[-119.06199599999999,34.230801],"type":"Point"}
}