{
  "type": "Feature",
  "properties": {
    "addr:full":"1829 Roanoke Ave Sacramento CA 95838",
    "addr:housenumber":"1829",
    "addr:postcode":"95838",
    "addr:street":"Roanoke Ave",
    "iso:country":"US",
    "sg:address":"1829 Roanoke Ave",
    "sg:city":"Sacramento",
    "sg:classifiers":[
        {
            "category":"Building & Trades",
            "subcategory":"Construction",
            "type":"Services"
        }
    ],
    "sg:phone":"+1 916 927 1613",
    "sg:postcode":"95838",
    "sg:province":"CA",
    "sg:tags":[
        "roofing",
        "contractor"
    ],
    "wof:name":"A-1 Affordable Roofing",
    "wof:placetype":"venue"
},
  "geometry": {"coordinates":[-121.42397099999999,38.634682],"type":"Point"}
}