{
  "type": "Feature",
  "properties": {
    "addr:full":"561 Almond Ct Kerman CA 93630",
    "addr:housenumber":"561",
    "addr:postcode":"93630",
    "addr:street":"Almond Ct",
    "iso:country":"US",
    "sg:address":"561 Almond Ct",
    "sg:city":"Kerman",
    "sg:classifiers":[
        {
            "category":"Shopping",
            "subcategory":"Beauty & Cosmetics",
            "type":"Retail Goods"
        }
    ],
    "sg:phone":"+1 559 846 9133",
    "sg:postcode":"93630",
    "sg:province":"CA",
    "sg:tags":[
        "perfume",
        "salons-equipment",
        "supply"
    ],
    "wof:name":"Permanent Cosmetics By Johnnie",
    "wof:placetype":"venue"
},
  "geometry": {"coordinates":[-120.07476800000001,36.726052],"type":"Point"}
}