{
  "type": "Feature",
  "properties": {
    "iso:country":"US",
    "sg:address":"5405 Alton Pkwy",
    "sg:city":"Irvine",
    "sg:classifiers":[
        {
            "category":"Wholesale",
            "subcategory":"Furniture",
            "type":"Manufacturing & Wholesale Goods"
        }
    ],
    "sg:phone":"+1 949 786 1358",
    "sg:postcode":"92604",
    "sg:province":"CA",
    "wof:name":"Diversified Office Systems",
    "wof:placetype":"venue"
},
  "geometry": {"coordinates":[-117.789793,33.670629],"type":"Point"}
}