{
  "type": "Feature",
  "properties": {
    "addr:full":"1901 Camino Vida Roble Carlsbad CA 92008",
    "addr:housenumber":"1901",
    "addr:postcode":"92008",
    "addr:street":"Camino Vida Roble",
    "iso:country":"US",
    "sg:address":"1901 Camino Vida Roble",
    "sg:city":"Carlsbad",
    "sg:classifiers":[
        {
            "category":"Professional",
            "subcategory":"Accounting & Tax Preparation",
            "type":"Services"
        }
    ],
    "sg:phone":"+1 760 602 0952",
    "sg:postcode":"92008",
    "sg:province":"CA",
    "sg:tags":[
        "accountant"
    ],
    "wof:name":"Hamner & Associates Cpa's",
    "wof:placetype":"venue"
},
  "geometry": {"coordinates":[-117.288906,33.123412],"type":"Point"}
}