{
  "type": "Feature",
  "properties": {
    "iso:country":"US",
    "sg:address":"3862 Katella Ave Ste A",
    "sg:city":"Los Alamitos",
    "sg:classifiers":[
        {
            "category":"Health Services",
            "subcategory":"Dentist",
            "type":"Services"
        }
    ],
    "sg:phone":"+1 562 795 5190",
    "sg:postcode":"90721",
    "sg:province":"CA",
    "wof:name":"P.D. Tran, DDS",
    "wof:placetype":"venue"
},
  "geometry": {"coordinates":[-118.065804,33.803024],"type":"Point"}
}