{
  "type": "Feature",
  "properties": {
    "addr:full":"220 Trevethan Ave Santa Cruz CA 95062",
    "addr:housenumber":"220",
    "addr:postcode":"95062",
    "addr:street":"Trevethan Ave",
    "iso:country":"US",
    "sg:address":"220 Trevethan Ave",
    "sg:city":"Santa Cruz",
    "sg:classifiers":[
        {
            "category":"Building & Trades",
            "subcategory":"Construction",
            "type":"Services"
        }
    ],
    "sg:phone":"+1 831 469 7252",
    "sg:postcode":"95062",
    "sg:province":"CA",
    "sg:tags":[
        "contractor",
        "mfg"
    ],
    "wof:name":"Empire Tile Works",
    "wof:placetype":"venue"
},
  "geometry": {"coordinates":[-122.000276,36.984756],"type":"Point"}
}