{
  "type": "Feature",
  "properties": {
    "addr:full":"1496 Maxine Ave San Jose CA 95125",
    "addr:housenumber":"1496",
    "addr:postcode":"95125",
    "addr:street":"Maxine Ave",
    "iso:country":"US",
    "sg:address":"1496 Maxine Ave",
    "sg:city":"San Jose",
    "sg:classifiers":[
        {
            "category":"Shopping",
            "subcategory":"Computers & Home Electronics",
            "type":"Retail Goods"
        }
    ],
    "sg:phone":"+1 408 978 3858",
    "sg:postcode":"95125",
    "sg:province":"CA",
    "sg:tags":[
        "audio"
    ],
    "wof:name":"Visual Matter",
    "wof:placetype":"venue"
},
  "geometry": {"coordinates":[-121.89797299999999,37.28335],"type":"Point"}
}