{
  "type": "Feature",
  "properties": {
    "addr:full":"747 W Katella Ave Ste 106 Orange CA 92867",
    "addr:housenumber":"747",
    "addr:postcode":"92867",
    "addr:street":"W Katella Ave Ste 106",
    "iso:country":"US",
    "sg:address":"747 W Katella Ave Ste 106",
    "sg:city":"Orange",
    "sg:classifiers":[
        {
            "category":"Cinema",
            "subcategory":"Movie Theater",
            "type":"Entertainment"
        }
    ],
    "sg:phone":"+1 714 450 1016",
    "sg:postcode":"92867",
    "sg:province":"CA",
    "wof:name":"Into Very In Movies",
    "wof:placetype":"venue"
},
  "geometry": {"coordinates":[-117.861,33.809101],"type":"Point"}
}