{
  "type": "Feature",
  "properties": {
    "addr:full":"5774 N Lead Ave Fresno CA 93711",
    "addr:housenumber":"5774",
    "addr:postcode":"93711",
    "addr:street":"N Lead Ave",
    "iso:country":"US",
    "sg:address":"5774 N Lead Ave",
    "sg:city":"Fresno",
    "sg:classifiers":[
        {
            "category":"Personal",
            "subcategory":"Shoe Repair & Shine",
            "type":"Services"
        }
    ],
    "sg:phone":"+1 559 432 6990",
    "sg:postcode":"93711",
    "sg:province":"CA",
    "sg:tags":[
        "parlor",
        "used",
        "merchandise"
    ],
    "wof:name":"Sarkis Shoe Repair",
    "wof:placetype":"venue"
},
  "geometry": {"coordinates":[-119.84716,36.821933],"type":"Point"}
}