{
  "type": "Feature",
  "properties": {
    "addr:full":"1570 Corporate Dr Costa Mesa CA 92626",
    "addr:housenumber":"1570",
    "addr:postcode":"92626",
    "addr:street":"Corporate Dr",
    "iso:country":"US",
    "sg:address":"1570 Corporate Dr",
    "sg:city":"Costa Mesa",
    "sg:classifiers":[
        {
            "category":"Restaurant",
            "type":"Food & Drink"
        }
    ],
    "sg:phone":"+1 714 751 5777",
    "sg:postcode":"92626",
    "sg:province":"CA",
    "sg:tags":[
        "eating"
    ],
    "wof:name":"Bacchus Inspired Cuisine",
    "wof:placetype":"venue"
},
  "geometry": {"coordinates":[-117.923467,33.697945],"type":"Point"}
}