{
  "type": "Feature",
  "properties": {
    "addr:full":"1 W Pine St Lodi CA 95240",
    "addr:housenumber":"1",
    "addr:postcode":"95240",
    "addr:street":"W Pine St",
    "iso:country":"US",
    "sg:address":"1 W Pine St",
    "sg:city":"Lodi",
    "sg:classifiers":[
        {
            "category":"Personal",
            "subcategory":"Beauty Salon",
            "type":"Services"
        }
    ],
    "sg:phone":"+1 209 366 2255",
    "sg:postcode":"95240",
    "sg:province":"CA",
    "sg:tags":[
        "spa",
        "day"
    ],
    "wof:name":"Ciao Bella",
    "wof:placetype":"venue"
},
  "geometry": {"coordinates":[-121.272278,38.134151],"type":"Point"}
}