{
  "type": "Feature",
  "properties": {
    "addr:full":"134 Tivoli Ln Danville CA 94506",
    "addr:housenumber":"134",
    "addr:postcode":"94506",
    "addr:street":"Tivoli Ln",
    "iso:country":"US",
    "sg:address":"134 Tivoli Ln",
    "sg:city":"Danville",
    "sg:classifiers":[
        {
            "category":"Professional",
            "subcategory":"Management & Consulting",
            "type":"Services"
        }
    ],
    "sg:phone":"+1 925 736 5333",
    "sg:postcode":"94506",
    "sg:province":"CA",
    "sg:tags":[
        "public",
        "relations"
    ],
    "wof:name":"K J P R",
    "wof:placetype":"venue"
},
  "geometry": {"coordinates":[-121.92731999999999,37.802651],"type":"Point"}
}