{
  "type": "Feature",
  "properties": {
    "addr:full":"2310 Valley West Dr Santa Rosa CA 95401",
    "addr:housenumber":"2310",
    "addr:postcode":"95401",
    "addr:street":"Valley West Dr",
    "iso:country":"US",
    "sg:address":"2310 Valley West Dr",
    "sg:city":"Santa Rosa",
    "sg:classifiers":[
        {
            "category":"Professional",
            "type":"Services"
        }
    ],
    "sg:phone":"+1 707 542 9829",
    "sg:postcode":"95401",
    "sg:province":"CA",
    "wof:name":"Nana Vegas Handcrafts",
    "wof:placetype":"venue"
},
  "geometry": {"coordinates":[-122.758633,38.435967],"type":"Point"}
}