{
  "type": "Feature",
  "properties": {
    "iso:country":"US",
    "sg:address":"14538 Keswick St",
    "sg:city":"Van Nuys",
    "sg:classifiers":[
        {
            "category":"Wholesale",
            "subcategory":"Home Furnishings",
            "type":"Manufacturing & Wholesale Goods"
        }
    ],
    "sg:phone":"+1 818 982 6095",
    "sg:postcode":"91405",
    "sg:province":"CA",
    "wof:name":"Western Nat Stoned & Tumbled",
    "wof:placetype":"venue"
},
  "geometry": {"coordinates":[-118.451541,34.210194],"type":"Point"}
}