{
  "type": "Feature",
  "properties": {
    "iso:country":"US",
    "sg:address":"221 Estates Dr",
    "sg:city":"Roseville",
    "sg:classifiers":[
        {
            "category":"Banks & Credit Unions",
            "subcategory":"Bank",
            "type":"Services"
        }
    ],
    "sg:phone":"+1 916 782 3146",
    "sg:postcode":"95678",
    "sg:province":"CA",
    "sg:website":"www.usbank.com",
    "wof:name":"US Bank",
    "wof:placetype":"venue"
},
  "geometry": {"coordinates":[-121.272142,38.747382],"type":"Point"}
}