{
  "type": "Feature",
  "properties": {
    "addr:full":"100 Cielo Ln Novato CA 94949",
    "addr:housenumber":"100",
    "addr:postcode":"94949",
    "addr:street":"Cielo Ln",
    "iso:country":"US",
    "sg:address":"100 Cielo Ln",
    "sg:city":"Novato",
    "sg:classifiers":[
        {
            "category":"Building & Trades",
            "subcategory":"Construction",
            "type":"Services"
        }
    ],
    "sg:phone":"+1 415 884 0308",
    "sg:postcode":"94949",
    "sg:province":"CA",
    "sg:tags":[
        "coping",
        "plastering",
        "tiling",
        "pool",
        "swimming"
    ],
    "wof:name":"John Jr's Pool Svc",
    "wof:placetype":"venue"
},
  "geometry": {"coordinates":[-122.532282,38.057603],"type":"Point"}
}