{
  "type": "Feature",
  "properties": {
    "addr:full":"1356 N Main St Walnut Creek CA 94596",
    "addr:housenumber":"1356",
    "addr:postcode":"94596",
    "addr:street":"N Main St",
    "iso:country":"US",
    "sg:address":"1356 N Main St",
    "sg:city":"Walnut Creek",
    "sg:classifiers":[
        {
            "category":"Shopping",
            "subcategory":"Clothing, Apparel, & Fashions",
            "type":"Retail Goods"
        }
    ],
    "sg:phone":"+1 925 933 8050",
    "sg:postcode":"94596",
    "sg:province":"CA",
    "sg:tags":[
        "furnishing"
    ],
    "wof:name":"Atlas",
    "wof:placetype":"venue"
},
  "geometry": {"coordinates":[-122.060597,37.898989],"type":"Point"}
}