{
  "type": "Feature",
  "properties": {
    "addr:full":"25 Glenshire Ln Chico CA 95973",
    "addr:housenumber":"25",
    "addr:postcode":"95973",
    "addr:street":"Glenshire Ln",
    "iso:country":"US",
    "sg:address":"25 Glenshire Ln",
    "sg:city":"Chico",
    "sg:classifiers":[
        {
            "category":"Shopping",
            "subcategory":"Hobbies, Toys, & Games",
            "type":"Retail Goods"
        }
    ],
    "sg:phone":"+1 530 566 1555",
    "sg:postcode":"95973",
    "sg:province":"CA",
    "wof:name":"Alphablock",
    "wof:placetype":"venue"
},
  "geometry": {"coordinates":[-121.835832,39.766164],"type":"Point"}
}