{
  "type": "Feature",
  "properties": {
    "iso:country":"US",
    "sg:address":"6665 N Long Beach Blvd",
    "sg:city":"Long Beach",
    "sg:classifiers":[
        {
            "category":"Real Estate",
            "subcategory":"Real Estate Agent",
            "type":"Services"
        }
    ],
    "sg:phone":"+1 310 639 0745",
    "sg:postcode":"90805",
    "sg:province":"CA",
    "sg:tags":[
        "authorities",
        "housing"
    ],
    "wof:name":"Westland Housing",
    "wof:placetype":"venue"
},
  "geometry": {"coordinates":[-118.203321,33.875937],"type":"Point"}
}