{
  "type": "Feature",
  "properties": {
    "addr:full":"13005 Pinnacle Loop Truckee CA 96161",
    "addr:housenumber":"13005",
    "addr:postcode":"96161",
    "addr:street":"Pinnacle Loop",
    "iso:country":"US",
    "sg:address":"13005 Pinnacle Loop",
    "sg:city":"Truckee",
    "sg:classifiers":[
        {
            "category":"Organizations",
            "subcategory":"Membership Organization",
            "type":"Services"
        }
    ],
    "sg:phone":"+1 530 582 4197",
    "sg:postcode":"96161",
    "sg:province":"CA",
    "sg:website":"www.homa.org",
    "wof:name":"Dr Homa Darabi Foundation",
    "wof:placetype":"venue"
},
  "geometry": {"coordinates":[-120.24866400000001,39.368041],"type":"Point"}
}