{
  "type": "Feature",
  "properties": {
    "addr:full":"4881 Popejoy Ct San Jose CA 95118",
    "addr:postcode":"4881;95118",
    "addr:street":"Popejoy Ct",
    "iso:country":"US",
    "sg:address":"4881 Popejoy Ct",
    "sg:city":"San Jose",
    "sg:classifiers":[
        {
            "category":"Professional",
            "type":"Services"
        }
    ],
    "sg:phone":"+1 408 439 2752",
    "sg:postcode":"95118",
    "sg:province":"CA",
    "wof:name":"Elite Leads of Silcon Val",
    "wof:placetype":"venue"
},
  "geometry": {"coordinates":[-121.906738,37.251752],"type":"Point"}
}