{
  "type": "Feature",
  "properties": {
    "iso:country":"US",
    "sg:address":"351 Wayne Ave",
    "sg:city":"Oakland",
    "sg:classifiers":[
        {
            "category":"Health Services",
            "subcategory":"Health Practitioner",
            "type":"Services"
        }
    ],
    "sg:phone":"+1 510 839 4800",
    "sg:postcode":"94606",
    "sg:province":"CA",
    "sg:tags":[
        "hypnotist"
    ],
    "sg:website":"www.hypnotherapycenter.com",
    "wof:name":"Center For Hypnotherapy",
    "wof:placetype":"venue"
},
  "geometry": {"coordinates":[-122.252042,37.803598],"type":"Point"}
}