{
  "type": "Feature",
  "properties": {
    "iso:country":"US",
    "sg:address":"1719 Park St",
    "sg:city":"Alameda",
    "sg:classifiers":[
        {
            "category":"Retail",
            "subcategory":"Auto Repair",
            "type":"Services"
        }
    ],
    "sg:phone":"+1 510 521 0651",
    "sg:postcode":"94501",
    "sg:province":"CA",
    "sg:tags":[
        "repairing",
        "automobile"
    ],
    "sg:website":"www.germanautoserviceandrepair.com",
    "wof:name":"German Auto SVC",
    "wof:placetype":"venue"
},
  "geometry": {"coordinates":[-122.23942,37.768281],"type":"Point"}
}