{
  "type": "Feature",
  "properties": {
    "addr:full":"1751 Hamner Ave Norco CA 92860",
    "addr:housenumber":"1751",
    "addr:postcode":"92860",
    "addr:street":"Hamner Ave",
    "iso:country":"US",
    "sg:address":"1751 Hamner Ave",
    "sg:city":"Norco",
    "sg:classifiers":[
        {
            "category":"Autos & Motor Vehicles",
            "subcategory":"Recreational Vehicle Sales",
            "type":"Retail Goods"
        }
    ],
    "sg:phone":"+1 951 734 0371",
    "sg:postcode":"92860",
    "sg:province":"CA",
    "wof:name":"Norco Camper Co",
    "wof:placetype":"venue"
},
  "geometry": {"coordinates":[-117.561215,33.909452],"type":"Point"}
}