{
  "type": "Feature",
  "properties": {
    "addr:full":"3977 Union Pacific Ave Los Angeles CA 90023",
    "addr:housenumber":"3977",
    "addr:postcode":"90023",
    "addr:street":"Union Pacific Ave",
    "iso:country":"US",
    "sg:address":"3977 Union Pacific Ave",
    "sg:city":"Los Angeles",
    "sg:classifiers":[
        {
            "category":"Manufacturing",
            "subcategory":"Metals",
            "type":"Manufacturing & Wholesale Goods"
        }
    ],
    "sg:phone":"+1 323 262 5095",
    "sg:postcode":"90023",
    "sg:province":"CA",
    "wof:name":"Mendoza Polishing",
    "wof:placetype":"venue"
},
  "geometry": {"coordinates":[-118.189498,34.016653],"type":"Point"}
}