{
  "type": "Feature",
  "properties": {
    "addr:full":"320 W Temple St Los Angeles CA 90026",
    "addr:housenumber":"320",
    "addr:postcode":"90026",
    "addr:street":"W Temple St",
    "iso:country":"US",
    "sg:address":"320 W Temple St",
    "sg:city":"Los Angeles",
    "sg:classifiers":[
        {
            "category":"Government",
            "subcategory":"Court House",
            "type":"Public Place"
        }
    ],
    "sg:phone":"+1 213 974 5911",
    "sg:postcode":"90026",
    "sg:province":"CA",
    "sg:tags":[
        "legal"
    ],
    "wof:name":"La Co Daappellate",
    "wof:placetype":"venue"
},
  "geometry": {"coordinates":[-118.24438499999999,34.056283],"type":"Point"}
}