{
  "type": "Feature",
  "properties": {
    "addr:full":"155 5th St Huntington Beach CA 92648",
    "addr:housenumber":"155",
    "addr:postcode":"92648",
    "addr:street":"5Th St",
    "iso:country":"US",
    "sg:address":"155 5th St",
    "sg:city":"Huntington Beach",
    "sg:classifiers":[
        {
            "category":"Sports & Exercise",
            "subcategory":"Bicycle Rental",
            "type":"Entertainment"
        }
    ],
    "sg:phone":"+1 714 500 0010",
    "sg:postcode":"92648",
    "sg:province":"CA",
    "sg:tags":[
        "wear"
    ],
    "sg:website":"www.activerideshop.com",
    "wof:name":"Active Ride Shop",
    "wof:placetype":"venue"
},
  "geometry": {"coordinates":[-118.00229400000001,33.658253],"type":"Point"}
}