{
  "type": "Feature",
  "properties": {
    "iso:country":"US",
    "sg:address":"2301 Monarch St",
    "sg:city":"Alameda",
    "sg:classifiers":[
        {
            "category":"Autos & Motor Vehicles",
            "subcategory":"Auto Supplies",
            "type":"Retail Goods"
        },
        {
            "category":"Retail",
            "subcategory":"Auto Repair",
            "type":"Services"
        }
    ],
    "sg:phone":"+1 510 749 0935",
    "sg:postcode":"94501",
    "sg:province":"CA",
    "sg:tags":[
        "lettering",
        "automobile",
        "body",
        "truck",
        "painting",
        "repairing"
    ],
    "wof:name":"MV Leasing",
    "wof:placetype":"venue"
},
  "geometry": {"coordinates":[-122.308509,37.784318],"type":"Point"}
}