{
  "type": "Feature",
  "properties": {
    "addr:full":"5025 Newport Ave San Diego CA 92107",
    "addr:housenumber":"5025",
    "addr:postcode":"92107",
    "addr:street":"Newport Ave",
    "iso:country":"US",
    "sg:address":"5025 Newport Ave",
    "sg:city":"San Diego",
    "sg:classifiers":[
        {
            "category":"Restaurant",
            "type":"Food & Drink"
        }
    ],
    "sg:phone":"+1 619 222 4311",
    "sg:postcode":"92107",
    "sg:province":"CA",
    "sg:tags":[
        "barbeque"
    ],
    "sg:website":"www.barbquehouse.com",
    "wof:name":"Bar-B-Que House",
    "wof:placetype":"venue"
},
  "geometry": {"coordinates":[-117.251498,32.747126],"type":"Point"}
}