{
  "type": "Feature",
  "properties": {
    "iso:country":"US",
    "sg:address":"1886 College Ave",
    "sg:city":"Livermore",
    "sg:classifiers":[
        {
            "category":"Social Services",
            "subcategory":"Child Care",
            "type":"Services"
        }
    ],
    "sg:phone":"+1 925 443 1689",
    "sg:postcode":"94550",
    "sg:province":"CA",
    "sg:tags":[
        "kindergarten",
        "academic",
        "school"
    ],
    "wof:name":"Beth Emek Preschool",
    "wof:placetype":"venue"
},
  "geometry": {"coordinates":[-121.770495,37.674509],"type":"Point"}
}