{
  "type": "Feature",
  "properties": {
    "addr:full":"1030 Gettysburg Ave Ste 100C Clovis CA 93612",
    "addr:housenumber":"1030",
    "addr:postcode":"93612",
    "addr:street":"Gettysburg Ave Ste 100C",
    "iso:country":"US",
    "sg:address":"1030 Gettysburg Ave Ste 100C",
    "sg:city":"Clovis",
    "sg:classifiers":[
        {
            "category":"Professional",
            "subcategory":"Printing & Photocopies",
            "type":"Services"
        }
    ],
    "sg:phone":"+1 559 291 1396",
    "sg:postcode":"93612",
    "sg:province":"CA",
    "sg:tags":[
        "flag",
        "banners",
        "pennant"
    ],
    "wof:name":"Cox Richard",
    "wof:placetype":"venue"
},
  "geometry": {"coordinates":[-119.69594499999999,36.80123],"type":"Point"}
}