{
  "type": "Feature",
  "properties": {
    "addr:full":"5309 W 135th Street Hawthorne CA 90250",
    "addr:housenumber":"5309",
    "addr:postcode":"90250",
    "addr:street":"W 135Th Street",
    "iso:country":"US",
    "sg:address":"5309 W 135th Street",
    "sg:city":"Hawthorne",
    "sg:classifiers":[
        {
            "category":"Social Services",
            "subcategory":"Child Care",
            "type":"Services"
        },
        {
            "category":"Education",
            "subcategory":"Preschool",
            "type":"Public Place"
        },
        {
            "category":"Education",
            "subcategory":"School",
            "type":"Public Place"
        }
    ],
    "sg:phone":"+1 310 536 9353",
    "sg:postcode":"90250",
    "sg:province":"CA",
    "sg:tags":[
        "elementary",
        "day"
    ],
    "wof:name":"Rainbow River-Administrative Office",
    "wof:placetype":"venue"
},
  "geometry": {"coordinates":[-118.373035,33.90938],"type":"Point"}
}