{
  "type": "Feature",
  "properties": {
    "addr:full":"2851 W Pico Blvd Los Angeles CA 90006",
    "addr:housenumber":"2851",
    "addr:postcode":"90006",
    "addr:street":"W Pico Blvd",
    "iso:country":"US",
    "sg:address":"2851 W Pico Blvd",
    "sg:city":"Los Angeles",
    "sg:classifiers":[
        {
            "category":"Retail",
            "subcategory":"Auto Repair",
            "type":"Services"
        }
    ],
    "sg:phone":"+1 323 733 8565",
    "sg:postcode":"90006",
    "sg:province":"CA",
    "sg:tags":[
        "wrecker"
    ],
    "wof:name":"Olympic Towing Svc",
    "wof:placetype":"venue"
},
  "geometry": {"coordinates":[-118.301385,34.047298],"type":"Point"}
}