{
  "type": "Feature",
  "properties": {
    "iso:country":"US",
    "sg:address":"6351 Owensmouth Ave Ste 100",
    "sg:city":"Woodland Hills",
    "sg:classifiers":[
        {
            "category":"Professional",
            "subcategory":"Lawyer & Legal Services",
            "type":"Services"
        }
    ],
    "sg:phone":"+1 818 884 0101",
    "sg:postcode":"91367",
    "sg:province":"CA",
    "wof:name":"Heisler Trey Atty Heisler Bray & Be Eson Lw Ofc of",
    "wof:placetype":"venue"
},
  "geometry": {"coordinates":[-118.601997,34.185902],"type":"Point"}
}