{
  "type": "Feature",
  "properties": {
    "iso:country":"US",
    "sg:address":"37150 Van Gaale Ln",
    "sg:city":"Murrieta",
    "sg:classifiers":[
        {
            "category":"Wholesale",
            "subcategory":"Motor Vehicles",
            "type":"Manufacturing & Wholesale Goods"
        }
    ],
    "sg:phone":"+1 951 698 5674",
    "sg:postcode":"92563",
    "sg:province":"CA",
    "sg:tags":[
        "automobile",
        "transporter"
    ],
    "wof:name":"Lanssens Auto Transport",
    "wof:placetype":"venue"
},
  "geometry": {"coordinates":[-117.11415100000001,33.582065],"type":"Point"}
}