{
  "type": "Feature",
  "properties": {
    "iso:country":"US",
    "sg:address":"1051 13th St Ste 8C",
    "sg:city":"Imperial Beach",
    "sg:classifiers":[
        {
            "category":"Personal",
            "subcategory":"Barber",
            "type":"Services"
        }
    ],
    "sg:phone":"+1 619 575 2600",
    "sg:postcode":"91932",
    "sg:province":"CA",
    "wof:name":"Felipe's Barber Shop",
    "wof:placetype":"venue"
},
  "geometry": {"coordinates":[-117.105678,32.577382],"type":"Point"}
}