{
  "type": "Feature",
  "properties": {
    "addr:full":"1517 Locust St Walnut Creek CA 94596",
    "addr:housenumber":"1517",
    "addr:postcode":"94596",
    "addr:street":"Locust St",
    "iso:country":"US",
    "sg:address":"1517 Locust St",
    "sg:city":"Walnut Creek",
    "sg:classifiers":[
        {
            "category":"Shopping",
            "type":"Retail Goods"
        }
    ],
    "sg:phone":"+1 925 939 2450",
    "sg:postcode":"94596",
    "sg:province":"CA",
    "sg:tags":[
        "limb",
        "artificial"
    ],
    "wof:name":"Marzel's",
    "wof:placetype":"venue"
},
  "geometry": {"coordinates":[-122.06302100000001,37.901116],"type":"Point"}
}