{
  "type": "Feature",
  "properties": {
    "iso:country":"US",
    "sg:address":"25030 Via Santee",
    "sg:city":"Murrieta",
    "sg:classifiers":[
        {
            "category":"Education",
            "subcategory":"School",
            "type":"Public Place"
        }
    ],
    "sg:phone":"+1 951 696 1404",
    "sg:postcode":"92563",
    "sg:province":"CA",
    "wof:name":"Rail Ranch School",
    "wof:placetype":"venue"
},
  "geometry": {"coordinates":[-117.174292,33.578452],"type":"Point"}
}