{
  "type": "Feature",
  "properties": {
    "addr:full":"1343 River Rd Modesto CA 95351",
    "addr:housenumber":"1343",
    "addr:postcode":"ca 95351",
    "addr:street":"River Rd",
    "iso:country":"US",
    "sg:address":"1343 River Rd",
    "sg:city":"Modesto",
    "sg:classifiers":[
        {
            "category":"Real Estate",
            "subcategory":"Real Estate Agent",
            "type":"Services"
        }
    ],
    "sg:phone":"+1 209 578 4000",
    "sg:postcode":"95351",
    "sg:province":"CA",
    "wof:name":"Susan Ion",
    "wof:placetype":"venue"
},
  "geometry": {"coordinates":[-120.973112,37.621767],"type":"Point"}
}