{
  "type": "Feature",
  "properties": {
    "iso:country":"US",
    "sg:address":"5341 W 93rd St",
    "sg:city":"Los Angeles",
    "sg:classifiers":[
        {
            "category":"Professional",
            "subcategory":"Management & Consulting",
            "type":"Services"
        }
    ],
    "sg:phone":"+1 310 670 4171",
    "sg:postcode":"90045",
    "sg:province":"CA",
    "sg:tags":[
        "consultant",
        "business"
    ],
    "wof:name":"Jolisa Management Co",
    "wof:placetype":"venue"
},
  "geometry": {"coordinates":[-118.374907,33.951692],"type":"Point"}
}