{
  "type": "Feature",
  "properties": {
    "addr:full":"807 Montgomery Street San Francisco CA 94133",
    "addr:housenumber":"807",
    "addr:postcode":"94133",
    "addr:street":"Montgomery Street",
    "iso:country":"US",
    "sg:address":"807 Montgomery Street",
    "sg:city":"San Francisco",
    "sg:classifiers":[
        {
            "category":"Professional",
            "subcategory":"Lawyer & Legal Services",
            "type":"Services"
        }
    ],
    "sg:phone":"+1 415 362 0101",
    "sg:postcode":"94133",
    "sg:province":"CA",
    "sg:tags":[
        "personal",
        "injury"
    ],
    "wof:name":"Arnold Laub Law Offices of",
    "wof:placetype":"venue"
},
  "geometry": {"coordinates":[-122.403677,37.796613],"type":"Point"}
}