{
  "type": "Feature",
  "properties": {
    "iso:country":"US",
    "sg:address":"951 Commercial St",
    "sg:city":"Palo Alto",
    "sg:classifiers":[
        {
            "category":"Building & Trades",
            "subcategory":"Construction",
            "type":"Services"
        }
    ],
    "sg:phone":"+1 650 424 0356",
    "sg:postcode":"94303",
    "sg:province":"CA",
    "sg:tags":[
        "tile",
        "ceramic",
        "installing",
        "contractor"
    ],
    "wof:name":"Color Tile",
    "wof:placetype":"venue"
},
  "geometry": {"coordinates":[-122.10018,37.422645],"type":"Point"}
}