{
  "type": "Feature",
  "properties": {
    "addr:full":"3330 W Vernon Ave Los Angeles CA 90008",
    "addr:housenumber":"3330",
    "addr:postcode":"90008",
    "addr:street":"W Vernon Ave",
    "iso:country":"US",
    "sg:address":"3330 W Vernon Ave",
    "sg:city":"Los Angeles",
    "sg:classifiers":[
        {
            "category":"Retail",
            "subcategory":"Auto Repair",
            "type":"Services"
        }
    ],
    "sg:phone":"+1 323 292 4157",
    "sg:postcode":"90008",
    "sg:province":"CA",
    "sg:tags":[
        "transmission"
    ],
    "wof:name":"Parks Auto Transmission",
    "wof:placetype":"venue"
},
  "geometry": {"coordinates":[-118.329686,34.003569],"type":"Point"}
}