{
  "type": "Feature",
  "properties": {
    "iso:country":"US",
    "sg:address":"249 W Jackson St",
    "sg:city":"Hayward",
    "sg:classifiers":[
        {
            "category":"Wholesale",
            "subcategory":"Painting Supplies",
            "type":"Manufacturing & Wholesale Goods"
        },
        {
            "category":"Shopping",
            "subcategory":"Crafts & Fabrics",
            "type":"Retail Goods"
        }
    ],
    "sg:phone":"+1 510 385 8024",
    "sg:postcode":"94544",
    "sg:province":"CA",
    "sg:tags":[
        "goods-wholesale",
        "art",
        "manufacturer"
    ],
    "wof:name":"Ram Tri- Enterprises Inc",
    "wof:placetype":"venue"
},
  "geometry": {"coordinates":[-122.089904,37.652186],"type":"Point"}
}