{
  "type": "Feature",
  "properties": {
    "addr:full":"44100 Monterey Ave Palm Desert CA 92260",
    "addr:housenumber":"44100",
    "addr:postcode":"ca 92260",
    "addr:street":"Monterey Ave",
    "iso:country":"US",
    "sg:address":"44100 Monterey Ave",
    "sg:city":"Palm Desert",
    "sg:classifiers":[
        {
            "category":"Real Estate",
            "subcategory":"Architect",
            "type":"Services"
        }
    ],
    "sg:phone":"+1 760 862 1836",
    "sg:postcode":"92260",
    "sg:province":"CA",
    "wof:name":"Forward Architecture & Design Inc",
    "wof:placetype":"venue"
},
  "geometry": {"coordinates":[-116.390885,33.727896],"type":"Point"}
}