{
  "type": "Feature",
  "properties": {
    "addr:full":"18055 Bushard St Fountain Valley CA 92708",
    "addr:postcode":"18055;92708",
    "addr:street":"Bushard St",
    "iso:country":"US",
    "sg:address":"18055 Bushard St",
    "sg:city":"Fountain Valley",
    "sg:classifiers":[
        {
            "category":"Health Services",
            "subcategory":"Doctor",
            "type":"Services"
        }
    ],
    "sg:phone":"+1 714 968 4474",
    "sg:postcode":"92708",
    "sg:province":"CA",
    "sg:tags":[
        "orthopedist"
    ],
    "wof:name":"Levin Dr David R",
    "wof:placetype":"venue"
},
  "geometry": {"coordinates":[-117.96310099999999,33.699413],"type":"Point"}
}