{
  "type": "Feature",
  "properties": {
    "addr:full":"3030 Old Ranch Pkwy Seal Beach CA 90740",
    "addr:housenumber":"3030",
    "addr:postcode":"90740",
    "addr:street":"Old Ranch Pkwy",
    "iso:country":"US",
    "sg:address":"3030 Old Ranch Pkwy",
    "sg:city":"Seal Beach",
    "sg:classifiers":[
        {
            "category":"Professional",
            "subcategory":"Lawyer & Legal Services",
            "type":"Services"
        }
    ],
    "sg:phone":"+1 310 543 4363",
    "sg:postcode":"90740",
    "sg:province":"CA",
    "sg:tags":[
        "divorce",
        "law",
        "family"
    ],
    "wof:name":"Gilligan Law Corporation",
    "wof:placetype":"venue"
},
  "geometry": {"coordinates":[-118.079002,33.775101],"type":"Point"}
}