{
  "type": "Feature",
  "properties": {
    "addr:full":"12155 Flint Pl Poway CA 92064",
    "addr:housenumber":"12155",
    "addr:postcode":"ca 92064",
    "addr:street":"Flint Pl",
    "iso:country":"US",
    "sg:address":"12155 Flint Pl",
    "sg:city":"Poway",
    "sg:classifiers":[
        {
            "category":"Manufacturing",
            "subcategory":"Printing",
            "type":"Manufacturing & Wholesale Goods"
        }
    ],
    "sg:phone":"+1 858 695 8221",
    "sg:postcode":"92064",
    "sg:province":"CA",
    "sg:tags":[
        "commercial"
    ],
    "sg:website":"www.nwp1.com",
    "wof:name":"Network Printing & Copy Ctr",
    "wof:placetype":"venue"
},
  "geometry": {"coordinates":[-117.04011199999999,32.937591],"type":"Point"}
}