{
  "type": "Feature",
  "properties": {
    "iso:country":"US",
    "sg:address":"3512 Santa Rosa Ave",
    "sg:city":"Santa Rosa",
    "sg:classifiers":[
        {
            "category":"Freight",
            "type":"Transportation"
        }
    ],
    "sg:phone":"+1 707 585 3791",
    "sg:postcode":"95407",
    "sg:province":"CA",
    "sg:tags":[
        "commercial",
        "storage"
    ],
    "wof:name":"Santa Rosa Avenue Self Storage",
    "wof:placetype":"venue"
},
  "geometry": {"coordinates":[-122.71346800000001,38.390576],"type":"Point"}
}