{
  "type": "Feature",
  "properties": {
    "addr:full":"4545 N Palm Ave Fresno CA 93704",
    "addr:housenumber":"4545",
    "addr:postcode":"93704",
    "addr:street":"N Palm Ave",
    "iso:country":"US",
    "sg:address":"4545 N Palm Ave",
    "sg:city":"Fresno",
    "sg:classifiers":[
        {
            "category":"Social Services",
            "subcategory":"Child Care",
            "type":"Services"
        }
    ],
    "sg:phone":"+1 559 225 6945",
    "sg:postcode":"93704",
    "sg:province":"CA",
    "sg:tags":[
        "kindergarten",
        "academic",
        "school"
    ],
    "wof:name":"Kinder Academy",
    "wof:placetype":"venue"
},
  "geometry": {"coordinates":[-119.808617,36.800319],"type":"Point"}
}