{
  "type": "Feature",
  "properties": {
    "addr:full":"555 Boyd Rd Pleasant Hill CA 94523",
    "addr:housenumber":"555",
    "addr:postcode":"94523",
    "addr:street":"Boyd Rd",
    "iso:country":"US",
    "sg:address":"555 Boyd Rd",
    "sg:city":"Pleasant Hill",
    "sg:classifiers":[
        {
            "category":"Organizations",
            "subcategory":"Religious Organization",
            "type":"Services"
        }
    ],
    "sg:phone":"+1 925 946 1742",
    "sg:postcode":"94523",
    "sg:province":"CA",
    "wof:name":"The Corporation of The Pres of",
    "wof:placetype":"venue"
},
  "geometry": {"coordinates":[-122.080316,37.943566],"type":"Point"}
}