{
  "type": "Feature",
  "properties": {
    "iso:country":"US",
    "sg:address":"125 Bethany Dr",
    "sg:city":"Scotts Valley",
    "sg:classifiers":[
        {
            "category":"Recreation",
            "type":"Entertainment"
        }
    ],
    "sg:phone":"+1 831 438 4947",
    "sg:postcode":"95066",
    "sg:province":"CA",
    "sg:tags":[
        "psychic",
        "medium"
    ],
    "wof:name":"Maria Silvermoon Psychic Med",
    "wof:placetype":"venue"
},
  "geometry": {"coordinates":[-121.995505,37.070626],"type":"Point"}
}