{
  "type": "Feature",
  "properties": {
    "iso:country":"US",
    "sg:address":"309 W Verdugo Ave",
    "sg:city":"Burbank",
    "sg:classifiers":[
        {
            "category":"Building & Trades",
            "subcategory":"Plumbing",
            "type":"Services"
        }
    ],
    "sg:phone":"+1 818 843 2301",
    "sg:postcode":"91502",
    "sg:province":"CA",
    "sg:tags":[
        "system",
        "heating",
        "contractor",
        "air conditioning",
        "conditioning/hvac"
    ],
    "sg:website":"www.certifiedac.net",
    "wof:name":"Certified Air Conditioning",
    "wof:placetype":"venue"
},
  "geometry": {"coordinates":[-118.314003,34.170799],"type":"Point"}
}