{
  "type": "Feature",
  "properties": {
    "addr:full":"22787 Golden Locust Dr Corona CA 92883",
    "addr:housenumber":"22787",
    "addr:postcode":"92883",
    "addr:street":"Golden Locust Dr",
    "iso:country":"US",
    "sg:address":"22787 Golden Locust Dr",
    "sg:city":"Corona",
    "sg:classifiers":[
        {
            "category":"Real Estate",
            "subcategory":"Developer",
            "type":"Services"
        }
    ],
    "sg:phone":"+1 951 277 4123",
    "sg:postcode":"92883",
    "sg:province":"CA",
    "wof:name":"Being Your Best",
    "wof:placetype":"venue"
},
  "geometry": {"coordinates":[-117.506274,33.788983],"type":"Point"}
}