{
  "type": "Feature",
  "properties": {
    "iso:country":"US",
    "sg:address":"449 Powell St",
    "sg:city":"San Francisco",
    "sg:classifiers":[
        {
            "category":"Shopping",
            "subcategory":"Catalog Store",
            "type":"Retail Goods"
        }
    ],
    "sg:phone":"+1 858 551 2523",
    "sg:postcode":"94102",
    "sg:province":"CA",
    "sg:tags":[
        "mail",
        "order"
    ],
    "wof:name":"Rigpa Publications",
    "wof:placetype":"venue"
},
  "geometry": {"coordinates":[-122.408594,37.788757],"type":"Point"}
}