{
  "type": "Feature",
  "properties": {
    "iso:country":"US",
    "sg:address":"1320 Golden Gate Ave",
    "sg:city":"San Francisco",
    "sg:classifiers":[
        {
            "category":"Organizations",
            "subcategory":"Religious Organization",
            "type":"Services"
        }
    ],
    "sg:phone":"+1 415 921 0878",
    "sg:postcode":"94115",
    "sg:province":"CA",
    "sg:tags":[
        "church"
    ],
    "wof:name":"El-Bethel Baptist Church",
    "wof:placetype":"venue"
},
  "geometry": {"coordinates":[-122.43334299999999,37.779471],"type":"Point"}
}