{
  "type": "Feature",
  "properties": {
    "iso:country":"US",
    "sg:address":"31191 State Rte 44",
    "sg:city":"Shingletown",
    "sg:classifiers":[
        {
            "category":"Autos & Motor Vehicles",
            "subcategory":"Auto Supplies",
            "type":"Retail Goods"
        }
    ],
    "sg:phone":"+1 530 474 1234",
    "sg:postcode":"96088",
    "sg:province":"CA",
    "sg:tags":[
        "automobile",
        "parts"
    ],
    "wof:name":"Shingletown Auto Repair",
    "wof:placetype":"venue"
},
  "geometry": {"coordinates":[-121.898917,40.491231],"type":"Point"}
}