{
  "type": "Feature",
  "properties": {
    "iso:country":"US",
    "sg:address":"251 Airport Rd",
    "sg:city":"Oceanside",
    "sg:classifiers":[
        {
            "category":"Education",
            "subcategory":"Special Training",
            "type":"Public Place"
        }
    ],
    "sg:phone":"+1 760 721 1706",
    "sg:postcode":"92058",
    "sg:province":"CA",
    "sg:tags":[
        "school",
        "specialty"
    ],
    "wof:name":"T E R I INC",
    "wof:placetype":"venue"
},
  "geometry": {"coordinates":[-117.349099,33.214052],"type":"Point"}
}