{
  "type": "Feature",
  "properties": {
    "iso:country":"US",
    "sg:address":"131 S Rodeo Dr",
    "sg:city":"Beverly Hills",
    "sg:classifiers":[
        {
            "category":"Professional",
            "type":"Services"
        }
    ],
    "sg:phone":"+1 310 550 7980",
    "sg:postcode":"90212",
    "sg:province":"CA",
    "sg:tags":[
        "arena",
        "stadium"
    ],
    "wof:name":"Beverly Hills Sport",
    "wof:placetype":"venue"
},
  "geometry": {"coordinates":[-118.401258,34.066477],"type":"Point"}
}