{
  "type": "Feature",
  "properties": {
    "addr:full":"1975 Old Adobe Rd Petaluma CA 94954",
    "addr:housenumber":"1975",
    "addr:postcode":"94954",
    "addr:street":"Old Adobe Rd",
    "iso:country":"US",
    "sg:address":"1975 Old Adobe Rd",
    "sg:city":"Petaluma",
    "sg:classifiers":[
        {
            "category":"Building & Trades",
            "subcategory":"Construction",
            "type":"Services"
        }
    ],
    "sg:phone":"+1 415 457 1243",
    "sg:postcode":"94954",
    "sg:province":"CA",
    "sg:tags":[
        "water",
        "well",
        "drilling"
    ],
    "wof:name":"Anderson Pump",
    "wof:placetype":"venue"
},
  "geometry": {"coordinates":[-122.622817,38.276928],"type":"Point"}
}