{
  "type": "Feature",
  "properties": {
    "addr:full":"7176 Olive Ave Winton CA 95388",
    "addr:housenumber":"7176",
    "addr:postcode":"95388",
    "addr:street":"Olive Ave",
    "iso:country":"US",
    "sg:address":"7176 Olive Ave",
    "sg:city":"Winton",
    "sg:classifiers":[
        {
            "category":"Building & Trades",
            "subcategory":"Construction",
            "type":"Services"
        }
    ],
    "sg:phone":"+1 209 358 9398",
    "sg:postcode":"95388",
    "sg:province":"CA",
    "sg:tags":[
        "wallcoverings-installation",
        "wallpaper",
        "painting",
        "contractor"
    ],
    "wof:name":"Jeffreys Painting",
    "wof:placetype":"venue"
},
  "geometry": {"coordinates":[-120.616434,37.396642],"type":"Point"}
}