{
  "type": "Feature",
  "properties": {
    "addr:full":"10270 Donner Pass Rd Truckee CA 96161",
    "addr:housenumber":"10270",
    "addr:postcode":"96161",
    "addr:street":"Donner Pass Rd",
    "iso:country":"US",
    "sg:address":"10270 Donner Pass Rd",
    "sg:city":"Truckee",
    "sg:classifiers":[
        {
            "category":"Education",
            "subcategory":"Special Training",
            "type":"Public Place"
        }
    ],
    "sg:phone":"+1 530 448 9899",
    "sg:postcode":"96161",
    "sg:province":"CA",
    "sg:tags":[
        "school",
        "massage"
    ],
    "wof:name":"Body Being Massage Ctr",
    "wof:placetype":"venue"
},
  "geometry": {"coordinates":[-120.188897,39.326624],"type":"Point"}
}