{
  "type": "Feature",
  "properties": {
    "addr:full":"777 W Shaw Ave Fresno CA 93704",
    "addr:housenumber":"777",
    "addr:postcode":"93704",
    "addr:street":"W Shaw Ave",
    "iso:country":"US",
    "sg:address":"777 W Shaw Ave",
    "sg:city":"Fresno",
    "sg:classifiers":[
        {
            "category":"Health Services",
            "subcategory":"Chiropractor",
            "type":"Services"
        }
    ],
    "sg:phone":"+1 559 227 1777",
    "sg:postcode":"93704",
    "sg:province":"CA",
    "sg:tags":[
        "chiropractic"
    ],
    "sg:website":"http://www.nwfamilychiro.com",
    "wof:name":"Northwest Family Chiropractic",
    "wof:placetype":"venue"
},
  "geometry": {"coordinates":[-119.807857,36.808325],"type":"Point"}
}