{
  "type": "Feature",
  "properties": {
    "addr:full":"2096 Cascade Blvd Shasta Lake CA 96019",
    "addr:housenumber":"2096",
    "addr:postcode":"96019",
    "addr:street":"Cascade Blvd",
    "iso:country":"US",
    "sg:address":"2096 Cascade Blvd",
    "sg:city":"Shasta Lake",
    "sg:classifiers":[
        {
            "category":"Organizations",
            "subcategory":"Non-profit Organization",
            "type":"Services"
        }
    ],
    "sg:phone":"+1 530 275 5622",
    "sg:postcode":"96019",
    "sg:province":"CA",
    "sg:tags":[
        "information",
        "alcoholism",
        "treatment"
    ],
    "wof:name":"Cornerstone Residential Trtmnt",
    "wof:placetype":"venue"
},
  "geometry": {"coordinates":[-122.354271,40.673031],"type":"Point"}
}