{
  "type": "Feature",
  "properties": {
    "iso:country":"US",
    "sg:address":"3205 Haley St",
    "sg:city":"Bakersfield",
    "sg:classifiers":[
        {
            "category":"Building & Trades",
            "subcategory":"Plumbing",
            "type":"Services"
        }
    ],
    "sg:phone":"+1 661 204 6704",
    "sg:postcode":"93305",
    "sg:province":"CA",
    "sg:tags":[
        "plumber",
        "industrial",
        "contractors-commercial"
    ],
    "wof:name":"Aztec Plumbing",
    "wof:placetype":"venue"
},
  "geometry": {"coordinates":[-118.97638000000001,35.402278],"type":"Point"}
}