{
  "type": "Feature",
  "properties": {
    "iso:country":"US",
    "sg:address":"450 N Brand Blvd",
    "sg:city":"Glendale",
    "sg:classifiers":[
        {
            "category":"Professional",
            "subcategory":"Art Services",
            "type":"Services"
        }
    ],
    "sg:phone":"+1 818 291 6260",
    "sg:postcode":"91203",
    "sg:province":"CA",
    "sg:tags":[
        "graphic",
        "designer"
    ],
    "wof:name":"Brandtopia",
    "wof:placetype":"venue"
},
  "geometry": {"coordinates":[-118.255007,34.152317],"type":"Point"}
}