{
  "type": "Feature",
  "properties": {
    "iso:country":"US",
    "sg:address":"80 N Sally St",
    "sg:city":"Hollister",
    "sg:classifiers":[
        {
            "category":"Government",
            "subcategory":"Office",
            "type":"Public Place"
        }
    ],
    "sg:phone":"+1 831 443 3138",
    "sg:postcode":"95023",
    "sg:province":"CA",
    "sg:tags":[
        "state",
        "program"
    ],
    "wof:name":"Motor Vehicle Dept",
    "wof:placetype":"venue"
},
  "geometry": {"coordinates":[-121.399934,36.856954],"type":"Point"}
}