{
  "type": "Feature",
  "properties": {
    "addr:full":"6007 Camino Manzano Anaheim CA 92807",
    "addr:housenumber":"6007",
    "addr:postcode":"92807",
    "addr:street":"Camino Manzano",
    "iso:country":"US",
    "sg:address":"6007 Camino Manzano",
    "sg:city":"Anaheim",
    "sg:classifiers":[
        {
            "category":"Building & Trades",
            "subcategory":"Construction",
            "type":"Services"
        }
    ],
    "sg:phone":"+1 949 232 8566",
    "sg:postcode":"92807",
    "sg:province":"CA",
    "sg:tags":[
        "contractor"
    ],
    "wof:name":"California Home Renovation",
    "wof:placetype":"venue"
},
  "geometry": {"coordinates":[-117.78206299999999,33.857092],"type":"Point"}
}