{
  "type": "Feature",
  "properties": {
    "addr:full":"116 Manhattan Beach Blvd Manhattan Beach CA 90266",
    "addr:housenumber":"116",
    "addr:postcode":"90266",
    "addr:street":"Manhattan Beach Blvd",
    "iso:country":"US",
    "sg:address":"116 Manhattan Beach Blvd",
    "sg:city":"Manhattan Beach",
    "sg:classifiers":[
        {
            "category":"Bars & Pubs",
            "type":"Food & Drink"
        }
    ],
    "sg:phone":"+1 310 376 7857",
    "sg:postcode":"90266",
    "sg:province":"CA",
    "sg:tags":[
        "diva"
    ],
    "sg:website":"www.shellbacktavern.com/",
    "wof:name":"The Shellback Tavern",
    "wof:placetype":"venue"
},
  "geometry": {"coordinates":[-118.41100299999999,33.884399],"type":"Point"}
}