{
  "type": "Feature",
  "properties": {
    "addr:full":"9645 Bolsa Ave Westminster CA 92683",
    "addr:housenumber":"9645",
    "addr:postcode":"92683",
    "addr:street":"Bolsa Ave",
    "iso:country":"US",
    "sg:address":"9645 Bolsa Ave",
    "sg:city":"Westminster",
    "sg:classifiers":[
        {
            "category":"Shopping",
            "subcategory":"Beauty & Cosmetics",
            "type":"Retail Goods"
        }
    ],
    "sg:phone":"+1 714 775 7366",
    "sg:postcode":"92683",
    "sg:province":"CA",
    "sg:tags":[
        "supply"
    ],
    "wof:name":"Tong Beauty Supply",
    "wof:placetype":"venue"
},
  "geometry": {"coordinates":[-117.96055,33.745127],"type":"Point"}
}