{
  "type": "Feature",
  "properties": {
    "addr:full":"3155 Leticia Dr Hacienda Heights CA 91745",
    "addr:housenumber":"3155",
    "addr:postcode":"91745",
    "addr:street":"Leticia Dr",
    "iso:country":"US",
    "sg:address":"3155 Leticia Dr",
    "sg:city":"Hacienda Heights",
    "sg:classifiers":[
        {
            "category":"Real Estate",
            "subcategory":"Real Estate Agent",
            "type":"Services"
        }
    ],
    "sg:phone":"+1 626 336 0715",
    "sg:postcode":"91745",
    "sg:province":"CA",
    "wof:name":"Barbara Lopez",
    "wof:placetype":"venue"
},
  "geometry": {"coordinates":[-117.97624,33.982411],"type":"Point"}
}