{
  "type": "Feature",
  "properties": {
    "addr:full":"2214 5th Avenue San Diego CA 92101",
    "addr:housenumber":"2214",
    "addr:postcode":"92101",
    "addr:street":"5Th Avenue",
    "iso:country":"US",
    "sg:address":"2214 5th Avenue",
    "sg:city":"San Diego",
    "sg:classifiers":[
        {
            "category":"Professional",
            "subcategory":"Lawyer & Legal Services",
            "type":"Services"
        }
    ],
    "sg:phone":"+1 619 296 9387",
    "sg:postcode":"92101",
    "sg:province":"CA",
    "wof:name":"Brictson Timothy",
    "wof:placetype":"venue"
},
  "geometry": {"coordinates":[-117.160135,32.728524],"type":"Point"}
}