{
  "type": "Feature",
  "properties": {
    "iso:country":"US",
    "sg:address":"212 Palomar St",
    "sg:city":"Chula Vista",
    "sg:classifiers":[
        {
            "category":"Real Estate",
            "subcategory":"Real Estate Operator",
            "type":"Services"
        }
    ],
    "sg:phone":"+1 619 426 1381",
    "sg:postcode":"91911",
    "sg:province":"CA",
    "sg:tags":[
        "apartment"
    ],
    "wof:name":"Palomar Gardens Apartments",
    "wof:placetype":"venue"
},
  "geometry": {"coordinates":[-117.062462,32.607294],"type":"Point"}
}