{
  "type": "Feature",
  "properties": {
    "addr:full":"2941 Honolulu Ave La Crescenta CA 91214",
    "addr:housenumber":"2941",
    "addr:postcode":"91214",
    "addr:street":"Honolulu Ave",
    "iso:country":"US",
    "sg:address":"2941 Honolulu Ave",
    "sg:city":"La Crescenta",
    "sg:classifiers":[
        {
            "category":"Building & Trades",
            "subcategory":"Construction",
            "type":"Services"
        }
    ],
    "sg:phone":"+1 818 957 2177",
    "sg:postcode":"91214",
    "sg:province":"CA",
    "sg:tags":[
        "contractor"
    ],
    "wof:name":"Miracle Mthod Bthroom Rstrtion",
    "wof:placetype":"venue"
},
  "geometry": {"coordinates":[-118.24385599999999,34.213925],"type":"Point"}
}