{
  "type": "Feature",
  "properties": {
    "addr:full":"9380 Orangevale Ave Orangevale CA 95662",
    "addr:postcode":"9380;95662",
    "addr:street":"Orangevale Ave",
    "iso:country":"US",
    "sg:address":"9380 Orangevale Ave",
    "sg:city":"Orangevale",
    "sg:classifiers":[
        {
            "category":"Building & Trades",
            "subcategory":"Plumbing",
            "type":"Services"
        }
    ],
    "sg:phone":"+1 916 989 1280",
    "sg:postcode":"95662",
    "sg:province":"CA",
    "sg:tags":[
        "system",
        "contractor",
        "equipment",
        "air conditioning"
    ],
    "wof:name":"C & C Mechanical",
    "wof:placetype":"venue"
},
  "geometry": {"coordinates":[-121.202791,38.681733],"type":"Point"}
}