{
  "type": "Feature",
  "properties": {
    "addr:full":"11555 Nebraska Ave Los Angeles CA 90025",
    "addr:housenumber":"11555",
    "addr:postcode":"90025",
    "addr:street":"Nebraska Ave",
    "iso:country":"US",
    "sg:address":"11555 Nebraska Ave",
    "sg:city":"Los Angeles",
    "sg:classifiers":[
        {
            "category":"Professional",
            "subcategory":"Art Services",
            "type":"Services"
        }
    ],
    "sg:phone":"+1 310 312 3024",
    "sg:postcode":"90025",
    "sg:province":"CA",
    "sg:tags":[
        "photographer"
    ],
    "wof:name":"Martin Lowe Group",
    "wof:placetype":"venue"
},
  "geometry": {"coordinates":[-118.450382,34.041505],"type":"Point"}
}