{
  "type": "Feature",
  "properties": {
    "addr:full":"2120 Benton Dr Redding CA 96003",
    "addr:housenumber":"2120",
    "addr:postcode":"96003",
    "addr:street":"Benton Dr",
    "iso:country":"US",
    "sg:address":"2120 Benton Dr",
    "sg:city":"Redding",
    "sg:classifiers":[
        {
            "category":"Health Services",
            "subcategory":"Nursing And Care Facility",
            "type":"Services"
        }
    ],
    "sg:phone":"+1 530 243 6317",
    "sg:postcode":"96003",
    "sg:province":"CA",
    "sg:tags":[
        "home",
        "convalescent"
    ],
    "sg:website":"www.kindredhealthcare.com",
    "wof:name":"Canyonwood Nursing & Rehab Ctr",
    "wof:placetype":"venue"
},
  "geometry": {"coordinates":[-122.401427,40.595082],"type":"Point"}
}