{
  "type": "Feature",
  "properties": {
    "addr:full":"40210 el Camino Real Greenfield CA 93927",
    "addr:housenumber":"40210",
    "addr:postcode":"93927",
    "addr:street":"El Camino Real",
    "iso:country":"US",
    "sg:address":"40210 el Camino Real",
    "sg:city":"Greenfield",
    "sg:classifiers":[
        {
            "category":"Autos & Motor Vehicles",
            "subcategory":"Fuel & Gas Station",
            "type":"Retail Goods"
        }
    ],
    "sg:phone":"+1 831 674 5019",
    "sg:postcode":"93927",
    "sg:province":"CA",
    "sg:tags":[
        "oil"
    ],
    "wof:name":"Shell",
    "wof:placetype":"venue"
},
  "geometry": {"coordinates":[-121.255206,36.33906],"type":"Point"}
}