{
  "type": "Feature",
  "properties": {
    "iso:country":"US",
    "sg:address":"1505 High St",
    "sg:city":"Alameda",
    "sg:classifiers":[
        {
            "category":"Food & Beverages",
            "subcategory":"Groceries & Convenience Stores",
            "type":"Retail Goods"
        }
    ],
    "sg:phone":"+1 510 865 2529",
    "sg:postcode":"94501",
    "sg:province":"CA",
    "sg:tags":[
        "grocer"
    ],
    "wof:name":"Bonfare Market 3",
    "wof:placetype":"venue"
},
  "geometry": {"coordinates":[-122.231003,37.7593],"type":"Point"}
}