{
  "type": "Feature",
  "properties": {
    "addr:full":"10170 Lott Rd Durham CA 95938",
    "addr:housenumber":"10170",
    "addr:postcode":"95938",
    "addr:street":"Lott Rd",
    "iso:country":"US",
    "sg:address":"10170 Lott Rd",
    "sg:city":"Durham",
    "sg:classifiers":[
        {
            "category":"Professional",
            "type":"Services"
        }
    ],
    "sg:phone":"+1 530 342 1327",
    "sg:postcode":"95938",
    "sg:province":"CA",
    "wof:name":"Anthony A Lamalfa Jr",
    "wof:placetype":"venue"
},
  "geometry": {"coordinates":[-121.77379500000001,39.675734],"type":"Point"}
}