{
  "type": "Feature",
  "properties": {
    "addr:full":"9604 Greenleaf Ave Whittier CA 90605",
    "addr:housenumber":"9604",
    "addr:postcode":"90605",
    "addr:street":"Greenleaf Ave",
    "iso:country":"US",
    "sg:address":"9604 Greenleaf Ave",
    "sg:city":"Whittier",
    "sg:classifiers":[
        {
            "category":"Shopping",
            "subcategory":"Used Merchandise",
            "type":"Retail Goods"
        }
    ],
    "sg:phone":"+1 562 941 9420",
    "sg:postcode":"90605",
    "sg:province":"CA",
    "wof:name":"Dust Bunnys Haven",
    "wof:placetype":"venue"
},
  "geometry": {"coordinates":[-118.053558,33.949294],"type":"Point"}
}