{
  "type": "Feature",
  "properties": {
    "iso:country":"US",
    "sg:address":"757 Saranac Dr",
    "sg:city":"Sunnyvale",
    "sg:classifiers":[
        {
            "category":"Manufacturing",
            "subcategory":"Electronics",
            "type":"Manufacturing & Wholesale Goods"
        },
        {
            "category":"Shopping",
            "subcategory":"Computers & Home Electronics",
            "type":"Retail Goods"
        }
    ],
    "sg:phone":"+1 408 735 7575",
    "sg:postcode":"94087",
    "sg:province":"CA",
    "sg:tags":[
        "consulting",
        "management",
        "supply",
        "mfg",
        "component",
        "equipment",
        "electronic"
    ],
    "wof:name":"Joiner's Data",
    "wof:placetype":"venue"
},
  "geometry": {"coordinates":[-122.045466,37.35866],"type":"Point"}
}