{
  "type": "Feature",
  "properties": {
    "addr:full":"2721 Adriatic Way Sacramento CA 95826",
    "addr:housenumber":"2721",
    "addr:postcode":"95826",
    "addr:street":"Adriatic Way",
    "iso:country":"US",
    "sg:address":"2721 Adriatic Way",
    "sg:city":"Sacramento",
    "sg:classifiers":[
        {
            "category":"Banks & Credit Unions",
            "subcategory":"Bank",
            "type":"Services"
        }
    ],
    "sg:phone":"+1 916 364 5023",
    "sg:postcode":"95826",
    "sg:province":"CA",
    "sg:tags":[
        "loan",
        "real estate"
    ],
    "wof:name":"Mortgage Loan Specialists",
    "wof:placetype":"venue"
},
  "geometry": {"coordinates":[-121.357941,38.564865],"type":"Point"}
}