{
  "type": "Feature",
  "properties": {
    "addr:full":"1617 Westcliff Dr Ste 103 Newport Beach CA 92660",
    "addr:housenumber":"1617",
    "addr:postcode":"92660",
    "addr:street":"Westcliff Dr Ste 103",
    "iso:country":"US",
    "sg:address":"1617 Westcliff Dr Ste 103",
    "sg:city":"Newport Beach",
    "sg:classifiers":[
        {
            "category":"Shopping",
            "subcategory":"Clothing, Apparel, & Fashions",
            "type":"Retail Goods"
        }
    ],
    "sg:phone":"+1 949 515 0233",
    "sg:postcode":"92660",
    "sg:province":"CA",
    "sg:tags":[
        "clothing",
        "women's"
    ],
    "wof:name":"The Queen Bee",
    "wof:placetype":"venue"
},
  "geometry": {"coordinates":[-117.908649,33.628319],"type":"Point"}
}