{
  "type": "Feature",
  "properties": {
    "addr:full":"500 W Mount Diablo Ave Tracy CA 95376",
    "addr:housenumber":"500",
    "addr:postcode":"95376",
    "addr:street":"W Mount Diablo Ave",
    "iso:country":"US",
    "sg:address":"500 W Mount Diablo Ave",
    "sg:city":"Tracy",
    "sg:classifiers":[
        {
            "category":"Education",
            "subcategory":"School",
            "type":"Public Place"
        }
    ],
    "sg:phone":"+1 209 831 5214",
    "sg:postcode":"95376",
    "sg:province":"CA",
    "sg:website":"www.tusd.net",
    "wof:name":"South Elementary School",
    "wof:placetype":"venue"
},
  "geometry": {"coordinates":[-121.434721,37.728793],"type":"Point"}
}