{
  "type": "Feature",
  "properties": {
    "addr:full":"4439 Park Green Ct Sacramento CA 95821",
    "addr:housenumber":"4439",
    "addr:postcode":"95821",
    "addr:street":"Park Green Ct",
    "iso:country":"US",
    "sg:address":"4439 Park Green Ct",
    "sg:city":"Sacramento",
    "sg:classifiers":[
        {
            "category":"Sports & Exercise",
            "subcategory":"Gym",
            "type":"Entertainment"
        }
    ],
    "sg:phone":"+1 916 488 9663",
    "sg:postcode":"95821",
    "sg:province":"CA",
    "sg:tags":[
        "club",
        "health",
        "studio",
        "gymnasium"
    ],
    "wof:name":"Heart Zones Circuit Training",
    "wof:placetype":"venue"
},
  "geometry": {"coordinates":[-121.36038600000001,38.639131],"type":"Point"}
}