{
  "type": "Feature",
  "properties": {
    "addr:full":"1288 Columbus St # 147 San Francisco CA 94133",
    "addr:housenumber":"1288",
    "addr:postcode":"94133",
    "addr:street":"Columbus St # 147",
    "iso:country":"US",
    "sg:address":"1288 Columbus St # 147",
    "sg:city":"San Francisco",
    "sg:classifiers":[
        {
            "category":"Building & Trades",
            "subcategory":"Electrical",
            "type":"Services"
        }
    ],
    "sg:phone":"+1 415 398 2959",
    "sg:postcode":"94133",
    "sg:province":"CA",
    "sg:tags":[
        "electrician"
    ],
    "wof:name":"Premium Home Appliance",
    "wof:placetype":"venue"
},
  "geometry": {"coordinates":[-122.418238,37.805897],"type":"Point"}
}