{
  "type": "Feature",
  "properties": {
    "addr:full":"5500 Woodruff Ave Lakewood CA 90713",
    "addr:housenumber":"5500",
    "addr:postcode":"90713",
    "addr:street":"Woodruff Ave",
    "iso:country":"US",
    "sg:address":"5500 Woodruff Ave",
    "sg:city":"Lakewood",
    "sg:classifiers":[
        {
            "category":"Banks & Credit Unions",
            "subcategory":"Bank",
            "type":"Services"
        }
    ],
    "sg:phone":"+1 562 867 5457",
    "sg:postcode":"90713",
    "sg:province":"CA",
    "wof:name":"Wells Fargo Bank",
    "wof:placetype":"venue"
},
  "geometry": {"coordinates":[-118.116997,33.856602],"type":"Point"}
}