{
  "type": "Feature",
  "properties": {
    "iso:country":"US",
    "sg:address":"2030 Main Street Suite 1600",
    "sg:city":"Irvine",
    "sg:classifiers":[
        {
            "category":"Professional",
            "subcategory":"Lawyer & Legal Services",
            "type":"Services"
        }
    ],
    "sg:phone":"+1 949 476 0600",
    "sg:postcode":"92614",
    "sg:province":"CA",
    "wof:name":"Morinello Carmen Law Offices of",
    "wof:placetype":"venue"
},
  "geometry": {"coordinates":[-117.817215,33.67398],"type":"Point"}
}