{
  "type": "Feature",
  "properties": {
    "iso:country":"US",
    "sg:address":"325 Prescott Ln",
    "sg:city":"Pacific Grove",
    "sg:classifiers":[
        {
            "category":"Professional",
            "subcategory":"Printing & Photocopies",
            "type":"Services"
        }
    ],
    "sg:phone":"+1 831 373 5115",
    "sg:postcode":"93950",
    "sg:province":"CA",
    "sg:tags":[
        "blueprinting"
    ],
    "wof:name":"American Blueprint Svc",
    "wof:placetype":"venue"
},
  "geometry": {"coordinates":[-121.920515,36.604942],"type":"Point"}
}