{
  "type": "Feature",
  "properties": {
    "addr:full":"325 Prescott Ln Pacific Grove CA 93950",
    "addr:housenumber":"325",
    "addr:postcode":"93950",
    "addr:street":"Prescott Ln",
    "iso:country":"US",
    "sg:address":"325 Prescott Ln",
    "sg:city":"Pacific Grove",
    "sg:classifiers":[
        {
            "category":"Professional",
            "subcategory":"Printing & Photocopies",
            "type":"Services"
        }
    ],
    "sg:phone":"+1 831 373 5115",
    "sg:postcode":"93950",
    "sg:province":"CA",
    "sg:tags":[
        "blueprinting"
    ],
    "wof:name":"American Blueprint Svc",
    "wof:placetype":"venue"
},
  "geometry": {"coordinates":[-121.92051499999999,36.604942],"type":"Point"}
}