{
  "type": "Feature",
  "properties": {
    "iso:country":"US",
    "sg:address":"7803 Hanford Armona Rd",
    "sg:city":"Hanford",
    "sg:classifiers":[
        {
            "category":"Government",
            "subcategory":"Office",
            "type":"Public Place"
        }
    ],
    "sg:phone":"+1 559 583 8829",
    "sg:postcode":"93230",
    "sg:province":"CA",
    "sg:tags":[
        "management"
    ],
    "wof:name":"Kings County Waste Management",
    "wof:placetype":"venue"
},
  "geometry": {"coordinates":[-119.596279,36.313435],"type":"Point"}
}