{
  "type": "Feature",
  "properties": {
    "addr:full":"6630 4th Ave Sacramento CA 95817",
    "addr:housenumber":"6630",
    "addr:postcode":"95817",
    "addr:street":"4Th Ave",
    "iso:country":"US",
    "sg:address":"6630 4th Ave",
    "sg:city":"Sacramento",
    "sg:classifiers":[
        {
            "category":"Home & Garden",
            "subcategory":"Garden Supply",
            "type":"Retail Goods"
        }
    ],
    "sg:phone":"+1 916 456 4669",
    "sg:postcode":"95817",
    "sg:province":"CA",
    "wof:name":"Fox Christmas Trees",
    "wof:placetype":"venue"
},
  "geometry": {"coordinates":[-121.426203,38.548377],"type":"Point"}
}