{
  "type": "Feature",
  "properties": {
    "iso:country":"US",
    "sg:address":"13570 N Ponderosa Way",
    "sg:city":"Nevada City",
    "sg:classifiers":[
        {
            "category":"Farming",
            "subcategory":"Vineyard",
            "type":"Manufacturing & Wholesale Goods"
        }
    ],
    "sg:phone":"+1 530 272 5580",
    "sg:postcode":"95959",
    "sg:province":"CA",
    "wof:name":"North Ponderosa Vineyards",
    "wof:placetype":"venue"
},
  "geometry": {"coordinates":[-121.152512,39.253641],"type":"Point"}
}