{
  "type": "Feature",
  "properties": {
    "iso:country":"US",
    "sg:address":"516 S Broadway",
    "sg:city":"Los Angeles",
    "sg:classifiers":[
        {
            "category":"Shopping",
            "subcategory":"Gifts & Souvenirs",
            "type":"Retail Goods"
        }
    ],
    "sg:phone":"+1 213 327 0904",
    "sg:postcode":"90013",
    "sg:province":"CA",
    "sg:tags":[
        "flower"
    ],
    "wof:name":"Vital Works",
    "wof:placetype":"venue"
},
  "geometry": {"coordinates":[-118.251098,34.047826],"type":"Point"}
}