{
  "type": "Feature",
  "properties": {
    "addr:full":"285 S San Gabriel Blvd Pasadena CA 91107",
    "addr:housenumber":"285",
    "addr:postcode":"91107",
    "addr:street":"S San Gabriel Blvd",
    "iso:country":"US",
    "sg:address":"285 S San Gabriel Blvd",
    "sg:city":"Pasadena",
    "sg:classifiers":[
        {
            "category":"Wholesale",
            "subcategory":"Electrical",
            "type":"Manufacturing & Wholesale Goods"
        }
    ],
    "sg:phone":"+1 626 792 5557",
    "sg:postcode":"91107",
    "sg:province":"CA",
    "sg:tags":[
        "equipment",
        "electric",
        "merchandise"
    ],
    "wof:name":"Lees Electronics",
    "wof:placetype":"venue"
},
  "geometry": {"coordinates":[-118.094714,34.140298],"type":"Point"}
}