{
  "type": "Feature",
  "properties": {
    "iso:country":"US",
    "sg:address":"44 Commerce Pl",
    "sg:city":"Vacaville",
    "sg:classifiers":[
        {
            "category":"Shopping",
            "type":"Retail Goods"
        }
    ],
    "sg:phone":"+1 707 689 6004",
    "sg:postcode":"95687",
    "sg:province":"CA",
    "sg:tags":[
        "aquarium"
    ],
    "wof:name":"Paradise Aquatics",
    "wof:placetype":"venue"
},
  "geometry": {"coordinates":[-121.936501,38.353084],"type":"Point"}
}