{
  "type": "Feature",
  "properties": {
    "addr:full":"1618 W 134th St Gardena CA 90249",
    "addr:housenumber":"1618",
    "addr:postcode":"90249",
    "addr:street":"W 134Th St",
    "iso:country":"US",
    "sg:address":"1618 W 134th St",
    "sg:city":"Gardena",
    "sg:classifiers":[
        {
            "category":"Wholesale",
            "subcategory":"Durable Goods & Equipment",
            "type":"Manufacturing & Wholesale Goods"
        }
    ],
    "sg:phone":"+1 310 327 2139",
    "sg:postcode":"90249",
    "sg:province":"CA",
    "wof:name":"Pt Supply",
    "wof:placetype":"venue"
},
  "geometry": {"coordinates":[-118.30278800000001,33.910724],"type":"Point"}
}