{
  "type": "Feature",
  "properties": {
    "iso:country":"US",
    "sg:address":"231 E Alessandro Blvd",
    "sg:city":"Riverside",
    "sg:classifiers":[
        {
            "category":"Mining & Drilling",
            "type":"Manufacturing & Wholesale Goods"
        }
    ],
    "sg:phone":"+1 951 776 3975",
    "sg:postcode":"92508",
    "sg:province":"CA",
    "sg:tags":[
        "well"
    ],
    "wof:name":"Directional Resrcs",
    "wof:placetype":"venue"
},
  "geometry": {"coordinates":[-117.324398,33.916326],"type":"Point"}
}