{
  "type": "Feature",
  "properties": {
    "addr:full":"2322 I St Sacramento CA 95816",
    "addr:housenumber":"2322",
    "addr:postcode":"95816",
    "addr:street":"I St",
    "iso:country":"US",
    "sg:address":"2322 I St",
    "sg:city":"Sacramento",
    "sg:phone":"+1 916 442 7878",
    "sg:postcode":"95816",
    "sg:province":"CA",
    "sg:tags":[
        "equipment",
        "shelving",
        "commercial"
    ],
    "sg:website":"http://www.catalyst.net",
    "wof:name":"Harriman Systems Shelving",
    "wof:placetype":"venue"
},
  "geometry": {"coordinates":[-121.475112,38.576646],"type":"Point"}
}