{
  "type": "Feature",
  "properties": {
    "iso:country":"US",
    "sg:address":"744 Hillcrest Ln",
    "sg:city":"Fallbrook",
    "sg:classifiers":[
        {
            "category":"Farming",
            "subcategory":"Crops",
            "type":"Manufacturing & Wholesale Goods"
        }
    ],
    "sg:phone":"+1 760 731 0992",
    "sg:postcode":"92028",
    "sg:province":"CA",
    "sg:tags":[
        "farm"
    ],
    "wof:name":"Hacienda Avocados",
    "wof:placetype":"venue"
},
  "geometry": {"coordinates":[-117.24438600000001,33.391184],"type":"Point"}
}