{
  "type": "Feature",
  "properties": {
    "addr:full":"1701 W Sequoia Ave Orange CA 92868",
    "addr:housenumber":"1701",
    "addr:postcode":"92868",
    "addr:street":"W Sequoia Ave",
    "iso:country":"US",
    "sg:address":"1701 W Sequoia Ave",
    "sg:city":"Orange",
    "sg:classifiers":[
        {
            "category":"Manufacturing",
            "subcategory":"Electronics",
            "type":"Manufacturing & Wholesale Goods"
        }
    ],
    "sg:phone":"+1 714 939 6699",
    "sg:postcode":"92868",
    "sg:province":"CA",
    "sg:tags":[
        "communications",
        "electronic",
        "mfg"
    ],
    "wof:name":"Zettler Components Inc",
    "wof:placetype":"venue"
},
  "geometry": {"coordinates":[-117.87375900000001,33.798444],"type":"Point"}
}