{
  "type": "Feature",
  "properties": {
    "addr:full":"10540 Anderson St Loma Linda CA 92354",
    "addr:housenumber":"10540",
    "addr:postcode":"92354",
    "addr:street":"Anderson St",
    "iso:country":"US",
    "sg:address":"10540 Anderson St",
    "sg:city":"Loma Linda",
    "sg:classifiers":[
        {
            "category":"Restaurant",
            "type":"Food & Drink"
        }
    ],
    "sg:phone":"+1 909 796 7827",
    "sg:postcode":"92354",
    "sg:province":"CA",
    "wof:name":"B K Subs",
    "wof:placetype":"venue"
},
  "geometry": {"coordinates":[-117.26128,34.06249],"type":"Point"}
}