{
  "type": "Feature",
  "properties": {
    "addr:full":"14322 Di Giorgio Rd Arvin CA 93203",
    "addr:postcode":"93203",
    "addr:street":"Di Giorgio Rd",
    "iso:country":"US",
    "sg:address":"14322 Di Giorgio Rd",
    "sg:city":"Arvin",
    "sg:classifiers":[
        {
            "category":"Wholesale",
            "subcategory":"Fruits & Vegetables",
            "type":"Manufacturing & Wholesale Goods"
        }
    ],
    "sg:phone":"+1 661 854 4436",
    "sg:postcode":"93203",
    "sg:province":"CA",
    "sg:tags":[
        "shipper"
    ],
    "sg:website":"www.greenvalleypackers.com",
    "wof:name":"Green Valley Packers",
    "wof:placetype":"venue"
},
  "geometry": {"coordinates":[-118.84430500000001,35.252762],"type":"Point"}
}