{
  "type": "Feature",
  "properties": {
    "addr:full":"1144 E Elizabeth St Fresno CA 93728",
    "addr:housenumber":"1144",
    "addr:postcode":"93728",
    "addr:street":"E Elizabeth St",
    "iso:country":"US",
    "sg:address":"1144 E Elizabeth St",
    "sg:city":"Fresno",
    "sg:classifiers":[
        {
            "category":"Real Estate",
            "subcategory":"Real Estate Operator",
            "type":"Services"
        }
    ],
    "sg:phone":"+1 559 485 1408",
    "sg:postcode":"93728",
    "sg:province":"CA",
    "sg:tags":[
        "apartment"
    ],
    "wof:name":"Tower Court Apartments",
    "wof:placetype":"venue"
},
  "geometry": {"coordinates":[-119.79686599999999,36.75528],"type":"Point"}
}