{
  "type": "Feature",
  "properties": {
    "iso:country":"US",
    "sg:address":"7149 Weedpatch Hwy",
    "sg:city":"Bakersfield",
    "sg:classifiers":[
        {
            "category":"Wholesale",
            "subcategory":"Fruits & Vegetables",
            "type":"Manufacturing & Wholesale Goods"
        }
    ],
    "sg:phone":"+1 661 845 1071",
    "sg:postcode":"93307",
    "sg:province":"CA",
    "wof:name":"Johnny's Produce",
    "wof:placetype":"venue"
},
  "geometry": {"coordinates":[-118.914333,35.296116],"type":"Point"}
}