{
  "type": "Feature",
  "properties": {
    "addr:full":"3400 Mount Diablo Blvd Lafayette CA 94549",
    "addr:housenumber":"3400",
    "addr:postcode":"94549",
    "addr:street":"Mount Diablo Blvd",
    "iso:country":"US",
    "sg:address":"3400 Mount Diablo Blvd",
    "sg:city":"Lafayette",
    "sg:classifiers":[
        {
            "category":"Real Estate",
            "subcategory":"Real Estate Agent",
            "type":"Services"
        }
    ],
    "sg:phone":"+1 925 933 4000",
    "sg:postcode":"94549",
    "sg:province":"CA",
    "wof:name":"Hall Equities Group",
    "wof:placetype":"venue"
},
  "geometry": {"coordinates":[-122.109707,37.893743],"type":"Point"}
}