{
  "type": "Feature",
  "properties": {
    "addr:full":"957 Maple St Carpinteria CA 93013",
    "addr:housenumber":"957",
    "addr:postcode":"93013",
    "addr:street":"Maple St",
    "iso:country":"US",
    "sg:address":"957 Maple St",
    "sg:city":"Carpinteria",
    "sg:classifiers":[
        {
            "category":"Health Services",
            "subcategory":"Doctor",
            "type":"Services"
        },
        {
            "category":"Health Services",
            "subcategory":"Clinic",
            "type":"Services"
        }
    ],
    "sg:phone":"+1 805 566 0441",
    "sg:postcode":"93013",
    "sg:province":"CA",
    "sg:tags":[
        "counseling",
        "mental"
    ],
    "sg:website":"www.docrotz.com/",
    "wof:name":"Rotz Roland PHD",
    "wof:placetype":"venue"
},
  "geometry": {"coordinates":[-119.51799800000001,34.3978],"type":"Point"}
}