{
  "type": "Feature",
  "properties": {
    "iso:country":"US",
    "sg:address":"6080 Valley View Ct",
    "sg:city":"Placerville",
    "sg:classifiers":[
        {
            "category":"Banks & Credit Unions",
            "subcategory":"Investment Brokerage",
            "type":"Services"
        }
    ],
    "sg:phone":"+1 530 644 5099",
    "sg:postcode":"95667",
    "sg:province":"CA",
    "sg:tags":[
        "broker",
        "commodity"
    ],
    "wof:name":"True Color Lithographics",
    "wof:placetype":"venue"
},
  "geometry": {"coordinates":[-120.607107,38.697898],"type":"Point"}
}