{
  "type": "Feature",
  "properties": {
    "iso:country":"US",
    "sg:address":"6226 Colfax Ave",
    "sg:city":"North Hollywood",
    "sg:classifiers":[
        {
            "category":"Organizations",
            "subcategory":"Religious Organization",
            "type":"Services"
        }
    ],
    "sg:phone":"+1 818 508 6467",
    "sg:postcode":"91606",
    "sg:province":"CA",
    "sg:tags":[
        "church"
    ],
    "wof:name":"Iglesia Evangelica Bethel",
    "wof:placetype":"venue"
},
  "geometry": {"coordinates":[-118.38800000000001,34.184399],"type":"Point"}
}