{
  "type": "Feature",
  "properties": {
    "iso:country":"US",
    "sg:address":"716 Perrott Ave",
    "sg:city":"Loleta",
    "sg:classifiers":[
        {
            "category":"Professional",
            "subcategory":"Business Services",
            "type":"Services"
        }
    ],
    "sg:phone":"+1 707 733 9516",
    "sg:postcode":"95540",
    "sg:province":"CA",
    "sg:tags":[
        "appraiser"
    ],
    "wof:name":"North Pacific Appraisal Svc",
    "wof:placetype":"venue"
},
  "geometry": {"coordinates":[-124.22009,40.645823],"type":"Point"}
}