{
  "type": "Feature",
  "properties": {
    "addr:full":"1844 Almaden Rd San Jose CA 95125",
    "addr:housenumber":"1844",
    "addr:postcode":"95125",
    "addr:street":"Almaden Rd",
    "iso:country":"US",
    "sg:address":"1844 Almaden Rd",
    "sg:city":"San Jose",
    "sg:classifiers":[
        {
            "category":"Home & Garden",
            "subcategory":"Building Materials",
            "type":"Retail Goods"
        }
    ],
    "sg:phone":"+1 408 269 5232",
    "sg:postcode":"95125",
    "sg:province":"CA",
    "sg:tags":[
        "glass",
        "window",
        "plate"
    ],
    "wof:name":"South Valley Auto Glass",
    "wof:placetype":"venue"
},
  "geometry": {"coordinates":[-121.880217,37.299927],"type":"Point"}
}