{
  "type": "Feature",
  "properties": {
    "addr:full":"44150 Town Center Way Palm Desert CA 92260",
    "addr:housenumber":"44150",
    "addr:postcode":"ca 92260",
    "addr:street":"Town Center Way",
    "iso:country":"US",
    "sg:address":"44150 Town Center Way",
    "sg:city":"Palm Desert",
    "sg:classifiers":[
        {
            "category":"Restaurant",
            "type":"Food & Drink"
        }
    ],
    "sg:phone":"+1 760 779 1617",
    "sg:postcode":"92260",
    "sg:province":"CA",
    "wof:name":"Palms Cafe",
    "wof:placetype":"venue"
},
  "geometry": {"coordinates":[-116.398376,33.728268],"type":"Point"}
}