{
  "type": "Feature",
  "properties": {
    "iso:country":"US",
    "sg:address":"391 Fenley Ave",
    "sg:city":"San Jose",
    "sg:classifiers":[
        {
            "category":"Communications",
            "type":"Services"
        }
    ],
    "sg:phone":"+1 408 984 3444",
    "sg:postcode":"95117",
    "sg:province":"CA",
    "sg:tags":[
        "communication"
    ],
    "wof:name":"Powelson Communications",
    "wof:placetype":"venue"
},
  "geometry": {"coordinates":[-121.95642599999999,37.320119],"type":"Point"}
}