{
  "type": "Feature",
  "properties": {
    "addr:full":"1862 Homestead Rd Santa Clara CA 95050",
    "addr:housenumber":"1862",
    "addr:postcode":"95050",
    "addr:street":"Homestead Rd",
    "iso:country":"US",
    "sg:address":"1862 Homestead Rd",
    "sg:city":"Santa Clara",
    "sg:classifiers":[
        {
            "category":"Farming",
            "subcategory":"Orchard",
            "type":"Manufacturing & Wholesale Goods"
        }
    ],
    "sg:phone":"+1 408 243 6661",
    "sg:postcode":"95050",
    "sg:province":"CA",
    "sg:tags":[
        "fruit",
        "tree"
    ],
    "wof:name":"Burton Skow",
    "wof:placetype":"venue"
},
  "geometry": {"coordinates":[-121.956399,37.343759],"type":"Point"}
}