{
  "type": "Feature",
  "properties": {
    "iso:country":"US",
    "sg:address":"1316 E Katella Ave",
    "sg:city":"Anaheim",
    "sg:classifiers":[
        {
            "category":"Manufacturing",
            "subcategory":"Printing",
            "type":"Manufacturing & Wholesale Goods"
        }
    ],
    "sg:phone":"+1 714 633 9600",
    "sg:postcode":"92805",
    "sg:province":"CA",
    "sg:tags":[
        "commercial"
    ],
    "wof:name":"Heritage Enterprises",
    "wof:placetype":"venue"
},
  "geometry": {"coordinates":[-117.895791,33.803266],"type":"Point"}
}