{
  "type": "Feature",
  "properties": {
    "addr:full":"885 N San Antonio Rd Los Altos CA 94022",
    "addr:housenumber":"885",
    "addr:postcode":"94022",
    "addr:street":"N San Antonio Rd",
    "iso:country":"US",
    "sg:address":"885 N San Antonio Rd",
    "sg:city":"Los Altos",
    "sg:classifiers":[
        {
            "category":"Insurance",
            "subcategory":"Insurance Agent",
            "type":"Services"
        }
    ],
    "sg:phone":"+1 650 917 1520",
    "sg:postcode":"94022",
    "sg:province":"CA",
    "wof:name":"Post Risk Management Insurance",
    "wof:placetype":"venue"
},
  "geometry": {"coordinates":[-122.114125,37.39849],"type":"Point"}
}