{
  "type": "Feature",
  "properties": {
    "iso:country":"US",
    "sg:address":"120 W Inyo Ave",
    "sg:city":"Tulare",
    "sg:classifiers":[
        {
            "category":"Professional",
            "subcategory":"Accounting & Tax Preparation",
            "type":"Services"
        }
    ],
    "sg:phone":"+1 559 685 5602",
    "sg:postcode":"93274",
    "sg:province":"CA",
    "sg:tags":[
        "payroll"
    ],
    "wof:name":"Payroll Card",
    "wof:placetype":"venue"
},
  "geometry": {"coordinates":[-119.34914000000001,36.205033],"type":"Point"}
}