{
  "type": "Feature",
  "properties": {
    "addr:full":"937 Cam Caballo Nipomo CA 93444",
    "addr:housenumber":"937",
    "addr:postcode":"93444",
    "addr:street":"Cam Caballo",
    "iso:country":"US",
    "sg:address":"937 Cam Caballo",
    "sg:city":"Nipomo",
    "sg:classifiers":[
        {
            "category":"Real Estate",
            "subcategory":"Real Estate Agent",
            "type":"Services"
        }
    ],
    "sg:phone":"+1 805 929 2839",
    "sg:postcode":"93444",
    "sg:province":"CA",
    "wof:name":"In House Homes & Loans",
    "wof:placetype":"venue"
},
  "geometry": {"coordinates":[-120.512809,35.035063],"type":"Point"}
}