{
  "type": "Feature",
  "properties": {
    "addr:full":"10935 San Marcos Rd Atascadero CA 93422",
    "addr:housenumber":"10935",
    "addr:postcode":"93422",
    "addr:street":"San Marcos Rd",
    "iso:country":"US",
    "sg:address":"10935 San Marcos Rd",
    "sg:city":"Atascadero",
    "sg:classifiers":[
        {
            "category":"Manufacturing",
            "subcategory":"Jewelry",
            "type":"Manufacturing & Wholesale Goods"
        }
    ],
    "sg:phone":"+1 805 235 4749",
    "sg:postcode":"93422",
    "sg:province":"CA",
    "sg:tags":[
        "costume",
        "mfg"
    ],
    "wof:name":"Stacie Horton Cookie Lee Jwly",
    "wof:placetype":"venue"
},
  "geometry": {"coordinates":[-120.700957,35.457197],"type":"Point"}
}