{
  "type": "Feature",
  "properties": {
    "addr:full":"333 W Santa Clara St Ste 300 San Jose CA 95113",
    "addr:housenumber":"333",
    "addr:postcode":"95113",
    "addr:street":"W Santa Clara St Ste 300",
    "iso:country":"US",
    "sg:address":"333 W Santa Clara St Ste 300",
    "sg:city":"San Jose",
    "sg:classifiers":[
        {
            "category":"Coffee & Tea",
            "type":"Food & Drink"
        },
        {
            "category":"Food & Beverages",
            "subcategory":"Bakery",
            "type":"Retail Goods"
        },
        {
            "category":"Bagels",
            "subcategory":"None",
            "type":"Food & Drink"
        }
    ],
    "sg:phone":"+1 408 971 2804",
    "sg:postcode":"95113",
    "sg:province":"CA",
    "sg:tags":[
        "sandwich"
    ],
    "wof:name":"Nosh Cafe & Catering",
    "wof:placetype":"venue"
},
  "geometry": {"coordinates":[-121.89619999999999,37.334315],"type":"Point"}
}