{
  "type": "Feature",
  "properties": {
    "addr:full":"3200 Airport Ave Ste 10 Santa Monica CA 90405",
    "addr:housenumber":"3200",
    "addr:postcode":"90405",
    "addr:street":"Airport Ave Ste 10",
    "iso:country":"US",
    "sg:address":"3200 Airport Ave Ste 10",
    "sg:city":"Santa Monica",
    "sg:classifiers":[
        {
            "category":"Professional",
            "type":"Services"
        }
    ],
    "sg:phone":"+1 213 457 9507",
    "sg:postcode":"90405",
    "sg:province":"CA",
    "wof:name":"Richard Clemenson Associates",
    "wof:placetype":"venue"
},
  "geometry": {"coordinates":[-118.446865,34.015544],"type":"Point"}
}