{
  "type": "Feature",
  "properties": {
    "addr:full":"8480 Melrose Ln El Cajon CA 92021",
    "addr:housenumber":"8480",
    "addr:postcode":"92021",
    "addr:street":"Melrose Ln",
    "iso:country":"US",
    "sg:address":"8480 Melrose Ln",
    "sg:city":"El Cajon",
    "sg:classifiers":[
        {
            "category":"Manufacturing",
            "subcategory":"Glass & Minerals",
            "type":"Manufacturing & Wholesale Goods"
        }
    ],
    "sg:phone":"+1 619 443 5794",
    "sg:postcode":"92021",
    "sg:province":"CA",
    "sg:tags":[
        "product",
        "mfg"
    ],
    "wof:name":"John R Pangborn",
    "wof:placetype":"venue"
},
  "geometry": {"coordinates":[-116.921121,32.829818],"type":"Point"}
}