{
  "type": "Feature",
  "properties": {
    "addr:full":"11371 Lower Circle Dr Grass Valley CA 95949",
    "addr:housenumber":"11371",
    "addr:postcode":"95949",
    "addr:street":"Lower Circle Dr",
    "iso:country":"US",
    "sg:address":"11371 Lower Circle Dr",
    "sg:city":"Grass Valley",
    "sg:classifiers":[
        {
            "category":"Education",
            "subcategory":"Special Training",
            "type":"Public Place"
        }
    ],
    "sg:phone":"+1 530 273 6760",
    "sg:postcode":"95949",
    "sg:province":"CA",
    "sg:tags":[
        "reading",
        "instruction",
        "improvement"
    ],
    "wof:name":"Nancy Mitchell Language Arts",
    "wof:placetype":"venue"
},
  "geometry": {"coordinates":[-121.04985000000001,39.13843],"type":"Point"}
}