{
  "type": "Feature",
  "properties": {
    "addr:full":"5007 Gage Ave Bell CA 90201",
    "addr:housenumber":"5007",
    "addr:postcode":"90201",
    "addr:street":"Gage Ave",
    "iso:country":"US",
    "sg:address":"5007 Gage Ave",
    "sg:city":"Bell",
    "sg:classifiers":[
        {
            "category":"Shopping",
            "subcategory":"Musical Instruments",
            "type":"Retail Goods"
        }
    ],
    "sg:phone":"+1 323 560 1551",
    "sg:postcode":"90201",
    "sg:province":"CA",
    "sg:tags":[
        "music",
        "dealer"
    ],
    "wof:name":"Del Sol Music",
    "wof:placetype":"venue"
},
  "geometry": {"coordinates":[-118.175764,33.976892],"type":"Point"}
}