{
  "type": "Feature",
  "properties": {
    "addr:full":"22915 Canyon Way Colfax CA 95713",
    "addr:housenumber":"22915",
    "addr:postcode":"95713",
    "addr:street":"Canyon Way",
    "iso:country":"US",
    "sg:address":"22915 Canyon Way",
    "sg:city":"Colfax",
    "sg:classifiers":[
        {
            "category":"Professional",
            "subcategory":"Art Services",
            "type":"Services"
        }
    ],
    "sg:phone":"+1 530 346 9399",
    "sg:postcode":"95713",
    "sg:province":"CA",
    "sg:tags":[
        "graphic",
        "designer"
    ],
    "wof:name":"Mystic Design",
    "wof:placetype":"venue"
},
  "geometry": {"coordinates":[-120.96119400000001,39.074097],"type":"Point"}
}