{
  "type": "Feature",
  "properties": {
    "addr:full":"3110 Deronda Drive Los Angeles CA 90068",
    "addr:housenumber":"3110",
    "addr:postcode":"90068",
    "addr:street":"Deronda Drive",
    "iso:country":"US",
    "sg:address":"3110 Deronda Drive",
    "sg:city":"Los Angeles",
    "sg:classifiers":[
        {
            "category":"Real Estate",
            "subcategory":"Architect",
            "type":"Services"
        }
    ],
    "sg:phone":"+1 323 464 7226",
    "sg:postcode":"90068",
    "sg:province":"CA",
    "wof:name":"Chuda James Archt",
    "wof:placetype":"venue"
},
  "geometry": {"coordinates":[-118.321574,34.126782],"type":"Point"}
}