{
  "type": "Feature",
  "properties": {
    "iso:country":"US",
    "sg:address":"303 Vintage Park Dr Ste 110",
    "sg:city":"Foster City",
    "sg:classifiers":[
        {
            "category":"Professional",
            "subcategory":"Lawyer & Legal Services",
            "type":"Services"
        }
    ],
    "sg:phone":"+1 650 349 9000",
    "sg:postcode":"94404",
    "sg:province":"CA",
    "sg:website":"www.bayareafamilyattorney.com",
    "wof:name":"The Wenzell Law Group",
    "wof:placetype":"venue"
},
  "geometry": {"coordinates":[-122.277056,37.568056],"type":"Point"}
}