{
  "type": "Feature",
  "properties": {
    "addr:full":"660 W 7th St San Pedro CA 90731",
    "addr:housenumber":"660",
    "addr:postcode":"90731",
    "addr:street":"W 7Th St",
    "iso:country":"US",
    "sg:address":"660 W 7th St",
    "sg:city":"San Pedro",
    "sg:classifiers":[
        {
            "category":"Health Services",
            "subcategory":"Chiropractor",
            "type":"Services"
        }
    ],
    "sg:phone":"+1 310 832 4476",
    "sg:postcode":"90731",
    "sg:province":"CA",
    "wof:name":"Absolutely Vital Chiropractic",
    "wof:placetype":"venue"
},
  "geometry": {"coordinates":[-118.291208,33.737935],"type":"Point"}
}