{
  "type": "Feature",
  "properties": {
    "addr:full":"634 Oak Grove Dr Glendora CA 91741",
    "addr:housenumber":"634",
    "addr:postcode":"91741",
    "addr:street":"Oak Grove Dr",
    "iso:country":"US",
    "sg:address":"634 Oak Grove Dr",
    "sg:city":"Glendora",
    "sg:classifiers":[
        {
            "category":"Banks & Credit Unions",
            "subcategory":"Investment Brokerage",
            "type":"Services"
        }
    ],
    "sg:phone":"+1 626 335 8317",
    "sg:postcode":"91741",
    "sg:province":"CA",
    "sg:tags":[
        "trust"
    ],
    "wof:name":"Schell Family Trust 09 21",
    "wof:placetype":"venue"
},
  "geometry": {"coordinates":[-117.856121,34.151719],"type":"Point"}
}