{
  "type": "Feature",
  "properties": {
    "addr:full":"5 Lucerne Street #1 San Francisco CA 94103",
    "addr:housenumber":"5",
    "addr:postcode":"94103",
    "addr:street":"Lucerne Street # 1",
    "iso:country":"US",
    "sg:address":"5 Lucerne Street #1",
    "sg:city":"San Francisco",
    "sg:classifiers":[
        {
            "category":"Professional",
            "subcategory":"Computer Services",
            "type":"Services"
        }
    ],
    "sg:postcode":"94103",
    "sg:province":"CA",
    "sg:tags":[
        "reminder-calendar-event-api"
    ],
    "sg:website":"http://remindblast.com",
    "wof:name":"RemindBlast",
    "wof:placetype":"venue"
},
  "geometry": {"coordinates":[-122.401259,37.773439],"type":"Point"}
}