{
  "type": "Feature",
  "properties": {
    "iso:country":"US",
    "sg:address":"1004 Washington Ave",
    "sg:city":"Winters",
    "sg:classifiers":[
        {
            "category":"Retail",
            "subcategory":"Animal Services",
            "type":"Services"
        }
    ],
    "sg:phone":"+1 530 795 2705",
    "sg:postcode":"95694",
    "sg:province":"CA",
    "sg:tags":[
        "pet",
        "grooming",
        "washing"
    ],
    "wof:name":"Carolyn's Dog Grooming",
    "wof:placetype":"venue"
},
  "geometry": {"coordinates":[-121.98486800000001,38.520861],"type":"Point"}
}