{
  "type": "Feature",
  "properties": {
    "addr:full":"14015 Poway Rd Poway CA 92064",
    "addr:housenumber":"14015",
    "addr:postcode":"ca 92064",
    "addr:street":"Poway Rd",
    "iso:country":"US",
    "sg:address":"14015 Poway Rd",
    "sg:city":"Poway",
    "sg:classifiers":[
        {
            "category":"Retail",
            "subcategory":"Auto Repair",
            "type":"Services"
        }
    ],
    "sg:phone":"+1 858 486 1626",
    "sg:postcode":"92064",
    "sg:province":"CA",
    "sg:tags":[
        "repairing",
        "automobile"
    ],
    "wof:name":"Darnell's Automotive",
    "wof:placetype":"venue"
},
  "geometry": {"coordinates":[-117.02638399999999,32.956189],"type":"Point"}
}