{
  "type": "Feature",
  "properties": {
    "addr:full":"222 N T St Lompoc CA 93436",
    "addr:housenumber":"222",
    "addr:postcode":"93436",
    "addr:street":"N T St",
    "iso:country":"US",
    "sg:address":"222 N T St",
    "sg:city":"Lompoc",
    "sg:classifiers":[
        {
            "category":"Real Estate",
            "subcategory":"Real Estate Operator",
            "type":"Services"
        }
    ],
    "sg:phone":"+1 805 735 7437",
    "sg:postcode":"93436",
    "sg:province":"CA",
    "sg:tags":[
        "apartment"
    ],
    "wof:name":"Westcreek Villa",
    "wof:placetype":"venue"
},
  "geometry": {"coordinates":[-120.47299099999999,34.641579],"type":"Point"}
}