{
  "type": "Feature",
  "properties": {
    "addr:full":"42300 de Luz Rd Temecula CA 92590",
    "addr:postcode":"42300;92590",
    "addr:street":"De Luz Rd",
    "iso:country":"US",
    "sg:address":"42300 de Luz Rd",
    "sg:city":"Temecula",
    "sg:classifiers":[
        {
            "category":"Mining & Drilling",
            "type":"Manufacturing & Wholesale Goods"
        }
    ],
    "sg:phone":"+1 951 695 5522",
    "sg:postcode":"92590",
    "sg:province":"CA",
    "sg:tags":[
        "field"
    ],
    "wof:name":"Memory Lane",
    "wof:placetype":"venue"
},
  "geometry": {"coordinates":[-117.206075,33.5353],"type":"Point"}
}