{
  "type": "Feature",
  "properties": {
    "iso:country":"US",
    "sg:address":"27349 Jefferson Ave",
    "sg:city":"Temecula",
    "sg:classifiers":[
        {
            "category":"Communications",
            "subcategory":"Radio Station",
            "type":"Services"
        }
    ],
    "sg:phone":"+1 951 699 1399",
    "sg:postcode":"92562",
    "sg:province":"CA",
    "sg:tags":[
        "broadcast"
    ],
    "wof:name":"Kogo FM",
    "wof:placetype":"venue"
},
  "geometry": {"coordinates":[-117.16718,33.52304],"type":"Point"}
}