{
  "type": "Feature",
  "properties": {
    "addr:full":"2010 Jimmy Durante Blvd Del Mar CA 92014",
    "addr:housenumber":"2010",
    "addr:postcode":"92014",
    "addr:street":"Jimmy Durante Blvd",
    "iso:country":"US",
    "sg:address":"2010 Jimmy Durante Blvd",
    "sg:city":"Del Mar",
    "sg:classifiers":[
        {
            "category":"Professional",
            "subcategory":"Advertising",
            "type":"Services"
        }
    ],
    "sg:phone":"+1 858 259 2000",
    "sg:postcode":"92014",
    "sg:province":"CA",
    "sg:tags":[
        "counselor"
    ],
    "wof:name":"Big Bang Idea Engineering",
    "wof:placetype":"venue"
},
  "geometry": {"coordinates":[-117.265123,32.967436],"type":"Point"}
}