{
  "type": "Feature",
  "properties": {
    "addr:full":"2319 Troy Ave South El Monte CA 91733",
    "addr:housenumber":"2319",
    "addr:postcode":"91733",
    "addr:street":"Troy Ave",
    "iso:country":"US",
    "sg:address":"2319 Troy Ave",
    "sg:city":"South El Monte",
    "sg:classifiers":[
        {
            "category":"Wholesale",
            "subcategory":"Machinery & Supplies",
            "type":"Manufacturing & Wholesale Goods"
        }
    ],
    "sg:phone":"+1 626 448 5739",
    "sg:postcode":"91733",
    "sg:province":"CA",
    "sg:tags":[
        "food",
        "equipment",
        "product",
        "processing"
    ],
    "wof:name":"Trejo's Food Equipment",
    "wof:placetype":"venue"
},
  "geometry": {"coordinates":[-118.06587500000001,34.055375],"type":"Point"}
}