{
  "type": "Feature",
  "properties": {
    "addr:full":"1208 Floyd Ave Ste. B-6 Modesto CA 95350",
    "addr:housenumber":"1208",
    "addr:postcode":"ca 95350",
    "addr:street":"Floyd Ave Ste. B-6",
    "iso:country":"US",
    "sg:address":"1208 Floyd Ave Ste. B-6",
    "sg:city":"Modesto",
    "sg:classifiers":[
        {
            "category":"Manufacturing",
            "subcategory":"Chemicals & Compounds",
            "type":"Manufacturing & Wholesale Goods"
        },
        {
            "category":"Personal",
            "subcategory":"Hair Removal",
            "type":"Services"
        }
    ],
    "sg:phone":"+1 209 531 6884",
    "sg:postcode":"95350",
    "sg:province":"CA",
    "sg:tags":[
        "electrolysis"
    ],
    "wof:name":"Arnett Janet Licensed Electrologist",
    "wof:placetype":"venue"
},
  "geometry": {"coordinates":[-120.977531,37.67804],"type":"Point"}
}