{
  "type": "Feature",
  "properties": {
    "addr:full":"2200 Santa Ana Valley Rd Hollister CA 95023",
    "addr:housenumber":"2200",
    "addr:postcode":"hollister ca 95023",
    "addr:street":"Santa Ana Valley Rd",
    "iso:country":"US",
    "sg:address":"2200 Santa Ana Valley Rd",
    "sg:city":"Hollister",
    "sg:classifiers":[
        {
            "category":"Real Estate",
            "subcategory":"Real Estate Agent",
            "type":"Services"
        }
    ],
    "sg:phone":"+1 831 637 2544",
    "sg:postcode":"95023",
    "sg:province":"CA",
    "wof:name":"Del Felice Realty",
    "wof:placetype":"venue"
},
  "geometry": {"coordinates":[-121.32015,36.85372],"type":"Point"}
}