{
  "type": "Feature",
  "properties": {
    "addr:full":"13435 Mulberry Dr Apt 16 Whittier CA 90605",
    "addr:housenumber":"13435;16",
    "addr:postcode":"90605",
    "addr:street":"Mulberry Dr Apt",
    "iso:country":"US",
    "sg:address":"13435 Mulberry Dr Apt 16",
    "sg:city":"Whittier",
    "sg:classifiers":[
        {
            "category":"Real Estate",
            "subcategory":"Real Estate Operator",
            "type":"Services"
        }
    ],
    "sg:phone":"+1 562 698 1692",
    "sg:postcode":"90605",
    "sg:province":"CA",
    "sg:tags":[
        "apartment"
    ],
    "wof:name":"Stoneridge Apartments",
    "wof:placetype":"venue"
},
  "geometry": {"coordinates":[-118.041639,33.952735],"type":"Point"}
}