{
  "type": "Feature",
  "properties": {
    "addr:full":"1107 N Tustin St Orange CA 92867",
    "addr:housenumber":"1107",
    "addr:postcode":"92867",
    "addr:street":"N Tustin St",
    "iso:country":"US",
    "sg:address":"1107 N Tustin St",
    "sg:city":"Orange",
    "sg:classifiers":[
        {
            "category":"Restaurant",
            "type":"Food & Drink"
        }
    ],
    "sg:phone":"+1 714 532 6311",
    "sg:postcode":"92867",
    "sg:province":"CA",
    "wof:name":"Quan's Restaurant",
    "wof:placetype":"venue"
},
  "geometry": {"coordinates":[-117.835589,33.805628],"type":"Point"}
}