{
  "type": "Feature",
  "properties": {
    "addr:full":"20140 Pine Dr W Pioneer CA 95666",
    "addr:housenumber":"20140",
    "addr:postcode":"95666",
    "addr:street":"Pine Dr W",
    "iso:country":"US",
    "sg:address":"20140 Pine Dr W",
    "sg:city":"Pioneer",
    "sg:classifiers":[
        {
            "category":"Building & Trades",
            "subcategory":"Construction",
            "type":"Services"
        }
    ],
    "sg:phone":"+1 209 295 2800",
    "sg:postcode":"95666",
    "sg:province":"CA",
    "sg:tags":[
        "masonry",
        "contractor"
    ],
    "wof:name":"Leland Peterson Construction",
    "wof:placetype":"venue"
},
  "geometry": {"coordinates":[-120.53326300000001,38.501646],"type":"Point"}
}