{
  "type": "Feature",
  "properties": {
    "addr:full":"1102 Wieling Way Petaluma CA 94954",
    "addr:housenumber":"1102",
    "addr:postcode":"94954",
    "addr:street":"Wieling Way",
    "iso:country":"US",
    "sg:address":"1102 Wieling Way",
    "sg:city":"Petaluma",
    "sg:classifiers":[
        {
            "category":"Professional",
            "subcategory":"Computer Services",
            "type":"Services"
        }
    ],
    "sg:phone":"+1 415 640 0381",
    "sg:postcode":"94954",
    "sg:province":"CA",
    "sg:tags":[
        "publisher",
        "developer",
        "software"
    ],
    "wof:name":"Adam Doti",
    "wof:placetype":"venue"
},
  "geometry": {"coordinates":[-122.602723,38.236869],"type":"Point"}
}