{
  "type": "Feature",
  "properties": {
    "iso:country":"US",
    "sg:address":"2509 E Florence Ave",
    "sg:city":"Huntington Park",
    "sg:classifiers":[
        {
            "category":"Professional",
            "subcategory":"Business Services",
            "type":"Services"
        }
    ],
    "sg:phone":"+1 323 589 9079",
    "sg:postcode":"90255",
    "sg:province":"CA",
    "sg:tags":[
        "slitting",
        "cutting"
    ],
    "wof:name":"Edge",
    "wof:placetype":"venue"
},
  "geometry": {"coordinates":[-118.227283,33.974484],"type":"Point"}
}