{
  "type": "Feature",
  "properties": {
    "iso:country":"US",
    "sg:address":"11605 New Ave",
    "sg:city":"Gilroy",
    "sg:classifiers":[
        {
            "category":"Wholesale",
            "subcategory":"Plants",
            "type":"Manufacturing & Wholesale Goods"
        }
    ],
    "sg:phone":"+1 408 683 4862",
    "sg:postcode":"95020",
    "sg:province":"CA",
    "sg:tags":[
        "nursery",
        "tree"
    ],
    "wof:name":"Menlo Growers",
    "wof:placetype":"venue"
},
  "geometry": {"coordinates":[-121.56188,37.077989],"type":"Point"}
}