{
  "type": "Feature",
  "properties": {
    "iso:country":"US",
    "sg:address":"10781 Los Alamitos Blvd",
    "sg:city":"Los Alamitos",
    "sg:classifiers":[
        {
            "category":"Banks & Credit Unions",
            "subcategory":"Bank",
            "type":"Services"
        }
    ],
    "sg:phone":"+1 562 280 0451",
    "sg:postcode":"90720",
    "sg:province":"CA",
    "sg:tags":[
        "loan",
        "real estate"
    ],
    "wof:name":"Cutrell Inc",
    "wof:placetype":"venue"
},
  "geometry": {"coordinates":[-118.071995,33.80663],"type":"Point"}
}