{
  "type": "Feature",
  "properties": {
    "addr:full":"400 W Gettysburg Ave Clovis CA 93612",
    "addr:housenumber":"400",
    "addr:postcode":"93612",
    "addr:street":"W Gettysburg Ave",
    "iso:country":"US",
    "sg:address":"400 W Gettysburg Ave",
    "sg:city":"Clovis",
    "sg:classifiers":[
        {
            "category":"Real Estate",
            "subcategory":"Real Estate Operator",
            "type":"Services"
        }
    ],
    "sg:phone":"+1 559 291 9555",
    "sg:postcode":"93612",
    "sg:province":"CA",
    "sg:tags":[
        "apartment"
    ],
    "wof:name":"Merit Manor Apartments",
    "wof:placetype":"venue"
},
  "geometry": {"coordinates":[-119.72266999999999,36.801227],"type":"Point"}
}