{
  "type": "Feature",
  "properties": {
    "iso:country":"US",
    "sg:address":"130 N Santa Cruz Ave",
    "sg:city":"Los Gatos",
    "sg:classifiers":[
        {
            "category":"Professional",
            "type":"Services"
        },
        {
            "category":"Shopping",
            "subcategory":"Clothing, Apparel, & Fashions",
            "type":"Retail Goods"
        }
    ],
    "sg:phone":"+1 408 395 3332",
    "sg:postcode":"95030",
    "sg:province":"CA",
    "sg:tags":[
        "item",
        "boutique"
    ],
    "wof:name":"Mad Hattress",
    "wof:placetype":"venue"
},
  "geometry": {"coordinates":[-121.98300999999999,37.22441],"type":"Point"}
}