{
  "type": "Feature",
  "properties": {
    "iso:country":"US",
    "sg:address":"998 Broadway",
    "sg:city":"El Cajon",
    "sg:classifiers":[
        {
            "category":"Restaurant",
            "type":"Food & Drink"
        }
    ],
    "sg:phone":"+1 619 447 4196",
    "sg:postcode":"92021",
    "sg:province":"CA",
    "wof:name":"Silva's Taco Shop",
    "wof:placetype":"venue"
},
  "geometry": {"coordinates":[-116.950985,32.807693],"type":"Point"}
}