{
  "type": "Feature",
  "properties": {
    "iso:country":"US",
    "sg:address":"5000 Hardwick St #6614",
    "sg:city":"Lakewood",
    "sg:classifiers":[
        {
            "category":"Home & Garden",
            "subcategory":"Building Materials",
            "type":"Retail Goods"
        },
        {
            "category":"Building & Trades",
            "subcategory":"Construction",
            "type":"Services"
        }
    ],
    "sg:phone":"+1 562 529 3500",
    "sg:postcode":"90712",
    "sg:province":"CA",
    "sg:tags":[
        "contractor",
        "supply"
    ],
    "sg:website":"www.homedepot.com",
    "wof:name":"The Home Depot",
    "wof:placetype":"venue"
},
  "geometry": {"coordinates":[-118.134197,33.850467],"type":"Point"}
}