{
  "type": "Feature",
  "properties": {
    "iso:country":"US",
    "sg:address":"7196 Regional St",
    "sg:city":"Dublin",
    "sg:classifiers":[
        {
            "category":"Personal",
            "subcategory":"Beauty Salon",
            "type":"Services"
        }
    ],
    "sg:phone":"+1 925 829 1962",
    "sg:postcode":"94568",
    "sg:province":"CA",
    "wof:name":"Cachet-Full Svc Salon",
    "wof:placetype":"venue"
},
  "geometry": {"coordinates":[-121.93457600000001,37.70507],"type":"Point"}
}