{
  "type": "Feature",
  "properties": {
    "iso:country":"US",
    "sg:address":"77971 Wildcat Dr",
    "sg:city":"Palm Desert",
    "sg:classifiers":[
        {
            "category":"Manufacturing",
            "subcategory":"Tools & Machinery",
            "type":"Manufacturing & Wholesale Goods"
        }
    ],
    "sg:phone":"+1 760 200 9772",
    "sg:postcode":"92211",
    "sg:province":"CA",
    "sg:tags":[
        "physician",
        "surgeon"
    ],
    "wof:name":"Tellus Medical Products Inc",
    "wof:placetype":"venue"
},
  "geometry": {"coordinates":[-116.305331,33.764927],"type":"Point"}
}