{
  "type": "Feature",
  "properties": {
    "iso:country":"US",
    "sg:address":"137 Dakota St",
    "sg:city":"Santa Cruz",
    "sg:classifiers":[
        {
            "category":"Park",
            "type":"Public Place"
        },
        {
            "category":"Recreation",
            "subcategory":"Playground",
            "type":"Entertainment"
        }
    ],
    "sg:postcode":"95067",
    "sg:province":"CA",
    "sg:website":"www.ci.santa-cruz.ca.us/pr/parks...",
    "wof:name":"San Lorenzo Park",
    "wof:placetype":"venue"
},
  "geometry": {"coordinates":[-122.021271,36.976021],"type":"Point"}
}