{
  "type": "Feature",
  "properties": {
    "addr:full":"2335 E Valley Pkwy Escondido CA 92027",
    "addr:housenumber":"2335",
    "addr:postcode":"92027",
    "addr:street":"E Valley Pkwy",
    "iso:country":"US",
    "sg:address":"2335 E Valley Pkwy",
    "sg:city":"Escondido",
    "sg:classifiers":[
        {
            "category":"Restaurant",
            "type":"Food & Drink"
        }
    ],
    "sg:phone":"+1 760 738 1837",
    "sg:postcode":"92027",
    "sg:province":"CA",
    "wof:name":"Marvins Oriental",
    "wof:placetype":"venue"
},
  "geometry": {"coordinates":[-117.045756,33.140166],"type":"Point"}
}