{
  "type": "Feature",
  "properties": {
    "iso:country":"US",
    "sg:address":"280 Blackfoot Ln",
    "sg:city":"Ventura",
    "sg:classifiers":[
        {
            "category":"Retail",
            "subcategory":"Repair Shop",
            "type":"Services"
        }
    ],
    "sg:phone":"+1 805 653 6161",
    "sg:postcode":"93001",
    "sg:province":"CA",
    "sg:tags":[
        "upholsterer"
    ],
    "wof:name":"Merlin West Interiors",
    "wof:placetype":"venue"
},
  "geometry": {"coordinates":[-119.289504,34.303962],"type":"Point"}
}