{
  "type": "Feature",
  "properties": {
    "iso:country":"US",
    "sg:address":"725 E Mauna Loa Ave",
    "sg:city":"Glendora",
    "sg:classifiers":[
        {
            "category":"Recreation",
            "type":"Entertainment"
        }
    ],
    "sg:phone":"+1 626 335 2078",
    "sg:postcode":"91740",
    "sg:province":"CA",
    "sg:tags":[
        "parks"
    ],
    "wof:name":"Glendora Preservation",
    "wof:placetype":"venue"
},
  "geometry": {"coordinates":[-117.856826,34.125184],"type":"Point"}
}