{
  "type": "Feature",
  "properties": {
    "addr:full":"2032 N Gateway Blvd Fresno CA 93727",
    "addr:housenumber":"2032",
    "addr:postcode":"93727",
    "addr:street":"N Gateway Blvd",
    "iso:country":"US",
    "sg:address":"2032 N Gateway Blvd",
    "sg:city":"Fresno",
    "sg:classifiers":[
        {
            "category":"Professional",
            "subcategory":"Accounting & Tax Preparation",
            "type":"Services"
        }
    ],
    "sg:phone":"+1 559 255 1744",
    "sg:postcode":"93727",
    "sg:province":"CA",
    "sg:tags":[
        "billing"
    ],
    "wof:name":"Medical Systems Inc",
    "wof:placetype":"venue"
},
  "geometry": {"coordinates":[-119.726719,36.767527],"type":"Point"}
}