{
  "type": "Feature",
  "properties": {
    "addr:full":"3828 W Slauson Ave Los Angeles CA 90043",
    "addr:housenumber":"3828",
    "addr:postcode":"90043",
    "addr:street":"W Slauson Ave",
    "iso:country":"US",
    "sg:address":"3828 W Slauson Ave",
    "sg:city":"Los Angeles",
    "sg:classifiers":[
        {
            "category":"Organizations",
            "subcategory":"Community Association",
            "type":"Services"
        }
    ],
    "sg:phone":"+1 323 298 0308",
    "sg:postcode":"90043",
    "sg:province":"CA",
    "sg:tags":[
        "military"
    ],
    "wof:name":"American Legion",
    "wof:placetype":"venue"
},
  "geometry": {"coordinates":[-118.34009399999999,33.988898],"type":"Point"}
}