{
  "type": "Feature",
  "properties": {
    "iso:country":"US",
    "sg:address":"815 S State Hwy 49",
    "sg:city":"Jackson",
    "sg:classifiers":[
        {
            "category":"Health Services",
            "subcategory":"Doctor",
            "type":"Services"
        }
    ],
    "sg:phone":"+1 209 223 5808",
    "sg:postcode":"95642",
    "sg:province":"CA",
    "sg:tags":[
        "physician",
        "surgeon"
    ],
    "wof:name":"Lodi Plaza Head & Neck Assoc",
    "wof:placetype":"venue"
},
  "geometry": {"coordinates":[-120.768654,38.343672],"type":"Point"}
}