{
  "type": "Feature",
  "properties": {
    "iso:country":"US",
    "sg:address":"958 Santa Rosa Ave",
    "sg:city":"Santa Rosa",
    "sg:classifiers":[
        {
            "category":"Restaurant",
            "type":"Food & Drink"
        }
    ],
    "sg:phone":"+1 707 545 5747",
    "sg:postcode":"95404",
    "sg:province":"CA",
    "wof:name":"Taqueria Don Jose",
    "wof:placetype":"venue"
},
  "geometry": {"coordinates":[-122.712625,38.427936],"type":"Point"}
}