{
  "type": "Feature",
  "properties": {
    "addr:full":"1701 E Alondra Blvd Compton CA 90221",
    "addr:housenumber":"1701",
    "addr:postcode":"90221",
    "addr:street":"E Alondra Blvd",
    "iso:country":"US",
    "sg:address":"1701 E Alondra Blvd",
    "sg:city":"Compton",
    "sg:classifiers":[
        {
            "category":"Organizations",
            "subcategory":"Professional Association",
            "type":"Services"
        }
    ],
    "sg:phone":"+1 310 763 2572",
    "sg:postcode":"90221",
    "sg:province":"CA",
    "wof:name":"NAACP",
    "wof:placetype":"venue"
},
  "geometry": {"coordinates":[-118.20307699999999,33.888709],"type":"Point"}
}