{
  "type": "Feature",
  "properties": {
    "iso:country":"US",
    "sg:address":"2140 W Chapman Ave",
    "sg:city":"Orange",
    "sg:classifiers":[
        {
            "category":"Professional",
            "subcategory":"Lawyer & Legal Services",
            "type":"Services"
        }
    ],
    "sg:phone":"+1 714 938 1355",
    "sg:postcode":"92868",
    "sg:province":"CA",
    "sg:tags":[
        "attorney"
    ],
    "wof:name":"Adams Esq",
    "wof:placetype":"venue"
},
  "geometry": {"coordinates":[-117.87564999999999,33.787956],"type":"Point"}
}