{
  "type": "Feature",
  "properties": {
    "addr:full":"600 Santa Cruz Ave Menlo Park CA 94025",
    "addr:housenumber":"600",
    "addr:postcode":"94025",
    "addr:street":"Santa Cruz Ave",
    "iso:country":"US",
    "sg:address":"600 Santa Cruz Ave",
    "sg:city":"Menlo Park",
    "sg:classifiers":[
        {
            "category":"Restaurant",
            "type":"Food & Drink"
        }
    ],
    "sg:menulink":"http://www.allmenus.com/ca/san-mateo/20219-stacks/menu/",
    "sg:phone":"+1 650 838 0066",
    "sg:postcode":"94025",
    "sg:province":"CA",
    "sg:tags":[
        "american"
    ],
    "wof:name":"Stacks'",
    "wof:placetype":"venue"
},
  "geometry": {"coordinates":[-122.183046,37.453425],"type":"Point"}
}