{
  "type": "Feature",
  "properties": {
    "iso:country":"US",
    "sg:address":"4780 Caterpillar Rd",
    "sg:city":"Redding",
    "sg:classifiers":[
        {
            "category":"Real Estate",
            "subcategory":"Architect",
            "type":"Services"
        }
    ],
    "sg:phone":"+1 530 243 0796",
    "sg:postcode":"96003",
    "sg:province":"CA",
    "sg:tags":[
        "home",
        "planning",
        "design"
    ],
    "wof:name":"Column Works",
    "wof:placetype":"venue"
},
  "geometry": {"coordinates":[-122.385107,40.626356],"type":"Point"}
}