{
  "type": "Feature",
  "properties": {
    "iso:country":"US",
    "sg:address":"121 S 1st St",
    "sg:city":"San Jose",
    "sg:classifiers":[
        {
            "category":"Banks & Credit Unions",
            "subcategory":"Bank",
            "type":"Services"
        }
    ],
    "sg:phone":"+1 408 277 6535",
    "sg:postcode":"95113",
    "sg:province":"CA",
    "sg:website":"www.wellsfargo.com",
    "wof:name":"Wells Fargo Bank",
    "wof:placetype":"venue"
},
  "geometry": {"coordinates":[-121.88902400000001,37.333993],"type":"Point"}
}