{
  "type": "Feature",
  "properties": {
    "iso:country":"US",
    "sg:address":"29560 Rancho California Rd",
    "sg:city":"Temecula",
    "sg:classifiers":[
        {
            "category":"Cinema",
            "subcategory":"Movie Rental",
            "type":"Entertainment"
        }
    ],
    "sg:phone":"+1 951 693 1330",
    "sg:postcode":"92591",
    "sg:province":"CA",
    "sg:tags":[
        "leasing",
        "video",
        "disc",
        "tape"
    ],
    "sg:website":"www.hollywoodvideo.com",
    "wof:name":"Hollywood Video",
    "wof:placetype":"venue"
},
  "geometry": {"coordinates":[-117.144867,33.50538],"type":"Point"}
}