{
  "type": "Feature",
  "properties": {
    "addr:full":"27515 Enterprise Cir W Temecula CA 92590",
    "addr:housenumber":"27515",
    "addr:postcode":"92590",
    "addr:street":"Enterprise Cir W",
    "iso:country":"US",
    "sg:address":"27515 Enterprise Cir W",
    "sg:city":"Temecula",
    "sg:classifiers":[
        {
            "category":"Education",
            "subcategory":"Dance Studio",
            "type":"Public Place"
        }
    ],
    "sg:phone":"+1 951 600 8583",
    "sg:postcode":"92590",
    "sg:province":"CA",
    "sg:tags":[
        "instruction",
        "dancing"
    ],
    "wof:name":"Svetlana's Dance Academy",
    "wof:placetype":"venue"
},
  "geometry": {"coordinates":[-117.16459,33.514427],"type":"Point"}
}