{
  "type": "Feature",
  "properties": {
    "iso:country":"US",
    "sg:address":"719 Beaumont Ave",
    "sg:city":"Beaumont",
    "sg:classifiers":[
        {
            "category":"Personal",
            "subcategory":"Nail Salon",
            "type":"Services"
        }
    ],
    "sg:phone":"+1 888 893 8603",
    "sg:postcode":"92223",
    "sg:province":"CA",
    "wof:name":"Top Nails Spa",
    "wof:placetype":"venue"
},
  "geometry": {"coordinates":[-116.977171,33.931304],"type":"Point"}
}