{
  "type": "Feature",
  "properties": {
    "iso:country":"US",
    "sg:address":"6795 Washington St",
    "sg:city":"Yountville",
    "sg:classifiers":[
        {
            "category":"Personal",
            "subcategory":"Beauty Salon",
            "type":"Services"
        }
    ],
    "sg:phone":"+1 707 944 0200",
    "sg:postcode":"94599",
    "sg:province":"CA",
    "wof:name":"Details With Dixie Hair-Nail",
    "wof:placetype":"venue"
},
  "geometry": {"coordinates":[-122.366529,38.405687],"type":"Point"}
}