{
  "type": "Feature",
  "properties": {
    "addr:full":"5027 Irwindale Ave Irwindale CA 91706",
    "addr:housenumber":"5027",
    "addr:postcode":"91706",
    "addr:street":"Irwindale Ave",
    "iso:country":"US",
    "sg:address":"5027 Irwindale Ave",
    "sg:city":"Irwindale",
    "sg:classifiers":[
        {
            "category":"Wholesale",
            "subcategory":"Durable Goods & Equipment",
            "type":"Manufacturing & Wholesale Goods"
        }
    ],
    "sg:phone":"+1 626 338 6786",
    "sg:postcode":"91706",
    "sg:province":"CA",
    "sg:tags":[
        "importer"
    ],
    "wof:name":"Studio 702",
    "wof:placetype":"venue"
},
  "geometry": {"coordinates":[-117.93423199999999,34.10306],"type":"Point"}
}