{
  "type": "Feature",
  "properties": {
    "iso:country":"US",
    "sg:address":"1107 S Alvarado Street",
    "sg:city":"Los Angeles",
    "sg:classifiers":[
        {
            "category":"Building & Trades",
            "subcategory":"Locksmith",
            "type":"Services"
        }
    ],
    "sg:phone":"+1 213 596 1730",
    "sg:postcode":"90006",
    "sg:province":"CA",
    "sg:tags":[
        "key"
    ],
    "wof:name":"S Alvarado Emergency Locksmith",
    "wof:placetype":"venue"
},
  "geometry": {"coordinates":[-118.280829,34.050166],"type":"Point"}
}