{
  "type": "Feature",
  "properties": {
    "addr:full":"5748 la Mirada Ave Los Angeles CA 90038",
    "addr:housenumber":"5748",
    "addr:postcode":"90038",
    "addr:street":"La Mirada Ave",
    "iso:country":"US",
    "sg:address":"5748 la Mirada Ave",
    "sg:city":"Los Angeles",
    "sg:classifiers":[
        {
            "category":"Manufacturing",
            "subcategory":"Jewelry",
            "type":"Manufacturing & Wholesale Goods"
        }
    ],
    "sg:phone":"+1 323 465 6219",
    "sg:postcode":"90038",
    "sg:province":"CA",
    "sg:tags":[
        "jewelery",
        "design",
        "custom"
    ],
    "wof:name":"Dulyan Millennium Design",
    "wof:placetype":"venue"
},
  "geometry": {"coordinates":[-118.21376100000001,34.027828],"type":"Point"}
}