{
  "type": "Feature",
  "properties": {
    "addr:full":"1201 Glen Cove Pkwy Vallejo CA 94591",
    "addr:housenumber":"1201",
    "addr:postcode":"94591",
    "addr:street":"Glen Cove Pkwy",
    "iso:country":"US",
    "sg:address":"1201 Glen Cove Pkwy",
    "sg:city":"Vallejo",
    "sg:classifiers":[
        {
            "category":"Real Estate",
            "subcategory":"Real Estate Operator",
            "type":"Services"
        }
    ],
    "sg:phone":"+1 707 648 7364",
    "sg:postcode":"94591",
    "sg:province":"CA",
    "sg:tags":[
        "condominium"
    ],
    "wof:name":"Glen Cove Landing Condo Assn",
    "wof:placetype":"venue"
},
  "geometry": {"coordinates":[-122.221744,38.068405],"type":"Point"}
}