{
  "type": "Feature",
  "properties": {
    "addr:full":"227 W Valley Blvd San Gabriel CA 91776",
    "addr:housenumber":"227",
    "addr:postcode":"91776",
    "addr:street":"W Valley Blvd",
    "iso:country":"US",
    "sg:address":"227 W Valley Blvd",
    "sg:city":"San Gabriel",
    "sg:classifiers":[
        {
            "category":"Shopping",
            "type":"Retail Goods"
        }
    ],
    "sg:phone":"+1 626 642 0388",
    "sg:postcode":"91776",
    "sg:province":"CA",
    "sg:tags":[
        "telephone",
        "cellular"
    ],
    "wof:name":"Tian Shan Trading USA Inc",
    "wof:placetype":"venue"
},
  "geometry": {"coordinates":[-118.10297199999999,34.079651],"type":"Point"}
}