{
  "type": "Feature",
  "properties": {
    "addr:full":"5484 Dewey Dr Fair Oaks CA 95628",
    "addr:housenumber":"5484",
    "addr:postcode":"95628",
    "addr:street":"Dewey Dr",
    "iso:country":"US",
    "sg:address":"5484 Dewey Dr",
    "sg:city":"Fair Oaks",
    "sg:classifiers":[
        {
            "category":"Restaurant",
            "type":"Food & Drink"
        }
    ],
    "sg:menulink":"http://www.allmenus.com/ca/sacramento/234295-pick-up-stix/menu/",
    "sg:phone":"+1 916 965 6936",
    "sg:postcode":"95628",
    "sg:province":"CA",
    "sg:tags":[
        "japanese",
        "chinese",
        "asian"
    ],
    "wof:name":"Pick Up Stix",
    "wof:placetype":"venue"
},
  "geometry": {"coordinates":[-121.308578,38.665187],"type":"Point"}
}