{
  "type": "Feature",
  "properties": {
    "iso:country":"US",
    "sg:address":"32 E 25th Ave",
    "sg:city":"San Mateo",
    "sg:classifiers":[
        {
            "category":"Wholesale",
            "subcategory":"Furniture",
            "type":"Manufacturing & Wholesale Goods"
        }
    ],
    "sg:phone":"+1 650 341 9983",
    "sg:postcode":"94403",
    "sg:province":"CA",
    "wof:name":"Mattress Madness",
    "wof:placetype":"venue"
},
  "geometry": {"coordinates":[-122.305376,37.544667],"type":"Point"}
}