{
  "type": "Feature",
  "properties": {
    "addr:full":"501 N 1st St Patterson CA 95363",
    "addr:housenumber":"501",
    "addr:postcode":"95363",
    "addr:street":"N 1St St",
    "iso:country":"US",
    "sg:address":"501 N 1st St",
    "sg:city":"Patterson",
    "sg:classifiers":[
        {
            "category":"Building & Trades",
            "subcategory":"Construction",
            "type":"Services"
        }
    ],
    "sg:phone":"+1 209 892 8450",
    "sg:postcode":"95363",
    "sg:province":"CA",
    "sg:tags":[
        "resurfacing",
        "laying",
        "refinishing",
        "floor"
    ],
    "wof:name":"United Floor Covering Inc",
    "wof:placetype":"venue"
},
  "geometry": {"coordinates":[-121.132385,37.479437],"type":"Point"}
}