{
  "type": "Feature",
  "properties": {
    "iso:country":"US",
    "sg:address":"716 Yarmouth Rd",
    "sg:city":"Palos Vrds Ests",
    "sg:classifiers":[
        {
            "category":"Professional",
            "subcategory":"Accounting & Tax Preparation",
            "type":"Services"
        }
    ],
    "sg:phone":"+1 310 265 8051",
    "sg:postcode":"90274",
    "sg:province":"CA",
    "sg:tags":[
        "return",
        "filing"
    ],
    "wof:name":"Kathleen F Moreau Ax",
    "wof:placetype":"venue"
},
  "geometry": {"coordinates":[-118.41886,33.775711],"type":"Point"}
}