{
  "type": "Feature",
  "properties": {
    "addr:full":"13075 Springdale St Westminster CA 92683",
    "addr:housenumber":"13075",
    "addr:postcode":"92683",
    "addr:street":"Springdale St",
    "iso:country":"US",
    "sg:address":"13075 Springdale St",
    "sg:city":"Westminster",
    "sg:classifiers":[
        {
            "category":"Manufacturing",
            "subcategory":"Printing",
            "type":"Manufacturing & Wholesale Goods"
        }
    ],
    "sg:phone":"+1 714 890 0522",
    "sg:postcode":"92683",
    "sg:province":"CA",
    "sg:tags":[
        "lithographic",
        "commercial"
    ],
    "wof:name":"Dj Custom Printing",
    "wof:placetype":"venue"
},
  "geometry": {"coordinates":[-118.020796,33.773649],"type":"Point"}
}