{
  "type": "Feature",
  "properties": {
    "addr:full":"5600 Paseo Del Norte Carlsbad CA 92008",
    "addr:housenumber":"5600",
    "addr:postcode":"92008",
    "addr:street":"Paseo Del Norte",
    "iso:country":"US",
    "sg:address":"5600 Paseo Del Norte",
    "sg:city":"Carlsbad",
    "sg:classifiers":[
        {
            "category":"Home & Garden",
            "subcategory":"Home Furnishings",
            "type":"Retail Goods"
        }
    ],
    "sg:phone":"+1 760 931 6868",
    "sg:postcode":"92008",
    "sg:province":"CA",
    "sg:tags":[
        "bath",
        "kitchen"
    ],
    "sg:website":"www.lcstores.com",
    "wof:name":"Le Creuset",
    "wof:placetype":"venue"
},
  "geometry": {"coordinates":[-117.32265599999999,33.126136],"type":"Point"}
}