{
  "type": "Feature",
  "properties": {
    "addr:full":"7610 Miramar Rd San Diego CA 92126",
    "addr:housenumber":"7610",
    "addr:postcode":"92126",
    "addr:street":"Miramar Rd",
    "iso:country":"US",
    "sg:address":"7610 Miramar Rd",
    "sg:city":"San Diego",
    "sg:classifiers":[
        {
            "category":"Health Services",
            "subcategory":"Clinic",
            "type":"Services"
        }
    ],
    "sg:phone":"+1 858 693 7229",
    "sg:postcode":"92126",
    "sg:province":"CA",
    "sg:tags":[
        "equipment",
        "therapy",
        "oxygen"
    ],
    "wof:name":"Oxy Vac",
    "wof:placetype":"venue"
},
  "geometry": {"coordinates":[-117.152781,32.884045],"type":"Point"}
}