{
  "type": "Feature",
  "properties": {
    "addr:full":"422 Robert Ave Santa Clara CA 95050",
    "addr:housenumber":"422",
    "addr:postcode":"95050",
    "addr:street":"Robert Ave",
    "iso:country":"US",
    "sg:address":"422 Robert Ave",
    "sg:city":"Santa Clara",
    "sg:classifiers":[
        {
            "category":"Retail",
            "subcategory":"Auto Repair",
            "type":"Services"
        }
    ],
    "sg:phone":"+1 408 748 1412",
    "sg:postcode":"95050",
    "sg:province":"CA",
    "sg:website":"www.honda.com",
    "wof:name":"Lingao Auto Repair",
    "wof:placetype":"venue"
},
  "geometry": {"coordinates":[-121.94202300000001,37.364502],"type":"Point"}
}