{
  "type": "Feature",
  "properties": {
    "addr:full":"4904 Melrose Ave Los Angeles CA 90029",
    "addr:housenumber":"4904",
    "addr:postcode":"90029",
    "addr:street":"Melrose Ave",
    "iso:country":"US",
    "sg:address":"4904 Melrose Ave",
    "sg:city":"Los Angeles",
    "sg:classifiers":[
        {
            "category":"Shopping",
            "subcategory":"Clothing, Apparel, & Fashions",
            "type":"Retail Goods"
        }
    ],
    "sg:phone":"+1 323 467 8904",
    "sg:postcode":"90029",
    "sg:province":"CA",
    "sg:tags":[
        "tailor"
    ],
    "wof:name":"Julian Tailor",
    "wof:placetype":"venue"
},
  "geometry": {"coordinates":[-118.307559,34.083442],"type":"Point"}
}