{
  "type": "Feature",
  "properties": {
    "iso:country":"US",
    "sg:address":"1675 Willow St",
    "sg:city":"San Jose",
    "sg:classifiers":[
        {
            "category":"Insurance",
            "subcategory":"Insurance Agent",
            "type":"Services"
        }
    ],
    "sg:phone":"+1 408 723 6350",
    "sg:postcode":"95125",
    "sg:province":"CA",
    "sg:website":"www.bci-ins.com",
    "wof:name":"BCI Insurance Svc",
    "wof:placetype":"venue"
},
  "geometry": {"coordinates":[-121.912942,37.303885],"type":"Point"}
}