{
  "type": "Feature",
  "properties": {
    "iso:country":"US",
    "sg:address":"836 Broadway",
    "sg:city":"Chula Vista",
    "sg:classifiers":[
        {
            "category":"Home & Garden",
            "subcategory":"Furniture",
            "type":"Retail Goods"
        }
    ],
    "sg:phone":"+1 619 585 1164",
    "sg:postcode":"91911",
    "sg:province":"CA",
    "sg:tags":[
        "builder",
        "custom"
    ],
    "wof:name":"Kevin Warehouse Furniture",
    "wof:placetype":"venue"
},
  "geometry": {"coordinates":[-117.085258,32.620151],"type":"Point"}
}