{
  "type": "Feature",
  "properties": {
    "addr:full":"2441 Holly Dr Tracy CA 95376",
    "addr:housenumber":"2441",
    "addr:postcode":"95376",
    "addr:street":"Holly Dr",
    "iso:country":"US",
    "sg:address":"2441 Holly Dr",
    "sg:city":"Tracy",
    "sg:classifiers":[
        {
            "category":"Social Services",
            "type":"Services"
        }
    ],
    "sg:phone":"+1 209 836 5424",
    "sg:postcode":"95376",
    "sg:province":"CA",
    "sg:tags":[
        "organization",
        "welfare"
    ],
    "wof:name":"Tracy Interfaith Ministries",
    "wof:placetype":"venue"
},
  "geometry": {"coordinates":[-121.425989,37.754315],"type":"Point"}
}