{
  "type": "Feature",
  "properties": {
    "addr:full":"3535 Maricopa St Torrance CA 90503",
    "addr:housenumber":"3535",
    "addr:postcode":"90503",
    "addr:street":"Maricopa St",
    "iso:country":"US",
    "sg:address":"3535 Maricopa St",
    "sg:city":"Torrance",
    "sg:classifiers":[
        {
            "category":"Real Estate",
            "subcategory":"Real Estate Operator",
            "type":"Services"
        }
    ],
    "sg:phone":"+1 310 542 1832",
    "sg:postcode":"90503",
    "sg:province":"CA",
    "sg:tags":[
        "apartment"
    ],
    "wof:name":"Maricopa Associates",
    "wof:placetype":"venue"
},
  "geometry": {"coordinates":[-118.347954,33.839599],"type":"Point"}
}