{
  "type": "Feature",
  "properties": {
    "iso:country":"US",
    "sg:address":"6399 Wilshire Blvd # 307",
    "sg:city":"Los Angeles",
    "sg:classifiers":[
        {
            "category":"Health Services",
            "subcategory":"Chiropractor",
            "type":"Services"
        }
    ],
    "sg:phone":"+1 310 278 4567",
    "sg:postcode":"90048",
    "sg:province":"CA",
    "sg:website":"www.drorpelli.com",
    "wof:name":"Dr Orpelli Chiropractic",
    "wof:placetype":"venue"
},
  "geometry": {"coordinates":[-118.368002,34.064121],"type":"Point"}
}