{
  "type": "Feature",
  "properties": {
    "iso:country":"US",
    "sg:address":"172 Lorie Ct",
    "sg:city":"Walnut Creek",
    "sg:classifiers":[
        {
            "category":"Education",
            "subcategory":"Special Training",
            "type":"Public Place"
        }
    ],
    "sg:phone":"+1 925 938 2307",
    "sg:postcode":"94597",
    "sg:province":"CA",
    "sg:tags":[
        "management"
    ],
    "wof:name":"Bob Eddy & Assoc Management",
    "wof:placetype":"venue"
},
  "geometry": {"coordinates":[-122.07041700000001,37.916901],"type":"Point"}
}