{
  "type": "Feature",
  "properties": {
    "addr:full":"2410 Samaritan Drive San Jose CA 95124",
    "addr:postcode":"2410;95124",
    "addr:street":"Samaritan Drive",
    "iso:country":"US",
    "sg:address":"2410 Samaritan Drive",
    "sg:city":"San Jose",
    "sg:classifiers":[
        {
            "category":"Health Services",
            "subcategory":"Doctor",
            "type":"Services"
        }
    ],
    "sg:phone":"+1 408 371 0390",
    "sg:postcode":"95124",
    "sg:province":"CA",
    "wof:name":"Radiological Associates Medical Group of Santa Clara Valley",
    "wof:placetype":"venue"
},
  "geometry": {"coordinates":[-121.945241,37.251081],"type":"Point"}
}