{
  "type": "Feature",
  "properties": {
    "addr:full":"111 Cal Ave Barstow CA 92311",
    "addr:housenumber":"111",
    "addr:postcode":"92311",
    "addr:street":"Cal Ave",
    "iso:country":"US",
    "sg:address":"111 Cal Ave",
    "sg:city":"Barstow",
    "sg:classifiers":[
        {
            "category":"Building & Trades",
            "subcategory":"Plumbing",
            "type":"Services"
        }
    ],
    "sg:phone":"+1 760 256 8401",
    "sg:postcode":"92311",
    "sg:province":"CA",
    "sg:tags":[
        "conditioning",
        "air",
        "system",
        "contractor"
    ],
    "wof:name":"H & B Mechanical Inc",
    "wof:placetype":"venue"
},
  "geometry": {"coordinates":[-116.99889,34.890029],"type":"Point"}
}