{
  "type": "Feature",
  "properties": {
    "addr:full":"241 Mistletoe Rd Los Gatos CA 95032",
    "addr:housenumber":"241",
    "addr:postcode":"95032",
    "addr:street":"Mistletoe Rd",
    "iso:country":"US",
    "sg:address":"241 Mistletoe Rd",
    "sg:city":"Los Gatos",
    "sg:classifiers":[
        {
            "category":"Professional",
            "subcategory":"Computer Services",
            "type":"Services"
        }
    ],
    "sg:phone":"+1 408 866 1023",
    "sg:postcode":"95032",
    "sg:province":"CA",
    "sg:tags":[
        "consultant",
        "designer"
    ],
    "wof:name":"O'Leary Consulting Svc",
    "wof:placetype":"venue"
},
  "geometry": {"coordinates":[-121.98928100000001,37.256122],"type":"Point"}
}