{
  "type": "Feature",
  "properties": {
    "iso:country":"US",
    "sg:address":"2029 Main St",
    "sg:city":"Oakley",
    "sg:classifiers":[
        {
            "category":"Professional",
            "subcategory":"Accounting & Tax Preparation",
            "type":"Services"
        }
    ],
    "sg:phone":"+1 925 679 1111",
    "sg:postcode":"94561",
    "sg:province":"CA",
    "sg:tags":[
        "accountant"
    ],
    "wof:name":"Richard D Callister CPA",
    "wof:placetype":"venue"
},
  "geometry": {"coordinates":[-121.736161,38.005115],"type":"Point"}
}