{
  "type": "Feature",
  "properties": {
    "iso:country":"US",
    "sg:address":"335 Willow Hts",
    "sg:city":"Aptos",
    "sg:classifiers":[
        {
            "category":"Wholesale",
            "subcategory":"Apparel",
            "type":"Manufacturing & Wholesale Goods"
        }
    ],
    "sg:phone":"+1 831 662 9347",
    "sg:postcode":"95003",
    "sg:province":"CA",
    "sg:tags":[
        "shoes-wholesale",
        "manufacturer"
    ],
    "wof:name":"Rand Elliot Rueter",
    "wof:placetype":"venue"
},
  "geometry": {"coordinates":[-121.827974,36.975691],"type":"Point"}
}