{
  "type": "Feature",
  "properties": {
    "addr:full":"6560 Greenback Ln Citrus Heights CA 95621",
    "addr:housenumber":"6560",
    "addr:postcode":"95621",
    "addr:street":"Greenback Ln",
    "iso:country":"US",
    "sg:address":"6560 Greenback Ln",
    "sg:city":"Citrus Heights",
    "sg:classifiers":[
        {
            "category":"Health Services",
            "subcategory":"Doctor",
            "type":"Services"
        }
    ],
    "sg:phone":"+1 916 727 1989",
    "sg:postcode":"95621",
    "sg:province":"CA",
    "wof:name":"My Family Clinic",
    "wof:placetype":"venue"
},
  "geometry": {"coordinates":[-121.311837,38.677983],"type":"Point"}
}