{
  "type": "Feature",
  "properties": {
    "iso:country":"US",
    "sg:address":"939 W El Camino Real Suite 116",
    "sg:city":"Sunnyvale",
    "sg:classifiers":[
        {
            "category":"Health Services",
            "subcategory":"Optometrist",
            "type":"Services"
        }
    ],
    "sg:phone":"+1 408 739 0591",
    "sg:postcode":"94087",
    "sg:province":"CA",
    "sg:website":"www.spectrumoptometric.com",
    "wof:name":"Spectrum Optometric Center",
    "wof:placetype":"venue"
},
  "geometry": {"coordinates":[-122.04562,37.371661],"type":"Point"}
}