{
  "type": "Feature",
  "properties": {
    "addr:full":"5715 Stockton Blvd Sacramento CA 95824",
    "addr:housenumber":"5715",
    "addr:postcode":"95824",
    "addr:street":"Stockton Blvd",
    "iso:country":"US",
    "sg:address":"5715 Stockton Blvd",
    "sg:city":"Sacramento",
    "sg:classifiers":[
        {
            "category":"Shopping",
            "type":"Retail Goods"
        }
    ],
    "sg:phone":"+1 916 452 5888",
    "sg:postcode":"95824",
    "sg:province":"CA",
    "sg:tags":[
        "wedding",
        "supply"
    ],
    "wof:name":"Wiegman's Sacramento Floral Co",
    "wof:placetype":"venue"
},
  "geometry": {"coordinates":[-121.441118,38.521964],"type":"Point"}
}