{
  "type": "Feature",
  "properties": {
    "iso:country":"US",
    "sg:address":"13191 Crossroads Pkwy N",
    "sg:city":"City Of Industry",
    "sg:classifiers":[
        {
            "category":"Real Estate",
            "subcategory":"Real Estate Agent",
            "type":"Services"
        }
    ],
    "sg:phone":"+1 562 695 7244",
    "sg:postcode":"91746",
    "sg:province":"CA",
    "sg:website":"www.daumcommercial.com",
    "wof:name":"Daum Commercial Ind Real Est",
    "wof:placetype":"venue"
},
  "geometry": {"coordinates":[-118.01545400000001,34.029683],"type":"Point"}
}