{
  "type": "Feature",
  "properties": {
    "addr:full":"940 Dwight Way Berkeley CA 94710",
    "addr:housenumber":"940",
    "addr:postcode":"94710",
    "addr:street":"Dwight Way",
    "iso:country":"US",
    "sg:address":"940 Dwight Way",
    "sg:city":"Berkeley",
    "sg:classifiers":[
        {
            "category":"Real Estate",
            "subcategory":"Architect",
            "type":"Services"
        }
    ],
    "sg:phone":"+1 510 843 6781",
    "sg:postcode":"94710",
    "sg:province":"CA",
    "sg:website":"www.planhouse.biz",
    "wof:name":"Plan-House",
    "wof:placetype":"venue"
},
  "geometry": {"coordinates":[-122.297997,37.872501],"type":"Point"}
}