{
  "type": "Feature",
  "properties": {
    "iso:country":"US",
    "sg:address":"1871 N Gaffey St",
    "sg:city":"San Pedro",
    "sg:classifiers":[
        {
            "category":"Manufacturing",
            "subcategory":"Signs",
            "type":"Manufacturing & Wholesale Goods"
        }
    ],
    "sg:phone":"+1 310 521 9995",
    "sg:postcode":"90731",
    "sg:province":"CA",
    "sg:tags":[
        "specialty",
        "mfg"
    ],
    "wof:name":"Worldwide Graphics",
    "wof:placetype":"venue"
},
  "geometry": {"coordinates":[-118.29300600000001,33.760653],"type":"Point"}
}