{
  "type": "Feature",
  "properties": {
    "addr:full":"5385 Franklin Blvd Ste F Sacramento CA 95820",
    "addr:housenumber":"5385",
    "addr:postcode":"95820",
    "addr:street":"Franklin Blvd Ste F",
    "iso:country":"US",
    "sg:address":"5385 Franklin Blvd Ste F",
    "sg:city":"Sacramento",
    "sg:classifiers":[
        {
            "category":"Personal",
            "subcategory":"Beauty Salon",
            "type":"Services"
        }
    ],
    "sg:phone":"+1 916 455 8241",
    "sg:postcode":"95820",
    "sg:province":"CA",
    "wof:name":"Xochitl Beauty Salon",
    "wof:placetype":"venue"
},
  "geometry": {"coordinates":[-121.472156,38.52637],"type":"Point"}
}