{
  "type": "Feature",
  "properties": {
    "iso:country":"US",
    "sg:address":"2923 Martin Luther King Jr Way",
    "sg:city":"Berkeley",
    "sg:classifiers":[
        {
            "category":"Professional",
            "subcategory":"Computer Services",
            "type":"Services"
        }
    ],
    "sg:phone":"+1 510 845 8757",
    "sg:postcode":"94703",
    "sg:province":"CA",
    "sg:tags":[
        "graphics"
    ],
    "wof:name":"A K Graphics",
    "wof:placetype":"venue"
},
  "geometry": {"coordinates":[-122.27114,37.854696],"type":"Point"}
}