{
  "type": "Feature",
  "properties": {
    "iso:country":"US",
    "sg:address":"49 Knox Dr",
    "sg:city":"Lafayette",
    "sg:classifiers":[
        {
            "category":"Social Services",
            "type":"Services"
        }
    ],
    "sg:phone":"+1 925 932 3448",
    "sg:postcode":"94549",
    "sg:province":"CA",
    "sg:tags":[
        "organization",
        "welfare"
    ],
    "wof:name":"Widowed Persons Support",
    "wof:placetype":"venue"
},
  "geometry": {"coordinates":[-122.156898,37.88718],"type":"Point"}
}