{
  "type": "Feature",
  "properties": {
    "iso:country":"US",
    "sg:address":"25826 Serenata Dr",
    "sg:city":"Mission Viejo",
    "sg:classifiers":[
        {
            "category":"Wholesale",
            "subcategory":"Machinery & Supplies",
            "type":"Manufacturing & Wholesale Goods"
        }
    ],
    "sg:phone":"+1 949 770 5089",
    "sg:postcode":"92691",
    "sg:province":"CA",
    "sg:tags":[
        "product",
        "industrial",
        "sawmill",
        "special",
        "mfg"
    ],
    "wof:name":"Kelvin Corp",
    "wof:placetype":"venue"
},
  "geometry": {"coordinates":[-117.666154,33.586808],"type":"Point"}
}