{
  "type": "Feature",
  "properties": {
    "iso:country":"US",
    "sg:address":"8464 Corbin Ave",
    "sg:city":"Northridge",
    "sg:classifiers":[
        {
            "category":"Education",
            "subcategory":"School",
            "type":"Public Place"
        }
    ],
    "sg:phone":"+1 818 886 3508",
    "sg:postcode":"91324",
    "sg:province":"CA",
    "sg:website":"www.kidsvilleusa.com",
    "wof:name":"Kidsville USA",
    "wof:placetype":"venue"
},
  "geometry": {"coordinates":[-118.562222,34.222309],"type":"Point"}
}