{
  "type": "Feature",
  "properties": {
    "iso:country":"US",
    "sg:address":"4941 Clairemont Drive",
    "sg:city":"San Diego",
    "sg:classifiers":[
        {
            "category":"Retail",
            "subcategory":"Veterinary Services",
            "type":"Services"
        }
    ],
    "sg:phone":"+1 858 274 1760",
    "sg:postcode":"92117",
    "sg:province":"CA",
    "sg:tags":[
        "veterinarian"
    ],
    "wof:name":"Clairemont Square Animal Hospital",
    "wof:placetype":"venue"
},
  "geometry": {"coordinates":[-117.20383099999999,32.832653],"type":"Point"}
}