{
  "type": "Feature",
  "properties": {
    "addr:full":"45 Mc Cormick Aly Pasadena CA 91105",
    "addr:housenumber":"45",
    "addr:postcode":"91105",
    "addr:street":"Mc Cormick Aly",
    "iso:country":"US",
    "sg:address":"45 Mc Cormick Aly",
    "sg:city":"Pasadena",
    "sg:classifiers":[
        {
            "category":"Wholesale",
            "subcategory":"Apparel",
            "type":"Manufacturing & Wholesale Goods"
        }
    ],
    "sg:phone":"+1 626 440 9364",
    "sg:postcode":"91105",
    "sg:province":"CA",
    "sg:tags":[
        "footwear"
    ],
    "wof:name":"Rocket Dog",
    "wof:placetype":"venue"
},
  "geometry": {"coordinates":[-118.152039,34.145182],"type":"Point"}
}