{
  "type": "Feature",
  "properties": {
    "iso:country":"US",
    "sg:address":"1852 E Palmdale Blvd",
    "sg:city":"Palmdale",
    "sg:classifiers":[
        {
            "category":"Restaurant",
            "type":"Food & Drink"
        }
    ],
    "sg:phone":"+1 661 273 1677",
    "sg:postcode":"93550",
    "sg:province":"CA",
    "wof:name":"Mandarin Express",
    "wof:placetype":"venue"
},
  "geometry": {"coordinates":[-118.095247,34.579617],"type":"Point"}
}