{
  "type": "Feature",
  "properties": {
    "addr:full":"3408 Hillview Ave Palo Alto CA 94304",
    "addr:housenumber":"3408",
    "addr:postcode":"94304",
    "addr:street":"Hillview Ave",
    "iso:country":"US",
    "sg:address":"3408 Hillview Ave",
    "sg:city":"Palo Alto",
    "sg:classifiers":[
        {
            "category":"Banks & Credit Unions",
            "subcategory":"Bank",
            "type":"Services"
        }
    ],
    "sg:phone":"+1 650 855 3360",
    "sg:postcode":"94304",
    "sg:province":"CA",
    "sg:tags":[
        "federal",
        "loan",
        "broker"
    ],
    "wof:name":"Addison Avenue Federal Cr Un",
    "wof:placetype":"venue"
},
  "geometry": {"coordinates":[-122.143503,37.395488],"type":"Point"}
}