{
  "type": "Feature",
  "properties": {
    "iso:country":"US",
    "sg:address":"1155 3rd St",
    "sg:city":"Oakland",
    "sg:classifiers":[
        {
            "category":"Freight",
            "type":"Transportation"
        }
    ],
    "sg:phone":"+1 510 444 0414",
    "sg:postcode":"94607",
    "sg:province":"CA",
    "sg:tags":[
        "over",
        "road",
        "trucking"
    ],
    "wof:name":"Walt Wilson Trucking Inc",
    "wof:placetype":"venue"
},
  "geometry": {"coordinates":[-122.290274,37.80125],"type":"Point"}
}