{
  "type": "Feature",
  "properties": {
    "addr:full":"170 Blake St Apt 1 San Francisco CA 94118",
    "addr:housenumber":"170;1",
    "addr:postcode":"94118",
    "addr:street":"Blake St Apt",
    "iso:country":"US",
    "sg:address":"170 Blake St Apt 1",
    "sg:city":"San Francisco",
    "sg:classifiers":[
        {
            "category":"Sports & Exercise",
            "subcategory":"Gym",
            "type":"Entertainment"
        }
    ],
    "sg:phone":"+1 415 525 1518",
    "sg:postcode":"94118",
    "sg:province":"CA",
    "sg:tags":[
        "trainer"
    ],
    "sg:website":"www.attackfitnesssf.com",
    "wof:name":"Attack Fitness",
    "wof:placetype":"venue"
},
  "geometry": {"coordinates":[-122.45062,37.781075],"type":"Point"}
}