{
  "type": "Feature",
  "properties": {
    "addr:full":"856 E Valley Blvd San Gabriel CA 91776",
    "addr:housenumber":"856",
    "addr:postcode":"91776",
    "addr:street":"E Valley Blvd",
    "iso:country":"US",
    "sg:address":"856 E Valley Blvd",
    "sg:city":"San Gabriel",
    "sg:classifiers":[
        {
            "category":"Health Services",
            "subcategory":"Chiropractor",
            "type":"Services"
        }
    ],
    "sg:phone":"+1 626 288 2599",
    "sg:postcode":"91776",
    "sg:province":"CA",
    "wof:name":"Harmony Chiropractic Clinic and Day Spa",
    "wof:placetype":"venue"
},
  "geometry": {"coordinates":[-118.08877,34.080201],"type":"Point"}
}