{
  "type": "Feature",
  "properties": {
    "addr:full":"1879 2nd St San Rafael CA 94901",
    "addr:housenumber":"1879",
    "addr:postcode":"94901",
    "addr:street":"2Nd St",
    "iso:country":"US",
    "sg:address":"1879 2nd St",
    "sg:city":"San Rafael",
    "sg:classifiers":[
        {
            "category":"Professional",
            "subcategory":"Management & Consulting",
            "type":"Services"
        }
    ],
    "sg:phone":"+1 415 451 6000",
    "sg:postcode":"94901",
    "sg:province":"CA",
    "sg:tags":[
        "consultant",
        "training"
    ],
    "sg:website":"www.thecoaches.com",
    "wof:name":"Coaches Training",
    "wof:placetype":"venue"
},
  "geometry": {"coordinates":[-122.540766,37.973818],"type":"Point"}
}