{
  "type": "Feature",
  "properties": {
    "addr:full":"1212 Riverpark Ct Modesto CA 95351",
    "addr:housenumber":"1212",
    "addr:postcode":"ca 95351",
    "addr:street":"Riverpark Ct",
    "iso:country":"US",
    "sg:address":"1212 Riverpark Ct",
    "sg:city":"Modesto",
    "sg:classifiers":[
        {
            "category":"Building & Trades",
            "subcategory":"Construction",
            "type":"Services"
        }
    ],
    "sg:phone":"+1 209 993 2493",
    "sg:postcode":"95351",
    "sg:province":"CA",
    "sg:tags":[
        "contractor"
    ],
    "wof:name":"Joel Daniel Construction",
    "wof:placetype":"venue"
},
  "geometry": {"coordinates":[-120.94602500000001,37.612428],"type":"Point"}
}