{
  "type": "Feature",
  "properties": {
    "addr:full":"737 Lake Front Dr Sacramento CA 95831",
    "addr:housenumber":"737",
    "addr:postcode":"95831",
    "addr:street":"Lake Front Dr",
    "iso:country":"US",
    "sg:address":"737 Lake Front Dr",
    "sg:city":"Sacramento",
    "sg:classifiers":[
        {
            "category":"Professional",
            "subcategory":"Accounting & Tax Preparation",
            "type":"Services"
        }
    ],
    "sg:phone":"+1 916 393 8063",
    "sg:postcode":"95831",
    "sg:province":"CA",
    "sg:tags":[
        "accountant"
    ],
    "wof:name":"Gregory M Burbage CPA",
    "wof:placetype":"venue"
},
  "geometry": {"coordinates":[-121.532732,38.479386],"type":"Point"}
}