{
  "type": "Feature",
  "properties": {
    "iso:country":"US",
    "sg:address":"590 York St",
    "sg:city":"San Francisco",
    "sg:classifiers":[
        {
            "category":"Professional",
            "subcategory":"Business Services",
            "type":"Services"
        }
    ],
    "sg:phone":"+1 415 503 1174",
    "sg:postcode":"94110",
    "sg:province":"CA",
    "sg:tags":[
        "interior",
        "consultant",
        "design",
        "decorator"
    ],
    "wof:name":"Amy Lee",
    "wof:placetype":"venue"
},
  "geometry": {"coordinates":[-122.409321,37.762977],"type":"Point"}
}