{
  "type": "Feature",
  "properties": {
    "iso:country":"US",
    "sg:address":"4048 Johnson Dr",
    "sg:city":"Oceanside",
    "sg:classifiers":[
        {
            "category":"Professional",
            "subcategory":"Management & Consulting",
            "type":"Services"
        }
    ],
    "sg:phone":"+1 760 941 4443",
    "sg:postcode":"92056",
    "sg:province":"CA",
    "sg:tags":[
        "international",
        "consultant"
    ],
    "wof:name":"Export Promotion Co",
    "wof:placetype":"venue"
},
  "geometry": {"coordinates":[-117.297799,33.190815],"type":"Point"}
}