{
  "type": "Feature",
  "properties": {
    "addr:full":"24955 Pacific Coast Hwy Malibu CA 90265",
    "addr:housenumber":"24955",
    "addr:postcode":"90265",
    "addr:street":"Pacific Coast Hwy",
    "iso:country":"US",
    "sg:address":"24955 Pacific Coast Hwy",
    "sg:city":"Malibu",
    "sg:classifiers":[
        {
            "category":"Banks & Credit Unions",
            "subcategory":"Investment Brokerage",
            "type":"Services"
        }
    ],
    "sg:phone":"+1 310 456 5373",
    "sg:postcode":"90265",
    "sg:province":"CA",
    "sg:tags":[
        "advisory"
    ],
    "wof:name":"Pundit Financial Services Inc",
    "wof:placetype":"venue"
},
  "geometry": {"coordinates":[-118.71883,34.033958],"type":"Point"}
}