{
  "type": "Feature",
  "properties": {
    "addr:full":"4250 Shoemake Ave Modesto CA 95358",
    "addr:housenumber":"4250",
    "addr:postcode":"ca 95358",
    "addr:street":"Shoemake Ave",
    "iso:country":"US",
    "sg:address":"4250 Shoemake Ave",
    "sg:city":"Modesto",
    "sg:classifiers":[
        {
            "category":"Real Estate",
            "subcategory":"Real Estate Services",
            "type":"Services"
        },
        {
            "category":"Real Estate",
            "subcategory":"Real Estate Agent",
            "type":"Services"
        }
    ],
    "sg:phone":"+1 209 577 1978",
    "sg:postcode":"95358",
    "sg:province":"CA",
    "sg:tags":[
        "buyer",
        "broker"
    ],
    "wof:name":"Lillian L Trudell",
    "wof:placetype":"venue"
},
  "geometry": {"coordinates":[-121.07180099999999,37.667228],"type":"Point"}
}