{
  "type": "Feature",
  "properties": {
    "addr:full":"1840 41st Ave Capitola CA 95010",
    "addr:housenumber":"1840",
    "addr:postcode":"95010",
    "addr:street":"41St Ave",
    "iso:country":"US",
    "sg:address":"1840 41st Ave",
    "sg:city":"Capitola",
    "sg:classifiers":[
        {
            "category":"Real Estate",
            "subcategory":"Real Estate Agent",
            "type":"Services"
        }
    ],
    "sg:phone":"+1 831 462 1087",
    "sg:postcode":"95010",
    "sg:province":"CA",
    "wof:name":"Miller Real Estate",
    "wof:placetype":"venue"
},
  "geometry": {"coordinates":[-121.964838,36.97506],"type":"Point"}
}