{
  "type": "Feature",
  "properties": {
    "iso:country":"US",
    "sg:address":"14351 Red Hill Ave Ste C",
    "sg:city":"Tustin",
    "sg:classifiers":[
        {
            "category":"Health Services",
            "subcategory":"Clinic",
            "type":"Services"
        }
    ],
    "sg:phone":"+1 714 837 8997",
    "sg:postcode":"92780",
    "sg:province":"CA",
    "sg:tags":[
        "counseling",
        "mental"
    ],
    "sg:website":"www.oc-therapy.com",
    "wof:name":"Michelle Malloy MFT",
    "wof:placetype":"venue"
},
  "geometry": {"coordinates":[-117.819648,33.729677],"type":"Point"}
}