{
  "type": "Feature",
  "properties": {
    "addr:full":"40670 Malibar Ave Hemet CA 92544",
    "addr:postcode":"40670;92544",
    "addr:street":"Malibar Ave",
    "iso:country":"US",
    "sg:address":"40670 Malibar Ave",
    "sg:city":"Hemet",
    "sg:classifiers":[
        {
            "category":"Personal",
            "subcategory":"Beauty Salon",
            "type":"Services"
        }
    ],
    "sg:phone":"+1 951 929 2177",
    "sg:postcode":"92544",
    "sg:province":"CA",
    "wof:name":"Robin's Nest",
    "wof:placetype":"venue"
},
  "geometry": {"coordinates":[-116.95120199999999,33.736007],"type":"Point"}
}