{
  "type": "Feature",
  "properties": {
    "addr:full":"57 Parker Irvine CA 92618",
    "addr:housenumber":"57",
    "addr:postcode":"92618",
    "addr:street":"Parker",
    "iso:country":"US",
    "sg:address":"57 Parker",
    "sg:city":"Irvine",
    "sg:classifiers":[
        {
            "category":"Professional",
            "type":"Services"
        }
    ],
    "sg:phone":"+1 714 396 5005",
    "sg:postcode":"92618",
    "sg:province":"CA",
    "wof:name":"Esaripalace Co",
    "wof:placetype":"venue"
},
  "geometry": {"coordinates":[-117.702038,33.657962],"type":"Point"}
}