{
  "type": "Feature",
  "properties": {
    "iso:country":"US",
    "sg:address":"4060 S el Camino Real",
    "sg:city":"San Mateo",
    "sg:classifiers":[
        {
            "category":"Personal",
            "subcategory":"Beauty Salon",
            "type":"Services"
        }
    ],
    "sg:phone":"+1 650 349 2899",
    "sg:postcode":"94403",
    "sg:province":"CA",
    "wof:name":"European Facials By Clara",
    "wof:placetype":"venue"
},
  "geometry": {"coordinates":[-122.29131,37.532008],"type":"Point"}
}