{
  "type": "Feature",
  "properties": {
    "addr:full":"3176 Cam Colorados Lafayette CA 94549",
    "addr:housenumber":"3176",
    "addr:postcode":"94549",
    "addr:street":"Cam Colorados",
    "iso:country":"US",
    "sg:address":"3176 Cam Colorados",
    "sg:city":"Lafayette",
    "sg:classifiers":[
        {
            "category":"Professional",
            "type":"Services"
        }
    ],
    "sg:phone":"+1 925 299 1546",
    "sg:postcode":"94549",
    "sg:province":"CA",
    "wof:name":"Cramer Bergman LLC",
    "wof:placetype":"venue"
},
  "geometry": {"coordinates":[-122.09617299999999,37.858119],"type":"Point"}
}