{
  "type": "Feature",
  "properties": {
    "iso:country":"US",
    "sg:address":"868 Altos Oaks Dr",
    "sg:city":"Los Altos",
    "sg:classifiers":[
        {
            "category":"Professional",
            "type":"Services"
        }
    ],
    "sg:phone":"+1 650 964 2667",
    "sg:postcode":"94024",
    "sg:province":"CA",
    "wof:name":"Lggm Inc",
    "wof:placetype":"venue"
},
  "geometry": {"coordinates":[-122.087853,37.359205],"type":"Point"}
}