{
  "type": "Feature",
  "properties": {
    "iso:country":"US",
    "sg:address":"501 S Reino Rd",
    "sg:city":"Newbury Park",
    "sg:classifiers":[
        {
            "category":"Professional",
            "subcategory":"Computer Services",
            "type":"Services"
        }
    ],
    "sg:phone":"+1 805 375 2446",
    "sg:postcode":"91320",
    "sg:province":"CA",
    "sg:tags":[
        "home",
        "consulting",
        "page",
        "dev",
        "internet"
    ],
    "wof:name":"Intertek LLC",
    "wof:placetype":"venue"
},
  "geometry": {"coordinates":[-118.956519,34.163751],"type":"Point"}
}