{
  "type": "Feature",
  "properties": {
    "addr:full":"2565 Kilburn Ave Napa CA 94558",
    "addr:housenumber":"2565",
    "addr:postcode":"94558",
    "addr:street":"Kilburn Ave",
    "iso:country":"US",
    "sg:address":"2565 Kilburn Ave",
    "sg:city":"Napa",
    "sg:classifiers":[
        {
            "category":"Food & Beverages",
            "subcategory":"Meat & Fish",
            "type":"Retail Goods"
        }
    ],
    "sg:phone":"+1 707 226 3015",
    "sg:postcode":"94558",
    "sg:province":"CA",
    "wof:name":"Napa Food Ctr Meat & Deli",
    "wof:placetype":"venue"
},
  "geometry": {"coordinates":[-122.303256,38.294317],"type":"Point"}
}