{
  "type": "Feature",
  "properties": {
    "iso:country":"US",
    "sg:address":"2030 Camden Ave",
    "sg:city":"San Jose",
    "sg:classifiers":[
        {
            "category":"Organizations",
            "subcategory":"Religious Organization",
            "type":"Services"
        }
    ],
    "sg:phone":"+1 408 377 7748",
    "sg:postcode":"95124",
    "sg:province":"CA",
    "sg:tags":[
        "church"
    ],
    "wof:name":"Camden Avenue Baptist Church",
    "wof:placetype":"venue"
},
  "geometry": {"coordinates":[-121.935319,37.262209],"type":"Point"}
}