{
  "type": "Feature",
  "properties": {
    "iso:country":"US",
    "sg:address":"30 Van Ness Ave",
    "sg:city":"San Francisco",
    "sg:classifiers":[
        {
            "category":"Government",
            "subcategory":"Office",
            "type":"Public Place"
        }
    ],
    "sg:phone":"+1 415 557 7201",
    "sg:postcode":"94102",
    "sg:province":"CA",
    "sg:tags":[
        "regulatory",
        "agency",
        "labor"
    ],
    "wof:name":"Office Lbor Stndrds Enfrcement",
    "wof:placetype":"venue"
},
  "geometry": {"coordinates":[-122.419294,37.776042],"type":"Point"}
}