{
  "type": "Feature",
  "properties": {
    "addr:full":"2205 Faraday Ave Carlsbad CA 92008",
    "addr:housenumber":"2205",
    "addr:postcode":"92008",
    "addr:street":"Faraday Ave",
    "iso:country":"US",
    "sg:address":"2205 Faraday Ave",
    "sg:city":"Carlsbad",
    "sg:classifiers":[
        {
            "category":"Food & Beverages",
            "subcategory":"Specialty",
            "type":"Retail Goods"
        }
    ],
    "sg:phone":"+1 800 824 7861",
    "sg:postcode":"92008",
    "sg:province":"CA",
    "sg:tags":[
        "supplement",
        "vitamin"
    ],
    "wof:name":"Neo-Life Joanne & Norvel Martens",
    "wof:placetype":"venue"
},
  "geometry": {"coordinates":[-117.280027,33.13399],"type":"Point"}
}