{
  "type": "Feature",
  "properties": {
    "addr:full":"1504 W Cambridge Ave Fresno CA 93705",
    "addr:housenumber":"1504",
    "addr:postcode":"93705",
    "addr:street":"W Cambridge Ave",
    "iso:country":"US",
    "sg:address":"1504 W Cambridge Ave",
    "sg:city":"Fresno",
    "sg:classifiers":[
        {
            "category":"Professional",
            "subcategory":"Management & Consulting",
            "type":"Services"
        }
    ],
    "sg:phone":"+1 559 442 8138",
    "sg:postcode":"93705",
    "sg:province":"CA",
    "sg:tags":[
        "party",
        "planning"
    ],
    "wof:name":"Clowning By Scruffy",
    "wof:placetype":"venue"
},
  "geometry": {"coordinates":[-119.831042,36.76932],"type":"Point"}
}