{
  "type": "Feature",
  "properties": {
    "iso:country":"US",
    "sg:address":"87 W Colorado Blvd",
    "sg:city":"Pasadena",
    "sg:classifiers":[
        {
            "category":"Shopping",
            "subcategory":"Clothing, Apparel, & Fashions",
            "type":"Retail Goods"
        }
    ],
    "sg:phone":"+1 626 304 0055",
    "sg:postcode":"91105",
    "sg:province":"CA",
    "sg:tags":[
        "men's",
        "clothing",
        "accessory",
        "women's"
    ],
    "wof:name":"Diesel USA Pasadena",
    "wof:placetype":"venue"
},
  "geometry": {"coordinates":[-118.152,34.145599],"type":"Point"}
}