{
  "type": "Feature",
  "properties": {
    "iso:country":"US",
    "sg:address":"484 Lighthouse Ave",
    "sg:city":"Monterey",
    "sg:classifiers":[
        {
            "category":"Health Services",
            "subcategory":"Medical Lab",
            "type":"Services"
        }
    ],
    "sg:phone":"+1 831 375 7338",
    "sg:postcode":"93940",
    "sg:province":"CA",
    "sg:tags":[
        "laboratory"
    ],
    "wof:name":"Bay Dental Laboratories",
    "wof:placetype":"venue"
},
  "geometry": {"coordinates":[-121.900137,36.611659],"type":"Point"}
}