{
  "type": "Feature",
  "properties": {
    "addr:full":"14000 Pioneer Blvd Norwalk CA 90650",
    "addr:housenumber":"14000",
    "addr:postcode":"90650",
    "addr:street":"Pioneer Blvd",
    "iso:country":"US",
    "sg:address":"14000 Pioneer Blvd",
    "sg:city":"Norwalk",
    "sg:classifiers":[
        {
            "category":"Shopping",
            "subcategory":"Party Supplies",
            "type":"Retail Goods"
        },
        {
            "category":"Home & Garden",
            "subcategory":"Home Furnishings",
            "type":"Retail Goods"
        }
    ],
    "sg:phone":"+1 562 863 3580",
    "sg:postcode":"90650",
    "sg:province":"CA",
    "sg:tags":[
        "decor"
    ],
    "wof:name":"EDDYS JUMP",
    "wof:placetype":"venue"
},
  "geometry": {"coordinates":[-118.238209,33.904104],"type":"Point"}
}