{
  "type": "Feature",
  "properties": {
    "addr:full":"17328 S Mountain Rd Santa Paula CA 93060",
    "addr:housenumber":"17328",
    "addr:postcode":"93060",
    "addr:street":"S Mountain Rd",
    "iso:country":"US",
    "sg:address":"17328 S Mountain Rd",
    "sg:city":"Santa Paula",
    "sg:classifiers":[
        {
            "category":"Organizations",
            "subcategory":"Professional Association",
            "type":"Services"
        }
    ],
    "sg:phone":"+1 805 525 7319",
    "sg:postcode":"93060",
    "sg:province":"CA",
    "wof:name":"SAMCO",
    "wof:placetype":"venue"
},
  "geometry": {"coordinates":[-119.05580999999999,34.342047],"type":"Point"}
}