{
  "type": "Feature",
  "properties": {
    "iso:country":"US",
    "sg:address":"3205 Manhattan Ave",
    "sg:city":"Hermosa Beach",
    "sg:classifiers":[
        {
            "category":"Sports & Exercise",
            "subcategory":"Gym",
            "type":"Entertainment"
        }
    ],
    "sg:phone":"+1 310 376 6242",
    "sg:postcode":"90254",
    "sg:province":"CA",
    "sg:tags":[
        "club",
        "health",
        "studio",
        "gymnasium"
    ],
    "wof:name":"Pilates Room",
    "wof:placetype":"venue"
},
  "geometry": {"coordinates":[-118.406266,33.875836],"type":"Point"}
}