{
  "type": "Feature",
  "properties": {
    "addr:full":"9001 Las Tunas Dr Temple City CA 91780",
    "addr:housenumber":"9001",
    "addr:postcode":"91780",
    "addr:street":"Las Tunas Dr",
    "iso:country":"US",
    "sg:address":"9001 Las Tunas Dr",
    "sg:city":"Temple City",
    "sg:classifiers":[
        {
            "category":"Personal",
            "subcategory":"Barber",
            "type":"Services"
        }
    ],
    "sg:phone":"+1 626 451 0014",
    "sg:postcode":"91780",
    "sg:province":"CA",
    "wof:name":"Family Barbers",
    "wof:placetype":"venue"
},
  "geometry": {"coordinates":[-118.071707,34.104196],"type":"Point"}
}