{
  "type": "Feature",
  "properties": {
    "addr:full":"1093 Lincoln Ave San Jose CA 95125",
    "addr:housenumber":"1093",
    "addr:postcode":"95125",
    "addr:street":"Lincoln Ave",
    "iso:country":"US",
    "sg:address":"1093 Lincoln Ave",
    "sg:city":"San Jose",
    "sg:classifiers":[
        {
            "category":"Professional",
            "subcategory":"Lawyer & Legal Services",
            "type":"Services"
        }
    ],
    "sg:phone":"+1 408 298 3838",
    "sg:postcode":"95125",
    "sg:province":"CA",
    "sg:website":"www.knapplaw.com/",
    "wof:name":"Law Offices of Knapp & Knapp",
    "wof:placetype":"venue"
},
  "geometry": {"coordinates":[-121.901404,37.308952],"type":"Point"}
}