{
  "type": "Feature",
  "properties": {
    "iso:country":"US",
    "sg:address":"2615 H St",
    "sg:city":"Bakersfield",
    "sg:classifiers":[
        {
            "category":"Health Services",
            "subcategory":"Doctor",
            "type":"Services"
        }
    ],
    "sg:phone":"+1 661 635 3000",
    "sg:postcode":"93301",
    "sg:province":"CA",
    "sg:tags":[
        "clinic"
    ],
    "wof:name":"Comprehensive Care Clinic",
    "wof:placetype":"venue"
},
  "geometry": {"coordinates":[-119.02122199999999,35.38373],"type":"Point"}
}