{
  "type": "Feature",
  "properties": {
    "addr:full":"718 Pacific Ave San Francisco CA 94133",
    "addr:housenumber":"718",
    "addr:postcode":"94133",
    "addr:street":"Pacific Ave",
    "iso:country":"US",
    "sg:address":"718 Pacific Ave",
    "sg:city":"San Francisco",
    "sg:classifiers":[
        {
            "category":"Food & Beverages",
            "subcategory":"Specialty",
            "type":"Retail Goods"
        }
    ],
    "sg:phone":"+1 415 397 6888",
    "sg:postcode":"94133",
    "sg:province":"CA",
    "sg:tags":[
        "herb"
    ],
    "wof:name":"Kee Cheung Co",
    "wof:placetype":"venue"
},
  "geometry": {"coordinates":[-122.407105,37.796955],"type":"Point"}
}