{
  "type": "Feature",
  "properties": {
    "iso:country":"US",
    "sg:address":"200 Glendora Ave",
    "sg:city":"La Puente",
    "sg:classifiers":[
        {
            "category":"Banks & Credit Unions",
            "subcategory":"Financial Services",
            "type":"Services"
        }
    ],
    "sg:phone":"+1 626 961 1222",
    "sg:postcode":"91744",
    "sg:province":"CA",
    "sg:tags":[
        "investment"
    ],
    "wof:name":"Jazzy Investment Corporation",
    "wof:placetype":"venue"
},
  "geometry": {"coordinates":[-117.953044,34.022314],"type":"Point"}
}