{
  "type": "Feature",
  "properties": {
    "addr:full":"3526 Manthey Rd Stockton CA 95206",
    "addr:housenumber":"3526",
    "addr:postcode":"95206",
    "addr:street":"Manthey Rd",
    "iso:country":"US",
    "sg:address":"3526 Manthey Rd",
    "sg:city":"Stockton",
    "sg:classifiers":[
        {
            "category":"Personal",
            "subcategory":"Beauty Salon",
            "type":"Services"
        }
    ],
    "sg:phone":"+1 209 234 0796",
    "sg:postcode":"95206",
    "sg:province":"CA",
    "wof:name":"Hot Nails 2000",
    "wof:placetype":"venue"
},
  "geometry": {"coordinates":[-121.293712,37.910972],"type":"Point"}
}