{
  "type": "Feature",
  "properties": {
    "addr:full":"528 N LaBrea Avenue Los Angeles CA 90036",
    "addr:housenumber":"528",
    "addr:postcode":"90036",
    "addr:street":"N Labrea Avenue",
    "iso:country":"US",
    "sg:address":"528 N LaBrea Avenue",
    "sg:city":"Los Angeles",
    "sg:classifiers":[
        {
            "category":"Arts & Performance",
            "subcategory":"Arts Center",
            "type":"Entertainment"
        },
        {
            "category":"Retail",
            "subcategory":"Event Space",
            "type":"Services"
        },
        {
            "category":"Bars & Pubs",
            "subcategory":"Nightclub",
            "type":"Food & Drink"
        }
    ],
    "sg:phone":"+1 323 937 2343",
    "sg:postcode":"90036",
    "sg:province":"CA",
    "sg:tags":[
        "venue",
        "nightlife"
    ],
    "sg:website":"www.myspace.com/labrea528studio",
    "wof:name":"Studio 528",
    "wof:placetype":"venue"
},
  "geometry": {"coordinates":[-118.343706,34.081176],"type":"Point"}
}