{
  "type": "Feature",
  "properties": {
    "iso:country":"US",
    "sg:address":"3727 W 6th St",
    "sg:city":"Los Angeles",
    "sg:classifiers":[
        {
            "category":"Building & Trades",
            "subcategory":"Plumbing",
            "type":"Services"
        }
    ],
    "sg:phone":"+1 213 240 4719",
    "sg:postcode":"90020",
    "sg:province":"CA",
    "sg:tags":[
        "contractor"
    ],
    "wof:name":"Rosa Kin L AC",
    "wof:placetype":"venue"
},
  "geometry": {"coordinates":[-118.30346400000001,34.063625],"type":"Point"}
}