{
  "type": "Feature",
  "properties": {
    "iso:country":"US",
    "sg:address":"2201 W Pico Blvd",
    "sg:city":"Los Angeles",
    "sg:classifiers":[
        {
            "category":"Professional",
            "type":"Services"
        }
    ],
    "sg:phone":"+1 213 387 4153",
    "sg:postcode":"90006",
    "sg:province":"CA",
    "wof:name":"Sung S Chul",
    "wof:placetype":"venue"
},
  "geometry": {"coordinates":[-118.285332,34.047278],"type":"Point"}
}