{
  "type": "Feature",
  "properties": {
    "iso:country":"US",
    "sg:address":"2975 Meridian Ave",
    "sg:city":"San Jose",
    "sg:classifiers":[
        {
            "category":"Banks & Credit Unions",
            "subcategory":"Bank",
            "type":"Services"
        }
    ],
    "sg:phone":"+1 408 983 0588",
    "sg:postcode":"95124",
    "sg:province":"CA",
    "sg:website":"www.bankofamerica.com",
    "wof:name":"Bank Of America",
    "wof:placetype":"venue"
},
  "geometry": {"coordinates":[-121.906899,37.271544],"type":"Point"}
}