{
  "type": "Feature",
  "properties": {
    "iso:country":"US",
    "sg:address":"5189 Hospital Rd",
    "sg:city":"Mariposa",
    "sg:classifiers":[
        {
            "category":"Health Services",
            "subcategory":"Hospital",
            "type":"Services"
        }
    ],
    "sg:phone":"+1 209 966 3631",
    "sg:postcode":"95338",
    "sg:province":"CA",
    "wof:name":"John C Fremont Hospital",
    "wof:placetype":"venue"
},
  "geometry": {"coordinates":[-119.977679,37.502674],"type":"Point"}
}