{
  "type": "Feature",
  "properties": {
    "iso:country":"US",
    "sg:address":"2570 3rd St",
    "sg:city":"Sacramento",
    "sg:classifiers":[
        {
            "category":"Professional",
            "type":"Services"
        }
    ],
    "sg:phone":"+1 916 325 0035",
    "sg:postcode":"95818",
    "sg:province":"CA",
    "sg:tags":[
        "establishment"
    ],
    "wof:name":"Comsites West",
    "wof:placetype":"venue"
},
  "geometry": {"coordinates":[-121.510378,38.565456],"type":"Point"}
}