{
  "type": "Feature",
  "properties": {
    "iso:country":"US",
    "sg:address":"2454 Bryant St",
    "sg:city":"San Francisco",
    "sg:classifiers":[
        {
            "category":"Manufacturing",
            "subcategory":"Apparel",
            "type":"Manufacturing & Wholesale Goods"
        }
    ],
    "sg:phone":"+1 415 826 7187",
    "sg:postcode":"94110",
    "sg:province":"CA",
    "sg:tags":[
        "clot",
        "outerwear",
        "mfg"
    ],
    "wof:name":"Crave",
    "wof:placetype":"venue"
},
  "geometry": {"coordinates":[-122.40944500000001,37.755273],"type":"Point"}
}