{
  "type": "Feature",
  "properties": {
    "iso:country":"US",
    "sg:address":"1661 E Chapman Ave",
    "sg:city":"Fullerton",
    "sg:classifiers":[
        {
            "category":"Insurance",
            "subcategory":"Insurance Agent",
            "type":"Services"
        }
    ],
    "sg:phone":"+1 714 525 6328",
    "sg:postcode":"92831",
    "sg:province":"CA",
    "wof:name":"Sweney Insurance Service",
    "wof:placetype":"venue"
},
  "geometry": {"coordinates":[-117.899162,33.874217],"type":"Point"}
}