{
  "type": "Feature",
  "properties": {
    "iso:country":"US",
    "sg:address":"13223 Black Mountain Rd",
    "sg:city":"San Diego",
    "sg:classifiers":[
        {
            "category":"Personal",
            "subcategory":"Beauty Salon",
            "type":"Services"
        }
    ],
    "sg:phone":"+1 858 538 4751",
    "sg:postcode":"92129",
    "sg:province":"CA",
    "sg:tags":[
        "manicuring"
    ],
    "wof:name":"Nails By Julie Q",
    "wof:placetype":"venue"
},
  "geometry": {"coordinates":[-117.1296,32.956069],"type":"Point"}
}