{
  "type": "Feature",
  "properties": {
    "iso:country":"US",
    "sg:address":"18062 Irvine Blvd Ste 206",
    "sg:city":"Tustin",
    "sg:classifiers":[
        {
            "category":"Health Services",
            "subcategory":"Doctor",
            "type":"Services"
        }
    ],
    "sg:phone":"+1 714 832 9016",
    "sg:postcode":"92780",
    "sg:province":"CA",
    "wof:name":"Pacific South Medical Group",
    "wof:placetype":"venue"
},
  "geometry": {"coordinates":[-117.818001,33.748199],"type":"Point"}
}