{
  "type": "Feature",
  "properties": {
    "iso:country":"US",
    "sg:address":"6956 N Tully Rd",
    "sg:city":"Linden",
    "sg:classifiers":[
        {
            "category":"Manufacturing",
            "subcategory":"Retail Goods",
            "type":"Manufacturing & Wholesale Goods"
        }
    ],
    "sg:phone":"+1 209 931 2764",
    "sg:postcode":"95236",
    "sg:province":"CA",
    "sg:tags":[
        "product",
        "mfg"
    ],
    "wof:name":"Grizzly Industries LLC",
    "wof:placetype":"venue"
},
  "geometry": {"coordinates":[-121.128103,38.034961],"type":"Point"}
}