{
  "type": "Feature",
  "properties": {
    "addr:full":"11308 Penrose St Sun Valley CA 91352",
    "addr:housenumber":"11308",
    "addr:postcode":"91352",
    "addr:street":"Penrose St",
    "iso:country":"US",
    "sg:address":"11308 Penrose St",
    "sg:city":"Sun Valley",
    "sg:classifiers":[
        {
            "category":"Wholesale",
            "subcategory":"Apparel",
            "type":"Manufacturing & Wholesale Goods"
        }
    ],
    "sg:phone":"+1 818 252 3382",
    "sg:postcode":"91352",
    "sg:province":"CA",
    "wof:name":"Martha's Clothing",
    "wof:placetype":"venue"
},
  "geometry": {"coordinates":[-118.37929,34.223368],"type":"Point"}
}