{
  "type": "Feature",
  "properties": {
    "iso:country":"US",
    "sg:address":"9025 Sepulveda Blvd",
    "sg:city":"Sepulveda",
    "sg:classifiers":[
        {
            "category":"Retail",
            "subcategory":"Auto Repair",
            "type":"Services"
        }
    ],
    "sg:phone":"+1 818 830 0082",
    "sg:postcode":"91343",
    "sg:province":"CA",
    "sg:tags":[
        "repairing",
        "automobile",
        "radiator"
    ],
    "wof:name":"A & S Radiator & Mechanical",
    "wof:placetype":"venue"
},
  "geometry": {"coordinates":[-118.467584,34.233256],"type":"Point"}
}