{
  "type": "Feature",
  "properties": {
    "addr:full":"157 Appian Way South San Francisco CA 94080",
    "addr:housenumber":"157",
    "addr:postcode":"94080",
    "addr:street":"Appian Way",
    "iso:country":"US",
    "sg:address":"157 Appian Way",
    "sg:city":"South San Francisco",
    "sg:phone":"+1 650 588 1384",
    "sg:postcode":"94080",
    "sg:province":"CA",
    "sg:tags":[
        "equipment",
        "hotel",
        "supply"
    ],
    "wof:name":"Jopel Inc",
    "wof:placetype":"venue"
},
  "geometry": {"coordinates":[-122.445154,37.641375],"type":"Point"}
}