{
  "type": "Feature",
  "properties": {
    "addr:full":"5130 N Long Beach Blvd Long Beach CA 90805",
    "addr:housenumber":"5130",
    "addr:postcode":"90805",
    "addr:street":"N Long Beach Blvd",
    "iso:country":"US",
    "sg:address":"5130 N Long Beach Blvd",
    "sg:city":"Long Beach",
    "sg:classifiers":[
        {
            "category":"Autos & Motor Vehicles",
            "subcategory":"Auto Supplies",
            "type":"Retail Goods"
        }
    ],
    "sg:phone":"+1 562 422 4643",
    "sg:postcode":"90805",
    "sg:province":"CA",
    "sg:tags":[
        "automobile",
        "parts"
    ],
    "wof:name":"Amigos Auto Parts",
    "wof:placetype":"venue"
},
  "geometry": {"coordinates":[-118.19473600000001,33.849388],"type":"Point"}
}