{
  "type": "Feature",
  "properties": {
    "addr:full":"3555 Clares Street Capitola CA 95010",
    "addr:housenumber":"3555",
    "addr:postcode":"95010",
    "addr:street":"Clares Street",
    "iso:country":"US",
    "sg:address":"3555 Clares Street",
    "sg:city":"Capitola",
    "sg:classifiers":[
        {
            "category":"Shopping Center",
            "type":"Public Place"
        }
    ],
    "sg:phone":"+1 831 464 1774",
    "sg:postcode":"95010",
    "sg:province":"CA",
    "wof:name":"Brown Ranch Marketplace",
    "wof:placetype":"venue"
},
  "geometry": {"coordinates":[-121.968817,36.978284],"type":"Point"}
}