{
  "type": "Feature",
  "properties": {
    "iso:country":"US",
    "sg:address":"1221 West Third Street",
    "sg:city":"Los Angeles",
    "sg:classifiers":[
        {
            "category":"Real Estate",
            "subcategory":"Real Estate Operator",
            "type":"Services"
        }
    ],
    "sg:phone":"+1 866 690 2888",
    "sg:postcode":"90017",
    "sg:province":"CA",
    "sg:tags":[
        "apartment"
    ],
    "sg:website":"www.thevisconti.com/",
    "wof:name":"The Visconti",
    "wof:placetype":"venue"
},
  "geometry": {"coordinates":[-118.258687,34.057069],"type":"Point"}
}