{
  "type": "Feature",
  "properties": {
    "iso:country":"US",
    "sg:address":"1615 Barcelona St",
    "sg:city":"Livermore",
    "sg:classifiers":[
        {
            "category":"Professional",
            "subcategory":"Business Services",
            "type":"Services"
        }
    ],
    "sg:phone":"+1 925 245 0927",
    "sg:postcode":"94550",
    "sg:province":"CA",
    "sg:tags":[
        "drafting"
    ],
    "wof:name":"Colombo Design Co",
    "wof:placetype":"venue"
},
  "geometry": {"coordinates":[-121.78210199999999,37.660938],"type":"Point"}
}