{
  "type": "Feature",
  "properties": {
    "addr:full":"11505 Plane Tree Rd Fontana CA 92337",
    "addr:housenumber":"11505",
    "addr:postcode":"92337",
    "addr:street":"Plane Tree Rd",
    "iso:country":"US",
    "sg:address":"11505 Plane Tree Rd",
    "sg:city":"Fontana",
    "sg:classifiers":[
        {
            "category":"Freight",
            "type":"Transportation"
        }
    ],
    "sg:phone":"+1 909 823 1965",
    "sg:postcode":"92337",
    "sg:province":"CA",
    "sg:tags":[
        "local",
        "storage",
        "trucking"
    ],
    "wof:name":"M & M Specialty",
    "wof:placetype":"venue"
},
  "geometry": {"coordinates":[-117.458887,34.045511],"type":"Point"}
}