{
  "type": "Feature",
  "properties": {
    "addr:full":"1360 Bordeaux Dr Sunnyvale CA 94089",
    "addr:housenumber":"1360",
    "addr:postcode":"94089",
    "addr:street":"Bordeaux Dr",
    "iso:country":"US",
    "sg:address":"1360 Bordeaux Dr",
    "sg:city":"Sunnyvale",
    "sg:classifiers":[
        {
            "category":"Wholesale",
            "subcategory":"Electrical",
            "type":"Manufacturing & Wholesale Goods"
        }
    ],
    "sg:phone":"+1 408 745 0718",
    "sg:postcode":"94089",
    "sg:province":"CA",
    "sg:tags":[
        "semiconductor"
    ],
    "sg:website":"www.gttw.com.tw",
    "wof:name":"Global Testing Corp",
    "wof:placetype":"venue"
},
  "geometry": {"coordinates":[-122.02221,37.415659],"type":"Point"}
}