{
  "type": "Feature",
  "properties": {
    "addr:full":"3253 Stevens Creek Blvd San Jose CA 95117",
    "addr:housenumber":"3253",
    "addr:postcode":"95117",
    "addr:street":"Stevens Creek Blvd",
    "iso:country":"US",
    "sg:address":"3253 Stevens Creek Blvd",
    "sg:city":"San Jose",
    "sg:classifiers":[
        {
            "category":"Restaurant",
            "type":"Food & Drink"
        }
    ],
    "sg:menulink":"http://www.allmenus.com/ca/san-jose/75357-round-table-pizza/menu/",
    "sg:phone":"+1 408 296 3040",
    "sg:postcode":"95117",
    "sg:province":"CA",
    "sg:tags":[
        "american",
        "pizza"
    ],
    "wof:name":"Round Table Pizza",
    "wof:placetype":"venue"
},
  "geometry": {"coordinates":[-121.954425,37.32366],"type":"Point"}
}