{
  "type": "Feature",
  "properties": {
    "addr:full":"260 Church St San Francisco CA 94114",
    "addr:housenumber":"260",
    "addr:postcode":"94114",
    "addr:street":"Church St",
    "iso:country":"US",
    "sg:address":"260 Church St",
    "sg:city":"San Francisco",
    "sg:classifiers":[
        {
            "category":"Coffee & Tea",
            "type":"Food & Drink"
        }
    ],
    "sg:phone":"+1 415 621 2233",
    "sg:postcode":"94114",
    "sg:province":"CA",
    "wof:name":"Church Street Cafe",
    "wof:placetype":"venue"
},
  "geometry": {"coordinates":[-122.428909,37.766673],"type":"Point"}
}