{
  "type": "Feature",
  "properties": {
    "addr:full":"1329 Monterey St San Luis Obispo CA 93401",
    "addr:housenumber":"1329",
    "addr:postcode":"93401",
    "addr:street":"Monterey St",
    "iso:country":"US",
    "sg:address":"1329 Monterey St",
    "sg:city":"San Luis Obispo",
    "sg:classifiers":[
        {
            "category":"Shopping",
            "type":"Retail Goods"
        }
    ],
    "sg:phone":"+1 805 541 1300",
    "sg:postcode":"93401",
    "sg:province":"CA",
    "sg:tags":[
        "pet",
        "food",
        "supply"
    ],
    "wof:name":"Aquatic Adventures",
    "wof:placetype":"venue"
},
  "geometry": {"coordinates":[-120.65616300000001,35.284865],"type":"Point"}
}