{
  "type": "Feature",
  "properties": {
    "addr:full":"4401 E Anaheim St Long Beach CA 90804",
    "addr:housenumber":"4401",
    "addr:postcode":"90804",
    "addr:street":"E Anaheim St",
    "iso:country":"US",
    "sg:address":"4401 E Anaheim St",
    "sg:city":"Long Beach",
    "sg:classifiers":[
        {
            "category":"Retail",
            "subcategory":"Auto Repair",
            "type":"Services"
        }
    ],
    "sg:phone":"+1 562 438 1658",
    "sg:postcode":"90804",
    "sg:province":"CA",
    "sg:tags":[
        "brake"
    ],
    "sg:website":"www.eastlongbeachbrake.com",
    "wof:name":"East Long Beach Brake Service",
    "wof:placetype":"venue"
},
  "geometry": {"coordinates":[-118.141257,33.782853],"type":"Point"}
}