{
  "type": "Feature",
  "properties": {
    "addr:full":"1310 Bayswater Ave Burlingame CA 94010",
    "addr:housenumber":"1310",
    "addr:postcode":"94010",
    "addr:street":"Bayswater Ave",
    "iso:country":"US",
    "sg:address":"1310 Bayswater Ave",
    "sg:city":"Burlingame",
    "sg:classifiers":[
        {
            "category":"Organizations",
            "subcategory":"Religious Organization",
            "type":"Services"
        }
    ],
    "sg:phone":"+1 650 344 6884",
    "sg:postcode":"94010",
    "sg:province":"CA",
    "sg:tags":[
        "church"
    ],
    "wof:name":"St Catherine Catholic Church",
    "wof:placetype":"venue"
},
  "geometry": {"coordinates":[-122.345297,37.575279],"type":"Point"}
}