{
  "type": "Feature",
  "properties": {
    "iso:country":"US",
    "sg:address":"2649 Vista Way",
    "sg:city":"Oceanside",
    "sg:classifiers":[
        {
            "category":"Home & Garden",
            "subcategory":"Building Materials",
            "type":"Retail Goods"
        }
    ],
    "sg:phone":"+1 760 757 2266",
    "sg:postcode":"92054",
    "sg:province":"CA",
    "sg:tags":[
        "paint"
    ],
    "wof:name":"Kids N' Paint",
    "wof:placetype":"venue"
},
  "geometry": {"coordinates":[-117.329857,33.183147],"type":"Point"}
}