{
  "type": "Feature",
  "properties": {
    "iso:country":"US",
    "sg:address":"255 Parr Blvd",
    "sg:city":"Richmond",
    "sg:classifiers":[
        {
            "category":"Building & Trades",
            "subcategory":"Cleaning & Sanitation",
            "type":"Services"
        },
        {
            "category":"Professional",
            "subcategory":"Business Services",
            "type":"Services"
        }
    ],
    "sg:phone":"+1 510 235 1393",
    "sg:postcode":"94801",
    "sg:province":"CA",
    "sg:tags":[
        "control",
        "product",
        "hazardous",
        "material",
        "removal",
        "environmental",
        "ecological"
    ],
    "wof:name":"Ecology Control Industries, Inc.",
    "wof:placetype":"venue"
},
  "geometry": {"coordinates":[-122.366654,37.968299],"type":"Point"}
}