{
  "type": "Feature",
  "properties": {
    "iso:country":"US",
    "sg:address":"14724 Ventura Blvd",
    "sg:city":"Sherman Oaks",
    "sg:classifiers":[
        {
            "category":"Health Services",
            "subcategory":"Doctor",
            "type":"Services"
        }
    ],
    "sg:phone":"+1 818 905 6000",
    "sg:postcode":"91403",
    "sg:province":"CA",
    "sg:tags":[
        "physician",
        "surgeon"
    ],
    "wof:name":"Global Radiology",
    "wof:placetype":"venue"
},
  "geometry": {"coordinates":[-118.454812,34.151838],"type":"Point"}
}