{
  "type": "Feature",
  "properties": {
    "iso:country":"US",
    "sg:address":"33030 Ocean View Dr",
    "sg:city":"Fort Bragg",
    "sg:classifiers":[
        {
            "category":"Social Services",
            "subcategory":"Adult Care",
            "type":"Services"
        }
    ],
    "sg:phone":"+1 707 961 0245",
    "sg:postcode":"95437",
    "sg:province":"CA",
    "sg:tags":[
        "home",
        "residential"
    ],
    "wof:name":"Coastal Dunes Retreat",
    "wof:placetype":"venue"
},
  "geometry": {"coordinates":[-123.764709,39.529655],"type":"Point"}
}