{
  "type": "Feature",
  "properties": {
    "iso:country":"US",
    "sg:address":"417 N Chester Ave",
    "sg:city":"Bakersfield",
    "sg:classifiers":[
        {
            "category":"Retail",
            "subcategory":"Auto Repair",
            "type":"Services"
        }
    ],
    "sg:phone":"+1 661 393 0809",
    "sg:postcode":"93308",
    "sg:province":"CA",
    "sg:tags":[
        "brake"
    ],
    "wof:name":"Dennis Beachler's Wheel",
    "wof:placetype":"venue"
},
  "geometry": {"coordinates":[-119.021165,35.410331],"type":"Point"}
}