{
  "type": "Feature",
  "properties": {
    "addr:full":"3737 E 14th St Long Beach CA 90804",
    "addr:housenumber":"3737",
    "addr:postcode":"90804",
    "addr:street":"E 14Th St",
    "iso:country":"US",
    "sg:address":"3737 E 14th St",
    "sg:city":"Long Beach",
    "sg:classifiers":[
        {
            "category":"Shopping",
            "subcategory":"Used Merchandise",
            "type":"Retail Goods"
        }
    ],
    "sg:phone":"+1 562 987 2220",
    "sg:postcode":"90804",
    "sg:province":"CA",
    "wof:name":"Consignment and Imports",
    "wof:placetype":"venue"
},
  "geometry": {"coordinates":[-118.148445,33.784936],"type":"Point"}
}