{
  "type": "Feature",
  "properties": {
    "addr:full":"23930 Avenida Crescenta Santa Clarita CA 91355",
    "addr:housenumber":"23930",
    "addr:postcode":"91355",
    "addr:street":"Avenida Crescenta",
    "iso:country":"US",
    "sg:address":"23930 Avenida Crescenta",
    "sg:city":"Santa Clarita",
    "sg:classifiers":[
        {
            "category":"Building & Trades",
            "subcategory":"Plumbing",
            "type":"Services"
        }
    ],
    "sg:phone":"+1 661 255 9611",
    "sg:postcode":"91355",
    "sg:province":"CA",
    "wof:name":"Plumbologist The",
    "wof:placetype":"venue"
},
  "geometry": {"coordinates":[-118.55278,34.383384],"type":"Point"}
}