{
  "type": "Feature",
  "properties": {
    "iso:country":"US",
    "sg:address":"2000 Petaluma Blvd N",
    "sg:city":"Petaluma",
    "sg:classifiers":[
        {
            "category":"Retail",
            "subcategory":"Auto Repair",
            "type":"Services"
        }
    ],
    "sg:phone":"+1 707 766 8106",
    "sg:postcode":"94952",
    "sg:province":"CA",
    "sg:tags":[
        "wrecker"
    ],
    "wof:name":"Dion's Auto Mall",
    "wof:placetype":"venue"
},
  "geometry": {"coordinates":[-122.649974,38.253593],"type":"Point"}
}