{
  "type": "Feature",
  "properties": {
    "addr:full":"1439 Sweetwater Ln Spring Valley CA 91977",
    "addr:housenumber":"1439",
    "addr:postcode":"91977",
    "addr:street":"Sweetwater Ln",
    "iso:country":"US",
    "sg:address":"1439 Sweetwater Ln",
    "sg:city":"Spring Valley",
    "sg:classifiers":[
        {
            "category":"Professional",
            "type":"Services"
        }
    ],
    "sg:phone":"+1 619 466 3723",
    "sg:postcode":"91977",
    "sg:province":"CA",
    "wof:name":"Toby Howard Designs",
    "wof:placetype":"venue"
},
  "geometry": {"coordinates":[-117.005563,32.718794],"type":"Point"}
}