{
  "type": "Feature",
  "properties": {
    "addr:full":"1244 Deerpark Dr Fullerton CA 92831",
    "addr:housenumber":"1244",
    "addr:postcode":"92831",
    "addr:street":"Deerpark Dr",
    "iso:country":"US",
    "sg:address":"1244 Deerpark Dr",
    "sg:city":"Fullerton",
    "sg:classifiers":[
        {
            "category":"Building & Trades",
            "subcategory":"Landscaping Services",
            "type":"Services"
        }
    ],
    "sg:phone":"+1 714 985 9864",
    "sg:postcode":"92831",
    "sg:province":"CA",
    "sg:tags":[
        "landscape"
    ],
    "wof:name":"Johns Landscape",
    "wof:placetype":"venue"
},
  "geometry": {"coordinates":[-117.877895,33.883842],"type":"Point"}
}