{
  "type": "Feature",
  "properties": {
    "addr:full":"834 Olympic Ct Brentwood CA 94513",
    "addr:housenumber":"834",
    "addr:postcode":"94513",
    "addr:street":"Olympic Ct",
    "iso:country":"US",
    "sg:address":"834 Olympic Ct",
    "sg:city":"Brentwood",
    "sg:classifiers":[
        {
            "category":"Taxi",
            "type":"Transportation"
        }
    ],
    "sg:phone":"+1 925 676 8841",
    "sg:postcode":"94513",
    "sg:province":"CA",
    "sg:tags":[
        "taxicab"
    ],
    "wof:name":"Valley Cab Co",
    "wof:placetype":"venue"
},
  "geometry": {"coordinates":[-121.737589,37.933494],"type":"Point"}
}