{
  "type": "Feature",
  "properties": {
    "iso:country":"US",
    "sg:address":"4020 Salem St",
    "sg:city":"Concord",
    "sg:classifiers":[
        {
            "category":"Professional",
            "type":"Services"
        }
    ],
    "sg:phone":"+1 925 288 0250",
    "sg:postcode":"94521",
    "sg:province":"CA",
    "wof:name":"Seal E",
    "wof:placetype":"venue"
},
  "geometry": {"coordinates":[-121.997691,37.970174],"type":"Point"}
}