{
  "type": "Feature",
  "properties": {
    "iso:country":"US",
    "sg:address":"7101 Yorktown Ave Ste 107",
    "sg:city":"Huntington Beach",
    "sg:classifiers":[
        {
            "category":"Restaurant",
            "type":"Food & Drink"
        }
    ],
    "sg:phone":"+1 714 374 7678",
    "sg:postcode":"92648",
    "sg:province":"CA",
    "sg:tags":[
        "pizza"
    ],
    "sg:website":"www.pizzarito.net",
    "wof:name":"Pizzarito",
    "wof:placetype":"venue"
},
  "geometry": {"coordinates":[-118.003698,33.680697],"type":"Point"}
}