{
  "type": "Feature",
  "properties": {
    "addr:full":"250 E Hamilton Ave Campbell CA 95008",
    "addr:housenumber":"250",
    "addr:postcode":"95008",
    "addr:street":"E Hamilton Ave",
    "iso:country":"US",
    "sg:address":"250 E Hamilton Ave",
    "sg:city":"Campbell",
    "sg:classifiers":[
        {
            "category":"Professional",
            "subcategory":"Advertising",
            "type":"Services"
        }
    ],
    "sg:phone":"+1 408 866 7000",
    "sg:postcode":"95008",
    "sg:province":"CA",
    "wof:name":"Westwind Identity Products Inc",
    "wof:placetype":"venue"
},
  "geometry": {"coordinates":[-121.945628,37.294089],"type":"Point"}
}