{
  "type": "Feature",
  "properties": {
    "addr:full":"2727 Park Blvd Oakland CA 94606",
    "addr:housenumber":"2727",
    "addr:postcode":"94606",
    "addr:street":"Park Blvd",
    "iso:country":"US",
    "sg:address":"2727 Park Blvd",
    "sg:city":"Oakland",
    "sg:classifiers":[
        {
            "category":"Social Services",
            "subcategory":"Child Care",
            "type":"Services"
        }
    ],
    "sg:phone":"+1 510 763 0629",
    "sg:postcode":"94606",
    "sg:province":"CA",
    "sg:tags":[
        "day"
    ],
    "wof:name":"Small Frye Day Care Preschool-Night",
    "wof:placetype":"venue"
},
  "geometry": {"coordinates":[-122.24099699999999,37.802601],"type":"Point"}
}