{
  "type": "Feature",
  "properties": {
    "iso:country":"US",
    "sg:address":"16141 Sherman Way",
    "sg:city":"Van Nuys",
    "sg:classifiers":[
        {
            "category":"Autos & Motor Vehicles",
            "subcategory":"Motorcycle Sales",
            "type":"Retail Goods"
        }
    ],
    "sg:phone":"+1 818 994 2882",
    "sg:postcode":"91406",
    "sg:province":"CA",
    "sg:tags":[
        "scooter"
    ],
    "sg:website":"www.suzukiofvannuys.com",
    "wof:name":"Suzuki Of Van Nuys",
    "wof:placetype":"venue"
},
  "geometry": {"coordinates":[-118.485106,34.201125],"type":"Point"}
}