{
  "type": "Feature",
  "properties": {
    "addr:full":"10531 S Western Ave Los Angeles CA 90047",
    "addr:housenumber":"10531",
    "addr:postcode":"90047",
    "addr:street":"S Western Ave",
    "iso:country":"US",
    "sg:address":"10531 S Western Ave",
    "sg:city":"Los Angeles",
    "sg:classifiers":[
        {
            "category":"Social Services",
            "subcategory":"Child Care",
            "type":"Services"
        }
    ],
    "sg:phone":"+1 323 756 8097",
    "sg:postcode":"90047",
    "sg:province":"CA",
    "sg:tags":[
        "kindergarten",
        "academic",
        "school"
    ],
    "wof:name":"Nelson Christian School",
    "wof:placetype":"venue"
},
  "geometry": {"coordinates":[-118.309094,33.940077],"type":"Point"}
}