{
  "type": "Feature",
  "properties": {
    "iso:country":"US",
    "sg:address":"12824 Lakeshore Dr",
    "sg:city":"Lakeside",
    "sg:classifiers":[
        {
            "category":"Social Services",
            "type":"Services"
        }
    ],
    "sg:phone":"+1 619 443 9293",
    "sg:postcode":"92040",
    "sg:province":"CA",
    "sg:tags":[
        "youth",
        "organization",
        "center"
    ],
    "wof:name":"Boys & Girls Club Of Lakeside",
    "wof:placetype":"venue"
},
  "geometry": {"coordinates":[-116.91284,32.85856],"type":"Point"}
}