{
  "type": "Feature",
  "properties": {
    "iso:country":"US",
    "sg:address":"831 Grant Ave",
    "sg:city":"San Francisco",
    "sg:classifiers":[
        {
            "category":"Coffee & Tea",
            "type":"Food & Drink"
        }
    ],
    "sg:phone":"+1 415 395 0868",
    "sg:postcode":"94108",
    "sg:province":"CA",
    "sg:website":"www.redblossomtea.com",
    "wof:name":"Red Blossom Tea Company",
    "wof:placetype":"venue"
},
  "geometry": {"coordinates":[-122.406569,37.794727],"type":"Point"}
}