{
  "type": "Feature",
  "properties": {
    "addr:full":"42263 58th St W Lancaster CA 93536",
    "addr:housenumber":"42263",
    "addr:postcode":"93536",
    "addr:street":"58Th St W",
    "iso:country":"US",
    "sg:address":"42263 58th St W",
    "sg:city":"Lancaster",
    "sg:classifiers":[
        {
            "category":"Travel",
            "subcategory":"Travel Agent",
            "type":"Entertainment"
        }
    ],
    "sg:phone":"+1 661 722 3113",
    "sg:postcode":"93536",
    "sg:province":"CA",
    "sg:tags":[
        "operator",
        "tour"
    ],
    "wof:name":"Tours With TLC",
    "wof:placetype":"venue"
},
  "geometry": {"coordinates":[-118.23282,34.650073],"type":"Point"}
}