{
  "type": "Feature",
  "properties": {
    "addr:full":"369 E 17th St Ste 12 Costa Mesa CA 92627",
    "addr:housenumber":"369",
    "addr:postcode":"92627",
    "addr:street":"E 17Th St Ste 12",
    "iso:country":"US",
    "sg:address":"369 E 17th St Ste 12",
    "sg:city":"Costa Mesa",
    "sg:classifiers":[
        {
            "category":"Restaurant",
            "type":"Food & Drink"
        }
    ],
    "sg:phone":"+1 949 646 4644",
    "sg:postcode":"92627",
    "sg:province":"CA",
    "sg:tags":[
        "mongolian",
        "barbeque"
    ],
    "wof:name":"Mongolian Bar-B-Que Pan Asia",
    "wof:placetype":"venue"
},
  "geometry": {"coordinates":[-117.912924,33.631384],"type":"Point"}
}