{
  "type": "Feature",
  "properties": {
    "addr:full":"5252 S Hoover St Los Angeles CA 90037",
    "addr:housenumber":"5252",
    "addr:postcode":"90037",
    "addr:street":"S Hoover St",
    "iso:country":"US",
    "sg:address":"5252 S Hoover St",
    "sg:city":"Los Angeles",
    "sg:classifiers":[
        {
            "category":"Organizations",
            "subcategory":"Religious Organization",
            "type":"Services"
        }
    ],
    "sg:phone":"+1 323 232 2447",
    "sg:postcode":"90037",
    "sg:province":"CA",
    "sg:tags":[
        "church"
    ],
    "wof:name":"Epistles of God Church",
    "wof:placetype":"venue"
},
  "geometry": {"coordinates":[-118.287003,33.994701],"type":"Point"}
}