{
  "type": "Feature",
  "properties": {
    "iso:country":"US",
    "sg:address":"15555 E 14th St",
    "sg:city":"San Leandro",
    "sg:classifiers":[
        {
            "category":"Shopping",
            "subcategory":"Mobile Phones",
            "type":"Retail Goods"
        }
    ],
    "sg:phone":"+1 510 481 2883",
    "sg:postcode":"94578",
    "sg:province":"CA",
    "wof:name":"RadioShack",
    "wof:placetype":"venue"
},
  "geometry": {"coordinates":[-122.12478299999999,37.702338],"type":"Point"}
}