{
  "type": "Feature",
  "properties": {
    "addr:full":"647 14th St Arcata CA 95521",
    "addr:housenumber":"647",
    "addr:postcode":"95521",
    "addr:street":"14Th St",
    "iso:country":"US",
    "sg:address":"647 14th St",
    "sg:city":"Arcata",
    "sg:classifiers":[
        {
            "category":"Organizations",
            "subcategory":"Religious Organization",
            "type":"Services"
        }
    ],
    "sg:phone":"+1 707 822 1082",
    "sg:postcode":"95521",
    "sg:province":"CA",
    "wof:name":"First Church of Christ",
    "wof:placetype":"venue"
},
  "geometry": {"coordinates":[-124.083898,40.872583],"type":"Point"}
}