{
  "type": "Feature",
  "properties": {
    "addr:full":"611 Santa Rosa Ave Santa Rosa CA 95404",
    "addr:housenumber":"611",
    "addr:postcode":"95404",
    "addr:street":"Santa Rosa Ave",
    "iso:country":"US",
    "sg:address":"611 Santa Rosa Ave",
    "sg:city":"Santa Rosa",
    "sg:classifiers":[
        {
            "category":"Manufacturing",
            "subcategory":"Signs",
            "type":"Manufacturing & Wholesale Goods"
        }
    ],
    "sg:phone":"+1 707 578 8200",
    "sg:postcode":"95404",
    "sg:province":"CA",
    "sg:tags":[
        "specialty",
        "mfg"
    ],
    "wof:name":"Epic Images",
    "wof:placetype":"venue"
},
  "geometry": {"coordinates":[-122.71150299999999,38.432308],"type":"Point"}
}