{
  "type": "Feature",
  "properties": {
    "iso:country":"US",
    "sg:address":"605 Evergreen Dr",
    "sg:city":"Wheatland",
    "sg:classifiers":[
        {
            "category":"Shopping",
            "subcategory":"Used Merchandise",
            "type":"Retail Goods"
        }
    ],
    "sg:phone":"+1 530 249 1536",
    "sg:postcode":"95692",
    "sg:province":"CA",
    "wof:name":"Old Town Second Hand",
    "wof:placetype":"venue"
},
  "geometry": {"coordinates":[-121.43734,39.015398],"type":"Point"}
}