{
  "type": "Feature",
  "properties": {
    "iso:country":"US",
    "sg:address":"1414 E Shaw Ave",
    "sg:city":"Fresno",
    "sg:classifiers":[
        {
            "category":"Restaurant",
            "type":"Food & Drink"
        }
    ],
    "sg:phone":"+1 559 228 3388",
    "sg:postcode":"93710",
    "sg:province":"CA",
    "wof:name":"Dragon Palace",
    "wof:placetype":"venue"
},
  "geometry": {"coordinates":[-119.765084,36.80865],"type":"Point"}
}