{
  "type": "Feature",
  "properties": {
    "addr:full":"2110 Pacific Ave Alameda CA 94501",
    "addr:housenumber":"2110",
    "addr:postcode":"94501",
    "addr:street":"Pacific Ave",
    "iso:country":"US",
    "sg:address":"2110 Pacific Ave",
    "sg:city":"Alameda",
    "sg:classifiers":[
        {
            "category":"Professional",
            "subcategory":"Business Services",
            "type":"Services"
        }
    ],
    "sg:phone":"+1 510 749 9803",
    "sg:postcode":"94501",
    "sg:province":"CA",
    "sg:tags":[
        "diver"
    ],
    "wof:name":"Harvey Industries",
    "wof:placetype":"venue"
},
  "geometry": {"coordinates":[-122.24505600000001,37.76933],"type":"Point"}
}