{
  "type": "Feature",
  "properties": {
    "addr:full":"2201 Polk St San Francisco CA 94109",
    "addr:housenumber":"2201",
    "addr:postcode":"94109",
    "addr:street":"Polk St",
    "iso:country":"US",
    "sg:address":"2201 Polk St",
    "sg:city":"San Francisco",
    "sg:classifiers":[
        {
            "category":"Bars & Pubs",
            "type":"Food & Drink"
        }
    ],
    "sg:phone":"+1 415 928 2303",
    "sg:postcode":"94109",
    "sg:province":"CA",
    "wof:name":"Royal Oak",
    "wof:placetype":"venue"
},
  "geometry": {"coordinates":[-122.42225000000001,37.797001],"type":"Point"}
}