{
  "type": "Feature",
  "properties": {
    "addr:full":"102 S Euclid Ave San Diego CA 92114",
    "addr:housenumber":"102",
    "addr:postcode":"92114",
    "addr:street":"S Euclid Ave",
    "iso:country":"US",
    "sg:address":"102 S Euclid Ave",
    "sg:city":"San Diego",
    "sg:classifiers":[
        {
            "category":"Professional",
            "subcategory":"Lawyer & Legal Services",
            "type":"Services"
        }
    ],
    "sg:phone":"+1 619 262 0896",
    "sg:postcode":"92114",
    "sg:province":"CA",
    "sg:tags":[
        "attorney"
    ],
    "sg:website":"www.lassd.org",
    "wof:name":"Legal Aid Society Of San Diego",
    "wof:placetype":"venue"
},
  "geometry": {"coordinates":[-117.085076,32.703228],"type":"Point"}
}