{
  "type": "Feature",
  "properties": {
    "iso:country":"US",
    "sg:address":"645 Raymond Ave",
    "sg:city":"Santa Monica",
    "sg:classifiers":[
        {
            "category":"Real Estate",
            "subcategory":"Real Estate Agent",
            "type":"Services"
        }
    ],
    "sg:phone":"+1 310 392 9368",
    "sg:postcode":"90405",
    "sg:province":"CA",
    "sg:tags":[
        "consultant"
    ],
    "wof:name":"Anderson & Assoc",
    "wof:placetype":"venue"
},
  "geometry": {"coordinates":[-118.475797,34.004131],"type":"Point"}
}