{
  "type": "Feature",
  "properties": {
    "addr:full":"286 Barnard Ave San Jose CA 95125",
    "addr:housenumber":"286",
    "addr:postcode":"95125",
    "addr:street":"Barnard Ave",
    "iso:country":"US",
    "sg:address":"286 Barnard Ave",
    "sg:city":"San Jose",
    "sg:classifiers":[
        {
            "category":"Personal",
            "type":"Services"
        }
    ],
    "sg:phone":"+1 408 286 2110",
    "sg:postcode":"95125",
    "sg:province":"CA",
    "sg:tags":[
        "party",
        "planning",
        "event"
    ],
    "sg:website":"www.itsabouttheart.com",
    "wof:name":"North American Theatre Technology",
    "wof:placetype":"venue"
},
  "geometry": {"coordinates":[-121.87571199999999,37.306496],"type":"Point"}
}