{
  "type": "Feature",
  "properties": {
    "iso:country":"US",
    "sg:address":"272 King St",
    "sg:city":"San Francisco",
    "sg:classifiers":[
        {
            "category":"Personal",
            "subcategory":"Tanning Parlor",
            "type":"Services"
        }
    ],
    "sg:phone":"+1 415 512 8267",
    "sg:postcode":"94107",
    "sg:province":"CA",
    "sg:website":"www.tanbella.com",
    "wof:name":"Tan Bella",
    "wof:placetype":"venue"
},
  "geometry": {"coordinates":[-122.393501,37.776929],"type":"Point"}
}