{
  "type": "Feature",
  "properties": {
    "addr:full":"272 King St San Francisco CA 94107",
    "addr:housenumber":"272",
    "addr:postcode":"94107",
    "addr:street":"King St",
    "iso:country":"US",
    "sg:address":"272 King St",
    "sg:city":"San Francisco",
    "sg:classifiers":[
        {
            "category":"Personal",
            "subcategory":"Tanning Parlor",
            "type":"Services"
        }
    ],
    "sg:phone":"+1 415 512 8267",
    "sg:postcode":"94107",
    "sg:province":"CA",
    "sg:website":"www.tanbella.com",
    "wof:name":"Tan Bella",
    "wof:placetype":"venue"
},
  "geometry": {"coordinates":[-122.393501,37.776929],"type":"Point"}
}