{
  "type": "Feature",
  "properties": {
    "addr:full":"3555 W Temple Street Los Angeles CA 90004",
    "addr:housenumber":"3555",
    "addr:postcode":"90004",
    "addr:street":"W Temple Street",
    "iso:country":"US",
    "sg:address":"3555 W Temple Street",
    "sg:city":"Los Angeles",
    "sg:classifiers":[
        {
            "category":"Health Services",
            "subcategory":"Doctor",
            "type":"Services"
        }
    ],
    "sg:phone":"+1 323 644 6888",
    "sg:postcode":"90004",
    "sg:province":"CA",
    "wof:name":"Holy Medical Clinic",
    "wof:placetype":"venue"
},
  "geometry": {"coordinates":[-118.285706,34.076618],"type":"Point"}
}