{
  "type": "Feature",
  "properties": {
    "iso:country":"US",
    "sg:address":"303 Highland Ave",
    "sg:city":"National City",
    "sg:classifiers":[
        {
            "category":"Professional",
            "type":"Services"
        }
    ],
    "sg:phone":"+1 619 474 6735",
    "sg:postcode":"91950",
    "sg:province":"CA",
    "wof:name":"Lip Liner",
    "wof:placetype":"venue"
},
  "geometry": {"coordinates":[-117.100008,32.68163],"type":"Point"}
}