{
  "type": "Feature",
  "properties": {
    "iso:country":"US",
    "sg:address":"5624 Vineland Ave",
    "sg:city":"North Hollywood",
    "sg:classifiers":[
        {
            "category":"Communications",
            "type":"Services"
        }
    ],
    "sg:phone":"+1 818 769 8863",
    "sg:postcode":"91601",
    "sg:province":"CA",
    "sg:tags":[
        "recording",
        "rehearsal",
        "studio"
    ],
    "wof:name":"Full Kilt",
    "wof:placetype":"venue"
},
  "geometry": {"coordinates":[-118.370003,34.173],"type":"Point"}
}