{
  "type": "Feature",
  "properties": {
    "addr:full":"1265 Craig Ave Sonoma CA 95476",
    "addr:housenumber":"1265",
    "addr:postcode":"95476",
    "addr:street":"Craig Ave",
    "iso:country":"US",
    "sg:address":"1265 Craig Ave",
    "sg:city":"Sonoma",
    "sg:classifiers":[
        {
            "category":"Manufacturing",
            "subcategory":"Food",
            "type":"Manufacturing & Wholesale Goods"
        }
    ],
    "sg:phone":"+1 707 996 1478",
    "sg:postcode":"95476",
    "sg:province":"CA",
    "sg:tags":[
        "eating",
        "mfg"
    ],
    "wof:name":"Berthoud Vineyards & Winery",
    "wof:placetype":"venue"
},
  "geometry": {"coordinates":[-122.502707,38.301893],"type":"Point"}
}