{
  "type": "Feature",
  "properties": {
    "addr:full":"1480 W 178th St Gardena CA 90248",
    "addr:housenumber":"1480",
    "addr:postcode":"90248",
    "addr:street":"W 178Th St",
    "iso:country":"US",
    "sg:address":"1480 W 178th St",
    "sg:city":"Gardena",
    "sg:classifiers":[
        {
            "category":"Professional",
            "subcategory":"Testing Lab",
            "type":"Services"
        }
    ],
    "sg:phone":"+1 310 324 9427",
    "sg:postcode":"90248",
    "sg:province":"CA",
    "sg:tags":[
        "analytical",
        "laboratory"
    ],
    "wof:name":"R G A Labs",
    "wof:placetype":"venue"
},
  "geometry": {"coordinates":[-118.301975,33.869222],"type":"Point"}
}