{
  "type": "Feature",
  "properties": {
    "iso:country":"US",
    "sg:address":"14519 Ramona Blvd",
    "sg:city":"Baldwin Park",
    "sg:classifiers":[
        {
            "category":"Restaurant",
            "type":"Food & Drink"
        }
    ],
    "sg:menulink":"http://www.allmenus.com/ca/east-san-gabriel-valley/87702-little-caesars-pizza/menu/",
    "sg:phone":"+1 626 430 9166",
    "sg:postcode":"91706",
    "sg:province":"CA",
    "sg:tags":[
        "american",
        "pizza"
    ],
    "wof:name":"Little Caesar's Pizza",
    "wof:placetype":"venue"
},
  "geometry": {"coordinates":[-117.95793,34.088034],"type":"Point"}
}