{
  "type": "Feature",
  "properties": {
    "addr:full":"6718 San Ramon Dr Los Angeles CA 90042",
    "addr:housenumber":"6718",
    "addr:postcode":"90042",
    "addr:street":"San Ramon Dr",
    "iso:country":"US",
    "sg:address":"6718 San Ramon Dr",
    "sg:city":"Los Angeles",
    "sg:classifiers":[
        {
            "category":"Health Services",
            "subcategory":"Nursing And Care Facility",
            "type":"Services"
        }
    ],
    "sg:phone":"+1 323 257 7746",
    "sg:postcode":"90042",
    "sg:province":"CA",
    "sg:tags":[
        "home",
        "convalescent"
    ],
    "wof:name":"Frederick I Hoskins Inc",
    "wof:placetype":"venue"
},
  "geometry": {"coordinates":[-118.16779699999999,34.121809],"type":"Point"}
}