{
  "type": "Feature",
  "properties": {
    "iso:country":"US",
    "sg:address":"500 Newport Center Dr",
    "sg:city":"Newport Beach",
    "sg:classifiers":[
        {
            "category":"Professional",
            "type":"Services"
        }
    ],
    "sg:phone":"+1 949 721 0734",
    "sg:postcode":"92660",
    "sg:province":"CA",
    "sg:tags":[
        "establishment"
    ],
    "wof:name":"WINC Enterprises",
    "wof:placetype":"venue"
},
  "geometry": {"coordinates":[-117.87228500000001,33.616716],"type":"Point"}
}