{
  "type": "Feature",
  "properties": {
    "addr:full":"2372 Buena Vista Ave Walnut Creek CA 94597",
    "addr:housenumber":"2372",
    "addr:postcode":"94597",
    "addr:street":"Buena Vista Ave",
    "iso:country":"US",
    "sg:address":"2372 Buena Vista Ave",
    "sg:city":"Walnut Creek",
    "sg:classifiers":[
        {
            "category":"Social Services",
            "subcategory":"Child Care",
            "type":"Services"
        }
    ],
    "sg:phone":"+1 925 930 0272",
    "sg:postcode":"94597",
    "sg:province":"CA",
    "wof:name":"Buena Vista Club",
    "wof:placetype":"venue"
},
  "geometry": {"coordinates":[-122.071057,37.911542],"type":"Point"}
}