{
  "type": "Feature",
  "properties": {
    "addr:full":"1128 Westmont Dr San Pedro CA 90731",
    "addr:housenumber":"1128",
    "addr:postcode":"90731",
    "addr:street":"Westmont Dr",
    "iso:country":"US",
    "sg:address":"1128 Westmont Dr",
    "sg:city":"San Pedro",
    "sg:classifiers":[
        {
            "category":"Retail",
            "subcategory":"Auto Repair",
            "type":"Services"
        }
    ],
    "sg:phone":"+1 310 519 1455",
    "sg:postcode":"90731",
    "sg:province":"CA",
    "sg:tags":[
        "repairing",
        "automobile"
    ],
    "wof:name":"Matteo's Auto Repair",
    "wof:placetype":"venue"
},
  "geometry": {"coordinates":[-118.302119,33.763503],"type":"Point"}
}