{
  "type": "Feature",
  "properties": {
    "iso:country":"US",
    "sg:address":"7710 N Fresno St",
    "sg:city":"Fresno",
    "sg:classifiers":[
        {
            "category":"Health Services",
            "subcategory":"Doctor",
            "type":"Services"
        }
    ],
    "sg:phone":"+1 559 437 9100",
    "sg:postcode":"93720",
    "sg:province":"CA",
    "sg:tags":[
        "physician",
        "surgeon"
    ],
    "wof:name":"Weight Management Ctr",
    "wof:placetype":"venue"
},
  "geometry": {"coordinates":[-119.7837,36.850196],"type":"Point"}
}