{
  "type": "Feature",
  "properties": {
    "addr:full":"8407 Ruggles Ct Fair Oaks CA 95628",
    "addr:housenumber":"8407",
    "addr:postcode":"95628",
    "addr:street":"Ruggles Ct",
    "iso:country":"US",
    "sg:address":"8407 Ruggles Ct",
    "sg:city":"Fair Oaks",
    "sg:classifiers":[
        {
            "category":"Professional",
            "type":"Services"
        }
    ],
    "sg:phone":"+1 916 965 3234",
    "sg:postcode":"95628",
    "sg:province":"CA",
    "wof:name":"Daneshvar Inc",
    "wof:placetype":"venue"
},
  "geometry": {"coordinates":[-121.246477,38.654783],"type":"Point"}
}