{
  "type": "Feature",
  "properties": {
    "iso:country":"US",
    "sg:address":"1100 Cll del Cerro",
    "sg:city":"San Clemente",
    "sg:classifiers":[
        {
            "category":"Professional",
            "type":"Services"
        }
    ],
    "sg:phone":"+1 949 429 6726",
    "sg:postcode":"92672",
    "sg:province":"CA",
    "wof:name":"Paul Lebine & Assoc Inc",
    "wof:placetype":"venue"
},
  "geometry": {"coordinates":[-117.59926,33.444919],"type":"Point"}
}