{
  "type": "Feature",
  "properties": {
    "addr:full":"403 Stoneybrook Ct Danville CA 94506",
    "addr:housenumber":"403",
    "addr:postcode":"94506",
    "addr:street":"Stoneybrook Ct",
    "iso:country":"US",
    "sg:address":"403 Stoneybrook Ct",
    "sg:city":"Danville",
    "sg:classifiers":[
        {
            "category":"Wholesale",
            "subcategory":"Non-durable Goods",
            "type":"Manufacturing & Wholesale Goods"
        }
    ],
    "sg:phone":"+1 925 736 4566",
    "sg:postcode":"94506",
    "sg:province":"CA",
    "wof:name":"Nikssa Trading Corp",
    "wof:placetype":"venue"
},
  "geometry": {"coordinates":[-121.88865,37.802585],"type":"Point"}
}