{
  "type": "Feature",
  "properties": {
    "addr:full":"4500 Los Feliz Blvd Los Angeles CA 90027",
    "addr:housenumber":"4500",
    "addr:postcode":"90027",
    "addr:street":"Los Feliz Blvd",
    "iso:country":"US",
    "sg:address":"4500 Los Feliz Blvd",
    "sg:city":"Los Angeles",
    "sg:classifiers":[
        {
            "category":"Bars & Pubs",
            "type":"Food & Drink"
        }
    ],
    "sg:phone":"+1 323 661 6837",
    "sg:postcode":"90027",
    "sg:province":"CA",
    "sg:website":"www.the-derby.com",
    "wof:name":"Derby Club",
    "wof:placetype":"venue"
},
  "geometry": {"coordinates":[-118.28934,34.111534],"type":"Point"}
}