{
  "type": "Feature",
  "properties": {
    "addr:full":"2185 N Euclid Ave Upland CA 91784",
    "addr:housenumber":"2185",
    "addr:postcode":"91784",
    "addr:street":"N Euclid Ave",
    "iso:country":"US",
    "sg:address":"2185 N Euclid Ave",
    "sg:city":"Upland",
    "sg:classifiers":[
        {
            "category":"Building & Trades",
            "subcategory":"Construction",
            "type":"Services"
        }
    ],
    "sg:phone":"+1 909 985 3242",
    "sg:postcode":"91784",
    "sg:province":"CA",
    "sg:tags":[
        "steel",
        "erection",
        "designer",
        "swimming",
        "dealer",
        "pool",
        "structural"
    ],
    "wof:name":"Gates Rebar Co",
    "wof:placetype":"venue"
},
  "geometry": {"coordinates":[-117.651414,34.142649],"type":"Point"}
}