{
  "type": "Feature",
  "properties": {
    "iso:country":"US",
    "sg:address":"4800 J St",
    "sg:city":"Sacramento",
    "sg:classifiers":[
        {
            "category":"Shopping",
            "subcategory":"Pharmacy",
            "type":"Retail Goods"
        }
    ],
    "sg:postcode":"95857",
    "sg:province":"CA",
    "sg:tags":[
        "drugstore"
    ],
    "sg:website":"www.riteaid.com",
    "wof:name":"Rite Aid",
    "wof:placetype":"venue"
},
  "geometry": {"coordinates":[-121.44367,38.567039],"type":"Point"}
}