{
  "type": "Feature",
  "properties": {
    "iso:country":"US",
    "sg:address":"1108 Santee St",
    "sg:city":"Los Angeles",
    "sg:classifiers":[
        {
            "category":"Wholesale",
            "subcategory":"Apparel",
            "type":"Manufacturing & Wholesale Goods"
        }
    ],
    "sg:phone":"+1 213 746 8610",
    "sg:postcode":"90015",
    "sg:province":"CA",
    "sg:tags":[
        "clothing"
    ],
    "wof:name":"Designer Fashions California",
    "wof:placetype":"venue"
},
  "geometry": {"coordinates":[-118.257187,34.036367],"type":"Point"}
}