{
  "type": "Feature",
  "properties": {
    "iso:country":"US",
    "sg:address":"6791 Pentz Rd",
    "sg:city":"Paradise",
    "sg:classifiers":[
        {
            "category":"Building & Trades",
            "subcategory":"Landscaping Services",
            "type":"Services"
        }
    ],
    "sg:phone":"+1 530 877 6055",
    "sg:postcode":"95969",
    "sg:province":"CA",
    "sg:tags":[
        "tree"
    ],
    "wof:name":"Tom's Tree Svc & Certified",
    "wof:placetype":"venue"
},
  "geometry": {"coordinates":[-121.579654,39.781883],"type":"Point"}
}