{
  "type": "Feature",
  "properties": {
    "addr:full":"6205 State Street Huntington Park CA 90255",
    "addr:housenumber":"6205",
    "addr:postcode":"90255",
    "addr:street":"State Street",
    "iso:country":"US",
    "sg:address":"6205 State Street",
    "sg:city":"Huntington Park",
    "sg:classifiers":[
        {
            "category":"Personal",
            "subcategory":"Beauty Salon",
            "type":"Services"
        }
    ],
    "sg:phone":"+1 323 587 1171",
    "sg:postcode":"90255",
    "sg:province":"CA",
    "sg:tags":[
        "hair"
    ],
    "wof:name":"Marlyn Beauty Salon",
    "wof:placetype":"venue"
},
  "geometry": {"coordinates":[-118.21249,33.983277],"type":"Point"}
}