{
  "type": "Feature",
  "properties": {
    "iso:country":"US",
    "sg:address":"8121 S Figueroa St",
    "sg:city":"Los Angeles",
    "sg:classifiers":[
        {
            "category":"Retail",
            "subcategory":"Auto Repair",
            "type":"Services"
        }
    ],
    "sg:phone":"+1 323 751 9838",
    "sg:postcode":"90003",
    "sg:province":"CA",
    "wof:name":"Wichos Smog Service",
    "wof:placetype":"venue"
},
  "geometry": {"coordinates":[-118.28299699999999,33.965199],"type":"Point"}
}