{
  "type": "Feature",
  "properties": {
    "iso:country":"US",
    "sg:address":"1130 N Chinowth St",
    "sg:city":"Visalia",
    "sg:classifiers":[
        {
            "category":"Health Services",
            "subcategory":"Doctor",
            "type":"Services"
        }
    ],
    "sg:phone":"+1 559 732 7850",
    "sg:postcode":"93291",
    "sg:province":"CA",
    "sg:tags":[
        "dentist"
    ],
    "wof:name":"Kermit L Norton Inc",
    "wof:placetype":"venue"
},
  "geometry": {"coordinates":[-119.336258,36.338729],"type":"Point"}
}