{
  "type": "Feature",
  "properties": {
    "iso:country":"US",
    "sg:address":"39990 Roadrunner Ln",
    "sg:city":"Boulevard",
    "sg:classifiers":[
        {
            "category":"Food & Beverages",
            "subcategory":"Meat & Fish",
            "type":"Retail Goods"
        }
    ],
    "sg:phone":"+1 619 766 4244",
    "sg:postcode":"91905",
    "sg:province":"CA",
    "wof:name":"Brofas Smoked & Custom Meats",
    "wof:placetype":"venue"
},
  "geometry": {"coordinates":[-116.286685,32.684203],"type":"Point"}
}