{
  "type": "Feature",
  "properties": {
    "iso:country":"US",
    "sg:address":"6801 Brush Ln",
    "sg:city":"Modesto",
    "sg:classifiers":[
        {
            "category":"Freight",
            "type":"Transportation"
        }
    ],
    "sg:phone":"+1 209 538 6469",
    "sg:postcode":"95358",
    "sg:province":"CA",
    "sg:tags":[
        "trucking"
    ],
    "wof:name":"Whitehead Livestock Transport",
    "wof:placetype":"venue"
},
  "geometry": {"coordinates":[-121.107296,37.558735],"type":"Point"}
}