{
  "type": "Feature",
  "properties": {
    "addr:full":"2351 Vehicle Drive Rancho Cordova CA 95670",
    "addr:housenumber":"2351",
    "addr:postcode":"95670",
    "addr:street":"Vehicle Drive",
    "iso:country":"US",
    "sg:address":"2351 Vehicle Drive",
    "sg:city":"Rancho Cordova",
    "sg:classifiers":[
        {
            "category":"Retail",
            "subcategory":"Laundry & Dry Cleaning",
            "type":"Services"
        }
    ],
    "sg:phone":"+1 916 852 7524",
    "sg:postcode":"95670",
    "sg:province":"CA",
    "wof:name":"Ark Cleaners",
    "wof:placetype":"venue"
},
  "geometry": {"coordinates":[-121.27160600000001,38.613549],"type":"Point"}
}