{
  "type": "Feature",
  "properties": {
    "addr:full":"80 Great Oaks Blvd San Jose CA 95119",
    "addr:housenumber":"80",
    "addr:postcode":"95119",
    "addr:street":"Great Oaks Blvd",
    "iso:country":"US",
    "sg:address":"80 Great Oaks Blvd",
    "sg:city":"San Jose",
    "sg:classifiers":[
        {
            "category":"Social Services",
            "type":"Services"
        }
    ],
    "sg:phone":"+1 408 226 0550",
    "sg:postcode":"95119",
    "sg:province":"CA",
    "sg:tags":[
        "veteran",
        "for"
    ],
    "wof:name":"Social Services Agency",
    "wof:placetype":"venue"
},
  "geometry": {"coordinates":[-121.778554,37.234415],"type":"Point"}
}