{
  "type": "Feature",
  "properties": {
    "addr:full":"4436 Atlantic Avenue Long Beach CA 90807",
    "addr:housenumber":"4436",
    "addr:postcode":"90807",
    "addr:street":"Atlantic Avenue",
    "iso:country":"US",
    "sg:address":"4436 Atlantic Avenue",
    "sg:city":"Long Beach",
    "sg:classifiers":[
        {
            "category":"Banks & Credit Unions",
            "subcategory":"Bank",
            "type":"Services"
        }
    ],
    "sg:phone":"+1 562 598 9007",
    "sg:postcode":"90807",
    "sg:province":"CA",
    "sg:website":"www.lbsfcu.org",
    "wof:name":"LBS Financial Credit Union",
    "wof:placetype":"venue"
},
  "geometry": {"coordinates":[-118.184738,33.838261],"type":"Point"}
}