{
  "type": "Feature",
  "properties": {
    "addr:full":"210 S Beverly Dr Beverly Hills CA 90212",
    "addr:housenumber":"210",
    "addr:postcode":"90212",
    "addr:street":"S Beverly Dr",
    "iso:country":"US",
    "sg:address":"210 S Beverly Dr",
    "sg:city":"Beverly Hills",
    "sg:classifiers":[
        {
            "category":"Shopping",
            "subcategory":"Clothing, Apparel, & Fashions",
            "type":"Retail Goods"
        }
    ],
    "sg:phone":"+1 310 271 5454",
    "sg:postcode":"90212",
    "sg:province":"CA",
    "wof:name":"Body",
    "wof:placetype":"venue"
},
  "geometry": {"coordinates":[-118.39899699999999,34.062498],"type":"Point"}
}