{
  "type": "Feature",
  "properties": {
    "addr:full":"22708 Victory Blvd Woodland Hills CA 91367",
    "addr:housenumber":"22708",
    "addr:postcode":"91367",
    "addr:street":"Victory Blvd",
    "iso:country":"US",
    "sg:address":"22708 Victory Blvd",
    "sg:city":"Woodland Hills",
    "sg:classifiers":[
        {
            "category":"Travel",
            "subcategory":"Travel Agent",
            "type":"Entertainment"
        }
    ],
    "sg:phone":"+1 818 883 2660",
    "sg:postcode":"91367",
    "sg:province":"CA",
    "wof:name":"AAA Automobile Club of So Calif",
    "wof:placetype":"venue"
},
  "geometry": {"coordinates":[-118.621466,34.186173],"type":"Point"}
}