{
  "type": "Feature",
  "properties": {
    "iso:country":"US",
    "sg:address":"1079 Brockton Ln",
    "sg:city":"Ventura",
    "sg:classifiers":[
        {
            "category":"Building & Trades",
            "subcategory":"Landscaping Services",
            "type":"Services"
        }
    ],
    "sg:phone":"+1 805 643 6735",
    "sg:postcode":"93001",
    "sg:province":"CA",
    "sg:tags":[
        "landscape",
        "contractor"
    ],
    "wof:name":"Bordwell Stephen Landscaping",
    "wof:placetype":"venue"
},
  "geometry": {"coordinates":[-119.275048,34.267091],"type":"Point"}
}