{
  "type": "Feature",
  "properties": {
    "iso:country":"US",
    "sg:address":"4242 Campus Dr",
    "sg:city":"Irvine",
    "sg:classifiers":[
        {
            "category":"Arts & Performance",
            "subcategory":"Arts Center",
            "type":"Entertainment"
        },
        {
            "category":"Arts & Performance",
            "subcategory":"Music",
            "type":"Entertainment"
        },
        {
            "category":"Cinema",
            "subcategory":"Movie Theater",
            "type":"Entertainment"
        },
        {
            "category":"Arts & Performance",
            "subcategory":"Theater",
            "type":"Entertainment"
        }
    ],
    "sg:phone":"+1 949 854 4646",
    "sg:postcode":"92612",
    "sg:province":"CA",
    "sg:tags":[
        "opera",
        "ballet",
        "performing",
        "venue"
    ],
    "sg:website":"www.thebarclay.org/",
    "wof:name":"Irvine Barclay Theatre",
    "wof:placetype":"venue"
},
  "geometry": {"coordinates":[-117.838948,33.648633],"type":"Point"}
}