{
  "type": "Feature",
  "properties": {
    "iso:country":"US",
    "sg:address":"17412 Serene Dr",
    "sg:city":"Morgan Hill",
    "sg:classifiers":[
        {
            "category":"Real Estate",
            "subcategory":"Real Estate Agent",
            "type":"Services"
        }
    ],
    "sg:phone":"+1 408 778 1992",
    "sg:postcode":"95037",
    "sg:province":"CA",
    "sg:tags":[
        "appraiser"
    ],
    "wof:name":"Peter Bolino & Assoc",
    "wof:placetype":"venue"
},
  "geometry": {"coordinates":[-121.63966499999999,37.135404],"type":"Point"}
}