{
  "type": "Feature",
  "properties": {
    "addr:full":"1706 W 1st St Ste A Santa Ana CA 92703",
    "addr:housenumber":"1706",
    "addr:postcode":"92703",
    "addr:street":"W 1St St Ste A",
    "iso:country":"US",
    "sg:address":"1706 W 1st St Ste A",
    "sg:city":"Santa Ana",
    "sg:classifiers":[
        {
            "category":"Shopping",
            "subcategory":"Computers & Home Electronics",
            "type":"Retail Goods"
        },
        {
            "category":"Professional",
            "subcategory":"Computer Services",
            "type":"Services"
        }
    ],
    "sg:phone":"+1 714 543 0932",
    "sg:postcode":"92703",
    "sg:province":"CA",
    "sg:tags":[
        "stereo",
        "installation"
    ],
    "wof:name":"Precision Sounds",
    "wof:placetype":"venue"
},
  "geometry": {"coordinates":[-117.891998,33.745399],"type":"Point"}
}