{
  "type": "Feature",
  "properties": {
    "addr:full":"23640 Reed Way Hayward CA 94541",
    "addr:housenumber":"23640",
    "addr:postcode":"94541",
    "addr:street":"Reed Way",
    "iso:country":"US",
    "sg:address":"23640 Reed Way",
    "sg:city":"Hayward",
    "sg:classifiers":[
        {
            "category":"Education",
            "subcategory":"School",
            "type":"Public Place"
        }
    ],
    "sg:phone":"+1 510 293 8547",
    "sg:postcode":"94541",
    "sg:province":"CA",
    "wof:name":"Hayward Unified School District",
    "wof:placetype":"venue"
},
  "geometry": {"coordinates":[-122.10731800000001,37.656035],"type":"Point"}
}