{
  "type": "Feature",
  "properties": {
    "iso:country":"US",
    "sg:address":"18645 Sherman Way",
    "sg:city":"Reseda",
    "sg:classifiers":[
        {
            "category":"Professional",
            "subcategory":"Computer Services",
            "type":"Services"
        }
    ],
    "sg:phone":"+1 818 609 8900",
    "sg:postcode":"91335",
    "sg:province":"CA",
    "sg:tags":[
        "website",
        "design"
    ],
    "wof:name":"Adsol Technologies",
    "wof:placetype":"venue"
},
  "geometry": {"coordinates":[-118.540262,34.201134],"type":"Point"}
}