{
  "type": "Feature",
  "properties": {
    "addr:full":"623 Hazel St Bakersfield CA 93307",
    "addr:housenumber":"623",
    "addr:postcode":"93307",
    "addr:street":"Hazel St",
    "iso:country":"US",
    "sg:address":"623 Hazel St",
    "sg:city":"Bakersfield",
    "sg:classifiers":[
        {
            "category":"Professional",
            "subcategory":"Research",
            "type":"Services"
        }
    ],
    "sg:phone":"+1 661 637 1851",
    "sg:postcode":"93307",
    "sg:province":"CA",
    "sg:tags":[
        "foundation",
        "philanthropic"
    ],
    "wof:name":"Tinoqui-Chalola Cultural",
    "wof:placetype":"venue"
},
  "geometry": {"coordinates":[-118.96356299999999,35.362966],"type":"Point"}
}