{
  "type": "Feature",
  "properties": {
    "addr:full":"236 E Maple Ave Monrovia CA 91016",
    "addr:housenumber":"236",
    "addr:postcode":"91016",
    "addr:street":"E Maple Ave",
    "iso:country":"US",
    "sg:address":"236 E Maple Ave",
    "sg:city":"Monrovia",
    "sg:classifiers":[
        {
            "category":"Manufacturing",
            "subcategory":"Apparel",
            "type":"Manufacturing & Wholesale Goods"
        }
    ],
    "sg:phone":"+1 626 826 6901",
    "sg:postcode":"91016",
    "sg:province":"CA",
    "sg:tags":[
        "outerwear",
        "mfg"
    ],
    "wof:name":"Waboo Organic Chld Apparrel",
    "wof:placetype":"venue"
},
  "geometry": {"coordinates":[-117.997135,34.141501],"type":"Point"}
}