{
  "type": "Feature",
  "properties": {
    "addr:full":"801 N San Fernando Blvd Burbank CA 91502",
    "addr:housenumber":"801",
    "addr:postcode":"91502",
    "addr:street":"N San Fernando Blvd",
    "iso:country":"US",
    "sg:address":"801 N San Fernando Blvd",
    "sg:city":"Burbank",
    "sg:classifiers":[
        {
            "category":"Banks & Credit Unions",
            "subcategory":"Bank",
            "type":"Services"
        }
    ],
    "sg:phone":"+1 818 846 7023",
    "sg:postcode":"91502",
    "sg:province":"CA",
    "sg:website":"http://www.comerica.com",
    "wof:name":"Comerica",
    "wof:placetype":"venue"
},
  "geometry": {"coordinates":[-118.315432,34.185758],"type":"Point"}
}