{
  "type": "Feature",
  "properties": {
    "addr:full":"PO Box 136 Canoga Park CA 91305",
    "addr:housenumber":"po",
    "addr:postcode":"91305",
    "addr:street":"Box 136",
    "iso:country":"US",
    "sg:address":"PO Box 136",
    "sg:city":"Canoga Park",
    "sg:classifiers":[
        {
            "category":"Shopping",
            "subcategory":"Comic Books",
            "type":"Retail Goods"
        }
    ],
    "sg:phone":"+1 818 992 1636",
    "sg:postcode":"91305",
    "sg:province":"CA",
    "wof:name":"A Collector's Dream",
    "wof:placetype":"venue"
},
  "geometry": {"coordinates":[-118.602997,34.201],"type":"Point"}
}