{
  "type": "Feature",
  "properties": {
    "addr:full":"1700 California Street Suite 475 San Francisco CA 94109",
    "addr:housenumber":"1700",
    "addr:postcode":"94109",
    "addr:street":"California Street Suite 475",
    "iso:country":"US",
    "sg:address":"1700 California Street Suite 475",
    "sg:city":"San Francisco",
    "sg:classifiers":[
        {
            "category":"Professional",
            "subcategory":"Employment Agencies",
            "type":"Services"
        }
    ],
    "sg:phone":"+1 415 885 1534",
    "sg:postcode":"94109",
    "sg:province":"CA",
    "wof:name":"Med Staff",
    "wof:placetype":"venue"
},
  "geometry": {"coordinates":[-122.421997,37.790401],"type":"Point"}
}