{
  "type": "Feature",
  "properties": {
    "addr:full":"2300 E 7th St National City CA 91950",
    "addr:housenumber":"2300",
    "addr:postcode":"91950",
    "addr:street":"E 7Th St",
    "iso:country":"US",
    "sg:address":"2300 E 7th St",
    "sg:city":"National City",
    "sg:classifiers":[
        {
            "category":"Health Services",
            "subcategory":"Nursing And Care Facility",
            "type":"Services"
        }
    ],
    "sg:phone":"+1 619 267 8400",
    "sg:postcode":"91950",
    "sg:province":"CA",
    "sg:tags":[
        "home",
        "convalescent"
    ],
    "sg:website":"www.amicare.com",
    "wof:name":"Amicare Inc",
    "wof:placetype":"venue"
},
  "geometry": {"coordinates":[-117.082703,32.683597],"type":"Point"}
}