{
  "type": "Feature",
  "properties": {
    "iso:country":"US",
    "sg:address":"2700 Linden Rd",
    "sg:city":"West Sacramento",
    "sg:classifiers":[
        {
            "category":"Education",
            "subcategory":"Preschool",
            "type":"Public Place"
        },
        {
            "category":"Education",
            "subcategory":"School",
            "type":"Public Place"
        }
    ],
    "sg:phone":"+1 916 372 7838",
    "sg:postcode":"95691",
    "sg:province":"CA",
    "sg:tags":[
        "elementary"
    ],
    "wof:name":"Portside Montessori",
    "wof:placetype":"venue"
},
  "geometry": {"coordinates":[-121.54642800000001,38.550783],"type":"Point"}
}