{
  "type": "Feature",
  "properties": {
    "iso:country":"US",
    "sg:address":"15915 Ventura Blvd",
    "sg:city":"Encino",
    "sg:classifiers":[
        {
            "category":"Professional",
            "subcategory":"Accounting & Tax Preparation",
            "type":"Services"
        }
    ],
    "sg:phone":"+1 818 789 4417",
    "sg:postcode":"91436",
    "sg:province":"CA",
    "sg:tags":[
        "accountant"
    ],
    "sg:website":"www.stollercpa.com",
    "wof:name":"John D Stoller Inc",
    "wof:placetype":"venue"
},
  "geometry": {"coordinates":[-118.481165,34.156102],"type":"Point"}
}