{
  "type": "Feature",
  "properties": {
    "iso:country":"US",
    "sg:address":"939 S Atlantic Blvd",
    "sg:city":"Monterey Park",
    "sg:classifiers":[
        {
            "category":"Wholesale",
            "subcategory":"Non-durable Goods",
            "type":"Manufacturing & Wholesale Goods"
        }
    ],
    "sg:phone":"+1 626 576 8729",
    "sg:postcode":"91754",
    "sg:province":"CA",
    "wof:name":"Family Mutual Corp",
    "wof:placetype":"venue"
},
  "geometry": {"coordinates":[-118.138835,34.049791],"type":"Point"}
}