{
  "type": "Feature",
  "properties": {
    "addr:full":"1532 W Sunset Blvd Los Angeles CA 90026",
    "addr:housenumber":"1532",
    "addr:postcode":"90026",
    "addr:street":"W Sunset Blvd",
    "iso:country":"US",
    "sg:address":"1532 W Sunset Blvd",
    "sg:city":"Los Angeles",
    "sg:classifiers":[
        {
            "category":"Insurance",
            "subcategory":"Health Insurance",
            "type":"Services"
        }
    ],
    "sg:phone":"+1 213 975 9001",
    "sg:postcode":"90026",
    "sg:province":"CA",
    "sg:tags":[
        "market"
    ],
    "wof:name":"Estrellita Nutrician Center",
    "wof:placetype":"venue"
},
  "geometry": {"coordinates":[-118.25599699999999,34.076302],"type":"Point"}
}