{
  "type": "Feature",
  "properties": {
    "addr:full":"55 Carr Dr Moraga CA 94556",
    "addr:housenumber":"55",
    "addr:postcode":"94556",
    "addr:street":"Carr Dr",
    "iso:country":"US",
    "sg:address":"55 Carr Dr",
    "sg:city":"Moraga",
    "sg:classifiers":[
        {
            "category":"Health Services",
            "subcategory":"Doctor",
            "type":"Services"
        },
        {
            "category":"Health Services",
            "subcategory":"Hospital",
            "type":"Services"
        }
    ],
    "sg:phone":"+1 925 376 2025",
    "sg:postcode":"94556",
    "sg:province":"CA",
    "sg:tags":[
        "nursing",
        "consultant",
        "medical",
        "practice",
        "home"
    ],
    "wof:name":"A Whole Life Healing Resources",
    "wof:placetype":"venue"
},
  "geometry": {"coordinates":[-122.12224000000001,37.833126],"type":"Point"}
}