{
  "type": "Feature",
  "properties": {
    "addr:full":"1020 E Pacific Coast Hwy Long Beach CA 90806",
    "addr:housenumber":"1020",
    "addr:postcode":"90806",
    "addr:street":"E Pacific Coast Hwy",
    "iso:country":"US",
    "sg:address":"1020 E Pacific Coast Hwy",
    "sg:city":"Long Beach",
    "sg:classifiers":[
        {
            "category":"Shopping",
            "subcategory":"Pharmacy",
            "type":"Retail Goods"
        }
    ],
    "sg:phone":"+1 562 218 3181",
    "sg:postcode":"90806",
    "sg:province":"CA",
    "wof:name":"PMW Pharmacy",
    "wof:placetype":"venue"
},
  "geometry": {"coordinates":[-118.18040999999999,33.789778],"type":"Point"}
}