{
  "type": "Feature",
  "properties": {
    "iso:country":"US",
    "sg:address":"1100 Air Way",
    "sg:city":"Glendale",
    "sg:classifiers":[
        {
            "category":"Shopping",
            "subcategory":"Computers & Home Electronics",
            "type":"Retail Goods"
        }
    ],
    "sg:phone":"+1 818 409 5222",
    "sg:postcode":"91201",
    "sg:province":"CA",
    "sg:tags":[
        "television",
        "radio"
    ],
    "wof:name":"Kwhy TV 22 Ind Sp",
    "wof:placetype":"venue"
},
  "geometry": {"coordinates":[-118.289391,34.1649],"type":"Point"}
}