{
  "type": "Feature",
  "properties": {
    "iso:country":"US",
    "sg:address":"6107 N Fresno St Ste 101",
    "sg:city":"Fresno",
    "sg:classifiers":[
        {
            "category":"Health Services",
            "subcategory":"Doctor",
            "type":"Services"
        }
    ],
    "sg:phone":"+1 559 435 4433",
    "sg:postcode":"93710",
    "sg:province":"CA",
    "sg:tags":[
        "physician",
        "surgeon"
    ],
    "sg:website":"http://www.wishmd.com",
    "wof:name":"W.I.S.H Women's Imaging Specialists in Healthcare",
    "wof:placetype":"venue"
},
  "geometry": {"coordinates":[-119.781408,36.824946],"type":"Point"}
}