{
  "type": "Feature",
  "properties": {
    "addr:full":"5009 Whittier Blvd Los Angeles CA 90022",
    "addr:housenumber":"5009",
    "addr:postcode":"90022",
    "addr:street":"Whittier Blvd",
    "iso:country":"US",
    "sg:address":"5009 Whittier Blvd",
    "sg:city":"Los Angeles",
    "sg:classifiers":[
        {
            "category":"Retail",
            "subcategory":"Portrait Studio",
            "type":"Services"
        }
    ],
    "sg:phone":"+1 323 980 0883",
    "sg:postcode":"90022",
    "sg:province":"CA",
    "sg:tags":[
        "photographer"
    ],
    "wof:name":"Rigo's Photo & Video Studio",
    "wof:placetype":"venue"
},
  "geometry": {"coordinates":[-118.16126300000001,34.021314],"type":"Point"}
}