{
  "type": "Feature",
  "properties": {
    "addr:full":"5151 Franklin Ave Los Angeles CA 90027",
    "addr:housenumber":"5151",
    "addr:postcode":"90027",
    "addr:street":"Franklin Ave",
    "iso:country":"US",
    "sg:address":"5151 Franklin Ave",
    "sg:city":"Los Angeles",
    "sg:classifiers":[
        {
            "category":"Freight",
            "type":"Transportation"
        }
    ],
    "sg:phone":"+1 323 662 6456",
    "sg:postcode":"90027",
    "sg:province":"CA",
    "sg:tags":[
        "courier"
    ],
    "wof:name":"Oam Delivery Service Inc",
    "wof:placetype":"venue"
},
  "geometry": {"coordinates":[-118.301203,34.105464],"type":"Point"}
}