{
  "type": "Feature",
  "properties": {
    "addr:full":"1624 W Katella Ave Orange CA 92867",
    "addr:housenumber":"1624",
    "addr:postcode":"92867",
    "addr:street":"W Katella Ave",
    "iso:country":"US",
    "sg:address":"1624 W Katella Ave",
    "sg:city":"Orange",
    "sg:classifiers":[
        {
            "category":"Home & Garden",
            "subcategory":"Furniture",
            "type":"Retail Goods"
        }
    ],
    "sg:phone":"+1 714 289 3642",
    "sg:postcode":"92867",
    "sg:province":"CA",
    "wof:name":"Kid's Factory",
    "wof:placetype":"venue"
},
  "geometry": {"coordinates":[-117.869463,33.807314],"type":"Point"}
}