{
  "type": "Feature",
  "properties": {
    "iso:country":"US",
    "sg:address":"1155 Broadway St",
    "sg:city":"Redwood City",
    "sg:classifiers":[
        {
            "category":"Building & Trades",
            "subcategory":"Construction",
            "type":"Services"
        }
    ],
    "sg:phone":"+1 650 216 9679",
    "sg:postcode":"94063",
    "sg:province":"CA",
    "sg:tags":[
        "resurfacing",
        "laying",
        "refinishing",
        "floor"
    ],
    "wof:name":"Floortec Inc",
    "wof:placetype":"venue"
},
  "geometry": {"coordinates":[-122.211946,37.486434],"type":"Point"}
}