{
  "type": "Feature",
  "properties": {
    "addr:full":"234 S Pacific Coast Hwy Suite 202 Redondo Beach CA 90277",
    "addr:housenumber":"234",
    "addr:postcode":"90277",
    "addr:street":"S Pacific Coast Hwy Suite 202",
    "iso:country":"US",
    "sg:address":"234 S Pacific Coast Hwy Suite 202",
    "sg:city":"Redondo Beach",
    "sg:classifiers":[
        {
            "category":"Health Services",
            "subcategory":"Health Practitioner",
            "type":"Services"
        },
        {
            "category":"Health Services",
            "subcategory":"Chiropractor",
            "type":"Services"
        }
    ],
    "sg:phone":"+1 310 374 7482",
    "sg:postcode":"90277",
    "sg:province":"CA",
    "sg:tags":[
        "nutritionist"
    ],
    "wof:name":"Center For Holistic Health",
    "wof:placetype":"venue"
},
  "geometry": {"coordinates":[-118.38428399999999,33.839545],"type":"Point"}
}