{
  "type": "Feature",
  "properties": {
    "addr:full":"633 Ruberta Ave Glendale CA 91201",
    "addr:housenumber":"633",
    "addr:postcode":"91201",
    "addr:street":"Ruberta Ave",
    "iso:country":"US",
    "sg:address":"633 Ruberta Ave",
    "sg:city":"Glendale",
    "sg:classifiers":[
        {
            "category":"Wholesale",
            "subcategory":"Hardware",
            "type":"Manufacturing & Wholesale Goods"
        }
    ],
    "sg:phone":"+1 818 956 7511",
    "sg:postcode":"91201",
    "sg:province":"CA",
    "sg:tags":[
        "air",
        "parts",
        "conditioning",
        "supply"
    ],
    "wof:name":"Toro Aire",
    "wof:placetype":"venue"
},
  "geometry": {"coordinates":[-118.29276,34.163387],"type":"Point"}
}