{
  "type": "Feature",
  "properties": {
    "addr:full":"265 Magnolia Ave Larkspur CA 94939",
    "addr:housenumber":"265",
    "addr:postcode":"94939",
    "addr:street":"Magnolia Ave",
    "iso:country":"US",
    "sg:address":"265 Magnolia Ave",
    "sg:city":"Larkspur",
    "sg:classifiers":[
        {
            "category":"Real Estate",
            "subcategory":"Architect",
            "type":"Services"
        }
    ],
    "sg:phone":"+1 415 927 9500",
    "sg:postcode":"94939",
    "sg:province":"CA",
    "wof:name":"Pacific Design Group",
    "wof:placetype":"venue"
},
  "geometry": {"coordinates":[-122.536041,37.93288],"type":"Point"}
}