{
  "type": "Feature",
  "properties": {
    "addr:full":"12759 Foothill Blvd Etiwanda CA 91730",
    "addr:housenumber":"12759",
    "addr:postcode":"91730",
    "addr:street":"Foothill Blvd",
    "iso:country":"US",
    "sg:address":"12759 Foothill Blvd",
    "sg:city":"Etiwanda",
    "sg:classifiers":[
        {
            "category":"Freight",
            "type":"Transportation"
        }
    ],
    "sg:phone":"+1 909 463 6214",
    "sg:postcode":"91730",
    "sg:province":"CA",
    "sg:tags":[
        "trucking"
    ],
    "wof:name":"Steadfast Transportation",
    "wof:placetype":"venue"
},
  "geometry": {"coordinates":[-117.53,34.106244],"type":"Point"}
}