{
  "type": "Feature",
  "properties": {
    "addr:full":"1144 W 163rd St Gardena CA 90247",
    "addr:housenumber":"1144",
    "addr:postcode":"90247",
    "addr:street":"W 163Rd St",
    "iso:country":"US",
    "sg:address":"1144 W 163rd St",
    "sg:city":"Gardena",
    "sg:classifiers":[
        {
            "category":"Manufacturing",
            "subcategory":"Apparel",
            "type":"Manufacturing & Wholesale Goods"
        }
    ],
    "sg:phone":"+1 310 217 1714",
    "sg:postcode":"90247",
    "sg:province":"CA",
    "sg:tags":[
        "clothing",
        "mfg"
    ],
    "wof:name":"Blacklava",
    "wof:placetype":"venue"
},
  "geometry": {"coordinates":[-118.294875,33.883235],"type":"Point"}
}