{
  "type": "Feature",
  "properties": {
    "iso:country":"US",
    "sg:address":"18824 Soledad Canyon Rd",
    "sg:city":"Canyon Country",
    "sg:classifiers":[
        {
            "category":"Banks & Credit Unions",
            "subcategory":"Bank",
            "type":"Services"
        }
    ],
    "sg:phone":"+1 661 298 0160",
    "sg:postcode":"91351",
    "sg:province":"CA",
    "sg:tags":[
        "loan",
        "real estate"
    ],
    "wof:name":"Santa Clarita Funding Corp",
    "wof:placetype":"venue"
},
  "geometry": {"coordinates":[-118.462355,34.415759],"type":"Point"}
}