{
  "type": "Feature",
  "properties": {
    "iso:country":"US",
    "sg:address":"280 Casey Rd",
    "sg:city":"Moorpark",
    "sg:classifiers":[
        {
            "category":"Education",
            "subcategory":"School",
            "type":"Public Place"
        }
    ],
    "sg:phone":"+1 805 517 1722",
    "sg:postcode":"93021",
    "sg:province":"CA",
    "sg:website":"www.wcs.mrpk.k12.ca.us",
    "wof:name":"Walnut Canyon School",
    "wof:placetype":"venue"
},
  "geometry": {"coordinates":[-118.88530900000001,34.288403],"type":"Point"}
}