{
  "type": "Feature",
  "properties": {
    "addr:full":"456 Geary St San Francisco CA 94102",
    "addr:housenumber":"456",
    "addr:postcode":"94102",
    "addr:street":"Geary St",
    "iso:country":"US",
    "sg:address":"456 Geary St",
    "sg:city":"San Francisco",
    "sg:classifiers":[
        {
            "category":"Shopping",
            "type":"Retail Goods"
        }
    ],
    "sg:phone":"+1 415 346 7812",
    "sg:postcode":"94102",
    "sg:province":"CA",
    "sg:tags":[
        "art",
        "gallery"
    ],
    "sg:website":"www.freynorris.com",
    "wof:name":"Frey Norris Gallery",
    "wof:placetype":"venue"
},
  "geometry": {"coordinates":[-122.41080599999999,37.787049],"type":"Point"}
}