{
  "type": "Feature",
  "properties": {
    "iso:country":"US",
    "sg:address":"2215 16th Pl",
    "sg:city":"Delano",
    "sg:classifiers":[
        {
            "category":"Professional",
            "type":"Services"
        }
    ],
    "sg:phone":"+1 661 721 1458",
    "sg:postcode":"93215",
    "sg:province":"CA",
    "wof:name":"Dreamesign",
    "wof:placetype":"venue"
},
  "geometry": {"coordinates":[-119.224951,35.77671],"type":"Point"}
}