{
  "type": "Feature",
  "properties": {
    "iso:country":"US",
    "sg:address":"3030 W Olympic Blvd Ste 113",
    "sg:city":"Los Angeles",
    "sg:classifiers":[
        {
            "category":"Bakery",
            "type":"Food & Drink"
        }
    ],
    "sg:phone":"+1 213 386 4778",
    "sg:postcode":"90006",
    "sg:province":"CA",
    "wof:name":"Myoung Hwa Bakery",
    "wof:placetype":"venue"
},
  "geometry": {"coordinates":[-118.301003,34.052601],"type":"Point"}
}