{
  "type": "Feature",
  "properties": {
    "iso:country":"US",
    "sg:address":"35730 Panorama Dr",
    "sg:city":"Yucaipa",
    "sg:classifiers":[
        {
            "category":"Professional",
            "subcategory":"Engineering",
            "type":"Services"
        }
    ],
    "sg:phone":"+1 909 797 3660",
    "sg:postcode":"92399",
    "sg:province":"CA",
    "sg:tags":[
        "engineer"
    ],
    "wof:name":"Randall Engineering",
    "wof:placetype":"venue"
},
  "geometry": {"coordinates":[-117.02418900000001,34.043621],"type":"Point"}
}