{
  "type": "Feature",
  "properties": {
    "iso:country":"US",
    "sg:address":"601 Garfield Dr",
    "sg:city":"Petaluma",
    "sg:classifiers":[
        {
            "category":"Farming",
            "subcategory":"Dairy Farm",
            "type":"Manufacturing & Wholesale Goods"
        },
        {
            "category":"Farming",
            "subcategory":"Farm",
            "type":"Manufacturing & Wholesale Goods"
        }
    ],
    "sg:phone":"+1 707 773 1586",
    "sg:postcode":"94954",
    "sg:province":"CA",
    "wof:name":"Alves Dairy",
    "wof:placetype":"venue"
},
  "geometry": {"coordinates":[-122.60779599999999,38.255138],"type":"Point"}
}