{
  "type": "Feature",
  "properties": {
    "iso:country":"US",
    "sg:address":"41 E 4th Ave",
    "sg:city":"San Mateo",
    "sg:classifiers":[
        {
            "category":"Restaurant",
            "type":"Food & Drink"
        }
    ],
    "sg:menulink":"http://www.allmenus.com/ca/san-mateo/158214-california-roll/menu/",
    "sg:phone":"+1 650 348 4896",
    "sg:postcode":"94401",
    "sg:province":"CA",
    "sg:tags":[
        "sushi",
        "asian"
    ],
    "wof:name":"California Roll",
    "wof:placetype":"venue"
},
  "geometry": {"coordinates":[-122.32437,37.562806],"type":"Point"}
}