{
  "type": "Feature",
  "properties": {
    "addr:full":"2370 Grande Vista Pl Oakland CA 94601",
    "addr:housenumber":"2370",
    "addr:postcode":"94601",
    "addr:street":"Grande Vista Pl",
    "iso:country":"US",
    "sg:address":"2370 Grande Vista Pl",
    "sg:city":"Oakland",
    "sg:classifiers":[
        {
            "category":"Social Services",
            "subcategory":"Child Care",
            "type":"Services"
        }
    ],
    "sg:phone":"+1 510 534 2010",
    "sg:postcode":"94601",
    "sg:province":"CA",
    "sg:tags":[
        "center"
    ],
    "wof:name":"ICRI Oakland",
    "wof:placetype":"venue"
},
  "geometry": {"coordinates":[-122.22471899999999,37.793752],"type":"Point"}
}