{
  "type": "Feature",
  "properties": {
    "iso:country":"US",
    "sg:address":"4512 Corte Pastel",
    "sg:city":"Oceanside",
    "sg:classifiers":[
        {
            "category":"Wholesale",
            "subcategory":"Non-durable Goods",
            "type":"Manufacturing & Wholesale Goods"
        }
    ],
    "sg:phone":"+1 760 295 7603",
    "sg:postcode":"92056",
    "sg:province":"CA",
    "wof:name":"Walker Distribution",
    "wof:placetype":"venue"
},
  "geometry": {"coordinates":[-117.295339,33.221597],"type":"Point"}
}