{
  "type": "Feature",
  "properties": {
    "addr:full":"11844 Jefferson Blvd Culver City CA 90230",
    "addr:housenumber":"11844",
    "addr:postcode":"90230",
    "addr:street":"Jefferson Blvd",
    "iso:country":"US",
    "sg:address":"11844 Jefferson Blvd",
    "sg:city":"Culver City",
    "sg:classifiers":[
        {
            "category":"Building & Trades",
            "subcategory":"Construction",
            "type":"Services"
        }
    ],
    "sg:phone":"+1 310 391 3400",
    "sg:postcode":"90230",
    "sg:province":"CA",
    "sg:tags":[
        "contractor"
    ],
    "wof:name":"Sunset Glass Tinting MBL Svc",
    "wof:placetype":"venue"
},
  "geometry": {"coordinates":[-118.402659,33.985482],"type":"Point"}
}