{
  "type": "Feature",
  "properties": {
    "iso:country":"US",
    "sg:address":"3294 Royal Dr",
    "sg:city":"Cameron Park",
    "sg:classifiers":[
        {
            "category":"Health Services",
            "subcategory":"Chiropractor",
            "type":"Services"
        }
    ],
    "sg:phone":"+1 530 672 1790",
    "sg:postcode":"95682",
    "sg:province":"CA",
    "wof:name":"Sierra Chiropractic",
    "wof:placetype":"venue"
},
  "geometry": {"coordinates":[-120.980619,38.660599],"type":"Point"}
}