{
  "type": "Feature",
  "properties": {
    "addr:full":"29300 Central Ave Lake Elsinore CA 92532",
    "addr:postcode":"29300;92532",
    "addr:street":"Central Ave",
    "iso:country":"US",
    "sg:address":"29300 Central Ave",
    "sg:city":"Lake Elsinore",
    "sg:classifiers":[
        {
            "category":"Autos & Motor Vehicles",
            "subcategory":"Fuel & Gas Station",
            "type":"Retail Goods"
        }
    ],
    "sg:phone":"+1 951 674 2976",
    "sg:postcode":"92532",
    "sg:province":"CA",
    "sg:tags":[
        "oil"
    ],
    "wof:name":"Mobil Oil Corp",
    "wof:placetype":"venue"
},
  "geometry": {"coordinates":[-117.334829,33.694265],"type":"Point"}
}