{
  "type": "Feature",
  "properties": {
    "iso:country":"US",
    "sg:address":"122 Penn St",
    "sg:city":"El Segundo",
    "sg:classifiers":[
        {
            "category":"Professional",
            "subcategory":"Research",
            "type":"Services"
        }
    ],
    "sg:phone":"+1 310 414 9200",
    "sg:postcode":"90245",
    "sg:province":"CA",
    "sg:tags":[
        "development",
        "laboratory"
    ],
    "wof:name":"Skylab",
    "wof:placetype":"venue"
},
  "geometry": {"coordinates":[-118.409959,33.917539],"type":"Point"}
}