{
  "type": "Feature",
  "properties": {
    "iso:country":"US",
    "sg:address":"10289 Manchester Dr",
    "sg:city":"Truckee",
    "sg:classifiers":[
        {
            "category":"Building & Trades",
            "subcategory":"Landscaping Services",
            "type":"Services"
        }
    ],
    "sg:phone":"+1 530 587 8899",
    "sg:postcode":"96161",
    "sg:province":"CA",
    "sg:tags":[
        "landscape"
    ],
    "wof:name":"Lawerence P Stock",
    "wof:placetype":"venue"
},
  "geometry": {"coordinates":[-120.105664,39.357086],"type":"Point"}
}