{
  "type": "Feature",
  "properties": {
    "addr:full":"796 Lake Blvd Redding CA 96003",
    "addr:housenumber":"796",
    "addr:postcode":"96003",
    "addr:street":"Lake Blvd",
    "iso:country":"US",
    "sg:address":"796 Lake Blvd",
    "sg:city":"Redding",
    "sg:classifiers":[
        {
            "category":"Building & Trades",
            "subcategory":"Construction",
            "type":"Services"
        }
    ],
    "sg:phone":"+1 530 246 1283",
    "sg:postcode":"96003",
    "sg:province":"CA",
    "sg:tags":[
        "fire",
        "restoration",
        "damage"
    ],
    "wof:name":"Restoration & Construction Co",
    "wof:placetype":"venue"
},
  "geometry": {"coordinates":[-122.39410100000001,40.617241],"type":"Point"}
}