{
  "type": "Feature",
  "properties": {
    "addr:full":"824 Harbor Boulevard Sacramento CA 95814",
    "addr:housenumber":"824",
    "addr:postcode":"95814",
    "addr:street":"Harbor Boulevard",
    "iso:country":"US",
    "sg:address":"824 Harbor Boulevard",
    "sg:city":"Sacramento",
    "sg:classifiers":[
        {
            "category":"Banks & Credit Unions",
            "subcategory":"Bank",
            "type":"Services"
        }
    ],
    "sg:phone":"+1 916 372 7711",
    "sg:postcode":"95814",
    "sg:province":"CA",
    "sg:website":"www.checkmaxplus.com",
    "wof:name":"Check Max Plus",
    "wof:placetype":"venue"
},
  "geometry": {"coordinates":[-121.492394,38.57756],"type":"Point"}
}