{
  "type": "Feature",
  "properties": {
    "addr:full":"4035 Oceanside Blvd Oceanside CA 92056",
    "addr:housenumber":"4035",
    "addr:postcode":"92056",
    "addr:street":"Oceanside Blvd",
    "iso:country":"US",
    "sg:address":"4035 Oceanside Blvd",
    "sg:city":"Oceanside",
    "sg:classifiers":[
        {
            "category":"Building & Trades",
            "subcategory":"Construction",
            "type":"Services"
        }
    ],
    "sg:phone":"+1 760 758 4797",
    "sg:postcode":"92056",
    "sg:province":"CA",
    "sg:tags":[
        "carpentry",
        "contractor"
    ],
    "wof:name":"T L C Finish Carpentry",
    "wof:placetype":"venue"
},
  "geometry": {"coordinates":[-117.290644,33.205407],"type":"Point"}
}