{
  "type": "Feature",
  "properties": {
    "addr:full":"13211 Brooks Dr Baldwin Park CA 91706",
    "addr:housenumber":"13211",
    "addr:postcode":"91706",
    "addr:street":"Brooks Dr",
    "iso:country":"US",
    "sg:address":"13211 Brooks Dr",
    "sg:city":"Baldwin Park",
    "sg:classifiers":[
        {
            "category":"Professional",
            "type":"Services"
        }
    ],
    "sg:phone":"+1 626 869 0288",
    "sg:postcode":"91706",
    "sg:province":"CA",
    "wof:name":"Ilites",
    "wof:placetype":"venue"
},
  "geometry": {"coordinates":[-117.983143,34.098496],"type":"Point"}
}