{
  "type": "Feature",
  "properties": {
    "iso:country":"US",
    "sg:address":"215 Cajon St",
    "sg:city":"Redlands",
    "sg:classifiers":[
        {
            "category":"Professional",
            "subcategory":"Lawyer & Legal Services",
            "type":"Services"
        }
    ],
    "sg:phone":"+1 909 793 0818",
    "sg:postcode":"92373",
    "sg:province":"CA",
    "wof:name":"PATRICK KYLE",
    "wof:placetype":"venue"
},
  "geometry": {"coordinates":[-117.180976,34.329869],"type":"Point"}
}