{
  "type": "Feature",
  "properties": {
    "addr:full":"1116 W Collins Ave Orange CA 92867",
    "addr:housenumber":"1116",
    "addr:postcode":"92867",
    "addr:street":"W Collins Ave",
    "iso:country":"US",
    "sg:address":"1116 W Collins Ave",
    "sg:city":"Orange",
    "sg:classifiers":[
        {
            "category":"Professional",
            "subcategory":"Computer Services",
            "type":"Services"
        }
    ],
    "sg:phone":"+1 714 628 0077",
    "sg:postcode":"92867",
    "sg:province":"CA",
    "sg:tags":[
        "repair"
    ],
    "wof:name":"B L T Services",
    "wof:placetype":"venue"
},
  "geometry": {"coordinates":[-117.865121,33.802272],"type":"Point"}
}