{
  "type": "Feature",
  "properties": {
    "addr:full":"14565 Windmill Rd Victorville CA 92394",
    "addr:housenumber":"14565",
    "addr:postcode":"92394",
    "addr:street":"Windmill Rd",
    "iso:country":"US",
    "sg:address":"14565 Windmill Rd",
    "sg:city":"Victorville",
    "sg:classifiers":[
        {
            "category":"Real Estate",
            "subcategory":"Real Estate Agent",
            "type":"Services"
        }
    ],
    "sg:phone":"+1 760 245 9206",
    "sg:postcode":"92394",
    "sg:province":"CA",
    "wof:name":"Platinum Peaks Inc",
    "wof:placetype":"venue"
},
  "geometry": {"coordinates":[-117.348135,34.515699],"type":"Point"}
}