{
  "type": "Feature",
  "properties": {
    "iso:country":"US",
    "sg:address":"1234 Barger Pl",
    "sg:city":"Ramona",
    "sg:classifiers":[
        {
            "category":"Organizations",
            "subcategory":"Religious Organization",
            "type":"Services"
        }
    ],
    "sg:phone":"+1 760 789 0562",
    "sg:postcode":"92065",
    "sg:province":"CA",
    "sg:tags":[
        "church"
    ],
    "wof:name":"Grace Community Church",
    "wof:placetype":"venue"
},
  "geometry": {"coordinates":[-116.865543,33.031098],"type":"Point"}
}