{
  "type": "Feature",
  "properties": {
    "addr:full":"846 E Valley Blvd San Gabriel CA 91776",
    "addr:housenumber":"846",
    "addr:postcode":"91776",
    "addr:street":"E Valley Blvd",
    "iso:country":"US",
    "sg:address":"846 E Valley Blvd",
    "sg:city":"San Gabriel",
    "sg:classifiers":[
        {
            "category":"Home & Garden",
            "subcategory":"Home Furnishings",
            "type":"Retail Goods"
        }
    ],
    "sg:phone":"+1 626 288 1290",
    "sg:postcode":"91776",
    "sg:province":"CA",
    "sg:tags":[
        "equipment",
        "fireplace"
    ],
    "wof:name":"Fireside & Patio Ctr",
    "wof:placetype":"venue"
},
  "geometry": {"coordinates":[-118.08823700000001,34.080193],"type":"Point"}
}