{
  "type": "Feature",
  "properties": {
    "iso:country":"US",
    "sg:address":"5333 Inadale Ave",
    "sg:city":"Los Angeles",
    "sg:classifiers":[
        {
            "category":"Professional",
            "type":"Services"
        }
    ],
    "sg:phone":"+1 323 291 0386",
    "sg:postcode":"90043",
    "sg:province":"CA",
    "sg:tags":[
        "establishment"
    ],
    "wof:name":"Value It",
    "wof:placetype":"venue"
},
  "geometry": {"coordinates":[-118.348826,33.994772],"type":"Point"}
}