{
  "type": "Feature",
  "properties": {
    "addr:full":"2766 Old Sonoma Rd Napa CA 94558",
    "addr:housenumber":"2766",
    "addr:postcode":"94558",
    "addr:street":"Old Sonoma Rd",
    "iso:country":"US",
    "sg:address":"2766 Old Sonoma Rd",
    "sg:city":"Napa",
    "sg:classifiers":[
        {
            "category":"Restaurant",
            "type":"Food & Drink"
        }
    ],
    "sg:phone":"+1 707 252 6178",
    "sg:postcode":"94558",
    "sg:province":"CA",
    "wof:name":"Foothill Cafe",
    "wof:placetype":"venue"
},
  "geometry": {"coordinates":[-122.308317,38.287752],"type":"Point"}
}