{
  "type": "Feature",
  "properties": {
    "iso:country":"US",
    "sg:address":"12335 Woodside Ave",
    "sg:city":"Lakeside",
    "sg:classifiers":[
        {
            "category":"Education",
            "subcategory":"School",
            "type":"Public Place"
        }
    ],
    "sg:phone":"+1 619 390 2600",
    "sg:postcode":"92040",
    "sg:province":"CA",
    "sg:website":"www.lsschools.k12.ca.us",
    "wof:name":"Lakeside School District",
    "wof:placetype":"venue"
},
  "geometry": {"coordinates":[-116.926184,32.856645],"type":"Point"}
}