{
  "type": "Feature",
  "properties": {
    "addr:full":"1039 Silverado St La Jolla CA 92037",
    "addr:housenumber":"1039",
    "addr:postcode":"92037",
    "addr:street":"Silverado St",
    "iso:country":"US",
    "sg:address":"1039 Silverado St",
    "sg:city":"La Jolla",
    "sg:classifiers":[
        {
            "category":"Personal",
            "subcategory":"Beauty Salon",
            "type":"Services"
        }
    ],
    "sg:phone":"+1 858 551 0470",
    "sg:postcode":"92037",
    "sg:province":"CA",
    "sg:tags":[
        "hair"
    ],
    "sg:website":"standardsalon.com",
    "wof:name":"The Standard Salon",
    "wof:placetype":"venue"
},
  "geometry": {"coordinates":[-117.273484,32.845209],"type":"Point"}
}