{
  "type": "Feature",
  "properties": {
    "addr:full":"7200 State Rte 273 Anderson CA 96007",
    "addr:housenumber":"7200",
    "addr:postcode":"96007",
    "addr:street":"State Rte 273",
    "iso:country":"US",
    "sg:address":"7200 State Rte 273",
    "sg:city":"Anderson",
    "sg:classifiers":[
        {
            "category":"Food & Beverages",
            "subcategory":"Groceries & Convenience Stores",
            "type":"Retail Goods"
        }
    ],
    "sg:phone":"+1 530 246 2519",
    "sg:postcode":"96007",
    "sg:province":"CA",
    "sg:tags":[
        "grocer"
    ],
    "wof:name":"Midway Market",
    "wof:placetype":"venue"
},
  "geometry": {"coordinates":[-122.36009799999999,40.490177],"type":"Point"}
}