{
  "type": "Feature",
  "properties": {
    "iso:country":"US",
    "sg:address":"10821 Old Santa Susana Pass Rd",
    "sg:city":"Chatsworth",
    "sg:classifiers":[
        {
            "category":"Building & Trades",
            "subcategory":"Plumbing",
            "type":"Services"
        }
    ],
    "sg:phone":"+1 818 700 1233",
    "sg:postcode":"91311",
    "sg:province":"CA",
    "sg:tags":[
        "conditioning",
        "air",
        "system",
        "contractor"
    ],
    "wof:name":"Fresh Air Systems",
    "wof:placetype":"venue"
},
  "geometry": {"coordinates":[-118.60541600000001,34.271937],"type":"Point"}
}