{
  "type": "Feature",
  "properties": {
    "addr:full":"249 Eddy St San Francisco CA 94102",
    "addr:housenumber":"249",
    "addr:postcode":"94102",
    "addr:street":"Eddy St",
    "iso:country":"US",
    "sg:address":"249 Eddy St",
    "sg:city":"San Francisco",
    "sg:classifiers":[
        {
            "category":"Health Services",
            "subcategory":"Nursing And Care Facility",
            "type":"Services"
        }
    ],
    "sg:phone":"+1 415 474 6524",
    "sg:postcode":"94102",
    "sg:province":"CA",
    "sg:tags":[
        "home",
        "apartment",
        "community",
        "retirement"
    ],
    "wof:name":"Aspen Tenderloin Apts II",
    "wof:placetype":"venue"
},
  "geometry": {"coordinates":[-122.41177500000001,37.783904],"type":"Point"}
}