{
  "type": "Feature",
  "properties": {
    "addr:full":"1500 Green Hills Rd # 101 Santa Cruz CA 95066",
    "addr:housenumber":"1500",
    "addr:postcode":"95066",
    "addr:street":"Green Hills Rd # 101",
    "iso:country":"US",
    "sg:address":"1500 Green Hills Rd # 101",
    "sg:city":"Santa Cruz",
    "sg:classifiers":[
        {
            "category":"Place Of Worship",
            "subcategory":"Church",
            "type":"Public Place"
        }
    ],
    "sg:phone":"+1 831 477 7777",
    "sg:postcode":"95066",
    "sg:province":"CA",
    "sg:website":"calvarychapelsantacruz.org",
    "wof:name":"Calvary Chapel Santa Cruz",
    "wof:placetype":"venue"
},
  "geometry": {"coordinates":[-122.010175,37.048971],"type":"Point"}
}