{
  "type": "Feature",
  "properties": {
    "addr:full":"Nob Hill Shopping Center 2601 Blanding Ave. Alameda CA 94501",
    "addr:housenumber":"2601",
    "addr:postcode":"94501",
    "addr:street":"Blanding Ave.",
    "iso:country":"US",
    "sg:address":"Nob Hill Shopping Center 2601 Blanding Ave.",
    "sg:city":"Alameda",
    "sg:classifiers":[
        {
            "category":"Shopping",
            "subcategory":"Mobile Phones",
            "type":"Retail Goods"
        }
    ],
    "sg:phone":"+1 510 864 8255",
    "sg:postcode":"94501",
    "sg:province":"CA",
    "sg:website":"www.parrotatt.com",
    "wof:name":"Parrot AT&T",
    "wof:placetype":"venue"
},
  "geometry": {"coordinates":[-122.23336,37.768373],"type":"Point"}
}