{
  "type": "Feature",
  "properties": {
    "iso:country":"US",
    "sg:address":"8629 Garvey Ave",
    "sg:city":"Rosemead",
    "sg:classifiers":[
        {
            "category":"Retail",
            "subcategory":"Auto Repair",
            "type":"Services"
        }
    ],
    "sg:phone":"+1 626 573 8468",
    "sg:postcode":"91770",
    "sg:province":"CA",
    "sg:tags":[
        "glass",
        "coating",
        "tinting"
    ],
    "wof:name":"KAR Tint",
    "wof:placetype":"venue"
},
  "geometry": {"coordinates":[-118.08182600000001,34.062744],"type":"Point"}
}