{
  "type": "Feature",
  "properties": {
    "iso:country":"US",
    "sg:address":"1026 Via Prado",
    "sg:city":"Fallbrook",
    "sg:classifiers":[
        {
            "category":"Manufacturing",
            "subcategory":"Building Materials",
            "type":"Manufacturing & Wholesale Goods"
        }
    ],
    "sg:phone":"+1 760 451 0590",
    "sg:postcode":"92028",
    "sg:province":"CA",
    "sg:tags":[
        "mfg",
        "wood",
        "kitchen",
        "cabinet"
    ],
    "wof:name":"Bobs Custom Cabinets",
    "wof:placetype":"venue"
},
  "geometry": {"coordinates":[-117.224749,33.365733],"type":"Point"}
}