{
  "type": "Feature",
  "properties": {
    "addr:full":"1221 Fell St San Francisco CA 94117",
    "addr:housenumber":"1221",
    "addr:postcode":"94117",
    "addr:street":"Fell St",
    "iso:country":"US",
    "sg:address":"1221 Fell St",
    "sg:city":"San Francisco",
    "sg:classifiers":[
        {
            "category":"Shopping",
            "subcategory":"Musical Instruments",
            "type":"Retail Goods"
        }
    ],
    "sg:phone":"+1 415 522 1302",
    "sg:postcode":"94117",
    "sg:province":"CA",
    "sg:website":"www.panhandleguitar.com",
    "wof:name":"Panhandle Guitars",
    "wof:placetype":"venue"
},
  "geometry": {"coordinates":[-122.438996,37.773817],"type":"Point"}
}