{
  "type": "Feature",
  "properties": {
    "iso:country":"US",
    "sg:address":"2233 Jesse St",
    "sg:city":"Los Angeles",
    "sg:classifiers":[
        {
            "category":"Freight",
            "type":"Transportation"
        }
    ],
    "sg:phone":"+1 323 526 3623",
    "sg:postcode":"90023",
    "sg:province":"CA",
    "sg:tags":[
        "warehouse",
        "storage"
    ],
    "sg:website":"www.glaciercold.com",
    "wof:name":"GLAICER Cold Storage",
    "wof:placetype":"venue"
},
  "geometry": {"coordinates":[-118.224262,34.036798],"type":"Point"}
}