{
  "type": "Feature",
  "properties": {
    "iso:country":"US",
    "sg:address":"310 Becerra Way",
    "sg:city":"Davis",
    "sg:classifiers":[
        {
            "category":"Real Estate",
            "subcategory":"Real Estate Operator",
            "type":"Services"
        }
    ],
    "sg:phone":"+1 530 757 4439",
    "sg:postcode":"95618",
    "sg:province":"CA",
    "sg:tags":[
        "apartment"
    ],
    "wof:name":"Willow Glen Senior Duplexes",
    "wof:placetype":"venue"
},
  "geometry": {"coordinates":[-121.704522,38.548411],"type":"Point"}
}