{
  "type": "Feature",
  "properties": {
    "iso:country":"US",
    "sg:address":"3213 S Central Ave",
    "sg:city":"Los Angeles",
    "sg:classifiers":[
        {
            "category":"Professional",
            "subcategory":"Management & Consulting",
            "type":"Services"
        }
    ],
    "sg:phone":"+1 323 235 5000",
    "sg:postcode":"90011",
    "sg:province":"CA",
    "sg:tags":[
        "retail",
        "direct",
        "sales"
    ],
    "wof:name":"El Ojo De Agua",
    "wof:placetype":"venue"
},
  "geometry": {"coordinates":[-118.256587,34.013844],"type":"Point"}
}