{
  "type": "Feature",
  "properties": {
    "iso:country":"US",
    "sg:address":"230 W Portal Ave",
    "sg:city":"San Francisco",
    "sg:classifiers":[
        {
            "category":"Bars & Pubs",
            "subcategory":"Wine Bar",
            "type":"Food & Drink"
        }
    ],
    "sg:phone":"+1 415 731 7000",
    "sg:postcode":"94127",
    "sg:province":"CA",
    "sg:website":"www.quesyrahsf.com",
    "wof:name":"Que Syrah",
    "wof:placetype":"venue"
},
  "geometry": {"coordinates":[-122.46855100000001,37.738636],"type":"Point"}
}