{
  "type": "Feature",
  "properties": {
    "iso:country":"US",
    "sg:address":"3842 Cerritos Ave",
    "sg:city":"Los Alamitos",
    "sg:classifiers":[
        {
            "category":"Shopping",
            "subcategory":"Thrift Store",
            "type":"Retail Goods"
        }
    ],
    "sg:phone":"+1 562 431 0880",
    "sg:postcode":"90720",
    "sg:province":"CA",
    "wof:name":"Grateful Hearts Store House",
    "wof:placetype":"venue"
},
  "geometry": {"coordinates":[-118.066002,33.810299],"type":"Point"}
}