{
  "type": "Feature",
  "properties": {
    "iso:country":"US",
    "sg:address":"411 Palm Dr",
    "sg:city":"Glendale",
    "sg:classifiers":[
        {
            "category":"Real Estate",
            "subcategory":"Real Estate Operator",
            "type":"Services"
        }
    ],
    "sg:phone":"+1 818 543 7382",
    "sg:postcode":"91202",
    "sg:province":"CA",
    "sg:tags":[
        "apartment"
    ],
    "wof:name":"Norhadian Arman",
    "wof:placetype":"venue"
},
  "geometry": {"coordinates":[-118.262373,34.162272],"type":"Point"}
}