{
  "type": "Feature",
  "properties": {
    "addr:full":"1810 S Central St Visalia CA 93277",
    "addr:housenumber":"1810",
    "addr:postcode":"93277",
    "addr:street":"S Central St",
    "iso:country":"US",
    "sg:address":"1810 S Central St",
    "sg:city":"Visalia",
    "sg:classifiers":[
        {
            "category":"Banks & Credit Unions",
            "subcategory":"Bank",
            "type":"Services"
        }
    ],
    "sg:phone":"+1 559 636 8611",
    "sg:postcode":"93277",
    "sg:province":"CA",
    "sg:tags":[
        "loan",
        "real estate"
    ],
    "wof:name":"Mission Hills Mortgage",
    "wof:placetype":"venue"
},
  "geometry": {"coordinates":[-119.311978,36.313063],"type":"Point"}
}