{
  "type": "Feature",
  "properties": {
    "iso:country":"US",
    "sg:address":"80 S Main St",
    "sg:city":"Templeton",
    "sg:classifiers":[
        {
            "category":"Retail",
            "subcategory":"Veterinary Services",
            "type":"Services"
        }
    ],
    "sg:phone":"+1 805 434 2002",
    "sg:postcode":"93465",
    "sg:province":"CA",
    "wof:name":"Blake Daniel A Dvm",
    "wof:placetype":"venue"
},
  "geometry": {"coordinates":[-120.702437,35.55264],"type":"Point"}
}