{
  "type": "Feature",
  "properties": {
    "iso:country":"US",
    "sg:address":"69459 Heritage Ct",
    "sg:city":"Cathedral City",
    "sg:classifiers":[
        {
            "category":"Wholesale",
            "subcategory":"Groceries",
            "type":"Manufacturing & Wholesale Goods"
        }
    ],
    "sg:phone":"+1 760 321 7174",
    "sg:postcode":"92234",
    "sg:province":"CA",
    "sg:tags":[
        "confectionery"
    ],
    "wof:name":"Tk Dist Terprises",
    "wof:placetype":"venue"
},
  "geometry": {"coordinates":[-116.450602,33.826094],"type":"Point"}
}