{
  "type": "Feature",
  "properties": {
    "iso:country":"US",
    "sg:address":"1240 Montreal Dr",
    "sg:city":"Lake Arrowhead",
    "sg:classifiers":[
        {
            "category":"Freight",
            "type":"Transportation"
        }
    ],
    "sg:phone":"+1 909 336 3391",
    "sg:postcode":"92352",
    "sg:province":"CA",
    "sg:tags":[
        "line"
    ],
    "wof:name":"Transport Related Svc",
    "wof:placetype":"venue"
},
  "geometry": {"coordinates":[-117.18216,34.272408],"type":"Point"}
}