{
  "type": "Feature",
  "properties": {
    "addr:full":"345 W 5th St Long Beach CA 90802",
    "addr:housenumber":"345",
    "addr:postcode":"90802",
    "addr:street":"W 5Th St",
    "iso:country":"US",
    "sg:address":"345 W 5th St",
    "sg:city":"Long Beach",
    "sg:classifiers":[
        {
            "category":"Building & Trades",
            "subcategory":"Landscaping Services",
            "type":"Services"
        }
    ],
    "sg:phone":"+1 562 436 0785",
    "sg:postcode":"90802",
    "sg:province":"CA",
    "sg:tags":[
        "gardener"
    ],
    "wof:name":"C R Landscaping",
    "wof:placetype":"venue"
},
  "geometry": {"coordinates":[-118.195999,33.7728],"type":"Point"}
}