{
  "type": "Feature",
  "properties": {
    "addr:full":"549 Main St Pleasanton CA 94566",
    "addr:housenumber":"549",
    "addr:postcode":"94566",
    "addr:street":"Main St",
    "iso:country":"US",
    "sg:address":"549 Main St",
    "sg:city":"Pleasanton",
    "sg:classifiers":[
        {
            "category":"Shopping",
            "subcategory":"Clothing, Apparel, & Fashions",
            "type":"Retail Goods"
        }
    ],
    "sg:phone":"+1 925 600 9670",
    "sg:postcode":"94566",
    "sg:province":"CA",
    "sg:tags":[
        "designer"
    ],
    "wof:name":"Me N Emmi's",
    "wof:placetype":"venue"
},
  "geometry": {"coordinates":[-121.87567900000001,37.660964],"type":"Point"}
}