{
  "type": "Feature",
  "properties": {
    "addr:full":"6700 Pacific Blvd Huntington Park CA 90255",
    "addr:housenumber":"6700",
    "addr:postcode":"90255",
    "addr:street":"Pacific Blvd;Park",
    "iso:country":"US",
    "sg:address":"6700 Pacific Blvd",
    "sg:city":"Huntington Park",
    "sg:classifiers":[
        {
            "category":"Manufacturing",
            "subcategory":"Apparel",
            "type":"Manufacturing & Wholesale Goods"
        }
    ],
    "sg:phone":"+1 323 771 8266",
    "sg:postcode":"90255",
    "sg:province":"CA",
    "sg:tags":[
        "clothing"
    ],
    "wof:name":"Saab & Sons Clothing Inc",
    "wof:placetype":"venue"
},
  "geometry": {"coordinates":[-118.22510200000001,33.9777],"type":"Point"}
}