{
  "type": "Feature",
  "properties": {
    "addr:full":"7627 Bierstan St Citrus Heights CA 95621",
    "addr:housenumber":"7627",
    "addr:postcode":"95621",
    "addr:street":"Bierstan St",
    "iso:country":"US",
    "sg:address":"7627 Bierstan St",
    "sg:city":"Citrus Heights",
    "sg:classifiers":[
        {
            "category":"Building & Trades",
            "subcategory":"Construction",
            "type":"Services"
        }
    ],
    "sg:phone":"+1 916 721 9371",
    "sg:postcode":"95621",
    "sg:province":"CA",
    "sg:tags":[
        "material",
        "contractor"
    ],
    "wof:name":"Terrys Plaster",
    "wof:placetype":"venue"
},
  "geometry": {"coordinates":[-121.319197,38.703724],"type":"Point"}
}