{
  "type": "Feature",
  "properties": {
    "iso:country":"US",
    "sg:address":"2442 Eureka Way",
    "sg:city":"Redding",
    "sg:classifiers":[
        {
            "category":"Personal",
            "subcategory":"Beauty Salon",
            "type":"Services"
        }
    ],
    "sg:phone":"+1 530 244 6228",
    "sg:postcode":"96001",
    "sg:province":"CA",
    "wof:name":"Notorious For Hair",
    "wof:placetype":"venue"
},
  "geometry": {"coordinates":[-122.40758,40.586348],"type":"Point"}
}