{
  "type": "Feature",
  "properties": {
    "iso:country":"US",
    "sg:address":"579 Coleman Ave",
    "sg:city":"San Jose",
    "sg:classifiers":[
        {
            "category":"Fast Food",
            "type":"Food & Drink"
        },
        {
            "category":"Restaurant",
            "type":"Food & Drink"
        }
    ],
    "sg:phone":"+1 408 920 7772",
    "sg:postcode":"95110",
    "sg:province":"CA",
    "sg:tags":[
        "hawaiian"
    ],
    "sg:website":"www.hawaiianbarbecue.com",
    "wof:name":"L&L Hawaiian Barbecue",
    "wof:placetype":"venue"
},
  "geometry": {"coordinates":[-121.906998,37.340698],"type":"Point"}
}