{
  "type": "Feature",
  "properties": {
    "addr:full":"1013 Pardee Street Berkeley CA 94710",
    "addr:housenumber":"1013",
    "addr:postcode":"94710",
    "addr:street":"Pardee Street",
    "iso:country":"US",
    "sg:address":"1013 Pardee Street",
    "sg:city":"Berkeley",
    "sg:classifiers":[
        {
            "category":"Professional",
            "subcategory":"Computer Services",
            "type":"Services"
        }
    ],
    "sg:phone":"+1 510 548 4433",
    "sg:postcode":"94710",
    "sg:province":"CA",
    "sg:tags":[
        "repair"
    ],
    "sg:website":"www.manouch.com",
    "wof:name":"Manouch Computer Consulting & Services",
    "wof:placetype":"venue"
},
  "geometry": {"coordinates":[-122.290001,37.8568],"type":"Point"}
}