{
  "type": "Feature",
  "properties": {
    "addr:full":"124 Lomita Ave Vacaville CA 95688",
    "addr:housenumber":"124",
    "addr:postcode":"95688",
    "addr:street":"Lomita Ave",
    "iso:country":"US",
    "sg:address":"124 Lomita Ave",
    "sg:city":"Vacaville",
    "sg:classifiers":[
        {
            "category":"Shopping",
            "subcategory":"Computers & Home Electronics",
            "type":"Retail Goods"
        }
    ],
    "sg:phone":"+1 707 447 6035",
    "sg:postcode":"95688",
    "sg:province":"CA",
    "wof:name":"F A Beaker Climbing",
    "wof:placetype":"venue"
},
  "geometry": {"coordinates":[-121.982854,38.369286],"type":"Point"}
}