{
  "type": "Feature",
  "properties": {
    "iso:country":"US",
    "sg:address":"1042 Country Club Dr 1B",
    "sg:city":"Moraga",
    "sg:classifiers":[
        {
            "category":"Travel",
            "subcategory":"Travel Agent",
            "type":"Entertainment"
        },
        {
            "category":"Landmark",
            "subcategory":"Tourist Information",
            "type":"Public Place"
        }
    ],
    "sg:phone":"+1 925 631 1111",
    "sg:postcode":"94556",
    "sg:province":"CA",
    "sg:tags":[
        "agency",
        "promoter",
        "tours-operators"
    ],
    "wof:name":"Mckenzie Tours",
    "wof:placetype":"venue"
},
  "geometry": {"coordinates":[-122.127044,37.83225],"type":"Point"}
}