{
  "type": "Feature",
  "properties": {
    "addr:full":"8618 Sewanee Ct Sun Valley CA 91352",
    "addr:housenumber":"8618",
    "addr:postcode":"91352",
    "addr:street":"Sewanee Ct",
    "iso:country":"US",
    "sg:address":"8618 Sewanee Ct",
    "sg:city":"Sun Valley",
    "sg:classifiers":[
        {
            "category":"Building & Trades",
            "subcategory":"Plumbing",
            "type":"Services"
        }
    ],
    "sg:phone":"+1 818 767 4637",
    "sg:postcode":"91352",
    "sg:province":"CA",
    "sg:tags":[
        "contractor"
    ],
    "wof:name":"Nickels Plumbing",
    "wof:placetype":"venue"
},
  "geometry": {"coordinates":[-118.36124,34.226975],"type":"Point"}
}