{
  "type": "Feature",
  "properties": {
    "iso:country":"US",
    "sg:address":"424 E 25th St",
    "sg:city":"Los Angeles",
    "sg:classifiers":[
        {
            "category":"Building & Trades",
            "subcategory":"Construction",
            "type":"Services"
        }
    ],
    "sg:phone":"+1 213 765 0260",
    "sg:postcode":"90011",
    "sg:province":"CA",
    "sg:tags":[
        "contractor"
    ],
    "wof:name":"Zepeda Roofing",
    "wof:placetype":"venue"
},
  "geometry": {"coordinates":[-118.264023,34.02402],"type":"Point"}
}