{
  "type": "Feature",
  "properties": {
    "addr:full":"5459 Mary Jo Way San Jose CA 95124",
    "addr:housenumber":"5459",
    "addr:postcode":"95124",
    "addr:street":"Mary Jo Way",
    "iso:country":"US",
    "sg:address":"5459 Mary Jo Way",
    "sg:city":"San Jose",
    "sg:classifiers":[
        {
            "category":"Building & Trades",
            "subcategory":"Construction",
            "type":"Services"
        }
    ],
    "sg:phone":"+1 408 219 5502",
    "sg:postcode":"95124",
    "sg:province":"CA",
    "sg:tags":[
        "concrete",
        "contractor"
    ],
    "wof:name":"Richard Souza Concrete",
    "wof:placetype":"venue"
},
  "geometry": {"coordinates":[-121.91768999999999,37.23993],"type":"Point"}
}