{
  "type": "Feature",
  "properties": {
    "iso:country":"US",
    "sg:address":"1037 W 9th St",
    "sg:city":"Upland",
    "sg:classifiers":[
        {
            "category":"Wholesale",
            "subcategory":"Electrical",
            "type":"Manufacturing & Wholesale Goods"
        },
        {
            "category":"Shopping",
            "subcategory":"Computers & Home Electronics",
            "type":"Retail Goods"
        }
    ],
    "sg:phone":"+1 909 982 9806",
    "sg:postcode":"91786",
    "sg:province":"CA",
    "sg:tags":[
        "equipment",
        "consumer",
        "electric",
        "supply"
    ],
    "wof:name":"New Bedford Panoramex",
    "wof:placetype":"venue"
},
  "geometry": {"coordinates":[-117.666061,34.096032],"type":"Point"}
}