{
  "type": "Feature",
  "properties": {
    "iso:country":"US",
    "sg:address":"9445 Red Spruce Way",
    "sg:city":"Elk Grove",
    "sg:classifiers":[
        {
            "category":"Building & Trades",
            "subcategory":"Landscaping Services",
            "type":"Services"
        }
    ],
    "sg:phone":"+1 916 837 4259",
    "sg:postcode":"95624",
    "sg:province":"CA",
    "sg:tags":[
        "lawn",
        "maintenance",
        "grounds"
    ],
    "wof:name":"Martinez Gardening & Mntnc",
    "wof:placetype":"venue"
},
  "geometry": {"coordinates":[-121.347827,38.404557],"type":"Point"}
}