{
  "type": "Feature",
  "properties": {
    "addr:full":"942 Hamner Ave Norco CA 92860",
    "addr:housenumber":"942",
    "addr:postcode":"92860",
    "addr:street":"Hamner Ave",
    "iso:country":"US",
    "sg:address":"942 Hamner Ave",
    "sg:city":"Norco",
    "sg:classifiers":[
        {
            "category":"Retail",
            "subcategory":"Auto Repair",
            "type":"Services"
        }
    ],
    "sg:phone":"+1 951 371 4374",
    "sg:postcode":"92860",
    "sg:province":"CA",
    "sg:tags":[
        "repairing",
        "automobile"
    ],
    "wof:name":"M C Auto Repair",
    "wof:placetype":"venue"
},
  "geometry": {"coordinates":[-117.563108,33.897011],"type":"Point"}
}