{
  "type": "Feature",
  "properties": {
    "addr:full":"20410 Town Center Lane Cupertino CA 95014",
    "addr:housenumber":"20410",
    "addr:postcode":"95014",
    "addr:street":"Town Center Lane",
    "iso:country":"US",
    "sg:address":"20410 Town Center Lane",
    "sg:city":"Cupertino",
    "sg:classifiers":[
        {
            "category":"Health Services",
            "subcategory":"Health Practitioner",
            "type":"Services"
        }
    ],
    "sg:phone":"+1 408 873 1273",
    "sg:postcode":"95014",
    "sg:province":"CA",
    "sg:tags":[
        "acupuncture"
    ],
    "wof:name":"Yao Robert Acupuncture & Herb Clinic",
    "wof:placetype":"venue"
},
  "geometry": {"coordinates":[-122.03087499999999,37.318367],"type":"Point"}
}