{
  "type": "Feature",
  "properties": {
    "addr:full":"4112 Market St San Diego CA 92102",
    "addr:housenumber":"4112",
    "addr:postcode":"92102",
    "addr:street":"Market St",
    "iso:country":"US",
    "sg:address":"4112 Market St",
    "sg:city":"San Diego",
    "sg:classifiers":[
        {
            "category":"Manufacturing",
            "subcategory":"Printing",
            "type":"Manufacturing & Wholesale Goods"
        }
    ],
    "sg:phone":"+1 619 262 6986",
    "sg:postcode":"92102",
    "sg:province":"CA",
    "sg:tags":[
        "lithographic",
        "commercial"
    ],
    "wof:name":"Printing Emporium",
    "wof:placetype":"venue"
},
  "geometry": {"coordinates":[-117.105835,32.711561],"type":"Point"}
}