{
  "type": "Feature",
  "properties": {
    "addr:full":"3287 Silver Ridge Ct Oceanside CA 92058",
    "addr:housenumber":"3287",
    "addr:postcode":"92058",
    "addr:street":"Silver Ridge Ct",
    "iso:country":"US",
    "sg:address":"3287 Silver Ridge Ct",
    "sg:city":"Oceanside",
    "sg:classifiers":[
        {
            "category":"Building & Trades",
            "subcategory":"Construction",
            "type":"Services"
        }
    ],
    "sg:phone":"+1 760 722 0815",
    "sg:postcode":"92058",
    "sg:province":"CA",
    "sg:tags":[
        "hanging",
        "contractor"
    ],
    "wof:name":"Adajj Pro Painting",
    "wof:placetype":"venue"
},
  "geometry": {"coordinates":[-117.351823,33.229524],"type":"Point"}
}