{
  "type": "Feature",
  "properties": {
    "iso:country":"US",
    "sg:address":"892 St. Elizabeth Dr.",
    "sg:city":"San Jose",
    "sg:classifiers":[
        {
            "category":"Building & Trades",
            "subcategory":"Construction",
            "type":"Services"
        }
    ],
    "sg:phone":"+1 408 499 3798",
    "sg:postcode":"95126",
    "sg:province":"CA",
    "sg:tags":[
        "contractor"
    ],
    "sg:website":"www.rodmorenotileandstone.com",
    "wof:name":"Rod Moreno Tile and Stone",
    "wof:placetype":"venue"
},
  "geometry": {"coordinates":[-121.91582200000001,37.308255],"type":"Point"}
}