{
  "type": "Feature",
  "properties": {
    "addr:full":"514 K St Eureka CA 95501",
    "addr:housenumber":"514",
    "addr:postcode":"95501",
    "addr:street":"K St",
    "iso:country":"US",
    "sg:address":"514 K St",
    "sg:city":"Eureka",
    "sg:classifiers":[
        {
            "category":"Insurance",
            "subcategory":"Insurance Agent",
            "type":"Services"
        }
    ],
    "sg:phone":"+1 707 443 1648",
    "sg:postcode":"95501",
    "sg:province":"CA",
    "wof:name":"Vickers Insurance",
    "wof:placetype":"venue"
},
  "geometry": {"coordinates":[-124.1605,40.802533],"type":"Point"}
}