{
  "type": "Feature",
  "properties": {
    "iso:country":"US",
    "sg:address":"580 Wilshire Dr",
    "sg:city":"Redding",
    "sg:classifiers":[
        {
            "category":"Real Estate",
            "subcategory":"Real Estate Operator",
            "type":"Services"
        }
    ],
    "sg:phone":"+1 530 222 0532",
    "sg:postcode":"96002",
    "sg:province":"CA",
    "sg:tags":[
        "apartment"
    ],
    "wof:name":"Wilshire Place Apartments",
    "wof:placetype":"venue"
},
  "geometry": {"coordinates":[-122.361487,40.561874],"type":"Point"}
}