{
  "type": "Feature",
  "properties": {
    "iso:country":"US",
    "sg:address":"6800 Owensmouth Ave",
    "sg:city":"Canoga Park",
    "sg:classifiers":[
        {
            "category":"Restaurant",
            "type":"Food & Drink"
        }
    ],
    "sg:phone":"+1 818 340 1201",
    "sg:postcode":"91303",
    "sg:province":"CA",
    "wof:name":"Our Place Cafe",
    "wof:placetype":"venue"
},
  "geometry": {"coordinates":[-118.601997,34.193802],"type":"Point"}
}