{
  "type": "Feature",
  "properties": {
    "addr:full":"25140 Meredith Ct Hayward CA 94545",
    "addr:housenumber":"25140",
    "addr:postcode":"94545",
    "addr:street":"Meredith Ct",
    "iso:country":"US",
    "sg:address":"25140 Meredith Ct",
    "sg:city":"Hayward",
    "sg:classifiers":[
        {
            "category":"Manufacturing",
            "subcategory":"Printing",
            "type":"Manufacturing & Wholesale Goods"
        }
    ],
    "sg:phone":"+1 510 772 8991",
    "sg:postcode":"94545",
    "sg:province":"CA",
    "sg:tags":[
        "publisher",
        "software"
    ],
    "wof:name":"Conolay Consulting",
    "wof:placetype":"venue"
},
  "geometry": {"coordinates":[-122.100942,37.644656],"type":"Point"}
}