{
  "type": "Feature",
  "properties": {
    "addr:full":"7420 Broadway Lemon Grove CA 91945",
    "addr:housenumber":"7420",
    "addr:postcode":"91945",
    "addr:street":"Broadway",
    "iso:country":"US",
    "sg:address":"7420 Broadway",
    "sg:city":"Lemon Grove",
    "sg:classifiers":[
        {
            "category":"Food & Beverages",
            "subcategory":"Groceries & Convenience Stores",
            "type":"Retail Goods"
        }
    ],
    "sg:phone":"+1 619 463 4774",
    "sg:postcode":"91945",
    "sg:province":"CA",
    "wof:name":"Food 4 Less",
    "wof:placetype":"venue"
},
  "geometry": {"coordinates":[-117.03760800000001,32.742694],"type":"Point"}
}