{
  "type": "Feature",
  "properties": {
    "iso:country":"US",
    "sg:address":"2525 Monument Blvd",
    "sg:city":"Concord",
    "sg:classifiers":[
        {
            "category":"Retail",
            "subcategory":"Auto Repair",
            "type":"Services"
        }
    ],
    "sg:phone":"+1 925 687 6062",
    "sg:postcode":"94520",
    "sg:province":"CA",
    "sg:tags":[
        "muffler",
        "exhaust",
        "system"
    ],
    "wof:name":"Midas Auto Svc Experts",
    "wof:placetype":"venue"
},
  "geometry": {"coordinates":[-122.033317,37.960389],"type":"Point"}
}