{
  "type": "Feature",
  "properties": {
    "iso:country":"US",
    "sg:address":"3911 E Balch Ave",
    "sg:city":"Fresno",
    "sg:classifiers":[
        {
            "category":"Building & Trades",
            "subcategory":"Construction",
            "type":"Services"
        }
    ],
    "sg:phone":"+1 559 252 2413",
    "sg:postcode":"93702",
    "sg:province":"CA",
    "sg:tags":[
        "contractor"
    ],
    "wof:name":"J R Construction",
    "wof:placetype":"venue"
},
  "geometry": {"coordinates":[-119.75795599999999,36.738163],"type":"Point"}
}