{
  "type": "Feature",
  "properties": {
    "iso:country":"US",
    "sg:address":"2410 W 6th St",
    "sg:city":"Los Angeles",
    "sg:classifiers":[
        {
            "category":"Personal",
            "subcategory":"Barber",
            "type":"Services"
        }
    ],
    "sg:phone":"+1 213 380 0582",
    "sg:postcode":"90057",
    "sg:province":"CA",
    "wof:name":"Barber Shop & Beauty Salon Aguilar",
    "wof:placetype":"venue"
},
  "geometry": {"coordinates":[-118.27800000000001,34.0611],"type":"Point"}
}