{
  "type": "Feature",
  "properties": {
    "addr:full":"884 Eastlake Pkwy #1622 Chula Vista CA 91913",
    "addr:housenumber":"884",
    "addr:postcode":"91913",
    "addr:street":"Eastlake Pkwy # 1622",
    "iso:country":"US",
    "sg:address":"884 Eastlake Pkwy #1622",
    "sg:city":"Chula Vista",
    "sg:classifiers":[
        {
            "category":"Personal",
            "subcategory":"Beauty Salon",
            "type":"Services"
        }
    ],
    "sg:phone":"+1 619 651 8375",
    "sg:postcode":"91913",
    "sg:province":"CA",
    "sg:tags":[
        "spa"
    ],
    "wof:name":"Happy Nails",
    "wof:placetype":"venue"
},
  "geometry": {"coordinates":[-116.968474,32.65242],"type":"Point"}
}