{
  "type": "Feature",
  "properties": {
    "iso:country":"US",
    "sg:address":"400 E 12th St",
    "sg:city":"Los Angeles",
    "sg:classifiers":[
        {
            "category":"Shopping",
            "subcategory":"Clothing, Apparel, & Fashions",
            "type":"Retail Goods"
        }
    ],
    "sg:phone":"+1 213 748 9849",
    "sg:postcode":"90015",
    "sg:province":"CA",
    "sg:tags":[
        "clothing",
        "women's"
    ],
    "wof:name":"Jasmine",
    "wof:placetype":"venue"
},
  "geometry": {"coordinates":[-118.25599699999999,34.0355],"type":"Point"}
}