{
  "type": "Feature",
  "properties": {
    "iso:country":"US",
    "sg:address":"41615 Regan Way",
    "sg:city":"Murrieta",
    "sg:classifiers":[
        {
            "category":"Building & Trades",
            "subcategory":"Construction",
            "type":"Services"
        }
    ],
    "sg:phone":"+1 951 461 4843",
    "sg:postcode":"92562",
    "sg:province":"CA",
    "sg:tags":[
        "tile",
        "dealer"
    ],
    "wof:name":"Califorina Tile Setters",
    "wof:placetype":"venue"
},
  "geometry": {"coordinates":[-117.17573400000001,33.526731],"type":"Point"}
}