{
  "type": "Feature",
  "properties": {
    "iso:country":"US",
    "sg:address":"1303 W Oleander Ave",
    "sg:city":"Perris",
    "sg:phone":"+1 951 780 4879",
    "sg:postcode":"92571",
    "sg:province":"CA",
    "sg:website":"http://www.mesafenceco.com",
    "wof:name":"Mesa Fence Co., Inc",
    "wof:placetype":"venue"
},
  "geometry": {"coordinates":[-117.24184700000001,33.866439],"type":"Point"}
}