{
  "type": "Feature",
  "properties": {
    "addr:full":"310 E Bradley Ave Ofc El Cajon CA 92021",
    "addr:housenumber":"310",
    "addr:postcode":"92021",
    "addr:street":"E Bradley Ave",
    "iso:country":"US",
    "sg:address":"310 E Bradley Ave Ofc",
    "sg:city":"El Cajon",
    "sg:classifiers":[
        {
            "category":"Real Estate",
            "subcategory":"Real Estate Operator",
            "type":"Services"
        }
    ],
    "sg:phone":"+1 619 562 3792",
    "sg:postcode":"92021",
    "sg:province":"CA",
    "sg:tags":[
        "apartment"
    ],
    "wof:name":"Bradley Arms Apartments",
    "wof:placetype":"venue"
},
  "geometry": {"coordinates":[-116.95700100000001,32.819099],"type":"Point"}
}