{
  "type": "Feature",
  "properties": {
    "addr:full":"2880 Tunnel St Placerville CA 95667",
    "addr:housenumber":"2880",
    "addr:postcode":"95667",
    "addr:street":"Tunnel St",
    "iso:country":"US",
    "sg:address":"2880 Tunnel St",
    "sg:city":"Placerville",
    "sg:classifiers":[
        {
            "category":"Real Estate",
            "subcategory":"Real Estate Operator",
            "type":"Services"
        }
    ],
    "sg:phone":"+1 530 626 6951",
    "sg:postcode":"95667",
    "sg:province":"CA",
    "sg:tags":[
        "apartment"
    ],
    "wof:name":"Tunnel Street Senior Ctr",
    "wof:placetype":"venue"
},
  "geometry": {"coordinates":[-120.803347,38.733507],"type":"Point"}
}