{
  "type": "Feature",
  "properties": {
    "addr:full":"25 Richmond Rd San Anselmo CA 94960",
    "addr:housenumber":"25",
    "addr:postcode":"94960",
    "addr:street":"Richmond Rd",
    "iso:country":"US",
    "sg:address":"25 Richmond Rd",
    "sg:city":"San Anselmo",
    "sg:classifiers":[
        {
            "category":"Professional",
            "type":"Services"
        }
    ],
    "sg:phone":"+1 415 259 0813",
    "sg:postcode":"94960",
    "sg:province":"CA",
    "wof:name":"Jonathan Wraith",
    "wof:placetype":"venue"
},
  "geometry": {"coordinates":[-122.56415,37.97056],"type":"Point"}
}