{
  "type": "Feature",
  "properties": {
    "addr:full":"9388 Mira Mesa Blvd San Diego CA 92126",
    "addr:housenumber":"9388",
    "addr:postcode":"92126",
    "addr:street":"Mira Mesa Blvd",
    "iso:country":"US",
    "sg:address":"9388 Mira Mesa Blvd",
    "sg:city":"San Diego",
    "sg:classifiers":[
        {
            "category":"Personal",
            "subcategory":"Barber",
            "type":"Services"
        }
    ],
    "sg:phone":"+1 858 271 8121",
    "sg:postcode":"92126",
    "sg:province":"CA",
    "wof:name":"Mira Mesa Hair Fashions",
    "wof:placetype":"venue"
},
  "geometry": {"coordinates":[-117.121779,32.917267],"type":"Point"}
}