{
  "type": "Feature",
  "properties": {
    "iso:country":"US",
    "sg:address":"4827 Live Oak St",
    "sg:city":"Bell",
    "sg:classifiers":[
        {
            "category":"Professional",
            "type":"Services"
        }
    ],
    "sg:phone":"+1 323 773 4486",
    "sg:postcode":"90201",
    "sg:province":"CA",
    "wof:name":"Thelma Habet Co",
    "wof:placetype":"venue"
},
  "geometry": {"coordinates":[-118.18152000000001,33.967394],"type":"Point"}
}