{
  "type": "Feature",
  "properties": {
    "addr:full":"5212 Colfax Ave North Hollywood CA 91601",
    "addr:housenumber":"5212",
    "addr:postcode":"91601",
    "addr:street":"Colfax Ave",
    "iso:country":"US",
    "sg:address":"5212 Colfax Ave",
    "sg:city":"North Hollywood",
    "sg:classifiers":[
        {
            "category":"Home & Garden",
            "subcategory":"Home Furnishings",
            "type":"Retail Goods"
        }
    ],
    "sg:phone":"+1 818 508 7129",
    "sg:postcode":"91601",
    "sg:province":"CA",
    "wof:name":"Ross Carlock & Assoc Inc",
    "wof:placetype":"venue"
},
  "geometry": {"coordinates":[-118.387682,34.165504],"type":"Point"}
}