{
  "type": "Feature",
  "properties": {
    "iso:country":"US",
    "sg:address":"1471 Industrial Ave",
    "sg:city":"San Jose",
    "sg:classifiers":[
        {
            "category":"Wholesale",
            "subcategory":"Construction Materials",
            "type":"Manufacturing & Wholesale Goods"
        }
    ],
    "sg:phone":"+1 408 298 8723",
    "sg:postcode":"95131",
    "sg:province":"CA",
    "sg:tags":[
        "fence"
    ],
    "wof:name":"A C Lumber Fences Decks Patio",
    "wof:placetype":"venue"
},
  "geometry": {"coordinates":[-121.899798,37.37025],"type":"Point"}
}