{
  "type": "Feature",
  "properties": {
    "addr:full":"5107 Clayton Rd Concord CA 94521",
    "addr:housenumber":"5107",
    "addr:postcode":"94521",
    "addr:street":"Clayton Rd",
    "iso:country":"US",
    "sg:address":"5107 Clayton Rd",
    "sg:city":"Concord",
    "sg:classifiers":[
        {
            "category":"Food & Beverages",
            "subcategory":"Groceries & Convenience Stores",
            "type":"Retail Goods"
        }
    ],
    "sg:phone":"+1 925 689 4311",
    "sg:postcode":"94521",
    "sg:province":"CA",
    "wof:name":"7-Eleven",
    "wof:placetype":"venue"
},
  "geometry": {"coordinates":[-121.965974,37.955286],"type":"Point"}
}