{
  "type": "Feature",
  "properties": {
    "addr:full":"2700 Harvest Rd Modesto CA 95355",
    "addr:housenumber":"2700",
    "addr:postcode":"ca 95355",
    "addr:street":"Harvest Rd",
    "iso:country":"US",
    "sg:address":"2700 Harvest Rd",
    "sg:city":"Modesto",
    "sg:classifiers":[
        {
            "category":"Farming",
            "subcategory":"Livestock Farm",
            "type":"Manufacturing & Wholesale Goods"
        }
    ],
    "sg:phone":"+1 209 579 2913",
    "sg:postcode":"95355",
    "sg:province":"CA",
    "sg:tags":[
        "beef",
        "feedlot",
        "cattle"
    ],
    "wof:name":"Peter Caviness",
    "wof:placetype":"venue"
},
  "geometry": {"coordinates":[-120.943979,37.664094],"type":"Point"}
}