{
  "type": "Feature",
  "properties": {
    "addr:full":"333 S Anita Dr Orange CA 92868",
    "addr:housenumber":"333",
    "addr:postcode":"92868",
    "addr:street":"S Anita Dr",
    "iso:country":"US",
    "sg:address":"333 S Anita Dr",
    "sg:city":"Orange",
    "sg:classifiers":[
        {
            "category":"Deli",
            "type":"Food & Drink"
        },
        {
            "category":"Food & Beverages",
            "subcategory":"Bakery",
            "type":"Retail Goods"
        }
    ],
    "sg:phone":"+1 714 939 2000",
    "sg:postcode":"92868",
    "sg:province":"CA",
    "sg:tags":[
        "sandwich"
    ],
    "wof:name":"Deli 333",
    "wof:placetype":"venue"
},
  "geometry": {"coordinates":[-117.881017,33.785006],"type":"Point"}
}