{
  "type": "Feature",
  "properties": {
    "iso:country":"US",
    "sg:address":"100 S Prospect Ave",
    "sg:city":"Redondo Beach",
    "sg:classifiers":[
        {
            "category":"Arts & Performance",
            "subcategory":"Theater",
            "type":"Entertainment"
        }
    ],
    "sg:phone":"+1 310 792 8069",
    "sg:postcode":"90277",
    "sg:province":"CA",
    "sg:tags":[
        "music"
    ],
    "wof:name":"K & P Productions",
    "wof:placetype":"venue"
},
  "geometry": {"coordinates":[-118.376203,33.840737],"type":"Point"}
}