{
  "type": "Feature",
  "properties": {
    "addr:full":"3280 E 59th St Long Beach CA 90805",
    "addr:housenumber":"3280",
    "addr:postcode":"90805",
    "addr:street":"E 59Th St",
    "iso:country":"US",
    "sg:address":"3280 E 59th St",
    "sg:city":"Long Beach",
    "sg:phone":"+1 562 630 8995",
    "sg:postcode":"90805",
    "sg:province":"CA",
    "sg:tags":[
        "oil"
    ],
    "wof:name":"Shoop & Luther Inc",
    "wof:placetype":"venue"
},
  "geometry": {"coordinates":[-118.151842,33.862853],"type":"Point"}
}