{
  "type": "Feature",
  "properties": {
    "iso:country":"US",
    "sg:address":"6008 Allred Rd",
    "sg:city":"Mariposa",
    "sg:classifiers":[
        {
            "category":"Retail",
            "subcategory":"Auto Repair",
            "type":"Services"
        }
    ],
    "sg:phone":"+1 209 966 5630",
    "sg:postcode":"95338",
    "sg:province":"CA",
    "sg:tags":[
        "repairing",
        "automobile"
    ],
    "wof:name":"Brand Automotive Svc",
    "wof:placetype":"venue"
},
  "geometry": {"coordinates":[-119.936729,37.521082],"type":"Point"}
}