{
  "type": "Feature",
  "properties": {
    "addr:full":"212 S Notre Dame St Orange CA 92869",
    "addr:housenumber":"212",
    "addr:postcode":"92869",
    "addr:street":"S Notre Dame St",
    "iso:country":"US",
    "sg:address":"212 S Notre Dame St",
    "sg:city":"Orange",
    "sg:classifiers":[
        {
            "category":"Professional",
            "type":"Services"
        }
    ],
    "sg:phone":"+1 714 997 0757",
    "sg:postcode":"92869",
    "sg:province":"CA",
    "wof:name":"Nguyen Son H",
    "wof:placetype":"venue"
},
  "geometry": {"coordinates":[-117.785303,33.784904],"type":"Point"}
}