{
  "type": "Feature",
  "properties": {
    "addr:full":"3380 Middlefield Rd Menlo Park CA 94025",
    "addr:housenumber":"3380",
    "addr:postcode":"94025",
    "addr:street":"Middlefield Rd",
    "iso:country":"US",
    "sg:address":"3380 Middlefield Rd",
    "sg:city":"Menlo Park",
    "sg:classifiers":[
        {
            "category":"Food & Beverages",
            "subcategory":"Groceries & Convenience Stores",
            "type":"Retail Goods"
        }
    ],
    "sg:phone":"+1 650 368 9226",
    "sg:postcode":"94025",
    "sg:province":"CA",
    "sg:tags":[
        "grocer"
    ],
    "wof:name":"Michoacam Supermarket",
    "wof:placetype":"venue"
},
  "geometry": {"coordinates":[-122.202578,37.47082],"type":"Point"}
}