{
  "type": "Feature",
  "properties": {
    "iso:country":"US",
    "sg:address":"4321 Secret House Pl",
    "sg:city":"Foresthill",
    "sg:classifiers":[
        {
            "category":"Insurance",
            "subcategory":"Hazard Insurance",
            "type":"Services"
        },
        {
            "category":"Insurance",
            "subcategory":"Life Insurance",
            "type":"Services"
        }
    ],
    "sg:phone":"+1 530 367 5786",
    "sg:postcode":"95631",
    "sg:province":"CA",
    "wof:name":"Scott Freeland",
    "wof:placetype":"venue"
},
  "geometry": {"coordinates":[-120.90780599999999,39.005921],"type":"Point"}
}