{
  "type": "Feature",
  "properties": {
    "iso:country":"US",
    "sg:address":"9901 Indiana Ave",
    "sg:city":"Riverside",
    "sg:classifiers":[
        {
            "category":"Shopping",
            "subcategory":"Hobbies, Toys, & Games",
            "type":"Retail Goods"
        }
    ],
    "sg:phone":"+1 951 359 7100",
    "sg:postcode":"92503",
    "sg:province":"CA",
    "wof:name":"Discount Auto Diecast",
    "wof:placetype":"venue"
},
  "geometry": {"coordinates":[-117.452398,33.907877],"type":"Point"}
}