{
  "type": "Feature",
  "properties": {
    "iso:country":"US",
    "sg:address":"235 Broadway Ct",
    "sg:city":"Long Beach",
    "sg:classifiers":[
        {
            "category":"Freight",
            "type":"Transportation"
        }
    ],
    "sg:phone":"+1 562 436 4561",
    "sg:postcode":"90802",
    "sg:province":"CA",
    "sg:tags":[
        "agency",
        "customhouse",
        "broker",
        "insurance"
    ],
    "wof:name":"American Customs Brokers Co",
    "wof:placetype":"venue"
},
  "geometry": {"coordinates":[-118.18441799999999,33.770409],"type":"Point"}
}