{
  "type": "Feature",
  "properties": {
    "addr:full":"1520 N Mountain Ave Ontario CA 91762",
    "addr:housenumber":"1520",
    "addr:postcode":"91762",
    "addr:street":"N Mountain Ave",
    "iso:country":"US",
    "sg:address":"1520 N Mountain Ave",
    "sg:city":"Ontario",
    "sg:classifiers":[
        {
            "category":"Coffee & Tea",
            "type":"Food & Drink"
        }
    ],
    "sg:menulink":"http://www.allmenus.com/ca/ontario/118668-starbucks-coffee/menu/",
    "sg:phone":"+1 909 391 4245",
    "sg:postcode":"91762",
    "sg:province":"CA",
    "sg:tags":[
        "american"
    ],
    "wof:name":"Starbucks Coffee",
    "wof:placetype":"venue"
},
  "geometry": {"coordinates":[-117.67003,34.085545],"type":"Point"}
}