{
  "type": "Feature",
  "properties": {
    "addr:full":"17395 Laurel Rd Los Gatos CA 95033",
    "addr:housenumber":"17395",
    "addr:postcode":"95033",
    "addr:street":"Laurel Rd",
    "iso:country":"US",
    "sg:address":"17395 Laurel Rd",
    "sg:city":"Los Gatos",
    "sg:classifiers":[
        {
            "category":"Freight",
            "type":"Transportation"
        }
    ],
    "sg:phone":"+1 408 353 1980",
    "sg:postcode":"95033",
    "sg:province":"CA",
    "sg:tags":[
        "operator",
        "trucking"
    ],
    "wof:name":"Ronald Banchero Transportation",
    "wof:placetype":"venue"
},
  "geometry": {"coordinates":[-121.972903,37.10468],"type":"Point"}
}