{
  "type": "Feature",
  "properties": {
    "iso:country":"US",
    "sg:address":"780 Redwood Ave",
    "sg:city":"Seaside",
    "sg:classifiers":[
        {
            "category":"Building & Trades",
            "subcategory":"Plumbing",
            "type":"Services"
        },
        {
            "category":"Home & Garden",
            "subcategory":"Building Materials",
            "type":"Retail Goods"
        },
        {
            "category":"Building & Trades",
            "subcategory":"Construction",
            "type":"Services"
        }
    ],
    "sg:phone":"+1 831 757 9804",
    "sg:postcode":"93955",
    "sg:province":"CA",
    "sg:tags":[
        "heater",
        "plumber",
        "system",
        "specialty",
        "water",
        "equipment",
        "heating",
        "contractor"
    ],
    "wof:name":"Ramirez Plumbing",
    "wof:placetype":"venue"
},
  "geometry": {"coordinates":[-121.847753,36.612814],"type":"Point"}
}