{
  "type": "Feature",
  "properties": {
    "addr:full":"780 Atlantic Ave Long Beach CA 90813",
    "addr:housenumber":"780",
    "addr:postcode":"90813",
    "addr:street":"Atlantic Ave",
    "iso:country":"US",
    "sg:address":"780 Atlantic Ave",
    "sg:city":"Long Beach",
    "sg:classifiers":[
        {
            "category":"Education",
            "subcategory":"School",
            "type":"Public Place"
        }
    ],
    "sg:phone":"+1 562 437 0681",
    "sg:postcode":"90813",
    "sg:province":"CA",
    "sg:tags":[
        "high",
        "middle",
        "elementary"
    ],
    "wof:name":"Long Beach Community Services Development Corp Inc",
    "wof:placetype":"venue"
},
  "geometry": {"coordinates":[-118.18499799999999,33.776299],"type":"Point"}
}