{
  "type": "Feature",
  "properties": {
    "addr:full":"2552 5th Ave Ste A Oroville CA 95965",
    "addr:housenumber":"2552",
    "addr:postcode":"95965",
    "addr:street":"5Th Ave Ste A",
    "iso:country":"US",
    "sg:address":"2552 5th Ave Ste A",
    "sg:city":"Oroville",
    "sg:classifiers":[
        {
            "category":"Home & Garden",
            "subcategory":"Building Materials",
            "type":"Retail Goods"
        },
        {
            "category":"Building & Trades",
            "subcategory":"Construction",
            "type":"Services"
        },
        {
            "category":"Military Area",
            "subcategory":"Armory",
            "type":"Public Place"
        }
    ],
    "sg:phone":"+1 530 533 1341",
    "sg:postcode":"95965",
    "sg:province":"CA",
    "sg:tags":[
        "repair",
        "door",
        "fence",
        "contractor",
        "garage",
        "opener",
        "fence-sales"
    ],
    "wof:name":"Campbell Fence & Repair",
    "wof:placetype":"venue"
},
  "geometry": {"coordinates":[-121.565499,39.497315],"type":"Point"}
}