{
  "type": "Feature",
  "properties": {
    "iso:country":"US",
    "sg:address":"2500 Manhattan Beach Blvd",
    "sg:city":"Redondo Beach",
    "sg:classifiers":[
        {
            "category":"Home & Garden",
            "subcategory":"Garden Supply",
            "type":"Retail Goods"
        }
    ],
    "sg:phone":"+1 310 371 5554",
    "sg:postcode":"90249",
    "sg:province":"CA",
    "sg:tags":[
        "nursery",
        "gardening"
    ],
    "sg:website":"www.performancenursery.com",
    "wof:name":"Performance Nursery",
    "wof:placetype":"venue"
},
  "geometry": {"coordinates":[-118.36646,33.887296],"type":"Point"}
}