{
  "type": "Feature",
  "properties": {
    "addr:full":"2034 N Potter Ave Simi Valley CA 93065",
    "addr:housenumber":"2034",
    "addr:postcode":"93065",
    "addr:street":"N Potter Ave",
    "iso:country":"US",
    "sg:address":"2034 N Potter Ave",
    "sg:city":"Simi Valley",
    "sg:classifiers":[
        {
            "category":"Manufacturing",
            "subcategory":"Retail Goods",
            "type":"Manufacturing & Wholesale Goods"
        }
    ],
    "sg:phone":"+1 805 527 9014",
    "sg:postcode":"93065",
    "sg:province":"CA",
    "sg:tags":[
        "mfg",
        "product",
        "trade",
        "contractor"
    ],
    "wof:name":"Cemtak Inc",
    "wof:placetype":"venue"
},
  "geometry": {"coordinates":[-118.760749,34.274362],"type":"Point"}
}