{
  "type": "Feature",
  "properties": {
    "iso:country":"US",
    "sg:address":"2578 Newport Blvd",
    "sg:city":"Costa Mesa",
    "sg:classifiers":[
        {
            "category":"Retail",
            "subcategory":"Laundry & Dry Cleaning",
            "type":"Services"
        }
    ],
    "sg:phone":"+1 949 722 6777",
    "sg:postcode":"92627",
    "sg:province":"CA",
    "wof:name":"Courtesy Cleaners",
    "wof:placetype":"venue"
},
  "geometry": {"coordinates":[-117.900002,33.660099],"type":"Point"}
}