{
  "type": "Feature",
  "properties": {
    "iso:country":"US",
    "sg:address":"1290 Pacific Coast Hwy",
    "sg:city":"Harbor City",
    "sg:classifiers":[
        {
            "category":"Shopping",
            "subcategory":"Clothing, Apparel, & Fashions",
            "type":"Retail Goods"
        }
    ],
    "sg:phone":"+1 310 534 3424",
    "sg:postcode":"90710",
    "sg:province":"CA",
    "sg:tags":[
        "sheepskin",
        "specialty"
    ],
    "wof:name":"Sunny Sheepskins",
    "wof:placetype":"venue"
},
  "geometry": {"coordinates":[-118.29964699999999,33.789394],"type":"Point"}
}