{
  "type": "Feature",
  "properties": {
    "addr:full":"1290 Pacific Coast Hwy Harbor City CA 90710",
    "addr:housenumber":"1290",
    "addr:postcode":"90710",
    "addr:street":"Pacific Coast Hwy",
    "iso:country":"US",
    "sg:address":"1290 Pacific Coast Hwy",
    "sg:city":"Harbor City",
    "sg:classifiers":[
        {
            "category":"Shopping",
            "subcategory":"Clothing, Apparel, & Fashions",
            "type":"Retail Goods"
        }
    ],
    "sg:phone":"+1 310 534 3424",
    "sg:postcode":"90710",
    "sg:province":"CA",
    "sg:tags":[
        "sheepskin",
        "specialty"
    ],
    "wof:name":"Sunny Sheepskins",
    "wof:placetype":"venue"
},
  "geometry": {"coordinates":[-118.29964699999999,33.789394],"type":"Point"}
}