{
  "type": "Feature",
  "properties": {
    "iso:country":"US",
    "sg:address":"15486 Robert Ct",
    "sg:city":"Grass Valley",
    "sg:classifiers":[
        {
            "category":"Travel",
            "subcategory":"Travel Agent",
            "type":"Entertainment"
        }
    ],
    "sg:phone":"+1 530 272 4458",
    "sg:postcode":"95949",
    "sg:province":"CA",
    "sg:tags":[
        "consultant"
    ],
    "wof:name":"Adventure Water Travel",
    "wof:placetype":"venue"
},
  "geometry": {"coordinates":[-121.05131299999999,39.143457],"type":"Point"}
}