{
  "type": "Feature",
  "properties": {
    "addr:full":"21549 Palomar St Wildomar CA 92595",
    "addr:housenumber":"21549",
    "addr:postcode":"92595",
    "addr:street":"Palomar St",
    "iso:country":"US",
    "sg:address":"21549 Palomar St",
    "sg:city":"Wildomar",
    "sg:classifiers":[
        {
            "category":"Shopping",
            "subcategory":"Used Merchandise",
            "type":"Retail Goods"
        }
    ],
    "sg:phone":"+1 951 678 4252",
    "sg:postcode":"92595",
    "sg:province":"CA",
    "sg:tags":[
        "shop",
        "thrift"
    ],
    "wof:name":"Thrift Store",
    "wof:placetype":"venue"
},
  "geometry": {"coordinates":[-117.272423,33.603418],"type":"Point"}
}