{
  "type": "Feature",
  "properties": {
    "iso:country":"US",
    "sg:address":"7582 Park Ave",
    "sg:city":"Garden Grove",
    "sg:classifiers":[
        {
            "category":"Building & Trades",
            "subcategory":"Construction",
            "type":"Services"
        }
    ],
    "sg:phone":"+1 714 898 9496",
    "sg:postcode":"92841",
    "sg:province":"CA",
    "sg:tags":[
        "sign",
        "contractor"
    ],
    "wof:name":"Instant Signs",
    "wof:placetype":"venue"
},
  "geometry": {"coordinates":[-118.000182,33.776818],"type":"Point"}
}