{
  "type": "Feature",
  "properties": {
    "iso:country":"US",
    "sg:address":"50 Airport Parkway Ofc",
    "sg:city":"San Jose",
    "sg:classifiers":[
        {
            "category":"Professional",
            "subcategory":"Lawyer & Legal Services",
            "type":"Services"
        }
    ],
    "sg:phone":"+1 408 437 7750",
    "sg:postcode":"95110",
    "sg:province":"CA",
    "wof:name":"Law Office of Sandra Savage",
    "wof:placetype":"venue"
},
  "geometry": {"coordinates":[-121.920524,37.371051],"type":"Point"}
}