{
  "type": "Feature",
  "properties": {
    "iso:country":"US",
    "sg:address":"338 W Pico Blvd",
    "sg:city":"Los Angeles",
    "sg:classifiers":[
        {
            "category":"Manufacturing",
            "subcategory":"Printing",
            "type":"Manufacturing & Wholesale Goods"
        }
    ],
    "sg:phone":"+1 323 231 1556",
    "sg:postcode":"90015",
    "sg:province":"CA",
    "sg:tags":[
        "commercial"
    ],
    "wof:name":"Acro Press",
    "wof:placetype":"venue"
},
  "geometry": {"coordinates":[-118.264274,34.038776],"type":"Point"}
}