{
  "type": "Feature",
  "properties": {
    "addr:full":"807 North Rd Belmont CA 94002",
    "addr:housenumber":"807",
    "addr:postcode":"94002",
    "addr:street":"North Rd",
    "iso:country":"US",
    "sg:address":"807 North Rd",
    "sg:city":"Belmont",
    "sg:classifiers":[
        {
            "category":"Wholesale",
            "subcategory":"Computers",
            "type":"Manufacturing & Wholesale Goods"
        }
    ],
    "sg:phone":"+1 650 832 1602",
    "sg:postcode":"94002",
    "sg:province":"CA",
    "wof:name":"Jp",
    "wof:placetype":"venue"
},
  "geometry": {"coordinates":[-122.287521,37.529079],"type":"Point"}
}