{
  "type": "Feature",
  "properties": {
    "addr:full":"536 W Line St Bishop CA 93514",
    "addr:housenumber":"536",
    "addr:postcode":"93514",
    "addr:street":"W Line St",
    "iso:country":"US",
    "sg:address":"536 W Line St",
    "sg:city":"Bishop",
    "sg:classifiers":[
        {
            "category":"Shopping",
            "type":"Retail Goods"
        }
    ],
    "sg:phone":"+1 760 873 8848",
    "sg:postcode":"93514",
    "sg:province":"CA",
    "sg:tags":[
        "hearing",
        "equipment",
        "supply",
        "impaired"
    ],
    "wof:name":"Mountain Hearing Ctr",
    "wof:placetype":"venue"
},
  "geometry": {"coordinates":[-118.399591,37.361278],"type":"Point"}
}