{
  "type": "Feature",
  "properties": {
    "iso:country":"US",
    "sg:address":"915 W Brooks St",
    "sg:city":"Ontario",
    "sg:classifiers":[
        {
            "category":"Retail",
            "subcategory":"Auto Repair",
            "type":"Services"
        }
    ],
    "sg:phone":"+1 909 984 2229",
    "sg:postcode":"91762",
    "sg:province":"CA",
    "sg:tags":[
        "wrecker"
    ],
    "wof:name":"M & D Towing",
    "wof:placetype":"venue"
},
  "geometry": {"coordinates":[-117.668977,34.062118],"type":"Point"}
}