{
  "type": "Feature",
  "properties": {
    "addr:full":"9000 el Camino Real Atascadero CA 93422",
    "addr:housenumber":"9000",
    "addr:postcode":"93422",
    "addr:street":"El Camino Real",
    "iso:country":"US",
    "sg:address":"9000 el Camino Real",
    "sg:city":"Atascadero",
    "sg:classifiers":[
        {
            "category":"Retail",
            "subcategory":"Auto Repair",
            "type":"Services"
        }
    ],
    "sg:phone":"+1 805 462 2862",
    "sg:postcode":"93422",
    "sg:province":"CA",
    "sg:tags":[
        "automobile",
        "smog"
    ],
    "wof:name":"Scotts Auto Care",
    "wof:placetype":"venue"
},
  "geometry": {"coordinates":[-120.652517,35.470041],"type":"Point"}
}