{
  "type": "Feature",
  "properties": {
    "iso:country":"US",
    "sg:address":"1111 E Tahquitz Canyon Way Ste 121",
    "sg:city":"Palm Springs",
    "sg:classifiers":[
        {
            "category":"Health Services",
            "subcategory":"Clinic",
            "type":"Services"
        },
        {
            "category":"Professional",
            "subcategory":"Management & Consulting",
            "type":"Services"
        }
    ],
    "sg:phone":"+1 760 288 6755",
    "sg:postcode":"92262",
    "sg:province":"CA",
    "sg:tags":[
        "counseling",
        "life",
        "coach",
        "mental"
    ],
    "wof:name":"Alicia Stalker LMFT",
    "wof:placetype":"venue"
},
  "geometry": {"coordinates":[-116.53312,33.822211],"type":"Point"}
}