{
  "type": "Feature",
  "properties": {
    "addr:full":"2524 Fender Ave Fullerton CA 92831",
    "addr:housenumber":"2524",
    "addr:postcode":"92831",
    "addr:street":"Fender Ave",
    "iso:country":"US",
    "sg:address":"2524 Fender Ave",
    "sg:city":"Fullerton",
    "sg:classifiers":[
        {
            "category":"Cinema",
            "subcategory":"Movie Rental",
            "type":"Entertainment"
        }
    ],
    "sg:phone":"+1 714 626 0969",
    "sg:postcode":"92831",
    "sg:province":"CA",
    "sg:tags":[
        "game",
        "video"
    ],
    "wof:name":"Fountain Tool",
    "wof:placetype":"venue"
},
  "geometry": {"coordinates":[-117.88417800000001,33.868015],"type":"Point"}
}