{
  "type": "Feature",
  "properties": {
    "iso:country":"US",
    "sg:address":"24631 Crenshaw Blvd Ste J",
    "sg:city":"Torrance",
    "sg:classifiers":[
        {
            "category":"Coffee & Tea",
            "type":"Food & Drink"
        },
        {
            "category":"Restaurant",
            "type":"Food & Drink"
        }
    ],
    "sg:phone":"+1 310 539 8984",
    "sg:postcode":"90505",
    "sg:province":"CA",
    "sg:tags":[
        "taiwanese"
    ],
    "sg:website":"www.cafeidol.com",
    "wof:name":"Cafe Idol",
    "wof:placetype":"venue"
},
  "geometry": {"coordinates":[-118.328048,33.801953],"type":"Point"}
}