{
  "type": "Feature",
  "properties": {
    "iso:country":"US",
    "sg:address":"3383 Michael Dr",
    "sg:city":"Newbury Park",
    "sg:classifiers":[
        {
            "category":"Building & Trades",
            "subcategory":"Construction",
            "type":"Services"
        }
    ],
    "sg:phone":"+1 805 375 1157",
    "sg:postcode":"91320",
    "sg:province":"CA",
    "sg:tags":[
        "roofing",
        "contractor"
    ],
    "wof:name":"Harris Roofing",
    "wof:placetype":"venue"
},
  "geometry": {"coordinates":[-118.94790500000001,34.180325],"type":"Point"}
}