{
  "type": "Feature",
  "properties": {
    "addr:full":"1001 Riverside Rd Watsonville CA 95076",
    "addr:housenumber":"1001",
    "addr:postcode":"95076",
    "addr:street":"Riverside Rd",
    "iso:country":"US",
    "sg:address":"1001 Riverside Rd",
    "sg:city":"Watsonville",
    "sg:classifiers":[
        {
            "category":"Farming",
            "subcategory":"Orchard",
            "type":"Manufacturing & Wholesale Goods"
        }
    ],
    "sg:phone":"+1 831 722 9719",
    "sg:postcode":"95076",
    "sg:province":"CA",
    "sg:tags":[
        "grove",
        "management"
    ],
    "wof:name":"B Banovac Orchards",
    "wof:placetype":"venue"
},
  "geometry": {"coordinates":[-121.69686400000001,36.92417],"type":"Point"}
}