{
  "type": "Feature",
  "properties": {
    "addr:full":"10624 Forest St Santa Fe Springs CA 90670",
    "addr:housenumber":"10624",
    "addr:postcode":"90670",
    "addr:street":"Forest St",
    "iso:country":"US",
    "sg:address":"10624 Forest St",
    "sg:city":"Santa Fe Springs",
    "sg:classifiers":[
        {
            "category":"Manufacturing",
            "subcategory":"Tools & Machinery",
            "type":"Manufacturing & Wholesale Goods"
        }
    ],
    "sg:phone":"+1 562 944 7611",
    "sg:postcode":"90670",
    "sg:province":"CA",
    "sg:tags":[
        "concrete",
        "cutting",
        "breaking",
        "equipment"
    ],
    "wof:name":"De LA Rosa Mfg Inc",
    "wof:placetype":"venue"
},
  "geometry": {"coordinates":[-118.06605500000001,33.935883],"type":"Point"}
}