{
  "type": "Feature",
  "properties": {
    "iso:country":"US",
    "sg:address":"5281 Rio Grande Dr",
    "sg:city":"San Jose",
    "sg:classifiers":[
        {
            "category":"Wholesale",
            "subcategory":"Home Furnishings",
            "type":"Manufacturing & Wholesale Goods"
        }
    ],
    "sg:phone":"+1 408 224 8659",
    "sg:postcode":"95136",
    "sg:province":"CA",
    "sg:tags":[
        "blind",
        "shade"
    ],
    "wof:name":"Roel Enterprises",
    "wof:placetype":"venue"
},
  "geometry": {"coordinates":[-121.824997,37.260101],"type":"Point"}
}