{
  "type": "Feature",
  "properties": {
    "iso:country":"US",
    "sg:address":"2848 Comstock St",
    "sg:city":"San Diego",
    "sg:classifiers":[
        {
            "category":"Building & Trades",
            "subcategory":"Landscaping Services",
            "type":"Services"
        }
    ],
    "sg:phone":"+1 858 565 7699",
    "sg:postcode":"92111",
    "sg:province":"CA",
    "sg:tags":[
        "lawn",
        "maintenance",
        "grounds"
    ],
    "wof:name":"Ricardos Gardening & Landscpng",
    "wof:placetype":"venue"
},
  "geometry": {"coordinates":[-117.175617,32.793728],"type":"Point"}
}