{
  "type": "Feature",
  "properties": {
    "addr:full":"20048 Santa Ana Ave Costa Mesa CA 92627",
    "addr:postcode":"20048;92627",
    "addr:street":"Santa Ana Ave",
    "iso:country":"US",
    "sg:address":"20048 Santa Ana Ave",
    "sg:city":"Costa Mesa",
    "sg:classifiers":[
        {
            "category":"Deli",
            "type":"Food & Drink"
        }
    ],
    "sg:postcode":"92627",
    "sg:province":"CA",
    "wof:name":"JR's Deli",
    "wof:placetype":"venue"
},
  "geometry": {"coordinates":[-117.88210100000001,33.666555],"type":"Point"}
}