{
  "type": "Feature",
  "properties": {
    "addr:full":"222 Winston St Los Angeles CA 90013",
    "addr:housenumber":"222",
    "addr:postcode":"90013",
    "addr:street":"Winston St",
    "iso:country":"US",
    "sg:address":"222 Winston St",
    "sg:city":"Los Angeles",
    "sg:classifiers":[
        {
            "category":"Wholesale",
            "subcategory":"Drugs",
            "type":"Manufacturing & Wholesale Goods"
        }
    ],
    "sg:phone":"+1 213 688 9520",
    "sg:postcode":"90013",
    "sg:province":"CA",
    "sg:tags":[
        "cosmetic"
    ],
    "wof:name":"California Cosmetic Co",
    "wof:placetype":"venue"
},
  "geometry": {"coordinates":[-118.24570799999999,34.045616],"type":"Point"}
}