{
  "type": "Feature",
  "properties": {
    "addr:full":"3110 E Houston Ave Visalia CA 93292",
    "addr:housenumber":"3110",
    "addr:postcode":"93292",
    "addr:street":"E Houston Ave",
    "iso:country":"US",
    "sg:address":"3110 E Houston Ave",
    "sg:city":"Visalia",
    "sg:classifiers":[
        {
            "category":"Education",
            "subcategory":"Special Training",
            "type":"Public Place"
        }
    ],
    "sg:phone":"+1 559 730 7655",
    "sg:postcode":"93292",
    "sg:province":"CA",
    "sg:tags":[
        "school"
    ],
    "sg:website":"www.visalia.k12.ca.us",
    "wof:name":"Visalia Adult School",
    "wof:placetype":"venue"
},
  "geometry": {"coordinates":[-119.257983,36.342065],"type":"Point"}
}