{
  "type": "Feature",
  "properties": {
    "iso:country":"US",
    "sg:address":"3164 Buena Hills Dr",
    "sg:city":"Oceanside",
    "sg:classifiers":[
        {
            "category":"Taxi",
            "type":"Transportation"
        }
    ],
    "sg:phone":"+1 760 722 7472",
    "sg:postcode":"92056",
    "sg:province":"CA",
    "sg:tags":[
        "shuttle",
        "taxicab",
        "airport"
    ],
    "wof:name":"Coastal Cab",
    "wof:placetype":"venue"
},
  "geometry": {"coordinates":[-117.306366,33.187152],"type":"Point"}
}