{
  "type": "Feature",
  "properties": {
    "addr:full":"3500 Amber Dr San Jose CA 95117",
    "addr:housenumber":"3500",
    "addr:postcode":"95117",
    "addr:street":"Amber Dr",
    "iso:country":"US",
    "sg:address":"3500 Amber Dr",
    "sg:city":"San Jose",
    "sg:classifiers":[
        {
            "category":"Social Services",
            "subcategory":"Child Care",
            "type":"Services"
        },
        {
            "category":"Education",
            "subcategory":"Preschool",
            "type":"Public Place"
        },
        {
            "category":"Education",
            "subcategory":"School",
            "type":"Public Place"
        }
    ],
    "sg:phone":"+1 408 248 2464",
    "sg:postcode":"95117",
    "sg:province":"CA",
    "sg:tags":[
        "high",
        "middle",
        "day",
        "elementary"
    ],
    "wof:name":"Primary Plus School",
    "wof:placetype":"venue"
},
  "geometry": {"coordinates":[-121.959999,37.304901],"type":"Point"}
}