{
  "type": "Feature",
  "properties": {
    "iso:country":"US",
    "sg:address":"1937 E 4th St",
    "sg:city":"Ontario",
    "sg:classifiers":[
        {
            "category":"Shopping",
            "subcategory":"Florist",
            "type":"Retail Goods"
        }
    ],
    "sg:phone":"+1 909 987 0497",
    "sg:postcode":"91764",
    "sg:province":"CA",
    "wof:name":"Flowers By Annemarie",
    "wof:placetype":"venue"
},
  "geometry": {"coordinates":[-117.609121,34.07751],"type":"Point"}
}