{
  "type": "Feature",
  "properties": {
    "addr:full":"8156 E Santa Ana Canyon Rd Anaheim CA 92808",
    "addr:housenumber":"8156",
    "addr:postcode":"92808",
    "addr:street":"E Santa Ana Canyon Rd",
    "iso:country":"US",
    "sg:address":"8156 E Santa Ana Canyon Rd",
    "sg:city":"Anaheim",
    "sg:classifiers":[
        {
            "category":"Shopping",
            "subcategory":"Department Store",
            "type":"Retail Goods"
        }
    ],
    "sg:phone":"+1 714 921 2826",
    "sg:postcode":"92808",
    "sg:province":"CA",
    "wof:name":"Pier 1 Imports",
    "wof:placetype":"venue"
},
  "geometry": {"coordinates":[-117.75099899999999,33.868401],"type":"Point"}
}