{
  "type": "Feature",
  "properties": {
    "addr:full":"2506 Glade Dr Santa Clara CA 95051",
    "addr:housenumber":"2506",
    "addr:postcode":"95051",
    "addr:street":"Glade Dr",
    "iso:country":"US",
    "sg:address":"2506 Glade Dr",
    "sg:city":"Santa Clara",
    "sg:classifiers":[
        {
            "category":"Building & Trades",
            "subcategory":"Cleaning & Sanitation",
            "type":"Services"
        }
    ],
    "sg:phone":"+1 408 244 5558",
    "sg:postcode":"95051",
    "sg:province":"CA",
    "sg:tags":[
        "janitor"
    ],
    "wof:name":"J & G Janitorial Svc",
    "wof:placetype":"venue"
},
  "geometry": {"coordinates":[-121.98667500000001,37.367032],"type":"Point"}
}