{
  "type": "Feature",
  "properties": {
    "addr:full":"11139 Azahar St Ventura CA 93004",
    "addr:housenumber":"11139",
    "addr:postcode":"93004",
    "addr:street":"Azahar St",
    "iso:country":"US",
    "sg:address":"11139 Azahar St",
    "sg:city":"Ventura",
    "sg:classifiers":[
        {
            "category":"Wholesale",
            "subcategory":"Farm Supplies",
            "type":"Manufacturing & Wholesale Goods"
        }
    ],
    "sg:phone":"+1 805 659 5478",
    "sg:postcode":"93004",
    "sg:province":"CA",
    "wof:name":"Chavarria Hay & Grain",
    "wof:placetype":"venue"
},
  "geometry": {"coordinates":[-119.147441,34.283915],"type":"Point"}
}