{
  "type": "Feature",
  "properties": {
    "iso:country":"US",
    "sg:address":"5580 Lake Park Way",
    "sg:city":"La Mesa",
    "sg:classifiers":[
        {
            "category":"Manufacturing",
            "subcategory":"Rubber & Plastics",
            "type":"Manufacturing & Wholesale Goods"
        }
    ],
    "sg:phone":"+1 619 697 3961",
    "sg:postcode":"91942",
    "sg:province":"CA",
    "wof:name":"Belitz Mold & Product Design",
    "wof:placetype":"venue"
},
  "geometry": {"coordinates":[-117.034375,32.781985],"type":"Point"}
}