{
  "type": "Feature",
  "properties": {
    "addr:full":"117 Theresa Ave American Canyon CA 94503",
    "addr:housenumber":"117",
    "addr:postcode":"94503",
    "addr:street":"Theresa Ave",
    "iso:country":"US",
    "sg:address":"117 Theresa Ave",
    "sg:city":"American Canyon",
    "sg:classifiers":[
        {
            "category":"Education",
            "subcategory":"School",
            "type":"Public Place"
        }
    ],
    "sg:phone":"+1 707 642 1143",
    "sg:postcode":"94503",
    "sg:province":"CA",
    "wof:name":"Calvary Baptist Christian Acad",
    "wof:placetype":"venue"
},
  "geometry": {"coordinates":[-122.257262,38.181884],"type":"Point"}
}