{
  "type": "Feature",
  "properties": {
    "iso:country":"US",
    "sg:address":"13329 Moorpark St",
    "sg:city":"Sherman Oaks",
    "sg:classifiers":[
        {
            "category":"Shopping",
            "subcategory":"Tobacco",
            "type":"Retail Goods"
        }
    ],
    "sg:phone":"+1 818 906 3654",
    "sg:postcode":"91423",
    "sg:province":"CA",
    "sg:tags":[
        "cigarette",
        "cigar",
        "dealer"
    ],
    "wof:name":"9 To 7 Discount Cigarettes",
    "wof:placetype":"venue"
},
  "geometry": {"coordinates":[-118.423527,34.15043],"type":"Point"}
}