{
  "type": "Feature",
  "properties": {
    "addr:full":"602 S Rockefeller Ave Ontario CA 91761",
    "addr:housenumber":"602",
    "addr:postcode":"91761",
    "addr:street":"S Rockefeller Ave",
    "iso:country":"US",
    "sg:address":"602 S Rockefeller Ave",
    "sg:city":"Ontario",
    "sg:classifiers":[
        {
            "category":"Manufacturing",
            "subcategory":"Retail Goods",
            "type":"Manufacturing & Wholesale Goods"
        },
        {
            "category":"Manufacturing",
            "subcategory":"Paper Products",
            "type":"Manufacturing & Wholesale Goods"
        }
    ],
    "sg:phone":"+1 909 605 6746",
    "sg:postcode":"91761",
    "sg:province":"CA",
    "sg:tags":[
        "corrugated",
        "box",
        "manufacturer",
        "mfg"
    ],
    "wof:name":"Pro Active Packaging & Display",
    "wof:placetype":"venue"
},
  "geometry": {"coordinates":[-117.55468999999999,34.05549],"type":"Point"}
}