{
  "type": "Feature",
  "properties": {
    "iso:country":"US",
    "sg:address":"2527 84th Ave",
    "sg:city":"Oakland",
    "sg:classifiers":[
        {
            "category":"Professional",
            "subcategory":"Management & Consulting",
            "type":"Services"
        }
    ],
    "sg:phone":"+1 510 562 4926",
    "sg:postcode":"94605",
    "sg:province":"CA",
    "sg:tags":[
        "construction"
    ],
    "wof:name":"Assets Under Management Constr",
    "wof:placetype":"venue"
},
  "geometry": {"coordinates":[-122.164258,37.76143],"type":"Point"}
}