{
  "type": "Feature",
  "properties": {
    "iso:country":"US",
    "sg:address":"8817 Reseda Blvd",
    "sg:city":"Northridge",
    "sg:classifiers":[
        {
            "category":"Organizations",
            "subcategory":"Non-profit Organization",
            "type":"Services"
        }
    ],
    "sg:phone":"+1 818 772 0176",
    "sg:postcode":"91324",
    "sg:province":"CA",
    "wof:name":"Domestic Abuse Ctr",
    "wof:placetype":"venue"
},
  "geometry": {"coordinates":[-118.536159,34.231683],"type":"Point"}
}