{
  "type": "Feature",
  "properties": {
    "iso:country":"US",
    "sg:address":"400 S El Camino Real",
    "sg:city":"San Mateo",
    "sg:classifiers":[
        {
            "category":"Professional",
            "subcategory":"Accounting & Tax Preparation",
            "type":"Services"
        }
    ],
    "sg:phone":"+1 650 348 2993",
    "sg:postcode":"94402",
    "sg:province":"CA",
    "sg:tags":[
        "accountant"
    ],
    "wof:name":"Gullo James G & Co",
    "wof:placetype":"venue"
},
  "geometry": {"coordinates":[-122.324997,37.562302],"type":"Point"}
}