{
  "type": "Feature",
  "properties": {
    "iso:country":"US",
    "sg:address":"15071 Imperial Hwy",
    "sg:city":"La Mirada",
    "sg:classifiers":[
        {
            "category":"Health Services",
            "subcategory":"Doctor",
            "type":"Services"
        }
    ],
    "sg:phone":"+1 562 943 2995",
    "sg:postcode":"90638",
    "sg:province":"CA",
    "sg:tags":[
        "surgeon",
        "oral"
    ],
    "wof:name":"Roodzant Gerald P DDS",
    "wof:placetype":"venue"
},
  "geometry": {"coordinates":[-118.011002,33.9174],"type":"Point"}
}