{
  "type": "Feature",
  "properties": {
    "addr:full":"1028 Walnutwood Ct Los Banos CA 93635",
    "addr:housenumber":"1028",
    "addr:postcode":"93635",
    "addr:street":"Walnutwood Ct",
    "iso:country":"US",
    "sg:address":"1028 Walnutwood Ct",
    "sg:city":"Los Banos",
    "sg:classifiers":[
        {
            "category":"Building & Trades",
            "subcategory":"Plumbing",
            "type":"Services"
        }
    ],
    "sg:phone":"+1 209 827 9749",
    "sg:postcode":"93635",
    "sg:province":"CA",
    "sg:tags":[
        "contractor"
    ],
    "wof:name":"Jimmie Lujan Plumbing",
    "wof:placetype":"venue"
},
  "geometry": {"coordinates":[-120.84154599999999,37.079121],"type":"Point"}
}