{
  "type": "Feature",
  "properties": {
    "iso:country":"US",
    "sg:address":"1726 N Vermont Ave",
    "sg:city":"Los Angeles",
    "sg:classifiers":[
        {
            "category":"Ice Cream",
            "type":"Food & Drink"
        }
    ],
    "sg:phone":"+1 323 661 0411",
    "sg:postcode":"90027",
    "sg:province":"CA",
    "sg:tags":[
        "frozen",
        "yogurt"
    ],
    "sg:website":"www.pinkberry.com",
    "wof:name":"Pinkberry",
    "wof:placetype":"venue"
},
  "geometry": {"coordinates":[-118.291776,34.102525],"type":"Point"}
}