{
  "type": "Feature",
  "properties": {
    "iso:country":"US",
    "sg:address":"4331 Louisiana St",
    "sg:city":"San Diego",
    "sg:classifiers":[
        {
            "category":"Farming",
            "subcategory":"Farm & Veterinary Services",
            "type":"Manufacturing & Wholesale Goods"
        }
    ],
    "sg:phone":"+1 619 861 9169",
    "sg:postcode":"92104",
    "sg:province":"CA",
    "sg:tags":[
        "research"
    ],
    "wof:name":"On The Lookout Inc",
    "wof:placetype":"venue"
},
  "geometry": {"coordinates":[-117.140068,32.755271],"type":"Point"}
}