{
  "type": "Feature",
  "properties": {
    "iso:country":"US",
    "sg:address":"24509 Walnut St",
    "sg:city":"Santa Clarita",
    "sg:classifiers":[
        {
            "category":"Social Services",
            "type":"Services"
        }
    ],
    "sg:phone":"+1 661 287 5996",
    "sg:postcode":"91321",
    "sg:province":"CA",
    "sg:tags":[
        "counselor",
        "marriage",
        "family"
    ],
    "wof:name":"Zaroff & Zaroff",
    "wof:placetype":"venue"
},
  "geometry": {"coordinates":[-118.53095,34.380851],"type":"Point"}
}