{
  "type": "Feature",
  "properties": {
    "iso:country":"US",
    "sg:address":"13110 Lakewood Blvd",
    "sg:city":"Bellflower",
    "sg:classifiers":[
        {
            "category":"Autos & Motor Vehicles",
            "subcategory":"Automobile Sales",
            "type":"Retail Goods"
        }
    ],
    "sg:phone":"+1 562 633 6090",
    "sg:postcode":"90706",
    "sg:province":"CA",
    "sg:tags":[
        "car",
        "dealer"
    ],
    "wof:name":"Empresa Motors Inc",
    "wof:placetype":"venue"
},
  "geometry": {"coordinates":[-118.14272,33.909314],"type":"Point"}
}