{
  "type": "Feature",
  "properties": {
    "addr:full":"7530 Mesa College Dr San Diego CA 92111",
    "addr:housenumber":"7530",
    "addr:postcode":"92111",
    "addr:street":"Mesa College Dr",
    "iso:country":"US",
    "sg:address":"7530 Mesa College Dr",
    "sg:city":"San Diego",
    "sg:classifiers":[
        {
            "category":"Restaurant",
            "type":"Food & Drink"
        }
    ],
    "sg:phone":"+1 858 279 3618",
    "sg:postcode":"92111",
    "sg:province":"CA",
    "sg:tags":[
        "eating"
    ],
    "wof:name":"Maerasy Lao Thai Cusine",
    "wof:placetype":"venue"
},
  "geometry": {"coordinates":[-117.15939400000001,32.801439],"type":"Point"}
}