{
  "type": "Feature",
  "properties": {
    "addr:full":"1378 Nacion Ave Chula Vista CA 91911",
    "addr:housenumber":"1378",
    "addr:postcode":"91911",
    "addr:street":"Nacion Ave",
    "iso:country":"US",
    "sg:address":"1378 Nacion Ave",
    "sg:city":"Chula Vista",
    "sg:classifiers":[
        {
            "category":"Freight",
            "type":"Transportation"
        }
    ],
    "sg:phone":"+1 619 778 4239",
    "sg:postcode":"91911",
    "sg:province":"CA",
    "sg:tags":[
        "operator",
        "trucking"
    ],
    "wof:name":"Nahual Freightlines",
    "wof:placetype":"venue"
},
  "geometry": {"coordinates":[-117.038466,32.613388],"type":"Point"}
}