{
  "type": "Feature",
  "properties": {
    "iso:country":"US",
    "sg:address":"8939 S Sepulveda Blvd",
    "sg:city":"Los Angeles",
    "sg:classifiers":[
        {
            "category":"Health Services",
            "subcategory":"Hospital",
            "type":"Services"
        }
    ],
    "sg:phone":"+1 310 338 1587",
    "sg:postcode":"90045",
    "sg:province":"CA",
    "sg:tags":[
        "mental"
    ],
    "wof:name":"Delores A Hill",
    "wof:placetype":"venue"
},
  "geometry": {"coordinates":[-118.396127,33.957237],"type":"Point"}
}