{
  "type": "Feature",
  "properties": {
    "addr:full":"4601 Lang Ave Mcclellan CA 95652",
    "addr:housenumber":"4601",
    "addr:postcode":"95652",
    "addr:street":"Lang Ave",
    "iso:country":"US",
    "sg:address":"4601 Lang Ave",
    "sg:city":"Mcclellan",
    "sg:classifiers":[
        {
            "category":"Building & Trades",
            "subcategory":"Construction",
            "type":"Services"
        }
    ],
    "sg:phone":"+1 916 925 0626",
    "sg:postcode":"95652",
    "sg:province":"CA",
    "sg:tags":[
        "mason",
        "masonry",
        "industrial",
        "contractors-commercial",
        "contractor"
    ],
    "wof:name":"Rox Pro Sacramento",
    "wof:placetype":"venue"
},
  "geometry": {"coordinates":[-121.42131000000001,38.651031],"type":"Point"}
}