{
  "type": "Feature",
  "properties": {
    "iso:country":"US",
    "sg:address":"237 Corbett Canyon Rd",
    "sg:city":"Arroyo Grande",
    "sg:classifiers":[
        {
            "category":"Building & Trades",
            "subcategory":"Construction",
            "type":"Services"
        }
    ],
    "sg:phone":"+1 805 473 8499",
    "sg:postcode":"93420",
    "sg:province":"CA",
    "sg:tags":[
        "general",
        "contractor"
    ],
    "wof:name":"Chaffee",
    "wof:placetype":"venue"
},
  "geometry": {"coordinates":[-120.57033300000001,35.132471],"type":"Point"}
}