{
  "type": "Feature",
  "properties": {
    "iso:country":"US",
    "sg:address":"3724 Park Pl",
    "sg:city":"Glendale",
    "sg:classifiers":[
        {
            "category":"Building & Trades",
            "subcategory":"Electrical",
            "type":"Services"
        }
    ],
    "sg:phone":"+1 818 957 8961",
    "sg:postcode":"91201",
    "sg:province":"CA",
    "sg:tags":[
        "electrician"
    ],
    "wof:name":"Calif Associated Power",
    "wof:placetype":"venue"
},
  "geometry": {"coordinates":[-118.292,34.170601],"type":"Point"}
}