{
  "type": "Feature",
  "properties": {
    "iso:country":"US",
    "sg:address":"4265 Summerwood Ct",
    "sg:city":"Vacaville",
    "sg:classifiers":[
        {
            "category":"Professional",
            "type":"Services"
        }
    ],
    "sg:phone":"+1 707 447 2494",
    "sg:postcode":"95688",
    "sg:province":"CA",
    "wof:name":"Budget Blinds Of Fairfield",
    "wof:placetype":"venue"
},
  "geometry": {"coordinates":[-121.98687,38.414885],"type":"Point"}
}