{
  "type": "Feature",
  "properties": {
    "addr:full":"412 S Pacific Coast Hwy Redondo Beach CA 90277",
    "addr:housenumber":"412",
    "addr:postcode":"90277",
    "addr:street":"S Pacific Coast Hwy",
    "iso:country":"US",
    "sg:address":"412 S Pacific Coast Hwy",
    "sg:city":"Redondo Beach",
    "sg:classifiers":[
        {
            "category":"Sports & Exercise",
            "subcategory":"Gym",
            "type":"Entertainment"
        }
    ],
    "sg:phone":"+1 310 316 2220",
    "sg:postcode":"90277",
    "sg:province":"CA",
    "sg:tags":[
        "spa",
        "health"
    ],
    "wof:name":"Lotus Spa",
    "wof:placetype":"venue"
},
  "geometry": {"coordinates":[-118.385059,33.834932],"type":"Point"}
}