{
  "type": "Feature",
  "properties": {
    "addr:full":"10078 Arrow Rte Rancho Cucamonga CA 91730",
    "addr:housenumber":"10078",
    "addr:postcode":"91730",
    "addr:street":"Arrow Rte",
    "iso:country":"US",
    "sg:address":"10078 Arrow Rte",
    "sg:city":"Rancho Cucamonga",
    "sg:classifiers":[
        {
            "category":"Education",
            "subcategory":"Special Training",
            "type":"Public Place"
        }
    ],
    "sg:phone":"+1 909 941 3705",
    "sg:postcode":"91730",
    "sg:province":"CA",
    "sg:tags":[
        "tutoring"
    ],
    "wof:name":"Kumon Of Rancho Cucamonga",
    "wof:placetype":"venue"
},
  "geometry": {"coordinates":[-117.58668400000001,34.099371],"type":"Point"}
}