{
  "type": "Feature",
  "properties": {
    "iso:country":"US",
    "sg:address":"223 S Riverside Ave",
    "sg:city":"Rialto",
    "sg:classifiers":[
        {
            "category":"Insurance",
            "subcategory":"Insurance Agent",
            "type":"Services"
        }
    ],
    "sg:phone":"+1 909 421 7700",
    "sg:postcode":"92376",
    "sg:province":"CA",
    "wof:name":"Total Budget Insurance",
    "wof:placetype":"venue"
},
  "geometry": {"coordinates":[-117.370204,34.097346],"type":"Point"}
}