{
  "type": "Feature",
  "properties": {
    "addr:full":"2480 E Colorado Blvd Pasadena CA 91107",
    "addr:housenumber":"2480",
    "addr:postcode":"91107",
    "addr:street":"E Colorado Blvd",
    "iso:country":"US",
    "sg:address":"2480 E Colorado Blvd",
    "sg:city":"Pasadena",
    "sg:classifiers":[
        {
            "category":"Personal",
            "subcategory":"Tattoo Parlor",
            "type":"Services"
        }
    ],
    "sg:phone":"+1 626 578 1330",
    "sg:postcode":"91107",
    "sg:province":"CA",
    "sg:website":"www.shoguntattoo.com",
    "wof:name":"Shogun Tattoo Studios",
    "wof:placetype":"venue"
},
  "geometry": {"coordinates":[-118.09920200000001,34.146038],"type":"Point"}
}