{
  "type": "Feature",
  "properties": {
    "addr:full":"4731 Telegraph Ave Oakland CA 94609",
    "addr:housenumber":"4731",
    "addr:postcode":"94609",
    "addr:street":"Telegraph Ave",
    "iso:country":"US",
    "sg:address":"4731 Telegraph Ave",
    "sg:city":"Oakland",
    "sg:classifiers":[
        {
            "category":"Personal",
            "subcategory":"Barber",
            "type":"Services"
        }
    ],
    "sg:phone":"+1 510 595 3645",
    "sg:postcode":"94609",
    "sg:province":"CA",
    "wof:name":"Ebony Men's",
    "wof:placetype":"venue"
},
  "geometry": {"coordinates":[-122.26300000000001,37.834999],"type":"Point"}
}