{
  "type": "Feature",
  "properties": {
    "addr:full":"1011 Portola Dr San Francisco CA 94127",
    "addr:housenumber":"1011",
    "addr:postcode":"94127",
    "addr:street":"Portola Dr",
    "iso:country":"US",
    "sg:address":"1011 Portola Dr",
    "sg:city":"San Francisco",
    "sg:classifiers":[
        {
            "category":"Professional",
            "subcategory":"Lawyer & Legal Services",
            "type":"Services"
        }
    ],
    "sg:phone":"+1 415 504 7029",
    "sg:postcode":"94127",
    "sg:province":"CA",
    "sg:tags":[
        "attorney"
    ],
    "wof:name":"Thomas P Carey Attorney At Law",
    "wof:placetype":"venue"
},
  "geometry": {"coordinates":[-122.45746800000001,37.740969],"type":"Point"}
}