{
  "type": "Feature",
  "properties": {
    "iso:country":"US",
    "sg:address":"1800 Stokes St",
    "sg:city":"San Jose",
    "sg:classifiers":[
        {
            "category":"Building & Trades",
            "subcategory":"Cleaning & Sanitation",
            "type":"Services"
        }
    ],
    "sg:phone":"+1 408 449 3382",
    "sg:postcode":"95126",
    "sg:province":"CA",
    "sg:tags":[
        "carpet"
    ],
    "wof:name":"Elite Carpet Care",
    "wof:placetype":"venue"
},
  "geometry": {"coordinates":[-121.926374,37.300345],"type":"Point"}
}