{
  "type": "Feature",
  "properties": {
    "iso:country":"US",
    "sg:address":"1041 Bishop St",
    "sg:city":"San Luis Obispo",
    "sg:classifiers":[
        {
            "category":"Banks & Credit Unions",
            "subcategory":"Bank",
            "type":"Services"
        }
    ],
    "sg:phone":"+1 805 545 9235",
    "sg:postcode":"93401",
    "sg:province":"CA",
    "sg:tags":[
        "loan",
        "real estate"
    ],
    "wof:name":"CTX Mortgage Co",
    "wof:placetype":"venue"
},
  "geometry": {"coordinates":[-120.65106,35.270652],"type":"Point"}
}