{
  "type": "Feature",
  "properties": {
    "iso:country":"US",
    "sg:address":"6674 Mission St",
    "sg:city":"Daly City",
    "sg:classifiers":[
        {
            "category":"Professional",
            "subcategory":"Lawyer & Legal Services",
            "type":"Services"
        }
    ],
    "sg:phone":"+1 650 991 1154",
    "sg:postcode":"94014",
    "sg:province":"CA",
    "sg:tags":[
        "attorney"
    ],
    "wof:name":"Ted Laguatan & Assoc",
    "wof:placetype":"venue"
},
  "geometry": {"coordinates":[-122.46301099999999,37.702746],"type":"Point"}
}