{
  "type": "Feature",
  "properties": {
    "addr:full":"2507 Nebraska Ave Selma CA 93662",
    "addr:housenumber":"2507",
    "addr:postcode":"93662",
    "addr:street":"Nebraska Ave",
    "iso:country":"US",
    "sg:address":"2507 Nebraska Ave",
    "sg:city":"Selma",
    "sg:classifiers":[
        {
            "category":"Food & Beverages",
            "subcategory":"Meat & Fish",
            "type":"Retail Goods"
        }
    ],
    "sg:phone":"+1 559 891 8760",
    "sg:postcode":"93662",
    "sg:province":"CA",
    "wof:name":"Botanas Carniceria Y Taqueria",
    "wof:placetype":"venue"
},
  "geometry": {"coordinates":[-119.62414800000001,36.561568],"type":"Point"}
}