{
  "type": "Feature",
  "properties": {
    "addr:full":"707 Sutter St Yuba City CA 95991",
    "addr:housenumber":"707",
    "addr:postcode":"95991",
    "addr:street":"Sutter St",
    "iso:country":"US",
    "sg:address":"707 Sutter St",
    "sg:city":"Yuba City",
    "sg:classifiers":[
        {
            "category":"Shopping",
            "subcategory":"Florist",
            "type":"Retail Goods"
        }
    ],
    "sg:phone":"+1 530 673 0182",
    "sg:postcode":"95991",
    "sg:province":"CA",
    "wof:name":"Flowers By Jesus",
    "wof:placetype":"venue"
},
  "geometry": {"coordinates":[-121.609617,39.139913],"type":"Point"}
}