{
  "type": "Feature",
  "properties": {
    "addr:full":"2084 Mission Street San Francisco CA 94110",
    "addr:housenumber":"2084",
    "addr:postcode":"94110",
    "addr:street":"Mission Street",
    "iso:country":"US",
    "sg:address":"2084 Mission Street",
    "sg:city":"San Francisco",
    "sg:classifiers":[
        {
            "category":"Travel",
            "subcategory":"Hotels & Motels",
            "type":"Entertainment"
        }
    ],
    "sg:phone":"+1 415 553 6190",
    "sg:postcode":"94110",
    "sg:province":"CA",
    "wof:name":"Frances Hotel",
    "wof:placetype":"venue"
},
  "geometry": {"coordinates":[-122.41999800000001,37.763802],"type":"Point"}
}