{
  "type": "Feature",
  "properties": {
    "addr:full":"125 S Mount Vernon Ave Lindsay CA 93247",
    "addr:housenumber":"125",
    "addr:postcode":"93247",
    "addr:street":"S Mount Vernon Ave",
    "iso:country":"US",
    "sg:address":"125 S Mount Vernon Ave",
    "sg:city":"Lindsay",
    "sg:classifiers":[
        {
            "category":"Wholesale",
            "subcategory":"Fruits & Vegetables",
            "type":"Manufacturing & Wholesale Goods"
        }
    ],
    "sg:phone":"+1 559 562 1327",
    "sg:postcode":"93247",
    "sg:province":"CA",
    "sg:tags":[
        "shipper"
    ],
    "wof:name":"Yokohl Valley Packing",
    "wof:placetype":"venue"
},
  "geometry": {"coordinates":[-119.09262699999999,36.201319],"type":"Point"}
}