{
  "type": "Feature",
  "properties": {
    "addr:full":"13573 Larwin Cir Santa Fe Springs CA 90670",
    "addr:housenumber":"13573",
    "addr:postcode":"90670",
    "addr:street":"Larwin Cir",
    "iso:country":"US",
    "sg:address":"13573 Larwin Cir",
    "sg:city":"Santa Fe Springs",
    "sg:classifiers":[
        {
            "category":"Manufacturing",
            "subcategory":"Printing",
            "type":"Manufacturing & Wholesale Goods"
        }
    ],
    "sg:phone":"+1 562 941 3031",
    "sg:postcode":"90670",
    "sg:province":"CA",
    "sg:tags":[
        "bookbinder"
    ],
    "wof:name":"Pel Bookbinding Corp",
    "wof:placetype":"venue"
},
  "geometry": {"coordinates":[-118.03944799999999,33.908734],"type":"Point"}
}