{
  "type": "Feature",
  "properties": {
    "addr:full":"238 Beel Dr Santa Cruz CA 95060",
    "addr:housenumber":"238",
    "addr:postcode":"95060",
    "addr:street":"Beel Dr",
    "iso:country":"US",
    "sg:address":"238 Beel Dr",
    "sg:city":"Santa Cruz",
    "sg:classifiers":[
        {
            "category":"Manufacturing",
            "subcategory":"Furniture",
            "type":"Manufacturing & Wholesale Goods"
        }
    ],
    "sg:phone":"+1 831 423 2950",
    "sg:postcode":"95060",
    "sg:province":"CA",
    "sg:tags":[
        "drapery",
        "mfg"
    ],
    "wof:name":"Vertical Sales",
    "wof:placetype":"venue"
},
  "geometry": {"coordinates":[-122.01378099999999,37.003101],"type":"Point"}
}