{
  "type": "Feature",
  "properties": {
    "iso:country":"US",
    "sg:address":"1617 Silver Lake Blvd",
    "sg:city":"Los Angeles",
    "sg:classifiers":[
        {
            "category":"Arts & Performance",
            "subcategory":"Art Gallery",
            "type":"Entertainment"
        },
        {
            "category":"Shopping",
            "subcategory":"Crafts & Fabrics",
            "type":"Retail Goods"
        }
    ],
    "sg:phone":"+1 323 660 7991",
    "sg:postcode":"90026",
    "sg:province":"CA",
    "sg:website":"www.studio1617.com",
    "wof:name":"Studio 1617",
    "wof:placetype":"venue"
},
  "geometry": {"coordinates":[-118.269107,34.08847],"type":"Point"}
}