{
  "type": "Feature",
  "properties": {
    "addr:full":"1041 E 16th St Upland CA 91784",
    "addr:housenumber":"1041",
    "addr:postcode":"91784",
    "addr:street":"E 16Th St",
    "iso:country":"US",
    "sg:address":"1041 E 16th St",
    "sg:city":"Upland",
    "sg:classifiers":[
        {
            "category":"Restaurant",
            "type":"Food & Drink"
        }
    ],
    "sg:phone":"+1 909 949 1618",
    "sg:postcode":"91784",
    "sg:province":"CA",
    "sg:tags":[
        "caterer"
    ],
    "wof:name":"Afaire To Remember Catering",
    "wof:placetype":"venue"
},
  "geometry": {"coordinates":[-117.640923,34.12163],"type":"Point"}
}