{
  "type": "Feature",
  "properties": {
    "addr:full":"9010 Rosecrans Ave Bellflower CA 90706",
    "addr:housenumber":"9010",
    "addr:postcode":"90706",
    "addr:street":"Rosecrans Ave",
    "iso:country":"US",
    "sg:address":"9010 Rosecrans Ave",
    "sg:city":"Bellflower",
    "sg:classifiers":[
        {
            "category":"Retail",
            "subcategory":"Auto Repair",
            "type":"Services"
        }
    ],
    "sg:phone":"+1 562 633 4517",
    "sg:postcode":"90706",
    "sg:province":"CA",
    "sg:tags":[
        "repairing",
        "automobile"
    ],
    "wof:name":"Ernesto Raygoza",
    "wof:placetype":"venue"
},
  "geometry": {"coordinates":[-118.14070700000001,33.903783],"type":"Point"}
}