{
  "type": "Feature",
  "properties": {
    "iso:country":"US",
    "sg:address":"610 Industrial Dr",
    "sg:city":"Exeter",
    "sg:classifiers":[
        {
            "category":"Freight",
            "type":"Transportation"
        }
    ],
    "sg:phone":"+1 559 592 6021",
    "sg:postcode":"93221",
    "sg:province":"CA",
    "sg:tags":[
        "commercial",
        "storage"
    ],
    "wof:name":"Exeter Mini Storage",
    "wof:placetype":"venue"
},
  "geometry": {"coordinates":[-119.140553,36.289566],"type":"Point"}
}