{
  "type": "Feature",
  "properties": {
    "iso:country":"US",
    "sg:address":"17660 Carpintero Ave",
    "sg:city":"Bellflower",
    "sg:classifiers":[
        {
            "category":"Organizations",
            "subcategory":"Religious Organization",
            "type":"Services"
        }
    ],
    "sg:phone":"+1 562 866 9842",
    "sg:postcode":"90706",
    "sg:province":"CA",
    "wof:name":"Corporation of President of Th",
    "wof:placetype":"venue"
},
  "geometry": {"coordinates":[-118.114262,33.872625],"type":"Point"}
}