{
  "type": "Feature",
  "properties": {
    "addr:full":"1506 Constitution Blvd Salinas CA 93905",
    "addr:housenumber":"1506",
    "addr:postcode":"93905",
    "addr:street":"Constitution Blvd",
    "iso:country":"US",
    "sg:address":"1506 Constitution Blvd",
    "sg:city":"Salinas",
    "sg:classifiers":[
        {
            "category":"Personal",
            "subcategory":"Beauty Salon",
            "type":"Services"
        }
    ],
    "sg:phone":"+1 831 444 8137",
    "sg:postcode":"93905",
    "sg:province":"CA",
    "wof:name":"Supercuts",
    "wof:placetype":"venue"
},
  "geometry": {"coordinates":[-121.62099000000001,36.700286],"type":"Point"}
}