{
  "type": "Feature",
  "properties": {
    "iso:country":"US",
    "sg:address":"516 Viewridge Dr",
    "sg:city":"Angwin",
    "sg:classifiers":[
        {
            "category":"Professional",
            "subcategory":"Computer Services",
            "type":"Services"
        }
    ],
    "sg:phone":"+1 707 965 0636",
    "sg:postcode":"94508",
    "sg:province":"CA",
    "sg:tags":[
        "consultant",
        "designer",
        "datum",
        "system"
    ],
    "wof:name":"Begetech",
    "wof:placetype":"venue"
},
  "geometry": {"coordinates":[-122.453245,38.559366],"type":"Point"}
}