{
  "type": "Feature",
  "properties": {
    "iso:country":"US",
    "sg:address":"2100 Garden Rd",
    "sg:city":"Monterey",
    "sg:classifiers":[
        {
            "category":"Professional",
            "subcategory":"Lawyer & Legal Services",
            "type":"Services"
        }
    ],
    "sg:phone":"+1 831 455 2100",
    "sg:postcode":"93940",
    "sg:province":"CA",
    "sg:tags":[
        "attorney"
    ],
    "wof:name":"Sharyn F Evers",
    "wof:placetype":"venue"
},
  "geometry": {"coordinates":[-121.856153,36.586135],"type":"Point"}
}