{
  "type": "Feature",
  "properties": {
    "addr:full":"800 Commercial Ave Oxnard CA 93030",
    "addr:housenumber":"800",
    "addr:postcode":"93030",
    "addr:street":"Commercial Ave",
    "iso:country":"US",
    "sg:address":"800 Commercial Ave",
    "sg:city":"Oxnard",
    "sg:classifiers":[
        {
            "category":"Manufacturing",
            "subcategory":"Food",
            "type":"Manufacturing & Wholesale Goods"
        }
    ],
    "sg:phone":"+1 805 487 5483",
    "sg:postcode":"93030",
    "sg:province":"CA",
    "sg:tags":[
        "frozen",
        "processor"
    ],
    "wof:name":"J M Smucker Co",
    "wof:placetype":"venue"
},
  "geometry": {"coordinates":[-119.173115,34.193866],"type":"Point"}
}