{
  "type": "Feature",
  "properties": {
    "iso:country":"US",
    "sg:address":"15315 Magnolia Blvd",
    "sg:city":"Sherman Oaks",
    "sg:classifiers":[
        {
            "category":"Restaurant",
            "type":"Food & Drink"
        }
    ],
    "sg:phone":"+1 818 788 0955",
    "sg:postcode":"91403",
    "sg:province":"CA",
    "wof:name":"Courtyard Deli",
    "wof:placetype":"venue"
},
  "geometry": {"coordinates":[-118.469285,34.164845],"type":"Point"}
}