{
  "type": "Feature",
  "properties": {
    "addr:full":"540 Bella Dr Newbury Park CA 91320",
    "addr:housenumber":"540",
    "addr:postcode":"91320",
    "addr:street":"Bella Dr",
    "iso:country":"US",
    "sg:address":"540 Bella Dr",
    "sg:city":"Newbury Park",
    "sg:classifiers":[
        {
            "category":"Professional",
            "subcategory":"Business Services",
            "type":"Services"
        }
    ],
    "sg:phone":"+1 805 389 7477",
    "sg:postcode":"91320",
    "sg:province":"CA",
    "wof:name":"United Business Forms",
    "wof:placetype":"venue"
},
  "geometry": {"coordinates":[-118.94161,34.185776],"type":"Point"}
}