{
  "type": "Feature",
  "properties": {
    "addr:full":"3136 W 109th St Inglewood CA 90303",
    "addr:housenumber":"3136",
    "addr:postcode":"90303",
    "addr:street":"W 109Th St",
    "iso:country":"US",
    "sg:address":"3136 W 109th St",
    "sg:city":"Inglewood",
    "sg:classifiers":[
        {
            "category":"Building & Trades",
            "subcategory":"Plumbing",
            "type":"Services"
        }
    ],
    "sg:phone":"+1 310 677 5879",
    "sg:postcode":"90303",
    "sg:province":"CA",
    "sg:tags":[
        "contractor"
    ],
    "wof:name":"Jefferson Perry Heating & Plbg",
    "wof:placetype":"venue"
},
  "geometry": {"coordinates":[-118.32651300000001,33.936777],"type":"Point"}
}