{
  "type": "Feature",
  "properties": {
    "addr:full":"309 Airport Boulevard South San Francisco CA 94080",
    "addr:housenumber":"309",
    "addr:postcode":"94080",
    "addr:street":"Airport Boulevard",
    "iso:country":"US",
    "sg:address":"309 Airport Boulevard",
    "sg:city":"South San Francisco",
    "sg:classifiers":[
        {
            "category":"Bars & Pubs",
            "subcategory":"Dive Bar",
            "type":"Food & Drink"
        }
    ],
    "sg:phone":"+1 650 588 3698",
    "sg:postcode":"94080",
    "sg:province":"CA",
    "wof:name":"Christy's Bar & Grill",
    "wof:placetype":"venue"
},
  "geometry": {"coordinates":[-122.407859,37.655021],"type":"Point"}
}