{
  "type": "Feature",
  "properties": {
    "addr:full":"2031 Harbison Dr Vacaville CA 95687",
    "addr:housenumber":"2031",
    "addr:postcode":"95687",
    "addr:street":"Harbison Dr",
    "iso:country":"US",
    "sg:address":"2031 Harbison Dr",
    "sg:city":"Vacaville",
    "sg:classifiers":[
        {
            "category":"Shopping",
            "subcategory":"Clothing, Apparel, & Fashions",
            "type":"Retail Goods"
        }
    ],
    "sg:phone":"+1 707 449 9433",
    "sg:postcode":"95687",
    "sg:province":"CA",
    "sg:tags":[
        "apparel",
        "women's"
    ],
    "sg:website":"http://Avenue.com",
    "wof:name":"Avenue",
    "wof:placetype":"venue"
},
  "geometry": {"coordinates":[-121.964157,38.362783],"type":"Point"}
}