{
  "type": "Feature",
  "properties": {
    "addr:full":"2818 Conant Ave Modesto CA 95350",
    "addr:housenumber":"2818",
    "addr:postcode":"ca 95350",
    "addr:street":"Conant Ave",
    "iso:country":"US",
    "sg:address":"2818 Conant Ave",
    "sg:city":"Modesto",
    "sg:classifiers":[
        {
            "category":"Education",
            "subcategory":"School",
            "type":"Public Place"
        }
    ],
    "sg:phone":"+1 209 529 5430",
    "sg:postcode":"95350",
    "sg:province":"CA",
    "wof:name":"Stanislaus Union School Dist",
    "wof:placetype":"venue"
},
  "geometry": {"coordinates":[-121.040437,37.682148],"type":"Point"}
}