{
  "type": "Feature",
  "properties": {
    "addr:full":"1045 Shary Cir Concord CA 94518",
    "addr:housenumber":"1045",
    "addr:postcode":"94518",
    "addr:street":"Shary Cir",
    "iso:country":"US",
    "sg:address":"1045 Shary Cir",
    "sg:city":"Concord",
    "sg:classifiers":[
        {
            "category":"Manufacturing",
            "subcategory":"Chemicals & Compounds",
            "type":"Manufacturing & Wholesale Goods"
        }
    ],
    "sg:phone":"+1 925 798 8818",
    "sg:postcode":"94518",
    "sg:province":"CA",
    "sg:tags":[
        "biological",
        "product",
        "mfg"
    ],
    "wof:name":"Microbiological Media",
    "wof:placetype":"venue"
},
  "geometry": {"coordinates":[-122.03135399999999,37.952922],"type":"Point"}
}