{
  "type": "Feature",
  "properties": {
    "addr:full":"861 University Ave Palo Alto CA 94301",
    "addr:housenumber":"861",
    "addr:postcode":"94301",
    "addr:street":"University Ave",
    "iso:country":"US",
    "sg:address":"861 University Ave",
    "sg:city":"Palo Alto",
    "sg:classifiers":[
        {
            "category":"Real Estate",
            "subcategory":"Real Estate Operator",
            "type":"Services"
        }
    ],
    "sg:phone":"+1 650 324 1693",
    "sg:postcode":"94301",
    "sg:province":"CA",
    "sg:tags":[
        "apartment"
    ],
    "wof:name":"University Garden Apartments",
    "wof:placetype":"venue"
},
  "geometry": {"coordinates":[-122.155083,37.452446],"type":"Point"}
}