{
  "type": "Feature",
  "properties": {
    "iso:country":"US",
    "sg:address":"9 Montebello Way",
    "sg:city":"Los Gatos",
    "sg:classifiers":[
        {
            "category":"Recreation",
            "type":"Entertainment"
        }
    ],
    "sg:phone":"+1 408 761 3914",
    "sg:postcode":"95030",
    "sg:province":"CA",
    "sg:tags":[
        "instruction",
        "yoga"
    ],
    "sg:website":"www.yogacenterlosgatos.com",
    "wof:name":"Yoga Center of Los Gatos",
    "wof:placetype":"venue"
},
  "geometry": {"coordinates":[-121.983479,37.22193],"type":"Point"}
}