{
  "type": "Feature",
  "properties": {
    "addr:full":"1145 W Coronado St Upland CA 91786",
    "addr:housenumber":"1145",
    "addr:postcode":"91786",
    "addr:street":"W Coronado St",
    "iso:country":"US",
    "sg:address":"1145 W Coronado St",
    "sg:city":"Upland",
    "sg:classifiers":[
        {
            "category":"Professional",
            "type":"Services"
        }
    ],
    "sg:phone":"+1 909 982 8201",
    "sg:postcode":"91786",
    "sg:province":"CA",
    "wof:name":"Mark Fields",
    "wof:placetype":"venue"
},
  "geometry": {"coordinates":[-117.668142,34.118769],"type":"Point"}
}