{
  "type": "Feature",
  "properties": {
    "iso:country":"US",
    "sg:address":"1848 W Florence Ave",
    "sg:city":"Los Angeles",
    "sg:classifiers":[
        {
            "category":"Wholesale",
            "subcategory":"Groceries",
            "type":"Manufacturing & Wholesale Goods"
        }
    ],
    "sg:phone":"+1 323 752 2391",
    "sg:postcode":"90047",
    "sg:province":"CA",
    "sg:tags":[
        "bakery",
        "baker"
    ],
    "wof:name":"Lupita's Bakery Inc",
    "wof:placetype":"venue"
},
  "geometry": {"coordinates":[-118.310997,33.974701],"type":"Point"}
}