{
  "type": "Feature",
  "properties": {
    "addr:full":"804 Harbor Blvd West Sacramento CA 95691",
    "addr:housenumber":"804",
    "addr:postcode":"95691",
    "addr:street":"Harbor Blvd",
    "iso:country":"US",
    "sg:address":"804 Harbor Blvd",
    "sg:city":"West Sacramento",
    "sg:classifiers":[
        {
            "category":"Health Services",
            "subcategory":"Doctor",
            "type":"Services"
        }
    ],
    "sg:phone":"+1 916 375 0720",
    "sg:postcode":"95691",
    "sg:province":"CA",
    "sg:tags":[
        "physician",
        "surgeon"
    ],
    "wof:name":"Harbor Medical Clinic",
    "wof:placetype":"venue"
},
  "geometry": {"coordinates":[-121.548785,38.577422],"type":"Point"}
}