{
  "type": "Feature",
  "properties": {
    "addr:full":"4623 Quail Lakes Dr Stockton CA 95207",
    "addr:housenumber":"4623",
    "addr:postcode":"95207",
    "addr:street":"Quail Lakes Dr",
    "iso:country":"US",
    "sg:address":"4623 Quail Lakes Dr",
    "sg:city":"Stockton",
    "sg:classifiers":[
        {
            "category":"Health Services",
            "subcategory":"Health Practitioner",
            "type":"Services"
        }
    ],
    "sg:phone":"+1 209 951 6491",
    "sg:postcode":"95207",
    "sg:province":"CA",
    "sg:tags":[
        "audiologists"
    ],
    "wof:name":"Stockton Hearing & Speech Ctr",
    "wof:placetype":"venue"
},
  "geometry": {"coordinates":[-121.34022400000001,37.987307],"type":"Point"}
}