{
  "type": "Feature",
  "properties": {
    "addr:full":"1924 Hacienda Dr Vista CA 92081",
    "addr:housenumber":"1924",
    "addr:postcode":"92081",
    "addr:street":"Hacienda Dr",
    "iso:country":"US",
    "sg:address":"1924 Hacienda Dr",
    "sg:city":"Vista",
    "sg:classifiers":[
        {
            "category":"Shopping",
            "subcategory":"Luggage & Leather Goods",
            "type":"Retail Goods"
        }
    ],
    "sg:phone":"+1 760 758 2310",
    "sg:postcode":"92081",
    "sg:province":"CA",
    "wof:name":"Price Mart",
    "wof:placetype":"venue"
},
  "geometry": {"coordinates":[-117.28198999999999,33.186373],"type":"Point"}
}