{
  "type": "Feature",
  "properties": {
    "addr:full":"142 Cinnabar Way Hercules CA 94547",
    "addr:housenumber":"142",
    "addr:postcode":"94547",
    "addr:street":"Cinnabar Way",
    "iso:country":"US",
    "sg:address":"142 Cinnabar Way",
    "sg:city":"Hercules",
    "sg:classifiers":[
        {
            "category":"Travel",
            "subcategory":"Travel Agent",
            "type":"Entertainment"
        }
    ],
    "sg:phone":"+1 510 799 9366",
    "sg:postcode":"94547",
    "sg:province":"CA",
    "sg:tags":[
        "agency",
        "bureau"
    ],
    "wof:name":"Universal USA Travel & Tour",
    "wof:placetype":"venue"
},
  "geometry": {"coordinates":[-122.27559100000001,38.005249],"type":"Point"}
}