{
  "type": "Feature",
  "properties": {
    "iso:country":"US",
    "sg:address":"1998 Republic Ave",
    "sg:city":"San Leandro",
    "sg:classifiers":[
        {
            "category":"Manufacturing",
            "subcategory":"Printing",
            "type":"Manufacturing & Wholesale Goods"
        }
    ],
    "sg:phone":"+1 510 351 7705",
    "sg:postcode":"94577",
    "sg:province":"CA",
    "sg:tags":[
        "printer"
    ],
    "sg:website":"www.gica.com",
    "wof:name":"Specialty Graphics Inc",
    "wof:placetype":"venue"
},
  "geometry": {"coordinates":[-122.17035,37.705059],"type":"Point"}
}