{
  "type": "Feature",
  "properties": {
    "addr:full":"7469 Palmetto Ave Fontana CA 92336",
    "addr:housenumber":"7469",
    "addr:postcode":"92336",
    "addr:street":"Palmetto Ave",
    "iso:country":"US",
    "sg:address":"7469 Palmetto Ave",
    "sg:city":"Fontana",
    "sg:classifiers":[
        {
            "category":"Building & Trades",
            "subcategory":"Landscaping Services",
            "type":"Services"
        }
    ],
    "sg:phone":"+1 909 823 2677",
    "sg:postcode":"92336",
    "sg:province":"CA",
    "sg:tags":[
        "heavy",
        "construction"
    ],
    "wof:name":"A-A Custom Groundskeeping",
    "wof:placetype":"venue"
},
  "geometry": {"coordinates":[-117.427087,34.118694],"type":"Point"}
}