{
  "type": "Feature",
  "properties": {
    "addr:full":"1336 Ridgewood Dr Eureka CA 95503",
    "addr:housenumber":"1336",
    "addr:postcode":"95503",
    "addr:street":"Ridgewood Dr",
    "iso:country":"US",
    "sg:address":"1336 Ridgewood Dr",
    "sg:city":"Eureka",
    "sg:classifiers":[
        {
            "category":"Real Estate",
            "subcategory":"Real Estate Services",
            "type":"Services"
        }
    ],
    "sg:phone":"+1 707 444 3153",
    "sg:postcode":"95503",
    "sg:province":"CA",
    "sg:tags":[
        "management"
    ],
    "wof:name":"Edward W Holland",
    "wof:placetype":"venue"
},
  "geometry": {"coordinates":[-124.161182,40.734392],"type":"Point"}
}