{
  "type": "Feature",
  "properties": {
    "addr:full":"17600 S Santa Fe Ave Compton CA 90221",
    "addr:housenumber":"17600",
    "addr:postcode":"90221",
    "addr:street":"S Santa Fe Ave",
    "iso:country":"US",
    "sg:address":"17600 S Santa Fe Ave",
    "sg:city":"Compton",
    "sg:classifiers":[
        {
            "category":"Government",
            "subcategory":"Office",
            "type":"Public Place"
        }
    ],
    "sg:phone":"+1 310 761 2263",
    "sg:postcode":"90221",
    "sg:province":"CA",
    "sg:tags":[
        "general"
    ],
    "wof:name":"Dpss",
    "wof:placetype":"venue"
},
  "geometry": {"coordinates":[-118.21316899999999,33.869302],"type":"Point"}
}