{
  "type": "Feature",
  "properties": {
    "addr:full":"3415 S San Pedro St Los Angeles CA 90011",
    "addr:housenumber":"3415",
    "addr:postcode":"90011",
    "addr:street":"S San Pedro St",
    "iso:country":"US",
    "sg:address":"3415 S San Pedro St",
    "sg:city":"Los Angeles",
    "sg:classifiers":[
        {
            "category":"Home & Garden",
            "subcategory":"Building Materials",
            "type":"Retail Goods"
        }
    ],
    "sg:phone":"+1 323 750 3710",
    "sg:postcode":"90011",
    "sg:province":"CA",
    "sg:tags":[
        "installs",
        "glass",
        "frame",
        "door",
        "windows"
    ],
    "wof:name":"United Glass and Metal",
    "wof:placetype":"venue"
},
  "geometry": {"coordinates":[-118.26581,34.014657],"type":"Point"}
}