{
  "type": "Feature",
  "properties": {
    "addr:full":"28605 County Road 104 Davis CA 95618",
    "addr:housenumber":"28605",
    "addr:postcode":"95618",
    "addr:street":"County Road 104",
    "iso:country":"US",
    "sg:address":"28605 County Road 104",
    "sg:city":"Davis",
    "sg:classifiers":[
        {
            "category":"Banks & Credit Unions",
            "subcategory":"Financial Services",
            "type":"Services"
        }
    ],
    "sg:phone":"+1 530 753 2116",
    "sg:postcode":"95618",
    "sg:province":"CA",
    "sg:tags":[
        "card-merchant"
    ],
    "sg:website":"http://www.americanexpress.com",
    "wof:name":"American Express",
    "wof:placetype":"venue"
},
  "geometry": {"coordinates":[-121.695121,38.523786],"type":"Point"}
}