{
  "type": "Feature",
  "properties": {
    "addr:full":"1206 N Texas St Fairfield CA 94533",
    "addr:housenumber":"1206",
    "addr:postcode":"94533",
    "addr:street":"N Texas St",
    "iso:country":"US",
    "sg:address":"1206 N Texas St",
    "sg:city":"Fairfield",
    "sg:classifiers":[
        {
            "category":"Autos & Motor Vehicles",
            "subcategory":"Automobile Sales",
            "type":"Retail Goods"
        }
    ],
    "sg:phone":"+1 707 422 9321",
    "sg:postcode":"94533",
    "sg:province":"CA",
    "sg:tags":[
        "car",
        "dealer"
    ],
    "wof:name":"Tod's Fine Cars",
    "wof:placetype":"venue"
},
  "geometry": {"coordinates":[-122.03411699999999,38.253066],"type":"Point"}
}