{
  "type": "Feature",
  "properties": {
    "addr:full":"9401 Waples St San Diego CA 92121",
    "addr:housenumber":"9401",
    "addr:postcode":"92121",
    "addr:street":"Waples St",
    "iso:country":"US",
    "sg:address":"9401 Waples St",
    "sg:city":"San Diego",
    "sg:classifiers":[
        {
            "category":"Manufacturing",
            "subcategory":"Printing",
            "type":"Manufacturing & Wholesale Goods"
        }
    ],
    "sg:phone":"+1 858 558 5270",
    "sg:postcode":"92121",
    "sg:province":"CA",
    "sg:tags":[
        "screen",
        "mfg",
        "commercial",
        "trimming"
    ],
    "sg:website":"www.madengine.com",
    "wof:name":"Mad Engine Inc",
    "wof:placetype":"venue"
},
  "geometry": {"coordinates":[-117.184718,32.901561],"type":"Point"}
}