{
  "type": "Feature",
  "properties": {
    "iso:country":"US",
    "sg:address":"5095 Telegraph Ave Ste C",
    "sg:city":"Oakland",
    "sg:classifiers":[
        {
            "category":"Shopping",
            "subcategory":"Clothing, Apparel, & Fashions",
            "type":"Retail Goods"
        },
        {
            "category":"Wholesale",
            "subcategory":"Stationery",
            "type":"Manufacturing & Wholesale Goods"
        },
        {
            "category":"Shopping",
            "subcategory":"Used Merchandise",
            "type":"Retail Goods"
        }
    ],
    "sg:phone":"+1 510 595 5325",
    "sg:postcode":"94609",
    "sg:province":"CA",
    "sg:tags":[
        "vintage",
        "children's",
        "consignment",
        "clothing",
        "card"
    ],
    "sg:website":"www.rubysgarden.com",
    "wof:name":"Ruby's Garden Local-Grown Kidwear",
    "wof:placetype":"venue"
},
  "geometry": {"coordinates":[-122.26243700000001,37.837156],"type":"Point"}
}