{
  "type": "Feature",
  "properties": {
    "addr:full":"6381 Hollywood Blvd Los Angeles CA 90028",
    "addr:housenumber":"6381",
    "addr:postcode":"90028",
    "addr:street":"Hollywood Blvd",
    "iso:country":"US",
    "sg:address":"6381 Hollywood Blvd",
    "sg:city":"Los Angeles",
    "sg:classifiers":[
        {
            "category":"Real Estate",
            "subcategory":"Real Estate Agent",
            "type":"Services"
        }
    ],
    "sg:phone":"+1 323 467 4444",
    "sg:postcode":"90028",
    "sg:province":"CA",
    "wof:name":"VIP Group",
    "wof:placetype":"venue"
},
  "geometry": {"coordinates":[-118.329277,34.101681],"type":"Point"}
}