{
  "type": "Feature",
  "properties": {
    "iso:country":"US",
    "sg:address":"2649 Mission St",
    "sg:city":"San Francisco",
    "sg:classifiers":[
        {
            "category":"Travel",
            "subcategory":"Travel Agent",
            "type":"Entertainment"
        }
    ],
    "sg:phone":"+1 415 826 8100",
    "sg:postcode":"94110",
    "sg:province":"CA",
    "sg:website":"ImperialTravelService.com",
    "wof:name":"Imperial Travel Service",
    "wof:placetype":"venue"
},
  "geometry": {"coordinates":[-122.418713,37.754593],"type":"Point"}
}