{
  "type": "Feature",
  "properties": {
    "iso:country":"US",
    "sg:address":"356 Hartz Ave",
    "sg:city":"Danville",
    "sg:classifiers":[
        {
            "category":"Restaurant",
            "type":"Food & Drink"
        }
    ],
    "sg:phone":"+1 925 552 6676",
    "sg:postcode":"94526",
    "sg:province":"CA",
    "wof:name":"Norms Place",
    "wof:placetype":"venue"
},
  "geometry": {"coordinates":[-122.00026200000001,37.822079],"type":"Point"}
}