{
  "type": "Feature",
  "properties": {
    "addr:full":"5101 53rd Ave Sacramento CA 95823",
    "addr:housenumber":"5101",
    "addr:postcode":"95823",
    "addr:street":"53Rd Ave",
    "iso:country":"US",
    "sg:address":"5101 53rd Ave",
    "sg:city":"Sacramento",
    "sg:classifiers":[
        {
            "category":"Manufacturing",
            "subcategory":"Metals",
            "type":"Manufacturing & Wholesale Goods"
        }
    ],
    "sg:phone":"+1 916 230 3358",
    "sg:postcode":"95823",
    "sg:province":"CA",
    "wof:name":"Mike's Mobile Plating",
    "wof:placetype":"venue"
},
  "geometry": {"coordinates":[-121.44297,38.503495],"type":"Point"}
}