{
  "type": "Feature",
  "properties": {
    "addr:full":"355 S Western Ave Los Angeles CA 90020",
    "addr:housenumber":"355",
    "addr:postcode":"90020",
    "addr:street":"S Western Ave",
    "iso:country":"US",
    "sg:address":"355 S Western Ave",
    "sg:city":"Los Angeles",
    "sg:classifiers":[
        {
            "category":"Shopping",
            "subcategory":"Books",
            "type":"Retail Goods"
        }
    ],
    "sg:phone":"+1 213 739 2021",
    "sg:postcode":"90020",
    "sg:province":"CA",
    "sg:tags":[
        "comic"
    ],
    "wof:name":"California Comic",
    "wof:placetype":"venue"
},
  "geometry": {"coordinates":[-118.308998,34.067902],"type":"Point"}
}