{
  "type": "Feature",
  "properties": {
    "addr:full":"2339 Gold Meadow Way Gold River CA 95670",
    "addr:housenumber":"2339",
    "addr:postcode":"95670",
    "addr:street":"Gold Meadow Way",
    "iso:country":"US",
    "sg:address":"2339 Gold Meadow Way",
    "sg:city":"Gold River",
    "sg:classifiers":[
        {
            "category":"Professional",
            "subcategory":"Lawyer & Legal Services",
            "type":"Services"
        }
    ],
    "sg:phone":"+1 916 859 4910",
    "sg:postcode":"95670",
    "sg:province":"CA",
    "sg:tags":[
        "personal",
        "injury"
    ],
    "wof:name":"Brown Adam C Attorney At Law",
    "wof:placetype":"venue"
},
  "geometry": {"coordinates":[-121.262001,38.622898],"type":"Point"}
}