{
  "type": "Feature",
  "properties": {
    "iso:country":"US",
    "sg:address":"9602 Las Tunas Dr",
    "sg:city":"Temple City",
    "sg:classifiers":[
        {
            "category":"Travel",
            "subcategory":"Travel Agent",
            "type":"Entertainment"
        }
    ],
    "sg:phone":"+1 626 285 4830",
    "sg:postcode":"91780",
    "sg:province":"CA",
    "sg:tags":[
        "agency",
        "bureau"
    ],
    "wof:name":"India West Travel & Appliances",
    "wof:placetype":"venue"
},
  "geometry": {"coordinates":[-118.059503,34.1068],"type":"Point"}
}