{
  "type": "Feature",
  "properties": {
    "addr:full":"231 S Peach Ave Fresno CA 93727",
    "addr:housenumber":"231",
    "addr:postcode":"93727",
    "addr:street":"S Peach Ave",
    "iso:country":"US",
    "sg:address":"231 S Peach Ave",
    "sg:city":"Fresno",
    "sg:classifiers":[
        {
            "category":"Farming",
            "subcategory":"Farm",
            "type":"Manufacturing & Wholesale Goods"
        }
    ],
    "sg:phone":"+1 559 455 1124",
    "sg:postcode":"93727",
    "sg:province":"CA",
    "wof:name":"Michael Moua",
    "wof:placetype":"venue"
},
  "geometry": {"coordinates":[-119.718209,36.74115],"type":"Point"}
}