{
  "type": "Feature",
  "properties": {
    "iso:country":"US",
    "sg:address":"78450 Ave 41",
    "sg:city":"Bermuda Dunes",
    "sg:classifiers":[
        {
            "category":"Building & Trades",
            "subcategory":"Construction",
            "type":"Services"
        }
    ],
    "sg:phone":"+1 760 772 8446",
    "sg:postcode":"92203",
    "sg:province":"CA",
    "sg:tags":[
        "contractor"
    ],
    "wof:name":"Doug Wall Construction Inc",
    "wof:placetype":"venue"
},
  "geometry": {"coordinates":[-116.29795300000001,33.751032],"type":"Point"}
}