{
  "type": "Feature",
  "properties": {
    "iso:country":"US",
    "sg:address":"302 E 5th Ave",
    "sg:city":"San Mateo",
    "sg:classifiers":[
        {
            "category":"Shopping",
            "subcategory":"Optical Goods",
            "type":"Retail Goods"
        }
    ],
    "sg:phone":"+1 650 342 3562",
    "sg:postcode":"94402",
    "sg:province":"CA",
    "sg:tags":[
        "optician"
    ],
    "wof:name":"Johnsen & Bruun Opticians",
    "wof:placetype":"venue"
},
  "geometry": {"coordinates":[-122.320243,37.56449],"type":"Point"}
}