{
  "type": "Feature",
  "properties": {
    "addr:full":"2036 Broadway St Eureka CA 95501",
    "addr:housenumber":"2036",
    "addr:postcode":"95501",
    "addr:street":"Broadway St",
    "iso:country":"US",
    "sg:address":"2036 Broadway St",
    "sg:city":"Eureka",
    "sg:classifiers":[
        {
            "category":"Retail",
            "subcategory":"Auto Repair",
            "type":"Services"
        }
    ],
    "sg:phone":"+1 707 443 4467",
    "sg:postcode":"95501",
    "sg:province":"CA",
    "sg:tags":[
        "repairing",
        "automobile"
    ],
    "wof:name":"Antich Automotive",
    "wof:placetype":"venue"
},
  "geometry": {"coordinates":[-124.179433,40.789574],"type":"Point"}
}