{
  "type": "Feature",
  "properties": {
    "addr:full":"1503 E Abila St Carson CA 90745",
    "addr:housenumber":"1503",
    "addr:postcode":"90745",
    "addr:street":"E Abila St",
    "iso:country":"US",
    "sg:address":"1503 E Abila St",
    "sg:city":"Carson",
    "sg:classifiers":[
        {
            "category":"Personal",
            "subcategory":"Beauty Salon",
            "type":"Services"
        }
    ],
    "sg:phone":"+1 310 835 1202",
    "sg:postcode":"90745",
    "sg:province":"CA",
    "wof:name":"Hair Plus Nails Boutique",
    "wof:placetype":"venue"
},
  "geometry": {"coordinates":[-118.244118,33.828755],"type":"Point"}
}