{
  "type": "Feature",
  "properties": {
    "iso:country":"US",
    "sg:address":"209 West Grand Ave",
    "sg:city":"El Segundo",
    "sg:classifiers":[
        {
            "category":"Sports & Exercise",
            "subcategory":"Gym",
            "type":"Entertainment"
        }
    ],
    "sg:phone":"+1 310 414 8180",
    "sg:postcode":"90245",
    "sg:province":"CA",
    "sg:tags":[
        "pilate"
    ],
    "wof:name":"Studio Pilates",
    "wof:placetype":"venue"
},
  "geometry": {"coordinates":[-118.41761200000001,33.919069],"type":"Point"}
}