{
  "type": "Feature",
  "properties": {
    "iso:country":"US",
    "sg:address":"5775 E Los Angeles Ave",
    "sg:city":"Simi Valley",
    "sg:classifiers":[
        {
            "category":"Professional",
            "subcategory":"Management & Consulting",
            "type":"Services"
        }
    ],
    "sg:phone":"+1 805 581 5791",
    "sg:postcode":"93063",
    "sg:province":"CA",
    "sg:tags":[
        "marketing",
        "consultant"
    ],
    "sg:website":"www.thewrightco.com",
    "wof:name":"Wright Co",
    "wof:placetype":"venue"
},
  "geometry": {"coordinates":[-118.67994899999999,34.271805],"type":"Point"}
}