{
  "type": "Feature",
  "properties": {
    "addr:full":"221 W Crest St Escondido CA 92025",
    "addr:housenumber":"221",
    "addr:postcode":"92025",
    "addr:street":"W Crest St",
    "iso:country":"US",
    "sg:address":"221 W Crest St",
    "sg:city":"Escondido",
    "sg:classifiers":[
        {
            "category":"Real Estate",
            "subcategory":"Real Estate Agent",
            "type":"Services"
        }
    ],
    "sg:phone":"+1 760 737 0222",
    "sg:postcode":"92025",
    "sg:province":"CA",
    "wof:name":"Klose 2 Home",
    "wof:placetype":"venue"
},
  "geometry": {"coordinates":[-117.087745,33.131065],"type":"Point"}
}