{
  "type": "Feature",
  "properties": {
    "addr:full":"1045 Whitley Ave Corcoran CA 93212",
    "addr:housenumber":"1045",
    "addr:postcode":"93212",
    "addr:street":"Whitley Ave",
    "iso:country":"US",
    "sg:address":"1045 Whitley Ave",
    "sg:city":"Corcoran",
    "sg:classifiers":[
        {
            "category":"Banks & Credit Unions",
            "subcategory":"Bank",
            "type":"Services"
        }
    ],
    "sg:phone":"+1 559 992 5136",
    "sg:postcode":"93212",
    "sg:province":"CA",
    "wof:name":"Bank Of The West",
    "wof:placetype":"venue"
},
  "geometry": {"coordinates":[-119.56053300000001,36.097965],"type":"Point"}
}