{
  "type": "Feature",
  "properties": {
    "addr:full":"9865 E Avenue Q Q6 Palmdale CA 93591",
    "addr:housenumber":"9865",
    "addr:postcode":"ca 93591",
    "addr:street":"E Avenue Q Q6",
    "iso:country":"US",
    "sg:address":"9865 E Avenue Q Q6",
    "sg:city":"Palmdale",
    "sg:classifiers":[
        {
            "category":"Building & Trades",
            "subcategory":"Construction",
            "type":"Services"
        }
    ],
    "sg:phone":"+1 661 944 4151",
    "sg:postcode":"93591",
    "sg:province":"CA",
    "sg:tags":[
        "plastering",
        "contractor"
    ],
    "wof:name":"Castillo Plastering",
    "wof:placetype":"venue"
},
  "geometry": {"coordinates":[-117.95358299999999,34.587074],"type":"Point"}
}