{
  "type": "Feature",
  "properties": {
    "iso:country":"US",
    "sg:address":"2258 W Winton Ave",
    "sg:city":"Hayward",
    "sg:classifiers":[
        {
            "category":"Freight",
            "type":"Transportation"
        }
    ],
    "sg:phone":"+1 510 786 9075",
    "sg:postcode":"94545",
    "sg:province":"CA",
    "sg:tags":[
        "arrangement"
    ],
    "wof:name":"Kintetsu World Express",
    "wof:placetype":"venue"
},
  "geometry": {"coordinates":[-122.135952,37.652803],"type":"Point"}
}