{
  "type": "Feature",
  "properties": {
    "addr:full":"600 S D St Perris CA 92570",
    "addr:housenumber":"600",
    "addr:postcode":"92570",
    "addr:street":"S D St",
    "iso:country":"US",
    "sg:address":"600 S D St",
    "sg:city":"Perris",
    "sg:classifiers":[
        {
            "category":"Organizations",
            "subcategory":"Community Association",
            "type":"Services"
        }
    ],
    "sg:phone":"+1 951 657 6275",
    "sg:postcode":"92570",
    "sg:province":"CA",
    "sg:tags":[
        "military"
    ],
    "wof:name":"American Legion",
    "wof:placetype":"venue"
},
  "geometry": {"coordinates":[-117.228679,33.781332],"type":"Point"}
}