{
  "type": "Feature",
  "properties": {
    "iso:country":"US",
    "sg:address":"2025 28th St",
    "sg:city":"Sacramento",
    "sg:classifiers":[
        {
            "category":"Real Estate",
            "subcategory":"Real Estate Operator",
            "type":"Services"
        }
    ],
    "sg:phone":"+1 916 451 1601",
    "sg:postcode":"95818",
    "sg:province":"CA",
    "sg:tags":[
        "apartment"
    ],
    "wof:name":"Elms the",
    "wof:placetype":"venue"
},
  "geometry": {"coordinates":[-121.47399900000001,38.5625],"type":"Point"}
}