{
  "type": "Feature",
  "properties": {
    "iso:country":"US",
    "sg:address":"1868 Arrow Hwy",
    "sg:city":"La Verne",
    "sg:classifiers":[
        {
            "category":"Building & Trades",
            "subcategory":"Electrical",
            "type":"Services"
        }
    ],
    "sg:phone":"+1 909 447 8160",
    "sg:postcode":"91750",
    "sg:province":"CA",
    "sg:tags":[
        "electrical",
        "contractor"
    ],
    "wof:name":"Proactive Electric",
    "wof:placetype":"venue"
},
  "geometry": {"coordinates":[-117.776557,34.099068],"type":"Point"}
}