{
  "type": "Feature",
  "properties": {
    "addr:full":"1290 Las Flores Dr Carlsbad CA 92008",
    "addr:housenumber":"1290",
    "addr:postcode":"92008",
    "addr:street":"Las Flores Dr",
    "iso:country":"US",
    "sg:address":"1290 Las Flores Dr",
    "sg:city":"Carlsbad",
    "sg:classifiers":[
        {
            "category":"Food & Beverages",
            "subcategory":"Liquor & Beverages",
            "type":"Retail Goods"
        },
        {
            "category":"Food & Beverages",
            "subcategory":"Groceries & Convenience Stores",
            "type":"Retail Goods"
        }
    ],
    "sg:phone":"+1 760 434 1691",
    "sg:postcode":"92008",
    "sg:province":"CA",
    "sg:tags":[
        "juice",
        "bottler",
        "beverages-distributors"
    ],
    "wof:name":"Juice Plus",
    "wof:placetype":"venue"
},
  "geometry": {"coordinates":[-117.344533,33.17067],"type":"Point"}
}