{
  "type": "Feature",
  "properties": {
    "iso:country":"US",
    "sg:address":"2345 Erringer Rd",
    "sg:city":"Simi Valley",
    "sg:classifiers":[
        {
            "category":"Insurance",
            "subcategory":"Insurance Agent",
            "type":"Services"
        }
    ],
    "sg:phone":"+1 805 584 2400",
    "sg:postcode":"93065",
    "sg:province":"CA",
    "wof:name":"Farmers Insurance",
    "wof:placetype":"venue"
},
  "geometry": {"coordinates":[-118.761439,34.277363],"type":"Point"}
}