{
  "type": "Feature",
  "properties": {
    "iso:country":"US",
    "sg:address":"10642 Westminster Ave",
    "sg:city":"Garden Grove",
    "sg:classifiers":[
        {
            "category":"Restaurant",
            "type":"Food & Drink"
        }
    ],
    "sg:phone":"+1 714 537 4920",
    "sg:postcode":"92843",
    "sg:province":"CA",
    "sg:tags":[
        "chinese"
    ],
    "wof:name":"Wong's Restaurant",
    "wof:placetype":"venue"
},
  "geometry": {"coordinates":[-117.943001,33.759499],"type":"Point"}
}