{
  "type": "Feature",
  "properties": {
    "addr:full":"2186 Granite Dr Alamo CA 94507",
    "addr:housenumber":"2186",
    "addr:postcode":"94507",
    "addr:street":"Granite Dr",
    "iso:country":"US",
    "sg:address":"2186 Granite Dr",
    "sg:city":"Alamo",
    "sg:classifiers":[
        {
            "category":"Professional",
            "subcategory":"Engineering",
            "type":"Services"
        }
    ],
    "sg:phone":"+1 925 838 0569",
    "sg:postcode":"94507",
    "sg:province":"CA",
    "sg:tags":[
        "engineer"
    ],
    "wof:name":"Christian Perez Consulting",
    "wof:placetype":"venue"
},
  "geometry": {"coordinates":[-122.016514,37.859543],"type":"Point"}
}