{
  "type": "Feature",
  "properties": {
    "addr:full":"522 105th Ave Oakland CA 94603",
    "addr:housenumber":"522",
    "addr:postcode":"94603",
    "addr:street":"105Th Ave",
    "iso:country":"US",
    "sg:address":"522 105th Ave",
    "sg:city":"Oakland",
    "sg:classifiers":[
        {
            "category":"Home & Garden",
            "subcategory":"Garden Supply",
            "type":"Retail Goods"
        }
    ],
    "sg:phone":"+1 510 568 5498",
    "sg:postcode":"94603",
    "sg:province":"CA",
    "sg:tags":[
        "landscaping",
        "equipment"
    ],
    "wof:name":"Sau, Samiuela",
    "wof:placetype":"venue"
},
  "geometry": {"coordinates":[-122.17951499999999,37.731419],"type":"Point"}
}