{
  "type": "Feature",
  "properties": {
    "addr:full":"129 S Western Ave Los Angeles CA 90004",
    "addr:housenumber":"129",
    "addr:postcode":"90004",
    "addr:street":"S Western Ave",
    "iso:country":"US",
    "sg:address":"129 S Western Ave",
    "sg:city":"Los Angeles",
    "sg:classifiers":[
        {
            "category":"Shopping",
            "subcategory":"Antiques",
            "type":"Retail Goods"
        }
    ],
    "sg:phone":"+1 213 385 2595",
    "sg:postcode":"90004",
    "sg:province":"CA",
    "wof:name":"Inner Vision Antiques",
    "wof:placetype":"venue"
},
  "geometry": {"coordinates":[-118.308998,34.073002],"type":"Point"}
}