{
  "type": "Feature",
  "properties": {
    "addr:full":"3900 Sisk Rd Modesto CA 95356",
    "addr:housenumber":"3900",
    "addr:postcode":"ca 95356",
    "addr:street":"Sisk Rd",
    "iso:country":"US",
    "sg:address":"3900 Sisk Rd",
    "sg:city":"Modesto",
    "sg:classifiers":[
        {
            "category":"Shopping",
            "subcategory":"Books",
            "type":"Retail Goods"
        }
    ],
    "sg:phone":"+1 209 543 6095",
    "sg:postcode":"95356",
    "sg:province":"CA",
    "sg:tags":[
        "dealer"
    ],
    "wof:name":"Borders Books Music & Cafe",
    "wof:placetype":"venue"
},
  "geometry": {"coordinates":[-121.06899799999999,37.698142],"type":"Point"}
}