{
  "type": "Feature",
  "properties": {
    "iso:country":"US",
    "sg:address":"443 E San Ysidro Blvd",
    "sg:city":"San Ysidro",
    "sg:classifiers":[
        {
            "category":"Retail",
            "subcategory":"Repair Shop",
            "type":"Services"
        }
    ],
    "sg:phone":"+1 619 662 9744",
    "sg:postcode":"92173",
    "sg:province":"CA",
    "sg:tags":[
        "jewelry"
    ],
    "wof:name":"Soto's Jewelry",
    "wof:placetype":"venue"
},
  "geometry": {"coordinates":[-117.03765300000001,32.550685],"type":"Point"}
}