{
  "type": "Feature",
  "properties": {
    "addr:full":"2580 Senter Rd San Jose CA 95111",
    "addr:postcode":"2580;95111",
    "addr:street":"Senter Rd",
    "iso:country":"US",
    "sg:address":"2580 Senter Rd",
    "sg:city":"San Jose",
    "sg:classifiers":[
        {
            "category":"Building & Trades",
            "subcategory":"Landscaping Services",
            "type":"Services"
        }
    ],
    "sg:phone":"+1 408 295 3695",
    "sg:postcode":"95111",
    "sg:province":"CA",
    "sg:website":"www.castellolandco.com",
    "wof:name":"Castello Landscape Construction",
    "wof:placetype":"venue"
},
  "geometry": {"coordinates":[-121.84278500000001,37.307033],"type":"Point"}
}