{
  "type": "Feature",
  "properties": {
    "addr:full":"14777 Colter Way Magalia CA 95954",
    "addr:housenumber":"14777",
    "addr:postcode":"95954",
    "addr:street":"Colter Way",
    "iso:country":"US",
    "sg:address":"14777 Colter Way",
    "sg:city":"Magalia",
    "sg:classifiers":[
        {
            "category":"Retail",
            "subcategory":"Laundry & Dry Cleaning",
            "type":"Services"
        }
    ],
    "sg:phone":"+1 530 873 9700",
    "sg:postcode":"95954",
    "sg:province":"CA",
    "sg:tags":[
        "cleaners",
        "rug",
        "carpet"
    ],
    "wof:name":"Carpet Masters Carpet",
    "wof:placetype":"venue"
},
  "geometry": {"coordinates":[-121.60638,39.846196],"type":"Point"}
}