{
  "type": "Feature",
  "properties": {
    "iso:country":"US",
    "sg:address":"1950 Villa Ave",
    "sg:city":"El Centro",
    "sg:classifiers":[
        {
            "category":"Education",
            "subcategory":"School",
            "type":"Public Place"
        }
    ],
    "sg:phone":"+1 760 337 6555",
    "sg:postcode":"92243",
    "sg:province":"CA",
    "sg:website":"www.ecsd.k12.ca.us",
    "wof:name":"King Elementary School",
    "wof:placetype":"venue"
},
  "geometry": {"coordinates":[-115.578643,32.803652],"type":"Point"}
}