{
  "type": "Feature",
  "properties": {
    "iso:country":"US",
    "sg:address":"7472 N Fresno St",
    "sg:city":"Fresno",
    "sg:classifiers":[
        {
            "category":"Health Services",
            "subcategory":"Chiropractor",
            "type":"Services"
        }
    ],
    "sg:phone":"+1 559 435 2225",
    "sg:postcode":"93720",
    "sg:province":"CA",
    "sg:tags":[
        "chiropractic"
    ],
    "wof:name":"Woodward Park Accident & Injury Center",
    "wof:placetype":"venue"
},
  "geometry": {"coordinates":[-119.783689,36.845986],"type":"Point"}
}