{
  "type": "Feature",
  "properties": {
    "addr:full":"5980 Fairmount Ave San Diego CA 92120",
    "addr:housenumber":"5980",
    "addr:postcode":"92120",
    "addr:street":"Fairmount Ave",
    "iso:country":"US",
    "sg:address":"5980 Fairmount Ave",
    "sg:city":"San Diego",
    "sg:classifiers":[
        {
            "category":"Building & Trades",
            "subcategory":"Plumbing",
            "type":"Services"
        }
    ],
    "sg:phone":"+1 619 280 9951",
    "sg:postcode":"92120",
    "sg:province":"CA",
    "sg:tags":[
        "contractor"
    ],
    "wof:name":"Grj Enterprises",
    "wof:placetype":"venue"
},
  "geometry": {"coordinates":[-117.101606,32.78228],"type":"Point"}
}