{
  "type": "Feature",
  "properties": {
    "iso:country":"US",
    "sg:address":"103 W Alameda Ave",
    "sg:city":"Burbank",
    "sg:classifiers":[
        {
            "category":"Building & Trades",
            "subcategory":"Plumbing",
            "type":"Services"
        }
    ],
    "sg:phone":"+1 818 566 1390",
    "sg:postcode":"91502",
    "sg:province":"CA",
    "sg:tags":[
        "contractor"
    ],
    "wof:name":"Number One State Plumbing",
    "wof:placetype":"venue"
},
  "geometry": {"coordinates":[-118.303379,34.171216],"type":"Point"}
}