{
  "type": "Feature",
  "properties": {
    "addr:full":"3654 35th Ave Oakland CA 94619",
    "addr:housenumber":"3654",
    "addr:postcode":"94619",
    "addr:street":"35Th Ave",
    "iso:country":"US",
    "sg:address":"3654 35th Ave",
    "sg:city":"Oakland",
    "sg:classifiers":[
        {
            "category":"Real Estate",
            "subcategory":"Real Estate Services",
            "type":"Services"
        }
    ],
    "sg:phone":"+1 510 531 4600",
    "sg:postcode":"94619",
    "sg:province":"CA",
    "sg:tags":[
        "management",
        "property"
    ],
    "wof:name":"Pay Day Management Co",
    "wof:placetype":"venue"
},
  "geometry": {"coordinates":[-122.19899700000001,37.7943],"type":"Point"}
}