{
  "type": "Feature",
  "properties": {
    "iso:country":"US",
    "sg:address":"3381 Industrial Ave",
    "sg:city":"Rocklin",
    "sg:classifiers":[
        {
            "category":"Freight",
            "type":"Transportation"
        }
    ],
    "sg:phone":"+1 916 748 7765",
    "sg:postcode":"95765",
    "sg:province":"CA",
    "wof:name":"TNT Logistics North America",
    "wof:placetype":"venue"
},
  "geometry": {"coordinates":[-121.307817,38.795245],"type":"Point"}
}