{
  "type": "Feature",
  "properties": {
    "iso:country":"US",
    "sg:address":"1587 Schallenberger Rd",
    "sg:city":"San Jose",
    "sg:classifiers":[
        {
            "category":"Professional",
            "subcategory":"Detective & Security Services",
            "type":"Services"
        }
    ],
    "sg:phone":"+1 408 998 2002",
    "sg:postcode":"95131",
    "sg:province":"CA",
    "sg:tags":[
        "installs",
        "alarm",
        "monitor",
        "system"
    ],
    "wof:name":"Sonitrol",
    "wof:placetype":"venue"
},
  "geometry": {"coordinates":[-121.897059,37.377475],"type":"Point"}
}