{
  "type": "Feature",
  "properties": {
    "addr:full":"331 Soquel Ave Santa Cruz CA 95062",
    "addr:housenumber":"331",
    "addr:postcode":"95062",
    "addr:street":"Soquel Ave",
    "iso:country":"US",
    "sg:address":"331 Soquel Ave",
    "sg:city":"Santa Cruz",
    "sg:classifiers":[
        {
            "category":"Professional",
            "subcategory":"Lawyer & Legal Services",
            "type":"Services"
        }
    ],
    "sg:phone":"+1 831 429 9191",
    "sg:postcode":"95062",
    "sg:province":"CA",
    "sg:tags":[
        "attorney"
    ],
    "wof:name":"Chang & Spencer",
    "wof:placetype":"venue"
},
  "geometry": {"coordinates":[-122.019685,36.974401],"type":"Point"}
}