{
  "type": "Feature",
  "properties": {
    "addr:full":"317 N West St Visalia CA 93291",
    "addr:housenumber":"317",
    "addr:postcode":"93291",
    "addr:street":"N West St",
    "iso:country":"US",
    "sg:address":"317 N West St",
    "sg:city":"Visalia",
    "sg:classifiers":[
        {
            "category":"Wholesale",
            "subcategory":"Fruits & Vegetables",
            "type":"Manufacturing & Wholesale Goods"
        }
    ],
    "sg:phone":"+1 559 741 9707",
    "sg:postcode":"93291",
    "sg:province":"CA",
    "sg:tags":[
        "fresh",
        "produce",
        "broker"
    ],
    "wof:name":"Tradewind Farms Inc",
    "wof:placetype":"venue"
},
  "geometry": {"coordinates":[-119.29669,36.332251],"type":"Point"}
}