{
  "type": "Feature",
  "properties": {
    "iso:country":"US",
    "sg:address":"2780 Skypark Dr",
    "sg:city":"Torrance",
    "sg:classifiers":[
        {
            "category":"Real Estate",
            "subcategory":"Real Estate Agent",
            "type":"Services"
        }
    ],
    "sg:phone":"+1 310 784 2500",
    "sg:postcode":"90505",
    "sg:province":"CA",
    "sg:tags":[
        "re"
    ],
    "wof:name":"Airport Atrium Corp",
    "wof:placetype":"venue"
},
  "geometry": {"coordinates":[-118.335634,33.804489],"type":"Point"}
}