{
  "type": "Feature",
  "properties": {
    "iso:country":"US",
    "sg:address":"2345 Statham Blvd",
    "sg:city":"Oxnard",
    "sg:classifiers":[
        {
            "category":"Home & Garden",
            "subcategory":"Building Materials",
            "type":"Retail Goods"
        }
    ],
    "sg:phone":"+1 805 487 9241",
    "sg:postcode":"93033",
    "sg:province":"CA",
    "wof:name":"Diversified Panel Systems",
    "wof:placetype":"venue"
},
  "geometry": {"coordinates":[-119.165618,34.175478],"type":"Point"}
}