{
  "type": "Feature",
  "properties": {
    "iso:country":"US",
    "sg:address":"2650 Telegraph Ave",
    "sg:city":"Berkeley",
    "sg:classifiers":[
        {
            "category":"Restaurant",
            "type":"Food & Drink"
        }
    ],
    "sg:menulink":"http://www.allmenus.com/ca/berkeley/46580-akasaka-sushi/menu/",
    "sg:phone":"+1 510 841 0444",
    "sg:postcode":"94704",
    "sg:province":"CA",
    "sg:tags":[
        "japanese",
        "asian"
    ],
    "wof:name":"Akasaka Sushi",
    "wof:placetype":"venue"
},
  "geometry": {"coordinates":[-122.25896,37.861944],"type":"Point"}
}