{
  "type": "Feature",
  "properties": {
    "iso:country":"US",
    "sg:address":"1800 L St",
    "sg:city":"Sacramento",
    "sg:classifiers":[
        {
            "category":"Bars & Pubs",
            "type":"Food & Drink"
        },
        {
            "category":"Restaurant",
            "type":"Food & Drink"
        },
        {
            "category":"Organizations",
            "subcategory":"Community Association",
            "type":"Services"
        }
    ],
    "sg:phone":"+1 916 447 9440",
    "sg:postcode":"95811",
    "sg:province":"CA",
    "sg:tags":[
        "club",
        "tapa",
        "spanish",
        "mexican",
        "basque"
    ],
    "wof:name":"Aioli Bodega Espanola",
    "wof:placetype":"venue"
},
  "geometry": {"coordinates":[-121.483487,38.575208],"type":"Point"}
}