{
  "type": "Feature",
  "properties": {
    "addr:full":"1207 E Palmdale Blvd Palmdale CA 93550",
    "addr:housenumber":"1207",
    "addr:postcode":"ca 93550",
    "addr:street":"E Palmdale Blvd",
    "iso:country":"US",
    "sg:address":"1207 E Palmdale Blvd",
    "sg:city":"Palmdale",
    "sg:classifiers":[
        {
            "category":"Shopping",
            "subcategory":"Gifts & Souvenirs",
            "type":"Retail Goods"
        }
    ],
    "sg:phone":"+1 661 265 8874",
    "sg:postcode":"93550",
    "sg:province":"CA",
    "wof:name":"Fiesta Party Supply",
    "wof:placetype":"venue"
},
  "geometry": {"coordinates":[-118.10739700000001,34.57967],"type":"Point"}
}