{
  "type": "Feature",
  "properties": {
    "iso:country":"US",
    "sg:address":"8240 14th Avenue",
    "sg:city":"Sacramento",
    "sg:classifiers":[
        {
            "category":"Personal",
            "type":"Services"
        }
    ],
    "sg:phone":"+1 916 457 4000",
    "sg:postcode":"95826",
    "sg:province":"CA",
    "sg:tags":[
        "towing"
    ],
    "wof:name":"Central Valley Towing",
    "wof:placetype":"venue"
},
  "geometry": {"coordinates":[-121.401668,38.539534],"type":"Point"}
}