{
  "type": "Feature",
  "properties": {
    "addr:full":"12460 Euclid St Garden Grove CA 92840",
    "addr:housenumber":"12460",
    "addr:postcode":"92840",
    "addr:street":"Euclid St",
    "iso:country":"US",
    "sg:address":"12460 Euclid St",
    "sg:city":"Garden Grove",
    "sg:classifiers":[
        {
            "category":"Building & Trades",
            "subcategory":"Plumbing",
            "type":"Services"
        }
    ],
    "sg:phone":"+1 714 534 7774",
    "sg:postcode":"92840",
    "sg:province":"CA",
    "sg:tags":[
        "contractor"
    ],
    "wof:name":"Ram Rooter",
    "wof:placetype":"venue"
},
  "geometry": {"coordinates":[-117.941008,33.782539],"type":"Point"}
}