{
  "type": "Feature",
  "properties": {
    "addr:full":"36 Houston St San Francisco CA 94133",
    "addr:housenumber":"36",
    "addr:postcode":"94133",
    "addr:street":"Houston St",
    "iso:country":"US",
    "sg:address":"36 Houston St",
    "sg:city":"San Francisco",
    "sg:classifiers":[
        {
            "category":"Banks & Credit Unions",
            "subcategory":"Investment Brokerage",
            "type":"Services"
        }
    ],
    "sg:phone":"+1 415 749 2000",
    "sg:postcode":"94133",
    "sg:province":"CA",
    "sg:tags":[
        "consultant",
        "planning",
        "financial"
    ],
    "wof:name":"Silicon Valley Capitol",
    "wof:placetype":"venue"
},
  "geometry": {"coordinates":[-122.41623,37.803935],"type":"Point"}
}