{
  "type": "Feature",
  "properties": {
    "iso:country":"US",
    "sg:address":"2101 Sacramento St Ste 102",
    "sg:city":"San Francisco",
    "sg:classifiers":[
        {
            "category":"Arts & Performance",
            "subcategory":"Art Gallery",
            "type":"Entertainment"
        }
    ],
    "sg:phone":"+1 415 875 9055",
    "sg:postcode":"94109",
    "sg:province":"CA",
    "sg:website":"www.lisadent.com",
    "wof:name":"Lisa Dent Gallery",
    "wof:placetype":"venue"
},
  "geometry": {"coordinates":[-122.427477,37.790707],"type":"Point"}
}