{
  "type": "Feature",
  "properties": {
    "addr:full":"1898 Cherry Ave Long Beach CA 90755",
    "addr:housenumber":"1898",
    "addr:postcode":"90755",
    "addr:street":"Cherry Ave",
    "iso:country":"US",
    "sg:address":"1898 Cherry Ave",
    "sg:city":"Long Beach",
    "sg:classifiers":[
        {
            "category":"Food & Beverages",
            "subcategory":"Liquor & Beverages",
            "type":"Retail Goods"
        }
    ],
    "sg:phone":"+1 562 494 7972",
    "sg:postcode":"90755",
    "sg:province":"CA",
    "sg:tags":[
        "beer",
        "spirit",
        "wine"
    ],
    "wof:name":"Signal Liquor",
    "wof:placetype":"venue"
},
  "geometry": {"coordinates":[-118.167474,33.79166],"type":"Point"}
}