{
  "type": "Feature",
  "properties": {
    "addr:full":"1000 Sunset Pkwy Novato CA 94947",
    "addr:housenumber":"1000",
    "addr:postcode":"94947",
    "addr:street":"Sunset Pkwy",
    "iso:country":"US",
    "sg:address":"1000 Sunset Pkwy",
    "sg:city":"Novato",
    "sg:classifiers":[
        {
            "category":"Education",
            "subcategory":"School",
            "type":"Public Place"
        }
    ],
    "sg:phone":"+1 415 883 7831",
    "sg:postcode":"94947",
    "sg:province":"CA",
    "sg:website":"www.nusd.org",
    "wof:name":"San Jose Middle School",
    "wof:placetype":"venue"
},
  "geometry": {"coordinates":[-122.568279,38.074937],"type":"Point"}
}