{
  "type": "Feature",
  "properties": {
    "iso:country":"US",
    "sg:address":"837 E Ventura St",
    "sg:city":"Santa Paula",
    "sg:classifiers":[
        {
            "category":"Organizations",
            "subcategory":"Religious Organization",
            "type":"Services"
        }
    ],
    "sg:phone":"+1 805 525 8073",
    "sg:postcode":"93060",
    "sg:province":"CA",
    "sg:tags":[
        "church"
    ],
    "wof:name":"Jehovah's Witnesses",
    "wof:placetype":"venue"
},
  "geometry": {"coordinates":[-119.062487,34.351299],"type":"Point"}
}