{
  "type": "Feature",
  "properties": {
    "addr:full":"10033 Saich Way Cupertino CA 95014",
    "addr:housenumber":"10033",
    "addr:postcode":"95014",
    "addr:street":"Saich Way",
    "iso:country":"US",
    "sg:address":"10033 Saich Way",
    "sg:city":"Cupertino",
    "sg:classifiers":[
        {
            "category":"Food & Beverages",
            "subcategory":"Groceries & Convenience Stores",
            "type":"Retail Goods"
        }
    ],
    "sg:phone":"+1 408 255 9515",
    "sg:postcode":"95014",
    "sg:province":"CA",
    "sg:website":"www.7-eleven.com",
    "wof:name":"7-Eleven",
    "wof:placetype":"venue"
},
  "geometry": {"coordinates":[-122.037413,37.324042],"type":"Point"}
}