{
  "type": "Feature",
  "properties": {
    "iso:country":"US",
    "sg:address":"13012 Sunshine Ave",
    "sg:city":"Whittier",
    "sg:classifiers":[
        {
            "category":"Retail",
            "subcategory":"Repair Shop",
            "type":"Services"
        }
    ],
    "sg:phone":"+1 562 944 3038",
    "sg:postcode":"90605",
    "sg:province":"CA",
    "sg:tags":[
        "welding"
    ],
    "wof:name":"Hall's Welding Inc",
    "wof:placetype":"venue"
},
  "geometry": {"coordinates":[-118.053159,33.920777],"type":"Point"}
}