{
  "type": "Feature",
  "properties": {
    "iso:country":"US",
    "sg:address":"5266 N Colonial Ave",
    "sg:city":"Fresno",
    "sg:classifiers":[
        {
            "category":"Banks & Credit Unions",
            "subcategory":"Investment Brokerage",
            "type":"Services"
        }
    ],
    "sg:phone":"+1 559 432 7676",
    "sg:postcode":"93704",
    "sg:province":"CA",
    "wof:name":"North Palm Investment Co",
    "wof:placetype":"venue"
},
  "geometry": {"coordinates":[-119.804171,36.81356],"type":"Point"}
}