{
  "type": "Feature",
  "properties": {
    "addr:full":"215 Masonic Ave San Francisco CA 94118",
    "addr:housenumber":"215",
    "addr:postcode":"94118",
    "addr:street":"Masonic Ave",
    "iso:country":"US",
    "sg:address":"215 Masonic Ave",
    "sg:city":"San Francisco",
    "sg:classifiers":[
        {
            "category":"Wholesale",
            "subcategory":"Toys & Hobbies",
            "type":"Manufacturing & Wholesale Goods"
        }
    ],
    "sg:phone":"+1 415 292 6260",
    "sg:postcode":"94118",
    "sg:province":"CA",
    "wof:name":"Tribal Art Dolls",
    "wof:placetype":"venue"
},
  "geometry": {"coordinates":[-122.447191,37.778821],"type":"Point"}
}