{
  "type": "Feature",
  "properties": {
    "addr:full":"1367 Capitola Rd Santa Cruz CA 95062",
    "addr:housenumber":"1367",
    "addr:postcode":"95062",
    "addr:street":"Capitola Rd",
    "iso:country":"US",
    "sg:address":"1367 Capitola Rd",
    "sg:city":"Santa Cruz",
    "sg:classifiers":[
        {
            "category":"Retail",
            "subcategory":"Animal Services",
            "type":"Services"
        }
    ],
    "sg:phone":"+1 831 462 3235",
    "sg:postcode":"95062",
    "sg:province":"CA",
    "sg:tags":[
        "pet",
        "grooming",
        "washing"
    ],
    "wof:name":"Animal House Dog Cat Grooming",
    "wof:placetype":"venue"
},
  "geometry": {"coordinates":[-121.98558800000001,36.976673],"type":"Point"}
}