{
  "type": "Feature",
  "properties": {
    "iso:country":"US",
    "sg:address":"1200 Creekside Dr",
    "sg:city":"Folsom",
    "sg:classifiers":[
        {
            "category":"Professional",
            "type":"Services"
        }
    ],
    "sg:phone":"+1 916 351 2137",
    "sg:postcode":"95630",
    "sg:province":"CA",
    "wof:name":"Roger Treinen",
    "wof:placetype":"venue"
},
  "geometry": {"coordinates":[-121.15165500000001,38.666764],"type":"Point"}
}