{
  "type": "Feature",
  "properties": {
    "iso:country":"US",
    "sg:address":"10700 S De Anza Blvd",
    "sg:city":"Cupertino",
    "sg:classifiers":[
        {
            "category":"Restaurant",
            "type":"Food & Drink"
        }
    ],
    "sg:phone":"+1 408 252 1797",
    "sg:postcode":"95014",
    "sg:province":"CA",
    "sg:tags":[
        "sushi",
        "bar",
        "japanese"
    ],
    "wof:name":"Yoshida",
    "wof:placetype":"venue"
},
  "geometry": {"coordinates":[-122.031694,37.313071],"type":"Point"}
}