{
  "type": "Feature",
  "properties": {
    "addr:full":"122 S Prospect Ave Redondo Beach CA 90277",
    "addr:housenumber":"122",
    "addr:postcode":"90277",
    "addr:street":"S Prospect Ave",
    "iso:country":"US",
    "sg:address":"122 S Prospect Ave",
    "sg:city":"Redondo Beach",
    "sg:classifiers":[
        {
            "category":"Wholesale",
            "subcategory":"Non-durable Goods",
            "type":"Manufacturing & Wholesale Goods"
        }
    ],
    "sg:phone":"+1 310 540 1895",
    "sg:postcode":"90277",
    "sg:province":"CA",
    "sg:tags":[
        "advertising"
    ],
    "wof:name":"Coread Corp",
    "wof:placetype":"venue"
},
  "geometry": {"coordinates":[-118.376198,33.841165],"type":"Point"}
}