{
  "type": "Feature",
  "properties": {
    "iso:country":"US",
    "sg:address":"5555 W Dorothea Ave",
    "sg:city":"Visalia",
    "sg:classifiers":[
        {
            "category":"Professional",
            "subcategory":"Management & Consulting",
            "type":"Services"
        }
    ],
    "sg:phone":"+1 559 733 8200",
    "sg:postcode":"93277",
    "sg:province":"CA",
    "sg:tags":[
        "consultant",
        "business"
    ],
    "wof:name":"Cobb & Co",
    "wof:placetype":"venue"
},
  "geometry": {"coordinates":[-119.352574,36.302116],"type":"Point"}
}