{
  "type": "Feature",
  "properties": {
    "iso:country":"US",
    "sg:address":"25 Little Creek Ln",
    "sg:city":"Novato",
    "sg:classifiers":[
        {
            "category":"Utilities",
            "subcategory":"Telephone",
            "type":"Services"
        }
    ],
    "sg:phone":"+1 415 265 2717",
    "sg:postcode":"94945",
    "sg:province":"CA",
    "sg:tags":[
        "communications"
    ],
    "wof:name":"Dentallistcom",
    "wof:placetype":"venue"
},
  "geometry": {"coordinates":[-122.57606699999999,38.125463],"type":"Point"}
}