{
  "type": "Feature",
  "properties": {
    "iso:country":"US",
    "sg:address":"2812 Santa Monica Blvd",
    "sg:city":"Santa Monica",
    "sg:classifiers":[
        {
            "category":"Social Services",
            "type":"Services"
        }
    ],
    "sg:phone":"+1 310 392 4441",
    "sg:postcode":"90404",
    "sg:province":"CA",
    "sg:tags":[
        "counselor",
        "marriage",
        "family"
    ],
    "wof:name":"Dortee Farrar Phd Mft",
    "wof:placetype":"venue"
},
  "geometry": {"coordinates":[-118.471527,34.035428],"type":"Point"}
}