{
  "type": "Feature",
  "properties": {
    "addr:full":"1719 Casa Nueva St Woodland CA 95695",
    "addr:housenumber":"1719",
    "addr:postcode":"95695",
    "addr:street":"Casa Nueva St",
    "iso:country":"US",
    "sg:address":"1719 Casa Nueva St",
    "sg:city":"Woodland",
    "sg:classifiers":[
        {
            "category":"Building & Trades",
            "subcategory":"Landscaping Services",
            "type":"Services"
        }
    ],
    "sg:phone":"+1 530 662 6675",
    "sg:postcode":"95695",
    "sg:province":"CA",
    "sg:tags":[
        "landscape"
    ],
    "wof:name":"Bob Hadley Landscaping",
    "wof:placetype":"venue"
},
  "geometry": {"coordinates":[-121.79019099999999,38.657626],"type":"Point"}
}