{
  "type": "Feature",
  "properties": {
    "addr:full":"16157 San Bernardino Ave Fontana CA 92335",
    "addr:housenumber":"16157",
    "addr:postcode":"92335",
    "addr:street":"San Bernardino Ave",
    "iso:country":"US",
    "sg:address":"16157 San Bernardino Ave",
    "sg:city":"Fontana",
    "sg:classifiers":[
        {
            "category":"Restaurant",
            "type":"Food & Drink"
        }
    ],
    "sg:phone":"+1 909 357 3822",
    "sg:postcode":"92335",
    "sg:province":"CA",
    "wof:name":"Miguel's Jr",
    "wof:placetype":"venue"
},
  "geometry": {"coordinates":[-117.452609,34.077467],"type":"Point"}
}