{
  "type": "Feature",
  "properties": {
    "addr:full":"2094 Walsh Ave Santa Clara CA 95050",
    "addr:housenumber":"2094",
    "addr:postcode":"95050",
    "addr:street":"Walsh Ave",
    "iso:country":"US",
    "sg:address":"2094 Walsh Ave",
    "sg:city":"Santa Clara",
    "sg:classifiers":[
        {
            "category":"Retail",
            "subcategory":"Repair Shop",
            "type":"Services"
        }
    ],
    "sg:phone":"+1 408 988 6962",
    "sg:postcode":"95050",
    "sg:province":"CA",
    "sg:tags":[
        "equipment",
        "electronic",
        "supply"
    ],
    "sg:website":"www.precprog.com",
    "wof:name":"Precision Programming",
    "wof:placetype":"venue"
},
  "geometry": {"coordinates":[-121.96108099999999,37.369393],"type":"Point"}
}