{
  "type": "Feature",
  "properties": {
    "iso:country":"US",
    "sg:address":"11770 Bernardo Plaza Ct",
    "sg:city":"San Diego",
    "sg:classifiers":[
        {
            "category":"Insurance",
            "subcategory":"Insurance Agent",
            "type":"Services"
        }
    ],
    "sg:phone":"+1 858 674 4944",
    "sg:postcode":"92128",
    "sg:province":"CA",
    "sg:tags":[
        "consultant"
    ],
    "wof:name":"Net Cost Advisors",
    "wof:placetype":"venue"
},
  "geometry": {"coordinates":[-117.075193,33.020425],"type":"Point"}
}