{
  "type": "Feature",
  "properties": {
    "iso:country":"US",
    "sg:address":"25008 Viking St",
    "sg:city":"Hayward",
    "sg:classifiers":[
        {
            "category":"Wholesale",
            "subcategory":"Machinery & Supplies",
            "type":"Manufacturing & Wholesale Goods"
        }
    ],
    "sg:phone":"+1 800 809 1361",
    "sg:postcode":"94545",
    "sg:province":"CA",
    "sg:tags":[
        "equipment",
        "material",
        "handling"
    ],
    "wof:name":"Big Joe Handling Systems",
    "wof:placetype":"venue"
},
  "geometry": {"coordinates":[-122.12488,37.637291],"type":"Point"}
}