{
  "type": "Feature",
  "properties": {
    "iso:country":"US",
    "sg:address":"2800 E Observatory Ave",
    "sg:city":"Los Angeles",
    "sg:classifiers":[
        {
            "category":"Sports & Exercise",
            "subcategory":"Gym",
            "type":"Entertainment"
        },
        {
            "category":"Recreation",
            "type":"Entertainment"
        }
    ],
    "sg:phone":"+1 415 261 3641",
    "sg:postcode":"90027",
    "sg:province":"CA",
    "sg:tags":[
        "yoga",
        "hiking"
    ],
    "wof:name":"Hiking Yoga",
    "wof:placetype":"venue"
},
  "geometry": {"coordinates":[-118.300352,34.118378],"type":"Point"}
}