{
  "type": "Feature",
  "properties": {
    "addr:full":"1 Shrader St # 640 San Francisco CA 94117",
    "addr:housenumber":"1",
    "addr:postcode":"94117",
    "addr:street":"Shrader St # 640",
    "iso:country":"US",
    "sg:address":"1 Shrader St # 640",
    "sg:city":"San Francisco",
    "sg:classifiers":[
        {
            "category":"Community Center",
            "type":"Public Place"
        }
    ],
    "sg:phone":"+1 415 752 0100",
    "sg:postcode":"94117",
    "sg:province":"CA",
    "sg:tags":[
        "medical"
    ],
    "wof:name":"Mercy Doctors Medical Group",
    "wof:placetype":"venue"
},
  "geometry": {"coordinates":[-122.453148,37.774845],"type":"Point"}
}