{
  "type": "Feature",
  "properties": {
    "addr:full":"5117 Vecchio Way Salida CA 95368",
    "addr:housenumber":"5117",
    "addr:postcode":"95368",
    "addr:street":"Vecchio Way",
    "iso:country":"US",
    "sg:address":"5117 Vecchio Way",
    "sg:city":"Salida",
    "sg:classifiers":[
        {
            "category":"Freight",
            "type":"Transportation"
        }
    ],
    "sg:phone":"+1 209 543 1719",
    "sg:postcode":"95368",
    "sg:province":"CA",
    "wof:name":"Robinson Transportation",
    "wof:placetype":"venue"
},
  "geometry": {"coordinates":[-121.091139,37.720415],"type":"Point"}
}