{
  "type": "Feature",
  "properties": {
    "addr:full":"7138 Shoup Ave Canoga Park CA 91307",
    "addr:housenumber":"7138",
    "addr:postcode":"91307",
    "addr:street":"Shoup Ave",
    "iso:country":"US",
    "sg:address":"7138 Shoup Ave",
    "sg:city":"Canoga Park",
    "sg:classifiers":[
        {
            "category":"Personal",
            "subcategory":"Beauty Salon",
            "type":"Services"
        }
    ],
    "sg:phone":"+1 818 992 6332",
    "sg:postcode":"91307",
    "sg:province":"CA",
    "wof:name":"Hair Etcetera",
    "wof:placetype":"venue"
},
  "geometry": {"coordinates":[-118.61459000000001,34.20001],"type":"Point"}
}