{
  "type": "Feature",
  "properties": {
    "addr:full":"109 Plaza Dr Vallejo CA 94591",
    "addr:housenumber":"109",
    "addr:postcode":"94591",
    "addr:street":"Plaza Dr",
    "iso:country":"US",
    "sg:address":"109 Plaza Dr",
    "sg:city":"Vallejo",
    "sg:phone":"+1 800 326 3264",
    "sg:postcode":"94591",
    "sg:province":"CA",
    "sg:website":"http://www.cinemark.com",
    "wof:name":"Century 14 Vallejo",
    "wof:placetype":"venue"
},
  "geometry": {"coordinates":[-122.217789,38.134331],"type":"Point"}
}