{
  "type": "Feature",
  "properties": {
    "iso:country":"US",
    "sg:address":"21031 Ventura Blvd",
    "sg:city":"Woodland Hills",
    "sg:classifiers":[
        {
            "category":"Banks & Credit Unions",
            "subcategory":"Financial Services",
            "type":"Services"
        }
    ],
    "sg:phone":"+1 818 592 6533",
    "sg:postcode":"91364",
    "sg:province":"CA",
    "sg:tags":[
        "broker",
        "mortgage"
    ],
    "wof:name":"Mortgage Discounters",
    "wof:placetype":"venue"
},
  "geometry": {"coordinates":[-118.591003,34.166698],"type":"Point"}
}