{
  "type": "Feature",
  "properties": {
    "iso:country":"US",
    "sg:address":"3333 Bowers Ave Ste 130",
    "sg:city":"Santa Clara",
    "sg:classifiers":[
        {
            "category":"Real Estate",
            "subcategory":"Architect",
            "type":"Services"
        }
    ],
    "sg:phone":"+1 408 496 0676",
    "sg:postcode":"95054",
    "sg:province":"CA",
    "wof:name":"Arc Tec Inc",
    "wof:placetype":"venue"
},
  "geometry": {"coordinates":[-121.977997,37.381302],"type":"Point"}
}