{
  "type": "Feature",
  "properties": {
    "addr:full":"1290 W Valley Pkwy Escondido CA 92029",
    "addr:housenumber":"1290",
    "addr:postcode":"92029",
    "addr:street":"W Valley Pkwy",
    "iso:country":"US",
    "sg:address":"1290 W Valley Pkwy",
    "sg:city":"Escondido",
    "sg:classifiers":[
        {
            "category":"Travel",
            "subcategory":"Hotels & Motels",
            "type":"Entertainment"
        }
    ],
    "sg:phone":"+1 760 489 1010",
    "sg:postcode":"92029",
    "sg:province":"CA",
    "sg:tags":[
        "lodging"
    ],
    "wof:name":"Comfort Inn Escondido",
    "wof:placetype":"venue"
},
  "geometry": {"coordinates":[-117.101596,33.113831],"type":"Point"}
}