{
  "type": "Feature",
  "properties": {
    "addr:full":"239 D St San Rafael CA 94901",
    "addr:housenumber":"239",
    "addr:postcode":"94901",
    "addr:street":"D St",
    "iso:country":"US",
    "sg:address":"239 D St",
    "sg:city":"San Rafael",
    "sg:classifiers":[
        {
            "category":"Real Estate",
            "subcategory":"Real Estate Agent",
            "type":"Services"
        }
    ],
    "sg:phone":"+1 707 766 6481",
    "sg:postcode":"94901",
    "sg:province":"CA",
    "sg:tags":[
        "investment"
    ],
    "wof:name":"Investment Property Capitol",
    "wof:placetype":"venue"
},
  "geometry": {"coordinates":[-122.53336899999999,37.965057],"type":"Point"}
}