{
  "type": "Feature",
  "properties": {
    "iso:country":"US",
    "sg:address":"1611 N San Fernando Blvd",
    "sg:city":"Burbank",
    "sg:classifiers":[
        {
            "category":"Professional",
            "subcategory":"Credit Reporting & Collection",
            "type":"Services"
        }
    ],
    "sg:phone":"+1 818 841 6000",
    "sg:postcode":"91504",
    "sg:province":"CA",
    "sg:tags":[
        "agency"
    ],
    "wof:name":"Finex Systems Inc",
    "wof:placetype":"venue"
},
  "geometry": {"coordinates":[-118.324167,34.191527],"type":"Point"}
}