{
  "type": "Feature",
  "properties": {
    "iso:country":"US",
    "sg:address":"5301 Arroyo Rd",
    "sg:city":"Livermore",
    "sg:classifiers":[
        {
            "category":"Park",
            "type":"Public Place"
        }
    ],
    "sg:phone":"+1 925 960 2400",
    "sg:postcode":"94550",
    "sg:province":"CA",
    "wof:name":"Livermore Park Ranger Office",
    "wof:placetype":"venue"
},
  "geometry": {"coordinates":[-121.75943700000001,37.620968],"type":"Point"}
}