{
  "type": "Feature",
  "properties": {
    "iso:country":"US",
    "sg:address":"25741 Obrero Dr",
    "sg:city":"Mission Viejo",
    "sg:classifiers":[
        {
            "category":"Autos & Motor Vehicles",
            "subcategory":"Auto Supplies",
            "type":"Retail Goods"
        }
    ],
    "sg:phone":"+1 949 458 1571",
    "sg:postcode":"92691",
    "sg:province":"CA",
    "wof:name":"Pitstop",
    "wof:placetype":"venue"
},
  "geometry": {"coordinates":[-117.680554,33.619327],"type":"Point"}
}