{
  "type": "Feature",
  "properties": {
    "iso:country":"US",
    "sg:address":"177 Post Street",
    "sg:city":"San Francisco",
    "sg:classifiers":[
        {
            "category":"Professional",
            "subcategory":"Lawyer & Legal Services",
            "type":"Services"
        }
    ],
    "sg:phone":"+1 415 433 3993",
    "sg:postcode":"94108",
    "sg:province":"CA",
    "sg:website":"www.jungreislaw.com",
    "wof:name":"Jungreis Law",
    "wof:placetype":"venue"
},
  "geometry": {"coordinates":[-122.404999,37.788799],"type":"Point"}
}