{
  "type": "Feature",
  "properties": {
    "addr:full":"3580 Blackhawk Plaza Cir Danville CA 94506",
    "addr:housenumber":"3580",
    "addr:postcode":"94506",
    "addr:street":"Blackhawk Plaza Cir",
    "iso:country":"US",
    "sg:address":"3580 Blackhawk Plaza Cir",
    "sg:city":"Danville",
    "sg:classifiers":[
        {
            "category":"Health Services",
            "subcategory":"Doctor",
            "type":"Services"
        }
    ],
    "sg:phone":"+1 925 275 9333",
    "sg:postcode":"94506",
    "sg:province":"CA",
    "sg:tags":[
        "physician",
        "surgeon"
    ],
    "wof:name":"Jeffrey Riopelle MD",
    "wof:placetype":"venue"
},
  "geometry": {"coordinates":[-121.916543,37.800432],"type":"Point"}
}