{
  "type": "Feature",
  "properties": {
    "iso:country":"US",
    "sg:address":"14142 Hortense St",
    "sg:city":"Sherman Oaks",
    "sg:classifiers":[
        {
            "category":"Professional",
            "subcategory":"Business Services",
            "type":"Services"
        }
    ],
    "sg:phone":"+1 818 784 2328",
    "sg:postcode":"91423",
    "sg:province":"CA",
    "sg:tags":[
        "consultant",
        "production",
        "music"
    ],
    "wof:name":"Brasilian Beat Productions",
    "wof:placetype":"venue"
},
  "geometry": {"coordinates":[-118.441759,34.154697],"type":"Point"}
}