{
  "type": "Feature",
  "properties": {
    "addr:full":"3922 Mascari Pl Spring Valley CA 91977",
    "addr:housenumber":"3922",
    "addr:postcode":"91977",
    "addr:street":"Mascari Pl",
    "iso:country":"US",
    "sg:address":"3922 Mascari Pl",
    "sg:city":"Spring Valley",
    "sg:classifiers":[
        {
            "category":"Professional",
            "subcategory":"Accounting & Tax Preparation",
            "type":"Services"
        }
    ],
    "sg:phone":"+1 619 469 7765",
    "sg:postcode":"91977",
    "sg:province":"CA",
    "sg:tags":[
        "return",
        "filing"
    ],
    "wof:name":"Frank S Mascari Income Tax Svc",
    "wof:placetype":"venue"
},
  "geometry": {"coordinates":[-116.991794,32.752533],"type":"Point"}
}