{
  "type": "Feature",
  "properties": {
    "iso:country":"US",
    "sg:address":"612 N Douty St",
    "sg:city":"Hanford",
    "sg:classifiers":[
        {
            "category":"Health Services",
            "subcategory":"Chiropractor",
            "type":"Services"
        }
    ],
    "sg:phone":"+1 559 584 7991",
    "sg:postcode":"93230",
    "sg:province":"CA",
    "wof:name":"Wickert Chiropractic",
    "wof:placetype":"venue"
},
  "geometry": {"coordinates":[-119.646101,36.331615],"type":"Point"}
}