{
  "type": "Feature",
  "properties": {
    "addr:full":"34845 Yucaipa Blvd Yucaipa CA 92399",
    "addr:postcode":"34845;92399",
    "addr:street":"Yucaipa Blvd",
    "iso:country":"US",
    "sg:address":"34845 Yucaipa Blvd",
    "sg:city":"Yucaipa",
    "sg:classifiers":[
        {
            "category":"Professional",
            "type":"Services"
        }
    ],
    "sg:phone":"+1 909 797 9166",
    "sg:postcode":"92399",
    "sg:province":"CA",
    "sg:tags":[
        "establishment"
    ],
    "wof:name":"Vicki's Medical Transcription",
    "wof:placetype":"venue"
},
  "geometry": {"coordinates":[-117.04593800000001,34.033802],"type":"Point"}
}