{
  "type": "Feature",
  "properties": {
    "addr:full":"18 Carlsbad Ln Aliso Viejo CA 92656",
    "addr:housenumber":"18",
    "addr:postcode":"92656",
    "addr:street":"Carlsbad Ln",
    "iso:country":"US",
    "sg:address":"18 Carlsbad Ln",
    "sg:city":"Aliso Viejo",
    "sg:classifiers":[
        {
            "category":"Building & Trades",
            "subcategory":"Landscaping Services",
            "type":"Services"
        }
    ],
    "sg:phone":"+1 949 831 9851",
    "sg:postcode":"92656",
    "sg:province":"CA",
    "wof:name":"Garden Visions Ldscp Design",
    "wof:placetype":"venue"
},
  "geometry": {"coordinates":[-117.736011,33.581992],"type":"Point"}
}