{
  "type": "Feature",
  "properties": {
    "addr:full":"12260 San Pablo Ave Richmond CA 94805",
    "addr:housenumber":"12260",
    "addr:postcode":"94805",
    "addr:street":"San Pablo Ave",
    "iso:country":"US",
    "sg:address":"12260 San Pablo Ave",
    "sg:city":"Richmond",
    "sg:classifiers":[
        {
            "category":"Shopping",
            "subcategory":"Catalog Store",
            "type":"Retail Goods"
        }
    ],
    "sg:phone":"+1 510 234 2188",
    "sg:postcode":"94805",
    "sg:province":"CA",
    "sg:tags":[
        "mail",
        "order",
        "sportswear",
        "mfg"
    ],
    "sg:website":"www.jagware-posingsuits.com",
    "wof:name":"Jagware",
    "wof:placetype":"venue"
},
  "geometry": {"coordinates":[-122.324484,37.93431],"type":"Point"}
}