{
  "type": "Feature",
  "properties": {
    "iso:country":"US",
    "sg:address":"4908 Via Fresco",
    "sg:city":"Camarillo",
    "sg:classifiers":[
        {
            "category":"Real Estate",
            "subcategory":"Real Estate Services",
            "type":"Services"
        },
        {
            "category":"Real Estate",
            "subcategory":"Real Estate Agent",
            "type":"Services"
        }
    ],
    "sg:phone":"+1 805 407 1318",
    "sg:postcode":"93012",
    "sg:province":"CA",
    "sg:tags":[
        "buyer",
        "broker"
    ],
    "wof:name":"Puckett Real Estate Team",
    "wof:placetype":"venue"
},
  "geometry": {"coordinates":[-119.007976,34.232319],"type":"Point"}
}