{
  "type": "Feature",
  "properties": {
    "addr:full":"249 E Tulare Ave Tulare CA 93274",
    "addr:housenumber":"249",
    "addr:postcode":"93274",
    "addr:street":"E Tulare Ave",
    "iso:country":"US",
    "sg:address":"249 E Tulare Ave",
    "sg:city":"Tulare",
    "sg:classifiers":[
        {
            "category":"Food & Beverages",
            "subcategory":"Groceries & Convenience Stores",
            "type":"Retail Goods"
        }
    ],
    "sg:phone":"+1 559 738 8294",
    "sg:postcode":"93274",
    "sg:province":"CA",
    "sg:tags":[
        "grocer"
    ],
    "wof:name":"Victorian Market",
    "wof:placetype":"venue"
},
  "geometry": {"coordinates":[-119.34599799999999,36.208025],"type":"Point"}
}