{
  "type": "Feature",
  "properties": {
    "iso:country":"US",
    "sg:address":"10 California St",
    "sg:city":"Stockton",
    "sg:classifiers":[
        {
            "category":"Restaurant",
            "type":"Food & Drink"
        }
    ],
    "sg:phone":"+1 209 464 1722",
    "sg:postcode":"95202",
    "sg:province":"CA",
    "wof:name":"Market Fresh Pizza Co",
    "wof:placetype":"venue"
},
  "geometry": {"coordinates":[-121.284758,37.954549],"type":"Point"}
}