{
  "type": "Feature",
  "properties": {
    "addr:full":"207 Fifth Avenue San Diego CA 92101",
    "addr:housenumber":"207",
    "addr:postcode":"92101",
    "addr:street":"Fifth Avenue",
    "iso:country":"US",
    "sg:address":"207 Fifth Avenue",
    "sg:city":"San Diego",
    "sg:classifiers":[
        {
            "category":"Bars & Pubs",
            "subcategory":"Nightclub",
            "type":"Food & Drink"
        }
    ],
    "sg:phone":"+1 619 764 6926",
    "sg:postcode":"92101",
    "sg:province":"CA",
    "sg:tags":[
        "nightlife"
    ],
    "wof:name":"207",
    "wof:placetype":"venue"
},
  "geometry": {"coordinates":[-117.160175,32.707337],"type":"Point"}
}