{
  "type": "Feature",
  "properties": {
    "addr:full":"2960 Ironwood Ave Morro Bay CA 93442",
    "addr:housenumber":"2960",
    "addr:postcode":"93442",
    "addr:street":"Ironwood Ave",
    "iso:country":"US",
    "sg:address":"2960 Ironwood Ave",
    "sg:city":"Morro Bay",
    "sg:classifiers":[
        {
            "category":"Retail",
            "subcategory":"Laundry & Dry Cleaning",
            "type":"Services"
        }
    ],
    "sg:phone":"+1 805 772 0467",
    "sg:postcode":"93442",
    "sg:province":"CA",
    "sg:tags":[
        "cleaners",
        "rug",
        "carpet"
    ],
    "wof:name":"Bay-Vue Quality Cleaning Svc",
    "wof:placetype":"venue"
},
  "geometry": {"coordinates":[-120.85589899999999,35.395501],"type":"Point"}
}