{
  "type": "Feature",
  "properties": {
    "iso:country":"US",
    "sg:address":"5621 W McKenzie Ave",
    "sg:city":"Fresno",
    "sg:classifiers":[
        {
            "category":"Utilities",
            "subcategory":"Refuse",
            "type":"Services"
        }
    ],
    "sg:phone":"+1 559 277 0424",
    "sg:postcode":"93723",
    "sg:province":"CA",
    "sg:tags":[
        "system"
    ],
    "wof:name":"Als Plastics",
    "wof:placetype":"venue"
},
  "geometry": {"coordinates":[-119.89537799999999,36.746252],"type":"Point"}
}