{
  "type": "Feature",
  "properties": {
    "iso:country":"US",
    "sg:address":"252 N El Camino Real Ste 5",
    "sg:city":"Encinitas",
    "sg:classifiers":[
        {
            "category":"Restaurant",
            "type":"Food & Drink"
        }
    ],
    "sg:phone":"+1 760 635 2800",
    "sg:postcode":"92024",
    "sg:province":"CA",
    "sg:tags":[
        "pizza"
    ],
    "sg:website":"www.pizzicatopizza.com/home/?p=28",
    "wof:name":"Pizzicato Gourmet Pizza",
    "wof:placetype":"venue"
},
  "geometry": {"coordinates":[-117.260965,33.051866],"type":"Point"}
}