{
  "type": "Feature",
  "properties": {
    "addr:full":"1145 Bont Ln Walnut Creek CA 94596",
    "addr:housenumber":"1145",
    "addr:postcode":"94596",
    "addr:street":"Bont Ln",
    "iso:country":"US",
    "sg:address":"1145 Bont Ln",
    "sg:city":"Walnut Creek",
    "sg:classifiers":[
        {
            "category":"Retail",
            "subcategory":"Auto Repair",
            "type":"Services"
        }
    ],
    "sg:phone":"+1 925 933 8525",
    "sg:postcode":"94596",
    "sg:province":"CA",
    "sg:tags":[
        "repairing",
        "automobile"
    ],
    "wof:name":"Walnut Creek Svc Ctr",
    "wof:placetype":"venue"
},
  "geometry": {"coordinates":[-122.06866100000001,37.896156],"type":"Point"}
}