{
  "type": "Feature",
  "properties": {
    "iso:country":"US",
    "sg:address":"21250 Hawthorne Blvd",
    "sg:city":"Torrance",
    "sg:classifiers":[
        {
            "category":"Organizations",
            "subcategory":"Non-profit Organization",
            "type":"Services"
        }
    ],
    "sg:phone":"+1 310 316 7350",
    "sg:postcode":"90503",
    "sg:province":"CA",
    "sg:tags":[
        "service/non-profit",
        "community"
    ],
    "wof:name":"Nelson Charities",
    "wof:placetype":"venue"
},
  "geometry": {"coordinates":[-118.353069,33.836015],"type":"Point"}
}