{
  "type": "Feature",
  "properties": {
    "iso:country":"US",
    "sg:address":"2920 Spring Mountain Rd",
    "sg:city":"Saint Helena",
    "sg:classifiers":[
        {
            "category":"Farming",
            "subcategory":"Vineyard",
            "type":"Manufacturing & Wholesale Goods"
        }
    ],
    "sg:phone":"+1 707 968 9229",
    "sg:postcode":"94574",
    "sg:province":"CA",
    "sg:tags":[
        "grape"
    ],
    "wof:name":"Shadow Lace Vineyards",
    "wof:placetype":"venue"
},
  "geometry": {"coordinates":[-122.506339,38.514895],"type":"Point"}
}