{
  "type": "Feature",
  "properties": {
    "addr:full":"390 Bel Marin Keys Blvd Novato CA 94949",
    "addr:housenumber":"390",
    "addr:postcode":"94949",
    "addr:street":"Bel Marin Keys Blvd",
    "iso:country":"US",
    "sg:address":"390 Bel Marin Keys Blvd",
    "sg:city":"Novato",
    "sg:classifiers":[
        {
            "category":"Wholesale",
            "subcategory":"Machinery & Supplies",
            "type":"Manufacturing & Wholesale Goods"
        }
    ],
    "sg:phone":"+1 415 883 9604",
    "sg:postcode":"94949",
    "sg:province":"CA",
    "sg:tags":[
        "equipment",
        "industrial"
    ],
    "wof:name":"McKenna Engineering & Eqp Co",
    "wof:placetype":"venue"
},
  "geometry": {"coordinates":[-122.537567,38.074126],"type":"Point"}
}