{
  "type": "Feature",
  "properties": {
    "addr:full":"1400 Quail Street Newport Beach CA 92660",
    "addr:housenumber":"1400",
    "addr:postcode":"92660",
    "addr:street":"Quail Street",
    "iso:country":"US",
    "sg:address":"1400 Quail Street",
    "sg:city":"Newport Beach",
    "sg:classifiers":[
        {
            "category":"Communications",
            "subcategory":"Newspaper",
            "type":"Services"
        }
    ],
    "sg:phone":"+1 949 833 2550",
    "sg:postcode":"92660",
    "sg:province":"CA",
    "sg:tags":[
        "print",
        "medium"
    ],
    "wof:name":"Oc the Place",
    "wof:placetype":"venue"
},
  "geometry": {"coordinates":[-117.87948900000001,33.632027],"type":"Point"}
}