{
  "type": "Feature",
  "properties": {
    "iso:country":"US",
    "sg:address":"538 Central Ave",
    "sg:city":"Shafter",
    "sg:classifiers":[
        {
            "category":"Food & Beverages",
            "subcategory":"Groceries & Convenience Stores",
            "type":"Retail Goods"
        }
    ],
    "sg:phone":"+1 661 746 5496",
    "sg:postcode":"93263",
    "sg:province":"CA",
    "sg:tags":[
        "grocer"
    ],
    "wof:name":"Central Avenue Food Store",
    "wof:placetype":"venue"
},
  "geometry": {"coordinates":[-119.272542,35.504253],"type":"Point"}
}