{
  "type": "Feature",
  "properties": {
    "iso:country":"US",
    "sg:address":"40 Rose Ave",
    "sg:city":"Venice",
    "sg:classifiers":[
        {
            "category":"Professional",
            "type":"Services"
        }
    ],
    "sg:phone":"+1 310 392 9117",
    "sg:postcode":"90291",
    "sg:province":"CA",
    "wof:name":"Glenzilla Prod",
    "wof:placetype":"venue"
},
  "geometry": {"coordinates":[-118.47895200000001,33.995341],"type":"Point"}
}