{
  "type": "Feature",
  "properties": {
    "addr:full":"4726 International Blvd Oakland CA 94601",
    "addr:housenumber":"4726",
    "addr:postcode":"94601",
    "addr:street":"International Blvd",
    "iso:country":"US",
    "sg:address":"4726 International Blvd",
    "sg:city":"Oakland",
    "sg:classifiers":[
        {
            "category":"Personal",
            "subcategory":"Beauty Salon",
            "type":"Services"
        }
    ],
    "sg:phone":"+1 510 533 3799",
    "sg:postcode":"94601",
    "sg:province":"CA",
    "wof:name":"Maryely Beauty Salon",
    "wof:placetype":"venue"
},
  "geometry": {"coordinates":[-122.21076100000001,37.770556],"type":"Point"}
}