{
  "type": "Feature",
  "properties": {
    "addr:full":"1600 E Florida Ave Hemet CA 92544",
    "addr:housenumber":"1600",
    "addr:postcode":"92544",
    "addr:street":"E Florida Ave",
    "iso:country":"US",
    "sg:address":"1600 E Florida Ave",
    "sg:city":"Hemet",
    "sg:classifiers":[
        {
            "category":"Professional",
            "subcategory":"Lawyer & Legal Services",
            "type":"Services"
        }
    ],
    "sg:phone":"+1 951 658 7162",
    "sg:postcode":"92544",
    "sg:province":"CA",
    "sg:tags":[
        "attorney"
    ],
    "wof:name":"Swan Carpenter Wallis Mckenzie",
    "wof:placetype":"venue"
},
  "geometry": {"coordinates":[-116.957379,33.747693],"type":"Point"}
}