{
  "type": "Feature",
  "properties": {
    "addr:full":"1822 Shuey Ave Walnut Creek CA 94596",
    "addr:housenumber":"1822",
    "addr:postcode":"94596",
    "addr:street":"Shuey Ave",
    "iso:country":"US",
    "sg:address":"1822 Shuey Ave",
    "sg:city":"Walnut Creek",
    "sg:classifiers":[
        {
            "category":"Real Estate",
            "subcategory":"Real Estate Agent",
            "type":"Services"
        }
    ],
    "sg:phone":"+1 925 930 9401",
    "sg:postcode":"94596",
    "sg:province":"CA",
    "wof:name":"Brokerage",
    "wof:placetype":"venue"
},
  "geometry": {"coordinates":[-122.066081,37.899764],"type":"Point"}
}