{
  "type": "Feature",
  "properties": {
    "iso:country":"US",
    "sg:address":"763 Temescal Way",
    "sg:city":"Emerald Hills",
    "sg:classifiers":[
        {
            "category":"Building & Trades",
            "subcategory":"Construction",
            "type":"Services"
        }
    ],
    "sg:phone":"+1 650 366 9860",
    "sg:postcode":"94062",
    "sg:province":"CA",
    "sg:tags":[
        "house",
        "contractor"
    ],
    "wof:name":"Woodside Builders",
    "wof:placetype":"venue"
},
  "geometry": {"coordinates":[-122.266709,37.459081],"type":"Point"}
}