{
  "type": "Feature",
  "properties": {
    "iso:country":"US",
    "sg:address":"32432 Alipaz St",
    "sg:city":"San Juan Capistrano",
    "sg:classifiers":[
        {
            "category":"Retail",
            "subcategory":"Repair Shop",
            "type":"Services"
        }
    ],
    "sg:phone":"+1 949 661 5881",
    "sg:postcode":"92675",
    "sg:province":"CA",
    "sg:tags":[
        "pump",
        "air",
        "gas",
        "sales",
        "compressed"
    ],
    "wof:name":"Kern Pump & Compressor",
    "wof:placetype":"venue"
},
  "geometry": {"coordinates":[-117.67211,33.49078],"type":"Point"}
}