{
  "type": "Feature",
  "properties": {
    "addr:full":"2350 McBride Ln Santa Rosa CA 95403",
    "addr:housenumber":"2350",
    "addr:postcode":"95403",
    "addr:street":"Mcbride Ln",
    "iso:country":"US",
    "sg:address":"2350 McBride Ln",
    "sg:city":"Santa Rosa",
    "sg:classifiers":[
        {
            "category":"Freight",
            "type":"Transportation"
        }
    ],
    "sg:phone":"+1 707 578 0330",
    "sg:postcode":"95403",
    "sg:province":"CA",
    "sg:tags":[
        "building",
        "opera",
        "general",
        "nonresidential"
    ],
    "wof:name":"Mc Bride Apts",
    "wof:placetype":"venue"
},
  "geometry": {"coordinates":[-122.73014999999999,38.463206],"type":"Point"}
}