{
  "type": "Feature",
  "properties": {
    "addr:full":"401 N Fairview Ave Goleta CA 93117",
    "addr:housenumber":"401",
    "addr:postcode":"93117",
    "addr:street":"N Fairview Ave",
    "iso:country":"US",
    "sg:address":"401 N Fairview Ave",
    "sg:city":"Goleta",
    "sg:classifiers":[
        {
            "category":"Education",
            "subcategory":"School",
            "type":"Public Place"
        }
    ],
    "sg:phone":"+1 805 681 1200",
    "sg:postcode":"93117",
    "sg:province":"CA",
    "wof:name":"Goleta Union School District",
    "wof:placetype":"venue"
},
  "geometry": {"coordinates":[-119.830675,34.448938],"type":"Point"}
}