{
  "type": "Feature",
  "properties": {
    "iso:country":"US",
    "sg:address":"4501 X Street",
    "sg:city":"Sacramento",
    "sg:classifiers":[
        {
            "category":"Health Services",
            "subcategory":"Doctor",
            "type":"Services"
        }
    ],
    "sg:phone":"+1 916 734 5959",
    "sg:postcode":"95817",
    "sg:province":"CA",
    "sg:tags":[
        "cardiologist"
    ],
    "sg:website":"www.ucdmc.ucdavis.edu/cancer",
    "wof:name":"Calhoun Royce MD Cardiac Surgry",
    "wof:placetype":"venue"
},
  "geometry": {"coordinates":[-121.453385,38.553539],"type":"Point"}
}