{
  "type": "Feature",
  "properties": {
    "iso:country":"US",
    "sg:address":"16200 Hawthorne Blvd",
    "sg:city":"Lawndale",
    "sg:classifiers":[
        {
            "category":"Retail",
            "subcategory":"Auto Rental",
            "type":"Services"
        }
    ],
    "sg:phone":"+1 310 370 6600",
    "sg:postcode":"90260",
    "sg:province":"CA",
    "sg:tags":[
        "passenger",
        "car"
    ],
    "wof:name":"Avis Contrs Licenses Svc Ctr",
    "wof:placetype":"venue"
},
  "geometry": {"coordinates":[-118.352305,33.884623],"type":"Point"}
}