{
  "type": "Feature",
  "properties": {
    "iso:country":"US",
    "sg:address":"10600 Wilshire Blvd",
    "sg:city":"Los Angeles",
    "sg:classifiers":[
        {
            "category":"Professional",
            "subcategory":"Accounting & Tax Preparation",
            "type":"Services"
        }
    ],
    "sg:phone":"+1 310 441 1450",
    "sg:postcode":"90024",
    "sg:province":"CA",
    "sg:tags":[
        "bookkeeping",
        "general"
    ],
    "wof:name":"Incorportate Express Inc",
    "wof:placetype":"venue"
},
  "geometry": {"coordinates":[-118.435735,34.060855],"type":"Point"}
}