{
  "type": "Feature",
  "properties": {
    "iso:country":"US",
    "sg:address":"1177 W Shaw Ave",
    "sg:city":"Fresno",
    "sg:classifiers":[
        {
            "category":"Wholesale",
            "subcategory":"Fruits & Vegetables",
            "type":"Manufacturing & Wholesale Goods"
        }
    ],
    "sg:phone":"+1 559 222 7200",
    "sg:postcode":"93711",
    "sg:province":"CA",
    "wof:name":"RJO Produce Distr Inc",
    "wof:placetype":"venue"
},
  "geometry": {"coordinates":[-119.810888,36.808292],"type":"Point"}
}