{
  "type": "Feature",
  "properties": {
    "addr:full":"1125 3rd St Santa Monica CA 90403",
    "addr:housenumber":"1125",
    "addr:postcode":"90403",
    "addr:street":"3Rd St",
    "iso:country":"US",
    "sg:address":"1125 3rd St",
    "sg:city":"Santa Monica",
    "sg:classifiers":[
        {
            "category":"Health Services",
            "subcategory":"Nursing And Care Facility",
            "type":"Services"
        }
    ],
    "sg:phone":"+1 310 395 4545",
    "sg:postcode":"90403",
    "sg:province":"CA",
    "sg:tags":[
        "home",
        "retirement",
        "community"
    ],
    "wof:name":"Wilshire House",
    "wof:placetype":"venue"
},
  "geometry": {"coordinates":[-118.499514,34.018729],"type":"Point"}
}