{
  "type": "Feature",
  "properties": {
    "iso:country":"US",
    "sg:address":"11340 Broadview Dr",
    "sg:city":"Moorpark",
    "sg:classifiers":[
        {
            "category":"Professional",
            "subcategory":"Management & Consulting",
            "type":"Services"
        }
    ],
    "sg:phone":"+1 805 529 8781",
    "sg:postcode":"93021",
    "sg:province":"CA",
    "sg:tags":[
        "consultant",
        "business"
    ],
    "sg:website":"www.pathometrix.com",
    "wof:name":"Pathometrix",
    "wof:placetype":"venue"
},
  "geometry": {"coordinates":[-118.90716999999999,34.268356],"type":"Point"}
}