{
  "type": "Feature",
  "properties": {
    "addr:full":"373 S Palm Canyon Dr Ste A Palm Springs CA 92262",
    "addr:housenumber":"373",
    "addr:postcode":"92262",
    "addr:street":"S Palm Canyon Dr Ste A",
    "iso:country":"US",
    "sg:address":"373 S Palm Canyon Dr Ste A",
    "sg:city":"Palm Springs",
    "sg:classifiers":[
        {
            "category":"Home & Garden",
            "subcategory":"Furniture",
            "type":"Retail Goods"
        }
    ],
    "sg:phone":"+1 760 778 6224",
    "sg:postcode":"92262",
    "sg:province":"CA",
    "sg:tags":[
        "store"
    ],
    "wof:name":"Vintage Oasis",
    "wof:placetype":"venue"
},
  "geometry": {"coordinates":[-116.546954,33.818137],"type":"Point"}
}