{
  "type": "Feature",
  "properties": {
    "addr:full":"610 W 6th St Los Angeles CA 90017",
    "addr:housenumber":"610",
    "addr:postcode":"90017",
    "addr:street":"W 6Th St",
    "iso:country":"US",
    "sg:address":"610 W 6th St",
    "sg:city":"Los Angeles",
    "sg:classifiers":[
        {
            "category":"Restaurant",
            "type":"Food & Drink"
        }
    ],
    "sg:phone":"+1 213 623 3362",
    "sg:postcode":"90017",
    "sg:province":"CA",
    "sg:tags":[
        "caterer"
    ],
    "sg:website":"www.yorkshiregrillla.com",
    "wof:name":"Yorkshire Grill",
    "wof:placetype":"venue"
},
  "geometry": {"coordinates":[-118.25563200000001,34.048872],"type":"Point"}
}