{
  "type": "Feature",
  "properties": {
    "iso:country":"US",
    "sg:address":"7947 Greenback Ln",
    "sg:city":"Citrus Heights",
    "sg:classifiers":[
        {
            "category":"Shopping",
            "subcategory":"Mobile Phones",
            "type":"Retail Goods"
        }
    ],
    "sg:phone":"+1 916 721 3600",
    "sg:postcode":"95610",
    "sg:province":"CA",
    "wof:name":"Sprint Store",
    "wof:placetype":"venue"
},
  "geometry": {"coordinates":[-121.26799800000001,38.6786],"type":"Point"}
}