{
  "type": "Feature",
  "properties": {
    "addr:full":"9155 el Camino Real Atascadero CA 93422",
    "addr:housenumber":"9155",
    "addr:postcode":"93422",
    "addr:street":"El Camino Real",
    "iso:country":"US",
    "sg:address":"9155 el Camino Real",
    "sg:city":"Atascadero",
    "sg:classifiers":[
        {
            "category":"Restaurant",
            "type":"Food & Drink"
        }
    ],
    "sg:phone":"+1 805 461 8222",
    "sg:postcode":"93422",
    "sg:province":"CA",
    "wof:name":"Margarita's",
    "wof:placetype":"venue"
},
  "geometry": {"coordinates":[-120.651911,35.469256],"type":"Point"}
}