{
  "type": "Feature",
  "properties": {
    "iso:country":"US",
    "sg:address":"7949 Ramona Ave",
    "sg:city":"Sacramento",
    "sg:classifiers":[
        {
            "category":"Wholesale",
            "subcategory":"Machinery & Supplies",
            "type":"Manufacturing & Wholesale Goods"
        }
    ],
    "sg:phone":"+1 916 452 4849",
    "sg:postcode":"95826",
    "sg:province":"CA",
    "sg:tags":[
        "equipment",
        "industrial"
    ],
    "wof:name":"Coast Line Supply",
    "wof:placetype":"venue"
},
  "geometry": {"coordinates":[-121.413417,38.544638],"type":"Point"}
}