{
  "type": "Feature",
  "properties": {
    "addr:full":"215 W Main St Santa Maria CA 93458",
    "addr:housenumber":"215",
    "addr:postcode":"93458",
    "addr:street":"W Main St",
    "iso:country":"US",
    "sg:address":"215 W Main St",
    "sg:city":"Santa Maria",
    "sg:classifiers":[
        {
            "category":"Shopping",
            "subcategory":"Clothing, Apparel, & Fashions",
            "type":"Retail Goods"
        }
    ],
    "sg:phone":"+1 805 347 1233",
    "sg:postcode":"93458",
    "sg:province":"CA",
    "wof:name":"RAD Thrift Store",
    "wof:placetype":"venue"
},
  "geometry": {"coordinates":[-120.43755899999999,34.953296],"type":"Point"}
}