{
  "type": "Feature",
  "properties": {
    "iso:country":"US",
    "sg:address":"1734 Canberra Pl",
    "sg:city":"El Dorado Hills",
    "sg:classifiers":[
        {
            "category":"Manufacturing",
            "subcategory":"Chemicals & Compounds",
            "type":"Manufacturing & Wholesale Goods"
        }
    ],
    "sg:phone":"+1 916 939 0839",
    "sg:postcode":"95762",
    "sg:province":"CA",
    "wof:name":"Noveon Inc",
    "wof:placetype":"venue"
},
  "geometry": {"coordinates":[-121.06961,38.683817],"type":"Point"}
}