{
  "type": "Feature",
  "properties": {
    "addr:full":"3755 Avocado Blvd #123 La Mesa CA 91941",
    "addr:housenumber":"3755",
    "addr:postcode":"91941",
    "addr:street":"Avocado Blvd # 123",
    "iso:country":"US",
    "sg:address":"3755 Avocado Blvd #123",
    "sg:city":"La Mesa",
    "sg:classifiers":[
        {
            "category":"Personal",
            "type":"Services"
        }
    ],
    "sg:phone":"+1 800 899 8896",
    "sg:postcode":"91941",
    "sg:province":"CA",
    "sg:tags":[
        "sewing",
        "alteration"
    ],
    "sg:website":"www.symbolixpatches.com",
    "wof:name":"Symbolix Patches",
    "wof:placetype":"venue"
},
  "geometry": {"coordinates":[-116.96197100000001,32.747562],"type":"Point"}
}