{
  "type": "Feature",
  "properties": {
    "addr:full":"2324 7th St Wasco CA 93280",
    "addr:housenumber":"2324",
    "addr:postcode":"ca 93280",
    "addr:street":"7Th St",
    "iso:country":"US",
    "sg:address":"2324 7th St",
    "sg:city":"Wasco",
    "sg:classifiers":[
        {
            "category":"Local Transit",
            "type":"Transportation"
        }
    ],
    "sg:phone":"+1 661 758 3200",
    "sg:postcode":"93280",
    "sg:province":"CA",
    "sg:tags":[
        "ambulance"
    ],
    "wof:name":"KERN Ambulance",
    "wof:placetype":"venue"
},
  "geometry": {"coordinates":[-119.353493,35.594367],"type":"Point"}
}