{
  "type": "Feature",
  "properties": {
    "iso:country":"US",
    "sg:address":"1700 E Harding Way",
    "sg:city":"Stockton",
    "sg:classifiers":[
        {
            "category":"Organizations",
            "subcategory":"Religious Organization",
            "type":"Services"
        }
    ],
    "sg:phone":"+1 209 943 2201",
    "sg:postcode":"95205",
    "sg:province":"CA",
    "sg:tags":[
        "church"
    ],
    "wof:name":"Heavenly Gate Missionary Chr",
    "wof:placetype":"venue"
},
  "geometry": {"coordinates":[-121.27208,37.971205],"type":"Point"}
}