{
  "type": "Feature",
  "properties": {
    "iso:country":"US",
    "sg:address":"10015 Palisades Dr",
    "sg:city":"Truckee",
    "sg:classifiers":[
        {
            "category":"Real Estate",
            "subcategory":"Real Estate Agent",
            "type":"Services"
        }
    ],
    "sg:phone":"+1 530 587 4500",
    "sg:postcode":"96161",
    "sg:province":"CA",
    "sg:tags":[
        "rental",
        "vacation"
    ],
    "sg:website":"www.mvvr.com",
    "wof:name":"Martis Valley Vacation Rentals",
    "wof:placetype":"venue"
},
  "geometry": {"coordinates":[-120.177128,39.326035],"type":"Point"}
}