{
  "type": "Feature",
  "properties": {
    "addr:full":"1129 Weber Way Sacramento CA 95822",
    "addr:housenumber":"1129",
    "addr:postcode":"95822",
    "addr:street":"Weber Way",
    "iso:country":"US",
    "sg:address":"1129 Weber Way",
    "sg:city":"Sacramento",
    "sg:classifiers":[
        {
            "category":"Food & Beverages",
            "subcategory":"Liquor & Beverages",
            "type":"Retail Goods"
        },
        {
            "category":"Food & Beverages",
            "subcategory":"Groceries & Convenience Stores",
            "type":"Retail Goods"
        }
    ],
    "sg:phone":"+1 916 442 5984",
    "sg:postcode":"95822",
    "sg:province":"CA",
    "sg:tags":[
        "juice",
        "bottler",
        "beverages-distributors"
    ],
    "wof:name":"Hydropot Grow Juice",
    "wof:placetype":"venue"
},
  "geometry": {"coordinates":[-121.514025,38.534453],"type":"Point"}
}