{
  "type": "Feature",
  "properties": {
    "addr:full":"130 Larkspur St Brookdale CA 95007",
    "addr:housenumber":"130",
    "addr:postcode":"95007",
    "addr:street":"Larkspur St",
    "iso:country":"US",
    "sg:address":"130 Larkspur St",
    "sg:city":"Brookdale",
    "sg:classifiers":[
        {
            "category":"Professional",
            "type":"Services"
        }
    ],
    "sg:phone":"+1 831 338 6590",
    "sg:postcode":"95007",
    "sg:province":"CA",
    "sg:tags":[
        "establishment"
    ],
    "wof:name":"Hackerlabs 1",
    "wof:placetype":"venue"
},
  "geometry": {"coordinates":[-122.10622600000001,37.106343],"type":"Point"}
}