{
  "type": "Feature",
  "properties": {
    "addr:full":"5830 Gage Ave Bell Gardens CA 90201",
    "addr:housenumber":"5830",
    "addr:postcode":"90201",
    "addr:street":"Gage Ave",
    "iso:country":"US",
    "sg:address":"5830 Gage Ave",
    "sg:city":"Bell Gardens",
    "sg:classifiers":[
        {
            "category":"Real Estate",
            "subcategory":"Real Estate Services",
            "type":"Services"
        }
    ],
    "sg:phone":"+1 323 587 6795",
    "sg:postcode":"90201",
    "sg:province":"CA",
    "sg:tags":[
        "management",
        "property"
    ],
    "wof:name":"Infinite Real Estate",
    "wof:placetype":"venue"
},
  "geometry": {"coordinates":[-118.16112,33.975214],"type":"Point"}
}