{
  "type": "Feature",
  "properties": {
    "addr:full":"1497 S Gage St San Bernardino CA 92408",
    "addr:housenumber":"1497",
    "addr:postcode":"92408",
    "addr:street":"S Gage St",
    "iso:country":"US",
    "sg:address":"1497 S Gage St",
    "sg:city":"San Bernardino",
    "sg:classifiers":[
        {
            "category":"Freight",
            "type":"Transportation"
        }
    ],
    "sg:phone":"+1 909 478 9711",
    "sg:postcode":"92408",
    "sg:province":"CA",
    "sg:tags":[
        "transport"
    ],
    "wof:name":"Golden State Envmtl Svcs",
    "wof:placetype":"venue"
},
  "geometry": {"coordinates":[-117.265,34.075478],"type":"Point"}
}