{
  "type": "Feature",
  "properties": {
    "addr:full":"4339 E Imperial Hwy Lynwood CA 90262",
    "addr:housenumber":"4339",
    "addr:postcode":"90262",
    "addr:street":"E Imperial Hwy",
    "iso:country":"US",
    "sg:address":"4339 E Imperial Hwy",
    "sg:city":"Lynwood",
    "sg:classifiers":[
        {
            "category":"Restaurant",
            "type":"Food & Drink"
        }
    ],
    "sg:menulink":"http://www.allmenus.com/ca/compton/197999-kfc---kentucky-fried-chicken/menu/",
    "sg:phone":"+1 310 608 1518",
    "sg:postcode":"90262",
    "sg:province":"CA",
    "sg:tags":[
        "american",
        "chicken"
    ],
    "wof:name":"KFC - Kentucky Fried Chicken",
    "wof:placetype":"venue"
},
  "geometry": {"coordinates":[-118.18499199999999,33.930838],"type":"Point"}
}