{
  "type": "Feature",
  "properties": {
    "addr:full":"12850 Seal Beach Blvd Seal Beach CA 90740",
    "addr:housenumber":"12850",
    "addr:postcode":"90740",
    "addr:street":"Seal Beach Blvd",
    "iso:country":"US",
    "sg:address":"12850 Seal Beach Blvd",
    "sg:city":"Seal Beach",
    "sg:classifiers":[
        {
            "category":"Travel",
            "subcategory":"Hotels & Motels",
            "type":"Entertainment"
        }
    ],
    "sg:phone":"+1 562 596 8330",
    "sg:postcode":"90740",
    "sg:province":"CA",
    "sg:website":"www.ayressealbeach.com",
    "wof:name":"Ayres Hotel Seal Beach",
    "wof:placetype":"venue"
},
  "geometry": {"coordinates":[-118.07241500000001,33.776025],"type":"Point"}
}