{
  "type": "Feature",
  "properties": {
    "iso:country":"US",
    "sg:address":"38420 Sierra Hwy",
    "sg:city":"Palmdale",
    "sg:classifiers":[
        {
            "category":"Shopping",
            "subcategory":"Used Merchandise",
            "type":"Retail Goods"
        }
    ],
    "sg:phone":"+1 661 267 2403",
    "sg:postcode":"93550",
    "sg:province":"CA",
    "sg:tags":[
        "appliance"
    ],
    "wof:name":"Antelope Valley Discount Aplnc",
    "wof:placetype":"venue"
},
  "geometry": {"coordinates":[-118.116569,34.579901],"type":"Point"}
}