{
  "type": "Feature",
  "properties": {
    "addr:full":"2341 Poipu Way San Diego CA 92154",
    "addr:housenumber":"2341",
    "addr:postcode":"92154",
    "addr:street":"Poipu Way",
    "iso:country":"US",
    "sg:address":"2341 Poipu Way",
    "sg:city":"San Diego",
    "sg:classifiers":[
        {
            "category":"Building & Trades",
            "subcategory":"Construction",
            "type":"Services"
        }
    ],
    "sg:phone":"+1 619 575 0639",
    "sg:postcode":"92154",
    "sg:province":"CA",
    "sg:tags":[
        "coping",
        "plastering",
        "tiling",
        "pool",
        "swimming"
    ],
    "wof:name":"Conradi's Pool Svc",
    "wof:placetype":"venue"
},
  "geometry": {"coordinates":[-117.068347,32.586228],"type":"Point"}
}