{
  "type": "Feature",
  "properties": {
    "iso:country":"US",
    "sg:address":"2425 Olympic Blvd",
    "sg:city":"Santa Monica",
    "sg:classifiers":[
        {
            "category":"Utilities",
            "subcategory":"Cable",
            "type":"Services"
        }
    ],
    "sg:phone":"+1 310 315 0816",
    "sg:postcode":"90404",
    "sg:province":"CA",
    "sg:tags":[
        "television"
    ],
    "wof:name":"Cablevision IFC",
    "wof:placetype":"venue"
},
  "geometry": {"coordinates":[-118.470711,34.02766],"type":"Point"}
}