{
  "type": "Feature",
  "properties": {
    "iso:country":"US",
    "sg:address":"4887 La Palma Ave",
    "sg:city":"La Palma",
    "sg:classifiers":[
        {
            "category":"Health Services",
            "subcategory":"Doctor",
            "type":"Services"
        }
    ],
    "sg:phone":"+1 562 402 4555",
    "sg:postcode":"90623",
    "sg:province":"CA",
    "sg:tags":[
        "surgeon",
        "oral"
    ],
    "wof:name":"Kang Kyu S DDS",
    "wof:placetype":"venue"
},
  "geometry": {"coordinates":[-118.047997,33.846401],"type":"Point"}
}