{
  "type": "Feature",
  "properties": {
    "addr:full":"2705 Morgan Territory Rd Clayton CA 94517",
    "addr:housenumber":"2705",
    "addr:postcode":"94517",
    "addr:street":"Morgan Territory Rd",
    "iso:country":"US",
    "sg:address":"2705 Morgan Territory Rd",
    "sg:city":"Clayton",
    "sg:classifiers":[
        {
            "category":"Personal",
            "subcategory":"Beauty Salon",
            "type":"Services"
        }
    ],
    "sg:phone":"+1 925 672 4131",
    "sg:postcode":"94517",
    "sg:province":"CA",
    "wof:name":"First Impressions By Sand",
    "wof:placetype":"venue"
},
  "geometry": {"coordinates":[-121.87226200000001,37.896714],"type":"Point"}
}