{
  "type": "Feature",
  "properties": {
    "iso:country":"US",
    "sg:address":"5320 W Holland Ave",
    "sg:city":"Fresno",
    "sg:classifiers":[
        {
            "category":"Taxi",
            "type":"Transportation"
        }
    ],
    "sg:phone":"+1 559 276 5778",
    "sg:postcode":"93722",
    "sg:province":"CA",
    "sg:tags":[
        "taxicab"
    ],
    "wof:name":"Tapinder Bhandal Taxi Svc",
    "wof:placetype":"venue"
},
  "geometry": {"coordinates":[-119.886534,36.7976],"type":"Point"}
}