{
  "type": "Feature",
  "properties": {
    "iso:country":"US",
    "sg:address":"220 47th St",
    "sg:city":"San Diego",
    "sg:classifiers":[
        {
            "category":"Real Estate",
            "subcategory":"Real Estate Operator",
            "type":"Services"
        }
    ],
    "sg:phone":"+1 619 263 2686",
    "sg:postcode":"92102",
    "sg:province":"CA",
    "sg:tags":[
        "apartment"
    ],
    "wof:name":"Creekside Villa Apartments",
    "wof:placetype":"venue"
},
  "geometry": {"coordinates":[-117.09371400000001,32.706358],"type":"Point"}
}