{
  "type": "Feature",
  "properties": {
    "addr:full":"19682 Hirsch Ct Anderson CA 96007",
    "addr:housenumber":"19682",
    "addr:postcode":"96007",
    "addr:street":"Hirsch Ct",
    "iso:country":"US",
    "sg:address":"19682 Hirsch Ct",
    "sg:city":"Anderson",
    "sg:classifiers":[
        {
            "category":"Professional",
            "type":"Services"
        }
    ],
    "sg:phone":"+1 530 365 9920",
    "sg:postcode":"96007",
    "sg:province":"CA",
    "sg:tags":[
        "establishment"
    ],
    "wof:name":"Ancient Innovation Corporation",
    "wof:placetype":"venue"
},
  "geometry": {"coordinates":[-122.31833,40.466109],"type":"Point"}
}