{
  "type": "Feature",
  "properties": {
    "addr:full":"9033 McFadden Ave Westminster CA 92683",
    "addr:housenumber":"9033",
    "addr:postcode":"92683",
    "addr:street":"Mcfadden Ave",
    "iso:country":"US",
    "sg:address":"9033 McFadden Ave",
    "sg:city":"Westminster",
    "sg:classifiers":[
        {
            "category":"Professional",
            "type":"Services"
        }
    ],
    "sg:phone":"+1 714 892 5851",
    "sg:postcode":"92683",
    "sg:province":"CA",
    "sg:tags":[
        "caterer"
    ],
    "wof:name":"AAA Catering",
    "wof:placetype":"venue"
},
  "geometry": {"coordinates":[-117.971412,33.737643],"type":"Point"}
}