{
  "type": "Feature",
  "properties": {
    "addr:full":"9600 Cozycroft Ave Ste D Chatsworth CA 91311",
    "addr:housenumber":"9600",
    "addr:postcode":"91311",
    "addr:street":"Cozycroft Ave Ste D",
    "iso:country":"US",
    "sg:address":"9600 Cozycroft Ave Ste D",
    "sg:city":"Chatsworth",
    "sg:classifiers":[
        {
            "category":"Shopping",
            "subcategory":"Stationery & Office Supplies",
            "type":"Retail Goods"
        },
        {
            "category":"Manufacturing",
            "subcategory":"Paper Products",
            "type":"Manufacturing & Wholesale Goods"
        }
    ],
    "sg:phone":"+1 818 700 8500",
    "sg:postcode":"91311",
    "sg:province":"CA",
    "sg:tags":[
        "equipment",
        "laminations",
        "laminating",
        "plastic"
    ],
    "wof:name":"Arrow Laminating",
    "wof:placetype":"venue"
},
  "geometry": {"coordinates":[-118.581974,34.244538],"type":"Point"}
}