{
  "type": "Feature",
  "properties": {
    "addr:full":"25431 Trabuco Rd Lake Forest CA 92630",
    "addr:housenumber":"25431",
    "addr:postcode":"92630",
    "addr:street":"Trabuco Rd",
    "iso:country":"US",
    "sg:address":"25431 Trabuco Rd",
    "sg:city":"Lake Forest",
    "sg:classifiers":[
        {
            "category":"Sports & Exercise",
            "subcategory":"Gym",
            "type":"Entertainment"
        }
    ],
    "sg:phone":"+1 949 588 6293",
    "sg:postcode":"92630",
    "sg:province":"CA",
    "sg:tags":[
        "club",
        "health",
        "studio",
        "gymnasium"
    ],
    "wof:name":"Amazing Pace Women's Fitness",
    "wof:placetype":"venue"
},
  "geometry": {"coordinates":[-117.687343,33.648924],"type":"Point"}
}