{
  "type": "Feature",
  "properties": {
    "addr:full":"17095 Western Ave Torrance CA 90510",
    "addr:housenumber":"17095",
    "addr:postcode":"90510",
    "addr:street":"Western Ave",
    "iso:country":"US",
    "sg:address":"17095 Western Ave",
    "sg:city":"Torrance",
    "sg:classifiers":[
        {
            "category":"Restaurant",
            "type":"Food & Drink"
        }
    ],
    "sg:phone":"+1 310 324 7077",
    "sg:postcode":"90510",
    "sg:province":"CA",
    "sg:tags":[
        "korean"
    ],
    "wof:name":"Western Soondae",
    "wof:placetype":"venue"
},
  "geometry": {"coordinates":[-118.309106,33.83733],"type":"Point"}
}