{
  "type": "Feature",
  "properties": {
    "iso:country":"US",
    "sg:address":"712 Bancroft Rd",
    "sg:city":"Walnut Creek",
    "sg:classifiers":[
        {
            "category":"Building & Trades",
            "subcategory":"Landscaping Services",
            "type":"Services"
        }
    ],
    "sg:phone":"+1 925 946 9008",
    "sg:postcode":"94598",
    "sg:province":"CA",
    "sg:tags":[
        "landscape",
        "contractor"
    ],
    "wof:name":"Liedstrand Landscape Cnstr",
    "wof:placetype":"venue"
},
  "geometry": {"coordinates":[-122.041144,37.927814],"type":"Point"}
}