{
  "type": "Feature",
  "properties": {
    "iso:country":"US",
    "sg:address":"7965 Ave Navidad",
    "sg:city":"San Diego",
    "sg:classifiers":[
        {
            "category":"Wholesale",
            "subcategory":"Sporting Goods",
            "type":"Manufacturing & Wholesale Goods"
        }
    ],
    "sg:phone":"+1 760 230 2035",
    "sg:postcode":"92122",
    "sg:province":"CA",
    "sg:tags":[
        "exporter"
    ],
    "wof:name":"E N P",
    "wof:placetype":"venue"
},
  "geometry": {"coordinates":[-117.211248,32.86391],"type":"Point"}
}