{
  "type": "Feature",
  "properties": {
    "addr:full":"5455 8th St Carpinteria CA 93013",
    "addr:housenumber":"5455",
    "addr:postcode":"93013",
    "addr:street":"8Th St",
    "iso:country":"US",
    "sg:address":"5455 8th St",
    "sg:city":"Carpinteria",
    "sg:classifiers":[
        {
            "category":"Retail",
            "subcategory":"Repair Shop",
            "type":"Services"
        }
    ],
    "sg:phone":"+1 805 684 5054",
    "sg:postcode":"93013",
    "sg:province":"CA",
    "sg:tags":[
        "signal",
        "construction",
        "traffic",
        "maintenance"
    ],
    "wof:name":"Traffic Signal Maintenance",
    "wof:placetype":"venue"
},
  "geometry": {"coordinates":[-119.51502499999999,34.393401],"type":"Point"}
}