{
  "type": "Feature",
  "properties": {
    "addr:full":"519 S Center St Turlock CA 95380",
    "addr:housenumber":"519",
    "addr:postcode":"95380",
    "addr:street":"S Center St",
    "iso:country":"US",
    "sg:address":"519 S Center St",
    "sg:city":"Turlock",
    "sg:classifiers":[
        {
            "category":"Professional",
            "subcategory":"Engineering",
            "type":"Services"
        },
        {
            "category":"Autos & Motor Vehicles",
            "subcategory":"Automobile Sales",
            "type":"Retail Goods"
        }
    ],
    "sg:phone":"+1 209 668 1099",
    "sg:postcode":"95380",
    "sg:province":"CA",
    "sg:tags":[
        "classic"
    ],
    "wof:name":"Reed's Restoration & Machine",
    "wof:placetype":"venue"
},
  "geometry": {"coordinates":[-120.838765,37.489826],"type":"Point"}
}