{
  "type": "Feature",
  "properties": {
    "iso:country":"US",
    "sg:address":"2025 N Long Beach Boulevard",
    "sg:city":"Compton",
    "sg:classifiers":[
        {
            "category":"Shopping",
            "subcategory":"Party Supplies",
            "type":"Retail Goods"
        },
        {
            "category":"Personal",
            "type":"Services"
        }
    ],
    "sg:phone":"+1 310 637 1685",
    "sg:postcode":"90221",
    "sg:province":"CA",
    "sg:tags":[
        "planning",
        "event"
    ],
    "wof:name":"El Paraiso Party Supply",
    "wof:placetype":"venue"
},
  "geometry": {"coordinates":[-118.208876,33.909471],"type":"Point"}
}