{
  "type": "Feature",
  "properties": {
    "iso:country":"US",
    "sg:address":"93 N Lake Ave",
    "sg:city":"Pasadena",
    "sg:classifiers":[
        {
            "category":"Restaurant",
            "type":"Food & Drink"
        }
    ],
    "sg:phone":"+1 626 793 2448",
    "sg:postcode":"91101",
    "sg:province":"CA",
    "sg:tags":[
        "japanese"
    ],
    "wof:name":"Midori",
    "wof:placetype":"venue"
},
  "geometry": {"coordinates":[-118.13200399999999,34.147701],"type":"Point"}
}