{
  "type": "Feature",
  "properties": {
    "iso:country":"US",
    "sg:address":"936 Oller St",
    "sg:city":"Mendota",
    "sg:classifiers":[
        {
            "category":"Shopping",
            "subcategory":"Gifts & Souvenirs",
            "type":"Retail Goods"
        }
    ],
    "sg:phone":"+1 559 655 8076",
    "sg:postcode":"93640",
    "sg:province":"CA",
    "sg:tags":[
        "shop"
    ],
    "wof:name":"Baby Gifts",
    "wof:placetype":"venue"
},
  "geometry": {"coordinates":[-120.377459,36.75287],"type":"Point"}
}