{
  "type": "Feature",
  "properties": {
    "addr:full":"300 Sands Dr San Jose CA 95125",
    "addr:housenumber":"300",
    "addr:postcode":"95125",
    "addr:street":"Sands Dr",
    "iso:country":"US",
    "sg:address":"300 Sands Dr",
    "sg:city":"San Jose",
    "sg:classifiers":[
        {
            "category":"Real Estate",
            "subcategory":"Real Estate Operator",
            "type":"Services"
        }
    ],
    "sg:phone":"+1 408 448 1592",
    "sg:postcode":"95125",
    "sg:province":"CA",
    "sg:tags":[
        "apartment"
    ],
    "wof:name":"Canoas Terrace",
    "wof:placetype":"venue"
},
  "geometry": {"coordinates":[-121.8717,37.289547],"type":"Point"}
}