{
  "type": "Feature",
  "properties": {
    "addr:full":"2547 8th St Berkeley CA 94710",
    "addr:housenumber":"2547",
    "addr:postcode":"94710",
    "addr:street":"8Th St",
    "iso:country":"US",
    "sg:address":"2547 8th St",
    "sg:city":"Berkeley",
    "sg:classifiers":[
        {
            "category":"Home & Garden",
            "subcategory":"Home Furnishings",
            "type":"Retail Goods"
        }
    ],
    "sg:phone":"+1 510 841 8135",
    "sg:postcode":"94710",
    "sg:province":"CA",
    "sg:tags":[
        "pottery"
    ],
    "wof:name":"Bob Pool Pottery",
    "wof:placetype":"venue"
},
  "geometry": {"coordinates":[-122.29275699999999,37.860042],"type":"Point"}
}