{
  "type": "Feature",
  "properties": {
    "addr:full":"1255 Battery St San Francisco CA 94111",
    "addr:housenumber":"1255",
    "addr:postcode":"94111",
    "addr:street":"Battery St",
    "iso:country":"US",
    "sg:address":"1255 Battery St",
    "sg:city":"San Francisco",
    "sg:classifiers":[
        {
            "category":"Restaurant",
            "type":"Food & Drink"
        }
    ],
    "sg:phone":"+1 415 397 1230",
    "sg:postcode":"94111",
    "sg:province":"CA",
    "wof:name":"Chili-Up",
    "wof:placetype":"venue"
},
  "geometry": {"coordinates":[-122.401974,37.802715],"type":"Point"}
}