{
  "type": "Feature",
  "properties": {
    "iso:country":"US",
    "sg:address":"3698 S Chestnut Ave",
    "sg:city":"Fresno",
    "sg:classifiers":[
        {
            "category":"Freight",
            "type":"Transportation"
        }
    ],
    "sg:phone":"+1 559 485 5865",
    "sg:postcode":"93725",
    "sg:province":"CA",
    "sg:tags":[
        "trucking"
    ],
    "wof:name":"Lake Shore Pacific Corp",
    "wof:placetype":"venue"
},
  "geometry": {"coordinates":[-119.736725,36.681332],"type":"Point"}
}