{
  "type": "Feature",
  "properties": {
    "iso:country":"US",
    "sg:address":"1451 W Capitol Ave",
    "sg:city":"West Sacramento",
    "sg:classifiers":[
        {
            "category":"Travel",
            "subcategory":"Hotels & Motels",
            "type":"Entertainment"
        }
    ],
    "sg:phone":"+1 916 371 0931",
    "sg:postcode":"95691",
    "sg:province":"CA",
    "wof:name":"Stardust Motel",
    "wof:placetype":"venue"
},
  "geometry": {"coordinates":[-121.52800000000001,38.580299],"type":"Point"}
}