{
  "type": "Feature",
  "properties": {
    "iso:country":"US",
    "sg:address":"251 Arthur Rd",
    "sg:city":"Martinez",
    "sg:classifiers":[
        {
            "category":"Professional",
            "subcategory":"Engineering",
            "type":"Services"
        }
    ],
    "sg:phone":"+1 925 229 5508",
    "sg:postcode":"94553",
    "sg:province":"CA",
    "sg:tags":[
        "general",
        "contractor"
    ],
    "wof:name":"Kel-Tec Builders",
    "wof:placetype":"venue"
},
  "geometry": {"coordinates":[-122.089024,38.010087],"type":"Point"}
}