{
  "type": "Feature",
  "properties": {
    "iso:country":"US",
    "sg:address":"4300 Holt Blvd",
    "sg:city":"Montclair",
    "sg:classifiers":[
        {
            "category":"Freight",
            "type":"Transportation"
        }
    ],
    "sg:phone":"+1 909 621 1607",
    "sg:postcode":"91763",
    "sg:province":"CA",
    "sg:tags":[
        "operator",
        "local",
        "trucking"
    ],
    "wof:name":"Maribel Trucking",
    "wof:placetype":"venue"
},
  "geometry": {"coordinates":[-117.707595,34.063252],"type":"Point"}
}