{
  "type": "Feature",
  "properties": {
    "iso:country":"US",
    "sg:address":"12439 Secretariat Dr",
    "sg:city":"Etiwanda",
    "sg:classifiers":[
        {
            "category":"Building & Trades",
            "subcategory":"Construction",
            "type":"Services"
        }
    ],
    "sg:phone":"+1 909 899 4967",
    "sg:postcode":"91739",
    "sg:province":"CA",
    "sg:tags":[
        "painter"
    ],
    "wof:name":"Born To Paint",
    "wof:placetype":"venue"
},
  "geometry": {"coordinates":[-117.532567,34.13903],"type":"Point"}
}