{
  "type": "Feature",
  "properties": {
    "addr:full":"1248 Washington St Red Bluff CA 96080",
    "addr:housenumber":"1248",
    "addr:postcode":"96080",
    "addr:street":"Washington St",
    "iso:country":"US",
    "sg:address":"1248 Washington St",
    "sg:city":"Red Bluff",
    "sg:classifiers":[
        {
            "category":"Professional",
            "subcategory":"Lawyer & Legal Services",
            "type":"Services"
        }
    ],
    "sg:phone":"+1 530 529 4266",
    "sg:postcode":"96080",
    "sg:province":"CA",
    "sg:tags":[
        "attorney"
    ],
    "wof:name":"Diane L Martin Logan",
    "wof:placetype":"venue"
},
  "geometry": {"coordinates":[-122.240188,40.181909],"type":"Point"}
}