{
  "type": "Feature",
  "properties": {
    "iso:country":"US",
    "sg:address":"4064 Lemonberry Pl",
    "sg:city":"Thousand Oaks",
    "sg:classifiers":[
        {
            "category":"Professional",
            "type":"Services"
        }
    ],
    "sg:phone":"+1 805 531 5465",
    "sg:postcode":"91362",
    "sg:province":"CA",
    "wof:name":"Ibci",
    "wof:placetype":"venue"
},
  "geometry": {"coordinates":[-118.84151300000001,34.234956],"type":"Point"}
}