{
  "type": "Feature",
  "properties": {
    "addr:full":"3031 Red Hat Ln Whittier CA 90601",
    "addr:housenumber":"3031",
    "addr:postcode":"90601",
    "addr:street":"Red Hat Ln",
    "iso:country":"US",
    "sg:address":"3031 Red Hat Ln",
    "sg:city":"Whittier",
    "sg:classifiers":[
        {
            "category":"Wholesale",
            "subcategory":"Non-durable Goods",
            "type":"Manufacturing & Wholesale Goods"
        }
    ],
    "sg:phone":"+1 562 692 8879",
    "sg:postcode":"90601",
    "sg:province":"CA",
    "wof:name":"Twin Star Body Gear Inc",
    "wof:placetype":"venue"
},
  "geometry": {"coordinates":[-118.03887,34.024486],"type":"Point"}
}