{
  "type": "Feature",
  "properties": {
    "iso:country":"US",
    "sg:address":"2510 S San Pedro St",
    "sg:city":"Los Angeles",
    "sg:classifiers":[
        {
            "category":"Shopping",
            "subcategory":"Party Supplies",
            "type":"Retail Goods"
        }
    ],
    "sg:phone":"+1 213 748 1193",
    "sg:postcode":"90011",
    "sg:province":"CA",
    "wof:name":"Jessica's Jumpers & Party Supplies",
    "wof:placetype":"venue"
},
  "geometry": {"coordinates":[-118.260796,34.209955],"type":"Point"}
}