{
  "type": "Feature",
  "properties": {
    "addr:full":"1050 Melody Ln Roseville CA 95678",
    "addr:housenumber":"1050",
    "addr:postcode":"95678",
    "addr:street":"Melody Ln",
    "iso:country":"US",
    "sg:address":"1050 Melody Ln",
    "sg:city":"Roseville",
    "sg:classifiers":[
        {
            "category":"Professional",
            "subcategory":"Business Services",
            "type":"Services"
        }
    ],
    "sg:phone":"+1 916 783 7999",
    "sg:postcode":"95678",
    "sg:province":"CA",
    "sg:tags":[
        "trade",
        "fair",
        "show"
    ],
    "sg:website":"www.monsterdisplays.com",
    "wof:name":"Advantage Exhibit & Graphics",
    "wof:placetype":"venue"
},
  "geometry": {"coordinates":[-121.29093399999999,38.726567],"type":"Point"}
}