{
  "type": "Feature",
  "properties": {
    "iso:country":"US",
    "sg:address":"228 Nut Tree Rd",
    "sg:city":"Vacaville",
    "sg:classifiers":[
        {
            "category":"Shopping",
            "subcategory":"Clothing, Apparel, & Fashions",
            "type":"Retail Goods"
        }
    ],
    "sg:phone":"+1 707 447 9066",
    "sg:postcode":"95687",
    "sg:province":"CA",
    "sg:tags":[
        "apparel",
        "accessory",
        "women's"
    ],
    "sg:website":"http://www.anntaylor.com",
    "wof:name":"Ann Taylor",
    "wof:placetype":"venue"
},
  "geometry": {"coordinates":[-121.95528899999999,38.367366],"type":"Point"}
}