{
  "type": "Feature",
  "properties": {
    "iso:country":"US",
    "sg:address":"4891 Gold Spur Rd",
    "sg:city":"Shingle Springs",
    "sg:classifiers":[
        {
            "category":"Building & Trades",
            "subcategory":"Plumbing",
            "type":"Services"
        }
    ],
    "sg:phone":"+1 530 672 0964",
    "sg:postcode":"95682",
    "sg:province":"CA",
    "sg:tags":[
        "contractor"
    ],
    "wof:name":"American River Mechanical Inc",
    "wof:placetype":"venue"
},
  "geometry": {"coordinates":[-120.97077400000001,38.64003],"type":"Point"}
}