{
  "type": "Feature",
  "properties": {
    "iso:country":"US",
    "sg:address":"2740 W Olympic Boulevard",
    "sg:city":"Los Angeles",
    "sg:classifiers":[
        {
            "category":"Restaurant",
            "type":"Food & Drink"
        }
    ],
    "sg:phone":"+1 213 380 7759",
    "sg:postcode":"90006",
    "sg:province":"CA",
    "wof:name":"Peking Dumpling",
    "wof:placetype":"venue"
},
  "geometry": {"coordinates":[-118.293288,34.052772],"type":"Point"}
}