{
  "type": "Feature",
  "properties": {
    "iso:country":"US",
    "sg:address":"48125 Alder Ln",
    "sg:city":"Palm Desert",
    "sg:classifiers":[
        {
            "category":"Professional",
            "type":"Services"
        }
    ],
    "sg:phone":"+1 760 346 1218",
    "sg:postcode":"92260",
    "sg:province":"CA",
    "wof:name":"Fancy Pants",
    "wof:placetype":"venue"
},
  "geometry": {"coordinates":[-116.37823,33.69853],"type":"Point"}
}