{
  "type": "Feature",
  "properties": {
    "iso:country":"US",
    "sg:address":"1100 E Hamilton Avenue",
    "sg:city":"Campbell",
    "sg:classifiers":[
        {
            "category":"Education",
            "subcategory":"Special Training",
            "type":"Public Place"
        }
    ],
    "sg:phone":"+1 408 377 1113",
    "sg:postcode":"95008",
    "sg:province":"CA",
    "sg:tags":[
        "school",
        "language"
    ],
    "wof:name":"Languages Institute.",
    "wof:placetype":"venue"
},
  "geometry": {"coordinates":[-121.931318,37.29424],"type":"Point"}
}