{
  "type": "Feature",
  "properties": {
    "iso:country":"US",
    "sg:address":"901 Sagebrush Pl",
    "sg:city":"Newbury Park",
    "sg:classifiers":[
        {
            "category":"Professional",
            "type":"Services"
        }
    ],
    "sg:phone":"+1 805 480 1877",
    "sg:postcode":"91320",
    "sg:province":"CA",
    "sg:tags":[
        "hanging",
        "contractor"
    ],
    "wof:name":"Tole Fairy Dctn Arts Studio",
    "wof:placetype":"venue"
},
  "geometry": {"coordinates":[-118.94695,34.161242],"type":"Point"}
}