{
  "type": "Feature",
  "properties": {
    "iso:country":"US",
    "sg:address":"1210 Hollenbeck Ave",
    "sg:city":"Sunnyvale",
    "sg:classifiers":[
        {
            "category":"Building & Trades",
            "subcategory":"Landscaping Services",
            "type":"Services"
        }
    ],
    "sg:phone":"+1 408 732 1587",
    "sg:postcode":"94087",
    "sg:province":"CA",
    "sg:tags":[
        "landscape",
        "contractor"
    ],
    "wof:name":"Leonard's Landscaping",
    "wof:placetype":"venue"
},
  "geometry": {"coordinates":[-122.04145,37.353922],"type":"Point"}
}