{
  "type": "Feature",
  "properties": {
    "iso:country":"US",
    "sg:address":"1990 El Camino Real",
    "sg:city":"Santa Clara",
    "sg:classifiers":[
        {
            "category":"Fast Food",
            "type":"Food & Drink"
        }
    ],
    "sg:phone":"+1 408 244 0281",
    "sg:postcode":"95050",
    "sg:province":"CA",
    "sg:tags":[
        "burger"
    ],
    "sg:website":"www.mcdonalds.com",
    "wof:name":"McDonald's",
    "wof:placetype":"venue"
},
  "geometry": {"coordinates":[-121.958866,37.35229],"type":"Point"}
}