{
  "type": "Feature",
  "properties": {
    "addr:full":"650 Townsend St San Francisco CA 94103",
    "addr:housenumber":"650",
    "addr:postcode":"94103",
    "addr:street":"Townsend St",
    "iso:country":"US",
    "sg:address":"650 Townsend St",
    "sg:city":"San Francisco",
    "sg:classifiers":[
        {
            "category":"Utilities",
            "subcategory":"Telephone",
            "type":"Services"
        }
    ],
    "sg:phone":"+1 415 462 5685",
    "sg:postcode":"94103",
    "sg:province":"CA",
    "sg:tags":[
        "communications",
        "computer",
        "software"
    ],
    "wof:name":"Sputnik  Inc",
    "wof:placetype":"venue"
},
  "geometry": {"coordinates":[-122.403035,37.771011],"type":"Point"}
}