{
  "type": "Feature",
  "properties": {
    "addr:full":"645 Cabrillo Avenue, Suite 2 Santa Cruz CA 95065",
    "addr:housenumber":"645",
    "addr:postcode":"95065",
    "addr:street":"Cabrillo Avenue Suite 2",
    "iso:country":"US",
    "sg:address":"645 Cabrillo Avenue, Suite 2",
    "sg:city":"Santa Cruz",
    "sg:classifiers":[
        {
            "category":"Banks & Credit Unions",
            "subcategory":"Financial Services",
            "type":"Services"
        }
    ],
    "sg:phone":"+1 831 479 4782",
    "sg:postcode":"95065",
    "sg:province":"CA",
    "sg:website":"www.ptbservices.com",
    "wof:name":"PTB Services",
    "wof:placetype":"venue"
},
  "geometry": {"coordinates":[-121.97622699999999,37.006663],"type":"Point"}
}