{
  "type": "Feature",
  "properties": {
    "addr:full":"7094 Miramar Road San Diego CA 92121",
    "addr:housenumber":"7094",
    "addr:postcode":"92121",
    "addr:street":"Miramar Road",
    "iso:country":"US",
    "sg:address":"7094 Miramar Road",
    "sg:city":"San Diego",
    "sg:classifiers":[
        {
            "category":"Personal",
            "subcategory":"Beauty Salon",
            "type":"Services"
        }
    ],
    "sg:phone":"+1 858 566 8264",
    "sg:postcode":"92121",
    "sg:province":"CA",
    "sg:tags":[
        "hair"
    ],
    "wof:name":"Lee's Hair Cut",
    "wof:placetype":"venue"
},
  "geometry": {"coordinates":[-117.162278,32.879271],"type":"Point"}
}