{
  "type": "Feature",
  "properties": {
    "iso:country":"US",
    "sg:address":"601 University Ave",
    "sg:city":"Sacramento",
    "sg:classifiers":[
        {
            "category":"Professional",
            "subcategory":"Engineering",
            "type":"Services"
        }
    ],
    "sg:phone":"+1 916 929 3124",
    "sg:postcode":"95825",
    "sg:province":"CA",
    "sg:tags":[
        "engineer"
    ],
    "sg:website":"www.dmjmharris.com",
    "wof:name":"DMJM Harris",
    "wof:placetype":"venue"
},
  "geometry": {"coordinates":[-121.419436,38.565882],"type":"Point"}
}