{
  "type": "Feature",
  "properties": {
    "addr:full":"2 Municipal Wharf Santa Cruz CA 95060",
    "addr:housenumber":"2",
    "addr:postcode":"95060",
    "addr:street":"Municipal Wharf",
    "iso:country":"US",
    "sg:address":"2 Municipal Wharf",
    "sg:city":"Santa Cruz",
    "sg:classifiers":[
        {
            "category":"Recreation",
            "subcategory":"Boat Charter",
            "type":"Entertainment"
        }
    ],
    "sg:phone":"+1 831 425 8445",
    "sg:postcode":"95060",
    "sg:province":"CA",
    "sg:tags":[
        "rafting/kayaking"
    ],
    "sg:website":"www.kayaksantacruz.com",
    "wof:name":"Venture Quest Kayaking",
    "wof:placetype":"venue"
},
  "geometry": {"coordinates":[-122.023726,36.962919],"type":"Point"}
}