{
  "type": "Feature",
  "properties": {
    "iso:country":"US",
    "sg:address":"555 Portola Dr",
    "sg:city":"San Francisco",
    "sg:classifiers":[
        {
            "category":"Education",
            "subcategory":"School",
            "type":"Public Place"
        }
    ],
    "sg:phone":"+1 415 920 5185",
    "sg:postcode":"94131",
    "sg:province":"CA",
    "wof:name":"Athletics Office",
    "wof:placetype":"venue"
},
  "geometry": {"coordinates":[-122.451569,37.745454],"type":"Point"}
}