{
  "type": "Feature",
  "properties": {
    "addr:full":"1029 Flintridge Ave La Canada Fltrdg CA 91011",
    "addr:housenumber":"1029",
    "addr:postcode":"91011",
    "addr:street":"Flintridge Ave La",
    "iso:country":"US",
    "sg:address":"1029 Flintridge Ave",
    "sg:city":"La Canada Fltrdg",
    "sg:classifiers":[
        {
            "category":"Professional",
            "subcategory":"Management & Consulting",
            "type":"Services"
        }
    ],
    "sg:phone":"+1 818 790 9400",
    "sg:postcode":"91011",
    "sg:province":"CA",
    "sg:tags":[
        "marketing",
        "program"
    ],
    "wof:name":"Lugosi Enterprises",
    "wof:placetype":"venue"
},
  "geometry": {"coordinates":[-118.201297,34.191875],"type":"Point"}
}