{
  "type": "Feature",
  "properties": {
    "addr:full":"1910 N Broadway Walnut Creek CA 94596",
    "addr:housenumber":"1910",
    "addr:postcode":"94596",
    "addr:street":"N Broadway",
    "iso:country":"US",
    "sg:address":"1910 N Broadway",
    "sg:city":"Walnut Creek",
    "sg:classifiers":[
        {
            "category":"Government",
            "subcategory":"Office",
            "type":"Public Place"
        }
    ],
    "sg:phone":"+1 925 935 4464",
    "sg:postcode":"94596",
    "sg:province":"CA",
    "sg:tags":[
        "transportation"
    ],
    "wof:name":"Walnut Creek DMV Office",
    "wof:placetype":"venue"
},
  "geometry": {"coordinates":[-122.06138799999999,37.906604],"type":"Point"}
}