{
  "type": "Feature",
  "properties": {
    "iso:country":"US",
    "sg:address":"237 E Main St",
    "sg:city":"El Cajon",
    "sg:classifiers":[
        {
            "category":"Recreation",
            "subcategory":"Arcade",
            "type":"Entertainment"
        }
    ],
    "sg:phone":"+1 619 548 0071",
    "sg:postcode":"92019",
    "sg:province":"CA",
    "sg:website":"equinoxlasertag.com/home.html/",
    "wof:name":"Equinox Laser Tag",
    "wof:placetype":"venue"
},
  "geometry": {"coordinates":[-116.959693,32.794596],"type":"Point"}
}