{
  "type": "Feature",
  "properties": {
    "iso:country":"US",
    "sg:address":"30339 Old Hwy 58",
    "sg:city":"Barstow",
    "sg:classifiers":[
        {
            "category":"Retail",
            "subcategory":"Repair Shop",
            "type":"Services"
        }
    ],
    "sg:phone":"+1 760 256 9270",
    "sg:postcode":"92311",
    "sg:province":"CA",
    "sg:tags":[
        "upholsterer"
    ],
    "wof:name":"Hernandez Upholstering",
    "wof:placetype":"venue"
},
  "geometry": {"coordinates":[-117.000306,34.917473],"type":"Point"}
}