{
  "type": "Feature",
  "properties": {
    "addr:full":"7855 W Sunset Blvd Los Angeles CA 90046",
    "addr:housenumber":"7855",
    "addr:postcode":"90046",
    "addr:street":"W Sunset Blvd",
    "iso:country":"US",
    "sg:address":"7855 W Sunset Blvd",
    "sg:city":"Los Angeles",
    "sg:classifiers":[
        {
            "category":"Food & Beverages",
            "subcategory":"Liquor & Beverages",
            "type":"Retail Goods"
        }
    ],
    "sg:phone":"+1 323 874 0410",
    "sg:postcode":"90046",
    "sg:province":"CA",
    "sg:tags":[
        "beer",
        "spirit",
        "wine"
    ],
    "sg:website":"www.almorwines.com",
    "wof:name":"Almor Wine and Spirits",
    "wof:placetype":"venue"
},
  "geometry": {"coordinates":[-118.361,34.0979],"type":"Point"}
}