{
  "type": "Feature",
  "properties": {
    "addr:full":"314 E Santa Clara St San Jose CA 95113",
    "addr:housenumber":"314",
    "addr:postcode":"95113",
    "addr:street":"E Santa Clara St",
    "iso:country":"US",
    "sg:address":"314 E Santa Clara St",
    "sg:city":"San Jose",
    "sg:classifiers":[
        {
            "category":"Real Estate",
            "subcategory":"Real Estate Agent",
            "type":"Services"
        }
    ],
    "sg:phone":"+1 408 280 6979",
    "sg:postcode":"95113",
    "sg:province":"CA",
    "wof:name":"Sunset Enterprises",
    "wof:placetype":"venue"
},
  "geometry": {"coordinates":[-121.883392,37.339484],"type":"Point"}
}