{
  "type": "Feature",
  "properties": {
    "iso:country":"US",
    "sg:address":"314 Pomello Dr",
    "sg:city":"Claremont",
    "sg:classifiers":[
        {
            "category":"Professional",
            "subcategory":"Business Services",
            "type":"Services"
        }
    ],
    "sg:phone":"+1 909 621 3909",
    "sg:postcode":"91711",
    "sg:province":"CA",
    "sg:tags":[
        "holding"
    ],
    "wof:name":"Town & Country Industries, Inc.",
    "wof:placetype":"venue"
},
  "geometry": {"coordinates":[-117.712733,34.136056],"type":"Point"}
}