{
  "type": "Feature",
  "properties": {
    "iso:country":"US",
    "sg:address":"2424 Almaden Rd",
    "sg:city":"San Jose",
    "sg:classifiers":[
        {
            "category":"Restaurant",
            "type":"Food & Drink"
        }
    ],
    "sg:phone":"+1 408 269 3100",
    "sg:postcode":"95125",
    "sg:province":"CA",
    "sg:tags":[
        "mexican"
    ],
    "wof:name":"La Chosita Restaurant",
    "wof:placetype":"venue"
},
  "geometry": {"coordinates":[-121.881167,37.290105],"type":"Point"}
}