{
  "type": "Feature",
  "properties": {
    "iso:country":"US",
    "sg:address":"213 Pine Ave",
    "sg:city":"Long Beach",
    "sg:classifiers":[
        {
            "category":"Wholesale",
            "subcategory":"Machinery & Supplies",
            "type":"Manufacturing & Wholesale Goods"
        }
    ],
    "sg:phone":"+1 562 590 1414",
    "sg:postcode":"90802",
    "sg:province":"CA",
    "sg:tags":[
        "salon",
        "beauty"
    ],
    "wof:name":"Pine Avenue Health & Beauty",
    "wof:placetype":"venue"
},
  "geometry": {"coordinates":[-118.192458,33.769475],"type":"Point"}
}