{
  "type": "Feature",
  "properties": {
    "iso:country":"US",
    "sg:address":"30675 Vanderbilt St",
    "sg:city":"Hayward",
    "sg:classifiers":[
        {
            "category":"Home & Garden",
            "subcategory":"Household Appliances",
            "type":"Retail Goods"
        }
    ],
    "sg:phone":"+1 510 487 5425",
    "sg:postcode":"94544",
    "sg:province":"CA",
    "wof:name":"Gerolds Appliance Svc",
    "wof:placetype":"venue"
},
  "geometry": {"coordinates":[-122.039697,37.624307],"type":"Point"}
}