{
  "type": "Feature",
  "properties": {
    "iso:country":"US",
    "sg:address":"4305 Gesner St",
    "sg:city":"San Diego",
    "sg:classifiers":[
        {
            "category":"Professional",
            "type":"Services"
        }
    ],
    "sg:phone":"+1 858 342 8704",
    "sg:postcode":"92117",
    "sg:province":"CA",
    "sg:tags":[
        "establishment"
    ],
    "wof:name":"Jasmine's",
    "wof:placetype":"venue"
},
  "geometry": {"coordinates":[-117.202017,32.791409],"type":"Point"}
}