{
  "type": "Feature",
  "properties": {
    "iso:country":"US",
    "sg:address":"2657 S 2nd St",
    "sg:city":"Fresno",
    "sg:classifiers":[
        {
            "category":"Restaurant",
            "type":"Food & Drink"
        }
    ],
    "sg:phone":"+1 559 000 1111",
    "sg:postcode":"93706",
    "sg:province":"CA",
    "wof:name":"In-N-Out Burger",
    "wof:placetype":"venue"
},
  "geometry": {"coordinates":[-119.771424,36.706468],"type":"Point"}
}