{
  "type": "Feature",
  "properties": {
    "addr:full":"804 E California Ave Bakersfield CA 93307",
    "addr:housenumber":"804",
    "addr:postcode":"93307",
    "addr:street":"E California Ave",
    "iso:country":"US",
    "sg:address":"804 E California Ave",
    "sg:city":"Bakersfield",
    "sg:classifiers":[
        {
            "category":"Professional",
            "type":"Services"
        }
    ],
    "sg:phone":"+1 661 323 0870",
    "sg:postcode":"93307",
    "sg:province":"CA",
    "wof:name":"Max Autosound",
    "wof:placetype":"venue"
},
  "geometry": {"coordinates":[-118.994534,35.368527],"type":"Point"}
}