{
  "type": "Feature",
  "properties": {
    "iso:country":"US",
    "sg:address":"18630 State Rte 89 Scn",
    "sg:city":"Hat Creek",
    "sg:classifiers":[
        {
            "category":"Government",
            "subcategory":"Post Office",
            "type":"Public Place"
        }
    ],
    "sg:phone":"+1 530 335 4744",
    "sg:postcode":"96040",
    "sg:province":"CA",
    "wof:name":"US Post Office",
    "wof:placetype":"venue"
},
  "geometry": {"coordinates":[-121.516346,40.836436],"type":"Point"}
}