{
  "type": "Feature",
  "properties": {
    "iso:country":"US",
    "sg:address":"14626 Gundry Ave",
    "sg:city":"Paramount",
    "sg:classifiers":[
        {
            "category":"Education",
            "subcategory":"School",
            "type":"Public Place"
        }
    ],
    "sg:phone":"+1 562 602 6965",
    "sg:postcode":"90723",
    "sg:province":"CA",
    "sg:tags":[
        "elementary"
    ],
    "wof:name":"Los Cerritos Elementary School",
    "wof:placetype":"venue"
},
  "geometry": {"coordinates":[-118.17600299999999,33.900902],"type":"Point"}
}