{
  "type": "Feature",
  "properties": {
    "addr:full":"465 Bellevue Ave Apt 22 Oakland CA 94610",
    "addr:housenumber":"465;22",
    "addr:postcode":"94610",
    "addr:street":"Bellevue Ave Apt",
    "iso:country":"US",
    "sg:address":"465 Bellevue Ave Apt 22",
    "sg:city":"Oakland",
    "sg:classifiers":[
        {
            "category":"Wholesale",
            "subcategory":"Medical Equipment & Supplies",
            "type":"Manufacturing & Wholesale Goods"
        }
    ],
    "sg:phone":"+1 510 918 5752",
    "sg:postcode":"94610",
    "sg:province":"CA",
    "sg:tags":[
        "laboratory"
    ],
    "wof:name":"Spynsite",
    "wof:placetype":"venue"
},
  "geometry": {"coordinates":[-122.252927,37.807905],"type":"Point"}
}