{
  "type": "Feature",
  "properties": {
    "iso:country":"US",
    "sg:address":"572 W Foothill Blvd",
    "sg:city":"Rialto",
    "sg:classifiers":[
        {
            "category":"Professional",
            "subcategory":"Accounting & Tax Preparation",
            "type":"Services"
        }
    ],
    "sg:phone":"+1 909 875 6600",
    "sg:postcode":"92376",
    "sg:province":"CA",
    "sg:tags":[
        "return",
        "filing"
    ],
    "wof:name":"Liberty Tax Svc",
    "wof:placetype":"venue"
},
  "geometry": {"coordinates":[-117.38203799999999,34.106835],"type":"Point"}
}