{
  "type": "Feature",
  "properties": {
    "addr:full":"1 Hegenberger Rd Oakland CA 94621",
    "addr:housenumber":"1",
    "addr:postcode":"94621",
    "addr:street":"Hegenberger Rd",
    "iso:country":"US",
    "sg:address":"1 Hegenberger Rd",
    "sg:city":"Oakland",
    "sg:classifiers":[
        {
            "category":"Travel",
            "subcategory":"Hotels & Motels",
            "type":"Entertainment"
        },
        {
            "category":"Restaurant",
            "type":"Food & Drink"
        }
    ],
    "sg:phone":"+1 510 635 5000",
    "sg:postcode":"94621",
    "sg:province":"CA",
    "sg:website":"www1.hilton.com/en_US/hi/hotel/O...",
    "wof:name":"Hilton Oakland Airport",
    "wof:placetype":"venue"
},
  "geometry": {"coordinates":[-122.202003,37.7271],"type":"Point"}
}