{
  "type": "Feature",
  "properties": {
    "addr:full":"13064 Van Nuys Blvd Pacoima CA 91331",
    "addr:housenumber":"13064",
    "addr:postcode":"91331",
    "addr:street":"Van Nuys Blvd",
    "iso:country":"US",
    "sg:address":"13064 Van Nuys Blvd",
    "sg:city":"Pacoima",
    "sg:classifiers":[
        {
            "category":"Social Services",
            "type":"Services"
        }
    ],
    "sg:phone":"+1 818 899 7846",
    "sg:postcode":"91331",
    "sg:province":"CA",
    "wof:name":"After Thoughts Production",
    "wof:placetype":"venue"
},
  "geometry": {"coordinates":[-118.41825300000001,34.268895],"type":"Point"}
}