{
  "type": "Feature",
  "properties": {
    "addr:full":"313 Cumora Ln Ben Lomond CA 95005",
    "addr:housenumber":"313",
    "addr:postcode":"95005",
    "addr:street":"Cumora Ln",
    "iso:country":"US",
    "sg:address":"313 Cumora Ln",
    "sg:city":"Ben Lomond",
    "sg:classifiers":[
        {
            "category":"Recreation",
            "type":"Entertainment"
        }
    ],
    "sg:phone":"+1 831 336 5311",
    "sg:postcode":"95005",
    "sg:province":"CA",
    "sg:tags":[
        "club",
        "membership"
    ],
    "wof:name":"Phoenix Lk Golf CLB A Cal Lim",
    "wof:placetype":"venue"
},
  "geometry": {"coordinates":[-122.06962900000001,37.08171],"type":"Point"}
}