{
  "type": "Feature",
  "properties": {
    "iso:country":"US",
    "sg:address":"9647 Folsom Blvd",
    "sg:city":"Sacramento",
    "sg:classifiers":[
        {
            "category":"Shopping",
            "subcategory":"Computers & Home Electronics",
            "type":"Retail Goods"
        }
    ],
    "sg:phone":"+1 916 364 8087",
    "sg:postcode":"95827",
    "sg:province":"CA",
    "sg:tags":[
        "software"
    ],
    "wof:name":"R K Solutions",
    "wof:placetype":"venue"
},
  "geometry": {"coordinates":[-121.341154,38.569547],"type":"Point"}
}