{
  "type": "Feature",
  "properties": {
    "iso:country":"US",
    "sg:address":"2121 E Pacific Coast Hwy",
    "sg:city":"Long Beach",
    "sg:classifiers":[
        {
            "category":"Insurance",
            "subcategory":"Insurance Agent",
            "type":"Services"
        }
    ],
    "sg:phone":"+1 949 456 9509",
    "sg:postcode":"90804",
    "sg:province":"CA",
    "wof:name":"MBP Insurance Inc",
    "wof:placetype":"venue"
},
  "geometry": {"coordinates":[-118.165526,33.789929],"type":"Point"}
}