{
  "type": "Feature",
  "properties": {
    "iso:country":"US",
    "sg:address":"219 N Harbor Blvd",
    "sg:city":"Fullerton",
    "sg:classifiers":[
        {
            "category":"Wholesale",
            "subcategory":"Electrical",
            "type":"Manufacturing & Wholesale Goods"
        }
    ],
    "sg:phone":"+1 714 870 9117",
    "sg:postcode":"92832",
    "sg:province":"CA",
    "sg:tags":[
        "electronic"
    ],
    "wof:name":"Studio 40",
    "wof:placetype":"venue"
},
  "geometry": {"coordinates":[-117.924323,33.872203],"type":"Point"}
}