{
  "type": "Feature",
  "properties": {
    "addr:full":"343 N Oak St Inglewood CA 90302",
    "addr:housenumber":"343",
    "addr:postcode":"90302",
    "addr:street":"N Oak St",
    "iso:country":"US",
    "sg:address":"343 N Oak St",
    "sg:city":"Inglewood",
    "sg:classifiers":[
        {
            "category":"Freight",
            "type":"Transportation"
        }
    ],
    "sg:phone":"+1 310 671 8300",
    "sg:postcode":"90302",
    "sg:province":"CA",
    "sg:tags":[
        "broker",
        "customs"
    ],
    "wof:name":"INTERNATIONAL Logistics Svc",
    "wof:placetype":"venue"
},
  "geometry": {"coordinates":[-118.366724,33.966439],"type":"Point"}
}