{
  "type": "Feature",
  "properties": {
    "iso:country":"US",
    "sg:address":"14028 Lambert Rd",
    "sg:city":"Whittier",
    "sg:classifiers":[
        {
            "category":"Home & Garden",
            "subcategory":"Home Furnishings",
            "type":"Retail Goods"
        }
    ],
    "sg:phone":"+1 562 696 2148",
    "sg:postcode":"90605",
    "sg:province":"CA",
    "sg:tags":[
        "equipment",
        "electrical"
    ],
    "wof:name":"Discount Lighting",
    "wof:placetype":"venue"
},
  "geometry": {"coordinates":[-118.028449,33.951655],"type":"Point"}
}