{
  "type": "Feature",
  "properties": {
    "addr:full":"46921 Warm Springs Blvd Ste 101 Fremont CA 94539",
    "addr:housenumber":"46921",
    "addr:postcode":"94539",
    "addr:street":"Warm Springs Blvd Ste 101",
    "iso:country":"US",
    "sg:address":"46921 Warm Springs Blvd Ste 101",
    "sg:city":"Fremont",
    "sg:classifiers":[
        {
            "category":"Professional",
            "type":"Services"
        },
        {
            "category":"Personal",
            "type":"Services"
        }
    ],
    "sg:phone":"+1 510 673 8912",
    "sg:postcode":"94539",
    "sg:province":"CA",
    "sg:tags":[
        "local"
    ],
    "sg:website":"www.docstranslate.com",
    "wof:name":"Bay Area International Translation Services",
    "wof:placetype":"venue"
},
  "geometry": {"coordinates":[-121.929103,37.488238],"type":"Point"}
}