{
  "type": "Feature",
  "properties": {
    "addr:full":"1335 S Azusa Ave West Covina CA 91791",
    "addr:housenumber":"1335",
    "addr:postcode":"91791",
    "addr:street":"S Azusa Ave",
    "iso:country":"US",
    "sg:address":"1335 S Azusa Ave",
    "sg:city":"West Covina",
    "sg:classifiers":[
        {
            "category":"Professional",
            "subcategory":"Accounting & Tax Preparation",
            "type":"Services"
        }
    ],
    "sg:phone":"+1 626 918 2920",
    "sg:postcode":"91791",
    "sg:province":"CA",
    "sg:tags":[
        "return",
        "filing"
    ],
    "wof:name":"Advance Bookkeeping & Tax Svc",
    "wof:placetype":"venue"
},
  "geometry": {"coordinates":[-117.907979,34.052089],"type":"Point"}
}