{
  "type": "Feature",
  "properties": {
    "addr:full":"23101 Lake Center Dr Ste 200 Lake Forest CA 92630",
    "addr:housenumber":"23101",
    "addr:postcode":"92630",
    "addr:street":"Lake Center Dr Ste 200",
    "iso:country":"US",
    "sg:address":"23101 Lake Center Dr Ste 200",
    "sg:city":"Lake Forest",
    "sg:classifiers":[
        {
            "category":"Professional",
            "subcategory":"Lawyer & Legal Services",
            "type":"Services"
        }
    ],
    "sg:phone":"+1 949 452 0500",
    "sg:postcode":"92630",
    "sg:province":"CA",
    "wof:name":"McFarlin & Anderson",
    "wof:placetype":"venue"
},
  "geometry": {"coordinates":[-117.717437,33.627185],"type":"Point"}
}