{
  "type": "Feature",
  "properties": {
    "iso:country":"US",
    "sg:address":"5031 York Blvd",
    "sg:city":"Los Angeles",
    "sg:classifiers":[
        {
            "category":"Home & Garden",
            "subcategory":"Hardware",
            "type":"Retail Goods"
        }
    ],
    "sg:phone":"+1 323 256 1001",
    "sg:postcode":"90042",
    "sg:province":"CA",
    "wof:name":"99 Cents Solo Store Inc",
    "wof:placetype":"venue"
},
  "geometry": {"coordinates":[-118.20528,34.121267],"type":"Point"}
}