{
  "type": "Feature",
  "properties": {
    "iso:country":"US",
    "sg:address":"570 Monterey Blvd",
    "sg:city":"San Francisco",
    "sg:classifiers":[
        {
            "category":"Professional",
            "subcategory":"Employment Agencies",
            "type":"Services"
        }
    ],
    "sg:phone":"+1 415 405 0051",
    "sg:postcode":"94127",
    "sg:province":"CA",
    "sg:tags":[
        "consultant",
        "search",
        "executive"
    ],
    "sg:website":"www.grantprosearch.com",
    "wof:name":"Grant Pro Search",
    "wof:placetype":"venue"
},
  "geometry": {"coordinates":[-122.44811,37.731664],"type":"Point"}
}