{
  "type": "Feature",
  "properties": {
    "addr:full":"2940 Fernside Blvd Alameda CA 94501",
    "addr:housenumber":"2940",
    "addr:postcode":"94501",
    "addr:street":"Fernside Blvd",
    "iso:country":"US",
    "sg:address":"2940 Fernside Blvd",
    "sg:city":"Alameda",
    "sg:classifiers":[
        {
            "category":"Shopping",
            "subcategory":"Gifts & Souvenirs",
            "type":"Retail Goods"
        }
    ],
    "sg:phone":"+1 510 864 8150",
    "sg:postcode":"94501",
    "sg:province":"CA",
    "sg:tags":[
        "shop"
    ],
    "wof:name":"Back To The 40's",
    "wof:placetype":"venue"
},
  "geometry": {"coordinates":[-122.22944099999999,37.765558],"type":"Point"}
}