{
  "type": "Feature",
  "properties": {
    "iso:country":"US",
    "sg:address":"5751 Palmer Way Lbby",
    "sg:city":"Carlsbad",
    "sg:classifiers":[
        {
            "category":"Real Estate",
            "subcategory":"Architect",
            "type":"Services"
        }
    ],
    "sg:phone":"+1 760 438 2963",
    "sg:postcode":"92008",
    "sg:province":"CA",
    "wof:name":"Beery John S Architect Aia",
    "wof:placetype":"venue"
},
  "geometry": {"coordinates":[-117.272003,33.137901],"type":"Point"}
}