{
  "type": "Feature",
  "properties": {
    "iso:country":"US",
    "sg:address":"2869 Octavia St",
    "sg:city":"San Francisco",
    "sg:classifiers":[
        {
            "category":"Professional",
            "subcategory":"Lawyer & Legal Services",
            "type":"Services"
        }
    ],
    "sg:phone":"+1 415 956 3020",
    "sg:postcode":"94123",
    "sg:province":"CA",
    "wof:name":"Ottonello Edward Atty",
    "wof:placetype":"venue"
},
  "geometry": {"coordinates":[-122.42908799999999,37.798683],"type":"Point"}
}