{
  "type": "Feature",
  "properties": {
    "addr:full":"653 S Clarence Street Los Angeles CA 90023",
    "addr:housenumber":"653",
    "addr:postcode":"90023",
    "addr:street":"S Clarence Street",
    "iso:country":"US",
    "sg:address":"653 S Clarence Street",
    "sg:city":"Los Angeles",
    "sg:classifiers":[
        {
            "category":"Retail",
            "subcategory":"Repair Shop",
            "type":"Services"
        }
    ],
    "sg:phone":"+1 323 264 4533",
    "sg:postcode":"90023",
    "sg:province":"CA",
    "sg:tags":[
        "reupholstery",
        "furniture"
    ],
    "wof:name":"Bellcraft Office Furniture",
    "wof:placetype":"venue"
},
  "geometry": {"coordinates":[-118.222048,34.036621],"type":"Point"}
}