{
  "type": "Feature",
  "properties": {
    "addr:full":"390 Grand Avenue #5 Oakland CA 94610",
    "addr:housenumber":"390",
    "addr:postcode":"94610",
    "addr:street":"Grand Avenue # 5",
    "iso:country":"US",
    "sg:address":"390 Grand Avenue #5",
    "sg:city":"Oakland",
    "sg:classifiers":[
        {
            "category":"Professional",
            "type":"Services"
        }
    ],
    "sg:phone":"+1 510 835 4092",
    "sg:postcode":"94610",
    "sg:province":"CA",
    "sg:website":"www.bubblefant.com",
    "wof:name":"David Goldstone Illustrator",
    "wof:placetype":"venue"
},
  "geometry": {"coordinates":[-122.254312,37.809106],"type":"Point"}
}