{
  "type": "Feature",
  "properties": {
    "addr:full":"1006 N Idaho St San Mateo CA 94401",
    "addr:housenumber":"1006",
    "addr:postcode":"94401",
    "addr:street":"N Idaho St",
    "iso:country":"US",
    "sg:address":"1006 N Idaho St",
    "sg:city":"San Mateo",
    "sg:classifiers":[
        {
            "category":"Manufacturing",
            "subcategory":"Signs",
            "type":"Manufacturing & Wholesale Goods"
        }
    ],
    "sg:phone":"+1 650 342 1540",
    "sg:postcode":"94401",
    "sg:province":"CA",
    "wof:name":"KANE Wood Signs LTD",
    "wof:placetype":"venue"
},
  "geometry": {"coordinates":[-122.33259700000001,37.58623],"type":"Point"}
}