{
  "type": "Feature",
  "properties": {
    "iso:country":"US",
    "sg:address":"4955 Van Nuys Blvd Frnt",
    "sg:city":"Sherman Oaks",
    "sg:classifiers":[
        {
            "category":"Shopping",
            "subcategory":"Pharmacy",
            "type":"Retail Goods"
        }
    ],
    "sg:phone":"+1 818 905 0669",
    "sg:postcode":"91403",
    "sg:province":"CA",
    "sg:tags":[
        "drugstore"
    ],
    "sg:website":"www.michaelspharmacy.com",
    "wof:name":"Michael's Pharmacy",
    "wof:placetype":"venue"
},
  "geometry": {"coordinates":[-118.44899700000001,34.160301],"type":"Point"}
}