{
  "type": "Feature",
  "properties": {
    "addr:full":"38035 53rd St E Palmdale CA 93552",
    "addr:housenumber":"38035",
    "addr:postcode":"ca 93552",
    "addr:street":"53Rd St E",
    "iso:country":"US",
    "sg:address":"38035 53rd St E",
    "sg:city":"Palmdale",
    "sg:classifiers":[
        {
            "category":"Retail",
            "subcategory":"Laundry & Dry Cleaning",
            "type":"Services"
        }
    ],
    "sg:phone":"+1 661 433 9848",
    "sg:postcode":"93552",
    "sg:province":"CA",
    "sg:tags":[
        "cleaner",
        "rug",
        "carpet"
    ],
    "wof:name":"Carpet Cleaners Specialist",
    "wof:placetype":"venue"
},
  "geometry": {"coordinates":[-118.035151,34.573559],"type":"Point"}
}