{
  "type": "Feature",
  "properties": {
    "addr:full":"3904 Adeline St Emeryville CA 94608",
    "addr:housenumber":"3904",
    "addr:postcode":"94608",
    "addr:street":"Adeline St",
    "iso:country":"US",
    "sg:address":"3904 Adeline St",
    "sg:city":"Emeryville",
    "sg:classifiers":[
        {
            "category":"Personal",
            "subcategory":"Beauty Salon",
            "type":"Services"
        }
    ],
    "sg:phone":"+1 510 655 7755",
    "sg:postcode":"94608",
    "sg:province":"CA",
    "wof:name":"In The Cut Hair Studio",
    "wof:placetype":"venue"
},
  "geometry": {"coordinates":[-122.278824,37.829674],"type":"Point"}
}