{
  "type": "Feature",
  "properties": {
    "iso:country":"US",
    "sg:address":"10 Commercial Blvd.",
    "sg:city":"Novato",
    "sg:classifiers":[
        {
            "category":"Professional",
            "subcategory":"Computer Services",
            "type":"Services"
        }
    ],
    "sg:phone":"+1 415 302 1800",
    "sg:postcode":"94949",
    "sg:province":"CA",
    "sg:tags":[
        "mobile--games",
        "games",
        "interconnected",
        "multiplayer"
    ],
    "sg:website":"http://www.timelapsemobile.com",
    "wof:name":"TimeLapse mobile",
    "wof:placetype":"venue"
},
  "geometry": {"coordinates":[-122.532764,38.068491],"type":"Point"}
}