{
  "type": "Feature",
  "properties": {
    "addr:full":"27480 Ynez Rd Ste 2 Temecula CA 92591",
    "addr:housenumber":"27480",
    "addr:postcode":"92591",
    "addr:street":"Ynez Rd Ste 2",
    "iso:country":"US",
    "sg:address":"27480 Ynez Rd Ste 2",
    "sg:city":"Temecula",
    "sg:phone":"+1 951 694 9948",
    "sg:postcode":"92591",
    "sg:province":"CA",
    "sg:website":"http://www.rubios.com",
    "wof:name":"Rubio's",
    "wof:placetype":"venue"
},
  "geometry": {"coordinates":[-117.149745,33.504929],"type":"Point"}
}