{
  "type": "Feature",
  "properties": {
    "addr:full":"20440 Redwood Rd Castro Valley CA 94546",
    "addr:housenumber":"20440",
    "addr:postcode":"94546",
    "addr:street":"Redwood Rd",
    "iso:country":"US",
    "sg:address":"20440 Redwood Rd",
    "sg:city":"Castro Valley",
    "sg:classifiers":[
        {
            "category":"Arena",
            "subcategory":"Sports Club",
            "type":"Entertainment"
        }
    ],
    "sg:phone":"+1 510 733 6500",
    "sg:postcode":"94546",
    "sg:province":"CA",
    "sg:tags":[
        "martial art"
    ],
    "wof:name":"Karate For Kids",
    "wof:placetype":"venue"
},
  "geometry": {"coordinates":[-122.07399700000001,37.6973],"type":"Point"}
}