{
  "type": "Feature",
  "properties": {
    "addr:full":"24201 Valencia Blvd Ste 2025 Santa Clarita CA 91355",
    "addr:housenumber":"24201",
    "addr:postcode":"91355",
    "addr:street":"Valencia Blvd Ste 2025",
    "iso:country":"US",
    "sg:address":"24201 Valencia Blvd Ste 2025",
    "sg:city":"Santa Clarita",
    "sg:classifiers":[
        {
            "category":"Shopping",
            "subcategory":"Jewelry",
            "type":"Retail Goods"
        }
    ],
    "sg:phone":"+1 661 799 9290",
    "sg:postcode":"91355",
    "sg:province":"CA",
    "wof:name":"Andrews Fine Jewelers",
    "wof:placetype":"venue"
},
  "geometry": {"coordinates":[-118.557683,34.413351],"type":"Point"}
}