{
  "type": "Feature",
  "properties": {
    "addr:full":"1493 N Montebello Blvd Montebello CA 90640",
    "addr:housenumber":"1493",
    "addr:postcode":"90640",
    "addr:street":"N Montebello Blvd",
    "iso:country":"US",
    "sg:address":"1493 N Montebello Blvd",
    "sg:city":"Montebello",
    "sg:classifiers":[
        {
            "category":"Banks & Credit Unions",
            "subcategory":"Bank",
            "type":"Services"
        }
    ],
    "sg:phone":"+1 888 338 8880",
    "sg:postcode":"90640",
    "sg:province":"CA",
    "sg:tags":[
        "saving",
        "commercial"
    ],
    "wof:name":"United Commercial Bank",
    "wof:placetype":"venue"
},
  "geometry": {"coordinates":[-118.09073600000001,34.034031],"type":"Point"}
}