{
  "type": "Feature",
  "properties": {
    "addr:full":"399 Encinal St Santa Cruz CA 95060",
    "addr:housenumber":"399",
    "addr:postcode":"95060",
    "addr:street":"Encinal St",
    "iso:country":"US",
    "sg:address":"399 Encinal St",
    "sg:city":"Santa Cruz",
    "sg:classifiers":[
        {
            "category":"Arena",
            "subcategory":"Sports Club",
            "type":"Entertainment"
        }
    ],
    "sg:phone":"+1 831 459 8901",
    "sg:postcode":"95060",
    "sg:province":"CA",
    "sg:tags":[
        "martial art"
    ],
    "sg:website":"www.lairdsacademy.com",
    "wof:name":"Laird's Academy of Martial Arts",
    "wof:placetype":"venue"
},
  "geometry": {"coordinates":[-122.039001,36.987499],"type":"Point"}
}