{
  "type": "Feature",
  "properties": {
    "iso:country":"US",
    "sg:address":"730 W Broadway",
    "sg:city":"Glendale",
    "sg:classifiers":[
        {
            "category":"Autos & Motor Vehicles",
            "subcategory":"Auto Supplies",
            "type":"Retail Goods"
        }
    ],
    "sg:phone":"+1 818 957 0406",
    "sg:postcode":"91204",
    "sg:province":"CA",
    "sg:tags":[
        "wheel",
        "cover"
    ],
    "wof:name":"ABC Wheel & Tire Inc",
    "wof:placetype":"venue"
},
  "geometry": {"coordinates":[-118.27123400000001,34.14669],"type":"Point"}
}