{
  "type": "Feature",
  "properties": {
    "addr:full":"1940 Ralston Ave Belmont CA 94002",
    "addr:housenumber":"1940",
    "addr:postcode":"94002",
    "addr:street":"Ralston Ave",
    "iso:country":"US",
    "sg:address":"1940 Ralston Ave",
    "sg:city":"Belmont",
    "sg:classifiers":[
        {
            "category":"Real Estate",
            "subcategory":"Real Estate Agent",
            "type":"Services"
        }
    ],
    "sg:phone":"+1 650 508 1441",
    "sg:postcode":"94002",
    "sg:province":"CA",
    "sg:website":"www.morganhomes.com",
    "wof:name":"MorganHomes.com",
    "wof:placetype":"venue"
},
  "geometry": {"coordinates":[-122.293254,37.512541],"type":"Point"}
}