{
  "type": "Feature",
  "properties": {
    "iso:country":"US",
    "sg:address":"914 W Spruce St",
    "sg:city":"San Bernardino",
    "sg:classifiers":[
        {
            "category":"Food & Beverages",
            "subcategory":"Groceries & Convenience Stores",
            "type":"Retail Goods"
        }
    ],
    "sg:phone":"+1 909 889 5605",
    "sg:postcode":"92411",
    "sg:province":"CA",
    "sg:tags":[
        "grocer"
    ],
    "wof:name":"Ybarra's Grocery",
    "wof:placetype":"venue"
},
  "geometry": {"coordinates":[-117.305369,34.109355],"type":"Point"}
}