{
  "type": "Feature",
  "properties": {
    "iso:country":"US",
    "sg:address":"22142 Itasca St",
    "sg:city":"Chatsworth",
    "sg:classifiers":[
        {
            "category":"Retail",
            "subcategory":"Repair Shop",
            "type":"Services"
        }
    ],
    "sg:phone":"+1 818 752 0029",
    "sg:postcode":"91311",
    "sg:province":"CA",
    "sg:tags":[
        "lock",
        "locksmith"
    ],
    "wof:name":"Pat's Mobile Lock & Key",
    "wof:placetype":"venue"
},
  "geometry": {"coordinates":[-118.609874,34.244848],"type":"Point"}
}