{
  "type": "Feature",
  "properties": {
    "addr:full":"620 S Main St Milpitas CA 95035",
    "addr:housenumber":"620",
    "addr:postcode":"95035",
    "addr:street":"S Main St",
    "iso:country":"US",
    "sg:address":"620 S Main St",
    "sg:city":"Milpitas",
    "sg:classifiers":[
        {
            "category":"Communications",
            "type":"Services"
        }
    ],
    "sg:phone":"+1 408 263 6275",
    "sg:postcode":"95035",
    "sg:province":"CA",
    "wof:name":"Mark Tiernan Communications",
    "wof:placetype":"venue"
},
  "geometry": {"coordinates":[-121.904112,37.420097],"type":"Point"}
}