{
  "type": "Feature",
  "properties": {
    "iso:country":"US",
    "sg:address":"591 Cam de la Reina",
    "sg:city":"San Diego",
    "sg:classifiers":[
        {
            "category":"Personal",
            "type":"Services"
        }
    ],
    "sg:phone":"+1 619 297 8640",
    "sg:postcode":"92108",
    "sg:province":"CA",
    "sg:tags":[
        "control",
        "weight"
    ],
    "sg:website":"www.ihmonline.com",
    "wof:name":"Institute For Health Mntnc",
    "wof:placetype":"venue"
},
  "geometry": {"coordinates":[-117.161958,32.766304],"type":"Point"}
}