{
  "type": "Feature",
  "properties": {
    "addr:full":"5200 S Alameda St Los Angeles CA 90058",
    "addr:housenumber":"5200",
    "addr:postcode":"90058",
    "addr:street":"S Alameda St",
    "iso:country":"US",
    "sg:address":"5200 S Alameda St",
    "sg:city":"Los Angeles",
    "sg:classifiers":[
        {
            "category":"Manufacturing",
            "subcategory":"Food",
            "type":"Manufacturing & Wholesale Goods"
        }
    ],
    "sg:phone":"+1 323 586 0820",
    "sg:postcode":"90058",
    "sg:province":"CA",
    "sg:tags":[
        "product",
        "mfg"
    ],
    "wof:name":"Lee Shara Fresh",
    "wof:placetype":"venue"
},
  "geometry": {"coordinates":[-118.23797399999999,33.992991],"type":"Point"}
}