{
  "type": "Feature",
  "properties": {
    "iso:country":"US",
    "sg:address":"1534 Fremont Blvd",
    "sg:city":"Seaside",
    "sg:classifiers":[
        {
            "category":"Restaurant",
            "type":"Food & Drink"
        }
    ],
    "sg:menulink":"http://www.allmenus.com/ca/seaside-monterey/150349-subway/menu/",
    "sg:phone":"+1 831 899 0103",
    "sg:postcode":"93955",
    "sg:province":"CA",
    "sg:tags":[
        "american",
        "sandwich"
    ],
    "wof:name":"Subway",
    "wof:placetype":"venue"
},
  "geometry": {"coordinates":[-121.845778,36.608222],"type":"Point"}
}