{
  "type": "Feature",
  "properties": {
    "addr:full":"26980 Prairie Dog Ln Moreno Valley CA 92555",
    "addr:housenumber":"26980",
    "addr:postcode":"92555",
    "addr:street":"Prairie Dog Ln",
    "iso:country":"US",
    "sg:address":"26980 Prairie Dog Ln",
    "sg:city":"Moreno Valley",
    "sg:classifiers":[
        {
            "category":"Farming",
            "subcategory":"Farm & Veterinary Services",
            "type":"Manufacturing & Wholesale Goods"
        }
    ],
    "sg:phone":"+1 951 243 3280",
    "sg:postcode":"92555",
    "sg:province":"CA",
    "sg:tags":[
        "crop",
        "harvesting"
    ],
    "wof:name":"Pacheco Farm Services",
    "wof:placetype":"venue"
},
  "geometry": {"coordinates":[-117.193023,33.941932],"type":"Point"}
}