{
  "type": "Feature",
  "properties": {
    "iso:country":"US",
    "sg:address":"7324 Folsom Blvd Ste D",
    "sg:city":"Sacramento",
    "sg:classifiers":[
        {
            "category":"Food & Beverages",
            "subcategory":"Meat & Fish",
            "type":"Retail Goods"
        }
    ],
    "sg:phone":"+1 916 379 0701",
    "sg:postcode":"95826",
    "sg:province":"CA",
    "sg:tags":[
        "seafood",
        "market"
    ],
    "wof:name":"R & J Seafood Company",
    "wof:placetype":"venue"
},
  "geometry": {"coordinates":[-121.417995,38.550631],"type":"Point"}
}