{
  "type": "Feature",
  "properties": {
    "iso:country":"US",
    "sg:address":"12100 Wilshire Blvd",
    "sg:city":"Los Angeles",
    "sg:classifiers":[
        {
            "category":"Real Estate",
            "subcategory":"Real Estate Agent",
            "type":"Services"
        }
    ],
    "sg:phone":"+1 310 820 9730",
    "sg:postcode":"90025",
    "sg:province":"CA",
    "sg:tags":[
        "management"
    ],
    "wof:name":"Fairmont Management",
    "wof:placetype":"venue"
},
  "geometry": {"coordinates":[-118.46831,34.043422],"type":"Point"}
}