{
  "type": "Feature",
  "properties": {
    "addr:full":"2061 N Maryland Ave Colton CA 92324",
    "addr:housenumber":"2061",
    "addr:postcode":"92324",
    "addr:street":"N Maryland Ave",
    "iso:country":"US",
    "sg:address":"2061 N Maryland Ave",
    "sg:city":"Colton",
    "sg:classifiers":[
        {
            "category":"Building & Trades",
            "subcategory":"Construction",
            "type":"Services"
        }
    ],
    "sg:phone":"+1 909 423 0931",
    "sg:postcode":"92324",
    "sg:province":"CA",
    "sg:tags":[
        "tile",
        "dealer"
    ],
    "wof:name":"Mosaic Legs",
    "wof:placetype":"venue"
},
  "geometry": {"coordinates":[-117.32612899999999,34.09104],"type":"Point"}
}