{
  "type": "Feature",
  "properties": {
    "iso:country":"US",
    "sg:address":"1130 W Hobsonway",
    "sg:city":"Blythe",
    "sg:classifiers":[
        {
            "category":"Professional",
            "subcategory":"Lawyer & Legal Services",
            "type":"Services"
        }
    ],
    "sg:phone":"+1 760 922 5051",
    "sg:postcode":"92225",
    "sg:province":"CA",
    "sg:tags":[
        "attorney"
    ],
    "wof:name":"Shaffer Cormell Law Offices",
    "wof:placetype":"venue"
},
  "geometry": {"coordinates":[-114.609193,33.610072],"type":"Point"}
}