{
  "type": "Feature",
  "properties": {
    "iso:country":"US",
    "sg:address":"1916 Lincoln St",
    "sg:city":"Oceanside",
    "sg:classifiers":[
        {
            "category":"Wholesale",
            "subcategory":"Sporting Goods",
            "type":"Manufacturing & Wholesale Goods"
        }
    ],
    "sg:phone":"+1 760 433 6943",
    "sg:postcode":"92054",
    "sg:province":"CA",
    "wof:name":"Mattison Distribution",
    "wof:placetype":"venue"
},
  "geometry": {"coordinates":[-117.354738,33.175338],"type":"Point"}
}