{
  "type": "Feature",
  "properties": {
    "addr:full":"315 S Camden Dr Beverly Hills CA 90212",
    "addr:housenumber":"315",
    "addr:postcode":"90212",
    "addr:street":"S Camden Dr",
    "iso:country":"US",
    "sg:address":"315 S Camden Dr",
    "sg:city":"Beverly Hills",
    "sg:classifiers":[
        {
            "category":"Real Estate",
            "subcategory":"Architect",
            "type":"Services"
        }
    ],
    "sg:phone":"+1 310 860 8984",
    "sg:postcode":"90212",
    "sg:province":"CA",
    "wof:name":"Builders Team",
    "wof:placetype":"venue"
},
  "geometry": {"coordinates":[-118.402525,34.159913],"type":"Point"}
}