{
  "type": "Feature",
  "properties": {
    "iso:country":"US",
    "sg:address":"616 Howard Ave",
    "sg:city":"Montebello",
    "sg:classifiers":[
        {
            "category":"Manufacturing",
            "subcategory":"Printing",
            "type":"Manufacturing & Wholesale Goods"
        }
    ],
    "sg:phone":"+1 323 721 2774",
    "sg:postcode":"90640",
    "sg:province":"CA",
    "sg:tags":[
        "lithographic",
        "commercial"
    ],
    "wof:name":"I Print For You",
    "wof:placetype":"venue"
},
  "geometry": {"coordinates":[-118.10910699999999,34.021308],"type":"Point"}
}