{
  "type": "Feature",
  "properties": {
    "addr:full":"21115 Sherman Way Canoga Park CA 91303",
    "addr:housenumber":"21115",
    "addr:postcode":"91303",
    "addr:street":"Sherman Way",
    "iso:country":"US",
    "sg:address":"21115 Sherman Way",
    "sg:city":"Canoga Park",
    "sg:classifiers":[
        {
            "category":"Shopping",
            "subcategory":"Pharmacy",
            "type":"Retail Goods"
        }
    ],
    "sg:phone":"+1 818 936 4025",
    "sg:postcode":"91303",
    "sg:province":"CA",
    "sg:tags":[
        "drugstore"
    ],
    "wof:name":"VICTORY HOMECARE PHARMACY",
    "wof:placetype":"venue"
},
  "geometry": {"coordinates":[-118.59360100000001,34.201177],"type":"Point"}
}