{
  "type": "Feature",
  "properties": {
    "addr:full":"3195 Glendale Blvd Los Angeles CA 90039",
    "addr:housenumber":"3195",
    "addr:postcode":"90039",
    "addr:street":"Glendale Blvd",
    "iso:country":"US",
    "sg:address":"3195 Glendale Blvd",
    "sg:city":"Los Angeles",
    "sg:classifiers":[
        {
            "category":"Shopping",
            "subcategory":"Crafts & Fabrics",
            "type":"Retail Goods"
        }
    ],
    "sg:phone":"+1 323 663 3838",
    "sg:postcode":"90039",
    "sg:province":"CA",
    "sg:tags":[
        "art"
    ],
    "sg:website":"www.thelittleknittery.com/",
    "wof:name":"The Little Knittery",
    "wof:placetype":"venue"
},
  "geometry": {"coordinates":[-118.261126,34.117844],"type":"Point"}
}