{
  "type": "Feature",
  "properties": {
    "iso:country":"US",
    "sg:address":"7 Upper Newport Plaza Dr",
    "sg:city":"Newport Beach",
    "sg:classifiers":[
        {
            "category":"Building & Trades",
            "subcategory":"Landscaping Services",
            "type":"Services"
        }
    ],
    "sg:phone":"+1 949 261 8820",
    "sg:postcode":"92660",
    "sg:province":"CA",
    "sg:tags":[
        "planning",
        "landscape"
    ],
    "wof:name":"PBR",
    "wof:placetype":"venue"
},
  "geometry": {"coordinates":[-117.871676,33.661007],"type":"Point"}
}