{
  "type": "Feature",
  "properties": {
    "iso:country":"US",
    "sg:address":"3910 Prospect Ave",
    "sg:city":"Yorba Linda",
    "sg:classifiers":[
        {
            "category":"Manufacturing",
            "subcategory":"Tools & Machinery",
            "type":"Manufacturing & Wholesale Goods"
        }
    ],
    "sg:phone":"+1 714 961 1922",
    "sg:postcode":"92886",
    "sg:province":"CA",
    "sg:tags":[
        "mfg"
    ],
    "wof:name":"Digitool",
    "wof:placetype":"venue"
},
  "geometry": {"coordinates":[-117.837502,33.902344],"type":"Point"}
}