{
  "type": "Feature",
  "properties": {
    "iso:country":"US",
    "sg:address":"3038 Shelby Dr",
    "sg:city":"National City",
    "sg:classifiers":[
        {
            "category":"Social Services",
            "subcategory":"Child Care",
            "type":"Services"
        }
    ],
    "sg:phone":"+1 619 267 5264",
    "sg:postcode":"91950",
    "sg:province":"CA",
    "wof:name":"Little Seeds Family Childcare",
    "wof:placetype":"venue"
},
  "geometry": {"coordinates":[-117.075934,32.661551],"type":"Point"}
}