{
  "type": "Feature",
  "properties": {
    "addr:full":"2522 South Bascom Avenue Campbell CA 95008",
    "addr:housenumber":"2522",
    "addr:postcode":"95008",
    "addr:street":"South Bascom Avenue",
    "iso:country":"US",
    "sg:address":"2522 South Bascom Avenue",
    "sg:city":"Campbell",
    "sg:classifiers":[
        {
            "category":"Building & Trades",
            "subcategory":"Construction",
            "type":"Services"
        }
    ],
    "sg:phone":"+1 408 693 5292",
    "sg:postcode":"95008",
    "sg:province":"CA",
    "sg:tags":[
        "contractor"
    ],
    "wof:name":"Hunsaker Construction",
    "wof:placetype":"venue"
},
  "geometry": {"coordinates":[-121.93215600000001,37.27736],"type":"Point"}
}