{
  "type": "Feature",
  "properties": {
    "iso:country":"US",
    "sg:address":"511 L St",
    "sg:city":"Davis",
    "sg:classifiers":[
        {
            "category":"Wholesale",
            "subcategory":"Electrical",
            "type":"Manufacturing & Wholesale Goods"
        }
    ],
    "sg:phone":"+1 530 297 7254",
    "sg:postcode":"95616",
    "sg:province":"CA",
    "sg:tags":[
        "testing",
        "apparatus"
    ],
    "wof:name":"A T M's Of California",
    "wof:placetype":"venue"
},
  "geometry": {"coordinates":[-121.734775,38.550081],"type":"Point"}
}