{
  "type": "Feature",
  "properties": {
    "iso:country":"US",
    "sg:address":"850 S Harris St",
    "sg:city":"Hanford",
    "sg:classifiers":[
        {
            "category":"Social Services",
            "subcategory":"Child Care",
            "type":"Services"
        }
    ],
    "sg:phone":"+1 559 583 8485",
    "sg:postcode":"93230",
    "sg:province":"CA",
    "wof:name":"Rosa Parks Learning Ctr",
    "wof:placetype":"venue"
},
  "geometry": {"coordinates":[-119.64267700000001,36.315283],"type":"Point"}
}