{
  "type": "Feature",
  "properties": {
    "addr:full":"15381 7th St Victorville CA 92395",
    "addr:housenumber":"15381",
    "addr:postcode":"92395",
    "addr:street":"7Th St",
    "iso:country":"US",
    "sg:address":"15381 7th St",
    "sg:city":"Victorville",
    "sg:classifiers":[
        {
            "category":"Health Services",
            "subcategory":"Doctor",
            "type":"Services"
        },
        {
            "category":"Health Services",
            "subcategory":"Clinic",
            "type":"Services"
        }
    ],
    "sg:phone":"+1 760 245 2380",
    "sg:postcode":"92395",
    "sg:province":"CA",
    "sg:tags":[
        "physician",
        "family",
        "practice",
        "surgeons",
        "medicine",
        "surgeon"
    ],
    "wof:name":"Clinica Medica Laross",
    "wof:placetype":"venue"
},
  "geometry": {"coordinates":[-117.298278,34.531564],"type":"Point"}
}