{
  "type": "Feature",
  "properties": {
    "addr:full":"111 Sylvia Way San Rafael CA 94903",
    "addr:housenumber":"111",
    "addr:postcode":"94903",
    "addr:street":"Sylvia Way",
    "iso:country":"US",
    "sg:address":"111 Sylvia Way",
    "sg:city":"San Rafael",
    "sg:classifiers":[
        {
            "category":"Social Services",
            "type":"Services"
        }
    ],
    "sg:phone":"+1 415 453 0532",
    "sg:postcode":"94903",
    "sg:province":"CA",
    "sg:tags":[
        "counselor",
        "marriage",
        "family"
    ],
    "wof:name":"Richard D Flout",
    "wof:placetype":"venue"
},
  "geometry": {"coordinates":[-122.56517599999999,38.009153],"type":"Point"}
}