{
  "type": "Feature",
  "properties": {
    "iso:country":"US",
    "sg:address":"800 S Grand Ave",
    "sg:city":"Santa Ana",
    "sg:classifiers":[
        {
            "category":"Retail",
            "subcategory":"Auto Repair",
            "type":"Services"
        }
    ],
    "sg:phone":"+1 714 972 1216",
    "sg:postcode":"92705",
    "sg:province":"CA",
    "wof:name":"Toyauto",
    "wof:placetype":"venue"
},
  "geometry": {"coordinates":[-117.850414,33.737441],"type":"Point"}
}