{
  "type": "Feature",
  "properties": {
    "iso:country":"US",
    "sg:address":"2111 Portola Rd",
    "sg:city":"Ventura",
    "sg:classifiers":[
        {
            "category":"Home & Garden",
            "subcategory":"Furniture",
            "type":"Retail Goods"
        }
    ],
    "sg:phone":"+1 805 339 6388",
    "sg:postcode":"93003",
    "sg:province":"CA",
    "wof:name":"BKM Total Office-California",
    "wof:placetype":"venue"
},
  "geometry": {"coordinates":[-119.22483200000001,34.254894],"type":"Point"}
}