{
  "type": "Feature",
  "properties": {
    "iso:country":"US",
    "sg:address":"130 N Sherman Ave",
    "sg:city":"Corona",
    "sg:classifiers":[
        {
            "category":"Manufacturing",
            "subcategory":"Tools & Machinery",
            "type":"Manufacturing & Wholesale Goods"
        }
    ],
    "sg:phone":"+1 951 582 9399",
    "sg:postcode":"92882",
    "sg:province":"CA",
    "sg:tags":[
        "machine",
        "shop"
    ],
    "wof:name":"CMAG Enterprises Inc",
    "wof:placetype":"venue"
},
  "geometry": {"coordinates":[-117.58790999999999,33.883927],"type":"Point"}
}