{
  "type": "Feature",
  "properties": {
    "addr:full":"16100 Garfield Ave Paramount CA 90723",
    "addr:housenumber":"16100",
    "addr:postcode":"90723",
    "addr:street":"Garfield Ave",
    "iso:country":"US",
    "sg:address":"16100 Garfield Ave",
    "sg:city":"Paramount",
    "sg:classifiers":[
        {
            "category":"Wholesale",
            "subcategory":"Hardware",
            "type":"Manufacturing & Wholesale Goods"
        },
        {
            "category":"Manufacturing",
            "subcategory":"Retail Goods",
            "type":"Manufacturing & Wholesale Goods"
        }
    ],
    "sg:phone":"+1 562 630 2334",
    "sg:postcode":"90723",
    "sg:province":"CA",
    "sg:tags":[
        "fastener",
        "mfg"
    ],
    "wof:name":"J Power Products",
    "wof:placetype":"venue"
},
  "geometry": {"coordinates":[-118.16866,33.887685],"type":"Point"}
}