{
  "type": "Feature",
  "properties": {
    "addr:full":"1274 S Bonnie Beach Pl Los Angeles CA 90023",
    "addr:housenumber":"1274",
    "addr:postcode":"90023",
    "addr:street":"S Bonnie Beach Pl",
    "iso:country":"US",
    "sg:address":"1274 S Bonnie Beach Pl",
    "sg:city":"Los Angeles",
    "sg:classifiers":[
        {
            "category":"Freight",
            "type":"Transportation"
        }
    ],
    "sg:phone":"+1 323 264 7656",
    "sg:postcode":"90023",
    "sg:province":"CA",
    "sg:tags":[
        "trucking"
    ],
    "wof:name":"Santamaria Trucking",
    "wof:placetype":"venue"
},
  "geometry": {"coordinates":[-118.181211,34.018323],"type":"Point"}
}