{
  "type": "Feature",
  "properties": {
    "addr:full":"131 Mace St Madera CA 93638",
    "addr:housenumber":"131",
    "addr:postcode":"93638",
    "addr:street":"Mace St",
    "iso:country":"US",
    "sg:address":"131 Mace St",
    "sg:city":"Madera",
    "sg:classifiers":[
        {
            "category":"Government",
            "subcategory":"Office",
            "type":"Public Place"
        }
    ],
    "sg:phone":"+1 559 673 9752",
    "sg:postcode":"93638",
    "sg:province":"CA",
    "sg:tags":[
        "housing",
        "program"
    ],
    "wof:name":"Housing Auth Madera Pblc Phone",
    "wof:placetype":"venue"
},
  "geometry": {"coordinates":[-120.049997,36.96884],"type":"Point"}
}