{
  "type": "Feature",
  "properties": {
    "iso:country":"US",
    "sg:address":"4621 Burr St",
    "sg:city":"Bakersfield",
    "sg:classifiers":[
        {
            "category":"Mining & Drilling",
            "type":"Manufacturing & Wholesale Goods"
        }
    ],
    "sg:phone":"+1 661 321 3400",
    "sg:postcode":"93308",
    "sg:province":"CA",
    "sg:tags":[
        "field"
    ],
    "wof:name":"Rodco",
    "wof:placetype":"venue"
},
  "geometry": {"coordinates":[-119.052982,35.378683],"type":"Point"}
}