{
  "type": "Feature",
  "properties": {
    "iso:country":"US",
    "sg:address":"180 Capp St",
    "sg:city":"San Francisco",
    "sg:classifiers":[
        {
            "category":"Home & Garden",
            "subcategory":"Household Appliances",
            "type":"Retail Goods"
        }
    ],
    "sg:phone":"+1 415 626 7488",
    "sg:postcode":"94110",
    "sg:province":"CA",
    "sg:tags":[
        "machine",
        "sewing",
        "attachment"
    ],
    "wof:name":"Joanna Sewing Shop",
    "wof:placetype":"venue"
},
  "geometry": {"coordinates":[-122.41871999999999,37.764805],"type":"Point"}
}