{
  "type": "Feature",
  "properties": {
    "iso:country":"US",
    "sg:address":"1404 Paradise Rd",
    "sg:city":"Modesto",
    "sg:classifiers":[
        {
            "category":"Shopping",
            "subcategory":"Music",
            "type":"Retail Goods"
        }
    ],
    "sg:phone":"+1 209 579 7123",
    "sg:postcode":"95351",
    "sg:province":"CA",
    "sg:tags":[
        "video",
        "disc",
        "tape",
        "cassette"
    ],
    "wof:name":"Hi Fi Video",
    "wof:placetype":"venue"
},
  "geometry": {"coordinates":[-121.029421,37.616642],"type":"Point"}
}