{
  "type": "Feature",
  "properties": {
    "addr:full":"1044 C St Hayward CA 94541",
    "addr:housenumber":"1044",
    "addr:postcode":"94541",
    "addr:street":"C St",
    "iso:country":"US",
    "sg:address":"1044 C St",
    "sg:city":"Hayward",
    "sg:classifiers":[
        {
            "category":"Health Services",
            "subcategory":"Chiropractor",
            "type":"Services"
        }
    ],
    "sg:phone":"+1 510 537 3451",
    "sg:postcode":"94541",
    "sg:province":"CA",
    "sg:website":"www.herndonchiropractic.com",
    "wof:name":"Herndon Chiropractic",
    "wof:placetype":"venue"
},
  "geometry": {"coordinates":[-122.081001,37.672298],"type":"Point"}
}