{
  "type": "Feature",
  "properties": {
    "iso:country":"US",
    "sg:address":"5318 Palma Ave",
    "sg:city":"Atascadero",
    "sg:classifiers":[
        {
            "category":"Organizations",
            "subcategory":"Religious Organization",
            "type":"Services"
        }
    ],
    "sg:phone":"+1 805 466 0379",
    "sg:postcode":"93422",
    "sg:province":"CA",
    "sg:tags":[
        "church"
    ],
    "wof:name":"Atascadero-St Luke's Episcopal",
    "wof:placetype":"venue"
},
  "geometry": {"coordinates":[-120.675279,35.492978],"type":"Point"}
}