{
  "type": "Feature",
  "properties": {
    "iso:country":"US",
    "sg:address":"234 E Yosemite Ave",
    "sg:city":"Madera",
    "sg:classifiers":[
        {
            "category":"Shopping",
            "subcategory":"Department Store",
            "type":"Retail Goods"
        }
    ],
    "sg:phone":"+1 559 673 6011",
    "sg:postcode":"93638",
    "sg:province":"CA",
    "wof:name":"Factory 2-U",
    "wof:placetype":"venue"
},
  "geometry": {"coordinates":[-120.057687,36.963021],"type":"Point"}
}