{
  "type": "Feature",
  "properties": {
    "iso:country":"US",
    "sg:address":"24226 Sunnymead Blvd",
    "sg:city":"Moreno Valley",
    "sg:classifiers":[
        {
            "category":"Real Estate",
            "subcategory":"Real Estate Agent",
            "type":"Services"
        }
    ],
    "sg:phone":"+1 951 243 8620",
    "sg:postcode":"92553",
    "sg:province":"CA",
    "wof:name":"Independence Realty",
    "wof:placetype":"venue"
},
  "geometry": {"coordinates":[-117.241412,33.939173],"type":"Point"}
}