{
  "type": "Feature",
  "properties": {
    "iso:country":"US",
    "sg:address":"314 Pestana Ave",
    "sg:city":"Santa Cruz",
    "sg:classifiers":[
        {
            "category":"Shopping",
            "subcategory":"Florist",
            "type":"Retail Goods"
        }
    ],
    "sg:phone":"+1 831 427 2101",
    "sg:postcode":"95065",
    "sg:province":"CA",
    "sg:website":"www.sweeleysdesign.com",
    "wof:name":"Sweeley's Design Shop",
    "wof:placetype":"venue"
},
  "geometry": {"coordinates":[-121.975993,37.00087],"type":"Point"}
}