{
  "type": "Feature",
  "properties": {
    "iso:country":"US",
    "sg:address":"3 West 37th Avenue Suite 20",
    "sg:city":"San Mateo",
    "sg:classifiers":[
        {
            "category":"Personal",
            "subcategory":"Skin Care",
            "type":"Services"
        }
    ],
    "sg:phone":"+1 650 345 7500",
    "sg:postcode":"94403",
    "sg:province":"CA",
    "sg:website":"endermologiestudio.com/",
    "wof:name":"The Endermologie Studio",
    "wof:placetype":"venue"
},
  "geometry": {"coordinates":[-122.294749,37.534331],"type":"Point"}
}