{
  "type": "Feature",
  "properties": {
    "iso:country":"US",
    "sg:address":"1075 W 9th St",
    "sg:city":"Upland",
    "sg:classifiers":[
        {
            "category":"Building & Trades",
            "subcategory":"Construction",
            "type":"Services"
        },
        {
            "category":"Manufacturing",
            "subcategory":"Building Materials",
            "type":"Manufacturing & Wholesale Goods"
        },
        {
            "category":"Home & Garden",
            "subcategory":"Carpets & Floor Coverings",
            "type":"Retail Goods"
        }
    ],
    "sg:phone":"+1 909 949 2000",
    "sg:postcode":"91786",
    "sg:province":"CA",
    "sg:tags":[
        "materials-wholesale",
        "manufacturer",
        "tile-contractors"
    ],
    "wof:name":"Euro Floors Inc",
    "wof:placetype":"venue"
},
  "geometry": {"coordinates":[-117.667006,34.096026],"type":"Point"}
}