{
  "type": "Feature",
  "properties": {
    "addr:full":"1130 Research Dr Redlands CA 92374",
    "addr:housenumber":"1130",
    "addr:postcode":"92374",
    "addr:street":"Research Dr",
    "iso:country":"US",
    "sg:address":"1130 Research Dr",
    "sg:city":"Redlands",
    "sg:classifiers":[
        {
            "category":"Manufacturing",
            "subcategory":"Furniture",
            "type":"Manufacturing & Wholesale Goods"
        }
    ],
    "sg:phone":"+1 909 799 8550",
    "sg:postcode":"92374",
    "sg:province":"CA",
    "sg:tags":[
        "mfg",
        "wood",
        "kitchen",
        "cabinet"
    ],
    "sg:website":"www.caseworx.com",
    "wof:name":"Caseworx Inc",
    "wof:placetype":"venue"
},
  "geometry": {"coordinates":[-117.236681,34.07003],"type":"Point"}
}