{
  "type": "Feature",
  "properties": {
    "addr:full":"842 15th Pl Hermosa Beach CA 90254",
    "addr:housenumber":"842",
    "addr:postcode":"90254",
    "addr:street":"15Th Pl",
    "iso:country":"US",
    "sg:address":"842 15th Pl",
    "sg:city":"Hermosa Beach",
    "sg:classifiers":[
        {
            "category":"Organizations",
            "subcategory":"Non-profit Organization",
            "type":"Services"
        }
    ],
    "sg:phone":"+1 310 937 2544",
    "sg:postcode":"90254",
    "sg:province":"CA",
    "sg:tags":[
        "fund",
        "counselor",
        "raising"
    ],
    "wof:name":"JLK Promotions",
    "wof:placetype":"venue"
},
  "geometry": {"coordinates":[-118.391372,33.866545],"type":"Point"}
}