{
  "type": "Feature",
  "properties": {
    "iso:country":"US",
    "sg:address":"339 S A St",
    "sg:city":"Oxnard",
    "sg:classifiers":[
        {
            "category":"Home & Garden",
            "subcategory":"Furniture",
            "type":"Retail Goods"
        }
    ],
    "sg:phone":"+1 805 247 1868",
    "sg:postcode":"93030",
    "sg:province":"CA",
    "wof:name":"Crystal's Furniture",
    "wof:placetype":"venue"
},
  "geometry": {"coordinates":[-119.178636,34.199501],"type":"Point"}
}