{
  "type": "Feature",
  "properties": {
    "iso:country":"US",
    "sg:address":"9163 Chesapeake Dr",
    "sg:city":"San Diego",
    "sg:classifiers":[
        {
            "category":"Utilities",
            "subcategory":"Refuse",
            "type":"Services"
        }
    ],
    "sg:phone":"+1 619 670 0609",
    "sg:postcode":"92123",
    "sg:province":"CA",
    "sg:tags":[
        "disposal",
        "waste"
    ],
    "wof:name":"Chemical Safety Assoc Inc",
    "wof:placetype":"venue"
},
  "geometry": {"coordinates":[-117.131447,32.838889],"type":"Point"}
}