{
  "type": "Feature",
  "properties": {
    "addr:full":"4509 Camden Ct Granite Bay CA 95746",
    "addr:housenumber":"4509",
    "addr:postcode":"95746",
    "addr:street":"Camden Ct",
    "iso:country":"US",
    "sg:address":"4509 Camden Ct",
    "sg:city":"Granite Bay",
    "sg:classifiers":[
        {
            "category":"Freight",
            "type":"Transportation"
        }
    ],
    "sg:phone":"+1 916 791 5280",
    "sg:postcode":"95746",
    "sg:province":"CA",
    "sg:tags":[
        "courier"
    ],
    "wof:name":"HB Anderson Inc",
    "wof:placetype":"venue"
},
  "geometry": {"coordinates":[-121.21607899999999,38.728722],"type":"Point"}
}