{
  "type": "Feature",
  "properties": {
    "addr:full":"5043 Main St Coulterville CA 95311",
    "addr:housenumber":"5043",
    "addr:postcode":"95311",
    "addr:street":"Main St",
    "iso:country":"US",
    "sg:address":"5043 Main St",
    "sg:city":"Coulterville",
    "sg:classifiers":[
        {
            "category":"Personal",
            "subcategory":"Beauty Salon",
            "type":"Services"
        }
    ],
    "sg:phone":"+1 209 878 3251",
    "sg:postcode":"95311",
    "sg:province":"CA",
    "sg:tags":[
        "hair",
        "stylist"
    ],
    "wof:name":"Millie's Hair Mine",
    "wof:placetype":"venue"
},
  "geometry": {"coordinates":[-120.194771,37.712841],"type":"Point"}
}