{
  "type": "Feature",
  "properties": {
    "iso:country":"US",
    "sg:address":"1100 Blue Lake Sq",
    "sg:city":"Mountain View",
    "sg:classifiers":[
        {
            "category":"Professional",
            "subcategory":"Management & Consulting",
            "type":"Services"
        }
    ],
    "sg:phone":"+1 650 964 4717",
    "sg:postcode":"94040",
    "sg:province":"CA",
    "sg:tags":[
        "consultant",
        "business"
    ],
    "wof:name":"Rauco",
    "wof:placetype":"venue"
},
  "geometry": {"coordinates":[-122.06908,37.35847],"type":"Point"}
}