{
  "type": "Feature",
  "properties": {
    "iso:country":"US",
    "sg:address":"11721 Norgrove Ln",
    "sg:city":"Los Alamitos",
    "sg:classifiers":[
        {
            "category":"Wholesale",
            "subcategory":"Hardware",
            "type":"Manufacturing & Wholesale Goods"
        }
    ],
    "sg:phone":"+1 562 431 7804",
    "sg:postcode":"90720",
    "sg:province":"CA",
    "sg:tags":[
        "water",
        "product",
        "industrial",
        "commercial",
        "treatment"
    ],
    "wof:name":"Aqua Dynamics International",
    "wof:placetype":"venue"
},
  "geometry": {"coordinates":[-118.08112,33.792029],"type":"Point"}
}