{
  "type": "Feature",
  "properties": {
    "iso:country":"US",
    "sg:address":"1200 Hidden Valley Rd",
    "sg:city":"Westlake Village",
    "sg:classifiers":[
        {
            "category":"Recreation",
            "type":"Entertainment"
        }
    ],
    "sg:phone":"+1 805 495 7972",
    "sg:postcode":"91361",
    "sg:province":"CA",
    "sg:tags":[
        "animal"
    ],
    "wof:name":"Mark Watring Stables",
    "wof:placetype":"venue"
},
  "geometry": {"coordinates":[-118.919308,34.151072],"type":"Point"}
}