{
  "type": "Feature",
  "properties": {
    "addr:full":"932 A St Hayward CA 94541",
    "addr:housenumber":"932",
    "addr:postcode":"94541",
    "addr:street":"A St",
    "iso:country":"US",
    "sg:address":"932 A St",
    "sg:city":"Hayward",
    "sg:classifiers":[
        {
            "category":"Travel",
            "subcategory":"Travel Agent",
            "type":"Entertainment"
        }
    ],
    "sg:phone":"+1 510 538 2537",
    "sg:postcode":"94541",
    "sg:province":"CA",
    "sg:tags":[
        "agency",
        "bureau"
    ],
    "wof:name":"Top Travel Svc",
    "wof:placetype":"venue"
},
  "geometry": {"coordinates":[-122.084248,37.673725],"type":"Point"}
}