{
  "type": "Feature",
  "properties": {
    "iso:country":"US",
    "sg:address":"3744 Mt Diablo Blvd",
    "sg:city":"Lafayette",
    "sg:classifiers":[
        {
            "category":"Health Services",
            "subcategory":"Nursing And Care Facility",
            "type":"Services"
        }
    ],
    "sg:phone":"+1 925 283 9340",
    "sg:postcode":"94549",
    "sg:province":"CA",
    "sg:tags":[
        "nurse",
        "practice-arnp",
        "nurses-advanced"
    ],
    "wof:name":"Rn Teri Lac Leichenger",
    "wof:placetype":"venue"
},
  "geometry": {"coordinates":[-122.13162199999999,37.889405],"type":"Point"}
}