{
  "type": "Feature",
  "properties": {
    "iso:country":"US",
    "sg:address":"1730 P St",
    "sg:city":"Merced",
    "sg:classifiers":[
        {
            "category":"Insurance",
            "subcategory":"Hazard Insurance",
            "type":"Services"
        }
    ],
    "sg:phone":"+1 209 383 3303",
    "sg:postcode":"95340",
    "sg:province":"CA",
    "wof:name":"State Farm Insurance",
    "wof:placetype":"venue"
},
  "geometry": {"coordinates":[-120.489238,37.303969],"type":"Point"}
}