{
  "type": "Feature",
  "properties": {
    "iso:country":"US",
    "sg:address":"66 Argonaut Suite 100",
    "sg:city":"Aliso Viejo",
    "sg:classifiers":[
        {
            "category":"Arts & Performance",
            "subcategory":"Arts Center",
            "type":"Entertainment"
        },
        {
            "category":"Sports & Exercise",
            "subcategory":"Gym",
            "type":"Entertainment"
        }
    ],
    "sg:phone":"+1 949 837 0095",
    "sg:postcode":"92656",
    "sg:province":"CA",
    "sg:tags":[
        "trainer",
        "performing"
    ],
    "sg:website":"www.balletconservatorysv.com",
    "wof:name":"Ballet Conservatory",
    "wof:placetype":"venue"
},
  "geometry": {"coordinates":[-117.724146,33.592446],"type":"Point"}
}