{
  "type": "Feature",
  "properties": {
    "iso:country":"US",
    "sg:address":"2404 N Glassell St",
    "sg:city":"Orange",
    "sg:classifiers":[
        {
            "category":"Manufacturing",
            "subcategory":"Chemicals & Compounds",
            "type":"Manufacturing & Wholesale Goods"
        }
    ],
    "sg:phone":"+1 714 915 2937",
    "sg:postcode":"92865",
    "sg:province":"CA",
    "sg:tags":[
        "preparation",
        "toilet",
        "mfg"
    ],
    "wof:name":"Luxuriant",
    "wof:placetype":"venue"
},
  "geometry": {"coordinates":[-117.853044,33.827779],"type":"Point"}
}