{
  "type": "Feature",
  "properties": {
    "iso:country":"US",
    "sg:address":"1253 N La Brea Ave",
    "sg:city":"West Hollywood",
    "sg:classifiers":[
        {
            "category":"Restaurant",
            "type":"Food & Drink"
        }
    ],
    "sg:phone":"+1 323 969 8611",
    "sg:postcode":"90038",
    "sg:province":"CA",
    "sg:tags":[
        "thai"
    ],
    "sg:website":"www.KinareeThaiBistro.com/",
    "wof:name":"Kinaree Thai Bistro",
    "wof:placetype":"venue"
},
  "geometry": {"coordinates":[-118.344113,34.093959],"type":"Point"}
}