{
  "type": "Feature",
  "properties": {
    "addr:full":"902 Burlingame Ave Clovis CA 93612",
    "addr:housenumber":"902",
    "addr:postcode":"93612",
    "addr:street":"Burlingame Ave",
    "iso:country":"US",
    "sg:address":"902 Burlingame Ave",
    "sg:city":"Clovis",
    "sg:classifiers":[
        {
            "category":"Professional",
            "type":"Services"
        }
    ],
    "sg:phone":"+1 559 299 7674",
    "sg:postcode":"93612",
    "sg:province":"CA",
    "wof:name":"Jean Skaf",
    "wof:placetype":"venue"
},
  "geometry": {"coordinates":[-119.697142,36.834542],"type":"Point"}
}