{
  "type": "Feature",
  "properties": {
    "addr:full":"1026 Pine St Paso Robles CA 93446",
    "addr:housenumber":"1026",
    "addr:postcode":"93446",
    "addr:street":"Pine St",
    "iso:country":"US",
    "sg:address":"1026 Pine St",
    "sg:city":"Paso Robles",
    "sg:classifiers":[
        {
            "category":"Wholesale",
            "subcategory":"Machinery & Supplies",
            "type":"Manufacturing & Wholesale Goods"
        }
    ],
    "sg:phone":"+1 805 238 2112",
    "sg:postcode":"93446",
    "sg:province":"CA",
    "sg:tags":[
        "janitor"
    ],
    "wof:name":"Western Janitor Supply",
    "wof:placetype":"venue"
},
  "geometry": {"coordinates":[-120.688597,35.624956],"type":"Point"}
}