{
  "type": "Feature",
  "properties": {
    "addr:full":"13021 Leffingwell Ave Santa Fe Springs CA 90670",
    "addr:housenumber":"13021",
    "addr:postcode":"90670",
    "addr:street":"Leffingwell Ave",
    "iso:country":"US",
    "sg:address":"13021 Leffingwell Ave",
    "sg:city":"Santa Fe Springs",
    "sg:classifiers":[
        {
            "category":"Personal",
            "type":"Services"
        }
    ],
    "sg:phone":"+1 562 645 5730",
    "sg:postcode":"90670",
    "sg:province":"CA",
    "sg:tags":[
        "mover",
        "local"
    ],
    "sg:website":"www.navl.com/yelp-BeltmannGroupS...",
    "wof:name":"Beltmann Relocation Group Inc.",
    "wof:placetype":"venue"
},
  "geometry": {"coordinates":[-118.050252,33.915355],"type":"Point"}
}