{
  "type": "Feature",
  "properties": {
    "addr:full":"1777 Angela St San Jose CA 95125",
    "addr:housenumber":"1777",
    "addr:postcode":"95125",
    "addr:street":"Angela St",
    "iso:country":"US",
    "sg:address":"1777 Angela St",
    "sg:city":"San Jose",
    "sg:classifiers":[
        {
            "category":"Retail",
            "subcategory":"Auto Repair",
            "type":"Services"
        }
    ],
    "sg:phone":"+1 408 288 7766",
    "sg:postcode":"95125",
    "sg:province":"CA",
    "wof:name":"Dastgah Auto Service Center",
    "wof:placetype":"venue"
},
  "geometry": {"coordinates":[-121.876999,37.304798],"type":"Point"}
}