{
  "type": "Feature",
  "properties": {
    "addr:full":"471 Almond Dr Lodi CA 95240",
    "addr:housenumber":"471",
    "addr:postcode":"95240",
    "addr:street":"Almond Dr",
    "iso:country":"US",
    "sg:address":"471 Almond Dr",
    "sg:city":"Lodi",
    "sg:classifiers":[
        {
            "category":"Home & Garden",
            "subcategory":"Mobile Homes",
            "type":"Retail Goods"
        }
    ],
    "sg:phone":"+1 209 368 5731",
    "sg:postcode":"95240",
    "sg:province":"CA",
    "wof:name":"United Homes Of America",
    "wof:placetype":"venue"
},
  "geometry": {"coordinates":[-121.263606,38.111278],"type":"Point"}
}