{
  "type": "Feature",
  "properties": {
    "addr:full":"Dolores & 7th Avenue Carmel CA 93923",
    "addr:postcode":"93923",
    "addr:street":"Avenue",
    "iso:country":"US",
    "sg:address":"Dolores & 7th Avenue",
    "sg:city":"Carmel",
    "sg:classifiers":[
        {
            "category":"Coffee & Tea",
            "type":"Food & Drink"
        },
        {
            "category":"Food & Beverages",
            "subcategory":"Bakery",
            "type":"Retail Goods"
        }
    ],
    "sg:phone":"+1 831 624 6365",
    "sg:postcode":"93923",
    "sg:province":"CA",
    "sg:tags":[
        "sandwich"
    ],
    "sg:website":"www.tuckbox.com",
    "wof:name":"The Tuck Box",
    "wof:placetype":"venue"
},
  "geometry": {"coordinates":[-121.922675,36.553764],"type":"Point"}
}