{
  "type": "Feature",
  "properties": {
    "addr:full":"5550 W End Rd Arcata CA 95521",
    "addr:housenumber":"5550",
    "addr:postcode":"95521",
    "addr:street":"W End Rd",
    "iso:country":"US",
    "sg:address":"5550 W End Rd",
    "sg:city":"Arcata",
    "sg:classifiers":[
        {
            "category":"Freight",
            "type":"Transportation"
        }
    ],
    "sg:phone":"+1 707 822 2975",
    "sg:postcode":"95521",
    "sg:province":"CA",
    "sg:tags":[
        "operator",
        "local",
        "trucking"
    ],
    "wof:name":"Wayne Bare Trucking Inc",
    "wof:placetype":"venue"
},
  "geometry": {"coordinates":[-124.071789,40.905153],"type":"Point"}
}