{
  "type": "Feature",
  "properties": {
    "iso:country":"US",
    "sg:address":"4436 S Chestnut Ave",
    "sg:city":"Fresno",
    "sg:classifiers":[
        {
            "category":"Retail",
            "subcategory":"Auto Repair",
            "type":"Services"
        }
    ],
    "sg:phone":"+1 559 233 5615",
    "sg:postcode":"93725",
    "sg:province":"CA",
    "sg:tags":[
        "repairing",
        "automobile"
    ],
    "wof:name":"Jose's Auto Repair",
    "wof:placetype":"venue"
},
  "geometry": {"coordinates":[-119.736648,36.66386],"type":"Point"}
}