{
  "type": "Feature",
  "properties": {
    "addr:full":"350 Bay St Pier 39 San Francisco CA 94133",
    "addr:housenumber":"350;39",
    "addr:postcode":"94133",
    "addr:street":"Bay St Pier",
    "iso:country":"US",
    "sg:address":"350 Bay St Pier 39",
    "sg:city":"San Francisco",
    "sg:classifiers":[
        {
            "category":"Recreation",
            "subcategory":"Boat Charter",
            "type":"Entertainment"
        }
    ],
    "sg:phone":"+1 415 378 4887",
    "sg:postcode":"94133",
    "sg:province":"CA",
    "sg:tags":[
        "boating"
    ],
    "sg:website":"www.sailsf.com",
    "wof:name":"San Francisco Sailing Company",
    "wof:placetype":"venue"
},
  "geometry": {"coordinates":[-122.412756,37.805845],"type":"Point"}
}