{
  "type": "Feature",
  "properties": {
    "addr:full":"217 Percy Ave Yuba City CA 95991",
    "addr:housenumber":"217",
    "addr:postcode":"95991",
    "addr:street":"Percy Ave",
    "iso:country":"US",
    "sg:address":"217 Percy Ave",
    "sg:city":"Yuba City",
    "sg:classifiers":[
        {
            "category":"Personal",
            "subcategory":"Beauty Salon",
            "type":"Services"
        }
    ],
    "sg:phone":"+1 530 671 0742",
    "sg:postcode":"95991",
    "sg:province":"CA",
    "wof:name":"Hair Affair",
    "wof:placetype":"venue"
},
  "geometry": {"coordinates":[-121.615534,39.126292],"type":"Point"}
}