{
  "type": "Feature",
  "properties": {
    "addr:full":"840 Auditorium Dr Redding CA 96001",
    "addr:housenumber":"840",
    "addr:postcode":"96001",
    "addr:street":"Auditorium Dr",
    "iso:country":"US",
    "sg:address":"840 Auditorium Dr",
    "sg:city":"Redding",
    "sg:classifiers":[
        {
            "category":"Museum",
            "type":"Entertainment"
        }
    ],
    "sg:phone":"+1 530 243 8850",
    "sg:postcode":"96001",
    "sg:province":"CA",
    "wof:name":"Turtle Bay Exploration Park",
    "wof:placetype":"venue"
},
  "geometry": {"coordinates":[-122.378803,40.587926],"type":"Point"}
}