{
  "type": "Feature",
  "properties": {
    "addr:full":"22807 Lyons Ave Newhall CA 91321",
    "addr:housenumber":"22807",
    "addr:postcode":"91321",
    "addr:street":"Lyons Ave",
    "iso:country":"US",
    "sg:address":"22807 Lyons Ave",
    "sg:city":"Newhall",
    "sg:classifiers":[
        {
            "category":"Retail",
            "subcategory":"Auto Rental",
            "type":"Services"
        }
    ],
    "sg:phone":"+1 661 222 7878",
    "sg:postcode":"91321",
    "sg:province":"CA",
    "sg:tags":[
        "renting",
        "passenger",
        "car",
        "automobile"
    ],
    "wof:name":"Enterprise Rent-A-Car",
    "wof:placetype":"venue"
},
  "geometry": {"coordinates":[-118.531998,34.380402],"type":"Point"}
}