{
  "type": "Feature",
  "properties": {
    "addr:full":"215 Santa Monica Blvd Santa Monica CA 90401",
    "addr:housenumber":"215",
    "addr:postcode":"90401",
    "addr:street":"Santa Monica Blvd",
    "iso:country":"US",
    "sg:address":"215 Santa Monica Blvd",
    "sg:city":"Santa Monica",
    "sg:classifiers":[
        {
            "category":"Shopping",
            "subcategory":"Shoes",
            "type":"Retail Goods"
        }
    ],
    "sg:phone":"+1 310 395 8999",
    "sg:postcode":"90401",
    "sg:province":"CA",
    "wof:name":"Easy Spirit",
    "wof:placetype":"venue"
},
  "geometry": {"coordinates":[-118.49626499999999,34.015609],"type":"Point"}
}