{
  "type": "Feature",
  "properties": {
    "iso:country":"US",
    "sg:address":"7533 Mctavish Cir",
    "sg:city":"Sacramento",
    "sg:classifiers":[
        {
            "category":"Shopping",
            "subcategory":"Hobbies, Toys, & Games",
            "type":"Retail Goods"
        }
    ],
    "sg:phone":"+1 916 688 8624",
    "sg:postcode":"95828",
    "sg:province":"CA",
    "sg:tags":[
        "toy",
        "store",
        "supply"
    ],
    "wof:name":"K & W Carpet And Toys Inc",
    "wof:placetype":"venue"
},
  "geometry": {"coordinates":[-121.41515800000001,38.482899],"type":"Point"}
}