{
  "type": "Feature",
  "properties": {
    "addr:full":"155 N Raymond Ave Pasadena CA 91103",
    "addr:housenumber":"155",
    "addr:postcode":"91103",
    "addr:street":"N Raymond Ave",
    "iso:country":"US",
    "sg:address":"155 N Raymond Ave",
    "sg:city":"Pasadena",
    "sg:classifiers":[
        {
            "category":"Bars & Pubs",
            "subcategory":"Wine Bar",
            "type":"Food & Drink"
        }
    ],
    "sg:phone":"+1 626 844 9333",
    "sg:postcode":"91103",
    "sg:province":"CA",
    "sg:website":"www.heritagewinecompany.com",
    "wof:name":"Heritage Wine Company",
    "wof:placetype":"venue"
},
  "geometry": {"coordinates":[-118.14934599999999,34.148569],"type":"Point"}
}