{
  "type": "Feature",
  "properties": {
    "iso:country":"US",
    "sg:address":"750 Sugar Pine Dr",
    "sg:city":"Lathrop",
    "sg:classifiers":[
        {
            "category":"Professional",
            "subcategory":"Management & Consulting",
            "type":"Services"
        }
    ],
    "sg:phone":"+1 209 983 5293",
    "sg:postcode":"95330",
    "sg:province":"CA",
    "sg:tags":[
        "consultant",
        "planning"
    ],
    "wof:name":"Cad Technology",
    "wof:placetype":"venue"
},
  "geometry": {"coordinates":[-121.27871500000001,37.83177],"type":"Point"}
}