{
  "type": "Feature",
  "properties": {
    "addr:full":"5728 el Cajon Blvd San Diego CA 92115",
    "addr:housenumber":"5728",
    "addr:postcode":"92115",
    "addr:street":"El Cajon Blvd",
    "iso:country":"US",
    "sg:address":"5728 el Cajon Blvd",
    "sg:city":"San Diego",
    "sg:classifiers":[
        {
            "category":"Manufacturing",
            "subcategory":"Signs",
            "type":"Manufacturing & Wholesale Goods"
        }
    ],
    "sg:phone":"+1 619 286 4079",
    "sg:postcode":"92115",
    "sg:province":"CA",
    "wof:name":"Business Signs",
    "wof:placetype":"venue"
},
  "geometry": {"coordinates":[-117.073092,32.75879],"type":"Point"}
}