{
  "type": "Feature",
  "properties": {
    "addr:full":"19113 S Hamilton Ave Gardena CA 90248",
    "addr:housenumber":"19113",
    "addr:postcode":"90248",
    "addr:street":"S Hamilton Ave",
    "iso:country":"US",
    "sg:address":"19113 S Hamilton Ave",
    "sg:city":"Gardena",
    "sg:classifiers":[
        {
            "category":"Building & Trades",
            "subcategory":"Construction",
            "type":"Services"
        }
    ],
    "sg:phone":"+1 310 719 7103",
    "sg:postcode":"90248",
    "sg:province":"CA",
    "sg:tags":[
        "foundation",
        "contractor"
    ],
    "wof:name":"August Construction & Drilling",
    "wof:placetype":"venue"
},
  "geometry": {"coordinates":[-118.28608,33.85499],"type":"Point"}
}