{
  "type": "Feature",
  "properties": {
    "addr:full":"2730 Fulton St San Francisco CA 94118",
    "addr:housenumber":"2730",
    "addr:postcode":"94118",
    "addr:street":"Fulton St",
    "iso:country":"US",
    "sg:address":"2730 Fulton St",
    "sg:city":"San Francisco",
    "sg:classifiers":[
        {
            "category":"Health Services",
            "subcategory":"Health Practitioner",
            "type":"Services"
        }
    ],
    "sg:phone":"+1 415 387 2315",
    "sg:postcode":"94118",
    "sg:province":"CA",
    "sg:tags":[
        "psychologist"
    ],
    "wof:name":"Gary A Lucchese PHD",
    "wof:placetype":"venue"
},
  "geometry": {"coordinates":[-122.46137400000001,37.77401],"type":"Point"}
}