{
  "type": "Feature",
  "properties": {
    "iso:country":"US",
    "sg:address":"324 S Brookhurst St",
    "sg:city":"Anaheim",
    "sg:classifiers":[
        {
            "category":"Restaurant",
            "type":"Food & Drink"
        }
    ],
    "sg:phone":"+1 714 778 0730",
    "sg:postcode":"92804",
    "sg:province":"CA",
    "wof:name":"Taco Bell",
    "wof:placetype":"venue"
},
  "geometry": {"coordinates":[-117.959,33.828201],"type":"Point"}
}