{
  "type": "Feature",
  "properties": {
    "iso:country":"US",
    "sg:address":"1143 E 63rd St",
    "sg:city":"Los Angeles",
    "sg:classifiers":[
        {
            "category":"Professional",
            "type":"Services"
        }
    ],
    "sg:phone":"+1 323 232 8589",
    "sg:postcode":"90001",
    "sg:province":"CA",
    "sg:tags":[
        "establishment"
    ],
    "wof:name":"Becrra Guadalupe",
    "wof:placetype":"venue"
},
  "geometry": {"coordinates":[-118.256015,33.982534],"type":"Point"}
}