{
  "type": "Feature",
  "properties": {
    "addr:full":"320 W Pacific Coast Hwy Wilmington CA 90744",
    "addr:housenumber":"320",
    "addr:postcode":"90744",
    "addr:street":"W Pacific Coast Hwy",
    "iso:country":"US",
    "sg:address":"320 W Pacific Coast Hwy",
    "sg:city":"Wilmington",
    "sg:classifiers":[
        {
            "category":"Personal",
            "subcategory":"Barber",
            "type":"Services"
        }
    ],
    "sg:phone":"+1 310 513 9874",
    "sg:postcode":"90744",
    "sg:province":"CA",
    "wof:name":"John's Hairstyling",
    "wof:placetype":"venue"
},
  "geometry": {"coordinates":[-118.266998,33.7911],"type":"Point"}
}