{
  "type": "Feature",
  "properties": {
    "iso:country":"US",
    "sg:address":"19800 Van Ness Ave",
    "sg:city":"Torrance",
    "sg:classifiers":[
        {
            "category":"Manufacturing",
            "subcategory":"Metals",
            "type":"Manufacturing & Wholesale Goods"
        }
    ],
    "sg:phone":"+1 310 323 9500",
    "sg:postcode":"90501",
    "sg:province":"CA",
    "sg:tags":[
        "die",
        "casting",
        "aluminum"
    ],
    "wof:name":"Garrett Processing",
    "wof:placetype":"venue"
},
  "geometry": {"coordinates":[-118.317691,33.850507],"type":"Point"}
}