{
  "type": "Feature",
  "properties": {
    "addr:full":"114 W Lime Ave Monrovia CA 91016",
    "addr:housenumber":"114",
    "addr:postcode":"91016",
    "addr:street":"W Lime Ave",
    "iso:country":"US",
    "sg:address":"114 W Lime Ave",
    "sg:city":"Monrovia",
    "sg:classifiers":[
        {
            "category":"Shopping",
            "subcategory":"Clothing, Apparel, & Fashions",
            "type":"Retail Goods"
        },
        {
            "category":"Building & Trades",
            "subcategory":"Cleaning & Sanitation",
            "type":"Services"
        },
        {
            "category":"Manufacturing",
            "subcategory":"Building Materials",
            "type":"Manufacturing & Wholesale Goods"
        },
        {
            "category":"Sports & Exercise",
            "subcategory":"Playing Field",
            "type":"Entertainment"
        }
    ],
    "sg:phone":"+1 626 471 9912",
    "sg:postcode":"91016",
    "sg:province":"CA",
    "sg:tags":[
        "repairing",
        "storage",
        "dyeing-retail",
        "fur",
        "remodeling"
    ],
    "sg:website":"http://www.bondfurs.com",
    "wof:name":"Bond Furs Inc",
    "wof:placetype":"venue"
},
  "geometry": {"coordinates":[-118.00128100000001,34.148068],"type":"Point"}
}