{
  "type": "Feature",
  "properties": {
    "iso:country":"US",
    "sg:address":"100 Northridge Shopping Ctr",
    "sg:city":"Salinas",
    "sg:classifiers":[
        {
            "category":"Shopping",
            "subcategory":"Clothing, Apparel, & Fashions",
            "type":"Retail Goods"
        },
        {
            "category":"Shopping",
            "subcategory":"Beauty & Cosmetics",
            "type":"Retail Goods"
        },
        {
            "category":"Home & Garden",
            "subcategory":"Home Furnishings",
            "type":"Retail Goods"
        },
        {
            "category":"Shopping",
            "type":"Retail Goods"
        },
        {
            "category":"Shopping",
            "subcategory":"Catalog Store",
            "type":"Retail Goods"
        },
        {
            "category":"Professional",
            "subcategory":"Art Services",
            "type":"Services"
        },
        {
            "category":"Shopping",
            "subcategory":"Shoes",
            "type":"Retail Goods"
        },
        {
            "category":"Shopping",
            "subcategory":"Department Store",
            "type":"Retail Goods"
        },
        {
            "category":"Shopping",
            "subcategory":"Jewelry",
            "type":"Retail Goods"
        }
    ],
    "sg:phone":"+1 888 314 5960",
    "sg:postcode":"93906",
    "sg:province":"CA",
    "sg:tags":[
        "draperies",
        "designer",
        "vertical",
        "supply",
        "blinds-venetian",
        "jeweler",
        "equipment",
        "window",
        "interior",
        "treatment",
        "housewares",
        "curtain",
        "showroom",
        "clothing",
        "decorator",
        "merchandise"
    ],
    "sg:website":"http://national.citysearch.com/profile/external/46618905/salinas_ca/jcpenney_custom_decorating.html?publisher=yellowpages&reference_id=1&placement=ypwebsitemip",
    "wof:name":"JCPenney Custom Decorating",
    "wof:placetype":"venue"
},
  "geometry": {"coordinates":[-121.655388,36.71693],"type":"Point"}
}