{
  "type": "Feature",
  "properties": {
    "addr:full":"3056 24th St San Francisco CA 94110",
    "addr:housenumber":"3056",
    "addr:postcode":"94110",
    "addr:street":"24Th St",
    "iso:country":"US",
    "sg:address":"3056 24th St",
    "sg:city":"San Francisco",
    "sg:classifiers":[
        {
            "category":"Shopping",
            "subcategory":"Gifts & Souvenirs",
            "type":"Retail Goods"
        }
    ],
    "sg:phone":"+1 415 643 5347",
    "sg:postcode":"94110",
    "sg:province":"CA",
    "sg:tags":[
        "shop"
    ],
    "wof:name":"La Noventa Y Siete",
    "wof:placetype":"venue"
},
  "geometry": {"coordinates":[-122.413411,37.752622],"type":"Point"}
}