{
  "type": "Feature",
  "properties": {
    "addr:full":"1069 Center St San Carlos CA 94070",
    "addr:housenumber":"1069",
    "addr:postcode":"94070",
    "addr:street":"Center St",
    "iso:country":"US",
    "sg:address":"1069 Center St",
    "sg:city":"San Carlos",
    "sg:classifiers":[
        {
            "category":"Home & Garden",
            "subcategory":"Building Materials",
            "type":"Retail Goods"
        }
    ],
    "sg:phone":"+1 650 593 3079",
    "sg:postcode":"94070",
    "sg:province":"CA",
    "sg:tags":[
        "lumber"
    ],
    "wof:name":"Redwood Lumber & Supply Co",
    "wof:placetype":"venue"
},
  "geometry": {"coordinates":[-122.246855,37.498105],"type":"Point"}
}