{
  "type": "Feature",
  "properties": {
    "iso:country":"US",
    "sg:address":"4811 Hopyard Rd",
    "sg:city":"Pleasanton",
    "sg:classifiers":[
        {
            "category":"Manufacturing",
            "subcategory":"Textiles",
            "type":"Manufacturing & Wholesale Goods"
        },
        {
            "category":"Home & Garden",
            "subcategory":"Building Materials",
            "type":"Retail Goods"
        },
        {
            "category":"Building & Trades",
            "subcategory":"Construction",
            "type":"Services"
        },
        {
            "category":"Utilities",
            "subcategory":"Natural Gas",
            "type":"Services"
        }
    ],
    "sg:phone":"+1 925 463 6000",
    "sg:postcode":"94588",
    "sg:province":"CA",
    "sg:tags":[
        "stone",
        "tile-wholesale",
        "marble-natural",
        "bathroom",
        "tile-contractors",
        "granite",
        "remodeling",
        "manufacturer"
    ],
    "sg:website":"http://www.callahantileandstone.com",
    "wof:name":"Callahan Tile & Stone",
    "wof:placetype":"venue"
},
  "geometry": {"coordinates":[-121.903571,37.691603],"type":"Point"}
}