{
  "type": "Feature",
  "properties": {
    "addr:full":"4000 Barranca Pkwy Irvine CA 92604",
    "addr:housenumber":"4000",
    "addr:postcode":"92604",
    "addr:street":"Barranca Pkwy",
    "iso:country":"US",
    "sg:address":"4000 Barranca Pkwy",
    "sg:city":"Irvine",
    "sg:classifiers":[
        {
            "category":"Wholesale",
            "subcategory":"Electrical",
            "type":"Manufacturing & Wholesale Goods"
        }
    ],
    "sg:phone":"+1 949 262 3235",
    "sg:postcode":"92604",
    "sg:province":"CA",
    "sg:tags":[
        "battery",
        "standby",
        "industrial",
        "system",
        "power"
    ],
    "wof:name":"Courtney Industrial Battery",
    "wof:placetype":"venue"
},
  "geometry": {"coordinates":[-117.807068,33.68325],"type":"Point"}
}