{
  "type": "Feature",
  "properties": {
    "addr:full":"1901 S Bascom Avenue Suite 280 Campbell CA 95008",
    "addr:housenumber":"1901",
    "addr:postcode":"95008",
    "addr:street":"S Bascom Avenue Suite 280",
    "iso:country":"US",
    "sg:address":"1901 S Bascom Avenue Suite 280",
    "sg:city":"Campbell",
    "sg:classifiers":[
        {
            "category":"Banks & Credit Unions",
            "subcategory":"Financial Services",
            "type":"Services"
        }
    ],
    "sg:phone":"+1 408 583 3100",
    "sg:postcode":"95008",
    "sg:province":"CA",
    "sg:tags":[
        "broker",
        "mortgage"
    ],
    "wof:name":"Lawson & Assc",
    "wof:placetype":"venue"
},
  "geometry": {"coordinates":[-121.931648,37.289779],"type":"Point"}
}