{
  "type": "Feature",
  "properties": {
    "addr:full":"101 W Central Ave Brea CA 92821",
    "addr:housenumber":"101",
    "addr:postcode":"92821",
    "addr:street":"W Central Ave",
    "iso:country":"US",
    "sg:address":"101 W Central Ave",
    "sg:city":"Brea",
    "sg:classifiers":[
        {
            "category":"Professional",
            "subcategory":"Engineering",
            "type":"Services"
        }
    ],
    "sg:phone":"+1 714 562 5020",
    "sg:postcode":"92821",
    "sg:province":"CA",
    "sg:tags":[
        "engineer"
    ],
    "sg:website":"www.bachmon.com",
    "wof:name":"Bachmon Engineering",
    "wof:placetype":"venue"
},
  "geometry": {"coordinates":[-117.89512000000001,33.93208],"type":"Point"}
}