{
  "type": "Feature",
  "properties": {
    "iso:country":"US",
    "sg:address":"430 W 168th St",
    "sg:city":"Gardena",
    "sg:classifiers":[
        {
            "category":"Building & Trades",
            "subcategory":"Construction",
            "type":"Services"
        }
    ],
    "sg:phone":"+1 310 327 2263",
    "sg:postcode":"90248",
    "sg:province":"CA",
    "sg:tags":[
        "roofing",
        "contractor"
    ],
    "wof:name":"Mutual Roofing Company Inc",
    "wof:placetype":"venue"
},
  "geometry": {"coordinates":[-118.281217,33.879427],"type":"Point"}
}