{
  "type": "Feature",
  "properties": {
    "addr:full":"310 San Bruno Ave E San Bruno CA 94066",
    "addr:housenumber":"310",
    "addr:postcode":"94066",
    "addr:street":"San Bruno Ave E",
    "iso:country":"US",
    "sg:address":"310 San Bruno Ave E",
    "sg:city":"San Bruno",
    "sg:classifiers":[
        {
            "category":"Autos & Motor Vehicles",
            "subcategory":"Fuel & Gas Station",
            "type":"Retail Goods"
        }
    ],
    "sg:phone":"+1 650 583 8793",
    "sg:postcode":"94066",
    "sg:province":"CA",
    "sg:tags":[
        "oil"
    ],
    "wof:name":"Barbaria Exxon",
    "wof:placetype":"venue"
},
  "geometry": {"coordinates":[-122.41029899999999,37.630928],"type":"Point"}
}