{
  "type": "Feature",
  "properties": {
    "iso:country":"US",
    "sg:address":"2228 Knobcone Ave",
    "sg:city":"Anderson",
    "sg:classifiers":[
        {
            "category":"Shopping",
            "type":"Retail Goods"
        }
    ],
    "sg:phone":"+1 530 365 3251",
    "sg:postcode":"96007",
    "sg:province":"CA",
    "sg:tags":[
        "marker",
        "grave"
    ],
    "wof:name":"Sherman Memorials",
    "wof:placetype":"venue"
},
  "geometry": {"coordinates":[-122.298389,40.435262],"type":"Point"}
}