{
  "type": "Feature",
  "properties": {
    "addr:full":"128 E Juanita Ave Glendora CA 91740",
    "addr:housenumber":"128",
    "addr:postcode":"91740",
    "addr:street":"E Juanita Ave",
    "iso:country":"US",
    "sg:address":"128 E Juanita Ave",
    "sg:city":"Glendora",
    "sg:classifiers":[
        {
            "category":"Professional",
            "subcategory":"Computer Services",
            "type":"Services"
        }
    ],
    "sg:phone":"+1 626 335 2187",
    "sg:postcode":"91740",
    "sg:province":"CA",
    "sg:tags":[
        "repair"
    ],
    "wof:name":"Computer Troubleshooters",
    "wof:placetype":"venue"
},
  "geometry": {"coordinates":[-117.86177600000001,34.110236],"type":"Point"}
}