{
  "type": "Feature",
  "properties": {
    "iso:country":"US",
    "sg:address":"50 Eastshore",
    "sg:city":"Irvine",
    "sg:classifiers":[
        {
            "category":"Real Estate",
            "subcategory":"Real Estate Operator",
            "type":"Services"
        }
    ],
    "sg:phone":"+1 949 551 6800",
    "sg:postcode":"92604",
    "sg:province":"CA",
    "sg:tags":[
        "apartment"
    ],
    "wof:name":"Woodbridge Meadows Apartments",
    "wof:placetype":"venue"
},
  "geometry": {"coordinates":[-117.78632899999999,33.676112],"type":"Point"}
}