{
  "type": "Feature",
  "properties": {
    "iso:country":"US",
    "sg:address":"2991 el Camino Real",
    "sg:city":"Redwood City",
    "sg:classifiers":[
        {
            "category":"Professional",
            "subcategory":"Lawyer & Legal Services",
            "type":"Services"
        }
    ],
    "sg:phone":"+1 650 482 3082",
    "sg:postcode":"94061",
    "sg:province":"CA",
    "sg:tags":[
        "attorney"
    ],
    "wof:name":"David M Woolfe",
    "wof:placetype":"venue"
},
  "geometry": {"coordinates":[-122.21168,37.469234],"type":"Point"}
}