{
  "type": "Feature",
  "properties": {
    "addr:full":"2959 S King Road San Jose CA 95122",
    "addr:housenumber":"2959",
    "addr:postcode":"95122",
    "addr:street":"S King Road",
    "iso:country":"US",
    "sg:address":"2959 S King Road",
    "sg:city":"San Jose",
    "sg:classifiers":[
        {
            "category":"Government",
            "subcategory":"Office",
            "type":"Public Place"
        }
    ],
    "sg:phone":"+1 408 528 9925",
    "sg:postcode":"95122",
    "sg:province":"CA",
    "sg:tags":[
        "smog",
        "check"
    ],
    "wof:name":"Evergreen Smog",
    "wof:placetype":"venue"
},
  "geometry": {"coordinates":[-121.813199,37.313488],"type":"Point"}
}