{
  "type": "Feature",
  "properties": {
    "iso:country":"US",
    "sg:address":"116 N Y St",
    "sg:city":"Lompoc",
    "sg:classifiers":[
        {
            "category":"Building & Trades",
            "subcategory":"Landscaping Services",
            "type":"Services"
        }
    ],
    "sg:phone":"+1 805 968 8535",
    "sg:postcode":"93436",
    "sg:province":"CA",
    "sg:tags":[
        "tree"
    ],
    "wof:name":"Mcpherson Tree Care, Inc.",
    "wof:placetype":"venue"
},
  "geometry": {"coordinates":[-120.478427,34.639629],"type":"Point"}
}