{
  "type": "Feature",
  "properties": {
    "iso:country":"US",
    "sg:address":"538 Cleveland Ave",
    "sg:city":"Sebastopol",
    "sg:classifiers":[
        {
            "category":"Manufacturing",
            "subcategory":"Food",
            "type":"Manufacturing & Wholesale Goods"
        }
    ],
    "sg:phone":"+1 707 823 6704",
    "sg:postcode":"95472",
    "sg:province":"CA",
    "sg:tags":[
        "preparation",
        "grocery",
        "mfg"
    ],
    "wof:name":"R Honey Pots",
    "wof:placetype":"venue"
},
  "geometry": {"coordinates":[-122.829171,38.406762],"type":"Point"}
}