{
  "type": "Feature",
  "properties": {
    "iso:country":"US",
    "sg:address":"2925 Sycamore Dr",
    "sg:city":"Simi Valley",
    "sg:classifiers":[
        {
            "category":"Health Services",
            "subcategory":"Health Practitioner",
            "type":"Services"
        }
    ],
    "sg:phone":"+1 805 583 9575",
    "sg:postcode":"93065",
    "sg:province":"CA",
    "sg:tags":[
        "therapist",
        "physical"
    ],
    "wof:name":"Genesis Physical Therapy",
    "wof:placetype":"venue"
},
  "geometry": {"coordinates":[-118.74398,34.288356],"type":"Point"}
}