{
  "type": "Feature",
  "properties": {
    "addr:full":"216 S Broadway Santa Ana CA 92701",
    "addr:housenumber":"216",
    "addr:postcode":"92701",
    "addr:street":"S Broadway",
    "iso:country":"US",
    "sg:address":"216 S Broadway",
    "sg:city":"Santa Ana",
    "sg:classifiers":[
        {
            "category":"Organizations",
            "subcategory":"Religious Organization",
            "type":"Services"
        }
    ],
    "sg:phone":"+1 714 547 9200",
    "sg:postcode":"92701",
    "sg:province":"CA",
    "sg:tags":[
        "church"
    ],
    "wof:name":"Iglesia Del Cuerpo De Cristo",
    "wof:placetype":"venue"
},
  "geometry": {"coordinates":[-117.869804,33.74355],"type":"Point"}
}