{
  "type": "Feature",
  "properties": {
    "iso:country":"US",
    "sg:address":"767 E Blithedale Ave",
    "sg:city":"Mill Valley",
    "sg:classifiers":[
        {
            "category":"Banks & Credit Unions",
            "subcategory":"Bank",
            "type":"Services"
        }
    ],
    "sg:phone":"+1 415 388 4101",
    "sg:postcode":"94941",
    "sg:province":"CA",
    "wof:name":"US Bank",
    "wof:placetype":"venue"
},
  "geometry": {"coordinates":[-122.524728,37.901993],"type":"Point"}
}