{
  "type": "Feature",
  "properties": {
    "iso:country":"US",
    "sg:address":"23 22nd St",
    "sg:city":"Hermosa Beach",
    "sg:classifiers":[
        {
            "category":"Restaurant",
            "type":"Food & Drink"
        }
    ],
    "sg:phone":"+1 310 379 0070",
    "sg:postcode":"90254",
    "sg:province":"CA",
    "wof:name":"Martha's Corner",
    "wof:placetype":"venue"
},
  "geometry": {"coordinates":[-118.403581,33.869391],"type":"Point"}
}