{
  "type": "Feature",
  "properties": {
    "iso:country":"US",
    "sg:address":"1120 S Glendora Ave",
    "sg:city":"West Covina",
    "sg:classifiers":[
        {
            "category":"Real Estate",
            "subcategory":"Real Estate Agent",
            "type":"Services"
        }
    ],
    "sg:phone":"+1 626 918 2288",
    "sg:postcode":"91790",
    "sg:province":"CA",
    "wof:name":"World Realty",
    "wof:placetype":"venue"
},
  "geometry": {"coordinates":[-117.938305,34.055462],"type":"Point"}
}