{
  "type": "Feature",
  "properties": {
    "addr:full":"3331 Rancho del Monico Rd Covina CA 91724",
    "addr:housenumber":"3331",
    "addr:postcode":"91724",
    "addr:street":"Rancho Del Monico Rd",
    "iso:country":"US",
    "sg:address":"3331 Rancho del Monico Rd",
    "sg:city":"Covina",
    "sg:classifiers":[
        {
            "category":"Professional",
            "subcategory":"Business Services",
            "type":"Services"
        }
    ],
    "sg:phone":"+1 626 332 7797",
    "sg:postcode":"91724",
    "sg:province":"CA",
    "sg:tags":[
        "outerwear",
        "mfg"
    ],
    "wof:name":"California Joy Inc",
    "wof:placetype":"venue"
},
  "geometry": {"coordinates":[-117.855853,34.078067],"type":"Point"}
}