{
  "type": "Feature",
  "properties": {
    "iso:country":"US",
    "sg:address":"57 Presidio Ave",
    "sg:city":"Corte Madera",
    "sg:classifiers":[
        {
            "category":"Wholesale",
            "subcategory":"Stationery",
            "type":"Manufacturing & Wholesale Goods"
        }
    ],
    "sg:phone":"+1 415 924 0904",
    "sg:postcode":"94925",
    "sg:province":"CA",
    "sg:tags":[
        "map"
    ],
    "wof:name":"City Maps Inc",
    "wof:placetype":"venue"
},
  "geometry": {"coordinates":[-122.5214,37.922405],"type":"Point"}
}