{
  "type": "Feature",
  "properties": {
    "iso:country":"US",
    "sg:address":"418 W 6th St",
    "sg:city":"Los Angeles",
    "sg:classifiers":[
        {
            "category":"Restaurant",
            "type":"Food & Drink"
        }
    ],
    "sg:phone":"+1 213 689 4438",
    "sg:postcode":"90014",
    "sg:province":"CA",
    "sg:website":"www.ardascafe.com",
    "wof:name":"Arda's Cafe",
    "wof:placetype":"venue"
},
  "geometry": {"coordinates":[-118.253799,34.04767],"type":"Point"}
}