{
  "type": "Feature",
  "properties": {
    "addr:full":"1842 Foothill Blvd Oakland CA 94606",
    "addr:housenumber":"1842",
    "addr:postcode":"94606",
    "addr:street":"Foothill Blvd",
    "iso:country":"US",
    "sg:address":"1842 Foothill Blvd",
    "sg:city":"Oakland",
    "sg:classifiers":[
        {
            "category":"Manufacturing",
            "subcategory":"Printing",
            "type":"Manufacturing & Wholesale Goods"
        }
    ],
    "sg:phone":"+1 510 535 2020",
    "sg:postcode":"94606",
    "sg:province":"CA",
    "sg:tags":[
        "commercial"
    ],
    "wof:name":"Red Star Black Rose Printing",
    "wof:placetype":"venue"
},
  "geometry": {"coordinates":[-122.239806,37.788467],"type":"Point"}
}