{
  "type": "Feature",
  "properties": {
    "addr:full":"1940 N Bullis Rd Compton CA 90221",
    "addr:housenumber":"1940",
    "addr:postcode":"90221",
    "addr:street":"N Bullis Rd",
    "iso:country":"US",
    "sg:address":"1940 N Bullis Rd",
    "sg:city":"Compton",
    "sg:classifiers":[
        {
            "category":"Restaurant",
            "type":"Food & Drink"
        }
    ],
    "sg:phone":"+1 310 762 9446",
    "sg:postcode":"90221",
    "sg:province":"CA",
    "wof:name":"Marias Tortas Y Jugos",
    "wof:placetype":"venue"
},
  "geometry": {"coordinates":[-118.206891,33.908673],"type":"Point"}
}