{
  "type": "Feature",
  "properties": {
    "addr:full":"202 Via Villena Encinitas CA 92024",
    "addr:housenumber":"202",
    "addr:postcode":"92024",
    "addr:street":"Via Villena",
    "iso:country":"US",
    "sg:address":"202 Via Villena",
    "sg:city":"Encinitas",
    "sg:classifiers":[
        {
            "category":"Wholesale",
            "subcategory":"Electrical",
            "type":"Manufacturing & Wholesale Goods"
        }
    ],
    "sg:phone":"+1 760 634 2462",
    "sg:postcode":"92024",
    "sg:province":"CA",
    "sg:tags":[
        "equipment"
    ],
    "wof:name":"Prime Source Electronics Inc",
    "wof:placetype":"venue"
},
  "geometry": {"coordinates":[-117.26604399999999,33.049752],"type":"Point"}
}