{
  "type": "Feature",
  "properties": {
    "iso:country":"US",
    "sg:address":"1653 W Washington Blvd",
    "sg:city":"Los Angeles",
    "sg:classifiers":[
        {
            "category":"Health Services",
            "subcategory":"Doctor",
            "type":"Services"
        }
    ],
    "sg:phone":"+1 323 731 7780",
    "sg:postcode":"90007",
    "sg:province":"CA",
    "sg:tags":[
        "physician",
        "surgeon"
    ],
    "wof:name":"Howard K Ragland MD",
    "wof:placetype":"venue"
},
  "geometry": {"coordinates":[-118.292703,34.040075],"type":"Point"}
}