{
  "type": "Feature",
  "properties": {
    "iso:country":"US",
    "sg:address":"3901 E Whitmore Ave",
    "sg:city":"Ceres",
    "sg:classifiers":[
        {
            "category":"Organizations",
            "subcategory":"Religious Organization",
            "type":"Services"
        }
    ],
    "sg:phone":"+1 209 537 3831",
    "sg:postcode":"95307",
    "sg:province":"CA",
    "sg:tags":[
        "church"
    ],
    "wof:name":"Ceres Valley View Church",
    "wof:placetype":"venue"
},
  "geometry": {"coordinates":[-120.923768,37.594858],"type":"Point"}
}