{
  "type": "Feature",
  "properties": {
    "addr:full":"780 E Francis St Ontario CA 91761",
    "addr:housenumber":"780",
    "addr:postcode":"91761",
    "addr:street":"E Francis St",
    "iso:country":"US",
    "sg:address":"780 E Francis St",
    "sg:city":"Ontario",
    "sg:classifiers":[
        {
            "category":"Manufacturing",
            "subcategory":"Chemicals & Compounds",
            "type":"Manufacturing & Wholesale Goods"
        }
    ],
    "sg:phone":"+1 909 930 6700",
    "sg:postcode":"91761",
    "sg:province":"CA",
    "sg:tags":[
        "plastic"
    ],
    "wof:name":"PBY Plastics",
    "wof:placetype":"venue"
},
  "geometry": {"coordinates":[-117.640269,34.041072],"type":"Point"}
}