{
  "type": "Feature",
  "properties": {
    "iso:country":"US",
    "sg:address":"3453 Ingraham St",
    "sg:city":"San Diego",
    "sg:classifiers":[
        {
            "category":"Personal",
            "type":"Services"
        }
    ],
    "sg:phone":"+1 619 920 2976",
    "sg:postcode":"92109",
    "sg:province":"CA",
    "sg:tags":[
        "planning",
        "wedding"
    ],
    "wof:name":"Wedding Elegance",
    "wof:placetype":"venue"
},
  "geometry": {"coordinates":[-117.236689,32.782372],"type":"Point"}
}