{
  "type": "Feature",
  "properties": {
    "addr:full":"1184 Forest Ave Pacific Grove CA 93950",
    "addr:housenumber":"1184",
    "addr:postcode":"93950",
    "addr:street":"Forest Ave",
    "iso:country":"US",
    "sg:address":"1184 Forest Ave",
    "sg:city":"Pacific Grove",
    "sg:classifiers":[
        {
            "category":"Personal",
            "subcategory":"Beauty Salon",
            "type":"Services"
        }
    ],
    "sg:phone":"+1 831 372 8332",
    "sg:postcode":"93950",
    "sg:province":"CA",
    "wof:name":"Adara Salon",
    "wof:placetype":"venue"
},
  "geometry": {"coordinates":[-121.920624,36.60496],"type":"Point"}
}