{
  "type": "Feature",
  "properties": {
    "addr:full":"10330 Pioneer Blvd Santa Fe Springs CA 90670",
    "addr:housenumber":"10330",
    "addr:postcode":"90670",
    "addr:street":"Pioneer Blvd",
    "iso:country":"US",
    "sg:address":"10330 Pioneer Blvd",
    "sg:city":"Santa Fe Springs",
    "sg:classifiers":[
        {
            "category":"Professional",
            "subcategory":"Lawyer & Legal Services",
            "type":"Services"
        }
    ],
    "sg:phone":"+1 562 946 9391",
    "sg:postcode":"90670",
    "sg:province":"CA",
    "wof:name":"Miller Paul H Attorney At Law",
    "wof:placetype":"venue"
},
  "geometry": {"coordinates":[-118.081197,33.942347],"type":"Point"}
}