{
  "type": "Feature",
  "properties": {
    "iso:country":"US",
    "sg:address":"401 N E St",
    "sg:city":"Madera",
    "sg:classifiers":[
        {
            "category":"Autos & Motor Vehicles",
            "subcategory":"Auto Supplies",
            "type":"Retail Goods"
        }
    ],
    "sg:phone":"+1 559 661 1105",
    "sg:postcode":"93638",
    "sg:province":"CA",
    "sg:tags":[
        "tire"
    ],
    "wof:name":"Jerez Tires",
    "wof:placetype":"venue"
},
  "geometry": {"coordinates":[-120.063367,36.965576],"type":"Point"}
}