{
  "type": "Feature",
  "properties": {
    "iso:country":"US",
    "sg:address":"1932 10th Ave",
    "sg:city":"Los Angeles",
    "sg:classifiers":[
        {
            "category":"Social Services",
            "subcategory":"Child Care",
            "type":"Services"
        }
    ],
    "sg:phone":"+1 323 766 7449",
    "sg:postcode":"90018",
    "sg:province":"CA",
    "sg:tags":[
        "kindergarten",
        "academic",
        "school"
    ],
    "wof:name":"L A Montessori",
    "wof:placetype":"venue"
},
  "geometry": {"coordinates":[-118.32737299999999,34.038248],"type":"Point"}
}