{
  "type": "Feature",
  "properties": {
    "addr:full":"1311 Washington Pl Santa Ana CA 92701",
    "addr:housenumber":"1311",
    "addr:postcode":"92701",
    "addr:street":"Washington Pl",
    "iso:country":"US",
    "sg:address":"1311 Washington Pl",
    "sg:city":"Santa Ana",
    "sg:classifiers":[
        {
            "category":"Professional",
            "type":"Services"
        }
    ],
    "sg:phone":"+1 714 558 9155",
    "sg:postcode":"92701",
    "sg:province":"CA",
    "wof:name":"PC Wizards Inc",
    "wof:placetype":"venue"
},
  "geometry": {"coordinates":[-117.851129,33.756764],"type":"Point"}
}