{
  "type": "Feature",
  "properties": {
    "iso:country":"US",
    "sg:address":"3628 Sacramento St",
    "sg:city":"San Francisco",
    "sg:classifiers":[
        {
            "category":"Health Services",
            "subcategory":"Health Practitioner",
            "type":"Services"
        }
    ],
    "sg:phone":"+1 415 346 6636",
    "sg:postcode":"94118",
    "sg:province":"CA",
    "sg:tags":[
        "psychologist"
    ],
    "wof:name":"Paula Sitelman PHD",
    "wof:placetype":"venue"
},
  "geometry": {"coordinates":[-122.453233,37.787477],"type":"Point"}
}