{
  "type": "Feature",
  "properties": {
    "addr:full":"16910 Parthenia St Northridge CA 91343",
    "addr:housenumber":"16910",
    "addr:postcode":"91343",
    "addr:street":"Parthenia St",
    "iso:country":"US",
    "sg:address":"16910 Parthenia St",
    "sg:city":"Northridge",
    "sg:classifiers":[
        {
            "category":"Personal",
            "subcategory":"Barber",
            "type":"Services"
        }
    ],
    "sg:phone":"+1 818 894 9952",
    "sg:postcode":"91343",
    "sg:province":"CA",
    "wof:name":"Shearcuts",
    "wof:placetype":"venue"
},
  "geometry": {"coordinates":[-118.501279,34.228416],"type":"Point"}
}