{
  "type": "Feature",
  "properties": {
    "addr:full":"2946 Adams Ave San Diego CA 92116",
    "addr:housenumber":"2946",
    "addr:postcode":"92116",
    "addr:street":"Adams Ave",
    "iso:country":"US",
    "sg:address":"2946 Adams Ave",
    "sg:city":"San Diego",
    "sg:classifiers":[
        {
            "category":"Home & Garden",
            "subcategory":"Building Materials",
            "type":"Retail Goods"
        }
    ],
    "sg:phone":"+1 619 283 3638",
    "sg:postcode":"92116",
    "sg:province":"CA",
    "wof:name":"Quicksilver Stained GL & Gifts",
    "wof:placetype":"venue"
},
  "geometry": {"coordinates":[-117.130431,32.762962],"type":"Point"}
}