{
  "type": "Feature",
  "properties": {
    "addr:full":"1620 Ventura Blvd Camarillo CA 93010",
    "addr:housenumber":"1620",
    "addr:postcode":"93010",
    "addr:street":"Ventura Blvd",
    "iso:country":"US",
    "sg:address":"1620 Ventura Blvd",
    "sg:city":"Camarillo",
    "sg:classifiers":[
        {
            "category":"Professional",
            "type":"Services"
        }
    ],
    "sg:phone":"+1 805 482 3810",
    "sg:postcode":"93010",
    "sg:province":"CA",
    "sg:tags":[
        "caterer"
    ],
    "wof:name":"Belvedere Family Catering",
    "wof:placetype":"venue"
},
  "geometry": {"coordinates":[-119.048908,34.216915],"type":"Point"}
}