{
  "type": "Feature",
  "properties": {
    "iso:country":"US",
    "sg:address":"8635 W 3rd St",
    "sg:city":"Los Angeles",
    "sg:classifiers":[
        {
            "category":"Health Services",
            "subcategory":"Doctor",
            "type":"Services"
        }
    ],
    "sg:phone":"+1 310 659 4023",
    "sg:postcode":"90048",
    "sg:province":"CA",
    "sg:tags":[
        "physician",
        "surgeon"
    ],
    "wof:name":"Michael H Weiss MD",
    "wof:placetype":"venue"
},
  "geometry": {"coordinates":[-118.381642,34.073578],"type":"Point"}
}