{
  "type": "Feature",
  "properties": {
    "iso:country":"US",
    "sg:address":"826 W Main St",
    "sg:city":"Santa Maria",
    "sg:classifiers":[
        {
            "category":"Retail",
            "subcategory":"Auto Repair",
            "type":"Services"
        }
    ],
    "sg:phone":"+1 805 925 2341",
    "sg:postcode":"93458",
    "sg:province":"CA",
    "sg:tags":[
        "shop",
        "exhaust",
        "parts",
        "muffler",
        "system"
    ],
    "wof:name":"Carl's Muffler Shop",
    "wof:placetype":"venue"
},
  "geometry": {"coordinates":[-120.445882,34.953119],"type":"Point"}
}