{
  "type": "Feature",
  "properties": {
    "addr:full":"1415 Stannage Ave Berkeley CA 94702",
    "addr:housenumber":"1415",
    "addr:postcode":"94702",
    "addr:street":"Stannage Ave",
    "iso:country":"US",
    "sg:address":"1415 Stannage Ave",
    "sg:city":"Berkeley",
    "sg:classifiers":[
        {
            "category":"Professional",
            "type":"Services"
        }
    ],
    "sg:phone":"+1 510 525 4375",
    "sg:postcode":"94702",
    "sg:province":"CA",
    "sg:tags":[
        "arts",
        "artist"
    ],
    "wof:name":"Susan Mc Allister Portrait",
    "wof:placetype":"venue"
},
  "geometry": {"coordinates":[-122.293234,37.878447],"type":"Point"}
}