{
  "type": "Feature",
  "properties": {
    "addr:full":"2626 N California St Stockton CA 95204",
    "addr:housenumber":"2626",
    "addr:postcode":"95204",
    "addr:street":"N California St",
    "iso:country":"US",
    "sg:address":"2626 N California St",
    "sg:city":"Stockton",
    "sg:classifiers":[
        {
            "category":"Health Services",
            "subcategory":"Doctor",
            "type":"Services"
        }
    ],
    "sg:phone":"+1 209 941 8073",
    "sg:postcode":"95204",
    "sg:province":"CA",
    "sg:tags":[
        "medicine",
        "physician",
        "surgeon",
        "internal",
        "surgeons"
    ],
    "wof:name":"Emanuel Orellana Md",
    "wof:placetype":"venue"
},
  "geometry": {"coordinates":[-121.291685,37.976996],"type":"Point"}
}