{
  "type": "Feature",
  "properties": {
    "iso:country":"US",
    "sg:address":"1201 1/2 S Escondido Blvd C",
    "sg:city":"Escondido",
    "sg:classifiers":[
        {
            "category":"Retail",
            "subcategory":"Repair Shop",
            "type":"Services"
        }
    ],
    "sg:phone":"+1 760 480 4761",
    "sg:postcode":"92025",
    "sg:province":"CA",
    "sg:tags":[
        "vinyl"
    ],
    "wof:name":"Jesus Ramirez Upholstery",
    "wof:placetype":"venue"
},
  "geometry": {"coordinates":[-117.07717599999999,33.11039],"type":"Point"}
}