{
  "type": "Feature",
  "properties": {
    "iso:country":"US",
    "sg:address":"1625 San Carlos Ave B",
    "sg:city":"San Carlos",
    "sg:classifiers":[
        {
            "category":"Insurance",
            "subcategory":"Hazard Insurance",
            "type":"Services"
        }
    ],
    "sg:phone":"+1 650 580 6337",
    "sg:postcode":"94070",
    "sg:province":"CA",
    "sg:website":"www.insurancebayarea.com/",
    "wof:name":"Insurance San Francisco",
    "wof:placetype":"venue"
},
  "geometry": {"coordinates":[-122.265064,37.50318],"type":"Point"}
}