{
  "type": "Feature",
  "properties": {
    "iso:country":"US",
    "sg:address":"5114 Lankershim Blvd",
    "sg:city":"North Hollywood",
    "sg:classifiers":[
        {
            "category":"Arts & Performance",
            "subcategory":"Arts Center",
            "type":"Entertainment"
        }
    ],
    "sg:phone":"+1 818 506 5436",
    "sg:postcode":"91601",
    "sg:province":"CA",
    "sg:tags":[
        "performing"
    ],
    "sg:website":"antaeus.org/",
    "wof:name":"The Antaeus Company",
    "wof:placetype":"venue"
},
  "geometry": {"coordinates":[-118.373682,34.163345],"type":"Point"}
}