{
  "type": "Feature",
  "properties": {
    "iso:country":"US",
    "sg:address":"9475 E Ave",
    "sg:city":"Hesperia",
    "sg:classifiers":[
        {
            "category":"Manufacturing",
            "subcategory":"Tools & Machinery",
            "type":"Manufacturing & Wholesale Goods"
        },
        {
            "category":"Wholesale",
            "subcategory":"Machinery & Supplies",
            "type":"Manufacturing & Wholesale Goods"
        }
    ],
    "sg:phone":"+1 760 244 4522",
    "sg:postcode":"92345",
    "sg:province":"CA",
    "sg:tags":[
        "building",
        "equipment",
        "construction",
        "industrial"
    ],
    "wof:name":"Hesperia Equipment Repair",
    "wof:placetype":"venue"
},
  "geometry": {"coordinates":[-117.29170499999999,34.42401],"type":"Point"}
}