{
  "type": "Feature",
  "properties": {
    "addr:full":"6743 Sepulveda Blvd Van Nuys CA 91411",
    "addr:housenumber":"6743",
    "addr:postcode":"91411",
    "addr:street":"Sepulveda Blvd",
    "iso:country":"US",
    "sg:address":"6743 Sepulveda Blvd",
    "sg:city":"Van Nuys",
    "sg:classifiers":[
        {
            "category":"Shopping",
            "subcategory":"Bicycles & Sporting Goods",
            "type":"Retail Goods"
        }
    ],
    "sg:phone":"+1 818 994 1822",
    "sg:postcode":"91411",
    "sg:province":"CA",
    "sg:tags":[
        "tackle",
        "fishing"
    ],
    "wof:name":"Bob Sands Fishing Tackle",
    "wof:placetype":"venue"
},
  "geometry": {"coordinates":[-118.466261,34.193804],"type":"Point"}
}