{
  "type": "Feature",
  "properties": {
    "iso:country":"US",
    "sg:address":"735 State St",
    "sg:city":"Santa Barbara",
    "sg:classifiers":[
        {
            "category":"Professional",
            "subcategory":"Research",
            "type":"Services"
        }
    ],
    "sg:phone":"+1 805 963 8761",
    "sg:postcode":"93101",
    "sg:province":"CA",
    "sg:tags":[
        "development",
        "laboratory"
    ],
    "sg:website":"www.mrcsb.com",
    "wof:name":"Atk Mission Research",
    "wof:placetype":"venue"
},
  "geometry": {"coordinates":[-119.698958,34.419195],"type":"Point"}
}