{
  "type": "Feature",
  "properties": {
    "iso:country":"US",
    "sg:address":"2200 W Orangewood Ave",
    "sg:city":"Orange",
    "sg:classifiers":[
        {
            "category":"Professional",
            "subcategory":"Employment Agencies",
            "type":"Services"
        }
    ],
    "sg:phone":"+1 714 939 1266",
    "sg:postcode":"92868",
    "sg:province":"CA",
    "sg:tags":[
        "opportunity",
        "contractor"
    ],
    "sg:website":"http://www.spherion.com",
    "wof:name":"Spherion",
    "wof:placetype":"venue"
},
  "geometry": {"coordinates":[-117.875559,33.795792],"type":"Point"}
}