{
  "type": "Feature",
  "properties": {
    "iso:country":"US",
    "sg:address":"1239 Sylvan Rd",
    "sg:city":"Monterey",
    "sg:classifiers":[
        {
            "category":"Home & Garden",
            "subcategory":"Home Furnishings",
            "type":"Retail Goods"
        },
        {
            "category":"Real Estate",
            "subcategory":"Architect",
            "type":"Services"
        }
    ],
    "sg:phone":"+1 831 375 4949",
    "sg:postcode":"93940",
    "sg:province":"CA",
    "sg:tags":[
        "planning",
        "design"
    ],
    "wof:name":"Hovick Design",
    "wof:placetype":"venue"
},
  "geometry": {"coordinates":[-121.86799499999999,36.584635],"type":"Point"}
}