{
  "type": "Feature",
  "properties": {
    "iso:country":"US",
    "sg:address":"10661 Ellis Ave",
    "sg:city":"Fountain Valley",
    "sg:classifiers":[
        {
            "category":"Communications",
            "type":"Services"
        }
    ],
    "sg:phone":"+1 714 968 1948",
    "sg:postcode":"92708",
    "sg:province":"CA",
    "sg:tags":[
        "carrier"
    ],
    "wof:name":"Advanced Cable & Comm Inc",
    "wof:placetype":"venue"
},
  "geometry": {"coordinates":[-117.94091400000001,33.694306],"type":"Point"}
}