{
  "type": "Feature",
  "properties": {
    "addr:full":"10776 Scripps Ranch Blvd San Diego CA 92131",
    "addr:housenumber":"10776",
    "addr:postcode":"ranch;92131",
    "addr:street":"Scripps;Blvd",
    "iso:country":"US",
    "sg:address":"10776 Scripps Ranch Blvd",
    "sg:city":"San Diego",
    "sg:classifiers":[
        {
            "category":"Real Estate",
            "subcategory":"Real Estate Operator",
            "type":"Services"
        }
    ],
    "sg:phone":"+1 858 566 9500",
    "sg:postcode":"92131",
    "sg:province":"CA",
    "sg:tags":[
        "apartment"
    ],
    "wof:name":"Monarch Scripps-Ranch Apts",
    "wof:placetype":"venue"
},
  "geometry": {"coordinates":[-117.111197,32.916254],"type":"Point"}
}