{
  "type": "Feature",
  "properties": {
    "iso:country":"US",
    "sg:address":"3033 5th Ave",
    "sg:city":"San Diego",
    "sg:classifiers":[
        {
            "category":"Real Estate",
            "subcategory":"Architect",
            "type":"Services"
        }
    ],
    "sg:phone":"+1 619 725 0980",
    "sg:postcode":"92103",
    "sg:province":"CA",
    "sg:website":"www.kpaa.com",
    "wof:name":"KPA Assoc Inc",
    "wof:placetype":"venue"
},
  "geometry": {"coordinates":[-117.160264,32.737323],"type":"Point"}
}