{
  "type": "Feature",
  "properties": {
    "iso:country":"US",
    "sg:address":"211 River St",
    "sg:city":"Santa Cruz",
    "sg:classifiers":[
        {
            "category":"Travel",
            "subcategory":"Hotels & Motels",
            "type":"Entertainment"
        }
    ],
    "sg:phone":"+1 831 426 2090",
    "sg:postcode":"95060",
    "sg:province":"CA",
    "sg:website":"www.wkellyinsurance.com",
    "wof:name":"William W Kelly & Co",
    "wof:placetype":"venue"
},
  "geometry": {"coordinates":[-122.028361,36.979715],"type":"Point"}
}