{
  "type": "Feature",
  "properties": {
    "iso:country":"US",
    "sg:address":"1618 N Missile Way",
    "sg:city":"Anaheim",
    "sg:classifiers":[
        {
            "category":"Wholesale",
            "subcategory":"Machinery & Supplies",
            "type":"Manufacturing & Wholesale Goods"
        }
    ],
    "sg:phone":"+1 714 525 9990",
    "sg:postcode":"92801",
    "sg:province":"CA",
    "sg:tags":[
        "whole",
        "demolition",
        "equipment"
    ],
    "wof:name":"Tramac Corporation",
    "wof:placetype":"venue"
},
  "geometry": {"coordinates":[-117.917678,33.858026],"type":"Point"}
}