{
  "type": "Feature",
  "properties": {
    "addr:full":"6050 W Jefferson Blvd Los Angeles CA 90016",
    "addr:housenumber":"6050",
    "addr:postcode":"90016",
    "addr:street":"W Jefferson Blvd",
    "iso:country":"US",
    "sg:address":"6050 W Jefferson Blvd",
    "sg:city":"Los Angeles",
    "sg:classifiers":[
        {
            "category":"Shopping",
            "subcategory":"Florist",
            "type":"Retail Goods"
        }
    ],
    "sg:phone":"+1 310 838 8378",
    "sg:postcode":"90016",
    "sg:province":"CA",
    "sg:website":"www.innergardens.com",
    "wof:name":"Inner Gardens",
    "wof:placetype":"venue"
},
  "geometry": {"coordinates":[-118.382661,34.020386],"type":"Point"}
}