{
  "type": "Feature",
  "properties": {
    "iso:country":"US",
    "sg:address":"4234 City Terrace Dr",
    "sg:city":"Los Angeles",
    "sg:classifiers":[
        {
            "category":"Professional",
            "type":"Services"
        }
    ],
    "sg:phone":"+1 323 780 6003",
    "sg:postcode":"90063",
    "sg:province":"CA",
    "wof:name":"El Sabroson",
    "wof:placetype":"venue"
},
  "geometry": {"coordinates":[-118.176048,34.056306],"type":"Point"}
}