{
  "type": "Feature",
  "properties": {
    "iso:country":"US",
    "sg:address":"37349 Niles Blvd",
    "sg:city":"Fremont",
    "sg:classifiers":[
        {
            "category":"Bars & Pubs",
            "type":"Food & Drink"
        },
        {
            "category":"Restaurant",
            "type":"Food & Drink"
        },
        {
            "category":"Bars & Pubs",
            "subcategory":"Lounge",
            "type":"Food & Drink"
        }
    ],
    "sg:phone":"+1 510 792 5522",
    "sg:postcode":"94536",
    "sg:province":"CA",
    "sg:tags":[
        "brew",
        "grill",
        "cocktail"
    ],
    "wof:name":"The Florence Bar",
    "wof:placetype":"venue"
},
  "geometry": {"coordinates":[-121.980476,37.577258],"type":"Point"}
}