{
  "type": "Feature",
  "properties": {
    "iso:country":"US",
    "sg:address":"1360 E Pacheco Blvd",
    "sg:city":"Los Banos",
    "sg:classifiers":[
        {
            "category":"Shopping",
            "subcategory":"Pharmacy",
            "type":"Retail Goods"
        }
    ],
    "sg:phone":"+1 209 826 2600",
    "sg:postcode":"93635",
    "sg:province":"CA",
    "wof:name":"Walgreens",
    "wof:placetype":"venue"
},
  "geometry": {"coordinates":[-120.835342,37.056917],"type":"Point"}
}