{
  "type": "Feature",
  "properties": {
    "addr:full":"4187 Bernardo Ct Chino CA 91710",
    "addr:housenumber":"4187",
    "addr:postcode":"91710",
    "addr:street":"Bernardo Ct",
    "iso:country":"US",
    "sg:address":"4187 Bernardo Ct",
    "sg:city":"Chino",
    "sg:classifiers":[
        {
            "category":"Social Services",
            "type":"Services"
        }
    ],
    "sg:phone":"+1 909 628 9441",
    "sg:postcode":"91710",
    "sg:province":"CA",
    "sg:tags":[
        "program",
        "services-information",
        "referral"
    ],
    "wof:name":"Linda Howe",
    "wof:placetype":"venue"
},
  "geometry": {"coordinates":[-117.713121,34.009847],"type":"Point"}
}