{
  "type": "Feature",
  "properties": {
    "addr:full":"1260 Kensington Dr Merced CA 95340",
    "addr:housenumber":"1260",
    "addr:postcode":"95340",
    "addr:street":"Kensington Dr",
    "iso:country":"US",
    "sg:address":"1260 Kensington Dr",
    "sg:city":"Merced",
    "sg:classifiers":[
        {
            "category":"Home & Garden",
            "subcategory":"Furniture",
            "type":"Retail Goods"
        }
    ],
    "sg:phone":"+1 209 722 0216",
    "sg:postcode":"95340",
    "sg:province":"CA",
    "sg:tags":[
        "set",
        "gift",
        "mfg",
        "bedding",
        "bed",
        "bedroom",
        "baby",
        "clothing"
    ],
    "wof:name":"Forget Me Knot",
    "wof:placetype":"venue"
},
  "geometry": {"coordinates":[-120.456863,37.319279],"type":"Point"}
}