{
  "type": "Feature",
  "properties": {
    "iso:country":"US",
    "sg:address":"8629 Whittier Blvd",
    "sg:city":"Pico Rivera",
    "sg:classifiers":[
        {
            "category":"Retail",
            "subcategory":"Repair Shop",
            "type":"Services"
        }
    ],
    "sg:phone":"+1 562 463 4921",
    "sg:postcode":"90660",
    "sg:province":"CA",
    "sg:tags":[
        "television",
        "radio"
    ],
    "wof:name":"Nash TV",
    "wof:placetype":"venue"
},
  "geometry": {"coordinates":[-118.087399,34.00289],"type":"Point"}
}