{
  "type": "Feature",
  "properties": {
    "iso:country":"US",
    "sg:address":"23480 Park Sorrento",
    "sg:city":"Calabasas",
    "sg:classifiers":[
        {
            "category":"Professional",
            "subcategory":"Accounting & Tax Preparation",
            "type":"Services"
        }
    ],
    "sg:phone":"+1 818 591 1300",
    "sg:postcode":"91302",
    "sg:province":"CA",
    "sg:tags":[
        "firm"
    ],
    "wof:name":"Feddersen & Company LLP",
    "wof:placetype":"venue"
},
  "geometry": {"coordinates":[-118.639342,34.155972],"type":"Point"}
}