{
  "type": "Feature",
  "properties": {
    "addr:full":"18440 Hatteras St Tarzana CA 91356",
    "addr:housenumber":"18440",
    "addr:postcode":"91356",
    "addr:street":"Hatteras St",
    "iso:country":"US",
    "sg:address":"18440 Hatteras St",
    "sg:city":"Tarzana",
    "sg:classifiers":[
        {
            "category":"Insurance",
            "subcategory":"Insurance Agent",
            "type":"Services"
        }
    ],
    "sg:phone":"+1 818 987 5000",
    "sg:postcode":"91356",
    "sg:province":"CA",
    "wof:name":"Health & Life Insurance",
    "wof:placetype":"venue"
},
  "geometry": {"coordinates":[-118.532402,34.177375],"type":"Point"}
}