{
  "type": "Feature",
  "properties": {
    "iso:country":"US",
    "sg:address":"915 25th St",
    "sg:city":"Sacramento",
    "sg:classifiers":[
        {
            "category":"Shopping",
            "subcategory":"Musical Instruments",
            "type":"Retail Goods"
        }
    ],
    "sg:phone":"+1 916 505 9225",
    "sg:postcode":"95816",
    "sg:province":"CA",
    "sg:tags":[
        "music",
        "store"
    ],
    "wof:name":"Five & Dime Records",
    "wof:placetype":"venue"
},
  "geometry": {"coordinates":[-121.47284500000001,38.575862],"type":"Point"}
}