{
  "type": "Feature",
  "properties": {
    "addr:full":"1387 Garden Hwy Sacramento CA 95833",
    "addr:housenumber":"1387",
    "addr:postcode":"95833",
    "addr:street":"Garden Hwy",
    "iso:country":"US",
    "sg:address":"1387 Garden Hwy",
    "sg:city":"Sacramento",
    "sg:classifiers":[
        {
            "category":"Professional",
            "subcategory":"Lawyer & Legal Services",
            "type":"Services"
        }
    ],
    "sg:phone":"+1 916 920 2287",
    "sg:postcode":"95833",
    "sg:province":"CA",
    "wof:name":"Lea Robt & Associates",
    "wof:placetype":"venue"
},
  "geometry": {"coordinates":[-121.51675,38.604192],"type":"Point"}
}