{
  "type": "Feature",
  "properties": {
    "iso:country":"US",
    "sg:address":"1506 W Industrial Park St",
    "sg:city":"Covina",
    "sg:classifiers":[
        {
            "category":"Manufacturing",
            "subcategory":"Tools & Machinery",
            "type":"Manufacturing & Wholesale Goods"
        }
    ],
    "sg:phone":"+1 626 966 0377",
    "sg:postcode":"91722",
    "sg:province":"CA",
    "sg:tags":[
        "machine",
        "shop"
    ],
    "wof:name":"J & L Precision",
    "wof:placetype":"venue"
},
  "geometry": {"coordinates":[-117.921969,34.091205],"type":"Point"}
}