{
  "type": "Feature",
  "properties": {
    "iso:country":"US",
    "sg:address":"22501 Foothill Blvd",
    "sg:city":"Hayward",
    "sg:classifiers":[
        {
            "category":"Shopping",
            "subcategory":"Pharmacy",
            "type":"Retail Goods"
        }
    ],
    "sg:phone":"+1 510 881 9470",
    "sg:postcode":"94541",
    "sg:province":"CA",
    "sg:tags":[
        "drugstore"
    ],
    "sg:website":"www.longs.com",
    "wof:name":"Longs Drugs",
    "wof:placetype":"venue"
},
  "geometry": {"coordinates":[-122.081998,37.675183],"type":"Point"}
}