{
  "type": "Feature",
  "properties": {
    "addr:full":"1290 Jefferson St Napa CA 94559",
    "addr:housenumber":"1290",
    "addr:postcode":"94559",
    "addr:street":"Jefferson St",
    "iso:country":"US",
    "sg:address":"1290 Jefferson St",
    "sg:city":"Napa",
    "sg:classifiers":[
        {
            "category":"Real Estate",
            "subcategory":"Real Estate Agent",
            "type":"Services"
        }
    ],
    "sg:phone":"+1 707 255 8711",
    "sg:postcode":"94559",
    "sg:province":"CA",
    "wof:name":"Alpha Realty",
    "wof:placetype":"venue"
},
  "geometry": {"coordinates":[-122.29298300000001,38.299107],"type":"Point"}
}