{
  "type": "Feature",
  "properties": {
    "addr:full":"3901 Mount Vernon Ave Bakersfield CA 93306",
    "addr:housenumber":"3901",
    "addr:postcode":"93306",
    "addr:street":"Mount Vernon Ave",
    "iso:country":"US",
    "sg:address":"3901 Mount Vernon Ave",
    "sg:city":"Bakersfield",
    "sg:classifiers":[
        {
            "category":"Banks & Credit Unions",
            "subcategory":"Bank",
            "type":"Services"
        }
    ],
    "sg:phone":"+1 661 833 7900",
    "sg:postcode":"93306",
    "sg:province":"CA",
    "wof:name":"KERN Schools Federal Cu",
    "wof:placetype":"venue"
},
  "geometry": {"coordinates":[-118.967494,35.407745],"type":"Point"}
}