{
  "type": "Feature",
  "properties": {
    "iso:country":"US",
    "sg:address":"12808 Snow Rd",
    "sg:city":"Bakersfield",
    "sg:classifiers":[
        {
            "category":"Building & Trades",
            "subcategory":"Construction",
            "type":"Services"
        }
    ],
    "sg:phone":"+1 661 391 4545",
    "sg:postcode":"93314",
    "sg:province":"CA",
    "sg:tags":[
        "excavation",
        "operator",
        "contractor",
        "local",
        "trucking"
    ],
    "wof:name":"Golden Construction & Excav",
    "wof:placetype":"venue"
},
  "geometry": {"coordinates":[-119.13946199999999,35.427057],"type":"Point"}
}