{
  "type": "Feature",
  "properties": {
    "iso:country":"US",
    "sg:address":"9272 Borden Ave",
    "sg:city":"Sun Valley",
    "sg:classifiers":[
        {
            "category":"Manufacturing",
            "subcategory":"Motor Vehicles & Parts",
            "type":"Manufacturing & Wholesale Goods"
        }
    ],
    "sg:phone":"+1 818 504 2388",
    "sg:postcode":"91352",
    "sg:province":"CA",
    "sg:tags":[
        "automobile",
        "supply"
    ],
    "sg:website":"www.wingmaster.com",
    "wof:name":"Wingmaster",
    "wof:placetype":"venue"
},
  "geometry": {"coordinates":[-118.369219,34.237821],"type":"Point"}
}