{
  "type": "Feature",
  "properties": {
    "iso:country":"US",
    "sg:address":"15604 Ruthelen Ave",
    "sg:city":"Gardena",
    "sg:classifiers":[
        {
            "category":"Building & Trades",
            "subcategory":"Construction",
            "type":"Services"
        }
    ],
    "sg:phone":"+1 310 515 0752",
    "sg:postcode":"90249",
    "sg:province":"CA",
    "sg:tags":[
        "contractor"
    ],
    "wof:name":"Bills Fencing",
    "wof:placetype":"venue"
},
  "geometry": {"coordinates":[-118.312427,33.890761],"type":"Point"}
}