{
  "type": "Feature",
  "properties": {
    "addr:full":"Wilshire International Food Court 3500 Wilshire Blvd Los Angeles CA 90010",
    "addr:housenumber":"3500",
    "addr:postcode":"90010",
    "addr:street":"Wilshire Blvd",
    "iso:country":"US",
    "sg:address":"Wilshire International Food Court 3500 Wilshire Blvd",
    "sg:city":"Los Angeles",
    "sg:classifiers":[
        {
            "category":"Restaurant",
            "type":"Food & Drink"
        }
    ],
    "sg:phone":"+1 213 380 4510",
    "sg:postcode":"90010",
    "sg:province":"CA",
    "sg:tags":[
        "middle",
        "mediterranean",
        "eastern"
    ],
    "wof:name":"Sizzlin Kabob",
    "wof:placetype":"venue"
},
  "geometry": {"coordinates":[-118.295884,34.061672],"type":"Point"}
}