{
  "type": "Feature",
  "properties": {
    "addr:full":"1831 Howell Mountain Rd St Helena CA 94574",
    "addr:housenumber":"1831",
    "addr:postcode":"94574",
    "addr:street":"Howell Mountain Rd",
    "iso:country":"US",
    "sg:address":"1831 Howell Mountain Rd",
    "sg:city":"St Helena",
    "sg:classifiers":[
        {
            "category":"Farming",
            "subcategory":"Vineyard",
            "type":"Manufacturing & Wholesale Goods"
        },
        {
            "category":"Farming",
            "subcategory":"Farm & Veterinary Services",
            "type":"Manufacturing & Wholesale Goods"
        }
    ],
    "sg:phone":"+1 707 963 7050",
    "sg:postcode":"94574",
    "sg:province":"CA",
    "sg:tags":[
        "management"
    ],
    "wof:name":"Mitchell Vineyard Management",
    "wof:placetype":"venue"
},
  "geometry": {"coordinates":[-122.449517,38.513201],"type":"Point"}
}