{
  "type": "Feature",
  "properties": {
    "addr:full":"15410 Stafford St City Of Industry CA 91744",
    "addr:housenumber":"15410",
    "addr:postcode":"91744",
    "addr:street":"Stafford St",
    "iso:country":"US",
    "sg:address":"15410 Stafford St",
    "sg:city":"City Of Industry",
    "sg:classifiers":[
        {
            "category":"Professional",
            "subcategory":"Business Services",
            "type":"Services"
        }
    ],
    "sg:phone":"+1 626 961 9988",
    "sg:postcode":"91744",
    "sg:province":"CA",
    "sg:tags":[
        "slitting",
        "cutting"
    ],
    "wof:name":"Chavez Cutting Svc",
    "wof:placetype":"venue"
},
  "geometry": {"coordinates":[-117.962531,34.027562],"type":"Point"}
}