{
  "type": "Feature",
  "properties": {
    "iso:country":"US",
    "sg:address":"1383 E Napa St",
    "sg:city":"Sonoma",
    "sg:classifiers":[
        {
            "category":"Freight",
            "type":"Transportation"
        }
    ],
    "sg:phone":"+1 707 938 5296",
    "sg:postcode":"95476",
    "sg:province":"CA",
    "sg:tags":[
        "trucking"
    ],
    "wof:name":"Ford Trucking",
    "wof:placetype":"venue"
},
  "geometry": {"coordinates":[-122.431836,38.28862],"type":"Point"}
}