{
  "type": "Feature",
  "properties": {
    "iso:country":"US",
    "sg:address":"880 Victory Dr",
    "sg:city":"Hollister",
    "sg:classifiers":[
        {
            "category":"Professional",
            "subcategory":"Business Services",
            "type":"Services"
        }
    ],
    "sg:phone":"+1 831 637 2194",
    "sg:postcode":"95023",
    "sg:province":"CA",
    "wof:name":"World Insptn Netwrk Monterey",
    "wof:placetype":"venue"
},
  "geometry": {"coordinates":[-121.386812,36.83623],"type":"Point"}
}