{
  "type": "Feature",
  "properties": {
    "iso:country":"US",
    "sg:address":"528 Colorado Ave",
    "sg:city":"Santa Monica",
    "sg:classifiers":[
        {
            "category":"Professional",
            "subcategory":"Lawyer & Legal Services",
            "type":"Services"
        }
    ],
    "sg:phone":"+1 310 393 1198",
    "sg:postcode":"90401",
    "sg:province":"CA",
    "sg:tags":[
        "attorney"
    ],
    "wof:name":"Kenneth Kahn",
    "wof:placetype":"venue"
},
  "geometry": {"coordinates":[-118.490787,34.014628],"type":"Point"}
}