{
  "type": "Feature",
  "properties": {
    "addr:full":"2321 N Pacific Ave Stockton CA 95204",
    "addr:housenumber":"2321",
    "addr:postcode":"95204",
    "addr:street":"N Pacific Ave",
    "iso:country":"US",
    "sg:address":"2321 N Pacific Ave",
    "sg:city":"Stockton",
    "sg:classifiers":[
        {
            "category":"Wholesale",
            "subcategory":"Machinery & Supplies",
            "type":"Manufacturing & Wholesale Goods"
        }
    ],
    "sg:phone":"+1 209 466 3210",
    "sg:postcode":"95204",
    "sg:province":"CA",
    "sg:tags":[
        "equipment",
        "barber"
    ],
    "wof:name":"Henry's Miracle Mile Styling",
    "wof:placetype":"venue"
},
  "geometry": {"coordinates":[-121.301424,37.972786],"type":"Point"}
}