{
  "type": "Feature",
  "properties": {
    "iso:country":"US",
    "sg:address":"16225 Austin Rd",
    "sg:city":"Manteca",
    "sg:classifiers":[
        {
            "category":"Farming",
            "subcategory":"Crops",
            "type":"Manufacturing & Wholesale Goods"
        }
    ],
    "sg:phone":"+1 209 823 1833",
    "sg:postcode":"95336",
    "sg:province":"CA",
    "sg:tags":[
        "grove",
        "nut",
        "tree"
    ],
    "wof:name":"Ed Munoz",
    "wof:placetype":"venue"
},
  "geometry": {"coordinates":[-121.180702,37.816635],"type":"Point"}
}