{
  "type": "Feature",
  "properties": {
    "iso:country":"US",
    "sg:address":"66 E Herndon Ave",
    "sg:city":"Fresno",
    "sg:classifiers":[
        {
            "category":"Restaurant",
            "type":"Food & Drink"
        }
    ],
    "sg:phone":"+1 559 446 0607",
    "sg:postcode":"93720",
    "sg:province":"CA",
    "wof:name":"Toom Thai Cuisine",
    "wof:placetype":"venue"
},
  "geometry": {"coordinates":[-119.789249,36.837385],"type":"Point"}
}