{
  "type": "Feature",
  "properties": {
    "addr:full":"1000 Pine Ave Redlands CA 92373",
    "addr:housenumber":"1000",
    "addr:postcode":"92373",
    "addr:street":"Pine Ave",
    "iso:country":"US",
    "sg:address":"1000 Pine Ave",
    "sg:city":"Redlands",
    "sg:classifiers":[
        {
            "category":"Professional",
            "type":"Services"
        }
    ],
    "sg:phone":"+1 909 307 9789",
    "sg:postcode":"92373",
    "sg:province":"CA",
    "wof:name":"Vr Groups LLC",
    "wof:placetype":"venue"
},
  "geometry": {"coordinates":[-117.196872,34.051984],"type":"Point"}
}