{
  "type": "Feature",
  "properties": {
    "addr:full":"22647 Ventura Blvd., #115 Woodland Hills CA 91364",
    "addr:housenumber":"22647",
    "addr:postcode":"91364",
    "addr:street":"Ventura Blvd. # 115",
    "iso:country":"US",
    "sg:address":"22647 Ventura Blvd., #115",
    "sg:city":"Woodland Hills",
    "sg:classifiers":[
        {
            "category":"Personal",
            "type":"Services"
        }
    ],
    "sg:phone":"+1 818 709 4202",
    "sg:postcode":"91364",
    "sg:province":"CA",
    "sg:tags":[
        "mover"
    ],
    "sg:website":"www.northamericanmoving.net",
    "wof:name":"North American Movers, Inc.",
    "wof:placetype":"venue"
},
  "geometry": {"coordinates":[-118.62009,34.167063],"type":"Point"}
}