{
  "type": "Feature",
  "properties": {
    "addr:full":"3240 Broad St San Luis Obispo CA 93401",
    "addr:housenumber":"3240",
    "addr:postcode":"93401",
    "addr:street":"Broad St",
    "iso:country":"US",
    "sg:address":"3240 Broad St",
    "sg:city":"San Luis Obispo",
    "sg:classifiers":[
        {
            "category":"Restaurant",
            "type":"Food & Drink"
        }
    ],
    "sg:menulink":"http://www.allmenus.com/ca/san-luis-obispo/150207-subway/menu/",
    "sg:phone":"+1 805 788 0558",
    "sg:postcode":"93401",
    "sg:province":"CA",
    "sg:tags":[
        "american",
        "sandwich"
    ],
    "wof:name":"Subway",
    "wof:placetype":"venue"
},
  "geometry": {"coordinates":[-120.647969,35.258276],"type":"Point"}
}