{
  "type": "Feature",
  "properties": {
    "iso:country":"US",
    "sg:address":"3765 Solano Ave",
    "sg:city":"Napa",
    "sg:classifiers":[
        {
            "category":"Organizations",
            "subcategory":"Religious Organization",
            "type":"Services"
        }
    ],
    "sg:phone":"+1 707 255 4033",
    "sg:postcode":"94558",
    "sg:province":"CA",
    "sg:tags":[
        "church"
    ],
    "sg:website":"www.gracenapa.org",
    "wof:name":"Grace Baptist Church Of Napa",
    "wof:placetype":"venue"
},
  "geometry": {"coordinates":[-122.310242,38.320997],"type":"Point"}
}