{
  "type": "Feature",
  "properties": {
    "iso:country":"US",
    "sg:address":"657 S Cochran Ave",
    "sg:city":"Los Angeles",
    "sg:classifiers":[
        {
            "category":"Professional",
            "subcategory":"Computer Services",
            "type":"Services"
        }
    ],
    "sg:phone":"+1 310 910 1190",
    "sg:postcode":"90036",
    "sg:province":"CA",
    "sg:tags":[
        "repair"
    ],
    "sg:website":"www.sebecomputercare.com/",
    "wof:name":"Sebe Expert Computer Care",
    "wof:placetype":"venue"
},
  "geometry": {"coordinates":[-118.34752899999999,34.063249],"type":"Point"}
}