{
  "type": "Feature",
  "properties": {
    "addr:full":"14876 Raymer St Van Nuys CA 91405",
    "addr:housenumber":"14876",
    "addr:postcode":"91405",
    "addr:street":"Raymer St",
    "iso:country":"US",
    "sg:address":"14876 Raymer St",
    "sg:city":"Van Nuys",
    "sg:classifiers":[
        {
            "category":"Wholesale",
            "subcategory":"Durable Goods & Equipment",
            "type":"Manufacturing & Wholesale Goods"
        }
    ],
    "sg:phone":"+1 818 781 4141",
    "sg:postcode":"91405",
    "sg:province":"CA",
    "sg:tags":[
        "architect",
        "supply"
    ],
    "sg:website":"www.apfi.com",
    "wof:name":"Architectural Products",
    "wof:placetype":"venue"
},
  "geometry": {"coordinates":[-118.457982,34.213211],"type":"Point"}
}