{
  "type": "Feature",
  "properties": {
    "iso:country":"US",
    "sg:address":"17050 Davis Rd",
    "sg:city":"Lakeview",
    "sg:classifiers":[
        {
            "category":"Recreation",
            "type":"Entertainment"
        }
    ],
    "sg:phone":"+1 951 928 0580",
    "sg:postcode":"92567",
    "sg:province":"CA",
    "sg:tags":[
        "parks"
    ],
    "wof:name":"San Jacinto Wildlife Area",
    "wof:placetype":"venue"
},
  "geometry": {"coordinates":[-117.12203100000001,33.871113],"type":"Point"}
}