{
  "type": "Feature",
  "properties": {
    "iso:country":"US",
    "sg:address":"41 Cll Maravilla",
    "sg:city":"San Clemente",
    "sg:classifiers":[
        {
            "category":"Professional",
            "subcategory":"Management & Consulting",
            "type":"Services"
        }
    ],
    "sg:phone":"+1 949 498 9824",
    "sg:postcode":"92673",
    "sg:province":"CA",
    "sg:tags":[
        "consultant",
        "training"
    ],
    "wof:name":"Alert",
    "wof:placetype":"venue"
},
  "geometry": {"coordinates":[-117.611281,33.456168],"type":"Point"}
}