{
  "type": "Feature",
  "properties": {
    "addr:full":"300 W Grand Ave Escondido CA 92025",
    "addr:housenumber":"300",
    "addr:postcode":"92025",
    "addr:street":"W Grand Ave",
    "iso:country":"US",
    "sg:address":"300 W Grand Ave",
    "sg:city":"Escondido",
    "sg:classifiers":[
        {
            "category":"Travel",
            "subcategory":"Hotels & Motels",
            "type":"Entertainment"
        }
    ],
    "sg:phone":"+1 760 745 8723",
    "sg:postcode":"92025",
    "sg:province":"CA",
    "wof:name":"Palecek Skaja & Broyles",
    "wof:placetype":"venue"
},
  "geometry": {"coordinates":[-117.085531,33.119624],"type":"Point"}
}