{
  "type": "Feature",
  "properties": {
    "iso:country":"US",
    "sg:address":"2251 Alden Ave",
    "sg:city":"Redding",
    "sg:classifiers":[
        {
            "category":"Manufacturing",
            "subcategory":"Lumber",
            "type":"Manufacturing & Wholesale Goods"
        }
    ],
    "sg:phone":"+1 530 222 1163",
    "sg:postcode":"96002",
    "sg:province":"CA",
    "sg:tags":[
        "logging"
    ],
    "wof:name":"Greg Caldwell Logging",
    "wof:placetype":"venue"
},
  "geometry": {"coordinates":[-122.329638,40.560768],"type":"Point"}
}