{
  "type": "Feature",
  "properties": {
    "addr:full":"4515 Littlejohn St Baldwin Park CA 91706",
    "addr:housenumber":"4515",
    "addr:postcode":"91706",
    "addr:street":"Littlejohn St",
    "iso:country":"US",
    "sg:address":"4515 Littlejohn St",
    "sg:city":"Baldwin Park",
    "sg:classifiers":[
        {
            "category":"Organizations",
            "subcategory":"Religious Organization",
            "type":"Services"
        }
    ],
    "sg:phone":"+1 626 337 0069",
    "sg:postcode":"91706",
    "sg:province":"CA",
    "wof:name":"Proper Enlightment Meditation",
    "wof:placetype":"venue"
},
  "geometry": {"coordinates":[-117.983756,34.093424],"type":"Point"}
}