{
  "type": "Feature",
  "properties": {
    "addr:full":"31 Kingsburry Ct Chico CA 95926",
    "addr:housenumber":"31",
    "addr:postcode":"95926",
    "addr:street":"Kingsburry Ct",
    "iso:country":"US",
    "sg:address":"31 Kingsburry Ct",
    "sg:city":"Chico",
    "sg:classifiers":[
        {
            "category":"Professional",
            "subcategory":"Management & Consulting",
            "type":"Services"
        }
    ],
    "sg:phone":"+1 530 345 5521",
    "sg:postcode":"95926",
    "sg:province":"CA",
    "sg:tags":[
        "retail",
        "direct",
        "sales"
    ],
    "wof:name":"Miss Vics Lics",
    "wof:placetype":"venue"
},
  "geometry": {"coordinates":[-121.87145599999999,39.730064],"type":"Point"}
}