{
  "type": "Feature",
  "properties": {
    "addr:full":"1630 E Herndon Ave Fresno CA 93720",
    "addr:housenumber":"1630",
    "addr:postcode":"93720",
    "addr:street":"E Herndon Ave",
    "iso:country":"US",
    "sg:address":"1630 E Herndon Ave",
    "sg:city":"Fresno",
    "sg:classifiers":[
        {
            "category":"Health Services",
            "subcategory":"Doctor",
            "type":"Services"
        }
    ],
    "sg:phone":"+1 559 449 1622",
    "sg:postcode":"93720",
    "sg:province":"CA",
    "sg:tags":[
        "physician",
        "family",
        "practice",
        "surgeons",
        "medicine",
        "surgeon"
    ],
    "wof:name":"Watson Timothy C",
    "wof:placetype":"venue"
},
  "geometry": {"coordinates":[-119.758391,36.837528],"type":"Point"}
}