{
  "type": "Feature",
  "properties": {
    "addr:full":"866 4th St San Rafael CA 94901",
    "addr:housenumber":"866",
    "addr:postcode":"94901",
    "addr:street":"4Th St",
    "iso:country":"US",
    "sg:address":"866 4th St",
    "sg:city":"San Rafael",
    "sg:classifiers":[
        {
            "category":"Shopping",
            "type":"Retail Goods"
        }
    ],
    "sg:phone":"+1 415 485 1339",
    "sg:postcode":"94901",
    "sg:province":"CA",
    "sg:tags":[
        "merchandise"
    ],
    "wof:name":"Marin Cellular",
    "wof:placetype":"venue"
},
  "geometry": {"coordinates":[-122.525723,37.972959],"type":"Point"}
}