{
  "type": "Feature",
  "properties": {
    "iso:country":"US",
    "sg:address":"7440 Downing Ave",
    "sg:city":"Bakersfield",
    "sg:classifiers":[
        {
            "category":"Manufacturing",
            "subcategory":"Tools & Machinery",
            "type":"Manufacturing & Wholesale Goods"
        }
    ],
    "sg:phone":"+1 661 589 5214",
    "sg:postcode":"93308",
    "sg:province":"CA",
    "sg:tags":[
        "field",
        "oil",
        "equipment"
    ],
    "wof:name":"R & M Energy Systems",
    "wof:placetype":"venue"
},
  "geometry": {"coordinates":[-119.085661,35.390633],"type":"Point"}
}