{
  "type": "Feature",
  "properties": {
    "addr:full":"5328 Newcastle Ave Encino CA 91316",
    "addr:housenumber":"5328",
    "addr:postcode":"91316",
    "addr:street":"Newcastle Ave",
    "iso:country":"US",
    "sg:address":"5328 Newcastle Ave",
    "sg:city":"Encino",
    "sg:classifiers":[
        {
            "category":"Building & Trades",
            "subcategory":"Cleaning & Sanitation",
            "type":"Services"
        }
    ],
    "sg:phone":"+1 818 295 0206",
    "sg:postcode":"91316",
    "sg:province":"CA",
    "sg:tags":[
        "janitor"
    ],
    "wof:name":"Competition Clean & Mntnc",
    "wof:placetype":"venue"
},
  "geometry": {"coordinates":[-118.52428399999999,34.169378],"type":"Point"}
}