{
  "type": "Feature",
  "properties": {
    "iso:country":"US",
    "sg:address":"2837 Bechelli Ln",
    "sg:city":"Redding",
    "sg:classifiers":[
        {
            "category":"Real Estate",
            "subcategory":"Real Estate Agent",
            "type":"Services"
        }
    ],
    "sg:phone":"+1 530 221 0111",
    "sg:postcode":"96002",
    "sg:province":"CA",
    "sg:website":"www.cbshasta.com",
    "wof:name":"First Shasta Realty",
    "wof:placetype":"venue"
},
  "geometry": {"coordinates":[-122.362472,40.56397],"type":"Point"}
}