{
  "type": "Feature",
  "properties": {
    "iso:country":"US",
    "sg:address":"9824 National Blvd",
    "sg:city":"Los Angeles",
    "sg:classifiers":[
        {
            "category":"Restaurant",
            "type":"Food & Drink"
        }
    ],
    "sg:phone":"+1 310 842 3977",
    "sg:postcode":"90034",
    "sg:province":"CA",
    "sg:tags":[
        "sushi",
        "bar"
    ],
    "wof:name":"Sushi Zo",
    "wof:placetype":"venue"
},
  "geometry": {"coordinates":[-118.400002,34.0313],"type":"Point"}
}