{
  "type": "Feature",
  "properties": {
    "addr:full":"16775 Bernardo Center Dr San Diego CA 92128",
    "addr:housenumber":"16775",
    "addr:postcode":"92128",
    "addr:street":"Bernardo Center Dr",
    "iso:country":"US",
    "sg:address":"16775 Bernardo Center Dr",
    "sg:city":"San Diego",
    "sg:classifiers":[
        {
            "category":"Home & Garden",
            "subcategory":"Carpets & Floor Coverings",
            "type":"Retail Goods"
        }
    ],
    "sg:phone":"+1 858 487 2323",
    "sg:postcode":"92128",
    "sg:province":"CA",
    "sg:tags":[
        "material"
    ],
    "wof:name":"Bernardo Flooring & Design",
    "wof:placetype":"venue"
},
  "geometry": {"coordinates":[-117.07589299999999,33.017072],"type":"Point"}
}