{
  "type": "Feature",
  "properties": {
    "addr:full":"22731 Aspan St Lake Forest CA 92630",
    "addr:housenumber":"22731",
    "addr:postcode":"92630",
    "addr:street":"Aspan St",
    "iso:country":"US",
    "sg:address":"22731 Aspan St",
    "sg:city":"Lake Forest",
    "sg:classifiers":[
        {
            "category":"Shopping",
            "subcategory":"Clothing, Apparel, & Fashions",
            "type":"Retail Goods"
        }
    ],
    "sg:phone":"+1 949 770 2291",
    "sg:postcode":"92630",
    "sg:province":"CA",
    "sg:tags":[
        "riding",
        "equipment"
    ],
    "wof:name":"El Toro Tack & Feed",
    "wof:placetype":"venue"
},
  "geometry": {"coordinates":[-117.71468,33.631419],"type":"Point"}
}