{
  "type": "Feature",
  "properties": {
    "iso:country":"US",
    "sg:address":"885 Commerce St",
    "sg:city":"Redding",
    "sg:classifiers":[
        {
            "category":"Wholesale",
            "subcategory":"Auto Parts",
            "type":"Manufacturing & Wholesale Goods"
        }
    ],
    "sg:phone":"+1 530 221 9250",
    "sg:postcode":"96002",
    "sg:province":"CA",
    "sg:tags":[
        "body",
        "automobile",
        "shop"
    ],
    "wof:name":"Redding Auto Finishes",
    "wof:placetype":"venue"
},
  "geometry": {"coordinates":[-122.357046,40.572919],"type":"Point"}
}