{
  "type": "Feature",
  "properties": {
    "addr:full":"4500 Ocean Blvd San Diego CA 92109",
    "addr:housenumber":"4500",
    "addr:postcode":"92109",
    "addr:street":"Ocean Blvd",
    "iso:country":"US",
    "sg:address":"4500 Ocean Blvd",
    "sg:city":"San Diego",
    "sg:classifiers":[
        {
            "category":"Home & Garden",
            "subcategory":"Garden Supply",
            "type":"Retail Goods"
        }
    ],
    "sg:phone":"+1 858 490 8990",
    "sg:postcode":"92109",
    "sg:province":"CA",
    "sg:website":"www.swingsandthingssd.com/",
    "wof:name":"Swings N Things",
    "wof:placetype":"venue"
},
  "geometry": {"coordinates":[-117.25701100000001,32.796191],"type":"Point"}
}