{
  "type": "Feature",
  "properties": {
    "addr:full":"201 Spear, San Francisco, CA, USA",
    "addr:housenumber":201,
    "addr:street":"Spear Street",
    "name:eng_x_preferred":[
        "Mapzen"
    ],
    "name:eng_x_variant":[
        "Mapzen West"
    ],
    "wof:name":"Mapzen",
    "wof:placetype":"venue"
},
  "geometry": {"coordinates":[-122.391977,37.79124],"type":"Point"}
}