{
  "type": "Feature",
  "properties": {
    "addr:full":"355 Rosemary Ln Encinitas CA 92024",
    "addr:housenumber":"355",
    "addr:postcode":"92024",
    "addr:street":"Rosemary Ln",
    "iso:country":"US",
    "sg:address":"355 Rosemary Ln",
    "sg:city":"Encinitas",
    "sg:classifiers":[
        {
            "category":"Banks & Credit Unions",
            "subcategory":"Financial Services",
            "type":"Services"
        }
    ],
    "sg:phone":"+1 760 753 4496",
    "sg:postcode":"92024",
    "sg:province":"CA",
    "sg:tags":[
        "trust",
        "management"
    ],
    "wof:name":"Bumann Family Trust",
    "wof:placetype":"venue"
},
  "geometry": {"coordinates":[-117.232974,33.042548],"type":"Point"}
}