{
  "type": "Feature",
  "properties": {
    "iso:country":"US",
    "sg:address":"1031 W Manchester Ave",
    "sg:city":"Los Angeles",
    "sg:classifiers":[
        {
            "category":"Freight",
            "type":"Transportation"
        }
    ],
    "sg:phone":"+1 310 337 0087",
    "sg:postcode":"90044",
    "sg:province":"CA",
    "sg:tags":[
        "operator",
        "trucking",
        "local",
        "courier",
        "air"
    ],
    "wof:name":"Pacific International Aircargo",
    "wof:placetype":"venue"
},
  "geometry": {"coordinates":[-118.293989,33.960021],"type":"Point"}
}