{
  "type": "Feature",
  "properties": {
    "addr:full":"1710 Griffith Ave Los Angeles CA 90021",
    "addr:housenumber":"1710",
    "addr:postcode":"90021",
    "addr:street":"Griffith Ave",
    "iso:country":"US",
    "sg:address":"1710 Griffith Ave",
    "sg:city":"Los Angeles",
    "sg:classifiers":[
        {
            "category":"Manufacturing",
            "subcategory":"Printing",
            "type":"Manufacturing & Wholesale Goods"
        }
    ],
    "sg:phone":"+1 213 748 0303",
    "sg:postcode":"90021",
    "sg:province":"CA",
    "sg:tags":[
        "screen"
    ],
    "wof:name":"Good Choi's LLC",
    "wof:placetype":"venue"
},
  "geometry": {"coordinates":[-118.25217000000001,34.027282],"type":"Point"}
}