{
  "type": "Feature",
  "properties": {
    "iso:country":"US",
    "sg:address":"5848 Foothill Blvd",
    "sg:city":"Oakland",
    "sg:classifiers":[
        {
            "category":"Food & Beverages",
            "subcategory":"Fruits & Vegetables",
            "type":"Retail Goods"
        }
    ],
    "sg:phone":"+1 510 562 2107",
    "sg:postcode":"94605",
    "sg:province":"CA",
    "sg:tags":[
        "produce"
    ],
    "wof:name":"Roger's Produce",
    "wof:placetype":"venue"
},
  "geometry": {"coordinates":[-122.191298,37.771862],"type":"Point"}
}