{
  "type": "Feature",
  "properties": {
    "iso:country":"US",
    "sg:address":"3017 E 4th St",
    "sg:city":"Los Angeles",
    "sg:classifiers":[
        {
            "category":"Manufacturing",
            "subcategory":"Printing",
            "type":"Manufacturing & Wholesale Goods"
        }
    ],
    "sg:phone":"+1 323 261 9641",
    "sg:postcode":"90063",
    "sg:province":"CA",
    "sg:tags":[
        "commercial"
    ],
    "wof:name":"Imprenta Mexico",
    "wof:placetype":"venue"
},
  "geometry": {"coordinates":[-118.202775,34.036731],"type":"Point"}
}