{
  "type": "Feature",
  "properties": {
    "iso:country":"US",
    "sg:address":"2315 18th Ave",
    "sg:city":"San Francisco",
    "sg:classifiers":[
        {
            "category":"Organizations",
            "subcategory":"Religious Organization",
            "type":"Services"
        }
    ],
    "sg:phone":"+1 650 726 1348",
    "sg:postcode":"94116",
    "sg:province":"CA",
    "wof:name":"Corporation of President of Th",
    "wof:placetype":"venue"
},
  "geometry": {"coordinates":[-122.47471299999999,37.743359],"type":"Point"}
}