{
  "type": "Feature",
  "properties": {
    "iso:country":"US",
    "sg:address":"3237 Adams Ave",
    "sg:city":"San Diego",
    "sg:classifiers":[
        {
            "category":"Banks & Credit Unions",
            "subcategory":"Investment Brokerage",
            "type":"Services"
        }
    ],
    "sg:phone":"+1 619 528 2953",
    "sg:postcode":"92116",
    "sg:province":"CA",
    "sg:tags":[
        "consultant",
        "financing"
    ],
    "wof:name":"Brand America Inc",
    "wof:placetype":"venue"
},
  "geometry": {"coordinates":[-117.124616,32.763298],"type":"Point"}
}