{
  "type": "Feature",
  "properties": {
    "iso:country":"US",
    "sg:address":"69195 Ramon Rd",
    "sg:city":"Cathedral City",
    "sg:classifiers":[
        {
            "category":"Wholesale",
            "subcategory":"Sporting Goods",
            "type":"Manufacturing & Wholesale Goods"
        }
    ],
    "sg:phone":"+1 760 770 0437",
    "sg:postcode":"92234",
    "sg:province":"CA",
    "sg:tags":[
        "equipment",
        "pool",
        "swimming"
    ],
    "wof:name":"Leslie's Swimming Pools",
    "wof:placetype":"venue"
},
  "geometry": {"coordinates":[-116.457958,33.815897],"type":"Point"}
}