{
  "type": "Feature",
  "properties": {
    "addr:full":"1050 Marina Village Pkwy Alameda CA 94501",
    "addr:housenumber":"1050",
    "addr:postcode":"94501",
    "addr:street":"Marina Village Pkwy",
    "iso:country":"US",
    "sg:address":"1050 Marina Village Pkwy",
    "sg:city":"Alameda",
    "sg:classifiers":[
        {
            "category":"Health Services",
            "subcategory":"Doctor",
            "type":"Services"
        }
    ],
    "sg:phone":"+1 510 523 8411",
    "sg:postcode":"94501",
    "sg:province":"CA",
    "sg:tags":[
        "dentist"
    ],
    "wof:name":"Richard B Marill DDS",
    "wof:placetype":"venue"
},
  "geometry": {"coordinates":[-122.27259599999999,37.785364],"type":"Point"}
}