{
  "type": "Feature",
  "properties": {
    "iso:country":"US",
    "sg:address":"601 Carmen Dr",
    "sg:city":"Camarillo",
    "sg:classifiers":[
        {
            "category":"Government",
            "subcategory":"Office",
            "type":"Public Place"
        }
    ],
    "sg:phone":"+1 805 388 5382",
    "sg:postcode":"93010",
    "sg:province":"CA",
    "sg:tags":[
        "village"
    ],
    "wof:name":"Camarillo Public Svc",
    "wof:placetype":"venue"
},
  "geometry": {"coordinates":[-119.050675,34.223547],"type":"Point"}
}