{
  "type": "Feature",
  "properties": {
    "addr:full":"4950 Pacific St Rocklin CA 95677",
    "addr:housenumber":"4950",
    "addr:postcode":"95677",
    "addr:street":"Pacific St",
    "iso:country":"US",
    "sg:address":"4950 Pacific St",
    "sg:city":"Rocklin",
    "sg:classifiers":[
        {
            "category":"Restaurant",
            "type":"Food & Drink"
        }
    ],
    "sg:phone":"+1 916 624 1920",
    "sg:postcode":"95677",
    "sg:province":"CA",
    "wof:name":"Rosy's",
    "wof:placetype":"venue"
},
  "geometry": {"coordinates":[-121.233816,38.793791],"type":"Point"}
}