{
  "type": "Feature",
  "properties": {
    "addr:full":"740 Metcalf St Escondido CA 92025",
    "addr:housenumber":"740",
    "addr:postcode":"92025",
    "addr:street":"Metcalf St",
    "iso:country":"US",
    "sg:address":"740 Metcalf St",
    "sg:city":"Escondido",
    "sg:classifiers":[
        {
            "category":"Wholesale",
            "subcategory":"Auto Parts",
            "type":"Manufacturing & Wholesale Goods"
        }
    ],
    "sg:phone":"+1 760 480 2583",
    "sg:postcode":"92025",
    "sg:province":"CA",
    "sg:tags":[
        "equipment",
        "brake"
    ],
    "wof:name":"County Wide Equipment",
    "wof:placetype":"venue"
},
  "geometry": {"coordinates":[-117.101513,33.12533],"type":"Point"}
}