{
  "type": "Feature",
  "properties": {
    "iso:country":"US",
    "sg:address":"1669 Barcelona St",
    "sg:city":"Livermore",
    "sg:classifiers":[
        {
            "category":"Building & Trades",
            "subcategory":"Landscaping Services",
            "type":"Services"
        }
    ],
    "sg:phone":"+1 925 456 6515",
    "sg:postcode":"94550",
    "sg:province":"CA",
    "wof:name":"Pride Landscaping",
    "wof:placetype":"venue"
},
  "geometry": {"coordinates":[-121.782104,37.661231],"type":"Point"}
}