{
  "type": "Feature",
  "properties": {
    "iso:country":"US",
    "sg:address":"1532 Lakewood Ave",
    "sg:city":"Modesto",
    "sg:classifiers":[
        {
            "category":"Shopping",
            "subcategory":"Beauty & Cosmetics",
            "type":"Retail Goods"
        },
        {
            "category":"Personal",
            "subcategory":"Barber",
            "type":"Services"
        }
    ],
    "sg:phone":"+1 209 521 0149",
    "sg:postcode":"95355",
    "sg:province":"CA",
    "sg:tags":[
        "equipment",
        "salons-equipment",
        "supply"
    ],
    "wof:name":"West Coast Beauty Supply",
    "wof:placetype":"venue"
},
  "geometry": {"coordinates":[-120.939003,37.665699],"type":"Point"}
}