{
  "type": "Feature",
  "properties": {
    "iso:country":"US",
    "sg:address":"824 4th St",
    "sg:city":"Orland",
    "sg:classifiers":[
        {
            "category":"Cinema",
            "subcategory":"Movie Rental",
            "type":"Entertainment"
        }
    ],
    "sg:phone":"+1 530 865 8633",
    "sg:postcode":"95963",
    "sg:province":"CA",
    "sg:tags":[
        "leasing",
        "video",
        "disc",
        "tape"
    ],
    "wof:name":"Movie Gallery",
    "wof:placetype":"venue"
},
  "geometry": {"coordinates":[-122.194254,39.746021],"type":"Point"}
}