{
  "type": "Feature",
  "properties": {
    "iso:country":"US",
    "sg:address":"800 Lincoln Blvd",
    "sg:city":"Venice",
    "sg:classifiers":[
        {
            "category":"Retail",
            "subcategory":"Auto Repair",
            "type":"Services"
        }
    ],
    "sg:phone":"+1 310 399 8313",
    "sg:postcode":"90291",
    "sg:province":"CA",
    "sg:tags":[
        "repairing",
        "automobile",
        "used",
        "general"
    ],
    "sg:website":"www.englishcars.com",
    "wof:name":"Peter's Marina Motors",
    "wof:placetype":"venue"
},
  "geometry": {"coordinates":[-118.462723,33.998866],"type":"Point"}
}