{
  "type": "Feature",
  "properties": {
    "iso:country":"US",
    "sg:address":"18 Chatelaine",
    "sg:city":"Newport Beach",
    "sg:classifiers":[
        {
            "category":"Wholesale",
            "subcategory":"Machinery & Supplies",
            "type":"Manufacturing & Wholesale Goods"
        }
    ],
    "sg:phone":"+1 949 219 9869",
    "sg:postcode":"92657",
    "sg:province":"CA",
    "sg:tags":[
        "field",
        "oil",
        "equipment"
    ],
    "wof:name":"Lani Corporation",
    "wof:placetype":"venue"
},
  "geometry": {"coordinates":[-117.839467,33.613829],"type":"Point"}
}