{
  "type": "Feature",
  "properties": {
    "addr:full":"1520 Cielo Ln Nipomo CA 93444",
    "addr:housenumber":"1520",
    "addr:postcode":"93444",
    "addr:street":"Cielo Ln",
    "iso:country":"US",
    "sg:address":"1520 Cielo Ln",
    "sg:city":"Nipomo",
    "sg:classifiers":[
        {
            "category":"Building & Trades",
            "subcategory":"Construction",
            "type":"Services"
        }
    ],
    "sg:phone":"+1 805 931 0374",
    "sg:postcode":"93444",
    "sg:province":"CA",
    "sg:tags":[
        "home",
        "improvement"
    ],
    "wof:name":"Harms Home Improvment",
    "wof:placetype":"venue"
},
  "geometry": {"coordinates":[-120.48764199999999,35.009889],"type":"Point"}
}