{
  "type": "Feature",
  "properties": {
    "iso:country":"US",
    "sg:address":"10351 Merritt St",
    "sg:city":"Castroville",
    "sg:classifiers":[
        {
            "category":"Social Services",
            "type":"Services"
        }
    ],
    "sg:phone":"+1 831 633 3866",
    "sg:postcode":"95012",
    "sg:province":"CA",
    "sg:tags":[
        "organization",
        "welfare"
    ],
    "wof:name":"Mid-Bay Emergency Food Ctr",
    "wof:placetype":"venue"
},
  "geometry": {"coordinates":[-121.761599,36.768373],"type":"Point"}
}