{
  "type": "Feature",
  "properties": {
    "addr:full":"777 Florida St San Francisco CA 94110",
    "addr:housenumber":"777",
    "addr:postcode":"94110",
    "addr:street":"Florida St",
    "iso:country":"US",
    "sg:address":"777 Florida St",
    "sg:city":"San Francisco",
    "sg:classifiers":[
        {
            "category":"Professional",
            "subcategory":"Art Services",
            "type":"Services"
        }
    ],
    "sg:phone":"+1 415 648 1991",
    "sg:postcode":"94110",
    "sg:province":"CA",
    "sg:tags":[
        "photographer"
    ],
    "wof:name":"Deborah Jones Photography Inc",
    "wof:placetype":"venue"
},
  "geometry": {"coordinates":[-122.41083999999999,37.760136],"type":"Point"}
}