{
  "type": "Feature",
  "properties": {
    "iso:country":"US",
    "sg:address":"7533 N 1st St",
    "sg:city":"Fresno",
    "sg:classifiers":[
        {
            "category":"Arts & Performance",
            "subcategory":"Theater",
            "type":"Entertainment"
        }
    ],
    "sg:phone":"+1 559 351 6258",
    "sg:postcode":"93720",
    "sg:province":"CA",
    "sg:tags":[
        "entertainer"
    ],
    "wof:name":"J's Premier Entertainment",
    "wof:placetype":"venue"
},
  "geometry": {"coordinates":[-119.77466200000001,36.8459],"type":"Point"}
}