{
  "type": "Feature",
  "properties": {
    "addr:full":"600 Cherry Ln Tehachapi CA 93561",
    "addr:housenumber":"600",
    "addr:postcode":"93561",
    "addr:street":"Cherry Ln",
    "iso:country":"US",
    "sg:address":"600 Cherry Ln",
    "sg:city":"Tehachapi",
    "sg:classifiers":[
        {
            "category":"Real Estate",
            "subcategory":"Real Estate Operator",
            "type":"Services"
        }
    ],
    "sg:phone":"+1 866 566 0190",
    "sg:postcode":"93561",
    "sg:province":"CA",
    "sg:tags":[
        "apartment"
    ],
    "wof:name":"Sierra Vista Apartments",
    "wof:placetype":"venue"
},
  "geometry": {"coordinates":[-118.45723700000001,35.120701],"type":"Point"}
}