{
  "type": "Feature",
  "properties": {
    "iso:country":"US",
    "sg:address":"2445 Peppertree Ln",
    "sg:city":"Riverside",
    "sg:classifiers":[
        {
            "category":"Sports & Exercise",
            "subcategory":"Sports Center",
            "type":"Entertainment"
        }
    ],
    "sg:phone":"+1 951 789 1863",
    "sg:postcode":"92506",
    "sg:province":"CA",
    "wof:name":"Conejo Valley Royals Club Softball Inc",
    "wof:placetype":"venue"
},
  "geometry": {"coordinates":[-117.384811,33.926834],"type":"Point"}
}