{
  "type": "Feature",
  "properties": {
    "addr:full":"10835 Vanowen St North Hollywood CA 91605",
    "addr:housenumber":"10835",
    "addr:postcode":"91605",
    "addr:street":"Vanowen St",
    "iso:country":"US",
    "sg:address":"10835 Vanowen St",
    "sg:city":"North Hollywood",
    "sg:classifiers":[
        {
            "category":"Shopping",
            "subcategory":"Bicycles & Sporting Goods",
            "type":"Retail Goods"
        }
    ],
    "sg:phone":"+1 818 761 7482",
    "sg:postcode":"91605",
    "sg:province":"CA",
    "wof:name":"United Nation Soccor League Inc",
    "wof:placetype":"venue"
},
  "geometry": {"coordinates":[-118.366997,34.194],"type":"Point"}
}