{
  "type": "Feature",
  "properties": {
    "iso:country":"US",
    "sg:address":"690 Peterson Ranch Rd",
    "sg:city":"Templeton",
    "sg:classifiers":[
        {
            "category":"Social Services",
            "type":"Services"
        }
    ],
    "sg:phone":"+1 805 434 2081",
    "sg:postcode":"93465",
    "sg:province":"CA",
    "sg:tags":[
        "care",
        "center",
        "day"
    ],
    "wof:name":"EOC Adult Day Svc",
    "wof:placetype":"venue"
},
  "geometry": {"coordinates":[-120.711906,35.558145],"type":"Point"}
}