{
  "type": "Feature",
  "properties": {
    "addr:full":"216 E Sierra St Portola CA 96122",
    "addr:housenumber":"216",
    "addr:postcode":"96122",
    "addr:street":"E Sierra St",
    "iso:country":"US",
    "sg:address":"216 E Sierra St",
    "sg:city":"Portola",
    "sg:classifiers":[
        {
            "category":"Autos & Motor Vehicles",
            "subcategory":"Auto Supplies",
            "type":"Retail Goods"
        },
        {
            "category":"Retail",
            "subcategory":"Auto Repair",
            "type":"Services"
        }
    ],
    "sg:phone":"+1 530 832 5431",
    "sg:postcode":"96122",
    "sg:province":"CA",
    "sg:tags":[
        "station",
        "gasoline",
        "tire",
        "general"
    ],
    "wof:name":"Wesley's Tires Plus",
    "wof:placetype":"venue"
},
  "geometry": {"coordinates":[-120.46617000000001,39.811533],"type":"Point"}
}