{
  "type": "Feature",
  "properties": {
    "iso:country":"US",
    "sg:address":"242 Redwood Hwy",
    "sg:city":"Mill Valley",
    "sg:classifiers":[
        {
            "category":"Travel",
            "subcategory":"Travel Agent",
            "type":"Entertainment"
        }
    ],
    "sg:phone":"+1 415 332 4843",
    "sg:postcode":"94941",
    "sg:province":"CA",
    "sg:tags":[
        "tours",
        "promoter"
    ],
    "wof:name":"San Francisco Seaplane Tours",
    "wof:placetype":"venue"
},
  "geometry": {"coordinates":[-122.51034199999999,37.875884],"type":"Point"}
}