{
  "type": "Feature",
  "properties": {
    "iso:country":"US",
    "sg:address":"1253 Birchwood Dr.",
    "sg:city":"Sunnyvale",
    "sg:classifiers":[
        {
            "category":"Autos & Motor Vehicles",
            "subcategory":"Automobile Sales",
            "type":"Retail Goods"
        },
        {
            "category":"Retail",
            "subcategory":"Auto Rental",
            "type":"Services"
        }
    ],
    "sg:phone":"+1 408 734 5438",
    "sg:postcode":"94089",
    "sg:province":"CA",
    "sg:tags":[
        "car"
    ],
    "sg:website":"www.accessoptions.com",
    "wof:name":"Access Options",
    "wof:placetype":"venue"
},
  "geometry": {"coordinates":[-121.992988,37.405013],"type":"Point"}
}