{
  "type": "Feature",
  "properties": {
    "addr:full":"2708 Vineyard Pl Fowler CA 93625",
    "addr:housenumber":"2708",
    "addr:postcode":"93625",
    "addr:street":"Vineyard Pl",
    "iso:country":"US",
    "sg:address":"2708 Vineyard Pl",
    "sg:city":"Fowler",
    "sg:classifiers":[
        {
            "category":"Autos & Motor Vehicles",
            "subcategory":"Automobile Sales",
            "type":"Retail Goods"
        },
        {
            "category":"Retail",
            "subcategory":"Auto Repair",
            "type":"Services"
        }
    ],
    "sg:phone":"+1 559 834 2400",
    "sg:postcode":"93625",
    "sg:province":"CA",
    "sg:tags":[
        "dealers-used",
        "new",
        "used",
        "cars-wholesale",
        "car"
    ],
    "wof:name":"Sierra Auto Center",
    "wof:placetype":"venue"
},
  "geometry": {"coordinates":[-119.657106,36.604783],"type":"Point"}
}