{
  "type": "Feature",
  "properties": {
    "iso:country":"US",
    "sg:address":"6391 Magnolia Ave",
    "sg:city":"Riverside",
    "sg:classifiers":[
        {
            "category":"Banks & Credit Unions",
            "subcategory":"Bank",
            "type":"Services"
        }
    ],
    "sg:phone":"+1 951 684 2566",
    "sg:postcode":"92506",
    "sg:province":"CA",
    "sg:tags":[
        "escrow"
    ],
    "wof:name":"Raincross Escrow Inc",
    "wof:placetype":"venue"
},
  "geometry": {"coordinates":[-117.394688,33.956485],"type":"Point"}
}