{
  "type": "Feature",
  "properties": {
    "addr:full":"20380 Town Center Ln Ste 170 Cupertino CA 95014",
    "addr:housenumber":"20380",
    "addr:postcode":"95014",
    "addr:street":"Town Center Ln Ste 170",
    "iso:country":"US",
    "sg:address":"20380 Town Center Ln Ste 170",
    "sg:city":"Cupertino",
    "sg:classifiers":[
        {
            "category":"Banks & Credit Unions",
            "subcategory":"Financial Services",
            "type":"Services"
        }
    ],
    "sg:phone":"+1 408 996 8828",
    "sg:postcode":"95014",
    "sg:province":"CA",
    "sg:tags":[
        "broker",
        "mortgage"
    ],
    "wof:name":"Bayhome Financial Corporation",
    "wof:placetype":"venue"
},
  "geometry": {"coordinates":[-122.038476,37.318111],"type":"Point"}
}