{
  "type": "Feature",
  "properties": {
    "addr:full":"305 Scott St Folsom CA 95630",
    "addr:housenumber":"305",
    "addr:postcode":"95630",
    "addr:street":"Scott St",
    "iso:country":"US",
    "sg:address":"305 Scott St",
    "sg:city":"Folsom",
    "sg:classifiers":[
        {
            "category":"Professional",
            "type":"Services"
        }
    ],
    "sg:phone":"+1 916 985 6200",
    "sg:postcode":"95630",
    "sg:province":"CA",
    "sg:tags":[
        "establishment"
    ],
    "wof:name":"Fait & Fait",
    "wof:placetype":"venue"
},
  "geometry": {"coordinates":[-121.174679,38.678199],"type":"Point"}
}