{
  "type": "Feature",
  "properties": {
    "iso:country":"US",
    "sg:address":"3046 Everwood Dr",
    "sg:city":"Riverside",
    "sg:classifiers":[
        {
            "category":"Building & Trades",
            "subcategory":"Construction",
            "type":"Services"
        }
    ],
    "sg:phone":"+1 951 351 4231",
    "sg:postcode":"92503",
    "sg:province":"CA",
    "wof:name":"Newport Grading Inc",
    "wof:placetype":"venue"
},
  "geometry": {"coordinates":[-117.47803,33.886392],"type":"Point"}
}