{
  "type": "Feature",
  "properties": {
    "addr:full":"9535 Artesia Blvd Bellflower CA 90706",
    "addr:housenumber":"9535",
    "addr:postcode":"90706",
    "addr:street":"Artesia Blvd",
    "iso:country":"US",
    "sg:address":"9535 Artesia Blvd",
    "sg:city":"Bellflower",
    "sg:classifiers":[
        {
            "category":"Building & Trades",
            "subcategory":"Construction",
            "type":"Services"
        }
    ],
    "sg:phone":"+1 562 866 5000",
    "sg:postcode":"90706",
    "sg:province":"CA",
    "sg:tags":[
        "layer",
        "carpet"
    ],
    "wof:name":"Best Home Carpet",
    "wof:placetype":"venue"
},
  "geometry": {"coordinates":[-118.130982,33.874876],"type":"Point"}
}