{
  "type": "Feature",
  "properties": {
    "iso:country":"US",
    "sg:address":"625 E Oak St",
    "sg:city":"Stockton",
    "sg:classifiers":[
        {
            "category":"Real Estate",
            "subcategory":"Real Estate Operator",
            "type":"Services"
        }
    ],
    "sg:phone":"+1 209 469 2562",
    "sg:postcode":"95202",
    "sg:province":"CA",
    "sg:tags":[
        "building",
        "apartment"
    ],
    "wof:name":"Doyle Gardens",
    "wof:placetype":"venue"
},
  "geometry": {"coordinates":[-121.28386,37.960037],"type":"Point"}
}