{
  "type": "Feature",
  "properties": {
    "addr:full":"2400 S Hill St Los Angeles CA 90007",
    "addr:housenumber":"2400",
    "addr:postcode":"90007",
    "addr:street":"S Hill St",
    "iso:country":"US",
    "sg:address":"2400 S Hill St",
    "sg:city":"Los Angeles",
    "sg:classifiers":[
        {
            "category":"Professional",
            "type":"Services"
        }
    ],
    "sg:phone":"+1 213 745 6777",
    "sg:postcode":"90007",
    "sg:province":"CA",
    "sg:tags":[
        "establishment"
    ],
    "wof:name":"Due Sang Corp",
    "wof:placetype":"venue"
},
  "geometry": {"coordinates":[-118.27019799999999,34.026758],"type":"Point"}
}