{
  "type": "Feature",
  "properties": {
    "iso:country":"US",
    "sg:address":"3206 Loma Verde Dr",
    "sg:city":"San Jose",
    "sg:classifiers":[
        {
            "category":"Real Estate",
            "subcategory":"Real Estate Operator",
            "type":"Services"
        }
    ],
    "sg:phone":"+1 408 378 1956",
    "sg:postcode":"95117",
    "sg:province":"CA",
    "sg:tags":[
        "apartment"
    ],
    "wof:name":"Villa Verde Apartments",
    "wof:placetype":"venue"
},
  "geometry": {"coordinates":[-121.952003,37.298801],"type":"Point"}
}