{
  "type": "Feature",
  "properties": {
    "addr:full":"5121 Garfield Ave Sacramento CA 95841",
    "addr:housenumber":"5121",
    "addr:postcode":"95841",
    "addr:street":"Garfield Ave",
    "iso:country":"US",
    "sg:address":"5121 Garfield Ave",
    "sg:city":"Sacramento",
    "sg:classifiers":[
        {
            "category":"Building & Trades",
            "subcategory":"Cleaning & Sanitation",
            "type":"Services"
        }
    ],
    "sg:phone":"+1 916 801 3072",
    "sg:postcode":"95841",
    "sg:province":"CA",
    "sg:tags":[
        "janitor"
    ],
    "wof:name":"Sunrise Cleaning Svc",
    "wof:placetype":"venue"
},
  "geometry": {"coordinates":[-121.33779199999999,38.659287],"type":"Point"}
}