{
  "type": "Feature",
  "properties": {
    "addr:full":"895 S Norton Ave Los Angeles CA 90005",
    "addr:housenumber":"895",
    "addr:postcode":"90005",
    "addr:street":"S Norton Ave",
    "iso:country":"US",
    "sg:address":"895 S Norton Ave",
    "sg:city":"Los Angeles",
    "sg:classifiers":[
        {
            "category":"Professional",
            "subcategory":"Business Services",
            "type":"Services"
        }
    ],
    "sg:phone":"+1 323 932 6296",
    "sg:postcode":"90005",
    "sg:province":"CA",
    "wof:name":"Sommers Technologies",
    "wof:placetype":"venue"
},
  "geometry": {"coordinates":[-118.31878500000001,34.058255],"type":"Point"}
}