{
  "type": "Feature",
  "properties": {
    "iso:country":"US",
    "sg:address":"6361 25th street",
    "sg:city":"Sacramento",
    "sg:classifiers":[
        {
            "category":"Sports & Exercise",
            "subcategory":"Gym",
            "type":"Entertainment"
        }
    ],
    "sg:postcode":"95822",
    "sg:province":"CA",
    "sg:tags":[
        "trainer"
    ],
    "sg:website":"www.TheOtherSideOfStrength.com",
    "wof:name":"The Other Side of Strength",
    "wof:placetype":"venue"
},
  "geometry": {"coordinates":[-121.481341,38.510728],"type":"Point"}
}