{
  "type": "Feature",
  "properties": {
    "iso:country":"US",
    "sg:address":"2145 19th Ave",
    "sg:city":"San Francisco",
    "sg:classifiers":[
        {
            "category":"Education",
            "subcategory":"Special Training",
            "type":"Public Place"
        }
    ],
    "sg:phone":"+1 415 564 2970",
    "sg:postcode":"94116",
    "sg:province":"CA",
    "sg:tags":[
        "adult"
    ],
    "sg:website":"www.kaplanprofessionalschools.com",
    "wof:name":"Kaplan Professional Schools",
    "wof:placetype":"venue"
},
  "geometry": {"coordinates":[-122.4761,37.747831],"type":"Point"}
}