{
  "type": "Feature",
  "properties": {
    "addr:full":"20340 Main St Stratford CA 93266",
    "addr:housenumber":"20340",
    "addr:postcode":"93266",
    "addr:street":"Main St",
    "iso:country":"US",
    "sg:address":"20340 Main St",
    "sg:city":"Stratford",
    "sg:classifiers":[
        {
            "category":"Government",
            "subcategory":"Post Office",
            "type":"Public Place"
        }
    ],
    "sg:phone":"+1 559 947 3004",
    "sg:postcode":"93266",
    "sg:province":"CA",
    "sg:tags":[
        "postal",
        "us"
    ],
    "wof:name":"US Post Office",
    "wof:placetype":"venue"
},
  "geometry": {"coordinates":[-119.82369300000001,36.1893],"type":"Point"}
}