{
  "type": "Feature",
  "properties": {
    "iso:country":"US",
    "sg:address":"401 E St",
    "sg:city":"Santa Rosa",
    "sg:classifiers":[
        {
            "category":"Shopping",
            "subcategory":"Music",
            "type":"Retail Goods"
        }
    ],
    "sg:phone":"+1 707 573 8040",
    "sg:postcode":"95404",
    "sg:province":"CA",
    "sg:tags":[
        "group"
    ],
    "wof:name":"Hotwax",
    "wof:placetype":"venue"
},
  "geometry": {"coordinates":[-122.711179,38.443687],"type":"Point"}
}