{
  "type": "Feature",
  "properties": {
    "iso:country":"US",
    "sg:address":"1903 E Deere Ave",
    "sg:city":"Santa Ana",
    "sg:classifiers":[
        {
            "category":"Home & Garden",
            "subcategory":"Furniture",
            "type":"Retail Goods"
        }
    ],
    "sg:phone":"+1 949 756 9111",
    "sg:postcode":"92705",
    "sg:province":"CA",
    "sg:tags":[
        "store"
    ],
    "wof:name":"Casa Bonita LLC",
    "wof:placetype":"venue"
},
  "geometry": {"coordinates":[-117.849052,33.705143],"type":"Point"}
}