{
  "type": "Feature",
  "properties": {
    "addr:full":"2915 Graceland Way Glendale CA 91206",
    "addr:housenumber":"2915",
    "addr:postcode":"91206",
    "addr:street":"Graceland Way",
    "iso:country":"US",
    "sg:address":"2915 Graceland Way",
    "sg:city":"Glendale",
    "sg:classifiers":[
        {
            "category":"Real Estate",
            "subcategory":"Real Estate Agent",
            "type":"Services"
        }
    ],
    "sg:phone":"+1 818 240 0777",
    "sg:postcode":"91206",
    "sg:province":"CA",
    "wof:name":"Regency Real Estate Svc",
    "wof:placetype":"venue"
},
  "geometry": {"coordinates":[-118.205845,34.169909],"type":"Point"}
}