{
  "type": "Feature",
  "properties": {
    "iso:country":"US",
    "sg:address":"24891 Nellie Gail Rd",
    "sg:city":"Laguna Hills",
    "sg:classifiers":[
        {
            "category":"Professional",
            "subcategory":"Management & Consulting",
            "type":"Services"
        }
    ],
    "sg:phone":"+1 949 643 2832",
    "sg:postcode":"92653",
    "sg:province":"CA",
    "sg:tags":[
        "consultant",
        "educational"
    ],
    "wof:name":"Retail Mind",
    "wof:placetype":"venue"
},
  "geometry": {"coordinates":[-117.692215,33.569926],"type":"Point"}
}