{
  "type": "Feature",
  "properties": {
    "addr:full":"4370 Palm Ave San Diego CA 92154",
    "addr:housenumber":"4370",
    "addr:postcode":"92154",
    "addr:street":"Palm Ave",
    "iso:country":"US",
    "sg:address":"4370 Palm Ave",
    "sg:city":"San Diego",
    "sg:classifiers":[
        {
            "category":"Health Services",
            "subcategory":"Doctor",
            "type":"Services"
        }
    ],
    "sg:phone":"+1 619 428 8682",
    "sg:postcode":"92154",
    "sg:province":"CA",
    "sg:tags":[
        "dentist"
    ],
    "wof:name":"Jerome A Bannister DDS",
    "wof:placetype":"venue"
},
  "geometry": {"coordinates":[-117.03998,32.583782],"type":"Point"}
}