{
  "type": "Feature",
  "properties": {
    "addr:full":"8811 Garvey Ave Rosemead CA 91770",
    "addr:housenumber":"8811",
    "addr:postcode":"91770",
    "addr:street":"Garvey Ave",
    "iso:country":"US",
    "sg:address":"8811 Garvey Ave",
    "sg:city":"Rosemead",
    "sg:classifiers":[
        {
            "category":"Personal",
            "subcategory":"Skin Care",
            "type":"Services"
        }
    ],
    "sg:phone":"+1 626 288 1799",
    "sg:postcode":"91770",
    "sg:province":"CA",
    "wof:name":"Mary Kay Cosmetics Sales Director-Ka Yee Chau",
    "wof:placetype":"venue"
},
  "geometry": {"coordinates":[-118.077003,34.062801],"type":"Point"}
}