{
  "type": "Feature",
  "properties": {
    "iso:country":"US",
    "sg:address":"780 Main St",
    "sg:city":"Pleasanton",
    "sg:classifiers":[
        {
            "category":"Social Services",
            "subcategory":"Child Care",
            "type":"Services"
        }
    ],
    "sg:phone":"+1 925 462 5200",
    "sg:postcode":"94566",
    "sg:province":"CA",
    "sg:tags":[
        "center"
    ],
    "wof:name":"Innovius",
    "wof:placetype":"venue"
},
  "geometry": {"coordinates":[-121.87432,37.663833],"type":"Point"}
}