{
  "type": "Feature",
  "properties": {
    "addr:full":"5870 Melrose Ave Los Angeles CA 90038",
    "addr:housenumber":"5870",
    "addr:postcode":"90038",
    "addr:street":"Melrose Ave",
    "iso:country":"US",
    "sg:address":"5870 Melrose Ave",
    "sg:city":"Los Angeles",
    "sg:classifiers":[
        {
            "category":"Restaurant",
            "type":"Food & Drink"
        }
    ],
    "sg:phone":"+1 323 468 9345",
    "sg:postcode":"90038",
    "sg:province":"CA",
    "sg:tags":[
        "mexican"
    ],
    "sg:website":"www.teresmexicangrill.smoola.com",
    "wof:name":"Tere's Mexican Grill",
    "wof:placetype":"venue"
},
  "geometry": {"coordinates":[-118.328003,34.083401],"type":"Point"}
}