{
  "type": "Feature",
  "properties": {
    "iso:country":"US",
    "sg:address":"26400 La Alameda",
    "sg:city":"Mission Viejo",
    "sg:classifiers":[
        {
            "category":"Organizations",
            "subcategory":"Religious Organization",
            "type":"Services"
        }
    ],
    "sg:phone":"+1 949 716 3377",
    "sg:postcode":"92691",
    "sg:province":"CA",
    "sg:website":"www.liftupamerica.com",
    "wof:name":"Lift Up America",
    "wof:placetype":"venue"
},
  "geometry": {"coordinates":[-117.669938,33.56386],"type":"Point"}
}