{
  "type": "Feature",
  "properties": {
    "addr:full":"809 Center St Santa Cruz CA 95060",
    "addr:housenumber":"809",
    "addr:postcode":"95060",
    "addr:street":"Center St",
    "iso:country":"US",
    "sg:address":"809 Center St",
    "sg:city":"Santa Cruz",
    "sg:classifiers":[
        {
            "category":"Government",
            "subcategory":"Office",
            "type":"Public Place"
        }
    ],
    "sg:phone":"+1 831 420 5040",
    "sg:postcode":"95060",
    "sg:province":"CA",
    "sg:tags":[
        "village"
    ],
    "wof:name":"Santa Cruz Human Resources",
    "wof:placetype":"venue"
},
  "geometry": {"coordinates":[-122.02910900000001,36.974728],"type":"Point"}
}