{
  "type": "Feature",
  "properties": {
    "iso:country":"US",
    "sg:address":"4112 Monterey Hwy",
    "sg:city":"San Jose",
    "sg:classifiers":[
        {
            "category":"Shopping",
            "subcategory":"Discount & Variety Stores",
            "type":"Retail Goods"
        },
        {
            "category":"Shopping",
            "subcategory":"Music",
            "type":"Retail Goods"
        }
    ],
    "sg:phone":"+1 408 226 0199",
    "sg:postcode":"95111",
    "sg:province":"CA",
    "sg:tags":[
        "tape",
        "disc",
        "video",
        "cassette"
    ],
    "wof:name":"Thai Binh Video",
    "wof:placetype":"venue"
},
  "geometry": {"coordinates":[-121.835306,37.278202],"type":"Point"}
}