{
  "type": "Feature",
  "properties": {
    "addr:full":"337 E Main St Ventura CA 93001",
    "addr:housenumber":"337",
    "addr:postcode":"93001",
    "addr:street":"E Main St",
    "iso:country":"US",
    "sg:address":"337 E Main St",
    "sg:city":"Ventura",
    "sg:classifiers":[
        {
            "category":"Shopping",
            "subcategory":"Used Merchandise",
            "type":"Retail Goods"
        }
    ],
    "sg:phone":"+1 805 648 1335",
    "sg:postcode":"93001",
    "sg:province":"CA",
    "sg:tags":[
        "antique",
        "dealer"
    ],
    "wof:name":"Provence Antiques",
    "wof:placetype":"venue"
},
  "geometry": {"coordinates":[-119.29512099999999,34.280886],"type":"Point"}
}