{
  "type": "Feature",
  "properties": {
    "iso:country":"US",
    "sg:address":"1331 Kearney St",
    "sg:city":"Los Angeles",
    "sg:classifiers":[
        {
            "category":"Real Estate",
            "subcategory":"Real Estate Operator",
            "type":"Services"
        }
    ],
    "sg:phone":"+1 323 981 0700",
    "sg:postcode":"90033",
    "sg:province":"CA",
    "sg:tags":[
        "apartment"
    ],
    "wof:name":"Aliso Village Apartments",
    "wof:placetype":"venue"
},
  "geometry": {"coordinates":[-118.208,34.049099],"type":"Point"}
}