{
  "type": "Feature",
  "properties": {
    "addr:full":"2615 Saturn Ave Huntington Park CA 90255",
    "addr:housenumber":"2615",
    "addr:postcode":"90255",
    "addr:street":"Saturn Ave;Park",
    "iso:country":"US",
    "sg:address":"2615 Saturn Ave",
    "sg:city":"Huntington Park",
    "sg:classifiers":[
        {
            "category":"Personal",
            "subcategory":"Beauty Salon",
            "type":"Services"
        }
    ],
    "sg:phone":"+1 323 581 4904",
    "sg:postcode":"90255",
    "sg:province":"CA",
    "wof:name":"Omar's Beauty Salon",
    "wof:placetype":"venue"
},
  "geometry": {"coordinates":[-118.224768,33.976979],"type":"Point"}
}