{
  "type": "Feature",
  "properties": {
    "addr:full":"20661 Santa Maria Ave Castro Valley CA 94546",
    "addr:postcode":"20661;94546",
    "addr:street":"Santa Maria Ave",
    "iso:country":"US",
    "sg:address":"20661 Santa Maria Ave",
    "sg:city":"Castro Valley",
    "sg:classifiers":[
        {
            "category":"Professional",
            "subcategory":"Accounting & Tax Preparation",
            "type":"Services"
        }
    ],
    "sg:phone":"+1 510 889 9135",
    "sg:postcode":"94546",
    "sg:province":"CA",
    "sg:tags":[
        "return",
        "filing"
    ],
    "wof:name":"Don & Linda's Tax Svc",
    "wof:placetype":"venue"
},
  "geometry": {"coordinates":[-122.07845500000001,37.696528],"type":"Point"}
}