{
  "type": "Feature",
  "properties": {
    "iso:country":"US",
    "sg:address":"5638 Atlantic Ave",
    "sg:city":"Long Beach",
    "sg:classifiers":[
        {
            "category":"Shopping",
            "subcategory":"Gifts & Souvenirs",
            "type":"Retail Goods"
        }
    ],
    "sg:phone":"+1 562 728 1800",
    "sg:postcode":"90805",
    "sg:province":"CA",
    "wof:name":"Seasons Gift Shop",
    "wof:placetype":"venue"
},
  "geometry": {"coordinates":[-118.184893,33.859686],"type":"Point"}
}