{
  "type": "Feature",
  "properties": {
    "addr:full":"535 Leisure St Livermore CA 94551",
    "addr:housenumber":"535",
    "addr:postcode":"94551",
    "addr:street":"Leisure St",
    "iso:country":"US",
    "sg:address":"535 Leisure St",
    "sg:city":"Livermore",
    "sg:classifiers":[
        {
            "category":"Home & Garden",
            "subcategory":"Building Materials",
            "type":"Retail Goods"
        }
    ],
    "sg:phone":"+1 925 456 9650",
    "sg:postcode":"94551",
    "sg:province":"CA",
    "sg:tags":[
        "energy",
        "conservation",
        "prod"
    ],
    "wof:name":"Eastwood Energy Livermore Br",
    "wof:placetype":"venue"
},
  "geometry": {"coordinates":[-121.719494,37.710367],"type":"Point"}
}