{
  "type": "Feature",
  "properties": {
    "addr:full":"913 San Ramon Valley Blvd Danville CA 94526",
    "addr:housenumber":"913",
    "addr:postcode":"94526",
    "addr:street":"San Ramon Valley Blvd",
    "iso:country":"US",
    "sg:address":"913 San Ramon Valley Blvd",
    "sg:city":"Danville",
    "sg:classifiers":[
        {
            "category":"Health Services",
            "subcategory":"Health Practitioner",
            "type":"Services"
        }
    ],
    "sg:phone":"+1 925 838 2248",
    "sg:postcode":"94526",
    "sg:province":"CA",
    "sg:tags":[
        "psychotherapist"
    ],
    "wof:name":"Susann Green",
    "wof:placetype":"venue"
},
  "geometry": {"coordinates":[-121.991967,37.807681],"type":"Point"}
}