{
  "type": "Feature",
  "properties": {
    "addr:full":"3129 S Hacienda Blvd Hacienda Heights CA 91745",
    "addr:housenumber":"3129",
    "addr:postcode":"91745",
    "addr:street":"S Hacienda Blvd",
    "iso:country":"US",
    "sg:address":"3129 S Hacienda Blvd",
    "sg:city":"Hacienda Heights",
    "sg:classifiers":[
        {
            "category":"Professional",
            "subcategory":"Business Services",
            "type":"Services"
        }
    ],
    "sg:phone":"+1 626 961 3782",
    "sg:postcode":"91745",
    "sg:province":"CA",
    "sg:tags":[
        "trade",
        "fair",
        "show"
    ],
    "sg:website":"www.rockwar.com",
    "wof:name":"MEGA Shows",
    "wof:placetype":"venue"
},
  "geometry": {"coordinates":[-117.97236100000001,33.979799],"type":"Point"}
}