{
  "type": "Feature",
  "properties": {
    "addr:full":"790 Caliente Ave Livermore CA 94550",
    "addr:housenumber":"790",
    "addr:postcode":"94550",
    "addr:street":"Caliente Ave",
    "iso:country":"US",
    "sg:address":"790 Caliente Ave",
    "sg:city":"Livermore",
    "sg:classifiers":[
        {
            "category":"Autos & Motor Vehicles",
            "subcategory":"Auto Supplies",
            "type":"Retail Goods"
        },
        {
            "category":"Wholesale",
            "subcategory":"Auto Parts",
            "type":"Manufacturing & Wholesale Goods"
        }
    ],
    "sg:phone":"+1 925 455 6740",
    "sg:postcode":"94550",
    "sg:province":"CA",
    "sg:tags":[
        "automotive",
        "used",
        "automobile"
    ],
    "wof:name":"Yoshino Keech Auto Parts",
    "wof:placetype":"venue"
},
  "geometry": {"coordinates":[-121.787514,37.66785],"type":"Point"}
}