{
  "type": "Feature",
  "properties": {
    "iso:country":"US",
    "sg:address":"1174 National Dr, Suite 10",
    "sg:city":"Sacramento",
    "sg:classifiers":[
        {
            "category":"Professional",
            "subcategory":"Detective & Security Services",
            "type":"Services"
        }
    ],
    "sg:phone":"+1 800 438 4357",
    "sg:postcode":"95834",
    "sg:province":"CA",
    "sg:tags":[
        "system"
    ],
    "sg:website":"www.protectionone.com",
    "wof:name":"Protection One",
    "wof:placetype":"venue"
},
  "geometry": {"coordinates":[-121.487049,38.64385],"type":"Point"}
}