{
  "type": "Feature",
  "properties": {
    "iso:country":"US",
    "sg:address":"27051 Henry Mayo Dr",
    "sg:city":"Valencia",
    "sg:classifiers":[
        {
            "category":"Education",
            "subcategory":"School",
            "type":"Public Place"
        }
    ],
    "sg:phone":"+1 661 294 1427",
    "sg:postcode":"91355",
    "sg:province":"CA",
    "sg:tags":[
        "high",
        "middle",
        "elementary"
    ],
    "wof:name":"Castaic Elementary School",
    "wof:placetype":"venue"
},
  "geometry": {"coordinates":[-118.608002,34.439602],"type":"Point"}
}