{
  "type": "Feature",
  "properties": {
    "iso:country":"US",
    "sg:address":"41389 Rd 44",
    "sg:city":"Reedley",
    "sg:classifiers":[
        {
            "category":"Wholesale",
            "subcategory":"Fruits & Vegetables",
            "type":"Manufacturing & Wholesale Goods"
        }
    ],
    "sg:phone":"+1 559 638 7497",
    "sg:postcode":"93654",
    "sg:province":"CA",
    "sg:tags":[
        "shipper"
    ],
    "wof:name":"Sunbird Packing",
    "wof:placetype":"venue"
},
  "geometry": {"coordinates":[-119.47558,36.546514],"type":"Point"}
}