{
  "type": "Feature",
  "properties": {
    "iso:country":"US",
    "sg:address":"4600 Ashe Rd",
    "sg:city":"Bakersfield",
    "sg:classifiers":[
        {
            "category":"Home & Garden",
            "subcategory":"Building Materials",
            "type":"Retail Goods"
        }
    ],
    "sg:phone":"+1 661 836 1750",
    "sg:postcode":"93313",
    "sg:province":"CA",
    "sg:tags":[
        "windows"
    ],
    "wof:name":"Pacific Glass & Window Co",
    "wof:placetype":"venue"
},
  "geometry": {"coordinates":[-119.074363,35.315837],"type":"Point"}
}