{
  "type": "Feature",
  "properties": {
    "addr:full":"165 Stonewood St Downey CA 90241",
    "addr:housenumber":"165",
    "addr:postcode":"90241",
    "addr:street":"Stonewood St",
    "iso:country":"US",
    "sg:address":"165 Stonewood St",
    "sg:city":"Downey",
    "sg:classifiers":[
        {
            "category":"Shopping Center",
            "type":"Public Place"
        }
    ],
    "sg:phone":"+1 562 862 0255",
    "sg:postcode":"90241",
    "sg:province":"CA",
    "wof:name":"Regis Salon",
    "wof:placetype":"venue"
},
  "geometry": {"coordinates":[-118.1211,33.938281],"type":"Point"}
}