{
  "type": "Feature",
  "properties": {
    "addr:full":"3327 San Gabriel Blvd Ste D Rosemead CA 91770",
    "addr:housenumber":"3327",
    "addr:postcode":"91770",
    "addr:street":"San Gabriel Blvd Ste D",
    "iso:country":"US",
    "sg:address":"3327 San Gabriel Blvd Ste D",
    "sg:city":"Rosemead",
    "sg:classifiers":[
        {
            "category":"Health Services",
            "subcategory":"Health Practitioner",
            "type":"Services"
        }
    ],
    "sg:phone":"+1 626 571 8588",
    "sg:postcode":"91770",
    "sg:province":"CA",
    "sg:tags":[
        "acupuncture"
    ],
    "wof:name":"Hope Medical Clinic",
    "wof:placetype":"venue"
},
  "geometry": {"coordinates":[-118.091003,34.068298],"type":"Point"}
}