{
  "type": "Feature",
  "properties": {
    "addr:full":"4023 W 6th St Los Angeles CA 90020",
    "addr:housenumber":"4023",
    "addr:postcode":"90020",
    "addr:street":"W 6Th St",
    "iso:country":"US",
    "sg:address":"4023 W 6th St",
    "sg:city":"Los Angeles",
    "sg:classifiers":[
        {
            "category":"Real Estate",
            "subcategory":"Real Estate Agent",
            "type":"Services"
        }
    ],
    "sg:phone":"+1 213 386 8191",
    "sg:postcode":"90020",
    "sg:province":"CA",
    "wof:name":"Edwin R Bernstein",
    "wof:placetype":"venue"
},
  "geometry": {"coordinates":[-118.31110700000001,34.063592],"type":"Point"}
}