{
  "type": "Feature",
  "properties": {
    "iso:country":"US",
    "sg:address":"5802 College Ave",
    "sg:city":"Oakland",
    "sg:classifiers":[
        {
            "category":"Health Services",
            "subcategory":"Optometrist",
            "type":"Services"
        }
    ],
    "sg:phone":"+1 510 653 4242",
    "sg:postcode":"94618",
    "sg:province":"CA",
    "wof:name":"Lin Susan T Optometrist OD",
    "wof:placetype":"venue"
},
  "geometry": {"coordinates":[-122.251999,37.845402],"type":"Point"}
}