{
  "type": "Feature",
  "properties": {
    "iso:country":"US",
    "sg:address":"12310 State Rte 33",
    "sg:city":"Gustine",
    "sg:classifiers":[
        {
            "category":"Restaurant",
            "type":"Food & Drink"
        }
    ],
    "sg:phone":"+1 209 826 6353",
    "sg:postcode":"95322",
    "sg:province":"CA",
    "wof:name":"Mid-California 76",
    "wof:placetype":"venue"
},
  "geometry": {"coordinates":[-121.015531,37.110006],"type":"Point"}
}