{
  "type": "Feature",
  "properties": {
    "iso:country":"US",
    "sg:address":"9093 Spring Valley Rd",
    "sg:city":"Marysville",
    "sg:classifiers":[
        {
            "category":"Building & Trades",
            "subcategory":"Construction",
            "type":"Services"
        }
    ],
    "sg:phone":"+1 530 743 2108",
    "sg:postcode":"95901",
    "sg:province":"CA",
    "sg:tags":[
        "earth",
        "excavating",
        "moving",
        "contractor"
    ],
    "wof:name":"Mc Ewen Construction",
    "wof:placetype":"venue"
},
  "geometry": {"coordinates":[-121.45507000000001,39.232484],"type":"Point"}
}