{
  "type": "Feature",
  "properties": {
    "addr:full":"2041 Harbison Dr Vacaville CA 95687",
    "addr:housenumber":"2041",
    "addr:postcode":"95687",
    "addr:street":"Harbison Dr",
    "iso:country":"US",
    "sg:address":"2041 Harbison Dr",
    "sg:city":"Vacaville",
    "sg:classifiers":[
        {
            "category":"Shopping",
            "subcategory":"Used Merchandise",
            "type":"Retail Goods"
        }
    ],
    "sg:phone":"+1 707 448 1212",
    "sg:postcode":"95687",
    "sg:province":"CA",
    "sg:tags":[
        "infant",
        "wear"
    ],
    "wof:name":"Once Upon A Child",
    "wof:placetype":"venue"
},
  "geometry": {"coordinates":[-121.963381,38.361656],"type":"Point"}
}