{
  "type": "Feature",
  "properties": {
    "addr:full":"9052 Haskell St Riverside CA 92503",
    "addr:housenumber":"9052",
    "addr:postcode":"92503",
    "addr:street":"Haskell St",
    "iso:country":"US",
    "sg:address":"9052 Haskell St",
    "sg:city":"Riverside",
    "sg:classifiers":[
        {
            "category":"Building & Trades",
            "subcategory":"Construction",
            "type":"Services"
        }
    ],
    "sg:phone":"+1 951 637 8971",
    "sg:postcode":"92503",
    "sg:province":"CA",
    "sg:tags":[
        "residential"
    ],
    "wof:name":"Flintridge Construction Svc",
    "wof:placetype":"venue"
},
  "geometry": {"coordinates":[-117.433148,33.918503],"type":"Point"}
}