{
  "type": "Feature",
  "properties": {
    "addr:full":"171 N Santa Rosa St San Luis Obispo CA 93405",
    "addr:housenumber":"171",
    "addr:postcode":"93405",
    "addr:street":"N Santa Rosa St",
    "iso:country":"US",
    "sg:address":"171 N Santa Rosa St",
    "sg:city":"San Luis Obispo",
    "sg:classifiers":[
        {
            "category":"Health Services",
            "subcategory":"Medical Lab",
            "type":"Services"
        }
    ],
    "sg:phone":"+1 805 543 5718",
    "sg:postcode":"93405",
    "sg:province":"CA",
    "sg:tags":[
        "laboratory"
    ],
    "sg:website":"www.unilab.org",
    "wof:name":"Unilab Corp",
    "wof:placetype":"venue"
},
  "geometry": {"coordinates":[-120.668335,35.294543],"type":"Point"}
}