{
  "type": "Feature",
  "properties": {
    "addr:full":"3629 Grand Ave Oakland CA 94610",
    "addr:housenumber":"3629",
    "addr:postcode":"94610",
    "addr:street":"Grand Ave",
    "iso:country":"US",
    "sg:address":"3629 Grand Ave",
    "sg:city":"Oakland",
    "sg:classifiers":[
        {
            "category":"Health Services",
            "subcategory":"Clinic",
            "type":"Services"
        }
    ],
    "sg:phone":"+1 510 545 2147",
    "sg:postcode":"94610",
    "sg:province":"CA",
    "sg:tags":[
        "counseling",
        "mental"
    ],
    "wof:name":"My Sleep Coach Jessica",
    "wof:placetype":"venue"
},
  "geometry": {"coordinates":[-122.24611299999999,37.815597],"type":"Point"}
}