{
  "type": "Feature",
  "properties": {
    "iso:country":"US",
    "sg:address":"7960 N Waverly Rd",
    "sg:city":"Linden",
    "sg:classifiers":[
        {
            "category":"Banks & Credit Unions",
            "subcategory":"Bank",
            "type":"Services"
        }
    ],
    "sg:phone":"+1 209 887 2737",
    "sg:postcode":"95236",
    "sg:province":"CA",
    "sg:tags":[
        "broker",
        "mortgage"
    ],
    "wof:name":"Agribusiness Financial",
    "wof:placetype":"venue"
},
  "geometry": {"coordinates":[-120.944721,38.029112],"type":"Point"}
}