{
  "type": "Feature",
  "properties": {
    "addr:full":"1549 Lisa St Carpinteria CA 93013",
    "addr:housenumber":"1549",
    "addr:postcode":"93013",
    "addr:street":"Lisa St",
    "iso:country":"US",
    "sg:address":"1549 Lisa St",
    "sg:city":"Carpinteria",
    "sg:classifiers":[
        {
            "category":"Farming",
            "subcategory":"Nursery",
            "type":"Manufacturing & Wholesale Goods"
        }
    ],
    "sg:phone":"+1 805 566 0839",
    "sg:postcode":"93013",
    "sg:province":"CA",
    "sg:tags":[
        "ornamental"
    ],
    "wof:name":"Methmann Orchids",
    "wof:placetype":"venue"
},
  "geometry": {"coordinates":[-119.50766299999999,34.404773],"type":"Point"}
}