{
  "type": "Feature",
  "properties": {
    "iso:country":"US",
    "sg:address":"3232 Stine Rd",
    "sg:city":"Bakersfield",
    "sg:classifiers":[
        {
            "category":"Food & Beverages",
            "subcategory":"Groceries & Convenience Stores",
            "type":"Retail Goods"
        }
    ],
    "sg:phone":"+1 661 832 6445",
    "sg:postcode":"93309",
    "sg:province":"CA",
    "sg:tags":[
        "grocer"
    ],
    "wof:name":"Lucky Seven",
    "wof:placetype":"venue"
},
  "geometry": {"coordinates":[-119.056596,35.326272],"type":"Point"}
}