{
  "type": "Feature",
  "properties": {
    "iso:country":"US",
    "sg:address":"9023 S Broadway",
    "sg:city":"Los Angeles",
    "sg:classifiers":[
        {
            "category":"Home & Garden",
            "subcategory":"Hardware",
            "type":"Retail Goods"
        }
    ],
    "sg:phone":"+1 323 242 9482",
    "sg:postcode":"90003",
    "sg:province":"CA",
    "sg:tags":[
        "store"
    ],
    "wof:name":"El Companys Hardware",
    "wof:placetype":"venue"
},
  "geometry": {"coordinates":[-118.27800000000001,33.9548],"type":"Point"}
}