{
  "type": "Feature",
  "properties": {
    "iso:country":"US",
    "sg:address":"4651 Mission Blvd",
    "sg:city":"San Diego",
    "sg:classifiers":[
        {
            "category":"Shopping",
            "subcategory":"Hobbies, Toys, & Games",
            "type":"Retail Goods"
        }
    ],
    "sg:phone":"+1 858 273 1921",
    "sg:postcode":"92109",
    "sg:province":"CA",
    "sg:tags":[
        "kite"
    ],
    "wof:name":"Ride The Wind",
    "wof:placetype":"venue"
},
  "geometry": {"coordinates":[-117.256208,32.798896],"type":"Point"}
}