{
  "type": "Feature",
  "properties": {
    "addr:full":"300 Continental Blvd El Segundo CA 90245",
    "addr:housenumber":"300",
    "addr:postcode":"90245",
    "addr:street":"Continental Blvd",
    "iso:country":"US",
    "sg:address":"300 Continental Blvd",
    "sg:city":"El Segundo",
    "sg:classifiers":[
        {
            "category":"Parking",
            "type":"Transportation"
        }
    ],
    "sg:phone":"+1 310 726 0199",
    "sg:postcode":"90245",
    "sg:province":"CA",
    "sg:website":"www.abm.com",
    "wof:name":"Ampco System Parking",
    "wof:placetype":"venue"
},
  "geometry": {"coordinates":[-118.39059399999999,33.91953],"type":"Point"}
}