{
  "type": "Feature",
  "properties": {
    "addr:full":"217 Old County Rd Belmont CA 94002",
    "addr:housenumber":"217",
    "addr:postcode":"94002",
    "addr:street":"Old County Rd",
    "iso:country":"US",
    "sg:address":"217 Old County Rd",
    "sg:city":"Belmont",
    "sg:classifiers":[
        {
            "category":"Building & Trades",
            "subcategory":"Construction",
            "type":"Services"
        }
    ],
    "sg:phone":"+1 650 591 2186",
    "sg:postcode":"94002",
    "sg:province":"CA",
    "sg:tags":[
        "maker",
        "cabinet"
    ],
    "wof:name":"Creative Cabinets",
    "wof:placetype":"venue"
},
  "geometry": {"coordinates":[-122.284361,37.528125],"type":"Point"}
}