{
  "type": "Feature",
  "properties": {
    "addr:full":"888 Brannan St San Francisco CA 94103",
    "addr:housenumber":"888",
    "addr:postcode":"94103",
    "addr:street":"Brannan St",
    "iso:country":"US",
    "sg:address":"888 Brannan St",
    "sg:city":"San Francisco",
    "sg:classifiers":[
        {
            "category":"Wholesale",
            "subcategory":"Jewelry",
            "type":"Manufacturing & Wholesale Goods"
        }
    ],
    "sg:phone":"+1 415 861 8858",
    "sg:postcode":"94103",
    "sg:province":"CA",
    "sg:tags":[
        "jeweler"
    ],
    "wof:name":"H J Ho Trading Inc",
    "wof:placetype":"venue"
},
  "geometry": {"coordinates":[-122.40449,37.772337],"type":"Point"}
}