{
  "type": "Feature",
  "properties": {
    "addr:full":"203 Great Mall Dr Milpitas CA 95035",
    "addr:housenumber":"203",
    "addr:postcode":"95035",
    "addr:street":"Great Mall Dr",
    "iso:country":"US",
    "sg:address":"203 Great Mall Dr",
    "sg:city":"Milpitas",
    "sg:classifiers":[
        {
            "category":"Shopping",
            "subcategory":"Shoes",
            "type":"Retail Goods"
        }
    ],
    "sg:phone":"+1 408 934 9500",
    "sg:postcode":"95035",
    "sg:province":"CA",
    "wof:name":"Zee Kids Footwear",
    "wof:placetype":"venue"
},
  "geometry": {"coordinates":[-121.900373,37.419361],"type":"Point"}
}