{
  "type": "Feature",
  "properties": {
    "iso:country":"US",
    "sg:address":"1300 del Monte Center",
    "sg:city":"Monterey",
    "sg:classifiers":[
        {
            "category":"Shopping",
            "subcategory":"Bicycles & Sporting Goods",
            "type":"Retail Goods"
        }
    ],
    "sg:phone":"+1 831 375 8800",
    "sg:postcode":"93940",
    "sg:province":"CA",
    "sg:website":"www.big5.com",
    "wof:name":"Big 5 Sporting Goods",
    "wof:placetype":"venue"
},
  "geometry": {"coordinates":[-121.89603700000001,36.585622],"type":"Point"}
}