{
  "type": "Feature",
  "properties": {
    "iso:country":"US",
    "sg:address":"2437 Center Rd",
    "sg:city":"Novato",
    "sg:classifiers":[
        {
            "category":"Wholesale",
            "subcategory":"Hardware",
            "type":"Manufacturing & Wholesale Goods"
        }
    ],
    "sg:phone":"+1 415 892 5602",
    "sg:postcode":"94947",
    "sg:province":"CA",
    "wof:name":"Coldwell Mackay",
    "wof:placetype":"venue"
},
  "geometry": {"coordinates":[-122.611583,38.112053],"type":"Point"}
}