{
  "type": "Feature",
  "properties": {
    "addr:full":"871 Lorinda Ln Chico CA 95973",
    "addr:housenumber":"871",
    "addr:postcode":"95973",
    "addr:street":"Lorinda Ln",
    "iso:country":"US",
    "sg:address":"871 Lorinda Ln",
    "sg:city":"Chico",
    "sg:classifiers":[
        {
            "category":"Building & Trades",
            "subcategory":"Landscaping Services",
            "type":"Services"
        }
    ],
    "sg:phone":"+1 530 343 6608",
    "sg:postcode":"95973",
    "sg:province":"CA",
    "sg:tags":[
        "tree"
    ],
    "wof:name":"Ledford's Tree Svc",
    "wof:placetype":"venue"
},
  "geometry": {"coordinates":[-121.844723,39.762726],"type":"Point"}
}