{
  "type": "Feature",
  "properties": {
    "addr:full":"162 S Rancho Santa Fe Rd Encinitas CA 92024",
    "addr:housenumber":"162",
    "addr:postcode":"92024",
    "addr:street":"S Rancho Santa Fe Rd",
    "iso:country":"US",
    "sg:address":"162 S Rancho Santa Fe Rd",
    "sg:city":"Encinitas",
    "sg:classifiers":[
        {
            "category":"Restaurant",
            "type":"Food & Drink"
        }
    ],
    "sg:menulink":"http://www.allmenus.com/ca/san-diego/30613-firenze-trattoria/menu/",
    "sg:phone":"+1 760 944 9000",
    "sg:postcode":"92024",
    "sg:province":"CA",
    "sg:tags":[
        "italian"
    ],
    "wof:name":"Firenze Trattoria",
    "wof:placetype":"venue"
},
  "geometry": {"coordinates":[-117.237549,33.035868],"type":"Point"}
}