{
  "type": "Feature",
  "properties": {
    "addr:full":"107 San Thomas Way Danville CA 94526",
    "addr:housenumber":"107",
    "addr:postcode":"94526",
    "addr:street":"San Thomas Way",
    "iso:country":"US",
    "sg:address":"107 San Thomas Way",
    "sg:city":"Danville",
    "sg:classifiers":[
        {
            "category":"Utilities",
            "subcategory":"Telephone",
            "type":"Services"
        }
    ],
    "sg:phone":"+1 925 743 0365",
    "sg:postcode":"94526",
    "sg:province":"CA",
    "sg:tags":[
        "communications"
    ],
    "wof:name":"Good Luck Games Company",
    "wof:placetype":"venue"
},
  "geometry": {"coordinates":[-121.98931899999999,37.80447],"type":"Point"}
}