{
  "type": "Feature",
  "properties": {
    "addr:full":"1010 S Bon View Ave Ontario CA 91761",
    "addr:housenumber":"1010",
    "addr:postcode":"91761",
    "addr:street":"S Bon View Ave",
    "iso:country":"US",
    "sg:address":"1010 S Bon View Ave",
    "sg:city":"Ontario",
    "sg:classifiers":[
        {
            "category":"Recreation",
            "type":"Entertainment"
        }
    ],
    "sg:phone":"+1 909 930 3344",
    "sg:postcode":"91761",
    "sg:province":"CA",
    "sg:tags":[
        "hall",
        "auditorium"
    ],
    "wof:name":"Bon View Community Ctr",
    "wof:placetype":"venue"
},
  "geometry": {"coordinates":[-117.636996,34.051624],"type":"Point"}
}