{
  "type": "Feature",
  "properties": {
    "iso:country":"US",
    "sg:address":"151 North Garfield",
    "sg:city":"Alhambra",
    "sg:classifiers":[
        {
            "category":"Fast Food",
            "type":"Food & Drink"
        }
    ],
    "sg:postcode":"91801",
    "sg:province":"CA",
    "sg:website":"www.kfc.com/",
    "wof:name":"Kentucky Fried Chicken",
    "wof:placetype":"venue"
},
  "geometry": {"coordinates":[-118.12586899999999,34.093751],"type":"Point"}
}