{
  "type": "Feature",
  "properties": {
    "addr:full":"1101 Montana Ave Santa Monica CA 90403",
    "addr:housenumber":"1101",
    "addr:postcode":"90403",
    "addr:street":"Montana Ave",
    "iso:country":"US",
    "sg:address":"1101 Montana Ave",
    "sg:city":"Santa Monica",
    "sg:classifiers":[
        {
            "category":"Real Estate",
            "subcategory":"Real Estate Operator",
            "type":"Services"
        }
    ],
    "sg:phone":"+1 310 451 9877",
    "sg:postcode":"90403",
    "sg:province":"CA",
    "sg:tags":[
        "building",
        "nonresidential"
    ],
    "wof:name":"Heslov Properties",
    "wof:placetype":"venue"
},
  "geometry": {"coordinates":[-118.497511,34.030297],"type":"Point"}
}