{
  "type": "Feature",
  "properties": {
    "addr:full":"40404 California Oaks Rd Murrieta CA 92562",
    "addr:housenumber":"40404",
    "addr:postcode":"92562",
    "addr:street":"California Oaks Rd",
    "iso:country":"US",
    "sg:address":"40404 California Oaks Rd",
    "sg:city":"Murrieta",
    "sg:classifiers":[
        {
            "category":"Restaurant",
            "type":"Food & Drink"
        }
    ],
    "sg:menulink":"http://www.allmenus.com/ca/murrieta/74109-dominos-pizza/menu/",
    "sg:phone":"+1 951 696 0117",
    "sg:postcode":"92562",
    "sg:province":"CA",
    "sg:tags":[
        "american",
        "wing",
        "pizza"
    ],
    "wof:name":"Domino's Pizza",
    "wof:placetype":"venue"
},
  "geometry": {"coordinates":[-117.199513,33.57828],"type":"Point"}
}