{
  "type": "Feature",
  "properties": {
    "iso:country":"US",
    "sg:address":"12320 Woodruff Ave",
    "sg:city":"Downey",
    "sg:classifiers":[
        {
            "category":"Personal",
            "type":"Services"
        }
    ],
    "sg:phone":"+1 562 861 2345",
    "sg:postcode":"90241",
    "sg:province":"CA",
    "sg:tags":[
        "towing"
    ],
    "wof:name":"Doug's Tug",
    "wof:placetype":"venue"
},
  "geometry": {"coordinates":[-118.114295,33.920418],"type":"Point"}
}