{
  "type": "Feature",
  "properties": {
    "addr:full":"703 Market St Ste 251 San Francisco CA 94103",
    "addr:housenumber":"703",
    "addr:postcode":"94103",
    "addr:street":"Market St Ste 251",
    "iso:country":"US",
    "sg:address":"703 Market St Ste 251",
    "sg:city":"San Francisco",
    "sg:classifiers":[
        {
            "category":"Travel",
            "subcategory":"Travel Agent",
            "type":"Entertainment"
        }
    ],
    "sg:phone":"+1 415 356 2260",
    "sg:postcode":"94103",
    "sg:province":"CA",
    "sg:website":"www.yankeeclippertravel.com",
    "wof:name":"Yankee Clipper Travel",
    "wof:placetype":"venue"
},
  "geometry": {"coordinates":[-122.40366,37.787429],"type":"Point"}
}