{
  "type": "Feature",
  "properties": {
    "iso:country":"US",
    "sg:address":"7336 Freeman Pl",
    "sg:city":"Goleta",
    "sg:classifiers":[
        {
            "category":"Building & Trades",
            "subcategory":"Construction",
            "type":"Services"
        }
    ],
    "sg:phone":"+1 805 968 2030",
    "sg:postcode":"93117",
    "sg:province":"CA",
    "wof:name":"Remo System & Fittings",
    "wof:placetype":"venue"
},
  "geometry": {"coordinates":[-119.881792,34.427266],"type":"Point"}
}