{
  "type": "Feature",
  "properties": {
    "addr:full":"637 S Hill St Los Angeles CA 90014",
    "addr:housenumber":"637",
    "addr:postcode":"90014",
    "addr:street":"S Hill St",
    "iso:country":"US",
    "sg:address":"637 S Hill St",
    "sg:city":"Los Angeles",
    "sg:classifiers":[
        {
            "category":"Shopping",
            "subcategory":"Jewelry",
            "type":"Retail Goods"
        }
    ],
    "sg:phone":"+1 213 623 4822",
    "sg:postcode":"90014",
    "sg:province":"CA",
    "wof:name":"Star Jewelry",
    "wof:placetype":"venue"
},
  "geometry": {"coordinates":[-118.251999,34.0448],"type":"Point"}
}