{
  "type": "Feature",
  "properties": {
    "iso:country":"US",
    "sg:address":"3125 Tomahawk Dr",
    "sg:city":"Stockton",
    "sg:classifiers":[
        {
            "category":"Professional",
            "subcategory":"Computer Services",
            "type":"Services"
        }
    ],
    "sg:phone":"+1 209 649 8318",
    "sg:postcode":"95205",
    "sg:province":"CA",
    "wof:name":"Convergent Network Solutions",
    "wof:placetype":"venue"
},
  "geometry": {"coordinates":[-121.254752,37.985606],"type":"Point"}
}