{
  "type": "Feature",
  "properties": {
    "iso:country":"US",
    "sg:address":"24708 Viejas Blvd",
    "sg:city":"Descanso",
    "sg:classifiers":[
        {
            "category":"Professional",
            "subcategory":"Business Services",
            "type":"Services"
        }
    ],
    "sg:phone":"+1 619 445 4744",
    "sg:postcode":"91916",
    "sg:province":"CA",
    "sg:tags":[
        "license"
    ],
    "wof:name":"Country Services",
    "wof:placetype":"venue"
},
  "geometry": {"coordinates":[-116.614287,32.857176],"type":"Point"}
}