{
  "type": "Feature",
  "properties": {
    "iso:country":"US",
    "sg:address":"835 W Harbor Dr #C",
    "sg:city":"San Diego",
    "sg:classifiers":[
        {
            "category":"Coffee & Tea",
            "type":"Food & Drink"
        },
        {
            "category":"Shopping",
            "subcategory":"Books",
            "type":"Retail Goods"
        }
    ],
    "sg:phone":"+1 619 232 4855",
    "sg:postcode":"92101",
    "sg:province":"CA",
    "sg:tags":[
        "bookstore"
    ],
    "sg:website":"www.upstartcrowtrading.com",
    "wof:name":"Upstart Crow Bookstore & Coffee House",
    "wof:placetype":"venue"
},
  "geometry": {"coordinates":[-117.169763,32.708595],"type":"Point"}
}