{
  "type": "Feature",
  "properties": {
    "addr:full":"5428 California Ave Bakersfield CA 93309",
    "addr:housenumber":"5428",
    "addr:postcode":"93309",
    "addr:street":"California Ave",
    "iso:country":"US",
    "sg:address":"5428 California Ave",
    "sg:city":"Bakersfield",
    "sg:classifiers":[
        {
            "category":"Personal",
            "subcategory":"Beauty Salon",
            "type":"Services"
        }
    ],
    "sg:phone":"+1 661 324 4247",
    "sg:postcode":"93309",
    "sg:province":"CA",
    "wof:name":"Split Ends",
    "wof:placetype":"venue"
},
  "geometry": {"coordinates":[-119.06084,35.359676],"type":"Point"}
}