{
  "type": "Feature",
  "properties": {
    "iso:country":"US",
    "sg:address":"1020 University Ave",
    "sg:city":"San Diego",
    "sg:classifiers":[
        {
            "category":"Personal",
            "subcategory":"Beauty Salon",
            "type":"Services"
        }
    ],
    "sg:phone":"+1 619 905 5221",
    "sg:postcode":"92103",
    "sg:province":"CA",
    "sg:tags":[
        "hair"
    ],
    "sg:website":"www.empirebeautysupply.com",
    "wof:name":"Empire Beauty Supply Hillcrest",
    "wof:placetype":"venue"
},
  "geometry": {"coordinates":[-117.15433,32.748566],"type":"Point"}
}