{
  "type": "Feature",
  "properties": {
    "addr:full":"980 E Campbell Ave Campbell CA 95008",
    "addr:housenumber":"980",
    "addr:postcode":"95008",
    "addr:street":"E Campbell Ave",
    "iso:country":"US",
    "sg:address":"980 E Campbell Ave",
    "sg:city":"Campbell",
    "sg:classifiers":[
        {
            "category":"Restaurant",
            "type":"Food & Drink"
        }
    ],
    "sg:menulink":"http://www.allmenus.com/ca/san-jose/45729-the-original-hickory-pit/menu/",
    "sg:phone":"+1 408 371 2400",
    "sg:postcode":"95008",
    "sg:province":"CA",
    "sg:tags":[
        "barbecue",
        "american"
    ],
    "wof:name":"The Original Hickory Pit",
    "wof:placetype":"venue"
},
  "geometry": {"coordinates":[-121.932457,37.287054],"type":"Point"}
}