{
  "type": "Feature",
  "properties": {
    "addr:full":"2550 W El Camino Avenue Sacramento CA 95833",
    "addr:housenumber":"2550",
    "addr:postcode":"95833",
    "addr:street":"W El Camino Avenue",
    "iso:country":"US",
    "sg:address":"2550 W El Camino Avenue",
    "sg:city":"Sacramento",
    "sg:classifiers":[
        {
            "category":"Health Services",
            "subcategory":"Optometrist",
            "type":"Services"
        }
    ],
    "sg:phone":"+1 916 921 2020",
    "sg:postcode":"95833",
    "sg:province":"CA",
    "wof:name":"Leong Richard G Dr Optmtrst",
    "wof:placetype":"venue"
},
  "geometry": {"coordinates":[-121.518584,38.614075],"type":"Point"}
}