{
  "type": "Feature",
  "properties": {
    "addr:full":"2210 Boynton Ave Fairfield CA 94533",
    "addr:housenumber":"2210",
    "addr:postcode":"94533",
    "addr:street":"Boynton Ave",
    "iso:country":"US",
    "sg:address":"2210 Boynton Ave",
    "sg:city":"Fairfield",
    "sg:classifiers":[
        {
            "category":"Insurance",
            "subcategory":"Insurance Agent",
            "type":"Services"
        },
        {
            "category":"Insurance",
            "subcategory":"Hazard Insurance",
            "type":"Services"
        },
        {
            "category":"Insurance",
            "subcategory":"Title Insurance",
            "type":"Services"
        },
        {
            "category":"Insurance",
            "subcategory":"Life Insurance",
            "type":"Services"
        }
    ],
    "sg:phone":"+1 707 425 8045",
    "sg:postcode":"94533",
    "sg:province":"CA",
    "sg:tags":[
        "auto",
        "commercial",
        "motorcycle",
        "business",
        "homeowner"
    ],
    "sg:website":"http://solanoinsurance.net",
    "wof:name":"Solano Insurance Services Inc.",
    "wof:placetype":"venue"
},
  "geometry": {"coordinates":[-122.06622299999999,38.24984],"type":"Point"}
}