{
  "type": "Feature",
  "properties": {
    "iso:country":"US",
    "sg:address":"503 Canal Blvd. Suite A",
    "sg:city":"Point Richmond",
    "sg:classifiers":[
        {
            "category":"Professional",
            "subcategory":"Computer Services",
            "type":"Services"
        }
    ],
    "sg:phone":"+1 510 307 8228",
    "sg:postcode":"94804",
    "sg:province":"CA",
    "sg:tags":[
        "silverlight",
        "microsoft-surface",
        "web",
        "mobile",
        "software",
        "user-experience"
    ],
    "sg:website":"http://www.vertigo.com",
    "wof:name":"Vertigo",
    "wof:placetype":"venue"
},
  "geometry": {"coordinates":[-122.378281,37.924972],"type":"Point"}
}