{
  "type": "Feature",
  "properties": {
    "addr:full":"15201 Camelot Dr. San Jose CA 95132",
    "addr:housenumber":"15201",
    "addr:postcode":"95132",
    "addr:street":"Camelot Dr.",
    "iso:country":"US",
    "sg:address":"15201 Camelot Dr.",
    "sg:city":"San Jose",
    "sg:classifiers":[
        {
            "category":"Building & Trades",
            "subcategory":"Plumbing",
            "type":"Services"
        }
    ],
    "sg:phone":"+1 408 509 2772",
    "sg:postcode":"95132",
    "sg:province":"CA",
    "sg:website":"fixitplumbing.net/",
    "wof:name":"Fix-It Plumbing",
    "wof:placetype":"venue"
},
  "geometry": {"coordinates":[-121.836142,37.402556],"type":"Point"}
}