{
  "type": "Feature",
  "properties": {
    "addr:full":"7862 Sterling Dr Oakland CA 94605",
    "addr:housenumber":"7862",
    "addr:postcode":"94605",
    "addr:street":"Sterling Dr",
    "iso:country":"US",
    "sg:address":"7862 Sterling Dr",
    "sg:city":"Oakland",
    "sg:classifiers":[
        {
            "category":"Shopping",
            "subcategory":"Books",
            "type":"Retail Goods"
        }
    ],
    "sg:phone":"+1 510 562 3338",
    "sg:postcode":"94605",
    "sg:province":"CA",
    "sg:tags":[
        "dealer"
    ],
    "wof:name":"Book Junkies",
    "wof:placetype":"venue"
},
  "geometry": {"coordinates":[-122.15876299999999,37.768799],"type":"Point"}
}