{
  "type": "Feature",
  "properties": {
    "iso:country":"US",
    "sg:address":"6238 E Twin Peak Cir",
    "sg:city":"Anaheim",
    "sg:classifiers":[
        {
            "category":"Manufacturing",
            "subcategory":"Printing",
            "type":"Manufacturing & Wholesale Goods"
        }
    ],
    "sg:phone":"+1 714 615 1968",
    "sg:postcode":"92807",
    "sg:province":"CA",
    "sg:tags":[
        "periodical"
    ],
    "wof:name":"Through Gourdvine Magazine",
    "wof:placetype":"venue"
},
  "geometry": {"coordinates":[-117.775819,33.832021],"type":"Point"}
}