{
  "type": "Feature",
  "properties": {
    "addr:full":"115 Berkeley Square Berkeley CA 94709",
    "addr:housenumber":"115",
    "addr:postcode":"94709",
    "addr:street":"Berkeley Square",
    "iso:country":"US",
    "sg:address":"115 Berkeley Square",
    "sg:city":"Berkeley",
    "sg:classifiers":[
        {
            "category":"Health Services",
            "subcategory":"Dentist",
            "type":"Services"
        }
    ],
    "sg:phone":"+1 510 540 8484",
    "sg:postcode":"94709",
    "sg:province":"CA",
    "wof:name":"West Coast Dental",
    "wof:placetype":"venue"
},
  "geometry": {"coordinates":[-122.26799800000001,37.870998],"type":"Point"}
}