{
  "type": "Feature",
  "properties": {
    "addr:full":"4126 E Belmont Ave Fresno CA 93702",
    "addr:housenumber":"4126",
    "addr:postcode":"93702",
    "addr:street":"E Belmont Ave",
    "iso:country":"US",
    "sg:address":"4126 E Belmont Ave",
    "sg:city":"Fresno",
    "sg:classifiers":[
        {
            "category":"Home & Garden",
            "subcategory":"Household Appliances",
            "type":"Retail Goods"
        }
    ],
    "sg:phone":"+1 559 497 6421",
    "sg:postcode":"93702",
    "sg:province":"CA",
    "wof:name":"Good Appliance",
    "wof:placetype":"venue"
},
  "geometry": {"coordinates":[-119.754991,36.750414],"type":"Point"}
}