{
  "type": "Feature",
  "properties": {
    "addr:full":"98 Sanger Pl San Diego CA 92173",
    "addr:housenumber":"98",
    "addr:postcode":"92173",
    "addr:street":"Sanger Pl",
    "iso:country":"US",
    "sg:address":"98 Sanger Pl",
    "sg:city":"San Diego",
    "sg:classifiers":[
        {
            "category":"Travel",
            "subcategory":"Travel Agent",
            "type":"Entertainment"
        }
    ],
    "sg:phone":"+1 619 428 5311",
    "sg:postcode":"92173",
    "sg:province":"CA",
    "sg:tags":[
        "agency",
        "bureau"
    ],
    "wof:name":"Baja Trips",
    "wof:placetype":"venue"
},
  "geometry": {"coordinates":[-117.0461,32.553556],"type":"Point"}
}