{
  "type": "Feature",
  "properties": {
    "iso:country":"US",
    "sg:address":"1223 N Batavia St",
    "sg:city":"Orange",
    "sg:classifiers":[
        {
            "category":"Retail",
            "subcategory":"Auto Repair",
            "type":"Services"
        }
    ],
    "sg:phone":"+1 714 744 3687",
    "sg:postcode":"92867",
    "sg:province":"CA",
    "sg:tags":[
        "body",
        "automobile",
        "painting",
        "repairing"
    ],
    "wof:name":"Lake's Auto Shop",
    "wof:placetype":"venue"
},
  "geometry": {"coordinates":[-117.86173700000001,33.807796],"type":"Point"}
}