{
  "type": "Feature",
  "properties": {
    "addr:full":"38636 Kimbro St Fremont CA 94536",
    "addr:housenumber":"38636",
    "addr:postcode":"94536",
    "addr:street":"Kimbro St",
    "iso:country":"US",
    "sg:address":"38636 Kimbro St",
    "sg:city":"Fremont",
    "sg:classifiers":[
        {
            "category":"Real Estate",
            "subcategory":"Real Estate Agent",
            "type":"Services"
        }
    ],
    "sg:phone":"+1 510 797 4436",
    "sg:postcode":"94536",
    "sg:province":"CA",
    "wof:name":"Vincent E Wallace",
    "wof:placetype":"venue"
},
  "geometry": {"coordinates":[-121.99552199999999,37.547472],"type":"Point"}
}