{
  "type": "Feature",
  "properties": {
    "addr:full":"2290 N 1st St Ste 209b San Jose CA 95131",
    "addr:housenumber":"2290",
    "addr:postcode":"95131",
    "addr:street":"N 1St St Ste 209B",
    "iso:country":"US",
    "sg:address":"2290 N 1st St Ste 209b",
    "sg:city":"San Jose",
    "sg:classifiers":[
        {
            "category":"Insurance",
            "subcategory":"Hazard Insurance",
            "type":"Services"
        }
    ],
    "sg:phone":"+1 408 434 0640",
    "sg:postcode":"95131",
    "sg:province":"CA",
    "sg:website":"www.farmersagent.com/rbuitrago1",
    "wof:name":"Rudy Buitrago",
    "wof:placetype":"venue"
},
  "geometry": {"coordinates":[-121.92127499999999,37.378862],"type":"Point"}
}