{
  "type": "Feature",
  "properties": {
    "iso:country":"US",
    "sg:address":"2005 Citrus Ave",
    "sg:city":"Chico",
    "sg:classifiers":[
        {
            "category":"Building & Trades",
            "subcategory":"Construction",
            "type":"Services"
        }
    ],
    "sg:phone":"+1 530 345 8806",
    "sg:postcode":"95926",
    "sg:province":"CA",
    "sg:tags":[
        "house"
    ],
    "wof:name":"Chico Home Improvement",
    "wof:placetype":"venue"
},
  "geometry": {"coordinates":[-121.85608000000001,39.744206],"type":"Point"}
}