{
  "type": "Feature",
  "properties": {
    "addr:full":"601 Van Ness Avenue San Francisco CA 94102",
    "addr:housenumber":"601",
    "addr:postcode":"94102",
    "addr:street":"Van Ness Avenue",
    "iso:country":"US",
    "sg:address":"601 Van Ness Avenue",
    "sg:city":"San Francisco",
    "sg:classifiers":[
        {
            "category":"Professional",
            "subcategory":"Lawyer & Legal Services",
            "type":"Services"
        }
    ],
    "sg:phone":"+1 415 777 5501",
    "sg:postcode":"94102",
    "sg:province":"CA",
    "wof:name":"Tarkington O'connor & O'neill",
    "wof:placetype":"venue"
},
  "geometry": {"coordinates":[-122.417131,37.781234],"type":"Point"}
}