{
  "type": "Feature",
  "properties": {
    "addr:full":"8237 Allport Ave Santa Fe Springs CA 90670",
    "addr:postcode":"8237;90670",
    "addr:street":"Allport Ave",
    "iso:country":"US",
    "sg:address":"8237 Allport Ave",
    "sg:city":"Santa Fe Springs",
    "sg:classifiers":[
        {
            "category":"Manufacturing",
            "subcategory":"Printing",
            "type":"Manufacturing & Wholesale Goods"
        }
    ],
    "sg:phone":"+1 562 696 8022",
    "sg:postcode":"90670",
    "sg:province":"CA",
    "sg:tags":[
        "printer"
    ],
    "wof:name":"Fault Line Screen Printing",
    "wof:placetype":"venue"
},
  "geometry": {"coordinates":[-118.064882,33.965136],"type":"Point"}
}