{
  "type": "Feature",
  "properties": {
    "addr:full":"135 W Mission Ave Escondido CA 92025",
    "addr:housenumber":"135",
    "addr:postcode":"92025",
    "addr:street":"W Mission Ave",
    "iso:country":"US",
    "sg:address":"135 W Mission Ave",
    "sg:city":"Escondido",
    "sg:classifiers":[
        {
            "category":"Insurance",
            "subcategory":"Insurance Agent",
            "type":"Services"
        }
    ],
    "sg:phone":"+1 760 743 5393",
    "sg:postcode":"92025",
    "sg:province":"CA",
    "wof:name":"Mike Davis Insurance",
    "wof:placetype":"venue"
},
  "geometry": {"coordinates":[-117.088686,33.129242],"type":"Point"}
}