{
  "type": "Feature",
  "properties": {
    "addr:full":"3613 Sacramento St San Francisco CA 94118",
    "addr:housenumber":"3613",
    "addr:postcode":"94118",
    "addr:street":"Sacramento St",
    "iso:country":"US",
    "sg:address":"3613 Sacramento St",
    "sg:city":"San Francisco",
    "sg:classifiers":[
        {
            "category":"Professional",
            "type":"Services"
        },
        {
            "category":"Food & Beverages",
            "subcategory":"Bakery",
            "type":"Retail Goods"
        }
    ],
    "sg:phone":"+1 415 567 8640",
    "sg:postcode":"94118",
    "sg:province":"CA",
    "sg:tags":[
        "sandwich",
        "caterer"
    ],
    "sg:website":"www.dolceandsalato.com/",
    "wof:name":"Dolce & Salato",
    "wof:placetype":"venue"
},
  "geometry": {"coordinates":[-122.45228899999999,37.787492],"type":"Point"}
}