{
  "type": "Feature",
  "properties": {
    "iso:country":"US",
    "sg:address":"21039 Devonshire St",
    "sg:city":"Chatsworth",
    "sg:classifiers":[
        {
            "category":"Health Services",
            "subcategory":"Chiropractor",
            "type":"Services"
        }
    ],
    "sg:phone":"+1 818 280 2486",
    "sg:postcode":"91311",
    "sg:province":"CA",
    "sg:tags":[
        "chiropractic"
    ],
    "wof:name":"Allcare Chiropractic Center",
    "wof:placetype":"venue"
},
  "geometry": {"coordinates":[-118.591601,34.257247],"type":"Point"}
}