{
  "type": "Feature",
  "properties": {
    "iso:country":"US",
    "sg:address":"305 Old Turnpike Rd",
    "sg:city":"Los Gatos",
    "sg:classifiers":[
        {
            "category":"Professional",
            "subcategory":"Research",
            "type":"Services"
        }
    ],
    "sg:phone":"+1 408 353 8397",
    "sg:postcode":"95033",
    "sg:province":"CA",
    "wof:name":"Stanford Photothermal Solution",
    "wof:placetype":"venue"
},
  "geometry": {"coordinates":[-121.95197899999999,37.085474],"type":"Point"}
}