{
  "type": "Feature",
  "properties": {
    "addr:full":"431 Leoni Dr Grover Beach CA 93433",
    "addr:housenumber":"431",
    "addr:postcode":"93433",
    "addr:street":"Leoni Dr",
    "iso:country":"US",
    "sg:address":"431 Leoni Dr",
    "sg:city":"Grover Beach",
    "sg:classifiers":[
        {
            "category":"Manufacturing",
            "subcategory":"Jewelry",
            "type":"Manufacturing & Wholesale Goods"
        }
    ],
    "sg:phone":"+1 805 473 2562",
    "sg:postcode":"93433",
    "sg:province":"CA",
    "sg:tags":[
        "costume"
    ],
    "sg:website":"www.scarecrowinc.com",
    "wof:name":"Scarecrow Inc",
    "wof:placetype":"venue"
},
  "geometry": {"coordinates":[-120.623716,35.11337],"type":"Point"}
}