{
  "type": "Feature",
  "properties": {
    "iso:country":"US",
    "sg:address":"2030 Spyglass Dr",
    "sg:city":"San Bruno",
    "sg:classifiers":[
        {
            "category":"Autos & Motor Vehicles",
            "subcategory":"Auto Supplies",
            "type":"Retail Goods"
        }
    ],
    "sg:phone":"+1 650 355 3991",
    "sg:postcode":"94066",
    "sg:province":"CA",
    "wof:name":"Performance International",
    "wof:placetype":"venue"
},
  "geometry": {"coordinates":[-122.469493,37.63688],"type":"Point"}
}