{
  "type": "Feature",
  "properties": {
    "iso:country":"US",
    "sg:address":"5948 Auburn Blvd",
    "sg:city":"Citrus Heights",
    "sg:classifiers":[
        {
            "category":"Bars & Pubs",
            "subcategory":"Lounge",
            "type":"Food & Drink"
        },
        {
            "category":"Casinos & Gambling",
            "type":"Entertainment"
        },
        {
            "category":"Bars & Pubs",
            "subcategory":"Sports Bar",
            "type":"Food & Drink"
        }
    ],
    "sg:phone":"+1 916 331 2345",
    "sg:postcode":"95621",
    "sg:province":"CA",
    "sg:website":"www.playphoenixcasino.com",
    "wof:name":"Phoenix Casino & Lounge",
    "wof:placetype":"venue"
},
  "geometry": {"coordinates":[-121.325265,38.674533],"type":"Point"}
}