{
  "type": "Feature",
  "properties": {
    "iso:country":"US",
    "sg:address":"295 N Lake Blvd",
    "sg:city":"Sunnyside-Tahoe City",
    "sg:classifiers":[
        {
            "category":"Autos & Motor Vehicles",
            "subcategory":"Auto Supplies",
            "type":"Retail Goods"
        }
    ],
    "sg:postcode":"96146",
    "sg:province":"CA",
    "sg:tags":[
        "part"
    ],
    "wof:name":"North Lake Tahoe Auto Parts",
    "wof:placetype":"venue"
},
  "geometry": {"coordinates":[-120.14333499999999,39.169304],"type":"Point"}
}