{
  "type": "Feature",
  "properties": {
    "addr:full":"1430 Koll Cir San Jose CA 95112",
    "addr:housenumber":"1430",
    "addr:postcode":"95112",
    "addr:street":"Koll Cir",
    "iso:country":"US",
    "sg:address":"1430 Koll Cir",
    "sg:city":"San Jose",
    "sg:classifiers":[
        {
            "category":"Communications",
            "type":"Services"
        }
    ],
    "sg:phone":"+1 408 436 9451",
    "sg:postcode":"95112",
    "sg:province":"CA",
    "wof:name":"Xcel Communications",
    "wof:placetype":"venue"
},
  "geometry": {"coordinates":[-121.906767,37.365912],"type":"Point"}
}