{
  "type": "Feature",
  "properties": {
    "addr:full":"19148 Ash St Bloomington CA 92316",
    "addr:housenumber":"19148",
    "addr:postcode":"92316",
    "addr:street":"Ash St",
    "iso:country":"US",
    "sg:address":"19148 Ash St",
    "sg:city":"Bloomington",
    "sg:classifiers":[
        {
            "category":"Retail",
            "subcategory":"Auto Repair",
            "type":"Services"
        }
    ],
    "sg:phone":"+1 909 877 6477",
    "sg:postcode":"92316",
    "sg:province":"CA",
    "sg:tags":[
        "wrecker"
    ],
    "wof:name":"R C Towing Transport & Recover",
    "wof:placetype":"venue"
},
  "geometry": {"coordinates":[-117.384406,34.059048],"type":"Point"}
}