{
  "type": "Feature",
  "properties": {
    "addr:full":"19091 Pruneridge Ave Cupertino CA 95014",
    "addr:postcode":"19091;95014",
    "addr:street":"Pruneridge Ave",
    "iso:country":"US",
    "sg:address":"19091 Pruneridge Ave",
    "sg:city":"Cupertino",
    "sg:classifiers":[
        {
            "category":"Manufacturing",
            "subcategory":"Electronics",
            "type":"Manufacturing & Wholesale Goods"
        },
        {
            "category":"Shopping",
            "subcategory":"Computers & Home Electronics",
            "type":"Retail Goods"
        },
        {
            "category":"Wholesale",
            "subcategory":"Computers",
            "type":"Manufacturing & Wholesale Goods"
        }
    ],
    "sg:phone":"+1 408 447 3959",
    "sg:postcode":"95014",
    "sg:province":"CA",
    "sg:tags":[
        "printer",
        "supply",
        "equipment",
        "computer-wholesale",
        "printers-equipment",
        "manufacturer"
    ],
    "sg:website":"http://www.brma.com",
    "wof:name":"Hewlett-Packard Company",
    "wof:placetype":"venue"
},
  "geometry": {"coordinates":[-122.007003,37.3322],"type":"Point"}
}