{
  "type": "Feature",
  "properties": {
    "addr:full":"1309 Edison Dr Hanford CA 93230",
    "addr:housenumber":"1309",
    "addr:postcode":"ca 93230",
    "addr:street":"Edison Dr",
    "iso:country":"US",
    "sg:address":"1309 Edison Dr",
    "sg:city":"Hanford",
    "sg:classifiers":[
        {
            "category":"Real Estate",
            "subcategory":"Real Estate Agent",
            "type":"Services"
        }
    ],
    "sg:phone":"+1 559 585 1700",
    "sg:postcode":"93230",
    "sg:province":"CA",
    "wof:name":"Walnut Forest Estates",
    "wof:placetype":"venue"
},
  "geometry": {"coordinates":[-119.658973,36.30938],"type":"Point"}
}