{
  "type": "Feature",
  "properties": {
    "addr:full":"5201 Deer Valley Rd Antioch CA 94531",
    "addr:housenumber":"5201",
    "addr:postcode":"ca 94531",
    "addr:street":"Deer Valley Rd",
    "iso:country":"US",
    "sg:address":"5201 Deer Valley Rd",
    "sg:city":"Antioch",
    "sg:classifiers":[
        {
            "category":"Health Services",
            "subcategory":"Medical Lab",
            "type":"Services"
        }
    ],
    "sg:phone":"+1 925 757 3450",
    "sg:postcode":"94531",
    "sg:province":"CA",
    "sg:tags":[
        "laboratory"
    ],
    "wof:name":"Hutchison Dental Lab",
    "wof:placetype":"venue"
},
  "geometry": {"coordinates":[-121.782843,37.971791],"type":"Point"}
}