{
  "type": "Feature",
  "properties": {
    "iso:country":"US",
    "sg:address":"601 Las Tunas Dr Ste 101",
    "sg:city":"Arcadia",
    "sg:classifiers":[
        {
            "category":"Health Services",
            "subcategory":"Doctor",
            "type":"Services"
        }
    ],
    "sg:phone":"+1 626 462 0000",
    "sg:postcode":"91007",
    "sg:province":"CA",
    "sg:tags":[
        "obstetrician",
        "gynecologist"
    ],
    "wof:name":"Margaret Juarez MD",
    "wof:placetype":"venue"
},
  "geometry": {"coordinates":[-118.050997,34.107938],"type":"Point"}
}