{
  "type": "Feature",
  "properties": {
    "addr:full":"1026 Diamond Dr Arcata CA 95521",
    "addr:housenumber":"1026",
    "addr:postcode":"95521",
    "addr:street":"Diamond Dr",
    "iso:country":"US",
    "sg:address":"1026 Diamond Dr",
    "sg:city":"Arcata",
    "sg:classifiers":[
        {
            "category":"Building & Trades",
            "subcategory":"Construction",
            "type":"Services"
        }
    ],
    "sg:phone":"+1 707 825 6953",
    "sg:postcode":"95521",
    "sg:province":"CA",
    "sg:tags":[
        "contractor"
    ],
    "wof:name":"Brisby Construction",
    "wof:placetype":"venue"
},
  "geometry": {"coordinates":[-124.071876,40.886783],"type":"Point"}
}