{
  "type": "Feature",
  "properties": {
    "addr:full":"726 E Valley Blvd San Gabriel CA 91776",
    "addr:housenumber":"726",
    "addr:postcode":"91776",
    "addr:street":"E Valley Blvd",
    "iso:country":"US",
    "sg:address":"726 E Valley Blvd",
    "sg:city":"San Gabriel",
    "sg:classifiers":[
        {
            "category":"Shopping",
            "subcategory":"Jewelry",
            "type":"Retail Goods"
        }
    ],
    "sg:phone":"+1 626 288 9888",
    "sg:postcode":"91776",
    "sg:province":"CA",
    "wof:name":"CA Jewlery",
    "wof:placetype":"venue"
},
  "geometry": {"coordinates":[-118.041929,34.003299],"type":"Point"}
}