{
  "type": "Feature",
  "properties": {
    "addr:full":"1300 E 223rd St Carson CA 90745",
    "addr:housenumber":"1300",
    "addr:postcode":"90745",
    "addr:street":"E 223Rd St",
    "iso:country":"US",
    "sg:address":"1300 E 223rd St",
    "sg:city":"Carson",
    "sg:classifiers":[
        {
            "category":"Education",
            "subcategory":"Special Training",
            "type":"Public Place"
        }
    ],
    "sg:phone":"+1 310 834 6284",
    "sg:postcode":"90745",
    "sg:province":"CA",
    "sg:tags":[
        "tutoring"
    ],
    "wof:name":"West Carson Kumon Center",
    "wof:placetype":"venue"
},
  "geometry": {"coordinates":[-118.249888,33.8236],"type":"Point"}
}