{
  "type": "Feature",
  "properties": {
    "iso:country":"US",
    "sg:address":"222 S Irena Avenue Unit K",
    "sg:city":"Redondo Beach",
    "sg:classifiers":[
        {
            "category":"Landmark",
            "subcategory":"Tourist Information",
            "type":"Public Place"
        }
    ],
    "sg:phone":"+1 310 543 2590",
    "sg:postcode":"90277",
    "sg:province":"CA",
    "sg:tags":[
        "tour"
    ],
    "wof:name":"Overseas Motorhome Tours",
    "wof:placetype":"venue"
},
  "geometry": {"coordinates":[-118.38013599999999,33.839798],"type":"Point"}
}