{
  "type": "Feature",
  "properties": {
    "iso:country":"US",
    "sg:address":"455 Judson St",
    "sg:city":"Redlands",
    "sg:classifiers":[
        {
            "category":"Building & Trades",
            "subcategory":"Cleaning & Sanitation",
            "type":"Services"
        }
    ],
    "sg:phone":"+1 909 553 3166",
    "sg:postcode":"92374",
    "sg:province":"CA",
    "sg:tags":[
        "janitor"
    ],
    "wof:name":"Gizelle Janitorial Svc",
    "wof:placetype":"venue"
},
  "geometry": {"coordinates":[-117.156458,34.058884],"type":"Point"}
}