{
  "type": "Feature",
  "properties": {
    "addr:full":"4101 Abbott Dr Bakersfield CA 93312",
    "addr:housenumber":"4101",
    "addr:postcode":"93312",
    "addr:street":"Abbott Dr",
    "iso:country":"US",
    "sg:address":"4101 Abbott Dr",
    "sg:city":"Bakersfield",
    "sg:classifiers":[
        {
            "category":"Personal",
            "subcategory":"Beauty Salon",
            "type":"Services"
        }
    ],
    "sg:phone":"+1 661 836 1809",
    "sg:postcode":"93312",
    "sg:province":"CA",
    "wof:name":"Hair Designs By Susan",
    "wof:placetype":"venue"
},
  "geometry": {"coordinates":[-119.10694599999999,35.3966],"type":"Point"}
}