{
  "type": "Feature",
  "properties": {
    "iso:country":"US",
    "sg:address":"2125 Arden Way",
    "sg:city":"Sacramento",
    "sg:classifiers":[
        {
            "category":"Home & Garden",
            "subcategory":"Furniture",
            "type":"Retail Goods"
        }
    ],
    "sg:phone":"+1 916 925 5662",
    "sg:postcode":"95825",
    "sg:province":"CA",
    "sg:tags":[
        "store"
    ],
    "wof:name":"Furniture Showcase",
    "wof:placetype":"venue"
},
  "geometry": {"coordinates":[-121.41625000000001,38.596349],"type":"Point"}
}