{
  "type": "Feature",
  "properties": {
    "addr:full":"2620 Alum Rock Ave San Jose CA 95116",
    "addr:housenumber":"2620",
    "addr:postcode":"95116",
    "addr:street":"Alum Rock Ave",
    "iso:country":"US",
    "sg:address":"2620 Alum Rock Ave",
    "sg:city":"San Jose",
    "sg:classifiers":[
        {
            "category":"Health Services",
            "subcategory":"Medical Lab",
            "type":"Services"
        }
    ],
    "sg:phone":"+1 408 926 5625",
    "sg:postcode":"95116",
    "sg:province":"CA",
    "sg:tags":[
        "clinical",
        "testing"
    ],
    "wof:name":"Quest Diagnostic",
    "wof:placetype":"venue"
},
  "geometry": {"coordinates":[-121.83741000000001,37.361289],"type":"Point"}
}