{
  "type": "Feature",
  "properties": {
    "iso:country":"US",
    "sg:address":"331 E 9th St",
    "sg:city":"San Bernardino",
    "sg:classifiers":[
        {
            "category":"Restaurant",
            "type":"Food & Drink"
        }
    ],
    "sg:phone":"+1 909 381 9464",
    "sg:postcode":"92410",
    "sg:province":"CA",
    "sg:tags":[
        "eating"
    ],
    "wof:name":"Wing Factory",
    "wof:placetype":"venue"
},
  "geometry": {"coordinates":[-117.27515,34.115719],"type":"Point"}
}