{
  "type": "Feature",
  "properties": {
    "addr:full":"2016 Freedom Blvd Freedom CA 95019",
    "addr:housenumber":"2016",
    "addr:postcode":"95019",
    "addr:street":"Freedom Blvd",
    "iso:country":"US",
    "sg:address":"2016 Freedom Blvd",
    "sg:city":"Freedom",
    "sg:classifiers":[
        {
            "category":"Health Services",
            "subcategory":"Doctor",
            "type":"Services"
        }
    ],
    "sg:phone":"+1 831 722 1786",
    "sg:postcode":"95019",
    "sg:province":"CA",
    "sg:tags":[
        "dentist"
    ],
    "wof:name":"Del Sol Dental",
    "wof:placetype":"venue"
},
  "geometry": {"coordinates":[-121.777824,36.938379],"type":"Point"}
}