{
  "type": "Feature",
  "properties": {
    "addr:full":"505 Arcade Dr Ventura CA 93003",
    "addr:housenumber":"505",
    "addr:postcode":"93003",
    "addr:street":"Arcade Dr",
    "iso:country":"US",
    "sg:address":"505 Arcade Dr",
    "sg:city":"Ventura",
    "sg:classifiers":[
        {
            "category":"Retail",
            "subcategory":"Animal Services",
            "type":"Services"
        }
    ],
    "sg:phone":"+1 805 643 5518",
    "sg:postcode":"93003",
    "sg:province":"CA",
    "wof:name":"Aleta & Pams Pampered Pooch",
    "wof:placetype":"venue"
},
  "geometry": {"coordinates":[-119.26652,34.269078],"type":"Point"}
}