{
  "type": "Feature",
  "properties": {
    "iso:country":"US",
    "sg:address":"6957 Reseda Blvd",
    "sg:city":"Reseda",
    "sg:classifiers":[
        {
            "category":"Autos & Motor Vehicles",
            "subcategory":"Auto Supplies",
            "type":"Retail Goods"
        },
        {
            "category":"Retail",
            "subcategory":"Auto Repair",
            "type":"Services"
        }
    ],
    "sg:phone":"+1 818 996 9940",
    "sg:postcode":"91335",
    "sg:province":"CA",
    "sg:tags":[
        "lettering",
        "automobile",
        "body",
        "dent",
        "truck",
        "removal",
        "painting",
        "repairing"
    ],
    "wof:name":"Hart Auto Body",
    "wof:placetype":"venue"
},
  "geometry": {"coordinates":[-118.536041,34.196714],"type":"Point"}
}