{
  "type": "Feature",
  "properties": {
    "addr:full":"1130 el Medio Ave Pacific Plsds CA 90272",
    "addr:housenumber":"1130",
    "addr:postcode":"90272",
    "addr:street":"El Medio Ave",
    "iso:country":"US",
    "sg:address":"1130 el Medio Ave",
    "sg:city":"Pacific Plsds",
    "sg:classifiers":[
        {
            "category":"Professional",
            "type":"Services"
        }
    ],
    "sg:phone":"+1 323 954 6464",
    "sg:postcode":"90272",
    "sg:province":"CA",
    "sg:tags":[
        "establishment"
    ],
    "wof:name":"Stun",
    "wof:placetype":"venue"
},
  "geometry": {"coordinates":[-118.533709,34.055402],"type":"Point"}
}