{
  "type": "Feature",
  "properties": {
    "addr:full":"2132 E Montclair Plaza Ln Montclair CA 91763",
    "addr:housenumber":"2132",
    "addr:postcode":"91763",
    "addr:street":"E Montclair Plaza Ln",
    "iso:country":"US",
    "sg:address":"2132 E Montclair Plaza Ln",
    "sg:city":"Montclair",
    "sg:classifiers":[
        {
            "category":"Shopping",
            "subcategory":"Clothing, Apparel, & Fashions",
            "type":"Retail Goods"
        }
    ],
    "sg:phone":"+1 909 621 1772",
    "sg:postcode":"91763",
    "sg:province":"CA",
    "wof:name":"Limited Express",
    "wof:placetype":"venue"
},
  "geometry": {"coordinates":[-117.696579,34.087387],"type":"Point"}
}