{
  "type": "Feature",
  "properties": {
    "addr:full":"2456 Amaryl Dr San Jose CA 95132",
    "addr:housenumber":"2456",
    "addr:postcode":"95132",
    "addr:street":"Amaryl Dr",
    "iso:country":"US",
    "sg:address":"2456 Amaryl Dr",
    "sg:city":"San Jose",
    "sg:classifiers":[
        {
            "category":"Shopping",
            "subcategory":"Gifts & Souvenirs",
            "type":"Retail Goods"
        }
    ],
    "sg:phone":"+1 408 926 3759",
    "sg:postcode":"95132",
    "sg:province":"CA",
    "wof:name":"Wonderpond Gifts",
    "wof:placetype":"venue"
},
  "geometry": {"coordinates":[-121.86423000000001,37.391854],"type":"Point"}
}