{
  "type": "Feature",
  "properties": {
    "addr:full":"1018 W. Collins Ave Orange CA 92867",
    "addr:housenumber":"1018",
    "addr:postcode":"92867",
    "addr:street":"W. Collins Ave",
    "iso:country":"US",
    "sg:address":"1018 W. Collins Ave",
    "sg:city":"Orange",
    "sg:classifiers":[
        {
            "category":"Building & Trades",
            "subcategory":"Construction",
            "type":"Services"
        }
    ],
    "sg:phone":"+1 714 997 1907",
    "sg:postcode":"92867",
    "sg:province":"CA",
    "sg:tags":[
        "contractor"
    ],
    "wof:name":"McDe's Concrete Pumping",
    "wof:placetype":"venue"
},
  "geometry": {"coordinates":[-117.863703,33.802389],"type":"Point"}
}