{
  "type": "Feature",
  "properties": {
    "addr:full":"81 Madrona St San Carlos CA 94070",
    "addr:housenumber":"81",
    "addr:postcode":"94070",
    "addr:street":"Madrona St",
    "iso:country":"US",
    "sg:address":"81 Madrona St",
    "sg:city":"San Carlos",
    "sg:classifiers":[
        {
            "category":"Building & Trades",
            "subcategory":"Construction",
            "type":"Services"
        }
    ],
    "sg:phone":"+1 650 595 4533",
    "sg:postcode":"94070",
    "sg:province":"CA",
    "sg:tags":[
        "painter"
    ],
    "wof:name":"Edgewood Painting Inc",
    "wof:placetype":"venue"
},
  "geometry": {"coordinates":[-122.271004,37.504799],"type":"Point"}
}