{
  "type": "Feature",
  "properties": {
    "addr:full":"19937 Valley View Dr Topanga CA 90290",
    "addr:housenumber":"19937",
    "addr:postcode":"90290",
    "addr:street":"Valley View Dr",
    "iso:country":"US",
    "sg:address":"19937 Valley View Dr",
    "sg:city":"Topanga",
    "sg:classifiers":[
        {
            "category":"Shopping",
            "subcategory":"Catalog Store",
            "type":"Retail Goods"
        }
    ],
    "sg:phone":"+1 310 455 2969",
    "sg:postcode":"90290",
    "sg:province":"CA",
    "sg:tags":[
        "development",
        "product",
        "reading",
        "for",
        "health",
        "education"
    ],
    "wof:name":"Preception Dynamics Institute",
    "wof:placetype":"venue"
},
  "geometry": {"coordinates":[-118.605042,34.083634],"type":"Point"}
}