{
  "type": "Feature",
  "properties": {
    "iso:country":"US",
    "sg:address":"6622 Bell Bluff Ave",
    "sg:city":"San Diego",
    "sg:classifiers":[
        {
            "category":"Building & Trades",
            "subcategory":"Construction",
            "type":"Services"
        }
    ],
    "sg:phone":"+1 619 582 0109",
    "sg:postcode":"92119",
    "sg:province":"CA",
    "sg:tags":[
        "contractor"
    ],
    "wof:name":"Paradise Roofing Co",
    "wof:placetype":"venue"
},
  "geometry": {"coordinates":[-117.05429599999999,32.815324],"type":"Point"}
}