{
  "type": "Feature",
  "properties": {
    "addr:full":"7001 World Way W Los Angeles CA 90045",
    "addr:housenumber":"7001",
    "addr:postcode":"90045",
    "addr:street":"World Way W",
    "iso:country":"US",
    "sg:address":"7001 World Way W",
    "sg:city":"Los Angeles",
    "sg:classifiers":[
        {
            "category":"Airline",
            "type":"Transportation"
        }
    ],
    "sg:phone":"+1 310 645 3866",
    "sg:postcode":"90045",
    "sg:province":"CA",
    "sg:tags":[
        "scheduled",
        "company",
        "air"
    ],
    "wof:name":"American Sales and Management",
    "wof:placetype":"venue"
},
  "geometry": {"coordinates":[-118.411143,33.942488],"type":"Point"}
}