{
  "type": "Feature",
  "properties": {
    "addr:full":"4940 Sepulveda Boulevard Culver City CA 90230",
    "addr:housenumber":"4940",
    "addr:postcode":"90230",
    "addr:street":"Sepulveda Boulevard",
    "iso:country":"US",
    "sg:address":"4940 Sepulveda Boulevard",
    "sg:city":"Culver City",
    "sg:classifiers":[
        {
            "category":"Retail",
            "subcategory":"Auto Rental",
            "type":"Services"
        }
    ],
    "sg:phone":"+1 310 390 9641",
    "sg:postcode":"90230",
    "sg:province":"CA",
    "sg:tags":[
        "car"
    ],
    "sg:website":"www.enterprise.com",
    "wof:name":"Enterprise Rent-A-Car",
    "wof:placetype":"venue"
},
  "geometry": {"coordinates":[-118.40188000000001,33.999968],"type":"Point"}
}