{
  "type": "Feature",
  "properties": {
    "addr:full":"4174 Digger Pine Dr Mariposa CA 95338",
    "addr:postcode":"4174;95338",
    "addr:street":"Digger Pine Dr",
    "iso:country":"US",
    "sg:address":"4174 Digger Pine Dr",
    "sg:city":"Mariposa",
    "sg:classifiers":[
        {
            "category":"Retail",
            "subcategory":"Animal Services",
            "type":"Services"
        }
    ],
    "sg:phone":"+1 209 966 2870",
    "sg:postcode":"95338",
    "sg:province":"CA",
    "wof:name":"Kinbridge Alpacas",
    "wof:placetype":"venue"
},
  "geometry": {"coordinates":[-119.97901899999999,37.421591],"type":"Point"}
}