{
  "type": "Feature",
  "properties": {
    "addr:full":"3846 5th Ave San Diego CA 92103",
    "addr:housenumber":"3846",
    "addr:postcode":"92103",
    "addr:street":"5Th Ave",
    "iso:country":"US",
    "sg:address":"3846 5th Ave",
    "sg:city":"San Diego",
    "sg:classifiers":[
        {
            "category":"Personal",
            "subcategory":"Beauty Salon",
            "type":"Services"
        }
    ],
    "sg:phone":"+1 619 291 7511",
    "sg:postcode":"92103",
    "sg:province":"CA",
    "sg:tags":[
        "hair"
    ],
    "sg:website":"www.jetrhys.com",
    "wof:name":"Jet Rhys Hair Salon",
    "wof:placetype":"venue"
},
  "geometry": {"coordinates":[-117.160004,32.747799],"type":"Point"}
}