{
  "type": "Feature",
  "properties": {
    "iso:country":"US",
    "sg:address":"5900 Entrada Ave",
    "sg:city":"Atascadero",
    "sg:classifiers":[
        {
            "category":"Professional",
            "subcategory":"Advertising",
            "type":"Services"
        }
    ],
    "sg:phone":"+1 805 466 6680",
    "sg:postcode":"93422",
    "sg:province":"CA",
    "sg:tags":[
        "mail"
    ],
    "sg:website":"www.thepaperworks.com",
    "wof:name":"Paper Works",
    "wof:placetype":"venue"
},
  "geometry": {"coordinates":[-120.66873699999999,35.490096],"type":"Point"}
}