{
  "type": "Feature",
  "properties": {
    "addr:full":"24002 Via Fabricante Unit 510 Mission Viejo CA 92691",
    "addr:housenumber":"24002;510",
    "addr:postcode":"92691",
    "addr:street":"Via Fabricante Unit",
    "iso:country":"US",
    "sg:address":"24002 Via Fabricante Unit 510",
    "sg:city":"Mission Viejo",
    "sg:classifiers":[
        {
            "category":"Retail",
            "subcategory":"Auto Repair",
            "type":"Services"
        }
    ],
    "sg:phone":"+1 949 855 6700",
    "sg:postcode":"92691",
    "sg:province":"CA",
    "wof:name":"Saddleback Cars",
    "wof:placetype":"venue"
},
  "geometry": {"coordinates":[-117.68124400000001,33.615231],"type":"Point"}
}