{
  "type": "Feature",
  "properties": {
    "iso:country":"US",
    "sg:address":"2461 W Washington Blvd",
    "sg:city":"Los Angeles",
    "sg:classifiers":[
        {
            "category":"Wholesale",
            "subcategory":"Auto Parts",
            "type":"Manufacturing & Wholesale Goods"
        }
    ],
    "sg:phone":"+1 323 737 0833",
    "sg:postcode":"90018",
    "sg:province":"CA",
    "wof:name":"Astp",
    "wof:placetype":"venue"
},
  "geometry": {"coordinates":[-118.31769799999999,34.039912],"type":"Point"}
}