{
  "type": "Feature",
  "properties": {
    "addr:full":"4388 Tujunga Ave Studio City CA 91604",
    "addr:housenumber":"4388",
    "addr:postcode":"91604",
    "addr:street":"Tujunga Ave",
    "iso:country":"US",
    "sg:address":"4388 Tujunga Ave",
    "sg:city":"Studio City",
    "sg:classifiers":[
        {
            "category":"Autos & Motor Vehicles",
            "subcategory":"Fuel & Gas Station",
            "type":"Retail Goods"
        }
    ],
    "sg:phone":"+1 818 769 9090",
    "sg:postcode":"91604",
    "sg:province":"CA",
    "sg:tags":[
        "oil"
    ],
    "wof:name":"Eytan Enterprise Inc",
    "wof:placetype":"venue"
},
  "geometry": {"coordinates":[-118.378905,34.148824],"type":"Point"}
}