{
  "type": "Feature",
  "properties": {
    "iso:country":"US",
    "sg:address":"1224 Adams St",
    "sg:city":"St Helena",
    "sg:classifiers":[
        {
            "category":"Shopping",
            "subcategory":"Clothing, Apparel, & Fashions",
            "type":"Retail Goods"
        }
    ],
    "sg:phone":"+1 707 963 9042",
    "sg:postcode":"94574",
    "sg:province":"CA",
    "sg:tags":[
        "sportswear"
    ],
    "wof:name":"Sportago",
    "wof:placetype":"venue"
},
  "geometry": {"coordinates":[-122.47057700000001,38.505131],"type":"Point"}
}