{
  "type": "Feature",
  "properties": {
    "addr:full":"8550 Production Ave San Diego CA 92121",
    "addr:housenumber":"8550",
    "addr:postcode":"92121",
    "addr:street":"Production Ave",
    "iso:country":"US",
    "sg:address":"8550 Production Ave",
    "sg:city":"San Diego",
    "sg:classifiers":[
        {
            "category":"Manufacturing",
            "subcategory":"Chemicals & Compounds",
            "type":"Manufacturing & Wholesale Goods"
        }
    ],
    "sg:phone":"+1 858 621 9021",
    "sg:postcode":"92121",
    "sg:province":"CA",
    "sg:tags":[
        "mfg"
    ],
    "wof:name":"R & R Distributors",
    "wof:placetype":"venue"
},
  "geometry": {"coordinates":[-117.165164,32.884865],"type":"Point"}
}