{
  "type": "Feature",
  "properties": {
    "addr:full":"627 Dudley Rd French Camp CA 95231",
    "addr:housenumber":"627",
    "addr:postcode":"95231",
    "addr:street":"Dudley Rd",
    "iso:country":"US",
    "sg:address":"627 Dudley Rd",
    "sg:city":"French Camp",
    "sg:classifiers":[
        {
            "category":"Building & Trades",
            "subcategory":"Construction",
            "type":"Services"
        }
    ],
    "sg:phone":"+1 209 983 8628",
    "sg:postcode":"95231",
    "sg:province":"CA",
    "sg:tags":[
        "downspouts",
        "house",
        "gutter"
    ],
    "wof:name":"Quality Home Impovement Co",
    "wof:placetype":"venue"
},
  "geometry": {"coordinates":[-121.255819,37.880854],"type":"Point"}
}