{
  "type": "Feature",
  "properties": {
    "addr:full":"3031 Wilson Rd Bakersfield CA 93304",
    "addr:housenumber":"3031",
    "addr:postcode":"93304",
    "addr:street":"Wilson Rd",
    "iso:country":"US",
    "sg:address":"3031 Wilson Rd",
    "sg:city":"Bakersfield",
    "sg:classifiers":[
        {
            "category":"Retail",
            "subcategory":"Laundry & Dry Cleaning",
            "type":"Services"
        }
    ],
    "sg:phone":"+1 661 836 3399",
    "sg:postcode":"93304",
    "sg:province":"CA",
    "sg:tags":[
        "cleaners"
    ],
    "wof:name":"Waterfall Cleaners",
    "wof:placetype":"venue"
},
  "geometry": {"coordinates":[-119.037173,35.332135],"type":"Point"}
}