{
  "type": "Feature",
  "properties": {
    "addr:full":"1411 N Grand Ave Covina CA 91724",
    "addr:housenumber":"1411",
    "addr:postcode":"91724",
    "addr:street":"N Grand Ave",
    "iso:country":"US",
    "sg:address":"1411 N Grand Ave",
    "sg:city":"Covina",
    "sg:classifiers":[
        {
            "category":"Wholesale",
            "subcategory":"Home Furnishings",
            "type":"Manufacturing & Wholesale Goods"
        }
    ],
    "sg:phone":"+1 626 246 5478",
    "sg:postcode":"91724",
    "sg:province":"CA",
    "wof:name":"Able TEC Inc",
    "wof:placetype":"venue"
},
  "geometry": {"coordinates":[-117.872432,34.105115],"type":"Point"}
}