{
  "type": "Feature",
  "properties": {
    "iso:country":"US",
    "sg:address":"26081 Merit Cir",
    "sg:city":"Laguna Hills",
    "sg:classifiers":[
        {
            "category":"Wholesale",
            "subcategory":"Fruits & Vegetables",
            "type":"Manufacturing & Wholesale Goods"
        }
    ],
    "sg:phone":"+1 949 367 0281",
    "sg:postcode":"92653",
    "sg:province":"CA",
    "sg:tags":[
        "veggie"
    ],
    "wof:name":"Hellman J Produce Inc",
    "wof:placetype":"venue"
},
  "geometry": {"coordinates":[-117.67451,33.574188],"type":"Point"}
}