{
  "type": "Feature",
  "properties": {
    "iso:country":"US",
    "sg:address":"1551 N Tustin Ave",
    "sg:city":"Santa Ana",
    "sg:classifiers":[
        {
            "category":"Banks & Credit Unions",
            "subcategory":"Bank",
            "type":"Services"
        }
    ],
    "sg:phone":"+1 714 479 1300",
    "sg:postcode":"92705",
    "sg:province":"CA",
    "sg:tags":[
        "financing"
    ],
    "wof:name":"A-L Financial Corp",
    "wof:placetype":"venue"
},
  "geometry": {"coordinates":[-117.834125,33.752201],"type":"Point"}
}