{
  "type": "Feature",
  "properties": {
    "addr:full":"4520 W Eight Mile Rd Stockton CA 95209",
    "addr:housenumber":"4520",
    "addr:postcode":"95209",
    "addr:street":"W Eight Mile Rd",
    "iso:country":"US",
    "sg:address":"4520 W Eight Mile Rd",
    "sg:city":"Stockton",
    "sg:classifiers":[
        {
            "category":"Government",
            "subcategory":"Office",
            "type":"Public Place"
        }
    ],
    "sg:phone":"+1 209 953 8800",
    "sg:postcode":"95209",
    "sg:province":"CA",
    "sg:tags":[
        "executive"
    ],
    "wof:name":"Oak Grove Regional Park",
    "wof:placetype":"venue"
},
  "geometry": {"coordinates":[-121.372803,38.057836],"type":"Point"}
}