{
  "type": "Feature",
  "properties": {
    "addr:full":"11219 Sawyer Ave Oakdale CA 95361",
    "addr:housenumber":"11219",
    "addr:postcode":"95361",
    "addr:street":"Sawyer Ave",
    "iso:country":"US",
    "sg:address":"11219 Sawyer Ave",
    "sg:city":"Oakdale",
    "sg:classifiers":[
        {
            "category":"Building & Trades",
            "subcategory":"Equipment Rental",
            "type":"Services"
        }
    ],
    "sg:phone":"+1 209 848 0920",
    "sg:postcode":"95361",
    "sg:province":"CA",
    "sg:tags":[
        "carpet",
        "cleaning",
        "rug"
    ],
    "wof:name":"Rug Doctor",
    "wof:placetype":"venue"
},
  "geometry": {"coordinates":[-120.905108,37.803434],"type":"Point"}
}