{
  "type": "Feature",
  "properties": {
    "addr:full":"132 Harbor Way Santa Barbara CA 93109",
    "addr:housenumber":"132",
    "addr:postcode":"93109",
    "addr:street":"Harbor Way",
    "iso:country":"US",
    "sg:address":"132 Harbor Way",
    "sg:city":"Santa Barbara",
    "sg:classifiers":[
        {
            "category":"Autos & Motor Vehicles",
            "subcategory":"Boat Sales",
            "type":"Retail Goods"
        }
    ],
    "sg:phone":"+1 805 965 4538",
    "sg:postcode":"93109",
    "sg:province":"CA",
    "sg:tags":[
        "yacht",
        "broker"
    ],
    "sg:website":"www.chandlery.com",
    "wof:name":"Chandlery",
    "wof:placetype":"venue"
},
  "geometry": {"coordinates":[-119.69431400000001,34.403704],"type":"Point"}
}