{
  "type": "Feature",
  "properties": {
    "iso:country":"US",
    "sg:address":"1852 W 11th St",
    "sg:city":"Tracy",
    "sg:classifiers":[
        {
            "category":"Shopping",
            "subcategory":"Gifts & Souvenirs",
            "type":"Retail Goods"
        }
    ],
    "sg:phone":"+1 209 830 7588",
    "sg:postcode":"95376",
    "sg:province":"CA",
    "sg:tags":[
        "party",
        "supply"
    ],
    "wof:name":"JNB Enterprises",
    "wof:placetype":"venue"
},
  "geometry": {"coordinates":[-121.446525,37.739497],"type":"Point"}
}