{
  "type": "Feature",
  "properties": {
    "addr:full":"1310 Noia Ave Antioch CA 94509",
    "addr:housenumber":"1310",
    "addr:postcode":"ca 94509",
    "addr:street":"Noia Ave",
    "iso:country":"US",
    "sg:address":"1310 Noia Ave",
    "sg:city":"Antioch",
    "sg:classifiers":[
        {
            "category":"Shopping",
            "subcategory":"Hobbies, Toys, & Games",
            "type":"Retail Goods"
        }
    ],
    "sg:phone":"+1 925 779 1665",
    "sg:postcode":"94509",
    "sg:province":"CA",
    "wof:name":"Hawks RC Raceway & Hobby Shop",
    "wof:placetype":"venue"
},
  "geometry": {"coordinates":[-121.798198,38.008195],"type":"Point"}
}