{
  "type": "Feature",
  "properties": {
    "iso:country":"US",
    "sg:address":"124 Belvedere St",
    "sg:city":"San Rafael",
    "sg:classifiers":[
        {
            "category":"Professional",
            "subcategory":"Business Services",
            "type":"Services"
        }
    ],
    "sg:phone":"+1 415 455 8211",
    "sg:postcode":"94901",
    "sg:province":"CA",
    "sg:tags":[
        "embroidery"
    ],
    "wof:name":"G & G Monogram",
    "wof:placetype":"venue"
},
  "geometry": {"coordinates":[-122.50625700000001,37.963542],"type":"Point"}
}