{
  "type": "Feature",
  "properties": {
    "iso:country":"US",
    "sg:address":"21159 Calistoga St",
    "sg:city":"Middletown",
    "sg:classifiers":[
        {
            "category":"Personal",
            "subcategory":"Barber",
            "type":"Services"
        }
    ],
    "sg:phone":"+1 707 987 2281",
    "sg:postcode":"95461",
    "sg:province":"CA",
    "wof:name":"Middletown Barber Shop",
    "wof:placetype":"venue"
},
  "geometry": {"coordinates":[-122.615118,38.752733],"type":"Point"}
}