{
  "type": "Feature",
  "properties": {
    "iso:country":"US",
    "sg:address":"101 Industrial Way",
    "sg:city":"Belmont",
    "sg:classifiers":[
        {
            "category":"Shopping",
            "subcategory":"Gifts & Souvenirs",
            "type":"Retail Goods"
        }
    ],
    "sg:phone":"+1 650 622 9649",
    "sg:postcode":"94002",
    "sg:province":"CA",
    "sg:tags":[
        "party",
        "supply"
    ],
    "wof:name":"E Party Unlimited",
    "wof:placetype":"venue"
},
  "geometry": {"coordinates":[-122.402327,37.658218],"type":"Point"}
}