{
  "type": "Feature",
  "properties": {
    "iso:country":"US",
    "sg:address":"13311 Garden Grove Blvd",
    "sg:city":"Garden Grove",
    "sg:classifiers":[
        {
            "category":"Home & Garden",
            "subcategory":"Household Appliances",
            "type":"Retail Goods"
        }
    ],
    "sg:phone":"+1 714 750 5540",
    "sg:postcode":"92843",
    "sg:province":"CA",
    "sg:tags":[
        "cleaners",
        "vacuum"
    ],
    "wof:name":"Elite Systems",
    "wof:placetype":"venue"
},
  "geometry": {"coordinates":[-117.903032,33.774445],"type":"Point"}
}