{
  "type": "Feature",
  "properties": {
    "addr:full":"101 Kalmus Dr Costa Mesa CA 92626",
    "addr:housenumber":"101",
    "addr:postcode":"92626",
    "addr:street":"Kalmus Dr",
    "iso:country":"US",
    "sg:address":"101 Kalmus Dr",
    "sg:city":"Costa Mesa",
    "sg:classifiers":[
        {
            "category":"Building & Trades",
            "subcategory":"Construction",
            "type":"Services"
        }
    ],
    "sg:phone":"+1 949 272 9328",
    "sg:postcode":"92626",
    "sg:province":"CA",
    "sg:tags":[
        "contractor"
    ],
    "sg:website":"bit.ly/aXeptR",
    "wof:name":"EverGreen Garage Door",
    "wof:placetype":"venue"
},
  "geometry": {"coordinates":[-117.883869,33.673043],"type":"Point"}
}