{
  "type": "Feature",
  "properties": {
    "addr:full":"4981 Cloutier Dr Oakdale CA 95368",
    "addr:housenumber":"4981",
    "addr:postcode":"95368",
    "addr:street":"Cloutier Dr",
    "iso:country":"US",
    "sg:address":"4981 Cloutier Dr",
    "sg:city":"Oakdale",
    "sg:classifiers":[
        {
            "category":"Building & Trades",
            "subcategory":"Construction",
            "type":"Services"
        }
    ],
    "sg:phone":"+1 209 847 6401",
    "sg:postcode":"95368",
    "sg:province":"CA",
    "sg:tags":[
        "dry wall",
        "contractor"
    ],
    "wof:name":"Western Drywall Inc",
    "wof:placetype":"venue"
},
  "geometry": {"coordinates":[-121.083884,37.708259],"type":"Point"}
}