{
  "type": "Feature",
  "properties": {
    "addr:full":"42540 6th St E Lancaster CA 93535",
    "addr:housenumber":"42540",
    "addr:postcode":"93535",
    "addr:street":"6Th St E",
    "iso:country":"US",
    "sg:address":"42540 6th St E",
    "sg:city":"Lancaster",
    "sg:classifiers":[
        {
            "category":"Autos & Motor Vehicles",
            "subcategory":"Auto Supplies",
            "type":"Retail Goods"
        }
    ],
    "sg:phone":"+1 661 965 1840",
    "sg:postcode":"93535",
    "sg:province":"CA",
    "sg:tags":[
        "automobile",
        "part",
        "accessory"
    ],
    "wof:name":"Extreme Auto Body Parts & Accessories",
    "wof:placetype":"venue"
},
  "geometry": {"coordinates":[-118.118939,34.655686],"type":"Point"}
}