{
  "type": "Feature",
  "properties": {
    "addr:full":"535 Mehlschau Rd Nipomo CA 93444",
    "addr:housenumber":"535",
    "addr:postcode":"93444",
    "addr:street":"Mehlschau Rd",
    "iso:country":"US",
    "sg:address":"535 Mehlschau Rd",
    "sg:city":"Nipomo",
    "sg:classifiers":[
        {
            "category":"Place Of Worship",
            "subcategory":"Church",
            "type":"Public Place"
        },
        {
            "category":"Shopping",
            "subcategory":"Party Supplies",
            "type":"Retail Goods"
        },
        {
            "category":"Retail",
            "subcategory":"Event Space",
            "type":"Services"
        },
        {
            "category":"Personal",
            "type":"Services"
        },
        {
            "category":"Recreation",
            "type":"Entertainment"
        }
    ],
    "sg:phone":"+1 805 929 3939",
    "sg:postcode":"93444",
    "sg:province":"CA",
    "sg:tags":[
        "ceremony",
        "facility",
        "consultant",
        "hall",
        "planning",
        "marriage",
        "reception",
        "wedding",
        "banquet",
        "chapel"
    ],
    "wof:name":"Dana-Powers House",
    "wof:placetype":"venue"
},
  "geometry": {"coordinates":[-120.475319,35.060965],"type":"Point"}
}