{
  "type": "Feature",
  "properties": {
    "addr:full":"452 S Main St Willits CA 95490",
    "addr:housenumber":"452",
    "addr:postcode":"95490",
    "addr:street":"S Main St",
    "iso:country":"US",
    "sg:address":"452 S Main St",
    "sg:city":"Willits",
    "sg:classifiers":[
        {
            "category":"Travel",
            "subcategory":"Hotels & Motels",
            "type":"Entertainment"
        }
    ],
    "sg:phone":"+1 707 459 2231",
    "sg:postcode":"95490",
    "sg:province":"CA",
    "wof:name":"Pepperwood Motel",
    "wof:placetype":"venue"
},
  "geometry": {"coordinates":[-123.352395,39.407085],"type":"Point"}
}