{
  "type": "Feature",
  "properties": {
    "iso:country":"US",
    "sg:address":"6915 Sunkist Dr",
    "sg:city":"Oakland",
    "sg:classifiers":[
        {
            "category":"Organizations",
            "subcategory":"Religious Organization",
            "type":"Services"
        }
    ],
    "sg:phone":"+1 510 636 9323",
    "sg:postcode":"94605",
    "sg:province":"CA",
    "sg:tags":[
        "church"
    ],
    "wof:name":"Greater Emanuel Baptist Church",
    "wof:placetype":"venue"
},
  "geometry": {"coordinates":[-122.16791600000001,37.774003],"type":"Point"}
}