{
  "type": "Feature",
  "properties": {
    "addr:full":"7830 Trade St San Diego CA 92121",
    "addr:housenumber":"7830",
    "addr:postcode":"92121",
    "addr:street":"Trade St",
    "iso:country":"US",
    "sg:address":"7830 Trade St",
    "sg:city":"San Diego",
    "sg:classifiers":[
        {
            "category":"Manufacturing",
            "subcategory":"Motor Vehicles & Parts",
            "type":"Manufacturing & Wholesale Goods"
        }
    ],
    "sg:phone":"+1 858 530 0353",
    "sg:postcode":"92121",
    "sg:province":"CA",
    "sg:tags":[
        "automotive",
        "mfg"
    ],
    "wof:name":"Neal Brothers Inc",
    "wof:placetype":"venue"
},
  "geometry": {"coordinates":[-117.152894,32.889171],"type":"Point"}
}