{
  "type": "Feature",
  "properties": {
    "addr:full":"2224 Crenshaw Blvd Los Angeles CA 90016",
    "addr:housenumber":"2224",
    "addr:postcode":"90016",
    "addr:street":"Crenshaw Blvd",
    "iso:country":"US",
    "sg:address":"2224 Crenshaw Blvd",
    "sg:city":"Los Angeles",
    "sg:classifiers":[
        {
            "category":"Professional",
            "type":"Services"
        }
    ],
    "sg:phone":"+1 323 733 1324",
    "sg:postcode":"90016",
    "sg:province":"CA",
    "wof:name":"Volkomen Strasse",
    "wof:placetype":"venue"
},
  "geometry": {"coordinates":[-118.331416,34.039541],"type":"Point"}
}