{
  "type": "Feature",
  "properties": {
    "addr:full":"42100 Boscell Rd Fremont CA 94538",
    "addr:housenumber":"42100",
    "addr:postcode":"94538",
    "addr:street":"Boscell Rd",
    "iso:country":"US",
    "sg:address":"42100 Boscell Rd",
    "sg:city":"Fremont",
    "sg:classifiers":[
        {
            "category":"Building & Trades",
            "subcategory":"Landscaping Services",
            "type":"Services"
        }
    ],
    "sg:phone":"+1 510 353 1320",
    "sg:postcode":"94538",
    "sg:province":"CA",
    "sg:tags":[
        "house",
        "construction",
        "landscape",
        "contractor"
    ],
    "wof:name":"Capital Landscape Construction",
    "wof:placetype":"venue"
},
  "geometry": {"coordinates":[-121.984381,37.510587],"type":"Point"}
}