{
  "type": "Feature",
  "properties": {
    "iso:country":"US",
    "sg:address":"13285 Winfield St",
    "sg:city":"Panorama City",
    "sg:classifiers":[
        {
            "category":"Freight",
            "type":"Transportation"
        }
    ],
    "sg:phone":"+1 818 901 8888",
    "sg:postcode":"91402",
    "sg:province":"CA",
    "sg:tags":[
        "courier"
    ],
    "wof:name":"Instant Courier Svc",
    "wof:placetype":"venue"
},
  "geometry": {"coordinates":[-118.421876,34.225565],"type":"Point"}
}