{
  "type": "Feature",
  "properties": {
    "iso:country":"US",
    "sg:address":"4439 Olney St",
    "sg:city":"San Diego",
    "sg:classifiers":[
        {
            "category":"Social Services",
            "type":"Services"
        }
    ],
    "sg:phone":"+1 858 490 3850",
    "sg:postcode":"92109",
    "sg:province":"CA",
    "sg:tags":[
        "organization",
        "welfare"
    ],
    "wof:name":"Homeless Outreach Team",
    "wof:placetype":"venue"
},
  "geometry": {"coordinates":[-117.229434,32.801055],"type":"Point"}
}