{
  "type": "Feature",
  "properties": {
    "iso:country":"US",
    "sg:address":"2303 Ygnacio Valley Rd",
    "sg:city":"Walnut Creek",
    "sg:classifiers":[
        {
            "category":"Education",
            "subcategory":"School",
            "type":"Public Place"
        }
    ],
    "sg:phone":"+1 925 954 6322",
    "sg:postcode":"94598",
    "sg:province":"CA",
    "wof:name":"North Creek Academy & Preschl",
    "wof:placetype":"venue"
},
  "geometry": {"coordinates":[-122.024261,37.924346],"type":"Point"}
}