{
  "type": "Feature",
  "properties": {
    "addr:full":"5939 Balboa Ave. San Diego CA 92111",
    "addr:housenumber":"5939",
    "addr:postcode":"92111",
    "addr:street":"Balboa Ave.",
    "iso:country":"US",
    "sg:address":"5939 Balboa Ave.",
    "sg:city":"San Diego",
    "sg:classifiers":[
        {
            "category":"Real Estate",
            "subcategory":"Real Estate Services",
            "type":"Services"
        },
        {
            "category":"Education",
            "subcategory":"School",
            "type":"Public Place"
        }
    ],
    "sg:phone":"+1 858 571 1411",
    "sg:postcode":"92111",
    "sg:province":"CA",
    "sg:website":"www.kaplanprofessionalschools.co...",
    "wof:name":"Anthony Schools",
    "wof:placetype":"venue"
},
  "geometry": {"coordinates":[-117.177544,32.820065],"type":"Point"}
}