{
  "type": "Feature",
  "properties": {
    "iso:country":"US",
    "sg:address":"52 Harold Ave",
    "sg:city":"San Jose",
    "sg:classifiers":[
        {
            "category":"Social Services",
            "type":"Services"
        }
    ],
    "sg:phone":"+1 408 241 4175",
    "sg:postcode":"95117",
    "sg:province":"CA",
    "sg:tags":[
        "counselor",
        "marriage",
        "family"
    ],
    "wof:name":"Janet Karzmark",
    "wof:placetype":"venue"
},
  "geometry": {"coordinates":[-121.96217,37.32698],"type":"Point"}
}