{
  "type": "Feature",
  "properties": {
    "addr:full":"339 9th St Oakland CA 94607",
    "addr:housenumber":"339",
    "addr:postcode":"94607",
    "addr:street":"9Th St",
    "iso:country":"US",
    "sg:address":"339 9th St",
    "sg:city":"Oakland",
    "sg:classifiers":[
        {
            "category":"Restaurant",
            "type":"Food & Drink"
        }
    ],
    "sg:phone":"+1 510 839 3188",
    "sg:postcode":"94607",
    "sg:province":"CA",
    "sg:tags":[
        "chinese"
    ],
    "wof:name":"Big Dish Restaurant",
    "wof:placetype":"venue"
},
  "geometry": {"coordinates":[-122.270709,37.799864],"type":"Point"}
}