{
  "type": "Feature",
  "properties": {
    "addr:full":"528 Capitola Avenue Capitola CA 95010",
    "addr:housenumber":"528",
    "addr:postcode":"95010",
    "addr:street":"Capitola Avenue",
    "iso:country":"US",
    "sg:address":"528 Capitola Avenue",
    "sg:city":"Capitola",
    "sg:classifiers":[
        {
            "category":"Health Services",
            "subcategory":"Doctor",
            "type":"Services"
        }
    ],
    "sg:phone":"+1 831 462 9826",
    "sg:postcode":"95010",
    "sg:province":"CA",
    "wof:name":"Kevin Hasenauer, MD",
    "wof:placetype":"venue"
},
  "geometry": {"coordinates":[-121.953011,36.976772],"type":"Point"}
}