{
  "type": "Feature",
  "properties": {
    "addr:full":"73020 el Paseo Palm Desert CA 92260",
    "addr:housenumber":"73020",
    "addr:postcode":"ca 92260",
    "addr:street":"El Paseo",
    "iso:country":"US",
    "sg:address":"73020 el Paseo",
    "sg:city":"Palm Desert",
    "sg:classifiers":[
        {
            "category":"Real Estate",
            "subcategory":"Real Estate Agent",
            "type":"Services"
        }
    ],
    "sg:phone":"+1 760 776 8838",
    "sg:postcode":"92260",
    "sg:province":"CA",
    "sg:tags":[
        "investment"
    ],
    "wof:name":"Reservis Inc",
    "wof:placetype":"venue"
},
  "geometry": {"coordinates":[-116.39067300000001,33.719803],"type":"Point"}
}