{
  "type": "Feature",
  "properties": {
    "addr:full":"11430 Fair Oaks Boulevard Fair Oaks CA 95628",
    "addr:housenumber":"11430",
    "addr:postcode":"95628",
    "addr:street":"Fair Oaks Boulevard",
    "iso:country":"US",
    "sg:address":"11430 Fair Oaks Boulevard",
    "sg:city":"Fair Oaks",
    "sg:classifiers":[
        {
            "category":"Shopping",
            "subcategory":"Pets & Pet Supplies",
            "type":"Retail Goods"
        }
    ],
    "sg:phone":"+1 916 966 6758",
    "sg:postcode":"95628",
    "sg:province":"CA",
    "sg:tags":[
        "training"
    ],
    "wof:name":"St Francis Pet Info Center",
    "wof:placetype":"venue"
},
  "geometry": {"coordinates":[-121.262259,38.659685],"type":"Point"}
}