{
  "type": "Feature",
  "properties": {
    "addr:full":"2107 Dwight Way Berkeley CA 94704",
    "addr:housenumber":"2107",
    "addr:postcode":"94704",
    "addr:street":"Dwight Way",
    "iso:country":"US",
    "sg:address":"2107 Dwight Way",
    "sg:city":"Berkeley",
    "sg:classifiers":[
        {
            "category":"Health Services",
            "subcategory":"Optometrist",
            "type":"Services"
        }
    ],
    "sg:phone":"+1 510 843 2021",
    "sg:postcode":"94704",
    "sg:province":"CA",
    "wof:name":"Berkeley Optometric Group",
    "wof:placetype":"venue"
},
  "geometry": {"coordinates":[-122.266998,37.863998],"type":"Point"}
}