{
  "type": "Feature",
  "properties": {
    "iso:country":"US",
    "sg:address":"520 Bohemian Hwy",
    "sg:city":"Sebastopol",
    "sg:classifiers":[
        {
            "category":"Travel",
            "subcategory":"Hotels & Motels",
            "type":"Entertainment"
        }
    ],
    "sg:phone":"+1 707 874 2526",
    "sg:postcode":"95472",
    "sg:province":"CA",
    "sg:tags":[
        "breakfast",
        "accommodation",
        "bed"
    ],
    "wof:name":"Green Apple Inn",
    "wof:placetype":"venue"
},
  "geometry": {"coordinates":[-122.91799899999999,38.373402],"type":"Point"}
}