{
  "type": "Feature",
  "properties": {
    "iso:country":"US",
    "sg:address":"2433 Fruitvale Ave",
    "sg:city":"Bakersfield",
    "sg:classifiers":[
        {
            "category":"Manufacturing",
            "subcategory":"Tools & Machinery",
            "type":"Manufacturing & Wholesale Goods"
        }
    ],
    "sg:phone":"+1 661 327 4571",
    "sg:postcode":"93308",
    "sg:province":"CA",
    "sg:tags":[
        "machine",
        "shop"
    ],
    "wof:name":"Hoffman Machines & Fabrication",
    "wof:placetype":"venue"
},
  "geometry": {"coordinates":[-119.074512,35.380885],"type":"Point"}
}