{
  "type": "Feature",
  "properties": {
    "iso:country":"US",
    "sg:address":"3700 24th St",
    "sg:city":"San Francisco",
    "sg:classifiers":[
        {
            "category":"Health Services",
            "subcategory":"Doctor",
            "type":"Services"
        }
    ],
    "sg:phone":"+1 415 641 1019",
    "sg:postcode":"94114",
    "sg:province":"CA",
    "sg:tags":[
        "physician",
        "surgeon",
        "pediatrician"
    ],
    "sg:website":"www.noevalleypediatrics.com",
    "wof:name":"Noe Valley Pediatrics",
    "wof:placetype":"venue"
},
  "geometry": {"coordinates":[-122.42557600000001,37.75195],"type":"Point"}
}