{
  "type": "Feature",
  "properties": {
    "iso:country":"US",
    "sg:address":"240 W 7th St",
    "sg:city":"Long Beach",
    "sg:classifiers":[
        {
            "category":"Real Estate",
            "subcategory":"Real Estate Operator",
            "type":"Services"
        }
    ],
    "sg:phone":"+1 562 436 1661",
    "sg:postcode":"90813",
    "sg:province":"CA",
    "sg:tags":[
        "apartment"
    ],
    "wof:name":"Sara's Apartments",
    "wof:placetype":"venue"
},
  "geometry": {"coordinates":[-118.19499999999999,33.775299],"type":"Point"}
}