{
  "type": "Feature",
  "properties": {
    "addr:full":"37533 Enterprise Ct Newark CA 94560",
    "addr:housenumber":"37533",
    "addr:postcode":"94560",
    "addr:street":"Enterprise Ct",
    "iso:country":"US",
    "sg:address":"37533 Enterprise Ct",
    "sg:city":"Newark",
    "sg:classifiers":[
        {
            "category":"Manufacturing",
            "subcategory":"Tools & Machinery",
            "type":"Manufacturing & Wholesale Goods"
        }
    ],
    "sg:phone":"+1 510 796 1152",
    "sg:postcode":"94560",
    "sg:province":"CA",
    "sg:tags":[
        "industrial",
        "mfg"
    ],
    "wof:name":"D B Screw Machine Products",
    "wof:placetype":"venue"
},
  "geometry": {"coordinates":[-122.04033099999999,37.522454],"type":"Point"}
}