{
  "type": "Feature",
  "properties": {
    "addr:full":"2343 N Oxnard Blvd Oxnard CA 93036",
    "addr:housenumber":"2343",
    "addr:postcode":"93036",
    "addr:street":"N Oxnard Blvd",
    "iso:country":"US",
    "sg:address":"2343 N Oxnard Blvd",
    "sg:city":"Oxnard",
    "sg:classifiers":[
        {
            "category":"Recreation",
            "type":"Entertainment"
        }
    ],
    "sg:phone":"+1 805 278 6045",
    "sg:postcode":"93036",
    "sg:province":"CA",
    "sg:tags":[
        "martial",
        "arts",
        "instruction"
    ],
    "wof:name":"ATA Blackbelt Inc",
    "wof:placetype":"venue"
},
  "geometry": {"coordinates":[-119.17822,34.22883],"type":"Point"}
}