{
  "type": "Feature",
  "properties": {
    "addr:full":"90 Great Oaks Blvd San Jose CA 95119",
    "addr:housenumber":"90",
    "addr:postcode":"95119",
    "addr:street":"Great Oaks Blvd",
    "iso:country":"US",
    "sg:address":"90 Great Oaks Blvd",
    "sg:city":"San Jose",
    "sg:classifiers":[
        {
            "category":"Insurance",
            "subcategory":"Insurance Agent",
            "type":"Services"
        }
    ],
    "sg:phone":"+1 408 229 0653",
    "sg:postcode":"95119",
    "sg:province":"CA",
    "wof:name":"Cal-Valley Insurance Svc",
    "wof:placetype":"venue"
},
  "geometry": {"coordinates":[-121.77789900000001,37.234918],"type":"Point"}
}