{
  "type": "Feature",
  "properties": {
    "addr:full":"489 S Rosario Ave San Jacinto CA 92583",
    "addr:housenumber":"489",
    "addr:postcode":"92583",
    "addr:street":"S Rosario Ave",
    "iso:country":"US",
    "sg:address":"489 S Rosario Ave",
    "sg:city":"San Jacinto",
    "sg:classifiers":[
        {
            "category":"Building & Trades",
            "subcategory":"Construction",
            "type":"Services"
        }
    ],
    "sg:phone":"+1 951 654 5180",
    "sg:postcode":"92583",
    "sg:province":"CA",
    "sg:tags":[
        "house"
    ],
    "wof:name":"Thomas & Sons Construction",
    "wof:placetype":"venue"
},
  "geometry": {"coordinates":[-116.947165,33.781148],"type":"Point"}
}