{
  "type": "Feature",
  "properties": {
    "addr:full":"1255 N University St Redlands CA 92374",
    "addr:housenumber":"1255",
    "addr:postcode":"92374",
    "addr:street":"N University St",
    "iso:country":"US",
    "sg:address":"1255 N University St",
    "sg:city":"Redlands",
    "sg:classifiers":[
        {
            "category":"Personal",
            "type":"Services"
        }
    ],
    "sg:phone":"+1 909 798 8967",
    "sg:postcode":"92374",
    "sg:province":"CA",
    "sg:tags":[
        "miscellaneous"
    ],
    "wof:name":"A Little Assistance",
    "wof:placetype":"venue"
},
  "geometry": {"coordinates":[-117.167311,34.069899],"type":"Point"}
}