{
  "type": "Feature",
  "properties": {
    "iso:country":"US",
    "sg:address":"1459 Garnet Ave",
    "sg:city":"San Diego",
    "sg:classifiers":[
        {
            "category":"Restaurant",
            "type":"Food & Drink"
        }
    ],
    "sg:phone":"+1 858 270 7766",
    "sg:postcode":"92109",
    "sg:province":"CA",
    "sg:tags":[
        "pizza"
    ],
    "sg:website":"www.hobokenpizza.com",
    "wof:name":"Hoboken Pizza & Beer Joint",
    "wof:placetype":"venue"
},
  "geometry": {"coordinates":[-117.24299600000001,32.7994],"type":"Point"}
}