{
  "type": "Feature",
  "properties": {
    "addr:full":"205 W Bluff Ave Fresno CA 93711",
    "addr:housenumber":"205",
    "addr:postcode":"93711",
    "addr:street":"W Bluff Ave",
    "iso:country":"US",
    "sg:address":"205 W Bluff Ave",
    "sg:city":"Fresno",
    "sg:classifiers":[
        {
            "category":"Farming",
            "subcategory":"Livestock Farm",
            "type":"Manufacturing & Wholesale Goods"
        }
    ],
    "sg:phone":"+1 559 438 6265",
    "sg:postcode":"93711",
    "sg:province":"CA",
    "sg:tags":[
        "real",
        "property",
        "animal",
        "lessor",
        "general"
    ],
    "wof:name":"Fordin Ranches Inc",
    "wof:placetype":"venue"
},
  "geometry": {"coordinates":[-119.793358,36.868948],"type":"Point"}
}