{
  "type": "Feature",
  "properties": {
    "iso:country":"US",
    "sg:address":"7217 Melrose Ave",
    "sg:city":"Los Angeles",
    "sg:classifiers":[
        {
            "category":"Food & Beverages",
            "subcategory":"Specialty",
            "type":"Retail Goods"
        }
    ],
    "sg:phone":"+1 323 857 5300",
    "sg:postcode":"90046",
    "sg:province":"CA",
    "sg:tags":[
        "health",
        "diet"
    ],
    "sg:website":"www.uchoose.net",
    "wof:name":"Ecstacy Melrose",
    "wof:placetype":"venue"
},
  "geometry": {"coordinates":[-118.34709700000001,34.08357],"type":"Point"}
}