{
  "type": "Feature",
  "properties": {
    "iso:country":"US",
    "sg:address":"355 Mildred Ave",
    "sg:city":"Galt",
    "sg:classifiers":[
        {
            "category":"Wholesale",
            "subcategory":"Farm Supplies",
            "type":"Manufacturing & Wholesale Goods"
        }
    ],
    "sg:phone":"+1 209 745 6827",
    "sg:postcode":"95632",
    "sg:province":"CA",
    "sg:tags":[
        "livestock"
    ],
    "wof:name":"Joseph Azevedo",
    "wof:placetype":"venue"
},
  "geometry": {"coordinates":[-121.301446,38.261617],"type":"Point"}
}