{
  "type": "Feature",
  "properties": {
    "addr:full":"26150 Enterprise Way Lake Forest CA 92630",
    "addr:housenumber":"26150",
    "addr:postcode":"92630",
    "addr:street":"Enterprise Way",
    "iso:country":"US",
    "sg:address":"26150 Enterprise Way",
    "sg:city":"Lake Forest",
    "sg:classifiers":[
        {
            "category":"Professional",
            "subcategory":"Engineering",
            "type":"Services"
        }
    ],
    "sg:phone":"+1 949 250 4700",
    "sg:postcode":"92630",
    "sg:province":"CA",
    "sg:tags":[
        "engineer"
    ],
    "wof:name":"Mvp Engineering",
    "wof:placetype":"venue"
},
  "geometry": {"coordinates":[-117.674346,33.666819],"type":"Point"}
}