{
  "type": "Feature",
  "properties": {
    "addr:full":"400 E Gobbi St Ukiah CA 95482",
    "addr:housenumber":"400",
    "addr:postcode":"ca 95482",
    "addr:street":"E Gobbi St",
    "iso:country":"US",
    "sg:address":"400 E Gobbi St",
    "sg:city":"Ukiah",
    "sg:classifiers":[
        {
            "category":"Insurance",
            "subcategory":"Hazard Insurance",
            "type":"Services"
        },
        {
            "category":"Banks & Credit Unions",
            "subcategory":"Bank",
            "type":"Services"
        }
    ],
    "sg:phone":"+1 707 472 2940",
    "sg:postcode":"95482",
    "sg:province":"CA",
    "sg:tags":[
        "commercial",
        "saving",
        "business"
    ],
    "sg:website":"http://statefarm.com",
    "wof:name":"Myer Jerry",
    "wof:placetype":"venue"
},
  "geometry": {"coordinates":[-123.200996,39.14436],"type":"Point"}
}