{
  "type": "Feature",
  "properties": {
    "addr:full":"209 N Curryer St Santa Maria CA 93458",
    "addr:housenumber":"209",
    "addr:postcode":"93458",
    "addr:street":"N Curryer St",
    "iso:country":"US",
    "sg:address":"209 N Curryer St",
    "sg:city":"Santa Maria",
    "sg:classifiers":[
        {
            "category":"Farming",
            "subcategory":"Farm",
            "type":"Manufacturing & Wholesale Goods"
        }
    ],
    "sg:phone":"+1 805 928 5929",
    "sg:postcode":"93458",
    "sg:province":"CA",
    "sg:tags":[
        "crop",
        "general"
    ],
    "wof:name":"Twin Berry Farm",
    "wof:placetype":"venue"
},
  "geometry": {"coordinates":[-120.44144900000001,34.954851],"type":"Point"}
}