{
  "type": "Feature",
  "properties": {
    "iso:country":"US",
    "sg:address":"14554 Sambar St",
    "sg:city":"Chino Hills",
    "sg:classifiers":[
        {
            "category":"Wholesale",
            "subcategory":"Hardware",
            "type":"Manufacturing & Wholesale Goods"
        }
    ],
    "sg:phone":"+1 909 597 7697",
    "sg:postcode":"91709",
    "sg:province":"CA",
    "sg:tags":[
        "refrigeration"
    ],
    "wof:name":"Cetina Vally Refridgeration",
    "wof:placetype":"venue"
},
  "geometry": {"coordinates":[-117.729656,33.989041],"type":"Point"}
}