{
  "type": "Feature",
  "properties": {
    "addr:full":"352 Roan Dr Tracy CA 95376",
    "addr:housenumber":"352",
    "addr:postcode":"95376",
    "addr:street":"Roan Dr",
    "iso:country":"US",
    "sg:address":"352 Roan Dr",
    "sg:city":"Tracy",
    "sg:classifiers":[
        {
            "category":"Farming",
            "subcategory":"Livestock Farm",
            "type":"Manufacturing & Wholesale Goods"
        },
        {
            "category":"Professional",
            "type":"Services"
        }
    ],
    "sg:phone":"+1 209 839 1876",
    "sg:postcode":"95376",
    "sg:province":"CA",
    "sg:tags":[
        "establishment",
        "specialty",
        "animal"
    ],
    "wof:name":"Whisker Watchers",
    "wof:placetype":"venue"
},
  "geometry": {"coordinates":[-121.44032900000001,37.726471],"type":"Point"}
}