{
  "type": "Feature",
  "properties": {
    "addr:full":"456 S 2nd St San Jose CA 95113",
    "addr:housenumber":"456",
    "addr:postcode":"95113",
    "addr:street":"S 2Nd St",
    "iso:country":"US",
    "sg:address":"456 S 2nd St",
    "sg:city":"San Jose",
    "sg:classifiers":[
        {
            "category":"Banks & Credit Unions",
            "subcategory":"Investment Brokerage",
            "type":"Services"
        }
    ],
    "sg:phone":"+1 408 292 4788",
    "sg:postcode":"95113",
    "sg:province":"CA",
    "sg:tags":[
        "advisory",
        "referral"
    ],
    "wof:name":"DO Hung",
    "wof:placetype":"venue"
},
  "geometry": {"coordinates":[-121.884325,37.329939],"type":"Point"}
}