{
  "type": "Feature",
  "properties": {
    "iso:country":"US",
    "sg:address":"7737 Amestoy Ave",
    "sg:city":"Van Nuys",
    "sg:classifiers":[
        {
            "category":"Shopping",
            "subcategory":"Beauty & Cosmetics",
            "type":"Retail Goods"
        }
    ],
    "sg:phone":"+1 818 757 0762",
    "sg:postcode":"91406",
    "sg:province":"CA",
    "sg:tags":[
        "merchandise"
    ],
    "wof:name":"Beauty Cosmetics",
    "wof:placetype":"venue"
},
  "geometry": {"coordinates":[-118.505575,34.210282],"type":"Point"}
}