{
  "type": "Feature",
  "properties": {
    "iso:country":"US",
    "sg:address":"136 Delhi St",
    "sg:city":"Stockton",
    "sg:classifiers":[
        {
            "category":"Professional",
            "type":"Services"
        }
    ],
    "sg:phone":"+1 209 941 0793",
    "sg:postcode":"95206",
    "sg:province":"CA",
    "wof:name":"Lifetime Union Cookware",
    "wof:placetype":"venue"
},
  "geometry": {"coordinates":[-121.286618,37.92978],"type":"Point"}
}