{
  "type": "Feature",
  "properties": {
    "addr:full":"2007 Main St Julian CA 92036",
    "addr:housenumber":"2007",
    "addr:postcode":"92036",
    "addr:street":"Main St",
    "iso:country":"US",
    "sg:address":"2007 Main St",
    "sg:city":"Julian",
    "sg:classifiers":[
        {
            "category":"Shopping",
            "subcategory":"Gifts & Souvenirs",
            "type":"Retail Goods"
        }
    ],
    "sg:phone":"+1 760 765 3885",
    "sg:postcode":"92036",
    "sg:province":"CA",
    "sg:tags":[
        "shop"
    ],
    "wof:name":"Christmas Cottage",
    "wof:placetype":"venue"
},
  "geometry": {"coordinates":[-116.601016,33.077503],"type":"Point"}
}