{
  "type": "Feature",
  "properties": {
    "iso:country":"US",
    "sg:address":"217 E 25th St",
    "sg:city":"Upland",
    "sg:classifiers":[
        {
            "category":"Wholesale",
            "subcategory":"Machinery & Supplies",
            "type":"Manufacturing & Wholesale Goods"
        }
    ],
    "sg:phone":"+1 909 981 4200",
    "sg:postcode":"91784",
    "sg:province":"CA",
    "sg:tags":[
        "equipment",
        "industrial"
    ],
    "wof:name":"Industrial Hardware & Svc Co",
    "wof:placetype":"venue"
},
  "geometry": {"coordinates":[-117.651014,34.155527],"type":"Point"}
}