{
  "type": "Feature",
  "properties": {
    "iso:country":"US",
    "sg:address":"2170 Folsom St",
    "sg:city":"San Francisco",
    "sg:classifiers":[
        {
            "category":"Wholesale",
            "subcategory":"Home Furnishings",
            "type":"Manufacturing & Wholesale Goods"
        }
    ],
    "sg:phone":"+1 415 621 0764",
    "sg:postcode":"94110",
    "sg:province":"CA",
    "sg:website":"www.lunares.net",
    "wof:name":"Lunares",
    "wof:placetype":"venue"
},
  "geometry": {"coordinates":[-122.415162,37.763235],"type":"Point"}
}