{
  "type": "Feature",
  "properties": {
    "addr:full":"11684 Ventura Blvd Studio City CA 91604",
    "addr:housenumber":"11684",
    "addr:postcode":"91604",
    "addr:street":"Ventura Blvd",
    "iso:country":"US",
    "sg:address":"11684 Ventura Blvd",
    "sg:city":"Studio City",
    "sg:classifiers":[
        {
            "category":"Health Services",
            "subcategory":"Clinic",
            "type":"Services"
        },
        {
            "category":"Education",
            "subcategory":"Special Training",
            "type":"Public Place"
        }
    ],
    "sg:phone":"+1 818 780 7093",
    "sg:postcode":"91604",
    "sg:province":"CA",
    "sg:tags":[
        "aids",
        "testing",
        "information"
    ],
    "wof:name":"Alive & Well Aids Alternatives",
    "wof:placetype":"venue"
},
  "geometry": {"coordinates":[-118.385288,34.140346],"type":"Point"}
}