{
  "type": "Feature",
  "properties": {
    "iso:country":"US",
    "sg:address":"430 N Claremont Ave",
    "sg:city":"Fresno",
    "sg:classifiers":[
        {
            "category":"Building & Trades",
            "subcategory":"Landscaping Services",
            "type":"Services"
        }
    ],
    "sg:phone":"+1 559 252 3178",
    "sg:postcode":"93727",
    "sg:province":"CA",
    "sg:tags":[
        "landscape"
    ],
    "wof:name":"Lennie Slaughter Landscaping",
    "wof:placetype":"venue"
},
  "geometry": {"coordinates":[-119.690021,36.749057],"type":"Point"}
}