{
  "type": "Feature",
  "properties": {
    "addr:full":"1100 5th Ave Los Angeles CA 90019",
    "addr:housenumber":"1100",
    "addr:postcode":"90019",
    "addr:street":"5Th Ave",
    "iso:country":"US",
    "sg:address":"1100 5th Ave",
    "sg:city":"Los Angeles",
    "sg:classifiers":[
        {
            "category":"Professional",
            "type":"Services"
        }
    ],
    "sg:phone":"+1 323 731 6076",
    "sg:postcode":"90019",
    "sg:province":"CA",
    "wof:name":"Cristina S Acantilado",
    "wof:placetype":"venue"
},
  "geometry": {"coordinates":[-118.322452,34.047433],"type":"Point"}
}