{
  "type": "Feature",
  "properties": {
    "iso:country":"US",
    "sg:address":"1174 Castro Street Suite 200",
    "sg:city":"Mountain View",
    "sg:classifiers":[
        {
            "category":"Health Services",
            "subcategory":"Doctor",
            "type":"Services"
        }
    ],
    "sg:phone":"+1 650 934 7808",
    "sg:postcode":"94040",
    "sg:province":"CA",
    "sg:website":"www.caminomedical.org/ProviderSe...",
    "wof:name":"Dr. Teresa Huang, MD",
    "wof:placetype":"venue"
},
  "geometry": {"coordinates":[-122.085999,37.381699],"type":"Point"}
}