{
  "type": "Feature",
  "properties": {
    "iso:country":"US",
    "sg:address":"3900 Cross Creek Rd",
    "sg:city":"Malibu",
    "sg:classifiers":[
        {
            "category":"Professional",
            "type":"Services"
        }
    ],
    "sg:phone":"+1 310 456 8874",
    "sg:postcode":"90265",
    "sg:province":"CA",
    "sg:tags":[
        "establishment"
    ],
    "wof:name":"Sotheby's International",
    "wof:placetype":"venue"
},
  "geometry": {"coordinates":[-118.685295,34.035564],"type":"Point"}
}