{
  "type": "Feature",
  "properties": {
    "iso:country":"US",
    "sg:address":"222 N Sepulveda Blvd",
    "sg:city":"El Segundo",
    "sg:classifiers":[
        {
            "category":"Personal",
            "subcategory":"Skin Care",
            "type":"Services"
        }
    ],
    "sg:phone":"+1 310 662 4774",
    "sg:postcode":"90245",
    "sg:province":"CA",
    "wof:name":"Moy Skincare",
    "wof:placetype":"venue"
},
  "geometry": {"coordinates":[-118.395693,33.918536],"type":"Point"}
}