{
  "type": "Feature",
  "properties": {
    "iso:country":"US",
    "sg:address":"3627 Sagunto St",
    "sg:city":"Santa Ynez",
    "sg:classifiers":[
        {
            "category":"Travel",
            "subcategory":"Hotels & Motels",
            "type":"Entertainment"
        }
    ],
    "sg:phone":"+1 805 688 5588",
    "sg:postcode":"93460",
    "sg:province":"CA",
    "sg:tags":[
        "breakfast",
        "accommodation",
        "bed"
    ],
    "sg:website":"www.santaynezinn.com",
    "wof:name":"Santa Ynez Inn",
    "wof:placetype":"venue"
},
  "geometry": {"coordinates":[-120.079254,34.612937],"type":"Point"}
}