{
  "type": "Feature",
  "properties": {
    "iso:country":"US",
    "sg:address":"507 York St",
    "sg:city":"Vallejo",
    "sg:classifiers":[
        {
            "category":"Retail",
            "subcategory":"Self-service Laundry",
            "type":"Services"
        }
    ],
    "sg:phone":"+1 707 645 1797",
    "sg:postcode":"94590",
    "sg:province":"CA",
    "wof:name":"York Wash & Dry",
    "wof:placetype":"venue"
},
  "geometry": {"coordinates":[-122.253389,38.100005],"type":"Point"}
}