{
  "type": "Feature",
  "properties": {
    "addr:full":"1866 W Lacey Blvd Hanford CA 93230",
    "addr:housenumber":"1866",
    "addr:postcode":"ca 93230",
    "addr:street":"W Lacey Blvd",
    "iso:country":"US",
    "sg:address":"1866 W Lacey Blvd",
    "sg:city":"Hanford",
    "sg:classifiers":[
        {
            "category":"Personal",
            "subcategory":"Beauty Salon",
            "type":"Services"
        }
    ],
    "sg:phone":"+1 559 589 1394",
    "sg:postcode":"93230",
    "sg:province":"CA",
    "sg:tags":[
        "manicuring"
    ],
    "wof:name":"Nails World",
    "wof:placetype":"venue"
},
  "geometry": {"coordinates":[-119.668865,36.328077],"type":"Point"}
}