{
  "type": "Feature",
  "properties": {
    "iso:country":"US",
    "sg:address":"8024 N el Dorado St",
    "sg:city":"Stockton",
    "sg:classifiers":[
        {
            "category":"Food & Beverages",
            "subcategory":"Groceries & Convenience Stores",
            "type":"Retail Goods"
        }
    ],
    "sg:phone":"+1 209 477 5004",
    "sg:postcode":"95210",
    "sg:province":"CA",
    "sg:tags":[
        "grocer"
    ],
    "wof:name":"Arunn Market",
    "wof:placetype":"venue"
},
  "geometry": {"coordinates":[-121.315111,38.021067],"type":"Point"}
}