{
  "type": "Feature",
  "properties": {
    "addr:full":"16210 Haas Ave Torrance CA 90504",
    "addr:housenumber":"16210",
    "addr:postcode":"90504",
    "addr:street":"Haas Ave",
    "iso:country":"US",
    "sg:address":"16210 Haas Ave",
    "sg:city":"Torrance",
    "sg:classifiers":[
        {
            "category":"Personal",
            "subcategory":"Nail Salon",
            "type":"Services"
        }
    ],
    "sg:phone":"+1 310 527 6135",
    "sg:postcode":"90504",
    "sg:province":"CA",
    "wof:name":"Care Nails",
    "wof:placetype":"venue"
},
  "geometry": {"coordinates":[-118.317001,33.8834],"type":"Point"}
}