{
  "type": "Feature",
  "properties": {
    "iso:country":"US",
    "sg:address":"3490 S Broadway",
    "sg:city":"Los Angeles",
    "sg:classifiers":[
        {
            "category":"Professional",
            "type":"Services"
        }
    ],
    "sg:phone":"+1 310 830 8427",
    "sg:postcode":"90007",
    "sg:province":"CA",
    "sg:tags":[
        "establishment"
    ],
    "wof:name":"Deva Kidz",
    "wof:placetype":"venue"
},
  "geometry": {"coordinates":[-118.274266,34.018318],"type":"Point"}
}