{
  "type": "Feature",
  "properties": {
    "addr:full":"1037 Ashby Ave Berkeley CA 94710",
    "addr:housenumber":"1037",
    "addr:postcode":"94710",
    "addr:street":"Ashby Ave",
    "iso:country":"US",
    "sg:address":"1037 Ashby Ave",
    "sg:city":"Berkeley",
    "sg:classifiers":[
        {
            "category":"Professional",
            "subcategory":"Computer Services",
            "type":"Services"
        }
    ],
    "sg:phone":"+1 510 450 9709",
    "sg:postcode":"94710",
    "sg:province":"CA",
    "sg:tags":[
        "design",
        "network",
        "system"
    ],
    "wof:name":"Vector Data",
    "wof:placetype":"venue"
},
  "geometry": {"coordinates":[-122.28874999999999,37.851737],"type":"Point"}
}