{
  "type": "Feature",
  "properties": {
    "iso:country":"US",
    "sg:address":"2970 Rimpau Ave",
    "sg:city":"Corona",
    "sg:classifiers":[
        {
            "category":"Government",
            "subcategory":"Office",
            "type":"Public Place"
        }
    ],
    "sg:phone":"+1 951 736 2478",
    "sg:postcode":"92881",
    "sg:province":"CA",
    "sg:tags":[
        "water",
        "production",
        "municipal"
    ],
    "wof:name":"Water Production",
    "wof:placetype":"venue"
},
  "geometry": {"coordinates":[-117.54648899999999,33.839538],"type":"Point"}
}