{
  "type": "Feature",
  "properties": {
    "iso:country":"US",
    "sg:address":"1050 N Twin Oaks Valley Rd",
    "sg:city":"San Marcos",
    "sg:classifiers":[
        {
            "category":"Real Estate",
            "subcategory":"Real Estate Agent",
            "type":"Services"
        }
    ],
    "sg:phone":"+1 760 471 7316",
    "sg:postcode":"92069",
    "sg:province":"CA",
    "sg:tags":[
        "property",
        "management"
    ],
    "wof:name":"CLK Investments",
    "wof:placetype":"venue"
},
  "geometry": {"coordinates":[-117.161177,33.155692],"type":"Point"}
}