{
  "type": "Feature",
  "properties": {
    "iso:country":"US",
    "sg:address":"2201 Park Ave",
    "sg:city":"Chico",
    "sg:classifiers":[
        {
            "category":"Wholesale",
            "subcategory":"Machinery & Supplies",
            "type":"Manufacturing & Wholesale Goods"
        }
    ],
    "sg:phone":"+1 530 894 0123",
    "sg:postcode":"95928",
    "sg:province":"CA",
    "sg:tags":[
        "janitor",
        "establishment",
        "equipment"
    ],
    "wof:name":"C M Janitorial Supply",
    "wof:placetype":"venue"
},
  "geometry": {"coordinates":[-121.81592999999999,39.715252],"type":"Point"}
}