{
  "type": "Feature",
  "properties": {
    "addr:full":"11650 Santa Monica Blvd Los Angeles CA 90025",
    "addr:housenumber":"11650",
    "addr:postcode":"90025",
    "addr:street":"Santa Monica Blvd",
    "iso:country":"US",
    "sg:address":"11650 Santa Monica Blvd",
    "sg:city":"Los Angeles",
    "sg:classifiers":[
        {
            "category":"Shopping",
            "subcategory":"Used Merchandise",
            "type":"Retail Goods"
        }
    ],
    "sg:phone":"+1 310 571 0385",
    "sg:postcode":"90025",
    "sg:province":"CA",
    "sg:tags":[
        "antique"
    ],
    "wof:name":"Going Going Gone Inc",
    "wof:placetype":"venue"
},
  "geometry": {"coordinates":[-118.456045,34.043755],"type":"Point"}
}