{
  "type": "Feature",
  "properties": {
    "addr:full":"2111 National Ave Hayward CA 94545",
    "addr:housenumber":"2111",
    "addr:postcode":"94545",
    "addr:street":"National Ave",
    "iso:country":"US",
    "sg:address":"2111 National Ave",
    "sg:city":"Hayward",
    "sg:classifiers":[
        {
            "category":"Retail",
            "subcategory":"Repair Shop",
            "type":"Services"
        }
    ],
    "sg:phone":"+1 510 783 3125",
    "sg:postcode":"94545",
    "sg:province":"CA",
    "sg:tags":[
        "welding"
    ],
    "wof:name":"Bogue's Welding Svc",
    "wof:placetype":"venue"
},
  "geometry": {"coordinates":[-122.123431,37.649713],"type":"Point"}
}