{
  "type": "Feature",
  "properties": {
    "iso:country":"US",
    "sg:address":"19944 Buck Ridge Rd",
    "sg:city":"Grass Valley",
    "sg:classifiers":[
        {
            "category":"Home & Garden",
            "subcategory":"Furniture",
            "type":"Retail Goods"
        }
    ],
    "sg:phone":"+1 530 346 2079",
    "sg:postcode":"95949",
    "sg:province":"CA",
    "wof:name":"Naked Tree Woodworking",
    "wof:placetype":"venue"
},
  "geometry": {"coordinates":[-121.018901,39.116246],"type":"Point"}
}