{
  "type": "Feature",
  "properties": {
    "iso:country":"US",
    "sg:address":"2202 E Anderson St",
    "sg:city":"Vernon",
    "sg:classifiers":[
        {
            "category":"Manufacturing",
            "subcategory":"Toys & Sporting Goods",
            "type":"Manufacturing & Wholesale Goods"
        }
    ],
    "sg:phone":"+1 323 582 3005",
    "sg:postcode":"90058",
    "sg:province":"CA",
    "sg:tags":[
        "goods-wholesale",
        "manufacturer"
    ],
    "sg:website":"http://www.aisuniforms.com",
    "wof:name":"Sports Robe",
    "wof:placetype":"venue"
},
  "geometry": {"coordinates":[-118.233602,33.989851],"type":"Point"}
}