{
  "type": "Feature",
  "properties": {
    "iso:country":"US",
    "sg:address":"18763 Napa St",
    "sg:city":"Northridge",
    "sg:classifiers":[
        {
            "category":"Building & Trades",
            "subcategory":"Construction",
            "type":"Services"
        }
    ],
    "sg:phone":"+1 818 886 6471",
    "sg:postcode":"91324",
    "sg:province":"CA",
    "sg:tags":[
        "finishing",
        "wood",
        "refinishing"
    ],
    "wof:name":"Vic's Wood Stripping & Rfnshng",
    "wof:placetype":"venue"
},
  "geometry": {"coordinates":[-118.541955,34.226494],"type":"Point"}
}