{
  "type": "Feature",
  "properties": {
    "iso:country":"US",
    "sg:address":"229 Utah Ave",
    "sg:city":"South San Francisco",
    "sg:classifiers":[
        {
            "category":"Shopping",
            "subcategory":"Florist",
            "type":"Retail Goods"
        }
    ],
    "sg:phone":"+1 800 755 2800",
    "sg:postcode":"94080",
    "sg:province":"CA",
    "sg:website":"www.arteflorum.com/",
    "wof:name":"ARTEflorum.com",
    "wof:placetype":"venue"
},
  "geometry": {"coordinates":[-122.39825399999999,37.64724],"type":"Point"}
}