{
  "type": "Feature",
  "properties": {
    "iso:country":"US",
    "sg:address":"869 W 21st St",
    "sg:city":"Upland",
    "sg:classifiers":[
        {
            "category":"Banks & Credit Unions",
            "subcategory":"Investment Brokerage",
            "type":"Services"
        }
    ],
    "sg:phone":"+1 951 733 4286",
    "sg:postcode":"91784",
    "sg:province":"CA",
    "sg:tags":[
        "consultant",
        "planning",
        "financial"
    ],
    "wof:name":"Profit Consulting",
    "wof:placetype":"venue"
},
  "geometry": {"coordinates":[-117.66348600000001,34.139737],"type":"Point"}
}