{
  "type": "Feature",
  "properties": {
    "addr:full":"4390 Daywalt Rd Sebastopol CA 95472",
    "addr:housenumber":"4390",
    "addr:postcode":"95472",
    "addr:street":"Daywalt Rd",
    "iso:country":"US",
    "sg:address":"4390 Daywalt Rd",
    "sg:city":"Sebastopol",
    "sg:classifiers":[
        {
            "category":"Building & Trades",
            "subcategory":"Construction",
            "type":"Services"
        }
    ],
    "sg:phone":"+1 707 829 5266",
    "sg:postcode":"95472",
    "sg:province":"CA",
    "sg:tags":[
        "painter"
    ],
    "wof:name":"Hug's Mobile Sandblasting",
    "wof:placetype":"venue"
},
  "geometry": {"coordinates":[-122.77153800000001,38.357641],"type":"Point"}
}