{
  "type": "Feature",
  "properties": {
    "addr:full":"28211 Crown Valley Pkwy Laguna Niguel CA 92677",
    "addr:housenumber":"28211",
    "addr:postcode":"92677",
    "addr:street":"Crown Valley Pkwy",
    "iso:country":"US",
    "sg:address":"28211 Crown Valley Pkwy",
    "sg:city":"Laguna Niguel",
    "sg:classifiers":[
        {
            "category":"Banks & Credit Unions",
            "subcategory":"Bank",
            "type":"Services"
        }
    ],
    "sg:phone":"+1 949 362 1057",
    "sg:postcode":"92677",
    "sg:province":"CA",
    "wof:name":"World Savings Bank",
    "wof:placetype":"venue"
},
  "geometry": {"coordinates":[-117.691253,33.543849],"type":"Point"}
}