{
  "type": "Feature",
  "properties": {
    "iso:country":"US",
    "sg:address":"5835 Chenault Dr",
    "sg:city":"Modesto",
    "sg:classifiers":[
        {
            "category":"Professional",
            "subcategory":"Engineering",
            "type":"Services"
        },
        {
            "category":"Wholesale",
            "subcategory":"Machinery & Supplies",
            "type":"Manufacturing & Wholesale Goods"
        }
    ],
    "sg:phone":"+1 209 537 5066",
    "sg:postcode":"95356",
    "sg:province":"CA",
    "sg:tags":[
        "equipment-parts",
        "refrigeration",
        "freezers-wholesale",
        "engineer",
        "refrigerator",
        "manufacturer"
    ],
    "wof:name":"Instant Cooling Equipment",
    "wof:placetype":"venue"
},
  "geometry": {"coordinates":[-120.99127300000001,37.723841],"type":"Point"}
}