{
  "type": "Feature",
  "properties": {
    "iso:country":"US",
    "sg:address":"1301 61st St",
    "sg:city":"Emeryville",
    "sg:classifiers":[
        {
            "category":"Building & Trades",
            "subcategory":"Construction",
            "type":"Services"
        }
    ],
    "sg:phone":"+1 510 658 9892",
    "sg:postcode":"94608",
    "sg:province":"CA",
    "sg:tags":[
        "general",
        "contractor"
    ],
    "wof:name":"Dream Builders",
    "wof:placetype":"venue"
},
  "geometry": {"coordinates":[-122.29019700000001,37.842608],"type":"Point"}
}