{
  "type": "Feature",
  "properties": {
    "addr:full":"840 N Cypress St Orange CA 92866",
    "addr:housenumber":"840",
    "addr:postcode":"92866",
    "addr:street":"N Cypress St",
    "iso:country":"US",
    "sg:address":"840 N Cypress St",
    "sg:city":"Orange",
    "sg:classifiers":[
        {
            "category":"Shopping",
            "type":"Retail Goods"
        }
    ],
    "sg:phone":"+1 714 744 1178",
    "sg:postcode":"92866",
    "sg:province":"CA",
    "sg:tags":[
        "art",
        "gallery",
        "dealer"
    ],
    "wof:name":"T N Art & Engineering",
    "wof:placetype":"venue"
},
  "geometry": {"coordinates":[-117.85642199999999,33.796182],"type":"Point"}
}