{
  "type": "Feature",
  "properties": {
    "iso:country":"US",
    "sg:address":"63 Brady St",
    "sg:city":"San Francisco",
    "sg:classifiers":[
        {
            "category":"Utilities",
            "subcategory":"Telephone",
            "type":"Services"
        }
    ],
    "sg:phone":"+1 415 252 5382",
    "sg:postcode":"94103",
    "sg:province":"CA",
    "sg:tags":[
        "communications"
    ],
    "wof:name":"Parlez Communications",
    "wof:placetype":"venue"
},
  "geometry": {"coordinates":[-122.421042,37.773535],"type":"Point"}
}