{
  "type": "Feature",
  "properties": {
    "addr:full":"702 Encinas Ave Calexico CA 92231",
    "addr:housenumber":"702",
    "addr:postcode":"92231",
    "addr:street":"Encinas Ave",
    "iso:country":"US",
    "sg:address":"702 Encinas Ave",
    "sg:city":"Calexico",
    "sg:classifiers":[
        {
            "category":"Organizations",
            "subcategory":"Religious Organization",
            "type":"Services"
        }
    ],
    "sg:phone":"+1 760 357 6333",
    "sg:postcode":"92231",
    "sg:province":"CA",
    "sg:tags":[
        "church"
    ],
    "wof:name":"First Chinese Baptist Church",
    "wof:placetype":"venue"
},
  "geometry": {"coordinates":[-115.488094,32.672668],"type":"Point"}
}