{
  "type": "Feature",
  "properties": {
    "addr:full":"375 S Main St Pomona CA 91766",
    "addr:housenumber":"375",
    "addr:postcode":"91766",
    "addr:street":"S Main St",
    "iso:country":"US",
    "sg:address":"375 S Main St",
    "sg:city":"Pomona",
    "sg:classifiers":[
        {
            "category":"Wholesale",
            "subcategory":"Durable Goods & Equipment",
            "type":"Manufacturing & Wholesale Goods"
        },
        {
            "category":"Banks & Credit Unions",
            "subcategory":"Bank",
            "type":"Services"
        }
    ],
    "sg:phone":"+1 909 524 0123",
    "sg:postcode":"91766",
    "sg:province":"CA",
    "sg:tags":[
        "loan",
        "real estate"
    ],
    "sg:website":"www.ontimehomeloans.com",
    "wof:name":"Universal West",
    "wof:placetype":"venue"
},
  "geometry": {"coordinates":[-117.75234500000001,34.056649],"type":"Point"}
}