{
  "type": "Feature",
  "properties": {
    "iso:country":"US",
    "sg:address":"305 West Lake Boulevard P.O. Box 6567",
    "sg:city":"Tahoe City",
    "sg:classifiers":[
        {
            "category":"Professional",
            "subcategory":"Lawyer & Legal Services",
            "type":"Services"
        }
    ],
    "sg:phone":"+1 530 583 5523",
    "sg:postcode":"96145",
    "sg:province":"CA",
    "sg:website":"www.jillgregorylaw.com",
    "wof:name":"Law Offices of Jill S Gregory",
    "wof:placetype":"venue"
},
  "geometry": {"coordinates":[-120.145177,39.161763],"type":"Point"}
}