{
  "type": "Feature",
  "properties": {
    "iso:country":"US",
    "sg:address":"1391 Elsinor Ave",
    "sg:city":"Ventura",
    "sg:classifiers":[
        {
            "category":"Manufacturing",
            "subcategory":"Paper Products",
            "type":"Manufacturing & Wholesale Goods"
        }
    ],
    "sg:phone":"+1 805 647 0343",
    "sg:postcode":"93004",
    "sg:province":"CA",
    "sg:tags":[
        "box"
    ],
    "wof:name":"D B Boxes",
    "wof:placetype":"venue"
},
  "geometry": {"coordinates":[-119.158021,34.276629],"type":"Point"}
}