{
  "type": "Feature",
  "properties": {
    "addr:full":"2100 Cormorant Dr Fairfield CA 94533",
    "addr:housenumber":"2100",
    "addr:postcode":"94533",
    "addr:street":"Cormorant Dr",
    "iso:country":"US",
    "sg:address":"2100 Cormorant Dr",
    "sg:city":"Fairfield",
    "sg:classifiers":[
        {
            "category":"Wholesale",
            "subcategory":"Auto Parts",
            "type":"Manufacturing & Wholesale Goods"
        }
    ],
    "sg:phone":"+1 707 425 5368",
    "sg:postcode":"94533",
    "sg:province":"CA",
    "sg:tags":[
        "operator",
        "local",
        "trucking"
    ],
    "wof:name":"Kents Distributing",
    "wof:placetype":"venue"
},
  "geometry": {"coordinates":[-122.008978,38.268485],"type":"Point"}
}