{
  "type": "Feature",
  "properties": {
    "addr:full":"8871 Research Dr Irvine CA 92618",
    "addr:housenumber":"8871",
    "addr:postcode":"92618",
    "addr:street":"Research Dr",
    "iso:country":"US",
    "sg:address":"8871 Research Dr",
    "sg:city":"Irvine",
    "sg:classifiers":[
        {
            "category":"Utilities",
            "subcategory":"Telephone",
            "type":"Services"
        }
    ],
    "sg:phone":"+1 949 425 1300",
    "sg:postcode":"92618",
    "sg:province":"CA",
    "sg:tags":[
        "wireless"
    ],
    "sg:website":"www.enlacewireless.com",
    "wof:name":"Cingular Wireless",
    "wof:placetype":"venue"
},
  "geometry": {"coordinates":[-117.737111,33.641408],"type":"Point"}
}