{
  "type": "Feature",
  "properties": {
    "addr:full":"16351 Gothard St Huntington Beach CA 92647",
    "addr:postcode":"16351;92647",
    "addr:street":"Gothard St",
    "iso:country":"US",
    "sg:address":"16351 Gothard St",
    "sg:city":"Huntington Beach",
    "sg:classifiers":[
        {
            "category":"Arts & Performance",
            "subcategory":"Theater",
            "type":"Entertainment"
        }
    ],
    "sg:phone":"+1 714 842 8422",
    "sg:postcode":"92647",
    "sg:province":"CA",
    "sg:tags":[
        "television",
        "program",
        "producer"
    ],
    "sg:website":"www.burrud.com",
    "wof:name":"Burrud Productions Inc",
    "wof:placetype":"venue"
},
  "geometry": {"coordinates":[-118.000297,33.725031],"type":"Point"}
}