{
  "type": "Feature",
  "properties": {
    "iso:country":"US",
    "sg:address":"26 Menker St",
    "sg:city":"Watsonville",
    "sg:classifiers":[
        {
            "category":"Freight",
            "type":"Transportation"
        }
    ],
    "sg:phone":"+1 831 724 8632",
    "sg:postcode":"95076",
    "sg:province":"CA",
    "sg:tags":[
        "operator",
        "trucking"
    ],
    "wof:name":"Solorio Trucking Company LLC",
    "wof:placetype":"venue"
},
  "geometry": {"coordinates":[-121.756773,36.905708],"type":"Point"}
}