{
  "type": "Feature",
  "properties": {
    "addr:full":"1378 Hilda Ave Glendale CA 91205",
    "addr:housenumber":"1378",
    "addr:postcode":"91205",
    "addr:street":"Hilda Ave",
    "iso:country":"US",
    "sg:address":"1378 Hilda Ave",
    "sg:city":"Glendale",
    "sg:classifiers":[
        {
            "category":"Building & Trades",
            "subcategory":"Construction",
            "type":"Services"
        }
    ],
    "sg:phone":"+1 818 241 4596",
    "sg:postcode":"91205",
    "sg:province":"CA",
    "sg:tags":[
        "designer"
    ],
    "wof:name":"Ol Au Design Lab",
    "wof:placetype":"venue"
},
  "geometry": {"coordinates":[-118.23549300000001,34.135361],"type":"Point"}
}