{
  "type": "Feature",
  "properties": {
    "iso:country":"US",
    "sg:address":"14432 Union Ave",
    "sg:city":"San Jose",
    "sg:classifiers":[
        {
            "category":"Personal",
            "subcategory":"Massage",
            "type":"Services"
        },
        {
            "category":"Personal",
            "subcategory":"Hair Removal",
            "type":"Services"
        },
        {
            "category":"Personal",
            "subcategory":"Skin Care",
            "type":"Services"
        }
    ],
    "sg:phone":"+1 408 371 5974",
    "sg:postcode":"95124",
    "sg:province":"CA",
    "sg:website":"www.newimagedayspa.com",
    "wof:name":"New Image Skin Care & Day Spa",
    "wof:placetype":"venue"
},
  "geometry": {"coordinates":[-121.931,37.257999],"type":"Point"}
}