{
  "type": "Feature",
  "properties": {
    "iso:country":"US",
    "sg:address":"388 Market St",
    "sg:city":"San Francisco",
    "sg:classifiers":[
        {
            "category":"Professional",
            "subcategory":"Lawyer & Legal Services",
            "type":"Services"
        }
    ],
    "sg:phone":"+1 415 956 5959",
    "sg:postcode":"94111",
    "sg:province":"CA",
    "sg:tags":[
        "attorney"
    ],
    "wof:name":"Spiegel Liao & Kagay",
    "wof:placetype":"venue"
},
  "geometry": {"coordinates":[-122.397382,37.792406],"type":"Point"}
}