{
  "type": "Feature",
  "properties": {
    "iso:country":"US",
    "sg:address":"8148 Orchid Dr",
    "sg:city":"Corona",
    "sg:classifiers":[
        {
            "category":"Real Estate",
            "subcategory":"Architect",
            "type":"Services"
        }
    ],
    "sg:phone":"+1 951 479 5464",
    "sg:postcode":"92880",
    "sg:province":"CA",
    "sg:tags":[
        "residential",
        "designer"
    ],
    "wof:name":"G & L Design Consultants",
    "wof:placetype":"venue"
},
  "geometry": {"coordinates":[-117.601286,33.94195],"type":"Point"}
}