{
  "type": "Feature",
  "properties": {
    "iso:country":"US",
    "sg:address":"625 Encino Vista Dr",
    "sg:city":"Thousand Oaks",
    "sg:classifiers":[
        {
            "category":"Professional",
            "type":"Services"
        }
    ],
    "sg:phone":"+1 805 496 1212",
    "sg:postcode":"91362",
    "sg:province":"CA",
    "wof:name":"Terrence J Kelley",
    "wof:placetype":"venue"
},
  "geometry": {"coordinates":[-118.859039,34.185661],"type":"Point"}
}