{
  "type": "Feature",
  "properties": {
    "addr:full":"3130 del Monte Blvd Marina CA 93933",
    "addr:housenumber":"3130",
    "addr:postcode":"93933",
    "addr:street":"Del Monte Blvd",
    "iso:country":"US",
    "sg:address":"3130 del Monte Blvd",
    "sg:city":"Marina",
    "sg:classifiers":[
        {
            "category":"Health Services",
            "subcategory":"Doctor",
            "type":"Services"
        }
    ],
    "sg:phone":"+1 831 883 3330",
    "sg:postcode":"93933",
    "sg:province":"CA",
    "sg:tags":[
        "clinic"
    ],
    "wof:name":"Doctors On Duty Medical Clncs",
    "wof:placetype":"venue"
},
  "geometry": {"coordinates":[-121.800613,36.68634],"type":"Point"}
}