{
  "type": "Feature",
  "properties": {
    "addr:full":"7101 Hwy 9 Felton CA 95018",
    "addr:housenumber":"7101",
    "addr:postcode":"95018",
    "addr:street":"Hwy 9",
    "iso:country":"US",
    "sg:address":"7101 Hwy 9",
    "sg:city":"Felton",
    "sg:classifiers":[
        {
            "category":"Education",
            "subcategory":"School",
            "type":"Public Place"
        }
    ],
    "sg:phone":"+1 831 335 0576",
    "sg:postcode":"95018",
    "sg:province":"CA",
    "sg:website":"www.slvhs.slv.k12.ca.us",
    "wof:name":"Valley Independent Prep",
    "wof:placetype":"venue"
},
  "geometry": {"coordinates":[-122.080111,37.062907],"type":"Point"}
}