{
  "type": "Feature",
  "properties": {
    "addr:full":"46509 Mission Blvd Fremont CA 94539",
    "addr:housenumber":"46509",
    "addr:postcode":"94539",
    "addr:street":"Mission Blvd",
    "iso:country":"US",
    "sg:address":"46509 Mission Blvd",
    "sg:city":"Fremont",
    "sg:classifiers":[
        {
            "category":"Banks & Credit Unions",
            "subcategory":"Bank",
            "type":"Services"
        }
    ],
    "sg:phone":"+1 510 249 0914",
    "sg:postcode":"94539",
    "sg:province":"CA",
    "sg:tags":[
        "financing"
    ],
    "wof:name":"Amex Financial",
    "wof:placetype":"venue"
},
  "geometry": {"coordinates":[-121.925954,37.492968],"type":"Point"}
}