{
  "type": "Feature",
  "properties": {
    "addr:full":"2601 Van Buren Pl Los Angeles CA 90007",
    "addr:housenumber":"2601",
    "addr:postcode":"90007",
    "addr:street":"Van Buren Pl",
    "iso:country":"US",
    "sg:address":"2601 Van Buren Pl",
    "sg:city":"Los Angeles",
    "sg:classifiers":[
        {
            "category":"Food & Beverages",
            "subcategory":"Groceries & Convenience Stores",
            "type":"Retail Goods"
        }
    ],
    "sg:phone":"+1 323 733 4311",
    "sg:postcode":"90007",
    "sg:province":"CA",
    "sg:tags":[
        "market"
    ],
    "wof:name":"Ninety Nine Plus Market",
    "wof:placetype":"venue"
},
  "geometry": {"coordinates":[-118.29698500000001,34.030908],"type":"Point"}
}