{
  "type": "Feature",
  "properties": {
    "addr:full":"101 Broadway Oakland CA 94607",
    "addr:housenumber":"101",
    "addr:postcode":"94607",
    "addr:street":"Broadway",
    "iso:country":"US",
    "sg:address":"101 Broadway",
    "sg:city":"Oakland",
    "sg:classifiers":[
        {
            "category":"Professional",
            "subcategory":"Lawyer & Legal Services",
            "type":"Services"
        }
    ],
    "sg:phone":"+1 510 839 6633",
    "sg:postcode":"94607",
    "sg:province":"CA",
    "sg:tags":[
        "attorney"
    ],
    "wof:name":"Rina Hirai Law Offices",
    "wof:placetype":"venue"
},
  "geometry": {"coordinates":[-122.276432,37.796085],"type":"Point"}
}