{
  "type": "Feature",
  "properties": {
    "iso:country":"US",
    "sg:address":"549 W el Camino Real",
    "sg:city":"Mountain View",
    "sg:classifiers":[
        {
            "category":"Retail",
            "subcategory":"Laundry & Dry Cleaning",
            "type":"Services"
        }
    ],
    "sg:phone":"+1 650 968 8000",
    "sg:postcode":"94040",
    "sg:province":"CA",
    "wof:name":"Laundry Express",
    "wof:placetype":"venue"
},
  "geometry": {"coordinates":[-122.079763,37.383523],"type":"Point"}
}