{
  "type": "Feature",
  "properties": {
    "iso:country":"US",
    "sg:address":"778 Clay St",
    "sg:city":"San Francisco",
    "sg:classifiers":[
        {
            "category":"Social Services",
            "subcategory":"Adult Care",
            "type":"Services"
        }
    ],
    "sg:phone":"+1 415 397 8322",
    "sg:postcode":"94108",
    "sg:province":"CA",
    "sg:tags":[
        "organization",
        "senior",
        "citizen"
    ],
    "wof:name":"American Asian Elderly Society",
    "wof:placetype":"venue"
},
  "geometry": {"coordinates":[-122.406077,37.794376],"type":"Point"}
}