{
  "type": "Feature",
  "properties": {
    "iso:country":"US",
    "sg:address":"10052 Rosecrans Ave",
    "sg:city":"Bellflower",
    "sg:classifiers":[
        {
            "category":"Personal",
            "subcategory":"Skin Care",
            "type":"Services"
        }
    ],
    "sg:phone":"+1 562 925 2577",
    "sg:postcode":"90706",
    "sg:province":"CA",
    "sg:website":"allaboutskinbyjoan.com/",
    "wof:name":"All About Skin",
    "wof:placetype":"venue"
},
  "geometry": {"coordinates":[-118.117944,33.902002],"type":"Point"}
}