{
  "type": "Feature",
  "properties": {
    "iso:country":"US",
    "sg:address":"1201 W Main St",
    "sg:city":"Ripon",
    "sg:classifiers":[
        {
            "category":"Personal",
            "subcategory":"Beauty Salon",
            "type":"Services"
        }
    ],
    "sg:phone":"+1 209 599 6800",
    "sg:postcode":"95366",
    "sg:province":"CA",
    "wof:name":"California Styling",
    "wof:placetype":"venue"
},
  "geometry": {"coordinates":[-121.136817,37.739522],"type":"Point"}
}