{
  "type": "Feature",
  "properties": {
    "addr:full":"2209 Fremont St Monterey CA 93940",
    "addr:housenumber":"2209",
    "addr:postcode":"93940",
    "addr:street":"Fremont St",
    "iso:country":"US",
    "sg:address":"2209 Fremont St",
    "sg:city":"Monterey",
    "sg:classifiers":[
        {
            "category":"Autos & Motor Vehicles",
            "subcategory":"Automobile Sales",
            "type":"Retail Goods"
        }
    ],
    "sg:phone":"+1 831 649 8294",
    "sg:postcode":"93940",
    "sg:province":"CA",
    "sg:tags":[
        "car",
        "used",
        "dealer"
    ],
    "wof:name":"S & S Auto Sales",
    "wof:placetype":"venue"
},
  "geometry": {"coordinates":[-121.856365,36.597177],"type":"Point"}
}