{
  "type": "Feature",
  "properties": {
    "iso:country":"US",
    "sg:address":"6835 Paradise Rd",
    "sg:city":"Salinas",
    "sg:classifiers":[
        {
            "category":"Social Services",
            "type":"Services"
        }
    ],
    "sg:phone":"+1 831 663 9200",
    "sg:postcode":"93907",
    "sg:province":"CA",
    "sg:tags":[
        "organization",
        "welfare"
    ],
    "wof:name":"Central Coast Youth Foundation",
    "wof:placetype":"venue"
},
  "geometry": {"coordinates":[-121.701509,36.814202],"type":"Point"}
}