{
  "type": "Feature",
  "properties": {
    "iso:country":"US",
    "sg:address":"555 S Arrowhead Ave",
    "sg:city":"San Bernardino",
    "sg:classifiers":[
        {
            "category":"Manufacturing",
            "subcategory":"Tools & Machinery",
            "type":"Manufacturing & Wholesale Goods"
        }
    ],
    "sg:phone":"+1 909 885 3851",
    "sg:postcode":"92408",
    "sg:province":"CA",
    "sg:tags":[
        "body",
        "automobile",
        "shop",
        "equipment"
    ],
    "wof:name":"Sherwin-Williams Paints",
    "wof:placetype":"venue"
},
  "geometry": {"coordinates":[-117.28959399999999,34.091566],"type":"Point"}
}