{
  "type": "Feature",
  "properties": {
    "addr:full":"41047 173rd St E Lancaster CA 93535",
    "addr:housenumber":"41047",
    "addr:postcode":"93535",
    "addr:street":"173Rd St E",
    "iso:country":"US",
    "sg:address":"41047 173rd St E",
    "sg:city":"Lancaster",
    "sg:classifiers":[
        {
            "category":"Place Of Worship",
            "type":"Public Place"
        }
    ],
    "sg:phone":"+1 661 264 3047",
    "sg:postcode":"93535",
    "sg:province":"CA",
    "sg:tags":[
        "church"
    ],
    "wof:name":"Bgc Unlimited",
    "wof:placetype":"venue"
},
  "geometry": {"coordinates":[-117.82154199999999,34.624919],"type":"Point"}
}