{
  "type": "Feature",
  "properties": {
    "addr:full":"221 Madonna Rd San Luis Obispo CA 93405",
    "addr:housenumber":"221",
    "addr:postcode":"93405",
    "addr:street":"Madonna Rd",
    "iso:country":"US",
    "sg:address":"221 Madonna Rd",
    "sg:city":"San Luis Obispo",
    "sg:classifiers":[
        {
            "category":"Real Estate",
            "subcategory":"Real Estate Operator",
            "type":"Services"
        }
    ],
    "sg:phone":"+1 805 544 5710",
    "sg:postcode":"93405",
    "sg:province":"CA",
    "sg:tags":[
        "development",
        "company",
        "plaza"
    ],
    "wof:name":"Madonna Plaza Instnl Assoc",
    "wof:placetype":"venue"
},
  "geometry": {"coordinates":[-120.676104,35.263996],"type":"Point"}
}