{
  "type": "Feature",
  "properties": {
    "iso:country":"US",
    "sg:address":"1911 Hillhurst Ave",
    "sg:city":"Los Angeles",
    "sg:classifiers":[
        {
            "category":"Professional",
            "subcategory":"Detective & Security Services",
            "type":"Services"
        }
    ],
    "sg:phone":"+1 323 664 5277",
    "sg:postcode":"90027",
    "sg:province":"CA",
    "sg:tags":[
        "guard",
        "patrol"
    ],
    "wof:name":"Los Angeles Protection Svc",
    "wof:placetype":"venue"
},
  "geometry": {"coordinates":[-118.287493,34.106562],"type":"Point"}
}