{
  "type": "Feature",
  "properties": {
    "addr:full":"Hilton San Diego Resort & Spa 1775 East Mission Bay Drive San Diego CA 92109",
    "addr:housenumber":"1775",
    "addr:postcode":"92109",
    "addr:street":"East Mission Bay Drive",
    "iso:country":"US",
    "sg:address":"Hilton San Diego Resort & Spa 1775 East Mission Bay Drive",
    "sg:city":"San Diego",
    "sg:classifiers":[
        {
            "category":"Personal",
            "subcategory":"Day Spa",
            "type":"Services"
        }
    ],
    "sg:phone":"+1 619 276 4010",
    "sg:postcode":"92109",
    "sg:province":"CA",
    "sg:website":"www.hilton.com/en/hi/hotels/hote...",
    "wof:name":"Spa Brezza",
    "wof:placetype":"venue"
},
  "geometry": {"coordinates":[-117.20959499999999,32.777304],"type":"Point"}
}