{
  "type": "Feature",
  "properties": {
    "addr:full":"4125 Inglewood Blvd. Los Angeles CA 90066",
    "addr:housenumber":"4125",
    "addr:postcode":"90066",
    "addr:street":"Inglewood Blvd.",
    "iso:country":"US",
    "sg:address":"4125 Inglewood Blvd.",
    "sg:city":"Los Angeles",
    "sg:classifiers":[
        {
            "category":"Banks & Credit Unions",
            "subcategory":"Atm",
            "type":"Services"
        }
    ],
    "sg:phone":"+1 323 304 1961",
    "sg:postcode":"90066",
    "sg:province":"CA",
    "sg:tags":[
        "bankruptcy"
    ],
    "sg:website":"bankruptcy-losangeles.com/",
    "wof:name":"Los Angeles Bankruptcy Specialist",
    "wof:placetype":"venue"
},
  "geometry": {"coordinates":[-118.423958,33.999427],"type":"Point"}
}