{
  "type": "Feature",
  "properties": {
    "addr:full":"8405 Pershing Drive Playa Del Rey CA 90293",
    "addr:housenumber":"8405",
    "addr:postcode":"90293",
    "addr:street":"Pershing Drive",
    "iso:country":"US",
    "sg:address":"8405 Pershing Drive",
    "sg:city":"Playa Del Rey",
    "sg:classifiers":[
        {
            "category":"Parking",
            "type":"Transportation"
        }
    ],
    "sg:phone":"+1 310 301 8078",
    "sg:postcode":"90293",
    "sg:province":"CA",
    "wof:name":"Ouellet Jas V",
    "wof:placetype":"venue"
},
  "geometry": {"coordinates":[-118.443067,33.957296],"type":"Point"}
}