{
  "type": "Feature",
  "properties": {
    "addr:full":"4864 Bresee Ave Baldwin Park CA 91706",
    "addr:postcode":"4864;91706",
    "addr:street":"Bresee Ave",
    "iso:country":"US",
    "sg:address":"4864 Bresee Ave",
    "sg:city":"Baldwin Park",
    "sg:classifiers":[
        {
            "category":"Building & Trades",
            "subcategory":"Construction",
            "type":"Services"
        }
    ],
    "sg:phone":"+1 626 962 5349",
    "sg:postcode":"91706",
    "sg:province":"CA",
    "sg:tags":[
        "contractor"
    ],
    "wof:name":"Henrys Fence",
    "wof:placetype":"venue"
},
  "geometry": {"coordinates":[-117.971074,34.101812],"type":"Point"}
}