{
  "type": "Feature",
  "properties": {
    "iso:country":"US",
    "sg:address":"1125 Miller Ave",
    "sg:city":"Berkeley",
    "sg:classifiers":[
        {
            "category":"Professional",
            "subcategory":"Computer Services",
            "type":"Services"
        }
    ],
    "sg:phone":"+1 510 548 3053",
    "sg:postcode":"94708",
    "sg:province":"CA",
    "sg:tags":[
        "designer",
        "rooms-installation",
        "consultant",
        "system",
        "equipment"
    ],
    "wof:name":"Mapps Inc.",
    "wof:placetype":"venue"
},
  "geometry": {"coordinates":[-122.25593499999999,37.891075],"type":"Point"}
}