{
  "type": "Feature",
  "properties": {
    "iso:country":"US",
    "sg:address":"3398 22nd St",
    "sg:city":"San Francisco",
    "sg:classifiers":[
        {
            "category":"Food & Beverages",
            "subcategory":"Groceries & Convenience Stores",
            "type":"Retail Goods"
        }
    ],
    "sg:phone":"+1 415 826 5584",
    "sg:postcode":"94110",
    "sg:province":"CA",
    "wof:name":"Pride Superette",
    "wof:placetype":"venue"
},
  "geometry": {"coordinates":[-122.42312699999999,37.75521],"type":"Point"}
}