{
  "type": "Feature",
  "properties": {
    "addr:full":"2330 1/2 Stockton Blvd Sacramento CA 95817",
    "addr:housenumber":"2330 1 / 2",
    "addr:postcode":"95817",
    "addr:street":"Stockton Blvd",
    "iso:country":"US",
    "sg:address":"2330 1/2 Stockton Blvd",
    "sg:city":"Sacramento",
    "sg:classifiers":[
        {
            "category":"Community Center",
            "type":"Public Place"
        }
    ],
    "sg:phone":"+1 916 734 2401",
    "sg:postcode":"95817",
    "sg:province":"CA",
    "sg:tags":[
        "medical"
    ],
    "wof:name":"UC Davis Health System",
    "wof:placetype":"venue"
},
  "geometry": {"coordinates":[-121.45739,38.554029],"type":"Point"}
}