{
  "type": "Feature",
  "properties": {
    "iso:country":"US",
    "sg:address":"48861 Royal Oaks Dr",
    "sg:city":"Oakhurst",
    "sg:classifiers":[
        {
            "category":"Shopping",
            "subcategory":"Luggage & Leather Goods",
            "type":"Retail Goods"
        }
    ],
    "sg:phone":"+1 559 683 0798",
    "sg:postcode":"93644",
    "sg:province":"CA",
    "wof:name":"Elden's Leatherworks",
    "wof:placetype":"venue"
},
  "geometry": {"coordinates":[-119.656043,37.327975],"type":"Point"}
}