{
  "type": "Feature",
  "properties": {
    "addr:full":"9542 Sunflower St Rancho Cucamonga CA 91737",
    "addr:housenumber":"9542",
    "addr:postcode":"91737",
    "addr:street":"Sunflower St",
    "iso:country":"US",
    "sg:address":"9542 Sunflower St",
    "sg:city":"Rancho Cucamonga",
    "sg:classifiers":[
        {
            "category":"Professional",
            "type":"Services"
        }
    ],
    "sg:phone":"+1 909 948 5978",
    "sg:postcode":"91737",
    "sg:province":"CA",
    "wof:name":"3x Converting",
    "wof:placetype":"venue"
},
  "geometry": {"coordinates":[-117.59602,34.146215],"type":"Point"}
}