{
  "type": "Feature",
  "properties": {
    "addr:full":"4601 Grissom St Bakersfield CA 93309",
    "addr:housenumber":"4601",
    "addr:postcode":"93309",
    "addr:street":"Grissom St",
    "iso:country":"US",
    "sg:address":"4601 Grissom St",
    "sg:city":"Bakersfield",
    "sg:classifiers":[
        {
            "category":"Wholesale",
            "subcategory":"Sporting Goods",
            "type":"Manufacturing & Wholesale Goods"
        }
    ],
    "sg:phone":"+1 661 837 8344",
    "sg:postcode":"93309",
    "sg:province":"CA",
    "sg:tags":[
        "equipment",
        "pool",
        "swimming"
    ],
    "wof:name":"SCP Pool Corp",
    "wof:placetype":"venue"
},
  "geometry": {"coordinates":[-119.061474,35.313981],"type":"Point"}
}