{
  "type": "Feature",
  "properties": {
    "iso:country":"US",
    "sg:address":"2802 Juan St",
    "sg:city":"San Diego",
    "sg:classifiers":[
        {
            "category":"Professional",
            "subcategory":"Management & Consulting",
            "type":"Services"
        }
    ],
    "sg:phone":"+1 619 294 8602",
    "sg:postcode":"92110",
    "sg:province":"CA",
    "sg:tags":[
        "consultant",
        "business"
    ],
    "wof:name":"Interstate Management & Acctng",
    "wof:placetype":"venue"
},
  "geometry": {"coordinates":[-117.1972,32.755986],"type":"Point"}
}