{
  "type": "Feature",
  "properties": {
    "addr:full":"3444 W Clinton Ave Fresno CA 93722",
    "addr:housenumber":"3444",
    "addr:postcode":"93722",
    "addr:street":"W Clinton Ave",
    "iso:country":"US",
    "sg:address":"3444 W Clinton Ave",
    "sg:city":"Fresno",
    "sg:classifiers":[
        {
            "category":"Communications",
            "subcategory":"Film & Video Production",
            "type":"Services"
        }
    ],
    "sg:phone":"+1 559 260 7136",
    "sg:postcode":"93722",
    "sg:province":"CA",
    "sg:tags":[
        "taping"
    ],
    "wof:name":"Hmong Pacific Entertainment",
    "wof:placetype":"venue"
},
  "geometry": {"coordinates":[-119.85421100000001,36.771965],"type":"Point"}
}