{
  "type": "Feature",
  "properties": {
    "iso:country":"US",
    "sg:address":"1218 Cll Fantasia",
    "sg:city":"San Marcos",
    "sg:classifiers":[
        {
            "category":"Building & Trades",
            "subcategory":"Landscaping Services",
            "type":"Services"
        }
    ],
    "sg:phone":"+1 760 599 9172",
    "sg:postcode":"92069",
    "sg:province":"CA",
    "wof:name":"Sunset Gardening Service",
    "wof:placetype":"venue"
},
  "geometry": {"coordinates":[-117.185393,33.16145],"type":"Point"}
}