{
  "type": "Feature",
  "properties": {
    "addr:full":"24360 Amador St Hayward CA 94544",
    "addr:housenumber":"24360",
    "addr:postcode":"94544",
    "addr:street":"Amador St",
    "iso:country":"US",
    "sg:address":"24360 Amador St",
    "sg:city":"Hayward",
    "sg:classifiers":[
        {
            "category":"Parking",
            "type":"Transportation"
        }
    ],
    "sg:phone":"+1 510 732 5928",
    "sg:postcode":"94544",
    "sg:province":"CA",
    "sg:tags":[
        "garage"
    ],
    "wof:name":"Douglas Parking Co",
    "wof:placetype":"venue"
},
  "geometry": {"coordinates":[-122.094065,37.658051],"type":"Point"}
}