{
  "type": "Feature",
  "properties": {
    "iso:country":"US",
    "sg:address":"420 Edgerton Dr",
    "sg:city":"San Bernardino",
    "sg:classifiers":[
        {
            "category":"Professional",
            "subcategory":"Management & Consulting",
            "type":"Services"
        }
    ],
    "sg:phone":"+1 909 224 2141",
    "sg:postcode":"92405",
    "sg:province":"CA",
    "sg:tags":[
        "consultant"
    ],
    "wof:name":"Allied Resources Intl",
    "wof:placetype":"venue"
},
  "geometry": {"coordinates":[-117.290589,34.160631],"type":"Point"}
}