{
  "type": "Feature",
  "properties": {
    "addr:full":"323 W Valley Blvd San Gabriel CA 91776",
    "addr:housenumber":"323",
    "addr:postcode":"91776",
    "addr:street":"W Valley Blvd",
    "iso:country":"US",
    "sg:address":"323 W Valley Blvd",
    "sg:city":"San Gabriel",
    "sg:classifiers":[
        {
            "category":"Health Services",
            "subcategory":"Doctor",
            "type":"Services"
        }
    ],
    "sg:phone":"+1 626 300 0005",
    "sg:postcode":"91776",
    "sg:province":"CA",
    "wof:name":"Doan Gia-Gia MD",
    "wof:placetype":"venue"
},
  "geometry": {"coordinates":[-118.103996,34.079399],"type":"Point"}
}