{
  "type": "Feature",
  "properties": {
    "addr:full":"3400 W Ball Rd Ste 207 Anaheim CA 92804",
    "addr:housenumber":"3400",
    "addr:postcode":"92804",
    "addr:street":"W Ball Rd Ste 207",
    "iso:country":"US",
    "sg:address":"3400 W Ball Rd Ste 207",
    "sg:city":"Anaheim",
    "sg:classifiers":[
        {
            "category":"Health Services",
            "subcategory":"Doctor",
            "type":"Services"
        }
    ],
    "sg:phone":"+1 714 826 7440",
    "sg:postcode":"92804",
    "sg:province":"CA",
    "sg:tags":[
        "medicine",
        "physician",
        "practice",
        "surgeons",
        "family"
    ],
    "wof:name":"Dariush, Javanshir M.D., Inc.",
    "wof:placetype":"venue"
},
  "geometry": {"coordinates":[-118.007919,33.81728],"type":"Point"}
}