{
  "type": "Feature",
  "properties": {
    "iso:country":"US",
    "sg:address":"1658 11th St",
    "sg:city":"Santa Monica",
    "sg:classifiers":[
        {
            "category":"Shopping",
            "subcategory":"Used Merchandise",
            "type":"Retail Goods"
        }
    ],
    "sg:phone":"+1 310 450 7235",
    "sg:postcode":"90404",
    "sg:province":"CA",
    "sg:tags":[
        "shop",
        "thrift"
    ],
    "wof:name":"Salvation Army Thrift Store",
    "wof:placetype":"venue"
},
  "geometry": {"coordinates":[-118.48412500000001,34.018136],"type":"Point"}
}