{
  "type": "Feature",
  "properties": {
    "addr:full":"11355 W Olympic Blvd Los Angeles CA 90064",
    "addr:housenumber":"11355",
    "addr:postcode":"90064",
    "addr:street":"W Olympic Blvd",
    "iso:country":"US",
    "sg:address":"11355 W Olympic Blvd",
    "sg:city":"Los Angeles",
    "sg:classifiers":[
        {
            "category":"Professional",
            "subcategory":"Lawyer & Legal Services",
            "type":"Services"
        }
    ],
    "sg:phone":"+1 310 312 6733",
    "sg:postcode":"90064",
    "sg:province":"CA",
    "wof:name":"Wegner Steven D Law Offices of",
    "wof:placetype":"venue"
},
  "geometry": {"coordinates":[-118.442001,34.037601],"type":"Point"}
}