{
  "type": "Feature",
  "properties": {
    "iso:country":"US",
    "sg:address":"200 S Elm Drive",
    "sg:city":"Beverly Hills",
    "sg:classifiers":[
        {
            "category":"Education",
            "subcategory":"School",
            "type":"Public Place"
        }
    ],
    "sg:phone":"+1 310 229 3665",
    "sg:postcode":"90212",
    "sg:province":"CA",
    "sg:tags":[
        "high",
        "middle",
        "elementary"
    ],
    "sg:website":"www.beverlyhills.k12.ca.us",
    "wof:name":"Beverly Hills Unified School District",
    "wof:placetype":"venue"
},
  "geometry": {"coordinates":[-118.395006,34.064923],"type":"Point"}
}