{
  "type": "Feature",
  "properties": {
    "addr:full":"3540 Oakdale Rd Modesto CA 95357",
    "addr:housenumber":"3540",
    "addr:postcode":"ca 95357",
    "addr:street":"Oakdale Rd",
    "iso:country":"US",
    "sg:address":"3540 Oakdale Rd",
    "sg:city":"Modesto",
    "sg:classifiers":[
        {
            "category":"Organizations",
            "subcategory":"Religious Organization",
            "type":"Services"
        }
    ],
    "sg:phone":"+1 209 551 2927",
    "sg:postcode":"95357",
    "sg:province":"CA",
    "sg:tags":[
        "church"
    ],
    "wof:name":"Grace Worship Ctr",
    "wof:placetype":"venue"
},
  "geometry": {"coordinates":[-120.957949,37.691119],"type":"Point"}
}