{
  "type": "Feature",
  "properties": {
    "addr:full":"36243 Inland Valley Dr Ste 260 Wildomar CA 92595",
    "addr:postcode":"36243;92595",
    "addr:street":"Inland Valley Dr Ste 260",
    "iso:country":"US",
    "sg:address":"36243 Inland Valley Dr Ste 260",
    "sg:city":"Wildomar",
    "sg:classifiers":[
        {
            "category":"Health Services",
            "subcategory":"Medical Lab",
            "type":"Services"
        }
    ],
    "sg:phone":"+1 866 322 7154",
    "sg:postcode":"92595",
    "sg:province":"CA",
    "wof:name":"STD Tests Wildomar STD Testing Center",
    "wof:placetype":"venue"
},
  "geometry": {"coordinates":[-117.236808,33.596144],"type":"Point"}
}