{
  "type": "Feature",
  "properties": {
    "addr:full":"7906 Santa Monica Blvd Los Angeles CA 90046",
    "addr:housenumber":"7906",
    "addr:postcode":"90046",
    "addr:street":"Santa Monica Blvd",
    "iso:country":"US",
    "sg:address":"7906 Santa Monica Blvd",
    "sg:city":"Los Angeles",
    "sg:classifiers":[
        {
            "category":"Professional",
            "subcategory":"Computer Services",
            "type":"Services"
        }
    ],
    "sg:phone":"+1 740 972 6939",
    "sg:postcode":"90046",
    "sg:province":"CA",
    "sg:website":"http://www.profounder.com",
    "wof:name":"ProFounder",
    "wof:placetype":"venue"
},
  "geometry": {"coordinates":[-118.362664,34.090722],"type":"Point"}
}