{
  "type": "Feature",
  "properties": {
    "addr:full":"1724 N Vermont Ave Los Angeles CA 90027",
    "addr:housenumber":"1724",
    "addr:postcode":"90027",
    "addr:street":"N Vermont Ave",
    "iso:country":"US",
    "sg:address":"1724 N Vermont Ave",
    "sg:city":"Los Angeles",
    "sg:classifiers":[
        {
            "category":"Shopping",
            "subcategory":"Clothing, Apparel, & Fashions",
            "type":"Retail Goods"
        }
    ],
    "sg:phone":"+1 323 666 2965",
    "sg:postcode":"90027",
    "sg:province":"CA",
    "sg:tags":[
        "hair",
        "salon"
    ],
    "sg:website":"www.purple-circle.com",
    "wof:name":"Purple Circle",
    "wof:placetype":"venue"
},
  "geometry": {"coordinates":[-118.291392,34.102526],"type":"Point"}
}