{
  "type": "Feature",
  "properties": {
    "addr:full":"3390 Cherry Avenue Long Beach CA 90807",
    "addr:housenumber":"3390",
    "addr:postcode":"90807",
    "addr:street":"Cherry Avenue",
    "iso:country":"US",
    "sg:address":"3390 Cherry Avenue",
    "sg:city":"Long Beach",
    "sg:classifiers":[
        {
            "category":"Retail",
            "subcategory":"Car Wash",
            "type":"Services"
        }
    ],
    "sg:phone":"+1 562 988 2868",
    "sg:postcode":"90807",
    "sg:province":"CA",
    "wof:name":"Cherry Hill Auto Wash",
    "wof:placetype":"venue"
},
  "geometry": {"coordinates":[-118.167151,33.818465],"type":"Point"}
}