{
  "type": "Feature",
  "properties": {
    "iso:country":"US",
    "sg:address":"1800 Robertson Rd",
    "sg:city":"Modesto",
    "sg:classifiers":[
        {
            "category":"Food & Beverages",
            "subcategory":"Groceries & Convenience Stores",
            "type":"Retail Goods"
        }
    ],
    "sg:phone":"+1 209 521 0177",
    "sg:postcode":"95351",
    "sg:province":"CA",
    "wof:name":"River View Market",
    "wof:placetype":"venue"
},
  "geometry": {"coordinates":[-121.018997,37.6134],"type":"Point"}
}