{
  "type": "Feature",
  "properties": {
    "iso:country":"US",
    "sg:address":"14750 Arminta St",
    "sg:city":"Panorama City",
    "sg:classifiers":[
        {
            "category":"Wholesale",
            "subcategory":"Electrical",
            "type":"Manufacturing & Wholesale Goods"
        }
    ],
    "sg:phone":"+1 818 786 8226",
    "sg:postcode":"91402",
    "sg:province":"CA",
    "sg:tags":[
        "repair",
        "armature"
    ],
    "wof:name":"HP Electric Motor Service",
    "wof:placetype":"venue"
},
  "geometry": {"coordinates":[-118.450532,34.213332],"type":"Point"}
}