{
  "type": "Feature",
  "properties": {
    "addr:full":"9400 Brighton Way Ste 309 Beverly Hills CA 90210",
    "addr:housenumber":"9400",
    "addr:postcode":"90210",
    "addr:street":"Brighton Way Ste 309;Hills Ca",
    "iso:country":"US",
    "sg:address":"9400 Brighton Way Ste 309",
    "sg:city":"Beverly Hills",
    "sg:classifiers":[
        {
            "category":"Health Services",
            "subcategory":"Dentist",
            "type":"Services"
        }
    ],
    "sg:phone":"+1 310 273 7397",
    "sg:postcode":"90210",
    "sg:province":"CA",
    "sg:website":"www.bhcdental.com",
    "wof:name":"Beverly Hills Cosmetic Dentistry",
    "wof:placetype":"venue"
},
  "geometry": {"coordinates":[-118.401016,34.070254],"type":"Point"}
}