{
  "type": "Feature",
  "properties": {
    "iso:country":"US",
    "sg:address":"900 Van Ness Ave",
    "sg:city":"San Francisco",
    "sg:classifiers":[
        {
            "category":"Utilities",
            "subcategory":"Mobile Phone",
            "type":"Services"
        }
    ],
    "sg:phone":"+1 415 440 5370",
    "sg:postcode":"94109",
    "sg:province":"CA",
    "sg:tags":[
        "communication",
        "radiotelephone"
    ],
    "wof:name":"Metro PCS Wireless",
    "wof:placetype":"venue"
},
  "geometry": {"coordinates":[-122.421018,37.784303],"type":"Point"}
}