{
  "type": "Feature",
  "properties": {
    "addr:full":"4349 Heather Ridge Ln Redding CA 96001",
    "addr:housenumber":"4349",
    "addr:postcode":"96001",
    "addr:street":"Heather Ridge Ln",
    "iso:country":"US",
    "sg:address":"4349 Heather Ridge Ln",
    "sg:city":"Redding",
    "sg:classifiers":[
        {
            "category":"Building & Trades",
            "subcategory":"Landscaping Services",
            "type":"Services"
        }
    ],
    "sg:phone":"+1 530 246 4070",
    "sg:postcode":"96001",
    "sg:province":"CA",
    "sg:tags":[
        "designer",
        "landscape"
    ],
    "wof:name":"Landscape Artistry",
    "wof:placetype":"venue"
},
  "geometry": {"coordinates":[-122.41442000000001,40.55037],"type":"Point"}
}