{
  "type": "Feature",
  "properties": {
    "addr:full":"701 W Kimberly Ave Ste 120 Placentia CA 92870",
    "addr:housenumber":"701",
    "addr:postcode":"ste 120;ca 92870",
    "addr:street":"W Kimberly Ave",
    "iso:country":"US",
    "sg:address":"701 W Kimberly Ave Ste 120",
    "sg:city":"Placentia",
    "sg:classifiers":[
        {
            "category":"Retail",
            "subcategory":"Auto Repair",
            "type":"Services"
        }
    ],
    "sg:phone":"+1 714 961 7940",
    "sg:postcode":"92870",
    "sg:province":"CA",
    "sg:website":"www.ca.gov",
    "wof:name":"California State of",
    "wof:placetype":"venue"
},
  "geometry": {"coordinates":[-117.879997,33.863098],"type":"Point"}
}