{
  "type": "Feature",
  "properties": {
    "addr:full":"16900 Clark Ave Bellflower CA 90706",
    "addr:housenumber":"16900",
    "addr:postcode":"90706",
    "addr:street":"Clark Ave",
    "iso:country":"US",
    "sg:address":"16900 Clark Ave",
    "sg:city":"Bellflower",
    "sg:classifiers":[
        {
            "category":"Retail",
            "subcategory":"Auto Repair",
            "type":"Services"
        }
    ],
    "sg:phone":"+1 562 925 8913",
    "sg:postcode":"90706",
    "sg:province":"CA",
    "sg:tags":[
        "body",
        "shop"
    ],
    "wof:name":"Jrf Body Shop",
    "wof:placetype":"venue"
},
  "geometry": {"coordinates":[-118.13400300000001,33.881001],"type":"Point"}
}