{
  "type": "Feature",
  "properties": {
    "iso:country":"US",
    "sg:address":"16900 Clark Ave",
    "sg:city":"Bellflower",
    "sg:classifiers":[
        {
            "category":"Retail",
            "subcategory":"Auto Repair",
            "type":"Services"
        }
    ],
    "sg:phone":"+1 562 925 8913",
    "sg:postcode":"90706",
    "sg:province":"CA",
    "sg:tags":[
        "body",
        "shop"
    ],
    "wof:name":"Jrf Body Shop",
    "wof:placetype":"venue"
},
  "geometry": {"coordinates":[-118.134003,33.881001],"type":"Point"}
}