{
  "type": "Feature",
  "properties": {
    "addr:full":"2615 Forest Ave Chico CA 95928",
    "addr:housenumber":"2615",
    "addr:postcode":"95928",
    "addr:street":"Forest Ave",
    "iso:country":"US",
    "sg:address":"2615 Forest Ave",
    "sg:city":"Chico",
    "sg:classifiers":[
        {
            "category":"Health Services",
            "subcategory":"Medical Lab",
            "type":"Services"
        }
    ],
    "sg:phone":"+1 530 343 3482",
    "sg:postcode":"95928",
    "sg:province":"CA",
    "sg:tags":[
        "imaging"
    ],
    "wof:name":"Advance Craniofacial Imaging",
    "wof:placetype":"venue"
},
  "geometry": {"coordinates":[-121.792286,39.717191],"type":"Point"}
}