{
  "type": "Feature",
  "properties": {
    "addr:full":"9478 Lime Ave Fontana CA 92335",
    "addr:housenumber":"9478",
    "addr:postcode":"92335",
    "addr:street":"Lime Ave",
    "iso:country":"US",
    "sg:address":"9478 Lime Ave",
    "sg:city":"Fontana",
    "sg:classifiers":[
        {
            "category":"Autos & Motor Vehicles",
            "subcategory":"Auto Supplies",
            "type":"Retail Goods"
        }
    ],
    "sg:phone":"+1 909 574 9507",
    "sg:postcode":"92335",
    "sg:province":"CA",
    "sg:tags":[
        "tire"
    ],
    "wof:name":"Crist Truck Tire Service",
    "wof:placetype":"venue"
},
  "geometry": {"coordinates":[-117.464641,34.081462],"type":"Point"}
}