{
  "type": "Feature",
  "properties": {
    "addr:full":"2401 Lomitas Ave Santa Rosa CA 95404",
    "addr:housenumber":"2401",
    "addr:postcode":"95404",
    "addr:street":"Lomitas Ave",
    "iso:country":"US",
    "sg:address":"2401 Lomitas Ave",
    "sg:city":"Santa Rosa",
    "sg:classifiers":[
        {
            "category":"Professional",
            "subcategory":"Art Services",
            "type":"Services"
        }
    ],
    "sg:phone":"+1 707 575 1205",
    "sg:postcode":"95404",
    "sg:province":"CA",
    "sg:tags":[
        "photographer"
    ],
    "wof:name":"Paul Miller",
    "wof:placetype":"venue"
},
  "geometry": {"coordinates":[-122.71644999999999,38.465221],"type":"Point"}
}