{
  "type": "Feature",
  "properties": {
    "addr:full":"955 Post Street San Francisco CA 94109",
    "addr:housenumber":"955",
    "addr:postcode":"94109",
    "addr:street":"Post Street",
    "iso:country":"US",
    "sg:address":"955 Post Street",
    "sg:city":"San Francisco",
    "sg:classifiers":[
        {
            "category":"Retail",
            "subcategory":"Auto Repair",
            "type":"Services"
        }
    ],
    "sg:phone":"+1 415 771 4050",
    "sg:postcode":"94109",
    "sg:province":"CA",
    "wof:name":"Post Auto Repair Inc",
    "wof:placetype":"venue"
},
  "geometry": {"coordinates":[-122.417637,37.787168],"type":"Point"}
}