{
  "type": "Feature",
  "properties": {
    "iso:country":"US",
    "sg:address":"632 N Garfield Ave",
    "sg:city":"Monterey Park",
    "sg:classifiers":[
        {
            "category":"Autos & Motor Vehicles",
            "subcategory":"Fuel & Gas Station",
            "type":"Retail Goods"
        }
    ],
    "sg:phone":"+1 626 288 5570",
    "sg:postcode":"91755",
    "sg:province":"CA",
    "sg:tags":[
        "oil"
    ],
    "wof:name":"Au Shell",
    "wof:placetype":"venue"
},
  "geometry": {"coordinates":[-118.122902,34.068608],"type":"Point"}
}