{
  "type": "Feature",
  "properties": {
    "addr:full":"2400 Pacific Ave Ste 507 San Francisco CA 94115",
    "addr:housenumber":"2400",
    "addr:postcode":"94115",
    "addr:street":"Pacific Ave Ste 507",
    "iso:country":"US",
    "sg:address":"2400 Pacific Ave Ste 507",
    "sg:city":"San Francisco",
    "sg:classifiers":[
        {
            "category":"Building & Trades",
            "subcategory":"Construction",
            "type":"Services"
        }
    ],
    "sg:phone":"+1 415 921 5534",
    "sg:postcode":"94115",
    "sg:province":"CA",
    "sg:tags":[
        "interior",
        "design"
    ],
    "sg:website":"kitchendesignbyjoanne.com",
    "wof:name":"Joanne Cannell Kitchen & Bath Design",
    "wof:placetype":"venue"
},
  "geometry": {"coordinates":[-122.435069,37.793543],"type":"Point"}
}