{
  "type": "Feature",
  "properties": {
    "addr:full":"3965 State St Santa Barbara CA 93105",
    "addr:housenumber":"3965",
    "addr:postcode":"93105",
    "addr:street":"State St",
    "iso:country":"US",
    "sg:address":"3965 State St",
    "sg:city":"Santa Barbara",
    "sg:classifiers":[
        {
            "category":"Shopping",
            "subcategory":"Department Store",
            "type":"Retail Goods"
        }
    ],
    "sg:phone":"+1 805 683 1174",
    "sg:postcode":"93105",
    "sg:province":"CA",
    "wof:name":"Ross Dress For Less",
    "wof:placetype":"venue"
},
  "geometry": {"coordinates":[-119.752228,34.440372],"type":"Point"}
}