{
  "type": "Feature",
  "properties": {
    "addr:full":"2211 W 78th St Inglewood CA 90305",
    "addr:housenumber":"2211",
    "addr:postcode":"90305",
    "addr:street":"W 78Th St",
    "iso:country":"US",
    "sg:address":"2211 W 78th St",
    "sg:city":"Inglewood",
    "sg:classifiers":[
        {
            "category":"Manufacturing",
            "subcategory":"Printing",
            "type":"Manufacturing & Wholesale Goods"
        }
    ],
    "sg:phone":"+1 323 759 0039",
    "sg:postcode":"90305",
    "sg:province":"CA",
    "sg:tags":[
        "publishing"
    ],
    "wof:name":"Gwis Publishing Co",
    "wof:placetype":"venue"
},
  "geometry": {"coordinates":[-118.31979699999999,33.969168],"type":"Point"}
}