{
  "type": "Feature",
  "properties": {
    "iso:country":"US",
    "sg:address":"4059 Edwards Ave",
    "sg:city":"Oakland",
    "sg:classifiers":[
        {
            "category":"Shopping",
            "subcategory":"Computers & Home Electronics",
            "type":"Retail Goods"
        }
    ],
    "sg:phone":"+1 510 382 0558",
    "sg:postcode":"94605",
    "sg:province":"CA",
    "sg:tags":[
        "radio",
        "television",
        "electronic",
        "store"
    ],
    "wof:name":"Tanya Enterprises - Parent Co",
    "wof:placetype":"venue"
},
  "geometry": {"coordinates":[-122.165857,37.775288],"type":"Point"}
}