{
  "type": "Feature",
  "properties": {
    "addr:full":"10213 Rosecrans Ave Bellflower CA 90706",
    "addr:housenumber":"10213",
    "addr:postcode":"90706",
    "addr:street":"Rosecrans Ave",
    "iso:country":"US",
    "sg:address":"10213 Rosecrans Ave",
    "sg:city":"Bellflower",
    "sg:classifiers":[
        {
            "category":"Health Services",
            "subcategory":"Nursing And Care Facility",
            "type":"Services"
        }
    ],
    "sg:phone":"+1 562 461 0600",
    "sg:postcode":"90706",
    "sg:province":"CA",
    "sg:tags":[
        "hospice"
    ],
    "wof:name":"Viva Hospice Svc Inc",
    "wof:placetype":"venue"
},
  "geometry": {"coordinates":[-118.11526499999999,33.902118],"type":"Point"}
}