{
  "type": "Feature",
  "properties": {
    "addr:full":"927 E Hillsdale Blvd Foster City CA 94403",
    "addr:housenumber":"927",
    "addr:postcode":"94403",
    "addr:street":"E Hillsdale Blvd",
    "iso:country":"US",
    "sg:address":"927 E Hillsdale Blvd",
    "sg:city":"Foster City",
    "sg:classifiers":[
        {
            "category":"Professional",
            "subcategory":"Employment Agencies",
            "type":"Services"
        }
    ],
    "sg:phone":"+1 650 570 4645",
    "sg:postcode":"94403",
    "sg:province":"CA",
    "sg:tags":[
        "opportunity"
    ],
    "wof:name":"Remedy Intelligent Staffing",
    "wof:placetype":"venue"
},
  "geometry": {"coordinates":[-122.27656899999999,37.554907],"type":"Point"}
}