{
  "type": "Feature",
  "properties": {
    "iso:country":"US",
    "sg:address":"1091 Shary Cir",
    "sg:city":"Concord",
    "sg:classifiers":[
        {
            "category":"Retail",
            "subcategory":"Laundry & Dry Cleaning",
            "type":"Services"
        }
    ],
    "sg:phone":"+1 925 356 2234",
    "sg:postcode":"94518",
    "sg:province":"CA",
    "sg:tags":[
        "cleaners"
    ],
    "wof:name":"Dutch Girl Cleaners",
    "wof:placetype":"venue"
},
  "geometry": {"coordinates":[-122.030888,37.955835],"type":"Point"}
}