{
  "type": "Feature",
  "properties": {
    "iso:country":"US",
    "sg:address":"4901 El Camino Real",
    "sg:city":"Carlsbad",
    "sg:classifiers":[
        {
            "category":"Home & Garden",
            "subcategory":"Garden Supply",
            "type":"Retail Goods"
        }
    ],
    "sg:phone":"+1 760 632 9996",
    "sg:postcode":"92008",
    "sg:province":"CA",
    "sg:tags":[
        "nursery",
        "gardening"
    ],
    "sg:website":"www.oasisnursery.net",
    "wof:name":"Oasis Nursery & Landscaping Inc",
    "wof:placetype":"venue"
},
  "geometry": {"coordinates":[-117.30639499999999,33.151349],"type":"Point"}
}