{
  "type": "Feature",
  "properties": {
    "iso:country":"US",
    "sg:address":"1050 N Western Ave",
    "sg:city":"Los Angeles",
    "sg:classifiers":[
        {
            "category":"Wholesale",
            "subcategory":"Durable Goods & Equipment",
            "type":"Manufacturing & Wholesale Goods"
        }
    ],
    "sg:phone":"+1 213 680 0579",
    "sg:postcode":"90029",
    "sg:province":"CA",
    "sg:tags":[
        "importer"
    ],
    "wof:name":"Catalina's Importers Co",
    "wof:placetype":"venue"
},
  "geometry": {"coordinates":[-118.309099,34.090246],"type":"Point"}
}