{
  "type": "Feature",
  "properties": {
    "iso:country":"US",
    "sg:address":"5565 W Las Positas Blvd",
    "sg:city":"Pleasanton",
    "sg:classifiers":[
        {
            "category":"Health Services",
            "subcategory":"Medical Lab",
            "type":"Services"
        }
    ],
    "sg:phone":"+1 925 734 3345",
    "sg:postcode":"94588",
    "sg:province":"CA",
    "sg:tags":[
        "laboratory"
    ],
    "wof:name":"Valley Care Laboratory",
    "wof:placetype":"venue"
},
  "geometry": {"coordinates":[-121.888668,37.687226],"type":"Point"}
}