{
  "type": "Feature",
  "properties": {
    "iso:country":"US",
    "sg:address":"3605 Heindon Rd",
    "sg:city":"Arcata",
    "sg:classifiers":[
        {
            "category":"Insurance",
            "subcategory":"Hazard Insurance",
            "type":"Services"
        }
    ],
    "sg:phone":"+1 707 822 1458",
    "sg:postcode":"95521",
    "sg:province":"CA",
    "sg:tags":[
        "commercial",
        "business"
    ],
    "wof:name":"Virtues",
    "wof:placetype":"venue"
},
  "geometry": {"coordinates":[-124.091347,40.903726],"type":"Point"}
}