{
  "type": "Feature",
  "properties": {
    "addr:full":"875 E H St Chula Vista CA 91910",
    "addr:housenumber":"875",
    "addr:postcode":"91910",
    "addr:street":"E H St",
    "iso:country":"US",
    "sg:address":"875 E H St",
    "sg:city":"Chula Vista",
    "sg:classifiers":[
        {
            "category":"Retail",
            "subcategory":"Portrait Studio",
            "type":"Services"
        }
    ],
    "sg:phone":"+1 619 421 8097",
    "sg:postcode":"91910",
    "sg:province":"CA",
    "sg:tags":[
        "photographer"
    ],
    "wof:name":"Olan Mills Studio",
    "wof:placetype":"venue"
},
  "geometry": {"coordinates":[-117.029011,32.63605],"type":"Point"}
}