{
  "type": "Feature",
  "properties": {
    "addr:full":"2850 Main St Ste 5 Susanville CA 96130",
    "addr:housenumber":"2850",
    "addr:postcode":"96130",
    "addr:street":"Main St Ste 5",
    "iso:country":"US",
    "sg:address":"2850 Main St Ste 5",
    "sg:city":"Susanville",
    "sg:classifiers":[
        {
            "category":"Personal",
            "subcategory":"Beauty Salon",
            "type":"Services"
        }
    ],
    "sg:phone":"+1 530 251 1888",
    "sg:postcode":"96130",
    "sg:province":"CA",
    "sg:tags":[
        "hair",
        "stylist"
    ],
    "wof:name":"The Top Hair Salon",
    "wof:placetype":"venue"
},
  "geometry": {"coordinates":[-120.63776900000001,40.411683],"type":"Point"}
}