{
  "type": "Feature",
  "properties": {
    "addr:full":"81 Gregory Ln Pleasant Hill CA 94523",
    "addr:housenumber":"81",
    "addr:postcode":"94523",
    "addr:street":"Gregory Ln",
    "iso:country":"US",
    "sg:address":"81 Gregory Ln",
    "sg:city":"Pleasant Hill",
    "sg:classifiers":[
        {
            "category":"Real Estate",
            "subcategory":"Real Estate Agent",
            "type":"Services"
        }
    ],
    "sg:phone":"+1 925 685 1585",
    "sg:postcode":"94523",
    "sg:province":"CA",
    "wof:name":"RMB Realty",
    "wof:placetype":"venue"
},
  "geometry": {"coordinates":[-122.06191099999999,37.948016],"type":"Point"}
}