{
  "type": "Feature",
  "properties": {
    "iso:country":"US",
    "sg:address":"81 Gregory Ln",
    "sg:city":"Pleasant Hill",
    "sg:classifiers":[
        {
            "category":"Real Estate",
            "subcategory":"Real Estate Agent",
            "type":"Services"
        }
    ],
    "sg:phone":"+1 925 685 1585",
    "sg:postcode":"94523",
    "sg:province":"CA",
    "wof:name":"RMB Realty",
    "wof:placetype":"venue"
},
  "geometry": {"coordinates":[-122.061911,37.948016],"type":"Point"}
}