{
  "type": "Feature",
  "properties": {
    "addr:full":"12268 Sunset Ave Grass Valley CA 95945",
    "addr:housenumber":"12268",
    "addr:postcode":"95945",
    "addr:street":"Sunset Ave",
    "iso:country":"US",
    "sg:address":"12268 Sunset Ave",
    "sg:city":"Grass Valley",
    "sg:classifiers":[
        {
            "category":"Banks & Credit Unions",
            "subcategory":"Financial Services",
            "type":"Services"
        }
    ],
    "sg:phone":"+1 530 272 1223",
    "sg:postcode":"95945",
    "sg:province":"CA",
    "sg:tags":[
        "investor"
    ],
    "wof:name":"Creative Stock Investors",
    "wof:placetype":"venue"
},
  "geometry": {"coordinates":[-121.100888,39.228153],"type":"Point"}
}