{
  "type": "Feature",
  "properties": {
    "iso:country":"US",
    "sg:address":"2973 Union Ave",
    "sg:city":"San Jose",
    "sg:classifiers":[
        {
            "category":"Sports & Exercise",
            "subcategory":"Gym",
            "type":"Entertainment"
        }
    ],
    "sg:phone":"+1 408 626 7053",
    "sg:postcode":"95124",
    "sg:province":"CA",
    "sg:tags":[
        "trainer"
    ],
    "wof:name":"Curves",
    "wof:placetype":"venue"
},
  "geometry": {"coordinates":[-121.931,37.2677],"type":"Point"}
}