{
  "type": "Feature",
  "properties": {
    "iso:country":"US",
    "sg:address":"6310 San Vicente Blvd",
    "sg:city":"Los Angeles",
    "sg:classifiers":[
        {
            "category":"Utilities",
            "subcategory":"Telephone",
            "type":"Services"
        }
    ],
    "sg:phone":"+1 323 930 0102",
    "sg:postcode":"90048",
    "sg:province":"CA",
    "sg:tags":[
        "communications",
        "news"
    ],
    "wof:name":"Magmall",
    "wof:placetype":"venue"
},
  "geometry": {"coordinates":[-118.367333,34.060786],"type":"Point"}
}