{
  "type": "Feature",
  "properties": {
    "iso:country":"US",
    "sg:address":"3251 E 26th St",
    "sg:city":"Los Angeles",
    "sg:classifiers":[
        {
            "category":"Manufacturing",
            "subcategory":"Leather Goods",
            "type":"Manufacturing & Wholesale Goods"
        }
    ],
    "sg:phone":"+1 323 881 6262",
    "sg:postcode":"90023",
    "sg:province":"CA",
    "sg:website":"www.californiapak.com",
    "wof:name":"California Pak Intl Inc",
    "wof:placetype":"venue"
},
  "geometry": {"coordinates":[-118.214489,34.013172],"type":"Point"}
}