{
  "type": "Feature",
  "properties": {
    "addr:full":"1750 September Song Ct San Jose CA 95131",
    "addr:housenumber":"1750",
    "addr:postcode":"95131",
    "addr:street":"September Song Ct",
    "iso:country":"US",
    "sg:address":"1750 September Song Ct",
    "sg:city":"San Jose",
    "sg:classifiers":[
        {
            "category":"Shopping",
            "subcategory":"Clothing, Apparel, & Fashions",
            "type":"Retail Goods"
        }
    ],
    "sg:phone":"+1 408 269 7407",
    "sg:postcode":"95131",
    "sg:province":"CA",
    "wof:name":"Fashion Avenue",
    "wof:placetype":"venue"
},
  "geometry": {"coordinates":[-121.875298,37.378337],"type":"Point"}
}