{
  "type": "Feature",
  "properties": {
    "iso:country":"US",
    "sg:address":"10945 South St Ste 106 A",
    "sg:city":"Cerritos",
    "sg:classifiers":[
        {
            "category":"Professional",
            "subcategory":"Accounting & Tax Preparation",
            "type":"Services"
        }
    ],
    "sg:phone":"+1 562 467 1124",
    "sg:postcode":"90703",
    "sg:province":"CA",
    "sg:tags":[
        "accountant"
    ],
    "sg:website":"www.faganfagan.com",
    "wof:name":"Fagan & Fagan, LLP",
    "wof:placetype":"venue"
},
  "geometry": {"coordinates":[-118.100758,33.858689],"type":"Point"}
}