{
  "type": "Feature",
  "properties": {
    "addr:full":"10603 Old Redwood Hwy Windsor CA 95492",
    "addr:housenumber":"10603",
    "addr:postcode":"95492",
    "addr:street":"Old Redwood Hwy",
    "iso:country":"US",
    "sg:address":"10603 Old Redwood Hwy",
    "sg:city":"Windsor",
    "sg:classifiers":[
        {
            "category":"Wholesale",
            "subcategory":"Machinery & Supplies",
            "type":"Manufacturing & Wholesale Goods"
        }
    ],
    "sg:phone":"+1 707 431 1356",
    "sg:postcode":"95492",
    "sg:province":"CA",
    "sg:tags":[
        "vineyard",
        "product"
    ],
    "wof:name":"Vineyard Industry Products Co",
    "wof:placetype":"venue"
},
  "geometry": {"coordinates":[-122.826926,38.563416],"type":"Point"}
}