{
  "type": "Feature",
  "properties": {
    "addr:full":"251 W 84th Pl Los Angeles CA 90003",
    "addr:housenumber":"251",
    "addr:postcode":"90003",
    "addr:street":"W 84Th Pl",
    "iso:country":"US",
    "sg:address":"251 W 84th Pl",
    "sg:city":"Los Angeles",
    "sg:classifiers":[
        {
            "category":"Building & Trades",
            "subcategory":"Construction",
            "type":"Services"
        }
    ],
    "sg:phone":"+1 323 758 4866",
    "sg:postcode":"90003",
    "sg:province":"CA",
    "sg:tags":[
        "roofing",
        "contractor"
    ],
    "wof:name":"Professional Roofing Svc",
    "wof:placetype":"venue"
},
  "geometry": {"coordinates":[-118.275486,33.962436],"type":"Point"}
}