{
  "type": "Feature",
  "properties": {
    "addr:full":"2017 del Paso Blvd Sacramento CA 95815",
    "addr:housenumber":"2017",
    "addr:postcode":"95815",
    "addr:street":"Del Paso Blvd",
    "iso:country":"US",
    "sg:address":"2017 del Paso Blvd",
    "sg:city":"Sacramento",
    "sg:classifiers":[
        {
            "category":"Professional",
            "subcategory":"Lawyer & Legal Services",
            "type":"Services"
        }
    ],
    "sg:phone":"+1 916 564 1481",
    "sg:postcode":"95815",
    "sg:province":"CA",
    "sg:tags":[
        "naturalization",
        "immigration"
    ],
    "wof:name":"E P Svc",
    "wof:placetype":"venue"
},
  "geometry": {"coordinates":[-121.451786,38.609722],"type":"Point"}
}