{
  "type": "Feature",
  "properties": {
    "iso:country":"US",
    "sg:address":"2080 N Tustin Ave",
    "sg:city":"Santa Ana",
    "sg:classifiers":[
        {
            "category":"Professional",
            "subcategory":"Engineering",
            "type":"Services"
        }
    ],
    "sg:phone":"+1 714 836 9535",
    "sg:postcode":"92705",
    "sg:province":"CA",
    "sg:tags":[
        "engineer"
    ],
    "wof:name":"Cochran & Assoc Inc",
    "wof:placetype":"venue"
},
  "geometry": {"coordinates":[-117.83584,33.764521],"type":"Point"}
}