{
  "type": "Feature",
  "properties": {
    "addr:full":"7403 Princess View Drive San Diego CA 92120",
    "addr:housenumber":"7403",
    "addr:postcode":"92120",
    "addr:street":"Princess View Drive",
    "iso:country":"US",
    "sg:address":"7403 Princess View Drive",
    "sg:city":"San Diego",
    "sg:classifiers":[
        {
            "category":"Personal",
            "subcategory":"Beauty Salon",
            "type":"Services"
        }
    ],
    "sg:phone":"+1 619 265 4541",
    "sg:postcode":"92120",
    "sg:province":"CA",
    "sg:tags":[
        "spa"
    ],
    "wof:name":"Timeless Salon & Day Spa",
    "wof:placetype":"venue"
},
  "geometry": {"coordinates":[-117.078986,32.80506],"type":"Point"}
}