{
  "type": "Feature",
  "properties": {
    "iso:country":"US",
    "sg:address":"800 W Whittier Blvd",
    "sg:city":"La Habra",
    "sg:classifiers":[
        {
            "category":"Restaurant",
            "type":"Food & Drink"
        }
    ],
    "sg:phone":"+1 562 694 3812",
    "sg:postcode":"90631",
    "sg:province":"CA",
    "sg:tags":[
        "drinking",
        "eating"
    ],
    "sg:website":"www.elcholo.com",
    "wof:name":"Cat & The Custard Cup Ltd",
    "wof:placetype":"venue"
},
  "geometry": {"coordinates":[-117.957024,33.93911],"type":"Point"}
}