{
  "type": "Feature",
  "properties": {
    "iso:country":"US",
    "sg:address":"51 Commonwealth Ave",
    "sg:city":"San Francisco",
    "sg:classifiers":[
        {
            "category":"Organizations",
            "subcategory":"Professional Association",
            "type":"Services"
        }
    ],
    "sg:phone":"+1 415 668 7542",
    "sg:postcode":"94118",
    "sg:province":"CA",
    "wof:name":"ARF Kristapor Committee",
    "wof:placetype":"venue"
},
  "geometry": {"coordinates":[-122.455848,37.785059],"type":"Point"}
}