{
  "type": "Feature",
  "properties": {
    "addr:full":"5019 Taylor Way El Dorado Hills CA 95762",
    "addr:housenumber":"5019",
    "addr:postcode":"95762",
    "addr:street":"Taylor Way",
    "iso:country":"US",
    "sg:address":"5019 Taylor Way",
    "sg:city":"El Dorado Hills",
    "sg:classifiers":[
        {
            "category":"Banks & Credit Unions",
            "subcategory":"Bank",
            "type":"Services"
        }
    ],
    "sg:phone":"+1 916 941 9471",
    "sg:postcode":"95762",
    "sg:province":"CA",
    "sg:tags":[
        "broker",
        "mortgage"
    ],
    "wof:name":"Secured Investments of America",
    "wof:placetype":"venue"
},
  "geometry": {"coordinates":[-121.067751,38.67022],"type":"Point"}
}