{
  "type": "Feature",
  "properties": {
    "addr:full":"9723 Aviation Blvd Los Angeles CA 90045",
    "addr:housenumber":"9723",
    "addr:postcode":"90045",
    "addr:street":"Aviation Blvd",
    "iso:country":"US",
    "sg:address":"9723 Aviation Blvd",
    "sg:city":"Los Angeles",
    "sg:classifiers":[
        {
            "category":"Retail",
            "subcategory":"Auto Repair",
            "type":"Services"
        }
    ],
    "sg:phone":"+1 310 337 2804",
    "sg:postcode":"90045",
    "sg:province":"CA",
    "sg:tags":[
        "wrecker"
    ],
    "wof:name":"A Fast Towing",
    "wof:placetype":"venue"
},
  "geometry": {"coordinates":[-118.378063,33.949355],"type":"Point"}
}