{
  "type": "Feature",
  "properties": {
    "addr:full":"1986 Mountain Blvd. Oakland CA 94611",
    "addr:housenumber":"1986",
    "addr:postcode":"94611",
    "addr:street":"Mountain Blvd.",
    "iso:country":"US",
    "sg:address":"1986 Mountain Blvd.",
    "sg:city":"Oakland",
    "sg:classifiers":[
        {
            "category":"Real Estate",
            "subcategory":"Real Estate Agent",
            "type":"Services"
        }
    ],
    "sg:phone":"+1 415 722 8949",
    "sg:postcode":"94611",
    "sg:province":"CA",
    "sg:website":"www.MichelleWilliamsRealtor.com",
    "wof:name":"Michelle Williams, East Bay Sotheby's International Realty",
    "wof:placetype":"venue"
},
  "geometry": {"coordinates":[-122.21024,37.8276],"type":"Point"}
}