{
  "type": "Feature",
  "properties": {
    "iso:country":"US",
    "sg:address":"2338 W 6th St",
    "sg:city":"Santa Ana",
    "sg:classifiers":[
        {
            "category":"Building & Trades",
            "subcategory":"Construction",
            "type":"Services"
        }
    ],
    "sg:phone":"+1 714 547 8050",
    "sg:postcode":"92703",
    "sg:province":"CA",
    "sg:tags":[
        "contractor"
    ],
    "wof:name":"Pinehill Construction",
    "wof:placetype":"venue"
},
  "geometry": {"coordinates":[-117.900002,33.749699],"type":"Point"}
}