{
  "type": "Feature",
  "properties": {
    "iso:country":"US",
    "sg:address":"807 N Garfield Ave Apt A",
    "sg:city":"Alhambra",
    "sg:classifiers":[
        {
            "category":"Wholesale",
            "subcategory":"Computers",
            "type":"Manufacturing & Wholesale Goods"
        }
    ],
    "sg:phone":"+1 626 961 3699",
    "sg:postcode":"91801",
    "sg:province":"CA",
    "wof:name":"KTC Engineering Associates",
    "wof:placetype":"venue"
},
  "geometry": {"coordinates":[-118.13194799999999,34.102122],"type":"Point"}
}