{
  "type": "Feature",
  "properties": {
    "addr:full":"1130 E Shaw Ave Fresno CA 93710",
    "addr:housenumber":"1130",
    "addr:postcode":"93710",
    "addr:street":"E Shaw Ave",
    "iso:country":"US",
    "sg:address":"1130 E Shaw Ave",
    "sg:city":"Fresno",
    "sg:classifiers":[
        {
            "category":"Building & Trades",
            "subcategory":"Construction",
            "type":"Services"
        }
    ],
    "sg:phone":"+1 559 222 9323",
    "sg:postcode":"93710",
    "sg:province":"CA",
    "sg:tags":[
        "pond",
        "supply"
    ],
    "wof:name":"Aqua Docs",
    "wof:placetype":"venue"
},
  "geometry": {"coordinates":[-119.77104799999999,36.808638],"type":"Point"}
}