{
  "type": "Feature",
  "properties": {
    "addr:full":"1111 S Main St Yreka CA 96097",
    "addr:housenumber":"1111",
    "addr:postcode":"96097",
    "addr:street":"S Main St",
    "iso:country":"US",
    "sg:address":"1111 S Main St",
    "sg:city":"Yreka",
    "sg:classifiers":[
        {
            "category":"Travel",
            "subcategory":"Hotels & Motels",
            "type":"Entertainment"
        }
    ],
    "sg:phone":"+1 530 842 2751",
    "sg:postcode":"96097",
    "sg:province":"CA",
    "wof:name":"Klamath Motor Lodge",
    "wof:placetype":"venue"
},
  "geometry": {"coordinates":[-122.639216,41.721928],"type":"Point"}
}