{
  "type": "Feature",
  "properties": {
    "addr:full":"102 N Sunrise Way Palm Springs CA 92262",
    "addr:housenumber":"102",
    "addr:postcode":"92262",
    "addr:street":"N Sunrise Way",
    "iso:country":"US",
    "sg:address":"102 N Sunrise Way",
    "sg:city":"Palm Springs",
    "sg:classifiers":[
        {
            "category":"Restaurant",
            "type":"Food & Drink"
        }
    ],
    "sg:phone":"+1 760 323 9291",
    "sg:postcode":"92262",
    "sg:province":"CA",
    "sg:website":"www.clj.com",
    "wof:name":"Carl's Jr",
    "wof:placetype":"venue"
},
  "geometry": {"coordinates":[-116.52815,33.823187],"type":"Point"}
}