{
  "type": "Feature",
  "properties": {
    "addr:full":"1613 N Pepper St Burbank CA 91505",
    "addr:housenumber":"1613",
    "addr:postcode":"91505",
    "addr:street":"N Pepper St",
    "iso:country":"US",
    "sg:address":"1613 N Pepper St",
    "sg:city":"Burbank",
    "sg:classifiers":[
        {
            "category":"Professional",
            "subcategory":"Management & Consulting",
            "type":"Services"
        }
    ],
    "sg:phone":"+1 818 556 6646",
    "sg:postcode":"91505",
    "sg:province":"CA",
    "sg:tags":[
        "business"
    ],
    "wof:name":"Anwar Zraikat Consulting",
    "wof:placetype":"venue"
},
  "geometry": {"coordinates":[-118.35040600000001,34.180894],"type":"Point"}
}