{
  "type": "Feature",
  "properties": {
    "iso:country":"US",
    "sg:address":"2398 E Foothill Blvd",
    "sg:city":"Pasadena",
    "sg:classifiers":[
        {
            "category":"Manufacturing",
            "subcategory":"Apparel",
            "type":"Manufacturing & Wholesale Goods"
        }
    ],
    "sg:phone":"+1 626 792 2842",
    "sg:postcode":"91107",
    "sg:province":"CA",
    "sg:tags":[
        "outerwear",
        "mfg"
    ],
    "wof:name":"Rosemeiers Sportswear",
    "wof:placetype":"venue"
},
  "geometry": {"coordinates":[-118.101359,34.149658],"type":"Point"}
}