{
  "type": "Feature",
  "properties": {
    "iso:country":"US",
    "sg:address":"2920 Arden Way",
    "sg:city":"Sacramento",
    "sg:classifiers":[
        {
            "category":"Shopping",
            "subcategory":"Shoes",
            "type":"Retail Goods"
        }
    ],
    "sg:phone":"+1 916 485 2000",
    "sg:postcode":"95825",
    "sg:province":"CA",
    "sg:tags":[
        "store"
    ],
    "wof:name":"Uniform Advantage",
    "wof:placetype":"venue"
},
  "geometry": {"coordinates":[-121.396135,38.595893],"type":"Point"}
}