{
  "type": "Feature",
  "properties": {
    "iso:country":"US",
    "sg:address":"611 S Catalina St",
    "sg:city":"Los Angeles",
    "sg:classifiers":[
        {
            "category":"Building & Trades",
            "subcategory":"Electrical",
            "type":"Services"
        }
    ],
    "sg:phone":"+1 213 480 9700",
    "sg:postcode":"90005",
    "sg:province":"CA",
    "sg:tags":[
        "electric",
        "contractor"
    ],
    "wof:name":"Hi Tek Electric Co",
    "wof:placetype":"venue"
},
  "geometry": {"coordinates":[-118.29543700000001,34.062745],"type":"Point"}
}