{
  "type": "Feature",
  "properties": {
    "iso:country":"US",
    "sg:address":"38463 Fremont Blvd",
    "sg:city":"Fremont",
    "sg:classifiers":[
        {
            "category":"Recreation",
            "type":"Entertainment"
        }
    ],
    "sg:phone":"+1 510 739 1560",
    "sg:postcode":"94536",
    "sg:province":"CA",
    "sg:tags":[
        "psychic",
        "medium"
    ],
    "wof:name":"Advisors",
    "wof:placetype":"venue"
},
  "geometry": {"coordinates":[-121.997766,37.553299],"type":"Point"}
}