{
  "type": "Feature",
  "properties": {
    "iso:country":"US",
    "sg:address":"822 Main St",
    "sg:city":"Redwood City",
    "sg:classifiers":[
        {
            "category":"Personal",
            "subcategory":"Beauty Salon",
            "type":"Services"
        }
    ],
    "sg:phone":"+1 650 299 1817",
    "sg:postcode":"94063",
    "sg:province":"CA",
    "wof:name":"Ava Body Care & Beauty Salon",
    "wof:placetype":"venue"
},
  "geometry": {"coordinates":[-122.226327,37.485951],"type":"Point"}
}