{
  "type": "Feature",
  "properties": {
    "iso:country":"US",
    "sg:address":"74947 Hwy 111",
    "sg:city":"Indian Wells",
    "sg:classifiers":[
        {
            "category":"Real Estate",
            "subcategory":"Developer",
            "type":"Services"
        }
    ],
    "sg:phone":"+1 760 773 5855",
    "sg:postcode":"92210",
    "sg:province":"CA",
    "wof:name":"Carver Co",
    "wof:placetype":"venue"
},
  "geometry": {"coordinates":[-116.357504,33.721319],"type":"Point"}
}