{
  "type": "Feature",
  "properties": {
    "iso:country":"US",
    "sg:address":"1214 Stevens Ct",
    "sg:city":"Merced",
    "sg:classifiers":[
        {
            "category":"Building & Trades",
            "subcategory":"Construction",
            "type":"Services"
        }
    ],
    "sg:phone":"+1 209 385 1441",
    "sg:postcode":"95340",
    "sg:province":"CA",
    "sg:tags":[
        "handyman"
    ],
    "wof:name":"Nick's Handyman Svc",
    "wof:placetype":"venue"
},
  "geometry": {"coordinates":[-120.457416,37.319984],"type":"Point"}
}