{
  "type": "Feature",
  "properties": {
    "iso:country":"US",
    "sg:address":"535 Lincoln Ave",
    "sg:city":"Redwood City",
    "sg:classifiers":[
        {
            "category":"Building & Trades",
            "subcategory":"Landscaping Services",
            "type":"Services"
        }
    ],
    "sg:phone":"+1 650 368 6984",
    "sg:postcode":"94061",
    "sg:province":"CA",
    "wof:name":"Juan Rosales Gardening",
    "wof:placetype":"venue"
},
  "geometry": {"coordinates":[-122.23095000000001,37.47629],"type":"Point"}
}