{
  "type": "Feature",
  "properties": {
    "iso:country":"US",
    "sg:address":"2024 N Broadway",
    "sg:city":"Santa Ana",
    "sg:classifiers":[
        {
            "category":"Professional",
            "subcategory":"Lawyer & Legal Services",
            "type":"Services"
        }
    ],
    "sg:phone":"+1 714 547 2745",
    "sg:postcode":"92706",
    "sg:province":"CA",
    "wof:name":"Ungerman Wm S Atty",
    "wof:placetype":"venue"
},
  "geometry": {"coordinates":[-117.870003,33.762798],"type":"Point"}
}