{
  "type": "Feature",
  "properties": {
    "iso:country":"US",
    "sg:address":"6950 Almaden Expy Ste 107",
    "sg:city":"San Jose",
    "sg:classifiers":[
        {
            "category":"Shopping",
            "subcategory":"Pets & Pet Supplies",
            "type":"Retail Goods"
        }
    ],
    "sg:phone":"+1 800 874 5908",
    "sg:postcode":"95120",
    "sg:province":"CA",
    "sg:tags":[
        "groomers"
    ],
    "sg:website":"www.aroundtownpetspa.com",
    "wof:name":"Around Town Pet Spa",
    "wof:placetype":"venue"
},
  "geometry": {"coordinates":[-121.845304,37.210268],"type":"Point"}
}