{
  "type": "Feature",
  "properties": {
    "iso:country":"US",
    "sg:address":"480 G St",
    "sg:city":"Arcata",
    "sg:classifiers":[
        {
            "category":"Autos & Motor Vehicles",
            "subcategory":"Auto Supplies",
            "type":"Retail Goods"
        },
        {
            "category":"Wholesale",
            "subcategory":"Auto Parts",
            "type":"Manufacturing & Wholesale Goods"
        }
    ],
    "sg:phone":"+1 707 822 3674",
    "sg:postcode":"95521",
    "sg:province":"CA",
    "sg:tags":[
        "automobile"
    ],
    "wof:name":"Ken's Auto Parts",
    "wof:placetype":"venue"
},
  "geometry": {"coordinates":[-124.08721199999999,40.864937],"type":"Point"}
}