{
  "type": "Feature",
  "properties": {
    "iso:country":"US",
    "sg:address":"48910 Airline Hwy",
    "sg:city":"King City",
    "sg:classifiers":[
        {
            "category":"Government",
            "subcategory":"Office",
            "type":"Public Place"
        }
    ],
    "sg:phone":"+1 831 385 5348",
    "sg:postcode":"93930",
    "sg:province":"CA",
    "sg:tags":[
        "management"
    ],
    "wof:name":"Hepsededam Mutual Water Co",
    "wof:placetype":"venue"
},
  "geometry": {"coordinates":[-120.936623,36.265899],"type":"Point"}
}