{
  "type": "Feature",
  "properties": {
    "addr:full":"930 N San Dimas Ave San Dimas CA 91773",
    "addr:housenumber":"930",
    "addr:postcode":"91773",
    "addr:street":"N San Dimas Ave",
    "iso:country":"US",
    "sg:address":"930 N San Dimas Ave",
    "sg:city":"San Dimas",
    "sg:classifiers":[
        {
            "category":"Real Estate",
            "subcategory":"Real Estate Operator",
            "type":"Services"
        }
    ],
    "sg:phone":"+1 909 592 3150",
    "sg:postcode":"91773",
    "sg:province":"CA",
    "sg:tags":[
        "apartment"
    ],
    "wof:name":"Villas At San Dimas Ave",
    "wof:placetype":"venue"
},
  "geometry": {"coordinates":[-117.80705,34.119645],"type":"Point"}
}