{
  "type": "Feature",
  "properties": {
    "iso:country":"US",
    "sg:address":"17321 Valley View Ave",
    "sg:city":"Cerritos",
    "sg:classifiers":[
        {
            "category":"Home & Garden",
            "subcategory":"Furniture",
            "type":"Retail Goods"
        }
    ],
    "sg:phone":"+1 562 356 2424",
    "sg:postcode":"90703",
    "sg:province":"CA",
    "sg:tags":[
        "store"
    ],
    "wof:name":"Pacific Sales Home Furnishing",
    "wof:placetype":"venue"
},
  "geometry": {"coordinates":[-118.028999,33.877102],"type":"Point"}
}