{
  "type": "Feature",
  "properties": {
    "iso:country":"US",
    "sg:address":"1034 W Arrow Hwy",
    "sg:city":"San Dimas",
    "sg:classifiers":[
        {
            "category":"Restaurant",
            "type":"Food & Drink"
        }
    ],
    "sg:menulink":"http://www.allmenus.com/ca/east-san-gabriel-valley/123231-quiznos-sub/menu/",
    "sg:phone":"+1 909 971 9719",
    "sg:postcode":"91773",
    "sg:province":"CA",
    "sg:tags":[
        "wrap",
        "american",
        "sandwich"
    ],
    "wof:name":"Quiznos Sub",
    "wof:placetype":"venue"
},
  "geometry": {"coordinates":[-117.827387,34.106138],"type":"Point"}
}