{
  "type": "Feature",
  "properties": {
    "iso:country":"US",
    "sg:address":"74140 el Paseo",
    "sg:city":"Palm Desert",
    "sg:classifiers":[
        {
            "category":"Shopping",
            "subcategory":"Computers & Home Electronics",
            "type":"Retail Goods"
        }
    ],
    "sg:phone":"+1 760 342 1221",
    "sg:postcode":"92260",
    "sg:province":"CA",
    "sg:tags":[
        "equipment",
        "dealer"
    ],
    "wof:name":"Walker's Computers",
    "wof:placetype":"venue"
},
  "geometry": {"coordinates":[-116.37130500000001,33.72042],"type":"Point"}
}