{
  "type": "Feature",
  "properties": {
    "addr:full":"3689 Midway Dr San Diego CA 92110",
    "addr:housenumber":"3689",
    "addr:postcode":"92110",
    "addr:street":"Midway Dr",
    "iso:country":"US",
    "sg:address":"3689 Midway Dr",
    "sg:city":"San Diego",
    "sg:classifiers":[
        {
            "category":"Health Services",
            "subcategory":"Chiropractor",
            "type":"Services"
        }
    ],
    "sg:phone":"+1 619 222 8885",
    "sg:postcode":"92110",
    "sg:province":"CA",
    "wof:name":"Greater Life Family Chiro",
    "wof:placetype":"venue"
},
  "geometry": {"coordinates":[-117.216959,32.753115],"type":"Point"}
}