{
  "type": "Feature",
  "properties": {
    "addr:full":"2375 Oakleaf Canyon Rd Walnut CA 91789",
    "addr:housenumber":"2375",
    "addr:postcode":"91789",
    "addr:street":"Oakleaf Canyon Rd",
    "iso:country":"US",
    "sg:address":"2375 Oakleaf Canyon Rd",
    "sg:city":"Walnut",
    "sg:classifiers":[
        {
            "category":"Building & Trades",
            "subcategory":"Landscaping Services",
            "type":"Services"
        }
    ],
    "sg:phone":"+1 909 595 1959",
    "sg:postcode":"91789",
    "sg:province":"CA",
    "wof:name":"Maria Sandoval",
    "wof:placetype":"venue"
},
  "geometry": {"coordinates":[-117.86318900000001,33.977964],"type":"Point"}
}