{
  "type": "Feature",
  "properties": {
    "iso:country":"US",
    "sg:address":"2375 Oakleaf Canyon Rd",
    "sg:city":"Walnut",
    "sg:classifiers":[
        {
            "category":"Building & Trades",
            "subcategory":"Landscaping Services",
            "type":"Services"
        }
    ],
    "sg:phone":"+1 909 595 1959",
    "sg:postcode":"91789",
    "sg:province":"CA",
    "wof:name":"Maria Sandoval",
    "wof:placetype":"venue"
},
  "geometry": {"coordinates":[-117.863189,33.977964],"type":"Point"}
}