{
  "type": "Feature",
  "properties": {
    "addr:full":"1500 Crestfield Dr Duarte CA 91010",
    "addr:housenumber":"1500",
    "addr:postcode":"91010",
    "addr:street":"Crestfield Dr",
    "iso:country":"US",
    "sg:address":"1500 Crestfield Dr",
    "sg:city":"Duarte",
    "sg:classifiers":[
        {
            "category":"Freight",
            "type":"Transportation"
        }
    ],
    "sg:phone":"+1 626 357 4330",
    "sg:postcode":"91010",
    "sg:province":"CA",
    "sg:tags":[
        "commercial",
        "storage"
    ],
    "wof:name":"Mt Olive Self Storage",
    "wof:placetype":"venue"
},
  "geometry": {"coordinates":[-117.951588,34.137032],"type":"Point"}
}