{
  "type": "Feature",
  "properties": {
    "addr:full":"421 Bernard St Los Angeles CA 90012",
    "addr:housenumber":"421",
    "addr:postcode":"90012",
    "addr:street":"Bernard St",
    "iso:country":"US",
    "sg:address":"421 Bernard St",
    "sg:city":"Los Angeles",
    "sg:classifiers":[
        {
            "category":"Organizations",
            "subcategory":"Professional Association",
            "type":"Services"
        }
    ],
    "sg:phone":"+1 323 222 8011",
    "sg:postcode":"90012",
    "sg:province":"CA",
    "wof:name":"Gee Hok Oak Tien Assn",
    "wof:placetype":"venue"
},
  "geometry": {"coordinates":[-118.236964,34.067219],"type":"Point"}
}