{
  "type": "Feature",
  "properties": {
    "iso:country":"US",
    "sg:address":"3417 Crenshaw Blvd",
    "sg:city":"Los Angeles",
    "sg:classifiers":[
        {
            "category":"Shopping",
            "subcategory":"Clothing, Apparel, & Fashions",
            "type":"Retail Goods"
        }
    ],
    "sg:phone":"+1 323 734 3212",
    "sg:postcode":"90016",
    "sg:province":"CA",
    "sg:tags":[
        "family"
    ],
    "wof:name":"Patton To Score",
    "wof:placetype":"venue"
},
  "geometry": {"coordinates":[-118.335174,34.02416],"type":"Point"}
}