{
  "type": "Feature",
  "properties": {
    "addr:full":"6873 N Lake Blvd Tahoe Vista CA 96148",
    "addr:housenumber":"6873",
    "addr:postcode":"96148",
    "addr:street":"N Lake Blvd",
    "iso:country":"US",
    "sg:address":"6873 N Lake Blvd",
    "sg:city":"Tahoe Vista",
    "sg:classifiers":[
        {
            "category":"Health Services",
            "subcategory":"Health Practitioner",
            "type":"Services"
        }
    ],
    "sg:phone":"+1 530 546 6052",
    "sg:postcode":"96148",
    "sg:province":"CA",
    "sg:tags":[
        "medicine",
        "alternative"
    ],
    "wof:name":"Homeopathy",
    "wof:placetype":"venue"
},
  "geometry": {"coordinates":[-120.055013,39.240565],"type":"Point"}
}