{
  "type": "Feature",
  "properties": {
    "iso:country":"US",
    "sg:address":"835 3rd St",
    "sg:city":"Eureka",
    "sg:classifiers":[
        {
            "category":"Professional",
            "subcategory":"Computer Services",
            "type":"Services"
        }
    ],
    "sg:phone":"+1 707 441 0404",
    "sg:postcode":"95501",
    "sg:province":"CA",
    "sg:tags":[
        "prepackaged",
        "develops",
        "software"
    ],
    "wof:name":"S-Matrix Corporation",
    "wof:placetype":"venue"
},
  "geometry": {"coordinates":[-124.162693,40.804152],"type":"Point"}
}