{
  "type": "Feature",
  "properties": {
    "addr:full":"5079 Lone Tree Way Antioch CA 94531",
    "addr:housenumber":"5079",
    "addr:postcode":"ca 94531",
    "addr:street":"Lone Tree Way",
    "iso:country":"US",
    "sg:address":"5079 Lone Tree Way",
    "sg:city":"Antioch",
    "sg:classifiers":[
        {
            "category":"Social Services",
            "type":"Services"
        },
        {
            "category":"Health Services",
            "subcategory":"Nursing And Care Facility",
            "type":"Services"
        },
        {
            "category":"Health Services",
            "subcategory":"Health Practitioner",
            "type":"Services"
        },
        {
            "category":"Social Services",
            "subcategory":"Adult Care",
            "type":"Services"
        }
    ],
    "sg:phone":"+1 925 779 9000",
    "sg:postcode":"94531",
    "sg:province":"CA",
    "sg:tags":[
        "counseling",
        "nurses-home",
        "consulting",
        "geriatric",
        "alzheimer's",
        "assisted",
        "disability",
        "elder",
        "citizen",
        "home",
        "living",
        "nurse",
        "eldercare-home",
        "senior"
    ],
    "sg:website":"http://www.brightstarcare.com/find-a-location/ca/antioch-brentwood-stockton/",
    "wof:name":"BrightStar - Antioch",
    "wof:placetype":"venue"
},
  "geometry": {"coordinates":[-121.760204,37.961762],"type":"Point"}
}