{
  "type": "Feature",
  "properties": {
    "addr:full":"10061 Riverside Dr Toluca Lake CA 91602",
    "addr:housenumber":"10061",
    "addr:postcode":"91602",
    "addr:street":"Riverside Dr",
    "iso:country":"US",
    "sg:address":"10061 Riverside Dr",
    "sg:city":"Toluca Lake",
    "sg:classifiers":[
        {
            "category":"Professional",
            "subcategory":"Management & Consulting",
            "type":"Services"
        }
    ],
    "sg:phone":"+1 818 623 0557",
    "sg:postcode":"91602",
    "sg:province":"CA",
    "sg:tags":[
        "consultant",
        "business"
    ],
    "wof:name":"Inovative Development",
    "wof:placetype":"venue"
},
  "geometry": {"coordinates":[-118.350326,34.152283],"type":"Point"}
}