{
  "type": "Feature",
  "properties": {
    "addr:full":"2340 Montpelier Drive San Jose CA 95116",
    "addr:housenumber":"2340",
    "addr:postcode":"95116",
    "addr:street":"Montpelier Drive",
    "iso:country":"US",
    "sg:address":"2340 Montpelier Drive",
    "sg:city":"San Jose",
    "sg:classifiers":[
        {
            "category":"Health Services",
            "subcategory":"Doctor",
            "type":"Services"
        }
    ],
    "sg:phone":"+1 408 347 9001",
    "sg:postcode":"95116",
    "sg:province":"CA",
    "sg:website":"www.sjgi.com",
    "wof:name":"Nguyen Khanh Kim MD",
    "wof:placetype":"venue"
},
  "geometry": {"coordinates":[-121.84760799999999,37.364834],"type":"Point"}
}