{
  "type": "Feature",
  "properties": {
    "addr:full":"320 Turtle Creek Ct San Jose CA 95125",
    "addr:housenumber":"320",
    "addr:postcode":"95125",
    "addr:street":"Turtle Creek Ct",
    "iso:country":"US",
    "sg:address":"320 Turtle Creek Ct",
    "sg:city":"San Jose",
    "sg:classifiers":[
        {
            "category":"Home & Garden",
            "subcategory":"Building Materials",
            "type":"Retail Goods"
        }
    ],
    "sg:phone":"+1 408 998 1744",
    "sg:postcode":"95125",
    "sg:province":"CA",
    "sg:tags":[
        "glass",
        "window",
        "plate"
    ],
    "wof:name":"Cline & Assoc",
    "wof:placetype":"venue"
},
  "geometry": {"coordinates":[-121.87400700000001,37.302879],"type":"Point"}
}