{
  "type": "Feature",
  "properties": {
    "addr:full":"3445 Cahuenga Boulevard W Los Angeles CA 90068",
    "addr:housenumber":"3445",
    "addr:postcode":"90068",
    "addr:street":"Cahuenga Boulevard W",
    "iso:country":"US",
    "sg:address":"3445 Cahuenga Boulevard W",
    "sg:city":"Los Angeles",
    "sg:classifiers":[
        {
            "category":"Shopping",
            "subcategory":"Music",
            "type":"Retail Goods"
        }
    ],
    "sg:phone":"+1 818 848 4180",
    "sg:postcode":"90068",
    "sg:province":"CA",
    "sg:tags":[
        "dvd's"
    ],
    "wof:name":"Disc Makers",
    "wof:placetype":"venue"
},
  "geometry": {"coordinates":[-118.35358100000001,34.132214],"type":"Point"}
}