{
  "type": "Feature",
  "properties": {
    "iso:country":"US",
    "sg:address":"2940 Lincoln Ave",
    "sg:city":"Yountville",
    "sg:classifiers":[
        {
            "category":"Professional",
            "type":"Services"
        }
    ],
    "sg:phone":"+1 707 944 0800",
    "sg:postcode":"94599",
    "sg:province":"CA",
    "wof:name":"Steve & Kathy Luebcke",
    "wof:placetype":"venue"
},
  "geometry": {"coordinates":[-122.368004,38.408145],"type":"Point"}
}