{
  "type": "Feature",
  "properties": {
    "addr:full":"11926 Woodruff Ave Downey CA 90241",
    "addr:housenumber":"11926",
    "addr:postcode":"90241",
    "addr:street":"Woodruff Ave",
    "iso:country":"US",
    "sg:address":"11926 Woodruff Ave",
    "sg:city":"Downey",
    "sg:classifiers":[
        {
            "category":"Wholesale",
            "subcategory":"Construction Materials",
            "type":"Manufacturing & Wholesale Goods"
        },
        {
            "category":"Home & Garden",
            "subcategory":"Building Materials",
            "type":"Retail Goods"
        },
        {
            "category":"Building & Trades",
            "subcategory":"Construction",
            "type":"Services"
        }
    ],
    "sg:phone":"+1 562 630 4638",
    "sg:postcode":"90241",
    "sg:province":"CA",
    "sg:tags":[
        "fence-sales",
        "manufacturer",
        "fence-wholesale",
        "fence",
        "contractor"
    ],
    "wof:name":"Paris Fence Supply",
    "wof:placetype":"venue"
},
  "geometry": {"coordinates":[-118.11670700000001,33.9271],"type":"Point"}
}