{
  "type": "Feature",
  "properties": {
    "iso:country":"US",
    "sg:address":"500 Newport Center Dr",
    "sg:city":"Newport Beach",
    "sg:classifiers":[
        {
            "category":"Cinema",
            "subcategory":"Movie Rental",
            "type":"Entertainment"
        }
    ],
    "sg:phone":"+1 949 644 6609",
    "sg:postcode":"92660",
    "sg:province":"CA",
    "sg:tags":[
        "video",
        "tape",
        "film"
    ],
    "wof:name":"Vid Film Services Europe Inc",
    "wof:placetype":"venue"
},
  "geometry": {"coordinates":[-117.872285,33.616716],"type":"Point"}
}