{
  "type": "Feature",
  "properties": {
    "addr:full":"99 Sanchez St San Francisco CA 94114",
    "addr:housenumber":"99",
    "addr:postcode":"94114",
    "addr:street":"Sanchez St",
    "iso:country":"US",
    "sg:address":"99 Sanchez St",
    "sg:city":"San Francisco",
    "sg:classifiers":[
        {
            "category":"Home & Garden",
            "subcategory":"Furniture",
            "type":"Retail Goods"
        }
    ],
    "sg:phone":"+1 415 621 3761",
    "sg:postcode":"94114",
    "sg:province":"CA",
    "wof:name":"Books & Bookshelves",
    "wof:placetype":"venue"
},
  "geometry": {"coordinates":[-122.43135599999999,37.769321],"type":"Point"}
}