{
  "type": "Feature",
  "properties": {
    "addr:full":"363 S Indian Hill Blvd Claremont CA 91711",
    "addr:housenumber":"363",
    "addr:postcode":"91711",
    "addr:street":"S Indian Hill Blvd",
    "iso:country":"US",
    "sg:address":"363 S Indian Hill Blvd",
    "sg:city":"Claremont",
    "sg:classifiers":[
        {
            "category":"Professional",
            "subcategory":"Lawyer & Legal Services",
            "type":"Services"
        }
    ],
    "sg:phone":"+1 909 624 3661",
    "sg:postcode":"91711",
    "sg:province":"CA",
    "sg:tags":[
        "attorney"
    ],
    "wof:name":"Rowley & Rinaldelli",
    "wof:placetype":"venue"
},
  "geometry": {"coordinates":[-117.71928200000001,34.088868],"type":"Point"}
}