{
  "type": "Feature",
  "properties": {
    "addr:full":"9107 Wilshire Blvd Beverly Hills CA 90210",
    "addr:housenumber":"9107",
    "addr:postcode":"90210",
    "addr:street":"Wilshire Blvd",
    "iso:country":"US",
    "sg:address":"9107 Wilshire Blvd",
    "sg:city":"Beverly Hills",
    "sg:classifiers":[
        {
            "category":"Professional",
            "subcategory":"Employment Agencies",
            "type":"Services"
        }
    ],
    "sg:phone":"+1 310 205 3103",
    "sg:postcode":"90210",
    "sg:province":"CA",
    "sg:tags":[
        "opportunity"
    ],
    "wof:name":"Best Employment Corp",
    "wof:placetype":"venue"
},
  "geometry": {"coordinates":[-118.390207,34.067125],"type":"Point"}
}