{
  "type": "Feature",
  "properties": {
    "addr:full":"9872 Chapman Ave Ste 110 Garden Grove CA 92841",
    "addr:housenumber":"9872",
    "addr:postcode":"92841",
    "addr:street":"Chapman Ave Ste 110",
    "iso:country":"US",
    "sg:address":"9872 Chapman Ave Ste 110",
    "sg:city":"Garden Grove",
    "sg:classifiers":[
        {
            "category":"Real Estate",
            "subcategory":"Real Estate Services",
            "type":"Services"
        },
        {
            "category":"Banks & Credit Unions",
            "subcategory":"Financial Services",
            "type":"Services"
        },
        {
            "category":"Real Estate",
            "subcategory":"Real Estate Agent",
            "type":"Services"
        }
    ],
    "sg:phone":"+1 714 530 3331",
    "sg:postcode":"92841",
    "sg:province":"CA",
    "sg:tags":[
        "property",
        "management",
        "broker",
        "mortgage"
    ],
    "sg:website":"www.nationalbrokers.net",
    "wof:name":"National Brokers",
    "wof:placetype":"venue"
},
  "geometry": {"coordinates":[-117.96041700000001,33.787968],"type":"Point"}
}