{
  "type": "Feature",
  "properties": {
    "addr:full":"2060 Alameda Padre Serra Santa Barbara CA 93103",
    "addr:housenumber":"2060",
    "addr:postcode":"93103",
    "addr:street":"Alameda Padre Serra",
    "iso:country":"US",
    "sg:address":"2060 Alameda Padre Serra",
    "sg:city":"Santa Barbara",
    "sg:classifiers":[
        {
            "category":"Professional",
            "subcategory":"Business Services",
            "type":"Services"
        }
    ],
    "sg:phone":"+1 805 966 6160",
    "sg:postcode":"93103",
    "sg:province":"CA",
    "wof:name":"Prodmar",
    "wof:placetype":"venue"
},
  "geometry": {"coordinates":[-119.70758499999999,34.438324],"type":"Point"}
}