{
  "type": "Feature",
  "properties": {
    "iso:country":"US",
    "sg:address":"1257 Quarry Ln Ste 100",
    "sg:city":"Pleasanton",
    "sg:classifiers":[
        {
            "category":"Professional",
            "subcategory":"Engineering",
            "type":"Services"
        }
    ],
    "sg:phone":"+1 925 931 0370",
    "sg:postcode":"94566",
    "sg:province":"CA",
    "sg:tags":[
        "consulting",
        "engineer"
    ],
    "wof:name":"C S G Consultants",
    "wof:placetype":"venue"
},
  "geometry": {"coordinates":[-121.865623,37.674549],"type":"Point"}
}