{
  "type": "Feature",
  "properties": {
    "iso:country":"US",
    "sg:address":"1125 N Pacific Ave",
    "sg:city":"Glendale",
    "sg:classifiers":[
        {
            "category":"Education",
            "subcategory":"School",
            "type":"Public Place"
        }
    ],
    "sg:phone":"+1 818 247 0605",
    "sg:postcode":"91202",
    "sg:province":"CA",
    "wof:name":"All Nations Academy",
    "wof:placetype":"venue"
},
  "geometry": {"coordinates":[-118.264662,34.161589],"type":"Point"}
}