{
  "type": "Feature",
  "properties": {
    "addr:full":"38 Corporate Park Irvine CA 92606",
    "addr:housenumber":"38",
    "addr:postcode":"92606",
    "addr:street":"Corporate Park",
    "iso:country":"US",
    "sg:address":"38 Corporate Park",
    "sg:city":"Irvine",
    "sg:classifiers":[
        {
            "category":"Professional",
            "subcategory":"Lawyer & Legal Services",
            "type":"Services"
        }
    ],
    "sg:phone":"+1 949 467 9147",
    "sg:postcode":"92606",
    "sg:province":"CA",
    "sg:tags":[
        "divorce",
        "law",
        "family"
    ],
    "sg:website":"www.ocfamlawyer.com",
    "wof:name":"Michael Efron-Kring&Chung LLP",
    "wof:placetype":"venue"
},
  "geometry": {"coordinates":[-117.827406,33.688785],"type":"Point"}
}