{
  "type": "Feature",
  "properties": {
    "addr:full":"916 13th St Modesto CA 95354",
    "addr:housenumber":"916",
    "addr:postcode":"ca 95354",
    "addr:street":"13Th St",
    "iso:country":"US",
    "sg:address":"916 13th St",
    "sg:city":"Modesto",
    "sg:classifiers":[
        {
            "category":"Restaurant",
            "type":"Food & Drink"
        }
    ],
    "sg:phone":"+1 209 529 3500",
    "sg:postcode":"95354",
    "sg:province":"CA",
    "wof:name":"Oceana Bar and Grill",
    "wof:placetype":"venue"
},
  "geometry": {"coordinates":[-120.99700199999999,37.642502],"type":"Point"}
}