{
  "type": "Feature",
  "properties": {
    "iso:country":"US",
    "sg:address":"4374 Camphor Ave",
    "sg:city":"Yorba Linda",
    "sg:classifiers":[
        {
            "category":"Professional",
            "type":"Services"
        }
    ],
    "sg:phone":"+1 714 779 1754",
    "sg:postcode":"92886",
    "sg:province":"CA",
    "wof:name":"Drayton Designs",
    "wof:placetype":"venue"
},
  "geometry": {"coordinates":[-117.775166,33.898504],"type":"Point"}
}