{
  "type": "Feature",
  "properties": {
    "iso:country":"US",
    "sg:address":"1435 4th St",
    "sg:city":"Berkeley",
    "sg:classifiers":[
        {
            "category":"Manufacturing",
            "subcategory":"Printing",
            "type":"Manufacturing & Wholesale Goods"
        }
    ],
    "sg:phone":"+1 510 526 1645",
    "sg:postcode":"94710",
    "sg:province":"CA",
    "sg:tags":[
        "publisher"
    ],
    "wof:name":"Favero Angela Hartley & Marks",
    "wof:placetype":"venue"
},
  "geometry": {"coordinates":[-122.302167,37.874931],"type":"Point"}
}