{
  "type": "Feature",
  "properties": {
    "iso:country":"US",
    "sg:address":"4275 Asher St",
    "sg:city":"San Diego",
    "sg:classifiers":[
        {
            "category":"Professional",
            "subcategory":"Management & Consulting",
            "type":"Services"
        }
    ],
    "sg:phone":"+1 619 276 4333",
    "sg:postcode":"92110",
    "sg:province":"CA",
    "sg:tags":[
        "consultant",
        "business"
    ],
    "wof:name":"Innovative Business Consultant",
    "wof:placetype":"venue"
},
  "geometry": {"coordinates":[-117.206709,32.778556],"type":"Point"}
}