{
  "type": "Feature",
  "properties": {
    "addr:full":"425 Market St Ste 2226 San Francisco CA 94105",
    "addr:housenumber":"425",
    "addr:postcode":"94105",
    "addr:street":"Market St Ste 2226",
    "iso:country":"US",
    "sg:address":"425 Market St Ste 2226",
    "sg:city":"San Francisco",
    "sg:classifiers":[
        {
            "category":"Professional",
            "type":"Services"
        }
    ],
    "sg:phone":"+1 415 955 2681",
    "sg:postcode":"94105",
    "sg:province":"CA",
    "sg:website":"www.hirecounsel.com",
    "wof:name":"HIRECounsel",
    "wof:placetype":"venue"
},
  "geometry": {"coordinates":[-122.398126,37.791128],"type":"Point"}
}