{
  "type": "Feature",
  "properties": {
    "iso:country":"US",
    "sg:address":"2905 Cadiz St",
    "sg:city":"San Diego",
    "sg:classifiers":[
        {
            "category":"Social Services",
            "subcategory":"Child Care",
            "type":"Services"
        }
    ],
    "sg:phone":"+1 619 523 2510",
    "sg:postcode":"92110",
    "sg:province":"CA",
    "wof:name":"Neighborhood House Loma Portal",
    "wof:placetype":"venue"
},
  "geometry": {"coordinates":[-117.210645,32.744209],"type":"Point"}
}