{
  "type": "Feature",
  "properties": {
    "addr:full":"27500 Marguerite Parkway Mission Viejo CA 92692",
    "addr:housenumber":"27500",
    "addr:postcode":"92692",
    "addr:street":"Marguerite Parkway",
    "iso:country":"US",
    "sg:address":"27500 Marguerite Parkway",
    "sg:city":"Mission Viejo",
    "sg:classifiers":[
        {
            "category":"Retail",
            "subcategory":"Laundry & Dry Cleaning",
            "type":"Services"
        }
    ],
    "sg:phone":"+1 949 347 0118",
    "sg:postcode":"92692",
    "sg:province":"CA",
    "sg:website":"www.parkwaycleaners.com",
    "wof:name":"Parkway Cleaners",
    "wof:placetype":"venue"
},
  "geometry": {"coordinates":[-117.65779999999999,33.564694],"type":"Point"}
}