{
  "type": "Feature",
  "properties": {
    "iso:country":"US",
    "sg:address":"461 E Menlo Ave",
    "sg:city":"Hemet",
    "sg:classifiers":[
        {
            "category":"Manufacturing",
            "subcategory":"Chemicals & Compounds",
            "type":"Manufacturing & Wholesale Goods"
        }
    ],
    "sg:phone":"+1 951 654 1350",
    "sg:postcode":"92543",
    "sg:province":"CA",
    "sg:tags":[
        "specialty"
    ],
    "wof:name":"Overnight Industrial",
    "wof:placetype":"venue"
},
  "geometry": {"coordinates":[-116.968118,33.758369],"type":"Point"}
}