{
  "type": "Feature",
  "properties": {
    "addr:full":"24201 Valencia Blvd Ste 146 Santa Clarita CA 91355",
    "addr:housenumber":"24201",
    "addr:postcode":"91355",
    "addr:street":"Valencia Blvd Ste 146",
    "iso:country":"US",
    "sg:address":"24201 Valencia Blvd Ste 146",
    "sg:city":"Santa Clarita",
    "sg:classifiers":[
        {
            "category":"Shopping",
            "subcategory":"Clothing, Apparel, & Fashions",
            "type":"Retail Goods"
        }
    ],
    "sg:phone":"+1 661 253 9916",
    "sg:postcode":"91355",
    "sg:province":"CA",
    "sg:tags":[
        "accessory"
    ],
    "wof:name":"Amuse",
    "wof:placetype":"venue"
},
  "geometry": {"coordinates":[-118.557683,34.413351],"type":"Point"}
}