{
  "type": "Feature",
  "properties": {
    "addr:full":"2145 Morrill Ave San Jose CA 95132",
    "addr:housenumber":"2145",
    "addr:postcode":"95132",
    "addr:street":"Morrill Ave",
    "iso:country":"US",
    "sg:address":"2145 Morrill Ave",
    "sg:city":"San Jose",
    "sg:classifiers":[
        {
            "category":"Shopping",
            "subcategory":"Shoes",
            "type":"Retail Goods"
        }
    ],
    "sg:phone":"+1 408 945 1988",
    "sg:postcode":"95132",
    "sg:province":"CA",
    "wof:name":"Payless Shoe Source",
    "wof:placetype":"venue"
},
  "geometry": {"coordinates":[-121.874853,37.415106],"type":"Point"}
}