{
  "type": "Feature",
  "properties": {
    "iso:country":"US",
    "sg:address":"11912 Rivera Rd",
    "sg:city":"Santa Fe Springs",
    "sg:classifiers":[
        {
            "category":"Shopping",
            "subcategory":"Department Store",
            "type":"Retail Goods"
        },
        {
            "category":"Home & Garden",
            "subcategory":"Home Furnishings",
            "type":"Retail Goods"
        }
    ],
    "sg:phone":"+1 562 696 2911",
    "sg:postcode":"90670",
    "sg:province":"CA",
    "sg:tags":[
        "housewares"
    ],
    "wof:name":"Emblema Enterprise",
    "wof:placetype":"venue"
},
  "geometry": {"coordinates":[-118.059108,33.965284],"type":"Point"}
}