{
  "type": "Feature",
  "properties": {
    "addr:full":"9303 Spring Hill School Rd Sebastopol CA 95472",
    "addr:housenumber":"9303",
    "addr:postcode":"95472",
    "addr:street":"Spring;School Rd",
    "iso:country":"US",
    "sg:address":"9303 Spring Hill School Rd",
    "sg:city":"Sebastopol",
    "sg:classifiers":[
        {
            "category":"Building & Trades",
            "subcategory":"Construction",
            "type":"Services"
        }
    ],
    "sg:phone":"+1 707 478 9485",
    "sg:postcode":"95472",
    "sg:province":"CA",
    "sg:tags":[
        "contractor"
    ],
    "wof:name":"Bill Holden Construction",
    "wof:placetype":"venue"
},
  "geometry": {"coordinates":[-122.862709,38.395423],"type":"Point"}
}