{
  "type": "Feature",
  "properties": {
    "addr:full":"1086 Golden Gate Avenue San Francisco CA 94115",
    "addr:housenumber":"1086",
    "addr:postcode":"94115",
    "addr:street":"Golden Gate Avenue",
    "iso:country":"US",
    "sg:address":"1086 Golden Gate Avenue",
    "sg:city":"San Francisco",
    "sg:classifiers":[
        {
            "category":"Real Estate",
            "subcategory":"Real Estate Operator",
            "type":"Services"
        }
    ],
    "sg:phone":"+1 415 929 1161",
    "sg:postcode":"94115",
    "sg:province":"CA",
    "sg:tags":[
        "apartment"
    ],
    "wof:name":"Thomas Paine Square Apartments",
    "wof:placetype":"venue"
},
  "geometry": {"coordinates":[-122.435592,37.785819],"type":"Point"}
}