{
  "type": "Feature",
  "properties": {
    "addr:full":"5375 Lakeshore Blvd Lakeport CA 95453",
    "addr:housenumber":"5375",
    "addr:postcode":"95453",
    "addr:street":"Lakeshore Blvd",
    "iso:country":"US",
    "sg:address":"5375 Lakeshore Blvd",
    "sg:city":"Lakeport",
    "sg:classifiers":[
        {
            "category":"Health Services",
            "subcategory":"Doctor",
            "type":"Services"
        }
    ],
    "sg:phone":"+1 707 263 5679",
    "sg:postcode":"95453",
    "sg:province":"CA",
    "sg:tags":[
        "physician",
        "surgeon"
    ],
    "wof:name":"Lakeshore Medical Assoc",
    "wof:placetype":"venue"
},
  "geometry": {"coordinates":[-122.903077,39.105513],"type":"Point"}
}