{
  "type": "Feature",
  "properties": {
    "iso:country":"US",
    "sg:address":"7650 Sunset Ave",
    "sg:city":"Fair Oaks",
    "sg:classifiers":[
        {
            "category":"Building & Trades",
            "subcategory":"Plumbing",
            "type":"Services"
        }
    ],
    "sg:phone":"+1 916 965 1201",
    "sg:postcode":"95628",
    "sg:province":"CA",
    "sg:tags":[
        "contractor"
    ],
    "wof:name":"Alexeys Service",
    "wof:placetype":"venue"
},
  "geometry": {"coordinates":[-121.28278,38.652695],"type":"Point"}
}