{
  "type": "Feature",
  "properties": {
    "addr:full":"4 Locust Ave Mill Valley CA 94941",
    "addr:housenumber":"4",
    "addr:postcode":"94941",
    "addr:street":"Locust Ave",
    "iso:country":"US",
    "sg:address":"4 Locust Ave",
    "sg:city":"Mill Valley",
    "sg:classifiers":[
        {
            "category":"Restaurant",
            "type":"Food & Drink"
        }
    ],
    "sg:phone":"+1 415 388 6958",
    "sg:postcode":"94941",
    "sg:province":"CA",
    "wof:name":"Mill Valley Coffee Shop",
    "wof:placetype":"venue"
},
  "geometry": {"coordinates":[-122.537054,37.898625],"type":"Point"}
}