{
  "type": "Feature",
  "properties": {
    "addr:full":"140 S 15th St Chowchilla CA 93610",
    "addr:housenumber":"140",
    "addr:postcode":"93610",
    "addr:street":"S 15Th St",
    "iso:country":"US",
    "sg:address":"140 S 15th St",
    "sg:city":"Chowchilla",
    "sg:classifiers":[
        {
            "category":"Restaurant",
            "type":"Food & Drink"
        }
    ],
    "sg:menulink":"http://www.allmenus.com/ca/chowchilla/68375-pizza-factory/menu/",
    "sg:phone":"+1 559 665 4000",
    "sg:postcode":"93610",
    "sg:province":"CA",
    "sg:tags":[
        "american",
        "pizza"
    ],
    "wof:name":"Pizza Factory",
    "wof:placetype":"venue"
},
  "geometry": {"coordinates":[-120.270875,37.113632],"type":"Point"}
}