{
  "type": "Feature",
  "properties": {
    "iso:country":"US",
    "sg:address":"22209 Mission Blvd",
    "sg:city":"Hayward",
    "sg:classifiers":[
        {
            "category":"Autos & Motor Vehicles",
            "subcategory":"Automobile Sales",
            "type":"Retail Goods"
        }
    ],
    "sg:phone":"+1 510 581 4400",
    "sg:postcode":"94541",
    "sg:province":"CA",
    "sg:tags":[
        "car",
        "dealer"
    ],
    "wof:name":"Auto Plaza",
    "wof:placetype":"venue"
},
  "geometry": {"coordinates":[-122.087418,37.675013],"type":"Point"}
}