{
  "type": "Feature",
  "properties": {
    "iso:country":"US",
    "sg:address":"19401 Harborgate Way",
    "sg:city":"Torrance",
    "sg:classifiers":[
        {
            "category":"Professional",
            "type":"Services"
        }
    ],
    "sg:phone":"+1 310 782 0923",
    "sg:postcode":"90501",
    "sg:province":"CA",
    "sg:tags":[
        "establishment"
    ],
    "wof:name":"Seville Classics Inc",
    "wof:placetype":"venue"
},
  "geometry": {"coordinates":[-118.30353599999999,33.850628],"type":"Point"}
}