{
  "type": "Feature",
  "properties": {
    "addr:full":"4716 Foulger Dr Santa Rosa CA 95405",
    "addr:housenumber":"4716",
    "addr:postcode":"95405",
    "addr:street":"Foulger Dr",
    "iso:country":"US",
    "sg:address":"4716 Foulger Dr",
    "sg:city":"Santa Rosa",
    "sg:classifiers":[
        {
            "category":"Professional",
            "subcategory":"Employment Agencies",
            "type":"Services"
        }
    ],
    "sg:phone":"+1 707 537 8247",
    "sg:postcode":"95405",
    "sg:province":"CA",
    "sg:tags":[
        "modeling"
    ],
    "wof:name":"Patricia Rile Modeling & Actng",
    "wof:placetype":"venue"
},
  "geometry": {"coordinates":[-122.65691099999999,38.44026],"type":"Point"}
}