{
  "type": "Feature",
  "properties": {
    "addr:full":"801 S. Glenoaks Bl Burbank CA 91502",
    "addr:housenumber":"801;bl",
    "addr:postcode":"91502",
    "addr:street":"S. Glenoaks",
    "iso:country":"US",
    "sg:address":"801 S. Glenoaks Bl",
    "sg:city":"Burbank",
    "sg:classifiers":[
        {
            "category":"Professional",
            "subcategory":"Employment Agencies",
            "type":"Services"
        }
    ],
    "sg:phone":"+1 310 274 6880",
    "sg:postcode":"91502",
    "sg:province":"CA",
    "wof:name":"Temps On Time-the Employment Center",
    "wof:placetype":"venue"
},
  "geometry": {"coordinates":[-118.29947199999999,34.17785],"type":"Point"}
}