{
  "type": "Feature",
  "properties": {
    "iso:country":"US",
    "sg:address":"1115 Healdsburg Ave",
    "sg:city":"Healdsburg",
    "sg:classifiers":[
        {
            "category":"Manufacturing",
            "subcategory":"Rubber & Plastics",
            "type":"Manufacturing & Wholesale Goods"
        },
        {
            "category":"Autos & Motor Vehicles",
            "subcategory":"Auto Supplies",
            "type":"Retail Goods"
        },
        {
            "category":"Retail",
            "subcategory":"Auto Repair",
            "type":"Services"
        }
    ],
    "sg:phone":"+1 707 433 6644",
    "sg:postcode":"95448",
    "sg:province":"CA",
    "sg:tags":[
        "wheel",
        "oil",
        "tires-wholesale",
        "tire",
        "wheels-frame",
        "retread",
        "lube",
        "brake",
        "axle",
        "wheels-aligning",
        "recap",
        "balancing",
        "servicing-equipment",
        "manufacturer"
    ],
    "sg:website":"http://www.bigotires.com",
    "wof:name":"Big O Tires",
    "wof:placetype":"venue"
},
  "geometry": {"coordinates":[-122.872654,38.623867],"type":"Point"}
}