{
  "type": "Feature",
  "properties": {
    "iso:country":"US",
    "sg:address":"9407 Oakmore Rd",
    "sg:city":"Los Angeles",
    "sg:classifiers":[
        {
            "category":"Real Estate",
            "subcategory":"Real Estate Agent",
            "type":"Services"
        }
    ],
    "sg:phone":"+1 310 202 0619",
    "sg:postcode":"90035",
    "sg:province":"CA",
    "sg:tags":[
        "management"
    ],
    "wof:name":"Eustis Plaza Inc",
    "wof:placetype":"venue"
},
  "geometry": {"coordinates":[-118.393119,34.04779],"type":"Point"}
}