{
  "type": "Feature",
  "properties": {
    "addr:full":"5425 Ericson Way Unit C Arcata CA 95521",
    "addr:housenumber":"5425",
    "addr:postcode":"95521",
    "addr:street":"Ericson Way Unit C",
    "iso:country":"US",
    "sg:address":"5425 Ericson Way Unit C",
    "sg:city":"Arcata",
    "sg:classifiers":[
        {
            "category":"Restaurant",
            "type":"Food & Drink"
        }
    ],
    "sg:phone":"+1 707 825 0178",
    "sg:postcode":"95521",
    "sg:province":"CA",
    "sg:tags":[
        "italian"
    ],
    "wof:name":"Hasta BE Pasta",
    "wof:placetype":"venue"
},
  "geometry": {"coordinates":[-124.06928600000001,40.903522],"type":"Point"}
}