{
  "type": "Feature",
  "properties": {
    "addr:full":"1246 Folsom St San Francisco CA 94101",
    "addr:housenumber":"1246",
    "addr:postcode":"94101",
    "addr:street":"Folsom St",
    "iso:country":"US",
    "sg:address":"1246 Folsom St",
    "sg:city":"San Francisco",
    "sg:classifiers":[
        {
            "category":"Arts & Performance",
            "subcategory":"Arts Center",
            "type":"Entertainment"
        }
    ],
    "sg:phone":"+1 415 289 6766",
    "sg:postcode":"94101",
    "sg:province":"CA",
    "sg:tags":[
        "performing"
    ],
    "sg:website":"www.thunderbirdtheatre.com",
    "wof:name":"Thunderbird Theatre Company",
    "wof:placetype":"venue"
},
  "geometry": {"coordinates":[-122.410994,37.774589],"type":"Point"}
}