{
  "type": "Feature",
  "properties": {
    "iso:country":"US",
    "sg:address":"1625 E Main St",
    "sg:city":"El Cajon",
    "sg:classifiers":[
        {
            "category":"Health Services",
            "subcategory":"Doctor",
            "type":"Services"
        }
    ],
    "sg:phone":"+1 619 579 5115",
    "sg:postcode":"92021",
    "sg:province":"CA",
    "sg:tags":[
        "physician",
        "surgeon"
    ],
    "wof:name":"Skin & Skin Cancer Medical Grp",
    "wof:placetype":"venue"
},
  "geometry": {"coordinates":[-116.91924,32.811099],"type":"Point"}
}