{
  "type": "Feature",
  "properties": {
    "addr:full":"550 W 16th St Long Beach CA 90813",
    "addr:housenumber":"550",
    "addr:postcode":"90813",
    "addr:street":"W 16Th St",
    "iso:country":"US",
    "sg:address":"550 W 16th St",
    "sg:city":"Long Beach",
    "sg:classifiers":[
        {
            "category":"Manufacturing",
            "subcategory":"Motor Vehicles & Parts",
            "type":"Manufacturing & Wholesale Goods"
        }
    ],
    "sg:phone":"+1 562 437 0061",
    "sg:postcode":"90813",
    "sg:province":"CA",
    "sg:tags":[
        "automobile",
        "supply"
    ],
    "sg:website":"www.acmeautoheadlining.com",
    "wof:name":"Acme Auto Headlining Co",
    "wof:placetype":"venue"
},
  "geometry": {"coordinates":[-118.19880999999999,33.786789],"type":"Point"}
}