{
  "type": "Feature",
  "properties": {
    "iso:country":"US",
    "sg:address":"8960 Corte Pozos",
    "sg:city":"Spring Valley",
    "sg:classifiers":[
        {
            "category":"Social Services",
            "subcategory":"Adult Care",
            "type":"Services"
        }
    ],
    "sg:phone":"+1 619 470 1504",
    "sg:postcode":"91977",
    "sg:province":"CA",
    "sg:tags":[
        "home",
        "residential"
    ],
    "wof:name":"Lakeview Residential Care Home",
    "wof:placetype":"venue"
},
  "geometry": {"coordinates":[-117.005403,32.696249],"type":"Point"}
}