{
  "type": "Feature",
  "properties": {
    "iso:country":"US",
    "sg:address":"6607 W 5th St",
    "sg:city":"Los Angeles",
    "sg:classifiers":[
        {
            "category":"Building & Trades",
            "subcategory":"Construction",
            "type":"Services"
        }
    ],
    "sg:phone":"+1 323 655 5900",
    "sg:postcode":"90048",
    "sg:province":"CA",
    "sg:tags":[
        "house"
    ],
    "wof:name":"J M Carlson Construction",
    "wof:placetype":"venue"
},
  "geometry": {"coordinates":[-118.373663,34.068854],"type":"Point"}
}