{
  "type": "Feature",
  "properties": {
    "iso:country":"US",
    "sg:address":"700 S Vermont Ave",
    "sg:city":"Los Angeles",
    "sg:classifiers":[
        {
            "category":"Autos & Motor Vehicles",
            "subcategory":"Fuel & Gas Station",
            "type":"Retail Goods"
        }
    ],
    "sg:phone":"+1 213 389 3989",
    "sg:postcode":"90005",
    "sg:province":"CA",
    "wof:name":"Vermont Shell Auto Center",
    "wof:placetype":"venue"
},
  "geometry": {"coordinates":[-118.292,34.059502],"type":"Point"}
}