{
  "type": "Feature",
  "properties": {
    "iso:country":"US",
    "sg:address":"12150 Tech Center Dr",
    "sg:city":"Poway",
    "sg:classifiers":[
        {
            "category":"Retail",
            "subcategory":"Repair Shop",
            "type":"Services"
        }
    ],
    "sg:phone":"+1 858 679 2400",
    "sg:postcode":"92064",
    "sg:province":"CA",
    "sg:tags":[
        "mfg"
    ],
    "sg:website":"www.kone.com",
    "wof:name":"KONE Inc",
    "wof:placetype":"venue"
},
  "geometry": {"coordinates":[-117.036556,32.938316],"type":"Point"}
}