{
  "type": "Feature",
  "properties": {
    "iso:country":"US",
    "sg:address":"736 Cordoba St",
    "sg:city":"Soledad",
    "sg:classifiers":[
        {
            "category":"Shopping",
            "subcategory":"Computers & Home Electronics",
            "type":"Retail Goods"
        }
    ],
    "sg:phone":"+1 831 678 3583",
    "sg:postcode":"93960",
    "sg:province":"CA",
    "wof:name":"Crandalls Computer",
    "wof:placetype":"venue"
},
  "geometry": {"coordinates":[-121.32084999999999,36.4342],"type":"Point"}
}