{
  "type": "Feature",
  "properties": {
    "addr:full":"301 N M St Dinuba CA 93618",
    "addr:housenumber":"301",
    "addr:postcode":"93618",
    "addr:street":"N M St",
    "iso:country":"US",
    "sg:address":"301 N M St",
    "sg:city":"Dinuba",
    "sg:classifiers":[
        {
            "category":"Wholesale",
            "subcategory":"Fruits & Vegetables",
            "type":"Manufacturing & Wholesale Goods"
        }
    ],
    "sg:phone":"+1 559 591 4782",
    "sg:postcode":"93618",
    "sg:province":"CA",
    "sg:website":"www.amberfoods.com",
    "wof:name":"Amber Foods",
    "wof:placetype":"venue"
},
  "geometry": {"coordinates":[-119.394515,36.543065],"type":"Point"}
}