{
  "type": "Feature",
  "properties": {
    "iso:country":"US",
    "sg:address":"1416 Park Ave",
    "sg:city":"Alameda",
    "sg:classifiers":[
        {
            "category":"Communications",
            "subcategory":"Newspaper",
            "type":"Services"
        }
    ],
    "sg:phone":"+1 510 747 1060",
    "sg:postcode":"94501",
    "sg:province":"CA",
    "sg:tags":[
        "print",
        "medium"
    ],
    "sg:website":"www.oaklandmagazine.com",
    "wof:name":"Oakland Magazine",
    "wof:placetype":"venue"
},
  "geometry": {"coordinates":[-122.241196,37.764166],"type":"Point"}
}