{
  "type": "Feature",
  "properties": {
    "addr:full":"205 W Mission Ave Escondido CA 92025",
    "addr:housenumber":"205",
    "addr:postcode":"92025",
    "addr:street":"W Mission Ave",
    "iso:country":"US",
    "sg:address":"205 W Mission Ave",
    "sg:city":"Escondido",
    "sg:classifiers":[
        {
            "category":"Health Services",
            "subcategory":"Chiropractor",
            "type":"Services"
        }
    ],
    "sg:phone":"+1 760 480 0077",
    "sg:postcode":"92025",
    "sg:province":"CA",
    "sg:tags":[
        "medicine",
        "alternative",
        "practitioner"
    ],
    "sg:website":"http://www.calpainrelief.com",
    "wof:name":"Lim Chiropractic Clinic",
    "wof:placetype":"venue"
},
  "geometry": {"coordinates":[-117.087458,33.129692],"type":"Point"}
}