{
  "type": "Feature",
  "properties": {
    "iso:country":"US",
    "sg:address":"1001 6th St",
    "sg:city":"Sacramento",
    "sg:classifiers":[
        {
            "category":"Government",
            "subcategory":"Office",
            "type":"Public Place"
        }
    ],
    "sg:phone":"+1 916 446 4040",
    "sg:postcode":"95814",
    "sg:province":"CA",
    "sg:tags":[
        "housing",
        "program"
    ],
    "wof:name":"Glenwood Hotel Investors",
    "wof:placetype":"venue"
},
  "geometry": {"coordinates":[-121.498541,38.582282],"type":"Point"}
}