{
  "type": "Feature",
  "properties": {
    "addr:full":"920 E Colorado Blvd Pasadena CA 91106",
    "addr:housenumber":"920",
    "addr:postcode":"91106",
    "addr:street":"E Colorado Blvd",
    "iso:country":"US",
    "sg:address":"920 E Colorado Blvd",
    "sg:city":"Pasadena",
    "sg:classifiers":[
        {
            "category":"Professional",
            "subcategory":"Computer Services",
            "type":"Services"
        }
    ],
    "sg:phone":"+1 626 577 2100",
    "sg:postcode":"91106",
    "sg:province":"CA",
    "sg:tags":[
        "repair"
    ],
    "sg:website":"www.pcconnect.net",
    "wof:name":"PC Connect",
    "wof:placetype":"venue"
},
  "geometry": {"coordinates":[-118.131603,34.145869],"type":"Point"}
}