{
  "type": "Feature",
  "properties": {
    "addr:full":"1001 Ocean St Santa Cruz CA 95060",
    "addr:housenumber":"1001",
    "addr:postcode":"95060",
    "addr:street":"Ocean St",
    "iso:country":"US",
    "sg:address":"1001 Ocean St",
    "sg:city":"Santa Cruz",
    "sg:classifiers":[
        {
            "category":"Home & Garden",
            "subcategory":"Building Materials",
            "type":"Retail Goods"
        }
    ],
    "sg:phone":"+1 831 427 0211",
    "sg:postcode":"95060",
    "sg:province":"CA",
    "sg:tags":[
        "paint"
    ],
    "sg:website":"www.kellymoore.com",
    "wof:name":"Kelley-Moore Paint Co",
    "wof:placetype":"venue"
},
  "geometry": {"coordinates":[-122.022161,36.981866],"type":"Point"}
}