{
  "type": "Feature",
  "properties": {
    "addr:full":"328 Center St Healdsburg CA 95448",
    "addr:housenumber":"328",
    "addr:postcode":"95448",
    "addr:street":"Center St",
    "iso:country":"US",
    "sg:address":"328 Center St",
    "sg:city":"Healdsburg",
    "sg:classifiers":[
        {
            "category":"Shopping",
            "subcategory":"Jewelry",
            "type":"Retail Goods"
        }
    ],
    "sg:phone":"+1 707 431 1810",
    "sg:postcode":"95448",
    "sg:province":"CA",
    "sg:tags":[
        "appraiser",
        "jeweler"
    ],
    "sg:website":"http://www.goldbloomjewelers.com",
    "wof:name":"Gold Bloom",
    "wof:placetype":"venue"
},
  "geometry": {"coordinates":[-122.869614,38.611271],"type":"Point"}
}