{
  "type": "Feature",
  "properties": {
    "iso:country":"US",
    "sg:address":"1560 Geer Rd",
    "sg:city":"Turlock",
    "sg:classifiers":[
        {
            "category":"Personal",
            "subcategory":"Beauty Salon",
            "type":"Services"
        }
    ],
    "sg:phone":"+1 209 669 7955",
    "sg:postcode":"95380",
    "sg:province":"CA",
    "sg:tags":[
        "manicuring"
    ],
    "wof:name":"Model Nails",
    "wof:placetype":"venue"
},
  "geometry": {"coordinates":[-120.848802,37.507052],"type":"Point"}
}