{
  "type": "Feature",
  "properties": {
    "iso:country":"US",
    "sg:address":"5811 E Princeton Ave",
    "sg:city":"Fresno",
    "sg:classifiers":[
        {
            "category":"Building & Trades",
            "subcategory":"Plumbing",
            "type":"Services"
        }
    ],
    "sg:phone":"+1 559 291 9296",
    "sg:postcode":"93727",
    "sg:province":"CA",
    "sg:tags":[
        "plumbing",
        "contractor"
    ],
    "wof:name":"Quantum Mechanical Contrs Inc",
    "wof:placetype":"venue"
},
  "geometry": {"coordinates":[-119.690635,36.775892],"type":"Point"}
}