{
  "type": "Feature",
  "properties": {
    "iso:country":"US",
    "sg:address":"395 Sierra Madre Villa Ave",
    "sg:city":"Pasadena",
    "sg:classifiers":[
        {
            "category":"Professional",
            "subcategory":"Computer Services",
            "type":"Services"
        }
    ],
    "sg:phone":"+1 626 793 5748",
    "sg:postcode":"91107",
    "sg:province":"CA",
    "sg:tags":[
        "cd-rom"
    ],
    "sg:website":"http://www.allenashley.com",
    "wof:name":"Allen Ashley",
    "wof:placetype":"venue"
},
  "geometry": {"coordinates":[-118.082166,34.153145],"type":"Point"}
}