{
  "type": "Feature",
  "properties": {
    "addr:full":"10076 Grizzly Flat Rd Grizzly Flats CA 95636",
    "addr:housenumber":"10076",
    "addr:postcode":"95636",
    "addr:street":"Grizzly Flat Rd",
    "iso:country":"US",
    "sg:address":"10076 Grizzly Flat Rd",
    "sg:city":"Grizzly Flats",
    "sg:classifiers":[
        {
            "category":"Education",
            "subcategory":"Special Training",
            "type":"Public Place"
        }
    ],
    "sg:phone":"+1 530 621 1557",
    "sg:postcode":"95636",
    "sg:province":"CA",
    "sg:tags":[
        "aid",
        "instruction",
        "first"
    ],
    "wof:name":"Charles A Nichols",
    "wof:placetype":"venue"
},
  "geometry": {"coordinates":[-120.538072,38.633216],"type":"Point"}
}