{
  "type": "Feature",
  "properties": {
    "addr:full":"275 Gateway Dr Pacifica CA 94044",
    "addr:housenumber":"275",
    "addr:postcode":"94044",
    "addr:street":"Gateway Dr",
    "iso:country":"US",
    "sg:address":"275 Gateway Dr",
    "sg:city":"Pacifica",
    "sg:classifiers":[
        {
            "category":"Autos & Motor Vehicles",
            "subcategory":"Auto Supplies",
            "type":"Retail Goods"
        }
    ],
    "sg:phone":"+1 650 219 8646",
    "sg:postcode":"94044",
    "sg:province":"CA",
    "sg:tags":[
        "wheel",
        "cover"
    ],
    "wof:name":"Mr Dubs",
    "wof:placetype":"venue"
},
  "geometry": {"coordinates":[-122.478008,37.659796],"type":"Point"}
}