{
  "type": "Feature",
  "properties": {
    "addr:full":"1055 8th St Oakland CA 94607",
    "addr:housenumber":"1055",
    "addr:postcode":"94607",
    "addr:street":"8Th St",
    "iso:country":"US",
    "sg:address":"1055 8th St",
    "sg:city":"Oakland",
    "sg:classifiers":[
        {
            "category":"Real Estate",
            "subcategory":"Real Estate Operator",
            "type":"Services"
        },
        {
            "category":"Building & Trades",
            "subcategory":"Construction",
            "type":"Services"
        },
        {
            "category":"Real Estate",
            "subcategory":"Real Estate Services",
            "type":"Services"
        }
    ],
    "sg:phone":"+1 510 835 0620",
    "sg:postcode":"94607",
    "sg:province":"CA",
    "sg:tags":[
        "apartment",
        "management",
        "condominium"
    ],
    "wof:name":"Apollo Housing",
    "wof:placetype":"venue"
},
  "geometry": {"coordinates":[-122.28600299999999,37.804401],"type":"Point"}
}