{
  "type": "Feature",
  "properties": {
    "addr:full":"9059 Lamar St Spring Valley CA 91977",
    "addr:housenumber":"9059",
    "addr:postcode":"91977",
    "addr:street":"Lamar St",
    "iso:country":"US",
    "sg:address":"9059 Lamar St",
    "sg:city":"Spring Valley",
    "sg:classifiers":[
        {
            "category":"Building & Trades",
            "subcategory":"Construction",
            "type":"Services"
        }
    ],
    "sg:phone":"+1 619 527 2132",
    "sg:postcode":"91977",
    "sg:province":"CA",
    "sg:tags":[
        "fire",
        "restoration",
        "damage"
    ],
    "wof:name":"A Rescue One Restoration",
    "wof:placetype":"venue"
},
  "geometry": {"coordinates":[-117.00314299999999,32.73936],"type":"Point"}
}