{
  "type": "Feature",
  "properties": {
    "addr:full":"3301 Airport Dr Torrance CA 90505",
    "addr:housenumber":"3301",
    "addr:postcode":"90505",
    "addr:street":"Airport Dr",
    "iso:country":"US",
    "sg:address":"3301 Airport Dr",
    "sg:city":"Torrance",
    "sg:classifiers":[
        {
            "category":"Organizations",
            "subcategory":"Non-profit Organization",
            "type":"Services"
        }
    ],
    "sg:phone":"+1 310 539 3422",
    "sg:postcode":"90505",
    "sg:province":"CA",
    "wof:name":"Civil Air Patrol Squadrons",
    "wof:placetype":"venue"
},
  "geometry": {"coordinates":[-118.342085,33.800449],"type":"Point"}
}