{
  "type": "Feature",
  "properties": {
    "iso:country":"US",
    "sg:address":"7260 E Southgate Dr",
    "sg:city":"Sacramento",
    "sg:classifiers":[
        {
            "category":"Health Services",
            "subcategory":"Doctor",
            "type":"Services"
        }
    ],
    "sg:phone":"+1 916 422 6671",
    "sg:postcode":"95823",
    "sg:province":"CA",
    "sg:tags":[
        "dentist"
    ],
    "wof:name":"Janice Work Pediatric Dntstry",
    "wof:placetype":"venue"
},
  "geometry": {"coordinates":[-121.43737,38.494797],"type":"Point"}
}