{
  "type": "Feature",
  "properties": {
    "addr:full":"10309 Santa Monica Boulevard Los Angeles CA 90025",
    "addr:housenumber":"10309",
    "addr:postcode":"90025",
    "addr:street":"Santa Monica Boulevard",
    "iso:country":"US",
    "sg:address":"10309 Santa Monica Boulevard",
    "sg:city":"Los Angeles",
    "sg:classifiers":[
        {
            "category":"Health Services",
            "subcategory":"Doctor",
            "type":"Services"
        }
    ],
    "sg:phone":"+1 310 553 1432",
    "sg:postcode":"90025",
    "sg:province":"CA",
    "wof:name":"Kline David A MD",
    "wof:placetype":"venue"
},
  "geometry": {"coordinates":[-118.422206,34.058993],"type":"Point"}
}