{
  "type": "Feature",
  "properties": {
    "iso:country":"US",
    "sg:address":"1231 W Robinhood Dr",
    "sg:city":"Stockton",
    "sg:classifiers":[
        {
            "category":"Wholesale",
            "subcategory":"Groceries",
            "type":"Manufacturing & Wholesale Goods"
        }
    ],
    "sg:phone":"+1 209 466 8591",
    "sg:postcode":"95207",
    "sg:province":"CA",
    "sg:tags":[
        "grocer"
    ],
    "wof:name":"Ca Delta Farms Inc",
    "wof:placetype":"venue"
},
  "geometry": {"coordinates":[-121.320948,37.999694],"type":"Point"}
}