{
  "type": "Feature",
  "properties": {
    "addr:full":"30300 Whipple Rd Union City CA 94587",
    "addr:housenumber":"30300",
    "addr:postcode":"94587",
    "addr:street":"Whipple Rd",
    "iso:country":"US",
    "sg:address":"30300 Whipple Rd",
    "sg:city":"Union City",
    "sg:classifiers":[
        {
            "category":"Manufacturing",
            "subcategory":"Tools & Machinery",
            "type":"Manufacturing & Wholesale Goods"
        }
    ],
    "sg:phone":"+1 510 441 1100",
    "sg:postcode":"94587",
    "sg:province":"CA",
    "sg:tags":[
        "mfg",
        "light",
        "fixture",
        "design",
        "fluorescent",
        "indirect"
    ],
    "sg:website":"www.finelite.com",
    "wof:name":"Finelite Inc",
    "wof:placetype":"venue"
},
  "geometry": {"coordinates":[-122.084594,37.605572],"type":"Point"}
}