{
  "type": "Feature",
  "properties": {
    "iso:country":"US",
    "sg:address":"790 Lucerne Dr",
    "sg:city":"Sunnyvale",
    "sg:classifiers":[
        {
            "category":"Insurance",
            "subcategory":"Insurance Agent",
            "type":"Services"
        }
    ],
    "sg:phone":"+1 408 733 3753",
    "sg:postcode":"94085",
    "sg:province":"CA",
    "wof:name":"Al Caso Insurance",
    "wof:placetype":"venue"
},
  "geometry": {"coordinates":[-122.01415,37.379609],"type":"Point"}
}