{
  "type": "Feature",
  "properties": {
    "iso:country":"US",
    "sg:address":"2000 W Pueblo Ave",
    "sg:city":"Napa",
    "sg:classifiers":[
        {
            "category":"Recreation",
            "type":"Entertainment"
        }
    ],
    "sg:phone":"+1 707 255 5470",
    "sg:postcode":"94558",
    "sg:province":"CA",
    "sg:tags":[
        "martial",
        "arts",
        "instruction"
    ],
    "wof:name":"Red Dragon Karate",
    "wof:placetype":"venue"
},
  "geometry": {"coordinates":[-122.308768,38.313657],"type":"Point"}
}