{
  "type": "Feature",
  "properties": {
    "addr:full":"890 Van Horn Way El Cajon CA 92019",
    "addr:housenumber":"890",
    "addr:postcode":"92019",
    "addr:street":"Van Horn Way",
    "iso:country":"US",
    "sg:address":"890 Van Horn Way",
    "sg:city":"El Cajon",
    "sg:classifiers":[
        {
            "category":"Professional",
            "type":"Services"
        }
    ],
    "sg:phone":"+1 619 579 8844",
    "sg:postcode":"92019",
    "sg:province":"CA",
    "wof:name":"S&J Gardens",
    "wof:placetype":"venue"
},
  "geometry": {"coordinates":[-116.91184199999999,32.780879],"type":"Point"}
}