{
  "type": "Feature",
  "properties": {
    "addr:full":"921 S Fresno St Los Angeles CA 90023",
    "addr:housenumber":"921",
    "addr:postcode":"90023",
    "addr:street":"S Fresno St",
    "iso:country":"US",
    "sg:address":"921 S Fresno St",
    "sg:city":"Los Angeles",
    "sg:classifiers":[
        {
            "category":"Professional",
            "type":"Services"
        }
    ],
    "sg:phone":"+1 323 780 0159",
    "sg:postcode":"90023",
    "sg:province":"CA",
    "wof:name":"Rafael Parada",
    "wof:placetype":"venue"
},
  "geometry": {"coordinates":[-118.20698,34.028838],"type":"Point"}
}