{
  "type": "Feature",
  "properties": {
    "iso:country":"US",
    "sg:address":"7428 Redwood Blvd",
    "sg:city":"Novato",
    "sg:classifiers":[
        {
            "category":"Science Facility",
            "type":"Public Place"
        }
    ],
    "sg:phone":"+1 415 892 3182",
    "sg:postcode":"94945",
    "sg:province":"CA",
    "sg:tags":[
        "development",
        "laboratories-research"
    ],
    "wof:name":"Atira Technology",
    "wof:placetype":"venue"
},
  "geometry": {"coordinates":[-122.569256,38.109708],"type":"Point"}
}