{
  "type": "Feature",
  "properties": {
    "addr:full":"2021 E Via Burton Ste L Anaheim CA 92806",
    "addr:housenumber":"2021",
    "addr:postcode":"92806",
    "addr:street":"E Via Burton Ste L",
    "iso:country":"US",
    "sg:address":"2021 E Via Burton Ste L",
    "sg:city":"Anaheim",
    "sg:classifiers":[
        {
            "category":"Arts & Performance",
            "subcategory":"Music",
            "type":"Entertainment"
        }
    ],
    "sg:phone":"+1 714 533 0061",
    "sg:postcode":"92806",
    "sg:province":"CA",
    "sg:tags":[
        "dj"
    ],
    "wof:name":"Kumba Entertainment & Event Services",
    "wof:placetype":"venue"
},
  "geometry": {"coordinates":[-117.889,33.8563],"type":"Point"}
}