{
  "type": "Feature",
  "properties": {
    "iso:country":"US",
    "sg:address":"100 W Broadway",
    "sg:city":"Glendale",
    "sg:classifiers":[
        {
            "category":"Education",
            "subcategory":"Special Training",
            "type":"Public Place"
        }
    ],
    "sg:phone":"+1 818 547 4995",
    "sg:postcode":"91210",
    "sg:province":"CA",
    "sg:tags":[
        "school",
        "language"
    ],
    "wof:name":"Inline Translation Services",
    "wof:placetype":"venue"
},
  "geometry": {"coordinates":[-118.254997,34.146301],"type":"Point"}
}