{
  "type": "Feature",
  "properties": {
    "iso:country":"US",
    "sg:address":"775 N 10th St",
    "sg:city":"San Jose",
    "sg:classifiers":[
        {
            "category":"Food & Beverages",
            "subcategory":"Fruits & Vegetables",
            "type":"Retail Goods"
        },
        {
            "category":"Wholesale",
            "subcategory":"Fruits & Vegetables",
            "type":"Manufacturing & Wholesale Goods"
        }
    ],
    "sg:phone":"+1 408 275 6231",
    "sg:postcode":"95112",
    "sg:province":"CA",
    "sg:tags":[
        "produce"
    ],
    "wof:name":"National Produce Inc",
    "wof:placetype":"venue"
},
  "geometry": {"coordinates":[-121.891206,37.354102],"type":"Point"}
}