{
  "type": "Feature",
  "properties": {
    "iso:country":"US",
    "sg:address":"18417 Arminta St",
    "sg:city":"Reseda",
    "sg:classifiers":[
        {
            "category":"Freight",
            "type":"Transportation"
        }
    ],
    "sg:phone":"+1 818 344 0386",
    "sg:postcode":"91335",
    "sg:province":"CA",
    "sg:tags":[
        "operator",
        "local",
        "trucking"
    ],
    "wof:name":"Armen Chrakian Trucking",
    "wof:placetype":"venue"
},
  "geometry": {"coordinates":[-118.532518,34.213909],"type":"Point"}
}