{
  "type": "Feature",
  "properties": {
    "iso:country":"US",
    "sg:address":"5200 W Sunset Blvd",
    "sg:city":"Los Angeles",
    "sg:classifiers":[
        {
            "category":"Travel",
            "subcategory":"Hotels & Motels",
            "type":"Entertainment"
        }
    ],
    "sg:phone":"+1 323 666 0692",
    "sg:postcode":"90027",
    "sg:province":"CA",
    "wof:name":"Value Inn",
    "wof:placetype":"venue"
},
  "geometry": {"coordinates":[-118.303001,34.098202],"type":"Point"}
}