{
  "type": "Feature",
  "properties": {
    "addr:full":"7590 Fay Ave La Jolla CA 92037",
    "addr:housenumber":"7590",
    "addr:postcode":"92037",
    "addr:street":"Fay Ave",
    "iso:country":"US",
    "sg:address":"7590 Fay Ave",
    "sg:city":"La Jolla",
    "sg:classifiers":[
        {
            "category":"Professional",
            "subcategory":"Management & Consulting",
            "type":"Services"
        }
    ],
    "sg:phone":"+1 858 456 2249",
    "sg:postcode":"92037",
    "sg:province":"CA",
    "sg:tags":[
        "consultant"
    ],
    "wof:name":"Autism Spectrum Consultants",
    "wof:placetype":"venue"
},
  "geometry": {"coordinates":[-117.274367,32.841872],"type":"Point"}
}