{
  "type": "Feature",
  "properties": {
    "iso:country":"US",
    "sg:address":"15 Florence Ave",
    "sg:city":"Watsonville",
    "sg:classifiers":[
        {
            "category":"Farming",
            "subcategory":"Berry Farm",
            "type":"Manufacturing & Wholesale Goods"
        }
    ],
    "sg:phone":"+1 831 728 5088",
    "sg:postcode":"95076",
    "sg:province":"CA",
    "sg:tags":[
        "crop"
    ],
    "wof:name":"Padilla Farms",
    "wof:placetype":"venue"
},
  "geometry": {"coordinates":[-121.75043,36.901451],"type":"Point"}
}