{
  "type": "Feature",
  "properties": {
    "addr:full":"17872 Portsmouth Cir Villa Park CA 92861",
    "addr:postcode":"17872;92861",
    "addr:street":"Portsmouth Cir",
    "iso:country":"US",
    "sg:address":"17872 Portsmouth Cir",
    "sg:city":"Villa Park",
    "sg:classifiers":[
        {
            "category":"Building & Trades",
            "subcategory":"Electrical",
            "type":"Services"
        }
    ],
    "sg:phone":"+1 714 633 8320",
    "sg:postcode":"92861",
    "sg:province":"CA",
    "sg:tags":[
        "electric",
        "contractor"
    ],
    "wof:name":"Belovsky Electric",
    "wof:placetype":"venue"
},
  "geometry": {"coordinates":[-117.82141799999999,33.803029],"type":"Point"}
}