{
  "type": "Feature",
  "properties": {
    "iso:country":"US",
    "sg:address":"525 11th Ave Ste 1509",
    "sg:city":"San Diego",
    "sg:classifiers":[
        {
            "category":"Banks & Credit Unions",
            "subcategory":"Financial Services",
            "type":"Services"
        },
        {
            "category":"Real Estate",
            "subcategory":"Real Estate Agent",
            "type":"Services"
        }
    ],
    "sg:phone":"+1 619 316 7044",
    "sg:postcode":"92101",
    "sg:province":"CA",
    "sg:tags":[
        "broker",
        "mortgage"
    ],
    "sg:website":"www.mysuperbmortgage.com",
    "wof:name":"Superb Mortgage and Real Estate",
    "wof:placetype":"venue"
},
  "geometry": {"coordinates":[-117.154196,32.710782],"type":"Point"}
}