{
  "type": "Feature",
  "properties": {
    "iso:country":"US",
    "sg:address":"735 N Grand Ave",
    "sg:city":"Santa Ana",
    "sg:classifiers":[
        {
            "category":"Personal",
            "type":"Services"
        }
    ],
    "sg:phone":"+1 714 390 7088",
    "sg:postcode":"92701",
    "sg:province":"CA",
    "sg:tags":[
        "bankruptcy"
    ],
    "wof:name":"Bankruptcy Center",
    "wof:placetype":"venue"
},
  "geometry": {"coordinates":[-117.85175700000001,33.750857],"type":"Point"}
}