{
  "type": "Feature",
  "properties": {
    "addr:full":"14158 Albers Way Chino CA 91710",
    "addr:housenumber":"14158",
    "addr:postcode":"91710",
    "addr:street":"Albers Way",
    "iso:country":"US",
    "sg:address":"14158 Albers Way",
    "sg:city":"Chino",
    "sg:classifiers":[
        {
            "category":"Building & Trades",
            "subcategory":"Electrical",
            "type":"Services"
        }
    ],
    "sg:phone":"+1 909 606 8555",
    "sg:postcode":"91710",
    "sg:province":"CA",
    "sg:tags":[
        "electrician"
    ],
    "wof:name":"Live Wire Electric",
    "wof:placetype":"venue"
},
  "geometry": {"coordinates":[-117.652719,33.996705],"type":"Point"}
}