{
  "type": "Feature",
  "properties": {
    "addr:full":"3255 16th St San Francisco CA 94103",
    "addr:housenumber":"3255",
    "addr:postcode":"94103",
    "addr:street":"16Th St",
    "iso:country":"US",
    "sg:address":"3255 16th St",
    "sg:city":"San Francisco",
    "sg:classifiers":[
        {
            "category":"Real Estate",
            "subcategory":"Real Estate Agent",
            "type":"Services"
        }
    ],
    "sg:phone":"+1 415 701 8001",
    "sg:postcode":"94103",
    "sg:province":"CA",
    "wof:name":"Randon Mc Kendrick Real Estate",
    "wof:placetype":"venue"
},
  "geometry": {"coordinates":[-122.4259,37.764608],"type":"Point"}
}