{
  "type": "Feature",
  "properties": {
    "iso:country":"US",
    "sg:address":"3208 E 14th St",
    "sg:city":"Oakland",
    "sg:classifiers":[
        {
            "category":"Manufacturing",
            "subcategory":"Apparel",
            "type":"Manufacturing & Wholesale Goods"
        },
        {
            "category":"Shopping",
            "subcategory":"Clothing, Apparel, & Fashions",
            "type":"Retail Goods"
        }
    ],
    "sg:phone":"+1 510 534 8177",
    "sg:postcode":"94601",
    "sg:province":"CA",
    "sg:tags":[
        "sewing",
        "contractor"
    ],
    "wof:name":"Castro's Designs",
    "wof:placetype":"venue"
},
  "geometry": {"coordinates":[-122.224571,37.777145],"type":"Point"}
}