{
  "type": "Feature",
  "properties": {
    "iso:country":"US",
    "sg:address":"10058 Joerschke Dr",
    "sg:city":"Grass Valley",
    "sg:classifiers":[
        {
            "category":"Health Services",
            "subcategory":"Optometrist",
            "type":"Services"
        }
    ],
    "sg:phone":"+1 530 273 5583",
    "sg:postcode":"95945",
    "sg:province":"CA",
    "wof:name":"Kevin D Woodburn OD",
    "wof:placetype":"venue"
},
  "geometry": {"coordinates":[-121.041776,39.234113],"type":"Point"}
}