{
  "type": "Feature",
  "properties": {
    "iso:country":"US",
    "sg:address":"19600 Fairchild Rd. #260",
    "sg:city":"Irvine",
    "sg:classifiers":[
        {
            "category":"Personal",
            "subcategory":"Beauty Salon",
            "type":"Services"
        }
    ],
    "sg:phone":"+1 949 336 7979",
    "sg:postcode":"92612",
    "sg:province":"CA",
    "sg:tags":[
        "hair"
    ],
    "sg:website":"www.enertialaser.com",
    "wof:name":"Enertia Laser",
    "wof:placetype":"venue"
},
  "geometry": {"coordinates":[-117.85898899999999,33.65737],"type":"Point"}
}