{
  "type": "Feature",
  "properties": {
    "addr:full":"15610 Firmona Ave Lawndale CA 90260",
    "addr:housenumber":"15610",
    "addr:postcode":"ca 90260",
    "addr:street":"Firmona Ave",
    "iso:country":"US",
    "sg:address":"15610 Firmona Ave",
    "sg:city":"Lawndale",
    "sg:classifiers":[
        {
            "category":"Professional",
            "subcategory":"Management & Consulting",
            "type":"Services"
        }
    ],
    "sg:phone":"+1 310 675 7600",
    "sg:postcode":"90260",
    "sg:province":"CA",
    "sg:tags":[
        "consultant",
        "construction"
    ],
    "wof:name":"Firmona Villas Homeowners",
    "wof:placetype":"venue"
},
  "geometry": {"coordinates":[-118.35757700000001,33.889035],"type":"Point"}
}