{
  "type": "Feature",
  "properties": {
    "addr:full":"353 E 17th Street Costa Mesa CA 92627",
    "addr:housenumber":"353",
    "addr:postcode":"92627",
    "addr:street":"E 17Th Street",
    "iso:country":"US",
    "sg:address":"353 E 17th Street",
    "sg:city":"Costa Mesa",
    "sg:classifiers":[
        {
            "category":"Bakery",
            "type":"Food & Drink"
        }
    ],
    "sg:phone":"+1 949 642 0822",
    "sg:postcode":"92627",
    "sg:province":"CA",
    "wof:name":"Marie Callender's Restaurants & Bakeries",
    "wof:placetype":"venue"
},
  "geometry": {"coordinates":[-117.913685,33.632099],"type":"Point"}
}