{
  "type": "Feature",
  "properties": {
    "addr:full":"405 South St Redding CA 96001",
    "addr:housenumber":"405",
    "addr:postcode":"96001",
    "addr:street":"South St",
    "iso:country":"US",
    "sg:address":"405 South St",
    "sg:city":"Redding",
    "sg:classifiers":[
        {
            "category":"Health Services",
            "subcategory":"Doctor",
            "type":"Services"
        }
    ],
    "sg:phone":"+1 530 246 0801",
    "sg:postcode":"96001",
    "sg:province":"CA",
    "sg:tags":[
        "dentist"
    ],
    "wof:name":"David R Pugh DDS",
    "wof:placetype":"venue"
},
  "geometry": {"coordinates":[-122.375384,40.578414],"type":"Point"}
}