{
  "type": "Feature",
  "properties": {
    "addr:full":"10356 Truckee Airport Rd Truckee CA 96161",
    "addr:housenumber":"10356",
    "addr:postcode":"96161",
    "addr:street":"Truckee Airport Rd",
    "iso:country":"US",
    "sg:address":"10356 Truckee Airport Rd",
    "sg:city":"Truckee",
    "sg:classifiers":[
        {
            "category":"Airport",
            "type":"Transportation"
        }
    ],
    "sg:phone":"+1 530 587 4119",
    "sg:postcode":"96161",
    "sg:province":"CA",
    "sg:website":"www.truckeetahoeairport.com",
    "wof:name":"Truckee Tahoe Airport",
    "wof:placetype":"venue"
},
  "geometry": {"coordinates":[-120.13603000000001,39.35223],"type":"Point"}
}