{
  "type": "Feature",
  "properties": {
    "addr:full":"1124 Main Street Irvine CA 92614",
    "addr:housenumber":"1124",
    "addr:postcode":"92614",
    "addr:street":"Main Street",
    "iso:country":"US",
    "sg:address":"1124 Main Street",
    "sg:city":"Irvine",
    "sg:classifiers":[
        {
            "category":"Building & Trades",
            "subcategory":"Construction",
            "type":"Services"
        }
    ],
    "sg:phone":"+1 949 724 1800",
    "sg:postcode":"92614",
    "sg:province":"CA",
    "sg:tags":[
        "contractor"
    ],
    "wof:name":"Beardall Associates",
    "wof:placetype":"venue"
},
  "geometry": {"coordinates":[-117.866867,33.69093],"type":"Point"}
}