{
  "type": "Feature",
  "properties": {
    "addr:full":"1480 Emory St San Jose CA 95126",
    "addr:housenumber":"1480",
    "addr:postcode":"95126",
    "addr:street":"Emory St",
    "iso:country":"US",
    "sg:address":"1480 Emory St",
    "sg:city":"San Jose",
    "sg:classifiers":[
        {
            "category":"Building & Trades",
            "subcategory":"Cleaning & Sanitation",
            "type":"Services"
        }
    ],
    "sg:phone":"+1 408 595 4371",
    "sg:postcode":"95126",
    "sg:province":"CA",
    "sg:tags":[
        "window"
    ],
    "wof:name":"Quality Window Cleaning & Sls",
    "wof:placetype":"venue"
},
  "geometry": {"coordinates":[-121.927387,37.333998],"type":"Point"}
}