{
  "type": "Feature",
  "properties": {
    "addr:full":"9990 el Camino Real Atascadero CA 93422",
    "addr:housenumber":"9990",
    "addr:postcode":"93422",
    "addr:street":"El Camino Real",
    "iso:country":"US",
    "sg:address":"9990 el Camino Real",
    "sg:city":"Atascadero",
    "sg:classifiers":[
        {
            "category":"Restaurant",
            "type":"Food & Drink"
        }
    ],
    "sg:phone":"+1 805 461 1110",
    "sg:postcode":"93422",
    "sg:province":"CA",
    "sg:tags":[
        "delicatessen"
    ],
    "wof:name":"Chalk Mountain Liquor & Deli",
    "wof:placetype":"venue"
},
  "geometry": {"coordinates":[-120.64666200000001,35.463518],"type":"Point"}
}