{
  "type": "Feature",
  "properties": {
    "addr:full":"13625 Gramercy Pl Gardena CA 90249",
    "addr:housenumber":"13625",
    "addr:postcode":"90249",
    "addr:street":"Gramercy Pl",
    "iso:country":"US",
    "sg:address":"13625 Gramercy Pl",
    "sg:city":"Gardena",
    "sg:classifiers":[
        {
            "category":"Wholesale",
            "subcategory":"Non-durable Goods",
            "type":"Manufacturing & Wholesale Goods"
        }
    ],
    "sg:phone":"+1 310 217 1686",
    "sg:postcode":"90249",
    "sg:province":"CA",
    "sg:tags":[
        "tropical",
        "water",
        "fish",
        "salt"
    ],
    "wof:name":"Marine Aquarium Warehouse",
    "wof:placetype":"venue"
},
  "geometry": {"coordinates":[-118.31349899999999,33.908054],"type":"Point"}
}