{
  "type": "Feature",
  "properties": {
    "addr:full":"568 S Franklin St Fort Bragg CA 95437",
    "addr:housenumber":"568",
    "addr:postcode":"95437",
    "addr:street":"S Franklin St",
    "iso:country":"US",
    "sg:address":"568 S Franklin St",
    "sg:city":"Fort Bragg",
    "sg:classifiers":[
        {
            "category":"Home & Garden",
            "subcategory":"Building Materials",
            "type":"Retail Goods"
        },
        {
            "category":"Manufacturing",
            "subcategory":"Glass & Minerals",
            "type":"Manufacturing & Wholesale Goods"
        }
    ],
    "sg:phone":"+1 707 964 6751",
    "sg:postcode":"95437",
    "sg:province":"CA",
    "sg:tags":[
        "product",
        "leaded",
        "mfg"
    ],
    "wof:name":"Fagerskogs Stained Glass",
    "wof:placetype":"venue"
},
  "geometry": {"coordinates":[-123.80454,39.435063],"type":"Point"}
}