{
  "type": "Feature",
  "properties": {
    "addr:full":"2504 Rigdon St Napa CA 94558",
    "addr:housenumber":"2504",
    "addr:postcode":"94558",
    "addr:street":"Rigdon St",
    "iso:country":"US",
    "sg:address":"2504 Rigdon St",
    "sg:city":"Napa",
    "sg:classifiers":[
        {
            "category":"Building & Trades",
            "subcategory":"Cleaning & Sanitation",
            "type":"Services"
        }
    ],
    "sg:phone":"+1 707 252 7102",
    "sg:postcode":"94558",
    "sg:province":"CA",
    "sg:tags":[
        "fireplace",
        "chimney"
    ],
    "wof:name":"Top Hat Chimney Sweep",
    "wof:placetype":"venue"
},
  "geometry": {"coordinates":[-122.328012,38.322041],"type":"Point"}
}