{
  "type": "Feature",
  "properties": {
    "addr:full":"192 S Murphy Ave Sunnyvale CA 94086",
    "addr:housenumber":"192",
    "addr:postcode":"94086",
    "addr:street":"S Murphy Ave",
    "iso:country":"US",
    "sg:address":"192 S Murphy Ave",
    "sg:city":"Sunnyvale",
    "sg:classifiers":[
        {
            "category":"Manufacturing",
            "subcategory":"Printing",
            "type":"Manufacturing & Wholesale Goods"
        }
    ],
    "sg:phone":"+1 408 617 1884",
    "sg:postcode":"94086",
    "sg:province":"CA",
    "sg:tags":[
        "publisher",
        "software"
    ],
    "wof:name":"Mental Models Inc",
    "wof:placetype":"venue"
},
  "geometry": {"coordinates":[-122.029816,37.377482],"type":"Point"}
}