{
  "type": "Feature",
  "properties": {
    "addr:full":"918 W Avenue J Lancaster CA 93534",
    "addr:housenumber":"918",
    "addr:postcode":"93534",
    "addr:street":"W Avenue J",
    "iso:country":"US",
    "sg:address":"918 W Avenue J",
    "sg:city":"Lancaster",
    "sg:classifiers":[
        {
            "category":"Social Services",
            "subcategory":"Child Care",
            "type":"Services"
        },
        {
            "category":"Education",
            "subcategory":"Preschool",
            "type":"Public Place"
        }
    ],
    "sg:phone":"+1 661 942 0812",
    "sg:postcode":"93534",
    "sg:province":"CA",
    "sg:tags":[
        "kindergarten"
    ],
    "sg:website":"http://www.lumcfccc.com",
    "wof:name":"Footprints Christian Children Center",
    "wof:placetype":"venue"
},
  "geometry": {"coordinates":[-118.14620600000001,34.689449],"type":"Point"}
}