{
  "type": "Feature",
  "properties": {
    "iso:country":"US",
    "sg:address":"2008 McGaw Avenue",
    "sg:city":"Irvine",
    "sg:classifiers":[
        {
            "category":"Shopping",
            "subcategory":"Mobile Phones",
            "type":"Retail Goods"
        }
    ],
    "sg:phone":"+1 949 567 6800",
    "sg:postcode":"92614",
    "sg:province":"CA",
    "wof:name":"Voicestream Wireless",
    "wof:placetype":"venue"
},
  "geometry": {"coordinates":[-117.84453600000001,33.692331],"type":"Point"}
}