{
  "type": "Feature",
  "properties": {
    "iso:country":"US",
    "sg:address":"1951 Fremont Blvd",
    "sg:city":"Seaside",
    "sg:classifiers":[
        {
            "category":"Utilities",
            "subcategory":"Mobile Phone",
            "type":"Services"
        }
    ],
    "sg:phone":"+1 831 583 9430",
    "sg:postcode":"93955",
    "sg:province":"CA",
    "sg:tags":[
        "telephone",
        "cellular"
    ],
    "wof:name":"Nextel Retail",
    "wof:placetype":"venue"
},
  "geometry": {"coordinates":[-121.84056200000001,36.619313],"type":"Point"}
}