{
  "type": "Feature",
  "properties": {
    "iso:country":"US",
    "sg:address":"699 W Line St",
    "sg:city":"Bishop",
    "sg:classifiers":[
        {
            "category":"Building & Trades",
            "subcategory":"Construction",
            "type":"Services"
        }
    ],
    "sg:phone":"+1 760 873 1076",
    "sg:postcode":"93514",
    "sg:province":"CA",
    "sg:tags":[
        "contractor"
    ],
    "wof:name":"K & H Smith",
    "wof:placetype":"venue"
},
  "geometry": {"coordinates":[-118.40014,37.36141],"type":"Point"}
}