{
  "type": "Feature",
  "properties": {
    "addr:full":"5012 Central Ave Bonita CA 91902",
    "addr:housenumber":"5012",
    "addr:postcode":"91902",
    "addr:street":"Central Ave",
    "iso:country":"US",
    "sg:address":"5012 Central Ave",
    "sg:city":"Bonita",
    "sg:classifiers":[
        {
            "category":"Real Estate",
            "subcategory":"Real Estate Agent",
            "type":"Services"
        }
    ],
    "sg:phone":"+1 619 472 6900",
    "sg:postcode":"91902",
    "sg:province":"CA",
    "wof:name":"Southwest Realtors",
    "wof:placetype":"venue"
},
  "geometry": {"coordinates":[-117.023053,32.668597],"type":"Point"}
}