{
  "type": "Feature",
  "properties": {
    "iso:country":"US",
    "sg:address":"330 Main St",
    "sg:city":"Pismo Beach",
    "sg:classifiers":[
        {
            "category":"Real Estate",
            "subcategory":"Real Estate Agent",
            "type":"Services"
        }
    ],
    "sg:phone":"+1 805 773 9585",
    "sg:postcode":"93449",
    "sg:province":"CA",
    "wof:name":"Ocean West Properties",
    "wof:placetype":"venue"
},
  "geometry": {"coordinates":[-120.64094799999999,35.141922],"type":"Point"}
}