{
  "type": "Feature",
  "properties": {
    "addr:full":"950 Fulton Avenue Sacramento CA 95825",
    "addr:housenumber":"950",
    "addr:postcode":"95825",
    "addr:street":"Fulton Avenue",
    "iso:country":"US",
    "sg:address":"950 Fulton Avenue",
    "sg:city":"Sacramento",
    "sg:classifiers":[
        {
            "category":"Health Services",
            "subcategory":"Health Practitioner",
            "type":"Services"
        }
    ],
    "sg:phone":"+1 916 483 2686",
    "sg:postcode":"95825",
    "sg:province":"CA",
    "sg:tags":[
        "acupuncture"
    ],
    "sg:website":"www.biogrip.com",
    "wof:name":"Biogrip",
    "wof:placetype":"venue"
},
  "geometry": {"coordinates":[-121.401443,38.581525],"type":"Point"}
}