{
  "type": "Feature",
  "properties": {
    "iso:country":"US",
    "sg:address":"1666 Garnet Ave",
    "sg:city":"San Diego",
    "sg:classifiers":[
        {
            "category":"Professional",
            "subcategory":"Accounting & Tax Preparation",
            "type":"Services"
        }
    ],
    "sg:phone":"+1 619 285 1828",
    "sg:postcode":"92109",
    "sg:province":"CA",
    "sg:tags":[
        "bookkeeping",
        "general"
    ],
    "wof:name":"KEC Svc",
    "wof:placetype":"venue"
},
  "geometry": {"coordinates":[-117.24012399999999,32.799997],"type":"Point"}
}