{
  "type": "Feature",
  "properties": {
    "addr:full":"5523 Mission Rd Bonsall CA 92003",
    "addr:housenumber":"5523",
    "addr:postcode":"92003",
    "addr:street":"Mission Rd",
    "iso:country":"US",
    "sg:address":"5523 Mission Rd",
    "sg:city":"Bonsall",
    "sg:classifiers":[
        {
            "category":"Health Services",
            "subcategory":"Chiropractor",
            "type":"Services"
        }
    ],
    "sg:phone":"+1 760 724 8104",
    "sg:postcode":"92003",
    "sg:province":"CA",
    "sg:tags":[
        "chiropractic"
    ],
    "sg:website":"http://www.tru-healthtravel.com",
    "wof:name":"Tru-Health Chiropractic",
    "wof:placetype":"venue"
},
  "geometry": {"coordinates":[-117.225644,33.29119],"type":"Point"}
}