{
  "type": "Feature",
  "properties": {
    "addr:full":"10708 Jefferson Blvd Culver City CA 90230",
    "addr:housenumber":"10708",
    "addr:postcode":"90230",
    "addr:street":"Jefferson Blvd",
    "iso:country":"US",
    "sg:address":"10708 Jefferson Blvd",
    "sg:city":"Culver City",
    "sg:classifiers":[
        {
            "category":"Restaurant",
            "type":"Food & Drink"
        }
    ],
    "sg:phone":"+1 310 839 2841",
    "sg:postcode":"90230",
    "sg:province":"CA",
    "sg:tags":[
        "pakistani",
        "indian"
    ],
    "sg:website":"www.shalimarcuisineofindia.com",
    "wof:name":"Shalimar Cuisine of India",
    "wof:placetype":"venue"
},
  "geometry": {"coordinates":[-118.393997,34.0037],"type":"Point"}
}