{
  "type": "Feature",
  "properties": {
    "iso:country":"US",
    "sg:address":"203 Teloma Dr",
    "sg:city":"Ventura",
    "sg:classifiers":[
        {
            "category":"Shopping",
            "type":"Retail Goods"
        }
    ],
    "sg:phone":"+1 805 658 2455",
    "sg:postcode":"93003",
    "sg:province":"CA",
    "sg:tags":[
        "material",
        "artist",
        "supply"
    ],
    "wof:name":"21st Century Hieroglyphics",
    "wof:placetype":"venue"
},
  "geometry": {"coordinates":[-119.224957,34.28258],"type":"Point"}
}