{
  "type": "Feature",
  "properties": {
    "addr:full":"1350 N Harding Ave Unit D Pasadena CA 91104",
    "addr:housenumber":"1350",
    "addr:postcode":"91104",
    "addr:street":"N Harding Ave Unit D",
    "iso:country":"US",
    "sg:address":"1350 N Harding Ave Unit D",
    "sg:city":"Pasadena",
    "sg:classifiers":[
        {
            "category":"Personal",
            "type":"Services"
        }
    ],
    "sg:phone":"+1 310 880 9940",
    "sg:postcode":"91104",
    "sg:province":"CA",
    "sg:tags":[
        "towing"
    ],
    "wof:name":"West Trans Hauler",
    "wof:placetype":"venue"
},
  "geometry": {"coordinates":[-118.101708,34.169819],"type":"Point"}
}