{
  "type": "Feature",
  "properties": {
    "addr:full":"9838 Cow Creek Dr Palo Cedro CA 96073",
    "addr:housenumber":"9838",
    "addr:postcode":"96073",
    "addr:street":"Cow Creek Dr",
    "iso:country":"US",
    "sg:address":"9838 Cow Creek Dr",
    "sg:city":"Palo Cedro",
    "sg:classifiers":[
        {
            "category":"Building & Trades",
            "subcategory":"Landscaping Services",
            "type":"Services"
        }
    ],
    "sg:phone":"+1 530 246 5685",
    "sg:postcode":"96073",
    "sg:province":"CA",
    "sg:tags":[
        "landscape"
    ],
    "wof:name":"Eagle Landscape",
    "wof:placetype":"venue"
},
  "geometry": {"coordinates":[-122.223859,40.571535],"type":"Point"}
}