{
  "type": "Feature",
  "properties": {
    "addr:full":"61 Vista Ln Alamo CA 94507",
    "addr:housenumber":"61",
    "addr:postcode":"94507",
    "addr:street":"Vista Ln",
    "iso:country":"US",
    "sg:address":"61 Vista Ln",
    "sg:city":"Alamo",
    "sg:classifiers":[
        {
            "category":"Building & Trades",
            "subcategory":"Electrical",
            "type":"Services"
        }
    ],
    "sg:phone":"+1 925 938 3190",
    "sg:postcode":"94507",
    "sg:province":"CA",
    "sg:tags":[
        "electrician"
    ],
    "wof:name":"Rolly L White Inc",
    "wof:placetype":"venue"
},
  "geometry": {"coordinates":[-122.048722,37.87],"type":"Point"}
}