{
  "type": "Feature",
  "properties": {
    "addr:full":"90 Bonaventura Dr San Jose CA 95134",
    "addr:housenumber":"90",
    "addr:postcode":"95134",
    "addr:street":"Bonaventura Dr",
    "iso:country":"US",
    "sg:address":"90 Bonaventura Dr",
    "sg:city":"San Jose",
    "sg:classifiers":[
        {
            "category":"Wholesale",
            "subcategory":"Computers",
            "type":"Manufacturing & Wholesale Goods"
        }
    ],
    "sg:phone":"+1 408 435 7868",
    "sg:postcode":"95134",
    "sg:province":"CA",
    "wof:name":"Urchoice Electronics",
    "wof:placetype":"venue"
},
  "geometry": {"coordinates":[-121.92800099999999,37.389099],"type":"Point"}
}