{
  "type": "Feature",
  "properties": {
    "iso:country":"US",
    "sg:address":"23430 Hawthorne Blvd. Building 3 Suite 280",
    "sg:city":"Torrance",
    "sg:classifiers":[
        {
            "category":"Health Services",
            "subcategory":"Health Practitioner",
            "type":"Services"
        }
    ],
    "sg:phone":"+1 310 570 9723",
    "sg:postcode":"90505",
    "sg:province":"CA",
    "sg:tags":[
        "acupuncture"
    ],
    "sg:website":"www.holisticlac.com/",
    "wof:name":"Holistic Alternatives Acupuncture",
    "wof:placetype":"venue"
},
  "geometry": {"coordinates":[-118.349487,33.813159],"type":"Point"}
}