{
  "type": "Feature",
  "properties": {
    "iso:country":"US",
    "sg:address":"705 Westmount Dr",
    "sg:city":"West Hollywood",
    "sg:classifiers":[
        {
            "category":"Autos & Motor Vehicles",
            "subcategory":"Automobile Sales",
            "type":"Retail Goods"
        },
        {
            "category":"Airline",
            "type":"Transportation"
        }
    ],
    "sg:phone":"+1 323 654 8669",
    "sg:postcode":"90069",
    "sg:province":"CA",
    "sg:tags":[
        "shuttle",
        "airport",
        "limo"
    ],
    "sg:website":"www.westhollywoodlimousine.com",
    "wof:name":"Monaco Limousine/West Hollywood Limousine",
    "wof:placetype":"venue"
},
  "geometry": {"coordinates":[-118.37893800000001,34.083736],"type":"Point"}
}