{
  "type": "Feature",
  "properties": {
    "addr:full":"13381 Epping Way Tustin CA 92780",
    "addr:housenumber":"13381",
    "addr:postcode":"92780",
    "addr:street":"Epping Way",
    "iso:country":"US",
    "sg:address":"13381 Epping Way",
    "sg:city":"Tustin",
    "sg:classifiers":[
        {
            "category":"Building & Trades",
            "subcategory":"Construction",
            "type":"Services"
        }
    ],
    "sg:phone":"+1 714 832 9149",
    "sg:postcode":"92780",
    "sg:province":"CA",
    "sg:tags":[
        "house"
    ],
    "wof:name":"D S Wagner Construction Inc",
    "wof:placetype":"venue"
},
  "geometry": {"coordinates":[-117.808943,33.739311],"type":"Point"}
}