{
  "type": "Feature",
  "properties": {
    "iso:country":"US",
    "sg:address":"2126 Courtland Ave",
    "sg:city":"San Marino",
    "sg:classifiers":[
        {
            "category":"Banks & Credit Unions",
            "subcategory":"Financial Services",
            "type":"Services"
        }
    ],
    "sg:phone":"+1 626 799 4444",
    "sg:postcode":"91108",
    "sg:province":"CA",
    "sg:tags":[
        "trust",
        "investment",
        "real estate"
    ],
    "wof:name":"Huh Partners LP",
    "wof:placetype":"venue"
},
  "geometry": {"coordinates":[-118.12796,34.115675],"type":"Point"}
}