{
  "type": "Feature",
  "properties": {
    "addr:full":"14 W Wabash Ave Eureka CA 95501",
    "addr:housenumber":"14",
    "addr:postcode":"95501",
    "addr:street":"W Wabash Ave",
    "iso:country":"US",
    "sg:address":"14 W Wabash Ave",
    "sg:city":"Eureka",
    "sg:classifiers":[
        {
            "category":"Professional",
            "subcategory":"Employment Agencies",
            "type":"Services"
        }
    ],
    "sg:phone":"+1 707 268 1866",
    "sg:postcode":"95501",
    "sg:province":"CA",
    "sg:tags":[
        "opportunity"
    ],
    "sg:website":"www.mc-staffing.com",
    "wof:name":"Express Personnel Svc",
    "wof:placetype":"venue"
},
  "geometry": {"coordinates":[-124.17121,40.791546],"type":"Point"}
}