{
  "type": "Feature",
  "properties": {
    "iso:country":"US",
    "sg:address":"201 Spear St Ste 100",
    "sg:city":"San Francisco",
    "sg:classifiers":[
        {
            "category":"Coffee & Tea",
            "type":"Food & Drink"
        }
    ],
    "sg:phone":"+1 415 974 5077",
    "sg:postcode":"94150",
    "sg:province":"CA",
    "sg:website":"www.starbucks.com",
    "wof:name":"Starbucks",
    "wof:placetype":"venue"
},
  "geometry": {"coordinates":[-122.391791,37.791185],"type":"Point"}
}