{
  "type": "Feature",
  "properties": {
    "addr:full":"119 Marion Trl Chester CA 96020",
    "addr:housenumber":"119",
    "addr:postcode":"96020",
    "addr:street":"Marion Trl",
    "iso:country":"US",
    "sg:address":"119 Marion Trl",
    "sg:city":"Chester",
    "sg:classifiers":[
        {
            "category":"Shopping",
            "subcategory":"Gifts & Souvenirs",
            "type":"Retail Goods"
        }
    ],
    "sg:phone":"+1 530 258 2121",
    "sg:postcode":"96020",
    "sg:province":"CA",
    "sg:tags":[
        "shop"
    ],
    "wof:name":"Brittney's Gifts",
    "wof:placetype":"venue"
},
  "geometry": {"coordinates":[-121.21536999999999,40.24295],"type":"Point"}
}