{
  "type": "Feature",
  "properties": {
    "iso:country":"US",
    "sg:address":"32111 Shadow Mountain Ln",
    "sg:city":"Thousand Palms",
    "sg:classifiers":[
        {
            "category":"Farming",
            "subcategory":"Nursery",
            "type":"Manufacturing & Wholesale Goods"
        }
    ],
    "sg:phone":"+1 760 835 2662",
    "sg:postcode":"92276",
    "sg:province":"CA",
    "sg:tags":[
        "ornamental"
    ],
    "wof:name":"C & M Growers",
    "wof:placetype":"venue"
},
  "geometry": {"coordinates":[-116.34391599999999,33.816276],"type":"Point"}
}