{
  "type": "Feature",
  "properties": {
    "iso:country":"US",
    "sg:address":"1402 Miss Elle Way",
    "sg:city":"Alpine",
    "sg:classifiers":[
        {
            "category":"Home & Garden",
            "subcategory":"Hardware",
            "type":"Retail Goods"
        }
    ],
    "sg:phone":"+1 619 659 9384",
    "sg:postcode":"91901",
    "sg:province":"CA",
    "wof:name":"Snap-On Tools",
    "wof:placetype":"venue"
},
  "geometry": {"coordinates":[-116.760413,32.831604],"type":"Point"}
}