{
  "type": "Feature",
  "properties": {
    "iso:country":"US",
    "sg:address":"24051 John F Kennedy Dr",
    "sg:city":"Moreno Valley",
    "sg:classifiers":[
        {
            "category":"Food & Beverages",
            "subcategory":"Groceries & Convenience Stores",
            "type":"Retail Goods"
        }
    ],
    "sg:phone":"+1 951 247 5582",
    "sg:postcode":"92551",
    "sg:province":"CA",
    "wof:name":"Circle K",
    "wof:placetype":"venue"
},
  "geometry": {"coordinates":[-117.243573,33.902774],"type":"Point"}
}