{
  "type": "Feature",
  "properties": {
    "iso:country":"US",
    "sg:address":"1516 Pomona St",
    "sg:city":"Crockett",
    "sg:classifiers":[
        {
            "category":"Shopping",
            "subcategory":"Gifts & Souvenirs",
            "type":"Retail Goods"
        }
    ],
    "sg:phone":"+1 510 787 1609",
    "sg:postcode":"94525",
    "sg:province":"CA",
    "wof:name":"Balloon Odyssey",
    "wof:placetype":"venue"
},
  "geometry": {"coordinates":[-122.225274,38.05249],"type":"Point"}
}