{
  "type": "Feature",
  "properties": {
    "iso:country":"US",
    "sg:address":"8706 Delta St",
    "sg:city":"La Mesa",
    "sg:classifiers":[
        {
            "category":"Home & Garden",
            "subcategory":"Home Furnishings",
            "type":"Retail Goods"
        }
    ],
    "sg:phone":"+1 619 464 0541",
    "sg:postcode":"91942",
    "sg:province":"CA",
    "wof:name":"Interiors Unlimited",
    "wof:placetype":"venue"
},
  "geometry": {"coordinates":[-117.009015,32.78564],"type":"Point"}
}