{
  "type": "Feature",
  "properties": {
    "iso:country":"US",
    "sg:address":"5461 Holt Blvd",
    "sg:city":"Montclair",
    "sg:classifiers":[
        {
            "category":"Insurance",
            "subcategory":"Insurance Agent",
            "type":"Services"
        }
    ],
    "sg:phone":"+1 909 621 0133",
    "sg:postcode":"91763",
    "sg:province":"CA",
    "wof:name":"Aries Insurance",
    "wof:placetype":"venue"
},
  "geometry": {"coordinates":[-117.68657,34.063183],"type":"Point"}
}