{
  "type": "Feature",
  "properties": {
    "iso:country":"US",
    "sg:address":"3070 Bay Vista Ct",
    "sg:city":"Benicia",
    "sg:classifiers":[
        {
            "category":"Wholesale",
            "subcategory":"Auto Parts",
            "type":"Manufacturing & Wholesale Goods"
        }
    ],
    "sg:phone":"+1 707 751 0942",
    "sg:postcode":"94510",
    "sg:province":"CA",
    "sg:tags":[
        "automobile",
        "supply"
    ],
    "wof:name":"Goldgate International",
    "wof:placetype":"venue"
},
  "geometry": {"coordinates":[-122.132209,38.061832],"type":"Point"}
}