{
  "type": "Feature",
  "properties": {
    "addr:full":"26582 Shane Dr Lake Forest CA 92630",
    "addr:housenumber":"26582",
    "addr:postcode":"92630",
    "addr:street":"Shane Dr",
    "iso:country":"US",
    "sg:address":"26582 Shane Dr",
    "sg:city":"Lake Forest",
    "sg:classifiers":[
        {
            "category":"Building & Trades",
            "subcategory":"Construction",
            "type":"Services"
        }
    ],
    "sg:phone":"+1 949 581 5327",
    "sg:postcode":"92630",
    "sg:province":"CA",
    "sg:tags":[
        "contractor"
    ],
    "wof:name":"Faithco Building Corp",
    "wof:placetype":"venue"
},
  "geometry": {"coordinates":[-117.666989,33.641985],"type":"Point"}
}