{
  "type": "Feature",
  "properties": {
    "addr:full":"5853 Whittier Blvd Los Angeles CA 90022",
    "addr:housenumber":"5853",
    "addr:postcode":"90022",
    "addr:street":"Whittier Blvd",
    "iso:country":"US",
    "sg:address":"5853 Whittier Blvd",
    "sg:city":"Los Angeles",
    "sg:classifiers":[
        {
            "category":"Wholesale",
            "subcategory":"Hardware",
            "type":"Manufacturing & Wholesale Goods"
        }
    ],
    "sg:phone":"+1 323 888 6639",
    "sg:postcode":"90022",
    "sg:province":"CA",
    "sg:tags":[
        "tool"
    ],
    "wof:name":"World Trading USA",
    "wof:placetype":"venue"
},
  "geometry": {"coordinates":[-118.144419,34.017779],"type":"Point"}
}