{
  "type": "Feature",
  "properties": {
    "addr:full":"1563 Jayken Way Chula Vista CA 91911",
    "addr:housenumber":"1563",
    "addr:postcode":"91911",
    "addr:street":"Jayken Way",
    "iso:country":"US",
    "sg:address":"1563 Jayken Way",
    "sg:city":"Chula Vista",
    "sg:classifiers":[
        {
            "category":"Professional",
            "subcategory":"Accounting & Tax Preparation",
            "type":"Services"
        }
    ],
    "sg:phone":"+1 619 691 1313",
    "sg:postcode":"91911",
    "sg:province":"CA",
    "sg:tags":[
        "return",
        "filing"
    ],
    "wof:name":"Solorio's Tax Svc",
    "wof:placetype":"venue"
},
  "geometry": {"coordinates":[-117.081249,32.6004],"type":"Point"}
}