{
  "type": "Feature",
  "properties": {
    "iso:country":"US",
    "sg:address":"9150 Alcosta Blvd",
    "sg:city":"San Ramon",
    "sg:classifiers":[
        {
            "category":"Personal",
            "type":"Services"
        }
    ],
    "sg:phone":"+1 925 560 9690",
    "sg:postcode":"94583",
    "sg:province":"CA",
    "wof:name":"Tropical Solution Inc",
    "wof:placetype":"venue"
},
  "geometry": {"coordinates":[-121.931703,37.729459],"type":"Point"}
}