{
  "type": "Feature",
  "properties": {
    "iso:country":"US",
    "sg:address":"4 Park Plaza",
    "sg:city":"Irvine",
    "sg:classifiers":[
        {
            "category":"Professional",
            "subcategory":"Lawyer & Legal Services",
            "type":"Services"
        }
    ],
    "sg:phone":"+1 949 955 5555",
    "sg:postcode":"92614",
    "sg:province":"CA",
    "wof:name":"Wehrer Susan K Paparelli & Partners Llp",
    "wof:placetype":"venue"
},
  "geometry": {"coordinates":[-117.83848399999999,33.678664],"type":"Point"}
}