{
  "type": "Feature",
  "properties": {
    "iso:country":"US",
    "sg:address":"4049 Beckwith Rd",
    "sg:city":"Modesto",
    "sg:classifiers":[
        {
            "category":"Professional",
            "type":"Services"
        }
    ],
    "sg:phone":"+1 209 571 9860",
    "sg:postcode":"95358",
    "sg:province":"CA",
    "wof:name":"Raymond Dillard",
    "wof:placetype":"venue"
},
  "geometry": {"coordinates":[-121.076045,37.6818],"type":"Point"}
}