{
  "type": "Feature",
  "properties": {
    "iso:country":"US",
    "sg:address":"10725 Ellis Ave",
    "sg:city":"Fountain Valley",
    "sg:classifiers":[
        {
            "category":"Manufacturing",
            "subcategory":"Toys & Sporting Goods",
            "type":"Manufacturing & Wholesale Goods"
        }
    ],
    "sg:phone":"+1 714 963 3990",
    "sg:postcode":"92708",
    "sg:province":"CA",
    "sg:tags":[
        "mfg"
    ],
    "wof:name":"Worry Box Inc",
    "wof:placetype":"venue"
},
  "geometry": {"coordinates":[-117.93698000000001,33.69432],"type":"Point"}
}