{
  "type": "Feature",
  "properties": {
    "addr:full":"1955 Texas St Fairfield CA 94533",
    "addr:housenumber":"1955",
    "addr:postcode":"94533",
    "addr:street":"Texas St",
    "iso:country":"US",
    "sg:address":"1955 Texas St",
    "sg:city":"Fairfield",
    "sg:classifiers":[
        {
            "category":"Organizations",
            "subcategory":"Non-profit Organization",
            "type":"Services"
        }
    ],
    "sg:phone":"+1 707 426 6932",
    "sg:postcode":"94533",
    "sg:province":"CA",
    "sg:tags":[
        "disability"
    ],
    "wof:name":"PACE Winery Square",
    "wof:placetype":"venue"
},
  "geometry": {"coordinates":[-122.06296500000001,38.249376],"type":"Point"}
}