{
  "type": "Feature",
  "properties": {
    "iso:country":"US",
    "sg:address":"1043 Serpentine Ln",
    "sg:city":"Pleasanton",
    "sg:classifiers":[
        {
            "category":"Home & Garden",
            "subcategory":"Carpets & Floor Coverings",
            "type":"Retail Goods"
        }
    ],
    "sg:phone":"+1 925 829 0738",
    "sg:postcode":"94566",
    "sg:province":"CA",
    "sg:tags":[
        "dealer",
        "rug"
    ],
    "wof:name":"Floors By Leo",
    "wof:placetype":"venue"
},
  "geometry": {"coordinates":[-121.86757,37.671493],"type":"Point"}
}