{
  "type": "Feature",
  "properties": {
    "addr:full":"1122 Rainier Ave Pacifica CA 94044",
    "addr:housenumber":"1122",
    "addr:postcode":"94044",
    "addr:street":"Rainier Ave",
    "iso:country":"US",
    "sg:address":"1122 Rainier Ave",
    "sg:city":"Pacifica",
    "sg:classifiers":[
        {
            "category":"Building & Trades",
            "subcategory":"Construction",
            "type":"Services"
        }
    ],
    "sg:phone":"+1 650 359 0770",
    "sg:postcode":"94044",
    "sg:province":"CA",
    "sg:tags":[
        "tile-contractors"
    ],
    "wof:name":"Coastside Tile",
    "wof:placetype":"venue"
},
  "geometry": {"coordinates":[-122.46365400000001,37.591228],"type":"Point"}
}