{
  "type": "Feature",
  "properties": {
    "iso:country":"US",
    "sg:address":"2111 Pan American Plz",
    "sg:city":"San Diego",
    "sg:classifiers":[
        {
            "category":"Government",
            "subcategory":"Office",
            "type":"Public Place"
        }
    ],
    "sg:phone":"+1 619 525 8264",
    "sg:postcode":"92101",
    "sg:province":"CA",
    "sg:tags":[
        "village"
    ],
    "wof:name":"San Diego Municipal Gym",
    "wof:placetype":"venue"
},
  "geometry": {"coordinates":[-117.15278600000001,32.727387],"type":"Point"}
}