{
  "type": "Feature",
  "properties": {
    "iso:country":"US",
    "sg:address":"2700 Oswell St",
    "sg:city":"Bakersfield",
    "sg:classifiers":[
        {
            "category":"Autos & Motor Vehicles",
            "subcategory":"Fuel & Gas Station",
            "type":"Retail Goods"
        }
    ],
    "sg:phone":"+1 661 871 1200",
    "sg:postcode":"93306",
    "sg:province":"CA",
    "sg:tags":[
        "oil"
    ],
    "wof:name":"Steve Thorne Chevron",
    "wof:placetype":"venue"
},
  "geometry": {"coordinates":[-118.949813,35.39913],"type":"Point"}
}