{
  "type": "Feature",
  "properties": {
    "addr:full":"701 S Atlantic Blvd Monterey Park CA 91754",
    "addr:housenumber":"701",
    "addr:postcode":"91754",
    "addr:street":"S Atlantic Blvd",
    "iso:country":"US",
    "sg:address":"701 S Atlantic Blvd",
    "sg:city":"Monterey Park",
    "sg:classifiers":[
        {
            "category":"Wholesale",
            "subcategory":"Non-durable Goods",
            "type":"Manufacturing & Wholesale Goods"
        }
    ],
    "sg:phone":"+1 626 293 7124",
    "sg:postcode":"91754",
    "sg:province":"CA",
    "wof:name":"North American Consultants & M",
    "wof:placetype":"venue"
},
  "geometry": {"coordinates":[-118.136163,34.054049],"type":"Point"}
}