{
  "type": "Feature",
  "properties": {
    "addr:full":"7857 Girard Ave La Jolla CA 92037",
    "addr:housenumber":"7857",
    "addr:postcode":"92037",
    "addr:street":"Girard Ave",
    "iso:country":"US",
    "sg:address":"7857 Girard Ave",
    "sg:city":"La Jolla",
    "sg:classifiers":[
        {
            "category":"Food & Beverages",
            "subcategory":"Candy",
            "type":"Retail Goods"
        },
        {
            "category":"Restaurant",
            "type":"Food & Drink"
        }
    ],
    "sg:phone":"+1 858 459 2877",
    "sg:postcode":"92037",
    "sg:province":"CA",
    "sg:tags":[
        "dessert"
    ],
    "sg:website":"www.cupslj.com",
    "wof:name":"Cups",
    "wof:placetype":"venue"
},
  "geometry": {"coordinates":[-117.27394200000001,32.846214],"type":"Point"}
}