{
  "type": "Feature",
  "properties": {
    "iso:country":"US",
    "sg:address":"3293 Firth Way",
    "sg:city":"San Jose",
    "sg:classifiers":[
        {
            "category":"Real Estate",
            "subcategory":"Real Estate Operator",
            "type":"Services"
        }
    ],
    "sg:phone":"+1 408 274 1651",
    "sg:postcode":"95121",
    "sg:province":"CA",
    "sg:tags":[
        "property",
        "lessor"
    ],
    "wof:name":"Lewis & Sotcher",
    "wof:placetype":"venue"
},
  "geometry": {"coordinates":[-121.80889000000001,37.308004],"type":"Point"}
}