{
  "type": "Feature",
  "properties": {
    "iso:country":"US",
    "sg:address":"1698 S Lewis St",
    "sg:city":"Anaheim",
    "sg:classifiers":[
        {
            "category":"Food & Beverages",
            "subcategory":"Groceries & Convenience Stores",
            "type":"Retail Goods"
        }
    ],
    "sg:phone":"+1 714 634 8960",
    "sg:postcode":"92805",
    "sg:province":"CA",
    "wof:name":"Cornerstone Equipment",
    "wof:placetype":"venue"
},
  "geometry": {"coordinates":[-117.89773599999999,33.805717],"type":"Point"}
}