{
  "type": "Feature",
  "properties": {
    "iso:country":"US",
    "sg:address":"1223 Santee Street",
    "sg:city":"Los Angeles",
    "sg:classifiers":[
        {
            "category":"Shopping",
            "subcategory":"Clothing, Apparel, & Fashions",
            "type":"Retail Goods"
        }
    ],
    "sg:phone":"+1 213 741 0902",
    "sg:postcode":"90015",
    "sg:province":"CA",
    "sg:tags":[
        "accessory",
        "clothing",
        "women's"
    ],
    "wof:name":"A P Designs",
    "wof:placetype":"venue"
},
  "geometry": {"coordinates":[-118.257695,34.035652],"type":"Point"}
}