{
  "type": "Feature",
  "properties": {
    "iso:country":"US",
    "sg:address":"103 Locust Street",
    "sg:city":"Santa Cruz",
    "sg:classifiers":[
        {
            "category":"Arts & Performance",
            "subcategory":"Art Gallery",
            "type":"Entertainment"
        }
    ],
    "sg:phone":"+1 831 457 1177",
    "sg:postcode":"95060",
    "sg:province":"CA",
    "wof:name":"The Glass Gallery",
    "wof:placetype":"venue"
},
  "geometry": {"coordinates":[-122.026493,36.975223],"type":"Point"}
}