{
  "type": "Feature",
  "properties": {
    "addr:full":"725 6th St Paso Robles CA 93446",
    "addr:housenumber":"725",
    "addr:postcode":"93446",
    "addr:street":"6Th St",
    "iso:country":"US",
    "sg:address":"725 6th St",
    "sg:city":"Paso Robles",
    "sg:classifiers":[
        {
            "category":"Professional",
            "type":"Services"
        }
    ],
    "sg:phone":"+1 805 239 2964",
    "sg:postcode":"93446",
    "sg:province":"CA",
    "wof:name":"Nancy Mangan & Face Facts",
    "wof:placetype":"venue"
},
  "geometry": {"coordinates":[-120.689846,35.620558],"type":"Point"}
}