{
  "type": "Feature",
  "properties": {
    "addr:full":"4820 Forman Ave North Hollywood CA 91601",
    "addr:housenumber":"4820",
    "addr:postcode":"91601",
    "addr:street":"Forman Ave",
    "iso:country":"US",
    "sg:address":"4820 Forman Ave",
    "sg:city":"North Hollywood",
    "sg:classifiers":[
        {
            "category":"Professional",
            "type":"Services"
        }
    ],
    "sg:phone":"+1 818 766 1980",
    "sg:postcode":"91601",
    "sg:province":"CA",
    "sg:tags":[
        "caterer"
    ],
    "wof:name":"Under The",
    "wof:placetype":"venue"
},
  "geometry": {"coordinates":[-118.352682,34.158167],"type":"Point"}
}