{
  "type": "Feature",
  "properties": {
    "addr:full":"1919 Boeing Way Stockton CA 95206",
    "addr:housenumber":"1919",
    "addr:postcode":"95206",
    "addr:street":"Boeing Way",
    "iso:country":"US",
    "sg:address":"1919 Boeing Way",
    "sg:city":"Stockton",
    "sg:classifiers":[
        {
            "category":"Freight",
            "type":"Transportation"
        }
    ],
    "sg:phone":"+1 916 373 3333",
    "sg:postcode":"95206",
    "sg:province":"CA",
    "sg:tags":[
        "distribution",
        "center"
    ],
    "wof:name":"Raleys Hbc Distribution Center",
    "wof:placetype":"venue"
},
  "geometry": {"coordinates":[-121.247559,37.908339],"type":"Point"}
}