{
  "type": "Feature",
  "properties": {
    "addr:full":"1122 Westwood Blvd Los Angeles CA 90024",
    "addr:housenumber":"1122",
    "addr:postcode":"90024",
    "addr:street":"Westwood Blvd",
    "iso:country":"US",
    "sg:address":"1122 Westwood Blvd",
    "sg:city":"Los Angeles",
    "sg:classifiers":[
        {
            "category":"Retail",
            "subcategory":"Repair Shop",
            "type":"Services"
        },
        {
            "category":"Shopping",
            "subcategory":"Gifts & Souvenirs",
            "type":"Retail Goods"
        },
        {
            "category":"Shopping",
            "subcategory":"Jewelry",
            "type":"Retail Goods"
        }
    ],
    "sg:phone":"+1 310 208 5350",
    "sg:postcode":"90024",
    "sg:province":"CA",
    "sg:tags":[
        "flower",
        "watch"
    ],
    "wof:name":"Glitterati",
    "wof:placetype":"venue"
},
  "geometry": {"coordinates":[-118.4451,34.060279],"type":"Point"}
}