{
  "type": "Feature",
  "properties": {
    "iso:country":"US",
    "sg:address":"142 Jason St",
    "sg:city":"Manteca",
    "sg:classifiers":[
        {
            "category":"Food & Beverages",
            "subcategory":"Meat & Fish",
            "type":"Retail Goods"
        }
    ],
    "sg:phone":"+1 209 239 4184",
    "sg:postcode":"95336",
    "sg:province":"CA",
    "wof:name":"Fagundes Meats & Catering Inc",
    "wof:placetype":"venue"
},
  "geometry": {"coordinates":[-121.215895,37.809998],"type":"Point"}
}