{
  "type": "Feature",
  "properties": {
    "iso:country":"US",
    "sg:address":"5310 Balls Ferry Rd",
    "sg:city":"Anderson",
    "sg:classifiers":[
        {
            "category":"Retail",
            "subcategory":"Animal Services",
            "type":"Services"
        }
    ],
    "sg:phone":"+1 530 365 7363",
    "sg:postcode":"96007",
    "sg:province":"CA",
    "sg:tags":[
        "pet",
        "grooming",
        "washing"
    ],
    "wof:name":"Flying Furr",
    "wof:placetype":"venue"
},
  "geometry": {"coordinates":[-122.247491,40.441527],"type":"Point"}
}