{
  "type": "Feature",
  "properties": {
    "addr:full":"534 Ferro Ln Paso Robles CA 93446",
    "addr:housenumber":"534",
    "addr:postcode":"93446",
    "addr:street":"Ferro Ln",
    "iso:country":"US",
    "sg:address":"534 Ferro Ln",
    "sg:city":"Paso Robles",
    "sg:classifiers":[
        {
            "category":"Wholesale",
            "subcategory":"Machinery & Supplies",
            "type":"Manufacturing & Wholesale Goods"
        }
    ],
    "sg:phone":"+1 805 238 3715",
    "sg:postcode":"93446",
    "sg:province":"CA",
    "sg:tags":[
        "equipment",
        "industrial"
    ],
    "wof:name":"Issys Pumping",
    "wof:placetype":"venue"
},
  "geometry": {"coordinates":[-120.67741700000001,35.627818],"type":"Point"}
}