{
  "type": "Feature",
  "properties": {
    "addr:full":"27556 Sierra Hwy Canyon Country CA 91351",
    "addr:housenumber":"27556",
    "addr:postcode":"91351",
    "addr:street":"Sierra Hwy",
    "iso:country":"US",
    "sg:address":"27556 Sierra Hwy",
    "sg:city":"Canyon Country",
    "sg:classifiers":[
        {
            "category":"Wholesale",
            "subcategory":"Machinery & Supplies",
            "type":"Manufacturing & Wholesale Goods"
        }
    ],
    "sg:phone":"+1 661 251 0036",
    "sg:postcode":"91351",
    "sg:province":"CA",
    "sg:tags":[
        "salon",
        "beauty"
    ],
    "wof:name":"Beauty Forum Inc",
    "wof:placetype":"venue"
},
  "geometry": {"coordinates":[-118.462535,34.407111],"type":"Point"}
}