{
  "type": "Feature",
  "properties": {
    "addr:full":"1176 Aster Ave Sunnyvale CA 94086",
    "addr:housenumber":"1176",
    "addr:postcode":"94086",
    "addr:street":"Aster Ave",
    "iso:country":"US",
    "sg:address":"1176 Aster Ave",
    "sg:city":"Sunnyvale",
    "sg:classifiers":[
        {
            "category":"Manufacturing",
            "subcategory":"Metals",
            "type":"Manufacturing & Wholesale Goods"
        },
        {
            "category":"Manufacturing",
            "subcategory":"Tools & Machinery",
            "type":"Manufacturing & Wholesale Goods"
        }
    ],
    "sg:phone":"+1 408 243 7047",
    "sg:postcode":"94086",
    "sg:province":"CA",
    "sg:tags":[
        "machine",
        "stampings",
        "mfg"
    ],
    "wof:name":"Sum Manufacturing",
    "wof:placetype":"venue"
},
  "geometry": {"coordinates":[-121.997795,37.369224],"type":"Point"}
}