{
  "type": "Feature",
  "properties": {
    "iso:country":"US",
    "sg:address":"3160 Imperial Hwy",
    "sg:city":"Lynwood",
    "sg:classifiers":[
        {
            "category":"Shopping",
            "subcategory":"Shoes",
            "type":"Retail Goods"
        }
    ],
    "sg:phone":"+1 310 762 1117",
    "sg:postcode":"90262",
    "sg:province":"CA",
    "wof:name":"All City Footware",
    "wof:placetype":"venue"
},
  "geometry": {"coordinates":[-118.21261199999999,33.930195],"type":"Point"}
}