{
  "type": "Feature",
  "properties": {
    "iso:country":"US",
    "sg:address":"2234 el Capitan Dr",
    "sg:city":"Riverside",
    "sg:classifiers":[
        {
            "category":"Real Estate",
            "subcategory":"Real Estate Agent",
            "type":"Services"
        }
    ],
    "sg:phone":"+1 951 781 3600",
    "sg:postcode":"92506",
    "sg:province":"CA",
    "wof:name":"Hughes Realty",
    "wof:placetype":"venue"
},
  "geometry": {"coordinates":[-117.36060500000001,33.941443],"type":"Point"}
}