{
  "type": "Feature",
  "properties": {
    "iso:country":"US",
    "sg:address":"1771 State Rte 4",
    "sg:city":"Arnold",
    "sg:classifiers":[
        {
            "category":"Home & Garden",
            "subcategory":"Building Materials",
            "type":"Retail Goods"
        }
    ],
    "sg:phone":"+1 209 795 4038",
    "sg:postcode":"95223",
    "sg:province":"CA",
    "sg:tags":[
        "door"
    ],
    "wof:name":"Al Cal Door & Trim",
    "wof:placetype":"venue"
},
  "geometry": {"coordinates":[-120.358034,38.250562],"type":"Point"}
}