{
  "type": "Feature",
  "properties": {
    "iso:country":"US",
    "sg:address":"35 River Pointe Way",
    "sg:city":"Lodi",
    "sg:classifiers":[
        {
            "category":"Professional",
            "type":"Services"
        }
    ],
    "sg:phone":"+1 209 369 3075",
    "sg:postcode":"95240",
    "sg:province":"CA",
    "wof:name":"Rhonda Love",
    "wof:placetype":"venue"
},
  "geometry": {"coordinates":[-121.271708,38.14615],"type":"Point"}
}