{
  "type": "Feature",
  "properties": {
    "addr:full":"25146 Sherman Rd Romoland CA 92585",
    "addr:housenumber":"25146",
    "addr:postcode":"92585",
    "addr:street":"Sherman Rd",
    "iso:country":"US",
    "sg:address":"25146 Sherman Rd",
    "sg:city":"Romoland",
    "sg:classifiers":[
        {
            "category":"Manufacturing",
            "subcategory":"Tools & Machinery",
            "type":"Manufacturing & Wholesale Goods"
        }
    ],
    "sg:phone":"+1 951 928 9161",
    "sg:postcode":"92585",
    "sg:province":"CA",
    "sg:tags":[
        "mold"
    ],
    "wof:name":"James Patrick Tooling",
    "wof:placetype":"venue"
},
  "geometry": {"coordinates":[-117.18035999999999,33.755044],"type":"Point"}
}