{
  "type": "Feature",
  "properties": {
    "iso:country":"US",
    "sg:address":"1325 el Pinal Dr",
    "sg:city":"Stockton",
    "sg:classifiers":[
        {
            "category":"Home & Garden",
            "subcategory":"Furniture",
            "type":"Retail Goods"
        }
    ],
    "sg:phone":"+1 209 463 6365",
    "sg:postcode":"95205",
    "sg:province":"CA",
    "wof:name":"Interior Specialists",
    "wof:placetype":"venue"
},
  "geometry": {"coordinates":[-121.281266,37.977928],"type":"Point"}
}