{
  "type": "Feature",
  "properties": {
    "iso:country":"US",
    "sg:address":"6151 Pony Express Trl",
    "sg:city":"Pollock Pines",
    "sg:classifiers":[
        {
            "category":"Shopping",
            "subcategory":"Used Merchandise",
            "type":"Retail Goods"
        }
    ],
    "sg:phone":"+1 530 644 3214",
    "sg:postcode":"95726",
    "sg:province":"CA",
    "wof:name":"Twice Is Nice",
    "wof:placetype":"venue"
},
  "geometry": {"coordinates":[-120.58970100000001,38.759123],"type":"Point"}
}