{
  "type": "Feature",
  "properties": {
    "addr:full":"2500 Milvia St Berkeley CA 94704",
    "addr:housenumber":"2500",
    "addr:postcode":"94704",
    "addr:street":"Milvia St",
    "iso:country":"US",
    "sg:address":"2500 Milvia St",
    "sg:city":"Berkeley",
    "sg:classifiers":[
        {
            "category":"Health Services",
            "subcategory":"Doctor",
            "type":"Services"
        }
    ],
    "sg:phone":"+1 510 486 1700",
    "sg:postcode":"94704",
    "sg:province":"CA",
    "sg:tags":[
        "physician",
        "surgeon"
    ],
    "wof:name":"Dermatology Assoc Of Berkeley",
    "wof:placetype":"venue"
},
  "geometry": {"coordinates":[-122.26974199999999,37.862763],"type":"Point"}
}