{
  "type": "Feature",
  "properties": {
    "addr:full":"791 University Ave Sacramento CA 95825",
    "addr:housenumber":"791",
    "addr:postcode":"95825",
    "addr:street":"University Ave",
    "iso:country":"US",
    "sg:address":"791 University Ave",
    "sg:city":"Sacramento",
    "sg:classifiers":[
        {
            "category":"Health Services",
            "subcategory":"Health Practitioner",
            "type":"Services"
        }
    ],
    "sg:phone":"+1 916 922 7876",
    "sg:postcode":"95825",
    "sg:province":"CA",
    "sg:tags":[
        "psychologist"
    ],
    "wof:name":"Arna M Munford PHD",
    "wof:placetype":"venue"
},
  "geometry": {"coordinates":[-121.418869,38.568401],"type":"Point"}
}