{
  "type": "Feature",
  "properties": {
    "addr:full":"3720 Easton Dr Ste 1 Bakersfield CA 93309",
    "addr:housenumber":"3720",
    "addr:postcode":"93309",
    "addr:street":"Easton Dr Ste 1",
    "iso:country":"US",
    "sg:address":"3720 Easton Dr Ste 1",
    "sg:city":"Bakersfield",
    "sg:classifiers":[
        {
            "category":"Communications",
            "subcategory":"Film & Video Production",
            "type":"Services"
        }
    ],
    "sg:phone":"+1 661 282 2830",
    "sg:postcode":"93309",
    "sg:province":"CA",
    "sg:tags":[
        "services-commercial"
    ],
    "wof:name":"Media Equipment Corp",
    "wof:placetype":"venue"
},
  "geometry": {"coordinates":[-119.05148,35.369888],"type":"Point"}
}