{
  "type": "Feature",
  "properties": {
    "iso:country":"US",
    "sg:address":"8406 W 3rd Street",
    "sg:city":"Los Angeles",
    "sg:classifiers":[
        {
            "category":"Manufacturing",
            "subcategory":"Leather Goods",
            "type":"Manufacturing & Wholesale Goods"
        }
    ],
    "sg:phone":"+1 323 653 8132",
    "sg:postcode":"90048",
    "sg:province":"CA",
    "wof:name":"Jacob's Leather Goods",
    "wof:placetype":"venue"
},
  "geometry": {"coordinates":[-118.37347800000001,34.073165],"type":"Point"}
}