{
  "type": "Feature",
  "properties": {
    "iso:country":"US",
    "sg:address":"2011 P St Ste 301",
    "sg:city":"Sacramento",
    "sg:classifiers":[
        {
            "category":"Personal",
            "subcategory":"Beauty Salon",
            "type":"Services"
        }
    ],
    "sg:phone":"+1 916 442 3141",
    "sg:postcode":"95814",
    "sg:province":"CA",
    "sg:tags":[
        "makeup",
        "artist"
    ],
    "sg:website":"www.veronicajesthetics.com",
    "wof:name":"Veronica J Esthetics",
    "wof:placetype":"venue"
},
  "geometry": {"coordinates":[-121.48217200000001,38.570246],"type":"Point"}
}