{
  "type": "Feature",
  "properties": {
    "iso:country":"US",
    "sg:address":"3515 W Burbank Blvd",
    "sg:city":"Burbank",
    "sg:classifiers":[
        {
            "category":"Shopping",
            "subcategory":"Florist",
            "type":"Retail Goods"
        }
    ],
    "sg:phone":"+1 818 848 1717",
    "sg:postcode":"91505",
    "sg:province":"CA",
    "wof:name":"Fancy Garden",
    "wof:placetype":"venue"
},
  "geometry": {"coordinates":[-118.349192,34.175121],"type":"Point"}
}