{
  "type": "Feature",
  "properties": {
    "iso:country":"US",
    "sg:address":"2565 Lund St Ste K",
    "sg:city":"El Cajon",
    "sg:classifiers":[
        {
            "category":"Professional",
            "subcategory":"Advertising",
            "type":"Services"
        }
    ],
    "sg:phone":"+1 619 825 1945",
    "sg:postcode":"92020",
    "sg:province":"CA",
    "sg:tags":[
        "marketing"
    ],
    "sg:website":"www.thecouponlocator.com",
    "wof:name":"The Coupon Locator",
    "wof:placetype":"venue"
},
  "geometry": {"coordinates":[-116.999239,32.828317],"type":"Point"}
}