{
  "type": "Feature",
  "properties": {
    "iso:country":"US",
    "sg:address":"1720 W Ave J",
    "sg:city":"Lancaster",
    "sg:classifiers":[
        {
            "category":"Health Services",
            "subcategory":"Doctor",
            "type":"Services"
        }
    ],
    "sg:phone":"+1 661 952 1100",
    "sg:postcode":"93534",
    "sg:province":"CA",
    "sg:tags":[
        "clinic"
    ],
    "sg:website":"www.rvsc.com",
    "wof:name":"Regional Valley Surgery Ctr",
    "wof:placetype":"venue"
},
  "geometry": {"coordinates":[-118.16168999999999,34.689266],"type":"Point"}
}