{
  "type": "Feature",
  "properties": {
    "iso:country":"US",
    "sg:address":"575 Price St",
    "sg:city":"Pismo Beach",
    "sg:classifiers":[
        {
            "category":"Communications",
            "subcategory":"Film & Video Production",
            "type":"Services"
        }
    ],
    "sg:phone":"+1 805 556 0331",
    "sg:postcode":"93449",
    "sg:province":"CA",
    "sg:tags":[
        "taping"
    ],
    "sg:website":"www.pacificcoastpro.com",
    "wof:name":"Pacific Coast Productions",
    "wof:placetype":"venue"
},
  "geometry": {"coordinates":[-120.638727,35.140425],"type":"Point"}
}