{
  "type": "Feature",
  "properties": {
    "iso:country":"US",
    "sg:address":"11404 Alvarado Rd",
    "sg:city":"Oakdale",
    "sg:classifiers":[
        {
            "category":"Building & Trades",
            "subcategory":"Equipment Rental",
            "type":"Services"
        }
    ],
    "sg:phone":"+1 209 848 4677",
    "sg:postcode":"95361",
    "sg:province":"CA",
    "sg:tags":[
        "disabled",
        "person",
        "supply"
    ],
    "wof:name":"Hold Your Horses",
    "wof:placetype":"venue"
},
  "geometry": {"coordinates":[-120.774827,37.725522],"type":"Point"}
}