{
  "type": "Feature",
  "properties": {
    "addr:full":"594 N State College Blvd Fullerton CA 92831",
    "addr:housenumber":"594",
    "addr:postcode":"92831",
    "addr:street":"N State College Blvd",
    "iso:country":"US",
    "sg:address":"594 N State College Blvd",
    "sg:city":"Fullerton",
    "sg:classifiers":[
        {
            "category":"Building & Trades",
            "subcategory":"Electrical",
            "type":"Services"
        }
    ],
    "sg:phone":"+1 714 871 5949",
    "sg:postcode":"92831",
    "sg:province":"CA",
    "sg:tags":[
        "electrical",
        "contractor"
    ],
    "wof:name":"James Thompson Electric",
    "wof:placetype":"venue"
},
  "geometry": {"coordinates":[-117.889534,33.874988],"type":"Point"}
}