{
  "type": "Feature",
  "properties": {
    "iso:country":"US",
    "sg:address":"970 McLaughlin Ave",
    "sg:city":"San Jose",
    "sg:classifiers":[
        {
            "category":"Manufacturing",
            "subcategory":"Tools & Machinery",
            "type":"Manufacturing & Wholesale Goods"
        }
    ],
    "sg:phone":"+1 408 629 1132",
    "sg:postcode":"95122",
    "sg:province":"CA",
    "sg:tags":[
        "control",
        "mfg",
        "power",
        "f"
    ],
    "wof:name":"Bsa",
    "wof:placetype":"venue"
},
  "geometry": {"coordinates":[-121.854758,37.334073],"type":"Point"}
}