{
  "type": "Feature",
  "properties": {
    "iso:country":"US",
    "sg:address":"224 N 27th St",
    "sg:city":"San Jose",
    "sg:classifiers":[
        {
            "category":"Professional",
            "subcategory":"Art Services",
            "type":"Services"
        }
    ],
    "sg:phone":"+1 408 288 6441",
    "sg:postcode":"95116",
    "sg:province":"CA",
    "sg:tags":[
        "graphic",
        "designer"
    ],
    "wof:name":"Lucina Designs",
    "wof:placetype":"venue"
},
  "geometry": {"coordinates":[-121.868577,37.352124],"type":"Point"}
}