{
  "type": "Feature",
  "properties": {
    "addr:full":"26 Medway Rd San Rafael CA 94901",
    "addr:housenumber":"26",
    "addr:postcode":"94901",
    "addr:street":"Medway Rd",
    "iso:country":"US",
    "sg:address":"26 Medway Rd",
    "sg:city":"San Rafael",
    "sg:classifiers":[
        {
            "category":"Freight",
            "type":"Transportation"
        }
    ],
    "sg:phone":"+1 415 453 7954",
    "sg:postcode":"94901",
    "sg:province":"CA",
    "sg:tags":[
        "operator",
        "mover",
        "trucking"
    ],
    "wof:name":"Aloha Moving and Storage",
    "wof:placetype":"venue"
},
  "geometry": {"coordinates":[-122.51025799999999,37.962972],"type":"Point"}
}