{
  "type": "Feature",
  "properties": {
    "iso:country":"US",
    "sg:address":"245 Brook Rd",
    "sg:city":"Auburn",
    "sg:classifiers":[
        {
            "category":"Building & Trades",
            "subcategory":"Construction",
            "type":"Services"
        }
    ],
    "sg:phone":"+1 530 885 5302",
    "sg:postcode":"95603",
    "sg:province":"CA",
    "sg:tags":[
        "contractor"
    ],
    "wof:name":"Roumage Construction",
    "wof:placetype":"venue"
},
  "geometry": {"coordinates":[-121.061537,38.895378],"type":"Point"}
}