{
  "type": "Feature",
  "properties": {
    "addr:full":"2167 55th Ave Sacramento CA 95822",
    "addr:housenumber":"2167",
    "addr:postcode":"95822",
    "addr:street":"55Th Ave",
    "iso:country":"US",
    "sg:address":"2167 55th Ave",
    "sg:city":"Sacramento",
    "sg:classifiers":[
        {
            "category":"Shopping",
            "subcategory":"Florist",
            "type":"Retail Goods"
        }
    ],
    "sg:phone":"+1 916 842 1802",
    "sg:postcode":"95822",
    "sg:province":"CA",
    "wof:name":"Move It With Care",
    "wof:placetype":"venue"
},
  "geometry": {"coordinates":[-121.488101,38.50079],"type":"Point"}
}