{
  "type": "Feature",
  "properties": {
    "addr:full":"1330 Industrial Ave Escondido CA 92029",
    "addr:housenumber":"1330",
    "addr:postcode":"92029",
    "addr:street":"Industrial Ave",
    "iso:country":"US",
    "sg:address":"1330 Industrial Ave",
    "sg:city":"Escondido",
    "sg:classifiers":[
        {
            "category":"Retail",
            "subcategory":"Repair Shop",
            "type":"Services"
        }
    ],
    "sg:phone":"+1 760 748 8518",
    "sg:postcode":"92029",
    "sg:province":"CA",
    "sg:tags":[
        "antique",
        "restoring"
    ],
    "wof:name":"L Ciuffo Studios",
    "wof:placetype":"venue"
},
  "geometry": {"coordinates":[-117.106503,33.119569],"type":"Point"}
}