{
  "type": "Feature",
  "properties": {
    "addr:full":"4778 Dewey Dr Fair Oaks CA 95628",
    "addr:housenumber":"4778",
    "addr:postcode":"95628",
    "addr:street":"Dewey Dr",
    "iso:country":"US",
    "sg:address":"4778 Dewey Dr",
    "sg:city":"Fair Oaks",
    "sg:classifiers":[
        {
            "category":"Professional",
            "subcategory":"Business Services",
            "type":"Services"
        }
    ],
    "sg:phone":"+1 916 961 2222",
    "sg:postcode":"95628",
    "sg:province":"CA",
    "sg:tags":[
        "paging",
        "answering"
    ],
    "sg:website":"www.proserv800.com",
    "wof:name":"AA-Signius Communications",
    "wof:placetype":"venue"
},
  "geometry": {"coordinates":[-121.308305,38.651676],"type":"Point"}
}