{
  "type": "Feature",
  "properties": {
    "addr:full":"340 Old Mill Rd Santa Barbara CA 93110",
    "addr:housenumber":"340",
    "addr:postcode":"93110",
    "addr:street":"Old Mill Rd",
    "iso:country":"US",
    "sg:address":"340 Old Mill Rd",
    "sg:city":"Santa Barbara",
    "sg:classifiers":[
        {
            "category":"Professional",
            "type":"Services"
        }
    ],
    "sg:phone":"+1 805 683 3005",
    "sg:postcode":"93110",
    "sg:province":"CA",
    "sg:tags":[
        "establishment"
    ],
    "wof:name":"Anacapa Systems",
    "wof:placetype":"venue"
},
  "geometry": {"coordinates":[-119.764675,34.443839],"type":"Point"}
}