{
  "type": "Feature",
  "properties": {
    "iso:country":"US",
    "sg:address":"12401 Wilshire Blvd",
    "sg:city":"Los Angeles",
    "sg:classifiers":[
        {
            "category":"Health Services",
            "subcategory":"Doctor",
            "type":"Services"
        }
    ],
    "sg:phone":"+1 310 571 1116",
    "sg:postcode":"90025",
    "sg:province":"CA",
    "sg:tags":[
        "physician",
        "surgeon"
    ],
    "wof:name":"Jerry Eyeler MD",
    "wof:placetype":"venue"
},
  "geometry": {"coordinates":[-118.470888,34.041334],"type":"Point"}
}