{
  "type": "Feature",
  "properties": {
    "addr:full":"2309 W Hammer Ln Stockton CA 95209",
    "addr:housenumber":"2309",
    "addr:postcode":"95209",
    "addr:street":"W Hammer Ln",
    "iso:country":"US",
    "sg:address":"2309 W Hammer Ln",
    "sg:city":"Stockton",
    "sg:classifiers":[
        {
            "category":"Shopping",
            "type":"Retail Goods"
        }
    ],
    "sg:phone":"+1 209 957 1793",
    "sg:postcode":"95209",
    "sg:province":"CA",
    "sg:tags":[
        "telephone",
        "cellular"
    ],
    "wof:name":"Radio Shack",
    "wof:placetype":"venue"
},
  "geometry": {"coordinates":[-121.34477699999999,38.021332],"type":"Point"}
}