{
  "type": "Feature",
  "properties": {
    "addr:full":"5899 Cerritos Ave Cypress CA 90630",
    "addr:housenumber":"5899",
    "addr:postcode":"90630",
    "addr:street":"Cerritos Ave",
    "iso:country":"US",
    "sg:address":"5899 Cerritos Ave",
    "sg:city":"Cypress",
    "sg:classifiers":[
        {
            "category":"Personal",
            "subcategory":"Nail Salon",
            "type":"Services"
        }
    ],
    "sg:phone":"+1 714 827 9863",
    "sg:postcode":"90630",
    "sg:province":"CA",
    "wof:name":"Q Nail & Spa",
    "wof:placetype":"venue"
},
  "geometry": {"coordinates":[-118.032122,33.810019],"type":"Point"}
}