{
  "type": "Feature",
  "properties": {
    "addr:full":"2563 Glen Alma Way San Jose CA 95148",
    "addr:housenumber":"2563",
    "addr:postcode":"95148",
    "addr:street":"Glen Alma Way",
    "iso:country":"US",
    "sg:address":"2563 Glen Alma Way",
    "sg:city":"San Jose",
    "sg:classifiers":[
        {
            "category":"Building & Trades",
            "subcategory":"Construction",
            "type":"Services"
        }
    ],
    "sg:phone":"+1 408 238 8619",
    "sg:postcode":"95148",
    "sg:province":"CA",
    "sg:tags":[
        "finishing",
        "wood",
        "refinishing"
    ],
    "wof:name":"Marcelo's Refinishing & Repair",
    "wof:placetype":"venue"
},
  "geometry": {"coordinates":[-121.804194,37.331313],"type":"Point"}
}