{
  "type": "Feature",
  "properties": {
    "iso:country":"US",
    "sg:address":"3168 Pliny St",
    "sg:city":"Riverside",
    "sg:classifiers":[
        {
            "category":"Building & Trades",
            "subcategory":"Landscaping Services",
            "type":"Services"
        }
    ],
    "sg:phone":"+1 951 687 1711",
    "sg:postcode":"92504",
    "sg:province":"CA",
    "wof:name":"Express Landscape Maintenance",
    "wof:placetype":"venue"
},
  "geometry": {"coordinates":[-117.40494,33.930314],"type":"Point"}
}