{
  "type": "Feature",
  "properties": {
    "addr:full":"7546 Parkway Dr La Mesa CA 91942",
    "addr:housenumber":"7546",
    "addr:postcode":"91942",
    "addr:street":"Parkway Dr",
    "iso:country":"US",
    "sg:address":"7546 Parkway Dr",
    "sg:city":"La Mesa",
    "sg:classifiers":[
        {
            "category":"Real Estate",
            "subcategory":"Real Estate Operator",
            "type":"Services"
        }
    ],
    "sg:phone":"+1 619 463 9155",
    "sg:postcode":"91942",
    "sg:province":"CA",
    "sg:tags":[
        "apartment"
    ],
    "wof:name":"Parkway Apartments",
    "wof:placetype":"venue"
},
  "geometry": {"coordinates":[-117.01799800000001,32.784599],"type":"Point"}
}