{
  "type": "Feature",
  "properties": {
    "addr:full":"340 Miller Ave Mill Valley CA 94941",
    "addr:housenumber":"340",
    "addr:postcode":"94941",
    "addr:street":"Miller Ave",
    "iso:country":"US",
    "sg:address":"340 Miller Ave",
    "sg:city":"Mill Valley",
    "sg:classifiers":[
        {
            "category":"Autos & Motor Vehicles",
            "subcategory":"Fuel & Gas Station",
            "type":"Retail Goods"
        }
    ],
    "sg:phone":"+1 415 388 0188",
    "sg:postcode":"94941",
    "sg:province":"CA",
    "sg:tags":[
        "oil"
    ],
    "wof:name":"Xtra Oil Co",
    "wof:placetype":"venue"
},
  "geometry": {"coordinates":[-122.537009,37.897507],"type":"Point"}
}