{
  "type": "Feature",
  "properties": {
    "iso:country":"US",
    "sg:address":"5078 W Pico Boulevard",
    "sg:city":"Los Angeles",
    "sg:classifiers":[
        {
            "category":"Shopping",
            "subcategory":"Florist",
            "type":"Retail Goods"
        }
    ],
    "sg:phone":"+1 323 964 8185",
    "sg:postcode":"90019",
    "sg:province":"CA",
    "wof:name":"Yazmin's Flower",
    "wof:placetype":"venue"
},
  "geometry": {"coordinates":[-118.348812,34.048048],"type":"Point"}
}