{
  "type": "Feature",
  "properties": {
    "addr:full":"1885 Bay Rd East Palo Alto CA 94303",
    "addr:housenumber":"1885",
    "addr:postcode":"94303",
    "addr:street":"Bay Rd",
    "iso:country":"US",
    "sg:address":"1885 Bay Rd",
    "sg:city":"East Palo Alto",
    "sg:classifiers":[
        {
            "category":"Autos & Motor Vehicles",
            "subcategory":"Auto Supplies",
            "type":"Retail Goods"
        }
    ],
    "sg:phone":"+1 650 323 1885",
    "sg:postcode":"94303",
    "sg:province":"CA",
    "sg:tags":[
        "automobile",
        "parts"
    ],
    "wof:name":"Anything Scout",
    "wof:placetype":"venue"
},
  "geometry": {"coordinates":[-122.13381699999999,37.472235],"type":"Point"}
}