{
  "type": "Feature",
  "properties": {
    "addr:full":"120 Cassia Dr Walnut Creek CA 94544",
    "addr:housenumber":"120",
    "addr:postcode":"94544",
    "addr:street":"Cassia Dr",
    "iso:country":"US",
    "sg:address":"120 Cassia Dr",
    "sg:city":"Walnut Creek",
    "sg:classifiers":[
        {
            "category":"Health Services",
            "subcategory":"Doctor",
            "type":"Services"
        }
    ],
    "sg:phone":"+1 925 979 9969",
    "sg:postcode":"94544",
    "sg:province":"CA",
    "sg:tags":[
        "physician",
        "surgeon"
    ],
    "wof:name":"Center Advanced Gynecologic",
    "wof:placetype":"venue"
},
  "geometry": {"coordinates":[-122.066191,37.637718],"type":"Point"}
}