{
  "type": "Feature",
  "properties": {
    "addr:full":"447 Great Mall Drive Suite 130 Milpitas CA 95035",
    "addr:housenumber":"447",
    "addr:postcode":"95035",
    "addr:street":"Great Mall Drive Suite 130",
    "iso:country":"US",
    "sg:address":"447 Great Mall Drive Suite 130",
    "sg:city":"Milpitas",
    "sg:classifiers":[
        {
            "category":"Shopping",
            "subcategory":"Jewelry",
            "type":"Retail Goods"
        },
        {
            "category":"Shopping",
            "subcategory":"Gifts & Souvenirs",
            "type":"Retail Goods"
        }
    ],
    "sg:phone":"+1 408 934 9799",
    "sg:postcode":"95035",
    "sg:province":"CA",
    "sg:tags":[
        "flower"
    ],
    "sg:website":"www.claires.com/",
    "wof:name":"Claire's Boutique",
    "wof:placetype":"venue"
},
  "geometry": {"coordinates":[-121.897003,37.412498],"type":"Point"}
}