{
  "type": "Feature",
  "properties": {
    "iso:country":"US",
    "sg:address":"457 E Gridley Rd",
    "sg:city":"Gridley",
    "sg:classifiers":[
        {
            "category":"Farming",
            "subcategory":"Crops",
            "type":"Manufacturing & Wholesale Goods"
        }
    ],
    "sg:phone":"+1 530 846 4214",
    "sg:postcode":"95948",
    "sg:province":"CA",
    "sg:tags":[
        "grove",
        "nut",
        "tree"
    ],
    "wof:name":"Golden West Farms",
    "wof:placetype":"venue"
},
  "geometry": {"coordinates":[-121.66956999999999,39.363449],"type":"Point"}
}