{
  "type": "Feature",
  "properties": {
    "addr:full":"3266 Avenida Del Alba Carlsbad CA 92009",
    "addr:housenumber":"3266",
    "addr:postcode":"92009",
    "addr:street":"Avenida Del Alba",
    "iso:country":"US",
    "sg:address":"3266 Avenida Del Alba",
    "sg:city":"Carlsbad",
    "sg:classifiers":[
        {
            "category":"Building & Trades",
            "subcategory":"Cleaning & Sanitation",
            "type":"Services"
        }
    ],
    "sg:phone":"+1 760 846 3357",
    "sg:postcode":"92009",
    "sg:province":"CA",
    "sg:tags":[
        "home"
    ],
    "wof:name":"Castle Guard Window Cleaning",
    "wof:placetype":"venue"
},
  "geometry": {"coordinates":[-117.24007899999999,33.065092],"type":"Point"}
}