{
  "type": "Feature",
  "properties": {
    "iso:country":"US",
    "sg:address":"200 W D St",
    "sg:city":"Encinitas",
    "sg:classifiers":[
        {
            "category":"Insurance",
            "subcategory":"Insurance Agent",
            "type":"Services"
        },
        {
            "category":"Banks & Credit Unions",
            "subcategory":"Financial Services",
            "type":"Services"
        }
    ],
    "sg:phone":"+1 760 753 1066",
    "sg:postcode":"92024",
    "sg:province":"CA",
    "sg:tags":[
        "counseling",
        "debt",
        "adjuster"
    ],
    "wof:name":"Debt Management",
    "wof:placetype":"venue"
},
  "geometry": {"coordinates":[-117.2948,33.045898],"type":"Point"}
}