{
  "type": "Feature",
  "properties": {
    "addr:full":"1433 W Merced Ave West Covina CA 91790",
    "addr:housenumber":"1433",
    "addr:postcode":"91790",
    "addr:street":"W Merced Ave",
    "iso:country":"US",
    "sg:address":"1433 W Merced Ave",
    "sg:city":"West Covina",
    "sg:classifiers":[
        {
            "category":"Health Services",
            "subcategory":"Doctor",
            "type":"Services"
        }
    ],
    "sg:phone":"+1 626 962 2421",
    "sg:postcode":"91790",
    "sg:province":"CA",
    "sg:tags":[
        "physician",
        "surgeon"
    ],
    "wof:name":"Hee Yong Oh MD",
    "wof:placetype":"venue"
},
  "geometry": {"coordinates":[-117.946298,34.061545],"type":"Point"}
}