{
  "type": "Feature",
  "properties": {
    "addr:full":"424 N Kaweah Ave Exeter CA 93221",
    "addr:housenumber":"424",
    "addr:postcode":"93221",
    "addr:street":"N Kaweah Ave",
    "iso:country":"US",
    "sg:address":"424 N Kaweah Ave",
    "sg:city":"Exeter",
    "sg:classifiers":[
        {
            "category":"Food & Beverages",
            "subcategory":"Groceries & Convenience Stores",
            "type":"Retail Goods"
        }
    ],
    "sg:phone":"+1 559 592 3361",
    "sg:postcode":"93221",
    "sg:province":"CA",
    "wof:name":"Nickels Pay Less",
    "wof:placetype":"venue"
},
  "geometry": {"coordinates":[-119.135763,36.304003],"type":"Point"}
}