{
  "type": "Feature",
  "properties": {
    "addr:full":"1705 S Catalina Ave Redondo Beach CA 90277",
    "addr:housenumber":"1705",
    "addr:postcode":"90277",
    "addr:street":"S Catalina Ave",
    "iso:country":"US",
    "sg:address":"1705 S Catalina Ave",
    "sg:city":"Redondo Beach",
    "sg:classifiers":[
        {
            "category":"Shopping",
            "subcategory":"Gifts & Souvenirs",
            "type":"Retail Goods"
        }
    ],
    "sg:phone":"+1 310 791 7104",
    "sg:postcode":"90277",
    "sg:province":"CA",
    "sg:tags":[
        "shop"
    ],
    "wof:name":"Harmony Works",
    "wof:placetype":"venue"
},
  "geometry": {"coordinates":[-118.38824700000001,33.818376],"type":"Point"}
}