{
  "type": "Feature",
  "properties": {
    "addr:full":"513 S Maclay St San Fernando CA 91340",
    "addr:housenumber":"513",
    "addr:postcode":"91340",
    "addr:street":"S Maclay St",
    "iso:country":"US",
    "sg:address":"513 S Maclay St",
    "sg:city":"San Fernando",
    "sg:classifiers":[
        {
            "category":"Food & Beverages",
            "subcategory":"Meat & Fish",
            "type":"Retail Goods"
        }
    ],
    "sg:phone":"+1 818 361 3700",
    "sg:postcode":"91340",
    "sg:province":"CA",
    "wof:name":"El Korita Restoratnte",
    "wof:placetype":"venue"
},
  "geometry": {"coordinates":[-118.444659,34.280984],"type":"Point"}
}