{
  "type": "Feature",
  "properties": {
    "addr:full":"316 Mira Loma Glendale CA 91204",
    "addr:housenumber":"316",
    "addr:postcode":"91204",
    "addr:street":"Mira",
    "iso:country":"US",
    "sg:address":"316 Mira Loma",
    "sg:city":"Glendale",
    "sg:classifiers":[
        {
            "category":"Professional",
            "subcategory":"Computer Services",
            "type":"Services"
        }
    ],
    "sg:phone":"+1 877 764 2460",
    "sg:postcode":"91204",
    "sg:province":"CA",
    "sg:tags":[
        "wireless-accessories",
        "wireless",
        "accessories",
        "mobile",
        "cellular",
        "iphone",
        "cases",
        "pda",
        "batteries",
        "bluetooth",
        "hands-free",
        "headset"
    ],
    "sg:website":"http://www.wirelessground.com",
    "wof:name":"WirelessGround",
    "wof:placetype":"venue"
},
  "geometry": {"coordinates":[-118.257454,34.123333],"type":"Point"}
}