{
  "type": "Feature",
  "properties": {
    "iso:country":"US",
    "sg:address":"558 la Sierra Dr",
    "sg:city":"Sacramento",
    "sg:classifiers":[
        {
            "category":"Personal",
            "subcategory":"Beauty Salon",
            "type":"Services"
        },
        {
            "category":"Personal",
            "subcategory":"Barber",
            "type":"Services"
        }
    ],
    "sg:phone":"+1 916 483 2070",
    "sg:postcode":"95864",
    "sg:province":"CA",
    "sg:tags":[
        "hair",
        "stylist"
    ],
    "wof:name":"Jim's Haircutters",
    "wof:placetype":"venue"
},
  "geometry": {"coordinates":[-121.381991,38.575247],"type":"Point"}
}