{
  "type": "Feature",
  "properties": {
    "addr:full":"18709 Brookhurst St Ste 5A Fountain Valley CA 92708",
    "addr:housenumber":"18709",
    "addr:postcode":"92708",
    "addr:street":"Brookhurst St Ste 5A",
    "iso:country":"US",
    "sg:address":"18709 Brookhurst St Ste 5A",
    "sg:city":"Fountain Valley",
    "sg:classifiers":[
        {
            "category":"Banks & Credit Unions",
            "subcategory":"Bank",
            "type":"Services"
        }
    ],
    "sg:phone":"+1 888 842 6328",
    "sg:postcode":"92708",
    "sg:province":"CA",
    "sg:website":"www.navyfederal.org/",
    "wof:name":"Navy Federal Credit Union",
    "wof:placetype":"venue"
},
  "geometry": {"coordinates":[-117.95423599999999,33.690742],"type":"Point"}
}