{
  "type": "Feature",
  "properties": {
    "addr:full":"608 S New Hampshire Ave Los Angeles CA 90005",
    "addr:housenumber":"608",
    "addr:postcode":"90005",
    "addr:street":"S New Hampshire Ave",
    "iso:country":"US",
    "sg:address":"608 S New Hampshire Ave",
    "sg:city":"Los Angeles",
    "sg:classifiers":[
        {
            "category":"Utilities",
            "subcategory":"Mobile Phone",
            "type":"Services"
        }
    ],
    "sg:phone":"+1 213 736 9900",
    "sg:postcode":"90005",
    "sg:province":"CA",
    "sg:tags":[
        "telephone",
        "cellular"
    ],
    "wof:name":"Sweet Talk Wireless",
    "wof:placetype":"venue"
},
  "geometry": {"coordinates":[-118.29283599999999,34.062673],"type":"Point"}
}