{
  "type": "Feature",
  "properties": {
    "iso:country":"US",
    "sg:address":"250 Montclair Avenue",
    "sg:city":"San Jose",
    "sg:classifiers":[
        {
            "category":"Health Services",
            "subcategory":"Dentist",
            "type":"Services"
        }
    ],
    "sg:phone":"+1 408 259 4663",
    "sg:postcode":"95116",
    "sg:province":"CA",
    "wof:name":"Prasad Anupam DDS",
    "wof:placetype":"venue"
},
  "geometry": {"coordinates":[-121.846693,37.364899],"type":"Point"}
}