{
  "type": "Feature",
  "properties": {
    "iso:country":"US",
    "sg:address":"510 J St",
    "sg:city":"Davis",
    "sg:classifiers":[
        {
            "category":"Professional",
            "type":"Services"
        }
    ],
    "sg:phone":"+1 530 792 0828",
    "sg:postcode":"95616",
    "sg:province":"CA",
    "wof:name":"Alice J Eichold",
    "wof:placetype":"venue"
},
  "geometry": {"coordinates":[-121.736726,38.548696],"type":"Point"}
}