{
  "type": "Feature",
  "properties": {
    "addr:full":"23525 Golden Springs Dr Diamond Bar CA 91765",
    "addr:housenumber":"23525",
    "addr:postcode":"91765",
    "addr:street":"Golden Springs Dr",
    "iso:country":"US",
    "sg:address":"23525 Golden Springs Dr",
    "sg:city":"Diamond Bar",
    "sg:classifiers":[
        {
            "category":"Health Services",
            "subcategory":"Doctor",
            "type":"Services"
        }
    ],
    "sg:phone":"+1 909 861 2211",
    "sg:postcode":"91765",
    "sg:province":"CA",
    "sg:tags":[
        "dentist"
    ],
    "wof:name":"Craig M Ammon Inc",
    "wof:placetype":"venue"
},
  "geometry": {"coordinates":[-117.807885,34.019349],"type":"Point"}
}