{
  "type": "Feature",
  "properties": {
    "iso:country":"US",
    "sg:address":"1133 Blythe St",
    "sg:city":"Foster City",
    "sg:classifiers":[
        {
            "category":"Professional",
            "subcategory":"Management & Consulting",
            "type":"Services"
        }
    ],
    "sg:phone":"+1 650 349 9848",
    "sg:postcode":"94404",
    "sg:province":"CA",
    "sg:tags":[
        "consultant",
        "training"
    ],
    "wof:name":"Techs Technology Svc",
    "wof:placetype":"venue"
},
  "geometry": {"coordinates":[-122.265389,37.544963],"type":"Point"}
}