{
  "type": "Feature",
  "properties": {
    "addr:full":"4401 E Main St Ventura CA 93003",
    "addr:housenumber":"4401",
    "addr:postcode":"93003",
    "addr:street":"E Main St",
    "iso:country":"US",
    "sg:address":"4401 E Main St",
    "sg:city":"Ventura",
    "sg:classifiers":[
        {
            "category":"Utilities",
            "subcategory":"Mobile Phone",
            "type":"Services"
        }
    ],
    "sg:phone":"+1 805 644 1000",
    "sg:postcode":"93003",
    "sg:province":"CA",
    "sg:tags":[
        "communication",
        "radiotelephone"
    ],
    "wof:name":"Auto Cellular Systems",
    "wof:placetype":"venue"
},
  "geometry": {"coordinates":[-119.233141,34.262351],"type":"Point"}
}