{
  "type": "Feature",
  "properties": {
    "addr:full":"2538 State Highway 99 Biggs CA 95917",
    "addr:housenumber":"2538",
    "addr:postcode":"95917",
    "addr:street":"State Highway 99",
    "iso:country":"US",
    "sg:address":"2538 State Highway 99",
    "sg:city":"Biggs",
    "sg:classifiers":[
        {
            "category":"Shopping",
            "subcategory":"Gifts & Souvenirs",
            "type":"Retail Goods"
        }
    ],
    "sg:phone":"+1 530 868 5830",
    "sg:postcode":"95917",
    "sg:province":"CA",
    "sg:tags":[
        "shop"
    ],
    "wof:name":"Terry Ott",
    "wof:placetype":"venue"
},
  "geometry": {"coordinates":[-121.688016,39.396504],"type":"Point"}
}