{
  "type": "Feature",
  "properties": {
    "iso:country":"US",
    "sg:address":"25885 San Fernando Rd",
    "sg:city":"Santa Clarita",
    "sg:classifiers":[
        {
            "category":"Retail",
            "subcategory":"Auto Repair",
            "type":"Services"
        }
    ],
    "sg:phone":"+1 661 799 8706",
    "sg:postcode":"91350",
    "sg:province":"CA",
    "sg:tags":[
        "automotive",
        "tire"
    ],
    "wof:name":"Guzman Tires",
    "wof:placetype":"venue"
},
  "geometry": {"coordinates":[-118.541,34.412701],"type":"Point"}
}