{
  "type": "Feature",
  "properties": {
    "iso:country":"US",
    "sg:address":"2516 11th Ave",
    "sg:city":"Los Angeles",
    "sg:classifiers":[
        {
            "category":"Professional",
            "subcategory":"Research",
            "type":"Services"
        }
    ],
    "sg:phone":"+1 323 766 8355",
    "sg:postcode":"90018",
    "sg:province":"CA",
    "sg:tags":[
        "organization"
    ],
    "wof:name":"Paulo Freire Institute",
    "wof:placetype":"venue"
},
  "geometry": {"coordinates":[-118.329489,34.032882],"type":"Point"}
}