{
  "type": "Feature",
  "properties": {
    "addr:full":"464 Cll Primera San Ysidro CA 92173",
    "addr:housenumber":"464",
    "addr:postcode":"92173",
    "addr:street":"Cll Primera",
    "iso:country":"US",
    "sg:address":"464 Cll Primera",
    "sg:city":"San Ysidro",
    "sg:classifiers":[
        {
            "category":"Wholesale",
            "subcategory":"Electrical",
            "type":"Manufacturing & Wholesale Goods"
        }
    ],
    "sg:phone":"+1 619 428 8121",
    "sg:postcode":"92173",
    "sg:province":"CA",
    "sg:tags":[
        "electronic"
    ],
    "wof:name":"Ig Electronics Inc",
    "wof:placetype":"venue"
},
  "geometry": {"coordinates":[-117.048952,32.552556],"type":"Point"}
}