{
  "type": "Feature",
  "properties": {
    "iso:country":"US",
    "sg:address":"12381 Wilshire Blvd",
    "sg:city":"Los Angeles",
    "sg:classifiers":[
        {
            "category":"Health Services",
            "subcategory":"Health Practitioner",
            "type":"Services"
        }
    ],
    "sg:phone":"+1 310 826 1314",
    "sg:postcode":"90025",
    "sg:province":"CA",
    "sg:tags":[
        "acupuncture"
    ],
    "wof:name":"Chinese Healing Institute",
    "wof:placetype":"venue"
},
  "geometry": {"coordinates":[-118.470021,34.04219],"type":"Point"}
}