{
  "type": "Feature",
  "properties": {
    "addr:full":"725 Plaza Ct Chula Vista CA 91910",
    "addr:housenumber":"725",
    "addr:postcode":"91910",
    "addr:street":"Plaza Ct",
    "iso:country":"US",
    "sg:address":"725 Plaza Ct",
    "sg:city":"Chula Vista",
    "sg:classifiers":[
        {
            "category":"Home & Garden",
            "subcategory":"Hardware",
            "type":"Retail Goods"
        },
        {
            "category":"Home & Garden",
            "subcategory":"Building Materials",
            "type":"Retail Goods"
        },
        {
            "category":"Home & Garden",
            "subcategory":"Carpets & Floor Coverings",
            "type":"Retail Goods"
        }
    ],
    "sg:phone":"+1 619 421 6200",
    "sg:postcode":"91910",
    "sg:province":"CA",
    "sg:tags":[
        "flooring",
        "store",
        "supply"
    ],
    "sg:website":"www.homedepot.com",
    "wof:name":"Home Depot",
    "wof:placetype":"venue"
},
  "geometry": {"coordinates":[-117.03197900000001,32.637408],"type":"Point"}
}