{
  "type": "Feature",
  "properties": {
    "iso:country":"US",
    "sg:address":"10419 Bogardus Ave",
    "sg:city":"Whittier",
    "sg:classifiers":[
        {
            "category":"Insurance",
            "subcategory":"Insurance Agent",
            "type":"Services"
        }
    ],
    "sg:phone":"+1 562 902 9448",
    "sg:postcode":"90603",
    "sg:province":"CA",
    "wof:name":"Farmers Insurance Group",
    "wof:placetype":"venue"
},
  "geometry": {"coordinates":[-117.98429899999999,33.941816],"type":"Point"}
}