{
  "type": "Feature",
  "properties": {
    "addr:full":"130 Stony Point Rd Santa Rosa CA 95407",
    "addr:housenumber":"130",
    "addr:postcode":"95407",
    "addr:street":"Stony Point Rd",
    "iso:country":"US",
    "sg:address":"130 Stony Point Rd",
    "sg:city":"Santa Rosa",
    "sg:classifiers":[
        {
            "category":"Banks & Credit Unions",
            "subcategory":"Bank",
            "type":"Services"
        }
    ],
    "sg:phone":"+1 707 546 7722",
    "sg:postcode":"95407",
    "sg:province":"CA",
    "sg:tags":[
        "financing"
    ],
    "wof:name":"Fireside Thrift Co",
    "wof:placetype":"venue"
},
  "geometry": {"coordinates":[-122.74428399999999,38.440308],"type":"Point"}
}