{
  "type": "Feature",
  "properties": {
    "iso:country":"US",
    "sg:address":"130 Stony Point Rd",
    "sg:city":"Santa Rosa",
    "sg:classifiers":[
        {
            "category":"Banks & Credit Unions",
            "subcategory":"Bank",
            "type":"Services"
        }
    ],
    "sg:phone":"+1 707 546 7722",
    "sg:postcode":"95407",
    "sg:province":"CA",
    "sg:tags":[
        "financing"
    ],
    "wof:name":"Fireside Thrift Co",
    "wof:placetype":"venue"
},
  "geometry": {"coordinates":[-122.744284,38.440308],"type":"Point"}
}