{
  "type": "Feature",
  "properties": {
    "iso:country":"US",
    "sg:address":"9550 Mission Blvd",
    "sg:city":"Riverside",
    "sg:classifiers":[
        {
            "category":"Manufacturing",
            "subcategory":"Building Materials",
            "type":"Manufacturing & Wholesale Goods"
        }
    ],
    "sg:phone":"+1 951 360 0035",
    "sg:postcode":"92509",
    "sg:province":"CA",
    "sg:tags":[
        "mfg",
        "wood",
        "kitchen",
        "cabinet"
    ],
    "wof:name":"Patral Custom Cabinets",
    "wof:placetype":"venue"
},
  "geometry": {"coordinates":[-117.49087,34.011709],"type":"Point"}
}