{
  "type": "Feature",
  "properties": {
    "iso:country":"US",
    "sg:address":"1440 Koll Cir",
    "sg:city":"San Jose",
    "sg:classifiers":[
        {
            "category":"Professional",
            "subcategory":"Business Services",
            "type":"Services"
        }
    ],
    "sg:phone":"+1 408 436 9336",
    "sg:postcode":"95112",
    "sg:province":"CA",
    "sg:tags":[
        "auctioneer"
    ],
    "wof:name":"A One Auction",
    "wof:placetype":"venue"
},
  "geometry": {"coordinates":[-121.906433,37.365644],"type":"Point"}
}