{
  "type": "Feature",
  "properties": {
    "iso:country":"US",
    "sg:address":"224 S 24th St",
    "sg:city":"San Jose",
    "sg:classifiers":[
        {
            "category":"Wholesale",
            "subcategory":"Dairy",
            "type":"Manufacturing & Wholesale Goods"
        }
    ],
    "sg:phone":"+1 408 993 0329",
    "sg:postcode":"95116",
    "sg:province":"CA",
    "sg:tags":[
        "frozen",
        "dessert",
        "ice",
        "cream"
    ],
    "wof:name":"Me Ice Cream",
    "wof:placetype":"venue"
},
  "geometry": {"coordinates":[-121.863514,37.342803],"type":"Point"}
}