{
  "type": "Feature",
  "properties": {
    "addr:full":"1447 Glacier St Simi Valley CA 93063",
    "addr:housenumber":"1447",
    "addr:postcode":"93063",
    "addr:street":"Glacier St",
    "iso:country":"US",
    "sg:address":"1447 Glacier St",
    "sg:city":"Simi Valley",
    "sg:classifiers":[
        {
            "category":"Shopping",
            "subcategory":"Used Merchandise",
            "type":"Retail Goods"
        }
    ],
    "sg:phone":"+1 805 520 1347",
    "sg:postcode":"93063",
    "sg:province":"CA",
    "wof:name":"Shelby S Gifts & Antiques",
    "wof:placetype":"venue"
},
  "geometry": {"coordinates":[-118.733313,34.266849],"type":"Point"}
}