{
  "type": "Feature",
  "properties": {
    "iso:country":"US",
    "sg:address":"619 W McFadden Ave",
    "sg:city":"Santa Ana",
    "sg:classifiers":[
        {
            "category":"Food & Beverages",
            "subcategory":"Liquor & Beverages",
            "type":"Retail Goods"
        },
        {
            "category":"Food & Beverages",
            "subcategory":"Groceries & Convenience Stores",
            "type":"Retail Goods"
        }
    ],
    "sg:phone":"+1 714 836 0318",
    "sg:postcode":"92707",
    "sg:province":"CA",
    "sg:tags":[
        "beer",
        "spirit",
        "wine"
    ],
    "wof:name":"Fairview Liquor Market",
    "wof:placetype":"venue"
},
  "geometry": {"coordinates":[-117.87400100000001,33.734402],"type":"Point"}
}