{
  "type": "Feature",
  "properties": {
    "addr:full":"400 Mira Loma Dr Bakersfield CA 93309",
    "addr:housenumber":"400",
    "addr:postcode":"93309",
    "addr:street":"Mira Loma Dr",
    "iso:country":"US",
    "sg:address":"400 Mira Loma Dr",
    "sg:city":"Bakersfield",
    "sg:classifiers":[
        {
            "category":"Shopping",
            "subcategory":"Hobbies, Toys, & Games",
            "type":"Retail Goods"
        }
    ],
    "sg:phone":"+1 661 831 9955",
    "sg:postcode":"93309",
    "sg:province":"CA",
    "sg:tags":[
        "craft",
        "supply"
    ],
    "wof:name":"Tanya's Fabrics & Things",
    "wof:placetype":"venue"
},
  "geometry": {"coordinates":[-119.049834,35.361452],"type":"Point"}
}