{
  "type": "Feature",
  "properties": {
    "iso:country":"US",
    "sg:address":"75 Malaga Cove Plz",
    "sg:city":"Palos Vrds Ests",
    "sg:classifiers":[
        {
            "category":"Real Estate",
            "subcategory":"Developer",
            "type":"Services"
        }
    ],
    "sg:phone":"+1 310 465 1885",
    "sg:postcode":"90274",
    "sg:province":"CA",
    "wof:name":"K R Gibbs Assoc",
    "wof:placetype":"venue"
},
  "geometry": {"coordinates":[-118.389208,33.800402],"type":"Point"}
}