{
  "type": "Feature",
  "properties": {
    "iso:country":"US",
    "sg:address":"831 E Holt Blvd",
    "sg:city":"Ontario",
    "sg:classifiers":[
        {
            "category":"Retail",
            "subcategory":"Auto Rental",
            "type":"Services"
        }
    ],
    "sg:phone":"+1 909 986 6628",
    "sg:postcode":"91761",
    "sg:province":"CA",
    "sg:tags":[
        "renting",
        "truck",
        "leasing"
    ],
    "sg:website":"www.uhaul.com",
    "wof:name":"U-Haul Co",
    "wof:placetype":"venue"
},
  "geometry": {"coordinates":[-117.640861,34.063461],"type":"Point"}
}