{
  "type": "Feature",
  "properties": {
    "iso:country":"US",
    "sg:address":"608 Main St",
    "sg:city":"Pleasanton",
    "sg:classifiers":[
        {
            "category":"Professional",
            "subcategory":"Engineering",
            "type":"Services"
        }
    ],
    "sg:phone":"+1 925 426 2386",
    "sg:postcode":"94566",
    "sg:province":"CA",
    "sg:tags":[
        "engineer"
    ],
    "wof:name":"Pegasus Design",
    "wof:placetype":"venue"
},
  "geometry": {"coordinates":[-121.87491300000001,37.662388],"type":"Point"}
}