{
  "type": "Feature",
  "properties": {
    "iso:country":"US",
    "sg:address":"3601 Reich Ln",
    "sg:city":"Riverbank",
    "sg:classifiers":[
        {
            "category":"Banks & Credit Unions",
            "subcategory":"Investment Brokerage",
            "type":"Services"
        }
    ],
    "sg:phone":"+1 209 869 4667",
    "sg:postcode":"95367",
    "sg:province":"CA",
    "sg:tags":[
        "advisory"
    ],
    "wof:name":"Capas Property Investments",
    "wof:placetype":"venue"
},
  "geometry": {"coordinates":[-120.929393,37.72161],"type":"Point"}
}