{
  "type": "Feature",
  "properties": {
    "iso:country":"US",
    "sg:address":"1345 S Diamond Bar Blvd",
    "sg:city":"Diamond Bar",
    "sg:classifiers":[
        {
            "category":"Restaurant",
            "type":"Food & Drink"
        }
    ],
    "sg:menulink":"http://www.allmenus.com/ca/east-san-gabriel-valley/74016-ameci-pizza--pasta/menu/",
    "sg:phone":"+1 909 396 6800",
    "sg:postcode":"91765",
    "sg:province":"CA",
    "sg:tags":[
        "american",
        "pizza"
    ],
    "wof:name":"Ameci Pizza & Pasta",
    "wof:placetype":"venue"
},
  "geometry": {"coordinates":[-117.81366,33.997539],"type":"Point"}
}