{
  "type": "Feature",
  "properties": {
    "addr:full":"14652 Central Ave Chino CA 91710",
    "addr:postcode":"14652;91710",
    "addr:street":"Central Ave",
    "iso:country":"US",
    "sg:address":"14652 Central Ave",
    "sg:city":"Chino",
    "sg:classifiers":[
        {
            "category":"Wholesale",
            "subcategory":"Durable Goods & Equipment",
            "type":"Manufacturing & Wholesale Goods"
        }
    ],
    "sg:phone":"+1 909 606 6126",
    "sg:postcode":"91710",
    "sg:province":"CA",
    "sg:tags":[
        "importer"
    ],
    "wof:name":"Virgelles Inc II",
    "wof:placetype":"venue"
},
  "geometry": {"coordinates":[-117.688982,33.985585],"type":"Point"}
}