{
  "type": "Feature",
  "properties": {
    "iso:country":"US",
    "sg:address":"711 Fair Oaks Ave Ste E",
    "sg:city":"South Pasadena",
    "sg:classifiers":[
        {
            "category":"Retail",
            "subcategory":"Laundry & Dry Cleaning",
            "type":"Services"
        }
    ],
    "sg:phone":"+1 626 441 5500",
    "sg:postcode":"91030",
    "sg:province":"CA",
    "wof:name":"Tele Cleaners",
    "wof:placetype":"venue"
},
  "geometry": {"coordinates":[-118.150281,34.117532],"type":"Point"}
}