{
  "type": "Feature",
  "properties": {
    "addr:full":"711 Fair Oaks Ave Ste E South Pasadena CA 91030",
    "addr:housenumber":"711",
    "addr:postcode":"91030",
    "addr:street":"Fair Oaks Ave Ste E",
    "iso:country":"US",
    "sg:address":"711 Fair Oaks Ave Ste E",
    "sg:city":"South Pasadena",
    "sg:classifiers":[
        {
            "category":"Retail",
            "subcategory":"Laundry & Dry Cleaning",
            "type":"Services"
        }
    ],
    "sg:phone":"+1 626 441 5500",
    "sg:postcode":"91030",
    "sg:province":"CA",
    "wof:name":"Tele Cleaners",
    "wof:placetype":"venue"
},
  "geometry": {"coordinates":[-118.15028100000001,34.117532],"type":"Point"}
}