{
  "type": "Feature",
  "properties": {
    "iso:country":"US",
    "sg:address":"7915 Lindley Ave",
    "sg:city":"Reseda",
    "sg:classifiers":[
        {
            "category":"Social Services",
            "type":"Services"
        },
        {
            "category":"Health Services",
            "subcategory":"Nursing And Care Facility",
            "type":"Services"
        }
    ],
    "sg:phone":"+1 818 609 9477",
    "sg:postcode":"91335",
    "sg:province":"CA",
    "sg:tags":[
        "blind",
        "product",
        "disability",
        "developmentally",
        "disabled",
        "vision",
        "need",
        "impaired",
        "special"
    ],
    "wof:name":"TLC For The Blind",
    "wof:placetype":"venue"
},
  "geometry": {"coordinates":[-118.527331,34.213921],"type":"Point"}
}