{
  "type": "Feature",
  "properties": {
    "iso:country":"US",
    "sg:address":"3193 Belick St",
    "sg:city":"Santa Clara",
    "sg:classifiers":[
        {
            "category":"Manufacturing",
            "subcategory":"Tools & Machinery",
            "type":"Manufacturing & Wholesale Goods"
        }
    ],
    "sg:phone":"+1 408 980 9119",
    "sg:postcode":"95054",
    "sg:province":"CA",
    "sg:tags":[
        "equipment",
        "consulting"
    ],
    "wof:name":"Engineering and Mfg Svcs",
    "wof:placetype":"venue"
},
  "geometry": {"coordinates":[-121.942408,37.380584],"type":"Point"}
}