{
  "type": "Feature",
  "properties": {
    "addr:full":"1234 E Franklin Ave El Segundo CA 90245",
    "addr:housenumber":"1234",
    "addr:postcode":"90245",
    "addr:street":"E Franklin Ave",
    "iso:country":"US",
    "sg:address":"1234 E Franklin Ave",
    "sg:city":"El Segundo",
    "sg:classifiers":[
        {
            "category":"Health Services",
            "subcategory":"Clinic",
            "type":"Services"
        }
    ],
    "sg:phone":"+1 310 416 1099",
    "sg:postcode":"90245",
    "sg:province":"CA",
    "sg:tags":[
        "home",
        "care"
    ],
    "wof:name":"Jesi-Care Spported Living Agcy",
    "wof:placetype":"venue"
},
  "geometry": {"coordinates":[-118.40294799999999,33.917821],"type":"Point"}
}