{
  "type": "Feature",
  "properties": {
    "addr:full":"555 E El Camino Real Sunnyvale CA 94087",
    "addr:housenumber":"555",
    "addr:postcode":"94087",
    "addr:street":"E El Camino Real",
    "iso:country":"US",
    "sg:address":"555 E El Camino Real",
    "sg:city":"Sunnyvale",
    "sg:classifiers":[
        {
            "category":"Real Estate",
            "subcategory":"Real Estate Operator",
            "type":"Services"
        }
    ],
    "sg:phone":"+1 408 738 0935",
    "sg:postcode":"94087",
    "sg:province":"CA",
    "sg:tags":[
        "apartment"
    ],
    "sg:website":"www.equityapartments.com/San-Fra...",
    "wof:name":"Arbor Terrace",
    "wof:placetype":"venue"
},
  "geometry": {"coordinates":[-122.02744800000001,37.36402],"type":"Point"}
}