{
  "type": "Feature",
  "properties": {
    "addr:full":"1848 Saratoga Ave Suite 2 Saratoga CA 95070",
    "addr:housenumber":"1848",
    "addr:postcode":"95070",
    "addr:street":"Saratoga Ave Suite 2",
    "iso:country":"US",
    "sg:address":"1848 Saratoga Ave Suite 2",
    "sg:city":"Saratoga",
    "sg:classifiers":[
        {
            "category":"Health Services",
            "subcategory":"Doctor",
            "type":"Services"
        }
    ],
    "sg:phone":"+1 408 370 2828",
    "sg:postcode":"95070",
    "sg:province":"CA",
    "sg:tags":[
        "practice",
        "family"
    ],
    "wof:name":"Anthony Wong, MD",
    "wof:placetype":"venue"
},
  "geometry": {"coordinates":[-121.995355,37.287985],"type":"Point"}
}