{
  "type": "Feature",
  "properties": {
    "addr:full":"810 West Maude Avenue Sunnyvale CA 94085",
    "addr:housenumber":"810",
    "addr:postcode":"94085",
    "addr:street":"West Maude Avenue",
    "iso:country":"US",
    "sg:address":"810 West Maude Avenue",
    "sg:city":"Sunnyvale",
    "sg:classifiers":[
        {
            "category":"Professional",
            "subcategory":"Computer Services",
            "type":"Services"
        }
    ],
    "sg:phone":"+1 408 727 1885",
    "sg:postcode":"94085",
    "sg:province":"CA",
    "sg:website":"http://www.8x8.com/",
    "wof:name":"8x8 Inc",
    "wof:placetype":"venue"
},
  "geometry": {"coordinates":[-122.03780999999999,37.39212],"type":"Point"}
}