{
  "type": "Feature",
  "properties": {
    "iso:country":"US",
    "sg:address":"16014 Adelante St",
    "sg:city":"Irwindale",
    "sg:classifiers":[
        {
            "category":"Wholesale",
            "subcategory":"Electrical",
            "type":"Manufacturing & Wholesale Goods"
        }
    ],
    "sg:phone":"+1 626 969 1188",
    "sg:postcode":"91702",
    "sg:province":"CA",
    "sg:tags":[
        "speaker"
    ],
    "wof:name":"United Suntech Craft Inc",
    "wof:placetype":"venue"
},
  "geometry": {"coordinates":[-117.931418,34.126794],"type":"Point"}
}