{
  "type": "Feature",
  "properties": {
    "addr:full":"905 Cole Ave Los Angeles CA 90038",
    "addr:housenumber":"905",
    "addr:postcode":"90038",
    "addr:street":"Cole Ave",
    "iso:country":"US",
    "sg:address":"905 Cole Ave",
    "sg:city":"Los Angeles",
    "sg:classifiers":[
        {
            "category":"Wholesale",
            "subcategory":"Photographic Equipment",
            "type":"Manufacturing & Wholesale Goods"
        }
    ],
    "sg:phone":"+1 323 463 1380",
    "sg:postcode":"90038",
    "sg:province":"CA",
    "sg:tags":[
        "motion",
        "picture",
        "supply"
    ],
    "sg:website":"www.locationcreations.com",
    "wof:name":"Location Creations",
    "wof:placetype":"venue"
},
  "geometry": {"coordinates":[-118.329955,34.088849],"type":"Point"}
}