{
  "type": "Feature",
  "properties": {
    "addr:full":"2907 S. Oak St., Ste 100 Santa Ana CA 92707",
    "addr:housenumber":"2907",
    "addr:postcode":"92707",
    "addr:street":"S. Oak St. Ste 100",
    "iso:country":"US",
    "sg:address":"2907 S. Oak St., Ste 100",
    "sg:city":"Santa Ana",
    "sg:classifiers":[
        {
            "category":"Professional",
            "type":"Services"
        },
        {
            "category":"Professional",
            "subcategory":"Computer Services",
            "type":"Services"
        }
    ],
    "sg:phone":"+1 714 556 5999",
    "sg:postcode":"92707",
    "sg:province":"CA",
    "sg:tags":[
        "repair"
    ],
    "sg:website":"www.rclick.com",
    "wof:name":"Right Click, Inc",
    "wof:placetype":"venue"
},
  "geometry": {"coordinates":[-117.86277,33.708296],"type":"Point"}
}