{
  "type": "Feature",
  "properties": {
    "addr:full":"446 W Mission Rd San Marcos CA 92069",
    "addr:housenumber":"446",
    "addr:postcode":"92069",
    "addr:street":"W Mission Rd",
    "iso:country":"US",
    "sg:address":"446 W Mission Rd",
    "sg:city":"San Marcos",
    "sg:classifiers":[
        {
            "category":"Real Estate",
            "subcategory":"Real Estate Agent",
            "type":"Services"
        }
    ],
    "sg:phone":"+1 760 752 7740",
    "sg:postcode":"92069",
    "sg:province":"CA",
    "wof:name":"Platinum Properties",
    "wof:placetype":"venue"
},
  "geometry": {"coordinates":[-117.17053300000001,33.144684],"type":"Point"}
}