{
  "type": "Feature",
  "properties": {
    "addr:full":"1129 Stockton St San Francisco CA 94133",
    "addr:housenumber":"1129",
    "addr:postcode":"94133",
    "addr:street":"Stockton St",
    "iso:country":"US",
    "sg:address":"1129 Stockton St",
    "sg:city":"San Francisco",
    "sg:classifiers":[
        {
            "category":"Professional",
            "subcategory":"Accounting & Tax Preparation",
            "type":"Services"
        }
    ],
    "sg:phone":"+1 415 788 0246",
    "sg:postcode":"94133",
    "sg:province":"CA",
    "sg:tags":[
        "bookkeeping",
        "general"
    ],
    "wof:name":"Chinatown Tax Svc",
    "wof:placetype":"venue"
},
  "geometry": {"coordinates":[-122.40846500000001,37.79644],"type":"Point"}
}