{
  "type": "Feature",
  "properties": {
    "iso:country":"US",
    "sg:address":"835 W Milford St",
    "sg:city":"Glendale",
    "sg:classifiers":[
        {
            "category":"Manufacturing",
            "subcategory":"Textiles",
            "type":"Manufacturing & Wholesale Goods"
        }
    ],
    "sg:phone":"+1 323 245 1701",
    "sg:postcode":"91203",
    "sg:province":"CA",
    "sg:tags":[
        "finishing",
        "plant",
        "cotton"
    ],
    "wof:name":"Fabric Flameproofing Co Inc",
    "wof:placetype":"venue"
},
  "geometry": {"coordinates":[-118.27451000000001,34.152291],"type":"Point"}
}