{
  "type": "Feature",
  "properties": {
    "addr:full":"60 Eucalyptus Knoll St Mill Valley CA 94941",
    "addr:housenumber":"60",
    "addr:postcode":"94941",
    "addr:street":"Eucalyptus Knoll St",
    "iso:country":"US",
    "sg:address":"60 Eucalyptus Knoll St",
    "sg:city":"Mill Valley",
    "sg:classifiers":[
        {
            "category":"Banks & Credit Unions",
            "subcategory":"Bank",
            "type":"Services"
        }
    ],
    "sg:phone":"+1 415 389 8898",
    "sg:postcode":"94941",
    "sg:province":"CA",
    "sg:tags":[
        "federal",
        "good",
        "agency"
    ],
    "wof:name":"FML & Assoc",
    "wof:placetype":"venue"
},
  "geometry": {"coordinates":[-122.52075000000001,37.893282],"type":"Point"}
}