{
  "type": "Feature",
  "properties": {
    "iso:country":"US",
    "sg:address":"13909 Old Harbor Ln",
    "sg:city":"Marina Del Rey",
    "sg:classifiers":[
        {
            "category":"Manufacturing",
            "subcategory":"Tools & Machinery",
            "type":"Manufacturing & Wholesale Goods"
        }
    ],
    "sg:phone":"+1 310 306 6741",
    "sg:postcode":"90292",
    "sg:province":"CA",
    "sg:tags":[
        "equipment",
        "lighting",
        "mfg"
    ],
    "wof:name":"Illuminator Company",
    "wof:placetype":"venue"
},
  "geometry": {"coordinates":[-118.45158499999999,33.96884],"type":"Point"}
}