{
  "type": "Feature",
  "properties": {
    "iso:country":"US",
    "sg:address":"821 S Cecelia St",
    "sg:city":"Los Angeles",
    "sg:classifiers":[
        {
            "category":"Professional",
            "type":"Services"
        }
    ],
    "sg:phone":"+1 213 688 9101",
    "sg:postcode":"90014",
    "sg:province":"CA",
    "wof:name":"Dae Park Inc",
    "wof:placetype":"venue"
},
  "geometry": {"coordinates":[-118.25221000000001,34.03954],"type":"Point"}
}