{
  "type": "Feature",
  "properties": {
    "addr:full":"474 5th St Gustine CA 95322",
    "addr:housenumber":"474",
    "addr:postcode":"95322",
    "addr:street":"5Th St",
    "iso:country":"US",
    "sg:address":"474 5th St",
    "sg:city":"Gustine",
    "sg:classifiers":[
        {
            "category":"Freight",
            "type":"Transportation"
        }
    ],
    "sg:phone":"+1 209 854 6445",
    "sg:postcode":"95322",
    "sg:province":"CA",
    "sg:tags":[
        "fixed",
        "motor",
        "facility"
    ],
    "wof:name":"Souza Trucking",
    "wof:placetype":"venue"
},
  "geometry": {"coordinates":[-120.999349,37.255723],"type":"Point"}
}