{
  "type": "Feature",
  "properties": {
    "addr:full":"1026 Palm St San Luis Obispo CA 93401",
    "addr:housenumber":"1026",
    "addr:postcode":"93401",
    "addr:street":"Palm St",
    "iso:country":"US",
    "sg:address":"1026 Palm St",
    "sg:city":"San Luis Obispo",
    "sg:classifiers":[
        {
            "category":"Professional",
            "subcategory":"Lawyer & Legal Services",
            "type":"Services"
        }
    ],
    "sg:phone":"+1 805 544 4546",
    "sg:postcode":"93401",
    "sg:province":"CA",
    "sg:tags":[
        "attorney"
    ],
    "sg:website":"www.slolegal.com",
    "wof:name":"Landplans",
    "wof:placetype":"venue"
},
  "geometry": {"coordinates":[-120.66107599999999,35.283327],"type":"Point"}
}