{
  "type": "Feature",
  "properties": {
    "iso:country":"US",
    "sg:address":"3160 Folsom Boulevard",
    "sg:city":"Sacramento",
    "sg:classifiers":[
        {
            "category":"Health Services",
            "subcategory":"Doctor",
            "type":"Services"
        }
    ],
    "sg:phone":"+1 916 733 3344",
    "sg:postcode":"95816",
    "sg:province":"CA",
    "sg:tags":[
        "cardiologist"
    ],
    "wof:name":"Casas Jack MD Facc",
    "wof:placetype":"venue"
},
  "geometry": {"coordinates":[-121.465575,38.568776],"type":"Point"}
}