{
  "type": "Feature",
  "properties": {
    "iso:country":"US",
    "sg:address":"58 Maxwell",
    "sg:city":"Irvine",
    "sg:classifiers":[
        {
            "category":"Insurance",
            "subcategory":"Health Insurance",
            "type":"Services"
        }
    ],
    "sg:phone":"+1 949 788 9292",
    "sg:postcode":"92618",
    "sg:province":"CA",
    "sg:tags":[
        "market"
    ],
    "sg:website":"www.hepahealth.com",
    "wof:name":"Hepapro Corp",
    "wof:placetype":"venue"
},
  "geometry": {"coordinates":[-117.736301,33.631964],"type":"Point"}
}