{
  "type": "Feature",
  "properties": {
    "addr:full":"2050 Concourse Dr Ste 42 San Jose CA 95131",
    "addr:housenumber":"2050",
    "addr:postcode":"95131",
    "addr:street":"Concourse Dr Ste 42 San Jose",
    "iso:country":"US",
    "sg:address":"2050 Concourse Dr Ste 42",
    "sg:city":"San Jose",
    "sg:classifiers":[
        {
            "category":"Education",
            "subcategory":"School",
            "type":"Public Place"
        }
    ],
    "sg:phone":"+1 408 456 6978",
    "sg:postcode":"95131",
    "sg:province":"CA",
    "wof:name":"Little Flocks Education Development Center",
    "wof:placetype":"venue"
},
  "geometry": {"coordinates":[-121.89074599999999,37.396917],"type":"Point"}
}