{
  "type": "Feature",
  "properties": {
    "iso:country":"US",
    "sg:address":"73900 el Paseo",
    "sg:city":"Palm Desert",
    "sg:classifiers":[
        {
            "category":"Shopping",
            "subcategory":"Jewelry",
            "type":"Retail Goods"
        }
    ],
    "sg:phone":"+1 760 340 9008",
    "sg:postcode":"92260",
    "sg:province":"CA",
    "wof:name":"HM Young Jewelers",
    "wof:placetype":"venue"
},
  "geometry": {"coordinates":[-116.373758,33.719817],"type":"Point"}
}