{
  "type": "Feature",
  "properties": {
    "iso:country":"US",
    "sg:address":"101 1st St",
    "sg:city":"Los Altos",
    "sg:classifiers":[
        {
            "category":"Building & Trades",
            "subcategory":"Landscaping Services",
            "type":"Services"
        }
    ],
    "sg:phone":"+1 831 425 4769",
    "sg:postcode":"94022",
    "sg:province":"CA",
    "sg:tags":[
        "landscape"
    ],
    "wof:name":"Barbara Bernie Ldscp Design",
    "wof:placetype":"venue"
},
  "geometry": {"coordinates":[-122.11867,37.37903],"type":"Point"}
}