{
  "type": "Feature",
  "properties": {
    "iso:country":"US",
    "sg:address":"3937 9th Ave",
    "sg:city":"San Diego",
    "sg:classifiers":[
        {
            "category":"Health Services",
            "subcategory":"Health Practitioner",
            "type":"Services"
        }
    ],
    "sg:phone":"+1 619 574 0677",
    "sg:postcode":"92103",
    "sg:province":"CA",
    "sg:tags":[
        "psychotherapist"
    ],
    "wof:name":"Kathy Gilbert",
    "wof:placetype":"venue"
},
  "geometry": {"coordinates":[-117.156288,32.749224],"type":"Point"}
}