{
  "type": "Feature",
  "properties": {
    "iso:country":"US",
    "sg:address":"13141 Riverside Dr",
    "sg:city":"Sherman Oaks",
    "sg:classifiers":[
        {
            "category":"Building & Trades",
            "subcategory":"Construction",
            "type":"Services"
        }
    ],
    "sg:phone":"+1 818 905 1296",
    "sg:postcode":"91423",
    "sg:province":"CA",
    "sg:tags":[
        "residential"
    ],
    "wof:name":"Pcs Properties",
    "wof:placetype":"venue"
},
  "geometry": {"coordinates":[-118.419231,34.157613],"type":"Point"}
}