{
  "type": "Feature",
  "properties": {
    "addr:full":"1730 Great Hwy San Francisco CA 94122",
    "addr:housenumber":"1730",
    "addr:postcode":"94122",
    "addr:street":"Great Hwy",
    "iso:country":"US",
    "sg:address":"1730 Great Hwy",
    "sg:city":"San Francisco",
    "sg:classifiers":[
        {
            "category":"Education",
            "subcategory":"Music School",
            "type":"Public Place"
        },
        {
            "category":"Education",
            "subcategory":"Special Training",
            "type":"Public Place"
        }
    ],
    "sg:phone":"+1 650 468 4084",
    "sg:postcode":"94122",
    "sg:province":"CA",
    "sg:tags":[
        "instrument",
        "musical",
        "specialty",
        "teacher"
    ],
    "wof:name":"Drumming, Meditation, And Learning To Flow",
    "wof:placetype":"venue"
},
  "geometry": {"coordinates":[-122.50829400000001,37.754083],"type":"Point"}
}