{
  "type": "Feature",
  "properties": {
    "addr:full":"710 N Beach Blvd La Habra CA 90631",
    "addr:housenumber":"710",
    "addr:postcode":"90631",
    "addr:street":"N Beach Blvd",
    "iso:country":"US",
    "sg:address":"710 N Beach Blvd",
    "sg:city":"La Habra",
    "sg:classifiers":[
        {
            "category":"Home & Garden",
            "subcategory":"Hardware",
            "type":"Retail Goods"
        }
    ],
    "sg:phone":"+1 562 691 1711",
    "sg:postcode":"90631",
    "sg:province":"CA",
    "wof:name":"James Hardware",
    "wof:placetype":"venue"
},
  "geometry": {"coordinates":[-117.967989,33.939658],"type":"Point"}
}