{
  "type": "Feature",
  "properties": {
    "addr:full":"967 N Elmwood Ave Rialto CA 92376",
    "addr:housenumber":"967",
    "addr:postcode":"92376",
    "addr:street":"N Elmwood Ave",
    "iso:country":"US",
    "sg:address":"967 N Elmwood Ave",
    "sg:city":"Rialto",
    "sg:classifiers":[
        {
            "category":"Professional",
            "subcategory":"Business Services",
            "type":"Services"
        }
    ],
    "sg:phone":"+1 909 875 5008",
    "sg:postcode":"92376",
    "sg:province":"CA",
    "sg:tags":[
        "inspection"
    ],
    "wof:name":"L M Home Inspection Svc",
    "wof:placetype":"venue"
},
  "geometry": {"coordinates":[-117.39263,34.117085],"type":"Point"}
}