{
  "type": "Feature",
  "properties": {
    "iso:country":"US",
    "sg:address":"300 N Lake Ave",
    "sg:city":"Pasadena",
    "sg:classifiers":[
        {
            "category":"Banks & Credit Unions",
            "subcategory":"Investment Brokerage",
            "type":"Services"
        }
    ],
    "sg:phone":"+1 626 449 7406",
    "sg:postcode":"91101",
    "sg:province":"CA",
    "sg:tags":[
        "security"
    ],
    "sg:website":"www.agedwards.com",
    "wof:name":"A G Edwards & Sons Inc",
    "wof:placetype":"venue"
},
  "geometry": {"coordinates":[-118.13233200000001,34.150937],"type":"Point"}
}