{
  "type": "Feature",
  "properties": {
    "iso:country":"US",
    "sg:address":"103 Washington Blvd",
    "sg:city":"Marina Del Rey",
    "sg:classifiers":[
        {
            "category":"Shopping",
            "subcategory":"Gifts & Souvenirs",
            "type":"Retail Goods"
        }
    ],
    "sg:phone":"+1 310 301 2464",
    "sg:postcode":"90292",
    "sg:province":"CA",
    "wof:name":"Girl From Ipanema",
    "wof:placetype":"venue"
},
  "geometry": {"coordinates":[-118.465355,33.97998],"type":"Point"}
}