{
  "type": "Feature",
  "properties": {
    "addr:full":"103 Washington Blvd Marina Del Rey CA 90292",
    "addr:housenumber":"103",
    "addr:postcode":"90292",
    "addr:street":"Washington Blvd",
    "iso:country":"US",
    "sg:address":"103 Washington Blvd",
    "sg:city":"Marina Del Rey",
    "sg:classifiers":[
        {
            "category":"Shopping",
            "subcategory":"Gifts & Souvenirs",
            "type":"Retail Goods"
        }
    ],
    "sg:phone":"+1 310 301 2464",
    "sg:postcode":"90292",
    "sg:province":"CA",
    "wof:name":"Girl From Ipanema",
    "wof:placetype":"venue"
},
  "geometry": {"coordinates":[-118.465355,33.97998],"type":"Point"}
}