{
  "type": "Feature",
  "properties": {
    "addr:full":"1649 Martin Luther King Jr Way Berkeley CA 94709",
    "addr:housenumber":"1649",
    "addr:postcode":"94709",
    "addr:street":"Martin Luther King Jr Way",
    "iso:country":"US",
    "sg:address":"1649 Martin Luther King Jr Way",
    "sg:city":"Berkeley",
    "sg:classifiers":[
        {
            "category":"Taxi",
            "type":"Transportation"
        }
    ],
    "sg:phone":"+1 510 843 1111",
    "sg:postcode":"94709",
    "sg:province":"CA",
    "wof:name":"Yellow A-1 Cab Company",
    "wof:placetype":"venue"
},
  "geometry": {"coordinates":[-122.273343,37.876261],"type":"Point"}
}