{
  "type": "Feature",
  "properties": {
    "iso:country":"US",
    "sg:address":"13320 Cam Canada",
    "sg:city":"El Cajon",
    "sg:classifiers":[
        {
            "category":"Shopping",
            "type":"Retail Goods"
        }
    ],
    "sg:phone":"+1 619 443 1630",
    "sg:postcode":"92021",
    "sg:province":"CA",
    "sg:tags":[
        "cosmetic",
        "perfume"
    ],
    "wof:name":"Novier Independent Consultant",
    "wof:placetype":"venue"
},
  "geometry": {"coordinates":[-116.900395,32.827325],"type":"Point"}
}