{
  "type": "Feature",
  "properties": {
    "addr:full":"111 W 5th St Los Angeles CA 90013",
    "addr:housenumber":"111",
    "addr:postcode":"90013",
    "addr:street":"W 5Th St",
    "iso:country":"US",
    "sg:address":"111 W 5th St",
    "sg:city":"Los Angeles",
    "sg:classifiers":[
        {
            "category":"Real Estate",
            "subcategory":"Real Estate Operator",
            "type":"Services"
        }
    ],
    "sg:phone":"+1 213 689 9687",
    "sg:postcode":"90013",
    "sg:province":"CA",
    "sg:tags":[
        "building",
        "operation",
        "apartment"
    ],
    "wof:name":"Frontier Hotel",
    "wof:placetype":"venue"
},
  "geometry": {"coordinates":[-118.248949,34.047034],"type":"Point"}
}