{
  "type": "Feature",
  "properties": {
    "addr:full":"16727 Gazeley St Canyon Country CA 91351",
    "addr:postcode":"16727;91351",
    "addr:street":"Gazeley St",
    "iso:country":"US",
    "sg:address":"16727 Gazeley St",
    "sg:city":"Canyon Country",
    "sg:classifiers":[
        {
            "category":"Organizations",
            "subcategory":"Religious Organization",
            "type":"Services"
        }
    ],
    "sg:phone":"+1 661 298 4446",
    "sg:postcode":"91351",
    "sg:province":"CA",
    "sg:tags":[
        "church"
    ],
    "wof:name":"Vessels Of Harvest Ministry",
    "wof:placetype":"venue"
},
  "geometry": {"coordinates":[-118.42732100000001,34.448985],"type":"Point"}
}