{
  "type": "Feature",
  "properties": {
    "addr:full":"6157 Lakewood Blvd Lakewood CA 90712",
    "addr:housenumber":"6157",
    "addr:postcode":"90712",
    "addr:street":"Lakewood Blvd",
    "iso:country":"US",
    "sg:address":"6157 Lakewood Blvd",
    "sg:city":"Lakewood",
    "sg:classifiers":[
        {
            "category":"Manufacturing",
            "subcategory":"Tools & Machinery",
            "type":"Manufacturing & Wholesale Goods"
        }
    ],
    "sg:phone":"+1 562 531 3593",
    "sg:postcode":"90712",
    "sg:province":"CA",
    "sg:tags":[
        "bio",
        "product",
        "mfg"
    ],
    "wof:name":"Randox Laboratories Ltd",
    "wof:placetype":"venue"
},
  "geometry": {"coordinates":[-118.14260299999999,33.8667],"type":"Point"}
}