{
  "type": "Feature",
  "properties": {
    "addr:full":"7000 Hollywood Blvd Los Angeles CA 90028",
    "addr:housenumber":"7000",
    "addr:postcode":"90028",
    "addr:street":"Hollywood Blvd",
    "iso:country":"US",
    "sg:address":"7000 Hollywood Blvd",
    "sg:city":"Los Angeles",
    "sg:classifiers":[
        {
            "category":"Organizations",
            "subcategory":"Professional Association",
            "type":"Services"
        }
    ],
    "sg:phone":"+1 323 464 7616",
    "sg:postcode":"90028",
    "sg:province":"CA",
    "wof:name":"NAACP",
    "wof:placetype":"venue"
},
  "geometry": {"coordinates":[-118.34173699999999,34.101538],"type":"Point"}
}