{
  "type": "Feature",
  "properties": {
    "addr:full":"2666 Homestead Rd Santa Clara CA 95051",
    "addr:housenumber":"2666",
    "addr:postcode":"95051",
    "addr:street":"Homestead Rd",
    "iso:country":"US",
    "sg:address":"2666 Homestead Rd",
    "sg:city":"Santa Clara",
    "sg:classifiers":[
        {
            "category":"Shopping",
            "subcategory":"Baby Store",
            "type":"Retail Goods"
        },
        {
            "category":"Shopping",
            "subcategory":"Clothing, Apparel, & Fashions",
            "type":"Retail Goods"
        },
        {
            "category":"Shopping",
            "subcategory":"Thrift Store",
            "type":"Retail Goods"
        }
    ],
    "sg:phone":"+1 408 244 2248",
    "sg:postcode":"95051",
    "sg:province":"CA",
    "sg:tags":[
        "children's",
        "clothing",
        "gear",
        "furniture"
    ],
    "sg:website":"santaclara.kidtokid.com/",
    "wof:name":"Kid to Kid",
    "wof:placetype":"venue"
},
  "geometry": {"coordinates":[-121.97386299999999,37.339267],"type":"Point"}
}