{
  "type": "Feature",
  "properties": {
    "iso:country":"US",
    "sg:address":"18050 Woodland Ave",
    "sg:city":"Morgan Hill",
    "sg:classifiers":[
        {
            "category":"Real Estate",
            "subcategory":"Real Estate Agent",
            "type":"Services"
        }
    ],
    "sg:phone":"+1 408 778 7325",
    "sg:postcode":"95037",
    "sg:province":"CA",
    "wof:name":"H & H Realty",
    "wof:placetype":"venue"
},
  "geometry": {"coordinates":[-121.687092,37.121976],"type":"Point"}
}