{
  "type": "Feature",
  "properties": {
    "iso:country":"US",
    "sg:address":"214 S Fetterly Ave",
    "sg:city":"Los Angeles",
    "sg:classifiers":[
        {
            "category":"Government",
            "subcategory":"Court House",
            "type":"Public Place"
        }
    ],
    "sg:phone":"+1 323 780 2064",
    "sg:postcode":"90022",
    "sg:province":"CA",
    "sg:tags":[
        "legal"
    ],
    "wof:name":"Public Defender",
    "wof:placetype":"venue"
},
  "geometry": {"coordinates":[-118.160842,34.034889],"type":"Point"}
}