{
  "type": "Feature",
  "properties": {
    "addr:full":"25 Sunfish Irvine CA 92604",
    "addr:housenumber":"25",
    "addr:postcode":"92604",
    "addr:street":"Sunfish",
    "iso:country":"US",
    "sg:address":"25 Sunfish",
    "sg:city":"Irvine",
    "sg:classifiers":[
        {
            "category":"Professional",
            "type":"Services"
        }
    ],
    "sg:phone":"+1 949 552 3773",
    "sg:postcode":"92604",
    "sg:province":"CA",
    "wof:name":"Leslie E Wise A Professional",
    "wof:placetype":"venue"
},
  "geometry": {"coordinates":[-117.78908,33.684439],"type":"Point"}
}