{
  "type": "Feature",
  "properties": {
    "addr:full":"1844 W 11th St Ste C Upland CA 91786",
    "addr:housenumber":"1844",
    "addr:postcode":"91786",
    "addr:street":"W 11Th St Ste C",
    "iso:country":"US",
    "sg:address":"1844 W 11th St Ste C",
    "sg:city":"Upland",
    "sg:classifiers":[
        {
            "category":"Communications",
            "subcategory":"Film & Video Production",
            "type":"Services"
        }
    ],
    "sg:phone":"+1 909 949 4316",
    "sg:postcode":"91786",
    "sg:province":"CA",
    "sg:tags":[
        "recording",
        "service-sound"
    ],
    "wof:name":"Rfb&D",
    "wof:placetype":"venue"
},
  "geometry": {"coordinates":[-117.686305,34.10323],"type":"Point"}
}