{
  "type": "Feature",
  "properties": {
    "addr:full":"2873 Octavia St San Francisco CA 94123",
    "addr:housenumber":"2873",
    "addr:postcode":"94123",
    "addr:street":"Octavia St",
    "iso:country":"US",
    "sg:address":"2873 Octavia St",
    "sg:city":"San Francisco",
    "sg:classifiers":[
        {
            "category":"Personal",
            "subcategory":"Beauty Salon",
            "type":"Services"
        }
    ],
    "sg:phone":"+1 415 928 1139",
    "sg:postcode":"94123",
    "sg:province":"CA",
    "sg:tags":[
        "hair"
    ],
    "wof:name":"Clip Art Hair Design",
    "wof:placetype":"venue"
},
  "geometry": {"coordinates":[-122.429092,37.798705],"type":"Point"}
}