{
  "type": "Feature",
  "properties": {
    "addr:full":"3028 N Sunnyside Ave Fresno CA 93727",
    "addr:housenumber":"3028",
    "addr:postcode":"93727",
    "addr:street":"N Sunnyside Ave",
    "iso:country":"US",
    "sg:address":"3028 N Sunnyside Ave",
    "sg:city":"Fresno",
    "sg:classifiers":[
        {
            "category":"Shopping",
            "subcategory":"Computers & Home Electronics",
            "type":"Retail Goods"
        }
    ],
    "sg:phone":"+1 559 490 7777",
    "sg:postcode":"93727",
    "sg:province":"CA",
    "sg:tags":[
        "equipment",
        "satellite",
        "system"
    ],
    "wof:name":"California Satellite",
    "wof:placetype":"venue"
},
  "geometry": {"coordinates":[-119.69161,36.777922],"type":"Point"}
}