{
  "type": "Feature",
  "properties": {
    "iso:country":"US",
    "sg:address":"21101 Sherman Way",
    "sg:city":"Canoga Park",
    "sg:classifiers":[
        {
            "category":"Restaurant",
            "type":"Food & Drink"
        }
    ],
    "sg:phone":"+1 818 887 0445",
    "sg:postcode":"91303",
    "sg:province":"CA",
    "sg:tags":[
        "chinese"
    ],
    "wof:name":"Royal Dragon Chinese Restaurant",
    "wof:placetype":"venue"
},
  "geometry": {"coordinates":[-118.593002,34.200901],"type":"Point"}
}