{
  "type": "Feature",
  "properties": {
    "iso:country":"US",
    "sg:address":"1608 Saint Andrews Dr",
    "sg:city":"Yuba City",
    "sg:classifiers":[
        {
            "category":"Freight",
            "type":"Transportation"
        }
    ],
    "sg:phone":"+1 530 671 5589",
    "sg:postcode":"95993",
    "sg:province":"CA",
    "sg:tags":[
        "operator",
        "local",
        "trucking"
    ],
    "wof:name":"Hundal Trucking Ranjit Hu",
    "wof:placetype":"venue"
},
  "geometry": {"coordinates":[-121.645068,39.103761],"type":"Point"}
}