{
  "type": "Feature",
  "properties": {
    "addr:full":"1608 Saint Andrews Dr Yuba City CA 95993",
    "addr:housenumber":"1608",
    "addr:postcode":"95993",
    "addr:street":"Saint Andrews Dr",
    "iso:country":"US",
    "sg:address":"1608 Saint Andrews Dr",
    "sg:city":"Yuba City",
    "sg:classifiers":[
        {
            "category":"Freight",
            "type":"Transportation"
        }
    ],
    "sg:phone":"+1 530 671 5589",
    "sg:postcode":"95993",
    "sg:province":"CA",
    "sg:tags":[
        "operator",
        "local",
        "trucking"
    ],
    "wof:name":"Hundal Trucking Ranjit Hu",
    "wof:placetype":"venue"
},
  "geometry": {"coordinates":[-121.64506799999999,39.103761],"type":"Point"}
}