{
  "type": "Feature",
  "properties": {
    "addr:full":"1265 Commercial Ave Oxnard CA 93030",
    "addr:housenumber":"1265",
    "addr:postcode":"93030",
    "addr:street":"Commercial Ave",
    "iso:country":"US",
    "sg:address":"1265 Commercial Ave",
    "sg:city":"Oxnard",
    "sg:classifiers":[
        {
            "category":"Manufacturing",
            "subcategory":"Tools & Machinery",
            "type":"Manufacturing & Wholesale Goods"
        }
    ],
    "sg:phone":"+1 805 486 8444",
    "sg:postcode":"93030",
    "sg:province":"CA",
    "sg:tags":[
        "farm",
        "equipment"
    ],
    "wof:name":"Ventura Manufacturing Co",
    "wof:placetype":"venue"
},
  "geometry": {"coordinates":[-119.17115099999999,34.189447],"type":"Point"}
}