{
  "type": "Feature",
  "properties": {
    "addr:full":"1701 Lundy Ave STe 160 San Jose CA 95131",
    "addr:housenumber":"1701",
    "addr:postcode":"95131",
    "addr:street":"Lundy Ave Ste 160",
    "iso:country":"US",
    "sg:address":"1701 Lundy Ave STe 160",
    "sg:city":"San Jose",
    "sg:classifiers":[
        {
            "category":"Coffee & Tea",
            "type":"Food & Drink"
        }
    ],
    "sg:phone":"+1 408 573 8208",
    "sg:postcode":"95131",
    "sg:province":"CA",
    "wof:name":"Cafe 97",
    "wof:placetype":"venue"
},
  "geometry": {"coordinates":[-121.88744199999999,37.387055],"type":"Point"}
}