{
  "type": "Feature",
  "properties": {
    "addr:full":"Pier 40 Embarcadero San Francisco CA 94107",
    "addr:housenumber":40,
    "addr:postcode":"94107",
    "addr:street":"Embarcadero",
    "iso:country":"US",
    "sg:address":"Pier 40 Embarcadero",
    "sg:city":"San Francisco",
    "sg:classifiers":[
        {
            "category":"Restaurant",
            "type":"Food & Drink"
        }
    ],
    "sg:menulink":"http://www.allmenus.com/ca/san-francisco/93933-java-house/menu/",
    "sg:phone":"+1 415 495 7260",
    "sg:postcode":"94107",
    "sg:province":"CA",
    "sg:tags":[
        "american"
    ],
    "wof:name":"Java House",
    "wof:placetype":"venue"
},
  "geometry": {"coordinates":[-122.388597,37.782655],"type":"Point"}
}