{
  "type": "Feature",
  "properties": {
    "addr:full":"640 S Hill St Los Angeles CA 90014",
    "addr:housenumber":"640",
    "addr:postcode":"90014",
    "addr:street":"S Hill St",
    "iso:country":"US",
    "sg:address":"640 S Hill St",
    "sg:city":"Los Angeles",
    "sg:classifiers":[
        {
            "category":"Wholesale",
            "subcategory":"Jewelry",
            "type":"Manufacturing & Wholesale Goods"
        }
    ],
    "sg:phone":"+1 213 362 0888",
    "sg:postcode":"90014",
    "sg:province":"CA",
    "sg:tags":[
        "stone",
        "jeweler"
    ],
    "wof:name":"Waddy Jewelry Co Ltd",
    "wof:placetype":"venue"
},
  "geometry": {"coordinates":[-118.253936,34.046449],"type":"Point"}
}