{
  "type": "Feature",
  "properties": {
    "addr:full":"92 Corporate Park Irvine CA 92606",
    "addr:housenumber":"92",
    "addr:postcode":"92606",
    "addr:street":"Corporate Park",
    "iso:country":"US",
    "sg:address":"92 Corporate Park",
    "sg:city":"Irvine",
    "sg:classifiers":[
        {
            "category":"Donuts",
            "subcategory":"None",
            "type":"Food & Drink"
        }
    ],
    "sg:phone":"+1 949 660 1807",
    "sg:postcode":"92606",
    "sg:province":"CA",
    "wof:name":"Jannys Donuts",
    "wof:placetype":"venue"
},
  "geometry": {"coordinates":[-117.82652400000001,33.692299],"type":"Point"}
}