{
  "type": "Feature",
  "properties": {
    "iso:country":"US",
    "sg:address":"148 Elm Ave",
    "sg:city":"San Bruno",
    "sg:classifiers":[
        {
            "category":"Retail",
            "subcategory":"Animal Services",
            "type":"Services"
        }
    ],
    "sg:phone":"+1 650 834 2063",
    "sg:postcode":"94066",
    "sg:province":"CA",
    "sg:tags":[
        "pet"
    ],
    "wof:name":"Bay Area Aquaria",
    "wof:placetype":"venue"
},
  "geometry": {"coordinates":[-122.409701,37.615619],"type":"Point"}
}