{
  "type": "Feature",
  "properties": {
    "iso:country":"US",
    "sg:address":"10525 S Broadway",
    "sg:city":"Los Angeles",
    "sg:classifiers":[
        {
            "category":"Organizations",
            "subcategory":"Religious Organization",
            "type":"Services"
        }
    ],
    "sg:phone":"+1 323 756 9561",
    "sg:postcode":"90003",
    "sg:province":"CA",
    "sg:tags":[
        "church"
    ],
    "wof:name":"Sunflower Baptist Church",
    "wof:placetype":"venue"
},
  "geometry": {"coordinates":[-118.27821900000001,33.940329],"type":"Point"}
}