{
  "type": "Feature",
  "properties": {
    "iso:country":"US",
    "sg:address":"4847 Broadwater Dr",
    "sg:city":"Sacramento",
    "sg:classifiers":[
        {
            "category":"Wholesale",
            "subcategory":"Non-durable Goods",
            "type":"Manufacturing & Wholesale Goods"
        }
    ],
    "sg:phone":"+1 916 928 4358",
    "sg:postcode":"95835",
    "sg:province":"CA",
    "wof:name":"Wakata Trading",
    "wof:placetype":"venue"
},
  "geometry": {"coordinates":[-121.52511199999999,38.662514],"type":"Point"}
}