{
  "type": "Feature",
  "properties": {
    "iso:country":"US",
    "sg:address":"11520 Telegraph Rd",
    "sg:city":"Santa Fe Springs",
    "sg:classifiers":[
        {
            "category":"Retail",
            "subcategory":"Repair Shop",
            "type":"Services"
        }
    ],
    "sg:phone":"+1 562 864 2533",
    "sg:postcode":"90670",
    "sg:province":"CA",
    "sg:tags":[
        "jewelry"
    ],
    "wof:name":"Irma's Jewels",
    "wof:placetype":"venue"
},
  "geometry": {"coordinates":[-118.086348,33.947359],"type":"Point"}
}