{
  "type": "Feature",
  "properties": {
    "addr:full":"14811 E 14th Street San Leandro CA 94578",
    "addr:housenumber":"14811",
    "addr:postcode":"94578",
    "addr:street":"E 14Th Street",
    "iso:country":"US",
    "sg:address":"14811 E 14th Street",
    "sg:city":"San Leandro",
    "sg:classifiers":[
        {
            "category":"Home & Garden",
            "subcategory":"Carpets & Floor Coverings",
            "type":"Retail Goods"
        }
    ],
    "sg:phone":"+1 510 614 8019",
    "sg:postcode":"94578",
    "sg:province":"CA",
    "sg:tags":[
        "mattress"
    ],
    "sg:website":"www.bpmatt.com",
    "wof:name":"Best Price Mattress",
    "wof:placetype":"venue"
},
  "geometry": {"coordinates":[-122.133596,37.708213],"type":"Point"}
}