{
  "type": "Feature",
  "properties": {
    "addr:full":"7998 Mission Center Ct San Diego CA 92108",
    "addr:housenumber":"7998",
    "addr:postcode":"92108",
    "addr:street":"Mission Center Ct",
    "iso:country":"US",
    "sg:address":"7998 Mission Center Ct",
    "sg:city":"San Diego",
    "sg:classifiers":[
        {
            "category":"Real Estate",
            "subcategory":"Real Estate Operator",
            "type":"Services"
        }
    ],
    "sg:phone":"+1 858 569 1793",
    "sg:postcode":"92108",
    "sg:province":"CA",
    "sg:tags":[
        "apartment"
    ],
    "sg:website":"www.parkvillasnorth.com",
    "wof:name":"Park Villas North Condominium Association",
    "wof:placetype":"venue"
},
  "geometry": {"coordinates":[-117.151527,32.773181],"type":"Point"}
}