{
  "type": "Feature",
  "properties": {
    "addr:full":"5931 Reseda Blvd Tarzana CA 91356",
    "addr:housenumber":"5931",
    "addr:postcode":"91356",
    "addr:street":"Reseda Blvd",
    "iso:country":"US",
    "sg:address":"5931 Reseda Blvd",
    "sg:city":"Tarzana",
    "sg:classifiers":[
        {
            "category":"Professional",
            "type":"Services"
        }
    ],
    "sg:phone":"+1 818 344 8488",
    "sg:postcode":"91356",
    "sg:province":"CA",
    "wof:name":"Terraces At Boulevard",
    "wof:placetype":"venue"
},
  "geometry": {"coordinates":[-118.53608699999999,34.179224],"type":"Point"}
}