{
  "type": "Feature",
  "properties": {
    "addr:full":"13455 Brooks Dr Baldwin Park CA 91706",
    "addr:housenumber":"13455",
    "addr:postcode":"91706",
    "addr:street":"Brooks Dr",
    "iso:country":"US",
    "sg:address":"13455 Brooks Dr",
    "sg:city":"Baldwin Park",
    "sg:classifiers":[
        {
            "category":"Manufacturing",
            "subcategory":"Metals",
            "type":"Manufacturing & Wholesale Goods"
        }
    ],
    "sg:phone":"+1 626 856 8979",
    "sg:postcode":"91706",
    "sg:province":"CA",
    "sg:tags":[
        "coating"
    ],
    "wof:name":"Front Edge Technology Inc",
    "wof:placetype":"venue"
},
  "geometry": {"coordinates":[-117.981973,34.098451],"type":"Point"}
}