{
  "type": "Feature",
  "properties": {
    "iso:country":"US",
    "sg:address":"23542 Lyons Ave Ste 207",
    "sg:city":"Santa Clarita",
    "sg:classifiers":[
        {
            "category":"Insurance",
            "subcategory":"Hazard Insurance",
            "type":"Services"
        }
    ],
    "sg:phone":"+1 661 222 7999",
    "sg:postcode":"91321",
    "sg:province":"CA",
    "wof:name":"Halverson Insurance Services",
    "wof:placetype":"venue"
},
  "geometry": {"coordinates":[-118.546324,34.379318],"type":"Point"}
}