{
  "type": "Feature",
  "properties": {
    "iso:country":"US",
    "sg:address":"30872 S Coast Hwy",
    "sg:city":"Laguna Beach",
    "sg:classifiers":[
        {
            "category":"Mining & Drilling",
            "type":"Manufacturing & Wholesale Goods"
        }
    ],
    "sg:phone":"+1 949 376 9366",
    "sg:postcode":"92651",
    "sg:province":"CA",
    "sg:tags":[
        "field",
        "diamond",
        "gas"
    ],
    "wof:name":"Baytown Energy Corp",
    "wof:placetype":"venue"
},
  "geometry": {"coordinates":[-117.756862,33.515882],"type":"Point"}
}