{
  "type": "Feature",
  "properties": {
    "iso:country":"US",
    "sg:address":"1933 Laredo Ct",
    "sg:city":"Stockton",
    "sg:classifiers":[
        {
            "category":"Professional",
            "type":"Services"
        }
    ],
    "sg:phone":"+1 209 474 8342",
    "sg:postcode":"95209",
    "sg:province":"CA",
    "wof:name":"Hmmr",
    "wof:placetype":"venue"
},
  "geometry": {"coordinates":[-121.336411,38.04013],"type":"Point"}
}