{
  "type": "Feature",
  "properties": {
    "iso:country":"US",
    "sg:address":"9333 Baseline Rd",
    "sg:city":"Rancho Cucamonga",
    "sg:classifiers":[
        {
            "category":"Real Estate",
            "subcategory":"Real Estate Agent",
            "type":"Services"
        }
    ],
    "sg:phone":"+1 909 945 5151",
    "sg:postcode":"91730",
    "sg:province":"CA",
    "wof:name":"Infinity Real Estate",
    "wof:placetype":"venue"
},
  "geometry": {"coordinates":[-117.601059,34.121467],"type":"Point"}
}