{
  "type": "Feature",
  "properties": {
    "iso:country":"US",
    "sg:address":"2582 W Beechwood Ave",
    "sg:city":"Fresno",
    "sg:classifiers":[
        {
            "category":"Manufacturing",
            "subcategory":"Retail Goods",
            "type":"Manufacturing & Wholesale Goods"
        }
    ],
    "sg:phone":"+1 415 648 1320",
    "sg:postcode":"93711",
    "sg:province":"CA",
    "sg:tags":[
        "manufacturer"
    ],
    "wof:name":"Aspen Leaf",
    "wof:placetype":"venue"
},
  "geometry": {"coordinates":[-119.836824,36.838274],"type":"Point"}
}