{
  "type": "Feature",
  "properties": {
    "iso:country":"US",
    "sg:address":"2652 Marconi Ave",
    "sg:city":"Sacramento",
    "sg:classifiers":[
        {
            "category":"Sports & Exercise",
            "subcategory":"Gym",
            "type":"Entertainment"
        },
        {
            "category":"Arena",
            "subcategory":"Sports Club",
            "type":"Entertainment"
        }
    ],
    "sg:phone":"+1 916 481 6815",
    "sg:postcode":"95821",
    "sg:province":"CA",
    "sg:tags":[
        "trainer",
        "martial art"
    ],
    "sg:website":"www.robinsonstkd.com",
    "wof:name":"Robinson's Taekwondo",
    "wof:placetype":"venue"
},
  "geometry": {"coordinates":[-121.400021,38.617937],"type":"Point"}
}