{
  "type": "Feature",
  "properties": {
    "iso:country":"US",
    "sg:address":"4328 Eagle Rock Blvd",
    "sg:city":"Los Angeles",
    "sg:classifiers":[
        {
            "category":"Building & Trades",
            "subcategory":"Construction",
            "type":"Services"
        }
    ],
    "sg:phone":"+1 323 256 5913",
    "sg:postcode":"90041",
    "sg:province":"CA",
    "sg:tags":[
        "roofing",
        "contractor"
    ],
    "wof:name":"Empire Contracting Roof Svc",
    "wof:placetype":"venue"
},
  "geometry": {"coordinates":[-118.22216,34.123276],"type":"Point"}
}