{
  "type": "Feature",
  "properties": {
    "iso:country":"US",
    "sg:address":"23510 Crenshaw Blvd",
    "sg:city":"Torrance",
    "sg:classifiers":[
        {
            "category":"Retail",
            "subcategory":"Auto Repair",
            "type":"Services"
        }
    ],
    "sg:phone":"+1 310 534 3451",
    "sg:postcode":"90505",
    "sg:province":"CA",
    "wof:name":"Express Smog Check Repair",
    "wof:placetype":"venue"
},
  "geometry": {"coordinates":[-118.327894,33.812605],"type":"Point"}
}