{
  "type": "Feature",
  "properties": {
    "iso:country":"US",
    "sg:address":"5640 District Blvd",
    "sg:city":"Bakersfield",
    "sg:classifiers":[
        {
            "category":"Farming",
            "subcategory":"Farm & Veterinary Services",
            "type":"Manufacturing & Wholesale Goods"
        }
    ],
    "sg:phone":"+1 661 664 7698",
    "sg:postcode":"93313",
    "sg:province":"CA",
    "sg:tags":[
        "control",
        "weed"
    ],
    "wof:name":"Grass Roots",
    "wof:placetype":"venue"
},
  "geometry": {"coordinates":[-119.065252,35.313133],"type":"Point"}
}