{
  "type": "Feature",
  "properties": {
    "addr:full":"1316 N Hacienda Blvd La Puente CA 91744",
    "addr:housenumber":"1316",
    "addr:postcode":"91744",
    "addr:street":"N Hacienda Blvd",
    "iso:country":"US",
    "sg:address":"1316 N Hacienda Blvd",
    "sg:city":"La Puente",
    "sg:classifiers":[
        {
            "category":"Personal",
            "type":"Services"
        }
    ],
    "sg:phone":"+1 626 919 1640",
    "sg:postcode":"91744",
    "sg:province":"CA",
    "sg:tags":[
        "wear",
        "formal"
    ],
    "wof:name":"Casino's Tux Shop",
    "wof:placetype":"venue"
},
  "geometry": {"coordinates":[-117.94915,34.043985],"type":"Point"}
}