{
  "type": "Feature",
  "properties": {
    "iso:country":"US",
    "sg:address":"25582 Via Velador",
    "sg:city":"Valencia",
    "sg:classifiers":[
        {
            "category":"Professional",
            "subcategory":"Accounting & Tax Preparation",
            "type":"Services"
        }
    ],
    "sg:phone":"+1 661 255 0685",
    "sg:postcode":"91355",
    "sg:province":"CA",
    "sg:tags":[
        "accountant"
    ],
    "wof:name":"Arthur F Collins CPA",
    "wof:placetype":"venue"
},
  "geometry": {"coordinates":[-118.55772,34.38485],"type":"Point"}
}