{
  "type": "Feature",
  "properties": {
    "addr:full":"12864 Via Esperia Del Mar CA 92014",
    "addr:housenumber":"12864",
    "addr:postcode":"92014",
    "addr:street":"Via Esperia",
    "iso:country":"US",
    "sg:address":"12864 Via Esperia",
    "sg:city":"Del Mar",
    "sg:classifiers":[
        {
            "category":"Professional",
            "subcategory":"Advertising",
            "type":"Services"
        }
    ],
    "sg:phone":"+1 858 755 1079",
    "sg:postcode":"92014",
    "sg:province":"CA",
    "sg:website":"www.epuppet.com",
    "wof:name":"Lawrence Technology Marketing",
    "wof:placetype":"venue"
},
  "geometry": {"coordinates":[-117.25154999999999,32.93281],"type":"Point"}
}