{
  "type": "Feature",
  "properties": {
    "addr:full":"192 S Main St Porterville CA 93257",
    "addr:housenumber":"192",
    "addr:postcode":"93257",
    "addr:street":"S Main St",
    "iso:country":"US",
    "sg:address":"192 S Main St",
    "sg:city":"Porterville",
    "sg:classifiers":[
        {
            "category":"Fast Food",
            "type":"Food & Drink"
        },
        {
            "category":"Restaurant",
            "type":"Food & Drink"
        },
        {
            "category":"Ice Cream",
            "type":"Food & Drink"
        }
    ],
    "sg:phone":"+1 559 784 1231",
    "sg:postcode":"93257",
    "sg:province":"CA",
    "sg:tags":[
        "frozen",
        "dessert",
        "hot",
        "hamburger",
        "dog"
    ],
    "sg:website":"http://www.fostersfreeze.com/",
    "wof:name":"Fosters Freeze",
    "wof:placetype":"venue"
},
  "geometry": {"coordinates":[-119.016509,36.062582],"type":"Point"}
}