{
  "type": "Feature",
  "properties": {
    "iso:country":"US",
    "sg:address":"12643 Imperial Hwy",
    "sg:city":"Santa Fe Springs",
    "sg:classifiers":[
        {
            "category":"Wholesale",
            "subcategory":"Auto Parts",
            "type":"Manufacturing & Wholesale Goods"
        }
    ],
    "sg:phone":"+1 562 692 7516",
    "sg:postcode":"90670",
    "sg:province":"CA",
    "sg:tags":[
        "automobile",
        "wrecking"
    ],
    "wof:name":"Santa Fe Auto Salvage Inc",
    "wof:placetype":"venue"
},
  "geometry": {"coordinates":[-118.060416,33.917094],"type":"Point"}
}