{
  "type": "Feature",
  "properties": {
    "iso:country":"US",
    "sg:address":"14618 Tyler Foote Rd",
    "sg:city":"Nevada City",
    "sg:classifiers":[
        {
            "category":"Building & Trades",
            "subcategory":"Construction",
            "type":"Services"
        }
    ],
    "sg:phone":"+1 530 478 7556",
    "sg:postcode":"95959",
    "sg:province":"CA",
    "sg:tags":[
        "contractor"
    ],
    "sg:website":"www.thecourse.org",
    "wof:name":"Ananda Design & Construction",
    "wof:placetype":"venue"
},
  "geometry": {"coordinates":[-121.046024,39.367682],"type":"Point"}
}