{
  "type": "Feature",
  "properties": {
    "iso:country":"US",
    "sg:address":"2015 Bywood Dr",
    "sg:city":"Oakland",
    "sg:classifiers":[
        {
            "category":"Professional",
            "subcategory":"Accounting & Tax Preparation",
            "type":"Services"
        }
    ],
    "sg:phone":"+1 510 531 1223",
    "sg:postcode":"94602",
    "sg:province":"CA",
    "sg:tags":[
        "return",
        "filing"
    ],
    "wof:name":"Tucker & Assoc Professional",
    "wof:placetype":"venue"
},
  "geometry": {"coordinates":[-122.208316,37.814126],"type":"Point"}
}