{
  "type": "Feature",
  "properties": {
    "addr:full":"11415 W Bernardo Ct San Diego CA 92127",
    "addr:housenumber":"11415",
    "addr:postcode":"92127",
    "addr:street":"W Bernardo Ct",
    "iso:country":"US",
    "sg:address":"11415 W Bernardo Ct",
    "sg:city":"San Diego",
    "sg:classifiers":[
        {
            "category":"Professional",
            "subcategory":"Lawyer & Legal Services",
            "type":"Services"
        }
    ],
    "sg:phone":"+1 858 487 3061",
    "sg:postcode":"92127",
    "sg:province":"CA",
    "sg:tags":[
        "attorney"
    ],
    "wof:name":"Ewing & Bowman Apc LAW Ofc",
    "wof:placetype":"venue"
},
  "geometry": {"coordinates":[-117.083375,33.021117],"type":"Point"}
}