{
  "type": "Feature",
  "properties": {
    "iso:country":"US",
    "sg:address":"10606 Trademark Pkwy N",
    "sg:city":"Rancho Cucamonga",
    "sg:classifiers":[
        {
            "category":"Professional",
            "subcategory":"Accounting & Tax Preparation",
            "type":"Services"
        }
    ],
    "sg:phone":"+1 909 989 5867",
    "sg:postcode":"91730",
    "sg:province":"CA",
    "sg:tags":[
        "accountant"
    ],
    "sg:website":"www.swensoncorp.com",
    "wof:name":"Swenson Corp",
    "wof:placetype":"venue"
},
  "geometry": {"coordinates":[-117.573405,34.08106],"type":"Point"}
}