{
  "type": "Feature",
  "properties": {
    "addr:full":"2401 National City Blvd National City CA 91950",
    "addr:housenumber":"2401",
    "addr:postcode":"91950",
    "addr:street":"National City Blvd",
    "iso:country":"US",
    "sg:address":"2401 National City Blvd",
    "sg:city":"National City",
    "sg:classifiers":[
        {
            "category":"Autos & Motor Vehicles",
            "subcategory":"Automobile Sales",
            "type":"Retail Goods"
        }
    ],
    "sg:phone":"+1 619 477 6677",
    "sg:postcode":"91950",
    "sg:province":"CA",
    "sg:tags":[
        "car",
        "dealer"
    ],
    "wof:name":"Kelly's Auto Ctr Inc",
    "wof:placetype":"venue"
},
  "geometry": {"coordinates":[-117.101206,32.661161],"type":"Point"}
}