{
  "type": "Feature",
  "properties": {
    "iso:country":"US",
    "sg:address":"400 Emerson Ave",
    "sg:city":"Calexico",
    "sg:classifiers":[
        {
            "category":"Education",
            "subcategory":"Special Training",
            "type":"Public Place"
        }
    ],
    "sg:phone":"+1 760 357 1929",
    "sg:postcode":"92231",
    "sg:province":"CA",
    "sg:tags":[
        "educational"
    ],
    "wof:name":"Sign's Store",
    "wof:placetype":"venue"
},
  "geometry": {"coordinates":[-115.49991900000001,32.669838],"type":"Point"}
}