{
  "type": "Feature",
  "properties": {
    "addr:full":"11049 Santa Monica Blvd Los Angeles CA 90025",
    "addr:housenumber":"11049",
    "addr:postcode":"90025",
    "addr:street":"Santa Monica Blvd",
    "iso:country":"US",
    "sg:address":"11049 Santa Monica Blvd",
    "sg:city":"Los Angeles",
    "sg:classifiers":[
        {
            "category":"Restaurant",
            "type":"Food & Drink"
        }
    ],
    "sg:phone":"+1 310 473 6618",
    "sg:postcode":"90025",
    "sg:province":"CA",
    "sg:tags":[
        "shop",
        "tea",
        "coffee"
    ],
    "sg:website":"www.coffeebean.com",
    "wof:name":"The Coffee Bean & Tea Leaf",
    "wof:placetype":"venue"
},
  "geometry": {"coordinates":[-118.44293500000001,34.048165],"type":"Point"}
}