{
  "type": "Feature",
  "properties": {
    "addr:full":"2417 Mariner Sq Lp Alameda CA 94501",
    "addr:housenumber":"2417",
    "addr:postcode":"94501",
    "addr:street":"Mariner Sq Lp Alameda",
    "iso:country":"US",
    "sg:address":"2417 Mariner Sq Lp",
    "sg:city":"Alameda",
    "sg:classifiers":[
        {
            "category":"Professional",
            "subcategory":"Engineering",
            "type":"Services"
        }
    ],
    "sg:phone":"+1 510 299 1811",
    "sg:postcode":"94501",
    "sg:province":"CA",
    "sg:tags":[
        "engineer"
    ],
    "wof:name":"Petrochem Marine Consultants",
    "wof:placetype":"venue"
},
  "geometry": {"coordinates":[-122.27860200000001,37.786431],"type":"Point"}
}