{
  "type": "Feature",
  "properties": {
    "iso:country":"US",
    "sg:address":"2413 Pacific Coast Hwy",
    "sg:city":"Lomita",
    "sg:classifiers":[
        {
            "category":"Real Estate",
            "subcategory":"Real Estate Operator",
            "type":"Services"
        },
        {
            "category":"Building & Trades",
            "subcategory":"Construction",
            "type":"Services"
        }
    ],
    "sg:phone":"+1 310 539 1062",
    "sg:postcode":"90717",
    "sg:province":"CA",
    "sg:tags":[
        "repairing",
        "property",
        "remodeling",
        "lessor",
        "contractor"
    ],
    "wof:name":"Jetson Development",
    "wof:placetype":"venue"
},
  "geometry": {"coordinates":[-118.325996,33.7896],"type":"Point"}
}