{
  "type": "Feature",
  "properties": {
    "addr:full":"146 N Fremont St San Mateo CA 94401",
    "addr:housenumber":"146",
    "addr:postcode":"94401",
    "addr:street":"N Fremont St",
    "iso:country":"US",
    "sg:address":"146 N Fremont St",
    "sg:city":"San Mateo",
    "sg:classifiers":[
        {
            "category":"Building & Trades",
            "subcategory":"Cleaning & Sanitation",
            "type":"Services"
        }
    ],
    "sg:phone":"+1 650 348 3861",
    "sg:postcode":"94401",
    "sg:province":"CA",
    "sg:tags":[
        "home"
    ],
    "wof:name":"Jimys Housecleaning Inc",
    "wof:placetype":"venue"
},
  "geometry": {"coordinates":[-122.323033,37.572945],"type":"Point"}
}