{
  "type": "Feature",
  "properties": {
    "iso:country":"US",
    "sg:address":"13300 Burbank Blvd",
    "sg:city":"Sherman Oaks",
    "sg:classifiers":[
        {
            "category":"Retail",
            "subcategory":"Auto Repair",
            "type":"Services"
        }
    ],
    "sg:phone":"+1 818 786 5370",
    "sg:postcode":"91401",
    "sg:province":"CA",
    "wof:name":"Dad & Me Auto",
    "wof:placetype":"venue"
},
  "geometry": {"coordinates":[-118.422997,34.172199],"type":"Point"}
}