{
  "type": "Feature",
  "properties": {
    "addr:full":"2086 Newpark Mall Ste K1072 Newark CA 94560",
    "addr:housenumber":"2086",
    "addr:postcode":"94560",
    "addr:street":"Newpark Mall Ste K1072",
    "iso:country":"US",
    "sg:address":"2086 Newpark Mall Ste K1072",
    "sg:city":"Newark",
    "sg:classifiers":[
        {
            "category":"Shopping",
            "subcategory":"Clothing, Apparel, & Fashions",
            "type":"Retail Goods"
        }
    ],
    "sg:phone":"+1 510 574 0980",
    "sg:postcode":"94560",
    "sg:province":"CA",
    "sg:tags":[
        "apparel",
        "women's"
    ],
    "wof:name":"Accessorize It",
    "wof:placetype":"venue"
},
  "geometry": {"coordinates":[-121.99750899999999,37.525129],"type":"Point"}
}