{
  "type": "Feature",
  "properties": {
    "addr:full":"717 S Grant St San Mateo CA 94402",
    "addr:housenumber":"717",
    "addr:postcode":"94402",
    "addr:street":"S Grant St",
    "iso:country":"US",
    "sg:address":"717 S Grant St",
    "sg:city":"San Mateo",
    "sg:classifiers":[
        {
            "category":"Building & Trades",
            "subcategory":"Construction",
            "type":"Services"
        }
    ],
    "sg:phone":"+1 650 348 8960",
    "sg:postcode":"94402",
    "sg:province":"CA",
    "sg:tags":[
        "general",
        "contractor"
    ],
    "wof:name":"Mc Manis & Assoc",
    "wof:placetype":"venue"
},
  "geometry": {"coordinates":[-122.31304799999999,37.565186],"type":"Point"}
}