{
  "type": "Feature",
  "properties": {
    "addr:full":"3636 E Olive Ave Fresno CA 93702",
    "addr:housenumber":"3636",
    "addr:postcode":"93702",
    "addr:street":"E Olive Ave",
    "iso:country":"US",
    "sg:address":"3636 E Olive Ave",
    "sg:city":"Fresno",
    "sg:classifiers":[
        {
            "category":"Autos & Motor Vehicles",
            "subcategory":"Automobile Sales",
            "type":"Retail Goods"
        }
    ],
    "sg:phone":"+1 559 233 1123",
    "sg:postcode":"93702",
    "sg:province":"CA",
    "sg:tags":[
        "car",
        "dealer"
    ],
    "wof:name":"K & N Auto Sales",
    "wof:placetype":"venue"
},
  "geometry": {"coordinates":[-119.764804,36.757631],"type":"Point"}
}