{
  "type": "Feature",
  "properties": {
    "iso:country":"US",
    "sg:address":"3844 Adams Ave",
    "sg:city":"San Diego",
    "sg:classifiers":[
        {
            "category":"Recreation",
            "type":"Entertainment"
        }
    ],
    "sg:phone":"+1 619 280 0082",
    "sg:postcode":"92116",
    "sg:province":"CA",
    "sg:tags":[
        "martial",
        "arts",
        "instruction"
    ],
    "wof:name":"Aikido San Diego Aikikai",
    "wof:placetype":"venue"
},
  "geometry": {"coordinates":[-117.111545,32.763357],"type":"Point"}
}