{
  "type": "Feature",
  "properties": {
    "addr:full":"9817 Bonnie Vista Pl La Mesa CA 91941",
    "addr:housenumber":"9817",
    "addr:postcode":"91941",
    "addr:street":"Bonnie Vista Pl",
    "iso:country":"US",
    "sg:address":"9817 Bonnie Vista Pl",
    "sg:city":"La Mesa",
    "sg:classifiers":[
        {
            "category":"Real Estate",
            "subcategory":"Real Estate Agent",
            "type":"Services"
        }
    ],
    "sg:phone":"+1 619 670 5785",
    "sg:postcode":"91941",
    "sg:province":"CA",
    "wof:name":"Real Estate Ambassador",
    "wof:placetype":"venue"
},
  "geometry": {"coordinates":[-116.983334,32.756296],"type":"Point"}
}