{
  "type": "Feature",
  "properties": {
    "iso:country":"US",
    "sg:address":"1227 Windimer Dr",
    "sg:city":"Los Altos",
    "sg:classifiers":[
        {
            "category":"Building & Trades",
            "subcategory":"Electrical",
            "type":"Services"
        }
    ],
    "sg:phone":"+1 650 967 8138",
    "sg:postcode":"94024",
    "sg:province":"CA",
    "sg:tags":[
        "electric",
        "contractor"
    ],
    "wof:name":"Falcon Electric",
    "wof:placetype":"venue"
},
  "geometry": {"coordinates":[-122.079228,37.34044],"type":"Point"}
}