{
  "type": "Feature",
  "properties": {
    "iso:country":"US",
    "sg:address":"3201 E 69th St",
    "sg:city":"Long Beach",
    "sg:classifiers":[
        {
            "category":"Freight",
            "type":"Transportation"
        }
    ],
    "sg:phone":"+1 310 834 1359",
    "sg:postcode":"90805",
    "sg:province":"CA",
    "sg:tags":[
        "operator",
        "trucking"
    ],
    "wof:name":"Beneto Inc",
    "wof:placetype":"venue"
},
  "geometry": {"coordinates":[-118.15160299999999,33.880158],"type":"Point"}
}