{
  "type": "Feature",
  "properties": {
    "addr:full":"5726 La Jolla Blvd. Suite 119 La Jolla CA 92037",
    "addr:housenumber":"5726",
    "addr:postcode":"92037",
    "addr:street":"La Jolla Blvd. Suite 119",
    "iso:country":"US",
    "sg:address":"5726 La Jolla Blvd. Suite 119",
    "sg:city":"La Jolla",
    "sg:classifiers":[
        {
            "category":"Personal",
            "subcategory":"Massage",
            "type":"Services"
        }
    ],
    "sg:phone":"+1 619 495 8712",
    "sg:postcode":"92037",
    "sg:province":"CA",
    "wof:name":"Carried Away Massage & Body Products",
    "wof:placetype":"venue"
},
  "geometry": {"coordinates":[-117.27130699999999,32.816403],"type":"Point"}
}