{
  "type": "Feature",
  "properties": {
    "addr:full":"710 Solano St Corning CA 96021",
    "addr:housenumber":"710",
    "addr:postcode":"96021",
    "addr:street":"Solano St",
    "iso:country":"US",
    "sg:address":"710 Solano St",
    "sg:city":"Corning",
    "sg:classifiers":[
        {
            "category":"Health Services",
            "subcategory":"Health Practitioner",
            "type":"Services"
        }
    ],
    "sg:phone":"+1 530 824 9355",
    "sg:postcode":"96021",
    "sg:province":"CA",
    "sg:tags":[
        "therapist",
        "physical"
    ],
    "wof:name":"Physical Therapy & Wellness",
    "wof:placetype":"venue"
},
  "geometry": {"coordinates":[-122.1756,39.927977],"type":"Point"}
}