{
  "type": "Feature",
  "properties": {
    "addr:full":"1187 Krona Ln Concord CA 94521",
    "addr:housenumber":"1187",
    "addr:postcode":"94521",
    "addr:street":"Krona Ln",
    "iso:country":"US",
    "sg:address":"1187 Krona Ln",
    "sg:city":"Concord",
    "sg:classifiers":[
        {
            "category":"Building & Trades",
            "subcategory":"Construction",
            "type":"Services"
        }
    ],
    "sg:phone":"+1 925 672 4985",
    "sg:postcode":"94521",
    "sg:province":"CA",
    "sg:tags":[
        "coping",
        "plastering",
        "tiling",
        "pool",
        "swimming"
    ],
    "wof:name":"Sparkling Pools Svc",
    "wof:placetype":"venue"
},
  "geometry": {"coordinates":[-121.956596,37.937757],"type":"Point"}
}