{
  "type": "Feature",
  "properties": {
    "addr:full":"21103 Vanowen St Canoga Park CA 91303",
    "addr:housenumber":"21103",
    "addr:postcode":"91303",
    "addr:street":"Vanowen St",
    "iso:country":"US",
    "sg:address":"21103 Vanowen St",
    "sg:city":"Canoga Park",
    "sg:classifiers":[
        {
            "category":"Health Services",
            "subcategory":"Doctor",
            "type":"Services"
        },
        {
            "category":"Health Services",
            "subcategory":"Chiropractor",
            "type":"Services"
        }
    ],
    "sg:phone":"+1 818 346 9600",
    "sg:postcode":"91303",
    "sg:province":"CA",
    "sg:website":"www.drcolleenphillips.com",
    "wof:name":"Malpractice & You",
    "wof:placetype":"venue"
},
  "geometry": {"coordinates":[-118.593002,34.193699],"type":"Point"}
}