{
  "type": "Feature",
  "properties": {
    "addr:full":"127 W Janss Rd Thousand Oaks CA 91360",
    "addr:housenumber":"127",
    "addr:postcode":"91360",
    "addr:street":"W Janss Rd",
    "iso:country":"US",
    "sg:address":"127 W Janss Rd",
    "sg:city":"Thousand Oaks",
    "sg:classifiers":[
        {
            "category":"Building & Trades",
            "subcategory":"Plumbing",
            "type":"Services"
        }
    ],
    "sg:phone":"+1 805 494 1338",
    "sg:postcode":"91360",
    "sg:province":"CA",
    "sg:tags":[
        "product",
        "management",
        "energy",
        "system"
    ],
    "wof:name":"Crystal Energy",
    "wof:placetype":"venue"
},
  "geometry": {"coordinates":[-118.876265,34.20403],"type":"Point"}
}