{
  "type": "Feature",
  "properties": {
    "addr:full":"425 N Main St Salinas CA 93901",
    "addr:housenumber":"425",
    "addr:postcode":"93901",
    "addr:street":"N Main St",
    "iso:country":"US",
    "sg:address":"425 N Main St",
    "sg:city":"Salinas",
    "sg:classifiers":[
        {
            "category":"Manufacturing",
            "subcategory":"Tools & Machinery",
            "type":"Manufacturing & Wholesale Goods"
        }
    ],
    "sg:phone":"+1 831 783 1000",
    "sg:postcode":"93901",
    "sg:province":"CA",
    "sg:tags":[
        "battery",
        "storage",
        "mfg"
    ],
    "wof:name":"Frontier Self Storage",
    "wof:placetype":"venue"
},
  "geometry": {"coordinates":[-121.652931,36.684214],"type":"Point"}
}