{
  "type": "Feature",
  "properties": {
    "addr:full":"3551 Castro Valley Blvd Castro Valley CA 94546",
    "addr:housenumber":"3551",
    "addr:postcode":"94546",
    "addr:street":"Castro Valley Blvd",
    "iso:country":"US",
    "sg:address":"3551 Castro Valley Blvd",
    "sg:city":"Castro Valley",
    "sg:classifiers":[
        {
            "category":"Real Estate",
            "subcategory":"Real Estate Agent",
            "type":"Services"
        }
    ],
    "sg:phone":"+1 510 881 7500",
    "sg:postcode":"94546",
    "sg:province":"CA",
    "sg:website":"www.cahillandco.com",
    "wof:name":"Cahill & Co Real Estate",
    "wof:placetype":"venue"
},
  "geometry": {"coordinates":[-122.07146899999999,37.694874],"type":"Point"}
}