{
  "type": "Feature",
  "properties": {
    "iso:country":"US",
    "sg:address":"5501 Traffic Way",
    "sg:city":"Atascadero",
    "sg:classifiers":[
        {
            "category":"Autos & Motor Vehicles",
            "subcategory":"Auto Supplies",
            "type":"Retail Goods"
        }
    ],
    "sg:phone":"+1 805 461 0072",
    "sg:postcode":"93422",
    "sg:province":"CA",
    "sg:tags":[
        "automobile",
        "parts"
    ],
    "wof:name":"Titan Inc",
    "wof:placetype":"venue"
},
  "geometry": {"coordinates":[-120.66778,35.496241],"type":"Point"}
}