{
  "type": "Feature",
  "properties": {
    "addr:full":"5 Rose Ave Venice CA 90291",
    "addr:housenumber":"5",
    "addr:postcode":"90291",
    "addr:street":"Rose Ave",
    "iso:country":"US",
    "sg:address":"5 Rose Ave",
    "sg:city":"Venice",
    "sg:classifiers":[
        {
            "category":"Real Estate",
            "subcategory":"Developer",
            "type":"Services"
        }
    ],
    "sg:phone":"+1 310 399 7422",
    "sg:postcode":"90291",
    "sg:province":"CA",
    "wof:name":"Oceanview Apartments",
    "wof:placetype":"venue"
},
  "geometry": {"coordinates":[-118.480345,33.994764],"type":"Point"}
}