{
  "type": "Feature",
  "properties": {
    "iso:country":"US",
    "sg:address":"1818 Harmon St Ste 3",
    "sg:city":"Berkeley",
    "sg:classifiers":[
        {
            "category":"Building & Trades",
            "subcategory":"Construction",
            "type":"Services"
        }
    ],
    "sg:phone":"+1 510 428 2700",
    "sg:postcode":"94703",
    "sg:province":"CA",
    "sg:tags":[
        "contractor"
    ],
    "sg:website":"whitehousebuilders.com",
    "wof:name":"Whitehouse Builders, Inc",
    "wof:placetype":"venue"
},
  "geometry": {"coordinates":[-122.27216900000001,37.849577],"type":"Point"}
}