{
  "type": "Feature",
  "properties": {
    "iso:country":"US",
    "sg:address":"6001 W Olympic Boulevard",
    "sg:city":"Los Angeles",
    "sg:classifiers":[
        {
            "category":"Personal",
            "subcategory":"Shoe Repair & Shine",
            "type":"Services"
        }
    ],
    "sg:phone":"+1 323 857 0987",
    "sg:postcode":"90036",
    "sg:province":"CA",
    "wof:name":"Best Shoe Repair & Alterations",
    "wof:placetype":"venue"
},
  "geometry": {"coordinates":[-118.362172,34.057872],"type":"Point"}
}