{
  "type": "Feature",
  "properties": {
    "addr:full":"2022 California Ave Santa Monica CA 90403",
    "addr:housenumber":"2022",
    "addr:postcode":"90403",
    "addr:street":"California Ave",
    "iso:country":"US",
    "sg:address":"2022 California Ave",
    "sg:city":"Santa Monica",
    "sg:classifiers":[
        {
            "category":"Professional",
            "subcategory":"Accounting & Tax Preparation",
            "type":"Services"
        }
    ],
    "sg:phone":"+1 310 393 0471",
    "sg:postcode":"90403",
    "sg:province":"CA",
    "sg:tags":[
        "accountant"
    ],
    "wof:name":"Ahmed M Saleh CPA",
    "wof:placetype":"venue"
},
  "geometry": {"coordinates":[-118.484419,34.032914],"type":"Point"}
}