{
  "type": "Feature",
  "properties": {
    "addr:full":"5102 Hopyard Rd Pleasanton CA 94588",
    "addr:housenumber":"5102",
    "addr:postcode":"94588",
    "addr:street":"Hopyard Rd",
    "iso:country":"US",
    "sg:address":"5102 Hopyard Rd",
    "sg:city":"Pleasanton",
    "sg:classifiers":[
        {
            "category":"Travel",
            "subcategory":"Hotels & Motels",
            "type":"Entertainment"
        }
    ],
    "sg:phone":"+1 925 463 2626",
    "sg:postcode":"94588",
    "sg:province":"CA",
    "sg:website":"http://www.motel6.com",
    "wof:name":"Motel 6",
    "wof:placetype":"venue"
},
  "geometry": {"coordinates":[-121.903702,37.696822],"type":"Point"}
}