{
  "type": "Feature",
  "properties": {
    "addr:full":"4370 Long Valley Rd Santa Ynez CA 93460",
    "addr:housenumber":"4370",
    "addr:postcode":"93460",
    "addr:street":"Long Valley Rd",
    "iso:country":"US",
    "sg:address":"4370 Long Valley Rd",
    "sg:city":"Santa Ynez",
    "sg:classifiers":[
        {
            "category":"Retail",
            "subcategory":"Car Wash",
            "type":"Services"
        }
    ],
    "sg:phone":"+1 805 350 3061",
    "sg:postcode":"93460",
    "sg:province":"CA",
    "sg:tags":[
        "automobile",
        "detail",
        "clean"
    ],
    "wof:name":"Dan's Fantastic Windows",
    "wof:placetype":"venue"
},
  "geometry": {"coordinates":[-120.058571,34.702024],"type":"Point"}
}