{
  "type": "Feature",
  "properties": {
    "addr:full":"3313 Sunny Oak Ct Bakersfield CA 93311",
    "addr:housenumber":"3313",
    "addr:postcode":"93311",
    "addr:street":"Sunny Oak Ct",
    "iso:country":"US",
    "sg:address":"3313 Sunny Oak Ct",
    "sg:city":"Bakersfield",
    "sg:classifiers":[
        {
            "category":"Professional",
            "subcategory":"Management & Consulting",
            "type":"Services"
        }
    ],
    "sg:phone":"+1 661 664 0423",
    "sg:postcode":"93311",
    "sg:province":"CA",
    "sg:tags":[
        "fuel"
    ],
    "wof:name":"Donadio Money Management",
    "wof:placetype":"venue"
},
  "geometry": {"coordinates":[-119.10134499999999,35.324951],"type":"Point"}
}