{
  "type": "Feature",
  "properties": {
    "iso:country":"US",
    "sg:address":"8 Whitewood Way",
    "sg:city":"Irvine",
    "sg:classifiers":[
        {
            "category":"Banks & Credit Unions",
            "subcategory":"Investment Brokerage",
            "type":"Services"
        }
    ],
    "sg:phone":"+1 949 552 5256",
    "sg:postcode":"92612",
    "sg:province":"CA",
    "sg:tags":[
        "security"
    ],
    "wof:name":"Insurance Securities",
    "wof:placetype":"venue"
},
  "geometry": {"coordinates":[-117.821493,33.661069],"type":"Point"}
}