{
  "type": "Feature",
  "properties": {
    "iso:country":"US",
    "sg:address":"2920 Grand Ave",
    "sg:city":"Los Olivos",
    "sg:classifiers":[
        {
            "category":"Real Estate",
            "subcategory":"Architect",
            "type":"Services"
        }
    ],
    "sg:phone":"+1 805 688 4974",
    "sg:postcode":"93441",
    "sg:province":"CA",
    "wof:name":"Jones & Jones Planning & Arch",
    "wof:placetype":"venue"
},
  "geometry": {"coordinates":[-120.114926,34.666306],"type":"Point"}
}