{
  "type": "Feature",
  "properties": {
    "addr:full":"138 E Spain St Sonoma CA 95476",
    "addr:housenumber":"138",
    "addr:postcode":"95476",
    "addr:street":"E Spain St",
    "iso:country":"US",
    "sg:address":"138 E Spain St",
    "sg:city":"Sonoma",
    "sg:classifiers":[
        {
            "category":"Travel",
            "subcategory":"Hotels & Motels",
            "type":"Entertainment"
        }
    ],
    "sg:phone":"+1 707 939 7070",
    "sg:postcode":"95476",
    "sg:province":"CA",
    "sg:tags":[
        "breakfast",
        "accommodation",
        "bed"
    ],
    "wof:name":"Andrea's Hidden Cottage",
    "wof:placetype":"venue"
},
  "geometry": {"coordinates":[-122.454942,38.293523],"type":"Point"}
}