{
  "type": "Feature",
  "properties": {
    "iso:country":"US",
    "sg:address":"2798 Aiello Dr",
    "sg:city":"San Jose",
    "sg:classifiers":[
        {
            "category":"Autos & Motor Vehicles",
            "subcategory":"Auto Supplies",
            "type":"Retail Goods"
        }
    ],
    "sg:phone":"+1 408 281 3325",
    "sg:postcode":"95111",
    "sg:province":"CA",
    "sg:tags":[
        "equipment",
        "racing",
        "car",
        "automobile"
    ],
    "wof:name":"Santomauro Racing Products",
    "wof:placetype":"venue"
},
  "geometry": {"coordinates":[-121.84736599999999,37.294804],"type":"Point"}
}