{
  "type": "Feature",
  "properties": {
    "addr:full":"1236 D St Ramona CA 92065",
    "addr:housenumber":"1236",
    "addr:postcode":"92065",
    "addr:street":"D St",
    "iso:country":"US",
    "sg:address":"1236 D St",
    "sg:city":"Ramona",
    "sg:classifiers":[
        {
            "category":"Manufacturing",
            "subcategory":"Metals",
            "type":"Manufacturing & Wholesale Goods"
        }
    ],
    "sg:phone":"+1 760 788 7377",
    "sg:postcode":"92065",
    "sg:province":"CA",
    "sg:tags":[
        "metalwork",
        "architectural",
        "mfg"
    ],
    "wof:name":"Palomar Iron",
    "wof:placetype":"venue"
},
  "geometry": {"coordinates":[-116.872062,33.038768],"type":"Point"}
}