{
  "type": "Feature",
  "properties": {
    "addr:full":"6021 Woodminster Cir Orangevale CA 95662",
    "addr:housenumber":"6021",
    "addr:postcode":"95662",
    "addr:street":"Woodminster Cir",
    "iso:country":"US",
    "sg:address":"6021 Woodminster Cir",
    "sg:city":"Orangevale",
    "sg:classifiers":[
        {
            "category":"Professional",
            "subcategory":"Business Services",
            "type":"Services"
        }
    ],
    "sg:phone":"+1 916 247 8556",
    "sg:postcode":"95662",
    "sg:province":"CA",
    "sg:tags":[
        "notary"
    ],
    "wof:name":"An Area Mobile Notary",
    "wof:placetype":"venue"
},
  "geometry": {"coordinates":[-121.194407,38.677338],"type":"Point"}
}