{
  "type": "Feature",
  "properties": {
    "addr:full":"201 N Verdugo Rd Glendale CA 91206",
    "addr:housenumber":"201",
    "addr:postcode":"91206",
    "addr:street":"N Verdugo Rd",
    "iso:country":"US",
    "sg:address":"201 N Verdugo Rd",
    "sg:city":"Glendale",
    "sg:classifiers":[
        {
            "category":"Food & Beverages",
            "subcategory":"Groceries & Convenience Stores",
            "type":"Retail Goods"
        }
    ],
    "sg:phone":"+1 818 244 5541",
    "sg:postcode":"91206",
    "sg:province":"CA",
    "wof:name":"Verdugo Dairy",
    "wof:placetype":"venue"
},
  "geometry": {"coordinates":[-118.236,34.148201],"type":"Point"}
}