{
  "type": "Feature",
  "properties": {
    "iso:country":"US",
    "sg:address":"1278 Westwood Blvd",
    "sg:city":"Los Angeles",
    "sg:classifiers":[
        {
            "category":"Retail",
            "subcategory":"Veterinary Services",
            "type":"Services"
        }
    ],
    "sg:phone":"+1 310 446 3908",
    "sg:postcode":"90024",
    "sg:province":"CA",
    "sg:tags":[
        "veterinarian"
    ],
    "sg:website":"www.myvaluevet.com/",
    "wof:name":"Value Vet",
    "wof:placetype":"venue"
},
  "geometry": {"coordinates":[-118.442601,34.057511],"type":"Point"}
}