{
  "type": "Feature",
  "properties": {
    "iso:country":"US",
    "sg:address":"520 S Virgil Ave",
    "sg:city":"Los Angeles",
    "sg:classifiers":[
        {
            "category":"Social Services",
            "type":"Services"
        }
    ],
    "sg:phone":"+1 323 251 2710",
    "sg:postcode":"90020",
    "sg:province":"CA",
    "sg:tags":[
        "organization",
        "welfare"
    ],
    "wof:name":"Los Angeles Coalition",
    "wof:placetype":"venue"
},
  "geometry": {"coordinates":[-118.28697,34.064008],"type":"Point"}
}