{
  "type": "Feature",
  "properties": {
    "iso:country":"US",
    "sg:address":"21243 Ventura Blvd",
    "sg:city":"Woodland Hills",
    "sg:classifiers":[
        {
            "category":"Real Estate",
            "subcategory":"Real Estate Agent",
            "type":"Services"
        }
    ],
    "sg:phone":"+1 818 888 3311",
    "sg:postcode":"91364",
    "sg:province":"CA",
    "wof:name":"Vickter Investment Properties",
    "wof:placetype":"venue"
},
  "geometry": {"coordinates":[-118.595209,34.167462],"type":"Point"}
}