{
  "type": "Feature",
  "properties": {
    "addr:full":"889 Moraga Rd Lafayette CA 94549",
    "addr:housenumber":"889",
    "addr:postcode":"94549",
    "addr:street":"Moraga Rd",
    "iso:country":"US",
    "sg:address":"889 Moraga Rd",
    "sg:city":"Lafayette",
    "sg:classifiers":[
        {
            "category":"Professional",
            "subcategory":"Lawyer & Legal Services",
            "type":"Services"
        }
    ],
    "sg:phone":"+1 925 299 2030",
    "sg:postcode":"94549",
    "sg:province":"CA",
    "sg:tags":[
        "attorney"
    ],
    "wof:name":"Crosetti & Titmus",
    "wof:placetype":"venue"
},
  "geometry": {"coordinates":[-122.118133,37.886163],"type":"Point"}
}