{
  "type": "Feature",
  "properties": {
    "addr:full":"7601 State Street Huntington Park CA 90255",
    "addr:housenumber":"7601",
    "addr:postcode":"90255",
    "addr:street":"State Street",
    "iso:country":"US",
    "sg:address":"7601 State Street",
    "sg:city":"Huntington Park",
    "sg:classifiers":[
        {
            "category":"Restaurant",
            "type":"Food & Drink"
        }
    ],
    "sg:phone":"+1 323 581 1532",
    "sg:postcode":"90255",
    "sg:province":"CA",
    "wof:name":"El Sinaloense Restaurant",
    "wof:placetype":"venue"
},
  "geometry": {"coordinates":[-118.209937,33.969159],"type":"Point"}
}