{
  "type": "Feature",
  "properties": {
    "addr:full":"11782 Donner Pass Rd Truckee CA 96161",
    "addr:housenumber":"11782",
    "addr:postcode":"96161",
    "addr:street":"Donner Pass Rd",
    "iso:country":"US",
    "sg:address":"11782 Donner Pass Rd",
    "sg:city":"Truckee",
    "sg:classifiers":[
        {
            "category":"Fast Food",
            "type":"Food & Drink"
        },
        {
            "category":"Restaurant",
            "type":"Food & Drink"
        }
    ],
    "sg:phone":"+1 530 587 3456",
    "sg:postcode":"96161",
    "sg:province":"CA",
    "sg:tags":[
        "italian",
        "pizza"
    ],
    "wof:name":"Pizza Shack",
    "wof:placetype":"venue"
},
  "geometry": {"coordinates":[-120.21492600000001,39.326047],"type":"Point"}
}