{
  "type": "Feature",
  "properties": {
    "iso:country":"US",
    "sg:address":"9559 W Whitesbridge Ave",
    "sg:city":"Fresno",
    "sg:classifiers":[
        {
            "category":"Retail",
            "subcategory":"Auto Rental",
            "type":"Services"
        }
    ],
    "sg:phone":"+1 559 233 3394",
    "sg:postcode":"93706",
    "sg:province":"CA",
    "sg:tags":[
        "renting",
        "truck",
        "leasing"
    ],
    "wof:name":"Heinz Water Truck Rentals",
    "wof:placetype":"venue"
},
  "geometry": {"coordinates":[-119.961915,36.734979],"type":"Point"}
}