{
  "type": "Feature",
  "properties": {
    "addr:full":"436 S Beverly Dr Beverly Hills CA 90212",
    "addr:housenumber":"436",
    "addr:postcode":"90212",
    "addr:street":"S Beverly Dr",
    "iso:country":"US",
    "sg:address":"436 S Beverly Dr",
    "sg:city":"Beverly Hills",
    "sg:classifiers":[
        {
            "category":"Organizations",
            "subcategory":"Religious Organization",
            "type":"Services"
        }
    ],
    "sg:phone":"+1 310 277 1164",
    "sg:postcode":"90212",
    "sg:province":"CA",
    "sg:tags":[
        "church"
    ],
    "wof:name":"Mount Calvary Lutheran Church",
    "wof:placetype":"venue"
},
  "geometry": {"coordinates":[-118.39817600000001,34.059275],"type":"Point"}
}