{
  "type": "Feature",
  "properties": {
    "addr:full":"319 Main St Salinas CA 93901",
    "addr:housenumber":"319",
    "addr:postcode":"93901",
    "addr:street":"Main St",
    "iso:country":"US",
    "sg:address":"319 Main St",
    "sg:city":"Salinas",
    "sg:classifiers":[
        {
            "category":"Retail",
            "subcategory":"Repair Shop",
            "type":"Services"
        }
    ],
    "sg:phone":"+1 831 422 8333",
    "sg:postcode":"93901",
    "sg:province":"CA",
    "sg:tags":[
        "lock",
        "locksmith"
    ],
    "wof:name":"Lock Stock N Barrel",
    "wof:placetype":"venue"
},
  "geometry": {"coordinates":[-121.65471599999999,36.673618],"type":"Point"}
}