{
  "type": "Feature",
  "properties": {
    "addr:full":"2059 Polk St San Francisco CA 94109",
    "addr:housenumber":"2059",
    "addr:postcode":"94109",
    "addr:street":"Polk St",
    "iso:country":"US",
    "sg:address":"2059 Polk St",
    "sg:city":"San Francisco",
    "sg:classifiers":[
        {
            "category":"Personal",
            "subcategory":"Beauty Salon",
            "type":"Services"
        }
    ],
    "sg:phone":"+1 415 775 7885",
    "sg:postcode":"94109",
    "sg:province":"CA",
    "sg:tags":[
        "shop",
        "equipment",
        "cosmetic",
        "supply"
    ],
    "wof:name":"Harry's Hair Studio",
    "wof:placetype":"venue"
},
  "geometry": {"coordinates":[-122.421762,37.795801],"type":"Point"}
}