{
  "type": "Feature",
  "properties": {
    "addr:full":"20700 E River Rd Ripon CA 95366",
    "addr:housenumber":"20700",
    "addr:postcode":"ca 95366",
    "addr:street":"E River Rd",
    "iso:country":"US",
    "sg:address":"20700 E River Rd",
    "sg:city":"Ripon",
    "sg:classifiers":[
        {
            "category":"Education",
            "subcategory":"School",
            "type":"Public Place"
        }
    ],
    "sg:phone":"+1 209 599 5714",
    "sg:postcode":"95366",
    "sg:province":"CA",
    "wof:name":"Bird's Nest Childrens Ctr",
    "wof:placetype":"venue"
},
  "geometry": {"coordinates":[-121.086223,37.760997],"type":"Point"}
}