{
  "type": "Feature",
  "properties": {
    "iso:country":"US",
    "sg:address":"650 5th St",
    "sg:city":"San Francisco",
    "sg:classifiers":[
        {
            "category":"Professional",
            "type":"Services"
        }
    ],
    "sg:phone":"+1 415 318 7000",
    "sg:postcode":"94107",
    "sg:province":"CA",
    "sg:tags":[
        "establishment"
    ],
    "wof:name":"Slo",
    "wof:placetype":"venue"
},
  "geometry": {"coordinates":[-122.397206,37.775332],"type":"Point"}
}