{
  "type": "Feature",
  "properties": {
    "iso:country":"US",
    "sg:address":"19560 Magnolia Ave",
    "sg:city":"Lakeview",
    "sg:classifiers":[
        {
            "category":"Social Services",
            "subcategory":"Child Care",
            "type":"Services"
        }
    ],
    "sg:phone":"+1 951 928 0615",
    "sg:postcode":"92567",
    "sg:province":"CA",
    "sg:tags":[
        "kindergarten",
        "academic",
        "school"
    ],
    "wof:name":"Jesus Center Christian School",
    "wof:placetype":"venue"
},
  "geometry": {"coordinates":[-117.12065200000001,33.837122],"type":"Point"}
}