{
  "type": "Feature",
  "properties": {
    "addr:full":"2 Oak St Bakersfield CA 93304",
    "addr:housenumber":"2",
    "addr:postcode":"93304",
    "addr:street":"Oak St",
    "iso:country":"US",
    "sg:address":"2 Oak St",
    "sg:city":"Bakersfield",
    "sg:classifiers":[
        {
            "category":"Autos & Motor Vehicles",
            "subcategory":"Fuel & Gas Station",
            "type":"Retail Goods"
        }
    ],
    "sg:phone":"+1 661 638 0301",
    "sg:postcode":"93304",
    "sg:province":"CA",
    "sg:tags":[
        "oil"
    ],
    "wof:name":"Oak Street Mobil",
    "wof:placetype":"venue"
},
  "geometry": {"coordinates":[-119.03894099999999,35.356065],"type":"Point"}
}