{
  "type": "Feature",
  "properties": {
    "addr:full":"2265 Honolulu Ave Montrose CA 91020",
    "addr:postcode":"2265;91020",
    "addr:street":"Honolulu Ave",
    "iso:country":"US",
    "sg:address":"2265 Honolulu Ave",
    "sg:city":"Montrose",
    "sg:classifiers":[
        {
            "category":"Bars & Pubs",
            "subcategory":"Sports Bar",
            "type":"Food & Drink"
        },
        {
            "category":"Restaurant",
            "type":"Food & Drink"
        }
    ],
    "sg:phone":"+1 818 236 4810",
    "sg:postcode":"91020",
    "sg:province":"CA",
    "sg:tags":[
        "new",
        "american"
    ],
    "sg:website":"www.thefatdogla.com",
    "wof:name":"The Fat Dog",
    "wof:placetype":"venue"
},
  "geometry": {"coordinates":[-118.22707,34.20563],"type":"Point"}
}