{
  "type": "Feature",
  "properties": {
    "iso:country":"US",
    "sg:address":"206 E 2nd Ave",
    "sg:city":"La Habra",
    "sg:classifiers":[
        {
            "category":"Home & Garden",
            "subcategory":"Hardware",
            "type":"Retail Goods"
        }
    ],
    "sg:phone":"+1 562 694 8564",
    "sg:postcode":"90631",
    "sg:province":"CA",
    "sg:tags":[
        "saw"
    ],
    "wof:name":"Keller Saw Svc",
    "wof:placetype":"venue"
},
  "geometry": {"coordinates":[-117.943296,33.929794],"type":"Point"}
}