{
  "type": "Feature",
  "properties": {
    "iso:country":"US",
    "sg:address":"833 Dover Drive Suite 1",
    "sg:city":"Newport Beach",
    "sg:classifiers":[
        {
            "category":"Sports & Exercise",
            "subcategory":"Gym",
            "type":"Entertainment"
        }
    ],
    "sg:phone":"+1 949 677 4495",
    "sg:postcode":"92663",
    "sg:province":"CA",
    "sg:tags":[
        "trainer"
    ],
    "sg:website":"www.shawnryanfitness.com/",
    "wof:name":"Shawn Ryan Personal Training",
    "wof:placetype":"venue"
},
  "geometry": {"coordinates":[-117.906475,33.623395],"type":"Point"}
}