{
  "type": "Feature",
  "properties": {
    "addr:full":"46400 Fremont Blvd Fremont CA 94538",
    "addr:housenumber":"46400",
    "addr:postcode":"94538",
    "addr:street":"Fremont Blvd",
    "iso:country":"US",
    "sg:address":"46400 Fremont Blvd",
    "sg:city":"Fremont",
    "sg:classifiers":[
        {
            "category":"Professional",
            "subcategory":"Engineering",
            "type":"Services"
        },
        {
            "category":"Home & Garden",
            "subcategory":"Building Materials",
            "type":"Retail Goods"
        },
        {
            "category":"Building & Trades",
            "subcategory":"Construction",
            "type":"Services"
        }
    ],
    "sg:phone":"+1 510 933 7000",
    "sg:postcode":"94538",
    "sg:province":"CA",
    "sg:tags":[
        "repair",
        "management",
        "energy",
        "systems-service",
        "equipment",
        "solar",
        "systems-dealers",
        "engineer"
    ],
    "sg:website":"http://www.greenvolts.com",
    "wof:name":"Greenvolts, Inc.",
    "wof:placetype":"venue"
},
  "geometry": {"coordinates":[-121.945885,37.483968],"type":"Point"}
}