{
  "type": "Feature",
  "properties": {
    "iso:country":"US",
    "sg:address":"1183 W Holt Ave",
    "sg:city":"Pomona",
    "sg:classifiers":[
        {
            "category":"Retail",
            "subcategory":"Auto Repair",
            "type":"Services"
        }
    ],
    "sg:phone":"+1 909 623 4199",
    "sg:postcode":"91768",
    "sg:province":"CA",
    "sg:tags":[
        "body",
        "automobile",
        "painting"
    ],
    "wof:name":"Gongara's Body & Paint",
    "wof:placetype":"venue"
},
  "geometry": {"coordinates":[-117.768687,34.062006],"type":"Point"}
}