{
  "type": "Feature",
  "properties": {
    "addr:full":"11662 N Ham Ln Spc 51 Lodi CA 95242",
    "addr:housenumber":"11662;51",
    "addr:postcode":"ca 95242",
    "addr:street":"N Ham Ln",
    "iso:country":"US",
    "sg:address":"11662 N Ham Ln Spc 51",
    "sg:city":"Lodi",
    "sg:classifiers":[
        {
            "category":"Real Estate",
            "subcategory":"Real Estate Agent",
            "type":"Services"
        }
    ],
    "sg:phone":"+1 209 365 9112",
    "sg:postcode":"95242",
    "sg:province":"CA",
    "wof:name":"Merrill John",
    "wof:placetype":"venue"
},
  "geometry": {"coordinates":[-121.28738300000001,38.075877],"type":"Point"}
}