{
  "type": "Feature",
  "properties": {
    "addr:full":"3407 Glendale Blvd Los Angeles CA 90039",
    "addr:housenumber":"3407",
    "addr:postcode":"90039",
    "addr:street":"Glendale Blvd",
    "iso:country":"US",
    "sg:address":"3407 Glendale Blvd",
    "sg:city":"Los Angeles",
    "sg:classifiers":[
        {
            "category":"Recreation",
            "type":"Entertainment"
        }
    ],
    "sg:phone":"+1 323 953 6653",
    "sg:postcode":"90039",
    "sg:province":"CA",
    "sg:tags":[
        "martial",
        "arts",
        "instruction"
    ],
    "wof:name":"Sam's Martial Arts Academy",
    "wof:placetype":"venue"
},
  "geometry": {"coordinates":[-118.25826000000001,34.120687],"type":"Point"}
}