{
  "type": "Feature",
  "properties": {
    "iso:country":"US",
    "sg:address":"5055 Chiles Rd",
    "sg:city":"Davis",
    "sg:classifiers":[
        {
            "category":"Retail",
            "subcategory":"Auto Rental",
            "type":"Services"
        }
    ],
    "sg:phone":"+1 530 753 1300",
    "sg:postcode":"95618",
    "sg:province":"CA",
    "sg:tags":[
        "renting",
        "automobile"
    ],
    "wof:name":"Enterprise Rent-A-Car",
    "wof:placetype":"venue"
},
  "geometry": {"coordinates":[-121.691884,38.551877],"type":"Point"}
}