{
  "type": "Feature",
  "properties": {
    "addr:full":"1456 Mondana Pl Pittsburg CA 94565",
    "addr:housenumber":"1456",
    "addr:postcode":"94565",
    "addr:street":"Mondana Pl",
    "iso:country":"US",
    "sg:address":"1456 Mondana Pl",
    "sg:city":"Pittsburg",
    "sg:classifiers":[
        {
            "category":"Shopping",
            "type":"Retail Goods"
        },
        {
            "category":"Organizations",
            "subcategory":"Non-profit Organization",
            "type":"Services"
        }
    ],
    "sg:phone":"+1 925 432 8312",
    "sg:postcode":"94565",
    "sg:province":"CA",
    "sg:tags":[
        "fund",
        "games",
        "raising",
        "merchandise",
        "supply"
    ],
    "wof:name":"The Original Teens 60's",
    "wof:placetype":"venue"
},
  "geometry": {"coordinates":[-121.866765,38.005568],"type":"Point"}
}