{
  "type": "Feature",
  "properties": {
    "addr:full":"1591 Pease Rd Yuba City CA 95993",
    "addr:housenumber":"1591",
    "addr:postcode":"95993",
    "addr:street":"Pease Rd",
    "iso:country":"US",
    "sg:address":"1591 Pease Rd",
    "sg:city":"Yuba City",
    "sg:classifiers":[
        {
            "category":"Professional",
            "subcategory":"Business Services",
            "type":"Services"
        }
    ],
    "sg:phone":"+1 530 671 2515",
    "sg:postcode":"95993",
    "sg:province":"CA",
    "sg:tags":[
        "packaging"
    ],
    "wof:name":"Richard R Wilbur Shop",
    "wof:placetype":"venue"
},
  "geometry": {"coordinates":[-121.641425,39.170922],"type":"Point"}
}