{
  "type": "Feature",
  "properties": {
    "addr:full":"2710 Annapolis Cir San Bernardino CA 92408",
    "addr:housenumber":"2710",
    "addr:postcode":"92408",
    "addr:street":"Annapolis Cir",
    "iso:country":"US",
    "sg:address":"2710 Annapolis Cir",
    "sg:city":"San Bernardino",
    "sg:classifiers":[
        {
            "category":"Retail",
            "subcategory":"Auto Repair",
            "type":"Services"
        }
    ],
    "sg:phone":"+1 909 996 0906",
    "sg:postcode":"92408",
    "sg:province":"CA",
    "sg:tags":[
        "body",
        "automobile",
        "painting"
    ],
    "wof:name":"Dent Source",
    "wof:placetype":"venue"
},
  "geometry": {"coordinates":[-117.286035,34.051017],"type":"Point"}
}