{
  "type": "Feature",
  "properties": {
    "addr:full":"1439 W Collins Ave Orange CA 92867",
    "addr:housenumber":"1439",
    "addr:postcode":"92867",
    "addr:street":"W Collins Ave",
    "iso:country":"US",
    "sg:address":"1439 W Collins Ave",
    "sg:city":"Orange",
    "sg:classifiers":[
        {
            "category":"Retail",
            "subcategory":"Auto Repair",
            "type":"Services"
        }
    ],
    "sg:phone":"+1 714 997 1955",
    "sg:postcode":"92867",
    "sg:province":"CA",
    "wof:name":"Old Town Orange Automotive",
    "wof:placetype":"venue"
},
  "geometry": {"coordinates":[-117.868048,33.802445],"type":"Point"}
}