{
  "type": "Feature",
  "properties": {
    "iso:country":"US",
    "sg:address":"8531 Wellsford Pl",
    "sg:city":"Santa Fe Springs",
    "sg:classifiers":[
        {
            "category":"Wholesale",
            "subcategory":"Electrical",
            "type":"Manufacturing & Wholesale Goods"
        }
    ],
    "sg:phone":"+1 562 945 5221",
    "sg:postcode":"90670",
    "sg:province":"CA",
    "sg:tags":[
        "light",
        "bulb"
    ],
    "wof:name":"Edgenet",
    "wof:placetype":"venue"
},
  "geometry": {"coordinates":[-118.058752,33.964592],"type":"Point"}
}