{
  "type": "Feature",
  "properties": {
    "iso:country":"US",
    "sg:address":"1015 E Robidoux St",
    "sg:city":"Wilmington",
    "sg:classifiers":[
        {
            "category":"Professional",
            "type":"Services"
        }
    ],
    "sg:phone":"+1 310 549 8957",
    "sg:postcode":"90744",
    "sg:province":"CA",
    "sg:tags":[
        "establishment"
    ],
    "wof:name":"M T Gomez",
    "wof:placetype":"venue"
},
  "geometry": {"coordinates":[-118.248019,33.788495],"type":"Point"}
}