{
  "type": "Feature",
  "properties": {
    "addr:full":"1842 Washington Way Venice CA 90291",
    "addr:housenumber":"1842",
    "addr:postcode":"90291",
    "addr:street":"Washington Way",
    "iso:country":"US",
    "sg:address":"1842 Washington Way",
    "sg:city":"Venice",
    "sg:classifiers":[
        {
            "category":"Professional",
            "subcategory":"Accounting & Tax Preparation",
            "type":"Services"
        }
    ],
    "sg:phone":"+1 310 823 6363",
    "sg:postcode":"90291",
    "sg:province":"CA",
    "sg:tags":[
        "return",
        "filing"
    ],
    "wof:name":"Sarlo Income Tax",
    "wof:placetype":"venue"
},
  "geometry": {"coordinates":[-118.459968,33.987841],"type":"Point"}
}