{
  "type": "Feature",
  "properties": {
    "addr:full":"3201 Loma Verde Dr San Jose CA 95117",
    "addr:housenumber":"3201",
    "addr:postcode":"95117",
    "addr:street":"Loma Verde Dr",
    "iso:country":"US",
    "sg:address":"3201 Loma Verde Dr",
    "sg:city":"San Jose",
    "sg:classifiers":[
        {
            "category":"Wholesale",
            "subcategory":"Medical Equipment & Supplies",
            "type":"Manufacturing & Wholesale Goods"
        }
    ],
    "sg:phone":"+1 408 374 7181",
    "sg:postcode":"95117",
    "sg:province":"CA",
    "wof:name":"Shersons",
    "wof:placetype":"venue"
},
  "geometry": {"coordinates":[-121.95438900000001,37.298871],"type":"Point"}
}