{
  "type": "Feature",
  "properties": {
    "iso:country":"US",
    "sg:address":"5834 Robertson Ave",
    "sg:city":"Carmichael",
    "sg:classifiers":[
        {
            "category":"Home & Garden",
            "subcategory":"Building Materials",
            "type":"Retail Goods"
        },
        {
            "category":"Building & Trades",
            "subcategory":"Construction",
            "type":"Services"
        },
        {
            "category":"Home & Garden",
            "subcategory":"Furniture",
            "type":"Retail Goods"
        }
    ],
    "sg:phone":"+1 916 944 0906",
    "sg:postcode":"95608",
    "sg:province":"CA",
    "sg:tags":[
        "supply",
        "altering",
        "equipment-household",
        "contractor",
        "planning",
        "design",
        "interior",
        "cabinet",
        "remodeling",
        "maker",
        "kitchen"
    ],
    "sg:website":"www.narfinecarpentry.com",
    "wof:name":"Nar Fine Carpentry",
    "wof:placetype":"venue"
},
  "geometry": {"coordinates":[-121.32911900000001,38.620765],"type":"Point"}
}