{
  "type": "Feature",
  "properties": {
    "iso:country":"US",
    "sg:address":"604 Main St",
    "sg:city":"Half Moon Bay",
    "sg:classifiers":[
        {
            "category":"Personal",
            "subcategory":"Beauty Salon",
            "type":"Services"
        }
    ],
    "sg:phone":"+1 650 726 8152",
    "sg:postcode":"94019",
    "sg:province":"CA",
    "sg:tags":[
        "manicuring"
    ],
    "wof:name":"Nail Elegant",
    "wof:placetype":"venue"
},
  "geometry": {"coordinates":[-122.429605,37.461646],"type":"Point"}
}