{
  "type": "Feature",
  "properties": {
    "addr:full":"3523 Clayton Rd Concord CA 94519",
    "addr:housenumber":"3523",
    "addr:postcode":"94519",
    "addr:street":"Clayton Rd",
    "iso:country":"US",
    "sg:address":"3523 Clayton Rd",
    "sg:city":"Concord",
    "sg:classifiers":[
        {
            "category":"Retail",
            "subcategory":"Laundry & Dry Cleaning",
            "type":"Services"
        }
    ],
    "sg:phone":"+1 925 825 8910",
    "sg:postcode":"94519",
    "sg:province":"CA",
    "sg:tags":[
        "cleaners"
    ],
    "wof:name":"Tlc Cleaners",
    "wof:placetype":"venue"
},
  "geometry": {"coordinates":[-122.011748,37.970809],"type":"Point"}
}