{
  "type": "Feature",
  "properties": {
    "addr:full":"3586 Santa Anita Ave El Monte CA 91731",
    "addr:housenumber":"3586",
    "addr:postcode":"91731",
    "addr:street":"Santa Anita Ave",
    "iso:country":"US",
    "sg:address":"3586 Santa Anita Ave",
    "sg:city":"El Monte",
    "sg:classifiers":[
        {
            "category":"Restaurant",
            "type":"Food & Drink"
        }
    ],
    "sg:phone":"+1 626 454 5481",
    "sg:postcode":"91731",
    "sg:province":"CA",
    "sg:tags":[
        "mexican"
    ],
    "wof:name":"Alfredo's Mexican Food",
    "wof:placetype":"venue"
},
  "geometry": {"coordinates":[-118.042,34.0737],"type":"Point"}
}