{
  "type": "Feature",
  "properties": {
    "iso:country":"US",
    "sg:address":"15829 Imperial Hwy",
    "sg:city":"La Mirada",
    "sg:classifiers":[
        {
            "category":"Shopping",
            "subcategory":"Pets & Pet Supplies",
            "type":"Retail Goods"
        }
    ],
    "sg:phone":"+1 562 947 4530",
    "sg:postcode":"90638",
    "sg:province":"CA",
    "sg:tags":[
        "groomers"
    ],
    "wof:name":"Ooh Puppy",
    "wof:placetype":"venue"
},
  "geometry": {"coordinates":[-117.993338,33.917366],"type":"Point"}
}