{
  "type": "Feature",
  "properties": {
    "iso:country":"US",
    "sg:address":"1522 Carlisle Dr",
    "sg:city":"San Mateo",
    "sg:classifiers":[
        {
            "category":"Real Estate",
            "subcategory":"Real Estate Services",
            "type":"Services"
        }
    ],
    "sg:phone":"+1 650 571 5300",
    "sg:postcode":"94402",
    "sg:province":"CA",
    "sg:tags":[
        "home",
        "inspector"
    ],
    "sg:website":"www.npiweb.com/Default.aspx?alia...",
    "wof:name":"Dean Stocker - Comprehensive Realty Inspections",
    "wof:placetype":"venue"
},
  "geometry": {"coordinates":[-122.30495999999999,37.560903],"type":"Point"}
}