{
  "type": "Feature",
  "properties": {
    "addr:full":"12220 Kirkham Rd Poway CA 92064",
    "addr:housenumber":"12220",
    "addr:postcode":"ca 92064",
    "addr:street":"Kirkham Rd",
    "iso:country":"US",
    "sg:address":"12220 Kirkham Rd",
    "sg:city":"Poway",
    "sg:classifiers":[
        {
            "category":"Wholesale",
            "subcategory":"Non-durable Goods",
            "type":"Manufacturing & Wholesale Goods"
        },
        {
            "category":"Professional",
            "subcategory":"Business Services",
            "type":"Services"
        }
    ],
    "sg:phone":"+1 858 513 3913",
    "sg:postcode":"92064",
    "sg:province":"CA",
    "sg:tags":[
        "dry",
        "party",
        "goods-wholesale",
        "supplies-wholesale",
        "manufacturer"
    ],
    "wof:name":"Poway Warehose Distribution",
    "wof:placetype":"venue"
},
  "geometry": {"coordinates":[-117.051059,32.939901],"type":"Point"}
}