{
  "type": "Feature",
  "properties": {
    "addr:full":"10350 Mission Gorge Rd Santee CA 92071",
    "addr:housenumber":"10350",
    "addr:postcode":"92071",
    "addr:street":"Mission Gorge Rd",
    "iso:country":"US",
    "sg:address":"10350 Mission Gorge Rd",
    "sg:city":"Santee",
    "sg:classifiers":[
        {
            "category":"Autos & Motor Vehicles",
            "subcategory":"Auto Supplies",
            "type":"Retail Goods"
        }
    ],
    "sg:phone":"+1 619 448 9110",
    "sg:postcode":"92071",
    "sg:province":"CA",
    "sg:tags":[
        "automobile",
        "parts"
    ],
    "wof:name":"Johnson's Bug Machine & Racing",
    "wof:placetype":"venue"
},
  "geometry": {"coordinates":[-116.97179199999999,32.838504],"type":"Point"}
}