{
  "type": "Feature",
  "properties": {
    "addr:full":"3527 Mt Diablo Blvd Lafayette CA 94549",
    "addr:housenumber":"3527",
    "addr:postcode":"94549",
    "addr:street":"Mt Diablo Blvd",
    "iso:country":"US",
    "sg:address":"3527 Mt Diablo Blvd",
    "sg:city":"Lafayette",
    "sg:classifiers":[
        {
            "category":"Professional",
            "subcategory":"Lawyer & Legal Services",
            "type":"Services"
        }
    ],
    "sg:phone":"+1 925 947 1540",
    "sg:postcode":"94549",
    "sg:province":"CA",
    "sg:tags":[
        "attorney"
    ],
    "wof:name":"Lawrence Kaplan",
    "wof:placetype":"venue"
},
  "geometry": {"coordinates":[-122.12016300000001,37.891754],"type":"Point"}
}