{
  "type": "Feature",
  "properties": {
    "addr:full":"1889 Mount Diablo Blvd Walnut Creek CA 94596",
    "addr:housenumber":"1889",
    "addr:postcode":"94596",
    "addr:street":"Mount Diablo Blvd",
    "iso:country":"US",
    "sg:address":"1889 Mount Diablo Blvd",
    "sg:city":"Walnut Creek",
    "sg:classifiers":[
        {
            "category":"Wholesale",
            "subcategory":"Construction Materials",
            "type":"Manufacturing & Wholesale Goods"
        }
    ],
    "sg:phone":"+1 925 210 1042",
    "sg:postcode":"94596",
    "sg:province":"CA",
    "sg:tags":[
        "slate"
    ],
    "sg:website":"www.americanslate.com",
    "wof:name":"American Slate Company",
    "wof:placetype":"venue"
},
  "geometry": {"coordinates":[-122.06659500000001,37.897296],"type":"Point"}
}