{
  "type": "Feature",
  "properties": {
    "addr:full":"410 Santa Ynez Way Sacramento CA 95816",
    "addr:housenumber":"410",
    "addr:postcode":"95816",
    "addr:street":"Santa Ynez Way",
    "iso:country":"US",
    "sg:address":"410 Santa Ynez Way",
    "sg:city":"Sacramento",
    "sg:classifiers":[
        {
            "category":"Building & Trades",
            "subcategory":"Landscaping Services",
            "type":"Services"
        }
    ],
    "sg:phone":"+1 916 452 7242",
    "sg:postcode":"95816",
    "sg:province":"CA",
    "sg:tags":[
        "tree"
    ],
    "wof:name":"Wenner Terry Glendenning",
    "wof:placetype":"venue"
},
  "geometry": {"coordinates":[-121.455544,38.577566],"type":"Point"}
}