{
  "type": "Feature",
  "properties": {
    "addr:full":"1222 1st Street, Suite 3 Coronado CA 92118",
    "addr:housenumber":"1222",
    "addr:postcode":"92118",
    "addr:street":"1St Street Suite 3",
    "iso:country":"US",
    "sg:address":"1222 1st Street, Suite 3",
    "sg:city":"Coronado",
    "sg:classifiers":[
        {
            "category":"Shopping",
            "subcategory":"Party Supplies",
            "type":"Retail Goods"
        },
        {
            "category":"Shopping",
            "subcategory":"Florist",
            "type":"Retail Goods"
        }
    ],
    "sg:phone":"+1 619 322 9568",
    "sg:postcode":"92118",
    "sg:province":"CA",
    "sg:website":"www.embellishmint.com",
    "wof:name":"Embellishmint",
    "wof:placetype":"venue"
},
  "geometry": {"coordinates":[-117.170951,32.697835],"type":"Point"}
}