{
  "type": "Feature",
  "properties": {
    "iso:country":"US",
    "sg:address":"2960 Van Ness Avenue",
    "sg:city":"San Francisco",
    "sg:classifiers":[
        {
            "category":"Professional",
            "subcategory":"Accounting & Tax Preparation",
            "type":"Services"
        }
    ],
    "sg:phone":"+1 415 775 9500",
    "sg:postcode":"94109",
    "sg:province":"CA",
    "sg:tags":[
        "accountant"
    ],
    "wof:name":"Terry Woo & Company",
    "wof:placetype":"venue"
},
  "geometry": {"coordinates":[-122.42071900000001,37.790727],"type":"Point"}
}