{
  "type": "Feature",
  "properties": {
    "addr:full":"1995 Froude St San Diego CA 92107",
    "addr:housenumber":"1995",
    "addr:postcode":"92107",
    "addr:street":"Froude St",
    "iso:country":"US",
    "sg:address":"1995 Froude St",
    "sg:city":"San Diego",
    "sg:classifiers":[
        {
            "category":"Building & Trades",
            "subcategory":"Plumbing",
            "type":"Services"
        }
    ],
    "sg:phone":"+1 619 222 6093",
    "sg:postcode":"92107",
    "sg:province":"CA",
    "sg:tags":[
        "contractor"
    ],
    "wof:name":"Mt Plumbing",
    "wof:placetype":"venue"
},
  "geometry": {"coordinates":[-117.242886,32.743902],"type":"Point"}
}