{
  "type": "Feature",
  "properties": {
    "iso:country":"US",
    "sg:address":"1001 Marina Village Pkwy",
    "sg:city":"Alameda",
    "sg:classifiers":[
        {
            "category":"Professional",
            "subcategory":"Lawyer & Legal Services",
            "type":"Services"
        }
    ],
    "sg:phone":"+1 510 523 5272",
    "sg:postcode":"94501",
    "sg:province":"CA",
    "wof:name":"Mitchell Kenneth E",
    "wof:placetype":"venue"
},
  "geometry": {"coordinates":[-122.271558,37.784607],"type":"Point"}
}