{
  "type": "Feature",
  "properties": {
    "addr:full":"2617 S Main St Lakeport CA 95453",
    "addr:housenumber":"2617",
    "addr:postcode":"95453",
    "addr:street":"S Main St",
    "iso:country":"US",
    "sg:address":"2617 S Main St",
    "sg:city":"Lakeport",
    "sg:classifiers":[
        {
            "category":"Professional",
            "subcategory":"Computer Services",
            "type":"Services"
        }
    ],
    "sg:phone":"+1 707 263 3364",
    "sg:postcode":"95453",
    "sg:province":"CA",
    "sg:tags":[
        "internet"
    ],
    "wof:name":"Internet Private Harvest",
    "wof:placetype":"venue"
},
  "geometry": {"coordinates":[-122.91304599999999,39.019029],"type":"Point"}
}