{
  "type": "Feature",
  "properties": {
    "iso:country":"US",
    "sg:address":"551 N Date St",
    "sg:city":"Escondido",
    "sg:classifiers":[
        {
            "category":"Real Estate",
            "subcategory":"Real Estate Operator",
            "type":"Services"
        }
    ],
    "sg:phone":"+1 760 738 0083",
    "sg:postcode":"92025",
    "sg:province":"CA",
    "sg:tags":[
        "building",
        "apartment"
    ],
    "wof:name":"Stonewood Villas",
    "wof:placetype":"venue"
},
  "geometry": {"coordinates":[-117.072263,33.130037],"type":"Point"}
}