{
  "type": "Feature",
  "properties": {
    "addr:full":"1250 Arnold Way Alpine CA 91901",
    "addr:housenumber":"1250",
    "addr:postcode":"91901",
    "addr:street":"Arnold Way",
    "iso:country":"US",
    "sg:address":"1250 Arnold Way",
    "sg:city":"Alpine",
    "sg:classifiers":[
        {
            "category":"Health Services",
            "subcategory":"Chiropractor",
            "type":"Services"
        }
    ],
    "sg:phone":"+1 619 445 7676",
    "sg:postcode":"91901",
    "sg:province":"CA",
    "wof:name":"Alpine Chiropractic Wellness",
    "wof:placetype":"venue"
},
  "geometry": {"coordinates":[-116.790432,32.833598],"type":"Point"}
}