{
  "type": "Feature",
  "properties": {
    "iso:country":"US",
    "sg:address":"4332 South St",
    "sg:city":"Lakewood",
    "sg:classifiers":[
        {
            "category":"Shopping",
            "subcategory":"Pets & Pet Supplies",
            "type":"Retail Goods"
        },
        {
            "category":"Retail",
            "subcategory":"Animal Services",
            "type":"Services"
        }
    ],
    "sg:phone":"+1 562 529 8414",
    "sg:postcode":"90712",
    "sg:province":"CA",
    "sg:tags":[
        "store"
    ],
    "sg:website":"www.yourelegantpet.com",
    "wof:name":"Your Elegant Pet",
    "wof:placetype":"venue"
},
  "geometry": {"coordinates":[-118.141313,33.860238],"type":"Point"}
}