{
  "type": "Feature",
  "properties": {
    "iso:country":"US",
    "sg:address":"20307 S Western Ave",
    "sg:city":"Torrance",
    "sg:classifiers":[
        {
            "category":"Social Services",
            "subcategory":"Job Training",
            "type":"Services"
        }
    ],
    "sg:phone":"+1 310 328 2822",
    "sg:postcode":"90501",
    "sg:province":"CA",
    "sg:tags":[
        "retardation",
        "disabled",
        "mental",
        "dev"
    ],
    "sg:website":"www.elwyn.org",
    "wof:name":"California Elwyn Inc",
    "wof:placetype":"venue"
},
  "geometry": {"coordinates":[-118.309352,33.845709],"type":"Point"}
}