{
  "type": "Feature",
  "properties": {
    "iso:country":"US",
    "sg:address":"27322 E el Macero Dr",
    "sg:city":"Davis",
    "sg:classifiers":[
        {
            "category":"Health Services",
            "subcategory":"Doctor",
            "type":"Services"
        }
    ],
    "sg:phone":"+1 530 758 8285",
    "sg:postcode":"95618",
    "sg:province":"CA",
    "sg:tags":[
        "medical"
    ],
    "wof:name":"James F McMahon MD Inc",
    "wof:placetype":"venue"
},
  "geometry": {"coordinates":[-121.676803,38.54153],"type":"Point"}
}