{
  "type": "Feature",
  "properties": {
    "addr:full":"3659 Santa Maria Ct Castro Valley CA 94546",
    "addr:housenumber":"3659",
    "addr:postcode":"94546",
    "addr:street":"Santa Maria Ct",
    "iso:country":"US",
    "sg:address":"3659 Santa Maria Ct",
    "sg:city":"Castro Valley",
    "sg:classifiers":[
        {
            "category":"Home & Garden",
            "subcategory":"Hardware",
            "type":"Retail Goods"
        }
    ],
    "sg:phone":"+1 510 537 1178",
    "sg:postcode":"94546",
    "sg:province":"CA",
    "sg:tags":[
        "industrial",
        "supply"
    ],
    "wof:name":"Tool Network",
    "wof:placetype":"venue"
},
  "geometry": {"coordinates":[-122.078929,37.700903],"type":"Point"}
}