{
  "type": "Feature",
  "properties": {
    "addr:full":"1515 Q St Sacramento CA 95857",
    "addr:housenumber":"1515",
    "addr:postcode":"95857",
    "addr:street":"Q St",
    "iso:country":"US",
    "sg:address":"1515 Q St",
    "sg:city":"Sacramento",
    "sg:classifiers":[
        {
            "category":"Park",
            "type":"Public Place"
        },
        {
            "category":"Recreation",
            "subcategory":"Playground",
            "type":"Entertainment"
        }
    ],
    "sg:postcode":"95857",
    "sg:province":"CA",
    "sg:website":"www.cityofsacramento.org/parksan...",
    "wof:name":"Fremont Park",
    "wof:placetype":"venue"
},
  "geometry": {"coordinates":[-121.48969700000001,38.570685],"type":"Point"}
}