{
  "type": "Feature",
  "properties": {
    "iso:country":"US",
    "sg:address":"1762 Hamilton Avenue",
    "sg:city":"San Jose",
    "sg:classifiers":[
        {
            "category":"Banks & Credit Unions",
            "subcategory":"Financial Services",
            "type":"Services"
        }
    ],
    "sg:phone":"+1 408 267 5000",
    "sg:postcode":"95125",
    "sg:province":"CA",
    "sg:tags":[
        "broker",
        "mortgage"
    ],
    "wof:name":"Bay Residential Mortgage Networks",
    "wof:placetype":"venue"
},
  "geometry": {"coordinates":[-121.91707599999999,37.294524],"type":"Point"}
}