{
  "type": "Feature",
  "properties": {
    "iso:country":"US",
    "sg:address":"861 6th Ave",
    "sg:city":"San Diego",
    "sg:classifiers":[
        {
            "category":"Wholesale",
            "subcategory":"Jewelry",
            "type":"Manufacturing & Wholesale Goods"
        }
    ],
    "sg:phone":"+1 619 232 2624",
    "sg:postcode":"92101",
    "sg:province":"CA",
    "sg:tags":[
        "stone",
        "jeweler"
    ],
    "wof:name":"Thomas M Schneider",
    "wof:placetype":"venue"
},
  "geometry": {"coordinates":[-117.159172,32.714028],"type":"Point"}
}