{
  "type": "Feature",
  "properties": {
    "addr:full":"2822 W Rialto Ave Rialto CA 92376",
    "addr:housenumber":"2822",
    "addr:postcode":"92376",
    "addr:street":"W Rialto Ave",
    "iso:country":"US",
    "sg:address":"2822 W Rialto Ave",
    "sg:city":"Rialto",
    "sg:classifiers":[
        {
            "category":"Retail",
            "subcategory":"Laundry & Dry Cleaning",
            "type":"Services"
        }
    ],
    "sg:phone":"+1 909 874 2623",
    "sg:postcode":"92376",
    "sg:province":"CA",
    "sg:tags":[
        "cleaners"
    ],
    "wof:name":"Star Cleaners",
    "wof:placetype":"venue"
},
  "geometry": {"coordinates":[-117.350317,34.099632],"type":"Point"}
}