{
  "type": "Feature",
  "properties": {
    "iso:country":"US",
    "sg:address":"4401 Eastgate Mall",
    "sg:city":"San Diego",
    "sg:classifiers":[
        {
            "category":"Banks & Credit Unions",
            "subcategory":"Investment Brokerage",
            "type":"Services"
        }
    ],
    "sg:phone":"+1 858 677 0600",
    "sg:postcode":"92121",
    "sg:province":"CA",
    "sg:tags":[
        "management"
    ],
    "wof:name":"Kingsbury Associates",
    "wof:placetype":"venue"
},
  "geometry": {"coordinates":[-117.213154,32.87768],"type":"Point"}
}