{
  "type": "Feature",
  "properties": {
    "addr:full":"483 Pimentel Way Sacramento CA 95831",
    "addr:housenumber":"483",
    "addr:postcode":"95831",
    "addr:street":"Pimentel Way",
    "iso:country":"US",
    "sg:address":"483 Pimentel Way",
    "sg:city":"Sacramento",
    "sg:classifiers":[
        {
            "category":"Building & Trades",
            "subcategory":"Landscaping Services",
            "type":"Services"
        }
    ],
    "sg:phone":"+1 916 421 6725",
    "sg:postcode":"95831",
    "sg:province":"CA",
    "sg:tags":[
        "aged",
        "homes-institutional"
    ],
    "wof:name":"Macklin & Associates",
    "wof:placetype":"venue"
},
  "geometry": {"coordinates":[-121.54530699999999,38.491767],"type":"Point"}
}