{
  "type": "Feature",
  "properties": {
    "addr:full":"8757 Washington Blvd. Culver City CA 90232",
    "addr:housenumber":"8757",
    "addr:postcode":"90232",
    "addr:street":"Washington Blvd.",
    "iso:country":"US",
    "sg:address":"8757 Washington Blvd.",
    "sg:city":"Culver City",
    "sg:classifiers":[
        {
            "category":"Insurance",
            "subcategory":"Hazard Insurance",
            "type":"Services"
        }
    ],
    "sg:phone":"+1 310 405 4250",
    "sg:postcode":"90232",
    "sg:province":"CA",
    "sg:website":"www.peninsulageneral.com",
    "wof:name":"Peninsula General Health Insurance",
    "wof:placetype":"venue"
},
  "geometry": {"coordinates":[-118.386154,34.028498],"type":"Point"}
}