{
  "type": "Feature",
  "properties": {
    "iso:country":"US",
    "sg:address":"20720 Estel Ln",
    "sg:city":"Red Bluff",
    "sg:classifiers":[
        {
            "category":"Building & Trades",
            "subcategory":"Electrical",
            "type":"Services"
        }
    ],
    "sg:phone":"+1 530 529 4948",
    "sg:postcode":"96080",
    "sg:province":"CA",
    "sg:tags":[
        "electrical",
        "contractor"
    ],
    "wof:name":"Johnson Electric",
    "wof:placetype":"venue"
},
  "geometry": {"coordinates":[-122.267294,40.189375],"type":"Point"}
}