{
  "type": "Feature",
  "properties": {
    "addr:full":"3695 India St San Diego CA 92103",
    "addr:housenumber":"3695",
    "addr:postcode":"92103",
    "addr:street":"India St",
    "iso:country":"US",
    "sg:address":"3695 India St",
    "sg:city":"San Diego",
    "sg:classifiers":[
        {
            "category":"Restaurant",
            "type":"Food & Drink"
        }
    ],
    "sg:phone":"+1 619 299 0333",
    "sg:postcode":"92103",
    "sg:province":"CA",
    "sg:tags":[
        "mexican"
    ],
    "wof:name":"El Indio",
    "wof:placetype":"venue"
},
  "geometry": {"coordinates":[-117.180221,32.742296],"type":"Point"}
}