{
  "type": "Feature",
  "properties": {
    "addr:full":"2644 Bayshore Pkwy Mountain View CA 94043",
    "addr:housenumber":"2644",
    "addr:postcode":"94043",
    "addr:street":"Bayshore Pkwy",
    "iso:country":"US",
    "sg:address":"2644 Bayshore Pkwy",
    "sg:city":"Mountain View",
    "sg:classifiers":[
        {
            "category":"Professional",
            "type":"Services"
        }
    ],
    "sg:phone":"+1 650 965 1231",
    "sg:postcode":"94043",
    "sg:province":"CA",
    "sg:tags":[
        "scientist"
    ],
    "wof:name":"Nano Craft Electron Microscopy",
    "wof:placetype":"venue"
},
  "geometry": {"coordinates":[-122.099351,37.427694],"type":"Point"}
}