{
  "type": "Feature",
  "properties": {
    "iso:country":"US",
    "sg:address":"116 Los Cerritos Mall",
    "sg:city":"Cerritos",
    "sg:classifiers":[
        {
            "category":"Shopping",
            "subcategory":"Pets & Pet Supplies",
            "type":"Retail Goods"
        }
    ],
    "sg:phone":"+1 562 402 9237",
    "sg:postcode":"90703",
    "sg:province":"CA",
    "sg:tags":[
        "store"
    ],
    "sg:website":"www.barkworks.com",
    "wof:name":"Barkworks",
    "wof:placetype":"venue"
},
  "geometry": {"coordinates":[-118.092786,33.862543],"type":"Point"}
}