{
  "type": "Feature",
  "properties": {
    "addr:full":"1117 Powell Street San Francisco CA 94108",
    "addr:housenumber":"1117",
    "addr:postcode":"94108",
    "addr:street":"Powell Street",
    "iso:country":"US",
    "sg:address":"1117 Powell Street",
    "sg:city":"San Francisco",
    "sg:classifiers":[
        {
            "category":"Personal",
            "subcategory":"Beauty Salon",
            "type":"Services"
        }
    ],
    "sg:phone":"+1 415 982 2833",
    "sg:postcode":"94108",
    "sg:province":"CA",
    "sg:tags":[
        "hair"
    ],
    "wof:name":"Jenny Hair Studio",
    "wof:placetype":"venue"
},
  "geometry": {"coordinates":[-122.410004,37.795101],"type":"Point"}
}