{
  "type": "Feature",
  "properties": {
    "addr:full":"2320 Mark West Springs Rd Santa Rosa CA 95404",
    "addr:housenumber":"2320",
    "addr:postcode":"95404",
    "addr:street":"Mark West Springs Rd",
    "iso:country":"US",
    "sg:address":"2320 Mark West Springs Rd",
    "sg:city":"Santa Rosa",
    "sg:classifiers":[
        {
            "category":"Social Services",
            "type":"Services"
        }
    ],
    "sg:phone":"+1 707 571 7558",
    "sg:postcode":"95404",
    "sg:province":"CA",
    "sg:tags":[
        "worker"
    ],
    "wof:name":"National Assn-Social Workers",
    "wof:placetype":"venue"
},
  "geometry": {"coordinates":[-122.720468,38.547464],"type":"Point"}
}