{
  "type": "Feature",
  "properties": {
    "iso:country":"US",
    "sg:address":"7200 Bandini Blvd",
    "sg:city":"City Of Commerce",
    "sg:classifiers":[
        {
            "category":"Home & Garden",
            "subcategory":"Furniture",
            "type":"Retail Goods"
        }
    ],
    "sg:phone":"+1 323 888 2085",
    "sg:postcode":"90040",
    "sg:province":"CA",
    "wof:name":"Kids Center",
    "wof:placetype":"venue"
},
  "geometry": {"coordinates":[-118.132859,33.983404],"type":"Point"}
}