{
  "type": "Feature",
  "properties": {
    "addr:full":"13699 E Manning Ave Parlier CA 93648",
    "addr:housenumber":"13699",
    "addr:postcode":"93648",
    "addr:street":"E Manning Ave",
    "iso:country":"US",
    "sg:address":"13699 E Manning Ave",
    "sg:city":"Parlier",
    "sg:classifiers":[
        {
            "category":"Shopping",
            "subcategory":"Music",
            "type":"Retail Goods"
        }
    ],
    "sg:phone":"+1 559 646 0999",
    "sg:postcode":"93648",
    "sg:province":"CA",
    "sg:tags":[
        "video",
        "disc",
        "tape",
        "cassette"
    ],
    "wof:name":"Movie Gallery",
    "wof:placetype":"venue"
},
  "geometry": {"coordinates":[-119.54365900000001,36.604823],"type":"Point"}
}