{
  "type": "Feature",
  "properties": {
    "iso:country":"US",
    "sg:address":"11424 Aberdeen Dr",
    "sg:city":"Fontana",
    "sg:classifiers":[
        {
            "category":"Personal",
            "type":"Services"
        }
    ],
    "sg:phone":"+1 909 854 0825",
    "sg:postcode":"92337",
    "sg:province":"CA",
    "sg:tags":[
        "party",
        "planning",
        "event"
    ],
    "wof:name":"Event Planning Everlasting Vision",
    "wof:placetype":"venue"
},
  "geometry": {"coordinates":[-117.46317000000001,34.044935],"type":"Point"}
}