{
  "type": "Feature",
  "properties": {
    "iso:country":"US",
    "sg:address":"55 Shaver St",
    "sg:city":"San Rafael",
    "sg:classifiers":[
        {
            "category":"Professional",
            "subcategory":"Accounting & Tax Preparation",
            "type":"Services"
        }
    ],
    "sg:phone":"+1 415 479 4006",
    "sg:postcode":"94901",
    "sg:province":"CA",
    "sg:tags":[
        "return",
        "filing"
    ],
    "wof:name":"Deep In The Art Of Taxes",
    "wof:placetype":"venue"
},
  "geometry": {"coordinates":[-122.534801,37.972186],"type":"Point"}
}