{
  "type": "Feature",
  "properties": {
    "iso:country":"US",
    "sg:address":"11930 Banner Dr Suite 71",
    "sg:city":"Garden Grove",
    "sg:classifiers":[
        {
            "category":"Professional",
            "subcategory":"Art Services",
            "type":"Services"
        },
        {
            "category":"Communications",
            "type":"Services"
        }
    ],
    "sg:phone":"+1 866 731 7773",
    "sg:postcode":"92843",
    "sg:province":"CA",
    "sg:tags":[
        "web",
        "graphic",
        "design"
    ],
    "wof:name":"Avant Garde Productions",
    "wof:placetype":"venue"
},
  "geometry": {"coordinates":[-117.921952,33.768127],"type":"Point"}
}