{
  "type": "Feature",
  "properties": {
    "addr:full":"543 Orange Ave Coronado CA 92118",
    "addr:housenumber":"543",
    "addr:postcode":"92118",
    "addr:street":"Orange Ave",
    "iso:country":"US",
    "sg:address":"543 Orange Ave",
    "sg:city":"Coronado",
    "sg:classifiers":[
        {
            "category":"Health Services",
            "subcategory":"Doctor",
            "type":"Services"
        }
    ],
    "sg:phone":"+1 619 435 6231",
    "sg:postcode":"92118",
    "sg:province":"CA",
    "sg:tags":[
        "dentist"
    ],
    "wof:name":"Lee M Skaalen DDS",
    "wof:placetype":"venue"
},
  "geometry": {"coordinates":[-117.17610500000001,32.692189],"type":"Point"}
}