{
  "type": "Feature",
  "properties": {
    "iso:country":"US",
    "sg:address":"1177 W Hammer Ln",
    "sg:city":"Stockton",
    "sg:classifiers":[
        {
            "category":"Home & Garden",
            "subcategory":"Furniture",
            "type":"Retail Goods"
        }
    ],
    "sg:phone":"+1 209 472 1508",
    "sg:postcode":"95209",
    "sg:province":"CA",
    "sg:tags":[
        "equipment"
    ],
    "wof:name":"Furniture Discounters",
    "wof:placetype":"venue"
},
  "geometry": {"coordinates":[-121.325726,38.021132],"type":"Point"}
}