{
  "type": "Feature",
  "properties": {
    "iso:country":"US",
    "sg:address":"1163 Chess Dr Ste K",
    "sg:city":"Foster City",
    "sg:classifiers":[
        {
            "category":"Shopping",
            "subcategory":"Discount & Variety Stores",
            "type":"Retail Goods"
        },
        {
            "category":"Wholesale",
            "subcategory":"Computers",
            "type":"Manufacturing & Wholesale Goods"
        }
    ],
    "sg:phone":"+1 650 212 3198",
    "sg:postcode":"94404",
    "sg:province":"CA",
    "sg:website":"tier1pc.com",
    "wof:name":"Tier1PC",
    "wof:placetype":"venue"
},
  "geometry": {"coordinates":[-122.272464,37.566344],"type":"Point"}
}