{
  "type": "Feature",
  "properties": {
    "iso:country":"US",
    "sg:address":"1822 Aston Ave",
    "sg:city":"Carlsbad",
    "sg:classifiers":[
        {
            "category":"Health Services",
            "subcategory":"Dentist",
            "type":"Services"
        }
    ],
    "sg:phone":"+1 760 804 5823",
    "sg:postcode":"92008",
    "sg:province":"CA",
    "sg:tags":[
        "equipment",
        "dental",
        "supply"
    ],
    "wof:name":"Henry Schein",
    "wof:placetype":"venue"
},
  "geometry": {"coordinates":[-117.28890800000001,33.1323],"type":"Point"}
}