{
  "type": "Feature",
  "properties": {
    "addr:full":"1495 Auto Center Dr Ontario CA 91761",
    "addr:housenumber":"1495",
    "addr:postcode":"91761",
    "addr:street":"Auto Center Dr",
    "iso:country":"US",
    "sg:address":"1495 Auto Center Dr",
    "sg:city":"Ontario",
    "sg:classifiers":[
        {
            "category":"Freight",
            "type":"Transportation"
        }
    ],
    "sg:phone":"+1 909 390 4460",
    "sg:postcode":"91761",
    "sg:province":"CA",
    "sg:tags":[
        "warehouse",
        "self",
        "storage"
    ],
    "wof:name":"Adelphia Warehouse",
    "wof:placetype":"venue"
},
  "geometry": {"coordinates":[-117.544039,34.047945],"type":"Point"}
}