{
  "type": "Feature",
  "properties": {
    "addr:full":"3765 Oxford St Napa CA 94558",
    "addr:housenumber":"3765",
    "addr:postcode":"94558",
    "addr:street":"Oxford St",
    "iso:country":"US",
    "sg:address":"3765 Oxford St",
    "sg:city":"Napa",
    "sg:classifiers":[
        {
            "category":"Social Services",
            "subcategory":"Child Care",
            "type":"Services"
        }
    ],
    "sg:phone":"+1 707 252 9330",
    "sg:postcode":"94558",
    "sg:province":"CA",
    "wof:name":"Young World Of Learning",
    "wof:placetype":"venue"
},
  "geometry": {"coordinates":[-122.319321,38.325488],"type":"Point"}
}