{
  "type": "Feature",
  "properties": {
    "addr:full":"2720 Griffith Park Blvd Los Angeles CA 90027",
    "addr:housenumber":"2720",
    "addr:postcode":"90027",
    "addr:street":"Griffith Park Blvd",
    "iso:country":"US",
    "sg:address":"2720 Griffith Park Blvd",
    "sg:city":"Los Angeles",
    "sg:classifiers":[
        {
            "category":"Restaurant",
            "type":"Food & Drink"
        }
    ],
    "sg:phone":"+1 323 662 0978",
    "sg:postcode":"90027",
    "sg:province":"CA",
    "wof:name":"Song Hay Inn",
    "wof:placetype":"venue"
},
  "geometry": {"coordinates":[-118.27465599999999,34.108826],"type":"Point"}
}