{
  "type": "Feature",
  "properties": {
    "iso:country":"US",
    "sg:address":"4040 W Washington Blvd",
    "sg:city":"Los Angeles",
    "sg:classifiers":[
        {
            "category":"Retail",
            "subcategory":"Repair Shop",
            "type":"Services"
        }
    ],
    "sg:phone":"+1 323 737 6225",
    "sg:postcode":"90018",
    "sg:province":"CA",
    "sg:tags":[
        "jewelry"
    ],
    "wof:name":"Hubert Jewelry Repair",
    "wof:placetype":"venue"
},
  "geometry": {"coordinates":[-118.326821,34.039807],"type":"Point"}
}