{
  "type": "Feature",
  "properties": {
    "addr:full":"758 E 9th St Los Angeles CA 90021",
    "addr:housenumber":"758",
    "addr:postcode":"90021",
    "addr:street":"E 9Th St",
    "iso:country":"US",
    "sg:address":"758 E 9th St",
    "sg:city":"Los Angeles",
    "sg:classifiers":[
        {
            "category":"Shopping",
            "subcategory":"Crafts & Fabrics",
            "type":"Retail Goods"
        }
    ],
    "sg:phone":"+1 213 489 9755",
    "sg:postcode":"90021",
    "sg:province":"CA",
    "sg:tags":[
        "sewing"
    ],
    "wof:name":"Fabric Finance",
    "wof:placetype":"venue"
},
  "geometry": {"coordinates":[-118.24870199999999,34.035737],"type":"Point"}
}