{
  "type": "Feature",
  "properties": {
    "iso:country":"US",
    "sg:address":"126 Main St",
    "sg:city":"Watsonville",
    "sg:classifiers":[
        {
            "category":"Food & Beverages",
            "subcategory":"Groceries & Convenience Stores",
            "type":"Retail Goods"
        }
    ],
    "sg:phone":"+1 831 724 0886",
    "sg:postcode":"95076",
    "sg:province":"CA",
    "sg:tags":[
        "grocer"
    ],
    "wof:name":"Elvira's Market",
    "wof:placetype":"venue"
},
  "geometry": {"coordinates":[-121.75279999999999,36.906688],"type":"Point"}
}