{
  "type": "Feature",
  "properties": {
    "addr:full":"15878 Monterey St Morgan Hill CA 95037",
    "addr:housenumber":"15878",
    "addr:postcode":"95037",
    "addr:street":"Monterey St",
    "iso:country":"US",
    "sg:address":"15878 Monterey St",
    "sg:city":"Morgan Hill",
    "sg:classifiers":[
        {
            "category":"Food & Beverages",
            "subcategory":"Groceries & Convenience Stores",
            "type":"Retail Goods"
        }
    ],
    "sg:phone":"+1 408 778 5287",
    "sg:postcode":"95037",
    "sg:province":"CA",
    "sg:tags":[
        "product"
    ],
    "wof:name":"Fast Stop Food Store",
    "wof:placetype":"venue"
},
  "geometry": {"coordinates":[-121.640969,37.111213],"type":"Point"}
}