{
  "type": "Feature",
  "properties": {
    "iso:country":"US",
    "sg:address":"4512 Monaco St",
    "sg:city":"San Diego",
    "sg:classifiers":[
        {
            "category":"Building & Trades",
            "subcategory":"Cleaning & Sanitation",
            "type":"Services"
        }
    ],
    "sg:phone":"+1 619 523 1937",
    "sg:postcode":"92107",
    "sg:province":"CA",
    "sg:tags":[
        "window"
    ],
    "wof:name":"Lily's Window Cleaning",
    "wof:placetype":"venue"
},
  "geometry": {"coordinates":[-117.25634700000001,32.724046],"type":"Point"}
}