{
  "type": "Feature",
  "properties": {
    "addr:full":"360 Lafata St St Helena CA 94574",
    "addr:housenumber":"360",
    "addr:postcode":"94574",
    "addr:street":"Lafata St",
    "iso:country":"US",
    "sg:address":"360 Lafata St",
    "sg:city":"St Helena",
    "sg:classifiers":[
        {
            "category":"Farming",
            "subcategory":"Vineyard",
            "type":"Manufacturing & Wholesale Goods"
        }
    ],
    "sg:phone":"+1 707 963 7303",
    "sg:postcode":"94574",
    "sg:province":"CA",
    "wof:name":"Jack Neal & Son Inc",
    "wof:placetype":"venue"
},
  "geometry": {"coordinates":[-122.458726,38.500265],"type":"Point"}
}