{
  "type": "Feature",
  "properties": {
    "iso:country":"US",
    "sg:address":"21624 Ives Dr",
    "sg:city":"California City",
    "sg:classifiers":[
        {
            "category":"Manufacturing",
            "subcategory":"Wood Products",
            "type":"Manufacturing & Wholesale Goods"
        }
    ],
    "sg:phone":"+1 760 373 2247",
    "sg:postcode":"93505",
    "sg:province":"CA",
    "wof:name":"Bairs Engraving and Signs",
    "wof:placetype":"venue"
},
  "geometry": {"coordinates":[-117.936593,35.135828],"type":"Point"}
}