{
  "type": "Feature",
  "properties": {
    "addr:full":"4640 Lankershim Blvd North Hollywood CA 91602",
    "addr:postcode":"4640;91602",
    "addr:street":"Lankershim Blvd",
    "iso:country":"US",
    "sg:address":"4640 Lankershim Blvd",
    "sg:city":"North Hollywood",
    "sg:classifiers":[
        {
            "category":"Health Services",
            "subcategory":"Doctor",
            "type":"Services"
        }
    ],
    "sg:phone":"+1 818 762 6094",
    "sg:postcode":"91602",
    "sg:province":"CA",
    "sg:tags":[
        "clinic"
    ],
    "wof:name":"Integrated Medical Solutions",
    "wof:placetype":"venue"
},
  "geometry": {"coordinates":[-118.368982,34.155558],"type":"Point"}
}