{
  "type": "Feature",
  "properties": {
    "addr:full":"2325 Georgia St Napa CA 94559",
    "addr:housenumber":"2325",
    "addr:postcode":"94559",
    "addr:street":"Georgia St",
    "iso:country":"US",
    "sg:address":"2325 Georgia St",
    "sg:city":"Napa",
    "sg:classifiers":[
        {
            "category":"Banks & Credit Unions",
            "subcategory":"Bank",
            "type":"Services"
        }
    ],
    "sg:phone":"+1 707 257 6000",
    "sg:postcode":"94559",
    "sg:province":"CA",
    "sg:tags":[
        "broker",
        "mortgage"
    ],
    "wof:name":"Homes of NAPA Valley",
    "wof:placetype":"venue"
},
  "geometry": {"coordinates":[-122.297602,38.30791],"type":"Point"}
}