{
  "type": "Feature",
  "properties": {
    "iso:country":"US",
    "sg:address":"10323 Santa Monica Blvd #106",
    "sg:city":"Century City",
    "sg:classifiers":[
        {
            "category":"Personal",
            "subcategory":"Beauty Salon",
            "type":"Services"
        }
    ],
    "sg:phone":"+1 310 266 8514",
    "sg:postcode":"90025",
    "sg:province":"CA",
    "sg:tags":[
        "spa"
    ],
    "sg:website":"www.spiritualityspa.com/",
    "wof:name":"Spirituality Spa The Holistic Therapy Group",
    "wof:placetype":"venue"
},
  "geometry": {"coordinates":[-118.42236800000001,34.058736],"type":"Point"}
}