{
  "type": "Feature",
  "properties": {
    "iso:country":"US",
    "sg:address":"4729 Planz Rd",
    "sg:city":"Bakersfield",
    "sg:classifiers":[
        {
            "category":"Professional",
            "subcategory":"Lawyer & Legal Services",
            "type":"Services"
        },
        {
            "category":"Government",
            "subcategory":"Office",
            "type":"Public Place"
        }
    ],
    "sg:phone":"+1 661 836 9977",
    "sg:postcode":"93309",
    "sg:province":"CA",
    "sg:tags":[
        "executive",
        "naturalization",
        "immigration"
    ],
    "wof:name":"A Servicio De Inmigracion",
    "wof:placetype":"venue"
},
  "geometry": {"coordinates":[-119.056229,35.32498],"type":"Point"}
}