{
  "type": "Feature",
  "properties": {
    "addr:full":"442 Colyton St Los Angeles CA 90013",
    "addr:housenumber":"442",
    "addr:postcode":"90013",
    "addr:street":"Colyton St",
    "iso:country":"US",
    "sg:address":"442 Colyton St",
    "sg:city":"Los Angeles",
    "sg:classifiers":[
        {
            "category":"Manufacturing",
            "subcategory":"Apparel",
            "type":"Manufacturing & Wholesale Goods"
        }
    ],
    "sg:phone":"+1 213 680 0337",
    "sg:postcode":"90013",
    "sg:province":"CA",
    "sg:tags":[
        "shower",
        "curtain",
        "mfg"
    ],
    "wof:name":"Industrial Revolution",
    "wof:placetype":"venue"
},
  "geometry": {"coordinates":[-118.236243,34.042443],"type":"Point"}
}