{
  "type": "Feature",
  "properties": {
    "iso:country":"US",
    "sg:address":"17315 Coolwater Avenue Lk",
    "sg:city":"Los Angeles",
    "sg:classifiers":[
        {
            "category":"Social Services",
            "subcategory":"Child Care",
            "type":"Services"
        }
    ],
    "sg:phone":"+1 661 264 1920",
    "sg:postcode":"90001",
    "sg:province":"CA",
    "sg:tags":[
        "day"
    ],
    "sg:website":"www.littlebitofheaven.com",
    "wof:name":"Little Bit of Heaven",
    "wof:placetype":"venue"
},
  "geometry": {"coordinates":[-118.248999,33.974767],"type":"Point"}
}