{
  "type": "Feature",
  "properties": {
    "addr:full":"1646 E Washington St Colton CA 92324",
    "addr:housenumber":"1646",
    "addr:postcode":"92324",
    "addr:street":"E Washington St",
    "iso:country":"US",
    "sg:address":"1646 E Washington St",
    "sg:city":"Colton",
    "sg:classifiers":[
        {
            "category":"Retail",
            "subcategory":"Repair Shop",
            "type":"Services"
        }
    ],
    "sg:phone":"+1 909 825 2142",
    "sg:postcode":"92324",
    "sg:province":"CA",
    "sg:tags":[
        "lock",
        "locksmith"
    ],
    "wof:name":"Any Hour Lock & Safe",
    "wof:placetype":"venue"
},
  "geometry": {"coordinates":[-117.301405,34.04834],"type":"Point"}
}