{
  "type": "Feature",
  "properties": {
    "addr:full":"238 Commercial St Nevada City CA 95959",
    "addr:housenumber":"238",
    "addr:postcode":"95959",
    "addr:street":"Commercial St",
    "iso:country":"US",
    "sg:address":"238 Commercial St",
    "sg:city":"Nevada City",
    "sg:classifiers":[
        {
            "category":"Restaurant",
            "type":"Food & Drink"
        }
    ],
    "sg:phone":"+1 530 265 5757",
    "sg:postcode":"95959",
    "sg:province":"CA",
    "wof:name":"Sushi Q",
    "wof:placetype":"venue"
},
  "geometry": {"coordinates":[-121.018072,39.263189],"type":"Point"}
}