{
  "type": "Feature",
  "properties": {
    "iso:country":"US",
    "sg:address":"4000 Foothill Blvd",
    "sg:city":"Oakland",
    "sg:classifiers":[
        {
            "category":"Retail",
            "subcategory":"Repair Shop",
            "type":"Services"
        },
        {
            "category":"Professional",
            "subcategory":"Detective & Security Services",
            "type":"Services"
        }
    ],
    "sg:phone":"+1 510 534 2345",
    "sg:postcode":"94601",
    "sg:province":"CA",
    "sg:tags":[
        "skip",
        "tracing",
        "bail",
        "bond"
    ],
    "wof:name":"Christopher John Scott Bail Bonds",
    "wof:placetype":"venue"
},
  "geometry": {"coordinates":[-122.21534699999999,37.777828],"type":"Point"}
}