{
  "type": "Feature",
  "properties": {
    "addr:full":"1121 E Valley Blvd San Gabriel CA 91776",
    "addr:housenumber":"1121",
    "addr:postcode":"91776",
    "addr:street":"E Valley Blvd",
    "iso:country":"US",
    "sg:address":"1121 E Valley Blvd",
    "sg:city":"San Gabriel",
    "sg:classifiers":[
        {
            "category":"Health Services",
            "subcategory":"Doctor",
            "type":"Services"
        }
    ],
    "sg:phone":"+1 626 307 9288",
    "sg:postcode":"91776",
    "sg:province":"CA",
    "wof:name":"Sino America Medpach",
    "wof:placetype":"venue"
},
  "geometry": {"coordinates":[-118.42021800000001,34.057577],"type":"Point"}
}