{
  "type": "Feature",
  "properties": {
    "iso:country":"US",
    "sg:address":"103 N Garfield Ave Ste F",
    "sg:city":"Alhambra",
    "sg:classifiers":[
        {
            "category":"Health Services",
            "subcategory":"Doctor",
            "type":"Services"
        }
    ],
    "sg:phone":"+1 626 458 3276",
    "sg:postcode":"91801",
    "sg:province":"CA",
    "wof:name":"Brener Harry M MD Inc",
    "wof:placetype":"venue"
},
  "geometry": {"coordinates":[-118.126999,34.096001],"type":"Point"}
}