{
  "type": "Feature",
  "properties": {
    "addr:full":"10730 Valley Dr Plymouth CA 95669",
    "addr:housenumber":"10730",
    "addr:postcode":"95669",
    "addr:street":"Valley Dr",
    "iso:country":"US",
    "sg:address":"10730 Valley Dr",
    "sg:city":"Plymouth",
    "sg:classifiers":[
        {
            "category":"Manufacturing",
            "subcategory":"Food",
            "type":"Manufacturing & Wholesale Goods"
        }
    ],
    "sg:phone":"+1 209 245 4910",
    "sg:postcode":"95669",
    "sg:province":"CA",
    "sg:tags":[
        "winery"
    ],
    "sg:website":"www.amadorwinegrapes.com",
    "wof:name":"Amador County Wine Grape",
    "wof:placetype":"venue"
},
  "geometry": {"coordinates":[-120.827389,38.523947],"type":"Point"}
}