{
  "type": "Feature",
  "properties": {
    "iso:country":"US",
    "sg:address":"18612 Well St",
    "sg:city":"Rowland Heights",
    "sg:classifiers":[
        {
            "category":"Wholesale",
            "subcategory":"Apparel",
            "type":"Manufacturing & Wholesale Goods"
        }
    ],
    "sg:phone":"+1 626 581 1003",
    "sg:postcode":"91748",
    "sg:province":"CA",
    "sg:tags":[
        "piece"
    ],
    "wof:name":"Universal Apparel Solutions",
    "wof:placetype":"venue"
},
  "geometry": {"coordinates":[-117.898411,33.992553],"type":"Point"}
}