{
  "type": "Feature",
  "properties": {
    "iso:country":"US",
    "sg:address":"2059 Pinercrest Dr",
    "sg:city":"Santa Rosa",
    "sg:classifiers":[
        {
            "category":"Professional",
            "type":"Services"
        }
    ],
    "sg:phone":"+1 707 526 4795",
    "sg:postcode":"95403",
    "sg:province":"CA",
    "wof:name":"El Nino Homecare For Elder",
    "wof:placetype":"venue"
},
  "geometry": {"coordinates":[-122.757732,38.469609],"type":"Point"}
}