{
  "type": "Feature",
  "properties": {
    "iso:country":"US",
    "sg:address":"2072 Pike Ave",
    "sg:city":"San Leandro",
    "sg:classifiers":[
        {
            "category":"Manufacturing",
            "subcategory":"Tobacco Products",
            "type":"Manufacturing & Wholesale Goods"
        }
    ],
    "sg:phone":"+1 925 485 7827",
    "sg:postcode":"94577",
    "sg:province":"CA",
    "wof:name":"Lorillard Tobacco Co",
    "wof:placetype":"venue"
},
  "geometry": {"coordinates":[-122.165311,37.696671],"type":"Point"}
}