{
  "type": "Feature",
  "properties": {
    "iso:country":"US",
    "sg:address":"1334 S Main St",
    "sg:city":"Los Angeles",
    "sg:classifiers":[
        {
            "category":"Professional",
            "type":"Services"
        }
    ],
    "sg:phone":"+1 213 745 7100",
    "sg:postcode":"90015",
    "sg:province":"CA",
    "sg:tags":[
        "establishment"
    ],
    "wof:name":"Kriss Kross",
    "wof:placetype":"venue"
},
  "geometry": {"coordinates":[-118.260515,34.036107],"type":"Point"}
}