{
  "type": "Feature",
  "properties": {
    "addr:full":"4975 S Bradley Rd Santa Maria CA 93455",
    "addr:housenumber":"4975",
    "addr:postcode":"93455",
    "addr:street":"S Bradley Rd",
    "iso:country":"US",
    "sg:address":"4975 S Bradley Rd",
    "sg:city":"Santa Maria",
    "sg:classifiers":[
        {
            "category":"Food & Beverages",
            "subcategory":"Groceries & Convenience Stores",
            "type":"Retail Goods"
        }
    ],
    "sg:phone":"+1 805 937 3355",
    "sg:postcode":"93455",
    "sg:province":"CA",
    "wof:name":"7-Eleven",
    "wof:placetype":"venue"
},
  "geometry": {"coordinates":[-120.418896,34.868264],"type":"Point"}
}