{
  "type": "Feature",
  "properties": {
    "iso:country":"US",
    "sg:address":"6048 Pacific Boulevard",
    "sg:city":"Huntington Park",
    "sg:classifiers":[
        {
            "category":"Restaurant",
            "type":"Food & Drink"
        }
    ],
    "sg:phone":"+1 323 585 2500",
    "sg:postcode":"90255",
    "sg:province":"CA",
    "sg:website":"www.pizzahut.com",
    "wof:name":"Pizza Hut",
    "wof:placetype":"venue"
},
  "geometry": {"coordinates":[-118.225326,33.985666],"type":"Point"}
}