{
  "type": "Feature",
  "properties": {
    "iso:country":"US",
    "sg:address":"7100 Dunfield Ave",
    "sg:city":"Los Angeles",
    "sg:classifiers":[
        {
            "category":"Manufacturing",
            "subcategory":"Metals",
            "type":"Manufacturing & Wholesale Goods"
        }
    ],
    "sg:phone":"+1 310 649 1288",
    "sg:postcode":"90045",
    "sg:province":"CA",
    "sg:tags":[
        "product",
        "fabricated",
        "merchandise",
        "mfg"
    ],
    "wof:name":"Trophy Sales West",
    "wof:placetype":"venue"
},
  "geometry": {"coordinates":[-118.397485,33.976779],"type":"Point"}
}