{
  "type": "Feature",
  "properties": {
    "addr:full":"315 N San Mateo Dr San Mateo CA 94401",
    "addr:housenumber":"315",
    "addr:postcode":"94401",
    "addr:street":"N San Mateo Dr",
    "iso:country":"US",
    "sg:address":"315 N San Mateo Dr",
    "sg:city":"San Mateo",
    "sg:classifiers":[
        {
            "category":"Personal",
            "subcategory":"Massage",
            "type":"Services"
        },
        {
            "category":"Personal",
            "subcategory":"Hair Removal",
            "type":"Services"
        },
        {
            "category":"Personal",
            "subcategory":"Skin Care",
            "type":"Services"
        },
        {
            "category":"Personal",
            "subcategory":"Day Spa",
            "type":"Services"
        }
    ],
    "sg:phone":"+1 650 348 7546",
    "sg:postcode":"94401",
    "sg:province":"CA",
    "sg:website":"www.the-estheticians.com",
    "wof:name":"Estheticians Skin Care Center",
    "wof:placetype":"venue"
},
  "geometry": {"coordinates":[-122.331722,37.571005],"type":"Point"}
}