{
  "type": "Feature",
  "properties": {
    "addr:full":"50 Post St San Francisco CA 94104",
    "addr:housenumber":"50",
    "addr:postcode":"94104",
    "addr:street":"Post St",
    "iso:country":"US",
    "sg:address":"50 Post St",
    "sg:city":"San Francisco",
    "sg:classifiers":[
        {
            "category":"Retail",
            "subcategory":"Laundry & Dry Cleaning",
            "type":"Services"
        }
    ],
    "sg:phone":"+1 415 986 0359",
    "sg:postcode":"94104",
    "sg:province":"CA",
    "sg:tags":[
        "cleaners"
    ],
    "wof:name":"Executive Cleaners",
    "wof:placetype":"venue"
},
  "geometry": {"coordinates":[-122.403533,37.78899],"type":"Point"}
}