{
  "type": "Feature",
  "properties": {
    "iso:country":"US",
    "sg:address":"929 Clay St",
    "sg:city":"San Francisco",
    "sg:classifiers":[
        {
            "category":"Health Services",
            "subcategory":"Doctor",
            "type":"Services"
        }
    ],
    "sg:phone":"+1 415 392 9690",
    "sg:postcode":"94108",
    "sg:province":"CA",
    "wof:name":"Jin Wenwu MD",
    "wof:placetype":"venue"
},
  "geometry": {"coordinates":[-122.40837500000001,37.793868],"type":"Point"}
}