{
  "type": "Feature",
  "properties": {
    "addr:full":"156 S Spruce Ave Ste 201 South San Francisco CA 94080",
    "addr:housenumber":"156",
    "addr:postcode":"94080",
    "addr:street":"S Spruce Ave Ste 201",
    "iso:country":"US",
    "sg:address":"156 S Spruce Ave Ste 201",
    "sg:city":"South San Francisco",
    "sg:classifiers":[
        {
            "category":"Education",
            "subcategory":"Kindergarten",
            "type":"Public Place"
        }
    ],
    "sg:phone":"+1 650 952 7101",
    "sg:postcode":"94080",
    "sg:province":"CA",
    "sg:tags":[
        "school",
        "driving"
    ],
    "wof:name":"Melody Driving School",
    "wof:placetype":"venue"
},
  "geometry": {"coordinates":[-122.41843299999999,37.649579],"type":"Point"}
}