{
  "type": "Feature",
  "properties": {
    "iso:country":"US",
    "sg:address":"107 S Coast Hwy",
    "sg:city":"Oceanside",
    "sg:classifiers":[
        {
            "category":"Food & Beverages",
            "subcategory":"Groceries & Convenience Stores",
            "type":"Retail Goods"
        }
    ],
    "sg:phone":"+1 760 757 9411",
    "sg:postcode":"92054",
    "sg:province":"CA",
    "wof:name":"Yard Carribean Market",
    "wof:placetype":"venue"
},
  "geometry": {"coordinates":[-117.37799800000001,33.1945],"type":"Point"}
}