{
  "type": "Feature",
  "properties": {
    "addr:full":"1439 N Bristol St Santa Ana CA 92706",
    "addr:housenumber":"1439",
    "addr:postcode":"92706",
    "addr:street":"N Bristol St",
    "iso:country":"US",
    "sg:address":"1439 N Bristol St",
    "sg:city":"Santa Ana",
    "sg:classifiers":[
        {
            "category":"Restaurant",
            "type":"Food & Drink"
        }
    ],
    "sg:phone":"+1 714 558 1154",
    "sg:postcode":"92706",
    "sg:province":"CA",
    "wof:name":"McDonald's Restaurants",
    "wof:placetype":"venue"
},
  "geometry": {"coordinates":[-117.885002,33.757599],"type":"Point"}
}