{
  "type": "Feature",
  "properties": {
    "addr:full":"11830 Saticoy St North Hollywood CA 91605",
    "addr:housenumber":"11830",
    "addr:postcode":"91605",
    "addr:street":"Saticoy St",
    "iso:country":"US",
    "sg:address":"11830 Saticoy St",
    "sg:city":"North Hollywood",
    "sg:classifiers":[
        {
            "category":"Organizations",
            "subcategory":"Religious Organization",
            "type":"Services"
        }
    ],
    "sg:phone":"+1 818 764 5321",
    "sg:postcode":"91605",
    "sg:province":"CA",
    "sg:tags":[
        "church"
    ],
    "wof:name":"Church Of Jesus Christ Of Lds",
    "wof:placetype":"venue"
},
  "geometry": {"coordinates":[-118.391873,34.20839],"type":"Point"}
}