{
  "type": "Feature",
  "properties": {
    "addr:full":"5650 Imhoff Dr Concord CA 94520",
    "addr:housenumber":"5650",
    "addr:postcode":"94520",
    "addr:street":"Imhoff Dr",
    "iso:country":"US",
    "sg:address":"5650 Imhoff Dr",
    "sg:city":"Concord",
    "sg:classifiers":[
        {
            "category":"Shopping",
            "subcategory":"Hobbies, Toys, & Games",
            "type":"Retail Goods"
        }
    ],
    "sg:phone":"+1 925 685 6566",
    "sg:postcode":"94520",
    "sg:province":"CA",
    "sg:tags":[
        "model",
        "supply"
    ],
    "wof:name":"Just Trains",
    "wof:placetype":"venue"
},
  "geometry": {"coordinates":[-122.05737000000001,38.001761],"type":"Point"}
}