{
  "type": "Feature",
  "properties": {
    "iso:country":"US",
    "sg:address":"1801 W Romneya Dr",
    "sg:city":"Anaheim",
    "sg:classifiers":[
        {
            "category":"Health Services",
            "subcategory":"Doctor",
            "type":"Services"
        }
    ],
    "sg:phone":"+1 714 776 5920",
    "sg:postcode":"92801",
    "sg:province":"CA",
    "sg:tags":[
        "physician",
        "surgeon"
    ],
    "wof:name":"Anaheim Cardiology Medical Grp",
    "wof:placetype":"venue"
},
  "geometry": {"coordinates":[-117.944796,33.850789],"type":"Point"}
}