{
  "type": "Feature",
  "properties": {
    "iso:country":"US",
    "sg:address":"Ghirardelli Square",
    "sg:city":"San Francisco",
    "sg:classifiers":[
        {
            "category":"Professional",
            "type":"Services"
        }
    ],
    "sg:phone":"+1 415 771 4894",
    "sg:postcode":"94109",
    "sg:province":"CA",
    "sg:tags":[
        "caterer"
    ],
    "sg:website":"www.laurelscatering.com",
    "wof:name":"Laurel's Catering",
    "wof:placetype":"venue"
},
  "geometry": {"coordinates":[-122.42346499999999,37.805452],"type":"Point"}
}