{
  "type": "Feature",
  "properties": {
    "addr:full":"69975 Frank Sinatra Dr Rancho Mirage CA 92270",
    "addr:housenumber":"69975",
    "addr:postcode":"92270",
    "addr:street":"Frank Sinatra Dr",
    "iso:country":"US",
    "sg:address":"69975 Frank Sinatra Dr",
    "sg:city":"Rancho Mirage",
    "sg:classifiers":[
        {
            "category":"Real Estate",
            "subcategory":"Developer",
            "type":"Services"
        }
    ],
    "sg:phone":"+1 760 328 7664",
    "sg:postcode":"92270",
    "sg:province":"CA",
    "sg:tags":[
        "mobile",
        "home"
    ],
    "wof:name":"Rancho Mirage Mobile Home Park",
    "wof:placetype":"venue"
},
  "geometry": {"coordinates":[-116.447191,33.77234],"type":"Point"}
}