{
  "type": "Feature",
  "properties": {
    "iso:country":"US",
    "sg:address":"24043 Hawthorne Blvd",
    "sg:city":"Torrance",
    "sg:classifiers":[
        {
            "category":"Retail",
            "subcategory":"Auto Repair",
            "type":"Services"
        }
    ],
    "sg:phone":"+1 310 791 8480",
    "sg:postcode":"90505",
    "sg:province":"CA",
    "wof:name":"E-Z Lube Inc",
    "wof:placetype":"venue"
},
  "geometry": {"coordinates":[-118.350998,33.806301],"type":"Point"}
}