{
  "type": "Feature",
  "properties": {
    "addr:full":"155 Bovet Rd. Suite 207 San Mateo CA 94402",
    "addr:housenumber":"155",
    "addr:postcode":"94402",
    "addr:street":"Bovet Rd. Suite 207",
    "iso:country":"US",
    "sg:address":"155 Bovet Rd. Suite 207",
    "sg:city":"San Mateo",
    "sg:classifiers":[
        {
            "category":"Professional",
            "subcategory":"Computer Services",
            "type":"Services"
        }
    ],
    "sg:phone":"+1 650 288 3500",
    "sg:postcode":"94402",
    "sg:province":"CA",
    "sg:tags":[
        "textbooks",
        "books",
        "online-media",
        "renting-online",
        "netflix-model",
        "college-textbooks",
        "ebooks",
        "online-textbooks",
        "online-books",
        "tikiman"
    ],
    "sg:website":"http://www.bookrenter.com",
    "wof:name":"BookRenter.com",
    "wof:placetype":"venue"
},
  "geometry": {"coordinates":[-122.31446800000001,37.551366],"type":"Point"}
}