{
  "type": "Feature",
  "properties": {
    "addr:full":"4035 Beyer Blvd San Ysidro CA 92173",
    "addr:housenumber":"4035",
    "addr:postcode":"92173",
    "addr:street":"Beyer Blvd",
    "iso:country":"US",
    "sg:address":"4035 Beyer Blvd",
    "sg:city":"San Ysidro",
    "sg:classifiers":[
        {
            "category":"Local Transit",
            "type":"Transportation"
        }
    ],
    "sg:phone":"+1 619 233 3004",
    "sg:postcode":"92173",
    "sg:province":"CA",
    "sg:tags":[
        "public"
    ],
    "sg:website":"www.sdcommute.com",
    "wof:name":"Beyer Boulevard Blue Line Station",
    "wof:placetype":"venue"
},
  "geometry": {"coordinates":[-117.04721000000001,32.558252],"type":"Point"}
}