{
  "type": "Feature",
  "properties": {
    "iso:country":"US",
    "sg:address":"369 W Portal Ave",
    "sg:city":"San Francisco",
    "sg:classifiers":[
        {
            "category":"Home & Garden",
            "subcategory":"Carpets & Floor Coverings",
            "type":"Retail Goods"
        }
    ],
    "sg:phone":"+1 415 751 2827",
    "sg:postcode":"94127",
    "sg:province":"CA",
    "sg:tags":[
        "blind",
        "material",
        "shade"
    ],
    "sg:website":"www.armstrongcarpet.com",
    "wof:name":"Armstrong Carpet & Linoleum",
    "wof:placetype":"venue"
},
  "geometry": {"coordinates":[-122.470082,37.737018],"type":"Point"}
}