{
  "type": "Feature",
  "properties": {
    "iso:country":"US",
    "sg:address":"4950 Pacific Ave",
    "sg:city":"Stockton",
    "sg:classifiers":[
        {
            "category":"Personal",
            "subcategory":"Beauty Salon",
            "type":"Services"
        }
    ],
    "sg:phone":"+1 209 473 8240",
    "sg:postcode":"95207",
    "sg:province":"CA",
    "wof:name":"Lieu Skin Care",
    "wof:placetype":"venue"
},
  "geometry": {"coordinates":[-121.314533,37.996026],"type":"Point"}
}