{
  "type": "Feature",
  "properties": {
    "iso:country":"US",
    "sg:address":"433 Estudillo Ave",
    "sg:city":"San Leandro",
    "sg:classifiers":[
        {
            "category":"Health Services",
            "subcategory":"Health Practitioner",
            "type":"Services"
        }
    ],
    "sg:phone":"+1 510 351 9198",
    "sg:postcode":"94577",
    "sg:province":"CA",
    "sg:tags":[
        "therapist",
        "physical"
    ],
    "wof:name":"Unicare Physical Therapy",
    "wof:placetype":"venue"
},
  "geometry": {"coordinates":[-122.151342,37.726111],"type":"Point"}
}