{
  "type": "Feature",
  "properties": {
    "iso:country":"US",
    "sg:address":"509 Swift St",
    "sg:city":"Santa Cruz",
    "sg:classifiers":[
        {
            "category":"Sports & Exercise",
            "subcategory":"Gym",
            "type":"Entertainment"
        }
    ],
    "sg:phone":"+1 831 420 0657",
    "sg:postcode":"95060",
    "sg:province":"CA",
    "sg:tags":[
        "trainer"
    ],
    "wof:name":"West Side Studio",
    "wof:placetype":"venue"
},
  "geometry": {"coordinates":[-122.033997,36.992599],"type":"Point"}
}