{
  "type": "Feature",
  "properties": {
    "addr:full":"6000 Shelter Bay Ave Mill Valley CA 94941",
    "addr:housenumber":"6000",
    "addr:postcode":"94941",
    "addr:street":"Shelter Bay Ave",
    "iso:country":"US",
    "sg:address":"6000 Shelter Bay Ave",
    "sg:city":"Mill Valley",
    "sg:classifiers":[
        {
            "category":"Wholesale",
            "subcategory":"Electrical",
            "type":"Manufacturing & Wholesale Goods"
        }
    ],
    "sg:phone":"+1 415 389 9701",
    "sg:postcode":"94941",
    "sg:province":"CA",
    "sg:tags":[
        "alarm",
        "burglar",
        "system"
    ],
    "wof:name":"Protection Service Industries",
    "wof:placetype":"venue"
},
  "geometry": {"coordinates":[-122.518828,37.893491],"type":"Point"}
}