{
  "type": "Feature",
  "properties": {
    "iso:country":"US",
    "sg:address":"455 Moraga Rd",
    "sg:city":"Moraga",
    "sg:classifiers":[
        {
            "category":"Building & Trades",
            "subcategory":"Construction",
            "type":"Services"
        },
        {
            "category":"Home & Garden",
            "subcategory":"Furniture",
            "type":"Retail Goods"
        }
    ],
    "sg:phone":"+1 925 377 5100",
    "sg:postcode":"94556",
    "sg:province":"CA",
    "sg:tags":[
        "carpentry",
        "c",
        "material",
        "maker",
        "cabinet"
    ],
    "wof:name":"Cal Cabinets",
    "wof:placetype":"venue"
},
  "geometry": {"coordinates":[-122.124415,37.856771],"type":"Point"}
}