{
  "type": "Feature",
  "properties": {
    "addr:full":"315 N San Mateo Drive San Mateo CA 94401",
    "addr:housenumber":"315",
    "addr:postcode":"94401",
    "addr:street":"N San Mateo Drive",
    "iso:country":"US",
    "sg:address":"315 N San Mateo Drive",
    "sg:city":"San Mateo",
    "sg:classifiers":[
        {
            "category":"Health Services",
            "subcategory":"Dentist",
            "type":"Services"
        }
    ],
    "sg:phone":"+1 650 343 1083",
    "sg:postcode":"94401",
    "sg:province":"CA",
    "wof:name":"Schram Richard E DDS",
    "wof:placetype":"venue"
},
  "geometry": {"coordinates":[-122.332002,37.571608],"type":"Point"}
}