{
  "type": "Feature",
  "properties": {
    "iso:country":"US",
    "sg:address":"2404 Loring St",
    "sg:city":"San Diego",
    "sg:classifiers":[
        {
            "category":"Health Services",
            "subcategory":"Nursing And Care Facility",
            "type":"Services"
        }
    ],
    "sg:phone":"+1 858 274 4110",
    "sg:postcode":"92109",
    "sg:province":"CA",
    "wof:name":"Wesley Palms",
    "wof:placetype":"venue"
},
  "geometry": {"coordinates":[-117.226905,32.811858],"type":"Point"}
}