{
  "type": "Feature",
  "properties": {
    "addr:full":"702 Mangrove Ave 112 Chico CA 95926",
    "addr:housenumber":"702;112",
    "addr:postcode":"95926",
    "addr:street":"Mangrove Ave",
    "iso:country":"US",
    "sg:address":"702 Mangrove Ave 112",
    "sg:city":"Chico",
    "sg:classifiers":[
        {
            "category":"Real Estate",
            "subcategory":"Real Estate Services",
            "type":"Services"
        },
        {
            "category":"Real Estate",
            "subcategory":"Real Estate Agent",
            "type":"Services"
        }
    ],
    "sg:phone":"+1 530 899 9073",
    "sg:postcode":"95926",
    "sg:province":"CA",
    "sg:tags":[
        "management"
    ],
    "wof:name":"Aloha Real Estate Services",
    "wof:placetype":"venue"
},
  "geometry": {"coordinates":[-121.83571600000001,39.735179],"type":"Point"}
}