{
  "type": "Feature",
  "properties": {
    "iso:country":"US",
    "sg:address":"5660 Boulder Canyon Dr",
    "sg:city":"Castro Valley",
    "sg:classifiers":[
        {
            "category":"Building & Trades",
            "subcategory":"Landscaping Services",
            "type":"Services"
        }
    ],
    "sg:phone":"+1 510 537 3198",
    "sg:postcode":"94552",
    "sg:province":"CA",
    "sg:tags":[
        "landscape",
        "contractor"
    ],
    "wof:name":"Greenfield Landscape",
    "wof:placetype":"venue"
},
  "geometry": {"coordinates":[-122.034087,37.691637],"type":"Point"}
}