{
  "type": "Feature",
  "properties": {
    "addr:full":"16909 Devonshire St Granada Hills CA 91344",
    "addr:housenumber":"16909",
    "addr:postcode":"91344",
    "addr:street":"Devonshire St",
    "iso:country":"US",
    "sg:address":"16909 Devonshire St",
    "sg:city":"Granada Hills",
    "sg:classifiers":[
        {
            "category":"Education",
            "subcategory":"Dance Studio",
            "type":"Public Place"
        }
    ],
    "sg:phone":"+1 818 368 8789",
    "sg:postcode":"91344",
    "sg:province":"CA",
    "sg:tags":[
        "instruction",
        "dancing"
    ],
    "wof:name":"Tony Tee Dance Projects",
    "wof:placetype":"venue"
},
  "geometry": {"coordinates":[-118.498458,34.257569],"type":"Point"}
}