{
  "type": "Feature",
  "properties": {
    "addr:full":"520 Grass Valley Hwy Auburn CA 95603",
    "addr:housenumber":"520",
    "addr:postcode":"ca 95603",
    "addr:street":"Grass Valley Hwy",
    "iso:country":"US",
    "sg:address":"520 Grass Valley Hwy",
    "sg:city":"Auburn",
    "sg:classifiers":[
        {
            "category":"Retail",
            "subcategory":"Auto Rental",
            "type":"Services"
        }
    ],
    "sg:phone":"+1 530 823 8520",
    "sg:postcode":"95603",
    "sg:province":"CA",
    "sg:tags":[
        "renting",
        "automobile"
    ],
    "wof:name":"Avis Rent A Car",
    "wof:placetype":"venue"
},
  "geometry": {"coordinates":[-121.07713,38.909773],"type":"Point"}
}