{
  "type": "Feature",
  "properties": {
    "iso:country":"US",
    "sg:address":"27000 Crown Valley Pkwy",
    "sg:city":"Mission Viejo",
    "sg:classifiers":[
        {
            "category":"Building & Trades",
            "subcategory":"Cleaning & Sanitation",
            "type":"Services"
        }
    ],
    "sg:phone":"+1 949 347 6806",
    "sg:postcode":"92677",
    "sg:province":"CA",
    "sg:tags":[
        "maintenance"
    ],
    "wof:name":"Southeast Service",
    "wof:placetype":"venue"
},
  "geometry": {"coordinates":[-117.66961999999999,33.561759],"type":"Point"}
}