{
  "type": "Feature",
  "properties": {
    "addr:full":"4844 Telegraph Ave Oakland CA 94609",
    "addr:housenumber":"4844",
    "addr:postcode":"94609",
    "addr:street":"Telegraph Ave",
    "iso:country":"US",
    "sg:address":"4844 Telegraph Ave",
    "sg:city":"Oakland",
    "sg:classifiers":[
        {
            "category":"Sports & Exercise",
            "subcategory":"Gym",
            "type":"Entertainment"
        }
    ],
    "sg:phone":"+1 510 333 2299",
    "sg:postcode":"94609",
    "sg:province":"CA",
    "sg:tags":[
        "pilate"
    ],
    "wof:name":"Pilates With Lindsey",
    "wof:placetype":"venue"
},
  "geometry": {"coordinates":[-122.262305,37.835271],"type":"Point"}
}