{
  "type": "Feature",
  "properties": {
    "iso:country":"US",
    "sg:address":"2018 W Glenwood Ave",
    "sg:city":"Turlock",
    "sg:classifiers":[
        {
            "category":"Freight",
            "type":"Transportation"
        }
    ],
    "sg:phone":"+1 209 669 7710",
    "sg:postcode":"95380",
    "sg:province":"CA",
    "sg:tags":[
        "operator",
        "local",
        "trucking"
    ],
    "wof:name":"Soltero Trucking",
    "wof:placetype":"venue"
},
  "geometry": {"coordinates":[-120.870711,37.474417],"type":"Point"}
}