{
  "type": "Feature",
  "properties": {
    "iso:country":"US",
    "sg:address":"22630 Main St.",
    "sg:city":"Hayward",
    "sg:classifiers":[
        {
            "category":"Health Services",
            "subcategory":"Chiropractor",
            "type":"Services"
        }
    ],
    "sg:phone":"+1 510 856 0036",
    "sg:postcode":"94543",
    "sg:province":"CA",
    "wof:name":"Body Mind Connection",
    "wof:placetype":"venue"
},
  "geometry": {"coordinates":[-122.08200100000001,37.672501],"type":"Point"}
}