{
  "type": "Feature",
  "properties": {
    "iso:country":"US",
    "sg:address":"23101 Sherman Pl Ste 405",
    "sg:city":"West Hills",
    "sg:classifiers":[
        {
            "category":"Health Services",
            "subcategory":"Doctor",
            "type":"Services"
        }
    ],
    "sg:phone":"+1 818 347 3287",
    "sg:postcode":"91307",
    "sg:province":"CA",
    "wof:name":"Jeon Edward H MD",
    "wof:placetype":"venue"
},
  "geometry": {"coordinates":[-118.628998,34.2005],"type":"Point"}
}