{
  "type": "Feature",
  "properties": {
    "addr:full":"7923 S Central Ave Los Angeles CA 90001",
    "addr:housenumber":"7923",
    "addr:postcode":"90001",
    "addr:street":"S Central Ave",
    "iso:country":"US",
    "sg:address":"7923 S Central Ave",
    "sg:city":"Los Angeles",
    "sg:classifiers":[
        {
            "category":"Home & Garden",
            "subcategory":"Household Appliances",
            "type":"Retail Goods"
        }
    ],
    "sg:phone":"+1 323 588 4118",
    "sg:postcode":"90001",
    "sg:province":"CA",
    "wof:name":"Pacific Appliances",
    "wof:placetype":"venue"
},
  "geometry": {"coordinates":[-118.25672400000001,33.966771],"type":"Point"}
}