{
  "type": "Feature",
  "properties": {
    "addr:full":"10398 Rockingham Dr Sacramento CA 95827",
    "addr:housenumber":"10398",
    "addr:postcode":"95827",
    "addr:street":"Rockingham Dr",
    "iso:country":"US",
    "sg:address":"10398 Rockingham Dr",
    "sg:city":"Sacramento",
    "sg:classifiers":[
        {
            "category":"Real Estate",
            "subcategory":"Real Estate Agent",
            "type":"Services"
        }
    ],
    "sg:phone":"+1 916 364 5509",
    "sg:postcode":"95827",
    "sg:province":"CA",
    "sg:tags":[
        "management"
    ],
    "wof:name":"Mather Business Ctr",
    "wof:placetype":"venue"
},
  "geometry": {"coordinates":[-121.30646299999999,38.574011],"type":"Point"}
}