{
  "type": "Feature",
  "properties": {
    "addr:full":"3205 Midway Dr Ste A & D San Diego CA 92110",
    "addr:housenumber":"3205",
    "addr:postcode":"92110",
    "addr:street":"Midway Dr Ste A",
    "iso:country":"US",
    "sg:address":"3205 Midway Dr Ste A & D",
    "sg:city":"San Diego",
    "sg:classifiers":[
        {
            "category":"Professional",
            "subcategory":"Computer Services",
            "type":"Services"
        }
    ],
    "sg:phone":"+1 619 224 2919",
    "sg:postcode":"92110",
    "sg:province":"CA",
    "sg:tags":[
        "repair"
    ],
    "sg:website":"www.selectronic.net",
    "wof:name":"Selectronic",
    "wof:placetype":"venue"
},
  "geometry": {"coordinates":[-117.20983099999999,32.750142],"type":"Point"}
}