{
  "type": "Feature",
  "properties": {
    "addr:full":"316 E Acequia Ave Visalia CA 93291",
    "addr:housenumber":"316",
    "addr:postcode":"93291",
    "addr:street":"E Acequia Ave",
    "iso:country":"US",
    "sg:address":"316 E Acequia Ave",
    "sg:city":"Visalia",
    "sg:classifiers":[
        {
            "category":"Health Services",
            "subcategory":"Doctor",
            "type":"Services"
        }
    ],
    "sg:phone":"+1 559 627 9107",
    "sg:postcode":"93291",
    "sg:province":"CA",
    "sg:tags":[
        "physician",
        "surgeon"
    ],
    "wof:name":"Allergy Institute",
    "wof:placetype":"venue"
},
  "geometry": {"coordinates":[-119.289097,36.329336],"type":"Point"}
}