{
  "type": "Feature",
  "properties": {
    "addr:full":"8913 S San Pedro St Los Angeles CA 90003",
    "addr:housenumber":"8913",
    "addr:postcode":"90003",
    "addr:street":"S San Pedro St",
    "iso:country":"US",
    "sg:address":"8913 S San Pedro St",
    "sg:city":"Los Angeles",
    "sg:classifiers":[
        {
            "category":"Retail",
            "subcategory":"Auto Repair",
            "type":"Services"
        }
    ],
    "sg:phone":"+1 323 751 8492",
    "sg:postcode":"90003",
    "sg:province":"CA",
    "sg:tags":[
        "automobile",
        "inspection"
    ],
    "wof:name":"Community Smog",
    "wof:placetype":"venue"
},
  "geometry": {"coordinates":[-118.269589,33.954791],"type":"Point"}
}