{
  "type": "Feature",
  "properties": {
    "iso:country":"US",
    "sg:address":"25150 Hancock Ave",
    "sg:city":"Murrieta",
    "sg:classifiers":[
        {
            "category":"Health Services",
            "subcategory":"Doctor",
            "type":"Services"
        }
    ],
    "sg:phone":"+1 951 698 4660",
    "sg:postcode":"92562",
    "sg:province":"CA",
    "sg:tags":[
        "physician",
        "surgeon"
    ],
    "wof:name":"Fallbrook Temecula Vly Ortho",
    "wof:placetype":"venue"
},
  "geometry": {"coordinates":[-117.182401,33.568273],"type":"Point"}
}