{
  "type": "Feature",
  "properties": {
    "iso:country":"US",
    "sg:address":"16960 Foothill Blvd",
    "sg:city":"Fontana",
    "sg:classifiers":[
        {
            "category":"Personal",
            "subcategory":"Beauty Salon",
            "type":"Services"
        }
    ],
    "sg:phone":"+1 909 350 2732",
    "sg:postcode":"92335",
    "sg:province":"CA",
    "sg:tags":[
        "manicuring"
    ],
    "wof:name":"Cal Nails",
    "wof:placetype":"venue"
},
  "geometry": {"coordinates":[-117.435612,34.106695],"type":"Point"}
}