{
  "type": "Feature",
  "properties": {
    "iso:country":"US",
    "sg:address":"153 S Cypress St",
    "sg:city":"Orange",
    "sg:classifiers":[
        {
            "category":"Real Estate",
            "subcategory":"Architect",
            "type":"Services"
        }
    ],
    "sg:phone":"+1 714 532 6878",
    "sg:postcode":"92866",
    "sg:province":"CA",
    "wof:name":"Sinrazon Inc",
    "wof:placetype":"venue"
},
  "geometry": {"coordinates":[-117.85619,33.786913],"type":"Point"}
}