{
  "type": "Feature",
  "properties": {
    "addr:full":"1555 S Western Avenue Los Angeles CA 90006",
    "addr:housenumber":"1555",
    "addr:postcode":"90006",
    "addr:street":"S Western Avenue",
    "iso:country":"US",
    "sg:address":"1555 S Western Avenue",
    "sg:city":"Los Angeles",
    "sg:classifiers":[
        {
            "category":"Restaurant",
            "type":"Food & Drink"
        }
    ],
    "sg:phone":"+1 323 733 4000",
    "sg:postcode":"90006",
    "sg:province":"CA",
    "sg:tags":[
        "pizza"
    ],
    "wof:name":"Pizza Hut",
    "wof:placetype":"venue"
},
  "geometry": {"coordinates":[-118.308892,34.04388],"type":"Point"}
}