{
  "type": "Feature",
  "properties": {
    "addr:full":"8918 W Pico Blvd Los Angeles CA 90035",
    "addr:housenumber":"8918",
    "addr:postcode":"90035",
    "addr:street":"W Pico Blvd",
    "iso:country":"US",
    "sg:address":"8918 W Pico Blvd",
    "sg:city":"Los Angeles",
    "sg:classifiers":[
        {
            "category":"Wholesale",
            "subcategory":"Groceries",
            "type":"Manufacturing & Wholesale Goods"
        }
    ],
    "sg:phone":"+1 310 990 4573",
    "sg:postcode":"90035",
    "sg:province":"CA",
    "wof:name":"Harmony Works",
    "wof:placetype":"venue"
},
  "geometry": {"coordinates":[-118.385716,34.05515],"type":"Point"}
}