{
  "type": "Feature",
  "properties": {
    "iso:country":"US",
    "sg:address":"836 Washington St",
    "sg:city":"San Francisco",
    "sg:classifiers":[
        {
            "category":"Food & Beverages",
            "subcategory":"Specialty",
            "type":"Retail Goods"
        }
    ],
    "sg:phone":"+1 415 392 1188",
    "sg:postcode":"94108",
    "sg:province":"CA",
    "sg:tags":[
        "health",
        "diet"
    ],
    "wof:name":"Ben Li Intl Trading Co",
    "wof:placetype":"venue"
},
  "geometry": {"coordinates":[-122.407165,37.795136],"type":"Point"}
}