{
  "type": "Feature",
  "properties": {
    "iso:country":"US",
    "sg:address":"San Antonio Road",
    "sg:city":"Vandenberg AFB",
    "sg:classifiers":[
        {
            "category":"Sports & Exercise",
            "subcategory":"Golf",
            "type":"Entertainment"
        }
    ],
    "sg:phone":"+1 805 734 1333",
    "sg:postcode":"93437",
    "sg:province":"CA",
    "sg:website":"www.30svs.com/svbg.html",
    "wof:name":"Marshallia Ranch Golf Course",
    "wof:placetype":"venue"
},
  "geometry": {"coordinates":[-120.518806,34.778862],"type":"Point"}
}