{
  "type": "Feature",
  "properties": {
    "addr:full":"12801 Philadelphia St Whittier CA 90601",
    "addr:housenumber":"12801",
    "addr:postcode":"90601",
    "addr:street":"Philadelphia St",
    "iso:country":"US",
    "sg:address":"12801 Philadelphia St",
    "sg:city":"Whittier",
    "sg:classifiers":[
        {
            "category":"Manufacturing",
            "subcategory":"Printing",
            "type":"Manufacturing & Wholesale Goods"
        }
    ],
    "sg:phone":"+1 562 698 0128",
    "sg:postcode":"90601",
    "sg:province":"CA",
    "sg:tags":[
        "printer"
    ],
    "wof:name":"Beacon Press Inc",
    "wof:placetype":"venue"
},
  "geometry": {"coordinates":[-118.039114,33.979106],"type":"Point"}
}