{
  "type": "Feature",
  "properties": {
    "addr:full":"7277 Myrtle Pl Fontana CA 92336",
    "addr:housenumber":"7277",
    "addr:postcode":"92336",
    "addr:street":"Myrtle Pl",
    "iso:country":"US",
    "sg:address":"7277 Myrtle Pl",
    "sg:city":"Fontana",
    "sg:classifiers":[
        {
            "category":"Professional",
            "subcategory":"Business Services",
            "type":"Services"
        }
    ],
    "sg:phone":"+1 909 969 5081",
    "sg:postcode":"92336",
    "sg:province":"CA",
    "sg:tags":[
        "management"
    ],
    "wof:name":"Cq Enterprises Inc",
    "wof:placetype":"venue"
},
  "geometry": {"coordinates":[-117.46874200000001,34.122067],"type":"Point"}
}