{
  "type": "Feature",
  "properties": {
    "addr:full":"3192 Heritage Estates Ct San Jose CA 95148",
    "addr:housenumber":"3192",
    "addr:postcode":"95148",
    "addr:street":"Heritage Estates Ct",
    "iso:country":"US",
    "sg:address":"3192 Heritage Estates Ct",
    "sg:city":"San Jose",
    "sg:classifiers":[
        {
            "category":"Building & Trades",
            "subcategory":"Construction",
            "type":"Services"
        }
    ],
    "sg:phone":"+1 408 270 4180",
    "sg:postcode":"95148",
    "sg:province":"CA",
    "sg:tags":[
        "painter"
    ],
    "wof:name":"Creative Wall Designs",
    "wof:placetype":"venue"
},
  "geometry": {"coordinates":[-121.77995199999999,37.318195],"type":"Point"}
}