{
  "type": "Feature",
  "properties": {
    "acgov:api":"544.0",
    "acgov:type":"HS",
    "addr:full":"2607 Myrtle St. Oakland CA",
    "wof:categories":[
        "education_and_religion:education=school"
    ],
    "wof:name":"Expression, Excellence, Community, Empow",
    "wof:placetype":"venue"
},
  "geometry": {"coordinates":[-122.27873635899402,37.81787881902952],"type":"Point"}
}