{
  "type": "Feature",
  "properties": {
    "addr:full":"210 San Jose Ave Ste 22 San Jose CA 95125",
    "addr:housenumber":"210",
    "addr:postcode":"95125",
    "addr:street":"San Jose Ave Ste 22 San Jose",
    "iso:country":"US",
    "sg:address":"210 San Jose Ave Ste 22",
    "sg:city":"San Jose",
    "sg:classifiers":[
        {
            "category":"Retail",
            "subcategory":"Repair Shop",
            "type":"Services"
        }
    ],
    "sg:phone":"+1 408 294 6758",
    "sg:postcode":"95125",
    "sg:province":"CA",
    "sg:tags":[
        "reupholstery",
        "furniture"
    ],
    "wof:name":"Valdez Upholstery",
    "wof:placetype":"venue"
},
  "geometry": {"coordinates":[-121.875,37.309399],"type":"Point"}
}