{
  "type": "Feature",
  "properties": {
    "addr:full":"1065 5th Ave San Diego CA 92101",
    "addr:housenumber":"1065",
    "addr:postcode":"92101",
    "addr:street":"5Th Ave",
    "iso:country":"US",
    "sg:address":"1065 5th Ave",
    "sg:city":"San Diego",
    "sg:classifiers":[
        {
            "category":"Shopping",
            "subcategory":"Jewelry",
            "type":"Retail Goods"
        }
    ],
    "sg:phone":"+1 619 232 2023",
    "sg:postcode":"92101",
    "sg:province":"CA",
    "sg:tags":[
        "watch"
    ],
    "wof:name":"Eric Watch",
    "wof:placetype":"venue"
},
  "geometry": {"coordinates":[-117.160085,32.715967],"type":"Point"}
}