{
  "type": "Feature",
  "properties": {
    "iso:country":"US",
    "sg:address":"12170 4th St",
    "sg:city":"Yucaipa",
    "sg:classifiers":[
        {
            "category":"Restaurant",
            "type":"Food & Drink"
        }
    ],
    "sg:phone":"+1 909 790 6123",
    "sg:postcode":"92399",
    "sg:province":"CA",
    "sg:tags":[
        "italian"
    ],
    "sg:website":"www.twoguyspizza.net",
    "wof:name":"Two Guys Pasta & Pizza",
    "wof:placetype":"venue"
},
  "geometry": {"coordinates":[-117.051874,34.032761],"type":"Point"}
}