{
  "type": "Feature",
  "properties": {
    "iso:country":"US",
    "sg:address":"7071 Warner Ave",
    "sg:city":"Huntington Beach",
    "sg:classifiers":[
        {
            "category":"Professional",
            "subcategory":"Business Services",
            "type":"Services"
        }
    ],
    "sg:phone":"+1 714 962 5441",
    "sg:postcode":"92647",
    "sg:province":"CA",
    "sg:tags":[
        "establishment"
    ],
    "wof:name":"Event Booking & Services",
    "wof:placetype":"venue"
},
  "geometry": {"coordinates":[-118.00157900000001,33.715582],"type":"Point"}
}