{
  "type": "Feature",
  "properties": {
    "addr:full":"2593 S King Rd Ste 4 San Jose CA 95122",
    "addr:housenumber":"2593",
    "addr:postcode":"95122",
    "addr:street":"S King Rd Ste 4",
    "iso:country":"US",
    "sg:address":"2593 S King Rd Ste 4",
    "sg:city":"San Jose",
    "sg:classifiers":[
        {
            "category":"Health Services",
            "subcategory":"Doctor",
            "type":"Services"
        }
    ],
    "sg:phone":"+1 408 532 0960",
    "sg:postcode":"95122",
    "sg:province":"CA",
    "wof:name":"Truong Hien Ngoc MD",
    "wof:placetype":"venue"
},
  "geometry": {"coordinates":[-121.822998,37.318699],"type":"Point"}
}