{
  "type": "Feature",
  "properties": {
    "addr:full":"18981 Sonoma Hwy Sonoma CA 95476",
    "addr:housenumber":"18981",
    "addr:postcode":"95476",
    "addr:street":"Sonoma Hwy",
    "iso:country":"US",
    "sg:address":"18981 Sonoma Hwy",
    "sg:city":"Sonoma",
    "sg:classifiers":[
        {
            "category":"Retail",
            "subcategory":"Auto Rental",
            "type":"Services"
        }
    ],
    "sg:phone":"+1 707 938 0200",
    "sg:postcode":"95476",
    "sg:province":"CA",
    "sg:tags":[
        "renting",
        "automobile"
    ],
    "wof:name":"Enterprise Rent-A-Car",
    "wof:placetype":"venue"
},
  "geometry": {"coordinates":[-122.47638600000001,38.302986],"type":"Point"}
}