{
  "type": "Feature",
  "properties": {
    "addr:full":"938 Adams St Benicia CA 94510",
    "addr:housenumber":"938",
    "addr:postcode":"94510",
    "addr:street":"Adams St",
    "iso:country":"US",
    "sg:address":"938 Adams St",
    "sg:city":"Benicia",
    "sg:phone":"+1 707 747 4776",
    "sg:postcode":"94510",
    "sg:province":"CA",
    "sg:website":"http://www.asfloors.com",
    "wof:name":"A & S Floors",
    "wof:placetype":"venue"
},
  "geometry": {"coordinates":[-122.13800000000001,38.047691],"type":"Point"}
}