{
  "type": "Feature",
  "properties": {
    "addr:full":"9297 Thilow Dr Sacramento CA 95826",
    "addr:housenumber":"9297",
    "addr:postcode":"95826",
    "addr:street":"Thilow Dr",
    "iso:country":"US",
    "sg:address":"9297 Thilow Dr",
    "sg:city":"Sacramento",
    "sg:classifiers":[
        {
            "category":"Building & Trades",
            "subcategory":"Electrical",
            "type":"Services"
        }
    ],
    "sg:phone":"+1 916 849 9949",
    "sg:postcode":"95826",
    "sg:province":"CA",
    "sg:tags":[
        "electrician"
    ],
    "wof:name":"Engstrom Electric",
    "wof:placetype":"venue"
},
  "geometry": {"coordinates":[-121.35432400000001,38.55544],"type":"Point"}
}