{
  "type": "Feature",
  "properties": {
    "iso:country":"US",
    "sg:address":"750 W Gonzales Rd",
    "sg:city":"Oxnard",
    "sg:classifiers":[
        {
            "category":"Professional",
            "subcategory":"Engineering",
            "type":"Services"
        },
        {
            "category":"Professional",
            "subcategory":"Research",
            "type":"Services"
        }
    ],
    "sg:phone":"+1 805 604 0052",
    "sg:postcode":"93036",
    "sg:province":"CA",
    "sg:tags":[
        "environmental",
        "ecological"
    ],
    "wof:name":"Malcolm Pirnie Inc",
    "wof:placetype":"venue"
},
  "geometry": {"coordinates":[-119.186305,34.219141],"type":"Point"}
}