{
  "type": "Feature",
  "properties": {
    "iso:country":"US",
    "sg:address":"7465 Verona Dr",
    "sg:city":"Rancho Murieta",
    "sg:classifiers":[
        {
            "category":"Real Estate",
            "subcategory":"Real Estate Agent",
            "type":"Services"
        }
    ],
    "sg:phone":"+1 916 354 1743",
    "sg:postcode":"95683",
    "sg:province":"CA",
    "wof:name":"Domingo Murrieta Properties",
    "wof:placetype":"venue"
},
  "geometry": {"coordinates":[-121.073547,38.487257],"type":"Point"}
}