{
  "type": "Feature",
  "properties": {
    "iso:country":"US",
    "sg:address":"15051 Leffingwell Rd",
    "sg:city":"Whittier",
    "sg:classifiers":[
        {
            "category":"Manufacturing",
            "subcategory":"Apparel",
            "type":"Manufacturing & Wholesale Goods"
        }
    ],
    "sg:phone":"+1 562 903 9065",
    "sg:postcode":"90604",
    "sg:province":"CA",
    "sg:tags":[
        "garment",
        "manufacturer"
    ],
    "wof:name":"Genre Consultant Inc",
    "wof:placetype":"venue"
},
  "geometry": {"coordinates":[-118.011811,33.926766],"type":"Point"}
}