{
  "type": "Feature",
  "properties": {
    "addr:full":"14441 Brookhurst St Ste 5 Garden Grove CA 92843",
    "addr:housenumber":"14441",
    "addr:postcode":"92843",
    "addr:street":"Brookhurst St Ste 5",
    "iso:country":"US",
    "sg:address":"14441 Brookhurst St Ste 5",
    "sg:city":"Garden Grove",
    "sg:classifiers":[
        {
            "category":"Shopping",
            "subcategory":"Bridal",
            "type":"Retail Goods"
        }
    ],
    "sg:phone":"+1 714 775 4611",
    "sg:postcode":"92843",
    "sg:province":"CA",
    "wof:name":"Thai Bridal & Florist",
    "wof:placetype":"venue"
},
  "geometry": {"coordinates":[-117.95500199999999,33.7533],"type":"Point"}
}