{
  "type": "Feature",
  "properties": {
    "iso:country":"US",
    "sg:address":"10025 Elk Mountain Rd",
    "sg:city":"Upper Lake",
    "sg:classifiers":[
        {
            "category":"Government",
            "subcategory":"Office",
            "type":"Public Place"
        }
    ],
    "sg:phone":"+1 707 275 2361",
    "sg:postcode":"95485",
    "sg:province":"CA",
    "wof:name":"Us Forest Srv",
    "wof:placetype":"venue"
},
  "geometry": {"coordinates":[-122.906443,39.171363],"type":"Point"}
}