{
  "type": "Feature",
  "properties": {
    "iso:country":"US",
    "sg:address":"141 Briggs Ranch Dr",
    "sg:city":"Folsom",
    "sg:classifiers":[
        {
            "category":"Banks & Credit Unions",
            "subcategory":"Bank",
            "type":"Services"
        }
    ],
    "sg:phone":"+1 916 769 7275",
    "sg:postcode":"95630",
    "sg:province":"CA",
    "sg:tags":[
        "loan",
        "real estate"
    ],
    "wof:name":"Central Alliance Mortgage",
    "wof:placetype":"venue"
},
  "geometry": {"coordinates":[-121.137109,38.687765],"type":"Point"}
}