{
  "type": "Feature",
  "properties": {
    "iso:country":"US",
    "sg:address":"25433 Blackwood Rd",
    "sg:city":"Murrieta",
    "sg:classifiers":[
        {
            "category":"Building & Trades",
            "subcategory":"Cleaning & Sanitation",
            "type":"Services"
        }
    ],
    "sg:phone":"+1 951 506 9977",
    "sg:postcode":"92563",
    "sg:province":"CA",
    "sg:tags":[
        "janitor"
    ],
    "wof:name":"Bucketeer Maintenance",
    "wof:placetype":"venue"
},
  "geometry": {"coordinates":[-117.169252,33.562399],"type":"Point"}
}