{
  "type": "Feature",
  "properties": {
    "iso:country":"US",
    "sg:address":"17503 Sonoma Hwy",
    "sg:city":"Sonoma",
    "sg:classifiers":[
        {
            "category":"Professional",
            "subcategory":"Art Services",
            "type":"Services"
        }
    ],
    "sg:phone":"+1 707 939 1131",
    "sg:postcode":"95476",
    "sg:province":"CA",
    "sg:tags":[
        "graphic",
        "designer"
    ],
    "sg:website":"www.studio-y.com",
    "wof:name":"Studio Y",
    "wof:placetype":"venue"
},
  "geometry": {"coordinates":[-122.484421,38.317957],"type":"Point"}
}