{
  "type": "Feature",
  "properties": {
    "addr:full":"5900 Monterey Rd Los Angeles CA 90042",
    "addr:housenumber":"5900",
    "addr:postcode":"90042",
    "addr:street":"Monterey Rd",
    "iso:country":"US",
    "sg:address":"5900 Monterey Rd",
    "sg:city":"Los Angeles",
    "sg:classifiers":[
        {
            "category":"Restaurant",
            "type":"Food & Drink"
        }
    ],
    "sg:phone":"+1 323 257 0580",
    "sg:postcode":"90042",
    "sg:province":"CA",
    "sg:tags":[
        "thai"
    ],
    "wof:name":"Noodle Head-Thai Food",
    "wof:placetype":"venue"
},
  "geometry": {"coordinates":[-118.18440200000001,34.104733],"type":"Point"}
}