{
  "type": "Feature",
  "properties": {
    "iso:country":"US",
    "sg:address":"1011 A St",
    "sg:city":"Antioch",
    "sg:classifiers":[
        {
            "category":"Professional",
            "subcategory":"Lawyer & Legal Services",
            "type":"Services"
        }
    ],
    "sg:phone":"+1 925 757 7020",
    "sg:postcode":"94509",
    "sg:province":"CA",
    "sg:tags":[
        "attorney"
    ],
    "sg:website":"www.deltalawyer.com",
    "wof:name":"Hobin Shingler & Simon LLP",
    "wof:placetype":"venue"
},
  "geometry": {"coordinates":[-121.805938,38.010288],"type":"Point"}
}