{
  "type": "Feature",
  "properties": {
    "addr:full":"2812 Santa Monica Blvd. Ste. 206 Santa Monica CA 90404",
    "addr:housenumber":"2812",
    "addr:postcode":"90404",
    "addr:street":"Santa Monica Blvd. Ste. 206",
    "iso:country":"US",
    "sg:address":"2812 Santa Monica Blvd. Ste. 206",
    "sg:city":"Santa Monica",
    "sg:classifiers":[
        {
            "category":"Professional",
            "subcategory":"Advertising",
            "type":"Services"
        }
    ],
    "sg:phone":"+1 646 723 4600",
    "sg:postcode":"90404",
    "sg:province":"CA",
    "sg:tags":[
        "adotube",
        "video",
        "monetize-video",
        "video-advertising",
        "in-video",
        "monetization"
    ],
    "sg:website":"http://www.adotube.com/",
    "wof:name":"AdoTube",
    "wof:placetype":"venue"
},
  "geometry": {"coordinates":[-118.471575,34.035382],"type":"Point"}
}