{
  "type": "Feature",
  "properties": {
    "addr:full":"6441 Burt Rd Irvine CA 92618",
    "addr:housenumber":"6441",
    "addr:postcode":"92618",
    "addr:street":"Burt Rd",
    "iso:country":"US",
    "sg:address":"6441 Burt Rd",
    "sg:city":"Irvine",
    "sg:classifiers":[
        {
            "category":"Autos & Motor Vehicles",
            "subcategory":"Automobile Sales",
            "type":"Retail Goods"
        }
    ],
    "sg:phone":"+1 949 653 6711",
    "sg:postcode":"92618",
    "sg:province":"CA",
    "sg:tags":[
        "automotive"
    ],
    "sg:website":"www.travelandusa.com/McMahonsRV/...",
    "wof:name":"McMahon's RV Service",
    "wof:placetype":"venue"
},
  "geometry": {"coordinates":[-117.762123,33.679393],"type":"Point"}
}