{
  "type": "Feature",
  "properties": {
    "iso:country":"US",
    "sg:address":"519 E Broadway",
    "sg:city":"Glendale",
    "sg:classifiers":[
        {
            "category":"Health Services",
            "subcategory":"Doctor",
            "type":"Services"
        }
    ],
    "sg:phone":"+1 818 409 3020",
    "sg:postcode":"91205",
    "sg:province":"CA",
    "wof:name":"Janoian Noobar MD",
    "wof:placetype":"venue"
},
  "geometry": {"coordinates":[-118.24900100000001,34.1465],"type":"Point"}
}