{
  "type": "Feature",
  "properties": {
    "iso:country":"US",
    "sg:address":"1441 W Olympic Blvd",
    "sg:city":"Los Angeles",
    "sg:classifiers":[
        {
            "category":"Professional",
            "subcategory":"Lawyer & Legal Services",
            "type":"Services"
        }
    ],
    "sg:phone":"+1 213 736 1031",
    "sg:postcode":"90015",
    "sg:province":"CA",
    "wof:name":"Western Law Ctr For Disablty Rghts At Lyla Lw Schl",
    "wof:placetype":"venue"
},
  "geometry": {"coordinates":[-118.272003,34.0481],"type":"Point"}
}