{
  "type": "Feature",
  "properties": {
    "iso:country":"US",
    "sg:address":"107 S Fair Oaks Ave",
    "sg:city":"Pasadena",
    "sg:classifiers":[
        {
            "category":"Professional",
            "type":"Services"
        }
    ],
    "sg:phone":"+1 626 744 1304",
    "sg:postcode":"91105",
    "sg:province":"CA",
    "wof:name":"Neoterranean Com",
    "wof:placetype":"venue"
},
  "geometry": {"coordinates":[-118.150531,34.144341],"type":"Point"}
}