{
  "type": "Feature",
  "properties": {
    "iso:country":"US",
    "sg:address":"7035 Morro Rd",
    "sg:city":"Atascadero",
    "sg:classifiers":[
        {
            "category":"Banks & Credit Unions",
            "subcategory":"Investment Brokerage",
            "type":"Services"
        }
    ],
    "sg:phone":"+1 805 466 1776",
    "sg:postcode":"93422",
    "sg:province":"CA",
    "sg:tags":[
        "advisory",
        "financial"
    ],
    "sg:website":"www.hurstfinancial.com",
    "wof:name":"Hurst Financial Corp",
    "wof:placetype":"venue"
},
  "geometry": {"coordinates":[-120.666359,35.480615],"type":"Point"}
}