{
  "type": "Feature",
  "properties": {
    "iso:country":"US",
    "sg:address":"15425 Los Gatos Blvd",
    "sg:city":"Los Gatos",
    "sg:classifiers":[
        {
            "category":"Banks & Credit Unions",
            "subcategory":"Investment Brokerage",
            "type":"Services"
        }
    ],
    "sg:phone":"+1 408 358 5811",
    "sg:postcode":"95032",
    "sg:province":"CA",
    "sg:tags":[
        "management"
    ],
    "sg:website":"www.enterprise-trust.com",
    "wof:name":"Enterprise Trust & Investment",
    "wof:placetype":"venue"
},
  "geometry": {"coordinates":[-121.959726,37.242955],"type":"Point"}
}