{
  "type": "Feature",
  "properties": {
    "addr:full":"1320 Simpson Way Escondido CA 92029",
    "addr:housenumber":"1320",
    "addr:postcode":"92029",
    "addr:street":"Simpson Way",
    "iso:country":"US",
    "sg:address":"1320 Simpson Way",
    "sg:city":"Escondido",
    "sg:classifiers":[
        {
            "category":"Retail",
            "subcategory":"Auto Repair",
            "type":"Services"
        }
    ],
    "sg:phone":"+1 760 432 8785",
    "sg:postcode":"92029",
    "sg:province":"CA",
    "sg:tags":[
        "body",
        "conversion",
        "van",
        "automotive",
        "accessory",
        "truck"
    ],
    "sg:website":"www.handivanmobility.com",
    "wof:name":"Handi-Van",
    "wof:placetype":"venue"
},
  "geometry": {"coordinates":[-117.107462,33.121973],"type":"Point"}
}