{
  "type": "Feature",
  "properties": {
    "addr:full":"7472 N Fresno St Fresno CA 93720",
    "addr:housenumber":"7472",
    "addr:postcode":"93720",
    "addr:street":"N Fresno",
    "iso:country":"US",
    "sg:address":"7472 N Fresno St",
    "sg:city":"Fresno",
    "sg:classifiers":[
        {
            "category":"Insurance",
            "subcategory":"Insurance Agent",
            "type":"Services"
        },
        {
            "category":"Insurance",
            "subcategory":"Hazard Insurance",
            "type":"Services"
        },
        {
            "category":"Insurance",
            "subcategory":"Title Insurance",
            "type":"Services"
        },
        {
            "category":"Insurance",
            "subcategory":"Life Insurance",
            "type":"Services"
        }
    ],
    "sg:phone":"+1 559 435 7791",
    "sg:postcode":"93720",
    "sg:province":"CA",
    "sg:tags":[
        "auto",
        "commercial",
        "business",
        "homeowner"
    ],
    "sg:website":"http://www.farmersagent.com/dcarnation/",
    "wof:name":"Doug Carnation - Farmers Insurance",
    "wof:placetype":"venue"
},
  "geometry": {"coordinates":[-119.783689,36.845986],"type":"Point"}
}