{
  "type": "Feature",
  "properties": {
    "addr:full":"6729 N Palm Ave Fresno CA 93704",
    "addr:housenumber":"6729",
    "addr:postcode":"93704",
    "addr:street":"N Palm Ave",
    "iso:country":"US",
    "sg:address":"6729 N Palm Ave",
    "sg:city":"Fresno",
    "sg:classifiers":[
        {
            "category":"Real Estate",
            "subcategory":"Real Estate Agent",
            "type":"Services"
        }
    ],
    "sg:phone":"+1 559 490 5669",
    "sg:postcode":"93704",
    "sg:province":"CA",
    "sg:tags":[
        "management"
    ],
    "wof:name":"Eurocal Partners",
    "wof:placetype":"venue"
},
  "geometry": {"coordinates":[-119.808379,36.835517],"type":"Point"}
}