{
  "type": "Feature",
  "properties": {
    "addr:full":"3840 N McKinley St Corona CA 92879",
    "addr:housenumber":"3840",
    "addr:postcode":"92879",
    "addr:street":"N Mckinley St",
    "iso:country":"US",
    "sg:address":"3840 N McKinley St",
    "sg:city":"Corona",
    "sg:classifiers":[
        {
            "category":"Recreation",
            "type":"Entertainment"
        }
    ],
    "sg:phone":"+1 951 734 0430",
    "sg:postcode":"92879",
    "sg:province":"CA",
    "sg:tags":[
        "parlor",
        "billiard"
    ],
    "wof:name":"Korner Pocket",
    "wof:placetype":"venue"
},
  "geometry": {"coordinates":[-117.514275,33.881952],"type":"Point"}
}