{
  "type": "Feature",
  "properties": {
    "addr:full":"7426 Cherry Ave Fontana CA 92335",
    "addr:housenumber":"7426",
    "addr:postcode":"92335",
    "addr:street":"Cherry Ave",
    "iso:country":"US",
    "sg:address":"7426 Cherry Ave",
    "sg:city":"Fontana",
    "sg:classifiers":[
        {
            "category":"Shopping",
            "subcategory":"Clothing, Apparel, & Fashions",
            "type":"Retail Goods"
        }
    ],
    "sg:phone":"+1 909 355 2010",
    "sg:postcode":"92335",
    "sg:province":"CA",
    "sg:tags":[
        "furnishing"
    ],
    "wof:name":"Ultimate Gear",
    "wof:placetype":"venue"
},
  "geometry": {"coordinates":[-117.48862699999999,34.11846],"type":"Point"}
}