{
  "type": "Feature",
  "properties": {
    "iso:country":"US",
    "sg:address":"7426 Cherry Ave",
    "sg:city":"Fontana",
    "sg:classifiers":[
        {
            "category":"Shopping",
            "subcategory":"Clothing, Apparel, & Fashions",
            "type":"Retail Goods"
        }
    ],
    "sg:phone":"+1 909 355 2010",
    "sg:postcode":"92335",
    "sg:province":"CA",
    "sg:tags":[
        "furnishing"
    ],
    "wof:name":"Ultimate Gear",
    "wof:placetype":"venue"
},
  "geometry": {"coordinates":[-117.488627,34.11846],"type":"Point"}
}