{
  "type": "Feature",
  "properties": {
    "iso:country":"US",
    "sg:address":"17027 Grafton St",
    "sg:city":"Esparto",
    "sg:classifiers":[
        {
            "category":"Building & Trades",
            "subcategory":"Equipment Rental",
            "type":"Services"
        }
    ],
    "sg:phone":"+1 530 787 3027",
    "sg:postcode":"95627",
    "sg:province":"CA",
    "sg:tags":[
        "contractors'"
    ],
    "wof:name":"Cooper, Grant Equipment",
    "wof:placetype":"venue"
},
  "geometry": {"coordinates":[-122.017388,38.69304],"type":"Point"}
}