{
  "type": "Feature",
  "properties": {
    "addr:full":"2835 E 11th St Los Angeles CA 90023",
    "addr:housenumber":"2835",
    "addr:postcode":"90023",
    "addr:street":"E 11Th St",
    "iso:country":"US",
    "sg:address":"2835 E 11th St",
    "sg:city":"Los Angeles",
    "sg:classifiers":[
        {
            "category":"Manufacturing",
            "subcategory":"Apparel",
            "type":"Manufacturing & Wholesale Goods"
        }
    ],
    "sg:phone":"+1 323 780 2820",
    "sg:postcode":"90023",
    "sg:province":"CA",
    "sg:tags":[
        "sewing",
        "contractor"
    ],
    "wof:name":"Schefres Fashions",
    "wof:placetype":"venue"
},
  "geometry": {"coordinates":[-118.216694,34.022035],"type":"Point"}
}