{
  "type": "Feature",
  "properties": {
    "addr:full":"604 Main St Half Moon Bay CA 94019",
    "addr:housenumber":"604",
    "addr:postcode":"94019",
    "addr:street":"Main St",
    "iso:country":"US",
    "sg:address":"604 Main St",
    "sg:city":"Half Moon Bay",
    "sg:classifiers":[
        {
            "category":"Home & Garden",
            "subcategory":"Furniture",
            "type":"Retail Goods"
        }
    ],
    "sg:phone":"+1 650 712 8900",
    "sg:postcode":"94019",
    "sg:province":"CA",
    "wof:name":"Sense-Peace Asian Style Furn",
    "wof:placetype":"venue"
},
  "geometry": {"coordinates":[-122.429605,37.461646],"type":"Point"}
}