{
  "type": "Feature",
  "properties": {
    "addr:full":"3615 Westridge Ct Kelseyville CA 95451",
    "addr:housenumber":"3615",
    "addr:postcode":"95451",
    "addr:street":"Westridge Ct",
    "iso:country":"US",
    "sg:address":"3615 Westridge Ct",
    "sg:city":"Kelseyville",
    "sg:classifiers":[
        {
            "category":"Wholesale",
            "subcategory":"Chemicals & Plastics",
            "type":"Manufacturing & Wholesale Goods"
        }
    ],
    "sg:phone":"+1 707 279 6720",
    "sg:postcode":"95451",
    "sg:province":"CA",
    "sg:tags":[
        "cleaning",
        "compound"
    ],
    "wof:name":"Citrus Resources",
    "wof:placetype":"venue"
},
  "geometry": {"coordinates":[-122.785403,38.997388],"type":"Point"}
}