{
  "type": "Feature",
  "properties": {
    "iso:country":"US",
    "sg:address":"200 Jennings St",
    "sg:city":"San Francisco",
    "sg:classifiers":[
        {
            "category":"Wholesale",
            "subcategory":"Groceries",
            "type":"Manufacturing & Wholesale Goods"
        }
    ],
    "sg:phone":"+1 415 206 7400",
    "sg:postcode":"94124",
    "sg:province":"CA",
    "sg:tags":[
        "beverage"
    ],
    "wof:name":"Pepsi-Cola Co",
    "wof:placetype":"venue"
},
  "geometry": {"coordinates":[-122.37911,37.73768],"type":"Point"}
}