{
  "type": "Feature",
  "properties": {
    "addr:full":"17973 Ranchera Rd Shasta Lake CA 96019",
    "addr:housenumber":"17973",
    "addr:postcode":"96019",
    "addr:street":"Ranchera Rd",
    "iso:country":"US",
    "sg:address":"17973 Ranchera Rd",
    "sg:city":"Shasta Lake",
    "sg:classifiers":[
        {
            "category":"Shopping",
            "subcategory":"Gifts & Souvenirs",
            "type":"Retail Goods"
        }
    ],
    "sg:phone":"+1 530 275 0735",
    "sg:postcode":"96019",
    "sg:province":"CA",
    "sg:tags":[
        "basket",
        "parcel"
    ],
    "wof:name":"Little Bit Gifts",
    "wof:placetype":"venue"
},
  "geometry": {"coordinates":[-122.396423,40.674987],"type":"Point"}
}