{
  "type": "Feature",
  "properties": {
    "addr:full":"8119 San Leandro St Oakland CA 94621",
    "addr:housenumber":"8119",
    "addr:postcode":"94621",
    "addr:street":"San Leandro St",
    "iso:country":"US",
    "sg:address":"8119 San Leandro St",
    "sg:city":"Oakland",
    "sg:classifiers":[
        {
            "category":"Restaurant",
            "type":"Food & Drink"
        }
    ],
    "sg:phone":"+1 510 635 9899",
    "sg:postcode":"94621",
    "sg:province":"CA",
    "sg:tags":[
        "mexican"
    ],
    "wof:name":"Estrellas De Sinaloa",
    "wof:placetype":"venue"
},
  "geometry": {"coordinates":[-122.19168500000001,37.749023],"type":"Point"}
}