{
  "type": "Feature",
  "properties": {
    "iso:country":"US",
    "sg:address":"8510 Firestone Blvd",
    "sg:city":"Downey",
    "sg:classifiers":[
        {
            "category":"Fast Food",
            "type":"Food & Drink"
        },
        {
            "category":"Restaurant",
            "type":"Food & Drink"
        }
    ],
    "sg:postcode":"90241",
    "sg:province":"CA",
    "sg:tags":[
        "chinese"
    ],
    "wof:name":"Panda Express",
    "wof:placetype":"venue"
},
  "geometry": {"coordinates":[-118.12938,33.938169],"type":"Point"}
}