{
  "type": "Feature",
  "properties": {
    "iso:country":"US",
    "sg:address":"1101 5th Ave",
    "sg:city":"San Rafael",
    "sg:classifiers":[
        {
            "category":"Professional",
            "subcategory":"Lawyer & Legal Services",
            "type":"Services"
        }
    ],
    "sg:phone":"+1 415 457 5707",
    "sg:postcode":"94901",
    "sg:province":"CA",
    "sg:tags":[
        "attorney"
    ],
    "wof:name":"Charles B Tunnell",
    "wof:placetype":"venue"
},
  "geometry": {"coordinates":[-122.52931700000001,37.974278],"type":"Point"}
}