{
  "type": "Feature",
  "properties": {
    "addr:full":"1529 W Ramsey St Banning CA 92220",
    "addr:housenumber":"1529",
    "addr:postcode":"92220",
    "addr:street":"W Ramsey St",
    "iso:country":"US",
    "sg:address":"1529 W Ramsey St",
    "sg:city":"Banning",
    "sg:classifiers":[
        {
            "category":"Shopping",
            "subcategory":"Clothing, Apparel, & Fashions",
            "type":"Retail Goods"
        }
    ],
    "sg:phone":"+1 951 922 1200",
    "sg:postcode":"92220",
    "sg:province":"CA",
    "sg:tags":[
        "uniform"
    ],
    "wof:name":"Uniform Solutions",
    "wof:placetype":"venue"
},
  "geometry": {"coordinates":[-116.893491,33.925496],"type":"Point"}
}