{
  "type": "Feature",
  "properties": {
    "iso:country":"US",
    "sg:address":"14430 Bevers Way",
    "sg:city":"Pioneer",
    "sg:classifiers":[
        {
            "category":"Building & Trades",
            "subcategory":"Construction",
            "type":"Services"
        }
    ],
    "sg:phone":"+1 209 295 4397",
    "sg:postcode":"95666",
    "sg:province":"CA",
    "sg:tags":[
        "maker",
        "cabinet"
    ],
    "wof:name":"Ark Cabinets & Woodworking",
    "wof:placetype":"venue"
},
  "geometry": {"coordinates":[-120.592341,38.416326],"type":"Point"}
}