{
  "type": "Feature",
  "properties": {
    "addr:full":"727 Clovis Ave Clovis CA 93612",
    "addr:housenumber":"727",
    "addr:postcode":"93612",
    "addr:street":"Clovis Ave",
    "iso:country":"US",
    "sg:address":"727 Clovis Ave",
    "sg:city":"Clovis",
    "sg:classifiers":[
        {
            "category":"Professional",
            "type":"Services"
        }
    ],
    "sg:phone":"+1 559 299 9774",
    "sg:postcode":"93612",
    "sg:province":"CA",
    "sg:tags":[
        "establishment"
    ],
    "wof:name":"DKH Enterprises",
    "wof:placetype":"venue"
},
  "geometry": {"coordinates":[-119.70055600000001,36.821088],"type":"Point"}
}