{
  "type": "Feature",
  "properties": {
    "iso:country":"US",
    "sg:address":"2050 Springfield Dr # 315",
    "sg:city":"Chico",
    "sg:classifiers":[
        {
            "category":"Building & Trades",
            "subcategory":"Construction",
            "type":"Services"
        }
    ],
    "sg:phone":"+1 530 520 5012",
    "sg:postcode":"95928",
    "sg:province":"CA",
    "sg:tags":[
        "roofing",
        "industrial",
        "contractors-commercial",
        "contractor"
    ],
    "wof:name":"Western Roofing",
    "wof:placetype":"venue"
},
  "geometry": {"coordinates":[-121.799019,39.729839],"type":"Point"}
}