{
  "type": "Feature",
  "properties": {
    "addr:full":"2379 Mahan Way San Pablo CA 94806",
    "addr:housenumber":"2379",
    "addr:postcode":"94806",
    "addr:street":"Mahan Way",
    "iso:country":"US",
    "sg:address":"2379 Mahan Way",
    "sg:city":"San Pablo",
    "sg:classifiers":[
        {
            "category":"Shopping",
            "subcategory":"Music",
            "type":"Retail Goods"
        }
    ],
    "sg:phone":"+1 510 741 5457",
    "sg:postcode":"94806",
    "sg:province":"CA",
    "wof:name":"Pure Image Records",
    "wof:placetype":"venue"
},
  "geometry": {"coordinates":[-122.31504700000001,37.992773],"type":"Point"}
}