{
  "type": "Feature",
  "properties": {
    "iso:country":"US",
    "sg:address":"40915 Encyclopedia Circle",
    "sg:city":"Fremont",
    "sg:classifiers":[
        {
            "category":"Professional",
            "subcategory":"Research",
            "type":"Services"
        }
    ],
    "sg:phone":"+1 510 687 9501",
    "sg:postcode":"94538",
    "sg:province":"CA",
    "sg:website":"http://www.oorjaprotonics.com/",
    "wof:name":"Oorja Protonics",
    "wof:placetype":"venue"
},
  "geometry": {"coordinates":[-121.989221,37.517479],"type":"Point"}
}