{
  "type": "Feature",
  "properties": {
    "addr:full":"9265 Telegraph Rd Pico Rivera CA 90660",
    "addr:housenumber":"9265",
    "addr:postcode":"90660",
    "addr:street":"Telegraph Rd",
    "iso:country":"US",
    "sg:address":"9265 Telegraph Rd",
    "sg:city":"Pico Rivera",
    "sg:classifiers":[
        {
            "category":"Health Services",
            "subcategory":"Optometrist",
            "type":"Services"
        }
    ],
    "sg:phone":"+1 562 222 1822",
    "sg:postcode":"90660",
    "sg:province":"CA",
    "wof:name":"Arcos Sylvia OD",
    "wof:placetype":"venue"
},
  "geometry": {"coordinates":[-118.105003,33.957401],"type":"Point"}
}