{
  "type": "Feature",
  "properties": {
    "iso:country":"US",
    "sg:address":"9634 Washburn Rd Ste A",
    "sg:city":"Downey",
    "sg:classifiers":[
        {
            "category":"Shopping",
            "subcategory":"Beauty & Cosmetics",
            "type":"Retail Goods"
        }
    ],
    "sg:phone":"+1 562 940 8300",
    "sg:postcode":"90241",
    "sg:province":"CA",
    "sg:tags":[
        "supply"
    ],
    "sg:website":"www.healthspecialty.com",
    "wof:name":"Health Specialty",
    "wof:placetype":"venue"
},
  "geometry": {"coordinates":[-118.115905,33.924192],"type":"Point"}
}