{
  "type": "Feature",
  "properties": {
    "iso:country":"US",
    "sg:address":"1206 Maple Ave",
    "sg:city":"Los Angeles",
    "sg:classifiers":[
        {
            "category":"Wholesale",
            "subcategory":"Apparel",
            "type":"Manufacturing & Wholesale Goods"
        }
    ],
    "sg:phone":"+1 213 744 0188",
    "sg:postcode":"90015",
    "sg:province":"CA",
    "sg:tags":[
        "clothing"
    ],
    "wof:name":"Daniella Kid Inc",
    "wof:placetype":"venue"
},
  "geometry": {"coordinates":[-118.257114,34.034586],"type":"Point"}
}