{
  "type": "Feature",
  "properties": {
    "addr:full":"2491 W Shaw Ave Fresno CA 93711",
    "addr:housenumber":"2491",
    "addr:postcode":"93711",
    "addr:street":"W Shaw Ave",
    "iso:country":"US",
    "sg:address":"2491 W Shaw Ave",
    "sg:city":"Fresno",
    "sg:classifiers":[
        {
            "category":"Banks & Credit Unions",
            "subcategory":"Investment Brokerage",
            "type":"Services"
        },
        {
            "category":"Insurance",
            "subcategory":"Hazard Insurance",
            "type":"Services"
        },
        {
            "category":"Banks & Credit Unions",
            "subcategory":"Financial Services",
            "type":"Services"
        }
    ],
    "sg:phone":"+1 559 225 1767",
    "sg:postcode":"93711",
    "sg:province":"CA",
    "sg:tags":[
        "advisory",
        "planning",
        "consultant"
    ],
    "wof:name":"Primerica Financial Svc",
    "wof:placetype":"venue"
},
  "geometry": {"coordinates":[-119.837532,36.807991],"type":"Point"}
}