{
  "type": "Feature",
  "properties": {
    "addr:full":"68337 Kieley Rd Cathedral City CA 92234",
    "addr:postcode":"68337;92234",
    "addr:street":"Kieley Rd",
    "iso:country":"US",
    "sg:address":"68337 Kieley Rd",
    "sg:city":"Cathedral City",
    "sg:classifiers":[
        {
            "category":"Building & Trades",
            "subcategory":"Plumbing",
            "type":"Services"
        }
    ],
    "sg:phone":"+1 760 321 7448",
    "sg:postcode":"92234",
    "sg:province":"CA",
    "sg:website":"www.hammerpumping.com",
    "wof:name":"Hammer Pumping Inc",
    "wof:placetype":"venue"
},
  "geometry": {"coordinates":[-116.46919200000001,33.785891],"type":"Point"}
}