{
  "type": "Feature",
  "properties": {
    "iso:country":"US",
    "sg:address":"8015 S Sepulveda Blvd",
    "sg:city":"Westchester",
    "sg:classifiers":[
        {
            "category":"Sports & Exercise",
            "subcategory":"Gym",
            "type":"Entertainment"
        }
    ],
    "sg:phone":"+1 310 670 4316",
    "sg:postcode":"90045",
    "sg:province":"CA",
    "sg:tags":[
        "trainer"
    ],
    "wof:name":"Westchester Family YMCA",
    "wof:placetype":"venue"
},
  "geometry": {"coordinates":[-118.396765,33.966569],"type":"Point"}
}