{
  "type": "Feature",
  "properties": {
    "iso:country":"US",
    "sg:address":"1791 Tribute Rd Ste E",
    "sg:city":"Sacramento",
    "sg:classifiers":[
        {
            "category":"Professional",
            "subcategory":"Printing & Photocopies",
            "type":"Services"
        }
    ],
    "sg:phone":"+1 916 920 9500",
    "sg:postcode":"95815",
    "sg:province":"CA",
    "sg:tags":[
        "services-commercial"
    ],
    "wof:name":"Color Promotion Industries",
    "wof:placetype":"venue"
},
  "geometry": {"coordinates":[-121.447006,38.597431],"type":"Point"}
}