{
  "type": "Feature",
  "properties": {
    "addr:full":"732 N Highland Ave Los Angeles CA 90038",
    "addr:housenumber":"732",
    "addr:postcode":"90038",
    "addr:street":"N Highland Ave",
    "iso:country":"US",
    "sg:address":"732 N Highland Ave",
    "sg:city":"Los Angeles",
    "sg:classifiers":[
        {
            "category":"Health Services",
            "subcategory":"Clinic",
            "type":"Services"
        }
    ],
    "sg:phone":"+1 323 957 6555",
    "sg:postcode":"90038",
    "sg:province":"CA",
    "wof:name":"Mt Sinai Day Adult Healthcare",
    "wof:placetype":"venue"
},
  "geometry": {"coordinates":[-118.338511,34.084683],"type":"Point"}
}