{
  "type": "Feature",
  "properties": {
    "iso:country":"US",
    "sg:address":"300 Lakeside Dr",
    "sg:city":"Oakland",
    "sg:classifiers":[
        {
            "category":"Shopping",
            "subcategory":"Florist",
            "type":"Retail Goods"
        }
    ],
    "sg:phone":"+1 510 832 8653",
    "sg:postcode":"94666",
    "sg:province":"CA",
    "wof:name":"Sweet Bloom",
    "wof:placetype":"venue"
},
  "geometry": {"coordinates":[-122.263357,37.806653],"type":"Point"}
}