{
  "type": "Feature",
  "properties": {
    "addr:full":"4500 Macarthur Blvd Newport Beach CA 92660",
    "addr:housenumber":"4500",
    "addr:postcode":"92660",
    "addr:street":"Macarthur Blvd",
    "iso:country":"US",
    "sg:address":"4500 Macarthur Blvd",
    "sg:city":"Newport Beach",
    "sg:classifiers":[
        {
            "category":"Shopping",
            "subcategory":"Florist",
            "type":"Retail Goods"
        }
    ],
    "sg:phone":"+1 949 466 1413",
    "sg:postcode":"92660",
    "sg:province":"CA",
    "wof:name":"Rachel Lyn Floral Decor",
    "wof:placetype":"venue"
},
  "geometry": {"coordinates":[-117.864029,33.671738],"type":"Point"}
}