{
  "type": "Feature",
  "properties": {
    "iso:country":"US",
    "sg:address":"515 Central Ave",
    "sg:city":"Mountain View",
    "sg:classifiers":[
        {
            "category":"Taxi",
            "type":"Transportation"
        }
    ],
    "sg:phone":"+1 650 254 1230",
    "sg:postcode":"94043",
    "sg:province":"CA",
    "sg:tags":[
        "taxicab"
    ],
    "wof:name":"Yellow A Cab",
    "wof:placetype":"venue"
},
  "geometry": {"coordinates":[-122.07446299999999,37.396829],"type":"Point"}
}