{
  "type": "Feature",
  "properties": {
    "iso:country":"US",
    "sg:address":"18726 S Laurel Park Rd",
    "sg:city":"Compton",
    "sg:classifiers":[
        {
            "category":"Freight",
            "type":"Transportation"
        }
    ],
    "sg:phone":"+1 310 952 8850",
    "sg:postcode":"90220",
    "sg:province":"CA",
    "sg:tags":[
        "intrastate",
        "trucking"
    ],
    "wof:name":"Harbor Rail Transport",
    "wof:placetype":"venue"
},
  "geometry": {"coordinates":[-118.219258,33.861363],"type":"Point"}
}