{
  "type": "Feature",
  "properties": {
    "addr:full":"3144 Palm St Mcclellan CA 95652",
    "addr:housenumber":"3144",
    "addr:postcode":"95652",
    "addr:street":"Palm St",
    "iso:country":"US",
    "sg:address":"3144 Palm St",
    "sg:city":"Mcclellan",
    "sg:classifiers":[
        {
            "category":"Professional",
            "subcategory":"Printing & Photocopies",
            "type":"Services"
        }
    ],
    "sg:phone":"+1 916 641 1700",
    "sg:postcode":"95652",
    "sg:province":"CA",
    "sg:tags":[
        "duplicating",
        "copying"
    ],
    "wof:name":"Kopiworks",
    "wof:placetype":"venue"
},
  "geometry": {"coordinates":[-121.388165,38.665462],"type":"Point"}
}