{
  "type": "Feature",
  "properties": {
    "addr:full":"405 Ave 6 Lake Elsinore CA 92530",
    "addr:housenumber":"405",
    "addr:postcode":"92530",
    "addr:street":"Ave 6",
    "iso:country":"US",
    "sg:address":"405 Ave 6",
    "sg:city":"Lake Elsinore",
    "sg:classifiers":[
        {
            "category":"Building & Trades",
            "subcategory":"Construction",
            "type":"Services"
        }
    ],
    "sg:phone":"+1 760 807 1161",
    "sg:postcode":"92530",
    "sg:province":"CA",
    "sg:tags":[
        "contractor"
    ],
    "sg:website":"www.lakeelsinorehandyman.com/",
    "wof:name":"Carl Can Fix It",
    "wof:placetype":"venue"
},
  "geometry": {"coordinates":[-117.31091499999999,33.6654],"type":"Point"}
}