{
  "type": "Feature",
  "properties": {
    "iso:country":"US",
    "sg:address":"1117 11th St",
    "sg:city":"Manhattan Beach",
    "sg:classifiers":[
        {
            "category":"Insurance",
            "subcategory":"Insurance Agent",
            "type":"Services"
        }
    ],
    "sg:phone":"+1 310 798 1047",
    "sg:postcode":"90266",
    "sg:province":"CA",
    "wof:name":"Dan Carmona",
    "wof:placetype":"venue"
},
  "geometry": {"coordinates":[-118.39411,33.886638],"type":"Point"}
}