{
  "type": "Feature",
  "properties": {
    "iso:country":"US",
    "sg:address":"1445 Foothill Blvd",
    "sg:city":"La Verne",
    "sg:classifiers":[
        {
            "category":"Wholesale",
            "subcategory":"Furniture",
            "type":"Manufacturing & Wholesale Goods"
        }
    ],
    "sg:phone":"+1 909 596 9014",
    "sg:postcode":"91750",
    "sg:province":"CA",
    "wof:name":"Eclecticity",
    "wof:placetype":"venue"
},
  "geometry": {"coordinates":[-117.776479,34.117195],"type":"Point"}
}