{
  "type": "Feature",
  "properties": {
    "iso:country":"US",
    "sg:address":"3432 Serpentine Dr",
    "sg:city":"Antioch",
    "sg:classifiers":[
        {
            "category":"Banks & Credit Unions",
            "subcategory":"Bank",
            "type":"Services"
        }
    ],
    "sg:phone":"+1 925 778 0118",
    "sg:postcode":"94509",
    "sg:province":"CA",
    "sg:tags":[
        "equipment",
        "leasing"
    ],
    "wof:name":"CIT",
    "wof:placetype":"venue"
},
  "geometry": {"coordinates":[-121.791315,37.985412],"type":"Point"}
}