{
  "type": "Feature",
  "properties": {
    "addr:full":"901 E 31st St Los Angeles CA 90011",
    "addr:housenumber":"901",
    "addr:postcode":"90011",
    "addr:street":"E 31St St",
    "iso:country":"US",
    "sg:address":"901 E 31st St",
    "sg:city":"Los Angeles",
    "sg:classifiers":[
        {
            "category":"Wholesale",
            "subcategory":"Apparel",
            "type":"Manufacturing & Wholesale Goods"
        }
    ],
    "sg:phone":"+1 323 234 5755",
    "sg:postcode":"90011",
    "sg:province":"CA",
    "wof:name":"Basic Mode",
    "wof:placetype":"venue"
},
  "geometry": {"coordinates":[-118.257295,34.014826],"type":"Point"}
}