{
  "type": "Feature",
  "properties": {
    "addr:full":"8300 Arroyo Cir Gilroy CA 95020",
    "addr:housenumber":"8300",
    "addr:postcode":"95020",
    "addr:street":"Arroyo Cir",
    "iso:country":"US",
    "sg:address":"8300 Arroyo Cir",
    "sg:city":"Gilroy",
    "sg:classifiers":[
        {
            "category":"Home & Garden",
            "subcategory":"Home Furnishings",
            "type":"Retail Goods"
        }
    ],
    "sg:phone":"+1 408 847 3747",
    "sg:postcode":"95020",
    "sg:province":"CA",
    "sg:tags":[
        "kitchen",
        "accessory"
    ],
    "sg:website":"www.kitcol.com",
    "wof:name":"Kitchen Collection",
    "wof:placetype":"venue"
},
  "geometry": {"coordinates":[-121.56229,37.022392],"type":"Point"}
}