{
  "type": "Feature",
  "properties": {
    "addr:full":"1529 Cypress St Walnut Creek CA 94596",
    "addr:housenumber":"1529",
    "addr:postcode":"94596",
    "addr:street":"Cypress St",
    "iso:country":"US",
    "sg:address":"1529 Cypress St",
    "sg:city":"Walnut Creek",
    "sg:phone":"+1 925 943 1023",
    "sg:postcode":"94596",
    "sg:province":"CA",
    "sg:tags":[
        "equipment",
        "commercial"
    ],
    "wof:name":"Victorex Wholesale",
    "wof:placetype":"venue"
},
  "geometry": {"coordinates":[-122.06199100000001,37.898882],"type":"Point"}
}