{
  "type": "Feature",
  "properties": {
    "addr:full":"2101 Forest Avenue Suite 118 San Jose CA 95128",
    "addr:housenumber":"2101",
    "addr:postcode":"95128",
    "addr:street":"Forest Avenue Suite 118",
    "iso:country":"US",
    "sg:address":"2101 Forest Avenue Suite 118",
    "sg:city":"San Jose",
    "sg:classifiers":[
        {
            "category":"Health Services",
            "subcategory":"Doctor",
            "type":"Services"
        }
    ],
    "sg:phone":"+1 408 292 8800",
    "sg:postcode":"95128",
    "sg:province":"CA",
    "sg:tags":[
        "podiatrist"
    ],
    "sg:website":"FootAnkleDocs.com",
    "wof:name":"Bruce I. Lerman, DPM, Inc.",
    "wof:placetype":"venue"
},
  "geometry": {"coordinates":[-121.937118,37.327079],"type":"Point"}
}