{
  "type": "Feature",
  "properties": {
    "addr:full":"4015 W 132nd St Hawthorne CA 90250",
    "addr:housenumber":"4015",
    "addr:postcode":"90250",
    "addr:street":"W 132Nd St",
    "iso:country":"US",
    "sg:address":"4015 W 132nd St",
    "sg:city":"Hawthorne",
    "sg:classifiers":[
        {
            "category":"Wholesale",
            "subcategory":"Non-durable Goods",
            "type":"Manufacturing & Wholesale Goods"
        }
    ],
    "sg:phone":"+1 310 679 6623",
    "sg:postcode":"90250",
    "sg:province":"CA",
    "wof:name":"Authorized Distributor MA",
    "wof:placetype":"venue"
},
  "geometry": {"coordinates":[-118.344229,33.913175],"type":"Point"}
}