{
  "type": "Feature",
  "properties": {
    "iso:country":"US",
    "sg:address":"2979 Coloma St",
    "sg:city":"Placerville",
    "sg:classifiers":[
        {
            "category":"Education",
            "subcategory":"School",
            "type":"Public Place"
        }
    ],
    "sg:phone":"+1 530 642 3018",
    "sg:postcode":"95667",
    "sg:province":"CA",
    "wof:name":"A Tutoring Place",
    "wof:placetype":"venue"
},
  "geometry": {"coordinates":[-120.803854,38.729575],"type":"Point"}
}