{
  "type": "Feature",
  "properties": {
    "addr:full":"7080 Donlon Way Dublin CA 94568",
    "addr:postcode":"7080;94568",
    "addr:street":"Donlon Way",
    "iso:country":"US",
    "sg:address":"7080 Donlon Way",
    "sg:city":"Dublin",
    "sg:classifiers":[
        {
            "category":"Personal",
            "type":"Services"
        }
    ],
    "sg:phone":"+1 925 833 9044",
    "sg:postcode":"94568",
    "sg:province":"CA",
    "sg:tags":[
        "therapist",
        "massage"
    ],
    "wof:name":"Michelle Porcher Therapeutic",
    "wof:placetype":"venue"
},
  "geometry": {"coordinates":[-121.939054,37.702161],"type":"Point"}
}