{
  "type": "Feature",
  "properties": {
    "iso:country":"US",
    "sg:address":"52 Via Brida",
    "sg:city":"Rancho Santa Margarita",
    "sg:classifiers":[
        {
            "category":"Wholesale",
            "subcategory":"Non-durable Goods",
            "type":"Manufacturing & Wholesale Goods"
        }
    ],
    "sg:phone":"+1 949 623 2757",
    "sg:postcode":"92688",
    "sg:province":"CA",
    "wof:name":"Muirlands Trade Intl",
    "wof:placetype":"venue"
},
  "geometry": {"coordinates":[-117.612452,33.655605],"type":"Point"}
}