{
  "type": "Feature",
  "properties": {
    "addr:full":"1148 Palm Ave Imperial Beach CA 91932",
    "addr:housenumber":"1148",
    "addr:postcode":"91932",
    "addr:street":"Palm Ave",
    "iso:country":"US",
    "sg:address":"1148 Palm Ave",
    "sg:city":"Imperial Beach",
    "sg:classifiers":[
        {
            "category":"Retail",
            "subcategory":"Repair Shop",
            "type":"Services"
        }
    ],
    "sg:phone":"+1 619 424 3389",
    "sg:postcode":"91932",
    "sg:province":"CA",
    "sg:tags":[
        "lock",
        "locksmith"
    ],
    "wof:name":"D & L Lock & Key Svc",
    "wof:placetype":"venue"
},
  "geometry": {"coordinates":[-117.110478,32.583958],"type":"Point"}
}