{
  "type": "Feature",
  "properties": {
    "addr:full":"300 Burton Mesa Blvd Lompoc CA 93436",
    "addr:housenumber":"300",
    "addr:postcode":"93436",
    "addr:street":"Burton Mesa Blvd",
    "iso:country":"US",
    "sg:address":"300 Burton Mesa Blvd",
    "sg:city":"Lompoc",
    "sg:classifiers":[
        {
            "category":"Real Estate",
            "subcategory":"Real Estate Operator",
            "type":"Services"
        }
    ],
    "sg:phone":"+1 805 733 0096",
    "sg:postcode":"93436",
    "sg:province":"CA",
    "sg:tags":[
        "apartment"
    ],
    "wof:name":"Heritage Oak Villas-Vandenberg",
    "wof:placetype":"venue"
},
  "geometry": {"coordinates":[-120.455862,34.701197],"type":"Point"}
}