{
  "type": "Feature",
  "properties": {
    "addr:full":"20550 Hawthorne Blvd Torrance CA 90503",
    "addr:housenumber":"20550",
    "addr:postcode":"90503",
    "addr:street":"Hawthorne Blvd",
    "iso:country":"US",
    "sg:address":"20550 Hawthorne Blvd",
    "sg:city":"Torrance",
    "sg:classifiers":[
        {
            "category":"Autos & Motor Vehicles",
            "subcategory":"Automobile Sales",
            "type":"Retail Goods"
        }
    ],
    "sg:phone":"+1 866 650 5706",
    "sg:postcode":"90503",
    "sg:province":"CA",
    "sg:tags":[
        "car"
    ],
    "sg:website":"www.pacificaudi.com",
    "wof:name":"Pacific Audi",
    "wof:placetype":"venue"
},
  "geometry": {"coordinates":[-118.35316,33.843574],"type":"Point"}
}