{
  "type": "Feature",
  "properties": {
    "iso:country":"US",
    "sg:address":"9353 Greenback Ln",
    "sg:city":"Orangevale",
    "sg:classifiers":[
        {
            "category":"Bars & Pubs",
            "type":"Food & Drink"
        }
    ],
    "sg:phone":"+1 916 988 4763",
    "sg:postcode":"95662",
    "sg:province":"CA",
    "sg:tags":[
        "club",
        "night"
    ],
    "wof:name":"Black Stallion",
    "wof:placetype":"venue"
},
  "geometry": {"coordinates":[-121.204226,38.678234],"type":"Point"}
}