{
  "type": "Feature",
  "properties": {
    "addr:full":"5031 Jackson St. North Highlands CA 95660",
    "addr:housenumber":"5031",
    "addr:postcode":"95660",
    "addr:street":"Jackson St.",
    "iso:country":"US",
    "sg:address":"5031 Jackson St.",
    "sg:city":"North Highlands",
    "sg:classifiers":[
        {
            "category":"Education",
            "subcategory":"Preschool",
            "type":"Public Place"
        }
    ],
    "sg:phone":"+1 916 332 1227",
    "sg:postcode":"95660",
    "sg:province":"CA",
    "sg:website":"www.relevantyellow.com/Preschool...",
    "wof:name":"Learning Garden Preschool & Infant Care",
    "wof:placetype":"venue"
},
  "geometry": {"coordinates":[-121.374357,38.6585],"type":"Point"}
}