{
  "type": "Feature",
  "properties": {
    "addr:full":"7203 Arlington Ave Riverside CA 92503",
    "addr:housenumber":"7203",
    "addr:postcode":"92503",
    "addr:street":"Arlington Ave",
    "iso:country":"US",
    "sg:address":"7203 Arlington Ave",
    "sg:city":"Riverside",
    "sg:classifiers":[
        {
            "category":"Wholesale",
            "subcategory":"Groceries",
            "type":"Manufacturing & Wholesale Goods"
        }
    ],
    "sg:phone":"+1 951 343 8822",
    "sg:postcode":"92503",
    "sg:province":"CA",
    "sg:tags":[
        "food",
        "product"
    ],
    "wof:name":"Riverside County Foster",
    "wof:placetype":"venue"
},
  "geometry": {"coordinates":[-117.45270600000001,33.945874],"type":"Point"}
}