{
  "type": "Feature",
  "properties": {
    "iso:country":"US",
    "sg:address":"2605 E Cesar E Chavez Avenue",
    "sg:city":"Los Angeles",
    "sg:classifiers":[
        {
            "category":"Restaurant",
            "type":"Food & Drink"
        }
    ],
    "sg:phone":"+1 323 261 9569",
    "sg:postcode":"90033",
    "sg:province":"CA",
    "wof:name":"Restaurant Bahia Ensenada",
    "wof:placetype":"venue"
},
  "geometry": {"coordinates":[-118.204561,34.045504],"type":"Point"}
}