{
  "type": "Feature",
  "properties": {
    "iso:country":"US",
    "sg:address":"1950 W Adams Blvd",
    "sg:city":"Los Angeles",
    "sg:classifiers":[
        {
            "category":"Home & Garden",
            "subcategory":"Carpets & Floor Coverings",
            "type":"Retail Goods"
        }
    ],
    "sg:phone":"+1 323 766 0010",
    "sg:postcode":"90018",
    "sg:province":"CA",
    "sg:tags":[
        "material"
    ],
    "wof:name":"Rivera's Floor Covering Supply",
    "wof:placetype":"venue"
},
  "geometry": {"coordinates":[-118.306972,34.032627],"type":"Point"}
}