{
  "type": "Feature",
  "properties": {
    "addr:full":"8675 Washington Blvd Culver City CA 90232",
    "addr:housenumber":"8675",
    "addr:postcode":"90232",
    "addr:street":"Washington Blvd",
    "iso:country":"US",
    "sg:address":"8675 Washington Blvd",
    "sg:city":"Culver City",
    "sg:classifiers":[
        {
            "category":"Home & Garden",
            "subcategory":"Carpets & Floor Coverings",
            "type":"Retail Goods"
        }
    ],
    "sg:phone":"+1 310 558 3155",
    "sg:postcode":"90232",
    "sg:province":"CA",
    "sg:tags":[
        "mattress"
    ],
    "sg:website":"www.hbeds.com",
    "wof:name":"H?stens Beds at Helms Bakery",
    "wof:placetype":"venue"
},
  "geometry": {"coordinates":[-118.38332800000001,34.029964],"type":"Point"}
}