{
  "type": "Feature",
  "properties": {
    "addr:full":"10675 Sorrento Valley Rd San Diego CA 92121",
    "addr:housenumber":"10675",
    "addr:postcode":"92121",
    "addr:street":"Sorrento Valley Rd",
    "iso:country":"US",
    "sg:address":"10675 Sorrento Valley Rd",
    "sg:city":"San Diego",
    "sg:classifiers":[
        {
            "category":"Utilities",
            "subcategory":"Telephone",
            "type":"Services"
        },
        {
            "category":"Wholesale",
            "subcategory":"Electrical",
            "type":"Manufacturing & Wholesale Goods"
        }
    ],
    "sg:phone":"+1 858 457 1800",
    "sg:postcode":"92121",
    "sg:province":"CA",
    "sg:tags":[
        "wireless",
        "communications",
        "telecommunication"
    ],
    "sg:website":"www.prominentcomm.com",
    "wof:name":"Prominent Communications Inc",
    "wof:placetype":"venue"
},
  "geometry": {"coordinates":[-117.217626,32.895215],"type":"Point"}
}