{
  "type": "Feature",
  "properties": {
    "addr:full":"41369 Rd 128 Orosi CA 93647",
    "addr:postcode":"41369;93647",
    "addr:street":"Rd 128",
    "iso:country":"US",
    "sg:address":"41369 Rd 128",
    "sg:city":"Orosi",
    "sg:classifiers":[
        {
            "category":"Restaurant",
            "type":"Food & Drink"
        }
    ],
    "sg:phone":"+1 559 528 6710",
    "sg:postcode":"93647",
    "sg:province":"CA",
    "sg:tags":[
        "pizza"
    ],
    "wof:name":"Orosi Pizza House",
    "wof:placetype":"venue"
},
  "geometry": {"coordinates":[-119.28693699999999,36.541043],"type":"Point"}
}