{
  "type": "Feature",
  "properties": {
    "iso:country":"US",
    "sg:address":"1741 N Kingsley Dr",
    "sg:city":"Los Angeles",
    "sg:classifiers":[
        {
            "category":"Real Estate",
            "subcategory":"Real Estate Operator",
            "type":"Services"
        }
    ],
    "sg:phone":"+1 323 463 3721",
    "sg:postcode":"90027",
    "sg:province":"CA",
    "sg:tags":[
        "apartment"
    ],
    "wof:name":"Hollywood Kingsley Apartments",
    "wof:placetype":"venue"
},
  "geometry": {"coordinates":[-118.303585,34.104658],"type":"Point"}
}