{
  "type": "Feature",
  "properties": {
    "iso:country":"US",
    "sg:address":"33315 US Hwy 215",
    "sg:city":"Menifee",
    "sg:classifiers":[
        {
            "category":"Personal",
            "subcategory":"Barber",
            "type":"Services"
        }
    ],
    "sg:phone":"+1 951 672 1964",
    "sg:postcode":"92584",
    "sg:province":"CA",
    "wof:name":"Bonnie's Hair Stop",
    "wof:placetype":"venue"
},
  "geometry": {"coordinates":[-117.172016,33.636823],"type":"Point"}
}