{
  "type": "Feature",
  "properties": {
    "addr:full":"409 Vernon Way El Cajon CA 92020",
    "addr:housenumber":"409",
    "addr:postcode":"92020",
    "addr:street":"Vernon Way",
    "iso:country":"US",
    "sg:address":"409 Vernon Way",
    "sg:city":"El Cajon",
    "sg:classifiers":[
        {
            "category":"Professional",
            "subcategory":"Advertising",
            "type":"Services"
        }
    ],
    "sg:phone":"+1 619 593 9121",
    "sg:postcode":"92020",
    "sg:province":"CA",
    "sg:tags":[
        "delivery",
        "list",
        "mailing",
        "courier"
    ],
    "sg:website":"www.mailmgmtgroup.com",
    "wof:name":"Mail Management Group",
    "wof:placetype":"venue"
},
  "geometry": {"coordinates":[-116.96700300000001,32.812199],"type":"Point"}
}