{
  "type": "Feature",
  "properties": {
    "addr:full":"115 N Exchange Pl San Dimas CA 91773",
    "addr:housenumber":"115",
    "addr:postcode":"91773",
    "addr:street":"N Exchange Pl",
    "iso:country":"US",
    "sg:address":"115 N Exchange Pl",
    "sg:city":"San Dimas",
    "sg:classifiers":[
        {
            "category":"Utilities",
            "subcategory":"Water",
            "type":"Services"
        }
    ],
    "sg:phone":"+1 909 599 1289",
    "sg:postcode":"91773",
    "sg:province":"CA",
    "sg:tags":[
        "company",
        "sewage"
    ],
    "wof:name":"Southern California Water Co",
    "wof:placetype":"venue"
},
  "geometry": {"coordinates":[-117.808483,34.106993],"type":"Point"}
}