{
  "type": "Feature",
  "properties": {
    "iso:country":"US",
    "sg:address":"1268 E Ohio Ave",
    "sg:city":"Escondido",
    "sg:classifiers":[
        {
            "category":"Real Estate",
            "subcategory":"Real Estate Operator",
            "type":"Services"
        }
    ],
    "sg:phone":"+1 760 741 6039",
    "sg:postcode":"92027",
    "sg:province":"CA",
    "sg:tags":[
        "apartment"
    ],
    "wof:name":"Casa Victoria Apartments",
    "wof:placetype":"venue"
},
  "geometry": {"coordinates":[-117.065032,33.128526],"type":"Point"}
}