{
  "type": "Feature",
  "properties": {
    "addr:full":"468 Gold Ridge Rd Sebastopol CA 95472",
    "addr:housenumber":"468",
    "addr:postcode":"95472",
    "addr:street":"Gold Ridge Rd",
    "iso:country":"US",
    "sg:address":"468 Gold Ridge Rd",
    "sg:city":"Sebastopol",
    "sg:classifiers":[
        {
            "category":"Professional",
            "type":"Services"
        }
    ],
    "sg:phone":"+1 707 824 1876",
    "sg:postcode":"95472",
    "sg:province":"CA",
    "wof:name":"Fonecash",
    "wof:placetype":"venue"
},
  "geometry": {"coordinates":[-122.867053,38.391026],"type":"Point"}
}