{
  "type": "Feature",
  "properties": {
    "addr:full":"17057 Sunburst St Northridge CA 91325",
    "addr:housenumber":"17057",
    "addr:postcode":"91325",
    "addr:street":"Sunburst St",
    "iso:country":"US",
    "sg:address":"17057 Sunburst St",
    "sg:city":"Northridge",
    "sg:classifiers":[
        {
            "category":"Wholesale",
            "subcategory":"Drugs",
            "type":"Manufacturing & Wholesale Goods"
        }
    ],
    "sg:phone":"+1 818 709 6530",
    "sg:postcode":"91325",
    "sg:province":"CA",
    "wof:name":"Mary Caryls",
    "wof:placetype":"venue"
},
  "geometry": {"coordinates":[-118.506913,34.234491],"type":"Point"}
}