{
  "type": "Feature",
  "properties": {
    "iso:country":"US",
    "sg:address":"2280 Earl St",
    "sg:city":"Los Angeles",
    "sg:classifiers":[
        {
            "category":"Communications",
            "subcategory":"Film & Video Production",
            "type":"Services"
        }
    ],
    "sg:phone":"+1 323 644 7589",
    "sg:postcode":"90039",
    "sg:province":"CA",
    "sg:tags":[
        "motion",
        "picture"
    ],
    "wof:name":"In Sync",
    "wof:placetype":"venue"
},
  "geometry": {"coordinates":[-118.25537,34.095608],"type":"Point"}
}