{
  "type": "Feature",
  "properties": {
    "iso:country":"US",
    "sg:address":"3095 Timberline Dr",
    "sg:city":"Corona",
    "sg:classifiers":[
        {
            "category":"Shopping",
            "subcategory":"Used Merchandise",
            "type":"Retail Goods"
        }
    ],
    "sg:phone":"+1 951 280 0026",
    "sg:postcode":"92882",
    "sg:province":"CA",
    "sg:tags":[
        "antique"
    ],
    "wof:name":"Sandor's Galleria",
    "wof:placetype":"venue"
},
  "geometry": {"coordinates":[-117.625137,33.874421],"type":"Point"}
}