{
  "type": "Feature",
  "properties": {
    "iso:country":"US",
    "sg:address":"30333 Morning View Dr",
    "sg:city":"Malibu",
    "sg:classifiers":[
        {
            "category":"Professional",
            "type":"Services"
        }
    ],
    "sg:phone":"+1 310 457 9901",
    "sg:postcode":"90265",
    "sg:province":"CA",
    "wof:name":"Albert Stern",
    "wof:placetype":"venue"
},
  "geometry": {"coordinates":[-118.83217500000001,34.026581],"type":"Point"}
}