{
  "type": "Feature",
  "properties": {
    "iso:country":"US",
    "sg:address":"1805 N Lafayette Ave",
    "sg:city":"Fresno",
    "sg:classifiers":[
        {
            "category":"Professional",
            "subcategory":"Management & Consulting",
            "type":"Services"
        }
    ],
    "sg:phone":"+1 559 891 8104",
    "sg:postcode":"93705",
    "sg:province":"CA",
    "sg:tags":[
        "consultant",
        "educational"
    ],
    "wof:name":"Southwest Technical College",
    "wof:placetype":"venue"
},
  "geometry": {"coordinates":[-119.83775199999999,36.764662],"type":"Point"}
}