{
  "type": "Feature",
  "properties": {
    "addr:full":"1710 Scott St San Francisco CA 94115",
    "addr:housenumber":"1710",
    "addr:postcode":"94115",
    "addr:street":"Scott St",
    "iso:country":"US",
    "sg:address":"1710 Scott St",
    "sg:city":"San Francisco",
    "sg:classifiers":[
        {
            "category":"Building & Trades",
            "subcategory":"Construction",
            "type":"Services"
        }
    ],
    "sg:phone":"+1 415 449 3700",
    "sg:postcode":"94115",
    "sg:province":"CA",
    "sg:tags":[
        "home",
        "builder"
    ],
    "wof:name":"Seniors At Home",
    "wof:placetype":"venue"
},
  "geometry": {"coordinates":[-122.438305,37.786308],"type":"Point"}
}