{
  "type": "Feature",
  "properties": {
    "addr:full":"2311 Cotton Ct Santa Rosa CA 95401",
    "addr:housenumber":"2311",
    "addr:postcode":"95401",
    "addr:street":"Cotton Ct",
    "iso:country":"US",
    "sg:address":"2311 Cotton Ct",
    "sg:city":"Santa Rosa",
    "sg:classifiers":[
        {
            "category":"Banks & Credit Unions",
            "subcategory":"Bank",
            "type":"Services"
        }
    ],
    "sg:phone":"+1 707 544 1997",
    "sg:postcode":"95401",
    "sg:province":"CA",
    "sg:tags":[
        "broker",
        "mortgage"
    ],
    "wof:name":"CC & S Realty",
    "wof:placetype":"venue"
},
  "geometry": {"coordinates":[-122.764228,38.445922],"type":"Point"}
}