{
  "type": "Feature",
  "properties": {
    "iso:country":"US",
    "sg:address":"7241 Garden Grove Blvd. Suite L",
    "sg:city":"Garden Grove",
    "sg:classifiers":[
        {
            "category":"Shopping",
            "subcategory":"Stationery & Office Supplies",
            "type":"Retail Goods"
        }
    ],
    "sg:phone":"+1 714 893 7032",
    "sg:postcode":"92841",
    "sg:province":"CA",
    "sg:tags":[
        "equipment"
    ],
    "sg:website":"www.allbarcodesystems.com",
    "wof:name":"All Barcode Systems, Inc.",
    "wof:placetype":"venue"
},
  "geometry": {"coordinates":[-118.004122,33.773785],"type":"Point"}
}