{
  "type": "Feature",
  "properties": {
    "addr:full":"10422 Trask Ave Garden Grove CA 92843",
    "addr:housenumber":"10422",
    "addr:postcode":"92843",
    "addr:street":"Trask Ave",
    "iso:country":"US",
    "sg:address":"10422 Trask Ave",
    "sg:city":"Garden Grove",
    "sg:classifiers":[
        {
            "category":"Travel",
            "subcategory":"Travel Agent",
            "type":"Entertainment"
        }
    ],
    "sg:phone":"+1 714 636 8829",
    "sg:postcode":"92843",
    "sg:province":"CA",
    "sg:tags":[
        "agency"
    ],
    "wof:name":"A B C Travel & Express Service",
    "wof:placetype":"venue"
},
  "geometry": {"coordinates":[-117.94660399999999,33.766767],"type":"Point"}
}