{
  "type": "Feature",
  "properties": {
    "addr:full":"1000 Maple Ave Los Angeles CA 90015",
    "addr:housenumber":"1000",
    "addr:postcode":"90015",
    "addr:street":"Maple Ave",
    "iso:country":"US",
    "sg:address":"1000 Maple Ave",
    "sg:city":"Los Angeles",
    "sg:classifiers":[
        {
            "category":"Shopping",
            "subcategory":"Clothing, Apparel, & Fashions",
            "type":"Retail Goods"
        }
    ],
    "sg:phone":"+1 213 747 1245",
    "sg:postcode":"90015",
    "sg:province":"CA",
    "wof:name":"Liz Fashion",
    "wof:placetype":"venue"
},
  "geometry": {"coordinates":[-118.255127,34.03714],"type":"Point"}
}