{
  "type": "Feature",
  "properties": {
    "addr:full":"290 W Brokaw Rd Santa Clara CA 95050",
    "addr:housenumber":"290",
    "addr:postcode":"95050",
    "addr:street":"W Brokaw Rd",
    "iso:country":"US",
    "sg:address":"290 W Brokaw Rd",
    "sg:city":"Santa Clara",
    "sg:classifiers":[
        {
            "category":"Shopping",
            "subcategory":"Computers & Home Electronics",
            "type":"Retail Goods"
        }
    ],
    "sg:phone":"+1 408 988 1191",
    "sg:postcode":"95050",
    "sg:province":"CA",
    "sg:tags":[
        "software"
    ],
    "wof:name":"Bay Area Duplication",
    "wof:placetype":"venue"
},
  "geometry": {"coordinates":[-121.933978,37.357604],"type":"Point"}
}