{
  "type": "Feature",
  "properties": {
    "iso:country":"US",
    "sg:address":"422 N 2nd Ave",
    "sg:city":"Upland",
    "sg:classifiers":[
        {
            "category":"Real Estate",
            "subcategory":"Real Estate Agent",
            "type":"Services"
        }
    ],
    "sg:phone":"+1 909 608 0381",
    "sg:postcode":"91786",
    "sg:province":"CA",
    "sg:website":"www.providenthomeloans.com",
    "wof:name":"Provident Realty",
    "wof:placetype":"venue"
},
  "geometry": {"coordinates":[-117.64836,34.099452],"type":"Point"}
}