{
  "type": "Feature",
  "properties": {
    "addr:full":"660 E Los Angeles Ave Simi Valley CA 93065",
    "addr:housenumber":"660",
    "addr:postcode":"93065",
    "addr:street":"E Los Angeles Ave",
    "iso:country":"US",
    "sg:address":"660 E Los Angeles Ave",
    "sg:city":"Simi Valley",
    "sg:classifiers":[
        {
            "category":"Restaurant",
            "type":"Food & Drink"
        }
    ],
    "sg:menulink":"http://www.allmenus.com/ca/simi-valley/240060-panda-express/menu/",
    "sg:phone":"+1 805 583 5713",
    "sg:postcode":"93065",
    "sg:province":"CA",
    "sg:tags":[
        "asian",
        "chinese"
    ],
    "wof:name":"Panda Express",
    "wof:placetype":"venue"
},
  "geometry": {"coordinates":[-118.78467000000001,34.270786],"type":"Point"}
}