{
  "type": "Feature",
  "properties": {
    "addr:full":"1509 Mateo St Los Angeles CA 90021",
    "addr:housenumber":"1509",
    "addr:postcode":"90021",
    "addr:street":"Mateo St",
    "iso:country":"US",
    "sg:address":"1509 Mateo St",
    "sg:city":"Los Angeles",
    "sg:classifiers":[
        {
            "category":"Professional",
            "subcategory":"Business Services",
            "type":"Services"
        }
    ],
    "sg:phone":"+1 213 744 1670",
    "sg:postcode":"90021",
    "sg:province":"CA",
    "sg:tags":[
        "labeling"
    ],
    "wof:name":"Apparel Star Co",
    "wof:placetype":"venue"
},
  "geometry": {"coordinates":[-118.23228,34.027213],"type":"Point"}
}