{
  "type": "Feature",
  "properties": {
    "iso:country":"US",
    "sg:address":"121 buckingham Dr # 54",
    "sg:city":"Santa Clara",
    "sg:classifiers":[
        {
            "category":"Taxi",
            "type":"Transportation"
        }
    ],
    "sg:phone":"+1 408 605 7995",
    "sg:postcode":"95051",
    "sg:province":"CA",
    "sg:website":"www.yellowcab4u.com",
    "wof:name":"Taxi Santa Clara Yellow Cab",
    "wof:placetype":"venue"
},
  "geometry": {"coordinates":[-121.971481,37.326049],"type":"Point"}
}