{
  "type": "Feature",
  "properties": {
    "iso:country":"US",
    "sg:address":"11815 Del AMO Blvd",
    "sg:city":"Cerritos",
    "sg:classifiers":[
        {
            "category":"Personal",
            "subcategory":"Barber",
            "type":"Services"
        }
    ],
    "sg:phone":"+1 562 865 9734",
    "sg:postcode":"90703",
    "sg:province":"CA",
    "wof:name":"Hair Craze",
    "wof:placetype":"venue"
},
  "geometry": {"coordinates":[-118.082001,33.846199],"type":"Point"}
}