{
  "type": "Feature",
  "properties": {
    "addr:full":"3300 Broadway Ste 3511 Eureka CA 95501",
    "addr:housenumber":"3300",
    "addr:postcode":"95501",
    "addr:street":"Broadway Ste 3511",
    "iso:country":"US",
    "sg:address":"3300 Broadway Ste 3511",
    "sg:city":"Eureka",
    "sg:classifiers":[
        {
            "category":"Personal",
            "subcategory":"Shoe Repair & Shine",
            "type":"Services"
        }
    ],
    "sg:phone":"+1 707 445 9462",
    "sg:postcode":"95501",
    "sg:province":"CA",
    "sg:tags":[
        "sunglass"
    ],
    "sg:website":"http://www.sunglasshut.com",
    "wof:name":"Sunglass Hut",
    "wof:placetype":"venue"
},
  "geometry": {"coordinates":[-124.187927,40.778759],"type":"Point"}
}