{
  "type": "Feature",
  "properties": {
    "iso:country":"US",
    "sg:address":"7051 Monterey St",
    "sg:city":"Gilroy",
    "sg:classifiers":[
        {
            "category":"Food & Beverages",
            "subcategory":"Liquor & Beverages",
            "type":"Retail Goods"
        }
    ],
    "sg:phone":"+1 408 846 8830",
    "sg:postcode":"95020",
    "sg:province":"CA",
    "wof:name":"Cheer Liquor Market",
    "wof:placetype":"venue"
},
  "geometry": {"coordinates":[-121.56598099999999,37.000518],"type":"Point"}
}