{
  "type": "Feature",
  "properties": {
    "addr:full":"1117 Irving St San Francisco CA 94122",
    "addr:housenumber":"1117",
    "addr:postcode":"94122",
    "addr:street":"Irving St",
    "iso:country":"US",
    "sg:address":"1117 Irving St",
    "sg:city":"San Francisco",
    "sg:classifiers":[
        {
            "category":"Personal",
            "subcategory":"Massage",
            "type":"Services"
        }
    ],
    "sg:phone":"+1 415 665 0100",
    "sg:postcode":"94122",
    "sg:province":"CA",
    "sg:website":"www.relaxfeetsf.com",
    "wof:name":"Relax Feet Massage",
    "wof:placetype":"venue"
},
  "geometry": {"coordinates":[-122.469824,37.763874],"type":"Point"}
}