{
  "type": "Feature",
  "properties": {
    "addr:full":"3045 Rosecrans St San Diego CA 92110",
    "addr:housenumber":"3045",
    "addr:postcode":"92110",
    "addr:street":"Rosecrans St",
    "iso:country":"US",
    "sg:address":"3045 Rosecrans St",
    "sg:city":"San Diego",
    "sg:classifiers":[
        {
            "category":"Personal",
            "subcategory":"Beauty Salon",
            "type":"Services"
        }
    ],
    "sg:phone":"+1 619 226 9299",
    "sg:postcode":"92110",
    "sg:province":"CA",
    "sg:tags":[
        "spa",
        "day"
    ],
    "wof:name":"A Piece Of Brasil",
    "wof:placetype":"venue"
},
  "geometry": {"coordinates":[-117.211006,32.745779],"type":"Point"}
}