{
  "type": "Feature",
  "properties": {
    "iso:country":"US",
    "sg:address":"Powell & Market.",
    "sg:city":"San Francisco",
    "sg:classifiers":[
        {
            "category":"Local Transit",
            "type":"Transportation"
        }
    ],
    "sg:postcode":"94101",
    "sg:province":"CA",
    "sg:tags":[
        "public"
    ],
    "sg:website":"www.sfcablecar.com/routes.html",
    "wof:name":"Cable Car - Powell/Hyde Line",
    "wof:placetype":"venue"
},
  "geometry": {"coordinates":[-122.407785,37.784635],"type":"Point"}
}