{
  "type": "Feature",
  "properties": {
    "addr:full":"1236 W Brooks St Ontario CA 91762",
    "addr:housenumber":"1236",
    "addr:postcode":"91762",
    "addr:street":"W Brooks St",
    "iso:country":"US",
    "sg:address":"1236 W Brooks St",
    "sg:city":"Ontario",
    "sg:classifiers":[
        {
            "category":"Retail",
            "subcategory":"Repair Shop",
            "type":"Services"
        }
    ],
    "sg:phone":"+1 909 988 4054",
    "sg:postcode":"91762",
    "sg:province":"CA",
    "sg:tags":[
        "equipment",
        "electric"
    ],
    "wof:name":"Integrated Quality Svc",
    "wof:placetype":"venue"
},
  "geometry": {"coordinates":[-117.67395999999999,34.062031],"type":"Point"}
}