{
  "type": "Feature",
  "properties": {
    "addr:full":"25405 Hancock Ave Murrieta CA 92562",
    "addr:housenumber":"25405",
    "addr:postcode":"92562",
    "addr:street":"Hancock Ave",
    "iso:country":"US",
    "sg:address":"25405 Hancock Ave",
    "sg:city":"Murrieta",
    "sg:classifiers":[
        {
            "category":"Shopping",
            "subcategory":"Pharmacy",
            "type":"Retail Goods"
        }
    ],
    "sg:phone":"+1 951 304 2038",
    "sg:postcode":"92562",
    "sg:province":"CA",
    "wof:name":"Pharma Care",
    "wof:placetype":"venue"
},
  "geometry": {"coordinates":[-117.185197,33.559269],"type":"Point"}
}