{
  "type": "Feature",
  "properties": {
    "iso:country":"US",
    "sg:address":"2760 Jane St",
    "sg:city":"Riverside",
    "sg:classifiers":[
        {
            "category":"Education",
            "subcategory":"School",
            "type":"Public Place"
        }
    ],
    "sg:phone":"+1 951 788 7305",
    "sg:postcode":"92506",
    "sg:province":"CA",
    "wof:name":"Washington Elementary School",
    "wof:placetype":"venue"
},
  "geometry": {"coordinates":[-117.38212900000001,33.934443],"type":"Point"}
}