{
  "type": "Feature",
  "properties": {
    "addr:full":"2720 Santa Rosa Ave Santa Rosa CA 95407",
    "addr:housenumber":"2720",
    "addr:postcode":"95407",
    "addr:street":"Santa Rosa Ave",
    "iso:country":"US",
    "sg:address":"2720 Santa Rosa Ave",
    "sg:city":"Santa Rosa",
    "sg:classifiers":[
        {
            "category":"Shopping",
            "subcategory":"Stationery & Office Supplies",
            "type":"Retail Goods"
        }
    ],
    "sg:phone":"+1 707 523 7700",
    "sg:postcode":"95407",
    "sg:province":"CA",
    "sg:website":"www.officemax.com",
    "wof:name":"Office Max",
    "wof:placetype":"venue"
},
  "geometry": {"coordinates":[-122.71340499999999,38.409235],"type":"Point"}
}