{
  "type": "Feature",
  "properties": {
    "iso:country":"US",
    "sg:address":"5030 J St Ste 301",
    "sg:city":"Sacramento",
    "sg:classifiers":[
        {
            "category":"Health Services",
            "subcategory":"Doctor",
            "type":"Services"
        }
    ],
    "sg:phone":"+1 916 451 8430",
    "sg:postcode":"95819",
    "sg:province":"CA",
    "wof:name":"McCrimons Daniel E MD",
    "wof:placetype":"venue"
},
  "geometry": {"coordinates":[-121.442081,38.566358],"type":"Point"}
}