{
  "type": "Feature",
  "properties": {
    "iso:country":"US",
    "sg:address":"601 S Glenoaks Blvd Ste 100",
    "sg:city":"Burbank",
    "sg:classifiers":[
        {
            "category":"Banks & Credit Unions",
            "subcategory":"Bank",
            "type":"Services"
        }
    ],
    "sg:phone":"+1 818 953 4300",
    "sg:postcode":"91502",
    "sg:province":"CA",
    "wof:name":"Union Bank of California",
    "wof:placetype":"venue"
},
  "geometry": {"coordinates":[-118.30149,34.179471],"type":"Point"}
}