{
  "type": "Feature",
  "properties": {
    "addr:full":"480 McCreery Avenue San Jose CA 95116",
    "addr:housenumber":"480",
    "addr:postcode":"95116",
    "addr:street":"Mccreery Avenue",
    "iso:country":"US",
    "sg:address":"480 McCreery Avenue",
    "sg:city":"San Jose",
    "sg:classifiers":[
        {
            "category":"Place Of Worship",
            "subcategory":"Church",
            "type":"Public Place"
        }
    ],
    "sg:phone":"+1 408 929 4470",
    "sg:postcode":"95116",
    "sg:province":"CA",
    "wof:name":"First Apostolic Church",
    "wof:placetype":"venue"
},
  "geometry": {"coordinates":[-121.845651,37.347009],"type":"Point"}
}