{
  "type": "Feature",
  "properties": {
    "iso:country":"US",
    "sg:address":"2755 Jefferson St",
    "sg:city":"Carlsbad",
    "sg:classifiers":[
        {
            "category":"Professional",
            "subcategory":"Lawyer & Legal Services",
            "type":"Services"
        }
    ],
    "sg:phone":"+1 760 434 3330",
    "sg:postcode":"92008",
    "sg:province":"CA",
    "sg:tags":[
        "divorce",
        "law",
        "family"
    ],
    "wof:name":"Burke Daniel V",
    "wof:placetype":"venue"
},
  "geometry": {"coordinates":[-117.348,33.164001],"type":"Point"}
}