{
  "type": "Feature",
  "properties": {
    "addr:full":"2665 Main St Santa Monica CA 90405",
    "addr:housenumber":"2665",
    "addr:postcode":"90405",
    "addr:street":"Main St",
    "iso:country":"US",
    "sg:address":"2665 Main St",
    "sg:city":"Santa Monica",
    "sg:classifiers":[
        {
            "category":"Social Services",
            "subcategory":"Child Care",
            "type":"Services"
        }
    ],
    "sg:phone":"+1 310 450 4512",
    "sg:postcode":"90405",
    "sg:province":"CA",
    "wof:name":"Monkie",
    "wof:placetype":"venue"
},
  "geometry": {"coordinates":[-118.483345,34.001903],"type":"Point"}
}