{
  "type": "Feature",
  "properties": {
    "iso:country":"US",
    "sg:address":"100 N Winchester Blvd",
    "sg:city":"Santa Clara",
    "sg:classifiers":[
        {
            "category":"Social Services",
            "type":"Services"
        }
    ],
    "sg:phone":"+1 408 246 8380",
    "sg:postcode":"95050",
    "sg:province":"CA",
    "sg:tags":[
        "counseling"
    ],
    "wof:name":"Counseling Services",
    "wof:placetype":"venue"
},
  "geometry": {"coordinates":[-121.9502,37.327363],"type":"Point"}
}