{
  "type": "Feature",
  "properties": {
    "iso:country":"US",
    "sg:address":"7899 N Pershing Ave",
    "sg:city":"Stockton",
    "sg:classifiers":[
        {
            "category":"Personal",
            "type":"Services"
        }
    ],
    "sg:phone":"+1 209 478 7008",
    "sg:postcode":"95207",
    "sg:province":"CA",
    "sg:tags":[
        "therapist",
        "massage"
    ],
    "wof:name":"Debbie Sears",
    "wof:placetype":"venue"
},
  "geometry": {"coordinates":[-121.330006,38.020232],"type":"Point"}
}