{
  "type": "Feature",
  "properties": {
    "iso:country":"US",
    "sg:address":"7965 W 4th St",
    "sg:city":"Los Angeles",
    "sg:classifiers":[
        {
            "category":"Building & Trades",
            "subcategory":"Electrical",
            "type":"Services"
        }
    ],
    "sg:phone":"+1 323 651 1183",
    "sg:postcode":"90048",
    "sg:province":"CA",
    "sg:tags":[
        "electrical",
        "contractor"
    ],
    "wof:name":"Oaks Electric",
    "wof:placetype":"venue"
},
  "geometry": {"coordinates":[-118.363665,34.07022],"type":"Point"}
}