{
  "type": "Feature",
  "properties": {
    "iso:country":"US",
    "sg:address":"3950 Via Real",
    "sg:city":"Carpinteria",
    "sg:classifiers":[
        {
            "category":"Shopping",
            "subcategory":"Florist",
            "type":"Retail Goods"
        }
    ],
    "sg:phone":"+1 805 684 3012",
    "sg:postcode":"93013",
    "sg:province":"CA",
    "wof:name":"Flower Basket",
    "wof:placetype":"venue"
},
  "geometry": {"coordinates":[-119.542626,34.406177],"type":"Point"}
}