{
  "type": "Feature",
  "properties": {
    "iso:country":"US",
    "sg:address":"1783 E Thousand Oaks Blvd",
    "sg:city":"Thousand Oaks",
    "sg:classifiers":[
        {
            "category":"Personal",
            "subcategory":"Beauty Salon",
            "type":"Services"
        }
    ],
    "sg:phone":"+1 805 494 3936",
    "sg:postcode":"91362",
    "sg:province":"CA",
    "wof:name":"Joshua's Beauty Salon",
    "wof:placetype":"venue"
},
  "geometry": {"coordinates":[-118.849643,34.17665],"type":"Point"}
}