{
  "type": "Feature",
  "properties": {
    "iso:country":"US",
    "sg:address":"177 W Colorado Blvd",
    "sg:city":"Pasadena",
    "sg:classifiers":[
        {
            "category":"Utilities",
            "subcategory":"Telephone",
            "type":"Services"
        }
    ],
    "sg:phone":"+1 626 578 4111",
    "sg:postcode":"91105",
    "sg:province":"CA",
    "sg:tags":[
        "communications",
        "radiotelephone",
        "communication"
    ],
    "wof:name":"Pacific Bell",
    "wof:placetype":"venue"
},
  "geometry": {"coordinates":[-118.15259399999999,34.145834],"type":"Point"}
}