{
  "type": "Feature",
  "properties": {
    "addr:full":"3748 13th Ave Oakland CA 94610",
    "addr:housenumber":"3748",
    "addr:postcode":"94610",
    "addr:street":"13Th Ave",
    "iso:country":"US",
    "sg:address":"3748 13th Ave",
    "sg:city":"Oakland",
    "sg:classifiers":[
        {
            "category":"Education",
            "subcategory":"School",
            "type":"Public Place"
        }
    ],
    "sg:phone":"+1 510 879 2100",
    "sg:postcode":"94610",
    "sg:province":"CA",
    "sg:tags":[
        "high",
        "middle",
        "elementary"
    ],
    "wof:name":"Oakland Public Schools",
    "wof:placetype":"venue"
},
  "geometry": {"coordinates":[-122.229347,37.803806],"type":"Point"}
}