{
  "type": "Feature",
  "properties": {
    "addr:full":"1945 E 17th St Santa Ana CA 92705",
    "addr:housenumber":"1945",
    "addr:postcode":"92705",
    "addr:street":"E 17Th St",
    "iso:country":"US",
    "sg:address":"1945 E 17th St",
    "sg:city":"Santa Ana",
    "sg:classifiers":[
        {
            "category":"Restaurant",
            "type":"Food & Drink"
        }
    ],
    "sg:phone":"+1 714 547 7771",
    "sg:postcode":"92705",
    "sg:province":"CA",
    "sg:tags":[
        "traditional",
        "american"
    ],
    "wof:name":"Camille's Sidewalk Cafe",
    "wof:placetype":"venue"
},
  "geometry": {"coordinates":[-117.83731400000001,33.759977],"type":"Point"}
}