{
  "type": "Feature",
  "properties": {
    "iso:country":"US",
    "sg:address":"1812 Woolsey St",
    "sg:city":"Berkeley",
    "sg:classifiers":[
        {
            "category":"Real Estate",
            "subcategory":"Real Estate Services",
            "type":"Services"
        }
    ],
    "sg:phone":"+1 510 204 9945",
    "sg:postcode":"94703",
    "sg:province":"CA",
    "sg:tags":[
        "rental"
    ],
    "wof:name":"Valarie Jo Vaughan",
    "wof:placetype":"venue"
},
  "geometry": {"coordinates":[-122.27211800000001,37.851423],"type":"Point"}
}