{
  "type": "Feature",
  "properties": {
    "iso:country":"US",
    "sg:address":"1520 E Main St",
    "sg:city":"Barstow",
    "sg:classifiers":[
        {
            "category":"Restaurant",
            "type":"Food & Drink"
        }
    ],
    "sg:phone":"+1 760 256 1381",
    "sg:postcode":"92311",
    "sg:province":"CA",
    "sg:tags":[
        "style",
        "mexican",
        "family"
    ],
    "wof:name":"Los Domingos Restaurant",
    "wof:placetype":"venue"
},
  "geometry": {"coordinates":[-117.00300900000001,34.893423],"type":"Point"}
}