{
  "type": "Feature",
  "properties": {
    "addr:full":"1153 N 2nd St El Cajon CA 92021",
    "addr:housenumber":"1153",
    "addr:postcode":"92021",
    "addr:street":"N 2Nd St",
    "iso:country":"US",
    "sg:address":"1153 N 2nd St",
    "sg:city":"El Cajon",
    "sg:classifiers":[
        {
            "category":"Personal",
            "subcategory":"Tattoo Parlor",
            "type":"Services"
        }
    ],
    "sg:phone":"+1 619 444 7246",
    "sg:postcode":"92021",
    "sg:province":"CA",
    "sg:tags":[
        "tattooing"
    ],
    "wof:name":"Addictive Pain Tattoo",
    "wof:placetype":"venue"
},
  "geometry": {"coordinates":[-116.93565,32.810557],"type":"Point"}
}