{
  "type": "Feature",
  "properties": {
    "iso:country":"US",
    "sg:address":"1542 Broadway",
    "sg:city":"Oakland",
    "sg:classifiers":[
        {
            "category":"Shopping",
            "subcategory":"Clothing, Apparel, & Fashions",
            "type":"Retail Goods"
        }
    ],
    "sg:phone":"+1 510 271 0020",
    "sg:postcode":"94612",
    "sg:province":"CA",
    "sg:tags":[
        "accessory",
        "clothing",
        "women's"
    ],
    "wof:name":"Clothing Store The",
    "wof:placetype":"venue"
},
  "geometry": {"coordinates":[-122.2702,37.805461],"type":"Point"}
}