{
  "type": "Feature",
  "properties": {
    "addr:full":"2560 Patterson Rd Riverbank CA 95367",
    "addr:housenumber":"2560",
    "addr:postcode":"95367",
    "addr:street":"Patterson Rd",
    "iso:country":"US",
    "sg:address":"2560 Patterson Rd",
    "sg:city":"Riverbank",
    "sg:classifiers":[
        {
            "category":"Real Estate",
            "subcategory":"Developer",
            "type":"Services"
        },
        {
            "category":"Wholesale",
            "subcategory":"Groceries",
            "type":"Manufacturing & Wholesale Goods"
        }
    ],
    "sg:phone":"+1 209 863 9604",
    "sg:postcode":"95367",
    "sg:province":"CA",
    "wof:name":"Dry Creek Beverage",
    "wof:placetype":"venue"
},
  "geometry": {"coordinates":[-120.949761,37.732624],"type":"Point"}
}