{
  "type": "Feature",
  "properties": {
    "iso:country":"US",
    "sg:address":"16501 Stonehaven Ct",
    "sg:city":"La Mirada",
    "sg:classifiers":[
        {
            "category":"Professional",
            "subcategory":"Engineering",
            "type":"Services"
        }
    ],
    "sg:phone":"+1 562 947 6711",
    "sg:postcode":"90638",
    "sg:province":"CA",
    "sg:tags":[
        "engineer"
    ],
    "wof:name":"Kearn Engineering",
    "wof:placetype":"venue"
},
  "geometry": {"coordinates":[-117.979745,33.91007],"type":"Point"}
}