{
  "type": "Feature",
  "properties": {
    "addr:full":"509 Galaxy Way Modesto CA 95356",
    "addr:housenumber":"509",
    "addr:postcode":"ca 95356",
    "addr:street":"Galaxy Way",
    "iso:country":"US",
    "sg:address":"509 Galaxy Way",
    "sg:city":"Modesto",
    "sg:classifiers":[
        {
            "category":"Real Estate",
            "subcategory":"Real Estate Operator",
            "type":"Services"
        }
    ],
    "sg:phone":"+1 209 578 4612",
    "sg:postcode":"95356",
    "sg:province":"CA",
    "sg:tags":[
        "building",
        "nonresidential",
        "general"
    ],
    "wof:name":"North Modesto Industrial Park",
    "wof:placetype":"venue"
},
  "geometry": {"coordinates":[-121.00021,37.707747],"type":"Point"}
}