{
  "type": "Feature",
  "properties": {
    "iso:country":"US",
    "sg:address":"3737 Martin Luther King Jr Blvd",
    "sg:city":"Lynwood",
    "sg:classifiers":[
        {
            "category":"Health Services",
            "subcategory":"Doctor",
            "type":"Services"
        }
    ],
    "sg:phone":"+1 310 637 1971",
    "sg:postcode":"90262",
    "sg:province":"CA",
    "sg:tags":[
        "physician",
        "surgeon"
    ],
    "wof:name":"Flaxie R Fletcher MD",
    "wof:placetype":"venue"
},
  "geometry": {"coordinates":[-118.200632,33.928801],"type":"Point"}
}