{
  "type": "Feature",
  "properties": {
    "iso:country":"US",
    "sg:address":"630 E Main St",
    "sg:city":"Alhambra",
    "sg:classifiers":[
        {
            "category":"Freight",
            "type":"Transportation"
        },
        {
            "category":"Professional",
            "subcategory":"Printing & Photocopies",
            "type":"Services"
        },
        {
            "category":"Professional",
            "subcategory":"Computer Services",
            "type":"Services"
        }
    ],
    "sg:phone":"+1 626 457 8270",
    "sg:postcode":"91801",
    "sg:province":"CA",
    "sg:tags":[
        "repair",
        "shipping"
    ],
    "sg:website":"www.broadsolutions.net",
    "wof:name":"Broad Solutions",
    "wof:placetype":"venue"
},
  "geometry": {"coordinates":[-118.121002,34.098099],"type":"Point"}
}