{
  "type": "Feature",
  "properties": {
    "addr:full":"5329 San Pablo Dam Rd El Sobrante CA 94803",
    "addr:housenumber":"5329",
    "addr:postcode":"94803",
    "addr:street":"San Pablo Dam Rd",
    "iso:country":"US",
    "sg:address":"5329 San Pablo Dam Rd",
    "sg:city":"El Sobrante",
    "sg:classifiers":[
        {
            "category":"Autos & Motor Vehicles",
            "subcategory":"Fuel & Gas Station",
            "type":"Retail Goods"
        }
    ],
    "sg:phone":"+1 510 758 0261",
    "sg:postcode":"94803",
    "sg:province":"CA",
    "sg:tags":[
        "oil"
    ],
    "wof:name":"Golden Gate Shell El Sobrante",
    "wof:placetype":"venue"
},
  "geometry": {"coordinates":[-122.283506,37.960359],"type":"Point"}
}