{
  "type": "Feature",
  "properties": {
    "addr:full":"355 Coddingtown Center Santa Rosa CA 95401",
    "addr:housenumber":"355",
    "addr:postcode":"95401",
    "addr:street":"Coddingtown Center",
    "iso:country":"US",
    "sg:address":"355 Coddingtown Center",
    "sg:city":"Santa Rosa",
    "sg:classifiers":[
        {
            "category":"Shopping",
            "subcategory":"Computers & Home Electronics",
            "type":"Retail Goods"
        }
    ],
    "sg:phone":"+1 707 569 9558",
    "sg:postcode":"95401",
    "sg:province":"CA",
    "sg:tags":[
        "game",
        "video"
    ],
    "wof:name":"Funcoland",
    "wof:placetype":"venue"
},
  "geometry": {"coordinates":[-122.727429,38.458098],"type":"Point"}
}