{
  "type": "Feature",
  "properties": {
    "iso:country":"US",
    "sg:address":"675 S Westmoreland Ave",
    "sg:city":"Los Angeles",
    "sg:classifiers":[
        {
            "category":"Professional",
            "subcategory":"Lawyer & Legal Services",
            "type":"Services"
        }
    ],
    "sg:phone":"+1 213 738 6823",
    "sg:postcode":"90005",
    "sg:province":"CA",
    "wof:name":"Goodman Max A Attorney",
    "wof:placetype":"venue"
},
  "geometry": {"coordinates":[-118.289001,34.060299],"type":"Point"}
}