{
  "type": "Feature",
  "properties": {
    "iso:country":"US",
    "sg:address":"795 el Camino Real",
    "sg:city":"Palo Alto",
    "sg:classifiers":[
        {
            "category":"Health Services",
            "subcategory":"Doctor",
            "type":"Services"
        }
    ],
    "sg:phone":"+1 650 326 8120",
    "sg:postcode":"94301",
    "sg:province":"CA",
    "sg:tags":[
        "physician",
        "surgeon"
    ],
    "sg:website":"www.pamf.org",
    "wof:name":"Research Institute",
    "wof:placetype":"venue"
},
  "geometry": {"coordinates":[-122.162205,37.439172],"type":"Point"}
}