{
  "type": "Feature",
  "properties": {
    "iso:country":"US",
    "sg:address":"521 N Tustin Ave",
    "sg:city":"Santa Ana",
    "sg:classifiers":[
        {
            "category":"Real Estate",
            "subcategory":"Real Estate Operator",
            "type":"Services"
        }
    ],
    "sg:phone":"+1 714 647 6350",
    "sg:postcode":"92705",
    "sg:province":"CA",
    "sg:tags":[
        "apartment"
    ],
    "wof:name":"The Village Apartments",
    "wof:placetype":"venue"
},
  "geometry": {"coordinates":[-117.834,33.749199],"type":"Point"}
}