{
  "type": "Feature",
  "properties": {
    "addr:full":"2136 Kettner Blvd San Diego CA 92101",
    "addr:housenumber":"2136",
    "addr:postcode":"92101",
    "addr:street":"Kettner Blvd",
    "iso:country":"US",
    "sg:address":"2136 Kettner Blvd",
    "sg:city":"San Diego",
    "sg:classifiers":[
        {
            "category":"Home & Garden",
            "subcategory":"Furniture",
            "type":"Retail Goods"
        }
    ],
    "sg:phone":"+1 619 234 3841",
    "sg:postcode":"92101",
    "sg:province":"CA",
    "sg:tags":[
        "store"
    ],
    "sg:website":"www.zazouhome.com/",
    "wof:name":"Zazou Home",
    "wof:placetype":"venue"
},
  "geometry": {"coordinates":[-117.170998,32.726501],"type":"Point"}
}