{
  "type": "Feature",
  "properties": {
    "addr:full":"421 N Varney St Burbank CA 91502",
    "addr:housenumber":"421",
    "addr:postcode":"91502",
    "addr:street":"N Varney St",
    "iso:country":"US",
    "sg:address":"421 N Varney St",
    "sg:city":"Burbank",
    "sg:classifiers":[
        {
            "category":"Manufacturing",
            "subcategory":"Tools & Machinery",
            "type":"Manufacturing & Wholesale Goods"
        }
    ],
    "sg:phone":"+1 818 846 1825",
    "sg:postcode":"91502",
    "sg:province":"CA",
    "sg:tags":[
        "machine",
        "shop"
    ],
    "wof:name":"Jean Gore Narek",
    "wof:placetype":"venue"
},
  "geometry": {"coordinates":[-118.317053,34.180576],"type":"Point"}
}