{
  "type": "Feature",
  "properties": {
    "iso:country":"US",
    "sg:address":"11399 Mountain View Dr",
    "sg:city":"Rancho Cucamonga",
    "sg:classifiers":[
        {
            "category":"Freight",
            "type":"Transportation"
        }
    ],
    "sg:phone":"+1 951 830 0338",
    "sg:postcode":"91730",
    "sg:province":"CA",
    "sg:tags":[
        "operator",
        "local",
        "trucking"
    ],
    "wof:name":"Nabert Trucking",
    "wof:placetype":"venue"
},
  "geometry": {"coordinates":[-117.55358699999999,34.116411],"type":"Point"}
}