{
  "type": "Feature",
  "properties": {
    "iso:country":"US",
    "sg:address":"275 Fairchild Ave",
    "sg:city":"Chico",
    "sg:classifiers":[
        {
            "category":"Building & Trades",
            "subcategory":"Construction",
            "type":"Services"
        }
    ],
    "sg:phone":"+1 530 742 7665",
    "sg:postcode":"95973",
    "sg:province":"CA",
    "sg:tags":[
        "designer",
        "dealer",
        "pool",
        "swimming"
    ],
    "wof:name":"Bi-County Pool Construction",
    "wof:placetype":"venue"
},
  "geometry": {"coordinates":[-121.849593,39.797363],"type":"Point"}
}