{
  "type": "Feature",
  "properties": {
    "addr:full":"618 E Chestnut St Glendale CA 91205",
    "addr:housenumber":"618",
    "addr:postcode":"91205",
    "addr:street":"E Chestnut St",
    "iso:country":"US",
    "sg:address":"618 E Chestnut St",
    "sg:city":"Glendale",
    "sg:classifiers":[
        {
            "category":"Local Transit",
            "type":"Transportation"
        }
    ],
    "sg:phone":"+1 818 244 9936",
    "sg:postcode":"91205",
    "sg:province":"CA",
    "wof:name":"Airway Transportation",
    "wof:placetype":"venue"
},
  "geometry": {"coordinates":[-118.24643500000001,34.139841],"type":"Point"}
}