{
  "type": "Feature",
  "properties": {
    "addr:full":"2800 E Philadelphia St Ontario CA 91761",
    "addr:housenumber":"2800 e",
    "addr:postcode":"91761",
    "addr:street":"Philadelphia St",
    "iso:country":"US",
    "sg:address":"2800 E Philadelphia St",
    "sg:city":"Ontario",
    "sg:classifiers":[
        {
            "category":"Freight",
            "type":"Transportation"
        }
    ],
    "sg:phone":"+1 800 755 2090",
    "sg:postcode":"91761",
    "sg:province":"CA",
    "sg:tags":[
        "warehouse",
        "facility"
    ],
    "wof:name":"McKesson Mdcl-Srgical Minn Inc",
    "wof:placetype":"venue"
},
  "geometry": {"coordinates":[-117.587317,34.033726],"type":"Point"}
}