{
  "type": "Feature",
  "properties": {
    "iso:country":"US",
    "sg:address":"3328 Macaulay St",
    "sg:city":"San Diego",
    "sg:classifiers":[
        {
            "category":"Wholesale",
            "subcategory":"Groceries",
            "type":"Manufacturing & Wholesale Goods"
        }
    ],
    "sg:phone":"+1 619 223 4804",
    "sg:postcode":"92106",
    "sg:province":"CA",
    "wof:name":"California Hot Sauce",
    "wof:placetype":"venue"
},
  "geometry": {"coordinates":[-117.229014,32.731531],"type":"Point"}
}