{
  "type": "Feature",
  "properties": {
    "addr:full":"3625 W 6th St Los Angeles CA 90020",
    "addr:housenumber":"3625",
    "addr:postcode":"90020",
    "addr:street":"W 6Th St",
    "iso:country":"US",
    "sg:address":"3625 W 6th St",
    "sg:city":"Los Angeles",
    "sg:classifiers":[
        {
            "category":"Professional",
            "type":"Services"
        },
        {
            "category":"Professional",
            "subcategory":"Management & Consulting",
            "type":"Services"
        }
    ],
    "sg:phone":"+1 213 388 3655",
    "sg:postcode":"90020",
    "sg:province":"CA",
    "sg:tags":[
        "consultant",
        "sport"
    ],
    "wof:name":"International Baseball Bureau",
    "wof:placetype":"venue"
},
  "geometry": {"coordinates":[-118.301084,34.063638],"type":"Point"}
}