{
  "type": "Feature",
  "properties": {
    "addr:full":"504 E 3rd Ave San Mateo CA 94401",
    "addr:housenumber":"504",
    "addr:postcode":"94401",
    "addr:street":"E 3Rd Ave",
    "iso:country":"US",
    "sg:address":"504 E 3rd Ave",
    "sg:city":"San Mateo",
    "sg:classifiers":[
        {
            "category":"Restaurant",
            "type":"Food & Drink"
        }
    ],
    "sg:phone":"+1 650 343 9925",
    "sg:postcode":"94401",
    "sg:province":"CA",
    "sg:tags":[
        "mexican"
    ],
    "wof:name":"Las Palomas Taqueria",
    "wof:placetype":"venue"
},
  "geometry": {"coordinates":[-122.320999,37.5667],"type":"Point"}
}