{
  "type": "Feature",
  "properties": {
    "iso:country":"US",
    "sg:address":"35 3rd St",
    "sg:city":"Eureka",
    "sg:classifiers":[
        {
            "category":"Manufacturing",
            "subcategory":"Signs",
            "type":"Manufacturing & Wholesale Goods"
        }
    ],
    "sg:phone":"+1 707 442 3061",
    "sg:postcode":"95501",
    "sg:province":"CA",
    "wof:name":"Sharp Autographics",
    "wof:placetype":"venue"
},
  "geometry": {"coordinates":[-124.171374,40.802953],"type":"Point"}
}