{
  "type": "Feature",
  "properties": {
    "iso:country":"US",
    "sg:address":"1183 Maple St",
    "sg:city":"Turlock",
    "sg:classifiers":[
        {
            "category":"Shopping",
            "subcategory":"Gifts & Souvenirs",
            "type":"Retail Goods"
        }
    ],
    "sg:phone":"+1 209 668 7438",
    "sg:postcode":"95380",
    "sg:province":"CA",
    "sg:tags":[
        "party",
        "supply"
    ],
    "wof:name":"White Flight",
    "wof:placetype":"venue"
},
  "geometry": {"coordinates":[-120.854831,37.481935],"type":"Point"}
}