{
  "type": "Feature",
  "properties": {
    "iso:country":"US",
    "sg:address":"945 Main St",
    "sg:city":"St Helena",
    "sg:classifiers":[
        {
            "category":"Manufacturing",
            "subcategory":"Food",
            "type":"Manufacturing & Wholesale Goods"
        },
        {
            "category":"Wholesale",
            "subcategory":"Groceries",
            "type":"Manufacturing & Wholesale Goods"
        }
    ],
    "sg:phone":"+1 707 942 1110",
    "sg:postcode":"94574",
    "sg:province":"CA",
    "sg:tags":[
        "mfg",
        "carbonated",
        "beverage",
        "alcoholic"
    ],
    "wof:name":"Roto Beverage LLC",
    "wof:placetype":"venue"
},
  "geometry": {"coordinates":[-122.46525,38.501993],"type":"Point"}
}