{
  "type": "Feature",
  "properties": {
    "addr:full":"2925 Adeline St Emeryville CA 94608",
    "addr:housenumber":"2925",
    "addr:postcode":"94608",
    "addr:street":"Adeline St",
    "iso:country":"US",
    "sg:address":"2925 Adeline St",
    "sg:city":"Emeryville",
    "sg:classifiers":[
        {
            "category":"Food & Beverages",
            "subcategory":"Supermarket",
            "type":"Retail Goods"
        }
    ],
    "sg:phone":"+1 510 452 8244",
    "sg:postcode":"94608",
    "sg:province":"CA",
    "sg:tags":[
        "super",
        "store"
    ],
    "wof:name":"Fargo Choice Foods",
    "wof:placetype":"venue"
},
  "geometry": {"coordinates":[-122.28185999999999,37.821372],"type":"Point"}
}