{
  "type": "Feature",
  "properties": {
    "iso:country":"US",
    "sg:address":"1945 S Rice Rd",
    "sg:city":"Ojai",
    "sg:classifiers":[
        {
            "category":"Building & Trades",
            "subcategory":"Electrical",
            "type":"Services"
        }
    ],
    "sg:phone":"+1 805 649 6888",
    "sg:postcode":"93023",
    "sg:province":"CA",
    "sg:tags":[
        "booth",
        "equipment",
        "telephone",
        "pay"
    ],
    "wof:name":"Western Payphone Systems",
    "wof:placetype":"venue"
},
  "geometry": {"coordinates":[-119.293993,34.424506],"type":"Point"}
}