{
  "type": "Feature",
  "properties": {
    "addr:full":"248 E 1st St Los Angeles CA 90012",
    "addr:housenumber":"248",
    "addr:postcode":"90012",
    "addr:street":"E 1St St",
    "iso:country":"US",
    "sg:address":"248 E 1st St",
    "sg:city":"Los Angeles",
    "sg:classifiers":[
        {
            "category":"Professional",
            "type":"Services"
        }
    ],
    "sg:phone":"+1 213 626 0332",
    "sg:postcode":"90012",
    "sg:province":"CA",
    "wof:name":"Care Entree",
    "wof:placetype":"venue"
},
  "geometry": {"coordinates":[-118.241355,34.050742],"type":"Point"}
}