{
  "type": "Feature",
  "properties": {
    "addr:full":"3565 Mt Diablo Blvd Lafayette CA 94549",
    "addr:housenumber":"3565",
    "addr:postcode":"94549",
    "addr:street":"Mt Diablo Blvd",
    "iso:country":"US",
    "sg:address":"3565 Mt Diablo Blvd",
    "sg:city":"Lafayette",
    "sg:classifiers":[
        {
            "category":"Restaurant",
            "type":"Food & Drink"
        }
    ],
    "sg:menulink":"http://www.allmenus.com/ca/central-contra-costa/268795-postino/menu/",
    "sg:phone":"+1 925 299 8700",
    "sg:postcode":"94549",
    "sg:province":"CA",
    "sg:tags":[
        "italian"
    ],
    "wof:name":"Postino",
    "wof:placetype":"venue"
},
  "geometry": {"coordinates":[-122.121134,37.891095],"type":"Point"}
}