{
  "type": "Feature",
  "properties": {
    "iso:country":"US",
    "sg:address":"354 S Broadway",
    "sg:city":"Los Angeles",
    "sg:classifiers":[
        {
            "category":"Shopping",
            "subcategory":"Jewelry",
            "type":"Retail Goods"
        }
    ],
    "sg:phone":"+1 213 621 2577",
    "sg:postcode":"90013",
    "sg:province":"CA",
    "sg:tags":[
        "jeweler"
    ],
    "wof:name":"Jewelry Liquidation",
    "wof:placetype":"venue"
},
  "geometry": {"coordinates":[-118.248687,34.050269],"type":"Point"}
}