{
  "type": "Feature",
  "properties": {
    "iso:country":"US",
    "sg:address":"1095 N Allen Ave",
    "sg:city":"Pasadena",
    "sg:classifiers":[
        {
            "category":"Shopping",
            "type":"Retail Goods"
        }
    ],
    "sg:phone":"+1 626 345 0050",
    "sg:postcode":"91104",
    "sg:province":"CA",
    "sg:tags":[
        "limb",
        "artificial"
    ],
    "sg:website":"www.aestheticprosthetics.com",
    "wof:name":"Aesthetic Prosthetics",
    "wof:placetype":"venue"
},
  "geometry": {"coordinates":[-118.113153,34.164735],"type":"Point"}
}