{
  "type": "Feature",
  "properties": {
    "addr:full":"4466 Industrial St Simi Valley CA 93063",
    "addr:housenumber":"4466",
    "addr:postcode":"93063",
    "addr:street":"Industrial St",
    "iso:country":"US",
    "sg:address":"4466 Industrial St",
    "sg:city":"Simi Valley",
    "sg:classifiers":[
        {
            "category":"Professional",
            "subcategory":"Accounting & Tax Preparation",
            "type":"Services"
        }
    ],
    "sg:phone":"+1 805 583 1984",
    "sg:postcode":"93063",
    "sg:province":"CA",
    "sg:tags":[
        "bookkeeping",
        "general"
    ],
    "wof:name":"AAA Bookkeeping & Financial",
    "wof:placetype":"venue"
},
  "geometry": {"coordinates":[-118.70222699999999,34.273184],"type":"Point"}
}