{
  "type": "Feature",
  "properties": {
    "addr:full":"2014 Laguna St San Francisco CA 94115",
    "addr:housenumber":"2014",
    "addr:postcode":"94115",
    "addr:street":"Laguna St",
    "iso:country":"US",
    "sg:address":"2014 Laguna St",
    "sg:city":"San Francisco",
    "sg:classifiers":[
        {
            "category":"Professional",
            "subcategory":"Management & Consulting",
            "type":"Services"
        }
    ],
    "sg:phone":"+1 415 307 2280",
    "sg:postcode":"94115",
    "sg:province":"CA",
    "sg:tags":[
        "consultant",
        "design"
    ],
    "wof:name":"Charles Group Inc",
    "wof:placetype":"venue"
},
  "geometry": {"coordinates":[-122.428997,37.790339],"type":"Point"}
}