{
  "type": "Feature",
  "properties": {
    "addr:full":"650 S Hill St Los Angeles CA 90014",
    "addr:housenumber":"650",
    "addr:postcode":"90014",
    "addr:street":"S Hill St",
    "iso:country":"US",
    "sg:address":"650 S Hill St",
    "sg:city":"Los Angeles",
    "sg:classifiers":[
        {
            "category":"Manufacturing",
            "subcategory":"Jewelry",
            "type":"Manufacturing & Wholesale Goods"
        }
    ],
    "sg:phone":"+1 213 488 9555",
    "sg:postcode":"90014",
    "sg:province":"CA",
    "wof:name":"H & A Jewelry",
    "wof:placetype":"venue"
},
  "geometry": {"coordinates":[-118.253823,34.046596],"type":"Point"}
}