{
  "type": "Feature",
  "properties": {
    "addr:full":"316 Elm Ave Long Beach CA 90802",
    "addr:housenumber":"316",
    "addr:postcode":"90802",
    "addr:street":"Elm Ave",
    "iso:country":"US",
    "sg:address":"316 Elm Ave",
    "sg:city":"Long Beach",
    "sg:classifiers":[
        {
            "category":"Shopping",
            "subcategory":"Shoes",
            "type":"Retail Goods"
        }
    ],
    "sg:phone":"+1 562 436 8000",
    "sg:postcode":"90802",
    "sg:province":"CA",
    "sg:tags":[
        "store"
    ],
    "wof:name":"Fresh Footwear",
    "wof:placetype":"venue"
},
  "geometry": {"coordinates":[-118.187505,33.77071],"type":"Point"}
}