{
  "type": "Feature",
  "properties": {
    "addr:full":"21101 Oxnard St Woodland Hills CA 91367",
    "addr:housenumber":"21101",
    "addr:postcode":"91367",
    "addr:street":"Oxnard St",
    "iso:country":"US",
    "sg:address":"21101 Oxnard St",
    "sg:city":"Woodland Hills",
    "sg:classifiers":[
        {
            "category":"Wholesale",
            "subcategory":"Drugs",
            "type":"Manufacturing & Wholesale Goods"
        }
    ],
    "sg:phone":"+1 818 226 1968",
    "sg:postcode":"91367",
    "sg:province":"CA",
    "sg:tags":[
        "mobile",
        "hematologist",
        "blood",
        "therapeutic"
    ],
    "wof:name":"Hemacare Corporation",
    "wof:placetype":"venue"
},
  "geometry": {"coordinates":[-118.59736100000001,34.179243],"type":"Point"}
}