{
  "type": "Feature",
  "properties": {
    "iso:country":"US",
    "sg:address":"102 E el Monte St",
    "sg:city":"South El Monte",
    "sg:classifiers":[
        {
            "category":"Retail",
            "subcategory":"Auto Rental",
            "type":"Services"
        }
    ],
    "sg:phone":"+1 877 603 0471",
    "sg:postcode":"91776",
    "sg:province":"CA",
    "sg:tags":[
        "truck"
    ],
    "wof:name":"Penske",
    "wof:placetype":"venue"
},
  "geometry": {"coordinates":[-118.09735499999999,34.094081],"type":"Point"}
}