{
  "type": "Feature",
  "properties": {
    "iso:country":"US",
    "sg:address":"468 N Rodeo Dr",
    "sg:city":"Beverly Hills",
    "sg:classifiers":[
        {
            "category":"Shopping",
            "type":"Retail Goods"
        }
    ],
    "sg:phone":"+1 310 274 4003",
    "sg:postcode":"90210",
    "sg:province":"CA",
    "wof:name":"Brooks Brothers",
    "wof:placetype":"venue"
},
  "geometry": {"coordinates":[-118.403876,34.070644],"type":"Point"}
}