{
  "type": "Feature",
  "properties": {
    "iso:country":"US",
    "sg:address":"1042 Orange St",
    "sg:city":"Santa Maria",
    "sg:classifiers":[
        {
            "category":"Real Estate",
            "subcategory":"Real Estate Operator",
            "type":"Services"
        }
    ],
    "sg:phone":"+1 805 922 3386",
    "sg:postcode":"93458",
    "sg:province":"CA",
    "sg:tags":[
        "apartment"
    ],
    "wof:name":"VIP Future Corp",
    "wof:placetype":"venue"
},
  "geometry": {"coordinates":[-120.450028,34.948337],"type":"Point"}
}