{
  "type": "Feature",
  "properties": {
    "addr:full":"1659 Adrian Rd Burlingame CA 94010",
    "addr:housenumber":"1659",
    "addr:postcode":"94010",
    "addr:street":"Adrian Rd",
    "iso:country":"US",
    "sg:address":"1659 Adrian Rd",
    "sg:city":"Burlingame",
    "sg:classifiers":[
        {
            "category":"Manufacturing",
            "subcategory":"Printing",
            "type":"Manufacturing & Wholesale Goods"
        }
    ],
    "sg:phone":"+1 650 697 0505",
    "sg:postcode":"94010",
    "sg:province":"CA",
    "sg:tags":[
        "printer"
    ],
    "wof:name":"3-Day Envelopes",
    "wof:placetype":"venue"
},
  "geometry": {"coordinates":[-122.374377,37.597627],"type":"Point"}
}