{
  "type": "Feature",
  "properties": {
    "iso:country":"US",
    "sg:address":"2709 Orange Ave",
    "sg:city":"Santa Ana",
    "sg:classifiers":[
        {
            "category":"Shopping",
            "type":"Retail Goods"
        }
    ],
    "sg:phone":"+1 714 444 2119",
    "sg:postcode":"92707",
    "sg:province":"CA",
    "sg:tags":[
        "merchandise"
    ],
    "wof:name":"Jerrys Woodshop",
    "wof:placetype":"venue"
},
  "geometry": {"coordinates":[-117.865755,33.709004],"type":"Point"}
}