{
  "type": "Feature",
  "properties": {
    "addr:full":"1500 Carlson Blvd Richmond CA 94804",
    "addr:housenumber":"1500",
    "addr:postcode":"94804",
    "addr:street":"Carlson Blvd",
    "iso:country":"US",
    "sg:address":"1500 Carlson Blvd",
    "sg:city":"Richmond",
    "sg:classifiers":[
        {
            "category":"Retail",
            "subcategory":"Car Wash",
            "type":"Services"
        }
    ],
    "sg:phone":"+1 510 235 9809",
    "sg:postcode":"94804",
    "sg:province":"CA",
    "sg:tags":[
        "auto",
        "detailing",
        "detail",
        "clean",
        "automobile"
    ],
    "wof:name":"Chalk's Auto Salon",
    "wof:placetype":"venue"
},
  "geometry": {"coordinates":[-122.318237,37.911724],"type":"Point"}
}