{
  "type": "Feature",
  "properties": {
    "addr:full":"10020 Cherry Ridge Rd Sebastopol CA 95472",
    "addr:housenumber":"10020",
    "addr:postcode":"95472",
    "addr:street":"Cherry Ridge Rd",
    "iso:country":"US",
    "sg:address":"10020 Cherry Ridge Rd",
    "sg:city":"Sebastopol",
    "sg:classifiers":[
        {
            "category":"Freight",
            "type":"Transportation"
        }
    ],
    "sg:phone":"+1 707 823 4821",
    "sg:postcode":"95472",
    "sg:province":"CA",
    "sg:tags":[
        "trucking"
    ],
    "wof:name":"Silva Brothers Orchards",
    "wof:placetype":"venue"
},
  "geometry": {"coordinates":[-122.873243,38.413831],"type":"Point"}
}