{
  "type": "Feature",
  "properties": {
    "addr:full":"4345 Olive Ave Fairfield CA 94533",
    "addr:housenumber":"4345",
    "addr:postcode":"94533",
    "addr:street":"Olive Ave",
    "iso:country":"US",
    "sg:address":"4345 Olive Ave",
    "sg:city":"Fairfield",
    "sg:classifiers":[
        {
            "category":"Professional",
            "subcategory":"Advertising",
            "type":"Services"
        }
    ],
    "sg:phone":"+1 707 425 2514",
    "sg:postcode":"94533",
    "sg:province":"CA",
    "sg:tags":[
        "distribution"
    ],
    "wof:name":"DMS Distributing",
    "wof:placetype":"venue"
},
  "geometry": {"coordinates":[-122.00342499999999,38.253541],"type":"Point"}
}