{
  "type": "Feature",
  "properties": {
    "addr:full":"34107 Natoma Rd Auberry CA 93602",
    "addr:postcode":"34107;93602",
    "addr:street":"Natoma Rd",
    "iso:country":"US",
    "sg:address":"34107 Natoma Rd",
    "sg:city":"Auberry",
    "sg:classifiers":[
        {
            "category":"Farming",
            "subcategory":"Vineyard",
            "type":"Manufacturing & Wholesale Goods"
        }
    ],
    "sg:phone":"+1 559 841 7289",
    "sg:postcode":"93602",
    "sg:province":"CA",
    "sg:tags":[
        "grape"
    ],
    "wof:name":"Sandy Little Enterprises",
    "wof:placetype":"venue"
},
  "geometry": {"coordinates":[-119.37376,37.042922],"type":"Point"}
}