{
  "type": "Feature",
  "properties": {
    "addr:full":"1919 Gunston Way San Jose CA 95124",
    "addr:housenumber":"1919",
    "addr:postcode":"95124",
    "addr:street":"Gunston Way",
    "iso:country":"US",
    "sg:address":"1919 Gunston Way",
    "sg:city":"San Jose",
    "sg:classifiers":[
        {
            "category":"Education",
            "subcategory":"Preschool",
            "type":"Public Place"
        }
    ],
    "sg:phone":"+1 408 377 5390",
    "sg:postcode":"95124",
    "sg:province":"CA",
    "sg:website":"www.discoverypreschool.org",
    "wof:name":"Discovery Parent-Child Pre-School",
    "wof:placetype":"venue"
},
  "geometry": {"coordinates":[-121.92279000000001,37.255535],"type":"Point"}
}