{
  "type": "Feature",
  "properties": {
    "iso:country":"US",
    "sg:address":"755 Fiero Ln",
    "sg:city":"San Luis Obispo",
    "sg:classifiers":[
        {
            "category":"Wholesale",
            "subcategory":"Drugs",
            "type":"Manufacturing & Wholesale Goods"
        }
    ],
    "sg:phone":"+1 805 541 0783",
    "sg:postcode":"93401",
    "sg:province":"CA",
    "sg:tags":[
        "pharmaceutical",
        "product"
    ],
    "wof:name":"Pharmarx Pharmaceutical Inc",
    "wof:placetype":"venue"
},
  "geometry": {"coordinates":[-120.642813,35.244058],"type":"Point"}
}