{
  "type": "Feature",
  "properties": {
    "iso:country":"US",
    "sg:address":"9543 Culver Blvd",
    "sg:city":"Culver City",
    "sg:classifiers":[
        {
            "category":"Communications",
            "subcategory":"Film & Video Production",
            "type":"Services"
        }
    ],
    "sg:phone":"+1 310 845 9070",
    "sg:postcode":"90232",
    "sg:province":"CA",
    "wof:name":"Time Warner",
    "wof:placetype":"venue"
},
  "geometry": {"coordinates":[-118.39502899999999,34.02317],"type":"Point"}
}