{
  "type": "Feature",
  "properties": {
    "iso:country":"US",
    "sg:address":"11721 Whittier Blvd",
    "sg:city":"Whittier",
    "sg:classifiers":[
        {
            "category":"Freight",
            "type":"Transportation"
        }
    ],
    "sg:phone":"+1 562 908 0799",
    "sg:postcode":"90601",
    "sg:province":"CA",
    "sg:tags":[
        "shipping"
    ],
    "sg:website":"www.ups.com/",
    "wof:name":"UPS Store",
    "wof:placetype":"venue"
},
  "geometry": {"coordinates":[-118.051272,33.981397],"type":"Point"}
}