{
  "type": "Feature",
  "properties": {
    "iso:country":"US",
    "sg:address":"9830 Sierra Ave",
    "sg:city":"Fontana",
    "sg:classifiers":[
        {
            "category":"Shopping",
            "subcategory":"Clothing, Apparel, & Fashions",
            "type":"Retail Goods"
        }
    ],
    "sg:phone":"+1 909 822 1838",
    "sg:postcode":"92335",
    "sg:province":"CA",
    "wof:name":"Fashion One",
    "wof:placetype":"venue"
},
  "geometry": {"coordinates":[-117.435758,34.076352],"type":"Point"}
}