{
  "type": "Feature",
  "properties": {
    "iso:country":"US",
    "sg:address":"41865 State Hwy 299",
    "sg:city":"Willow Creek",
    "sg:phone":"+1 530 629 3388",
    "sg:postcode":"95573",
    "sg:province":"CA",
    "sg:tags":[
        "gas"
    ],
    "wof:name":"Campora Propane Svc",
    "wof:placetype":"venue"
},
  "geometry": {"coordinates":[-123.62616800000001,40.937041],"type":"Point"}
}