{
  "type": "Feature",
  "properties": {
    "iso:country":"US",
    "sg:address":"5250 Front St",
    "sg:city":"Rocklin",
    "sg:classifiers":[
        {
            "category":"Professional",
            "type":"Services"
        }
    ],
    "sg:phone":"+1 916 630 1950",
    "sg:postcode":"95677",
    "sg:province":"CA",
    "sg:tags":[
        "establishment"
    ],
    "wof:name":"Zalgud Co",
    "wof:placetype":"venue"
},
  "geometry": {"coordinates":[-121.238705,38.791018],"type":"Point"}
}