{
  "type": "Feature",
  "properties": {
    "iso:country":"US",
    "sg:address":"5065 Stone Ave",
    "sg:city":"Riverside",
    "sg:classifiers":[
        {
            "category":"Farming",
            "subcategory":"Aquatic Farm",
            "type":"Manufacturing & Wholesale Goods"
        }
    ],
    "sg:phone":"+1 951 685 7666",
    "sg:postcode":"92509",
    "sg:province":"CA",
    "sg:tags":[
        "beekeeper"
    ],
    "wof:name":"Happy Bee Co",
    "wof:placetype":"venue"
},
  "geometry": {"coordinates":[-117.466786,33.998238],"type":"Point"}
}