{
  "type": "Feature",
  "properties": {
    "iso:country":"US",
    "sg:address":"3065 Rosecrans Pl",
    "sg:city":"San Diego",
    "sg:classifiers":[
        {
            "category":"Professional",
            "subcategory":"Accounting & Tax Preparation",
            "type":"Services"
        }
    ],
    "sg:phone":"+1 619 758 9223",
    "sg:postcode":"92110",
    "sg:province":"CA",
    "sg:tags":[
        "bookkeeping",
        "general"
    ],
    "wof:name":"Bookkeeping Dept",
    "wof:placetype":"venue"
},
  "geometry": {"coordinates":[-117.21176800000001,32.744652],"type":"Point"}
}