{
  "type": "Feature",
  "properties": {
    "addr:full":"2084 Jeremy Ln Escondido CA 92027",
    "addr:housenumber":"2084",
    "addr:postcode":"92027",
    "addr:street":"Jeremy Ln",
    "iso:country":"US",
    "sg:address":"2084 Jeremy Ln",
    "sg:city":"Escondido",
    "sg:classifiers":[
        {
            "category":"Retail",
            "subcategory":"Laundry & Dry Cleaning",
            "type":"Services"
        }
    ],
    "sg:phone":"+1 760 741 1144",
    "sg:postcode":"92027",
    "sg:province":"CA",
    "sg:tags":[
        "cleaners",
        "rug",
        "carpet"
    ],
    "wof:name":"All Clean Enterprises LLC",
    "wof:placetype":"venue"
},
  "geometry": {"coordinates":[-117.062319,33.153488],"type":"Point"}
}