{
  "type": "Feature",
  "properties": {
    "iso:country":"US",
    "sg:address":"4 Janet Way",
    "sg:city":"Belvedere Tibrn",
    "sg:classifiers":[
        {
            "category":"Professional",
            "subcategory":"Management & Consulting",
            "type":"Services"
        }
    ],
    "sg:phone":"+1 415 381 8060",
    "sg:postcode":"94920",
    "sg:province":"CA",
    "sg:tags":[
        "consultant",
        "business"
    ],
    "sg:website":"www.corewisdom.com",
    "wof:name":"Lifeprinciple Technologies",
    "wof:placetype":"venue"
},
  "geometry": {"coordinates":[-122.495859,37.896072],"type":"Point"}
}