{
  "type": "Feature",
  "properties": {
    "addr:full":"785 N Main St Bishop CA 93514",
    "addr:housenumber":"785",
    "addr:postcode":"93514",
    "addr:street":"N Main St",
    "iso:country":"US",
    "sg:address":"785 N Main St",
    "sg:city":"Bishop",
    "sg:classifiers":[
        {
            "category":"Restaurant",
            "type":"Food & Drink"
        }
    ],
    "sg:phone":"+1 760 872 1144",
    "sg:postcode":"93514",
    "sg:province":"CA",
    "wof:name":"Imperial Gourmet Chinese",
    "wof:placetype":"venue"
},
  "geometry": {"coordinates":[-118.395458,37.368462],"type":"Point"}
}