{
  "type": "Feature",
  "properties": {
    "addr:full":"2841 S Diamond Bar Blvd Diamond Bar CA 91765",
    "addr:housenumber":"2841",
    "addr:postcode":"91765",
    "addr:street":"S;Blvd",
    "iso:country":"US",
    "sg:address":"2841 S Diamond Bar Blvd",
    "sg:city":"Diamond Bar",
    "sg:classifiers":[
        {
            "category":"Retail",
            "subcategory":"Laundry & Dry Cleaning",
            "type":"Services"
        }
    ],
    "sg:phone":"+1 909 595 6213",
    "sg:postcode":"91765",
    "sg:province":"CA",
    "sg:tags":[
        "drycleaning",
        "plant"
    ],
    "wof:name":"Diamond Bar Cleaners",
    "wof:placetype":"venue"
},
  "geometry": {"coordinates":[-117.839151,33.972367],"type":"Point"}
}