{
  "type": "Feature",
  "properties": {
    "addr:full":"349 Cobalt Way Sunnyvale CA 94085",
    "addr:housenumber":"349",
    "addr:postcode":"94085",
    "addr:street":"Cobalt Way",
    "iso:country":"US",
    "sg:address":"349 Cobalt Way",
    "sg:city":"Sunnyvale",
    "sg:classifiers":[
        {
            "category":"Professional",
            "type":"Services"
        }
    ],
    "sg:phone":"+1 408 738 5785",
    "sg:postcode":"94085",
    "sg:province":"CA",
    "sg:tags":[
        "establishment"
    ],
    "wof:name":"Cut On The Action",
    "wof:placetype":"venue"
},
  "geometry": {"coordinates":[-121.99526299999999,37.377787],"type":"Point"}
}