{
  "type": "Feature",
  "properties": {
    "addr:full":"13011 Newport Ave Ste 102A Tustin CA 92780",
    "addr:housenumber":"13011",
    "addr:postcode":"92780",
    "addr:street":"Newport Ave Ste 102A",
    "iso:country":"US",
    "sg:address":"13011 Newport Ave Ste 102A",
    "sg:city":"Tustin",
    "sg:classifiers":[
        {
            "category":"Shopping",
            "subcategory":"Clothing, Apparel, & Fashions",
            "type":"Retail Goods"
        }
    ],
    "sg:phone":"+1 714 665 5994",
    "sg:postcode":"92780",
    "sg:province":"CA",
    "sg:tags":[
        "lingerie",
        "clothing",
        "women's"
    ],
    "sg:website":"www.aperfectfitonline.com",
    "wof:name":"A Perfect Fit",
    "wof:placetype":"venue"
},
  "geometry": {"coordinates":[-117.81094400000001,33.749477],"type":"Point"}
}