{
  "type": "Feature",
  "properties": {
    "addr:full":"5446 Beach Blvd Buena Park CA 90621",
    "addr:housenumber":"5446",
    "addr:postcode":"90621",
    "addr:street":"Beach Blvd",
    "iso:country":"US",
    "sg:address":"5446 Beach Blvd",
    "sg:city":"Buena Park",
    "sg:classifiers":[
        {
            "category":"Restaurant",
            "type":"Food & Drink"
        }
    ],
    "sg:phone":"+1 714 994 4008",
    "sg:postcode":"90621",
    "sg:province":"CA",
    "sg:tags":[
        "korean"
    ],
    "wof:name":"Myungdong Tofu House",
    "wof:placetype":"venue"
},
  "geometry": {"coordinates":[-117.998001,33.882198],"type":"Point"}
}