{
  "type": "Feature",
  "properties": {
    "iso:country":"US",
    "sg:address":"4305 Emily Way",
    "sg:city":"Redding",
    "sg:classifiers":[
        {
            "category":"Professional",
            "type":"Services"
        }
    ],
    "sg:phone":"+1 530 241 3060",
    "sg:postcode":"96001",
    "sg:province":"CA",
    "wof:name":"Special Olympic Shasta County",
    "wof:placetype":"venue"
},
  "geometry": {"coordinates":[-122.398629,40.550932],"type":"Point"}
}