{
  "type": "Feature",
  "properties": {
    "addr:full":"4857 Huntington Dr N Los Angeles CA 90032",
    "addr:housenumber":"4857",
    "addr:postcode":"90032",
    "addr:street":"Huntington Dr N",
    "iso:country":"US",
    "sg:address":"4857 Huntington Dr N",
    "sg:city":"Los Angeles",
    "sg:classifiers":[
        {
            "category":"Health Services",
            "subcategory":"Doctor",
            "type":"Services"
        }
    ],
    "sg:phone":"+1 323 226 9042",
    "sg:postcode":"90032",
    "sg:province":"CA",
    "sg:tags":[
        "clinic"
    ],
    "wof:name":"Mosaic Family Care Med Group",
    "wof:placetype":"venue"
},
  "geometry": {"coordinates":[-118.178307,34.086433],"type":"Point"}
}