{
  "type": "Feature",
  "properties": {
    "iso:country":"US",
    "sg:address":"3941 Holly Dr Ste J",
    "sg:city":"Tracy",
    "sg:classifiers":[
        {
            "category":"Autos & Motor Vehicles",
            "subcategory":"Auto Supplies",
            "type":"Retail Goods"
        }
    ],
    "sg:phone":"+1 209 839 1400",
    "sg:postcode":"95304",
    "sg:province":"CA",
    "sg:tags":[
        "transmission",
        "automobile",
        "accessory",
        "part",
        "transmissions-other",
        "clutch"
    ],
    "sg:website":"http://www.tranzpro.com",
    "wof:name":"Tranzpro",
    "wof:placetype":"venue"
},
  "geometry": {"coordinates":[-121.42599300000001,37.765406],"type":"Point"}
}