{
  "type": "Feature",
  "properties": {
    "iso:country":"US",
    "sg:address":"3000 Cherry Laurel Ct",
    "sg:city":"Bakersfield",
    "sg:classifiers":[
        {
            "category":"Real Estate",
            "subcategory":"Real Estate Agent",
            "type":"Services"
        }
    ],
    "sg:phone":"+1 661 322 6787",
    "sg:postcode":"93308",
    "sg:province":"CA",
    "sg:tags":[
        "inspection"
    ],
    "wof:name":"Luttrell's Home Inspection",
    "wof:placetype":"venue"
},
  "geometry": {"coordinates":[-119.03187200000001,35.434708],"type":"Point"}
}