{
  "type": "Feature",
  "properties": {
    "iso:country":"US",
    "sg:address":"6193 Lake Murray Blvd",
    "sg:city":"La Mesa",
    "sg:classifiers":[
        {
            "category":"Personal",
            "subcategory":"Beauty Salon",
            "type":"Services"
        }
    ],
    "sg:phone":"+1 619 461 2211",
    "sg:postcode":"91942",
    "sg:province":"CA",
    "wof:name":"Sophia's Salon & Spa",
    "wof:placetype":"venue"
},
  "geometry": {"coordinates":[-117.021462,32.78972],"type":"Point"}
}