{
  "type": "Feature",
  "properties": {
    "addr:full":"2350 E el Segundo Blvd El Segundo CA 90245",
    "addr:housenumber":"2350",
    "addr:postcode":"90245",
    "addr:street":"E El Segundo Blvd",
    "iso:country":"US",
    "sg:address":"2350 E el Segundo Blvd",
    "sg:city":"El Segundo",
    "sg:classifiers":[
        {
            "category":"Education",
            "subcategory":"Library",
            "type":"Public Place"
        }
    ],
    "sg:phone":"+1 310 336 6738",
    "sg:postcode":"90245",
    "sg:province":"CA",
    "sg:tags":[
        "special",
        "interest"
    ],
    "wof:name":"Charles C Lauritsen Library",
    "wof:placetype":"venue"
},
  "geometry": {"coordinates":[-118.381326,33.916297],"type":"Point"}
}