{
  "type": "Feature",
  "properties": {
    "addr:full":"645 W Harding Way Stockton CA 95204",
    "addr:housenumber":"645",
    "addr:postcode":"95204",
    "addr:street":"W Harding Way",
    "iso:country":"US",
    "sg:address":"645 W Harding Way",
    "sg:city":"Stockton",
    "sg:classifiers":[
        {
            "category":"Professional",
            "subcategory":"Testing Lab",
            "type":"Services"
        },
        {
            "category":"Health Services",
            "subcategory":"Medical Lab",
            "type":"Services"
        }
    ],
    "sg:phone":"+1 209 546 1933",
    "sg:postcode":"95204",
    "sg:province":"CA",
    "sg:tags":[
        "laboratory",
        "dental"
    ],
    "wof:name":"1st Priority Dental Labratory",
    "wof:placetype":"venue"
},
  "geometry": {"coordinates":[-121.303535,37.965903],"type":"Point"}
}