{
  "type": "Feature",
  "properties": {
    "iso:country":"US",
    "sg:address":"7001 Reseda Blvd",
    "sg:city":"Reseda",
    "sg:classifiers":[
        {
            "category":"Autos & Motor Vehicles",
            "subcategory":"Auto Supplies",
            "type":"Retail Goods"
        }
    ],
    "sg:phone":"+1 818 344 4410",
    "sg:postcode":"91335",
    "sg:province":"CA",
    "sg:tags":[
        "equipment",
        "racing",
        "car",
        "automobile"
    ],
    "wof:name":"2 K Racing",
    "wof:placetype":"venue"
},
  "geometry": {"coordinates":[-118.536044,34.199297],"type":"Point"}
}