{
  "type": "Feature",
  "properties": {
    "addr:full":"403 San Benito Ave Gerber CA 96035",
    "addr:housenumber":"403",
    "addr:postcode":"96035",
    "addr:street":"San Benito Ave",
    "iso:country":"US",
    "sg:address":"403 San Benito Ave",
    "sg:city":"Gerber",
    "sg:classifiers":[
        {
            "category":"Bars & Pubs",
            "type":"Food & Drink"
        }
    ],
    "sg:phone":"+1 530 385 1895",
    "sg:postcode":"96035",
    "sg:province":"CA",
    "wof:name":"Pasa Tiempo Club",
    "wof:placetype":"venue"
},
  "geometry": {"coordinates":[-122.150167,40.0534],"type":"Point"}
}