{
  "type": "Feature",
  "properties": {
    "iso:country":"US",
    "sg:address":"759 W San Carlos St",
    "sg:city":"San Jose",
    "sg:classifiers":[
        {
            "category":"Wholesale",
            "subcategory":"Farm Supplies",
            "type":"Manufacturing & Wholesale Goods"
        }
    ],
    "sg:phone":"+1 408 287 9090",
    "sg:postcode":"95126",
    "sg:province":"CA",
    "sg:tags":[
        "pet",
        "feed",
        "store"
    ],
    "sg:website":"www.samsdowntownfeed.com",
    "wof:name":"Sam's Downtown Feed & Pet Supply",
    "wof:placetype":"venue"
},
  "geometry": {"coordinates":[-121.904999,37.3237],"type":"Point"}
}