{
  "type": "Feature",
  "properties": {
    "addr:full":"5655 E Beverly Blvd Los Angeles CA 90022",
    "addr:housenumber":"5655",
    "addr:postcode":"90022",
    "addr:street":"E Beverly Blvd",
    "iso:country":"US",
    "sg:address":"5655 E Beverly Blvd",
    "sg:city":"Los Angeles",
    "sg:classifiers":[
        {
            "category":"Social Services",
            "type":"Services"
        }
    ],
    "sg:phone":"+1 323 724 4446",
    "sg:postcode":"90022",
    "sg:province":"CA",
    "sg:tags":[
        "counselor",
        "marriage",
        "family"
    ],
    "wof:name":"CBC Education Inc",
    "wof:placetype":"venue"
},
  "geometry": {"coordinates":[-118.14482599999999,34.026965],"type":"Point"}
}