{
  "type": "Feature",
  "properties": {
    "iso:country":"US",
    "sg:address":"120 Florin St",
    "sg:city":"Pismo Beach",
    "sg:classifiers":[
        {
            "category":"Shopping",
            "subcategory":"Beauty & Cosmetics",
            "type":"Retail Goods"
        }
    ],
    "sg:phone":"+1 805 773 0461",
    "sg:postcode":"93449",
    "sg:province":"CA",
    "sg:tags":[
        "merchandise"
    ],
    "wof:name":"Mary Kay Cosmetics",
    "wof:placetype":"venue"
},
  "geometry": {"coordinates":[-120.69603499999999,35.171598],"type":"Point"}
}