{
  "type": "Feature",
  "properties": {
    "iso:country":"US",
    "sg:address":"2585 Samaritan Drive Suite 302",
    "sg:city":"San Jose",
    "sg:classifiers":[
        {
            "category":"Health Services",
            "subcategory":"Doctor",
            "type":"Services"
        }
    ],
    "sg:phone":"+1 408 356 7788",
    "sg:postcode":"95124",
    "sg:province":"CA",
    "wof:name":"Center For Plastic & Cosmetic Surgery",
    "wof:placetype":"venue"
},
  "geometry": {"coordinates":[-121.951756,37.252969],"type":"Point"}
}