{
  "type": "Feature",
  "properties": {
    "iso:country":"US",
    "sg:address":"2200 E 27th St",
    "sg:city":"Long Beach",
    "sg:classifiers":[
        {
            "category":"Professional",
            "subcategory":"Lawyer & Legal Services",
            "type":"Services"
        }
    ],
    "sg:phone":"+1 562 595 1337",
    "sg:postcode":"90755",
    "sg:province":"CA",
    "sg:website":"www.signalattorneyservice.com",
    "wof:name":"Signal Attorney Service",
    "wof:placetype":"venue"
},
  "geometry": {"coordinates":[-118.165419,33.806092],"type":"Point"}
}