{
  "type": "Feature",
  "properties": {
    "iso:country":"US",
    "sg:address":"18525 Sutter Blvd",
    "sg:city":"Morgan Hill",
    "sg:classifiers":[
        {
            "category":"Real Estate",
            "subcategory":"Developer",
            "type":"Services"
        }
    ],
    "sg:phone":"+1 408 776 1041",
    "sg:postcode":"95037",
    "sg:province":"CA",
    "wof:name":"Archdesign Inc",
    "wof:placetype":"venue"
},
  "geometry": {"coordinates":[-121.653937,37.146742],"type":"Point"}
}