{
  "type": "Feature",
  "properties": {
    "iso:country":"US",
    "sg:address":"9089 Foothills Blvd",
    "sg:city":"Roseville",
    "sg:classifiers":[
        {
            "category":"Insurance",
            "subcategory":"Insurance Agent",
            "type":"Services"
        }
    ],
    "sg:phone":"+1 916 789 9600",
    "sg:postcode":"95747",
    "sg:province":"CA",
    "wof:name":"Foothill Insurance Svc Inc",
    "wof:placetype":"venue"
},
  "geometry": {"coordinates":[-121.31377999999999,38.777751],"type":"Point"}
}