{
  "type": "Feature",
  "properties": {
    "addr:full":"3214 Durahart St Riverside CA 92507",
    "addr:housenumber":"3214",
    "addr:postcode":"92507",
    "addr:street":"Durahart St",
    "iso:country":"US",
    "sg:address":"3214 Durahart St",
    "sg:city":"Riverside",
    "sg:classifiers":[
        {
            "category":"Professional",
            "subcategory":"Advertising",
            "type":"Services"
        }
    ],
    "sg:phone":"+1 951 369 9588",
    "sg:postcode":"92507",
    "sg:province":"CA",
    "sg:tags":[
        "distribution"
    ],
    "wof:name":"Envisioned Technologies Inc",
    "wof:placetype":"venue"
},
  "geometry": {"coordinates":[-117.34979,33.985878],"type":"Point"}
}