{
  "type": "Feature",
  "properties": {
    "iso:country":"US",
    "sg:address":"215 Barber Ct",
    "sg:city":"Milpitas",
    "sg:classifiers":[
        {
            "category":"Travel",
            "subcategory":"Hotels & Motels",
            "type":"Entertainment"
        }
    ],
    "sg:phone":"+1 408 428 9090",
    "sg:postcode":"95035",
    "sg:province":"CA",
    "sg:tags":[
        "corporate",
        "lodging"
    ],
    "sg:website":"www.hamptoninn.com",
    "wof:name":"Hampton Inn",
    "wof:placetype":"venue"
},
  "geometry": {"coordinates":[-121.918999,37.423698],"type":"Point"}
}