{
  "type": "Feature",
  "properties": {
    "addr:full":"2275 Redondo Ave Nu Image Now Wellness Center Signal Hill CA 90755",
    "addr:housenumber":"2275",
    "addr:postcode":"90755",
    "addr:street":"Redondo Ave",
    "iso:country":"US",
    "sg:address":"2275 Redondo Ave Nu Image Now Wellness Center",
    "sg:city":"Signal Hill",
    "sg:classifiers":[
        {
            "category":"Personal",
            "subcategory":"Massage",
            "type":"Services"
        },
        {
            "category":"Health Services",
            "subcategory":"Health Practitioner",
            "type":"Services"
        },
        {
            "category":"Health Services",
            "subcategory":"Chiropractor",
            "type":"Services"
        }
    ],
    "sg:phone":"+1 562 938 7665",
    "sg:postcode":"90755",
    "sg:province":"CA",
    "sg:tags":[
        "therapy",
        "physical"
    ],
    "sg:website":"www.nuimagenow.com",
    "wof:name":"Brian Hiroshi Lum, DC",
    "wof:placetype":"venue"
},
  "geometry": {"coordinates":[-118.151962,33.798026],"type":"Point"}
}