{
  "type": "Feature",
  "properties": {
    "addr:full":"3481 Airport Dr Torrance CA 90505",
    "addr:housenumber":"3481",
    "addr:postcode":"90505",
    "addr:street":"Airport Dr",
    "iso:country":"US",
    "sg:address":"3481 Airport Dr",
    "sg:city":"Torrance",
    "sg:classifiers":[
        {
            "category":"Education",
            "subcategory":"Special Training",
            "type":"Public Place"
        }
    ],
    "sg:phone":"+1 310 539 8565",
    "sg:postcode":"90505",
    "sg:province":"CA",
    "sg:tags":[
        "aircraft",
        "school"
    ],
    "wof:name":"Pacific Coast Helicopters",
    "wof:placetype":"venue"
},
  "geometry": {"coordinates":[-118.343897,33.801963],"type":"Point"}
}