{
  "type": "Feature",
  "properties": {
    "iso:country":"US",
    "sg:address":"316 E Manchester Blvd",
    "sg:city":"Inglewood",
    "sg:classifiers":[
        {
            "category":"Wholesale",
            "subcategory":"Medical Equipment & Supplies",
            "type":"Manufacturing & Wholesale Goods"
        }
    ],
    "sg:phone":"+1 310 330 7636",
    "sg:postcode":"90301",
    "sg:province":"CA",
    "sg:tags":[
        "physician",
        "surgeon",
        "care",
        "health",
        "home"
    ],
    "wof:name":"Confidence First Medical Supplies",
    "wof:placetype":"venue"
},
  "geometry": {"coordinates":[-118.35115500000001,33.961789],"type":"Point"}
}