{
  "type": "Feature",
  "properties": {
    "addr:full":"24080 Outrigger Dr Canyon Lake CA 92587",
    "addr:housenumber":"24080",
    "addr:postcode":"92587",
    "addr:street":"Outrigger Dr",
    "iso:country":"US",
    "sg:address":"24080 Outrigger Dr",
    "sg:city":"Canyon Lake",
    "sg:classifiers":[
        {
            "category":"Health Services",
            "subcategory":"Chiropractor",
            "type":"Services"
        }
    ],
    "sg:phone":"+1 951 674 4995",
    "sg:postcode":"92587",
    "sg:province":"CA",
    "wof:name":"Tri-Lakes Chiropractic",
    "wof:placetype":"venue"
},
  "geometry": {"coordinates":[-117.24085100000001,33.686156],"type":"Point"}
}