{
  "type": "Feature",
  "properties": {
    "addr:full":"190 Martha St Studio H San Jose CA 95112",
    "addr:housenumber":"190",
    "addr:postcode":"95112",
    "addr:street":"Martha St",
    "iso:country":"US",
    "sg:address":"190 Martha St Studio H",
    "sg:city":"San Jose",
    "sg:classifiers":[
        {
            "category":"Arts & Performance",
            "subcategory":"Arts Center",
            "type":"Entertainment"
        }
    ],
    "sg:phone":"+1 408 410 3229",
    "sg:postcode":"95112",
    "sg:province":"CA",
    "sg:website":"soilstudios.com/",
    "wof:name":"SOIL Creative Studios",
    "wof:placetype":"venue"
},
  "geometry": {"coordinates":[-121.876599,37.324297],"type":"Point"}
}