{
  "type": "Feature",
  "properties": {
    "addr:full":"300 J St Apt 57 Davis CA 95616",
    "addr:housenumber":"300;57",
    "addr:postcode":"95616",
    "addr:street":"J St Apt",
    "iso:country":"US",
    "sg:address":"300 J St Apt 57",
    "sg:city":"Davis",
    "sg:classifiers":[
        {
            "category":"Real Estate",
            "subcategory":"Real Estate Services",
            "type":"Services"
        },
        {
            "category":"Real Estate",
            "subcategory":"Real Estate Operator",
            "type":"Services"
        }
    ],
    "sg:phone":"+1 530 753 3408",
    "sg:postcode":"95616",
    "sg:province":"CA",
    "sg:tags":[
        "vacancy",
        "apartment",
        "rental",
        "listing"
    ],
    "wof:name":"University Square Apts",
    "wof:placetype":"venue"
},
  "geometry": {"coordinates":[-121.73590900000001,38.545502],"type":"Point"}
}