{
  "type": "Feature",
  "properties": {
    "iso:country":"US",
    "sg:address":"5755 Westminster Blvd",
    "sg:city":"Westminster",
    "sg:classifiers":[
        {
            "category":"Travel",
            "subcategory":"Hotels & Motels",
            "type":"Entertainment"
        }
    ],
    "sg:phone":"+1 714 898 4043",
    "sg:postcode":"92683",
    "sg:province":"CA",
    "sg:tags":[
        "lodging"
    ],
    "sg:website":"www.bestwesternwestminsterinn.com/",
    "wof:name":"Best Western Westminster Inn",
    "wof:placetype":"venue"
},
  "geometry": {"coordinates":[-118.028999,33.759102],"type":"Point"}
}