{
  "type": "Feature",
  "properties": {
    "addr:full":"24405 Chestnut St Newhall CA 91321",
    "addr:housenumber":"24405",
    "addr:postcode":"91321",
    "addr:street":"Chestnut St",
    "iso:country":"US",
    "sg:address":"24405 Chestnut St",
    "sg:city":"Newhall",
    "sg:classifiers":[
        {
            "category":"Banks & Credit Unions",
            "subcategory":"Bank",
            "type":"Services"
        }
    ],
    "sg:phone":"+1 661 255 7670",
    "sg:postcode":"91321",
    "sg:province":"CA",
    "sg:tags":[
        "loan",
        "real estate"
    ],
    "wof:name":"Pacific View Mtg & Real Est",
    "wof:placetype":"venue"
},
  "geometry": {"coordinates":[-118.531228,34.379536],"type":"Point"}
}