{
  "type": "Feature",
  "properties": {
    "iso:country":"US",
    "sg:address":"100 E Tujunga Ave",
    "sg:city":"Burbank",
    "sg:classifiers":[
        {
            "category":"Insurance",
            "subcategory":"Insurance Agent",
            "type":"Services"
        }
    ],
    "sg:phone":"+1 818 846 5297",
    "sg:postcode":"91502",
    "sg:province":"CA",
    "wof:name":"California Indemnity Insurance",
    "wof:placetype":"venue"
},
  "geometry": {"coordinates":[-118.30673,34.179373],"type":"Point"}
}