{
  "type": "Feature",
  "properties": {
    "iso:country":"US",
    "sg:address":"49 Natoma St",
    "sg:city":"Folsom",
    "sg:classifiers":[
        {
            "category":"Professional",
            "subcategory":"Lawyer & Legal Services",
            "type":"Services"
        }
    ],
    "sg:phone":"+1 916 985 2753",
    "sg:postcode":"95630",
    "sg:province":"CA",
    "sg:tags":[
        "attorney"
    ],
    "sg:website":"www.hoffmanandhoffman.com",
    "wof:name":"Hoffman & Hoffman",
    "wof:placetype":"venue"
},
  "geometry": {"coordinates":[-121.163189,38.681552],"type":"Point"}
}