{
  "type": "Feature",
  "properties": {
    "iso:country":"US",
    "sg:address":"226 N Palm Canyon Dr",
    "sg:city":"Palm Springs",
    "sg:classifiers":[
        {
            "category":"Personal",
            "subcategory":"Piercing",
            "type":"Services"
        }
    ],
    "sg:phone":"+1 760 323 4252",
    "sg:postcode":"92262",
    "sg:province":"CA",
    "sg:tags":[
        "body"
    ],
    "wof:name":"Fit To Be Tyed",
    "wof:placetype":"venue"
},
  "geometry": {"coordinates":[-116.546997,33.825401],"type":"Point"}
}