{
  "type": "Feature",
  "properties": {
    "iso:country":"US",
    "sg:address":"909 Montgomery St",
    "sg:city":"San Francisco",
    "sg:classifiers":[
        {
            "category":"Professional",
            "subcategory":"Business Services",
            "type":"Services"
        }
    ],
    "sg:phone":"+1 415 982 6015",
    "sg:postcode":"94133",
    "sg:province":"CA",
    "sg:tags":[
        "interior",
        "consultant",
        "design",
        "decorator"
    ],
    "wof:name":"Aston Pereira & Assoc",
    "wof:placetype":"venue"
},
  "geometry": {"coordinates":[-122.40385999999999,37.797816],"type":"Point"}
}