{
  "type": "Feature",
  "properties": {
    "addr:full":"1217 England St Huntington Beach CA 92648",
    "addr:housenumber":"1217",
    "addr:postcode":"92648",
    "addr:street":"England St",
    "iso:country":"US",
    "sg:address":"1217 England St",
    "sg:city":"Huntington Beach",
    "sg:classifiers":[
        {
            "category":"Manufacturing",
            "subcategory":"Toys & Sporting Goods",
            "type":"Manufacturing & Wholesale Goods"
        }
    ],
    "sg:phone":"+1 714 342 2331",
    "sg:postcode":"92648",
    "sg:province":"CA",
    "sg:tags":[
        "mfg"
    ],
    "wof:name":"Urban Dummy",
    "wof:placetype":"venue"
},
  "geometry": {"coordinates":[-117.991895,33.668383],"type":"Point"}
}