{
  "type": "Feature",
  "properties": {
    "addr:full":"11719 Moorpark St Studio City CA 91604",
    "addr:housenumber":"11719",
    "addr:postcode":"91604",
    "addr:street":"Moorpark St",
    "iso:country":"US",
    "sg:address":"11719 Moorpark St",
    "sg:city":"Studio City",
    "sg:classifiers":[
        {
            "category":"Organizations",
            "subcategory":"Political Organization",
            "type":"Services"
        }
    ],
    "sg:phone":"+1 818 623 0555",
    "sg:postcode":"91604",
    "sg:province":"CA",
    "wof:name":"Armenian Cultural Foundation",
    "wof:placetype":"venue"
},
  "geometry": {"coordinates":[-118.388261,34.150442],"type":"Point"}
}