{
  "type": "Feature",
  "properties": {
    "addr:full":"789 Valley Rd Arroyo Grande CA 93420",
    "addr:housenumber":"789",
    "addr:postcode":"93420",
    "addr:street":"Valley Rd",
    "iso:country":"US",
    "sg:address":"789 Valley Rd",
    "sg:city":"Arroyo Grande",
    "sg:classifiers":[
        {
            "category":"Organizations",
            "subcategory":"Religious Organization",
            "type":"Services"
        }
    ],
    "sg:phone":"+1 805 481 1335",
    "sg:postcode":"93420",
    "sg:province":"CA",
    "sg:tags":[
        "church"
    ],
    "wof:name":"Unity Church-Five Cities",
    "wof:placetype":"venue"
},
  "geometry": {"coordinates":[-120.581418,35.106095],"type":"Point"}
}