{
  "type": "Feature",
  "properties": {
    "iso:country":"US",
    "sg:address":"13440 Crowley St",
    "sg:city":"Panorama City",
    "sg:classifiers":[
        {
            "category":"Wholesale",
            "subcategory":"Non-durable Goods",
            "type":"Manufacturing & Wholesale Goods"
        }
    ],
    "sg:phone":"+1 818 786 4606",
    "sg:postcode":"91402",
    "sg:province":"CA",
    "wof:name":"Happy Frog",
    "wof:placetype":"venue"
},
  "geometry": {"coordinates":[-118.42652,34.225014],"type":"Point"}
}