{
  "type": "Feature",
  "properties": {
    "addr:full":"2238 Truckee Dr Santa Rosa CA 95401",
    "addr:housenumber":"2238",
    "addr:postcode":"95401",
    "addr:street":"Truckee Dr",
    "iso:country":"US",
    "sg:address":"2238 Truckee Dr",
    "sg:city":"Santa Rosa",
    "sg:classifiers":[
        {
            "category":"Shopping",
            "subcategory":"Hobbies, Toys, & Games",
            "type":"Retail Goods"
        }
    ],
    "sg:phone":"+1 707 526 0445",
    "sg:postcode":"95401",
    "sg:province":"CA",
    "wof:name":"Toys Like New",
    "wof:placetype":"venue"
},
  "geometry": {"coordinates":[-122.758241,38.444692],"type":"Point"}
}