{
  "type": "Feature",
  "properties": {
    "addr:full":"12921 Crenshaw Blvd Hawthorne CA 90250",
    "addr:housenumber":"12921",
    "addr:postcode":"90250",
    "addr:street":"Crenshaw Blvd",
    "iso:country":"US",
    "sg:address":"12921 Crenshaw Blvd",
    "sg:city":"Hawthorne",
    "sg:classifiers":[
        {
            "category":"Freight",
            "type":"Transportation"
        }
    ],
    "sg:phone":"+1 310 355 1890",
    "sg:postcode":"90250",
    "sg:province":"CA",
    "sg:tags":[
        "cargo",
        "containerized",
        "arrangement"
    ],
    "wof:name":"Evergreen Aviation Ground Logi",
    "wof:placetype":"venue"
},
  "geometry": {"coordinates":[-118.326578,33.91373],"type":"Point"}
}