{
  "type": "Feature",
  "properties": {
    "addr:full":"1214 E L St Wilmington CA 90744",
    "addr:housenumber":"1214",
    "addr:postcode":"90744",
    "addr:street":"E L St",
    "iso:country":"US",
    "sg:address":"1214 E L St",
    "sg:city":"Wilmington",
    "sg:classifiers":[
        {
            "category":"Food & Beverages",
            "subcategory":"Groceries & Convenience Stores",
            "type":"Retail Goods"
        }
    ],
    "sg:phone":"+1 310 830 8070",
    "sg:postcode":"90744",
    "sg:province":"CA",
    "wof:name":"Amigo Market",
    "wof:placetype":"venue"
},
  "geometry": {"coordinates":[-118.248001,33.787399],"type":"Point"}
}