{
  "type": "Feature",
  "properties": {
    "addr:full":"419 Stonewood St Downey CA 90241",
    "addr:housenumber":"419",
    "addr:postcode":"90241",
    "addr:street":"Stonewood St",
    "iso:country":"US",
    "sg:address":"419 Stonewood St",
    "sg:city":"Downey",
    "sg:classifiers":[
        {
            "category":"Personal",
            "subcategory":"Beauty Salon",
            "type":"Services"
        }
    ],
    "sg:phone":"+1 562 861 5515",
    "sg:postcode":"90241",
    "sg:province":"CA",
    "wof:name":"Blooming Beauty",
    "wof:placetype":"venue"
},
  "geometry": {"coordinates":[-118.12252100000001,33.937133],"type":"Point"}
}