{
  "type": "Feature",
  "properties": {
    "iso:country":"US",
    "sg:address":"24806 N Kennefick Rd",
    "sg:city":"Galt",
    "sg:classifiers":[
        {
            "category":"Retail",
            "subcategory":"Veterinary Services",
            "type":"Services"
        }
    ],
    "sg:phone":"+1 209 334 1660",
    "sg:postcode":"95632",
    "sg:province":"CA",
    "wof:name":"Linda Lauper Dvm",
    "wof:placetype":"venue"
},
  "geometry": {"coordinates":[-121.244867,38.218119],"type":"Point"}
}