{
  "type": "Feature",
  "properties": {
    "addr:full":"1518 Solano St Corning CA 96021",
    "addr:housenumber":"1518",
    "addr:postcode":"96021",
    "addr:street":"Solano St",
    "iso:country":"US",
    "sg:address":"1518 Solano St",
    "sg:city":"Corning",
    "sg:classifiers":[
        {
            "category":"Health Services",
            "subcategory":"Chiropractor",
            "type":"Services"
        }
    ],
    "sg:phone":"+1 530 824 2448",
    "sg:postcode":"96021",
    "sg:province":"CA",
    "wof:name":"Corning Chiropractic Office",
    "wof:placetype":"venue"
},
  "geometry": {"coordinates":[-122.186689,39.927981],"type":"Point"}
}