{
  "type": "Feature",
  "properties": {
    "iso:country":"US",
    "sg:address":"11246 Pepperview Ter",
    "sg:city":"San Diego",
    "sg:classifiers":[
        {
            "category":"Shopping",
            "subcategory":"Catalog Store",
            "type":"Retail Goods"
        }
    ],
    "sg:phone":"+1 858 578 6625",
    "sg:postcode":"92131",
    "sg:province":"CA",
    "sg:tags":[
        "mail",
        "house"
    ],
    "wof:name":"The Dragon Fairies",
    "wof:placetype":"venue"
},
  "geometry": {"coordinates":[-117.075981,32.92388],"type":"Point"}
}