{
  "type": "Feature",
  "properties": {
    "addr:full":"10841 N Wolfe Rd Cupertino CA 95014",
    "addr:housenumber":"10841",
    "addr:postcode":"95014",
    "addr:street":"N Wolfe Rd",
    "iso:country":"US",
    "sg:address":"10841 N Wolfe Rd",
    "sg:city":"Cupertino",
    "sg:classifiers":[
        {
            "category":"Personal",
            "subcategory":"Beauty Salon",
            "type":"Services"
        }
    ],
    "sg:phone":"+1 408 252 1223",
    "sg:postcode":"95014",
    "sg:province":"CA",
    "wof:name":"Hair Experience",
    "wof:placetype":"venue"
},
  "geometry": {"coordinates":[-122.014231,37.334513],"type":"Point"}
}