{
  "type": "Feature",
  "properties": {
    "addr:full":"676 W Wilson Ave Ste K Glendale CA 91203",
    "addr:housenumber":"676",
    "addr:postcode":"91203",
    "addr:street":"W Wilson Ave Ste K",
    "iso:country":"US",
    "sg:address":"676 W Wilson Ave Ste K",
    "sg:city":"Glendale",
    "sg:classifiers":[
        {
            "category":"Wholesale",
            "subcategory":"Computers",
            "type":"Manufacturing & Wholesale Goods"
        },
        {
            "category":"Professional",
            "subcategory":"Computer Services",
            "type":"Services"
        }
    ],
    "sg:phone":"+1 818 246 4915",
    "sg:postcode":"91203",
    "sg:province":"CA",
    "sg:tags":[
        "repair"
    ],
    "wof:name":"Verdugo Systems & Intergration Inc",
    "wof:placetype":"venue"
},
  "geometry": {"coordinates":[-118.269683,34.147633],"type":"Point"}
}