{
  "type": "Feature",
  "properties": {
    "iso:country":"US",
    "sg:address":"871 Silver Spur Rd",
    "sg:city":"Rolling Hls Ests",
    "sg:classifiers":[
        {
            "category":"Restaurant",
            "type":"Food & Drink"
        }
    ],
    "sg:phone":"+1 310 265 0115",
    "sg:postcode":"90274",
    "sg:province":"CA",
    "wof:name":"Town & Country Pizza",
    "wof:placetype":"venue"
},
  "geometry": {"coordinates":[-118.37058,33.771273],"type":"Point"}
}