{
  "type": "Feature",
  "properties": {
    "addr:full":"1274 Auto Park Way Escondido CA 92029",
    "addr:housenumber":"1274",
    "addr:postcode":"92029",
    "addr:street":"Auto Park Way",
    "iso:country":"US",
    "sg:address":"1274 Auto Park Way",
    "sg:city":"Escondido",
    "sg:classifiers":[
        {
            "category":"Shopping",
            "subcategory":"Clothing, Apparel, & Fashions",
            "type":"Retail Goods"
        },
        {
            "category":"Shopping",
            "subcategory":"Department Store",
            "type":"Retail Goods"
        },
        {
            "category":"Shopping",
            "subcategory":"Discount & Variety Stores",
            "type":"Retail Goods"
        }
    ],
    "sg:phone":"+1 760 746 9528",
    "sg:postcode":"92029",
    "sg:province":"CA",
    "sg:tags":[
        "apparel",
        "clothing",
        "women's"
    ],
    "sg:website":"http://www.tjmaxx.com",
    "wof:name":"Tj Maxx",
    "wof:placetype":"venue"
},
  "geometry": {"coordinates":[-117.09971899999999,33.111842],"type":"Point"}
}