{
  "type": "Feature",
  "properties": {
    "iso:country":"US",
    "sg:address":"2121 Dogwood Rd",
    "sg:city":"El Centro",
    "sg:classifiers":[
        {
            "category":"Wholesale",
            "subcategory":"Fruits & Vegetables",
            "type":"Manufacturing & Wholesale Goods"
        }
    ],
    "sg:phone":"+1 760 353 5645",
    "sg:postcode":"92243",
    "sg:province":"CA",
    "sg:tags":[
        "shipper"
    ],
    "wof:name":"Bonanza Farms Inc",
    "wof:placetype":"venue"
},
  "geometry": {"coordinates":[-115.535761,32.806542],"type":"Point"}
}