{
  "type": "Feature",
  "properties": {
    "addr:full":"5324 Baldwin Ave Apt 1 Temple City CA 91780",
    "addr:housenumber":"5324;1",
    "addr:postcode":"91780",
    "addr:street":"Baldwin Ave Apt",
    "iso:country":"US",
    "sg:address":"5324 Baldwin Ave Apt 1",
    "sg:city":"Temple City",
    "sg:classifiers":[
        {
            "category":"Real Estate",
            "subcategory":"Real Estate Operator",
            "type":"Services"
        }
    ],
    "sg:phone":"+1 626 442 1176",
    "sg:postcode":"91780",
    "sg:province":"CA",
    "sg:tags":[
        "apartment"
    ],
    "wof:name":"Baldwin Arms Apartments",
    "wof:placetype":"venue"
},
  "geometry": {"coordinates":[-118.050003,34.098301],"type":"Point"}
}