{
  "type": "Feature",
  "properties": {
    "addr:full":"915 S Alvarado St Los Angeles CA 90006",
    "addr:housenumber":"915",
    "addr:postcode":"90006",
    "addr:street":"S Alvarado St",
    "iso:country":"US",
    "sg:address":"915 S Alvarado St",
    "sg:city":"Los Angeles",
    "sg:classifiers":[
        {
            "category":"Home & Garden",
            "subcategory":"Hardware",
            "type":"Retail Goods"
        }
    ],
    "sg:phone":"+1 213 382 1305",
    "sg:postcode":"90006",
    "sg:province":"CA",
    "sg:tags":[
        "store"
    ],
    "sg:website":"www.acehardware.com",
    "wof:name":"Alvarado Paint & Hardware",
    "wof:placetype":"venue"
},
  "geometry": {"coordinates":[-118.279999,34.051899],"type":"Point"}
}