{
  "type": "Feature",
  "properties": {
    "iso:country":"US",
    "sg:address":"22821 Fortuna Ln",
    "sg:city":"Mission Viejo",
    "sg:classifiers":[
        {
            "category":"Building & Trades",
            "subcategory":"Electrical",
            "type":"Services"
        }
    ],
    "sg:phone":"+1 949 770 9523",
    "sg:postcode":"92691",
    "sg:province":"CA",
    "sg:tags":[
        "electrical",
        "contractor"
    ],
    "wof:name":"S & S Electrical Contractors",
    "wof:placetype":"venue"
},
  "geometry": {"coordinates":[-117.672269,33.631102],"type":"Point"}
}