{
  "type": "Feature",
  "properties": {
    "iso:country":"US",
    "sg:address":"10643 Norwalk Blvd",
    "sg:city":"Santa Fe Springs",
    "sg:classifiers":[
        {
            "category":"Manufacturing",
            "subcategory":"Metals",
            "type":"Manufacturing & Wholesale Goods"
        }
    ],
    "sg:phone":"+1 562 944 8808",
    "sg:postcode":"90670",
    "sg:province":"CA",
    "sg:tags":[
        "treating",
        "heat"
    ],
    "wof:name":"Continental Heat Treating Inc",
    "wof:placetype":"venue"
},
  "geometry": {"coordinates":[-118.072686,33.935383],"type":"Point"}
}