{
  "type": "Feature",
  "properties": {
    "iso:country":"US",
    "sg:address":"2708 E 1st Street",
    "sg:city":"Los Angeles",
    "sg:classifiers":[
        {
            "category":"Shopping",
            "subcategory":"Jewelry",
            "type":"Retail Goods"
        }
    ],
    "sg:phone":"+1 323 981 0168",
    "sg:postcode":"90033",
    "sg:province":"CA",
    "wof:name":"Don Roberto Jewelers",
    "wof:placetype":"venue"
},
  "geometry": {"coordinates":[-118.204771,34.041366],"type":"Point"}
}