{
  "type": "Feature",
  "properties": {
    "addr:full":"7915 Haskell Ave Van Nuys CA 91406",
    "addr:housenumber":"7915",
    "addr:postcode":"91406",
    "addr:street":"Haskell Ave",
    "iso:country":"US",
    "sg:address":"7915 Haskell Ave",
    "sg:city":"Van Nuys",
    "sg:classifiers":[
        {
            "category":"Manufacturing",
            "subcategory":"Apparel",
            "type":"Manufacturing & Wholesale Goods"
        }
    ],
    "sg:phone":"+1 818 782 7568",
    "sg:postcode":"91406",
    "sg:province":"CA",
    "sg:tags":[
        "brassiere"
    ],
    "wof:name":"Olga Warnaco Co",
    "wof:placetype":"venue"
},
  "geometry": {"coordinates":[-118.475014,34.215458],"type":"Point"}
}