{
  "type": "Feature",
  "properties": {
    "addr:full":"2093 Mission St San Francisco CA 94110",
    "addr:housenumber":"2093",
    "addr:postcode":"94110",
    "addr:street":"Mission St",
    "iso:country":"US",
    "sg:address":"2093 Mission St",
    "sg:city":"San Francisco",
    "sg:classifiers":[
        {
            "category":"Personal",
            "subcategory":"Beauty Salon",
            "type":"Services"
        }
    ],
    "sg:phone":"+1 415 621 5359",
    "sg:postcode":"94110",
    "sg:province":"CA",
    "wof:name":"Ernesto's Hair Salon",
    "wof:placetype":"venue"
},
  "geometry": {"coordinates":[-122.41955400000001,37.764957],"type":"Point"}
}