{
  "type": "Feature",
  "properties": {
    "addr:full":"806 N Broadway Santa Ana CA 92701",
    "addr:housenumber":"806",
    "addr:postcode":"92701",
    "addr:street":"N Broadway",
    "iso:country":"US",
    "sg:address":"806 N Broadway",
    "sg:city":"Santa Ana",
    "sg:classifiers":[
        {
            "category":"Professional",
            "subcategory":"Lawyer & Legal Services",
            "type":"Services"
        }
    ],
    "sg:phone":"+1 714 835 1371",
    "sg:postcode":"92701",
    "sg:province":"CA",
    "sg:website":"www.sheldondavis.com",
    "wof:name":"Davis Sheldon Atty",
    "wof:placetype":"venue"
},
  "geometry": {"coordinates":[-117.870003,33.7523],"type":"Point"}
}