{
  "type": "Feature",
  "properties": {
    "addr:full":"1544 Purdue Ave Los Angeles CA 90025",
    "addr:housenumber":"1544",
    "addr:postcode":"90025",
    "addr:street":"Purdue Ave",
    "iso:country":"US",
    "sg:address":"1544 Purdue Ave",
    "sg:city":"Los Angeles",
    "sg:classifiers":[
        {
            "category":"Shopping",
            "type":"Retail Goods"
        }
    ],
    "sg:phone":"+1 310 477 9090",
    "sg:postcode":"90025",
    "sg:province":"CA",
    "sg:tags":[
        "picture",
        "frame"
    ],
    "wof:name":"Randolph Laub Studio",
    "wof:placetype":"venue"
},
  "geometry": {"coordinates":[-118.451126,34.046505],"type":"Point"}
}