{
  "type": "Feature",
  "properties": {
    "iso:country":"US",
    "sg:address":"805 S Gaffey St",
    "sg:city":"San Pedro",
    "sg:classifiers":[
        {
            "category":"Professional",
            "subcategory":"Lawyer & Legal Services",
            "type":"Services"
        }
    ],
    "sg:phone":"+1 310 833 5344",
    "sg:postcode":"90731",
    "sg:province":"CA",
    "sg:tags":[
        "attorney"
    ],
    "wof:name":"Peter Larkin Law Offices",
    "wof:placetype":"venue"
},
  "geometry": {"coordinates":[-118.292406,33.737771],"type":"Point"}
}