{
  "type": "Feature",
  "properties": {
    "iso:country":"US",
    "sg:address":"881 el Dorado St",
    "sg:city":"Chico",
    "sg:classifiers":[
        {
            "category":"Manufacturing",
            "subcategory":"Chemicals & Compounds",
            "type":"Manufacturing & Wholesale Goods"
        }
    ],
    "sg:phone":"+1 530 899 1660",
    "sg:postcode":"95928",
    "sg:province":"CA",
    "sg:tags":[
        "industrial",
        "organic"
    ],
    "wof:name":"Sulharai Organic",
    "wof:placetype":"venue"
},
  "geometry": {"coordinates":[-121.81165799999999,39.741653],"type":"Point"}
}