{
  "type": "Feature",
  "properties": {
    "iso:country":"US",
    "sg:address":"4457 Sacramento Ave",
    "sg:city":"Fremont",
    "sg:classifiers":[
        {
            "category":"Shopping",
            "subcategory":"Music",
            "type":"Retail Goods"
        }
    ],
    "sg:phone":"+1 510 979 9784",
    "sg:postcode":"94538",
    "sg:province":"CA",
    "sg:tags":[
        "compact",
        "record",
        "disc",
        "tape"
    ],
    "wof:name":"Sonika Records",
    "wof:placetype":"venue"
},
  "geometry": {"coordinates":[-121.989915,37.54177],"type":"Point"}
}