{
  "type": "Feature",
  "properties": {
    "addr:full":"2018 Shattuck Ave Berkeley CA 94704",
    "addr:housenumber":"2018",
    "addr:postcode":"94704",
    "addr:street":"Shattuck Ave",
    "iso:country":"US",
    "sg:address":"2018 Shattuck Ave",
    "sg:city":"Berkeley",
    "sg:classifiers":[
        {
            "category":"Arts & Performance",
            "subcategory":"Theater",
            "type":"Entertainment"
        }
    ],
    "sg:phone":"+1 510 612 3686",
    "sg:postcode":"94704",
    "sg:province":"CA",
    "sg:tags":[
        "live",
        "music",
        "wedding"
    ],
    "wof:name":"Dance Beat",
    "wof:placetype":"venue"
},
  "geometry": {"coordinates":[-122.268367,37.871951],"type":"Point"}
}