{
  "type": "Feature",
  "properties": {
    "iso:country":"US",
    "sg:address":"105 Wessex Way",
    "sg:city":"Folsom",
    "sg:classifiers":[
        {
            "category":"Professional",
            "type":"Services"
        }
    ],
    "sg:phone":"+1 916 984 8922",
    "sg:postcode":"95630",
    "sg:province":"CA",
    "wof:name":"Life Ties",
    "wof:placetype":"venue"
},
  "geometry": {"coordinates":[-121.141508,38.660419],"type":"Point"}
}