{
  "type": "Feature",
  "properties": {
    "iso:country":"US",
    "sg:address":"1778 Mitchell Rd Ste 209",
    "sg:city":"Ceres",
    "sg:classifiers":[
        {
            "category":"Shopping",
            "subcategory":"Clothing, Apparel, & Fashions",
            "type":"Retail Goods"
        }
    ],
    "sg:phone":"+1 209 537 5370",
    "sg:postcode":"95307",
    "sg:province":"CA",
    "sg:tags":[
        "accessory",
        "clothing",
        "women's"
    ],
    "wof:name":"Affection Clothing",
    "wof:placetype":"venue"
},
  "geometry": {"coordinates":[-120.93847599999999,37.603408],"type":"Point"}
}