{
  "type": "Feature",
  "properties": {
    "addr:full":"577 Geary St San Francisco CA 94102",
    "addr:housenumber":"577",
    "addr:postcode":"94102",
    "addr:street":"Geary St",
    "iso:country":"US",
    "sg:address":"577 Geary St",
    "sg:city":"San Francisco",
    "sg:classifiers":[
        {
            "category":"Shopping",
            "type":"Retail Goods"
        }
    ],
    "sg:phone":"+1 415 674 9500",
    "sg:postcode":"94102",
    "sg:province":"CA",
    "sg:tags":[
        "art",
        "gallery",
        "dealer"
    ],
    "wof:name":"Lee Gallery",
    "wof:placetype":"venue"
},
  "geometry": {"coordinates":[-122.412746,37.786721],"type":"Point"}
}