{
  "type": "Feature",
  "properties": {
    "addr:full":"149 E Virginia St San Jose CA 95112",
    "addr:housenumber":"149",
    "addr:postcode":"95112",
    "addr:street":"E Virginia St",
    "iso:country":"US",
    "sg:address":"149 E Virginia St",
    "sg:city":"San Jose",
    "sg:classifiers":[
        {
            "category":"Shopping",
            "type":"Retail Goods"
        }
    ],
    "sg:phone":"+1 408 280 6398",
    "sg:postcode":"95112",
    "sg:province":"CA",
    "sg:tags":[
        "auto",
        "used",
        "general",
        "merchandise",
        "repair"
    ],
    "wof:name":"Wonda Engine",
    "wof:placetype":"venue"
},
  "geometry": {"coordinates":[-121.87832899999999,37.325589],"type":"Point"}
}