{
  "type": "Feature",
  "properties": {
    "addr:full":"445 W Beach St Watsonville CA 95076",
    "addr:housenumber":"445",
    "addr:postcode":"95076",
    "addr:street":"W Beach St",
    "iso:country":"US",
    "sg:address":"445 W Beach St",
    "sg:city":"Watsonville",
    "sg:classifiers":[
        {
            "category":"Building & Trades",
            "subcategory":"Construction",
            "type":"Services"
        }
    ],
    "sg:phone":"+1 831 768 8060",
    "sg:postcode":"95076",
    "sg:province":"CA",
    "sg:tags":[
        "fabricator",
        "metal"
    ],
    "wof:name":"Pajaro Valley Fabrication",
    "wof:placetype":"venue"
},
  "geometry": {"coordinates":[-121.763651,36.907031],"type":"Point"}
}