{
  "type": "Feature",
  "properties": {
    "iso:country":"US",
    "sg:address":"632 San Mateo Ave",
    "sg:city":"San Bruno",
    "sg:classifiers":[
        {
            "category":"Restaurant",
            "type":"Food & Drink"
        },
        {
            "category":"Food & Beverages",
            "subcategory":"Groceries & Convenience Stores",
            "type":"Retail Goods"
        }
    ],
    "sg:phone":"+1 650 794 1290",
    "sg:postcode":"94066",
    "sg:province":"CA",
    "sg:tags":[
        "mexican"
    ],
    "wof:name":"Cuquio Produce",
    "wof:placetype":"venue"
},
  "geometry": {"coordinates":[-122.41100299999999,37.627102],"type":"Point"}
}