{
  "type": "Feature",
  "properties": {
    "iso:country":"US",
    "sg:address":"1193 Magnolia Ave",
    "sg:city":"Corona",
    "sg:classifiers":[
        {
            "category":"Food & Beverages",
            "subcategory":"Groceries & Convenience Stores",
            "type":"Retail Goods"
        }
    ],
    "sg:phone":"+1 951 736 1399",
    "sg:postcode":"92879",
    "sg:province":"CA",
    "sg:tags":[
        "supermarket"
    ],
    "wof:name":"Stater Bros Markets",
    "wof:placetype":"venue"
},
  "geometry": {"coordinates":[-117.547087,33.863186],"type":"Point"}
}