{
  "type": "Feature",
  "properties": {
    "addr:full":"5780 Market St Emeryville CA 94608",
    "addr:housenumber":"5780",
    "addr:postcode":"94608",
    "addr:street":"Market St",
    "iso:country":"US",
    "sg:address":"5780 Market St",
    "sg:city":"Emeryville",
    "sg:classifiers":[
        {
            "category":"Education",
            "subcategory":"Special Training",
            "type":"Public Place"
        }
    ],
    "sg:phone":"+1 510 653 4772",
    "sg:postcode":"94608",
    "sg:province":"CA",
    "sg:tags":[
        "self",
        "motivational",
        "improvement"
    ],
    "wof:name":"Val's Designs-Organized Pack",
    "wof:placetype":"venue"
},
  "geometry": {"coordinates":[-122.27471,37.842616],"type":"Point"}
}