{
  "type": "Feature",
  "properties": {
    "iso:country":"US",
    "sg:address":"3030 E Jackson Ave",
    "sg:city":"Anaheim",
    "sg:classifiers":[
        {
            "category":"Building & Trades",
            "subcategory":"Landscaping Services",
            "type":"Services"
        }
    ],
    "sg:phone":"+1 714 630 5312",
    "sg:postcode":"92806",
    "sg:province":"CA",
    "wof:name":"Carranza Armndo Lawn Grdn Care",
    "wof:placetype":"venue"
},
  "geometry": {"coordinates":[-117.85831,33.845174],"type":"Point"}
}