{
  "type": "Feature",
  "properties": {
    "iso:country":"US",
    "sg:address":"335 W Rialto Ave",
    "sg:city":"Rialto",
    "sg:classifiers":[
        {
            "category":"Government",
            "subcategory":"Office",
            "type":"Public Place"
        }
    ],
    "sg:phone":"+1 909 820 2608",
    "sg:postcode":"92376",
    "sg:province":"CA",
    "sg:tags":[
        "executive"
    ],
    "wof:name":"Water & Sewer Billing/New Svc",
    "wof:placetype":"venue"
},
  "geometry": {"coordinates":[-117.376057,34.099456],"type":"Point"}
}