{
  "type": "Feature",
  "properties": {
    "iso:country":"US",
    "sg:address":"1741 Torrance Blvd",
    "sg:city":"Torrance",
    "sg:classifiers":[
        {
            "category":"Wholesale",
            "subcategory":"Durable Goods & Equipment",
            "type":"Manufacturing & Wholesale Goods"
        }
    ],
    "sg:phone":"+1 310 328 6708",
    "sg:postcode":"90501",
    "sg:province":"CA",
    "sg:tags":[
        "representative",
        "manufacturer"
    ],
    "wof:name":"Associated Representatives",
    "wof:placetype":"venue"
},
  "geometry": {"coordinates":[-118.311412,33.837841],"type":"Point"}
}