{
  "type": "Feature",
  "properties": {
    "addr:full":"26295 Mace Blvd Davis CA 95618",
    "addr:housenumber":"26295",
    "addr:postcode":"95618",
    "addr:street":"Mace Blvd",
    "iso:country":"US",
    "sg:address":"26295 Mace Blvd",
    "sg:city":"Davis",
    "sg:classifiers":[
        {
            "category":"Food & Beverages",
            "subcategory":"Fruits & Vegetables",
            "type":"Retail Goods"
        }
    ],
    "sg:phone":"+1 530 750 3379",
    "sg:postcode":"95618",
    "sg:province":"CA",
    "sg:tags":[
        "produce"
    ],
    "wof:name":"Ikedas Produce Markets",
    "wof:placetype":"venue"
},
  "geometry": {"coordinates":[-121.694542,38.5289],"type":"Point"}
}