{
  "type": "Feature",
  "properties": {
    "addr:full":"John F Kennedy Dr across from the Conservatory of Flowers San Francisco CA 94117",
    "addr:postcode":"94117",
    "addr:street":"John F Kennedy Dr",
    "iso:country":"US",
    "sg:address":"John F Kennedy Dr across from the Conservatory of Flowers",
    "sg:city":"San Francisco",
    "sg:classifiers":[
        {
            "category":"Park",
            "type":"Public Place"
        }
    ],
    "sg:postcode":"94117",
    "sg:province":"CA",
    "wof:name":"Lily Pond",
    "wof:placetype":"venue"
},
  "geometry": {"coordinates":[-122.461467,37.770715],"type":"Point"}
}