{
  "type": "Feature",
  "properties": {
    "addr:full":"1849 Thunderbolt Dr Porterville CA 93257",
    "addr:housenumber":"1849",
    "addr:postcode":"93257",
    "addr:street":"Thunderbolt Dr",
    "iso:country":"US",
    "sg:address":"1849 Thunderbolt Dr",
    "sg:city":"Porterville",
    "sg:classifiers":[
        {
            "category":"Home & Garden",
            "subcategory":"Furniture",
            "type":"Retail Goods"
        }
    ],
    "sg:phone":"+1 559 782 8968",
    "sg:postcode":"93257",
    "sg:province":"CA",
    "sg:tags":[
        "builder",
        "custom"
    ],
    "wof:name":"Custom Handcrafted Furnishings",
    "wof:placetype":"venue"
},
  "geometry": {"coordinates":[-119.059273,36.030989],"type":"Point"}
}