{
  "type": "Feature",
  "properties": {
    "iso:country":"US",
    "sg:address":"4954 E Kings Canyon Rd",
    "sg:city":"Fresno",
    "sg:classifiers":[
        {
            "category":"Wholesale",
            "subcategory":"Jewelry",
            "type":"Manufacturing & Wholesale Goods"
        }
    ],
    "sg:phone":"+1 559 452 8165",
    "sg:postcode":"93727",
    "sg:province":"CA",
    "sg:tags":[
        "stone",
        "jeweler"
    ],
    "wof:name":"Marlene's Jewelry",
    "wof:placetype":"venue"
},
  "geometry": {"coordinates":[-119.72956600000001,36.735835],"type":"Point"}
}