{
  "type": "Feature",
  "properties": {
    "addr:full":"4115 Broad St San Luis Obispo CA 93401",
    "addr:housenumber":"4115",
    "addr:postcode":"93401",
    "addr:street":"Broad St",
    "iso:country":"US",
    "sg:address":"4115 Broad St",
    "sg:city":"San Luis Obispo",
    "sg:classifiers":[
        {
            "category":"Professional",
            "type":"Services"
        }
    ],
    "sg:phone":"+1 805 781 9292",
    "sg:postcode":"93401",
    "sg:province":"CA",
    "sg:tags":[
        "establishment"
    ],
    "wof:name":"KDDB",
    "wof:placetype":"venue"
},
  "geometry": {"coordinates":[-120.641086,35.244686],"type":"Point"}
}