{
  "type": "Feature",
  "properties": {
    "addr:full":"1641 Washington St. Santa Clara CA 95050",
    "addr:housenumber":"1641",
    "addr:postcode":"95050",
    "addr:street":"Washington St.",
    "iso:country":"US",
    "sg:address":"1641 Washington St.",
    "sg:city":"Santa Clara",
    "sg:classifiers":[
        {
            "category":"Building & Trades",
            "subcategory":"Electrical",
            "type":"Services"
        }
    ],
    "sg:phone":"+1 408 529 4181",
    "sg:postcode":"95050",
    "sg:province":"CA",
    "sg:tags":[
        "electrician"
    ],
    "wof:name":"GetShocked Electric",
    "wof:placetype":"venue"
},
  "geometry": {"coordinates":[-121.947625,37.355828],"type":"Point"}
}