{
  "type": "Feature",
  "properties": {
    "iso:country":"US",
    "sg:address":"2344 Derby St",
    "sg:city":"Berkeley",
    "sg:classifiers":[
        {
            "category":"Organizations",
            "subcategory":"Professional Association",
            "type":"Services"
        }
    ],
    "sg:phone":"+1 510 549 9848",
    "sg:postcode":"94705",
    "sg:province":"CA",
    "sg:tags":[
        "business",
        "trade"
    ],
    "wof:name":"International Youth Nuclear Congress",
    "wof:placetype":"venue"
},
  "geometry": {"coordinates":[-122.261235,37.861089],"type":"Point"}
}