{
  "type": "Feature",
  "properties": {
    "addr:full":"2362 Cove Ave Los Angeles CA 90039",
    "addr:housenumber":"2362",
    "addr:postcode":"90039",
    "addr:street":"Cove Ave",
    "iso:country":"US",
    "sg:address":"2362 Cove Ave",
    "sg:city":"Los Angeles",
    "sg:classifiers":[
        {
            "category":"Health Services",
            "subcategory":"Health Practitioner",
            "type":"Services"
        }
    ],
    "sg:phone":"+1 323 663 2340",
    "sg:postcode":"90039",
    "sg:province":"CA",
    "sg:tags":[
        "psychologist"
    ],
    "wof:name":"Dorothea Mc Arthur PHD",
    "wof:placetype":"venue"
},
  "geometry": {"coordinates":[-118.26044400000001,34.09487],"type":"Point"}
}