{
  "type": "Feature",
  "properties": {
    "addr:full":"722 Ventura Place San Diego CA 92109",
    "addr:housenumber":"722",
    "addr:postcode":"92109",
    "addr:street":"Ventura Place",
    "iso:country":"US",
    "sg:address":"722 Ventura Place",
    "sg:city":"San Diego",
    "sg:classifiers":[
        {
            "category":"Shopping",
            "subcategory":"Clothing, Apparel, & Fashions",
            "type":"Retail Goods"
        }
    ],
    "sg:phone":"+1 858 488 1621",
    "sg:postcode":"92109",
    "sg:province":"CA",
    "sg:tags":[
        "accessory",
        "clothing",
        "women's"
    ],
    "wof:name":"Miss Mission Beach",
    "wof:placetype":"venue"
},
  "geometry": {"coordinates":[-117.252241,32.771927],"type":"Point"}
}