{
  "type": "Feature",
  "properties": {
    "addr:full":"1501 Tollhouse Rd Clovis CA 93611",
    "addr:housenumber":"1501",
    "addr:postcode":"93611",
    "addr:street":"Tollhouse Rd",
    "iso:country":"US",
    "sg:address":"1501 Tollhouse Rd",
    "sg:city":"Clovis",
    "sg:classifiers":[
        {
            "category":"Retail",
            "subcategory":"Auto Repair",
            "type":"Services"
        }
    ],
    "sg:phone":"+1 559 297 6800",
    "sg:postcode":"93611",
    "sg:province":"CA",
    "sg:tags":[
        "wrecker"
    ],
    "wof:name":"AATAK Towing",
    "wof:placetype":"venue"
},
  "geometry": {"coordinates":[-119.687166,36.829066],"type":"Point"}
}