{
  "type": "Feature",
  "properties": {
    "iso:country":"US",
    "sg:address":"22584 Chestnut St",
    "sg:city":"Hayward",
    "sg:classifiers":[
        {
            "category":"Professional",
            "type":"Services"
        }
    ],
    "sg:phone":"+1 510 583 0305",
    "sg:postcode":"94541",
    "sg:province":"CA",
    "sg:tags":[
        "establishment"
    ],
    "wof:name":"Woodjems",
    "wof:placetype":"venue"
},
  "geometry": {"coordinates":[-122.074831,37.679174],"type":"Point"}
}