{
  "type": "Feature",
  "properties": {
    "addr:full":"453 Horton Plaza San Diego CA 92101",
    "addr:housenumber":"453",
    "addr:postcode":"92101",
    "addr:street":"Horton",
    "iso:country":"US",
    "sg:address":"453 Horton Plaza",
    "sg:city":"San Diego",
    "sg:classifiers":[
        {
            "category":"Restaurant",
            "type":"Food & Drink"
        }
    ],
    "sg:phone":"+1 619 231 6678",
    "sg:postcode":"92101",
    "sg:province":"CA",
    "wof:name":"Panda Express",
    "wof:placetype":"venue"
},
  "geometry": {"coordinates":[-117.162082,32.714176],"type":"Point"}
}