{
  "type": "Feature",
  "properties": {
    "addr:full":"20410 Town Ctr Ln Ste 150 Cupertino CA 95014",
    "addr:housenumber":"20410",
    "addr:postcode":"95014",
    "addr:street":"Town Ctr Ln Ste 150",
    "iso:country":"US",
    "sg:address":"20410 Town Ctr Ln Ste 150",
    "sg:city":"Cupertino",
    "sg:classifiers":[
        {
            "category":"Health Services",
            "subcategory":"Chiropractor",
            "type":"Services"
        }
    ],
    "sg:phone":"+1 408 446 2800",
    "sg:postcode":"95014",
    "sg:province":"CA",
    "wof:name":"Scott A Swarthout, DC",
    "wof:placetype":"venue"
},
  "geometry": {"coordinates":[-122.03090899999999,37.318397],"type":"Point"}
}