{
  "type": "Feature",
  "properties": {
    "addr:full":"2105 S Bascom Ave Campbell CA 95008",
    "addr:housenumber":"2105",
    "addr:postcode":"95008",
    "addr:street":"S Bascom Ave",
    "iso:country":"US",
    "sg:address":"2105 S Bascom Ave",
    "sg:city":"Campbell",
    "sg:classifiers":[
        {
            "category":"Travel",
            "subcategory":"Travel Agent",
            "type":"Entertainment"
        }
    ],
    "sg:phone":"+1 408 369 6878",
    "sg:postcode":"95008",
    "sg:province":"CA",
    "sg:tags":[
        "agency",
        "bureau"
    ],
    "sg:website":"www.zentechherbal.net",
    "wof:name":"Peregrine Travel",
    "wof:placetype":"venue"
},
  "geometry": {"coordinates":[-121.93182,37.285791],"type":"Point"}
}