{
  "type": "Feature",
  "properties": {
    "addr:full":"9 W Portal Ave San Francisco CA 94127",
    "addr:housenumber":"9",
    "addr:postcode":"94127",
    "addr:street":"W Portal Ave",
    "iso:country":"US",
    "sg:address":"9 W Portal Ave",
    "sg:city":"San Francisco",
    "sg:classifiers":[
        {
            "category":"Food & Beverages",
            "subcategory":"Liquor & Beverages",
            "type":"Retail Goods"
        },
        {
            "category":"Shopping",
            "type":"Retail Goods"
        }
    ],
    "sg:phone":"+1 415 420 7268",
    "sg:postcode":"94127",
    "sg:province":"CA",
    "sg:tags":[
        "beer",
        "spirit",
        "wine"
    ],
    "sg:website":"vindebut.com",
    "wof:name":"Vin Debut",
    "wof:placetype":"venue"
},
  "geometry": {"coordinates":[-122.46578599999999,37.740604],"type":"Point"}
}