{
  "type": "Feature",
  "properties": {
    "addr:full":"8459 S Western Ave Los Angeles CA 90047",
    "addr:housenumber":"8459",
    "addr:postcode":"90047",
    "addr:street":"S Western Ave",
    "iso:country":"US",
    "sg:address":"8459 S Western Ave",
    "sg:city":"Los Angeles",
    "sg:classifiers":[
        {
            "category":"Organizations",
            "subcategory":"Religious Organization",
            "type":"Services"
        }
    ],
    "sg:phone":"+1 323 750 1450",
    "sg:postcode":"90047",
    "sg:province":"CA",
    "sg:tags":[
        "church"
    ],
    "wof:name":"Holy Pilgrim Church Of God",
    "wof:placetype":"venue"
},
  "geometry": {"coordinates":[-118.309076,33.961266],"type":"Point"}
}