{
  "type": "Feature",
  "properties": {
    "iso:country":"US",
    "sg:address":"4986 Watt Ave Ste B",
    "sg:city":"North Highlands",
    "sg:classifiers":[
        {
            "category":"Home & Garden",
            "subcategory":"Household Appliances",
            "type":"Retail Goods"
        }
    ],
    "sg:phone":"+1 916 344 3520",
    "sg:postcode":"95660",
    "sg:province":"CA",
    "sg:tags":[
        "repair"
    ],
    "wof:name":"DeWALT Service Center",
    "wof:placetype":"venue"
},
  "geometry": {"coordinates":[-121.381775,38.65729],"type":"Point"}
}