{
  "type": "Feature",
  "properties": {
    "iso:country":"US",
    "sg:address":"633 Vallejo St",
    "sg:city":"San Francisco",
    "sg:classifiers":[
        {
            "category":"Shopping",
            "subcategory":"Gifts & Souvenirs",
            "type":"Retail Goods"
        }
    ],
    "sg:phone":"+1 415 837 0618",
    "sg:postcode":"94133",
    "sg:province":"CA",
    "wof:name":"Fappy Gift Shop",
    "wof:placetype":"venue"
},
  "geometry": {"coordinates":[-122.40869000000001,37.798514],"type":"Point"}
}