{
  "type": "Feature",
  "properties": {
    "addr:full":"480 San Ramon Valley Blvd Danville CA 94583",
    "addr:housenumber":"480",
    "addr:postcode":"94583",
    "addr:street":"San Ramon Valley Blvd",
    "iso:country":"US",
    "sg:address":"480 San Ramon Valley Blvd",
    "sg:city":"Danville",
    "sg:classifiers":[
        {
            "category":"Personal",
            "subcategory":"Beauty Salon",
            "type":"Services"
        }
    ],
    "sg:phone":"+1 925 820 0908",
    "sg:postcode":"94583",
    "sg:province":"CA",
    "sg:tags":[
        "manicuring"
    ],
    "wof:name":"Elegant Nails",
    "wof:placetype":"venue"
},
  "geometry": {"coordinates":[-121.996478,37.818567],"type":"Point"}
}