{
  "type": "Feature",
  "properties": {
    "addr:full":"3260 Laurashawn Ln Escondido CA 92026",
    "addr:housenumber":"3260",
    "addr:postcode":"92026",
    "addr:street":"Laurashawn Ln",
    "iso:country":"US",
    "sg:address":"3260 Laurashawn Ln",
    "sg:city":"Escondido",
    "sg:classifiers":[
        {
            "category":"Retail",
            "subcategory":"Repair Shop",
            "type":"Services"
        }
    ],
    "sg:phone":"+1 760 271 5262",
    "sg:postcode":"92026",
    "sg:province":"CA",
    "sg:tags":[
        "tile",
        "grout",
        "restoration",
        "cleaning"
    ],
    "wof:name":"David's Cleaning Svc",
    "wof:placetype":"venue"
},
  "geometry": {"coordinates":[-117.08653099999999,33.177248],"type":"Point"}
}