{
  "type": "Feature",
  "properties": {
    "addr:full":"8045 Fletcher Pkwy La Mesa CA 91942",
    "addr:housenumber":"8045",
    "addr:postcode":"91942",
    "addr:street":"Fletcher Pkwy",
    "iso:country":"US",
    "sg:address":"8045 Fletcher Pkwy",
    "sg:city":"La Mesa",
    "sg:classifiers":[
        {
            "category":"Restaurant",
            "type":"Food & Drink"
        }
    ],
    "sg:menulink":"http://www.allmenus.com/ca/san-diego/216461-mcdonalds/menu/",
    "sg:postcode":"91942",
    "sg:province":"CA",
    "sg:tags":[
        "burger",
        "american"
    ],
    "wof:name":"McDonald's",
    "wof:placetype":"venue"
},
  "geometry": {"coordinates":[-117.02451499999999,32.774465],"type":"Point"}
}