{
  "type": "Feature",
  "properties": {
    "addr:full":"1415 Truxtun Ave Bakersfield CA 93301",
    "addr:housenumber":"1415",
    "addr:postcode":"93301",
    "addr:street":"Truxtun Ave",
    "iso:country":"US",
    "sg:address":"1415 Truxtun Ave",
    "sg:city":"Bakersfield",
    "sg:classifiers":[
        {
            "category":"Government",
            "subcategory":"Police Station",
            "type":"Public Place"
        }
    ],
    "sg:phone":"+1 661 868 6850",
    "sg:postcode":"93301",
    "sg:province":"CA",
    "sg:tags":[
        "sheriff"
    ],
    "wof:name":"KERN County Sheriff",
    "wof:placetype":"venue"
},
  "geometry": {"coordinates":[-119.01866200000001,35.37326],"type":"Point"}
}