{
  "type": "Feature",
  "properties": {
    "addr:full":"210 E Cleveland Ave Madera CA 93638",
    "addr:housenumber":"210",
    "addr:postcode":"93638",
    "addr:street":"E Cleveland Ave",
    "iso:country":"US",
    "sg:address":"210 E Cleveland Ave",
    "sg:city":"Madera",
    "sg:classifiers":[
        {
            "category":"Organizations",
            "subcategory":"Religious Organization",
            "type":"Services"
        }
    ],
    "sg:phone":"+1 559 675 0421",
    "sg:postcode":"93638",
    "sg:province":"CA",
    "sg:tags":[
        "church"
    ],
    "wof:name":"Calvary Baptist Church",
    "wof:placetype":"venue"
},
  "geometry": {"coordinates":[-120.06541300000001,36.974407],"type":"Point"}
}