{
  "type": "Feature",
  "properties": {
    "addr:full":"14418 Oxnard St Van Nuys CA 91401",
    "addr:housenumber":"14418",
    "addr:postcode":"91401",
    "addr:street":"Oxnard St",
    "iso:country":"US",
    "sg:address":"14418 Oxnard St",
    "sg:city":"Van Nuys",
    "sg:classifiers":[
        {
            "category":"Wholesale",
            "subcategory":"Motor Vehicles",
            "type":"Manufacturing & Wholesale Goods"
        }
    ],
    "sg:phone":"+1 818 988 3652",
    "sg:postcode":"91401",
    "sg:province":"CA",
    "sg:tags":[
        "automobile"
    ],
    "wof:name":"Remi Autosport Inc",
    "wof:placetype":"venue"
},
  "geometry": {"coordinates":[-118.446557,34.179317],"type":"Point"}
}