{
  "type": "Feature",
  "properties": {
    "addr:full":"503 S Catalina Ave Redondo Beach CA 90277",
    "addr:housenumber":"503",
    "addr:postcode":"90277",
    "addr:street":"S Catalina Ave",
    "iso:country":"US",
    "sg:address":"503 S Catalina Ave",
    "sg:city":"Redondo Beach",
    "sg:classifiers":[
        {
            "category":"Professional",
            "subcategory":"Art Services",
            "type":"Services"
        }
    ],
    "sg:phone":"+1 310 540 6300",
    "sg:postcode":"90277",
    "sg:province":"CA",
    "sg:tags":[
        "photographer"
    ],
    "wof:name":"Boulger & Kanuit Photography",
    "wof:placetype":"venue"
},
  "geometry": {"coordinates":[-118.388249,33.833357],"type":"Point"}
}