{
  "type": "Feature",
  "properties": {
    "iso:country":"US",
    "sg:address":"6741 Five Star Blvd",
    "sg:city":"Rocklin",
    "sg:classifiers":[
        {
            "category":"Health Services",
            "subcategory":"Chiropractor",
            "type":"Services"
        }
    ],
    "sg:phone":"+1 916 624 4150",
    "sg:postcode":"95677",
    "sg:province":"CA",
    "wof:name":"Pierce Chiropractic Office",
    "wof:placetype":"venue"
},
  "geometry": {"coordinates":[-121.264149,38.781205],"type":"Point"}
}