{
  "type": "Feature",
  "properties": {
    "iso:country":"US",
    "sg:address":"21710 Stevens Creek Blvd Ste 101",
    "sg:city":"Cupertino",
    "sg:classifiers":[
        {
            "category":"Personal",
            "subcategory":"Massage",
            "type":"Services"
        }
    ],
    "sg:phone":"+1 408 777 8438",
    "sg:postcode":"95014",
    "sg:province":"CA",
    "wof:name":"Your Quiet Center Massage",
    "wof:placetype":"venue"
},
  "geometry": {"coordinates":[-122.05413,37.322403],"type":"Point"}
}