{
  "type": "Feature",
  "properties": {
    "addr:full":"295 Brookview Ct Santee CA 92071",
    "addr:housenumber":"295",
    "addr:postcode":"92071",
    "addr:street":"Brookview Ct",
    "iso:country":"US",
    "sg:address":"295 Brookview Ct",
    "sg:city":"Santee",
    "sg:classifiers":[
        {
            "category":"Shopping",
            "subcategory":"Catalog Store",
            "type":"Retail Goods"
        }
    ],
    "sg:phone":"+1 619 994 3995",
    "sg:postcode":"92071",
    "sg:province":"CA",
    "sg:tags":[
        "house",
        "mail"
    ],
    "wof:name":"Music & You",
    "wof:placetype":"venue"
},
  "geometry": {"coordinates":[-116.98621799999999,32.846343],"type":"Point"}
}