{
  "type": "Feature",
  "properties": {
    "addr:full":"1508 Alum Rock Ave San Jose CA 95116",
    "addr:housenumber":"1508",
    "addr:postcode":"95116",
    "addr:street":"Alum Rock Ave",
    "iso:country":"US",
    "sg:address":"1508 Alum Rock Ave",
    "sg:city":"San Jose",
    "sg:classifiers":[
        {
            "category":"Wholesale",
            "subcategory":"Electrical",
            "type":"Manufacturing & Wholesale Goods"
        }
    ],
    "sg:phone":"+1 408 254 1000",
    "sg:postcode":"95116",
    "sg:province":"CA",
    "sg:tags":[
        "radio",
        "electronic"
    ],
    "wof:name":"Cellular 2000",
    "wof:placetype":"venue"
},
  "geometry": {"coordinates":[-121.86049300000001,37.350357],"type":"Point"}
}