{
  "type": "Feature",
  "properties": {
    "iso:country":"US",
    "sg:address":"460 W Mission Rd",
    "sg:city":"San Marcos",
    "sg:classifiers":[
        {
            "category":"Shopping",
            "subcategory":"Gifts & Souvenirs",
            "type":"Retail Goods"
        }
    ],
    "sg:phone":"+1 760 591 7946",
    "sg:postcode":"92069",
    "sg:province":"CA",
    "sg:tags":[
        "party",
        "supply"
    ],
    "wof:name":"Dulceria El Pilon Party Supls",
    "wof:placetype":"venue"
},
  "geometry": {"coordinates":[-117.17081399999999,33.14475],"type":"Point"}
}