{
  "type": "Feature",
  "properties": {
    "iso:country":"US",
    "sg:address":"530 Divisadero St #255",
    "sg:city":"San Francisco",
    "sg:classifiers":[
        {
            "category":"Personal",
            "subcategory":"Beauty Salon",
            "type":"Services"
        }
    ],
    "sg:phone":"+1 415 307 7900",
    "sg:postcode":"94117",
    "sg:province":"CA",
    "sg:tags":[
        "spa"
    ],
    "sg:website":"www.slimsensations.net",
    "wof:name":"Slim Sensations, Inc.",
    "wof:placetype":"venue"
},
  "geometry": {"coordinates":[-122.437371,37.77457],"type":"Point"}
}