{
  "type": "Feature",
  "properties": {
    "addr:full":"75 Northam Ave San Carlos CA 94070",
    "addr:housenumber":"75",
    "addr:postcode":"94070",
    "addr:street":"Northam Ave",
    "iso:country":"US",
    "sg:address":"75 Northam Ave",
    "sg:city":"San Carlos",
    "sg:classifiers":[
        {
            "category":"Wholesale",
            "subcategory":"Sporting Goods",
            "type":"Manufacturing & Wholesale Goods"
        }
    ],
    "sg:phone":"+1 925 866 2777",
    "sg:postcode":"94070",
    "sg:province":"CA",
    "sg:tags":[
        "equipment",
        "pool",
        "swimming"
    ],
    "wof:name":"Swimming Pool Repair",
    "wof:placetype":"venue"
},
  "geometry": {"coordinates":[-122.274027,37.507177],"type":"Point"}
}