{
  "type": "Feature",
  "properties": {
    "iso:country":"US",
    "sg:address":"220 Eagle Trace Dr",
    "sg:city":"Half Moon Bay",
    "sg:classifiers":[
        {
            "category":"Professional",
            "subcategory":"Research",
            "type":"Services"
        }
    ],
    "sg:phone":"+1 650 726 3800",
    "sg:postcode":"94019",
    "sg:province":"CA",
    "sg:tags":[
        "organization",
        "noncommercial"
    ],
    "wof:name":"Feld Institute LLC",
    "wof:placetype":"venue"
},
  "geometry": {"coordinates":[-122.42796,37.435385],"type":"Point"}
}