{
  "type": "Feature",
  "properties": {
    "iso:country":"US",
    "sg:address":"915 L St",
    "sg:city":"Sacramento",
    "sg:classifiers":[
        {
            "category":"Professional",
            "subcategory":"Management & Consulting",
            "type":"Services"
        }
    ],
    "sg:phone":"+1 916 443 5943",
    "sg:postcode":"95814",
    "sg:province":"CA",
    "sg:tags":[
        "lobbyist"
    ],
    "wof:name":"Morshed & Assoc",
    "wof:placetype":"venue"
},
  "geometry": {"coordinates":[-121.494545,38.578228],"type":"Point"}
}