{
  "type": "Feature",
  "properties": {
    "addr:full":"40 2nd Ave Chula Vista CA 91910",
    "addr:housenumber":"40",
    "addr:postcode":"91910",
    "addr:street":"2Nd Ave",
    "iso:country":"US",
    "sg:address":"40 2nd Ave",
    "sg:city":"Chula Vista",
    "sg:classifiers":[
        {
            "category":"Shopping",
            "type":"Retail Goods"
        }
    ],
    "sg:phone":"+1 619 426 1345",
    "sg:postcode":"91910",
    "sg:province":"CA",
    "sg:tags":[
        "merchandise"
    ],
    "wof:name":"Pro Straps & Tie Downs",
    "wof:placetype":"venue"
},
  "geometry": {"coordinates":[-117.079207,32.651008],"type":"Point"}
}