{
  "type": "Feature",
  "properties": {
    "addr:full":"3333 Central Ave Riverside CA 92506",
    "addr:housenumber":"3333",
    "addr:postcode":"92506",
    "addr:street":"Central Ave",
    "iso:country":"US",
    "sg:address":"3333 Central Ave",
    "sg:city":"Riverside",
    "sg:classifiers":[
        {
            "category":"Banks & Credit Unions",
            "subcategory":"Investment Brokerage",
            "type":"Services"
        }
    ],
    "sg:phone":"+1 951 788 9922",
    "sg:postcode":"92506",
    "sg:province":"CA",
    "sg:tags":[
        "retirement",
        "planning"
    ],
    "wof:name":"Retirement Solutions",
    "wof:placetype":"venue"
},
  "geometry": {"coordinates":[-117.382187,33.95374],"type":"Point"}
}