{
  "type": "Feature",
  "properties": {
    "addr:full":"4453 Durfee Ave El Monte CA 91732",
    "addr:housenumber":"4453",
    "addr:postcode":"91732",
    "addr:street":"Durfee Ave",
    "iso:country":"US",
    "sg:address":"4453 Durfee Ave",
    "sg:city":"El Monte",
    "sg:classifiers":[
        {
            "category":"Freight",
            "type":"Transportation"
        }
    ],
    "sg:phone":"+1 626 448 2668",
    "sg:postcode":"91732",
    "sg:province":"CA",
    "sg:tags":[
        "arrangement"
    ],
    "wof:name":"Sesco Group Inc",
    "wof:placetype":"venue"
},
  "geometry": {"coordinates":[-118.00379599999999,34.079927],"type":"Point"}
}