{
  "type": "Feature",
  "properties": {
    "iso:country":"US",
    "sg:address":"1012 Freeman St",
    "sg:city":"Santa Ana",
    "sg:classifiers":[
        {
            "category":"Real Estate",
            "subcategory":"Real Estate Agent",
            "type":"Services"
        }
    ],
    "sg:phone":"+1 714 953 6142",
    "sg:postcode":"92703",
    "sg:province":"CA",
    "wof:name":"A-Plus Realty",
    "wof:placetype":"venue"
},
  "geometry": {"coordinates":[-117.87935,33.755685],"type":"Point"}
}