{
  "type": "Feature",
  "properties": {
    "iso:country":"US",
    "sg:address":"945 Glen Dr",
    "sg:city":"San Leandro",
    "sg:classifiers":[
        {
            "category":"Building & Trades",
            "subcategory":"Electrical",
            "type":"Services"
        }
    ],
    "sg:phone":"+1 510 569 0942",
    "sg:postcode":"94577",
    "sg:province":"CA",
    "sg:tags":[
        "electrician"
    ],
    "wof:name":"Alpen Electric Inc",
    "wof:placetype":"venue"
},
  "geometry": {"coordinates":[-122.146004,37.732201],"type":"Point"}
}