{
  "type": "Feature",
  "properties": {
    "iso:country":"US",
    "sg:address":"2903 W Capitol Avenue",
    "sg:city":"West Sacramento",
    "sg:classifiers":[
        {
            "category":"Home & Garden",
            "subcategory":"Furniture",
            "type":"Retail Goods"
        }
    ],
    "sg:phone":"+1 916 372 7377",
    "sg:postcode":"95691",
    "sg:province":"CA",
    "sg:tags":[
        "store"
    ],
    "wof:name":"Bella Furniture",
    "wof:placetype":"venue"
},
  "geometry": {"coordinates":[-121.54921899999999,38.579063],"type":"Point"}
}