{
  "type": "Feature",
  "properties": {
    "addr:full":"1417 4th St Berkeley CA 94710",
    "addr:housenumber":"1417",
    "addr:postcode":"94710",
    "addr:street":"4Th St",
    "iso:country":"US",
    "sg:address":"1417 4th St",
    "sg:city":"Berkeley",
    "sg:classifiers":[
        {
            "category":"Professional",
            "subcategory":"Printing & Photocopies",
            "type":"Services"
        }
    ],
    "sg:phone":"+1 510 559 3181",
    "sg:postcode":"94710",
    "sg:province":"CA",
    "sg:website":"www.plifeprint.com",
    "wof:name":"PrintLife Communications",
    "wof:placetype":"venue"
},
  "geometry": {"coordinates":[-122.302345,37.876375],"type":"Point"}
}