{
  "type": "Feature",
  "properties": {
    "iso:country":"US",
    "sg:address":"1801 Versailles Ave",
    "sg:city":"Alameda",
    "sg:classifiers":[
        {
            "category":"Building & Trades",
            "subcategory":"Construction",
            "type":"Services"
        }
    ],
    "sg:phone":"+1 510 864 7164",
    "sg:postcode":"94501",
    "sg:province":"CA",
    "sg:tags":[
        "house"
    ],
    "wof:name":"Castaway Construction",
    "wof:placetype":"venue"
},
  "geometry": {"coordinates":[-122.23209300000001,37.766895],"type":"Point"}
}