{
  "type": "Feature",
  "properties": {
    "iso:country":"US",
    "sg:address":"1634 3rd St",
    "sg:city":"Duarte",
    "sg:classifiers":[
        {
            "category":"Organizations",
            "subcategory":"Professional Association",
            "type":"Services"
        }
    ],
    "sg:phone":"+1 626 357 3333",
    "sg:postcode":"91010",
    "sg:province":"CA",
    "sg:tags":[
        "chambers",
        "commerce"
    ],
    "wof:name":"Duarte Chamber Of Commerce",
    "wof:placetype":"venue"
},
  "geometry": {"coordinates":[-117.968546,34.140838],"type":"Point"}
}