{
  "type": "Feature",
  "properties": {
    "addr:full":"2170 S Towne Centre Pl Anaheim CA 92806",
    "addr:housenumber":"2170",
    "addr:postcode":"92806",
    "addr:street":"S Towne Centre Pl",
    "iso:country":"US",
    "sg:address":"2170 S Towne Centre Pl",
    "sg:city":"Anaheim",
    "sg:classifiers":[
        {
            "category":"Utilities",
            "subcategory":"Mobile Phone",
            "type":"Services"
        }
    ],
    "sg:phone":"+1 714 940 0845",
    "sg:postcode":"92806",
    "sg:province":"CA",
    "sg:tags":[
        "telephone",
        "cellular"
    ],
    "wof:name":"Verizon",
    "wof:placetype":"venue"
},
  "geometry": {"coordinates":[-117.882819,33.79477],"type":"Point"}
}