{
  "type": "Feature",
  "properties": {
    "iso:country":"US",
    "sg:address":"9619 Chesapeake Drive",
    "sg:city":"San Diego",
    "sg:classifiers":[
        {
            "category":"Banks & Credit Unions",
            "subcategory":"Financial Services",
            "type":"Services"
        }
    ],
    "sg:phone":"+1 858 495 0522",
    "sg:postcode":"92123",
    "sg:province":"CA",
    "sg:tags":[
        "broker",
        "mortgage"
    ],
    "wof:name":"AAA Discount Broker",
    "wof:placetype":"venue"
},
  "geometry": {"coordinates":[-117.12365699999999,32.833538],"type":"Point"}
}