{
  "type": "Feature",
  "properties": {
    "iso:country":"US",
    "sg:address":"23501 Old Stage Rd",
    "sg:city":"Gonzales",
    "sg:classifiers":[
        {
            "category":"Building & Trades",
            "subcategory":"Electrical",
            "type":"Services"
        }
    ],
    "sg:phone":"+1 831 679 2406",
    "sg:postcode":"93926",
    "sg:province":"CA",
    "sg:tags":[
        "electric",
        "contractor"
    ],
    "sg:website":"www.brookselectric.com",
    "wof:name":"Brooks Electrical Svc Inc",
    "wof:placetype":"venue"
},
  "geometry": {"coordinates":[-121.494253,36.5766],"type":"Point"}
}