{
  "type": "Feature",
  "properties": {
    "addr:full":"7000 Melrose Ave Los Angeles CA 90038",
    "addr:housenumber":"7000",
    "addr:postcode":"90038",
    "addr:street":"Melrose Ave",
    "iso:country":"US",
    "sg:address":"7000 Melrose Ave",
    "sg:city":"Los Angeles",
    "sg:classifiers":[
        {
            "category":"Health Services",
            "subcategory":"Chiropractor",
            "type":"Services"
        }
    ],
    "sg:phone":"+1 323 935 3969",
    "sg:postcode":"90038",
    "sg:province":"CA",
    "wof:name":"Chiro De Luna",
    "wof:placetype":"venue"
},
  "geometry": {"coordinates":[-118.34405,34.083431],"type":"Point"}
}