{
  "type": "Feature",
  "properties": {
    "addr:full":"40880 County Center Dr G Temecula CA 92591",
    "addr:housenumber":"40880",
    "addr:postcode":"92591",
    "addr:street":"County Center Dr G",
    "iso:country":"US",
    "sg:address":"40880 County Center Dr G",
    "sg:city":"Temecula",
    "sg:classifiers":[
        {
            "category":"Education",
            "subcategory":"Special Training",
            "type":"Public Place"
        }
    ],
    "sg:phone":"+1 951 719 1150",
    "sg:postcode":"92591",
    "sg:province":"CA",
    "sg:website":"http://www.thomsonlearning.com",
    "wof:name":"Education To Go",
    "wof:placetype":"venue"
},
  "geometry": {"coordinates":[-117.159666,33.528824],"type":"Point"}
}