{
  "type": "Feature",
  "properties": {
    "addr:full":"2822 Filbert St San Francisco CA 94123",
    "addr:housenumber":"2822",
    "addr:postcode":"94123",
    "addr:street":"Filbert St",
    "iso:country":"US",
    "sg:address":"2822 Filbert St",
    "sg:city":"San Francisco",
    "sg:classifiers":[
        {
            "category":"Farming",
            "subcategory":"Vineyard",
            "type":"Manufacturing & Wholesale Goods"
        }
    ],
    "sg:phone":"+1 415 567 6163",
    "sg:postcode":"94123",
    "sg:province":"CA",
    "sg:tags":[
        "grape"
    ],
    "wof:name":"Ghirardelli Vineyards",
    "wof:placetype":"venue"
},
  "geometry": {"coordinates":[-122.446776,37.796693],"type":"Point"}
}