{
  "type": "Feature",
  "properties": {
    "addr:full":"5047 Robert J Mathews Pkwy El Dorado Hills CA 95762",
    "addr:housenumber":"5047",
    "addr:postcode":"95762",
    "addr:street":"Robert J Mathews Pkwy",
    "iso:country":"US",
    "sg:address":"5047 Robert J Mathews Pkwy",
    "sg:city":"El Dorado Hills",
    "sg:classifiers":[
        {
            "category":"Building & Trades",
            "subcategory":"Cleaning & Sanitation",
            "type":"Services"
        }
    ],
    "sg:phone":"+1 530 621 1256",
    "sg:postcode":"95762",
    "sg:province":"CA",
    "sg:tags":[
        "window"
    ],
    "sg:website":"www.squeakyclean.com",
    "wof:name":"Squeaky Clean Windows & Mini",
    "wof:placetype":"venue"
},
  "geometry": {"coordinates":[-121.059787,38.624917],"type":"Point"}
}