{
  "type": "Feature",
  "properties": {
    "addr:full":"919 Cll Amanecer San Clemente CA 92673",
    "addr:housenumber":"919",
    "addr:postcode":"92673",
    "addr:street":"Cll Amanecer",
    "iso:country":"US",
    "sg:address":"919 Cll Amanecer",
    "sg:city":"San Clemente",
    "sg:classifiers":[
        {
            "category":"Professional",
            "subcategory":"Business Services",
            "type":"Services"
        }
    ],
    "sg:phone":"+1 949 498 6365",
    "sg:postcode":"92673",
    "sg:province":"CA",
    "sg:tags":[
        "repairing",
        "sign"
    ],
    "wof:name":"Seaborne Signs",
    "wof:placetype":"venue"
},
  "geometry": {"coordinates":[-117.605862,33.449585],"type":"Point"}
}