{
  "type": "Feature",
  "properties": {
    "iso:country":"US",
    "sg:address":"5335 Debbie Rd",
    "sg:city":"Santa Barbara",
    "sg:classifiers":[
        {
            "category":"Building & Trades",
            "subcategory":"Construction",
            "type":"Services"
        }
    ],
    "sg:phone":"+1 805 964 9951",
    "sg:postcode":"93111",
    "sg:province":"CA",
    "sg:tags":[
        "paving",
        "contractor"
    ],
    "sg:website":"www.graniteconstruction.com",
    "wof:name":"Granite Construction Co",
    "wof:placetype":"venue"
},
  "geometry": {"coordinates":[-119.809254,34.437477],"type":"Point"}
}