{
  "type": "Feature",
  "properties": {
    "addr:full":"8105 Madison Ave Fair Oaks CA 95628",
    "addr:housenumber":"8105",
    "addr:postcode":"95628",
    "addr:street":"Madison Ave",
    "iso:country":"US",
    "sg:address":"8105 Madison Ave",
    "sg:city":"Fair Oaks",
    "sg:classifiers":[
        {
            "category":"Restaurant",
            "type":"Food & Drink"
        }
    ],
    "sg:menulink":"http://www.allmenus.com/ca/sacramento/171358-carls-jr/menu/",
    "sg:phone":"+1 916 962 3415",
    "sg:postcode":"95628",
    "sg:province":"CA",
    "sg:tags":[
        "burger",
        "american"
    ],
    "wof:name":"Carl's Jr.",
    "wof:placetype":"venue"
},
  "geometry": {"coordinates":[-121.261128,38.66439],"type":"Point"}
}