{
  "type": "Feature",
  "properties": {
    "addr:full":"7416 Lindsay Rd Bakersfield CA 93313",
    "addr:housenumber":"7416",
    "addr:postcode":"93313",
    "addr:street":"Lindsay Rd",
    "iso:country":"US",
    "sg:address":"7416 Lindsay Rd",
    "sg:city":"Bakersfield",
    "sg:classifiers":[
        {
            "category":"Train Station",
            "subcategory":"Light Rail",
            "type":"Transportation"
        }
    ],
    "sg:phone":"+1 661 831 8323",
    "sg:postcode":"93313",
    "sg:province":"CA",
    "sg:tags":[
        "weigher"
    ],
    "wof:name":"Valley Scale Service",
    "wof:placetype":"venue"
},
  "geometry": {"coordinates":[-119.08454,35.230659],"type":"Point"}
}