{
  "type": "Feature",
  "properties": {
    "iso:country":"US",
    "sg:address":"15237 W Sunset Blvd",
    "sg:city":"Pacific Palisades",
    "sg:classifiers":[
        {
            "category":"Travel",
            "subcategory":"Hotels & Motels",
            "type":"Entertainment"
        }
    ],
    "sg:phone":"+1 310 454 8905",
    "sg:postcode":"90272",
    "sg:province":"CA",
    "sg:tags":[
        "operation"
    ],
    "wof:name":"Beach House Studios",
    "wof:placetype":"venue"
},
  "geometry": {"coordinates":[-118.52451000000001,34.046318],"type":"Point"}
}