{
  "type": "Feature",
  "properties": {
    "addr:full":"23961 Calle De La Magdalena Ste 503 Laguna Hills CA 92653",
    "addr:housenumber":"23961",
    "addr:postcode":"92653",
    "addr:street":"Calle De La Magdalena Ste 503",
    "iso:country":"US",
    "sg:address":"23961 Calle De La Magdalena Ste 503",
    "sg:city":"Laguna Hills",
    "sg:classifiers":[
        {
            "category":"Farming",
            "subcategory":"Crops",
            "type":"Manufacturing & Wholesale Goods"
        }
    ],
    "sg:phone":"+1 949 472 9446",
    "sg:postcode":"92653",
    "sg:province":"CA",
    "sg:tags":[
        "fertility"
    ],
    "sg:website":"www.havingbabies.com",
    "wof:name":"Daniel Potter, MD",
    "wof:placetype":"venue"
},
  "geometry": {"coordinates":[-117.710019,33.608221],"type":"Point"}
}