{
  "type": "Feature",
  "properties": {
    "addr:full":"39775 Tinderbox Way Murrieta CA 92562",
    "addr:housenumber":"39775",
    "addr:postcode":"92562",
    "addr:street":"Tinderbox Way",
    "iso:country":"US",
    "sg:address":"39775 Tinderbox Way",
    "sg:city":"Murrieta",
    "sg:classifiers":[
        {
            "category":"Communications",
            "type":"Services"
        }
    ],
    "sg:phone":"+1 951 696 7277",
    "sg:postcode":"92562",
    "sg:province":"CA",
    "sg:tags":[
        "communication"
    ],
    "wof:name":"Easy Living Solutions",
    "wof:placetype":"venue"
},
  "geometry": {"coordinates":[-117.210751,33.594684],"type":"Point"}
}