{
  "type": "Feature",
  "properties": {
    "addr:full":"1300 N Dutton Ave Santa Rosa CA 95401",
    "addr:housenumber":"1300",
    "addr:postcode":"95401",
    "addr:street":"N Dutton Ave",
    "iso:country":"US",
    "sg:address":"1300 N Dutton Ave",
    "sg:city":"Santa Rosa",
    "sg:classifiers":[
        {
            "category":"Social Services",
            "type":"Services"
        }
    ],
    "sg:phone":"+1 707 527 5097",
    "sg:postcode":"95401",
    "sg:province":"CA",
    "sg:tags":[
        "organization",
        "welfare"
    ],
    "wof:name":"Community Action Agency",
    "wof:placetype":"venue"
},
  "geometry": {"coordinates":[-122.73339,38.449615],"type":"Point"}
}