{
  "type": "Feature",
  "properties": {
    "addr:full":"350 S Main St Fort Bragg CA 95437",
    "addr:housenumber":"350",
    "addr:postcode":"95437",
    "addr:street":"S Main St",
    "iso:country":"US",
    "sg:address":"350 S Main St",
    "sg:city":"Fort Bragg",
    "sg:classifiers":[
        {
            "category":"Wholesale",
            "subcategory":"Auto Parts",
            "type":"Manufacturing & Wholesale Goods"
        }
    ],
    "sg:phone":"+1 707 964 7259",
    "sg:postcode":"95437",
    "sg:province":"CA",
    "sg:tags":[
        "equipment",
        "truck"
    ],
    "wof:name":"Acme Bearing & Supply Co",
    "wof:placetype":"venue"
},
  "geometry": {"coordinates":[-123.805823,39.438643],"type":"Point"}
}