{
  "type": "Feature",
  "properties": {
    "addr:full":"22 N White Rd Ste 10 San Jose CA 95127",
    "addr:housenumber":"22",
    "addr:postcode":"95127",
    "addr:street":"N White Rd Ste 10 San Jose",
    "iso:country":"US",
    "sg:address":"22 N White Rd Ste 10",
    "sg:city":"San Jose",
    "sg:classifiers":[
        {
            "category":"Restaurant",
            "type":"Food & Drink"
        }
    ],
    "sg:phone":"+1 408 254 4400",
    "sg:postcode":"95127",
    "sg:province":"CA",
    "sg:tags":[
        "pizza"
    ],
    "sg:website":"nypizzatogo.com/",
    "wof:name":"New York Pizza",
    "wof:placetype":"venue"
},
  "geometry": {"coordinates":[-121.828489,37.3664],"type":"Point"}
}