{
  "type": "Feature",
  "properties": {
    "addr:full":"1044 Pioneer Way Suite E El Cajon CA 92020",
    "addr:housenumber":"1044",
    "addr:postcode":"92020",
    "addr:street":"Pioneer Way Suite E",
    "iso:country":"US",
    "sg:address":"1044 Pioneer Way Suite E",
    "sg:city":"El Cajon",
    "sg:classifiers":[
        {
            "category":"Professional",
            "subcategory":"Computer Services",
            "type":"Services"
        }
    ],
    "sg:phone":"+1 866 290 3083",
    "sg:postcode":"92020",
    "sg:province":"CA",
    "sg:tags":[
        "phone-cards",
        "prepaid-phone-cards",
        "international-phone-cards",
        "calling-cards",
        "prepaid-calling-cards",
        "international-calling-cards"
    ],
    "sg:website":"http://speedypin.com",
    "wof:name":"SpeedyPin",
    "wof:placetype":"venue"
},
  "geometry": {"coordinates":[-116.967603,32.807955],"type":"Point"}
}