{
  "type": "Feature",
  "properties": {
    "iso:country":"US",
    "sg:address":"858 High St",
    "sg:city":"Auburn",
    "sg:classifiers":[
        {
            "category":"Shopping",
            "subcategory":"Bicycles & Sporting Goods",
            "type":"Retail Goods"
        }
    ],
    "sg:phone":"+1 530 885 9200",
    "sg:postcode":"95603",
    "sg:province":"CA",
    "sg:tags":[
        "tackle",
        "fishing"
    ],
    "wof:name":"Auburn Outdoor Sports",
    "wof:placetype":"venue"
},
  "geometry": {"coordinates":[-121.069125,38.900929],"type":"Point"}
}