{
  "type": "Feature",
  "properties": {
    "addr:full":"2010 E Ocean Blvd Long Beach CA 90803",
    "addr:housenumber":"2010",
    "addr:postcode":"90803",
    "addr:street":"E Ocean Blvd",
    "iso:country":"US",
    "sg:address":"2010 E Ocean Blvd",
    "sg:city":"Long Beach",
    "sg:classifiers":[
        {
            "category":"Travel",
            "subcategory":"Hotels & Motels",
            "type":"Entertainment"
        }
    ],
    "sg:phone":"+1 562 437 0771",
    "sg:postcode":"90803",
    "sg:province":"CA",
    "wof:name":"Beach Plaza Hotel",
    "wof:placetype":"venue"
},
  "geometry": {"coordinates":[-118.166213,33.764037],"type":"Point"}
}