{
  "type": "Feature",
  "properties": {
    "addr:full":"144 Woodrow Ave Ste 4 Modesto CA 95350",
    "addr:housenumber":"144",
    "addr:postcode":"ca 95350",
    "addr:street":"Woodrow Ave Ste 4",
    "iso:country":"US",
    "sg:address":"144 Woodrow Ave Ste 4",
    "sg:city":"Modesto",
    "sg:classifiers":[
        {
            "category":"Personal",
            "subcategory":"Beauty Salon",
            "type":"Services"
        }
    ],
    "sg:phone":"+1 209 544 3902",
    "sg:postcode":"95350",
    "sg:province":"CA",
    "sg:tags":[
        "hair",
        "stylist"
    ],
    "wof:name":"Hair Unlimited",
    "wof:placetype":"venue"
},
  "geometry": {"coordinates":[-120.994833,37.685497],"type":"Point"}
}