{
  "type": "Feature",
  "properties": {
    "iso:country":"US",
    "sg:address":"522 Aliento Way",
    "sg:city":"Camarillo",
    "sg:classifiers":[
        {
            "category":"Transit Center",
            "subcategory":"Freight",
            "type":"Transportation"
        },
        {
            "category":"Freight",
            "type":"Transportation"
        }
    ],
    "sg:phone":"+1 805 384 1936",
    "sg:postcode":"93012",
    "sg:province":"CA",
    "sg:tags":[
        "local",
        "trucking-motor",
        "trucking"
    ],
    "wof:name":"Callaway Trucking Company Inc",
    "wof:placetype":"venue"
},
  "geometry": {"coordinates":[-119.00715099999999,34.221097],"type":"Point"}
}