{
  "type": "Feature",
  "properties": {
    "iso:country":"US",
    "sg:address":"2700 Augustine Drive",
    "sg:city":"Santa Clara",
    "sg:classifiers":[
        {
            "category":"Wholesale",
            "subcategory":"Computers",
            "type":"Manufacturing & Wholesale Goods"
        },
        {
            "category":"Professional",
            "subcategory":"Computer Services",
            "type":"Services"
        }
    ],
    "sg:phone":"+1 408 330 9060",
    "sg:postcode":"95054",
    "sg:province":"CA",
    "sg:tags":[
        "repair"
    ],
    "wof:name":"Amherst Technologies",
    "wof:placetype":"venue"
},
  "geometry": {"coordinates":[-121.975385,37.382335],"type":"Point"}
}