{
  "type": "Feature",
  "properties": {
    "addr:full":"913 Kevin Ct Modesto CA 95350",
    "addr:housenumber":"913",
    "addr:postcode":"ca 95350",
    "addr:street":"Kevin Ct",
    "iso:country":"US",
    "sg:address":"913 Kevin Ct",
    "sg:city":"Modesto",
    "sg:classifiers":[
        {
            "category":"Manufacturing",
            "subcategory":"Apparel",
            "type":"Manufacturing & Wholesale Goods"
        }
    ],
    "sg:phone":"+1 209 564 6336",
    "sg:postcode":"95350",
    "sg:province":"CA",
    "sg:tags":[
        "textile",
        "product",
        "fabricated",
        "mfg"
    ],
    "wof:name":"Discount Vinyl & Garden Center",
    "wof:placetype":"venue"
},
  "geometry": {"coordinates":[-121.00621599999999,37.687119],"type":"Point"}
}