{
  "type": "Feature",
  "properties": {
    "iso:country":"US",
    "sg:address":"4146 Moselle Ct",
    "sg:city":"Pleasanton",
    "sg:classifiers":[
        {
            "category":"Professional",
            "type":"Services"
        }
    ],
    "sg:phone":"+1 925 820 8798",
    "sg:postcode":"94566",
    "sg:province":"CA",
    "wof:name":"Georgia W Bareiss",
    "wof:placetype":"venue"
},
  "geometry": {"coordinates":[-121.861492,37.658004],"type":"Point"}
}