{
  "type": "Feature",
  "properties": {
    "addr:full":"15024 Leffingwell Rd La Mirada CA 90638",
    "addr:housenumber":"15024",
    "addr:postcode":"90638",
    "addr:street":"Leffingwell Rd",
    "iso:country":"US",
    "sg:address":"15024 Leffingwell Rd",
    "sg:city":"La Mirada",
    "sg:classifiers":[
        {
            "category":"Home & Garden",
            "subcategory":"Furniture",
            "type":"Retail Goods"
        }
    ],
    "sg:phone":"+1 562 943 2123",
    "sg:postcode":"90638",
    "sg:province":"CA",
    "sg:tags":[
        "store"
    ],
    "sg:website":"visionsinfurnitureinc.com",
    "wof:name":"Visions In Furniture",
    "wof:placetype":"venue"
},
  "geometry": {"coordinates":[-118.011002,33.926899],"type":"Point"}
}