{
  "type": "Feature",
  "properties": {
    "iso:country":"US",
    "sg:address":"1715 Strand Way",
    "sg:city":"Coronado",
    "sg:classifiers":[
        {
            "category":"Recreation",
            "type":"Entertainment"
        }
    ],
    "sg:phone":"+1 619 437 8877",
    "sg:postcode":"92118",
    "sg:province":"CA",
    "sg:tags":[
        "charter",
        "boat"
    ],
    "sg:website":"www.charterconnection.com",
    "wof:name":"Charter Connection",
    "wof:placetype":"venue"
},
  "geometry": {"coordinates":[-117.17416900000001,32.678559],"type":"Point"}
}