{
  "type": "Feature",
  "properties": {
    "iso:country":"US",
    "sg:address":"10518 Garvey Ave",
    "sg:city":"El Monte",
    "sg:classifiers":[
        {
            "category":"Donuts",
            "subcategory":"None",
            "type":"Food & Drink"
        }
    ],
    "sg:phone":"+1 626 350 9708",
    "sg:postcode":"91733",
    "sg:province":"CA",
    "wof:name":"Yum Yum Donuts",
    "wof:placetype":"venue"
},
  "geometry": {"coordinates":[-118.04299899999999,34.062599],"type":"Point"}
}