{
  "type": "Feature",
  "properties": {
    "addr:full":"440 5th St Hollister CA 95023",
    "addr:housenumber":"440",
    "addr:postcode":"hollister ca 95023",
    "addr:street":"5Th St",
    "iso:country":"US",
    "sg:address":"440 5th St",
    "sg:city":"Hollister",
    "sg:classifiers":[
        {
            "category":"Government",
            "subcategory":"Court House",
            "type":"Public Place"
        }
    ],
    "sg:phone":"+1 831 637 3741",
    "sg:postcode":"95023",
    "sg:province":"CA",
    "wof:name":"San Benito County Justice Crt",
    "wof:placetype":"venue"
},
  "geometry": {"coordinates":[-121.403994,36.851565],"type":"Point"}
}