{
  "type": "Feature",
  "properties": {
    "addr:full":"7513 Hillview St Highland CA 92346",
    "addr:housenumber":"7513",
    "addr:postcode":"92346",
    "addr:street":"Hillview St",
    "iso:country":"US",
    "sg:address":"7513 Hillview St",
    "sg:city":"Highland",
    "sg:classifiers":[
        {
            "category":"Marine",
            "type":"Transportation"
        }
    ],
    "sg:phone":"+1 909 862 4509",
    "sg:postcode":"92346",
    "sg:province":"CA",
    "sg:tags":[
        "water"
    ],
    "wof:name":"David Cornwell",
    "wof:placetype":"venue"
},
  "geometry": {"coordinates":[-117.220482,34.117156],"type":"Point"}
}