{
  "type": "Feature",
  "properties": {
    "addr:full":"2015 Birch Rd Ste 1015 Chula Vista CA 91915",
    "addr:housenumber":"2015",
    "addr:postcode":"91915",
    "addr:street":"Birch Rd Ste 1015",
    "iso:country":"US",
    "sg:address":"2015 Birch Rd Ste 1015",
    "sg:city":"Chula Vista",
    "sg:classifiers":[
        {
            "category":"Shopping",
            "subcategory":"Clothing, Apparel, & Fashions",
            "type":"Retail Goods"
        }
    ],
    "sg:phone":"+1 619 421 5870",
    "sg:postcode":"91915",
    "sg:province":"CA",
    "sg:tags":[
        "accessory",
        "clothing",
        "women's"
    ],
    "wof:name":"bebe",
    "wof:placetype":"venue"
},
  "geometry": {"coordinates":[-116.967264,32.621277],"type":"Point"}
}