{
  "type": "Feature",
  "properties": {
    "addr:full":"922 S Union Ave Bakersfield CA 93307",
    "addr:housenumber":"922",
    "addr:postcode":"93307",
    "addr:street":"S Union Ave",
    "iso:country":"US",
    "sg:address":"922 S Union Ave",
    "sg:city":"Bakersfield",
    "sg:classifiers":[
        {
            "category":"Professional",
            "subcategory":"Computer Services",
            "type":"Services"
        }
    ],
    "sg:phone":"+1 661 322 2685",
    "sg:postcode":"93307",
    "sg:province":"CA",
    "sg:tags":[
        "refurbishing",
        "reselling"
    ],
    "wof:name":"PC Equipment Brk Liquidators",
    "wof:placetype":"venue"
},
  "geometry": {"coordinates":[-119.00293499999999,35.345388],"type":"Point"}
}