{
  "type": "Feature",
  "properties": {
    "addr:full":"970 N Broadway Los Angeles CA 90012",
    "addr:housenumber":"970",
    "addr:postcode":"90012",
    "addr:street":"N Broadway",
    "iso:country":"US",
    "sg:address":"970 N Broadway",
    "sg:city":"Los Angeles",
    "sg:classifiers":[
        {
            "category":"Insurance",
            "subcategory":"Health Insurance",
            "type":"Services"
        }
    ],
    "sg:phone":"+1 213 625 5988",
    "sg:postcode":"90012",
    "sg:province":"CA",
    "sg:tags":[
        "market"
    ],
    "wof:name":"AA Nutrient & Products Inc",
    "wof:placetype":"venue"
},
  "geometry": {"coordinates":[-118.23699999999999,34.065601],"type":"Point"}
}