{
  "type": "Feature",
  "properties": {
    "iso:country":"US",
    "sg:address":"7650 Palmer Rd",
    "sg:city":"Los Alamos",
    "sg:classifiers":[
        {
            "category":"Farming",
            "subcategory":"Vineyard",
            "type":"Manufacturing & Wholesale Goods"
        }
    ],
    "sg:phone":"+1 805 344 5594",
    "sg:postcode":"93454",
    "sg:province":"CA",
    "wof:name":"Premier Coastal Vineyard",
    "wof:placetype":"venue"
},
  "geometry": {"coordinates":[-120.332751,34.792106],"type":"Point"}
}