{
  "type": "Feature",
  "properties": {
    "iso:country":"US",
    "sg:address":"1220 Howard Avenue",
    "sg:city":"Burlingame",
    "sg:classifiers":[
        {
            "category":"Professional",
            "subcategory":"Lawyer & Legal Services",
            "type":"Services"
        }
    ],
    "sg:phone":"+1 650 548 1171",
    "sg:postcode":"94010",
    "sg:province":"CA",
    "sg:tags":[
        "divorce",
        "law",
        "family"
    ],
    "wof:name":"Murray Lisa R",
    "wof:placetype":"venue"
},
  "geometry": {"coordinates":[-122.344917,37.577805],"type":"Point"}
}