{
  "type": "Feature",
  "properties": {
    "iso:country":"US",
    "sg:address":"39668 Rd 36",
    "sg:city":"Kingsburg",
    "sg:classifiers":[
        {
            "category":"Farming",
            "subcategory":"Vineyard",
            "type":"Manufacturing & Wholesale Goods"
        }
    ],
    "sg:phone":"+1 559 897 3871",
    "sg:postcode":"93631",
    "sg:province":"CA",
    "sg:tags":[
        "grape"
    ],
    "wof:name":"Darrel Olson",
    "wof:placetype":"venue"
},
  "geometry": {"coordinates":[-119.49362600000001,36.516428],"type":"Point"}
}