{
  "type": "Feature",
  "properties": {
    "iso:country":"US",
    "sg:address":"1736 43rd Ave",
    "sg:city":"Capitola",
    "sg:classifiers":[
        {
            "category":"Building & Trades",
            "subcategory":"Construction",
            "type":"Services"
        }
    ],
    "sg:phone":"+1 831 295 3938",
    "sg:postcode":"95010",
    "sg:province":"CA",
    "sg:tags":[
        "painter"
    ],
    "sg:website":"www.patcrowleypainting.com/",
    "wof:name":"Pat Crowley Painting",
    "wof:placetype":"venue"
},
  "geometry": {"coordinates":[-121.961563,36.974447],"type":"Point"}
}