{
  "type": "Feature",
  "properties": {
    "addr:full":"2462 E Slauson Ave Huntington Park CA 90255",
    "addr:housenumber":"2462",
    "addr:postcode":"90255",
    "addr:street":"E Slauson Ave;Park",
    "iso:country":"US",
    "sg:address":"2462 E Slauson Ave",
    "sg:city":"Huntington Park",
    "sg:classifiers":[
        {
            "category":"Personal",
            "subcategory":"Beauty Salon",
            "type":"Services"
        }
    ],
    "sg:phone":"+1 323 583 0414",
    "sg:postcode":"90255",
    "sg:province":"CA",
    "wof:name":"Doris Beauty Salon",
    "wof:placetype":"venue"
},
  "geometry": {"coordinates":[-118.22914,33.989139],"type":"Point"}
}