{
  "type": "Feature",
  "properties": {
    "addr:full":"858 Alta Ave Palm Springs CA 92285",
    "addr:housenumber":"858",
    "addr:postcode":"92285",
    "addr:street":"Alta Ave",
    "iso:country":"US",
    "sg:address":"858 Alta Ave",
    "sg:city":"Palm Springs",
    "sg:classifiers":[
        {
            "category":"Professional",
            "subcategory":"Management & Consulting",
            "type":"Services"
        }
    ],
    "sg:phone":"+1 760 416 7226",
    "sg:postcode":"92285",
    "sg:province":"CA",
    "sg:tags":[
        "living",
        "assisted",
        "facility",
        "consultant"
    ],
    "wof:name":"Western Horizons Care",
    "wof:placetype":"venue"
},
  "geometry": {"coordinates":[-116.360328,34.26387],"type":"Point"}
}