{
  "type": "Feature",
  "properties": {
    "addr:full":"4651 University Ave San Diego CA 92105",
    "addr:housenumber":"4651",
    "addr:postcode":"92105",
    "addr:street":"University Ave",
    "iso:country":"US",
    "sg:address":"4651 University Ave",
    "sg:city":"San Diego",
    "sg:classifiers":[
        {
            "category":"Food & Beverages",
            "subcategory":"Groceries & Convenience Stores",
            "type":"Retail Goods"
        }
    ],
    "sg:phone":"+1 619 563 2309",
    "sg:postcode":"92105",
    "sg:province":"CA",
    "sg:tags":[
        "grocer"
    ],
    "wof:name":"Eagle Food Ctr",
    "wof:placetype":"venue"
},
  "geometry": {"coordinates":[-117.093887,32.749553],"type":"Point"}
}