{
  "type": "Feature",
  "properties": {
    "addr:full":"3655 Pacific Hwy San Diego CA 92101",
    "addr:housenumber":"3655",
    "addr:postcode":"92101",
    "addr:street":"Pacific Hwy",
    "iso:country":"US",
    "sg:address":"3655 Pacific Hwy",
    "sg:city":"San Diego",
    "sg:classifiers":[
        {
            "category":"Retail",
            "subcategory":"Laundry & Dry Cleaning",
            "type":"Services"
        }
    ],
    "sg:phone":"+1 619 299 9000",
    "sg:postcode":"92101",
    "sg:province":"CA",
    "sg:tags":[
        "cleaners"
    ],
    "sg:website":"www.cleanteam.com",
    "wof:name":"Clean Team Co",
    "wof:placetype":"venue"
},
  "geometry": {"coordinates":[-117.18391099999999,32.740464],"type":"Point"}
}