{
  "type": "Feature",
  "properties": {
    "addr:full":"235 Radio Rd Corona CA 92879",
    "addr:housenumber":"235",
    "addr:postcode":"92879",
    "addr:street":"Radio Rd",
    "iso:country":"US",
    "sg:address":"235 Radio Rd",
    "sg:city":"Corona",
    "sg:classifiers":[
        {
            "category":"Manufacturing",
            "subcategory":"Metals",
            "type":"Manufacturing & Wholesale Goods"
        },
        {
            "category":"Manufacturing",
            "subcategory":"Rubber & Plastics",
            "type":"Manufacturing & Wholesale Goods"
        }
    ],
    "sg:phone":"+1 951 272 1300",
    "sg:postcode":"92879",
    "sg:province":"CA",
    "sg:tags":[
        "windows",
        "product",
        "mfg"
    ],
    "wof:name":"Certainteed Corona",
    "wof:placetype":"venue"
},
  "geometry": {"coordinates":[-117.542554,33.880208],"type":"Point"}
}