{
  "type": "Feature",
  "properties": {
    "iso:country":"US",
    "sg:address":"17821 17th St Ste 140",
    "sg:city":"Tustin",
    "sg:classifiers":[
        {
            "category":"Professional",
            "subcategory":"Lawyer & Legal Services",
            "type":"Services"
        }
    ],
    "sg:phone":"+1 714 573 8990",
    "sg:postcode":"92780",
    "sg:province":"CA",
    "wof:name":"Cane Walker & Harkins Llp",
    "wof:placetype":"venue"
},
  "geometry": {"coordinates":[-117.821871,33.759939],"type":"Point"}
}