{
  "type": "Feature",
  "properties": {
    "iso:country":"US",
    "sg:address":"27720 Ave Scott",
    "sg:city":"Valencia",
    "sg:classifiers":[
        {
            "category":"Professional",
            "subcategory":"Business Services",
            "type":"Services"
        }
    ],
    "sg:phone":"+1 661 257 0696",
    "sg:postcode":"91355",
    "sg:province":"CA",
    "sg:tags":[
        "appraiser"
    ],
    "sg:website":"www.agsappraisals.com",
    "wof:name":"Ag Stewart Appraisal Svc",
    "wof:placetype":"venue"
},
  "geometry": {"coordinates":[-118.571338,34.433589],"type":"Point"}
}