{
  "type": "Feature",
  "properties": {
    "iso:country":"US",
    "sg:address":"1520 Industrial Ave",
    "sg:city":"Escondido",
    "sg:classifiers":[
        {
            "category":"Retail",
            "subcategory":"Laundry & Dry Cleaning",
            "type":"Services"
        },
        {
            "category":"Home & Garden",
            "subcategory":"Home Furnishings",
            "type":"Retail Goods"
        },
        {
            "category":"Home & Garden",
            "subcategory":"Building Materials",
            "type":"Retail Goods"
        },
        {
            "category":"Building & Trades",
            "subcategory":"Cleaning & Sanitation",
            "type":"Services"
        },
        {
            "category":"Home & Garden",
            "subcategory":"Carpets & Floor Coverings",
            "type":"Retail Goods"
        }
    ],
    "sg:phone":"+1 760 740 1170",
    "sg:postcode":"92029",
    "sg:province":"CA",
    "sg:tags":[
        "cleaner",
        "etc-repair",
        "vertical",
        "rug",
        "shutter",
        "blinds-venetian",
        "window"
    ],
    "sg:website":"http://www.ashleyblindco.com",
    "wof:name":"Ashley's Cleaning",
    "wof:placetype":"venue"
},
  "geometry": {"coordinates":[-117.109444,33.120708],"type":"Point"}
}