{
  "type": "Feature",
  "properties": {
    "iso:country":"US",
    "sg:address":"29017 Avocado St",
    "sg:city":"Lake Elsinore",
    "sg:classifiers":[
        {
            "category":"Education",
            "subcategory":"Special Training",
            "type":"Public Place"
        }
    ],
    "sg:phone":"+1 951 245 0273",
    "sg:postcode":"92530",
    "sg:province":"CA",
    "sg:tags":[
        "instruction",
        "music"
    ],
    "wof:name":"KWIK Start Piano",
    "wof:placetype":"venue"
},
  "geometry": {"coordinates":[-117.398274,33.700844],"type":"Point"}
}