{
  "type": "Feature",
  "properties": {
    "addr:full":"630 Pleasant Valley Rd Diamond Springs CA 95619",
    "addr:housenumber":"630",
    "addr:postcode":"95619",
    "addr:street":"Pleasant Valley Rd",
    "iso:country":"US",
    "sg:address":"630 Pleasant Valley Rd",
    "sg:city":"Diamond Springs",
    "sg:classifiers":[
        {
            "category":"Personal",
            "subcategory":"Beauty Salon",
            "type":"Services"
        }
    ],
    "sg:phone":"+1 530 622 2128",
    "sg:postcode":"95619",
    "sg:province":"CA",
    "wof:name":"Charlene's Hair Fashions",
    "wof:placetype":"venue"
},
  "geometry": {"coordinates":[-120.81279000000001,38.694792],"type":"Point"}
}