{
  "type": "Feature",
  "properties": {
    "iso:country":"US",
    "sg:address":"5607 Almaden Expressway",
    "sg:city":"San Jose",
    "sg:classifiers":[
        {
            "category":"Autos & Motor Vehicles",
            "subcategory":"Fuel & Gas Station",
            "type":"Retail Goods"
        }
    ],
    "sg:phone":"+1 408 266 7047",
    "sg:postcode":"95118",
    "sg:province":"CA",
    "wof:name":"Edwards John R",
    "wof:placetype":"venue"
},
  "geometry": {"coordinates":[-121.875201,37.250105],"type":"Point"}
}