{
  "type": "Feature",
  "properties": {
    "iso:country":"US",
    "sg:address":"6137 Via de Los Cerros",
    "sg:city":"Pleasanton",
    "sg:classifiers":[
        {
            "category":"Real Estate",
            "subcategory":"Real Estate Agent",
            "type":"Services"
        }
    ],
    "sg:phone":"+1 925 417 2221",
    "sg:postcode":"94566",
    "sg:province":"CA",
    "wof:name":"Homescape",
    "wof:placetype":"venue"
},
  "geometry": {"coordinates":[-121.902193,37.672154],"type":"Point"}
}