{
  "type": "Feature",
  "properties": {
    "iso:country":"US",
    "sg:address":"320 1st St",
    "sg:city":"Oakland",
    "sg:classifiers":[
        {
            "category":"Real Estate",
            "subcategory":"Real Estate Agent",
            "type":"Services"
        }
    ],
    "sg:phone":"+1 510 465 2828",
    "sg:postcode":"94607",
    "sg:province":"CA",
    "wof:name":"Goodeal Realty",
    "wof:placetype":"venue"
},
  "geometry": {"coordinates":[-122.274458,37.794326],"type":"Point"}
}