{
  "type": "Feature",
  "properties": {
    "iso:country":"US",
    "sg:address":"Chinatown Central & West Plz",
    "sg:city":"Los Angeles",
    "sg:classifiers":[
        {
            "category":"Arts & Performance",
            "subcategory":"Festival",
            "type":"Entertainment"
        }
    ],
    "sg:postcode":"90012",
    "sg:province":"CA",
    "sg:website":"www.chinatownsummernights.com/",
    "wof:name":"Chinatown Summer Nights",
    "wof:placetype":"venue"
},
  "geometry": {"coordinates":[-118.33627,33.998135],"type":"Point"}
}