{
  "type": "Feature",
  "properties": {
    "iso:country":"US",
    "sg:address":"16039 Brookhurst St",
    "sg:city":"Fountain Valley",
    "sg:classifiers":[
        {
            "category":"Home & Garden",
            "subcategory":"Furniture",
            "type":"Retail Goods"
        }
    ],
    "sg:phone":"+1 714 839 8808",
    "sg:postcode":"92708",
    "sg:province":"CA",
    "sg:tags":[
        "store"
    ],
    "wof:name":"Euro-Asian Furnishings Inc",
    "wof:placetype":"venue"
},
  "geometry": {"coordinates":[-117.95487900000001,33.729764],"type":"Point"}
}