{
  "type": "Feature",
  "properties": {
    "iso:country":"US",
    "sg:address":"689 Morse St",
    "sg:city":"San Jose",
    "sg:classifiers":[
        {
            "category":"Manufacturing",
            "subcategory":"Electronics",
            "type":"Manufacturing & Wholesale Goods"
        }
    ],
    "sg:phone":"+1 408 221 1711",
    "sg:postcode":"95126",
    "sg:province":"CA",
    "sg:tags":[
        "mfg",
        "boards",
        "circuit",
        "printed"
    ],
    "wof:name":"Fabrite Inc",
    "wof:placetype":"venue"
},
  "geometry": {"coordinates":[-121.919904,37.335506],"type":"Point"}
}