{
  "type": "Feature",
  "properties": {
    "iso:country":"US",
    "sg:address":"3794 Putah Creek Rd",
    "sg:city":"Winters",
    "sg:classifiers":[
        {
            "category":"Building & Trades",
            "subcategory":"Landscaping Services",
            "type":"Services"
        }
    ],
    "sg:phone":"+1 530 795 1475",
    "sg:postcode":"95694",
    "sg:province":"CA",
    "wof:name":"Suisun Valley Landscape",
    "wof:placetype":"venue"
},
  "geometry": {"coordinates":[-122.017028,38.487521],"type":"Point"}
}