{
  "type": "Feature",
  "properties": {
    "iso:country":"US",
    "sg:address":"637 S Hill St",
    "sg:city":"Los Angeles",
    "sg:classifiers":[
        {
            "category":"Shopping",
            "subcategory":"Jewelry",
            "type":"Retail Goods"
        }
    ],
    "sg:phone":"+1 213 955 0038",
    "sg:postcode":"90014",
    "sg:province":"CA",
    "sg:tags":[
        "jeweler"
    ],
    "wof:name":"If Jewelry",
    "wof:placetype":"venue"
},
  "geometry": {"coordinates":[-118.25409999999999,34.046482],"type":"Point"}
}