{
  "type": "Feature",
  "properties": {
    "iso:country":"US",
    "sg:address":"24028 Tobaro Ct",
    "sg:city":"Murrieta",
    "sg:classifiers":[
        {
            "category":"Personal",
            "type":"Services"
        }
    ],
    "sg:phone":"+1 951 677 7101",
    "sg:postcode":"92562",
    "sg:province":"CA",
    "sg:tags":[
        "bureau"
    ],
    "wof:name":"Smooth Moves",
    "wof:placetype":"venue"
},
  "geometry": {"coordinates":[-117.19806199999999,33.589418],"type":"Point"}
}