{
  "type": "Feature",
  "properties": {
    "addr:full":"704 W Mission Blvd Pomona CA 91766",
    "addr:housenumber":"704",
    "addr:postcode":"91766",
    "addr:street":"W Mission Blvd",
    "iso:country":"US",
    "sg:address":"704 W Mission Blvd",
    "sg:city":"Pomona",
    "sg:classifiers":[
        {
            "category":"Retail",
            "subcategory":"Auto Rental",
            "type":"Services"
        }
    ],
    "sg:phone":"+1 909 469 9813",
    "sg:postcode":"91766",
    "sg:province":"CA",
    "sg:tags":[
        "renting",
        "truck",
        "leasing"
    ],
    "wof:name":"U-Haul Co",
    "wof:placetype":"venue"
},
  "geometry": {"coordinates":[-117.75766,34.054924],"type":"Point"}
}