{
  "type": "Feature",
  "properties": {
    "addr:full":"928 Canada Ct Rowland Heights CA 91748",
    "addr:housenumber":"928",
    "addr:postcode":"91748",
    "addr:street":"Canada Ct",
    "iso:country":"US",
    "sg:address":"928 Canada Ct",
    "sg:city":"Rowland Heights",
    "sg:classifiers":[
        {
            "category":"Professional",
            "type":"Services"
        }
    ],
    "sg:phone":"+1 626 913 9963",
    "sg:postcode":"91748",
    "sg:province":"CA",
    "wof:name":"Kingston Foundry",
    "wof:placetype":"venue"
},
  "geometry": {"coordinates":[-117.920911,34.003155],"type":"Point"}
}