{
  "type": "Feature",
  "properties": {
    "addr:full":"1210 Sonoma Ave Santa Rosa CA 95405",
    "addr:housenumber":"1210",
    "addr:postcode":"95405",
    "addr:street":"Sonoma Ave",
    "iso:country":"US",
    "sg:address":"1210 Sonoma Ave",
    "sg:city":"Santa Rosa",
    "sg:classifiers":[
        {
            "category":"Health Services",
            "subcategory":"Doctor",
            "type":"Services"
        }
    ],
    "sg:phone":"+1 707 579 9200",
    "sg:postcode":"95405",
    "sg:province":"CA",
    "sg:tags":[
        "physician",
        "surgeon"
    ],
    "wof:name":"Beauty & Health Medical Ctr",
    "wof:placetype":"venue"
},
  "geometry": {"coordinates":[-122.699201,38.441233],"type":"Point"}
}