{
  "type": "Feature",
  "properties": {
    "addr:full":"3205 Lakeshore Ave Oakland CA 94610",
    "addr:housenumber":"3205",
    "addr:postcode":"94610",
    "addr:street":"Lakeshore Ave",
    "iso:country":"US",
    "sg:address":"3205 Lakeshore Ave",
    "sg:city":"Oakland",
    "sg:classifiers":[
        {
            "category":"Restaurant",
            "type":"Food & Drink"
        }
    ],
    "sg:phone":"+1 510 444 0702",
    "sg:postcode":"94610",
    "sg:province":"CA",
    "wof:name":"Subway Sandwiches & Salads",
    "wof:placetype":"venue"
},
  "geometry": {"coordinates":[-122.245003,37.8106],"type":"Point"}
}