{
  "type": "Feature",
  "properties": {
    "addr:full":"8951 Complex Dr San Diego CA 92123",
    "addr:housenumber":"8951",
    "addr:postcode":"92123",
    "addr:street":"Complex Dr",
    "iso:country":"US",
    "sg:address":"8951 Complex Dr",
    "sg:city":"San Diego",
    "sg:classifiers":[
        {
            "category":"Building & Trades",
            "subcategory":"Electrical",
            "type":"Services"
        }
    ],
    "sg:phone":"+1 858 860 2720",
    "sg:postcode":"92123",
    "sg:province":"CA",
    "wof:name":"L & M Cable",
    "wof:placetype":"venue"
},
  "geometry": {"coordinates":[-117.138879,32.830036],"type":"Point"}
}