{
  "type": "Feature",
  "properties": {
    "addr:full":"10128 Fair Oaks Boulevard Fair Oaks CA 95628",
    "addr:housenumber":"10128",
    "addr:postcode":"95628",
    "addr:street":"Fair Oaks Boulevard",
    "iso:country":"US",
    "sg:address":"10128 Fair Oaks Boulevard",
    "sg:city":"Fair Oaks",
    "sg:classifiers":[
        {
            "category":"Shopping",
            "subcategory":"Beauty & Cosmetics",
            "type":"Retail Goods"
        }
    ],
    "sg:phone":"+1 916 961 1555",
    "sg:postcode":"95628",
    "sg:province":"CA",
    "sg:tags":[
        "supply"
    ],
    "wof:name":"Hair Clips",
    "wof:placetype":"venue"
},
  "geometry": {"coordinates":[-121.269955,38.641113],"type":"Point"}
}