{
  "type": "Feature",
  "properties": {
    "iso:country":"US",
    "sg:address":"44611 Orchard Ln",
    "sg:city":"Lancaster",
    "sg:classifiers":[
        {
            "category":"Building & Trades",
            "subcategory":"Electrical",
            "type":"Services"
        }
    ],
    "sg:phone":"+1 661 949 3316",
    "sg:postcode":"93534",
    "sg:province":"CA",
    "sg:tags":[
        "electric",
        "contractor"
    ],
    "wof:name":"J K Electric",
    "wof:placetype":"venue"
},
  "geometry": {"coordinates":[-118.159599,34.6933],"type":"Point"}
}