{
  "type": "Feature",
  "properties": {
    "addr:full":"91 Spicer St Salinas CA 93901",
    "addr:housenumber":"91",
    "addr:postcode":"93901",
    "addr:street":"Spicer St",
    "iso:country":"US",
    "sg:address":"91 Spicer St",
    "sg:city":"Salinas",
    "sg:classifiers":[
        {
            "category":"Wholesale",
            "subcategory":"Stationery",
            "type":"Manufacturing & Wholesale Goods"
        }
    ],
    "sg:phone":"+1 831 424 7647",
    "sg:postcode":"93901",
    "sg:province":"CA",
    "sg:tags":[
        "box",
        "fiber"
    ],
    "wof:name":"Calpine Containers",
    "wof:placetype":"venue"
},
  "geometry": {"coordinates":[-121.643974,36.666256],"type":"Point"}
}