{
  "type": "Feature",
  "properties": {
    "addr:full":"2210 E Highland Ave San Bernardino CA 92404",
    "addr:housenumber":"2210",
    "addr:postcode":"92404",
    "addr:street":"E Highland Ave",
    "iso:country":"US",
    "sg:address":"2210 E Highland Ave",
    "sg:city":"San Bernardino",
    "sg:classifiers":[
        {
            "category":"Government",
            "subcategory":"Office",
            "type":"Public Place"
        }
    ],
    "sg:phone":"+1 909 864 1097",
    "sg:postcode":"92404",
    "sg:province":"CA",
    "sg:tags":[
        "state",
        "program",
        "health"
    ],
    "wof:name":"San Manuel Indian Health",
    "wof:placetype":"venue"
},
  "geometry": {"coordinates":[-117.238416,34.135933],"type":"Point"}
}