{
  "type": "Feature",
  "properties": {
    "addr:full":"1610 N Newhope St Santa Ana CA 92701",
    "addr:housenumber":"1610",
    "addr:postcode":"92701",
    "addr:street":"N Newhope St",
    "iso:country":"US",
    "sg:address":"1610 N Newhope St",
    "sg:city":"Santa Ana",
    "sg:classifiers":[
        {
            "category":"Retail",
            "subcategory":"Auto Repair",
            "type":"Services"
        }
    ],
    "sg:phone":"+1 714 636 3850",
    "sg:postcode":"92701",
    "sg:province":"CA",
    "sg:tags":[
        "body",
        "shop"
    ],
    "sg:website":"www.occlearcoat.com/",
    "wof:name":"Clear Coat Frame & Collision",
    "wof:placetype":"venue"
},
  "geometry": {"coordinates":[-117.928945,33.75862],"type":"Point"}
}