{
  "type": "Feature",
  "properties": {
    "iso:country":"US",
    "sg:address":"4040 Barranca Pkwy Suite 125",
    "sg:city":"Irvine",
    "sg:phone":"+1 949 786 1188",
    "sg:postcode":"92604",
    "sg:province":"CA",
    "wof:name":"Liu Chris C DDS",
    "wof:placetype":"venue"
},
  "geometry": {"coordinates":[-117.807344,33.683353],"type":"Point"}
}