{
  "type": "Feature",
  "properties": {
    "addr:full":"23905 Clinton Keith Rd Wildomar CA 92595",
    "addr:housenumber":"23905",
    "addr:postcode":"92595",
    "addr:street":"Clinton Keith Rd",
    "iso:country":"US",
    "sg:address":"23905 Clinton Keith Rd",
    "sg:city":"Wildomar",
    "sg:classifiers":[
        {
            "category":"Building & Trades",
            "subcategory":"Electrical",
            "type":"Services"
        }
    ],
    "sg:phone":"+1 951 333 9609",
    "sg:postcode":"92595",
    "sg:province":"CA",
    "sg:tags":[
        "electrician"
    ],
    "wof:name":"Clean Energy Solar Systems, Inc.",
    "wof:placetype":"venue"
},
  "geometry": {"coordinates":[-117.24280299999999,33.597182],"type":"Point"}
}