{
  "type": "Feature",
  "properties": {
    "iso:country":"US",
    "sg:address":"24613 Ave 212",
    "sg:city":"Lindsay",
    "sg:classifiers":[
        {
            "category":"Professional",
            "subcategory":"Management & Consulting",
            "type":"Services"
        }
    ],
    "sg:phone":"+1 559 568 1416",
    "sg:postcode":"93247",
    "sg:province":"CA",
    "sg:tags":[
        "consultant"
    ],
    "wof:name":"Valley Consulting",
    "wof:placetype":"venue"
},
  "geometry": {"coordinates":[-119.023551,36.174507],"type":"Point"}
}