{
  "type": "Feature",
  "properties": {
    "addr:full":"1707 4th St Santa Monica CA 90401",
    "addr:housenumber":"1707",
    "addr:postcode":"90401",
    "addr:street":"4Th St",
    "iso:country":"US",
    "sg:address":"1707 4th St",
    "sg:city":"Santa Monica",
    "sg:classifiers":[
        {
            "category":"Building & Trades",
            "subcategory":"Equipment Rental",
            "type":"Services"
        }
    ],
    "sg:phone":"+1 310 260 6358",
    "sg:postcode":"90401",
    "sg:province":"CA",
    "wof:name":"Audio Visual Headquarters",
    "wof:placetype":"venue"
},
  "geometry": {"coordinates":[-118.48732,34.009664],"type":"Point"}
}