{
  "type": "Feature",
  "properties": {
    "iso:country":"US",
    "sg:address":"6006 Vantage Ave",
    "sg:city":"North Hollywood",
    "sg:classifiers":[
        {
            "category":"Personal",
            "subcategory":"Beauty Salon",
            "type":"Services"
        }
    ],
    "sg:phone":"+1 818 487 8701",
    "sg:postcode":"91606",
    "sg:province":"CA",
    "wof:name":"Luxxor Beauty Salon",
    "wof:placetype":"venue"
},
  "geometry": {"coordinates":[-118.397548,34.181108],"type":"Point"}
}