{
  "type": "Feature",
  "properties": {
    "addr:full":"1547 W Juno Ave Anaheim CA 92802",
    "addr:housenumber":"1547",
    "addr:postcode":"92802",
    "addr:street":"W Juno Ave",
    "iso:country":"US",
    "sg:address":"1547 W Juno Ave",
    "sg:city":"Anaheim",
    "sg:classifiers":[
        {
            "category":"Building & Trades",
            "subcategory":"Cleaning & Sanitation",
            "type":"Services"
        }
    ],
    "sg:phone":"+1 714 404 8339",
    "sg:postcode":"92802",
    "sg:province":"CA",
    "sg:tags":[
        "carpet"
    ],
    "wof:name":"Five Star Carpet Cleaning",
    "wof:placetype":"venue"
},
  "geometry": {"coordinates":[-117.935096,33.819003],"type":"Point"}
}