{
  "type": "Feature",
  "properties": {
    "addr:full":"260 E Magnolia Blvd Burbank CA 91502",
    "addr:housenumber":"260",
    "addr:postcode":"91502",
    "addr:street":"E Magnolia Blvd",
    "iso:country":"US",
    "sg:address":"260 E Magnolia Blvd",
    "sg:city":"Burbank",
    "sg:classifiers":[
        {
            "category":"Restaurant",
            "type":"Food & Drink"
        }
    ],
    "sg:phone":"+1 818 843 8339",
    "sg:postcode":"91502",
    "sg:province":"CA",
    "sg:tags":[
        "middle",
        "eastern"
    ],
    "sg:website":"www.gitanarestaurant.com/",
    "wof:name":"Gitana Restaurant",
    "wof:placetype":"venue"
},
  "geometry": {"coordinates":[-118.310997,34.1838],"type":"Point"}
}