{
  "type": "Feature",
  "properties": {
    "addr:full":"859 Stillwater Rd Broderick CA 95605",
    "addr:housenumber":"859",
    "addr:postcode":"95605",
    "addr:street":"Stillwater Rd",
    "iso:country":"US",
    "sg:address":"859 Stillwater Rd",
    "sg:city":"Broderick",
    "sg:classifiers":[
        {
            "category":"Wholesale",
            "subcategory":"Electrical",
            "type":"Manufacturing & Wholesale Goods"
        }
    ],
    "sg:phone":"+1 916 373 6999",
    "sg:postcode":"95605",
    "sg:province":"CA",
    "sg:tags":[
        "battery"
    ],
    "sg:website":"www.celeritypower.com",
    "wof:name":"Celerity Power Svc",
    "wof:placetype":"venue"
},
  "geometry": {"coordinates":[-121.55615400000001,38.59062],"type":"Point"}
}