{
  "type": "Feature",
  "properties": {
    "iso:country":"US",
    "sg:address":"2726 Avalon Ave",
    "sg:city":"Carlsbad",
    "sg:classifiers":[
        {
            "category":"Professional",
            "type":"Services"
        }
    ],
    "sg:phone":"+1 760 729 9929",
    "sg:postcode":"92010",
    "sg:province":"CA",
    "wof:name":"Wm Bud Walls II",
    "wof:placetype":"venue"
},
  "geometry": {"coordinates":[-117.307166,33.164875],"type":"Point"}
}