{
  "type": "Feature",
  "properties": {
    "addr:full":"21672 Plano Trabuco Rd Trabuco Canyon CA 92679",
    "addr:housenumber":"21672",
    "addr:postcode":"92679",
    "addr:street":"Plano Trabuco Rd",
    "iso:country":"US",
    "sg:address":"21672 Plano Trabuco Rd",
    "sg:city":"Trabuco Canyon",
    "sg:classifiers":[
        {
            "category":"Food & Beverages",
            "subcategory":"Groceries & Convenience Stores",
            "type":"Retail Goods"
        }
    ],
    "sg:phone":"+1 949 589 3780",
    "sg:postcode":"92679",
    "sg:province":"CA",
    "sg:tags":[
        "grocer"
    ],
    "wof:name":"Albertsons",
    "wof:placetype":"venue"
},
  "geometry": {"coordinates":[-117.578503,33.641931],"type":"Point"}
}