{
  "type": "Feature",
  "properties": {
    "iso:country":"US",
    "sg:address":"6437 Ira Ave",
    "sg:city":"Bell Gardens",
    "sg:classifiers":[
        {
            "category":"Building & Trades",
            "subcategory":"Construction",
            "type":"Services"
        }
    ],
    "sg:phone":"+1 323 773 3658",
    "sg:postcode":"90201",
    "sg:province":"CA",
    "sg:tags":[
        "contractor"
    ],
    "wof:name":"Excellence Builders",
    "wof:placetype":"venue"
},
  "geometry": {"coordinates":[-118.15232399999999,33.972727],"type":"Point"}
}