{
  "type": "Feature",
  "properties": {
    "iso:country":"US",
    "sg:address":"27872 Crown Valley Pkwy",
    "sg:city":"Mission Viejo",
    "sg:classifiers":[
        {
            "category":"Retail",
            "subcategory":"Storage",
            "type":"Services"
        }
    ],
    "sg:phone":"+1 949 364 6219",
    "sg:postcode":"92691",
    "sg:province":"CA",
    "sg:tags":[
        "self"
    ],
    "wof:name":"Allsize Self Storage",
    "wof:placetype":"venue"
},
  "geometry": {"coordinates":[-117.66799899999999,33.611198],"type":"Point"}
}