{
  "type": "Feature",
  "properties": {
    "addr:full":"1228 Broadway Placerville CA 95667",
    "addr:housenumber":"1228",
    "addr:postcode":"95667",
    "addr:street":"Broadway",
    "iso:country":"US",
    "sg:address":"1228 Broadway",
    "sg:city":"Placerville",
    "sg:classifiers":[
        {
            "category":"Coffee & Tea",
            "type":"Food & Drink"
        }
    ],
    "sg:menulink":"http://www.allmenus.com/ca/placerville/108123-starbucks-coffee/menu/",
    "sg:phone":"+1 530 626 6024",
    "sg:postcode":"95667",
    "sg:province":"CA",
    "sg:tags":[
        "american"
    ],
    "wof:name":"Starbucks Coffee",
    "wof:placetype":"venue"
},
  "geometry": {"coordinates":[-120.786888,38.730852],"type":"Point"}
}