{
  "type": "Feature",
  "properties": {
    "addr:full":"286 Sun Valley Mall Concord CA 94520",
    "addr:housenumber":"286",
    "addr:postcode":"94520",
    "addr:street":"Sun Valley Mall",
    "iso:country":"US",
    "sg:address":"286 Sun Valley Mall",
    "sg:city":"Concord",
    "sg:classifiers":[
        {
            "category":"Restaurant",
            "type":"Food & Drink"
        }
    ],
    "sg:menulink":"http://www.allmenus.com/ca/central-contra-costa/149916-subway/menu/",
    "sg:phone":"+1 925 798 3623",
    "sg:postcode":"94520",
    "sg:province":"CA",
    "sg:tags":[
        "american",
        "sandwich"
    ],
    "wof:name":"Subway",
    "wof:placetype":"venue"
},
  "geometry": {"coordinates":[-122.06205300000001,37.967168],"type":"Point"}
}