{
  "type": "Feature",
  "properties": {
    "iso:country":"US",
    "sg:address":"1999 Tuolumne St",
    "sg:city":"Fresno",
    "sg:classifiers":[
        {
            "category":"Professional",
            "subcategory":"Management & Consulting",
            "type":"Services"
        }
    ],
    "sg:phone":"+1 559 441 9441",
    "sg:postcode":"93721",
    "sg:province":"CA",
    "sg:tags":[
        "consultant",
        "business"
    ],
    "wof:name":"Ramzay Group",
    "wof:placetype":"venue"
},
  "geometry": {"coordinates":[-119.7955,36.737176],"type":"Point"}
}