{
  "type": "Feature",
  "properties": {
    "iso:country":"US",
    "sg:address":"439 S Bascom Avenue",
    "sg:city":"San Jose",
    "sg:classifiers":[
        {
            "category":"Food & Beverages",
            "subcategory":"Liquor & Beverages",
            "type":"Retail Goods"
        }
    ],
    "sg:phone":"+1 408 294 3993",
    "sg:postcode":"95128",
    "sg:province":"CA",
    "sg:tags":[
        "beer",
        "spirit",
        "wine"
    ],
    "wof:name":"Tip Top Liquors",
    "wof:placetype":"venue"
},
  "geometry": {"coordinates":[-121.931838,37.321067],"type":"Point"}
}