{
  "type": "Feature",
  "properties": {
    "iso:country":"US",
    "sg:address":"18655 S Western Ave",
    "sg:city":"Gardena",
    "sg:classifiers":[
        {
            "category":"Manufacturing",
            "subcategory":"Food",
            "type":"Manufacturing & Wholesale Goods"
        }
    ],
    "sg:phone":"+1 310 533 3270",
    "sg:postcode":"90248",
    "sg:province":"CA",
    "sg:tags":[
        "product",
        "mfg"
    ],
    "sg:website":"www.kingshawaiian.com",
    "wof:name":"Kings Hawaiian Bakery West",
    "wof:placetype":"venue"
},
  "geometry": {"coordinates":[-118.309223,33.861125],"type":"Point"}
}