{
  "type": "Feature",
  "properties": {
    "iso:country":"US",
    "sg:address":"6295 Westridge Ct",
    "sg:city":"Eureka",
    "sg:classifiers":[
        {
            "category":"Health Services",
            "subcategory":"Doctor",
            "type":"Services"
        }
    ],
    "sg:phone":"+1 707 445 5938",
    "sg:postcode":"95503",
    "sg:province":"CA",
    "sg:tags":[
        "physician",
        "surgeon"
    ],
    "wof:name":"North Coast Anisthesiology",
    "wof:placetype":"venue"
},
  "geometry": {"coordinates":[-124.165331,40.736003],"type":"Point"}
}