{
  "type": "Feature",
  "properties": {
    "addr:full":"108 Associated Rd S San Francisco CA 94080",
    "addr:housenumber":"108",
    "addr:postcode":"94080",
    "addr:street":"Associated Rd S",
    "iso:country":"US",
    "sg:address":"108 Associated Rd",
    "sg:city":"S San Francisco",
    "sg:classifiers":[
        {
            "category":"Wholesale",
            "subcategory":"Groceries",
            "type":"Manufacturing & Wholesale Goods"
        }
    ],
    "sg:phone":"+1 650 635 1637",
    "sg:postcode":"94080",
    "sg:province":"CA",
    "sg:tags":[
        "rice"
    ],
    "wof:name":"Gordon Sales Co",
    "wof:placetype":"venue"
},
  "geometry": {"coordinates":[-122.40543,37.652347],"type":"Point"}
}