{
  "type": "Feature",
  "properties": {
    "iso:country":"US",
    "sg:address":"485 Victor Way",
    "sg:city":"Salinas",
    "sg:classifiers":[
        {
            "category":"Professional",
            "subcategory":"Research",
            "type":"Services"
        }
    ],
    "sg:phone":"+1 831 422 2290",
    "sg:postcode":"93907",
    "sg:province":"CA",
    "sg:tags":[
        "environmental",
        "ecological"
    ],
    "wof:name":"Environmental Restoration Svc",
    "wof:placetype":"venue"
},
  "geometry": {"coordinates":[-121.668952,36.684645],"type":"Point"}
}