{
  "type": "Feature",
  "properties": {
    "addr:full":"12847 Kling St Studio City CA 91604",
    "addr:postcode":"12847;91604",
    "addr:street":"Kling St",
    "iso:country":"US",
    "sg:address":"12847 Kling St",
    "sg:city":"Studio City",
    "sg:classifiers":[
        {
            "category":"Professional",
            "subcategory":"Computer Services",
            "type":"Services"
        }
    ],
    "sg:phone":"+1 818 506 7750",
    "sg:postcode":"91604",
    "sg:province":"CA",
    "wof:name":"Cyberfactor",
    "wof:placetype":"venue"
},
  "geometry": {"coordinates":[-118.412583,34.155877],"type":"Point"}
}