{
  "type": "Feature",
  "properties": {
    "iso:country":"US",
    "sg:address":"6911 Topanga Canyon Blvd",
    "sg:city":"Canoga Park",
    "sg:classifiers":[
        {
            "category":"Building & Trades",
            "subcategory":"Cleaning & Sanitation",
            "type":"Services"
        }
    ],
    "sg:phone":"+1 818 716 2888",
    "sg:postcode":"91303",
    "sg:province":"CA",
    "sg:tags":[
        "property",
        "maintenance"
    ],
    "wof:name":"Elat Associates",
    "wof:placetype":"venue"
},
  "geometry": {"coordinates":[-118.605912,34.19606],"type":"Point"}
}