{
  "type": "Feature",
  "properties": {
    "addr:full":"4130 Lake Tahoe Blvd South Lake Tahoe CA 96150",
    "addr:housenumber":"4130",
    "addr:postcode":"96150",
    "addr:street":"Lake Tahoe Blvd",
    "iso:country":"US",
    "sg:address":"4130 Lake Tahoe Blvd",
    "sg:city":"South Lake Tahoe",
    "sg:classifiers":[
        {
            "category":"Travel",
            "subcategory":"Hotels & Motels",
            "type":"Entertainment"
        }
    ],
    "sg:phone":"+1 530 544 6461",
    "sg:postcode":"96150",
    "sg:province":"CA",
    "wof:name":"Ambassador Motor Lodge",
    "wof:placetype":"venue"
},
  "geometry": {"coordinates":[-119.94211199999999,38.958967],"type":"Point"}
}