{
  "type": "Feature",
  "properties": {
    "addr:full":"1912 Coronado Ave San Diego CA 92154",
    "addr:housenumber":"1912",
    "addr:postcode":"92154",
    "addr:street":"Coronado Ave",
    "iso:country":"US",
    "sg:address":"1912 Coronado Ave",
    "sg:city":"San Diego",
    "sg:classifiers":[
        {
            "category":"Home & Garden",
            "subcategory":"Mobile Homes",
            "type":"Retail Goods"
        }
    ],
    "sg:phone":"+1 619 423 2337",
    "sg:postcode":"92154",
    "sg:province":"CA",
    "wof:name":"San Diego Mobile Home Sales",
    "wof:placetype":"venue"
},
  "geometry": {"coordinates":[-117.091357,32.576571],"type":"Point"}
}