{
  "type": "Feature",
  "properties": {
    "addr:full":"13625 Manhasset Rd Apple Valley CA 92308",
    "addr:housenumber":"13625",
    "addr:postcode":"92308",
    "addr:street":"Manhasset Rd",
    "iso:country":"US",
    "sg:address":"13625 Manhasset Rd",
    "sg:city":"Apple Valley",
    "sg:classifiers":[
        {
            "category":"Retail",
            "subcategory":"Auto Repair",
            "type":"Services"
        }
    ],
    "sg:phone":"+1 760 240 5602",
    "sg:postcode":"92308",
    "sg:province":"CA",
    "sg:tags":[
        "repairing",
        "automobile"
    ],
    "wof:name":"J & D Auto",
    "wof:placetype":"venue"
},
  "geometry": {"coordinates":[-117.1848,34.498204],"type":"Point"}
}