{
  "type": "Feature",
  "properties": {
    "iso:country":"US",
    "sg:address":"2686 Montrose Pl",
    "sg:city":"Santa Barbara",
    "sg:classifiers":[
        {
            "category":"Professional",
            "type":"Services"
        }
    ],
    "sg:phone":"+1 805 569 0217",
    "sg:postcode":"93105",
    "sg:province":"CA",
    "sg:tags":[
        "establishment"
    ],
    "wof:name":"Ryerson Master Assoc",
    "wof:placetype":"venue"
},
  "geometry": {"coordinates":[-119.71524,34.451702],"type":"Point"}
}