{
  "type": "Feature",
  "properties": {
    "addr:full":"23141 Lake Center Dr Lake Forest CA 92630",
    "addr:housenumber":"23141",
    "addr:postcode":"92630",
    "addr:street":"Lake Center Dr",
    "iso:country":"US",
    "sg:address":"23141 Lake Center Dr",
    "sg:city":"Lake Forest",
    "sg:classifiers":[
        {
            "category":"Education",
            "subcategory":"Vocational School",
            "type":"Public Place"
        }
    ],
    "sg:phone":"+1 949 452 0606",
    "sg:postcode":"92630",
    "sg:province":"CA",
    "sg:website":"www.cpimedic.com",
    "wof:name":"California Paramedic Institute",
    "wof:placetype":"venue"
},
  "geometry": {"coordinates":[-117.716675,33.626525],"type":"Point"}
}