{
  "type": "Feature",
  "properties": {
    "addr:full":"1410 Encinal Ave Alameda CA 94501",
    "addr:housenumber":"1410",
    "addr:postcode":"94501",
    "addr:street":"Encinal Ave",
    "iso:country":"US",
    "sg:address":"1410 Encinal Ave",
    "sg:city":"Alameda",
    "sg:classifiers":[
        {
            "category":"Restaurant",
            "type":"Food & Drink"
        }
    ],
    "sg:phone":"+1 510 769 9787",
    "sg:postcode":"94501",
    "sg:province":"CA",
    "sg:tags":[
        "chinese"
    ],
    "wof:name":"Little Joe's Express",
    "wof:placetype":"venue"
},
  "geometry": {"coordinates":[-122.262001,37.770302],"type":"Point"}
}