{
  "type": "Feature",
  "properties": {
    "iso:country":"US",
    "sg:address":"17 W Shaw Ave",
    "sg:city":"Clovis",
    "sg:classifiers":[
        {
            "category":"Retail",
            "subcategory":"Laundry & Dry Cleaning",
            "type":"Services"
        }
    ],
    "sg:phone":"+1 559 299 7111",
    "sg:postcode":"93612",
    "sg:province":"CA",
    "sg:tags":[
        "cleaners"
    ],
    "wof:name":"Lamoure's Cleaners & Laundry",
    "wof:placetype":"venue"
},
  "geometry": {"coordinates":[-119.70986499999999,36.808558],"type":"Point"}
}