{
  "type": "Feature",
  "properties": {
    "addr:full":"87 Scripps Dr Sacramento CA 95825",
    "addr:housenumber":"87",
    "addr:postcode":"95825",
    "addr:street":"Scripps Dr",
    "iso:country":"US",
    "sg:address":"87 Scripps Dr",
    "sg:city":"Sacramento",
    "sg:classifiers":[
        {
            "category":"Personal",
            "type":"Services"
        }
    ],
    "sg:phone":"+1 916 929 6748",
    "sg:postcode":"95825",
    "sg:province":"CA",
    "sg:tags":[
        "therapist",
        "massage"
    ],
    "wof:name":"Shimmon Kim",
    "wof:placetype":"venue"
},
  "geometry": {"coordinates":[-121.409149,38.571369],"type":"Point"}
}