{
  "type": "Feature",
  "properties": {
    "iso:country":"US",
    "sg:address":"2650 Elm Ave Ste 101",
    "sg:city":"Long Beach",
    "sg:classifiers":[
        {
            "category":"Health Services",
            "subcategory":"Doctor",
            "type":"Services"
        }
    ],
    "sg:phone":"+1 562 595 0166",
    "sg:postcode":"90806",
    "sg:province":"CA",
    "wof:name":"Brakin Mario I MD Faap Inc",
    "wof:placetype":"venue"
},
  "geometry": {"coordinates":[-118.188004,33.804699],"type":"Point"}
}