{
  "type": "Feature",
  "properties": {
    "addr:full":"1040 W Ave J Lancaster CA 93534",
    "addr:housenumber":"1040",
    "addr:postcode":"93534",
    "addr:street":"W Ave J",
    "iso:country":"US",
    "sg:address":"1040 W Ave J",
    "sg:city":"Lancaster",
    "sg:classifiers":[
        {
            "category":"Government",
            "subcategory":"Court House",
            "type":"Public Place"
        },
        {
            "category":"Government",
            "subcategory":"Office",
            "type":"Public Place"
        }
    ],
    "sg:phone":"+1 661 949 6501",
    "sg:postcode":"93534",
    "sg:province":"CA",
    "sg:tags":[
        "state",
        "system"
    ],
    "wof:name":"Los Angeles County Superior Ct",
    "wof:placetype":"venue"
},
  "geometry": {"coordinates":[-118.148934,34.689281],"type":"Point"}
}