{
  "type": "Feature",
  "properties": {
    "addr:full":"41060 High St Fremont CA 94538",
    "addr:housenumber":"41060",
    "addr:postcode":"94538",
    "addr:street":"High St",
    "iso:country":"US",
    "sg:address":"41060 High St",
    "sg:city":"Fremont",
    "sg:classifiers":[
        {
            "category":"Retail",
            "subcategory":"Auto Repair",
            "type":"Services"
        }
    ],
    "sg:phone":"+1 510 490 3624",
    "sg:postcode":"94538",
    "sg:province":"CA",
    "sg:tags":[
        "repairing",
        "automobile"
    ],
    "wof:name":"ATR Auto Svc",
    "wof:placetype":"venue"
},
  "geometry": {"coordinates":[-121.95639199999999,37.535451],"type":"Point"}
}