{
  "type": "Feature",
  "properties": {
    "iso:country":"US",
    "sg:address":"47550 Kato Rd",
    "sg:city":"Fremont",
    "sg:classifiers":[
        {
            "category":"Professional",
            "subcategory":"Business Services",
            "type":"Services"
        }
    ],
    "sg:phone":"+1 510 353 0177",
    "sg:postcode":"94538",
    "sg:province":"CA",
    "sg:tags":[
        "packaging"
    ],
    "wof:name":"Extron Logistics",
    "wof:placetype":"venue"
},
  "geometry": {"coordinates":[-121.932039,37.476593],"type":"Point"}
}