{
  "type": "Feature",
  "properties": {
    "addr:full":"1306 James Ave Redwood City CA 94062",
    "addr:housenumber":"1306",
    "addr:postcode":"94062",
    "addr:street":"James Ave",
    "iso:country":"US",
    "sg:address":"1306 James Ave",
    "sg:city":"Redwood City",
    "sg:classifiers":[
        {
            "category":"Building & Trades",
            "subcategory":"Construction",
            "type":"Services"
        }
    ],
    "sg:phone":"+1 650 363 2706",
    "sg:postcode":"94062",
    "sg:province":"CA",
    "sg:tags":[
        "roofing",
        "contractor"
    ],
    "wof:name":"Allen-Ricci's Roofing Co",
    "wof:placetype":"venue"
},
  "geometry": {"coordinates":[-122.24347899999999,37.4763],"type":"Point"}
}