{
  "type": "Feature",
  "properties": {
    "addr:full":"1550 Pacific Ave Santa Rosa CA 95404",
    "addr:housenumber":"1550",
    "addr:postcode":"95404",
    "addr:street":"Pacific Ave",
    "iso:country":"US",
    "sg:address":"1550 Pacific Ave",
    "sg:city":"Santa Rosa",
    "sg:classifiers":[
        {
            "category":"Social Services",
            "subcategory":"Child Care",
            "type":"Services"
        }
    ],
    "sg:phone":"+1 707 542 7396",
    "sg:postcode":"95404",
    "sg:province":"CA",
    "sg:tags":[
        "kindergarten",
        "academic",
        "school"
    ],
    "wof:name":"Presbyterian Preschool",
    "wof:placetype":"venue"
},
  "geometry": {"coordinates":[-122.70312,38.452913],"type":"Point"}
}