{
  "type": "Feature",
  "properties": {
    "iso:country":"US",
    "sg:address":"2271 Tustin St",
    "sg:city":"Orange",
    "sg:classifiers":[
        {
            "category":"Fast Food",
            "type":"Food & Drink"
        },
        {
            "category":"Restaurant",
            "type":"Food & Drink"
        }
    ],
    "sg:phone":"+1 714 283 1628",
    "sg:postcode":"92865",
    "sg:province":"CA",
    "sg:tags":[
        "fusion",
        "asian"
    ],
    "wof:name":"Tikiyaki",
    "wof:placetype":"venue"
},
  "geometry": {"coordinates":[-117.835992,33.826154],"type":"Point"}
}