{
  "type": "Feature",
  "properties": {
    "iso:country":"US",
    "sg:address":"2019 Santa Anita Ave",
    "sg:city":"South El Monte",
    "sg:classifiers":[
        {
            "category":"Banks & Credit Unions",
            "subcategory":"Bank",
            "type":"Services"
        }
    ],
    "sg:phone":"+1 626 443 1534",
    "sg:postcode":"91733",
    "sg:province":"CA",
    "sg:tags":[
        "company",
        "trust"
    ],
    "wof:name":"James Jebbia Norf Trust",
    "wof:placetype":"venue"
},
  "geometry": {"coordinates":[-118.04246999999999,34.053497],"type":"Point"}
}