{
  "type": "Feature",
  "properties": {
    "addr:full":"19 Spectrum Pointe Dr Lake Forest CA 92630",
    "addr:housenumber":"19",
    "addr:postcode":"92630",
    "addr:street":"Spectrum Pointe Dr",
    "iso:country":"US",
    "sg:address":"19 Spectrum Pointe Dr",
    "sg:city":"Lake Forest",
    "sg:classifiers":[
        {
            "category":"Autos & Motor Vehicles",
            "subcategory":"Automobile Sales",
            "type":"Retail Goods"
        },
        {
            "category":"Insurance",
            "subcategory":"Hazard Insurance",
            "type":"Services"
        }
    ],
    "sg:phone":"+1 949 387 7774",
    "sg:postcode":"92630",
    "sg:province":"CA",
    "sg:tags":[
        "automotive"
    ],
    "sg:website":"www.AutoAppraisalNetwork.com",
    "wof:name":"Auto Appraisal Network",
    "wof:placetype":"venue"
},
  "geometry": {"coordinates":[-117.691361,33.661006],"type":"Point"}
}