{
  "type": "Feature",
  "properties": {
    "addr:full":"227 Atlantic Ave Shafter CA 93263",
    "addr:housenumber":"227",
    "addr:postcode":"93263",
    "addr:street":"Atlantic Ave",
    "iso:country":"US",
    "sg:address":"227 Atlantic Ave",
    "sg:city":"Shafter",
    "sg:classifiers":[
        {
            "category":"Wholesale",
            "subcategory":"Apparel",
            "type":"Manufacturing & Wholesale Goods"
        }
    ],
    "sg:phone":"+1 661 746 0970",
    "sg:postcode":"93263",
    "sg:province":"CA",
    "sg:tags":[
        "textile"
    ],
    "wof:name":"Cavalier Mills Inc",
    "wof:placetype":"venue"
},
  "geometry": {"coordinates":[-119.28239499999999,35.50159],"type":"Point"}
}