{
  "type": "Feature",
  "properties": {
    "addr:full":"12827 Harbor Blvd Garden Grove CA 92648",
    "addr:housenumber":"12827",
    "addr:postcode":"92648",
    "addr:street":"Harbor Blvd",
    "iso:country":"US",
    "sg:address":"12827 Harbor Blvd",
    "sg:city":"Garden Grove",
    "sg:classifiers":[
        {
            "category":"Home & Garden",
            "subcategory":"Household Appliances",
            "type":"Retail Goods"
        },
        {
            "category":"Home & Garden",
            "subcategory":"Building Materials",
            "type":"Retail Goods"
        }
    ],
    "sg:phone":"+1 714 590 8729",
    "sg:postcode":"92648",
    "sg:province":"CA",
    "sg:tags":[
        "supply"
    ],
    "sg:website":"www.ReStoreOC.org",
    "wof:name":"Habitat for Humanity OC ReStore",
    "wof:placetype":"venue"
},
  "geometry": {"coordinates":[-117.916684,33.776385],"type":"Point"}
}