{
  "type": "Feature",
  "properties": {
    "iso:country":"US",
    "sg:address":"2120 Market St",
    "sg:city":"San Francisco",
    "sg:classifiers":[
        {
            "category":"Health Services",
            "subcategory":"Health Practitioner",
            "type":"Services"
        }
    ],
    "sg:phone":"+1 415 552 3337",
    "sg:postcode":"94114",
    "sg:province":"CA",
    "sg:tags":[
        "acupuncture"
    ],
    "wof:name":"Cindy Icke",
    "wof:placetype":"venue"
},
  "geometry": {"coordinates":[-122.429036,37.767671],"type":"Point"}
}