{
  "type": "Feature",
  "properties": {
    "addr:full":"1688 N Zediker Ave Sanger CA 93657",
    "addr:housenumber":"1688",
    "addr:postcode":"ca 93657",
    "addr:street":"N Zediker Ave",
    "iso:country":"US",
    "sg:address":"1688 N Zediker Ave",
    "sg:city":"Sanger",
    "sg:classifiers":[
        {
            "category":"Farming",
            "subcategory":"Orchard",
            "type":"Manufacturing & Wholesale Goods"
        }
    ],
    "sg:phone":"+1 559 875 1886",
    "sg:postcode":"93657",
    "sg:province":"CA",
    "sg:tags":[
        "grape",
        "citrus",
        "trucking",
        "vineyard",
        "grove",
        "fruit",
        "local"
    ],
    "wof:name":"Fancher Greek Packing",
    "wof:placetype":"venue"
},
  "geometry": {"coordinates":[-119.519808,36.760619],"type":"Point"}
}