{
  "type": "Feature",
  "properties": {
    "addr:full":"30630 Rancho California Rd Temecula CA 92591",
    "addr:housenumber":"30630",
    "addr:postcode":"92591",
    "addr:street":"Rancho California Rd",
    "iso:country":"US",
    "sg:address":"30630 Rancho California Rd",
    "sg:city":"Temecula",
    "sg:classifiers":[
        {
            "category":"Health Services",
            "subcategory":"Chiropractor",
            "type":"Services"
        }
    ],
    "sg:phone":"+1 951 694 6350",
    "sg:postcode":"92591",
    "sg:province":"CA",
    "wof:name":"Palomar Village Chiropractic",
    "wof:placetype":"venue"
},
  "geometry": {"coordinates":[-117.126197,33.508321],"type":"Point"}
}