{
  "type": "Feature",
  "properties": {
    "addr:full":"5800 Llano Rd Atascadero CA 93422",
    "addr:postcode":"5800;93422",
    "addr:street":"Llano Rd",
    "iso:country":"US",
    "sg:address":"5800 Llano Rd",
    "sg:city":"Atascadero",
    "sg:classifiers":[
        {
            "category":"Freight",
            "type":"Transportation"
        }
    ],
    "sg:phone":"+1 805 748 4308",
    "sg:postcode":"93422",
    "sg:province":"CA",
    "sg:tags":[
        "operator",
        "local",
        "trucking"
    ],
    "wof:name":"Deliveries Unlimited",
    "wof:placetype":"venue"
},
  "geometry": {"coordinates":[-120.70777,35.479158],"type":"Point"}
}