{
  "type": "Feature",
  "properties": {
    "iso:country":"US",
    "sg:address":"2215 Truxtun Ave",
    "sg:city":"Bakersfield",
    "sg:classifiers":[
        {
            "category":"Health Services",
            "subcategory":"Doctor",
            "type":"Services"
        }
    ],
    "sg:phone":"+1 661 632 5275",
    "sg:postcode":"93301",
    "sg:province":"CA",
    "sg:tags":[
        "physician",
        "surgeon"
    ],
    "wof:name":"Reagan Bellinghausen MD",
    "wof:placetype":"venue"
},
  "geometry": {"coordinates":[-119.028047,35.373295],"type":"Point"}
}