{
  "type": "Feature",
  "properties": {
    "addr:full":"13071 Red Dog Rd Nevada City CA 95959",
    "addr:housenumber":"13071",
    "addr:postcode":"95959",
    "addr:street":"Red Dog Rd",
    "iso:country":"US",
    "sg:address":"13071 Red Dog Rd",
    "sg:city":"Nevada City",
    "sg:classifiers":[
        {
            "category":"Communications",
            "subcategory":"Film & Video Production",
            "type":"Services"
        }
    ],
    "sg:phone":"+1 530 265 2201",
    "sg:postcode":"95959",
    "sg:province":"CA",
    "sg:tags":[
        "taping"
    ],
    "wof:name":"SLP Productions",
    "wof:placetype":"venue"
},
  "geometry": {"coordinates":[-120.964838,39.25567],"type":"Point"}
}