{
  "type": "Feature",
  "properties": {
    "addr:full":"2622 Sweetwater Rd Spring Valley CA 91977",
    "addr:housenumber":"2622",
    "addr:postcode":"91977",
    "addr:street":"Sweetwater Rd",
    "iso:country":"US",
    "sg:address":"2622 Sweetwater Rd",
    "sg:city":"Spring Valley",
    "sg:classifiers":[
        {
            "category":"Autos & Motor Vehicles",
            "subcategory":"Boat Sales",
            "type":"Retail Goods"
        }
    ],
    "sg:phone":"+1 619 465 3562",
    "sg:postcode":"91977",
    "sg:province":"CA",
    "sg:tags":[
        "top",
        "upholstery",
        "cover"
    ],
    "wof:name":"Boat & Auto Upholstery",
    "wof:placetype":"venue"
},
  "geometry": {"coordinates":[-117.01456399999999,32.734395],"type":"Point"}
}