{
  "type": "Feature",
  "properties": {
    "addr:full":"3838 California Street Rm 616 San Francisco CA 94118",
    "addr:housenumber":"3838;616",
    "addr:postcode":"94118",
    "addr:street":"California Street Rm",
    "iso:country":"US",
    "sg:address":"3838 California Street Rm 616",
    "sg:city":"San Francisco",
    "sg:classifiers":[
        {
            "category":"Health Services",
            "subcategory":"Doctor",
            "type":"Services"
        }
    ],
    "sg:phone":"+1 415 668 0411",
    "sg:postcode":"94118",
    "sg:province":"CA",
    "wof:name":"Chiu Yanek S Y MD",
    "wof:placetype":"venue"
},
  "geometry": {"coordinates":[-122.459999,37.7812],"type":"Point"}
}