{
  "type": "Feature",
  "properties": {
    "iso:country":"US",
    "sg:address":"1455 Van Ness Ave",
    "sg:city":"Fresno",
    "sg:classifiers":[
        {
            "category":"Building & Trades",
            "subcategory":"Plumbing",
            "type":"Services"
        }
    ],
    "sg:phone":"+1 559 227 6986",
    "sg:postcode":"93721",
    "sg:province":"CA",
    "sg:tags":[
        "plumbing-drain",
        "cleaning",
        "sewer"
    ],
    "wof:name":"Drain Service And Plumbing Repair",
    "wof:placetype":"venue"
},
  "geometry": {"coordinates":[-119.794085,36.739146],"type":"Point"}
}