{
  "type": "Feature",
  "properties": {
    "iso:country":"US",
    "sg:address":"21416 Ventura Blvd",
    "sg:city":"Woodland Hills",
    "sg:classifiers":[
        {
            "category":"Professional",
            "subcategory":"Printing & Photocopies",
            "type":"Services"
        }
    ],
    "sg:phone":"+1 818 703 8686",
    "sg:postcode":"91364",
    "sg:province":"CA",
    "wof:name":"California Copy & Printing Center",
    "wof:placetype":"venue"
},
  "geometry": {"coordinates":[-118.598,34.168098],"type":"Point"}
}