{
  "type": "Feature",
  "properties": {
    "addr:full":"3171 Adams Ave Ste D San Diego CA 92101",
    "addr:housenumber":"3171",
    "addr:postcode":"92101",
    "addr:street":"Adams Ave Ste D",
    "iso:country":"US",
    "sg:address":"3171 Adams Ave Ste D",
    "sg:city":"San Diego",
    "sg:classifiers":[
        {
            "category":"Government",
            "subcategory":"City Hall",
            "type":"Public Place"
        },
        {
            "category":"Personal",
            "type":"Services"
        }
    ],
    "sg:phone":"+1 619 501 1715",
    "sg:postcode":"92101",
    "sg:province":"CA",
    "sg:tags":[
        "local"
    ],
    "sg:website":"www.goldenstatefireprotection.com",
    "wof:name":"Golden State Fire Protection",
    "wof:placetype":"venue"
},
  "geometry": {"coordinates":[-117.12568400000001,32.763103],"type":"Point"}
}