{
  "type": "Feature",
  "properties": {
    "iso:country":"US",
    "sg:address":"1180 Philadelphia St",
    "sg:city":"Pomona",
    "sg:classifiers":[
        {
            "category":"Food & Beverages",
            "subcategory":"Groceries & Convenience Stores",
            "type":"Retail Goods"
        }
    ],
    "sg:phone":"+1 909 591 8304",
    "sg:postcode":"91766",
    "sg:province":"CA",
    "sg:tags":[
        "market"
    ],
    "wof:name":"Mercadito Mexico",
    "wof:placetype":"venue"
},
  "geometry": {"coordinates":[-117.732343,34.033647],"type":"Point"}
}