{
  "type": "Feature",
  "properties": {
    "addr:full":"210 Railroad Ave Danville CA 94526",
    "addr:housenumber":"210",
    "addr:postcode":"94526",
    "addr:street":"Railroad Ave",
    "iso:country":"US",
    "sg:address":"210 Railroad Ave",
    "sg:city":"Danville",
    "sg:classifiers":[
        {
            "category":"Real Estate",
            "subcategory":"Real Estate Services",
            "type":"Services"
        }
    ],
    "sg:phone":"+1 925 838 1098",
    "sg:postcode":"94526",
    "sg:province":"CA",
    "sg:tags":[
        "company",
        "title"
    ],
    "sg:website":"www.ticoronline.com",
    "wof:name":"Ticor Title Insurance",
    "wof:placetype":"venue"
},
  "geometry": {"coordinates":[-121.998869,37.819989],"type":"Point"}
}