{
  "type": "Feature",
  "properties": {
    "addr:full":"1115 High St Auburn CA 95603",
    "addr:housenumber":"1115",
    "addr:postcode":"ca 95603",
    "addr:street":"High St",
    "iso:country":"US",
    "sg:address":"1115 High St",
    "sg:city":"Auburn",
    "sg:classifiers":[
        {
            "category":"Health Services",
            "subcategory":"Health Practitioner",
            "type":"Services"
        }
    ],
    "sg:phone":"+1 530 823 3352",
    "sg:postcode":"95603",
    "sg:province":"CA",
    "sg:tags":[
        "hypnotist"
    ],
    "wof:name":"Heart",
    "wof:placetype":"venue"
},
  "geometry": {"coordinates":[-121.071371,38.897148],"type":"Point"}
}