{
  "type": "Feature",
  "properties": {
    "iso:country":"US",
    "sg:address":"4127 N Long Beach Blvd",
    "sg:city":"Long Beach",
    "sg:classifiers":[
        {
            "category":"Building & Trades",
            "subcategory":"Construction",
            "type":"Services"
        }
    ],
    "sg:phone":"+1 562 426 5553",
    "sg:postcode":"90807",
    "sg:province":"CA",
    "sg:tags":[
        "marble",
        "contractor"
    ],
    "wof:name":"Millennium Marble Co",
    "wof:placetype":"venue"
},
  "geometry": {"coordinates":[-118.189421,33.832631],"type":"Point"}
}