{
  "type": "Feature",
  "properties": {
    "addr:full":"609 Broadway Chula Vista CA 91910",
    "addr:housenumber":"609",
    "addr:postcode":"91910",
    "addr:street":"Broadway",
    "iso:country":"US",
    "sg:address":"609 Broadway",
    "sg:city":"Chula Vista",
    "sg:classifiers":[
        {
            "category":"Restaurant",
            "type":"Food & Drink"
        }
    ],
    "sg:menulink":"http://www.allmenus.com/ca/san-diego/149878-subway/menu/",
    "sg:phone":"+1 619 585 0373",
    "sg:postcode":"91910",
    "sg:province":"CA",
    "sg:tags":[
        "american",
        "sandwich"
    ],
    "wof:name":"Subway",
    "wof:placetype":"venue"
},
  "geometry": {"coordinates":[-117.087791,32.62711],"type":"Point"}
}