{
  "type": "Feature",
  "properties": {
    "iso:country":"US",
    "sg:address":"17846 Ridgeway Rd",
    "sg:city":"Granada Hills",
    "sg:classifiers":[
        {
            "category":"Professional",
            "subcategory":"Computer Services",
            "type":"Services"
        }
    ],
    "sg:phone":"+1 818 831 0970",
    "sg:postcode":"91344",
    "sg:province":"CA",
    "sg:tags":[
        "datum"
    ],
    "wof:name":"Global Marketing Technology",
    "wof:placetype":"venue"
},
  "geometry": {"coordinates":[-118.523141,34.284093],"type":"Point"}
}