{
  "type": "Feature",
  "properties": {
    "iso:country":"US",
    "sg:address":"11863 Grevillea Ave",
    "sg:city":"Hawthorne",
    "sg:classifiers":[
        {
            "category":"Shopping",
            "subcategory":"Computers & Home Electronics",
            "type":"Retail Goods"
        }
    ],
    "sg:phone":"+1 310 644 3950",
    "sg:postcode":"90250",
    "sg:province":"CA",
    "sg:tags":[
        "software"
    ],
    "wof:name":"WPS & Assoc",
    "wof:placetype":"venue"
},
  "geometry": {"coordinates":[-118.354825,33.92625],"type":"Point"}
}