{
  "type": "Feature",
  "properties": {
    "addr:full":"400 el Pintado Rd Danville CA 94526",
    "addr:housenumber":"400",
    "addr:postcode":"94526",
    "addr:street":"El Pintado Rd",
    "iso:country":"US",
    "sg:address":"400 el Pintado Rd",
    "sg:city":"Danville",
    "sg:classifiers":[
        {
            "category":"Social Services",
            "subcategory":"Adult Care",
            "type":"Services"
        }
    ],
    "sg:phone":"+1 925 838 3020",
    "sg:postcode":"94526",
    "sg:province":"CA",
    "sg:tags":[
        "home",
        "residential"
    ],
    "wof:name":"Barrington Court Residence",
    "wof:placetype":"venue"
},
  "geometry": {"coordinates":[-121.999304,37.83272],"type":"Point"}
}