{
  "type": "Feature",
  "properties": {
    "iso:country":"US",
    "sg:address":"25621 Via Alisa",
    "sg:city":"Valencia",
    "sg:classifiers":[
        {
            "category":"Professional",
            "type":"Services"
        }
    ],
    "sg:phone":"+1 661 645 4260",
    "sg:postcode":"91381",
    "sg:province":"CA",
    "sg:tags":[
        "caterer"
    ],
    "wof:name":"Panache Catering",
    "wof:placetype":"venue"
},
  "geometry": {"coordinates":[-118.58476899999999,34.405028],"type":"Point"}
}