{
  "type": "Feature",
  "properties": {
    "iso:country":"US",
    "sg:address":"11700 Blucher Ave",
    "sg:city":"Granada Hills",
    "sg:classifiers":[
        {
            "category":"Wholesale",
            "subcategory":"Durable Goods & Equipment",
            "type":"Manufacturing & Wholesale Goods"
        }
    ],
    "sg:phone":"+1 818 831 7980",
    "sg:postcode":"91344",
    "sg:province":"CA",
    "wof:name":"North Hill Recycling",
    "wof:placetype":"venue"
},
  "geometry": {"coordinates":[-118.469979,34.280083],"type":"Point"}
}