{
  "type": "Feature",
  "properties": {
    "iso:country":"US",
    "sg:address":"5243 Mission St",
    "sg:city":"San Francisco",
    "sg:classifiers":[
        {
            "category":"Banks & Credit Unions",
            "subcategory":"Bank",
            "type":"Services"
        }
    ],
    "sg:phone":"+1 415 239 1090",
    "sg:postcode":"94112",
    "sg:province":"CA",
    "wof:name":"LBP Remittance Company",
    "wof:placetype":"venue"
},
  "geometry": {"coordinates":[-122.442052,37.714929],"type":"Point"}
}