{
  "type": "Feature",
  "properties": {
    "addr:full":"1601 E Muncie Ave Fresno CA 93720",
    "addr:housenumber":"1601",
    "addr:postcode":"93720",
    "addr:street":"E Muncie Ave",
    "iso:country":"US",
    "sg:address":"1601 E Muncie Ave",
    "sg:city":"Fresno",
    "sg:classifiers":[
        {
            "category":"Restaurant",
            "type":"Food & Drink"
        }
    ],
    "sg:phone":"+1 559 323 9195",
    "sg:postcode":"93720",
    "sg:province":"CA",
    "wof:name":"House Of Dumplings",
    "wof:placetype":"venue"
},
  "geometry": {"coordinates":[-119.75675200000001,36.854207],"type":"Point"}
}