{
  "type": "Feature",
  "properties": {
    "addr:full":"8075 W 3rd St Los Angeles CA 90048",
    "addr:housenumber":"8075",
    "addr:postcode":"90048",
    "addr:street":"W 3Rd St",
    "iso:country":"US",
    "sg:address":"8075 W 3rd St",
    "sg:city":"Los Angeles",
    "sg:classifiers":[
        {
            "category":"Education",
            "subcategory":"Vocational School",
            "type":"Public Place"
        }
    ],
    "sg:phone":"+1 323 933 8006",
    "sg:postcode":"90048",
    "sg:province":"CA",
    "sg:website":"www.lapsinc.com",
    "wof:name":"LAPS-Los Angeles Pro Servers",
    "wof:placetype":"venue"
},
  "geometry": {"coordinates":[-118.36523,34.072097],"type":"Point"}
}