{
  "type": "Feature",
  "properties": {
    "addr:full":"1120 3rd St South Lake Tahoe CA 96150",
    "addr:housenumber":"1120",
    "addr:postcode":"96150",
    "addr:street":"3Rd St",
    "iso:country":"US",
    "sg:address":"1120 3rd St",
    "sg:city":"South Lake Tahoe",
    "sg:classifiers":[
        {
            "category":"Government",
            "subcategory":"Office",
            "type":"Public Place"
        }
    ],
    "sg:phone":"+1 530 573 3280",
    "sg:postcode":"96150",
    "sg:province":"CA",
    "wof:name":"El Dorado County Family Spprt",
    "wof:placetype":"venue"
},
  "geometry": {"coordinates":[-119.99669400000001,38.912918],"type":"Point"}
}