{
  "type": "Feature",
  "properties": {
    "iso:country":"US",
    "sg:address":"3643 Tivola St",
    "sg:city":"Santa Ynez",
    "sg:classifiers":[
        {
            "category":"Professional",
            "type":"Services"
        }
    ],
    "sg:phone":"+1 805 688 7466",
    "sg:postcode":"93460",
    "sg:province":"CA",
    "wof:name":"Charles R Smith",
    "wof:placetype":"venue"
},
  "geometry": {"coordinates":[-120.079494,34.614411],"type":"Point"}
}