{
  "type": "Feature",
  "properties": {
    "addr:full":"880 Main St Cambria CA 93428",
    "addr:housenumber":"880",
    "addr:postcode":"93428",
    "addr:street":"Main St",
    "iso:country":"US",
    "sg:address":"880 Main St",
    "sg:city":"Cambria",
    "sg:classifiers":[
        {
            "category":"Shopping",
            "type":"Retail Goods"
        }
    ],
    "sg:phone":"+1 805 927 8190",
    "sg:postcode":"93428",
    "sg:province":"CA",
    "sg:tags":[
        "art",
        "gallery",
        "dealer"
    ],
    "wof:name":"Allied Art Assn",
    "wof:placetype":"venue"
},
  "geometry": {"coordinates":[-121.09674,35.564951],"type":"Point"}
}