{
  "type": "Feature",
  "properties": {
    "iso:country":"US",
    "sg:address":"12128 Front St",
    "sg:city":"Norwalk",
    "sg:classifiers":[
        {
            "category":"Coffee & Tea",
            "type":"Food & Drink"
        },
        {
            "category":"Restaurant",
            "type":"Food & Drink"
        }
    ],
    "sg:phone":"+1 562 219 0699",
    "sg:postcode":"90650",
    "sg:province":"CA",
    "sg:tags":[
        "espresso"
    ],
    "wof:name":"Papa Pambiancos Cafe",
    "wof:placetype":"venue"
},
  "geometry": {"coordinates":[-118.075466,33.908142],"type":"Point"}
}