{
  "type": "Feature",
  "properties": {
    "addr:full":"12128 Front St Norwalk CA 90650",
    "addr:housenumber":"12128",
    "addr:postcode":"90650",
    "addr:street":"Front St",
    "iso:country":"US",
    "sg:address":"12128 Front St",
    "sg:city":"Norwalk",
    "sg:classifiers":[
        {
            "category":"Coffee & Tea",
            "type":"Food & Drink"
        },
        {
            "category":"Restaurant",
            "type":"Food & Drink"
        }
    ],
    "sg:phone":"+1 562 219 0699",
    "sg:postcode":"90650",
    "sg:province":"CA",
    "sg:tags":[
        "espresso"
    ],
    "wof:name":"Papa Pambiancos Cafe",
    "wof:placetype":"venue"
},
  "geometry": {"coordinates":[-118.07546600000001,33.908142],"type":"Point"}
}