{
  "type": "Feature",
  "properties": {
    "iso:country":"US",
    "sg:address":"496 N Garfield Ave",
    "sg:city":"Montebello",
    "sg:classifiers":[
        {
            "category":"Shopping",
            "subcategory":"Clothing, Apparel, & Fashions",
            "type":"Retail Goods"
        }
    ],
    "sg:phone":"+1 323 838 8073",
    "sg:postcode":"90640",
    "sg:province":"CA",
    "sg:tags":[
        "uniform"
    ],
    "sg:website":"www.uniformexpressltd.com",
    "wof:name":"Uniform Express LTD",
    "wof:placetype":"venue"
},
  "geometry": {"coordinates":[-118.134039,34.022076],"type":"Point"}
}