{
  "type": "Feature",
  "properties": {
    "addr:full":"3517 Hillcap Avenue San Jose CA 95136",
    "addr:housenumber":"3517",
    "addr:postcode":"95136",
    "addr:street":"Hillcap Avenue",
    "iso:country":"US",
    "sg:address":"3517 Hillcap Avenue",
    "sg:city":"San Jose",
    "sg:classifiers":[
        {
            "category":"Retail",
            "subcategory":"Auto Rental",
            "type":"Services"
        }
    ],
    "sg:phone":"+1 408 361 0430",
    "sg:postcode":"95136",
    "sg:province":"CA",
    "sg:tags":[
        "car"
    ],
    "sg:website":"www.enterprise.com",
    "wof:name":"Enterprise Rent-A-Car",
    "wof:placetype":"venue"
},
  "geometry": {"coordinates":[-121.844273,37.281076],"type":"Point"}
}