{
  "type": "Feature",
  "properties": {
    "addr:full":"672 L St Chula Vista CA 91911",
    "addr:housenumber":"672",
    "addr:postcode":"91911",
    "addr:street":"L St",
    "iso:country":"US",
    "sg:address":"672 L St",
    "sg:city":"Chula Vista",
    "sg:classifiers":[
        {
            "category":"Shopping",
            "subcategory":"Clothing, Apparel, & Fashions",
            "type":"Retail Goods"
        }
    ],
    "sg:phone":"+1 619 422 2172",
    "sg:postcode":"91911",
    "sg:province":"CA",
    "sg:tags":[
        "sport",
        "wear",
        "sportswear"
    ],
    "wof:name":"M & D Retailers",
    "wof:placetype":"venue"
},
  "geometry": {"coordinates":[-117.08899700000001,32.615898],"type":"Point"}
}