{
  "type": "Feature",
  "properties": {
    "iso:country":"US",
    "sg:address":"555 California St",
    "sg:city":"San Francisco",
    "sg:classifiers":[
        {
            "category":"Insurance",
            "subcategory":"Insurance Agent",
            "type":"Services"
        }
    ],
    "sg:phone":"+1 415 781 1700",
    "sg:postcode":"94104",
    "sg:province":"CA",
    "sg:website":"www.genre.com",
    "wof:name":"General Reinsurance Corp",
    "wof:placetype":"venue"
},
  "geometry": {"coordinates":[-122.40436699999999,37.792571],"type":"Point"}
}