{
  "type": "Feature",
  "properties": {
    "addr:full":"950 Wind Drift Dr Carlsbad CA 92011",
    "addr:housenumber":"950",
    "addr:postcode":"92011",
    "addr:street":"Wind Drift Dr",
    "iso:country":"US",
    "sg:address":"950 Wind Drift Dr",
    "sg:city":"Carlsbad",
    "sg:classifiers":[
        {
            "category":"Professional",
            "type":"Services"
        }
    ],
    "sg:phone":"+1 760 431 0662",
    "sg:postcode":"92011",
    "sg:province":"CA",
    "wof:name":"Glamourtech Inc",
    "wof:placetype":"venue"
},
  "geometry": {"coordinates":[-117.311825,33.11748],"type":"Point"}
}