{
  "type": "Feature",
  "properties": {
    "addr:full":"4470 Highway 78 Julian CA 92036",
    "addr:housenumber":"4470",
    "addr:postcode":"92036",
    "addr:street":"Highway 78",
    "iso:country":"US",
    "sg:address":"4470 Highway 78",
    "sg:city":"Julian",
    "sg:classifiers":[
        {
            "category":"Shopping",
            "subcategory":"Gifts & Souvenirs",
            "type":"Retail Goods"
        }
    ],
    "sg:phone":"+1 760 765 2159",
    "sg:postcode":"92036",
    "sg:province":"CA",
    "sg:tags":[
        "shop"
    ],
    "wof:name":"American Gardener",
    "wof:placetype":"venue"
},
  "geometry": {"coordinates":[-116.646308,33.097487],"type":"Point"}
}