{
  "type": "Feature",
  "properties": {
    "iso:country":"US",
    "sg:address":"5445 Balboa Blvd",
    "sg:city":"Encino",
    "sg:classifiers":[
        {
            "category":"Professional",
            "subcategory":"Lawyer & Legal Services",
            "type":"Services"
        }
    ],
    "sg:phone":"+1 818 788 1888",
    "sg:postcode":"91316",
    "sg:province":"CA",
    "sg:tags":[
        "attorney"
    ],
    "wof:name":"Robert Rentzer",
    "wof:placetype":"venue"
},
  "geometry": {"coordinates":[-118.501167,34.170094],"type":"Point"}
}