{
  "type": "Feature",
  "properties": {
    "addr:full":"5940 E Washington Blvd Commerce CA 90040",
    "addr:housenumber":"5940",
    "addr:postcode":"90040",
    "addr:street":"E Washington Blvd",
    "iso:country":"US",
    "sg:address":"5940 E Washington Blvd",
    "sg:city":"Commerce",
    "sg:classifiers":[
        {
            "category":"Wholesale",
            "subcategory":"Non-durable Goods",
            "type":"Manufacturing & Wholesale Goods"
        }
    ],
    "sg:phone":"+1 323 725 3500",
    "sg:postcode":"90040",
    "sg:province":"CA",
    "sg:tags":[
        "rep",
        "merchandise-wholesale",
        "manufacturer"
    ],
    "wof:name":"Litco",
    "wof:placetype":"venue"
},
  "geometry": {"coordinates":[-118.151095,33.997379],"type":"Point"}
}