{
  "type": "Feature",
  "properties": {
    "addr:full":"41 S Capitol Ave San Jose CA 95127",
    "addr:housenumber":"41",
    "addr:postcode":"95127",
    "addr:street":"S Capitol Ave",
    "iso:country":"US",
    "sg:address":"41 S Capitol Ave",
    "sg:city":"San Jose",
    "sg:classifiers":[
        {
            "category":"Autos & Motor Vehicles",
            "subcategory":"Auto Supplies",
            "type":"Retail Goods"
        }
    ],
    "sg:phone":"+1 408 258 8273",
    "sg:postcode":"95127",
    "sg:province":"CA",
    "sg:tags":[
        "wheel",
        "repair",
        "cover"
    ],
    "sg:website":"www.caliwheels.com",
    "wof:name":"California Wheels",
    "wof:placetype":"venue"
},
  "geometry": {"coordinates":[-121.835026,37.36185],"type":"Point"}
}