{
  "type": "Feature",
  "properties": {
    "iso:country":"US",
    "sg:address":"1503 Aviation Blvd",
    "sg:city":"Redondo Beach",
    "sg:classifiers":[
        {
            "category":"Wholesale",
            "subcategory":"Electrical",
            "type":"Manufacturing & Wholesale Goods"
        }
    ],
    "sg:phone":"+1 310 379 4223",
    "sg:postcode":"90278",
    "sg:province":"CA",
    "sg:tags":[
        "alarm",
        "burglar",
        "system"
    ],
    "sg:website":"www.freezeframevideo.com",
    "wof:name":"Freeze Frame Video",
    "wof:placetype":"venue"
},
  "geometry": {"coordinates":[-118.38261199999999,33.869119],"type":"Point"}
}