{
  "type": "Feature",
  "properties": {
    "iso:country":"US",
    "sg:address":"2180 Roth Way",
    "sg:city":"Turlock",
    "sg:classifiers":[
        {
            "category":"Freight",
            "type":"Transportation"
        }
    ],
    "sg:phone":"+1 209 632 5935",
    "sg:postcode":"95380",
    "sg:province":"CA",
    "sg:tags":[
        "operator",
        "local",
        "trucking"
    ],
    "wof:name":"Tony Atwood Trucking",
    "wof:placetype":"venue"
},
  "geometry": {"coordinates":[-120.872999,37.50573],"type":"Point"}
}