{
  "type": "Feature",
  "properties": {
    "iso:country":"US",
    "sg:address":"1394 Vine St",
    "sg:city":"San Jose",
    "sg:classifiers":[
        {
            "category":"Autos & Motor Vehicles",
            "subcategory":"Automobile Sales",
            "type":"Retail Goods"
        }
    ],
    "sg:phone":"+1 408 297 9860",
    "sg:postcode":"95110",
    "sg:province":"CA",
    "sg:tags":[
        "car",
        "dealer"
    ],
    "wof:name":"Jake's Auto Sales",
    "wof:placetype":"venue"
},
  "geometry": {"coordinates":[-121.879909,37.314092],"type":"Point"}
}