{
  "type": "Feature",
  "properties": {
    "addr:full":"9495 San Fernando Rd Sun Valley CA 91352",
    "addr:housenumber":"9495",
    "addr:postcode":"91352",
    "addr:street":"San Fernando Rd",
    "iso:country":"US",
    "sg:address":"9495 San Fernando Rd",
    "sg:city":"Sun Valley",
    "sg:classifiers":[
        {
            "category":"Home & Garden",
            "subcategory":"Building Materials",
            "type":"Retail Goods"
        }
    ],
    "sg:phone":"+1 818 768 6424",
    "sg:postcode":"91352",
    "sg:province":"CA",
    "sg:tags":[
        "windows"
    ],
    "wof:name":"Ventsam Sash & Door Mfg Co",
    "wof:placetype":"venue"
},
  "geometry": {"coordinates":[-118.39568800000001,34.24076],"type":"Point"}
}