{
  "type": "Feature",
  "properties": {
    "iso:country":"US",
    "sg:address":"2457 Man O War Ct",
    "sg:city":"Atwater",
    "sg:classifiers":[
        {
            "category":"Education",
            "subcategory":"School",
            "type":"Public Place"
        },
        {
            "category":"Sports & Exercise",
            "subcategory":"Playing Field",
            "type":"Entertainment"
        }
    ],
    "sg:phone":"+1 209 722 7958",
    "sg:postcode":"95301",
    "sg:province":"CA",
    "sg:tags":[
        "personal",
        "development"
    ],
    "wof:name":"Central Valley Christian",
    "wof:placetype":"venue"
},
  "geometry": {"coordinates":[-120.55727,37.323752],"type":"Point"}
}