{
  "type": "Feature",
  "properties": {
    "iso:country":"US",
    "sg:address":"566 Casanova Ave",
    "sg:city":"Monterey",
    "sg:classifiers":[
        {
            "category":"Travel",
            "subcategory":"Travel Agent",
            "type":"Entertainment"
        }
    ],
    "sg:phone":"+1 831 649 1278",
    "sg:postcode":"93940",
    "sg:province":"CA",
    "sg:tags":[
        "agency"
    ],
    "wof:name":"Family Travel",
    "wof:placetype":"venue"
},
  "geometry": {"coordinates":[-121.854714,36.598937],"type":"Point"}
}