{
  "type": "Feature",
  "properties": {
    "iso:country":"US",
    "sg:address":"1537 S 56th St",
    "sg:city":"El Cerrito",
    "sg:classifiers":[
        {
            "category":"Manufacturing",
            "subcategory":"Printing",
            "type":"Manufacturing & Wholesale Goods"
        }
    ],
    "sg:phone":"+1 510 235 5800",
    "sg:postcode":"94530",
    "sg:province":"CA",
    "sg:tags":[
        "commercial",
        "printer",
        "lithographic"
    ],
    "wof:name":"Mercuri Litho Inc",
    "wof:placetype":"venue"
},
  "geometry": {"coordinates":[-122.31664600000001,37.920332],"type":"Point"}
}