{
  "type": "Feature",
  "properties": {
    "iso:country":"US",
    "sg:address":"741 Charles E Young Dr N",
    "sg:city":"Los Angeles",
    "sg:classifiers":[
        {
            "category":"Local Transit",
            "type":"Transportation"
        }
    ],
    "sg:phone":"+1 310 825 5977",
    "sg:postcode":"90024",
    "sg:province":"CA",
    "sg:tags":[
        "university"
    ],
    "wof:name":"Ucla Fleet Services",
    "wof:placetype":"venue"
},
  "geometry": {"coordinates":[-118.450267,34.071892],"type":"Point"}
}