{
  "type": "Feature",
  "properties": {
    "addr:full":"2641 Crenshaw Blvd Los Angeles CA 90016",
    "addr:housenumber":"2641",
    "addr:postcode":"90016",
    "addr:street":"Crenshaw Blvd",
    "iso:country":"US",
    "sg:address":"2641 Crenshaw Blvd",
    "sg:city":"Los Angeles",
    "sg:phone":"+1 323 972 2135",
    "sg:postcode":"90016",
    "sg:province":"CA",
    "sg:tags":[
        "farm",
        "field",
        "crop"
    ],
    "wof:name":"Stepping Up Into Society A",
    "wof:placetype":"venue"
},
  "geometry": {"coordinates":[-118.335176,34.031428],"type":"Point"}
}