{
  "type": "Feature",
  "properties": {
    "addr:full":"5900 Wilshire Blvd 2nd Fl Los Angeles CA 90036",
    "addr:housenumber":"5900",
    "addr:postcode":"90036",
    "addr:street":"Wilshire Blvd 2Nd Fl",
    "iso:country":"US",
    "sg:address":"5900 Wilshire Blvd 2nd Fl",
    "sg:city":"Los Angeles",
    "sg:classifiers":[
        {
            "category":"Health Services",
            "subcategory":"Chiropractor",
            "type":"Services"
        }
    ],
    "sg:phone":"+1 323 938 5575",
    "sg:postcode":"90036",
    "sg:province":"CA",
    "sg:website":"www.citysportshealth.com",
    "wof:name":"City Sports Health Center",
    "wof:placetype":"venue"
},
  "geometry": {"coordinates":[-118.35878700000001,34.062164],"type":"Point"}
}