{
  "type": "Feature",
  "properties": {
    "addr:full":"741 Academy Ave Sanger CA 93657",
    "addr:housenumber":"741",
    "addr:postcode":"ca 93657",
    "addr:street":"Academy Ave",
    "iso:country":"US",
    "sg:address":"741 Academy Ave",
    "sg:city":"Sanger",
    "sg:classifiers":[
        {
            "category":"Home & Garden",
            "subcategory":"Carpets & Floor Coverings",
            "type":"Retail Goods"
        }
    ],
    "sg:phone":"+1 559 875 4030",
    "sg:postcode":"93657",
    "sg:province":"CA",
    "sg:tags":[
        "material"
    ],
    "wof:name":"Carpet Corner",
    "wof:placetype":"venue"
},
  "geometry": {"coordinates":[-119.55585600000001,36.705735],"type":"Point"}
}