{
  "type": "Feature",
  "properties": {
    "iso:country":"US",
    "sg:address":"5455 Wilshire Blvd",
    "sg:city":"Los Angeles",
    "sg:classifiers":[
        {
            "category":"Restaurant",
            "type":"Food & Drink"
        }
    ],
    "sg:phone":"+1 323 936 4978",
    "sg:postcode":"90036",
    "sg:province":"CA",
    "sg:tags":[
        "cafeteria"
    ],
    "wof:name":"Janna's Cafe",
    "wof:placetype":"venue"
},
  "geometry": {"coordinates":[-118.348189,34.062328],"type":"Point"}
}