{
  "type": "Feature",
  "properties": {
    "addr:full":"251 Rhode Island St San Francisco CA 94103",
    "addr:housenumber":"251",
    "addr:postcode":"94103",
    "addr:street":"Rhode Island St",
    "iso:country":"US",
    "sg:address":"251 Rhode Island St",
    "sg:city":"San Francisco",
    "sg:classifiers":[
        {
            "category":"Restaurant",
            "type":"Food & Drink"
        },
        {
            "category":"Wholesale",
            "subcategory":"Groceries",
            "type":"Manufacturing & Wholesale Goods"
        }
    ],
    "sg:menulink":"http://www.allmenus.com/ca/san-francisco/276344-dos-pinas/menu/",
    "sg:phone":"+1 415 252 8220",
    "sg:postcode":"94103",
    "sg:province":"CA",
    "sg:tags":[
        "mexican"
    ],
    "wof:name":"Dos Pinas",
    "wof:placetype":"venue"
},
  "geometry": {"coordinates":[-122.40257800000001,37.766741],"type":"Point"}
}