{
  "type": "Feature",
  "properties": {
    "iso:country":"US",
    "sg:address":"1000 Pine Ave",
    "sg:city":"Redlands",
    "sg:classifiers":[
        {
            "category":"Building & Trades",
            "subcategory":"Construction",
            "type":"Services"
        }
    ],
    "sg:phone":"+1 909 798 9427",
    "sg:postcode":"92373",
    "sg:province":"CA",
    "sg:tags":[
        "contractor"
    ],
    "sg:website":"www.cottenconstruction.net",
    "wof:name":"Cotten Construction",
    "wof:placetype":"venue"
},
  "geometry": {"coordinates":[-117.19559700000001,34.212697],"type":"Point"}
}