{
  "type": "Feature",
  "properties": {
    "addr:full":"19800 Hirsch Ct Anderson CA 96007",
    "addr:postcode":"19800;96007",
    "addr:street":"Hirsch Ct",
    "iso:country":"US",
    "sg:address":"19800 Hirsch Ct",
    "sg:city":"Anderson",
    "sg:classifiers":[
        {
            "category":"Freight",
            "type":"Transportation"
        }
    ],
    "sg:phone":"+1 530 365 8240",
    "sg:postcode":"96007",
    "sg:province":"CA",
    "sg:tags":[
        "general"
    ],
    "wof:name":"Olsen Commercial & Storage",
    "wof:placetype":"venue"
},
  "geometry": {"coordinates":[-122.31994,40.464991],"type":"Point"}
}