{
  "type": "Feature",
  "properties": {
    "addr:full":"431 E Broadway Long Beach CA 90899",
    "addr:housenumber":"431",
    "addr:postcode":"90899",
    "addr:street":"E Broadway",
    "iso:country":"US",
    "sg:address":"431 E Broadway",
    "sg:city":"Long Beach",
    "sg:classifiers":[
        {
            "category":"Sports & Exercise",
            "subcategory":"Gym",
            "type":"Entertainment"
        },
        {
            "category":"Arena",
            "subcategory":"Sports Club",
            "type":"Entertainment"
        }
    ],
    "sg:phone":"+1 562 590 8888",
    "sg:postcode":"90899",
    "sg:province":"CA",
    "sg:tags":[
        "martial art",
        "yoga"
    ],
    "sg:website":"www.hathakwan.com",
    "wof:name":"Hatha Kwan Center",
    "wof:placetype":"venue"
},
  "geometry": {"coordinates":[-118.18688899999999,33.769304],"type":"Point"}
}