{
  "type": "Feature",
  "properties": {
    "addr:full":"812 Pacific Ave Santa Cruz CA 95060",
    "addr:housenumber":"812",
    "addr:postcode":"95060",
    "addr:street":"Pacific Ave",
    "iso:country":"US",
    "sg:address":"812 Pacific Ave",
    "sg:city":"Santa Cruz",
    "sg:classifiers":[
        {
            "category":"Shopping",
            "subcategory":"Used Merchandise",
            "type":"Retail Goods"
        }
    ],
    "sg:phone":"+1 831 429 8118",
    "sg:postcode":"95060",
    "sg:province":"CA",
    "sg:tags":[
        "vintage",
        "consignment"
    ],
    "wof:name":"The Salvation Army Store",
    "wof:placetype":"venue"
},
  "geometry": {"coordinates":[-122.025002,36.969898],"type":"Point"}
}