{
  "type": "Feature",
  "properties": {
    "iso:country":"US",
    "sg:address":"3571 Town Ct",
    "sg:city":"Auburn",
    "sg:classifiers":[
        {
            "category":"Building & Trades",
            "subcategory":"Electrical",
            "type":"Services"
        }
    ],
    "sg:phone":"+1 530 888 1092",
    "sg:postcode":"95602",
    "sg:province":"CA",
    "sg:tags":[
        "electric",
        "contractor"
    ],
    "wof:name":"California Electrical Contrs",
    "wof:placetype":"venue"
},
  "geometry": {"coordinates":[-121.099076,38.947261],"type":"Point"}
}