{
  "type": "Feature",
  "properties": {
    "addr:full":"3375 Browns Valley Rd Napa CA 94558",
    "addr:housenumber":"3375",
    "addr:postcode":"94558",
    "addr:street":"Browns Valley Rd",
    "iso:country":"US",
    "sg:address":"3375 Browns Valley Rd",
    "sg:city":"Napa",
    "sg:classifiers":[
        {
            "category":"Home & Garden",
            "subcategory":"Building Materials",
            "type":"Retail Goods"
        }
    ],
    "sg:phone":"+1 707 224 6877",
    "sg:postcode":"94558",
    "sg:province":"CA",
    "sg:tags":[
        "roofing"
    ],
    "wof:name":"Bright Group",
    "wof:placetype":"venue"
},
  "geometry": {"coordinates":[-122.337254,38.30543],"type":"Point"}
}