{
  "type": "Feature",
  "properties": {
    "addr:full":"2055 Hyde Street San Francisco CA 94109",
    "addr:housenumber":"2055",
    "addr:postcode":"94109",
    "addr:street":"Hyde Street",
    "iso:country":"US",
    "sg:address":"2055 Hyde Street",
    "sg:city":"San Francisco",
    "sg:classifiers":[
        {
            "category":"Professional",
            "subcategory":"Accounting & Tax Preparation",
            "type":"Services"
        }
    ],
    "sg:phone":"+1 415 771 6505",
    "sg:postcode":"94109",
    "sg:province":"CA",
    "sg:tags":[
        "accountant"
    ],
    "wof:name":"Standing Barry H CPA",
    "wof:placetype":"venue"
},
  "geometry": {"coordinates":[-122.41939499999999,37.80001],"type":"Point"}
}