{
  "type": "Feature",
  "properties": {
    "iso:country":"US",
    "sg:address":"1459 Freedom Blvd Ste 4",
    "sg:city":"Watsonville",
    "sg:classifiers":[
        {
            "category":"Personal",
            "subcategory":"Beauty Salon",
            "type":"Services"
        },
        {
            "category":"Shopping",
            "subcategory":"Party Supplies",
            "type":"Retail Goods"
        }
    ],
    "sg:phone":"+1 831 722 1192",
    "sg:postcode":"95076",
    "sg:province":"CA",
    "sg:tags":[
        "wedding"
    ],
    "wof:name":"La Donna",
    "wof:placetype":"venue"
},
  "geometry": {"coordinates":[-121.76642,36.928409],"type":"Point"}
}