{
  "type": "Feature",
  "properties": {
    "addr:full":"1292 Foxwood Way San Jose CA 95118",
    "addr:housenumber":"1292",
    "addr:postcode":"95118",
    "addr:street":"Foxwood Way",
    "iso:country":"US",
    "sg:address":"1292 Foxwood Way",
    "sg:city":"San Jose",
    "sg:classifiers":[
        {
            "category":"Shopping",
            "subcategory":"Beauty & Cosmetics",
            "type":"Retail Goods"
        }
    ],
    "sg:phone":"+1 408 267 3377",
    "sg:postcode":"95118",
    "sg:province":"CA",
    "sg:tags":[
        "merchandise"
    ],
    "wof:name":"Mary Kay Cosmetics",
    "wof:placetype":"venue"
},
  "geometry": {"coordinates":[-121.88571399999999,37.248447],"type":"Point"}
}