{
  "type": "Feature",
  "properties": {
    "addr:full":"804 N Hacienda Blvd La Puente CA 91744",
    "addr:housenumber":"804",
    "addr:postcode":"91744",
    "addr:street":"N Hacienda Blvd",
    "iso:country":"US",
    "sg:address":"804 N Hacienda Blvd",
    "sg:city":"La Puente",
    "sg:classifiers":[
        {
            "category":"Travel",
            "subcategory":"Travel Agent",
            "type":"Entertainment"
        }
    ],
    "sg:phone":"+1 626 333 1635",
    "sg:postcode":"91744",
    "sg:province":"CA",
    "sg:tags":[
        "agency",
        "bureau"
    ],
    "wof:name":"Ok Travel",
    "wof:placetype":"venue"
},
  "geometry": {"coordinates":[-117.95028499999999,34.034592],"type":"Point"}
}