{
  "type": "Feature",
  "properties": {
    "addr:full":"1180 Campbell Ave San Jose CA 95126",
    "addr:housenumber":"1180",
    "addr:postcode":"95126",
    "addr:street":"Campbell Ave",
    "iso:country":"US",
    "sg:address":"1180 Campbell Ave",
    "sg:city":"San Jose",
    "sg:classifiers":[
        {
            "category":"Wholesale",
            "subcategory":"Stationery",
            "type":"Manufacturing & Wholesale Goods"
        }
    ],
    "sg:phone":"+1 408 244 0444",
    "sg:postcode":"95126",
    "sg:province":"CA",
    "sg:tags":[
        "packaging",
        "material"
    ],
    "wof:name":"Odyssey Enterprises Inc",
    "wof:placetype":"venue"
},
  "geometry": {"coordinates":[-121.92887,37.34771],"type":"Point"}
}