{
  "type": "Feature",
  "properties": {
    "iso:country":"US",
    "sg:address":"6790 Moonstone Beach Dr",
    "sg:city":"Cambria",
    "sg:classifiers":[
        {
            "category":"Travel",
            "subcategory":"Hotels & Motels",
            "type":"Entertainment"
        }
    ],
    "sg:phone":"+1 805 927 1066",
    "sg:postcode":"93428",
    "sg:province":"CA",
    "sg:website":"www.whitewaterinn.com",
    "wof:name":"White Water Inn",
    "wof:placetype":"venue"
},
  "geometry": {"coordinates":[-121.117853,35.580733],"type":"Point"}
}