{
  "type": "Feature",
  "properties": {
    "addr:full":"10224 Mason Ave Chatsworth CA 91311",
    "addr:housenumber":"10224",
    "addr:postcode":"91311",
    "addr:street":"Mason Ave",
    "iso:country":"US",
    "sg:address":"10224 Mason Ave",
    "sg:city":"Chatsworth",
    "sg:phone":"+1 818 700 0111",
    "sg:postcode":"91311",
    "sg:province":"CA",
    "wof:name":"House Of Shishkabob",
    "wof:placetype":"venue"
},
  "geometry": {"coordinates":[-118.579842,34.255892],"type":"Point"}
}