{
  "type": "Feature",
  "properties": {
    "addr:full":"3208 Mission St San Francisco CA 94110",
    "addr:housenumber":"3208",
    "addr:postcode":"94110",
    "addr:street":"Mission St",
    "iso:country":"US",
    "sg:address":"3208 Mission St",
    "sg:city":"San Francisco",
    "sg:classifiers":[
        {
            "category":"Health Services",
            "subcategory":"Dentist",
            "type":"Services"
        }
    ],
    "sg:phone":"+1 415 641 8900",
    "sg:postcode":"94110",
    "sg:province":"CA",
    "sg:website":"www.missiondentalcare.com",
    "wof:name":"Mission Dental Care",
    "wof:placetype":"venue"
},
  "geometry": {"coordinates":[-122.42013900000001,37.745312],"type":"Point"}
}