{
  "type": "Feature",
  "properties": {
    "iso:country":"US",
    "sg:address":"3208 Mission St",
    "sg:city":"San Francisco",
    "sg:classifiers":[
        {
            "category":"Health Services",
            "subcategory":"Dentist",
            "type":"Services"
        }
    ],
    "sg:phone":"+1 415 641 8900",
    "sg:postcode":"94110",
    "sg:province":"CA",
    "sg:website":"www.missiondentalcare.com",
    "wof:name":"Mission Dental Care",
    "wof:placetype":"venue"
},
  "geometry": {"coordinates":[-122.42013900000001,37.745312],"type":"Point"}
}