{
  "type": "Feature",
  "properties": {
    "iso:country":"US",
    "sg:address":"20216 Barnard Ave",
    "sg:city":"Walnut",
    "sg:classifiers":[
        {
            "category":"Wholesale",
            "subcategory":"Home Furnishings",
            "type":"Manufacturing & Wholesale Goods"
        }
    ],
    "sg:phone":"+1 909 598 8912",
    "sg:postcode":"91789",
    "sg:province":"CA",
    "sg:tags":[
        "product"
    ],
    "wof:name":"L A Home Products",
    "wof:placetype":"venue"
},
  "geometry": {"coordinates":[-117.86250699999999,34.020749],"type":"Point"}
}