{
  "type": "Feature",
  "properties": {
    "iso:country":"US",
    "sg:address":"2222 N Santiago Blvd",
    "sg:city":"Orange",
    "sg:classifiers":[
        {
            "category":"Education",
            "subcategory":"School",
            "type":"Public Place"
        }
    ],
    "sg:phone":"+1 714 998 5151",
    "sg:postcode":"92867",
    "sg:province":"CA",
    "sg:tags":[
        "high",
        "middle",
        "elementary"
    ],
    "sg:website":"www.lhsoc.org",
    "wof:name":"Lutheran High School of Orange County",
    "wof:placetype":"venue"
},
  "geometry": {"coordinates":[-117.827003,33.825298],"type":"Point"}
}