{
  "type": "Feature",
  "properties": {
    "iso:country":"US",
    "sg:address":"11845 Beach Blvd",
    "sg:city":"Stanton",
    "sg:classifiers":[
        {
            "category":"Shopping",
            "subcategory":"Tobacco",
            "type":"Retail Goods"
        }
    ],
    "sg:phone":"+1 714 898 2729",
    "sg:postcode":"90680",
    "sg:province":"CA",
    "sg:tags":[
        "shop"
    ],
    "wof:name":"1St Smoke Shop",
    "wof:placetype":"venue"
},
  "geometry": {"coordinates":[-117.99322,33.790484],"type":"Point"}
}