{
  "type": "Feature",
  "properties": {
    "iso:country":"US",
    "sg:address":"1443 Estrella Way",
    "sg:city":"Turlock",
    "sg:classifiers":[
        {
            "category":"Building & Trades",
            "subcategory":"Construction",
            "type":"Services"
        }
    ],
    "sg:phone":"+1 209 632 0025",
    "sg:postcode":"95382",
    "sg:province":"CA",
    "sg:tags":[
        "home",
        "builder"
    ],
    "wof:name":"Morrison Homes",
    "wof:placetype":"venue"
},
  "geometry": {"coordinates":[-120.86611,37.534501],"type":"Point"}
}