{
  "type": "Feature",
  "properties": {
    "iso:country":"US",
    "sg:address":"901 McHenry Ave",
    "sg:city":"Modesto",
    "sg:classifiers":[
        {
            "category":"Wholesale",
            "subcategory":"Durable Goods & Equipment",
            "type":"Manufacturing & Wholesale Goods"
        }
    ],
    "sg:phone":"+1 209 236 0603",
    "sg:postcode":"95350",
    "sg:province":"CA",
    "sg:tags":[
        "representative",
        "manufacturer"
    ],
    "wof:name":"Clipper Controls",
    "wof:placetype":"venue"
},
  "geometry": {"coordinates":[-120.99383899999999,37.657302],"type":"Point"}
}