{
  "type": "Feature",
  "properties": {
    "iso:country":"US",
    "sg:address":"1655 Carlotti Dr",
    "sg:city":"Santa Maria",
    "sg:classifiers":[
        {
            "category":"Wholesale",
            "subcategory":"Machinery & Supplies",
            "type":"Manufacturing & Wholesale Goods"
        }
    ],
    "sg:phone":"+1 805 348 1720",
    "sg:postcode":"93454",
    "sg:province":"CA",
    "sg:tags":[
        "truck"
    ],
    "sg:website":"www.altalift.net",
    "wof:name":"Alta Lift",
    "wof:placetype":"venue"
},
  "geometry": {"coordinates":[-120.420976,34.968377],"type":"Point"}
}