{
  "type": "Feature",
  "properties": {
    "addr:full":"2290 Diamond Blvd Ste 200 Concord CA 94520",
    "addr:housenumber":"2290",
    "addr:postcode":"94520",
    "addr:street":"Diamond Blvd Ste 200",
    "iso:country":"US",
    "sg:address":"2290 Diamond Blvd Ste 200",
    "sg:city":"Concord",
    "sg:classifiers":[
        {
            "category":"Professional",
            "subcategory":"Management & Consulting",
            "type":"Services"
        }
    ],
    "sg:phone":"+1 925 671 2400",
    "sg:postcode":"94520",
    "sg:province":"CA",
    "sg:tags":[
        "consultant"
    ],
    "wof:name":"Stephnson Th-Linsco Private Le",
    "wof:placetype":"venue"
},
  "geometry": {"coordinates":[-122.06086000000001,37.977457],"type":"Point"}
}