{
  "type": "Feature",
  "properties": {
    "addr:full":"4111 Randolph St San Diego CA 92103",
    "addr:housenumber":"4111",
    "addr:postcode":"92103",
    "addr:street":"Randolph St",
    "iso:country":"US",
    "sg:address":"4111 Randolph St",
    "sg:city":"San Diego",
    "sg:classifiers":[
        {
            "category":"Manufacturing",
            "subcategory":"Tools & Machinery",
            "type":"Manufacturing & Wholesale Goods"
        }
    ],
    "sg:phone":"+1 619 297 3314",
    "sg:postcode":"92103",
    "sg:province":"CA",
    "sg:tags":[
        "physician",
        "surgeon"
    ],
    "wof:name":"Loops L L C",
    "wof:placetype":"venue"
},
  "geometry": {"coordinates":[-117.17675800000001,32.752556],"type":"Point"}
}