{
  "type": "Feature",
  "properties": {
    "addr:full":"15180 River Rd Guerneville CA 95446",
    "addr:housenumber":"15180",
    "addr:postcode":"95446",
    "addr:street":"River Rd",
    "iso:country":"US",
    "sg:address":"15180 River Rd",
    "sg:city":"Guerneville",
    "sg:classifiers":[
        {
            "category":"Autos & Motor Vehicles",
            "subcategory":"Automobile Sales",
            "type":"Retail Goods"
        },
        {
            "category":"Autos & Motor Vehicles",
            "subcategory":"Auto Supplies",
            "type":"Retail Goods"
        },
        {
            "category":"Wholesale",
            "subcategory":"Auto Parts",
            "type":"Manufacturing & Wholesale Goods"
        },
        {
            "category":"Retail",
            "subcategory":"Auto Repair",
            "type":"Services"
        }
    ],
    "sg:phone":"+1 707 869 2803",
    "sg:postcode":"95446",
    "sg:province":"CA",
    "sg:tags":[
        "parts",
        "accessory",
        "equipment",
        "rebuilt-wholesale",
        "supplies-used",
        "accessories-wholesale",
        "electrical",
        "rebuilt",
        "manufacturer"
    ],
    "sg:website":"http://www.napaonline.com",
    "wof:name":"River Auto Parts",
    "wof:placetype":"venue"
},
  "geometry": {"coordinates":[-122.98470500000001,38.511264],"type":"Point"}
}