{
  "type": "Feature",
  "properties": {
    "addr:full":"2924 Maple Avenue Los Angeles CA 90011",
    "addr:housenumber":"2924",
    "addr:postcode":"90011",
    "addr:street":"Maple Avenue",
    "iso:country":"US",
    "sg:address":"2924 Maple Avenue",
    "sg:city":"Los Angeles",
    "sg:classifiers":[
        {
            "category":"Food & Beverages",
            "subcategory":"Groceries & Convenience Stores",
            "type":"Retail Goods"
        }
    ],
    "sg:phone":"+1 213 749 7846",
    "sg:postcode":"90011",
    "sg:province":"CA",
    "wof:name":"30th Street Market",
    "wof:placetype":"venue"
},
  "geometry": {"coordinates":[-118.26747899999999,34.020453],"type":"Point"}
}