{
  "type": "Feature",
  "properties": {
    "iso:country":"US",
    "sg:address":"800 Perkins Way",
    "sg:city":"Auburn",
    "sg:classifiers":[
        {
            "category":"Social Services",
            "subcategory":"Child Care",
            "type":"Services"
        }
    ],
    "sg:phone":"+1 530 887 1762",
    "sg:postcode":"95603",
    "sg:province":"CA",
    "wof:name":"Discovery Club Sites",
    "wof:placetype":"venue"
},
  "geometry": {"coordinates":[-121.07433,38.87325],"type":"Point"}
}