{
  "type": "Feature",
  "properties": {
    "iso:country":"US",
    "sg:address":"356 N Hayworth Ave",
    "sg:city":"Los Angeles",
    "sg:classifiers":[
        {
            "category":"Arts & Performance",
            "subcategory":"Theater",
            "type":"Entertainment"
        }
    ],
    "sg:phone":"+1 323 852 1775",
    "sg:postcode":"90048",
    "sg:province":"CA",
    "sg:tags":[
        "talent",
        "agency",
        "casting"
    ],
    "wof:name":"Angela Black Management Inc",
    "wof:placetype":"venue"
},
  "geometry": {"coordinates":[-118.362561,34.077001],"type":"Point"}
}