{
  "type": "Feature",
  "properties": {
    "iso:country":"US",
    "sg:address":"17400 Peak Ave",
    "sg:city":"Morgan Hill",
    "sg:classifiers":[
        {
            "category":"Organizations",
            "subcategory":"Religious Organization",
            "type":"Services"
        }
    ],
    "sg:phone":"+1 408 779 3959",
    "sg:postcode":"95037",
    "sg:province":"CA",
    "wof:name":"St Catherines School",
    "wof:placetype":"venue"
},
  "geometry": {"coordinates":[-121.66201,37.12616],"type":"Point"}
}