{
  "type": "Feature",
  "properties": {
    "addr:full":"20047 Mayall St Chatsworth CA 91311",
    "addr:postcode":"20047;91311",
    "addr:street":"Mayall St",
    "iso:country":"US",
    "sg:address":"20047 Mayall St",
    "sg:city":"Chatsworth",
    "sg:classifiers":[
        {
            "category":"Manufacturing",
            "subcategory":"Leather Goods",
            "type":"Manufacturing & Wholesale Goods"
        }
    ],
    "sg:phone":"+1 818 554 8932",
    "sg:postcode":"91311",
    "sg:province":"CA",
    "sg:tags":[
        "mfg",
        "luggage"
    ],
    "wof:name":"Dan Selzer",
    "wof:placetype":"venue"
},
  "geometry": {"coordinates":[-118.57006,34.253698],"type":"Point"}
}