{
  "type": "Feature",
  "properties": {
    "iso:country":"US",
    "sg:address":"2517 Van Ness Avenue",
    "sg:city":"San Francisco",
    "sg:classifiers":[
        {
            "category":"Personal",
            "subcategory":"Massage",
            "type":"Services"
        }
    ],
    "sg:phone":"+1 415 571 0760",
    "sg:postcode":"94109",
    "sg:province":"CA",
    "wof:name":"Massage4yourstress",
    "wof:placetype":"venue"
},
  "geometry": {"coordinates":[-122.424476,37.798798],"type":"Point"}
}