{
  "type": "Feature",
  "properties": {
    "iso:country":"US",
    "sg:address":"2319 Alameda Ave",
    "sg:city":"Ventura",
    "sg:classifiers":[
        {
            "category":"Wholesale",
            "subcategory":"Machinery & Supplies",
            "type":"Manufacturing & Wholesale Goods"
        }
    ],
    "sg:phone":"+1 805 639 3058",
    "sg:postcode":"93003",
    "sg:province":"CA",
    "sg:tags":[
        "sprinkler"
    ],
    "wof:name":"Ace Fire Protection",
    "wof:placetype":"venue"
},
  "geometry": {"coordinates":[-119.208461,34.252835],"type":"Point"}
}