{
  "type": "Feature",
  "properties": {
    "addr:full":"2031 Falcon Dr Fairfield CA 94533",
    "addr:housenumber":"2031",
    "addr:postcode":"94533",
    "addr:street":"Falcon Dr",
    "iso:country":"US",
    "sg:address":"2031 Falcon Dr",
    "sg:city":"Fairfield",
    "sg:classifiers":[
        {
            "category":"Social Services",
            "subcategory":"Adult Care",
            "type":"Services"
        }
    ],
    "sg:phone":"+1 707 422 5226",
    "sg:postcode":"94533",
    "sg:province":"CA",
    "sg:tags":[
        "home",
        "facility",
        "residential"
    ],
    "wof:name":"Shackleford Family Home",
    "wof:placetype":"venue"
},
  "geometry": {"coordinates":[-122.01731100000001,38.266048],"type":"Point"}
}