{
  "type": "Feature",
  "properties": {
    "iso:country":"US",
    "sg:address":"6309 Landis Ave",
    "sg:city":"Carmichael",
    "sg:classifiers":[
        {
            "category":"Building & Trades",
            "subcategory":"Construction",
            "type":"Services"
        }
    ],
    "sg:phone":"+1 916 369 1245",
    "sg:postcode":"95608",
    "sg:province":"CA",
    "sg:tags":[
        "sheetrock",
        "contractor"
    ],
    "wof:name":"Craftsman Painting",
    "wof:placetype":"venue"
},
  "geometry": {"coordinates":[-121.320376,38.625965],"type":"Point"}
}