{
  "type": "Feature",
  "properties": {
    "iso:country":"US",
    "sg:address":"3084 Sunrise Blvd",
    "sg:city":"Rancho Cordova",
    "sg:classifiers":[
        {
            "category":"Personal",
            "subcategory":"Nail Salon",
            "type":"Services"
        }
    ],
    "sg:phone":"+1 916 852 1861",
    "sg:postcode":"95742",
    "sg:province":"CA",
    "sg:website":"www.marieclairesalon.com",
    "wof:name":"Marie Claire Salon",
    "wof:placetype":"venue"
},
  "geometry": {"coordinates":[-121.26610100000001,38.591513],"type":"Point"}
}