{
  "type": "Feature",
  "properties": {
    "iso:country":"US",
    "sg:address":"3347 Michelson Dr",
    "sg:city":"Irvine",
    "sg:classifiers":[
        {
            "category":"Government",
            "subcategory":"Office",
            "type":"Public Place"
        }
    ],
    "sg:phone":"+1 949 724 2598",
    "sg:postcode":"92612",
    "sg:province":"CA",
    "sg:tags":[
        "government-state"
    ],
    "wof:name":"California State of",
    "wof:placetype":"venue"
},
  "geometry": {"coordinates":[-117.83923299999999,33.67049],"type":"Point"}
}