{
  "type": "Feature",
  "properties": {
    "iso:country":"US",
    "sg:address":"1440 S. Manzanita Avenue",
    "sg:city":"Palm Springs",
    "sg:classifiers":[
        {
            "category":"Professional",
            "subcategory":"Advertising",
            "type":"Services"
        }
    ],
    "sg:phone":"+1 760 320 1414",
    "sg:postcode":"92264",
    "sg:province":"CA",
    "sg:tags":[
        "email-marketing",
        "email-marketing-software"
    ],
    "sg:website":"http://www.vipermailer.com",
    "wof:name":"Viper Logic",
    "wof:placetype":"venue"
},
  "geometry": {"coordinates":[-116.53419599999999,33.80647],"type":"Point"}
}