{
  "type": "Feature",
  "properties": {
    "addr:full":"1713 Dwight Way Apt F Berkeley CA 94703",
    "addr:housenumber":"1713",
    "addr:postcode":"94703",
    "addr:street":"Dwight Way Apt F",
    "iso:country":"US",
    "sg:address":"1713 Dwight Way Apt F",
    "sg:city":"Berkeley",
    "sg:classifiers":[
        {
            "category":"Arts & Performance",
            "subcategory":"Dance",
            "type":"Entertainment"
        }
    ],
    "sg:phone":"+1 510 612 3686",
    "sg:postcode":"94703",
    "sg:province":"CA",
    "sg:tags":[
        "instruction",
        "dancing"
    ],
    "wof:name":"Dance Beat",
    "wof:placetype":"venue"
},
  "geometry": {"coordinates":[-122.275932,37.862859],"type":"Point"}
}