{
  "type": "Feature",
  "properties": {
    "addr:full":"7861 Clay Ave Huntington Beach CA 92648",
    "addr:housenumber":"7861",
    "addr:postcode":"92648",
    "addr:street":"Clay Ave",
    "iso:country":"US",
    "sg:address":"7861 Clay Ave",
    "sg:city":"Huntington Beach",
    "sg:classifiers":[
        {
            "category":"Freight",
            "type":"Transportation"
        }
    ],
    "sg:phone":"+1 714 369 3017",
    "sg:postcode":"92648",
    "sg:province":"CA",
    "sg:tags":[
        "water"
    ],
    "wof:name":"Elixigen Company",
    "wof:placetype":"venue"
},
  "geometry": {"coordinates":[-117.991688,33.683149],"type":"Point"}
}