{
  "type": "Feature",
  "properties": {
    "iso:country":"US",
    "sg:address":"1010 Sir Francis Drake Blvd",
    "sg:city":"Kentfield",
    "sg:classifiers":[
        {
            "category":"Health Services",
            "subcategory":"Health Practitioner",
            "type":"Services"
        }
    ],
    "sg:phone":"+1 415 456 0232",
    "sg:postcode":"94904",
    "sg:province":"CA",
    "sg:tags":[
        "psychologist"
    ],
    "wof:name":"Leslie Horn PHD",
    "wof:placetype":"venue"
},
  "geometry": {"coordinates":[-122.547791,37.955961],"type":"Point"}
}