{
  "type": "Feature",
  "properties": {
    "addr:full":"3415 Via Lido Newport Beach CA 92663",
    "addr:housenumber":"3415",
    "addr:postcode":"92663",
    "addr:street":"Via Lido",
    "iso:country":"US",
    "sg:address":"3415 Via Lido",
    "sg:city":"Newport Beach",
    "sg:classifiers":[
        {
            "category":"Retail",
            "subcategory":"Laundry & Dry Cleaning",
            "type":"Services"
        }
    ],
    "sg:phone":"+1 949 673 3394",
    "sg:postcode":"92663",
    "sg:province":"CA",
    "wof:name":"Kona Cleaners",
    "wof:placetype":"venue"
},
  "geometry": {"coordinates":[-117.92838999999999,33.617864],"type":"Point"}
}