{
  "type": "Feature",
  "properties": {
    "iso:country":"US",
    "sg:address":"1420 S State St",
    "sg:city":"Ukiah",
    "sg:classifiers":[
        {
            "category":"Food & Beverages",
            "subcategory":"Supermarket",
            "type":"Retail Goods"
        }
    ],
    "sg:phone":"+1 707 468 1625",
    "sg:postcode":"95482",
    "sg:province":"CA",
    "sg:tags":[
        "super",
        "store"
    ],
    "wof:name":"Super Chavez Market",
    "wof:placetype":"venue"
},
  "geometry": {"coordinates":[-123.204437,39.127419],"type":"Point"}
}