{
  "type": "Feature",
  "properties": {
    "addr:full":"1420 S State St Ukiah CA 95482",
    "addr:housenumber":"1420",
    "addr:postcode":"ca 95482",
    "addr:street":"S State St",
    "iso:country":"US",
    "sg:address":"1420 S State St",
    "sg:city":"Ukiah",
    "sg:classifiers":[
        {
            "category":"Food & Beverages",
            "subcategory":"Supermarket",
            "type":"Retail Goods"
        }
    ],
    "sg:phone":"+1 707 468 1625",
    "sg:postcode":"95482",
    "sg:province":"CA",
    "sg:tags":[
        "super",
        "store"
    ],
    "wof:name":"Super Chavez Market",
    "wof:placetype":"venue"
},
  "geometry": {"coordinates":[-123.204437,39.127419],"type":"Point"}
}