{
  "type": "Feature",
  "properties": {
    "iso:country":"US",
    "sg:address":"9546 Brighton Way",
    "sg:city":"Beverly Hills",
    "sg:classifiers":[
        {
            "category":"Shopping",
            "subcategory":"Shoes",
            "type":"Retail Goods"
        }
    ],
    "sg:phone":"+1 310 285 9880",
    "sg:postcode":"90210",
    "sg:province":"CA",
    "sg:website":"www.viaspiga.com",
    "wof:name":"Via Spiga",
    "wof:placetype":"venue"
},
  "geometry": {"coordinates":[-118.403507,34.068778],"type":"Point"}
}