{
  "type": "Feature",
  "properties": {
    "iso:country":"US",
    "sg:address":"8383 Fargo Ave",
    "sg:city":"Hanford",
    "sg:classifiers":[
        {
            "category":"Farming",
            "subcategory":"Livestock Farm",
            "type":"Manufacturing & Wholesale Goods"
        }
    ],
    "sg:phone":"+1 559 582 3376",
    "sg:postcode":"93230",
    "sg:province":"CA",
    "sg:tags":[
        "beef",
        "feedlot",
        "cattle"
    ],
    "wof:name":"Rawhide Cattle Co",
    "wof:placetype":"venue"
},
  "geometry": {"coordinates":[-119.594107,36.357088],"type":"Point"}
}