{
  "type": "Feature",
  "properties": {
    "iso:country":"US",
    "sg:address":"22017 Arrowhead Ln",
    "sg:city":"Lake Forest",
    "sg:classifiers":[
        {
            "category":"Freight",
            "type":"Transportation"
        }
    ],
    "sg:phone":"+1 949 837 9397",
    "sg:postcode":"92630",
    "sg:province":"CA",
    "sg:tags":[
        "delivery"
    ],
    "wof:name":"Affordable Delivery Svc",
    "wof:placetype":"venue"
},
  "geometry": {"coordinates":[-117.70264899999999,33.642837],"type":"Point"}
}