{
  "type": "Feature",
  "properties": {
    "iso:country":"US",
    "sg:address":"9220 Activity Rd",
    "sg:city":"San Diego",
    "sg:classifiers":[
        {
            "category":"Building & Trades",
            "subcategory":"Equipment Rental",
            "type":"Services"
        }
    ],
    "sg:phone":"+1 619 282 2633",
    "sg:postcode":"92126",
    "sg:province":"CA",
    "sg:tags":[
        "repair",
        "profess",
        "electrical"
    ],
    "wof:name":"MSI Production Services",
    "wof:placetype":"venue"
},
  "geometry": {"coordinates":[-117.129275,32.896715],"type":"Point"}
}