{
  "type": "Feature",
  "properties": {
    "addr:full":"5770 Obata Way Gilroy CA 95020",
    "addr:housenumber":"5770",
    "addr:postcode":"95020",
    "addr:street":"Obata Way",
    "iso:country":"US",
    "sg:address":"5770 Obata Way",
    "sg:city":"Gilroy",
    "sg:classifiers":[
        {
            "category":"Manufacturing",
            "subcategory":"Tools & Machinery",
            "type":"Manufacturing & Wholesale Goods"
        }
    ],
    "sg:phone":"+1 408 846 5737",
    "sg:postcode":"95020",
    "sg:province":"CA",
    "sg:tags":[
        "industrial",
        "mfg"
    ],
    "wof:name":"Accuracy Tooling",
    "wof:placetype":"venue"
},
  "geometry": {"coordinates":[-121.55013,36.985272],"type":"Point"}
}