{
  "type": "Feature",
  "properties": {
    "addr:full":"5558 E Edith Dr Fresno CA 93727",
    "addr:housenumber":"5558",
    "addr:postcode":"93727",
    "addr:street":"E Edith Dr",
    "iso:country":"US",
    "sg:address":"5558 E Edith Dr",
    "sg:city":"Fresno",
    "sg:classifiers":[
        {
            "category":"Recreation",
            "type":"Entertainment"
        }
    ],
    "sg:phone":"+1 559 307 4333",
    "sg:postcode":"93727",
    "sg:province":"CA",
    "sg:tags":[
        "martial",
        "arts",
        "instruction"
    ],
    "wof:name":"Choy Lee Fut King Fu",
    "wof:placetype":"venue"
},
  "geometry": {"coordinates":[-119.70348300000001,36.789093],"type":"Point"}
}