{
  "type": "Feature",
  "properties": {
    "addr:full":"2441 Imola Ave W Napa CA 94558",
    "addr:housenumber":"2441",
    "addr:postcode":"94558",
    "addr:street":"Imola Ave W",
    "iso:country":"US",
    "sg:address":"2441 Imola Ave W",
    "sg:city":"Napa",
    "sg:classifiers":[
        {
            "category":"Health Services",
            "subcategory":"Chiropractor",
            "type":"Services"
        }
    ],
    "sg:phone":"+1 707 252 3365",
    "sg:postcode":"94558",
    "sg:province":"CA",
    "wof:name":"Juan F Sacristan DC",
    "wof:placetype":"venue"
},
  "geometry": {"coordinates":[-122.30166,38.281831],"type":"Point"}
}