{
  "type": "Feature",
  "properties": {
    "iso:country":"US",
    "sg:address":"1101 S California Blvd",
    "sg:city":"Walnut Creek",
    "sg:classifiers":[
        {
            "category":"Bakery",
            "type":"Food & Drink"
        }
    ],
    "sg:menulink":"http://www.allmenus.com/ca/central-contra-costa/58715-marie-callenders/menu/",
    "sg:phone":"+1 925 943 7100",
    "sg:postcode":"94596",
    "sg:province":"CA",
    "sg:tags":[
        "american",
        "pastry"
    ],
    "wof:name":"Marie Callender's",
    "wof:placetype":"venue"
},
  "geometry": {"coordinates":[-122.063542,37.897203],"type":"Point"}
}