{
  "type": "Feature",
  "properties": {
    "iso:country":"US",
    "sg:address":"728 A St",
    "sg:city":"San Rafael",
    "sg:classifiers":[
        {
            "category":"Personal",
            "subcategory":"Beauty Salon",
            "type":"Services"
        }
    ],
    "sg:phone":"+1 415 457 3603",
    "sg:postcode":"94901",
    "sg:province":"CA",
    "wof:name":"Hair By Gene",
    "wof:placetype":"venue"
},
  "geometry": {"coordinates":[-122.52847300000001,37.971035],"type":"Point"}
}