{
  "type": "Feature",
  "properties": {
    "addr:full":"14511 S Bascom Avenue Los Gatos CA 95032",
    "addr:housenumber":"14511",
    "addr:postcode":"95032",
    "addr:street":"S Bascom Avenue",
    "iso:country":"US",
    "sg:address":"14511 S Bascom Avenue",
    "sg:city":"Los Gatos",
    "sg:classifiers":[
        {
            "category":"Health Services",
            "subcategory":"Doctor",
            "type":"Services"
        }
    ],
    "sg:phone":"+1 408 356 3146",
    "sg:postcode":"95032",
    "sg:province":"CA",
    "sg:tags":[
        "surgeon",
        "oral"
    ],
    "sg:website":"www.drfollmar.com",
    "wof:name":"Follmar Kenneth E II DDS.",
    "wof:placetype":"venue"
},
  "geometry": {"coordinates":[-121.94861299999999,37.257656],"type":"Point"}
}