{
  "type": "Feature",
  "properties": {
    "addr:full":"2301 Theatre Dr Paso Robles CA 93446",
    "addr:housenumber":"2301",
    "addr:postcode":"93446",
    "addr:street":"Theatre Dr",
    "iso:country":"US",
    "sg:address":"2301 Theatre Dr",
    "sg:city":"Paso Robles",
    "sg:classifiers":[
        {
            "category":"Coffee & Tea",
            "type":"Food & Drink"
        }
    ],
    "sg:menulink":"http://www.allmenus.com/ca/atascadero/108105-starbucks-coffee/menu/",
    "sg:phone":"+1 805 237 8278",
    "sg:postcode":"93446",
    "sg:province":"CA",
    "sg:tags":[
        "american"
    ],
    "wof:name":"Starbucks Coffee",
    "wof:placetype":"venue"
},
  "geometry": {"coordinates":[-120.696619,35.584252],"type":"Point"}
}