{
  "type": "Feature",
  "properties": {
    "iso:country":"US",
    "sg:address":"1816 Cougar Ln",
    "sg:city":"Clovis",
    "sg:classifiers":[
        {
            "category":"Social Services",
            "type":"Services"
        }
    ],
    "sg:phone":"+1 559 298 6487",
    "sg:postcode":"93611",
    "sg:province":"CA",
    "sg:tags":[
        "counselor",
        "marriage",
        "family"
    ],
    "wof:name":"Linda Moradian & Assoc",
    "wof:placetype":"venue"
},
  "geometry": {"coordinates":[-119.681621,36.8153],"type":"Point"}
}