{
  "type": "Feature",
  "properties": {
    "addr:full":"759 W 18th St Merced CA 95340",
    "addr:housenumber":"759",
    "addr:postcode":"95340",
    "addr:street":"W 18Th St",
    "iso:country":"US",
    "sg:address":"759 W 18th St",
    "sg:city":"Merced",
    "sg:classifiers":[
        {
            "category":"Shopping",
            "subcategory":"Florist",
            "type":"Retail Goods"
        }
    ],
    "sg:phone":"+1 209 722 6295",
    "sg:postcode":"95340",
    "sg:province":"CA",
    "wof:name":"Tioga Florist",
    "wof:placetype":"venue"
},
  "geometry": {"coordinates":[-120.486571,37.303827],"type":"Point"}
}