{
  "type": "Feature",
  "properties": {
    "addr:full":"12742 Crenshaw Boulevard Hawthorne CA 90250",
    "addr:housenumber":"12742",
    "addr:postcode":"90250",
    "addr:street":"Crenshaw Boulevard",
    "iso:country":"US",
    "sg:address":"12742 Crenshaw Boulevard",
    "sg:city":"Hawthorne",
    "sg:classifiers":[
        {
            "category":"Shopping",
            "subcategory":"Shoes",
            "type":"Retail Goods"
        }
    ],
    "sg:phone":"+1 323 455 1720",
    "sg:postcode":"90250",
    "sg:province":"CA",
    "sg:tags":[
        "store"
    ],
    "wof:name":"Kicks",
    "wof:placetype":"venue"
},
  "geometry": {"coordinates":[-118.326532,33.91707],"type":"Point"}
}