{
  "type": "Feature",
  "properties": {
    "iso:country":"US",
    "sg:address":"2148 Sunset Blvd",
    "sg:city":"Los Angeles",
    "sg:classifiers":[
        {
            "category":"Shopping",
            "subcategory":"Clothing, Apparel, & Fashions",
            "type":"Retail Goods"
        }
    ],
    "sg:phone":"+1 323 570 0051",
    "sg:postcode":"90026",
    "sg:province":"CA",
    "sg:tags":[
        "clothing",
        "women's"
    ],
    "sg:website":"www.taxicdc.com",
    "wof:name":"Taxi CDC",
    "wof:placetype":"venue"
},
  "geometry": {"coordinates":[-118.265032,34.077387],"type":"Point"}
}