{
  "type": "Feature",
  "properties": {
    "iso:country":"US",
    "sg:address":"150 Shoreline Hwy",
    "sg:city":"Mill Valley",
    "sg:classifiers":[
        {
            "category":"Professional",
            "subcategory":"Research",
            "type":"Services"
        }
    ],
    "sg:phone":"+1 510 478 0010",
    "sg:postcode":"94965",
    "sg:province":"CA",
    "sg:tags":[
        "environmental",
        "ecological"
    ],
    "wof:name":"AREA Environmental Svc",
    "wof:placetype":"venue"
},
  "geometry": {"coordinates":[-122.522606,37.879536],"type":"Point"}
}