{
  "type": "Feature",
  "properties": {
    "addr:full":"9127 Painter Ave Whittier CA 90602",
    "addr:housenumber":"9127",
    "addr:postcode":"90602",
    "addr:street":"Painter Ave",
    "iso:country":"US",
    "sg:address":"9127 Painter Ave",
    "sg:city":"Whittier",
    "sg:classifiers":[
        {
            "category":"Retail",
            "subcategory":"Auto Repair",
            "type":"Services"
        }
    ],
    "sg:phone":"+1 562 696 2480",
    "sg:postcode":"90602",
    "sg:province":"CA",
    "wof:name":"Aztlan Automatic Transmission Center",
    "wof:placetype":"venue"
},
  "geometry": {"coordinates":[-118.041,33.955601],"type":"Point"}
}