{
  "type": "Feature",
  "properties": {
    "iso:country":"US",
    "sg:address":"3800 Via Oro Ave",
    "sg:city":"Long Beach",
    "sg:classifiers":[
        {
            "category":"Communications",
            "subcategory":"Television Station",
            "type":"Services"
        }
    ],
    "sg:phone":"+1 310 847 5550",
    "sg:postcode":"90810",
    "sg:province":"CA",
    "sg:tags":[
        "provider"
    ],
    "wof:name":"Direct Tv",
    "wof:placetype":"venue"
},
  "geometry": {"coordinates":[-118.21199799999999,33.828098],"type":"Point"}
}