{
  "type": "Feature",
  "properties": {
    "addr:full":"641 Erlandson St Richmond CA 94804",
    "addr:housenumber":"641",
    "addr:postcode":"94804",
    "addr:street":"Erlandson St",
    "iso:country":"US",
    "sg:address":"641 Erlandson St",
    "sg:city":"Richmond",
    "sg:classifiers":[
        {
            "category":"Manufacturing",
            "subcategory":"Tools & Machinery",
            "type":"Manufacturing & Wholesale Goods"
        }
    ],
    "sg:phone":"+1 510 233 3723",
    "sg:postcode":"94804",
    "sg:province":"CA",
    "sg:tags":[
        "designed",
        "built"
    ],
    "wof:name":"Monterey Industries",
    "wof:placetype":"venue"
},
  "geometry": {"coordinates":[-122.337007,37.92277],"type":"Point"}
}