{
  "type": "Feature",
  "properties": {
    "addr:full":"13096 Blackbird St Garden Grove CA 92843",
    "addr:housenumber":"13096",
    "addr:postcode":"92843",
    "addr:street":"Blackbird St",
    "iso:country":"US",
    "sg:address":"13096 Blackbird St",
    "sg:city":"Garden Grove",
    "sg:classifiers":[
        {
            "category":"Freight",
            "type":"Transportation"
        }
    ],
    "sg:phone":"+1 714 719 4747",
    "sg:postcode":"92843",
    "sg:province":"CA",
    "sg:tags":[
        "operator",
        "local",
        "trucking"
    ],
    "wof:name":"JP Group Transportation",
    "wof:placetype":"venue"
},
  "geometry": {"coordinates":[-117.912954,33.774376],"type":"Point"}
}