{
  "type": "Feature",
  "properties": {
    "addr:full":"4033 Avati Dr San Diego CA 92117",
    "addr:housenumber":"4033",
    "addr:postcode":"92117",
    "addr:street":"Avati Dr",
    "iso:country":"US",
    "sg:address":"4033 Avati Dr",
    "sg:city":"San Diego",
    "sg:classifiers":[
        {
            "category":"Restaurant",
            "type":"Food & Drink"
        }
    ],
    "sg:phone":"+1 858 273 2828",
    "sg:postcode":"92117",
    "sg:province":"CA",
    "sg:tags":[
        "mexican"
    ],
    "wof:name":"Pacific Taco Shop No 3",
    "wof:placetype":"venue"
},
  "geometry": {"coordinates":[-117.216003,32.814602],"type":"Point"}
}