{
  "type": "Feature",
  "properties": {
    "iso:country":"US",
    "sg:address":"150 N Hill Ave",
    "sg:city":"Pasadena",
    "sg:classifiers":[
        {
            "category":"Health Services",
            "subcategory":"Medical Lab",
            "type":"Services"
        }
    ],
    "sg:phone":"+1 626 335 6410",
    "sg:postcode":"91106",
    "sg:province":"CA",
    "sg:tags":[
        "laboratory"
    ],
    "wof:name":"Millenium Diagnostics",
    "wof:placetype":"venue"
},
  "geometry": {"coordinates":[-118.12129299999999,34.149145],"type":"Point"}
}