{
  "type": "Feature",
  "properties": {
    "addr:full":"724 Towne Ave Los Angeles CA 90021",
    "addr:housenumber":"724",
    "addr:postcode":"90021",
    "addr:street":"Towne Ave",
    "iso:country":"US",
    "sg:address":"724 Towne Ave",
    "sg:city":"Los Angeles",
    "sg:classifiers":[
        {
            "category":"Building & Trades",
            "subcategory":"Construction",
            "type":"Services"
        }
    ],
    "sg:phone":"+1 213 489 7790",
    "sg:postcode":"90021",
    "sg:province":"CA",
    "sg:tags":[
        "contractor"
    ],
    "wof:name":"Cube Construction Inc",
    "wof:placetype":"venue"
},
  "geometry": {"coordinates":[-118.245817,34.03893],"type":"Point"}
}