{
  "type": "Feature",
  "properties": {
    "iso:country":"US",
    "sg:address":"2417 190th St",
    "sg:city":"Redondo Beach",
    "sg:classifiers":[
        {
            "category":"Retail",
            "subcategory":"Laundry & Dry Cleaning",
            "type":"Services"
        }
    ],
    "sg:postcode":"90278",
    "sg:province":"CA",
    "wof:name":"Coin Laundry",
    "wof:placetype":"venue"
},
  "geometry": {"coordinates":[-118.371242,33.858481],"type":"Point"}
}