{
  "type": "Feature",
  "properties": {
    "iso:country":"US",
    "sg:address":"18351 Beach Boulevard Suite I",
    "sg:city":"Huntington Beach",
    "sg:classifiers":[
        {
            "category":"Banks & Credit Unions",
            "subcategory":"Financial Services",
            "type":"Services"
        }
    ],
    "sg:phone":"+1 714 842 0699",
    "sg:postcode":"92648",
    "sg:province":"CA",
    "sg:tags":[
        "broker",
        "mortgage"
    ],
    "sg:website":"www.pearsonfinancial.com",
    "wof:name":"Pearson Financial",
    "wof:placetype":"venue"
},
  "geometry": {"coordinates":[-117.98902099999999,33.695289],"type":"Point"}
}