{
  "type": "Feature",
  "properties": {
    "addr:full":"8284 Murray Ave Gilroy CA 95020",
    "addr:housenumber":"8284",
    "addr:postcode":"95020",
    "addr:street":"Murray Ave",
    "iso:country":"US",
    "sg:address":"8284 Murray Ave",
    "sg:city":"Gilroy",
    "sg:classifiers":[
        {
            "category":"Building & Trades",
            "subcategory":"Equipment Rental",
            "type":"Services"
        }
    ],
    "sg:phone":"+1 408 848 9847",
    "sg:postcode":"95020",
    "sg:province":"CA",
    "sg:tags":[
        "yard",
        "leasing",
        "store"
    ],
    "wof:name":"Golden State Portables Rental Company",
    "wof:placetype":"venue"
},
  "geometry": {"coordinates":[-121.567894,37.019169],"type":"Point"}
}