{
  "type": "Feature",
  "properties": {
    "iso:country":"US",
    "sg:address":"3026 Lakeshore Ave",
    "sg:city":"Oakland",
    "sg:classifiers":[
        {
            "category":"Retail",
            "subcategory":"Auto Rental",
            "type":"Services"
        }
    ],
    "sg:phone":"+1 510 250 7632",
    "sg:postcode":"94610",
    "sg:province":"CA",
    "sg:tags":[
        "limousine"
    ],
    "wof:name":"Limousine All Star",
    "wof:placetype":"venue"
},
  "geometry": {"coordinates":[-122.247237,37.809287],"type":"Point"}
}