{
  "type": "Feature",
  "properties": {
    "addr:full":"32122 Cam Capistrano San Juan Capistrano CA 92675",
    "addr:housenumber":"32122",
    "addr:postcode":"92675",
    "addr:street":"Cam Capistrano",
    "iso:country":"US",
    "sg:address":"32122 Cam Capistrano",
    "sg:city":"San Juan Capistrano",
    "sg:classifiers":[
        {
            "category":"Banks & Credit Unions",
            "subcategory":"Bank",
            "type":"Services"
        }
    ],
    "sg:phone":"+1 949 240 3300",
    "sg:postcode":"92675",
    "sg:province":"CA",
    "sg:tags":[
        "financial"
    ],
    "wof:name":"First One Lending Corporation",
    "wof:placetype":"venue"
},
  "geometry": {"coordinates":[-117.662582,33.49705],"type":"Point"}
}