{
  "type": "Feature",
  "properties": {
    "iso:country":"US",
    "sg:address":"1519 Shaver Way",
    "sg:city":"Placentia",
    "sg:classifiers":[
        {
            "category":"Banks & Credit Unions",
            "subcategory":"Financial Services",
            "type":"Services"
        }
    ],
    "sg:phone":"+1 714 524 6703",
    "sg:postcode":"92870",
    "sg:province":"CA",
    "sg:tags":[
        "trust",
        "management"
    ],
    "wof:name":"Belz Trust",
    "wof:placetype":"venue"
},
  "geometry": {"coordinates":[-117.857212,33.890531],"type":"Point"}
}