{
  "type": "Feature",
  "properties": {
    "addr:full":"234 E State Rte 246 Buellton CA 93427",
    "addr:housenumber":"234",
    "addr:postcode":"93427",
    "addr:street":"E State Rte 246",
    "iso:country":"US",
    "sg:address":"234 E State Rte 246",
    "sg:city":"Buellton",
    "sg:classifiers":[
        {
            "category":"Banks & Credit Unions",
            "subcategory":"Bank",
            "type":"Services"
        }
    ],
    "sg:phone":"+1 805 688 4463",
    "sg:postcode":"93427",
    "sg:province":"CA",
    "wof:name":"Los Padres Bank",
    "wof:placetype":"venue"
},
  "geometry": {"coordinates":[-120.186993,34.610869],"type":"Point"}
}