{
  "type": "Feature",
  "properties": {
    "iso:country":"US",
    "sg:address":"1468 Yosemite Cir",
    "sg:city":"Clayton",
    "sg:classifiers":[
        {
            "category":"Professional",
            "subcategory":"Management & Consulting",
            "type":"Services"
        }
    ],
    "sg:phone":"+1 925 672 3694",
    "sg:postcode":"94517",
    "sg:province":"CA",
    "sg:tags":[
        "consultant",
        "educational"
    ],
    "wof:name":"Kids Kreative Inc",
    "wof:placetype":"venue"
},
  "geometry": {"coordinates":[-121.949827,37.947488],"type":"Point"}
}