{
  "type": "Feature",
  "properties": {
    "addr:full":"3506 Glen Ellen Dr Fairfield CA 94534",
    "addr:housenumber":"3506",
    "addr:postcode":"94534",
    "addr:street":"Glen Ellen Dr",
    "iso:country":"US",
    "sg:address":"3506 Glen Ellen Dr",
    "sg:city":"Fairfield",
    "sg:classifiers":[
        {
            "category":"Professional",
            "subcategory":"Business Services",
            "type":"Services"
        }
    ],
    "sg:phone":"+1 707 426 6080",
    "sg:postcode":"94534",
    "sg:province":"CA",
    "sg:tags":[
        "information",
        "referral"
    ],
    "wof:name":"Web Mag Pie",
    "wof:placetype":"venue"
},
  "geometry": {"coordinates":[-122.03559199999999,38.293048],"type":"Point"}
}