{
  "type": "Feature",
  "properties": {
    "iso:country":"US",
    "sg:address":"204 E Alondra Blvd",
    "sg:city":"Compton",
    "sg:classifiers":[
        {
            "category":"Retail",
            "subcategory":"Auto Repair",
            "type":"Services"
        }
    ],
    "sg:phone":"+1 310 637 5308",
    "sg:postcode":"90220",
    "sg:province":"CA",
    "wof:name":"Sinaloa Auto Repair",
    "wof:placetype":"venue"
},
  "geometry": {"coordinates":[-118.221001,33.8885],"type":"Point"}
}