{
  "type": "Feature",
  "properties": {
    "addr:full":"1300 I St Sacramento CA 95814",
    "addr:housenumber":"1300",
    "addr:postcode":"95814",
    "addr:street":"I St",
    "iso:country":"US",
    "sg:address":"1300 I St",
    "sg:city":"Sacramento",
    "sg:classifiers":[
        {
            "category":"Government",
            "subcategory":"Court House",
            "type":"Public Place"
        }
    ],
    "sg:phone":"+1 916 324 5016",
    "sg:postcode":"95814",
    "sg:province":"CA",
    "sg:tags":[
        "justice"
    ],
    "wof:name":"Office of Attorney General",
    "wof:placetype":"venue"
},
  "geometry": {"coordinates":[-121.487409,38.57991],"type":"Point"}
}