{
  "type": "Feature",
  "properties": {
    "iso:country":"US",
    "sg:address":"2871 E Via Martens",
    "sg:city":"Anaheim",
    "sg:classifiers":[
        {
            "category":"Building & Trades",
            "subcategory":"Plumbing",
            "type":"Services"
        }
    ],
    "sg:phone":"+1 714 666 8450",
    "sg:postcode":"92806",
    "sg:province":"CA",
    "sg:tags":[
        "fire",
        "installation",
        "sprinkler"
    ],
    "wof:name":"Residential Fire Systems Inc",
    "wof:placetype":"venue"
},
  "geometry": {"coordinates":[-117.872221,33.856417],"type":"Point"}
}