{
  "type": "Feature",
  "properties": {
    "iso:country":"US",
    "sg:address":"220 W Stetson Ave",
    "sg:city":"Hemet",
    "sg:classifiers":[
        {
            "category":"Shopping",
            "subcategory":"Department Store",
            "type":"Retail Goods"
        }
    ],
    "sg:phone":"+1 951 925 7741",
    "sg:postcode":"92543",
    "sg:province":"CA",
    "wof:name":"Kmart",
    "wof:placetype":"venue"
},
  "geometry": {"coordinates":[-116.973122,33.729486],"type":"Point"}
}