{
  "type": "Feature",
  "properties": {
    "iso:country":"US",
    "sg:address":"2370 W Carson St",
    "sg:city":"Torrance",
    "sg:classifiers":[
        {
            "category":"Building & Trades",
            "subcategory":"Cleaning & Sanitation",
            "type":"Services"
        }
    ],
    "sg:phone":"+1 310 328 4950",
    "sg:postcode":"90501",
    "sg:province":"CA",
    "sg:tags":[
        "janitor"
    ],
    "wof:name":"Sarner",
    "wof:placetype":"venue"
},
  "geometry": {"coordinates":[-118.325253,33.831241],"type":"Point"}
}