{
  "type": "Feature",
  "properties": {
    "iso:country":"US",
    "sg:address":"1088 Bay Blvd",
    "sg:city":"Chula Vista",
    "sg:classifiers":[
        {
            "category":"Retail",
            "subcategory":"Auto Repair",
            "type":"Services"
        }
    ],
    "sg:phone":"+1 619 425 7019",
    "sg:postcode":"91911",
    "sg:province":"CA",
    "sg:tags":[
        "repairing",
        "automobile"
    ],
    "wof:name":"A & D Automotive",
    "wof:placetype":"venue"
},
  "geometry": {"coordinates":[-117.092331,32.606319],"type":"Point"}
}