{
  "type": "Feature",
  "properties": {
    "iso:country":"US",
    "sg:address":"1116 Ysabel St",
    "sg:city":"Redondo Beach",
    "sg:classifiers":[
        {
            "category":"Shopping",
            "subcategory":"Gifts & Souvenirs",
            "type":"Retail Goods"
        }
    ],
    "sg:phone":"+1 310 375 3665",
    "sg:postcode":"90277",
    "sg:province":"CA",
    "sg:tags":[
        "basket",
        "parcel"
    ],
    "wof:name":"Mixed-Bag",
    "wof:placetype":"venue"
},
  "geometry": {"coordinates":[-118.374291,33.831496],"type":"Point"}
}