{
  "type": "Feature",
  "properties": {
    "iso:country":"US",
    "sg:address":"70 S Oakland Ave",
    "sg:city":"Pasadena",
    "sg:classifiers":[
        {
            "category":"Organizations",
            "subcategory":"Religious Organization",
            "type":"Services"
        }
    ],
    "sg:phone":"+1 626 793 6813",
    "sg:postcode":"91101",
    "sg:province":"CA",
    "sg:tags":[
        "church"
    ],
    "wof:name":"Christian Science Churches",
    "wof:placetype":"venue"
},
  "geometry": {"coordinates":[-118.139653,34.14517],"type":"Point"}
}