{
  "type": "Feature",
  "properties": {
    "addr:full":"601 Court St Woodland CA 95695",
    "addr:housenumber":"601",
    "addr:postcode":"95695",
    "addr:street":"Court St",
    "iso:country":"US",
    "sg:address":"601 Court St",
    "sg:city":"Woodland",
    "sg:classifiers":[
        {
            "category":"Government",
            "subcategory":"Office",
            "type":"Public Place"
        }
    ],
    "sg:phone":"+1 530 666 8668",
    "sg:postcode":"95695",
    "sg:province":"CA",
    "sg:tags":[
        "county",
        "taxation"
    ],
    "wof:name":"Yolo County Office Of Revenue",
    "wof:placetype":"venue"
},
  "geometry": {"coordinates":[-121.771879,38.678744],"type":"Point"}
}