{
  "type": "Feature",
  "properties": {
    "iso:country":"US",
    "sg:address":"826 Seward St Ste 202",
    "sg:city":"Los Angeles",
    "sg:classifiers":[
        {
            "category":"Building & Trades",
            "subcategory":"Plumbing",
            "type":"Services"
        }
    ],
    "sg:phone":"+1 310 597 4498",
    "sg:postcode":"90038",
    "sg:province":"CA",
    "sg:website":"www.mrspeedyplumbing.com",
    "wof:name":"Mr Speedy Plumbing",
    "wof:placetype":"venue"
},
  "geometry": {"coordinates":[-118.33284,34.086116],"type":"Point"}
}