{
  "type": "Feature",
  "properties": {
    "addr:full":"103 S. Robertson Blvd Los Angeles CA 90048",
    "addr:housenumber":"103",
    "addr:postcode":"90048",
    "addr:street":"S. Robertson Blvd",
    "iso:country":"US",
    "sg:address":"103 S. Robertson Blvd",
    "sg:city":"Los Angeles",
    "sg:classifiers":[
        {
            "category":"Shopping",
            "subcategory":"Clothing, Apparel, & Fashions",
            "type":"Retail Goods"
        }
    ],
    "sg:phone":"+1 310 285 0486",
    "sg:postcode":"90048",
    "sg:province":"CA",
    "sg:tags":[
        "men's",
        "clothing",
        "women's"
    ],
    "sg:website":"www.rockandrepublic.com",
    "wof:name":"Rock & Republic",
    "wof:placetype":"venue"
},
  "geometry": {"coordinates":[-118.38373900000001,34.075055],"type":"Point"}
}