{
  "type": "Feature",
  "properties": {
    "addr:full":"19598 Rd 124 Tulare CA 93274",
    "addr:housenumber":"19598",
    "addr:postcode":"93274",
    "addr:street":"Rd 124",
    "iso:country":"US",
    "sg:address":"19598 Rd 124",
    "sg:city":"Tulare",
    "sg:classifiers":[
        {
            "category":"Retail",
            "subcategory":"Animal Services",
            "type":"Services"
        }
    ],
    "sg:phone":"+1 559 686 2364",
    "sg:postcode":"93274",
    "sg:province":"CA",
    "sg:tags":[
        "shelter"
    ],
    "wof:name":"Dale Baker Hoof Trimming Inc",
    "wof:placetype":"venue"
},
  "geometry": {"coordinates":[-119.295249,36.145566],"type":"Point"}
}