{
  "type": "Feature",
  "properties": {
    "iso:country":"US",
    "sg:address":"389 N Magnolia Ave",
    "sg:city":"El Cajon",
    "sg:classifiers":[
        {
            "category":"Arts & Performance",
            "subcategory":"Theater",
            "type":"Entertainment"
        }
    ],
    "sg:phone":"+1 619 449 5096",
    "sg:postcode":"92020",
    "sg:province":"CA",
    "wof:name":"Otto Wilhelm Schmidt Theatre",
    "wof:placetype":"venue"
},
  "geometry": {"coordinates":[-116.96228,32.797604],"type":"Point"}
}