{
  "type": "Feature",
  "properties": {
    "addr:full":"503 Giuseppe Ct Roseville CA 95678",
    "addr:housenumber":"503",
    "addr:postcode":"95678",
    "addr:street":"Giuseppe Ct",
    "iso:country":"US",
    "sg:address":"503 Giuseppe Ct",
    "sg:city":"Roseville",
    "sg:classifiers":[
        {
            "category":"Wholesale",
            "subcategory":"Office Equipment",
            "type":"Manufacturing & Wholesale Goods"
        },
        {
            "category":"Professional",
            "subcategory":"Engineering",
            "type":"Services"
        }
    ],
    "sg:phone":"+1 916 771 4280",
    "sg:postcode":"95678",
    "sg:province":"CA",
    "sg:tags":[
        "stapler",
        "staples",
        "consultant",
        "energy",
        "conservation",
        "tacker"
    ],
    "wof:name":"Staples & Associates",
    "wof:placetype":"venue"
},
  "geometry": {"coordinates":[-121.300034,38.730986],"type":"Point"}
}