{
  "type": "Feature",
  "properties": {
    "addr:full":"11151 Olympic Blvd Los Angeles CA 90025",
    "addr:housenumber":"11151",
    "addr:postcode":"90025",
    "addr:street":"Olympic Blvd",
    "iso:country":"US",
    "sg:address":"11151 Olympic Blvd",
    "sg:city":"Los Angeles",
    "sg:classifiers":[
        {
            "category":"Retail",
            "subcategory":"Auto Rental",
            "type":"Services"
        }
    ],
    "sg:phone":"+1 310 478 5216",
    "sg:postcode":"90025",
    "sg:province":"CA",
    "sg:tags":[
        "car"
    ],
    "sg:website":"www.enterprise.com/car_rental/de...",
    "wof:name":"Enterprise Exotic Car Collection Los Angeles",
    "wof:placetype":"venue"
},
  "geometry": {"coordinates":[-118.438896,34.039862],"type":"Point"}
}