{
  "type": "Feature",
  "properties": {
    "addr:full":"2540 99th Ave Oakland CA 94605",
    "addr:housenumber":"2540",
    "addr:postcode":"94605",
    "addr:street":"99Th Ave",
    "iso:country":"US",
    "sg:address":"2540 99th Ave",
    "sg:city":"Oakland",
    "sg:classifiers":[
        {
            "category":"Building & Trades",
            "subcategory":"Construction",
            "type":"Services"
        }
    ],
    "sg:phone":"+1 510 569 2735",
    "sg:postcode":"94605",
    "sg:province":"CA",
    "sg:tags":[
        "concrete",
        "pumping",
        "contractor"
    ],
    "wof:name":"Craft's Concrete Pumping",
    "wof:placetype":"venue"
},
  "geometry": {"coordinates":[-122.155331,37.747895],"type":"Point"}
}