{
  "type": "Feature",
  "properties": {
    "addr:full":"303 Second Street San Francisco CA 94107",
    "addr:housenumber":"303",
    "addr:postcode":"94107",
    "addr:street":"Second Street",
    "iso:country":"US",
    "sg:address":"303 Second Street",
    "sg:city":"San Francisco",
    "sg:classifiers":[
        {
            "category":"Education",
            "subcategory":"Preschool",
            "type":"Public Place"
        }
    ],
    "sg:postcode":"94107",
    "sg:province":"CA",
    "wof:name":"Bright Horizons 2nd Street Campus",
    "wof:placetype":"venue"
},
  "geometry": {"coordinates":[-122.396657,37.785528],"type":"Point"}
}