{
  "type": "Feature",
  "properties": {
    "addr:full":"5125 Linda Vista Road San Diego CA 92184",
    "addr:housenumber":"5125",
    "addr:postcode":"92184",
    "addr:street":"Linda Vista Road",
    "iso:country":"US",
    "sg:address":"5125 Linda Vista Road",
    "sg:city":"San Diego",
    "sg:classifiers":[
        {
            "category":"Bars & Pubs",
            "subcategory":"Nightclub",
            "type":"Food & Drink"
        }
    ],
    "sg:phone":"+1 619 291 4279",
    "sg:postcode":"92184",
    "sg:province":"CA",
    "sg:tags":[
        "nightlife"
    ],
    "wof:name":"JC's",
    "wof:placetype":"venue"
},
  "geometry": {"coordinates":[-117.19699900000001,32.7644],"type":"Point"}
}