{
  "type": "Feature",
  "properties": {
    "iso:country":"US",
    "sg:address":"485 Raleigh Ave",
    "sg:city":"El Cajon",
    "sg:classifiers":[
        {
            "category":"Manufacturing",
            "subcategory":"Tools & Machinery",
            "type":"Manufacturing & Wholesale Goods"
        }
    ],
    "sg:phone":"+1 619 593 9675",
    "sg:postcode":"92020",
    "sg:province":"CA",
    "sg:tags":[
        "equipment",
        "air",
        "conditioning",
        "heating"
    ],
    "wof:name":"Upg",
    "wof:placetype":"venue"
},
  "geometry": {"coordinates":[-116.973223,32.79735],"type":"Point"}
}