{
  "type": "Feature",
  "properties": {
    "iso:country":"US",
    "sg:address":"1931 W Middlefield Rd",
    "sg:city":"Mountain View",
    "sg:classifiers":[
        {
            "category":"Autos & Motor Vehicles",
            "subcategory":"Automobile Sales",
            "type":"Retail Goods"
        }
    ],
    "sg:phone":"+1 650 966 1630",
    "sg:postcode":"94043",
    "sg:province":"CA",
    "sg:tags":[
        "car",
        "dealer"
    ],
    "wof:name":"Auto Best Buy",
    "wof:placetype":"venue"
},
  "geometry": {"coordinates":[-122.090194,37.410617],"type":"Point"}
}