{
  "type": "Feature",
  "properties": {
    "iso:country":"US",
    "sg:address":"14006 Riverside Dr, Space #35",
    "sg:city":"Sherman Oaks",
    "sg:classifiers":[
        {
            "category":"Shopping",
            "subcategory":"Clothing, Apparel, & Fashions",
            "type":"Retail Goods"
        }
    ],
    "sg:phone":"+1 818 995 7688",
    "sg:postcode":"91423",
    "sg:province":"CA",
    "sg:tags":[
        "clothing",
        "women's"
    ],
    "sg:website":"www.forever21.com",
    "wof:name":"Forever 21",
    "wof:placetype":"venue"
},
  "geometry": {"coordinates":[-118.438034,34.157627],"type":"Point"}
}