{
  "type": "Feature",
  "properties": {
    "iso:country":"US",
    "sg:address":"312 Berkeley Ave",
    "sg:city":"Roseville",
    "sg:classifiers":[
        {
            "category":"Building & Trades",
            "subcategory":"Construction",
            "type":"Services"
        }
    ],
    "sg:phone":"+1 916 786 8376",
    "sg:postcode":"95678",
    "sg:province":"CA",
    "sg:tags":[
        "altering",
        "remodeling",
        "contractor"
    ],
    "wof:name":"Brass Construction",
    "wof:placetype":"venue"
},
  "geometry": {"coordinates":[-121.289451,38.751218],"type":"Point"}
}