{
  "type": "Feature",
  "properties": {
    "iso:country":"US",
    "sg:address":"2850 Poplar St",
    "sg:city":"Emeryville",
    "sg:classifiers":[
        {
            "category":"Transit Center",
            "subcategory":"Freight",
            "type":"Transportation"
        },
        {
            "category":"Retail",
            "subcategory":"Pet Boarding",
            "type":"Services"
        }
    ],
    "sg:phone":"+1 510 836 5315",
    "sg:postcode":"94608",
    "sg:province":"CA",
    "sg:tags":[
        "packing",
        "crating",
        "container"
    ],
    "wof:name":"California Architectural Products",
    "wof:placetype":"venue"
},
  "geometry": {"coordinates":[-122.285262,37.821441],"type":"Point"}
}