{
  "type": "Feature",
  "properties": {
    "iso:country":"US",
    "sg:address":"29700 Bradley Rd",
    "sg:city":"Sun City",
    "sg:classifiers":[
        {
            "category":"Sports & Exercise",
            "subcategory":"Gym",
            "type":"Entertainment"
        }
    ],
    "sg:phone":"+1 951 246 3530",
    "sg:postcode":"92586",
    "sg:province":"CA",
    "sg:website":"www.mvacelite.com/",
    "wof:name":"Menifee Valley Athletic Club & Day Spa",
    "wof:placetype":"venue"
},
  "geometry": {"coordinates":[-117.188558,33.689647],"type":"Point"}
}