{
  "type": "Feature",
  "properties": {
    "addr:full":"157 Leisure Way Vacaville CA 95687",
    "addr:housenumber":"157",
    "addr:postcode":"95687",
    "addr:street":"Leisure Way",
    "iso:country":"US",
    "sg:address":"157 Leisure Way",
    "sg:city":"Vacaville",
    "sg:classifiers":[
        {
            "category":"Organizations",
            "subcategory":"Religious Organization",
            "type":"Services"
        }
    ],
    "sg:phone":"+1 707 451 7304",
    "sg:postcode":"95687",
    "sg:province":"CA",
    "sg:tags":[
        "church"
    ],
    "wof:name":"Apostolic Cornerstone Church",
    "wof:placetype":"venue"
},
  "geometry": {"coordinates":[-121.938883,38.374785],"type":"Point"}
}