{
  "type": "Feature",
  "properties": {
    "addr:full":"4416 N Highland Ave Manhattan Beach CA 90266",
    "addr:housenumber":"4416",
    "addr:postcode":"90266",
    "addr:street":"N Highland Ave",
    "iso:country":"US",
    "sg:address":"4416 N Highland Ave",
    "sg:city":"Manhattan Beach",
    "sg:classifiers":[
        {
            "category":"Building & Trades",
            "subcategory":"Construction",
            "type":"Services"
        }
    ],
    "sg:phone":"+1 310 545 0872",
    "sg:postcode":"90266",
    "sg:province":"CA",
    "sg:tags":[
        "residential"
    ],
    "wof:name":"Urban Coast Association",
    "wof:placetype":"venue"
},
  "geometry": {"coordinates":[-118.42048200000001,33.905863],"type":"Point"}
}