{
  "type": "Feature",
  "properties": {
    "addr:full":"6721 Greenleaf Ave Whittier CA 90601",
    "addr:housenumber":"6721",
    "addr:postcode":"90601",
    "addr:street":"Greenleaf Ave",
    "iso:country":"US",
    "sg:address":"6721 Greenleaf Ave",
    "sg:city":"Whittier",
    "sg:classifiers":[
        {
            "category":"Shopping",
            "type":"Retail Goods"
        }
    ],
    "sg:phone":"+1 562 464 3636",
    "sg:postcode":"90601",
    "sg:province":"CA",
    "sg:tags":[
        "cosmetic",
        "perfume"
    ],
    "sg:website":"www.pourlebain.com",
    "wof:name":"Pour Le Bain",
    "wof:placetype":"venue"
},
  "geometry": {"coordinates":[-118.037406,33.97922],"type":"Point"}
}