{
  "type": "Feature",
  "properties": {
    "iso:country":"US",
    "sg:address":"2545 Buena Vista Way",
    "sg:city":"Berkeley",
    "sg:classifiers":[
        {
            "category":"Professional",
            "subcategory":"Business Services",
            "type":"Services"
        }
    ],
    "sg:phone":"+1 510 649 1703",
    "sg:postcode":"94708",
    "sg:province":"CA",
    "sg:tags":[
        "consultant",
        "coach"
    ],
    "wof:name":"Paths To Green",
    "wof:placetype":"venue"
},
  "geometry": {"coordinates":[-122.25961100000001,37.881032],"type":"Point"}
}