{
  "type": "Feature",
  "properties": {
    "iso:country":"US",
    "sg:address":"9477 Bolsa Ave",
    "sg:city":"Westminster",
    "sg:classifiers":[
        {
            "category":"Food & Beverages",
            "subcategory":"Groceries & Convenience Stores",
            "type":"Retail Goods"
        }
    ],
    "sg:phone":"+1 714 775 2656",
    "sg:postcode":"92683",
    "sg:province":"CA",
    "sg:tags":[
        "grocer"
    ],
    "wof:name":"Anhduc Market",
    "wof:placetype":"venue"
},
  "geometry": {"coordinates":[-117.964471,33.744867],"type":"Point"}
}