{
  "type": "Feature",
  "properties": {
    "iso:country":"US",
    "sg:address":"34000 Doheny Park Rd",
    "sg:city":"Capistrano Beach",
    "sg:classifiers":[
        {
            "category":"Home & Garden",
            "subcategory":"Carpets & Floor Coverings",
            "type":"Retail Goods"
        }
    ],
    "sg:phone":"+1 949 496 4400",
    "sg:postcode":"92624",
    "sg:province":"CA",
    "sg:tags":[
        "window"
    ],
    "wof:name":"Koala Carpet & Flooring",
    "wof:placetype":"venue"
},
  "geometry": {"coordinates":[-117.676953,33.467011],"type":"Point"}
}