{
  "type": "Feature",
  "properties": {
    "iso:country":"US",
    "sg:address":"321 7th St",
    "sg:city":"Coronado",
    "sg:classifiers":[
        {
            "category":"Shopping",
            "subcategory":"Bicycles & Sporting Goods",
            "type":"Retail Goods"
        }
    ],
    "sg:phone":"+1 619 437 7095",
    "sg:postcode":"92118",
    "sg:province":"CA",
    "sg:website":"www.hwbt.com",
    "wof:name":"Howie Wowie Bicycle Tours",
    "wof:placetype":"venue"
},
  "geometry": {"coordinates":[-117.185873,32.69387],"type":"Point"}
}