{
  "type": "Feature",
  "properties": {
    "iso:country":"US",
    "sg:address":"1348 Bertland Ct",
    "sg:city":"San Jose",
    "sg:classifiers":[
        {
            "category":"Professional",
            "subcategory":"Management & Consulting",
            "type":"Services"
        }
    ],
    "sg:phone":"+1 408 254 3708",
    "sg:postcode":"95131",
    "sg:province":"CA",
    "sg:tags":[
        "consultant",
        "educational"
    ],
    "wof:name":"JSU Joblink Inc",
    "wof:placetype":"venue"
},
  "geometry": {"coordinates":[-121.87524,37.382955],"type":"Point"}
}