{
  "type": "Feature",
  "properties": {
    "iso:country":"US",
    "sg:address":"2330 W Middlefield Rd",
    "sg:city":"Mountain View",
    "sg:classifiers":[
        {
            "category":"Real Estate",
            "subcategory":"Architect",
            "type":"Services"
        }
    ],
    "sg:phone":"+1 831 625 2840",
    "sg:postcode":"94043",
    "sg:province":"CA",
    "sg:tags":[
        "building",
        "designer"
    ],
    "wof:name":"Honeywell Design",
    "wof:placetype":"venue"
},
  "geometry": {"coordinates":[-122.09611,37.411747],"type":"Point"}
}