{
  "type": "Feature",
  "properties": {
    "iso:country":"US",
    "sg:address":"6132 E Teton Ave",
    "sg:city":"Orange",
    "sg:classifiers":[
        {
            "category":"Government",
            "subcategory":"Office",
            "type":"Public Place"
        }
    ],
    "sg:phone":"+1 760 272 4010",
    "sg:postcode":"92867",
    "sg:province":"CA",
    "sg:tags":[
        "agricultural",
        "regulation",
        "marketing"
    ],
    "wof:name":"Growfirst",
    "wof:placetype":"venue"
},
  "geometry": {"coordinates":[-117.787782,33.820717],"type":"Point"}
}