{
  "type": "Feature",
  "properties": {
    "addr:full":"325 7th Avenue San Diego CA 92101",
    "addr:housenumber":"325",
    "addr:postcode":"92101",
    "addr:street":"7Th Avenue",
    "iso:country":"US",
    "sg:address":"325 7th Avenue",
    "sg:city":"San Diego",
    "sg:classifiers":[
        {
            "category":"Real Estate",
            "subcategory":"Real Estate Agent",
            "type":"Services"
        }
    ],
    "sg:phone":"+1 619 630 7138",
    "sg:postcode":"92101",
    "sg:province":"CA",
    "wof:name":"Richard M Combs",
    "wof:placetype":"venue"
},
  "geometry": {"coordinates":[-117.157848,32.708865],"type":"Point"}
}