{
  "type": "Feature",
  "properties": {
    "addr:full":"705 J St Sacramento CA 95814",
    "addr:housenumber":"705",
    "addr:postcode":"95814",
    "addr:street":"J St",
    "iso:country":"US",
    "sg:address":"705 J St",
    "sg:city":"Sacramento",
    "sg:classifiers":[
        {
            "category":"Professional",
            "type":"Services"
        }
    ],
    "sg:phone":"+1 916 442 6741",
    "sg:postcode":"95814",
    "sg:province":"CA",
    "wof:name":"Al Riccis Inc",
    "wof:placetype":"venue"
},
  "geometry": {"coordinates":[-121.496143,38.581109],"type":"Point"}
}