{
  "type": "Feature",
  "properties": {
    "addr:full":"501 Riverside Ave Paso Robles CA 93446",
    "addr:housenumber":"501",
    "addr:postcode":"93446",
    "addr:street":"Riverside Ave",
    "iso:country":"US",
    "sg:address":"501 Riverside Ave",
    "sg:city":"Paso Robles",
    "sg:classifiers":[
        {
            "category":"Wholesale",
            "subcategory":"Hardware",
            "type":"Manufacturing & Wholesale Goods"
        }
    ],
    "sg:phone":"+1 805 238 6906",
    "sg:postcode":"93446",
    "sg:province":"CA",
    "sg:tags":[
        "tool"
    ],
    "wof:name":"T-K Tool Co",
    "wof:placetype":"venue"
},
  "geometry": {"coordinates":[-120.68647799999999,35.620712],"type":"Point"}
}