{
  "type": "Feature",
  "properties": {
    "iso:country":"US",
    "sg:address":"5259 Corteen Pl",
    "sg:city":"Valley Village",
    "sg:classifiers":[
        {
            "category":"Communications",
            "subcategory":"Film & Video Production",
            "type":"Services"
        }
    ],
    "sg:phone":"+1 323 493 8644",
    "sg:postcode":"91607",
    "sg:province":"CA",
    "sg:tags":[
        "taping"
    ],
    "wof:name":"Black Derby Productions",
    "wof:placetype":"venue"
},
  "geometry": {"coordinates":[-118.402039,34.167203],"type":"Point"}
}