{
  "type": "Feature",
  "properties": {
    "addr:full":"2672 Bayshore Pkwy Mountain View CA 94043",
    "addr:housenumber":"2672",
    "addr:postcode":"94043",
    "addr:street":"Bayshore Pkwy",
    "iso:country":"US",
    "sg:address":"2672 Bayshore Pkwy",
    "sg:city":"Mountain View",
    "sg:classifiers":[
        {
            "category":"Health Services",
            "subcategory":"Health Practitioner",
            "type":"Services"
        }
    ],
    "sg:phone":"+1 650 988 1949",
    "sg:postcode":"94043",
    "sg:province":"CA",
    "sg:tags":[
        "psychologist"
    ],
    "wof:name":"Culberson Couple Counseling",
    "wof:placetype":"venue"
},
  "geometry": {"coordinates":[-122.100032,37.429331],"type":"Point"}
}