{
  "type": "Feature",
  "properties": {
    "addr:full":"10721 14th Ave Armona CA 93202",
    "addr:housenumber":"10721",
    "addr:postcode":"93202",
    "addr:street":"14Th Ave",
    "iso:country":"US",
    "sg:address":"10721 14th Ave",
    "sg:city":"Armona",
    "sg:classifiers":[
        {
            "category":"Shopping",
            "subcategory":"Gifts & Souvenirs",
            "type":"Retail Goods"
        }
    ],
    "sg:phone":"+1 559 582 7536",
    "sg:postcode":"93202",
    "sg:province":"CA",
    "sg:tags":[
        "party",
        "supply"
    ],
    "wof:name":"Mr Balloons",
    "wof:placetype":"venue"
},
  "geometry": {"coordinates":[-119.708904,36.318692],"type":"Point"}
}