{
  "type": "Feature",
  "properties": {
    "addr:full":"2196 Foothill Blvd Ste A2 La Canada Flintridge CA 91011",
    "addr:housenumber":"2196",
    "addr:postcode":"91011",
    "addr:street":"Foothill Blvd Ste A2 La Canada",
    "iso:country":"US",
    "sg:address":"2196 Foothill Blvd Ste A2",
    "sg:city":"La Canada Flintridge",
    "sg:classifiers":[
        {
            "category":"Shopping",
            "subcategory":"Clothing, Apparel, & Fashions",
            "type":"Retail Goods"
        }
    ],
    "sg:phone":"+1 818 957 3077",
    "sg:postcode":"91011",
    "sg:province":"CA",
    "sg:tags":[
        "children's",
        "clothing"
    ],
    "sg:website":"www.babyrai.com",
    "wof:name":"Baby Rai",
    "wof:placetype":"venue"
},
  "geometry": {"coordinates":[-118.22515,34.215863],"type":"Point"}
}