{
  "type": "Feature",
  "properties": {
    "addr:full":"4790 Dewey Dr Fair Oaks CA 95628",
    "addr:housenumber":"4790",
    "addr:postcode":"95628",
    "addr:street":"Dewey Dr",
    "iso:country":"US",
    "sg:address":"4790 Dewey Dr",
    "sg:city":"Fair Oaks",
    "sg:classifiers":[
        {
            "category":"Professional",
            "subcategory":"Accounting & Tax Preparation",
            "type":"Services"
        }
    ],
    "sg:phone":"+1 916 564 5555",
    "sg:postcode":"95628",
    "sg:province":"CA",
    "sg:tags":[
        "accountant"
    ],
    "wof:name":"Beil Mark CPA",
    "wof:placetype":"venue"
},
  "geometry": {"coordinates":[-121.307999,38.650501],"type":"Point"}
}