{
  "type": "Feature",
  "properties": {
    "iso:country":"US",
    "sg:address":"407 Irving Dr",
    "sg:city":"Burbank",
    "sg:classifiers":[
        {
            "category":"Donuts",
            "subcategory":"None",
            "type":"Food & Drink"
        }
    ],
    "sg:phone":"+1 818 843 9353",
    "sg:postcode":"91504",
    "sg:province":"CA",
    "wof:name":"Donut Prince",
    "wof:placetype":"venue"
},
  "geometry": {"coordinates":[-118.328003,34.1992],"type":"Point"}
}