{
  "type": "Feature",
  "properties": {
    "iso:country":"US",
    "sg:address":"1061 Leslie St",
    "sg:city":"La Habra",
    "sg:classifiers":[
        {
            "category":"Manufacturing",
            "subcategory":"Rubber & Plastics",
            "type":"Manufacturing & Wholesale Goods"
        }
    ],
    "sg:phone":"+1 714 738 7990",
    "sg:postcode":"90631",
    "sg:province":"CA",
    "sg:website":"www.acrylicdisplayinc.com",
    "wof:name":"American Acrylic Display",
    "wof:placetype":"venue"
},
  "geometry": {"coordinates":[-117.94009800000001,33.917494],"type":"Point"}
}