{
  "type": "Feature",
  "properties": {
    "iso:country":"US",
    "sg:address":"2236 S Santa Fe Ave",
    "sg:city":"Vista",
    "sg:classifiers":[
        {
            "category":"Building & Trades",
            "subcategory":"Landscaping Services",
            "type":"Services"
        }
    ],
    "sg:phone":"+1 760 941 3992",
    "sg:postcode":"92084",
    "sg:province":"CA",
    "sg:tags":[
        "durable",
        "good"
    ],
    "wof:name":"Sutton Tree Service Inc",
    "wof:placetype":"venue"
},
  "geometry": {"coordinates":[-117.206414,33.169578],"type":"Point"}
}