{
  "type": "Feature",
  "properties": {
    "iso:country":"US",
    "sg:address":"4939 Arlington Ave Ste B",
    "sg:city":"Riverside",
    "sg:phone":"+1 951 684 4160",
    "sg:postcode":"92504",
    "sg:province":"CA",
    "wof:name":"Heads Up By Lori",
    "wof:placetype":"venue"
},
  "geometry": {"coordinates":[-117.410674,33.946172],"type":"Point"}
}