{
  "type": "Feature",
  "properties": {
    "iso:country":"US",
    "sg:address":"675 Paularino Avenue",
    "sg:city":"Costa Mesa",
    "sg:classifiers":[
        {
            "category":"Food & Beverages",
            "subcategory":"Groceries & Convenience Stores",
            "type":"Retail Goods"
        }
    ],
    "sg:phone":"+1 714 751 4652",
    "sg:postcode":"92626",
    "sg:province":"CA",
    "wof:name":"7-Eleven Food Stores",
    "wof:placetype":"venue"
},
  "geometry": {"coordinates":[-117.884727,33.682363],"type":"Point"}
}