{
  "type": "Feature",
  "properties": {
    "iso:country":"US",
    "sg:address":"16904 Sierra Hwy",
    "sg:city":"Canyon Cntry",
    "sg:classifiers":[
        {
            "category":"Building & Trades",
            "subcategory":"Construction",
            "type":"Services"
        }
    ],
    "sg:phone":"+1 661 298 1192",
    "sg:postcode":"91351",
    "sg:province":"CA",
    "sg:tags":[
        "contractor"
    ],
    "wof:name":"R J G Construction",
    "wof:placetype":"venue"
},
  "geometry": {"coordinates":[-118.431999,34.438301],"type":"Point"}
}