{
  "type": "Feature",
  "properties": {
    "addr:full":"646 Flinn Ave Moorpark CA 93021",
    "addr:housenumber":"646",
    "addr:postcode":"ca 93021",
    "addr:street":"Flinn Ave",
    "iso:country":"US",
    "sg:address":"646 Flinn Ave",
    "sg:city":"Moorpark",
    "sg:classifiers":[
        {
            "category":"Building & Trades",
            "subcategory":"Construction",
            "type":"Services"
        }
    ],
    "sg:phone":"+1 805 530 3544",
    "sg:postcode":"93021",
    "sg:province":"CA",
    "sg:tags":[
        "concrete",
        "contractor"
    ],
    "wof:name":"C M Concrete Inc",
    "wof:placetype":"venue"
},
  "geometry": {"coordinates":[-118.87227300000001,34.28254],"type":"Point"}
}