{
  "type": "Feature",
  "properties": {
    "addr:full":"1080 N Irwin St Hanford CA 93230",
    "addr:housenumber":"1080",
    "addr:postcode":"ca 93230",
    "addr:street":"N Irwin St",
    "iso:country":"US",
    "sg:address":"1080 N Irwin St",
    "sg:city":"Hanford",
    "sg:classifiers":[
        {
            "category":"Health Services",
            "subcategory":"Chiropractor",
            "type":"Services"
        }
    ],
    "sg:phone":"+1 559 582 2684",
    "sg:postcode":"93230",
    "sg:province":"CA",
    "wof:name":"C S WYNN Chiropractic Offices",
    "wof:placetype":"venue"
},
  "geometry": {"coordinates":[-119.647764,36.335095],"type":"Point"}
}