{
  "type": "Feature",
  "properties": {
    "iso:country":"US",
    "sg:address":"4450 Black Ave Ste B",
    "sg:city":"Pleasanton",
    "sg:classifiers":[
        {
            "category":"Professional",
            "subcategory":"Lawyer & Legal Services",
            "type":"Services"
        }
    ],
    "sg:phone":"+1 925 462 0665",
    "sg:postcode":"94566",
    "sg:province":"CA",
    "sg:tags":[
        "attorney",
        "law",
        "family",
        "practice",
        "plan",
        "criminal"
    ],
    "wof:name":"Tomcik James R Law Office Of",
    "wof:placetype":"venue"
},
  "geometry": {"coordinates":[-121.87559299999999,37.672194],"type":"Point"}
}