{
  "type": "Feature",
  "properties": {
    "iso:country":"US",
    "sg:address":"480 2nd St",
    "sg:city":"San Francisco",
    "sg:classifiers":[
        {
            "category":"Professional",
            "type":"Services"
        }
    ],
    "sg:phone":"+1 415 357 1177",
    "sg:postcode":"94107",
    "sg:province":"CA",
    "sg:tags":[
        "establishment"
    ],
    "wof:name":"Hedge Flex",
    "wof:placetype":"venue"
},
  "geometry": {"coordinates":[-122.39392,37.783277],"type":"Point"}
}