{
  "type": "Feature",
  "properties": {
    "addr:full":"1063 Gayley Ave Los Angeles CA 90024",
    "addr:housenumber":"1063",
    "addr:postcode":"90024",
    "addr:street":"Gayley Ave",
    "iso:country":"US",
    "sg:address":"1063 Gayley Ave",
    "sg:city":"Los Angeles",
    "sg:classifiers":[
        {
            "category":"Real Estate",
            "subcategory":"Architect",
            "type":"Services"
        }
    ],
    "sg:phone":"+1 310 208 0197",
    "sg:postcode":"90024",
    "sg:province":"CA",
    "wof:name":"Bobrow-Thomas & Associates",
    "wof:placetype":"venue"
},
  "geometry": {"coordinates":[-118.44699900000001,34.061298],"type":"Point"}
}