{
  "type": "Feature",
  "properties": {
    "iso:country":"US",
    "sg:address":"1408 Esplanade",
    "sg:city":"Redondo Beach",
    "sg:classifiers":[
        {
            "category":"Freight",
            "type":"Transportation"
        }
    ],
    "sg:phone":"+1 310 792 8186",
    "sg:postcode":"90277",
    "sg:province":"CA",
    "wof:name":"Showtime Logistics",
    "wof:placetype":"venue"
},
  "geometry": {"coordinates":[-118.389695,33.821425],"type":"Point"}
}