{
  "type": "Feature",
  "properties": {
    "addr:full":"6060 Sunrise Vista Drive Citrus Heights CA 95610",
    "addr:housenumber":"6060",
    "addr:postcode":"95610",
    "addr:street":"Sunrise Vista Drive",
    "iso:country":"US",
    "sg:address":"6060 Sunrise Vista Drive",
    "sg:city":"Citrus Heights",
    "sg:classifiers":[
        {
            "category":"Banks & Credit Unions",
            "subcategory":"Investment Brokerage",
            "type":"Services"
        }
    ],
    "sg:phone":"+1 916 729 5181",
    "sg:postcode":"95610",
    "sg:province":"CA",
    "sg:tags":[
        "investing"
    ],
    "wof:name":"G M Kenney & Associates Estate & Insurance Services",
    "wof:placetype":"venue"
},
  "geometry": {"coordinates":[-121.26448000000001,38.676091],"type":"Point"}
}