{
  "type": "Feature",
  "properties": {
    "addr:full":"4739 Mission St San Francisco CA 94112",
    "addr:housenumber":"4739",
    "addr:postcode":"94112",
    "addr:street":"Mission St",
    "iso:country":"US",
    "sg:address":"4739 Mission St",
    "sg:city":"San Francisco",
    "sg:classifiers":[
        {
            "category":"Building & Trades",
            "subcategory":"Plumbing",
            "type":"Services"
        }
    ],
    "sg:phone":"+1 415 509 5069",
    "sg:postcode":"94112",
    "sg:province":"CA",
    "sg:website":"www.sfbayareaplumbing.com",
    "wof:name":"Maxxcal Plumbing",
    "wof:placetype":"venue"
},
  "geometry": {"coordinates":[-122.436516,37.72252],"type":"Point"}
}