{
  "type": "Feature",
  "properties": {
    "iso:country":"US",
    "sg:address":"33 3rd St",
    "sg:city":"Gonzales",
    "sg:classifiers":[
        {
            "category":"Food & Beverages",
            "subcategory":"Bakery",
            "type":"Retail Goods"
        }
    ],
    "sg:phone":"+1 831 675 2337",
    "sg:postcode":"93926",
    "sg:province":"CA",
    "sg:tags":[
        "baker"
    ],
    "wof:name":"LA Plaza Bakery",
    "wof:placetype":"venue"
},
  "geometry": {"coordinates":[-121.44382899999999,36.505998],"type":"Point"}
}