{
  "type": "Feature",
  "properties": {
    "iso:country":"US",
    "sg:address":"307 Pso Tesoro",
    "sg:city":"Walnut",
    "sg:classifiers":[
        {
            "category":"Shopping",
            "subcategory":"Clothing, Apparel, & Fashions",
            "type":"Retail Goods"
        }
    ],
    "sg:phone":"+1 909 598 7532",
    "sg:postcode":"91789",
    "sg:province":"CA",
    "sg:tags":[
        "wig",
        "toupee",
        "hairpiece"
    ],
    "wof:name":"MLZ Inc",
    "wof:placetype":"venue"
},
  "geometry": {"coordinates":[-117.857376,34.013622],"type":"Point"}
}