{
  "type": "Feature",
  "properties": {
    "iso:country":"US",
    "sg:address":"1691 Garden St",
    "sg:city":"Redlands",
    "sg:classifiers":[
        {
            "category":"Home & Garden",
            "subcategory":"Building Materials",
            "type":"Retail Goods"
        }
    ],
    "sg:phone":"+1 909 335 8530",
    "sg:postcode":"92373",
    "sg:province":"CA",
    "sg:tags":[
        "center",
        "merchandise-wholesale"
    ],
    "wof:name":"Kak Home & Garden Imports",
    "wof:placetype":"venue"
},
  "geometry": {"coordinates":[-117.15492999999999,34.026299],"type":"Point"}
}