{
  "type": "Feature",
  "properties": {
    "addr:full":"170 17th St Pacific Grove CA 93950",
    "addr:housenumber":"170",
    "addr:postcode":"93950",
    "addr:street":"17Th St",
    "iso:country":"US",
    "sg:address":"170 17th St",
    "sg:city":"Pacific Grove",
    "sg:classifiers":[
        {
            "category":"Social Services",
            "type":"Services"
        }
    ],
    "sg:phone":"+1 831 656 9605",
    "sg:postcode":"93950",
    "sg:province":"CA",
    "sg:tags":[
        "counselor",
        "marriage",
        "family"
    ],
    "wof:name":"Abbey Bukofzer Ms Family",
    "wof:placetype":"venue"
},
  "geometry": {"coordinates":[-121.91878199999999,36.621812],"type":"Point"}
}