{
  "type": "Feature",
  "properties": {
    "iso:country":"US",
    "sg:address":"1174 Blanc Ct",
    "sg:city":"Pleasanton",
    "sg:classifiers":[
        {
            "category":"Food & Beverages",
            "subcategory":"Specialty",
            "type":"Retail Goods"
        }
    ],
    "sg:phone":"+1 925 484 1076",
    "sg:postcode":"94566",
    "sg:province":"CA",
    "wof:name":"Healthy Resources",
    "wof:placetype":"venue"
},
  "geometry": {"coordinates":[-121.852278,37.655628],"type":"Point"}
}