{
  "type": "Feature",
  "properties": {
    "addr:full":"150 Clark St Auburn CA 95603",
    "addr:housenumber":"150",
    "addr:postcode":"ca 95603",
    "addr:street":"Clark St",
    "iso:country":"US",
    "sg:address":"150 Clark St",
    "sg:city":"Auburn",
    "sg:classifiers":[
        {
            "category":"Professional",
            "subcategory":"Detective & Security Services",
            "type":"Services"
        }
    ],
    "sg:phone":"+1 530 888 7522",
    "sg:postcode":"95603",
    "sg:province":"CA",
    "sg:tags":[
        "investigator"
    ],
    "wof:name":"Polinsky & Assoc Investigation",
    "wof:placetype":"venue"
},
  "geometry": {"coordinates":[-121.081678,38.890321],"type":"Point"}
}