{
  "type": "Feature",
  "properties": {
    "iso:country":"US",
    "sg:address":"779 Union St",
    "sg:city":"San Francisco",
    "sg:classifiers":[
        {
            "category":"Wholesale",
            "subcategory":"Computers",
            "type":"Manufacturing & Wholesale Goods"
        }
    ],
    "sg:phone":"+1 415 421 1131",
    "sg:postcode":"94133",
    "sg:province":"CA",
    "sg:tags":[
        "consulting",
        "it",
        "software"
    ],
    "wof:name":"Licatek Corporation",
    "wof:placetype":"venue"
},
  "geometry": {"coordinates":[-122.412082,37.800018],"type":"Point"}
}