{
  "type": "Feature",
  "properties": {
    "iso:country":"US",
    "sg:address":"14301 Inglewood Ave",
    "sg:city":"Hawthorne",
    "sg:classifiers":[
        {
            "category":"Restaurant",
            "type":"Food & Drink"
        }
    ],
    "sg:menulink":"http://www.allmenus.com/ca/inglewood/8921-dennys/menu/",
    "sg:phone":"+1 310 676 6097",
    "sg:postcode":"90250",
    "sg:province":"CA",
    "sg:tags":[
        "american",
        "diner"
    ],
    "wof:name":"Denny's",
    "wof:placetype":"venue"
},
  "geometry": {"coordinates":[-118.36129699999999,33.901625],"type":"Point"}
}