{
  "type": "Feature",
  "properties": {
    "addr:full":"16610 Pso de Las Brisas Ramona CA 92065",
    "addr:housenumber":"16610",
    "addr:postcode":"92065",
    "addr:street":"Pso De Las Brisas",
    "iso:country":"US",
    "sg:address":"16610 Pso de Las Brisas",
    "sg:city":"Ramona",
    "sg:classifiers":[
        {
            "category":"Professional",
            "type":"Services"
        }
    ],
    "sg:phone":"+1 760 787 9870",
    "sg:postcode":"92065",
    "sg:province":"CA",
    "wof:name":"Brisa Enterprises Inc",
    "wof:placetype":"venue"
},
  "geometry": {"coordinates":[-116.950288,33.020808],"type":"Point"}
}