{
  "type": "Feature",
  "properties": {
    "iso:country":"US",
    "sg:address":"8269 Laguna Blvd",
    "sg:city":"Elk Grove",
    "sg:classifiers":[
        {
            "category":"Shopping",
            "subcategory":"Jewelry",
            "type":"Retail Goods"
        }
    ],
    "sg:phone":"+1 916 684 1467",
    "sg:postcode":"95758",
    "sg:province":"CA",
    "sg:tags":[
        "jeweler"
    ],
    "wof:name":"Regal Jewelers",
    "wof:placetype":"venue"
},
  "geometry": {"coordinates":[-121.402525,38.422274],"type":"Point"}
}