{
  "type": "Feature",
  "properties": {
    "addr:full":"1275 Hudson Ave Saint Helena CA 94574",
    "addr:housenumber":"1275",
    "addr:postcode":"94574",
    "addr:street":"Hudson Ave",
    "iso:country":"US",
    "sg:address":"1275 Hudson Ave",
    "sg:city":"Saint Helena",
    "sg:classifiers":[
        {
            "category":"Travel",
            "subcategory":"Travel Agent",
            "type":"Entertainment"
        }
    ],
    "sg:phone":"+1 707 963 9504",
    "sg:postcode":"94574",
    "sg:province":"CA",
    "sg:tags":[
        "operator",
        "tour"
    ],
    "wof:name":"Galavant Price",
    "wof:placetype":"venue"
},
  "geometry": {"coordinates":[-122.47356499999999,38.49814],"type":"Point"}
}