{
  "type": "Feature",
  "properties": {
    "addr:full":"2323 Kern St Fresno CA 93721",
    "addr:housenumber":"2323",
    "addr:postcode":"93721",
    "addr:street":"Kern St",
    "iso:country":"US",
    "sg:address":"2323 Kern St",
    "sg:city":"Fresno",
    "sg:classifiers":[
        {
            "category":"Personal",
            "subcategory":"Shoe Repair & Shine",
            "type":"Services"
        }
    ],
    "sg:phone":"+1 559 268 3539",
    "sg:postcode":"93721",
    "sg:province":"CA",
    "sg:tags":[
        "repairing",
        "boot"
    ],
    "wof:name":"KERN Street Cobbler",
    "wof:placetype":"venue"
},
  "geometry": {"coordinates":[-119.78523800000001,36.735707],"type":"Point"}
}