{
  "type": "Feature",
  "properties": {
    "addr:full":"2523 California Street San Francisco CA 94115",
    "addr:housenumber":"2523",
    "addr:postcode":"94115",
    "addr:street":"California Street",
    "iso:country":"US",
    "sg:address":"2523 California Street",
    "sg:city":"San Francisco",
    "sg:classifiers":[
        {
            "category":"Real Estate",
            "subcategory":"Real Estate Services",
            "type":"Services"
        }
    ],
    "sg:phone":"+1 415 730 3337",
    "sg:postcode":"94115",
    "sg:province":"CA",
    "sg:website":"zephyrsf.com",
    "wof:name":"Marika Fishman - Zephyr Real Estate",
    "wof:placetype":"venue"
},
  "geometry": {"coordinates":[-122.43605100000001,37.788607],"type":"Point"}
}