{
  "type": "Feature",
  "properties": {
    "iso:country":"US",
    "sg:address":"141 S B St",
    "sg:city":"Exeter",
    "sg:classifiers":[
        {
            "category":"Shopping",
            "subcategory":"Used Merchandise",
            "type":"Retail Goods"
        }
    ],
    "sg:phone":"+1 559 594 4060",
    "sg:postcode":"93221",
    "sg:province":"CA",
    "sg:tags":[
        "antique"
    ],
    "wof:name":"By The Water Tower Antiques",
    "wof:placetype":"venue"
},
  "geometry": {"coordinates":[-119.13669,36.296882],"type":"Point"}
}