{
  "type": "Feature",
  "properties": {
    "iso:country":"US",
    "sg:address":"4262 Elenda St",
    "sg:city":"Culver City",
    "sg:classifiers":[
        {
            "category":"Manufacturing",
            "subcategory":"Furniture",
            "type":"Manufacturing & Wholesale Goods"
        }
    ],
    "sg:phone":"+1 310 558 1998",
    "sg:postcode":"90230",
    "sg:province":"CA",
    "sg:tags":[
        "household",
        "wood",
        "mfg"
    ],
    "wof:name":"Kathy Allred Designs",
    "wof:placetype":"venue"
},
  "geometry": {"coordinates":[-118.404347,34.00926],"type":"Point"}
}