{
  "type": "Feature",
  "properties": {
    "iso:country":"US",
    "sg:address":"109 Capitola Ave",
    "sg:city":"Capitola",
    "sg:classifiers":[
        {
            "category":"Shopping",
            "type":"Retail Goods"
        }
    ],
    "sg:phone":"+1 831 464 3838",
    "sg:postcode":"95010",
    "sg:province":"CA",
    "sg:tags":[
        "art",
        "gallery",
        "dealer"
    ],
    "wof:name":"Sally Bookman The Gallery",
    "wof:placetype":"venue"
},
  "geometry": {"coordinates":[-121.950985,36.972815],"type":"Point"}
}