{
  "type": "Feature",
  "properties": {
    "addr:full":"2712 26th Ave Oakland CA 94601",
    "addr:housenumber":"2712",
    "addr:postcode":"94601",
    "addr:street":"26Th Ave",
    "iso:country":"US",
    "sg:address":"2712 26th Ave",
    "sg:city":"Oakland",
    "sg:classifiers":[
        {
            "category":"Professional",
            "subcategory":"Management & Consulting",
            "type":"Services"
        }
    ],
    "sg:phone":"+1 510 436 4932",
    "sg:postcode":"94601",
    "sg:province":"CA",
    "sg:tags":[
        "retail",
        "direct",
        "sales"
    ],
    "wof:name":"El Elyon",
    "wof:placetype":"venue"
},
  "geometry": {"coordinates":[-122.221205,37.793467],"type":"Point"}
}