{
  "type": "Feature",
  "properties": {
    "iso:country":"US",
    "sg:address":"1870 S Carlos Ave",
    "sg:city":"Ontario",
    "sg:classifiers":[
        {
            "category":"Wholesale",
            "subcategory":"Motor Vehicles",
            "type":"Manufacturing & Wholesale Goods"
        }
    ],
    "sg:phone":"+1 909 930 1998",
    "sg:postcode":"91761",
    "sg:province":"CA",
    "sg:tags":[
        "automobile",
        "truck",
        "broker"
    ],
    "wof:name":"Paint Source Inc",
    "wof:placetype":"venue"
},
  "geometry": {"coordinates":[-117.606643,34.039157],"type":"Point"}
}