{
  "type": "Feature",
  "properties": {
    "addr:full":"5691 Jara Ct La Grange CA 95329",
    "addr:housenumber":"5691",
    "addr:postcode":"95329",
    "addr:street":"Jara Ct",
    "iso:country":"US",
    "sg:address":"5691 Jara Ct",
    "sg:city":"La Grange",
    "sg:classifiers":[
        {
            "category":"Building & Trades",
            "subcategory":"Plumbing",
            "type":"Services"
        }
    ],
    "sg:phone":"+1 209 852 9558",
    "sg:postcode":"95329",
    "sg:province":"CA",
    "sg:tags":[
        "sheet",
        "metal",
        "heating",
        "air",
        "conditioning",
        "contractor"
    ],
    "wof:name":"Nestech Mechanical Inc",
    "wof:placetype":"venue"
},
  "geometry": {"coordinates":[-120.353633,37.727058],"type":"Point"}
}