{
  "type": "Feature",
  "properties": {
    "iso:country":"US",
    "sg:address":"15701 Condon Ave",
    "sg:city":"Lawndale",
    "sg:classifiers":[
        {
            "category":"Retail",
            "subcategory":"Laundry & Dry Cleaning",
            "type":"Services"
        }
    ],
    "sg:phone":"+1 310 536 0477",
    "sg:postcode":"90260",
    "sg:province":"CA",
    "sg:tags":[
        "cleaners"
    ],
    "wof:name":"Karen's Plant",
    "wof:placetype":"venue"
},
  "geometry": {"coordinates":[-118.360035,33.889388],"type":"Point"}
}