{
  "type": "Feature",
  "properties": {
    "iso:country":"US",
    "sg:address":"708 1/2 Marigold Ave",
    "sg:city":"Corona Del Mar",
    "sg:classifiers":[
        {
            "category":"Building & Trades",
            "subcategory":"Construction",
            "type":"Services"
        }
    ],
    "sg:phone":"+1 949 640 7560",
    "sg:postcode":"92625",
    "sg:province":"CA",
    "sg:tags":[
        "contractor"
    ],
    "wof:name":"Team Ultimo General Contractor",
    "wof:placetype":"venue"
},
  "geometry": {"coordinates":[-117.867277,33.598369],"type":"Point"}
}