{
  "type": "Feature",
  "properties": {
    "addr:full":"1110 Larabee Creek Rd Redcrest CA 95569",
    "addr:housenumber":"1110",
    "addr:postcode":"95569",
    "addr:street":"Larabee Creek Rd",
    "iso:country":"US",
    "sg:address":"1110 Larabee Creek Rd",
    "sg:city":"Redcrest",
    "sg:classifiers":[
        {
            "category":"Building & Trades",
            "subcategory":"Construction",
            "type":"Services"
        }
    ],
    "sg:phone":"+1 707 722 4372",
    "sg:postcode":"95569",
    "sg:province":"CA",
    "sg:tags":[
        "painter"
    ],
    "wof:name":"Vic's Quality Painting",
    "wof:placetype":"venue"
},
  "geometry": {"coordinates":[-123.92885699999999,40.411907],"type":"Point"}
}