{
  "type": "Feature",
  "properties": {
    "iso:country":"US",
    "sg:address":"428 N Buchanan Cir",
    "sg:city":"Martinez",
    "sg:classifiers":[
        {
            "category":"Manufacturing",
            "subcategory":"Soap",
            "type":"Manufacturing & Wholesale Goods"
        }
    ],
    "sg:phone":"+1 925 372 8166",
    "sg:postcode":"94553",
    "sg:province":"CA",
    "sg:tags":[
        "detergent",
        "mfg"
    ],
    "wof:name":"Howell Associates",
    "wof:placetype":"venue"
},
  "geometry": {"coordinates":[-122.07188600000001,37.991108],"type":"Point"}
}