{
  "type": "Feature",
  "properties": {
    "addr:full":"18227 Jovan St Tarzana CA 91335",
    "addr:housenumber":"18227",
    "addr:postcode":"91335",
    "addr:street":"Jovan St",
    "iso:country":"US",
    "sg:address":"18227 Jovan St",
    "sg:city":"Tarzana",
    "sg:classifiers":[
        {
            "category":"Manufacturing",
            "subcategory":"Buildings",
            "type":"Manufacturing & Wholesale Goods"
        }
    ],
    "sg:phone":"+1 818 342 4175",
    "sg:postcode":"91335",
    "sg:province":"CA",
    "sg:tags":[
        "prefab"
    ],
    "wof:name":"Castlerock Manufactured Homes",
    "wof:placetype":"venue"
},
  "geometry": {"coordinates":[-118.531223,34.183048],"type":"Point"}
}