{
  "type": "Feature",
  "properties": {
    "addr:full":"26041 Cape Dr Laguna Niguel CA 92677",
    "addr:housenumber":"26041",
    "addr:postcode":"92677",
    "addr:street":"Cape Dr",
    "iso:country":"US",
    "sg:address":"26041 Cape Dr",
    "sg:city":"Laguna Niguel",
    "sg:classifiers":[
        {
            "category":"Building & Trades",
            "subcategory":"Electrical",
            "type":"Services"
        }
    ],
    "sg:phone":"+1 949 582 5624",
    "sg:postcode":"92677",
    "sg:province":"CA",
    "sg:tags":[
        "electrical",
        "contractor"
    ],
    "wof:name":"Powerlite Electric",
    "wof:placetype":"venue"
},
  "geometry": {"coordinates":[-117.676237,33.559538],"type":"Point"}
}