{
  "type": "Feature",
  "properties": {
    "iso:country":"US",
    "sg:address":"1330 30th St",
    "sg:city":"San Diego",
    "sg:classifiers":[
        {
            "category":"Retail",
            "subcategory":"Repair Shop",
            "type":"Services"
        }
    ],
    "sg:phone":"+1 619 424 3225",
    "sg:postcode":"92154",
    "sg:province":"CA",
    "sg:tags":[
        "repairing",
        "equipment",
        "electric"
    ],
    "sg:website":"www.qedsysinc.com",
    "wof:name":"QED Systems Inc",
    "wof:placetype":"venue"
},
  "geometry": {"coordinates":[-117.067046,32.571042],"type":"Point"}
}