{
  "type": "Feature",
  "properties": {
    "iso:country":"US",
    "sg:address":"251 Lincoln Blvd",
    "sg:city":"Venice",
    "sg:classifiers":[
        {
            "category":"Autos & Motor Vehicles",
            "subcategory":"Fuel & Gas Station",
            "type":"Retail Goods"
        }
    ],
    "sg:phone":"+1 310 392 3619",
    "sg:postcode":"90291",
    "sg:province":"CA",
    "sg:tags":[
        "oil"
    ],
    "wof:name":"Lincoln & Rose Gas Station",
    "wof:placetype":"venue"
},
  "geometry": {"coordinates":[-118.46829099999999,34.001507],"type":"Point"}
}