{
  "type": "Feature",
  "properties": {
    "iso:country":"US",
    "sg:address":"1257 Camino Del Rio S",
    "sg:city":"San Diego",
    "sg:classifiers":[
        {
            "category":"Personal",
            "subcategory":"Skin Care",
            "type":"Services"
        },
        {
            "category":"Personal",
            "subcategory":"Nail Salon",
            "type":"Services"
        }
    ],
    "sg:phone":"+1 619 297 1663",
    "sg:postcode":"92108",
    "sg:province":"CA",
    "wof:name":"Beau Monde Salon",
    "wof:placetype":"venue"
},
  "geometry": {"coordinates":[-117.152,32.765701],"type":"Point"}
}