{
  "type": "Feature",
  "properties": {
    "addr:full":"425 Orchard View Ave Martinez CA 94553",
    "addr:housenumber":"425",
    "addr:postcode":"94553",
    "addr:street":"Orchard View Ave",
    "iso:country":"US",
    "sg:address":"425 Orchard View Ave",
    "sg:city":"Martinez",
    "sg:classifiers":[
        {
            "category":"Retail",
            "subcategory":"Auto Repair",
            "type":"Services"
        }
    ],
    "sg:phone":"+1 925 457 2995",
    "sg:postcode":"94553",
    "sg:province":"CA",
    "sg:tags":[
        "truck"
    ],
    "wof:name":"Nor-Cal Lift Truck Repairs",
    "wof:placetype":"venue"
},
  "geometry": {"coordinates":[-122.111305,38.000006],"type":"Point"}
}