{
  "type": "Feature",
  "properties": {
    "iso:country":"US",
    "sg:address":"2717 Pierpont Blvd",
    "sg:city":"Ventura",
    "sg:classifiers":[
        {
            "category":"Manufacturing",
            "subcategory":"Toys & Sporting Goods",
            "type":"Manufacturing & Wholesale Goods"
        }
    ],
    "sg:phone":"+1 805 643 0943",
    "sg:postcode":"93001",
    "sg:province":"CA",
    "sg:tags":[
        "athletic"
    ],
    "wof:name":"Streetfish Longboard Co",
    "wof:placetype":"venue"
},
  "geometry": {"coordinates":[-119.268036,34.257364],"type":"Point"}
}