{
  "type": "Feature",
  "properties": {
    "addr:full":"397 Florin Rd Sacramento CA 95831",
    "addr:housenumber":"397",
    "addr:postcode":"95831",
    "addr:street":"Florin Rd",
    "iso:country":"US",
    "sg:address":"397 Florin Rd",
    "sg:city":"Sacramento",
    "sg:classifiers":[
        {
            "category":"Organizations",
            "subcategory":"Religious Organization",
            "type":"Services"
        }
    ],
    "sg:phone":"+1 916 391 2579",
    "sg:postcode":"95831",
    "sg:province":"CA",
    "sg:tags":[
        "church"
    ],
    "wof:name":"Women Talk It Out Issue Mnstry",
    "wof:placetype":"venue"
},
  "geometry": {"coordinates":[-121.54149200000001,38.508113],"type":"Point"}
}