{
  "type": "Feature",
  "properties": {
    "iso:country":"US",
    "sg:address":"9 California St",
    "sg:city":"Valley Springs",
    "sg:classifiers":[
        {
            "category":"Restaurant",
            "type":"Food & Drink"
        }
    ],
    "sg:phone":"+1 209 772 0888",
    "sg:postcode":"95252",
    "sg:province":"CA",
    "wof:name":"Good Friends Chinese Rstrnt",
    "wof:placetype":"venue"
},
  "geometry": {"coordinates":[-120.827529,38.193267],"type":"Point"}
}