{
  "type": "Feature",
  "properties": {
    "iso:country":"US",
    "sg:address":"15729 Youngwood Dr",
    "sg:city":"Whittier",
    "sg:classifiers":[
        {
            "category":"Retail",
            "subcategory":"Laundry & Dry Cleaning",
            "type":"Services"
        },
        {
            "category":"Building & Trades",
            "subcategory":"Cleaning & Sanitation",
            "type":"Services"
        }
    ],
    "sg:phone":"+1 562 458 9901",
    "sg:postcode":"90603",
    "sg:province":"CA",
    "sg:tags":[
        "cleaner",
        "house"
    ],
    "wof:name":"C W Cleaning Services",
    "wof:placetype":"venue"
},
  "geometry": {"coordinates":[-117.991463,33.95612],"type":"Point"}
}