{
  "type": "Feature",
  "properties": {
    "iso:country":"US",
    "sg:address":"1190 MacDonald Ave Ste E",
    "sg:city":"Richmond",
    "sg:classifiers":[
        {
            "category":"Banks & Credit Unions",
            "subcategory":"Financial Services",
            "type":"Services"
        }
    ],
    "sg:phone":"+1 510 235 0175",
    "sg:postcode":"94801",
    "sg:province":"CA",
    "sg:tags":[
        "cashing",
        "loan",
        "check"
    ],
    "sg:website":"www.checkcenters.com",
    "wof:name":"Check Center",
    "wof:placetype":"venue"
},
  "geometry": {"coordinates":[-122.35819100000001,37.935662],"type":"Point"}
}