{
  "type": "Feature",
  "properties": {
    "addr:full":"710 14th St San Francisco CA 94114",
    "addr:housenumber":"710",
    "addr:postcode":"94114",
    "addr:street":"14Th St",
    "iso:country":"US",
    "sg:address":"710 14th St",
    "sg:city":"San Francisco",
    "sg:classifiers":[
        {
            "category":"Travel",
            "subcategory":"Hotels & Motels",
            "type":"Entertainment"
        },
        {
            "category":"Travel",
            "subcategory":"Bed & Breakfast",
            "type":"Entertainment"
        }
    ],
    "sg:phone":"+1 415 431 4770",
    "sg:postcode":"94114",
    "sg:province":"CA",
    "sg:tags":[
        "house",
        "guest"
    ],
    "sg:website":"www.willowssf.com/",
    "wof:name":"Willows Inn",
    "wof:placetype":"venue"
},
  "geometry": {"coordinates":[-122.42923500000001,37.767733],"type":"Point"}
}