{
  "type": "Feature",
  "properties": {
    "addr:full":"265 N 1st St San Jose CA 95113",
    "addr:housenumber":"265",
    "addr:postcode":"95113",
    "addr:street":"N 1St St",
    "iso:country":"US",
    "sg:address":"265 N 1st St",
    "sg:city":"San Jose",
    "sg:classifiers":[
        {
            "category":"Bars & Pubs",
            "type":"Food & Drink"
        }
    ],
    "sg:phone":"+1 408 947 0497",
    "sg:postcode":"95113",
    "sg:province":"CA",
    "sg:website":"www.trialspub.com",
    "wof:name":"Trials Pub",
    "wof:placetype":"venue"
},
  "geometry": {"coordinates":[-121.89344199999999,37.339994],"type":"Point"}
}