{
  "type": "Feature",
  "properties": {
    "addr:full":"3315 E Florence Ave Huntington Park CA 90255",
    "addr:housenumber":"3315",
    "addr:postcode":"90255",
    "addr:street":"E Florence Ave;Park",
    "iso:country":"US",
    "sg:address":"3315 E Florence Ave",
    "sg:city":"Huntington Park",
    "sg:classifiers":[
        {
            "category":"Retail",
            "subcategory":"Auto Repair",
            "type":"Services"
        }
    ],
    "sg:phone":"+1 323 583 5900",
    "sg:postcode":"90255",
    "sg:province":"CA",
    "sg:tags":[
        "repairing",
        "automobile",
        "radiator"
    ],
    "wof:name":"Eagle Radiator Svc",
    "wof:placetype":"venue"
},
  "geometry": {"coordinates":[-118.20532300000001,33.972218],"type":"Point"}
}