{
  "type": "Feature",
  "properties": {
    "addr:full":"3605 Hillview Dr Riverside CA 92503",
    "addr:housenumber":"3605",
    "addr:postcode":"92503",
    "addr:street":"Hillview Dr",
    "iso:country":"US",
    "sg:address":"3605 Hillview Dr",
    "sg:city":"Riverside",
    "sg:classifiers":[
        {
            "category":"Retail",
            "subcategory":"Laundry & Dry Cleaning",
            "type":"Services"
        }
    ],
    "sg:phone":"+1 951 735 3058",
    "sg:postcode":"92503",
    "sg:province":"CA",
    "sg:tags":[
        "cleaners",
        "rug",
        "carpet"
    ],
    "wof:name":"Carpet Jenny",
    "wof:placetype":"venue"
},
  "geometry": {"coordinates":[-117.49964,33.884807],"type":"Point"}
}