{
  "type": "Feature",
  "properties": {
    "iso:country":"US",
    "sg:address":"23276 S Pointe Dr",
    "sg:city":"Laguna Hills",
    "sg:classifiers":[
        {
            "category":"Wholesale",
            "subcategory":"Construction Materials",
            "type":"Manufacturing & Wholesale Goods"
        }
    ],
    "sg:phone":"+1 949 454 8010",
    "sg:postcode":"92653",
    "sg:province":"CA",
    "wof:name":"North Pacific Group Inc",
    "wof:placetype":"venue"
},
  "geometry": {"coordinates":[-117.724446,33.625616],"type":"Point"}
}