{
  "type": "Feature",
  "properties": {
    "iso:country":"US",
    "sg:address":"18803 Studebaker Rd",
    "sg:city":"Cerritos",
    "sg:classifiers":[
        {
            "category":"Autos & Motor Vehicles",
            "subcategory":"Automobile Sales",
            "type":"Retail Goods"
        },
        {
            "category":"Retail",
            "subcategory":"Auto Repair",
            "type":"Services"
        }
    ],
    "sg:phone":"+1 888 203 2095",
    "sg:postcode":"90703",
    "sg:province":"CA",
    "sg:tags":[
        "body",
        "used",
        "car",
        "truck",
        "new",
        "painting",
        "repairing"
    ],
    "sg:website":"http://www.cerritosdodge.com",
    "wof:name":"Cerritos Dodge Chrysler Jeep",
    "wof:placetype":"venue"
},
  "geometry": {"coordinates":[-118.099701,33.860745],"type":"Point"}
}