{
  "type": "Feature",
  "properties": {
    "iso:country":"US",
    "sg:address":"61 E Main St # A",
    "sg:city":"Los Gatos",
    "sg:classifiers":[
        {
            "category":"Professional",
            "subcategory":"Lawyer & Legal Services",
            "type":"Services"
        }
    ],
    "sg:phone":"+1 408 395 6021",
    "sg:postcode":"95030",
    "sg:province":"CA",
    "wof:name":"Toothman James E & Assn",
    "wof:placetype":"venue"
},
  "geometry": {"coordinates":[-121.980003,37.2215],"type":"Point"}
}