{
  "type": "Feature",
  "properties": {
    "iso:country":"US",
    "sg:address":"1125 Northcrest Dr",
    "sg:city":"Crescent City",
    "sg:classifiers":[
        {
            "category":"Retail",
            "subcategory":"Auto Repair",
            "type":"Services"
        }
    ],
    "sg:phone":"+1 707 464 5903",
    "sg:postcode":"95531",
    "sg:province":"CA",
    "sg:tags":[
        "wrecker"
    ],
    "wof:name":"Budget Towing",
    "wof:placetype":"venue"
},
  "geometry": {"coordinates":[-124.199067,41.768921],"type":"Point"}
}