{
  "type": "Feature",
  "properties": {
    "addr:full":"652 N Doheny Dr West Hollywood CA 90069",
    "addr:housenumber":"652",
    "addr:postcode":"90069",
    "addr:street":"N Doheny Dr",
    "iso:country":"US",
    "sg:address":"652 N Doheny Dr",
    "sg:city":"West Hollywood",
    "sg:classifiers":[
        {
            "category":"Shopping",
            "subcategory":"Musical Instruments",
            "type":"Retail Goods"
        }
    ],
    "sg:phone":"+1 323 939 6200",
    "sg:postcode":"90069",
    "sg:province":"CA",
    "wof:name":"Skizzneck Music",
    "wof:placetype":"venue"
},
  "geometry": {"coordinates":[-118.389667,34.082764],"type":"Point"}
}