{
  "type": "Feature",
  "properties": {
    "addr:full":"2411 E Valley Pkwy Escondido CA 92027",
    "addr:housenumber":"2411",
    "addr:postcode":"92027",
    "addr:street":"E Valley Pkwy",
    "iso:country":"US",
    "sg:address":"2411 E Valley Pkwy",
    "sg:city":"Escondido",
    "sg:classifiers":[
        {
            "category":"Building & Trades",
            "subcategory":"Plumbing",
            "type":"Services"
        }
    ],
    "sg:phone":"+1 760 747 3689",
    "sg:postcode":"92027",
    "sg:province":"CA",
    "sg:tags":[
        "contractor"
    ],
    "wof:name":"Cabrillo AC & Htg",
    "wof:placetype":"venue"
},
  "geometry": {"coordinates":[-117.04380500000001,33.141104],"type":"Point"}
}