{
  "type": "Feature",
  "properties": {
    "iso:country":"US",
    "sg:address":"16982 San Bernardino Ave",
    "sg:city":"Fontana",
    "sg:classifiers":[
        {
            "category":"Real Estate",
            "subcategory":"Real Estate Operator",
            "type":"Services"
        }
    ],
    "sg:phone":"+1 909 428 0662",
    "sg:postcode":"92335",
    "sg:province":"CA",
    "sg:tags":[
        "apartment"
    ],
    "wof:name":"Acacia Gardens Apartments Inc",
    "wof:placetype":"venue"
},
  "geometry": {"coordinates":[-117.435322,34.07767],"type":"Point"}
}