{
  "type": "Feature",
  "properties": {
    "iso:country":"US",
    "sg:address":"70 Manor Dr",
    "sg:city":"San Francisco",
    "sg:classifiers":[
        {
            "category":"Manufacturing",
            "subcategory":"Apparel",
            "type":"Manufacturing & Wholesale Goods"
        }
    ],
    "sg:phone":"+1 415 584 5525",
    "sg:postcode":"94127",
    "sg:province":"CA",
    "sg:tags":[
        "mfg"
    ],
    "wof:name":"Dance Sport Image",
    "wof:placetype":"venue"
},
  "geometry": {"coordinates":[-122.46469999999999,37.726908],"type":"Point"}
}