{
  "type": "Feature",
  "properties": {
    "addr:full":"1613 Fulton St Fresno CA 93721",
    "addr:housenumber":"1613",
    "addr:postcode":"93721",
    "addr:street":"Fulton St",
    "iso:country":"US",
    "sg:address":"1613 Fulton St",
    "sg:city":"Fresno",
    "sg:classifiers":[
        {
            "category":"Building & Trades",
            "subcategory":"Landscaping Services",
            "type":"Services"
        }
    ],
    "sg:phone":"+1 559 266 4367",
    "sg:postcode":"93721",
    "sg:province":"CA",
    "sg:tags":[
        "designer",
        "landscape"
    ],
    "wof:name":"Robert Boro Landscape Arch",
    "wof:placetype":"venue"
},
  "geometry": {"coordinates":[-119.797707,36.74067],"type":"Point"}
}