{
  "type": "Feature",
  "properties": {
    "addr:full":"1333 E St Ramona CA 92065",
    "addr:housenumber":"1333",
    "addr:postcode":"92065",
    "addr:street":"E St",
    "iso:country":"US",
    "sg:address":"1333 E St",
    "sg:city":"Ramona",
    "sg:classifiers":[
        {
            "category":"Shopping",
            "type":"Retail Goods"
        }
    ],
    "sg:phone":"+1 760 789 0277",
    "sg:postcode":"92065",
    "sg:province":"CA",
    "sg:tags":[
        "merchandise"
    ],
    "wof:name":"G & H Bird Box Designs",
    "wof:placetype":"venue"
},
  "geometry": {"coordinates":[-116.872517,33.037359],"type":"Point"}
}