{
  "type": "Feature",
  "properties": {
    "iso:country":"US",
    "sg:address":"21380 Mann Rd",
    "sg:city":"Acampo",
    "sg:classifiers":[
        {
            "category":"Real Estate",
            "subcategory":"Real Estate Agent",
            "type":"Services"
        }
    ],
    "sg:phone":"+1 209 365 7906",
    "sg:postcode":"95220",
    "sg:province":"CA",
    "wof:name":"Duncan Commercial Properties",
    "wof:placetype":"venue"
},
  "geometry": {"coordinates":[-121.214921,38.17764],"type":"Point"}
}