{
  "type": "Feature",
  "properties": {
    "addr:full":"913 E California Blvd Pasadena CA 91106",
    "addr:housenumber":"913",
    "addr:postcode":"91106",
    "addr:street":"E California Blvd",
    "iso:country":"US",
    "sg:address":"913 E California Blvd",
    "sg:city":"Pasadena",
    "sg:classifiers":[
        {
            "category":"Restaurant",
            "type":"Food & Drink"
        }
    ],
    "sg:phone":"+1 626 795 1123",
    "sg:postcode":"91106",
    "sg:province":"CA",
    "sg:tags":[
        "dessert"
    ],
    "sg:website":"www.pienburger.com",
    "wof:name":"Pie 'n Burger",
    "wof:placetype":"venue"
},
  "geometry": {"coordinates":[-118.13200399999999,34.136002],"type":"Point"}
}