{
  "type": "Feature",
  "properties": {
    "iso:country":"US",
    "sg:address":"8160 Belvedere Ave",
    "sg:city":"Sacramento",
    "sg:classifiers":[
        {
            "category":"Wholesale",
            "subcategory":"Groceries",
            "type":"Manufacturing & Wholesale Goods"
        }
    ],
    "sg:phone":"+1 916 457 8283",
    "sg:postcode":"95826",
    "sg:province":"CA",
    "wof:name":"P H Ingredients",
    "wof:placetype":"venue"
},
  "geometry": {"coordinates":[-121.406628,38.537843],"type":"Point"}
}