{
  "type": "Feature",
  "properties": {
    "addr:full":"419 N Fairview St Santa Ana CA 92703",
    "addr:housenumber":"419",
    "addr:postcode":"92703",
    "addr:street":"N Fairview St",
    "iso:country":"US",
    "sg:address":"419 N Fairview St",
    "sg:city":"Santa Ana",
    "sg:classifiers":[
        {
            "category":"Restaurant",
            "type":"Food & Drink"
        }
    ],
    "sg:phone":"+1 714 558 8907",
    "sg:postcode":"92703",
    "sg:province":"CA",
    "wof:name":"Fairview Char-Broiler",
    "wof:placetype":"venue"
},
  "geometry": {"coordinates":[-117.904999,33.748402],"type":"Point"}
}