{
  "type": "Feature",
  "properties": {
    "iso:country":"US",
    "sg:address":"6431 Independence Ave",
    "sg:city":"Woodland Hills",
    "sg:classifiers":[
        {
            "category":"Communications",
            "subcategory":"Television Station",
            "type":"Services"
        }
    ],
    "sg:phone":"+1 818 348 2899",
    "sg:postcode":"91367",
    "sg:province":"CA",
    "wof:name":"Iran Tv Network",
    "wof:placetype":"venue"
},
  "geometry": {"coordinates":[-118.591003,34.187302],"type":"Point"}
}