{
  "type": "Feature",
  "properties": {
    "addr:full":"2677 E 26th St Los Angeles CA 90058",
    "addr:housenumber":"2677",
    "addr:postcode":"90058",
    "addr:street":"E 26Th St",
    "iso:country":"US",
    "sg:address":"2677 E 26th St",
    "sg:city":"Los Angeles",
    "sg:classifiers":[
        {
            "category":"Wholesale",
            "subcategory":"Chemicals & Plastics",
            "type":"Manufacturing & Wholesale Goods"
        },
        {
            "category":"Wholesale",
            "subcategory":"Scrap",
            "type":"Manufacturing & Wholesale Goods"
        }
    ],
    "sg:phone":"+1 323 582 4360",
    "sg:postcode":"90058",
    "sg:province":"CA",
    "sg:tags":[
        "refuse",
        "system"
    ],
    "wof:name":"Al's Plastics",
    "wof:placetype":"venue"
},
  "geometry": {"coordinates":[-118.224925,34.014421],"type":"Point"}
}