{
  "type": "Feature",
  "properties": {
    "iso:country":"US",
    "sg:address":"1999 S Bascom Ave",
    "sg:city":"Campbell",
    "sg:classifiers":[
        {
            "category":"Professional",
            "subcategory":"Lawyer & Legal Services",
            "type":"Services"
        }
    ],
    "sg:phone":"+1 408 626 9887",
    "sg:postcode":"95008",
    "sg:province":"CA",
    "wof:name":"Hofherr Hal Attorney",
    "wof:placetype":"venue"
},
  "geometry": {"coordinates":[-121.931999,37.286598],"type":"Point"}
}