{
  "type": "Feature",
  "properties": {
    "iso:country":"US",
    "sg:address":"1589 Live Oak Rd",
    "sg:city":"Vista",
    "sg:classifiers":[
        {
            "category":"Building & Trades",
            "subcategory":"Construction",
            "type":"Services"
        }
    ],
    "sg:phone":"+1 760 598 1638",
    "sg:postcode":"92081",
    "sg:province":"CA",
    "sg:tags":[
        "contractor"
    ],
    "wof:name":"Sokol Demolition Co",
    "wof:placetype":"venue"
},
  "geometry": {"coordinates":[-117.239081,33.168792],"type":"Point"}
}