{
  "type": "Feature",
  "properties": {
    "iso:country":"US",
    "sg:address":"754 Miller Avenue",
    "sg:city":"Cupertino",
    "sg:classifiers":[
        {
            "category":"Personal",
            "subcategory":"Hair Removal",
            "type":"Services"
        },
        {
            "category":"Personal",
            "subcategory":"Skin Care",
            "type":"Services"
        }
    ],
    "sg:phone":"+1 408 316 5840",
    "sg:postcode":"95014",
    "sg:province":"CA",
    "wof:name":"Saz's Beauty Service",
    "wof:placetype":"venue"
},
  "geometry": {"coordinates":[-122.01298199999999,37.314647],"type":"Point"}
}