{
  "type": "Feature",
  "properties": {
    "addr:full":"1417 San Andres St Santa Barbara CA 93101",
    "addr:housenumber":"1417",
    "addr:postcode":"93101",
    "addr:street":"San Andres St",
    "iso:country":"US",
    "sg:address":"1417 San Andres St",
    "sg:city":"Santa Barbara",
    "sg:classifiers":[
        {
            "category":"Restaurant",
            "type":"Food & Drink"
        }
    ],
    "sg:phone":"+1 805 899 1229",
    "sg:postcode":"93101",
    "sg:province":"CA",
    "wof:name":"Su Casa Fresh Mexican Grill",
    "wof:placetype":"venue"
},
  "geometry": {"coordinates":[-119.716189,34.418687],"type":"Point"}
}