{
  "type": "Feature",
  "properties": {
    "iso:country":"US",
    "sg:address":"1417 San Andres St",
    "sg:city":"Santa Barbara",
    "sg:classifiers":[
        {
            "category":"Restaurant",
            "type":"Food & Drink"
        }
    ],
    "sg:phone":"+1 805 899 1229",
    "sg:postcode":"93101",
    "sg:province":"CA",
    "wof:name":"Su Casa Fresh Mexican Grill",
    "wof:placetype":"venue"
},
  "geometry": {"coordinates":[-119.716189,34.418687],"type":"Point"}
}