{
  "type": "Feature",
  "properties": {
    "addr:full":"903 W Murray Ave Visalia CA 93291",
    "addr:housenumber":"903",
    "addr:postcode":"93291",
    "addr:street":"W Murray Ave",
    "iso:country":"US",
    "sg:address":"903 W Murray Ave",
    "sg:city":"Visalia",
    "sg:classifiers":[
        {
            "category":"Professional",
            "type":"Services"
        }
    ],
    "sg:phone":"+1 559 739 8665",
    "sg:postcode":"93291",
    "sg:province":"CA",
    "sg:tags":[
        "establishment"
    ],
    "wof:name":"Specialized Environments",
    "wof:placetype":"venue"
},
  "geometry": {"coordinates":[-119.30218600000001,36.333654],"type":"Point"}
}