{
  "type": "Feature",
  "properties": {
    "iso:country":"US",
    "sg:address":"5408 College Ave",
    "sg:city":"Oakland",
    "sg:classifiers":[
        {
            "category":"Personal",
            "subcategory":"Beauty Salon",
            "type":"Services"
        }
    ],
    "sg:phone":"+1 510 658 7299",
    "sg:postcode":"94620",
    "sg:province":"CA",
    "sg:tags":[
        "hair"
    ],
    "wof:name":"Bing's Salon",
    "wof:placetype":"venue"
},
  "geometry": {"coordinates":[-122.251363,37.840311],"type":"Point"}
}