{
  "type": "Feature",
  "properties": {
    "iso:country":"US",
    "sg:address":"1602 Grant Ave Ste 210",
    "sg:city":"Novato",
    "sg:classifiers":[
        {
            "category":"Personal",
            "subcategory":"Beauty Salon",
            "type":"Services"
        }
    ],
    "sg:phone":"+1 415 897 2686",
    "sg:postcode":"94945",
    "sg:province":"CA",
    "wof:name":"Katie Silkworth Hair Stylist",
    "wof:placetype":"venue"
},
  "geometry": {"coordinates":[-122.577112,38.108945],"type":"Point"}
}