{
  "type": "Feature",
  "properties": {
    "addr:full":"13063 Mustang St Victorville CA 92394",
    "addr:housenumber":"13063",
    "addr:postcode":"92394",
    "addr:street":"Mustang St",
    "iso:country":"US",
    "sg:address":"13063 Mustang St",
    "sg:city":"Victorville",
    "sg:classifiers":[
        {
            "category":"Local Transit",
            "type":"Transportation"
        }
    ],
    "sg:phone":"+1 760 246 5033",
    "sg:postcode":"92394",
    "sg:province":"CA",
    "wof:name":"Aartman Transportation",
    "wof:placetype":"venue"
},
  "geometry": {"coordinates":[-117.37599400000001,34.580901],"type":"Point"}
}