{
  "type": "Feature",
  "properties": {
    "iso:country":"US",
    "sg:address":"6418 Whittier Blvd",
    "sg:city":"Los Angeles",
    "sg:classifiers":[
        {
            "category":"Home & Garden",
            "subcategory":"Household Appliances",
            "type":"Retail Goods"
        }
    ],
    "sg:phone":"+1 323 724 8125",
    "sg:postcode":"90022",
    "sg:province":"CA",
    "sg:tags":[
        "cleaners",
        "vacuum"
    ],
    "wof:name":"R & J Opporunity",
    "wof:placetype":"venue"
},
  "geometry": {"coordinates":[-118.13412700000001,34.015467],"type":"Point"}
}