{
  "type": "Feature",
  "properties": {
    "iso:country":"US",
    "sg:address":"6566 Vanalden Ave",
    "sg:city":"Reseda",
    "sg:classifiers":[
        {
            "category":"Retail",
            "subcategory":"Laundry & Dry Cleaning",
            "type":"Services"
        }
    ],
    "sg:phone":"+1 818 705 6633",
    "sg:postcode":"91335",
    "sg:province":"CA",
    "sg:tags":[
        "cleaners",
        "rug",
        "carpet"
    ],
    "wof:name":"Ultra Clean Carpet & Upholstry",
    "wof:placetype":"venue"
},
  "geometry": {"coordinates":[-118.549126,34.190208],"type":"Point"}
}