{
  "type": "Feature",
  "properties": {
    "addr:full":"9102 Youngdale St San Gabriel CA 91775",
    "addr:housenumber":"9102",
    "addr:postcode":"91775",
    "addr:street":"Youngdale St",
    "iso:country":"US",
    "sg:address":"9102 Youngdale St",
    "sg:city":"San Gabriel",
    "sg:classifiers":[
        {
            "category":"Building & Trades",
            "subcategory":"Construction",
            "type":"Services"
        }
    ],
    "sg:phone":"+1 626 287 0576",
    "sg:postcode":"91775",
    "sg:province":"CA",
    "sg:tags":[
        "remodeling",
        "contractor"
    ],
    "wof:name":"Brummett & Demblon Inc",
    "wof:placetype":"venue"
},
  "geometry": {"coordinates":[-118.069321,34.121799],"type":"Point"}
}