{
  "type": "Feature",
  "properties": {
    "iso:country":"US",
    "sg:address":"1710 E 29th St",
    "sg:city":"Long Beach",
    "sg:classifiers":[
        {
            "category":"Freight",
            "type":"Transportation"
        }
    ],
    "sg:phone":"+1 562 988 7667",
    "sg:postcode":"90755",
    "sg:province":"CA",
    "sg:tags":[
        "interstate",
        "trucking"
    ],
    "wof:name":"System Transport",
    "wof:placetype":"venue"
},
  "geometry": {"coordinates":[-118.170767,33.809756],"type":"Point"}
}