{
  "type": "Feature",
  "properties": {
    "addr:full":"3825 W 6th St Los Angeles CA 90020",
    "addr:housenumber":"3825",
    "addr:postcode":"90020",
    "addr:street":"W 6Th St",
    "iso:country":"US",
    "sg:address":"3825 W 6th St",
    "sg:city":"Los Angeles",
    "sg:classifiers":[
        {
            "category":"Shopping",
            "subcategory":"Department Store",
            "type":"Retail Goods"
        }
    ],
    "sg:phone":"+1 213 385 2452",
    "sg:postcode":"90020",
    "sg:province":"CA",
    "sg:tags":[
        "shop"
    ],
    "wof:name":"Musicomline",
    "wof:placetype":"venue"
},
  "geometry": {"coordinates":[-118.305352,34.063538],"type":"Point"}
}