{
  "type": "Feature",
  "properties": {
    "addr:full":"6940 Sebastopol Ave Sebastopol CA 95472",
    "addr:housenumber":"6940",
    "addr:postcode":"95472",
    "addr:street":"Sebastopol Ave",
    "iso:country":"US",
    "sg:address":"6940 Sebastopol Ave",
    "sg:city":"Sebastopol",
    "sg:classifiers":[
        {
            "category":"Shopping",
            "subcategory":"Hobbies, Toys, & Games",
            "type":"Retail Goods"
        }
    ],
    "sg:phone":"+1 707 829 2003",
    "sg:postcode":"95472",
    "sg:province":"CA",
    "wof:name":"Toyworks",
    "wof:placetype":"venue"
},
  "geometry": {"coordinates":[-122.823148,38.4025],"type":"Point"}
}