{
  "type": "Feature",
  "properties": {
    "addr:full":"1731 S Cactus Ave Bloomington CA 92376",
    "addr:housenumber":"1731",
    "addr:postcode":"92376",
    "addr:street":"S Cactus Ave",
    "iso:country":"US",
    "sg:address":"1731 S Cactus Ave",
    "sg:city":"Bloomington",
    "sg:classifiers":[
        {
            "category":"Retail",
            "subcategory":"Auto Repair",
            "type":"Services"
        }
    ],
    "sg:phone":"+1 909 877 9636",
    "sg:postcode":"92376",
    "sg:province":"CA",
    "sg:tags":[
        "repairing",
        "automobile"
    ],
    "wof:name":"Inland Empire Automobile",
    "wof:placetype":"venue"
},
  "geometry": {"coordinates":[-117.38337,34.068941],"type":"Point"}
}