{
  "type": "Feature",
  "properties": {
    "addr:full":"16718 Farley Road Los Gatos CA 95032",
    "addr:housenumber":"16718",
    "addr:postcode":"95032",
    "addr:street":"Farley Road",
    "iso:country":"US",
    "sg:address":"16718 Farley Road",
    "sg:city":"Los Gatos",
    "sg:classifiers":[
        {
            "category":"Building & Trades",
            "subcategory":"Plumbing",
            "type":"Services"
        }
    ],
    "sg:phone":"+1 408 358 0404",
    "sg:postcode":"95032",
    "sg:province":"CA",
    "wof:name":"Elite Plumbing",
    "wof:placetype":"venue"
},
  "geometry": {"coordinates":[-121.96151500000001,37.239254],"type":"Point"}
}