{
  "type": "Feature",
  "properties": {
    "addr:full":"29229 Canwood St Ste 105 Agoura Hills CA 91301",
    "addr:housenumber":"29229",
    "addr:postcode":"91301",
    "addr:street":"Canwood St Ste 105",
    "iso:country":"US",
    "sg:address":"29229 Canwood St Ste 105",
    "sg:city":"Agoura Hills",
    "sg:classifiers":[
        {
            "category":"Building & Trades",
            "subcategory":"Construction",
            "type":"Services"
        }
    ],
    "sg:phone":"+1 818 707 1908",
    "sg:postcode":"91301",
    "sg:province":"CA",
    "sg:tags":[
        "interior",
        "design"
    ],
    "wof:name":"Bitton Design Group",
    "wof:placetype":"venue"
},
  "geometry": {"coordinates":[-118.760002,34.146599],"type":"Point"}
}