{
  "type": "Feature",
  "properties": {
    "iso:country":"US",
    "sg:address":"4879 Jadestone Ave",
    "sg:city":"San Bernardino",
    "sg:classifiers":[
        {
            "category":"Wholesale",
            "subcategory":"Office Equipment",
            "type":"Manufacturing & Wholesale Goods"
        }
    ],
    "sg:phone":"+1 909 473 3070",
    "sg:postcode":"92407",
    "sg:province":"CA",
    "wof:name":"Az Tech Office Solutions",
    "wof:placetype":"venue"
},
  "geometry": {"coordinates":[-117.349977,34.171667],"type":"Point"}
}