{
  "type": "Feature",
  "properties": {
    "addr:full":"13509 Ramona Ave Chino CA 91710",
    "addr:housenumber":"13509",
    "addr:postcode":"91710",
    "addr:street":"Ramona Ave",
    "iso:country":"US",
    "sg:address":"13509 Ramona Ave",
    "sg:city":"Chino",
    "sg:classifiers":[
        {
            "category":"Education",
            "subcategory":"School",
            "type":"Public Place"
        }
    ],
    "sg:phone":"+1 909 628 9903",
    "sg:postcode":"91710",
    "sg:province":"CA",
    "wof:name":"Buena Vista Cont High School",
    "wof:placetype":"venue"
},
  "geometry": {"coordinates":[-117.70662400000001,34.008217],"type":"Point"}
}