{
  "type": "Feature",
  "properties": {
    "addr:full":"839 International Ave Oakland CA 94606",
    "addr:housenumber":"839",
    "addr:postcode":"94606",
    "addr:street":"International Ave",
    "iso:country":"US",
    "sg:address":"839 International Ave",
    "sg:city":"Oakland",
    "sg:classifiers":[
        {
            "category":"Restaurant",
            "type":"Food & Drink"
        }
    ],
    "sg:phone":"+1 510 465 8892",
    "sg:postcode":"94606",
    "sg:province":"CA",
    "sg:tags":[
        "chinese",
        "vietnamese"
    ],
    "wof:name":"Minh Ky",
    "wof:placetype":"venue"
},
  "geometry": {"coordinates":[-122.25080699999999,37.793061],"type":"Point"}
}