{
  "type": "Feature",
  "properties": {
    "addr:full":"2395 Pleasant Hill Rd Pleasant Hill CA 94523",
    "addr:housenumber":"2395",
    "addr:postcode":"94523",
    "addr:street":"Pleasant Hill Rd",
    "iso:country":"US",
    "sg:address":"2395 Pleasant Hill Rd",
    "sg:city":"Pleasant Hill",
    "sg:classifiers":[
        {
            "category":"Shopping",
            "subcategory":"Bicycles & Sporting Goods",
            "type":"Retail Goods"
        }
    ],
    "sg:phone":"+1 925 891 4294",
    "sg:postcode":"94523",
    "sg:province":"CA",
    "sg:website":"www.spauldingsports.com",
    "wof:name":"Spaulding Sports",
    "wof:placetype":"venue"
},
  "geometry": {"coordinates":[-122.25502400000001,37.947661],"type":"Point"}
}