{
  "type": "Feature",
  "properties": {
    "addr:full":"3787 E California Blvd Pasadena CA 91107",
    "addr:housenumber":"3787",
    "addr:postcode":"91107",
    "addr:street":"E California Blvd",
    "iso:country":"US",
    "sg:address":"3787 E California Blvd",
    "sg:city":"Pasadena",
    "sg:classifiers":[
        {
            "category":"Home & Garden",
            "subcategory":"Household Appliances",
            "type":"Retail Goods"
        }
    ],
    "sg:phone":"+1 626 577 7667",
    "sg:postcode":"91107",
    "sg:province":"CA",
    "sg:tags":[
        "repair"
    ],
    "sg:website":"www.aarapp.com",
    "wof:name":"AARAPP Appliance Repair Team",
    "wof:placetype":"venue"
},
  "geometry": {"coordinates":[-118.07135,34.134882],"type":"Point"}
}