{
  "type": "Feature",
  "properties": {
    "addr:full":"250 San Pedro Rd Daly City CA 94014",
    "addr:housenumber":"250",
    "addr:postcode":"94014",
    "addr:street":"San Pedro Rd",
    "iso:country":"US",
    "sg:address":"250 San Pedro Rd",
    "sg:city":"Daly City",
    "sg:classifiers":[
        {
            "category":"Retail",
            "subcategory":"Auto Repair",
            "type":"Services"
        }
    ],
    "sg:phone":"+1 650 755 1050",
    "sg:postcode":"94014",
    "sg:province":"CA",
    "sg:tags":[
        "repairing",
        "automobile"
    ],
    "wof:name":"Collision Specialists",
    "wof:placetype":"venue"
},
  "geometry": {"coordinates":[-122.469498,37.686918],"type":"Point"}
}