{
  "type": "Feature",
  "properties": {
    "iso:country":"US",
    "sg:address":"17655 Osbourne Ave",
    "sg:city":"Chino Hills",
    "sg:classifiers":[
        {
            "category":"Travel",
            "subcategory":"Travel Agent",
            "type":"Entertainment"
        }
    ],
    "sg:phone":"+1 909 597 4597",
    "sg:postcode":"91709",
    "sg:province":"CA",
    "sg:tags":[
        "agency"
    ],
    "wof:name":"Cruise One",
    "wof:placetype":"venue"
},
  "geometry": {"coordinates":[-117.671537,33.932706],"type":"Point"}
}