{
  "type": "Feature",
  "properties": {
    "addr:full":"886 S Norton Ave Los Angeles CA 90005",
    "addr:housenumber":"886",
    "addr:postcode":"90005",
    "addr:street":"S Norton Ave",
    "iso:country":"US",
    "sg:address":"886 S Norton Ave",
    "sg:city":"Los Angeles",
    "sg:classifiers":[
        {
            "category":"Shopping",
            "subcategory":"Antiques",
            "type":"Retail Goods"
        }
    ],
    "sg:phone":"+1 323 933 6835",
    "sg:postcode":"90005",
    "sg:province":"CA",
    "wof:name":"Dapa Llc Jean De Merry",
    "wof:placetype":"venue"
},
  "geometry": {"coordinates":[-118.31999999999999,34.056099],"type":"Point"}
}