{
  "type": "Feature",
  "properties": {
    "iso:country":"US",
    "sg:address":"8693 Venice Blvd",
    "sg:city":"Los Angeles",
    "sg:classifiers":[
        {
            "category":"Restaurant",
            "type":"Food & Drink"
        }
    ],
    "sg:postcode":"90034",
    "sg:province":"CA",
    "sg:tags":[
        "mexican"
    ],
    "sg:website":"www.tacosdonjorge.com/",
    "wof:name":"Tacos Don Jorge",
    "wof:placetype":"venue"
},
  "geometry": {"coordinates":[-118.382198,34.032902],"type":"Point"}
}