{
  "type": "Feature",
  "properties": {
    "iso:country":"US",
    "sg:address":"5870 Traffic Way",
    "sg:city":"Atascadero",
    "sg:classifiers":[
        {
            "category":"Personal",
            "subcategory":"Beauty Salon",
            "type":"Services"
        }
    ],
    "sg:phone":"+1 805 462 0636",
    "sg:postcode":"93422",
    "sg:province":"CA",
    "wof:name":"A Day Of Grace Facial & Body",
    "wof:placetype":"venue"
},
  "geometry": {"coordinates":[-120.669491,35.490737],"type":"Point"}
}