{
  "type": "Feature",
  "properties": {
    "addr:full":"747 W Wilson Ave Glendale CA 91203",
    "addr:housenumber":"747",
    "addr:postcode":"91203",
    "addr:street":"W Wilson Ave",
    "iso:country":"US",
    "sg:address":"747 W Wilson Ave",
    "sg:city":"Glendale",
    "sg:classifiers":[
        {
            "category":"Food & Beverages",
            "subcategory":"Specialty",
            "type":"Retail Goods"
        }
    ],
    "sg:phone":"+1 818 507 1527",
    "sg:postcode":"91203",
    "sg:province":"CA",
    "sg:website":"www.theperfectbiteco.com/",
    "wof:name":"The Perfect Bite Co.",
    "wof:placetype":"venue"
},
  "geometry": {"coordinates":[-118.271976,34.148147],"type":"Point"}
}