{
  "type": "Feature",
  "properties": {
    "iso:country":"US",
    "sg:address":"1430 Gold Rush Ct",
    "sg:city":"Oakdale",
    "sg:classifiers":[
        {
            "category":"Building & Trades",
            "subcategory":"Construction",
            "type":"Services"
        },
        {
            "category":"Home & Garden",
            "subcategory":"Carpets & Floor Coverings",
            "type":"Retail Goods"
        }
    ],
    "sg:phone":"+1 510 768 0389",
    "sg:postcode":"95361",
    "sg:province":"CA",
    "sg:tags":[
        "material",
        "specialty",
        "flooring",
        "contractor"
    ],
    "wof:name":"Kenneth G. Price Flooring Contractor",
    "wof:placetype":"venue"
},
  "geometry": {"coordinates":[-120.829662,37.765284],"type":"Point"}
}