{
  "type": "Feature",
  "properties": {
    "iso:country":"US",
    "sg:address":"PO Box 4041",
    "sg:city":"Modesto",
    "sg:classifiers":[
        {
            "category":"Banks & Credit Unions",
            "subcategory":"Financial Services",
            "type":"Services"
        }
    ],
    "sg:phone":"+1 209 523 5626",
    "sg:postcode":"95352",
    "sg:province":"CA",
    "sg:tags":[
        "broker",
        "mortgage"
    ],
    "wof:name":"Central California Financial Corporation",
    "wof:placetype":"venue"
},
  "geometry": {"coordinates":[-121.019997,37.656601],"type":"Point"}
}