{
  "type": "Feature",
  "properties": {
    "addr:full":"7225 Monterey St Gilroy CA 95020",
    "addr:housenumber":"7225",
    "addr:postcode":"95020",
    "addr:street":"Monterey St",
    "iso:country":"US",
    "sg:address":"7225 Monterey St",
    "sg:city":"Gilroy",
    "sg:classifiers":[
        {
            "category":"Retail",
            "subcategory":"Auto Repair",
            "type":"Services"
        }
    ],
    "sg:phone":"+1 408 847 7359",
    "sg:postcode":"95020",
    "sg:province":"CA",
    "sg:tags":[
        "repairing",
        "automobile"
    ],
    "wof:name":"Rom's Auto Svc",
    "wof:placetype":"venue"
},
  "geometry": {"coordinates":[-121.567269,37.003373],"type":"Point"}
}