{
  "type": "Feature",
  "properties": {
    "iso:country":"US",
    "sg:address":"81 Wright Brothers Ave",
    "sg:city":"Livermore",
    "sg:classifiers":[
        {
            "category":"Retail",
            "subcategory":"Laundry & Dry Cleaning",
            "type":"Services"
        }
    ],
    "sg:phone":"+1 925 960 1630",
    "sg:postcode":"94551",
    "sg:province":"CA",
    "sg:tags":[
        "cleaners",
        "rug",
        "carpet"
    ],
    "wof:name":"Service Master Advanced Rstrtn",
    "wof:placetype":"venue"
},
  "geometry": {"coordinates":[-121.804377,37.689893],"type":"Point"}
}