{
  "type": "Feature",
  "properties": {
    "addr:full":"13535 Gault St Van Nuys CA 91405",
    "addr:housenumber":"13535",
    "addr:postcode":"91405",
    "addr:street":"Gault St",
    "iso:country":"US",
    "sg:address":"13535 Gault St",
    "sg:city":"Van Nuys",
    "sg:classifiers":[
        {
            "category":"Professional",
            "subcategory":"Credit Reporting & Collection",
            "type":"Services"
        }
    ],
    "sg:phone":"+1 818 909 9795",
    "sg:postcode":"91405",
    "sg:province":"CA",
    "sg:tags":[
        "agency"
    ],
    "wof:name":"A & A Collection Agency",
    "wof:placetype":"venue"
},
  "geometry": {"coordinates":[-118.42893599999999,34.199423],"type":"Point"}
}