{
  "type": "Feature",
  "properties": {
    "iso:country":"US",
    "sg:address":"1609 N Ave 55",
    "sg:city":"Los Angeles",
    "sg:classifiers":[
        {
            "category":"Professional",
            "type":"Services"
        }
    ],
    "sg:phone":"+1 323 254 8496",
    "sg:postcode":"90042",
    "sg:province":"CA",
    "wof:name":"Davis Alfred M & Associates",
    "wof:placetype":"venue"
},
  "geometry": {"coordinates":[-118.19758299999999,34.122904],"type":"Point"}
}