{
  "type": "Feature",
  "properties": {
    "addr:full":"1818 Cabrillo St San Francisco CA 94121",
    "addr:housenumber":"1818",
    "addr:postcode":"94121",
    "addr:street":"Cabrillo St",
    "iso:country":"US",
    "sg:address":"1818 Cabrillo St",
    "sg:city":"San Francisco",
    "sg:classifiers":[
        {
            "category":"Food & Beverages",
            "subcategory":"Groceries & Convenience Stores",
            "type":"Retail Goods"
        }
    ],
    "sg:phone":"+1 415 379 9780",
    "sg:postcode":"94121",
    "sg:province":"CA",
    "wof:name":"Lo Miu Kum",
    "wof:placetype":"venue"
},
  "geometry": {"coordinates":[-122.478821,37.774765],"type":"Point"}
}