{
  "type": "Feature",
  "properties": {
    "addr:full":"1287 N Jefferson St Anaheim CA 92807",
    "addr:housenumber":"1287",
    "addr:postcode":"92807",
    "addr:street":"N Jefferson St",
    "iso:country":"US",
    "sg:address":"1287 N Jefferson St",
    "sg:city":"Anaheim",
    "sg:classifiers":[
        {
            "category":"Professional",
            "type":"Services"
        }
    ],
    "sg:phone":"+1 714 632 8988",
    "sg:postcode":"92807",
    "sg:province":"CA",
    "sg:tags":[
        "establishment"
    ],
    "wof:name":"Aquatic Exhibit Group",
    "wof:placetype":"venue"
},
  "geometry": {"coordinates":[-117.837113,33.862706],"type":"Point"}
}