{
  "type": "Feature",
  "properties": {
    "addr:full":"427 Sherwood Dr Sausalito CA 94965",
    "addr:housenumber":"427",
    "addr:postcode":"94965",
    "addr:street":"Sherwood Dr",
    "iso:country":"US",
    "sg:address":"427 Sherwood Dr",
    "sg:city":"Sausalito",
    "sg:classifiers":[
        {
            "category":"Banks & Credit Unions",
            "subcategory":"Investment Brokerage",
            "type":"Services"
        }
    ],
    "sg:phone":"+1 415 302 1795",
    "sg:postcode":"94965",
    "sg:province":"CA",
    "sg:tags":[
        "advisory",
        "financial"
    ],
    "wof:name":"Pacific Financial Group",
    "wof:placetype":"venue"
},
  "geometry": {"coordinates":[-122.51816700000001,37.876221],"type":"Point"}
}