{
  "type": "Feature",
  "properties": {
    "addr:full":"9315 W Pico Blvd Los Angeles CA 90035",
    "addr:housenumber":"9315",
    "addr:postcode":"90035",
    "addr:street":"W Pico Blvd",
    "iso:country":"US",
    "sg:address":"9315 W Pico Blvd",
    "sg:city":"Los Angeles",
    "sg:classifiers":[
        {
            "category":"Organizations",
            "subcategory":"Religious Organization",
            "type":"Services"
        }
    ],
    "sg:phone":"+1 310 273 6954",
    "sg:postcode":"90035",
    "sg:province":"CA",
    "sg:tags":[
        "synagogue"
    ],
    "sg:website":"www.yicc.org",
    "wof:name":"Young Israel Of Century City",
    "wof:placetype":"venue"
},
  "geometry": {"coordinates":[-118.393839,34.055326],"type":"Point"}
}