{
  "type": "Feature",
  "properties": {
    "addr:full":"5694 Pentz Rd Paradise CA 95969",
    "addr:postcode":"5694;95969",
    "addr:street":"Pentz Rd",
    "iso:country":"US",
    "sg:address":"5694 Pentz Rd",
    "sg:city":"Paradise",
    "sg:classifiers":[
        {
            "category":"Retail",
            "subcategory":"Animal Services",
            "type":"Services"
        }
    ],
    "sg:phone":"+1 530 877 5411",
    "sg:postcode":"95969",
    "sg:province":"CA",
    "wof:name":"Muddy Paws",
    "wof:placetype":"venue"
},
  "geometry": {"coordinates":[-121.572327,39.747482],"type":"Point"}
}