{
  "type": "Feature",
  "properties": {
    "addr:full":"4701 Freeport Blvd Sacramento CA 95822",
    "addr:housenumber":"4701",
    "addr:postcode":"95822",
    "addr:street":"Freeport Blvd",
    "iso:country":"US",
    "sg:address":"4701 Freeport Blvd",
    "sg:city":"Sacramento",
    "sg:classifiers":[
        {
            "category":"Banks & Credit Unions",
            "subcategory":"Bank",
            "type":"Services"
        }
    ],
    "sg:phone":"+1 800 933 3000",
    "sg:postcode":"95822",
    "sg:province":"CA",
    "wof:name":"Home Savings of America",
    "wof:placetype":"venue"
},
  "geometry": {"coordinates":[-121.494682,38.532372],"type":"Point"}
}