{
  "type": "Feature",
  "properties": {
    "iso:country":"US",
    "sg:address":"415 E Pine St",
    "sg:city":"Compton",
    "sg:classifiers":[
        {
            "category":"Wholesale",
            "subcategory":"Auto Parts",
            "type":"Manufacturing & Wholesale Goods"
        }
    ],
    "sg:phone":"+1 310 638 8552",
    "sg:postcode":"90222",
    "sg:province":"CA",
    "sg:tags":[
        "automobile",
        "wrecking"
    ],
    "wof:name":"Southeast Auto Salvage",
    "wof:placetype":"venue"
},
  "geometry": {"coordinates":[-118.218521,33.911279],"type":"Point"}
}