{
  "type": "Feature",
  "properties": {
    "iso:country":"US",
    "sg:address":"5211 Telegraph Rd",
    "sg:city":"Los Angeles",
    "sg:classifiers":[
        {
            "category":"Professional",
            "subcategory":"Management & Consulting",
            "type":"Services"
        }
    ],
    "sg:phone":"+1 323 526 4402",
    "sg:postcode":"90022",
    "sg:province":"CA",
    "sg:tags":[
        "consultant",
        "broker"
    ],
    "wof:name":"United Consortium",
    "wof:placetype":"venue"
},
  "geometry": {"coordinates":[-118.159236,34.010867],"type":"Point"}
}