{
  "type": "Feature",
  "properties": {
    "iso:country":"US",
    "sg:address":"3730 Northland Drive",
    "sg:city":"Los Angeles",
    "sg:classifiers":[
        {
            "category":"Restaurant",
            "type":"Food & Drink"
        }
    ],
    "sg:phone":"+1 323 293 3749",
    "sg:postcode":"90008",
    "sg:province":"CA",
    "wof:name":"Holly's Bar-B-Que",
    "wof:placetype":"venue"
},
  "geometry": {"coordinates":[-118.340339,34.003063],"type":"Point"}
}