{
  "type": "Feature",
  "properties": {
    "iso:country":"US",
    "sg:address":"424 E Kendall Ave",
    "sg:city":"Ridgecrest",
    "sg:classifiers":[
        {
            "category":"Professional",
            "subcategory":"Engineering",
            "type":"Services"
        }
    ],
    "sg:phone":"+1 760 371 1442",
    "sg:postcode":"93555",
    "sg:province":"CA",
    "sg:tags":[
        "engineer"
    ],
    "wof:name":"Strain Gage Advice",
    "wof:placetype":"venue"
},
  "geometry": {"coordinates":[-117.66368199999999,35.586174],"type":"Point"}
}