{
  "type": "Feature",
  "properties": {
    "addr:full":"909 W Murray Ave Visalia CA 93291",
    "addr:housenumber":"909",
    "addr:postcode":"93291",
    "addr:street":"W Murray Ave",
    "iso:country":"US",
    "sg:address":"909 W Murray Ave",
    "sg:city":"Visalia",
    "sg:classifiers":[
        {
            "category":"Education",
            "subcategory":"School",
            "type":"Public Place"
        }
    ],
    "sg:phone":"+1 559 730 7563",
    "sg:postcode":"93291",
    "sg:province":"CA",
    "wof:name":"Visalia Unified School District North Visalia Education Center",
    "wof:placetype":"venue"
},
  "geometry": {"coordinates":[-119.301231,36.333732],"type":"Point"}
}