{
  "type": "Feature",
  "properties": {
    "addr:full":"307 McCord Ave Bakersfield CA 93308",
    "addr:housenumber":"307",
    "addr:postcode":"93308",
    "addr:street":"Mccord Ave",
    "iso:country":"US",
    "sg:address":"307 McCord Ave",
    "sg:city":"Bakersfield",
    "sg:classifiers":[
        {
            "category":"Building & Trades",
            "subcategory":"Construction",
            "type":"Services"
        }
    ],
    "sg:phone":"+1 661 391 0877",
    "sg:postcode":"93308",
    "sg:province":"CA",
    "sg:tags":[
        "painter"
    ],
    "wof:name":"James King Professional Paint",
    "wof:placetype":"venue"
},
  "geometry": {"coordinates":[-119.025395,35.406734],"type":"Point"}
}