{
  "type": "Feature",
  "properties": {
    "iso:country":"US",
    "sg:address":"1589 W El Camino Avenue",
    "sg:city":"Sacramento",
    "sg:classifiers":[
        {
            "category":"Retail",
            "subcategory":"Laundry & Dry Cleaning",
            "type":"Services"
        }
    ],
    "sg:phone":"+1 916 920 4056",
    "sg:postcode":"95833",
    "sg:province":"CA",
    "wof:name":"Dry Clean Today",
    "wof:placetype":"venue"
},
  "geometry": {"coordinates":[-121.497749,38.612805],"type":"Point"}
}