{
  "type": "Feature",
  "properties": {
    "addr:full":"760 Main St Ramona CA 92065",
    "addr:housenumber":"760",
    "addr:postcode":"92065",
    "addr:street":"Main St",
    "iso:country":"US",
    "sg:address":"760 Main St",
    "sg:city":"Ramona",
    "sg:classifiers":[
        {
            "category":"Shopping",
            "subcategory":"Used Merchandise",
            "type":"Retail Goods"
        }
    ],
    "sg:phone":"+1 760 788 2729",
    "sg:postcode":"92065",
    "sg:province":"CA",
    "sg:tags":[
        "antique"
    ],
    "wof:name":"Old Town Antiques",
    "wof:placetype":"venue"
},
  "geometry": {"coordinates":[-116.864502,33.044224],"type":"Point"}
}