{
  "type": "Feature",
  "properties": {
    "addr:full":"4809 Clairemont Dr San Diego CA 92117",
    "addr:housenumber":"4809",
    "addr:postcode":"92117",
    "addr:street":"Clairemont Dr",
    "iso:country":"US",
    "sg:address":"4809 Clairemont Dr",
    "sg:city":"San Diego",
    "sg:classifiers":[
        {
            "category":"Autos & Motor Vehicles",
            "subcategory":"Auto Supplies",
            "type":"Retail Goods"
        }
    ],
    "sg:phone":"+1 858 273 4900",
    "sg:postcode":"92117",
    "sg:province":"CA",
    "sg:tags":[
        "tire"
    ],
    "wof:name":"Express Tire",
    "wof:placetype":"venue"
},
  "geometry": {"coordinates":[-117.20390999999999,32.832459],"type":"Point"}
}