{
  "type": "Feature",
  "properties": {
    "addr:full":"960 San Antonio Ave Palo Alto CA 94303",
    "addr:housenumber":"960",
    "addr:postcode":"94303",
    "addr:street":"San Antonio Ave",
    "iso:country":"US",
    "sg:address":"960 San Antonio Ave",
    "sg:city":"Palo Alto",
    "sg:classifiers":[
        {
            "category":"Taxi",
            "type":"Transportation"
        }
    ],
    "sg:phone":"+1 650 362 1234",
    "sg:postcode":"94303",
    "sg:province":"CA",
    "sg:tags":[
        "taxicab"
    ],
    "wof:name":"Yellow Cab",
    "wof:placetype":"venue"
},
  "geometry": {"coordinates":[-122.10122699999999,37.425383],"type":"Point"}
}