{
  "type": "Feature",
  "properties": {
    "iso:country":"US",
    "sg:address":"1602 E Edinger Ave",
    "sg:city":"Santa Ana",
    "sg:classifiers":[
        {
            "category":"Shopping",
            "subcategory":"Clothing, Apparel, & Fashions",
            "type":"Retail Goods"
        }
    ],
    "sg:phone":"+1 714 558 3743",
    "sg:postcode":"92705",
    "sg:province":"CA",
    "sg:tags":[
        "costume"
    ],
    "wof:name":"L & N Costume Services",
    "wof:placetype":"venue"
},
  "geometry": {"coordinates":[-117.848,33.726601],"type":"Point"}
}