{
  "type": "Feature",
  "properties": {
    "iso:country":"US",
    "sg:address":"5455 Wilshire Blvd",
    "sg:city":"Los Angeles",
    "sg:classifiers":[
        {
            "category":"Manufacturing",
            "subcategory":"Food",
            "type":"Manufacturing & Wholesale Goods"
        }
    ],
    "sg:phone":"+1 323 857 0006",
    "sg:postcode":"90036",
    "sg:province":"CA",
    "sg:tags":[
        "product",
        "manufacturer"
    ],
    "wof:name":"Quantum Color Graphics",
    "wof:placetype":"venue"
},
  "geometry": {"coordinates":[-118.348189,34.062328],"type":"Point"}
}