{
  "type": "Feature",
  "properties": {
    "addr:full":"323 Pso Tesoro Walnut CA 91789",
    "addr:housenumber":"323",
    "addr:postcode":"91789",
    "addr:street":"Pso Tesoro",
    "iso:country":"US",
    "sg:address":"323 Pso Tesoro",
    "sg:city":"Walnut",
    "sg:classifiers":[
        {
            "category":"Professional",
            "type":"Services"
        }
    ],
    "sg:phone":"+1 909 839 0532",
    "sg:postcode":"91789",
    "sg:province":"CA",
    "sg:tags":[
        "establishment"
    ],
    "wof:name":"Gcc America",
    "wof:placetype":"venue"
},
  "geometry": {"coordinates":[-117.8571,34.01337],"type":"Point"}
}