{
  "type": "Feature",
  "properties": {
    "addr:full":"1535 N Broadway Escondido CA 92026",
    "addr:housenumber":"1535",
    "addr:postcode":"92026",
    "addr:street":"N Broadway",
    "iso:country":"US",
    "sg:address":"1535 N Broadway",
    "sg:city":"Escondido",
    "sg:classifiers":[
        {
            "category":"Education",
            "subcategory":"School",
            "type":"Public Place"
        }
    ],
    "sg:phone":"+1 760 291 4000",
    "sg:postcode":"92026",
    "sg:province":"CA",
    "sg:tags":[
        "high"
    ],
    "sg:website":"http://www.ehscougars.com",
    "wof:name":"Escondido High School",
    "wof:placetype":"venue"
},
  "geometry": {"coordinates":[-117.09017900000001,33.144211],"type":"Point"}
}