{
  "type": "Feature",
  "properties": {
    "iso:country":"US",
    "sg:address":"442 Anvilwood Dr",
    "sg:city":"Oakley",
    "sg:classifiers":[
        {
            "category":"Farming",
            "subcategory":"Farm",
            "type":"Manufacturing & Wholesale Goods"
        }
    ],
    "sg:phone":"+1 925 625 3808",
    "sg:postcode":"94561",
    "sg:province":"CA",
    "sg:tags":[
        "crop",
        "general"
    ],
    "wof:name":"Caviare Farms Ltd",
    "wof:placetype":"venue"
},
  "geometry": {"coordinates":[-121.702097,37.988414],"type":"Point"}
}