{
  "type": "Feature",
  "properties": {
    "iso:country":"US",
    "sg:address":"625 Alfred Nobel Dr",
    "sg:city":"Hercules",
    "sg:classifiers":[
        {
            "category":"Professional",
            "subcategory":"Research",
            "type":"Services"
        }
    ],
    "sg:phone":"+1 510 741 3000",
    "sg:postcode":"94547",
    "sg:province":"CA",
    "sg:tags":[
        "environmental",
        "ecological"
    ],
    "wof:name":"PTRL West Inc",
    "wof:placetype":"venue"
},
  "geometry": {"coordinates":[-122.274376,38.018185],"type":"Point"}
}