{
  "type": "Feature",
  "properties": {
    "addr:full":"3618 Thornton Ave Fremont CA 94536",
    "addr:housenumber":"3618",
    "addr:postcode":"94536",
    "addr:street":"Thornton Ave",
    "iso:country":"US",
    "sg:address":"3618 Thornton Ave",
    "sg:city":"Fremont",
    "sg:classifiers":[
        {
            "category":"Health Services",
            "subcategory":"Doctor",
            "type":"Services"
        }
    ],
    "sg:phone":"+1 510 797 2320",
    "sg:postcode":"94536",
    "sg:province":"CA",
    "sg:tags":[
        "dentist"
    ],
    "wof:name":"Steven T Fan DDS",
    "wof:placetype":"venue"
},
  "geometry": {"coordinates":[-122.01058,37.561813],"type":"Point"}
}