{
  "type": "Feature",
  "properties": {
    "iso:country":"US",
    "sg:address":"4615 Lankershim Blvd",
    "sg:city":"North Hollywood",
    "sg:classifiers":[
        {
            "category":"Restaurant",
            "type":"Food & Drink"
        }
    ],
    "sg:phone":"+1 818 769 1812",
    "sg:postcode":"91602",
    "sg:province":"CA",
    "sg:tags":[
        "french"
    ],
    "sg:website":"www.lepetitchateau.org",
    "wof:name":"Le Petit Chateau",
    "wof:placetype":"venue"
},
  "geometry": {"coordinates":[-118.368177,34.154193],"type":"Point"}
}