{
  "type": "Feature",
  "properties": {
    "iso:country":"US",
    "sg:address":"45531 Rancho Palmeras Dr",
    "sg:city":"Indian Wells",
    "sg:classifiers":[
        {
            "category":"Banks & Credit Unions",
            "subcategory":"Investment Brokerage",
            "type":"Services"
        }
    ],
    "sg:phone":"+1 760 568 1014",
    "sg:postcode":"92210",
    "sg:province":"CA",
    "sg:tags":[
        "consultant",
        "planning",
        "financial"
    ],
    "wof:name":"Prince E Pierson Conservator",
    "wof:placetype":"venue"
},
  "geometry": {"coordinates":[-116.34768099999999,33.71578],"type":"Point"}
}