{
  "type": "Feature",
  "properties": {
    "addr:full":"345 Chapala St Santa Barbara CA 93101",
    "addr:housenumber":"345",
    "addr:postcode":"93101",
    "addr:street":"Chapala St",
    "iso:country":"US",
    "sg:address":"345 Chapala St",
    "sg:city":"Santa Barbara",
    "sg:classifiers":[
        {
            "category":"Professional",
            "subcategory":"Computer Services",
            "type":"Services"
        }
    ],
    "sg:phone":"+1 805 965 2500",
    "sg:postcode":"93101",
    "sg:province":"CA",
    "sg:tags":[
        "website",
        "design"
    ],
    "wof:name":"Discount Solutions LLC",
    "wof:placetype":"venue"
},
  "geometry": {"coordinates":[-119.695233,34.414583],"type":"Point"}
}