{
  "type": "Feature",
  "properties": {
    "addr:full":"3770 Cherry Ave Long Beach CA 90807",
    "addr:housenumber":"3770",
    "addr:postcode":"90807",
    "addr:street":"Cherry Ave",
    "iso:country":"US",
    "sg:address":"3770 Cherry Ave",
    "sg:city":"Long Beach",
    "sg:classifiers":[
        {
            "category":"Autos & Motor Vehicles",
            "subcategory":"Automobile Sales",
            "type":"Retail Goods"
        },
        {
            "category":"Retail",
            "subcategory":"Auto Repair",
            "type":"Services"
        }
    ],
    "sg:phone":"+1 714 527 8779",
    "sg:postcode":"90807",
    "sg:province":"CA",
    "sg:tags":[
        "car"
    ],
    "sg:website":"www.harborhyundai.com/",
    "wof:name":"Harbor Chevrolet Corp",
    "wof:placetype":"venue"
},
  "geometry": {"coordinates":[-118.167,33.825901],"type":"Point"}
}