{
  "type": "Feature",
  "properties": {
    "iso:country":"US",
    "sg:address":"938 S 9th St",
    "sg:city":"Kerman",
    "sg:classifiers":[
        {
            "category":"Freight",
            "type":"Transportation"
        }
    ],
    "sg:phone":"+1 559 846 3915",
    "sg:postcode":"93630",
    "sg:province":"CA",
    "sg:tags":[
        "operator",
        "local",
        "trucking"
    ],
    "wof:name":"Rodriguez Trucking",
    "wof:placetype":"venue"
},
  "geometry": {"coordinates":[-120.055227,36.721079],"type":"Point"}
}