{
  "type": "Feature",
  "properties": {
    "addr:full":"18990 McKinley Ave Manteca CA 95337",
    "addr:housenumber":"18990",
    "addr:postcode":"95337",
    "addr:street":"Mckinley Ave",
    "iso:country":"US",
    "sg:address":"18990 McKinley Ave",
    "sg:city":"Manteca",
    "sg:classifiers":[
        {
            "category":"Freight",
            "type":"Transportation"
        }
    ],
    "sg:phone":"+1 209 823 1837",
    "sg:postcode":"95337",
    "sg:province":"CA",
    "sg:tags":[
        "operator",
        "local",
        "trucking"
    ],
    "wof:name":"Jesse M Espinoza Trucking",
    "wof:placetype":"venue"
},
  "geometry": {"coordinates":[-121.27046199999999,37.785769],"type":"Point"}
}