{
  "type": "Feature",
  "properties": {
    "addr:full":"945 Noble Way Santa Maria CA 93454",
    "addr:housenumber":"945",
    "addr:postcode":"93454",
    "addr:street":"Noble Way",
    "iso:country":"US",
    "sg:address":"945 Noble Way",
    "sg:city":"Santa Maria",
    "sg:classifiers":[
        {
            "category":"Freight",
            "type":"Transportation"
        }
    ],
    "sg:phone":"+1 805 739 5401",
    "sg:postcode":"93454",
    "sg:province":"CA",
    "sg:tags":[
        "distance",
        "local",
        "long",
        "trucking"
    ],
    "wof:name":"SAIA Motor Freight Line Inc",
    "wof:placetype":"venue"
},
  "geometry": {"coordinates":[-120.42173,34.970068],"type":"Point"}
}