{
  "type": "Feature",
  "properties": {
    "iso:country":"US",
    "sg:address":"1601 W Ave J",
    "sg:city":"Lancaster",
    "sg:classifiers":[
        {
            "category":"Health Services",
            "subcategory":"Doctor",
            "type":"Services"
        }
    ],
    "sg:phone":"+1 661 726 4504",
    "sg:postcode":"93534",
    "sg:province":"CA",
    "sg:tags":[
        "dentist"
    ],
    "wof:name":"Salomon Chams DDS",
    "wof:placetype":"venue"
},
  "geometry": {"coordinates":[-118.158759,34.68941],"type":"Point"}
}