{
  "type": "Feature",
  "properties": {
    "iso:country":"US",
    "sg:address":"26944 Cam de Estrella",
    "sg:city":"Capistrano Beach",
    "sg:classifiers":[
        {
            "category":"Personal",
            "subcategory":"Barber",
            "type":"Services"
        }
    ],
    "sg:phone":"+1 949 240 7704",
    "sg:postcode":"92624",
    "sg:province":"CA",
    "wof:name":"Beachtown Salon",
    "wof:placetype":"venue"
},
  "geometry": {"coordinates":[-117.65936,33.455306],"type":"Point"}
}