{
  "type": "Feature",
  "properties": {
    "iso:country":"US",
    "sg:address":"7323 Convoy Ct",
    "sg:city":"San Diego",
    "sg:classifiers":[
        {
            "category":"Food & Beverages",
            "subcategory":"Specialty",
            "type":"Retail Goods"
        }
    ],
    "sg:phone":"+1 858 573 2168",
    "sg:postcode":"92111",
    "sg:province":"CA",
    "sg:tags":[
        "herb"
    ],
    "wof:name":"De Chan Tan",
    "wof:placetype":"venue"
},
  "geometry": {"coordinates":[-117.162273,32.834594],"type":"Point"}
}