{
  "type": "Feature",
  "properties": {
    "iso:country":"US",
    "sg:address":"13341 Ventura Blvd",
    "sg:city":"Sherman Oaks",
    "sg:classifiers":[
        {
            "category":"Health Services",
            "subcategory":"Doctor",
            "type":"Services"
        }
    ],
    "sg:phone":"+1 818 385 3200",
    "sg:postcode":"91423",
    "sg:province":"CA",
    "sg:website":"www.goldenstatehealth.com",
    "wof:name":"Golden State Health Centers Inc",
    "wof:placetype":"venue"
},
  "geometry": {"coordinates":[-118.422997,34.146599],"type":"Point"}
}