{
  "type": "Feature",
  "properties": {
    "iso:country":"US",
    "sg:address":"21 Columbus Ave",
    "sg:city":"San Francisco",
    "sg:classifiers":[
        {
            "category":"Professional",
            "subcategory":"Engineering",
            "type":"Services"
        }
    ],
    "sg:phone":"+1 415 986 2871",
    "sg:postcode":"94111",
    "sg:province":"CA",
    "sg:tags":[
        "engineer"
    ],
    "sg:website":"www.baseline-env.com",
    "wof:name":"Baseline Environmental Consult",
    "wof:placetype":"venue"
},
  "geometry": {"coordinates":[-122.403913,37.795825],"type":"Point"}
}