{
  "type": "Feature",
  "properties": {
    "addr:full":"4671 Rosewood Ave Los Angeles CA 90004",
    "addr:housenumber":"4671",
    "addr:postcode":"90004",
    "addr:street":"Rosewood Ave",
    "iso:country":"US",
    "sg:address":"4671 Rosewood Ave",
    "sg:city":"Los Angeles",
    "sg:classifiers":[
        {
            "category":"Wholesale",
            "subcategory":"Construction Materials",
            "type":"Manufacturing & Wholesale Goods"
        }
    ],
    "sg:phone":"+1 323 578 1896",
    "sg:postcode":"90004",
    "sg:province":"CA",
    "wof:name":"Golden Body",
    "wof:placetype":"venue"
},
  "geometry": {"coordinates":[-118.306498,34.07906],"type":"Point"}
}