{
  "type": "Feature",
  "properties": {
    "addr:full":"1383 W Park Western Dr San Pedro CA 90732",
    "addr:housenumber":"1383",
    "addr:postcode":"90732",
    "addr:street":"W Park Western Dr",
    "iso:country":"US",
    "sg:address":"1383 W Park Western Dr",
    "sg:city":"San Pedro",
    "sg:classifiers":[
        {
            "category":"Personal",
            "subcategory":"Barber",
            "type":"Services"
        }
    ],
    "sg:phone":"+1 310 547 9138",
    "sg:postcode":"90732",
    "sg:province":"CA",
    "wof:name":"Park Plaza Barber Shop",
    "wof:placetype":"venue"
},
  "geometry": {"coordinates":[-118.30676,33.752938],"type":"Point"}
}