{
  "type": "Feature",
  "properties": {
    "iso:country":"US",
    "sg:address":"1757 W Carson St",
    "sg:city":"Torrance",
    "sg:classifiers":[
        {
            "category":"Wholesale",
            "subcategory":"Durable Goods & Equipment",
            "type":"Manufacturing & Wholesale Goods"
        },
        {
            "category":"Wholesale",
            "subcategory":"Non-durable Goods",
            "type":"Manufacturing & Wholesale Goods"
        }
    ],
    "sg:phone":"+1 310 782 6617",
    "sg:postcode":"90501",
    "sg:province":"CA",
    "sg:tags":[
        "exporter"
    ],
    "wof:name":"Jugame Net Trading",
    "wof:placetype":"venue"
},
  "geometry": {"coordinates":[-118.31164200000001,33.831516],"type":"Point"}
}