{
  "type": "Feature",
  "properties": {
    "iso:country":"US",
    "sg:address":"1061 S Prospero Dr",
    "sg:city":"Glendora",
    "sg:classifiers":[
        {
            "category":"Freight",
            "type":"Transportation"
        }
    ],
    "sg:phone":"+1 626 335 1112",
    "sg:postcode":"91740",
    "sg:province":"CA",
    "sg:tags":[
        "trucking"
    ],
    "wof:name":"Sewdlow Trucking",
    "wof:placetype":"venue"
},
  "geometry": {"coordinates":[-117.87883600000001,34.119253],"type":"Point"}
}