{
  "type": "Feature",
  "properties": {
    "iso:country":"US",
    "sg:address":"1015 Turquoise St Ste 4",
    "sg:city":"San Diego",
    "sg:classifiers":[
        {
            "category":"Retail",
            "subcategory":"Laundry & Dry Cleaning",
            "type":"Services"
        }
    ],
    "sg:phone":"+1 858 483 1781",
    "sg:postcode":"92109",
    "sg:province":"CA",
    "wof:name":"Dry Clean 4 Less",
    "wof:placetype":"venue"
},
  "geometry": {"coordinates":[-117.254997,32.809502],"type":"Point"}
}