{
  "type": "Feature",
  "properties": {
    "iso:country":"US",
    "sg:address":"1127 Reston Dr",
    "sg:city":"Folsom",
    "sg:classifiers":[
        {
            "category":"Professional",
            "subcategory":"Research",
            "type":"Services"
        },
        {
            "category":"Professional",
            "subcategory":"Advertising",
            "type":"Services"
        }
    ],
    "sg:phone":"+1 916 984 4190",
    "sg:postcode":"95630",
    "sg:province":"CA",
    "sg:tags":[
        "development",
        "marketing",
        "product"
    ],
    "wof:name":"Catalina Marketing Corporation",
    "wof:placetype":"venue"
},
  "geometry": {"coordinates":[-121.141263,38.665094],"type":"Point"}
}