{
  "type": "Feature",
  "properties": {
    "iso:country":"US",
    "sg:address":"4082 Adobe Rd",
    "sg:city":"Twentynine Palms",
    "sg:classifiers":[
        {
            "category":"Retail",
            "subcategory":"Auto Repair",
            "type":"Services"
        }
    ],
    "sg:phone":"+1 760 367 0222",
    "sg:postcode":"92277",
    "sg:province":"CA",
    "sg:tags":[
        "repairing",
        "automobile"
    ],
    "wof:name":"Speer Automotive",
    "wof:placetype":"venue"
},
  "geometry": {"coordinates":[-116.054225,34.179521],"type":"Point"}
}