{
  "type": "Feature",
  "properties": {
    "addr:full":"1902 2nd St Eureka CA 95501",
    "addr:housenumber":"1902",
    "addr:postcode":"95501",
    "addr:street":"2Nd St",
    "iso:country":"US",
    "sg:address":"1902 2nd St",
    "sg:city":"Eureka",
    "sg:classifiers":[
        {
            "category":"Retail",
            "subcategory":"Auto Repair",
            "type":"Services"
        }
    ],
    "sg:phone":"+1 707 444 3235",
    "sg:postcode":"95501",
    "sg:province":"CA",
    "sg:tags":[
        "repairing",
        "automobile"
    ],
    "wof:name":"Auto Masters Auto Repair",
    "wof:placetype":"venue"
},
  "geometry": {"coordinates":[-124.15141199999999,40.806253],"type":"Point"}
}