{
  "type": "Feature",
  "properties": {
    "addr:full":"216 Capitola Ave Capitola CA 95010",
    "addr:housenumber":"216",
    "addr:postcode":"95010",
    "addr:street":"Capitola Ave",
    "iso:country":"US",
    "sg:address":"216 Capitola Ave",
    "sg:city":"Capitola",
    "sg:classifiers":[
        {
            "category":"Shopping",
            "subcategory":"Gifts & Souvenirs",
            "type":"Retail Goods"
        }
    ],
    "sg:phone":"+1 831 475 0915",
    "sg:postcode":"95010",
    "sg:province":"CA",
    "sg:tags":[
        "shop",
        "art",
        "gallery"
    ],
    "sg:website":"www.dragginwood.com",
    "wof:name":"Dragginwood & the Magic Crystals",
    "wof:placetype":"venue"
},
  "geometry": {"coordinates":[-121.952003,36.973202],"type":"Point"}
}