{
  "type": "Feature",
  "properties": {
    "addr:full":"9120 Rd 236 Terra Bella CA 93270",
    "addr:postcode":"9120;93270",
    "addr:street":"Rd 236",
    "iso:country":"US",
    "sg:address":"9120 Rd 236",
    "sg:city":"Terra Bella",
    "sg:classifiers":[
        {
            "category":"Organizations",
            "subcategory":"Religious Organization",
            "type":"Services"
        }
    ],
    "sg:phone":"+1 559 535 7621",
    "sg:postcode":"93270",
    "sg:province":"CA",
    "sg:tags":[
        "church"
    ],
    "wof:name":"Miguel Miguel Pro Church",
    "wof:placetype":"venue"
},
  "geometry": {"coordinates":[-119.044674,35.951104],"type":"Point"}
}