{
  "type": "Feature",
  "properties": {
    "addr:full":"670 Crenshaw Blvd Los Angeles CA 90005",
    "addr:housenumber":"670",
    "addr:postcode":"90005",
    "addr:street":"Crenshaw Blvd",
    "iso:country":"US",
    "sg:address":"670 Crenshaw Blvd",
    "sg:city":"Los Angeles",
    "sg:classifiers":[
        {
            "category":"Education",
            "subcategory":"College",
            "type":"Public Place"
        }
    ],
    "sg:phone":"+1 323 634 0065",
    "sg:postcode":"90005",
    "sg:province":"CA",
    "sg:tags":[
        "academic",
        "school"
    ],
    "wof:name":"Koryo University",
    "wof:placetype":"venue"
},
  "geometry": {"coordinates":[-118.32021,34.059611],"type":"Point"}
}