{
  "type": "Feature",
  "properties": {
    "addr:full":"3400 Lomita Blvd Ste 504 Torrance CA 90505",
    "addr:housenumber":"3400",
    "addr:postcode":"90505",
    "addr:street":"Lomita Blvd Ste 504",
    "iso:country":"US",
    "sg:address":"3400 Lomita Blvd Ste 504",
    "sg:city":"Torrance",
    "sg:classifiers":[
        {
            "category":"Health Services",
            "subcategory":"Doctor",
            "type":"Services"
        }
    ],
    "sg:phone":"+1 310 784 2776",
    "sg:postcode":"90505",
    "sg:province":"CA",
    "sg:tags":[
        "surgeon",
        "oral"
    ],
    "wof:name":"Ota Kazuo DDS",
    "wof:placetype":"venue"
},
  "geometry": {"coordinates":[-118.345001,33.813099],"type":"Point"}
}