{
  "type": "Feature",
  "properties": {
    "iso:country":"US",
    "sg:address":"61 Lincoln Ctr",
    "sg:city":"Stockton",
    "sg:classifiers":[
        {
            "category":"Restaurant",
            "type":"Food & Drink"
        }
    ],
    "sg:menulink":"http://www.allmenus.com/ca/stockton/61793-payters-grill/menu/",
    "sg:phone":"+1 209 477 9513",
    "sg:postcode":"95207",
    "sg:province":"CA",
    "sg:tags":[
        "american"
    ],
    "wof:name":"Payter's Grill",
    "wof:placetype":"venue"
},
  "geometry": {"coordinates":[-121.31267699999999,38.016235],"type":"Point"}
}