{
  "type": "Feature",
  "properties": {
    "iso:country":"US",
    "sg:address":"8 Los Abitos",
    "sg:city":"Rancho Santa Margarita",
    "sg:classifiers":[
        {
            "category":"Professional",
            "type":"Services"
        }
    ],
    "sg:phone":"+1 949 459 7367",
    "sg:postcode":"92688",
    "sg:province":"CA",
    "wof:name":"Garden Party",
    "wof:placetype":"venue"
},
  "geometry": {"coordinates":[-117.590877,33.648418],"type":"Point"}
}