{
  "type": "Feature",
  "properties": {
    "iso:country":"US",
    "sg:address":"29724 Platanus Dr",
    "sg:city":"Escondido",
    "sg:classifiers":[
        {
            "category":"Health Services",
            "subcategory":"Clinic",
            "type":"Services"
        }
    ],
    "sg:phone":"+1 760 941 7078",
    "sg:postcode":"92026",
    "sg:province":"CA",
    "wof:name":"South Coast Anesthesia",
    "wof:placetype":"venue"
},
  "geometry": {"coordinates":[-117.14103299999999,33.255025],"type":"Point"}
}