{
  "type": "Feature",
  "properties": {
    "iso:country":"US",
    "sg:address":"4351 Melrose Ave",
    "sg:city":"Los Angeles",
    "sg:classifiers":[
        {
            "category":"Home & Garden",
            "subcategory":"Furniture",
            "type":"Retail Goods"
        }
    ],
    "sg:phone":"+1 323 669 1503",
    "sg:postcode":"90029",
    "sg:province":"CA",
    "sg:tags":[
        "store"
    ],
    "wof:name":"Melrose Furniture",
    "wof:placetype":"venue"
},
  "geometry": {"coordinates":[-118.29499800000001,34.0835],"type":"Point"}
}