{
  "type": "Feature",
  "properties": {
    "iso:country":"US",
    "sg:address":"10850 Gadsten Way",
    "sg:city":"Rancho Cordova",
    "sg:classifiers":[
        {
            "category":"Education",
            "subcategory":"School",
            "type":"Public Place"
        }
    ],
    "sg:phone":"+1 916 635 2379",
    "sg:postcode":"95670",
    "sg:province":"CA",
    "wof:name":"Folsom Cordova Unified School District",
    "wof:placetype":"venue"
},
  "geometry": {"coordinates":[-121.28018400000001,38.607469],"type":"Point"}
}