{
  "type": "Feature",
  "properties": {
    "iso:country":"US",
    "sg:address":"2209 E Valley Pkwy",
    "sg:city":"Escondido",
    "sg:classifiers":[
        {
            "category":"Food & Beverages",
            "subcategory":"Groceries & Convenience Stores",
            "type":"Retail Goods"
        }
    ],
    "sg:phone":"+1 760 743 6442",
    "sg:postcode":"92027",
    "sg:province":"CA",
    "sg:tags":[
        "grocer"
    ],
    "wof:name":"Cinco De Mayo Market",
    "wof:placetype":"venue"
},
  "geometry": {"coordinates":[-117.047804,33.139229],"type":"Point"}
}