{
  "type": "Feature",
  "properties": {
    "addr:full":"1000 E Vista Way Vista CA 92084",
    "addr:housenumber":"1000",
    "addr:postcode":"92084",
    "addr:street":"E Vista Way",
    "iso:country":"US",
    "sg:address":"1000 E Vista Way",
    "sg:city":"Vista",
    "sg:classifiers":[
        {
            "category":"Health Services",
            "subcategory":"Dentist",
            "type":"Services"
        }
    ],
    "sg:phone":"+1 760 940 4266",
    "sg:postcode":"92084",
    "sg:province":"CA",
    "sg:tags":[
        "dental",
        "clinic"
    ],
    "wof:name":"Dr Donald Fellers & Assoc",
    "wof:placetype":"venue"
},
  "geometry": {"coordinates":[-117.22933999999999,33.21209],"type":"Point"}
}