{
  "type": "Feature",
  "properties": {
    "addr:full":"11301 Olympic Blvd Los Angeles CA 90064",
    "addr:housenumber":"11301",
    "addr:postcode":"90064",
    "addr:street":"Olympic Blvd",
    "iso:country":"US",
    "sg:address":"11301 Olympic Blvd",
    "sg:city":"Los Angeles",
    "sg:classifiers":[
        {
            "category":"Food & Beverages",
            "subcategory":"Candy",
            "type":"Retail Goods"
        }
    ],
    "sg:phone":"+1 310 914 0404",
    "sg:postcode":"90064",
    "sg:province":"CA",
    "sg:tags":[
        "dessert"
    ],
    "wof:name":"Cake House",
    "wof:placetype":"venue"
},
  "geometry": {"coordinates":[-118.441288,34.038178],"type":"Point"}
}