{
  "type": "Feature",
  "properties": {
    "iso:country":"US",
    "sg:address":"7728 Obsidian Ct",
    "sg:city":"Cupertino",
    "sg:classifiers":[
        {
            "category":"Professional",
            "subcategory":"Business Services",
            "type":"Services"
        }
    ],
    "sg:phone":"+1 408 996 1055",
    "sg:postcode":"95014",
    "sg:province":"CA",
    "sg:tags":[
        "embroidery"
    ],
    "wof:name":"Pacific Embroidery",
    "wof:placetype":"venue"
},
  "geometry": {"coordinates":[-122.04278100000001,37.308169],"type":"Point"}
}