{
  "type": "Feature",
  "properties": {
    "iso:country":"US",
    "sg:address":"425 S Mathilda Avenue",
    "sg:city":"Sunnyvale",
    "sg:classifiers":[
        {
            "category":"Banks & Credit Unions",
            "subcategory":"Bank",
            "type":"Services"
        }
    ],
    "sg:phone":"+1 408 735 8111",
    "sg:postcode":"94086",
    "sg:province":"CA",
    "wof:name":"World Savings",
    "wof:placetype":"venue"
},
  "geometry": {"coordinates":[-122.03563699999999,37.373097],"type":"Point"}
}