{
  "type": "Feature",
  "properties": {
    "iso:country":"US",
    "sg:address":"8103 Beverly Blvd",
    "sg:city":"Los Angeles",
    "sg:classifiers":[
        {
            "category":"Restaurant",
            "type":"Food & Drink"
        }
    ],
    "sg:phone":"+1 323 658 6700",
    "sg:postcode":"90048",
    "sg:province":"CA",
    "sg:tags":[
        "sushi",
        "bar"
    ],
    "wof:name":"Sushi Time",
    "wof:placetype":"venue"
},
  "geometry": {"coordinates":[-118.36599699999999,34.076],"type":"Point"}
}