{
  "type": "Feature",
  "properties": {
    "iso:country":"US",
    "sg:address":"2901 Innsbruck Dr",
    "sg:city":"Redding",
    "sg:classifiers":[
        {
            "category":"Freight",
            "type":"Transportation"
        }
    ],
    "sg:phone":"+1 530 221 0315",
    "sg:postcode":"96003",
    "sg:province":"CA",
    "sg:tags":[
        "commercial",
        "storage"
    ],
    "wof:name":"Nor Cal Storage",
    "wof:placetype":"venue"
},
  "geometry": {"coordinates":[-122.30449900000001,40.567291],"type":"Point"}
}