{
  "type": "Feature",
  "properties": {
    "iso:country":"US",
    "sg:address":"991 N Blackstone St",
    "sg:city":"Tulare",
    "sg:classifiers":[
        {
            "category":"Travel",
            "subcategory":"Travel Agent",
            "type":"Entertainment"
        }
    ],
    "sg:phone":"+1 559 685 8000",
    "sg:postcode":"93274",
    "sg:province":"CA",
    "sg:tags":[
        "agency",
        "bureau"
    ],
    "sg:website":"www.extravel.net",
    "wof:name":"Executive Travel",
    "wof:placetype":"venue"
},
  "geometry": {"coordinates":[-119.33103300000001,36.218026],"type":"Point"}
}