{
  "type": "Feature",
  "properties": {
    "addr:full":"25269 The Old Rd Stevenson Ranch CA 91381",
    "addr:housenumber":"25269",
    "addr:postcode":"91381",
    "addr:street":"The Old Rd",
    "iso:country":"US",
    "sg:address":"25269 The Old Rd",
    "sg:city":"Stevenson Ranch",
    "sg:classifiers":[
        {
            "category":"Banks & Credit Unions",
            "subcategory":"Bank",
            "type":"Services"
        }
    ],
    "sg:phone":"+1 661 222 9577",
    "sg:postcode":"91381",
    "sg:province":"CA",
    "sg:tags":[
        "depository",
        "banking"
    ],
    "wof:name":"Fidelity National",
    "wof:placetype":"venue"
},
  "geometry": {"coordinates":[-118.564273,34.375772],"type":"Point"}
}