{
  "type": "Feature",
  "properties": {
    "addr:full":"1708 Castilla Way Modesto CA 95355",
    "addr:housenumber":"1708",
    "addr:postcode":"ca 95355",
    "addr:street":"Castilla Way",
    "iso:country":"US",
    "sg:address":"1708 Castilla Way",
    "sg:city":"Modesto",
    "sg:classifiers":[
        {
            "category":"Professional",
            "type":"Services"
        }
    ],
    "sg:phone":"+1 209 524 9126",
    "sg:postcode":"95355",
    "sg:province":"CA",
    "wof:name":"Urmila Ram",
    "wof:placetype":"venue"
},
  "geometry": {"coordinates":[-120.967506,37.683067],"type":"Point"}
}