{
  "type": "Feature",
  "properties": {
    "addr:full":"1456 Countryview Ln Vista CA 92081",
    "addr:housenumber":"1456",
    "addr:postcode":"92081",
    "addr:street":"Countryview Ln",
    "iso:country":"US",
    "sg:address":"1456 Countryview Ln",
    "sg:city":"Vista",
    "sg:classifiers":[
        {
            "category":"Building & Trades",
            "subcategory":"Landscaping Services",
            "type":"Services"
        }
    ],
    "sg:phone":"+1 760 598 6399",
    "sg:postcode":"92081",
    "sg:province":"CA",
    "sg:tags":[
        "landscape"
    ],
    "wof:name":"Denlawn",
    "wof:placetype":"venue"
},
  "geometry": {"coordinates":[-117.240245,33.164599],"type":"Point"}
}