{
  "type": "Feature",
  "properties": {
    "addr:full":"783 Devonshire Way Sunnyvale CA 94087",
    "addr:housenumber":"783",
    "addr:postcode":"94087",
    "addr:street":"Devonshire Way",
    "iso:country":"US",
    "sg:address":"783 Devonshire Way",
    "sg:city":"Sunnyvale",
    "sg:classifiers":[
        {
            "category":"Wholesale",
            "subcategory":"Non-durable Goods",
            "type":"Manufacturing & Wholesale Goods"
        }
    ],
    "sg:phone":"+1 408 737 2441",
    "sg:postcode":"94087",
    "sg:province":"CA",
    "wof:name":"Jr Imports",
    "wof:placetype":"venue"
},
  "geometry": {"coordinates":[-122.018401,37.346055],"type":"Point"}
}