{
  "type": "Feature",
  "properties": {
    "iso:country":"US",
    "sg:address":"140 Dominga Avenue",
    "sg:city":"Fairfax",
    "sg:classifiers":[
        {
            "category":"Professional",
            "subcategory":"Management & Consulting",
            "type":"Services"
        }
    ],
    "sg:postcode":"94930",
    "sg:province":"CA",
    "sg:tags":[
        "mac-help--mac-support",
        "onsite-service",
        "apple-consulting",
        "mac-consulting",
        "mac-tech-support",
        "macintosh-service",
        "marin-county",
        "san-francisco",
        "oregon",
        "eugene-oregon",
        "san-diego",
        "los-angeles",
        "portland-oregon",
        "adam-pettit",
        "ross-commins"
    ],
    "wof:name":"AMP Consulting",
    "wof:placetype":"venue"
},
  "geometry": {"coordinates":[-122.591037,37.983481],"type":"Point"}
}