{
  "type": "Feature",
  "properties": {
    "addr:full":"73 Horton Plz San Diego CA 92101",
    "addr:housenumber":"73",
    "addr:postcode":"92101",
    "addr:street":"Horton Plz",
    "iso:country":"US",
    "sg:address":"73 Horton Plz",
    "sg:city":"San Diego",
    "sg:classifiers":[
        {
            "category":"Restaurant",
            "type":"Food & Drink"
        }
    ],
    "sg:menulink":"http://www.allmenus.com/ca/san-diego/135650-jamba-juice/menu/",
    "sg:phone":"+1 619 615 1070",
    "sg:postcode":"92101",
    "sg:province":"CA",
    "sg:tags":[
        "smoothy",
        "juice",
        "american"
    ],
    "wof:name":"Jamba Juice",
    "wof:placetype":"venue"
},
  "geometry": {"coordinates":[-117.163417,32.713227],"type":"Point"}
}