{
  "type": "Feature",
  "properties": {
    "addr:full":"1270 Grand Ave Arroyo Grande CA 93420",
    "addr:housenumber":"1270",
    "addr:postcode":"93420",
    "addr:street":"Grand Ave",
    "iso:country":"US",
    "sg:address":"1270 Grand Ave",
    "sg:city":"Arroyo Grande",
    "sg:classifiers":[
        {
            "category":"Autos & Motor Vehicles",
            "subcategory":"Auto Supplies",
            "type":"Retail Goods"
        }
    ],
    "sg:phone":"+1 805 473 1337",
    "sg:postcode":"93420",
    "sg:province":"CA",
    "sg:tags":[
        "tire"
    ],
    "wof:name":"Santa Maria Tire Inc",
    "wof:placetype":"venue"
},
  "geometry": {"coordinates":[-120.602498,35.120691],"type":"Point"}
}