{
  "type": "Feature",
  "properties": {
    "iso:country":"US",
    "sg:address":"5393 Fetlock Ave",
    "sg:city":"Fontana",
    "sg:classifiers":[
        {
            "category":"Professional",
            "subcategory":"Management & Consulting",
            "type":"Services"
        }
    ],
    "sg:phone":"+1 909 463 1141",
    "sg:postcode":"92336",
    "sg:province":"CA",
    "sg:tags":[
        "marketing",
        "consultant"
    ],
    "wof:name":"Forbella Marketing & Consult",
    "wof:placetype":"venue"
},
  "geometry": {"coordinates":[-117.487476,34.155335],"type":"Point"}
}