{
  "type": "Feature",
  "properties": {
    "addr:full":"2019 17th St San Francisco CA 94103",
    "addr:housenumber":"2019",
    "addr:postcode":"94103",
    "addr:street":"17Th St",
    "iso:country":"US",
    "sg:address":"2019 17th St",
    "sg:city":"San Francisco",
    "sg:classifiers":[
        {
            "category":"Professional",
            "subcategory":"Accounting & Tax Preparation",
            "type":"Services"
        }
    ],
    "sg:phone":"+1 415 621 8956",
    "sg:postcode":"94103",
    "sg:province":"CA",
    "sg:tags":[
        "return",
        "filing"
    ],
    "sg:website":"www.axfar.com",
    "wof:name":"Axelrod & Farley",
    "wof:placetype":"venue"
},
  "geometry": {"coordinates":[-122.404349,37.764599],"type":"Point"}
}