{
  "type": "Feature",
  "properties": {
    "iso:country":"US",
    "sg:address":"1550 Chestnut St",
    "sg:city":"Susanville",
    "sg:classifiers":[
        {
            "category":"Building & Trades",
            "subcategory":"Equipment Rental",
            "type":"Services"
        }
    ],
    "sg:phone":"+1 530 257 4134",
    "sg:postcode":"96130",
    "sg:province":"CA",
    "sg:tags":[
        "yard"
    ],
    "wof:name":"United Rentals",
    "wof:placetype":"venue"
},
  "geometry": {"coordinates":[-120.649653,40.42399],"type":"Point"}
}