{
  "type": "Feature",
  "properties": {
    "addr:full":"3350 Market St San Diego CA 92102",
    "addr:housenumber":"3350",
    "addr:postcode":"92102",
    "addr:street":"Market St",
    "iso:country":"US",
    "sg:address":"3350 Market St",
    "sg:city":"San Diego",
    "sg:classifiers":[
        {
            "category":"Social Services",
            "subcategory":"Job Training",
            "type":"Services"
        }
    ],
    "sg:phone":"+1 619 338 0813",
    "sg:postcode":"92102",
    "sg:province":"CA",
    "sg:tags":[
        "career",
        "counseling",
        "vocational"
    ],
    "wof:name":"Career College Of San Diego",
    "wof:placetype":"venue"
},
  "geometry": {"coordinates":[-117.121593,32.711823],"type":"Point"}
}