{
  "type": "Feature",
  "properties": {
    "addr:full":"2021 The Alameda San Jose CA 95126",
    "addr:housenumber":"2021",
    "addr:postcode":"95126",
    "addr:street":"The Alameda",
    "iso:country":"US",
    "sg:address":"2021 The Alameda",
    "sg:city":"San Jose",
    "sg:classifiers":[
        {
            "category":"Professional",
            "subcategory":"Lawyer & Legal Services",
            "type":"Services"
        }
    ],
    "sg:phone":"+1 408 296 3816",
    "sg:postcode":"95126",
    "sg:province":"CA",
    "sg:tags":[
        "attorney"
    ],
    "wof:name":"Patrick E Standifer",
    "wof:placetype":"venue"
},
  "geometry": {"coordinates":[-121.926802,37.342809],"type":"Point"}
}