{
  "type": "Feature",
  "properties": {
    "addr:full":"669 Burning Tree Way Lompoc CA 93436",
    "addr:housenumber":"669",
    "addr:postcode":"93436",
    "addr:street":"Burning Tree Way",
    "iso:country":"US",
    "sg:address":"669 Burning Tree Way",
    "sg:city":"Lompoc",
    "sg:classifiers":[
        {
            "category":"Social Services",
            "subcategory":"Adult Care",
            "type":"Services"
        }
    ],
    "sg:phone":"+1 805 733 0112",
    "sg:postcode":"93436",
    "sg:province":"CA",
    "sg:tags":[
        "info",
        "life",
        "retirement"
    ],
    "wof:name":"Simmons Residential Care",
    "wof:placetype":"venue"
},
  "geometry": {"coordinates":[-120.45199599999999,34.712775],"type":"Point"}
}