{
  "type": "Feature",
  "properties": {
    "addr:full":"500 Sierra Point Pkwy Brisbane CA 94005",
    "addr:housenumber":"500",
    "addr:postcode":"94005",
    "addr:street":"Sierra Point Pkwy",
    "iso:country":"US",
    "sg:address":"500 Sierra Point Pkwy",
    "sg:city":"Brisbane",
    "sg:classifiers":[
        {
            "category":"Social Services",
            "type":"Services"
        },
        {
            "category":"Professional",
            "subcategory":"Employment Agencies",
            "type":"Services"
        },
        {
            "category":"Organizations",
            "subcategory":"Community Association",
            "type":"Services"
        }
    ],
    "sg:phone":"+1 650 952 0651",
    "sg:postcode":"94005",
    "sg:province":"CA",
    "sg:tags":[
        "club",
        "workers'",
        "placement",
        "volunteer"
    ],
    "wof:name":"Sierra Point Yacht Club",
    "wof:placetype":"venue"
},
  "geometry": {"coordinates":[-122.382514,37.674031],"type":"Point"}
}