{
  "type": "Feature",
  "properties": {
    "iso:country":"US",
    "sg:address":"7 Laguna Point Rd",
    "sg:city":"Chico",
    "sg:classifiers":[
        {
            "category":"Building & Trades",
            "subcategory":"Plumbing",
            "type":"Services"
        }
    ],
    "sg:phone":"+1 530 891 4420",
    "sg:postcode":"95928",
    "sg:province":"CA",
    "sg:tags":[
        "tank",
        "septic"
    ],
    "wof:name":"Hydrotec Solutions",
    "wof:placetype":"venue"
},
  "geometry": {"coordinates":[-121.788502,39.750754],"type":"Point"}
}