{
  "type": "Feature",
  "properties": {
    "iso:country":"US",
    "sg:address":"1100 Wall St",
    "sg:city":"La Jolla",
    "sg:classifiers":[
        {
            "category":"Shopping",
            "subcategory":"Clothing, Apparel, & Fashions",
            "type":"Retail Goods"
        }
    ],
    "sg:phone":"+1 858 551 8686",
    "sg:postcode":"92037",
    "sg:province":"CA",
    "sg:tags":[
        "furnishing"
    ],
    "sg:website":"www.tommybahama.com",
    "wof:name":"Tommy Bahama-LA Jolla",
    "wof:placetype":"venue"
},
  "geometry": {"coordinates":[-117.272683,32.847066],"type":"Point"}
}