{
  "type": "Feature",
  "properties": {
    "iso:country":"US",
    "sg:address":"360 Post St Ste 704",
    "sg:city":"San Francisco",
    "sg:classifiers":[
        {
            "category":"Health Services",
            "subcategory":"Dentist",
            "type":"Services"
        }
    ],
    "sg:phone":"+1 415 433 0119",
    "sg:postcode":"94108",
    "sg:province":"CA",
    "sg:website":"www.sfgreendentist.com",
    "wof:name":"Green Dentistry",
    "wof:placetype":"venue"
},
  "geometry": {"coordinates":[-122.407737,37.788353],"type":"Point"}
}