{
  "type": "Feature",
  "properties": {
    "addr:full":"1148 S Main Ave Fallbrook CA 92028",
    "addr:housenumber":"1148",
    "addr:postcode":"92028",
    "addr:street":"S Main Ave",
    "iso:country":"US",
    "sg:address":"1148 S Main Ave",
    "sg:city":"Fallbrook",
    "sg:classifiers":[
        {
            "category":"Retail",
            "subcategory":"Car Wash",
            "type":"Services"
        }
    ],
    "sg:phone":"+1 760 723 2998",
    "sg:postcode":"92028",
    "sg:province":"CA",
    "sg:tags":[
        "polishing",
        "washing"
    ],
    "wof:name":"Hands On Car Wash",
    "wof:placetype":"venue"
},
  "geometry": {"coordinates":[-117.251411,33.373202],"type":"Point"}
}