{
  "type": "Feature",
  "properties": {
    "addr:full":"95 Goldenrod Irvine CA 92614",
    "addr:housenumber":"95",
    "addr:postcode":"92614",
    "addr:street":"Goldenrod",
    "iso:country":"US",
    "sg:address":"95 Goldenrod",
    "sg:city":"Irvine",
    "sg:classifiers":[
        {
            "category":"Building & Trades",
            "subcategory":"Construction",
            "type":"Services"
        }
    ],
    "sg:phone":"+1 949 552 8400",
    "sg:postcode":"92614",
    "sg:province":"CA",
    "sg:tags":[
        "painter"
    ],
    "wof:name":"Sky Painting",
    "wof:placetype":"venue"
},
  "geometry": {"coordinates":[-117.79882499999999,33.671692],"type":"Point"}
}