{
  "type": "Feature",
  "properties": {
    "addr:full":"674 10th St Oakland CA 94607",
    "addr:housenumber":"674",
    "addr:postcode":"94607",
    "addr:street":"10Th St",
    "iso:country":"US",
    "sg:address":"674 10th St",
    "sg:city":"Oakland",
    "sg:classifiers":[
        {
            "category":"Professional",
            "subcategory":"Employment Agencies",
            "type":"Services"
        }
    ],
    "sg:phone":"+1 510 282 4852",
    "sg:postcode":"94607",
    "sg:province":"CA",
    "sg:tags":[
        "opportunity"
    ],
    "wof:name":"Our Family Friend",
    "wof:placetype":"venue"
},
  "geometry": {"coordinates":[-122.27818600000001,37.803735],"type":"Point"}
}