{
  "type": "Feature",
  "properties": {
    "addr:full":"344 Percy Ave Yuba City CA 95991",
    "addr:housenumber":"344",
    "addr:postcode":"95991",
    "addr:street":"Percy Ave",
    "iso:country":"US",
    "sg:address":"344 Percy Ave",
    "sg:city":"Yuba City",
    "sg:classifiers":[
        {
            "category":"Personal",
            "subcategory":"Beauty Salon",
            "type":"Services"
        }
    ],
    "sg:phone":"+1 530 671 0433",
    "sg:postcode":"95991",
    "sg:province":"CA",
    "wof:name":"Golden Comb",
    "wof:placetype":"venue"
},
  "geometry": {"coordinates":[-121.616298,39.129433],"type":"Point"}
}