{
  "type": "Feature",
  "properties": {
    "addr:full":"792 Nevada St Exd Nevada City CA 95959",
    "addr:housenumber":"792",
    "addr:postcode":"95959",
    "addr:street":"Nevada St Exd",
    "iso:country":"US",
    "sg:address":"792 Nevada St Exd",
    "sg:city":"Nevada City",
    "sg:classifiers":[
        {
            "category":"Manufacturing",
            "subcategory":"Building Materials",
            "type":"Manufacturing & Wholesale Goods"
        }
    ],
    "sg:phone":"+1 530 265 3268",
    "sg:postcode":"95959",
    "sg:province":"CA",
    "wof:name":"Cutting Edge",
    "wof:placetype":"venue"
},
  "geometry": {"coordinates":[-121.010952,39.270379],"type":"Point"}
}