{
  "type": "Feature",
  "properties": {
    "addr:full":"1467 Pine St San Francisco CA 94109",
    "addr:housenumber":"1467",
    "addr:postcode":"94109",
    "addr:street":"Pine St",
    "iso:country":"US",
    "sg:address":"1467 Pine St",
    "sg:city":"San Francisco",
    "sg:classifiers":[
        {
            "category":"Sports & Exercise",
            "subcategory":"Gym",
            "type":"Entertainment"
        }
    ],
    "sg:phone":"+1 415 346 7121",
    "sg:postcode":"94109",
    "sg:province":"CA",
    "sg:tags":[
        "personal",
        "trainer"
    ],
    "wof:name":"Norman Lin's SF Tae KWON Do",
    "wof:placetype":"venue"
},
  "geometry": {"coordinates":[-122.419603,37.789687],"type":"Point"}
}