{
  "type": "Feature",
  "properties": {
    "iso:country":"US",
    "sg:address":"1050 Essex St",
    "sg:city":"San Diego",
    "sg:classifiers":[
        {
            "category":"Real Estate",
            "subcategory":"Real Estate Operator",
            "type":"Services"
        }
    ],
    "sg:phone":"+1 619 294 4146",
    "sg:postcode":"92103",
    "sg:province":"CA",
    "sg:tags":[
        "apartment"
    ],
    "wof:name":"Hillcrest Regency",
    "wof:placetype":"venue"
},
  "geometry": {"coordinates":[-117.153892,32.747523],"type":"Point"}
}