{
  "type": "Feature",
  "properties": {
    "iso:country":"US",
    "sg:address":"3 Curtola Pkwy",
    "sg:city":"Vallejo",
    "sg:classifiers":[
        {
            "category":"Farming",
            "subcategory":"Fish & Marine Products",
            "type":"Manufacturing & Wholesale Goods"
        },
        {
            "category":"Recreation",
            "subcategory":"Fishing",
            "type":"Entertainment"
        }
    ],
    "sg:phone":"+1 707 642 4330",
    "sg:postcode":"94590",
    "sg:province":"CA",
    "sg:tags":[
        "tackle",
        "fishermen's",
        "bait",
        "supply"
    ],
    "wof:name":"Norm's Bait & Tackle",
    "wof:placetype":"venue"
},
  "geometry": {"coordinates":[-122.258268,38.097169],"type":"Point"}
}