{
  "type": "Feature",
  "properties": {
    "addr:full":"2801 Alton Pkwy. Irvine CA 92606",
    "addr:housenumber":"2801",
    "addr:postcode":"92606",
    "addr:street":"Alton Pkwy.",
    "iso:country":"US",
    "sg:address":"2801 Alton Pkwy.",
    "sg:city":"Irvine",
    "sg:classifiers":[
        {
            "category":"Real Estate",
            "subcategory":"Real Estate Operator",
            "type":"Services"
        }
    ],
    "sg:phone":"+1 949 724 1722",
    "sg:postcode":"92606",
    "sg:province":"CA",
    "sg:tags":[
        "apartment"
    ],
    "sg:website":"www.sheaapartments.com",
    "wof:name":"Calypso Apartments & Lofts",
    "wof:placetype":"venue"
},
  "geometry": {"coordinates":[-117.831936,33.688386],"type":"Point"}
}