{
  "type": "Feature",
  "properties": {
    "addr:full":"9841 Mason Ave Chatsworth CA 91311",
    "addr:housenumber":"9841",
    "addr:postcode":"91311",
    "addr:street":"Mason Ave",
    "iso:country":"US",
    "sg:address":"9841 Mason Ave",
    "sg:city":"Chatsworth",
    "sg:classifiers":[
        {
            "category":"Utilities",
            "subcategory":"Telephone",
            "type":"Services"
        },
        {
            "category":"Manufacturing",
            "subcategory":"Electronics",
            "type":"Manufacturing & Wholesale Goods"
        },
        {
            "category":"Communications",
            "type":"Services"
        },
        {
            "category":"Communications",
            "subcategory":"Television Station",
            "type":"Services"
        }
    ],
    "sg:phone":"+1 818 882 9900",
    "sg:postcode":"91311",
    "sg:province":"CA",
    "sg:tags":[
        "satellite",
        "telecommunications-equipment",
        "cable",
        "systems-repair",
        "supply",
        "consultant",
        "system",
        "equipment"
    ],
    "wof:name":"Don Mcdermott Communications Inc.",
    "wof:placetype":"venue"
},
  "geometry": {"coordinates":[-118.579798,34.249008],"type":"Point"}
}