{
  "type": "Feature",
  "properties": {
    "addr:full":"12250 el Camino Real San Diego CA 92130",
    "addr:housenumber":"12250",
    "addr:postcode":"92130",
    "addr:street":"El Camino Real",
    "iso:country":"US",
    "sg:address":"12250 el Camino Real",
    "sg:city":"San Diego",
    "sg:classifiers":[
        {
            "category":"Banks & Credit Unions",
            "subcategory":"Investment Brokerage",
            "type":"Services"
        }
    ],
    "sg:phone":"+1 858 509 4744",
    "sg:postcode":"92130",
    "sg:province":"CA",
    "sg:tags":[
        "consultant",
        "financing"
    ],
    "wof:name":"Shepherd Ventures",
    "wof:placetype":"venue"
},
  "geometry": {"coordinates":[-117.23800799999999,32.927625],"type":"Point"}
}