{
  "type": "Feature",
  "properties": {
    "iso:country":"US",
    "sg:address":"3425 Coffee Rd # A2",
    "sg:city":"Modesto",
    "sg:classifiers":[
        {
            "category":"Health Services",
            "subcategory":"Doctor",
            "type":"Services"
        }
    ],
    "sg:phone":"+1 209 204 8942",
    "sg:postcode":"95355",
    "sg:province":"CA",
    "sg:tags":[
        "physician",
        "surgeon"
    ],
    "wof:name":"Popli, Gagandeep S, Do - Psychiatric Medical Group",
    "wof:placetype":"venue"
},
  "geometry": {"coordinates":[-120.97607499999999,37.687814],"type":"Point"}
}