{
  "type": "Feature",
  "properties": {
    "iso:country":"US",
    "sg:address":"3523 5th Ave",
    "sg:city":"San Diego",
    "sg:classifiers":[
        {
            "category":"Personal",
            "type":"Services"
        }
    ],
    "sg:phone":"+1 619 788 9756",
    "sg:postcode":"92103",
    "sg:province":"CA",
    "sg:tags":[
        "sewing",
        "alteration"
    ],
    "wof:name":"Tailor Love",
    "wof:placetype":"venue"
},
  "geometry": {"coordinates":[-117.16025,32.741974],"type":"Point"}
}