{
  "type": "Feature",
  "properties": {
    "iso:country":"US",
    "sg:address":"1550 Bryant St",
    "sg:city":"San Francisco",
    "sg:classifiers":[
        {
            "category":"Professional",
            "subcategory":"Research",
            "type":"Services"
        }
    ],
    "sg:phone":"+1 415 522 5400",
    "sg:postcode":"94103",
    "sg:province":"CA",
    "sg:website":"www.harderco.com",
    "wof:name":"Harder & Co Community Research",
    "wof:placetype":"venue"
},
  "geometry": {"coordinates":[-122.41073299999999,37.767548],"type":"Point"}
}