{
  "type": "Feature",
  "properties": {
    "iso:country":"US",
    "sg:address":"6329 Van Nuys Blvd",
    "sg:city":"Van Nuys",
    "sg:classifiers":[
        {
            "category":"Shopping",
            "subcategory":"Used Merchandise",
            "type":"Retail Goods"
        }
    ],
    "sg:phone":"+1 818 787 6211",
    "sg:postcode":"91401",
    "sg:province":"CA",
    "sg:tags":[
        "pawnbroker"
    ],
    "wof:name":"K & K Internatl",
    "wof:placetype":"venue"
},
  "geometry": {"coordinates":[-118.448788,34.184781],"type":"Point"}
}