{
  "type": "Feature",
  "properties": {
    "iso:country":"US",
    "sg:address":"5190 Governor Drive",
    "sg:city":"San Diego",
    "sg:classifiers":[
        {
            "category":"Professional",
            "subcategory":"Accounting & Tax Preparation",
            "type":"Services"
        }
    ],
    "sg:phone":"+1 858 457 5252",
    "sg:postcode":"92122",
    "sg:province":"CA",
    "sg:tags":[
        "accountant"
    ],
    "wof:name":"Sonnenberg & Company Cpas",
    "wof:placetype":"venue"
},
  "geometry": {"coordinates":[-117.18525200000001,32.857109],"type":"Point"}
}