{
  "type": "Feature",
  "properties": {
    "iso:country":"US",
    "sg:address":"1300 S Soto St",
    "sg:city":"Los Angeles",
    "sg:classifiers":[
        {
            "category":"Manufacturing",
            "subcategory":"Printing",
            "type":"Manufacturing & Wholesale Goods"
        }
    ],
    "sg:phone":"+1 213 312 9000",
    "sg:postcode":"90023",
    "sg:province":"CA",
    "sg:tags":[
        "newspaper"
    ],
    "wof:name":"Siglo Xxi",
    "wof:placetype":"venue"
},
  "geometry": {"coordinates":[-118.219711,34.025552],"type":"Point"}
}