{
  "type": "Feature",
  "properties": {
    "iso:country":"US",
    "sg:address":"13201 Ryans Way",
    "sg:city":"Lakeside",
    "sg:classifiers":[
        {
            "category":"Manufacturing",
            "subcategory":"Textiles",
            "type":"Manufacturing & Wholesale Goods"
        }
    ],
    "sg:phone":"+1 619 390 0558",
    "sg:postcode":"92040",
    "sg:province":"CA",
    "sg:tags":[
        "mill",
        "knit",
        "outerwear"
    ],
    "wof:name":"Rude Gear",
    "wof:placetype":"venue"
},
  "geometry": {"coordinates":[-116.905222,32.841806],"type":"Point"}
}