{
  "type": "Feature",
  "properties": {
    "iso:country":"US",
    "sg:address":"14030 Gannet St",
    "sg:city":"Santa Fe Springs",
    "sg:classifiers":[
        {
            "category":"Wholesale",
            "subcategory":"Durable Goods & Equipment",
            "type":"Manufacturing & Wholesale Goods"
        }
    ],
    "sg:phone":"+1 562 921 0444",
    "sg:postcode":"90670",
    "sg:province":"CA",
    "sg:tags":[
        "exporter"
    ],
    "sg:website":"www.southlandpolymers.com",
    "wof:name":"Southland Polymers",
    "wof:placetype":"venue"
},
  "geometry": {"coordinates":[-118.034198,33.895585],"type":"Point"}
}