{
  "type": "Feature",
  "properties": {
    "iso:country":"US",
    "sg:address":"111 W 7th St",
    "sg:city":"Los Angeles",
    "sg:classifiers":[
        {
            "category":"Shopping",
            "subcategory":"Florist",
            "type":"Retail Goods"
        }
    ],
    "sg:phone":"+1 661 904 4455",
    "sg:postcode":"90014",
    "sg:province":"CA",
    "sg:website":"primarypetals.carbonmade.com",
    "wof:name":"Primary Petals",
    "wof:placetype":"venue"
},
  "geometry": {"coordinates":[-118.251253,34.044496],"type":"Point"}
}