{
  "type": "Feature",
  "properties": {
    "iso:country":"US",
    "sg:address":"105 E 5th St",
    "sg:city":"San Bernardino",
    "sg:classifiers":[
        {
            "category":"Retail",
            "subcategory":"Auto Repair",
            "type":"Services"
        }
    ],
    "sg:phone":"+1 909 386 2581",
    "sg:postcode":"92410",
    "sg:province":"CA",
    "sg:tags":[
        "automobile",
        "smog"
    ],
    "wof:name":"Ultra Mar Smog",
    "wof:placetype":"venue"
},
  "geometry": {"coordinates":[-117.284459,34.108319],"type":"Point"}
}