{
  "type": "Feature",
  "properties": {
    "addr:full":"520 Waller St San Francisco CA 94117",
    "addr:housenumber":"520",
    "addr:postcode":"94117",
    "addr:street":"Waller St",
    "iso:country":"US",
    "sg:address":"520 Waller St",
    "sg:city":"San Francisco",
    "sg:classifiers":[
        {
            "category":"Personal",
            "subcategory":"Beauty Salon",
            "type":"Services"
        }
    ],
    "sg:phone":"+1 415 621 8789",
    "sg:postcode":"94117",
    "sg:province":"CA",
    "wof:name":"Hairdoo Voodoo",
    "wof:placetype":"venue"
},
  "geometry": {"coordinates":[-122.432423,37.770984],"type":"Point"}
}