{
  "type": "Feature",
  "properties": {
    "iso:country":"US",
    "sg:address":"11441 Atlantic Ave",
    "sg:city":"Lynwood",
    "sg:classifiers":[
        {
            "category":"Real Estate",
            "subcategory":"Real Estate Services",
            "type":"Services"
        },
        {
            "category":"Real Estate",
            "subcategory":"Real Estate Agent",
            "type":"Services"
        }
    ],
    "sg:phone":"+1 310 637 9555",
    "sg:postcode":"90262",
    "sg:province":"CA",
    "sg:tags":[
        "buyer",
        "consultant",
        "broker"
    ],
    "wof:name":"Millenium 2000 Service",
    "wof:placetype":"venue"
},
  "geometry": {"coordinates":[-118.187798,33.92052],"type":"Point"}
}