{
  "type": "Feature",
  "properties": {
    "iso:country":"US",
    "sg:address":"45445 Portola Ave",
    "sg:city":"Palm Desert",
    "sg:classifiers":[
        {
            "category":"Real Estate",
            "subcategory":"Real Estate Agent",
            "type":"Services"
        }
    ],
    "sg:phone":"+1 760 837 1300",
    "sg:postcode":"92260",
    "sg:province":"CA",
    "wof:name":"DLC Realty",
    "wof:placetype":"venue"
},
  "geometry": {"coordinates":[-116.373826,33.718362],"type":"Point"}
}