{
  "type": "Feature",
  "properties": {
    "addr:full":"5731 E Santa Ana Canyon Rd Anaheim CA 92807",
    "addr:housenumber":"5731",
    "addr:postcode":"92807",
    "addr:street":"E Santa Ana Canyon Rd",
    "iso:country":"US",
    "sg:address":"5731 E Santa Ana Canyon Rd",
    "sg:city":"Anaheim",
    "sg:classifiers":[
        {
            "category":"Banks & Credit Unions",
            "subcategory":"Bank",
            "type":"Services"
        }
    ],
    "sg:phone":"+1 800 933 3000",
    "sg:postcode":"92807",
    "sg:province":"CA",
    "wof:name":"Home Savings of America",
    "wof:placetype":"venue"
},
  "geometry": {"coordinates":[-117.789888,33.851402],"type":"Point"}
}