{
  "type": "Feature",
  "properties": {
    "iso:country":"US",
    "sg:address":"725 Burnett Ave Ste 3",
    "sg:city":"San Francisco",
    "sg:classifiers":[
        {
            "category":"Travel",
            "subcategory":"Travel Agent",
            "type":"Entertainment"
        }
    ],
    "sg:phone":"+1 888 836 3656",
    "sg:postcode":"94131",
    "sg:province":"CA",
    "sg:website":"www.iat-us.com",
    "wof:name":"IAT Air Travel",
    "wof:placetype":"venue"
},
  "geometry": {"coordinates":[-122.445246,37.750653],"type":"Point"}
}