{
  "type": "Feature",
  "properties": {
    "iso:country":"US",
    "sg:address":"4227 Tierra Rejada Rd",
    "sg:city":"Moorpark",
    "sg:classifiers":[
        {
            "category":"Restaurant",
            "type":"Food & Drink"
        }
    ],
    "sg:phone":"+1 805 530 1555",
    "sg:postcode":"93021",
    "sg:province":"CA",
    "wof:name":"Sunset Terrace Restaurant",
    "wof:placetype":"venue"
},
  "geometry": {"coordinates":[-118.89721,34.26828],"type":"Point"}
}