{
  "type": "Feature",
  "properties": {
    "addr:full":"2862 21st Street San Francisco CA 94110",
    "addr:housenumber":"2862",
    "addr:postcode":"94110",
    "addr:street":"21St Street",
    "iso:country":"US",
    "sg:address":"2862 21st Street",
    "sg:city":"San Francisco",
    "sg:classifiers":[
        {
            "category":"Health Services",
            "subcategory":"Optometrist",
            "type":"Services"
        }
    ],
    "sg:phone":"+1 415 658 5333",
    "sg:postcode":"94110",
    "sg:province":"CA",
    "sg:tags":[
        "eye",
        "laser",
        "surgery/lasik"
    ],
    "wof:name":"Frankie Rodriguez",
    "wof:placetype":"venue"
},
  "geometry": {"coordinates":[-122.411849,37.757689],"type":"Point"}
}