{
  "type": "Feature",
  "properties": {
    "iso:country":"US",
    "sg:address":"10774 Jefferson Blvd",
    "sg:city":"Culver City",
    "sg:classifiers":[
        {
            "category":"Personal",
            "subcategory":"Shoe Repair & Shine",
            "type":"Services"
        }
    ],
    "sg:phone":"+1 310 559 4560",
    "sg:postcode":"90230",
    "sg:province":"CA",
    "wof:name":"Instant Shoe Repair",
    "wof:placetype":"venue"
},
  "geometry": {"coordinates":[-118.394997,34.002201],"type":"Point"}
}