{
  "type": "Feature",
  "properties": {
    "addr:full":"4847 Stratos Way Modesto CA 95356",
    "addr:postcode":"4847;ca 95356",
    "addr:street":"Stratos Way",
    "iso:country":"US",
    "sg:address":"4847 Stratos Way",
    "sg:city":"Modesto",
    "sg:classifiers":[
        {
            "category":"Sports & Exercise",
            "subcategory":"Gym",
            "type":"Entertainment"
        }
    ],
    "sg:phone":"+1 209 522 9309",
    "sg:postcode":"95356",
    "sg:province":"CA",
    "sg:tags":[
        "club",
        "health",
        "studio",
        "gymnasium"
    ],
    "wof:name":"Intersport Fitness Ctr",
    "wof:placetype":"venue"
},
  "geometry": {"coordinates":[-121.000277,37.709413],"type":"Point"}
}