{
  "type": "Feature",
  "properties": {
    "iso:country":"US",
    "sg:address":"8523 Lankershim Blvd",
    "sg:city":"Sun Valley",
    "sg:classifiers":[
        {
            "category":"Wholesale",
            "subcategory":"Machinery & Supplies",
            "type":"Manufacturing & Wholesale Goods"
        }
    ],
    "sg:phone":"+1 818 771 1691",
    "sg:postcode":"91352",
    "sg:province":"CA",
    "sg:tags":[
        "janitor"
    ],
    "wof:name":"Valley Janitorial Supplies",
    "wof:placetype":"venue"
},
  "geometry": {"coordinates":[-118.38785,34.222754],"type":"Point"}
}