{
  "type": "Feature",
  "properties": {
    "iso:country":"US",
    "sg:address":"315 16th St",
    "sg:city":"Sacramento",
    "sg:classifiers":[
        {
            "category":"Personal",
            "type":"Services"
        },
        {
            "category":"Shopping",
            "subcategory":"Used Merchandise",
            "type":"Retail Goods"
        }
    ],
    "sg:phone":"+1 916 448 0890",
    "sg:postcode":"95811",
    "sg:province":"CA",
    "sg:tags":[
        "vintage",
        "consignment",
        "local"
    ],
    "sg:website":"www.salvationarmyusa.org",
    "wof:name":"Salvation Army",
    "wof:placetype":"venue"
},
  "geometry": {"coordinates":[-121.481989,38.585527],"type":"Point"}
}