{
  "type": "Feature",
  "properties": {
    "addr:full":"45 Auto Center Dr Foothill Ranch CA 92610",
    "addr:housenumber":"45",
    "addr:postcode":"92610",
    "addr:street":"Auto Center Dr",
    "iso:country":"US",
    "sg:address":"45 Auto Center Dr",
    "sg:city":"Foothill Ranch",
    "sg:classifiers":[
        {
            "category":"Restaurant",
            "type":"Food & Drink"
        }
    ],
    "sg:menulink":"http://www.allmenus.com/ca/el-toro/155663-the-flame-broiler/menu/",
    "sg:phone":"+1 949 859 0100",
    "sg:postcode":"92610",
    "sg:province":"CA",
    "sg:tags":[
        "american"
    ],
    "wof:name":"The Flame Broiler",
    "wof:placetype":"venue"
},
  "geometry": {"coordinates":[-117.660072,33.674739],"type":"Point"}
}