{
  "type": "Feature",
  "properties": {
    "iso:country":"US",
    "sg:address":"1801 W Ave K",
    "sg:city":"Lancaster",
    "sg:classifiers":[
        {
            "category":"Shopping",
            "subcategory":"Computers & Home Electronics",
            "type":"Retail Goods"
        }
    ],
    "sg:phone":"+1 661 945 8140",
    "sg:postcode":"93534",
    "sg:province":"CA",
    "sg:tags":[
        "software"
    ],
    "sg:website":"www.realestatebottomline.com",
    "wof:name":"Turning Point Software",
    "wof:placetype":"venue"
},
  "geometry": {"coordinates":[-118.163467,34.674918],"type":"Point"}
}