{
  "type": "Feature",
  "properties": {
    "iso:country":"US",
    "sg:address":"1008 Huntington Dr",
    "sg:city":"San Marino",
    "sg:classifiers":[
        {
            "category":"Retail",
            "subcategory":"Laundry & Dry Cleaning",
            "type":"Services"
        }
    ],
    "sg:phone":"+1 626 300 8385",
    "sg:postcode":"91108",
    "sg:province":"CA",
    "wof:name":"Superior Dry Cleaners",
    "wof:placetype":"venue"
},
  "geometry": {"coordinates":[-118.125066,34.112917],"type":"Point"}
}