{
  "type": "Feature",
  "properties": {
    "iso:country":"US",
    "sg:address":"628 E Lincoln Ave",
    "sg:city":"Fresno",
    "sg:phone":"+1 559 268 4966",
    "sg:postcode":"93706",
    "sg:province":"CA",
    "sg:tags":[
        "irrigation",
        "system"
    ],
    "wof:name":"Drip Wrap Enterprises",
    "wof:placetype":"venue"
},
  "geometry": {"coordinates":[-119.780186,36.648847],"type":"Point"}
}