{
  "type": "Feature",
  "properties": {
    "iso:country":"US",
    "sg:address":"72333 Highway 111",
    "sg:city":"Palm Desert",
    "sg:classifiers":[
        {
            "category":"Health Services",
            "subcategory":"Doctor",
            "type":"Services"
        }
    ],
    "sg:phone":"+1 760 674 9666",
    "sg:postcode":"92260",
    "sg:province":"CA",
    "sg:tags":[
        "surgeon",
        "oral"
    ],
    "sg:website":"www.desertcrossingdental.com",
    "wof:name":"Parish Greg DDS",
    "wof:placetype":"venue"
},
  "geometry": {"coordinates":[-116.40300000000001,33.728199],"type":"Point"}
}