{
  "type": "Feature",
  "properties": {
    "addr:full":"35715 80th St E Littlerock CA 93543",
    "addr:housenumber":"35715",
    "addr:postcode":"littlerock ca 93543",
    "addr:street":"80Th St E",
    "iso:country":"US",
    "sg:address":"35715 80th St E",
    "sg:city":"Littlerock",
    "sg:classifiers":[
        {
            "category":"Wholesale",
            "subcategory":"Groceries",
            "type":"Manufacturing & Wholesale Goods"
        }
    ],
    "sg:phone":"+1 661 400 3563",
    "sg:postcode":"93543",
    "sg:province":"CA",
    "sg:tags":[
        "food",
        "products-wholesale"
    ],
    "wof:name":"Pacific West Marketing, Inc.",
    "wof:placetype":"venue"
},
  "geometry": {"coordinates":[-117.98812,34.530372],"type":"Point"}
}