{
  "type": "Feature",
  "properties": {
    "addr:full":"2501 Ladd Rd Modesto CA 95356",
    "addr:housenumber":"2501",
    "addr:postcode":"ca 95356",
    "addr:street":"Ladd Rd",
    "iso:country":"US",
    "sg:address":"2501 Ladd Rd",
    "sg:city":"Modesto",
    "sg:classifiers":[
        {
            "category":"Food & Beverages",
            "subcategory":"Bakery",
            "type":"Retail Goods"
        }
    ],
    "sg:phone":"+1 209 543 6777",
    "sg:postcode":"95356",
    "sg:province":"CA",
    "sg:tags":[
        "baker"
    ],
    "wof:name":"Tiers For Two",
    "wof:placetype":"venue"
},
  "geometry": {"coordinates":[-121.050466,37.732939],"type":"Point"}
}