{
  "type": "Feature",
  "properties": {
    "addr:full":"21803 Avalon Blvd Carson CA 90745",
    "addr:housenumber":"21803",
    "addr:postcode":"90745",
    "addr:street":"Avalon Blvd",
    "iso:country":"US",
    "sg:address":"21803 Avalon Blvd",
    "sg:city":"Carson",
    "sg:classifiers":[
        {
            "category":"Personal",
            "subcategory":"Beauty Salon",
            "type":"Services"
        }
    ],
    "sg:phone":"+1 310 835 4462",
    "sg:postcode":"90745",
    "sg:province":"CA",
    "sg:tags":[
        "hair",
        "stylist"
    ],
    "wof:name":"Haircare Oasis",
    "wof:placetype":"venue"
},
  "geometry": {"coordinates":[-118.26373599999999,33.830157],"type":"Point"}
}