{
  "type": "Feature",
  "properties": {
    "iso:country":"US",
    "sg:address":"21803 Avalon Blvd",
    "sg:city":"Carson",
    "sg:classifiers":[
        {
            "category":"Personal",
            "subcategory":"Beauty Salon",
            "type":"Services"
        }
    ],
    "sg:phone":"+1 310 835 4462",
    "sg:postcode":"90745",
    "sg:province":"CA",
    "sg:tags":[
        "hair",
        "stylist"
    ],
    "wof:name":"Haircare Oasis",
    "wof:placetype":"venue"
},
  "geometry": {"coordinates":[-118.263736,33.830157],"type":"Point"}
}