{
  "type": "Feature",
  "properties": {
    "addr:full":"9800 Corriente Rd Atascadero CA 93422",
    "addr:postcode":"9800;93422",
    "addr:street":"Corriente Rd",
    "iso:country":"US",
    "sg:address":"9800 Corriente Rd",
    "sg:city":"Atascadero",
    "sg:classifiers":[
        {
            "category":"Retail",
            "subcategory":"Animal Services",
            "type":"Services"
        }
    ],
    "sg:phone":"+1 805 466 7892",
    "sg:postcode":"93422",
    "sg:province":"CA",
    "sg:tags":[
        "pet",
        "boarding",
        "sitting"
    ],
    "wof:name":"Peg's Pet Care",
    "wof:placetype":"venue"
},
  "geometry": {"coordinates":[-120.71772199999999,35.493499],"type":"Point"}
}