{
  "type": "Feature",
  "properties": {
    "iso:country":"US",
    "sg:address":"3617 E Thousand Oaks Blvd",
    "sg:city":"Westlake Village",
    "sg:classifiers":[
        {
            "category":"Real Estate",
            "subcategory":"Real Estate Agent",
            "type":"Services"
        }
    ],
    "sg:phone":"+1 805 379 0102",
    "sg:postcode":"91362",
    "sg:province":"CA",
    "sg:tags":[
        "appraiser"
    ],
    "wof:name":"Blue Ribbon Appraisal",
    "wof:placetype":"venue"
},
  "geometry": {"coordinates":[-118.829224,34.164335],"type":"Point"}
}