{
  "type": "Feature",
  "properties": {
    "addr:full":"703 Pier Ave Hermosa Beach CA 90254",
    "addr:housenumber":"703",
    "addr:postcode":"90254",
    "addr:street":"Pier Ave",
    "iso:country":"US",
    "sg:address":"703 Pier Ave",
    "sg:city":"Hermosa Beach",
    "sg:classifiers":[
        {
            "category":"Wholesale",
            "subcategory":"Jewelry",
            "type":"Manufacturing & Wholesale Goods"
        }
    ],
    "sg:phone":"+1 310 372 0379",
    "sg:postcode":"90254",
    "sg:province":"CA",
    "sg:tags":[
        "watch"
    ],
    "wof:name":"Watches On TV",
    "wof:placetype":"venue"
},
  "geometry": {"coordinates":[-118.393388,33.864806],"type":"Point"}
}