{
  "type": "Feature",
  "properties": {
    "iso:country":"US",
    "sg:address":"2402 E Anaheim St",
    "sg:city":"Wilmington",
    "sg:classifiers":[
        {
            "category":"Manufacturing",
            "subcategory":"Petroleum Products",
            "type":"Manufacturing & Wholesale Goods"
        }
    ],
    "sg:phone":"+1 562 491 6877",
    "sg:postcode":"90744",
    "sg:province":"CA",
    "sg:tags":[
        "refinery",
        "oil"
    ],
    "wof:name":"Valero",
    "wof:placetype":"venue"
},
  "geometry": {"coordinates":[-118.2314,33.78179],"type":"Point"}
}