{
  "type": "Feature",
  "properties": {
    "iso:country":"US",
    "sg:address":"401 E 3rd Ave",
    "sg:city":"San Mateo",
    "sg:classifiers":[
        {
            "category":"Bars & Pubs",
            "subcategory":"Lounge",
            "type":"Food & Drink"
        }
    ],
    "sg:phone":"+1 650 347 1898",
    "sg:postcode":"94401",
    "sg:province":"CA",
    "sg:website":"www.gossipultralounge.com",
    "wof:name":"Gossip Ultralounge",
    "wof:placetype":"venue"
},
  "geometry": {"coordinates":[-122.321516,37.566148],"type":"Point"}
}