{
  "type": "Feature",
  "properties": {
    "iso:country":"US",
    "sg:address":"5199 Pacific Ave",
    "sg:city":"Long Beach",
    "sg:classifiers":[
        {
            "category":"Health Services",
            "subcategory":"Health Practitioner",
            "type":"Services"
        }
    ],
    "sg:phone":"+1 562 498 3379",
    "sg:postcode":"90805",
    "sg:province":"CA",
    "sg:tags":[
        "psychologist"
    ],
    "wof:name":"Michael J Kondas PHD",
    "wof:placetype":"venue"
},
  "geometry": {"coordinates":[-118.198059,33.849439],"type":"Point"}
}