{
  "type": "Feature",
  "properties": {
    "iso:country":"US",
    "sg:address":"605 Cll del Cerrito",
    "sg:city":"San Clemente",
    "sg:classifiers":[
        {
            "category":"Wholesale",
            "subcategory":"Hardware",
            "type":"Manufacturing & Wholesale Goods"
        }
    ],
    "sg:phone":"+1 949 366 9285",
    "sg:postcode":"92672",
    "sg:province":"CA",
    "sg:tags":[
        "equipment",
        "rep",
        "for",
        "supermarket",
        "mfg"
    ],
    "wof:name":"Market Systems Unlimited",
    "wof:placetype":"venue"
},
  "geometry": {"coordinates":[-117.59414099999999,33.411253],"type":"Point"}
}