{
  "type": "Feature",
  "properties": {
    "addr:full":"Mount Zion Gastroenterology 2330 Post St # 610 San Francisco CA 94115",
    "addr:housenumber":"2330",
    "addr:postcode":"94115",
    "addr:street":"Mount;Post St # 610",
    "iso:country":"US",
    "sg:address":"Mount Zion Gastroenterology 2330 Post St # 610",
    "sg:city":"San Francisco",
    "sg:classifiers":[
        {
            "category":"Health Services",
            "subcategory":"Doctor",
            "type":"Services"
        }
    ],
    "sg:phone":"+1 415 502 4444",
    "sg:postcode":"94115",
    "sg:province":"CA",
    "wof:name":"Jonathan Terdiman, MD",
    "wof:placetype":"venue"
},
  "geometry": {"coordinates":[-122.44041199999999,37.784511],"type":"Point"}
}