{
  "type": "Feature",
  "properties": {
    "iso:country":"US",
    "sg:address":"490 Airpark Rd",
    "sg:city":"Atwater",
    "sg:classifiers":[
        {
            "category":"Building & Trades",
            "subcategory":"Construction",
            "type":"Services"
        }
    ],
    "sg:phone":"+1 209 357 2159",
    "sg:postcode":"95301",
    "sg:province":"CA",
    "sg:tags":[
        "maker",
        "cabinet"
    ],
    "wof:name":"C R Cabinets",
    "wof:placetype":"venue"
},
  "geometry": {"coordinates":[-120.602359,37.33587],"type":"Point"}
}