{
  "type": "Feature",
  "properties": {
    "addr:full":"490 Airpark Rd Atwater CA 95301",
    "addr:housenumber":"490",
    "addr:postcode":"95301",
    "addr:street":"Airpark Rd",
    "iso:country":"US",
    "sg:address":"490 Airpark Rd",
    "sg:city":"Atwater",
    "sg:classifiers":[
        {
            "category":"Building & Trades",
            "subcategory":"Construction",
            "type":"Services"
        }
    ],
    "sg:phone":"+1 209 357 2159",
    "sg:postcode":"95301",
    "sg:province":"CA",
    "sg:tags":[
        "maker",
        "cabinet"
    ],
    "wof:name":"C R Cabinets",
    "wof:placetype":"venue"
},
  "geometry": {"coordinates":[-120.60235900000001,37.33587],"type":"Point"}
}