{
  "type": "Feature",
  "properties": {
    "addr:full":"24950 Via Florecer Mission Viejo CA 92692",
    "addr:housenumber":"24950",
    "addr:postcode":"92692",
    "addr:street":"Via Florecer",
    "iso:country":"US",
    "sg:address":"24950 Via Florecer",
    "sg:city":"Mission Viejo",
    "sg:classifiers":[
        {
            "category":"Autos & Motor Vehicles",
            "subcategory":"Auto Supplies",
            "type":"Retail Goods"
        }
    ],
    "sg:phone":"+1 949 454 6177",
    "sg:postcode":"92692",
    "sg:province":"CA",
    "sg:tags":[
        "glass"
    ],
    "wof:name":"Hanson's Auto Glass",
    "wof:placetype":"venue"
},
  "geometry": {"coordinates":[-117.655903,33.600599],"type":"Point"}
}