{
  "type": "Feature",
  "properties": {
    "addr:full":"13850 S Highway 101 Hopland CA 95449",
    "addr:housenumber":"13850",
    "addr:postcode":"95449",
    "addr:street":"S Highway 101",
    "iso:country":"US",
    "sg:address":"13850 S Highway 101",
    "sg:city":"Hopland",
    "sg:classifiers":[
        {
            "category":"Professional",
            "subcategory":"Engineering",
            "type":"Services"
        },
        {
            "category":"Building & Trades",
            "subcategory":"Construction",
            "type":"Services"
        }
    ],
    "sg:phone":"+1 707 744 1100",
    "sg:postcode":"95449",
    "sg:province":"CA",
    "sg:tags":[
        "consulting",
        "engineer",
        "contractor"
    ],
    "wof:name":"Richardson Engineering Contractors Inc.",
    "wof:placetype":"venue"
},
  "geometry": {"coordinates":[-123.11702,38.982695],"type":"Point"}
}