{
  "type": "Feature",
  "properties": {
    "iso:country":"US",
    "sg:address":"23441 S Pointe Dr",
    "sg:city":"Laguna Hills",
    "sg:classifiers":[
        {
            "category":"Health Services",
            "subcategory":"Doctor",
            "type":"Services"
        }
    ],
    "sg:phone":"+1 949 215 4099",
    "sg:postcode":"92653",
    "sg:province":"CA",
    "sg:tags":[
        "clinic"
    ],
    "wof:name":"Meier Clinics",
    "wof:placetype":"venue"
},
  "geometry": {"coordinates":[-117.721753,33.625464],"type":"Point"}
}