{
  "type": "Feature",
  "properties": {
    "iso:country":"US",
    "sg:address":"200 Clock Tower Pl Ste E150",
    "sg:city":"Carmel",
    "sg:classifiers":[
        {
            "category":"Banks & Credit Unions",
            "subcategory":"Financial Services",
            "type":"Services"
        }
    ],
    "sg:phone":"+1 831 625 9000",
    "sg:postcode":"93923",
    "sg:province":"CA",
    "sg:tags":[
        "broker",
        "mortgage"
    ],
    "wof:name":"CC & C Financial Corp",
    "wof:placetype":"venue"
},
  "geometry": {"coordinates":[-121.905473,36.539687],"type":"Point"}
}