{
  "type": "Feature",
  "properties": {
    "iso:country":"US",
    "sg:address":"8693 Wilshire Blvd",
    "sg:city":"Beverly Hills",
    "sg:classifiers":[
        {
            "category":"Health Services",
            "subcategory":"Medical Lab",
            "type":"Services"
        }
    ],
    "sg:phone":"+1 310 657 1077",
    "sg:postcode":"90211",
    "sg:province":"CA",
    "sg:tags":[
        "laboratory"
    ],
    "wof:name":"Immuno Sciences Lab Inc",
    "wof:placetype":"venue"
},
  "geometry": {"coordinates":[-118.38079,34.06637],"type":"Point"}
}