{
  "type": "Feature",
  "properties": {
    "addr:full":"207 W Chapman Ave Orange CA 92866",
    "addr:housenumber":"207",
    "addr:postcode":"92866",
    "addr:street":"W Chapman Ave",
    "iso:country":"US",
    "sg:address":"207 W Chapman Ave",
    "sg:city":"Orange",
    "sg:phone":"+1 714 639 2480",
    "sg:postcode":"92866",
    "sg:province":"CA",
    "wof:name":"Paul's Cocktails",
    "wof:placetype":"venue"
},
  "geometry": {"coordinates":[-117.85426699999999,33.787881],"type":"Point"}
}