{
  "type": "Feature",
  "properties": {
    "iso:country":"US",
    "sg:address":"6975 Cam Maquiladora",
    "sg:city":"San Diego",
    "sg:classifiers":[
        {
            "category":"Wholesale",
            "subcategory":"Machinery & Supplies",
            "type":"Manufacturing & Wholesale Goods"
        },
        {
            "category":"Wholesale",
            "subcategory":"Metals & Minerals",
            "type":"Manufacturing & Wholesale Goods"
        }
    ],
    "sg:phone":"+1 619 710 4255",
    "sg:postcode":"92154",
    "sg:province":"CA",
    "sg:tags":[
        "pipe",
        "fitting",
        "valve"
    ],
    "wof:name":"Pinnacle Industrial Supply Inc",
    "wof:placetype":"venue"
},
  "geometry": {"coordinates":[-116.992597,32.566899],"type":"Point"}
}