{
  "type": "Feature",
  "properties": {
    "addr:full":"11411 Vanowen St North Hollywood CA 91605",
    "addr:housenumber":"11411",
    "addr:postcode":"91605",
    "addr:street":"Vanowen St",
    "iso:country":"US",
    "sg:address":"11411 Vanowen St",
    "sg:city":"North Hollywood",
    "sg:classifiers":[
        {
            "category":"Manufacturing",
            "subcategory":"Musical Instruments",
            "type":"Manufacturing & Wholesale Goods"
        }
    ],
    "sg:phone":"+1 818 765 8929",
    "sg:postcode":"91605",
    "sg:province":"CA",
    "sg:tags":[
        "teacher"
    ],
    "sg:website":"www.bogneramplification.com",
    "wof:name":"Bogner Amplification",
    "wof:placetype":"venue"
},
  "geometry": {"coordinates":[-118.379997,34.193802],"type":"Point"}
}