{
  "type": "Feature",
  "properties": {
    "addr:full":"9610 Bellanca Ave Los Angeles CA 90045",
    "addr:postcode":"9610;90045",
    "addr:street":"Bellanca Ave",
    "iso:country":"US",
    "sg:address":"9610 Bellanca Ave",
    "sg:city":"Los Angeles",
    "sg:classifiers":[
        {
            "category":"Manufacturing",
            "subcategory":"Electronics",
            "type":"Manufacturing & Wholesale Goods"
        }
    ],
    "sg:phone":"+1 310 641 1290",
    "sg:postcode":"90045",
    "sg:province":"CA",
    "sg:tags":[
        "control",
        "security",
        "system"
    ],
    "wof:name":"Secom International",
    "wof:placetype":"venue"
},
  "geometry": {"coordinates":[-118.379895,33.947453],"type":"Point"}
}