{
  "type": "Feature",
  "properties": {
    "addr:full":"5049 8th St Carpinteria CA 93013",
    "addr:housenumber":"5049",
    "addr:postcode":"93013",
    "addr:street":"8Th St",
    "iso:country":"US",
    "sg:address":"5049 8th St",
    "sg:city":"Carpinteria",
    "sg:classifiers":[
        {
            "category":"Professional",
            "subcategory":"Art Services",
            "type":"Services"
        }
    ],
    "sg:phone":"+1 805 566 9912",
    "sg:postcode":"93013",
    "sg:province":"CA",
    "sg:tags":[
        "photographer"
    ],
    "wof:name":"Vision Photography",
    "wof:placetype":"venue"
},
  "geometry": {"coordinates":[-119.519075,34.396734],"type":"Point"}
}