{
  "type": "Feature",
  "properties": {
    "addr:full":"9325 Burchell Rd Gilroy CA 95020",
    "addr:postcode":"9325;95020",
    "addr:street":"Burchell Rd",
    "iso:country":"US",
    "sg:address":"9325 Burchell Rd",
    "sg:city":"Gilroy",
    "sg:classifiers":[
        {
            "category":"Building & Trades",
            "subcategory":"Equipment Rental",
            "type":"Services"
        }
    ],
    "sg:phone":"+1 408 840 2148",
    "sg:postcode":"95020",
    "sg:province":"CA",
    "sg:tags":[
        "yard",
        "store"
    ],
    "wof:name":"Paqstar",
    "wof:placetype":"venue"
},
  "geometry": {"coordinates":[-121.641301,37.027938],"type":"Point"}
}