{
  "type": "Feature",
  "properties": {
    "addr:full":"2158 Sutter St San Francisco CA 94115",
    "addr:housenumber":"2158",
    "addr:postcode":"94115",
    "addr:street":"Sutter St",
    "iso:country":"US",
    "sg:address":"2158 Sutter St",
    "sg:city":"San Francisco",
    "sg:classifiers":[
        {
            "category":"Shopping",
            "type":"Retail Goods"
        }
    ],
    "sg:phone":"+1 415 922 8978",
    "sg:postcode":"94115",
    "sg:province":"CA",
    "sg:tags":[
        "art",
        "gallery",
        "dealer"
    ],
    "wof:name":"David F Rosenthal",
    "wof:placetype":"venue"
},
  "geometry": {"coordinates":[-122.435802,37.785865],"type":"Point"}
}