{
  "type": "Feature",
  "properties": {
    "addr:full":"26508 Rd 196 Exeter CA 93221",
    "addr:postcode":"26508;93221",
    "addr:street":"Rd 196",
    "iso:country":"US",
    "sg:address":"26508 Rd 196",
    "sg:city":"Exeter",
    "sg:classifiers":[
        {
            "category":"Farming",
            "subcategory":"Orchard",
            "type":"Manufacturing & Wholesale Goods"
        }
    ],
    "sg:phone":"+1 559 592 2227",
    "sg:postcode":"93221",
    "sg:province":"CA",
    "sg:tags":[
        "citrus",
        "grove",
        "fruit"
    ],
    "wof:name":"Leigh John",
    "wof:placetype":"venue"
},
  "geometry": {"coordinates":[-119.136145,36.274081],"type":"Point"}
}