{
  "type": "Feature",
  "properties": {
    "addr:full":"1133 E Olive Ave Fresno CA 93728",
    "addr:housenumber":"1133",
    "addr:postcode":"93728",
    "addr:street":"E Olive Ave",
    "iso:country":"US",
    "sg:address":"1133 E Olive Ave",
    "sg:city":"Fresno",
    "sg:classifiers":[
        {
            "category":"Organizations",
            "subcategory":"Religious Organization",
            "type":"Services"
        }
    ],
    "sg:phone":"+1 559 237 6220",
    "sg:postcode":"93728",
    "sg:province":"CA",
    "sg:tags":[
        "church"
    ],
    "wof:name":"St Mary Of Magdala Cathedral",
    "wof:placetype":"venue"
},
  "geometry": {"coordinates":[-119.79770499999999,36.757751],"type":"Point"}
}