{
  "type": "Feature",
  "properties": {
    "iso:country":"US",
    "sg:address":"3121 Colorado Blvd",
    "sg:city":"Pasadena",
    "sg:classifiers":[
        {
            "category":"Health Services",
            "subcategory":"Clinic",
            "type":"Services"
        }
    ],
    "sg:phone":"+1 626 405 0820",
    "sg:postcode":"91107",
    "sg:province":"CA",
    "sg:tags":[
        "medical"
    ],
    "wof:name":"Roger Nomura Optometrist",
    "wof:placetype":"venue"
},
  "geometry": {"coordinates":[-118.08418,34.146938],"type":"Point"}
}