{
  "type": "Feature",
  "properties": {
    "addr:full":"969 Edgewater Blvd. #682 Foster City CA 94444",
    "addr:housenumber":"969",
    "addr:postcode":"94444",
    "addr:street":"Edgewater Blvd. # 682",
    "iso:country":"US",
    "sg:address":"969 Edgewater Blvd. #682",
    "sg:city":"Foster City",
    "sg:classifiers":[
        {
            "category":"Building & Trades",
            "subcategory":"Construction",
            "type":"Services"
        }
    ],
    "sg:phone":"+1 916 716 9523",
    "sg:postcode":"94444",
    "sg:province":"CA",
    "sg:tags":[
        "contractor"
    ],
    "sg:website":"www.lasalinc.com",
    "wof:name":"Lasal Construction",
    "wof:placetype":"venue"
},
  "geometry": {"coordinates":[-122.270794,37.544616],"type":"Point"}
}