{
  "type": "Feature",
  "properties": {
    "iso:country":"US",
    "sg:address":"3838 Ponderosa Rd",
    "sg:city":"Shingle Springs",
    "sg:classifiers":[
        {
            "category":"Organizations",
            "subcategory":"Religious Organization",
            "type":"Services"
        }
    ],
    "sg:phone":"+1 530 677 3646",
    "sg:postcode":"95682",
    "sg:province":"CA",
    "sg:tags":[
        "church"
    ],
    "sg:website":"www.foursquarefellowship.com",
    "wof:name":"Shingle Springs Foursquare Chr",
    "wof:placetype":"venue"
},
  "geometry": {"coordinates":[-120.938807,38.667847],"type":"Point"}
}