{
  "type": "Feature",
  "properties": {
    "addr:full":"2307 Ocean Ave Santa Monica CA 90405",
    "addr:housenumber":"2307",
    "addr:postcode":"90405",
    "addr:street":"Ocean Ave",
    "iso:country":"US",
    "sg:address":"2307 Ocean Ave",
    "sg:city":"Santa Monica",
    "sg:classifiers":[
        {
            "category":"Building & Trades",
            "subcategory":"Construction",
            "type":"Services"
        }
    ],
    "sg:phone":"+1 310 581 5221",
    "sg:postcode":"90405",
    "sg:province":"CA",
    "sg:tags":[
        "builder",
        "patio",
        "deck"
    ],
    "wof:name":"Deck Doctor",
    "wof:placetype":"venue"
},
  "geometry": {"coordinates":[-118.487543,34.003328],"type":"Point"}
}