{
  "type": "Feature",
  "properties": {
    "iso:country":"US",
    "sg:address":"1201 Tucker Rd",
    "sg:city":"Calistoga",
    "sg:classifiers":[
        {
            "category":"Farming",
            "subcategory":"Farm",
            "type":"Manufacturing & Wholesale Goods"
        }
    ],
    "sg:phone":"+1 707 942 9695",
    "sg:postcode":"94515",
    "sg:province":"CA",
    "wof:name":"Tucker Farm Ctr",
    "wof:placetype":"venue"
},
  "geometry": {"coordinates":[-122.531756,38.555898],"type":"Point"}
}