{
  "type": "Feature",
  "properties": {
    "addr:full":"1061 N State College Blvd Anaheim CA 92806",
    "addr:housenumber":"1061",
    "addr:postcode":"92806",
    "addr:street":"N State College Blvd",
    "iso:country":"US",
    "sg:address":"1061 N State College Blvd",
    "sg:city":"Anaheim",
    "sg:classifiers":[
        {
            "category":"Banks & Credit Unions",
            "subcategory":"Investment Brokerage",
            "type":"Services"
        }
    ],
    "sg:phone":"+1 714 533 1052",
    "sg:postcode":"92806",
    "sg:province":"CA",
    "sg:tags":[
        "investing"
    ],
    "wof:name":"Global Investment Management",
    "wof:placetype":"venue"
},
  "geometry": {"coordinates":[-117.88944600000001,33.84845],"type":"Point"}
}