{
  "type": "Feature",
  "properties": {
    "iso:country":"US",
    "sg:address":"3701 Wilshire Boulevard",
    "sg:city":"Los Angeles",
    "sg:classifiers":[
        {
            "category":"Professional",
            "subcategory":"Lawyer & Legal Services",
            "type":"Services"
        }
    ],
    "sg:phone":"+1 213 351 9583",
    "sg:postcode":"90010",
    "sg:province":"CA",
    "wof:name":"Curtis Greta S Atty",
    "wof:placetype":"venue"
},
  "geometry": {"coordinates":[-118.306594,34.06172],"type":"Point"}
}