{
  "type": "Feature",
  "properties": {
    "iso:country":"US",
    "sg:address":"39360 3rd St E",
    "sg:city":"Palmdale",
    "sg:classifiers":[
        {
            "category":"Autos & Motor Vehicles",
            "subcategory":"Auto Supplies",
            "type":"Retail Goods"
        }
    ],
    "sg:phone":"+1 661 272 9655",
    "sg:postcode":"93550",
    "sg:province":"CA",
    "sg:tags":[
        "automobile",
        "trade",
        "equipment",
        "car",
        "contractor",
        "racing"
    ],
    "wof:name":"Jackson Race Cars",
    "wof:placetype":"venue"
},
  "geometry": {"coordinates":[-118.125357,34.598287],"type":"Point"}
}