{
  "type": "Feature",
  "properties": {
    "addr:full":"3264 N Mountain Ave Claremont CA 91711",
    "addr:housenumber":"3264",
    "addr:postcode":"91711",
    "addr:street":"N Mountain Ave",
    "iso:country":"US",
    "sg:address":"3264 N Mountain Ave",
    "sg:city":"Claremont",
    "sg:classifiers":[
        {
            "category":"Real Estate",
            "subcategory":"Real Estate Agent",
            "type":"Services"
        }
    ],
    "sg:phone":"+1 909 624 8828",
    "sg:postcode":"91711",
    "sg:province":"CA",
    "wof:name":"Tlm Realty",
    "wof:placetype":"venue"
},
  "geometry": {"coordinates":[-117.72899099999999,34.126658],"type":"Point"}
}