{
  "type": "Feature",
  "properties": {
    "iso:country":"US",
    "sg:address":"633 S Knickerbocker Dr",
    "sg:city":"Sunnyvale",
    "sg:classifiers":[
        {
            "category":"Real Estate",
            "subcategory":"Real Estate Operator",
            "type":"Services"
        }
    ],
    "sg:phone":"+1 408 749 8600",
    "sg:postcode":"94087",
    "sg:province":"CA",
    "sg:tags":[
        "building",
        "apartment"
    ],
    "wof:name":"Sunrise Senior Living Inc",
    "wof:placetype":"venue"
},
  "geometry": {"coordinates":[-122.05920999999999,37.37228],"type":"Point"}
}