{
  "type": "Feature",
  "properties": {
    "iso:country":"US",
    "sg:address":"27825 Ferguson Dr",
    "sg:city":"Castaic",
    "sg:classifiers":[
        {
            "category":"Restaurant",
            "type":"Food & Drink"
        }
    ],
    "sg:phone":"+1 661 702 0771",
    "sg:postcode":"91384",
    "sg:province":"CA",
    "sg:website":"www.barbecue-catering.com",
    "wof:name":"George's Bar-B-Q Catering",
    "wof:placetype":"venue"
},
  "geometry": {"coordinates":[-118.62400100000001,34.492599],"type":"Point"}
}