{
  "type": "Feature",
  "properties": {
    "iso:country":"US",
    "sg:address":"18333 Dolan Way",
    "sg:city":"Santa Clarita",
    "sg:classifiers":[
        {
            "category":"Shopping",
            "subcategory":"Computers & Home Electronics",
            "type":"Retail Goods"
        }
    ],
    "sg:phone":"+1 661 298 6100",
    "sg:postcode":"91387",
    "sg:province":"CA",
    "wof:name":"Advanced Media Products",
    "wof:placetype":"venue"
},
  "geometry": {"coordinates":[-118.452984,34.41964],"type":"Point"}
}