{
  "type": "Feature",
  "properties": {
    "addr:full":"1725 Chicory Ct Redding CA 96002",
    "addr:housenumber":"1725",
    "addr:postcode":"96002",
    "addr:street":"Chicory Ct",
    "iso:country":"US",
    "sg:address":"1725 Chicory Ct",
    "sg:city":"Redding",
    "sg:classifiers":[
        {
            "category":"Arts & Performance",
            "subcategory":"Theater",
            "type":"Entertainment"
        }
    ],
    "sg:phone":"+1 530 221 3398",
    "sg:postcode":"96002",
    "sg:province":"CA",
    "sg:tags":[
        "musician"
    ],
    "sg:website":"www.shasta.com",
    "wof:name":"Straight Ahead Big Band",
    "wof:placetype":"venue"
},
  "geometry": {"coordinates":[-122.337942,40.537158],"type":"Point"}
}