{
  "type": "Feature",
  "properties": {
    "addr:full":"1260 Lathrop Rd Manteca CA 95330",
    "addr:housenumber":"1260",
    "addr:postcode":"95330",
    "addr:street":"Lathrop Rd",
    "iso:country":"US",
    "sg:address":"1260 Lathrop Rd",
    "sg:city":"Manteca",
    "sg:classifiers":[
        {
            "category":"Personal",
            "subcategory":"Beauty Salon",
            "type":"Services"
        }
    ],
    "sg:phone":"+1 209 825 7216",
    "sg:postcode":"95330",
    "sg:province":"CA",
    "sg:tags":[
        "manicuring"
    ],
    "wof:name":"Nails Only",
    "wof:placetype":"venue"
},
  "geometry": {"coordinates":[-121.273549,37.826332],"type":"Point"}
}