{
  "type": "Feature",
  "properties": {
    "addr:full":"PO Box 510 Victorville CA 92393",
    "addr:housenumber":"po",
    "addr:postcode":"92393",
    "addr:street":"Box 510",
    "iso:country":"US",
    "sg:address":"PO Box 510",
    "sg:city":"Victorville",
    "sg:classifiers":[
        {
            "category":"Retail",
            "subcategory":"Veterinary Services",
            "type":"Services"
        }
    ],
    "sg:phone":"+1 877 838 4624",
    "sg:postcode":"92393",
    "sg:province":"CA",
    "sg:tags":[
        "specialty"
    ],
    "sg:website":"http://vetimage.us",
    "wof:name":"VetImage Inc.",
    "wof:placetype":"venue"
},
  "geometry": {"coordinates":[-117.2902,34.5361],"type":"Point"}
}