{
  "type": "Feature",
  "properties": {
    "iso:country":"US",
    "sg:address":"14015 Midland Rd",
    "sg:city":"Poway",
    "sg:classifiers":[
        {
            "category":"Shopping",
            "subcategory":"Hobbies, Toys, & Games",
            "type":"Retail Goods"
        }
    ],
    "sg:phone":"+1 858 679 6890",
    "sg:postcode":"92064",
    "sg:province":"CA",
    "wof:name":"Its A Bead Thing",
    "wof:placetype":"venue"
},
  "geometry": {"coordinates":[-117.036073,32.968913],"type":"Point"}
}