{
  "type": "Feature",
  "properties": {
    "iso:country":"US",
    "sg:address":"1905 Apple St",
    "sg:city":"Oceanside",
    "sg:classifiers":[
        {
            "category":"Organizations",
            "subcategory":"Membership Organization",
            "type":"Services"
        }
    ],
    "sg:phone":"+1 760 721 2117",
    "sg:postcode":"92054",
    "sg:province":"CA",
    "wof:name":"Interface Community Svc",
    "wof:placetype":"venue"
},
  "geometry": {"coordinates":[-117.355856,33.19552],"type":"Point"}
}