{
  "type": "Feature",
  "properties": {
    "addr:full":"1143 Danbury Dr San Jose CA 95129",
    "addr:housenumber":"1143",
    "addr:postcode":"95129",
    "addr:street":"Danbury Dr",
    "iso:country":"US",
    "sg:address":"1143 Danbury Dr",
    "sg:city":"San Jose",
    "sg:classifiers":[
        {
            "category":"Professional",
            "subcategory":"Computer Services",
            "type":"Services"
        }
    ],
    "sg:phone":"+1 408 873 7050",
    "sg:postcode":"95129",
    "sg:province":"CA",
    "sg:tags":[
        "consultant",
        "designer"
    ],
    "wof:name":"Brilliant Solutions Inc",
    "wof:placetype":"venue"
},
  "geometry": {"coordinates":[-122.01961,37.303835],"type":"Point"}
}