{
  "type": "Feature",
  "properties": {
    "iso:country":"US",
    "sg:address":"2100 March Rd",
    "sg:city":"Roseville",
    "sg:classifiers":[
        {
            "category":"Retail",
            "subcategory":"Auto Repair",
            "type":"Services"
        }
    ],
    "sg:phone":"+1 916 781 8191",
    "sg:postcode":"95747",
    "sg:province":"CA",
    "sg:tags":[
        "repairing",
        "automobile"
    ],
    "wof:name":"J & T Auto Svc",
    "wof:placetype":"venue"
},
  "geometry": {"coordinates":[-121.315498,38.726841],"type":"Point"}
}