{
  "type": "Feature",
  "properties": {
    "iso:country":"US",
    "sg:address":"5941 Ave 160",
    "sg:city":"Tipton",
    "sg:classifiers":[
        {
            "category":"Farming",
            "subcategory":"Dairy Farm",
            "type":"Manufacturing & Wholesale Goods"
        }
    ],
    "sg:phone":"+1 559 752 1002",
    "sg:postcode":"93272",
    "sg:province":"CA",
    "wof:name":"Tevelde Gj Ranch",
    "wof:placetype":"venue"
},
  "geometry": {"coordinates":[-119.43476099999999,36.079918],"type":"Point"}
}