{
  "type": "Feature",
  "properties": {
    "addr:full":"1540 el Cerrito Ct Yuba City CA 95993",
    "addr:housenumber":"1540",
    "addr:postcode":"95993",
    "addr:street":"El Cerrito Ct",
    "iso:country":"US",
    "sg:address":"1540 el Cerrito Ct",
    "sg:city":"Yuba City",
    "sg:classifiers":[
        {
            "category":"Building & Trades",
            "subcategory":"Cleaning & Sanitation",
            "type":"Services"
        }
    ],
    "sg:phone":"+1 530 755 3627",
    "sg:postcode":"95993",
    "sg:province":"CA",
    "sg:tags":[
        "janitor"
    ],
    "wof:name":"Cleaning Specialist",
    "wof:placetype":"venue"
},
  "geometry": {"coordinates":[-121.647921,39.15188],"type":"Point"}
}