{
  "type": "Feature",
  "properties": {
    "addr:full":"15634 Quartz Valley Dr Fort Jones CA 96032",
    "addr:housenumber":"15634",
    "addr:postcode":"96032",
    "addr:street":"Quartz Valley Dr Fort Jones",
    "iso:country":"US",
    "sg:address":"15634 Quartz Valley Dr",
    "sg:city":"Fort Jones",
    "sg:classifiers":[
        {
            "category":"Building & Trades",
            "subcategory":"Construction",
            "type":"Services"
        }
    ],
    "sg:phone":"+1 530 468 2316",
    "sg:postcode":"96032",
    "sg:province":"CA",
    "sg:tags":[
        "hanging",
        "contractor"
    ],
    "wof:name":"Paul Ross Painting",
    "wof:placetype":"venue"
},
  "geometry": {"coordinates":[-122.97535499999999,41.617682],"type":"Point"}
}