{
  "type": "Feature",
  "properties": {
    "addr:full":"675 Townsend St San Francisco CA 94103",
    "addr:housenumber":"675",
    "addr:postcode":"94103",
    "addr:street":"Townsend St",
    "iso:country":"US",
    "sg:address":"675 Townsend St",
    "sg:city":"San Francisco",
    "sg:classifiers":[
        {
            "category":"Building & Trades",
            "subcategory":"Electrical",
            "type":"Services"
        }
    ],
    "sg:phone":"+1 415 241 0223",
    "sg:postcode":"94103",
    "sg:province":"CA",
    "sg:tags":[
        "equipment",
        "electrical",
        "electric",
        "contractor"
    ],
    "wof:name":"M D E Electric Co",
    "wof:placetype":"venue"
},
  "geometry": {"coordinates":[-122.40249900000001,37.771334],"type":"Point"}
}