{
  "type": "Feature",
  "properties": {
    "addr:full":"6906 Eastwood Ave Alta Loma CA 91701",
    "addr:housenumber":"6906",
    "addr:postcode":"91701",
    "addr:street":"Eastwood Ave",
    "iso:country":"US",
    "sg:address":"6906 Eastwood Ave",
    "sg:city":"Alta Loma",
    "sg:classifiers":[
        {
            "category":"Building & Trades",
            "subcategory":"Plumbing",
            "type":"Services"
        }
    ],
    "sg:phone":"+1 909 484 3231",
    "sg:postcode":"91701",
    "sg:province":"CA",
    "sg:tags":[
        "plumbing",
        "contractor"
    ],
    "wof:name":"Jay Indeck Plumbing",
    "wof:placetype":"venue"
},
  "geometry": {"coordinates":[-117.60496500000001,34.128692],"type":"Point"}
}