{
  "type": "Feature",
  "properties": {
    "addr:full":"1243 Boulevard Way Walnut Creek CA 94595",
    "addr:housenumber":"1243",
    "addr:postcode":"94595",
    "addr:street":"Boulevard Way",
    "iso:country":"US",
    "sg:address":"1243 Boulevard Way",
    "sg:city":"Walnut Creek",
    "sg:classifiers":[
        {
            "category":"Shopping",
            "type":"Retail Goods"
        }
    ],
    "sg:phone":"+1 925 947 0543",
    "sg:postcode":"94595",
    "sg:province":"CA",
    "sg:tags":[
        "plant",
        "flower",
        "tree",
        "artificial"
    ],
    "wof:name":"Sunflower",
    "wof:placetype":"venue"
},
  "geometry": {"coordinates":[-122.077551,37.893401],"type":"Point"}
}