{
  "type": "Feature",
  "properties": {
    "iso:country":"US",
    "sg:address":"1056 Terven Ave",
    "sg:city":"Salinas",
    "sg:classifiers":[
        {
            "category":"Wholesale",
            "subcategory":"Construction Materials",
            "type":"Manufacturing & Wholesale Goods"
        },
        {
            "category":"Shopping",
            "type":"Retail Goods"
        }
    ],
    "sg:phone":"+1 831 784 1261",
    "sg:postcode":"93901",
    "sg:province":"CA",
    "sg:tags":[
        "granite",
        "merchandise"
    ],
    "wof:name":"Monterey Bay Granite & Marble",
    "wof:placetype":"venue"
},
  "geometry": {"coordinates":[-121.628048,36.663266],"type":"Point"}
}