{
  "type": "Feature",
  "properties": {
    "iso:country":"US",
    "sg:address":"681 Main St Ste 206",
    "sg:city":"Placerville",
    "sg:classifiers":[
        {
            "category":"Health Services",
            "subcategory":"Nursing And Care Facility",
            "type":"Services"
        },
        {
            "category":"Health Services",
            "subcategory":"Health Practitioner",
            "type":"Services"
        }
    ],
    "sg:phone":"+1 530 626 2900",
    "sg:postcode":"95667",
    "sg:province":"CA",
    "sg:tags":[
        "home",
        "eldercare-home"
    ],
    "wof:name":"Marshall Hospital Home Care",
    "wof:placetype":"venue"
},
  "geometry": {"coordinates":[-120.791769,38.730146],"type":"Point"}
}