{
  "type": "Feature",
  "properties": {
    "addr:full":"1900 Coyote Point Dr San Mateo CA 94401",
    "addr:housenumber":"1900",
    "addr:postcode":"94401",
    "addr:street":"Coyote Point Dr",
    "iso:country":"US",
    "sg:address":"1900 Coyote Point Dr",
    "sg:city":"San Mateo",
    "sg:classifiers":[
        {
            "category":"Recreation",
            "subcategory":"Boat Charter",
            "type":"Entertainment"
        }
    ],
    "sg:phone":"+1 650 573 2594",
    "sg:postcode":"94401",
    "sg:province":"CA",
    "sg:tags":[
        "boating"
    ],
    "wof:name":"Coyote Point Marina",
    "wof:placetype":"venue"
},
  "geometry": {"coordinates":[-122.319,37.586498],"type":"Point"}
}