{
  "type": "Feature",
  "properties": {
    "iso:country":"US",
    "sg:address":"8174 Dillard Rd",
    "sg:city":"Wilton",
    "sg:classifiers":[
        {
            "category":"Recreation",
            "type":"Entertainment"
        }
    ],
    "sg:phone":"+1 916 687 7800",
    "sg:postcode":"95693",
    "sg:province":"CA",
    "sg:tags":[
        "stable"
    ],
    "wof:name":"Ed Murphy Cutting Horses",
    "wof:placetype":"venue"
},
  "geometry": {"coordinates":[-121.18076000000001,38.45769],"type":"Point"}
}