{
  "type": "Feature",
  "properties": {
    "addr:full":"50 Woodside Rd Redwood City CA 94061",
    "addr:housenumber":"50",
    "addr:postcode":"94061",
    "addr:street":"Woodside Rd",
    "iso:country":"US",
    "sg:address":"50 Woodside Rd",
    "sg:city":"Redwood City",
    "sg:classifiers":[
        {
            "category":"Building & Trades",
            "subcategory":"Landscaping Services",
            "type":"Services"
        }
    ],
    "sg:phone":"+1 650 464 2490",
    "sg:postcode":"94061",
    "sg:province":"CA",
    "wof:name":"Advanced Landscaping",
    "wof:placetype":"venue"
},
  "geometry": {"coordinates":[-122.221676,37.474537],"type":"Point"}
}