{
  "type": "Feature",
  "properties": {
    "iso:country":"US",
    "sg:address":"826 N Winchester Blvd Ste 1B",
    "sg:city":"San Jose",
    "sg:classifiers":[
        {
            "category":"Professional",
            "type":"Services"
        }
    ],
    "sg:phone":"+1 408 246 8798",
    "sg:postcode":"95128",
    "sg:province":"CA",
    "sg:website":"www.apollonow.com",
    "wof:name":"Apollo Hair Systems International",
    "wof:placetype":"venue"
},
  "geometry": {"coordinates":[-121.949427,37.330437],"type":"Point"}
}