{
  "type": "Feature",
  "properties": {
    "addr:full":"13601 Navajo Rd Apple Valley CA 92308",
    "addr:housenumber":"13601",
    "addr:postcode":"92308",
    "addr:street":"Navajo Rd",
    "iso:country":"US",
    "sg:address":"13601 Navajo Rd",
    "sg:city":"Apple Valley",
    "sg:classifiers":[
        {
            "category":"Food & Beverages",
            "subcategory":"Liquor & Beverages",
            "type":"Retail Goods"
        }
    ],
    "sg:phone":"+1 760 247 2647",
    "sg:postcode":"92308",
    "sg:province":"CA",
    "wof:name":"New Navajo Liquor",
    "wof:placetype":"venue"
},
  "geometry": {"coordinates":[-117.190162,34.499308],"type":"Point"}
}