{
  "type": "Feature",
  "properties": {
    "iso:country":"US",
    "sg:address":"4843 Laurel Canyon Blvd",
    "sg:city":"Valley Village",
    "sg:classifiers":[
        {
            "category":"Museum",
            "type":"Entertainment"
        }
    ],
    "sg:phone":"+1 818 760 8322",
    "sg:postcode":"91607",
    "sg:province":"CA",
    "sg:tags":[
        "information",
        "art"
    ],
    "wof:name":"Celtic Arts Center",
    "wof:placetype":"venue"
},
  "geometry": {"coordinates":[-118.397003,34.1591],"type":"Point"}
}