{
  "type": "Feature",
  "properties": {
    "iso:country":"US",
    "sg:address":"11221 Merritt St",
    "sg:city":"Castroville",
    "sg:classifiers":[
        {
            "category":"Restaurant",
            "type":"Food & Drink"
        }
    ],
    "sg:phone":"+1 831 633 0338",
    "sg:postcode":"95012",
    "sg:province":"CA",
    "sg:tags":[
        "shop",
        "coffee"
    ],
    "wof:name":"Norma Expresso Coffee Factory",
    "wof:placetype":"venue"
},
  "geometry": {"coordinates":[-121.75357099999999,36.762493],"type":"Point"}
}