{
  "type": "Feature",
  "properties": {
    "addr:full":"6921 N Lake Blvd Tahoe Vista CA 96148",
    "addr:housenumber":"6921",
    "addr:postcode":"96148",
    "addr:street":"N Lake Blvd",
    "iso:country":"US",
    "sg:address":"6921 N Lake Blvd",
    "sg:city":"Tahoe Vista",
    "sg:classifiers":[
        {
            "category":"Real Estate",
            "subcategory":"Architect",
            "type":"Services"
        }
    ],
    "sg:phone":"+1 530 546 6098",
    "sg:postcode":"96148",
    "sg:province":"CA",
    "wof:name":"Timberstone Construction",
    "wof:placetype":"venue"
},
  "geometry": {"coordinates":[-120.023156,39.240088],"type":"Point"}
}