{
  "type": "Feature",
  "properties": {
    "iso:country":"US",
    "sg:address":"27 Kimberley Pl",
    "sg:city":"Alamo",
    "sg:classifiers":[
        {
            "category":"Manufacturing",
            "subcategory":"Printing",
            "type":"Manufacturing & Wholesale Goods"
        }
    ],
    "sg:phone":"+1 925 855 1470",
    "sg:postcode":"94507",
    "sg:province":"CA",
    "sg:tags":[
        "multimedia"
    ],
    "wof:name":"Multimedia Consulting",
    "wof:placetype":"venue"
},
  "geometry": {"coordinates":[-122.01560000000001,37.844642],"type":"Point"}
}