{
  "type": "Feature",
  "properties": {
    "iso:country":"US",
    "sg:address":"1641 Atlantic Ave",
    "sg:city":"Long Beach",
    "sg:classifiers":[
        {
            "category":"Retail",
            "subcategory":"Auto Repair",
            "type":"Services"
        }
    ],
    "sg:phone":"+1 562 218 8074",
    "sg:postcode":"90813",
    "sg:province":"CA",
    "sg:tags":[
        "repairing",
        "automobile"
    ],
    "wof:name":"Fernando's Auto Repair",
    "wof:placetype":"venue"
},
  "geometry": {"coordinates":[-118.18499799999999,33.787899],"type":"Point"}
}