{
  "type": "Feature",
  "properties": {
    "iso:country":"US",
    "sg:address":"13211 S Normandie Ave",
    "sg:city":"Gardena",
    "sg:classifiers":[
        {
            "category":"Retail",
            "subcategory":"Auto Repair",
            "type":"Services"
        }
    ],
    "sg:phone":"+1 310 538 2627",
    "sg:postcode":"90249",
    "sg:province":"CA",
    "sg:tags":[
        "transmission"
    ],
    "wof:name":"Progress Transmissions",
    "wof:placetype":"venue"
},
  "geometry": {"coordinates":[-118.300453,33.910886],"type":"Point"}
}