{
  "type": "Feature",
  "properties": {
    "iso:country":"US",
    "sg:address":"40210 Big Bear Blvd",
    "sg:city":"Big Bear Lake",
    "sg:classifiers":[
        {
            "category":"Travel",
            "subcategory":"Hotels & Motels",
            "type":"Entertainment"
        }
    ],
    "sg:phone":"+1 909 878 2178",
    "sg:postcode":"92315",
    "sg:province":"CA",
    "sg:tags":[
        "resort"
    ],
    "sg:website":"www.wildwoodresort.com",
    "wof:name":"Wildwood Resort",
    "wof:placetype":"venue"
},
  "geometry": {"coordinates":[-116.92442699999999,34.239093],"type":"Point"}
}