{
  "type": "Feature",
  "properties": {
    "addr:full":"1500 Los Padres Blvd Santa Clara CA 95050",
    "addr:housenumber":"1500",
    "addr:postcode":"95050",
    "addr:street":"Los Padres Blvd",
    "iso:country":"US",
    "sg:address":"1500 Los Padres Blvd",
    "sg:city":"Santa Clara",
    "sg:classifiers":[
        {
            "category":"Travel",
            "subcategory":"Travel Agent",
            "type":"Entertainment"
        }
    ],
    "sg:phone":"+1 408 246 1993",
    "sg:postcode":"95050",
    "sg:province":"CA",
    "sg:tags":[
        "agency"
    ],
    "wof:name":"C&M Travel",
    "wof:placetype":"venue"
},
  "geometry": {"coordinates":[-121.9649,37.35227],"type":"Point"}
}