{
  "type": "Feature",
  "properties": {
    "addr:full":"2340 Cabot Ct Fairfield CA 94533",
    "addr:housenumber":"2340",
    "addr:postcode":"94533",
    "addr:street":"Cabot Ct",
    "iso:country":"US",
    "sg:address":"2340 Cabot Ct",
    "sg:city":"Fairfield",
    "sg:classifiers":[
        {
            "category":"Health Services",
            "subcategory":"Nursing And Care Facility",
            "type":"Services"
        }
    ],
    "sg:phone":"+1 707 863 8911",
    "sg:postcode":"94533",
    "sg:province":"CA",
    "wof:name":"Franklin Wiley Care Home",
    "wof:placetype":"venue"
},
  "geometry": {"coordinates":[-122.073806,38.24455],"type":"Point"}
}