{
  "type": "Feature",
  "properties": {
    "iso:country":"US",
    "sg:address":"3519 California St",
    "sg:city":"San Francisco",
    "sg:classifiers":[
        {
            "category":"Bagels",
            "subcategory":"None",
            "type":"Food & Drink"
        }
    ],
    "sg:phone":"+1 415 387 3874",
    "sg:postcode":"94118",
    "sg:province":"CA",
    "sg:website":"www.noahs.com",
    "wof:name":"Noah's Bagels",
    "wof:placetype":"venue"
},
  "geometry": {"coordinates":[-122.451964,37.786562],"type":"Point"}
}