{
  "type": "Feature",
  "properties": {
    "iso:country":"US",
    "sg:address":"1 Gate 6 Rd",
    "sg:city":"Sausalito",
    "sg:classifiers":[
        {
            "category":"Banks & Credit Unions",
            "subcategory":"Bank",
            "type":"Services"
        }
    ],
    "sg:phone":"+1 415 331 3300",
    "sg:postcode":"94965",
    "sg:province":"CA",
    "sg:tags":[
        "loan",
        "real estate"
    ],
    "wof:name":"First Nations Funding Group",
    "wof:placetype":"venue"
},
  "geometry": {"coordinates":[-122.50556,37.872697],"type":"Point"}
}