{
  "type": "Feature",
  "properties": {
    "addr:full":"4645 Carmel Mountain Rd San Diego CA 92130",
    "addr:housenumber":"4645",
    "addr:postcode":"92130",
    "addr:street":"Carmel Mountain Rd",
    "iso:country":"US",
    "sg:address":"4645 Carmel Mountain Rd",
    "sg:city":"San Diego",
    "sg:classifiers":[
        {
            "category":"Restaurant",
            "type":"Food & Drink"
        }
    ],
    "sg:menulink":"http://www.allmenus.com/ca/san-diego/5882-pick-up-stix/menu/",
    "sg:phone":"+1 858 794 0459",
    "sg:postcode":"92130",
    "sg:province":"CA",
    "sg:tags":[
        "japanese",
        "chinese",
        "asian"
    ],
    "wof:name":"Pick Up Stix",
    "wof:placetype":"venue"
},
  "geometry": {"coordinates":[-117.21526900000001,32.92129],"type":"Point"}
}