{
  "type": "Feature",
  "properties": {
    "addr:full":"2256 N Wilson Way Stockton CA 95205",
    "addr:housenumber":"2256",
    "addr:postcode":"95205",
    "addr:street":"N Wilson Way",
    "iso:country":"US",
    "sg:address":"2256 N Wilson Way",
    "sg:city":"Stockton",
    "sg:classifiers":[
        {
            "category":"Wholesale",
            "subcategory":"Vending Machines",
            "type":"Manufacturing & Wholesale Goods"
        }
    ],
    "sg:phone":"+1 209 948 9557",
    "sg:postcode":"95205",
    "sg:province":"CA",
    "wof:name":"A-Action Vending",
    "wof:placetype":"venue"
},
  "geometry": {"coordinates":[-121.274157,37.977607],"type":"Point"}
}