{
  "type": "Feature",
  "properties": {
    "iso:country":"US",
    "sg:address":"605 W Olympic Blvd",
    "sg:city":"Los Angeles",
    "sg:classifiers":[
        {
            "category":"Organizations",
            "subcategory":"Membership Organization",
            "type":"Services"
        },
        {
            "category":"Social Services",
            "type":"Services"
        }
    ],
    "sg:phone":"+1 213 626 3393",
    "sg:postcode":"90015",
    "sg:province":"CA",
    "sg:tags":[
        "crisis",
        "intervention"
    ],
    "sg:website":"www.lacaaw.org",
    "wof:name":"Los Angeles Commission-Women",
    "wof:placetype":"venue"
},
  "geometry": {"coordinates":[-118.262695,34.044414],"type":"Point"}
}