{
  "type": "Feature",
  "properties": {
    "addr:full":"1260 Huntington Drive Suite 206 South Pasadena CA 91030",
    "addr:housenumber":"1260",
    "addr:postcode":"91030",
    "addr:street":"Huntington Drive Suite 206",
    "iso:country":"US",
    "sg:address":"1260 Huntington Drive Suite 206",
    "sg:city":"South Pasadena",
    "sg:classifiers":[
        {
            "category":"Professional",
            "type":"Services"
        }
    ],
    "sg:phone":"+1 323 478 2650",
    "sg:postcode":"91030",
    "sg:province":"CA",
    "sg:website":"www.mytaxstrategies.com",
    "wof:name":"Tax Strategies, Inc.",
    "wof:placetype":"venue"
},
  "geometry": {"coordinates":[-118.154439,34.103374],"type":"Point"}
}