{
  "type": "Feature",
  "properties": {
    "addr:full":"2460 E 12th St Los Angeles CA 90021",
    "addr:housenumber":"2460",
    "addr:postcode":"90021",
    "addr:street":"E 12Th St",
    "iso:country":"US",
    "sg:address":"2460 E 12th St",
    "sg:city":"Los Angeles",
    "sg:classifiers":[
        {
            "category":"Shopping",
            "subcategory":"Clothing, Apparel, & Fashions",
            "type":"Retail Goods"
        }
    ],
    "sg:phone":"+1 213 553 1196",
    "sg:postcode":"90021",
    "sg:province":"CA",
    "wof:name":"Clothing Manufactures",
    "wof:placetype":"venue"
},
  "geometry": {"coordinates":[-118.229326,34.022597],"type":"Point"}
}