{
  "type": "Feature",
  "properties": {
    "iso:country":"US",
    "sg:address":"10845 Vanowen St",
    "sg:city":"North Hollywood",
    "sg:classifiers":[
        {
            "category":"Manufacturing",
            "subcategory":"Furniture",
            "type":"Manufacturing & Wholesale Goods"
        }
    ],
    "sg:phone":"+1 818 761 5189",
    "sg:postcode":"91605",
    "sg:province":"CA",
    "sg:tags":[
        "fixture",
        "material",
        "commercial",
        "display",
        "equipment"
    ],
    "wof:name":"Collins Crafts",
    "wof:placetype":"venue"
},
  "geometry": {"coordinates":[-118.367963,34.194019],"type":"Point"}
}