{
  "type": "Feature",
  "properties": {
    "addr:full":"1738 E Broadway Long Beach CA 90802",
    "addr:housenumber":"1738",
    "addr:postcode":"90802",
    "addr:street":"E Broadway",
    "iso:country":"US",
    "sg:address":"1738 E Broadway",
    "sg:city":"Long Beach",
    "sg:classifiers":[
        {
            "category":"Shopping",
            "subcategory":"Hobbies, Toys, & Games",
            "type":"Retail Goods"
        }
    ],
    "sg:phone":"+1 562 590 3233",
    "sg:postcode":"90802",
    "sg:province":"CA",
    "wof:name":"Pudgy Beads",
    "wof:placetype":"venue"
},
  "geometry": {"coordinates":[-118.170269,33.767532],"type":"Point"}
}