{
  "type": "Feature",
  "properties": {
    "addr:full":"1432 Richardson Ave Los Altos CA 94024",
    "addr:housenumber":"1432",
    "addr:postcode":"94024",
    "addr:street":"Richardson Ave",
    "iso:country":"US",
    "sg:address":"1432 Richardson Ave",
    "sg:city":"Los Altos",
    "sg:classifiers":[
        {
            "category":"Utilities",
            "subcategory":"Telephone",
            "type":"Services"
        }
    ],
    "sg:phone":"+1 650 964 9216",
    "sg:postcode":"94024",
    "sg:province":"CA",
    "sg:tags":[
        "communications"
    ],
    "wof:name":"Cynthia Fink",
    "wof:placetype":"venue"
},
  "geometry": {"coordinates":[-122.07285,37.350359],"type":"Point"}
}