{
  "type": "Feature",
  "properties": {
    "addr:full":"11018 Vanowen St North Hollywood CA 91605",
    "addr:housenumber":"11018",
    "addr:postcode":"91605",
    "addr:street":"Vanowen St",
    "iso:country":"US",
    "sg:address":"11018 Vanowen St",
    "sg:city":"North Hollywood",
    "sg:classifiers":[
        {
            "category":"Restaurant",
            "type":"Food & Drink"
        }
    ],
    "sg:phone":"+1 818 766 6710",
    "sg:postcode":"91605",
    "sg:province":"CA",
    "wof:name":"Mike's Fast Food & Restaurant",
    "wof:placetype":"venue"
},
  "geometry": {"coordinates":[-118.371101,34.193867],"type":"Point"}
}