{
  "type": "Feature",
  "properties": {
    "iso:country":"US",
    "sg:address":"355 Salem St",
    "sg:city":"Glendale",
    "sg:classifiers":[
        {
            "category":"Manufacturing",
            "subcategory":"Signs",
            "type":"Manufacturing & Wholesale Goods"
        }
    ],
    "sg:phone":"+1 818 545 8007",
    "sg:postcode":"91203",
    "sg:province":"CA",
    "sg:tags":[
        "commercial",
        "specialty",
        "mfg"
    ],
    "wof:name":"Ardo Co",
    "wof:placetype":"venue"
},
  "geometry": {"coordinates":[-118.260288,34.149018],"type":"Point"}
}