{
  "type": "Feature",
  "properties": {
    "addr:full":"9625 Mission Gorge Rd #B2-368 Santee CA 92071",
    "addr:housenumber":"9625",
    "addr:postcode":"92071",
    "addr:street":"Mission Gorge Rd # B2-368",
    "iso:country":"US",
    "sg:address":"9625 Mission Gorge Rd #B2-368",
    "sg:city":"Santee",
    "sg:classifiers":[
        {
            "category":"Building & Trades",
            "subcategory":"Pest Control",
            "type":"Services"
        }
    ],
    "sg:phone":"+1 855 284 7928",
    "sg:postcode":"92071",
    "sg:province":"CA",
    "sg:website":"www.bug-swat.com",
    "wof:name":"SWAT Team Pest Control & Termite",
    "wof:placetype":"venue"
},
  "geometry": {"coordinates":[-116.988207,32.838618],"type":"Point"}
}