{
  "type": "Feature",
  "properties": {
    "iso:country":"US",
    "sg:address":"2670 Walnut Ave",
    "sg:city":"Tustin",
    "sg:classifiers":[
        {
            "category":"Manufacturing",
            "subcategory":"Glass & Minerals",
            "type":"Manufacturing & Wholesale Goods"
        }
    ],
    "sg:phone":"+1 714 730 5029",
    "sg:postcode":"92780",
    "sg:province":"CA",
    "sg:tags":[
        "mfg"
    ],
    "wof:name":"Glass Minagerie",
    "wof:placetype":"venue"
},
  "geometry": {"coordinates":[-117.80802,33.716503],"type":"Point"}
}