{
  "type": "Feature",
  "properties": {
    "addr:full":"10626 Norwalk Blvd Santa Fe Springs CA 90670",
    "addr:housenumber":"10626",
    "addr:postcode":"90670",
    "addr:street":"Norwalk Blvd",
    "iso:country":"US",
    "sg:address":"10626 Norwalk Blvd",
    "sg:city":"Santa Fe Springs",
    "sg:classifiers":[
        {
            "category":"Wholesale",
            "subcategory":"Hardware",
            "type":"Manufacturing & Wholesale Goods"
        },
        {
            "category":"Professional",
            "type":"Services"
        }
    ],
    "sg:phone":"+1 562 944 8527",
    "sg:postcode":"90670",
    "sg:province":"CA",
    "sg:tags":[
        "control",
        "vibration"
    ],
    "wof:name":"Ball Mount Industries Inc",
    "wof:placetype":"venue"
},
  "geometry": {"coordinates":[-118.07261200000001,33.936114],"type":"Point"}
}