{
  "type": "Feature",
  "properties": {
    "iso:country":"US",
    "sg:address":"10 S Abbott Ave",
    "sg:city":"Milpitas",
    "sg:classifiers":[
        {
            "category":"Restaurant",
            "type":"Food & Drink"
        }
    ],
    "sg:phone":"+1 408 941 9868",
    "sg:postcode":"95035",
    "sg:province":"CA",
    "wof:name":"Kitchen To Go",
    "wof:placetype":"venue"
},
  "geometry": {"coordinates":[-121.914289,37.428706],"type":"Point"}
}