{
  "type": "Feature",
  "properties": {
    "iso:country":"US",
    "sg:address":"12420 San Fernando Rd",
    "sg:city":"Sylmar",
    "sg:classifiers":[
        {
            "category":"Professional",
            "subcategory":"Advertising",
            "type":"Services"
        }
    ],
    "sg:phone":"+1 818 364 2446",
    "sg:postcode":"91342",
    "sg:province":"CA",
    "sg:tags":[
        "designer",
        "display",
        "producer"
    ],
    "wof:name":"J S Displays",
    "wof:placetype":"venue"
},
  "geometry": {"coordinates":[-118.45200199999999,34.294228],"type":"Point"}
}