{
  "type": "Feature",
  "properties": {
    "iso:country":"US",
    "sg:address":"1270 Avenida Acaso Ste D",
    "sg:city":"Camarillo",
    "sg:classifiers":[
        {
            "category":"Wholesale",
            "subcategory":"Computers",
            "type":"Manufacturing & Wholesale Goods"
        }
    ],
    "sg:phone":"+1 805 384 0100",
    "sg:postcode":"93012",
    "sg:province":"CA",
    "wof:name":"Spar Technology",
    "wof:placetype":"venue"
},
  "geometry": {"coordinates":[-119.010372,34.229992],"type":"Point"}
}