{
  "type": "Feature",
  "properties": {
    "addr:full":"10309 National Blvd Los Angeles CA 90034",
    "addr:housenumber":"10309",
    "addr:postcode":"90034",
    "addr:street":"National Blvd",
    "iso:country":"US",
    "sg:address":"10309 National Blvd",
    "sg:city":"Los Angeles",
    "sg:classifiers":[
        {
            "category":"Marine",
            "type":"Transportation"
        }
    ],
    "sg:phone":"+1 310 202 6407",
    "sg:postcode":"90034",
    "sg:province":"CA",
    "sg:tags":[
        "repair",
        "auto",
        "general",
        "water",
        "carwash",
        "transport"
    ],
    "wof:name":"Mr Polish",
    "wof:placetype":"venue"
},
  "geometry": {"coordinates":[-118.410636,34.029345],"type":"Point"}
}