{
  "type": "Feature",
  "properties": {
    "addr:full":"1600 University Ave Berkeley CA 94703",
    "addr:housenumber":"1600",
    "addr:postcode":"94703",
    "addr:street":"University Ave",
    "iso:country":"US",
    "sg:address":"1600 University Ave",
    "sg:city":"Berkeley",
    "sg:classifiers":[
        {
            "category":"Shopping",
            "subcategory":"Used Merchandise",
            "type":"Retail Goods"
        }
    ],
    "sg:phone":"+1 510 841 2088",
    "sg:postcode":"94703",
    "sg:province":"CA",
    "sg:tags":[
        "vintage",
        "consignment"
    ],
    "sg:website":"www.outofthecloset.org/",
    "wof:name":"Out of the Closet",
    "wof:placetype":"venue"
},
  "geometry": {"coordinates":[-122.279999,37.870499],"type":"Point"}
}