{
  "type": "Feature",
  "properties": {
    "addr:full":"633 N Central Ave Ste 100 Glendale CA 91203",
    "addr:housenumber":"633",
    "addr:postcode":"91203",
    "addr:street":"N Central Ave Ste 100",
    "iso:country":"US",
    "sg:address":"633 N Central Ave Ste 100",
    "sg:city":"Glendale",
    "sg:classifiers":[
        {
            "category":"Shopping",
            "subcategory":"Pharmacy",
            "type":"Retail Goods"
        }
    ],
    "sg:phone":"+1 818 244 2522",
    "sg:postcode":"91203",
    "sg:province":"CA",
    "sg:tags":[
        "drugstore"
    ],
    "wof:name":"Riley's Prescription Pharmacy",
    "wof:placetype":"venue"
},
  "geometry": {"coordinates":[-118.25812500000001,34.15527],"type":"Point"}
}