{
  "type": "Feature",
  "properties": {
    "iso:country":"US",
    "sg:address":"6747 Odessa Ave",
    "sg:city":"Van Nuys",
    "sg:classifiers":[
        {
            "category":"Building & Trades",
            "subcategory":"Electrical",
            "type":"Services"
        }
    ],
    "sg:phone":"+1 818 785 1957",
    "sg:postcode":"91406",
    "sg:province":"CA",
    "sg:tags":[
        "telecommunication",
        "contractor"
    ],
    "wof:name":"American Business Comms Co",
    "wof:placetype":"venue"
},
  "geometry": {"coordinates":[-118.490274,34.191223],"type":"Point"}
}