{
  "type": "Feature",
  "properties": {
    "addr:full":"257 8th Ave La Puente CA 91746",
    "addr:housenumber":"257",
    "addr:postcode":"91746",
    "addr:street":"8Th Ave",
    "iso:country":"US",
    "sg:address":"257 8th Ave",
    "sg:city":"La Puente",
    "sg:classifiers":[
        {
            "category":"Professional",
            "type":"Services"
        },
        {
            "category":"Retail",
            "subcategory":"Auto Repair",
            "type":"Services"
        }
    ],
    "sg:phone":"+1 626 961 9300",
    "sg:postcode":"91746",
    "sg:province":"CA",
    "sg:tags":[
        "automobile",
        "customizing"
    ],
    "wof:name":"Viv's Customs",
    "wof:placetype":"venue"
},
  "geometry": {"coordinates":[-117.972404,34.03145],"type":"Point"}
}