{
  "type": "Feature",
  "properties": {
    "iso:country":"US",
    "sg:address":"707 Zion St",
    "sg:city":"Nevada City",
    "sg:classifiers":[
        {
            "category":"Health Services",
            "subcategory":"Health Practitioner",
            "type":"Services"
        }
    ],
    "sg:phone":"+1 530 265 4298",
    "sg:postcode":"95959",
    "sg:province":"CA",
    "sg:tags":[
        "acupuncture"
    ],
    "wof:name":"Turiya Hill",
    "wof:placetype":"venue"
},
  "geometry": {"coordinates":[-121.025367,39.254802],"type":"Point"}
}