{
  "type": "Feature",
  "properties": {
    "iso:country":"US",
    "sg:address":"8256 Louise Ave",
    "sg:city":"Northridge",
    "sg:classifiers":[
        {
            "category":"Wholesale",
            "subcategory":"Medical Equipment & Supplies",
            "type":"Manufacturing & Wholesale Goods"
        }
    ],
    "sg:phone":"+1 818 881 2330",
    "sg:postcode":"91325",
    "sg:province":"CA",
    "sg:tags":[
        "physician",
        "surgeon"
    ],
    "wof:name":"Star Med Care Supply",
    "wof:placetype":"venue"
},
  "geometry": {"coordinates":[-118.50980300000001,34.220807],"type":"Point"}
}