{
  "type": "Feature",
  "properties": {
    "addr:full":"22 Galleria San Clemente CA 92688",
    "addr:housenumber":"22",
    "addr:postcode":"92688",
    "addr:street":"Galleria",
    "iso:country":"US",
    "sg:address":"22 Galleria",
    "sg:city":"San Clemente",
    "sg:classifiers":[
        {
            "category":"Organizations",
            "subcategory":"Professional Association",
            "type":"Services"
        }
    ],
    "sg:phone":"+1 949 361 4685",
    "sg:postcode":"92688",
    "sg:province":"CA",
    "wof:name":"Telega Gallerie Cmmnty Assn",
    "wof:placetype":"venue"
},
  "geometry": {"coordinates":[-117.613275,33.636042],"type":"Point"}
}