{
  "type": "Feature",
  "properties": {
    "addr:full":"1406 Highland Ave National City CA 91950",
    "addr:housenumber":"1406",
    "addr:postcode":"91950",
    "addr:street":"Highland Ave",
    "iso:country":"US",
    "sg:address":"1406 Highland Ave",
    "sg:city":"National City",
    "sg:classifiers":[
        {
            "category":"Restaurant",
            "type":"Food & Drink"
        }
    ],
    "sg:phone":"+1 619 336 0481",
    "sg:postcode":"91950",
    "sg:province":"CA",
    "wof:name":"Roberto's Taco Shop",
    "wof:placetype":"venue"
},
  "geometry": {"coordinates":[-117.09644900000001,32.672122],"type":"Point"}
}