{
  "type": "Feature",
  "properties": {
    "iso:country":"US",
    "sg:address":"111 S Robertson Blvd",
    "sg:city":"Los Angeles",
    "sg:classifiers":[
        {
            "category":"Home & Garden",
            "subcategory":"Furniture",
            "type":"Retail Goods"
        }
    ],
    "sg:phone":"+1 310 278 8191",
    "sg:postcode":"90048",
    "sg:province":"CA",
    "sg:tags":[
        "mattress"
    ],
    "wof:name":"Mcroskey Mattress Co",
    "wof:placetype":"venue"
},
  "geometry": {"coordinates":[-118.383843,34.073671],"type":"Point"}
}