{
  "type": "Feature",
  "properties": {
    "addr:full":"191 Echo Valley Rd Salinas CA 93907",
    "addr:housenumber":"191",
    "addr:postcode":"93907",
    "addr:street":"Echo Valley Rd",
    "iso:country":"US",
    "sg:address":"191 Echo Valley Rd",
    "sg:city":"Salinas",
    "sg:classifiers":[
        {
            "category":"Building & Trades",
            "subcategory":"Construction",
            "type":"Services"
        }
    ],
    "sg:phone":"+1 831 663 5373",
    "sg:postcode":"93907",
    "sg:province":"CA",
    "sg:tags":[
        "masonry",
        "contractor"
    ],
    "wof:name":"Greg Morris Masonry",
    "wof:placetype":"venue"
},
  "geometry": {"coordinates":[-121.66309099999999,36.825428],"type":"Point"}
}