{
  "type": "Feature",
  "properties": {
    "addr:full":"502 E Main St El Centro CA 92243",
    "addr:housenumber":"502",
    "addr:postcode":"92243",
    "addr:street":"E Main St",
    "iso:country":"US",
    "sg:address":"502 E Main St",
    "sg:city":"El Centro",
    "sg:classifiers":[
        {
            "category":"Social Services",
            "type":"Services"
        }
    ],
    "sg:phone":"+1 760 352 0180",
    "sg:postcode":"92243",
    "sg:province":"CA",
    "sg:tags":[
        "organization",
        "welfare"
    ],
    "wof:name":"Association-Retarded Citizens",
    "wof:placetype":"venue"
},
  "geometry": {"coordinates":[-115.535308,32.792902],"type":"Point"}
}