{
  "type": "Feature",
  "properties": {
    "iso:country":"US",
    "sg:address":"8775 Tamarind Ave",
    "sg:city":"Fontana",
    "sg:classifiers":[
        {
            "category":"Professional",
            "subcategory":"Art Services",
            "type":"Services"
        }
    ],
    "sg:phone":"+1 909 356 8549",
    "sg:postcode":"92335",
    "sg:province":"CA",
    "sg:tags":[
        "production",
        "music",
        "film"
    ],
    "wof:name":"Wall Street Corporation",
    "wof:placetype":"venue"
},
  "geometry": {"coordinates":[-117.422604,34.094629],"type":"Point"}
}