{
  "type": "Feature",
  "properties": {
    "addr:full":"1420 E Cooley Dr Colton CA 92324",
    "addr:housenumber":"1420",
    "addr:postcode":"92324",
    "addr:street":"E Cooley Dr",
    "iso:country":"US",
    "sg:address":"1420 E Cooley Dr",
    "sg:city":"Colton",
    "sg:classifiers":[
        {
            "category":"Professional",
            "subcategory":"Management & Consulting",
            "type":"Services"
        }
    ],
    "sg:phone":"+1 909 783 2558",
    "sg:postcode":"92324",
    "sg:province":"CA",
    "sg:tags":[
        "consultant"
    ],
    "wof:name":"International Trade Conslnt",
    "wof:placetype":"venue"
},
  "geometry": {"coordinates":[-117.30033400000001,34.059881],"type":"Point"}
}