{
  "type": "Feature",
  "properties": {
    "addr:full":"1630 Orchard Dr Placentia CA 92870",
    "addr:housenumber":"1630",
    "addr:postcode":"ca 92870",
    "addr:street":"Orchard Dr",
    "iso:country":"US",
    "sg:address":"1630 Orchard Dr",
    "sg:city":"Placentia",
    "sg:classifiers":[
        {
            "category":"Real Estate",
            "subcategory":"Real Estate Operator",
            "type":"Services"
        }
    ],
    "sg:phone":"+1 714 524 8130",
    "sg:postcode":"92870",
    "sg:province":"CA",
    "sg:tags":[
        "apartment"
    ],
    "wof:name":"William Lyon Company",
    "wof:placetype":"venue"
},
  "geometry": {"coordinates":[-117.830348,33.871045],"type":"Point"}
}