{
  "type": "Feature",
  "properties": {
    "iso:country":"US",
    "sg:address":"6755 Mira Mesa Blvd",
    "sg:city":"San Diego",
    "sg:classifiers":[
        {
            "category":"Real Estate",
            "subcategory":"Real Estate Agent",
            "type":"Services"
        }
    ],
    "sg:phone":"+1 858 453 1222",
    "sg:postcode":"92126",
    "sg:province":"CA",
    "wof:name":"Circle R Realty",
    "wof:placetype":"venue"
},
  "geometry": {"coordinates":[-117.171302,32.907565],"type":"Point"}
}