{
  "type": "Feature",
  "properties": {
    "iso:country":"US",
    "sg:address":"720 E Dyer Rd",
    "sg:city":"Santa Ana",
    "sg:classifiers":[
        {
            "category":"Restaurant",
            "type":"Food & Drink"
        }
    ],
    "sg:menulink":"http://www.allmenus.com/ca/anaheim-santa-ana-garden-grove/178289-jack-in-the-box/menu/",
    "sg:phone":"+1 714 546 4296",
    "sg:postcode":"92705",
    "sg:province":"CA",
    "sg:tags":[
        "burger",
        "american"
    ],
    "wof:name":"Jack in the Box",
    "wof:placetype":"venue"
},
  "geometry": {"coordinates":[-117.85503199999999,33.708086],"type":"Point"}
}