{
  "type": "Feature",
  "properties": {
    "addr:full":"118 Princeton Ave Claremont CA 91711",
    "addr:housenumber":"118",
    "addr:postcode":"91711",
    "addr:street":"Princeton Ave",
    "iso:country":"US",
    "sg:address":"118 Princeton Ave",
    "sg:city":"Claremont",
    "sg:classifiers":[
        {
            "category":"Retail",
            "subcategory":"Laundry & Dry Cleaning",
            "type":"Services"
        }
    ],
    "sg:phone":"+1 909 626 0716",
    "sg:postcode":"91711",
    "sg:province":"CA",
    "sg:tags":[
        "cleaners",
        "rug",
        "carpet"
    ],
    "wof:name":"Fibercare & Svc",
    "wof:placetype":"venue"
},
  "geometry": {"coordinates":[-117.728455,34.090646],"type":"Point"}
}