{
  "type": "Feature",
  "properties": {
    "iso:country":"US",
    "sg:address":"5900 Triumph St",
    "sg:city":"Los Angeles",
    "sg:classifiers":[
        {
            "category":"Home & Garden",
            "subcategory":"Furniture",
            "type":"Retail Goods"
        }
    ],
    "sg:phone":"+1 323 262 2490",
    "sg:postcode":"90040",
    "sg:province":"CA",
    "sg:tags":[
        "store"
    ],
    "sg:website":"www.cfoakton.com",
    "wof:name":"C F Oakton Furniture",
    "wof:placetype":"venue"
},
  "geometry": {"coordinates":[-118.14482700000001,34.004674],"type":"Point"}
}