{
  "type": "Feature",
  "properties": {
    "iso:country":"US",
    "sg:address":"417 Washington Blvd",
    "sg:city":"Venice",
    "sg:classifiers":[
        {
            "category":"Real Estate",
            "subcategory":"Real Estate Agent",
            "type":"Services"
        }
    ],
    "sg:phone":"+1 310 306 3504",
    "sg:postcode":"90292",
    "sg:province":"CA",
    "wof:name":"KMK Capital Corp",
    "wof:placetype":"venue"
},
  "geometry": {"coordinates":[-118.463081,33.981345],"type":"Point"}
}