{
  "type": "Feature",
  "properties": {
    "addr:full":"417 E Randolph St Glendale CA 91207",
    "addr:housenumber":"417",
    "addr:postcode":"91207",
    "addr:street":"E Randolph St",
    "iso:country":"US",
    "sg:address":"417 E Randolph St",
    "sg:city":"Glendale",
    "sg:classifiers":[
        {
            "category":"Building & Trades",
            "subcategory":"Plumbing",
            "type":"Services"
        }
    ],
    "sg:phone":"+1 818 545 0653",
    "sg:postcode":"91207",
    "sg:province":"CA",
    "sg:tags":[
        "air",
        "conditioning",
        "general",
        "heating",
        "contractor"
    ],
    "wof:name":"Alp Heating & Air Conditioning",
    "wof:placetype":"venue"
},
  "geometry": {"coordinates":[-118.249492,34.165286],"type":"Point"}
}