{
  "type": "Feature",
  "properties": {
    "addr:full":"2207 Garnet Avenue San Diego CA 92109",
    "addr:housenumber":"2207",
    "addr:postcode":"92109",
    "addr:street":"Garnet Avenue",
    "iso:country":"US",
    "sg:address":"2207 Garnet Avenue",
    "sg:city":"San Diego",
    "sg:classifiers":[
        {
            "category":"Real Estate",
            "subcategory":"Real Estate Services",
            "type":"Services"
        }
    ],
    "sg:phone":"+1 858 490 1600",
    "sg:postcode":"92109",
    "sg:province":"CA",
    "sg:tags":[
        "management",
        "property"
    ],
    "wof:name":"K & R Properties",
    "wof:placetype":"venue"
},
  "geometry": {"coordinates":[-117.22975,32.80222],"type":"Point"}
}