{
  "type": "Feature",
  "properties": {
    "iso:country":"US",
    "sg:address":"2764 Cochran St",
    "sg:city":"Simi Valley",
    "sg:classifiers":[
        {
            "category":"Utilities",
            "subcategory":"Telephone",
            "type":"Services"
        }
    ],
    "sg:phone":"+1 805 583 9000",
    "sg:postcode":"93065",
    "sg:province":"CA",
    "sg:tags":[
        "communications",
        "company"
    ],
    "wof:name":"Power Communications",
    "wof:placetype":"venue"
},
  "geometry": {"coordinates":[-118.743047,34.278917],"type":"Point"}
}