{
  "type": "Feature",
  "properties": {
    "addr:full":"4532 S Minturn Rd Le Grand CA 95333",
    "addr:housenumber":"4532",
    "addr:postcode":"95333",
    "addr:street":"S Minturn Rd",
    "iso:country":"US",
    "sg:address":"4532 S Minturn Rd",
    "sg:city":"Le Grand",
    "sg:phone":"+1 209 389 4681",
    "sg:postcode":"95333",
    "sg:province":"CA",
    "sg:tags":[
        "farm",
        "corn",
        "wheat",
        "cotton"
    ],
    "wof:name":"Double G Farms",
    "wof:placetype":"venue"
},
  "geometry": {"coordinates":[-120.27074399999999,37.220671],"type":"Point"}
}