{
  "type": "Feature",
  "properties": {
    "addr:full":"2410 San Ramon Valley Blvd San Ramon CA 94583",
    "addr:housenumber":"2410",
    "addr:postcode":"94583",
    "addr:street":"San Ramon Valley Blvd",
    "iso:country":"US",
    "sg:address":"2410 San Ramon Valley Blvd",
    "sg:city":"San Ramon",
    "sg:classifiers":[
        {
            "category":"Restaurant",
            "type":"Food & Drink"
        }
    ],
    "sg:phone":"+1 925 820 0401",
    "sg:postcode":"94583",
    "sg:province":"CA",
    "sg:website":"www.tgifridays.com",
    "wof:name":"TGI Friday's",
    "wof:placetype":"venue"
},
  "geometry": {"coordinates":[-121.973631,37.771479],"type":"Point"}
}