{
  "type": "Feature",
  "properties": {
    "iso:country":"US",
    "sg:address":"3240 Quartz Ln",
    "sg:city":"Fullerton",
    "sg:classifiers":[
        {
            "category":"Building & Trades",
            "subcategory":"Construction",
            "type":"Services"
        }
    ],
    "sg:phone":"+1 714 366 5114",
    "sg:postcode":"92831",
    "sg:province":"CA",
    "sg:tags":[
        "tile",
        "dealer"
    ],
    "wof:name":"Advanced Sales Solutions",
    "wof:placetype":"venue"
},
  "geometry": {"coordinates":[-117.867832,33.883701],"type":"Point"}
}