{
  "type": "Feature",
  "properties": {
    "addr:full":"555 S State Hwy 49 Jackson CA 95642",
    "addr:housenumber":"555",
    "addr:postcode":"95642",
    "addr:street":"S State Hwy 49",
    "iso:country":"US",
    "sg:address":"555 S State Hwy 49",
    "sg:city":"Jackson",
    "sg:classifiers":[
        {
            "category":"Professional",
            "subcategory":"Management & Consulting",
            "type":"Services"
        }
    ],
    "sg:phone":"+1 209 257 0556",
    "sg:postcode":"95642",
    "sg:province":"CA",
    "sg:tags":[
        "retail",
        "direct",
        "sales"
    ],
    "wof:name":"Less Cost Food Co",
    "wof:placetype":"venue"
},
  "geometry": {"coordinates":[-120.77041800000001,38.344928],"type":"Point"}
}