{
  "type": "Feature",
  "properties": {
    "addr:full":"1437 Franklin St Oakland CA 94612",
    "addr:housenumber":"1437",
    "addr:postcode":"94612",
    "addr:street":"Franklin St",
    "iso:country":"US",
    "sg:address":"1437 Franklin St",
    "sg:city":"Oakland",
    "sg:classifiers":[
        {
            "category":"Restaurant",
            "type":"Food & Drink"
        }
    ],
    "sg:phone":"+1 510 251 9688",
    "sg:postcode":"94612",
    "sg:province":"CA",
    "sg:tags":[
        "chinese"
    ],
    "sg:website":"www.letasty.com",
    "wof:name":"Le Tasty Restaurant",
    "wof:placetype":"venue"
},
  "geometry": {"coordinates":[-122.269997,37.804298],"type":"Point"}
}