{
  "type": "Feature",
  "properties": {
    "addr:full":"920 S Coast Hwy Ste A Oceanside CA 92054",
    "addr:housenumber":"920",
    "addr:postcode":"92054",
    "addr:street":"S Coast Hwy Ste A",
    "iso:country":"US",
    "sg:address":"920 S Coast Hwy Ste A",
    "sg:city":"Oceanside",
    "sg:classifiers":[
        {
            "category":"Autos & Motor Vehicles",
            "subcategory":"Automobile Sales",
            "type":"Retail Goods"
        }
    ],
    "sg:phone":"+1 888 666 0746",
    "sg:postcode":"92054",
    "sg:province":"CA",
    "sg:tags":[
        "car"
    ],
    "wof:name":"Showtime Auto Brokers",
    "wof:placetype":"venue"
},
  "geometry": {"coordinates":[-117.372131,33.187088],"type":"Point"}
}