{
  "type": "Feature",
  "properties": {
    "addr:full":"922 San Leandro Ave Mountain View CA 94043",
    "addr:housenumber":"922",
    "addr:postcode":"94043",
    "addr:street":"San Leandro Ave",
    "iso:country":"US",
    "sg:address":"922 San Leandro Ave",
    "sg:city":"Mountain View",
    "sg:classifiers":[
        {
            "category":"Communications",
            "type":"Services"
        }
    ],
    "sg:phone":"+1 650 230 0184",
    "sg:postcode":"94043",
    "sg:province":"CA",
    "sg:tags":[
        "communication"
    ],
    "wof:name":"T & D Communications",
    "wof:placetype":"venue"
},
  "geometry": {"coordinates":[-122.071186,37.40799],"type":"Point"}
}