{
  "type": "Feature",
  "properties": {
    "addr:full":"1479 Berger Dr San Jose CA 95112",
    "addr:housenumber":"1479",
    "addr:postcode":"95112",
    "addr:street":"Berger Dr",
    "iso:country":"US",
    "sg:address":"1479 Berger Dr",
    "sg:city":"San Jose",
    "sg:classifiers":[
        {
            "category":"Building & Trades",
            "subcategory":"Plumbing",
            "type":"Services"
        }
    ],
    "sg:phone":"+1 408 266 2140",
    "sg:postcode":"95112",
    "sg:province":"CA",
    "sg:tags":[
        "plumbing",
        "contractor"
    ],
    "wof:name":"Plumb-A-Rooter",
    "wof:placetype":"venue"
},
  "geometry": {"coordinates":[-121.897435,37.370793],"type":"Point"}
}