{
  "type": "Feature",
  "properties": {
    "addr:full":"1515 S Coast Hwy Oceanside CA 92054",
    "addr:housenumber":"1515",
    "addr:postcode":"92054",
    "addr:street":"S Coast Hwy",
    "iso:country":"US",
    "sg:address":"1515 S Coast Hwy",
    "sg:city":"Oceanside",
    "sg:classifiers":[
        {
            "category":"Retail",
            "subcategory":"Auto Repair",
            "type":"Services"
        }
    ],
    "sg:phone":"+1 760 722 6852",
    "sg:postcode":"92054",
    "sg:province":"CA",
    "wof:name":"Automan Car Service",
    "wof:placetype":"venue"
},
  "geometry": {"coordinates":[-117.36599699999999,33.179699],"type":"Point"}
}