{
  "type": "Feature",
  "properties": {
    "addr:full":"7840 Madison Ave Fair Oaks CA 95628",
    "addr:housenumber":"7840",
    "addr:postcode":"95628",
    "addr:street":"Madison Ave",
    "iso:country":"US",
    "sg:address":"7840 Madison Ave",
    "sg:city":"Fair Oaks",
    "sg:classifiers":[
        {
            "category":"Building & Trades",
            "subcategory":"Construction",
            "type":"Services"
        }
    ],
    "sg:phone":"+1 530 673 1828",
    "sg:postcode":"95628",
    "sg:province":"CA",
    "sg:tags":[
        "company"
    ],
    "wof:name":"Leon Construction",
    "wof:placetype":"venue"
},
  "geometry": {"coordinates":[-121.27460499999999,38.663792],"type":"Point"}
}