{
  "type": "Feature",
  "properties": {
    "iso:country":"US",
    "sg:address":"825 Balboa Ave",
    "sg:city":"Capitola",
    "sg:classifiers":[
        {
            "category":"Recreation",
            "type":"Entertainment"
        }
    ],
    "sg:phone":"+1 831 479 0273",
    "sg:postcode":"95010",
    "sg:province":"CA",
    "sg:tags":[
        "party",
        "fishing"
    ],
    "sg:website":"www.parkplaceexcursions.com",
    "wof:name":"Park Place Excursions",
    "wof:placetype":"venue"
},
  "geometry": {"coordinates":[-121.940344,36.979296],"type":"Point"}
}