{
  "type": "Feature",
  "properties": {
    "addr:full":"3956 Cll Cita Santa Barbara CA 93110",
    "addr:housenumber":"3956",
    "addr:postcode":"93110",
    "addr:street":"Cll Cita",
    "iso:country":"US",
    "sg:address":"3956 Cll Cita",
    "sg:city":"Santa Barbara",
    "sg:classifiers":[
        {
            "category":"Social Services",
            "type":"Services"
        }
    ],
    "sg:phone":"+1 805 898 3937",
    "sg:postcode":"93110",
    "sg:province":"CA",
    "sg:tags":[
        "counseling"
    ],
    "wof:name":"Love Coach To The Stars",
    "wof:placetype":"venue"
},
  "geometry": {"coordinates":[-119.752934,34.448602],"type":"Point"}
}