{
  "type": "Feature",
  "properties": {
    "iso:country":"US",
    "sg:address":"2345 E Coast Hwy",
    "sg:city":"Corona Del Mar",
    "sg:classifiers":[
        {
            "category":"Shopping",
            "subcategory":"Mobile Phones",
            "type":"Retail Goods"
        }
    ],
    "sg:phone":"+1 949 675 2072",
    "sg:postcode":"92625",
    "sg:province":"CA",
    "wof:name":"Oceanview Wireless 122",
    "wof:placetype":"venue"
},
  "geometry": {"coordinates":[-117.87483899999999,33.604649],"type":"Point"}
}