{
  "type": "Feature",
  "properties": {
    "iso:country":"US",
    "sg:address":"246 Kensington Park",
    "sg:city":"Irvine",
    "sg:classifiers":[
        {
            "category":"Building & Trades",
            "subcategory":"Landscaping Services",
            "type":"Services"
        }
    ],
    "sg:phone":"+1 949 500 6320",
    "sg:postcode":"92606",
    "sg:province":"CA",
    "wof:name":"Terratec Landscape",
    "wof:placetype":"venue"
},
  "geometry": {"coordinates":[-117.798564,33.7065],"type":"Point"}
}