{
  "type": "Feature",
  "properties": {
    "addr:full":"627 Vallejo St San Francisco CA 94133",
    "addr:housenumber":"627",
    "addr:postcode":"94133",
    "addr:street":"Vallejo St",
    "iso:country":"US",
    "sg:address":"627 Vallejo St",
    "sg:city":"San Francisco",
    "sg:classifiers":[
        {
            "category":"Professional",
            "type":"Services"
        }
    ],
    "sg:phone":"+1 415 986 4710",
    "sg:postcode":"94133",
    "sg:province":"CA",
    "sg:tags":[
        "caterer"
    ],
    "sg:website":"www.premiercatering.com",
    "wof:name":"Premier Catering & Events",
    "wof:placetype":"venue"
},
  "geometry": {"coordinates":[-122.40788999999999,37.798543],"type":"Point"}
}