{
  "type": "Feature",
  "properties": {
    "iso:country":"US",
    "sg:address":"100 E Orangethorpe Ave",
    "sg:city":"Anaheim",
    "sg:classifiers":[
        {
            "category":"Home & Garden",
            "subcategory":"Carpets & Floor Coverings",
            "type":"Retail Goods"
        }
    ],
    "sg:phone":"+1 714 447 3567",
    "sg:postcode":"92801",
    "sg:province":"CA",
    "sg:tags":[
        "mattress"
    ],
    "sg:website":"www.sweetdealssweetdreams.com",
    "wof:name":"Premium Mattress Outlet Inc",
    "wof:placetype":"venue"
},
  "geometry": {"coordinates":[-117.91799899999999,33.859402],"type":"Point"}
}