{
  "type": "Feature",
  "properties": {
    "addr:full":"7550 Tampa Ave Reseda CA 91335",
    "addr:housenumber":"7550",
    "addr:postcode":"91335",
    "addr:street":"Tampa Ave",
    "iso:country":"US",
    "sg:address":"7550 Tampa Ave",
    "sg:city":"Reseda",
    "sg:classifiers":[
        {
            "category":"Personal",
            "subcategory":"Beauty Salon",
            "type":"Services"
        }
    ],
    "sg:phone":"+1 818 344 7874",
    "sg:postcode":"91335",
    "sg:province":"CA",
    "sg:tags":[
        "manicuring"
    ],
    "wof:name":"Chic Nails",
    "wof:placetype":"venue"
},
  "geometry": {"coordinates":[-118.553454,34.207951],"type":"Point"}
}