{
  "type": "Feature",
  "properties": {
    "addr:full":"5445 48th St Sacramento CA 95820",
    "addr:housenumber":"5445",
    "addr:postcode":"95820",
    "addr:street":"48Th St",
    "iso:country":"US",
    "sg:address":"5445 48th St",
    "sg:city":"Sacramento",
    "sg:classifiers":[
        {
            "category":"Professional",
            "type":"Services"
        }
    ],
    "sg:phone":"+1 916 798 5109",
    "sg:postcode":"95820",
    "sg:province":"CA",
    "wof:name":"Pete's Custom Svc",
    "wof:placetype":"venue"
},
  "geometry": {"coordinates":[-121.447631,38.527225],"type":"Point"}
}