{
  "type": "Feature",
  "properties": {
    "addr:full":"1959 W 140th Ave San Leandro CA 94577",
    "addr:housenumber":"1959",
    "addr:postcode":"94577",
    "addr:street":"W 140Th Ave",
    "iso:country":"US",
    "sg:address":"1959 W 140th Ave",
    "sg:city":"San Leandro",
    "sg:classifiers":[
        {
            "category":"Home & Garden",
            "subcategory":"Home Furnishings",
            "type":"Retail Goods"
        },
        {
            "category":"Home & Garden",
            "subcategory":"Building Materials",
            "type":"Retail Goods"
        }
    ],
    "sg:phone":"+1 510 667 0856",
    "sg:postcode":"94577",
    "sg:province":"CA",
    "sg:tags":[
        "decor",
        "supply"
    ],
    "sg:website":"www.romarts.us",
    "wof:name":"Romarts Marble & Granite",
    "wof:placetype":"venue"
},
  "geometry": {"coordinates":[-122.167447,37.700564],"type":"Point"}
}