{
  "type": "Feature",
  "properties": {
    "addr:full":"13055 Tom White Way Norwalk CA 90650",
    "addr:housenumber":"13055",
    "addr:postcode":"90650",
    "addr:street":"Tom White Way",
    "iso:country":"US",
    "sg:address":"13055 Tom White Way",
    "sg:city":"Norwalk",
    "sg:classifiers":[
        {
            "category":"Professional",
            "type":"Services"
        }
    ],
    "sg:phone":"+1 562 404 2575",
    "sg:postcode":"90650",
    "sg:province":"CA",
    "wof:name":"Mike & Jim Mechanic",
    "wof:placetype":"venue"
},
  "geometry": {"coordinates":[-118.05358200000001,33.905217],"type":"Point"}
}