{
  "type": "Feature",
  "properties": {
    "iso:country":"US",
    "sg:address":"7669 Bellaire Ave",
    "sg:city":"North Hollywood",
    "sg:classifiers":[
        {
            "category":"Retail",
            "subcategory":"Laundry & Dry Cleaning",
            "type":"Services"
        }
    ],
    "sg:phone":"+1 818 753 3955",
    "sg:postcode":"91605",
    "sg:province":"CA",
    "sg:tags":[
        "cleaners",
        "rug",
        "carpet"
    ],
    "wof:name":"V & H Steam N Carpet Care",
    "wof:placetype":"venue"
},
  "geometry": {"coordinates":[-118.41036699999999,34.209387],"type":"Point"}
}