{
  "type": "Feature",
  "properties": {
    "addr:full":"10100 Empyrean Way Los Angeles CA 90067",
    "addr:postcode":"10100;90067",
    "addr:street":"Empyrean Way",
    "iso:country":"US",
    "sg:address":"10100 Empyrean Way",
    "sg:city":"Los Angeles",
    "sg:classifiers":[
        {
            "category":"Real Estate",
            "subcategory":"Real Estate Operator",
            "type":"Services"
        }
    ],
    "sg:phone":"+1 310 557 8400",
    "sg:postcode":"90067",
    "sg:province":"CA",
    "sg:tags":[
        "condominium"
    ],
    "wof:name":"Le Parc Condominiums",
    "wof:placetype":"venue"
},
  "geometry": {"coordinates":[-118.40941599999999,34.053458],"type":"Point"}
}