{
  "type": "Feature",
  "properties": {
    "iso:country":"US",
    "sg:address":"2201 W Pico Boulevard",
    "sg:city":"Los Angeles",
    "sg:classifiers":[
        {
            "category":"Personal",
            "subcategory":"Barber",
            "type":"Services"
        },
        {
            "category":"Retail",
            "subcategory":"Portrait Studio",
            "type":"Services"
        }
    ],
    "sg:phone":"+1 213 487 4686",
    "sg:postcode":"90006",
    "sg:province":"CA",
    "sg:tags":[
        "photography",
        "store"
    ],
    "wof:name":"Pico and Hoover 1Hr Photo",
    "wof:placetype":"venue"
},
  "geometry": {"coordinates":[-118.284211,34.047299],"type":"Point"}
}