{
  "type": "Feature",
  "properties": {
    "addr:full":"24 Via Ulmaria Rancho Santa Margarita CA 92688",
    "addr:postcode":"92688",
    "addr:street":"Via Ulmaria",
    "iso:country":"US",
    "sg:address":"24 Via Ulmaria",
    "sg:city":"Rancho Santa Margarita",
    "sg:classifiers":[
        {
            "category":"Utilities",
            "subcategory":"Telephone",
            "type":"Services"
        }
    ],
    "sg:phone":"+1 949 589 6221",
    "sg:postcode":"92688",
    "sg:province":"CA",
    "sg:tags":[
        "communications"
    ],
    "wof:name":"Cyberiran",
    "wof:placetype":"venue"
},
  "geometry": {"coordinates":[-117.57759299999999,33.650789],"type":"Point"}
}