{
  "type": "Feature",
  "properties": {
    "iso:country":"US",
    "sg:address":"815 Jones St",
    "sg:city":"Berkeley",
    "sg:classifiers":[
        {
            "category":"Professional",
            "subcategory":"Business Services",
            "type":"Services"
        },
        {
            "category":"Home & Garden",
            "subcategory":"Home Furnishings",
            "type":"Retail Goods"
        }
    ],
    "sg:phone":"+1 510 525 6863",
    "sg:postcode":"94710",
    "sg:province":"CA",
    "sg:tags":[
        "curtain",
        "grocery",
        "made",
        "drapery",
        "mfg"
    ],
    "wof:name":"Hopes Interior & Drapery",
    "wof:placetype":"venue"
},
  "geometry": {"coordinates":[-122.300455,37.875235],"type":"Point"}
}