{
  "type": "Feature",
  "properties": {
    "iso:country":"US",
    "sg:address":"1245 16th St",
    "sg:city":"Santa Monica",
    "sg:classifiers":[
        {
            "category":"Health Services",
            "subcategory":"Doctor",
            "type":"Services"
        }
    ],
    "sg:phone":"+1 310 829 0933",
    "sg:postcode":"90404",
    "sg:province":"CA",
    "sg:tags":[
        "dentist"
    ],
    "wof:name":"Herbert Binder Inc",
    "wof:placetype":"venue"
},
  "geometry": {"coordinates":[-118.485945,34.027617],"type":"Point"}
}