{
  "type": "Feature",
  "properties": {
    "addr:full":"4490 Riddle Rd Shasta Lake CA 96019",
    "addr:housenumber":"4490",
    "addr:postcode":"96019",
    "addr:street":"Riddle Rd",
    "iso:country":"US",
    "sg:address":"4490 Riddle Rd",
    "sg:city":"Shasta Lake",
    "sg:classifiers":[
        {
            "category":"Building & Trades",
            "subcategory":"Construction",
            "type":"Services"
        }
    ],
    "sg:phone":"+1 530 275 1998",
    "sg:postcode":"96019",
    "sg:province":"CA",
    "sg:tags":[
        "road",
        "contractor"
    ],
    "wof:name":"River City Construction",
    "wof:placetype":"venue"
},
  "geometry": {"coordinates":[-122.364091,40.652997],"type":"Point"}
}