{
  "type": "Feature",
  "properties": {
    "addr:full":"1041 S Broadway Los Angeles CA 90015",
    "addr:housenumber":"1041",
    "addr:postcode":"90015",
    "addr:street":"S Broadway",
    "iso:country":"US",
    "sg:address":"1041 S Broadway",
    "sg:city":"Los Angeles",
    "sg:classifiers":[
        {
            "category":"Shopping",
            "subcategory":"Clothing, Apparel, & Fashions",
            "type":"Retail Goods"
        }
    ],
    "sg:phone":"+1 213 747 6132",
    "sg:postcode":"90015",
    "sg:province":"CA",
    "wof:name":"Carolyn Fashion",
    "wof:placetype":"venue"
},
  "geometry": {"coordinates":[-118.258402,34.040199],"type":"Point"}
}