{
  "type": "Feature",
  "properties": {
    "addr:full":"2045 Burton Dr Cambria CA 93428",
    "addr:housenumber":"2045",
    "addr:postcode":"93428",
    "addr:street":"Burton Dr",
    "iso:country":"US",
    "sg:address":"2045 Burton Dr",
    "sg:city":"Cambria",
    "sg:classifiers":[
        {
            "category":"Manufacturing",
            "subcategory":"Metals",
            "type":"Manufacturing & Wholesale Goods"
        }
    ],
    "sg:phone":"+1 805 927 5544",
    "sg:postcode":"93428",
    "sg:province":"CA",
    "sg:tags":[
        "mfg"
    ],
    "wof:name":"Bug Off Instant Screen Door",
    "wof:placetype":"venue"
},
  "geometry": {"coordinates":[-121.07936100000001,35.549385],"type":"Point"}
}