{
  "type": "Feature",
  "properties": {
    "iso:country":"US",
    "sg:address":"11424 B Ave",
    "sg:city":"Auburn",
    "sg:classifiers":[
        {
            "category":"Government",
            "subcategory":"Office",
            "type":"Public Place"
        }
    ],
    "sg:phone":"+1 530 886 3010",
    "sg:postcode":"95603",
    "sg:province":"CA",
    "wof:name":"Placer County Building Dept",
    "wof:placetype":"venue"
},
  "geometry": {"coordinates":[-121.10585,38.938924],"type":"Point"}
}