{
  "type": "Feature",
  "properties": {
    "iso:country":"US",
    "sg:address":"99 Harding Rd",
    "sg:city":"San Francisco",
    "sg:classifiers":[
        {
            "category":"Retail",
            "subcategory":"Event Space",
            "type":"Services"
        },
        {
            "category":"Sports & Exercise",
            "subcategory":"Golf",
            "type":"Entertainment"
        }
    ],
    "sg:phone":"+1 415 664 4690",
    "sg:postcode":"94132",
    "sg:province":"CA",
    "sg:tags":[
        "venue"
    ],
    "sg:website":"www.harding-park.com",
    "wof:name":"Harding Park Clubhouse",
    "wof:placetype":"venue"
},
  "geometry": {"coordinates":[-122.496797,37.724154],"type":"Point"}
}