{
  "type": "Feature",
  "properties": {
    "iso:country":"US",
    "sg:address":"3161 Cameron Park Dr",
    "sg:city":"Cameron Park",
    "sg:classifiers":[
        {
            "category":"Professional",
            "type":"Services"
        },
        {
            "category":"Real Estate",
            "subcategory":"Real Estate Agent",
            "type":"Services"
        }
    ],
    "sg:phone":"+1 530 676 2376",
    "sg:postcode":"95682",
    "sg:province":"CA",
    "wof:name":"Sell Smart Advantage",
    "wof:placetype":"venue"
},
  "geometry": {"coordinates":[-120.984809,38.68331],"type":"Point"}
}