{
  "type": "Feature",
  "properties": {
    "iso:country":"US",
    "sg:address":"14460 Walnut Grove-Thornton Rd",
    "sg:city":"Walnut Grove",
    "sg:classifiers":[
        {
            "category":"Building & Trades",
            "subcategory":"Construction",
            "type":"Services"
        }
    ],
    "sg:phone":"+1 916 776 1722",
    "sg:postcode":"95690",
    "sg:province":"CA",
    "sg:tags":[
        "general",
        "contractor"
    ],
    "wof:name":"William M Schauer & Sons Inc",
    "wof:placetype":"venue"
},
  "geometry": {"coordinates":[-121.51272299999999,38.227696],"type":"Point"}
}