{
  "type": "Feature",
  "properties": {
    "addr:full":"3187 Mission St San Francisco CA 94110",
    "addr:housenumber":"3187",
    "addr:postcode":"94110",
    "addr:street":"Mission St",
    "iso:country":"US",
    "sg:address":"3187 Mission St",
    "sg:city":"San Francisco",
    "sg:classifiers":[
        {
            "category":"Bars & Pubs",
            "subcategory":"Dive Bar",
            "type":"Food & Drink"
        }
    ],
    "sg:phone":"+1 415 824 1447",
    "sg:postcode":"94110",
    "sg:province":"CA",
    "sg:website":"www.arguslounge.com",
    "wof:name":"Argus",
    "wof:placetype":"venue"
},
  "geometry": {"coordinates":[-122.419436,37.745783],"type":"Point"}
}