{
  "type": "Feature",
  "properties": {
    "iso:country":"US",
    "sg:address":"1675 W Lacey Blvd",
    "sg:city":"Hanford",
    "sg:classifiers":[
        {
            "category":"Shopping",
            "subcategory":"Luggage & Leather Goods",
            "type":"Retail Goods"
        }
    ],
    "sg:phone":"+1 559 587 9953",
    "sg:postcode":"93230",
    "sg:province":"CA",
    "wof:name":"Global Luggage & Leather",
    "wof:placetype":"venue"
},
  "geometry": {"coordinates":[-119.671767,36.327917],"type":"Point"}
}