{
  "type": "Feature",
  "properties": {
    "iso:country":"US",
    "sg:address":"35 E 3rd Avenue",
    "sg:city":"San Mateo",
    "sg:classifiers":[
        {
            "category":"Restaurant",
            "type":"Food & Drink"
        }
    ],
    "sg:phone":"+1 650 347 2722",
    "sg:postcode":"94401",
    "sg:province":"CA",
    "sg:tags":[
        "chinese"
    ],
    "wof:name":"Tina's Gourmet",
    "wof:placetype":"venue"
},
  "geometry": {"coordinates":[-122.325354,37.563472],"type":"Point"}
}