{
  "type": "Feature",
  "properties": {
    "addr:full":"587 E El Camino Real Sunnyvale CA 94087",
    "addr:housenumber":"587",
    "addr:postcode":"94087",
    "addr:street":"E El Camino Real",
    "iso:country":"US",
    "sg:address":"587 E El Camino Real",
    "sg:city":"Sunnyvale",
    "sg:classifiers":[
        {
            "category":"Sports & Exercise",
            "subcategory":"Gym",
            "type":"Entertainment"
        }
    ],
    "sg:phone":"+1 408 245 9642",
    "sg:postcode":"94087",
    "sg:province":"CA",
    "sg:tags":[
        "yoga"
    ],
    "sg:website":"www.hanyoga.net",
    "wof:name":"Han Yoga",
    "wof:placetype":"venue"
},
  "geometry": {"coordinates":[-122.025251,37.362132],"type":"Point"}
}