{
  "type": "Feature",
  "properties": {
    "addr:full":"37 Quail Ct Walnut Creek CA 94596",
    "addr:housenumber":"37",
    "addr:postcode":"94596",
    "addr:street":"Quail Ct",
    "iso:country":"US",
    "sg:address":"37 Quail Ct",
    "sg:city":"Walnut Creek",
    "sg:classifiers":[
        {
            "category":"Social Services",
            "type":"Services"
        }
    ],
    "sg:phone":"+1 925 932 9898",
    "sg:postcode":"94596",
    "sg:province":"CA",
    "sg:tags":[
        "counselor",
        "marriage",
        "family"
    ],
    "wof:name":"Casi Kushel",
    "wof:placetype":"venue"
},
  "geometry": {"coordinates":[-122.05521400000001,37.887847],"type":"Point"}
}