{
  "type": "Feature",
  "properties": {
    "addr:full":"700 E Ave S Palmdale CA 93550",
    "addr:housenumber":"700",
    "addr:postcode":"ca 93550",
    "addr:street":"E Ave S",
    "iso:country":"US",
    "sg:address":"700 E Ave S",
    "sg:city":"Palmdale",
    "sg:classifiers":[
        {
            "category":"Utilities",
            "subcategory":"Water",
            "type":"Services"
        }
    ],
    "sg:phone":"+1 661 947 0232",
    "sg:postcode":"93550",
    "sg:province":"CA",
    "sg:tags":[
        "supply"
    ],
    "wof:name":"Palmdale Wtr Dst Trtmnt Plant",
    "wof:placetype":"venue"
},
  "geometry": {"coordinates":[-118.113891,34.557989],"type":"Point"}
}