{
  "type": "Feature",
  "properties": {
    "iso:country":"US",
    "sg:address":"504 Washington St",
    "sg:city":"Calistoga",
    "sg:classifiers":[
        {
            "category":"Building & Trades",
            "subcategory":"Construction",
            "type":"Services"
        }
    ],
    "sg:phone":"+1 707 942 5393",
    "sg:postcode":"94515",
    "sg:province":"CA",
    "sg:tags":[
        "maker",
        "cabinet"
    ],
    "wof:name":"Glenn Pope Woodworking",
    "wof:placetype":"venue"
},
  "geometry": {"coordinates":[-122.57181,38.576529],"type":"Point"}
}