{
  "type": "Feature",
  "properties": {
    "iso:country":"US",
    "sg:address":"7318 Melrose Ave",
    "sg:city":"Los Angeles",
    "sg:classifiers":[
        {
            "category":"Professional",
            "type":"Services"
        },
        {
            "category":"Shopping",
            "subcategory":"Clothing, Apparel, & Fashions",
            "type":"Retail Goods"
        }
    ],
    "sg:phone":"+1 323 936 0413",
    "sg:postcode":"90046",
    "sg:province":"CA",
    "sg:tags":[
        "accessory"
    ],
    "wof:name":"Chaque Jour Inc",
    "wof:placetype":"venue"
},
  "geometry": {"coordinates":[-118.34945999999999,34.083473],"type":"Point"}
}