{
  "type": "Feature",
  "properties": {
    "addr:full":"21550 Oxnard St Ste 450 Woodland Hls CA 91367",
    "addr:housenumber":"21550",
    "addr:postcode":"91367",
    "addr:street":"Oxnard St Ste 450",
    "iso:country":"US",
    "sg:address":"21550 Oxnard St Ste 450",
    "sg:city":"Woodland Hls",
    "sg:classifiers":[
        {
            "category":"Banks & Credit Unions",
            "subcategory":"Investment Brokerage",
            "type":"Services"
        }
    ],
    "sg:phone":"+1 818 224 6063",
    "sg:postcode":"91367",
    "sg:province":"CA",
    "sg:tags":[
        "investing"
    ],
    "wof:name":"Ventura Advisors",
    "wof:placetype":"venue"
},
  "geometry": {"coordinates":[-118.599458,34.179165],"type":"Point"}
}