{
  "type": "Feature",
  "properties": {
    "addr:full":"11732 Craw Ave Chino CA 91710",
    "addr:postcode":"11732;91710",
    "addr:street":"Craw Ave",
    "iso:country":"US",
    "sg:address":"11732 Craw Ave",
    "sg:city":"Chino",
    "sg:classifiers":[
        {
            "category":"Building & Trades",
            "subcategory":"Plumbing",
            "type":"Services"
        }
    ],
    "sg:phone":"+1 909 628 3303",
    "sg:postcode":"91710",
    "sg:province":"CA",
    "sg:tags":[
        "conditioning",
        "air",
        "system",
        "contractor"
    ],
    "wof:name":"Supreme Refrigeration",
    "wof:placetype":"venue"
},
  "geometry": {"coordinates":[-117.693056,34.038092],"type":"Point"}
}