{
  "type": "Feature",
  "properties": {
    "addr:full":"2695 N Sunnyside Ave Fresno CA 93727",
    "addr:housenumber":"2695",
    "addr:postcode":"93727",
    "addr:street":"N Sunnyside Ave",
    "iso:country":"US",
    "sg:address":"2695 N Sunnyside Ave",
    "sg:city":"Fresno",
    "sg:classifiers":[
        {
            "category":"Manufacturing",
            "subcategory":"Metals",
            "type":"Manufacturing & Wholesale Goods"
        }
    ],
    "sg:phone":"+1 559 294 1414",
    "sg:postcode":"93727",
    "sg:province":"CA",
    "sg:tags":[
        "metalwork",
        "architectural",
        "mfg"
    ],
    "wof:name":"M & M Metal Crafts",
    "wof:placetype":"venue"
},
  "geometry": {"coordinates":[-119.691956,36.774738],"type":"Point"}
}