{
  "type": "Feature",
  "properties": {
    "addr:full":"726 Main St Redwood City CA 94063",
    "addr:housenumber":"726",
    "addr:postcode":"94063",
    "addr:street":"Main St",
    "iso:country":"US",
    "sg:address":"726 Main St",
    "sg:city":"Redwood City",
    "sg:classifiers":[
        {
            "category":"Professional",
            "subcategory":"Engineering",
            "type":"Services"
        }
    ],
    "sg:phone":"+1 650 367 8100",
    "sg:postcode":"94063",
    "sg:province":"CA",
    "sg:tags":[
        "engineer"
    ],
    "wof:name":"Crosby Group",
    "wof:placetype":"venue"
},
  "geometry": {"coordinates":[-122.226403,37.486879],"type":"Point"}
}