{
  "type": "Feature",
  "properties": {
    "iso:country":"US",
    "sg:address":"26017 Huntington Ln",
    "sg:city":"Valencia",
    "sg:classifiers":[
        {
            "category":"Social Services",
            "type":"Services"
        }
    ],
    "sg:phone":"+1 661 775 0911",
    "sg:postcode":"91355",
    "sg:province":"CA",
    "sg:tags":[
        "agency",
        "adoption"
    ],
    "wof:name":"Father's Heart Adoption Agency",
    "wof:placetype":"venue"
},
  "geometry": {"coordinates":[-118.590735,34.437048],"type":"Point"}
}