{
  "type": "Feature",
  "properties": {
    "iso:country":"US",
    "sg:address":"6419 Ehrlich Ct",
    "sg:city":"Magalia",
    "sg:classifiers":[
        {
            "category":"Organizations",
            "subcategory":"Professional Association",
            "type":"Services"
        }
    ],
    "sg:phone":"+1 530 873 0615",
    "sg:postcode":"95954",
    "sg:province":"CA",
    "wof:name":"Carlos On The Ridge",
    "wof:placetype":"venue"
},
  "geometry": {"coordinates":[-121.597711,39.828768],"type":"Point"}
}