{
  "type": "Feature",
  "properties": {
    "addr:full":"2541 del Paso blvd. Sacramento CA 95815",
    "addr:housenumber":"2541",
    "addr:postcode":"95815",
    "addr:street":"Del Paso Blvd.",
    "iso:country":"US",
    "sg:address":"2541 del Paso blvd.",
    "sg:city":"Sacramento",
    "sg:classifiers":[
        {
            "category":"Shopping Center",
            "type":"Public Place"
        }
    ],
    "sg:phone":"+1 916 922 9009",
    "sg:postcode":"95815",
    "sg:province":"CA",
    "wof:name":"Dollar Plus",
    "wof:placetype":"venue"
},
  "geometry": {"coordinates":[-121.446308,38.613435],"type":"Point"}
}