{
  "type": "Feature",
  "properties": {
    "addr:full":"110 W C St Ste 1415 San Diego CA 92101",
    "addr:housenumber":"110",
    "addr:postcode":"92101",
    "addr:street":"W C St Ste 1415",
    "iso:country":"US",
    "sg:address":"110 W C St Ste 1415",
    "sg:city":"San Diego",
    "sg:classifiers":[
        {
            "category":"Professional",
            "subcategory":"Lawyer & Legal Services",
            "type":"Services"
        }
    ],
    "sg:phone":"+1 619 531 0111",
    "sg:postcode":"92101",
    "sg:province":"CA",
    "wof:name":"Bove Rick L",
    "wof:placetype":"venue"
},
  "geometry": {"coordinates":[-117.164001,32.716702],"type":"Point"}
}