{
  "type": "Feature",
  "properties": {
    "addr:full":"1238 West St Redding CA 96001",
    "addr:housenumber":"1238",
    "addr:postcode":"96001",
    "addr:street":"West St",
    "iso:country":"US",
    "sg:address":"1238 West St",
    "sg:city":"Redding",
    "sg:classifiers":[
        {
            "category":"Health Services",
            "subcategory":"Doctor",
            "type":"Services"
        }
    ],
    "sg:phone":"+1 530 246 2467",
    "sg:postcode":"96001",
    "sg:province":"CA",
    "sg:tags":[
        "physician",
        "family",
        "practice",
        "surgeons",
        "medicine",
        "surgeon"
    ],
    "wof:name":"Paul Schwartz Md",
    "wof:placetype":"venue"
},
  "geometry": {"coordinates":[-122.398411,40.585646],"type":"Point"}
}