{
  "type": "Feature",
  "properties": {
    "iso:country":"US",
    "sg:address":"1483 El Camino Real",
    "sg:city":"Santa Clara",
    "sg:classifiers":[
        {
            "category":"Retail",
            "subcategory":"Car Wash",
            "type":"Services"
        }
    ],
    "sg:phone":"+1 408 246 3308",
    "sg:postcode":"95050",
    "sg:province":"CA",
    "wof:name":"Santa Clara Car Wash",
    "wof:placetype":"venue"
},
  "geometry": {"coordinates":[-121.95500199999999,37.352402],"type":"Point"}
}