{
  "type": "Feature",
  "properties": {
    "addr:full":"16730 Bernardo Center Dr San Diego CA 92128",
    "addr:housenumber":"16730",
    "addr:postcode":"92128",
    "addr:street":"Bernardo Center Dr",
    "iso:country":"US",
    "sg:address":"16730 Bernardo Center Dr",
    "sg:city":"San Diego",
    "sg:classifiers":[
        {
            "category":"Real Estate",
            "subcategory":"Real Estate Agent",
            "type":"Services"
        }
    ],
    "sg:phone":"+1 858 673 0319",
    "sg:postcode":"92128",
    "sg:province":"CA",
    "wof:name":"Brooks Results Team",
    "wof:placetype":"venue"
},
  "geometry": {"coordinates":[-117.075686,33.018022],"type":"Point"}
}