{
  "type": "Feature",
  "properties": {
    "addr:full":"809 Channing Way Berkeley CA 94710",
    "addr:housenumber":"809",
    "addr:postcode":"94710",
    "addr:street":"Channing Way",
    "iso:country":"US",
    "sg:address":"809 Channing Way",
    "sg:city":"Berkeley",
    "sg:classifiers":[
        {
            "category":"Building & Trades",
            "subcategory":"Construction",
            "type":"Services"
        }
    ],
    "sg:phone":"+1 510 841 3607",
    "sg:postcode":"94710",
    "sg:province":"CA",
    "sg:tags":[
        "house"
    ],
    "wof:name":"Indian Rock Cnstr & Design",
    "wof:placetype":"venue"
},
  "geometry": {"coordinates":[-122.29619,37.861726],"type":"Point"}
}