{
  "type": "Feature",
  "properties": {
    "addr:full":"6615 Convoy Ct San Diego CA 92111",
    "addr:housenumber":"6615",
    "addr:postcode":"92111",
    "addr:street":"Convoy Ct",
    "iso:country":"US",
    "sg:address":"6615 Convoy Ct",
    "sg:city":"San Diego",
    "sg:classifiers":[
        {
            "category":"Professional",
            "type":"Services"
        }
    ],
    "sg:phone":"+1 858 361 2329",
    "sg:postcode":"92111",
    "sg:province":"CA",
    "wof:name":"Da Phone Guy",
    "wof:placetype":"venue"
},
  "geometry": {"coordinates":[-117.16821299999999,32.834632],"type":"Point"}
}