{
  "type": "Feature",
  "properties": {
    "iso:country":"US",
    "sg:address":"311 E Balboa Blvd",
    "sg:city":"Newport Beach",
    "sg:classifiers":[
        {
            "category":"Health Services",
            "subcategory":"Doctor",
            "type":"Services"
        }
    ],
    "sg:phone":"+1 949 721 1323",
    "sg:postcode":"92661",
    "sg:province":"CA",
    "wof:name":"Fleming Kirsten MD",
    "wof:placetype":"venue"
},
  "geometry": {"coordinates":[-117.903684,33.603197],"type":"Point"}
}