{
  "type": "Feature",
  "properties": {
    "addr:full":"12929 Telegraph Rd Santa Fe Springs CA 90670",
    "addr:housenumber":"12929",
    "addr:postcode":"90670",
    "addr:street":"Telegraph Rd",
    "iso:country":"US",
    "sg:address":"12929 Telegraph Rd",
    "sg:city":"Santa Fe Springs",
    "sg:classifiers":[
        {
            "category":"Autos & Motor Vehicles",
            "subcategory":"Motorcycle Sales",
            "type":"Retail Goods"
        }
    ],
    "sg:phone":"+1 562 903 7757",
    "sg:postcode":"90670",
    "sg:province":"CA",
    "sg:tags":[
        "scooter"
    ],
    "wof:name":"Attack Performance",
    "wof:placetype":"venue"
},
  "geometry": {"coordinates":[-118.056184,33.941894],"type":"Point"}
}