{
  "type": "Feature",
  "properties": {
    "addr:full":"106 W Branch St Arroyo Grande CA 93420",
    "addr:housenumber":"106",
    "addr:postcode":"93420",
    "addr:street":"W Branch St",
    "iso:country":"US",
    "sg:address":"106 W Branch St",
    "sg:city":"Arroyo Grande",
    "sg:classifiers":[
        {
            "category":"Shopping",
            "subcategory":"Used Merchandise",
            "type":"Retail Goods"
        }
    ],
    "sg:phone":"+1 805 481 0404",
    "sg:postcode":"93420",
    "sg:province":"CA",
    "sg:tags":[
        "antique"
    ],
    "wof:name":"Posies",
    "wof:placetype":"venue"
},
  "geometry": {"coordinates":[-120.581028,35.122682],"type":"Point"}
}