{
  "type": "Feature",
  "properties": {
    "addr:full":"1350 Burton Dr Bldg B Vacaville CA 95687",
    "addr:housenumber":"1350",
    "addr:postcode":"95687",
    "addr:street":"Burton Dr Bldg B",
    "iso:country":"US",
    "sg:address":"1350 Burton Dr Bldg B",
    "sg:city":"Vacaville",
    "sg:classifiers":[
        {
            "category":"Health Services",
            "subcategory":"Clinic",
            "type":"Services"
        }
    ],
    "sg:phone":"+1 707 446 4379",
    "sg:postcode":"95687",
    "sg:province":"CA",
    "sg:tags":[
        "welfare"
    ],
    "wof:name":"Davita Nephrology Medical Associates Of California Inc",
    "wof:placetype":"venue"
},
  "geometry": {"coordinates":[-121.95430899999999,38.36486],"type":"Point"}
}