{
  "type": "Feature",
  "properties": {
    "addr:full":"16410 S Vermont Ave Gardena CA 90247",
    "addr:housenumber":"16410",
    "addr:postcode":"90247",
    "addr:street":"S Vermont Ave",
    "iso:country":"US",
    "sg:address":"16410 S Vermont Ave",
    "sg:city":"Gardena",
    "sg:classifiers":[
        {
            "category":"Food & Beverages",
            "subcategory":"Specialty",
            "type":"Retail Goods"
        }
    ],
    "sg:phone":"+1 310 323 4690",
    "sg:postcode":"90247",
    "sg:province":"CA",
    "sg:tags":[
        "herb"
    ],
    "wof:name":"Salmo 23",
    "wof:placetype":"venue"
},
  "geometry": {"coordinates":[-118.29120899999999,33.882402],"type":"Point"}
}