{
  "type": "Feature",
  "properties": {
    "addr:full":"2508 E Brundage Ln Bakersfield CA 93307",
    "addr:housenumber":"2508",
    "addr:postcode":"93307",
    "addr:street":"E Brundage Ln",
    "iso:country":"US",
    "sg:address":"2508 E Brundage Ln",
    "sg:city":"Bakersfield",
    "sg:classifiers":[
        {
            "category":"Manufacturing",
            "subcategory":"Tools & Machinery",
            "type":"Manufacturing & Wholesale Goods"
        }
    ],
    "sg:phone":"+1 661 322 3722",
    "sg:postcode":"93307",
    "sg:province":"CA",
    "sg:tags":[
        "contractor"
    ],
    "sg:website":"www.mobilestorage.com",
    "wof:name":"Mobile Storage Group",
    "wof:placetype":"venue"
},
  "geometry": {"coordinates":[-118.9599,35.354196],"type":"Point"}
}