{
  "type": "Feature",
  "properties": {
    "iso:country":"US",
    "sg:address":"1111 S Stockton St",
    "sg:city":"Lodi",
    "sg:classifiers":[
        {
            "category":"Manufacturing",
            "subcategory":"Metals",
            "type":"Manufacturing & Wholesale Goods"
        }
    ],
    "sg:phone":"+1 209 369 1055",
    "sg:postcode":"95240",
    "sg:province":"CA",
    "sg:tags":[
        "stampings"
    ],
    "wof:name":"Dependable Precision Mfg",
    "wof:placetype":"venue"
},
  "geometry": {"coordinates":[-121.269484,38.118582],"type":"Point"}
}