{
  "type": "Feature",
  "properties": {
    "addr:full":"3906 Ross Ave San Jose CA 95124",
    "addr:housenumber":"3906",
    "addr:postcode":"95124",
    "addr:street":"Ross Ave",
    "iso:country":"US",
    "sg:address":"3906 Ross Ave",
    "sg:city":"San Jose",
    "sg:classifiers":[
        {
            "category":"Shopping",
            "subcategory":"Hobbies, Toys, & Games",
            "type":"Retail Goods"
        }
    ],
    "sg:phone":"+1 408 265 8593",
    "sg:postcode":"95124",
    "sg:province":"CA",
    "wof:name":"Fine Crafts & Imports",
    "wof:placetype":"venue"
},
  "geometry": {"coordinates":[-121.91347399999999,37.258973],"type":"Point"}
}