{
  "type": "Feature",
  "properties": {
    "addr:full":"777 S Arroyo Prkwy Ste 103 Pasadena CA 91105",
    "addr:housenumber":"777",
    "addr:postcode":"91105",
    "addr:street":"S Arroyo Prkwy Ste 103",
    "iso:country":"US",
    "sg:address":"777 S Arroyo Prkwy Ste 103",
    "sg:city":"Pasadena",
    "sg:classifiers":[
        {
            "category":"Health Services",
            "subcategory":"Clinic",
            "type":"Services"
        },
        {
            "category":"Health Services",
            "subcategory":"Health Practitioner",
            "type":"Services"
        }
    ],
    "sg:phone":"+1 626 737 1234",
    "sg:postcode":"91105",
    "sg:province":"CA",
    "sg:tags":[
        "nutritionist",
        "loss",
        "weight"
    ],
    "sg:website":"www.nutrition4lessonline.com",
    "wof:name":"Nutrition 4 Less",
    "wof:placetype":"venue"
},
  "geometry": {"coordinates":[-118.147533,34.132297],"type":"Point"}
}