{
  "type": "Feature",
  "properties": {
    "iso:country":"US",
    "sg:address":"13533 Indian St",
    "sg:city":"Moreno Valley",
    "sg:classifiers":[
        {
            "category":"Building & Trades",
            "subcategory":"Construction",
            "type":"Services"
        }
    ],
    "sg:phone":"+1 951 485 2904",
    "sg:postcode":"92553",
    "sg:province":"CA",
    "sg:tags":[
        "concrete",
        "contractor"
    ],
    "wof:name":"Moreno Valley Concrete Constr",
    "wof:placetype":"venue"
},
  "geometry": {"coordinates":[-117.235111,33.923647],"type":"Point"}
}