{
  "type": "Feature",
  "properties": {
    "iso:country":"US",
    "sg:address":"3672 W Shaw Ave",
    "sg:city":"Fresno",
    "sg:classifiers":[
        {
            "category":"Banks & Credit Unions",
            "subcategory":"Bank",
            "type":"Services"
        }
    ],
    "sg:phone":"+1 559 274 1111",
    "sg:postcode":"93711",
    "sg:province":"CA",
    "sg:tags":[
        "cashing",
        "check"
    ],
    "wof:name":"Cash Plus",
    "wof:placetype":"venue"
},
  "geometry": {"coordinates":[-119.861959,36.808355],"type":"Point"}
}