{
  "type": "Feature",
  "properties": {
    "addr:full":"1084 N El Camino Real Encinitas CA 92024",
    "addr:housenumber":"1084",
    "addr:postcode":"92024",
    "addr:street":"N El Camino Real",
    "iso:country":"US",
    "sg:address":"1084 N El Camino Real",
    "sg:city":"Encinitas",
    "sg:classifiers":[
        {
            "category":"Restaurant",
            "type":"Food & Drink"
        }
    ],
    "sg:menulink":"http://www.allmenus.com/ca/san-diego/239842-panda-express/menu/",
    "sg:phone":"+1 760 943 8888",
    "sg:postcode":"92024",
    "sg:province":"CA",
    "sg:tags":[
        "asian",
        "chinese"
    ],
    "wof:name":"Panda Express",
    "wof:placetype":"venue"
},
  "geometry": {"coordinates":[-117.264465,33.065156],"type":"Point"}
}