{
  "type": "Feature",
  "properties": {
    "iso:country":"US",
    "sg:address":"3099 Snell Pl",
    "sg:city":"Marina",
    "sg:classifiers":[
        {
            "category":"Banks & Credit Unions",
            "subcategory":"Investment Brokerage",
            "type":"Services"
        },
        {
            "category":"Shopping",
            "subcategory":"Computers & Home Electronics",
            "type":"Retail Goods"
        }
    ],
    "sg:phone":"+1 831 655 1007",
    "sg:postcode":"93933",
    "sg:province":"CA",
    "sg:tags":[
        "dvd",
        "video",
        "tape",
        "sale",
        "dvds-rental"
    ],
    "wof:name":"Video Unlimited",
    "wof:placetype":"venue"
},
  "geometry": {"coordinates":[-121.806259,36.686249],"type":"Point"}
}