{
  "type": "Feature",
  "properties": {
    "iso:country":"US",
    "sg:address":"1875 Feather River Blvd",
    "sg:city":"Oroville",
    "sg:classifiers":[
        {
            "category":"Education",
            "subcategory":"Dance Studio",
            "type":"Public Place"
        }
    ],
    "sg:phone":"+1 530 533 1043",
    "sg:postcode":"95965",
    "sg:province":"CA",
    "sg:tags":[
        "instruction",
        "dancing"
    ],
    "wof:name":"Creative Arts Ctr",
    "wof:placetype":"venue"
},
  "geometry": {"coordinates":[-121.570597,39.50347],"type":"Point"}
}