{
  "type": "Feature",
  "properties": {
    "addr:full":"3368 Redwood St San Diego CA 92104",
    "addr:housenumber":"3368",
    "addr:postcode":"92104",
    "addr:street":"Redwood St",
    "iso:country":"US",
    "sg:address":"3368 Redwood St",
    "sg:city":"San Diego",
    "sg:classifiers":[
        {
            "category":"Banks & Credit Unions",
            "subcategory":"Financial Services",
            "type":"Services"
        }
    ],
    "sg:phone":"+1 619 283 0855",
    "sg:postcode":"92104",
    "sg:province":"CA",
    "sg:tags":[
        "trust",
        "management"
    ],
    "wof:name":"Chicoine Family Trust",
    "wof:placetype":"venue"
},
  "geometry": {"coordinates":[-117.1194,32.737498],"type":"Point"}
}