{
  "type": "Feature",
  "properties": {
    "iso:country":"US",
    "sg:address":"15820 S Western Avenue",
    "sg:city":"Gardena",
    "sg:classifiers":[
        {
            "category":"Travel",
            "subcategory":"Hotels & Motels",
            "type":"Entertainment"
        }
    ],
    "sg:phone":"+1 310 538 9999",
    "sg:postcode":"90247",
    "sg:province":"CA",
    "wof:name":"Moonlight Inn",
    "wof:placetype":"venue"
},
  "geometry": {"coordinates":[-118.309286,33.887077],"type":"Point"}
}