{
  "type": "Feature",
  "properties": {
    "iso:country":"US",
    "sg:address":"4168 W Avenue 42",
    "sg:city":"Los Angeles",
    "sg:classifiers":[
        {
            "category":"Education",
            "subcategory":"School",
            "type":"Public Place"
        }
    ],
    "sg:phone":"+1 323 255 0571",
    "sg:postcode":"90065",
    "sg:province":"CA",
    "sg:tags":[
        "high",
        "middle",
        "elementary"
    ],
    "sg:website":"www.lausd.k12.ca.us",
    "wof:name":"Delevan Drive Elementary School",
    "wof:placetype":"venue"
},
  "geometry": {"coordinates":[-118.227997,34.127602],"type":"Point"}
}