{
  "type": "Feature",
  "properties": {
    "iso:country":"US",
    "sg:address":"49430 Rd 426",
    "sg:city":"Oakhurst",
    "sg:classifiers":[
        {
            "category":"Professional",
            "subcategory":"Research",
            "type":"Services"
        }
    ],
    "sg:phone":"+1 559 642 4880",
    "sg:postcode":"93644",
    "sg:province":"CA",
    "sg:tags":[
        "environmental",
        "ecological"
    ],
    "wof:name":"Hartesveldt Ecological",
    "wof:placetype":"venue"
},
  "geometry": {"coordinates":[-119.646373,37.327149],"type":"Point"}
}