{
  "type": "Feature",
  "properties": {
    "iso:country":"US",
    "sg:address":"100 Redlands Mall",
    "sg:city":"Redlands",
    "sg:classifiers":[
        {
            "category":"Shopping",
            "subcategory":"Jewelry",
            "type":"Retail Goods"
        },
        {
            "category":"Manufacturing",
            "subcategory":"Jewelry",
            "type":"Manufacturing & Wholesale Goods"
        }
    ],
    "sg:phone":"+1 909 793 0181",
    "sg:postcode":"92373",
    "sg:province":"CA",
    "sg:tags":[
        "manufacturer",
        "designer",
        "jewelers-wholesale",
        "jeweler"
    ],
    "wof:name":"Sterling & Co",
    "wof:placetype":"venue"
},
  "geometry": {"coordinates":[-117.183582,34.057377],"type":"Point"}
}