{
  "type": "Feature",
  "properties": {
    "addr:full":"22635 Claude Cir Lake Forest CA 92630",
    "addr:housenumber":"22635",
    "addr:postcode":"92630",
    "addr:street":"Claude Cir",
    "iso:country":"US",
    "sg:address":"22635 Claude Cir",
    "sg:city":"Lake Forest",
    "sg:classifiers":[
        {
            "category":"Wholesale",
            "subcategory":"Hardware",
            "type":"Manufacturing & Wholesale Goods"
        }
    ],
    "sg:phone":"+1 949 588 9066",
    "sg:postcode":"92630",
    "sg:province":"CA",
    "sg:tags":[
        "equipment",
        "energy",
        "solar"
    ],
    "wof:name":"South Coast Solar",
    "wof:placetype":"venue"
},
  "geometry": {"coordinates":[-117.686155,33.634038],"type":"Point"}
}