{
  "type": "Feature",
  "properties": {
    "addr:full":"3010 W Orange Ave Ste 202 Anaheim CA 92804",
    "addr:housenumber":"3010",
    "addr:postcode":"92804",
    "addr:street":"W Orange Ave Ste 202",
    "iso:country":"US",
    "sg:address":"3010 W Orange Ave Ste 202",
    "sg:city":"Anaheim",
    "sg:classifiers":[
        {
            "category":"Health Services",
            "subcategory":"Doctor",
            "type":"Services"
        }
    ],
    "sg:phone":"+1 714 761 5833",
    "sg:postcode":"92804",
    "sg:province":"CA",
    "wof:name":"Garcia Luis MD",
    "wof:placetype":"venue"
},
  "geometry": {"coordinates":[-117.977997,33.816399],"type":"Point"}
}