{
  "type": "Feature",
  "properties": {
    "iso:country":"US",
    "sg:address":"818 S Rimpau Blvd",
    "sg:city":"Los Angeles",
    "sg:classifiers":[
        {
            "category":"Shopping",
            "subcategory":"Optician",
            "type":"Retail Goods"
        }
    ],
    "sg:phone":"+1 323 653 3222",
    "sg:postcode":"90005",
    "sg:province":"CA",
    "sg:tags":[
        "eyewear"
    ],
    "wof:name":"In Style Optical",
    "wof:placetype":"venue"
},
  "geometry": {"coordinates":[-118.33210200000001,34.054686],"type":"Point"}
}