{
  "type": "Feature",
  "properties": {
    "iso:country":"US",
    "sg:address":"27722 Vis del Lago",
    "sg:city":"Mission Viejo",
    "sg:classifiers":[
        {
            "category":"Real Estate",
            "subcategory":"Real Estate Agent",
            "type":"Services"
        }
    ],
    "sg:phone":"+1 949 859 0105",
    "sg:postcode":"92692",
    "sg:province":"CA",
    "wof:name":"Kamran",
    "wof:placetype":"venue"
},
  "geometry": {"coordinates":[-117.649227,33.634649],"type":"Point"}
}