{
  "type": "Feature",
  "properties": {
    "addr:full":"19360 Dairen St Rowland Heights CA 91748",
    "addr:housenumber":"19360",
    "addr:postcode":"91748",
    "addr:street":"Dairen St",
    "iso:country":"US",
    "sg:address":"19360 Dairen St",
    "sg:city":"Rowland Heights",
    "sg:classifiers":[
        {
            "category":"Wholesale",
            "subcategory":"Durable Goods & Equipment",
            "type":"Manufacturing & Wholesale Goods"
        }
    ],
    "sg:phone":"+1 626 964 7099",
    "sg:postcode":"91748",
    "sg:province":"CA",
    "sg:tags":[
        "repair"
    ],
    "wof:name":"Security Fire Protection",
    "wof:placetype":"venue"
},
  "geometry": {"coordinates":[-117.88079399999999,33.980058],"type":"Point"}
}