{
  "type": "Feature",
  "properties": {
    "addr:full":"2885 Wilson Cmn Fremont CA 94538",
    "addr:housenumber":"2885",
    "addr:postcode":"94538",
    "addr:street":"Wilson Cmn",
    "iso:country":"US",
    "sg:address":"2885 Wilson Cmn",
    "sg:city":"Fremont",
    "sg:classifiers":[
        {
            "category":"Professional",
            "subcategory":"Management & Consulting",
            "type":"Services"
        }
    ],
    "sg:phone":"+1 510 657 0140",
    "sg:postcode":"94538",
    "sg:province":"CA",
    "sg:tags":[
        "consultant"
    ],
    "wof:name":"Maurer Consulting",
    "wof:placetype":"venue"
},
  "geometry": {"coordinates":[-121.959582,37.540724],"type":"Point"}
}