{
  "type": "Feature",
  "properties": {
    "iso:country":"US",
    "sg:address":"12151 Paramount Blvd",
    "sg:city":"Downey",
    "sg:classifiers":[
        {
            "category":"Personal",
            "subcategory":"Day Spa",
            "type":"Services"
        }
    ],
    "sg:phone":"+1 562 869 3870",
    "sg:postcode":"90242",
    "sg:province":"CA",
    "sg:website":"www.kskincare.com",
    "wof:name":"K Skin Care",
    "wof:placetype":"venue"
},
  "geometry": {"coordinates":[-118.147179,33.930598],"type":"Point"}
}