{
  "type": "Feature",
  "properties": {
    "iso:country":"US",
    "sg:address":"333 Casa Grande Rd",
    "sg:city":"Petaluma",
    "sg:classifiers":[
        {
            "category":"Farming",
            "subcategory":"Aquatic Farm",
            "type":"Manufacturing & Wholesale Goods"
        }
    ],
    "sg:phone":"+1 707 773 4973",
    "sg:postcode":"94954",
    "sg:province":"CA",
    "sg:tags":[
        "fish"
    ],
    "wof:name":"United Anglers Of Casa Grande",
    "wof:placetype":"venue"
},
  "geometry": {"coordinates":[-122.597083,38.241934],"type":"Point"}
}