{
  "type": "Feature",
  "properties": {
    "addr:full":"3720 Trade Way Cameron Park CA 95682",
    "addr:housenumber":"3720",
    "addr:postcode":"95682",
    "addr:street":"Trade Way",
    "iso:country":"US",
    "sg:address":"3720 Trade Way",
    "sg:city":"Cameron Park",
    "sg:classifiers":[
        {
            "category":"Wholesale",
            "subcategory":"Toys & Hobbies",
            "type":"Manufacturing & Wholesale Goods"
        }
    ],
    "sg:phone":"+1 530 672 6162",
    "sg:postcode":"95682",
    "sg:province":"CA",
    "sg:tags":[
        "wholesaler"
    ],
    "wof:name":"Wholesale Art & Framing",
    "wof:placetype":"venue"
},
  "geometry": {"coordinates":[-120.9509,38.655098],"type":"Point"}
}