{
  "type": "Feature",
  "properties": {
    "iso:country":"US",
    "sg:address":"2801 W Ball Rd Ste 10",
    "sg:city":"Anaheim",
    "sg:classifiers":[
        {
            "category":"Health Services",
            "subcategory":"Dentist",
            "type":"Services"
        }
    ],
    "sg:phone":"+1 714 527 5656",
    "sg:postcode":"92804",
    "sg:province":"CA",
    "wof:name":"First Dental Care",
    "wof:placetype":"venue"
},
  "geometry": {"coordinates":[-117.984582,33.817647],"type":"Point"}
}