{
  "type": "Feature",
  "properties": {
    "addr:full":"3533 Jamison Way Castro Valley CA 94546",
    "addr:housenumber":"3533",
    "addr:postcode":"94546",
    "addr:street":"Jamison Way",
    "iso:country":"US",
    "sg:address":"3533 Jamison Way",
    "sg:city":"Castro Valley",
    "sg:classifiers":[
        {
            "category":"Banks & Credit Unions",
            "subcategory":"Bank",
            "type":"Services"
        }
    ],
    "sg:phone":"+1 510 888 5626",
    "sg:postcode":"94546",
    "sg:province":"CA",
    "wof:name":"Service First Bank",
    "wof:placetype":"venue"
},
  "geometry": {"coordinates":[-122.077348,37.698014],"type":"Point"}
}