{
  "type": "Feature",
  "properties": {
    "iso:country":"US",
    "sg:address":"2023 Chicago Ave",
    "sg:city":"Riverside",
    "sg:classifiers":[
        {
            "category":"Manufacturing",
            "subcategory":"Tools & Machinery",
            "type":"Manufacturing & Wholesale Goods"
        }
    ],
    "sg:phone":"+1 951 652 1505",
    "sg:postcode":"92507",
    "sg:province":"CA",
    "sg:tags":[
        "industrial",
        "mfg"
    ],
    "wof:name":"Swiss Micro Turn",
    "wof:placetype":"venue"
},
  "geometry": {"coordinates":[-117.348501,33.994713],"type":"Point"}
}