{
  "type": "Feature",
  "properties": {
    "addr:full":"15229 Chaparral Ln Apple Valley CA 92307",
    "addr:housenumber":"15229",
    "addr:postcode":"92307",
    "addr:street":"Chaparral Ln",
    "iso:country":"US",
    "sg:address":"15229 Chaparral Ln",
    "sg:city":"Apple Valley",
    "sg:classifiers":[
        {
            "category":"Building & Trades",
            "subcategory":"Construction",
            "type":"Services"
        }
    ],
    "sg:phone":"+1 760 946 0209",
    "sg:postcode":"92307",
    "sg:province":"CA",
    "sg:tags":[
        "residential"
    ],
    "wof:name":"Richmond Construction",
    "wof:placetype":"venue"
},
  "geometry": {"coordinates":[-117.273121,34.527854],"type":"Point"}
}