{
  "type": "Feature",
  "properties": {
    "iso:country":"US",
    "sg:address":"1129 Rosewood Ave",
    "sg:city":"Inglewood",
    "sg:classifiers":[
        {
            "category":"Professional",
            "type":"Services"
        }
    ],
    "sg:phone":"+1 310 383 1595",
    "sg:postcode":"90301",
    "sg:province":"CA",
    "sg:tags":[
        "caterer"
    ],
    "wof:name":"Roger's Catering Services",
    "wof:placetype":"venue"
},
  "geometry": {"coordinates":[-118.360201,33.94855],"type":"Point"}
}