{
  "type": "Feature",
  "properties": {
    "addr:full":"14560 San Pablo Ave San Pablo CA 94806",
    "addr:housenumber":"14560",
    "addr:postcode":"94806",
    "addr:street":"San Pablo Ave",
    "iso:country":"US",
    "sg:address":"14560 San Pablo Ave",
    "sg:city":"San Pablo",
    "sg:classifiers":[
        {
            "category":"Organizations",
            "subcategory":"Religious Organization",
            "type":"Services"
        }
    ],
    "sg:phone":"+1 510 234 8166",
    "sg:postcode":"94806",
    "sg:province":"CA",
    "sg:tags":[
        "church"
    ],
    "wof:name":"New Bethel Church Of God",
    "wof:placetype":"venue"
},
  "geometry": {"coordinates":[-122.343836,37.968246],"type":"Point"}
}