{
  "type": "Feature",
  "properties": {
    "addr:full":"2728 Yosemite Ave Manteca CA 95337",
    "addr:housenumber":"2728",
    "addr:postcode":"95337",
    "addr:street":"Yosemite Ave",
    "iso:country":"US",
    "sg:address":"2728 Yosemite Ave",
    "sg:city":"Manteca",
    "sg:classifiers":[
        {
            "category":"Freight",
            "type":"Transportation"
        }
    ],
    "sg:phone":"+1 209 835 5129",
    "sg:postcode":"95337",
    "sg:province":"CA",
    "sg:tags":[
        "water"
    ],
    "wof:name":"Glenns Water Truck Service",
    "wof:placetype":"venue"
},
  "geometry": {"coordinates":[-121.265092,37.797229],"type":"Point"}
}