{
  "type": "Feature",
  "properties": {
    "iso:country":"US",
    "sg:address":"16780 Round Valley Cir",
    "sg:city":"Grass Valley",
    "sg:classifiers":[
        {
            "category":"Professional",
            "type":"Services"
        }
    ],
    "sg:phone":"+1 530 271 0897",
    "sg:postcode":"95949",
    "sg:province":"CA",
    "sg:tags":[
        "writer"
    ],
    "wof:name":"Pollywog Productions",
    "wof:placetype":"venue"
},
  "geometry": {"coordinates":[-121.070333,39.124362],"type":"Point"}
}