{
  "type": "Feature",
  "properties": {
    "addr:full":"2011 Chico Ave South El Monte CA 91733",
    "addr:housenumber":"2011",
    "addr:postcode":"91733",
    "addr:street":"Chico Ave",
    "iso:country":"US",
    "sg:address":"2011 Chico Ave",
    "sg:city":"South El Monte",
    "sg:classifiers":[
        {
            "category":"Retail",
            "subcategory":"Auto Repair",
            "type":"Services"
        }
    ],
    "sg:phone":"+1 626 279 9567",
    "sg:postcode":"91733",
    "sg:province":"CA",
    "sg:tags":[
        "body",
        "automobile",
        "painting"
    ],
    "wof:name":"C P Auto Body",
    "wof:placetype":"venue"
},
  "geometry": {"coordinates":[-118.060063,34.054901],"type":"Point"}
}