{
  "type": "Feature",
  "properties": {
    "addr:full":"6769 8th St Buena Park CA 90620",
    "addr:housenumber":"6769",
    "addr:postcode":"90620",
    "addr:street":"8Th St",
    "iso:country":"US",
    "sg:address":"6769 8th St",
    "sg:city":"Buena Park",
    "sg:classifiers":[
        {
            "category":"Personal",
            "subcategory":"Shoe Repair & Shine",
            "type":"Services"
        }
    ],
    "sg:phone":"+1 714 522 5556",
    "sg:postcode":"90620",
    "sg:province":"CA",
    "sg:website":"yosemitebum.com",
    "wof:name":"Yosemite Bum",
    "wof:placetype":"venue"
},
  "geometry": {"coordinates":[-118.014915,33.867217],"type":"Point"}
}