{
  "type": "Feature",
  "properties": {
    "addr:full":"575 Manzanita Ave Chico CA 95926",
    "addr:housenumber":"575",
    "addr:postcode":"95926",
    "addr:street":"Manzanita Ave",
    "iso:country":"US",
    "sg:address":"575 Manzanita Ave",
    "sg:city":"Chico",
    "sg:classifiers":[
        {
            "category":"Autos & Motor Vehicles",
            "subcategory":"Automobile Sales",
            "type":"Retail Goods"
        },
        {
            "category":"Retail",
            "subcategory":"Auto Repair",
            "type":"Services"
        }
    ],
    "sg:phone":"+1 530 891 1777",
    "sg:postcode":"95926",
    "sg:province":"CA",
    "sg:tags":[
        "truck",
        "used",
        "leasing",
        "car",
        "new"
    ],
    "sg:website":"http://www.chiconissan.com/",
    "wof:name":"Chico Nissan",
    "wof:placetype":"venue"
},
  "geometry": {"coordinates":[-121.843345,39.754989],"type":"Point"}
}