{
  "type": "Feature",
  "properties": {
    "addr:full":"4700 Old Ironsides Drive Santa Clara CA 95054",
    "addr:housenumber":"4700",
    "addr:postcode":"95054",
    "addr:street":"Old Ironsides Drive",
    "iso:country":"US",
    "sg:address":"4700 Old Ironsides Drive",
    "sg:city":"Santa Clara",
    "sg:classifiers":[
        {
            "category":"Utilities",
            "type":"Services"
        }
    ],
    "sg:phone":"+1 408 496 0617",
    "sg:postcode":"95054",
    "sg:province":"CA",
    "sg:tags":[
        "provider",
        "internet"
    ],
    "wof:name":"Internet Names World Wide",
    "wof:placetype":"venue"
},
  "geometry": {"coordinates":[-121.979551,37.397582],"type":"Point"}
}