{
  "type": "Feature",
  "properties": {
    "addr:full":"730 N Catalina Ave Redondo Beach CA 90277",
    "addr:housenumber":"730",
    "addr:postcode":"90277",
    "addr:street":"N Catalina Ave",
    "iso:country":"US",
    "sg:address":"730 N Catalina Ave",
    "sg:city":"Redondo Beach",
    "sg:classifiers":[
        {
            "category":"Retail",
            "subcategory":"Auto Repair",
            "type":"Services"
        }
    ],
    "sg:phone":"+1 310 318 1212",
    "sg:postcode":"90277",
    "sg:province":"CA",
    "sg:tags":[
        "repairing",
        "automobile"
    ],
    "wof:name":"Beach Cities Car Doctors",
    "wof:placetype":"venue"
},
  "geometry": {"coordinates":[-118.391852,33.848613],"type":"Point"}
}