{
  "type": "Feature",
  "properties": {
    "iso:country":"US",
    "sg:address":"8267 E Santa Ana Canyon Rd",
    "sg:city":"Anaheim",
    "sg:classifiers":[
        {
            "category":"Restaurant",
            "type":"Food & Drink"
        }
    ],
    "sg:menulink":"http://www.allmenus.com/ca/anaheim-santa-ana-garden-grove/123909-quiznos-sub/menu/",
    "sg:phone":"+1 714 921 8001",
    "sg:postcode":"92808",
    "sg:province":"CA",
    "sg:tags":[
        "wrap",
        "american",
        "sandwich"
    ],
    "wof:name":"Quiznos Sub",
    "wof:placetype":"venue"
},
  "geometry": {"coordinates":[-117.744502,33.867312],"type":"Point"}
}