{
  "type": "Feature",
  "properties": {
    "addr:full":"1560 Custer Ave San Francisco CA 94124",
    "addr:housenumber":"1560",
    "addr:postcode":"94124",
    "addr:street":"Custer Ave",
    "iso:country":"US",
    "sg:address":"1560 Custer Ave",
    "sg:city":"San Francisco",
    "sg:classifiers":[
        {
            "category":"Wholesale",
            "subcategory":"Apparel",
            "type":"Manufacturing & Wholesale Goods"
        }
    ],
    "sg:phone":"+1 415 643 6608",
    "sg:postcode":"94124",
    "sg:province":"CA",
    "wof:name":"Cheneral Inc",
    "wof:placetype":"venue"
},
  "geometry": {"coordinates":[-122.390111,37.745771],"type":"Point"}
}