{
  "type": "Feature",
  "properties": {
    "addr:full":"701 Santa Cruz Ave Menlo Park CA 94025",
    "addr:housenumber":"701",
    "addr:postcode":"94025",
    "addr:street":"Santa Cruz Ave",
    "iso:country":"US",
    "sg:address":"701 Santa Cruz Ave",
    "sg:city":"Menlo Park",
    "sg:classifiers":[
        {
            "category":"Banks & Credit Unions",
            "subcategory":"Bank",
            "type":"Services"
        }
    ],
    "sg:phone":"+1 650 322 8494",
    "sg:postcode":"94025",
    "sg:province":"CA",
    "wof:name":"California Savings Bank",
    "wof:placetype":"venue"
},
  "geometry": {"coordinates":[-122.18447399999999,37.451679],"type":"Point"}
}