{
  "type": "Feature",
  "properties": {
    "addr:full":"8236 Firestone Blvd Downey CA 90241",
    "addr:housenumber":"8236",
    "addr:postcode":"90241",
    "addr:street":"Firestone Blvd",
    "iso:country":"US",
    "sg:address":"8236 Firestone Blvd",
    "sg:city":"Downey",
    "sg:classifiers":[
        {
            "category":"Wholesale",
            "subcategory":"Auto Parts",
            "type":"Manufacturing & Wholesale Goods"
        }
    ],
    "sg:phone":"+1 562 863 7550",
    "sg:postcode":"90241",
    "sg:province":"CA",
    "sg:tags":[
        "equipment",
        "truck"
    ],
    "sg:website":"www.speedespeedometer.com",
    "wof:name":"Speede Speedometer Svc",
    "wof:placetype":"venue"
},
  "geometry": {"coordinates":[-118.133199,33.940137],"type":"Point"}
}