{
  "type": "Feature",
  "properties": {
    "iso:country":"US",
    "sg:address":"2371 Helen Rd",
    "sg:city":"Fallbrook",
    "sg:classifiers":[
        {
            "category":"Professional",
            "type":"Services"
        }
    ],
    "sg:phone":"+1 760 451 0357",
    "sg:postcode":"92028",
    "sg:province":"CA",
    "wof:name":"Jerry & INA Breitfelder",
    "wof:placetype":"venue"
},
  "geometry": {"coordinates":[-117.300234,33.439424],"type":"Point"}
}