{
  "type": "Feature",
  "properties": {
    "addr:full":"308 Encinal St Santa Cruz CA 95060",
    "addr:housenumber":"308",
    "addr:postcode":"95060",
    "addr:street":"Encinal St",
    "iso:country":"US",
    "sg:address":"308 Encinal St",
    "sg:city":"Santa Cruz",
    "sg:classifiers":[
        {
            "category":"Manufacturing",
            "subcategory":"Tools & Machinery",
            "type":"Manufacturing & Wholesale Goods"
        }
    ],
    "sg:phone":"+1 831 429 8175",
    "sg:postcode":"95060",
    "sg:province":"CA",
    "sg:tags":[
        "machine",
        "shop"
    ],
    "sg:website":"www.jacoworks.com",
    "wof:name":"Ja-Co Machine Works",
    "wof:placetype":"venue"
},
  "geometry": {"coordinates":[-122.034384,36.986899],"type":"Point"}
}