{
  "type": "Feature",
  "properties": {
    "iso:country":"US",
    "sg:address":"8149 S Gate Ave",
    "sg:city":"South Gate",
    "sg:classifiers":[
        {
            "category":"Professional",
            "type":"Services"
        }
    ],
    "sg:phone":"+1 323 569 1226",
    "sg:postcode":"90280",
    "sg:province":"CA",
    "wof:name":"Romero Graciela",
    "wof:placetype":"venue"
},
  "geometry": {"coordinates":[-118.213613,33.961414],"type":"Point"}
}