{
  "type": "Feature",
  "properties": {
    "addr:full":"3077 Fite Cir Sacramento CA 95827",
    "addr:housenumber":"3077",
    "addr:postcode":"95827",
    "addr:street":"Fite Cir",
    "iso:country":"US",
    "sg:address":"3077 Fite Cir",
    "sg:city":"Sacramento",
    "sg:classifiers":[
        {
            "category":"Professional",
            "subcategory":"Research",
            "type":"Services"
        }
    ],
    "sg:phone":"+1 916 366 1701",
    "sg:postcode":"95827",
    "sg:province":"CA",
    "sg:tags":[
        "environmental",
        "ecological"
    ],
    "sg:website":"www.kleinfelder.com",
    "wof:name":"Kleinfelder",
    "wof:placetype":"venue"
},
  "geometry": {"coordinates":[-121.324625,38.573459],"type":"Point"}
}