{
  "type": "Feature",
  "properties": {
    "iso:country":"US",
    "sg:address":"3709 Meade Ct",
    "sg:city":"Bakersfield",
    "sg:phone":"+1 661 835 1765",
    "sg:postcode":"93309",
    "sg:province":"CA",
    "sg:tags":[
        "farm",
        "cotton"
    ],
    "wof:name":"Alan Weidenbach",
    "wof:placetype":"venue"
},
  "geometry": {"coordinates":[-119.081942,35.320865],"type":"Point"}
}