{
  "type": "Feature",
  "properties": {
    "iso:country":"US",
    "sg:address":"10246 Topanga Canyon Blvd",
    "sg:city":"Chatsworth",
    "sg:classifiers":[
        {
            "category":"Retail",
            "subcategory":"Repair Shop",
            "type":"Services"
        }
    ],
    "sg:phone":"+1 818 886 5272",
    "sg:postcode":"91311",
    "sg:province":"CA",
    "sg:tags":[
        "vehicle"
    ],
    "wof:name":"Iron Sledz Custom Cycles",
    "wof:placetype":"venue"
},
  "geometry": {"coordinates":[-118.605896,34.256386],"type":"Point"}
}