{
  "type": "Feature",
  "properties": {
    "addr:full":"5326 Roxanne Dr San Jose CA 95124",
    "addr:housenumber":"5326",
    "addr:postcode":"95124",
    "addr:street":"Roxanne Dr",
    "iso:country":"US",
    "sg:address":"5326 Roxanne Dr",
    "sg:city":"San Jose",
    "sg:classifiers":[
        {
            "category":"Wholesale",
            "subcategory":"Computers",
            "type":"Manufacturing & Wholesale Goods"
        }
    ],
    "sg:phone":"+1 408 723 0352",
    "sg:postcode":"95124",
    "sg:province":"CA",
    "wof:name":"PS Systems",
    "wof:placetype":"venue"
},
  "geometry": {"coordinates":[-121.914838,37.24183],"type":"Point"}
}