{
  "type": "Feature",
  "properties": {
    "iso:country":"US",
    "sg:address":"46474 Longview Ln W",
    "sg:city":"Coarsegold",
    "sg:classifiers":[
        {
            "category":"Manufacturing",
            "subcategory":"Chemicals & Compounds",
            "type":"Manufacturing & Wholesale Goods"
        },
        {
            "category":"Utilities",
            "subcategory":"Water",
            "type":"Services"
        },
        {
            "category":"Building & Trades",
            "subcategory":"Construction",
            "type":"Services"
        },
        {
            "category":"Arts & Performance",
            "subcategory":"Arts Center",
            "type":"Entertainment"
        }
    ],
    "sg:phone":"+1 209 235 2569",
    "sg:postcode":"93614",
    "sg:province":"CA",
    "sg:tags":[
        "paint",
        "removing",
        "wallpaper",
        "specialty",
        "contractor",
        "equipment",
        "decorating",
        "hand",
        "painting"
    ],
    "wof:name":"A Great TIme to Paint",
    "wof:placetype":"venue"
},
  "geometry": {"coordinates":[-119.700373,37.199144],"type":"Point"}
}