{
  "type": "Feature",
  "properties": {
    "iso:country":"US",
    "sg:address":"27772 Biscayne Ave",
    "sg:city":"Hayward",
    "sg:classifiers":[
        {
            "category":"Freight",
            "type":"Transportation"
        }
    ],
    "sg:phone":"+1 510 732 6329",
    "sg:postcode":"94544",
    "sg:province":"CA",
    "sg:tags":[
        "operator",
        "local",
        "trucking"
    ],
    "wof:name":"Montes Trucking",
    "wof:placetype":"venue"
},
  "geometry": {"coordinates":[-122.074634,37.628848],"type":"Point"}
}