{
  "type": "Feature",
  "properties": {
    "addr:full":"4460 Pacific Blvd Vernon CA 90058",
    "addr:housenumber":"4460",
    "addr:postcode":"90058",
    "addr:street":"Pacific Blvd",
    "iso:country":"US",
    "sg:address":"4460 Pacific Blvd",
    "sg:city":"Vernon",
    "sg:classifiers":[
        {
            "category":"Manufacturing",
            "subcategory":"Chemicals & Compounds",
            "type":"Manufacturing & Wholesale Goods"
        }
    ],
    "sg:phone":"+1 800 776 3697",
    "sg:postcode":"90058",
    "sg:province":"CA",
    "sg:tags":[
        "product",
        "gypsum"
    ],
    "wof:name":"Pabco Paper Products",
    "wof:placetype":"venue"
},
  "geometry": {"coordinates":[-118.227898,34.00396],"type":"Point"}
}