{
  "type": "Feature",
  "properties": {
    "iso:country":"US",
    "sg:address":"40 Parkside Ln",
    "sg:city":"Pittsburg",
    "sg:classifiers":[
        {
            "category":"Retail",
            "subcategory":"Auto Repair",
            "type":"Services"
        }
    ],
    "sg:phone":"+1 925 458 9441",
    "sg:postcode":"94565",
    "sg:province":"CA",
    "sg:tags":[
        "repairing",
        "automobile"
    ],
    "wof:name":"Rivera Auto Repair & Smog Sta",
    "wof:placetype":"venue"
},
  "geometry": {"coordinates":[-121.887782,38.02495],"type":"Point"}
}