{
  "type": "Feature",
  "properties": {
    "addr:full":"9835 E Ave Hesperia CA 92345",
    "addr:housenumber":"9835",
    "addr:postcode":"92345",
    "addr:street":"E Ave",
    "iso:country":"US",
    "sg:address":"9835 E Ave",
    "sg:city":"Hesperia",
    "sg:classifiers":[
        {
            "category":"Building & Trades",
            "subcategory":"Construction",
            "type":"Services"
        }
    ],
    "sg:phone":"+1 760 947 5575",
    "sg:postcode":"92345",
    "sg:province":"CA",
    "sg:tags":[
        "sandblasting"
    ],
    "wof:name":"Elder Industries Inc",
    "wof:placetype":"venue"
},
  "geometry": {"coordinates":[-117.29013999999999,34.430873],"type":"Point"}
}