{
  "type": "Feature",
  "properties": {
    "addr:full":"7945 Flight Pl Los Angeles CA 90045",
    "addr:housenumber":"7945",
    "addr:postcode":"90045",
    "addr:street":"Flight Pl",
    "iso:country":"US",
    "sg:address":"7945 Flight Pl",
    "sg:city":"Los Angeles",
    "sg:classifiers":[
        {
            "category":"Manufacturing",
            "subcategory":"Paper Products",
            "type":"Manufacturing & Wholesale Goods"
        }
    ],
    "sg:phone":"+1 310 568 1136",
    "sg:postcode":"90045",
    "sg:province":"CA",
    "sg:tags":[
        "handmade",
        "mfg"
    ],
    "wof:name":"Mannaz Unlimited Inc",
    "wof:placetype":"venue"
},
  "geometry": {"coordinates":[-118.387659,33.964975],"type":"Point"}
}