{
  "type": "Feature",
  "properties": {
    "iso:country":"US",
    "sg:address":"5100 N 6th St",
    "sg:city":"Fresno",
    "sg:classifiers":[
        {
            "category":"Banks & Credit Unions",
            "subcategory":"Investment Brokerage",
            "type":"Services"
        }
    ],
    "sg:phone":"+1 559 650 0550",
    "sg:postcode":"93710",
    "sg:province":"CA",
    "sg:tags":[
        "management"
    ],
    "wof:name":"Raymond James Financial Svc",
    "wof:placetype":"venue"
},
  "geometry": {"coordinates":[-119.763159,36.810405],"type":"Point"}
}