{
  "type": "Feature",
  "properties": {
    "addr:full":"3407 Hiatt Dr Redding CA 96003",
    "addr:housenumber":"3407",
    "addr:postcode":"96003",
    "addr:street":"Hiatt Dr",
    "iso:country":"US",
    "sg:address":"3407 Hiatt Dr",
    "sg:city":"Redding",
    "sg:classifiers":[
        {
            "category":"Education",
            "subcategory":"School",
            "type":"Public Place"
        }
    ],
    "sg:phone":"+1 530 225 0420",
    "sg:postcode":"96003",
    "sg:province":"CA",
    "sg:tags":[
        "elementary"
    ],
    "sg:website":"http://www.gsd.k12.ca.us",
    "wof:name":"Buckeye Elementary School",
    "wof:placetype":"venue"
},
  "geometry": {"coordinates":[-122.403403,40.631035],"type":"Point"}
}