{
  "type": "Feature",
  "properties": {
    "iso:country":"US",
    "sg:address":"3658 Mt Diablo Blvd",
    "sg:city":"Lafayette",
    "sg:classifiers":[
        {
            "category":"Wholesale",
            "subcategory":"Drugs",
            "type":"Manufacturing & Wholesale Goods"
        }
    ],
    "sg:phone":"+1 925 299 9642",
    "sg:postcode":"94549",
    "sg:province":"CA",
    "sg:tags":[
        "decal"
    ],
    "wof:name":"Ace Screen Print Co",
    "wof:placetype":"venue"
},
  "geometry": {"coordinates":[-122.12743399999999,37.890869],"type":"Point"}
}