{
  "type": "Feature",
  "properties": {
    "addr:full":"2690 Country Club Dr Cameron Park CA 95682",
    "addr:housenumber":"2690",
    "addr:postcode":"95682",
    "addr:street":"Country Club Dr",
    "iso:country":"US",
    "sg:address":"2690 Country Club Dr",
    "sg:city":"Cameron Park",
    "sg:classifiers":[
        {
            "category":"Real Estate",
            "subcategory":"Real Estate Operator",
            "type":"Services"
        }
    ],
    "sg:phone":"+1 530 677 6210",
    "sg:postcode":"95682",
    "sg:province":"CA",
    "sg:tags":[
        "apartment"
    ],
    "wof:name":"Cambridge Garden Apartments",
    "wof:placetype":"venue"
},
  "geometry": {"coordinates":[-120.996437,38.660661],"type":"Point"}
}