{
  "type": "Feature",
  "properties": {
    "iso:country":"US",
    "sg:address":"9960 Glenoaks Blvd",
    "sg:city":"Sun Valley",
    "sg:classifiers":[
        {
            "category":"Wholesale",
            "subcategory":"Office Equipment",
            "type":"Manufacturing & Wholesale Goods"
        }
    ],
    "sg:phone":"+1 818 771 9066",
    "sg:postcode":"91352",
    "sg:province":"CA",
    "sg:tags":[
        "blueprinting",
        "supply"
    ],
    "sg:website":"www.reprographicsupply.com",
    "wof:name":"Repro-Graphic Supply",
    "wof:placetype":"venue"
},
  "geometry": {"coordinates":[-118.38828,34.250295],"type":"Point"}
}