{
  "type": "Feature",
  "properties": {
    "iso:country":"US",
    "sg:address":"16804 Lakewood Blvd",
    "sg:city":"Bellflower",
    "sg:classifiers":[
        {
            "category":"Shopping",
            "subcategory":"Discount & Variety Stores",
            "type":"Retail Goods"
        }
    ],
    "sg:phone":"+1 562 867 6265",
    "sg:postcode":"90706",
    "sg:province":"CA",
    "wof:name":"Lakewood 99 Cents & Up Store",
    "wof:placetype":"venue"
},
  "geometry": {"coordinates":[-118.142534,33.881142],"type":"Point"}
}