{
  "type": "Feature",
  "properties": {
    "iso:country":"US",
    "sg:address":"2092 Newbury Rd",
    "sg:city":"Newbury Park",
    "sg:classifiers":[
        {
            "category":"Personal",
            "subcategory":"Beauty Salon",
            "type":"Services"
        }
    ],
    "sg:phone":"+1 805 494 1771",
    "sg:postcode":"91320",
    "sg:province":"CA",
    "wof:name":"Laperia's Hair & Nails",
    "wof:placetype":"venue"
},
  "geometry": {"coordinates":[-118.923236,34.183827],"type":"Point"}
}