{
  "type": "Feature",
  "properties": {
    "addr:full":"2615 Ashby Ave Berkeley CA 94705",
    "addr:housenumber":"2615",
    "addr:postcode":"94705",
    "addr:street":"Ashby Ave",
    "iso:country":"US",
    "sg:address":"2615 Ashby Ave",
    "sg:city":"Berkeley",
    "sg:classifiers":[
        {
            "category":"Health Services",
            "subcategory":"Clinic",
            "type":"Services"
        },
        {
            "category":"Health Services",
            "subcategory":"Health Practitioner",
            "type":"Services"
        }
    ],
    "sg:phone":"+1 503 936 0908",
    "sg:postcode":"94705",
    "sg:province":"CA",
    "sg:tags":[
        "naturopathic/holistic",
        "welfare"
    ],
    "wof:name":"Luck Dragon Medicine",
    "wof:placetype":"venue"
},
  "geometry": {"coordinates":[-122.25484299999999,37.857086],"type":"Point"}
}