{
  "type": "Feature",
  "properties": {
    "iso:country":"US",
    "sg:address":"35 Del AMO Fashion Sq",
    "sg:city":"Torrance",
    "sg:classifiers":[
        {
            "category":"Shopping",
            "subcategory":"Clothing, Apparel, & Fashions",
            "type":"Retail Goods"
        },
        {
            "category":"Shopping Center",
            "type":"Public Place"
        }
    ],
    "sg:phone":"+1 310 371 3643",
    "sg:postcode":"90503",
    "sg:province":"CA",
    "sg:tags":[
        "lingerie",
        "clothing",
        "accessory",
        "women's"
    ],
    "wof:name":"Frederick's of Hollywood",
    "wof:placetype":"venue"
},
  "geometry": {"coordinates":[-118.350998,33.828602],"type":"Point"}
}