{
  "type": "Feature",
  "properties": {
    "addr:full":"10955 Ventura Blvd Studio City CA 91614",
    "addr:housenumber":"10955",
    "addr:postcode":"91614",
    "addr:street":"Ventura Blvd",
    "iso:country":"US",
    "sg:address":"10955 Ventura Blvd",
    "sg:city":"Studio City",
    "sg:classifiers":[
        {
            "category":"Juice Bar",
            "subcategory":"None",
            "type":"Food & Drink"
        }
    ],
    "sg:phone":"+1 818 769 6705",
    "sg:postcode":"91614",
    "sg:province":"CA",
    "sg:tags":[
        "smoothy"
    ],
    "sg:website":"www.jambajuice.com",
    "wof:name":"Jamba Juice",
    "wof:placetype":"venue"
},
  "geometry": {"coordinates":[-118.369472,34.14022],"type":"Point"}
}