{
  "type": "Feature",
  "properties": {
    "iso:country":"US",
    "sg:address":"14417 S Vermont Ave Apt 42",
    "sg:city":"Gardena",
    "sg:classifiers":[
        {
            "category":"Real Estate",
            "subcategory":"Real Estate Operator",
            "type":"Services"
        }
    ],
    "sg:phone":"+1 310 532 5375",
    "sg:postcode":"90247",
    "sg:province":"CA",
    "sg:tags":[
        "apartment"
    ],
    "wof:name":"Corsican Apartments The",
    "wof:placetype":"venue"
},
  "geometry": {"coordinates":[-118.291994,33.900701],"type":"Point"}
}