{
  "type": "Feature",
  "properties": {
    "addr:full":"150 Kern St Salinas CA 93905",
    "addr:housenumber":"150",
    "addr:postcode":"93905",
    "addr:street":"Kern St",
    "iso:country":"US",
    "sg:address":"150 Kern St",
    "sg:city":"Salinas",
    "sg:classifiers":[
        {
            "category":"Real Estate",
            "subcategory":"Real Estate Operator",
            "type":"Services"
        }
    ],
    "sg:phone":"+1 831 758 1500",
    "sg:postcode":"93905",
    "sg:province":"CA",
    "sg:tags":[
        "mobile",
        "home",
        "community"
    ],
    "wof:name":"Sherwood Lake Mobile Home Park",
    "wof:placetype":"venue"
},
  "geometry": {"coordinates":[-121.64080199999999,36.681239],"type":"Point"}
}