{
  "type": "Feature",
  "properties": {
    "iso:country":"US",
    "sg:address":"1315 Santa Luisa Dr",
    "sg:city":"Solana Beach",
    "sg:classifiers":[
        {
            "category":"Shopping",
            "subcategory":"Gifts & Souvenirs",
            "type":"Retail Goods"
        }
    ],
    "sg:phone":"+1 858 794 0949",
    "sg:postcode":"92075",
    "sg:province":"CA",
    "sg:tags":[
        "shop"
    ],
    "wof:name":"Hopie Co",
    "wof:placetype":"venue"
},
  "geometry": {"coordinates":[-117.244494,33.004109],"type":"Point"}
}