{
  "type": "Feature",
  "properties": {
    "addr:full":"1120 W Oak St Lodi CA 95240",
    "addr:housenumber":"1120",
    "addr:postcode":"95240",
    "addr:street":"W Oak St",
    "iso:country":"US",
    "sg:address":"1120 W Oak St",
    "sg:city":"Lodi",
    "sg:classifiers":[
        {
            "category":"Retail",
            "subcategory":"Animal Services",
            "type":"Services"
        }
    ],
    "sg:phone":"+1 209 368 1134",
    "sg:postcode":"95240",
    "sg:province":"CA",
    "sg:tags":[
        "pet",
        "boarding",
        "sitting"
    ],
    "wof:name":"Pet Watchers",
    "wof:placetype":"venue"
},
  "geometry": {"coordinates":[-121.287173,38.133163],"type":"Point"}
}