{
  "type": "Feature",
  "properties": {
    "iso:country":"US",
    "sg:address":"9400 Jersey Ave",
    "sg:city":"Santa Fe Springs",
    "sg:classifiers":[
        {
            "category":"Education",
            "subcategory":"Preschool",
            "type":"Public Place"
        },
        {
            "category":"Education",
            "subcategory":"School",
            "type":"Public Place"
        }
    ],
    "sg:phone":"+1 562 949 1115",
    "sg:postcode":"90670",
    "sg:province":"CA",
    "sg:tags":[
        "elementary"
    ],
    "wof:name":"Plaza De La Raza Headstart",
    "wof:placetype":"venue"
},
  "geometry": {"coordinates":[-118.082001,33.9543],"type":"Point"}
}