{
  "type": "Feature",
  "properties": {
    "iso:country":"US",
    "sg:address":"12651 Singing Wood Dr",
    "sg:city":"Santa Ana",
    "sg:classifiers":[
        {
            "category":"Real Estate",
            "subcategory":"Real Estate Services",
            "type":"Services"
        }
    ],
    "sg:phone":"+1 714 832 2900",
    "sg:postcode":"92705",
    "sg:province":"CA",
    "sg:tags":[
        "home",
        "inspector"
    ],
    "wof:name":"Mold Detection Services",
    "wof:placetype":"venue"
},
  "geometry": {"coordinates":[-117.79499800000001,33.7439],"type":"Point"}
}