{
  "type": "Feature",
  "properties": {
    "addr:full":"3855 Alamo St Simi Valley CA 93063",
    "addr:housenumber":"3855",
    "addr:postcode":"93063",
    "addr:street":"Alamo St",
    "iso:country":"US",
    "sg:address":"3855 Alamo St",
    "sg:city":"Simi Valley",
    "sg:classifiers":[
        {
            "category":"Government",
            "subcategory":"Office",
            "type":"Public Place"
        }
    ],
    "sg:phone":"+1 805 582 8062",
    "sg:postcode":"93063",
    "sg:province":"CA",
    "sg:tags":[
        "county",
        "resource"
    ],
    "wof:name":"Ventura County Human Svc Agcy",
    "wof:placetype":"venue"
},
  "geometry": {"coordinates":[-118.72335,34.286386],"type":"Point"}
}