{
  "type": "Feature",
  "properties": {
    "iso:country":"US",
    "sg:address":"1911 Commercenter Ct",
    "sg:city":"San Bernardino",
    "sg:classifiers":[
        {
            "category":"Travel",
            "subcategory":"Travel Agent",
            "type":"Entertainment"
        }
    ],
    "sg:phone":"+1 909 890 3735",
    "sg:postcode":"92408",
    "sg:province":"CA",
    "sg:tags":[
        "agency"
    ],
    "wof:name":"Sport Fishing",
    "wof:placetype":"venue"
},
  "geometry": {"coordinates":[-117.28222599999999,34.066179],"type":"Point"}
}