{
  "type": "Feature",
  "properties": {
    "addr:full":"260 N El Camino Real Encinitas CA 92024",
    "addr:housenumber":"260",
    "addr:postcode":"92024",
    "addr:street":"N El Camino Real",
    "iso:country":"US",
    "sg:address":"260 N El Camino Real",
    "sg:city":"Encinitas",
    "sg:classifiers":[
        {
            "category":"Restaurant",
            "type":"Food & Drink"
        }
    ],
    "sg:phone":"+1 760 634 3010",
    "sg:postcode":"92024",
    "sg:province":"CA",
    "sg:tags":[
        "new",
        "american",
        "asian",
        "fusion",
        "italian"
    ],
    "sg:website":"www.noodles.com",
    "wof:name":"Noodles & Company",
    "wof:placetype":"venue"
},
  "geometry": {"coordinates":[-117.26114699999999,33.052386],"type":"Point"}
}