{
  "type": "Feature",
  "properties": {
    "addr:full":"760 Market Street Suite 852 San Francisco CA 94102",
    "addr:housenumber":"760",
    "addr:postcode":"94102",
    "addr:street":"Market Street Suite 852",
    "iso:country":"US",
    "sg:address":"760 Market Street Suite 852",
    "sg:city":"San Francisco",
    "sg:classifiers":[
        {
            "category":"Professional",
            "subcategory":"Lawyer & Legal Services",
            "type":"Services"
        }
    ],
    "sg:phone":"+1 415 285 1881",
    "sg:postcode":"94102",
    "sg:province":"CA",
    "sg:tags":[
        "personal",
        "injury"
    ],
    "wof:name":"Law Office of Antonio Ramirez",
    "wof:placetype":"venue"
},
  "geometry": {"coordinates":[-122.417,37.780998],"type":"Point"}
}