{
  "type": "Feature",
  "properties": {
    "addr:full":"7035 N Figueroa St Los Angeles CA 90042",
    "addr:housenumber":"7035",
    "addr:postcode":"90042",
    "addr:street":"N Figueroa St",
    "iso:country":"US",
    "sg:address":"7035 N Figueroa St",
    "sg:city":"Los Angeles",
    "sg:classifiers":[
        {
            "category":"Home & Garden",
            "subcategory":"Building Materials",
            "type":"Retail Goods"
        }
    ],
    "sg:phone":"+1 323 258 8084",
    "sg:postcode":"90042",
    "sg:province":"CA",
    "sg:tags":[
        "glass",
        "window",
        "plate"
    ],
    "wof:name":"Tom's Glass & Mirror Co",
    "wof:placetype":"venue"
},
  "geometry": {"coordinates":[-118.18867899999999,34.130688],"type":"Point"}
}