{
  "type": "Feature",
  "properties": {
    "addr:full":"1100 Tyler Ave Greenfield CA 93927",
    "addr:housenumber":"1100",
    "addr:postcode":"93927",
    "addr:street":"Tyler Ave",
    "iso:country":"US",
    "sg:address":"1100 Tyler Ave",
    "sg:city":"Greenfield",
    "sg:classifiers":[
        {
            "category":"Freight",
            "type":"Transportation"
        }
    ],
    "sg:phone":"+1 831 674 0875",
    "sg:postcode":"93927",
    "sg:province":"CA",
    "sg:tags":[
        "operator",
        "local",
        "trucking"
    ],
    "wof:name":"M & H Trucking",
    "wof:placetype":"venue"
},
  "geometry": {"coordinates":[-121.244781,36.31242],"type":"Point"}
}