{
  "type": "Feature",
  "properties": {
    "addr:full":"27205 Waterford Dr Valencia CA 91354",
    "addr:housenumber":"27205",
    "addr:postcode":"91354",
    "addr:street":"Waterford Dr",
    "iso:country":"US",
    "sg:address":"27205 Waterford Dr",
    "sg:city":"Valencia",
    "sg:classifiers":[
        {
            "category":"Farming",
            "subcategory":"Crops",
            "type":"Manufacturing & Wholesale Goods"
        }
    ],
    "sg:phone":"+1 661 297 1073",
    "sg:postcode":"91354",
    "sg:province":"CA",
    "sg:tags":[
        "grove",
        "nut",
        "tree"
    ],
    "wof:name":"Bono Macs of Hawaii",
    "wof:placetype":"venue"
},
  "geometry": {"coordinates":[-118.54667499999999,34.436116],"type":"Point"}
}