{
  "type": "Feature",
  "properties": {
    "addr:full":"4208 Olympic Ave San Mateo CA 94403",
    "addr:housenumber":"4208",
    "addr:postcode":"94403",
    "addr:street":"Olympic Ave",
    "iso:country":"US",
    "sg:address":"4208 Olympic Ave",
    "sg:city":"San Mateo",
    "sg:classifiers":[
        {
            "category":"Insurance",
            "subcategory":"Insurance Agent",
            "type":"Services"
        }
    ],
    "sg:phone":"+1 650 525 3800",
    "sg:postcode":"94403",
    "sg:province":"CA",
    "wof:name":"State Farm Insurance",
    "wof:placetype":"venue"
},
  "geometry": {"coordinates":[-122.290864,37.529197],"type":"Point"}
}