{
  "type": "Feature",
  "properties": {
    "addr:full":"12462 Bradford Pl Granada Hills CA 91344",
    "addr:housenumber":"12462",
    "addr:postcode":"91344",
    "addr:street":"Bradford Pl",
    "iso:country":"US",
    "sg:address":"12462 Bradford Pl",
    "sg:city":"Granada Hills",
    "sg:classifiers":[
        {
            "category":"Wholesale",
            "subcategory":"Machinery & Supplies",
            "type":"Manufacturing & Wholesale Goods"
        }
    ],
    "sg:phone":"+1 213 892 1464",
    "sg:postcode":"91344",
    "sg:province":"CA",
    "sg:tags":[
        "sprinkler"
    ],
    "wof:name":"Pfp Inc",
    "wof:placetype":"venue"
},
  "geometry": {"coordinates":[-118.51528500000001,34.296422],"type":"Point"}
}