{
  "type": "Feature",
  "properties": {
    "addr:full":"5219 Apennines Cir San Jose CA 95138",
    "addr:housenumber":"5219",
    "addr:postcode":"95138",
    "addr:street":"Apennines Cir",
    "iso:country":"US",
    "sg:address":"5219 Apennines Cir",
    "sg:city":"San Jose",
    "sg:classifiers":[
        {
            "category":"Professional",
            "type":"Services"
        }
    ],
    "sg:phone":"+1 408 532 1213",
    "sg:postcode":"95138",
    "sg:province":"CA",
    "wof:name":"Holt Alliance",
    "wof:placetype":"venue"
},
  "geometry": {"coordinates":[-121.76736099999999,37.281724],"type":"Point"}
}