{
  "type": "Feature",
  "properties": {
    "iso:country":"US",
    "sg:address":"1317 S H St",
    "sg:city":"Bakersfield",
    "sg:classifiers":[
        {
            "category":"Insurance",
            "subcategory":"Insurance Agent",
            "type":"Services"
        }
    ],
    "sg:phone":"+1 661 395 0256",
    "sg:postcode":"93304",
    "sg:province":"CA",
    "wof:name":"Allstate Insurance",
    "wof:placetype":"venue"
},
  "geometry": {"coordinates":[-119.021269,35.341408],"type":"Point"}
}