{
  "type": "Feature",
  "properties": {
    "addr:full":"14455 Don Julian Rd City Of Industry CA 91746",
    "addr:housenumber":"14455",
    "addr:postcode":"91746",
    "addr:street":"Don Julian Rd",
    "iso:country":"US",
    "sg:address":"14455 Don Julian Rd",
    "sg:city":"City Of Industry",
    "sg:classifiers":[
        {
            "category":"Manufacturing",
            "subcategory":"Food",
            "type":"Manufacturing & Wholesale Goods"
        }
    ],
    "sg:phone":"+1 626 336 3886",
    "sg:postcode":"91746",
    "sg:province":"CA",
    "sg:tags":[
        "canning"
    ],
    "wof:name":"Lee Kum Kee USA Food Inc",
    "wof:placetype":"venue"
},
  "geometry": {"coordinates":[-117.980508,34.029148],"type":"Point"}
}