{
  "type": "Feature",
  "properties": {
    "addr:full":"2114 McKee Rd San Jose CA 95116",
    "addr:housenumber":"2114",
    "addr:postcode":"95116",
    "addr:street":"Mckee Rd",
    "iso:country":"US",
    "sg:address":"2114 McKee Rd",
    "sg:city":"San Jose",
    "sg:classifiers":[
        {
            "category":"Health Services",
            "subcategory":"Doctor",
            "type":"Services"
        }
    ],
    "sg:phone":"+1 408 251 4377",
    "sg:postcode":"95116",
    "sg:province":"CA",
    "sg:tags":[
        "physician",
        "surgeon"
    ],
    "wof:name":"Peter C Fung Inc",
    "wof:placetype":"venue"
},
  "geometry": {"coordinates":[-121.853126,37.363124],"type":"Point"}
}