{
  "type": "Feature",
  "properties": {
    "iso:country":"US",
    "sg:address":"811 N Avalon Blvd",
    "sg:city":"Wilmington",
    "sg:classifiers":[
        {
            "category":"Shopping",
            "subcategory":"Clothing, Apparel, & Fashions",
            "type":"Retail Goods"
        }
    ],
    "sg:phone":"+1 310 830 4369",
    "sg:postcode":"90744",
    "sg:province":"CA",
    "wof:name":"Joy 3927 Corp",
    "wof:placetype":"venue"
},
  "geometry": {"coordinates":[-118.262592,33.781085],"type":"Point"}
}