{
  "type": "Feature",
  "properties": {
    "addr:full":"718 S Hill St Los Angeles CA 90014",
    "addr:housenumber":"718",
    "addr:postcode":"90014",
    "addr:street":"S Hill St",
    "iso:country":"US",
    "sg:address":"718 S Hill St",
    "sg:city":"Los Angeles",
    "sg:classifiers":[
        {
            "category":"Wholesale",
            "subcategory":"Jewelry",
            "type":"Manufacturing & Wholesale Goods"
        }
    ],
    "sg:phone":"+1 213 627 8137",
    "sg:postcode":"90014",
    "sg:province":"CA",
    "sg:tags":[
        "stone",
        "precious"
    ],
    "wof:name":"Stallion & Co",
    "wof:placetype":"venue"
},
  "geometry": {"coordinates":[-118.255522,34.044687],"type":"Point"}
}