{
  "type": "Feature",
  "properties": {
    "addr:full":"100 N Hill Dr Ste 49 Brisbane CA 94005",
    "addr:housenumber":"100;49",
    "addr:postcode":"94005",
    "addr:street":"N Hill Dr Ste",
    "iso:country":"US",
    "sg:address":"100 N Hill Dr Ste 49",
    "sg:city":"Brisbane",
    "sg:classifiers":[
        {
            "category":"Wholesale",
            "subcategory":"Machinery & Supplies",
            "type":"Manufacturing & Wholesale Goods"
        }
    ],
    "sg:phone":"+1 415 467 7144",
    "sg:postcode":"94005",
    "sg:province":"CA",
    "sg:tags":[
        "designed",
        "specially"
    ],
    "wof:name":"Randall R S & Co.",
    "wof:placetype":"venue"
},
  "geometry": {"coordinates":[-122.406914,37.690578],"type":"Point"}
}