{
  "type": "Feature",
  "properties": {
    "addr:full":"11537 Apple Valley Rd Apple Valley CA 92308",
    "addr:housenumber":"11537",
    "addr:postcode":"92308",
    "addr:street":"Apple Valley Rd",
    "iso:country":"US",
    "sg:address":"11537 Apple Valley Rd",
    "sg:city":"Apple Valley",
    "sg:classifiers":[
        {
            "category":"Organizations",
            "subcategory":"Religious Organization",
            "type":"Services"
        }
    ],
    "sg:phone":"+1 760 961 2242",
    "sg:postcode":"92308",
    "sg:province":"CA",
    "sg:tags":[
        "church"
    ],
    "wof:name":"Jess Ranch Community Church",
    "wof:placetype":"venue"
},
  "geometry": {"coordinates":[-117.241602,34.462092],"type":"Point"}
}