{
  "type": "Feature",
  "properties": {
    "addr:full":"2650 Orbiter St Brea CA 92821",
    "addr:housenumber":"2650",
    "addr:postcode":"92821",
    "addr:street":"Orbiter St",
    "iso:country":"US",
    "sg:address":"2650 Orbiter St",
    "sg:city":"Brea",
    "sg:classifiers":[
        {
            "category":"Building & Trades",
            "subcategory":"Locksmith",
            "type":"Services"
        },
        {
            "category":"Manufacturing",
            "subcategory":"Soap",
            "type":"Manufacturing & Wholesale Goods"
        }
    ],
    "sg:phone":"+1 714 961 2400",
    "sg:postcode":"92821",
    "sg:province":"CA",
    "sg:tags":[
        "locks-wholesale",
        "lock",
        "manufacturer"
    ],
    "sg:website":"http://www.jaderange.com",
    "wof:name":"Falcon Lock Company Inc",
    "wof:placetype":"venue"
},
  "geometry": {"coordinates":[-117.859899,33.914328],"type":"Point"}
}