{
  "type": "Feature",
  "properties": {
    "addr:full":"13205 Osborne St Ste C Arleta CA 91331",
    "addr:housenumber":"13205",
    "addr:postcode":"91331",
    "addr:street":"Osborne St Ste C Arleta",
    "iso:country":"US",
    "sg:address":"13205 Osborne St Ste C",
    "sg:city":"Arleta",
    "sg:classifiers":[
        {
            "category":"Restaurant",
            "type":"Food & Drink"
        },
        {
            "category":"Donuts",
            "subcategory":"None",
            "type":"Food & Drink"
        }
    ],
    "sg:phone":"+1 818 899 3890",
    "sg:postcode":"91331",
    "sg:province":"CA",
    "sg:tags":[
        "shop"
    ],
    "wof:name":"Daily Fresh Donuts",
    "wof:placetype":"venue"
},
  "geometry": {"coordinates":[-118.420575,34.246101],"type":"Point"}
}