{
  "type": "Feature",
  "properties": {
    "iso:country":"US",
    "sg:address":"4165 E Thousand Oaks Blvd",
    "sg:city":"Westlake Village",
    "sg:classifiers":[
        {
            "category":"Real Estate",
            "subcategory":"Real Estate Services",
            "type":"Services"
        }
    ],
    "sg:phone":"+1 805 449 4242",
    "sg:postcode":"91362",
    "sg:province":"CA",
    "sg:tags":[
        "company",
        "title"
    ],
    "sg:website":"www.unitedtitle.com",
    "wof:name":"United Title Co",
    "wof:placetype":"venue"
},
  "geometry": {"coordinates":[-118.820347,34.159663],"type":"Point"}
}