{
  "type": "Feature",
  "properties": {
    "iso:country":"US",
    "sg:address":"2669 Elliott St",
    "sg:city":"Santa Clara",
    "sg:classifiers":[
        {
            "category":"Manufacturing",
            "subcategory":"Tools & Machinery",
            "type":"Manufacturing & Wholesale Goods"
        }
    ],
    "sg:phone":"+1 408 248 2064",
    "sg:postcode":"95051",
    "sg:province":"CA",
    "sg:tags":[
        "mfg"
    ],
    "wof:name":"Virdi Mold",
    "wof:placetype":"venue"
},
  "geometry": {"coordinates":[-121.973665,37.362475],"type":"Point"}
}