{
  "type": "Feature",
  "properties": {
    "iso:country":"US",
    "sg:address":"14102 Stowe Dr",
    "sg:city":"Poway",
    "sg:classifiers":[
        {
            "category":"Autos & Motor Vehicles",
            "subcategory":"Auto Supplies",
            "type":"Retail Goods"
        }
    ],
    "sg:phone":"+1 858 386 5900",
    "sg:postcode":"92064",
    "sg:province":"CA",
    "sg:tags":[
        "automobile",
        "absorber",
        "shock",
        "part",
        "strut"
    ],
    "wof:name":"Bilstein Shock Absorbers",
    "wof:placetype":"venue"
},
  "geometry": {"coordinates":[-117.028975,32.935684],"type":"Point"}
}