{
  "type": "Feature",
  "properties": {
    "addr:full":"265 E Carson St Carson CA 90745",
    "addr:housenumber":"265",
    "addr:postcode":"90745",
    "addr:street":"E Carson St",
    "iso:country":"US",
    "sg:address":"265 E Carson St",
    "sg:city":"Carson",
    "sg:classifiers":[
        {
            "category":"Building & Trades",
            "subcategory":"Locksmith",
            "type":"Services"
        }
    ],
    "sg:phone":"+1 310 549 0820",
    "sg:postcode":"90745",
    "sg:province":"CA",
    "sg:tags":[
        "key"
    ],
    "sg:website":"www.sanpedrolock.com",
    "wof:name":"Carson Lock & Safe",
    "wof:placetype":"venue"
},
  "geometry": {"coordinates":[-118.275002,33.831799],"type":"Point"}
}