{
  "type": "Feature",
  "properties": {
    "iso:country":"US",
    "sg:address":"19 Panorama Dr",
    "sg:city":"Vallejo",
    "sg:classifiers":[
        {
            "category":"Real Estate",
            "subcategory":"Real Estate Operator",
            "type":"Services"
        }
    ],
    "sg:phone":"+1 707 642 6400",
    "sg:postcode":"94589",
    "sg:province":"CA",
    "sg:tags":[
        "apartment"
    ],
    "wof:name":"Holiday Gardens Apartments",
    "wof:placetype":"venue"
},
  "geometry": {"coordinates":[-122.237807,38.124665],"type":"Point"}
}