{
  "type": "Feature",
  "properties": {
    "addr:full":"670 5th St Lincoln CA 95648",
    "addr:housenumber":"670",
    "addr:postcode":"95648",
    "addr:street":"5Th St",
    "iso:country":"US",
    "sg:address":"670 5th St",
    "sg:city":"Lincoln",
    "sg:classifiers":[
        {
            "category":"Personal",
            "subcategory":"Beauty Salon",
            "type":"Services"
        }
    ],
    "sg:phone":"+1 916 645 9836",
    "sg:postcode":"95648",
    "sg:province":"CA",
    "wof:name":"Lincolns City Barber Shop",
    "wof:placetype":"venue"
},
  "geometry": {"coordinates":[-121.292321,38.891957],"type":"Point"}
}