{
  "type": "Feature",
  "properties": {
    "addr:full":"34432 Yucaipa Blvd Ste E Yucaipa CA 92399",
    "addr:postcode":"34432;92399",
    "addr:street":"Yucaipa Blvd Ste E",
    "iso:country":"US",
    "sg:address":"34432 Yucaipa Blvd Ste E",
    "sg:city":"Yucaipa",
    "sg:classifiers":[
        {
            "category":"Shopping",
            "subcategory":"Mobile Phones",
            "type":"Retail Goods"
        }
    ],
    "sg:phone":"+1 909 797 4669",
    "sg:postcode":"92399",
    "sg:province":"CA",
    "sg:website":"www.radioshack.com",
    "wof:name":"Radioshack",
    "wof:placetype":"venue"
},
  "geometry": {"coordinates":[-117.053281,34.03391],"type":"Point"}
}