{
  "type": "Feature",
  "properties": {
    "iso:country":"US",
    "sg:address":"201 S Santa Fe Ave",
    "sg:city":"Los Angeles",
    "sg:classifiers":[
        {
            "category":"Professional",
            "subcategory":"Business Services",
            "type":"Services"
        }
    ],
    "sg:phone":"+1 213 489 7755",
    "sg:postcode":"90012",
    "sg:province":"CA",
    "sg:tags":[
        "consultant",
        "production",
        "music"
    ],
    "wof:name":"Kabuki Digital",
    "wof:placetype":"venue"
},
  "geometry": {"coordinates":[-118.232586,34.045977],"type":"Point"}
}