{
  "type": "Feature",
  "properties": {
    "addr:full":"1855 Industrial St Los Angeles CA 90021",
    "addr:housenumber":"1855",
    "addr:postcode":"90021",
    "addr:street":"Industrial St",
    "iso:country":"US",
    "sg:address":"1855 Industrial St",
    "sg:city":"Los Angeles",
    "sg:classifiers":[
        {
            "category":"Arts & Performance",
            "subcategory":"Theater",
            "type":"Entertainment"
        }
    ],
    "sg:phone":"+1 323 654 3487",
    "sg:postcode":"90021",
    "sg:province":"CA",
    "sg:tags":[
        "television",
        "program",
        "producer"
    ],
    "wof:name":"JCS Syndication Svc",
    "wof:placetype":"venue"
},
  "geometry": {"coordinates":[-118.23286400000001,34.035826],"type":"Point"}
}