{
  "type": "Feature",
  "properties": {
    "addr:full":"6900 Koll Center Pkwy Pleasanton CA 94566",
    "addr:postcode":"6900;94566",
    "addr:street":"Center Pkwy",
    "iso:country":"US",
    "sg:address":"6900 Koll Center Pkwy",
    "sg:city":"Pleasanton",
    "sg:classifiers":[
        {
            "category":"Insurance",
            "subcategory":"Insurance Agent",
            "type":"Services"
        }
    ],
    "sg:phone":"+1 925 875 1155",
    "sg:postcode":"94566",
    "sg:province":"CA",
    "wof:name":"Dunham Winoto",
    "wof:placetype":"venue"
},
  "geometry": {"coordinates":[-121.902584,37.660736],"type":"Point"}
}