{
  "type": "Feature",
  "properties": {
    "addr:full":"20465 E Peach Blossom Rd Walnut CA 91789",
    "addr:housenumber":"20465",
    "addr:postcode":"91789",
    "addr:street":"E Peach Blossom Rd",
    "iso:country":"US",
    "sg:address":"20465 E Peach Blossom Rd",
    "sg:city":"Walnut",
    "sg:classifiers":[
        {
            "category":"Real Estate",
            "subcategory":"Real Estate Operator",
            "type":"Services"
        }
    ],
    "sg:phone":"+1 909 595 1613",
    "sg:postcode":"91789",
    "sg:province":"CA",
    "sg:tags":[
        "apartment"
    ],
    "wof:name":"The Edwards Apts",
    "wof:placetype":"venue"
},
  "geometry": {"coordinates":[-117.857235,34.036503],"type":"Point"}
}