{
  "type": "Feature",
  "properties": {
    "addr:full":"725 85th Ave Oakland CA 94621",
    "addr:housenumber":"725",
    "addr:postcode":"94621",
    "addr:street":"85Th Ave",
    "iso:country":"US",
    "sg:address":"725 85th Ave",
    "sg:city":"Oakland",
    "sg:classifiers":[
        {
            "category":"Wholesale",
            "subcategory":"Drugs",
            "type":"Manufacturing & Wholesale Goods"
        }
    ],
    "sg:phone":"+1 510 729 7188",
    "sg:postcode":"94621",
    "sg:province":"CA",
    "sg:website":"www.benefitcosmetics.com",
    "wof:name":"Benefit Cosmetics",
    "wof:placetype":"venue"
},
  "geometry": {"coordinates":[-122.189598,37.746751],"type":"Point"}
}