{
  "type": "Feature",
  "properties": {
    "iso:country":"US",
    "sg:address":"2968 Alvarado St",
    "sg:city":"San Leandro",
    "sg:classifiers":[
        {
            "category":"Personal",
            "type":"Services"
        }
    ],
    "sg:phone":"+1 510 352 8066",
    "sg:postcode":"94577",
    "sg:province":"CA",
    "sg:tags":[
        "mover"
    ],
    "wof:name":"Hawaiian Ocean Transport",
    "wof:placetype":"venue"
},
  "geometry": {"coordinates":[-122.151917,37.705201],"type":"Point"}
}