{
  "type": "Feature",
  "properties": {
    "addr:full":"102 Pearson Rd Inyokern CA 93527",
    "addr:housenumber":"102",
    "addr:postcode":"93527",
    "addr:street":"Pearson Rd",
    "iso:country":"US",
    "sg:address":"102 Pearson Rd",
    "sg:city":"Inyokern",
    "sg:classifiers":[
        {
            "category":"Autos & Motor Vehicles",
            "subcategory":"Fuel & Gas Station",
            "type":"Retail Goods"
        }
    ],
    "sg:phone":"+1 760 377 5353",
    "sg:postcode":"93527",
    "sg:province":"CA",
    "sg:tags":[
        "oil"
    ],
    "wof:name":"Pearsonville Shell",
    "wof:placetype":"venue"
},
  "geometry": {"coordinates":[-117.87269000000001,35.808238],"type":"Point"}
}