{
  "type": "Feature",
  "properties": {
    "addr:full":"9215 Arrow Rte Rancho Cucamonga CA 91730",
    "addr:housenumber":"9215",
    "addr:postcode":"91730",
    "addr:street":"Arrow Rte",
    "iso:country":"US",
    "sg:address":"9215 Arrow Rte",
    "sg:city":"Rancho Cucamonga",
    "sg:classifiers":[
        {
            "category":"Social Services",
            "subcategory":"Child Care",
            "type":"Services"
        }
    ],
    "sg:phone":"+1 909 481 6427",
    "sg:postcode":"91730",
    "sg:province":"CA",
    "wof:name":"YMCA-Kids Club",
    "wof:placetype":"venue"
},
  "geometry": {"coordinates":[-117.604283,34.099261],"type":"Point"}
}