{
  "type": "Feature",
  "properties": {
    "addr:full":"99 Divisadero Street San Francisco CA 94117",
    "addr:housenumber":"99",
    "addr:postcode":"94117",
    "addr:street":"Divisadero Street",
    "iso:country":"US",
    "sg:address":"99 Divisadero Street",
    "sg:city":"San Francisco",
    "sg:classifiers":[
        {
            "category":"Professional",
            "subcategory":"Lawyer & Legal Services",
            "type":"Services"
        }
    ],
    "sg:phone":"+1 415 621 4100",
    "sg:postcode":"94117",
    "sg:province":"CA",
    "wof:name":"Law Office of Richard Mazer",
    "wof:placetype":"venue"
},
  "geometry": {"coordinates":[-122.43699599999999,37.768902],"type":"Point"}
}