{
  "type": "Feature",
  "properties": {
    "addr:full":"15408 Highway 178 Weldon CA 93283",
    "addr:housenumber":"15408",
    "addr:postcode":"93283",
    "addr:street":"Highway 178",
    "iso:country":"US",
    "sg:address":"15408 Highway 178",
    "sg:city":"Weldon",
    "sg:classifiers":[
        {
            "category":"Building & Trades",
            "subcategory":"Equipment Rental",
            "type":"Services"
        }
    ],
    "sg:phone":"+1 760 378 2500",
    "sg:postcode":"93283",
    "sg:province":"CA",
    "sg:tags":[
        "yard",
        "leasing",
        "store"
    ],
    "wof:name":"Lakeside Rental & Repair",
    "wof:placetype":"venue"
},
  "geometry": {"coordinates":[-118.354056,35.651724],"type":"Point"}
}