{
  "type": "Feature",
  "properties": {
    "iso:country":"US",
    "sg:address":"14 Corporate Plaza Dr",
    "sg:city":"Newport Beach",
    "sg:classifiers":[
        {
            "category":"Real Estate",
            "subcategory":"Real Estate Agent",
            "type":"Services"
        }
    ],
    "sg:phone":"+1 949 721 6984",
    "sg:postcode":"92660",
    "sg:province":"CA",
    "wof:name":"Capstone Commercial Properties",
    "wof:placetype":"venue"
},
  "geometry": {"coordinates":[-117.87693400000001,33.608506],"type":"Point"}
}