{
  "type": "Feature",
  "properties": {
    "addr:full":"2844 Carmel St Oakland CA 94602",
    "addr:housenumber":"2844",
    "addr:postcode":"94602",
    "addr:street":"Carmel St",
    "iso:country":"US",
    "sg:address":"2844 Carmel St",
    "sg:city":"Oakland",
    "sg:classifiers":[
        {
            "category":"Building & Trades",
            "subcategory":"Construction",
            "type":"Services"
        }
    ],
    "sg:phone":"+1 510 336 3494",
    "sg:postcode":"94602",
    "sg:province":"CA",
    "sg:tags":[
        "contractor"
    ],
    "wof:name":"Herman Schweirzer Painting",
    "wof:placetype":"venue"
},
  "geometry": {"coordinates":[-122.202399,37.800991],"type":"Point"}
}