{
  "type": "Feature",
  "properties": {
    "iso:country":"US",
    "sg:address":"2901 Ocean Park Blvd",
    "sg:city":"Santa Monica",
    "sg:classifiers":[
        {
            "category":"Professional",
            "subcategory":"Accounting & Tax Preparation",
            "type":"Services"
        }
    ],
    "sg:phone":"+1 310 452 3051",
    "sg:postcode":"90405",
    "sg:province":"CA",
    "sg:tags":[
        "return",
        "filing"
    ],
    "wof:name":"Diane Gray Business & Tax Svc",
    "wof:placetype":"venue"
},
  "geometry": {"coordinates":[-118.453873,34.019915],"type":"Point"}
}