{
  "type": "Feature",
  "properties": {
    "addr:full":"7230 Fairmount Ave El Cerrito CA 94530",
    "addr:housenumber":"7230",
    "addr:postcode":"94530",
    "addr:street":"Fairmount Ave",
    "iso:country":"US",
    "sg:address":"7230 Fairmount Ave",
    "sg:city":"El Cerrito",
    "sg:classifiers":[
        {
            "category":"Education",
            "subcategory":"School",
            "type":"Public Place"
        }
    ],
    "sg:phone":"+1 510 231 1413",
    "sg:postcode":"94530",
    "sg:province":"CA",
    "sg:tags":[
        "elementary"
    ],
    "sg:website":"www.hardingpta.org",
    "wof:name":"Harding Elementary School WCCUSD",
    "wof:placetype":"venue"
},
  "geometry": {"coordinates":[-122.29414,37.902118],"type":"Point"}
}