{
  "type": "Feature",
  "properties": {
    "addr:full":"4716 Woodman Ave Van Nuys CA 91423",
    "addr:housenumber":"4716",
    "addr:postcode":"91423",
    "addr:street":"Woodman Ave",
    "iso:country":"US",
    "sg:address":"4716 Woodman Ave",
    "sg:city":"Van Nuys",
    "sg:classifiers":[
        {
            "category":"Social Services",
            "type":"Services"
        }
    ],
    "sg:phone":"+1 818 907 9600",
    "sg:postcode":"91423",
    "sg:province":"CA",
    "sg:tags":[
        "organization",
        "welfare"
    ],
    "sg:website":"www.grief.net",
    "wof:name":"Grief Recovery Institute",
    "wof:placetype":"venue"
},
  "geometry": {"coordinates":[-118.431157,34.156256],"type":"Point"}
}