{
  "type": "Feature",
  "properties": {
    "addr:full":"926 J St Ste 905 Sacramento CA 95814",
    "addr:housenumber":"926",
    "addr:postcode":"95814",
    "addr:street":"J St Ste 905",
    "iso:country":"US",
    "sg:address":"926 J St Ste 905",
    "sg:city":"Sacramento",
    "sg:classifiers":[
        {
            "category":"Professional",
            "subcategory":"Lawyer & Legal Services",
            "type":"Services"
        }
    ],
    "sg:phone":"+1 916 442 6210",
    "sg:postcode":"95814",
    "sg:province":"CA",
    "sg:tags":[
        "clinic"
    ],
    "wof:name":"California Lawyers For Arts Inc",
    "wof:placetype":"venue"
},
  "geometry": {"coordinates":[-121.494105,38.580498],"type":"Point"}
}