{
  "type": "Feature",
  "properties": {
    "addr:full":"1606 Parrot Ct Ventura CA 93003",
    "addr:housenumber":"1606",
    "addr:postcode":"93003",
    "addr:street":"Parrot Ct",
    "iso:country":"US",
    "sg:address":"1606 Parrot Ct",
    "sg:city":"Ventura",
    "sg:classifiers":[
        {
            "category":"Professional",
            "type":"Services"
        }
    ],
    "sg:phone":"+1 805 658 7739",
    "sg:postcode":"93003",
    "sg:province":"CA",
    "wof:name":"No Limits",
    "wof:placetype":"venue"
},
  "geometry": {"coordinates":[-119.198941,34.261979],"type":"Point"}
}