{
  "type": "Feature",
  "properties": {
    "addr:full":"5687 Redwood Dr Rohnert Park CA 94928",
    "addr:housenumber":"5687",
    "addr:postcode":"94928",
    "addr:street":"Redwood Dr",
    "iso:country":"US",
    "sg:address":"5687 Redwood Dr",
    "sg:city":"Rohnert Park",
    "sg:classifiers":[
        {
            "category":"Retail",
            "subcategory":"Auto Repair",
            "type":"Services"
        }
    ],
    "sg:phone":"+1 707 584 4223",
    "sg:postcode":"94928",
    "sg:province":"CA",
    "sg:tags":[
        "repairing",
        "automobile"
    ],
    "sg:website":"www.aceautomotive.com",
    "wof:name":"Ace Automotive",
    "wof:placetype":"venue"
},
  "geometry": {"coordinates":[-122.713611,38.356967],"type":"Point"}
}