{
  "type": "Feature",
  "properties": {
    "acgov:api":"614.0",
    "acgov:type":"HS",
    "addr:full":"1633 East Ave. Hayward CA",
    "wof:categories":[
        "education_and_religion:education=school"
    ],
    "wof:name":"Hayward High",
    "wof:placetype":"venue"
},
  "geometry": {"coordinates":[-122.06828601091752,37.67235952146851],"type":"Point"}
}