{
  "type": "Feature",
  "properties": {
    "addr:full":"1744 University Ave Berkeley CA 94703",
    "addr:housenumber":"1744",
    "addr:postcode":"94703",
    "addr:street":"University Ave",
    "iso:country":"US",
    "sg:address":"1744 University Ave",
    "sg:city":"Berkeley",
    "sg:classifiers":[
        {
            "category":"Organizations",
            "subcategory":"Non-profit Organization",
            "type":"Services"
        }
    ],
    "sg:phone":"+1 510 704 9867",
    "sg:postcode":"94703",
    "sg:province":"CA",
    "sg:tags":[
        "service/non-profit",
        "community"
    ],
    "sg:website":"yeah-berkeley.org/index.php",
    "wof:name":"Youth Engagement, Advocacy and Housing",
    "wof:placetype":"venue"
},
  "geometry": {"coordinates":[-122.27659800000001,37.871024],"type":"Point"}
}