{
  "type": "Feature",
  "properties": {
    "iso:country":"US",
    "sg:address":"1101 National Dr Ste B",
    "sg:city":"Sacramento",
    "sg:classifiers":[
        {
            "category":"Government",
            "subcategory":"Office",
            "type":"Public Place"
        }
    ],
    "sg:phone":"+1 916 263 3560",
    "sg:postcode":"95834",
    "sg:province":"CA",
    "sg:tags":[
        "government-state"
    ],
    "sg:website":"http://www.dairycouncilofca.org",
    "wof:name":"Dairy Council Of California",
    "wof:placetype":"venue"
},
  "geometry": {"coordinates":[-121.487617,38.64679],"type":"Point"}
}