{
  "type": "Feature",
  "properties": {
    "addr:full":"937 E 20th St Long Beach CA 90806",
    "addr:housenumber":"937",
    "addr:postcode":"90806",
    "addr:street":"E 20Th St",
    "iso:country":"US",
    "sg:address":"937 E 20th St",
    "sg:city":"Long Beach",
    "sg:classifiers":[
        {
            "category":"Shopping",
            "subcategory":"Pharmacy",
            "type":"Retail Goods"
        }
    ],
    "sg:phone":"+1 562 218 0831",
    "sg:postcode":"90806",
    "sg:province":"CA",
    "sg:tags":[
        "homeopathic",
        "remedy"
    ],
    "wof:name":"Kava Wholesaler",
    "wof:placetype":"venue"
},
  "geometry": {"coordinates":[-118.18100099999999,33.793562],"type":"Point"}
}