{
  "type": "Feature",
  "properties": {
    "iso:country":"US",
    "sg:address":"6761 Sebastopol Ave",
    "sg:city":"Sebastopol",
    "sg:classifiers":[
        {
            "category":"Food & Beverages",
            "subcategory":"Specialty",
            "type":"Retail Goods"
        }
    ],
    "sg:phone":"+1 707 829 6600",
    "sg:postcode":"95472",
    "sg:province":"CA",
    "sg:tags":[
        "tea",
        "coffee"
    ],
    "wof:name":"Coffee Catz",
    "wof:placetype":"venue"
},
  "geometry": {"coordinates":[-122.819175,38.402814],"type":"Point"}
}