{
  "type": "Feature",
  "properties": {
    "iso:country":"US",
    "sg:address":"9528 E Heaney Cir",
    "sg:city":"Santee",
    "sg:classifiers":[
        {
            "category":"Wholesale",
            "subcategory":"Non-durable Goods",
            "type":"Manufacturing & Wholesale Goods"
        }
    ],
    "sg:phone":"+1 619 448 2799",
    "sg:postcode":"92071",
    "sg:province":"CA",
    "wof:name":"Jim Matthes Sales",
    "wof:placetype":"venue"
},
  "geometry": {"coordinates":[-116.998823,32.84957],"type":"Point"}
}