{
  "type": "Feature",
  "properties": {
    "addr:full":"1018 Hilgard Ave Los Angeles CA 90024",
    "addr:housenumber":"1018",
    "addr:postcode":"90024",
    "addr:street":"Hilgard Ave",
    "iso:country":"US",
    "sg:address":"1018 Hilgard Ave",
    "sg:city":"Los Angeles",
    "sg:classifiers":[
        {
            "category":"Organizations",
            "subcategory":"Religious Organization",
            "type":"Services"
        }
    ],
    "sg:phone":"+1 310 208 8189",
    "sg:postcode":"90024",
    "sg:province":"CA",
    "sg:tags":[
        "church"
    ],
    "wof:name":"28th Church-Christ Scientist",
    "wof:placetype":"venue"
},
  "geometry": {"coordinates":[-118.441948,34.060473],"type":"Point"}
}