{
  "type": "Feature",
  "properties": {
    "iso:country":"US",
    "sg:address":"1148 6th Ave",
    "sg:city":"Oakland",
    "sg:classifiers":[
        {
            "category":"Manufacturing",
            "subcategory":"Toys & Sporting Goods",
            "type":"Manufacturing & Wholesale Goods"
        }
    ],
    "sg:phone":"+1 510 452 0243",
    "sg:postcode":"94606",
    "sg:province":"CA",
    "sg:tags":[
        "equipment",
        "camping"
    ],
    "wof:name":"Mark Pack Works",
    "wof:placetype":"venue"
},
  "geometry": {"coordinates":[-122.25439,37.793905],"type":"Point"}
}