{
  "type": "Feature",
  "properties": {
    "iso:country":"US",
    "sg:address":"560 Waverley St",
    "sg:city":"Palo Alto",
    "sg:classifiers":[
        {
            "category":"Restaurant",
            "type":"Food & Drink"
        }
    ],
    "sg:menulink":"http://www.allmenus.com/ca/san-jose/267868-tai-pan/menu/",
    "sg:phone":"+1 650 329 9168",
    "sg:postcode":"94301",
    "sg:province":"CA",
    "sg:tags":[
        "asian",
        "chinese"
    ],
    "wof:name":"Tai Pan",
    "wof:placetype":"venue"
},
  "geometry": {"coordinates":[-122.159712,37.446407],"type":"Point"}
}