{
  "type": "Feature",
  "properties": {
    "addr:full":"147 Old Bernal Ave Pleasanton CA 94566",
    "addr:housenumber":"147",
    "addr:postcode":"94566",
    "addr:street":"Old Bernal Ave",
    "iso:country":"US",
    "sg:address":"147 Old Bernal Ave",
    "sg:city":"Pleasanton",
    "sg:classifiers":[
        {
            "category":"Freight",
            "type":"Transportation"
        }
    ],
    "sg:phone":"+1 925 426 0777",
    "sg:postcode":"94566",
    "sg:province":"CA",
    "sg:tags":[
        "general"
    ],
    "wof:name":"Pleasanton R V & Eqp Stor",
    "wof:placetype":"venue"
},
  "geometry": {"coordinates":[-121.87780100000001,37.658699],"type":"Point"}
}