{
  "type": "Feature",
  "properties": {
    "iso:country":"US",
    "sg:address":"42263 50th St W",
    "sg:city":"Quartz Hill",
    "sg:classifiers":[
        {
            "category":"Manufacturing",
            "subcategory":"Printing",
            "type":"Manufacturing & Wholesale Goods"
        }
    ],
    "sg:phone":"+1 661 722 2668",
    "sg:postcode":"93536",
    "sg:province":"CA",
    "sg:tags":[
        "newspaper"
    ],
    "wof:name":"Neue Presse",
    "wof:placetype":"venue"
},
  "geometry": {"coordinates":[-118.218628,34.650418],"type":"Point"}
}