{
  "type": "Feature",
  "properties": {
    "addr:full":"11660 Bartlett Ave Adelanto CA 92301",
    "addr:housenumber":"11660",
    "addr:postcode":"92301",
    "addr:street":"Bartlett Ave",
    "iso:country":"US",
    "sg:address":"11660 Bartlett Ave",
    "sg:city":"Adelanto",
    "sg:classifiers":[
        {
            "category":"Autos & Motor Vehicles",
            "subcategory":"Automobile Sales",
            "type":"Retail Goods"
        }
    ],
    "sg:phone":"+1 760 246 6977",
    "sg:postcode":"92301",
    "sg:province":"CA",
    "sg:tags":[
        "car",
        "dealer"
    ],
    "wof:name":"West Wood Auto Sales",
    "wof:placetype":"venue"
},
  "geometry": {"coordinates":[-117.410124,34.579298],"type":"Point"}
}