{
  "type": "Feature",
  "properties": {
    "addr:full":"3959 Goodwin Ave Los Angeles CA 90039",
    "addr:housenumber":"3959",
    "addr:postcode":"90039",
    "addr:street":"Goodwin Ave",
    "iso:country":"US",
    "sg:address":"3959 Goodwin Ave",
    "sg:city":"Los Angeles",
    "sg:classifiers":[
        {
            "category":"Manufacturing",
            "subcategory":"Chemicals & Compounds",
            "type":"Manufacturing & Wholesale Goods"
        }
    ],
    "sg:phone":"+1 323 245 6781",
    "sg:postcode":"90039",
    "sg:province":"CA",
    "sg:tags":[
        "polish"
    ],
    "sg:website":"www.sanitek.com",
    "wof:name":"Sanitek Products Inc",
    "wof:placetype":"venue"
},
  "geometry": {"coordinates":[-118.272426,34.137028],"type":"Point"}
}