{
  "type": "Feature",
  "properties": {
    "iso:country":"US",
    "sg:address":"1113 Hunterston Pl",
    "sg:city":"Cupertino",
    "sg:classifiers":[
        {
            "category":"Wholesale",
            "subcategory":"Electrical",
            "type":"Manufacturing & Wholesale Goods"
        }
    ],
    "sg:phone":"+1 408 564 5241",
    "sg:postcode":"95014",
    "sg:province":"CA",
    "sg:tags":[
        "electronic",
        "component"
    ],
    "wof:name":"Samtronics Inc",
    "wof:placetype":"venue"
},
  "geometry": {"coordinates":[-122.042411,37.305139],"type":"Point"}
}