{
  "type": "Feature",
  "properties": {
    "iso:country":"US",
    "sg:address":"7351 Brentwood Blvd",
    "sg:city":"Brentwood",
    "sg:classifiers":[
        {
            "category":"Shopping",
            "subcategory":"Jewelry",
            "type":"Retail Goods"
        }
    ],
    "sg:phone":"+1 925 240 1701",
    "sg:postcode":"94513",
    "sg:province":"CA",
    "sg:website":"www.925designs.net",
    "wof:name":"925 Designs",
    "wof:placetype":"venue"
},
  "geometry": {"coordinates":[-121.69636300000001,37.948503],"type":"Point"}
}