{
  "type": "Feature",
  "properties": {
    "iso:country":"US",
    "sg:address":"2841 Golden Gate Dr",
    "sg:city":"San Andreas",
    "sg:classifiers":[
        {
            "category":"Professional",
            "subcategory":"Engineering",
            "type":"Services"
        }
    ],
    "sg:phone":"+1 209 754 4011",
    "sg:postcode":"95245",
    "sg:province":"CA",
    "sg:tags":[
        "general",
        "contractor"
    ],
    "wof:name":"Don Steneck Construction Inc",
    "wof:placetype":"venue"
},
  "geometry": {"coordinates":[-120.712918,38.228891],"type":"Point"}
}