{
  "type": "Feature",
  "properties": {
    "addr:full":"1411 N Warren Ave Long Beach CA 90813",
    "addr:housenumber":"1411",
    "addr:postcode":"90813",
    "addr:street":"N Warren Ave",
    "iso:country":"US",
    "sg:address":"1411 N Warren Ave",
    "sg:city":"Long Beach",
    "sg:classifiers":[
        {
            "category":"Building & Trades",
            "subcategory":"Plumbing",
            "type":"Services"
        }
    ],
    "sg:phone":"+1 562 595 1595",
    "sg:postcode":"90813",
    "sg:province":"CA",
    "sg:tags":[
        "plumbing",
        "contractor"
    ],
    "wof:name":"Jordan's Rooter & Plumbing",
    "wof:placetype":"venue"
},
  "geometry": {"coordinates":[-118.175308,33.786046],"type":"Point"}
}