{
  "type": "Feature",
  "properties": {
    "addr:full":"5803 Pinewood Ct Paradise CA 95969",
    "addr:housenumber":"5803",
    "addr:postcode":"95969",
    "addr:street":"Pinewood Ct",
    "iso:country":"US",
    "sg:address":"5803 Pinewood Ct",
    "sg:city":"Paradise",
    "sg:classifiers":[
        {
            "category":"Communications",
            "type":"Services"
        },
        {
            "category":"Shopping",
            "subcategory":"Computers & Home Electronics",
            "type":"Retail Goods"
        }
    ],
    "sg:phone":"+1 530 877 1625",
    "sg:postcode":"95969",
    "sg:province":"CA",
    "sg:tags":[
        "sound",
        "television",
        "system",
        "equipment",
        "radio",
        "store"
    ],
    "wof:name":"Northstate Assistive Technology",
    "wof:placetype":"venue"
},
  "geometry": {"coordinates":[-121.639577,39.75661],"type":"Point"}
}