{
  "type": "Feature",
  "properties": {
    "addr:full":"6625 Benton Rd Paso Robles CA 93446",
    "addr:housenumber":"6625",
    "addr:postcode":"93446",
    "addr:street":"Benton Rd",
    "iso:country":"US",
    "sg:address":"6625 Benton Rd",
    "sg:city":"Paso Robles",
    "sg:classifiers":[
        {
            "category":"Utilities",
            "subcategory":"Refuse",
            "type":"Services"
        }
    ],
    "sg:phone":"+1 805 467 9283",
    "sg:postcode":"93446",
    "sg:province":"CA",
    "sg:tags":[
        "garbage",
        "collection"
    ],
    "wof:name":"San Miguel Garbage Co",
    "wof:placetype":"venue"
},
  "geometry": {"coordinates":[-120.70102199999999,35.696044],"type":"Point"}
}