{
  "type": "Feature",
  "properties": {
    "iso:country":"US",
    "sg:address":"2003 Georgia St",
    "sg:city":"Vallejo",
    "sg:classifiers":[
        {
            "category":"Real Estate",
            "subcategory":"Real Estate Services",
            "type":"Services"
        },
        {
            "category":"Real Estate",
            "subcategory":"Real Estate Agent",
            "type":"Services"
        }
    ],
    "sg:phone":"+1 707 643 2056",
    "sg:postcode":"94590",
    "sg:province":"CA",
    "sg:tags":[
        "management"
    ],
    "wof:name":"Cristina Arceo Inc",
    "wof:placetype":"venue"
},
  "geometry": {"coordinates":[-122.234533,38.100818],"type":"Point"}
}