{
  "type": "Feature",
  "properties": {
    "addr:full":"5661 Citrus Ct Cypress CA 90630",
    "addr:housenumber":"5661",
    "addr:postcode":"90630",
    "addr:street":"Citrus Ct",
    "iso:country":"US",
    "sg:address":"5661 Citrus Ct",
    "sg:city":"Cypress",
    "sg:classifiers":[
        {
            "category":"Manufacturing",
            "subcategory":"Tools & Machinery",
            "type":"Manufacturing & Wholesale Goods"
        }
    ],
    "sg:phone":"+1 714 826 8490",
    "sg:postcode":"90630",
    "sg:province":"CA",
    "sg:tags":[
        "conductive",
        "wiring",
        "devices",
        "mfg"
    ],
    "wof:name":"Lt & Mp Applications",
    "wof:placetype":"venue"
},
  "geometry": {"coordinates":[-118.03430299999999,33.825834],"type":"Point"}
}