{
  "type": "Feature",
  "properties": {
    "addr:full":"10568 Kewen Ave Pacoima CA 91331",
    "addr:housenumber":"10568",
    "addr:postcode":"91331",
    "addr:street":"Kewen Ave",
    "iso:country":"US",
    "sg:address":"10568 Kewen Ave",
    "sg:city":"Pacoima",
    "sg:classifiers":[
        {
            "category":"Personal",
            "subcategory":"Tattoo Parlor",
            "type":"Services"
        }
    ],
    "sg:phone":"+1 818 897 1714",
    "sg:postcode":"91331",
    "sg:province":"CA",
    "sg:tags":[
        "tattooing"
    ],
    "wof:name":"350 Tattoos & Sounds",
    "wof:placetype":"venue"
},
  "geometry": {"coordinates":[-118.424926,34.259896],"type":"Point"}
}