{
  "type": "Feature",
  "properties": {
    "iso:country":"US",
    "sg:address":"1285 Stone Dr",
    "sg:city":"San Marcos",
    "sg:classifiers":[
        {
            "category":"Real Estate",
            "subcategory":"Real Estate Agent",
            "type":"Services"
        }
    ],
    "sg:phone":"+1 760 744 1863",
    "sg:postcode":"92078",
    "sg:province":"CA",
    "wof:name":"Izbicki Development Corp",
    "wof:placetype":"venue"
},
  "geometry": {"coordinates":[-117.192931,33.136049],"type":"Point"}
}