{
  "type": "Feature",
  "properties": {
    "iso:country":"US",
    "sg:address":"255 Ash Ave",
    "sg:city":"Cayucos",
    "sg:classifiers":[
        {
            "category":"Professional",
            "subcategory":"Accounting & Tax Preparation",
            "type":"Services"
        }
    ],
    "sg:phone":"+1 805 995 0022",
    "sg:postcode":"93430",
    "sg:province":"CA",
    "sg:tags":[
        "accountant"
    ],
    "wof:name":"Michael Foster CPA",
    "wof:placetype":"venue"
},
  "geometry": {"coordinates":[-120.905953,35.450787],"type":"Point"}
}