{
  "type": "Feature",
  "properties": {
    "addr:full":"2150 18th Ave San Francisco CA 94116",
    "addr:housenumber":"2150",
    "addr:postcode":"94116",
    "addr:street":"18Th Ave",
    "iso:country":"US",
    "sg:address":"2150 18th Ave",
    "sg:city":"San Francisco",
    "sg:classifiers":[
        {
            "category":"Professional",
            "type":"Services"
        }
    ],
    "sg:phone":"+1 650 642 4286",
    "sg:postcode":"94116",
    "sg:province":"CA",
    "wof:name":"Feeney Trucking",
    "wof:placetype":"venue"
},
  "geometry": {"coordinates":[-122.474622,37.74774],"type":"Point"}
}