{
  "type": "Feature",
  "properties": {
    "addr:full":"41539 Kalmia St Murrieta CA 92562",
    "addr:postcode":"41539;92562",
    "addr:street":"Kalmia St",
    "iso:country":"US",
    "sg:address":"41539 Kalmia St",
    "sg:city":"Murrieta",
    "sg:phone":"+1 951 691 5428",
    "sg:postcode":"92562",
    "sg:province":"CA",
    "wof:name":"It's Greek 2u",
    "wof:placetype":"venue"
},
  "geometry": {"coordinates":[-117.211144,33.560939],"type":"Point"}
}