{
  "type": "Feature",
  "properties": {
    "iso:country":"US",
    "sg:address":"3131 S Bascom Avenue",
    "sg:city":"Campbell",
    "sg:classifiers":[
        {
            "category":"Health Services",
            "subcategory":"Dentist",
            "type":"Services"
        }
    ],
    "sg:phone":"+1 408 559 6800",
    "sg:postcode":"95008",
    "sg:province":"CA",
    "sg:tags":[
        "orthodontist"
    ],
    "wof:name":"Campbell Thomas DDS",
    "wof:placetype":"venue"
},
  "geometry": {"coordinates":[-121.94086,37.266477],"type":"Point"}
}