{
  "type": "Feature",
  "properties": {
    "addr:full":"11 Montecillo Dr Rolling Hls Ests CA 90274",
    "addr:housenumber":"11",
    "addr:postcode":"90274",
    "addr:street":"Montecillo Dr Rolling",
    "iso:country":"US",
    "sg:address":"11 Montecillo Dr",
    "sg:city":"Rolling Hls Ests",
    "sg:classifiers":[
        {
            "category":"Building & Trades",
            "subcategory":"Construction",
            "type":"Services"
        }
    ],
    "sg:phone":"+1 310 530 6736",
    "sg:postcode":"90274",
    "sg:province":"CA",
    "sg:tags":[
        "coping",
        "plastering",
        "tiling",
        "pool",
        "swimming"
    ],
    "wof:name":"See-Clear Pools & Spa",
    "wof:placetype":"venue"
},
  "geometry": {"coordinates":[-118.320447,33.777685],"type":"Point"}
}