{
  "type": "Feature",
  "properties": {
    "addr:full":"985 University Ave Los Gatos CA 95032",
    "addr:housenumber":"985",
    "addr:postcode":"95032",
    "addr:street":"University Ave",
    "iso:country":"US",
    "sg:address":"985 University Ave",
    "sg:city":"Los Gatos",
    "sg:classifiers":[
        {
            "category":"Communications",
            "subcategory":"Newspaper",
            "type":"Services"
        }
    ],
    "sg:phone":"+1 408 399 6972",
    "sg:postcode":"95032",
    "sg:province":"CA",
    "sg:tags":[
        "print",
        "medium"
    ],
    "wof:name":"Bay Area Parents Magazine",
    "wof:placetype":"venue"
},
  "geometry": {"coordinates":[-121.96673699999999,37.250653],"type":"Point"}
}