{
  "type": "Feature",
  "properties": {
    "addr:full":"9911 Central Rd Apple Valley CA 92308",
    "addr:housenumber":"9911",
    "addr:postcode":"92308",
    "addr:street":"Central Rd",
    "iso:country":"US",
    "sg:address":"9911 Central Rd",
    "sg:city":"Apple Valley",
    "sg:classifiers":[
        {
            "category":"Manufacturing",
            "subcategory":"Printing",
            "type":"Manufacturing & Wholesale Goods"
        }
    ],
    "sg:phone":"+1 760 247 0027",
    "sg:postcode":"92308",
    "sg:province":"CA",
    "sg:tags":[
        "publisher"
    ],
    "wof:name":"Squiggle Press Adventur Pblshr",
    "wof:placetype":"venue"
},
  "geometry": {"coordinates":[-117.17258099999999,34.432734],"type":"Point"}
}