{
  "type": "Feature",
  "properties": {
    "addr:full":"1641 W Imperial Hwy Ste 5C La Habra CA 90631",
    "addr:housenumber":"1641",
    "addr:postcode":"90631",
    "addr:street":"W Imperial Hwy Ste 5C",
    "iso:country":"US",
    "sg:address":"1641 W Imperial Hwy Ste 5C",
    "sg:city":"La Habra",
    "sg:classifiers":[
        {
            "category":"Health Services",
            "subcategory":"Dentist",
            "type":"Services"
        }
    ],
    "sg:phone":"+1 562 905 1828",
    "sg:postcode":"90631",
    "sg:province":"CA",
    "wof:name":"Star Dental Group",
    "wof:placetype":"venue"
},
  "geometry": {"coordinates":[-117.96399700000001,33.917301],"type":"Point"}
}