{
  "type": "Feature",
  "properties": {
    "addr:full":"942 Liberty Rd Petaluma CA 94952",
    "addr:housenumber":"942",
    "addr:postcode":"94952",
    "addr:street":"Liberty Rd",
    "iso:country":"US",
    "sg:address":"942 Liberty Rd",
    "sg:city":"Petaluma",
    "sg:classifiers":[
        {
            "category":"Farming",
            "subcategory":"Livestock Farm",
            "type":"Manufacturing & Wholesale Goods"
        }
    ],
    "sg:phone":"+1 707 762 3864",
    "sg:postcode":"94952",
    "sg:province":"CA",
    "sg:tags":[
        "specialty",
        "merchandise",
        "animal"
    ],
    "wof:name":"Paradise Great Danes",
    "wof:placetype":"venue"
},
  "geometry": {"coordinates":[-122.70095999999999,38.261524],"type":"Point"}
}