{
  "type": "Feature",
  "properties": {
    "iso:country":"US",
    "sg:address":"340 West St",
    "sg:city":"Tracy",
    "sg:classifiers":[
        {
            "category":"Manufacturing",
            "subcategory":"Metals",
            "type":"Manufacturing & Wholesale Goods"
        }
    ],
    "sg:phone":"+1 209 839 9270",
    "sg:postcode":"95376",
    "sg:province":"CA",
    "sg:tags":[
        "ornamental",
        "work"
    ],
    "wof:name":"Jesse's Welding Ornamental",
    "wof:placetype":"venue"
},
  "geometry": {"coordinates":[-121.43012400000001,37.731451],"type":"Point"}
}