{
  "type": "Feature",
  "properties": {
    "iso:country":"US",
    "sg:address":"2320 6th Ave",
    "sg:city":"San Diego",
    "sg:classifiers":[
        {
            "category":"Professional",
            "subcategory":"Business Services",
            "type":"Services"
        }
    ],
    "sg:phone":"+1 619 232 9499",
    "sg:postcode":"92101",
    "sg:province":"CA",
    "sg:tags":[
        "convention",
        "meeting",
        "facility"
    ],
    "sg:website":"www.pmmiconferences.com",
    "wof:name":"Preffered Meeting Management",
    "wof:placetype":"venue"
},
  "geometry": {"coordinates":[-117.15947199999999,32.730139],"type":"Point"}
}