{
  "type": "Feature",
  "properties": {
    "iso:country":"US",
    "sg:address":"2700 San Gabriel Blvd",
    "sg:city":"Rosemead",
    "sg:classifiers":[
        {
            "category":"Autos & Motor Vehicles",
            "subcategory":"Automobile Sales",
            "type":"Retail Goods"
        }
    ],
    "sg:phone":"+1 626 572 4004",
    "sg:postcode":"91770",
    "sg:province":"CA",
    "sg:tags":[
        "used",
        "car",
        "dealers-used",
        "new",
        "cars-wholesale"
    ],
    "sg:website":"www.easternautosales.com",
    "wof:name":"Eastern Auto Sales",
    "wof:placetype":"venue"
},
  "geometry": {"coordinates":[-118.090064,34.06078],"type":"Point"}
}