{
  "type": "Feature",
  "properties": {
    "addr:full":"5136 Dumont Pl Woodland Hills CA 91364",
    "addr:housenumber":"5136",
    "addr:postcode":"91364",
    "addr:street":"Dumont Pl",
    "iso:country":"US",
    "sg:address":"5136 Dumont Pl",
    "sg:city":"Woodland Hills",
    "sg:classifiers":[
        {
            "category":"Building & Trades",
            "subcategory":"Construction",
            "type":"Services"
        }
    ],
    "sg:phone":"+1 818 884 7592",
    "sg:postcode":"91364",
    "sg:province":"CA",
    "sg:tags":[
        "residential"
    ],
    "wof:name":"PLM Construction",
    "wof:placetype":"venue"
},
  "geometry": {"coordinates":[-118.58242799999999,34.162106],"type":"Point"}
}