{
  "type": "Feature",
  "properties": {
    "iso:country":"US",
    "sg:address":"1660 Hudson Ave",
    "sg:city":"San Francisco",
    "sg:classifiers":[
        {
            "category":"Wholesale",
            "subcategory":"Apparel",
            "type":"Manufacturing & Wholesale Goods"
        }
    ],
    "sg:phone":"+1 415 285 9228",
    "sg:postcode":"94124",
    "sg:province":"CA",
    "sg:tags":[
        "textile"
    ],
    "sg:website":"www.epochht.com",
    "wof:name":"Epoch Hometex Inc",
    "wof:placetype":"venue"
},
  "geometry": {"coordinates":[-122.38951,37.740743],"type":"Point"}
}