{
  "type": "Feature",
  "properties": {
    "addr:full":"4965 Canyon Dr Santa Rosa CA 95409",
    "addr:housenumber":"4965",
    "addr:postcode":"95409",
    "addr:street":"Canyon Dr",
    "iso:country":"US",
    "sg:address":"4965 Canyon Dr",
    "sg:city":"Santa Rosa",
    "sg:classifiers":[
        {
            "category":"Organizations",
            "subcategory":"Religious Organization",
            "type":"Services"
        }
    ],
    "sg:phone":"+1 707 545 1845",
    "sg:postcode":"95409",
    "sg:province":"CA",
    "sg:tags":[
        "church"
    ],
    "wof:name":"Giving Tree Assembly Of God",
    "wof:placetype":"venue"
},
  "geometry": {"coordinates":[-122.66491600000001,38.472528],"type":"Point"}
}