{
  "type": "Feature",
  "properties": {
    "addr:full":"2223 Union St San Francisco CA 94123",
    "addr:housenumber":"2223",
    "addr:postcode":"94123",
    "addr:street":"Union St",
    "iso:country":"US",
    "sg:address":"2223 Union St",
    "sg:city":"San Francisco",
    "sg:classifiers":[
        {
            "category":"Restaurant",
            "type":"Food & Drink"
        }
    ],
    "sg:phone":"+1 415 775 1130",
    "sg:postcode":"94123",
    "sg:province":"CA",
    "wof:name":"Night Monkey Restaurant",
    "wof:placetype":"venue"
},
  "geometry": {"coordinates":[-122.436834,37.796852],"type":"Point"}
}