{
  "type": "Feature",
  "properties": {
    "iso:country":"US",
    "sg:address":"1200 S Pacific Coast Hwy Ste E3",
    "sg:city":"Redondo Beach",
    "sg:classifiers":[
        {
            "category":"Sports & Exercise",
            "subcategory":"Gym",
            "type":"Entertainment"
        }
    ],
    "sg:phone":"+1 310 808 7201",
    "sg:postcode":"90277",
    "sg:province":"CA",
    "sg:tags":[
        "pilate"
    ],
    "sg:website":"bodyalchemistpilates.com",
    "wof:name":"The Body Alchemist LA",
    "wof:placetype":"venue"
},
  "geometry": {"coordinates":[-118.385207,33.824383],"type":"Point"}
}