{
  "type": "Feature",
  "properties": {
    "iso:country":"US",
    "sg:address":"1747 S Douglass Rd Ste B",
    "sg:city":"Anaheim",
    "sg:classifiers":[
        {
            "category":"Real Estate",
            "subcategory":"Architect",
            "type":"Services"
        }
    ],
    "sg:phone":"+1 714 938 0157",
    "sg:postcode":"92806",
    "sg:province":"CA",
    "wof:name":"Archeion Nevada",
    "wof:placetype":"venue"
},
  "geometry": {"coordinates":[-117.87799800000001,33.804901],"type":"Point"}
}