{
  "type": "Feature",
  "properties": {
    "iso:country":"US",
    "sg:address":"11833 Norwood Ave",
    "sg:city":"Riverside",
    "sg:classifiers":[
        {
            "category":"Transit Center",
            "subcategory":"Freight",
            "type":"Transportation"
        }
    ],
    "sg:phone":"+1 951 818 0488",
    "sg:postcode":"92505",
    "sg:province":"CA",
    "sg:tags":[
        "container"
    ],
    "wof:name":"Sea - West Enterprise",
    "wof:placetype":"venue"
},
  "geometry": {"coordinates":[-117.50626,33.918079],"type":"Point"}
}