{
  "type": "Feature",
  "properties": {
    "addr:full":"20475 Yellow Brick Rd Walnut CA 91789",
    "addr:housenumber":"20475",
    "addr:postcode":"91789",
    "addr:street":"Yellow Brick Rd",
    "iso:country":"US",
    "sg:address":"20475 Yellow Brick Rd",
    "sg:city":"Walnut",
    "sg:classifiers":[
        {
            "category":"Retail",
            "subcategory":"Auto Repair",
            "type":"Services"
        }
    ],
    "sg:phone":"+1 909 594 9040",
    "sg:postcode":"91789",
    "sg:province":"CA",
    "sg:tags":[
        "automobile",
        "customizing"
    ],
    "wof:name":"Dimension Lab",
    "wof:placetype":"venue"
},
  "geometry": {"coordinates":[-117.858846,33.999006],"type":"Point"}
}