{
  "type": "Feature",
  "properties": {
    "iso:country":"US",
    "sg:address":"516 W Shaw Ave",
    "sg:city":"Fresno",
    "sg:classifiers":[
        {
            "category":"Professional",
            "subcategory":"Accounting & Tax Preparation",
            "type":"Services"
        },
        {
            "category":"Professional",
            "subcategory":"Lawyer & Legal Services",
            "type":"Services"
        }
    ],
    "sg:phone":"+1 800 896 5536",
    "sg:postcode":"93704",
    "sg:province":"CA",
    "sg:tags":[
        "attorney",
        "return",
        "representative",
        "taxes-consultants"
    ],
    "sg:website":"http://www.jkharris.com/?ml_source=yellowpages",
    "wof:name":"JK Harris & Company",
    "wof:placetype":"venue"
},
  "geometry": {"coordinates":[-119.80156599999999,36.808545],"type":"Point"}
}