{
  "type": "Feature",
  "properties": {
    "iso:country":"US",
    "sg:address":"1111 6th Ave",
    "sg:city":"San Diego",
    "sg:classifiers":[
        {
            "category":"Professional",
            "subcategory":"Lawyer & Legal Services",
            "type":"Services"
        }
    ],
    "sg:phone":"+1 619 239 7877",
    "sg:postcode":"92101",
    "sg:province":"CA",
    "sg:tags":[
        "attorney"
    ],
    "wof:name":"Office Of Clients' Rights",
    "wof:placetype":"venue"
},
  "geometry": {"coordinates":[-117.159206,32.717705],"type":"Point"}
}