{
  "type": "Feature",
  "properties": {
    "iso:country":"US",
    "sg:address":"3883 Taylor Rd",
    "sg:city":"Loomis",
    "sg:classifiers":[
        {
            "category":"Restaurant",
            "type":"Food & Drink"
        }
    ],
    "sg:phone":"+1 916 652 6218",
    "sg:postcode":"95650",
    "sg:province":"CA",
    "wof:name":"Lorenzos Mexican Restaurant",
    "wof:placetype":"venue"
},
  "geometry": {"coordinates":[-121.201539,38.814652],"type":"Point"}
}