{
  "type": "Feature",
  "properties": {
    "addr:full":"201 Pine St San Francisco CA 94104",
    "addr:housenumber":"201",
    "addr:postcode":"94104",
    "addr:street":"Pine St",
    "iso:country":"US",
    "sg:address":"201 Pine St",
    "sg:city":"San Francisco",
    "sg:classifiers":[
        {
            "category":"Cafe",
            "type":"Food & Drink"
        }
    ],
    "sg:menulink":"http://www.allmenus.com/ca/san-francisco/46920-cafe-vivoli/menu/",
    "sg:phone":"+1 415 772 9922",
    "sg:postcode":"94104",
    "sg:province":"CA",
    "sg:tags":[
        "italian"
    ],
    "wof:name":"Cafe Vivoli",
    "wof:placetype":"venue"
},
  "geometry": {"coordinates":[-122.399922,37.79228],"type":"Point"}
}