{
  "type": "Feature",
  "properties": {
    "iso:country":"US",
    "sg:address":"300 S 1st Street",
    "sg:city":"San Jose",
    "sg:classifiers":[
        {
            "category":"Professional",
            "subcategory":"Lawyer & Legal Services",
            "type":"Services"
        }
    ],
    "sg:phone":"+1 408 293 9876",
    "sg:postcode":"95113",
    "sg:province":"CA",
    "wof:name":"Nachison Daniel Attorney At Law",
    "wof:placetype":"venue"
},
  "geometry": {"coordinates":[-121.887046,37.331535],"type":"Point"}
}