{
  "type": "Feature",
  "properties": {
    "addr:full":"6336 Lochinvar Way Sacramento CA 95823",
    "addr:housenumber":"6336",
    "addr:postcode":"95823",
    "addr:street":"Lochinvar Way",
    "iso:country":"US",
    "sg:address":"6336 Lochinvar Way",
    "sg:city":"Sacramento",
    "sg:classifiers":[
        {
            "category":"Home & Garden",
            "subcategory":"Building Materials",
            "type":"Retail Goods"
        }
    ],
    "sg:phone":"+1 916 747 1320",
    "sg:postcode":"95823",
    "sg:province":"CA",
    "sg:tags":[
        "garage",
        "opener",
        "door"
    ],
    "wof:name":"Abt Garage Doors & Openers",
    "wof:placetype":"venue"
},
  "geometry": {"coordinates":[-121.43078800000001,38.458247],"type":"Point"}
}