{
  "type": "Feature",
  "properties": {
    "iso:country":"US",
    "sg:address":"20 Ragsdale Dr",
    "sg:city":"Monterey",
    "sg:classifiers":[
        {
            "category":"Real Estate",
            "subcategory":"Developer",
            "type":"Services"
        }
    ],
    "sg:phone":"+1 831 333 1100",
    "sg:postcode":"93940",
    "sg:province":"CA",
    "wof:name":"Product Development Corp",
    "wof:placetype":"venue"
},
  "geometry": {"coordinates":[-121.820754,36.577886],"type":"Point"}
}