{
  "type": "Feature",
  "properties": {
    "addr:full":"4908 Salida Blvd Salida CA 95368",
    "addr:housenumber":"4908",
    "addr:postcode":"95368",
    "addr:street":"Salida Blvd",
    "iso:country":"US",
    "sg:address":"4908 Salida Blvd",
    "sg:city":"Salida",
    "sg:classifiers":[
        {
            "category":"Retail",
            "subcategory":"Auto Rental",
            "type":"Services"
        }
    ],
    "sg:phone":"+1 209 543 1744",
    "sg:postcode":"95368",
    "sg:province":"CA",
    "sg:tags":[
        "renting",
        "truck",
        "leasing"
    ],
    "wof:name":"U-Haul Co",
    "wof:placetype":"venue"
},
  "geometry": {"coordinates":[-121.083072,37.708168],"type":"Point"}
}