{
  "type": "Feature",
  "properties": {
    "iso:country":"US",
    "sg:address":"1848 Nelda Ct",
    "sg:city":"Yuba City",
    "sg:classifiers":[
        {
            "category":"Real Estate",
            "subcategory":"Real Estate Agent",
            "type":"Services"
        }
    ],
    "sg:phone":"+1 530 674 1885",
    "sg:postcode":"95993",
    "sg:province":"CA",
    "wof:name":"Residential Realty",
    "wof:placetype":"venue"
},
  "geometry": {"coordinates":[-121.649492,39.117008],"type":"Point"}
}