{
  "type": "Feature",
  "properties": {
    "addr:full":"300 S Buena Vista Ave Corona CA 92882",
    "addr:housenumber":"300",
    "addr:postcode":"92882",
    "addr:street":"S Buena Vista Ave",
    "iso:country":"US",
    "sg:address":"300 S Buena Vista Ave",
    "sg:city":"Corona",
    "sg:classifiers":[
        {
            "category":"Bus Station",
            "type":"Transportation"
        }
    ],
    "sg:phone":"+1 951 736 3234",
    "sg:postcode":"92882",
    "sg:province":"CA",
    "sg:tags":[
        "school",
        "maintenance"
    ],
    "wof:name":"Laidlaw Transit Inc",
    "wof:placetype":"venue"
},
  "geometry": {"coordinates":[-117.57757100000001,33.876633],"type":"Point"}
}