{
  "type": "Feature",
  "properties": {
    "iso:country":"US",
    "sg:address":"400 Mossdale Rd",
    "sg:city":"Lathrop",
    "sg:classifiers":[
        {
            "category":"Autos & Motor Vehicles",
            "subcategory":"Boat Sales",
            "type":"Retail Goods"
        }
    ],
    "sg:phone":"+1 209 983 9718",
    "sg:postcode":"95330",
    "sg:province":"CA",
    "sg:tags":[
        "dealer",
        "sales"
    ],
    "wof:name":"Mossdale Boat Sales",
    "wof:placetype":"venue"
},
  "geometry": {"coordinates":[-121.311279,37.78042],"type":"Point"}
}