{
  "type": "Feature",
  "properties": {
    "iso:country":"US",
    "sg:address":"2921 Roosevelt St",
    "sg:city":"Carlsbad",
    "sg:classifiers":[
        {
            "category":"Insurance",
            "subcategory":"Insurance Agent",
            "type":"Services"
        }
    ],
    "sg:phone":"+1 760 730 1800",
    "sg:postcode":"92008",
    "sg:province":"CA",
    "wof:name":"Mc Kinzie Insurance",
    "wof:placetype":"venue"
},
  "geometry": {"coordinates":[-117.347916,33.160351],"type":"Point"}
}