{
  "type": "Feature",
  "properties": {
    "iso:country":"US",
    "sg:address":"6135 N Mitre Ave",
    "sg:city":"Fresno",
    "sg:classifiers":[
        {
            "category":"Building & Trades",
            "subcategory":"Landscaping Services",
            "type":"Services"
        }
    ],
    "sg:phone":"+1 559 271 1712",
    "sg:postcode":"93722",
    "sg:province":"CA",
    "sg:tags":[
        "tree"
    ],
    "wof:name":"Barbella's Tree Svc",
    "wof:placetype":"venue"
},
  "geometry": {"coordinates":[-119.87361900000001,36.824921],"type":"Point"}
}