{
  "type": "Feature",
  "properties": {
    "addr:full":"421 Colyton St Los Angeles CA 90013",
    "addr:housenumber":"421",
    "addr:postcode":"90013",
    "addr:street":"Colyton St",
    "iso:country":"US",
    "sg:address":"421 Colyton St",
    "sg:city":"Los Angeles",
    "sg:classifiers":[
        {
            "category":"Wholesale",
            "subcategory":"Toys & Hobbies",
            "type":"Manufacturing & Wholesale Goods"
        }
    ],
    "sg:phone":"+1 213 617 7088",
    "sg:postcode":"90013",
    "sg:province":"CA",
    "wof:name":"LLT Warehouse",
    "wof:placetype":"venue"
},
  "geometry": {"coordinates":[-118.236333,34.042017],"type":"Point"}
}