{
  "type": "Feature",
  "properties": {
    "addr:full":"40291 Junction Dr 102 Oakhurst CA 93644",
    "addr:housenumber":"102",
    "addr:postcode":"40291;93644",
    "addr:street":"Junction Dr",
    "iso:country":"US",
    "sg:address":"40291 Junction Dr 102",
    "sg:city":"Oakhurst",
    "sg:classifiers":[
        {
            "category":"Insurance",
            "subcategory":"Hazard Insurance",
            "type":"Services"
        },
        {
            "category":"Insurance",
            "subcategory":"Insurance Agent",
            "type":"Services"
        },
        {
            "category":"Insurance",
            "subcategory":"Life Insurance",
            "type":"Services"
        },
        {
            "category":"Insurance",
            "subcategory":"Title Insurance",
            "type":"Services"
        }
    ],
    "sg:phone":"+1 559 683 4260",
    "sg:postcode":"93644",
    "sg:province":"CA",
    "sg:tags":[
        "auto",
        "commercial",
        "business",
        "homeowner"
    ],
    "sg:website":"http://www.farmersagent.com/rregert/",
    "wof:name":"Richard Regert - Farmers Insurance",
    "wof:placetype":"venue"
},
  "geometry": {"coordinates":[-119.658742,37.333089],"type":"Point"}
}