{
  "type": "Feature",
  "properties": {
    "addr:full":"419 E McGlincy Ln Campbell CA 95008",
    "addr:housenumber":"419",
    "addr:postcode":"95008",
    "addr:street":"E Mcglincy Ln",
    "iso:country":"US",
    "sg:address":"419 E McGlincy Ln",
    "sg:city":"Campbell",
    "sg:classifiers":[
        {
            "category":"Retail",
            "subcategory":"Auto Repair",
            "type":"Services"
        }
    ],
    "sg:phone":"+1 408 371 7679",
    "sg:postcode":"95008",
    "sg:province":"CA",
    "sg:website":"www.delongsautomotiverepair.com/",
    "wof:name":"De Long's Automotive",
    "wof:placetype":"venue"
},
  "geometry": {"coordinates":[-121.94255800000001,37.276832],"type":"Point"}
}