{
  "type": "Feature",
  "properties": {
    "addr:full":"1773 E Main St El Cajon CA 92021",
    "addr:housenumber":"1773",
    "addr:postcode":"92021",
    "addr:street":"E Main St",
    "iso:country":"US",
    "sg:address":"1773 E Main St",
    "sg:city":"El Cajon",
    "sg:classifiers":[
        {
            "category":"Restaurant",
            "type":"Food & Drink"
        }
    ],
    "sg:phone":"+1 619 442 0231",
    "sg:postcode":"92021",
    "sg:province":"CA",
    "sg:tags":[
        "pizza"
    ],
    "wof:name":"Mamma Rosa's Restaurant",
    "wof:placetype":"venue"
},
  "geometry": {"coordinates":[-116.91753799999999,32.813436],"type":"Point"}
}