{
  "type": "Feature",
  "properties": {
    "iso:country":"US",
    "sg:address":"15195 Arnold Dr",
    "sg:city":"Glen Ellen",
    "sg:classifiers":[
        {
            "category":"Retail",
            "subcategory":"Auto Repair",
            "type":"Services"
        }
    ],
    "sg:phone":"+1 707 996 1354",
    "sg:postcode":"95442",
    "sg:province":"CA",
    "sg:tags":[
        "repairing",
        "automobile"
    ],
    "wof:name":"Sonoma Volkswagen & Import Rpr",
    "wof:placetype":"venue"
},
  "geometry": {"coordinates":[-122.514189,38.344044],"type":"Point"}
}