{
  "type": "Feature",
  "properties": {
    "addr:full":"170 E Tahquitz Canyon Way Palm Springs CA 92262",
    "addr:housenumber":"170",
    "addr:postcode":"92262",
    "addr:street":"E Tahquitz Canyon Way",
    "iso:country":"US",
    "sg:address":"170 E Tahquitz Canyon Way",
    "sg:city":"Palm Springs",
    "sg:classifiers":[
        {
            "category":"Arts & Performance",
            "subcategory":"Art Gallery",
            "type":"Entertainment"
        }
    ],
    "sg:phone":"+1 760 808 4824",
    "sg:postcode":"92262",
    "sg:province":"CA",
    "sg:website":"www.mhalegallery.com",
    "wof:name":"M Hale Gallery",
    "wof:placetype":"venue"
},
  "geometry": {"coordinates":[-116.545918,33.823139],"type":"Point"}
}