{
  "type": "Feature",
  "properties": {
    "iso:country":"US",
    "sg:address":"9265 Glenoaks Blvd",
    "sg:city":"Sun Valley",
    "sg:classifiers":[
        {
            "category":"Real Estate",
            "subcategory":"Real Estate Agent",
            "type":"Services"
        }
    ],
    "sg:phone":"+1 818 768 2500",
    "sg:postcode":"91352",
    "sg:province":"CA",
    "wof:name":"American Diversified Properts",
    "wof:placetype":"venue"
},
  "geometry": {"coordinates":[-118.373694,34.236475],"type":"Point"}
}