{
  "type": "Feature",
  "properties": {
    "iso:country":"US",
    "sg:address":"2053 E 38th St",
    "sg:city":"Los Angeles",
    "sg:classifiers":[
        {
            "category":"Wholesale",
            "subcategory":"Metals & Minerals",
            "type":"Manufacturing & Wholesale Goods"
        }
    ],
    "sg:phone":"+1 323 234 2626",
    "sg:postcode":"90058",
    "sg:province":"CA",
    "sg:tags":[
        "die",
        "casting"
    ],
    "wof:name":"Commercial Die Casting Co",
    "wof:placetype":"venue"
},
  "geometry": {"coordinates":[-118.23812599999999,34.008115],"type":"Point"}
}