{
  "type": "Feature",
  "properties": {
    "iso:country":"US",
    "sg:address":"10940 Wilshire Blvd",
    "sg:city":"Los Angeles",
    "sg:classifiers":[
        {
            "category":"Professional",
            "subcategory":"Lawyer & Legal Services",
            "type":"Services"
        }
    ],
    "sg:phone":"+1 310 441 4277",
    "sg:postcode":"90024",
    "sg:province":"CA",
    "sg:tags":[
        "attorney"
    ],
    "wof:name":"Parham Zar Law Offices",
    "wof:placetype":"venue"
},
  "geometry": {"coordinates":[-118.44441399999999,34.058615],"type":"Point"}
}