{
  "type": "Feature",
  "properties": {
    "iso:country":"US",
    "sg:address":"Fashion Island 271 Newport Center Dr",
    "sg:city":"Newport Beach",
    "sg:classifiers":[
        {
            "category":"Shopping",
            "subcategory":"Clothing, Apparel, & Fashions",
            "type":"Retail Goods"
        },
        {
            "category":"Retail",
            "subcategory":"Self-service Laundry",
            "type":"Services"
        }
    ],
    "sg:phone":"+1 949 706 2002",
    "sg:postcode":"92660",
    "sg:province":"CA",
    "sg:tags":[
        "clothing",
        "swimwear",
        "women's"
    ],
    "sg:website":"www.maliamills.com/",
    "wof:name":"Malia Mills",
    "wof:placetype":"venue"
},
  "geometry": {"coordinates":[-117.87473900000001,33.615933],"type":"Point"}
}