{
  "type": "Feature",
  "properties": {
    "addr:full":"272 W Kenneth Rd Glendale CA 91202",
    "addr:housenumber":"272",
    "addr:postcode":"91202",
    "addr:street":"W Kenneth Rd",
    "iso:country":"US",
    "sg:address":"272 W Kenneth Rd",
    "sg:city":"Glendale",
    "sg:classifiers":[
        {
            "category":"Professional",
            "subcategory":"Detective & Security Services",
            "type":"Services"
        }
    ],
    "sg:phone":"+1 818 243 6192",
    "sg:postcode":"91202",
    "sg:province":"CA",
    "sg:tags":[
        "equipment",
        "electrical",
        "system"
    ],
    "wof:name":"Greater California Alarms",
    "wof:placetype":"venue"
},
  "geometry": {"coordinates":[-118.26089,34.168901],"type":"Point"}
}