{
  "type": "Feature",
  "properties": {
    "addr:full":"134 W Dana St Mountain View CA 94041",
    "addr:housenumber":"134",
    "addr:postcode":"94041",
    "addr:street":"W Dana St",
    "iso:country":"US",
    "sg:address":"134 W Dana St",
    "sg:city":"Mountain View",
    "sg:classifiers":[
        {
            "category":"Real Estate",
            "subcategory":"Real Estate Operator",
            "type":"Services"
        }
    ],
    "sg:phone":"+1 650 968 5695",
    "sg:postcode":"94041",
    "sg:province":"CA",
    "sg:tags":[
        "apartment"
    ],
    "wof:name":"Sunshine Garden Apartments",
    "wof:placetype":"venue"
},
  "geometry": {"coordinates":[-122.070447,37.388866],"type":"Point"}
}