{
  "type": "Feature",
  "properties": {
    "iso:country":"US",
    "sg:address":"4666 N Blythe Ave",
    "sg:city":"Fresno",
    "sg:classifiers":[
        {
            "category":"Government",
            "subcategory":"Post Office",
            "type":"Public Place"
        }
    ],
    "sg:phone":"+1 559 000 1111",
    "sg:postcode":"93722",
    "sg:province":"CA",
    "wof:name":"US Post Office",
    "wof:placetype":"venue"
},
  "geometry": {"coordinates":[-119.872549,36.805646],"type":"Point"}
}