{
  "type": "Feature",
  "properties": {
    "iso:country":"US",
    "sg:address":"400 Date Ave",
    "sg:city":"Alhambra",
    "sg:classifiers":[
        {
            "category":"Wholesale",
            "subcategory":"Groceries",
            "type":"Manufacturing & Wholesale Goods"
        }
    ],
    "sg:phone":"+1 626 308 3212",
    "sg:postcode":"91803",
    "sg:province":"CA",
    "sg:tags":[
        "canned",
        "cookie",
        "dried",
        "candy"
    ],
    "sg:website":"www.richintrading.com",
    "wof:name":"Richin Trading Inc",
    "wof:placetype":"venue"
},
  "geometry": {"coordinates":[-118.148123,34.084075],"type":"Point"}
}