{
  "type": "Feature",
  "properties": {
    "iso:country":"US",
    "sg:address":"444 Airport Blvd",
    "sg:city":"Watsonville",
    "sg:classifiers":[
        {
            "category":"Utilities",
            "subcategory":"Mobile Phone",
            "type":"Services"
        }
    ],
    "sg:phone":"+1 831 768 8586",
    "sg:postcode":"95076",
    "sg:province":"CA",
    "sg:tags":[
        "communication",
        "telephone",
        "cellular",
        "radiotelephone"
    ],
    "sg:website":"www.aquanovapoolnspa.com",
    "wof:name":"Cal Wireless",
    "wof:placetype":"venue"
},
  "geometry": {"coordinates":[-121.78631,36.932858],"type":"Point"}
}