{
  "type": "Feature",
  "properties": {
    "iso:country":"US",
    "sg:address":"2925 S Golden State Blvd",
    "sg:city":"Turlock",
    "sg:classifiers":[
        {
            "category":"Professional",
            "subcategory":"Business Services",
            "type":"Services"
        }
    ],
    "sg:phone":"+1 209 632 7463",
    "sg:postcode":"95380",
    "sg:province":"CA",
    "sg:tags":[
        "auctioneer"
    ],
    "wof:name":"Cow Town Horse & Livestock",
    "wof:placetype":"venue"
},
  "geometry": {"coordinates":[-120.817459,37.467435],"type":"Point"}
}