{
  "type": "Feature",
  "properties": {
    "iso:country":"US",
    "sg:address":"14685 Valley Vista Blvd",
    "sg:city":"Sherman Oaks",
    "sg:classifiers":[
        {
            "category":"Building & Trades",
            "subcategory":"Landscaping Services",
            "type":"Services"
        }
    ],
    "sg:phone":"+1 818 995 7644",
    "sg:postcode":"91403",
    "sg:province":"CA",
    "wof:name":"Terra Design",
    "wof:placetype":"venue"
},
  "geometry": {"coordinates":[-118.454245,34.145738],"type":"Point"}
}