{
  "type": "Feature",
  "properties": {
    "addr:full":"3960 Wishire Blvd Ste 408 Los Angeles CA 90010",
    "addr:postcode":"3960;90010",
    "addr:street":"Wishire Blvd Ste 408",
    "iso:country":"US",
    "sg:address":"3960 Wishire Blvd Ste 408",
    "sg:city":"Los Angeles",
    "sg:classifiers":[
        {
            "category":"Health Services",
            "subcategory":"Health Practitioner",
            "type":"Services"
        }
    ],
    "sg:phone":"+1 213 384 5804",
    "sg:postcode":"90010",
    "sg:province":"CA",
    "sg:tags":[
        "acupuncture"
    ],
    "wof:name":"Inae Acupuncture Clinic",
    "wof:placetype":"venue"
},
  "geometry": {"coordinates":[-118.313199,34.061647],"type":"Point"}
}