{
  "type": "Feature",
  "properties": {
    "addr:full":"5395 E Hunter Ave Anaheim CA 92807",
    "addr:housenumber":"5395 e",
    "addr:postcode":"92807",
    "addr:street":"Hunter Ave",
    "iso:country":"US",
    "sg:address":"5395 E Hunter Ave",
    "sg:city":"Anaheim",
    "sg:classifiers":[
        {
            "category":"Manufacturing",
            "subcategory":"Electronics",
            "type":"Manufacturing & Wholesale Goods"
        },
        {
            "category":"Manufacturing",
            "subcategory":"Tools & Machinery",
            "type":"Manufacturing & Wholesale Goods"
        }
    ],
    "sg:phone":"+1 714 696 5200",
    "sg:postcode":"92807",
    "sg:province":"CA",
    "sg:tags":[
        "connector",
        "industry",
        "electrical",
        "aerospace",
        "mfg"
    ],
    "wof:name":"Cristek Interconnects Inc",
    "wof:placetype":"venue"
},
  "geometry": {"coordinates":[-117.799755,33.862657],"type":"Point"}
}