{
  "type": "Feature",
  "properties": {
    "addr:full":"3740 Atlantic Ave Ste 202 Long Beach CA 90807",
    "addr:housenumber":"3740",
    "addr:postcode":"90807",
    "addr:street":"Atlantic Ave Ste 202",
    "iso:country":"US",
    "sg:address":"3740 Atlantic Ave Ste 202",
    "sg:city":"Long Beach",
    "sg:classifiers":[
        {
            "category":"Health Services",
            "subcategory":"Clinic",
            "type":"Services"
        }
    ],
    "sg:phone":"+1 562 761 9775",
    "sg:postcode":"90807",
    "sg:province":"CA",
    "sg:tags":[
        "counseling",
        "mental"
    ],
    "wof:name":"Unfinished Business",
    "wof:placetype":"venue"
},
  "geometry": {"coordinates":[-118.184595,33.825735],"type":"Point"}
}