{
  "type": "Feature",
  "properties": {
    "iso:country":"US",
    "sg:address":"11335 Louise Ave",
    "sg:city":"Granada Hills",
    "sg:classifiers":[
        {
            "category":"Building & Trades",
            "subcategory":"Construction",
            "type":"Services"
        }
    ],
    "sg:phone":"+1 818 363 1455",
    "sg:postcode":"91344",
    "sg:province":"CA",
    "sg:tags":[
        "concrete",
        "contractor"
    ],
    "wof:name":"TBCI Concrete Structures",
    "wof:placetype":"venue"
},
  "geometry": {"coordinates":[-118.510972,34.276761],"type":"Point"}
}