{
  "type": "Feature",
  "properties": {
    "addr:full":"116 S Arrowhead Ave San Bernardino CA 92408",
    "addr:housenumber":"116",
    "addr:postcode":"92408",
    "addr:street":"S Arrowhead Ave",
    "iso:country":"US",
    "sg:address":"116 S Arrowhead Ave",
    "sg:city":"San Bernardino",
    "sg:classifiers":[
        {
            "category":"Professional",
            "subcategory":"Detective & Security Services",
            "type":"Services"
        }
    ],
    "sg:phone":"+1 909 381 6638",
    "sg:postcode":"92408",
    "sg:province":"CA",
    "sg:tags":[
        "investigator"
    ],
    "wof:name":"Wright Investigations",
    "wof:placetype":"venue"
},
  "geometry": {"coordinates":[-117.28974599999999,34.100222],"type":"Point"}
}