{
  "type": "Feature",
  "properties": {
    "iso:country":"US",
    "sg:address":"1324 Flower St",
    "sg:city":"Bakersfield",
    "sg:classifiers":[
        {
            "category":"Food & Beverages",
            "subcategory":"Groceries & Convenience Stores",
            "type":"Retail Goods"
        }
    ],
    "sg:phone":"+1 661 323 8540",
    "sg:postcode":"93305",
    "sg:province":"CA",
    "sg:tags":[
        "grocer"
    ],
    "wof:name":"Leo's Market",
    "wof:placetype":"venue"
},
  "geometry": {"coordinates":[-118.979013,35.383811],"type":"Point"}
}