{
  "type": "Feature",
  "properties": {
    "addr:full":"10641 Mulberry Ave Fontana CA 92337",
    "addr:housenumber":"10641",
    "addr:postcode":"92337",
    "addr:street":"Mulberry Ave",
    "iso:country":"US",
    "sg:address":"10641 Mulberry Ave",
    "sg:city":"Fontana",
    "sg:classifiers":[
        {
            "category":"Freight",
            "type":"Transportation"
        }
    ],
    "sg:phone":"+1 909 355 4515",
    "sg:postcode":"92337",
    "sg:province":"CA",
    "sg:tags":[
        "operator",
        "local",
        "trucking"
    ],
    "wof:name":"Arrow Trucking Co",
    "wof:placetype":"venue"
},
  "geometry": {"coordinates":[-117.506654,34.058115],"type":"Point"}
}