{
  "type": "Feature",
  "properties": {
    "iso:country":"US",
    "sg:address":"1130 E Main St",
    "sg:city":"El Cajon",
    "sg:classifiers":[
        {
            "category":"Shopping",
            "subcategory":"Used Merchandise",
            "type":"Retail Goods"
        }
    ],
    "sg:phone":"+1 619 442 0238",
    "sg:postcode":"92021",
    "sg:province":"CA",
    "sg:tags":[
        "shop",
        "thrift"
    ],
    "wof:name":"Amvets Thrift Store",
    "wof:placetype":"venue"
},
  "geometry": {"coordinates":[-116.943777,32.794991],"type":"Point"}
}