{
  "type": "Feature",
  "properties": {
    "addr:full":"2100 E 7th St Oakland CA 94607",
    "addr:housenumber":"2100",
    "addr:postcode":"94607",
    "addr:street":"E 7Th St",
    "iso:country":"US",
    "sg:address":"2100 E 7th St",
    "sg:city":"Oakland",
    "sg:classifiers":[
        {
            "category":"Government",
            "subcategory":"City Hall",
            "type":"Public Place"
        }
    ],
    "sg:postcode":"94607",
    "sg:province":"CA",
    "sg:website":"stopwaste.org/home/index.asp?pag...",
    "wof:name":"Alameda County Household Hazardous Waste Facility",
    "wof:placetype":"venue"
},
  "geometry": {"coordinates":[-122.240652,37.775891],"type":"Point"}
}