{
  "type": "Feature",
  "properties": {
    "iso:country":"US",
    "sg:address":"21032 Main St",
    "sg:city":"Carson",
    "sg:classifiers":[
        {
            "category":"Building & Trades",
            "subcategory":"Plumbing",
            "type":"Services"
        }
    ],
    "sg:phone":"+1 310 513 6979",
    "sg:postcode":"90745",
    "sg:province":"CA",
    "sg:tags":[
        "plumbing",
        "contractor"
    ],
    "wof:name":"Lagmay Junior Plumbing",
    "wof:placetype":"venue"
},
  "geometry": {"coordinates":[-118.275346,33.817759],"type":"Point"}
}