{
  "type": "Feature",
  "properties": {
    "addr:full":"1133 N Brentwood Ave Rialto CA 92376",
    "addr:housenumber":"1133",
    "addr:postcode":"92376",
    "addr:street":"N Brentwood Ave",
    "iso:country":"US",
    "sg:address":"1133 N Brentwood Ave",
    "sg:city":"Rialto",
    "sg:classifiers":[
        {
            "category":"Building & Trades",
            "subcategory":"Landscaping Services",
            "type":"Services"
        }
    ],
    "sg:phone":"+1 909 421 4457",
    "sg:postcode":"92376",
    "sg:province":"CA",
    "wof:name":"Ah Landscape Maintenance",
    "wof:placetype":"venue"
},
  "geometry": {"coordinates":[-117.39576599999999,34.119974],"type":"Point"}
}