{
  "type": "Feature",
  "properties": {
    "iso:country":"US",
    "sg:address":"1456 W Ashlan Ave",
    "sg:city":"Fresno",
    "sg:classifiers":[
        {
            "category":"Restaurant",
            "type":"Food & Drink"
        }
    ],
    "sg:phone":"+1 559 230 1142",
    "sg:postcode":"93705",
    "sg:province":"CA",
    "wof:name":"Nubian Hut",
    "wof:placetype":"venue"
},
  "geometry": {"coordinates":[-119.827928,36.793886],"type":"Point"}
}