{
  "type": "Feature",
  "properties": {
    "addr:full":"2445 Morena Boulevard San Diego CA 92110",
    "addr:housenumber":"2445",
    "addr:postcode":"92110",
    "addr:street":"Morena Boulevard",
    "iso:country":"US",
    "sg:address":"2445 Morena Boulevard",
    "sg:city":"San Diego",
    "sg:classifiers":[
        {
            "category":"Banks & Credit Unions",
            "subcategory":"Financial Services",
            "type":"Services"
        }
    ],
    "sg:phone":"+1 619 275 8390",
    "sg:postcode":"92110",
    "sg:province":"CA",
    "sg:tags":[
        "broker",
        "mortgage"
    ],
    "sg:website":"www.jensenmortgage.com",
    "wof:name":"Jensen Mortgage",
    "wof:placetype":"venue"
},
  "geometry": {"coordinates":[-117.20601600000001,32.787737],"type":"Point"}
}