{
  "type": "Feature",
  "properties": {
    "addr:full":"880 W 1st St Apt 108 Los Angeles CA 90012",
    "addr:housenumber":"880;108",
    "addr:postcode":"90012",
    "addr:street":"W 1St St Apt",
    "iso:country":"US",
    "sg:address":"880 W 1st St Apt 108",
    "sg:city":"Los Angeles",
    "sg:classifiers":[
        {
            "category":"Professional",
            "subcategory":"Lawyer & Legal Services",
            "type":"Services"
        }
    ],
    "sg:phone":"+1 213 625 1679",
    "sg:postcode":"90012",
    "sg:province":"CA",
    "wof:name":"Anyia Alfred Law Office of",
    "wof:placetype":"venue"
},
  "geometry": {"coordinates":[-118.241997,34.061501],"type":"Point"}
}