{
  "type": "Feature",
  "properties": {
    "iso:country":"US",
    "sg:address":"2211 Rockefeller Dr",
    "sg:city":"Ceres",
    "sg:classifiers":[
        {
            "category":"Retail",
            "subcategory":"Auto Repair",
            "type":"Services"
        }
    ],
    "sg:phone":"+1 209 537 5081",
    "sg:postcode":"95307",
    "sg:province":"CA",
    "sg:tags":[
        "body",
        "automobile",
        "painting"
    ],
    "wof:name":"A 1 Auto Repairs",
    "wof:placetype":"venue"
},
  "geometry": {"coordinates":[-120.970992,37.601058],"type":"Point"}
}