{
  "type": "Feature",
  "properties": {
    "addr:full":"6044 34th Ave Sacramento CA 95824",
    "addr:housenumber":"6044",
    "addr:postcode":"95824",
    "addr:street":"34Th Ave",
    "iso:country":"US",
    "sg:address":"6044 34th Ave",
    "sg:city":"Sacramento",
    "sg:classifiers":[
        {
            "category":"Building & Trades",
            "subcategory":"Construction",
            "type":"Services"
        }
    ],
    "sg:phone":"+1 916 451 2757",
    "sg:postcode":"95824",
    "sg:province":"CA",
    "sg:tags":[
        "contractor"
    ],
    "wof:name":"Harrison George & Tamara",
    "wof:placetype":"venue"
},
  "geometry": {"coordinates":[-121.434552,38.523482],"type":"Point"}
}