{
  "type": "Feature",
  "properties": {
    "iso:country":"US",
    "sg:address":"2221 Edwards Ave",
    "sg:city":"South El Monte",
    "sg:classifiers":[
        {
            "category":"Wholesale",
            "subcategory":"Home Furnishings",
            "type":"Manufacturing & Wholesale Goods"
        }
    ],
    "sg:phone":"+1 626 443 7689",
    "sg:postcode":"91733",
    "sg:province":"CA",
    "sg:tags":[
        "kitchenware"
    ],
    "wof:name":"Ambaware Products Inc",
    "wof:placetype":"venue"
},
  "geometry": {"coordinates":[-118.04918000000001,34.053462],"type":"Point"}
}