{
  "type": "Feature",
  "properties": {
    "iso:country":"US",
    "sg:address":"856 Echo Valley Rd",
    "sg:city":"Salinas",
    "sg:classifiers":[
        {
            "category":"Building & Trades",
            "subcategory":"Electrical",
            "type":"Services"
        }
    ],
    "sg:phone":"+1 831 578 4827",
    "sg:postcode":"93907",
    "sg:province":"CA",
    "sg:tags":[
        "electric",
        "contractor"
    ],
    "wof:name":"A & A Electric",
    "wof:placetype":"venue"
},
  "geometry": {"coordinates":[-121.63131,36.8219],"type":"Point"}
}