{
  "type": "Feature",
  "properties": {
    "addr:full":"673 Sebastopol Rd Santa Rosa CA 95407",
    "addr:housenumber":"673",
    "addr:postcode":"95407",
    "addr:street":"Sebastopol Rd",
    "iso:country":"US",
    "sg:address":"673 Sebastopol Rd",
    "sg:city":"Santa Rosa",
    "sg:classifiers":[
        {
            "category":"Wholesale",
            "subcategory":"Construction Materials",
            "type":"Manufacturing & Wholesale Goods"
        }
    ],
    "sg:phone":"+1 707 542 0191",
    "sg:postcode":"95407",
    "sg:province":"CA",
    "sg:tags":[
        "glass"
    ],
    "wof:name":"ACI Distribution",
    "wof:placetype":"venue"
},
  "geometry": {"coordinates":[-122.72927300000001,38.429789],"type":"Point"}
}