{
  "type": "Feature",
  "properties": {
    "iso:country":"US",
    "sg:address":"300 Hospital Dr",
    "sg:city":"Vallejo",
    "sg:classifiers":[
        {
            "category":"Health Services",
            "subcategory":"Doctor",
            "type":"Services"
        }
    ],
    "sg:phone":"+1 707 554 5331",
    "sg:postcode":"94589",
    "sg:province":"CA",
    "sg:tags":[
        "physician",
        "surgeon"
    ],
    "wof:name":"James R Krasno MD",
    "wof:placetype":"venue"
},
  "geometry": {"coordinates":[-122.240009,38.131115],"type":"Point"}
}