{
  "type": "Feature",
  "properties": {
    "addr:full":"83149 Stone Canyon Ave Indio CA 92201",
    "addr:housenumber":"83149",
    "addr:postcode":"92201",
    "addr:street":"Stone Canyon Ave",
    "iso:country":"US",
    "sg:address":"83149 Stone Canyon Ave",
    "sg:city":"Indio",
    "sg:classifiers":[
        {
            "category":"Real Estate",
            "subcategory":"Real Estate Services",
            "type":"Services"
        },
        {
            "category":"Banks & Credit Unions",
            "subcategory":"Financial Services",
            "type":"Services"
        }
    ],
    "sg:phone":"+1 760 342 0600",
    "sg:postcode":"92201",
    "sg:province":"CA",
    "sg:tags":[
        "loan"
    ],
    "wof:name":"Downtown Financial Services",
    "wof:placetype":"venue"
},
  "geometry": {"coordinates":[-116.213774,33.709911],"type":"Point"}
}