{
  "type": "Feature",
  "properties": {
    "addr:full":"3200 Telegraph Rd Ventura CA 93003",
    "addr:housenumber":"3200",
    "addr:postcode":"93003",
    "addr:street":"Telegraph Rd",
    "iso:country":"US",
    "sg:address":"3200 Telegraph Rd",
    "sg:city":"Ventura",
    "sg:classifiers":[
        {
            "category":"Banks & Credit Unions",
            "subcategory":"Bank",
            "type":"Services"
        }
    ],
    "sg:phone":"+1 805 644 2199",
    "sg:postcode":"93003",
    "sg:province":"CA",
    "sg:tags":[
        "loan",
        "mortgage",
        "real estate"
    ],
    "wof:name":"United Pacific Mortgage Co Inc",
    "wof:placetype":"venue"
},
  "geometry": {"coordinates":[-119.25258700000001,34.272281],"type":"Point"}
}