{
  "type": "Feature",
  "properties": {
    "iso:country":"US",
    "sg:address":"3557 Lancer Way",
    "sg:city":"Carlsbad",
    "sg:classifiers":[
        {
            "category":"Arts & Performance",
            "subcategory":"Arts Center",
            "type":"Entertainment"
        }
    ],
    "sg:phone":"+1 760 434 1621",
    "sg:postcode":"92008",
    "sg:province":"CA",
    "sg:tags":[
        "performing"
    ],
    "wof:name":"Carlsbad Community Cultural Arts Center",
    "wof:placetype":"venue"
},
  "geometry": {"coordinates":[-117.32691199999999,33.162368],"type":"Point"}
}