{
  "type": "Feature",
  "properties": {
    "iso:country":"US",
    "sg:address":"4003 Bridge St",
    "sg:city":"Fair Oaks",
    "sg:classifiers":[
        {
            "category":"Shopping",
            "subcategory":"Pharmacy",
            "type":"Retail Goods"
        }
    ],
    "sg:phone":"+1 916 962 1099",
    "sg:postcode":"95628",
    "sg:province":"CA",
    "wof:name":"Raphael Pharmacy",
    "wof:placetype":"venue"
},
  "geometry": {"coordinates":[-121.266581,38.637677],"type":"Point"}
}