{
  "type": "Feature",
  "properties": {
    "addr:full":"23725 Chrisman Rd Tracy CA 95304",
    "addr:housenumber":"23725",
    "addr:postcode":"95304",
    "addr:street":"Chrisman Rd",
    "iso:country":"US",
    "sg:address":"23725 Chrisman Rd",
    "sg:city":"Tracy",
    "sg:classifiers":[
        {
            "category":"Home & Garden",
            "subcategory":"Furniture",
            "type":"Retail Goods"
        }
    ],
    "sg:phone":"+1 209 835 7555",
    "sg:postcode":"95304",
    "sg:province":"CA",
    "sg:tags":[
        "equipment",
        "kitchen",
        "cabinet"
    ],
    "wof:name":"Oliveri Cabinets Inc",
    "wof:placetype":"venue"
},
  "geometry": {"coordinates":[-121.39825500000001,37.743415],"type":"Point"}
}