{
  "type": "Feature",
  "properties": {
    "addr:full":"4300 Hacienda Dr Pleasanton CA 94588",
    "addr:housenumber":"4300",
    "addr:postcode":"94588",
    "addr:street":"Hacienda Dr",
    "iso:country":"US",
    "sg:address":"4300 Hacienda Dr",
    "sg:city":"Pleasanton",
    "sg:classifiers":[
        {
            "category":"Professional",
            "type":"Services"
        }
    ],
    "sg:phone":"+1 925 224 7747",
    "sg:postcode":"94588",
    "sg:province":"CA",
    "sg:tags":[
        "establishment"
    ],
    "wof:name":"Boehringer Mannheim Corp",
    "wof:placetype":"venue"
},
  "geometry": {"coordinates":[-121.89412299999999,37.695268],"type":"Point"}
}