{
  "type": "Feature",
  "properties": {
    "iso:country":"US",
    "sg:address":"909 W Compton Blvd",
    "sg:city":"Compton",
    "sg:classifiers":[
        {
            "category":"Organizations",
            "subcategory":"Membership Organization",
            "type":"Services"
        },
        {
            "category":"Shopping",
            "type":"Retail Goods"
        }
    ],
    "sg:phone":"+1 310 631 5541",
    "sg:postcode":"90220",
    "sg:province":"CA",
    "sg:tags":[
        "merchandise",
        "monument"
    ],
    "wof:name":"Calloway Monument Co",
    "wof:placetype":"venue"
},
  "geometry": {"coordinates":[-118.239975,33.895966],"type":"Point"}
}