{
  "type": "Feature",
  "properties": {
    "iso:country":"US",
    "sg:address":"1018 E Alameda St",
    "sg:city":"Manteca",
    "sg:classifiers":[
        {
            "category":"Professional",
            "subcategory":"Engineering",
            "type":"Services"
        }
    ],
    "sg:phone":"+1 209 823 0477",
    "sg:postcode":"95336",
    "sg:province":"CA",
    "sg:tags":[
        "general",
        "contractor"
    ],
    "wof:name":"Terraco Construction",
    "wof:placetype":"venue"
},
  "geometry": {"coordinates":[-121.203971,37.804379],"type":"Point"}
}