{
  "type": "Feature",
  "properties": {
    "addr:full":"5162 Gardena Ave San Diego CA 92110",
    "addr:housenumber":"5162",
    "addr:postcode":"92110",
    "addr:street":"Gardena Ave",
    "iso:country":"US",
    "sg:address":"5162 Gardena Ave",
    "sg:city":"San Diego",
    "sg:classifiers":[
        {
            "category":"Autos & Motor Vehicles",
            "subcategory":"Automobile Sales",
            "type":"Retail Goods"
        }
    ],
    "sg:phone":"+1 619 275 0088",
    "sg:postcode":"92110",
    "sg:province":"CA",
    "sg:tags":[
        "used"
    ],
    "wof:name":"Alvin H Weaver",
    "wof:placetype":"venue"
},
  "geometry": {"coordinates":[-117.194355,32.775723],"type":"Point"}
}