{
  "type": "Feature",
  "properties": {
    "addr:full":"1533 Greenbriar Way Los Banos CA 93635",
    "addr:housenumber":"1533",
    "addr:postcode":"93635",
    "addr:street":"Greenbriar Way",
    "iso:country":"US",
    "sg:address":"1533 Greenbriar Way",
    "sg:city":"Los Banos",
    "sg:classifiers":[
        {
            "category":"Restaurant",
            "type":"Food & Drink"
        }
    ],
    "sg:phone":"+1 209 826 7615",
    "sg:postcode":"93635",
    "sg:province":"CA",
    "sg:tags":[
        "caterer"
    ],
    "wof:name":"Yamaguchi Catering",
    "wof:placetype":"venue"
},
  "geometry": {"coordinates":[-120.83148,37.066154],"type":"Point"}
}