{
  "type": "Feature",
  "properties": {
    "iso:country":"US",
    "sg:address":"1400 W College Ave",
    "sg:city":"Visalia",
    "sg:classifiers":[
        {
            "category":"Retail",
            "subcategory":"Laundry & Dry Cleaning",
            "type":"Services"
        }
    ],
    "sg:phone":"+1 559 635 1997",
    "sg:postcode":"93277",
    "sg:province":"CA",
    "sg:tags":[
        "cleaners",
        "rug",
        "carpet"
    ],
    "wof:name":"Rugmasters Carpet & Upholstery",
    "wof:placetype":"venue"
},
  "geometry": {"coordinates":[-119.307903,36.323831],"type":"Point"}
}