{
  "type": "Feature",
  "properties": {
    "iso:country":"US",
    "sg:address":"4006 State Rte 140",
    "sg:city":"Catheys Valley",
    "sg:classifiers":[
        {
            "category":"Shopping",
            "subcategory":"Hobbies, Toys, & Games",
            "type":"Retail Goods"
        }
    ],
    "sg:phone":"+1 209 966 2127",
    "sg:postcode":"95306",
    "sg:province":"CA",
    "sg:tags":[
        "shop",
        "rock"
    ],
    "wof:name":"Yosemite Rocks & Gifts",
    "wof:placetype":"venue"
},
  "geometry": {"coordinates":[-120.02763,37.479966],"type":"Point"}
}