{
  "type": "Feature",
  "properties": {
    "iso:country":"US",
    "sg:address":"570 Orange Ave",
    "sg:city":"Perris",
    "sg:classifiers":[
        {
            "category":"Building & Trades",
            "subcategory":"Construction",
            "type":"Services"
        }
    ],
    "sg:phone":"+1 951 657 1641",
    "sg:postcode":"92571",
    "sg:province":"CA",
    "sg:tags":[
        "general",
        "contractor"
    ],
    "wof:name":"Basic Design",
    "wof:placetype":"venue"
},
  "geometry": {"coordinates":[-117.214129,33.81571],"type":"Point"}
}