{
  "type": "Feature",
  "properties": {
    "addr:full":"300 W Lodi Ave Lodi CA 95240",
    "addr:housenumber":"300",
    "addr:postcode":"95240",
    "addr:street":"W Lodi Ave",
    "iso:country":"US",
    "sg:address":"300 W Lodi Ave",
    "sg:city":"Lodi",
    "sg:classifiers":[
        {
            "category":"Health Services",
            "subcategory":"Doctor",
            "type":"Services"
        }
    ],
    "sg:phone":"+1 209 369 5811",
    "sg:postcode":"95240",
    "sg:province":"CA",
    "sg:tags":[
        "dentist"
    ],
    "wof:name":"Ronald A Forbes DDS",
    "wof:placetype":"venue"
},
  "geometry": {"coordinates":[-121.27726699999999,38.130052],"type":"Point"}
}