{
  "type": "Feature",
  "properties": {
    "addr:full":"8687 W Pico Blvd Los Angeles CA 90035",
    "addr:housenumber":"8687",
    "addr:postcode":"90035",
    "addr:street":"W Pico Blvd",
    "iso:country":"US",
    "sg:address":"8687 W Pico Blvd",
    "sg:city":"Los Angeles",
    "sg:classifiers":[
        {
            "category":"Retail",
            "subcategory":"Auto Repair",
            "type":"Services"
        }
    ],
    "sg:phone":"+1 310 271 5523",
    "sg:postcode":"90035",
    "sg:province":"CA",
    "sg:tags":[
        "repairing",
        "automobile"
    ],
    "wof:name":"V & A Auto Repair",
    "wof:placetype":"venue"
},
  "geometry": {"coordinates":[-118.38099699999999,34.054199],"type":"Point"}
}