{
  "type": "Feature",
  "properties": {
    "addr:full":"7720 Paradise Valley Rd San Diego CA 92139",
    "addr:housenumber":"7720",
    "addr:postcode":"92139",
    "addr:street":"Paradise Valley Rd",
    "iso:country":"US",
    "sg:address":"7720 Paradise Valley Rd",
    "sg:city":"San Diego",
    "sg:classifiers":[
        {
            "category":"Restaurant",
            "type":"Food & Drink"
        }
    ],
    "sg:phone":"+1 619 479 6720",
    "sg:postcode":"92139",
    "sg:province":"CA",
    "wof:name":"El Real Mexican Food",
    "wof:placetype":"venue"
},
  "geometry": {"coordinates":[-117.028451,32.695963],"type":"Point"}
}