{
  "type": "Feature",
  "properties": {
    "iso:country":"US",
    "sg:address":"1588 S Anaheim Blvd",
    "sg:city":"Anaheim",
    "sg:classifiers":[
        {
            "category":"Wholesale",
            "subcategory":"Auto Parts",
            "type":"Manufacturing & Wholesale Goods"
        }
    ],
    "sg:phone":"+1 714 776 4200",
    "sg:postcode":"92805",
    "sg:province":"CA",
    "sg:tags":[
        "supply"
    ],
    "wof:name":"Zareh Koocherian",
    "wof:placetype":"venue"
},
  "geometry": {"coordinates":[-117.905933,33.810237],"type":"Point"}
}