{
  "type": "Feature",
  "properties": {
    "iso:country":"US",
    "sg:address":"4740 Westside Rd",
    "sg:city":"Redding",
    "sg:classifiers":[
        {
            "category":"Professional",
            "type":"Services"
        }
    ],
    "sg:phone":"+1 530 247 1830",
    "sg:postcode":"96001",
    "sg:province":"CA",
    "wof:name":"Keelen Blade & Tool",
    "wof:placetype":"venue"
},
  "geometry": {"coordinates":[-122.386726,40.544416],"type":"Point"}
}