{
  "type": "Feature",
  "properties": {
    "iso:country":"US",
    "sg:address":"1500 Beverly Blvd",
    "sg:city":"Los Angeles",
    "sg:classifiers":[
        {
            "category":"Professional",
            "subcategory":"Detective & Security Services",
            "type":"Services"
        }
    ],
    "sg:phone":"+1 323 393 4557",
    "sg:postcode":"90026",
    "sg:province":"CA",
    "sg:tags":[
        "system"
    ],
    "sg:website":"www.my-cctv-pro.com",
    "wof:name":"Sultani Locksmith And Security",
    "wof:placetype":"venue"
},
  "geometry": {"coordinates":[-118.260668,34.0623],"type":"Point"}
}