{
  "type": "Feature",
  "properties": {
    "addr:full":"8891 Armorss Ave San Diego CA 92123",
    "addr:housenumber":"8891",
    "addr:postcode":"92123",
    "addr:street":"Armorss Ave",
    "iso:country":"US",
    "sg:address":"8891 Armorss Ave",
    "sg:city":"San Diego",
    "sg:classifiers":[
        {
            "category":"Professional",
            "type":"Services"
        }
    ],
    "sg:phone":"+1 858 277 6240",
    "sg:postcode":"92123",
    "sg:province":"CA",
    "wof:name":"Abba Consortium Inc",
    "wof:placetype":"venue"
},
  "geometry": {"coordinates":[-117.141594,32.793887],"type":"Point"}
}