{
  "type": "Feature",
  "properties": {
    "iso:country":"US",
    "sg:address":"368 Airport Blvd",
    "sg:city":"Salinas",
    "sg:classifiers":[
        {
            "category":"Government",
            "subcategory":"Office",
            "type":"Public Place"
        }
    ],
    "sg:phone":"+1 831 424 6513",
    "sg:postcode":"93905",
    "sg:province":"CA",
    "sg:tags":[
        "national",
        "guard"
    ],
    "wof:name":"National Guard",
    "wof:placetype":"venue"
},
  "geometry": {"coordinates":[-121.61483699999999,36.666526],"type":"Point"}
}