{
  "type": "Feature",
  "properties": {
    "addr:full":"2140 Lomita Blvd Lomita CA 90717",
    "addr:housenumber":"2140",
    "addr:postcode":"90717",
    "addr:street":"Lomita Blvd",
    "iso:country":"US",
    "sg:address":"2140 Lomita Blvd",
    "sg:city":"Lomita",
    "sg:classifiers":[
        {
            "category":"Health Services",
            "subcategory":"Medical Lab",
            "type":"Services"
        }
    ],
    "sg:phone":"+1 310 325 4588",
    "sg:postcode":"90717",
    "sg:province":"CA",
    "sg:tags":[
        "laboratory"
    ],
    "wof:name":"Mako's Dental Laboratory",
    "wof:placetype":"venue"
},
  "geometry": {"coordinates":[-118.317346,33.801278],"type":"Point"}
}