{
  "type": "Feature",
  "properties": {
    "iso:country":"US",
    "sg:address":"1540 N Ventura Ave",
    "sg:city":"Ventura",
    "sg:classifiers":[
        {
            "category":"Retail",
            "subcategory":"Repair Shop",
            "type":"Services"
        }
    ],
    "sg:phone":"+1 805 648 4072",
    "sg:postcode":"93001",
    "sg:province":"CA",
    "sg:tags":[
        "appliance"
    ],
    "wof:name":"Fix-It Shop",
    "wof:placetype":"venue"
},
  "geometry": {"coordinates":[-119.296127,34.296477],"type":"Point"}
}