{
  "type": "Feature",
  "properties": {
    "iso:country":"US",
    "sg:address":"14121 Browning Ave Ofc",
    "sg:city":"Tustin",
    "sg:classifiers":[
        {
            "category":"Real Estate",
            "subcategory":"Real Estate Operator",
            "type":"Services"
        }
    ],
    "sg:phone":"+1 714 730 6734",
    "sg:postcode":"92780",
    "sg:province":"CA",
    "sg:tags":[
        "apartment"
    ],
    "wof:name":"Pinetree Park Apartments",
    "wof:placetype":"venue"
},
  "geometry": {"coordinates":[-117.80999799999999,33.727402],"type":"Point"}
}