{
  "type": "Feature",
  "properties": {
    "addr:full":"Club Anton 428 3rd Street Oakland CA 94607",
    "addr:housenumber":"428",
    "addr:postcode":"94607",
    "addr:street":"3Rd Street",
    "iso:country":"US",
    "sg:address":"Club Anton 428 3rd Street",
    "sg:city":"Oakland",
    "sg:classifiers":[
        {
            "category":"Personal",
            "type":"Services"
        },
        {
            "category":"Recreation",
            "subcategory":"Dance Hall",
            "type":"Entertainment"
        }
    ],
    "sg:postcode":"94607",
    "sg:province":"CA",
    "sg:tags":[
        "club",
        "party",
        "planning",
        "event"
    ],
    "sg:website":"www.fullfigureentertainment.com/",
    "wof:name":"Full Figure Entertainment",
    "wof:placetype":"venue"
},
  "geometry": {"coordinates":[-122.27534,37.796533],"type":"Point"}
}