{
  "type": "Feature",
  "properties": {
    "iso:country":"US",
    "sg:address":"365 Hamilton St",
    "sg:city":"Costa Mesa",
    "sg:classifiers":[
        {
            "category":"Building & Trades",
            "subcategory":"Cleaning & Sanitation",
            "type":"Services"
        }
    ],
    "sg:phone":"+1 949 633 3415",
    "sg:postcode":"92627",
    "sg:province":"CA",
    "sg:tags":[
        "janitor"
    ],
    "wof:name":"Mint Condition",
    "wof:placetype":"venue"
},
  "geometry": {"coordinates":[-117.915695,33.650703],"type":"Point"}
}