{
  "type": "Feature",
  "properties": {
    "iso:country":"US",
    "sg:address":"10468 Beach Blvd",
    "sg:city":"Stanton",
    "sg:classifiers":[
        {
            "category":"Health Services",
            "subcategory":"Dentist",
            "type":"Services"
        }
    ],
    "sg:phone":"+1 714 995 5995",
    "sg:postcode":"90680",
    "sg:province":"CA",
    "wof:name":"Sy Esther DMD",
    "wof:placetype":"venue"
},
  "geometry": {"coordinates":[-117.99299600000001,33.810699],"type":"Point"}
}