{
  "type": "Feature",
  "properties": {
    "iso:country":"US",
    "sg:address":"550 E Carson Plaza Dr",
    "sg:city":"Carson",
    "sg:classifiers":[
        {
            "category":"Shopping",
            "type":"Retail Goods"
        }
    ],
    "sg:phone":"+1 310 243 1880",
    "sg:postcode":"90746",
    "sg:province":"CA",
    "sg:tags":[
        "enforcement",
        "law",
        "supply"
    ],
    "wof:name":"Sentinel Offender Svc",
    "wof:placetype":"venue"
},
  "geometry": {"coordinates":[-118.26436699999999,33.845233],"type":"Point"}
}