{
  "type": "Feature",
  "properties": {
    "iso:country":"US",
    "sg:address":"211 W Transit St",
    "sg:city":"Ontario",
    "sg:classifiers":[
        {
            "category":"Retail",
            "subcategory":"Auto Repair",
            "type":"Services"
        }
    ],
    "sg:phone":"+1 909 984 8116",
    "sg:postcode":"91762",
    "sg:province":"CA",
    "sg:tags":[
        "repairing",
        "automobile"
    ],
    "wof:name":"Eckles Wheel Alignment Ctr",
    "wof:placetype":"venue"
},
  "geometry": {"coordinates":[-117.65346099999999,34.062607],"type":"Point"}
}