{
  "type": "Feature",
  "properties": {
    "iso:country":"US",
    "sg:address":"3883 Euclid Ave",
    "sg:city":"San Diego",
    "sg:classifiers":[
        {
            "category":"Professional",
            "type":"Services"
        }
    ],
    "sg:phone":"+1 619 640 2504",
    "sg:postcode":"92105",
    "sg:province":"CA",
    "wof:name":"El Folklor Mexicano",
    "wof:placetype":"venue"
},
  "geometry": {"coordinates":[-117.092204,32.749303],"type":"Point"}
}