{
  "type": "Feature",
  "properties": {
    "iso:country":"US",
    "sg:address":"1201 E Colorado St Unit A",
    "sg:city":"Glendale",
    "sg:classifiers":[
        {
            "category":"Government",
            "subcategory":"Office",
            "type":"Public Place"
        }
    ],
    "sg:phone":"+1 818 956 1366",
    "sg:postcode":"91205",
    "sg:province":"CA",
    "sg:tags":[
        "smog",
        "check"
    ],
    "wof:name":"Glendale Smog & Test Only",
    "wof:placetype":"venue"
},
  "geometry": {"coordinates":[-118.23917400000001,34.142923],"type":"Point"}
}