{
  "type": "Feature",
  "properties": {
    "addr:full":"2398 Bateman Ave Duarte CA 91010",
    "addr:housenumber":"2398",
    "addr:postcode":"91010",
    "addr:street":"Bateman Ave",
    "iso:country":"US",
    "sg:address":"2398 Bateman Ave",
    "sg:city":"Duarte",
    "sg:classifiers":[
        {
            "category":"Professional",
            "subcategory":"Business Services",
            "type":"Services"
        }
    ],
    "sg:phone":"+1 626 256 8388",
    "sg:postcode":"91010",
    "sg:province":"CA",
    "sg:tags":[
        "organizing",
        "services-household"
    ],
    "wof:name":"Eagle Valley Management Inc.",
    "wof:placetype":"venue"
},
  "geometry": {"coordinates":[-117.985153,34.121342],"type":"Point"}
}