{
  "type": "Feature",
  "properties": {
    "addr:full":"7450 Foothill Rd Pleasanton CA 94566",
    "addr:housenumber":"7450",
    "addr:postcode":"94566",
    "addr:street":"Foothill Rd",
    "iso:country":"US",
    "sg:address":"7450 Foothill Rd",
    "sg:city":"Pleasanton",
    "sg:classifiers":[
        {
            "category":"Professional",
            "subcategory":"Management & Consulting",
            "type":"Services"
        }
    ],
    "sg:phone":"+1 925 485 1252",
    "sg:postcode":"94566",
    "sg:province":"CA",
    "sg:tags":[
        "communications",
        "consultant"
    ],
    "wof:name":"Meembay Consulting",
    "wof:placetype":"venue"
},
  "geometry": {"coordinates":[-121.89000299999999,37.635882],"type":"Point"}
}