{
  "type": "Feature",
  "properties": {
    "addr:full":"3511 Pacific Coast Hwy Ste G Torrance CA 90505",
    "addr:housenumber":"3511",
    "addr:postcode":"90505",
    "addr:street":"Pacific Coast Hwy Ste G",
    "iso:country":"US",
    "sg:address":"3511 Pacific Coast Hwy Ste G",
    "sg:city":"Torrance",
    "sg:classifiers":[
        {
            "category":"Professional",
            "type":"Services"
        },
        {
            "category":"Food & Beverages",
            "subcategory":"Bakery",
            "type":"Retail Goods"
        }
    ],
    "sg:phone":"+1 310 784 1070",
    "sg:postcode":"90505",
    "sg:province":"CA",
    "sg:tags":[
        "sandwich",
        "caterer"
    ],
    "sg:website":"www.lisasbonappetit.com",
    "wof:name":"Lisa's Bon Appetit",
    "wof:placetype":"venue"
},
  "geometry": {"coordinates":[-118.346315,33.802426],"type":"Point"}
}