{
  "type": "Feature",
  "properties": {
    "addr:full":"1905 Hamilton Ave San Jose CA 95125",
    "addr:housenumber":"1905",
    "addr:postcode":"95125",
    "addr:street":"Hamilton Ave",
    "iso:country":"US",
    "sg:address":"1905 Hamilton Ave",
    "sg:city":"San Jose",
    "sg:classifiers":[
        {
            "category":"Personal",
            "subcategory":"Nail Salon",
            "type":"Services"
        }
    ],
    "sg:phone":"+1 408 377 7270",
    "sg:postcode":"95125",
    "sg:province":"CA",
    "wof:name":"Stylish Nails",
    "wof:placetype":"venue"
},
  "geometry": {"coordinates":[-121.92053199999999,37.294537],"type":"Point"}
}