{
  "type": "Feature",
  "properties": {
    "addr:full":"800 N Sepulveda Blvd Manhattan Beach CA 90266",
    "addr:housenumber":"800",
    "addr:postcode":"90266",
    "addr:street":"N Sepulveda Blvd",
    "iso:country":"US",
    "sg:address":"800 N Sepulveda Blvd",
    "sg:city":"Manhattan Beach",
    "sg:classifiers":[
        {
            "category":"Restaurant",
            "type":"Food & Drink"
        }
    ],
    "sg:phone":"+1 310 376 4143",
    "sg:postcode":"90266",
    "sg:province":"CA",
    "sg:tags":[
        "fast"
    ],
    "sg:website":"www.elpolloloco.com",
    "wof:name":"El Pollo Loco",
    "wof:placetype":"venue"
},
  "geometry": {"coordinates":[-118.396004,33.884102],"type":"Point"}
}