{
  "type": "Feature",
  "properties": {
    "addr:full":"115 E Hawthorne St Fallbrook CA 92028",
    "addr:housenumber":"115",
    "addr:postcode":"92028",
    "addr:street":"E Hawthorne St",
    "iso:country":"US",
    "sg:address":"115 E Hawthorne St",
    "sg:city":"Fallbrook",
    "sg:classifiers":[
        {
            "category":"Building & Trades",
            "subcategory":"Construction",
            "type":"Services"
        },
        {
            "category":"Home & Garden",
            "subcategory":"Carpets & Floor Coverings",
            "type":"Retail Goods"
        }
    ],
    "sg:phone":"+1 760 728 2637",
    "sg:postcode":"92028",
    "sg:province":"CA",
    "sg:tags":[
        "interior",
        "design",
        "carpeting"
    ],
    "wof:name":"Village Interiors",
    "wof:placetype":"venue"
},
  "geometry": {"coordinates":[-117.25099899999999,33.3829],"type":"Point"}
}