{
  "type": "Feature",
  "properties": {
    "iso:country":"US",
    "sg:address":"9500 Gilman Drive",
    "sg:city":"La Jolla",
    "sg:classifiers":[
        {
            "category":"Arts & Performance",
            "subcategory":"Arts Center",
            "type":"Entertainment"
        }
    ],
    "sg:phone":"+1 858 534 4574",
    "sg:postcode":"92037",
    "sg:province":"CA",
    "sg:tags":[
        "performing"
    ],
    "sg:website":"theatre.ucsd.edu/season/",
    "wof:name":"UC San Diego Theatre & Dance",
    "wof:placetype":"venue"
},
  "geometry": {"coordinates":[-117.23961,32.875294],"type":"Point"}
}