{
  "type": "Feature",
  "properties": {
    "iso:country":"US",
    "sg:address":"4481 Sandburg Way",
    "sg:city":"Irvine",
    "sg:classifiers":[
        {
            "category":"Manufacturing",
            "subcategory":"Printing",
            "type":"Manufacturing & Wholesale Goods"
        }
    ],
    "sg:phone":"+1 949 559 9568",
    "sg:postcode":"92612",
    "sg:province":"CA",
    "sg:tags":[
        "publishing"
    ],
    "wof:name":"K International Press Rep",
    "wof:placetype":"venue"
},
  "geometry": {"coordinates":[-117.822085,33.659159],"type":"Point"}
}