{
  "type": "Feature",
  "properties": {
    "iso:country":"US",
    "sg:address":"650 Foothill Blvd",
    "sg:city":"La Canada Flintridge",
    "sg:classifiers":[
        {
            "category":"Health Services",
            "subcategory":"Health Practitioner",
            "type":"Services"
        }
    ],
    "sg:phone":"+1 818 952 0906",
    "sg:postcode":"91011",
    "sg:province":"CA",
    "sg:tags":[
        "therapy",
        "physical"
    ],
    "wof:name":"Sports Medicine Physical Therapy Group Inc",
    "wof:placetype":"venue"
},
  "geometry": {"coordinates":[-118.193001,34.200901],"type":"Point"}
}