{
  "type": "Feature",
  "properties": {
    "addr:full":"651 E Main St Ventura CA 93001",
    "addr:housenumber":"651",
    "addr:postcode":"93001",
    "addr:street":"E Main St",
    "iso:country":"US",
    "sg:address":"651 E Main St",
    "sg:city":"Ventura",
    "sg:classifiers":[
        {
            "category":"Government",
            "subcategory":"Office",
            "type":"Public Place"
        }
    ],
    "sg:phone":"+1 805 652 7523",
    "sg:postcode":"93001",
    "sg:province":"CA",
    "wof:name":"Support Services",
    "wof:placetype":"venue"
},
  "geometry": {"coordinates":[-119.29066899999999,34.280899],"type":"Point"}
}