{
  "type": "Feature",
  "properties": {
    "iso:country":"US",
    "sg:address":"951 W Arrow Hwy",
    "sg:city":"San Dimas",
    "sg:classifiers":[
        {
            "category":"Personal",
            "subcategory":"Beauty Salon",
            "type":"Services"
        }
    ],
    "sg:phone":"+1 909 599 1182",
    "sg:postcode":"91773",
    "sg:province":"CA",
    "sg:website":"www.fantasticsams.com",
    "wof:name":"Fantastic Sam's",
    "wof:placetype":"venue"
},
  "geometry": {"coordinates":[-117.828728,34.106513],"type":"Point"}
}