{
  "type": "Feature",
  "properties": {
    "addr:full":"14850 Cantara St Panorama City CA 91402",
    "addr:housenumber":"14850",
    "addr:postcode":"91402",
    "addr:street":"Cantara St",
    "iso:country":"US",
    "sg:address":"14850 Cantara St",
    "sg:city":"Panorama City",
    "sg:classifiers":[
        {
            "category":"Building & Trades",
            "subcategory":"Landscaping Services",
            "type":"Services"
        }
    ],
    "sg:phone":"+1 818 989 3998",
    "sg:postcode":"91402",
    "sg:province":"CA",
    "sg:tags":[
        "landscape"
    ],
    "wof:name":"Robert Morales Design",
    "wof:placetype":"venue"
},
  "geometry": {"coordinates":[-118.45737200000001,34.219248],"type":"Point"}
}