{
  "type": "Feature",
  "properties": {
    "iso:country":"US",
    "sg:address":"1872 Main St",
    "sg:city":"Saint Helena",
    "sg:classifiers":[
        {
            "category":"Professional",
            "subcategory":"Management & Consulting",
            "type":"Services"
        }
    ],
    "sg:phone":"+1 707 967 8411",
    "sg:postcode":"94574",
    "sg:province":"CA",
    "wof:name":"Arrow Destination Mktg Group",
    "wof:placetype":"venue"
},
  "geometry": {"coordinates":[-122.476792,38.50906],"type":"Point"}
}