{
  "type": "Feature",
  "properties": {
    "iso:country":"US",
    "sg:address":"201 W Sierra Ave",
    "sg:city":"Cotati",
    "sg:classifiers":[
        {
            "category":"Building & Trades",
            "subcategory":"Construction",
            "type":"Services"
        }
    ],
    "sg:phone":"+1 707 792 4610",
    "sg:postcode":"94931",
    "sg:province":"CA",
    "sg:tags":[
        "marking",
        "maintenance",
        "parking"
    ],
    "wof:name":"Public Works Superintendent",
    "wof:placetype":"venue"
},
  "geometry": {"coordinates":[-122.708819,38.323056],"type":"Point"}
}