{
  "type": "Feature",
  "properties": {
    "addr:full":"12428 Elgers St Cerritos CA 90703",
    "addr:housenumber":"12428",
    "addr:postcode":"ca 90703",
    "addr:street":"Elgers St",
    "iso:country":"US",
    "sg:address":"12428 Elgers St",
    "sg:city":"Cerritos",
    "sg:classifiers":[
        {
            "category":"Personal",
            "subcategory":"Beauty Salon",
            "type":"Services"
        }
    ],
    "sg:phone":"+1 310 732 3783",
    "sg:postcode":"90703",
    "sg:province":"CA",
    "wof:name":"My Spa Journeys",
    "wof:placetype":"venue"
},
  "geometry": {"coordinates":[-118.067881,33.866324],"type":"Point"}
}