{
  "type": "Feature",
  "properties": {
    "addr:full":"1203 67th St Emeryville CA 94608",
    "addr:housenumber":"1203",
    "addr:postcode":"94608",
    "addr:street":"67Th St",
    "iso:country":"US",
    "sg:address":"1203 67th St",
    "sg:city":"Emeryville",
    "sg:classifiers":[
        {
            "category":"Building & Trades",
            "subcategory":"Construction",
            "type":"Services"
        }
    ],
    "sg:phone":"+1 415 390 2321",
    "sg:postcode":"94608",
    "sg:province":"CA",
    "sg:tags":[
        "altering",
        "consultant",
        "remodeling",
        "contractor"
    ],
    "wof:name":"Artisan",
    "wof:placetype":"venue"
},
  "geometry": {"coordinates":[-122.28882400000001,37.849528],"type":"Point"}
}