{
  "type": "Feature",
  "properties": {
    "addr:full":"1277 Aspen Dr Pacifica CA 94044",
    "addr:housenumber":"1277",
    "addr:postcode":"94044",
    "addr:street":"Aspen Dr",
    "iso:country":"US",
    "sg:address":"1277 Aspen Dr",
    "sg:city":"Pacifica",
    "sg:classifiers":[
        {
            "category":"Wholesale",
            "subcategory":"Groceries",
            "type":"Manufacturing & Wholesale Goods"
        }
    ],
    "sg:phone":"+1 650 692 9098",
    "sg:postcode":"94044",
    "sg:province":"CA",
    "sg:tags":[
        "nut",
        "fruit",
        "dried"
    ],
    "wof:name":"Golden Banana",
    "wof:placetype":"venue"
},
  "geometry": {"coordinates":[-122.475808,37.586778],"type":"Point"}
}