{
  "type": "Feature",
  "properties": {
    "iso:country":"US",
    "sg:address":"7675 E 11th St",
    "sg:city":"Tracy",
    "sg:classifiers":[
        {
            "category":"Professional",
            "subcategory":"Business Services",
            "type":"Services"
        }
    ],
    "sg:phone":"+1 209 832 8400",
    "sg:postcode":"95304",
    "sg:province":"CA",
    "sg:tags":[
        "member",
        "mfg",
        "wood",
        "structural"
    ],
    "wof:name":"Piedmont Lumber",
    "wof:placetype":"venue"
},
  "geometry": {"coordinates":[-121.402943,37.739844],"type":"Point"}
}