{
  "type": "Feature",
  "properties": {
    "addr:full":"5055 Ave Encinas Carlsbad CA 92008",
    "addr:postcode":"92008",
    "addr:street":"5055 Ave Encinas",
    "iso:country":"US",
    "sg:address":"5055 Ave Encinas",
    "sg:city":"Carlsbad",
    "sg:classifiers":[
        {
            "category":"Health Services",
            "subcategory":"Health Practitioner",
            "type":"Services"
        }
    ],
    "sg:phone":"+1 760 602 0583",
    "sg:postcode":"92008",
    "sg:province":"CA",
    "sg:tags":[
        "nurse",
        "registry"
    ],
    "wof:name":"Dependable Nursing",
    "wof:placetype":"venue"
},
  "geometry": {"coordinates":[-117.32896700000001,33.131142],"type":"Point"}
}