{
  "type": "Feature",
  "properties": {
    "iso:country":"US",
    "sg:address":"6035 University Ave",
    "sg:city":"San Diego",
    "sg:classifiers":[
        {
            "category":"Real Estate",
            "subcategory":"Real Estate Agent",
            "type":"Services"
        }
    ],
    "sg:phone":"+1 530 305 2298",
    "sg:postcode":"92115",
    "sg:province":"CA",
    "wof:name":"Goodrich Real Estate & Ins",
    "wof:placetype":"venue"
},
  "geometry": {"coordinates":[-117.06521600000001,32.752519],"type":"Point"}
}