{
  "type": "Feature",
  "properties": {
    "addr:full":"4232 Atlantic Ave Long Beach CA 90807",
    "addr:housenumber":"4232",
    "addr:postcode":"90807",
    "addr:street":"Atlantic Ave",
    "iso:country":"US",
    "sg:address":"4232 Atlantic Ave",
    "sg:city":"Long Beach",
    "sg:classifiers":[
        {
            "category":"Personal",
            "subcategory":"Beauty Salon",
            "type":"Services"
        }
    ],
    "sg:phone":"+1 562 427 7977",
    "sg:postcode":"90807",
    "sg:province":"CA",
    "sg:tags":[
        "hair"
    ],
    "sg:website":"SALONMEDUSALB.COM",
    "wof:name":"Salon Medusa",
    "wof:placetype":"venue"
},
  "geometry": {"coordinates":[-118.184921,33.833376],"type":"Point"}
}