{
  "type": "Feature",
  "properties": {
    "addr:full":"334 19th St Oakland CA 94612",
    "addr:housenumber":"334",
    "addr:postcode":"94612",
    "addr:street":"19Th St",
    "iso:country":"US",
    "sg:address":"334 19th St",
    "sg:city":"Oakland",
    "sg:classifiers":[
        {
            "category":"Professional",
            "subcategory":"Research",
            "type":"Services"
        }
    ],
    "sg:phone":"+1 510 645 6200",
    "sg:postcode":"94612",
    "sg:province":"CA",
    "sg:tags":[
        "environmental",
        "ecological"
    ],
    "wof:name":"SCA Environmental Inc",
    "wof:placetype":"venue"
},
  "geometry": {"coordinates":[-122.26593,37.806562],"type":"Point"}
}