{
  "type": "Feature",
  "properties": {
    "addr:full":"181 W Orangethorpe Ave Placentia CA 92870",
    "addr:housenumber":"181",
    "addr:postcode":"ca 92870",
    "addr:street":"W Orangethorpe Ave",
    "iso:country":"US",
    "sg:address":"181 W Orangethorpe Ave",
    "sg:city":"Placentia",
    "sg:classifiers":[
        {
            "category":"Wholesale",
            "subcategory":"Medical Equipment & Supplies",
            "type":"Manufacturing & Wholesale Goods"
        }
    ],
    "sg:phone":"+1 714 693 2900",
    "sg:postcode":"92870",
    "sg:province":"CA",
    "sg:tags":[
        "physician",
        "surgeon"
    ],
    "wof:name":"Bestest International",
    "wof:placetype":"venue"
},
  "geometry": {"coordinates":[-117.87437799999999,33.862021],"type":"Point"}
}