{
  "type": "Feature",
  "properties": {
    "addr:full":"545 Bloomfield Rd Sebastopol CA 95472",
    "addr:housenumber":"545",
    "addr:postcode":"95472",
    "addr:street":"Bloomfield Rd",
    "iso:country":"US",
    "sg:address":"545 Bloomfield Rd",
    "sg:city":"Sebastopol",
    "sg:classifiers":[
        {
            "category":"Shopping",
            "subcategory":"Jewelry",
            "type":"Retail Goods"
        },
        {
            "category":"Manufacturing",
            "subcategory":"Jewelry",
            "type":"Manufacturing & Wholesale Goods"
        }
    ],
    "sg:phone":"+1 707 823 6890",
    "sg:postcode":"95472",
    "sg:province":"CA",
    "sg:tags":[
        "designer",
        "jeweler"
    ],
    "sg:website":"http://www.colleentoland.com",
    "wof:name":"Colleen Toland, Inc",
    "wof:placetype":"venue"
},
  "geometry": {"coordinates":[-122.806301,38.372454],"type":"Point"}
}