{
  "type": "Feature",
  "properties": {
    "iso:country":"US",
    "sg:address":"3790 Dunn Dr",
    "sg:city":"Los Angeles",
    "sg:classifiers":[
        {
            "category":"Freight",
            "type":"Transportation"
        }
    ],
    "sg:phone":"+1 310 837 3401",
    "sg:postcode":"90034",
    "sg:province":"CA",
    "wof:name":"Forex Cargo",
    "wof:placetype":"venue"
},
  "geometry": {"coordinates":[-118.400853,34.025081],"type":"Point"}
}