{
  "type": "Feature",
  "properties": {
    "iso:country":"US",
    "sg:address":"1340 E Covell Blvd",
    "sg:city":"Davis",
    "sg:classifiers":[
        {
            "category":"Professional",
            "type":"Services"
        },
        {
            "category":"Restaurant",
            "type":"Food & Drink"
        },
        {
            "category":"Fast Food",
            "type":"Food & Drink"
        }
    ],
    "sg:phone":"+1 530 758 7000",
    "sg:postcode":"95616",
    "sg:province":"CA",
    "sg:tags":[
        "delivery",
        "take",
        "pizza"
    ],
    "sg:website":"http://www.littlecaesars.com",
    "wof:name":"Little Caesars Pizza",
    "wof:placetype":"venue"
},
  "geometry": {"coordinates":[-121.735083,38.561095],"type":"Point"}
}