{
  "type": "Feature",
  "properties": {
    "addr:full":"21901 Burbank Blvd Woodland Hills CA 91367",
    "addr:housenumber":"21901",
    "addr:postcode":"91367",
    "addr:street":"Burbank Blvd",
    "iso:country":"US",
    "sg:address":"21901 Burbank Blvd",
    "sg:city":"Woodland Hills",
    "sg:classifiers":[
        {
            "category":"Local Transit",
            "type":"Transportation"
        }
    ],
    "sg:phone":"+1 818 888 5466",
    "sg:postcode":"91367",
    "sg:province":"CA",
    "sg:tags":[
        "limousine"
    ],
    "wof:name":"On Time Limo",
    "wof:placetype":"venue"
},
  "geometry": {"coordinates":[-118.603163,34.172665],"type":"Point"}
}