{
  "type": "Feature",
  "properties": {
    "iso:country":"US",
    "sg:address":"9701 Wilshire Blvd Ste 800",
    "sg:city":"Beverly Hills",
    "sg:classifiers":[
        {
            "category":"Real Estate",
            "subcategory":"Real Estate Agent",
            "type":"Services"
        }
    ],
    "sg:phone":"+1 323 829 1158",
    "sg:postcode":"90212",
    "sg:province":"CA",
    "sg:website":"www.sustainarealty.com",
    "wof:name":"Carrie Bryden - Sustainable Realty",
    "wof:placetype":"venue"
},
  "geometry": {"coordinates":[-118.406606,34.067227],"type":"Point"}
}