{
  "type": "Feature",
  "properties": {
    "addr:full":"13701 Bancroft Ave San Leandro CA 94577",
    "addr:housenumber":"13701",
    "addr:postcode":"94577",
    "addr:street":"Bancroft Ave",
    "iso:country":"US",
    "sg:address":"13701 Bancroft Ave",
    "sg:city":"San Leandro",
    "sg:classifiers":[
        {
            "category":"Building & Trades",
            "subcategory":"Construction",
            "type":"Services"
        }
    ],
    "sg:phone":"+1 510 483 2751",
    "sg:postcode":"94577",
    "sg:province":"CA",
    "sg:tags":[
        "contractor"
    ],
    "sg:website":"www.luchetticonstruction.com",
    "wof:name":"Jeff Luchetti Construction",
    "wof:placetype":"venue"
},
  "geometry": {"coordinates":[-122.140533,37.715479],"type":"Point"}
}