{
  "type": "Feature",
  "properties": {
    "iso:country":"US",
    "sg:address":"1205 Kibby Rd",
    "sg:city":"Merced",
    "sg:classifiers":[
        {
            "category":"Farming",
            "subcategory":"Orchard",
            "type":"Manufacturing & Wholesale Goods"
        }
    ],
    "sg:phone":"+1 209 383 6126",
    "sg:postcode":"95340",
    "sg:province":"CA",
    "sg:tags":[
        "grove",
        "management",
        "fruit",
        "tree"
    ],
    "wof:name":"Thiara Brothers Orchards",
    "wof:placetype":"venue"
},
  "geometry": {"coordinates":[-120.415295,37.300899],"type":"Point"}
}