{
  "type": "Feature",
  "properties": {
    "iso:country":"US",
    "sg:address":"14101 Euclid St",
    "sg:city":"Garden Grove",
    "sg:classifiers":[
        {
            "category":"Real Estate",
            "subcategory":"Real Estate Operator",
            "type":"Services"
        }
    ],
    "sg:phone":"+1 714 530 1242",
    "sg:postcode":"92843",
    "sg:province":"CA",
    "sg:tags":[
        "apartment"
    ],
    "wof:name":"Euclid Park Apartments",
    "wof:placetype":"venue"
},
  "geometry": {"coordinates":[-117.93800400000001,33.762798],"type":"Point"}
}