{
  "type": "Feature",
  "properties": {
    "iso:country":"US",
    "sg:address":"7551 Madso Ave",
    "sg:city":"Citrus Heights",
    "sg:classifiers":[
        {
            "category":"Health Services",
            "subcategory":"Doctor",
            "type":"Services"
        }
    ],
    "sg:phone":"+1 916 904 3030",
    "sg:postcode":"95621",
    "sg:province":"CA",
    "wof:name":"U C Davis Medical Group",
    "wof:placetype":"venue"
},
  "geometry": {"coordinates":[-121.30500000000001,38.694401],"type":"Point"}
}