{
  "type": "Feature",
  "properties": {
    "addr:full":"6538 Skyview Dr Orangevale CA 95662",
    "addr:housenumber":"6538",
    "addr:postcode":"95662",
    "addr:street":"Skyview Dr",
    "iso:country":"US",
    "sg:address":"6538 Skyview Dr",
    "sg:city":"Orangevale",
    "sg:classifiers":[
        {
            "category":"Building & Trades",
            "subcategory":"Construction",
            "type":"Services"
        }
    ],
    "sg:phone":"+1 916 944 1711",
    "sg:postcode":"95662",
    "sg:province":"CA",
    "sg:tags":[
        "ceiling"
    ],
    "wof:name":"Super Shooters",
    "wof:placetype":"venue"
},
  "geometry": {"coordinates":[-121.26130000000001,38.685379],"type":"Point"}
}