{
  "type": "Feature",
  "properties": {
    "iso:country":"US",
    "sg:address":"15222 Connector Ln",
    "sg:city":"Huntington Beach",
    "sg:classifiers":[
        {
            "category":"Wholesale",
            "subcategory":"Machinery & Supplies",
            "type":"Manufacturing & Wholesale Goods"
        }
    ],
    "sg:phone":"+1 714 897 1017",
    "sg:postcode":"92649",
    "sg:province":"CA",
    "sg:tags":[
        "commercial",
        "fan"
    ],
    "wof:name":"Chem Systems Inc",
    "wof:placetype":"venue"
},
  "geometry": {"coordinates":[-118.027143,33.741037],"type":"Point"}
}