{
  "type": "Feature",
  "properties": {
    "iso:country":"US",
    "sg:address":"927 11th St",
    "sg:city":"Modesto",
    "sg:classifiers":[
        {
            "category":"Restaurant",
            "type":"Food & Drink"
        }
    ],
    "sg:phone":"+1 209 572 2990",
    "sg:postcode":"95354",
    "sg:province":"CA",
    "sg:website":"www.tresetti.com",
    "wof:name":"Tresetti's World Caffe",
    "wof:placetype":"venue"
},
  "geometry": {"coordinates":[-120.99900100000001,37.640499],"type":"Point"}
}