{
  "type": "Feature",
  "properties": {
    "addr:full":"1568 Creekside Dr Folsom CA 95630",
    "addr:housenumber":"1568",
    "addr:postcode":"95630",
    "addr:street":"Creekside Dr",
    "iso:country":"US",
    "sg:address":"1568 Creekside Dr",
    "sg:city":"Folsom",
    "sg:classifiers":[
        {
            "category":"Social Services",
            "type":"Services"
        }
    ],
    "sg:phone":"+1 916 984 8769",
    "sg:postcode":"95630",
    "sg:province":"CA",
    "sg:tags":[
        "counselor",
        "marriage",
        "family"
    ],
    "wof:name":"Kathleen Beavers",
    "wof:placetype":"venue"
},
  "geometry": {"coordinates":[-121.1493,38.668333],"type":"Point"}
}