{
  "type": "Feature",
  "properties": {
    "addr:full":"2417 E Carson St Long Beach CA 90810",
    "addr:housenumber":"2417",
    "addr:postcode":"90810",
    "addr:street":"E Carson St",
    "iso:country":"US",
    "sg:address":"2417 E Carson St",
    "sg:city":"Long Beach",
    "sg:classifiers":[
        {
            "category":"Freight",
            "type":"Transportation"
        }
    ],
    "sg:phone":"+1 310 816 0260",
    "sg:postcode":"90810",
    "sg:province":"CA",
    "sg:tags":[
        "broker"
    ],
    "wof:name":"Intermodal Distribution Frt",
    "wof:placetype":"venue"
},
  "geometry": {"coordinates":[-118.22785500000001,33.832003],"type":"Point"}
}