{
  "type": "Feature",
  "properties": {
    "iso:country":"US",
    "sg:address":"300 Mcdaniel Cir",
    "sg:city":"Sacramento",
    "sg:phone":"+1 916 417 0102",
    "sg:postcode":"95838",
    "sg:province":"CA",
    "wof:name":"Hector Cazares",
    "wof:placetype":"venue"
},
  "geometry": {"coordinates":[-121.461009,38.636961],"type":"Point"}
}