{
  "type": "Feature",
  "properties": {
    "iso:country":"US",
    "sg:address":"861 Columbia Cir",
    "sg:city":"Redwood City",
    "sg:classifiers":[
        {
            "category":"Professional",
            "subcategory":"Business Services",
            "type":"Services"
        }
    ],
    "sg:phone":"+1 650 654 9124",
    "sg:postcode":"94065",
    "sg:province":"CA",
    "sg:tags":[
        "trade",
        "fair",
        "show"
    ],
    "wof:name":"Criket Strong Inc",
    "wof:placetype":"venue"
},
  "geometry": {"coordinates":[-122.237159,37.537041],"type":"Point"}
}