{
  "type": "Feature",
  "properties": {
    "iso:country":"US",
    "sg:address":"3810 Eagle Rock Blvd",
    "sg:city":"Los Angeles",
    "sg:classifiers":[
        {
            "category":"Freight",
            "type":"Transportation"
        }
    ],
    "sg:phone":"+1 323 255 3048",
    "sg:postcode":"90065",
    "sg:province":"CA",
    "sg:tags":[
        "paper",
        "general"
    ],
    "wof:name":"Public Storage Pickup & Dlvry",
    "wof:placetype":"venue"
},
  "geometry": {"coordinates":[-118.22995899999999,34.119502],"type":"Point"}
}