{
  "type": "Feature",
  "properties": {
    "addr:full":"1045 Broadway St San Pablo CA 94806",
    "addr:housenumber":"1045",
    "addr:postcode":"94806",
    "addr:street":"Broadway St",
    "iso:country":"US",
    "sg:address":"1045 Broadway St",
    "sg:city":"San Pablo",
    "sg:classifiers":[
        {
            "category":"Utilities",
            "subcategory":"Refuse",
            "type":"Services"
        }
    ],
    "sg:phone":"+1 510 236 2183",
    "sg:postcode":"94806",
    "sg:province":"CA",
    "sg:tags":[
        "system"
    ],
    "wof:name":"Jahlove Trading & Recycling",
    "wof:placetype":"venue"
},
  "geometry": {"coordinates":[-122.35190299999999,37.975378],"type":"Point"}
}