{
  "type": "Feature",
  "properties": {
    "addr:full":"28089 Smyth Dr Valencia CA 91355",
    "addr:postcode":"28089;91355",
    "addr:street":"Smyth Dr",
    "iso:country":"US",
    "sg:address":"28089 Smyth Dr",
    "sg:city":"Valencia",
    "sg:classifiers":[
        {
            "category":"Health Services",
            "subcategory":"Optometrist",
            "type":"Services"
        }
    ],
    "sg:phone":"+1 661 775 1860",
    "sg:postcode":"91355",
    "sg:province":"CA",
    "sg:website":"www.fvcoptometry.com",
    "wof:name":"Family Vision Care Optometry",
    "wof:placetype":"venue"
},
  "geometry": {"coordinates":[-118.57399700000001,34.4445],"type":"Point"}
}