{
  "type": "Feature",
  "properties": {
    "iso:country":"US",
    "sg:address":"1426 W 6th St",
    "sg:city":"Corona",
    "sg:classifiers":[
        {
            "category":"Manufacturing",
            "subcategory":"Tools & Machinery",
            "type":"Manufacturing & Wholesale Goods"
        }
    ],
    "sg:phone":"+1 951 329 7888",
    "sg:postcode":"92882",
    "sg:province":"CA",
    "sg:tags":[
        "product",
        "computer",
        "distribution"
    ],
    "wof:name":"Blessing Information Tech",
    "wof:placetype":"venue"
},
  "geometry": {"coordinates":[-117.588745,33.877811],"type":"Point"}
}