{
  "type": "Feature",
  "properties": {
    "iso:country":"US",
    "sg:address":"2262 Hidden Lakes Ct",
    "sg:city":"Martinez",
    "sg:classifiers":[
        {
            "category":"Social Services",
            "type":"Services"
        }
    ],
    "sg:phone":"+1 925 671 0758",
    "sg:postcode":"94553",
    "sg:province":"CA",
    "sg:tags":[
        "counselor",
        "marriage",
        "family"
    ],
    "wof:name":"Christian Counseling",
    "wof:placetype":"venue"
},
  "geometry": {"coordinates":[-122.083216,37.980278],"type":"Point"}
}