{
  "type": "Feature",
  "properties": {
    "addr:full":"440 Spruce St Turlock CA 95380",
    "addr:housenumber":"440",
    "addr:postcode":"95380",
    "addr:street":"Spruce St",
    "iso:country":"US",
    "sg:address":"440 Spruce St",
    "sg:city":"Turlock",
    "sg:classifiers":[
        {
            "category":"Building & Trades",
            "subcategory":"Landscaping Services",
            "type":"Services"
        }
    ],
    "sg:phone":"+1 209 656 1895",
    "sg:postcode":"95380",
    "sg:province":"CA",
    "sg:tags":[
        "landscape",
        "contractor"
    ],
    "wof:name":"Work Of Arts",
    "wof:placetype":"venue"
},
  "geometry": {"coordinates":[-120.85352899999999,37.48853],"type":"Point"}
}