{
  "type": "Feature",
  "properties": {
    "iso:country":"US",
    "sg:address":"23123 Ventura Blvd",
    "sg:city":"Woodland Hills",
    "sg:classifiers":[
        {
            "category":"Shopping",
            "subcategory":"Discount & Variety Stores",
            "type":"Retail Goods"
        }
    ],
    "sg:phone":"+1 818 591 7711",
    "sg:postcode":"91364",
    "sg:province":"CA",
    "sg:tags":[
        "merchandise",
        "general"
    ],
    "wof:name":"Champion Tent Sales",
    "wof:placetype":"venue"
},
  "geometry": {"coordinates":[-118.630172,34.163166],"type":"Point"}
}