{
  "type": "Feature",
  "properties": {
    "iso:country":"US",
    "sg:address":"130 S Murphy Ave",
    "sg:city":"Sunnyvale",
    "sg:classifiers":[
        {
            "category":"Bars & Pubs",
            "subcategory":"Dive Bar",
            "type":"Food & Drink"
        }
    ],
    "sg:phone":"+1 408 736 5770",
    "sg:postcode":"94086",
    "sg:province":"CA",
    "wof:name":"Paul & Harveys",
    "wof:placetype":"venue"
},
  "geometry": {"coordinates":[-122.029999,37.377201],"type":"Point"}
}