{
  "type": "Feature",
  "properties": {
    "iso:country":"US",
    "sg:address":"1520 Center St",
    "sg:city":"Stockton",
    "sg:classifiers":[
        {
            "category":"Real Estate",
            "subcategory":"Real Estate Agent",
            "type":"Services"
        }
    ],
    "sg:phone":"+1 209 464 5399",
    "sg:postcode":"95206",
    "sg:province":"CA",
    "wof:name":"Continental Real Estate",
    "wof:placetype":"venue"
},
  "geometry": {"coordinates":[-121.286238,37.936759],"type":"Point"}
}