{
  "type": "Feature",
  "properties": {
    "addr:full":"12405 Los Nietos Rd Santa Fe Springs CA 90670",
    "addr:housenumber":"12405",
    "addr:postcode":"90670",
    "addr:street":"Los Nietos Rd",
    "iso:country":"US",
    "sg:address":"12405 Los Nietos Rd",
    "sg:city":"Santa Fe Springs",
    "sg:classifiers":[
        {
            "category":"Wholesale",
            "subcategory":"Construction Materials",
            "type":"Manufacturing & Wholesale Goods"
        }
    ],
    "sg:phone":"+1 562 941 1459",
    "sg:postcode":"90670",
    "sg:province":"CA",
    "sg:tags":[
        "windows"
    ],
    "wof:name":"Service Aluminum Co",
    "wof:placetype":"venue"
},
  "geometry": {"coordinates":[-118.060106,33.949823],"type":"Point"}
}