{
  "type": "Feature",
  "properties": {
    "iso:country":"US",
    "sg:address":"1301 Princeton Ave",
    "sg:city":"Bakersfield",
    "sg:classifiers":[
        {
            "category":"Banks & Credit Unions",
            "subcategory":"Investment Brokerage",
            "type":"Services"
        }
    ],
    "sg:phone":"+1 661 871 6176",
    "sg:postcode":"93305",
    "sg:province":"CA",
    "sg:tags":[
        "trust"
    ],
    "wof:name":"Lischio Family Trust",
    "wof:placetype":"venue"
},
  "geometry": {"coordinates":[-118.97881099999999,35.408477],"type":"Point"}
}