{
  "type": "Feature",
  "properties": {
    "addr:full":"714 S Glenn Alan Ave West Covina CA 91791",
    "addr:housenumber":"714",
    "addr:postcode":"91791",
    "addr:street":"S Glenn Alan Ave",
    "iso:country":"US",
    "sg:address":"714 S Glenn Alan Ave",
    "sg:city":"West Covina",
    "sg:classifiers":[
        {
            "category":"Building & Trades",
            "subcategory":"Electrical",
            "type":"Services"
        }
    ],
    "sg:phone":"+1 626 339 8026",
    "sg:postcode":"91791",
    "sg:province":"CA",
    "sg:tags":[
        "electric",
        "contractor"
    ],
    "wof:name":"Ozuna Electric",
    "wof:placetype":"venue"
},
  "geometry": {"coordinates":[-117.903897,34.063135],"type":"Point"}
}