{
  "type": "Feature",
  "properties": {
    "iso:country":"US",
    "sg:address":"3849 E Ventura Ave",
    "sg:city":"Fresno",
    "sg:classifiers":[
        {
            "category":"Manufacturing",
            "subcategory":"Signs",
            "type":"Manufacturing & Wholesale Goods"
        },
        {
            "category":"Retail",
            "subcategory":"Auto Repair",
            "type":"Services"
        }
    ],
    "sg:phone":"+1 559 268 1478",
    "sg:postcode":"93702",
    "sg:province":"CA",
    "sg:tags":[
        "lettering",
        "truck",
        "specialty",
        "mfg"
    ],
    "wof:name":"J J S Signs",
    "wof:placetype":"venue"
},
  "geometry": {"coordinates":[-119.75948699999999,36.735933],"type":"Point"}
}