{
  "type": "Feature",
  "properties": {
    "iso:country":"US",
    "sg:address":"3700 Wilshire Blvd",
    "sg:city":"Los Angeles",
    "sg:classifiers":[
        {
            "category":"Professional",
            "subcategory":"Lawyer & Legal Services",
            "type":"Services"
        }
    ],
    "sg:phone":"+1 213 736 5300",
    "sg:postcode":"90010",
    "sg:province":"CA",
    "sg:tags":[
        "attorney"
    ],
    "wof:name":"Martin V Cuauhtemoc Law Ofc",
    "wof:placetype":"venue"
},
  "geometry": {"coordinates":[-118.30783599999999,34.061699],"type":"Point"}
}