{
  "type": "Feature",
  "properties": {
    "iso:country":"US",
    "sg:address":"233 Sunnyside Ave",
    "sg:city":"Clovis",
    "sg:classifiers":[
        {
            "category":"Restaurant",
            "type":"Food & Drink"
        }
    ],
    "sg:phone":"+1 559 299 2000",
    "sg:postcode":"93611",
    "sg:province":"CA",
    "wof:name":"B S Coffee Shop",
    "wof:placetype":"venue"
},
  "geometry": {"coordinates":[-119.690849,36.827806],"type":"Point"}
}