{
  "type": "Feature",
  "properties": {
    "addr:full":"1011 Magnolia Ave Larkspur CA 94939",
    "addr:housenumber":"1011",
    "addr:postcode":"94939",
    "addr:street":"Magnolia Ave",
    "iso:country":"US",
    "sg:address":"1011 Magnolia Ave",
    "sg:city":"Larkspur",
    "sg:classifiers":[
        {
            "category":"Wholesale",
            "subcategory":"Home Furnishings",
            "type":"Manufacturing & Wholesale Goods"
        }
    ],
    "sg:phone":"+1 415 925 1540",
    "sg:postcode":"94939",
    "sg:province":"CA",
    "sg:tags":[
        "linen"
    ],
    "wof:name":"Paper White LTD",
    "wof:placetype":"venue"
},
  "geometry": {"coordinates":[-122.546452,37.946884],"type":"Point"}
}