{
  "type": "Feature",
  "properties": {
    "iso:country":"US",
    "sg:address":"1701 Fortune Drive",
    "sg:city":"San Jose",
    "sg:classifiers":[
        {
            "category":"Wholesale",
            "subcategory":"Computers",
            "type":"Manufacturing & Wholesale Goods"
        }
    ],
    "sg:phone":"+1 408 433 0288",
    "sg:postcode":"95131",
    "sg:province":"CA",
    "wof:name":"Komax Technology",
    "wof:placetype":"venue"
},
  "geometry": {"coordinates":[-121.898183,37.40081],"type":"Point"}
}