{
  "type": "Feature",
  "properties": {
    "addr:full":"2175 Pickwick Dr Camarillo CA 93010",
    "addr:housenumber":"2175",
    "addr:postcode":"93010",
    "addr:street":"Pickwick Dr",
    "iso:country":"US",
    "sg:address":"2175 Pickwick Dr",
    "sg:city":"Camarillo",
    "sg:classifiers":[
        {
            "category":"Personal",
            "type":"Services"
        }
    ],
    "sg:phone":"+1 805 482 0122",
    "sg:postcode":"93010",
    "sg:province":"CA",
    "sg:tags":[
        "control",
        "weight"
    ],
    "wof:name":"Diet Center",
    "wof:placetype":"venue"
},
  "geometry": {"coordinates":[-119.03944300000001,34.222376],"type":"Point"}
}