{
  "type": "Feature",
  "properties": {
    "addr:full":"4010 Chicago Ave Riverside CA 92507",
    "addr:housenumber":"4010",
    "addr:postcode":"92507",
    "addr:street":"Chicago Ave",
    "iso:country":"US",
    "sg:address":"4010 Chicago Ave",
    "sg:city":"Riverside",
    "sg:classifiers":[
        {
            "category":"Restaurant",
            "type":"Food & Drink"
        }
    ],
    "sg:menulink":"http://www.allmenus.com/ca/riverside/150265-subway/menu/",
    "sg:phone":"+1 951 369 1000",
    "sg:postcode":"92507",
    "sg:province":"CA",
    "sg:tags":[
        "american",
        "sandwich"
    ],
    "wof:name":"Subway",
    "wof:placetype":"venue"
},
  "geometry": {"coordinates":[-117.348513,33.972485],"type":"Point"}
}