{
  "type": "Feature",
  "properties": {
    "addr:full":"438 S Murphy Ave Sunnyvale CA 94086",
    "addr:housenumber":"438",
    "addr:postcode":"94086",
    "addr:street":"S Murphy Ave",
    "iso:country":"US",
    "sg:address":"438 S Murphy Ave",
    "sg:city":"Sunnyvale",
    "sg:classifiers":[
        {
            "category":"Professional",
            "subcategory":"Lawyer & Legal Services",
            "type":"Services"
        }
    ],
    "sg:phone":"+1 408 733 0100",
    "sg:postcode":"94086",
    "sg:province":"CA",
    "sg:tags":[
        "personal",
        "injury"
    ],
    "sg:website":"vanderwalde.com",
    "wof:name":"Van Der Walde & Associates",
    "wof:placetype":"venue"
},
  "geometry": {"coordinates":[-122.031464,37.371885],"type":"Point"}
}