{
  "type": "Feature",
  "properties": {
    "iso:country":"US",
    "sg:address":"6552 Fruitridge Road",
    "sg:city":"Sacramento",
    "sg:classifiers":[
        {
            "category":"Retail",
            "subcategory":"Auto Repair",
            "type":"Services"
        }
    ],
    "sg:phone":"+1 916 387 8377",
    "sg:postcode":"95820",
    "sg:province":"CA",
    "wof:name":"Lam Auto Repair",
    "wof:placetype":"venue"
},
  "geometry": {"coordinates":[-121.426098,38.52499],"type":"Point"}
}