{
  "type": "Feature",
  "properties": {
    "iso:country":"US",
    "sg:address":"9685 Elk Grove Florin Rd",
    "sg:city":"Elk Grove",
    "sg:classifiers":[
        {
            "category":"Shopping",
            "subcategory":"Gifts & Souvenirs",
            "type":"Retail Goods"
        }
    ],
    "sg:phone":"+1 916 714 1100",
    "sg:postcode":"95624",
    "sg:province":"CA",
    "sg:tags":[
        "shop"
    ],
    "wof:name":"Nana's Charm",
    "wof:placetype":"venue"
},
  "geometry": {"coordinates":[-121.371458,38.406844],"type":"Point"}
}