{
  "type": "Feature",
  "properties": {
    "addr:full":"19075 Transport Ln Shafter CA 93263",
    "addr:housenumber":"19075",
    "addr:postcode":"93263",
    "addr:street":"Transport Ln",
    "iso:country":"US",
    "sg:address":"19075 Transport Ln",
    "sg:city":"Shafter",
    "sg:classifiers":[
        {
            "category":"Freight",
            "type":"Transportation"
        }
    ],
    "sg:phone":"+1 661 746 1132",
    "sg:postcode":"93263",
    "sg:province":"CA",
    "sg:tags":[
        "trucking"
    ],
    "wof:name":"Remedial Transportation Sltns",
    "wof:placetype":"venue"
},
  "geometry": {"coordinates":[-119.268569,35.458723],"type":"Point"}
}