{
  "type": "Feature",
  "properties": {
    "addr:full":"5600 Mowry School Rd Newark CA 94560",
    "addr:housenumber":"5600",
    "addr:postcode":"94560",
    "addr:street":"Mowry School Rd",
    "iso:country":"US",
    "sg:address":"5600 Mowry School Rd",
    "sg:city":"Newark",
    "sg:classifiers":[
        {
            "category":"Professional",
            "subcategory":"Advertising",
            "type":"Services"
        }
    ],
    "sg:phone":"+1 510 651 6877",
    "sg:postcode":"94560",
    "sg:province":"CA",
    "sg:website":"www.cybercalling.com",
    "wof:name":"CYBERCALLING.COM",
    "wof:placetype":"venue"
},
  "geometry": {"coordinates":[-121.99125600000001,37.523137],"type":"Point"}
}