{
  "type": "Feature",
  "properties": {
    "addr:full":"1991 Diners Ct San Bernardino CA 92408",
    "addr:housenumber":"1991",
    "addr:postcode":"92408",
    "addr:street":"Diners Ct",
    "iso:country":"US",
    "sg:address":"1991 Diners Ct",
    "sg:city":"San Bernardino",
    "sg:classifiers":[
        {
            "category":"Shopping",
            "subcategory":"Florist",
            "type":"Retail Goods"
        }
    ],
    "sg:phone":"+1 909 884 7177",
    "sg:postcode":"92408",
    "sg:province":"CA",
    "sg:website":"www.inlandflowers.com",
    "wof:name":"Inland Flowers",
    "wof:placetype":"venue"
},
  "geometry": {"coordinates":[-117.284313,34.06534],"type":"Point"}
}