{
  "type": "Feature",
  "properties": {
    "addr:full":"10531 Downey Ave Downey CA 90241",
    "addr:housenumber":"10531",
    "addr:postcode":"90241",
    "addr:street":"Downey Ave",
    "iso:country":"US",
    "sg:address":"10531 Downey Ave",
    "sg:city":"Downey",
    "sg:classifiers":[
        {
            "category":"Professional",
            "subcategory":"Accounting & Tax Preparation",
            "type":"Services"
        }
    ],
    "sg:phone":"+1 562 869 2429",
    "sg:postcode":"90241",
    "sg:province":"CA",
    "sg:tags":[
        "return",
        "filing"
    ],
    "wof:name":"1040 N More",
    "wof:placetype":"venue"
},
  "geometry": {"coordinates":[-118.12923000000001,33.946756],"type":"Point"}
}