{
  "type": "Feature",
  "properties": {
    "addr:full":"3825 State St Santa Barbara CA 93105",
    "addr:housenumber":"3825",
    "addr:postcode":"93105",
    "addr:street":"State St",
    "iso:country":"US",
    "sg:address":"3825 State St",
    "sg:city":"Santa Barbara",
    "sg:classifiers":[
        {
            "category":"Shopping",
            "subcategory":"Jewelry",
            "type":"Retail Goods"
        }
    ],
    "sg:phone":"+1 805 563 3679",
    "sg:postcode":"93105",
    "sg:province":"CA",
    "sg:tags":[
        "jeweler"
    ],
    "wof:name":"Zales Jewelers",
    "wof:placetype":"venue"
},
  "geometry": {"coordinates":[-119.747703,34.44036],"type":"Point"}
}