{
  "type": "Feature",
  "properties": {
    "addr:full":"1742 Solano Ave Berkeley CA 94707",
    "addr:housenumber":"1742",
    "addr:postcode":"94707",
    "addr:street":"Solano Ave",
    "iso:country":"US",
    "sg:address":"1742 Solano Ave",
    "sg:city":"Berkeley",
    "sg:classifiers":[
        {
            "category":"Health Services",
            "subcategory":"Doctor",
            "type":"Services"
        },
        {
            "category":"Shopping",
            "subcategory":"Pharmacy",
            "type":"Retail Goods"
        }
    ],
    "sg:phone":"+1 510 525 6895",
    "sg:postcode":"94707",
    "sg:province":"CA",
    "sg:tags":[
        "drugstore"
    ],
    "sg:website":"www.pharmaca.com",
    "wof:name":"Pharmaca Integrative Pharmacy",
    "wof:placetype":"venue"
},
  "geometry": {"coordinates":[-122.28134,37.891123],"type":"Point"}
}