{
  "type": "Feature",
  "properties": {
    "iso:country":"US",
    "sg:address":"3400 Sonoma Blvd",
    "sg:city":"Vallejo",
    "sg:classifiers":[
        {
            "category":"Health Services",
            "subcategory":"Doctor",
            "type":"Services"
        }
    ],
    "sg:phone":"+1 707 554 4000",
    "sg:postcode":"94590",
    "sg:province":"CA",
    "sg:tags":[
        "dentist"
    ],
    "wof:name":"Access Dental Ctr",
    "wof:placetype":"venue"
},
  "geometry": {"coordinates":[-122.254918,38.121948],"type":"Point"}
}