{
  "type": "Feature",
  "properties": {
    "iso:country":"US",
    "sg:address":"777 Railroad Ave",
    "sg:city":"Pittsburg",
    "sg:classifiers":[
        {
            "category":"Real Estate",
            "subcategory":"Real Estate Agent",
            "type":"Services"
        }
    ],
    "sg:phone":"+1 925 473 9294",
    "sg:postcode":"94565",
    "sg:province":"CA",
    "wof:name":"Leonard & Assoc",
    "wof:placetype":"venue"
},
  "geometry": {"coordinates":[-121.884564,38.029399],"type":"Point"}
}