{
  "type": "Feature",
  "properties": {
    "addr:full":"3403 10th St Riverside CA 92501",
    "addr:housenumber":"3403",
    "addr:postcode":"92501",
    "addr:street":"10Th St",
    "iso:country":"US",
    "sg:address":"3403 10th St",
    "sg:city":"Riverside",
    "sg:classifiers":[
        {
            "category":"Professional",
            "subcategory":"Lawyer & Legal Services",
            "type":"Services"
        },
        {
            "category":"Organizations",
            "subcategory":"Professional Association",
            "type":"Services"
        }
    ],
    "sg:phone":"+1 800 331 9570",
    "sg:postcode":"92501",
    "sg:province":"CA",
    "sg:tags":[
        "clinic",
        "form"
    ],
    "wof:name":"Lawyer Referral",
    "wof:placetype":"venue"
},
  "geometry": {"coordinates":[-117.372319,33.97832],"type":"Point"}
}