{
  "type": "Feature",
  "properties": {
    "addr:full":"17779 Vierra Canyon Rd Salinas CA 93907",
    "addr:housenumber":"17779",
    "addr:postcode":"93907",
    "addr:street":"Vierra Canyon Rd",
    "iso:country":"US",
    "sg:address":"17779 Vierra Canyon Rd",
    "sg:city":"Salinas",
    "sg:classifiers":[
        {
            "category":"Manufacturing",
            "subcategory":"Buildings",
            "type":"Manufacturing & Wholesale Goods"
        },
        {
            "category":"Building & Trades",
            "subcategory":"Construction",
            "type":"Services"
        }
    ],
    "sg:phone":"+1 831 442 9999",
    "sg:postcode":"93907",
    "sg:province":"CA",
    "sg:tags":[
        "home",
        "builder",
        "contractor"
    ],
    "wof:name":"Summerhill Mobile Homes",
    "wof:placetype":"venue"
},
  "geometry": {"coordinates":[-121.66053700000001,36.793601],"type":"Point"}
}