{
  "type": "Feature",
  "properties": {
    "iso:country":"US",
    "sg:address":"3222 Airway Dr",
    "sg:city":"Santa Rosa",
    "sg:classifiers":[
        {
            "category":"Manufacturing",
            "subcategory":"Musical Instruments",
            "type":"Manufacturing & Wholesale Goods"
        }
    ],
    "sg:phone":"+1 707 575 0654",
    "sg:postcode":"95403",
    "sg:province":"CA",
    "sg:website":"www.dolanclan.com",
    "wof:name":"Michael Dolan Custom Guitars",
    "wof:placetype":"venue"
},
  "geometry": {"coordinates":[-122.73802499999999,38.473843],"type":"Point"}
}