{
  "type": "Feature",
  "properties": {
    "iso:country":"US",
    "sg:address":"426 Main St",
    "sg:city":"Woodland",
    "sg:classifiers":[
        {
            "category":"Shopping",
            "subcategory":"Jewelry",
            "type":"Retail Goods"
        }
    ],
    "sg:phone":"+1 530 662 2202",
    "sg:postcode":"95695",
    "sg:province":"CA",
    "sg:tags":[
        "jeweler"
    ],
    "wof:name":"David Flory Jewelers",
    "wof:placetype":"venue"
},
  "geometry": {"coordinates":[-121.775099,38.677422],"type":"Point"}
}