{
  "type": "Feature",
  "properties": {
    "iso:country":"US",
    "sg:address":"3390 Coach Ln",
    "sg:city":"Cameron Park",
    "sg:classifiers":[
        {
            "category":"Real Estate",
            "subcategory":"Real Estate Services",
            "type":"Services"
        }
    ],
    "sg:phone":"+1 530 677 3608",
    "sg:postcode":"95682",
    "sg:province":"CA",
    "sg:tags":[
        "company",
        "title"
    ],
    "sg:website":"www.placertitle.com",
    "wof:name":"Placer Title Co",
    "wof:placetype":"venue"
},
  "geometry": {"coordinates":[-120.96938,38.658072],"type":"Point"}
}