{
  "type": "Feature",
  "properties": {
    "addr:full":"250 N Villa Ave Fresno CA 93727",
    "addr:housenumber":"250",
    "addr:postcode":"93727",
    "addr:street":"N Villa Ave",
    "iso:country":"US",
    "sg:address":"250 N Villa Ave",
    "sg:city":"Fresno",
    "sg:classifiers":[
        {
            "category":"Shopping",
            "subcategory":"Crafts & Fabrics",
            "type":"Retail Goods"
        }
    ],
    "sg:phone":"+1 559 251 3024",
    "sg:postcode":"93727",
    "sg:province":"CA",
    "sg:tags":[
        "supply"
    ],
    "wof:name":"From The Heart",
    "wof:placetype":"venue"
},
  "geometry": {"coordinates":[-119.713735,36.746652],"type":"Point"}
}