{
  "type": "Feature",
  "properties": {
    "iso:country":"US",
    "sg:address":"20 Lower Ragsdale Dr",
    "sg:city":"Monterey",
    "sg:classifiers":[
        {
            "category":"Professional",
            "subcategory":"Management & Consulting",
            "type":"Services"
        }
    ],
    "sg:phone":"+1 831 655 6477",
    "sg:postcode":"93940",
    "sg:province":"CA",
    "sg:tags":[
        "consultant",
        "business"
    ],
    "wof:name":"Healthcare Pathways Management",
    "wof:placetype":"venue"
},
  "geometry": {"coordinates":[-121.816387,36.575339],"type":"Point"}
}