{
  "type": "Feature",
  "properties": {
    "addr:full":"20 Lower Ragsdale Dr Monterey CA 93940",
    "addr:housenumber":"20",
    "addr:postcode":"93940",
    "addr:street":"Lower Ragsdale Dr",
    "iso:country":"US",
    "sg:address":"20 Lower Ragsdale Dr",
    "sg:city":"Monterey",
    "sg:classifiers":[
        {
            "category":"Professional",
            "subcategory":"Management & Consulting",
            "type":"Services"
        }
    ],
    "sg:phone":"+1 831 655 6477",
    "sg:postcode":"93940",
    "sg:province":"CA",
    "sg:tags":[
        "consultant",
        "business"
    ],
    "wof:name":"Healthcare Pathways Management",
    "wof:placetype":"venue"
},
  "geometry": {"coordinates":[-121.81638700000001,36.575339],"type":"Point"}
}