{
  "type": "Feature",
  "properties": {
    "iso:country":"US",
    "sg:address":"3029 S Robertson Blvd",
    "sg:city":"Los Angeles",
    "sg:classifiers":[
        {
            "category":"Autos & Motor Vehicles",
            "subcategory":"Fuel & Gas Station",
            "type":"Retail Goods"
        }
    ],
    "sg:phone":"+1 310 836 1497",
    "sg:postcode":"90034",
    "sg:province":"CA",
    "sg:website":"www.chevron.com",
    "wof:name":"Cheviot Chevron",
    "wof:placetype":"venue"
},
  "geometry": {"coordinates":[-118.389999,34.032501],"type":"Point"}
}