{
  "type": "Feature",
  "properties": {
    "addr:full":"159 Main St Salinas CA 93901",
    "addr:housenumber":"159",
    "addr:postcode":"93901",
    "addr:street":"Main St",
    "iso:country":"US",
    "sg:address":"159 Main St",
    "sg:city":"Salinas",
    "sg:classifiers":[
        {
            "category":"Government",
            "subcategory":"Office",
            "type":"Public Place"
        }
    ],
    "sg:phone":"+1 831 758 7387",
    "sg:postcode":"93901",
    "sg:province":"CA",
    "sg:tags":[
        "city",
        "planning",
        "dev"
    ],
    "wof:name":"Salinas City Redevelopment Agy",
    "wof:placetype":"venue"
},
  "geometry": {"coordinates":[-121.655283,36.676307],"type":"Point"}
}