{
  "type": "Feature",
  "properties": {
    "iso:country":"US",
    "sg:address":"2327 Blanding Ave",
    "sg:city":"Alameda",
    "sg:classifiers":[
        {
            "category":"Personal",
            "subcategory":"Beauty Salon",
            "type":"Services"
        }
    ],
    "sg:phone":"+1 510 521 6999",
    "sg:postcode":"94501",
    "sg:province":"CA",
    "wof:name":"Dee Hair & Make Up Artist",
    "wof:placetype":"venue"
},
  "geometry": {"coordinates":[-122.238542,37.771146],"type":"Point"}
}