{
  "type": "Feature",
  "properties": {
    "addr:full":"1260 S Soto Street Los Angeles CA 90023",
    "addr:housenumber":"1260",
    "addr:postcode":"90023",
    "addr:street":"S Soto Street",
    "iso:country":"US",
    "sg:address":"1260 S Soto Street",
    "sg:city":"Los Angeles",
    "sg:classifiers":[
        {
            "category":"Personal",
            "subcategory":"Nail Salon",
            "type":"Services"
        }
    ],
    "sg:phone":"+1 323 264 8052",
    "sg:postcode":"90023",
    "sg:province":"CA",
    "wof:name":"Paola Nails",
    "wof:placetype":"venue"
},
  "geometry": {"coordinates":[-118.219542,34.027254],"type":"Point"}
}