{
  "type": "Feature",
  "properties": {
    "addr:full":"3030 E Pacific Coast Hwy Long Beach CA 90804",
    "addr:housenumber":"3030",
    "addr:postcode":"90804",
    "addr:street":"E Pacific Coast Hwy",
    "iso:country":"US",
    "sg:address":"3030 E Pacific Coast Hwy",
    "sg:city":"Long Beach",
    "sg:classifiers":[
        {
            "category":"Home & Garden",
            "subcategory":"Furniture",
            "type":"Retail Goods"
        }
    ],
    "sg:phone":"+1 562 494 6999",
    "sg:postcode":"90804",
    "sg:province":"CA",
    "sg:tags":[
        "store"
    ],
    "wof:name":"Home Furniture & Appliances",
    "wof:placetype":"venue"
},
  "geometry": {"coordinates":[-118.155998,33.7897],"type":"Point"}
}