{
  "type": "Feature",
  "properties": {
    "iso:country":"US",
    "sg:address":"1715 Hope St",
    "sg:city":"South Pasadena",
    "sg:classifiers":[
        {
            "category":"Shopping",
            "type":"Retail Goods"
        }
    ],
    "sg:phone":"+1 626 441 4648",
    "sg:postcode":"91030",
    "sg:province":"CA",
    "sg:tags":[
        "merchandise"
    ],
    "wof:name":"Webee Big Girls",
    "wof:placetype":"venue"
},
  "geometry": {"coordinates":[-118.147763,34.116921],"type":"Point"}
}