{
  "type": "Feature",
  "properties": {
    "iso:country":"US",
    "sg:address":"3440 Motor Ave",
    "sg:city":"Los Angeles",
    "sg:classifiers":[
        {
            "category":"Communications",
            "subcategory":"Television Station",
            "type":"Services"
        }
    ],
    "sg:phone":"+1 310 204 1010",
    "sg:postcode":"90034",
    "sg:province":"CA",
    "sg:tags":[
        "broadcasting",
        "co"
    ],
    "wof:name":"Network 10 Australia",
    "wof:placetype":"venue"
},
  "geometry": {"coordinates":[-118.40879700000001,34.026975],"type":"Point"}
}