{
  "type": "Feature",
  "properties": {
    "addr:full":"3806 Durbin St Irwindale CA 91706",
    "addr:housenumber":"3806",
    "addr:postcode":"91706",
    "addr:street":"Durbin St",
    "iso:country":"US",
    "sg:address":"3806 Durbin St",
    "sg:city":"Irwindale",
    "sg:classifiers":[
        {
            "category":"Home & Garden",
            "subcategory":"Furniture",
            "type":"Retail Goods"
        }
    ],
    "sg:phone":"+1 626 480 7669",
    "sg:postcode":"91706",
    "sg:province":"CA",
    "wof:name":"Willco",
    "wof:placetype":"venue"
},
  "geometry": {"coordinates":[-117.993297,34.078799],"type":"Point"}
}