{
  "type": "Feature",
  "properties": {
    "addr:full":"1450 N Tustin Ave Ste 125 Santa Ana CA 92705",
    "addr:housenumber":"1450",
    "addr:postcode":"92705",
    "addr:street":"N Tustin Ave Ste 125",
    "iso:country":"US",
    "sg:address":"1450 N Tustin Ave Ste 125",
    "sg:city":"Santa Ana",
    "sg:classifiers":[
        {
            "category":"Professional",
            "subcategory":"Lawyer & Legal Services",
            "type":"Services"
        }
    ],
    "sg:phone":"+1 714 835 2357",
    "sg:postcode":"92705",
    "sg:province":"CA",
    "wof:name":"Cornelius R Scott Atty At Law",
    "wof:placetype":"venue"
},
  "geometry": {"coordinates":[-117.834,33.757],"type":"Point"}
}