{
  "type": "Feature",
  "properties": {
    "addr:full":"1441 W Redwood St Oxnard CA 93033",
    "addr:housenumber":"1441",
    "addr:postcode":"93033",
    "addr:street":"W Redwood St",
    "iso:country":"US",
    "sg:address":"1441 W Redwood St",
    "sg:city":"Oxnard",
    "sg:classifiers":[
        {
            "category":"Restaurant",
            "type":"Food & Drink"
        }
    ],
    "sg:phone":"+1 805 486 3619",
    "sg:postcode":"93033",
    "sg:province":"CA",
    "wof:name":"Little Tony's Italian Rstrnt",
    "wof:placetype":"venue"
},
  "geometry": {"coordinates":[-119.194711,34.173571],"type":"Point"}
}