{
  "type": "Feature",
  "properties": {
    "iso:country":"US",
    "sg:address":"22805 Figueroa St",
    "sg:city":"Carson",
    "sg:classifiers":[
        {
            "category":"Shopping",
            "subcategory":"Discount & Variety Stores",
            "type":"Retail Goods"
        }
    ],
    "sg:phone":"+1 562 453 9107",
    "sg:postcode":"90745",
    "sg:province":"CA",
    "wof:name":"Best 99 Cent & Market",
    "wof:placetype":"venue"
},
  "geometry": {"coordinates":[-118.285979,33.818818],"type":"Point"}
}