{
  "type": "Feature",
  "properties": {
    "iso:country":"US",
    "sg:address":"951 Old County Rd",
    "sg:city":"Belmont",
    "sg:classifiers":[
        {
            "category":"Education",
            "subcategory":"School",
            "type":"Public Place"
        }
    ],
    "sg:phone":"+1 650 595 5200",
    "sg:postcode":"94002",
    "sg:province":"CA",
    "sg:website":"www.passion.edu",
    "wof:name":"Passion University",
    "wof:placetype":"venue"
},
  "geometry": {"coordinates":[-122.275064,37.521487],"type":"Point"}
}