{
  "type": "Feature",
  "properties": {
    "addr:full":"1560 Leucadia Blvd Ste A Encinitas CA 92024",
    "addr:housenumber":"1560",
    "addr:postcode":"92024",
    "addr:street":"Leucadia Blvd Ste A",
    "iso:country":"US",
    "sg:address":"1560 Leucadia Blvd Ste A",
    "sg:city":"Encinitas",
    "sg:phone":"+1 760 635 2888",
    "sg:postcode":"92024",
    "sg:province":"CA",
    "sg:website":"http://www.peiwei.com/",
    "wof:name":"Pei Wei",
    "wof:placetype":"venue"
},
  "geometry": {"coordinates":[-117.264225,33.067862],"type":"Point"}
}