{
  "type": "Feature",
  "properties": {
    "iso:country":"US",
    "sg:address":"3012 Garnet Ln",
    "sg:city":"Fullerton",
    "sg:classifiers":[
        {
            "category":"Professional",
            "type":"Services"
        }
    ],
    "sg:phone":"+1 714 996 2574",
    "sg:postcode":"92831",
    "sg:province":"CA",
    "wof:name":"City Fllerton Garnet Cmnty Ctr",
    "wof:placetype":"venue"
},
  "geometry": {"coordinates":[-117.874908,33.886594],"type":"Point"}
}