{
  "type": "Feature",
  "properties": {
    "addr:full":"210 Canal St King City CA 93930",
    "addr:housenumber":"210",
    "addr:postcode":"93930",
    "addr:street":"Canal St",
    "iso:country":"US",
    "sg:address":"210 Canal St",
    "sg:city":"King City",
    "sg:classifiers":[
        {
            "category":"Health Services",
            "subcategory":"Clinic",
            "type":"Services"
        }
    ],
    "sg:phone":"+1 831 385 7100",
    "sg:postcode":"93930",
    "sg:province":"CA",
    "sg:tags":[
        "medical",
        "group"
    ],
    "wof:name":"So Mo Co Medical Group",
    "wof:placetype":"venue"
},
  "geometry": {"coordinates":[-121.13279900000001,36.207543],"type":"Point"}
}