{
  "type": "Feature",
  "properties": {
    "addr:full":"220 Hospital Dr Vallejo CA 94589",
    "addr:housenumber":"220",
    "addr:postcode":"94589",
    "addr:street":"Hospital Dr",
    "iso:country":"US",
    "sg:address":"220 Hospital Dr",
    "sg:city":"Vallejo",
    "sg:classifiers":[
        {
            "category":"Health Services",
            "subcategory":"Doctor",
            "type":"Services"
        }
    ],
    "sg:phone":"+1 707 643 6483",
    "sg:postcode":"94589",
    "sg:province":"CA",
    "sg:tags":[
        "physician",
        "surgeon"
    ],
    "wof:name":"Associated Family Physicians",
    "wof:placetype":"venue"
},
  "geometry": {"coordinates":[-122.239211,38.131146],"type":"Point"}
}