{
  "type": "Feature",
  "properties": {
    "addr:full":"45 S California St Ventura CA 93001",
    "addr:housenumber":"45",
    "addr:postcode":"93001",
    "addr:street":"S California St",
    "iso:country":"US",
    "sg:address":"45 S California St",
    "sg:city":"Ventura",
    "sg:classifiers":[
        {
            "category":"Food & Beverages",
            "subcategory":"Specialty",
            "type":"Retail Goods"
        }
    ],
    "sg:phone":"+1 805 652 1658",
    "sg:postcode":"93001",
    "sg:province":"CA",
    "sg:tags":[
        "health",
        "diet"
    ],
    "wof:name":"Herbs Of Hope & Consultation",
    "wof:placetype":"venue"
},
  "geometry": {"coordinates":[-119.293178,34.280105],"type":"Point"}
}