{
  "type": "Feature",
  "properties": {
    "iso:country":"US",
    "sg:address":"2133 W Chapman Ave",
    "sg:city":"Orange",
    "sg:classifiers":[
        {
            "category":"Professional",
            "subcategory":"Lawyer & Legal Services",
            "type":"Services"
        }
    ],
    "sg:phone":"+1 805 517 2922",
    "sg:postcode":"92868",
    "sg:province":"CA",
    "sg:tags":[
        "attorney",
        "bankruptcy"
    ],
    "wof:name":"BANKRUPTCY SPECIALISTS",
    "wof:placetype":"venue"
},
  "geometry": {"coordinates":[-117.875334,33.788043],"type":"Point"}
}