{
  "type": "Feature",
  "properties": {
    "iso:country":"US",
    "sg:address":"1345 Taylor St Ste 30",
    "sg:city":"San Francisco",
    "sg:classifiers":[
        {
            "category":"Building & Trades",
            "subcategory":"Electrical",
            "type":"Services"
        }
    ],
    "sg:phone":"+1 415 441 2291",
    "sg:postcode":"94108",
    "sg:province":"CA",
    "sg:tags":[
        "electrician"
    ],
    "wof:name":"All Around Electric",
    "wof:placetype":"venue"
},
  "geometry": {"coordinates":[-122.41347,37.794819],"type":"Point"}
}