{
  "type": "Feature",
  "properties": {
    "addr:full":"5852 Jeffries Ranch Rd Oceanside CA 92057",
    "addr:housenumber":"5852",
    "addr:postcode":"92057",
    "addr:street":"Jeffries Ranch Rd",
    "iso:country":"US",
    "sg:address":"5852 Jeffries Ranch Rd",
    "sg:city":"Oceanside",
    "sg:classifiers":[
        {
            "category":"Wholesale",
            "subcategory":"Non-durable Goods",
            "type":"Manufacturing & Wholesale Goods"
        }
    ],
    "sg:phone":"+1 760 732 1407",
    "sg:postcode":"92057",
    "sg:province":"CA",
    "sg:tags":[
        "wood",
        "gift"
    ],
    "wof:name":"Sawdust Man",
    "wof:placetype":"venue"
},
  "geometry": {"coordinates":[-117.252786,33.251792],"type":"Point"}
}