{
  "type": "Feature",
  "properties": {
    "addr:full":"4069 Marlborough Ave San Diego CA 92105",
    "addr:housenumber":"4069",
    "addr:postcode":"92105",
    "addr:street":"Marlborough Ave",
    "iso:country":"US",
    "sg:address":"4069 Marlborough Ave",
    "sg:city":"San Diego",
    "sg:classifiers":[
        {
            "category":"Banks & Credit Unions",
            "subcategory":"Financial Services",
            "type":"Services"
        }
    ],
    "sg:phone":"+1 619 280 1459",
    "sg:postcode":"92105",
    "sg:province":"CA",
    "sg:tags":[
        "international",
        "trade"
    ],
    "wof:name":"Golden Lake's Trading LTD",
    "wof:placetype":"venue"
},
  "geometry": {"coordinates":[-117.10560700000001,32.750208],"type":"Point"}
}