{
  "type": "Feature",
  "properties": {
    "iso:country":"US",
    "sg:address":"23314 Welby Way",
    "sg:city":"Canoga Park",
    "sg:classifiers":[
        {
            "category":"Building & Trades",
            "subcategory":"Construction",
            "type":"Services"
        }
    ],
    "sg:phone":"+1 818 676 0543",
    "sg:postcode":"91307",
    "sg:province":"CA",
    "sg:tags":[
        "house"
    ],
    "wof:name":"Laguire Const Comp",
    "wof:placetype":"venue"
},
  "geometry": {"coordinates":[-118.635366,34.192687],"type":"Point"}
}