{
  "type": "Feature",
  "properties": {
    "iso:country":"US",
    "sg:address":"582 S Murphy Ave",
    "sg:city":"Sunnyvale",
    "sg:classifiers":[
        {
            "category":"Wholesale",
            "subcategory":"Groceries",
            "type":"Manufacturing & Wholesale Goods"
        }
    ],
    "sg:phone":"+1 408 773 0290",
    "sg:postcode":"94086",
    "sg:province":"CA",
    "sg:tags":[
        "item",
        "specialty"
    ],
    "wof:name":"Attari",
    "wof:placetype":"venue"
},
  "geometry": {"coordinates":[-122.03215400000001,37.37046],"type":"Point"}
}