{
  "type": "Feature",
  "properties": {
    "iso:country":"US",
    "sg:address":"9420 Wilshire Blvd",
    "sg:city":"Beverly Hills",
    "sg:classifiers":[
        {
            "category":"Real Estate",
            "subcategory":"Real Estate Agent",
            "type":"Services"
        }
    ],
    "sg:phone":"+1 310 276 2020",
    "sg:postcode":"90212",
    "sg:province":"CA",
    "wof:name":"Canon At Wilshire Realty",
    "wof:placetype":"venue"
},
  "geometry": {"coordinates":[-118.397103,34.066965],"type":"Point"}
}