{
  "type": "Feature",
  "properties": {
    "addr:full":"39653 Avenue 12 Madera CA 93636",
    "addr:housenumber":"39653",
    "addr:postcode":"93636",
    "addr:street":"Avenue 12",
    "iso:country":"US",
    "sg:address":"39653 Avenue 12",
    "sg:city":"Madera",
    "sg:classifiers":[
        {
            "category":"Professional",
            "subcategory":"Management & Consulting",
            "type":"Services"
        }
    ],
    "sg:phone":"+1 559 435 0947",
    "sg:postcode":"93636",
    "sg:province":"CA",
    "sg:tags":[
        "farm"
    ],
    "wof:name":"Hershel L Irwin",
    "wof:placetype":"venue"
},
  "geometry": {"coordinates":[-119.827654,36.923112],"type":"Point"}
}