{
  "type": "Feature",
  "properties": {
    "addr:full":"417 Winthrop Dr Alhambra CA 91803",
    "addr:housenumber":"417",
    "addr:postcode":"91803",
    "addr:street":"Winthrop Dr",
    "iso:country":"US",
    "sg:address":"417 Winthrop Dr",
    "sg:city":"Alhambra",
    "sg:classifiers":[
        {
            "category":"Communications",
            "subcategory":"Film & Video Production",
            "type":"Services"
        }
    ],
    "sg:phone":"+1 626 576 0040",
    "sg:postcode":"91803",
    "sg:province":"CA",
    "sg:tags":[
        "tv",
        "radio",
        "services-commercial",
        "companies-film"
    ],
    "wof:name":"Paul Morse Productions",
    "wof:placetype":"venue"
},
  "geometry": {"coordinates":[-118.158332,34.087913],"type":"Point"}
}