{
  "type": "Feature",
  "properties": {
    "addr:full":"337 Main St Pleasanton CA 94566",
    "addr:housenumber":"337",
    "addr:postcode":"94566",
    "addr:street":"Main St",
    "iso:country":"US",
    "sg:address":"337 Main St",
    "sg:city":"Pleasanton",
    "sg:classifiers":[
        {
            "category":"Banks & Credit Unions",
            "subcategory":"Bank",
            "type":"Services"
        }
    ],
    "sg:phone":"+1 925 833 9588",
    "sg:postcode":"94566",
    "sg:province":"CA",
    "wof:name":"Bank Of America",
    "wof:placetype":"venue"
},
  "geometry": {"coordinates":[-121.876626,37.659262],"type":"Point"}
}