{
  "type": "Feature",
  "properties": {
    "addr:full":"651 6th Avenue San Francisco CA 94118",
    "addr:housenumber":"651",
    "addr:postcode":"94118",
    "addr:street":"6Th Avenue",
    "iso:country":"US",
    "sg:address":"651 6th Avenue",
    "sg:city":"San Francisco",
    "sg:classifiers":[
        {
            "category":"Education",
            "subcategory":"School",
            "type":"Public Place"
        }
    ],
    "sg:phone":"+1 415 750 8475",
    "sg:postcode":"94118",
    "sg:province":"CA",
    "sg:tags":[
        "high",
        "middle",
        "elementary"
    ],
    "wof:name":"Frank McCoppin Elementary School",
    "wof:placetype":"venue"
},
  "geometry": {"coordinates":[-122.46399700000001,37.776402],"type":"Point"}
}