{
  "type": "Feature",
  "properties": {
    "iso:country":"US",
    "sg:address":"810 E Ohio Ave",
    "sg:city":"Escondido",
    "sg:classifiers":[
        {
            "category":"Health Services",
            "subcategory":"Doctor",
            "type":"Services"
        }
    ],
    "sg:phone":"+1 760 746 7667",
    "sg:postcode":"92025",
    "sg:province":"CA",
    "sg:tags":[
        "medical"
    ],
    "wof:name":"William L Basuk MD",
    "wof:placetype":"venue"
},
  "geometry": {"coordinates":[-117.070533,33.126841],"type":"Point"}
}