{
  "type": "Feature",
  "properties": {
    "iso:country":"US",
    "sg:address":"625 Pine Knot Ave",
    "sg:city":"Big Bear Lake",
    "sg:classifiers":[
        {
            "category":"Professional",
            "type":"Services"
        }
    ],
    "sg:phone":"+1 909 866 8773",
    "sg:postcode":"92315",
    "sg:province":"CA",
    "sg:tags":[
        "establishment"
    ],
    "wof:name":"Plaza At Big Bear Lake",
    "wof:placetype":"venue"
},
  "geometry": {"coordinates":[-116.911564,34.242194],"type":"Point"}
}