{
  "type": "Feature",
  "properties": {
    "addr:full":"13401 Vaughn St San Fernando CA 91340",
    "addr:housenumber":"13401",
    "addr:postcode":"91340",
    "addr:street":"Vaughn St",
    "iso:country":"US",
    "sg:address":"13401 Vaughn St",
    "sg:city":"San Fernando",
    "sg:classifiers":[
        {
            "category":"Organizations",
            "subcategory":"Religious Organization",
            "type":"Services"
        }
    ],
    "sg:phone":"+1 818 365 2020",
    "sg:postcode":"91340",
    "sg:province":"CA",
    "sg:tags":[
        "church"
    ],
    "wof:name":"Mt Zion Baptist Church",
    "wof:placetype":"venue"
},
  "geometry": {"coordinates":[-118.426109,34.279002],"type":"Point"}
}