{
  "type": "Feature",
  "properties": {
    "addr:full":"1232 S Vermont Ave Los Angeles CA 90006",
    "addr:housenumber":"1232",
    "addr:postcode":"90006",
    "addr:street":"S Vermont Ave",
    "iso:country":"US",
    "sg:address":"1232 S Vermont Ave",
    "sg:city":"Los Angeles",
    "sg:classifiers":[
        {
            "category":"Banks & Credit Unions",
            "subcategory":"Bank",
            "type":"Services"
        }
    ],
    "sg:phone":"+1 323 730 9140",
    "sg:postcode":"90006",
    "sg:province":"CA",
    "sg:website":"www.bankofamerica.com",
    "wof:name":"Bank of America",
    "wof:placetype":"venue"
},
  "geometry": {"coordinates":[-118.291855,34.047255],"type":"Point"}
}