{
  "type": "Feature",
  "properties": {
    "iso:country":"US",
    "sg:address":"16613 Valley View Ave",
    "sg:city":"Cerritos",
    "sg:classifiers":[
        {
            "category":"Building & Trades",
            "subcategory":"Construction",
            "type":"Services"
        }
    ],
    "sg:phone":"+1 562 921 6766",
    "sg:postcode":"90703",
    "sg:province":"CA",
    "sg:tags":[
        "contractor"
    ],
    "wof:name":"Djm Construction Company Inc",
    "wof:placetype":"venue"
},
  "geometry": {"coordinates":[-118.028999,33.881199],"type":"Point"}
}