{
  "type": "Feature",
  "properties": {
    "iso:country":"US",
    "sg:address":"22114 S Vermont Ave",
    "sg:city":"Torrance",
    "sg:classifiers":[
        {
            "category":"Building & Trades",
            "subcategory":"Plumbing",
            "type":"Services"
        }
    ],
    "sg:phone":"+1 310 783 0118",
    "sg:postcode":"90502",
    "sg:province":"CA",
    "sg:website":"www.rcplumbing.net",
    "wof:name":"R C Plumbing",
    "wof:placetype":"venue"
},
  "geometry": {"coordinates":[-118.290104,33.82634],"type":"Point"}
}