{
  "type": "Feature",
  "properties": {
    "addr:full":"600 6th Street Coronado CA 92118",
    "addr:housenumber":"600",
    "addr:postcode":"92118",
    "addr:street":"6Th Street",
    "iso:country":"US",
    "sg:address":"600 6th Street",
    "sg:city":"Coronado",
    "sg:classifiers":[
        {
            "category":"Education",
            "subcategory":"School",
            "type":"Public Place"
        }
    ],
    "sg:phone":"+1 619 522 8915",
    "sg:postcode":"92118",
    "sg:province":"CA",
    "sg:tags":[
        "high",
        "middle",
        "elementary"
    ],
    "wof:name":"Coronado Unified School District",
    "wof:placetype":"venue"
},
  "geometry": {"coordinates":[-117.182006,32.693806],"type":"Point"}
}