{
  "type": "Feature",
  "properties": {
    "addr:full":"4228 el Cajon Blvd San Diego CA 92105",
    "addr:housenumber":"4228",
    "addr:postcode":"92105",
    "addr:street":"El Cajon Blvd",
    "iso:country":"US",
    "sg:address":"4228 el Cajon Blvd",
    "sg:city":"San Diego",
    "sg:classifiers":[
        {
            "category":"Health Services",
            "subcategory":"Doctor",
            "type":"Services"
        }
    ],
    "sg:phone":"+1 619 285 1522",
    "sg:postcode":"92105",
    "sg:province":"CA",
    "sg:tags":[
        "physician",
        "surgeon"
    ],
    "wof:name":"Huong Nguyen MD",
    "wof:placetype":"venue"
},
  "geometry": {"coordinates":[-117.104219,32.755213],"type":"Point"}
}