{
  "type": "Feature",
  "properties": {
    "addr:full":"568 W Galway St Rialto CA 92377",
    "addr:housenumber":"568",
    "addr:postcode":"92377",
    "addr:street":"W Galway St",
    "iso:country":"US",
    "sg:address":"568 W Galway St",
    "sg:city":"Rialto",
    "sg:classifiers":[
        {
            "category":"Building & Trades",
            "subcategory":"Equipment Rental",
            "type":"Services"
        }
    ],
    "sg:phone":"+1 909 820 1193",
    "sg:postcode":"92377",
    "sg:province":"CA",
    "sg:tags":[
        "party",
        "supply"
    ],
    "wof:name":"Jump A Lot Jumpers",
    "wof:placetype":"venue"
},
  "geometry": {"coordinates":[-117.381795,34.137576],"type":"Point"}
}