{
  "type": "Feature",
  "properties": {
    "iso:country":"US",
    "sg:address":"15401 S Figueroa Street",
    "sg:city":"Gardena",
    "sg:classifiers":[
        {
            "category":"Wholesale",
            "subcategory":"Furniture",
            "type":"Manufacturing & Wholesale Goods"
        },
        {
            "category":"Manufacturing",
            "subcategory":"Furniture",
            "type":"Manufacturing & Wholesale Goods"
        },
        {
            "category":"Home & Garden",
            "subcategory":"Furniture",
            "type":"Retail Goods"
        }
    ],
    "sg:phone":"+1 310 538 0955",
    "sg:postcode":"90248",
    "sg:province":"CA",
    "sg:tags":[
        "equipment",
        "manufacturer",
        "store",
        "furniture-wholesale",
        "supply"
    ],
    "wof:name":"Brentwood Fine Furniture Mfg",
    "wof:placetype":"venue"
},
  "geometry": {"coordinates":[-118.282839,33.891456],"type":"Point"}
}