{
  "type": "Feature",
  "properties": {
    "iso:country":"US",
    "sg:address":"6000 Contra Costa Rd",
    "sg:city":"Oakland",
    "sg:classifiers":[
        {
            "category":"Health Services",
            "subcategory":"Hospital",
            "type":"Services"
        }
    ],
    "sg:phone":"+1 510 653 7867",
    "sg:postcode":"94618",
    "sg:province":"CA",
    "sg:tags":[
        "center",
        "birth"
    ],
    "sg:website":"www.eastbaymoms.com",
    "wof:name":"East Bay Moms",
    "wof:placetype":"venue"
},
  "geometry": {"coordinates":[-122.23421399999999,37.846913],"type":"Point"}
}