{
  "type": "Feature",
  "properties": {
    "addr:full":"4139 Paramount Blvd Pico Rivera CA 90660",
    "addr:housenumber":"4139",
    "addr:postcode":"90660",
    "addr:street":"Paramount Blvd",
    "iso:country":"US",
    "sg:address":"4139 Paramount Blvd",
    "sg:city":"Pico Rivera",
    "sg:classifiers":[
        {
            "category":"Building & Trades",
            "subcategory":"Construction",
            "type":"Services"
        }
    ],
    "sg:phone":"+1 562 699 6977",
    "sg:postcode":"90660",
    "sg:province":"CA",
    "sg:tags":[
        "contractor"
    ],
    "wof:name":"Rain Gutter Co",
    "wof:placetype":"venue"
},
  "geometry": {"coordinates":[-118.085149,34.015644],"type":"Point"}
}