{
  "type": "Feature",
  "properties": {
    "iso:country":"US",
    "sg:address":"811 Palm St",
    "sg:city":"San Luis Obispo",
    "sg:classifiers":[
        {
            "category":"Building & Trades",
            "subcategory":"Equipment Rental",
            "type":"Services"
        }
    ],
    "sg:phone":"+1 805 781 3583",
    "sg:postcode":"93401",
    "sg:province":"CA",
    "sg:tags":[
        "audio",
        "leasing"
    ],
    "wof:name":"VSI Visual Svc Inc",
    "wof:placetype":"venue"
},
  "geometry": {"coordinates":[-120.663083,35.281993],"type":"Point"}
}