{
  "type": "Feature",
  "properties": {
    "iso:country":"US",
    "sg:address":"2150 W Ave M",
    "sg:city":"Palmdale",
    "sg:classifiers":[
        {
            "category":"Building & Trades",
            "subcategory":"Construction",
            "type":"Services"
        }
    ],
    "sg:phone":"+1 661 943 6832",
    "sg:postcode":"93551",
    "sg:province":"CA",
    "sg:tags":[
        "contractor"
    ],
    "wof:name":"Asbuilt Construction",
    "wof:placetype":"venue"
},
  "geometry": {"coordinates":[-118.168808,34.645683],"type":"Point"}
}