{
  "type": "Feature",
  "properties": {
    "addr:full":"124 Clayton Cir Vacaville CA 95687",
    "addr:housenumber":"124",
    "addr:postcode":"95687",
    "addr:street":"Clayton Cir",
    "iso:country":"US",
    "sg:address":"124 Clayton Cir",
    "sg:city":"Vacaville",
    "sg:classifiers":[
        {
            "category":"Building & Trades",
            "subcategory":"Cleaning & Sanitation",
            "type":"Services"
        }
    ],
    "sg:phone":"+1 707 451 7514",
    "sg:postcode":"95687",
    "sg:province":"CA",
    "sg:tags":[
        "window"
    ],
    "wof:name":"What A Pane",
    "wof:placetype":"venue"
},
  "geometry": {"coordinates":[-121.957082,38.340216],"type":"Point"}
}