{
  "type": "Feature",
  "properties": {
    "addr:full":"16241 Denley St Hacienda Heights CA 91745",
    "addr:housenumber":"16241",
    "addr:postcode":"91745",
    "addr:street":"Denley St",
    "iso:country":"US",
    "sg:address":"16241 Denley St",
    "sg:city":"Hacienda Heights",
    "sg:classifiers":[
        {
            "category":"Shopping",
            "type":"Retail Goods"
        }
    ],
    "sg:phone":"+1 626 968 0526",
    "sg:postcode":"91745",
    "sg:province":"CA",
    "sg:tags":[
        "merchandise"
    ],
    "wof:name":"IA Printing",
    "wof:placetype":"venue"
},
  "geometry": {"coordinates":[-117.952378,34.004919],"type":"Point"}
}