{
  "type": "Feature",
  "properties": {
    "addr:full":"1295 N Wishon Ave Fresno CA 93728",
    "addr:housenumber":"1295",
    "addr:postcode":"93728",
    "addr:street":"N Wishon Ave",
    "iso:country":"US",
    "sg:address":"1295 N Wishon Ave",
    "sg:city":"Fresno",
    "sg:classifiers":[
        {
            "category":"Communications",
            "type":"Services"
        }
    ],
    "sg:phone":"+1 559 443 7231",
    "sg:postcode":"93728",
    "sg:province":"CA",
    "wof:name":"M K Communications",
    "wof:placetype":"venue"
},
  "geometry": {"coordinates":[-119.801064,36.759426],"type":"Point"}
}