{
  "type": "Feature",
  "properties": {
    "addr:full":"3650 W Martin Luther King Jr Blvd Ste 142 Los Angeles CA 90008",
    "addr:housenumber":"3650",
    "addr:postcode":"90008",
    "addr:street":"W Martin Luther King Jr Blvd Ste 142",
    "iso:country":"US",
    "sg:address":"3650 W Martin Luther King Jr Blvd Ste 142",
    "sg:city":"Los Angeles",
    "sg:classifiers":[
        {
            "category":"Shopping",
            "subcategory":"Clothing, Apparel, & Fashions",
            "type":"Retail Goods"
        }
    ],
    "sg:phone":"+1 323 292 9833",
    "sg:postcode":"90008",
    "sg:province":"CA",
    "sg:tags":[
        "accessory",
        "clothing",
        "women's"
    ],
    "sg:website":"www.forever21.com",
    "wof:name":"Forever 21",
    "wof:placetype":"venue"
},
  "geometry": {"coordinates":[-118.33639599999999,34.129793],"type":"Point"}
}