{
  "type": "Feature",
  "properties": {
    "iso:country":"US",
    "sg:address":"1230 W Temple St",
    "sg:city":"Los Angeles",
    "sg:classifiers":[
        {
            "category":"Organizations",
            "subcategory":"Religious Organization",
            "type":"Services"
        }
    ],
    "sg:phone":"+1 213 250 9102",
    "sg:postcode":"90026",
    "sg:province":"CA",
    "sg:tags":[
        "church"
    ],
    "wof:name":"Jehovah's Witnesses",
    "wof:placetype":"venue"
},
  "geometry": {"coordinates":[-118.253748,34.065689],"type":"Point"}
}