{
  "type": "Feature",
  "properties": {
    "addr:full":"1057 E St Oakland CA 94621",
    "addr:housenumber":"1057",
    "addr:postcode":"94621",
    "addr:street":"E St",
    "iso:country":"US",
    "sg:address":"1057 E St",
    "sg:city":"Oakland",
    "sg:classifiers":[
        {
            "category":"Place Of Worship",
            "subcategory":"Church",
            "type":"Public Place"
        },
        {
            "category":"Place Of Worship",
            "type":"Public Place"
        }
    ],
    "sg:phone":"+1 510 632 5337",
    "sg:postcode":"94621",
    "sg:province":"CA",
    "sg:tags":[
        "churches-interdenominational",
        "churches-various",
        "denomination"
    ],
    "wof:name":"Jehovah's Witnesses",
    "wof:placetype":"venue"
},
  "geometry": {"coordinates":[-122.182514,37.748856],"type":"Point"}
}