{
  "type": "Feature",
  "properties": {
    "addr:full":"228 Main Street Suite 14 Venice CA 90291",
    "addr:housenumber":"228;14",
    "addr:postcode":"90291",
    "addr:street":"Main Street Suite",
    "iso:country":"US",
    "sg:address":"228 Main Street Suite 14",
    "sg:city":"Venice",
    "sg:classifiers":[
        {
            "category":"Professional",
            "subcategory":"Computer Services",
            "type":"Services"
        }
    ],
    "sg:postcode":"90291",
    "sg:province":"CA",
    "sg:tags":[
        "movie",
        "video",
        "clip",
        "clips",
        "video-clips",
        "movie-scenes"
    ],
    "sg:website":"http://movieclips.com",
    "wof:name":"MOVIECLIPS",
    "wof:placetype":"venue"
},
  "geometry": {"coordinates":[-118.477943,33.99656],"type":"Point"}
}