{
  "type": "Feature",
  "properties": {
    "addr:full":"71 W Tennyson Rd Hayward CA 94544",
    "addr:housenumber":"71",
    "addr:postcode":"94544",
    "addr:street":"W Tennyson Rd",
    "iso:country":"US",
    "sg:address":"71 W Tennyson Rd",
    "sg:city":"Hayward",
    "sg:classifiers":[
        {
            "category":"Home & Garden",
            "subcategory":"Household Appliances",
            "type":"Retail Goods"
        }
    ],
    "sg:phone":"+1 510 887 6612",
    "sg:postcode":"94544",
    "sg:province":"CA",
    "sg:tags":[
        "repair"
    ],
    "wof:name":"B-Vac Service",
    "wof:placetype":"venue"
},
  "geometry": {"coordinates":[-122.06500200000001,37.635399],"type":"Point"}
}