{
  "type": "Feature",
  "properties": {
    "addr:full":"1350 16th St Oakland CA 94607",
    "addr:housenumber":"1350",
    "addr:postcode":"94607",
    "addr:street":"16Th St",
    "iso:country":"US",
    "sg:address":"1350 16th St",
    "sg:city":"Oakland",
    "sg:classifiers":[
        {
            "category":"Communications",
            "subcategory":"Newspaper",
            "type":"Services"
        }
    ],
    "sg:phone":"+1 510 645 4250",
    "sg:postcode":"94607",
    "sg:province":"CA",
    "sg:tags":[
        "print",
        "medium"
    ],
    "wof:name":"San Francisco Newspaper Agency",
    "wof:placetype":"venue"
},
  "geometry": {"coordinates":[-122.289001,37.811901],"type":"Point"}
}