{
  "type": "Feature",
  "properties": {
    "iso:country":"US",
    "sg:address":"1570 Boulder Creek Rd",
    "sg:city":"Oceanside",
    "sg:classifiers":[
        {
            "category":"Education",
            "subcategory":"Special Training",
            "type":"Public Place"
        }
    ],
    "sg:phone":"+1 760 639 2897",
    "sg:postcode":"92056",
    "sg:province":"CA",
    "sg:tags":[
        "educational"
    ],
    "sg:website":"http://www.americanfenceassoc.com",
    "wof:name":"American Fence Association Inc",
    "wof:placetype":"venue"
},
  "geometry": {"coordinates":[-117.27576000000001,33.219097],"type":"Point"}
}