{
  "type": "Feature",
  "properties": {
    "addr:full":"5296 University Ave Ste H San Diego CA 92105",
    "addr:housenumber":"5296",
    "addr:postcode":"92105",
    "addr:street":"University Ave Ste H",
    "iso:country":"US",
    "sg:address":"5296 University Ave Ste H",
    "sg:city":"San Diego",
    "sg:classifiers":[
        {
            "category":"Shopping",
            "subcategory":"Pharmacy",
            "type":"Retail Goods"
        }
    ],
    "sg:phone":"+1 619 265 9900",
    "sg:postcode":"92105",
    "sg:province":"CA",
    "sg:tags":[
        "drugstore"
    ],
    "wof:name":"Anh Thu's Pharmacy",
    "wof:placetype":"venue"
},
  "geometry": {"coordinates":[-117.08156,32.749058],"type":"Point"}
}