{
  "type": "Feature",
  "properties": {
    "iso:country":"US",
    "sg:address":"555 Laurel Ave",
    "sg:city":"San Mateo",
    "sg:classifiers":[
        {
            "category":"Real Estate",
            "subcategory":"Real Estate Agent",
            "type":"Services"
        }
    ],
    "sg:phone":"+1 650 348 1607",
    "sg:postcode":"94401",
    "sg:province":"CA",
    "wof:name":"Susan Woo Realty Inc",
    "wof:placetype":"venue"
},
  "geometry": {"coordinates":[-122.321652,37.563073],"type":"Point"}
}