{
  "type": "Feature",
  "properties": {
    "iso:country":"US",
    "sg:address":"4646 E Los Angeles Ave",
    "sg:city":"Simi Valley",
    "sg:classifiers":[
        {
            "category":"Manufacturing",
            "subcategory":"Printing",
            "type":"Manufacturing & Wholesale Goods"
        }
    ],
    "sg:phone":"+1 805 527 0695",
    "sg:postcode":"93063",
    "sg:province":"CA",
    "sg:tags":[
        "printer"
    ],
    "sg:website":"www.libertysite.com",
    "wof:name":"Liberty Check Printers Inc",
    "wof:placetype":"venue"
},
  "geometry": {"coordinates":[-118.70689,34.271599],"type":"Point"}
}