{
  "type": "Feature",
  "properties": {
    "iso:country":"US",
    "sg:address":"11150 Santa Monica Blvd",
    "sg:city":"Los Angeles",
    "sg:classifiers":[
        {
            "category":"Professional",
            "type":"Services"
        }
    ],
    "sg:phone":"+1 310 479 9998",
    "sg:postcode":"90025",
    "sg:province":"CA",
    "sg:tags":[
        "establishment"
    ],
    "wof:name":"Los Angeles Capitol Mgmt",
    "wof:placetype":"venue"
},
  "geometry": {"coordinates":[-118.445194,34.047377],"type":"Point"}
}