{
  "type": "Feature",
  "properties": {
    "addr:full":"19720 Ventura Blvd Woodland Hills CA 91364",
    "addr:housenumber":"19720",
    "addr:postcode":"91364",
    "addr:street":"Ventura Blvd",
    "iso:country":"US",
    "sg:address":"19720 Ventura Blvd",
    "sg:city":"Woodland Hills",
    "sg:classifiers":[
        {
            "category":"Building & Trades",
            "subcategory":"Cleaning & Sanitation",
            "type":"Services"
        }
    ],
    "sg:phone":"+1 818 887 1134",
    "sg:postcode":"91364",
    "sg:province":"CA",
    "sg:tags":[
        "janitor"
    ],
    "wof:name":"Allstate Maintenance",
    "wof:placetype":"venue"
},
  "geometry": {"coordinates":[-118.563537,34.172405],"type":"Point"}
}