{
  "type": "Feature",
  "properties": {
    "addr:full":"10551 McFadden Ave Ste A Garden Grove CA 92843",
    "addr:housenumber":"10551",
    "addr:postcode":"92843",
    "addr:street":"Mcfadden Ave Ste A",
    "iso:country":"US",
    "sg:address":"10551 McFadden Ave Ste A",
    "sg:city":"Garden Grove",
    "sg:classifiers":[
        {
            "category":"Education",
            "subcategory":"Kindergarten",
            "type":"Public Place"
        }
    ],
    "sg:phone":"+1 714 265 8900",
    "sg:postcode":"92843",
    "sg:province":"CA",
    "sg:tags":[
        "school",
        "driving"
    ],
    "wof:name":"Gt Driving & Traffic School",
    "wof:placetype":"venue"
},
  "geometry": {"coordinates":[-117.944,33.736198],"type":"Point"}
}