{
  "type": "Feature",
  "properties": {
    "iso:country":"US",
    "sg:address":"5506 University Ave",
    "sg:city":"San Diego",
    "sg:classifiers":[
        {
            "category":"Personal",
            "type":"Services"
        }
    ],
    "sg:phone":"+1 619 582 0389",
    "sg:postcode":"92105",
    "sg:province":"CA",
    "sg:tags":[
        "therapist",
        "massage"
    ],
    "wof:name":"Hongs",
    "wof:placetype":"venue"
},
  "geometry": {"coordinates":[-117.078351,32.748594],"type":"Point"}
}