{
  "type": "Feature",
  "properties": {
    "addr:full":"8465 Enterprise Way Oakland CA 94621",
    "addr:housenumber":"8465",
    "addr:postcode":"94621",
    "addr:street":"Enterprise Way",
    "iso:country":"US",
    "sg:address":"8465 Enterprise Way",
    "sg:city":"Oakland",
    "sg:classifiers":[
        {
            "category":"Travel",
            "subcategory":"Hotels & Motels",
            "type":"Entertainment"
        }
    ],
    "sg:phone":"+1 510 632 8900",
    "sg:postcode":"94621",
    "sg:province":"CA",
    "wof:name":"Hampton Inn",
    "wof:placetype":"venue"
},
  "geometry": {"coordinates":[-122.19499999999999,37.744202],"type":"Point"}
}