{
  "type": "Feature",
  "properties": {
    "addr:full":"3720 20th St San Francisco CA 94110",
    "addr:housenumber":"3720",
    "addr:postcode":"94110",
    "addr:street":"20Th St",
    "iso:country":"US",
    "sg:address":"3720 20th St",
    "sg:city":"San Francisco",
    "sg:classifiers":[
        {
            "category":"Professional",
            "subcategory":"Business Services",
            "type":"Services"
        }
    ],
    "sg:phone":"+1 415 648 0181",
    "sg:postcode":"94110",
    "sg:province":"CA",
    "sg:tags":[
        "interior",
        "consultant",
        "design",
        "decorator"
    ],
    "wof:name":"Eden Wright Design",
    "wof:placetype":"venue"
},
  "geometry": {"coordinates":[-122.425405,37.75833],"type":"Point"}
}