{
  "type": "Feature",
  "properties": {
    "addr:full":"100 E Ave Pico San Clemente CA 92672",
    "addr:housenumber":"100",
    "addr:postcode":"92672",
    "addr:street":"E Ave Pico",
    "iso:country":"US",
    "sg:address":"100 E Ave Pico",
    "sg:city":"San Clemente",
    "sg:classifiers":[
        {
            "category":"Utilities",
            "subcategory":"Water",
            "type":"Services"
        }
    ],
    "sg:phone":"+1 949 361 8398",
    "sg:postcode":"92672",
    "sg:province":"CA",
    "sg:tags":[
        "sewer"
    ],
    "wof:name":"San Clemente City of",
    "wof:placetype":"venue"
},
  "geometry": {"coordinates":[-117.63124999999999,33.4324],"type":"Point"}
}