{
  "type": "Feature",
  "properties": {
    "addr:full":"408 Alameda de Las Pulgas Redwood City CA 94062",
    "addr:housenumber":"408",
    "addr:postcode":"94062",
    "addr:street":"Alameda De Las Pulgas",
    "iso:country":"US",
    "sg:address":"408 Alameda de Las Pulgas",
    "sg:city":"Redwood City",
    "sg:classifiers":[
        {
            "category":"Building & Trades",
            "subcategory":"Construction",
            "type":"Services"
        }
    ],
    "sg:phone":"+1 650 363 2411",
    "sg:postcode":"94062",
    "sg:province":"CA",
    "sg:tags":[
        "contractor",
        "remodeling",
        "general"
    ],
    "wof:name":"Pie Mar Construction",
    "wof:placetype":"venue"
},
  "geometry": {"coordinates":[-122.248626,37.470904],"type":"Point"}
}