{
  "type": "Feature",
  "properties": {
    "iso:country":"US",
    "sg:address":"7993 Sierra Ave",
    "sg:city":"Fontana",
    "sg:classifiers":[
        {
            "category":"Food & Beverages",
            "subcategory":"Specialty",
            "type":"Retail Goods"
        }
    ],
    "sg:phone":"+1 909 746 0317",
    "sg:postcode":"92336",
    "sg:province":"CA",
    "sg:tags":[
        "water",
        "bulk",
        "company"
    ],
    "wof:name":"Aqualife",
    "wof:placetype":"venue"
},
  "geometry": {"coordinates":[-117.435761,34.106722],"type":"Point"}
}