{
  "type": "Feature",
  "properties": {
    "iso:country":"US",
    "sg:address":"60 Marie St",
    "sg:city":"Sausalito",
    "sg:classifiers":[
        {
            "category":"Retail",
            "subcategory":"Veterinary Services",
            "type":"Services"
        }
    ],
    "sg:phone":"+1 415 331 5212",
    "sg:postcode":"94965",
    "sg:province":"CA",
    "sg:tags":[
        "veterinarian"
    ],
    "wof:name":"Sam Silverman DVM",
    "wof:placetype":"venue"
},
  "geometry": {"coordinates":[-122.493652,37.860002],"type":"Point"}
}