{
  "type": "Feature",
  "properties": {
    "iso:country":"US",
    "sg:address":"Bayshore Chiropractic 9000 Soquel Ave Ste 101",
    "sg:city":"Santa Cruz",
    "sg:classifiers":[
        {
            "category":"Health Services",
            "subcategory":"Health Practitioner",
            "type":"Services"
        }
    ],
    "sg:phone":"+1 831 462 0808",
    "sg:postcode":"95062",
    "sg:province":"CA",
    "sg:tags":[
        "acupuncture"
    ],
    "sg:website":"www.acupuncture.lokidoan.com",
    "wof:name":"Loki Doan, LAc",
    "wof:placetype":"venue"
},
  "geometry": {"coordinates":[-121.966505,36.981796],"type":"Point"}
}