{
  "type": "Feature",
  "properties": {
    "addr:full":"6777 Moore Dr Oakland CA 94611",
    "addr:housenumber":"6777",
    "addr:postcode":"94611",
    "addr:street":"Moore Dr",
    "iso:country":"US",
    "sg:address":"6777 Moore Dr",
    "sg:city":"Oakland",
    "sg:classifiers":[
        {
            "category":"Building & Trades",
            "subcategory":"Equipment Rental",
            "type":"Services"
        }
    ],
    "sg:phone":"+1 510 339 6038",
    "sg:postcode":"94611",
    "sg:province":"CA",
    "sg:tags":[
        "financing",
        "computer",
        "leasing"
    ],
    "sg:website":"http://www.cfgco.com",
    "wof:name":"Capital Finance Group",
    "wof:placetype":"venue"
},
  "geometry": {"coordinates":[-122.19072199999999,37.833147],"type":"Point"}
}