{
  "type": "Feature",
  "properties": {
    "addr:full":"1042 Polk St San Francisco CA 94109",
    "addr:housenumber":"1042",
    "addr:postcode":"94109",
    "addr:street":"Polk St",
    "iso:country":"US",
    "sg:address":"1042 Polk St",
    "sg:city":"San Francisco",
    "sg:classifiers":[
        {
            "category":"Food & Beverages",
            "subcategory":"Liquor & Beverages",
            "type":"Retail Goods"
        }
    ],
    "sg:phone":"+1 415 931 6288",
    "sg:postcode":"94109",
    "sg:province":"CA",
    "sg:tags":[
        "beer",
        "spirit",
        "wine"
    ],
    "wof:name":"J and D Liquor",
    "wof:placetype":"venue"
},
  "geometry": {"coordinates":[-122.419838,37.786709],"type":"Point"}
}