{
  "type": "Feature",
  "properties": {
    "addr:full":"6710 W Coast Hwy Newport Beach CA 92663",
    "addr:housenumber":"6710",
    "addr:postcode":"92663",
    "addr:street":"W Coast Hwy",
    "iso:country":"US",
    "sg:address":"6710 W Coast Hwy",
    "sg:city":"Newport Beach",
    "sg:classifiers":[
        {
            "category":"Food & Beverages",
            "subcategory":"Liquor & Beverages",
            "type":"Retail Goods"
        }
    ],
    "sg:phone":"+1 949 548 7025",
    "sg:postcode":"92663",
    "sg:province":"CA",
    "sg:tags":[
        "beer",
        "spirit",
        "wine"
    ],
    "wof:name":"Tradewinds Liquor",
    "wof:placetype":"venue"
},
  "geometry": {"coordinates":[-117.952175,33.628327],"type":"Point"}
}