{
  "type": "Feature",
  "properties": {
    "iso:country":"US",
    "sg:address":"306 S Abel Street",
    "sg:city":"Milpitas",
    "sg:classifiers":[
        {
            "category":"Health Services",
            "subcategory":"Health Practitioner",
            "type":"Services"
        }
    ],
    "sg:phone":"+1 408 956 9311",
    "sg:postcode":"95035",
    "sg:province":"CA",
    "sg:tags":[
        "acupuncture"
    ],
    "wof:name":"California Acupunture Clinic",
    "wof:placetype":"venue"
},
  "geometry": {"coordinates":[-121.908236,37.426708],"type":"Point"}
}