{
  "type": "Feature",
  "properties": {
    "addr:full":"1953 Pontius Ave Los Angeles CA 90025",
    "addr:housenumber":"1953",
    "addr:postcode":"90025",
    "addr:street":"Pontius Ave",
    "iso:country":"US",
    "sg:address":"1953 Pontius Ave",
    "sg:city":"Los Angeles",
    "sg:classifiers":[
        {
            "category":"Manufacturing",
            "subcategory":"Signs",
            "type":"Manufacturing & Wholesale Goods"
        }
    ],
    "sg:phone":"+1 310 826 4119",
    "sg:postcode":"90025",
    "sg:province":"CA",
    "wof:name":"Tom Williams Signs",
    "wof:placetype":"venue"
},
  "geometry": {"coordinates":[-118.441481,34.043429],"type":"Point"}
}