{
  "type": "Feature",
  "properties": {
    "iso:country":"US",
    "sg:address":"4855 el Camino Real",
    "sg:city":"Atascadero",
    "sg:classifiers":[
        {
            "category":"Personal",
            "subcategory":"Beauty Salon",
            "type":"Services"
        }
    ],
    "sg:phone":"+1 805 466 2457",
    "sg:postcode":"93422",
    "sg:province":"CA",
    "sg:tags":[
        "manicuring"
    ],
    "wof:name":"Nails By Barbie",
    "wof:placetype":"venue"
},
  "geometry": {"coordinates":[-120.680767,35.496493],"type":"Point"}
}