{
  "type": "Feature",
  "properties": {
    "iso:country":"US",
    "sg:address":"2191 Pleasantwood Ln",
    "sg:city":"Escondido",
    "sg:classifiers":[
        {
            "category":"Banks & Credit Unions",
            "subcategory":"Bank",
            "type":"Services"
        }
    ],
    "sg:phone":"+1 760 741 5232",
    "sg:postcode":"92026",
    "sg:province":"CA",
    "sg:tags":[
        "short",
        "institution",
        "business"
    ],
    "wof:name":"Americap Funding LLC",
    "wof:placetype":"venue"
},
  "geometry": {"coordinates":[-117.088046,33.160645],"type":"Point"}
}