{
  "type": "Feature",
  "properties": {
    "addr:full":"8383 Wren Ave Gilroy CA 95020",
    "addr:housenumber":"8383",
    "addr:postcode":"95020",
    "addr:street":"Wren Ave",
    "iso:country":"US",
    "sg:address":"8383 Wren Ave",
    "sg:city":"Gilroy",
    "sg:classifiers":[
        {
            "category":"Government",
            "subcategory":"Fire Station",
            "type":"Public Place"
        }
    ],
    "sg:phone":"+1 408 842 9645",
    "sg:postcode":"95020",
    "sg:province":"CA",
    "sg:tags":[
        "department"
    ],
    "wof:name":"Las Animas Fire Station",
    "wof:placetype":"venue"
},
  "geometry": {"coordinates":[-121.586742,37.016306],"type":"Point"}
}