{
  "type": "Feature",
  "properties": {
    "addr:full":"2750 S Alameda St Los Angeles CA 90058",
    "addr:housenumber":"2750",
    "addr:postcode":"90058",
    "addr:street":"S Alameda St",
    "iso:country":"US",
    "sg:address":"2750 S Alameda St",
    "sg:city":"Los Angeles",
    "sg:classifiers":[
        {
            "category":"Wholesale",
            "subcategory":"Chemicals & Plastics",
            "type":"Manufacturing & Wholesale Goods"
        },
        {
            "category":"Food & Beverages",
            "subcategory":"Fruits & Vegetables",
            "type":"Retail Goods"
        },
        {
            "category":"Shopping",
            "type":"Retail Goods"
        },
        {
            "category":"Shopping",
            "subcategory":"Discount & Variety Stores",
            "type":"Retail Goods"
        }
    ],
    "sg:phone":"+1 323 234 3089",
    "sg:postcode":"90058",
    "sg:province":"CA",
    "sg:tags":[
        "bag",
        "religious",
        "incense",
        "herb"
    ],
    "sg:website":"www.indioproducts.com",
    "wof:name":"Indio Products,Inc.",
    "wof:placetype":"venue"
},
  "geometry": {"coordinates":[-118.239729,34.012633],"type":"Point"}
}