{
  "type": "Feature",
  "properties": {
    "iso:country":"US",
    "sg:address":"333 Estudillo Ave Ste 205",
    "sg:city":"San Leandro",
    "sg:classifiers":[
        {
            "category":"Health Services",
            "subcategory":"Dentist",
            "type":"Services"
        }
    ],
    "sg:phone":"+1 510 483 5366",
    "sg:postcode":"94577",
    "sg:province":"CA",
    "wof:name":"Handog Coralinda M DMD",
    "wof:placetype":"venue"
},
  "geometry": {"coordinates":[-122.15300000000001,37.7258],"type":"Point"}
}