{
  "type": "Feature",
  "properties": {
    "iso:country":"US",
    "sg:address":"8700 Greenback Lane",
    "sg:city":"Orangevale",
    "sg:classifiers":[
        {
            "category":"Recreation",
            "subcategory":"Water Park",
            "type":"Entertainment"
        }
    ],
    "sg:phone":"+1 916 966 7946",
    "sg:postcode":"95662",
    "sg:province":"CA",
    "sg:tags":[
        "lake"
    ],
    "wof:name":"Ponz R US",
    "wof:placetype":"venue"
},
  "geometry": {"coordinates":[-121.23405700000001,38.678422],"type":"Point"}
}