{
  "type": "Feature",
  "properties": {
    "iso:country":"US",
    "sg:address":"8939 S Sepulveda Blvd",
    "sg:city":"Los Angeles",
    "sg:classifiers":[
        {
            "category":"Professional",
            "subcategory":"Management & Consulting",
            "type":"Services"
        }
    ],
    "sg:phone":"+1 310 342 9893",
    "sg:postcode":"90045",
    "sg:province":"CA",
    "sg:tags":[
        "consultant"
    ],
    "wof:name":"J B & M Consulting LLC",
    "wof:placetype":"venue"
},
  "geometry": {"coordinates":[-118.39612700000001,33.957237],"type":"Point"}
}