{
  "type": "Feature",
  "properties": {
    "addr:full":"5257 Amelia Dr San Jose CA 95118",
    "addr:housenumber":"5257",
    "addr:postcode":"95118",
    "addr:street":"Amelia Dr",
    "iso:country":"US",
    "sg:address":"5257 Amelia Dr",
    "sg:city":"San Jose",
    "sg:classifiers":[
        {
            "category":"Professional",
            "type":"Services"
        }
    ],
    "sg:phone":"+1 408 269 7104",
    "sg:postcode":"95118",
    "sg:province":"CA",
    "wof:name":"Mountain Workshop",
    "wof:placetype":"venue"
},
  "geometry": {"coordinates":[-121.896883,37.24583],"type":"Point"}
}