{
  "type": "Feature",
  "properties": {
    "addr:full":"315 Wall St Chico CA 95928",
    "addr:housenumber":"315",
    "addr:postcode":"95928",
    "addr:street":"Wall St",
    "iso:country":"US",
    "sg:address":"315 Wall St",
    "sg:city":"Chico",
    "sg:classifiers":[
        {
            "category":"Bars & Pubs",
            "type":"Food & Drink"
        }
    ],
    "sg:phone":"+1 530 893 0930",
    "sg:postcode":"95928",
    "sg:province":"CA",
    "sg:tags":[
        "club",
        "night"
    ],
    "wof:name":"Mr Lucky",
    "wof:placetype":"venue"
},
  "geometry": {"coordinates":[-121.8379,39.729722],"type":"Point"}
}