{
  "type": "Feature",
  "properties": {
    "addr:full":"665 Sutter Street San Francisco CA 94102",
    "addr:housenumber":"665",
    "addr:postcode":"94102",
    "addr:street":"Sutter Street",
    "iso:country":"US",
    "sg:address":"665 Sutter Street",
    "sg:city":"San Francisco",
    "sg:classifiers":[
        {
            "category":"Parking",
            "type":"Transportation"
        }
    ],
    "sg:phone":"+1 415 440 1652",
    "sg:postcode":"94102",
    "sg:province":"CA",
    "wof:name":"California Parking Company",
    "wof:placetype":"venue"
},
  "geometry": {"coordinates":[-122.411401,37.788811],"type":"Point"}
}