{
  "type": "Feature",
  "properties": {
    "iso:country":"US",
    "sg:address":"9477 Greenback Ln",
    "sg:city":"Folsom",
    "sg:classifiers":[
        {
            "category":"Building & Trades",
            "subcategory":"Pest Control",
            "type":"Services"
        }
    ],
    "sg:phone":"+1 916 987 9559",
    "sg:postcode":"95630",
    "sg:province":"CA",
    "wof:name":"Specialized Pest Patrol",
    "wof:placetype":"venue"
},
  "geometry": {"coordinates":[-121.196197,38.677999],"type":"Point"}
}