{
  "type": "Feature",
  "properties": {
    "addr:full":"1045 Hawaii Ave Chula Vista CA 91910",
    "addr:housenumber":"1045",
    "addr:postcode":"91910",
    "addr:street":"Hawaii Ave",
    "iso:country":"US",
    "sg:address":"1045 Hawaii Ave",
    "sg:city":"Chula Vista",
    "sg:classifiers":[
        {
            "category":"Retail",
            "subcategory":"Portrait Studio",
            "type":"Services"
        },
        {
            "category":"Professional",
            "subcategory":"Art Services",
            "type":"Services"
        }
    ],
    "sg:phone":"+1 619 575 0100",
    "sg:postcode":"91910",
    "sg:province":"CA",
    "sg:tags":[
        "photographer",
        "photography",
        "store"
    ],
    "wof:name":"Glamour Photographer",
    "wof:placetype":"venue"
},
  "geometry": {"coordinates":[-117.054001,32.635101],"type":"Point"}
}