{
  "type": "Feature",
  "properties": {
    "iso:country":"US",
    "sg:address":"2595 E Imperial Hwy",
    "sg:city":"Brea",
    "sg:classifiers":[
        {
            "category":"Professional",
            "type":"Services"
        }
    ],
    "sg:phone":"+1 714 256 4138",
    "sg:postcode":"92886",
    "sg:province":"CA",
    "wof:name":"Mobile Magic",
    "wof:placetype":"venue"
},
  "geometry": {"coordinates":[-117.86492699999999,33.911026],"type":"Point"}
}