{
  "type": "Feature",
  "properties": {
    "iso:country":"US",
    "sg:address":"15030 Alondra Blvd",
    "sg:city":"La Mirada",
    "sg:classifiers":[
        {
            "category":"Retail",
            "subcategory":"Car Wash",
            "type":"Services"
        }
    ],
    "sg:phone":"+1 562 726 2221",
    "sg:postcode":"90638",
    "sg:province":"CA",
    "wof:name":"Orange Coin Car Wash",
    "wof:placetype":"venue"
},
  "geometry": {"coordinates":[-118.010602,33.887755],"type":"Point"}
}