{
  "type": "Feature",
  "properties": {
    "iso:country":"US",
    "sg:address":"11088 Olson Dr Ste A",
    "sg:city":"Rancho Cordova",
    "sg:classifiers":[
        {
            "category":"Restaurant",
            "type":"Food & Drink"
        }
    ],
    "sg:phone":"+1 916 635 2744",
    "sg:postcode":"95670",
    "sg:province":"CA",
    "sg:tags":[
        "fusion",
        "asian",
        "chinese",
        "vietnamese"
    ],
    "sg:website":"www.mintsasia.com",
    "wof:name":"Mint's Euro-Asian Cuisine",
    "wof:placetype":"venue"
},
  "geometry": {"coordinates":[-121.28105499999999,38.598104],"type":"Point"}
}