{
  "type": "Feature",
  "properties": {
    "iso:country":"US",
    "sg:address":"320 W Orange Show Ln",
    "sg:city":"San Bernardino",
    "sg:classifiers":[
        {
            "category":"Building & Trades",
            "subcategory":"Electrical",
            "type":"Services"
        }
    ],
    "sg:phone":"+1 909 889 1161",
    "sg:postcode":"92408",
    "sg:province":"CA",
    "sg:tags":[
        "security",
        "electrical",
        "system",
        "contractor"
    ],
    "wof:name":"Protection Service Inds L P",
    "wof:placetype":"venue"
},
  "geometry": {"coordinates":[-117.29380500000001,34.081117],"type":"Point"}
}