{
  "type": "Feature",
  "properties": {
    "iso:country":"US",
    "sg:address":"5371 State St",
    "sg:city":"Montclair",
    "sg:classifiers":[
        {
            "category":"Manufacturing",
            "subcategory":"Metals",
            "type":"Manufacturing & Wholesale Goods"
        }
    ],
    "sg:phone":"+1 909 464 9629",
    "sg:postcode":"91763",
    "sg:province":"CA",
    "sg:tags":[
        "tube",
        "fabricating"
    ],
    "wof:name":"United Tube Bending",
    "wof:placetype":"venue"
},
  "geometry": {"coordinates":[-117.685452,34.059764],"type":"Point"}
}