{
  "type": "Feature",
  "properties": {
    "iso:country":"US",
    "sg:address":"312 E Los Angeles Ave",
    "sg:city":"Moorpark",
    "sg:classifiers":[
        {
            "category":"Food & Beverages",
            "subcategory":"Liquor & Beverages",
            "type":"Retail Goods"
        }
    ],
    "sg:phone":"+1 805 529 1534",
    "sg:postcode":"93021",
    "sg:province":"CA",
    "wof:name":"Moorepark Liquor Jr Market",
    "wof:placetype":"venue"
},
  "geometry": {"coordinates":[-118.838897,34.292598],"type":"Point"}
}