{
  "type": "Feature",
  "properties": {
    "iso:country":"US",
    "sg:address":"421 Walnut St",
    "sg:city":"Napa",
    "sg:classifiers":[
        {
            "category":"Building & Trades",
            "subcategory":"Construction",
            "type":"Services"
        }
    ],
    "sg:phone":"+1 707 226 5951",
    "sg:postcode":"94559",
    "sg:province":"CA",
    "sg:tags":[
        "contractor"
    ],
    "wof:name":"Marsey Brothers Construction",
    "wof:placetype":"venue"
},
  "geometry": {"coordinates":[-122.300294,38.292724],"type":"Point"}
}