{
  "type": "Feature",
  "properties": {
    "addr:full":"12851 W Chapman Ave Garden Grove CA 92840",
    "addr:housenumber":"12851",
    "addr:postcode":"92840",
    "addr:street":"W Chapman Ave",
    "iso:country":"US",
    "sg:address":"12851 W Chapman Ave",
    "sg:city":"Garden Grove",
    "sg:classifiers":[
        {
            "category":"Retail",
            "subcategory":"Funeral Services",
            "type":"Services"
        }
    ],
    "sg:phone":"+1 714 966 1918",
    "sg:postcode":"92840",
    "sg:province":"CA",
    "wof:name":"Direct Casket Inc",
    "wof:placetype":"venue"
},
  "geometry": {"coordinates":[-117.90718099999999,33.788869],"type":"Point"}
}