{
  "type": "Feature",
  "properties": {
    "addr:full":"1533 N Johnson Ave El Cajon CA 92020",
    "addr:housenumber":"1533",
    "addr:postcode":"92020",
    "addr:street":"N Johnson Ave",
    "iso:country":"US",
    "sg:address":"1533 N Johnson Ave",
    "sg:city":"El Cajon",
    "sg:classifiers":[
        {
            "category":"Manufacturing",
            "subcategory":"Tools & Machinery",
            "type":"Manufacturing & Wholesale Goods"
        }
    ],
    "sg:phone":"+1 619 440 2300",
    "sg:postcode":"92020",
    "sg:province":"CA",
    "sg:tags":[
        "metal",
        "fabrication"
    ],
    "wof:name":"Weldmac Manufacturing Co",
    "wof:placetype":"venue"
},
  "geometry": {"coordinates":[-116.97094199999999,32.816473],"type":"Point"}
}