{
  "type": "Feature",
  "properties": {
    "iso:country":"US",
    "sg:address":"800 Butte St",
    "sg:city":"Bakersfield",
    "sg:classifiers":[
        {
            "category":"Organizations",
            "subcategory":"Religious Organization",
            "type":"Services"
        }
    ],
    "sg:phone":"+1 661 323 9203",
    "sg:postcode":"93305",
    "sg:province":"CA",
    "sg:tags":[
        "church"
    ],
    "wof:name":"Full Gospel Lighthouse",
    "wof:placetype":"venue"
},
  "geometry": {"coordinates":[-118.992424,35.368781],"type":"Point"}
}