{
  "type": "Feature",
  "properties": {
    "addr:full":"9155 Telegraph Rd Pico Rivera CA 90660",
    "addr:housenumber":"9155",
    "addr:postcode":"90660",
    "addr:street":"Telegraph Rd",
    "iso:country":"US",
    "sg:address":"9155 Telegraph Rd",
    "sg:city":"Pico Rivera",
    "sg:classifiers":[
        {
            "category":"Real Estate",
            "subcategory":"Real Estate Agent",
            "type":"Services"
        }
    ],
    "sg:phone":"+1 562 231 1250",
    "sg:postcode":"90660",
    "sg:province":"CA",
    "wof:name":"Remax Online",
    "wof:placetype":"venue"
},
  "geometry": {"coordinates":[-118.106477,33.958624],"type":"Point"}
}