{
  "type": "Feature",
  "properties": {
    "iso:country":"US",
    "sg:address":"4519 E Cesar E Chavez Ave",
    "sg:city":"Los Angeles",
    "sg:classifiers":[
        {
            "category":"Insurance",
            "subcategory":"Insurance Agent",
            "type":"Services"
        }
    ],
    "sg:phone":"+1 323 268 0123",
    "sg:postcode":"90022",
    "sg:province":"CA",
    "wof:name":"Cali-Mex",
    "wof:placetype":"venue"
},
  "geometry": {"coordinates":[-118.16738,34.040665],"type":"Point"}
}