{
  "type": "Feature",
  "properties": {
    "iso:country":"US",
    "sg:address":"19701 Hamilton Ave",
    "sg:city":"Torrance",
    "sg:classifiers":[
        {
            "category":"Banks & Credit Unions",
            "subcategory":"Bank",
            "type":"Services"
        }
    ],
    "sg:phone":"+1 310 769 5760",
    "sg:postcode":"90502",
    "sg:province":"CA",
    "wof:name":"Honda Federal Credit Union",
    "wof:placetype":"venue"
},
  "geometry": {"coordinates":[-118.286205,33.85217],"type":"Point"}
}