{
  "type": "Feature",
  "properties": {
    "iso:country":"US",
    "sg:address":"1753 Fawn Glen Cir",
    "sg:city":"Fairfield",
    "sg:classifiers":[
        {
            "category":"Real Estate",
            "subcategory":"Real Estate Agent",
            "type":"Services"
        }
    ],
    "sg:phone":"+1 707 864 9867",
    "sg:postcode":"94534",
    "sg:province":"CA",
    "wof:name":"Oudynarath Sakko",
    "wof:placetype":"venue"
},
  "geometry": {"coordinates":[-122.134795,38.17115],"type":"Point"}
}