{
  "type": "Feature",
  "properties": {
    "addr:full":"20002 N Thornton Rd Lodi CA 95242",
    "addr:housenumber":"20002",
    "addr:postcode":"95242",
    "addr:street":"N Thornton Rd",
    "iso:country":"US",
    "sg:address":"20002 N Thornton Rd",
    "sg:city":"Lodi",
    "sg:classifiers":[
        {
            "category":"Farming",
            "subcategory":"Dairy Farm",
            "type":"Manufacturing & Wholesale Goods"
        }
    ],
    "sg:phone":"+1 209 368 4322",
    "sg:postcode":"95242",
    "sg:province":"CA",
    "wof:name":"Van Exel Dairy",
    "wof:placetype":"venue"
},
  "geometry": {"coordinates":[-121.39920499999999,38.17008],"type":"Point"}
}