{
  "type": "Feature",
  "properties": {
    "addr:full":"2005 Navy Dr Stockton CA 95206",
    "addr:housenumber":"2005",
    "addr:postcode":"95206",
    "addr:street":"Navy Dr",
    "iso:country":"US",
    "sg:address":"2005 Navy Dr",
    "sg:city":"Stockton",
    "sg:classifiers":[
        {
            "category":"Bus Charters",
            "type":"Transportation"
        }
    ],
    "sg:phone":"+1 209 466 4706",
    "sg:postcode":"95206",
    "sg:province":"CA",
    "sg:tags":[
        "rental"
    ],
    "wof:name":"Laidlaw Transit Inc",
    "wof:placetype":"venue"
},
  "geometry": {"coordinates":[-121.317403,37.937541],"type":"Point"}
}