{
  "type": "Feature",
  "properties": {
    "iso:country":"US",
    "sg:address":"5551 Columbia Dr S",
    "sg:city":"Fresno",
    "sg:classifiers":[
        {
            "category":"Building & Trades",
            "subcategory":"Construction",
            "type":"Services"
        }
    ],
    "sg:phone":"+1 559 252 1636",
    "sg:postcode":"93727",
    "sg:province":"CA",
    "sg:tags":[
        "painter"
    ],
    "wof:name":"David Zumkeller Painting",
    "wof:placetype":"venue"
},
  "geometry": {"coordinates":[-119.70559299999999,36.724041],"type":"Point"}
}