{
  "type": "Feature",
  "properties": {
    "iso:country":"US",
    "sg:address":"707 Augusta St",
    "sg:city":"Inglewood",
    "sg:classifiers":[
        {
            "category":"Manufacturing",
            "subcategory":"Buildings",
            "type":"Manufacturing & Wholesale Goods"
        },
        {
            "category":"Home & Garden",
            "subcategory":"Building Materials",
            "type":"Retail Goods"
        },
        {
            "category":"Building & Trades",
            "subcategory":"Locksmith",
            "type":"Services"
        },
        {
            "category":"Manufacturing",
            "subcategory":"Building Materials",
            "type":"Manufacturing & Wholesale Goods"
        },
        {
            "category":"Building & Trades",
            "subcategory":"Construction",
            "type":"Services"
        }
    ],
    "sg:phone":"+1 310 491 7052",
    "sg:postcode":"90302",
    "sg:province":"CA",
    "sg:tags":[
        "repairing",
        "repair",
        "industrial-sales",
        "door",
        "garage",
        "doors-commercial",
        "opener",
        "maintenance",
        "garages-building"
    ],
    "wof:name":"Garage Doors Repairs Inglewood",
    "wof:placetype":"venue"
},
  "geometry": {"coordinates":[-118.368991,33.964333],"type":"Point"}
}