{
  "type": "Feature",
  "properties": {
    "iso:country":"US",
    "sg:address":"11751 Mississippi Ave",
    "sg:city":"Los Angeles",
    "sg:classifiers":[
        {
            "category":"Manufacturing",
            "subcategory":"Metals",
            "type":"Manufacturing & Wholesale Goods"
        }
    ],
    "sg:phone":"+1 310 477 6555",
    "sg:postcode":"90025",
    "sg:province":"CA",
    "sg:tags":[
        "casting"
    ],
    "wof:name":"Debra Kurtz Casting",
    "wof:placetype":"venue"
},
  "geometry": {"coordinates":[-118.450397,34.034801],"type":"Point"}
}