{
  "type": "Feature",
  "properties": {
    "iso:country":"US",
    "sg:address":"17295 Brookhurst St",
    "sg:city":"Fountain Valley",
    "sg:classifiers":[
        {
            "category":"Fast Food",
            "type":"Food & Drink"
        },
        {
            "category":"Restaurant",
            "type":"Food & Drink"
        }
    ],
    "sg:phone":"+1 714 968 3445",
    "sg:postcode":"92708",
    "sg:province":"CA",
    "sg:tags":[
        "mexican"
    ],
    "wof:name":"Del Taco",
    "wof:placetype":"venue"
},
  "geometry": {"coordinates":[-117.954002,33.711498],"type":"Point"}
}