{
  "type": "Feature",
  "properties": {
    "iso:country":"US",
    "sg:address":"18080 Boris Dr",
    "sg:city":"Encino",
    "sg:classifiers":[
        {
            "category":"Manufacturing",
            "subcategory":"Musical Instruments",
            "type":"Manufacturing & Wholesale Goods"
        }
    ],
    "sg:phone":"+1 818 881 2258",
    "sg:postcode":"91316",
    "sg:province":"CA",
    "sg:tags":[
        "mfg"
    ],
    "wof:name":"Bradley Music Co",
    "wof:placetype":"venue"
},
  "geometry": {"coordinates":[-118.526849,34.154314],"type":"Point"}
}