{
  "type": "Feature",
  "properties": {
    "addr:full":"2713 Village Rd Lakewood CA 90712",
    "addr:housenumber":"2713",
    "addr:postcode":"90712",
    "addr:street":"Village Rd",
    "iso:country":"US",
    "sg:address":"2713 Village Rd",
    "sg:city":"Lakewood",
    "sg:classifiers":[
        {
            "category":"Professional",
            "type":"Services"
        }
    ],
    "sg:phone":"+1 562 420 1022",
    "sg:postcode":"90712",
    "sg:province":"CA",
    "wof:name":"Wayne D Rutledge",
    "wof:placetype":"venue"
},
  "geometry": {"coordinates":[-118.159863,33.835055],"type":"Point"}
}