{
  "type": "Feature",
  "properties": {
    "iso:country":"US",
    "sg:address":"233 Cathcart Street",
    "sg:city":"Santa Cruz",
    "sg:classifiers":[
        {
            "category":"Shopping",
            "subcategory":"Florist",
            "type":"Retail Goods"
        }
    ],
    "sg:phone":"+1 831 458 1118",
    "sg:postcode":"95060",
    "sg:province":"CA",
    "sg:website":"www.shaysflowers.com",
    "wof:name":"Shay's Flowers",
    "wof:placetype":"venue"
},
  "geometry": {"coordinates":[-122.02659,36.971488],"type":"Point"}
}