{
  "type": "Feature",
  "properties": {
    "iso:country":"US",
    "sg:address":"19 Serramonte Blvd",
    "sg:city":"Daly City",
    "sg:classifiers":[
        {
            "category":"Real Estate",
            "subcategory":"Real Estate Agent",
            "type":"Services"
        }
    ],
    "sg:phone":"+1 650 758 0288",
    "sg:postcode":"94015",
    "sg:province":"CA",
    "sg:website":"www.prudential.com",
    "wof:name":"Prudential California Realty",
    "wof:placetype":"venue"
},
  "geometry": {"coordinates":[-122.466944,37.669401],"type":"Point"}
}