{
  "type": "Feature",
  "properties": {
    "addr:full":"2500 W el Camino Real Mountain View CA 94040",
    "addr:housenumber":"2500",
    "addr:postcode":"94040",
    "addr:street":"W El Camino Real",
    "iso:country":"US",
    "sg:address":"2500 W el Camino Real",
    "sg:city":"Mountain View",
    "sg:classifiers":[
        {
            "category":"Restaurant",
            "type":"Food & Drink"
        }
    ],
    "sg:phone":"+1 650 941 0220",
    "sg:postcode":"94040",
    "sg:province":"CA",
    "wof:name":"Buenobueno",
    "wof:placetype":"venue"
},
  "geometry": {"coordinates":[-122.11055,37.399671],"type":"Point"}
}