{
  "type": "Feature",
  "properties": {
    "addr:full":"654 Harbor Island Dr Newport Beach CA 92660",
    "addr:housenumber":"654",
    "addr:postcode":"92660",
    "addr:street":"Harbor Island Dr",
    "iso:country":"US",
    "sg:address":"654 Harbor Island Dr",
    "sg:city":"Newport Beach",
    "sg:classifiers":[
        {
            "category":"Professional",
            "type":"Services"
        }
    ],
    "sg:phone":"+1 714 669 0881",
    "sg:postcode":"92660",
    "sg:province":"CA",
    "wof:name":"Carolyn R Nelson Inc",
    "wof:placetype":"venue"
},
  "geometry": {"coordinates":[-117.897355,33.611083],"type":"Point"}
}