{
  "type": "Feature",
  "properties": {
    "iso:country":"US",
    "sg:address":"5450 Morella Ave",
    "sg:city":"Valley Village",
    "sg:classifiers":[
        {
            "category":"Professional",
            "subcategory":"Advertising",
            "type":"Services"
        }
    ],
    "sg:phone":"+1 818 753 8998",
    "sg:postcode":"91607",
    "sg:province":"CA",
    "sg:tags":[
        "representative"
    ],
    "wof:name":"Joe Spinoza Co",
    "wof:placetype":"venue"
},
  "geometry": {"coordinates":[-118.389872,34.169483],"type":"Point"}
}