{
  "type": "Feature",
  "properties": {
    "addr:full":"61 Catalpa Ave Mill Valley CA 94941",
    "addr:housenumber":"61",
    "addr:postcode":"94941",
    "addr:street":"Catalpa Ave",
    "iso:country":"US",
    "sg:address":"61 Catalpa Ave",
    "sg:city":"Mill Valley",
    "sg:classifiers":[
        {
            "category":"Organizations",
            "subcategory":"Non-profit Organization",
            "type":"Services"
        }
    ],
    "sg:phone":"+1 415 383 9657",
    "sg:postcode":"94941",
    "sg:province":"CA",
    "sg:tags":[
        "fund",
        "counselor",
        "raising"
    ],
    "wof:name":"Irwin-Wells Assoc",
    "wof:placetype":"venue"
},
  "geometry": {"coordinates":[-122.53775,37.9029],"type":"Point"}
}