{
  "type": "Feature",
  "properties": {
    "iso:country":"US",
    "sg:address":"24247 Hawthorne Blvd",
    "sg:city":"Torrance",
    "sg:classifiers":[
        {
            "category":"Personal",
            "subcategory":"Beauty Salon",
            "type":"Services"
        }
    ],
    "sg:phone":"+1 310 378 3151",
    "sg:postcode":"90505",
    "sg:province":"CA",
    "sg:tags":[
        "manicuring"
    ],
    "wof:name":"Sara Tran",
    "wof:placetype":"venue"
},
  "geometry": {"coordinates":[-118.351087,33.801875],"type":"Point"}
}