{
  "type": "Feature",
  "properties": {
    "addr:full":"425 N Avenue 64 Los Angeles CA 90042",
    "addr:housenumber":"425;64",
    "addr:postcode":"90042",
    "addr:street":"N Avenue",
    "iso:country":"US",
    "sg:address":"425 N Avenue 64",
    "sg:city":"Los Angeles",
    "sg:classifiers":[
        {
            "category":"Organizations",
            "subcategory":"Religious Organization",
            "type":"Services"
        }
    ],
    "sg:phone":"+1 323 254 3995",
    "sg:postcode":"90042",
    "sg:province":"CA",
    "wof:name":"Redford Courts",
    "wof:placetype":"venue"
},
  "geometry": {"coordinates":[-118.18000000000001,34.117802],"type":"Point"}
}