{
  "type": "Feature",
  "properties": {
    "iso:country":"US",
    "sg:address":"425 Divisadero St",
    "sg:city":"San Francisco",
    "sg:classifiers":[
        {
            "category":"Professional",
            "subcategory":"Accounting & Tax Preparation",
            "type":"Services"
        }
    ],
    "sg:phone":"+1 415 552 7001",
    "sg:postcode":"94117",
    "sg:province":"CA",
    "sg:tags":[
        "return",
        "filing"
    ],
    "sg:website":"www.brianscottcpa.com",
    "wof:name":"Brian H Scott",
    "wof:placetype":"venue"
},
  "geometry": {"coordinates":[-122.437689,37.773821],"type":"Point"}
}