{
  "type": "Feature",
  "properties": {
    "iso:country":"US",
    "sg:address":"2940 16th St",
    "sg:city":"San Francisco",
    "sg:classifiers":[
        {
            "category":"Organizations",
            "subcategory":"Labor Organization",
            "type":"Services"
        }
    ],
    "sg:phone":"+1 415 863 9627",
    "sg:postcode":"94103",
    "sg:province":"CA",
    "wof:name":"Industrial Workers-The World",
    "wof:placetype":"venue"
},
  "geometry": {"coordinates":[-122.41786500000001,37.765247],"type":"Point"}
}