{
  "type": "Feature",
  "properties": {
    "addr:full":"605 Pioneer Dr Glendale CA 91203",
    "addr:housenumber":"605",
    "addr:postcode":"91203",
    "addr:street":"Pioneer Dr",
    "iso:country":"US",
    "sg:address":"605 Pioneer Dr",
    "sg:city":"Glendale",
    "sg:classifiers":[
        {
            "category":"Professional",
            "subcategory":"Business Services",
            "type":"Services"
        }
    ],
    "sg:phone":"+1 818 502 1111",
    "sg:postcode":"91203",
    "sg:province":"CA",
    "sg:tags":[
        "leather",
        "good",
        "mfg"
    ],
    "wof:name":"Seroj Sign",
    "wof:placetype":"venue"
},
  "geometry": {"coordinates":[-118.269233,34.154918],"type":"Point"}
}