{
  "type": "Feature",
  "properties": {
    "iso:country":"US",
    "sg:address":"294 Fox Hills Mall",
    "sg:city":"Culver City",
    "sg:classifiers":[
        {
            "category":"Manufacturing",
            "subcategory":"Leather Goods",
            "type":"Manufacturing & Wholesale Goods"
        }
    ],
    "sg:phone":"+1 310 390 6121",
    "sg:postcode":"90230",
    "sg:province":"CA",
    "wof:name":"Leather Zone",
    "wof:placetype":"venue"
},
  "geometry": {"coordinates":[-118.394895,33.985202],"type":"Point"}
}