{
  "type": "Feature",
  "properties": {
    "iso:country":"US",
    "sg:address":"720 E Michigan Ave",
    "sg:city":"Fresno",
    "sg:classifiers":[
        {
            "category":"Building & Trades",
            "subcategory":"Cleaning & Sanitation",
            "type":"Services"
        }
    ],
    "sg:phone":"+1 559 222 7157",
    "sg:postcode":"93704",
    "sg:province":"CA",
    "sg:tags":[
        "janitor"
    ],
    "wof:name":"A J Janitorial Svc",
    "wof:placetype":"venue"
},
  "geometry": {"coordinates":[-119.80266,36.776662],"type":"Point"}
}