{
  "type": "Feature",
  "properties": {
    "addr:full":"1170 N Hawk Cir Anaheim CA 92807",
    "addr:housenumber":"1170",
    "addr:postcode":"92807",
    "addr:street":"N Hawk Cir",
    "iso:country":"US",
    "sg:address":"1170 N Hawk Cir",
    "sg:city":"Anaheim",
    "sg:classifiers":[
        {
            "category":"Manufacturing",
            "subcategory":"Metals",
            "type":"Manufacturing & Wholesale Goods"
        },
        {
            "category":"Manufacturing",
            "subcategory":"Jewelry",
            "type":"Manufacturing & Wholesale Goods"
        }
    ],
    "sg:phone":"+1 714 632 0200",
    "sg:postcode":"92807",
    "sg:province":"CA",
    "sg:tags":[
        "platinum",
        "buyer",
        "metals-precious",
        "silver",
        "gold"
    ],
    "sg:website":"http://www.technic.com",
    "wof:name":"Technic, Inc.",
    "wof:placetype":"venue"
},
  "geometry": {"coordinates":[-117.834192,33.857215],"type":"Point"}
}