{
  "type": "Feature",
  "properties": {
    "addr:full":"11846 Perris Blvd Moreno Valley CA 92557",
    "addr:housenumber":"11846",
    "addr:postcode":"92557",
    "addr:street":"Perris Blvd",
    "iso:country":"US",
    "sg:address":"11846 Perris Blvd",
    "sg:city":"Moreno Valley",
    "sg:classifiers":[
        {
            "category":"Wholesale",
            "subcategory":"Non-durable Goods",
            "type":"Manufacturing & Wholesale Goods"
        }
    ],
    "sg:phone":"+1 951 242 6742",
    "sg:postcode":"92557",
    "sg:province":"CA",
    "wof:name":"Leisure Enterprises",
    "wof:placetype":"venue"
},
  "geometry": {"coordinates":[-117.22632299999999,33.946704],"type":"Point"}
}