{
  "type": "Feature",
  "properties": {
    "addr:full":"1303 Irwin Ave Escalon CA 95320",
    "addr:housenumber":"1303",
    "addr:postcode":"95320",
    "addr:street":"Irwin Ave",
    "iso:country":"US",
    "sg:address":"1303 Irwin Ave",
    "sg:city":"Escalon",
    "sg:classifiers":[
        {
            "category":"Organizations",
            "subcategory":"Religious Organization",
            "type":"Services"
        }
    ],
    "sg:phone":"+1 209 838 3209",
    "sg:postcode":"95320",
    "sg:province":"CA",
    "sg:tags":[
        "church"
    ],
    "wof:name":"Church Of Christ",
    "wof:placetype":"venue"
},
  "geometry": {"coordinates":[-121.004065,37.798581],"type":"Point"}
}