{
  "type": "Feature",
  "properties": {
    "addr:full":"8020 2nd St Downey CA 90241",
    "addr:housenumber":"8020",
    "addr:postcode":"90241",
    "addr:street":"2Nd St",
    "iso:country":"US",
    "sg:address":"8020 2nd St",
    "sg:city":"Downey",
    "sg:classifiers":[
        {
            "category":"Professional",
            "subcategory":"Lawyer & Legal Services",
            "type":"Services"
        }
    ],
    "sg:phone":"+1 562 923 5650",
    "sg:postcode":"90241",
    "sg:province":"CA",
    "sg:tags":[
        "attorney"
    ],
    "sg:website":"www.acimmigrationlaw.com",
    "wof:name":"Alexandru Cristea Law Offices",
    "wof:placetype":"venue"
},
  "geometry": {"coordinates":[-118.136197,33.942963],"type":"Point"}
}