{
  "type": "Feature",
  "properties": {
    "iso:country":"US",
    "sg:address":"6842 De Soto Ave",
    "sg:city":"Canoga Park",
    "sg:classifiers":[
        {
            "category":"Cinema",
            "subcategory":"Movie Rental",
            "type":"Entertainment"
        }
    ],
    "sg:phone":"+1 818 598 1475",
    "sg:postcode":"91303",
    "sg:province":"CA",
    "sg:tags":[
        "game",
        "video"
    ],
    "wof:name":"Mega Value Video",
    "wof:placetype":"venue"
},
  "geometry": {"coordinates":[-118.587997,34.195499],"type":"Point"}
}