{
  "type": "Feature",
  "properties": {
    "iso:country":"US",
    "sg:address":"6050 W Sunset Blvd",
    "sg:city":"Los Angeles",
    "sg:classifiers":[
        {
            "category":"Professional",
            "subcategory":"Business Services",
            "type":"Services"
        }
    ],
    "sg:phone":"+1 323 467 9375",
    "sg:postcode":"90028",
    "sg:province":"CA",
    "sg:tags":[
        "recording",
        "rehearsal",
        "studio"
    ],
    "sg:website":"www.oceanwayrecording.com",
    "wof:name":"Ocean Way Recording",
    "wof:placetype":"venue"
},
  "geometry": {"coordinates":[-118.32199900000001,34.098099],"type":"Point"}
}