{
  "type": "Feature",
  "properties": {
    "addr:full":"10750 7th St Rancho Cucamonga CA 91730",
    "addr:housenumber":"10750",
    "addr:postcode":"91730",
    "addr:street":"7Th St",
    "iso:country":"US",
    "sg:address":"10750 7th St",
    "sg:city":"Rancho Cucamonga",
    "sg:classifiers":[
        {
            "category":"Wholesale",
            "subcategory":"Drugs",
            "type":"Manufacturing & Wholesale Goods"
        }
    ],
    "sg:phone":"+1 909 394 0067",
    "sg:postcode":"91730",
    "sg:province":"CA",
    "sg:tags":[
        "distributor"
    ],
    "wof:name":"Cardinal Health 100 Inc",
    "wof:placetype":"venue"
},
  "geometry": {"coordinates":[-117.568916,34.088575],"type":"Point"}
}