{
  "type": "Feature",
  "properties": {
    "addr:full":"180 Spruce St San Francisco CA 94118",
    "addr:housenumber":"180",
    "addr:postcode":"94118",
    "addr:street":"Spruce St",
    "iso:country":"US",
    "sg:address":"180 Spruce St",
    "sg:city":"San Francisco",
    "sg:classifiers":[
        {
            "category":"Wholesale",
            "subcategory":"Electrical",
            "type":"Manufacturing & Wholesale Goods"
        }
    ],
    "sg:phone":"+1 415 333 8888",
    "sg:postcode":"94118",
    "sg:province":"CA",
    "sg:tags":[
        "video",
        "disc",
        "tape"
    ],
    "sg:website":"www.taiseng.com",
    "wof:name":"New Image Audio & Video Inc",
    "wof:placetype":"venue"
},
  "geometry": {"coordinates":[-122.45398400000001,37.78983],"type":"Point"}
}