{
  "type": "Feature",
  "properties": {
    "iso:country":"US",
    "sg:address":"526 S. Bascom Ave.",
    "sg:city":"San Jose",
    "sg:classifiers":[
        {
            "category":"Retail",
            "subcategory":"Laundry & Dry Cleaning",
            "type":"Services"
        }
    ],
    "sg:phone":"+1 408 292 4726",
    "sg:postcode":"95128",
    "sg:province":"CA",
    "wof:name":"Ritz Cleaners",
    "wof:placetype":"venue"
},
  "geometry": {"coordinates":[-121.931726,37.31895],"type":"Point"}
}