{
  "type": "Feature",
  "properties": {
    "iso:country":"US",
    "sg:address":"14140 Magnolia Blvd",
    "sg:city":"Sherman Oaks",
    "sg:classifiers":[
        {
            "category":"Health Services",
            "subcategory":"Doctor",
            "type":"Services"
        }
    ],
    "sg:phone":"+1 818 788 0937",
    "sg:postcode":"91423",
    "sg:province":"CA",
    "sg:tags":[
        "surgeon",
        "oral"
    ],
    "wof:name":"Wasserman Robert G DDS",
    "wof:placetype":"venue"
},
  "geometry": {"coordinates":[-118.441002,34.164799],"type":"Point"}
}