{
  "type": "Feature",
  "properties": {
    "iso:country":"US",
    "sg:address":"1105 Higuera St",
    "sg:city":"San Luis Obispo",
    "sg:classifiers":[
        {
            "category":"Banks & Credit Unions",
            "subcategory":"Bank",
            "type":"Services"
        }
    ],
    "sg:phone":"+1 805 595 5339",
    "sg:postcode":"93401",
    "sg:province":"CA",
    "sg:tags":[
        "national",
        "community"
    ],
    "wof:name":"Bank Of America",
    "wof:placetype":"venue"
},
  "geometry": {"coordinates":[-120.657901,35.282706],"type":"Point"}
}