{
  "type": "Feature",
  "properties": {
    "addr:full":"2999 Glascock St Oakland CA 94601",
    "addr:housenumber":"2999",
    "addr:postcode":"94601",
    "addr:street":"Glascock St",
    "iso:country":"US",
    "sg:address":"2999 Glascock St",
    "sg:city":"Oakland",
    "sg:classifiers":[
        {
            "category":"Education",
            "subcategory":"University",
            "type":"Public Place"
        }
    ],
    "sg:phone":"+1 510 261 4648",
    "sg:postcode":"94601",
    "sg:province":"CA",
    "sg:tags":[
        "college"
    ],
    "wof:name":"University of California-Berkeley",
    "wof:placetype":"venue"
},
  "geometry": {"coordinates":[-122.232114,37.77135],"type":"Point"}
}