{
  "type": "Feature",
  "properties": {
    "addr:full":"2426 Fruitridge Rd Sacramento CA 95822",
    "addr:housenumber":"2426",
    "addr:postcode":"95822",
    "addr:street":"Fruitridge Rd",
    "iso:country":"US",
    "sg:address":"2426 Fruitridge Rd",
    "sg:city":"Sacramento",
    "sg:classifiers":[
        {
            "category":"Fast Food",
            "type":"Food & Drink"
        },
        {
            "category":"Restaurant",
            "type":"Food & Drink"
        },
        {
            "category":"Ice Cream",
            "type":"Food & Drink"
        }
    ],
    "sg:phone":"+1 916 427 7915",
    "sg:postcode":"95822",
    "sg:province":"CA",
    "sg:tags":[
        "frozen",
        "traditional",
        "american",
        "yogurt"
    ],
    "sg:website":"www.dairyqueen.com",
    "wof:name":"Dairy Queen",
    "wof:placetype":"venue"
},
  "geometry": {"coordinates":[-121.483002,38.5247],"type":"Point"}
}