{
  "type": "Feature",
  "properties": {
    "iso:country":"US",
    "sg:address":"5051 Canyon Crest Dr",
    "sg:city":"Riverside",
    "sg:classifiers":[
        {
            "category":"Health Services",
            "subcategory":"Doctor",
            "type":"Services"
        }
    ],
    "sg:phone":"+1 951 788 0858",
    "sg:postcode":"92507",
    "sg:province":"CA",
    "sg:tags":[
        "dentist"
    ],
    "wof:name":"Sycamore Dental Practice",
    "wof:placetype":"venue"
},
  "geometry": {"coordinates":[-117.331126,33.959858],"type":"Point"}
}