{
  "type": "Feature",
  "properties": {
    "addr:full":"2510 Airpark Dr Redding CA 96001",
    "addr:housenumber":"2510",
    "addr:postcode":"96001",
    "addr:street":"Airpark Dr",
    "iso:country":"US",
    "sg:address":"2510 Airpark Dr",
    "sg:city":"Redding",
    "sg:classifiers":[
        {
            "category":"Health Services",
            "subcategory":"Doctor",
            "type":"Services"
        }
    ],
    "sg:phone":"+1 530 244 2882",
    "sg:postcode":"96001",
    "sg:province":"CA",
    "sg:tags":[
        "physician",
        "surgeon"
    ],
    "wof:name":"Northern California Surgical",
    "wof:placetype":"venue"
},
  "geometry": {"coordinates":[-122.401346,40.571149],"type":"Point"}
}