{
  "type": "Feature",
  "properties": {
    "iso:country":"US",
    "sg:address":"945 22nd Ave",
    "sg:city":"Oakland",
    "sg:classifiers":[
        {
            "category":"Real Estate",
            "subcategory":"Architect",
            "type":"Services"
        }
    ],
    "sg:phone":"+1 510 536 2896",
    "sg:postcode":"94606",
    "sg:province":"CA",
    "wof:name":"Hope Architects",
    "wof:placetype":"venue"
},
  "geometry": {"coordinates":[-122.24209399999999,37.780801],"type":"Point"}
}