{
  "type": "Feature",
  "properties": {
    "addr:full":"4713 Santorini Dr Cypress CA 90630",
    "addr:housenumber":"4713",
    "addr:postcode":"90630",
    "addr:street":"Santorini Dr",
    "iso:country":"US",
    "sg:address":"4713 Santorini Dr",
    "sg:city":"Cypress",
    "sg:classifiers":[
        {
            "category":"Health Services",
            "subcategory":"Clinic",
            "type":"Services"
        },
        {
            "category":"Community Center",
            "type":"Public Place"
        }
    ],
    "sg:phone":"+1 714 761 1748",
    "sg:postcode":"90630",
    "sg:province":"CA",
    "sg:tags":[
        "medical"
    ],
    "wof:name":"Robby T. Ayoub, M.D., Prof. Medical Corp.",
    "wof:placetype":"venue"
},
  "geometry": {"coordinates":[-118.05149299999999,33.821474],"type":"Point"}
}