{
  "type": "Feature",
  "properties": {
    "iso:country":"US",
    "sg:address":"8363 Center Dr Ste 6H",
    "sg:city":"La Mesa",
    "sg:classifiers":[
        {
            "category":"Retail",
            "subcategory":"Auto Rental",
            "type":"Services"
        }
    ],
    "sg:phone":"+1 619 698 2505",
    "sg:postcode":"91942",
    "sg:province":"CA",
    "sg:tags":[
        "car"
    ],
    "sg:website":"www.enterprise.com",
    "wof:name":"Enterprise Rent-a-Car",
    "wof:placetype":"venue"
},
  "geometry": {"coordinates":[-117.01749599999999,32.775009],"type":"Point"}
}