{
  "type": "Feature",
  "properties": {
    "addr:full":"371 Windsor River Rd Windsor CA 95492",
    "addr:housenumber":"371",
    "addr:postcode":"95492",
    "addr:street":"Windsor River Rd",
    "iso:country":"US",
    "sg:address":"371 Windsor River Rd",
    "sg:city":"Windsor",
    "sg:classifiers":[
        {
            "category":"Real Estate",
            "subcategory":"Real Estate Agent",
            "type":"Services"
        }
    ],
    "sg:phone":"+1 707 837 7800",
    "sg:postcode":"95492",
    "sg:province":"CA",
    "wof:name":"Remax Central-Windsor",
    "wof:placetype":"venue"
},
  "geometry": {"coordinates":[-122.816598,38.547328],"type":"Point"}
}