{
  "type": "Feature",
  "properties": {
    "addr:full":"271 Walnut St San Bruno CA 94066",
    "addr:housenumber":"271",
    "addr:postcode":"94066",
    "addr:street":"Walnut St",
    "iso:country":"US",
    "sg:address":"271 Walnut St",
    "sg:city":"San Bruno",
    "sg:classifiers":[
        {
            "category":"Manufacturing",
            "subcategory":"Furniture",
            "type":"Manufacturing & Wholesale Goods"
        }
    ],
    "sg:phone":"+1 650 583 1925",
    "sg:postcode":"94066",
    "sg:province":"CA",
    "sg:tags":[
        "fixture",
        "mfg"
    ],
    "wof:name":"Cantwell Associates",
    "wof:placetype":"venue"
},
  "geometry": {"coordinates":[-122.411016,37.632734],"type":"Point"}
}