{
  "type": "Feature",
  "properties": {
    "iso:country":"US",
    "sg:address":"926 J St Inside Citizen Hotel",
    "sg:city":"Sacramento",
    "sg:classifiers":[
        {
            "category":"Restaurant",
            "type":"Food & Drink"
        }
    ],
    "sg:phone":"+1 916 492 4400",
    "sg:postcode":"95814",
    "sg:province":"CA",
    "sg:tags":[
        "new",
        "american"
    ],
    "sg:website":"grangesacramento.com",
    "wof:name":"Grange Restaurant & Bar",
    "wof:placetype":"venue"
},
  "geometry": {"coordinates":[-121.493904,38.580112],"type":"Point"}
}