{
  "type": "Feature",
  "properties": {
    "iso:country":"US",
    "sg:address":"7312 Shepard Mesa Dr",
    "sg:city":"Carpinteria",
    "sg:classifiers":[
        {
            "category":"Building & Trades",
            "subcategory":"Construction",
            "type":"Services"
        }
    ],
    "sg:phone":"+1 805 684 1678",
    "sg:postcode":"93013",
    "sg:province":"CA",
    "sg:tags":[
        "excavating",
        "contractor"
    ],
    "wof:name":"Danny Howe Excavating",
    "wof:placetype":"venue"
},
  "geometry": {"coordinates":[-119.469024,34.399342],"type":"Point"}
}