{
  "type": "Feature",
  "properties": {
    "addr:full":"8953 Woodman Ave Arleta CA 91331",
    "addr:housenumber":"8953",
    "addr:postcode":"91331",
    "addr:street":"Woodman Ave",
    "iso:country":"US",
    "sg:address":"8953 Woodman Ave",
    "sg:city":"Arleta",
    "sg:classifiers":[
        {
            "category":"Professional",
            "subcategory":"Employment Agencies",
            "type":"Services"
        }
    ],
    "sg:phone":"+1 818 893 6747",
    "sg:postcode":"91331",
    "sg:province":"CA",
    "sg:tags":[
        "leasing"
    ],
    "wof:name":"Unlimited Labor Professionals",
    "wof:placetype":"venue"
},
  "geometry": {"coordinates":[-118.437136,34.230375],"type":"Point"}
}