{
  "type": "Feature",
  "properties": {
    "addr:full":"5532 Shattuck Ave Oakland CA 94609",
    "addr:housenumber":"5532",
    "addr:postcode":"94609",
    "addr:street":"Shattuck Ave",
    "iso:country":"US",
    "sg:address":"5532 Shattuck Ave",
    "sg:city":"Oakland",
    "sg:classifiers":[
        {
            "category":"Arts & Performance",
            "subcategory":"Art Gallery",
            "type":"Entertainment"
        }
    ],
    "sg:postcode":"94609",
    "sg:province":"CA",
    "sg:website":"www.marboegreengallery.com",
    "wof:name":"mg Gallery",
    "wof:placetype":"venue"
},
  "geometry": {"coordinates":[-122.264398,37.841079],"type":"Point"}
}