{
  "type": "Feature",
  "properties": {
    "addr:full":"1920 S Catalina Ave Redondo Beach CA 90277",
    "addr:housenumber":"1920",
    "addr:postcode":"90277",
    "addr:street":"S Catalina Ave",
    "iso:country":"US",
    "sg:address":"1920 S Catalina Ave",
    "sg:city":"Redondo Beach",
    "sg:classifiers":[
        {
            "category":"Autos & Motor Vehicles",
            "subcategory":"Fuel & Gas Station",
            "type":"Retail Goods"
        }
    ],
    "sg:phone":"+1 310 375 2001",
    "sg:postcode":"90277",
    "sg:province":"CA",
    "sg:tags":[
        "oil"
    ],
    "wof:name":"Walton's Automotive",
    "wof:placetype":"venue"
},
  "geometry": {"coordinates":[-118.386618,33.815645],"type":"Point"}
}