{
  "type": "Feature",
  "properties": {
    "addr:full":"1770 N Ventura Ave Ventura CA 93001",
    "addr:housenumber":"1770",
    "addr:postcode":"93001",
    "addr:street":"N Ventura Ave",
    "iso:country":"US",
    "sg:address":"1770 N Ventura Ave",
    "sg:city":"Ventura",
    "sg:classifiers":[
        {
            "category":"Wholesale",
            "subcategory":"Machinery & Supplies",
            "type":"Manufacturing & Wholesale Goods"
        }
    ],
    "sg:phone":"+1 805 653 1711",
    "sg:postcode":"93001",
    "sg:province":"CA",
    "sg:tags":[
        "tubing",
        "hose",
        "plastic"
    ],
    "wof:name":"Don's Industrial Supplies Inc",
    "wof:placetype":"venue"
},
  "geometry": {"coordinates":[-119.295526,34.298393],"type":"Point"}
}