{
  "type": "Feature",
  "properties": {
    "addr:full":"5332 S Broadway Los Angeles CA 90037",
    "addr:housenumber":"5332",
    "addr:postcode":"90037",
    "addr:street":"S Broadway",
    "iso:country":"US",
    "sg:address":"5332 S Broadway",
    "sg:city":"Los Angeles",
    "sg:classifiers":[
        {
            "category":"Shopping",
            "subcategory":"Computers & Home Electronics",
            "type":"Retail Goods"
        }
    ],
    "sg:phone":"+1 323 235 1959",
    "sg:postcode":"90037",
    "sg:province":"CA",
    "sg:tags":[
        "television",
        "radio"
    ],
    "wof:name":"Mike TV Svc",
    "wof:placetype":"venue"
},
  "geometry": {"coordinates":[-118.278228,33.993603],"type":"Point"}
}