{
  "type": "Feature",
  "properties": {
    "iso:country":"US",
    "sg:address":"310 Arroyo Dr",
    "sg:city":"Encinitas",
    "sg:classifiers":[
        {
            "category":"Building & Trades",
            "subcategory":"Construction",
            "type":"Services"
        }
    ],
    "sg:phone":"+1 760 753 1576",
    "sg:postcode":"92024",
    "sg:province":"CA",
    "sg:tags":[
        "contractor"
    ],
    "wof:name":"Rotscheck Construction",
    "wof:placetype":"venue"
},
  "geometry": {"coordinates":[-117.29300499999999,33.051481],"type":"Point"}
}