{
  "type": "Feature",
  "properties": {
    "iso:country":"US",
    "sg:address":"1420 4th St",
    "sg:city":"San Fernando",
    "sg:classifiers":[
        {
            "category":"Organizations",
            "subcategory":"Religious Organization",
            "type":"Services"
        }
    ],
    "sg:phone":"+1 818 361 6360",
    "sg:postcode":"91340",
    "sg:province":"CA",
    "sg:tags":[
        "church"
    ],
    "wof:name":"Church Of The Nazarene",
    "wof:placetype":"venue"
},
  "geometry": {"coordinates":[-118.43973,34.289034],"type":"Point"}
}