{
  "type": "Feature",
  "properties": {
    "addr:full":"245 S Los Robles Ave Pasadena CA 91101",
    "addr:housenumber":"245",
    "addr:postcode":"91101",
    "addr:street":"S Los Robles Ave",
    "iso:country":"US",
    "sg:address":"245 S Los Robles Ave",
    "sg:city":"Pasadena",
    "sg:classifiers":[
        {
            "category":"Banks & Credit Unions",
            "subcategory":"Investment Brokerage",
            "type":"Services"
        }
    ],
    "sg:phone":"+1 626 397 9072",
    "sg:postcode":"91101",
    "sg:province":"CA",
    "sg:tags":[
        "advisory",
        "financial"
    ],
    "wof:name":"Robert Bender & Assocs",
    "wof:placetype":"venue"
},
  "geometry": {"coordinates":[-118.141445,34.140796],"type":"Point"}
}