{
  "type": "Feature",
  "properties": {
    "iso:country":"US",
    "sg:address":"5610 Cypress Ave",
    "sg:city":"Carmichael",
    "sg:classifiers":[
        {
            "category":"Home & Garden",
            "subcategory":"Building Materials",
            "type":"Retail Goods"
        }
    ],
    "sg:phone":"+1 916 422 5080",
    "sg:postcode":"95608",
    "sg:province":"CA",
    "sg:tags":[
        "door"
    ],
    "wof:name":"Armstrong Garage Door Svc",
    "wof:placetype":"venue"
},
  "geometry": {"coordinates":[-121.330556,38.63883],"type":"Point"}
}