{
  "type": "Feature",
  "properties": {
    "addr:full":"440 Western Ave Glendale CA 91201",
    "addr:housenumber":"440",
    "addr:postcode":"91201",
    "addr:street":"Western Ave",
    "iso:country":"US",
    "sg:address":"440 Western Ave",
    "sg:city":"Glendale",
    "sg:classifiers":[
        {
            "category":"Insurance",
            "subcategory":"Insurance Agent",
            "type":"Services"
        }
    ],
    "sg:phone":"+1 818 242 2900",
    "sg:postcode":"91201",
    "sg:province":"CA",
    "wof:name":"Larry Pinching Insurance",
    "wof:placetype":"venue"
},
  "geometry": {"coordinates":[-118.29923100000001,34.16184],"type":"Point"}
}