{
  "type": "Feature",
  "properties": {
    "iso:country":"US",
    "sg:address":"2921 W Central Ave",
    "sg:city":"Santa Ana",
    "sg:classifiers":[
        {
            "category":"Building & Trades",
            "subcategory":"Electrical",
            "type":"Services"
        }
    ],
    "sg:phone":"+1 714 437 5252",
    "sg:postcode":"92704",
    "sg:province":"CA",
    "sg:tags":[
        "electric",
        "contractor"
    ],
    "wof:name":"EMC Electrical Maintenance",
    "wof:placetype":"venue"
},
  "geometry": {"coordinates":[-117.909093,33.712806],"type":"Point"}
}