{
  "type": "Feature",
  "properties": {
    "addr:full":"3311 Folsom Blvd Sacramento CA 95816",
    "addr:housenumber":"3311",
    "addr:postcode":"95816",
    "addr:street":"Folsom Blvd",
    "iso:country":"US",
    "sg:address":"3311 Folsom Blvd",
    "sg:city":"Sacramento",
    "sg:classifiers":[
        {
            "category":"Shopping",
            "subcategory":"Optician",
            "type":"Retail Goods"
        }
    ],
    "sg:phone":"+1 916 731 4393",
    "sg:postcode":"95816",
    "sg:province":"CA",
    "sg:tags":[
        "eyewear"
    ],
    "wof:name":"Twenty-Twenty Eyes",
    "wof:placetype":"venue"
},
  "geometry": {"coordinates":[-121.46399700000001,38.5676],"type":"Point"}
}