{
  "type": "Feature",
  "properties": {
    "iso:country":"US",
    "sg:address":"5 Aurora Dr",
    "sg:city":"Rolling Hls Ests",
    "sg:classifiers":[
        {
            "category":"Professional",
            "subcategory":"Management & Consulting",
            "type":"Services"
        }
    ],
    "sg:phone":"+1 310 530 9310",
    "sg:postcode":"90274",
    "sg:province":"CA",
    "sg:tags":[
        "consultant",
        "business"
    ],
    "wof:name":"Operation Productions Group",
    "wof:placetype":"venue"
},
  "geometry": {"coordinates":[-118.318708,33.778799],"type":"Point"}
}