{
  "type": "Feature",
  "properties": {
    "iso:country":"US",
    "sg:address":"235 Baldwin Ave",
    "sg:city":"San Mateo",
    "sg:classifiers":[
        {
            "category":"Retail",
            "subcategory":"Laundry & Dry Cleaning",
            "type":"Services"
        }
    ],
    "sg:phone":"+1 650 343 8793",
    "sg:postcode":"94401",
    "sg:province":"CA",
    "wof:name":"Sunrise Cleaners",
    "wof:placetype":"venue"
},
  "geometry": {"coordinates":[-122.325996,37.566799],"type":"Point"}
}