{
  "type": "Feature",
  "properties": {
    "iso:country":"US",
    "sg:address":"1280 Palmyrita Ave",
    "sg:city":"Riverside",
    "sg:classifiers":[
        {
            "category":"Wholesale",
            "subcategory":"Furniture",
            "type":"Manufacturing & Wholesale Goods"
        }
    ],
    "sg:phone":"+1 951 788 1632",
    "sg:postcode":"92507",
    "sg:province":"CA",
    "wof:name":"Trappings Too",
    "wof:placetype":"venue"
},
  "geometry": {"coordinates":[-117.334713,34.004735],"type":"Point"}
}