{
  "type": "Feature",
  "properties": {
    "addr:full":"1206 Country Estates Dr Vista CA 92084",
    "addr:housenumber":"1206",
    "addr:postcode":"92084",
    "addr:street":"Country Estates Dr",
    "iso:country":"US",
    "sg:address":"1206 Country Estates Dr",
    "sg:city":"Vista",
    "sg:classifiers":[
        {
            "category":"Manufacturing",
            "subcategory":"Tools & Machinery",
            "type":"Manufacturing & Wholesale Goods"
        }
    ],
    "sg:phone":"+1 760 726 1216",
    "sg:postcode":"92084",
    "sg:province":"CA",
    "sg:tags":[
        "orthodontic",
        "appliance",
        "mfg"
    ],
    "wof:name":"O D P",
    "wof:placetype":"venue"
},
  "geometry": {"coordinates":[-117.22303700000001,33.230908],"type":"Point"}
}