{
  "type": "Feature",
  "properties": {
    "addr:full":"3900 Viale Ave Eureka CA 95503",
    "addr:postcode":"95503",
    "addr:street":"Viale Ave",
    "iso:country":"US",
    "sg:address":"3900 Viale Ave",
    "sg:city":"Eureka",
    "sg:classifiers":[
        {
            "category":"Manufacturing",
            "subcategory":"Tools & Machinery",
            "type":"Manufacturing & Wholesale Goods"
        }
    ],
    "sg:phone":"+1 707 442 8306",
    "sg:postcode":"95503",
    "sg:province":"CA",
    "sg:tags":[
        "industrial",
        "mfg"
    ],
    "wof:name":"Wilson Machine",
    "wof:placetype":"venue"
},
  "geometry": {"coordinates":[-124.123757,40.780835],"type":"Point"}
}