{
  "type": "Feature",
  "properties": {
    "addr:full":"51 E Campbell Ave Campbell CA 95008",
    "addr:housenumber":"51 e",
    "addr:postcode":"95008",
    "addr:street":"Campbell Ave",
    "iso:country":"US",
    "sg:address":"51 E Campbell Ave",
    "sg:city":"Campbell",
    "sg:classifiers":[
        {
            "category":"Personal",
            "subcategory":"Beauty Salon",
            "type":"Services"
        }
    ],
    "sg:phone":"+1 408 376 4550",
    "sg:postcode":"95008",
    "sg:province":"CA",
    "wof:name":"Neutrogena",
    "wof:placetype":"venue"
},
  "geometry": {"coordinates":[-121.94903100000001,37.287095],"type":"Point"}
}