{
  "type": "Feature",
  "properties": {
    "iso:country":"US",
    "sg:address":"414 W Ridgecrest Blvd",
    "sg:city":"Ridgecrest",
    "sg:classifiers":[
        {
            "category":"Home & Garden",
            "subcategory":"Furniture",
            "type":"Retail Goods"
        }
    ],
    "sg:phone":"+1 760 375 4800",
    "sg:postcode":"93555",
    "sg:province":"CA",
    "sg:tags":[
        "store"
    ],
    "sg:website":"http://www.ashleyfurniturehomestore.com/",
    "wof:name":"Mpb Furniture Corporation",
    "wof:placetype":"venue"
},
  "geometry": {"coordinates":[-117.675792,35.622493],"type":"Point"}
}