{
  "type": "Feature",
  "properties": {
    "iso:country":"US",
    "sg:address":"4626 Willow Rd",
    "sg:city":"Pleasanton",
    "sg:classifiers":[
        {
            "category":"Health Services",
            "subcategory":"Clinic",
            "type":"Services"
        }
    ],
    "sg:phone":"+1 925 227 1306",
    "sg:postcode":"94588",
    "sg:province":"CA",
    "sg:tags":[
        "welfare"
    ],
    "wof:name":"Pacific Medical Orthotics And Prosthetics",
    "wof:placetype":"venue"
},
  "geometry": {"coordinates":[-121.898292,37.692677],"type":"Point"}
}