{
  "type": "Feature",
  "properties": {
    "iso:country":"US",
    "sg:address":"1301 26th St",
    "sg:city":"Oakland",
    "sg:classifiers":[
        {
            "category":"Freight",
            "type":"Transportation"
        }
    ],
    "sg:phone":"+1 510 465 6010",
    "sg:postcode":"94607",
    "sg:province":"CA",
    "sg:tags":[
        "warehouse",
        "storage"
    ],
    "wof:name":"Saroni Co",
    "wof:placetype":"venue"
},
  "geometry": {"coordinates":[-122.28724099999999,37.819741],"type":"Point"}
}