{
  "type": "Feature",
  "properties": {
    "addr:full":"43 Corporate Park Irvine CA 92606",
    "addr:housenumber":"43",
    "addr:postcode":"92606",
    "addr:street":"Corporate Park",
    "iso:country":"US",
    "sg:address":"43 Corporate Park",
    "sg:city":"Irvine",
    "sg:classifiers":[
        {
            "category":"Real Estate",
            "subcategory":"Architect",
            "type":"Services"
        }
    ],
    "sg:phone":"+1 949 752 0728",
    "sg:postcode":"92606",
    "sg:province":"CA",
    "wof:name":"Jallali Griffin Architects",
    "wof:placetype":"venue"
},
  "geometry": {"coordinates":[-117.82556,33.691797],"type":"Point"}
}