{
  "type": "Feature",
  "properties": {
    "iso:country":"US",
    "sg:address":"31360 Via Colinas",
    "sg:city":"Westlake Village",
    "sg:classifiers":[
        {
            "category":"Wholesale",
            "subcategory":"Electrical",
            "type":"Manufacturing & Wholesale Goods"
        }
    ],
    "sg:phone":"+1 818 865 8861",
    "sg:postcode":"91362",
    "sg:province":"CA",
    "sg:tags":[
        "equipment",
        "electronic",
        "supply"
    ],
    "sg:website":"www.telecomintl.com",
    "wof:name":"Telecom International",
    "wof:placetype":"venue"
},
  "geometry": {"coordinates":[-118.806398,34.157055],"type":"Point"}
}