{
  "type": "Feature",
  "properties": {
    "addr:full":"10621 Burbank Blvd North Hollywood CA 91601",
    "addr:housenumber":"10621",
    "addr:postcode":"91601",
    "addr:street":"Burbank Blvd",
    "iso:country":"US",
    "sg:address":"10621 Burbank Blvd",
    "sg:city":"North Hollywood",
    "sg:classifiers":[
        {
            "category":"Manufacturing",
            "subcategory":"Apparel",
            "type":"Manufacturing & Wholesale Goods"
        }
    ],
    "sg:phone":"+1 818 769 0665",
    "sg:postcode":"91601",
    "sg:province":"CA",
    "sg:tags":[
        "sewing",
        "alteration"
    ],
    "wof:name":"Embroidery Monogram",
    "wof:placetype":"venue"
},
  "geometry": {"coordinates":[-118.36199999999999,34.1721],"type":"Point"}
}