{
  "type": "Feature",
  "properties": {
    "addr:full":"15425 Vanowen St Van Nuys CA 91406",
    "addr:housenumber":"15425",
    "addr:postcode":"91406",
    "addr:street":"Vanowen St",
    "iso:country":"US",
    "sg:address":"15425 Vanowen St",
    "sg:city":"Van Nuys",
    "sg:classifiers":[
        {
            "category":"Real Estate",
            "subcategory":"Real Estate Operator",
            "type":"Services"
        }
    ],
    "sg:phone":"+1 818 779 1122",
    "sg:postcode":"91406",
    "sg:province":"CA",
    "sg:tags":[
        "apartment"
    ],
    "wof:name":"Morsh Property Management",
    "wof:placetype":"venue"
},
  "geometry": {"coordinates":[-118.468705,34.19399],"type":"Point"}
}