{
  "type": "Feature",
  "properties": {
    "addr:full":"443 Dutton Ave Santa Rosa CA 95407",
    "addr:housenumber":"443",
    "addr:postcode":"95407",
    "addr:street":"Dutton Ave",
    "iso:country":"US",
    "sg:address":"443 Dutton Ave",
    "sg:city":"Santa Rosa",
    "sg:classifiers":[
        {
            "category":"Shopping",
            "subcategory":"Gifts & Souvenirs",
            "type":"Retail Goods"
        }
    ],
    "sg:phone":"+1 707 575 5633",
    "sg:postcode":"95407",
    "sg:province":"CA",
    "wof:name":"Pt Co",
    "wof:placetype":"venue"
},
  "geometry": {"coordinates":[-122.725549,38.431134],"type":"Point"}
}