{
  "type": "Feature",
  "properties": {
    "addr:full":"7761 Greenback Ln Citrus Heights CA 95610",
    "addr:housenumber":"7761",
    "addr:postcode":"95610",
    "addr:street":"Greenback Ln",
    "iso:country":"US",
    "sg:address":"7761 Greenback Ln",
    "sg:city":"Citrus Heights",
    "sg:classifiers":[
        {
            "category":"Real Estate",
            "subcategory":"Real Estate Operator",
            "type":"Services"
        }
    ],
    "sg:phone":"+1 916 721 1847",
    "sg:postcode":"95610",
    "sg:province":"CA",
    "sg:tags":[
        "apartment"
    ],
    "wof:name":"Spring Creek Apartments",
    "wof:placetype":"venue"
},
  "geometry": {"coordinates":[-121.276726,38.678321],"type":"Point"}
}