{
  "type": "Feature",
  "properties": {
    "iso:country":"US",
    "sg:address":"6455 Independence Ave",
    "sg:city":"Woodland Hills",
    "sg:classifiers":[
        {
            "category":"Manufacturing",
            "subcategory":"Electronics",
            "type":"Manufacturing & Wholesale Goods"
        }
    ],
    "sg:phone":"+1 818 340 4898",
    "sg:postcode":"91367",
    "sg:province":"CA",
    "sg:tags":[
        "high",
        "laser",
        "power",
        "mfg"
    ],
    "wof:name":"Principia Lightworks Inc",
    "wof:placetype":"venue"
},
  "geometry": {"coordinates":[-118.59068600000001,34.187644],"type":"Point"}
}