{
  "type": "Feature",
  "properties": {
    "iso:country":"US",
    "sg:address":"137 Chesterfield Dr",
    "sg:city":"Cardiff",
    "sg:classifiers":[
        {
            "category":"Retail",
            "subcategory":"Repair Shop",
            "type":"Services"
        }
    ],
    "sg:phone":"+1 760 436 6655",
    "sg:postcode":"92007",
    "sg:province":"CA",
    "sg:tags":[
        "reupholstery",
        "upholsterer",
        "furniture"
    ],
    "wof:name":"Seaside Upholstery",
    "wof:placetype":"venue"
},
  "geometry": {"coordinates":[-117.280998,33.02],"type":"Point"}
}