{
  "type": "Feature",
  "properties": {
    "iso:country":"US",
    "sg:address":"5 Corporate Park Suite 268",
    "sg:city":"Irvine",
    "sg:classifiers":[
        {
            "category":"Utilities",
            "type":"Services"
        }
    ],
    "sg:phone":"+1 949 752 6368",
    "sg:postcode":"92606",
    "sg:province":"CA",
    "sg:tags":[
        "provider",
        "internet"
    ],
    "sg:website":"www.e2020.com",
    "wof:name":"E 2020 Technology",
    "wof:placetype":"venue"
},
  "geometry": {"coordinates":[-117.82796999999999,33.690982],"type":"Point"}
}