{
  "type": "Feature",
  "properties": {
    "addr:full":"2 N 2nd St San Jose CA 95113",
    "addr:housenumber":"2",
    "addr:postcode":"95113",
    "addr:street":"N 2Nd St",
    "iso:country":"US",
    "sg:address":"2 N 2nd St",
    "sg:city":"San Jose",
    "sg:classifiers":[
        {
            "category":"Professional",
            "subcategory":"Lawyer & Legal Services",
            "type":"Services"
        }
    ],
    "sg:phone":"+1 408 998 4123",
    "sg:postcode":"95113",
    "sg:province":"CA",
    "sg:tags":[
        "divorce",
        "law",
        "family"
    ],
    "wof:name":"Brock Barbara J Atty",
    "wof:placetype":"venue"
},
  "geometry": {"coordinates":[-121.889,37.3326],"type":"Point"}
}