{
  "type": "Feature",
  "properties": {
    "iso:country":"US",
    "sg:address":"7812 Broadway",
    "sg:city":"Lemon Grove",
    "sg:classifiers":[
        {
            "category":"Personal",
            "subcategory":"Nail Salon",
            "type":"Services"
        }
    ],
    "sg:phone":"+1 619 466 4643",
    "sg:postcode":"91945",
    "sg:province":"CA",
    "wof:name":"Vans Nail's",
    "wof:placetype":"venue"
},
  "geometry": {"coordinates":[-117.03013900000001,32.742798],"type":"Point"}
}