{
  "type": "Feature",
  "properties": {
    "addr:full":"7860 Golden Ave Lemon Grove CA 91945",
    "addr:housenumber":"7860",
    "addr:postcode":"91945",
    "addr:street":"Golden Ave",
    "iso:country":"US",
    "sg:address":"7860 Golden Ave",
    "sg:city":"Lemon Grove",
    "sg:classifiers":[
        {
            "category":"Professional",
            "type":"Services"
        }
    ],
    "sg:phone":"+1 619 698 5064",
    "sg:postcode":"91945",
    "sg:province":"CA",
    "sg:tags":[
        "establishment"
    ],
    "wof:name":"Community Options",
    "wof:placetype":"venue"
},
  "geometry": {"coordinates":[-117.03049300000001,32.742022],"type":"Point"}
}