{
  "type": "Feature",
  "properties": {
    "iso:country":"US",
    "sg:address":"26 South Raymond Avenue",
    "sg:city":"Pasadena",
    "sg:classifiers":[
        {
            "category":"Shopping",
            "subcategory":"Clothing, Apparel, & Fashions",
            "type":"Retail Goods"
        }
    ],
    "sg:phone":"+1 626 568 8090",
    "sg:postcode":"91105",
    "sg:province":"CA",
    "sg:tags":[
        "clothing",
        "women's"
    ],
    "wof:name":"Lulu Brandt",
    "wof:placetype":"venue"
},
  "geometry": {"coordinates":[-118.14886799999999,34.14518],"type":"Point"}
}