{
  "type": "Feature",
  "properties": {
    "iso:country":"US",
    "sg:address":"8138 Aspen Mall",
    "sg:city":"California City",
    "sg:classifiers":[
        {
            "category":"Sports & Exercise",
            "subcategory":"Gym",
            "type":"Entertainment"
        }
    ],
    "sg:phone":"+1 760 373 1348",
    "sg:postcode":"93505",
    "sg:province":"CA",
    "sg:tags":[
        "club",
        "health",
        "studio",
        "gymnasium"
    ],
    "wof:name":"Cal City Fitness Ctr",
    "wof:placetype":"venue"
},
  "geometry": {"coordinates":[-117.982996,35.123929],"type":"Point"}
}