{
  "type": "Feature",
  "properties": {
    "iso:country":"US",
    "sg:address":"74760 Hwy 111",
    "sg:city":"Indian Wells",
    "sg:classifiers":[
        {
            "category":"Professional",
            "subcategory":"Employment Agencies",
            "type":"Services"
        }
    ],
    "sg:phone":"+1 760 836 1877",
    "sg:postcode":"92210",
    "sg:province":"CA",
    "sg:tags":[
        "opportunity"
    ],
    "wof:name":"Officeteam",
    "wof:placetype":"venue"
},
  "geometry": {"coordinates":[-116.359697,33.721445],"type":"Point"}
}