{
  "type": "Feature",
  "properties": {
    "addr:full":"25517 National Trails Hwy Helendale CA 92342",
    "addr:housenumber":"25517",
    "addr:postcode":"92342",
    "addr:street":"National Trails Hwy",
    "iso:country":"US",
    "sg:address":"25517 National Trails Hwy",
    "sg:city":"Helendale",
    "sg:classifiers":[
        {
            "category":"Retail",
            "subcategory":"Repair Shop",
            "type":"Services"
        }
    ],
    "sg:phone":"+1 760 245 1678",
    "sg:postcode":"92342",
    "sg:province":"CA",
    "sg:tags":[
        "welding"
    ],
    "wof:name":"American Welding Shop",
    "wof:placetype":"venue"
},
  "geometry": {"coordinates":[-117.332826,34.714833],"type":"Point"}
}