{
  "type": "Feature",
  "properties": {
    "iso:country":"US",
    "sg:address":"1235 Highland Ave",
    "sg:city":"Duarte",
    "sg:classifiers":[
        {
            "category":"Home & Garden",
            "subcategory":"Household Appliances",
            "type":"Retail Goods"
        },
        {
            "category":"Building & Trades",
            "subcategory":"Plumbing",
            "type":"Services"
        },
        {
            "category":"Building & Trades",
            "subcategory":"Construction",
            "type":"Services"
        }
    ],
    "sg:phone":"+1 626 305 0126",
    "sg:postcode":"91010",
    "sg:province":"CA",
    "sg:tags":[
        "repair",
        "plumber",
        "industrial",
        "dishwashing",
        "specialty",
        "system",
        "machine",
        "heating",
        "contractor",
        "air conditioning",
        "contractors-commercial"
    ],
    "wof:name":"Mike Diamond",
    "wof:placetype":"venue"
},
  "geometry": {"coordinates":[-117.966634,34.139244],"type":"Point"}
}