{
  "type": "Feature",
  "properties": {
    "iso:country":"US",
    "sg:address":"3616 E 1st Street",
    "sg:city":"Los Angeles",
    "sg:classifiers":[
        {
            "category":"Health Services",
            "subcategory":"Doctor",
            "type":"Services"
        }
    ],
    "sg:phone":"+1 323 264 6157",
    "sg:postcode":"90063",
    "sg:province":"CA",
    "sg:tags":[
        "podiatrist"
    ],
    "wof:name":"Halperin Gabriel J",
    "wof:placetype":"venue"
},
  "geometry": {"coordinates":[-118.188374,34.035897],"type":"Point"}
}