{
  "type": "Feature",
  "properties": {
    "addr:full":"3537 Lynne Way Sacramento CA 95821",
    "addr:housenumber":"3537",
    "addr:postcode":"95821",
    "addr:street":"Lynne Way",
    "iso:country":"US",
    "sg:address":"3537 Lynne Way",
    "sg:city":"Sacramento",
    "sg:classifiers":[
        {
            "category":"Retail",
            "subcategory":"Animal Services",
            "type":"Services"
        }
    ],
    "sg:phone":"+1 916 451 7387",
    "sg:postcode":"95821",
    "sg:province":"CA",
    "sg:tags":[
        "pet",
        "boarding",
        "sitting"
    ],
    "wof:name":"Pet Pals",
    "wof:placetype":"venue"
},
  "geometry": {"coordinates":[-121.38175200000001,38.625268],"type":"Point"}
}