{
  "type": "Feature",
  "properties": {
    "addr:full":"5150 Fair Oaks Blvd 171 Carmichael CA 95608",
    "addr:housenumber":"5150;171",
    "addr:postcode":"95608",
    "addr:street":"Fair Oaks Blvd",
    "iso:country":"US",
    "sg:address":"5150 Fair Oaks Blvd 171",
    "sg:city":"Carmichael",
    "sg:classifiers":[
        {
            "category":"Building & Trades",
            "subcategory":"Construction",
            "type":"Services"
        }
    ],
    "sg:phone":"+1 916 489 4317",
    "sg:postcode":"95608",
    "sg:province":"CA",
    "sg:tags":[
        "system",
        "specialty",
        "heating",
        "contractor",
        "air conditioning"
    ],
    "wof:name":"Air Services Heating Ac",
    "wof:placetype":"venue"
},
  "geometry": {"coordinates":[-121.34468699999999,38.596682],"type":"Point"}
}