{
  "type": "Feature",
  "properties": {
    "addr:full":"150 Font Blvd San Francisco CA 94132",
    "addr:housenumber":"150",
    "addr:postcode":"94132",
    "addr:street":"Font Blvd",
    "iso:country":"US",
    "sg:address":"150 Font Blvd",
    "sg:city":"San Francisco",
    "sg:classifiers":[
        {
            "category":"Wholesale",
            "subcategory":"Farm Supplies",
            "type":"Manufacturing & Wholesale Goods"
        }
    ],
    "sg:phone":"+1 415 337 6235",
    "sg:postcode":"94132",
    "sg:province":"CA",
    "sg:tags":[
        "feed",
        "export",
        "animal"
    ],
    "wof:name":"Koam Trading Co",
    "wof:placetype":"venue"
},
  "geometry": {"coordinates":[-122.473895,37.715678],"type":"Point"}
}