{
  "type": "Feature",
  "properties": {
    "addr:full":"9424 Dayton Way Beverly Hills CA 90210",
    "addr:housenumber":"9424",
    "addr:postcode":"90210",
    "addr:street":"Dayton Way",
    "iso:country":"US",
    "sg:address":"9424 Dayton Way",
    "sg:city":"Beverly Hills",
    "sg:classifiers":[
        {
            "category":"Real Estate",
            "subcategory":"Architect",
            "type":"Services"
        }
    ],
    "sg:phone":"+1 310 247 8563",
    "sg:postcode":"90210",
    "sg:province":"CA",
    "wof:name":"Dazzan Giorgio & Associates Architects",
    "wof:placetype":"venue"
},
  "geometry": {"coordinates":[-118.40000499999999,34.068853],"type":"Point"}
}