{
  "type": "Feature",
  "properties": {
    "iso:country":"US",
    "sg:address":"4750 Coffee Rd",
    "sg:city":"Bakersfield",
    "sg:classifiers":[
        {
            "category":"Personal",
            "subcategory":"Tanning Parlor",
            "type":"Services"
        }
    ],
    "sg:phone":"+1 661 589 6511",
    "sg:postcode":"93308",
    "sg:province":"CA",
    "sg:tags":[
        "salon"
    ],
    "wof:name":"Endless Summer",
    "wof:placetype":"venue"
},
  "geometry": {"coordinates":[-119.092295,35.40027],"type":"Point"}
}