{
  "type": "Feature",
  "properties": {
    "iso:country":"US",
    "sg:address":"12121 Wilshire Blvd",
    "sg:city":"Los Angeles",
    "sg:classifiers":[
        {
            "category":"Banks & Credit Unions",
            "subcategory":"Bank",
            "type":"Services"
        }
    ],
    "sg:phone":"+1 310 622 7654",
    "sg:postcode":"90025",
    "sg:province":"CA",
    "wof:name":"Security Pacific Bank",
    "wof:placetype":"venue"
},
  "geometry": {"coordinates":[-118.468221,34.043614],"type":"Point"}
}