{
  "type": "Feature",
  "properties": {
    "iso:country":"US",
    "sg:address":"1080 Holly St",
    "sg:city":"San Carlos",
    "sg:classifiers":[
        {
            "category":"Health Services",
            "subcategory":"Chiropractor",
            "type":"Services"
        }
    ],
    "sg:phone":"+1 650 593 1103",
    "sg:postcode":"94070",
    "sg:province":"CA",
    "sg:website":"www.louckschiropractic.com",
    "wof:name":"Loucks Chiropractic",
    "wof:placetype":"venue"
},
  "geometry": {"coordinates":[-122.261251,37.509022],"type":"Point"}
}