{
  "type": "Feature",
  "properties": {
    "iso:country":"US",
    "sg:address":"23 Germaine Pl",
    "sg:city":"Novato",
    "sg:classifiers":[
        {
            "category":"Shopping",
            "subcategory":"Computers & Home Electronics",
            "type":"Retail Goods"
        }
    ],
    "sg:phone":"+1 415 884 0275",
    "sg:postcode":"94949",
    "sg:province":"CA",
    "sg:tags":[
        "equipment",
        "dealer"
    ],
    "sg:website":"www.millcom.com",
    "wof:name":"Millennium Computer Group Inc",
    "wof:placetype":"venue"
},
  "geometry": {"coordinates":[-122.565029,38.069261],"type":"Point"}
}