{
  "type": "Feature",
  "properties": {
    "addr:full":"14593 Buggy Whip Ln Prather CA 93651",
    "addr:housenumber":"14593",
    "addr:postcode":"93651",
    "addr:street":"Buggy Whip Ln",
    "iso:country":"US",
    "sg:address":"14593 Buggy Whip Ln",
    "sg:city":"Prather",
    "sg:classifiers":[
        {
            "category":"Building & Trades",
            "subcategory":"Construction",
            "type":"Services"
        }
    ],
    "sg:phone":"+1 559 323 7656",
    "sg:postcode":"93651",
    "sg:province":"CA",
    "sg:tags":[
        "carpentry",
        "contractor"
    ],
    "wof:name":"California Woodworking",
    "wof:placetype":"venue"
},
  "geometry": {"coordinates":[-119.512411,36.973569],"type":"Point"}
}