{
  "type": "Feature",
  "properties": {
    "iso:country":"US",
    "sg:address":"100 W Westward Ave",
    "sg:city":"Banning",
    "sg:classifiers":[
        {
            "category":"Education",
            "subcategory":"School",
            "type":"Public Place"
        }
    ],
    "sg:phone":"+1 951 922 0289",
    "sg:postcode":"92220",
    "sg:province":"CA",
    "wof:name":"Banning Unified School District",
    "wof:placetype":"venue"
},
  "geometry": {"coordinates":[-116.878114,33.917962],"type":"Point"}
}