{
  "type": "Feature",
  "properties": {
    "iso:country":"US",
    "sg:address":"24935 Ave Kearny",
    "sg:city":"Valencia",
    "sg:classifiers":[
        {
            "category":"Manufacturing",
            "subcategory":"Furniture",
            "type":"Manufacturing & Wholesale Goods"
        }
    ],
    "sg:phone":"+1 661 257 1771",
    "sg:postcode":"91355",
    "sg:province":"CA",
    "sg:tags":[
        "mfg",
        "stereo",
        "wood",
        "speaker",
        "cabinet"
    ],
    "wof:name":"Foster Electric (usa) Inc",
    "wof:placetype":"venue"
},
  "geometry": {"coordinates":[-118.57035999999999,34.436895],"type":"Point"}
}