{
  "type": "Feature",
  "properties": {
    "iso:country":"US",
    "sg:address":"343 E Main St",
    "sg:city":"Stockton",
    "sg:classifiers":[
        {
            "category":"Banks & Credit Unions",
            "subcategory":"Investment Brokerage",
            "type":"Services"
        }
    ],
    "sg:phone":"+1 209 941 0189",
    "sg:postcode":"95202",
    "sg:province":"CA",
    "sg:tags":[
        "advisory",
        "financial"
    ],
    "wof:name":"Great Valley Financial Inc",
    "wof:placetype":"venue"
},
  "geometry": {"coordinates":[-121.28635199999999,37.953336],"type":"Point"}
}