{
  "type": "Feature",
  "properties": {
    "iso:country":"US",
    "sg:address":"2651 Lee Ave",
    "sg:city":"South El Monte",
    "sg:classifiers":[
        {
            "category":"Manufacturing",
            "subcategory":"Metals",
            "type":"Manufacturing & Wholesale Goods"
        },
        {
            "category":"Professional",
            "subcategory":"Business Services",
            "type":"Services"
        }
    ],
    "sg:phone":"+1 626 448 5500",
    "sg:postcode":"91733",
    "sg:province":"CA",
    "sg:tags":[
        "notary",
        "saw",
        "mfg"
    ],
    "wof:name":"Covina Corp",
    "wof:placetype":"venue"
},
  "geometry": {"coordinates":[-118.067293,34.059051],"type":"Point"}
}