{
  "type": "Feature",
  "properties": {
    "addr:full":"8899 University Center Ln Ste 350 San Diego CA 92122",
    "addr:housenumber":"8899",
    "addr:postcode":"92122",
    "addr:street":"University Center Ln Ste 350",
    "iso:country":"US",
    "sg:address":"8899 University Center Ln Ste 350",
    "sg:city":"San Diego",
    "sg:classifiers":[
        {
            "category":"Health Services",
            "subcategory":"Doctor",
            "type":"Services"
        },
        {
            "category":"Health Services",
            "subcategory":"Clinic",
            "type":"Services"
        }
    ],
    "sg:phone":"+1 858 453 7224",
    "sg:postcode":"92122",
    "sg:province":"CA",
    "sg:tags":[
        "spa",
        "medical",
        "surgeon",
        "cosmetic"
    ],
    "sg:website":"www.facesskingym.com",
    "wof:name":"FACES SkinGym",
    "wof:placetype":"venue"
},
  "geometry": {"coordinates":[-117.228069,32.87009],"type":"Point"}
}