{
  "type": "Feature",
  "properties": {
    "iso:country":"US",
    "sg:address":"1227 Morena Boulevard",
    "sg:city":"San Diego",
    "sg:classifiers":[
        {
            "category":"Home & Garden",
            "subcategory":"Hardware",
            "type":"Retail Goods"
        }
    ],
    "sg:phone":"+1 619 275 6151",
    "sg:postcode":"92110",
    "sg:province":"CA",
    "sg:tags":[
        "store"
    ],
    "sg:website":"www.doorsetc.net",
    "wof:name":"Doors Etc",
    "wof:placetype":"venue"
},
  "geometry": {"coordinates":[-117.20182800000001,32.770198],"type":"Point"}
}