{
  "type": "Feature",
  "properties": {
    "iso:country":"US",
    "sg:address":"2515 Ave de Las Plantas",
    "sg:city":"Thousand Oaks",
    "sg:classifiers":[
        {
            "category":"Building & Trades",
            "subcategory":"Plumbing",
            "type":"Services"
        }
    ],
    "sg:phone":"+1 805 497 2020",
    "sg:postcode":"91360",
    "sg:province":"CA",
    "sg:tags":[
        "contractor"
    ],
    "wof:name":"Cantilever Plbg",
    "wof:placetype":"venue"
},
  "geometry": {"coordinates":[-118.859484,34.214106],"type":"Point"}
}