{
  "type": "Feature",
  "properties": {
    "addr:full":"2515 Ave de Las Plantas Thousand Oaks CA 91360",
    "addr:postcode":"91360",
    "addr:street":"2515 Ave De Las",
    "iso:country":"US",
    "sg:address":"2515 Ave de Las Plantas",
    "sg:city":"Thousand Oaks",
    "sg:classifiers":[
        {
            "category":"Building & Trades",
            "subcategory":"Plumbing",
            "type":"Services"
        }
    ],
    "sg:phone":"+1 805 497 2020",
    "sg:postcode":"91360",
    "sg:province":"CA",
    "sg:tags":[
        "contractor"
    ],
    "wof:name":"Cantilever Plbg",
    "wof:placetype":"venue"
},
  "geometry": {"coordinates":[-118.85948399999999,34.214106],"type":"Point"}
}