{
  "type": "Feature",
  "properties": {
    "iso:country":"US",
    "sg:address":"4320 Pacific St",
    "sg:city":"Rocklin",
    "sg:classifiers":[
        {
            "category":"Home & Garden",
            "subcategory":"Garden Supply",
            "type":"Retail Goods"
        }
    ],
    "sg:phone":"+1 916 630 8500",
    "sg:postcode":"95677",
    "sg:province":"CA",
    "sg:tags":[
        "landscaping",
        "equipment"
    ],
    "wof:name":"K & M Building Material Inc",
    "wof:placetype":"venue"
},
  "geometry": {"coordinates":[-121.221954,38.802382],"type":"Point"}
}