{
  "type": "Feature",
  "properties": {
    "addr:full":"4364 Piedmont Ave Oakland CA 94611",
    "addr:housenumber":"4364",
    "addr:postcode":"94611",
    "addr:street":"Piedmont Ave",
    "iso:country":"US",
    "sg:address":"4364 Piedmont Ave",
    "sg:city":"Oakland",
    "sg:classifiers":[
        {
            "category":"Shopping",
            "subcategory":"Music",
            "type":"Retail Goods"
        }
    ],
    "sg:phone":"+1 510 655 6844",
    "sg:postcode":"94611",
    "sg:province":"CA",
    "sg:tags":[
        "game",
        "disc",
        "tape",
        "video",
        "rental",
        "cassette"
    ],
    "sg:website":"www.videoroomoakland.com",
    "wof:name":"Video Room",
    "wof:placetype":"venue"
},
  "geometry": {"coordinates":[-122.248142,37.829656],"type":"Point"}
}