{
  "type": "Feature",
  "properties": {
    "iso:country":"US",
    "sg:address":"1411 W 7th St",
    "sg:city":"San Pedro",
    "sg:classifiers":[
        {
            "category":"Personal",
            "subcategory":"Beauty Salon",
            "type":"Services"
        }
    ],
    "sg:phone":"+1 310 548 0200",
    "sg:postcode":"90732",
    "sg:province":"CA",
    "wof:name":"Maria Zabatta At C'e LA Luna",
    "wof:placetype":"venue"
},
  "geometry": {"coordinates":[-118.308418,33.73778],"type":"Point"}
}