{
  "type": "Feature",
  "properties": {
    "addr:full":"14419 Sherman Way Van Nuys CA 91405",
    "addr:housenumber":"14419",
    "addr:postcode":"91405",
    "addr:street":"Sherman Way",
    "iso:country":"US",
    "sg:address":"14419 Sherman Way",
    "sg:city":"Van Nuys",
    "sg:classifiers":[
        {
            "category":"Restaurant",
            "type":"Food & Drink"
        }
    ],
    "sg:phone":"+1 818 787 6789",
    "sg:postcode":"91405",
    "sg:province":"CA",
    "sg:tags":[
        "pizza"
    ],
    "wof:name":"Big Mama's & Papa's PiZZeria",
    "wof:placetype":"venue"
},
  "geometry": {"coordinates":[-118.44681300000001,34.201347],"type":"Point"}
}