{
  "type": "Feature",
  "properties": {
    "addr:full":"2741 Dow Ave Tustin CA 92780",
    "addr:housenumber":"2741",
    "addr:postcode":"92780",
    "addr:street":"Dow Ave",
    "iso:country":"US",
    "sg:address":"2741 Dow Ave",
    "sg:city":"Tustin",
    "sg:classifiers":[
        {
            "category":"Wholesale",
            "subcategory":"Medical Equipment & Supplies",
            "type":"Manufacturing & Wholesale Goods"
        }
    ],
    "sg:phone":"+1 714 368 5200",
    "sg:postcode":"92780",
    "sg:province":"CA",
    "wof:name":"Sourceone Healthcare Tech OH",
    "wof:placetype":"venue"
},
  "geometry": {"coordinates":[-117.807529,33.712225],"type":"Point"}
}