{
  "type": "Feature",
  "properties": {
    "addr:full":"3280 Airflite Way Long Beach CA 90807",
    "addr:housenumber":"3280",
    "addr:postcode":"90807",
    "addr:street":"Airflite Way",
    "iso:country":"US",
    "sg:address":"3280 Airflite Way",
    "sg:city":"Long Beach",
    "sg:classifiers":[
        {
            "category":"Airport",
            "type":"Transportation"
        }
    ],
    "sg:phone":"+1 562 424 4451",
    "sg:postcode":"90807",
    "sg:province":"CA",
    "sg:tags":[
        "aircraft",
        "maintenance"
    ],
    "wof:name":"Long Beach Citation Svc Ctr",
    "wof:placetype":"venue"
},
  "geometry": {"coordinates":[-118.15906699999999,33.816707],"type":"Point"}
}