{
  "type": "Feature",
  "properties": {
    "addr:full":"920 Foxboro Dr Napa CA 94559",
    "addr:housenumber":"920",
    "addr:postcode":"94559",
    "addr:street":"Foxboro Dr",
    "iso:country":"US",
    "sg:address":"920 Foxboro Dr",
    "sg:city":"Napa",
    "sg:classifiers":[
        {
            "category":"Retail",
            "subcategory":"Portrait Studio",
            "type":"Services"
        }
    ],
    "sg:phone":"+1 707 253 8733",
    "sg:postcode":"94559",
    "sg:province":"CA",
    "sg:tags":[
        "photographer"
    ],
    "wof:name":"Portraits By Rebecca",
    "wof:placetype":"venue"
},
  "geometry": {"coordinates":[-122.27120600000001,38.29466],"type":"Point"}
}