{
  "type": "Feature",
  "properties": {
    "iso:country":"US",
    "sg:address":"11255 Juniper Ave",
    "sg:city":"Morongo Valley",
    "sg:classifiers":[
        {
            "category":"Shopping",
            "subcategory":"Florist",
            "type":"Retail Goods"
        }
    ],
    "sg:phone":"+1 760 363 7927",
    "sg:postcode":"92256",
    "sg:province":"CA",
    "wof:name":"Gourds By Ron",
    "wof:placetype":"venue"
},
  "geometry": {"coordinates":[-116.58955400000001,34.047517],"type":"Point"}
}