{
  "type": "Feature",
  "properties": {
    "iso:country":"US",
    "sg:address":"610 Richfield Rd",
    "sg:city":"Placentia",
    "sg:classifiers":[
        {
            "category":"Building & Trades",
            "subcategory":"Cleaning & Sanitation",
            "type":"Services"
        }
    ],
    "sg:phone":"+1 714 666 0190",
    "sg:postcode":"92870",
    "sg:province":"CA",
    "sg:tags":[
        "carpet"
    ],
    "wof:name":"Garland Contracting",
    "wof:placetype":"venue"
},
  "geometry": {"coordinates":[-117.825267,33.865942],"type":"Point"}
}