{
  "type": "Feature",
  "properties": {
    "iso:country":"US",
    "sg:address":"787 Avocado Ct",
    "sg:city":"Del Mar",
    "sg:classifiers":[
        {
            "category":"Retail",
            "subcategory":"Veterinary Services",
            "type":"Services"
        }
    ],
    "sg:phone":"+1 858 720 0269",
    "sg:postcode":"92014",
    "sg:province":"CA",
    "sg:tags":[
        "veterinarian"
    ],
    "wof:name":"San Diego Veterinary Surgery",
    "wof:placetype":"venue"
},
  "geometry": {"coordinates":[-117.249381,32.986585],"type":"Point"}
}