{
  "type": "Feature",
  "properties": {
    "addr:full":"1460 Golden Gate Ave #22 San Francisco CA 94115",
    "addr:housenumber":"1460",
    "addr:postcode":"94115",
    "addr:street":"Golden Gate Ave # 22",
    "iso:country":"US",
    "sg:address":"1460 Golden Gate Ave #22",
    "sg:city":"San Francisco",
    "sg:classifiers":[
        {
            "category":"Arts & Performance",
            "subcategory":"Arts Center",
            "type":"Entertainment"
        }
    ],
    "sg:postcode":"94115",
    "sg:province":"CA",
    "sg:website":"www.madeyouthink.org",
    "wof:name":"Madeyouthink.org",
    "wof:placetype":"venue"
},
  "geometry": {"coordinates":[-122.43499799999999,37.7794],"type":"Point"}
}