{
  "type": "Feature",
  "properties": {
    "addr:full":"6051 Hollywood Blvd Ste 205 Los Angeles CA 90028",
    "addr:housenumber":"6051",
    "addr:postcode":"90028",
    "addr:street":"Hollywood Blvd Ste 205",
    "iso:country":"US",
    "sg:address":"6051 Hollywood Blvd Ste 205",
    "sg:city":"Los Angeles",
    "sg:classifiers":[
        {
            "category":"Building & Trades",
            "subcategory":"Cleaning & Sanitation",
            "type":"Services"
        }
    ],
    "sg:phone":"+1 818 396 1694",
    "sg:postcode":"90028",
    "sg:province":"CA",
    "sg:tags":[
        "carpet"
    ],
    "sg:website":"www.californiacarpetcleaningcorp...",
    "wof:name":"California Carpet Cleaning Corporation In Los Angeles",
    "wof:placetype":"venue"
},
  "geometry": {"coordinates":[-118.321913,34.102033],"type":"Point"}
}