{
  "type": "Feature",
  "properties": {
    "addr:full":"3915 Mission Ave Ste 2 Oceanside CA 92054",
    "addr:housenumber":"3915",
    "addr:postcode":"92054",
    "addr:street":"Mission Ave Ste 2",
    "iso:country":"US",
    "sg:address":"3915 Mission Ave Ste 2",
    "sg:city":"Oceanside",
    "sg:classifiers":[
        {
            "category":"Health Services",
            "subcategory":"Optometrist",
            "type":"Services"
        }
    ],
    "sg:phone":"+1 760 757 8771",
    "sg:postcode":"92054",
    "sg:province":"CA",
    "wof:name":"Lundquist Kurt OD Optmtrst",
    "wof:placetype":"venue"
},
  "geometry": {"coordinates":[-117.322998,33.229801],"type":"Point"}
}