{
  "type": "Feature",
  "properties": {
    "addr:full":"2279 Railroad Ave Pittsburg CA 94565",
    "addr:housenumber":"2279",
    "addr:postcode":"94565",
    "addr:street":"Railroad Ave",
    "iso:country":"US",
    "sg:address":"2279 Railroad Ave",
    "sg:city":"Pittsburg",
    "sg:classifiers":[
        {
            "category":"Food & Beverages",
            "subcategory":"Liquor & Beverages",
            "type":"Retail Goods"
        }
    ],
    "sg:phone":"+1 925 427 4199",
    "sg:postcode":"94565",
    "sg:province":"CA",
    "wof:name":"Pittsburg Liquor & Deli",
    "wof:placetype":"venue"
},
  "geometry": {"coordinates":[-121.88921999999999,38.017122],"type":"Point"}
}