{
  "type": "Feature",
  "properties": {
    "iso:country":"US",
    "sg:address":"1555 14th St",
    "sg:city":"Santa Monica",
    "sg:classifiers":[
        {
            "category":"Professional",
            "subcategory":"Management & Consulting",
            "type":"Services"
        }
    ],
    "sg:phone":"+1 310 451 5009",
    "sg:postcode":"90404",
    "sg:province":"CA",
    "sg:tags":[
        "consultant",
        "publishing"
    ],
    "wof:name":"Foma Publishing",
    "wof:placetype":"venue"
},
  "geometry": {"coordinates":[-118.483329,34.022195],"type":"Point"}
}