{
  "type": "Feature",
  "properties": {
    "addr:full":"200 N Main St Santa Ana CA 92706",
    "addr:housenumber":"200",
    "addr:postcode":"92706",
    "addr:street":"N Main St",
    "iso:country":"US",
    "sg:address":"200 N Main St",
    "sg:city":"Santa Ana",
    "sg:classifiers":[
        {
            "category":"Government",
            "subcategory":"Office",
            "type":"Public Place"
        }
    ],
    "sg:phone":"+1 714 973 9004",
    "sg:postcode":"92706",
    "sg:province":"CA",
    "wof:name":"California Voter Registration",
    "wof:placetype":"venue"
},
  "geometry": {"coordinates":[-117.86762,33.74713],"type":"Point"}
}