{
  "type": "Feature",
  "properties": {
    "iso:country":"US",
    "sg:address":"16031 Arrow Hwy",
    "sg:city":"Irwindale",
    "sg:classifiers":[
        {
            "category":"Shopping",
            "subcategory":"Bicycles & Sporting Goods",
            "type":"Retail Goods"
        }
    ],
    "sg:phone":"+1 626 813 3503",
    "sg:postcode":"91706",
    "sg:province":"CA",
    "sg:tags":[
        "equipment",
        "playground"
    ],
    "sg:website":"www.totturf.com",
    "wof:name":"Robertson Industries",
    "wof:placetype":"venue"
},
  "geometry": {"coordinates":[-117.933862,34.106904],"type":"Point"}
}