{
  "type": "Feature",
  "properties": {
    "iso:country":"US",
    "sg:address":"257 Barbara Dr",
    "sg:city":"Los Gatos",
    "sg:classifiers":[
        {
            "category":"Building & Trades",
            "subcategory":"Plumbing",
            "type":"Services"
        }
    ],
    "sg:phone":"+1 408 377 7977",
    "sg:postcode":"95032",
    "sg:province":"CA",
    "sg:tags":[
        "plumbing",
        "contractor"
    ],
    "wof:name":"Down Under Plumbing Svc",
    "wof:placetype":"venue"
},
  "geometry": {"coordinates":[-121.928492,37.240963],"type":"Point"}
}