{
  "type": "Feature",
  "properties": {
    "addr:full":"2040 Scott St. San Francisco CA 94115",
    "addr:housenumber":"2040",
    "addr:postcode":"94115",
    "addr:street":"Scott St.",
    "iso:country":"US",
    "sg:address":"2040 Scott St.",
    "sg:city":"San Francisco",
    "sg:classifiers":[
        {
            "category":"Professional",
            "subcategory":"Computer Services",
            "type":"Services"
        }
    ],
    "sg:postcode":"94115",
    "sg:province":"CA",
    "sg:website":"http://local.to",
    "wof:name":"Local To",
    "wof:placetype":"venue"
},
  "geometry": {"coordinates":[-122.43882600000001,37.78884],"type":"Point"}
}