{
  "type": "Feature",
  "properties": {
    "iso:country":"US",
    "sg:address":"22441 Cardiff Dr",
    "sg:city":"Santa Clarita",
    "sg:classifiers":[
        {
            "category":"Building & Trades",
            "subcategory":"Construction",
            "type":"Services"
        }
    ],
    "sg:phone":"+1 661 254 2447",
    "sg:postcode":"91350",
    "sg:province":"CA",
    "sg:tags":[
        "painter"
    ],
    "wof:name":"Swihart Painting",
    "wof:placetype":"venue"
},
  "geometry": {"coordinates":[-118.527,34.402802],"type":"Point"}
}