{
  "type": "Feature",
  "properties": {
    "iso:country":"US",
    "sg:address":"1880 E Hammer Ln",
    "sg:city":"Stockton",
    "sg:classifiers":[
        {
            "category":"Home & Garden",
            "subcategory":"Furniture",
            "type":"Retail Goods"
        }
    ],
    "sg:phone":"+1 209 473 9772",
    "sg:postcode":"95210",
    "sg:province":"CA",
    "wof:name":"Premier Furniture Gallery",
    "wof:placetype":"venue"
},
  "geometry": {"coordinates":[-121.291882,38.020854],"type":"Point"}
}