{
  "type": "Feature",
  "properties": {
    "iso:country":"US",
    "sg:address":"13045 Tom White Way",
    "sg:city":"Norwalk",
    "sg:classifiers":[
        {
            "category":"Professional",
            "subcategory":"Advertising",
            "type":"Services"
        }
    ],
    "sg:phone":"+1 562 404 4884",
    "sg:postcode":"90650",
    "sg:province":"CA",
    "sg:tags":[
        "distribution"
    ],
    "wof:name":"Ruferd Corp",
    "wof:placetype":"venue"
},
  "geometry": {"coordinates":[-118.053466,33.905239],"type":"Point"}
}