{
  "type": "Feature",
  "properties": {
    "iso:country":"US",
    "sg:address":"2920 Clark Rd",
    "sg:city":"Oroville",
    "sg:classifiers":[
        {
            "category":"Real Estate",
            "subcategory":"Real Estate Operator",
            "type":"Services"
        }
    ],
    "sg:phone":"+1 530 891 5303",
    "sg:postcode":"95965",
    "sg:province":"CA",
    "sg:tags":[
        "mobile",
        "home",
        "community"
    ],
    "wof:name":"Foothills Mobile Home Park",
    "wof:placetype":"venue"
},
  "geometry": {"coordinates":[-121.629189,39.661219],"type":"Point"}
}