{
  "type": "Feature",
  "properties": {
    "iso:country":"US",
    "sg:address":"401 Peninsula Dr",
    "sg:city":"Westwood",
    "sg:classifiers":[
        {
            "category":"Banks & Credit Unions",
            "subcategory":"Bank",
            "type":"Services"
        }
    ],
    "sg:phone":"+1 530 596 4394",
    "sg:postcode":"96137",
    "sg:province":"CA",
    "wof:name":"Plumas Bank",
    "wof:placetype":"venue"
},
  "geometry": {"coordinates":[-121.12883,40.276538],"type":"Point"}
}