{
  "type": "Feature",
  "properties": {
    "addr:full":"18005 Avalon Blvd Carson CA 90746",
    "addr:housenumber":"18005",
    "addr:postcode":"90746",
    "addr:street":"Avalon Blvd",
    "iso:country":"US",
    "sg:address":"18005 Avalon Blvd",
    "sg:city":"Carson",
    "sg:classifiers":[
        {
            "category":"Banks & Credit Unions",
            "subcategory":"Bank",
            "type":"Services"
        }
    ],
    "sg:phone":"+1 310 516 6900",
    "sg:postcode":"90746",
    "sg:province":"CA",
    "sg:tags":[
        "saving",
        "commercial"
    ],
    "sg:website":"http://www.wellsfargo.com",
    "wof:name":"Wells Fargo Bank",
    "wof:placetype":"venue"
},
  "geometry": {"coordinates":[-118.26599899999999,33.866798],"type":"Point"}
}