{
  "type": "Feature",
  "properties": {
    "addr:full":"12134 Severn Way Riverside CA 92503",
    "addr:housenumber":"12134",
    "addr:postcode":"92503",
    "addr:street":"Severn Way",
    "iso:country":"US",
    "sg:address":"12134 Severn Way",
    "sg:city":"Riverside",
    "sg:classifiers":[
        {
            "category":"Professional",
            "subcategory":"Art Services",
            "type":"Services"
        }
    ],
    "sg:phone":"+1 951 371 4602",
    "sg:postcode":"92503",
    "sg:province":"CA",
    "sg:tags":[
        "graphic",
        "designer"
    ],
    "sg:website":"www.imageone.us",
    "wof:name":"Image One Creative Svc Inc",
    "wof:placetype":"venue"
},
  "geometry": {"coordinates":[-117.500095,33.896141],"type":"Point"}
}