{
  "type": "Feature",
  "properties": {
    "iso:country":"US",
    "sg:address":"1351 Broadway",
    "sg:city":"El Cajon",
    "sg:classifiers":[
        {
            "category":"Real Estate",
            "subcategory":"Real Estate Agent",
            "type":"Services"
        }
    ],
    "sg:phone":"+1 619 444 3092",
    "sg:postcode":"92021",
    "sg:province":"CA",
    "wof:name":"Coast Property Management",
    "wof:placetype":"venue"
},
  "geometry": {"coordinates":[-116.931321,32.807705],"type":"Point"}
}