{
  "type": "Feature",
  "properties": {
    "iso:country":"US",
    "sg:address":"431 Manzanita Ave",
    "sg:city":"Fairfield",
    "sg:classifiers":[
        {
            "category":"Building & Trades",
            "subcategory":"Construction",
            "type":"Services"
        }
    ],
    "sg:phone":"+1 707 428 0308",
    "sg:postcode":"94533",
    "sg:province":"CA",
    "sg:tags":[
        "coping",
        "plastering",
        "tiling",
        "pool",
        "swimming"
    ],
    "wof:name":"Advanced Leak Detection",
    "wof:placetype":"venue"
},
  "geometry": {"coordinates":[-122.04463800000001,38.277061],"type":"Point"}
}