{
  "type": "Feature",
  "properties": {
    "addr:full":"1828 San Pablo Ave #1 Berkeley CA 94702",
    "addr:housenumber":"1828",
    "addr:postcode":"94702",
    "addr:street":"San Pablo Ave # 1",
    "iso:country":"US",
    "sg:address":"1828 San Pablo Ave #1",
    "sg:city":"Berkeley",
    "sg:classifiers":[
        {
            "category":"Arts & Performance",
            "subcategory":"Art Gallery",
            "type":"Entertainment"
        }
    ],
    "sg:postcode":"94702",
    "sg:province":"CA",
    "sg:website":"www.pueblonuevogallery.com",
    "wof:name":"Pueblo Nuevo Art Space",
    "wof:placetype":"venue"
},
  "geometry": {"coordinates":[-122.292748,37.87077],"type":"Point"}
}