{
  "type": "Feature",
  "properties": {
    "iso:country":"US",
    "sg:address":"309 O St",
    "sg:city":"Eureka",
    "sg:classifiers":[
        {
            "category":"Professional",
            "subcategory":"Lawyer & Legal Services",
            "type":"Services"
        }
    ],
    "sg:phone":"+1 707 443 9842",
    "sg:postcode":"95501",
    "sg:province":"CA",
    "sg:tags":[
        "attorney"
    ],
    "wof:name":"Manny Daskal Law Offices",
    "wof:placetype":"venue"
},
  "geometry": {"coordinates":[-124.15678,40.805459],"type":"Point"}
}