{
  "type": "Feature",
  "properties": {
    "iso:country":"US",
    "sg:address":"1083 E Mission Blvd",
    "sg:city":"Pomona",
    "sg:classifiers":[
        {
            "category":"Food & Beverages",
            "subcategory":"Liquor & Beverages",
            "type":"Retail Goods"
        }
    ],
    "sg:phone":"+1 909 629 8890",
    "sg:postcode":"91766",
    "sg:province":"CA",
    "wof:name":"Sunny Liquor",
    "wof:placetype":"venue"
},
  "geometry": {"coordinates":[-117.736397,34.055517],"type":"Point"}
}