{
  "type": "Feature",
  "properties": {
    "addr:full":"872 N Delaware St San Mateo CA 94401",
    "addr:housenumber":"872",
    "addr:postcode":"94401",
    "addr:street":"N Delaware St",
    "iso:country":"US",
    "sg:address":"872 N Delaware St",
    "sg:city":"San Mateo",
    "sg:classifiers":[
        {
            "category":"Personal",
            "type":"Services"
        }
    ],
    "sg:phone":"+1 650 342 7448",
    "sg:postcode":"94401",
    "sg:province":"CA",
    "sg:tags":[
        "shopping"
    ],
    "wof:name":"CVS Pharmacy",
    "wof:placetype":"venue"
},
  "geometry": {"coordinates":[-122.334148,37.580096],"type":"Point"}
}