{
  "type": "Feature",
  "properties": {
    "addr:full":"3764 Lake Almanor Dr Westwood CA 96137",
    "addr:housenumber":"3764",
    "addr:postcode":"96137",
    "addr:street":"Lake Almanor Dr",
    "iso:country":"US",
    "sg:address":"3764 Lake Almanor Dr",
    "sg:city":"Westwood",
    "sg:classifiers":[
        {
            "category":"Professional",
            "subcategory":"Detective & Security Services",
            "type":"Services"
        }
    ],
    "sg:phone":"+1 530 596 4600",
    "sg:postcode":"96137",
    "sg:province":"CA",
    "sg:tags":[
        "information",
        "bureau"
    ],
    "wof:name":"Throwers Repair Service",
    "wof:placetype":"venue"
},
  "geometry": {"coordinates":[-121.09184500000001,40.267747],"type":"Point"}
}