{
  "type": "Feature",
  "properties": {
    "addr:full":"975 Broadway Chula Vista CA 91911",
    "addr:housenumber":"975",
    "addr:postcode":"91911",
    "addr:street":"Broadway",
    "iso:country":"US",
    "sg:address":"975 Broadway",
    "sg:city":"Chula Vista",
    "sg:classifiers":[
        {
            "category":"Personal",
            "subcategory":"Beauty Salon",
            "type":"Services"
        }
    ],
    "sg:phone":"+1 619 754 4383",
    "sg:postcode":"91911",
    "sg:province":"CA",
    "sg:tags":[
        "hair"
    ],
    "wof:name":"Lisa's Day Spa & Hair Salon",
    "wof:placetype":"venue"
},
  "geometry": {"coordinates":[-117.082764,32.614831],"type":"Point"}
}