{
  "type": "Feature",
  "properties": {
    "addr:full":"584 N Irving Blvd Los Angeles CA 90004",
    "addr:housenumber":"584",
    "addr:postcode":"90004",
    "addr:street":"N Irving Blvd",
    "iso:country":"US",
    "sg:address":"584 N Irving Blvd",
    "sg:city":"Los Angeles",
    "sg:classifiers":[
        {
            "category":"Shopping",
            "subcategory":"Jewelry",
            "type":"Retail Goods"
        }
    ],
    "sg:phone":"+1 323 463 8913",
    "sg:postcode":"90004",
    "sg:province":"CA",
    "wof:name":"STI INC",
    "wof:placetype":"venue"
},
  "geometry": {"coordinates":[-118.31855400000001,34.129999],"type":"Point"}
}