{
  "type": "Feature",
  "properties": {
    "addr:full":"3176 Arden Way Fair Oaks CA 95628",
    "addr:housenumber":"3176",
    "addr:postcode":"95628",
    "addr:street":"Arden Way",
    "iso:country":"US",
    "sg:address":"3176 Arden Way",
    "sg:city":"Fair Oaks",
    "sg:classifiers":[
        {
            "category":"Health Services",
            "subcategory":"Doctor",
            "type":"Services"
        },
        {
            "category":"Community Center",
            "type":"Public Place"
        }
    ],
    "sg:phone":"+1 916 977 3017",
    "sg:postcode":"95628",
    "sg:province":"CA",
    "sg:tags":[
        "medical"
    ],
    "wof:name":"Kaiser Permanente Sacramento Medical Center",
    "wof:placetype":"venue"
},
  "geometry": {"coordinates":[-121.390682,38.57404],"type":"Point"}
}