{
  "type": "Feature",
  "properties": {
    "addr:full":"24081 El Toro Road Laguna Hills CA 92653",
    "addr:housenumber":"24081",
    "addr:postcode":"92653",
    "addr:street":"El Toro Road",
    "iso:country":"US",
    "sg:address":"24081 El Toro Road",
    "sg:city":"Laguna Hills",
    "sg:classifiers":[
        {
            "category":"Shopping",
            "subcategory":"Pharmacy",
            "type":"Retail Goods"
        },
        {
            "category":"Food & Beverages",
            "subcategory":"Groceries & Convenience Stores",
            "type":"Retail Goods"
        }
    ],
    "sg:phone":"+1 949 206 9632",
    "sg:postcode":"92653",
    "sg:province":"CA",
    "sg:tags":[
        "drugstore"
    ],
    "sg:website":"www.walgreens.com",
    "wof:name":"Walgreens Drug Store",
    "wof:placetype":"venue"
},
  "geometry": {"coordinates":[-117.71061400000001,33.612768],"type":"Point"}
}