{
  "type": "Feature",
  "properties": {
    "addr:full":"1620 Koster St Eureka CA 95501",
    "addr:housenumber":"1620",
    "addr:postcode":"95501",
    "addr:street":"Koster St",
    "iso:country":"US",
    "sg:address":"1620 Koster St",
    "sg:city":"Eureka",
    "sg:classifiers":[
        {
            "category":"Home & Garden",
            "subcategory":"Hardware",
            "type":"Retail Goods"
        }
    ],
    "sg:phone":"+1 707 443 6737",
    "sg:postcode":"95501",
    "sg:province":"CA",
    "sg:tags":[
        "saw"
    ],
    "wof:name":"Western Chain Saw Co",
    "wof:placetype":"venue"
},
  "geometry": {"coordinates":[-124.178971,40.792599],"type":"Point"}
}