{
  "type": "Feature",
  "properties": {
    "iso:country":"US",
    "sg:address":"1717 Broadway St",
    "sg:city":"Vallejo",
    "sg:classifiers":[
        {
            "category":"Building & Trades",
            "subcategory":"Construction",
            "type":"Services"
        }
    ],
    "sg:phone":"+1 707 651 9322",
    "sg:postcode":"94589",
    "sg:province":"CA",
    "sg:tags":[
        "contractor",
        "fence-sales"
    ],
    "wof:name":"Morgan Fence Iron Inc",
    "wof:placetype":"venue"
},
  "geometry": {"coordinates":[-122.251676,38.12828],"type":"Point"}
}