{
  "type": "Feature",
  "properties": {
    "addr:full":"5768 Riverside Dr Chino CA 91710",
    "addr:housenumber":"5768",
    "addr:postcode":"91710",
    "addr:street":"Riverside Dr",
    "iso:country":"US",
    "sg:address":"5768 Riverside Dr",
    "sg:city":"Chino",
    "sg:classifiers":[
        {
            "category":"Personal",
            "subcategory":"Beauty Salon",
            "type":"Services"
        }
    ],
    "sg:phone":"+1 909 590 5673",
    "sg:postcode":"91710",
    "sg:province":"CA",
    "sg:tags":[
        "hair",
        "stylist"
    ],
    "sg:website":"http://www.hairex.com",
    "wof:name":"Hair Expressions",
    "wof:placetype":"venue"
},
  "geometry": {"coordinates":[-117.67909400000001,34.019138],"type":"Point"}
}