{
  "type": "Feature",
  "properties": {
    "addr:full":"22311 Montera Dr Salinas CA 93908",
    "addr:housenumber":"22311",
    "addr:postcode":"93908",
    "addr:street":"Montera Dr",
    "iso:country":"US",
    "sg:address":"22311 Montera Dr",
    "sg:city":"Salinas",
    "sg:classifiers":[
        {
            "category":"Organizations",
            "subcategory":"Professional Association",
            "type":"Services"
        }
    ],
    "sg:phone":"+1 831 484 1067",
    "sg:postcode":"93908",
    "sg:province":"CA",
    "sg:tags":[
        "business",
        "trade"
    ],
    "wof:name":"Fort International Trade",
    "wof:placetype":"venue"
},
  "geometry": {"coordinates":[-121.703861,36.597383],"type":"Point"}
}