{
  "type": "Feature",
  "properties": {
    "addr:full":"860 Tucker Ln Walnut CA 91789",
    "addr:housenumber":"860",
    "addr:postcode":"91789",
    "addr:street":"Tucker Ln",
    "iso:country":"US",
    "sg:address":"860 Tucker Ln",
    "sg:city":"Walnut",
    "sg:classifiers":[
        {
            "category":"Manufacturing",
            "subcategory":"Printing",
            "type":"Manufacturing & Wholesale Goods"
        }
    ],
    "sg:phone":"+1 909 594 9459",
    "sg:postcode":"91789",
    "sg:province":"CA",
    "sg:tags":[
        "scanning",
        "printer",
        "supply",
        "commercial",
        "equipment",
        "offset",
        "plotting"
    ],
    "sg:website":"http://www.marrsprint.net",
    "wof:name":"Marrs Printing",
    "wof:placetype":"venue"
},
  "geometry": {"coordinates":[-117.86066700000001,33.999104],"type":"Point"}
}