{
  "type": "Feature",
  "properties": {
    "iso:country":"US",
    "sg:address":"350 S Grand Ave Ste 3100",
    "sg:city":"Los Angeles",
    "sg:classifiers":[
        {
            "category":"Banks & Credit Unions",
            "subcategory":"Investment Brokerage",
            "type":"Services"
        }
    ],
    "sg:phone":"+1 213 270 2300",
    "sg:postcode":"90071",
    "sg:province":"CA",
    "sg:tags":[
        "investing"
    ],
    "wof:name":"Duff & Phelps",
    "wof:placetype":"venue"
},
  "geometry": {"coordinates":[-118.251565,34.211922],"type":"Point"}
}