{
  "type": "Feature",
  "properties": {
    "iso:country":"US",
    "sg:address":"5465 Morehouse Dr",
    "sg:city":"San Diego",
    "sg:classifiers":[
        {
            "category":"Building & Trades",
            "subcategory":"Cleaning & Sanitation",
            "type":"Services"
        }
    ],
    "sg:phone":"+1 858 546 7474",
    "sg:postcode":"92121",
    "sg:province":"CA",
    "sg:tags":[
        "property",
        "maintenance"
    ],
    "wof:name":"American Property Enterprises",
    "wof:placetype":"venue"
},
  "geometry": {"coordinates":[-117.196229,32.896806],"type":"Point"}
}