{
  "type": "Feature",
  "properties": {
    "addr:full":"1030 Railroad Ave Orland CA 95963",
    "addr:housenumber":"1030",
    "addr:postcode":"95963",
    "addr:street":"Railroad Ave",
    "iso:country":"US",
    "sg:address":"1030 Railroad Ave",
    "sg:city":"Orland",
    "sg:classifiers":[
        {
            "category":"Manufacturing",
            "subcategory":"Tools & Machinery",
            "type":"Manufacturing & Wholesale Goods"
        }
    ],
    "sg:phone":"+1 530 865 2138",
    "sg:postcode":"95963",
    "sg:province":"CA",
    "sg:tags":[
        "machine",
        "shop"
    ],
    "wof:name":"Ponci's Welding & Machine Shop",
    "wof:placetype":"venue"
},
  "geometry": {"coordinates":[-122.194779,39.74248],"type":"Point"}
}