{
  "type": "Feature",
  "properties": {
    "iso:country":"US",
    "sg:address":"2265 Cll del Mundo",
    "sg:city":"Santa Clara",
    "sg:classifiers":[
        {
            "category":"Manufacturing",
            "subcategory":"Tools & Machinery",
            "type":"Manufacturing & Wholesale Goods"
        }
    ],
    "sg:phone":"+1 408 988 4380",
    "sg:postcode":"95054",
    "sg:province":"CA",
    "sg:tags":[
        "machine",
        "shop"
    ],
    "wof:name":"Centerline Precision",
    "wof:placetype":"venue"
},
  "geometry": {"coordinates":[-121.965625,37.409886],"type":"Point"}
}