{
  "type": "Feature",
  "properties": {
    "iso:country":"US",
    "sg:address":"1011 E Bidwell St",
    "sg:city":"Folsom",
    "sg:classifiers":[
        {
            "category":"Building & Trades",
            "subcategory":"Construction",
            "type":"Services"
        }
    ],
    "sg:phone":"+1 916 983 1327",
    "sg:postcode":"95630",
    "sg:province":"CA",
    "sg:tags":[
        "coping",
        "plastering",
        "tiling",
        "pool",
        "swimming"
    ],
    "sg:website":"www.hancockpools.com",
    "wof:name":"Hancock Pool Svc & Supply",
    "wof:placetype":"venue"
},
  "geometry": {"coordinates":[-121.15270700000001,38.669175],"type":"Point"}
}