{
  "type": "Feature",
  "properties": {
    "iso:country":"US",
    "sg:address":"Millbrae Ave and Bayshore Hwy",
    "sg:city":"Millbrae",
    "sg:classifiers":[
        {
            "category":"Park",
            "type":"Public Place"
        }
    ],
    "sg:postcode":"94030",
    "sg:province":"CA",
    "wof:name":"Bayfront Park",
    "wof:placetype":"venue"
},
  "geometry": {"coordinates":[-122.377047,37.604791],"type":"Point"}
}