{
  "type": "Feature",
  "properties": {
    "addr:full":"3857 Castala Dr Palmdale CA 93550",
    "addr:housenumber":"3857",
    "addr:postcode":"ca 93550",
    "addr:street":"Castala Dr",
    "iso:country":"US",
    "sg:address":"3857 Castala Dr",
    "sg:city":"Palmdale",
    "sg:classifiers":[
        {
            "category":"Manufacturing",
            "subcategory":"Signs",
            "type":"Manufacturing & Wholesale Goods"
        }
    ],
    "sg:phone":"+1 661 285 7700",
    "sg:postcode":"93550",
    "sg:province":"CA",
    "wof:name":"Admoor Splash Window Art & Signs",
    "wof:placetype":"venue"
},
  "geometry": {"coordinates":[-118.05954,34.569013],"type":"Point"}
}