{
  "type": "Feature",
  "properties": {
    "addr:full":"57 S Craig Ave Pasadena CA 91107",
    "addr:housenumber":"57",
    "addr:postcode":"91107",
    "addr:street":"S Craig Ave",
    "iso:country":"US",
    "sg:address":"57 S Craig Ave",
    "sg:city":"Pasadena",
    "sg:classifiers":[
        {
            "category":"Building & Trades",
            "subcategory":"Plumbing",
            "type":"Services"
        },
        {
            "category":"Building & Trades",
            "subcategory":"Construction",
            "type":"Services"
        }
    ],
    "sg:phone":"+1 626 564 0368",
    "sg:postcode":"91107",
    "sg:province":"CA",
    "sg:tags":[
        "contractor",
        "industrial",
        "painting",
        "contractors-commercial",
        "tile-contractors"
    ],
    "wof:name":"Chuy's Ceramic Tile",
    "wof:placetype":"venue"
},
  "geometry": {"coordinates":[-118.106184,34.144922],"type":"Point"}
}