{
  "type": "Feature",
  "properties": {
    "iso:country":"US",
    "sg:address":"2580 Ross Ct",
    "sg:city":"Auburn",
    "sg:classifiers":[
        {
            "category":"Professional",
            "subcategory":"Engineering",
            "type":"Services"
        }
    ],
    "sg:phone":"+1 530 878 0524",
    "sg:postcode":"95602",
    "sg:province":"CA",
    "sg:tags":[
        "engineer"
    ],
    "wof:name":"RPD & Assoc",
    "wof:placetype":"venue"
},
  "geometry": {"coordinates":[-121.064775,38.975746],"type":"Point"}
}