{
  "type": "Feature",
  "properties": {
    "addr:full":"295 Fell St Ste A San Francisco CA 94102",
    "addr:housenumber":"295",
    "addr:postcode":"94102",
    "addr:street":"Fell St Ste A",
    "iso:country":"US",
    "sg:address":"295 Fell St Ste A",
    "sg:city":"San Francisco",
    "sg:classifiers":[
        {
            "category":"Health Services",
            "subcategory":"Clinic",
            "type":"Services"
        }
    ],
    "sg:phone":"+1 415 286 3298",
    "sg:postcode":"94102",
    "sg:province":"CA",
    "sg:tags":[
        "counseling",
        "mental"
    ],
    "wof:name":"K. Marcus Hartsfield, MFT",
    "wof:placetype":"venue"
},
  "geometry": {"coordinates":[-122.422724,37.775993],"type":"Point"}
}