{
  "type": "Feature",
  "properties": {
    "addr:full":"2250 E 52nd Street Los Angeles CA 90058",
    "addr:housenumber":"2250",
    "addr:postcode":"90058",
    "addr:street":"E 52Nd Street",
    "iso:country":"US",
    "sg:address":"2250 E 52nd Street",
    "sg:city":"Los Angeles",
    "sg:classifiers":[
        {
            "category":"Shopping",
            "subcategory":"Hobbies, Toys, & Games",
            "type":"Retail Goods"
        },
        {
            "category":"Personal",
            "subcategory":"Barber",
            "type":"Services"
        }
    ],
    "sg:phone":"+1 323 588 6838",
    "sg:postcode":"90058",
    "sg:province":"CA",
    "sg:tags":[
        "toy",
        "store"
    ],
    "wof:name":"Universal Star Trading",
    "wof:placetype":"venue"
},
  "geometry": {"coordinates":[-118.23231800000001,33.995135],"type":"Point"}
}