{
  "type": "Feature",
  "properties": {
    "iso:country":"US",
    "sg:address":"1875 S Grant St",
    "sg:city":"San Mateo",
    "sg:classifiers":[
        {
            "category":"Insurance",
            "subcategory":"Insurance Agent",
            "type":"Services"
        }
    ],
    "sg:phone":"+1 650 345 3571",
    "sg:postcode":"94402",
    "sg:province":"CA",
    "sg:website":"www.sanmateosunriserotary.com",
    "wof:name":"State Farm Insurance",
    "wof:placetype":"venue"
},
  "geometry": {"coordinates":[-122.302091,37.554463],"type":"Point"}
}