{
  "type": "Feature",
  "properties": {
    "iso:country":"US",
    "sg:address":"9829 Venice Blvd",
    "sg:city":"Los Angeles",
    "sg:classifiers":[
        {
            "category":"Restaurant",
            "type":"Food & Drink"
        }
    ],
    "sg:menulink":"http://www.allmenus.com/ca/los-angeles/163515-rallys/menu/",
    "sg:phone":"+1 310 836 1187",
    "sg:postcode":"90034",
    "sg:province":"CA",
    "sg:tags":[
        "sandwich",
        "dog",
        "burger",
        "hot",
        "wrap",
        "american"
    ],
    "wof:name":"Rally's",
    "wof:placetype":"venue"
},
  "geometry": {"coordinates":[-118.39866600000001,34.023886],"type":"Point"}
}