{
  "type": "Feature",
  "properties": {
    "addr:full":"36 Central Ave Upland CA 91786",
    "addr:housenumber":"36",
    "addr:postcode":"91786",
    "addr:street":"Central Ave",
    "iso:country":"US",
    "sg:address":"36 Central Ave",
    "sg:city":"Upland",
    "sg:classifiers":[
        {
            "category":"Wholesale",
            "subcategory":"Electrical",
            "type":"Manufacturing & Wholesale Goods"
        }
    ],
    "sg:phone":"+1 909 985 9191",
    "sg:postcode":"91786",
    "sg:province":"CA",
    "sg:tags":[
        "control"
    ],
    "sg:website":"www.byrdelectronics.com",
    "wof:name":"Byrd Electronics",
    "wof:placetype":"venue"
},
  "geometry": {"coordinates":[-117.689533,34.095311],"type":"Point"}
}