{
  "type": "Feature",
  "properties": {
    "iso:country":"US",
    "sg:address":"27050 Moody Rd",
    "sg:city":"Los Altos Hills",
    "sg:classifiers":[
        {
            "category":"Building & Trades",
            "subcategory":"Landscaping Services",
            "type":"Services"
        }
    ],
    "sg:phone":"+1 650 948 9474",
    "sg:postcode":"94022",
    "sg:province":"CA",
    "sg:tags":[
        "landscape",
        "contractor"
    ],
    "sg:website":"www.valleylandscape.com",
    "wof:name":"Valley Landscape",
    "wof:placetype":"venue"
},
  "geometry": {"coordinates":[-122.16409,37.35685],"type":"Point"}
}