{
  "type": "Feature",
  "properties": {
    "addr:full":"2375 Dumbarton Ave Palo Alto CA 94303",
    "addr:housenumber":"2375",
    "addr:postcode":"94303",
    "addr:street":"Dumbarton Ave",
    "iso:country":"US",
    "sg:address":"2375 Dumbarton Ave",
    "sg:city":"Palo Alto",
    "sg:classifiers":[
        {
            "category":"Professional",
            "subcategory":"Computer Services",
            "type":"Services"
        }
    ],
    "sg:phone":"+1 650 322 5734",
    "sg:postcode":"94303",
    "sg:province":"CA",
    "sg:tags":[
        "programing",
        "custom"
    ],
    "wof:name":"Samcom",
    "wof:placetype":"venue"
},
  "geometry": {"coordinates":[-122.145837,37.470199],"type":"Point"}
}