{
  "type": "Feature",
  "properties": {
    "addr:full":"28072 Turlock Ct Laguna Niguel CA 92677",
    "addr:housenumber":"28072",
    "addr:postcode":"92677",
    "addr:street":"Turlock Ct",
    "iso:country":"US",
    "sg:address":"28072 Turlock Ct",
    "sg:city":"Laguna Niguel",
    "sg:classifiers":[
        {
            "category":"Professional",
            "subcategory":"Accounting & Tax Preparation",
            "type":"Services"
        }
    ],
    "sg:phone":"+1 949 389 9048",
    "sg:postcode":"92677",
    "sg:province":"CA",
    "sg:tags":[
        "return",
        "filing"
    ],
    "wof:name":"Gene Curtis",
    "wof:placetype":"venue"
},
  "geometry": {"coordinates":[-117.703591,33.554753],"type":"Point"}
}