{
  "type": "Feature",
  "properties": {
    "iso:country":"US",
    "sg:address":"6128 Telegraph Rd",
    "sg:city":"Ventura",
    "sg:classifiers":[
        {
            "category":"Banks & Credit Unions",
            "subcategory":"Bank",
            "type":"Services"
        }
    ],
    "sg:phone":"+1 805 339 9122",
    "sg:postcode":"93003",
    "sg:province":"CA",
    "sg:tags":[
        "loan",
        "real estate"
    ],
    "wof:name":"CFC Mortgage",
    "wof:placetype":"venue"
},
  "geometry": {"coordinates":[-119.213619,34.278019],"type":"Point"}
}