{
  "type": "Feature",
  "properties": {
    "addr:full":"251 River Oaks Pkwy San Jose CA 95134",
    "addr:housenumber":"251",
    "addr:postcode":"95134",
    "addr:street":"River Oaks Pkwy",
    "iso:country":"US",
    "sg:address":"251 River Oaks Pkwy",
    "sg:city":"San Jose",
    "sg:classifiers":[
        {
            "category":"Professional",
            "subcategory":"Research",
            "type":"Services"
        }
    ],
    "sg:phone":"+1 408 468 8100",
    "sg:postcode":"95134",
    "sg:province":"CA",
    "sg:tags":[
        "high",
        "information",
        "market",
        "provides",
        "to"
    ],
    "wof:name":"Gartner Inc",
    "wof:placetype":"venue"
},
  "geometry": {"coordinates":[-121.928405,37.403766],"type":"Point"}
}