{
  "type": "Feature",
  "properties": {
    "addr:full":"824 Trestle Glen Rd Oakland CA 94610",
    "addr:housenumber":"824",
    "addr:postcode":"94610",
    "addr:street":"Trestle Glen Rd",
    "iso:country":"US",
    "sg:address":"824 Trestle Glen Rd",
    "sg:city":"Oakland",
    "sg:classifiers":[
        {
            "category":"Education",
            "subcategory":"School",
            "type":"Public Place"
        }
    ],
    "sg:phone":"+1 510 451 2535",
    "sg:postcode":"94610",
    "sg:province":"CA",
    "sg:tags":[
        "k-",
        "private"
    ],
    "wof:name":"Mr Apple's English Academy",
    "wof:placetype":"venue"
},
  "geometry": {"coordinates":[-122.23940399999999,37.808369],"type":"Point"}
}