{
  "type": "Feature",
  "properties": {
    "iso:country":"US",
    "sg:address":"27200 Tourney Rd Ste 475",
    "sg:city":"Valencia",
    "sg:classifiers":[
        {
            "category":"Professional",
            "subcategory":"Lawyer & Legal Services",
            "type":"Services"
        }
    ],
    "sg:phone":"+1 310 657 1001",
    "sg:postcode":"91355",
    "sg:province":"CA",
    "sg:website":"www.mehtamann.com",
    "wof:name":"Mehta & Mann Atty At Law",
    "wof:placetype":"venue"
},
  "geometry": {"coordinates":[-118.577003,34.417301],"type":"Point"}
}