{
  "type": "Feature",
  "properties": {
    "iso:country":"US",
    "sg:address":"4707 Quail Lakes Dr",
    "sg:city":"Stockton",
    "sg:classifiers":[
        {
            "category":"Personal",
            "subcategory":"Beauty Salon",
            "type":"Services"
        }
    ],
    "sg:phone":"+1 209 478 4832",
    "sg:postcode":"95207",
    "sg:province":"CA",
    "wof:name":"Precision Cuts",
    "wof:placetype":"venue"
},
  "geometry": {"coordinates":[-121.340339,37.988286],"type":"Point"}
}