{
  "type": "Feature",
  "properties": {
    "addr:full":"433 N Camden Dr Beverly Hills CA 90210",
    "addr:housenumber":"433",
    "addr:postcode":"90210",
    "addr:street":"N Camden Dr",
    "iso:country":"US",
    "sg:address":"433 N Camden Dr",
    "sg:city":"Beverly Hills",
    "sg:classifiers":[
        {
            "category":"Banks & Credit Unions",
            "subcategory":"Bank",
            "type":"Services"
        }
    ],
    "sg:phone":"+1 310 859 3830",
    "sg:postcode":"90210",
    "sg:province":"CA",
    "sg:tags":[
        "loan",
        "real estate"
    ],
    "wof:name":"Wells Fargo Home Mortgage Inc",
    "wof:placetype":"venue"
},
  "geometry": {"coordinates":[-118.40483500000001,34.069216],"type":"Point"}
}