{
  "type": "Feature",
  "properties": {
    "iso:country":"US",
    "sg:address":"15315 Cholame Rd",
    "sg:city":"Victorville",
    "sg:classifiers":[
        {
            "category":"Wholesale",
            "subcategory":"Auto Parts",
            "type":"Manufacturing & Wholesale Goods"
        }
    ],
    "sg:phone":"+1 760 962 0163",
    "sg:postcode":"92392",
    "sg:province":"CA",
    "sg:tags":[
        "body",
        "shop",
        "automobile"
    ],
    "wof:name":"D'Angelos Automotive & Indstrl",
    "wof:placetype":"venue"
},
  "geometry": {"coordinates":[-117.326617,34.502078],"type":"Point"}
}