{
  "type": "Feature",
  "properties": {
    "iso:country":"US",
    "sg:address":"1328 N H St",
    "sg:city":"San Bernardino",
    "sg:classifiers":[
        {
            "category":"Shopping",
            "subcategory":"Clothing, Apparel, & Fashions",
            "type":"Retail Goods"
        }
    ],
    "sg:phone":"+1 909 888 4272",
    "sg:postcode":"92405",
    "sg:province":"CA",
    "sg:tags":[
        "uniform",
        "supply"
    ],
    "sg:website":"www.aramark.com",
    "wof:name":"Aramark Uniform Svc",
    "wof:placetype":"venue"
},
  "geometry": {"coordinates":[-117.300999,34.124117],"type":"Point"}
}