{
  "type": "Feature",
  "properties": {
    "addr:full":"612 S Long Beach Blvd Compton CA 90221",
    "addr:housenumber":"612",
    "addr:postcode":"90221",
    "addr:street":"S Long Beach Blvd",
    "iso:country":"US",
    "sg:address":"612 S Long Beach Blvd",
    "sg:city":"Compton",
    "sg:classifiers":[
        {
            "category":"Retail",
            "subcategory":"Car Wash",
            "type":"Services"
        }
    ],
    "sg:phone":"+1 310 631 3575",
    "sg:postcode":"90221",
    "sg:province":"CA",
    "sg:tags":[
        "truck",
        "cleaning"
    ],
    "wof:name":"Westmatic",
    "wof:placetype":"venue"
},
  "geometry": {"coordinates":[-118.207593,33.891607],"type":"Point"}
}