{
  "type": "Feature",
  "properties": {
    "iso:country":"US",
    "sg:address":"160 Bell Ave",
    "sg:city":"Piedmont",
    "sg:classifiers":[
        {
            "category":"Professional",
            "subcategory":"Lawyer & Legal Services",
            "type":"Services"
        }
    ],
    "sg:phone":"+1 510 547 0545",
    "sg:postcode":"94611",
    "sg:province":"CA",
    "sg:website":"danashultz.com/blog",
    "wof:name":"Dana H. Shultz, Attorney at Law",
    "wof:placetype":"venue"
},
  "geometry": {"coordinates":[-122.22563599999999,37.827407],"type":"Point"}
}