{
  "type": "Feature",
  "properties": {
    "addr:full":"2610 Crow Canyon Rd San Ramon CA 94583",
    "addr:housenumber":"2610",
    "addr:postcode":"ca 94583",
    "addr:street":"Crow Canyon Rd",
    "iso:country":"US",
    "sg:address":"2610 Crow Canyon Rd",
    "sg:city":"San Ramon",
    "sg:classifiers":[
        {
            "category":"Professional",
            "subcategory":"Computer Services",
            "type":"Services"
        }
    ],
    "sg:phone":"+1 925 552 6007",
    "sg:postcode":"94583",
    "sg:province":"CA",
    "sg:tags":[
        "programing",
        "custom"
    ],
    "sg:website":"www.madaboutberries.com",
    "wof:name":"Meridian Technology Group",
    "wof:placetype":"venue"
},
  "geometry": {"coordinates":[-121.98579100000001,37.77388],"type":"Point"}
}