{
  "type": "Feature",
  "properties": {
    "iso:country":"US",
    "sg:address":"18757 Burbank Blvd # 116",
    "sg:city":"Tarzana",
    "sg:classifiers":[
        {
            "category":"Professional",
            "subcategory":"Computer Services",
            "type":"Services"
        },
        {
            "category":"Communications",
            "type":"Services"
        },
        {
            "category":"Internet Cafe",
            "subcategory":"None",
            "type":"Food & Drink"
        }
    ],
    "sg:phone":"+1 310 826 8634",
    "sg:postcode":"91356",
    "sg:province":"CA",
    "sg:tags":[
        "product",
        "designer",
        "consultant",
        "system",
        "data",
        "software"
    ],
    "wof:name":"Zenith Information Group",
    "wof:placetype":"venue"
},
  "geometry": {"coordinates":[-118.54223,34.172142],"type":"Point"}
}