{
  "type": "Feature",
  "properties": {
    "addr:full":"1770 Ocean Ave San Francisco CA 94112",
    "addr:housenumber":"1770",
    "addr:postcode":"94112",
    "addr:street":"Ocean Ave",
    "iso:country":"US",
    "sg:address":"1770 Ocean Ave",
    "sg:city":"San Francisco",
    "sg:classifiers":[
        {
            "category":"Cinema",
            "subcategory":"Movie Rental",
            "type":"Entertainment"
        }
    ],
    "sg:phone":"+1 415 333 3468",
    "sg:postcode":"94112",
    "sg:province":"CA",
    "sg:tags":[
        "leasing",
        "video",
        "disc",
        "tape"
    ],
    "sg:website":"www.blockbuster.com",
    "wof:name":"Blockbuster Video",
    "wof:placetype":"venue"
},
  "geometry": {"coordinates":[-122.460933,37.724987],"type":"Point"}
}