{
  "type": "Feature",
  "properties": {
    "iso:country":"US",
    "sg:address":"425 W Bonita Ave",
    "sg:city":"San Dimas",
    "sg:classifiers":[
        {
            "category":"Banks & Credit Unions",
            "subcategory":"Bank",
            "type":"Services"
        }
    ],
    "sg:phone":"+1 909 542 0460",
    "sg:postcode":"91773",
    "sg:province":"CA",
    "sg:tags":[
        "loan",
        "real estate"
    ],
    "wof:name":"Acropolis Mortgage",
    "wof:placetype":"venue"
},
  "geometry": {"coordinates":[-117.81538399999999,34.106748],"type":"Point"}
}