{
  "type": "Feature",
  "properties": {
    "iso:country":"US",
    "sg:address":"20450 Stevens Creek Blvd",
    "sg:city":"Cupertino",
    "sg:classifiers":[
        {
            "category":"Manufacturing",
            "subcategory":"Printing",
            "type":"Manufacturing & Wholesale Goods"
        }
    ],
    "sg:phone":"+1 408 470 4500",
    "sg:postcode":"95014",
    "sg:province":"CA",
    "sg:tags":[
        "publisher",
        "software"
    ],
    "wof:name":"Panta Systems",
    "wof:placetype":"venue"
},
  "geometry": {"coordinates":[-122.02833,37.322764],"type":"Point"}
}