{
  "type": "Feature",
  "properties": {
    "iso:country":"US",
    "sg:address":"5301 N Commerce Ave #1",
    "sg:city":"Moorpark",
    "sg:classifiers":[
        {
            "category":"Personal",
            "type":"Services"
        }
    ],
    "sg:phone":"+1 877 801 9037",
    "sg:postcode":"93021",
    "sg:province":"CA",
    "sg:tags":[
        "butlers'",
        "maids'"
    ],
    "sg:website":"http://local.ingenio.com/Listings/Details.aspx?NUM=a%3a9779274%3a13%3a4859924%3a14%3a0%3a7",
    "wof:name":"Merry Maids",
    "wof:placetype":"venue"
},
  "geometry": {"coordinates":[-118.89897499999999,34.280187],"type":"Point"}
}