{
  "type": "Feature",
  "properties": {
    "addr:full":"1768 Colorado Blvd Los Angeles CA 90041",
    "addr:housenumber":"1768",
    "addr:postcode":"90041",
    "addr:street":"Colorado Blvd",
    "iso:country":"US",
    "sg:address":"1768 Colorado Blvd",
    "sg:city":"Los Angeles",
    "sg:classifiers":[
        {
            "category":"Retail",
            "subcategory":"Repair Shop",
            "type":"Services"
        },
        {
            "category":"Building & Trades",
            "subcategory":"Construction",
            "type":"Services"
        }
    ],
    "sg:phone":"+1 323 256 8424",
    "sg:postcode":"90041",
    "sg:province":"CA",
    "sg:tags":[
        "sink",
        "bathtub",
        "refinishing",
        "contractor"
    ],
    "wof:name":"Reglazing Specialists",
    "wof:placetype":"venue"
},
  "geometry": {"coordinates":[-118.206182,34.139347],"type":"Point"}
}