{
  "type": "Feature",
  "properties": {
    "iso:country":"US",
    "sg:address":"1000 Universal Studios Blvd",
    "sg:city":"North Hollywood",
    "sg:classifiers":[
        {
            "category":"Banks & Credit Unions",
            "subcategory":"Investment Brokerage",
            "type":"Services"
        }
    ],
    "sg:phone":"+1 818 506 9178",
    "sg:postcode":"91608",
    "sg:province":"CA",
    "sg:tags":[
        "investing"
    ],
    "sg:website":"www.tjgroup.com",
    "wof:name":"Tj Group LLC",
    "wof:placetype":"venue"
},
  "geometry": {"coordinates":[-118.351488,34.134247],"type":"Point"}
}