{
  "type": "Feature",
  "properties": {
    "iso:country":"US",
    "sg:address":"216 S Reservoir St",
    "sg:city":"Pomona",
    "sg:classifiers":[
        {
            "category":"Organizations",
            "subcategory":"Religious Organization",
            "type":"Services"
        }
    ],
    "sg:phone":"+1 909 623 5515",
    "sg:postcode":"91766",
    "sg:province":"CA",
    "sg:tags":[
        "church"
    ],
    "wof:name":"Jesus S LA Roca",
    "wof:placetype":"venue"
},
  "geometry": {"coordinates":[-117.732566,34.057503],"type":"Point"}
}