{
  "type": "Feature",
  "properties": {
    "addr:full":"8333 Airport Blvd Los Angeles CA 90045",
    "addr:housenumber":"8333",
    "addr:postcode":"90045",
    "addr:street":"Airport Blvd",
    "iso:country":"US",
    "sg:address":"8333 Airport Blvd",
    "sg:city":"Los Angeles",
    "sg:classifiers":[
        {
            "category":"Education",
            "subcategory":"Preschool",
            "type":"Public Place"
        },
        {
            "category":"Education",
            "subcategory":"School",
            "type":"Public Place"
        }
    ],
    "sg:phone":"+1 310 216 6641",
    "sg:postcode":"90045",
    "sg:province":"CA",
    "sg:tags":[
        "elementary"
    ],
    "wof:name":"Carousel Schools",
    "wof:placetype":"venue"
},
  "geometry": {"coordinates":[-118.385002,33.961102],"type":"Point"}
}