{
  "type": "Feature",
  "properties": {
    "iso:country":"US",
    "sg:address":"1700 E Cesar E Chavez Ave",
    "sg:city":"Los Angeles",
    "sg:classifiers":[
        {
            "category":"Health Services",
            "subcategory":"Doctor",
            "type":"Services"
        }
    ],
    "sg:phone":"+1 323 262 4176",
    "sg:postcode":"90033",
    "sg:province":"CA",
    "sg:tags":[
        "physician",
        "surgeon"
    ],
    "wof:name":"Francis Y Lau Inc",
    "wof:placetype":"venue"
},
  "geometry": {"coordinates":[-118.21638,34.050651],"type":"Point"}
}