{
  "type": "Feature",
  "properties": {
    "iso:country":"US",
    "sg:address":"103 Vallerio Ave",
    "sg:city":"Ojai",
    "sg:classifiers":[
        {
            "category":"Organizations",
            "subcategory":"Non-profit Organization",
            "type":"Services"
        }
    ],
    "sg:phone":"+1 805 646 6830",
    "sg:postcode":"93023",
    "sg:province":"CA",
    "sg:tags":[
        "alternative",
        "abortion"
    ],
    "wof:name":"Pregnancy Hotline",
    "wof:placetype":"venue"
},
  "geometry": {"coordinates":[-119.26430499999999,34.442127],"type":"Point"}
}