{
  "type": "Feature",
  "properties": {
    "addr:full":"1050 77th Ave Oakland CA 94621",
    "addr:housenumber":"1050",
    "addr:postcode":"94621",
    "addr:street":"77Th Ave",
    "iso:country":"US",
    "sg:address":"1050 77th Ave",
    "sg:city":"Oakland",
    "sg:classifiers":[
        {
            "category":"Freight",
            "type":"Transportation"
        }
    ],
    "sg:phone":"+1 510 632 7112",
    "sg:postcode":"94621",
    "sg:province":"CA",
    "sg:tags":[
        "local",
        "trucking"
    ],
    "wof:name":"R & A Trucking Company",
    "wof:placetype":"venue"
},
  "geometry": {"coordinates":[-122.194012,37.751235],"type":"Point"}
}