{
  "type": "Feature",
  "properties": {
    "iso:country":"US",
    "sg:address":"3025 W Olive Ave",
    "sg:city":"Burbank",
    "sg:classifiers":[
        {
            "category":"Autos & Motor Vehicles",
            "subcategory":"Fuel & Gas Station",
            "type":"Retail Goods"
        },
        {
            "category":"Government",
            "subcategory":"Office",
            "type":"Public Place"
        }
    ],
    "sg:phone":"+1 818 559 3449",
    "sg:postcode":"91505",
    "sg:province":"CA",
    "sg:tags":[
        "automobile",
        "smog",
        "inspection",
        "check"
    ],
    "sg:website":"www.fairviewauto.net",
    "wof:name":"FAIRVIEW AUTO",
    "wof:placetype":"venue"
},
  "geometry": {"coordinates":[-118.333916,34.157188],"type":"Point"}
}