{
  "type": "Feature",
  "properties": {
    "iso:country":"US",
    "sg:address":"2037 Irving St",
    "sg:city":"San Francisco",
    "sg:classifiers":[
        {
            "category":"Professional",
            "subcategory":"Lawyer & Legal Services",
            "type":"Services"
        }
    ],
    "sg:phone":"+1 415 664 0998",
    "sg:postcode":"94122",
    "sg:province":"CA",
    "sg:tags":[
        "attorney"
    ],
    "wof:name":"De Kirby Vaughan Law Offices",
    "wof:placetype":"venue"
},
  "geometry": {"coordinates":[-122.48002099999999,37.763362],"type":"Point"}
}