{
  "type": "Feature",
  "properties": {
    "addr:full":"1171 Cam Tassajara Danville CA 94526",
    "addr:housenumber":"1171",
    "addr:postcode":"94526",
    "addr:street":"Cam Tassajara",
    "iso:country":"US",
    "sg:address":"1171 Cam Tassajara",
    "sg:city":"Danville",
    "sg:classifiers":[
        {
            "category":"Professional",
            "subcategory":"Advertising",
            "type":"Services"
        }
    ],
    "sg:phone":"+1 925 362 4656",
    "sg:postcode":"94526",
    "sg:province":"CA",
    "sg:tags":[
        "counselor"
    ],
    "sg:website":"www.website-art.com",
    "wof:name":"Design For Advertising",
    "wof:placetype":"venue"
},
  "geometry": {"coordinates":[-121.98180000000001,37.82078],"type":"Point"}
}