{
  "type": "Feature",
  "properties": {
    "iso:country":"US",
    "sg:address":"900 N Coast Hwy",
    "sg:city":"Laguna Beach",
    "sg:classifiers":[
        {
            "category":"Professional",
            "type":"Services"
        }
    ],
    "sg:phone":"+1 949 494 3566",
    "sg:postcode":"92651",
    "sg:province":"CA",
    "sg:tags":[
        "consultant",
        "geological"
    ],
    "wof:name":"Peter Borella Engineering",
    "wof:placetype":"venue"
},
  "geometry": {"coordinates":[-117.797664,33.547508],"type":"Point"}
}