{
  "type": "Feature",
  "properties": {
    "iso:country":"US",
    "sg:address":"11 Bay St",
    "sg:city":"San Rafael",
    "sg:classifiers":[
        {
            "category":"Wholesale",
            "subcategory":"Auto Parts",
            "type":"Manufacturing & Wholesale Goods"
        }
    ],
    "sg:phone":"+1 415 482 9668",
    "sg:postcode":"94901",
    "sg:province":"CA",
    "sg:tags":[
        "shop",
        "automotive",
        "sales",
        "repair"
    ],
    "wof:name":"Petestuffcom",
    "wof:placetype":"venue"
},
  "geometry": {"coordinates":[-122.515038,37.968263],"type":"Point"}
}