{
  "type": "Feature",
  "properties": {
    "iso:country":"US",
    "sg:address":"3655 Foothill Blvd",
    "sg:city":"La Crescenta",
    "sg:classifiers":[
        {
            "category":"Food & Beverages",
            "subcategory":"Liquor & Beverages",
            "type":"Retail Goods"
        }
    ],
    "sg:phone":"+1 818 248 4410",
    "sg:postcode":"91214",
    "sg:province":"CA",
    "wof:name":"Foothill Liquor",
    "wof:placetype":"venue"
},
  "geometry": {"coordinates":[-118.258352,34.235655],"type":"Point"}
}