{
  "type": "Feature",
  "properties": {
    "addr:full":"27584 Commerce Center Dr Temecula CA 92590",
    "addr:housenumber":"27584",
    "addr:postcode":"92590",
    "addr:street":"Commerce Center Dr",
    "iso:country":"US",
    "sg:address":"27584 Commerce Center Dr",
    "sg:city":"Temecula",
    "sg:classifiers":[
        {
            "category":"Autos & Motor Vehicles",
            "subcategory":"Auto Supplies",
            "type":"Retail Goods"
        }
    ],
    "sg:phone":"+1 951 676 6010",
    "sg:postcode":"92590",
    "sg:province":"CA",
    "sg:tags":[
        "automotive",
        "tire",
        "repair"
    ],
    "wof:name":"Barneys Tire & Wheel Inc",
    "wof:placetype":"venue"
},
  "geometry": {"coordinates":[-117.160642,33.511834],"type":"Point"}
}