{
  "type": "Feature",
  "properties": {
    "addr:full":"866 Diamond St San Diego CA 92109",
    "addr:housenumber":"866",
    "addr:postcode":"92109",
    "addr:street":"Diamond St",
    "iso:country":"US",
    "sg:address":"866 Diamond St",
    "sg:city":"San Diego",
    "sg:classifiers":[
        {
            "category":"Retail",
            "subcategory":"Repair Shop",
            "type":"Services"
        }
    ],
    "sg:phone":"+1 619 423 7085",
    "sg:postcode":"92109",
    "sg:province":"CA",
    "sg:tags":[
        "lock",
        "locksmith"
    ],
    "wof:name":"Bonnie & Clyde's Locksmiths",
    "wof:placetype":"venue"
},
  "geometry": {"coordinates":[-117.255633,32.799562],"type":"Point"}
}