{
  "type": "Feature",
  "properties": {
    "iso:country":"US",
    "sg:address":"6116 Merced Ave 165",
    "sg:city":"Oakland",
    "sg:classifiers":[
        {
            "category":"Professional",
            "type":"Services"
        },
        {
            "category":"Personal",
            "type":"Services"
        }
    ],
    "sg:phone":"+1 510 893 6896",
    "sg:postcode":"94611",
    "sg:province":"CA",
    "sg:tags":[
        "mover",
        "material",
        "moving",
        "services-labor"
    ],
    "sg:website":"http://www.familypackers.com",
    "wof:name":"Family Packers",
    "wof:placetype":"venue"
},
  "geometry": {"coordinates":[-122.209496,37.825],"type":"Point"}
}