{
  "type": "Feature",
  "properties": {
    "iso:country":"US",
    "sg:address":"35 Villa Ave",
    "sg:city":"Clovis",
    "sg:classifiers":[
        {
            "category":"Shopping",
            "subcategory":"Clothing, Apparel, & Fashions",
            "type":"Retail Goods"
        }
    ],
    "sg:phone":"+1 559 297 8213",
    "sg:postcode":"93612",
    "sg:province":"CA",
    "sg:tags":[
        "dressmaker"
    ],
    "wof:name":"Janet's Custom Sewing",
    "wof:placetype":"venue"
},
  "geometry": {"coordinates":[-119.713407,36.830266],"type":"Point"}
}