{
  "type": "Feature",
  "properties": {
    "iso:country":"US",
    "sg:address":"224 W California St",
    "sg:city":"Ontario",
    "sg:classifiers":[
        {
            "category":"Education",
            "subcategory":"School",
            "type":"Public Place"
        }
    ],
    "sg:phone":"+1 909 988 2280",
    "sg:postcode":"91762",
    "sg:province":"CA",
    "wof:name":"Mount Zion Christian School",
    "wof:placetype":"venue"
},
  "geometry": {"coordinates":[-117.65325900000001,34.055826],"type":"Point"}
}