{
  "type": "Feature",
  "properties": {
    "iso:country":"US",
    "sg:address":"1815 W 205th St",
    "sg:city":"Torrance",
    "sg:classifiers":[
        {
            "category":"Wholesale",
            "subcategory":"Electrical",
            "type":"Manufacturing & Wholesale Goods"
        },
        {
            "category":"Building & Trades",
            "subcategory":"Plumbing",
            "type":"Services"
        }
    ],
    "sg:phone":"+1 310 320 9800",
    "sg:postcode":"90501",
    "sg:province":"CA",
    "sg:tags":[
        "conditioning",
        "air",
        "refrigeration",
        "system",
        "contractor"
    ],
    "sg:website":"www.atlassales.com",
    "wof:name":"Atlas Sales",
    "wof:placetype":"venue"
},
  "geometry": {"coordinates":[-118.309833,33.844821],"type":"Point"}
}