{
  "type": "Feature",
  "properties": {
    "iso:country":"US",
    "sg:address":"7889 Firebrand Dr",
    "sg:city":"Dublin",
    "sg:classifiers":[
        {
            "category":"Building & Trades",
            "subcategory":"Construction",
            "type":"Services"
        }
    ],
    "sg:phone":"+1 925 833 8613",
    "sg:postcode":"94568",
    "sg:province":"CA",
    "sg:tags":[
        "roofing",
        "industrial",
        "contractors-commercial",
        "contractor"
    ],
    "wof:name":"Burnett Roofing",
    "wof:placetype":"venue"
},
  "geometry": {"coordinates":[-121.937933,37.713029],"type":"Point"}
}