{
  "type": "Feature",
  "properties": {
    "addr:full":"300 E 53rd St Los Angeles CA 90011",
    "addr:housenumber":"300",
    "addr:postcode":"90011",
    "addr:street":"E 53Rd St",
    "iso:country":"US",
    "sg:address":"300 E 53rd St",
    "sg:city":"Los Angeles",
    "sg:classifiers":[
        {
            "category":"Building & Trades",
            "subcategory":"Construction",
            "type":"Services"
        }
    ],
    "sg:phone":"+1 323 846 8411",
    "sg:postcode":"90011",
    "sg:province":"CA",
    "sg:tags":[
        "contractor"
    ],
    "wof:name":"Turner Construction",
    "wof:placetype":"venue"
},
  "geometry": {"coordinates":[-118.270118,33.994112],"type":"Point"}
}