{
  "type": "Feature",
  "properties": {
    "iso:country":"US",
    "sg:address":"1175 Dairy Ln",
    "sg:city":"Arroyo Grande",
    "sg:classifiers":[
        {
            "category":"Professional",
            "subcategory":"Engineering",
            "type":"Services"
        }
    ],
    "sg:phone":"+1 805 541 6000",
    "sg:postcode":"93420",
    "sg:province":"CA",
    "sg:tags":[
        "engineer"
    ],
    "wof:name":"Mc Chesney Engineering",
    "wof:placetype":"venue"
},
  "geometry": {"coordinates":[-120.573819,35.177994],"type":"Point"}
}