{
  "type": "Feature",
  "properties": {
    "addr:full":"115 W Arrellaga St Santa Barbara CA 93101",
    "addr:housenumber":"115",
    "addr:postcode":"93101",
    "addr:street":"W Arrellaga St",
    "iso:country":"US",
    "sg:address":"115 W Arrellaga St",
    "sg:city":"Santa Barbara",
    "sg:classifiers":[
        {
            "category":"Health Services",
            "subcategory":"Health Practitioner",
            "type":"Services"
        }
    ],
    "sg:phone":"+1 805 962 0508",
    "sg:postcode":"93101",
    "sg:province":"CA",
    "sg:tags":[
        "psychologist"
    ],
    "wof:name":"Anxiety & Panic Disorder Clnc",
    "wof:placetype":"venue"
},
  "geometry": {"coordinates":[-119.71164400000001,34.425065],"type":"Point"}
}