{
  "type": "Feature",
  "properties": {
    "addr:full":"19893 Berenda Blvd Madera CA 93638",
    "addr:postcode":"19893;93638",
    "addr:street":"Berenda Blvd",
    "iso:country":"US",
    "sg:address":"19893 Berenda Blvd",
    "sg:city":"Madera",
    "sg:classifiers":[
        {
            "category":"Building & Trades",
            "subcategory":"Construction",
            "type":"Services"
        }
    ],
    "sg:phone":"+1 559 675 8122",
    "sg:postcode":"93638",
    "sg:province":"CA",
    "sg:tags":[
        "roofing",
        "contractor"
    ],
    "sg:website":"www.phoenixcoatings.com",
    "wof:name":"Phoenix Coatings Inc",
    "wof:placetype":"venue"
},
  "geometry": {"coordinates":[-120.150059,37.038346],"type":"Point"}
}