{
  "type": "Feature",
  "properties": {
    "addr:full":"1210 S State College Blvd Anaheim CA 92806",
    "addr:housenumber":"1210",
    "addr:postcode":"92806",
    "addr:street":"S;Blvd",
    "iso:country":"US",
    "sg:address":"1210 S State College Blvd",
    "sg:city":"Anaheim",
    "sg:classifiers":[
        {
            "category":"Food & Beverages",
            "subcategory":"Liquor & Beverages",
            "type":"Retail Goods"
        }
    ],
    "sg:phone":"+1 714 776 1722",
    "sg:postcode":"92806",
    "sg:province":"CA",
    "sg:tags":[
        "beer",
        "spirit",
        "wine"
    ],
    "wof:name":"Star Liquor",
    "wof:placetype":"venue"
},
  "geometry": {"coordinates":[-117.889,33.817699],"type":"Point"}
}