{
  "type": "Feature",
  "properties": {
    "iso:country":"US",
    "sg:address":"947 State Rte 66",
    "sg:city":"Glendora",
    "sg:classifiers":[
        {
            "category":"Restaurant",
            "type":"Food & Drink"
        }
    ],
    "sg:phone":"+1 626 857 7270",
    "sg:postcode":"91740",
    "sg:province":"CA",
    "wof:name":"Sinbad Deli & Cafe",
    "wof:placetype":"venue"
},
  "geometry": {"coordinates":[-117.84835200000001,34.128787],"type":"Point"}
}