{
  "type": "Feature",
  "properties": {
    "iso:country":"US",
    "sg:address":"4049 Wilshire Blvd",
    "sg:city":"Los Angeles",
    "sg:classifiers":[
        {
            "category":"Home & Garden",
            "subcategory":"Home Furnishings",
            "type":"Retail Goods"
        }
    ],
    "sg:phone":"+1 213 368 4242",
    "sg:postcode":"90010",
    "sg:province":"CA",
    "sg:tags":[
        "housewares"
    ],
    "wof:name":"St James China Corp",
    "wof:placetype":"venue"
},
  "geometry": {"coordinates":[-118.316225,34.061771],"type":"Point"}
}