{
  "type": "Feature",
  "properties": {
    "addr:full":"10701 Wilshire Blvd Los Angeles CA 90024",
    "addr:housenumber":"10701",
    "addr:postcode":"90024",
    "addr:street":"Wilshire Blvd",
    "iso:country":"US",
    "sg:address":"10701 Wilshire Blvd",
    "sg:city":"Los Angeles",
    "sg:classifiers":[
        {
            "category":"Real Estate",
            "subcategory":"Real Estate Operator",
            "type":"Services"
        }
    ],
    "sg:phone":"+1 310 474 3591",
    "sg:postcode":"90024",
    "sg:province":"CA",
    "sg:tags":[
        "apartment"
    ],
    "wof:name":"Crown Towers",
    "wof:placetype":"venue"
},
  "geometry": {"coordinates":[-118.435997,34.060799],"type":"Point"}
}