{
  "type": "Feature",
  "properties": {
    "iso:country":"US",
    "sg:address":"1951 Hartnell Ave",
    "sg:city":"Redding",
    "sg:classifiers":[
        {
            "category":"Real Estate",
            "subcategory":"Real Estate Operator",
            "type":"Services"
        }
    ],
    "sg:phone":"+1 530 222 4229",
    "sg:postcode":"96002",
    "sg:province":"CA",
    "sg:tags":[
        "apartment"
    ],
    "wof:name":"Hartnell Oaks-Anderson Bros",
    "wof:placetype":"venue"
},
  "geometry": {"coordinates":[-122.335258,40.563634],"type":"Point"}
}