{
  "type": "Feature",
  "properties": {
    "iso:country":"US",
    "sg:address":"16307 Chino Corona Rd",
    "sg:city":"Chino",
    "sg:classifiers":[
        {
            "category":"Food & Beverages",
            "subcategory":"Groceries & Convenience Stores",
            "type":"Retail Goods"
        }
    ],
    "sg:phone":"+1 909 597 6102",
    "sg:postcode":"91708",
    "sg:province":"CA",
    "sg:tags":[
        "market"
    ],
    "wof:name":"Baci's Vera Villa Market",
    "wof:placetype":"venue"
},
  "geometry": {"coordinates":[-117.62192,33.946125],"type":"Point"}
}