{
  "type": "Feature",
  "properties": {
    "addr:full":"222 W 39th Ave San Mateo CA 94403",
    "addr:housenumber":"222",
    "addr:postcode":"94403",
    "addr:street":"W 39Th Ave",
    "iso:country":"US",
    "sg:address":"222 W 39th Ave",
    "sg:city":"San Mateo",
    "sg:classifiers":[
        {
            "category":"Health Services",
            "subcategory":"Doctor",
            "type":"Services"
        },
        {
            "category":"Health Services",
            "subcategory":"Hospital",
            "type":"Services"
        }
    ],
    "sg:phone":"+1 650 573 2222",
    "sg:postcode":"94403",
    "sg:province":"CA",
    "sg:tags":[
        "medicine",
        "obstetrician",
        "internal",
        "gynecologist"
    ],
    "wof:name":"San Mateo Medical Center",
    "wof:placetype":"venue"
},
  "geometry": {"coordinates":[-122.300003,37.530102],"type":"Point"}
}