{
  "type": "Feature",
  "properties": {
    "addr:full":"140 Las Tunas Dr Arcadia CA 91007",
    "addr:housenumber":"140",
    "addr:postcode":"91007",
    "addr:street":"Las Tunas Dr",
    "iso:country":"US",
    "sg:address":"140 Las Tunas Dr",
    "sg:city":"Arcadia",
    "sg:classifiers":[
        {
            "category":"Restaurant",
            "type":"Food & Drink"
        }
    ],
    "sg:phone":"+1 626 445 0544",
    "sg:postcode":"91007",
    "sg:province":"CA",
    "wof:name":"Alex Di Peppe's Italian Rstrnt",
    "wof:placetype":"venue"
},
  "geometry": {"coordinates":[-118.034238,34.107653],"type":"Point"}
}