{
  "type": "Feature",
  "properties": {
    "addr:full":"1821 Charter Way Stockton CA 95205",
    "addr:housenumber":"1821",
    "addr:postcode":"95205",
    "addr:street":"Charter Way",
    "iso:country":"US",
    "sg:address":"1821 Charter Way",
    "sg:city":"Stockton",
    "sg:classifiers":[
        {
            "category":"Manufacturing",
            "subcategory":"Furniture",
            "type":"Manufacturing & Wholesale Goods"
        }
    ],
    "sg:phone":"+1 209 948 8023",
    "sg:postcode":"95205",
    "sg:province":"CA",
    "sg:tags":[
        "rack"
    ],
    "sg:website":"www.andersenrack.com",
    "wof:name":"Anderson-Hannibal Rack",
    "wof:placetype":"venue"
},
  "geometry": {"coordinates":[-121.247224,37.940425],"type":"Point"}
}