{
  "type": "Feature",
  "properties": {
    "addr:full":"3051 12th Avenue Los Angeles CA 90018",
    "addr:housenumber":"3051",
    "addr:postcode":"90018",
    "addr:street":"12Th Avenue",
    "iso:country":"US",
    "sg:address":"3051 12th Avenue",
    "sg:city":"Los Angeles",
    "sg:classifiers":[
        {
            "category":"Banks & Credit Unions",
            "subcategory":"Financial Services",
            "type":"Services"
        }
    ],
    "sg:phone":"+1 323 766 9239",
    "sg:postcode":"90018",
    "sg:province":"CA",
    "sg:tags":[
        "broker",
        "mortgage"
    ],
    "wof:name":"Harbor Funding",
    "wof:placetype":"venue"
},
  "geometry": {"coordinates":[-118.331521,34.026209],"type":"Point"}
}