{
  "type": "Feature",
  "properties": {
    "iso:country":"US",
    "sg:address":"1501 Anita Ln",
    "sg:city":"Newport Beach",
    "sg:classifiers":[
        {
            "category":"Professional",
            "subcategory":"Management & Consulting",
            "type":"Services"
        }
    ],
    "sg:phone":"+1 949 515 3420",
    "sg:postcode":"92660",
    "sg:province":"CA",
    "sg:tags":[
        "consultant",
        "business"
    ],
    "wof:name":"Que 1",
    "wof:placetype":"venue"
},
  "geometry": {"coordinates":[-117.897374,33.63142],"type":"Point"}
}