{
  "type": "Feature",
  "properties": {
    "iso:country":"US",
    "sg:address":"521 W Montecito St",
    "sg:city":"Santa Barbara",
    "sg:classifiers":[
        {
            "category":"Shopping",
            "subcategory":"Clothing, Apparel, & Fashions",
            "type":"Retail Goods"
        }
    ],
    "sg:phone":"+1 805 963 9121",
    "sg:postcode":"93101",
    "sg:province":"CA",
    "wof:name":"Vixen Clothing",
    "wof:placetype":"venue"
},
  "geometry": {"coordinates":[-119.700188,34.408092],"type":"Point"}
}