{
  "type": "Feature",
  "properties": {
    "iso:country":"US",
    "sg:address":"11900 Big Tujunga Canyon Rd",
    "sg:city":"Tujunga",
    "sg:classifiers":[
        {
            "category":"Recreation",
            "subcategory":"Picnic Area",
            "type":"Entertainment"
        },
        {
            "category":"Community Center",
            "type":"Public Place"
        }
    ],
    "sg:phone":"+1 818 353 3188",
    "sg:postcode":"91042",
    "sg:province":"CA",
    "sg:tags":[
        "amusement",
        "arcade"
    ],
    "wof:name":"Robele Farms",
    "wof:placetype":"venue"
},
  "geometry": {"coordinates":[-118.294696,34.281595],"type":"Point"}
}