{
  "type": "Feature",
  "properties": {
    "addr:full":"535 N San Jacinto St Hemet CA 92543",
    "addr:housenumber":"535",
    "addr:postcode":"92543",
    "addr:street":"N San Jacinto St",
    "iso:country":"US",
    "sg:address":"535 N San Jacinto St",
    "sg:city":"Hemet",
    "sg:classifiers":[
        {
            "category":"Food & Beverages",
            "subcategory":"Bakery",
            "type":"Retail Goods"
        }
    ],
    "sg:phone":"+1 951 658 5700",
    "sg:postcode":"92543",
    "sg:province":"CA",
    "sg:tags":[
        "eating"
    ],
    "wof:name":"Donut Factory",
    "wof:placetype":"venue"
},
  "geometry": {"coordinates":[-116.95876699999999,33.754949],"type":"Point"}
}