{
  "type": "Feature",
  "properties": {
    "addr:full":"968 Admiral Callaghan Ln Vallejo CA 94591",
    "addr:housenumber":"968",
    "addr:postcode":"94591",
    "addr:street":"Admiral Callaghan Ln",
    "iso:country":"US",
    "sg:address":"968 Admiral Callaghan Ln",
    "sg:city":"Vallejo",
    "sg:classifiers":[
        {
            "category":"Airline",
            "type":"Transportation"
        }
    ],
    "sg:phone":"+1 650 634 4822",
    "sg:postcode":"94591",
    "sg:province":"CA",
    "sg:tags":[
        "scheduled",
        "air"
    ],
    "wof:name":"United",
    "wof:placetype":"venue"
},
  "geometry": {"coordinates":[-122.22451599999999,38.131357],"type":"Point"}
}