{
  "type": "Feature",
  "properties": {
    "addr:full":"400 E College St Fallbrook CA 92028",
    "addr:housenumber":"400",
    "addr:postcode":"92028",
    "addr:street":"E College St",
    "iso:country":"US",
    "sg:address":"400 E College St",
    "sg:city":"Fallbrook",
    "sg:classifiers":[
        {
            "category":"Organizations",
            "subcategory":"Religious Organization",
            "type":"Services"
        }
    ],
    "sg:phone":"+1 760 723 8291",
    "sg:postcode":"92028",
    "sg:province":"CA",
    "sg:tags":[
        "space",
        "venue",
        "event",
        "church"
    ],
    "wof:name":"Hilltop Center",
    "wof:placetype":"venue"
},
  "geometry": {"coordinates":[-117.248001,33.379002],"type":"Point"}
}