{
  "type": "Feature",
  "properties": {
    "addr:full":"24120 Garnier St Torrance CA 90505",
    "addr:postcode":"24120;90505",
    "addr:street":"Garnier St",
    "iso:country":"US",
    "sg:address":"24120 Garnier St",
    "sg:city":"Torrance",
    "sg:classifiers":[
        {
            "category":"Manufacturing",
            "subcategory":"Electronics",
            "type":"Manufacturing & Wholesale Goods"
        }
    ],
    "sg:phone":"+1 310 517 6456",
    "sg:postcode":"90505",
    "sg:province":"CA",
    "sg:tags":[
        "manufacture",
        "microcircuit"
    ],
    "wof:name":"Raytheon",
    "wof:placetype":"venue"
},
  "geometry": {"coordinates":[-118.338419,33.807868],"type":"Point"}
}