{
  "type": "Feature",
  "properties": {
    "addr:full":"575 N Driftwood Ave Rialto CA 92376",
    "addr:housenumber":"575",
    "addr:postcode":"92376",
    "addr:street":"N Driftwood Ave",
    "iso:country":"US",
    "sg:address":"575 N Driftwood Ave",
    "sg:city":"Rialto",
    "sg:classifiers":[
        {
            "category":"Professional",
            "subcategory":"Engineering",
            "type":"Services"
        }
    ],
    "sg:phone":"+1 909 873 0490",
    "sg:postcode":"92376",
    "sg:province":"CA",
    "sg:tags":[
        "engineer"
    ],
    "wof:name":"F & L Engineering",
    "wof:placetype":"venue"
},
  "geometry": {"coordinates":[-117.393041,34.11001],"type":"Point"}
}