{
  "type": "Feature",
  "properties": {
    "addr:full":"32033 Middle Ridge Rd Albion CA 95410",
    "addr:housenumber":"32033",
    "addr:postcode":"95410",
    "addr:street":"Middle Ridge Rd",
    "iso:country":"US",
    "sg:address":"32033 Middle Ridge Rd",
    "sg:city":"Albion",
    "sg:classifiers":[
        {
            "category":"Home & Garden",
            "subcategory":"Garden Supply",
            "type":"Retail Goods"
        }
    ],
    "sg:phone":"+1 707 937 0939",
    "sg:postcode":"95410",
    "sg:province":"CA",
    "wof:name":"Paintbox Plantsmen",
    "wof:placetype":"venue"
},
  "geometry": {"coordinates":[-123.73325199999999,39.209246],"type":"Point"}
}