{
  "type": "Feature",
  "properties": {
    "addr:full":"30198 Peterson Rd Mc Farland CA 93250",
    "addr:housenumber":"30198",
    "addr:postcode":"93250",
    "addr:street":"Peterson Rd",
    "iso:country":"US",
    "sg:address":"30198 Peterson Rd",
    "sg:city":"Mc Farland",
    "sg:phone":"+1 661 792 3468",
    "sg:postcode":"93250",
    "sg:province":"CA",
    "sg:tags":[
        "farm",
        "field",
        "crop",
        "cotton"
    ],
    "wof:name":"J R Regan Farms",
    "wof:placetype":"venue"
},
  "geometry": {"coordinates":[-119.27990200000001,35.70332],"type":"Point"}
}