{
  "type": "Feature",
  "properties": {
    "addr:full":"1173 el Camino Real Arroyo Grande CA 93420",
    "addr:housenumber":"1173",
    "addr:postcode":"93420",
    "addr:street":"El Camino Real",
    "iso:country":"US",
    "sg:address":"1173 el Camino Real",
    "sg:city":"Arroyo Grande",
    "sg:classifiers":[
        {
            "category":"Freight",
            "type":"Transportation"
        }
    ],
    "sg:phone":"+1 805 481 1300",
    "sg:postcode":"93420",
    "sg:province":"CA",
    "sg:tags":[
        "commercial",
        "self",
        "storage",
        "rental"
    ],
    "wof:name":"A & G Self Storage",
    "wof:placetype":"venue"
},
  "geometry": {"coordinates":[-120.594515,35.124259],"type":"Point"}
}