{
  "type": "Feature",
  "properties": {
    "iso:country":"US",
    "sg:address":"3302 Burton Ave",
    "sg:city":"Rosemead",
    "sg:classifiers":[
        {
            "category":"Professional",
            "type":"Services"
        }
    ],
    "sg:phone":"+1 626 572 0233",
    "sg:postcode":"91770",
    "sg:province":"CA",
    "wof:name":"Collectors",
    "wof:placetype":"venue"
},
  "geometry": {"coordinates":[-118.080355,34.064814],"type":"Point"}
}