{
  "type": "Feature",
  "properties": {
    "addr:full":"1050 Pioneer Way El Cajon CA 92020",
    "addr:housenumber":"1050",
    "addr:postcode":"92020",
    "addr:street":"Pioneer Way",
    "iso:country":"US",
    "sg:address":"1050 Pioneer Way",
    "sg:city":"El Cajon",
    "sg:classifiers":[
        {
            "category":"Retail",
            "subcategory":"Repair Shop",
            "type":"Services"
        }
    ],
    "sg:phone":"+1 619 401 0616",
    "sg:postcode":"92020",
    "sg:province":"CA",
    "wof:name":"Clean Space",
    "wof:placetype":"venue"
},
  "geometry": {"coordinates":[-116.96759299999999,32.807922],"type":"Point"}
}