{
  "type": "Feature",
  "properties": {
    "addr:full":"9627 Brighton Way Beverly Hills CA 90210",
    "addr:housenumber":"9627",
    "addr:postcode":"90210",
    "addr:street":"Brighton Way",
    "iso:country":"US",
    "sg:address":"9627 Brighton Way",
    "sg:city":"Beverly Hills",
    "sg:classifiers":[
        {
            "category":"Shopping",
            "subcategory":"Clothing, Apparel, & Fashions",
            "type":"Retail Goods"
        }
    ],
    "sg:phone":"+1 310 278 2980",
    "sg:postcode":"90210",
    "sg:province":"CA",
    "sg:tags":[
        "infant",
        "wear"
    ],
    "wof:name":"Rehoboth",
    "wof:placetype":"venue"
},
  "geometry": {"coordinates":[-118.40449700000001,34.068257],"type":"Point"}
}