{
  "type": "Feature",
  "properties": {
    "iso:country":"US",
    "sg:address":"2436 N Main St",
    "sg:city":"Salinas",
    "sg:classifiers":[
        {
            "category":"Professional",
            "subcategory":"Research",
            "type":"Services"
        }
    ],
    "sg:phone":"+1 831 444 8985",
    "sg:postcode":"93906",
    "sg:province":"CA",
    "sg:tags":[
        "environmental",
        "ecological"
    ],
    "wof:name":"Tech Source Environmental",
    "wof:placetype":"venue"
},
  "geometry": {"coordinates":[-121.656113,36.731483],"type":"Point"}
}