{
  "type": "Feature",
  "properties": {
    "addr:full":"710 W Main St Merced CA 95340",
    "addr:housenumber":"710",
    "addr:postcode":"95340",
    "addr:street":"W Main St",
    "iso:country":"US",
    "sg:address":"710 W Main St",
    "sg:city":"Merced",
    "sg:classifiers":[
        {
            "category":"Banks & Credit Unions",
            "subcategory":"Bank",
            "type":"Services"
        }
    ],
    "sg:phone":"+1 209 725 7040",
    "sg:postcode":"95340",
    "sg:province":"CA",
    "wof:name":"Bank Of America",
    "wof:placetype":"venue"
},
  "geometry": {"coordinates":[-120.48779999999999,37.302968],"type":"Point"}
}