{
  "type": "Feature",
  "properties": {
    "iso:country":"US",
    "sg:address":"700 W Orangewood Ave",
    "sg:city":"Anaheim",
    "sg:classifiers":[
        {
            "category":"Cinema",
            "subcategory":"Movie Rental",
            "type":"Entertainment"
        }
    ],
    "sg:phone":"+1 714 748 0255",
    "sg:postcode":"92802",
    "sg:province":"CA",
    "sg:tags":[
        "game",
        "video"
    ],
    "wof:name":"CIG Videos & Gifts",
    "wof:placetype":"venue"
},
  "geometry": {"coordinates":[-117.915572,33.795898],"type":"Point"}
}