{
  "type": "Feature",
  "properties": {
    "iso:country":"US",
    "sg:address":"8525 Lovers Ln",
    "sg:city":"Hollister",
    "sg:classifiers":[
        {
            "category":"Utilities",
            "subcategory":"Telephone",
            "type":"Services"
        }
    ],
    "sg:phone":"+1 831 634 1334",
    "sg:postcode":"95023",
    "sg:province":"CA",
    "sg:tags":[
        "telecommunication"
    ],
    "wof:name":"American Tower Corp",
    "wof:placetype":"venue"
},
  "geometry": {"coordinates":[-121.430036,36.957657],"type":"Point"}
}