{
  "type": "Feature",
  "properties": {
    "addr:full":"1231 W 9th St Upland CA 91786",
    "addr:housenumber":"1231",
    "addr:postcode":"91786",
    "addr:street":"W 9Th St",
    "iso:country":"US",
    "sg:address":"1231 W 9th St",
    "sg:city":"Upland",
    "sg:classifiers":[
        {
            "category":"Building & Trades",
            "subcategory":"Pest Control",
            "type":"Services"
        }
    ],
    "sg:phone":"+1 909 946 2824",
    "sg:postcode":"91786",
    "sg:province":"CA",
    "wof:name":"Northstar Exterminators",
    "wof:placetype":"venue"
},
  "geometry": {"coordinates":[-117.678647,34.096077],"type":"Point"}
}