{
  "type": "Feature",
  "properties": {
    "addr:full":"14718 Arminta St Van Nuys CA 91402",
    "addr:housenumber":"14718",
    "addr:postcode":"91402",
    "addr:street":"Arminta St",
    "iso:country":"US",
    "sg:address":"14718 Arminta St",
    "sg:city":"Van Nuys",
    "sg:classifiers":[
        {
            "category":"Manufacturing",
            "subcategory":"Tools & Machinery",
            "type":"Manufacturing & Wholesale Goods"
        }
    ],
    "sg:phone":"+1 818 786 8366",
    "sg:postcode":"91402",
    "sg:province":"CA",
    "sg:tags":[
        "machine",
        "shop"
    ],
    "wof:name":"Rothlisberger Manufacturing",
    "wof:placetype":"venue"
},
  "geometry": {"coordinates":[-118.450909,34.21333],"type":"Point"}
}