{
  "type": "Feature",
  "properties": {
    "addr:full":"1920 Main St Morro Bay CA 93442",
    "addr:housenumber":"1920",
    "addr:postcode":"93442",
    "addr:street":"Main St",
    "iso:country":"US",
    "sg:address":"1920 Main St",
    "sg:city":"Morro Bay",
    "sg:classifiers":[
        {
            "category":"Manufacturing",
            "subcategory":"Textiles",
            "type":"Manufacturing & Wholesale Goods"
        }
    ],
    "sg:phone":"+1 805 772 9665",
    "sg:postcode":"93442",
    "sg:province":"CA",
    "sg:tags":[
        "spinning",
        "mill",
        "yarn"
    ],
    "wof:name":"Morros Fleece Works",
    "wof:placetype":"venue"
},
  "geometry": {"coordinates":[-120.855548,35.381608],"type":"Point"}
}