{
  "type": "Feature",
  "properties": {
    "iso:country":"US",
    "sg:address":"21107 Victor St",
    "sg:city":"Torrance",
    "sg:classifiers":[
        {
            "category":"Freight",
            "type":"Transportation"
        }
    ],
    "sg:phone":"+1 310 542 9662",
    "sg:postcode":"90503",
    "sg:province":"CA",
    "sg:tags":[
        "operator",
        "local",
        "trucking"
    ],
    "wof:name":"Cash & Carry Delivery Service",
    "wof:placetype":"venue"
},
  "geometry": {"coordinates":[-118.366773,33.838771],"type":"Point"}
}