{
  "type": "Feature",
  "properties": {
    "iso:country":"US",
    "sg:address":"1390 Wallace Avenue",
    "sg:city":"San Francisco",
    "sg:classifiers":[
        {
            "category":"Building & Trades",
            "subcategory":"Construction",
            "type":"Services"
        }
    ],
    "sg:phone":"+1 415 822 8860",
    "sg:postcode":"94124",
    "sg:province":"CA",
    "sg:tags":[
        "contractor"
    ],
    "wof:name":"Grace Roofing",
    "wof:placetype":"venue"
},
  "geometry": {"coordinates":[-122.387001,37.7253],"type":"Point"}
}