{
  "type": "Feature",
  "properties": {
    "addr:full":"309 Magnolia Ave Ramona CA 92065",
    "addr:housenumber":"309",
    "addr:postcode":"92065",
    "addr:street":"Magnolia Ave",
    "iso:country":"US",
    "sg:address":"309 Magnolia Ave",
    "sg:city":"Ramona",
    "sg:classifiers":[
        {
            "category":"Building & Trades",
            "subcategory":"Construction",
            "type":"Services"
        }
    ],
    "sg:phone":"+1 760 789 2429",
    "sg:postcode":"92065",
    "sg:province":"CA",
    "sg:tags":[
        "contractor",
        "grading"
    ],
    "wof:name":"Shive Custom Grading",
    "wof:placetype":"venue"
},
  "geometry": {"coordinates":[-116.844911,33.054854],"type":"Point"}
}