{
  "type": "Feature",
  "properties": {
    "iso:country":"US",
    "sg:address":"12335 Icarus Ln",
    "sg:city":"Poway",
    "sg:classifiers":[
        {
            "category":"Retail",
            "subcategory":"Portrait Studio",
            "type":"Services"
        },
        {
            "category":"Professional",
            "subcategory":"Art Services",
            "type":"Services"
        }
    ],
    "sg:phone":"+1 858 486 1687",
    "sg:postcode":"92064",
    "sg:province":"CA",
    "sg:tags":[
        "photographer",
        "photography",
        "store"
    ],
    "wof:name":"Picture The Moment Photography",
    "wof:placetype":"venue"
},
  "geometry": {"coordinates":[-117.34033700000001,32.980252],"type":"Point"}
}