{
  "type": "Feature",
  "properties": {
    "addr:full":"3550 Wilshire Blvd Los Angeles CA 90010",
    "addr:housenumber":"3550",
    "addr:postcode":"90010",
    "addr:street":"Wilshire Blvd",
    "iso:country":"US",
    "sg:address":"3550 Wilshire Blvd",
    "sg:city":"Los Angeles",
    "sg:classifiers":[
        {
            "category":"Professional",
            "subcategory":"Lawyer & Legal Services",
            "type":"Services"
        }
    ],
    "sg:phone":"+1 323 655 9192",
    "sg:postcode":"90010",
    "sg:province":"CA",
    "wof:name":"Weaver John Atty At Law",
    "wof:placetype":"venue"
},
  "geometry": {"coordinates":[-118.30231499999999,34.061209],"type":"Point"}
}