{
  "type": "Feature",
  "properties": {
    "addr:full":"5924 West Blvd Los Angeles CA 90043",
    "addr:housenumber":"5924",
    "addr:postcode":"90043",
    "addr:street":"West Blvd",
    "iso:country":"US",
    "sg:address":"5924 West Blvd",
    "sg:city":"Los Angeles",
    "sg:classifiers":[
        {
            "category":"Professional",
            "subcategory":"Business Services",
            "type":"Services"
        }
    ],
    "sg:phone":"+1 323 295 0900",
    "sg:postcode":"90043",
    "sg:province":"CA",
    "sg:tags":[
        "recording",
        "rehearsal",
        "studio"
    ],
    "wof:name":"Scooter Jackson Records",
    "wof:placetype":"venue"
},
  "geometry": {"coordinates":[-118.334999,33.986599],"type":"Point"}
}