{
  "type": "Feature",
  "properties": {
    "iso:country":"US",
    "sg:address":"630 N San Mateo Dr",
    "sg:city":"San Mateo",
    "sg:classifiers":[
        {
            "category":"Professional",
            "subcategory":"Lawyer & Legal Services",
            "type":"Services"
        }
    ],
    "sg:phone":"+1 650 548 1028",
    "sg:postcode":"94401",
    "sg:province":"CA",
    "wof:name":"Tsu Jeffrey C Atty",
    "wof:placetype":"venue"
},
  "geometry": {"coordinates":[-122.334999,37.575001],"type":"Point"}
}