{
  "type": "Feature",
  "properties": {
    "iso:country":"US",
    "sg:address":"567 Hamilton Ave",
    "sg:city":"Menlo Park",
    "sg:classifiers":[
        {
            "category":"Organizations",
            "subcategory":"Religious Organization",
            "type":"Services"
        }
    ],
    "sg:phone":"+1 650 326 0577",
    "sg:postcode":"94025",
    "sg:province":"CA",
    "wof:name":"Church Of God",
    "wof:placetype":"venue"
},
  "geometry": {"coordinates":[-122.15797600000001,37.479167],"type":"Point"}
}