{
  "type": "Feature",
  "properties": {
    "iso:country":"US",
    "sg:address":"9702 International Blvd",
    "sg:city":"Oakland",
    "sg:classifiers":[
        {
            "category":"Health Services",
            "subcategory":"Nursing And Care Facility",
            "type":"Services"
        }
    ],
    "sg:phone":"+1 510 635 8422",
    "sg:postcode":"94603",
    "sg:province":"CA",
    "sg:tags":[
        "skilled"
    ],
    "sg:website":"www.walkerhouse.com",
    "wof:name":"Walker House",
    "wof:placetype":"venue"
},
  "geometry": {"coordinates":[-122.17043200000001,37.744522],"type":"Point"}
}