{
  "type": "Feature",
  "properties": {
    "iso:country":"US",
    "sg:address":"20875 Currier Rd",
    "sg:city":"Walnut",
    "sg:classifiers":[
        {
            "category":"Wholesale",
            "subcategory":"Groceries",
            "type":"Manufacturing & Wholesale Goods"
        }
    ],
    "sg:phone":"+1 909 869 0666",
    "sg:postcode":"91789",
    "sg:province":"CA",
    "sg:tags":[
        "food",
        "product",
        "health"
    ],
    "sg:website":"www.nu-health.com",
    "wof:name":"Nu-Health Product Co",
    "wof:placetype":"venue"
},
  "geometry": {"coordinates":[-117.846823,34.008359],"type":"Point"}
}