{
  "type": "Feature",
  "properties": {
    "iso:country":"US",
    "sg:address":"706 Charles Dr",
    "sg:city":"Oceanside",
    "sg:classifiers":[
        {
            "category":"Bars & Pubs",
            "type":"Food & Drink"
        },
        {
            "category":"Bars & Pubs",
            "subcategory":"Lounge",
            "type":"Food & Drink"
        }
    ],
    "sg:phone":"+1 760 966 1802",
    "sg:postcode":"92057",
    "sg:province":"CA",
    "sg:tags":[
        "cocktail"
    ],
    "wof:name":"Big Als Collectibles",
    "wof:placetype":"venue"
},
  "geometry": {"coordinates":[-117.296645,33.261441],"type":"Point"}
}