{
  "type": "Feature",
  "properties": {
    "addr:full":"871 Cotting Ct Vacaville CA 95688",
    "addr:housenumber":"871",
    "addr:postcode":"95688",
    "addr:street":"Cotting Ct",
    "iso:country":"US",
    "sg:address":"871 Cotting Ct",
    "sg:city":"Vacaville",
    "sg:classifiers":[
        {
            "category":"Manufacturing",
            "subcategory":"Tools & Machinery",
            "type":"Manufacturing & Wholesale Goods"
        },
        {
            "category":"Manufacturing",
            "subcategory":"Printing",
            "type":"Manufacturing & Wholesale Goods"
        }
    ],
    "sg:phone":"+1 707 469 7648",
    "sg:postcode":"95688",
    "sg:province":"CA",
    "sg:tags":[
        "commercial",
        "ink"
    ],
    "wof:name":"Sicpa",
    "wof:placetype":"venue"
},
  "geometry": {"coordinates":[-121.955626,38.397175],"type":"Point"}
}