{
  "type": "Feature",
  "properties": {
    "addr:full":"12700 Avalon Blvd Los Angeles CA 90061",
    "addr:housenumber":"12700",
    "addr:postcode":"90061",
    "addr:street":"Avalon Blvd",
    "iso:country":"US",
    "sg:address":"12700 Avalon Blvd",
    "sg:city":"Los Angeles",
    "sg:classifiers":[
        {
            "category":"Government",
            "subcategory":"Office",
            "type":"Public Place"
        }
    ],
    "sg:phone":"+1 323 418 7162",
    "sg:postcode":"90061",
    "sg:province":"CA",
    "sg:tags":[
        "employment"
    ],
    "wof:name":"Edd 1670",
    "wof:placetype":"venue"
},
  "geometry": {"coordinates":[-118.265248,33.916412],"type":"Point"}
}