{
  "type": "Feature",
  "properties": {
    "addr:full":"26176 Antonio Pkwy Rancho Santa Margarita CA 92688",
    "addr:housenumber":"26176",
    "addr:postcode":"92688",
    "addr:street":"Antonio Pkwy",
    "iso:country":"US",
    "sg:address":"26176 Antonio Pkwy",
    "sg:city":"Rancho Santa Margarita",
    "sg:classifiers":[
        {
            "category":"Organizations",
            "subcategory":"Religious Organization",
            "type":"Services"
        }
    ],
    "sg:phone":"+1 949 766 9610",
    "sg:postcode":"92688",
    "sg:province":"CA",
    "wof:name":"Corporation of President of Th",
    "wof:placetype":"venue"
},
  "geometry": {"coordinates":[-117.630645,33.582987],"type":"Point"}
}