{
  "type": "Feature",
  "properties": {
    "addr:full":"8754 Ashcroft Ave Los Angeles CA 90048",
    "addr:housenumber":"8754",
    "addr:postcode":"90048",
    "addr:street":"Ashcroft Ave",
    "iso:country":"US",
    "sg:address":"8754 Ashcroft Ave",
    "sg:city":"Los Angeles",
    "sg:classifiers":[
        {
            "category":"Manufacturing",
            "subcategory":"Apparel",
            "type":"Manufacturing & Wholesale Goods"
        }
    ],
    "sg:phone":"+1 310 358 9502",
    "sg:postcode":"90048",
    "sg:province":"CA",
    "sg:tags":[
        "designer",
        "pillow",
        "mfg"
    ],
    "wof:name":"Msl",
    "wof:placetype":"venue"
},
  "geometry": {"coordinates":[-118.382938,34.078917],"type":"Point"}
}