{
  "type": "Feature",
  "properties": {
    "iso:country":"US",
    "sg:address":"1700 S El Camino Real",
    "sg:city":"San Mateo",
    "sg:classifiers":[
        {
            "category":"Real Estate",
            "subcategory":"Real Estate Services",
            "type":"Services"
        }
    ],
    "sg:phone":"+1 650 574 7160",
    "sg:postcode":"94402",
    "sg:province":"CA",
    "sg:tags":[
        "management",
        "property"
    ],
    "wof:name":"Borel Estate Co",
    "wof:placetype":"venue"
},
  "geometry": {"coordinates":[-122.314003,37.5522],"type":"Point"}
}