{
  "type": "Feature",
  "properties": {
    "addr:full":"16520 Harbor Blvd Fountain Valley CA 92708",
    "addr:housenumber":"16520",
    "addr:postcode":"92708",
    "addr:street":"Harbor Blvd",
    "iso:country":"US",
    "sg:address":"16520 Harbor Blvd",
    "sg:city":"Fountain Valley",
    "sg:classifiers":[
        {
            "category":"Communications",
            "subcategory":"Film & Video Production",
            "type":"Services"
        }
    ],
    "sg:phone":"+1 714 839 5700",
    "sg:postcode":"92708",
    "sg:province":"CA",
    "sg:tags":[
        "taping"
    ],
    "wof:name":"411 Video Productions",
    "wof:placetype":"venue"
},
  "geometry": {"coordinates":[-117.919994,33.72116],"type":"Point"}
}