{
  "type": "Feature",
  "properties": {
    "iso:country":"US",
    "sg:address":"24721 Alicia Pkwy",
    "sg:city":"Laguna Hills",
    "sg:classifiers":[
        {
            "category":"Shopping",
            "subcategory":"Bicycles & Sporting Goods",
            "type":"Retail Goods"
        }
    ],
    "sg:phone":"+1 949 460 0854",
    "sg:postcode":"92653",
    "sg:province":"CA",
    "wof:name":"Soccer World",
    "wof:placetype":"venue"
},
  "geometry": {"coordinates":[-117.691002,33.6022],"type":"Point"}
}