{
  "type": "Feature",
  "properties": {
    "iso:country":"US",
    "sg:address":"7653 Melrose Ave",
    "sg:city":"Los Angeles",
    "sg:classifiers":[
        {
            "category":"Shopping",
            "subcategory":"Gifts & Souvenirs",
            "type":"Retail Goods"
        }
    ],
    "sg:phone":"+1 323 653 2561",
    "sg:postcode":"90046",
    "sg:province":"CA",
    "sg:tags":[
        "shop",
        "fashion"
    ],
    "wof:name":"Yonada Inc",
    "wof:placetype":"venue"
},
  "geometry": {"coordinates":[-118.35700199999999,34.083599],"type":"Point"}
}