{
  "type": "Feature",
  "properties": {
    "iso:country":"US",
    "sg:address":"4339 Rilea Way",
    "sg:city":"Oakland",
    "sg:classifiers":[
        {
            "category":"Home & Garden",
            "subcategory":"Household Appliances",
            "type":"Retail Goods"
        }
    ],
    "sg:phone":"+1 510 568 3705",
    "sg:postcode":"94605",
    "sg:province":"CA",
    "sg:tags":[
        "machine",
        "washing"
    ],
    "wof:name":"Skyline Service Appliance",
    "wof:placetype":"venue"
},
  "geometry": {"coordinates":[-122.150777,37.770812],"type":"Point"}
}