{
  "type": "Feature",
  "properties": {
    "iso:country":"US",
    "sg:address":"2324 S Atlantic Blvd # B",
    "sg:city":"Monterey Park",
    "sg:classifiers":[
        {
            "category":"Professional",
            "subcategory":"Lawyer & Legal Services",
            "type":"Services"
        }
    ],
    "sg:phone":"+1 323 724 0766",
    "sg:postcode":"91754",
    "sg:province":"CA",
    "wof:name":"Carmona Michael E Attorney At Law",
    "wof:placetype":"venue"
},
  "geometry": {"coordinates":[-118.146004,34.037399],"type":"Point"}
}