{
  "type": "Feature",
  "properties": {
    "addr:full":"2720 E Palmdale Blvd Palmdale CA 93550",
    "addr:housenumber":"2720",
    "addr:postcode":"ca 93550",
    "addr:street":"E Palmdale Blvd",
    "iso:country":"US",
    "sg:address":"2720 E Palmdale Blvd",
    "sg:city":"Palmdale",
    "sg:classifiers":[
        {
            "category":"Health Services",
            "subcategory":"Optometrist",
            "type":"Services"
        }
    ],
    "sg:phone":"+1 661 267 0026",
    "sg:postcode":"93550",
    "sg:province":"CA",
    "wof:name":"Antelope Valley Optometric Ctr",
    "wof:placetype":"venue"
},
  "geometry": {"coordinates":[-118.080277,34.580111],"type":"Point"}
}