{
  "type": "Feature",
  "properties": {
    "addr:full":"800 N Brand Blvd Glendale CA 91203",
    "addr:housenumber":"800",
    "addr:postcode":"91203",
    "addr:street":"N Brand Blvd",
    "iso:country":"US",
    "sg:address":"800 N Brand Blvd",
    "sg:city":"Glendale",
    "sg:classifiers":[
        {
            "category":"Real Estate",
            "subcategory":"Real Estate Agent",
            "type":"Services"
        }
    ],
    "sg:phone":"+1 818 549 1700",
    "sg:postcode":"91203",
    "sg:province":"CA",
    "wof:name":"P M Realty Group",
    "wof:placetype":"venue"
},
  "geometry": {"coordinates":[-118.255152,34.158462],"type":"Point"}
}