{
  "type": "Feature",
  "properties": {
    "addr:full":"10403 Lakewood Blvd Downey CA 90241",
    "addr:housenumber":"10403",
    "addr:postcode":"90241",
    "addr:street":"Lakewood Blvd",
    "iso:country":"US",
    "sg:address":"10403 Lakewood Blvd",
    "sg:city":"Downey",
    "sg:classifiers":[
        {
            "category":"Cinema",
            "subcategory":"Movie Rental",
            "type":"Entertainment"
        }
    ],
    "sg:phone":"+1 562 869 9933",
    "sg:postcode":"90241",
    "sg:province":"CA",
    "sg:tags":[
        "leasing",
        "video",
        "disc",
        "tape"
    ],
    "wof:name":"Champ Video & Wireless",
    "wof:placetype":"venue"
},
  "geometry": {"coordinates":[-118.118031,33.946136],"type":"Point"}
}