{
  "type": "Feature",
  "properties": {
    "addr:full":"650 N King Rd San Jose CA 95133",
    "addr:housenumber":"650",
    "addr:postcode":"95133",
    "addr:street":"N King Rd",
    "iso:country":"US",
    "sg:address":"650 N King Rd",
    "sg:city":"San Jose",
    "sg:classifiers":[
        {
            "category":"Education",
            "subcategory":"Special Training",
            "type":"Public Place"
        },
        {
            "category":"Education",
            "subcategory":"University",
            "type":"Public Place"
        }
    ],
    "sg:phone":"+1 408 258 0800",
    "sg:postcode":"95133",
    "sg:province":"CA",
    "sg:tags":[
        "school",
        "college",
        "specialty",
        "adult"
    ],
    "sg:website":"www.americanbci.com",
    "wof:name":"American Business College International",
    "wof:placetype":"venue"
},
  "geometry": {"coordinates":[-121.864998,37.3629],"type":"Point"}
}