{
  "type": "Feature",
  "properties": {
    "addr:full":"241 W Pacheco Blvd Los Banos CA 93635",
    "addr:housenumber":"241",
    "addr:postcode":"93635",
    "addr:street":"W Pacheco Blvd",
    "iso:country":"US",
    "sg:address":"241 W Pacheco Blvd",
    "sg:city":"Los Banos",
    "sg:classifiers":[
        {
            "category":"Real Estate",
            "subcategory":"Real Estate Agent",
            "type":"Services"
        }
    ],
    "sg:phone":"+1 209 827 6000",
    "sg:postcode":"93635",
    "sg:province":"CA",
    "wof:name":"Stone Creek Properties",
    "wof:placetype":"venue"
},
  "geometry": {"coordinates":[-120.856965,37.056804],"type":"Point"}
}