{
  "type": "Feature",
  "properties": {
    "addr:full":"1481 Foothill Blvd La Verne CA 91750",
    "addr:housenumber":"1481",
    "addr:postcode":"91750",
    "addr:street":"Foothill Blvd",
    "iso:country":"US",
    "sg:address":"1481 Foothill Blvd",
    "sg:city":"La Verne",
    "sg:classifiers":[
        {
            "category":"Personal",
            "subcategory":"Beauty Salon",
            "type":"Services"
        }
    ],
    "sg:phone":"+1 909 593 1981",
    "sg:postcode":"91750",
    "sg:province":"CA",
    "wof:name":"Laurie Cullins",
    "wof:placetype":"venue"
},
  "geometry": {"coordinates":[-117.77522,34.116746],"type":"Point"}
}