{
  "type": "Feature",
  "properties": {
    "addr:full":"10158 Mason Ave Chatsworth CA 91311",
    "addr:housenumber":"10158",
    "addr:postcode":"91311",
    "addr:street":"Mason Ave",
    "iso:country":"US",
    "sg:address":"10158 Mason Ave",
    "sg:city":"Chatsworth",
    "sg:classifiers":[
        {
            "category":"Shopping",
            "subcategory":"Clothing, Apparel, & Fashions",
            "type":"Retail Goods"
        }
    ],
    "sg:phone":"+1 818 576 0104",
    "sg:postcode":"91311",
    "sg:province":"CA",
    "sg:tags":[
        "designer"
    ],
    "wof:name":"Fashion Corner By Minoo",
    "wof:placetype":"venue"
},
  "geometry": {"coordinates":[-118.579745,34.256186],"type":"Point"}
}