{
  "type": "Feature",
  "properties": {
    "addr:full":"630 W Foothill Blvd Glendora CA 91741",
    "addr:housenumber":"630",
    "addr:postcode":"91741",
    "addr:street":"W Foothill Blvd",
    "iso:country":"US",
    "sg:address":"630 W Foothill Blvd",
    "sg:city":"Glendora",
    "sg:classifiers":[
        {
            "category":"Professional",
            "subcategory":"Management & Consulting",
            "type":"Services"
        },
        {
            "category":"Manufacturing",
            "subcategory":"Rubber & Plastics",
            "type":"Manufacturing & Wholesale Goods"
        }
    ],
    "sg:phone":"+1 626 914 9519",
    "sg:postcode":"91741",
    "sg:province":"CA",
    "sg:tags":[
        "consultant",
        "product",
        "mfg",
        "welding"
    ],
    "wof:name":"United Precision",
    "wof:placetype":"venue"
},
  "geometry": {"coordinates":[-117.87312900000001,34.135989],"type":"Point"}
}