{
  "type": "Feature",
  "properties": {
    "addr:full":"750 B St San Diego CA 92101",
    "addr:housenumber":"750",
    "addr:postcode":"92101",
    "addr:street":"B St",
    "iso:country":"US",
    "sg:address":"750 B St",
    "sg:city":"San Diego",
    "sg:classifiers":[
        {
            "category":"Professional",
            "subcategory":"Lawyer & Legal Services",
            "type":"Services"
        }
    ],
    "sg:phone":"+1 619 236 1255",
    "sg:postcode":"92101",
    "sg:province":"CA",
    "wof:name":"Grant John Atty",
    "wof:placetype":"venue"
},
  "geometry": {"coordinates":[-117.157901,32.718667],"type":"Point"}
}