{
  "type": "Feature",
  "properties": {
    "addr:full":"2580 San Ramon Valley Blvd San Ramon CA 94583",
    "addr:housenumber":"2580",
    "addr:postcode":"94583",
    "addr:street":"San Ramon Valley Blvd",
    "iso:country":"US",
    "sg:address":"2580 San Ramon Valley Blvd",
    "sg:city":"San Ramon",
    "sg:classifiers":[
        {
            "category":"Banks & Credit Unions",
            "subcategory":"Bank",
            "type":"Services"
        }
    ],
    "sg:phone":"+1 925 830 9800",
    "sg:postcode":"94583",
    "sg:province":"CA",
    "sg:tags":[
        "loan",
        "real estate"
    ],
    "wof:name":"Canyon View Lending",
    "wof:placetype":"venue"
},
  "geometry": {"coordinates":[-121.972301,37.769602],"type":"Point"}
}