{
  "type": "Feature",
  "properties": {
    "iso:country":"US",
    "sg:address":"775 Monterey Blvd",
    "sg:city":"San Francisco",
    "sg:classifiers":[
        {
            "category":"Real Estate",
            "subcategory":"Real Estate Agent",
            "type":"Services"
        }
    ],
    "sg:phone":"+1 415 334 0100",
    "sg:postcode":"94127",
    "sg:province":"CA",
    "sg:website":"www.brownandco-sf.com",
    "wof:name":"Brown & Company",
    "wof:placetype":"venue"
},
  "geometry": {"coordinates":[-122.452888,37.731403],"type":"Point"}
}