{
  "type": "Feature",
  "properties": {
    "addr:full":"2484 E Florence Ave Huntington Park CA 90255",
    "addr:housenumber":"2484",
    "addr:postcode":"90255",
    "addr:street":"E Florence Ave;Park",
    "iso:country":"US",
    "sg:address":"2484 E Florence Ave",
    "sg:city":"Huntington Park",
    "sg:classifiers":[
        {
            "category":"Bars & Pubs",
            "type":"Food & Drink"
        }
    ],
    "sg:phone":"+1 323 583 5551",
    "sg:postcode":"90255",
    "sg:province":"CA",
    "sg:tags":[
        "lounge",
        "cocktail"
    ],
    "wof:name":"Elva's Club",
    "wof:placetype":"venue"
},
  "geometry": {"coordinates":[-118.23003,33.97466],"type":"Point"}
}