{
  "type": "Feature",
  "properties": {
    "addr:full":"45353 Industrial Pl Fremont CA 94538",
    "addr:housenumber":"45353",
    "addr:postcode":"94538",
    "addr:street":"Industrial Pl",
    "iso:country":"US",
    "sg:address":"45353 Industrial Pl",
    "sg:city":"Fremont",
    "sg:classifiers":[
        {
            "category":"Retail",
            "subcategory":"Auto Repair",
            "type":"Services"
        }
    ],
    "sg:phone":"+1 510 490 8684",
    "sg:postcode":"94538",
    "sg:province":"CA",
    "sg:tags":[
        "body",
        "automobile",
        "painting"
    ],
    "wof:name":"Unique Autobody",
    "wof:placetype":"venue"
},
  "geometry": {"coordinates":[-121.95003800000001,37.495646],"type":"Point"}
}