{
  "type": "Feature",
  "properties": {
    "addr:full":"175 W Cluster St San Bernardino CA 92408",
    "addr:housenumber":"175",
    "addr:postcode":"92408",
    "addr:street":"W Cluster St",
    "iso:country":"US",
    "sg:address":"175 W Cluster St",
    "sg:city":"San Bernardino",
    "sg:classifiers":[
        {
            "category":"Government",
            "subcategory":"Office",
            "type":"Public Place"
        }
    ],
    "sg:phone":"+1 909 383 4692",
    "sg:postcode":"92408",
    "sg:province":"CA",
    "sg:tags":[
        "transportation"
    ],
    "wof:name":"Caltrans Metro Maintenance",
    "wof:placetype":"venue"
},
  "geometry": {"coordinates":[-117.286925,34.096961],"type":"Point"}
}