{
  "type": "Feature",
  "properties": {
    "iso:country":"US",
    "sg:address":"8929 S Sepulveda Blvd",
    "sg:city":"Los Angeles",
    "sg:classifiers":[
        {
            "category":"Freight",
            "type":"Transportation"
        },
        {
            "category":"Professional",
            "subcategory":"Business Services",
            "type":"Services"
        }
    ],
    "sg:phone":"+1 310 337 0377",
    "sg:postcode":"90045",
    "sg:province":"CA",
    "sg:tags":[
        "messenger",
        "courier"
    ],
    "sg:website":"www.apollocouriers.com",
    "wof:name":"Apollo Couriers Inc",
    "wof:placetype":"venue"
},
  "geometry": {"coordinates":[-118.396199,33.957141],"type":"Point"}
}