{
  "type": "Feature",
  "properties": {
    "addr:full":"321 Grey Ghost Ave San Jose CA 95111",
    "addr:housenumber":"321",
    "addr:postcode":"95111",
    "addr:street":"Grey Ghost Ave",
    "iso:country":"US",
    "sg:address":"321 Grey Ghost Ave",
    "sg:city":"San Jose",
    "sg:classifiers":[
        {
            "category":"Local Transit",
            "type":"Transportation"
        }
    ],
    "sg:phone":"+1 408 972 9126",
    "sg:postcode":"95111",
    "sg:province":"CA",
    "sg:tags":[
        "passenger"
    ],
    "sg:website":"www.southbaylimo.com",
    "wof:name":"South Bay Limo",
    "wof:placetype":"venue"
},
  "geometry": {"coordinates":[-121.80725,37.265922],"type":"Point"}
}