{
  "type": "Feature",
  "properties": {
    "iso:country":"US",
    "sg:address":"2970 Gordon Ave",
    "sg:city":"Santa Clara",
    "sg:classifiers":[
        {
            "category":"Manufacturing",
            "subcategory":"Tools & Machinery",
            "type":"Manufacturing & Wholesale Goods"
        }
    ],
    "sg:phone":"+1 408 245 9410",
    "sg:postcode":"95051",
    "sg:province":"CA",
    "sg:tags":[
        "machine",
        "shop"
    ],
    "wof:name":"Advantech Precision Machining",
    "wof:placetype":"venue"
},
  "geometry": {"coordinates":[-121.994808,37.37543],"type":"Point"}
}