{
  "type": "Feature",
  "properties": {
    "addr:full":"1145 State Rte 66 Glendora CA 91740",
    "addr:housenumber":"1145",
    "addr:postcode":"91740",
    "addr:street":"State Rte 66",
    "iso:country":"US",
    "sg:address":"1145 State Rte 66",
    "sg:city":"Glendora",
    "sg:classifiers":[
        {
            "category":"Retail",
            "subcategory":"Auto Repair",
            "type":"Services"
        }
    ],
    "sg:phone":"+1 626 914 3317",
    "sg:postcode":"91740",
    "sg:province":"CA",
    "sg:tags":[
        "transmission"
    ],
    "wof:name":"Glendora Tranmissions",
    "wof:placetype":"venue"
},
  "geometry": {"coordinates":[-117.843923,34.128735],"type":"Point"}
}