{
  "type": "Feature",
  "properties": {
    "iso:country":"US",
    "sg:address":"16835 Sierra Hwy",
    "sg:city":"Santa Clarita",
    "sg:classifiers":[
        {
            "category":"Building & Trades",
            "subcategory":"Plumbing",
            "type":"Services"
        }
    ],
    "sg:phone":"+1 661 252 7771",
    "sg:postcode":"91351",
    "sg:province":"CA",
    "wof:name":"MJ Hellmuth Plumbing Inc",
    "wof:placetype":"venue"
},
  "geometry": {"coordinates":[-118.42931799999999,34.44274],"type":"Point"}
}