{
  "type": "Feature",
  "properties": {
    "iso:country":"US",
    "sg:address":"6031 Shawnda Ct",
    "sg:city":"Citrus Heights",
    "sg:classifiers":[
        {
            "category":"Building & Trades",
            "subcategory":"Cleaning & Sanitation",
            "type":"Services"
        }
    ],
    "sg:phone":"+1 916 308 7768",
    "sg:postcode":"95621",
    "sg:province":"CA",
    "sg:tags":[
        "maintenance"
    ],
    "wof:name":"Lusac Building Svc",
    "wof:placetype":"venue"
},
  "geometry": {"coordinates":[-121.322473,38.696885],"type":"Point"}
}