{
  "type": "Feature",
  "properties": {
    "addr:full":"7716 Northridge Dr Citrus Heights CA 95610",
    "addr:housenumber":"7716",
    "addr:postcode":"95610",
    "addr:street":"Northridge Dr",
    "iso:country":"US",
    "sg:address":"7716 Northridge Dr",
    "sg:city":"Citrus Heights",
    "sg:classifiers":[
        {
            "category":"Building & Trades",
            "subcategory":"Electrical",
            "type":"Services"
        }
    ],
    "sg:phone":"+1 916 606 2581",
    "sg:postcode":"95610",
    "sg:province":"CA",
    "sg:tags":[
        "electrical",
        "contractor"
    ],
    "wof:name":"Carmichael Electric",
    "wof:placetype":"venue"
},
  "geometry": {"coordinates":[-121.281153,38.675151],"type":"Point"}
}