{
  "type": "Feature",
  "properties": {
    "iso:country":"US",
    "sg:address":"2568 Industrial Blvd",
    "sg:city":"West Sacramento",
    "sg:classifiers":[
        {
            "category":"Building & Trades",
            "subcategory":"Construction",
            "type":"Services"
        }
    ],
    "sg:phone":"+1 916 372 7422",
    "sg:postcode":"95691",
    "sg:province":"CA",
    "sg:tags":[
        "general",
        "contractor"
    ],
    "wof:name":"Northern California Constr",
    "wof:placetype":"venue"
},
  "geometry": {"coordinates":[-121.549102,38.568973],"type":"Point"}
}