{
  "type": "Feature",
  "properties": {
    "addr:full":"6101 Rosemead Blvd Pico Rivera CA 90660",
    "addr:housenumber":"6101",
    "addr:postcode":"90660",
    "addr:street":"Rosemead Blvd",
    "iso:country":"US",
    "sg:address":"6101 Rosemead Blvd",
    "sg:city":"Pico Rivera",
    "sg:classifiers":[
        {
            "category":"Food & Beverages",
            "subcategory":"Groceries & Convenience Stores",
            "type":"Retail Goods"
        }
    ],
    "sg:phone":"+1 562 942 7337",
    "sg:postcode":"90660",
    "sg:province":"CA",
    "sg:tags":[
        "market"
    ],
    "wof:name":"Super A Foods",
    "wof:placetype":"venue"
},
  "geometry": {"coordinates":[-118.091003,33.991001],"type":"Point"}
}