{
  "type": "Feature",
  "properties": {
    "addr:full":"900 Wilshire Boulevard Suite 1240 Los Angeles CA 90017",
    "addr:housenumber":"900",
    "addr:postcode":"90017",
    "addr:street":"Wilshire Boulevard Suite 1240",
    "iso:country":"US",
    "sg:address":"900 Wilshire Boulevard Suite 1240",
    "sg:city":"Los Angeles",
    "sg:classifiers":[
        {
            "category":"Professional",
            "subcategory":"Lawyer & Legal Services",
            "type":"Services"
        }
    ],
    "sg:phone":"+1 213 627 4401",
    "sg:postcode":"90017",
    "sg:province":"CA",
    "wof:name":"Wong Shu Attorney At Law",
    "wof:placetype":"venue"
},
  "geometry": {"coordinates":[-118.25925700000001,34.050028],"type":"Point"}
}