{
  "type": "Feature",
  "properties": {
    "addr:full":"12436 1st St Yucaipa CA 92399",
    "addr:housenumber":"12436",
    "addr:postcode":"92399",
    "addr:street":"1St St",
    "iso:country":"US",
    "sg:address":"12436 1st St",
    "sg:city":"Yucaipa",
    "sg:classifiers":[
        {
            "category":"Retail",
            "subcategory":"Car Wash",
            "type":"Services"
        }
    ],
    "sg:phone":"+1 909 708 9078",
    "sg:postcode":"92399",
    "sg:province":"CA",
    "sg:tags":[
        "automobile",
        "detail",
        "clean"
    ],
    "wof:name":"A Perfect Shine Mobile Detail",
    "wof:placetype":"venue"
},
  "geometry": {"coordinates":[-117.041082,34.02875],"type":"Point"}
}