{
  "type": "Feature",
  "properties": {
    "iso:country":"US",
    "sg:address":"1201 Laguna Street",
    "sg:city":"San Francisco",
    "sg:classifiers":[
        {
            "category":"Food & Beverages",
            "subcategory":"Groceries & Convenience Stores",
            "type":"Retail Goods"
        }
    ],
    "sg:phone":"+1 415 931 2810",
    "sg:postcode":"94115",
    "sg:province":"CA",
    "wof:name":"Convenient Deli & Grocery",
    "wof:placetype":"venue"
},
  "geometry": {"coordinates":[-122.42800099999999,37.7822],"type":"Point"}
}