{
  "type": "Feature",
  "properties": {
    "iso:country":"US",
    "sg:address":"34249 Monterey Ave #0667",
    "sg:city":"Rancho Mirage",
    "sg:classifiers":[
        {
            "category":"Home & Garden",
            "subcategory":"Building Materials",
            "type":"Retail Goods"
        }
    ],
    "sg:phone":"+1 760 324 0100",
    "sg:postcode":"92270",
    "sg:province":"CA",
    "sg:tags":[
        "supply"
    ],
    "wof:name":"Home Depot the",
    "wof:placetype":"venue"
},
  "geometry": {"coordinates":[-116.388276,33.792907],"type":"Point"}
}