{
  "type": "Feature",
  "properties": {
    "iso:country":"US",
    "sg:address":"7108 Katella Ave 371",
    "sg:city":"Stanton",
    "sg:classifiers":[
        {
            "category":"Communications",
            "subcategory":"Television Station",
            "type":"Services"
        }
    ],
    "sg:phone":"+1 714 900 3520",
    "sg:postcode":"90680",
    "sg:province":"CA",
    "sg:tags":[
        "network"
    ],
    "wof:name":"Mortech Network Services",
    "wof:placetype":"venue"
},
  "geometry": {"coordinates":[-118.008598,33.802818],"type":"Point"}
}