{
  "type": "Feature",
  "properties": {
    "addr:full":"1521 Santee St Los Angeles CA 90015",
    "addr:housenumber":"1521",
    "addr:postcode":"90015",
    "addr:street":"Santee St",
    "iso:country":"US",
    "sg:address":"1521 Santee St",
    "sg:city":"Los Angeles",
    "sg:classifiers":[
        {
            "category":"Shopping",
            "type":"Retail Goods"
        }
    ],
    "sg:phone":"+1 213 745 7627",
    "sg:postcode":"90015",
    "sg:province":"CA",
    "sg:tags":[
        "factory",
        "outlet"
    ],
    "wof:name":"Us Outlet",
    "wof:placetype":"venue"
},
  "geometry": {"coordinates":[-118.260431,34.032603],"type":"Point"}
}