{
  "type": "Feature",
  "properties": {
    "iso:country":"US",
    "sg:address":"2740 E Spring St",
    "sg:city":"Long Beach",
    "sg:classifiers":[
        {
            "category":"Building & Trades",
            "subcategory":"Electrical",
            "type":"Services"
        }
    ],
    "sg:phone":"+1 562 426 6698",
    "sg:postcode":"90806",
    "sg:province":"CA",
    "sg:tags":[
        "electrician"
    ],
    "wof:name":"Neubauer Electric",
    "wof:placetype":"venue"
},
  "geometry": {"coordinates":[-118.158997,33.811699],"type":"Point"}
}