{
  "type": "Feature",
  "properties": {
    "addr:full":"5151 F St Sacramento CA 95819",
    "addr:housenumber":"5151",
    "addr:postcode":"95819",
    "addr:street":"F St",
    "iso:country":"US",
    "sg:address":"5151 F St",
    "sg:city":"Sacramento",
    "sg:classifiers":[
        {
            "category":"Health Services",
            "subcategory":"Doctor",
            "type":"Services"
        }
    ],
    "sg:phone":"+1 916 733 6050",
    "sg:postcode":"95819",
    "sg:province":"CA",
    "sg:tags":[
        "physician",
        "surgeon"
    ],
    "wof:name":"Children's Specialists Medical",
    "wof:placetype":"venue"
},
  "geometry": {"coordinates":[-121.440173,38.570727],"type":"Point"}
}