{
  "type": "Feature",
  "properties": {
    "iso:country":"US",
    "sg:address":"3960 Normal St",
    "sg:city":"San Diego",
    "sg:classifiers":[
        {
            "category":"Government",
            "subcategory":"Office",
            "type":"Public Place"
        }
    ],
    "sg:phone":"+1 619 688 3324",
    "sg:postcode":"92103",
    "sg:province":"CA",
    "sg:tags":[
        "transportation"
    ],
    "wof:name":"Department of Motor Vehicles",
    "wof:placetype":"venue"
},
  "geometry": {"coordinates":[-117.148979,32.750235],"type":"Point"}
}