{
  "type": "Feature",
  "properties": {
    "addr:full":"185 Pelton Center Way San Leandro CA 94577",
    "addr:housenumber":"185",
    "addr:postcode":"94577",
    "addr:street":"Pelton Center Way",
    "iso:country":"US",
    "sg:address":"185 Pelton Center Way",
    "sg:city":"San Leandro",
    "sg:classifiers":[
        {
            "category":"Restaurant",
            "type":"Food & Drink"
        }
    ],
    "sg:phone":"+1 510 614 5576",
    "sg:postcode":"94577",
    "sg:province":"CA",
    "wof:name":"Perry's Food For The Soul",
    "wof:placetype":"venue"
},
  "geometry": {"coordinates":[-122.15457499999999,37.722682],"type":"Point"}
}