{
  "type": "Feature",
  "properties": {
    "iso:country":"US",
    "sg:address":"7968 Arjons Dr",
    "sg:city":"San Diego",
    "sg:classifiers":[
        {
            "category":"Shopping",
            "subcategory":"Computers & Home Electronics",
            "type":"Retail Goods"
        }
    ],
    "sg:phone":"+1 858 549 9072",
    "sg:postcode":"92126",
    "sg:province":"CA",
    "wof:name":"Raduga USA Corp",
    "wof:placetype":"venue"
},
  "geometry": {"coordinates":[-117.150852,32.893997],"type":"Point"}
}