{
  "type": "Feature",
  "properties": {
    "addr:full":"330 Kansas St El Segundo CA 90245",
    "addr:housenumber":"330",
    "addr:postcode":"90245",
    "addr:street":"Kansas St",
    "iso:country":"US",
    "sg:address":"330 Kansas St",
    "sg:city":"El Segundo",
    "sg:classifiers":[
        {
            "category":"Manufacturing",
            "subcategory":"Retail Goods",
            "type":"Manufacturing & Wholesale Goods"
        }
    ],
    "sg:phone":"+1 310 726 8784",
    "sg:postcode":"90245",
    "sg:province":"CA",
    "sg:tags":[
        "product",
        "mfg"
    ],
    "wof:name":"International Rectifier",
    "wof:placetype":"venue"
},
  "geometry": {"coordinates":[-118.400477,33.920124],"type":"Point"}
}