{
  "type": "Feature",
  "properties": {
    "addr:full":"1159 Duarte Rd Duarte CA 91010",
    "addr:housenumber":"1159",
    "addr:postcode":"91010",
    "addr:street":"Duarte Rd",
    "iso:country":"US",
    "sg:address":"1159 Duarte Rd",
    "sg:city":"Duarte",
    "sg:classifiers":[
        {
            "category":"Wholesale",
            "subcategory":"Electrical",
            "type":"Manufacturing & Wholesale Goods"
        }
    ],
    "sg:phone":"+1 877 305 1443",
    "sg:postcode":"91010",
    "sg:province":"CA",
    "sg:tags":[
        "hook",
        "distribute",
        "electric",
        "wire"
    ],
    "wof:name":"Flexwire Inc",
    "wof:placetype":"venue"
},
  "geometry": {"coordinates":[-117.979876,34.132251],"type":"Point"}
}