{
  "type": "Feature",
  "properties": {
    "iso:country":"US",
    "sg:address":"1114 N St Andrews Pl",
    "sg:city":"Los Angeles",
    "sg:classifiers":[
        {
            "category":"Food & Beverages",
            "subcategory":"Groceries & Convenience Stores",
            "type":"Retail Goods"
        }
    ],
    "sg:phone":"+1 323 463 3795",
    "sg:postcode":"90038",
    "sg:province":"CA",
    "sg:tags":[
        "market"
    ],
    "sg:website":"www.tomsmarket.com",
    "wof:name":"Tom's Market",
    "wof:placetype":"venue"
},
  "geometry": {"coordinates":[-118.310823,34.091243],"type":"Point"}
}