{
  "type": "Feature",
  "properties": {
    "iso:country":"US",
    "sg:address":"11224 Santa Fe Dr",
    "sg:city":"Ballico",
    "sg:classifiers":[
        {
            "category":"Government",
            "subcategory":"Post Office",
            "type":"Public Place"
        }
    ],
    "sg:phone":"+1 209 632 0694",
    "sg:postcode":"95303",
    "sg:province":"CA",
    "sg:tags":[
        "postal",
        "us"
    ],
    "wof:name":"US Post Office",
    "wof:placetype":"venue"
},
  "geometry": {"coordinates":[-120.70168200000001,37.451386],"type":"Point"}
}