{
  "type": "Feature",
  "properties": {
    "iso:country":"US",
    "sg:address":"1811 Douglas Blvd",
    "sg:city":"Roseville",
    "sg:classifiers":[
        {
            "category":"Shopping",
            "subcategory":"Gifts & Souvenirs",
            "type":"Retail Goods"
        }
    ],
    "sg:phone":"+1 916 780 1816",
    "sg:postcode":"95661",
    "sg:province":"CA",
    "sg:tags":[
        "shop"
    ],
    "wof:name":"Charmed Expressions",
    "wof:placetype":"venue"
},
  "geometry": {"coordinates":[-121.25714600000001,38.744301],"type":"Point"}
}