{
  "type": "Feature",
  "properties": {
    "iso:country":"US",
    "sg:address":"7877 Sauterne Dr",
    "sg:city":"Rancho Cucamonga",
    "sg:classifiers":[
        {
            "category":"Professional",
            "subcategory":"Management & Consulting",
            "type":"Services"
        }
    ],
    "sg:phone":"+1 909 948 9483",
    "sg:postcode":"91730",
    "sg:province":"CA",
    "sg:tags":[
        "consultant",
        "business"
    ],
    "wof:name":"M & J Assoc",
    "wof:placetype":"venue"
},
  "geometry": {"coordinates":[-117.607028,34.110158],"type":"Point"}
}