{
  "type": "Feature",
  "properties": {
    "iso:country":"US",
    "sg:address":"4830 St Elmo Dr",
    "sg:city":"Los Angeles",
    "sg:classifiers":[
        {
            "category":"Education",
            "subcategory":"Special Training",
            "type":"Public Place"
        }
    ],
    "sg:phone":"+1 323 931 3409",
    "sg:postcode":"90019",
    "sg:province":"CA",
    "sg:tags":[
        "school",
        "art"
    ],
    "wof:name":"St Elmo Village",
    "wof:placetype":"venue"
},
  "geometry": {"coordinates":[-118.343002,34.043499],"type":"Point"}
}