{
  "type": "Feature",
  "properties": {
    "addr:full":"7427 Redwood Blvd Novato CA 94945",
    "addr:housenumber":"7427",
    "addr:postcode":"94945",
    "addr:street":"Redwood Blvd",
    "iso:country":"US",
    "sg:address":"7427 Redwood Blvd",
    "sg:city":"Novato",
    "sg:classifiers":[
        {
            "category":"Shopping",
            "subcategory":"Used Merchandise",
            "type":"Retail Goods"
        }
    ],
    "sg:phone":"+1 415 892 4436",
    "sg:postcode":"94945",
    "sg:province":"CA",
    "sg:tags":[
        "antique"
    ],
    "wof:name":"Now & Then Antiques",
    "wof:placetype":"venue"
},
  "geometry": {"coordinates":[-122.569363,38.110006],"type":"Point"}
}