{
  "type": "Feature",
  "properties": {
    "addr:full":"2406 Magowan Dr Santa Rosa CA 95405",
    "addr:housenumber":"2406",
    "addr:postcode":"95405",
    "addr:street":"Magowan Dr",
    "iso:country":"US",
    "sg:address":"2406 Magowan Dr",
    "sg:city":"Santa Rosa",
    "sg:classifiers":[
        {
            "category":"Personal",
            "subcategory":"Beauty Salon",
            "type":"Services"
        }
    ],
    "sg:phone":"+1 707 528 3342",
    "sg:postcode":"95405",
    "sg:province":"CA",
    "wof:name":"Marsha Doughnut",
    "wof:placetype":"venue"
},
  "geometry": {"coordinates":[-122.68676499999999,38.445364],"type":"Point"}
}