{
  "type": "Feature",
  "properties": {
    "addr:full":"2021 N Pass Ave Burbank CA 91505",
    "addr:housenumber":"2021",
    "addr:postcode":"91505",
    "addr:street":"N Pass Ave",
    "iso:country":"US",
    "sg:address":"2021 N Pass Ave",
    "sg:city":"Burbank",
    "sg:classifiers":[
        {
            "category":"Building & Trades",
            "subcategory":"Pest Control",
            "type":"Services"
        }
    ],
    "sg:phone":"+1 818 569 5199",
    "sg:postcode":"91505",
    "sg:province":"CA",
    "sg:website":"www.avertpestcontrol.com",
    "wof:name":"Avert Environmental Pest Control",
    "wof:placetype":"venue"
},
  "geometry": {"coordinates":[-118.35480099999999,34.185651],"type":"Point"}
}