{
  "type": "Feature",
  "properties": {
    "addr:full":"27811 Perales Mission Viejo CA 92692",
    "addr:postcode":"27811;92692",
    "iso:country":"US",
    "sg:address":"27811 Perales",
    "sg:city":"Mission Viejo",
    "sg:classifiers":[
        {
            "category":"Building & Trades",
            "subcategory":"Landscaping Services",
            "type":"Services"
        }
    ],
    "sg:phone":"+1 949 455 0401",
    "sg:postcode":"92692",
    "sg:province":"CA",
    "wof:name":"Ornamental Iron Landscaping",
    "wof:placetype":"venue"
},
  "geometry": {"coordinates":[-117.644108,33.60753],"type":"Point"}
}