{
  "type": "Feature",
  "properties": {
    "addr:full":"1073 Miller Dr Lafayette CA 94549",
    "addr:housenumber":"1073",
    "addr:postcode":"94549",
    "addr:street":"Miller Dr",
    "iso:country":"US",
    "sg:address":"1073 Miller Dr",
    "sg:city":"Lafayette",
    "sg:classifiers":[
        {
            "category":"Shopping",
            "subcategory":"Pets & Pet Supplies",
            "type":"Retail Goods"
        },
        {
            "category":"Retail",
            "subcategory":"Veterinary Services",
            "type":"Services"
        }
    ],
    "sg:phone":"+1 925 283 5673",
    "sg:postcode":"94549",
    "sg:province":"CA",
    "sg:tags":[
        "specialty"
    ],
    "wof:name":"Parrotnanny Co",
    "wof:placetype":"venue"
},
  "geometry": {"coordinates":[-122.11135299999999,37.896985],"type":"Point"}
}