{
  "type": "Feature",
  "properties": {
    "addr:full":"10th Ave # 1333 San Francisco CA 94199",
    "addr:postcode":"94199",
    "addr:street":"10Th Ave # 1333",
    "iso:country":"US",
    "sg:address":"10th Ave # 1333",
    "sg:city":"San Francisco",
    "sg:classifiers":[
        {
            "category":"Coffee & Tea",
            "type":"Food & Drink"
        },
        {
            "category":"Donuts",
            "subcategory":"None",
            "type":"Food & Drink"
        }
    ],
    "sg:phone":"+1 808 739 2802",
    "sg:postcode":"94199",
    "sg:province":"CA",
    "wof:name":"CrazyCor",
    "wof:placetype":"venue"
},
  "geometry": {"coordinates":[-118.20316099999999,33.783151],"type":"Point"}
}