{
  "type": "Feature",
  "properties": {
    "addr:full":"5557 E Santa Ana Canyon Suite 202 Anaheim CA 92807",
    "addr:housenumber":"5557",
    "addr:postcode":"92807",
    "addr:street":"E Santa Ana Canyon Suite 202",
    "iso:country":"US",
    "sg:address":"5557 E Santa Ana Canyon Suite 202",
    "sg:city":"Anaheim",
    "sg:classifiers":[
        {
            "category":"Travel",
            "subcategory":"Travel Agent",
            "type":"Entertainment"
        }
    ],
    "sg:phone":"+1 714 974 0262",
    "sg:postcode":"92807",
    "sg:province":"CA",
    "wof:name":"Canyon Travel",
    "wof:placetype":"venue"
},
  "geometry": {"coordinates":[-117.79196399999999,33.851835],"type":"Point"}
}