{
  "type": "Feature",
  "properties": {
    "addr:full":"9426 Belford Ave Los Angeles CA 90045",
    "addr:housenumber":"9426",
    "addr:postcode":"90045",
    "addr:street":"Belford Ave",
    "iso:country":"US",
    "sg:address":"9426 Belford Ave",
    "sg:city":"Los Angeles",
    "sg:classifiers":[
        {
            "category":"Taxi",
            "type":"Transportation"
        }
    ],
    "sg:phone":"+1 310 216 2737",
    "sg:postcode":"90045",
    "sg:province":"CA",
    "sg:tags":[
        "taxicab"
    ],
    "wof:name":"Airport VIP Shuttle",
    "wof:placetype":"venue"
},
  "geometry": {"coordinates":[-118.383925,33.951211],"type":"Point"}
}