{
  "type": "Feature",
  "properties": {
    "iso:country":"US",
    "sg:address":"31786 Yucaipa Blvd",
    "sg:city":"Yucaipa",
    "sg:classifiers":[
        {
            "category":"Insurance",
            "subcategory":"Insurance Agent",
            "type":"Services"
        }
    ],
    "sg:phone":"+1 909 748 0074",
    "sg:postcode":"92399",
    "sg:province":"CA",
    "wof:name":"SCP Insurance Svc",
    "wof:placetype":"venue"
},
  "geometry": {"coordinates":[-117.109056,34.030748],"type":"Point"}
}