{
  "type": "Feature",
  "properties": {
    "iso:country":"US",
    "sg:address":"68420 Ramon Rd Ste 6",
    "sg:city":"Cathedral City",
    "sg:classifiers":[
        {
            "category":"Restaurant",
            "type":"Food & Drink"
        }
    ],
    "sg:phone":"+1 760 202 3920",
    "sg:postcode":"92234",
    "sg:province":"CA",
    "wof:name":"Azusena's Raspados Y Ice Cream",
    "wof:placetype":"venue"
},
  "geometry": {"coordinates":[-116.468002,33.816002],"type":"Point"}
}