{
  "type": "Feature",
  "properties": {
    "iso:country":"US",
    "sg:address":"2667 E 28th St Ste 508",
    "sg:city":"Long Beach",
    "sg:classifiers":[
        {
            "category":"Shopping",
            "subcategory":"Bicycles & Sporting Goods",
            "type":"Retail Goods"
        }
    ],
    "sg:phone":"+1 562 427 7400",
    "sg:postcode":"90755",
    "sg:province":"CA",
    "wof:name":"Executive Sports",
    "wof:placetype":"venue"
},
  "geometry": {"coordinates":[-118.160371,33.808058],"type":"Point"}
}