{
  "type": "Feature",
  "properties": {
    "addr:full":"2077 Gateway Place, Ste 300 San Jose CA 95110 ",
    "addr:housenumber":"2077",
    "addr:postcode":"95110",
    "addr:street":"Gateway Place Ste 300",
    "iso:country":"US",
    "sg:address":"2077 Gateway Place, Ste 300",
    "sg:city":"San Jose",
    "sg:classifiers":[
        {
            "category":"Professional",
            "subcategory":"Computer Services",
            "type":"Services"
        }
    ],
    "sg:phone":"+1 408 453 3333",
    "sg:postcode":"95110 ",
    "sg:province":"CA",
    "sg:website":"http://www.atrenta.com",
    "wof:name":"Atrenta",
    "wof:placetype":"venue"
},
  "geometry": {"coordinates":[-121.924308,37.371541],"type":"Point"}
}