{
  "type": "Feature",
  "properties": {
    "iso:country":"US",
    "sg:address":"2917 Del Paso Blvd",
    "sg:city":"Sacramento",
    "sg:classifiers":[
        {
            "category":"Real Estate",
            "subcategory":"Real Estate Services",
            "type":"Services"
        }
    ],
    "sg:phone":"+1 510 891 2365",
    "sg:postcode":"95815",
    "sg:province":"CA",
    "sg:tags":[
        "management",
        "property"
    ],
    "wof:name":"Goland Services Maintenance & Bookkeeping Properts",
    "wof:placetype":"venue"
},
  "geometry": {"coordinates":[-121.43699599999999,38.619202],"type":"Point"}
}