{
  "type": "Feature",
  "properties": {
    "addr:full":"1199 Grand Ave Arroyo Grande CA 93420",
    "addr:housenumber":"1199",
    "addr:postcode":"93420",
    "addr:street":"Grand Ave",
    "iso:country":"US",
    "sg:address":"1199 Grand Ave",
    "sg:city":"Arroyo Grande",
    "sg:classifiers":[
        {
            "category":"Banks & Credit Unions",
            "subcategory":"Bank",
            "type":"Services"
        }
    ],
    "sg:phone":"+1 805 473 6560",
    "sg:postcode":"93420",
    "sg:province":"CA",
    "wof:name":"Coast National Bank",
    "wof:placetype":"venue"
},
  "geometry": {"coordinates":[-120.59945500000001,35.120419],"type":"Point"}
}