{
  "type": "Feature",
  "properties": {
    "iso:country":"US",
    "sg:address":"965 Mission St",
    "sg:city":"San Francisco",
    "sg:classifiers":[
        {
            "category":"Education",
            "subcategory":"Special Training",
            "type":"Public Place"
        }
    ],
    "sg:phone":"+1 415 371 0198",
    "sg:postcode":"94103",
    "sg:province":"CA",
    "sg:tags":[
        "instruction",
        "music"
    ],
    "wof:name":"John D Scott Vocal Studio",
    "wof:placetype":"venue"
},
  "geometry": {"coordinates":[-122.408117,37.781456],"type":"Point"}
}