{
  "type": "Feature",
  "properties": {
    "addr:full":"4980 Allison Pkwy Vacaville CA 95688",
    "addr:housenumber":"4980",
    "addr:postcode":"95688",
    "addr:street":"Allison Pkwy",
    "iso:country":"US",
    "sg:address":"4980 Allison Pkwy",
    "sg:city":"Vacaville",
    "sg:classifiers":[
        {
            "category":"Autos & Motor Vehicles",
            "subcategory":"Auto Supplies",
            "type":"Retail Goods"
        },
        {
            "category":"Retail",
            "subcategory":"Auto Repair",
            "type":"Services"
        }
    ],
    "sg:phone":"+1 707 446 4444",
    "sg:postcode":"95688",
    "sg:province":"CA",
    "sg:tags":[
        "wheel",
        "recap",
        "retread",
        "tire"
    ],
    "sg:website":"http://www.bigotires.com",
    "wof:name":"Big O Tires",
    "wof:placetype":"venue"
},
  "geometry": {"coordinates":[-121.965828,38.392449],"type":"Point"}
}