{
  "type": "Feature",
  "properties": {
    "addr:full":"158 s. western ave. #101 Hancock Park CA 90004",
    "addr:housenumber":"158",
    "addr:postcode":"90004",
    "addr:street":"S. Western Ave. # 101",
    "iso:country":"US",
    "sg:address":"158 s. western ave. #101",
    "sg:city":"Hancock Park",
    "sg:classifiers":[
        {
            "category":"Professional",
            "type":"Services"
        }
    ],
    "sg:phone":"+1 213 389 0007",
    "sg:postcode":"90004",
    "sg:province":"CA",
    "wof:name":"DigitalProLAB",
    "wof:placetype":"venue"
},
  "geometry": {"coordinates":[-118.30876000000001,34.072004],"type":"Point"}
}