{
  "type": "Feature",
  "properties": {
    "addr:full":"888 S Figueroa Street Los Angeles CA 90017",
    "addr:housenumber":"888",
    "addr:postcode":"90017",
    "addr:street":"S Figueroa Street",
    "iso:country":"US",
    "sg:address":"888 S Figueroa Street",
    "sg:city":"Los Angeles",
    "sg:classifiers":[
        {
            "category":"Professional",
            "subcategory":"Lawyer & Legal Services",
            "type":"Services"
        }
    ],
    "sg:phone":"+1 213 488 0503",
    "sg:postcode":"90017",
    "sg:province":"CA",
    "wof:name":"Pitzhush Nancy Atty",
    "wof:placetype":"venue"
},
  "geometry": {"coordinates":[-118.262739,34.046263],"type":"Point"}
}