{
  "type": "Feature",
  "properties": {
    "iso:country":"US",
    "sg:address":"599 S Barranca Ave",
    "sg:city":"Covina",
    "sg:classifiers":[
        {
            "category":"Education",
            "subcategory":"Special Training",
            "type":"Public Place"
        },
        {
            "category":"Education",
            "subcategory":"Library",
            "type":"Public Place"
        }
    ],
    "sg:phone":"+1 626 332 4041",
    "sg:postcode":"91723",
    "sg:province":"CA",
    "sg:tags":[
        "instruction",
        "tutoring",
        "reading"
    ],
    "sg:website":"http://www.JonesTutoring.com",
    "wof:name":"Jones Reading & Math Clinics",
    "wof:placetype":"venue"
},
  "geometry": {"coordinates":[-117.88131,34.078979],"type":"Point"}
}