{
  "type": "Feature",
  "properties": {
    "addr:full":"1480 W Artesia Blvd Gardena CA 90248",
    "addr:housenumber":"1480",
    "addr:postcode":"90248",
    "addr:street":"W Artesia Blvd",
    "iso:country":"US",
    "sg:address":"1480 W Artesia Blvd",
    "sg:city":"Gardena",
    "sg:classifiers":[
        {
            "category":"Professional",
            "subcategory":"Research",
            "type":"Services"
        }
    ],
    "sg:phone":"+1 310 532 9653",
    "sg:postcode":"90248",
    "sg:province":"CA",
    "sg:website":"www.farwest.com",
    "wof:name":"Pacific Corrosion Research",
    "wof:placetype":"venue"
},
  "geometry": {"coordinates":[-118.301104,33.872749],"type":"Point"}
}