{
  "type": "Feature",
  "properties": {
    "addr:full":"1192 S 6th Street San Jose CA 95112",
    "addr:housenumber":"1192",
    "addr:postcode":"95112",
    "addr:street":"S 6Th Street",
    "iso:country":"US",
    "sg:address":"1192 S 6th Street",
    "sg:city":"San Jose",
    "sg:classifiers":[
        {
            "category":"Retail",
            "subcategory":"Auto Repair",
            "type":"Services"
        }
    ],
    "sg:phone":"+1 408 213 2906",
    "sg:postcode":"95112",
    "sg:province":"CA",
    "wof:name":"Vung Tau Complete Auto Repair",
    "wof:placetype":"venue"
},
  "geometry": {"coordinates":[-121.872255,37.321105],"type":"Point"}
}