{
  "type": "Feature",
  "properties": {
    "iso:country":"US",
    "sg:address":"2150 Village Park Way",
    "sg:city":"Encinitas",
    "sg:classifiers":[
        {
            "category":"Education",
            "subcategory":"School",
            "type":"Public Place"
        }
    ],
    "sg:phone":"+1 760 944 1892",
    "sg:postcode":"92024",
    "sg:province":"CA",
    "sg:tags":[
        "high",
        "middle",
        "elementary"
    ],
    "wof:name":"Diegueno Middle School",
    "wof:placetype":"venue"
},
  "geometry": {"coordinates":[-117.24299600000001,33.0564],"type":"Point"}
}