{
  "type": "Feature",
  "properties": {
    "iso:country":"US",
    "sg:address":"7800 Compton Ave",
    "sg:city":"Los Angeles",
    "sg:classifiers":[
        {
            "category":"Home & Garden",
            "subcategory":"Furniture",
            "type":"Retail Goods"
        }
    ],
    "sg:phone":"+1 323 582 5351",
    "sg:postcode":"90001",
    "sg:province":"CA",
    "sg:tags":[
        "chair"
    ],
    "wof:name":"Martin Avalos Chair Design",
    "wof:placetype":"venue"
},
  "geometry": {"coordinates":[-118.24765499999999,33.96799],"type":"Point"}
}