{
  "type": "Feature",
  "properties": {
    "iso:country":"US",
    "sg:address":"667 Arroyo St",
    "sg:city":"San Fernando",
    "sg:classifiers":[
        {
            "category":"Building & Trades",
            "subcategory":"Construction",
            "type":"Services"
        }
    ],
    "sg:phone":"+1 818 361 9500",
    "sg:postcode":"91342",
    "sg:province":"CA",
    "sg:tags":[
        "consultant",
        "demolition"
    ],
    "wof:name":"Padilla's Co",
    "wof:placetype":"venue"
},
  "geometry": {"coordinates":[-118.42595799999999,34.284389],"type":"Point"}
}