{
  "type": "Feature",
  "properties": {
    "addr:full":"421 Curran Ave Sacramento CA 95833",
    "addr:housenumber":"421",
    "addr:postcode":"95833",
    "addr:street":"Curran Ave",
    "iso:country":"US",
    "sg:address":"421 Curran Ave",
    "sg:city":"Sacramento",
    "sg:classifiers":[
        {
            "category":"Building & Trades",
            "subcategory":"Landscaping Services",
            "type":"Services"
        }
    ],
    "sg:phone":"+1 916 649 9046",
    "sg:postcode":"95833",
    "sg:province":"CA",
    "wof:name":"Crown Yard & Garden",
    "wof:placetype":"venue"
},
  "geometry": {"coordinates":[-121.47375599999999,38.621196],"type":"Point"}
}