{
  "type": "Feature",
  "properties": {
    "addr:full":"2100 Ward St Berkeley CA 94705",
    "addr:housenumber":"2100",
    "addr:postcode":"94705",
    "addr:street":"Ward St",
    "iso:country":"US",
    "sg:address":"2100 Ward St",
    "sg:city":"Berkeley",
    "sg:classifiers":[
        {
            "category":"Restaurant",
            "type":"Food & Drink"
        }
    ],
    "sg:phone":"+1 510 549 3486",
    "sg:postcode":"94705",
    "sg:province":"CA",
    "sg:tags":[
        "sushi",
        "bar"
    ],
    "sg:website":"www.kiralaberkeley.com",
    "wof:name":"Kirala Japanese Restaurant",
    "wof:placetype":"venue"
},
  "geometry": {"coordinates":[-122.266661,37.859338],"type":"Point"}
}