{
  "type": "Feature",
  "properties": {
    "addr:full":"1425 Venice Blvd Apt 7 Venice CA 90291",
    "addr:housenumber":"1425;7",
    "addr:postcode":"90291",
    "addr:street":"Venice Blvd Apt",
    "iso:country":"US",
    "sg:address":"1425 Venice Blvd Apt 7",
    "sg:city":"Venice",
    "sg:classifiers":[
        {
            "category":"Government",
            "subcategory":"City Hall",
            "type":"Public Place"
        }
    ],
    "sg:phone":"+1 310 463 7755",
    "sg:postcode":"90291",
    "sg:province":"CA",
    "sg:tags":[
        "town",
        "planner"
    ],
    "sg:website":"http://www.prismplanninginc.com",
    "wof:name":"Prism Planning Inc",
    "wof:placetype":"venue"
},
  "geometry": {"coordinates":[-118.449044,33.995989],"type":"Point"}
}