{
  "type": "Feature",
  "properties": {
    "iso:country":"US",
    "sg:address":"1059 Newpark Mall",
    "sg:city":"Newark",
    "sg:classifiers":[
        {
            "category":"Shopping",
            "subcategory":"Stationery & Office Supplies",
            "type":"Retail Goods"
        },
        {
            "category":"Shopping",
            "subcategory":"Gifts & Souvenirs",
            "type":"Retail Goods"
        }
    ],
    "sg:phone":"+1 510 797 4573",
    "sg:postcode":"94560",
    "sg:province":"CA",
    "sg:tags":[
        "shop",
        "store"
    ],
    "wof:name":"Sanrio",
    "wof:placetype":"venue"
},
  "geometry": {"coordinates":[-122.00030099999999,37.528255],"type":"Point"}
}