{
  "type": "Feature",
  "properties": {
    "iso:country":"US",
    "sg:address":"2040 Short Dr",
    "sg:city":"Hanford",
    "sg:classifiers":[
        {
            "category":"Farming",
            "subcategory":"Farm",
            "type":"Manufacturing & Wholesale Goods"
        }
    ],
    "sg:phone":"+1 559 582 0975",
    "sg:postcode":"93230",
    "sg:province":"CA",
    "sg:tags":[
        "crop",
        "general"
    ],
    "wof:name":"Dehart Farms",
    "wof:placetype":"venue"
},
  "geometry": {"coordinates":[-119.651045,36.348397],"type":"Point"}
}