{
  "type": "Feature",
  "properties": {
    "addr:full":"Howard Ave & Idaho St San Diego CA 92104",
    "addr:postcode":"92104",
    "addr:street":"Howard;St",
    "iso:country":"US",
    "sg:address":"Howard Ave & Idaho St",
    "sg:city":"San Diego",
    "sg:classifiers":[
        {
            "category":"Landmark",
            "subcategory":"Historic",
            "type":"Public Place"
        }
    ],
    "sg:postcode":"92104",
    "sg:province":"CA",
    "sg:tags":[
        "building",
        "historical"
    ],
    "wof:name":"North Park Water Tower",
    "wof:placetype":"venue"
},
  "geometry": {"coordinates":[-117.133876,32.754084],"type":"Point"}
}