{
  "type": "Feature",
  "properties": {
    "addr:full":"33 Creek Road Suite 280 Irvine CA 92604",
    "addr:housenumber":"33",
    "addr:postcode":"92604",
    "addr:street":"Creek Road Suite 280",
    "iso:country":"US",
    "sg:address":"33 Creek Road Suite 280",
    "sg:city":"Irvine",
    "sg:classifiers":[
        {
            "category":"Health Services",
            "subcategory":"Dentist",
            "type":"Services"
        }
    ],
    "sg:phone":"+1 949 551 4540",
    "sg:postcode":"92604",
    "sg:province":"CA",
    "sg:tags":[
        "orthodontist"
    ],
    "sg:website":"www.orthodontist.com",
    "wof:name":"Redmond Orthodontics",
    "wof:placetype":"venue"
},
  "geometry": {"coordinates":[-117.798056,33.675515],"type":"Point"}
}