{
  "type": "Feature",
  "properties": {
    "iso:country":"US",
    "sg:address":"3403 W Ramsey St",
    "sg:city":"Banning",
    "sg:classifiers":[
        {
            "category":"Food & Beverages",
            "subcategory":"Supermarket",
            "type":"Retail Goods"
        },
        {
            "category":"Food & Beverages",
            "subcategory":"Groceries & Convenience Stores",
            "type":"Retail Goods"
        }
    ],
    "sg:phone":"+1 951 849 0667",
    "sg:postcode":"92220",
    "sg:province":"CA",
    "sg:tags":[
        "super"
    ],
    "wof:name":"Rio Ranch Market",
    "wof:placetype":"venue"
},
  "geometry": {"coordinates":[-116.91248400000001,33.925838],"type":"Point"}
}