{
  "type": "Feature",
  "properties": {
    "addr:full":"405 14th St Oakland CA 94612",
    "addr:housenumber":"405",
    "addr:postcode":"94612",
    "addr:street":"14Th St",
    "iso:country":"US",
    "sg:address":"405 14th St",
    "sg:city":"Oakland",
    "sg:classifiers":[
        {
            "category":"Professional",
            "subcategory":"Lawyer & Legal Services",
            "type":"Services"
        }
    ],
    "sg:phone":"+1 510 835 8098",
    "sg:postcode":"94612",
    "sg:province":"CA",
    "sg:tags":[
        "information",
        "attorney",
        "referral",
        "plan"
    ],
    "sg:website":"http://www.youthlaw.org",
    "wof:name":"National Center For Youth Law",
    "wof:placetype":"venue"
},
  "geometry": {"coordinates":[-122.269997,37.803902],"type":"Point"}
}