{
  "type": "Feature",
  "properties": {
    "iso:country":"US",
    "sg:address":"1690 Adams Ave",
    "sg:city":"El Centro",
    "sg:classifiers":[
        {
            "category":"Real Estate",
            "subcategory":"Real Estate Agent",
            "type":"Services"
        }
    ],
    "sg:phone":"+1 760 337 7500",
    "sg:postcode":"92243",
    "sg:province":"CA",
    "sg:tags":[
        "authorities",
        "housing"
    ],
    "wof:name":"Imperial Valley Housing Auth",
    "wof:placetype":"venue"
},
  "geometry": {"coordinates":[-115.572079,32.796623],"type":"Point"}
}