{
  "type": "Feature",
  "properties": {
    "iso:country":"US",
    "sg:address":"1209 Willow Rd",
    "sg:city":"Menlo Park",
    "sg:classifiers":[
        {
            "category":"Food & Beverages",
            "subcategory":"Groceries & Convenience Stores",
            "type":"Retail Goods"
        }
    ],
    "sg:phone":"+1 650 325 8720",
    "sg:postcode":"94025",
    "sg:province":"CA",
    "sg:tags":[
        "grocer"
    ],
    "wof:name":"Quality Market",
    "wof:placetype":"venue"
},
  "geometry": {"coordinates":[-122.154095,37.473867],"type":"Point"}
}