{
  "type": "Feature",
  "properties": {
    "iso:country":"US",
    "sg:address":"1541 Haight St",
    "sg:city":"San Francisco",
    "sg:classifiers":[
        {
            "category":"Shopping",
            "subcategory":"Bicycles & Sporting Goods",
            "type":"Retail Goods"
        }
    ],
    "sg:phone":"+1 415 861 0404",
    "sg:postcode":"94117",
    "sg:province":"CA",
    "sg:tags":[
        "equipment",
        "camping"
    ],
    "wof:name":"Best Of California Surplus",
    "wof:placetype":"venue"
},
  "geometry": {"coordinates":[-122.448036,37.76981],"type":"Point"}
}