{
  "type": "Feature",
  "properties": {
    "addr:full":"373 S Mountain Ave Upland CA 91786",
    "addr:housenumber":"373",
    "addr:postcode":"91786",
    "addr:street":"S Mountain Ave",
    "iso:country":"US",
    "sg:address":"373 S Mountain Ave",
    "sg:city":"Upland",
    "sg:classifiers":[
        {
            "category":"Restaurant",
            "type":"Food & Drink"
        }
    ],
    "sg:phone":"+1 909 946 9077",
    "sg:postcode":"91786",
    "sg:province":"CA",
    "sg:tags":[
        "parlor",
        "ice",
        "cream"
    ],
    "wof:name":"Handel's Homemade Ice Cream",
    "wof:placetype":"venue"
},
  "geometry": {"coordinates":[-117.670214,34.091941],"type":"Point"}
}