{
  "type": "Feature",
  "properties": {
    "addr:full":"123 Di Salvo Ave San Jose CA 95128",
    "addr:housenumber":"123",
    "addr:postcode":"95128",
    "addr:street":"Di Salvo Ave",
    "iso:country":"US",
    "sg:address":"123 Di Salvo Ave",
    "sg:city":"San Jose",
    "sg:classifiers":[
        {
            "category":"Health Services",
            "subcategory":"Doctor",
            "type":"Services"
        }
    ],
    "sg:phone":"+1 408 998 4787",
    "sg:postcode":"95128",
    "sg:province":"CA",
    "sg:tags":[
        "physician",
        "surgeon"
    ],
    "wof:name":"Stephen T Imrie MD",
    "wof:placetype":"venue"
},
  "geometry": {"coordinates":[-121.937099,37.325544],"type":"Point"}
}