{
  "type": "Feature",
  "properties": {
    "iso:country":"US",
    "sg:address":"2229 E Mckinley Avenue",
    "sg:city":"Fresno",
    "sg:classifiers":[
        {
            "category":"Autos & Motor Vehicles",
            "subcategory":"Auto Supplies",
            "type":"Retail Goods"
        }
    ],
    "sg:phone":"+1 559 498 6414",
    "sg:postcode":"93703",
    "sg:province":"CA",
    "sg:tags":[
        "transmission"
    ],
    "wof:name":"Fat Kat Standard Mobile",
    "wof:placetype":"venue"
},
  "geometry": {"coordinates":[-119.78459700000001,36.765023],"type":"Point"}
}