{
  "type": "Feature",
  "properties": {
    "addr:full":"6194 Abrahamsen Ct Eureka CA 95503",
    "addr:housenumber":"6194",
    "addr:postcode":"95503",
    "addr:street":"Abrahamsen Ct",
    "iso:country":"US",
    "sg:address":"6194 Abrahamsen Ct",
    "sg:city":"Eureka",
    "sg:classifiers":[
        {
            "category":"Retail",
            "subcategory":"Repair Shop",
            "type":"Services"
        }
    ],
    "sg:phone":"+1 707 445 8097",
    "sg:postcode":"95503",
    "sg:province":"CA",
    "sg:tags":[
        "equipment"
    ],
    "wof:name":"NCI Svc Co",
    "wof:placetype":"venue"
},
  "geometry": {"coordinates":[-124.199876,40.732933],"type":"Point"}
}