{
  "type": "Feature",
  "properties": {
    "iso:country":"US",
    "sg:address":"10201 Imperial Ave",
    "sg:city":"Cupertino",
    "sg:classifiers":[
        {
            "category":"Professional",
            "subcategory":"Art Services",
            "type":"Services"
        },
        {
            "category":"Professional",
            "subcategory":"Printing & Photocopies",
            "type":"Services"
        }
    ],
    "sg:phone":"+1 408 996 1906",
    "sg:postcode":"95014",
    "sg:province":"CA",
    "sg:tags":[
        "graphic",
        "design"
    ],
    "sg:website":"www.californiatshirt.com",
    "wof:name":"California T-Shirt",
    "wof:placetype":"venue"
},
  "geometry": {"coordinates":[-122.053646,37.320069],"type":"Point"}
}