{
  "type": "Feature",
  "properties": {
    "addr:full":"1328 Henderson Way Woodland CA 95776",
    "addr:housenumber":"1328",
    "addr:postcode":"95776",
    "addr:street":"Henderson Way",
    "iso:country":"US",
    "sg:address":"1328 Henderson Way",
    "sg:city":"Woodland",
    "sg:classifiers":[
        {
            "category":"Home & Garden",
            "subcategory":"Building Materials",
            "type":"Retail Goods"
        },
        {
            "category":"Building & Trades",
            "subcategory":"Construction",
            "type":"Services"
        }
    ],
    "sg:phone":"+1 530 666 5188",
    "sg:postcode":"95776",
    "sg:province":"CA",
    "sg:tags":[
        "roofing",
        "gutter",
        "contractor",
        "downspouts",
        "industrial",
        "contractors-commercial"
    ],
    "sg:website":"http://www.ricolstadroofing.com",
    "wof:name":"Ric Olstad Roofing",
    "wof:placetype":"venue"
},
  "geometry": {"coordinates":[-121.76161999999999,38.670678],"type":"Point"}
}