{
  "type": "Feature",
  "properties": {
    "iso:country":"US",
    "sg:address":"26921 Crown Valley Parkway",
    "sg:city":"Mission Viejo",
    "sg:classifiers":[
        {
            "category":"Health Services",
            "subcategory":"Doctor",
            "type":"Services"
        }
    ],
    "sg:phone":"+1 949 282 1065",
    "sg:postcode":"92691",
    "sg:province":"CA",
    "wof:name":"Pino David M MD",
    "wof:placetype":"venue"
},
  "geometry": {"coordinates":[-117.667489,33.563054],"type":"Point"}
}