{
  "type": "Feature",
  "properties": {
    "addr:full":"625 Broadway Ste 600 San Diego CA 92101",
    "addr:housenumber":"625",
    "addr:postcode":"92101",
    "addr:street":"Broadway Ste 600",
    "iso:country":"US",
    "sg:address":"625 Broadway Ste 600",
    "sg:city":"San Diego",
    "sg:classifiers":[
        {
            "category":"Professional",
            "subcategory":"Lawyer & Legal Services",
            "type":"Services"
        }
    ],
    "sg:phone":"+1 619 234 8787",
    "sg:postcode":"92101",
    "sg:province":"CA",
    "wof:name":"Law Offices of Sergio Feria",
    "wof:placetype":"venue"
},
  "geometry": {"coordinates":[-117.158799,32.715458],"type":"Point"}
}