{
  "type": "Feature",
  "properties": {
    "addr:full":"1010 W Macarthur Blvd Santa Ana CA 92707",
    "addr:housenumber":"1010",
    "addr:postcode":"92707",
    "addr:street":"W Macarthur Blvd",
    "iso:country":"US",
    "sg:address":"1010 W Macarthur Blvd",
    "sg:city":"Santa Ana",
    "sg:classifiers":[
        {
            "category":"Health Services",
            "subcategory":"Clinic",
            "type":"Services"
        }
    ],
    "sg:phone":"+1 949 830 4745",
    "sg:postcode":"92707",
    "sg:province":"CA",
    "sg:tags":[
        "specialty",
        "outpatient"
    ],
    "wof:name":"Physicians Family Walk In Ctr",
    "wof:placetype":"venue"
},
  "geometry": {"coordinates":[-117.88162699999999,33.699845],"type":"Point"}
}