{
  "type": "Feature",
  "properties": {
    "addr:full":"16208 S Vermont Ave Gardena CA 90247",
    "addr:housenumber":"16208",
    "addr:postcode":"90247",
    "addr:street":"S Vermont Ave",
    "iso:country":"US",
    "sg:address":"16208 S Vermont Ave",
    "sg:city":"Gardena",
    "sg:classifiers":[
        {
            "category":"Shopping",
            "subcategory":"Discount & Variety Stores",
            "type":"Retail Goods"
        }
    ],
    "sg:phone":"+1 310 530 8494",
    "sg:postcode":"90247",
    "sg:province":"CA",
    "sg:tags":[
        "merchandise",
        "general"
    ],
    "wof:name":"South Bay Car Sales",
    "wof:placetype":"venue"
},
  "geometry": {"coordinates":[-118.291274,33.883367],"type":"Point"}
}