{
  "type": "Feature",
  "properties": {
    "addr:full":"40 Tesla Irvine CA 92618",
    "addr:housenumber":"40",
    "addr:postcode":"92618",
    "addr:street":"Tesla",
    "iso:country":"US",
    "sg:address":"40 Tesla",
    "sg:city":"Irvine",
    "sg:classifiers":[
        {
            "category":"Sports & Exercise",
            "subcategory":"Gym",
            "type":"Entertainment"
        }
    ],
    "sg:phone":"+1 949 387 7333",
    "sg:postcode":"92618",
    "sg:province":"CA",
    "sg:tags":[
        "trainer"
    ],
    "sg:website":"www.velocitysp.com/irvine",
    "wof:name":"Velocity Sports Performance",
    "wof:placetype":"venue"
},
  "geometry": {"coordinates":[-117.73699999999999,33.633099],"type":"Point"}
}