{
  "type": "Feature",
  "properties": {
    "iso:country":"US",
    "sg:address":"3966 Missouri Flat Rd",
    "sg:city":"Placerville",
    "sg:classifiers":[
        {
            "category":"Banks & Credit Unions",
            "subcategory":"Bank",
            "type":"Services"
        }
    ],
    "sg:phone":"+1 530 626 1300",
    "sg:postcode":"95667",
    "sg:province":"CA",
    "sg:tags":[
        "financing"
    ],
    "wof:name":"Beneficial California Inc",
    "wof:placetype":"venue"
},
  "geometry": {"coordinates":[-120.841785,38.712934],"type":"Point"}
}