{
  "type": "Feature",
  "properties": {
    "addr:full":"2944 E Frontera St Anaheim CA 92806",
    "addr:housenumber":"2944",
    "addr:postcode":"92806",
    "addr:street":"E Frontera St",
    "iso:country":"US",
    "sg:address":"2944 E Frontera St",
    "sg:city":"Anaheim",
    "sg:classifiers":[
        {
            "category":"Manufacturing",
            "subcategory":"Printing",
            "type":"Manufacturing & Wholesale Goods"
        }
    ],
    "sg:phone":"+1 714 632 7234",
    "sg:postcode":"92806",
    "sg:province":"CA",
    "sg:tags":[
        "commercial"
    ],
    "wof:name":"Skate Strap",
    "wof:placetype":"venue"
},
  "geometry": {"coordinates":[-117.864895,33.845943],"type":"Point"}
}