{
  "type": "Feature",
  "properties": {
    "iso:country":"US",
    "sg:address":"4412 Tyndall Ave",
    "sg:city":"Bakersfield",
    "sg:classifiers":[
        {
            "category":"Arts & Performance",
            "subcategory":"Theater",
            "type":"Entertainment"
        }
    ],
    "sg:phone":"+1 661 332 5635",
    "sg:postcode":"93313",
    "sg:province":"CA",
    "sg:tags":[
        "live",
        "music"
    ],
    "wof:name":"K O Productions Mobile Dj's",
    "wof:placetype":"venue"
},
  "geometry": {"coordinates":[-119.049207,35.298825],"type":"Point"}
}