{
  "type": "Feature",
  "properties": {
    "addr:full":"1717 E Olive Ave Merced CA 95340",
    "addr:housenumber":"1717",
    "addr:postcode":"95340",
    "addr:street":"E Olive Ave",
    "iso:country":"US",
    "sg:address":"1717 E Olive Ave",
    "sg:city":"Merced",
    "sg:classifiers":[
        {
            "category":"Organizations",
            "subcategory":"Religious Organization",
            "type":"Services"
        }
    ],
    "sg:phone":"+1 209 723 3707",
    "sg:postcode":"95340",
    "sg:province":"CA",
    "sg:tags":[
        "church"
    ],
    "wof:name":"Bear Creek Community Church",
    "wof:placetype":"venue"
},
  "geometry": {"coordinates":[-120.45108500000001,37.31854],"type":"Point"}
}