{
  "type": "Feature",
  "properties": {
    "iso:country":"US",
    "sg:address":"11109 Greenhurst Dr",
    "sg:city":"Riverside",
    "sg:classifiers":[
        {
            "category":"Manufacturing",
            "subcategory":"Tools & Machinery",
            "type":"Manufacturing & Wholesale Goods"
        }
    ],
    "sg:phone":"+1 951 830 6094",
    "sg:postcode":"92505",
    "sg:province":"CA",
    "sg:tags":[
        "industrial",
        "mfg"
    ],
    "wof:name":"Accurate Machine Werx",
    "wof:placetype":"venue"
},
  "geometry": {"coordinates":[-117.486668,33.913903],"type":"Point"}
}