{
  "type": "Feature",
  "properties": {
    "iso:country":"US",
    "sg:address":"25078 Peachland Avenue, Suite B Peachland Medical Arts Building",
    "sg:city":"Newhall",
    "sg:classifiers":[
        {
            "category":"Personal",
            "subcategory":"Massage",
            "type":"Services"
        },
        {
            "category":"Health Services",
            "subcategory":"Clinic",
            "type":"Services"
        }
    ],
    "sg:phone":"+1 661 255 7772",
    "sg:postcode":"91321",
    "sg:province":"CA",
    "sg:tags":[
        "medical"
    ],
    "sg:website":"www.johnrowinskimassage.com",
    "wof:name":"John Rowinski Massage & Lymphatic Therapy",
    "wof:placetype":"venue"
},
  "geometry": {"coordinates":[-118.54656,34.378697],"type":"Point"}
}