{
  "type": "Feature",
  "properties": {
    "addr:full":"764 Stanford Avenue Los Angeles CA 90021",
    "addr:housenumber":"764",
    "addr:postcode":"90021",
    "addr:street":"Stanford Avenue",
    "iso:country":"US",
    "sg:address":"764 Stanford Avenue",
    "sg:city":"Los Angeles",
    "sg:classifiers":[
        {
            "category":"Shopping",
            "subcategory":"Clothing, Apparel, & Fashions",
            "type":"Retail Goods"
        }
    ],
    "sg:phone":"+1 213 623 7110",
    "sg:postcode":"90021",
    "sg:province":"CA",
    "sg:tags":[
        "accessory",
        "clothing",
        "women's"
    ],
    "wof:name":"Lepanteha Fashions",
    "wof:placetype":"venue"
},
  "geometry": {"coordinates":[-118.246233,34.037431],"type":"Point"}
}