{
  "type": "Feature",
  "properties": {
    "iso:country":"US",
    "sg:address":"1320 L St",
    "sg:city":"Modesto",
    "sg:classifiers":[
        {
            "category":"Organizations",
            "subcategory":"Religious Organization",
            "type":"Services"
        }
    ],
    "sg:phone":"+1 209 577 8112",
    "sg:postcode":"95354",
    "sg:province":"CA",
    "sg:tags":[
        "church"
    ],
    "wof:name":"Christ Unity Baptist Church",
    "wof:placetype":"venue"
},
  "geometry": {"coordinates":[-120.998859,37.645112],"type":"Point"}
}