{
  "type": "Feature",
  "properties": {
    "iso:country":"US",
    "sg:address":"22219 Mission Blvd Apt B",
    "sg:city":"Hayward",
    "sg:classifiers":[
        {
            "category":"Building & Trades",
            "subcategory":"Landscaping Services",
            "type":"Services"
        }
    ],
    "sg:phone":"+1 510 776 2103",
    "sg:postcode":"94541",
    "sg:province":"CA",
    "wof:name":"Sea Breeze Landscaping",
    "wof:placetype":"venue"
},
  "geometry": {"coordinates":[-122.08880499999999,37.676153],"type":"Point"}
}