{
  "type": "Feature",
  "properties": {
    "iso:country":"US",
    "sg:address":"1701 Ocean Front Walk",
    "sg:city":"Venice",
    "sg:classifiers":[
        {
            "category":"Restaurant",
            "type":"Food & Drink"
        }
    ],
    "sg:phone":"+1 310 399 6990",
    "sg:postcode":"90291",
    "sg:province":"CA",
    "sg:tags":[
        "out"
    ],
    "wof:name":"Beach Garden",
    "wof:placetype":"venue"
},
  "geometry": {"coordinates":[-118.47318,33.986323],"type":"Point"}
}