{
  "type": "Feature",
  "properties": {
    "iso:country":"US",
    "sg:address":"1236 W 5th St",
    "sg:city":"Santa Ana",
    "sg:classifiers":[
        {
            "category":"Ice Cream",
            "type":"Food & Drink"
        }
    ],
    "sg:phone":"+1 714 547 1394",
    "sg:postcode":"92703",
    "sg:province":"CA",
    "sg:tags":[
        "frozen",
        "yogurt"
    ],
    "wof:name":"Tropical Ice Cream",
    "wof:placetype":"venue"
},
  "geometry": {"coordinates":[-117.88400300000001,33.748901],"type":"Point"}
}