{
  "type": "Feature",
  "properties": {
    "addr:full":"25662 Maximus St Mission Viejo CA 92691",
    "addr:postcode":"25662;92691",
    "addr:street":"Maximus St",
    "iso:country":"US",
    "sg:address":"25662 Maximus St",
    "sg:city":"Mission Viejo",
    "sg:classifiers":[
        {
            "category":"Shopping",
            "type":"Retail Goods"
        }
    ],
    "sg:phone":"+1 949 583 9291",
    "sg:postcode":"92691",
    "sg:province":"CA",
    "sg:tags":[
        "merchandise"
    ],
    "wof:name":"Custom Outdoor Concepts",
    "wof:placetype":"venue"
},
  "geometry": {"coordinates":[-117.68304500000001,33.60179],"type":"Point"}
}