{
  "type": "Feature",
  "properties": {
    "addr:full":"1158 Key Avenue San Francisco CA 94124",
    "addr:housenumber":"1158",
    "addr:postcode":"94124",
    "addr:street":"Key Avenue",
    "iso:country":"US",
    "sg:address":"1158 Key Avenue",
    "sg:city":"San Francisco",
    "sg:classifiers":[
        {
            "category":"Building & Trades",
            "subcategory":"Plumbing",
            "type":"Services"
        }
    ],
    "sg:phone":"+1 415 550 7628",
    "sg:postcode":"94124",
    "sg:province":"CA",
    "wof:name":"J.L. Plumbing",
    "wof:placetype":"venue"
},
  "geometry": {"coordinates":[-122.398858,37.720834],"type":"Point"}
}