{
  "type": "Feature",
  "properties": {
    "addr:full":"14556 Arrow Blvd Fontana CA 92335",
    "addr:housenumber":"14556",
    "addr:postcode":"92335",
    "addr:street":"Arrow Blvd",
    "iso:country":"US",
    "sg:address":"14556 Arrow Blvd",
    "sg:city":"Fontana",
    "sg:classifiers":[
        {
            "category":"Health Services",
            "subcategory":"Health Practitioner",
            "type":"Services"
        }
    ],
    "sg:phone":"+1 909 829 9443",
    "sg:postcode":"92335",
    "sg:province":"CA",
    "sg:tags":[
        "acupuncture"
    ],
    "wof:name":"Dalia Healthe Seven",
    "wof:placetype":"venue"
},
  "geometry": {"coordinates":[-117.488793,34.099312],"type":"Point"}
}