{
  "type": "Feature",
  "properties": {
    "iso:country":"US",
    "sg:address":"809 W San Marcos Blvd",
    "sg:city":"San Marcos",
    "sg:classifiers":[
        {
            "category":"Real Estate",
            "subcategory":"Real Estate Agent",
            "type":"Services"
        }
    ],
    "sg:phone":"+1 760 736 3600",
    "sg:postcode":"92078",
    "sg:province":"CA",
    "wof:name":"Golden Pacific Real Estate",
    "wof:placetype":"venue"
},
  "geometry": {"coordinates":[-117.18331499999999,33.135954],"type":"Point"}
}