{
  "type": "Feature",
  "properties": {
    "addr:full":"7245 Hillside Ave Los Angeles CA 90046",
    "addr:housenumber":"7245",
    "addr:postcode":"90046",
    "addr:street":"Hillside Ave",
    "iso:country":"US",
    "sg:address":"7245 Hillside Ave",
    "sg:city":"Los Angeles",
    "sg:classifiers":[
        {
            "category":"Real Estate",
            "subcategory":"Real Estate Operator",
            "type":"Services"
        }
    ],
    "sg:phone":"+1 323 851 2099",
    "sg:postcode":"90046",
    "sg:province":"CA",
    "sg:tags":[
        "apartment"
    ],
    "wof:name":"Hillside Terrace Apartments",
    "wof:placetype":"venue"
},
  "geometry": {"coordinates":[-118.347897,34.104691],"type":"Point"}
}