{
  "type": "Feature",
  "properties": {
    "iso:country":"US",
    "sg:address":"1862 S Broadway",
    "sg:city":"Santa Maria",
    "sg:classifiers":[
        {
            "category":"Banks & Credit Unions",
            "subcategory":"Investment Brokerage",
            "type":"Services"
        }
    ],
    "sg:phone":"+1 805 922 6901",
    "sg:postcode":"93454",
    "sg:province":"CA",
    "sg:tags":[
        "stock",
        "bond"
    ],
    "sg:website":"www.maguireinvestments.com",
    "wof:name":"Maguire Investments Inc",
    "wof:placetype":"venue"
},
  "geometry": {"coordinates":[-120.435858,34.926745],"type":"Point"}
}