{
  "type": "Feature",
  "properties": {
    "iso:country":"US",
    "sg:address":"17112 Simonds St",
    "sg:city":"Granada Hills",
    "sg:classifiers":[
        {
            "category":"Building & Trades",
            "subcategory":"Plumbing",
            "type":"Services"
        }
    ],
    "sg:phone":"+1 818 368 3943",
    "sg:postcode":"91344",
    "sg:province":"CA",
    "sg:tags":[
        "contractor"
    ],
    "wof:name":"Tee Plumbing",
    "wof:placetype":"venue"
},
  "geometry": {"coordinates":[-118.50929499999999,34.276376],"type":"Point"}
}