{
  "type": "Feature",
  "properties": {
    "addr:full":"5920 Gullstrand St San Diego CA 92122",
    "addr:housenumber":"5920",
    "addr:postcode":"92122",
    "addr:street":"Gullstrand St",
    "iso:country":"US",
    "sg:address":"5920 Gullstrand St",
    "sg:city":"San Diego",
    "sg:classifiers":[
        {
            "category":"Manufacturing",
            "subcategory":"Printing",
            "type":"Manufacturing & Wholesale Goods"
        }
    ],
    "sg:phone":"+1 858 455 9861",
    "sg:postcode":"92122",
    "sg:province":"CA",
    "sg:tags":[
        "periodical"
    ],
    "wof:name":"Dave A Underwood",
    "wof:placetype":"venue"
},
  "geometry": {"coordinates":[-117.190703,32.849973],"type":"Point"}
}