{
  "type": "Feature",
  "properties": {
    "addr:full":"4582 S Centinela Ave Los Angeles CA 90066",
    "addr:housenumber":"4582",
    "addr:postcode":"90066",
    "addr:street":"S Centinela Ave",
    "iso:country":"US",
    "sg:address":"4582 S Centinela Ave",
    "sg:city":"Los Angeles",
    "sg:classifiers":[
        {
            "category":"Restaurant",
            "type":"Food & Drink"
        }
    ],
    "sg:phone":"+1 310 391 8667",
    "sg:postcode":"90066",
    "sg:province":"CA",
    "sg:tags":[
        "mexican"
    ],
    "sg:website":"www.pepestacosla.com/",
    "wof:name":"Pepe's Tacos",
    "wof:placetype":"venue"
},
  "geometry": {"coordinates":[-118.420998,33.991199],"type":"Point"}
}