{
  "type": "Feature",
  "properties": {
    "addr:full":"1160 Mercantile St Oxnard CA 93030",
    "addr:housenumber":"1160",
    "addr:postcode":"93030",
    "addr:street":"Mercantile St",
    "iso:country":"US",
    "sg:address":"1160 Mercantile St",
    "sg:city":"Oxnard",
    "sg:classifiers":[
        {
            "category":"Manufacturing",
            "subcategory":"Metals",
            "type":"Manufacturing & Wholesale Goods"
        }
    ],
    "sg:phone":"+1 805 487 8501",
    "sg:postcode":"93030",
    "sg:province":"CA",
    "sg:tags":[
        "plating"
    ],
    "sg:website":"www.multichrome.com",
    "wof:name":"Coastal Multichrome Co",
    "wof:placetype":"venue"
},
  "geometry": {"coordinates":[-119.169434,34.188998],"type":"Point"}
}