{
  "type": "Feature",
  "properties": {
    "addr:full":"474 Moore Ln Healdsburg CA 95448",
    "addr:housenumber":"474",
    "addr:postcode":"95448",
    "addr:street":"Moore Ln",
    "iso:country":"US",
    "sg:address":"474 Moore Ln",
    "sg:city":"Healdsburg",
    "sg:classifiers":[
        {
            "category":"Professional",
            "type":"Services"
        }
    ],
    "sg:phone":"+1 707 433 5101",
    "sg:postcode":"95448",
    "sg:province":"CA",
    "wof:name":"Master Machines",
    "wof:placetype":"venue"
},
  "geometry": {"coordinates":[-122.874915,38.611676],"type":"Point"}
}