{
  "type": "Feature",
  "properties": {
    "iso:country":"US",
    "sg:address":"255 N El Cielo Rd Ste 140",
    "sg:city":"Palm Springs",
    "sg:classifiers":[
        {
            "category":"Real Estate",
            "subcategory":"Real Estate Services",
            "type":"Services"
        }
    ],
    "sg:phone":"+1 760 325 4091",
    "sg:postcode":"92262",
    "sg:province":"CA",
    "sg:tags":[
        "management",
        "property"
    ],
    "wof:name":"B P Management",
    "wof:placetype":"venue"
},
  "geometry": {"coordinates":[-116.510775,33.825299],"type":"Point"}
}