{
  "type": "Feature",
  "properties": {
    "iso:country":"US",
    "sg:address":"107 Sutter Ave",
    "sg:city":"Roseville",
    "sg:classifiers":[
        {
            "category":"Organizations",
            "subcategory":"Community Association",
            "type":"Services"
        }
    ],
    "sg:phone":"+1 916 786 4800",
    "sg:postcode":"95678",
    "sg:province":"CA",
    "sg:tags":[
        "club"
    ],
    "wof:name":"Lions-Roseville Host",
    "wof:placetype":"venue"
},
  "geometry": {"coordinates":[-121.279572,38.748514],"type":"Point"}
}