{
  "type": "Feature",
  "properties": {
    "iso:country":"US",
    "sg:address":"4555 El Cajon Boulevard",
    "sg:city":"San Diego",
    "sg:classifiers":[
        {
            "category":"Banks & Credit Unions",
            "subcategory":"Financial Services",
            "type":"Services"
        }
    ],
    "sg:phone":"+1 619 563 5263",
    "sg:postcode":"92115",
    "sg:province":"CA",
    "sg:tags":[
        "broker",
        "mortgage"
    ],
    "wof:name":"New Land Realty & Mortgage",
    "wof:placetype":"venue"
},
  "geometry": {"coordinates":[-117.096397,32.755425],"type":"Point"}
}