{
  "type": "Feature",
  "properties": {
    "addr:full":"217 Colfax Ave Grass Valley CA 95945",
    "addr:housenumber":"217",
    "addr:postcode":"95945",
    "addr:street":"Colfax Ave",
    "iso:country":"US",
    "sg:address":"217 Colfax Ave",
    "sg:city":"Grass Valley",
    "sg:classifiers":[
        {
            "category":"Manufacturing",
            "subcategory":"Food",
            "type":"Manufacturing & Wholesale Goods"
        }
    ],
    "sg:phone":"+1 530 273 0286",
    "sg:postcode":"95945",
    "sg:province":"CA",
    "sg:tags":[
        "product",
        "health"
    ],
    "wof:name":"King Richard's Pasties",
    "wof:placetype":"venue"
},
  "geometry": {"coordinates":[-121.058605,39.215917],"type":"Point"}
}