{
  "type": "Feature",
  "properties": {
    "addr:full":"203 Ave Victoria San Clemente CA 92672",
    "addr:housenumber":"203",
    "addr:postcode":"92672",
    "addr:street":"Ave",
    "iso:country":"US",
    "sg:address":"203 Ave Victoria",
    "sg:city":"San Clemente",
    "sg:classifiers":[
        {
            "category":"Personal",
            "subcategory":"Barber",
            "type":"Services"
        }
    ],
    "sg:phone":"+1 949 498 6401",
    "sg:postcode":"92672",
    "sg:province":"CA",
    "wof:name":"Bladewerks",
    "wof:placetype":"venue"
},
  "geometry": {"coordinates":[-117.615916,33.423095],"type":"Point"}
}