{
  "type": "Feature",
  "properties": {
    "addr:full":"16702 Grevillea Ave Lawndale CA 90260",
    "addr:housenumber":"16702",
    "addr:postcode":"ca 90260",
    "addr:street":"Grevillea Ave",
    "iso:country":"US",
    "sg:address":"16702 Grevillea Ave",
    "sg:city":"Lawndale",
    "sg:classifiers":[
        {
            "category":"Organizations",
            "subcategory":"Religious Organization",
            "type":"Services"
        }
    ],
    "sg:phone":"+1 310 371 2239",
    "sg:postcode":"90260",
    "sg:province":"CA",
    "sg:tags":[
        "church"
    ],
    "wof:name":"Lawndale Wesleyan Church",
    "wof:placetype":"venue"
},
  "geometry": {"coordinates":[-118.354709,33.878512],"type":"Point"}
}