{
  "type": "Feature",
  "properties": {
    "addr:full":"8080 Madison Ave Ste 204A Fair Oaks CA 95628",
    "addr:housenumber":"8080",
    "addr:postcode":"95628",
    "addr:street":"Madison Ave Ste 204A",
    "iso:country":"US",
    "sg:address":"8080 Madison Ave Ste 204A",
    "sg:city":"Fair Oaks",
    "sg:classifiers":[
        {
            "category":"Health Services",
            "subcategory":"Chiropractor",
            "type":"Services"
        }
    ],
    "sg:phone":"+1 916 965 8171",
    "sg:postcode":"95628",
    "sg:province":"CA",
    "sg:website":"www.lemaychiropractic.com/",
    "wof:name":"LeMay Chiropractic",
    "wof:placetype":"venue"
},
  "geometry": {"coordinates":[-121.263411,38.663975],"type":"Point"}
}