{
  "type": "Feature",
  "properties": {
    "iso:country":"US",
    "sg:address":"2601 Legend Ln",
    "sg:city":"Rowland Heights",
    "sg:classifiers":[
        {
            "category":"Banks & Credit Unions",
            "subcategory":"Financial Services",
            "type":"Services"
        }
    ],
    "sg:phone":"+1 626 912 5657",
    "sg:postcode":"91748",
    "sg:province":"CA",
    "sg:tags":[
        "trust",
        "management"
    ],
    "wof:name":"Parra Family Trust",
    "wof:placetype":"venue"
},
  "geometry": {"coordinates":[-117.91489799999999,33.973214],"type":"Point"}
}