{
  "type": "Feature",
  "properties": {
    "addr:full":"3944 Camellia Ln Santa Barbara CA 93110",
    "addr:housenumber":"3944",
    "addr:postcode":"93110",
    "addr:street":"Camellia Ln",
    "iso:country":"US",
    "sg:address":"3944 Camellia Ln",
    "sg:city":"Santa Barbara",
    "sg:classifiers":[
        {
            "category":"Building & Trades",
            "subcategory":"Landscaping Services",
            "type":"Services"
        }
    ],
    "sg:phone":"+1 805 965 8668",
    "sg:postcode":"93110",
    "sg:province":"CA",
    "sg:tags":[
        "landscape",
        "contractor"
    ],
    "wof:name":"Sierrascapes",
    "wof:placetype":"venue"
},
  "geometry": {"coordinates":[-119.752646,34.443507],"type":"Point"}
}