{
  "type": "Feature",
  "properties": {
    "addr:full":"1148 23rd St Richmond CA 94804",
    "addr:housenumber":"1148",
    "addr:postcode":"94804",
    "addr:street":"23Rd St",
    "iso:country":"US",
    "sg:address":"1148 23rd St",
    "sg:city":"Richmond",
    "sg:classifiers":[
        {
            "category":"Communications",
            "subcategory":"Film & Video Production",
            "type":"Services"
        }
    ],
    "sg:phone":"+1 510 233 4016",
    "sg:postcode":"94804",
    "sg:province":"CA",
    "sg:tags":[
        "taping"
    ],
    "wof:name":"Able Video",
    "wof:placetype":"venue"
},
  "geometry": {"coordinates":[-122.347342,37.949936],"type":"Point"}
}