{
  "type": "Feature",
  "properties": {
    "iso:country":"US",
    "sg:address":"2983 Michelson Dr",
    "sg:city":"Irvine",
    "sg:classifiers":[
        {
            "category":"Building & Trades",
            "subcategory":"Locksmith",
            "type":"Services"
        }
    ],
    "sg:phone":"+1 714 752 5061",
    "sg:postcode":"92612",
    "sg:province":"CA",
    "sg:tags":[
        "key"
    ],
    "sg:website":"www.availablelocksmithinc.com/Lo...",
    "wof:name":"Emergency Auto Locksmith",
    "wof:placetype":"venue"
},
  "geometry": {"coordinates":[-117.84542999999999,33.671235],"type":"Point"}
}