{
  "type": "Feature",
  "properties": {
    "addr:full":"1741 E Lambert Rd La Habra CA 90631",
    "addr:housenumber":"1741",
    "addr:postcode":"90631",
    "addr:street":"E Lambert Rd",
    "iso:country":"US",
    "sg:address":"1741 E Lambert Rd",
    "sg:city":"La Habra",
    "sg:classifiers":[
        {
            "category":"Retail",
            "subcategory":"Auto Repair",
            "type":"Services"
        }
    ],
    "sg:phone":"+1 562 697 3133",
    "sg:postcode":"90631",
    "sg:province":"CA",
    "sg:tags":[
        "body",
        "automobile",
        "painting"
    ],
    "wof:name":"Hanson's Auto Craft",
    "wof:placetype":"venue"
},
  "geometry": {"coordinates":[-117.92818699999999,33.924685],"type":"Point"}
}