{
  "type": "Feature",
  "properties": {
    "iso:country":"US",
    "sg:address":"2280 Otay Lakes Rd",
    "sg:city":"Chula Vista",
    "sg:classifiers":[
        {
            "category":"Banks & Credit Unions",
            "subcategory":"Bank",
            "type":"Services"
        }
    ],
    "sg:phone":"+1 619 421 5038",
    "sg:postcode":"91915",
    "sg:province":"CA",
    "wof:name":"San Diego County Credit Union",
    "wof:placetype":"venue"
},
  "geometry": {"coordinates":[-116.966404,32.647705],"type":"Point"}
}