{
  "type": "Feature",
  "properties": {
    "iso:country":"US",
    "sg:address":"1610 Monterey Rd Ste B",
    "sg:city":"San Jose",
    "sg:classifiers":[
        {
            "category":"Health Services",
            "subcategory":"Clinic",
            "type":"Services"
        }
    ],
    "sg:phone":"+1 408 280 1071",
    "sg:postcode":"95112",
    "sg:province":"CA",
    "sg:tags":[
        "cannabis"
    ],
    "wof:name":"Monterey Road Dispensary",
    "wof:placetype":"venue"
},
  "geometry": {"coordinates":[-121.870008,37.312718],"type":"Point"}
}