{
  "type": "Feature",
  "properties": {
    "addr:full":"3452 Main St Cottonwood CA 96022",
    "addr:housenumber":"3452",
    "addr:postcode":"96022",
    "addr:street":"Main St",
    "iso:country":"US",
    "sg:address":"3452 Main St",
    "sg:city":"Cottonwood",
    "sg:classifiers":[
        {
            "category":"Education",
            "subcategory":"School",
            "type":"Public Place"
        }
    ],
    "sg:phone":"+1 530 347 1477",
    "sg:postcode":"96022",
    "sg:province":"CA",
    "sg:tags":[
        "k-",
        "private"
    ],
    "wof:name":"Westwood Charter School",
    "wof:placetype":"venue"
},
  "geometry": {"coordinates":[-122.281036,40.38785],"type":"Point"}
}