{
  "type": "Feature",
  "properties": {
    "addr:full":"1575 N Van Ness Ave Fresno CA 93728",
    "addr:housenumber":"1575",
    "addr:postcode":"93728",
    "addr:street":"N Van Ness Ave",
    "iso:country":"US",
    "sg:address":"1575 N Van Ness Ave",
    "sg:city":"Fresno",
    "sg:classifiers":[
        {
            "category":"Health Services",
            "subcategory":"Health Practitioner",
            "type":"Services"
        }
    ],
    "sg:phone":"+1 559 266 2694",
    "sg:postcode":"93728",
    "sg:province":"CA",
    "sg:tags":[
        "psychologist"
    ],
    "wof:name":"Affiliates For Personal Growth",
    "wof:placetype":"venue"
},
  "geometry": {"coordinates":[-119.79904500000001,36.763591],"type":"Point"}
}