{
  "type": "Feature",
  "properties": {
    "iso:country":"US",
    "sg:address":"5310 Marina Pacifica Dr",
    "sg:city":"Long Beach",
    "sg:classifiers":[
        {
            "category":"Professional",
            "subcategory":"Engineering",
            "type":"Services"
        }
    ],
    "sg:phone":"+1 562 594 9111",
    "sg:postcode":"90803",
    "sg:province":"CA",
    "sg:tags":[
        "c",
        "marine",
        "telecommunication"
    ],
    "wof:name":"Communication & Trading Svcs",
    "wof:placetype":"venue"
},
  "geometry": {"coordinates":[-118.118588,33.760823],"type":"Point"}
}