{
  "type": "Feature",
  "properties": {
    "addr:full":"21 S Main St Willits CA 95490",
    "addr:housenumber":"21",
    "addr:postcode":"95490",
    "addr:street":"S Main St",
    "iso:country":"US",
    "sg:address":"21 S Main St",
    "sg:city":"Willits",
    "sg:classifiers":[
        {
            "category":"Shopping",
            "subcategory":"Clothing, Apparel, & Fashions",
            "type":"Retail Goods"
        }
    ],
    "sg:phone":"+1 707 456 9025",
    "sg:postcode":"95490",
    "sg:province":"CA",
    "wof:name":"Blue Sky Gallery",
    "wof:placetype":"venue"
},
  "geometry": {"coordinates":[-123.35436799999999,39.412155],"type":"Point"}
}