{
  "type": "Feature",
  "properties": {
    "iso:country":"US",
    "sg:address":"323 S 23rd St",
    "sg:city":"San Jose",
    "sg:classifiers":[
        {
            "category":"Mining & Drilling",
            "type":"Manufacturing & Wholesale Goods"
        }
    ],
    "sg:phone":"+1 408 297 3386",
    "sg:postcode":"95116",
    "sg:province":"CA",
    "sg:tags":[
        "stone",
        "dimension",
        "quarry"
    ],
    "wof:name":"The Caves Stone",
    "wof:placetype":"venue"
},
  "geometry": {"coordinates":[-121.865058,37.342801],"type":"Point"}
}