{
  "type": "Feature",
  "properties": {
    "addr:full":"6914 Fulton Ave North Hollywood CA 91605",
    "addr:housenumber":"6914",
    "addr:postcode":"91605",
    "addr:street":"Fulton Ave",
    "iso:country":"US",
    "sg:address":"6914 Fulton Ave",
    "sg:city":"North Hollywood",
    "sg:classifiers":[
        {
            "category":"Retail",
            "subcategory":"Car Wash",
            "type":"Services"
        }
    ],
    "sg:phone":"+1 818 765 5034",
    "sg:postcode":"91605",
    "sg:province":"CA",
    "sg:tags":[
        "automobile",
        "detail",
        "clean"
    ],
    "wof:name":"S S Auto Detail",
    "wof:placetype":"venue"
},
  "geometry": {"coordinates":[-118.42244700000001,34.195594],"type":"Point"}
}