{
  "type": "Feature",
  "properties": {
    "addr:full":"670 College St Hollister CA 95023",
    "addr:housenumber":"670",
    "addr:postcode":"hollister ca 95023",
    "addr:street":"College St",
    "iso:country":"US",
    "sg:address":"670 College St",
    "sg:city":"Hollister",
    "sg:classifiers":[
        {
            "category":"Education",
            "subcategory":"School",
            "type":"Public Place"
        }
    ],
    "sg:phone":"+1 831 637 4157",
    "sg:postcode":"95023",
    "sg:province":"CA",
    "sg:website":"www.sacredheartschool.org",
    "wof:name":"Sacred Heart School",
    "wof:placetype":"venue"
},
  "geometry": {"coordinates":[-121.409447,36.850725],"type":"Point"}
}