{
  "type": "Feature",
  "properties": {
    "iso:country":"US",
    "sg:address":"43769 15th St W",
    "sg:city":"Lancaster",
    "sg:classifiers":[
        {
            "category":"Restaurant",
            "type":"Food & Drink"
        }
    ],
    "sg:phone":"+1 661 951 7799",
    "sg:postcode":"93534",
    "sg:province":"CA",
    "wof:name":"Jalapeno Grill",
    "wof:placetype":"venue"
},
  "geometry": {"coordinates":[-118.156808,34.680008],"type":"Point"}
}