{
  "type": "Feature",
  "properties": {
    "addr:full":"23430 Moon Rd Corning CA 96021",
    "addr:housenumber":"23430",
    "addr:postcode":"96021",
    "addr:street":"Moon Rd",
    "iso:country":"US",
    "sg:address":"23430 Moon Rd",
    "sg:city":"Corning",
    "sg:classifiers":[
        {
            "category":"Farming",
            "subcategory":"Crops",
            "type":"Manufacturing & Wholesale Goods"
        }
    ],
    "sg:phone":"+1 530 824 3230",
    "sg:postcode":"96021",
    "sg:province":"CA",
    "sg:tags":[
        "grove",
        "nut",
        "tree"
    ],
    "wof:name":"Walter Mayes",
    "wof:placetype":"venue"
},
  "geometry": {"coordinates":[-122.16395199999999,39.917036],"type":"Point"}
}