{
  "type": "Feature",
  "properties": {
    "addr:full":"120 West Sierra Madre Blvd Sierra Madre CA 91024",
    "addr:housenumber":"120",
    "addr:postcode":"91024",
    "addr:street":"West Sierra Madre Blvd",
    "iso:country":"US",
    "sg:address":"120 West Sierra Madre Blvd",
    "sg:city":"Sierra Madre",
    "sg:classifiers":[
        {
            "category":"Professional",
            "subcategory":"Accounting & Tax Preparation",
            "type":"Services"
        }
    ],
    "sg:phone":"+1 626 355 8851",
    "sg:postcode":"91024",
    "sg:province":"CA",
    "sg:tags":[
        "accountant"
    ],
    "wof:name":"Seto Kirakosian Accountancy Corporation",
    "wof:placetype":"venue"
},
  "geometry": {"coordinates":[-118.055404,34.161612],"type":"Point"}
}