{
  "type": "Feature",
  "properties": {
    "addr:full":"18100 E Front St Linden CA 95236",
    "addr:housenumber":"18100",
    "addr:postcode":"95236",
    "addr:street":"E Front St",
    "iso:country":"US",
    "sg:address":"18100 E Front St",
    "sg:city":"Linden",
    "sg:classifiers":[
        {
            "category":"Social Services",
            "subcategory":"Child Care",
            "type":"Services"
        }
    ],
    "sg:phone":"+1 209 887 2589",
    "sg:postcode":"95236",
    "sg:province":"CA",
    "sg:tags":[
        "nursery",
        "day"
    ],
    "wof:name":"Head Start",
    "wof:placetype":"venue"
},
  "geometry": {"coordinates":[-121.094688,38.021169],"type":"Point"}
}