{
  "type": "Feature",
  "properties": {
    "addr:full":"5121 Westpark Dr North Hollywood CA 91601",
    "addr:housenumber":"5121",
    "addr:postcode":"91601",
    "addr:street":"Westpark Dr",
    "iso:country":"US",
    "sg:address":"5121 Westpark Dr",
    "sg:city":"North Hollywood",
    "sg:classifiers":[
        {
            "category":"Real Estate",
            "subcategory":"Real Estate Operator",
            "type":"Services"
        }
    ],
    "sg:phone":"+1 818 506 5989",
    "sg:postcode":"91601",
    "sg:province":"CA",
    "sg:tags":[
        "condominium"
    ],
    "wof:name":"Westpark Association",
    "wof:placetype":"venue"
},
  "geometry": {"coordinates":[-118.382693,34.163358],"type":"Point"}
}