{
  "type": "Feature",
  "properties": {
    "iso:country":"US",
    "sg:address":"2201 Jasmine St",
    "sg:city":"Oxnard",
    "sg:classifiers":[
        {
            "category":"Education",
            "subcategory":"School",
            "type":"Public Place"
        }
    ],
    "sg:phone":"+1 805 983 2280",
    "sg:postcode":"93036",
    "sg:province":"CA",
    "wof:name":"Sierra Linda Elementary",
    "wof:placetype":"venue"
},
  "geometry": {"coordinates":[-119.187778,34.22495],"type":"Point"}
}