{
  "type": "Feature",
  "properties": {
    "addr:full":"4806 Hooper Ave Los Angeles CA 90011",
    "addr:housenumber":"4806",
    "addr:postcode":"90011",
    "addr:street":"Hooper Ave",
    "iso:country":"US",
    "sg:address":"4806 Hooper Ave",
    "sg:city":"Los Angeles",
    "sg:classifiers":[
        {
            "category":"Food & Beverages",
            "subcategory":"Groceries & Convenience Stores",
            "type":"Retail Goods"
        }
    ],
    "sg:phone":"+1 323 234 4996",
    "sg:postcode":"90011",
    "sg:province":"CA",
    "wof:name":"Azte Paca",
    "wof:placetype":"venue"
},
  "geometry": {"coordinates":[-118.251948,33.999979],"type":"Point"}
}