{
  "type": "Feature",
  "properties": {
    "iso:country":"US",
    "sg:address":"2025 S Fern Ave",
    "sg:city":"Ontario",
    "sg:classifiers":[
        {
            "category":"Professional",
            "subcategory":"Business Services",
            "type":"Services"
        }
    ],
    "sg:phone":"+1 909 241 0063",
    "sg:postcode":"91762",
    "sg:province":"CA",
    "sg:tags":[
        "embroidery"
    ],
    "wof:name":"Serafin Design Studio",
    "wof:placetype":"venue"
},
  "geometry": {"coordinates":[-117.654521,34.033896],"type":"Point"}
}