{
  "type": "Feature",
  "properties": {
    "addr:full":"18625 Sherman Way Ste 104 Reseda CA 91335",
    "addr:housenumber":"18625",
    "addr:postcode":"91335",
    "addr:street":"Sherman Way Ste 104",
    "iso:country":"US",
    "sg:address":"18625 Sherman Way Ste 104",
    "sg:city":"Reseda",
    "sg:classifiers":[
        {
            "category":"Health Services",
            "subcategory":"Doctor",
            "type":"Services"
        }
    ],
    "sg:phone":"+1 818 342 8171",
    "sg:postcode":"91335",
    "sg:province":"CA",
    "sg:tags":[
        "medicine",
        "physician",
        "surgeon",
        "internal",
        "surgeons"
    ],
    "wof:name":"Phan Mai Tuyet Md",
    "wof:placetype":"venue"
},
  "geometry": {"coordinates":[-118.539688,34.20118],"type":"Point"}
}