{
  "type": "Feature",
  "properties": {
    "iso:country":"US",
    "sg:address":"8669 Research Dr",
    "sg:city":"Irvine",
    "sg:classifiers":[
        {
            "category":"Shopping",
            "subcategory":"Bicycles & Sporting Goods",
            "type":"Retail Goods"
        }
    ],
    "sg:phone":"+1 949 789 1800",
    "sg:postcode":"92618",
    "sg:province":"CA",
    "sg:website":"www.burton.com",
    "wof:name":"Burton Snowboards",
    "wof:placetype":"venue"
},
  "geometry": {"coordinates":[-117.74048000000001,33.644468],"type":"Point"}
}