{
  "type": "Feature",
  "properties": {
    "addr:full":"60 W Park Row Ave Ventura CA 93001",
    "addr:housenumber":"60",
    "addr:postcode":"93001",
    "addr:street":"W Park Row Ave",
    "iso:country":"US",
    "sg:address":"60 W Park Row Ave",
    "sg:city":"Ventura",
    "sg:classifiers":[
        {
            "category":"Autos & Motor Vehicles",
            "subcategory":"Automobile Sales",
            "type":"Retail Goods"
        }
    ],
    "sg:phone":"+1 805 653 5130",
    "sg:postcode":"93001",
    "sg:province":"CA",
    "sg:tags":[
        "dealers-used",
        "car",
        "used",
        "cars-wholesale"
    ],
    "wof:name":"Erickson Auto",
    "wof:placetype":"venue"
},
  "geometry": {"coordinates":[-119.300809,34.284748],"type":"Point"}
}