{
  "type": "Feature",
  "properties": {
    "addr:full":"1221 State St Santa Barbara CA 93101",
    "addr:housenumber":"1221",
    "addr:postcode":"93101",
    "addr:street":"State St",
    "iso:country":"US",
    "sg:address":"1221 State St",
    "sg:city":"Santa Barbara",
    "sg:classifiers":[
        {
            "category":"Health Services",
            "subcategory":"Chiropractor",
            "type":"Services"
        }
    ],
    "sg:phone":"+1 805 966 6920",
    "sg:postcode":"93101",
    "sg:province":"CA",
    "wof:name":"Kling Chiropractic",
    "wof:placetype":"venue"
},
  "geometry": {"coordinates":[-119.70556000000001,34.424045],"type":"Point"}
}