{
  "type": "Feature",
  "properties": {
    "addr:full":"1508 E Fairfield Ct Ontario CA 91761",
    "addr:housenumber":"1508",
    "addr:postcode":"91761",
    "addr:street":"E Fairfield Ct",
    "iso:country":"US",
    "sg:address":"1508 E Fairfield Ct",
    "sg:city":"Ontario",
    "sg:classifiers":[
        {
            "category":"Building & Trades",
            "subcategory":"Cleaning & Sanitation",
            "type":"Services"
        }
    ],
    "sg:phone":"+1 909 930 2586",
    "sg:postcode":"91761",
    "sg:province":"CA",
    "sg:tags":[
        "janitor"
    ],
    "wof:name":"Spik N Span Janitorial Svc",
    "wof:placetype":"venue"
},
  "geometry": {"coordinates":[-117.61581099999999,34.029659],"type":"Point"}
}