{
  "type": "Feature",
  "properties": {
    "iso:country":"US",
    "sg:address":"15207 S Vermont Ave",
    "sg:city":"Gardena",
    "sg:classifiers":[
        {
            "category":"Personal",
            "subcategory":"Barber",
            "type":"Services"
        }
    ],
    "sg:phone":"+1 310 532 1610",
    "sg:postcode":"90247",
    "sg:province":"CA",
    "wof:name":"Profile",
    "wof:placetype":"venue"
},
  "geometry": {"coordinates":[-118.292121,33.893222],"type":"Point"}
}