{
  "type": "Feature",
  "properties": {
    "iso:country":"US",
    "sg:address":"9877 W. Chapman Ave",
    "sg:city":"Garden Grove",
    "sg:classifiers":[
        {
            "category":"Building & Trades",
            "subcategory":"Plumbing",
            "type":"Services"
        }
    ],
    "sg:phone":"+1 714 528 0995",
    "sg:postcode":"92841",
    "sg:province":"CA",
    "sg:website":"plumbingcontractoringardengrove....",
    "wof:name":"Adam's Plumbing",
    "wof:placetype":"venue"
},
  "geometry": {"coordinates":[-117.960905,33.788662],"type":"Point"}
}