{
  "type": "Feature",
  "properties": {
    "addr:full":"6939 E Goldcrest St Long Beach CA 90815",
    "addr:housenumber":"6939",
    "addr:postcode":"90815",
    "addr:street":"E Goldcrest St",
    "iso:country":"US",
    "sg:address":"6939 E Goldcrest St",
    "sg:city":"Long Beach",
    "sg:classifiers":[
        {
            "category":"Organizations",
            "subcategory":"Religious Organization",
            "type":"Services"
        }
    ],
    "sg:phone":"+1 562 596 5107",
    "sg:postcode":"90815",
    "sg:province":"CA",
    "sg:tags":[
        "church"
    ],
    "wof:name":"Church Of God",
    "wof:placetype":"venue"
},
  "geometry": {"coordinates":[-118.096615,33.785405],"type":"Point"}
}