{
  "type": "Feature",
  "properties": {
    "addr:full":"2111 Mission St San Francisco CA 94110",
    "addr:housenumber":"2111",
    "addr:postcode":"94110",
    "addr:street":"Mission St",
    "iso:country":"US",
    "sg:address":"2111 Mission St",
    "sg:city":"San Francisco",
    "sg:classifiers":[
        {
            "category":"Communications",
            "subcategory":"Film & Video Production",
            "type":"Services"
        }
    ],
    "sg:phone":"+1 415 252 9065",
    "sg:postcode":"94110",
    "sg:province":"CA",
    "sg:tags":[
        "taping"
    ],
    "wof:name":"Sodasoap Productions",
    "wof:placetype":"venue"
},
  "geometry": {"coordinates":[-122.419411,37.763182],"type":"Point"}
}