{
  "type": "Feature",
  "properties": {
    "addr:full":"2302 Bridgeway Sausalito CA 94965",
    "addr:housenumber":"2302",
    "addr:postcode":"94965",
    "addr:street":"Bridgeway",
    "iso:country":"US",
    "sg:address":"2302 Bridgeway",
    "sg:city":"Sausalito",
    "sg:classifiers":[
        {
            "category":"Professional",
            "subcategory":"Art Services",
            "type":"Services"
        }
    ],
    "sg:phone":"+1 415 339 2232",
    "sg:postcode":"94965",
    "sg:province":"CA",
    "sg:tags":[
        "commercial",
        "design"
    ],
    "wof:name":"Leuschel Marianna-L Studio",
    "wof:placetype":"venue"
},
  "geometry": {"coordinates":[-122.498571,37.864764],"type":"Point"}
}