{
  "type": "Feature",
  "properties": {
    "addr:full":"4604 W Adams Blvd Los Angeles CA 90016",
    "addr:housenumber":"4604",
    "addr:postcode":"90016",
    "addr:street":"W Adams Blvd",
    "iso:country":"US",
    "sg:address":"4604 W Adams Blvd",
    "sg:city":"Los Angeles",
    "sg:classifiers":[
        {
            "category":"Retail",
            "subcategory":"Repair Shop",
            "type":"Services"
        }
    ],
    "sg:phone":"+1 323 733 5666",
    "sg:postcode":"90016",
    "sg:province":"CA",
    "sg:tags":[
        "upholsterer"
    ],
    "wof:name":"Reynaga Upholstery",
    "wof:placetype":"venue"
},
  "geometry": {"coordinates":[-118.341611,34.032479],"type":"Point"}
}