{
  "type": "Feature",
  "properties": {
    "addr:full":"1250 Oakmead Pkwy Ste 210 Sunnyvale CA 94085",
    "addr:housenumber":"1250",
    "addr:postcode":"94085",
    "addr:street":"Oakmead Pkwy Ste 210",
    "iso:country":"US",
    "sg:address":"1250 Oakmead Pkwy Ste 210",
    "sg:city":"Sunnyvale",
    "sg:classifiers":[
        {
            "category":"Professional",
            "subcategory":"Employment Agencies",
            "type":"Services"
        }
    ],
    "sg:phone":"+1 408 501 8852",
    "sg:postcode":"94085",
    "sg:province":"CA",
    "sg:website":"http://www.snpjobs.com",
    "wof:name":"Staffing Network Personnel",
    "wof:placetype":"venue"
},
  "geometry": {"coordinates":[-121.990138,37.386861],"type":"Point"}
}