{
  "type": "Feature",
  "properties": {
    "addr:full":"1698 River Oaks Cir Fairfield CA 94533",
    "addr:housenumber":"1698",
    "addr:postcode":"94533",
    "addr:street":"River Oaks Cir",
    "iso:country":"US",
    "sg:address":"1698 River Oaks Cir",
    "sg:city":"Fairfield",
    "sg:classifiers":[
        {
            "category":"Wholesale",
            "subcategory":"Electrical",
            "type":"Manufacturing & Wholesale Goods"
        }
    ],
    "sg:phone":"+1 707 425 1155",
    "sg:postcode":"94533",
    "sg:province":"CA",
    "sg:tags":[
        "elements",
        "electric",
        "heating"
    ],
    "wof:name":"Watlow Electric Of Sacramento",
    "wof:placetype":"venue"
},
  "geometry": {"coordinates":[-122.016139,38.29886],"type":"Point"}
}