{
  "type": "Feature",
  "properties": {
    "iso:country":"US",
    "sg:address":"951 Edgewater Blvd # M",
    "sg:city":"Foster City",
    "sg:classifiers":[
        {
            "category":"Professional",
            "subcategory":"Employment Agencies",
            "type":"Services"
        }
    ],
    "sg:phone":"+1 650 572 1744",
    "sg:postcode":"94404",
    "sg:province":"CA",
    "wof:name":"Foster City Personnel Agency",
    "wof:placetype":"venue"
},
  "geometry": {"coordinates":[-122.272003,37.544498],"type":"Point"}
}