{
  "type": "Feature",
  "properties": {
    "addr:full":"6145 Sunrise Mall Citrus Heights CA 95610",
    "addr:housenumber":"6145",
    "addr:postcode":"95610",
    "addr:street":"Sunrise Mall",
    "iso:country":"US",
    "sg:address":"6145 Sunrise Mall",
    "sg:city":"Citrus Heights",
    "sg:classifiers":[
        {
            "category":"Shopping",
            "subcategory":"Department Store",
            "type":"Retail Goods"
        }
    ],
    "sg:phone":"+1 916 726 3677",
    "sg:postcode":"95610",
    "sg:province":"CA",
    "sg:website":"www.christopherandbanks.com",
    "wof:name":"Christopher & Banks",
    "wof:placetype":"venue"
},
  "geometry": {"coordinates":[-121.27175200000001,38.675776],"type":"Point"}
}