{
  "type": "Feature",
  "properties": {
    "addr:full":"2895 Loma Vista Rd Ventura CA 93003",
    "addr:housenumber":"2895",
    "addr:postcode":"93003",
    "addr:street":"Loma Vista Rd",
    "iso:country":"US",
    "sg:address":"2895 Loma Vista Rd",
    "sg:city":"Ventura",
    "sg:classifiers":[
        {
            "category":"Health Services",
            "subcategory":"Health Practitioner",
            "type":"Services"
        }
    ],
    "sg:phone":"+1 805 643 4093",
    "sg:postcode":"93003",
    "sg:province":"CA",
    "sg:tags":[
        "therapist",
        "physical"
    ],
    "wof:name":"Pacific Therapy Svc",
    "wof:placetype":"venue"
},
  "geometry": {"coordinates":[-119.257608,34.275422],"type":"Point"}
}