{
  "type": "Feature",
  "properties": {
    "addr:full":"7740 Dublin Blvd Dublin CA 94568",
    "addr:housenumber":"7740",
    "addr:postcode":"94568",
    "addr:street":"Dublin Blvd",
    "iso:country":"US",
    "sg:address":"7740 Dublin Blvd",
    "sg:city":"Dublin",
    "sg:classifiers":[
        {
            "category":"Wholesale",
            "subcategory":"Machinery & Supplies",
            "type":"Manufacturing & Wholesale Goods"
        }
    ],
    "sg:phone":"+1 925 479 9161",
    "sg:postcode":"94568",
    "sg:province":"CA",
    "sg:tags":[
        "salon",
        "salons-equipment",
        "beauty"
    ],
    "wof:name":"Malys",
    "wof:placetype":"venue"
},
  "geometry": {"coordinates":[-121.931425,37.703546],"type":"Point"}
}