{
  "type": "Feature",
  "properties": {
    "iso:country":"US",
    "sg:address":"Neptune & Leucadia Blvd.",
    "sg:city":"Leucadia",
    "sg:classifiers":[
        {
            "category":"Recreation",
            "subcategory":"Water Park",
            "type":"Entertainment"
        },
        {
            "category":"Sports & Exercise",
            "subcategory":"Swimming Pool",
            "type":"Entertainment"
        }
    ],
    "sg:postcode":"92024",
    "sg:province":"CA",
    "sg:tags":[
        "beach"
    ],
    "sg:website":"www.beaconsbeach.com/",
    "wof:name":"Beacon's Beach",
    "wof:placetype":"venue"
},
  "geometry": {"coordinates":[-117.30439800000001,33.064701],"type":"Point"}
}