{
  "type": "Feature",
  "properties": {
    "iso:country":"US",
    "sg:address":"9550 Bolsa Ave",
    "sg:city":"Westminster",
    "sg:classifiers":[
        {
            "category":"Insurance",
            "subcategory":"Insurance Agent",
            "type":"Services"
        }
    ],
    "sg:phone":"+1 714 531 8450",
    "sg:postcode":"92683",
    "sg:province":"CA",
    "wof:name":"ATL Insurance Brokerage",
    "wof:placetype":"venue"
},
  "geometry": {"coordinates":[-117.961899,33.744817],"type":"Point"}
}