{
  "type": "Feature",
  "properties": {
    "iso:country":"US",
    "sg:address":"1821 Bowers Ave",
    "sg:city":"Santa Clara",
    "sg:classifiers":[
        {
            "category":"Organizations",
            "subcategory":"Religious Organization",
            "type":"Services"
        }
    ],
    "sg:phone":"+1 408 241 2375",
    "sg:postcode":"95051",
    "sg:province":"CA",
    "sg:tags":[
        "church"
    ],
    "sg:website":"www.christianchurchofsc.org",
    "wof:name":"Christian Church-Santa Clara",
    "wof:placetype":"venue"
},
  "geometry": {"coordinates":[-121.977694,37.356852],"type":"Point"}
}