{
  "type": "Feature",
  "properties": {
    "addr:full":"391 Beach Rd Burlingame CA 94010",
    "addr:housenumber":"391",
    "addr:postcode":"94010",
    "addr:street":"Beach Rd",
    "iso:country":"US",
    "sg:address":"391 Beach Rd",
    "sg:city":"Burlingame",
    "sg:classifiers":[
        {
            "category":"Building & Trades",
            "subcategory":"Construction",
            "type":"Services"
        }
    ],
    "sg:phone":"+1 650 342 5617",
    "sg:postcode":"94010",
    "sg:province":"CA",
    "sg:tags":[
        "contractor"
    ],
    "wof:name":"Wilkinson Construction",
    "wof:placetype":"venue"
},
  "geometry": {"coordinates":[-122.33607499999999,37.58827],"type":"Point"}
}