{
  "type": "Feature",
  "properties": {
    "addr:full":"150A Charcot Avenue San Jose CA 95131",
    "addr:housenumber":"150a",
    "addr:postcode":"95131",
    "addr:street":"Charcot Avenue",
    "iso:country":"US",
    "sg:address":"150A Charcot Avenue",
    "sg:city":"San Jose",
    "sg:classifiers":[
        {
            "category":"Professional",
            "subcategory":"Management & Consulting",
            "type":"Services"
        }
    ],
    "sg:postcode":"95131",
    "sg:province":"CA",
    "sg:tags":[
        "it-integration",
        "it-infrastructure",
        "it-supply-chain",
        "asset-management",
        "it-systems",
        "services",
        "custom",
        "contract",
        "solutions",
        "procurement",
        "design",
        "servers",
        "network",
        "data-storage",
        "hardware",
        "software"
    ],
    "sg:website":"http://www.mce.com/",
    "wof:name":"MCE IT Infrastructure Solutions",
    "wof:placetype":"venue"
},
  "geometry": {"coordinates":[-121.920187,37.379803],"type":"Point"}
}