{
  "type": "Feature",
  "properties": {
    "iso:country":"US",
    "sg:address":"1712 W Orangethorpe Ave",
    "sg:city":"Fullerton",
    "sg:classifiers":[
        {
            "category":"Restaurant",
            "type":"Food & Drink"
        }
    ],
    "sg:phone":"+1 714 773 1982",
    "sg:postcode":"92833",
    "sg:province":"CA",
    "wof:name":"Dairy Queen",
    "wof:placetype":"venue"
},
  "geometry": {"coordinates":[-117.95700100000001,33.859299],"type":"Point"}
}