{
  "type": "Feature",
  "properties": {
    "addr:full":"745 Agajanian Way Montebello CA 90640",
    "addr:housenumber":"745",
    "addr:postcode":"90640",
    "addr:street":"Agajanian Way",
    "iso:country":"US",
    "sg:address":"745 Agajanian Way",
    "sg:city":"Montebello",
    "sg:classifiers":[
        {
            "category":"Professional",
            "type":"Services"
        }
    ],
    "sg:phone":"+1 323 727 9542",
    "sg:postcode":"90640",
    "sg:province":"CA",
    "wof:name":"Honda Lyle Sgv",
    "wof:placetype":"venue"
},
  "geometry": {"coordinates":[-118.08671699999999,34.019973],"type":"Point"}
}