{
  "type": "Feature",
  "properties": {
    "addr:full":"5250 Philadelphia St Chino CA 91710",
    "addr:housenumber":"5250",
    "addr:postcode":"91710",
    "addr:street":"Philadelphia St",
    "iso:country":"US",
    "sg:address":"5250 Philadelphia St",
    "sg:city":"Chino",
    "sg:classifiers":[
        {
            "category":"Banks & Credit Unions",
            "subcategory":"Bank",
            "type":"Services"
        }
    ],
    "sg:phone":"+1 909 591 2071",
    "sg:postcode":"91710",
    "sg:province":"CA",
    "sg:tags":[
        "financing"
    ],
    "wof:name":"Citi Financial",
    "wof:placetype":"venue"
},
  "geometry": {"coordinates":[-117.690456,34.033669],"type":"Point"}
}