{
  "type": "Feature",
  "properties": {
    "addr:full":"5882 Newman St Cypress CA 90630",
    "addr:housenumber":"5882",
    "addr:postcode":"90630",
    "addr:street":"Newman St",
    "iso:country":"US",
    "sg:address":"5882 Newman St",
    "sg:city":"Cypress",
    "sg:classifiers":[
        {
            "category":"Professional",
            "subcategory":"Business Services",
            "type":"Services"
        }
    ],
    "sg:phone":"+1 714 827 2375",
    "sg:postcode":"90630",
    "sg:province":"CA",
    "sg:tags":[
        "drafting"
    ],
    "wof:name":"Dixon Detailing Svc",
    "wof:placetype":"venue"
},
  "geometry": {"coordinates":[-118.03294699999999,33.827972],"type":"Point"}
}