{
  "type": "Feature",
  "properties": {
    "addr:full":"23315 Elm Ave Torrance CA 90505",
    "addr:housenumber":"23315",
    "addr:postcode":"90505",
    "addr:street":"Elm Ave",
    "iso:country":"US",
    "sg:address":"23315 Elm Ave",
    "sg:city":"Torrance",
    "sg:classifiers":[
        {
            "category":"Shopping",
            "subcategory":"Beauty & Cosmetics",
            "type":"Retail Goods"
        }
    ],
    "sg:phone":"+1 310 530 8821",
    "sg:postcode":"90505",
    "sg:province":"CA",
    "sg:tags":[
        "surgical",
        "appliance"
    ],
    "wof:name":"Angel Orthopedic Technology",
    "wof:placetype":"venue"
},
  "geometry": {"coordinates":[-118.33255699999999,33.815245],"type":"Point"}
}