{
  "type": "Feature",
  "properties": {
    "iso:country":"US",
    "sg:address":"409 Rolyn Pl",
    "sg:city":"Arcadia",
    "sg:classifiers":[
        {
            "category":"Shopping",
            "subcategory":"Bicycles & Sporting Goods",
            "type":"Retail Goods"
        },
        {
            "category":"Sports & Exercise",
            "subcategory":"Swimming Pool",
            "type":"Entertainment"
        },
        {
            "category":"Building & Trades",
            "subcategory":"Construction",
            "type":"Services"
        },
        {
            "category":"Personal",
            "subcategory":"Sauna",
            "type":"Services"
        }
    ],
    "sg:phone":"+1 626 446 5256",
    "sg:postcode":"91007",
    "sg:province":"CA",
    "sg:tags":[
        "equipment",
        "supply"
    ],
    "sg:website":"http://www.rbperry.com",
    "wof:name":"Perry & Associates Contrs",
    "wof:placetype":"venue"
},
  "geometry": {"coordinates":[-118.03282,34.144062],"type":"Point"}
}