{
  "type": "Feature",
  "properties": {
    "addr:full":"346 Santa Margarita Dr San Rafael CA 94901",
    "addr:housenumber":"346",
    "addr:postcode":"94901",
    "addr:street":"Santa Margarita Dr",
    "iso:country":"US",
    "sg:address":"346 Santa Margarita Dr",
    "sg:city":"San Rafael",
    "sg:classifiers":[
        {
            "category":"Professional",
            "subcategory":"Lawyer & Legal Services",
            "type":"Services"
        }
    ],
    "sg:phone":"+1 415 491 4143",
    "sg:postcode":"94901",
    "sg:province":"CA",
    "sg:tags":[
        "attorney"
    ],
    "wof:name":"Stuart H Blecher",
    "wof:placetype":"venue"
},
  "geometry": {"coordinates":[-122.54558299999999,37.977948],"type":"Point"}
}