{
  "type": "Feature",
  "properties": {
    "iso:country":"US",
    "sg:address":"20 Mesa Oak Ln",
    "sg:city":"Danville",
    "sg:classifiers":[
        {
            "category":"Real Estate",
            "subcategory":"Real Estate Agent",
            "type":"Services"
        }
    ],
    "sg:phone":"+1 925 552 0255",
    "sg:postcode":"94506",
    "sg:province":"CA",
    "sg:website":"www.maryaspland.net",
    "wof:name":"Mary Aspland",
    "wof:placetype":"venue"
},
  "geometry": {"coordinates":[-121.934923,37.829864],"type":"Point"}
}