{
  "type": "Feature",
  "properties": {
    "addr:full":"510 N Puente Ave La Puente CA 91746",
    "addr:housenumber":"510",
    "addr:postcode":"91746",
    "addr:street":"N Puente Ave",
    "iso:country":"US",
    "sg:address":"510 N Puente Ave",
    "sg:city":"La Puente",
    "sg:classifiers":[
        {
            "category":"Arts & Performance",
            "subcategory":"Theater",
            "type":"Entertainment"
        }
    ],
    "sg:phone":"+1 626 333 9962",
    "sg:postcode":"91746",
    "sg:province":"CA",
    "sg:tags":[
        "entertainer"
    ],
    "wof:name":"A V Entertainment Inc",
    "wof:placetype":"venue"
},
  "geometry": {"coordinates":[-117.98235099999999,34.049921],"type":"Point"}
}