{
  "type": "Feature",
  "properties": {
    "addr:full":"1419 Superior Avenue Newport Beach CA 92663",
    "addr:housenumber":"1419",
    "addr:postcode":"92663",
    "addr:street":"Superior Avenue",
    "iso:country":"US",
    "sg:address":"1419 Superior Avenue",
    "sg:city":"Newport Beach",
    "sg:classifiers":[
        {
            "category":"Health Services",
            "subcategory":"Dentist",
            "type":"Services"
        }
    ],
    "sg:phone":"+1 949 646 4801",
    "sg:postcode":"92663",
    "sg:province":"CA",
    "wof:name":"Henderson Brian T DDS",
    "wof:placetype":"venue"
},
  "geometry": {"coordinates":[-117.92379099999999,33.625848],"type":"Point"}
}