{
  "type": "Feature",
  "properties": {
    "iso:country":"US",
    "sg:address":"95 S Market St",
    "sg:city":"San Jose",
    "sg:classifiers":[
        {
            "category":"Government",
            "subcategory":"Office",
            "type":"Public Place"
        }
    ],
    "sg:phone":"+1 408 971 9170",
    "sg:postcode":"95113",
    "sg:province":"CA",
    "sg:tags":[
        "federal",
        "international",
        "affairs"
    ],
    "wof:name":"Italian Vice Consulate",
    "wof:placetype":"venue"
},
  "geometry": {"coordinates":[-121.891392,37.334472],"type":"Point"}
}