{
  "type": "Feature",
  "properties": {
    "iso:country":"US",
    "sg:address":"8761 Lankershim Blvd",
    "sg:city":"Sun Valley",
    "sg:classifiers":[
        {
            "category":"Home & Garden",
            "subcategory":"Building Materials",
            "type":"Retail Goods"
        }
    ],
    "sg:phone":"+1 818 767 5465",
    "sg:postcode":"91352",
    "sg:province":"CA",
    "sg:tags":[
        "hinge"
    ],
    "wof:name":"Andre's Hinge & Tool & Dye Co",
    "wof:placetype":"venue"
},
  "geometry": {"coordinates":[-118.387846,34.230358],"type":"Point"}
}