{
  "type": "Feature",
  "properties": {
    "addr:full":"3625 Pomo Ln Modesto CA 95356",
    "addr:housenumber":"3625",
    "addr:postcode":"ca 95356",
    "addr:street":"Pomo Ln",
    "iso:country":"US",
    "sg:address":"3625 Pomo Ln",
    "sg:city":"Modesto",
    "sg:classifiers":[
        {
            "category":"Shopping",
            "subcategory":"Shoes",
            "type":"Retail Goods"
        }
    ],
    "sg:phone":"+1 209 324 0515",
    "sg:postcode":"95356",
    "sg:province":"CA",
    "wof:name":"Payless Window Supply",
    "wof:placetype":"venue"
},
  "geometry": {"coordinates":[-121.025839,37.692088],"type":"Point"}
}