{
  "type": "Feature",
  "properties": {
    "iso:country":"US",
    "sg:address":"5911 Cerritos Ave",
    "sg:city":"Cypress",
    "sg:classifiers":[
        {
            "category":"Banks & Credit Unions",
            "subcategory":"Bank",
            "type":"Services"
        }
    ],
    "sg:phone":"+1 714 527 5103",
    "sg:postcode":"90630",
    "sg:province":"CA",
    "wof:name":"Reyes David",
    "wof:placetype":"venue"
},
  "geometry": {"coordinates":[-118.029999,33.809898],"type":"Point"}
}