{
  "type": "Feature",
  "properties": {
    "addr:full":"40807 State Hwy 41 Oakhurst CA 93644",
    "addr:housenumber":"40807",
    "addr:postcode":"93644",
    "addr:street":"State Hwy 41",
    "iso:country":"US",
    "sg:address":"40807 State Hwy 41",
    "sg:city":"Oakhurst",
    "sg:classifiers":[
        {
            "category":"Bars & Pubs",
            "type":"Food & Drink"
        }
    ],
    "sg:phone":"+1 559 683 6667",
    "sg:postcode":"93644",
    "sg:province":"CA",
    "wof:name":"Oak Room",
    "wof:placetype":"venue"
},
  "geometry": {"coordinates":[-119.644071,37.339181],"type":"Point"}
}