{
  "type": "Feature",
  "properties": {
    "iso:country":"US",
    "sg:address":"146 E Alondra Blvd",
    "sg:city":"Gardena",
    "sg:classifiers":[
        {
            "category":"Home & Garden",
            "subcategory":"Carpets & Floor Coverings",
            "type":"Retail Goods"
        }
    ],
    "sg:phone":"+1 310 516 9272",
    "sg:postcode":"90248",
    "sg:province":"CA",
    "sg:tags":[
        "rug",
        "carpeting"
    ],
    "sg:website":"www.hmcarpet.net",
    "wof:name":"H M Carpet",
    "wof:placetype":"venue"
},
  "geometry": {"coordinates":[-118.274002,33.885502],"type":"Point"}
}