{
  "type": "Feature",
  "properties": {
    "addr:full":"2401 E Willow St Signal Hill CA 90755",
    "addr:housenumber":"2401",
    "addr:postcode":"90755",
    "addr:street":"E Willow St",
    "iso:country":"US",
    "sg:address":"2401 E Willow St",
    "sg:city":"Signal Hill",
    "sg:classifiers":[
        {
            "category":"Wholesale",
            "subcategory":"Durable Goods & Equipment",
            "type":"Manufacturing & Wholesale Goods"
        }
    ],
    "sg:phone":"+1 562 427 2775",
    "sg:postcode":"90755",
    "sg:province":"CA",
    "sg:tags":[
        "importer"
    ],
    "sg:website":"www.sassafety.com",
    "wof:name":"SAS Safety Co",
    "wof:placetype":"venue"
},
  "geometry": {"coordinates":[-118.162364,33.80433],"type":"Point"}
}