{
  "type": "Feature",
  "properties": {
    "iso:country":"US",
    "sg:address":"40232 Junction Dr",
    "sg:city":"Oakhurst",
    "sg:classifiers":[
        {
            "category":"Health Services",
            "subcategory":"Clinic",
            "type":"Services"
        }
    ],
    "sg:phone":"+1 559 658 6456",
    "sg:postcode":"93644",
    "sg:province":"CA",
    "sg:tags":[
        "home",
        "care"
    ],
    "wof:name":"Saint Agnes Hospital",
    "wof:placetype":"venue"
},
  "geometry": {"coordinates":[-119.65937,37.336442],"type":"Point"}
}