{
  "type": "Feature",
  "properties": {
    "iso:country":"US",
    "sg:address":"8797 Irvine Center Dr",
    "sg:city":"Irvine",
    "sg:classifiers":[
        {
            "category":"Retail",
            "subcategory":"Auto Repair",
            "type":"Services"
        }
    ],
    "sg:phone":"+1 949 453 0555",
    "sg:postcode":"92618",
    "sg:province":"CA",
    "sg:tags":[
        "repairing",
        "automobile"
    ],
    "wof:name":"Auto Craft Mercedes & Bmw",
    "wof:placetype":"venue"
},
  "geometry": {"coordinates":[-117.750362,33.65965],"type":"Point"}
}