{
  "type": "Feature",
  "properties": {
    "iso:country":"US",
    "sg:address":"8837 Airport Rd",
    "sg:city":"Redding",
    "sg:classifiers":[
        {
            "category":"Manufacturing",
            "subcategory":"Buildings",
            "type":"Manufacturing & Wholesale Goods"
        },
        {
            "category":"Home & Garden",
            "subcategory":"Home Furnishings",
            "type":"Retail Goods"
        },
        {
            "category":"Professional",
            "subcategory":"Business Services",
            "type":"Services"
        },
        {
            "category":"Building & Trades",
            "subcategory":"Construction",
            "type":"Services"
        },
        {
            "category":"Real Estate",
            "subcategory":"Architect",
            "type":"Services"
        }
    ],
    "sg:phone":"+1 530 222 1427",
    "sg:postcode":"96002",
    "sg:province":"CA",
    "sg:tags":[
        "designer",
        "residential",
        "builder",
        "drafting",
        "planning",
        "design",
        "contractor"
    ],
    "sg:website":"http://www.dezign4u.com",
    "wof:name":"Dezign Drafting & Plotting",
    "wof:placetype":"venue"
},
  "geometry": {"coordinates":[-122.302836,40.543963],"type":"Point"}
}