{
  "type": "Feature",
  "properties": {
    "iso:country":"US",
    "sg:address":"2900 Thurgood Marshall Dr",
    "sg:city":"Oxnard",
    "sg:classifiers":[
        {
            "category":"Education",
            "subcategory":"School",
            "type":"Public Place"
        }
    ],
    "sg:phone":"+1 805 983 7155",
    "sg:postcode":"93036",
    "sg:province":"CA",
    "wof:name":"Thurgood Marshall Elem School",
    "wof:placetype":"venue"
},
  "geometry": {"coordinates":[-119.20715300000001,34.222019],"type":"Point"}
}