{
  "type": "Feature",
  "properties": {
    "iso:country":"US",
    "sg:address":"1214 Apollo Way",
    "sg:city":"Sunnyvale",
    "sg:classifiers":[
        {
            "category":"Communications",
            "type":"Services"
        },
        {
            "category":"Professional",
            "subcategory":"Computer Services",
            "type":"Services"
        }
    ],
    "sg:phone":"+1 408 737 1600",
    "sg:postcode":"94086",
    "sg:province":"CA",
    "sg:tags":[
        "communication",
        "datum",
        "system"
    ],
    "wof:name":"A E S Networks Inc",
    "wof:placetype":"venue"
},
  "geometry": {"coordinates":[-121.994075,37.378328],"type":"Point"}
}