{
  "type": "Feature",
  "properties": {
    "addr:full":"264 N Highland Springs Ave Banning CA 92220",
    "addr:housenumber":"264",
    "addr:postcode":"92220",
    "addr:street":"N Highland Springs Ave",
    "iso:country":"US",
    "sg:address":"264 N Highland Springs Ave",
    "sg:city":"Banning",
    "sg:classifiers":[
        {
            "category":"Health Services",
            "subcategory":"Doctor",
            "type":"Services"
        }
    ],
    "sg:phone":"+1 951 922 6644",
    "sg:postcode":"92220",
    "sg:province":"CA",
    "sg:tags":[
        "physician",
        "surgeon"
    ],
    "wof:name":"Gustafson Orthopaedics Inc.",
    "wof:placetype":"venue"
},
  "geometry": {"coordinates":[-116.946894,33.930374],"type":"Point"}
}