{
  "type": "Feature",
  "properties": {
    "addr:full":"1031 25th St San Francisco CA 94107",
    "addr:housenumber":"1031",
    "addr:postcode":"94107",
    "addr:street":"25Th St",
    "iso:country":"US",
    "sg:address":"1031 25th St",
    "sg:city":"San Francisco",
    "sg:classifiers":[
        {
            "category":"Freight",
            "type":"Transportation"
        }
    ],
    "sg:phone":"+1 415 826 3400",
    "sg:postcode":"94107",
    "sg:province":"CA",
    "sg:tags":[
        "crating",
        "custom"
    ],
    "wof:name":"General Crating Inc",
    "wof:placetype":"venue"
},
  "geometry": {"coordinates":[-122.389488,37.752664],"type":"Point"}
}