{
  "type": "Feature",
  "properties": {
    "iso:country":"US",
    "sg:address":"17716 Pesante Rd",
    "sg:city":"Salinas",
    "sg:classifiers":[
        {
            "category":"Organizations",
            "subcategory":"Religious Organization",
            "type":"Services"
        }
    ],
    "sg:phone":"+1 831 663 4661",
    "sg:postcode":"93907",
    "sg:province":"CA",
    "sg:tags":[
        "church"
    ],
    "wof:name":"First Baptist Church-Prunedale",
    "wof:placetype":"venue"
},
  "geometry": {"coordinates":[-121.66318,36.776642],"type":"Point"}
}