{
  "type": "Feature",
  "properties": {
    "iso:country":"US",
    "sg:address":"22140 State Hwy 18",
    "sg:city":"Apple Valley",
    "sg:classifiers":[
        {
            "category":"Home & Garden",
            "subcategory":"Building Materials",
            "type":"Retail Goods"
        }
    ],
    "sg:phone":"+1 760 247 3667",
    "sg:postcode":"92307",
    "sg:province":"CA",
    "sg:tags":[
        "door"
    ],
    "wof:name":"Barr Lumber Co",
    "wof:placetype":"venue"
},
  "geometry": {"coordinates":[-117.181213,34.500664],"type":"Point"}
}