{
  "type": "Feature",
  "properties": {
    "addr:full":"8864 Greenback Ln Ste C Orangevale CA 95662",
    "addr:housenumber":"8864",
    "addr:postcode":"95662",
    "addr:street":"Greenback Ln Ste C",
    "iso:country":"US",
    "sg:address":"8864 Greenback Ln Ste C",
    "sg:city":"Orangevale",
    "sg:classifiers":[
        {
            "category":"Shopping",
            "subcategory":"Beauty & Cosmetics",
            "type":"Retail Goods"
        }
    ],
    "sg:phone":"+1 916 989 5887",
    "sg:postcode":"95662",
    "sg:province":"CA",
    "sg:tags":[
        "supply"
    ],
    "wof:name":"Eccentrix For Hair",
    "wof:placetype":"venue"
},
  "geometry": {"coordinates":[-121.227412,38.677908],"type":"Point"}
}