{
  "type": "Feature",
  "properties": {
    "iso:country":"US",
    "sg:address":"3864 1st Ave",
    "sg:city":"San Diego",
    "sg:classifiers":[
        {
            "category":"Retail",
            "subcategory":"Auto Repair",
            "type":"Services"
        }
    ],
    "sg:phone":"+1 619 297 4059",
    "sg:postcode":"92103",
    "sg:province":"CA",
    "sg:tags":[
        "repairing",
        "automobile"
    ],
    "wof:name":"Hillcrest Smog Test & Auto Rpr",
    "wof:placetype":"venue"
},
  "geometry": {"coordinates":[-117.163962,32.747383],"type":"Point"}
}