{
  "type": "Feature",
  "properties": {
    "addr:full":"1201 8th St San Francisco CA 94107",
    "addr:housenumber":"1201",
    "addr:postcode":"94107",
    "addr:street":"8Th St",
    "iso:country":"US",
    "sg:address":"1201 8th St",
    "sg:city":"San Francisco",
    "sg:classifiers":[
        {
            "category":"Coffee & Tea",
            "type":"Food & Drink"
        },
        {
            "category":"Restaurant",
            "type":"Food & Drink"
        },
        {
            "category":"Retail",
            "subcategory":"Event Space",
            "type":"Services"
        }
    ],
    "sg:phone":"+1 415 437 2947",
    "sg:postcode":"94107",
    "sg:province":"CA",
    "sg:tags":[
        "breakfast",
        "venue",
        "brunch"
    ],
    "sg:website":"www.axis-cafe.com",
    "wof:name":"Axis Caf? and Gallery",
    "wof:placetype":"venue"
},
  "geometry": {"coordinates":[-122.39966699999999,37.766695],"type":"Point"}
}