{
  "type": "Feature",
  "properties": {
    "addr:full":"447 Great Mall Dr Milpitas CA 95035",
    "addr:housenumber":"447",
    "addr:postcode":"95035",
    "addr:street":"Great Mall Dr",
    "iso:country":"US",
    "sg:address":"447 Great Mall Dr",
    "sg:city":"Milpitas",
    "sg:classifiers":[
        {
            "category":"Coffee & Tea",
            "type":"Food & Drink"
        }
    ],
    "sg:phone":"+1 408 719 0324",
    "sg:postcode":"95035",
    "sg:province":"CA",
    "sg:website":"www.starbucks.com",
    "wof:name":"Starbucks",
    "wof:placetype":"venue"
},
  "geometry": {"coordinates":[-121.897003,37.412498],"type":"Point"}
}