{
  "type": "Feature",
  "properties": {
    "iso:country":"US",
    "sg:address":"3249 Scott St",
    "sg:city":"San Francisco",
    "sg:classifiers":[
        {
            "category":"Food & Beverages",
            "subcategory":"Candy",
            "type":"Retail Goods"
        },
        {
            "category":"Bakery",
            "type":"Food & Drink"
        }
    ],
    "sg:phone":"+1 415 563 2253",
    "sg:postcode":"94123",
    "sg:province":"CA",
    "sg:tags":[
        "dessert"
    ],
    "sg:website":"www.karascupcakes.com",
    "wof:name":"Kara's Cupcakes",
    "wof:placetype":"venue"
},
  "geometry": {"coordinates":[-122.441098,37.799757],"type":"Point"}
}