{
  "type": "Feature",
  "properties": {
    "addr:full":"312 Los Cerritos Mall Cerritos CA 90703",
    "addr:housenumber":"312",
    "addr:postcode":"ca 90703",
    "addr:street":"Los Cerritos Mall",
    "iso:country":"US",
    "sg:address":"312 Los Cerritos Mall",
    "sg:city":"Cerritos",
    "sg:classifiers":[
        {
            "category":"Shopping",
            "subcategory":"Shoes",
            "type":"Retail Goods"
        }
    ],
    "sg:phone":"+1 562 402 5962",
    "sg:postcode":"90703",
    "sg:province":"CA",
    "wof:name":"Easy Spirit",
    "wof:placetype":"venue"
},
  "geometry": {"coordinates":[-118.09321199999999,33.85944],"type":"Point"}
}