{
  "type": "Feature",
  "properties": {
    "addr:full":"1955 Lucile Ave Stockton CA 95209",
    "addr:housenumber":"1955",
    "addr:postcode":"95209",
    "addr:street":"Lucile Ave",
    "iso:country":"US",
    "sg:address":"1955 Lucile Ave",
    "sg:city":"Stockton",
    "sg:classifiers":[
        {
            "category":"Shopping",
            "type":"Retail Goods"
        }
    ],
    "sg:phone":"+1 209 478 4125",
    "sg:postcode":"95209",
    "sg:province":"CA",
    "sg:tags":[
        "merchandise"
    ],
    "wof:name":"Sedona Scents",
    "wof:placetype":"venue"
},
  "geometry": {"coordinates":[-121.337857,38.033459],"type":"Point"}
}