{
  "type": "Feature",
  "properties": {
    "iso:country":"US",
    "sg:address":"301 E Charter Way",
    "sg:city":"Stockton",
    "sg:classifiers":[
        {
            "category":"Bars & Pubs",
            "type":"Food & Drink"
        }
    ],
    "sg:phone":"+1 209 937 0667",
    "sg:postcode":"95206",
    "sg:province":"CA",
    "wof:name":"Dos De Oro Bar",
    "wof:placetype":"venue"
},
  "geometry": {"coordinates":[-121.282775,37.939499],"type":"Point"}
}