{
  "type": "Feature",
  "properties": {
    "addr:full":"9300 Cherry Ave Fontana CA 92335",
    "addr:housenumber":"9300",
    "addr:postcode":"92335",
    "addr:street":"Cherry Ave",
    "iso:country":"US",
    "sg:address":"9300 Cherry Ave",
    "sg:city":"Fontana",
    "sg:classifiers":[
        {
            "category":"Professional",
            "type":"Services"
        }
    ],
    "sg:phone":"+1 909 427 1354",
    "sg:postcode":"92335",
    "sg:province":"CA",
    "wof:name":"Fernandez Racing",
    "wof:placetype":"venue"
},
  "geometry": {"coordinates":[-117.488849,34.083493],"type":"Point"}
}