{
  "type": "Feature",
  "properties": {
    "iso:country":"US",
    "sg:address":"12900 Garden Grove Blvd",
    "sg:city":"Garden Grove",
    "sg:classifiers":[
        {
            "category":"Social Services",
            "type":"Services"
        }
    ],
    "sg:phone":"+1 714 530 5360",
    "sg:postcode":"92843",
    "sg:province":"CA",
    "sg:tags":[
        "counselor",
        "marriage",
        "family"
    ],
    "wof:name":"Carlson & Carpenter Assoc",
    "wof:placetype":"venue"
},
  "geometry": {"coordinates":[-117.907349,33.774351],"type":"Point"}
}