{
  "type": "Feature",
  "properties": {
    "iso:country":"US",
    "sg:address":"34570 Linda Rosea Rd",
    "sg:city":"Temecula",
    "sg:classifiers":[
        {
            "category":"Building & Trades",
            "subcategory":"Electrical",
            "type":"Services"
        }
    ],
    "sg:phone":"+1 951 303 8108",
    "sg:postcode":"92592",
    "sg:province":"CA",
    "sg:tags":[
        "electrician",
        "contractor"
    ],
    "wof:name":"Derrick Hooks Electric",
    "wof:placetype":"venue"
},
  "geometry": {"coordinates":[-117.05789900000001,33.505028],"type":"Point"}
}