{
  "type": "Feature",
  "properties": {
    "iso:country":"US",
    "sg:address":"926 Broadway",
    "sg:city":"Santa Monica",
    "sg:classifiers":[
        {
            "category":"Retail",
            "subcategory":"Laundry & Dry Cleaning",
            "type":"Services"
        }
    ],
    "sg:phone":"+1 310 394 4800",
    "sg:postcode":"90401",
    "sg:province":"CA",
    "sg:tags":[
        "cleaners"
    ],
    "wof:name":"Broadway Cleaners",
    "wof:placetype":"venue"
},
  "geometry": {"coordinates":[-118.488521,34.019043],"type":"Point"}
}