{
  "type": "Feature",
  "properties": {
    "addr:full":"1550 Bancroft Ave San Francisco CA 94124",
    "addr:housenumber":"1550",
    "addr:postcode":"94124",
    "addr:street":"Bancroft Ave",
    "iso:country":"US",
    "sg:address":"1550 Bancroft Ave",
    "sg:city":"San Francisco",
    "sg:classifiers":[
        {
            "category":"Wholesale",
            "subcategory":"Seafood",
            "type":"Manufacturing & Wholesale Goods"
        }
    ],
    "sg:phone":"+1 415 822 6300",
    "sg:postcode":"94124",
    "sg:province":"CA",
    "wof:name":"Charlie Seafood",
    "wof:placetype":"venue"
},
  "geometry": {"coordinates":[-122.391994,37.725124],"type":"Point"}
}