{
  "type": "Feature",
  "properties": {
    "iso:country":"US",
    "sg:address":"9000 Woodman Ave",
    "sg:city":"Arleta",
    "sg:classifiers":[
        {
            "category":"Fast Food",
            "type":"Food & Drink"
        },
        {
            "category":"Restaurant",
            "type":"Food & Drink"
        }
    ],
    "sg:phone":"+1 818 893 6634",
    "sg:postcode":"91331",
    "sg:province":"CA",
    "sg:tags":[
        "american",
        "take",
        "chicken"
    ],
    "sg:website":"http://www.popeyes.com",
    "wof:name":"Popeyes Chicken & Biscuits",
    "wof:placetype":"venue"
},
  "geometry": {"coordinates":[-118.43866,34.232929],"type":"Point"}
}