{
  "type": "Feature",
  "properties": {
    "addr:full":"25060 Madison Ave Murrieta CA 92562",
    "addr:housenumber":"25060",
    "addr:postcode":"92562",
    "addr:street":"Madison Ave",
    "iso:country":"US",
    "sg:address":"25060 Madison Ave",
    "sg:city":"Murrieta",
    "sg:classifiers":[
        {
            "category":"Wholesale",
            "subcategory":"Groceries",
            "type":"Manufacturing & Wholesale Goods"
        }
    ],
    "sg:phone":"+1 951 698 8495",
    "sg:postcode":"92562",
    "sg:province":"CA",
    "sg:tags":[
        "grocer"
    ],
    "wof:name":"Smart & Final",
    "wof:placetype":"venue"
},
  "geometry": {"coordinates":[-117.198981,33.556145],"type":"Point"}
}