{
  "type": "Feature",
  "properties": {
    "addr:full":"4378 Planet Cir Union City CA 94587",
    "addr:housenumber":"4378",
    "addr:postcode":"94587",
    "addr:street":"Planet Cir",
    "iso:country":"US",
    "sg:address":"4378 Planet Cir",
    "sg:city":"Union City",
    "sg:classifiers":[
        {
            "category":"Professional",
            "type":"Services"
        }
    ],
    "sg:phone":"+1 510 324 2121",
    "sg:postcode":"94587",
    "sg:province":"CA",
    "wof:name":"S Singh",
    "wof:placetype":"venue"
},
  "geometry": {"coordinates":[-122.07219600000001,37.585546],"type":"Point"}
}