{
  "type": "Feature",
  "properties": {
    "addr:full":"14344 S Bethel Ave Kingsburg CA 93631",
    "addr:housenumber":"14344",
    "addr:postcode":"93631",
    "addr:street":"S Bethel Ave",
    "iso:country":"US",
    "sg:address":"14344 S Bethel Ave",
    "sg:city":"Kingsburg",
    "sg:classifiers":[
        {
            "category":"Wholesale",
            "subcategory":"Farm Supplies",
            "type":"Manufacturing & Wholesale Goods"
        }
    ],
    "sg:phone":"+1 559 897 7012",
    "sg:postcode":"93631",
    "sg:province":"CA",
    "sg:tags":[
        "equipment"
    ],
    "sg:website":"http://www.oxbocorp.com",
    "wof:name":"Oxbo International Corporation",
    "wof:placetype":"venue"
},
  "geometry": {"coordinates":[-119.57531,36.526672],"type":"Point"}
}