{
  "type": "Feature",
  "properties": {
    "addr:full":"1435 Huntington Ave S San Francisco CA 94066",
    "addr:housenumber":"1435",
    "addr:postcode":"94066",
    "addr:street":"Huntington Ave S",
    "iso:country":"US",
    "sg:address":"1435 Huntington Ave",
    "sg:city":"S San Francisco",
    "sg:classifiers":[
        {
            "category":"Professional",
            "subcategory":"Lawyer & Legal Services",
            "type":"Services"
        }
    ],
    "sg:phone":"+1 650 737 7968",
    "sg:postcode":"94066",
    "sg:province":"CA",
    "sg:tags":[
        "attorney"
    ],
    "wof:name":"George A Manus Law Offices",
    "wof:placetype":"venue"
},
  "geometry": {"coordinates":[-122.420755,37.642945],"type":"Point"}
}