{
  "type": "Feature",
  "properties": {
    "iso:country":"US",
    "sg:address":"460 Curtola Pkwy",
    "sg:city":"Vallejo",
    "sg:classifiers":[
        {
            "category":"Utilities",
            "subcategory":"Cable",
            "type":"Services"
        }
    ],
    "sg:phone":"+1 707 552 2505",
    "sg:postcode":"94590",
    "sg:province":"CA",
    "sg:tags":[
        "television"
    ],
    "wof:name":"Comcast Cable Holdings LLC",
    "wof:placetype":"venue"
},
  "geometry": {"coordinates":[-122.252574,38.097222],"type":"Point"}
}