{
  "type": "Feature",
  "properties": {
    "iso:country":"US",
    "sg:address":"19101 Beach Blvd",
    "sg:city":"Huntington Beach",
    "sg:classifiers":[
        {
            "category":"Personal",
            "subcategory":"Tanning Parlor",
            "type":"Services"
        }
    ],
    "sg:phone":"+1 714 375 5999",
    "sg:postcode":"92648",
    "sg:province":"CA",
    "sg:website":"www.ucatan.com",
    "wof:name":"U-CA-TAN Tanning Salons",
    "wof:placetype":"venue"
},
  "geometry": {"coordinates":[-117.98881799999999,33.684933],"type":"Point"}
}