{
  "type": "Feature",
  "properties": {
    "addr:full":"12925 Ave of the Giants Myers Flat CA 95554",
    "addr:housenumber":"12925;flat ca",
    "addr:postcode":"95554",
    "addr:street":"Ave Of The",
    "iso:country":"US",
    "sg:address":"12925 Ave of the Giants",
    "sg:city":"Myers Flat",
    "sg:classifiers":[
        {
            "category":"Farming",
            "subcategory":"Vineyard",
            "type":"Manufacturing & Wholesale Goods"
        }
    ],
    "sg:phone":"+1 707 943 3500",
    "sg:postcode":"95554",
    "sg:province":"CA",
    "wof:name":"Vineyard",
    "wof:placetype":"venue"
},
  "geometry": {"coordinates":[-123.88878,40.282379],"type":"Point"}
}