{
  "type": "Feature",
  "properties": {
    "iso:country":"US",
    "sg:address":"18637 Jurupa Ave",
    "sg:city":"Bloomington",
    "sg:classifiers":[
        {
            "category":"Freight",
            "type":"Transportation"
        }
    ],
    "sg:phone":"+1 909 877 8447",
    "sg:postcode":"92316",
    "sg:province":"CA",
    "sg:tags":[
        "local",
        "storage",
        "trucking"
    ],
    "wof:name":"Goff Trucking",
    "wof:placetype":"venue"
},
  "geometry": {"coordinates":[-117.397136,34.048512],"type":"Point"}
}