{
  "type": "Feature",
  "properties": {
    "iso:country":"US",
    "sg:address":"22177 Mission Blvd",
    "sg:city":"Hayward",
    "sg:classifiers":[
        {
            "category":"Autos & Motor Vehicles",
            "subcategory":"Auto Supplies",
            "type":"Retail Goods"
        }
    ],
    "sg:phone":"+1 510 583 7467",
    "sg:postcode":"94541",
    "sg:province":"CA",
    "sg:tags":[
        "tire"
    ],
    "wof:name":"East Bayz Customs",
    "wof:placetype":"venue"
},
  "geometry": {"coordinates":[-122.089995,37.676482],"type":"Point"}
}