{
  "type": "Feature",
  "properties": {
    "addr:full":"2781 Calloway Dr Bakersfield CA 93312",
    "addr:housenumber":"2781",
    "addr:postcode":"93312",
    "addr:street":"Calloway Dr",
    "iso:country":"US",
    "sg:address":"2781 Calloway Dr",
    "sg:city":"Bakersfield",
    "sg:classifiers":[
        {
            "category":"Personal",
            "subcategory":"Beauty Salon",
            "type":"Services"
        }
    ],
    "sg:phone":"+1 661 588 3317",
    "sg:postcode":"93312",
    "sg:province":"CA",
    "sg:tags":[
        "nail",
        "manicuring"
    ],
    "wof:name":"Princess Nails",
    "wof:placetype":"venue"
},
  "geometry": {"coordinates":[-119.10993999999999,35.386106],"type":"Point"}
}