{
  "type": "Feature",
  "properties": {
    "addr:full":"2209 Chestnut St San Francisco CA 94123",
    "addr:housenumber":"2209",
    "addr:postcode":"94123",
    "addr:street":"Chestnut St",
    "iso:country":"US",
    "sg:address":"2209 Chestnut St",
    "sg:city":"San Francisco",
    "sg:classifiers":[
        {
            "category":"Personal",
            "subcategory":"Day Spa",
            "type":"Services"
        }
    ],
    "sg:phone":"+1 415 749 6414",
    "sg:postcode":"94123",
    "sg:province":"CA",
    "wof:name":"Spa Etc.",
    "wof:placetype":"venue"
},
  "geometry": {"coordinates":[-122.43981100000001,37.800234],"type":"Point"}
}