{
  "type": "Feature",
  "properties": {
    "addr:full":"10510 Victory Blvd North Hollywood CA 91606",
    "addr:housenumber":"10510",
    "addr:postcode":"91606",
    "addr:street":"Victory Blvd",
    "iso:country":"US",
    "sg:address":"10510 Victory Blvd",
    "sg:city":"North Hollywood",
    "sg:classifiers":[
        {
            "category":"Autos & Motor Vehicles",
            "subcategory":"Automobile Sales",
            "type":"Retail Goods"
        }
    ],
    "sg:phone":"+1 818 487 8070",
    "sg:postcode":"91606",
    "sg:province":"CA",
    "sg:tags":[
        "limo"
    ],
    "wof:name":"Super Sedan Ride Inc",
    "wof:placetype":"venue"
},
  "geometry": {"coordinates":[-118.36000900000001,34.184776],"type":"Point"}
}