{
  "type": "Feature",
  "properties": {
    "addr:full":"2510 Grant Ave Redondo Beach CA 90278",
    "addr:housenumber":"2510",
    "addr:postcode":"90278",
    "addr:street":"Grant Ave",
    "iso:country":"US",
    "sg:address":"2510 Grant Ave",
    "sg:city":"Redondo Beach",
    "sg:classifiers":[
        {
            "category":"Building & Trades",
            "subcategory":"Construction",
            "type":"Services"
        }
    ],
    "sg:phone":"+1 310 324 9764",
    "sg:postcode":"90278",
    "sg:province":"CA",
    "sg:tags":[
        "resurfacing",
        "laying",
        "refinishing",
        "floor"
    ],
    "wof:name":"Victor Rodas Wood Floors",
    "wof:placetype":"venue"
},
  "geometry": {"coordinates":[-118.36445999999999,33.868958],"type":"Point"}
}