{
  "type": "Feature",
  "properties": {
    "iso:country":"US",
    "sg:address":"910 S Via Rodeo",
    "sg:city":"Placentia",
    "sg:classifiers":[
        {
            "category":"Sports & Exercise",
            "subcategory":"Gym",
            "type":"Entertainment"
        }
    ],
    "sg:phone":"+1 714 996 2229",
    "sg:postcode":"92870",
    "sg:province":"CA",
    "sg:tags":[
        "trainer"
    ],
    "wof:name":"Fitness Innovative Technologies",
    "wof:placetype":"venue"
},
  "geometry": {"coordinates":[-117.82033699999999,33.863049],"type":"Point"}
}