{
  "type": "Feature",
  "properties": {
    "addr:full":"2560 Wyandotte St Mountain View CA 94043",
    "addr:housenumber":"2560",
    "addr:postcode":"94043",
    "addr:street":"Wyandotte St",
    "iso:country":"US",
    "sg:address":"2560 Wyandotte St",
    "sg:city":"Mountain View",
    "sg:classifiers":[
        {
            "category":"Building & Trades",
            "subcategory":"Plumbing",
            "type":"Services"
        }
    ],
    "sg:phone":"+1 650 948 4727",
    "sg:postcode":"94043",
    "sg:province":"CA",
    "sg:tags":[
        "system",
        "radiant",
        "cooling",
        "heating"
    ],
    "wof:name":"Bonanza Heating & Air Cond",
    "wof:placetype":"venue"
},
  "geometry": {"coordinates":[-122.10014200000001,37.417001],"type":"Point"}
}