{
  "type": "Feature",
  "properties": {
    "iso:country":"US",
    "sg:address":"5311 Topanga Canyon Blvd Ste 201",
    "sg:city":"Woodland Hills",
    "sg:classifiers":[
        {
            "category":"Professional",
            "subcategory":"Accounting & Tax Preparation",
            "type":"Services"
        },
        {
            "category":"Real Estate",
            "subcategory":"Real Estate Services",
            "type":"Services"
        }
    ],
    "sg:phone":"+1 818 884 7285",
    "sg:postcode":"91364",
    "sg:province":"CA",
    "sg:tags":[
        "management",
        "accountant",
        "property"
    ],
    "wof:name":"Paul Dubrow, CPA",
    "wof:placetype":"venue"
},
  "geometry": {"coordinates":[-118.606267,34.166313],"type":"Point"}
}