{
  "type": "Feature",
  "properties": {
    "addr:full":"2033 S Broadway Santa Maria CA 93454",
    "addr:housenumber":"2033",
    "addr:postcode":"93454",
    "addr:street":"S Broadway",
    "iso:country":"US",
    "sg:address":"2033 S Broadway",
    "sg:city":"Santa Maria",
    "sg:classifiers":[
        {
            "category":"Insurance",
            "subcategory":"Insurance Agent",
            "type":"Services"
        }
    ],
    "sg:phone":"+1 805 922 5731",
    "sg:postcode":"93454",
    "sg:province":"CA",
    "wof:name":"AAA Insurance",
    "wof:placetype":"venue"
},
  "geometry": {"coordinates":[-120.436212,34.92359],"type":"Point"}
}