{
  "type": "Feature",
  "properties": {
    "addr:full":"720 Beacon Ave Los Angeles CA 90017",
    "addr:housenumber":"720",
    "addr:postcode":"90017",
    "addr:street":"Beacon Ave",
    "iso:country":"US",
    "sg:address":"720 Beacon Ave",
    "sg:city":"Los Angeles",
    "sg:classifiers":[
        {
            "category":"Real Estate",
            "subcategory":"Real Estate Operator",
            "type":"Services"
        }
    ],
    "sg:phone":"+1 213 484 0532",
    "sg:postcode":"90017",
    "sg:province":"CA",
    "sg:tags":[
        "building",
        "apartment"
    ],
    "wof:name":"Beacon Apartments",
    "wof:placetype":"venue"
},
  "geometry": {"coordinates":[-118.273096,34.053138],"type":"Point"}
}