{
  "type": "Feature",
  "properties": {
    "iso:country":"US",
    "sg:address":"3701 Rupert Rd",
    "sg:city":"Anderson",
    "sg:classifiers":[
        {
            "category":"Government",
            "subcategory":"Office",
            "type":"Public Place"
        }
    ],
    "sg:phone":"+1 530 378 6664",
    "sg:postcode":"96007",
    "sg:province":"CA",
    "sg:tags":[
        "govt",
        "city"
    ],
    "wof:name":"Anderson Waste Water Treatment",
    "wof:placetype":"venue"
},
  "geometry": {"coordinates":[-122.27602,40.467434],"type":"Point"}
}