{
  "type": "Feature",
  "properties": {
    "addr:full":"2415 Artesia Blvd Redondo Beach CA 90278",
    "addr:housenumber":"2415",
    "addr:postcode":"90278",
    "addr:street":"Artesia Blvd",
    "iso:country":"US",
    "sg:address":"2415 Artesia Blvd",
    "sg:city":"Redondo Beach",
    "sg:classifiers":[
        {
            "category":"Arena",
            "subcategory":"Sports Club",
            "type":"Entertainment"
        }
    ],
    "sg:phone":"+1 310 753 9559",
    "sg:postcode":"90278",
    "sg:province":"CA",
    "sg:tags":[
        "martial art"
    ],
    "sg:website":"www.capoeirasouthbay.com",
    "wof:name":"Capoeira Southbay",
    "wof:placetype":"venue"
},
  "geometry": {"coordinates":[-118.367203,33.873164],"type":"Point"}
}