{
  "type": "Feature",
  "properties": {
    "iso:country":"US",
    "sg:address":"27468 Ynez Rd",
    "sg:city":"Temecula",
    "sg:classifiers":[
        {
            "category":"Education",
            "subcategory":"Junior College",
            "type":"Public Place"
        }
    ],
    "sg:phone":"+1 951 694 4323",
    "sg:postcode":"92591",
    "sg:province":"CA",
    "sg:tags":[
        "technical",
        "institute"
    ],
    "wof:name":"Esthetiques Cosmetology Inst",
    "wof:placetype":"venue"
},
  "geometry": {"coordinates":[-117.150165,33.506889],"type":"Point"}
}