{
  "type": "Feature",
  "properties": {
    "addr:full":"753 Jefferson St Napa CA 94559",
    "addr:housenumber":"753",
    "addr:postcode":"94559",
    "addr:street":"Jefferson St",
    "iso:country":"US",
    "sg:address":"753 Jefferson St",
    "sg:city":"Napa",
    "sg:classifiers":[
        {
            "category":"Professional",
            "subcategory":"Accounting & Tax Preparation",
            "type":"Services"
        }
    ],
    "sg:phone":"+1 707 255 7043",
    "sg:postcode":"94559",
    "sg:province":"CA",
    "sg:tags":[
        "bookkeeping",
        "general"
    ],
    "wof:name":"Cynbar Ledgers Inc",
    "wof:placetype":"venue"
},
  "geometry": {"coordinates":[-122.29377599999999,38.295281],"type":"Point"}
}