{
  "type": "Feature",
  "properties": {
    "addr:full":"1771 W Romneya Dr Ste E Anaheim CA 92801",
    "addr:housenumber":"1771",
    "addr:postcode":"92801",
    "addr:street":"W Romneya Dr Ste E",
    "iso:country":"US",
    "sg:address":"1771 W Romneya Dr Ste E",
    "sg:city":"Anaheim",
    "sg:classifiers":[
        {
            "category":"Health Services",
            "subcategory":"Doctor",
            "type":"Services"
        }
    ],
    "sg:phone":"+1 714 758 8702",
    "sg:postcode":"92801",
    "sg:province":"CA",
    "wof:name":"Mann Jasbir S MD",
    "wof:placetype":"venue"
},
  "geometry": {"coordinates":[-117.945999,33.8507],"type":"Point"}
}