{
  "type": "Feature",
  "properties": {
    "iso:country":"US",
    "sg:address":"1295 N Wishon Ave Ste 1B",
    "sg:city":"Fresno",
    "sg:classifiers":[
        {
            "category":"Health Services",
            "subcategory":"Chiropractor",
            "type":"Services"
        }
    ],
    "sg:phone":"+1 559 250 0845",
    "sg:postcode":"93728",
    "sg:province":"CA",
    "sg:tags":[
        "chiropractic"
    ],
    "wof:name":"Stanley Melinda DC",
    "wof:placetype":"venue"
},
  "geometry": {"coordinates":[-119.801064,36.759426],"type":"Point"}
}