{
  "type": "Feature",
  "properties": {
    "addr:full":"5555 Mission St San Francisco CA 94112",
    "addr:housenumber":"5555",
    "addr:postcode":"94112",
    "addr:street":"Mission St",
    "iso:country":"US",
    "sg:address":"5555 Mission St",
    "sg:city":"San Francisco",
    "sg:classifiers":[
        {
            "category":"Personal",
            "subcategory":"Beauty Salon",
            "type":"Services"
        }
    ],
    "sg:phone":"+1 415 337 2663",
    "sg:postcode":"94112",
    "sg:province":"CA",
    "wof:name":"Oona Hair Studio",
    "wof:placetype":"venue"
},
  "geometry": {"coordinates":[-122.446383,37.711436],"type":"Point"}
}