{
  "type": "Feature",
  "properties": {
    "addr:full":"7044 Sunrise Blvd Ste A2 Citrus Heights CA 95610",
    "addr:housenumber":"7044",
    "addr:postcode":"95610",
    "addr:street":"Sunrise Blvd Ste A2",
    "iso:country":"US",
    "sg:address":"7044 Sunrise Blvd Ste A2",
    "sg:city":"Citrus Heights",
    "sg:classifiers":[
        {
            "category":"Health Services",
            "subcategory":"Chiropractor",
            "type":"Services"
        }
    ],
    "sg:phone":"+1 916 722 1211",
    "sg:postcode":"95610",
    "sg:province":"CA",
    "wof:name":"Johnson's Chiropractic",
    "wof:placetype":"venue"
},
  "geometry": {"coordinates":[-121.270098,38.695002],"type":"Point"}
}