{
  "type": "Feature",
  "properties": {
    "addr:full":"2151 Salvio St Concord CA 94520",
    "addr:housenumber":"2151",
    "addr:postcode":"94520",
    "addr:street":"Salvio St",
    "iso:country":"US",
    "sg:address":"2151 Salvio St",
    "sg:city":"Concord",
    "sg:classifiers":[
        {
            "category":"Restaurant",
            "type":"Food & Drink"
        }
    ],
    "sg:menulink":"http://www.allmenus.com/ca/central-contra-costa/61271-toscana-ristorante/menu/",
    "sg:phone":"+1 925 521 9010",
    "sg:postcode":"94520",
    "sg:province":"CA",
    "sg:tags":[
        "italian"
    ],
    "wof:name":"Toscana Ristorante",
    "wof:placetype":"venue"
},
  "geometry": {"coordinates":[-122.034212,37.977703],"type":"Point"}
}