{
  "type": "Feature",
  "properties": {
    "addr:full":"11501 Lakeland Rd Santa Fe Springs CA 90670",
    "addr:housenumber":"11501",
    "addr:postcode":"90670",
    "addr:street":"Lakeland Rd",
    "iso:country":"US",
    "sg:address":"11501 Lakeland Rd",
    "sg:city":"Santa Fe Springs",
    "sg:classifiers":[
        {
            "category":"Freight",
            "type":"Transportation"
        }
    ],
    "sg:phone":"+1 562 863 2083",
    "sg:postcode":"90670",
    "sg:province":"CA",
    "sg:tags":[
        "operator",
        "local",
        "trucking"
    ],
    "wof:name":"Henry Serna Trucking",
    "wof:placetype":"venue"
},
  "geometry": {"coordinates":[-118.087637,33.931135],"type":"Point"}
}