{
  "type": "Feature",
  "properties": {
    "addr:full":"1496 Solano Ave Albany CA 94706",
    "addr:housenumber":"1496",
    "addr:postcode":"94706",
    "addr:street":"Solano Ave",
    "iso:country":"US",
    "sg:address":"1496 Solano Ave",
    "sg:city":"Albany",
    "sg:classifiers":[
        {
            "category":"Building & Trades",
            "subcategory":"Landscaping Services",
            "type":"Services"
        }
    ],
    "sg:phone":"+1 510 527 6343",
    "sg:postcode":"94706",
    "sg:province":"CA",
    "sg:tags":[
        "environmental",
        "planning",
        "architecture",
        "landscape"
    ],
    "wof:name":"Haygood Assoc Ldscp Architects",
    "wof:placetype":"venue"
},
  "geometry": {"coordinates":[-122.288695,37.89074],"type":"Point"}
}