{
  "type": "Feature",
  "properties": {
    "addr:full":"27203 Woodbluff Rd Laguna Hills CA 92653",
    "addr:housenumber":"27203",
    "addr:postcode":"92653",
    "addr:street":"Woodbluff Rd",
    "iso:country":"US",
    "sg:address":"27203 Woodbluff Rd",
    "sg:city":"Laguna Hills",
    "sg:classifiers":[
        {
            "category":"Shopping",
            "subcategory":"Jewelry",
            "type":"Retail Goods"
        }
    ],
    "sg:phone":"+1 949 582 8670",
    "sg:postcode":"92653",
    "sg:province":"CA",
    "sg:tags":[
        "jeweler"
    ],
    "wof:name":"Anthony Jewelry Co",
    "wof:placetype":"venue"
},
  "geometry": {"coordinates":[-117.68281,33.568192],"type":"Point"}
}