{
  "type": "Feature",
  "properties": {
    "iso:country":"US",
    "sg:address":"20311 Valley Blvd",
    "sg:city":"Walnut",
    "sg:classifiers":[
        {
            "category":"Shopping",
            "subcategory":"Computers & Home Electronics",
            "type":"Retail Goods"
        }
    ],
    "sg:phone":"+1 909 594 9886",
    "sg:postcode":"91789",
    "sg:province":"CA",
    "sg:tags":[
        "parts",
        "supply"
    ],
    "wof:name":"Asia Pro Computer Co",
    "wof:placetype":"venue"
},
  "geometry": {"coordinates":[-117.858925,34.009588],"type":"Point"}
}