{
  "type": "Feature",
  "properties": {
    "addr:full":"4426 Chippendale Ct Union City CA 94587",
    "addr:housenumber":"4426",
    "addr:postcode":"94587",
    "addr:street":"Chippendale Ct",
    "iso:country":"US",
    "sg:address":"4426 Chippendale Ct",
    "sg:city":"Union City",
    "sg:classifiers":[
        {
            "category":"Manufacturing",
            "subcategory":"Furniture",
            "type":"Manufacturing & Wholesale Goods"
        }
    ],
    "sg:phone":"+1 510 487 9433",
    "sg:postcode":"94587",
    "sg:province":"CA",
    "sg:tags":[
        "drapery",
        "mfg"
    ],
    "wof:name":"Mr Mini-Blind",
    "wof:placetype":"venue"
},
  "geometry": {"coordinates":[-122.068586,37.58154],"type":"Point"}
}