{
  "type": "Feature",
  "properties": {
    "addr:full":"222 N Citrus Ave Azusa CA 91702",
    "addr:housenumber":"222",
    "addr:postcode":"91702",
    "addr:street":"N Citrus Ave",
    "iso:country":"US",
    "sg:address":"222 N Citrus Ave",
    "sg:city":"Azusa",
    "sg:classifiers":[
        {
            "category":"Personal",
            "subcategory":"Shoe Repair & Shine",
            "type":"Services"
        }
    ],
    "sg:phone":"+1 626 339 4300",
    "sg:postcode":"91702",
    "sg:province":"CA",
    "sg:tags":[
        "parlor",
        "shoes"
    ],
    "wof:name":"Vics Shoe Service",
    "wof:placetype":"venue"
},
  "geometry": {"coordinates":[-117.89003599999999,34.125544],"type":"Point"}
}