{
  "type": "Feature",
  "properties": {
    "addr:full":"3647 India St San Diego CA 92103",
    "addr:housenumber":"3647",
    "addr:postcode":"92103",
    "addr:street":"India St",
    "iso:country":"US",
    "sg:address":"3647 India St",
    "sg:city":"San Diego",
    "sg:classifiers":[
        {
            "category":"Real Estate",
            "subcategory":"Real Estate Operator",
            "type":"Services"
        }
    ],
    "sg:phone":"+1 619 220 5297",
    "sg:postcode":"92103",
    "sg:province":"CA",
    "sg:tags":[
        "property",
        "lessor"
    ],
    "wof:name":"H Q Global Workplaces Inc",
    "wof:placetype":"venue"
},
  "geometry": {"coordinates":[-117.178973,32.74079],"type":"Point"}
}