{
  "type": "Feature",
  "properties": {
    "iso:country":"US",
    "sg:address":"1835 Cunningham Ave",
    "sg:city":"San Jose",
    "sg:classifiers":[
        {
            "category":"Place Of Worship",
            "subcategory":"Church",
            "type":"Public Place"
        }
    ],
    "sg:phone":"+1 408 263 0406",
    "sg:postcode":"95122",
    "sg:province":"CA",
    "sg:website":"www.cwcsj.org",
    "wof:name":"Christian Worship Center",
    "wof:placetype":"venue"
},
  "geometry": {"coordinates":[-121.82971000000001,37.329696],"type":"Point"}
}