{
  "type": "Feature",
  "properties": {
    "iso:country":"US",
    "sg:address":"19192 Via Cuesta",
    "sg:city":"Ramona",
    "sg:classifiers":[
        {
            "category":"Wholesale",
            "subcategory":"Machinery & Supplies",
            "type":"Manufacturing & Wholesale Goods"
        }
    ],
    "sg:phone":"+1 760 788 3800",
    "sg:postcode":"92065",
    "sg:province":"CA",
    "sg:tags":[
        "dry wall",
        "contractor"
    ],
    "wof:name":"Innovative Drywall Systems Inc",
    "wof:placetype":"venue"
},
  "geometry": {"coordinates":[-116.935061,33.072079],"type":"Point"}
}