{
  "type": "Feature",
  "properties": {
    "addr:full":"615 State Rte 66 Glendora CA 91740",
    "addr:housenumber":"615",
    "addr:postcode":"91740",
    "addr:street":"State Rte 66",
    "iso:country":"US",
    "sg:address":"615 State Rte 66",
    "sg:city":"Glendora",
    "sg:classifiers":[
        {
            "category":"Health Services",
            "subcategory":"Doctor",
            "type":"Services"
        }
    ],
    "sg:phone":"+1 626 852 2599",
    "sg:postcode":"91740",
    "sg:province":"CA",
    "sg:tags":[
        "surgery",
        "cosmetic"
    ],
    "wof:name":"Woodglen Institute-Aesthetics",
    "wof:placetype":"venue"
},
  "geometry": {"coordinates":[-117.854907,34.128749],"type":"Point"}
}