{
  "type": "Feature",
  "properties": {
    "addr:full":"4115 N Mountain Ave San Bernardino CA 92404",
    "addr:housenumber":"4115",
    "addr:postcode":"92404",
    "addr:street":"N Mountain Ave",
    "iso:country":"US",
    "sg:address":"4115 N Mountain Ave",
    "sg:city":"San Bernardino",
    "sg:classifiers":[
        {
            "category":"Professional",
            "type":"Services"
        }
    ],
    "sg:phone":"+1 909 709 8074",
    "sg:postcode":"92404",
    "sg:province":"CA",
    "sg:tags":[
        "establishment"
    ],
    "wof:name":"Crazy Times Productions",
    "wof:placetype":"venue"
},
  "geometry": {"coordinates":[-117.25671199999999,34.165983],"type":"Point"}
}