{
  "type": "Feature",
  "properties": {
    "addr:full":"972 Cuyamaca Ave Chula Vista CA 91911",
    "addr:housenumber":"972",
    "addr:postcode":"91911",
    "addr:street":"Cuyamaca Ave",
    "iso:country":"US",
    "sg:address":"972 Cuyamaca Ave",
    "sg:city":"Chula Vista",
    "sg:classifiers":[
        {
            "category":"Shopping",
            "type":"Retail Goods"
        }
    ],
    "sg:phone":"+1 619 476 9986",
    "sg:postcode":"91911",
    "sg:province":"CA",
    "sg:tags":[
        "merchandise"
    ],
    "wof:name":"Purple Pincher",
    "wof:placetype":"venue"
},
  "geometry": {"coordinates":[-117.054784,32.623052],"type":"Point"}
}