{
  "type": "Feature",
  "properties": {
    "addr:full":"11822 Macgill St Garden Grove CA 92841",
    "addr:housenumber":"11822",
    "addr:postcode":"92841",
    "addr:street":"Macgill St",
    "iso:country":"US",
    "sg:address":"11822 Macgill St",
    "sg:city":"Garden Grove",
    "sg:classifiers":[
        {
            "category":"Shopping",
            "type":"Retail Goods"
        }
    ],
    "sg:phone":"+1 714 534 6886",
    "sg:postcode":"92841",
    "sg:province":"CA",
    "sg:tags":[
        "merchandise"
    ],
    "wof:name":"Barney G Yslava",
    "wof:placetype":"venue"
},
  "geometry": {"coordinates":[-117.97732999999999,33.790198],"type":"Point"}
}