{
  "type": "Feature",
  "properties": {
    "iso:country":"US",
    "sg:address":"138 Pierre Rd",
    "sg:city":"Walnut",
    "sg:classifiers":[
        {
            "category":"Retail",
            "subcategory":"Laundry & Dry Cleaning",
            "type":"Services"
        }
    ],
    "sg:phone":"+1 909 598 2478",
    "sg:postcode":"91789",
    "sg:province":"CA",
    "sg:tags":[
        "cleaners"
    ],
    "wof:name":"Walnut Cleaners",
    "wof:placetype":"venue"
},
  "geometry": {"coordinates":[-117.850191,34.017392],"type":"Point"}
}