{
  "type": "Feature",
  "properties": {
    "addr:full":"3100 Airway Ave Costa Mesa CA 92626",
    "addr:housenumber":"3100",
    "addr:postcode":"92626",
    "addr:street":"Airway Ave",
    "iso:country":"US",
    "sg:address":"3100 Airway Ave",
    "sg:city":"Costa Mesa",
    "sg:classifiers":[
        {
            "category":"Professional",
            "subcategory":"Management & Consulting",
            "type":"Services"
        }
    ],
    "sg:phone":"+1 714 545 1500",
    "sg:postcode":"92626",
    "sg:province":"CA",
    "sg:tags":[
        "consultant",
        "business"
    ],
    "wof:name":"Baldwin Business Consulting",
    "wof:placetype":"venue"
},
  "geometry": {"coordinates":[-117.87338,33.67608],"type":"Point"}
}