{
  "type": "Feature",
  "properties": {
    "iso:country":"US",
    "sg:address":"1410 E Cesar E Chavez Ave",
    "sg:city":"Los Angeles",
    "sg:classifiers":[
        {
            "category":"Retail",
            "subcategory":"Auto Repair",
            "type":"Services"
        }
    ],
    "sg:phone":"+1 323 264 5593",
    "sg:postcode":"90033",
    "sg:province":"CA",
    "sg:tags":[
        "body",
        "shop"
    ],
    "wof:name":"Joe's Body Shop",
    "wof:placetype":"venue"
},
  "geometry": {"coordinates":[-118.221001,34.052601],"type":"Point"}
}