{
  "type": "Feature",
  "properties": {
    "addr:full":"7623 State Street Huntington Park CA 90255",
    "addr:housenumber":"7623",
    "addr:postcode":"90255",
    "addr:street":"State Street",
    "iso:country":"US",
    "sg:address":"7623 State Street",
    "sg:city":"Huntington Park",
    "sg:classifiers":[
        {
            "category":"Restaurant",
            "type":"Food & Drink"
        }
    ],
    "sg:phone":"+1 323 589 0504",
    "sg:postcode":"90255",
    "sg:province":"CA",
    "wof:name":"Pop's Burgers",
    "wof:placetype":"venue"
},
  "geometry": {"coordinates":[-118.21003399999999,33.968495],"type":"Point"}
}