{
  "type": "Feature",
  "properties": {
    "iso:country":"US",
    "sg:address":"575 Bragato Rd",
    "sg:city":"San Carlos",
    "sg:classifiers":[
        {
            "category":"Personal",
            "type":"Services"
        }
    ],
    "sg:phone":"+1 650 637 1277",
    "sg:postcode":"94070",
    "sg:province":"CA",
    "sg:tags":[
        "mover"
    ],
    "wof:name":"Budget Movers & Storage",
    "wof:placetype":"venue"
},
  "geometry": {"coordinates":[-122.26599899999999,37.5154],"type":"Point"}
}