{
  "type": "Feature",
  "properties": {
    "addr:full":"12680 Sorrel Dr Apple Valley CA 92308",
    "addr:housenumber":"12680",
    "addr:postcode":"92308",
    "addr:street":"Sorrel Dr",
    "iso:country":"US",
    "sg:address":"12680 Sorrel Dr",
    "sg:city":"Apple Valley",
    "sg:classifiers":[
        {
            "category":"Shopping",
            "subcategory":"Catalog Store",
            "type":"Retail Goods"
        }
    ],
    "sg:phone":"+1 760 240 7412",
    "sg:postcode":"92308",
    "sg:province":"CA",
    "sg:tags":[
        "mail",
        "order"
    ],
    "wof:name":"Brewtality",
    "wof:placetype":"venue"
},
  "geometry": {"coordinates":[-117.247703,34.481095],"type":"Point"}
}