{
  "type": "Feature",
  "properties": {
    "addr:full":"2227 San Pablo Ave Oakland CA 94612",
    "addr:housenumber":"2227",
    "addr:postcode":"94612",
    "addr:street":"San Pablo Ave",
    "iso:country":"US",
    "sg:address":"2227 San Pablo Ave",
    "sg:city":"Oakland",
    "sg:classifiers":[
        {
            "category":"Wholesale",
            "subcategory":"Home Furnishings",
            "type":"Manufacturing & Wholesale Goods"
        }
    ],
    "sg:phone":"+1 415 738 9000",
    "sg:postcode":"94612",
    "sg:province":"CA",
    "sg:tags":[
        "blind",
        "shade"
    ],
    "sg:website":"www.windowwearswest.com",
    "wof:name":"Window Wears West",
    "wof:placetype":"venue"
},
  "geometry": {"coordinates":[-122.27445,37.812442],"type":"Point"}
}