{
  "type": "Feature",
  "properties": {
    "iso:country":"US",
    "sg:address":"7401 W Sunset Blvd",
    "sg:city":"Los Angeles",
    "sg:classifiers":[
        {
            "category":"Personal",
            "type":"Services"
        }
    ],
    "sg:phone":"+1 323 874 4200",
    "sg:postcode":"90046",
    "sg:province":"CA",
    "sg:tags":[
        "wear",
        "formal"
    ],
    "wof:name":"Tuxedo Center",
    "wof:placetype":"venue"
},
  "geometry": {"coordinates":[-118.351742,34.098015],"type":"Point"}
}