{
  "type": "Feature",
  "properties": {
    "addr:full":"1515 2nd Ave San Diego CA 92101",
    "addr:housenumber":"1515",
    "addr:postcode":"92101",
    "addr:street":"2Nd Ave",
    "iso:country":"US",
    "sg:address":"1515 2nd Ave",
    "sg:city":"San Diego",
    "sg:classifiers":[
        {
            "category":"Manufacturing",
            "subcategory":"Printing",
            "type":"Manufacturing & Wholesale Goods"
        }
    ],
    "sg:phone":"+1 619 849 2800",
    "sg:postcode":"92101",
    "sg:province":"CA",
    "sg:tags":[
        "publisher",
        "software"
    ],
    "sg:website":"www.solimarsystems.com",
    "wof:name":"Solimar Systems Inc",
    "wof:placetype":"venue"
},
  "geometry": {"coordinates":[-117.162874,32.721821],"type":"Point"}
}