{
  "type": "Feature",
  "properties": {
    "addr:full":"2913 W 156th St Gardena CA 90249",
    "addr:housenumber":"2913",
    "addr:postcode":"90249",
    "addr:street":"W 156Th St",
    "iso:country":"US",
    "sg:address":"2913 W 156th St",
    "sg:city":"Gardena",
    "sg:classifiers":[
        {
            "category":"Personal",
            "subcategory":"Beauty Salon",
            "type":"Services"
        }
    ],
    "sg:phone":"+1 310 327 9477",
    "sg:postcode":"90249",
    "sg:province":"CA",
    "sg:tags":[
        "make",
        "studio"
    ],
    "wof:name":"All Thats Natural",
    "wof:placetype":"venue"
},
  "geometry": {"coordinates":[-118.325749,33.889268],"type":"Point"}
}