{
  "type": "Feature",
  "properties": {
    "addr:full":"171 Pier Ave Santa Monica CA 90405",
    "addr:housenumber":"171",
    "addr:postcode":"90405",
    "addr:street":"Pier Ave",
    "iso:country":"US",
    "sg:address":"171 Pier Ave",
    "sg:city":"Santa Monica",
    "sg:classifiers":[
        {
            "category":"Manufacturing",
            "subcategory":"Paper Products",
            "type":"Manufacturing & Wholesale Goods"
        },
        {
            "category":"Professional",
            "subcategory":"Management & Consulting",
            "type":"Services"
        }
    ],
    "sg:phone":"+1 310 822 0481",
    "sg:postcode":"90405",
    "sg:province":"CA",
    "sg:tags":[
        "packaging",
        "material",
        "sales",
        "direct",
        "retail"
    ],
    "wof:name":"2 Pop",
    "wof:placetype":"venue"
},
  "geometry": {"coordinates":[-118.48047800000001,33.998293],"type":"Point"}
}