{
  "type": "Feature",
  "properties": {
    "iso:country":"US",
    "sg:address":"2396 Wailea Way",
    "sg:city":"San Diego",
    "sg:classifiers":[
        {
            "category":"Manufacturing",
            "subcategory":"Printing",
            "type":"Manufacturing & Wholesale Goods"
        }
    ],
    "sg:phone":"+1 619 575 1903",
    "sg:postcode":"92154",
    "sg:province":"CA",
    "sg:tags":[
        "commercial"
    ],
    "wof:name":"Tees & Things Enterprises",
    "wof:placetype":"venue"
},
  "geometry": {"coordinates":[-117.068587,32.585436],"type":"Point"}
}