{
  "type": "Feature",
  "properties": {
    "iso:country":"US",
    "sg:address":"11 Mill Creek",
    "sg:city":"Irvine",
    "sg:classifiers":[
        {
            "category":"Wholesale",
            "subcategory":"Machinery & Supplies",
            "type":"Manufacturing & Wholesale Goods"
        }
    ],
    "sg:phone":"+1 949 679 2660",
    "sg:postcode":"92603",
    "sg:province":"CA",
    "sg:tags":[
        "equipment",
        "transportation"
    ],
    "wof:name":"Econet USA Inc",
    "wof:placetype":"venue"
},
  "geometry": {"coordinates":[-117.81325699999999,33.643355],"type":"Point"}
}