{
  "type": "Feature",
  "properties": {
    "addr:full":"533 S Harvard Blvd Los Angeles CA 90020",
    "addr:housenumber":"533",
    "addr:postcode":"90020",
    "addr:street":"S Harvard Blvd",
    "iso:country":"US",
    "sg:address":"533 S Harvard Blvd",
    "sg:city":"Los Angeles",
    "sg:classifiers":[
        {
            "category":"Wholesale",
            "subcategory":"Durable Goods & Equipment",
            "type":"Manufacturing & Wholesale Goods"
        }
    ],
    "sg:phone":"+1 213 381 7354",
    "sg:postcode":"90020",
    "sg:province":"CA",
    "wof:name":"Wna Universal Trading",
    "wof:placetype":"venue"
},
  "geometry": {"coordinates":[-118.304182,34.064138],"type":"Point"}
}