{
  "type": "Feature",
  "properties": {
    "iso:country":"US",
    "sg:address":"18001 Sky Park Cir",
    "sg:city":"Irvine",
    "sg:classifiers":[
        {
            "category":"Professional",
            "subcategory":"Computer Services",
            "type":"Services"
        }
    ],
    "sg:phone":"+1 949 251 0965",
    "sg:postcode":"92614",
    "sg:province":"CA",
    "sg:tags":[
        "hardware",
        "provider",
        "internet",
        "software"
    ],
    "wof:name":"So What Software",
    "wof:placetype":"venue"
},
  "geometry": {"coordinates":[-117.86097700000001,33.690122],"type":"Point"}
}