{
  "type": "Feature",
  "properties": {
    "addr:full":"3388 W Century Blvd Inglewood CA 90303",
    "addr:housenumber":"3388",
    "addr:postcode":"90303",
    "addr:street":"W Century Blvd",
    "iso:country":"US",
    "sg:address":"3388 W Century Blvd",
    "sg:city":"Inglewood",
    "sg:classifiers":[
        {
            "category":"Ice Cream",
            "type":"Food & Drink"
        }
    ],
    "sg:menulink":"http://www.allmenus.com/ca/inglewood/183856-cold-stone-creamery/menu/",
    "sg:phone":"+1 310 671 1010",
    "sg:postcode":"90303",
    "sg:province":"CA",
    "sg:tags":[
        "smoothy",
        "juice",
        "american"
    ],
    "wof:name":"Cold Stone Creamery",
    "wof:placetype":"venue"
},
  "geometry": {"coordinates":[-118.33076800000001,33.945413],"type":"Point"}
}