{
  "type": "Feature",
  "properties": {
    "iso:country":"US",
    "sg:address":"534 State Rte 66",
    "sg:city":"Glendora",
    "sg:classifiers":[
        {
            "category":"Building & Trades",
            "subcategory":"Electrical",
            "type":"Services"
        }
    ],
    "sg:phone":"+1 626 852 5586",
    "sg:postcode":"91740",
    "sg:province":"CA",
    "sg:tags":[
        "electrical",
        "contractor"
    ],
    "wof:name":"David Stone Electrical",
    "wof:placetype":"venue"
},
  "geometry": {"coordinates":[-117.87222,34.12876],"type":"Point"}
}