{
  "type": "Feature",
  "properties": {
    "iso:country":"US",
    "sg:address":"8363 Reseda Blvd",
    "sg:city":"Northridge",
    "sg:classifiers":[
        {
            "category":"Health Services",
            "subcategory":"Doctor",
            "type":"Services"
        }
    ],
    "sg:phone":"+1 818 998 2102",
    "sg:postcode":"91324",
    "sg:province":"CA",
    "sg:tags":[
        "dentist"
    ],
    "wof:name":"Sun Valley Dental Group",
    "wof:placetype":"venue"
},
  "geometry": {"coordinates":[-118.53615499999999,34.223393],"type":"Point"}
}