{
  "type": "Feature",
  "properties": {
    "iso:country":"US",
    "sg:address":"1550 Kellogg Dr",
    "sg:city":"Anaheim",
    "sg:classifiers":[
        {
            "category":"Manufacturing",
            "subcategory":"Furniture",
            "type":"Manufacturing & Wholesale Goods"
        }
    ],
    "sg:phone":"+1 714 777 6086",
    "sg:postcode":"92807",
    "sg:province":"CA",
    "sg:tags":[
        "window",
        "shades"
    ],
    "sg:website":"www.rainbowindustrial.com",
    "wof:name":"Rainbow Industrial Co",
    "wof:placetype":"venue"
},
  "geometry": {"coordinates":[-117.806537,33.863358],"type":"Point"}
}