{
  "type": "Feature",
  "properties": {
    "addr:full":"159 Avis St Arroyo Grande CA 93420",
    "addr:housenumber":"159",
    "addr:postcode":"93420",
    "addr:street":"Avis St",
    "iso:country":"US",
    "sg:address":"159 Avis St",
    "sg:city":"Arroyo Grande",
    "sg:classifiers":[
        {
            "category":"Shopping",
            "subcategory":"Bicycles & Sporting Goods",
            "type":"Retail Goods"
        }
    ],
    "sg:phone":"+1 805 481 7260",
    "sg:postcode":"93420",
    "sg:province":"CA",
    "wof:name":"Pa Pa's Palapas",
    "wof:placetype":"venue"
},
  "geometry": {"coordinates":[-120.54016799999999,35.07752],"type":"Point"}
}