{
  "type": "Feature",
  "properties": {
    "iso:country":"US",
    "sg:address":"6310 Galaxy Ln",
    "sg:city":"Rocklin",
    "sg:classifiers":[
        {
            "category":"Wholesale",
            "subcategory":"Non-durable Goods",
            "type":"Manufacturing & Wholesale Goods"
        }
    ],
    "sg:phone":"+1 916 781 3903",
    "sg:postcode":"95677",
    "sg:province":"CA",
    "sg:tags":[
        "dry",
        "goods-wholesale"
    ],
    "wof:name":"California Automotive Wholesalers' Association",
    "wof:placetype":"venue"
},
  "geometry": {"coordinates":[-121.20796199999999,38.775954],"type":"Point"}
}