{
  "type": "Feature",
  "properties": {
    "iso:country":"US",
    "sg:address":"2139 1st St",
    "sg:city":"Napa",
    "sg:classifiers":[
        {
            "category":"Professional",
            "subcategory":"Lawyer & Legal Services",
            "type":"Services"
        }
    ],
    "sg:phone":"+1 707 252 0668",
    "sg:postcode":"94559",
    "sg:province":"CA",
    "sg:tags":[
        "attorney"
    ],
    "wof:name":"Leslie R Leister",
    "wof:placetype":"venue"
},
  "geometry": {"coordinates":[-122.29700099999999,38.297729],"type":"Point"}
}