{
  "type": "Feature",
  "properties": {
    "addr:full":"3525 W 3rd St Ste 2 Los Angeles CA 90020",
    "addr:housenumber":"3525",
    "addr:postcode":"90020",
    "addr:street":"W 3Rd St Ste 2",
    "iso:country":"US",
    "sg:address":"3525 W 3rd St Ste 2",
    "sg:city":"Los Angeles",
    "sg:classifiers":[
        {
            "category":"Restaurant",
            "type":"Food & Drink"
        },
        {
            "category":"Ice Cream",
            "type":"Food & Drink"
        }
    ],
    "sg:phone":"+1 213 387 5511",
    "sg:postcode":"90020",
    "sg:province":"CA",
    "sg:tags":[
        "frozen",
        "yogurt",
        "breakfast",
        "brunch"
    ],
    "wof:name":"BinnieLoco",
    "wof:placetype":"venue"
},
  "geometry": {"coordinates":[-118.292539,34.069303],"type":"Point"}
}