{
  "type": "Feature",
  "properties": {
    "addr:full":"3899 24th St San Francisco CA 94114",
    "addr:housenumber":"3899",
    "addr:postcode":"94114",
    "addr:street":"24Th St",
    "iso:country":"US",
    "sg:address":"3899 24th St",
    "sg:city":"San Francisco",
    "sg:classifiers":[
        {
            "category":"Shopping",
            "subcategory":"Clothing, Apparel, & Fashions",
            "type":"Retail Goods"
        }
    ],
    "sg:phone":"+1 415 648 1057",
    "sg:postcode":"94114",
    "sg:province":"CA",
    "wof:name":"Designers' Club",
    "wof:placetype":"venue"
},
  "geometry": {"coordinates":[-122.42854800000001,37.751638],"type":"Point"}
}