{
  "type": "Feature",
  "properties": {
    "addr:full":"190 Klamath Blvd Klamath CA 95548",
    "addr:housenumber":"190",
    "addr:postcode":"95548",
    "addr:street":"Klamath Blvd",
    "iso:country":"US",
    "sg:address":"190 Klamath Blvd",
    "sg:city":"Klamath",
    "sg:classifiers":[
        {
            "category":"Government",
            "subcategory":"Office",
            "type":"Public Place"
        }
    ],
    "sg:phone":"+1 707 482 1350",
    "sg:postcode":"95548",
    "sg:province":"CA",
    "sg:tags":[
        "offices-tribal"
    ],
    "sg:website":"http://www.yuroktribe.org",
    "wof:name":"Yurok Tribe",
    "wof:placetype":"venue"
},
  "geometry": {"coordinates":[-124.038157,41.529271],"type":"Point"}
}