{
  "type": "Feature",
  "properties": {
    "iso:country":"US",
    "sg:address":"430 N El Camino Real",
    "sg:city":"San Mateo",
    "sg:classifiers":[
        {
            "category":"Real Estate",
            "subcategory":"Real Estate Agent",
            "type":"Services"
        }
    ],
    "sg:phone":"+1 650 343 3700",
    "sg:postcode":"94401",
    "sg:province":"CA",
    "sg:website":"www.cashin.com",
    "wof:name":"Cashin Company",
    "wof:placetype":"venue"
},
  "geometry": {"coordinates":[-122.33594100000001,37.570516],"type":"Point"}
}