{
  "type": "Feature",
  "properties": {
    "iso:country":"US",
    "sg:address":"25218 del Mar Ave",
    "sg:city":"Hayward",
    "sg:classifiers":[
        {
            "category":"Manufacturing",
            "subcategory":"Metals",
            "type":"Manufacturing & Wholesale Goods"
        }
    ],
    "sg:phone":"+1 510 728 1214",
    "sg:postcode":"94542",
    "sg:province":"CA",
    "wof:name":"Ismael Metal Finish Inc",
    "wof:placetype":"venue"
},
  "geometry": {"coordinates":[-122.06998,37.657937],"type":"Point"}
}