{
  "type": "Feature",
  "properties": {
    "addr:full":"3750 Broadway Pl Los Angeles CA 90007",
    "addr:housenumber":"3750",
    "addr:postcode":"90007",
    "addr:street":"Broadway Pl",
    "iso:country":"US",
    "sg:address":"3750 Broadway Pl",
    "sg:city":"Los Angeles",
    "sg:classifiers":[
        {
            "category":"Manufacturing",
            "subcategory":"Textiles",
            "type":"Manufacturing & Wholesale Goods"
        }
    ],
    "sg:phone":"+1 323 232 2061",
    "sg:postcode":"90007",
    "sg:province":"CA",
    "sg:tags":[
        "mill",
        "knit",
        "weft",
        "fabric"
    ],
    "wof:name":"Antex Knitting Mills",
    "wof:placetype":"venue"
},
  "geometry": {"coordinates":[-118.27583300000001,34.013594],"type":"Point"}
}