{
  "type": "Feature",
  "properties": {
    "addr:full":"445 Bellevue Ave Oakland CA 94610",
    "addr:housenumber":"445",
    "addr:postcode":"94610",
    "addr:street":"Bellevue Ave",
    "iso:country":"US",
    "sg:address":"445 Bellevue Ave",
    "sg:city":"Oakland",
    "sg:classifiers":[
        {
            "category":"Health Services",
            "subcategory":"Clinic",
            "type":"Services"
        }
    ],
    "sg:phone":"+1 510 496 6026",
    "sg:postcode":"94610",
    "sg:province":"CA",
    "sg:tags":[
        "counseling",
        "mental"
    ],
    "wof:name":"Saint John Matilda MA",
    "wof:placetype":"venue"
},
  "geometry": {"coordinates":[-122.25299800000001,37.8088],"type":"Point"}
}