{
  "type": "Feature",
  "properties": {
    "iso:country":"US",
    "sg:address":"19335 Victory Blvd",
    "sg:city":"Tarzana",
    "sg:classifiers":[
        {
            "category":"Wholesale",
            "subcategory":"Groceries",
            "type":"Manufacturing & Wholesale Goods"
        }
    ],
    "sg:phone":"+1 818 996 3036",
    "sg:postcode":"91335",
    "sg:province":"CA",
    "sg:tags":[
        "frozen",
        "food"
    ],
    "wof:name":"International Foods",
    "wof:placetype":"venue"
},
  "geometry": {"coordinates":[-118.557535,34.186644],"type":"Point"}
}