{
  "type": "Feature",
  "properties": {
    "iso:country":"US",
    "sg:address":"14362 Raintree Rd",
    "sg:city":"Tustin",
    "sg:classifiers":[
        {
            "category":"Professional",
            "type":"Services"
        }
    ],
    "sg:phone":"+1 714 669 9168",
    "sg:postcode":"92780",
    "sg:province":"CA",
    "wof:name":"Gnl Ent",
    "wof:placetype":"venue"
},
  "geometry": {"coordinates":[-117.809067,33.721129],"type":"Point"}
}