{
  "type": "Feature",
  "properties": {
    "iso:country":"US",
    "sg:address":"1836 Grace Ave",
    "sg:city":"Los Angeles",
    "sg:classifiers":[
        {
            "category":"Professional",
            "type":"Services"
        }
    ],
    "sg:phone":"+1 323 469 8843",
    "sg:postcode":"90028",
    "sg:province":"CA",
    "wof:name":"Lynne A Philips",
    "wof:placetype":"venue"
},
  "geometry": {"coordinates":[-118.33211799999999,34.104774],"type":"Point"}
}