{
  "type": "Feature",
  "properties": {
    "iso:country":"US",
    "sg:address":"4929 N Van Ness Blvd",
    "sg:city":"Fresno",
    "sg:classifiers":[
        {
            "category":"Shopping",
            "subcategory":"Jewelry",
            "type":"Retail Goods"
        }
    ],
    "sg:phone":"+1 559 228 6805",
    "sg:postcode":"93704",
    "sg:province":"CA",
    "sg:tags":[
        "jeweler"
    ],
    "wof:name":"Josette & Co",
    "wof:placetype":"venue"
},
  "geometry": {"coordinates":[-119.807631,36.807787],"type":"Point"}
}