{
  "type": "Feature",
  "properties": {
    "addr:full":"23243 Ave 24 Ducor CA 93218",
    "addr:housenumber":"23243;24",
    "addr:postcode":"93218",
    "addr:street":"Ave",
    "iso:country":"US",
    "sg:address":"23243 Ave 24",
    "sg:city":"Ducor",
    "sg:classifiers":[
        {
            "category":"Home & Garden",
            "subcategory":"Building Materials",
            "type":"Retail Goods"
        }
    ],
    "sg:phone":"+1 559 534 2714",
    "sg:postcode":"93218",
    "sg:province":"CA",
    "sg:tags":[
        "paint"
    ],
    "wof:name":"Phillips Paints",
    "wof:placetype":"venue"
},
  "geometry": {"coordinates":[-119.056133,35.834073],"type":"Point"}
}