{
  "type": "Feature",
  "properties": {
    "iso:country":"US",
    "sg:address":"1445 E Foothill Blvd",
    "sg:city":"Upland",
    "sg:classifiers":[
        {
            "category":"Shopping",
            "subcategory":"Clothing, Apparel, & Fashions",
            "type":"Retail Goods"
        }
    ],
    "sg:phone":"+1 909 931 2880",
    "sg:postcode":"91786",
    "sg:province":"CA",
    "wof:name":"Socks Town",
    "wof:placetype":"venue"
},
  "geometry": {"coordinates":[-117.630595,34.106963],"type":"Point"}
}