{
  "type": "Feature",
  "properties": {
    "addr:full":"5218 S Vermont Avenue Los Angeles CA 90037",
    "addr:housenumber":"5218",
    "addr:postcode":"90037",
    "addr:street":"S Vermont Avenue",
    "iso:country":"US",
    "sg:address":"5218 S Vermont Avenue",
    "sg:city":"Los Angeles",
    "sg:classifiers":[
        {
            "category":"Restaurant",
            "type":"Food & Drink"
        }
    ],
    "sg:phone":"+1 323 752 8301",
    "sg:postcode":"90037",
    "sg:province":"CA",
    "wof:name":"Susana's Restaurant",
    "wof:placetype":"venue"
},
  "geometry": {"coordinates":[-118.29163200000001,33.994742],"type":"Point"}
}