{
  "type": "Feature",
  "properties": {
    "iso:country":"US",
    "sg:address":"2701 E Hammer Ln",
    "sg:city":"Stockton",
    "sg:classifiers":[
        {
            "category":"Social Services",
            "type":"Services"
        }
    ],
    "sg:phone":"+1 209 955 2070",
    "sg:postcode":"95210",
    "sg:province":"CA",
    "sg:tags":[
        "organization",
        "welfare"
    ],
    "wof:name":"Community Catalysts-California",
    "wof:placetype":"venue"
},
  "geometry": {"coordinates":[-121.28040900000001,38.021129],"type":"Point"}
}