{
  "type": "Feature",
  "properties": {
    "addr:full":"6242 Ascot Dr Oakland CA 94611",
    "addr:housenumber":"6242",
    "addr:postcode":"94611",
    "addr:street":"Ascot Dr",
    "iso:country":"US",
    "sg:address":"6242 Ascot Dr",
    "sg:city":"Oakland",
    "sg:classifiers":[
        {
            "category":"Professional",
            "type":"Services"
        }
    ],
    "sg:phone":"+1 415 309 0336",
    "sg:postcode":"94611",
    "sg:province":"CA",
    "sg:tags":[
        "writer"
    ],
    "wof:name":"Peter Fiske",
    "wof:placetype":"venue"
},
  "geometry": {"coordinates":[-122.19519099999999,37.821783],"type":"Point"}
}