{
  "type": "Feature",
  "properties": {
    "addr:full":"4733 Brooks St Montclair CA 91763",
    "addr:housenumber":"4733",
    "addr:postcode":"91763",
    "addr:street":"Brooks St",
    "iso:country":"US",
    "sg:address":"4733 Brooks St",
    "sg:city":"Montclair",
    "sg:classifiers":[
        {
            "category":"Autos & Motor Vehicles",
            "subcategory":"Auto Supplies",
            "type":"Retail Goods"
        }
    ],
    "sg:phone":"+1 909 626 4801",
    "sg:postcode":"91763",
    "sg:province":"CA",
    "sg:tags":[
        "alternator",
        "generators-automotive"
    ],
    "wof:name":"Hector's Alternators",
    "wof:placetype":"venue"
},
  "geometry": {"coordinates":[-117.701916,34.061619],"type":"Point"}
}