{
  "type": "Feature",
  "properties": {
    "addr:full":"23924 2nd St Hayward CA 94541",
    "addr:housenumber":"23924",
    "addr:postcode":"94541",
    "addr:street":"2Nd St",
    "iso:country":"US",
    "sg:address":"23924 2nd St",
    "sg:city":"Hayward",
    "sg:classifiers":[
        {
            "category":"Real Estate",
            "subcategory":"Real Estate Operator",
            "type":"Services"
        }
    ],
    "sg:phone":"+1 510 247 9416",
    "sg:postcode":"94541",
    "sg:province":"CA",
    "sg:tags":[
        "apartment"
    ],
    "wof:name":"Cinnamon Apartments",
    "wof:placetype":"venue"
},
  "geometry": {"coordinates":[-122.075816,37.6719],"type":"Point"}
}