{
  "type": "Feature",
  "properties": {
    "iso:country":"US",
    "sg:address":"12127 Carson St",
    "sg:city":"Hawaiian Gardens",
    "sg:classifiers":[
        {
            "category":"Shopping",
            "subcategory":"Pharmacy",
            "type":"Retail Goods"
        }
    ],
    "sg:phone":"+1 562 402 3396",
    "sg:postcode":"90716",
    "sg:province":"CA",
    "wof:name":"Hawaii Pharmacy",
    "wof:placetype":"venue"
},
  "geometry": {"coordinates":[-118.07384,33.831488],"type":"Point"}
}