{
  "type": "Feature",
  "properties": {
    "addr:full":"14 San Miguel Ave San Mateo CA 94403",
    "addr:housenumber":"14",
    "addr:postcode":"94403",
    "addr:street":"San Miguel Ave",
    "iso:country":"US",
    "sg:address":"14 San Miguel Ave",
    "sg:city":"San Mateo",
    "sg:classifiers":[
        {
            "category":"Professional",
            "subcategory":"Business Services",
            "type":"Services"
        }
    ],
    "sg:phone":"+1 650 579 2666",
    "sg:postcode":"94403",
    "sg:province":"CA",
    "sg:tags":[
        "event"
    ],
    "wof:name":"Start To Finish",
    "wof:placetype":"venue"
},
  "geometry": {"coordinates":[-122.29364,37.536487],"type":"Point"}
}