{
  "type": "Feature",
  "properties": {
    "addr:full":"17969 Beach Blvd Huntington Beach CA 92647",
    "addr:housenumber":"17969",
    "addr:postcode":"92647",
    "addr:street":"Beach Blvd",
    "iso:country":"US",
    "sg:address":"17969 Beach Blvd",
    "sg:city":"Huntington Beach",
    "sg:classifiers":[
        {
            "category":"Coffee & Tea",
            "type":"Food & Drink"
        }
    ],
    "sg:phone":"+1 714 841 0294",
    "sg:postcode":"92647",
    "sg:province":"CA",
    "sg:website":"www.coffeebean.com",
    "wof:name":"The Coffee Bean & Tea Leaf",
    "wof:placetype":"venue"
},
  "geometry": {"coordinates":[-117.98924,33.701391],"type":"Point"}
}