{
  "type": "Feature",
  "properties": {
    "iso:country":"US",
    "sg:address":"834 The Shops Blvd",
    "sg:city":"Mission Viejo",
    "sg:classifiers":[
        {
            "category":"Shopping",
            "subcategory":"Clothing, Apparel, & Fashions",
            "type":"Retail Goods"
        }
    ],
    "sg:phone":"+1 949 347 7165",
    "sg:postcode":"92691",
    "sg:province":"CA",
    "sg:website":"www.wetseal.com",
    "wof:name":"Arden B",
    "wof:placetype":"venue"
},
  "geometry": {"coordinates":[-117.669163,33.56058],"type":"Point"}
}