{
  "type": "Feature",
  "properties": {
    "addr:full":"27162 Ashton Cir Lake Forest CA 92630",
    "addr:housenumber":"27162",
    "addr:postcode":"92630",
    "addr:street":"Ashton Cir",
    "iso:country":"US",
    "sg:address":"27162 Ashton Cir",
    "sg:city":"Lake Forest",
    "sg:classifiers":[
        {
            "category":"Building & Trades",
            "subcategory":"Construction",
            "type":"Services"
        }
    ],
    "sg:phone":"+1 951 371 7401",
    "sg:postcode":"92630",
    "sg:province":"CA",
    "sg:tags":[
        "home",
        "builder"
    ],
    "wof:name":"Custom Design Construction",
    "wof:placetype":"venue"
},
  "geometry": {"coordinates":[-117.65672000000001,33.655515],"type":"Point"}
}