{
  "type": "Feature",
  "properties": {
    "addr:full":"3275 Stone Dr Finley CA 95435",
    "addr:housenumber":"3275",
    "addr:postcode":"95435",
    "addr:street":"Stone Dr",
    "iso:country":"US",
    "sg:address":"3275 Stone Dr",
    "sg:city":"Finley",
    "sg:classifiers":[
        {
            "category":"Wholesale",
            "subcategory":"Fruits & Vegetables",
            "type":"Manufacturing & Wholesale Goods"
        }
    ],
    "sg:phone":"+1 707 263 7327",
    "sg:postcode":"95435",
    "sg:province":"CA",
    "sg:tags":[
        "shipper"
    ],
    "wof:name":"Scully Packing Co",
    "wof:placetype":"venue"
},
  "geometry": {"coordinates":[-122.87546500000001,39.008105],"type":"Point"}
}