{
  "type": "Feature",
  "properties": {
    "addr:full":"18131 Valley Blvd Bloomington CA 92316",
    "addr:housenumber":"18131",
    "addr:postcode":"92316",
    "addr:street":"Valley Blvd",
    "iso:country":"US",
    "sg:address":"18131 Valley Blvd",
    "sg:city":"Bloomington",
    "sg:classifiers":[
        {
            "category":"Wholesale",
            "subcategory":"Auto Parts",
            "type":"Manufacturing & Wholesale Goods"
        }
    ],
    "sg:phone":"+1 909 873 2150",
    "sg:postcode":"92316",
    "sg:province":"CA",
    "sg:tags":[
        "speedometer"
    ],
    "wof:name":"Valley Speedo & Tach Inc",
    "wof:placetype":"venue"
},
  "geometry": {"coordinates":[-117.40786199999999,34.070373],"type":"Point"}
}