{
  "type": "Feature",
  "properties": {
    "iso:country":"US",
    "sg:address":"704 N Harbor Blvd",
    "sg:city":"Fullerton",
    "sg:classifiers":[
        {
            "category":"Health Services",
            "subcategory":"Doctor",
            "type":"Services"
        },
        {
            "category":"Health Services",
            "subcategory":"Podiatrist",
            "type":"Services"
        }
    ],
    "sg:phone":"+1 714 525 0225",
    "sg:postcode":"92832",
    "sg:province":"CA",
    "sg:tags":[
        "physician",
        "surgeons"
    ],
    "wof:name":"Serbin Martin E DPM",
    "wof:placetype":"venue"
},
  "geometry": {"coordinates":[-117.924004,33.876701],"type":"Point"}
}