{
  "type": "Feature",
  "properties": {
    "iso:country":"US",
    "sg:address":"4704 Gage Avenue",
    "sg:city":"Bell",
    "sg:classifiers":[
        {
            "category":"Shopping",
            "subcategory":"Florist",
            "type":"Retail Goods"
        }
    ],
    "sg:phone":"+1 323 562 4647",
    "sg:postcode":"90201",
    "sg:province":"CA",
    "sg:website":"www.letyscityofbellflorist.com",
    "wof:name":"Lety's City of Bell Florist",
    "wof:placetype":"venue"
},
  "geometry": {"coordinates":[-118.182349,33.97741],"type":"Point"}
}