{
  "type": "Feature",
  "properties": {
    "iso:country":"US",
    "sg:address":"10112 Fair Oaks Blvd",
    "sg:city":"Fair Oaks",
    "sg:classifiers":[
        {
            "category":"Professional",
            "subcategory":"Engineering",
            "type":"Services"
        }
    ],
    "sg:phone":"+1 916 965 6700",
    "sg:postcode":"95628",
    "sg:province":"CA",
    "sg:tags":[
        "engineer"
    ],
    "wof:name":"Integrated Recycling Inc",
    "wof:placetype":"venue"
},
  "geometry": {"coordinates":[-121.270094,38.642036],"type":"Point"}
}