{
  "type": "Feature",
  "properties": {
    "addr:full":"370 M St Crescent City CA 95531",
    "addr:housenumber":"370",
    "addr:postcode":"95531",
    "addr:street":"M St Crescent",
    "iso:country":"US",
    "sg:address":"370 M St",
    "sg:city":"Crescent City",
    "sg:classifiers":[
        {
            "category":"Restaurant",
            "type":"Food & Drink"
        }
    ],
    "sg:menulink":"http://www.allmenus.com/ca/crescent-city/213221-taco-bell/menu/",
    "sg:phone":"+1 707 465 3560",
    "sg:postcode":"95531",
    "sg:province":"CA",
    "sg:tags":[
        "mexican"
    ],
    "wof:name":"Taco Bell",
    "wof:placetype":"venue"
},
  "geometry": {"coordinates":[-124.193834,41.755062],"type":"Point"}
}