{
  "type": "Feature",
  "properties": {
    "iso:country":"US",
    "sg:address":"12725 Center Court Dr S",
    "sg:city":"Cerritos",
    "sg:classifiers":[
        {
            "category":"Shopping",
            "subcategory":"Gifts & Souvenirs",
            "type":"Retail Goods"
        }
    ],
    "sg:phone":"+1 562 809 8128",
    "sg:postcode":"90703",
    "sg:province":"CA",
    "sg:tags":[
        "shop"
    ],
    "wof:name":"Isle Of Gifts",
    "wof:placetype":"venue"
},
  "geometry": {"coordinates":[-118.059622,33.868267],"type":"Point"}
}