{
  "type": "Feature",
  "properties": {
    "addr:full":"270 Bristol Street Costa Mesa CA 92626",
    "addr:housenumber":"270",
    "addr:postcode":"92626",
    "addr:street":"Bristol Street",
    "iso:country":"US",
    "sg:address":"270 Bristol Street",
    "sg:city":"Costa Mesa",
    "sg:classifiers":[
        {
            "category":"Restaurant",
            "type":"Food & Drink"
        }
    ],
    "sg:phone":"+1 714 966 0855",
    "sg:postcode":"92626",
    "sg:province":"CA",
    "wof:name":"Teriyaki Time",
    "wof:placetype":"venue"
},
  "geometry": {"coordinates":[-117.882997,33.6673],"type":"Point"}
}