{
  "type": "Feature",
  "properties": {
    "addr:full":"2908 Oregon Ct Ste G1 Torrance CA 90503",
    "addr:housenumber":"2908",
    "addr:postcode":"90503",
    "addr:street":"Oregon Ct Ste G1",
    "iso:country":"US",
    "sg:address":"2908 Oregon Ct Ste G1",
    "sg:city":"Torrance",
    "sg:classifiers":[
        {
            "category":"Professional",
            "type":"Services"
        }
    ],
    "sg:phone":"+1 310 755 6780",
    "sg:postcode":"90503",
    "sg:province":"CA",
    "wof:name":"Wildfire",
    "wof:placetype":"venue"
},
  "geometry": {"coordinates":[-118.338886,33.845938],"type":"Point"}
}