{
  "type": "Feature",
  "properties": {
    "addr:full":"2200 E 4th St Los Angeles CA 90033",
    "addr:housenumber":"2200",
    "addr:postcode":"90033",
    "addr:street":"E 4Th St",
    "iso:country":"US",
    "sg:address":"2200 E 4th St",
    "sg:city":"Los Angeles",
    "sg:classifiers":[
        {
            "category":"Food & Beverages",
            "subcategory":"Groceries & Convenience Stores",
            "type":"Retail Goods"
        }
    ],
    "sg:phone":"+1 323 269 6444",
    "sg:postcode":"90033",
    "sg:province":"CA",
    "wof:name":"Sun Market",
    "wof:placetype":"venue"
},
  "geometry": {"coordinates":[-118.21399700000001,34.041599],"type":"Point"}
}