{
  "type": "Feature",
  "properties": {
    "addr:full":"8001 Othello Ave San Diego CA 92111",
    "addr:housenumber":"8001",
    "addr:postcode":"92111",
    "addr:street":"Othello Ave",
    "iso:country":"US",
    "sg:address":"8001 Othello Ave",
    "sg:city":"San Diego",
    "sg:classifiers":[
        {
            "category":"Shopping",
            "subcategory":"Department Store",
            "type":"Retail Goods"
        }
    ],
    "sg:phone":"+1 858 576 1570",
    "sg:postcode":"92111",
    "sg:province":"CA",
    "sg:website":"www.target.com",
    "wof:name":"Target",
    "wof:placetype":"venue"
},
  "geometry": {"coordinates":[-117.150296,32.816268],"type":"Point"}
}