{
  "type": "Feature",
  "properties": {
    "iso:country":"US",
    "sg:address":"32640 Ontario Way",
    "sg:city":"Lake Elsinore",
    "sg:classifiers":[
        {
            "category":"Professional",
            "subcategory":"Employment Agencies",
            "type":"Services"
        }
    ],
    "sg:phone":"+1 951 609 1415",
    "sg:postcode":"92530",
    "sg:province":"CA",
    "wof:name":"Thunder Staffing and Business Development",
    "wof:placetype":"venue"
},
  "geometry": {"coordinates":[-117.31497299999999,33.624113],"type":"Point"}
}