{
  "type": "Feature",
  "properties": {
    "iso:country":"US",
    "sg:address":"11100 Valley Blvd",
    "sg:city":"El Monte",
    "sg:classifiers":[
        {
            "category":"Manufacturing",
            "subcategory":"Tools & Machinery",
            "type":"Manufacturing & Wholesale Goods"
        },
        {
            "category":"Wholesale",
            "subcategory":"Electrical",
            "type":"Manufacturing & Wholesale Goods"
        }
    ],
    "sg:phone":"+1 626 442 2340",
    "sg:postcode":"91731",
    "sg:province":"CA",
    "sg:tags":[
        "equipment",
        "mfg",
        "electric",
        "supply"
    ],
    "wof:name":"Mitsubishi Electric Power Prod",
    "wof:placetype":"venue"
},
  "geometry": {"coordinates":[-118.032456,34.072597],"type":"Point"}
}