{
  "type": "Feature",
  "properties": {
    "addr:full":"930 S State St Hemet CA 92543",
    "addr:housenumber":"930",
    "addr:postcode":"92543",
    "addr:street":"S State St",
    "iso:country":"US",
    "sg:address":"930 S State St",
    "sg:city":"Hemet",
    "sg:classifiers":[
        {
            "category":"Social Services",
            "type":"Services"
        }
    ],
    "sg:phone":"+1 951 765 6955",
    "sg:postcode":"92543",
    "sg:province":"CA",
    "sg:tags":[
        "guidance",
        "child"
    ],
    "sg:website":"www.cflckids.org",
    "wof:name":"California Family Life Ctr",
    "wof:placetype":"venue"
},
  "geometry": {"coordinates":[-116.971467,33.729961],"type":"Point"}
}