{
  "type": "Feature",
  "properties": {
    "addr:full":"3220 M Street Sacramento CA 95816",
    "addr:housenumber":"3220",
    "addr:postcode":"95816",
    "addr:street":"M Street",
    "iso:country":"US",
    "sg:address":"3220 M Street",
    "sg:city":"Sacramento",
    "sg:classifiers":[
        {
            "category":"Professional",
            "subcategory":"Lawyer & Legal Services",
            "type":"Services"
        }
    ],
    "sg:phone":"+1 916 492 6555",
    "sg:postcode":"95816",
    "sg:province":"CA",
    "sg:website":"theisonlawgroup.com",
    "wof:name":"Ison Law Group the-Sacramento",
    "wof:placetype":"venue"
},
  "geometry": {"coordinates":[-121.46438499999999,38.569227],"type":"Point"}
}