{
  "type": "Feature",
  "properties": {
    "addr:full":"1391 Denton Way Redding CA 96002",
    "addr:housenumber":"1391",
    "addr:postcode":"96002",
    "addr:street":"Denton Way",
    "iso:country":"US",
    "sg:address":"1391 Denton Way",
    "sg:city":"Redding",
    "sg:classifiers":[
        {
            "category":"Health Services",
            "subcategory":"Nursing And Care Facility",
            "type":"Services"
        }
    ],
    "sg:phone":"+1 530 222 2149",
    "sg:postcode":"96002",
    "sg:province":"CA",
    "sg:tags":[
        "residential"
    ],
    "wof:name":"Monika's Residential Care",
    "wof:placetype":"venue"
},
  "geometry": {"coordinates":[-122.346678,40.547048],"type":"Point"}
}