{
  "type": "Feature",
  "properties": {
    "iso:country":"US",
    "sg:address":"625 Creston Rd",
    "sg:city":"Paso Robles",
    "sg:classifiers":[
        {
            "category":"Banks & Credit Unions",
            "subcategory":"Bank",
            "type":"Services"
        }
    ],
    "sg:phone":"+1 805 237 2000",
    "sg:postcode":"93446",
    "sg:province":"CA",
    "sg:tags":[
        "loan",
        "real estate"
    ],
    "wof:name":"Professional Processing",
    "wof:placetype":"venue"
},
  "geometry": {"coordinates":[-120.67522099999999,35.628271],"type":"Point"}
}