{
  "type": "Feature",
  "properties": {
    "iso:country":"US",
    "sg:address":"3511 Madison St",
    "sg:city":"Riverside",
    "sg:classifiers":[
        {
            "category":"Restaurant",
            "type":"Food & Drink"
        }
    ],
    "sg:phone":"+1 951 637 2411",
    "sg:postcode":"92504",
    "sg:province":"CA",
    "wof:name":"Ho Ho Chinese Food",
    "wof:placetype":"venue"
},
  "geometry": {"coordinates":[-117.405433,33.936543],"type":"Point"}
}