{
  "type": "Feature",
  "properties": {
    "addr:full":"332 Del AMO Fashion Sq Torrance CA 90503",
    "addr:housenumber":"332",
    "addr:postcode":"90503",
    "addr:street":"Del Amo Fashion Sq",
    "iso:country":"US",
    "sg:address":"332 Del AMO Fashion Sq",
    "sg:city":"Torrance",
    "sg:classifiers":[
        {
            "category":"Shopping",
            "subcategory":"Mobile Phones",
            "type":"Retail Goods"
        }
    ],
    "sg:phone":"+1 310 370 0353",
    "sg:postcode":"90503",
    "sg:province":"CA",
    "wof:name":"At & T Wireless Store",
    "wof:placetype":"venue"
},
  "geometry": {"coordinates":[-118.351997,33.8283],"type":"Point"}
}