{
  "type": "Feature",
  "properties": {
    "addr:full":"1833 Oxford Ave Cardiff By Sea CA 92007",
    "addr:housenumber":"1833",
    "addr:postcode":"92007",
    "addr:street":"Oxford Ave",
    "iso:country":"US",
    "sg:address":"1833 Oxford Ave",
    "sg:city":"Cardiff By Sea",
    "sg:classifiers":[
        {
            "category":"Wholesale",
            "subcategory":"Office Equipment",
            "type":"Manufacturing & Wholesale Goods"
        }
    ],
    "sg:phone":"+1 760 753 6021",
    "sg:postcode":"92007",
    "sg:province":"CA",
    "sg:tags":[
        "protection",
        "check",
        "mach"
    ],
    "wof:name":"Secure Payment System",
    "wof:placetype":"venue"
},
  "geometry": {"coordinates":[-117.280452,33.026275],"type":"Point"}
}