{
  "type": "Feature",
  "properties": {
    "addr:full":"1271 Tubbs Ln Calistoga CA 94515",
    "addr:housenumber":"1271",
    "addr:postcode":"94515",
    "addr:street":"Tubbs Ln",
    "iso:country":"US",
    "sg:address":"1271 Tubbs Ln",
    "sg:city":"Calistoga",
    "sg:classifiers":[
        {
            "category":"Farming",
            "subcategory":"Vineyard",
            "type":"Manufacturing & Wholesale Goods"
        }
    ],
    "sg:phone":"+1 707 942 0700",
    "sg:postcode":"94515",
    "sg:province":"CA",
    "sg:tags":[
        "grape"
    ],
    "wof:name":"Alfred Ban",
    "wof:placetype":"venue"
},
  "geometry": {"coordinates":[-122.600568,38.597357],"type":"Point"}
}