{
  "type": "Feature",
  "properties": {
    "iso:country":"US",
    "sg:address":"4551 Eggers Dr",
    "sg:city":"Fremont",
    "sg:classifiers":[
        {
            "category":"Professional",
            "subcategory":"Business Services",
            "type":"Services"
        }
    ],
    "sg:phone":"+1 510 793 4031",
    "sg:postcode":"94536",
    "sg:province":"CA",
    "sg:tags":[
        "interior",
        "consultant",
        "design",
        "decorator"
    ],
    "wof:name":"RMC Interiors Builders Supl",
    "wof:placetype":"venue"
},
  "geometry": {"coordinates":[-122.00183800000001,37.545848],"type":"Point"}
}