{
  "type": "Feature",
  "properties": {
    "addr:full":"5446 E Washington Blvd Los Angeles CA 90040",
    "addr:housenumber":"5446",
    "addr:postcode":"90040",
    "addr:street":"E Washington Blvd",
    "iso:country":"US",
    "sg:address":"5446 E Washington Blvd",
    "sg:city":"Los Angeles",
    "sg:classifiers":[
        {
            "category":"Professional",
            "type":"Services"
        }
    ],
    "sg:phone":"+1 323 728 3566",
    "sg:postcode":"90040",
    "sg:province":"CA",
    "sg:tags":[
        "wood",
        "specialty"
    ],
    "wof:name":"DKL Intertrading Inc",
    "wof:placetype":"venue"
},
  "geometry": {"coordinates":[-118.161993,34.001028],"type":"Point"}
}