{
  "type": "Feature",
  "properties": {
    "iso:country":"US",
    "sg:address":"10499 Merritt St",
    "sg:city":"Castroville",
    "sg:classifiers":[
        {
            "category":"Food & Beverages",
            "subcategory":"Groceries & Convenience Stores",
            "type":"Retail Goods"
        }
    ],
    "sg:phone":"+1 831 632 0280",
    "sg:postcode":"95012",
    "sg:province":"CA",
    "wof:name":"Primavera Market",
    "wof:placetype":"venue"
},
  "geometry": {"coordinates":[-121.760047,36.767399],"type":"Point"}
}