{
  "type": "Feature",
  "properties": {
    "addr:full":"2574 Grass Valley Hwy Auburn CA 95603",
    "addr:housenumber":"2574",
    "addr:postcode":"ca 95603",
    "addr:street":"Grass Valley Hwy",
    "iso:country":"US",
    "sg:address":"2574 Grass Valley Hwy",
    "sg:city":"Auburn",
    "sg:classifiers":[
        {
            "category":"Banks & Credit Unions",
            "subcategory":"Bank",
            "type":"Services"
        }
    ],
    "sg:phone":"+1 530 887 9242",
    "sg:postcode":"95603",
    "sg:province":"CA",
    "sg:tags":[
        "loan",
        "real estate"
    ],
    "wof:name":"Theodore Popson",
    "wof:placetype":"venue"
},
  "geometry": {"coordinates":[-121.09552499999999,38.937929],"type":"Point"}
}