{
  "type": "Feature",
  "properties": {
    "addr:full":"12038 Burbank Blvd Valley Village CA 91607",
    "addr:housenumber":"12038",
    "addr:postcode":"91607",
    "addr:street":"Burbank Blvd",
    "iso:country":"US",
    "sg:address":"12038 Burbank Blvd",
    "sg:city":"Valley Village",
    "sg:classifiers":[
        {
            "category":"Personal",
            "subcategory":"Beauty Salon",
            "type":"Services"
        }
    ],
    "sg:phone":"+1 818 760 1430",
    "sg:postcode":"91607",
    "sg:province":"CA",
    "sg:tags":[
        "nail",
        "manicuring"
    ],
    "wof:name":"Avante Nail Salons",
    "wof:placetype":"venue"
},
  "geometry": {"coordinates":[-118.396004,34.172199],"type":"Point"}
}