{
  "type": "Feature",
  "properties": {
    "iso:country":"US",
    "sg:address":"257 E 4th St",
    "sg:city":"Perris",
    "sg:classifiers":[
        {
            "category":"Retail",
            "subcategory":"Veterinary Services",
            "type":"Services"
        }
    ],
    "sg:phone":"+1 951 657 3139",
    "sg:postcode":"92570",
    "sg:province":"CA",
    "wof:name":"Hicks James F & Associates Dvm",
    "wof:placetype":"venue"
},
  "geometry": {"coordinates":[-117.22501,33.782306],"type":"Point"}
}