{
  "type": "Feature",
  "properties": {
    "iso:country":"US",
    "sg:address":"37313 Hinkley Rd",
    "sg:city":"Hinkley",
    "sg:classifiers":[
        {
            "category":"Organizations",
            "subcategory":"Religious Organization",
            "type":"Services"
        }
    ],
    "sg:phone":"+1 760 253 2247",
    "sg:postcode":"92347",
    "sg:province":"CA",
    "sg:tags":[
        "church"
    ],
    "wof:name":"Hinkley Bible Church",
    "wof:placetype":"venue"
},
  "geometry": {"coordinates":[-117.188851,34.932104],"type":"Point"}
}