{
  "type": "Feature",
  "properties": {
    "addr:full":"850 Eady Ave Calexico CA 92231",
    "addr:housenumber":"850",
    "addr:postcode":"92231",
    "addr:street":"Eady Ave",
    "iso:country":"US",
    "sg:address":"850 Eady Ave",
    "sg:city":"Calexico",
    "sg:classifiers":[
        {
            "category":"Social Services",
            "type":"Services"
        }
    ],
    "sg:phone":"+1 760 357 1264",
    "sg:postcode":"92231",
    "sg:province":"CA",
    "sg:tags":[
        "housing",
        "assistance"
    ],
    "wof:name":"Calexico Resident Management",
    "wof:placetype":"venue"
},
  "geometry": {"coordinates":[-115.510592,32.674799],"type":"Point"}
}