{
  "type": "Feature",
  "properties": {
    "addr:full":"6623 Florence Ave Bell Gardens CA 90201",
    "addr:housenumber":"6623",
    "addr:postcode":"90201",
    "addr:street":"Florence Ave",
    "iso:country":"US",
    "sg:address":"6623 Florence Ave",
    "sg:city":"Bell Gardens",
    "sg:classifiers":[
        {
            "category":"Retail",
            "subcategory":"Repair Shop",
            "type":"Services"
        }
    ],
    "sg:phone":"+1 562 927 0205",
    "sg:postcode":"90201",
    "sg:province":"CA",
    "sg:tags":[
        "reupholstery",
        "furniture"
    ],
    "wof:name":"Gil's Auto Center",
    "wof:placetype":"venue"
},
  "geometry": {"coordinates":[-118.146004,33.962299],"type":"Point"}
}