{
  "type": "Feature",
  "properties": {
    "addr:full":"5521 Holt Blvd Montclair CA 91763",
    "addr:housenumber":"5521",
    "addr:postcode":"91763",
    "addr:street":"Holt Blvd",
    "iso:country":"US",
    "sg:address":"5521 Holt Blvd",
    "sg:city":"Montclair",
    "sg:classifiers":[
        {
            "category":"Retail",
            "subcategory":"Auto Repair",
            "type":"Services"
        }
    ],
    "sg:phone":"+1 909 459 1177",
    "sg:postcode":"91763",
    "sg:province":"CA",
    "sg:tags":[
        "repairing",
        "automobile"
    ],
    "wof:name":"Montclair Test Only Ctr",
    "wof:placetype":"venue"
},
  "geometry": {"coordinates":[-117.68118200000001,34.063225],"type":"Point"}
}