{
  "type": "Feature",
  "properties": {
    "iso:country":"US",
    "sg:address":"16424 Victor St",
    "sg:city":"Victorville",
    "sg:classifiers":[
        {
            "category":"Professional",
            "type":"Services"
        }
    ],
    "sg:phone":"+1 760 951 2414",
    "sg:postcode":"92395",
    "sg:province":"CA",
    "sg:tags":[
        "establishment"
    ],
    "wof:name":"Power House-Deliverance",
    "wof:placetype":"venue"
},
  "geometry": {"coordinates":[-117.305301,34.521801],"type":"Point"}
}