{
  "type": "Feature",
  "properties": {
    "iso:country":"US",
    "sg:address":"3110 Bradshaw Rd",
    "sg:city":"Sacramento",
    "sg:classifiers":[
        {
            "category":"Food & Beverages",
            "subcategory":"Specialty",
            "type":"Retail Goods"
        },
        {
            "category":"Restaurant",
            "type":"Food & Drink"
        }
    ],
    "sg:phone":"+1 916 361 3888",
    "sg:postcode":"95827",
    "sg:province":"CA",
    "sg:tags":[
        "vietnamese"
    ],
    "sg:website":"hoavietonline.com/",
    "wof:name":"Pho Bac Hoa Viet",
    "wof:placetype":"venue"
},
  "geometry": {"coordinates":[-121.33699799999999,38.572399],"type":"Point"}
}