{
  "type": "Feature",
  "properties": {
    "iso:country":"US",
    "sg:address":"575 Dawson Dr",
    "sg:city":"Camarillo",
    "sg:classifiers":[
        {
            "category":"Local Transit",
            "type":"Transportation"
        }
    ],
    "sg:phone":"+1 805 987 8900",
    "sg:postcode":"93012",
    "sg:province":"CA",
    "sg:tags":[
        "limousine"
    ],
    "wof:name":"Suv Limousine Inc",
    "wof:placetype":"venue"
},
  "geometry": {"coordinates":[-119.036596,34.210046],"type":"Point"}
}