{
  "type": "Feature",
  "properties": {
    "iso:country":"US",
    "sg:address":"2009 10th Street",
    "sg:city":"Berkeley",
    "sg:classifiers":[
        {
            "category":"Education",
            "subcategory":"Preschool",
            "type":"Public Place"
        },
        {
            "category":"Education",
            "subcategory":"School",
            "type":"Public Place"
        }
    ],
    "sg:phone":"+1 510 548 4853",
    "sg:postcode":"94710",
    "sg:province":"CA",
    "sg:tags":[
        "elementary"
    ],
    "wof:name":"Berkely YMCA Hs",
    "wof:placetype":"venue"
},
  "geometry": {"coordinates":[-122.29299899999999,37.8685],"type":"Point"}
}