{
  "type": "Feature",
  "properties": {
    "iso:country":"US",
    "sg:address":"4360 Arden Way",
    "sg:city":"Sacramento",
    "sg:classifiers":[
        {
            "category":"Health Services",
            "subcategory":"Dentist",
            "type":"Services"
        }
    ],
    "sg:phone":"+1 916 481 0594",
    "sg:postcode":"95864",
    "sg:province":"CA",
    "wof:name":"Mucci James H DDS",
    "wof:placetype":"venue"
},
  "geometry": {"coordinates":[-121.362661,38.595536],"type":"Point"}
}