{
  "type": "Feature",
  "properties": {
    "addr:full":"143 Ammunition Rd Fallbrook CA 92028",
    "addr:housenumber":"143",
    "addr:postcode":"92028",
    "addr:street":"Ammunition Rd",
    "iso:country":"US",
    "sg:address":"143 Ammunition Rd",
    "sg:city":"Fallbrook",
    "sg:classifiers":[
        {
            "category":"Food & Beverages",
            "subcategory":"Liquor & Beverages",
            "type":"Retail Goods"
        }
    ],
    "sg:phone":"+1 760 728 8622",
    "sg:postcode":"92028",
    "sg:province":"CA",
    "sg:tags":[
        "beer",
        "spirit",
        "wine"
    ],
    "wof:name":"Happy Jug",
    "wof:placetype":"venue"
},
  "geometry": {"coordinates":[-117.251999,33.370998],"type":"Point"}
}