{
  "type": "Feature",
  "properties": {
    "iso:country":"US",
    "sg:address":"1133 Crenshaw Boulevard",
    "sg:city":"Los Angeles",
    "sg:classifiers":[
        {
            "category":"Health Services",
            "subcategory":"Doctor",
            "type":"Services"
        }
    ],
    "sg:phone":"+1 323 456 7890",
    "sg:postcode":"90019",
    "sg:province":"CA",
    "wof:name":"Song Benjamin I MD",
    "wof:placetype":"venue"
},
  "geometry": {"coordinates":[-118.324321,34.051934],"type":"Point"}
}