{
  "type": "Feature",
  "properties": {
    "addr:full":"54751 Wildwood Dr Idyllwild CA 92549",
    "addr:housenumber":"54751",
    "addr:postcode":"92549",
    "addr:street":"Wildwood Dr",
    "iso:country":"US",
    "sg:address":"54751 Wildwood Dr",
    "sg:city":"Idyllwild",
    "sg:classifiers":[
        {
            "category":"Manufacturing",
            "subcategory":"Textiles",
            "type":"Manufacturing & Wholesale Goods"
        }
    ],
    "sg:phone":"+1 951 659 8418",
    "sg:postcode":"92549",
    "sg:province":"CA",
    "sg:tags":[
        "mill",
        "knit",
        "outerwear"
    ],
    "wof:name":"Custom Vintage",
    "wof:placetype":"venue"
},
  "geometry": {"coordinates":[-116.70522699999999,33.741411],"type":"Point"}
}