{
  "type": "Feature",
  "properties": {
    "iso:country":"US",
    "sg:address":"5501 Imhoff Pl",
    "sg:city":"Martinez",
    "sg:classifiers":[
        {
            "category":"Building & Trades",
            "subcategory":"Construction",
            "type":"Services"
        }
    ],
    "sg:phone":"+1 925 682 2299",
    "sg:postcode":"94553",
    "sg:province":"CA",
    "sg:tags":[
        "product",
        "asphalt"
    ],
    "wof:name":"County Asphalt LLC",
    "wof:placetype":"venue"
},
  "geometry": {"coordinates":[-122.070949,37.99876],"type":"Point"}
}