{
  "type": "Feature",
  "properties": {
    "addr:full":"312 N Spring St Los Angeles CA 90012",
    "addr:housenumber":"312",
    "addr:postcode":"90012",
    "addr:street":"N Spring St",
    "iso:country":"US",
    "sg:address":"312 N Spring St",
    "sg:city":"Los Angeles",
    "sg:classifiers":[
        {
            "category":"Government",
            "subcategory":"Office",
            "type":"Public Place"
        }
    ],
    "sg:phone":"+1 213 894 6314",
    "sg:postcode":"90012",
    "sg:province":"CA",
    "wof:name":"Consuelo B Marshall",
    "wof:placetype":"venue"
},
  "geometry": {"coordinates":[-118.241686,34.055749],"type":"Point"}
}