{
  "type": "Feature",
  "properties": {
    "iso:country":"US",
    "sg:address":"327 N K St",
    "sg:city":"Lompoc",
    "sg:classifiers":[
        {
            "category":"Wholesale",
            "subcategory":"Machinery & Supplies",
            "type":"Manufacturing & Wholesale Goods"
        }
    ],
    "sg:phone":"+1 805 735 3520",
    "sg:postcode":"93436",
    "sg:province":"CA",
    "sg:tags":[
        "industrial"
    ],
    "wof:name":"American Industrial Supply",
    "wof:placetype":"venue"
},
  "geometry": {"coordinates":[-120.46175599999999,34.642691],"type":"Point"}
}