{
  "type": "Feature",
  "properties": {
    "addr:full":"1636 Alum Rock Ave San Jose CA 95116",
    "addr:housenumber":"1636",
    "addr:postcode":"95116",
    "addr:street":"Alum Rock Ave",
    "iso:country":"US",
    "sg:address":"1636 Alum Rock Ave",
    "sg:city":"San Jose",
    "sg:classifiers":[
        {
            "category":"Bakery",
            "type":"Food & Drink"
        }
    ],
    "sg:phone":"+1 408 258 2800",
    "sg:postcode":"95116",
    "sg:province":"CA",
    "wof:name":"Padaria Popular",
    "wof:placetype":"venue"
},
  "geometry": {"coordinates":[-121.85727300000001,37.35192],"type":"Point"}
}