{
  "type": "Feature",
  "properties": {
    "addr:full":"816 Maritime St Oakland CA 94607",
    "addr:housenumber":"816",
    "addr:postcode":"94607",
    "addr:street":"Maritime St",
    "iso:country":"US",
    "sg:address":"816 Maritime St",
    "sg:city":"Oakland",
    "sg:classifiers":[
        {
            "category":"Wholesale",
            "subcategory":"Machinery & Supplies",
            "type":"Manufacturing & Wholesale Goods"
        }
    ],
    "sg:phone":"+1 510 465 7637",
    "sg:postcode":"94607",
    "sg:province":"CA",
    "sg:tags":[
        "equipment",
        "material",
        "handling"
    ],
    "wof:name":"Eastbay Forklift Corp",
    "wof:placetype":"venue"
},
  "geometry": {"coordinates":[-122.31442,37.809358],"type":"Point"}
}