{
  "type": "Feature",
  "properties": {
    "addr:full":"2208 Sawtelle Blvd Los Angeles CA 90064",
    "addr:housenumber":"2208",
    "addr:postcode":"90064",
    "addr:street":"Sawtelle Blvd",
    "iso:country":"US",
    "sg:address":"2208 Sawtelle Blvd",
    "sg:city":"Los Angeles",
    "sg:classifiers":[
        {
            "category":"Personal",
            "subcategory":"Beauty Salon",
            "type":"Services"
        }
    ],
    "sg:phone":"+1 310 473 8565",
    "sg:postcode":"90064",
    "sg:province":"CA",
    "wof:name":"Musikawwuong Kamon Mahn",
    "wof:placetype":"venue"
},
  "geometry": {"coordinates":[-118.440034,34.036898],"type":"Point"}
}