{
  "type": "Feature",
  "properties": {
    "addr:full":"8350 Gardendale St Paramount CA 90723",
    "addr:postcode":"8350;90723",
    "addr:street":"Gardendale St",
    "iso:country":"US",
    "sg:address":"8350 Gardendale St",
    "sg:city":"Paramount",
    "sg:classifiers":[
        {
            "category":"Professional",
            "type":"Services"
        }
    ],
    "sg:phone":"+1 562 861 7400",
    "sg:postcode":"90723",
    "sg:province":"CA",
    "wof:name":"Awp International Inc",
    "wof:placetype":"venue"
},
  "geometry": {"coordinates":[-118.151707,33.914885],"type":"Point"}
}