{
  "type": "Feature",
  "properties": {
    "addr:full":"9640 Encino Ave Northridge CA 91325",
    "addr:housenumber":"9640",
    "addr:postcode":"91325",
    "addr:street":"Encino Ave",
    "iso:country":"US",
    "sg:address":"9640 Encino Ave",
    "sg:city":"Northridge",
    "sg:classifiers":[
        {
            "category":"Professional",
            "subcategory":"Advertising",
            "type":"Services"
        }
    ],
    "sg:phone":"+1 818 610 2600",
    "sg:postcode":"91325",
    "sg:province":"CA",
    "sg:tags":[
        "distribution"
    ],
    "wof:name":"K M Distr",
    "wof:placetype":"venue"
},
  "geometry": {"coordinates":[-118.515467,34.24656],"type":"Point"}
}