{
  "type": "Feature",
  "properties": {
    "iso:country":"US",
    "sg:address":"920 Fesler St",
    "sg:city":"El Cajon",
    "sg:classifiers":[
        {
            "category":"Manufacturing",
            "subcategory":"Building Materials",
            "type":"Manufacturing & Wholesale Goods"
        }
    ],
    "sg:phone":"+1 619 562 3343",
    "sg:postcode":"92020",
    "sg:province":"CA",
    "sg:tags":[
        "mfg",
        "wood",
        "cabinet"
    ],
    "wof:name":"J & J Cabinets",
    "wof:placetype":"venue"
},
  "geometry": {"coordinates":[-116.97125800000001,32.808858],"type":"Point"}
}