{
  "type": "Feature",
  "properties": {
    "addr:full":"1903 E Terrace Ave Fresno CA 93703",
    "addr:housenumber":"1903",
    "addr:postcode":"93703",
    "addr:street":"E Terrace Ave",
    "iso:country":"US",
    "sg:address":"1903 E Terrace Ave",
    "sg:city":"Fresno",
    "sg:classifiers":[
        {
            "category":"Social Services",
            "subcategory":"Child Care",
            "type":"Services"
        }
    ],
    "sg:phone":"+1 559 227 2255",
    "sg:postcode":"93703",
    "sg:province":"CA",
    "wof:name":"Wee Care Day Care",
    "wof:placetype":"venue"
},
  "geometry": {"coordinates":[-119.78604900000001,36.773246],"type":"Point"}
}