{
  "type": "Feature",
  "properties": {
    "iso:country":"US",
    "sg:address":"1501 W Willow St",
    "sg:city":"Long Beach",
    "sg:classifiers":[
        {
            "category":"Building & Trades",
            "subcategory":"Construction",
            "type":"Services"
        }
    ],
    "sg:phone":"+1 562 427 8677",
    "sg:postcode":"90810",
    "sg:province":"CA",
    "sg:tags":[
        "contractor"
    ],
    "wof:name":"C H Decktel Development Inc",
    "wof:placetype":"venue"
},
  "geometry": {"coordinates":[-118.213269,33.804379],"type":"Point"}
}