{
  "type": "Feature",
  "properties": {
    "iso:country":"US",
    "sg:address":"8660 Rio San Diego Drive",
    "sg:city":"San Diego",
    "sg:classifiers":[
        {
            "category":"Restaurant",
            "type":"Food & Drink"
        }
    ],
    "sg:phone":"+1 619 291 1547",
    "sg:postcode":"92108",
    "sg:province":"CA",
    "wof:name":"Anthony's Express",
    "wof:placetype":"venue"
},
  "geometry": {"coordinates":[-117.14279500000001,32.775311],"type":"Point"}
}