{
  "type": "Feature",
  "properties": {
    "addr:full":"1799 Rustin Ave Riverside CA 92507",
    "addr:housenumber":"1799",
    "addr:postcode":"92507",
    "addr:street":"Rustin Ave",
    "iso:country":"US",
    "sg:address":"1799 Rustin Ave",
    "sg:city":"Riverside",
    "sg:classifiers":[
        {
            "category":"Manufacturing",
            "subcategory":"Tools & Machinery",
            "type":"Manufacturing & Wholesale Goods"
        },
        {
            "category":"Wholesale",
            "subcategory":"Home Furnishings",
            "type":"Manufacturing & Wholesale Goods"
        }
    ],
    "sg:phone":"+1 951 682 9600",
    "sg:postcode":"92507",
    "sg:province":"CA",
    "sg:tags":[
        "lamp",
        "fixtures-wholesale",
        "lighting",
        "shade",
        "shades-wholesale",
        "manufacturer"
    ],
    "wof:name":"Candle Lamp Company",
    "wof:placetype":"venue"
},
  "geometry": {"coordinates":[-117.335503,33.996017],"type":"Point"}
}