{
  "type": "Feature",
  "properties": {
    "iso:country":"US",
    "sg:address":"2428 Durfee Ave",
    "sg:city":"El Monte",
    "sg:classifiers":[
        {
            "category":"Retail",
            "subcategory":"Auto Repair",
            "type":"Services"
        }
    ],
    "sg:phone":"+1 626 350 6221",
    "sg:postcode":"91732",
    "sg:province":"CA",
    "sg:tags":[
        "repairing",
        "automobile"
    ],
    "wof:name":"Torres Auto Repair",
    "wof:placetype":"venue"
},
  "geometry": {"coordinates":[-118.023256,34.050954],"type":"Point"}
}