{
  "type": "Feature",
  "properties": {
    "iso:country":"US",
    "sg:address":"40040 Castana Ln",
    "sg:city":"Palmdale",
    "sg:classifiers":[
        {
            "category":"Health Services",
            "subcategory":"Health Practitioner",
            "type":"Services"
        }
    ],
    "sg:phone":"+1 661 273 3922",
    "sg:postcode":"93551",
    "sg:province":"CA",
    "sg:tags":[
        "therapist",
        "physical"
    ],
    "wof:name":"Act To Action Inc",
    "wof:placetype":"venue"
},
  "geometry": {"coordinates":[-118.185367,34.609618],"type":"Point"}
}