{
  "type": "Feature",
  "properties": {
    "iso:country":"US",
    "sg:address":"333 Andover Dr",
    "sg:city":"Burbank",
    "sg:classifiers":[
        {
            "category":"Professional",
            "subcategory":"Business Services",
            "type":"Services"
        }
    ],
    "sg:phone":"+1 818 842 0137",
    "sg:postcode":"91504",
    "sg:province":"CA",
    "sg:tags":[
        "broker"
    ],
    "wof:name":"Ups SCS",
    "wof:placetype":"venue"
},
  "geometry": {"coordinates":[-118.321279,34.193916],"type":"Point"}
}