{
  "type": "Feature",
  "properties": {
    "iso:country":"US",
    "sg:address":"1318 Redwood Way",
    "sg:city":"Petaluma",
    "sg:classifiers":[
        {
            "category":"Professional",
            "subcategory":"Management & Consulting",
            "type":"Services"
        }
    ],
    "sg:phone":"+1 707 792 5678",
    "sg:postcode":"94954",
    "sg:province":"CA",
    "sg:tags":[
        "consultant",
        "business"
    ],
    "sg:website":"www.elkinstraining.com",
    "wof:name":"Elkins Training Co",
    "wof:placetype":"venue"
},
  "geometry": {"coordinates":[-122.665605,38.276086],"type":"Point"}
}