{
  "type": "Feature",
  "properties": {
    "addr:full":"6701 White Ln Bakersfield CA 93309",
    "addr:housenumber":"6701",
    "addr:postcode":"93309",
    "addr:street":"White Ln",
    "iso:country":"US",
    "sg:address":"6701 White Ln",
    "sg:city":"Bakersfield",
    "sg:classifiers":[
        {
            "category":"Restaurant",
            "type":"Food & Drink"
        }
    ],
    "sg:menulink":"http://www.allmenus.com/ca/bakersfield/231472-sonic/menu/",
    "sg:phone":"+1 661 827 9100",
    "sg:postcode":"93309",
    "sg:province":"CA",
    "sg:tags":[
        "burger",
        "american"
    ],
    "wof:name":"Sonic",
    "wof:placetype":"venue"
},
  "geometry": {"coordinates":[-119.076685,35.31767],"type":"Point"}
}