{
  "type": "Feature",
  "properties": {
    "iso:country":"US",
    "sg:address":"540 N Santa Cruz Ave",
    "sg:city":"Los Gatos",
    "sg:classifiers":[
        {
            "category":"Personal",
            "subcategory":"Beauty Salon",
            "type":"Services"
        }
    ],
    "sg:phone":"+1 408 395 7260",
    "sg:postcode":"95030",
    "sg:province":"CA",
    "sg:website":"www.delphidayspa.com",
    "wof:name":"Delphi Salon & Day Spa",
    "wof:placetype":"venue"
},
  "geometry": {"coordinates":[-121.978695,37.233367],"type":"Point"}
}