{
  "type": "Feature",
  "properties": {
    "iso:country":"US",
    "sg:address":"2027 Newcastle",
    "sg:city":"Cardiff By The Sea",
    "sg:classifiers":[
        {
            "category":"Government",
            "subcategory":"Post Office",
            "type":"Public Place"
        }
    ],
    "sg:phone":"+1 760 753 4180",
    "sg:postcode":"92007",
    "sg:province":"CA",
    "wof:name":"United States Post Office",
    "wof:placetype":"venue"
},
  "geometry": {"coordinates":[-117.28201300000001,33.022785],"type":"Point"}
}