{
  "type": "Feature",
  "properties": {
    "addr:full":"2543 Manchester Ave Cardiff By The Sea CA 92007",
    "addr:housenumber":"2543",
    "addr:postcode":"92007",
    "addr:street":"Manchester Ave",
    "iso:country":"US",
    "sg:address":"2543 Manchester Ave",
    "sg:city":"Cardiff By The Sea",
    "sg:classifiers":[
        {
            "category":"Wholesale",
            "subcategory":"Machinery & Supplies",
            "type":"Manufacturing & Wholesale Goods"
        }
    ],
    "sg:phone":"+1 760 644 2661",
    "sg:postcode":"92007",
    "sg:province":"CA",
    "sg:tags":[
        "equipment",
        "industrial"
    ],
    "wof:name":"Automation Proffesionals",
    "wof:placetype":"venue"
},
  "geometry": {"coordinates":[-117.27573,33.015102],"type":"Point"}
}