{
  "type": "Feature",
  "properties": {
    "addr:full":"7605 Huntington Ct Bakersfield CA 93308",
    "addr:housenumber":"7605",
    "addr:postcode":"93308",
    "addr:street":"Huntington Ct",
    "iso:country":"US",
    "sg:address":"7605 Huntington Ct",
    "sg:city":"Bakersfield",
    "sg:classifiers":[
        {
            "category":"Real Estate",
            "subcategory":"Architect",
            "type":"Services"
        }
    ],
    "sg:phone":"+1 661 588 8407",
    "sg:postcode":"93308",
    "sg:province":"CA",
    "wof:name":"Michael Dhanens",
    "wof:placetype":"venue"
},
  "geometry": {"coordinates":[-119.086528,35.403056],"type":"Point"}
}