{
  "type": "Feature",
  "properties": {
    "iso:country":"US",
    "sg:address":"3700 Sacramento St",
    "sg:city":"San Francisco",
    "sg:classifiers":[
        {
            "category":"Real Estate",
            "subcategory":"Real Estate Agent",
            "type":"Services"
        }
    ],
    "sg:phone":"+1 415 221 1800",
    "sg:postcode":"94118",
    "sg:province":"CA",
    "wof:name":"Presidio Properties Ltd",
    "wof:placetype":"venue"
},
  "geometry": {"coordinates":[-122.455236,37.787137],"type":"Point"}
}