{
  "type": "Feature",
  "properties": {
    "iso:country":"US",
    "sg:address":"2195 Station Village Way",
    "sg:city":"San Diego",
    "sg:classifiers":[
        {
            "category":"Manufacturing",
            "subcategory":"Retail Goods",
            "type":"Manufacturing & Wholesale Goods"
        }
    ],
    "sg:phone":"+1 619 260 8531",
    "sg:postcode":"92108",
    "sg:province":"CA",
    "sg:tags":[
        "product",
        "mfg"
    ],
    "wof:name":"Inbio Mfg",
    "wof:placetype":"venue"
},
  "geometry": {"coordinates":[-117.142473,32.775017],"type":"Point"}
}