{
  "type": "Feature",
  "properties": {
    "iso:country":"US",
    "sg:address":"115 Sansome St Ste 807",
    "sg:city":"San Francisco",
    "sg:classifiers":[
        {
            "category":"Health Services",
            "subcategory":"Health Practitioner",
            "type":"Services"
        }
    ],
    "sg:phone":"+1 415 310 8370",
    "sg:postcode":"94104",
    "sg:province":"CA",
    "sg:tags":[
        "acupuncture"
    ],
    "wof:name":"Cathy Lew, L.Ac.",
    "wof:placetype":"venue"
},
  "geometry": {"coordinates":[-122.400941,37.791418],"type":"Point"}
}