{
  "type": "Feature",
  "properties": {
    "iso:country":"US",
    "sg:address":"11835 W Olympic Blvd",
    "sg:city":"Los Angeles",
    "sg:classifiers":[
        {
            "category":"Professional",
            "subcategory":"Business Services",
            "type":"Services"
        }
    ],
    "sg:phone":"+1 310 444 1850",
    "sg:postcode":"90064",
    "sg:province":"CA",
    "sg:tags":[
        "trade",
        "fair",
        "show"
    ],
    "sg:website":"www.houstonautoshow.com",
    "wof:name":"Houston Auto Show",
    "wof:placetype":"venue"
},
  "geometry": {"coordinates":[-118.453363,34.032529],"type":"Point"}
}