{
  "type": "Feature",
  "properties": {
    "addr:full":"18008 S Vermont Ave Gardena CA 90248",
    "addr:housenumber":"18008",
    "addr:postcode":"90248",
    "addr:street":"S Vermont Ave",
    "iso:country":"US",
    "sg:address":"18008 S Vermont Ave",
    "sg:city":"Gardena",
    "sg:classifiers":[
        {
            "category":"Retail",
            "subcategory":"Auto Repair",
            "type":"Services"
        }
    ],
    "sg:phone":"+1 310 753 4497",
    "sg:postcode":"90248",
    "sg:province":"CA",
    "sg:tags":[
        "towing"
    ],
    "wof:name":"AAAA Lockout Towing Transport",
    "wof:placetype":"venue"
},
  "geometry": {"coordinates":[-118.290499,33.867354],"type":"Point"}
}