{
  "type": "Feature",
  "properties": {
    "addr:full":"26536 Ruether Ave Ste 612 Santa Clarita CA 91350",
    "addr:housenumber":"26536",
    "addr:postcode":"91350",
    "addr:street":"Ruether Ave Ste 612",
    "iso:country":"US",
    "sg:address":"26536 Ruether Ave Ste 612",
    "sg:city":"Santa Clarita",
    "sg:classifiers":[
        {
            "category":"Retail",
            "subcategory":"Auto Repair",
            "type":"Services"
        }
    ],
    "sg:phone":"+1 661 299 5910",
    "sg:postcode":"91350",
    "sg:province":"CA",
    "wof:name":"Executive Automotive",
    "wof:placetype":"venue"
},
  "geometry": {"coordinates":[-118.501999,34.4123],"type":"Point"}
}