{
  "type": "Feature",
  "properties": {
    "addr:full":"10833 Shoemaker Ave Santa Fe Springs CA 90670",
    "addr:housenumber":"10833",
    "addr:postcode":"90670",
    "addr:street":"Shoemaker Ave",
    "iso:country":"US",
    "sg:address":"10833 Shoemaker Ave",
    "sg:city":"Santa Fe Springs",
    "sg:classifiers":[
        {
            "category":"Freight",
            "type":"Transportation"
        }
    ],
    "sg:phone":"+1 562 946 6002",
    "sg:postcode":"90670",
    "sg:province":"CA",
    "sg:tags":[
        "warehouse"
    ],
    "wof:name":"Cigna",
    "wof:placetype":"venue"
},
  "geometry": {"coordinates":[-118.055285,33.932872],"type":"Point"}
}