{
  "type": "Feature",
  "properties": {
    "addr:full":"132 27th St Chula Vista CA 91911",
    "addr:housenumber":"132",
    "addr:postcode":"91911",
    "addr:street":"27Th St",
    "iso:country":"US",
    "sg:address":"132 27th St",
    "sg:city":"Chula Vista",
    "sg:classifiers":[
        {
            "category":"Government",
            "subcategory":"Office",
            "type":"Public Place"
        }
    ],
    "sg:phone":"+1 619 424 7481",
    "sg:postcode":"91911",
    "sg:province":"CA",
    "sg:tags":[
        "protection",
        "consumer",
        "agency"
    ],
    "wof:name":"Consumer World",
    "wof:placetype":"venue"
},
  "geometry": {"coordinates":[-117.07543800000001,32.593539],"type":"Point"}
}