{
  "type": "Feature",
  "properties": {
    "addr:full":"2540 Charleston St Oakland CA 94602",
    "addr:housenumber":"2540",
    "addr:postcode":"94602",
    "addr:street":"Charleston St",
    "iso:country":"US",
    "sg:address":"2540 Charleston St",
    "sg:city":"Oakland",
    "sg:classifiers":[
        {
            "category":"Education",
            "subcategory":"School",
            "type":"Public Place"
        }
    ],
    "sg:phone":"+1 510 531 7551",
    "sg:postcode":"94602",
    "sg:province":"CA",
    "sg:tags":[
        "child",
        "care",
        "day",
        "social"
    ],
    "wof:name":"East Bay Agency For Children",
    "wof:placetype":"venue"
},
  "geometry": {"coordinates":[-122.202003,37.807201],"type":"Point"}
}