{
  "type": "Feature",
  "properties": {
    "iso:country":"US",
    "sg:address":"23622 Calabasas Rd",
    "sg:city":"Calabasas",
    "sg:classifiers":[
        {
            "category":"Professional",
            "subcategory":"Credit Reporting & Collection",
            "type":"Services"
        }
    ],
    "sg:phone":"+1 818 222 1472",
    "sg:postcode":"91302",
    "sg:province":"CA",
    "sg:tags":[
        "agency"
    ],
    "wof:name":"Info 1",
    "wof:placetype":"venue"
},
  "geometry": {"coordinates":[-118.643176,34.155701],"type":"Point"}
}