{
  "type": "Feature",
  "properties": {
    "iso:country":"US",
    "sg:address":"5375B W Centinela Ave",
    "sg:city":"Los Angeles",
    "sg:classifiers":[
        {
            "category":"Ice Cream",
            "type":"Food & Drink"
        }
    ],
    "sg:phone":"+1 310 338 9513",
    "sg:postcode":"90045",
    "sg:province":"CA",
    "sg:tags":[
        "frozen",
        "yogurt"
    ],
    "sg:website":"www.coldstonecreamery.com",
    "wof:name":"Cold Stone Creamery",
    "wof:placetype":"venue"
},
  "geometry": {"coordinates":[-118.37351700000001,33.977274],"type":"Point"}
}