{
  "type": "Feature",
  "properties": {
    "addr:full":"9300 W Stockton Blvd Elk Grove CA 95758",
    "addr:housenumber":"9300",
    "addr:postcode":"95758",
    "addr:street":"W Stockton Blvd",
    "iso:country":"US",
    "sg:address":"9300 W Stockton Blvd",
    "sg:city":"Elk Grove",
    "sg:classifiers":[
        {
            "category":"Real Estate",
            "subcategory":"Real Estate Agent",
            "type":"Services"
        }
    ],
    "sg:phone":"+1 916 683 9269",
    "sg:postcode":"95758",
    "sg:province":"CA",
    "wof:name":"Jackson Properties",
    "wof:placetype":"venue"
},
  "geometry": {"coordinates":[-121.39328399999999,38.418082],"type":"Point"}
}