{
  "type": "Feature",
  "properties": {
    "iso:country":"US",
    "sg:address":"411 E Huntington Dr",
    "sg:city":"Arcadia",
    "sg:classifiers":[
        {
            "category":"Wholesale",
            "subcategory":"Machinery & Supplies",
            "type":"Manufacturing & Wholesale Goods"
        }
    ],
    "sg:phone":"+1 626 445 7503",
    "sg:postcode":"91006",
    "sg:province":"CA",
    "sg:tags":[
        "equipment",
        "establishment"
    ],
    "wof:name":"Lee International Beauty Group",
    "wof:placetype":"venue"
},
  "geometry": {"coordinates":[-118.021791,34.140243],"type":"Point"}
}