{
  "type": "Feature",
  "properties": {
    "iso:country":"US",
    "sg:address":"4682 Iowa St",
    "sg:city":"San Diego",
    "sg:classifiers":[
        {
            "category":"Manufacturing",
            "subcategory":"Tools & Machinery",
            "type":"Manufacturing & Wholesale Goods"
        }
    ],
    "sg:phone":"+1 619 283 3193",
    "sg:postcode":"92116",
    "sg:province":"CA",
    "sg:tags":[
        "process",
        "industrial"
    ],
    "sg:website":"www.sigmasystems.com",
    "wof:name":"Sigma Systems Corp",
    "wof:placetype":"venue"
},
  "geometry": {"coordinates":[-117.12611699999999,32.761876],"type":"Point"}
}