{
  "type": "Feature",
  "properties": {
    "iso:country":"US",
    "sg:address":"7484 Monterey St",
    "sg:city":"Gilroy",
    "sg:classifiers":[
        {
            "category":"Restaurant",
            "type":"Food & Drink"
        }
    ],
    "sg:phone":"+1 408 847 8812",
    "sg:postcode":"95020",
    "sg:province":"CA",
    "wof:name":"Carnitas Michoacan",
    "wof:placetype":"venue"
},
  "geometry": {"coordinates":[-121.568783,37.006996],"type":"Point"}
}