{
  "type": "Feature",
  "properties": {
    "addr:full":"15437 Anacapa Rd Victorville CA 92392",
    "addr:housenumber":"15437",
    "addr:postcode":"92392",
    "addr:street":"Anacapa Rd",
    "iso:country":"US",
    "sg:address":"15437 Anacapa Rd",
    "sg:city":"Victorville",
    "sg:classifiers":[
        {
            "category":"Real Estate",
            "subcategory":"Real Estate Agent",
            "type":"Services"
        }
    ],
    "sg:phone":"+1 760 962 0069",
    "sg:postcode":"92392",
    "sg:province":"CA",
    "wof:name":"New Millennium Discount Realty",
    "wof:placetype":"venue"
},
  "geometry": {"coordinates":[-117.32867899999999,34.504625],"type":"Point"}
}