{
  "type": "Feature",
  "properties": {
    "addr:full":"1035 5th St Ste A Monterey CA 93940",
    "addr:housenumber":"1035",
    "addr:postcode":"93940",
    "addr:street":"5Th St Ste A",
    "iso:country":"US",
    "sg:address":"1035 5th St Ste A",
    "sg:city":"Monterey",
    "sg:classifiers":[
        {
            "category":"Banks & Credit Unions",
            "subcategory":"Bank",
            "type":"Services"
        }
    ],
    "sg:phone":"+1 650 508 0300",
    "sg:postcode":"93940",
    "sg:province":"CA",
    "wof:name":"Provident Central Credit Union",
    "wof:placetype":"venue"
},
  "geometry": {"coordinates":[-121.88226899999999,36.596061],"type":"Point"}
}