{
  "type": "Feature",
  "properties": {
    "iso:country":"US",
    "sg:address":"510 S Stoneman Ave",
    "sg:city":"Alhambra",
    "sg:classifiers":[
        {
            "category":"Organizations",
            "subcategory":"Religious Organization",
            "type":"Services"
        }
    ],
    "sg:phone":"+1 626 284 7972",
    "sg:postcode":"91801",
    "sg:province":"CA",
    "sg:tags":[
        "church"
    ],
    "wof:name":"Alhambra Christian Ctr",
    "wof:placetype":"venue"
},
  "geometry": {"coordinates":[-118.122349,34.091003],"type":"Point"}
}