{
  "type": "Feature",
  "properties": {
    "iso:country":"US",
    "sg:address":"6771 Cumberland Dr",
    "sg:city":"Huntington Beach",
    "sg:classifiers":[
        {
            "category":"Wholesale",
            "subcategory":"Apparel",
            "type":"Manufacturing & Wholesale Goods"
        }
    ],
    "sg:phone":"+1 949 631 5737",
    "sg:postcode":"92647",
    "sg:province":"CA",
    "sg:tags":[
        "go",
        "clothing"
    ],
    "wof:name":"Sealevel Trading",
    "wof:placetype":"venue"
},
  "geometry": {"coordinates":[-118.010698,33.740931],"type":"Point"}
}