{
  "type": "Feature",
  "properties": {
    "iso:country":"US",
    "sg:address":"112 W 7th St",
    "sg:city":"Oxnard",
    "sg:classifiers":[
        {
            "category":"Restaurant",
            "type":"Food & Drink"
        }
    ],
    "sg:phone":"+1 805 486 9521",
    "sg:postcode":"93030",
    "sg:province":"CA",
    "wof:name":"El Taco De Mexico",
    "wof:placetype":"venue"
},
  "geometry": {"coordinates":[-119.177846,34.194948],"type":"Point"}
}