{
  "type": "Feature",
  "properties": {
    "iso:country":"US",
    "sg:address":"4055 Wilshire Boulevard",
    "sg:city":"Los Angeles",
    "sg:classifiers":[
        {
            "category":"Communications",
            "subcategory":"Newspaper",
            "type":"Services"
        }
    ],
    "sg:phone":"+1 213 365 1423",
    "sg:postcode":"90010",
    "sg:province":"CA",
    "sg:tags":[
        "print",
        "magazine",
        "medium"
    ],
    "wof:name":"Kim Oak",
    "wof:placetype":"venue"
},
  "geometry": {"coordinates":[-118.315915,34.061723],"type":"Point"}
}