{
  "type": "Feature",
  "properties": {
    "iso:country":"US",
    "sg:address":"5920 14th St",
    "sg:city":"Sacramento",
    "sg:classifiers":[
        {
            "category":"Building & Trades",
            "subcategory":"Electrical",
            "type":"Services"
        }
    ],
    "sg:phone":"+1 916 271 8893",
    "sg:postcode":"95822",
    "sg:province":"CA",
    "sg:tags":[
        "installation"
    ],
    "wof:name":"H & H Custom Fan Installation",
    "wof:placetype":"venue"
},
  "geometry": {"coordinates":[-121.506594,38.520172],"type":"Point"}
}