{
  "type": "Feature",
  "properties": {
    "addr:full":"670B Pancho Rd Camarillo CA 93012",
    "addr:housenumber":"670b",
    "addr:postcode":"93012",
    "addr:street":"Pancho Rd",
    "iso:country":"US",
    "sg:address":"670B Pancho Rd",
    "sg:city":"Camarillo",
    "sg:classifiers":[
        {
            "category":"Home & Garden",
            "subcategory":"Building Materials",
            "type":"Retail Goods"
        }
    ],
    "sg:phone":"+1 805 388 6319",
    "sg:postcode":"93012",
    "sg:province":"CA",
    "sg:website":"http://www.solarworld-ca.com",
    "wof:name":"Solarworld California",
    "wof:placetype":"venue"
},
  "geometry": {"coordinates":[-119.011786,34.203678],"type":"Point"}
}