{
  "type": "Feature",
  "properties": {
    "addr:full":"3739 El Camino Real Santa Clara CA 95051",
    "addr:housenumber":"3739",
    "addr:postcode":"95051",
    "addr:street":"El Camino Real",
    "iso:country":"US",
    "sg:address":"3739 El Camino Real",
    "sg:city":"Santa Clara",
    "sg:classifiers":[
        {
            "category":"Restaurant",
            "type":"Food & Drink"
        }
    ],
    "sg:phone":"+1 408 248 8433",
    "sg:postcode":"95051",
    "sg:province":"CA",
    "sg:tags":[
        "pakistani",
        "indian"
    ],
    "sg:website":"shanrestaurant.com/",
    "wof:name":"Shan II",
    "wof:placetype":"venue"
},
  "geometry": {"coordinates":[-121.99900100000001,37.352402],"type":"Point"}
}