{
  "type": "Feature",
  "properties": {
    "addr:full":"446 S Yucca Ave Rialto CA 92376",
    "addr:housenumber":"446",
    "addr:postcode":"92376",
    "addr:street":"S Yucca Ave",
    "iso:country":"US",
    "sg:address":"446 S Yucca Ave",
    "sg:city":"Rialto",
    "sg:classifiers":[
        {
            "category":"Freight",
            "type":"Transportation"
        }
    ],
    "sg:phone":"+1 909 877 6926",
    "sg:postcode":"92376",
    "sg:province":"CA",
    "sg:tags":[
        "trucking"
    ],
    "wof:name":"Lazer Truck Lines Inc",
    "wof:placetype":"venue"
},
  "geometry": {"coordinates":[-117.382458,34.093085],"type":"Point"}
}