{
  "type": "Feature",
  "properties": {
    "iso:country":"US",
    "sg:address":"1004 E 2nd St",
    "sg:city":"Calexico",
    "sg:classifiers":[
        {
            "category":"Wholesale",
            "subcategory":"Electrical",
            "type":"Manufacturing & Wholesale Goods"
        }
    ],
    "sg:phone":"+1 760 357 6747",
    "sg:postcode":"92231",
    "sg:province":"CA",
    "sg:tags":[
        "electric",
        "motor"
    ],
    "wof:name":"Electric Motors & Control",
    "wof:placetype":"venue"
},
  "geometry": {"coordinates":[-115.483934,32.666613],"type":"Point"}
}