{
  "type": "Feature",
  "properties": {
    "addr:full":"13857 York Ave Poway CA 92064",
    "addr:housenumber":"13857",
    "addr:postcode":"ca 92064",
    "addr:street":"York Ave",
    "iso:country":"US",
    "sg:address":"13857 York Ave",
    "sg:city":"Poway",
    "sg:classifiers":[
        {
            "category":"Utilities",
            "subcategory":"Refuse",
            "type":"Services"
        }
    ],
    "sg:phone":"+1 858 679 0275",
    "sg:postcode":"92064",
    "sg:province":"CA",
    "sg:tags":[
        "disposal",
        "waste"
    ],
    "wof:name":"KCCW",
    "wof:placetype":"venue"
},
  "geometry": {"coordinates":[-117.03886799999999,32.966649],"type":"Point"}
}