{
  "type": "Feature",
  "properties": {
    "addr:full":"13251 Ventura Blvd Studio City CA 91604",
    "addr:housenumber":"13251",
    "addr:postcode":"91604",
    "addr:street":"Ventura Blvd",
    "iso:country":"US",
    "sg:address":"13251 Ventura Blvd",
    "sg:city":"Studio City",
    "sg:classifiers":[
        {
            "category":"Retail",
            "subcategory":"Laundry & Dry Cleaning",
            "type":"Services"
        }
    ],
    "sg:phone":"+1 818 995 4474",
    "sg:postcode":"91604",
    "sg:province":"CA",
    "sg:tags":[
        "cleaner"
    ],
    "wof:name":"Century Cleaners",
    "wof:placetype":"venue"
},
  "geometry": {"coordinates":[-118.421997,34.1464],"type":"Point"}
}