{
  "type": "Feature",
  "properties": {
    "addr:full":"1221 Saviers Rd Oxnard CA 93033",
    "addr:housenumber":"1221",
    "addr:postcode":"93033",
    "addr:street":"Saviers Rd",
    "iso:country":"US",
    "sg:address":"1221 Saviers Rd",
    "sg:city":"Oxnard",
    "sg:classifiers":[
        {
            "category":"Bakery",
            "type":"Food & Drink"
        }
    ],
    "sg:phone":"+1 805 486 5922",
    "sg:postcode":"93033",
    "sg:province":"CA",
    "wof:name":"Vanessa Panadderia",
    "wof:placetype":"venue"
},
  "geometry": {"coordinates":[-119.177554,34.187956],"type":"Point"}
}