{
  "type": "Feature",
  "properties": {
    "addr:full":"3171 Petaluma Blvd N Petaluma CA 94952",
    "addr:housenumber":"3171",
    "addr:postcode":"94952",
    "addr:street":"Petaluma Blvd N",
    "iso:country":"US",
    "sg:address":"3171 Petaluma Blvd N",
    "sg:city":"Petaluma",
    "sg:classifiers":[
        {
            "category":"Building & Trades",
            "subcategory":"Landscaping Services",
            "type":"Services"
        }
    ],
    "sg:phone":"+1 707 769 1503",
    "sg:postcode":"94952",
    "sg:province":"CA",
    "sg:tags":[
        "landscape",
        "contractor"
    ],
    "wof:name":"Brad Brown Landscaping & Cmmcl",
    "wof:placetype":"venue"
},
  "geometry": {"coordinates":[-122.657704,38.258429],"type":"Point"}
}