{
  "type": "Feature",
  "properties": {
    "iso:country":"US",
    "sg:address":"1509 S Robertson Blvd",
    "sg:city":"Los Angeles",
    "sg:classifiers":[
        {
            "category":"Restaurant",
            "type":"Food & Drink"
        }
    ],
    "sg:phone":"+1 310 277 8055",
    "sg:postcode":"90035",
    "sg:province":"CA",
    "wof:name":"Koshushi",
    "wof:placetype":"venue"
},
  "geometry": {"coordinates":[-118.384243,34.051673],"type":"Point"}
}