{
  "type": "Feature",
  "properties": {
    "addr:full":"9402 Main St Plymouth CA 95669",
    "addr:housenumber":"9402",
    "addr:postcode":"95669",
    "addr:street":"Main St",
    "iso:country":"US",
    "sg:address":"9402 Main St",
    "sg:city":"Plymouth",
    "sg:phone":"+1 209 245 3463",
    "sg:postcode":"95669",
    "sg:province":"CA",
    "sg:website":"http://www.restauranttaste.com",
    "wof:name":"Taste",
    "wof:placetype":"venue"
},
  "geometry": {"coordinates":[-120.847847,38.481129],"type":"Point"}
}