{
  "type": "Feature",
  "properties": {
    "iso:country":"US",
    "sg:address":"379 Van Ness Ave",
    "sg:city":"Torrance",
    "sg:classifiers":[
        {
            "category":"Wholesale",
            "subcategory":"Toys & Hobbies",
            "type":"Manufacturing & Wholesale Goods"
        }
    ],
    "sg:phone":"+1 310 320 2227",
    "sg:postcode":"90501",
    "sg:province":"CA",
    "sg:tags":[
        "model",
        "supplies-wholesale",
        "manufacturer"
    ],
    "wof:name":"Como Latina",
    "wof:placetype":"venue"
},
  "geometry": {"coordinates":[-118.318613,33.845299],"type":"Point"}
}