{
  "type": "Feature",
  "properties": {
    "addr:full":"14350 Bear Valley Rd Victorville CA 92392",
    "addr:housenumber":"14350",
    "addr:postcode":"92392",
    "addr:street":"Bear Valley Rd",
    "iso:country":"US",
    "sg:address":"14350 Bear Valley Rd",
    "sg:city":"Victorville",
    "sg:classifiers":[
        {
            "category":"Insurance",
            "subcategory":"Insurance Agent",
            "type":"Services"
        }
    ],
    "sg:phone":"+1 760 962 6950",
    "sg:postcode":"92392",
    "sg:province":"CA",
    "wof:name":"West Coast Insurance Svc",
    "wof:placetype":"venue"
},
  "geometry": {"coordinates":[-117.35636100000001,34.470373],"type":"Point"}
}