{
  "type": "Feature",
  "properties": {
    "addr:full":"401 E Marshall St San Gabriel CA 91776",
    "addr:housenumber":"401",
    "addr:postcode":"91776",
    "addr:street":"E Marshall St",
    "iso:country":"US",
    "sg:address":"401 E Marshall St",
    "sg:city":"San Gabriel",
    "sg:classifiers":[
        {
            "category":"Shopping",
            "subcategory":"Party Supplies",
            "type":"Retail Goods"
        }
    ],
    "sg:phone":"+1 626 280 6559",
    "sg:postcode":"91776",
    "sg:province":"CA",
    "sg:website":"www.itsmypartyrentals.net",
    "wof:name":"It's My Party Rentals",
    "wof:placetype":"venue"
},
  "geometry": {"coordinates":[-118.584999,34.553713],"type":"Point"}
}