{
  "type": "Feature",
  "properties": {
    "addr:full":"5959 Florin Rd Sacramento CA 95823",
    "addr:housenumber":"5959",
    "addr:postcode":"95823",
    "addr:street":"Florin Rd",
    "iso:country":"US",
    "sg:address":"5959 Florin Rd",
    "sg:city":"Sacramento",
    "sg:classifiers":[
        {
            "category":"Restaurant",
            "type":"Food & Drink"
        }
    ],
    "sg:phone":"+1 916 422 3027",
    "sg:postcode":"95823",
    "sg:province":"CA",
    "wof:name":"China Express",
    "wof:placetype":"venue"
},
  "geometry": {"coordinates":[-121.434845,38.496153],"type":"Point"}
}