{
  "type": "Feature",
  "properties": {
    "addr:full":"158 W Gabilan St Salinas CA 93901",
    "addr:housenumber":"158",
    "addr:postcode":"93901",
    "addr:street":"W Gabilan St",
    "iso:country":"US",
    "sg:address":"158 W Gabilan St",
    "sg:city":"Salinas",
    "sg:classifiers":[
        {
            "category":"Banks & Credit Unions",
            "subcategory":"Investment Brokerage",
            "type":"Services"
        }
    ],
    "sg:phone":"+1 831 758 1575",
    "sg:postcode":"93901",
    "sg:province":"CA",
    "sg:tags":[
        "advisory",
        "financial"
    ],
    "sg:website":"www.andresenassoc.com",
    "wof:name":"Andresen & Assoc",
    "wof:placetype":"venue"
},
  "geometry": {"coordinates":[-121.660011,36.675072],"type":"Point"}
}