{
  "type": "Feature",
  "properties": {
    "addr:full":"2315 Stockton Blvd Sacramento CA 95817",
    "addr:housenumber":"2315",
    "addr:postcode":"95817",
    "addr:street":"Stockton Blvd",
    "iso:country":"US",
    "sg:address":"2315 Stockton Blvd",
    "sg:city":"Sacramento",
    "sg:classifiers":[
        {
            "category":"Health Services",
            "subcategory":"Doctor",
            "type":"Services"
        }
    ],
    "sg:phone":"+1 916 703 5200",
    "sg:postcode":"95817",
    "sg:province":"CA",
    "sg:tags":[
        "physician",
        "surgeon",
        "neurology",
        "surgeons"
    ],
    "wof:name":"Rudolph J Schrot Md Neurologic",
    "wof:placetype":"venue"
},
  "geometry": {"coordinates":[-121.45715300000001,38.553982],"type":"Point"}
}