{
  "type": "Feature",
  "properties": {
    "iso:country":"US",
    "sg:address":"15 Poco Way",
    "sg:city":"American Canyon",
    "sg:classifiers":[
        {
            "category":"Organizations",
            "subcategory":"Religious Organization",
            "type":"Services"
        }
    ],
    "sg:phone":"+1 707 643 9532",
    "sg:postcode":"94503",
    "sg:province":"CA",
    "sg:tags":[
        "church"
    ],
    "wof:name":"True Vine Community Church",
    "wof:placetype":"venue"
},
  "geometry": {"coordinates":[-122.25632,38.176842],"type":"Point"}
}