{
  "type": "Feature",
  "properties": {
    "addr:full":"1507 King St Santa Cruz CA 95060",
    "addr:housenumber":"1507",
    "addr:postcode":"95060",
    "addr:street":"King St",
    "iso:country":"US",
    "sg:address":"1507 King St",
    "sg:city":"Santa Cruz",
    "sg:classifiers":[
        {
            "category":"Professional",
            "subcategory":"Art Services",
            "type":"Services"
        }
    ],
    "sg:phone":"+1 831 460 9772",
    "sg:postcode":"95060",
    "sg:province":"CA",
    "sg:tags":[
        "photographer"
    ],
    "wof:name":"Ess & Ess",
    "wof:placetype":"venue"
},
  "geometry": {"coordinates":[-122.04541399999999,36.96545],"type":"Point"}
}