{
  "type": "Feature",
  "properties": {
    "iso:country":"US",
    "sg:address":"3051 Browns Ln",
    "sg:city":"Soquel",
    "sg:classifiers":[
        {
            "category":"Food & Beverages",
            "subcategory":"Specialty",
            "type":"Retail Goods"
        }
    ],
    "sg:phone":"+1 831 475 6219",
    "sg:postcode":"95073",
    "sg:province":"CA",
    "sg:tags":[
        "herb"
    ],
    "sg:website":"www.herbal-ahp.org",
    "wof:name":"American Herbal Pharmacopoeia",
    "wof:placetype":"venue"
},
  "geometry": {"coordinates":[-121.948339,36.988255],"type":"Point"}
}