{
  "type": "Feature",
  "properties": {
    "addr:full":"192 S Laurel Ave Upland CA 91786",
    "addr:housenumber":"192",
    "addr:postcode":"91786",
    "addr:street":"S Laurel Ave",
    "iso:country":"US",
    "sg:address":"192 S Laurel Ave",
    "sg:city":"Upland",
    "sg:classifiers":[
        {
            "category":"Real Estate",
            "subcategory":"Real Estate Services",
            "type":"Services"
        },
        {
            "category":"Real Estate",
            "subcategory":"Real Estate Agent",
            "type":"Services"
        }
    ],
    "sg:phone":"+1 909 373 1177",
    "sg:postcode":"91786",
    "sg:province":"CA",
    "sg:tags":[
        "buyer",
        "broker"
    ],
    "wof:name":"Bona Real Est",
    "wof:placetype":"venue"
},
  "geometry": {"coordinates":[-117.652474,34.092504],"type":"Point"}
}