{
  "type": "Feature",
  "properties": {
    "iso:country":"US",
    "sg:address":"2720 Via de la Valle",
    "sg:city":"Del Mar",
    "sg:classifiers":[
        {
            "category":"Sports & Exercise",
            "subcategory":"Gym",
            "type":"Entertainment"
        }
    ],
    "sg:phone":"+1 858 481 2255",
    "sg:postcode":"92014",
    "sg:province":"CA",
    "sg:tags":[
        "club",
        "health",
        "studio",
        "gymnasium"
    ],
    "wof:name":"Fitness Together",
    "wof:placetype":"venue"
},
  "geometry": {"coordinates":[-117.247859,32.981064],"type":"Point"}
}