{
  "type": "Feature",
  "properties": {
    "addr:full":"5506 S Figueroa Street Los Angeles CA 90037",
    "addr:housenumber":"5506",
    "addr:postcode":"90037",
    "addr:street":"S Figueroa Street",
    "iso:country":"US",
    "sg:address":"5506 S Figueroa Street",
    "sg:city":"Los Angeles",
    "sg:classifiers":[
        {
            "category":"Real Estate",
            "subcategory":"Real Estate Operator",
            "type":"Services"
        }
    ],
    "sg:phone":"+1 323 759 2378",
    "sg:postcode":"90037",
    "sg:province":"CA",
    "sg:tags":[
        "apartment"
    ],
    "wof:name":"Richard Hogan Manor",
    "wof:placetype":"venue"
},
  "geometry": {"coordinates":[-118.282661,33.99233],"type":"Point"}
}