{
  "type": "Feature",
  "properties": {
    "addr:full":"2715 W Jefferson Blvd Los Angeles CA 90018",
    "addr:housenumber":"2715",
    "addr:postcode":"90018",
    "addr:street":"W Jefferson Blvd",
    "iso:country":"US",
    "sg:address":"2715 W Jefferson Blvd",
    "sg:city":"Los Angeles",
    "sg:classifiers":[
        {
            "category":"Home & Garden",
            "subcategory":"Carpets & Floor Coverings",
            "type":"Retail Goods"
        }
    ],
    "sg:phone":"+1 323 944 6422",
    "sg:postcode":"90018",
    "sg:province":"CA",
    "sg:tags":[
        "carpeting"
    ],
    "sg:website":"dayonecarpet.com",
    "wof:name":"Day One Floor Covering",
    "wof:placetype":"venue"
},
  "geometry": {"coordinates":[-118.325435,34.025625],"type":"Point"}
}