{
  "type": "Feature",
  "properties": {
    "iso:country":"US",
    "sg:address":"1350 Bayshore Hwy",
    "sg:city":"Burlingame",
    "sg:classifiers":[
        {
            "category":"Banks & Credit Unions",
            "subcategory":"Bank",
            "type":"Services"
        }
    ],
    "sg:phone":"+1 650 347 8828",
    "sg:postcode":"94010",
    "sg:province":"CA",
    "sg:tags":[
        "loan",
        "real estate"
    ],
    "sg:website":"www.baycalfinancial.com",
    "wof:name":"Baycal Financial Corp",
    "wof:placetype":"venue"
},
  "geometry": {"coordinates":[-122.362077,37.591879],"type":"Point"}
}