{
  "type": "Feature",
  "properties": {
    "addr:full":"1400 Geary Blvd San Francisco CA 94109",
    "addr:housenumber":"1400",
    "addr:postcode":"94109",
    "addr:street":"Geary Blvd",
    "iso:country":"US",
    "sg:address":"1400 Geary Blvd",
    "sg:city":"San Francisco",
    "sg:classifiers":[
        {
            "category":"Social Services",
            "subcategory":"Job Training",
            "type":"Services"
        }
    ],
    "sg:phone":"+1 415 441 9698",
    "sg:postcode":"94109",
    "sg:province":"CA",
    "sg:tags":[
        "rehabilitation"
    ],
    "wof:name":"Rehab Works",
    "wof:placetype":"venue"
},
  "geometry": {"coordinates":[-122.42468700000001,37.785335],"type":"Point"}
}