{
  "type": "Feature",
  "properties": {
    "iso:country":"US",
    "sg:address":"20902 S Brant Ave",
    "sg:city":"Carson",
    "sg:classifiers":[
        {
            "category":"Building & Trades",
            "subcategory":"Plumbing",
            "type":"Services"
        }
    ],
    "sg:phone":"+1 310 618 0830",
    "sg:postcode":"90810",
    "sg:province":"CA",
    "sg:tags":[
        "conditioning",
        "air",
        "system",
        "contractor"
    ],
    "wof:name":"Cooling Mechanical",
    "wof:placetype":"venue"
},
  "geometry": {"coordinates":[-118.225943,33.839199],"type":"Point"}
}