{
  "type": "Feature",
  "properties": {
    "iso:country":"US",
    "sg:address":"14803 Morrison St",
    "sg:city":"Sherman Oaks",
    "sg:classifiers":[
        {
            "category":"Home & Garden",
            "subcategory":"Building Materials",
            "type":"Retail Goods"
        }
    ],
    "sg:phone":"+1 818 986 5383",
    "sg:postcode":"91403",
    "sg:province":"CA",
    "sg:tags":[
        "door",
        "gate",
        "operating",
        "devices"
    ],
    "wof:name":"A Advanced Access Controls",
    "wof:placetype":"venue"
},
  "geometry": {"coordinates":[-118.45738900000001,34.160392],"type":"Point"}
}