{
  "type": "Feature",
  "properties": {
    "iso:country":"US",
    "sg:address":"2430 E Olive Ave",
    "sg:city":"Fresno",
    "sg:classifiers":[
        {
            "category":"Autos & Motor Vehicles",
            "subcategory":"Fuel & Gas Station",
            "type":"Retail Goods"
        }
    ],
    "sg:phone":"+1 559 485 0807",
    "sg:postcode":"93701",
    "sg:province":"CA",
    "sg:tags":[
        "oil"
    ],
    "wof:name":"Valley Gas",
    "wof:placetype":"venue"
},
  "geometry": {"coordinates":[-119.782776,36.757605],"type":"Point"}
}