{
  "type": "Feature",
  "properties": {
    "iso:country":"US",
    "sg:address":"1045 Sansome St",
    "sg:city":"San Francisco",
    "sg:classifiers":[
        {
            "category":"Professional",
            "subcategory":"Art Services",
            "type":"Services"
        }
    ],
    "sg:phone":"+1 415 773 1000",
    "sg:postcode":"94111",
    "sg:province":"CA",
    "sg:tags":[
        "graphic",
        "designer"
    ],
    "sg:website":"www.kkainc.com",
    "wof:name":"Kate Keating & Assoc",
    "wof:placetype":"venue"
},
  "geometry": {"coordinates":[-122.402613,37.79988],"type":"Point"}
}