{
  "type": "Feature",
  "properties": {
    "addr:full":"3007 Bunsen Ave Ventura CA 93003",
    "addr:housenumber":"3007",
    "addr:postcode":"93003",
    "addr:street":"Bunsen Ave",
    "iso:country":"US",
    "sg:address":"3007 Bunsen Ave",
    "sg:city":"Ventura",
    "sg:classifiers":[
        {
            "category":"Shopping",
            "type":"Retail Goods"
        }
    ],
    "sg:phone":"+1 805 643 7747",
    "sg:postcode":"93003",
    "sg:province":"CA",
    "sg:tags":[
        "trophy",
        "medal",
        "award"
    ],
    "wof:name":"T & A Mfg",
    "wof:placetype":"venue"
},
  "geometry": {"coordinates":[-119.20956700000001,34.245387],"type":"Point"}
}