{
  "type": "Feature",
  "properties": {
    "addr:full":"2995 Upton Rd Martinez CA 94553",
    "addr:housenumber":"2995",
    "addr:postcode":"94553",
    "addr:street":"Upton Rd",
    "iso:country":"US",
    "sg:address":"2995 Upton Rd",
    "sg:city":"Martinez",
    "sg:classifiers":[
        {
            "category":"Retail",
            "subcategory":"Animal Services",
            "type":"Services"
        }
    ],
    "sg:phone":"+1 925 228 1206",
    "sg:postcode":"94553",
    "sg:province":"CA",
    "sg:tags":[
        "training",
        "dog"
    ],
    "sg:website":"www.euro-training.com",
    "wof:name":"Euro-Training Kennels",
    "wof:placetype":"venue"
},
  "geometry": {"coordinates":[-122.118594,37.988567],"type":"Point"}
}