{
  "type": "Feature",
  "properties": {
    "iso:country":"US",
    "sg:address":"402 W Broadway Ste 860",
    "sg:city":"San Diego",
    "sg:classifiers":[
        {
            "category":"Professional",
            "subcategory":"Lawyer & Legal Services",
            "type":"Services"
        }
    ],
    "sg:phone":"+1 619 236 8700",
    "sg:postcode":"92101",
    "sg:province":"CA",
    "sg:tags":[
        "personal",
        "injury"
    ],
    "sg:website":"www.injurylawyersofsandiego.com",
    "wof:name":"Laureti & Associates",
    "wof:placetype":"venue"
},
  "geometry": {"coordinates":[-117.166933,32.716251],"type":"Point"}
}