{
  "type": "Feature",
  "properties": {
    "iso:country":"US",
    "sg:address":"434 Galvez St",
    "sg:city":"Stanford",
    "sg:classifiers":[
        {
            "category":"Education",
            "subcategory":"College",
            "type":"Public Place"
        }
    ],
    "sg:phone":"+1 650 723 1754",
    "sg:postcode":"94305",
    "sg:province":"CA",
    "wof:name":"Hoover Institution",
    "wof:placetype":"venue"
},
  "geometry": {"coordinates":[-122.16506800000001,37.42893],"type":"Point"}
}