{
  "type": "Feature",
  "properties": {
    "addr:full":"9430 Warner Ave Ste A Fountain Valley CA 92708",
    "addr:housenumber":"9430",
    "addr:postcode":"92708",
    "addr:street":"Warner Ave Ste A",
    "iso:country":"US",
    "sg:address":"9430 Warner Ave Ste A",
    "sg:city":"Fountain Valley",
    "sg:classifiers":[
        {
            "category":"Education",
            "subcategory":"Preschool",
            "type":"Public Place"
        }
    ],
    "sg:phone":"+1 714 968 7400",
    "sg:postcode":"92708",
    "sg:province":"CA",
    "sg:website":"www.eldoradopreschool.org",
    "wof:name":"El Dorado Preschool of Orange County, Inc",
    "wof:placetype":"venue"
},
  "geometry": {"coordinates":[-117.964355,33.715869],"type":"Point"}
}