{
  "type": "Feature",
  "properties": {
    "iso:country":"US",
    "sg:address":"11719 Clark St",
    "sg:city":"Arcadia",
    "sg:classifiers":[
        {
            "category":"Wholesale",
            "subcategory":"Machinery & Supplies",
            "type":"Manufacturing & Wholesale Goods"
        }
    ],
    "sg:phone":"+1 626 303 8626",
    "sg:postcode":"91006",
    "sg:province":"CA",
    "sg:tags":[
        "bearing"
    ],
    "wof:name":"KCI",
    "wof:placetype":"venue"
},
  "geometry": {"coordinates":[-118.00661700000001,34.10194],"type":"Point"}
}