{
  "type": "Feature",
  "properties": {
    "iso:country":"US",
    "sg:address":"8557 Avenida Costa Sur",
    "sg:city":"San Diego",
    "sg:classifiers":[
        {
            "category":"Home & Garden",
            "subcategory":"Furniture",
            "type":"Retail Goods"
        }
    ],
    "sg:phone":"+1 619 661 1255",
    "sg:postcode":"92154",
    "sg:province":"CA",
    "sg:tags":[
        "store"
    ],
    "wof:name":"Furniture Wholesale",
    "wof:placetype":"venue"
},
  "geometry": {"coordinates":[-116.95906600000001,32.554741],"type":"Point"}
}