{
  "type": "Feature",
  "properties": {
    "iso:country":"US",
    "sg:address":"1445 Bulldog Ln",
    "sg:city":"Fresno",
    "sg:classifiers":[
        {
            "category":"Arts & Performance",
            "subcategory":"Theater",
            "type":"Entertainment"
        }
    ],
    "sg:phone":"+1 559 213 3822",
    "sg:postcode":"93710",
    "sg:province":"CA",
    "sg:tags":[
        "entertainer"
    ],
    "wof:name":"Raw-1 Enterprises Inc",
    "wof:placetype":"venue"
},
  "geometry": {"coordinates":[-119.761791,36.812163],"type":"Point"}
}