{
  "type": "Feature",
  "properties": {
    "iso:country":"US",
    "sg:address":"2934 Lomita Rd",
    "sg:city":"Santa Barbara",
    "sg:classifiers":[
        {
            "category":"Manufacturing",
            "subcategory":"Printing",
            "type":"Manufacturing & Wholesale Goods"
        }
    ],
    "sg:phone":"+1 805 563 2279",
    "sg:postcode":"93105",
    "sg:province":"CA",
    "sg:tags":[
        "book"
    ],
    "wof:name":"Side Door Press",
    "wof:placetype":"venue"
},
  "geometry": {"coordinates":[-119.73115900000001,34.43847],"type":"Point"}
}