{
  "type": "Feature",
  "properties": {
    "iso:country":"US",
    "sg:address":"904 E Washington Ave",
    "sg:city":"El Cajon",
    "sg:classifiers":[
        {
            "category":"Shopping",
            "subcategory":"Florist",
            "type":"Retail Goods"
        }
    ],
    "sg:phone":"+1 619 593 9222",
    "sg:postcode":"92020",
    "sg:province":"CA",
    "wof:name":"Wild Orchid Florist",
    "wof:placetype":"venue"
},
  "geometry": {"coordinates":[-116.948291,32.787731],"type":"Point"}
}