{
  "type": "Feature",
  "properties": {
    "addr:full":"2226 Bush St San Francisco CA 94115",
    "addr:housenumber":"2226",
    "addr:postcode":"94115",
    "addr:street":"Bush St",
    "iso:country":"US",
    "sg:address":"2226 Bush St",
    "sg:city":"San Francisco",
    "sg:classifiers":[
        {
            "category":"Shopping",
            "subcategory":"Clothing, Apparel, & Fashions",
            "type":"Retail Goods"
        },
        {
            "category":"Arts & Performance",
            "subcategory":"Art Gallery",
            "type":"Entertainment"
        }
    ],
    "sg:phone":"+1 888 601 0117",
    "sg:postcode":"94115",
    "sg:province":"CA",
    "sg:tags":[
        "men's",
        "clothing",
        "women's"
    ],
    "sg:website":"www.candystorecollective.com",
    "wof:name":"HELLO by Candystore Collective",
    "wof:placetype":"venue"
},
  "geometry": {"coordinates":[-122.43396799999999,37.786972],"type":"Point"}
}