{
  "type": "Feature",
  "properties": {
    "addr:full":"13031 Newport Ave Tustin CA 92780",
    "addr:housenumber":"13031",
    "addr:postcode":"92780",
    "addr:street":"Newport Ave",
    "iso:country":"US",
    "sg:address":"13031 Newport Ave",
    "sg:city":"Tustin",
    "sg:classifiers":[
        {
            "category":"Real Estate",
            "subcategory":"Real Estate Services",
            "type":"Services"
        }
    ],
    "sg:phone":"+1 714 352 2660",
    "sg:postcode":"92780",
    "sg:province":"CA",
    "sg:tags":[
        "management",
        "property"
    ],
    "wof:name":"Pickford Realty",
    "wof:placetype":"venue"
},
  "geometry": {"coordinates":[-117.811243,33.749376],"type":"Point"}
}