{
  "type": "Feature",
  "properties": {
    "addr:full":"34951 Shadow Wood Dr Yucaipa CA 92399",
    "addr:housenumber":"34951",
    "addr:postcode":"92399",
    "addr:street":"Shadow Wood Dr",
    "iso:country":"US",
    "sg:address":"34951 Shadow Wood Dr",
    "sg:city":"Yucaipa",
    "sg:classifiers":[
        {
            "category":"Building & Trades",
            "subcategory":"Landscaping Services",
            "type":"Services"
        }
    ],
    "sg:phone":"+1 909 877 4616",
    "sg:postcode":"92399",
    "sg:province":"CA",
    "sg:tags":[
        "lawn",
        "maintenance",
        "grounds"
    ],
    "wof:name":"Alpha & Omega Landscaping Svc",
    "wof:placetype":"venue"
},
  "geometry": {"coordinates":[-117.042343,34.053856],"type":"Point"}
}