{
  "type": "Feature",
  "properties": {
    "addr:full":"8885 Venice Boulevard Los Angeles CA 90034",
    "addr:housenumber":"8885",
    "addr:postcode":"90034",
    "addr:street":"Venice Boulevard",
    "iso:country":"US",
    "sg:address":"8885 Venice Boulevard",
    "sg:city":"Los Angeles",
    "sg:classifiers":[
        {
            "category":"Health Services",
            "subcategory":"Doctor",
            "type":"Services"
        }
    ],
    "sg:phone":"+1 310 836 2705",
    "sg:postcode":"90034",
    "sg:province":"CA",
    "sg:tags":[
        "surgeon",
        "cosmetic"
    ],
    "wof:name":"Crown Cosmetic Surgery",
    "wof:placetype":"venue"
},
  "geometry": {"coordinates":[-118.387742,34.029755],"type":"Point"}
}