{
  "type": "Feature",
  "properties": {
    "iso:country":"US",
    "sg:address":"1000 S Walker Ln",
    "sg:city":"Stockton",
    "sg:phone":"+1 209 462 7216",
    "sg:postcode":"95215",
    "sg:province":"CA",
    "sg:tags":[
        "farm"
    ],
    "wof:name":"A Caffese",
    "wof:placetype":"venue"
},
  "geometry": {"coordinates":[-121.221251,37.953171],"type":"Point"}
}