{
  "type": "Feature",
  "properties": {
    "addr:full":"15391 Arrow Blvd Fontana CA 92335",
    "addr:housenumber":"15391",
    "addr:postcode":"92335",
    "addr:street":"Arrow Blvd",
    "iso:country":"US",
    "sg:address":"15391 Arrow Blvd",
    "sg:city":"Fontana",
    "sg:classifiers":[
        {
            "category":"Wholesale",
            "subcategory":"Auto Parts",
            "type":"Manufacturing & Wholesale Goods"
        }
    ],
    "sg:phone":"+1 909 822 3715",
    "sg:postcode":"92335",
    "sg:province":"CA",
    "sg:tags":[
        "automobile"
    ],
    "wof:name":"Epic Auto Dismantling Inc",
    "wof:placetype":"venue"
},
  "geometry": {"coordinates":[-117.471003,34.099186],"type":"Point"}
}