{
  "type": "Feature",
  "properties": {
    "iso:country":"US",
    "sg:address":"304 E Tulare Ave",
    "sg:city":"Tulare",
    "sg:classifiers":[
        {
            "category":"Banks & Credit Unions",
            "subcategory":"Bank",
            "type":"Services"
        }
    ],
    "sg:phone":"+1 559 688 7844",
    "sg:postcode":"93274",
    "sg:province":"CA",
    "sg:tags":[
        "loan"
    ],
    "wof:name":"Farm Credit West",
    "wof:placetype":"venue"
},
  "geometry": {"coordinates":[-119.344825,36.208356],"type":"Point"}
}