{
  "type": "Feature",
  "properties": {
    "iso:country":"US",
    "sg:address":"5163 Eastside Rd",
    "sg:city":"Redding",
    "sg:classifiers":[
        {
            "category":"Building & Trades",
            "subcategory":"Construction",
            "type":"Services"
        }
    ],
    "sg:phone":"+1 530 246 7801",
    "sg:postcode":"96001",
    "sg:province":"CA",
    "sg:tags":[
        "masonry",
        "contractor"
    ],
    "wof:name":"Huber & Burton Inc",
    "wof:placetype":"venue"
},
  "geometry": {"coordinates":[-122.38516,40.543325],"type":"Point"}
}