{
  "type": "Feature",
  "properties": {
    "iso:country":"US",
    "sg:address":"2400 Chanticleer Ave",
    "sg:city":"Santa Cruz",
    "sg:classifiers":[
        {
            "category":"Museum",
            "type":"Entertainment"
        }
    ],
    "sg:phone":"+1 831 475 9600",
    "sg:postcode":"95062",
    "sg:province":"CA",
    "sg:tags":[
        "organization",
        "arts",
        "information"
    ],
    "sg:website":"www.ccscc.org",
    "wof:name":"Cultural Council Of Santa Cruz",
    "wof:placetype":"venue"
},
  "geometry": {"coordinates":[-121.97895,36.983892],"type":"Point"}
}