{
  "type": "Feature",
  "properties": {
    "iso:country":"US",
    "sg:address":"5730 Uplander Way Suite 110",
    "sg:city":"Culver City",
    "sg:classifiers":[
        {
            "category":"Food & Beverages",
            "subcategory":"Meat & Fish",
            "type":"Retail Goods"
        }
    ],
    "sg:phone":"+1 310 410 0603",
    "sg:postcode":"90230",
    "sg:province":"CA",
    "sg:tags":[
        "seafood",
        "market"
    ],
    "sg:website":"www.brightstarfoods.com",
    "wof:name":"Bright Star Foods",
    "wof:placetype":"venue"
},
  "geometry": {"coordinates":[-118.384629,33.986504],"type":"Point"}
}