{
  "type": "Feature",
  "properties": {
    "addr:full":"8111 Foothill Blvd Sunland CA 91040",
    "addr:housenumber":"8111",
    "addr:postcode":"91040",
    "addr:street":"Foothill Blvd",
    "iso:country":"US",
    "sg:address":"8111 Foothill Blvd",
    "sg:city":"Sunland",
    "sg:phone":"+1 818 352 7213",
    "sg:postcode":"91040",
    "sg:province":"CA",
    "wof:name":"Corsica Italian Delicatessen",
    "wof:placetype":"venue"
},
  "geometry": {"coordinates":[-118.31014399999999,34.259665],"type":"Point"}
}