{
  "type": "Feature",
  "properties": {
    "iso:country":"US",
    "sg:address":"8111 Foothill Blvd",
    "sg:city":"Sunland",
    "sg:phone":"+1 818 352 7213",
    "sg:postcode":"91040",
    "sg:province":"CA",
    "wof:name":"Corsica Italian Delicatessen",
    "wof:placetype":"venue"
},
  "geometry": {"coordinates":[-118.310144,34.259665],"type":"Point"}
}