{
  "type": "Feature",
  "properties": {
    "addr:full":"660 El Camino Real Ste 214 Millbrae CA 94030",
    "addr:housenumber":"660",
    "addr:postcode":"94030",
    "addr:street":"El Camino Real Ste 214 Millbrae",
    "iso:country":"US",
    "sg:address":"660 El Camino Real Ste 214",
    "sg:city":"Millbrae",
    "sg:classifiers":[
        {
            "category":"Professional",
            "subcategory":"Lawyer & Legal Services",
            "type":"Services"
        }
    ],
    "sg:phone":"+1 650 588 7700",
    "sg:postcode":"94030",
    "sg:province":"CA",
    "sg:website":"www.samaralaw.com",
    "wof:name":"Majeed S. Samara, Attorney At Law",
    "wof:placetype":"venue"
},
  "geometry": {"coordinates":[-122.39393699999999,37.604192],"type":"Point"}
}