{
  "type": "Feature",
  "properties": {
    "iso:country":"US",
    "sg:address":"1375 Sutter St",
    "sg:city":"San Francisco",
    "sg:classifiers":[
        {
            "category":"Shopping",
            "subcategory":"News",
            "type":"Retail Goods"
        }
    ],
    "sg:phone":"+1 415 354 4000",
    "sg:postcode":"94109",
    "sg:province":"CA",
    "sg:tags":[
        "magazine"
    ],
    "sg:website":"www.prenax.com",
    "wof:name":"Prenax Inc",
    "wof:placetype":"venue"
},
  "geometry": {"coordinates":[-122.42241,37.787423],"type":"Point"}
}