{
  "type": "Feature",
  "properties": {
    "addr:full":"1632 Pacific Ave Stockton CA 95204",
    "addr:housenumber":"1632",
    "addr:postcode":"95204",
    "addr:street":"Pacific Ave",
    "iso:country":"US",
    "sg:address":"1632 Pacific Ave",
    "sg:city":"Stockton",
    "sg:classifiers":[
        {
            "category":"Restaurant",
            "type":"Food & Drink"
        }
    ],
    "sg:menulink":"http://www.allmenus.com/ca/stockton/60103-luus-chicken-bowl/menu/",
    "sg:phone":"+1 209 461 6416",
    "sg:postcode":"95204",
    "sg:province":"CA",
    "sg:tags":[
        "asian",
        "chinese"
    ],
    "wof:name":"Luu's Chicken Bowl",
    "wof:placetype":"venue"
},
  "geometry": {"coordinates":[-121.298528,37.968064],"type":"Point"}
}