{
  "type": "Feature",
  "properties": {
    "iso:country":"US",
    "sg:address":"19161 Jasper Hill Rd",
    "sg:city":"Trabuco Canyon",
    "sg:classifiers":[
        {
            "category":"Professional",
            "subcategory":"Research",
            "type":"Services"
        }
    ],
    "sg:phone":"+1 949 766 0832",
    "sg:postcode":"92679",
    "sg:province":"CA",
    "sg:tags":[
        "development",
        "medical"
    ],
    "wof:name":"Bicer Medical Inc",
    "wof:placetype":"venue"
},
  "geometry": {"coordinates":[-117.637151,33.680788],"type":"Point"}
}