{
  "type": "Feature",
  "properties": {
    "iso:country":"US",
    "sg:address":"5216 Garfield Ave",
    "sg:city":"Sacramento",
    "sg:classifiers":[
        {
            "category":"Social Services",
            "subcategory":"Child Care",
            "type":"Services"
        }
    ],
    "sg:phone":"+1 916 344 5640",
    "sg:postcode":"95841",
    "sg:province":"CA",
    "wof:name":"Deanna's Day Care",
    "wof:placetype":"venue"
},
  "geometry": {"coordinates":[-121.336754,38.661679],"type":"Point"}
}