{
  "type": "Feature",
  "properties": {
    "addr:full":"7401 Morton Ave Ste A Newark CA 94560",
    "addr:housenumber":"7401",
    "addr:postcode":"94560",
    "addr:street":"Morton Ave Ste A",
    "iso:country":"US",
    "sg:address":"7401 Morton Ave Ste A",
    "sg:city":"Newark",
    "sg:classifiers":[
        {
            "category":"Food & Beverages",
            "subcategory":"Groceries & Convenience Stores",
            "type":"Retail Goods"
        }
    ],
    "sg:phone":"+1 510 797 7249",
    "sg:postcode":"94560",
    "sg:province":"CA",
    "wof:name":"Alidoro Gourment Int",
    "wof:placetype":"venue"
},
  "geometry": {"coordinates":[-122.34246400000001,37.519631],"type":"Point"}
}