{
  "type": "Feature",
  "properties": {
    "addr:full":"31500 Camille Dr Fort Bragg CA 95437",
    "addr:housenumber":"31500",
    "addr:postcode":"95437",
    "addr:street":"Camille Dr",
    "iso:country":"US",
    "sg:address":"31500 Camille Dr",
    "sg:city":"Fort Bragg",
    "sg:classifiers":[
        {
            "category":"Restaurant",
            "type":"Food & Drink"
        }
    ],
    "sg:phone":"+1 707 962 0937",
    "sg:postcode":"95437",
    "sg:province":"CA",
    "sg:tags":[
        "caterer"
    ],
    "wof:name":"Gourmet Treat",
    "wof:placetype":"venue"
},
  "geometry": {"coordinates":[-123.781193,39.423413],"type":"Point"}
}