{
  "type": "Feature",
  "properties": {
    "addr:full":"3447 8th Ave Los Angeles CA 90018",
    "addr:housenumber":"3447",
    "addr:postcode":"90018",
    "addr:street":"8Th Ave",
    "iso:country":"US",
    "sg:address":"3447 8th Ave",
    "sg:city":"Los Angeles",
    "sg:classifiers":[
        {
            "category":"Shopping",
            "subcategory":"Clothing, Apparel, & Fashions",
            "type":"Retail Goods"
        }
    ],
    "sg:phone":"+1 323 732 7557",
    "sg:postcode":"90018",
    "sg:province":"CA",
    "wof:name":"C & T Handbags & Accessories",
    "wof:placetype":"venue"
},
  "geometry": {"coordinates":[-118.32603400000001,34.023551],"type":"Point"}
}