{
  "type": "Feature",
  "properties": {
    "addr:full":"1405 Davis St Livingston CA 95334",
    "addr:housenumber":"1405",
    "addr:postcode":"95334",
    "addr:street":"Davis St",
    "iso:country":"US",
    "sg:address":"1405 Davis St",
    "sg:city":"Livingston",
    "sg:classifiers":[
        {
            "category":"Autos & Motor Vehicles",
            "subcategory":"Fuel & Gas Station",
            "type":"Retail Goods"
        }
    ],
    "sg:phone":"+1 209 394 7273",
    "sg:postcode":"95334",
    "sg:province":"CA",
    "sg:tags":[
        "oil"
    ],
    "wof:name":"Livingston Grocery/ KWIK Serv",
    "wof:placetype":"venue"
},
  "geometry": {"coordinates":[-120.720834,37.390089],"type":"Point"}
}