{
  "type": "Feature",
  "properties": {
    "addr:full":"936 61st St Emeryville CA 94608",
    "addr:housenumber":"936",
    "addr:postcode":"94608",
    "addr:street":"61St St",
    "iso:country":"US",
    "sg:address":"936 61st St",
    "sg:city":"Emeryville",
    "sg:phone":"+1 510 652 2060",
    "sg:postcode":"94608",
    "sg:province":"CA",
    "sg:website":"http://www.globalpartitions.com",
    "wof:name":"Global Specialties Direct",
    "wof:placetype":"venue"
},
  "geometry": {"coordinates":[-122.276623,37.845299],"type":"Point"}
}