{
  "type": "Feature",
  "properties": {
    "addr:full":"1048 N 10th St San Jose CA 95112",
    "addr:housenumber":"1048",
    "addr:postcode":"95112",
    "addr:street":"N 10Th St",
    "iso:country":"US",
    "sg:address":"1048 N 10th St",
    "sg:city":"San Jose",
    "sg:classifiers":[
        {
            "category":"Wholesale",
            "subcategory":"Machinery & Supplies",
            "type":"Manufacturing & Wholesale Goods"
        }
    ],
    "sg:phone":"+1 408 297 6642",
    "sg:postcode":"95112",
    "sg:province":"CA",
    "sg:tags":[
        "fitting",
        "hose",
        "coupling"
    ],
    "wof:name":"Royal Brass Inc",
    "wof:placetype":"venue"
},
  "geometry": {"coordinates":[-121.89567099999999,37.36044],"type":"Point"}
}