{
  "type": "Feature",
  "properties": {
    "addr:full":"11976 Bernardo Plaza Dr San Diego CA 92128",
    "addr:housenumber":"11976",
    "addr:postcode":"92128",
    "addr:street":"Bernardo Plaza Dr",
    "iso:country":"US",
    "sg:address":"11976 Bernardo Plaza Dr",
    "sg:city":"San Diego",
    "sg:classifiers":[
        {
            "category":"Food & Beverages",
            "subcategory":"Specialty",
            "type":"Retail Goods"
        }
    ],
    "sg:phone":"+1 858 673 4143",
    "sg:postcode":"92128",
    "sg:province":"CA",
    "sg:tags":[
        "health",
        "diet"
    ],
    "wof:name":"GNC",
    "wof:placetype":"venue"
},
  "geometry": {"coordinates":[-117.074634,33.02033],"type":"Point"}
}