{
  "type": "Feature",
  "properties": {
    "addr:full":"3969 24th Street San Francisco CA 94114",
    "addr:housenumber":"3969",
    "addr:postcode":"94114",
    "addr:street":"24Th Street",
    "iso:country":"US",
    "sg:address":"3969 24th Street",
    "sg:city":"San Francisco",
    "sg:classifiers":[
        {
            "category":"Health Services",
            "subcategory":"Dentist",
            "type":"Services"
        }
    ],
    "sg:phone":"+1 415 647 7077",
    "sg:postcode":"94114",
    "sg:province":"CA",
    "wof:name":"Kinney Barry D DDS",
    "wof:placetype":"venue"
},
  "geometry": {"coordinates":[-122.431,37.7514],"type":"Point"}
}