{
  "type": "Feature",
  "properties": {
    "iso:country":"US",
    "sg:address":"327 Texas St",
    "sg:city":"Antioch",
    "sg:classifiers":[
        {
            "category":"Government",
            "subcategory":"Office",
            "type":"Public Place"
        }
    ],
    "sg:phone":"+1 925 671 9174",
    "sg:postcode":"94509",
    "sg:province":"CA",
    "wof:name":"Environmental Biotech Of Contra Costa County",
    "wof:placetype":"venue"
},
  "geometry": {"coordinates":[-121.81119,37.999481],"type":"Point"}
}