{
  "type": "Feature",
  "properties": {
    "addr:full":"4619 Ave C Torrance CA 90505",
    "addr:housenumber":"4619",
    "addr:postcode":"90505",
    "addr:street":"Ave C",
    "iso:country":"US",
    "sg:address":"4619 Ave C",
    "sg:city":"Torrance",
    "sg:classifiers":[
        {
            "category":"Health Services",
            "subcategory":"Health Practitioner",
            "type":"Services"
        }
    ],
    "sg:phone":"+1 310 378 6161",
    "sg:postcode":"90505",
    "sg:province":"CA",
    "sg:tags":[
        "nurse",
        "registry"
    ],
    "wof:name":"Elite International Nurse Svc",
    "wof:placetype":"venue"
},
  "geometry": {"coordinates":[-118.363423,33.825177],"type":"Point"}
}