{
  "type": "Feature",
  "properties": {
    "addr:full":"14211 Garden Rd Poway CA 92064",
    "addr:housenumber":"14211",
    "addr:postcode":"ca 92064",
    "addr:street":"Garden Rd",
    "iso:country":"US",
    "sg:address":"14211 Garden Rd",
    "sg:city":"Poway",
    "sg:classifiers":[
        {
            "category":"Building & Trades",
            "subcategory":"Plumbing",
            "type":"Services"
        }
    ],
    "sg:phone":"+1 858 668 1701",
    "sg:postcode":"92064",
    "sg:province":"CA",
    "sg:tags":[
        "solar",
        "installation",
        "electric",
        "power",
        "sales"
    ],
    "wof:name":"Western Solar Inc",
    "wof:placetype":"venue"
},
  "geometry": {"coordinates":[-117.022447,32.956179],"type":"Point"}
}