{
  "type": "Feature",
  "properties": {
    "addr:full":"1 California St San Francisco CA 94111",
    "addr:housenumber":"1",
    "addr:postcode":"94111",
    "addr:street":"California St",
    "iso:country":"US",
    "sg:address":"1 California St",
    "sg:city":"San Francisco",
    "sg:classifiers":[
        {
            "category":"Banks & Credit Unions",
            "subcategory":"Investment Brokerage",
            "type":"Services"
        }
    ],
    "sg:phone":"+1 415 954 6700",
    "sg:postcode":"94111",
    "sg:province":"CA",
    "sg:tags":[
        "stock",
        "bond"
    ],
    "wof:name":"UBS Financial Svc",
    "wof:placetype":"venue"
},
  "geometry": {"coordinates":[-122.39760699999999,37.793509],"type":"Point"}
}