{
  "type": "Feature",
  "properties": {
    "addr:full":"13255 Poway Rd Poway CA 92064",
    "addr:housenumber":"13255",
    "addr:postcode":"ca 92064",
    "addr:street":"Poway Rd",
    "iso:country":"US",
    "sg:address":"13255 Poway Rd",
    "sg:city":"Poway",
    "sg:classifiers":[
        {
            "category":"Wholesale",
            "subcategory":"Machinery & Supplies",
            "type":"Manufacturing & Wholesale Goods"
        }
    ],
    "sg:phone":"+1 858 486 0830",
    "sg:postcode":"92064",
    "sg:province":"CA",
    "sg:tags":[
        "equipment",
        "irrigation",
        "system"
    ],
    "wof:name":"Poway Irrigation & Landscape",
    "wof:placetype":"venue"
},
  "geometry": {"coordinates":[-117.04271199999999,32.95639],"type":"Point"}
}