{
  "type": "Feature",
  "properties": {
    "iso:country":"US",
    "sg:address":"135 S El Camino Real",
    "sg:city":"Millbrae",
    "sg:classifiers":[
        {
            "category":"Fast Food",
            "type":"Food & Drink"
        },
        {
            "category":"Restaurant",
            "type":"Food & Drink"
        }
    ],
    "sg:phone":"+1 650 259 9301",
    "sg:postcode":"94030",
    "sg:province":"CA",
    "sg:tags":[
        "tex-mex"
    ],
    "sg:website":"www.chipotle.com",
    "wof:name":"Chipotle Mexican Grill",
    "wof:placetype":"venue"
},
  "geometry": {"coordinates":[-122.38642,37.597133],"type":"Point"}
}