{
  "type": "Feature",
  "properties": {
    "addr:full":"2790 S Halcyon Rd Arroyo Grande CA 93420",
    "addr:housenumber":"2790",
    "addr:postcode":"93420",
    "addr:street":"S Halcyon Rd",
    "iso:country":"US",
    "sg:address":"2790 S Halcyon Rd",
    "sg:city":"Arroyo Grande",
    "sg:classifiers":[
        {
            "category":"Personal",
            "subcategory":"Barber",
            "type":"Services"
        }
    ],
    "sg:phone":"+1 805 489 3372",
    "sg:postcode":"93420",
    "sg:province":"CA",
    "wof:name":"Five Cities Barber Shop",
    "wof:placetype":"venue"
},
  "geometry": {"coordinates":[-120.586703,35.080707],"type":"Point"}
}