{
  "type": "Feature",
  "properties": {
    "iso:country":"US",
    "sg:address":"30686 Thousand Oaks Blvd",
    "sg:city":"Agoura Hills",
    "sg:classifiers":[
        {
            "category":"Professional",
            "type":"Services"
        }
    ],
    "sg:phone":"+1 818 889 9191",
    "sg:postcode":"91301",
    "sg:province":"CA",
    "wof:name":"Takhtie House of Power",
    "wof:placetype":"venue"
},
  "geometry": {"coordinates":[-118.788134,34.154661],"type":"Point"}
}