{
  "type": "Feature",
  "properties": {
    "addr:full":"1430 E 28th St Long Beach CA 90755",
    "addr:housenumber":"1430",
    "addr:postcode":"90755",
    "addr:street":"E 28Th St",
    "iso:country":"US",
    "sg:address":"1430 E 28th St",
    "sg:city":"Long Beach",
    "sg:classifiers":[
        {
            "category":"Autos & Motor Vehicles",
            "subcategory":"Auto Supplies",
            "type":"Retail Goods"
        }
    ],
    "sg:phone":"+1 562 426 6901",
    "sg:postcode":"90755",
    "sg:province":"CA",
    "sg:tags":[
        "engine",
        "rebuilding",
        "automotive",
        "equipment",
        "parts",
        "automobile",
        "racing",
        "car"
    ],
    "wof:name":"Reath Automotive Corp",
    "wof:placetype":"venue"
},
  "geometry": {"coordinates":[-118.173327,33.807956],"type":"Point"}
}