{
  "type": "Feature",
  "properties": {
    "iso:country":"US",
    "sg:address":"121 S Hope Street Apt 115",
    "sg:city":"Los Angeles",
    "sg:classifiers":[
        {
            "category":"Shopping",
            "subcategory":"Jewelry",
            "type":"Retail Goods"
        }
    ],
    "sg:phone":"+1 213 628 2998",
    "sg:postcode":"90012",
    "sg:province":"CA",
    "wof:name":"Callaris Gemms",
    "wof:placetype":"venue"
},
  "geometry": {"coordinates":[-118.241423,34.061994],"type":"Point"}
}