{
  "type": "Feature",
  "properties": {
    "iso:country":"US",
    "sg:address":"16769 Bernardo Center Dr",
    "sg:city":"San Diego",
    "sg:classifiers":[
        {
            "category":"Social Services",
            "subcategory":"Adult Care",
            "type":"Services"
        }
    ],
    "sg:phone":"+1 858 487 2640",
    "sg:postcode":"92128",
    "sg:province":"CA",
    "sg:tags":[
        "organization",
        "senior",
        "citizen"
    ],
    "wof:name":"Rancho Bernardo Senior Svc",
    "wof:placetype":"venue"
},
  "geometry": {"coordinates":[-117.075852,33.017195],"type":"Point"}
}