{
  "type": "Feature",
  "properties": {
    "iso:country":"US",
    "sg:address":"5325 Elkhorn Blvd",
    "sg:city":"Sacramento",
    "sg:classifiers":[
        {
            "category":"Professional",
            "subcategory":"Detective & Security Services",
            "type":"Services"
        }
    ],
    "sg:phone":"+1 916 212 3183",
    "sg:postcode":"95842",
    "sg:province":"CA",
    "sg:tags":[
        "control",
        "monitoring",
        "system",
        "guard",
        "patrol"
    ],
    "sg:website":"http://fastsecuritypatrol.net",
    "wof:name":"Fast Private Security Patrol",
    "wof:placetype":"venue"
},
  "geometry": {"coordinates":[-121.341419,38.686267],"type":"Point"}
}