{
  "type": "Feature",
  "properties": {
    "iso:country":"US",
    "sg:address":"239 E Alameda Ave",
    "sg:city":"Burbank",
    "sg:classifiers":[
        {
            "category":"Professional",
            "subcategory":"Management & Consulting",
            "type":"Services"
        }
    ],
    "sg:phone":"+1 818 563 6466",
    "sg:postcode":"91502",
    "sg:province":"CA",
    "sg:tags":[
        "consultant",
        "security",
        "system"
    ],
    "wof:name":"PSA Professional Security Alrm",
    "wof:placetype":"venue"
},
  "geometry": {"coordinates":[-118.297654,34.176629],"type":"Point"}
}