{
  "type": "Feature",
  "properties": {
    "iso:country":"US",
    "sg:address":"829 Produce Court",
    "sg:city":"Los Angeles",
    "sg:classifiers":[
        {
            "category":"Wholesale",
            "subcategory":"Fruits & Vegetables",
            "type":"Manufacturing & Wholesale Goods"
        }
    ],
    "sg:phone":"+1 213 623 9110",
    "sg:postcode":"90021",
    "sg:province":"CA",
    "sg:tags":[
        "veggie"
    ],
    "wof:name":"Gomez Produce",
    "wof:placetype":"venue"
},
  "geometry": {"coordinates":[-118.24439,34.03416],"type":"Point"}
}