{
  "type": "Feature",
  "properties": {
    "addr:full":"610 Ave Victoria San Clemente CA 92672",
    "addr:housenumber":"610",
    "addr:postcode":"92672",
    "addr:street":"Ave",
    "iso:country":"US",
    "sg:address":"610 Ave Victoria",
    "sg:city":"San Clemente",
    "sg:classifiers":[
        {
            "category":"Travel",
            "subcategory":"Hotels & Motels",
            "type":"Entertainment"
        }
    ],
    "sg:phone":"+1 949 492 1234",
    "sg:postcode":"92672",
    "sg:province":"CA",
    "sg:website":"www.casatropicana.com",
    "wof:name":"Casa Tropicana Bed & Breakfast",
    "wof:placetype":"venue"
},
  "geometry": {"coordinates":[-117.61926,33.419514],"type":"Point"}
}