{
  "type": "Feature",
  "properties": {
    "iso:country":"US",
    "sg:address":"1963 San Bruno",
    "sg:city":"Newport Beach",
    "sg:classifiers":[
        {
            "category":"Professional",
            "type":"Services"
        }
    ],
    "sg:phone":"+1 949 759 6674",
    "sg:postcode":"92660",
    "sg:province":"CA",
    "wof:name":"Alt LLC",
    "wof:placetype":"venue"
},
  "geometry": {"coordinates":[-117.880456,33.632785],"type":"Point"}
}