{
  "type": "Feature",
  "properties": {
    "iso:country":"US",
    "sg:address":"2200 S Escondido Blvd",
    "sg:city":"Escondido",
    "sg:classifiers":[
        {
            "category":"Shopping",
            "type":"Retail Goods"
        }
    ],
    "sg:phone":"+1 760 747 5570",
    "sg:postcode":"92025",
    "sg:province":"CA",
    "sg:tags":[
        "collectible"
    ],
    "wof:name":"Angel Room",
    "wof:placetype":"venue"
},
  "geometry": {"coordinates":[-117.071462,33.09484],"type":"Point"}
}