{
  "type": "Feature",
  "properties": {
    "addr:full":"11145 Knott Ave Cypress CA 90630",
    "addr:housenumber":"11145",
    "addr:postcode":"90630",
    "addr:street":"Knott Ave",
    "iso:country":"US",
    "sg:address":"11145 Knott Ave",
    "sg:city":"Cypress",
    "sg:classifiers":[
        {
            "category":"Taxi",
            "type":"Transportation"
        }
    ],
    "sg:phone":"+1 714 220 0023",
    "sg:postcode":"90630",
    "sg:province":"CA",
    "wof:name":"A Yello Cab",
    "wof:placetype":"venue"
},
  "geometry": {"coordinates":[-118.011002,33.800701],"type":"Point"}
}