{
  "type": "Feature",
  "properties": {
    "iso:country":"US",
    "sg:address":"5434 Orangethorpe Ave",
    "sg:city":"La Palma",
    "sg:classifiers":[
        {
            "category":"Personal",
            "subcategory":"Beauty Salon",
            "type":"Services"
        }
    ],
    "sg:phone":"+1 714 522 0271",
    "sg:postcode":"90623",
    "sg:province":"CA",
    "wof:name":"Willy Sutliff",
    "wof:placetype":"venue"
},
  "geometry": {"coordinates":[-118.039513,33.858668],"type":"Point"}
}