{
  "type": "Feature",
  "properties": {
    "addr:full":"8350 La Mesa Blvd La Mesa CA 91941",
    "addr:housenumber":"8350",
    "addr:postcode":"91941",
    "addr:street":"La Mesa Blvd",
    "iso:country":"US",
    "sg:address":"8350 La Mesa Blvd",
    "sg:city":"La Mesa",
    "sg:classifiers":[
        {
            "category":"Restaurant",
            "type":"Food & Drink"
        }
    ],
    "sg:phone":"+1 619 466 6446",
    "sg:postcode":"91941",
    "sg:province":"CA",
    "sg:tags":[
        "sushi",
        "bar"
    ],
    "sg:website":"www.konnichiwa-sushi.com/",
    "wof:name":"John's Konichiwa Sushi",
    "wof:placetype":"venue"
},
  "geometry": {"coordinates":[-117.018021,32.765501],"type":"Point"}
}