{
  "type": "Feature",
  "properties": {
    "iso:country":"US",
    "sg:address":"39725 Garand Ln",
    "sg:city":"Palm Desert",
    "sg:classifiers":[
        {
            "category":"Wholesale",
            "subcategory":"Fruits & Vegetables",
            "type":"Manufacturing & Wholesale Goods"
        }
    ],
    "sg:phone":"+1 760 772 7383",
    "sg:postcode":"92211",
    "sg:province":"CA",
    "sg:tags":[
        "shipper"
    ],
    "sg:website":"www.jjranchpro.com",
    "wof:name":"J & J Ranch Produce",
    "wof:placetype":"venue"
},
  "geometry": {"coordinates":[-116.308105,33.760122],"type":"Point"}
}