{
  "type": "Feature",
  "properties": {
    "iso:country":"US",
    "sg:address":"500 Eubanks St",
    "sg:city":"Camarillo",
    "sg:classifiers":[
        {
            "category":"Government",
            "subcategory":"Jail",
            "type":"Public Place"
        }
    ],
    "sg:phone":"+1 805 388 4339",
    "sg:postcode":"93010",
    "sg:province":"CA",
    "sg:tags":[
        "general"
    ],
    "wof:name":"V C P A Work Furlough",
    "wof:placetype":"venue"
},
  "geometry": {"coordinates":[-119.081376,34.206229],"type":"Point"}
}