{
  "type": "Feature",
  "properties": {
    "addr:full":"647 W Shaw Ave Fresno CA 93704",
    "addr:housenumber":"647",
    "addr:postcode":"93704",
    "addr:street":"W Shaw Ave",
    "iso:country":"US",
    "sg:address":"647 W Shaw Ave",
    "sg:city":"Fresno",
    "sg:classifiers":[
        {
            "category":"Banks & Credit Unions",
            "subcategory":"Bank",
            "type":"Services"
        }
    ],
    "sg:phone":"+1 559 224 1806",
    "sg:postcode":"93704",
    "sg:province":"CA",
    "sg:tags":[
        "loan",
        "real estate"
    ],
    "wof:name":"Windsor Capitol Mortgage Corp",
    "wof:placetype":"venue"
},
  "geometry": {"coordinates":[-119.804841,36.808329],"type":"Point"}
}