{
  "type": "Feature",
  "properties": {
    "iso:country":"US",
    "sg:address":"19710 Ventura Blvd",
    "sg:city":"Woodland Hills",
    "sg:classifiers":[
        {
            "category":"Personal",
            "subcategory":"Nail Salon",
            "type":"Services"
        }
    ],
    "sg:phone":"+1 818 346 6245",
    "sg:postcode":"91364",
    "sg:province":"CA",
    "wof:name":"Reicheg Marlene",
    "wof:placetype":"venue"
},
  "geometry": {"coordinates":[-118.56199599999999,34.1726],"type":"Point"}
}