{
  "type": "Feature",
  "properties": {
    "addr:full":"118 Orange Ave Coronado CA 92118",
    "addr:housenumber":"118",
    "addr:postcode":"92118",
    "addr:street":"Orange Ave",
    "iso:country":"US",
    "sg:address":"118 Orange Ave",
    "sg:city":"Coronado",
    "sg:classifiers":[
        {
            "category":"Building & Trades",
            "subcategory":"Plumbing",
            "type":"Services"
        }
    ],
    "sg:phone":"+1 619 435 2132",
    "sg:postcode":"92118",
    "sg:province":"CA",
    "sg:tags":[
        "plumber"
    ],
    "wof:name":"Bay And Shore Company",
    "wof:placetype":"venue"
},
  "geometry": {"coordinates":[-117.172563,32.698529],"type":"Point"}
}