{
  "type": "Feature",
  "properties": {
    "iso:country":"US",
    "sg:address":"444 Camino Del Rio S",
    "sg:city":"San Diego",
    "sg:classifiers":[
        {
            "category":"Landmark",
            "subcategory":"Tourist Information",
            "type":"Public Place"
        }
    ],
    "sg:phone":"+1 619 491 3010",
    "sg:postcode":"92108",
    "sg:province":"CA",
    "sg:tags":[
        "tour"
    ],
    "wof:name":"Pacific Timeshare",
    "wof:placetype":"venue"
},
  "geometry": {"coordinates":[-117.13461,32.776033],"type":"Point"}
}