{
  "type": "Feature",
  "properties": {
    "iso:country":"US",
    "sg:address":"7138 Willow St",
    "sg:city":"Sebastopol",
    "sg:classifiers":[
        {
            "category":"Health Services",
            "subcategory":"Doctor",
            "type":"Services"
        }
    ],
    "sg:phone":"+1 707 823 5309",
    "sg:postcode":"95472",
    "sg:province":"CA",
    "sg:tags":[
        "dentist"
    ],
    "wof:name":"North Bay Dental Care",
    "wof:placetype":"venue"
},
  "geometry": {"coordinates":[-122.82404699999999,38.40004],"type":"Point"}
}