{
  "type": "Feature",
  "properties": {
    "iso:country":"US",
    "sg:address":"11582 Moen St",
    "sg:city":"Anaheim",
    "sg:classifiers":[
        {
            "category":"Building & Trades",
            "subcategory":"Plumbing",
            "type":"Services"
        }
    ],
    "sg:phone":"+1 714 502 9729",
    "sg:postcode":"92804",
    "sg:province":"CA",
    "wof:name":"Pipedream Plumbing",
    "wof:placetype":"venue"
},
  "geometry": {"coordinates":[-117.985946,33.794328],"type":"Point"}
}