{
  "type": "Feature",
  "properties": {
    "addr:full":"635 Anderson Rd Ste 12 Davis CA 95616",
    "addr:housenumber":"635;12",
    "addr:postcode":"95616",
    "addr:street":"Anderson Rd Ste",
    "iso:country":"US",
    "sg:address":"635 Anderson Rd Ste 12",
    "sg:city":"Davis",
    "sg:classifiers":[
        {
            "category":"Insurance",
            "subcategory":"Health Insurance",
            "type":"Services"
        }
    ],
    "sg:phone":"+1 530 759 9804",
    "sg:postcode":"95616",
    "sg:province":"CA",
    "sg:tags":[
        "plans-information",
        "referral"
    ],
    "wof:name":"Sutter Center For Integrative Health & Healing",
    "wof:placetype":"venue"
},
  "geometry": {"coordinates":[-121.758735,38.548111],"type":"Point"}
}