{
  "type": "Feature",
  "properties": {
    "addr:full":"345 W 2nd St Calexico CA 92231",
    "addr:housenumber":"345",
    "addr:postcode":"92231",
    "addr:street":"W 2Nd St",
    "iso:country":"US",
    "sg:address":"345 W 2nd St",
    "sg:city":"Calexico",
    "sg:classifiers":[
        {
            "category":"Professional",
            "subcategory":"Detective & Security Services",
            "type":"Services"
        }
    ],
    "sg:phone":"+1 760 357 9333",
    "sg:postcode":"92231",
    "sg:province":"CA",
    "sg:tags":[
        "information",
        "bureau"
    ],
    "wof:name":"Dragon Recovery Services",
    "wof:placetype":"venue"
},
  "geometry": {"coordinates":[-115.502133,32.666576],"type":"Point"}
}