{
  "type": "Feature",
  "properties": {
    "addr:full":"600 E Hamilton Ave Campbell CA 95008",
    "addr:housenumber":"600",
    "addr:postcode":"95008",
    "addr:street":"E Hamilton Ave",
    "iso:country":"US",
    "sg:address":"600 E Hamilton Ave",
    "sg:city":"Campbell",
    "sg:classifiers":[
        {
            "category":"Shopping",
            "subcategory":"Stationery & Office Supplies",
            "type":"Retail Goods"
        },
        {
            "category":"Shopping",
            "subcategory":"Music",
            "type":"Retail Goods"
        },
        {
            "category":"Shopping",
            "subcategory":"Computers & Home Electronics",
            "type":"Retail Goods"
        },
        {
            "category":"Wholesale",
            "subcategory":"Computers",
            "type":"Manufacturing & Wholesale Goods"
        }
    ],
    "sg:phone":"+1 408 364 3700",
    "sg:postcode":"95008",
    "sg:province":"CA",
    "sg:tags":[
        "equipment",
        "dvd's"
    ],
    "sg:website":"www.frys.com",
    "wof:name":"Fry's Electronics",
    "wof:placetype":"venue"
},
  "geometry": {"coordinates":[-121.939159,37.292567],"type":"Point"}
}