{
  "type": "Feature",
  "properties": {
    "iso:country":"US",
    "sg:address":"1122 W Poplar St",
    "sg:city":"Compton",
    "sg:classifiers":[
        {
            "category":"Professional",
            "subcategory":"Lawyer & Legal Services",
            "type":"Services"
        }
    ],
    "sg:phone":"+1 310 898 1234",
    "sg:postcode":"90220",
    "sg:province":"CA",
    "sg:tags":[
        "notary"
    ],
    "wof:name":"Bill Latham Income Tax Service",
    "wof:placetype":"venue"
},
  "geometry": {"coordinates":[-118.245003,33.900101],"type":"Point"}
}