{
  "type": "Feature",
  "properties": {
    "iso:country":"US",
    "sg:address":"24 Serramonte Blvd",
    "sg:city":"Daly City",
    "sg:classifiers":[
        {
            "category":"Shopping",
            "subcategory":"Clothing, Apparel, & Fashions",
            "type":"Retail Goods"
        }
    ],
    "sg:phone":"+1 650 992 2918",
    "sg:postcode":"94015",
    "sg:province":"CA",
    "wof:name":"Hollister Co",
    "wof:placetype":"venue"
},
  "geometry": {"coordinates":[-122.46697,37.669551],"type":"Point"}
}