{
  "type": "Feature",
  "properties": {
    "addr:full":"1204 Porta Ballena Alameda CA 94501",
    "addr:housenumber":"1204",
    "addr:postcode":"94501",
    "addr:street":"Porta Ballena",
    "iso:country":"US",
    "sg:address":"1204 Porta Ballena",
    "sg:city":"Alameda",
    "sg:classifiers":[
        {
            "category":"Professional",
            "type":"Services"
        }
    ],
    "sg:phone":"+1 510 337 1914",
    "sg:postcode":"94501",
    "sg:province":"CA",
    "wof:name":"Ecosense Inc",
    "wof:placetype":"venue"
},
  "geometry": {"coordinates":[-122.285324,37.768688],"type":"Point"}
}