{
  "type": "Feature",
  "properties": {
    "addr:full":"600 S Main St Bishop CA 93514",
    "addr:housenumber":"600",
    "addr:postcode":"93514",
    "addr:street":"S Main St",
    "iso:country":"US",
    "sg:address":"600 S Main St",
    "sg:city":"Bishop",
    "sg:classifiers":[
        {
            "category":"Retail",
            "subcategory":"Auto Rental",
            "type":"Services"
        }
    ],
    "sg:phone":"+1 760 872 6224",
    "sg:postcode":"93514",
    "sg:province":"CA",
    "sg:tags":[
        "renting",
        "truck",
        "leasing"
    ],
    "wof:name":"U-Haul Co",
    "wof:placetype":"venue"
},
  "geometry": {"coordinates":[-118.395267,37.355522],"type":"Point"}
}