{
  "type": "Feature",
  "properties": {
    "iso:country":"US",
    "sg:address":"1197 E Washington Ave",
    "sg:city":"El Cajon",
    "sg:classifiers":[
        {
            "category":"Building & Trades",
            "subcategory":"Construction",
            "type":"Services"
        }
    ],
    "sg:phone":"+1 619 334 2509",
    "sg:postcode":"92019",
    "sg:province":"CA",
    "sg:tags":[
        "hanging",
        "contractor"
    ],
    "wof:name":"Feather Touch Exterior",
    "wof:placetype":"venue"
},
  "geometry": {"coordinates":[-116.941324,32.787592],"type":"Point"}
}