{
  "type": "Feature",
  "properties": {
    "iso:country":"US",
    "sg:address":"2409 N Wilmington Ave",
    "sg:city":"Compton",
    "sg:classifiers":[
        {
            "category":"Shopping",
            "type":"Retail Goods"
        },
        {
            "category":"Food & Beverages",
            "subcategory":"Groceries & Convenience Stores",
            "type":"Retail Goods"
        }
    ],
    "sg:phone":"+1 310 747 0268",
    "sg:postcode":"90222",
    "sg:province":"CA",
    "sg:tags":[
        "merchandise"
    ],
    "wof:name":"Mart Moes Mini",
    "wof:placetype":"venue"
},
  "geometry": {"coordinates":[-118.239335,33.914409],"type":"Point"}
}