{
  "type": "Feature",
  "properties": {
    "iso:country":"US",
    "sg:address":"45002 Date Ave",
    "sg:city":"Lancaster",
    "sg:classifiers":[
        {
            "category":"Education",
            "subcategory":"School",
            "type":"Public Place"
        }
    ],
    "sg:phone":"+1 661 948 3613",
    "sg:postcode":"93534",
    "sg:province":"CA",
    "wof:name":"Sacred Heart School",
    "wof:placetype":"venue"
},
  "geometry": {"coordinates":[-118.140974,34.69982],"type":"Point"}
}