{
  "type": "Feature",
  "properties": {
    "addr:full":"1219 E Adams Blvd Los Angeles CA 90011",
    "addr:housenumber":"1219",
    "addr:postcode":"90011",
    "addr:street":"E Adams Blvd",
    "iso:country":"US",
    "sg:address":"1219 E Adams Blvd",
    "sg:city":"Los Angeles",
    "sg:classifiers":[
        {
            "category":"Organizations",
            "subcategory":"Religious Organization",
            "type":"Services"
        }
    ],
    "sg:phone":"+1 323 233 1870",
    "sg:postcode":"90011",
    "sg:province":"CA",
    "sg:tags":[
        "church"
    ],
    "wof:name":"Iglesia Bethania",
    "wof:placetype":"venue"
},
  "geometry": {"coordinates":[-118.250457,34.016844],"type":"Point"}
}