{
  "type": "Feature",
  "properties": {
    "addr:full":"7425 el Camino Real Atascadero CA 93422",
    "addr:housenumber":"7425",
    "addr:postcode":"93422",
    "addr:street":"El Camino Real",
    "iso:country":"US",
    "sg:address":"7425 el Camino Real",
    "sg:city":"Atascadero",
    "sg:classifiers":[
        {
            "category":"Home & Garden",
            "subcategory":"Home Furnishings",
            "type":"Retail Goods"
        }
    ],
    "sg:phone":"+1 805 466 8813",
    "sg:postcode":"93422",
    "sg:province":"CA",
    "sg:tags":[
        "window",
        "business",
        "covering"
    ],
    "wof:name":"Window Affair",
    "wof:placetype":"venue"
},
  "geometry": {"coordinates":[-120.66383999999999,35.48538],"type":"Point"}
}