{
  "type": "Feature",
  "properties": {
    "iso:country":"US",
    "sg:address":"5300 Pacific Blvd",
    "sg:city":"Huntington Park",
    "sg:classifiers":[
        {
            "category":"Manufacturing",
            "subcategory":"Apparel",
            "type":"Manufacturing & Wholesale Goods"
        }
    ],
    "sg:phone":"+1 323 589 6271",
    "sg:postcode":"90255",
    "sg:province":"CA",
    "sg:tags":[
        "sewing",
        "contractor"
    ],
    "wof:name":"TLC Apparel Inc",
    "wof:placetype":"venue"
},
  "geometry": {"coordinates":[-118.225126,33.995367],"type":"Point"}
}