{
  "type": "Feature",
  "properties": {
    "iso:country":"US",
    "sg:address":"11010 State Hwy 99",
    "sg:city":"Los Molinos",
    "sg:classifiers":[
        {
            "category":"Farming",
            "subcategory":"Crops",
            "type":"Manufacturing & Wholesale Goods"
        }
    ],
    "sg:phone":"+1 530 527 8028",
    "sg:postcode":"96055",
    "sg:province":"CA",
    "sg:tags":[
        "grove",
        "nut",
        "fruit",
        "tree",
        "orchard"
    ],
    "wof:name":"Agri Development Company",
    "wof:placetype":"venue"
},
  "geometry": {"coordinates":[-122.11835000000001,40.116901],"type":"Point"}
}