{
  "type": "Feature",
  "properties": {
    "iso:country":"US",
    "sg:address":"17618 Chatsworth St",
    "sg:city":"Granada Hills",
    "sg:classifiers":[
        {
            "category":"Shopping",
            "type":"Retail Goods"
        }
    ],
    "sg:phone":"+1 818 368 5719",
    "sg:postcode":"91344",
    "sg:province":"CA",
    "sg:tags":[
        "equipment",
        "pool",
        "swimming"
    ],
    "wof:name":"Leslie's Swimming Pool Supply",
    "wof:placetype":"venue"
},
  "geometry": {"coordinates":[-118.51941100000001,34.264805],"type":"Point"}
}