{
  "type": "Feature",
  "properties": {
    "addr:full":"9607 Van Nuys Blvd Panorama City CA 91402",
    "addr:housenumber":"9607",
    "addr:postcode":"91402",
    "addr:street":"Van Nuys Blvd",
    "iso:country":"US",
    "sg:address":"9607 Van Nuys Blvd",
    "sg:city":"Panorama City",
    "sg:classifiers":[
        {
            "category":"Shopping",
            "subcategory":"Clothing, Apparel, & Fashions",
            "type":"Retail Goods"
        }
    ],
    "sg:phone":"+1 818 766 9166",
    "sg:postcode":"91402",
    "sg:province":"CA",
    "wof:name":"Global Stich Art",
    "wof:placetype":"venue"
},
  "geometry": {"coordinates":[-118.450312,34.244859],"type":"Point"}
}