{
  "type": "Feature",
  "properties": {
    "addr:full":"14425 Newport Ave Tustin CA 92780",
    "addr:housenumber":"14425",
    "addr:postcode":"92780",
    "addr:street":"Newport Ave",
    "iso:country":"US",
    "sg:address":"14425 Newport Ave",
    "sg:city":"Tustin",
    "sg:classifiers":[
        {
            "category":"Restaurant",
            "type":"Food & Drink"
        }
    ],
    "sg:phone":"+1 714 832 3434",
    "sg:postcode":"92780",
    "sg:province":"CA",
    "sg:tags":[
        "pizza",
        "italian"
    ],
    "sg:website":"www.flaviositaliankitchen.com",
    "wof:name":"Flavio's Italian Kitchen",
    "wof:placetype":"venue"
},
  "geometry": {"coordinates":[-117.827637,33.732692],"type":"Point"}
}