{
  "type": "Feature",
  "properties": {
    "iso:country":"US",
    "sg:address":"555 E Tachevah Dr",
    "sg:city":"Palm Springs",
    "sg:classifiers":[
        {
            "category":"Health Services",
            "subcategory":"Doctor",
            "type":"Services"
        }
    ],
    "sg:phone":"+1 760 320 1805",
    "sg:postcode":"92262",
    "sg:province":"CA",
    "sg:tags":[
        "obstetrician",
        "gynecologist"
    ],
    "wof:name":"Palm Springs Women's Health Care Associates",
    "wof:placetype":"venue"
},
  "geometry": {"coordinates":[-116.542406,33.837065],"type":"Point"}
}