{
  "type": "Feature",
  "properties": {
    "addr:full":"3701 Blackwood Rd South Lake Tahoe CA 96150",
    "addr:housenumber":"3701",
    "addr:postcode":"96150",
    "addr:street":"Blackwood Rd",
    "iso:country":"US",
    "sg:address":"3701 Blackwood Rd",
    "sg:city":"South Lake Tahoe",
    "sg:classifiers":[
        {
            "category":"Professional",
            "type":"Services"
        }
    ],
    "sg:phone":"+1 530 544 7715",
    "sg:postcode":"96150",
    "sg:province":"CA",
    "sg:tags":[
        "establishment"
    ],
    "wof:name":"Blackwood Association",
    "wof:placetype":"venue"
},
  "geometry": {"coordinates":[-119.956215,38.940526],"type":"Point"}
}