{
  "type": "Feature",
  "properties": {
    "iso:country":"US",
    "sg:address":"7110 N Washoe Ave",
    "sg:city":"Firebaugh",
    "sg:classifiers":[
        {
            "category":"Farming",
            "subcategory":"Farm & Veterinary Services",
            "type":"Manufacturing & Wholesale Goods"
        }
    ],
    "sg:phone":"+1 559 659 3901",
    "sg:postcode":"93622",
    "sg:province":"CA",
    "sg:tags":[
        "bean",
        "cleaning"
    ],
    "wof:name":"Valley Seed Growers",
    "wof:placetype":"venue"
},
  "geometry": {"coordinates":[-120.457544,36.836682],"type":"Point"}
}