{
  "type": "Feature",
  "properties": {
    "iso:country":"US",
    "sg:address":"1477 Plymouth St",
    "sg:city":"Mountain View",
    "sg:classifiers":[
        {
            "category":"Restaurant",
            "type":"Food & Drink"
        }
    ],
    "sg:phone":"+1 650 960 0268",
    "sg:postcode":"94043",
    "sg:province":"CA",
    "wof:name":"New Mas Restaurant",
    "wof:placetype":"venue"
},
  "geometry": {"coordinates":[-122.080698,37.416493],"type":"Point"}
}