{
  "type": "Feature",
  "properties": {
    "iso:country":"US",
    "sg:address":"2966 Wilshire Blvd",
    "sg:city":"Los Angeles",
    "sg:classifiers":[
        {
            "category":"Health Services",
            "subcategory":"Health Practitioner",
            "type":"Services"
        }
    ],
    "sg:phone":"+1 213 487 3133",
    "sg:postcode":"90010",
    "sg:province":"CA",
    "sg:tags":[
        "acupuncture"
    ],
    "wof:name":"L A Sam Bo Dang Acupuncture",
    "wof:placetype":"venue"
},
  "geometry": {"coordinates":[-118.28600299999999,34.061798],"type":"Point"}
}