{
  "type": "Feature",
  "properties": {
    "iso:country":"US",
    "sg:address":"24155 Laguna Hills Mall",
    "sg:city":"Laguna Hills",
    "sg:classifiers":[
        {
            "category":"Shopping Center",
            "type":"Public Place"
        }
    ],
    "sg:phone":"+1 949 586 8282",
    "sg:postcode":"92653",
    "sg:province":"CA",
    "wof:name":"InfoLine",
    "wof:placetype":"venue"
},
  "geometry": {"coordinates":[-117.709234,33.612321],"type":"Point"}
}