{
  "type": "Feature",
  "properties": {
    "addr:full":"21436 Vintage Way El Toro CA 92630",
    "addr:housenumber":"21436",
    "addr:postcode":"92630",
    "addr:street":"Vintage Way",
    "iso:country":"US",
    "sg:address":"21436 Vintage Way",
    "sg:city":"El Toro",
    "sg:classifiers":[
        {
            "category":"Shopping",
            "subcategory":"Hobbies, Toys, & Games",
            "type":"Retail Goods"
        }
    ],
    "sg:phone":"+1 949 497 5497",
    "sg:postcode":"92630",
    "sg:province":"CA",
    "sg:tags":[
        "craft",
        "supply"
    ],
    "wof:name":"Ripkords Limited",
    "wof:placetype":"venue"
},
  "geometry": {"coordinates":[-117.657538,33.654054],"type":"Point"}
}