{
  "type": "Feature",
  "properties": {
    "addr:full":"1884 Commons Ct Windsor CA 95492",
    "addr:housenumber":"1884",
    "addr:postcode":"95492",
    "addr:street":"Commons Ct",
    "iso:country":"US",
    "sg:address":"1884 Commons Ct",
    "sg:city":"Windsor",
    "sg:classifiers":[
        {
            "category":"Professional",
            "type":"Services"
        }
    ],
    "sg:phone":"+1 707 836 7434",
    "sg:postcode":"95492",
    "sg:province":"CA",
    "wof:name":"Filomena Pardo Sixto",
    "wof:placetype":"venue"
},
  "geometry": {"coordinates":[-122.818637,38.551671],"type":"Point"}
}