{
  "type": "Feature",
  "properties": {
    "addr:full":"350 Parnassus Ave Ste 403 San Francisco CA 94117",
    "addr:housenumber":"350",
    "addr:postcode":"94117",
    "addr:street":"Parnassus Ave Ste 403",
    "iso:country":"US",
    "sg:address":"350 Parnassus Ave Ste 403",
    "sg:city":"San Francisco",
    "sg:classifiers":[
        {
            "category":"Health Services",
            "subcategory":"Dentist",
            "type":"Services"
        }
    ],
    "sg:phone":"+1 415 681 0668",
    "sg:postcode":"94117",
    "sg:province":"CA",
    "wof:name":"Robert A. Chong, DDS, Inc.",
    "wof:placetype":"venue"
},
  "geometry": {"coordinates":[-122.456333,37.764095],"type":"Point"}
}