{
  "type": "Feature",
  "properties": {
    "addr:full":"10234 Diener Rd Kelseyville CA 95451",
    "addr:housenumber":"10234",
    "addr:postcode":"95451",
    "addr:street":"Diener Rd",
    "iso:country":"US",
    "sg:address":"10234 Diener Rd",
    "sg:city":"Kelseyville",
    "sg:classifiers":[
        {
            "category":"Building & Trades",
            "subcategory":"Construction",
            "type":"Services"
        }
    ],
    "sg:phone":"+1 707 928 6759",
    "sg:postcode":"95451",
    "sg:province":"CA",
    "sg:tags":[
        "painter"
    ],
    "wof:name":"Mc Intosh Painting",
    "wof:placetype":"venue"
},
  "geometry": {"coordinates":[-122.719143,38.891816],"type":"Point"}
}