{
  "type": "Feature",
  "properties": {
    "addr:full":"2344 Emerson St Palo Alto CA 94301",
    "addr:housenumber":"2344",
    "addr:postcode":"94301",
    "addr:street":"Emerson St",
    "iso:country":"US",
    "sg:address":"2344 Emerson St",
    "sg:city":"Palo Alto",
    "sg:classifiers":[
        {
            "category":"Professional",
            "type":"Services"
        }
    ],
    "sg:phone":"+1 650 326 2902",
    "sg:postcode":"94301",
    "sg:province":"CA",
    "sg:tags":[
        "scientist"
    ],
    "wof:name":"Applied Sciences Consultants",
    "wof:placetype":"venue"
},
  "geometry": {"coordinates":[-122.139729,37.430107],"type":"Point"}
}