{
  "type": "Feature",
  "properties": {
    "iso:country":"US",
    "sg:address":"17415 Catalpa St",
    "sg:city":"Hesperia",
    "sg:classifiers":[
        {
            "category":"Professional",
            "type":"Services"
        }
    ],
    "sg:phone":"+1 760 948 8100",
    "sg:postcode":"92345",
    "sg:province":"CA",
    "wof:name":"Artisan Molds & Castings",
    "wof:placetype":"venue"
},
  "geometry": {"coordinates":[-117.284323,34.460222],"type":"Point"}
}