{
  "type": "Feature",
  "properties": {
    "iso:country":"US",
    "sg:address":"89 W El Camino Real",
    "sg:city":"Mountain View",
    "sg:classifiers":[
        {
            "category":"Restaurant",
            "type":"Food & Drink"
        }
    ],
    "sg:phone":"+1 650 625 8374",
    "sg:postcode":"94040",
    "sg:province":"CA",
    "sg:tags":[
        "breakfast",
        "mexican",
        "brunch"
    ],
    "sg:website":"www.loscharrosrestaurant.com",
    "wof:name":"Los Charros Restaurant",
    "wof:placetype":"venue"
},
  "geometry": {"coordinates":[-122.075687,37.381598],"type":"Point"}
}