{
  "type": "Feature",
  "properties": {
    "addr:full":"2225 Bess Ave Livermore CA 94550",
    "addr:housenumber":"2225",
    "addr:postcode":"94550",
    "addr:street":"Bess Ave",
    "iso:country":"US",
    "sg:address":"2225 Bess Ave",
    "sg:city":"Livermore",
    "sg:classifiers":[
        {
            "category":"Building & Trades",
            "subcategory":"Landscaping Services",
            "type":"Services"
        }
    ],
    "sg:phone":"+1 925 606 6312",
    "sg:postcode":"94550",
    "sg:province":"CA",
    "sg:tags":[
        "consultant",
        "designer",
        "landscape"
    ],
    "sg:website":"http://exteriordesigns.homestead.com",
    "wof:name":"Exterior Designs Landscape & Pool Construction",
    "wof:placetype":"venue"
},
  "geometry": {"coordinates":[-121.762871,37.66242],"type":"Point"}
}