{
  "type": "Feature",
  "properties": {
    "iso:country":"US",
    "sg:address":"702 Wilshire Blvd",
    "sg:city":"Los Angeles",
    "sg:classifiers":[
        {
            "category":"Wholesale",
            "subcategory":"Durable Goods & Equipment",
            "type":"Manufacturing & Wholesale Goods"
        }
    ],
    "sg:phone":"+1 213 251 0005",
    "sg:postcode":"90017",
    "sg:province":"CA",
    "sg:tags":[
        "importer"
    ],
    "wof:name":"Joy Trading Co",
    "wof:placetype":"venue"
},
  "geometry": {"coordinates":[-118.258169,34.049285],"type":"Point"}
}