{
  "type": "Feature",
  "properties": {
    "addr:full":"1318 E. Valley Blvd. Alhambra CA 91801",
    "addr:housenumber":"1318",
    "addr:postcode":"91801",
    "addr:street":"E. Valley Blvd.",
    "iso:country":"US",
    "sg:address":"1318 E. Valley Blvd.",
    "sg:city":"Alhambra",
    "sg:classifiers":[
        {
            "category":"Travel",
            "subcategory":"Travel Agent",
            "type":"Entertainment"
        }
    ],
    "sg:phone":"+1 626 299 0999",
    "sg:postcode":"91801",
    "sg:province":"CA",
    "sg:website":"www.lailaitravel.com",
    "wof:name":"Lai Lai Travel",
    "wof:placetype":"venue"
},
  "geometry": {"coordinates":[-118.11059,34.079195],"type":"Point"}
}