{
  "type": "Feature",
  "properties": {
    "iso:country":"US",
    "sg:address":"21550 Circle Dr",
    "sg:city":"Tehachapi",
    "sg:classifiers":[
        {
            "category":"Real Estate",
            "subcategory":"Real Estate Services",
            "type":"Services"
        },
        {
            "category":"Real Estate",
            "subcategory":"Real Estate Agent",
            "type":"Services"
        }
    ],
    "sg:phone":"+1 661 822 1800",
    "sg:postcode":"93561",
    "sg:province":"CA",
    "sg:tags":[
        "buyer",
        "broker"
    ],
    "wof:name":"Adams Don Lands",
    "wof:placetype":"venue"
},
  "geometry": {"coordinates":[-118.49260599999999,35.132966],"type":"Point"}
}