{
  "type": "Feature",
  "properties": {
    "iso:country":"US",
    "sg:address":"5444 W Los Altos Ave",
    "sg:city":"Fresno",
    "sg:classifiers":[
        {
            "category":"Wholesale",
            "subcategory":"Vending Machines",
            "type":"Manufacturing & Wholesale Goods"
        }
    ],
    "sg:phone":"+1 559 277 3862",
    "sg:postcode":"93722",
    "sg:province":"CA",
    "wof:name":"H & H Vending",
    "wof:placetype":"venue"
},
  "geometry": {"coordinates":[-119.888564,36.832991],"type":"Point"}
}