{
  "type": "Feature",
  "properties": {
    "iso:country":"US",
    "sg:address":"110 Monterey Ave",
    "sg:city":"Capitola",
    "sg:classifiers":[
        {
            "category":"Restaurant",
            "type":"Food & Drink"
        }
    ],
    "sg:phone":"+1 831 464 2583",
    "sg:postcode":"95010",
    "sg:province":"CA",
    "sg:tags":[
        "new",
        "seafood",
        "american"
    ],
    "sg:website":"www.bwsteakhouse.com",
    "wof:name":"Bluewater Steakhouse",
    "wof:placetype":"venue"
},
  "geometry": {"coordinates":[-121.950588,36.972217],"type":"Point"}
}