{
  "type": "Feature",
  "properties": {
    "addr:full":"335 San Benito St Ste C Hollister CA 95023",
    "addr:housenumber":"335",
    "addr:postcode":"hollister ca 95023",
    "addr:street":"San Benito St Ste C",
    "iso:country":"US",
    "sg:address":"335 San Benito St Ste C",
    "sg:city":"Hollister",
    "sg:classifiers":[
        {
            "category":"Real Estate",
            "subcategory":"Real Estate Services",
            "type":"Services"
        },
        {
            "category":"Banks & Credit Unions",
            "subcategory":"Financial Services",
            "type":"Services"
        }
    ],
    "sg:phone":"+1 831 636 8240",
    "sg:postcode":"95023",
    "sg:province":"CA",
    "sg:tags":[
        "loan",
        "processing"
    ],
    "wof:name":"Shamrock Funding",
    "wof:placetype":"venue"
},
  "geometry": {"coordinates":[-121.40203099999999,36.85302],"type":"Point"}
}