{
  "type": "Feature",
  "properties": {
    "addr:full":"896 N 4th Ave Upland CA 91786",
    "addr:housenumber":"896",
    "addr:postcode":"91786",
    "addr:street":"N 4Th Ave",
    "iso:country":"US",
    "sg:address":"896 N 4th Ave",
    "sg:city":"Upland",
    "sg:classifiers":[
        {
            "category":"Shopping",
            "subcategory":"Catalog Store",
            "type":"Retail Goods"
        }
    ],
    "sg:phone":"+1 909 949 4413",
    "sg:postcode":"91786",
    "sg:province":"CA",
    "sg:tags":[
        "mail",
        "house"
    ],
    "wof:name":"Crosslands Knives & Things",
    "wof:placetype":"venue"
},
  "geometry": {"coordinates":[-117.645038,34.105086],"type":"Point"}
}