{
  "type": "Feature",
  "properties": {
    "iso:country":"US",
    "sg:address":"4322 Rubidoux Blvd",
    "sg:city":"Riverside",
    "sg:classifiers":[
        {
            "category":"Autos & Motor Vehicles",
            "subcategory":"Automobile Sales",
            "type":"Retail Goods"
        }
    ],
    "sg:phone":"+1 951 684 4280",
    "sg:postcode":"92509",
    "sg:province":"CA",
    "sg:tags":[
        "equipment",
        "aircraft",
        "parts",
        "supply"
    ],
    "sg:website":"www.polyfiber.com",
    "wof:name":"Poly-Fiber Inc",
    "wof:placetype":"venue"
},
  "geometry": {"coordinates":[-117.409485,33.994082],"type":"Point"}
}