{
  "type": "Feature",
  "properties": {
    "iso:country":"US",
    "sg:address":"3330 Shearwater Dr",
    "sg:city":"Sacramento",
    "sg:classifiers":[
        {
            "category":"Professional",
            "subcategory":"Secretarial Services",
            "type":"Services"
        }
    ],
    "sg:phone":"+1 916 646 6384",
    "sg:postcode":"95833",
    "sg:province":"CA",
    "sg:tags":[
        "resume"
    ],
    "wof:name":"On The Market Pro Resumes",
    "wof:placetype":"venue"
},
  "geometry": {"coordinates":[-121.536464,38.607118],"type":"Point"}
}