{
  "type": "Feature",
  "properties": {
    "iso:country":"US",
    "sg:address":"1648 State St",
    "sg:city":"San Diego",
    "sg:classifiers":[
        {
            "category":"Professional",
            "subcategory":"Lawyer & Legal Services",
            "type":"Services"
        }
    ],
    "sg:phone":"+1 619 231 3991",
    "sg:postcode":"92101",
    "sg:province":"CA",
    "sg:tags":[
        "attorney"
    ],
    "wof:name":"George Siddell Law Office",
    "wof:placetype":"venue"
},
  "geometry": {"coordinates":[-117.166567,32.722481],"type":"Point"}
}