{
  "type": "Feature",
  "properties": {
    "addr:full":"621 Irving Dr Burbank CA 91504",
    "addr:housenumber":"621",
    "addr:postcode":"91504",
    "addr:street":"Irving Dr",
    "iso:country":"US",
    "sg:address":"621 Irving Dr",
    "sg:city":"Burbank",
    "sg:classifiers":[
        {
            "category":"Communications",
            "subcategory":"Film & Video Production",
            "type":"Services"
        }
    ],
    "sg:phone":"+1 818 558 7007",
    "sg:postcode":"91504",
    "sg:province":"CA",
    "sg:tags":[
        "motion",
        "picture",
        "studio",
        "producer"
    ],
    "wof:name":"Fresco Films West",
    "wof:placetype":"venue"
},
  "geometry": {"coordinates":[-118.323926,34.204203],"type":"Point"}
}