{
  "type": "Feature",
  "properties": {
    "iso:country":"US",
    "sg:address":"845 Jackson St",
    "sg:city":"San Francisco",
    "sg:classifiers":[
        {
            "category":"Health Services",
            "subcategory":"Hospital",
            "type":"Services"
        }
    ],
    "sg:phone":"+1 415 982 2400",
    "sg:postcode":"94133",
    "sg:province":"CA",
    "sg:website":"www.chinesehospital-sf.org",
    "wof:name":"Chinese Hospital",
    "wof:placetype":"venue"
},
  "geometry": {"coordinates":[-122.40931999999999,37.795629],"type":"Point"}
}