{
  "type": "Feature",
  "properties": {
    "addr:full":"4835 Venice Blvd Los Angeles CA 90019",
    "addr:housenumber":"4835",
    "addr:postcode":"90019",
    "addr:street":"Venice Blvd",
    "iso:country":"US",
    "sg:address":"4835 Venice Blvd",
    "sg:city":"Los Angeles",
    "sg:classifiers":[
        {
            "category":"Banks & Credit Unions",
            "subcategory":"Bank",
            "type":"Services"
        }
    ],
    "sg:phone":"+1 323 931 1886",
    "sg:postcode":"90019",
    "sg:province":"CA",
    "wof:name":"Broadway Federal Bank Fsb",
    "wof:placetype":"venue"
},
  "geometry": {"coordinates":[-118.343002,34.046299],"type":"Point"}
}