{
  "type": "Feature",
  "properties": {
    "iso:country":"US",
    "sg:address":"1527 W Mission Blvd",
    "sg:city":"Ontario",
    "sg:classifiers":[
        {
            "category":"Retail",
            "subcategory":"Auto Repair",
            "type":"Services"
        }
    ],
    "sg:phone":"+1 909 626 8919",
    "sg:postcode":"91762",
    "sg:province":"CA",
    "sg:tags":[
        "body",
        "repairing",
        "automobile",
        "dent",
        "removal",
        "painting"
    ],
    "sg:website":"http://www.montclairautobody.com",
    "wof:name":"Montclair Auto Body",
    "wof:placetype":"venue"
},
  "geometry": {"coordinates":[-117.679197,34.055858],"type":"Point"}
}