{
  "type": "Feature",
  "properties": {
    "addr:full":"501 N Glendale Ave Glendale CA 91206",
    "addr:housenumber":"501",
    "addr:postcode":"91206",
    "addr:street":"N Glendale Ave",
    "iso:country":"US",
    "sg:address":"501 N Glendale Ave",
    "sg:city":"Glendale",
    "sg:classifiers":[
        {
            "category":"Government",
            "subcategory":"Office",
            "type":"Public Place"
        }
    ],
    "sg:phone":"+1 818 500 5762",
    "sg:postcode":"91206",
    "sg:province":"CA",
    "sg:tags":[
        "county",
        "program",
        "health"
    ],
    "wof:name":"Los Angeles County Health Svc",
    "wof:placetype":"venue"
},
  "geometry": {"coordinates":[-118.24363700000001,34.153545],"type":"Point"}
}