{
  "type": "Feature",
  "properties": {
    "addr:full":"170 Newport Center Dr Newport Beach CA 92660",
    "addr:housenumber":"170",
    "addr:postcode":"92660",
    "addr:street":"Newport Center Dr",
    "iso:country":"US",
    "sg:address":"170 Newport Center Dr",
    "sg:city":"Newport Beach",
    "sg:classifiers":[
        {
            "category":"Banks & Credit Unions",
            "subcategory":"Financial Services",
            "type":"Services"
        }
    ],
    "sg:phone":"+1 949 719 2351",
    "sg:postcode":"92660",
    "sg:province":"CA",
    "sg:tags":[
        "broker",
        "mortgage"
    ],
    "wof:name":"World Savings",
    "wof:placetype":"venue"
},
  "geometry": {"coordinates":[-117.87599899999999,33.612598],"type":"Point"}
}