{
  "type": "Feature",
  "properties": {
    "iso:country":"US",
    "sg:address":"134 Burns Dr",
    "sg:city":"Yuba City",
    "sg:classifiers":[
        {
            "category":"Utilities",
            "subcategory":"Refuse",
            "type":"Services"
        }
    ],
    "sg:phone":"+1 530 671 6900",
    "sg:postcode":"95991",
    "sg:province":"CA",
    "sg:tags":[
        "system"
    ],
    "wof:name":"Yuba Stter Hhld Hzardous Waste",
    "wof:placetype":"venue"
},
  "geometry": {"coordinates":[-121.613608,39.108307],"type":"Point"}
}