{
  "type": "Feature",
  "properties": {
    "iso:country":"US",
    "sg:address":"1210 Central Blvd",
    "sg:city":"Brentwood",
    "sg:classifiers":[
        {
            "category":"Building & Trades",
            "subcategory":"Construction",
            "type":"Services"
        }
    ],
    "sg:phone":"+1 925 240 9678",
    "sg:postcode":"94513",
    "sg:province":"CA",
    "sg:tags":[
        "housing",
        "contractor"
    ],
    "wof:name":"Western Pacific Housing",
    "wof:placetype":"venue"
},
  "geometry": {"coordinates":[-121.702912,37.935725],"type":"Point"}
}