{
  "type": "Feature",
  "properties": {
    "iso:country":"US",
    "sg:address":"17419 Graciosa Rd",
    "sg:city":"San Diego",
    "sg:classifiers":[
        {
            "category":"Food & Beverages",
            "subcategory":"Fruits & Vegetables",
            "type":"Retail Goods"
        }
    ],
    "sg:phone":"+1 858 673 0671",
    "sg:postcode":"92128",
    "sg:province":"CA",
    "sg:tags":[
        "juice"
    ],
    "wof:name":"Diagraphics Corp",
    "wof:placetype":"venue"
},
  "geometry": {"coordinates":[-117.07278100000001,33.030641],"type":"Point"}
}