{
  "type": "Feature",
  "properties": {
    "addr:full":"9266 Madison Ave Orangevale CA 95662",
    "addr:housenumber":"9266",
    "addr:postcode":"95662",
    "addr:street":"Madison Ave",
    "iso:country":"US",
    "sg:address":"9266 Madison Ave",
    "sg:city":"Orangevale",
    "sg:classifiers":[
        {
            "category":"Insurance",
            "subcategory":"Hazard Insurance",
            "type":"Services"
        }
    ],
    "sg:phone":"+1 916 987 2071",
    "sg:postcode":"95662",
    "sg:province":"CA",
    "sg:tags":[
        "commercial",
        "business"
    ],
    "sg:website":"http://www.franksorci.com",
    "wof:name":"Sorci Insurance Agency",
    "wof:placetype":"venue"
},
  "geometry": {"coordinates":[-121.20842399999999,38.669353],"type":"Point"}
}