{
  "type": "Feature",
  "properties": {
    "addr:full":"1016 E 12th St Oakland CA 94607",
    "addr:housenumber":"1016",
    "addr:postcode":"94607",
    "addr:street":"E 12Th St",
    "iso:country":"US",
    "sg:address":"1016 E 12th St",
    "sg:city":"Oakland",
    "sg:classifiers":[
        {
            "category":"Education",
            "subcategory":"Kindergarten",
            "type":"Public Place"
        }
    ],
    "sg:phone":"+1 510 763 8383",
    "sg:postcode":"94607",
    "sg:province":"CA",
    "sg:tags":[
        "school",
        "driving"
    ],
    "wof:name":"Eagle Driving School",
    "wof:placetype":"venue"
},
  "geometry": {"coordinates":[-122.250409,37.791225],"type":"Point"}
}