{
  "type": "Feature",
  "properties": {
    "addr:full":"6773 E Clinton Ave Fresno CA 93727",
    "addr:housenumber":"6773",
    "addr:postcode":"93727",
    "addr:street":"E Clinton Ave",
    "iso:country":"US",
    "sg:address":"6773 E Clinton Ave",
    "sg:city":"Fresno",
    "sg:classifiers":[
        {
            "category":"Education",
            "subcategory":"Dance Studio",
            "type":"Public Place"
        }
    ],
    "sg:phone":"+1 559 485 2542",
    "sg:postcode":"93727",
    "sg:province":"CA",
    "sg:tags":[
        "instruction",
        "dancing"
    ],
    "wof:name":"Bob Curran Dance Studio",
    "wof:placetype":"venue"
},
  "geometry": {"coordinates":[-119.66459500000001,36.77206],"type":"Point"}
}