{
  "type": "Feature",
  "properties": {
    "addr:full":"152 S Lasky Dr Beverly Hills CA 90212",
    "addr:housenumber":"152",
    "addr:postcode":"90212",
    "addr:street":"S Lasky Dr",
    "iso:country":"US",
    "sg:address":"152 S Lasky Dr",
    "sg:city":"Beverly Hills",
    "sg:classifiers":[
        {
            "category":"Social Services",
            "type":"Services"
        }
    ],
    "sg:phone":"+1 323 656 3033",
    "sg:postcode":"90212",
    "sg:province":"CA",
    "sg:tags":[
        "worker"
    ],
    "wof:name":"Marliese Hirsch",
    "wof:placetype":"venue"
},
  "geometry": {"coordinates":[-118.40989500000001,34.066318],"type":"Point"}
}