{
  "type": "Feature",
  "properties": {
    "iso:country":"US",
    "sg:address":"2390 Crenshaw Blvd",
    "sg:city":"Torrance",
    "sg:classifiers":[
        {
            "category":"Shopping",
            "subcategory":"Clothing, Apparel, & Fashions",
            "type":"Retail Goods"
        }
    ],
    "sg:phone":"+1 310 782 3776",
    "sg:postcode":"90501",
    "sg:province":"CA",
    "wof:name":"Milan",
    "wof:placetype":"venue"
},
  "geometry": {"coordinates":[-118.32831899999999,33.823258],"type":"Point"}
}