{
  "type": "Feature",
  "properties": {
    "addr:full":"1833 S Coast Hwy Oceanside CA 92054",
    "addr:housenumber":"1833",
    "addr:postcode":"92054",
    "addr:street":"S Coast Hwy",
    "iso:country":"US",
    "sg:address":"1833 S Coast Hwy",
    "sg:city":"Oceanside",
    "sg:classifiers":[
        {
            "category":"Personal",
            "subcategory":"Nail Salon",
            "type":"Services"
        }
    ],
    "sg:phone":"+1 760 721 4876",
    "sg:postcode":"92054",
    "sg:province":"CA",
    "wof:name":"T & T Nails",
    "wof:placetype":"venue"
},
  "geometry": {"coordinates":[-117.361,33.174301],"type":"Point"}
}