{
  "type": "Feature",
  "properties": {
    "addr:full":"25060 W Ave Stanford Santa Clarita CA 91355",
    "addr:housenumber":"25060",
    "addr:postcode":"91355",
    "addr:street":"W Ave",
    "iso:country":"US",
    "sg:address":"25060 W Ave Stanford",
    "sg:city":"Santa Clarita",
    "sg:classifiers":[
        {
            "category":"Professional",
            "subcategory":"Computer Services",
            "type":"Services"
        }
    ],
    "sg:phone":"+1 661 295 5766",
    "sg:postcode":"91355",
    "sg:province":"CA",
    "sg:website":"www.arieypc.com",
    "wof:name":"Ariey Pro Computers",
    "wof:placetype":"venue"
},
  "geometry": {"coordinates":[-118.57713800000001,34.435253],"type":"Point"}
}