{
  "type": "Feature",
  "properties": {
    "iso:country":"US",
    "sg:address":"1051 Bryan Ave",
    "sg:city":"Tustin",
    "sg:classifiers":[
        {
            "category":"Health Services",
            "subcategory":"Hospital",
            "type":"Services"
        },
        {
            "category":"Social Services",
            "subcategory":"Retirement Home",
            "type":"Services"
        }
    ],
    "sg:phone":"+1 714 832 6780",
    "sg:postcode":"92780",
    "sg:province":"CA",
    "wof:name":"Tustin Care Center",
    "wof:placetype":"venue"
},
  "geometry": {"coordinates":[-117.816002,33.743698],"type":"Point"}
}