{
  "type": "Feature",
  "properties": {
    "iso:country":"US",
    "sg:address":"20550 E Kettleman Ln",
    "sg:city":"Lodi",
    "sg:classifiers":[
        {
            "category":"Manufacturing",
            "subcategory":"Metals",
            "type":"Manufacturing & Wholesale Goods"
        }
    ],
    "sg:phone":"+1 209 727 5656",
    "sg:postcode":"95240",
    "sg:province":"CA",
    "sg:tags":[
        "fabrication",
        "structural"
    ],
    "wof:name":"Wentzel Fabrication",
    "wof:placetype":"venue"
},
  "geometry": {"coordinates":[-121.064722,38.118482],"type":"Point"}
}