{
  "type": "Feature",
  "properties": {
    "addr:full":"1637 Staunton Avenue Los Angeles CA 90021",
    "addr:housenumber":"1637",
    "addr:postcode":"90021",
    "addr:street":"Staunton Avenue",
    "iso:country":"US",
    "sg:address":"1637 Staunton Avenue",
    "sg:city":"Los Angeles",
    "sg:classifiers":[
        {
            "category":"Shopping",
            "subcategory":"Clothing, Apparel, & Fashions",
            "type":"Retail Goods"
        }
    ],
    "sg:phone":"+1 213 746 0300",
    "sg:postcode":"90021",
    "sg:province":"CA",
    "sg:tags":[
        "clothing",
        "women's"
    ],
    "wof:name":"Pacific Silk Screen",
    "wof:placetype":"venue"
},
  "geometry": {"coordinates":[-118.241345,34.022198],"type":"Point"}
}