{
  "type": "Feature",
  "properties": {
    "iso:country":"US",
    "sg:address":"335 Melody Ln",
    "sg:city":"Salinas",
    "sg:classifiers":[
        {
            "category":"Professional",
            "subcategory":"Lawyer & Legal Services",
            "type":"Services"
        }
    ],
    "sg:phone":"+1 831 753 6125",
    "sg:postcode":"93901",
    "sg:province":"CA",
    "sg:tags":[
        "attorney"
    ],
    "wof:name":"Robert J Ernst III Law Offices",
    "wof:placetype":"venue"
},
  "geometry": {"coordinates":[-121.655277,36.673115],"type":"Point"}
}