{
  "type": "Feature",
  "properties": {
    "addr:full":"305 Fairmount Ave Oakland CA 94611",
    "addr:housenumber":"305",
    "addr:postcode":"94611",
    "addr:street":"Fairmount Ave",
    "iso:country":"US",
    "sg:address":"305 Fairmount Ave",
    "sg:city":"Oakland",
    "sg:classifiers":[
        {
            "category":"Manufacturing",
            "subcategory":"Buildings",
            "type":"Manufacturing & Wholesale Goods"
        },
        {
            "category":"Building & Trades",
            "subcategory":"Construction",
            "type":"Services"
        }
    ],
    "sg:phone":"+1 510 836 1302",
    "sg:postcode":"94611",
    "sg:province":"CA",
    "sg:tags":[
        "home",
        "builder",
        "contractor"
    ],
    "wof:name":"Hong Construction",
    "wof:placetype":"venue"
},
  "geometry": {"coordinates":[-122.258979,37.817512],"type":"Point"}
}