{
  "type": "Feature",
  "properties": {
    "addr:full":"2912 Telegraph Ave Oakland CA 94609",
    "addr:housenumber":"2912",
    "addr:postcode":"94609",
    "addr:street":"Telegraph Ave",
    "iso:country":"US",
    "sg:address":"2912 Telegraph Ave",
    "sg:city":"Oakland",
    "sg:classifiers":[
        {
            "category":"Shopping",
            "type":"Retail Goods"
        }
    ],
    "sg:phone":"+1 510 465 7384",
    "sg:postcode":"94609",
    "sg:province":"CA",
    "sg:tags":[
        "cosmetic",
        "perfume"
    ],
    "wof:name":"Shiseido Anna's Cosmetics",
    "wof:placetype":"venue"
},
  "geometry": {"coordinates":[-122.267256,37.818834],"type":"Point"}
}