{
  "type": "Feature",
  "properties": {
    "addr:full":"1808 Harmon St Berkeley CA 94703",
    "addr:housenumber":"1808",
    "addr:postcode":"94703",
    "addr:street":"Harmon St",
    "iso:country":"US",
    "sg:address":"1808 Harmon St",
    "sg:city":"Berkeley",
    "sg:classifiers":[
        {
            "category":"Wholesale",
            "subcategory":"Construction Materials",
            "type":"Manufacturing & Wholesale Goods"
        }
    ],
    "sg:phone":"+1 510 547 6464",
    "sg:postcode":"94703",
    "sg:province":"CA",
    "sg:tags":[
        "glass"
    ],
    "wof:name":"Research & Development Glass",
    "wof:placetype":"venue"
},
  "geometry": {"coordinates":[-122.271359,37.849594],"type":"Point"}
}