{
  "type": "Feature",
  "properties": {
    "iso:country":"US",
    "sg:address":"2810 Canon St",
    "sg:city":"San Diego",
    "sg:classifiers":[
        {
            "category":"Professional",
            "subcategory":"Business Services",
            "type":"Services"
        }
    ],
    "sg:phone":"+1 619 222 5228",
    "sg:postcode":"92106",
    "sg:province":"CA",
    "sg:tags":[
        "embroidery"
    ],
    "wof:name":"Graphix Group",
    "wof:placetype":"venue"
},
  "geometry": {"coordinates":[-117.230692,32.720869],"type":"Point"}
}