{
  "type": "Feature",
  "properties": {
    "iso:country":"US",
    "sg:address":"73815 S Delleker Rd",
    "sg:city":"Portola",
    "sg:classifiers":[
        {
            "category":"Wholesale",
            "subcategory":"Painting Supplies",
            "type":"Manufacturing & Wholesale Goods"
        },
        {
            "category":"Home & Garden",
            "subcategory":"Garden Supply",
            "type":"Retail Goods"
        },
        {
            "category":"Wholesale",
            "subcategory":"Construction Materials",
            "type":"Manufacturing & Wholesale Goods"
        },
        {
            "category":"Home & Garden",
            "subcategory":"Hardware",
            "type":"Retail Goods"
        }
    ],
    "sg:phone":"+1 530 832 4444",
    "sg:postcode":"96122",
    "sg:province":"CA",
    "sg:tags":[
        "lawn",
        "paint",
        "equipment",
        "part",
        "plumbing",
        "fixtures",
        "store"
    ],
    "sg:website":"http://www.truevalue.com",
    "wof:name":"Longfellow True Value Building Supply",
    "wof:placetype":"venue"
},
  "geometry": {"coordinates":[-120.49901,39.805115],"type":"Point"}
}