{
  "type": "Feature",
  "properties": {
    "addr:full":"44105 15th St W Ste 207 Lancaster CA 93534",
    "addr:housenumber":"44105",
    "addr:postcode":"93534",
    "addr:street":"15Th St W Ste 207",
    "iso:country":"US",
    "sg:address":"44105 15th St W Ste 207",
    "sg:city":"Lancaster",
    "sg:classifiers":[
        {
            "category":"Health Services",
            "subcategory":"Doctor",
            "type":"Services"
        },
        {
            "category":"Health Services",
            "subcategory":"Clinic",
            "type":"Services"
        },
        {
            "category":"Health Services",
            "subcategory":"Hospital",
            "type":"Services"
        }
    ],
    "sg:phone":"+1 661 948 5928",
    "sg:postcode":"93534",
    "sg:province":"CA",
    "sg:tags":[
        "physician",
        "oncology",
        "radiology",
        "cancer",
        "pediatrics-radiology",
        "surgeons",
        "hematology",
        "blood",
        "gynecologic",
        "treatment"
    ],
    "sg:website":"http://www.avcancercenter.com",
    "wof:name":"Antelope Valley Cancer Center",
    "wof:placetype":"venue"
},
  "geometry": {"coordinates":[-118.156837,34.684113],"type":"Point"}
}