{
  "type": "Feature",
  "properties": {
    "addr:full":"5611 Kanan Road Agoura Hills CA 91301",
    "addr:housenumber":"5611",
    "addr:postcode":"91301",
    "addr:street":"Kanan Road",
    "iso:country":"US",
    "sg:address":"5611 Kanan Road",
    "sg:city":"Agoura Hills",
    "sg:classifiers":[
        {
            "category":"Restaurant",
            "type":"Food & Drink"
        }
    ],
    "sg:phone":"+1 818 991 8799",
    "sg:postcode":"91301",
    "sg:province":"CA",
    "sg:tags":[
        "middle",
        "eastern"
    ],
    "sg:website":"www.falafelgrill.com",
    "wof:name":"Falafel Grill",
    "wof:placetype":"venue"
},
  "geometry": {"coordinates":[-118.758881,34.150833],"type":"Point"}
}