{
  "type": "Feature",
  "properties": {
    "addr:full":"4811 Geary Boulevard San Francisco CA 94118",
    "addr:housenumber":"4811",
    "addr:postcode":"94118",
    "addr:street":"Geary Boulevard",
    "iso:country":"US",
    "sg:address":"4811 Geary Boulevard",
    "sg:city":"San Francisco",
    "sg:classifiers":[
        {
            "category":"Health Services",
            "subcategory":"Clinic",
            "type":"Services"
        },
        {
            "category":"Shopping",
            "subcategory":"Tobacco",
            "type":"Retail Goods"
        }
    ],
    "sg:phone":"+1 415 386 4367",
    "sg:postcode":"94118",
    "sg:province":"CA",
    "sg:tags":[
        "shop",
        "medical"
    ],
    "sg:website":"thehempcenter.com",
    "wof:name":"The Hemp Center",
    "wof:placetype":"venue"
},
  "geometry": {"coordinates":[-122.471132,37.7804],"type":"Point"}
}