{
  "type": "Feature",
  "properties": {
    "iso:country":"US",
    "sg:address":"2916 Main St",
    "sg:city":"Santa Monica",
    "sg:classifiers":[
        {
            "category":"Food & Beverages",
            "subcategory":"Groceries & Convenience Stores",
            "type":"Retail Goods"
        },
        {
            "category":"Food & Beverages",
            "subcategory":"Liquor & Beverages",
            "type":"Retail Goods"
        }
    ],
    "sg:phone":"+1 310 399 8757",
    "sg:postcode":"90405",
    "sg:province":"CA",
    "sg:tags":[
        "market",
        "alcoholic"
    ],
    "wof:name":"Pagliari's Market & Deli",
    "wof:placetype":"venue"
},
  "geometry": {"coordinates":[-118.481089,33.999431],"type":"Point"}
}