{
  "type": "Feature",
  "properties": {
    "addr:full":"24325 San Fernando Rd Newhall CA 91321",
    "addr:housenumber":"24325",
    "addr:postcode":"91321",
    "addr:street":"San Fernando Rd",
    "iso:country":"US",
    "sg:address":"24325 San Fernando Rd",
    "sg:city":"Newhall",
    "sg:classifiers":[
        {
            "category":"Professional",
            "subcategory":"Accounting & Tax Preparation",
            "type":"Services"
        }
    ],
    "sg:phone":"+1 661 254 8297",
    "sg:postcode":"91321",
    "sg:province":"CA",
    "sg:tags":[
        "accountant"
    ],
    "wof:name":"Hyatt & Gidlow",
    "wof:placetype":"venue"
},
  "geometry": {"coordinates":[-118.528346,34.379254],"type":"Point"}
}