{
  "type": "Feature",
  "properties": {
    "addr:full":"950 Gilman St Berkeley CA 94710",
    "addr:housenumber":"950",
    "addr:postcode":"94710",
    "addr:street":"Gilman St",
    "iso:country":"US",
    "sg:address":"950 Gilman St",
    "sg:city":"Berkeley",
    "sg:classifiers":[
        {
            "category":"Professional",
            "subcategory":"Research",
            "type":"Services"
        }
    ],
    "sg:phone":"+1 510 525 4822",
    "sg:postcode":"94710",
    "sg:province":"CA",
    "sg:tags":[
        "publisher",
        "ecological",
        "environmental"
    ],
    "sg:website":"http://www.pkpress.com",
    "wof:name":"Aquifer Solutions Inc",
    "wof:placetype":"venue"
},
  "geometry": {"coordinates":[-122.298997,37.879847],"type":"Point"}
}