{
  "type": "Feature",
  "properties": {
    "iso:country":"US",
    "sg:address":"639 Saint Marks St Ste A",
    "sg:city":"Redding",
    "sg:classifiers":[
        {
            "category":"Retail",
            "subcategory":"Laundry & Dry Cleaning",
            "type":"Services"
        }
    ],
    "sg:phone":"+1 530 243 8691",
    "sg:postcode":"96003",
    "sg:province":"CA",
    "sg:tags":[
        "cleaner",
        "rug",
        "carpet"
    ],
    "wof:name":"King Carpet Specialists",
    "wof:placetype":"venue"
},
  "geometry": {"coordinates":[-122.392174,40.616901],"type":"Point"}
}