{
  "type": "Feature",
  "properties": {
    "addr:full":"1516 E South St Long Beach CA 90805",
    "addr:housenumber":"1516 e",
    "addr:postcode":"90805",
    "addr:street":"South St",
    "iso:country":"US",
    "sg:address":"1516 E South St",
    "sg:city":"Long Beach",
    "sg:classifiers":[
        {
            "category":"Shopping",
            "subcategory":"Pharmacy",
            "type":"Retail Goods"
        }
    ],
    "sg:phone":"+1 562 422 2256",
    "sg:postcode":"90805",
    "sg:province":"CA",
    "wof:name":"Big A Pharmacy",
    "wof:placetype":"venue"
},
  "geometry": {"coordinates":[-118.17390399999999,33.860034],"type":"Point"}
}