{
  "type": "Feature",
  "properties": {
    "addr:full":"633 E Pacific Coast Hwy Long Beach CA 90806",
    "addr:housenumber":"633",
    "addr:postcode":"90806",
    "addr:street":"E Pacific Coast Hwy",
    "iso:country":"US",
    "sg:address":"633 E Pacific Coast Hwy",
    "sg:city":"Long Beach",
    "sg:classifiers":[
        {
            "category":"Retail",
            "subcategory":"Repair Shop",
            "type":"Services"
        }
    ],
    "sg:phone":"+1 562 599 3441",
    "sg:postcode":"90806",
    "sg:province":"CA",
    "sg:tags":[
        "microwave",
        "oven"
    ],
    "wof:name":"AVT Electronics",
    "wof:placetype":"venue"
},
  "geometry": {"coordinates":[-118.184783,33.789926],"type":"Point"}
}