{
  "type": "Feature",
  "properties": {
    "addr:full":"34484 Colonia Feliz Davis CA 95616",
    "addr:postcode":"34484;95616",
    "iso:country":"US",
    "sg:address":"34484 Colonia Feliz",
    "sg:city":"Davis",
    "sg:classifiers":[
        {
            "category":"Manufacturing",
            "subcategory":"Lumber",
            "type":"Manufacturing & Wholesale Goods"
        }
    ],
    "sg:phone":"+1 530 756 2402",
    "sg:postcode":"95616",
    "sg:province":"CA",
    "sg:tags":[
        "hardwood",
        "mill"
    ],
    "wof:name":"California Contemporary",
    "wof:placetype":"venue"
},
  "geometry": {"coordinates":[-121.859216,38.5691],"type":"Point"}
}