{
  "type": "Feature",
  "properties": {
    "addr:full":"Exit Cafe 156 Eddy St San Francisco CA 94102",
    "addr:housenumber":"156",
    "addr:postcode":"94102",
    "addr:street":"Eddy St",
    "iso:country":"US",
    "sg:address":"Exit Cafe 156 Eddy St",
    "sg:city":"San Francisco",
    "sg:classifiers":[
        {
            "category":"Arts & Performance",
            "subcategory":"Arts Center",
            "type":"Entertainment"
        }
    ],
    "sg:phone":"+1 415 673 3847",
    "sg:postcode":"94102",
    "sg:province":"CA",
    "sg:tags":[
        "performing"
    ],
    "sg:website":"www.theexit.org/now.html",
    "wof:name":"The Pandora Experiment",
    "wof:placetype":"venue"
},
  "geometry": {"coordinates":[-122.41027,37.784259],"type":"Point"}
}