{
  "type": "Feature",
  "properties": {
    "addr:full":"32017 Live Oak Canyon Rd Redlands CA 92373",
    "addr:housenumber":"32017",
    "addr:postcode":"92373",
    "addr:street":"Live Oak Canyon Rd",
    "iso:country":"US",
    "sg:address":"32017 Live Oak Canyon Rd",
    "sg:city":"Redlands",
    "sg:classifiers":[
        {
            "category":"Farming",
            "subcategory":"Livestock Farm",
            "type":"Manufacturing & Wholesale Goods"
        }
    ],
    "sg:phone":"+1 951 237 0441",
    "sg:postcode":"92373",
    "sg:province":"CA",
    "sg:tags":[
        "animal",
        "general"
    ],
    "wof:name":"Amity Storage Ranch",
    "wof:placetype":"venue"
},
  "geometry": {"coordinates":[-117.10650800000001,34.0082],"type":"Point"}
}