{
  "type": "Feature",
  "properties": {
    "addr:full":"20671 Lake Forest Dr Lake Forest CA 92630",
    "addr:housenumber":"20671",
    "addr:postcode":"92630",
    "addr:street":"Lake Forest Dr",
    "iso:country":"US",
    "sg:address":"20671 Lake Forest Dr",
    "sg:city":"Lake Forest",
    "sg:classifiers":[
        {
            "category":"Health Services",
            "subcategory":"Chiropractor",
            "type":"Services"
        }
    ],
    "sg:phone":"+1 949 587 1717",
    "sg:postcode":"92630",
    "sg:province":"CA",
    "wof:name":"A A Accident & Injury Specs",
    "wof:placetype":"venue"
},
  "geometry": {"coordinates":[-117.688253,33.645928],"type":"Point"}
}