{
  "type": "Feature",
  "properties": {
    "iso:country":"US",
    "sg:address":"186 Emilia Ln",
    "sg:city":"Fallbrook",
    "sg:classifiers":[
        {
            "category":"Banks & Credit Unions",
            "subcategory":"Financial Services",
            "type":"Services"
        }
    ],
    "sg:phone":"+1 760 728 7574",
    "sg:postcode":"92028",
    "sg:province":"CA",
    "sg:tags":[
        "trust",
        "management"
    ],
    "wof:name":"Ball William C & Jean R Trust",
    "wof:placetype":"venue"
},
  "geometry": {"coordinates":[-117.214788,33.380734],"type":"Point"}
}