{
  "type": "Feature",
  "properties": {
    "iso:country":"US",
    "sg:address":"865 S Western Avenue",
    "sg:city":"Los Angeles",
    "sg:classifiers":[
        {
            "category":"Personal",
            "subcategory":"Shoe Repair & Shine",
            "type":"Services"
        }
    ],
    "sg:phone":"+1 213 383 2684",
    "sg:postcode":"90005",
    "sg:province":"CA",
    "wof:name":"Western Shoe Repair",
    "wof:placetype":"venue"
},
  "geometry": {"coordinates":[-118.308933,34.056151],"type":"Point"}
}