{
  "type": "Feature",
  "properties": {
    "iso:country":"US",
    "sg:address":"253 Bodem St",
    "sg:city":"Modesto",
    "sg:classifiers":[
        {
            "category":"Social Services",
            "subcategory":"Adult Care",
            "type":"Services"
        }
    ],
    "sg:phone":"+1 209 524 2129",
    "sg:postcode":"95350",
    "sg:province":"CA",
    "sg:tags":[
        "home",
        "residential"
    ],
    "wof:name":"Savala Guest Home",
    "wof:placetype":"venue"
},
  "geometry": {"coordinates":[-120.98547600000001,37.647862],"type":"Point"}
}