{
  "type": "Feature",
  "properties": {
    "addr:full":"3140 Naglee Rd Tracy CA 95304",
    "addr:housenumber":"3140",
    "addr:postcode":"95304",
    "addr:street":"Naglee Rd",
    "iso:country":"US",
    "sg:address":"3140 Naglee Rd",
    "sg:city":"Tracy",
    "sg:classifiers":[
        {
            "category":"Fast Food",
            "type":"Food & Drink"
        },
        {
            "category":"Restaurant",
            "type":"Food & Drink"
        }
    ],
    "sg:phone":"+1 209 835 9926",
    "sg:postcode":"95304",
    "sg:province":"CA",
    "sg:tags":[
        "style",
        "family",
        "american",
        "take",
        "pasta",
        "italian"
    ],
    "sg:website":"http://www.olivegarden.com",
    "wof:name":"Olive Garden",
    "wof:placetype":"venue"
},
  "geometry": {"coordinates":[-121.462321,37.758636],"type":"Point"}
}