{
  "type": "Feature",
  "properties": {
    "addr:full":"2214 Torrance Blvd Ste 204 Torrance CA 90501",
    "addr:housenumber":"2214",
    "addr:postcode":"90501",
    "addr:street":"Torrance Blvd Ste 204",
    "iso:country":"US",
    "sg:address":"2214 Torrance Blvd Ste 204",
    "sg:city":"Torrance",
    "sg:classifiers":[
        {
            "category":"Building & Trades",
            "subcategory":"Cleaning & Sanitation",
            "type":"Services"
        }
    ],
    "sg:phone":"+1 310 329 2901",
    "sg:postcode":"90501",
    "sg:province":"CA",
    "sg:tags":[
        "home"
    ],
    "wof:name":"Dana's Housekeeping Personnel Service Llc",
    "wof:placetype":"venue"
},
  "geometry": {"coordinates":[-118.31500200000001,33.827599],"type":"Point"}
}