{
  "type": "Feature",
  "properties": {
    "iso:country":"US",
    "sg:address":"414 Turney St",
    "sg:city":"Sausalito",
    "sg:classifiers":[
        {
            "category":"Wholesale",
            "subcategory":"Wine & Distilled Alcoholic Beverages",
            "type":"Manufacturing & Wholesale Goods"
        }
    ],
    "sg:phone":"+1 510 233 8466",
    "sg:postcode":"94965",
    "sg:province":"CA",
    "sg:tags":[
        "broker"
    ],
    "wof:name":"Tutto-Vino",
    "wof:placetype":"venue"
},
  "geometry": {"coordinates":[-122.486358,37.858939],"type":"Point"}
}