{
  "type": "Feature",
  "properties": {
    "addr:full":"23 San Angelo Rancho Santa Margarita CA 92688",
    "addr:housenumber":"23",
    "addr:postcode":"92688",
    "addr:street":"San Angelo",
    "iso:country":"US",
    "sg:address":"23 San Angelo",
    "sg:city":"Rancho Santa Margarita",
    "sg:classifiers":[
        {
            "category":"Professional",
            "type":"Services"
        }
    ],
    "sg:phone":"+1 949 598 5328",
    "sg:postcode":"92688",
    "sg:province":"CA",
    "wof:name":"Endless Fx",
    "wof:placetype":"venue"
},
  "geometry": {"coordinates":[-117.588611,33.636479],"type":"Point"}
}