{
  "type": "Feature",
  "properties": {
    "iso:country":"US",
    "sg:address":"650 Polk St",
    "sg:city":"San Francisco",
    "sg:classifiers":[
        {
            "category":"Autos & Motor Vehicles",
            "subcategory":"Auto Supplies",
            "type":"Retail Goods"
        }
    ],
    "sg:phone":"+1 415 409 1800",
    "sg:postcode":"94102",
    "sg:province":"CA",
    "sg:tags":[
        "automobile",
        "stereo",
        "installation",
        "alarm"
    ],
    "wof:name":"Audiologix",
    "wof:placetype":"venue"
},
  "geometry": {"coordinates":[-122.41885499999999,37.78283],"type":"Point"}
}