{
  "type": "Feature",
  "properties": {
    "addr:full":"14350 Pioneer Blvd Norwalk CA 90650",
    "addr:housenumber":"14350",
    "addr:postcode":"90650",
    "addr:street":"Pioneer Blvd",
    "iso:country":"US",
    "sg:address":"14350 Pioneer Blvd",
    "sg:city":"Norwalk",
    "sg:classifiers":[
        {
            "category":"Restaurant",
            "type":"Food & Drink"
        }
    ],
    "sg:phone":"+1 562 863 2290",
    "sg:postcode":"90650",
    "sg:province":"CA",
    "wof:name":"Noemi's Tortilleria",
    "wof:placetype":"venue"
},
  "geometry": {"coordinates":[-118.083,33.9007],"type":"Point"}
}