{
  "type": "Feature",
  "properties": {
    "iso:country":"US",
    "sg:address":"13655 Hwy 8 Bus",
    "sg:city":"El Cajon",
    "sg:classifiers":[
        {
            "category":"Building & Trades",
            "subcategory":"Plumbing",
            "type":"Services"
        }
    ],
    "sg:phone":"+1 619 590 0156",
    "sg:postcode":"92021",
    "sg:province":"CA",
    "sg:tags":[
        "air",
        "installation",
        "conditioning",
        "heating"
    ],
    "wof:name":"Quality Heating and AC",
    "wof:placetype":"venue"
},
  "geometry": {"coordinates":[-116.895167,32.839239],"type":"Point"}
}