{
  "type": "Feature",
  "properties": {
    "addr:full":"1172 Prospect St La Jolla CA 92037",
    "addr:housenumber":"1172",
    "addr:postcode":"92037",
    "addr:street":"Prospect St",
    "iso:country":"US",
    "sg:address":"1172 Prospect St",
    "sg:city":"La Jolla",
    "sg:classifiers":[
        {
            "category":"Ice Cream",
            "type":"Food & Drink"
        }
    ],
    "sg:menulink":"http://www.allmenus.com/ca/san-diego/232760-haagen-dazs/menu/",
    "sg:phone":"+1 858 459 4381",
    "sg:postcode":"92037",
    "sg:province":"CA",
    "sg:tags":[
        "american"
    ],
    "wof:name":"Haagen Dazs",
    "wof:placetype":"venue"
},
  "geometry": {"coordinates":[-117.273101,32.849039],"type":"Point"}
}