{
  "type": "Feature",
  "properties": {
    "addr:full":"3285 Edward Ave Santa Clara CA 95054",
    "addr:housenumber":"3285",
    "addr:postcode":"95054",
    "addr:street":"Edward Ave",
    "iso:country":"US",
    "sg:address":"3285 Edward Ave",
    "sg:city":"Santa Clara",
    "sg:classifiers":[
        {
            "category":"Manufacturing",
            "subcategory":"Tools & Machinery",
            "type":"Manufacturing & Wholesale Goods"
        }
    ],
    "sg:phone":"+1 408 844 9300",
    "sg:postcode":"95054",
    "sg:province":"CA",
    "sg:tags":[
        "lubricating",
        "system",
        "devices"
    ],
    "wof:name":"Central Equipment Svc",
    "wof:placetype":"venue"
},
  "geometry": {"coordinates":[-121.939926,37.38343],"type":"Point"}
}