{
  "type": "Feature",
  "properties": {
    "addr:full":"8531 Mariners Dr Stockton CA 95219",
    "addr:housenumber":"8531",
    "addr:postcode":"95219",
    "addr:street":"Mariners Dr",
    "iso:country":"US",
    "sg:address":"8531 Mariners Dr",
    "sg:city":"Stockton",
    "sg:classifiers":[
        {
            "category":"Restaurant",
            "type":"Food & Drink"
        }
    ],
    "sg:phone":"+1 209 477 5606",
    "sg:postcode":"95219",
    "sg:province":"CA",
    "wof:name":"Subway Sandwiches & Salads",
    "wof:placetype":"venue"
},
  "geometry": {"coordinates":[-121.361054,38.023859],"type":"Point"}
}