{
  "type": "Feature",
  "properties": {
    "addr:full":"233 W Main St Visalia CA 93291",
    "addr:housenumber":"233",
    "addr:postcode":"93291",
    "addr:street":"W Main St",
    "iso:country":"US",
    "sg:address":"233 W Main St",
    "sg:city":"Visalia",
    "sg:classifiers":[
        {
            "category":"Professional",
            "type":"Services"
        },
        {
            "category":"Coffee & Tea",
            "type":"Food & Drink"
        },
        {
            "category":"Restaurant",
            "type":"Food & Drink"
        }
    ],
    "sg:phone":"+1 559 741 1171",
    "sg:postcode":"93291",
    "sg:province":"CA",
    "sg:tags":[
        "espresso",
        "caterer"
    ],
    "sg:website":"http://www.mainstreetcafe.org",
    "wof:name":"Main Street Cafe",
    "wof:placetype":"venue"
},
  "geometry": {"coordinates":[-119.293818,36.330181],"type":"Point"}
}