{
  "type": "Feature",
  "properties": {
    "iso:country":"US",
    "sg:address":"839 W Washington St",
    "sg:city":"Eureka",
    "sg:classifiers":[
        {
            "category":"Professional",
            "subcategory":"Business Services",
            "type":"Services"
        },
        {
            "category":"Manufacturing",
            "subcategory":"Wood Products",
            "type":"Manufacturing & Wholesale Goods"
        },
        {
            "category":"Home & Garden",
            "subcategory":"Building Materials",
            "type":"Retail Goods"
        },
        {
            "category":"Building & Trades",
            "subcategory":"Construction",
            "type":"Services"
        },
        {
            "category":"Manufacturing",
            "subcategory":"Building Materials",
            "type":"Manufacturing & Wholesale Goods"
        }
    ],
    "sg:phone":"+1 707 443 7089",
    "sg:postcode":"95501",
    "sg:province":"CA",
    "sg:tags":[
        "roofing",
        "supply",
        "consultant",
        "specialty",
        "drafting",
        "equipment",
        "lumber",
        "insulation"
    ],
    "sg:website":"http://www.schmidbauerbuildingsupply.com",
    "wof:name":"Schmidbauer Building Supply",
    "wof:placetype":"venue"
},
  "geometry": {"coordinates":[-124.179152,40.798241],"type":"Point"}
}