{
  "type": "Feature",
  "properties": {
    "iso:country":"US",
    "sg:address":"2909 Community Ave",
    "sg:city":"La Crescenta",
    "sg:classifiers":[
        {
            "category":"Banks & Credit Unions",
            "subcategory":"Investment Brokerage",
            "type":"Services"
        }
    ],
    "sg:phone":"+1 818 248 5558",
    "sg:postcode":"91214",
    "sg:province":"CA",
    "sg:tags":[
        "stock",
        "bond"
    ],
    "wof:name":"GBS Financial",
    "wof:placetype":"venue"
},
  "geometry": {"coordinates":[-118.243775,34.224786],"type":"Point"}
}