{
  "type": "Feature",
  "properties": {
    "iso:country":"US",
    "sg:address":"11059 Garvey Ave",
    "sg:city":"El Monte",
    "sg:classifiers":[
        {
            "category":"Autos & Motor Vehicles",
            "subcategory":"Automobile Sales",
            "type":"Retail Goods"
        }
    ],
    "sg:phone":"+1 626 575 1218",
    "sg:postcode":"91733",
    "sg:province":"CA",
    "sg:tags":[
        "car",
        "used",
        "dealer"
    ],
    "wof:name":"Bel-Rich Auto Sales Inc",
    "wof:placetype":"venue"
},
  "geometry": {"coordinates":[-118.03570999999999,34.06283],"type":"Point"}
}