{
  "type": "Feature",
  "properties": {
    "iso:country":"US",
    "sg:address":"1683 Copenhagen Dr",
    "sg:city":"Solvang",
    "sg:classifiers":[
        {
            "category":"Shopping",
            "subcategory":"Gifts & Souvenirs",
            "type":"Retail Goods"
        }
    ],
    "sg:phone":"+1 805 693 1250",
    "sg:postcode":"93463",
    "sg:province":"CA",
    "sg:tags":[
        "shop"
    ],
    "wof:name":"Honey's",
    "wof:placetype":"venue"
},
  "geometry": {"coordinates":[-120.139199,34.594793],"type":"Point"}
}