{
  "type": "Feature",
  "properties": {
    "iso:country":"US",
    "sg:address":"9764 Stephens St",
    "sg:city":"Delhi",
    "sg:classifiers":[
        {
            "category":"Autos & Motor Vehicles",
            "subcategory":"Automobile Sales",
            "type":"Retail Goods"
        }
    ],
    "sg:phone":"+1 209 667 1904",
    "sg:postcode":"95315",
    "sg:province":"CA",
    "sg:tags":[
        "car",
        "dealer"
    ],
    "wof:name":"Valadez Used Cars",
    "wof:placetype":"venue"
},
  "geometry": {"coordinates":[-120.776445,37.430546],"type":"Point"}
}