{
  "type": "Feature",
  "properties": {
    "addr:full":"2504 el Camino Real Redwood City CA 94061",
    "addr:housenumber":"2504",
    "addr:postcode":"94061",
    "addr:street":"El Camino Real",
    "iso:country":"US",
    "sg:address":"2504 el Camino Real",
    "sg:city":"Redwood City",
    "sg:classifiers":[
        {
            "category":"Retail",
            "subcategory":"Auto Repair",
            "type":"Services"
        }
    ],
    "sg:phone":"+1 650 369 3368",
    "sg:postcode":"94061",
    "sg:province":"CA",
    "sg:tags":[
        "body",
        "automobile",
        "painting"
    ],
    "wof:name":"Dent Pro",
    "wof:placetype":"venue"
},
  "geometry": {"coordinates":[-122.21763799999999,37.473357],"type":"Point"}
}