{
  "type": "Feature",
  "properties": {
    "iso:country":"US",
    "sg:address":"130 McCormick Ave",
    "sg:city":"Costa Mesa",
    "sg:classifiers":[
        {
            "category":"Wholesale",
            "subcategory":"Computers",
            "type":"Manufacturing & Wholesale Goods"
        }
    ],
    "sg:phone":"+1 714 755 6550",
    "sg:postcode":"92626",
    "sg:province":"CA",
    "sg:website":"www.point4data.com",
    "wof:name":"Point 4 Data Corp",
    "wof:placetype":"venue"
},
  "geometry": {"coordinates":[-117.873242,33.683713],"type":"Point"}
}