{
  "type": "Feature",
  "properties": {
    "addr:full":"410 W Katella Ave Anaheim CA 92802",
    "addr:housenumber":"410",
    "addr:postcode":"92802",
    "addr:street":"W Katella Ave",
    "iso:country":"US",
    "sg:address":"410 W Katella Ave",
    "sg:city":"Anaheim",
    "sg:classifiers":[
        {
            "category":"Travel",
            "subcategory":"Hotels & Motels",
            "type":"Entertainment"
        }
    ],
    "sg:phone":"+1 714 776 9101",
    "sg:postcode":"92802",
    "sg:province":"CA",
    "wof:name":"Riviera Motel",
    "wof:placetype":"venue"
},
  "geometry": {"coordinates":[-117.912003,33.803398],"type":"Point"}
}