{
  "type": "Feature",
  "properties": {
    "addr:full":"13131 Los Angeles St Irwindale CA 91706",
    "addr:housenumber":"13131",
    "addr:postcode":"91706",
    "addr:street":"Los Angeles St",
    "iso:country":"US",
    "sg:address":"13131 Los Angeles St",
    "sg:city":"Irwindale",
    "sg:classifiers":[
        {
            "category":"Freight",
            "type":"Transportation"
        }
    ],
    "sg:phone":"+1 626 338 0652",
    "sg:postcode":"91706",
    "sg:province":"CA",
    "sg:tags":[
        "trucking"
    ],
    "wof:name":"R B Trucking",
    "wof:placetype":"venue"
},
  "geometry": {"coordinates":[-117.984076,34.092009],"type":"Point"}
}