{
  "type": "Feature",
  "properties": {
    "iso:country":"US",
    "sg:address":"7231 Santa Monica Blvd",
    "sg:city":"West Hollywood",
    "sg:classifiers":[
        {
            "category":"Health Services",
            "subcategory":"Doctor",
            "type":"Services"
        }
    ],
    "sg:phone":"+1 323 851 4777",
    "sg:postcode":"90046",
    "sg:province":"CA",
    "wof:name":"Apex Foundation",
    "wof:placetype":"venue"
},
  "geometry": {"coordinates":[-118.347412,34.085888],"type":"Point"}
}