{
  "type": "Feature",
  "properties": {
    "iso:country":"US",
    "sg:address":"899 Drake Ave",
    "sg:city":"Monterey",
    "sg:classifiers":[
        {
            "category":"Professional",
            "type":"Services"
        }
    ],
    "sg:phone":"+1 831 372 8717",
    "sg:postcode":"93940",
    "sg:province":"CA",
    "wof:name":"Frank Grillo Co",
    "wof:placetype":"venue"
},
  "geometry": {"coordinates":[-121.90406,36.609186],"type":"Point"}
}