{
  "type": "Feature",
  "properties": {
    "iso:country":"US",
    "sg:address":"233 Cajon St",
    "sg:city":"Redlands",
    "sg:classifiers":[
        {
            "category":"Professional",
            "type":"Services"
        }
    ],
    "sg:phone":"+1 909 792 9449",
    "sg:postcode":"92373",
    "sg:province":"CA",
    "wof:name":"Sagemark",
    "wof:placetype":"venue"
},
  "geometry": {"coordinates":[-117.180367,34.052454],"type":"Point"}
}