{
  "type": "Feature",
  "properties": {
    "iso:country":"US",
    "sg:address":"711 D St",
    "sg:city":"San Rafael",
    "sg:classifiers":[
        {
            "category":"Social Services",
            "type":"Services"
        }
    ],
    "sg:phone":"+1 415 456 0662",
    "sg:postcode":"94901",
    "sg:province":"CA",
    "sg:tags":[
        "counselor",
        "marriage",
        "family"
    ],
    "wof:name":"Zoe Brown",
    "wof:placetype":"venue"
},
  "geometry": {"coordinates":[-122.532391,37.971457],"type":"Point"}
}