{
  "type": "Feature",
  "properties": {
    "iso:country":"US",
    "sg:address":"831 E Valley Blvd",
    "sg:city":"San Gabriel",
    "sg:classifiers":[
        {
            "category":"Shopping",
            "subcategory":"Florist",
            "type":"Retail Goods"
        }
    ],
    "sg:phone":"+1 626 288 3077",
    "sg:postcode":"91776",
    "sg:province":"CA",
    "wof:name":"Dan Nhi Flowers & Gifts",
    "wof:placetype":"venue"
},
  "geometry": {"coordinates":[-118.089147,34.08053],"type":"Point"}
}