{
  "type": "Feature",
  "properties": {
    "addr:full":"1563 O Hara Ct Clayton CA 94517",
    "addr:housenumber":"1563",
    "addr:postcode":"94517",
    "addr:street":"O Hara Ct",
    "iso:country":"US",
    "sg:address":"1563 O Hara Ct",
    "sg:city":"Clayton",
    "sg:classifiers":[
        {
            "category":"Real Estate",
            "subcategory":"Real Estate Agent",
            "type":"Services"
        }
    ],
    "sg:phone":"+1 925 672 4499",
    "sg:postcode":"94517",
    "sg:province":"CA",
    "wof:name":"Howard Geller",
    "wof:placetype":"venue"
},
  "geometry": {"coordinates":[-122.088815,37.93963],"type":"Point"}
}