{
  "type": "Feature",
  "properties": {
    "addr:full":"713 del Paso Rd Sacramento CA 95834",
    "addr:housenumber":"713",
    "addr:postcode":"95834",
    "addr:street":"Del Paso Rd",
    "iso:country":"US",
    "sg:address":"713 del Paso Rd",
    "sg:city":"Sacramento",
    "sg:classifiers":[
        {
            "category":"Professional",
            "subcategory":"Computer Services",
            "type":"Services"
        }
    ],
    "sg:phone":"+1 916 641 7777",
    "sg:postcode":"95834",
    "sg:province":"CA",
    "sg:tags":[
        "consultant",
        "designer"
    ],
    "wof:name":"Computer Deductions Inc",
    "wof:placetype":"venue"
},
  "geometry": {"coordinates":[-121.47757900000001,38.655213],"type":"Point"}
}