{
  "type": "Feature",
  "properties": {
    "addr:full":"1907 W San Bernardino Rd West Covina CA 91790",
    "addr:housenumber":"1907",
    "addr:postcode":"91790",
    "addr:street":"W San Bernardino Rd",
    "iso:country":"US",
    "sg:address":"1907 W San Bernardino Rd",
    "sg:city":"West Covina",
    "sg:classifiers":[
        {
            "category":"Retail",
            "subcategory":"Auto Repair",
            "type":"Services"
        }
    ],
    "sg:phone":"+1 626 337 4626",
    "sg:postcode":"91790",
    "sg:province":"CA",
    "sg:tags":[
        "body",
        "automobile",
        "painting"
    ],
    "wof:name":"Bob Lowry & Son Auto Body",
    "wof:placetype":"venue"
},
  "geometry": {"coordinates":[-117.943547,34.090277],"type":"Point"}
}