{
  "type": "Feature",
  "properties": {
    "addr:full":"5711 N Figueroa St Los Angeles CA 90042",
    "addr:housenumber":"5711",
    "addr:postcode":"90042",
    "addr:street":"N Figueroa St",
    "iso:country":"US",
    "sg:address":"5711 N Figueroa St",
    "sg:city":"Los Angeles",
    "sg:classifiers":[
        {
            "category":"Professional",
            "subcategory":"Printing & Photocopies",
            "type":"Services"
        }
    ],
    "sg:phone":"+1 323 256 5880",
    "sg:postcode":"90042",
    "sg:province":"CA",
    "sg:tags":[
        "duplicating",
        "copying"
    ],
    "wof:name":"Copy Express",
    "wof:placetype":"venue"
},
  "geometry": {"coordinates":[-118.192001,34.110001],"type":"Point"}
}