{
  "type": "Feature",
  "properties": {
    "addr:full":"2210 Mendocino Ave Santa Rosa CA 95403",
    "addr:housenumber":"2210",
    "addr:postcode":"95403",
    "addr:street":"Mendocino Ave",
    "iso:country":"US",
    "sg:address":"2210 Mendocino Ave",
    "sg:city":"Santa Rosa",
    "sg:classifiers":[
        {
            "category":"Restaurant",
            "type":"Food & Drink"
        }
    ],
    "sg:phone":"+1 707 545 7753",
    "sg:postcode":"95403",
    "sg:province":"CA",
    "sg:tags":[
        "shop",
        "coffee"
    ],
    "wof:name":"Starbucks",
    "wof:placetype":"venue"
},
  "geometry": {"coordinates":[-122.71813400000001,38.463011],"type":"Point"}
}