{
  "type": "Feature",
  "properties": {
    "addr:full":"1075 S Mission Rd Fallbrook CA 92028",
    "addr:housenumber":"1075",
    "addr:postcode":"92028",
    "addr:street":"S Mission Rd",
    "iso:country":"US",
    "sg:address":"1075 S Mission Rd",
    "sg:city":"Fallbrook",
    "sg:classifiers":[
        {
            "category":"Banks & Credit Unions",
            "subcategory":"Bank",
            "type":"Services"
        }
    ],
    "sg:phone":"+1 760 451 9969",
    "sg:postcode":"92028",
    "sg:province":"CA",
    "sg:tags":[
        "cashing",
        "check"
    ],
    "wof:name":"Check Cashing Place",
    "wof:placetype":"venue"
},
  "geometry": {"coordinates":[-117.253535,33.372647],"type":"Point"}
}