{
  "type": "Feature",
  "properties": {
    "iso:country":"US",
    "sg:address":"30530 Co Rd 17",
    "sg:city":"Woodland",
    "sg:classifiers":[
        {
            "category":"Wholesale",
            "subcategory":"Poultry",
            "type":"Manufacturing & Wholesale Goods"
        }
    ],
    "sg:phone":"+1 530 662 2346",
    "sg:postcode":"95695",
    "sg:province":"CA",
    "wof:name":"Madison Pheasant Farm",
    "wof:placetype":"venue"
},
  "geometry": {"coordinates":[-121.945475,38.736907],"type":"Point"}
}