{
  "type": "Feature",
  "properties": {
    "addr:full":"28040 Grassy Way Escondido CA 92026",
    "addr:housenumber":"28040",
    "addr:postcode":"92026",
    "addr:street":"Grassy Way",
    "iso:country":"US",
    "sg:address":"28040 Grassy Way",
    "sg:city":"Escondido",
    "sg:classifiers":[
        {
            "category":"Wholesale",
            "subcategory":"Apparel",
            "type":"Manufacturing & Wholesale Goods"
        }
    ],
    "sg:phone":"+1 760 751 9182",
    "sg:postcode":"92026",
    "sg:province":"CA",
    "sg:tags":[
        "clothing"
    ],
    "wof:name":"Joannas",
    "wof:placetype":"venue"
},
  "geometry": {"coordinates":[-117.105993,33.217908],"type":"Point"}
}