{
  "type": "Feature",
  "properties": {
    "addr:full":"11915 Carmel Mountain Rd San Diego CA 92129",
    "addr:housenumber":"11915",
    "addr:postcode":"92129",
    "addr:street":"Carmel Mountain Rd",
    "iso:country":"US",
    "sg:address":"11915 Carmel Mountain Rd",
    "sg:city":"San Diego",
    "sg:classifiers":[
        {
            "category":"Restaurant",
            "type":"Food & Drink"
        }
    ],
    "sg:phone":"+1 858 673 4175",
    "sg:postcode":"92129",
    "sg:province":"CA",
    "sg:tags":[
        "eating"
    ],
    "wof:name":"McDonalds",
    "wof:placetype":"venue"
},
  "geometry": {"coordinates":[-117.07707600000001,32.981403],"type":"Point"}
}