{
  "type": "Feature",
  "properties": {
    "addr:full":"1336 W 6th St Corona CA 92882",
    "addr:housenumber":"1336",
    "addr:postcode":"92882",
    "addr:street":"W 6Th St",
    "iso:country":"US",
    "sg:address":"1336 W 6th St",
    "sg:city":"Corona",
    "sg:classifiers":[
        {
            "category":"Retail",
            "subcategory":"Auto Repair",
            "type":"Services"
        }
    ],
    "sg:phone":"+1 951 279 0220",
    "sg:postcode":"92882",
    "sg:province":"CA",
    "sg:tags":[
        "repairing",
        "automobile"
    ],
    "wof:name":"Toyamasters",
    "wof:placetype":"venue"
},
  "geometry": {"coordinates":[-117.592641,33.878141],"type":"Point"}
}