{
  "type": "Feature",
  "properties": {
    "iso:country":"US",
    "sg:address":"12939 Lucille Ave",
    "sg:city":"Los Angeles",
    "sg:classifiers":[
        {
            "category":"Education",
            "subcategory":"School",
            "type":"Public Place"
        }
    ],
    "sg:phone":"+1 310 398 8334",
    "sg:postcode":"90066",
    "sg:province":"CA",
    "wof:name":"Beethoven St Children's Ctr",
    "wof:placetype":"venue"
},
  "geometry": {"coordinates":[-118.44384700000001,34.001056],"type":"Point"}
}