{
  "type": "Feature",
  "properties": {
    "addr:full":"17781 Mitchell N Irvine CA 92614",
    "addr:housenumber":"17781",
    "addr:postcode":"92614",
    "addr:street":"Mitchell N",
    "iso:country":"US",
    "sg:address":"17781 Mitchell N",
    "sg:city":"Irvine",
    "sg:classifiers":[
        {
            "category":"Professional",
            "type":"Services"
        }
    ],
    "sg:phone":"+1 949 833 0028",
    "sg:postcode":"92614",
    "sg:province":"CA",
    "wof:name":"Pure Tech Water Systems",
    "wof:placetype":"venue"
},
  "geometry": {"coordinates":[-117.862244,33.694657],"type":"Point"}
}