{
  "type": "Feature",
  "properties": {
    "iso:country":"US",
    "sg:address":"4009 W Valencia Dr",
    "sg:city":"Fullerton",
    "sg:classifiers":[
        {
            "category":"Food & Beverages",
            "subcategory":"Groceries & Convenience Stores",
            "type":"Retail Goods"
        }
    ],
    "sg:phone":"+1 714 525 6080",
    "sg:postcode":"92833",
    "sg:province":"CA",
    "wof:name":"Joe's Market",
    "wof:placetype":"venue"
},
  "geometry": {"coordinates":[-117.978996,33.866299],"type":"Point"}
}