{
  "type": "Feature",
  "properties": {
    "iso:country":"US",
    "sg:address":"200 Middlefield Rd",
    "sg:city":"Menlo Park",
    "sg:classifiers":[
        {
            "category":"Autos & Motor Vehicles",
            "subcategory":"Fuel & Gas Station",
            "type":"Retail Goods"
        }
    ],
    "sg:phone":"+1 650 331 1700",
    "sg:postcode":"94025",
    "sg:province":"CA",
    "sg:tags":[
        "oil"
    ],
    "wof:name":"Mobil ID",
    "wof:placetype":"venue"
},
  "geometry": {"coordinates":[-122.166672,37.45588],"type":"Point"}
}