{
  "type": "Feature",
  "properties": {
    "iso:country":"US",
    "sg:address":"2400 14th St",
    "sg:city":"Sacramento",
    "sg:classifiers":[
        {
            "category":"Professional",
            "type":"Services"
        }
    ],
    "sg:phone":"+1 916 446 3675",
    "sg:postcode":"95818",
    "sg:province":"CA",
    "wof:name":"Libations Soulon",
    "wof:placetype":"venue"
},
  "geometry": {"coordinates":[-121.494806,38.562864],"type":"Point"}
}