{
  "type": "Feature",
  "properties": {
    "addr:full":"715 W Capitol Expy San Jose CA 95136",
    "addr:housenumber":"715",
    "addr:postcode":"95136",
    "addr:street":"W Capitol Expy",
    "iso:country":"US",
    "sg:address":"715 W Capitol Expy",
    "sg:city":"San Jose",
    "sg:classifiers":[
        {
            "category":"Restaurant",
            "type":"Food & Drink"
        }
    ],
    "sg:phone":"+1 408 264 8692",
    "sg:postcode":"95136",
    "sg:province":"CA",
    "wof:name":"Mc Donald's",
    "wof:placetype":"venue"
},
  "geometry": {"coordinates":[-121.865191,37.274858],"type":"Point"}
}