{
  "type": "Feature",
  "properties": {
    "iso:country":"US",
    "sg:address":"75 Charter Oak Ave",
    "sg:city":"San Francisco",
    "sg:classifiers":[
        {
            "category":"Retail",
            "subcategory":"Auto Repair",
            "type":"Services"
        }
    ],
    "sg:phone":"+1 415 467 5653",
    "sg:postcode":"94124",
    "sg:province":"CA",
    "sg:tags":[
        "body"
    ],
    "wof:name":"V & M Auto Body",
    "wof:placetype":"venue"
},
  "geometry": {"coordinates":[-122.40479000000001,37.738],"type":"Point"}
}