{
  "type": "Feature",
  "properties": {
    "iso:country":"US",
    "sg:address":"1600 Exposition Blvd",
    "sg:city":"Sacramento",
    "sg:classifiers":[
        {
            "category":"Government",
            "subcategory":"Office",
            "type":"Public Place"
        }
    ],
    "sg:phone":"+1 916 263 2975",
    "sg:postcode":"95815",
    "sg:province":"CA",
    "wof:name":"County Fair",
    "wof:placetype":"venue"
},
  "geometry": {"coordinates":[-121.437434,38.595653],"type":"Point"}
}