{
  "type": "Feature",
  "properties": {
    "addr:full":"556 N 1st Street San Jose CA 95112",
    "addr:housenumber":"556",
    "addr:postcode":"95112",
    "addr:street":"N 1St Street",
    "iso:country":"US",
    "sg:address":"556 N 1st Street",
    "sg:city":"San Jose",
    "sg:classifiers":[
        {
            "category":"Professional",
            "subcategory":"Lawyer & Legal Services",
            "type":"Services"
        }
    ],
    "sg:phone":"+1 408 297 9400",
    "sg:postcode":"95112",
    "sg:province":"CA",
    "wof:name":"Vu Trac N Law Offices",
    "wof:placetype":"venue"
},
  "geometry": {"coordinates":[-121.88101,37.340699],"type":"Point"}
}