{
  "type": "Feature",
  "properties": {
    "iso:country":"US",
    "sg:address":"17947 Via Valencia",
    "sg:city":"San Lorenzo",
    "sg:classifiers":[
        {
            "category":"Professional",
            "subcategory":"Computer Services",
            "type":"Services"
        }
    ],
    "sg:phone":"+1 510 481 8600",
    "sg:postcode":"94580",
    "sg:province":"CA",
    "sg:tags":[
        "repair"
    ],
    "wof:name":"Ultimate Computer Systems",
    "wof:placetype":"venue"
},
  "geometry": {"coordinates":[-122.116997,37.680302],"type":"Point"}
}