{
  "type": "Feature",
  "properties": {
    "addr:full":"8230 Ferguson Ave Sacramento CA 95828",
    "addr:housenumber":"8230",
    "addr:postcode":"95828",
    "addr:street":"Ferguson Ave",
    "iso:country":"US",
    "sg:address":"8230 Ferguson Ave",
    "sg:city":"Sacramento",
    "sg:classifiers":[
        {
            "category":"Wholesale",
            "subcategory":"Sporting Goods",
            "type":"Manufacturing & Wholesale Goods"
        }
    ],
    "sg:phone":"+1 916 826 6412",
    "sg:postcode":"95828",
    "sg:province":"CA",
    "sg:tags":[
        "equipment",
        "billiard",
        "supply"
    ],
    "wof:name":"High Line Billiards",
    "wof:placetype":"venue"
},
  "geometry": {"coordinates":[-121.399716,38.523662],"type":"Point"}
}