{
  "type": "Feature",
  "properties": {
    "iso:country":"US",
    "sg:address":"12408 E Mountain View Ave",
    "sg:city":"Kingsburg",
    "sg:classifiers":[
        {
            "category":"Farming",
            "subcategory":"Orchard",
            "type":"Manufacturing & Wholesale Goods"
        }
    ],
    "sg:phone":"+1 559 638 2271",
    "sg:postcode":"93631",
    "sg:province":"CA",
    "sg:tags":[
        "farm"
    ],
    "wof:name":"Mountain View Ranch",
    "wof:placetype":"venue"
},
  "geometry": {"coordinates":[-119.575144,36.546797],"type":"Point"}
}