{
  "type": "Feature",
  "properties": {
    "addr:full":"16024 Gale Ave Hacienda Heights CA 91745",
    "addr:housenumber":"16024",
    "addr:postcode":"91745",
    "addr:street":"Gale Ave",
    "iso:country":"US",
    "sg:address":"16024 Gale Ave",
    "sg:city":"Hacienda Heights",
    "sg:classifiers":[
        {
            "category":"Professional",
            "type":"Services"
        },
        {
            "category":"Home & Garden",
            "subcategory":"Furniture",
            "type":"Retail Goods"
        }
    ],
    "sg:phone":"+1 626 820 0178",
    "sg:postcode":"91745",
    "sg:province":"CA",
    "wof:name":"Nicamay International Inc",
    "wof:placetype":"venue"
},
  "geometry": {"coordinates":[-117.957387,34.009062],"type":"Point"}
}