{
  "type": "Feature",
  "properties": {
    "iso:country":"US",
    "sg:address":"21420 Chase St",
    "sg:city":"Canoga Park",
    "sg:classifiers":[
        {
            "category":"Manufacturing",
            "subcategory":"Retail Goods",
            "type":"Manufacturing & Wholesale Goods"
        },
        {
            "category":"Manufacturing",
            "subcategory":"Tools & Machinery",
            "type":"Manufacturing & Wholesale Goods"
        }
    ],
    "sg:phone":"+1 818 998 8028",
    "sg:postcode":"91304",
    "sg:province":"CA",
    "sg:tags":[
        "industrial",
        "manufacturer",
        "mfg"
    ],
    "wof:name":"Pacific Design",
    "wof:placetype":"venue"
},
  "geometry": {"coordinates":[-118.599048,34.224484],"type":"Point"}
}