{
  "type": "Feature",
  "properties": {
    "addr:full":"100 Los Cerritos Mall Cerritos CA 90703",
    "addr:housenumber":"100;cerritos",
    "addr:postcode":"ca 90703",
    "addr:street":"Los;Mall",
    "iso:country":"US",
    "sg:address":"100 Los Cerritos Mall",
    "sg:city":"Cerritos",
    "sg:classifiers":[
        {
            "category":"Shopping",
            "subcategory":"Department Store",
            "type":"Retail Goods"
        }
    ],
    "sg:phone":"+1 562 403 8600",
    "sg:postcode":"90703",
    "sg:province":"CA",
    "wof:name":"Sears",
    "wof:placetype":"venue"
},
  "geometry": {"coordinates":[-118.095001,33.865601],"type":"Point"}
}