{
  "type": "Feature",
  "properties": {
    "addr:full":"2627 W 157th St Gardena CA 90249",
    "addr:housenumber":"2627",
    "addr:postcode":"90249",
    "addr:street":"W 157Th St",
    "iso:country":"US",
    "sg:address":"2627 W 157th St",
    "sg:city":"Gardena",
    "sg:classifiers":[
        {
            "category":"Building & Trades",
            "subcategory":"Construction",
            "type":"Services"
        }
    ],
    "sg:phone":"+1 310 516 8475",
    "sg:postcode":"90249",
    "sg:province":"CA",
    "sg:tags":[
        "spa",
        "hot",
        "installation",
        "tub"
    ],
    "wof:name":"Innovative Spas",
    "wof:placetype":"venue"
},
  "geometry": {"coordinates":[-118.321635,33.888383],"type":"Point"}
}