{
  "type": "Feature",
  "properties": {
    "addr:full":"1100 S La Brea Avenue Inglewood CA 90301",
    "addr:housenumber":"1100",
    "addr:postcode":"90301",
    "addr:street":"S;Brea Avenue",
    "iso:country":"US",
    "sg:address":"1100 S La Brea Avenue",
    "sg:city":"Inglewood",
    "sg:classifiers":[
        {
            "category":"Food & Beverages",
            "subcategory":"Groceries & Convenience Stores",
            "type":"Retail Goods"
        }
    ],
    "sg:phone":"+1 310 673 9806",
    "sg:postcode":"90301",
    "sg:province":"CA",
    "wof:name":"7-Eleven Food Stores",
    "wof:placetype":"venue"
},
  "geometry": {"coordinates":[-118.35268600000001,33.948848],"type":"Point"}
}