{
  "type": "Feature",
  "properties": {
    "iso:country":"US",
    "sg:address":"247 N Mountain Trl",
    "sg:city":"Sierra Madre",
    "sg:classifiers":[
        {
            "category":"Building & Trades",
            "subcategory":"Construction",
            "type":"Services"
        }
    ],
    "sg:phone":"+1 626 355 1226",
    "sg:postcode":"91024",
    "sg:province":"CA",
    "sg:tags":[
        "house"
    ],
    "wof:name":"Monty Murphy Construction",
    "wof:placetype":"venue"
},
  "geometry": {"coordinates":[-118.04824000000001,34.16592],"type":"Point"}
}