{
  "type": "Feature",
  "properties": {
    "addr:full":"5555 Keoncrest Cir Sacramento CA 95841",
    "addr:postcode":"5555;95841",
    "addr:street":"Keoncrest Cir",
    "iso:country":"US",
    "sg:address":"5555 Keoncrest Cir",
    "sg:city":"Sacramento",
    "sg:classifiers":[
        {
            "category":"Professional",
            "type":"Services"
        }
    ],
    "sg:phone":"+1 916 332 3250",
    "sg:postcode":"95841",
    "sg:province":"CA",
    "wof:name":"AKA Svc",
    "wof:placetype":"venue"
},
  "geometry": {"coordinates":[-121.335133,38.671422],"type":"Point"}
}