{
  "type": "Feature",
  "properties": {
    "addr:full":"9051 Soquel Dr Aptos CA 95003",
    "addr:housenumber":"9051",
    "addr:postcode":"ca 95003",
    "addr:street":"Soquel Dr",
    "iso:country":"US",
    "sg:address":"9051 Soquel Dr",
    "sg:city":"Aptos",
    "sg:classifiers":[
        {
            "category":"Health Services",
            "subcategory":"Doctor",
            "type":"Services"
        }
    ],
    "sg:phone":"+1 831 688 6712",
    "sg:postcode":"95003",
    "sg:province":"CA",
    "sg:tags":[
        "physician",
        "surgeon"
    ],
    "wof:name":"Richard G Gilbert MD",
    "wof:placetype":"venue"
},
  "geometry": {"coordinates":[-121.885408,36.976421],"type":"Point"}
}