{
  "type": "Feature",
  "properties": {
    "iso:country":"US",
    "sg:address":"2021 Ygnacio Valley Rd",
    "sg:city":"Walnut Creek",
    "sg:classifiers":[
        {
            "category":"Health Services",
            "subcategory":"Health Practitioner",
            "type":"Services"
        }
    ],
    "sg:phone":"+1 925 945 1474",
    "sg:postcode":"94598",
    "sg:province":"CA",
    "sg:tags":[
        "pathologist",
        "speech"
    ],
    "wof:name":"Speech Pathology Group",
    "wof:placetype":"venue"
},
  "geometry": {"coordinates":[-122.033069,37.921276],"type":"Point"}
}