{
  "type": "Feature",
  "properties": {
    "addr:full":"3585 Main St Riverside CA 92501",
    "addr:housenumber":"3585",
    "addr:postcode":"92501",
    "addr:street":"Main St",
    "iso:country":"US",
    "sg:address":"3585 Main St",
    "sg:city":"Riverside",
    "sg:classifiers":[
        {
            "category":"Manufacturing",
            "subcategory":"Printing",
            "type":"Manufacturing & Wholesale Goods"
        }
    ],
    "sg:phone":"+1 951 682 6070",
    "sg:postcode":"92501",
    "sg:province":"CA",
    "sg:tags":[
        "newspaper"
    ],
    "sg:website":"www.blackvoicenews.com",
    "wof:name":"Black Voice News",
    "wof:placetype":"venue"
},
  "geometry": {"coordinates":[-117.37264399999999,33.984819],"type":"Point"}
}