{
  "type": "Feature",
  "properties": {
    "addr:full":"3820 del Amo Blvd Torrance CA 90503",
    "addr:housenumber":"3820",
    "addr:postcode":"90503",
    "addr:street":"Del Amo Blvd",
    "iso:country":"US",
    "sg:address":"3820 del Amo Blvd",
    "sg:city":"Torrance",
    "sg:classifiers":[
        {
            "category":"Real Estate",
            "subcategory":"Real Estate Agent",
            "type":"Services"
        }
    ],
    "sg:phone":"+1 310 214 0060",
    "sg:postcode":"90503",
    "sg:province":"CA",
    "sg:tags":[
        "broker"
    ],
    "wof:name":"Equity Exchange RE & Inv Svcs",
    "wof:placetype":"venue"
},
  "geometry": {"coordinates":[-118.353612,33.84859],"type":"Point"}
}