{
  "type": "Feature",
  "properties": {
    "iso:country":"US",
    "sg:address":"14625 Domart Ave",
    "sg:city":"Norwalk",
    "sg:classifiers":[
        {
            "category":"Retail",
            "subcategory":"Repair Shop",
            "type":"Services"
        },
        {
            "category":"Building & Trades",
            "subcategory":"Construction",
            "type":"Services"
        }
    ],
    "sg:phone":"+1 562 868 1234",
    "sg:postcode":"90650",
    "sg:province":"CA",
    "sg:tags":[
        "welding",
        "contractor"
    ],
    "wof:name":"Kocina's Certified Welding",
    "wof:placetype":"venue"
},
  "geometry": {"coordinates":[-118.107497,33.897886],"type":"Point"}
}