{
  "type": "Feature",
  "properties": {
    "addr:full":"12310 Seal Beach Blvd Seal Beach CA 90740",
    "addr:housenumber":"12310",
    "addr:postcode":"90740",
    "addr:street":"Seal Beach Blvd",
    "iso:country":"US",
    "sg:address":"12310 Seal Beach Blvd",
    "sg:city":"Seal Beach",
    "sg:classifiers":[
        {
            "category":"Banks & Credit Unions",
            "subcategory":"Financial Services",
            "type":"Services"
        }
    ],
    "sg:phone":"+1 562 430 2335",
    "sg:postcode":"90740",
    "sg:province":"CA",
    "sg:tags":[
        "broker",
        "mortgage"
    ],
    "wof:name":"World Savings",
    "wof:placetype":"venue"
},
  "geometry": {"coordinates":[-118.07199900000001,33.783699],"type":"Point"}
}