{
  "type": "Feature",
  "properties": {
    "addr:full":"20805 Orr Springs Rd Ukiah CA 95482",
    "addr:housenumber":"20805",
    "addr:postcode":"ca 95482",
    "addr:street":"Orr Springs Rd",
    "iso:country":"US",
    "sg:address":"20805 Orr Springs Rd",
    "sg:city":"Ukiah",
    "sg:classifiers":[
        {
            "category":"Building & Trades",
            "subcategory":"Landscaping Services",
            "type":"Services"
        }
    ],
    "sg:phone":"+1 707 937 5139",
    "sg:postcode":"95482",
    "sg:province":"CA",
    "sg:tags":[
        "tree"
    ],
    "wof:name":"Tom's Tree Care",
    "wof:placetype":"venue"
},
  "geometry": {"coordinates":[-123.460187,39.231801],"type":"Point"}
}