{
  "type": "Feature",
  "properties": {
    "iso:country":"US",
    "sg:address":"Little Tokyo 120 Onizuka St",
    "sg:city":"Los Angeles",
    "sg:classifiers":[
        {
            "category":"Personal",
            "subcategory":"Tattoo Parlor",
            "type":"Services"
        }
    ],
    "sg:phone":"+1 213 626 0374",
    "sg:postcode":"90012",
    "sg:province":"CA",
    "sg:website":"www.onizukatattoo.com",
    "wof:name":"Onizuka Tattoo",
    "wof:placetype":"venue"
},
  "geometry": {"coordinates":[-118.24192600000001,34.050386],"type":"Point"}
}