{
  "type": "Feature",
  "properties": {
    "addr:full":"2109 Cornwell Ave Modesto CA 95350",
    "addr:housenumber":"2109",
    "addr:postcode":"ca 95350",
    "addr:street":"Cornwell Ave",
    "iso:country":"US",
    "sg:address":"2109 Cornwell Ave",
    "sg:city":"Modesto",
    "sg:classifiers":[
        {
            "category":"Home & Garden",
            "subcategory":"Household Appliances",
            "type":"Retail Goods"
        }
    ],
    "sg:phone":"+1 209 529 3093",
    "sg:postcode":"95350",
    "sg:province":"CA",
    "sg:tags":[
        "cont"
    ],
    "wof:name":"Al's Appliance Repair",
    "wof:placetype":"venue"
},
  "geometry": {"coordinates":[-121.035253,37.676465],"type":"Point"}
}