{
  "type": "Feature",
  "properties": {
    "addr:full":"21450 Golden Springs Dr Walnut CA 91789",
    "addr:housenumber":"21450",
    "addr:postcode":"91789",
    "addr:street":"Golden Springs Dr",
    "iso:country":"US",
    "sg:address":"21450 Golden Springs Dr",
    "sg:city":"Walnut",
    "sg:classifiers":[
        {
            "category":"Local Transit",
            "type":"Transportation"
        }
    ],
    "sg:phone":"+1 909 861 0040",
    "sg:postcode":"91789",
    "sg:province":"CA",
    "sg:tags":[
        "limousine"
    ],
    "wof:name":"Golden Moment Limousine",
    "wof:placetype":"venue"
},
  "geometry": {"coordinates":[-117.835582,34.001301],"type":"Point"}
}