{
  "type": "Feature",
  "properties": {
    "iso:country":"US",
    "sg:address":"9711 Reseda Blvd",
    "sg:city":"Northridge",
    "sg:phone":"+1 818 717 0234",
    "sg:postcode":"91324",
    "sg:province":"CA",
    "wof:name":"Seoul Kalbi",
    "wof:placetype":"venue"
},
  "geometry": {"coordinates":[-118.536079,34.246579],"type":"Point"}
}