{
  "type": "Feature",
  "properties": {
    "iso:country":"US",
    "sg:address":"832 W 9th St",
    "sg:city":"Los Angeles",
    "sg:classifiers":[
        {
            "category":"Social Services",
            "subcategory":"Adult Care",
            "type":"Services"
        }
    ],
    "sg:phone":"+1 213 627 0725",
    "sg:postcode":"90015",
    "sg:province":"CA",
    "sg:tags":[
        "residential"
    ],
    "wof:name":"Salvation Army Zahn Center",
    "wof:placetype":"venue"
},
  "geometry": {"coordinates":[-118.26325900000001,34.046214],"type":"Point"}
}