{
  "type": "Feature",
  "properties": {
    "iso:country":"US",
    "sg:address":"17695 Arrow Blvd",
    "sg:city":"Fontana",
    "sg:classifiers":[
        {
            "category":"Health Services",
            "subcategory":"Optometrist",
            "type":"Services"
        }
    ],
    "sg:phone":"+1 909 355 8883",
    "sg:postcode":"92335",
    "sg:province":"CA",
    "wof:name":"Henry Nguyen OD",
    "wof:placetype":"venue"
},
  "geometry": {"coordinates":[-117.420412,34.099357],"type":"Point"}
}