{
  "type": "Feature",
  "properties": {
    "addr:full":"1955 Pulgas Ave East Palo Alto CA 94303",
    "addr:housenumber":"1955",
    "addr:postcode":"94303",
    "addr:street":"Pulgas Ave",
    "iso:country":"US",
    "sg:address":"1955 Pulgas Ave",
    "sg:city":"East Palo Alto",
    "sg:classifiers":[
        {
            "category":"Home & Garden",
            "subcategory":"Building Materials",
            "type":"Retail Goods"
        }
    ],
    "sg:phone":"+1 650 328 8731",
    "sg:postcode":"94303",
    "sg:province":"CA",
    "wof:name":"Whole House Bldg Supl Hotline",
    "wof:placetype":"venue"
},
  "geometry": {"coordinates":[-122.13003500000001,37.456189],"type":"Point"}
}