{
  "type": "Feature",
  "properties": {
    "addr:full":"555 Laurel Ave San Mateo CA 94401",
    "addr:housenumber":"555",
    "addr:postcode":"94401",
    "addr:street":"Laurel Ave",
    "iso:country":"US",
    "sg:address":"555 Laurel Ave",
    "sg:city":"San Mateo",
    "sg:classifiers":[
        {
            "category":"Professional",
            "type":"Services"
        }
    ],
    "sg:phone":"+1 650 342 0756",
    "sg:postcode":"94401",
    "sg:province":"CA",
    "sg:tags":[
        "establishment"
    ],
    "wof:name":"D Piedemonte",
    "wof:placetype":"venue"
},
  "geometry": {"coordinates":[-122.321652,37.563073],"type":"Point"}
}