{
  "type": "Feature",
  "properties": {
    "addr:full":"1501 Doolittle Dr San Leandro CA 94577",
    "addr:housenumber":"1501",
    "addr:postcode":"94577",
    "addr:street":"Doolittle Dr",
    "iso:country":"US",
    "sg:address":"1501 Doolittle Dr",
    "sg:city":"San Leandro",
    "sg:classifiers":[
        {
            "category":"Manufacturing",
            "subcategory":"Metals",
            "type":"Manufacturing & Wholesale Goods"
        }
    ],
    "sg:phone":"+1 510 569 9123",
    "sg:postcode":"94577",
    "sg:province":"CA",
    "sg:tags":[
        "fabricator",
        "sheet"
    ],
    "wof:name":"Van-Mulder Sheet Metal Inc",
    "wof:placetype":"venue"
},
  "geometry": {"coordinates":[-122.18598299999999,37.714454],"type":"Point"}
}