{
  "type": "Feature",
  "properties": {
    "addr:full":"6765 Westminster Boulevard Westminster CA 92683",
    "addr:housenumber":"6765",
    "addr:postcode":"92683",
    "addr:street":"Westminster Boulevard",
    "iso:country":"US",
    "sg:address":"6765 Westminster Boulevard",
    "sg:city":"Westminster",
    "sg:classifiers":[
        {
            "category":"Shopping",
            "subcategory":"Clothing, Apparel, & Fashions",
            "type":"Retail Goods"
        },
        {
            "category":"Shopping",
            "subcategory":"Department Store",
            "type":"Retail Goods"
        }
    ],
    "sg:phone":"+1 714 379 7771",
    "sg:postcode":"92683",
    "sg:province":"CA",
    "sg:tags":[
        "apparel",
        "accessory",
        "clothing",
        "women's"
    ],
    "sg:website":"www.susiesdeals.com",
    "wof:name":"Susie's Deals",
    "wof:placetype":"venue"
},
  "geometry": {"coordinates":[-118.008484,33.759109],"type":"Point"}
}