{
  "type": "Feature",
  "properties": {
    "addr:full":"10055 Wolf Rd Grass Valley CA 95949",
    "addr:housenumber":"10055",
    "addr:postcode":"95949",
    "addr:street":"Wolf Rd",
    "iso:country":"US",
    "sg:address":"10055 Wolf Rd",
    "sg:city":"Grass Valley",
    "sg:classifiers":[
        {
            "category":"Education",
            "subcategory":"School",
            "type":"Public Place"
        }
    ],
    "sg:phone":"+1 530 268 9921",
    "sg:postcode":"95949",
    "sg:province":"CA",
    "wof:name":"Sierra Academy",
    "wof:placetype":"venue"
},
  "geometry": {"coordinates":[-121.095411,39.042513],"type":"Point"}
}