{
  "type": "Feature",
  "properties": {
    "iso:country":"US",
    "sg:address":"4319 Orange Grove Ave",
    "sg:city":"Sacramento",
    "sg:classifiers":[
        {
            "category":"Autos & Motor Vehicles",
            "subcategory":"Auto Supplies",
            "type":"Retail Goods"
        },
        {
            "category":"Sports & Exercise",
            "subcategory":"Race Track",
            "type":"Entertainment"
        }
    ],
    "sg:phone":"+1 916 483 5752",
    "sg:postcode":"95841",
    "sg:province":"CA",
    "sg:tags":[
        "performance",
        "automobile",
        "racing",
        "car",
        "equipment"
    ],
    "wof:name":"Race Car Specialties",
    "wof:placetype":"venue"
},
  "geometry": {"coordinates":[-121.36206199999999,38.647645],"type":"Point"}
}