{
  "type": "Feature",
  "properties": {
    "iso:country":"US",
    "sg:address":"4512 E Alondra Boulevard",
    "sg:city":"Compton",
    "sg:classifiers":[
        {
            "category":"Personal",
            "subcategory":"Barber",
            "type":"Services"
        }
    ],
    "sg:phone":"+1 310 764 1535",
    "sg:postcode":"90221",
    "sg:province":"CA",
    "wof:name":"Peluqueria Mexico No 2",
    "wof:placetype":"venue"
},
  "geometry": {"coordinates":[-118.191726,33.888584],"type":"Point"}
}