{
  "type": "Feature",
  "properties": {
    "addr:full":"2129 Auto Park Way Escondido CA 92029",
    "addr:housenumber":"2129",
    "addr:postcode":"92029",
    "addr:street":"Auto Park Way",
    "iso:country":"US",
    "sg:address":"2129 Auto Park Way",
    "sg:city":"Escondido",
    "sg:classifiers":[
        {
            "category":"Retail",
            "subcategory":"Auto Repair",
            "type":"Services"
        }
    ],
    "sg:phone":"+1 760 521 2314",
    "sg:postcode":"92029",
    "sg:province":"CA",
    "sg:tags":[
        "body",
        "painting",
        "repairing",
        "automobile"
    ],
    "wof:name":"A Perfect Fix",
    "wof:placetype":"venue"
},
  "geometry": {"coordinates":[-117.111957,33.119406],"type":"Point"}
}