{
  "type": "Feature",
  "properties": {
    "addr:full":"1528 Redwood Hwy Corte Madera CA 94925",
    "addr:housenumber":"1528",
    "addr:postcode":"94925",
    "addr:street":"Redwood Hwy",
    "iso:country":"US",
    "sg:address":"1528 Redwood Hwy",
    "sg:city":"Corte Madera",
    "sg:classifiers":[
        {
            "category":"Shopping",
            "subcategory":"Gifts & Souvenirs",
            "type":"Retail Goods"
        }
    ],
    "sg:phone":"+1 415 924 1998",
    "sg:postcode":"94925",
    "sg:province":"CA",
    "sg:tags":[
        "shop"
    ],
    "wof:name":"Illuminations",
    "wof:placetype":"venue"
},
  "geometry": {"coordinates":[-122.513042,37.931323],"type":"Point"}
}