{
  "type": "Feature",
  "properties": {
    "iso:country":"US",
    "sg:address":"44738 Sierra Hwy",
    "sg:city":"Lancaster",
    "sg:phone":"+1 661 948 9906",
    "sg:postcode":"93534",
    "sg:province":"CA",
    "sg:website":"http://www.wholesalemattressdistributors.com",
    "wof:name":"Wholesale Mattress Distributors",
    "wof:placetype":"venue"
},
  "geometry": {"coordinates":[-118.1365,34.695465],"type":"Point"}
}