{
  "type": "Feature",
  "properties": {
    "addr:full":"1010 Wilshire Blvd Los Angeles CA 90017",
    "addr:housenumber":"1010",
    "addr:postcode":"90017",
    "addr:street":"Wilshire Blvd",
    "iso:country":"US",
    "sg:address":"1010 Wilshire Blvd",
    "sg:city":"Los Angeles",
    "sg:classifiers":[
        {
            "category":"Utilities",
            "subcategory":"Telephone",
            "type":"Services"
        },
        {
            "category":"Professional",
            "subcategory":"Management & Consulting",
            "type":"Services"
        }
    ],
    "sg:phone":"+1 213 975 3747",
    "sg:postcode":"90017",
    "sg:province":"CA",
    "sg:tags":[
        "publishing",
        "direct",
        "relations",
        "labor",
        "communications",
        "department",
        "mail",
        "ad"
    ],
    "wof:name":"Pacific Bell Inc",
    "wof:placetype":"venue"
},
  "geometry": {"coordinates":[-118.2619,34.051583],"type":"Point"}
}