{
  "type": "Feature",
  "properties": {
    "addr:full":"2560 Alpine Blvd Ste 3 Alpine CA 91901",
    "addr:housenumber":"2560",
    "addr:postcode":"91901",
    "addr:street":"Alpine Blvd Ste 3",
    "iso:country":"US",
    "sg:address":"2560 Alpine Blvd Ste 3",
    "sg:city":"Alpine",
    "sg:classifiers":[
        {
            "category":"Real Estate",
            "subcategory":"Real Estate Services",
            "type":"Services"
        },
        {
            "category":"Real Estate",
            "subcategory":"Real Estate Agent",
            "type":"Services"
        }
    ],
    "sg:phone":"+1 619 659 1122",
    "sg:postcode":"91901",
    "sg:province":"CA",
    "sg:tags":[
        "buyer",
        "broker"
    ],
    "wof:name":"Cabins To Castles Realty",
    "wof:placetype":"venue"
},
  "geometry": {"coordinates":[-116.758578,32.834861],"type":"Point"}
}