{
  "type": "Feature",
  "properties": {
    "iso:country":"US",
    "sg:address":"14784 Foothill Blvd",
    "sg:city":"Fontana",
    "sg:classifiers":[
        {
            "category":"Autos & Motor Vehicles",
            "subcategory":"Automobile Sales",
            "type":"Retail Goods"
        }
    ],
    "sg:phone":"+1 909 829 7372",
    "sg:postcode":"92335",
    "sg:province":"CA",
    "sg:tags":[
        "dealers-used",
        "car",
        "used",
        "cars-wholesale"
    ],
    "wof:name":"Metro Auto Loan",
    "wof:placetype":"venue"
},
  "geometry": {"coordinates":[-117.48253099999999,34.106531],"type":"Point"}
}