{
  "type": "Feature",
  "properties": {
    "addr:full":"8540 Weirick Rd Corona CA 92883",
    "addr:housenumber":"8540",
    "addr:postcode":"92883",
    "addr:street":"Weirick Rd",
    "iso:country":"US",
    "sg:address":"8540 Weirick Rd",
    "sg:city":"Corona",
    "sg:classifiers":[
        {
            "category":"Organizations",
            "subcategory":"Religious Organization",
            "type":"Services"
        }
    ],
    "sg:phone":"+1 951 277 1801",
    "sg:postcode":"92883",
    "sg:province":"CA",
    "sg:tags":[
        "church"
    ],
    "wof:name":"St Mary Magdalene Church",
    "wof:placetype":"venue"
},
  "geometry": {"coordinates":[-117.51017899999999,33.806199],"type":"Point"}
}