{
  "type": "Feature",
  "properties": {
    "addr:full":"7532 Casa Blanca St Riverside CA 92504",
    "addr:housenumber":"7532",
    "addr:postcode":"92504",
    "addr:street":"Casa Blanca St",
    "iso:country":"US",
    "sg:address":"7532 Casa Blanca St",
    "sg:city":"Riverside",
    "sg:classifiers":[
        {
            "category":"Shopping",
            "subcategory":"Clothing, Apparel, & Fashions",
            "type":"Retail Goods"
        }
    ],
    "sg:phone":"+1 951 352 9558",
    "sg:postcode":"92504",
    "sg:province":"CA",
    "sg:tags":[
        "family"
    ],
    "wof:name":"Raz Nasibu & Urban Wear",
    "wof:placetype":"venue"
},
  "geometry": {"coordinates":[-117.405704,33.932911],"type":"Point"}
}