{
  "type": "Feature",
  "properties": {
    "addr:full":"12142 Marigold Ln Moreno Valley CA 92557",
    "addr:housenumber":"12142",
    "addr:postcode":"92557",
    "addr:street":"Marigold Ln",
    "iso:country":"US",
    "sg:address":"12142 Marigold Ln",
    "sg:city":"Moreno Valley",
    "sg:classifiers":[
        {
            "category":"Manufacturing",
            "subcategory":"Signs",
            "type":"Manufacturing & Wholesale Goods"
        }
    ],
    "sg:phone":"+1 951 924 5633",
    "sg:postcode":"92557",
    "sg:province":"CA",
    "wof:name":"Johnson's Sign Instltn Svc",
    "wof:placetype":"venue"
},
  "geometry": {"coordinates":[-117.235916,33.944896],"type":"Point"}
}