{
  "type": "Feature",
  "properties": {
    "addr:full":"870 N State Hwy 173 Lake Arrowhead CA 92407",
    "addr:housenumber":"870",
    "addr:postcode":"92407",
    "addr:street":"N State Hwy 173",
    "iso:country":"US",
    "sg:address":"870 N State Hwy 173",
    "sg:city":"Lake Arrowhead",
    "sg:classifiers":[
        {
            "category":"Autos & Motor Vehicles",
            "subcategory":"Boat Sales",
            "type":"Retail Goods"
        }
    ],
    "sg:phone":"+1 909 336 6151",
    "sg:postcode":"92407",
    "sg:province":"CA",
    "sg:tags":[
        "dealer",
        "sales"
    ],
    "wof:name":"Hardin Marine Arrowhead",
    "wof:placetype":"venue"
},
  "geometry": {"coordinates":[-117.169861,34.26599],"type":"Point"}
}