{
  "type": "Feature",
  "properties": {
    "iso:country":"US",
    "sg:address":"1525 Fulton St",
    "sg:city":"Fresno",
    "sg:classifiers":[
        {
            "category":"Restaurant",
            "type":"Food & Drink"
        }
    ],
    "sg:phone":"+1 559 237 0087",
    "sg:postcode":"93721",
    "sg:province":"CA",
    "sg:tags":[
        "banquet",
        "rooms"
    ],
    "wof:name":"Cornerstone Banquet",
    "wof:placetype":"venue"
},
  "geometry": {"coordinates":[-119.796464,36.739571],"type":"Point"}
}