{
  "type": "Feature",
  "properties": {
    "iso:country":"US",
    "sg:address":"11398 Kenyon Way",
    "sg:city":"Alta Loma",
    "sg:classifiers":[
        {
            "category":"Health Services",
            "subcategory":"Optometrist",
            "type":"Services"
        }
    ],
    "sg:phone":"+1 909 477 3211",
    "sg:postcode":"91701",
    "sg:province":"CA",
    "wof:name":"Lifetime Eyecare",
    "wof:placetype":"venue"
},
  "geometry": {"coordinates":[-117.558532,34.13431],"type":"Point"}
}