{
  "type": "Feature",
  "properties": {
    "iso:country":"US",
    "sg:address":"2221 W Olive Ave",
    "sg:city":"Burbank",
    "sg:classifiers":[
        {
            "category":"Communications",
            "subcategory":"Film & Video Production",
            "type":"Services"
        }
    ],
    "sg:phone":"+1 818 841 9321",
    "sg:postcode":"91506",
    "sg:province":"CA",
    "sg:tags":[
        "editing",
        "tape"
    ],
    "wof:name":"Open Road",
    "wof:placetype":"venue"
},
  "geometry": {"coordinates":[-118.32776,34.162935],"type":"Point"}
}