{
  "type": "Feature",
  "properties": {
    "addr:full":"744 Palm Ave South San Francisco CA 94080",
    "addr:housenumber":"744",
    "addr:postcode":"94080",
    "addr:street":"Palm Ave",
    "iso:country":"US",
    "sg:address":"744 Palm Ave",
    "sg:city":"South San Francisco",
    "sg:classifiers":[
        {
            "category":"Manufacturing",
            "subcategory":"Apparel",
            "type":"Manufacturing & Wholesale Goods"
        }
    ],
    "sg:phone":"+1 650 871 7076",
    "sg:postcode":"94080",
    "sg:province":"CA",
    "sg:tags":[
        "outerwear",
        "mfg"
    ],
    "wof:name":"Brand Revolution",
    "wof:placetype":"venue"
},
  "geometry": {"coordinates":[-122.42228900000001,37.659927],"type":"Point"}
}