{
  "type": "Feature",
  "properties": {
    "addr:full":"1050 S Van Ness Ave San Francisco CA 94110",
    "addr:housenumber":"1050",
    "addr:postcode":"94110",
    "addr:street":"S Van Ness Ave",
    "iso:country":"US",
    "sg:address":"1050 S Van Ness Ave",
    "sg:city":"San Francisco",
    "sg:classifiers":[
        {
            "category":"Professional",
            "type":"Services"
        }
    ],
    "sg:phone":"+1 415 206 1999",
    "sg:postcode":"94110",
    "sg:province":"CA",
    "sg:tags":[
        "establishment"
    ],
    "wof:name":"Lutheran Volunteer Corps",
    "wof:placetype":"venue"
},
  "geometry": {"coordinates":[-122.416704,37.756378],"type":"Point"}
}