{
  "type": "Feature",
  "properties": {
    "iso:country":"US",
    "sg:address":"9195 Valley View St",
    "sg:city":"Cypress",
    "sg:classifiers":[
        {
            "category":"Restaurant",
            "type":"Food & Drink"
        }
    ],
    "sg:phone":"+1 714 821 8883",
    "sg:postcode":"90630",
    "sg:province":"CA",
    "sg:tags":[
        "thai"
    ],
    "wof:name":"Thai BBQ & Noodle",
    "wof:placetype":"venue"
},
  "geometry": {"coordinates":[-118.02843300000001,33.828592],"type":"Point"}
}