{
  "type": "Feature",
  "properties": {
    "addr:full":"2800 N Main St Ste 232 Santa Ana CA 92705",
    "addr:housenumber":"2800",
    "addr:postcode":"92705",
    "addr:street":"N Main St Ste 232",
    "iso:country":"US",
    "sg:address":"2800 N Main St Ste 232",
    "sg:city":"Santa Ana",
    "sg:classifiers":[
        {
            "category":"Shopping",
            "subcategory":"Clothing, Apparel, & Fashions",
            "type":"Retail Goods"
        }
    ],
    "sg:phone":"+1 714 564 0721",
    "sg:postcode":"92705",
    "sg:province":"CA",
    "sg:tags":[
        "accessory",
        "clothing",
        "women's"
    ],
    "sg:website":"www.forever21.com",
    "wof:name":"Forever 21",
    "wof:placetype":"venue"
},
  "geometry": {"coordinates":[-117.869174,33.776339],"type":"Point"}
}