{
  "type": "Feature",
  "properties": {
    "addr:full":"25324 Via Artina Valencia CA 91355",
    "addr:housenumber":"25324",
    "addr:postcode":"91355",
    "addr:street":"Via Artina",
    "iso:country":"US",
    "sg:address":"25324 Via Artina",
    "sg:city":"Valencia",
    "sg:classifiers":[
        {
            "category":"Professional",
            "type":"Services"
        }
    ],
    "sg:phone":"+1 661 255 3288",
    "sg:postcode":"91355",
    "sg:province":"CA",
    "wof:name":"French Accent",
    "wof:placetype":"venue"
},
  "geometry": {"coordinates":[-118.556015,34.381255],"type":"Point"}
}