{
  "type": "Feature",
  "properties": {
    "iso:country":"US",
    "sg:address":"8429 Oakdale Ave",
    "sg:city":"Winnetka",
    "sg:classifiers":[
        {
            "category":"Professional",
            "subcategory":"Accounting & Tax Preparation",
            "type":"Services"
        }
    ],
    "sg:phone":"+1 818 886 4733",
    "sg:postcode":"91306",
    "sg:province":"CA",
    "wof:name":"Metromedical Mg",
    "wof:placetype":"venue"
},
  "geometry": {"coordinates":[-118.566744,34.2239],"type":"Point"}
}