{
  "type": "Feature",
  "properties": {
    "iso:country":"US",
    "sg:address":"7 Fairfield",
    "sg:city":"El Toro",
    "sg:classifiers":[
        {
            "category":"Building & Trades",
            "subcategory":"Construction",
            "type":"Services"
        }
    ],
    "sg:phone":"+1 949 294 8317",
    "sg:postcode":"92610",
    "sg:province":"CA",
    "sg:tags":[
        "house"
    ],
    "wof:name":"Accurate Construction Inc",
    "wof:placetype":"venue"
},
  "geometry": {"coordinates":[-117.67054,33.68707],"type":"Point"}
}