{
  "type": "Feature",
  "properties": {
    "iso:country":"US",
    "sg:address":"4043 Piedmont Ave",
    "sg:city":"Oakland",
    "sg:classifiers":[
        {
            "category":"Building & Trades",
            "subcategory":"Construction",
            "type":"Services"
        }
    ],
    "sg:phone":"+1 510 430 9332",
    "sg:postcode":"94611",
    "sg:province":"CA",
    "sg:tags":[
        "repairing",
        "remodeling",
        "contractor"
    ],
    "wof:name":"Wesley Construction Co",
    "wof:placetype":"venue"
},
  "geometry": {"coordinates":[-122.253432,37.825807],"type":"Point"}
}