{
  "type": "Feature",
  "properties": {
    "iso:country":"US",
    "sg:address":"540 N Santa Cruz Avenue",
    "sg:city":"Los Gatos",
    "sg:classifiers":[
        {
            "category":"Shopping",
            "subcategory":"Pets & Pet Supplies",
            "type":"Retail Goods"
        }
    ],
    "sg:phone":"+1 408 395 7074",
    "sg:postcode":"95030",
    "sg:province":"CA",
    "sg:tags":[
        "store"
    ],
    "wof:name":"Petco",
    "wof:placetype":"venue"
},
  "geometry": {"coordinates":[-121.979015,37.23299],"type":"Point"}
}