{
  "type": "Feature",
  "properties": {
    "addr:full":"10161 Bolsa Ave Ste A109 Westminster CA 92683",
    "addr:housenumber":"10161",
    "addr:postcode":"92683",
    "addr:street":"Bolsa Ave Ste A109",
    "iso:country":"US",
    "sg:address":"10161 Bolsa Ave Ste A109",
    "sg:city":"Westminster",
    "sg:classifiers":[
        {
            "category":"Restaurant",
            "type":"Food & Drink"
        }
    ],
    "sg:phone":"+1 714 531 3700",
    "sg:postcode":"92683",
    "sg:province":"CA",
    "wof:name":"Crawfish Factory",
    "wof:placetype":"venue"
},
  "geometry": {"coordinates":[-117.951864,33.745041],"type":"Point"}
}