{
  "type": "Feature",
  "properties": {
    "addr:full":"4000 Rhonda Dr San Jose CA 95101",
    "addr:housenumber":"4000",
    "addr:postcode":"95101",
    "addr:street":"Rhonda Dr",
    "iso:country":"US",
    "sg:address":"4000 Rhonda Dr",
    "sg:city":"San Jose",
    "sg:classifiers":[
        {
            "category":"Education",
            "subcategory":"School",
            "type":"Public Place"
        }
    ],
    "sg:phone":"+1 408 874 3100",
    "sg:postcode":"95101",
    "sg:province":"CA",
    "sg:tags":[
        "high",
        "middle",
        "elementary"
    ],
    "wof:name":"Anderson Elementary School",
    "wof:placetype":"venue"
},
  "geometry": {"coordinates":[-121.887001,37.388302],"type":"Point"}
}