{
  "type": "Feature",
  "properties": {
    "addr:full":"2220 Montana Ave Santa Monica CA 90403",
    "addr:housenumber":"2220",
    "addr:postcode":"90403",
    "addr:street":"Montana Ave",
    "iso:country":"US",
    "sg:address":"2220 Montana Ave",
    "sg:city":"Santa Monica",
    "sg:classifiers":[
        {
            "category":"Professional",
            "type":"Services"
        }
    ],
    "sg:phone":"+1 310 828 8817",
    "sg:postcode":"90403",
    "sg:province":"CA",
    "wof:name":"Glimmer",
    "wof:placetype":"venue"
},
  "geometry": {"coordinates":[-118.48666799999999,34.038992],"type":"Point"}
}