{
  "type": "Feature",
  "properties": {
    "addr:full":"110 Chase Ln Aptos CA 95003",
    "addr:housenumber":"110",
    "addr:postcode":"ca 95003",
    "addr:street":"Chase Ln",
    "iso:country":"US",
    "sg:address":"110 Chase Ln",
    "sg:city":"Aptos",
    "sg:classifiers":[
        {
            "category":"Manufacturing",
            "subcategory":"Printing",
            "type":"Manufacturing & Wholesale Goods"
        }
    ],
    "sg:phone":"+1 831 662 9584",
    "sg:postcode":"95003",
    "sg:province":"CA",
    "sg:tags":[
        "periodical"
    ],
    "wof:name":"Vance Publishing Corporation",
    "wof:placetype":"venue"
},
  "geometry": {"coordinates":[-121.898174,36.980394],"type":"Point"}
}