{
  "type": "Feature",
  "properties": {
    "addr:full":"14504 Nordhoff St Panorama City CA 91402",
    "addr:housenumber":"14504",
    "addr:postcode":"91402",
    "addr:street":"Nordhoff St",
    "iso:country":"US",
    "sg:address":"14504 Nordhoff St",
    "sg:city":"Panorama City",
    "sg:classifiers":[
        {
            "category":"Food & Beverages",
            "subcategory":"Bakery",
            "type":"Retail Goods"
        }
    ],
    "sg:phone":"+1 818 892 5904",
    "sg:postcode":"91402",
    "sg:province":"CA",
    "sg:tags":[
        "baker"
    ],
    "wof:name":"Panaderia LA Competidora",
    "wof:placetype":"venue"
},
  "geometry": {"coordinates":[-118.449549,34.23533],"type":"Point"}
}