{
  "type": "Feature",
  "properties": {
    "iso:country":"US",
    "sg:address":"919 S Atlantic Blvd",
    "sg:city":"Monterey Park",
    "sg:classifiers":[
        {
            "category":"Wholesale",
            "subcategory":"Non-durable Goods",
            "type":"Manufacturing & Wholesale Goods"
        }
    ],
    "sg:phone":"+1 626 300 8240",
    "sg:postcode":"91754",
    "sg:province":"CA",
    "wof:name":"First Top Home Loan Corp",
    "wof:placetype":"venue"
},
  "geometry": {"coordinates":[-118.138947,34.049569],"type":"Point"}
}