{
  "type": "Feature",
  "properties": {
    "addr:full":"564 Market St San Francisco CA 94104",
    "addr:housenumber":"564",
    "addr:postcode":"94104",
    "addr:street":"Market St",
    "iso:country":"US",
    "sg:address":"564 Market St",
    "sg:city":"San Francisco",
    "sg:classifiers":[
        {
            "category":"Personal",
            "type":"Services"
        }
    ],
    "sg:phone":"+1 415 205 2930",
    "sg:postcode":"94104",
    "sg:province":"CA",
    "sg:tags":[
        "electrolysis"
    ],
    "wof:name":"Personal Touch Electrolysis",
    "wof:placetype":"venue"
},
  "geometry": {"coordinates":[-122.400527,37.790271],"type":"Point"}
}