{
  "type": "Feature",
  "properties": {
    "iso:country":"US",
    "sg:address":"1711 Chelsea Way",
    "sg:city":"Roseville",
    "sg:classifiers":[
        {
            "category":"Building & Trades",
            "subcategory":"Electrical",
            "type":"Services"
        },
        {
            "category":"Wholesale",
            "subcategory":"Electrical",
            "type":"Manufacturing & Wholesale Goods"
        }
    ],
    "sg:phone":"+1 916 773 4080",
    "sg:postcode":"95661",
    "sg:province":"CA",
    "sg:tags":[
        "burglar",
        "fire",
        "alarm",
        "system",
        "contractor",
        "security"
    ],
    "wof:name":"Cornerstone Protective Svcs",
    "wof:placetype":"venue"
},
  "geometry": {"coordinates":[-121.259356,38.722677],"type":"Point"}
}