{
  "type": "Feature",
  "properties": {
    "addr:full":"450 Corbett Ave San Francisco CA 94114",
    "addr:housenumber":"450",
    "addr:postcode":"94114",
    "addr:street":"Corbett Ave",
    "iso:country":"US",
    "sg:address":"450 Corbett Ave",
    "sg:city":"San Francisco",
    "sg:classifiers":[
        {
            "category":"Real Estate",
            "subcategory":"Architect",
            "type":"Services"
        }
    ],
    "sg:phone":"+1 415 255 2932",
    "sg:postcode":"94114",
    "sg:province":"CA",
    "wof:name":"Biko Production",
    "wof:placetype":"venue"
},
  "geometry": {"coordinates":[-122.445712,37.75791],"type":"Point"}
}