{
  "type": "Feature",
  "properties": {
    "iso:country":"US",
    "sg:address":"2213 Pacific Coast Hwy",
    "sg:city":"Lomita",
    "sg:classifiers":[
        {
            "category":"Professional",
            "type":"Services"
        }
    ],
    "sg:phone":"+1 310 534 2974",
    "sg:postcode":"90717",
    "sg:province":"CA",
    "sg:tags":[
        "art",
        "restoring"
    ],
    "wof:name":"A & K Studio Framers",
    "wof:placetype":"venue"
},
  "geometry": {"coordinates":[-118.321398,33.789612],"type":"Point"}
}