{
  "type": "Feature",
  "properties": {
    "addr:full":"13848 Ventura Blvd Sherman Oaks CA 91423",
    "addr:housenumber":"13848",
    "addr:postcode":"91423",
    "addr:street":"Ventura Blvd",
    "iso:country":"US",
    "sg:address":"13848 Ventura Blvd",
    "sg:city":"Sherman Oaks",
    "sg:classifiers":[
        {
            "category":"Banks & Credit Unions",
            "subcategory":"Bank",
            "type":"Services"
        }
    ],
    "sg:phone":"+1 818 788 6303",
    "sg:postcode":"91423",
    "sg:province":"CA",
    "sg:tags":[
        "loan",
        "real estate"
    ],
    "wof:name":"Sterling Finance Co",
    "wof:placetype":"venue"
},
  "geometry": {"coordinates":[-118.434731,34.148519],"type":"Point"}
}