{
  "type": "Feature",
  "properties": {
    "addr:full":"28641 S Western Ave Rancho Palos Verdes CA 90275",
    "addr:housenumber":"28641",
    "addr:postcode":"90275",
    "addr:street":"S Western Ave",
    "iso:country":"US",
    "sg:address":"28641 S Western Ave",
    "sg:city":"Rancho Palos Verdes",
    "sg:classifiers":[
        {
            "category":"Deli",
            "type":"Food & Drink"
        },
        {
            "category":"Restaurant",
            "type":"Food & Drink"
        },
        {
            "category":"Recreation",
            "type":"Entertainment"
        }
    ],
    "sg:phone":"+1 310 832 9786",
    "sg:postcode":"90275",
    "sg:province":"CA",
    "sg:tags":[
        "active",
        "life",
        "italian"
    ],
    "sg:website":"www.portsidedeli.com",
    "wof:name":"Calatrello's Portside Deli & Gourmet Meats",
    "wof:placetype":"venue"
},
  "geometry": {"coordinates":[-118.312653,33.759431],"type":"Point"}
}