{
  "type": "Feature",
  "properties": {
    "addr:full":"6231 Geary Blvd San Francisco CA 94121",
    "addr:housenumber":"6231",
    "addr:postcode":"94121",
    "addr:street":"Geary Blvd",
    "iso:country":"US",
    "sg:address":"6231 Geary Blvd",
    "sg:city":"San Francisco",
    "sg:classifiers":[
        {
            "category":"Social Services",
            "type":"Services"
        }
    ],
    "sg:phone":"+1 415 876 0564",
    "sg:postcode":"94121",
    "sg:province":"CA",
    "sg:tags":[
        "youth",
        "organization",
        "center"
    ],
    "wof:name":"St George Pathfinders",
    "wof:placetype":"venue"
},
  "geometry": {"coordinates":[-122.486594,37.779865],"type":"Point"}
}