{
  "type": "Feature",
  "properties": {
    "addr:full":"304 E Clark St Redlands CA 92373",
    "addr:housenumber":"304",
    "addr:postcode":"92373",
    "addr:street":"E Clark St",
    "iso:country":"US",
    "sg:address":"304 E Clark St",
    "sg:city":"Redlands",
    "sg:classifiers":[
        {
            "category":"Building & Trades",
            "subcategory":"Landscaping Services",
            "type":"Services"
        }
    ],
    "sg:phone":"+1 909 889 7541",
    "sg:postcode":"92373",
    "sg:province":"CA",
    "sg:tags":[
        "tree"
    ],
    "wof:name":"A-1 Tree Svc",
    "wof:placetype":"venue"
},
  "geometry": {"coordinates":[-117.175996,34.054006],"type":"Point"}
}