{
  "type": "Feature",
  "properties": {
    "addr:full":"1 Eastridge Mall San Jose CA 95122",
    "addr:housenumber":"1",
    "addr:postcode":"95122",
    "addr:street":"Eastridge Mall",
    "iso:country":"US",
    "sg:address":"1 Eastridge Mall",
    "sg:city":"San Jose",
    "sg:classifiers":[
        {
            "category":"Shopping",
            "subcategory":"Mobile Phones",
            "type":"Retail Goods"
        }
    ],
    "sg:phone":"+1 408 274 1360",
    "sg:postcode":"95122",
    "sg:province":"CA",
    "wof:name":"The Mobile Solution",
    "wof:placetype":"venue"
},
  "geometry": {"coordinates":[-121.81499599999999,37.328453],"type":"Point"}
}