{
  "type": "Feature",
  "properties": {
    "addr:full":"1333 N Mcdowell Blvd Petaluma CA 94954",
    "addr:housenumber":"1333",
    "addr:postcode":"94954",
    "addr:street":"N Mcdowell Blvd",
    "iso:country":"US",
    "sg:address":"1333 N Mcdowell Blvd",
    "sg:city":"Petaluma",
    "sg:classifiers":[
        {
            "category":"Professional",
            "subcategory":"Computer Services",
            "type":"Services"
        }
    ],
    "sg:phone":"+1 707 781 9999",
    "sg:postcode":"94954",
    "sg:province":"CA",
    "sg:tags":[
        "isp",
        "provider",
        "internet"
    ],
    "wof:name":"Silicon Valley North",
    "wof:placetype":"venue"
},
  "geometry": {"coordinates":[-122.663439,38.272184],"type":"Point"}
}