{
  "type": "Feature",
  "properties": {
    "addr:full":"1138 Meadow Ln Concord CA 94520",
    "addr:housenumber":"1138",
    "addr:postcode":"94520",
    "addr:street":"Meadow Ln",
    "iso:country":"US",
    "sg:address":"1138 Meadow Ln",
    "sg:city":"Concord",
    "sg:classifiers":[
        {
            "category":"Autos & Motor Vehicles",
            "subcategory":"Auto Supplies",
            "type":"Retail Goods"
        }
    ],
    "sg:phone":"+1 925 521 0300",
    "sg:postcode":"94520",
    "sg:province":"CA",
    "sg:tags":[
        "automobile",
        "parts"
    ],
    "wof:name":"Asc Alternator & Starter Co",
    "wof:placetype":"venue"
},
  "geometry": {"coordinates":[-122.039176,37.95672],"type":"Point"}
}