{
  "type": "Feature",
  "properties": {
    "iso:country":"US",
    "sg:address":"1820 N Long Beach Blvd",
    "sg:city":"Compton",
    "sg:classifiers":[
        {
            "category":"Shopping",
            "subcategory":"Department Store",
            "type":"Retail Goods"
        }
    ],
    "sg:phone":"+1 310 537 4177",
    "sg:postcode":"90221",
    "sg:province":"CA",
    "sg:tags":[
        "variety"
    ],
    "sg:website":"http://www.dollar.com",
    "wof:name":"Dolex Dollar Express, Inc.",
    "wof:placetype":"venue"
},
  "geometry": {"coordinates":[-118.208772,33.908054],"type":"Point"}
}