{
  "type": "Feature",
  "properties": {
    "addr:full":"531 Bryant St San Francisco CA 94107",
    "addr:housenumber":"531",
    "addr:postcode":"94107",
    "addr:street":"Bryant St",
    "iso:country":"US",
    "sg:address":"531 Bryant St",
    "sg:city":"San Francisco",
    "sg:classifiers":[
        {
            "category":"Wholesale",
            "subcategory":"Furniture",
            "type":"Manufacturing & Wholesale Goods"
        }
    ],
    "sg:phone":"+1 415 278 9640",
    "sg:postcode":"94107",
    "sg:province":"CA",
    "sg:website":"www.thechairplace.com",
    "wof:name":"Chair Place",
    "wof:placetype":"venue"
},
  "geometry": {"coordinates":[-122.396467,37.7808],"type":"Point"}
}