{
  "type": "Feature",
  "properties": {
    "addr:full":"4859 Scotts Valley Dr Scotts Valley CA 95066",
    "addr:housenumber":"4859",
    "addr:postcode":"95066",
    "addr:street":"Scotts Valley Dr",
    "iso:country":"US",
    "sg:address":"4859 Scotts Valley Dr",
    "sg:city":"Scotts Valley",
    "sg:classifiers":[
        {
            "category":"Personal",
            "subcategory":"Beauty Salon",
            "type":"Services"
        }
    ],
    "sg:phone":"+1 831 440 1800",
    "sg:postcode":"95066",
    "sg:province":"CA",
    "sg:tags":[
        "spa",
        "day"
    ],
    "wof:name":"D'Lauren Cosmetics & Spa",
    "wof:placetype":"venue"
},
  "geometry": {"coordinates":[-122.013756,37.052479],"type":"Point"}
}