{
  "type": "Feature",
  "properties": {
    "iso:country":"US",
    "sg:address":"2175 Francisco Blvd E",
    "sg:city":"San Rafael",
    "sg:classifiers":[
        {
            "category":"Professional",
            "subcategory":"Engineering",
            "type":"Services"
        }
    ],
    "sg:phone":"+1 415 454 6056",
    "sg:postcode":"94901",
    "sg:province":"CA",
    "sg:tags":[
        "engineer"
    ],
    "wof:name":"Hydrologic Systems",
    "wof:placetype":"venue"
},
  "geometry": {"coordinates":[-122.479772,37.943662],"type":"Point"}
}