{
  "type": "Feature",
  "properties": {
    "addr:full":"11612 Knott St. #12 Garden Grove CA 92845",
    "addr:housenumber":"11612",
    "addr:postcode":"92845",
    "addr:street":"Knott St. # 12",
    "iso:country":"US",
    "sg:address":"11612 Knott St. #12",
    "sg:city":"Garden Grove",
    "sg:classifiers":[
        {
            "category":"Personal",
            "subcategory":"Beauty Salon",
            "type":"Services"
        }
    ],
    "sg:phone":"+1 714 393 4186",
    "sg:postcode":"92845",
    "sg:province":"CA",
    "sg:tags":[
        "makeup",
        "artist"
    ],
    "sg:website":"www.artisticcosmeticsolutions.com",
    "wof:name":"Artistic Cosmetic Solutions",
    "wof:placetype":"venue"
},
  "geometry": {"coordinates":[-118.01107500000001,33.793463],"type":"Point"}
}