{
  "type": "Feature",
  "properties": {
    "addr:full":"2658 Griffith Park Blvd Los Angeles CA 90039",
    "addr:housenumber":"2658",
    "addr:postcode":"90039",
    "addr:street":"Griffith Park Blvd",
    "iso:country":"US",
    "sg:address":"2658 Griffith Park Blvd",
    "sg:city":"Los Angeles",
    "sg:classifiers":[
        {
            "category":"Personal",
            "type":"Services"
        },
        {
            "category":"Shopping",
            "subcategory":"Pets & Pet Supplies",
            "type":"Retail Goods"
        }
    ],
    "sg:phone":"+1 213 260 1094",
    "sg:postcode":"90039",
    "sg:province":"CA",
    "sg:tags":[
        "walker",
        "party",
        "planning",
        "dog",
        "event"
    ],
    "wof:name":"The Natallia Agency, Personal Assistants",
    "wof:placetype":"venue"
},
  "geometry": {"coordinates":[-118.27216900000001,34.106632],"type":"Point"}
}