{
  "type": "Feature",
  "properties": {
    "iso:country":"US",
    "sg:address":"15045 W Sunset Blvd",
    "sg:city":"Pacific Palisades",
    "sg:classifiers":[
        {
            "category":"Government",
            "subcategory":"Fire Station",
            "type":"Public Place"
        }
    ],
    "sg:phone":"+1 310 575 8569",
    "sg:postcode":"90272",
    "sg:province":"CA",
    "sg:tags":[
        "protection"
    ],
    "wof:name":"Fire Dept-Station 69",
    "wof:placetype":"venue"
},
  "geometry": {"coordinates":[-118.522333,34.044511],"type":"Point"}
}