{
  "type": "Feature",
  "properties": {
    "addr:full":"14103 Brighton Ave Gardena CA 90249",
    "addr:housenumber":"14103",
    "addr:postcode":"90249",
    "addr:street":"Brighton Ave",
    "iso:country":"US",
    "sg:address":"14103 Brighton Ave",
    "sg:city":"Gardena",
    "sg:classifiers":[
        {
            "category":"Professional",
            "subcategory":"Business Services",
            "type":"Services"
        }
    ],
    "sg:phone":"+1 323 636 5761",
    "sg:postcode":"90249",
    "sg:province":"CA",
    "sg:tags":[
        "packaging"
    ],
    "wof:name":"Best Packing Supplies",
    "wof:placetype":"venue"
},
  "geometry": {"coordinates":[-118.301565,33.901939],"type":"Point"}
}