{
  "type": "Feature",
  "properties": {
    "iso:country":"US",
    "sg:address":"3612 Ocean Dr",
    "sg:city":"Manhattan Beach",
    "sg:classifiers":[
        {
            "category":"Insurance",
            "subcategory":"Insurance Agent",
            "type":"Services"
        }
    ],
    "sg:phone":"+1 310 478 0800",
    "sg:postcode":"90266",
    "sg:province":"CA",
    "sg:tags":[
        "adjuster"
    ],
    "wof:name":"Fleming & Hall LTD",
    "wof:placetype":"venue"
},
  "geometry": {"coordinates":[-118.41901300000001,33.899861],"type":"Point"}
}