{
  "type": "Feature",
  "properties": {
    "iso:country":"US",
    "sg:address":"1668 Main St",
    "sg:city":"Ramona",
    "sg:classifiers":[
        {
            "category":"Manufacturing",
            "subcategory":"Printing",
            "type":"Manufacturing & Wholesale Goods"
        }
    ],
    "sg:phone":"+1 760 788 0535",
    "sg:postcode":"92065",
    "sg:province":"CA",
    "sg:tags":[
        "screen"
    ],
    "wof:name":"Marketing WORX",
    "wof:placetype":"venue"
},
  "geometry": {"coordinates":[-116.878827,33.036359],"type":"Point"}
}