{
  "type": "Feature",
  "properties": {
    "addr:full":"7204 Walter Ave Sacramento CA 95828",
    "addr:housenumber":"7204",
    "addr:postcode":"95828",
    "addr:street":"Walter Ave",
    "iso:country":"US",
    "sg:address":"7204 Walter Ave",
    "sg:city":"Sacramento",
    "sg:classifiers":[
        {
            "category":"Professional",
            "type":"Services"
        }
    ],
    "sg:phone":"+1 916 682 5240",
    "sg:postcode":"95828",
    "sg:province":"CA",
    "sg:tags":[
        "publication",
        "editorial"
    ],
    "wof:name":"Gloria Cooksey",
    "wof:placetype":"venue"
},
  "geometry": {"coordinates":[-121.41943999999999,38.484959],"type":"Point"}
}