{
  "type": "Feature",
  "properties": {
    "iso:country":"US",
    "sg:address":"1276 N Lake Ave",
    "sg:city":"Pasadena",
    "sg:classifiers":[
        {
            "category":"Personal",
            "subcategory":"Beauty Salon",
            "type":"Services"
        }
    ],
    "sg:phone":"+1 626 794 9810",
    "sg:postcode":"91104",
    "sg:province":"CA",
    "wof:name":"Great Unisex",
    "wof:placetype":"venue"
},
  "geometry": {"coordinates":[-118.13221,34.16768],"type":"Point"}
}