{
  "type": "Feature",
  "properties": {
    "addr:full":"223 Erbes Rd Thousand Oaks CA 91362",
    "addr:housenumber":"223",
    "addr:postcode":"91362",
    "addr:street":"Erbes Rd",
    "iso:country":"US",
    "sg:address":"223 Erbes Rd",
    "sg:city":"Thousand Oaks",
    "sg:classifiers":[
        {
            "category":"Real Estate",
            "subcategory":"Real Estate Operator",
            "type":"Services"
        }
    ],
    "sg:phone":"+1 805 495 5520",
    "sg:postcode":"91362",
    "sg:province":"CA",
    "sg:tags":[
        "apartment"
    ],
    "wof:name":"LA Cresta Garden Apartments",
    "wof:placetype":"venue"
},
  "geometry": {"coordinates":[-118.848618,34.180204],"type":"Point"}
}