{
  "type": "Feature",
  "properties": {
    "iso:country":"US",
    "sg:address":"1303 Grand Ave",
    "sg:city":"Arroyo Grande",
    "sg:classifiers":[
        {
            "category":"Professional",
            "subcategory":"Accounting & Tax Preparation",
            "type":"Services"
        }
    ],
    "sg:phone":"+1 805 481 7600",
    "sg:postcode":"93420",
    "sg:province":"CA",
    "sg:tags":[
        "accountant"
    ],
    "sg:website":"www.lyonscpas.com",
    "wof:name":"Lyons & Lyons",
    "wof:placetype":"venue"
},
  "geometry": {"coordinates":[-120.602001,35.120512],"type":"Point"}
}