{
  "type": "Feature",
  "properties": {
    "iso:country":"US",
    "sg:address":"3740 E Colorado Blvd",
    "sg:city":"Pasadena",
    "sg:classifiers":[
        {
            "category":"Professional",
            "subcategory":"Computer Services",
            "type":"Services"
        }
    ],
    "sg:phone":"+1 626 720 3028",
    "sg:postcode":"91107",
    "sg:province":"CA",
    "sg:tags":[
        "repair"
    ],
    "sg:website":"www.silution.com",
    "wof:name":"Silution",
    "wof:placetype":"venue"
},
  "geometry": {"coordinates":[-118.20868900000001,34.146092],"type":"Point"}
}