{
  "type": "Feature",
  "properties": {
    "iso:country":"US",
    "sg:address":"7060 Motz St",
    "sg:city":"Paramount",
    "sg:classifiers":[
        {
            "category":"Shopping",
            "subcategory":"Stationery & Office Supplies",
            "type":"Retail Goods"
        }
    ],
    "sg:phone":"+1 562 531 2686",
    "sg:postcode":"90723",
    "sg:province":"CA",
    "sg:tags":[
        "equipment"
    ],
    "wof:name":"Corona Bros Installation",
    "wof:placetype":"venue"
},
  "geometry": {"coordinates":[-118.175281,33.887288],"type":"Point"}
}