{
  "type": "Feature",
  "properties": {
    "addr:full":"14936 Dillow St Westminster CA 92683",
    "addr:housenumber":"14936",
    "addr:postcode":"92683",
    "addr:street":"Dillow St",
    "iso:country":"US",
    "sg:address":"14936 Dillow St",
    "sg:city":"Westminster",
    "sg:classifiers":[
        {
            "category":"Freight",
            "type":"Transportation"
        }
    ],
    "sg:phone":"+1 714 899 1345",
    "sg:postcode":"92683",
    "sg:province":"CA",
    "sg:tags":[
        "opera",
        "arrangement",
        "local",
        "trucking"
    ],
    "wof:name":"Vn Cargo",
    "wof:placetype":"venue"
},
  "geometry": {"coordinates":[-117.966241,33.747147],"type":"Point"}
}