{
  "type": "Feature",
  "properties": {
    "iso:country":"US",
    "sg:address":"18812 Lenross Ct",
    "sg:city":"Castro Valley",
    "sg:classifiers":[
        {
            "category":"Building & Trades",
            "subcategory":"Construction",
            "type":"Services"
        }
    ],
    "sg:phone":"+1 510 538 1530",
    "sg:postcode":"94546",
    "sg:province":"CA",
    "sg:tags":[
        "contractor"
    ],
    "sg:website":"www.wonderlinroofing.com/",
    "wof:name":"Wonderlin Roofing Systems",
    "wof:placetype":"venue"
},
  "geometry": {"coordinates":[-122.079075,37.709749],"type":"Point"}
}