{
  "type": "Feature",
  "properties": {
    "addr:full":"5123 Sierra St Riverside CA 92504",
    "addr:housenumber":"5123",
    "addr:postcode":"92504",
    "addr:street":"Sierra St",
    "iso:country":"US",
    "sg:address":"5123 Sierra St",
    "sg:city":"Riverside",
    "sg:classifiers":[
        {
            "category":"Social Services",
            "subcategory":"Child Care",
            "type":"Services"
        }
    ],
    "sg:phone":"+1 951 354 2956",
    "sg:postcode":"92504",
    "sg:province":"CA",
    "wof:name":"Mary's Tot Stop Child Dev Ctr",
    "wof:placetype":"venue"
},
  "geometry": {"coordinates":[-117.41488699999999,33.949831],"type":"Point"}
}