{
  "type": "Feature",
  "properties": {
    "addr:full":"6501 Schirra Ct Bakersfield CA 93313",
    "addr:housenumber":"6501",
    "addr:postcode":"93313",
    "addr:street":"Schirra Ct",
    "iso:country":"US",
    "sg:address":"6501 Schirra Ct",
    "sg:city":"Bakersfield",
    "sg:classifiers":[
        {
            "category":"Organizations",
            "subcategory":"Religious Organization",
            "type":"Services"
        }
    ],
    "sg:phone":"+1 661 397 6422",
    "sg:postcode":"93313",
    "sg:province":"CA",
    "sg:tags":[
        "church"
    ],
    "wof:name":"Westbrook Chapel",
    "wof:placetype":"venue"
},
  "geometry": {"coordinates":[-119.08162799999999,35.31661],"type":"Point"}
}