{
  "type": "Feature",
  "properties": {
    "addr:full":"218 Reindollar Ave Marina CA 93933",
    "addr:housenumber":"218",
    "addr:postcode":"93933",
    "addr:street":"Reindollar Ave",
    "iso:country":"US",
    "sg:address":"218 Reindollar Ave",
    "sg:city":"Marina",
    "sg:classifiers":[
        {
            "category":"Retail",
            "subcategory":"Auto Repair",
            "type":"Services"
        }
    ],
    "sg:phone":"+1 831 384 6007",
    "sg:postcode":"93933",
    "sg:province":"CA",
    "sg:tags":[
        "body",
        "coating",
        "tinting",
        "trade",
        "glass",
        "contractor"
    ],
    "wof:name":"Peninsula Tint",
    "wof:placetype":"venue"
},
  "geometry": {"coordinates":[-121.80410999999999,36.68015],"type":"Point"}
}