{
  "type": "Feature",
  "properties": {
    "iso:country":"US",
    "sg:address":"13887 S Park Dr",
    "sg:city":"Magalia",
    "sg:classifiers":[
        {
            "category":"Banks & Credit Unions",
            "subcategory":"Financial Services",
            "type":"Services"
        }
    ],
    "sg:phone":"+1 530 873 4090",
    "sg:postcode":"95954",
    "sg:province":"CA",
    "sg:tags":[
        "investor"
    ],
    "wof:name":"Pickerrell Farris Wood",
    "wof:placetype":"venue"
},
  "geometry": {"coordinates":[-121.593947,39.81352],"type":"Point"}
}