{
  "type": "Feature",
  "properties": {
    "iso:country":"US",
    "sg:address":"11100 Cumpston St",
    "sg:city":"North Hollywood",
    "sg:classifiers":[
        {
            "category":"Building & Trades",
            "subcategory":"Electrical",
            "type":"Services"
        }
    ],
    "sg:phone":"+1 626 296 3666",
    "sg:postcode":"91601",
    "sg:province":"CA",
    "sg:tags":[
        "electrician"
    ],
    "wof:name":"Electric Connection",
    "wof:placetype":"venue"
},
  "geometry": {"coordinates":[-118.373001,34.169998],"type":"Point"}
}