{
  "type": "Feature",
  "properties": {
    "addr:full":"14027 River Rd Walnut Grove CA 95690",
    "addr:housenumber":"14027",
    "addr:postcode":"95690",
    "addr:street":"River Rd",
    "iso:country":"US",
    "sg:address":"14027 River Rd",
    "sg:city":"Walnut Grove",
    "sg:phone":"+1 916 776 1511",
    "sg:postcode":"95690",
    "sg:province":"CA",
    "sg:tags":[
        "gas"
    ],
    "wof:name":"Sheldon Gas Co",
    "wof:placetype":"venue"
},
  "geometry": {"coordinates":[-121.51461399999999,38.243477],"type":"Point"}
}