{
  "type": "Feature",
  "properties": {
    "iso:country":"US",
    "sg:address":"141 W McKnight Way",
    "sg:city":"Grass Valley",
    "sg:classifiers":[
        {
            "category":"Shopping",
            "subcategory":"Gifts & Souvenirs",
            "type":"Retail Goods"
        }
    ],
    "sg:phone":"+1 530 273 5442",
    "sg:postcode":"95949",
    "sg:province":"CA",
    "sg:tags":[
        "shop"
    ],
    "wof:name":"Kathy's Hallmark",
    "wof:placetype":"venue"
},
  "geometry": {"coordinates":[-121.061464,39.199504],"type":"Point"}
}