{
  "type": "Feature",
  "properties": {
    "iso:country":"US",
    "sg:address":"250 E El Segundo Blvd",
    "sg:city":"Los Angeles",
    "sg:classifiers":[
        {
            "category":"Shopping",
            "subcategory":"Bicycles & Sporting Goods",
            "type":"Retail Goods"
        }
    ],
    "sg:phone":"+1 310 768 3347",
    "sg:postcode":"90061",
    "sg:province":"CA",
    "wof:name":"Karla's Beauty Salon",
    "wof:placetype":"venue"
},
  "geometry": {"coordinates":[-118.269997,33.916302],"type":"Point"}
}