{
  "type": "Feature",
  "properties": {
    "iso:country":"US",
    "sg:address":"2150 N Centre City Pkwy #A",
    "sg:city":"Escondido",
    "sg:classifiers":[
        {
            "category":"Insurance",
            "subcategory":"Insurance Agent",
            "type":"Services"
        },
        {
            "category":"Insurance",
            "subcategory":"Hazard Insurance",
            "type":"Services"
        },
        {
            "category":"Insurance",
            "subcategory":"Title Insurance",
            "type":"Services"
        },
        {
            "category":"Insurance",
            "subcategory":"Life Insurance",
            "type":"Services"
        }
    ],
    "sg:phone":"+1 760 480 8761",
    "sg:postcode":"92026",
    "sg:province":"CA",
    "sg:tags":[
        "auto",
        "commercial",
        "business",
        "homeowner"
    ],
    "sg:website":"http://www.farmersagent.com/tduffy/",
    "wof:name":"Thomas Duffy - Farmers Insurance",
    "wof:placetype":"venue"
},
  "geometry": {"coordinates":[-117.101264,33.15724],"type":"Point"}
}