{
  "type": "Feature",
  "properties": {
    "iso:country":"US",
    "sg:address":"3343 Santa Fe St",
    "sg:city":"Riverbank",
    "sg:classifiers":[
        {
            "category":"Professional",
            "subcategory":"Detective & Security Services",
            "type":"Services"
        }
    ],
    "sg:phone":"+1 209 869 5555",
    "sg:postcode":"95367",
    "sg:province":"CA",
    "sg:tags":[
        "system"
    ],
    "wof:name":"American Alarms & Electronics",
    "wof:placetype":"venue"
},
  "geometry": {"coordinates":[-120.934617,37.736091],"type":"Point"}
}