{
  "type": "Feature",
  "properties": {
    "addr:full":"220 W Broadway San Diego CA 92101",
    "addr:housenumber":"220",
    "addr:postcode":"92101",
    "addr:street":"W Broadway",
    "iso:country":"US",
    "sg:address":"220 W Broadway",
    "sg:city":"San Diego",
    "sg:classifiers":[
        {
            "category":"Health Services",
            "subcategory":"Doctor",
            "type":"Services"
        }
    ],
    "sg:phone":"+1 619 531 3047",
    "sg:postcode":"92101",
    "sg:province":"CA",
    "sg:tags":[
        "physician",
        "surgeon"
    ],
    "wof:name":"Forensic Psychiatry Clinic",
    "wof:placetype":"venue"
},
  "geometry": {"coordinates":[-117.16542800000001,32.715793],"type":"Point"}
}