{
  "type": "Feature",
  "properties": {
    "iso:country":"US",
    "sg:address":"1325 el Pinal Dr",
    "sg:city":"Stockton",
    "sg:classifiers":[
        {
            "category":"Building & Trades",
            "subcategory":"Construction",
            "type":"Services"
        }
    ],
    "sg:phone":"+1 209 464 7602",
    "sg:postcode":"95205",
    "sg:province":"CA",
    "sg:tags":[
        "resurfacing",
        "laying",
        "refinishing",
        "floor"
    ],
    "wof:name":"Eastbay Flooring",
    "wof:placetype":"venue"
},
  "geometry": {"coordinates":[-121.281266,37.977928],"type":"Point"}
}