{
  "type": "Feature",
  "properties": {
    "addr:full":"8881 Fletcher Pkwy La Mesa CA 91942",
    "addr:housenumber":"8881",
    "addr:postcode":"91942",
    "addr:street":"Fletcher Pkwy",
    "iso:country":"US",
    "sg:address":"8881 Fletcher Pkwy",
    "sg:city":"La Mesa",
    "sg:classifiers":[
        {
            "category":"Health Services",
            "subcategory":"Doctor",
            "type":"Services"
        }
    ],
    "sg:phone":"+1 619 644 1400",
    "sg:postcode":"91942",
    "sg:province":"CA",
    "sg:tags":[
        "physician",
        "surgeon"
    ],
    "wof:name":"Kuljinder Grewal Inc",
    "wof:placetype":"venue"
},
  "geometry": {"coordinates":[-117.00197199999999,32.791629],"type":"Point"}
}