{
  "type": "Feature",
  "properties": {
    "iso:country":"US",
    "sg:address":"8751 Valley View St Ste B",
    "sg:city":"Buena Park",
    "sg:classifiers":[
        {
            "category":"Health Services",
            "subcategory":"Dentist",
            "type":"Services"
        }
    ],
    "sg:phone":"+1 714 827 2545",
    "sg:postcode":"90620",
    "sg:province":"CA",
    "wof:name":"Randall T Kanemaki, DDS",
    "wof:placetype":"venue"
},
  "geometry": {"coordinates":[-118.028489,33.835417],"type":"Point"}
}