{
  "type": "Feature",
  "properties": {
    "addr:full":"9601 Las Tunas Dr Temple City CA 91780",
    "addr:housenumber":"9601",
    "addr:postcode":"91780",
    "addr:street":"Las Tunas Dr",
    "iso:country":"US",
    "sg:address":"9601 Las Tunas Dr",
    "sg:city":"Temple City",
    "sg:classifiers":[
        {
            "category":"Banks & Credit Unions",
            "subcategory":"Bank",
            "type":"Services"
        }
    ],
    "sg:phone":"+1 626 537 3205",
    "sg:postcode":"91780",
    "sg:province":"CA",
    "wof:name":"Hsbc Bank USA",
    "wof:placetype":"venue"
},
  "geometry": {"coordinates":[-118.091166,34.106835],"type":"Point"}
}