{
  "type": "Feature",
  "properties": {
    "iso:country":"US",
    "sg:address":"1117 Fillmore St",
    "sg:city":"San Francisco",
    "sg:classifiers":[
        {
            "category":"Restaurant",
            "type":"Food & Drink"
        }
    ],
    "sg:menulink":"http://www.allmenus.com/ca/san-francisco/49968-tsing-tao-restaurant/menu/",
    "sg:phone":"+1 415 409 8818",
    "sg:postcode":"94115",
    "sg:province":"CA",
    "sg:tags":[
        "asian",
        "chinese"
    ],
    "wof:name":"Tsing Tao Restaurant",
    "wof:placetype":"venue"
},
  "geometry": {"coordinates":[-122.43201500000001,37.779789],"type":"Point"}
}