{
  "type": "Feature",
  "properties": {
    "iso:country":"US",
    "sg:address":"26 N Mill Creek Rd",
    "sg:city":"Quincy",
    "sg:classifiers":[
        {
            "category":"Local Transit",
            "type":"Transportation"
        }
    ],
    "sg:phone":"+1 530 283 2538",
    "sg:postcode":"95971",
    "sg:province":"CA",
    "sg:tags":[
        "bus",
        "line"
    ],
    "wof:name":"Plumas County Transit",
    "wof:placetype":"venue"
},
  "geometry": {"coordinates":[-120.904482,39.934282],"type":"Point"}
}