{
  "type": "Feature",
  "properties": {
    "iso:country":"US",
    "sg:address":"150 Castleton Way",
    "sg:city":"San Bruno",
    "sg:classifiers":[
        {
            "category":"Manufacturing",
            "subcategory":"Printing",
            "type":"Manufacturing & Wholesale Goods"
        }
    ],
    "sg:phone":"+1 415 433 4488",
    "sg:postcode":"94066",
    "sg:province":"CA",
    "sg:tags":[
        "printer"
    ],
    "wof:name":"CPS-San Francisco Printers",
    "wof:placetype":"venue"
},
  "geometry": {"coordinates":[-122.459384,37.630685],"type":"Point"}
}