{
  "type": "Feature",
  "properties": {
    "addr:full":"1221 Farmers Ln Santa Rosa CA 95405",
    "addr:housenumber":"1221",
    "addr:postcode":"95405",
    "addr:street":"Farmers Ln",
    "iso:country":"US",
    "sg:address":"1221 Farmers Ln",
    "sg:city":"Santa Rosa",
    "sg:classifiers":[
        {
            "category":"Banks & Credit Unions",
            "subcategory":"Investment Brokerage",
            "type":"Services"
        }
    ],
    "sg:phone":"+1 707 545 4584",
    "sg:postcode":"95405",
    "sg:province":"CA",
    "sg:tags":[
        "consultant",
        "planning",
        "financial"
    ],
    "wof:name":"Brewster Grove & Assoc",
    "wof:placetype":"venue"
},
  "geometry": {"coordinates":[-122.68713200000001,38.439953],"type":"Point"}
}