{
  "type": "Feature",
  "properties": {
    "addr:full":"542 15th St San Diego CA 92101",
    "addr:housenumber":"542",
    "addr:postcode":"92101",
    "addr:street":"15Th St",
    "iso:country":"US",
    "sg:address":"542 15th St",
    "sg:city":"San Diego",
    "sg:classifiers":[
        {
            "category":"Banks & Credit Unions",
            "subcategory":"Bank",
            "type":"Services"
        }
    ],
    "sg:phone":"+1 619 819 1603",
    "sg:postcode":"92101",
    "sg:province":"CA",
    "sg:tags":[
        "broker",
        "mortgage"
    ],
    "wof:name":"Americas Best Lenders",
    "wof:placetype":"venue"
},
  "geometry": {"coordinates":[-117.150432,32.710489],"type":"Point"}
}