{
  "type": "Feature",
  "properties": {
    "iso:country":"US",
    "sg:address":"3500 W 6th St",
    "sg:city":"Los Angeles",
    "sg:classifiers":[
        {
            "category":"Shopping",
            "subcategory":"Clothing, Apparel, & Fashions",
            "type":"Retail Goods"
        }
    ],
    "sg:phone":"+1 213 381 3106",
    "sg:postcode":"90020",
    "sg:province":"CA",
    "sg:tags":[
        "accessory",
        "clothing",
        "women's"
    ],
    "wof:name":"New York Fur La",
    "wof:placetype":"venue"
},
  "geometry": {"coordinates":[-118.298066,34.063746],"type":"Point"}
}