{
  "type": "Feature",
  "properties": {
    "iso:country":"US",
    "sg:address":"3929 Grand Ave",
    "sg:city":"Oakland",
    "sg:classifiers":[
        {
            "category":"Sports & Exercise",
            "subcategory":"Gym",
            "type":"Entertainment"
        }
    ],
    "sg:phone":"+1 510 594 8507",
    "sg:postcode":"94610",
    "sg:province":"CA",
    "sg:tags":[
        "club",
        "studio",
        "pilate",
        "health",
        "gymnasium"
    ],
    "sg:website":"www.elliehermanpilates.com",
    "wof:name":"Ellie Herman Studio",
    "wof:placetype":"venue"
},
  "geometry": {"coordinates":[-122.244828,37.818431],"type":"Point"}
}