{
  "type": "Feature",
  "properties": {
    "addr:full":"1290 San Tomas Aquino Rd San Jose CA 95117",
    "addr:housenumber":"1290",
    "addr:postcode":"95117",
    "addr:street":"San Tomas Aquino Rd",
    "iso:country":"US",
    "sg:address":"1290 San Tomas Aquino Rd",
    "sg:city":"San Jose",
    "sg:classifiers":[
        {
            "category":"Real Estate",
            "subcategory":"Real Estate Operator",
            "type":"Services"
        }
    ],
    "sg:phone":"+1 408 984 8888",
    "sg:postcode":"95117",
    "sg:province":"CA",
    "sg:tags":[
        "apartment"
    ],
    "sg:website":"www.aegena.com",
    "wof:name":"Aegena the",
    "wof:placetype":"venue"
},
  "geometry": {"coordinates":[-121.976997,37.3008],"type":"Point"}
}