{
  "type": "Feature",
  "properties": {
    "sfgov:dept":"7",
    "sfgov:deptname":"SF Unified School District (SFUSD)",
    "sfgov:facility_i":"0000060081",
    "sfgov:school_typ":"Charter School",
    "wof:categories":[
        "education_and_religion:education=school"
    ],
    "wof:name":"Five Keys Charter",
    "wof:placetype":"venue"
},
  "geometry": {"coordinates":[-122.40218005304878,37.77715318837473],"type":"Point"}
}