{
  "type": "Feature",
  "properties": {
    "iso:country":"US",
    "sg:address":"1801 E Main St",
    "sg:city":"Ventura",
    "sg:classifiers":[
        {
            "category":"Shopping",
            "subcategory":"Shoes",
            "type":"Retail Goods"
        }
    ],
    "sg:phone":"+1 805 650 3232",
    "sg:postcode":"93001",
    "sg:province":"CA",
    "wof:name":"Payless",
    "wof:placetype":"venue"
},
  "geometry": {"coordinates":[-119.272863,34.278697],"type":"Point"}
}