{
  "type": "Feature",
  "properties": {
    "addr:full":"4655 Fruitridge Rd Sacramento CA 95820",
    "addr:housenumber":"4655",
    "addr:postcode":"95820",
    "addr:street":"Fruitridge Rd",
    "iso:country":"US",
    "sg:address":"4655 Fruitridge Rd",
    "sg:city":"Sacramento",
    "sg:classifiers":[
        {
            "category":"Communications",
            "subcategory":"Television Station",
            "type":"Services"
        }
    ],
    "sg:phone":"+1 916 454 4548",
    "sg:postcode":"95820",
    "sg:province":"CA",
    "sg:website":"www.fox40.com/",
    "wof:name":"KTXL Fox 40",
    "wof:placetype":"venue"
},
  "geometry": {"coordinates":[-121.451312,38.525322],"type":"Point"}
}