{
  "type": "Feature",
  "properties": {
    "iso:country":"US",
    "sg:address":"327 W D St",
    "sg:city":"Lemoore",
    "sg:classifiers":[
        {
            "category":"Professional",
            "subcategory":"Art Services",
            "type":"Services"
        }
    ],
    "sg:phone":"+1 559 925 9005",
    "sg:postcode":"93245",
    "sg:province":"CA",
    "sg:tags":[
        "photographer"
    ],
    "wof:name":"Photographic Impressions",
    "wof:placetype":"venue"
},
  "geometry": {"coordinates":[-119.78521600000001,36.301652],"type":"Point"}
}