{
  "type": "Feature",
  "properties": {
    "iso:country":"US",
    "sg:address":"612 W Shorb St",
    "sg:city":"Alhambra",
    "sg:classifiers":[
        {
            "category":"Building & Trades",
            "subcategory":"Construction",
            "type":"Services"
        }
    ],
    "sg:phone":"+1 626 289 8547",
    "sg:postcode":"91803",
    "sg:province":"CA",
    "sg:tags":[
        "general",
        "contractor"
    ],
    "wof:name":"HMI Construction",
    "wof:placetype":"venue"
},
  "geometry": {"coordinates":[-118.130394,34.07937],"type":"Point"}
}