{
  "type": "Feature",
  "properties": {
    "iso:country":"US",
    "sg:address":"652 S Bridge St",
    "sg:city":"Visalia",
    "sg:classifiers":[
        {
            "category":"Wholesale",
            "subcategory":"Electrical",
            "type":"Manufacturing & Wholesale Goods"
        }
    ],
    "sg:phone":"+1 559 733 7111",
    "sg:postcode":"93277",
    "sg:province":"CA",
    "sg:tags":[
        "equipment"
    ],
    "wof:name":"Code 3 Installers",
    "wof:placetype":"venue"
},
  "geometry": {"coordinates":[-119.288785,36.323185],"type":"Point"}
}