{
  "type": "Feature",
  "properties": {
    "iso:country":"US",
    "sg:address":"6501 San Fernando Rd",
    "sg:city":"Glendale",
    "sg:classifiers":[
        {
            "category":"Home & Garden",
            "subcategory":"Home Furnishings",
            "type":"Retail Goods"
        }
    ],
    "sg:phone":"+1 818 551 1545",
    "sg:postcode":"91201",
    "sg:province":"CA",
    "sg:tags":[
        "decor"
    ],
    "wof:name":"Sandy's Rugs And Accessories",
    "wof:placetype":"venue"
},
  "geometry": {"coordinates":[-118.290307,34.167269],"type":"Point"}
}