{
  "type": "Feature",
  "properties": {
    "iso:country":"US",
    "sg:address":"100 W El Camino Real",
    "sg:city":"Mountain View",
    "sg:classifiers":[
        {
            "category":"Personal",
            "subcategory":"Beauty Salon",
            "type":"Services"
        },
        {
            "category":"Personal",
            "subcategory":"Nail Salon",
            "type":"Services"
        }
    ],
    "sg:phone":"+1 650 964 8100",
    "sg:postcode":"94040",
    "sg:province":"CA",
    "sg:tags":[
        "hair"
    ],
    "wof:name":"Absolute Perfection",
    "wof:placetype":"venue"
},
  "geometry": {"coordinates":[-122.07711500000001,37.382792],"type":"Point"}
}