{
  "type": "Feature",
  "properties": {
    "addr:full":"One Lagoon Drive Suite 100 Redwood Shores CA 94065",
    "addr:postcode":"94065",
    "addr:street":"Lagoon Drive Suite 100",
    "iso:country":"US",
    "sg:address":"One Lagoon Drive Suite 100",
    "sg:city":"Redwood Shores",
    "sg:classifiers":[
        {
            "category":"Professional",
            "subcategory":"Lawyer & Legal Services",
            "type":"Services"
        }
    ],
    "sg:phone":"+1 650 489 0850",
    "sg:postcode":"94065",
    "sg:province":"CA",
    "sg:tags":[
        "startups",
        "attorneys",
        "financings"
    ],
    "sg:website":"http://www.fortisgc.com",
    "wof:name":"Fortis General Counsel",
    "wof:placetype":"venue"
},
  "geometry": {"coordinates":[-122.261894,37.527702],"type":"Point"}
}