{
  "type": "Feature",
  "properties": {
    "addr:full":"11061 Stratford Way Garden Grove CA 92840",
    "addr:housenumber":"11061",
    "addr:postcode":"92840",
    "addr:street":"Stratford Way",
    "iso:country":"US",
    "sg:address":"11061 Stratford Way",
    "sg:city":"Garden Grove",
    "sg:classifiers":[
        {
            "category":"Building & Trades",
            "subcategory":"Construction",
            "type":"Services"
        }
    ],
    "sg:phone":"+1 714 914 8813",
    "sg:postcode":"92840",
    "sg:province":"CA",
    "wof:name":"Central Pacfic Design Build",
    "wof:placetype":"venue"
},
  "geometry": {"coordinates":[-117.954449,33.801889],"type":"Point"}
}