{
  "type": "Feature",
  "properties": {
    "iso:country":"US",
    "sg:address":"275 Battery St",
    "sg:city":"San Francisco",
    "sg:classifiers":[
        {
            "category":"Professional",
            "subcategory":"Lawyer & Legal Services",
            "type":"Services"
        }
    ],
    "sg:phone":"+1 415 956 1000",
    "sg:postcode":"94111",
    "sg:province":"CA",
    "wof:name":"Desai Nimish",
    "wof:placetype":"venue"
},
  "geometry": {"coordinates":[-122.400272,37.793936],"type":"Point"}
}