{
  "type": "Feature",
  "properties": {
    "addr:full":"4633 Vermont Pl Los Angeles CA 90029",
    "addr:housenumber":"4633",
    "addr:postcode":"90029",
    "addr:street":"Vermont Pl",
    "iso:country":"US",
    "sg:address":"4633 Vermont Pl",
    "sg:city":"Los Angeles",
    "sg:classifiers":[
        {
            "category":"Real Estate",
            "subcategory":"Real Estate Operator",
            "type":"Services"
        }
    ],
    "sg:phone":"+1 323 664 0545",
    "sg:postcode":"90029",
    "sg:province":"CA",
    "sg:tags":[
        "apartment"
    ],
    "wof:name":"Vermont Place Apartments",
    "wof:placetype":"venue"
},
  "geometry": {"coordinates":[-118.29132199999999,34.092353],"type":"Point"}
}