{
  "type": "Feature",
  "properties": {
    "iso:country":"US",
    "sg:address":"92 Eton Ct",
    "sg:city":"Santa Rosa",
    "sg:classifiers":[
        {
            "category":"Retail",
            "subcategory":"Laundry & Dry Cleaning",
            "type":"Services"
        }
    ],
    "sg:phone":"+1 707 542 7249",
    "sg:postcode":"95403",
    "sg:province":"CA",
    "sg:tags":[
        "cleaners",
        "rug",
        "carpet"
    ],
    "wof:name":"Phd Carpet Cleaning",
    "wof:placetype":"venue"
},
  "geometry": {"coordinates":[-122.75581699999999,38.500914],"type":"Point"}
}