{
  "type": "Feature",
  "properties": {
    "iso:country":"US",
    "sg:address":"42250 Baldaray Cir",
    "sg:city":"Temecula",
    "sg:classifiers":[
        {
            "category":"Manufacturing",
            "subcategory":"Retail Goods",
            "type":"Manufacturing & Wholesale Goods"
        }
    ],
    "sg:phone":"+1 951 506 3643",
    "sg:postcode":"92590",
    "sg:province":"CA",
    "sg:tags":[
        "product",
        "mfg"
    ],
    "wof:name":"Panic Mouse Inc",
    "wof:placetype":"venue"
},
  "geometry": {"coordinates":[-117.154218,33.49512],"type":"Point"}
}