{
  "type": "Feature",
  "properties": {
    "addr:full":"454 W Elm Ave Burbank CA 91506",
    "addr:housenumber":"454",
    "addr:postcode":"91506",
    "addr:street":"W Elm Ave",
    "iso:country":"US",
    "sg:address":"454 W Elm Ave",
    "sg:city":"Burbank",
    "sg:classifiers":[
        {
            "category":"Professional",
            "type":"Services"
        }
    ],
    "sg:phone":"+1 818 842 3653",
    "sg:postcode":"91506",
    "sg:province":"CA",
    "wof:name":"Mary Moffitt",
    "wof:placetype":"venue"
},
  "geometry": {"coordinates":[-118.309076,34.162732],"type":"Point"}
}