{
  "type": "Feature",
  "properties": {
    "addr:full":"7950 Dublin Blvd Ste 103A Dublin CA 94568",
    "addr:housenumber":"7950",
    "addr:postcode":"94568",
    "addr:street":"Dublin Blvd Ste 103A",
    "iso:country":"US",
    "sg:address":"7950 Dublin Blvd Ste 103A",
    "sg:city":"Dublin",
    "sg:classifiers":[
        {
            "category":"Insurance",
            "subcategory":"Hazard Insurance",
            "type":"Services"
        }
    ],
    "sg:phone":"+1 925 404 2000",
    "sg:postcode":"94568",
    "sg:province":"CA",
    "sg:website":"http://statefarm.mqgroup.com/url.asp?usr=056118",
    "wof:name":"State Farm Insurance Agent-Leslie Wolf",
    "wof:placetype":"venue"
},
  "geometry": {"coordinates":[-121.93529100000001,37.702307],"type":"Point"}
}