{
  "type": "Feature",
  "properties": {
    "iso:country":"US",
    "sg:address":"9721 Little Santa Monica Blvd",
    "sg:city":"Beverly Hills",
    "sg:classifiers":[
        {
            "category":"Personal",
            "subcategory":"Skin Care",
            "type":"Services"
        },
        {
            "category":"Personal",
            "subcategory":"Nail Salon",
            "type":"Services"
        }
    ],
    "sg:phone":"+1 310 271 7500",
    "sg:postcode":"90210",
    "sg:province":"CA",
    "sg:website":"www.pieleskinboutique.com",
    "wof:name":"Piele Skin Boutique",
    "wof:placetype":"venue"
},
  "geometry": {"coordinates":[-118.407798,34.068265],"type":"Point"}
}