{
  "type": "Feature",
  "properties": {
    "iso:country":"US",
    "sg:address":"4255 18th St",
    "sg:city":"San Francisco",
    "sg:classifiers":[
        {
            "category":"Health Services",
            "subcategory":"Health Practitioner",
            "type":"Services"
        }
    ],
    "sg:phone":"+1 415 626 2741",
    "sg:postcode":"94114",
    "sg:province":"CA",
    "sg:tags":[
        "naturopathic/holistic"
    ],
    "wof:name":"Diamondwood Medical Arts",
    "wof:placetype":"venue"
},
  "geometry": {"coordinates":[-122.43669300000001,37.760654],"type":"Point"}
}