{
  "type": "Feature",
  "properties": {
    "iso:country":"US",
    "sg:address":"6383 Yucca St",
    "sg:city":"Los Angeles",
    "sg:classifiers":[
        {
            "category":"Health Services",
            "subcategory":"Nursing And Care Facility",
            "type":"Services"
        }
    ],
    "sg:phone":"+1 323 461 3338",
    "sg:postcode":"90028",
    "sg:province":"CA",
    "sg:tags":[
        "home",
        "retirement",
        "community"
    ],
    "wof:name":"Allview Luxury Living",
    "wof:placetype":"venue"
},
  "geometry": {"coordinates":[-118.32876,34.104054],"type":"Point"}
}