{
  "type": "Feature",
  "properties": {
    "addr:full":"833 Ramona Ave La Verne CA 91750",
    "addr:housenumber":"833",
    "addr:postcode":"91750",
    "addr:street":"Ramona Ave",
    "iso:country":"US",
    "sg:address":"833 Ramona Ave",
    "sg:city":"La Verne",
    "sg:classifiers":[
        {
            "category":"Travel",
            "subcategory":"Travel Agent",
            "type":"Entertainment"
        }
    ],
    "sg:phone":"+1 909 394 0868",
    "sg:postcode":"91750",
    "sg:province":"CA",
    "sg:tags":[
        "agency"
    ],
    "wof:name":"Quest Fore Travel",
    "wof:placetype":"venue"
},
  "geometry": {"coordinates":[-117.789725,34.117077],"type":"Point"}
}