{
  "type": "Feature",
  "properties": {
    "iso:country":"US",
    "sg:address":"601 N Cedros Ave",
    "sg:city":"Solana Beach",
    "sg:classifiers":[
        {
            "category":"Building & Trades",
            "subcategory":"Landscaping Services",
            "type":"Services"
        },
        {
            "category":"Building & Trades",
            "subcategory":"Construction",
            "type":"Services"
        }
    ],
    "sg:phone":"+1 858 205 0990",
    "sg:postcode":"92075",
    "sg:province":"CA",
    "sg:tags":[
        "contractor"
    ],
    "sg:website":"www.atlas-construction.net",
    "wof:name":"Atlas Construction",
    "wof:placetype":"venue"
},
  "geometry": {"coordinates":[-117.27337199999999,32.998908],"type":"Point"}
}