{
  "type": "Feature",
  "properties": {
    "iso:country":"US",
    "sg:address":"3131 Bandini Blvd",
    "sg:city":"Los Angeles",
    "sg:classifiers":[
        {
            "category":"Wholesale",
            "subcategory":"Toys & Hobbies",
            "type":"Manufacturing & Wholesale Goods"
        }
    ],
    "sg:phone":"+1 323 266 3131",
    "sg:postcode":"90023",
    "sg:province":"CA",
    "wof:name":"Ppl Trading Co",
    "wof:placetype":"venue"
},
  "geometry": {"coordinates":[-118.215265,34.008723],"type":"Point"}
}