{
  "type": "Feature",
  "properties": {
    "addr:full":"10050 N Wolfe Road Cupertino CA 95014",
    "addr:housenumber":"10050",
    "addr:postcode":"95014",
    "addr:street":"N Wolfe Road",
    "iso:country":"US",
    "sg:address":"10050 N Wolfe Road",
    "sg:city":"Cupertino",
    "sg:classifiers":[
        {
            "category":"Professional",
            "subcategory":"Accounting & Tax Preparation",
            "type":"Services"
        }
    ],
    "sg:phone":"+1 408 446 5551",
    "sg:postcode":"95014",
    "sg:province":"CA",
    "sg:tags":[
        "accountant"
    ],
    "sg:website":"www.richardsmithtax.com/",
    "wof:name":"Richard Smith & Associates",
    "wof:placetype":"venue"
},
  "geometry": {"coordinates":[-122.01349500000001,37.323857],"type":"Point"}
}