{
  "type": "Feature",
  "properties": {
    "addr:full":"20855 Golden Springs Dr Diamond Bar CA 91765",
    "addr:housenumber":"20855",
    "addr:postcode":"91765",
    "addr:street":"Golden Springs Dr",
    "iso:country":"US",
    "sg:address":"20855 Golden Springs Dr",
    "sg:city":"Diamond Bar",
    "sg:classifiers":[
        {
            "category":"Banks & Credit Unions",
            "subcategory":"Bank",
            "type":"Services"
        }
    ],
    "sg:phone":"+1 909 444 0062",
    "sg:postcode":"91765",
    "sg:province":"CA",
    "sg:tags":[
        "loan",
        "real estate"
    ],
    "wof:name":"Rumar Mortgage Inc",
    "wof:placetype":"venue"
},
  "geometry": {"coordinates":[-117.84957799999999,33.998874],"type":"Point"}
}