{
  "type": "Feature",
  "properties": {
    "addr:full":"2820 S Vermont Ave Los Angeles CA 90007",
    "addr:housenumber":"2820",
    "addr:postcode":"90007",
    "addr:street":"S Vermont Ave",
    "iso:country":"US",
    "sg:address":"2820 S Vermont Ave",
    "sg:city":"Los Angeles",
    "sg:classifiers":[
        {
            "category":"Building & Trades",
            "subcategory":"Construction",
            "type":"Services"
        }
    ],
    "sg:phone":"+1 323 730 1779",
    "sg:postcode":"90007",
    "sg:province":"CA",
    "sg:tags":[
        "repairing",
        "remodeling",
        "contractor"
    ],
    "wof:name":"21st Century Home Remodeling",
    "wof:placetype":"venue"
},
  "geometry": {"coordinates":[-118.291464,34.029539],"type":"Point"}
}