{
  "type": "Feature",
  "properties": {
    "iso:country":"US",
    "sg:address":"762 S Main St",
    "sg:city":"Pixley",
    "sg:classifiers":[
        {
            "category":"Personal",
            "subcategory":"Beauty Salon",
            "type":"Services"
        }
    ],
    "sg:phone":"+1 559 757 3509",
    "sg:postcode":"93256",
    "sg:province":"CA",
    "wof:name":"Shalom 316",
    "wof:placetype":"venue"
},
  "geometry": {"coordinates":[-119.292857,35.966587],"type":"Point"}
}