{
  "type": "Feature",
  "properties": {
    "iso:country":"US",
    "sg:address":"1607 E Slauson Ave",
    "sg:city":"Los Angeles",
    "sg:classifiers":[
        {
            "category":"Building & Trades",
            "subcategory":"Construction",
            "type":"Services"
        }
    ],
    "sg:phone":"+1 323 583 9088",
    "sg:postcode":"90011",
    "sg:province":"CA",
    "sg:tags":[
        "contractor"
    ],
    "wof:name":"Ben Reininger Co",
    "wof:placetype":"venue"
},
  "geometry": {"coordinates":[-118.24653,33.989314],"type":"Point"}
}