{
  "type": "Feature",
  "properties": {
    "addr:full":"4605 Brooks St Montclair CA 91763",
    "addr:housenumber":"4605",
    "addr:postcode":"91763",
    "addr:street":"Brooks St",
    "iso:country":"US",
    "sg:address":"4605 Brooks St",
    "sg:city":"Montclair",
    "sg:classifiers":[
        {
            "category":"Retail",
            "subcategory":"Auto Repair",
            "type":"Services"
        }
    ],
    "sg:phone":"+1 909 625 5966",
    "sg:postcode":"91763",
    "sg:province":"CA",
    "sg:tags":[
        "body",
        "automobile",
        "painting"
    ],
    "wof:name":"Arturos Body Shop",
    "wof:placetype":"venue"
},
  "geometry": {"coordinates":[-117.70046000000001,34.06158],"type":"Point"}
}