{
  "type": "Feature",
  "properties": {
    "addr:full":"3490 Depot Rd Hayward CA 94545",
    "addr:housenumber":"3490",
    "addr:postcode":"94545",
    "addr:street":"Depot Rd",
    "iso:country":"US",
    "sg:address":"3490 Depot Rd",
    "sg:city":"Hayward",
    "sg:classifiers":[
        {
            "category":"Freight",
            "type":"Transportation"
        }
    ],
    "sg:phone":"+1 510 732 2773",
    "sg:postcode":"94545",
    "sg:province":"CA",
    "sg:tags":[
        "delivery"
    ],
    "wof:name":"Bobs Delivery",
    "wof:placetype":"venue"
},
  "geometry": {"coordinates":[-122.125078,37.638318],"type":"Point"}
}