{
  "type": "Feature",
  "properties": {
    "iso:country":"US",
    "sg:address":"525 Argonaut St",
    "sg:city":"Stockton",
    "sg:classifiers":[
        {
            "category":"Real Estate",
            "subcategory":"Real Estate Agent",
            "type":"Services"
        }
    ],
    "sg:phone":"+1 209 644 2000",
    "sg:postcode":"95203",
    "sg:province":"CA",
    "wof:name":"Property Maintenance Experts",
    "wof:placetype":"venue"
},
  "geometry": {"coordinates":[-121.308366,37.955569],"type":"Point"}
}