{
  "type": "Feature",
  "properties": {
    "iso:country":"US",
    "sg:address":"43430 State Hwy 74",
    "sg:city":"Hemet",
    "sg:classifiers":[
        {
            "category":"Professional",
            "subcategory":"Business Services",
            "type":"Services"
        }
    ],
    "sg:phone":"+1 951 927 5570",
    "sg:postcode":"92544",
    "sg:province":"CA",
    "sg:tags":[
        "box",
        "mail"
    ],
    "wof:name":"Mt Plaza Mail Pac & Ship",
    "wof:placetype":"venue"
},
  "geometry": {"coordinates":[-116.904034,33.74789],"type":"Point"}
}