{
  "type": "Feature",
  "properties": {
    "iso:country":"US",
    "sg:address":"3501 McHenry Ave",
    "sg:city":"Modesto",
    "sg:classifiers":[
        {
            "category":"Home & Garden",
            "subcategory":"Furniture",
            "type":"Retail Goods"
        }
    ],
    "sg:phone":"+1 209 573 8606",
    "sg:postcode":"95356",
    "sg:province":"CA",
    "wof:name":"California Living Furniture",
    "wof:placetype":"venue"
},
  "geometry": {"coordinates":[-120.994325,37.691161],"type":"Point"}
}