{
  "type": "Feature",
  "properties": {
    "addr:full":"15842 Dell View Rd El Cajon CA 92021",
    "addr:housenumber":"15842",
    "addr:postcode":"92021",
    "addr:street":"Dell View Rd",
    "iso:country":"US",
    "sg:address":"15842 Dell View Rd",
    "sg:city":"El Cajon",
    "sg:classifiers":[
        {
            "category":"Building & Trades",
            "subcategory":"Landscaping Services",
            "type":"Services"
        }
    ],
    "sg:phone":"+1 619 561 3858",
    "sg:postcode":"92021",
    "sg:province":"CA",
    "sg:tags":[
        "tree"
    ],
    "wof:name":"Bud's Tree Svc",
    "wof:placetype":"venue"
},
  "geometry": {"coordinates":[-116.833922,32.859495],"type":"Point"}
}