{
  "type": "Feature",
  "properties": {
    "addr:full":"5619 Scotts Valley Dr Scotts Valley CA 95066",
    "addr:housenumber":"5619",
    "addr:postcode":"95066",
    "addr:street":"Scotts Valley Dr",
    "iso:country":"US",
    "sg:address":"5619 Scotts Valley Dr",
    "sg:city":"Scotts Valley",
    "sg:classifiers":[
        {
            "category":"Professional",
            "subcategory":"Employment Agencies",
            "type":"Services"
        }
    ],
    "sg:phone":"+1 831 461 8182",
    "sg:postcode":"95066",
    "sg:province":"CA",
    "sg:tags":[
        "temporary",
        "help"
    ],
    "wof:name":"Volt Services Group",
    "wof:placetype":"venue"
},
  "geometry": {"coordinates":[-122.00643100000001,37.062335],"type":"Point"}
}