{
  "type": "Feature",
  "properties": {
    "acgov:api":"829.0",
    "acgov:type":"ES",
    "addr:full":"2015 Virginia St Berkeley CA",
    "wof:categories":[
        "education_and_religion:education=school"
    ],
    "wof:name":"Berkeley Arts Magnet at Whittier",
    "wof:placetype":"venue"
},
  "geometry": {"coordinates":[-122.27088527767826,37.8764786424587],"type":"Point"}
}