{
  "type": "Feature",
  "properties": {
    "addr:full":"4631 Teller Avenue Newport Beach CA 92660",
    "addr:housenumber":"4631",
    "addr:postcode":"92660",
    "addr:street":"Teller Avenue",
    "iso:country":"US",
    "sg:address":"4631 Teller Avenue",
    "sg:city":"Newport Beach",
    "sg:classifiers":[
        {
            "category":"Professional",
            "subcategory":"Lawyer & Legal Services",
            "type":"Services"
        }
    ],
    "sg:phone":"+1 949 752 7711",
    "sg:postcode":"92660",
    "sg:province":"CA",
    "sg:tags":[
        "personal",
        "injury"
    ],
    "wof:name":"Wentworth Theodore S Atty",
    "wof:placetype":"venue"
},
  "geometry": {"coordinates":[-117.8579,33.666128],"type":"Point"}
}