{
  "type": "Feature",
  "properties": {
    "addr:full":"5200 Huntington Ave Richmond CA 94804",
    "addr:housenumber":"5200",
    "addr:postcode":"94804",
    "addr:street":"Huntington Ave",
    "iso:country":"US",
    "sg:address":"5200 Huntington Ave",
    "sg:city":"Richmond",
    "sg:classifiers":[
        {
            "category":"Shopping",
            "subcategory":"Used Merchandise",
            "type":"Retail Goods"
        }
    ],
    "sg:phone":"+1 510 525 6592",
    "sg:postcode":"94804",
    "sg:province":"CA",
    "wof:name":"Hedgehog Books",
    "wof:placetype":"venue"
},
  "geometry": {"coordinates":[-122.31581,37.904543],"type":"Point"}
}