{
  "type": "Feature",
  "properties": {
    "addr:full":"5541 Santa Monica Blvd Los Angeles CA 90038",
    "addr:housenumber":"5541",
    "addr:postcode":"90038",
    "addr:street":"Santa Monica Blvd",
    "iso:country":"US",
    "sg:address":"5541 Santa Monica Blvd",
    "sg:city":"Los Angeles",
    "sg:classifiers":[
        {
            "category":"Shopping",
            "subcategory":"Jewelry",
            "type":"Retail Goods"
        }
    ],
    "sg:phone":"+1 323 463 4963",
    "sg:postcode":"90038",
    "sg:province":"CA",
    "wof:name":"7 Day Jewelry",
    "wof:placetype":"venue"
},
  "geometry": {"coordinates":[-118.310997,34.090599],"type":"Point"}
}