{
  "type": "Feature",
  "properties": {
    "addr:full":"6266 W Sunset Blvd Los Angeles CA 90028",
    "addr:housenumber":"6266",
    "addr:postcode":"90028",
    "addr:street":"W Sunset Blvd",
    "iso:country":"US",
    "sg:address":"6266 W Sunset Blvd",
    "sg:city":"Los Angeles",
    "sg:classifiers":[
        {
            "category":"Communications",
            "subcategory":"Film & Video Production",
            "type":"Services"
        },
        {
            "category":"Professional",
            "subcategory":"Management & Consulting",
            "type":"Services"
        }
    ],
    "sg:phone":"+1 323 467 1408",
    "sg:postcode":"90028",
    "sg:province":"CA",
    "sg:tags":[
        "motion",
        "consultant",
        "distribution",
        "business"
    ],
    "wof:name":"B Wooding Media Ltd",
    "wof:placetype":"venue"
},
  "geometry": {"coordinates":[-118.32617399999999,34.097922],"type":"Point"}
}