{
  "type": "Feature",
  "properties": {
    "addr:full":"18460 Cantara St Reseda CA 91335",
    "addr:housenumber":"18460",
    "addr:postcode":"91335",
    "addr:street":"Cantara St",
    "iso:country":"US",
    "sg:address":"18460 Cantara St",
    "sg:city":"Reseda",
    "sg:classifiers":[
        {
            "category":"Social Services",
            "subcategory":"Child Care",
            "type":"Services"
        }
    ],
    "sg:phone":"+1 818 885 5498",
    "sg:postcode":"91335",
    "sg:province":"CA",
    "sg:website":"www.brighthorizons.com",
    "wof:name":"Bright Horizons",
    "wof:placetype":"venue"
},
  "geometry": {"coordinates":[-118.535264,34.219141],"type":"Point"}
}