{
  "type": "Feature",
  "properties": {
    "addr:full":"6137 Pleasants Valley Rd Vacaville CA 95688",
    "addr:housenumber":"6137",
    "addr:postcode":"95688",
    "addr:street":"Pleasants Valley Rd",
    "iso:country":"US",
    "sg:address":"6137 Pleasants Valley Rd",
    "sg:city":"Vacaville",
    "sg:classifiers":[
        {
            "category":"Home & Garden",
            "subcategory":"Garden Supply",
            "type":"Retail Goods"
        }
    ],
    "sg:phone":"+1 707 451 9406",
    "sg:postcode":"95688",
    "sg:province":"CA",
    "sg:tags":[
        "nurseryman"
    ],
    "sg:website":"www.morningsunherbfarm.com",
    "wof:name":"Morningsun Herb Farm",
    "wof:placetype":"venue"
},
  "geometry": {"coordinates":[-122.024683,38.349854],"type":"Point"}
}