{
  "type": "Feature",
  "properties": {
    "addr:full":"442 Littlefield Ave S San Francisco CA 94080",
    "addr:housenumber":"442",
    "addr:postcode":"94080",
    "addr:street":"Littlefield Ave S",
    "iso:country":"US",
    "sg:address":"442 Littlefield Ave",
    "sg:city":"S San Francisco",
    "sg:classifiers":[
        {
            "category":"Freight",
            "type":"Transportation"
        }
    ],
    "sg:phone":"+1 650 589 1788",
    "sg:postcode":"94080",
    "sg:province":"CA",
    "sg:tags":[
        "arrangement"
    ],
    "sg:website":"www.lmfsfo.com",
    "wof:name":"Leader Mutual Freight System",
    "wof:placetype":"venue"
},
  "geometry": {"coordinates":[-122.394368,37.650229],"type":"Point"}
}