{
  "type": "Feature",
  "properties": {
    "addr:full":"Mission Springs Ct San Jose CA 95131",
    "addr:postcode":"95131",
    "addr:street":"Mission Springs Ct",
    "iso:country":"US",
    "sg:address":"Mission Springs Ct",
    "sg:city":"San Jose",
    "sg:classifiers":[
        {
            "category":"Building & Trades",
            "subcategory":"Construction",
            "type":"Services"
        }
    ],
    "sg:postcode":"95131",
    "sg:province":"CA",
    "sg:tags":[
        "contractor"
    ],
    "sg:website":"www.habitatsanjose.org",
    "wof:name":"Habitat for Humanity - Murphy",
    "wof:placetype":"venue"
},
  "geometry": {"coordinates":[-121.88863499999999,37.385379],"type":"Point"}
}