{
  "type": "Feature",
  "properties": {
    "iso:country":"US",
    "sg:address":"125 Kearny St",
    "sg:city":"San Francisco",
    "sg:classifiers":[
        {
            "category":"Shopping",
            "subcategory":"Photographic Equipment",
            "type":"Retail Goods"
        }
    ],
    "sg:phone":"+1 415 362 4708",
    "sg:postcode":"94108",
    "sg:province":"CA",
    "sg:tags":[
        "supply"
    ],
    "wof:name":"Brooks Camera",
    "wof:placetype":"venue"
},
  "geometry": {"coordinates":[-122.40378699999999,37.789118],"type":"Point"}
}