{
  "type": "Feature",
  "properties": {
    "addr:full":"811 Wilshire Blvd Suite 150 Los Angeles CA 90017",
    "addr:housenumber":"811",
    "addr:postcode":"90017",
    "addr:street":"Wilshire Blvd Suite 150",
    "iso:country":"US",
    "sg:address":"811 Wilshire Blvd Suite 150",
    "sg:city":"Los Angeles",
    "sg:classifiers":[
        {
            "category":"Professional",
            "subcategory":"Printing & Photocopies",
            "type":"Services"
        }
    ],
    "sg:phone":"+1 213 624 9626",
    "sg:postcode":"90017",
    "sg:province":"CA",
    "sg:website":"www.abcimaging.com",
    "wof:name":"ABC Imaging",
    "wof:placetype":"venue"
},
  "geometry": {"coordinates":[-118.258107,34.050107],"type":"Point"}
}