{
  "type": "Feature",
  "properties": {
    "addr:full":"1617 McGarry St Los Angeles CA 90021",
    "addr:housenumber":"1617",
    "addr:postcode":"90021",
    "addr:street":"Mcgarry St",
    "iso:country":"US",
    "sg:address":"1617 McGarry St",
    "sg:city":"Los Angeles",
    "sg:classifiers":[
        {
            "category":"Professional",
            "type":"Services"
        }
    ],
    "sg:phone":"+1 213 765 7909",
    "sg:postcode":"90021",
    "sg:province":"CA",
    "sg:tags":[
        "establishment"
    ],
    "wof:name":"World Casual Inc",
    "wof:placetype":"venue"
},
  "geometry": {"coordinates":[-118.240802,34.023003],"type":"Point"}
}