{
  "type": "Feature",
  "properties": {
    "iso:country":"US",
    "sg:address":"Los Angeles Air Force Base 200 N Douglas St Bldg 252",
    "sg:city":"El Segundo",
    "sg:classifiers":[
        {
            "category":"Coffee & Tea",
            "type":"Food & Drink"
        }
    ],
    "sg:phone":"+1 310 414 9404",
    "sg:postcode":"90245",
    "sg:province":"CA",
    "sg:website":"www.starbucks.com",
    "wof:name":"Starbucks",
    "wof:placetype":"venue"
},
  "geometry": {"coordinates":[-118.38318,33.916571],"type":"Point"}
}