{
  "type": "Feature",
  "properties": {
    "iso:country":"US",
    "sg:address":"21022 Primrose Ln",
    "sg:city":"Mission Viejo",
    "sg:classifiers":[
        {
            "category":"Building & Trades",
            "subcategory":"Construction",
            "type":"Services"
        }
    ],
    "sg:phone":"+1 949 770 2864",
    "sg:postcode":"92691",
    "sg:province":"CA",
    "sg:tags":[
        "painter"
    ],
    "wof:name":"Al Lowry Painting",
    "wof:placetype":"venue"
},
  "geometry": {"coordinates":[-117.646058,33.656466],"type":"Point"}
}