{
  "type": "Feature",
  "properties": {
    "addr:full":"2349 McKee Rd San Jose CA 95127",
    "addr:housenumber":"2349",
    "addr:postcode":"95127",
    "addr:street":"Mckee Rd",
    "iso:country":"US",
    "sg:address":"2349 McKee Rd",
    "sg:city":"San Jose",
    "sg:classifiers":[
        {
            "category":"Utilities",
            "subcategory":"Water",
            "type":"Services"
        }
    ],
    "sg:phone":"+1 408 729 1319",
    "sg:postcode":"95127",
    "sg:province":"CA",
    "sg:tags":[
        "product",
        "conservation"
    ],
    "wof:name":"Mc Kee Pure Water",
    "wof:placetype":"venue"
},
  "geometry": {"coordinates":[-121.849813,37.365539],"type":"Point"}
}