{
  "type": "Feature",
  "properties": {
    "addr:full":"7657 Galleon Way Carlsbad CA 92009",
    "addr:housenumber":"7657",
    "addr:postcode":"92009",
    "addr:street":"Galleon Way",
    "iso:country":"US",
    "sg:address":"7657 Galleon Way",
    "sg:city":"Carlsbad",
    "sg:classifiers":[
        {
            "category":"Professional",
            "type":"Services"
        }
    ],
    "sg:phone":"+1 760 436 0762",
    "sg:postcode":"92009",
    "sg:province":"CA",
    "sg:tags":[
        "establishment"
    ],
    "wof:name":"Hal D Sieling & Assoc",
    "wof:placetype":"venue"
},
  "geometry": {"coordinates":[-117.245913,33.083342],"type":"Point"}
}