{
  "type": "Feature",
  "properties": {
    "addr:full":"12439 Chandler Blvd North Hollywood CA 91607",
    "addr:housenumber":"12439",
    "addr:postcode":"91607",
    "addr:street":"Chandler Blvd",
    "iso:country":"US",
    "sg:address":"12439 Chandler Blvd",
    "sg:city":"North Hollywood",
    "sg:classifiers":[
        {
            "category":"Shopping",
            "type":"Retail Goods"
        }
    ],
    "sg:phone":"+1 818 762 3000",
    "sg:postcode":"91607",
    "sg:province":"CA",
    "sg:tags":[
        "trophy",
        "medal",
        "merchandise",
        "award"
    ],
    "wof:name":"G & W Trophies",
    "wof:placetype":"venue"
},
  "geometry": {"coordinates":[-118.404518,34.168723],"type":"Point"}
}