{
  "type": "Feature",
  "properties": {
    "addr:full":"31121 Via Colinas Westlake Village CA 91362",
    "addr:housenumber":"31121",
    "addr:postcode":"91362",
    "addr:street":"Via Colinas",
    "iso:country":"US",
    "sg:address":"31121 Via Colinas",
    "sg:city":"Westlake Village",
    "sg:phone":"+1 818 865 2380",
    "sg:postcode":"91362",
    "sg:province":"CA",
    "sg:tags":[
        "material",
        "fixture",
        "display"
    ],
    "wof:name":"PRI Inc",
    "wof:placetype":"venue"
},
  "geometry": {"coordinates":[-118.802134,34.153169],"type":"Point"}
}