{
  "type": "Feature",
  "properties": {
    "addr:full":"1835 Diesel Dr Sacramento CA 95838",
    "addr:housenumber":"1835",
    "addr:postcode":"95838",
    "addr:street":"Diesel Dr",
    "iso:country":"US",
    "sg:address":"1835 Diesel Dr",
    "sg:city":"Sacramento",
    "sg:classifiers":[
        {
            "category":"Professional",
            "type":"Services"
        }
    ],
    "sg:phone":"+1 916 922 3347",
    "sg:postcode":"95838",
    "sg:province":"CA",
    "sg:tags":[
        "establishment"
    ],
    "wof:name":"Toolan Associates",
    "wof:placetype":"venue"
},
  "geometry": {"coordinates":[-121.42767000000001,38.649134],"type":"Point"}
}