{
  "type": "Feature",
  "properties": {
    "iso:country":"US",
    "sg:address":"10433 Friars Rd Ste B",
    "sg:city":"San Diego",
    "sg:classifiers":[
        {
            "category":"Personal",
            "subcategory":"Skin Care",
            "type":"Services"
        }
    ],
    "sg:phone":"+1 619 280 9727",
    "sg:postcode":"92120",
    "sg:province":"CA",
    "sg:website":"www.healthywraps.com",
    "wof:name":"Rapid Results Bodywraps",
    "wof:placetype":"venue"
},
  "geometry": {"coordinates":[-117.099144,32.790415],"type":"Point"}
}