{
  "type": "Feature",
  "properties": {
    "addr:full":"1300 S Marion St Tulare CA 93274",
    "addr:housenumber":"1300",
    "addr:postcode":"93274",
    "addr:street":"S Marion St",
    "iso:country":"US",
    "sg:address":"1300 S Marion St",
    "sg:city":"Tulare",
    "sg:classifiers":[
        {
            "category":"Communications",
            "type":"Services"
        }
    ],
    "sg:phone":"+1 559 685 1278",
    "sg:postcode":"93274",
    "sg:province":"CA",
    "wof:name":"Skyquest Communications",
    "wof:placetype":"venue"
},
  "geometry": {"coordinates":[-119.32615699999999,36.194881],"type":"Point"}
}