{
  "type": "Feature",
  "properties": {
    "addr:full":"268 Gold Mine Dr San Francisco CA 94131",
    "addr:housenumber":"268",
    "addr:postcode":"94131",
    "addr:street":"Gold Mine Dr",
    "iso:country":"US",
    "sg:address":"268 Gold Mine Dr",
    "sg:city":"San Francisco",
    "sg:classifiers":[
        {
            "category":"Health Services",
            "subcategory":"Doctor",
            "type":"Services"
        }
    ],
    "sg:phone":"+1 415 285 6845",
    "sg:postcode":"94131",
    "sg:province":"CA",
    "sg:tags":[
        "physician",
        "surgeon"
    ],
    "wof:name":"Sam Harold Thal MD",
    "wof:placetype":"venue"
},
  "geometry": {"coordinates":[-122.43908500000001,37.741711],"type":"Point"}
}