{
  "type": "Feature",
  "properties": {
    "iso:country":"US",
    "sg:address":"660 Monterey Pass Rd",
    "sg:city":"Monterey Park",
    "sg:classifiers":[
        {
            "category":"Wholesale",
            "subcategory":"Home Furnishings",
            "type":"Manufacturing & Wholesale Goods"
        }
    ],
    "sg:phone":"+1 626 293 7227",
    "sg:postcode":"91754",
    "sg:province":"CA",
    "wof:name":"Chinawind International",
    "wof:placetype":"venue"
},
  "geometry": {"coordinates":[-118.145392,34.057233],"type":"Point"}
}