{
  "type": "Feature",
  "properties": {
    "addr:full":"3960 Whittier Blvd Los Angeles CA 90023",
    "addr:housenumber":"3960",
    "addr:postcode":"90023",
    "addr:street":"Whittier Blvd",
    "iso:country":"US",
    "sg:address":"3960 Whittier Blvd",
    "sg:city":"Los Angeles",
    "sg:classifiers":[
        {
            "category":"Restaurant",
            "type":"Food & Drink"
        }
    ],
    "sg:postcode":"90023",
    "sg:province":"CA",
    "sg:tags":[
        "mexican"
    ],
    "wof:name":"Restaurante El Zarape",
    "wof:placetype":"venue"
},
  "geometry": {"coordinates":[-118.18701,34.023934],"type":"Point"}
}