{
  "type": "Feature",
  "properties": {
    "addr:full":"128 South Acacia Solana Beach CA 92075",
    "addr:housenumber":"128",
    "addr:postcode":"92075",
    "addr:street":"South Acacia",
    "iso:country":"US",
    "sg:address":"128 South Acacia",
    "sg:city":"Solana Beach",
    "sg:classifiers":[
        {
            "category":"Personal",
            "subcategory":"Beauty Salon",
            "type":"Services"
        }
    ],
    "sg:phone":"+1 858 793 5300",
    "sg:postcode":"92075",
    "sg:province":"CA",
    "sg:tags":[
        "hair"
    ],
    "sg:website":"salonbythecove.com",
    "wof:name":"Salon by the Cove",
    "wof:placetype":"venue"
},
  "geometry": {"coordinates":[-117.27220199999999,32.990943],"type":"Point"}
}