{
  "type": "Feature",
  "properties": {
    "iso:country":"US",
    "sg:address":"1781 Newport Blvd Ste C",
    "sg:city":"Costa Mesa",
    "sg:classifiers":[
        {
            "category":"Shopping",
            "subcategory":"Clothing, Apparel, & Fashions",
            "type":"Retail Goods"
        },
        {
            "category":"Arts & Performance",
            "subcategory":"Art Gallery",
            "type":"Entertainment"
        }
    ],
    "sg:phone":"+1 949 650 0900",
    "sg:postcode":"92627",
    "sg:province":"CA",
    "sg:tags":[
        "accessory",
        "clothing",
        "women's"
    ],
    "wof:name":"Subject Matter Clothing & Culture",
    "wof:placetype":"venue"
},
  "geometry": {"coordinates":[-117.92148899999999,33.639116],"type":"Point"}
}