{
  "type": "Feature",
  "properties": {
    "iso:country":"US",
    "sg:address":"2424 E Valley Oaks Dr",
    "sg:city":"Visalia",
    "sg:classifiers":[
        {
            "category":"Real Estate",
            "subcategory":"Real Estate Agent",
            "type":"Services"
        }
    ],
    "sg:phone":"+1 559 627 1776",
    "sg:postcode":"93292",
    "sg:province":"CA",
    "wof:name":"Tulare County Assn-Realtors",
    "wof:placetype":"venue"
},
  "geometry": {"coordinates":[-119.264592,36.330377],"type":"Point"}
}