{
  "type": "Feature",
  "properties": {
    "addr:full":"50 Sand Creek Rd, #20 Brentwood CA 94513",
    "addr:housenumber":"50",
    "addr:postcode":"94513",
    "addr:street":"Sand Creek Rd # 20",
    "iso:country":"US",
    "sg:address":"50 Sand Creek Rd, #20",
    "sg:city":"Brentwood",
    "sg:classifiers":[
        {
            "category":"Personal",
            "subcategory":"Nail Salon",
            "type":"Services"
        }
    ],
    "sg:phone":"+1 925 308 7067",
    "sg:postcode":"94513",
    "sg:province":"CA",
    "wof:name":"Top Nails",
    "wof:placetype":"venue"
},
  "geometry": {"coordinates":[-121.697221,37.946048],"type":"Point"}
}