{
  "type": "Feature",
  "properties": {
    "addr:full":"57 Post St Ste 502 San Francisco CA 94104",
    "addr:housenumber":"57",
    "addr:postcode":"94104",
    "addr:street":"Post St Ste 502",
    "iso:country":"US",
    "sg:address":"57 Post St Ste 502",
    "sg:city":"San Francisco",
    "sg:classifiers":[
        {
            "category":"Professional",
            "subcategory":"Lawyer & Legal Services",
            "type":"Services"
        }
    ],
    "sg:phone":"+1 415 951 9900",
    "sg:postcode":"94104",
    "sg:province":"CA",
    "wof:name":"Moody E Craig Lawyer",
    "wof:placetype":"venue"
},
  "geometry": {"coordinates":[-122.402833,37.78886],"type":"Point"}
}