{
  "type": "Feature",
  "properties": {
    "iso:country":"US",
    "sg:address":"811 Traction Ave",
    "sg:city":"Los Angeles",
    "sg:classifiers":[
        {
            "category":"Arts & Performance",
            "subcategory":"Theater",
            "type":"Entertainment"
        }
    ],
    "sg:phone":"+1 213 687 7771",
    "sg:postcode":"90013",
    "sg:province":"CA",
    "sg:tags":[
        "television",
        "program",
        "producer"
    ],
    "sg:website":"www.mun2tv.com",
    "wof:name":"Perfect Image TV Film & Video",
    "wof:placetype":"venue"
},
  "geometry": {"coordinates":[-118.235291,34.045045],"type":"Point"}
}