{
  "type": "Feature",
  "properties": {
    "iso:country":"US",
    "sg:address":"631 13th St",
    "sg:city":"Paso Robles",
    "sg:classifiers":[
        {
            "category":"Restaurant",
            "type":"Food & Drink"
        }
    ],
    "sg:phone":"+1 805 237 9697",
    "sg:postcode":"93446",
    "sg:province":"CA",
    "wof:name":"LA Mexicana",
    "wof:placetype":"venue"
},
  "geometry": {"coordinates":[-120.69235,35.627691],"type":"Point"}
}