{
  "type": "Feature",
  "properties": {
    "addr:full":"3615 Victoria Ave Oxnard CA 93035",
    "addr:housenumber":"3615",
    "addr:postcode":"93035",
    "addr:street":"Victoria Ave",
    "iso:country":"US",
    "sg:address":"3615 Victoria Ave",
    "sg:city":"Oxnard",
    "sg:classifiers":[
        {
            "category":"Farming",
            "subcategory":"Fish & Marine Products",
            "type":"Manufacturing & Wholesale Goods"
        }
    ],
    "sg:phone":"+1 805 984 3422",
    "sg:postcode":"93035",
    "sg:province":"CA",
    "sg:tags":[
        "fishing"
    ],
    "wof:name":"Estina Spt Fishing & Tackle Sp",
    "wof:placetype":"venue"
},
  "geometry": {"coordinates":[-119.221763,34.166523],"type":"Point"}
}