{
  "type": "Feature",
  "properties": {
    "iso:country":"US",
    "sg:address":"2068 Ventura Blvd Ste C",
    "sg:city":"Camarillo",
    "sg:classifiers":[
        {
            "category":"Personal",
            "subcategory":"Beauty Salon",
            "type":"Services"
        }
    ],
    "sg:phone":"+1 805 300 2435",
    "sg:postcode":"93010",
    "sg:province":"CA",
    "sg:tags":[
        "spa"
    ],
    "wof:name":"Posh Hair & Skin Studio",
    "wof:placetype":"venue"
},
  "geometry": {"coordinates":[-119.04266200000001,34.216583],"type":"Point"}
}