{
  "type": "Feature",
  "properties": {
    "iso:country":"US",
    "sg:address":"3700 Sunset Ln",
    "sg:city":"Antioch",
    "sg:classifiers":[
        {
            "category":"Health Services",
            "subcategory":"Doctor",
            "type":"Services"
        }
    ],
    "sg:phone":"+1 925 757 0311",
    "sg:postcode":"94509",
    "sg:province":"CA",
    "sg:tags":[
        "physician",
        "surgeon"
    ],
    "wof:name":"Eric K Poon Inc",
    "wof:placetype":"venue"
},
  "geometry": {"coordinates":[-121.80431400000001,37.984457],"type":"Point"}
}