{
  "type": "Feature",
  "properties": {
    "addr:full":"4203 Genesee Ave San Diego CA 92117",
    "addr:housenumber":"4203",
    "addr:postcode":"92117",
    "addr:street":"Genesee Ave",
    "iso:country":"US",
    "sg:address":"4203 Genesee Ave",
    "sg:city":"San Diego",
    "sg:classifiers":[
        {
            "category":"Home & Garden",
            "subcategory":"Building Materials",
            "type":"Retail Goods"
        },
        {
            "category":"Manufacturing",
            "subcategory":"Furniture",
            "type":"Manufacturing & Wholesale Goods"
        }
    ],
    "sg:phone":"+1 858 715 1667",
    "sg:postcode":"92117",
    "sg:province":"CA",
    "sg:tags":[
        "shutter",
        "drapery",
        "mfg"
    ],
    "wof:name":"3 Day Blinds 9",
    "wof:placetype":"venue"
},
  "geometry": {"coordinates":[-117.182862,32.821355],"type":"Point"}
}