{
  "type": "Feature",
  "properties": {
    "addr:full":"1201 W 109th Pl Los Angeles CA 90044",
    "addr:housenumber":"1201",
    "addr:postcode":"90044",
    "addr:street":"W 109Th Pl",
    "iso:country":"US",
    "sg:address":"1201 W 109th Pl",
    "sg:city":"Los Angeles",
    "sg:classifiers":[
        {
            "category":"Freight",
            "type":"Transportation"
        }
    ],
    "sg:phone":"+1 323 754 6095",
    "sg:postcode":"90044",
    "sg:province":"CA",
    "sg:tags":[
        "operator",
        "local",
        "trucking"
    ],
    "wof:name":"Super A Trucking",
    "wof:placetype":"venue"
},
  "geometry": {"coordinates":[-118.29666,33.936409],"type":"Point"}
}