{
  "type": "Feature",
  "properties": {
    "addr:full":"1565 The Alameda San Jose CA 95126",
    "addr:housenumber":"1565",
    "addr:postcode":"95126",
    "addr:street":"The Alameda",
    "iso:country":"US",
    "sg:address":"1565 The Alameda",
    "sg:city":"San Jose",
    "sg:classifiers":[
        {
            "category":"Arts & Performance",
            "subcategory":"Art Gallery",
            "type":"Entertainment"
        }
    ],
    "sg:phone":"+1 408 275 1400",
    "sg:postcode":"95126",
    "sg:province":"CA",
    "wof:name":"Holistic Arts Bodywork Center",
    "wof:placetype":"venue"
},
  "geometry": {"coordinates":[-121.916242,37.334782],"type":"Point"}
}