{
  "type": "Feature",
  "properties": {
    "addr:full":"7422 Rock Creek Rd Farmington CA 95230",
    "addr:housenumber":"7422",
    "addr:postcode":"95230",
    "addr:street":"Rock Creek Rd",
    "iso:country":"US",
    "sg:address":"7422 Rock Creek Rd",
    "sg:city":"Farmington",
    "sg:classifiers":[
        {
            "category":"Travel",
            "subcategory":"Hotels & Motels",
            "type":"Entertainment"
        }
    ],
    "sg:phone":"+1 209 785 2974",
    "sg:postcode":"95230",
    "sg:province":"CA",
    "sg:tags":[
        "resort"
    ],
    "sg:website":"www.saltsprings.com",
    "wof:name":"Salt Springs Valley Resort",
    "wof:placetype":"venue"
},
  "geometry": {"coordinates":[-120.74863499999999,38.018392],"type":"Point"}
}