{
  "type": "Feature",
  "properties": {
    "iso:country":"US",
    "sg:address":"444 Castro St",
    "sg:city":"San Francisco",
    "sg:classifiers":[
        {
            "category":"Banks & Credit Unions",
            "subcategory":"Bank",
            "type":"Services"
        }
    ],
    "sg:phone":"+1 415 000 1111",
    "sg:postcode":"94114",
    "sg:province":"CA",
    "wof:name":"Cal Fed-California Federal",
    "wof:placetype":"venue"
},
  "geometry": {"coordinates":[-122.435134,37.761685],"type":"Point"}
}