{
  "type": "Feature",
  "properties": {
    "addr:full":"444 Castro St San Francisco CA 94114",
    "addr:housenumber":"444",
    "addr:postcode":"94114",
    "addr:street":"Castro St",
    "iso:country":"US",
    "sg:address":"444 Castro St",
    "sg:city":"San Francisco",
    "sg:classifiers":[
        {
            "category":"Banks & Credit Unions",
            "subcategory":"Bank",
            "type":"Services"
        }
    ],
    "sg:phone":"+1 415 000 1111",
    "sg:postcode":"94114",
    "sg:province":"CA",
    "wof:name":"Cal Fed-California Federal",
    "wof:placetype":"venue"
},
  "geometry": {"coordinates":[-122.43513400000001,37.761685],"type":"Point"}
}