{
  "type": "Feature",
  "properties": {
    "addr:full":"120 S Spalding Dr Ste 401 Beverly Hills CA 90212",
    "addr:housenumber":"120",
    "addr:postcode":"90212",
    "addr:street":"S Spalding Dr Ste 401;Hills Ca",
    "iso:country":"US",
    "sg:address":"120 S Spalding Dr Ste 401",
    "sg:city":"Beverly Hills",
    "sg:classifiers":[
        {
            "category":"Health Services",
            "subcategory":"Doctor",
            "type":"Services"
        }
    ],
    "sg:phone":"+1 310 659 2910",
    "sg:postcode":"90212",
    "sg:province":"CA",
    "sg:tags":[
        "orthopedist"
    ],
    "wof:name":"Beverly Hills Orthopedic Surgery Group",
    "wof:placetype":"venue"
},
  "geometry": {"coordinates":[-118.408997,34.066799],"type":"Point"}
}