{
  "type": "Feature",
  "properties": {
    "iso:country":"US",
    "sg:address":"561 Ruby St",
    "sg:city":"Redwood City",
    "sg:classifiers":[
        {
            "category":"Professional",
            "subcategory":"Management & Consulting",
            "type":"Services"
        }
    ],
    "sg:phone":"+1 650 568 1983",
    "sg:postcode":"94062",
    "sg:province":"CA",
    "sg:tags":[
        "consultant",
        "construction"
    ],
    "wof:name":"Ultimate Construction & Paint",
    "wof:placetype":"venue"
},
  "geometry": {"coordinates":[-122.24497700000001,37.472137],"type":"Point"}
}