{
  "type": "Feature",
  "properties": {
    "iso:country":"US",
    "sg:address":"4242 E Mariposa Rd",
    "sg:city":"Stockton",
    "sg:classifiers":[
        {
            "category":"Freight",
            "type":"Transportation"
        }
    ],
    "sg:phone":"+1 209 547 0960",
    "sg:postcode":"95215",
    "sg:province":"CA",
    "sg:tags":[
        "operator",
        "local",
        "trucking"
    ],
    "wof:name":"Joy Transport",
    "wof:placetype":"venue"
},
  "geometry": {"coordinates":[-121.216959,37.928174],"type":"Point"}
}