{
  "type": "Feature",
  "properties": {
    "addr:full":"472 Primero Ct Cotati CA 94931",
    "addr:housenumber":"472",
    "addr:postcode":"94931",
    "addr:street":"Primero Ct",
    "iso:country":"US",
    "sg:address":"472 Primero Ct",
    "sg:city":"Cotati",
    "sg:classifiers":[
        {
            "category":"Freight",
            "type":"Transportation"
        }
    ],
    "sg:phone":"+1 707 584 7339",
    "sg:postcode":"94931",
    "sg:province":"CA",
    "sg:tags":[
        "operator",
        "local",
        "trucking"
    ],
    "wof:name":"One Day Delivery Service",
    "wof:placetype":"venue"
},
  "geometry": {"coordinates":[-122.71574200000001,38.342076],"type":"Point"}
}