{
  "type": "Feature",
  "properties": {
    "iso:country":"US",
    "sg:address":"830 Tulare St",
    "sg:city":"Parlier",
    "sg:classifiers":[
        {
            "category":"Organizations",
            "subcategory":"Religious Organization",
            "type":"Services"
        }
    ],
    "sg:phone":"+1 559 646 2161",
    "sg:postcode":"93648",
    "sg:province":"CA",
    "sg:tags":[
        "church"
    ],
    "wof:name":"Catholic Church",
    "wof:placetype":"venue"
},
  "geometry": {"coordinates":[-119.530655,36.610284],"type":"Point"}
}