{
  "type": "Feature",
  "properties": {
    "addr:full":"2801 K Street Suite 410 Sacramento CA 95816",
    "addr:housenumber":"2801",
    "addr:postcode":"95816",
    "addr:street":"K Street Suite 410",
    "iso:country":"US",
    "sg:address":"2801 K Street Suite 410",
    "sg:city":"Sacramento",
    "sg:classifiers":[
        {
            "category":"Health Services",
            "subcategory":"Doctor",
            "type":"Services"
        },
        {
            "category":"Health Services",
            "subcategory":"Health Practitioner",
            "type":"Services"
        }
    ],
    "sg:phone":"+1 916 733 8277",
    "sg:postcode":"95816",
    "sg:province":"CA",
    "sg:tags":[
        "acupuncture",
        "orthopedist"
    ],
    "wof:name":"Hembd D Michael MD",
    "wof:placetype":"venue"
},
  "geometry": {"coordinates":[-121.46963700000001,38.57278],"type":"Point"}
}