{
  "type": "Feature",
  "properties": {
    "iso:country":"US",
    "sg:address":"205 Ave I",
    "sg:city":"Redondo Beach",
    "sg:classifiers":[
        {
            "category":"Social Services",
            "type":"Services"
        }
    ],
    "sg:phone":"+1 310 379 9412",
    "sg:postcode":"90277",
    "sg:province":"CA",
    "sg:tags":[
        "counselor",
        "marriage",
        "family"
    ],
    "wof:name":"Beach Cities Mediation Svc",
    "wof:placetype":"venue"
},
  "geometry": {"coordinates":[-118.38623800000001,33.819097],"type":"Point"}
}