{
  "type": "Feature",
  "properties": {
    "iso:country":"US",
    "sg:address":"23501 Fresno Coalinga Rd",
    "sg:city":"Five Points",
    "sg:classifiers":[
        {
            "category":"Wholesale",
            "subcategory":"Farm Supplies",
            "type":"Manufacturing & Wholesale Goods"
        }
    ],
    "sg:phone":"+1 559 884 8800",
    "sg:postcode":"93624",
    "sg:province":"CA",
    "sg:tags":[
        "livestock"
    ],
    "wof:name":"Tule River Ranch",
    "wof:placetype":"venue"
},
  "geometry": {"coordinates":[-120.149473,36.391809],"type":"Point"}
}