{
  "type": "Feature",
  "properties": {
    "iso:country":"US",
    "sg:address":"10517 Prospect Ave",
    "sg:city":"Santee",
    "sg:classifiers":[
        {
            "category":"Retail",
            "subcategory":"Auto Repair",
            "type":"Services"
        }
    ],
    "sg:phone":"+1 619 449 1224",
    "sg:postcode":"92071",
    "sg:province":"CA",
    "sg:tags":[
        "repairing",
        "automobile"
    ],
    "wof:name":"D & R Automotive",
    "wof:placetype":"venue"
},
  "geometry": {"coordinates":[-116.970354,32.831087],"type":"Point"}
}