{
  "type": "Feature",
  "properties": {
    "addr:full":"41 Wood St San Francisco CA 94118",
    "addr:housenumber":"41",
    "addr:postcode":"94118",
    "addr:street":"Wood St",
    "iso:country":"US",
    "sg:address":"41 Wood St",
    "sg:city":"San Francisco",
    "sg:classifiers":[
        {
            "category":"Utilities",
            "subcategory":"Telephone",
            "type":"Services"
        }
    ],
    "sg:phone":"+1 415 575 5500",
    "sg:postcode":"94118",
    "sg:province":"CA",
    "sg:tags":[
        "communications"
    ],
    "wof:name":"San Francisco Telephone",
    "wof:placetype":"venue"
},
  "geometry": {"coordinates":[-122.44881100000001,37.783934],"type":"Point"}
}