{
  "type": "Feature",
  "properties": {
    "iso:country":"US",
    "sg:address":"13136 Saticoy Ave Building L",
    "sg:city":"North Hollywood",
    "sg:classifiers":[
        {
            "category":"Shopping",
            "subcategory":"Bicycles & Sporting Goods",
            "type":"Retail Goods"
        }
    ],
    "sg:phone":"+1 818 982 2652",
    "sg:postcode":"91605",
    "sg:province":"CA",
    "sg:tags":[
        "outdoor",
        "gear"
    ],
    "sg:website":"www.k2scuba.com",
    "wof:name":"K2 Beach SCUBA & Snorkel Online",
    "wof:placetype":"venue"
},
  "geometry": {"coordinates":[-118.41954,34.207609],"type":"Point"}
}