{
  "type": "Feature",
  "properties": {
    "iso:country":"US",
    "sg:address":"632 Manuel T Freitas Pkwy",
    "sg:city":"San Rafael",
    "sg:classifiers":[
        {
            "category":"Shopping",
            "subcategory":"Clothing, Apparel, & Fashions",
            "type":"Retail Goods"
        }
    ],
    "sg:phone":"+1 415 472 7151",
    "sg:postcode":"94903",
    "sg:province":"CA",
    "sg:tags":[
        "tailor"
    ],
    "wof:name":"Northgate Tailor Shop & Clrs",
    "wof:placetype":"venue"
},
  "geometry": {"coordinates":[-122.560767,38.012333],"type":"Point"}
}