{
  "type": "Feature",
  "properties": {
    "iso:country":"US",
    "sg:address":"439 Hamilton Ave",
    "sg:city":"Palo Alto",
    "sg:classifiers":[
        {
            "category":"Retail",
            "subcategory":"Laundry & Dry Cleaning",
            "type":"Services"
        }
    ],
    "sg:phone":"+1 650 326 7896",
    "sg:postcode":"94301",
    "sg:province":"CA",
    "sg:tags":[
        "cleaners"
    ],
    "wof:name":"Gate Cleaners",
    "wof:placetype":"venue"
},
  "geometry": {"coordinates":[-122.158406,37.447084],"type":"Point"}
}