{
  "type": "Feature",
  "properties": {
    "iso:country":"US",
    "sg:address":"2073 Pullman Ave",
    "sg:city":"Simi Valley",
    "sg:classifiers":[
        {
            "category":"Professional",
            "type":"Services"
        }
    ],
    "sg:phone":"+1 805 583 0866",
    "sg:postcode":"93063",
    "sg:province":"CA",
    "wof:name":"Greg Foote",
    "wof:placetype":"venue"
},
  "geometry": {"coordinates":[-118.683441,34.273095],"type":"Point"}
}