{
  "type": "Feature",
  "properties": {
    "addr:full":"23945 Calabasas Rd Calabasas CA 91302",
    "addr:housenumber":"23945",
    "addr:postcode":"91302",
    "addr:street":"Calabasas Rd",
    "iso:country":"US",
    "sg:address":"23945 Calabasas Rd",
    "sg:city":"Calabasas",
    "sg:classifiers":[
        {
            "category":"Arts & Performance",
            "subcategory":"Theater",
            "type":"Entertainment"
        }
    ],
    "sg:phone":"+1 818 222 8206",
    "sg:postcode":"91302",
    "sg:province":"CA",
    "sg:tags":[
        "television",
        "program",
        "producer"
    ],
    "sg:website":"www.arief.com",
    "wof:name":"Arief International Inc",
    "wof:placetype":"venue"
},
  "geometry": {"coordinates":[-118.649164,34.153197],"type":"Point"}
}