{
  "type": "Feature",
  "properties": {
    "iso:country":"US",
    "sg:address":"5450 Thornwood Dr",
    "sg:city":"San Jose",
    "sg:classifiers":[
        {
            "category":"Insurance",
            "subcategory":"Insurance Agent",
            "type":"Services"
        }
    ],
    "sg:phone":"+1 408 629 4700",
    "sg:postcode":"95123",
    "sg:province":"CA",
    "wof:name":"State Farm Insurance",
    "wof:placetype":"venue"
},
  "geometry": {"coordinates":[-121.866229,37.254574],"type":"Point"}
}