{
  "type": "Feature",
  "properties": {
    "addr:full":"16033 Bolsa Chica St Huntington Beach CA 92649",
    "addr:housenumber":"16033",
    "addr:postcode":"92649",
    "addr:street":"Bolsa Chica St",
    "iso:country":"US",
    "sg:address":"16033 Bolsa Chica St",
    "sg:city":"Huntington Beach",
    "sg:classifiers":[
        {
            "category":"Shopping",
            "subcategory":"Bicycles & Sporting Goods",
            "type":"Retail Goods"
        }
    ],
    "sg:phone":"+1 714 840 0696",
    "sg:postcode":"92649",
    "sg:province":"CA",
    "wof:name":"Matts Mako Marine",
    "wof:placetype":"venue"
},
  "geometry": {"coordinates":[-118.041775,33.728379],"type":"Point"}
}