{
  "type": "Feature",
  "properties": {
    "iso:country":"US",
    "sg:address":"39511 Rd 20",
    "sg:city":"Kingsburg",
    "sg:classifiers":[
        {
            "category":"Farming",
            "subcategory":"Orchard",
            "type":"Manufacturing & Wholesale Goods"
        }
    ],
    "sg:phone":"+1 559 897 3970",
    "sg:postcode":"93631",
    "sg:province":"CA",
    "sg:tags":[
        "fruit",
        "tree"
    ],
    "wof:name":"Schnitzler Helmut",
    "wof:placetype":"venue"
},
  "geometry": {"coordinates":[-119.529985,36.507363],"type":"Point"}
}