{
  "type": "Feature",
  "properties": {
    "addr:full":"5405 N Blackstone Ave Fresno CA 93710",
    "addr:housenumber":"5405",
    "addr:postcode":"93710",
    "addr:street":"N Blackstone Ave",
    "iso:country":"US",
    "sg:address":"5405 N Blackstone Ave",
    "sg:city":"Fresno",
    "sg:classifiers":[
        {
            "category":"Autos & Motor Vehicles",
            "subcategory":"Fuel & Gas Station",
            "type":"Retail Goods"
        }
    ],
    "sg:phone":"+1 559 439 3306",
    "sg:postcode":"93710",
    "sg:province":"CA",
    "sg:tags":[
        "oil"
    ],
    "wof:name":"Northgate Shell",
    "wof:placetype":"venue"
},
  "geometry": {"coordinates":[-119.79044500000001,36.819048],"type":"Point"}
}