{
  "type": "Feature",
  "properties": {
    "iso:country":"US",
    "sg:address":"561 San Mateo Ave",
    "sg:city":"San Bruno",
    "sg:classifiers":[
        {
            "category":"Organizations",
            "subcategory":"Religious Organization",
            "type":"Services"
        }
    ],
    "sg:phone":"+1 650 866 4450",
    "sg:postcode":"94066",
    "sg:province":"CA",
    "wof:name":"Gospel Operation Intl",
    "wof:placetype":"venue"
},
  "geometry": {"coordinates":[-122.411325,37.625322],"type":"Point"}
}