{
  "type": "Feature",
  "properties": {
    "addr:full":"561 San Mateo Ave San Bruno CA 94066",
    "addr:housenumber":"561",
    "addr:postcode":"94066",
    "addr:street":"San Mateo Ave",
    "iso:country":"US",
    "sg:address":"561 San Mateo Ave",
    "sg:city":"San Bruno",
    "sg:classifiers":[
        {
            "category":"Organizations",
            "subcategory":"Religious Organization",
            "type":"Services"
        }
    ],
    "sg:phone":"+1 650 866 4450",
    "sg:postcode":"94066",
    "sg:province":"CA",
    "wof:name":"Gospel Operation Intl",
    "wof:placetype":"venue"
},
  "geometry": {"coordinates":[-122.41132500000001,37.625322],"type":"Point"}
}