{
  "type": "Feature",
  "properties": {
    "iso:country":"US",
    "sg:address":"5640 District Blvd",
    "sg:city":"Bakersfield",
    "sg:classifiers":[
        {
            "category":"Professional",
            "subcategory":"Business Services",
            "type":"Services"
        }
    ],
    "sg:phone":"+1 661 831 1227",
    "sg:postcode":"93313",
    "sg:province":"CA",
    "sg:tags":[
        "drafting"
    ],
    "wof:name":"Ryker Design",
    "wof:placetype":"venue"
},
  "geometry": {"coordinates":[-119.065252,35.313133],"type":"Point"}
}