{
  "type": "Feature",
  "properties": {
    "addr:full":"5630 District Blvd Bakersfield CA 93313",
    "addr:postcode":"5630;93313",
    "addr:street":"District Blvd",
    "iso:country":"US",
    "sg:address":"5630 District Blvd",
    "sg:city":"Bakersfield",
    "sg:classifiers":[
        {
            "category":"Professional",
            "subcategory":"Management & Consulting",
            "type":"Services"
        }
    ],
    "sg:phone":"+1 661 398 8888",
    "sg:postcode":"93313",
    "sg:province":"CA",
    "sg:tags":[
        "development",
        "industrial"
    ],
    "wof:name":"Stockdale Business Ctr",
    "wof:placetype":"venue"
},
  "geometry": {"coordinates":[-119.065337,35.313134],"type":"Point"}
}