{
  "type": "Feature",
  "properties": {
    "addr:full":"1850 Campbell St Oakland CA 94607",
    "addr:housenumber":"1850",
    "addr:postcode":"94607",
    "addr:street":"Campbell St",
    "iso:country":"US",
    "sg:address":"1850 Campbell St",
    "sg:city":"Oakland",
    "sg:classifiers":[
        {
            "category":"Building & Trades",
            "subcategory":"Construction",
            "type":"Services"
        }
    ],
    "sg:phone":"+1 510 444 4235",
    "sg:postcode":"94607",
    "sg:province":"CA",
    "sg:tags":[
        "maker",
        "cabinet"
    ],
    "wof:name":"Sun Woodworks",
    "wof:placetype":"venue"
},
  "geometry": {"coordinates":[-122.292233,37.815683],"type":"Point"}
}