{
  "type": "Feature",
  "properties": {
    "addr:full":"733 Baker St San Francisco CA 94115",
    "addr:housenumber":"733",
    "addr:postcode":"94115",
    "addr:street":"Baker St",
    "iso:country":"US",
    "sg:address":"733 Baker St",
    "sg:city":"San Francisco",
    "sg:classifiers":[
        {
            "category":"Health Services",
            "subcategory":"Health Practitioner",
            "type":"Services"
        }
    ],
    "sg:phone":"+1 415 775 0124",
    "sg:postcode":"94115",
    "sg:province":"CA",
    "sg:tags":[
        "medicine",
        "alternative"
    ],
    "wof:name":"Alexander Technique",
    "wof:placetype":"venue"
},
  "geometry": {"coordinates":[-122.441892,37.777985],"type":"Point"}
}