{
  "type": "Feature",
  "properties": {
    "iso:country":"US",
    "sg:address":"14460 Riverside St",
    "sg:city":"Hesperia",
    "sg:classifiers":[
        {
            "category":"Organizations",
            "subcategory":"Professional Association",
            "type":"Services"
        }
    ],
    "sg:phone":"+1 760 949 0367",
    "sg:postcode":"92345",
    "sg:province":"CA",
    "wof:name":"Hesperia Green Estates",
    "wof:placetype":"venue"
},
  "geometry": {"coordinates":[-117.347968,34.440389],"type":"Point"}
}