{
  "type": "Feature",
  "properties": {
    "iso:country":"US",
    "sg:address":"13336 Beach Avenue",
    "sg:city":"Marina Del Rey",
    "sg:classifiers":[
        {
            "category":"Real Estate",
            "subcategory":"Architect",
            "type":"Services"
        }
    ],
    "sg:phone":"+1 310 821 1548",
    "sg:postcode":"90292",
    "sg:province":"CA",
    "wof:name":"Lewis Marshall Archts",
    "wof:placetype":"venue"
},
  "geometry": {"coordinates":[-118.442495,33.992312],"type":"Point"}
}