{
  "type": "Feature",
  "properties": {
    "iso:country":"US",
    "sg:address":"2300 Central Ave",
    "sg:city":"Alameda",
    "sg:classifiers":[
        {
            "category":"Deli",
            "type":"Food & Drink"
        },
        {
            "category":"Restaurant",
            "type":"Food & Drink"
        },
        {
            "category":"Coffee & Tea",
            "type":"Food & Drink"
        }
    ],
    "sg:phone":"+1 510 864 0360",
    "sg:postcode":"94501",
    "sg:province":"CA",
    "sg:tags":[
        "delicatessen",
        "espresso"
    ],
    "wof:name":"Cafe Central",
    "wof:placetype":"venue"
},
  "geometry": {"coordinates":[-122.24400300000001,37.764599],"type":"Point"}
}