{
  "type": "Feature",
  "properties": {
    "iso:country":"US",
    "sg:address":"1230 Yuba St",
    "sg:city":"Marysville",
    "sg:classifiers":[
        {
            "category":"Wholesale",
            "subcategory":"Groceries",
            "type":"Manufacturing & Wholesale Goods"
        }
    ],
    "sg:phone":"+1 530 742 3010",
    "sg:postcode":"95901",
    "sg:province":"CA",
    "sg:tags":[
        "tortilla"
    ],
    "wof:name":"Casa Sanchez Tortilla Factory",
    "wof:placetype":"venue"
},
  "geometry": {"coordinates":[-121.584306,39.149429],"type":"Point"}
}