{
  "type": "Feature",
  "properties": {
    "addr:full":"505 S Flower Street Los Angeles CA 90071",
    "addr:housenumber":"505",
    "addr:postcode":"90071",
    "addr:street":"S Flower Street",
    "iso:country":"US",
    "sg:address":"505 S Flower Street",
    "sg:city":"Los Angeles",
    "sg:classifiers":[
        {
            "category":"Insurance",
            "subcategory":"Health Insurance",
            "type":"Services"
        }
    ],
    "sg:phone":"+1 213 489 7732",
    "sg:postcode":"90071",
    "sg:province":"CA",
    "sg:tags":[
        "market"
    ],
    "sg:website":"www.gnc.com",
    "wof:name":"Genl Nutrition Center",
    "wof:placetype":"venue"
},
  "geometry": {"coordinates":[-118.256152,34.05155],"type":"Point"}
}