{
  "type": "Feature",
  "properties": {
    "addr:full":"6918 Atlantic Ave Bell CA 90201",
    "addr:housenumber":"6918",
    "addr:postcode":"90201",
    "addr:street":"Atlantic Ave",
    "iso:country":"US",
    "sg:address":"6918 Atlantic Ave",
    "sg:city":"Bell",
    "sg:classifiers":[
        {
            "category":"Building & Trades",
            "subcategory":"Construction",
            "type":"Services"
        }
    ],
    "sg:phone":"+1 323 560 1720",
    "sg:postcode":"90201",
    "sg:province":"CA",
    "sg:tags":[
        "glazier"
    ],
    "wof:name":"Harris Glass Co",
    "wof:placetype":"venue"
},
  "geometry": {"coordinates":[-118.187623,33.972534],"type":"Point"}
}