{
  "type": "Feature",
  "properties": {
    "addr:full":"617 6th St Coronado CA 92118",
    "addr:housenumber":"617",
    "addr:postcode":"92118",
    "addr:street":"6Th St",
    "iso:country":"US",
    "sg:address":"617 6th St",
    "sg:city":"Coronado",
    "sg:classifiers":[
        {
            "category":"Real Estate",
            "subcategory":"Real Estate Agent",
            "type":"Services"
        }
    ],
    "sg:phone":"+1 619 208 6431",
    "sg:postcode":"92118",
    "sg:province":"CA",
    "wof:name":"Parvenu",
    "wof:placetype":"venue"
},
  "geometry": {"coordinates":[-117.18194200000001,32.693877],"type":"Point"}
}