{
  "type": "Feature",
  "properties": {
    "addr:full":"3326 E Coast Hwy Corona Del Mar CA 92625",
    "addr:housenumber":"3326",
    "addr:postcode":"92625",
    "addr:street":"E Coast Hwy",
    "iso:country":"US",
    "sg:address":"3326 E Coast Hwy",
    "sg:city":"Corona Del Mar",
    "sg:classifiers":[
        {
            "category":"Personal",
            "subcategory":"Barber",
            "type":"Services"
        }
    ],
    "sg:phone":"+1 949 673 8714",
    "sg:postcode":"92625",
    "sg:province":"CA",
    "wof:name":"Samuel Joseph's",
    "wof:placetype":"venue"
},
  "geometry": {"coordinates":[-117.871002,33.596001],"type":"Point"}
}