{
  "type": "Feature",
  "properties": {
    "iso:country":"US",
    "sg:address":"University of California, Irvine 5215 Barranca Parkway",
    "sg:city":"Irvine",
    "sg:classifiers":[
        {
            "category":"Autos & Motor Vehicles",
            "subcategory":"Automobile Sales",
            "type":"Retail Goods"
        }
    ],
    "sg:phone":"+1 949 824 1999",
    "sg:postcode":"92697",
    "sg:province":"CA",
    "sg:tags":[
        "automotive"
    ],
    "sg:website":"www.zevnet.org",
    "wof:name":"ZevNet",
    "wof:placetype":"venue"
},
  "geometry": {"coordinates":[-117.797327,33.676927],"type":"Point"}
}