{
  "type": "Feature",
  "properties": {
    "iso:country":"US",
    "sg:address":"2300 Vichy Springs Rd",
    "sg:city":"Ukiah",
    "sg:classifiers":[
        {
            "category":"Organizations",
            "subcategory":"Community Association",
            "type":"Services"
        }
    ],
    "sg:phone":"+1 707 462 3531",
    "sg:postcode":"95482",
    "sg:province":"CA",
    "sg:tags":[
        "club"
    ],
    "wof:name":"Ukiah Gun Club",
    "wof:placetype":"venue"
},
  "geometry": {"coordinates":[-123.166645,39.162586],"type":"Point"}
}