{
  "type": "Feature",
  "properties": {
    "addr:full":"Market St San Francisco CA 94101",
    "addr:postcode":"94101",
    "addr:street":"Market St",
    "iso:country":"US",
    "sg:address":"Market St",
    "sg:city":"San Francisco",
    "sg:classifiers":[
        {
            "category":"Restaurant",
            "type":"Food & Drink"
        }
    ],
    "sg:postcode":"94101",
    "sg:province":"CA",
    "sg:tags":[
        "flavor",
        "local"
    ],
    "wof:name":"Market Street",
    "wof:placetype":"venue"
},
  "geometry": {"coordinates":[-122.412819,37.780159],"type":"Point"}
}