{
  "type": "Feature",
  "properties": {
    "addr:full":"520 Capitol Mall Ste 380 Sacramento CA 95814",
    "addr:housenumber":"520",
    "addr:postcode":"95814",
    "addr:street":"Capitol Mall Ste 380",
    "iso:country":"US",
    "sg:address":"520 Capitol Mall Ste 380",
    "sg:city":"Sacramento",
    "sg:classifiers":[
        {
            "category":"Professional",
            "subcategory":"Accounting & Tax Preparation",
            "type":"Services"
        }
    ],
    "sg:phone":"+1 916 446 8910",
    "sg:postcode":"95814",
    "sg:province":"CA",
    "sg:tags":[
        "accountant"
    ],
    "sg:website":"www.whitakercpa.com",
    "wof:name":"Whitaker & Associates, Inc.",
    "wof:placetype":"venue"
},
  "geometry": {"coordinates":[-121.50080699999999,38.578148],"type":"Point"}
}