{
  "type": "Feature",
  "properties": {
    "iso:country":"US",
    "sg:address":"900 Grayson St",
    "sg:city":"Berkeley",
    "sg:classifiers":[
        {
            "category":"Fast Food",
            "type":"Food & Drink"
        },
        {
            "category":"Restaurant",
            "type":"Food & Drink"
        }
    ],
    "sg:phone":"+1 510 704 9900",
    "sg:postcode":"94701",
    "sg:province":"CA",
    "sg:tags":[
        "burger",
        "american",
        "brunch",
        "breakfast",
        "new"
    ],
    "sg:website":"www.900grayson.com",
    "wof:name":"900 Grayson",
    "wof:placetype":"venue"
},
  "geometry": {"coordinates":[-122.292328,37.855285],"type":"Point"}
}