{
  "type": "Feature",
  "properties": {
    "addr:full":"1020 Timothy Dr San Jose CA 95133",
    "addr:housenumber":"1020",
    "addr:postcode":"95133",
    "addr:street":"Timothy Dr",
    "iso:country":"US",
    "sg:address":"1020 Timothy Dr",
    "sg:city":"San Jose",
    "sg:classifiers":[
        {
            "category":"Autos & Motor Vehicles",
            "subcategory":"Motorcycle Sales",
            "type":"Retail Goods"
        }
    ],
    "sg:phone":"+1 408 295 7437",
    "sg:postcode":"95133",
    "sg:province":"CA",
    "wof:name":"Foster Mike",
    "wof:placetype":"venue"
},
  "geometry": {"coordinates":[-121.879346,37.363688],"type":"Point"}
}