{
  "type": "Feature",
  "properties": {
    "addr:full":"1515 W 178th St Gardena CA 90248",
    "addr:housenumber":"1515",
    "addr:postcode":"90248",
    "addr:street":"W 178Th St",
    "iso:country":"US",
    "sg:address":"1515 W 178th St",
    "sg:city":"Gardena",
    "sg:classifiers":[
        {
            "category":"Freight",
            "type":"Transportation"
        }
    ],
    "sg:phone":"+1 310 538 0468",
    "sg:postcode":"90248",
    "sg:province":"CA",
    "sg:tags":[
        "arrangement"
    ],
    "wof:name":"Great Luck Inc",
    "wof:placetype":"venue"
},
  "geometry": {"coordinates":[-118.304509,33.869293],"type":"Point"}
}