{
  "type": "Feature",
  "properties": {
    "iso:country":"US",
    "sg:address":"30 N Main St",
    "sg:city":"San Andreas",
    "sg:classifiers":[
        {
            "category":"Museum",
            "type":"Entertainment"
        }
    ],
    "sg:phone":"+1 209 754 1058",
    "sg:postcode":"95249",
    "sg:province":"CA",
    "wof:name":"Calaveras County Historical",
    "wof:placetype":"venue"
},
  "geometry": {"coordinates":[-120.680784,38.196789],"type":"Point"}
}