{
  "type": "Feature",
  "properties": {
    "addr:full":"534 N Coast Hwy 101 Encinitas CA 92024",
    "addr:housenumber":"534",
    "addr:postcode":"92024",
    "addr:street":"N Coast Hwy 101",
    "iso:country":"US",
    "sg:address":"534 N Coast Hwy 101",
    "sg:city":"Encinitas",
    "sg:classifiers":[
        {
            "category":"Restaurant",
            "type":"Food & Drink"
        }
    ],
    "sg:phone":"+1 760 634 6753",
    "sg:postcode":"92024",
    "sg:province":"CA",
    "sg:tags":[
        "pizza",
        "italian"
    ],
    "sg:website":"www.vigiluccis.com",
    "wof:name":"Vigilucci's Ristorante & Pizzeria",
    "wof:placetype":"venue"
},
  "geometry": {"coordinates":[-117.299869,33.058836],"type":"Point"}
}