{
  "type": "Feature",
  "properties": {
    "iso:country":"US",
    "sg:address":"2330 Westwood Blvd Ste 200",
    "sg:city":"Los Angeles",
    "sg:classifiers":[
        {
            "category":"Travel",
            "subcategory":"Travel Agent",
            "type":"Entertainment"
        }
    ],
    "sg:phone":"+1 310 481 2280",
    "sg:postcode":"90064",
    "sg:province":"CA",
    "sg:website":"www.888myTravel.com",
    "wof:name":"888mytravel.com",
    "wof:placetype":"venue"
},
  "geometry": {"coordinates":[-118.429949,34.041814],"type":"Point"}
}