{
  "type": "Feature",
  "properties": {
    "addr:full":"651 Kearny St San Francisco CA 94108",
    "addr:housenumber":"651",
    "addr:postcode":"94108",
    "addr:street":"Kearny St",
    "iso:country":"US",
    "sg:address":"651 Kearny St",
    "sg:city":"San Francisco",
    "sg:classifiers":[
        {
            "category":"Wholesale",
            "subcategory":"Electrical",
            "type":"Manufacturing & Wholesale Goods"
        }
    ],
    "sg:phone":"+1 415 831 2238",
    "sg:postcode":"94108",
    "sg:province":"CA",
    "sg:tags":[
        "electronic"
    ],
    "wof:name":"D Lee Trading",
    "wof:placetype":"venue"
},
  "geometry": {"coordinates":[-122.40485,37.794314],"type":"Point"}
}