{
  "type": "Feature",
  "properties": {
    "iso:country":"US",
    "sg:address":"926 W Evelyn Ave",
    "sg:city":"Sunnyvale",
    "sg:classifiers":[
        {
            "category":"Manufacturing",
            "subcategory":"Tools & Machinery",
            "type":"Manufacturing & Wholesale Goods"
        }
    ],
    "sg:phone":"+1 408 245 9555",
    "sg:postcode":"94086",
    "sg:province":"CA",
    "sg:tags":[
        "machine",
        "shop"
    ],
    "sg:website":"www.samaxinc.com",
    "wof:name":"Samax Precision Inc",
    "wof:placetype":"venue"
},
  "geometry": {"coordinates":[-122.043787,37.382645],"type":"Point"}
}