{
  "type": "Feature",
  "properties": {
    "addr:full":"1111 E Tahquitz Canyon Way Ste 121 Palm Springs CA 92262",
    "addr:housenumber":"1111",
    "addr:postcode":"92262",
    "addr:street":"E Tahquitz Canyon Way Ste 121",
    "iso:country":"US",
    "sg:address":"1111 E Tahquitz Canyon Way Ste 121",
    "sg:city":"Palm Springs",
    "sg:classifiers":[
        {
            "category":"Professional",
            "subcategory":"Lawyer & Legal Services",
            "type":"Services"
        }
    ],
    "sg:phone":"+1 760 318 5700",
    "sg:postcode":"92262",
    "sg:province":"CA",
    "sg:tags":[
        "divorce",
        "law",
        "family"
    ],
    "wof:name":"Gary Whitehead & Associates LLC Professional Legal Services Of S",
    "wof:placetype":"venue"
},
  "geometry": {"coordinates":[-116.53243999999999,33.822942],"type":"Point"}
}