{
  "type": "Feature",
  "properties": {
    "addr:full":"1120 Pope St St Helena CA 94574",
    "addr:housenumber":"1120",
    "addr:postcode":"94574",
    "addr:street":"Pope St",
    "iso:country":"US",
    "sg:address":"1120 Pope St",
    "sg:city":"St Helena",
    "sg:classifiers":[
        {
            "category":"Professional",
            "type":"Services"
        }
    ],
    "sg:phone":"+1 707 963 6141",
    "sg:postcode":"94574",
    "sg:province":"CA",
    "sg:tags":[
        "establishment"
    ],
    "wof:name":"Susan Branum Studio",
    "wof:placetype":"venue"
},
  "geometry": {"coordinates":[-122.466453,38.503728],"type":"Point"}
}