{
  "type": "Feature",
  "properties": {
    "iso:country":"US",
    "sg:address":"2103 Chico Ave",
    "sg:city":"South El Monte",
    "sg:classifiers":[
        {
            "category":"Manufacturing",
            "subcategory":"Furniture",
            "type":"Manufacturing & Wholesale Goods"
        }
    ],
    "sg:phone":"+1 626 442 5001",
    "sg:postcode":"91733",
    "sg:province":"CA",
    "wof:name":"Williamson Couch Co",
    "wof:placetype":"venue"
},
  "geometry": {"coordinates":[-118.060064,34.053962],"type":"Point"}
}