{
  "type": "Feature",
  "properties": {
    "addr:full":"2960 N Sunnyside Ave Fresno CA 93727",
    "addr:housenumber":"2960",
    "addr:postcode":"93727",
    "addr:street":"N Sunnyside Ave",
    "iso:country":"US",
    "sg:address":"2960 N Sunnyside Ave",
    "sg:city":"Fresno",
    "sg:classifiers":[
        {
            "category":"Autos & Motor Vehicles",
            "subcategory":"Auto Supplies",
            "type":"Retail Goods"
        }
    ],
    "sg:phone":"+1 559 292 7467",
    "sg:postcode":"93727",
    "sg:province":"CA",
    "sg:tags":[
        "wheel",
        "cover"
    ],
    "sg:website":"www.mazco.com",
    "wof:name":"Mazzeos Custom Wheels Ctr",
    "wof:placetype":"venue"
},
  "geometry": {"coordinates":[-119.69161200000001,36.777327],"type":"Point"}
}