{
  "type": "Feature",
  "properties": {
    "addr:full":"10888 Foothill Blvd Rancho Cucamonga CA 91730",
    "addr:housenumber":"10888",
    "addr:postcode":"91730",
    "addr:street":"Foothill Blvd",
    "iso:country":"US",
    "sg:address":"10888 Foothill Blvd",
    "sg:city":"Rancho Cucamonga",
    "sg:classifiers":[
        {
            "category":"Home & Garden",
            "subcategory":"Furniture",
            "type":"Retail Goods"
        }
    ],
    "sg:phone":"+1 909 481 9338",
    "sg:postcode":"91730",
    "sg:province":"CA",
    "sg:tags":[
        "mattress"
    ],
    "wof:name":"Banner Mattress Inc",
    "wof:placetype":"venue"
},
  "geometry": {"coordinates":[-117.570944,34.106574],"type":"Point"}
}