{
  "type": "Feature",
  "properties": {
    "iso:country":"US",
    "sg:address":"3288 Bell Rd",
    "sg:city":"Auburn",
    "sg:classifiers":[
        {
            "category":"Health Services",
            "subcategory":"Doctor",
            "type":"Services"
        }
    ],
    "sg:phone":"+1 530 886 2300",
    "sg:postcode":"95603",
    "sg:province":"CA",
    "sg:tags":[
        "medicine",
        "physician",
        "practice",
        "surgeons",
        "family"
    ],
    "wof:name":"Southern Medical Foudation",
    "wof:placetype":"venue"
},
  "geometry": {"coordinates":[-121.105137,38.941892],"type":"Point"}
}