{
  "type": "Feature",
  "properties": {
    "addr:full":"940 Palisade Dr Martinez CA 94553",
    "addr:housenumber":"940",
    "addr:postcode":"94553",
    "addr:street":"Palisade Dr",
    "iso:country":"US",
    "sg:address":"940 Palisade Dr",
    "sg:city":"Martinez",
    "sg:classifiers":[
        {
            "category":"Organizations",
            "subcategory":"Religious Organization",
            "type":"Services"
        }
    ],
    "sg:phone":"+1 925 372 4749",
    "sg:postcode":"94553",
    "sg:province":"CA",
    "sg:tags":[
        "church"
    ],
    "wof:name":"Church Of Jesus Christ Of Lds",
    "wof:placetype":"venue"
},
  "geometry": {"coordinates":[-122.103685,37.998956],"type":"Point"}
}