{
  "type": "Feature",
  "properties": {
    "iso:country":"US",
    "sg:address":"3345 Lochinvar Avenue",
    "sg:city":"Santa Clara",
    "sg:classifiers":[
        {
            "category":"Education",
            "subcategory":"Preschool",
            "type":"Public Place"
        },
        {
            "category":"Education",
            "subcategory":"School",
            "type":"Public Place"
        }
    ],
    "sg:phone":"+1 408 615 9416",
    "sg:postcode":"95051",
    "sg:province":"CA",
    "sg:tags":[
        "elementary"
    ],
    "wof:name":"Monticello School",
    "wof:placetype":"venue"
},
  "geometry": {"coordinates":[-121.98808200000001,37.339218],"type":"Point"}
}