{
  "type": "Feature",
  "properties": {
    "addr:full":"20050 Cajalco Rd Perris CA 92570",
    "addr:housenumber":"20050",
    "addr:postcode":"92570",
    "addr:street":"Cajalco Rd",
    "iso:country":"US",
    "sg:address":"20050 Cajalco Rd",
    "sg:city":"Perris",
    "sg:classifiers":[
        {
            "category":"Wholesale",
            "subcategory":"Home Furnishings",
            "type":"Manufacturing & Wholesale Goods"
        }
    ],
    "sg:phone":"+1 951 943 8473",
    "sg:postcode":"92570",
    "sg:province":"CA",
    "wof:name":"Aurelio C Peralta",
    "wof:placetype":"venue"
},
  "geometry": {"coordinates":[-117.31993300000001,33.83692],"type":"Point"}
}