{
  "type": "Feature",
  "properties": {
    "addr:full":"627 Velasco Ave San Francisco CA 94134",
    "addr:housenumber":"627",
    "addr:postcode":"94134",
    "addr:street":"Velasco Ave",
    "iso:country":"US",
    "sg:address":"627 Velasco Ave",
    "sg:city":"San Francisco",
    "sg:classifiers":[
        {
            "category":"Building & Trades",
            "subcategory":"Landscaping Services",
            "type":"Services"
        }
    ],
    "sg:phone":"+1 415 584 1394",
    "sg:postcode":"94134",
    "sg:province":"CA",
    "wof:name":"Flores Boni Complete Gardening",
    "wof:placetype":"venue"
},
  "geometry": {"coordinates":[-122.41834799999999,37.709575],"type":"Point"}
}