{
  "type": "Feature",
  "properties": {
    "iso:country":"US",
    "sg:address":"2006 Washington St",
    "sg:city":"San Francisco",
    "sg:classifiers":[
        {
            "category":"Building & Trades",
            "subcategory":"Construction",
            "type":"Services"
        }
    ],
    "sg:phone":"+1 415 567 4928",
    "sg:postcode":"94109",
    "sg:province":"CA",
    "sg:tags":[
        "contractor"
    ],
    "wof:name":"Ryan Associates",
    "wof:placetype":"venue"
},
  "geometry": {"coordinates":[-122.427736,37.792512],"type":"Point"}
}