{
  "type": "Feature",
  "properties": {
    "iso:country":"US",
    "sg:address":"11408 Renville St",
    "sg:city":"Lakewood",
    "sg:classifiers":[
        {
            "category":"Building & Trades",
            "subcategory":"Construction",
            "type":"Services"
        }
    ],
    "sg:phone":"+1 562 402 7577",
    "sg:postcode":"90715",
    "sg:province":"CA",
    "sg:tags":[
        "painter"
    ],
    "wof:name":"Jimmy O Rioja Paint Co",
    "wof:placetype":"venue"
},
  "geometry": {"coordinates":[-118.089996,33.8451],"type":"Point"}
}