{
  "type": "Feature",
  "properties": {
    "iso:country":"US",
    "sg:address":"11620 Cll Albara",
    "sg:city":"El Cajon",
    "sg:classifiers":[
        {
            "category":"Education",
            "subcategory":"College",
            "type":"Public Place"
        }
    ],
    "sg:phone":"+1 619 543 8257",
    "sg:postcode":"92019",
    "sg:province":"CA",
    "wof:name":"Regents of The Univ of Cal",
    "wof:placetype":"venue"
},
  "geometry": {"coordinates":[-116.940894,32.758188],"type":"Point"}
}