{
  "type": "Feature",
  "properties": {
    "addr:full":"1150 S Westmoreland Ave Los Angeles CA 90006",
    "addr:housenumber":"1150",
    "addr:postcode":"90006",
    "addr:street":"S Westmoreland Ave",
    "iso:country":"US",
    "sg:address":"1150 S Westmoreland Ave",
    "sg:city":"Los Angeles",
    "sg:classifiers":[
        {
            "category":"Professional",
            "subcategory":"Management & Consulting",
            "type":"Services"
        }
    ],
    "sg:phone":"+1 213 382 5596",
    "sg:postcode":"90006",
    "sg:province":"CA",
    "sg:tags":[
        "fuel"
    ],
    "wof:name":"Marathon Management Svc Inc",
    "wof:placetype":"venue"
},
  "geometry": {"coordinates":[-118.289013,34.049969],"type":"Point"}
}