{
  "type": "Feature",
  "properties": {
    "addr:full":"4010 W Crystal Ln Santa Ana CA 92704",
    "addr:housenumber":"4010",
    "addr:postcode":"92704",
    "addr:street":"W Crystal Ln",
    "iso:country":"US",
    "sg:address":"4010 W Crystal Ln",
    "sg:city":"Santa Ana",
    "sg:classifiers":[
        {
            "category":"Real Estate",
            "subcategory":"Real Estate Agent",
            "type":"Services"
        }
    ],
    "sg:phone":"+1 714 624 2777",
    "sg:postcode":"92704",
    "sg:province":"CA",
    "wof:name":"Merit Appraisal Services",
    "wof:placetype":"venue"
},
  "geometry": {"coordinates":[-117.922685,33.734148],"type":"Point"}
}