{
  "type": "Feature",
  "properties": {
    "addr:full":"17390 Muskrat Ave Adelanto CA 92301",
    "addr:housenumber":"17390",
    "addr:postcode":"92301",
    "addr:street":"Muskrat Ave",
    "iso:country":"US",
    "sg:address":"17390 Muskrat Ave",
    "sg:city":"Adelanto",
    "sg:classifiers":[
        {
            "category":"Manufacturing",
            "subcategory":"Tools & Machinery",
            "type":"Manufacturing & Wholesale Goods"
        }
    ],
    "sg:phone":"+1 760 246 9003",
    "sg:postcode":"92301",
    "sg:province":"CA",
    "sg:tags":[
        "machine",
        "shop",
        "industrial",
        "mfg"
    ],
    "wof:name":"Adams & Son's Die Co",
    "wof:placetype":"venue"
},
  "geometry": {"coordinates":[-117.44946400000001,34.566991],"type":"Point"}
}