{
  "type": "Feature",
  "properties": {
    "iso:country":"US",
    "sg:address":"160 Santa Clara Ave",
    "sg:city":"Oakland",
    "sg:classifiers":[
        {
            "category":"Personal",
            "subcategory":"Hair Removal",
            "type":"Services"
        }
    ],
    "sg:phone":"+1 510 653 3100",
    "sg:postcode":"94610",
    "sg:province":"CA",
    "wof:name":"Save Face",
    "wof:placetype":"venue"
},
  "geometry": {"coordinates":[-122.25258700000001,37.819087],"type":"Point"}
}