{
  "type": "Feature",
  "properties": {
    "addr:full":"1586 Hillman St Tulare CA 93274",
    "addr:housenumber":"1586",
    "addr:postcode":"93274",
    "addr:street":"Hillman St",
    "iso:country":"US",
    "sg:address":"1586 Hillman St",
    "sg:city":"Tulare",
    "sg:classifiers":[
        {
            "category":"Personal",
            "subcategory":"Beauty Salon",
            "type":"Services"
        }
    ],
    "sg:phone":"+1 559 686 4792",
    "sg:postcode":"93274",
    "sg:province":"CA",
    "sg:tags":[
        "hair",
        "stylist"
    ],
    "wof:name":"Saturday's Family Hair Care",
    "wof:placetype":"venue"
},
  "geometry": {"coordinates":[-119.330815,36.227151],"type":"Point"}
}