{
  "type": "Feature",
  "properties": {
    "addr:full":"22090 Rae Ln Cupertino CA 95014",
    "addr:housenumber":"22090",
    "addr:postcode":"95014",
    "addr:street":"Rae Ln",
    "iso:country":"US",
    "sg:address":"22090 Rae Ln",
    "sg:city":"Cupertino",
    "sg:classifiers":[
        {
            "category":"Recreation",
            "type":"Entertainment"
        }
    ],
    "sg:phone":"+1 408 253 3483",
    "sg:postcode":"95014",
    "sg:province":"CA",
    "sg:tags":[
        "pool",
        "swimming"
    ],
    "wof:name":"Cupertino Hills Swim & Racquet",
    "wof:placetype":"venue"
},
  "geometry": {"coordinates":[-122.062472,37.312659],"type":"Point"}
}