{
  "type": "Feature",
  "properties": {
    "addr:full":"99 Aero Camino Goleta CA 93117",
    "addr:housenumber":"99",
    "addr:postcode":"93117",
    "addr:street":"Camino Goleta",
    "iso:country":"US",
    "sg:address":"99 Aero Camino",
    "sg:city":"Goleta",
    "sg:classifiers":[
        {
            "category":"Professional",
            "subcategory":"Lawyer & Legal Services",
            "type":"Services"
        }
    ],
    "sg:phone":"+1 805 571 1550",
    "sg:postcode":"93117",
    "sg:province":"CA",
    "sg:tags":[
        "attorney",
        "bureau"
    ],
    "sg:website":"www.xprts-llc.com",
    "wof:name":"Xperts",
    "wof:placetype":"venue"
},
  "geometry": {"coordinates":[-119.848536,34.432886],"type":"Point"}
}