{
  "type": "Feature",
  "properties": {
    "iso:country":"US",
    "sg:address":"150 E Hamilton Ave",
    "sg:city":"Campbell",
    "sg:classifiers":[
        {
            "category":"Restaurant",
            "type":"Food & Drink"
        }
    ],
    "sg:phone":"+1 408 866 5377",
    "sg:postcode":"95008",
    "sg:province":"CA",
    "sg:tags":[
        "traditional",
        "american",
        "diner"
    ],
    "sg:website":"www.carrows.com",
    "wof:name":"Carrows",
    "wof:placetype":"venue"
},
  "geometry": {"coordinates":[-121.947498,37.294163],"type":"Point"}
}