{
  "type": "Feature",
  "properties": {
    "iso:country":"US",
    "sg:address":"1281 Fremont Blvd",
    "sg:city":"Seaside",
    "sg:classifiers":[
        {
            "category":"Wholesale",
            "subcategory":"Fruits & Vegetables",
            "type":"Manufacturing & Wholesale Goods"
        }
    ],
    "sg:phone":"+1 831 393 1362",
    "sg:postcode":"93955",
    "sg:province":"CA",
    "wof:name":"Camacho Produce",
    "wof:placetype":"venue"
},
  "geometry": {"coordinates":[-121.848023,36.604111],"type":"Point"}
}