{
  "type": "Feature",
  "properties": {
    "addr:full":"428 College Dr Ventura CA 93003",
    "addr:housenumber":"428",
    "addr:postcode":"93003",
    "addr:street":"College Dr",
    "iso:country":"US",
    "sg:address":"428 College Dr",
    "sg:city":"Ventura",
    "sg:classifiers":[
        {
            "category":"Building & Trades",
            "subcategory":"Construction",
            "type":"Services"
        }
    ],
    "sg:phone":"+1 805 658 3816",
    "sg:postcode":"93003",
    "sg:province":"CA",
    "sg:tags":[
        "painter"
    ],
    "wof:name":"Albino Chacon Painting Inc",
    "wof:placetype":"venue"
},
  "geometry": {"coordinates":[-119.241676,34.268159],"type":"Point"}
}