{
  "type": "Feature",
  "properties": {
    "addr:full":"1120 N St Sacramento CA 95814",
    "addr:housenumber":"1120",
    "addr:postcode":"95814",
    "addr:street":"N St",
    "iso:country":"US",
    "sg:address":"1120 N St",
    "sg:city":"Sacramento",
    "sg:classifiers":[
        {
            "category":"Government",
            "subcategory":"Office",
            "type":"Public Place"
        }
    ],
    "sg:phone":"+1 916 324 6362",
    "sg:postcode":"95814",
    "sg:province":"CA",
    "sg:tags":[
        "state",
        "program"
    ],
    "wof:name":"Rail Division",
    "wof:placetype":"venue"
},
  "geometry": {"coordinates":[-121.492952,38.575157],"type":"Point"}
}