{
  "type": "Feature",
  "properties": {
    "addr:full":"9327 Lamar St Spring Valley CA 91977",
    "addr:housenumber":"9327",
    "addr:postcode":"91977",
    "addr:street":"Lamar St",
    "iso:country":"US",
    "sg:address":"9327 Lamar St",
    "sg:city":"Spring Valley",
    "sg:classifiers":[
        {
            "category":"Building & Trades",
            "subcategory":"Construction",
            "type":"Services"
        }
    ],
    "sg:phone":"+1 619 460 6111",
    "sg:postcode":"91977",
    "sg:province":"CA",
    "sg:tags":[
        "tile",
        "dealer"
    ],
    "wof:name":"Bo-Designs Inc",
    "wof:placetype":"venue"
},
  "geometry": {"coordinates":[-116.994596,32.739444],"type":"Point"}
}