{
  "type": "Feature",
  "properties": {
    "addr:full":"9919 Topanga Canyon Blvd Chatsworth CA 91311",
    "addr:housenumber":"9919",
    "addr:postcode":"91311",
    "addr:street":"Topanga Canyon Blvd",
    "iso:country":"US",
    "sg:address":"9919 Topanga Canyon Blvd",
    "sg:city":"Chatsworth",
    "sg:classifiers":[
        {
            "category":"Farming",
            "subcategory":"Livestock Farm",
            "type":"Manufacturing & Wholesale Goods"
        }
    ],
    "sg:phone":"+1 818 341 1007",
    "sg:postcode":"91311",
    "sg:province":"CA",
    "sg:tags":[
        "reptile"
    ],
    "wof:name":"Exotic Life Fish & Reptiles",
    "wof:placetype":"venue"
},
  "geometry": {"coordinates":[-118.60603999999999,34.253268],"type":"Point"}
}