{
  "type": "Feature",
  "properties": {
    "addr:full":"321 S 1st St San Jose CA 95113",
    "addr:housenumber":"321",
    "addr:postcode":"95113",
    "addr:street":"S 1St St",
    "iso:country":"US",
    "sg:address":"321 S 1st St",
    "sg:city":"San Jose",
    "sg:classifiers":[
        {
            "category":"Restaurant",
            "type":"Food & Drink"
        }
    ],
    "sg:phone":"+1 408 289 8521",
    "sg:postcode":"95113",
    "sg:province":"CA",
    "sg:tags":[
        "vietnamese"
    ],
    "sg:website":"www.pho69noodle.com/Default.htm",
    "wof:name":"Pho 69",
    "wof:placetype":"venue"
},
  "geometry": {"coordinates":[-121.886827,37.331093],"type":"Point"}
}