{
  "type": "Feature",
  "properties": {
    "addr:full":"8723 Bellanca Ave Los Angeles CA 90045",
    "addr:postcode":"8723;90045",
    "addr:street":"Bellanca Ave",
    "iso:country":"US",
    "sg:address":"8723 Bellanca Ave",
    "sg:city":"Los Angeles",
    "sg:classifiers":[
        {
            "category":"Freight",
            "type":"Transportation"
        }
    ],
    "sg:phone":"+1 310 641 8728",
    "sg:postcode":"90045",
    "sg:province":"CA",
    "wof:name":"ACX Logistics Inc",
    "wof:placetype":"venue"
},
  "geometry": {"coordinates":[-118.38057999999999,33.954109],"type":"Point"}
}