{
  "type": "Feature",
  "properties": {
    "addr:full":"851 Prospect Ave Hollister CA 95023",
    "addr:housenumber":"851",
    "addr:postcode":"hollister ca 95023",
    "addr:street":"Prospect Ave",
    "iso:country":"US",
    "sg:address":"851 Prospect Ave",
    "sg:city":"Hollister",
    "sg:classifiers":[
        {
            "category":"Home & Garden",
            "subcategory":"Household Appliances",
            "type":"Retail Goods"
        }
    ],
    "sg:phone":"+1 831 637 2713",
    "sg:postcode":"95023",
    "sg:province":"CA",
    "wof:name":"Shaw's Appliance Svc",
    "wof:placetype":"venue"
},
  "geometry": {"coordinates":[-121.397178,36.847813],"type":"Point"}
}