{
  "type": "Feature",
  "properties": {
    "addr:full":"11003 S Grevillea Ave Inglewood CA 90304",
    "addr:housenumber":"11003",
    "addr:postcode":"90304",
    "addr:street":"S Grevillea Ave",
    "iso:country":"US",
    "sg:address":"11003 S Grevillea Ave",
    "sg:city":"Inglewood",
    "sg:classifiers":[
        {
            "category":"Building & Trades",
            "subcategory":"Construction",
            "type":"Services"
        }
    ],
    "sg:phone":"+1 310 477 9658",
    "sg:postcode":"90304",
    "sg:province":"CA",
    "sg:tags":[
        "wallcoverings-installation",
        "wallpaper",
        "painting",
        "contractor"
    ],
    "wof:name":"Cecil E Hunt Painting Contracter",
    "wof:placetype":"venue"
},
  "geometry": {"coordinates":[-118.35485300000001,33.935699],"type":"Point"}
}