{
  "type": "Feature",
  "properties": {
    "addr:full":"6355 Topanga Canyon Blvd Woodland Hills CA 91367",
    "addr:housenumber":"6355",
    "addr:postcode":"91367",
    "addr:street":"Topanga Canyon Blvd",
    "iso:country":"US",
    "sg:address":"6355 Topanga Canyon Blvd",
    "sg:city":"Woodland Hills",
    "sg:classifiers":[
        {
            "category":"Professional",
            "subcategory":"Lawyer & Legal Services",
            "type":"Services"
        }
    ],
    "sg:phone":"+1 818 704 4775",
    "sg:postcode":"91367",
    "sg:province":"CA",
    "sg:tags":[
        "attorney"
    ],
    "wof:name":"Robert M Russak",
    "wof:placetype":"venue"
},
  "geometry": {"coordinates":[-118.605878,34.183753],"type":"Point"}
}