{
  "type": "Feature",
  "properties": {
    "addr:full":"222 Mt Hermon Rd Ste H Scotts Valley CA 95066",
    "addr:housenumber":"222",
    "addr:postcode":"95066",
    "addr:street":"Mt Hermon Rd Ste H",
    "iso:country":"US",
    "sg:address":"222 Mt Hermon Rd Ste H",
    "sg:city":"Scotts Valley",
    "sg:classifiers":[
        {
            "category":"Personal",
            "subcategory":"Beauty Salon",
            "type":"Services"
        },
        {
            "category":"Personal",
            "subcategory":"Barber",
            "type":"Services"
        },
        {
            "category":"Personal",
            "subcategory":"Skin Care",
            "type":"Services"
        }
    ],
    "sg:phone":"+1 831 438 0111",
    "sg:postcode":"95066",
    "sg:province":"CA",
    "sg:tags":[
        "hair"
    ],
    "sg:website":"www.idealhairsalon.com",
    "wof:name":"Ideal Hair",
    "wof:placetype":"venue"
},
  "geometry": {"coordinates":[-122.02789,37.045829],"type":"Point"}
}