{
  "type": "Feature",
  "properties": {
    "addr:full":"490 F St Lincoln CA 95648",
    "addr:housenumber":"490",
    "addr:postcode":"95648",
    "addr:street":"F St",
    "iso:country":"US",
    "sg:address":"490 F St",
    "sg:city":"Lincoln",
    "sg:classifiers":[
        {
            "category":"Personal",
            "subcategory":"Beauty Salon",
            "type":"Services"
        }
    ],
    "sg:phone":"+1 916 645 2305",
    "sg:postcode":"95648",
    "sg:province":"CA",
    "wof:name":"Moxie Hair Co",
    "wof:placetype":"venue"
},
  "geometry": {"coordinates":[-121.291622,38.891776],"type":"Point"}
}