{
  "type": "Feature",
  "properties": {
    "iso:country":"US",
    "sg:address":"1600 S Douglass Rd",
    "sg:city":"Anaheim",
    "sg:classifiers":[
        {
            "category":"Banks & Credit Unions",
            "subcategory":"Bank",
            "type":"Services"
        }
    ],
    "sg:phone":"+1 714 937 1024",
    "sg:postcode":"92806",
    "sg:province":"CA",
    "sg:tags":[
        "loan",
        "real estate"
    ],
    "wof:name":"Ameriquest Mortgage Co",
    "wof:placetype":"venue"
},
  "geometry": {"coordinates":[-117.877572,33.808056],"type":"Point"}
}