{
  "type": "Feature",
  "properties": {
    "iso:country":"US",
    "sg:address":"4755 Randi Ct",
    "sg:city":"Union City",
    "sg:classifiers":[
        {
            "category":"Travel",
            "subcategory":"Travel Agent",
            "type":"Entertainment"
        }
    ],
    "sg:phone":"+1 510 489 6814",
    "sg:postcode":"94587",
    "sg:province":"CA",
    "sg:tags":[
        "agency"
    ],
    "wof:name":"Columbia Travel",
    "wof:placetype":"venue"
},
  "geometry": {"coordinates":[-122.0802,37.579364],"type":"Point"}
}