{
  "type": "Feature",
  "properties": {
    "iso:country":"US",
    "sg:address":"19234 Rawhide Rd",
    "sg:city":"Jamestown",
    "sg:classifiers":[
        {
            "category":"Organizations",
            "subcategory":"Non-profit Organization",
            "type":"Services"
        }
    ],
    "sg:phone":"+1 209 984 0454",
    "sg:postcode":"95327",
    "sg:province":"CA",
    "wof:name":"Sierra Waldorf School",
    "wof:placetype":"venue"
},
  "geometry": {"coordinates":[-120.450169,37.964597],"type":"Point"}
}