{
  "type": "Feature",
  "properties": {
    "addr:full":"11 Goodyear Irvine CA 92618",
    "addr:housenumber":"11",
    "addr:postcode":"92618",
    "addr:street":"Goodyear",
    "iso:country":"US",
    "sg:address":"11 Goodyear",
    "sg:city":"Irvine",
    "sg:classifiers":[
        {
            "category":"Shopping",
            "subcategory":"Crafts & Fabrics",
            "type":"Retail Goods"
        }
    ],
    "sg:phone":"+1 949 859 4890",
    "sg:postcode":"92618",
    "sg:province":"CA",
    "sg:tags":[
        "art",
        "supply"
    ],
    "wof:name":"Davinci Paint Company",
    "wof:placetype":"venue"
},
  "geometry": {"coordinates":[-117.710604,33.649139],"type":"Point"}
}