{
  "type": "Feature",
  "properties": {
    "addr:full":"2700 Colorado Boulevard Suite 260 Los Angeles CA 90041",
    "addr:housenumber":"2700",
    "addr:postcode":"90041",
    "addr:street":"Colorado Boulevard Suite 260",
    "iso:country":"US",
    "sg:address":"2700 Colorado Boulevard Suite 260",
    "sg:city":"Los Angeles",
    "sg:classifiers":[
        {
            "category":"Shopping",
            "subcategory":"Clothing, Apparel, & Fashions",
            "type":"Retail Goods"
        }
    ],
    "sg:phone":"+1 323 254 4215",
    "sg:postcode":"90041",
    "sg:province":"CA",
    "sg:tags":[
        "accessory",
        "clothing",
        "women's"
    ],
    "wof:name":"Cali",
    "wof:placetype":"venue"
},
  "geometry": {"coordinates":[-118.22458399999999,34.142737],"type":"Point"}
}