{
  "type": "Feature",
  "properties": {
    "iso:country":"US",
    "sg:address":"41180 Woodhaven Dr E",
    "sg:city":"Palm Desert",
    "sg:classifiers":[
        {
            "category":"Building & Trades",
            "subcategory":"Construction",
            "type":"Services"
        }
    ],
    "sg:phone":"+1 760 360 9736",
    "sg:postcode":"92211",
    "sg:province":"CA",
    "sg:tags":[
        "contractor"
    ],
    "wof:name":"Michael C Roof",
    "wof:placetype":"venue"
},
  "geometry": {"coordinates":[-116.305197,33.748619],"type":"Point"}
}