{
  "type": "Feature",
  "properties": {
    "iso:country":"US",
    "sg:address":"12301 Wilshire Blvd",
    "sg:city":"Los Angeles",
    "sg:classifiers":[
        {
            "category":"Professional",
            "subcategory":"Lawyer & Legal Services",
            "type":"Services"
        }
    ],
    "sg:phone":"+1 310 273 2404",
    "sg:postcode":"90025",
    "sg:province":"CA",
    "sg:tags":[
        "attorney"
    ],
    "wof:name":"Howard J Gorin Law Office",
    "wof:placetype":"venue"
},
  "geometry": {"coordinates":[-118.469652,34.042335],"type":"Point"}
}