{
  "type": "Feature",
  "properties": {
    "iso:country":"US",
    "sg:address":"18683 Morgan Valley Rd",
    "sg:city":"Lower Lake",
    "sg:phone":"+1 707 994 3043",
    "sg:postcode":"95457",
    "sg:province":"CA",
    "sg:tags":[
        "oil"
    ],
    "wof:name":"Amsoil Direct Jobber",
    "wof:placetype":"venue"
},
  "geometry": {"coordinates":[-122.56580200000001,38.899956],"type":"Point"}
}