{
  "type": "Feature",
  "properties": {
    "iso:country":"US",
    "sg:address":"1701 F St",
    "sg:city":"Bakersfield",
    "sg:classifiers":[
        {
            "category":"Personal",
            "subcategory":"Massage",
            "type":"Services"
        }
    ],
    "sg:phone":"+1 661 327 3529",
    "sg:postcode":"93301",
    "sg:province":"CA",
    "wof:name":"Hypnosis & Holistic Health",
    "wof:placetype":"venue"
},
  "geometry": {"coordinates":[-119.023524,35.375304],"type":"Point"}
}