{
  "type": "Feature",
  "properties": {
    "iso:country":"US",
    "sg:address":"123 E 9th St",
    "sg:city":"Upland",
    "sg:classifiers":[
        {
            "category":"Banks & Credit Unions",
            "subcategory":"Bank",
            "type":"Services"
        }
    ],
    "sg:phone":"+1 909 932 9226",
    "sg:postcode":"91786",
    "sg:province":"CA",
    "sg:tags":[
        "loan",
        "real estate"
    ],
    "wof:name":"Allied Equity",
    "wof:placetype":"venue"
},
  "geometry": {"coordinates":[-117.64869400000001,34.096193],"type":"Point"}
}