{
  "type": "Feature",
  "properties": {
    "addr:full":"31271 Niguel Rd Laguna Niguel CA 92677",
    "addr:postcode":"31271;92677",
    "addr:street":"Niguel Rd",
    "iso:country":"US",
    "sg:address":"31271 Niguel Rd",
    "sg:city":"Laguna Niguel",
    "sg:classifiers":[
        {
            "category":"Health Services",
            "subcategory":"Chiropractor",
            "type":"Services"
        }
    ],
    "sg:phone":"+1 949 218 4101",
    "sg:postcode":"92677",
    "sg:province":"CA",
    "wof:name":"Injury & Pain Relief Ctr",
    "wof:placetype":"venue"
},
  "geometry": {"coordinates":[-117.707978,33.506259],"type":"Point"}
}