{
  "type": "Feature",
  "properties": {
    "iso:country":"US",
    "sg:address":"1691 Lever Blvd",
    "sg:city":"Stockton",
    "sg:classifiers":[
        {
            "category":"Retail",
            "subcategory":"Repair Shop",
            "type":"Services"
        }
    ],
    "sg:phone":"+1 209 464 2336",
    "sg:postcode":"95206",
    "sg:province":"CA",
    "sg:tags":[
        "welding"
    ],
    "wof:name":"Almazan Welding Svc",
    "wof:placetype":"venue"
},
  "geometry": {"coordinates":[-121.310088,37.923219],"type":"Point"}
}