{
  "type": "Feature",
  "properties": {
    "addr:full":"351 8th St San Francisco CA 94103",
    "addr:housenumber":"351",
    "addr:postcode":"94103",
    "addr:street":"8Th St",
    "iso:country":"US",
    "sg:address":"351 8th St",
    "sg:city":"San Francisco",
    "sg:classifiers":[
        {
            "category":"Professional",
            "type":"Services"
        }
    ],
    "sg:phone":"+1 415 255 2245",
    "sg:postcode":"94103",
    "sg:province":"CA",
    "wof:name":"Got Bail",
    "wof:placetype":"venue"
},
  "geometry": {"coordinates":[-122.409864,37.775012],"type":"Point"}
}