{
  "type": "Feature",
  "properties": {
    "iso:country":"US",
    "sg:address":"430 S Westmoreland Ave",
    "sg:city":"Los Angeles",
    "sg:classifiers":[
        {
            "category":"Professional",
            "subcategory":"Art Services",
            "type":"Services"
        }
    ],
    "sg:phone":"+1 213 388 4002",
    "sg:postcode":"90020",
    "sg:province":"CA",
    "sg:tags":[
        "graphic",
        "designer"
    ],
    "wof:name":"Jefferies Association",
    "wof:placetype":"venue"
},
  "geometry": {"coordinates":[-118.288372,34.065669],"type":"Point"}
}