{
  "type": "Feature",
  "properties": {
    "iso:country":"US",
    "sg:address":"3130 Chardoney Way",
    "sg:city":"Mira Loma",
    "sg:classifiers":[
        {
            "category":"Professional",
            "type":"Services"
        }
    ],
    "sg:phone":"+1 951 681 9843",
    "sg:postcode":"91752",
    "sg:province":"CA",
    "wof:name":"Kathy L Barros",
    "wof:placetype":"venue"
},
  "geometry": {"coordinates":[-117.513381,34.029389],"type":"Point"}
}