{
  "type": "Feature",
  "properties": {
    "iso:country":"US",
    "sg:address":"1289 Linda Mar Blvd",
    "sg:city":"Pacifica",
    "sg:classifiers":[
        {
            "category":"Shopping",
            "subcategory":"Music",
            "type":"Retail Goods"
        }
    ],
    "sg:phone":"+1 650 359 7719",
    "sg:postcode":"94044",
    "sg:province":"CA",
    "sg:tags":[
        "video",
        "disc",
        "tape",
        "cassette"
    ],
    "wof:name":"California Super Video",
    "wof:placetype":"venue"
},
  "geometry": {"coordinates":[-122.487644,37.58511],"type":"Point"}
}