{
  "type": "Feature",
  "properties": {
    "addr:full":"1328 Crucero Dr San Jose CA 95122",
    "addr:housenumber":"1328",
    "addr:postcode":"95122",
    "addr:street":"Crucero Dr",
    "iso:country":"US",
    "sg:address":"1328 Crucero Dr",
    "sg:city":"San Jose",
    "sg:classifiers":[
        {
            "category":"Professional",
            "type":"Services"
        }
    ],
    "sg:phone":"+1 408 293 4892",
    "sg:postcode":"95122",
    "sg:province":"CA",
    "wof:name":"Marmol Y Tallos Granito",
    "wof:placetype":"venue"
},
  "geometry": {"coordinates":[-121.845699,37.331878],"type":"Point"}
}