{
  "type": "Feature",
  "properties": {
    "addr:full":"1655 Colorado Blvd Los Angeles CA 90041",
    "addr:housenumber":"1655",
    "addr:postcode":"90041",
    "addr:street":"Colorado Blvd",
    "iso:country":"US",
    "sg:address":"1655 Colorado Blvd",
    "sg:city":"Los Angeles",
    "sg:classifiers":[
        {
            "category":"Building & Trades",
            "subcategory":"Plumbing",
            "type":"Services"
        }
    ],
    "sg:phone":"+1 323 256 5556",
    "sg:postcode":"90041",
    "sg:province":"CA",
    "sg:tags":[
        "contractor"
    ],
    "wof:name":"Clairville Plumbing & Heating",
    "wof:placetype":"venue"
},
  "geometry": {"coordinates":[-118.202296,34.139613],"type":"Point"}
}