{
  "type": "Feature",
  "properties": {
    "iso:country":"US",
    "sg:address":"4766 E Whitmore Ave",
    "sg:city":"Ceres",
    "sg:classifiers":[
        {
            "category":"Farming",
            "subcategory":"Farm",
            "type":"Manufacturing & Wholesale Goods"
        }
    ],
    "sg:phone":"+1 209 537 3514",
    "sg:postcode":"95307",
    "sg:province":"CA",
    "wof:name":"Parks Farming Co",
    "wof:placetype":"venue"
},
  "geometry": {"coordinates":[-120.905501,37.594686],"type":"Point"}
}