{
  "type": "Feature",
  "properties": {
    "addr:full":"540 Brunken Ave Salinas CA 93901",
    "addr:housenumber":"540",
    "addr:postcode":"93901",
    "addr:street":"Brunken Ave",
    "iso:country":"US",
    "sg:address":"540 Brunken Ave",
    "sg:city":"Salinas",
    "sg:classifiers":[
        {
            "category":"Professional",
            "subcategory":"Business Services",
            "type":"Services"
        }
    ],
    "sg:phone":"+1 831 758 8845",
    "sg:postcode":"93901",
    "sg:province":"CA",
    "sg:tags":[
        "interior",
        "consultant",
        "design",
        "decorator"
    ],
    "wof:name":"Larry Vera Interior Design",
    "wof:placetype":"venue"
},
  "geometry": {"coordinates":[-121.64044,36.664272],"type":"Point"}
}