{
  "type": "Feature",
  "properties": {
    "addr:full":"990 Arden Way Sacramento CA 95815",
    "addr:housenumber":"990",
    "addr:postcode":"95815",
    "addr:street":"Arden Way",
    "iso:country":"US",
    "sg:address":"990 Arden Way",
    "sg:city":"Sacramento",
    "sg:classifiers":[
        {
            "category":"Shopping",
            "subcategory":"Florist",
            "type":"Retail Goods"
        }
    ],
    "sg:phone":"+1 800 890 2580",
    "sg:postcode":"95815",
    "sg:province":"CA",
    "wof:name":"Lydia Reibel's School of Floral Design",
    "wof:placetype":"venue"
},
  "geometry": {"coordinates":[-121.444063,38.606411],"type":"Point"}
}