{
  "type": "Feature",
  "properties": {
    "iso:country":"US",
    "sg:address":"5620 Pony Express Trl",
    "sg:city":"Camino",
    "sg:classifiers":[
        {
            "category":"Restaurant",
            "type":"Food & Drink"
        }
    ],
    "sg:phone":"+1 530 344 7593",
    "sg:postcode":"95709",
    "sg:province":"CA",
    "wof:name":"Sportsman's Hall",
    "wof:placetype":"venue"
},
  "geometry": {"coordinates":[-120.61857500000001,38.749421],"type":"Point"}
}