{
  "type": "Feature",
  "properties": {
    "addr:full":"3146 Keats St Fremont CA 94536",
    "addr:housenumber":"3146",
    "addr:postcode":"94536",
    "addr:street":"Keats St",
    "iso:country":"US",
    "sg:address":"3146 Keats St",
    "sg:city":"Fremont",
    "sg:classifiers":[
        {
            "category":"Health Services",
            "subcategory":"Clinic",
            "type":"Services"
        }
    ],
    "sg:phone":"+1 510 791 5125",
    "sg:postcode":"94536",
    "sg:province":"CA",
    "wof:name":"Intentions",
    "wof:placetype":"venue"
},
  "geometry": {"coordinates":[-121.989172,37.556033],"type":"Point"}
}