{
  "type": "Feature",
  "properties": {
    "addr:full":"505 N Humboldt Ave Ste D Willows CA 95988",
    "addr:housenumber":"505",
    "addr:postcode":"95988",
    "addr:street":"N Humboldt Ave Ste D",
    "iso:country":"US",
    "sg:address":"505 N Humboldt Ave Ste D",
    "sg:city":"Willows",
    "sg:classifiers":[
        {
            "category":"Insurance",
            "subcategory":"Hazard Insurance",
            "type":"Services"
        },
        {
            "category":"Travel",
            "subcategory":"Travel Agent",
            "type":"Entertainment"
        }
    ],
    "sg:phone":"+1 530 934 4648",
    "sg:postcode":"95988",
    "sg:province":"CA",
    "sg:tags":[
        "agency",
        "services-commercial"
    ],
    "sg:website":"http://www.californiastateautomobileassociation.com",
    "wof:name":"Aaa",
    "wof:placetype":"venue"
},
  "geometry": {"coordinates":[-122.212087,39.525786],"type":"Point"}
}