{
  "type": "Feature",
  "properties": {
    "addr:full":"2275 Camden Ave Campbell CA 95008",
    "addr:housenumber":"2275",
    "addr:postcode":"95008",
    "addr:street":"Camden Ave",
    "iso:country":"US",
    "sg:address":"2275 Camden Ave",
    "sg:city":"Campbell",
    "sg:classifiers":[
        {
            "category":"Organizations",
            "subcategory":"Religious Organization",
            "type":"Services"
        }
    ],
    "sg:phone":"+1 408 371 3770",
    "sg:postcode":"95008",
    "sg:province":"CA",
    "sg:tags":[
        "church"
    ],
    "wof:name":"Camden Assembly of God Church",
    "wof:placetype":"venue"
},
  "geometry": {"coordinates":[-121.941002,37.266399],"type":"Point"}
}