{
  "type": "Feature",
  "properties": {
    "iso:country":"US",
    "sg:address":"7432 Varna Ave",
    "sg:city":"North Hollywood",
    "sg:classifiers":[
        {
            "category":"Building & Trades",
            "subcategory":"Construction",
            "type":"Services"
        }
    ],
    "sg:phone":"+1 818 982 6266",
    "sg:postcode":"91605",
    "sg:province":"CA",
    "sg:tags":[
        "maker",
        "cabinet"
    ],
    "wof:name":"Manzano Cabinets",
    "wof:placetype":"venue"
},
  "geometry": {"coordinates":[-118.424634,34.203681],"type":"Point"}
}