{
  "type": "Feature",
  "properties": {
    "iso:country":"US",
    "sg:address":"1572 Garnet Ave",
    "sg:city":"San Diego",
    "sg:classifiers":[
        {
            "category":"Personal",
            "subcategory":"Tattoo Parlor",
            "type":"Services"
        }
    ],
    "sg:phone":"+1 858 490 4200",
    "sg:postcode":"92109",
    "sg:province":"CA",
    "sg:website":"www.edgewatertattoo.com",
    "wof:name":"Edgewater Tattoo",
    "wof:placetype":"venue"
},
  "geometry": {"coordinates":[-117.241133,32.799732],"type":"Point"}
}