{
  "type": "Feature",
  "properties": {
    "addr:full":"150 Post St San Francisco CA 94108",
    "addr:housenumber":"150",
    "addr:postcode":"94108",
    "addr:street":"Post St",
    "iso:country":"US",
    "sg:address":"150 Post St",
    "sg:city":"San Francisco",
    "sg:classifiers":[
        {
            "category":"Real Estate",
            "subcategory":"Developer",
            "type":"Services"
        }
    ],
    "sg:phone":"+1 415 395 0880",
    "sg:postcode":"94108",
    "sg:province":"CA",
    "wof:name":"Prado Group Inc",
    "wof:placetype":"venue"
},
  "geometry": {"coordinates":[-122.405134,37.788784],"type":"Point"}
}