{
  "type": "Feature",
  "properties": {
    "iso:country":"US",
    "sg:address":"150 Spear Street Suite 1800",
    "sg:city":"San Francisco",
    "sg:classifiers":[
        {
            "category":"Professional",
            "subcategory":"Lawyer & Legal Services",
            "type":"Services"
        }
    ],
    "sg:phone":"+1 415 541 0200",
    "sg:postcode":"94105",
    "sg:province":"CA",
    "wof:name":"Cooper Steven A Freeland Cooper & Foreman",
    "wof:placetype":"venue"
},
  "geometry": {"coordinates":[-122.39299800000001,37.791599],"type":"Point"}
}