{
  "type": "Feature",
  "properties": {
    "addr:full":"6570 Van Nuys Blvd San Fernando Valley CA 91405",
    "addr:housenumber":"6570",
    "addr:postcode":"91405",
    "addr:street":"Van Nuys Blvd",
    "iso:country":"US",
    "sg:address":"6570 Van Nuys Blvd",
    "sg:city":"San Fernando Valley",
    "sg:classifiers":[
        {
            "category":"Insurance",
            "subcategory":"Insurance Agent",
            "type":"Services"
        }
    ],
    "sg:phone":"+1 818 933 3888",
    "sg:postcode":"91405",
    "sg:province":"CA",
    "wof:name":"Adriana's Insurance Service",
    "wof:placetype":"venue"
},
  "geometry": {"coordinates":[-118.448694,34.190358],"type":"Point"}
}