{
  "type": "Feature",
  "properties": {
    "iso:country":"US",
    "sg:address":"PO Box 710997",
    "sg:city":"Santee",
    "sg:classifiers":[
        {
            "category":"Taxi",
            "type":"Transportation"
        },
        {
            "category":"Airline",
            "type":"Transportation"
        }
    ],
    "sg:phone":"+1 619 448 6699",
    "sg:postcode":"92072",
    "sg:province":"CA",
    "sg:tags":[
        "shuttle",
        "airport"
    ],
    "wof:name":"El Cajon Cab Company",
    "wof:placetype":"venue"
},
  "geometry": {"coordinates":[-116.98400100000001,32.838799],"type":"Point"}
}