{
  "type": "Feature",
  "properties": {
    "iso:country":"US",
    "sg:address":"11684 Ventura Blvd",
    "sg:city":"Studio City",
    "sg:classifiers":[
        {
            "category":"Real Estate",
            "subcategory":"Real Estate Agent",
            "type":"Services"
        }
    ],
    "sg:phone":"+1 818 506 5425",
    "sg:postcode":"91604",
    "sg:province":"CA",
    "wof:name":"Options Network",
    "wof:placetype":"venue"
},
  "geometry": {"coordinates":[-118.385288,34.140346],"type":"Point"}
}