{
  "type": "Feature",
  "properties": {
    "addr:full":"213 Nadine St Livermore CA 94550",
    "addr:housenumber":"213",
    "addr:postcode":"94550",
    "addr:street":"Nadine St",
    "iso:country":"US",
    "sg:address":"213 Nadine St",
    "sg:city":"Livermore",
    "sg:classifiers":[
        {
            "category":"Professional",
            "subcategory":"Computer Services",
            "type":"Services"
        }
    ],
    "sg:phone":"+1 925 292 0585",
    "sg:postcode":"94550",
    "sg:province":"CA",
    "sg:tags":[
        "related"
    ],
    "wof:name":"Compucom Systems Inc",
    "wof:placetype":"venue"
},
  "geometry": {"coordinates":[-121.792406,37.674962],"type":"Point"}
}