{
  "type": "Feature",
  "properties": {
    "iso:country":"US",
    "sg:address":"220 W Ave 26",
    "sg:city":"Los Angeles",
    "sg:classifiers":[
        {
            "category":"Retail",
            "subcategory":"Veterinary Services",
            "type":"Services"
        }
    ],
    "sg:phone":"+1 323 225 4228",
    "sg:postcode":"90031",
    "sg:province":"CA",
    "sg:tags":[
        "veterinarian"
    ],
    "wof:name":"LA Central Animal Hospital",
    "wof:placetype":"venue"
},
  "geometry": {"coordinates":[-118.217958,34.078808],"type":"Point"}
}