{
  "type": "Feature",
  "properties": {
    "addr:full":"5951 Avalon Blvd Los Angeles CA 90003",
    "addr:housenumber":"5951",
    "addr:postcode":"90003",
    "addr:street":"Avalon Blvd",
    "iso:country":"US",
    "sg:address":"5951 Avalon Blvd",
    "sg:city":"Los Angeles",
    "sg:classifiers":[
        {
            "category":"Building & Trades",
            "subcategory":"Plumbing",
            "type":"Services"
        }
    ],
    "sg:phone":"+1 323 232 7440",
    "sg:postcode":"90003",
    "sg:province":"CA",
    "sg:tags":[
        "contractor"
    ],
    "wof:name":"D & M Plumbing",
    "wof:placetype":"venue"
},
  "geometry": {"coordinates":[-118.26518,33.985631],"type":"Point"}
}