{
  "type": "Feature",
  "properties": {
    "addr:full":"151 H St Bakersfield CA 93304",
    "addr:housenumber":"151",
    "addr:postcode":"93304",
    "addr:street":"H St",
    "iso:country":"US",
    "sg:address":"151 H St",
    "sg:city":"Bakersfield",
    "sg:classifiers":[
        {
            "category":"Shopping",
            "subcategory":"Used Merchandise",
            "type":"Retail Goods"
        }
    ],
    "sg:phone":"+1 661 322 9326",
    "sg:postcode":"93304",
    "sg:province":"CA",
    "sg:tags":[
        "antique"
    ],
    "wof:name":"Fond Memories",
    "wof:placetype":"venue"
},
  "geometry": {"coordinates":[-119.02137500000001,35.356864],"type":"Point"}
}