{
  "type": "Feature",
  "properties": {
    "addr:full":"6837 Amador Valley Blvd Dublin CA 94568",
    "addr:housenumber":"6837",
    "addr:postcode":"94568",
    "addr:street":"Amador Valley Blvd",
    "iso:country":"US",
    "sg:address":"6837 Amador Valley Blvd",
    "sg:city":"Dublin",
    "sg:classifiers":[
        {
            "category":"Social Services",
            "subcategory":"Child Care",
            "type":"Services"
        }
    ],
    "sg:phone":"+1 925 803 4035",
    "sg:postcode":"94568",
    "sg:province":"CA",
    "wof:name":"A Creative Playschool",
    "wof:placetype":"venue"
},
  "geometry": {"coordinates":[-121.92008800000001,37.714345],"type":"Point"}
}