{
  "type": "Feature",
  "properties": {
    "iso:country":"US",
    "sg:address":"9500 Harritt Rd",
    "sg:city":"Lakeside",
    "sg:classifiers":[
        {
            "category":"Real Estate",
            "subcategory":"Real Estate Operator",
            "type":"Services"
        }
    ],
    "sg:phone":"+1 619 443 4453",
    "sg:postcode":"92040",
    "sg:province":"CA",
    "sg:tags":[
        "mobile",
        "home",
        "community"
    ],
    "wof:name":"Lake Jennings Park Estates",
    "wof:placetype":"venue"
},
  "geometry": {"coordinates":[-116.88588,32.851035],"type":"Point"}
}