{
  "type": "Feature",
  "properties": {
    "iso:country":"US",
    "sg:address":"4700 Florin Rd",
    "sg:city":"Sacramento",
    "sg:classifiers":[
        {
            "category":"Autos & Motor Vehicles",
            "subcategory":"Fuel & Gas Station",
            "type":"Retail Goods"
        }
    ],
    "sg:phone":"+1 916 422 3434",
    "sg:postcode":"95823",
    "sg:province":"CA",
    "sg:tags":[
        "oil"
    ],
    "wof:name":"Chevron Peeta",
    "wof:placetype":"venue"
},
  "geometry": {"coordinates":[-121.45132099999999,38.496072],"type":"Point"}
}