{
  "type": "Feature",
  "properties": {
    "addr:full":"19809 Cabot Blvd Hayward CA 94545",
    "addr:housenumber":"19809",
    "addr:postcode":"94545",
    "addr:street":"Cabot Blvd",
    "iso:country":"US",
    "sg:address":"19809 Cabot Blvd",
    "sg:city":"Hayward",
    "sg:classifiers":[
        {
            "category":"Building & Trades",
            "subcategory":"Construction",
            "type":"Services"
        }
    ],
    "sg:phone":"+1 510 783 3110",
    "sg:postcode":"94545",
    "sg:province":"CA",
    "sg:tags":[
        "contractor"
    ],
    "wof:name":"Bryant J H Jr Inc",
    "wof:placetype":"venue"
},
  "geometry": {"coordinates":[-122.139,37.654099],"type":"Point"}
}