{
  "type": "Feature",
  "properties": {
    "iso:country":"US",
    "sg:address":"9955 Valley Blvd",
    "sg:city":"El Monte",
    "sg:classifiers":[
        {
            "category":"Retail",
            "subcategory":"Car Wash",
            "type":"Services"
        }
    ],
    "sg:phone":"+1 626 575 1414",
    "sg:postcode":"91731",
    "sg:province":"CA",
    "wof:name":"Baldwin Car Wash Co",
    "wof:placetype":"venue"
},
  "geometry": {"coordinates":[-118.05300099999999,34.079102],"type":"Point"}
}