{
  "type": "Feature",
  "properties": {
    "addr:full":"1870 Illinois St San Francisco CA 94124",
    "addr:housenumber":"1870",
    "addr:postcode":"94124",
    "addr:street":"Illinois St",
    "iso:country":"US",
    "sg:address":"1870 Illinois St",
    "sg:city":"San Francisco",
    "sg:classifiers":[
        {
            "category":"Building & Trades",
            "subcategory":"Construction",
            "type":"Services"
        }
    ],
    "sg:phone":"+1 415 648 8779",
    "sg:postcode":"94124",
    "sg:province":"CA",
    "sg:tags":[
        "repairing",
        "remodeling",
        "contractor"
    ],
    "sg:website":"www.cvc-inc.com",
    "wof:name":"CVC Inc",
    "wof:placetype":"venue"
},
  "geometry": {"coordinates":[-122.38646,37.748767],"type":"Point"}
}