{
  "type": "Feature",
  "properties": {
    "iso:country":"US",
    "sg:address":"1061 Helen Power Dr",
    "sg:city":"Vacaville",
    "sg:classifiers":[
        {
            "category":"Food & Beverages",
            "subcategory":"Specialty",
            "type":"Retail Goods"
        }
    ],
    "sg:phone":"+1 707 451 8660",
    "sg:postcode":"95687",
    "sg:province":"CA",
    "sg:tags":[
        "vitamin"
    ],
    "sg:website":"www.gnc.com",
    "wof:name":"General Nutrition Ctr",
    "wof:placetype":"venue"
},
  "geometry": {"coordinates":[-121.960408,38.364478],"type":"Point"}
}