{
  "type": "Feature",
  "properties": {
    "iso:country":"US",
    "sg:address":"417 18th St",
    "sg:city":"Huntington Beach",
    "sg:classifiers":[
        {
            "category":"Professional",
            "type":"Services"
        }
    ],
    "sg:phone":"+1 714 960 5319",
    "sg:postcode":"92648",
    "sg:province":"CA",
    "wof:name":"Sonic Trends LLC",
    "wof:placetype":"venue"
},
  "geometry": {"coordinates":[-118.009947,33.668708],"type":"Point"}
}