{
  "type": "Feature",
  "properties": {
    "addr:full":"888 Prospect St Ste 140 La Jolla CA 92037",
    "addr:housenumber":"888",
    "addr:postcode":"92037",
    "addr:street":"Prospect St Ste 140",
    "iso:country":"US",
    "sg:address":"888 Prospect St Ste 140",
    "sg:city":"La Jolla",
    "sg:classifiers":[
        {
            "category":"Banks & Credit Unions",
            "subcategory":"Bank",
            "type":"Services"
        },
        {
            "category":"Banks & Credit Unions",
            "subcategory":"Financial Services",
            "type":"Services"
        }
    ],
    "sg:phone":"+1 858 454 8800",
    "sg:postcode":"92037",
    "sg:province":"CA",
    "sg:tags":[
        "broker",
        "mortgage"
    ],
    "wof:name":"La Jolla Bank F S B",
    "wof:placetype":"venue"
},
  "geometry": {"coordinates":[-117.27600099999999,32.8465],"type":"Point"}
}