{
  "type": "Feature",
  "properties": {
    "addr:full":"17480 Sage St Riverside CA 92504",
    "addr:housenumber":"17480",
    "addr:postcode":"92504",
    "addr:street":"Sage St",
    "iso:country":"US",
    "sg:address":"17480 Sage St",
    "sg:city":"Riverside",
    "sg:classifiers":[
        {
            "category":"Professional",
            "subcategory":"Engineering",
            "type":"Services"
        }
    ],
    "sg:phone":"+1 951 789 4292",
    "sg:postcode":"92504",
    "sg:province":"CA",
    "wof:name":"RCM & Associates",
    "wof:placetype":"venue"
},
  "geometry": {"coordinates":[-117.361333,33.884883],"type":"Point"}
}