{
  "type": "Feature",
  "properties": {
    "addr:full":"930 Commercial St Palo Alto CA 94303",
    "addr:housenumber":"930",
    "addr:postcode":"94303",
    "addr:street":"Commercial St",
    "iso:country":"US",
    "sg:address":"930 Commercial St",
    "sg:city":"Palo Alto",
    "sg:classifiers":[
        {
            "category":"Communications",
            "subcategory":"Film & Video Production",
            "type":"Services"
        }
    ],
    "sg:phone":"+1 650 494 1529",
    "sg:postcode":"94303",
    "sg:province":"CA",
    "sg:tags":[
        "duplication",
        "tape"
    ],
    "sg:website":"www.videotransform.com",
    "wof:name":"Videotransform Inc",
    "wof:placetype":"venue"
},
  "geometry": {"coordinates":[-122.09999500000001,37.422992],"type":"Point"}
}