{
  "type": "Feature",
  "properties": {
    "iso:country":"US",
    "sg:address":"1133 S Garfield Ave",
    "sg:city":"Alhambra",
    "sg:classifiers":[
        {
            "category":"Banks & Credit Unions",
            "subcategory":"Financial Services",
            "type":"Services"
        }
    ],
    "sg:phone":"+1 626 570 4828",
    "sg:postcode":"91801",
    "sg:province":"CA",
    "sg:tags":[
        "broker",
        "mortgage"
    ],
    "wof:name":"Coast Financial",
    "wof:placetype":"venue"
},
  "geometry": {"coordinates":[-118.123001,34.081799],"type":"Point"}
}