{
  "type": "Feature",
  "properties": {
    "addr:full":"8851 Lakewood Blvd Downey CA 90240",
    "addr:housenumber":"8851",
    "addr:postcode":"90240",
    "addr:street":"Lakewood Blvd",
    "iso:country":"US",
    "sg:address":"8851 Lakewood Blvd",
    "sg:city":"Downey",
    "sg:classifiers":[
        {
            "category":"Retail",
            "subcategory":"Auto Repair",
            "type":"Services"
        }
    ],
    "sg:phone":"+1 562 862 2177",
    "sg:postcode":"90240",
    "sg:province":"CA",
    "sg:tags":[
        "van",
        "conversion",
        "truck",
        "accessory"
    ],
    "sg:website":"www.sunsetvans.com",
    "wof:name":"Sunset Van Conversion",
    "wof:placetype":"venue"
},
  "geometry": {"coordinates":[-118.11067,33.960034],"type":"Point"}
}