{
  "type": "Feature",
  "properties": {
    "addr:full":"2516 W Jefferson Blvd Los Angeles CA 90018",
    "addr:housenumber":"2516",
    "addr:postcode":"90018",
    "addr:street":"W Jefferson Blvd",
    "iso:country":"US",
    "sg:address":"2516 W Jefferson Blvd",
    "sg:city":"Los Angeles",
    "sg:classifiers":[
        {
            "category":"Personal",
            "subcategory":"Barber",
            "type":"Services"
        }
    ],
    "sg:phone":"+1 323 733 4396",
    "sg:postcode":"90018",
    "sg:province":"CA",
    "wof:name":"Unique Beauty Salon",
    "wof:placetype":"venue"
},
  "geometry": {"coordinates":[-118.322998,34.0257],"type":"Point"}
}