{
  "type": "Feature",
  "properties": {
    "iso:country":"US",
    "sg:address":"19401 Rd 220",
    "sg:city":"Strathmore",
    "sg:classifiers":[
        {
            "category":"Farming",
            "subcategory":"Crops",
            "type":"Manufacturing & Wholesale Goods"
        }
    ],
    "sg:phone":"+1 559 562 2882",
    "sg:postcode":"93267",
    "sg:province":"CA",
    "sg:tags":[
        "farm",
        "olive",
        "groves",
        "vegetable",
        "product"
    ],
    "wof:name":"Adams Olive Ranch",
    "wof:placetype":"venue"
},
  "geometry": {"coordinates":[-119.080729,36.145525],"type":"Point"}
}