{
  "type": "Feature",
  "properties": {
    "addr:full":"3543 Trenton Way El Dorado Hills CA 95762",
    "addr:housenumber":"3543",
    "addr:postcode":"95762",
    "addr:street":"Trenton Way",
    "iso:country":"US",
    "sg:address":"3543 Trenton Way",
    "sg:city":"El Dorado Hills",
    "sg:classifiers":[
        {
            "category":"Professional",
            "subcategory":"Management & Consulting",
            "type":"Services"
        }
    ],
    "sg:phone":"+1 916 941 1305",
    "sg:postcode":"95762",
    "sg:province":"CA",
    "sg:tags":[
        "consultant",
        "resource",
        "human"
    ],
    "wof:name":"H R Options",
    "wof:placetype":"venue"
},
  "geometry": {"coordinates":[-121.080139,38.719382],"type":"Point"}
}