{
  "type": "Feature",
  "properties": {
    "iso:country":"US",
    "sg:address":"9939 Hibert St",
    "sg:city":"San Diego",
    "sg:classifiers":[
        {
            "category":"Education",
            "subcategory":"Special Training",
            "type":"Public Place"
        }
    ],
    "sg:phone":"+1 858 271 7323",
    "sg:postcode":"92131",
    "sg:province":"CA",
    "sg:tags":[
        "tutoring"
    ],
    "wof:name":"Knowlegepoints Of San Diego",
    "wof:placetype":"venue"
},
  "geometry": {"coordinates":[-117.11231,32.913759],"type":"Point"}
}