{
  "type": "Feature",
  "properties": {
    "addr:full":"28 E 25th Ave San Mateo CA 94403",
    "addr:housenumber":"28",
    "addr:postcode":"94403",
    "addr:street":"E 25Th Ave",
    "iso:country":"US",
    "sg:address":"28 E 25th Ave",
    "sg:city":"San Mateo",
    "sg:classifiers":[
        {
            "category":"Home & Garden",
            "subcategory":"Building Materials",
            "type":"Retail Goods"
        }
    ],
    "sg:phone":"+1 650 345 4858",
    "sg:postcode":"94403",
    "sg:province":"CA",
    "sg:tags":[
        "shutter"
    ],
    "wof:name":"Carlo Lindsey Custom Shutters",
    "wof:placetype":"venue"
},
  "geometry": {"coordinates":[-122.305362,37.544679],"type":"Point"}
}