{
  "type": "Feature",
  "properties": {
    "iso:country":"US",
    "sg:address":"4681 Arrow Hwy",
    "sg:city":"Montclair",
    "sg:classifiers":[
        {
            "category":"Retail",
            "subcategory":"Auto Repair",
            "type":"Services"
        }
    ],
    "sg:phone":"+1 909 625 2727",
    "sg:postcode":"91763",
    "sg:province":"CA",
    "sg:tags":[
        "repairing",
        "automobile"
    ],
    "sg:website":"www.mctierimport.com",
    "wof:name":"Mc Tier Import Repair",
    "wof:placetype":"venue"
},
  "geometry": {"coordinates":[-117.701234,34.092446],"type":"Point"}
}