{
  "type": "Feature",
  "properties": {
    "iso:country":"US",
    "sg:address":"702 W 16th St",
    "sg:city":"San Bernardino",
    "sg:classifiers":[
        {
            "category":"Social Services",
            "subcategory":"Child Care",
            "type":"Services"
        }
    ],
    "sg:phone":"+1 909 883 6040",
    "sg:postcode":"92405",
    "sg:province":"CA",
    "sg:tags":[
        "kindergarten",
        "academic",
        "school"
    ],
    "wof:name":"Cornerstone Christian Academy",
    "wof:placetype":"venue"
},
  "geometry": {"coordinates":[-117.30086799999999,34.128747],"type":"Point"}
}