{
  "type": "Feature",
  "properties": {
    "addr:full":"1330 Howard Street San Francisco CA 94103",
    "addr:housenumber":"1330",
    "addr:postcode":"94103",
    "addr:street":"Howard Street",
    "iso:country":"US",
    "sg:address":"1330 Howard Street",
    "sg:city":"San Francisco",
    "sg:classifiers":[
        {
            "category":"Home & Garden",
            "subcategory":"Household Appliances",
            "type":"Retail Goods"
        }
    ],
    "sg:phone":"+1 415 621 6660",
    "sg:postcode":"94103",
    "sg:province":"CA",
    "sg:tags":[
        "repair"
    ],
    "sg:website":"www.buysewingmachines.com/",
    "wof:name":"Apparel City Sewing Machine",
    "wof:placetype":"venue"
},
  "geometry": {"coordinates":[-122.414001,37.7747],"type":"Point"}
}