{
  "type": "Feature",
  "properties": {
    "addr:full":"22952 Garzota Dr Valencia CA 91354",
    "addr:housenumber":"22952",
    "addr:postcode":"91354",
    "addr:street":"Garzota Dr",
    "iso:country":"US",
    "sg:address":"22952 Garzota Dr",
    "sg:city":"Valencia",
    "sg:classifiers":[
        {
            "category":"Wholesale",
            "subcategory":"Toys & Hobbies",
            "type":"Manufacturing & Wholesale Goods"
        }
    ],
    "sg:phone":"+1 661 297 0642",
    "sg:postcode":"91354",
    "sg:province":"CA",
    "wof:name":"Davids Wheels LLC",
    "wof:placetype":"venue"
},
  "geometry": {"coordinates":[-118.53764700000001,34.437025],"type":"Point"}
}