{
  "type": "Feature",
  "properties": {
    "iso:country":"US",
    "sg:address":"9039 Bolsa Ave",
    "sg:city":"Westminster",
    "sg:classifiers":[
        {
            "category":"Manufacturing",
            "subcategory":"Chemicals & Compounds",
            "type":"Manufacturing & Wholesale Goods"
        }
    ],
    "sg:phone":"+1 714 901 3389",
    "sg:postcode":"92683",
    "sg:province":"CA",
    "sg:tags":[
        "shop",
        "product",
        "beauty",
        "drug",
        "mfg"
    ],
    "wof:name":"Cellu-Derm",
    "wof:placetype":"venue"
},
  "geometry": {"coordinates":[-117.97049,33.744831],"type":"Point"}
}