{
  "type": "Feature",
  "properties": {
    "addr:full":"5100 N Figueroa Street Los Angeles CA 90042",
    "addr:housenumber":"5100",
    "addr:postcode":"90042",
    "addr:street":"N Figueroa Street",
    "iso:country":"US",
    "sg:address":"5100 N Figueroa Street",
    "sg:city":"Los Angeles",
    "sg:classifiers":[
        {
            "category":"Food & Beverages",
            "subcategory":"Groceries & Convenience Stores",
            "type":"Retail Goods"
        }
    ],
    "sg:phone":"+1 323 982 0304",
    "sg:postcode":"90042",
    "sg:province":"CA",
    "wof:name":"Food 4 Less",
    "wof:placetype":"venue"
},
  "geometry": {"coordinates":[-118.200512,34.10567],"type":"Point"}
}