{
  "type": "Feature",
  "properties": {
    "addr:full":"3333 14th St Riverside CA 92501",
    "addr:housenumber":"3333",
    "addr:postcode":"92501",
    "addr:street":"14Th St",
    "iso:country":"US",
    "sg:address":"3333 14th St",
    "sg:city":"Riverside",
    "sg:classifiers":[
        {
            "category":"Professional",
            "subcategory":"Lawyer & Legal Services",
            "type":"Services"
        }
    ],
    "sg:phone":"+1 951 683 2410",
    "sg:postcode":"92501",
    "sg:province":"CA",
    "sg:tags":[
        "attorney"
    ],
    "wof:name":"Kinkle Rodiger & Spriggs",
    "wof:placetype":"venue"
},
  "geometry": {"coordinates":[-117.374281,33.974354],"type":"Point"}
}