{
  "type": "Feature",
  "properties": {
    "addr:full":"5735 E Pacific Coast Hwy Long Beach CA 90803",
    "addr:housenumber":"5735",
    "addr:postcode":"90803",
    "addr:street":"E Pacific Coast Hwy",
    "iso:country":"US",
    "sg:address":"5735 E Pacific Coast Hwy",
    "sg:city":"Long Beach",
    "sg:classifiers":[
        {
            "category":"Restaurant",
            "type":"Food & Drink"
        }
    ],
    "sg:phone":"+1 562 981 8300",
    "sg:postcode":"90803",
    "sg:province":"CA",
    "sg:tags":[
        "caterer"
    ],
    "sg:website":"www.thebigthrill.net",
    "wof:name":"Blueberry Hill",
    "wof:placetype":"venue"
},
  "geometry": {"coordinates":[-118.119688,33.773198],"type":"Point"}
}