{
  "type": "Feature",
  "properties": {
    "addr:full":"725 Sunnyvale Saratoga Rd Sunnyvale CA 94087",
    "addr:housenumber":"725",
    "addr:postcode":"94087",
    "addr:street":"Sunnyvale Saratoga Rd",
    "iso:country":"US",
    "sg:address":"725 Sunnyvale Saratoga Rd",
    "sg:city":"Sunnyvale",
    "sg:classifiers":[
        {
            "category":"Restaurant",
            "type":"Food & Drink"
        }
    ],
    "sg:phone":"+1 408 720 1700",
    "sg:postcode":"94087",
    "sg:province":"CA",
    "wof:name":"Una Mas",
    "wof:placetype":"venue"
},
  "geometry": {"coordinates":[-122.032408,37.36686],"type":"Point"}
}