{
  "type": "Feature",
  "properties": {
    "addr:full":"17923 S Santa Fe Ave Compton CA 90221",
    "addr:housenumber":"17923",
    "addr:postcode":"90221",
    "addr:street":"S Santa Fe Ave",
    "iso:country":"US",
    "sg:address":"17923 S Santa Fe Ave",
    "sg:city":"Compton",
    "sg:classifiers":[
        {
            "category":"Freight",
            "type":"Transportation"
        }
    ],
    "sg:phone":"+1 310 537 8397",
    "sg:postcode":"90221",
    "sg:province":"CA",
    "sg:tags":[
        "local",
        "storage",
        "trucking"
    ],
    "wof:name":"Cal-West Express Company Ltd",
    "wof:placetype":"venue"
},
  "geometry": {"coordinates":[-118.212765,33.867432],"type":"Point"}
}