{
  "type": "Feature",
  "properties": {
    "addr:full":"21030 Davis Rd Lodi CA 95242",
    "addr:housenumber":"21030",
    "addr:postcode":"95242",
    "addr:street":"Davis Rd",
    "iso:country":"US",
    "sg:address":"21030 Davis Rd",
    "sg:city":"Lodi",
    "sg:classifiers":[
        {
            "category":"Farming",
            "subcategory":"Vineyard",
            "type":"Manufacturing & Wholesale Goods"
        }
    ],
    "sg:phone":"+1 209 333 1300",
    "sg:postcode":"95242",
    "sg:province":"CA",
    "sg:tags":[
        "grape"
    ],
    "wof:name":"Three Oak Vineyards",
    "wof:placetype":"venue"
},
  "geometry": {"coordinates":[-121.33468499999999,38.163201],"type":"Point"}
}