{
  "type": "Feature",
  "properties": {
    "iso:country":"US",
    "sg:address":"65 Cleary Ct",
    "sg:city":"San Francisco",
    "sg:classifiers":[
        {
            "category":"Professional",
            "type":"Services"
        },
        {
            "category":"Manufacturing",
            "subcategory":"Printing",
            "type":"Manufacturing & Wholesale Goods"
        }
    ],
    "sg:phone":"+1 415 775 3504",
    "sg:postcode":"94109",
    "sg:province":"CA",
    "sg:tags":[
        "arts",
        "artist"
    ],
    "wof:name":"Glenna Evans Photography",
    "wof:placetype":"venue"
},
  "geometry": {"coordinates":[-122.42634,37.784976],"type":"Point"}
}