{
  "type": "Feature",
  "properties": {
    "addr:full":"10400 Beaumont Ave Cherry Valley CA 92223",
    "addr:housenumber":"10400",
    "addr:postcode":"92223",
    "addr:street":"Beaumont Ave",
    "iso:country":"US",
    "sg:address":"10400 Beaumont Ave",
    "sg:city":"Cherry Valley",
    "sg:classifiers":[
        {
            "category":"Building & Trades",
            "subcategory":"Construction",
            "type":"Services"
        }
    ],
    "sg:phone":"+1 951 845 8023",
    "sg:postcode":"92223",
    "sg:province":"CA",
    "sg:tags":[
        "contractor"
    ],
    "wof:name":"Herling Construction",
    "wof:placetype":"venue"
},
  "geometry": {"coordinates":[-116.97712799999999,33.970218],"type":"Point"}
}