{
  "type": "Feature",
  "properties": {
    "addr:full":"16024 E 14th St San Leandro CA 94578",
    "addr:housenumber":"16024",
    "addr:postcode":"94578",
    "addr:street":"E 14Th St",
    "iso:country":"US",
    "sg:address":"16024 E 14th St",
    "sg:city":"San Leandro",
    "sg:classifiers":[
        {
            "category":"Bars & Pubs",
            "type":"Food & Drink"
        }
    ],
    "sg:phone":"+1 510 276 6203",
    "sg:postcode":"94578",
    "sg:province":"CA",
    "sg:tags":[
        "drinking"
    ],
    "wof:name":"Club Zamora",
    "wof:placetype":"venue"
},
  "geometry": {"coordinates":[-122.11903,37.698742],"type":"Point"}
}