{
  "type": "Feature",
  "properties": {
    "iso:country":"US",
    "sg:address":"3154 Campus Dr",
    "sg:city":"San Mateo",
    "sg:classifiers":[
        {
            "category":"Retail",
            "subcategory":"Portrait Studio",
            "type":"Services"
        }
    ],
    "sg:phone":"+1 650 573 3355",
    "sg:postcode":"94497",
    "sg:province":"CA",
    "sg:tags":[
        "photo"
    ],
    "wof:name":"Choice Photgraphic",
    "wof:placetype":"venue"
},
  "geometry": {"coordinates":[-122.327808,37.533614],"type":"Point"}
}