{
  "type": "Feature",
  "properties": {
    "iso:country":"US",
    "sg:address":"9158 Rosedale Dr",
    "sg:city":"Spring Valley",
    "sg:classifiers":[
        {
            "category":"Building & Trades",
            "subcategory":"Construction",
            "type":"Services"
        }
    ],
    "sg:phone":"+1 619 466 1922",
    "sg:postcode":"91977",
    "sg:province":"CA",
    "sg:tags":[
        "concrete",
        "cutting",
        "breaking",
        "sawing"
    ],
    "wof:name":"Danner Bobcat Svc",
    "wof:placetype":"venue"
},
  "geometry": {"coordinates":[-117.000305,32.736234],"type":"Point"}
}