{
  "type": "Feature",
  "properties": {
    "addr:full":"17038 Devonshire St Northridge CA 91325",
    "addr:housenumber":"17038",
    "addr:postcode":"91325",
    "addr:street":"Devonshire St",
    "iso:country":"US",
    "sg:address":"17038 Devonshire St",
    "sg:city":"Northridge",
    "sg:classifiers":[
        {
            "category":"Professional",
            "subcategory":"Computer Services",
            "type":"Services"
        }
    ],
    "sg:phone":"+1 818 363 3638",
    "sg:postcode":"91325",
    "sg:province":"CA",
    "sg:tags":[
        "internet"
    ],
    "wof:name":"Ntp",
    "wof:placetype":"venue"
},
  "geometry": {"coordinates":[-118.505681,34.25746],"type":"Point"}
}