{
  "type": "Feature",
  "properties": {
    "iso:country":"US",
    "sg:address":"1255 Fall Creek Way",
    "sg:city":"Sacramento",
    "sg:phone":"+1 916 719 7030",
    "sg:postcode":"95833",
    "sg:province":"CA",
    "wof:name":"Csg-Sjmcbride Enterprises",
    "wof:placetype":"venue"
},
  "geometry": {"coordinates":[-121.489199,38.619231],"type":"Point"}
}