{
  "type": "Feature",
  "properties": {
    "iso:country":"US",
    "sg:address":"2720 W Orangethorpe Ave",
    "sg:city":"Fullerton",
    "sg:classifiers":[
        {
            "category":"Restaurant",
            "type":"Food & Drink"
        }
    ],
    "sg:phone":"+1 714 879 9636",
    "sg:postcode":"92833",
    "sg:province":"CA",
    "wof:name":"Burger Town",
    "wof:placetype":"venue"
},
  "geometry": {"coordinates":[-117.975998,33.8592],"type":"Point"}
}