{
  "type": "Feature",
  "properties": {
    "addr:full":"606 E 1st St Los Angeles CA 90012",
    "addr:housenumber":"606",
    "addr:postcode":"90012",
    "addr:street":"E 1St St",
    "iso:country":"US",
    "sg:address":"606 E 1st St",
    "sg:city":"Los Angeles",
    "sg:classifiers":[
        {
            "category":"Wholesale",
            "subcategory":"Durable Goods & Equipment",
            "type":"Manufacturing & Wholesale Goods"
        }
    ],
    "sg:phone":"+1 213 625 2566",
    "sg:postcode":"90012",
    "sg:province":"CA",
    "sg:tags":[
        "importer"
    ],
    "wof:name":"Seafriend",
    "wof:placetype":"venue"
},
  "geometry": {"coordinates":[-118.23617,34.048655],"type":"Point"}
}