{
  "type": "Feature",
  "properties": {
    "iso:country":"US",
    "sg:address":"265 Broadway",
    "sg:city":"Chula Vista",
    "sg:classifiers":[
        {
            "category":"Home & Garden",
            "subcategory":"Building Materials",
            "type":"Retail Goods"
        }
    ],
    "sg:phone":"+1 619 427 3500",
    "sg:postcode":"91910",
    "sg:province":"CA",
    "sg:tags":[
        "glass",
        "window",
        "plate"
    ],
    "wof:name":"Low Price Auto Glass Co",
    "wof:placetype":"venue"
},
  "geometry": {"coordinates":[-117.092597,32.639283],"type":"Point"}
}