{
  "type": "Feature",
  "properties": {
    "addr:full":"4540 Oceanside Blvd Ste 159 Oceanside CA 92056",
    "addr:housenumber":"4540",
    "addr:postcode":"92056",
    "addr:street":"Oceanside Blvd Ste 159",
    "iso:country":"US",
    "sg:address":"4540 Oceanside Blvd Ste 159",
    "sg:city":"Oceanside",
    "sg:classifiers":[
        {
            "category":"Banks & Credit Unions",
            "subcategory":"Financial Services",
            "type":"Services"
        }
    ],
    "sg:phone":"+1 760 433 0259",
    "sg:postcode":"92056",
    "sg:province":"CA",
    "sg:tags":[
        "broker",
        "mortgage"
    ],
    "wof:name":"Smc Mortgage Processing",
    "wof:placetype":"venue"
},
  "geometry": {"coordinates":[-117.28800200000001,33.194199],"type":"Point"}
}