{
  "type": "Feature",
  "properties": {
    "addr:full":"605 G St Lincoln CA 95648",
    "addr:housenumber":"605",
    "addr:postcode":"95648",
    "addr:street":"G St",
    "iso:country":"US",
    "sg:address":"605 G St",
    "sg:city":"Lincoln",
    "sg:classifiers":[
        {
            "category":"Insurance",
            "subcategory":"Hazard Insurance",
            "type":"Services"
        }
    ],
    "sg:phone":"+1 916 434 8997",
    "sg:postcode":"95648",
    "sg:province":"CA",
    "sg:tags":[
        "commercial",
        "business"
    ],
    "sg:website":"http://www.farmers.com",
    "wof:name":"Smith Bill Insurance Agency",
    "wof:placetype":"venue"
},
  "geometry": {"coordinates":[-121.29284,38.893601],"type":"Point"}
}