{
  "type": "Feature",
  "properties": {
    "iso:country":"US",
    "sg:address":"939 Live Oak Blvd",
    "sg:city":"Yuba City",
    "sg:classifiers":[
        {
            "category":"Banks & Credit Unions",
            "subcategory":"Bank",
            "type":"Services"
        }
    ],
    "sg:phone":"+1 530 671 1420",
    "sg:postcode":"95991",
    "sg:province":"CA",
    "sg:tags":[
        "loan"
    ],
    "wof:name":"Federal Land Bank Assn",
    "wof:placetype":"venue"
},
  "geometry": {"coordinates":[-121.62076,39.142626],"type":"Point"}
}