{
  "type": "Feature",
  "properties": {
    "addr:full":"507 Polk St San Francisco CA 94102",
    "addr:housenumber":"507",
    "addr:postcode":"94102",
    "addr:street":"Polk St",
    "iso:country":"US",
    "sg:address":"507 Polk St",
    "sg:city":"San Francisco",
    "sg:classifiers":[
        {
            "category":"Professional",
            "type":"Services"
        }
    ],
    "sg:phone":"+1 415 409 1352",
    "sg:postcode":"94102",
    "sg:province":"CA",
    "wof:name":"In-Formed Mind",
    "wof:placetype":"venue"
},
  "geometry": {"coordinates":[-122.418808,37.781236],"type":"Point"}
}