{
  "type": "Feature",
  "properties": {
    "addr:full":"660 S Figueroa St Los Angeles CA 90017",
    "addr:housenumber":"660",
    "addr:postcode":"90017",
    "addr:street":"S Figueroa St",
    "iso:country":"US",
    "sg:address":"660 S Figueroa St",
    "sg:city":"Los Angeles",
    "sg:classifiers":[
        {
            "category":"Banks & Credit Unions",
            "subcategory":"Investment Brokerage",
            "type":"Services"
        }
    ],
    "sg:phone":"+1 714 236 0866",
    "sg:postcode":"90017",
    "sg:province":"CA",
    "sg:tags":[
        "advisory",
        "referral"
    ],
    "wof:name":"Quantus Investment Group",
    "wof:placetype":"venue"
},
  "geometry": {"coordinates":[-118.259591,34.049598],"type":"Point"}
}