{
  "type": "Feature",
  "properties": {
    "addr:full":"1107 Sandhurst Ln La Verne CA 91750",
    "addr:housenumber":"1107",
    "addr:postcode":"91750",
    "addr:street":"Sandhurst Ln",
    "iso:country":"US",
    "sg:address":"1107 Sandhurst Ln",
    "sg:city":"La Verne",
    "sg:classifiers":[
        {
            "category":"Wholesale",
            "subcategory":"Construction Materials",
            "type":"Manufacturing & Wholesale Goods"
        }
    ],
    "sg:phone":"+1 909 592 0908",
    "sg:postcode":"91750",
    "sg:province":"CA",
    "sg:tags":[
        "concrete",
        "brick",
        "broker",
        "block"
    ],
    "wof:name":"Curtiss Merrill Concrete",
    "wof:placetype":"venue"
},
  "geometry": {"coordinates":[-117.76964,34.145518],"type":"Point"}
}