{
  "type": "Feature",
  "properties": {
    "iso:country":"US",
    "sg:address":"1716 W Ave N-4",
    "sg:city":"Palmdale",
    "sg:classifiers":[
        {
            "category":"Manufacturing",
            "subcategory":"Chemicals & Compounds",
            "type":"Manufacturing & Wholesale Goods"
        }
    ],
    "sg:phone":"+1 661 273 9595",
    "sg:postcode":"93551",
    "sg:province":"CA",
    "sg:tags":[
        "industrial",
        "gas",
        "mfg"
    ],
    "wof:name":"Praxair",
    "wof:placetype":"venue"
},
  "geometry": {"coordinates":[-118.16123399999999,34.62736],"type":"Point"}
}