{
  "type": "Feature",
  "properties": {
    "iso:country":"US",
    "sg:address":"385 6th Ave",
    "sg:city":"City Of Industry",
    "sg:classifiers":[
        {
            "category":"Food & Beverages",
            "subcategory":"Groceries & Convenience Stores",
            "type":"Retail Goods"
        }
    ],
    "sg:phone":"+1 626 330 1250",
    "sg:postcode":"91746",
    "sg:province":"CA",
    "sg:tags":[
        "product"
    ],
    "wof:name":"CTC Food Intl",
    "wof:placetype":"venue"
},
  "geometry": {"coordinates":[-117.981547,34.034134],"type":"Point"}
}