{
  "type": "Feature",
  "properties": {
    "iso:country":"US",
    "sg:address":"390 S Green Valley Rd",
    "sg:city":"Watsonville",
    "sg:classifiers":[
        {
            "category":"Health Services",
            "subcategory":"Doctor",
            "type":"Services"
        }
    ],
    "sg:phone":"+1 831 722 4106",
    "sg:postcode":"95076",
    "sg:province":"CA",
    "sg:tags":[
        "dentist"
    ],
    "wof:name":"Oral Health Fitness Ctr",
    "wof:placetype":"venue"
},
  "geometry": {"coordinates":[-121.77570299999999,36.932646],"type":"Point"}
}