{
  "type": "Feature",
  "properties": {
    "iso:country":"US",
    "sg:address":"1600 Quail Trl",
    "sg:city":"Brentwood",
    "sg:classifiers":[
        {
            "category":"Insurance",
            "subcategory":"Hazard Insurance",
            "type":"Services"
        }
    ],
    "sg:phone":"+1 925 470 8888",
    "sg:postcode":"94513",
    "sg:province":"CA",
    "sg:tags":[
        "commercial",
        "business"
    ],
    "wof:name":"Erickson Insurance",
    "wof:placetype":"venue"
},
  "geometry": {"coordinates":[-121.65518899999999,37.950069],"type":"Point"}
}