{
  "type": "Feature",
  "properties": {
    "addr:full":"26612 Towne Centre Dr Foothill Ranch CA 92610",
    "addr:housenumber":"26612",
    "addr:postcode":"92610",
    "addr:street":"Towne Centre Dr",
    "iso:country":"US",
    "sg:address":"26612 Towne Centre Dr",
    "sg:city":"Foothill Ranch",
    "sg:classifiers":[
        {
            "category":"Food & Beverages",
            "subcategory":"Bakery",
            "type":"Retail Goods"
        }
    ],
    "sg:phone":"+1 949 461 7070",
    "sg:postcode":"92610",
    "sg:province":"CA",
    "sg:tags":[
        "sandwich"
    ],
    "sg:website":"www.togos.com/",
    "wof:name":"Togo's",
    "wof:placetype":"venue"
},
  "geometry": {"coordinates":[-117.667445,33.675883],"type":"Point"}
}