{
  "type": "Feature",
  "properties": {
    "iso:country":"US",
    "sg:address":"1888 Collinsville Rd",
    "sg:city":"Birds Landing",
    "sg:classifiers":[
        {
            "category":"Building & Trades",
            "subcategory":"Landscaping Services",
            "type":"Services"
        }
    ],
    "sg:phone":"+1 707 374 5837",
    "sg:postcode":"94512",
    "sg:province":"CA",
    "wof:name":"Lancaster Landscape & Design",
    "wof:placetype":"venue"
},
  "geometry": {"coordinates":[-121.867958,38.12062],"type":"Point"}
}