{
  "type": "Feature",
  "properties": {
    "iso:country":"US",
    "sg:address":"1051 Foothill Blvd",
    "sg:city":"La Canada Fltrdg",
    "sg:classifiers":[
        {
            "category":"Personal",
            "subcategory":"Beauty Salon",
            "type":"Services"
        }
    ],
    "sg:phone":"+1 818 790 0189",
    "sg:postcode":"91011",
    "sg:province":"CA",
    "wof:name":"D J Beauty Health Ctr",
    "wof:placetype":"venue"
},
  "geometry": {"coordinates":[-118.200292,34.204559],"type":"Point"}
}