{
  "type": "Feature",
  "properties": {
    "iso:country":"US",
    "sg:address":"1341 W Robinhood Dr",
    "sg:city":"Stockton",
    "sg:classifiers":[
        {
            "category":"Professional",
            "type":"Services"
        }
    ],
    "sg:phone":"+1 209 475 4840",
    "sg:postcode":"95207",
    "sg:province":"CA",
    "sg:tags":[
        "establishment"
    ],
    "wof:name":"BMTI",
    "wof:placetype":"venue"
},
  "geometry": {"coordinates":[-121.32439100000001,37.998493],"type":"Point"}
}