{
  "type": "Feature",
  "properties": {
    "addr:full":"12235 Heacock St Moreno Valley CA 92557",
    "addr:housenumber":"12235",
    "addr:postcode":"92557",
    "addr:street":"Heacock St",
    "iso:country":"US",
    "sg:address":"12235 Heacock St",
    "sg:city":"Moreno Valley",
    "sg:classifiers":[
        {
            "category":"Personal",
            "subcategory":"Beauty Salon",
            "type":"Services"
        }
    ],
    "sg:phone":"+1 951 247 9999",
    "sg:postcode":"92557",
    "sg:province":"CA",
    "sg:tags":[
        "manicuring"
    ],
    "wof:name":"Pro Nail & Hair",
    "wof:placetype":"venue"
},
  "geometry": {"coordinates":[-117.24384000000001,33.9466],"type":"Point"}
}