{
  "type": "Feature",
  "properties": {
    "iso:country":"US",
    "sg:address":"20006 W Ave F",
    "sg:city":"Lancaster",
    "sg:classifiers":[
        {
            "category":"Home & Garden",
            "subcategory":"Building Materials",
            "type":"Retail Goods"
        }
    ],
    "sg:phone":"+1 661 724 1416",
    "sg:postcode":"93536",
    "sg:province":"CA",
    "sg:tags":[
        "glass",
        "window",
        "plate"
    ],
    "wof:name":"Commercial Glass Systems",
    "wof:placetype":"venue"
},
  "geometry": {"coordinates":[-118.48671899999999,34.747531],"type":"Point"}
}