{
  "type": "Feature",
  "properties": {
    "addr:full":"15592 Larch St Hesperia CA 92345",
    "addr:housenumber":"15592",
    "addr:postcode":"92345",
    "addr:street":"Larch St",
    "iso:country":"US",
    "sg:address":"15592 Larch St",
    "sg:city":"Hesperia",
    "sg:classifiers":[
        {
            "category":"Building & Trades",
            "subcategory":"Electrical",
            "type":"Services"
        }
    ],
    "sg:phone":"+1 760 949 2611",
    "sg:postcode":"92345",
    "sg:province":"CA",
    "sg:tags":[
        "electrician"
    ],
    "wof:name":"Flores Electric",
    "wof:placetype":"venue"
},
  "geometry": {"coordinates":[-117.322245,34.388813],"type":"Point"}
}