{
  "type": "Feature",
  "properties": {
    "iso:country":"US",
    "sg:address":"125 Hangar Way",
    "sg:city":"Watsonville",
    "sg:classifiers":[
        {
            "category":"Personal",
            "type":"Services"
        },
        {
            "category":"Professional",
            "subcategory":"Detective & Security Services",
            "type":"Services"
        },
        {
            "category":"Manufacturing",
            "subcategory":"Building Materials",
            "type":"Manufacturing & Wholesale Goods"
        }
    ],
    "sg:phone":"+1 831 786 9981",
    "sg:postcode":"95076",
    "sg:province":"CA",
    "sg:tags":[
        "control",
        "monitoring",
        "fire",
        "alarm",
        "system",
        "systems-wholesale",
        "medical",
        "manufacturer"
    ],
    "wof:name":"Strawberry Business Center Owners Association",
    "wof:placetype":"venue"
},
  "geometry": {"coordinates":[-121.790871,36.927145],"type":"Point"}
}