{
  "type": "Feature",
  "properties": {
    "iso:country":"US",
    "sg:address":"2102 Walsh Ave",
    "sg:city":"Santa Clara",
    "sg:classifiers":[
        {
            "category":"Professional",
            "subcategory":"Research",
            "type":"Services"
        }
    ],
    "sg:phone":"+1 408 748 1046",
    "sg:postcode":"95050",
    "sg:province":"CA",
    "sg:tags":[
        "development",
        "laboratory"
    ],
    "wof:name":"Kimia Corp",
    "wof:placetype":"venue"
},
  "geometry": {"coordinates":[-121.961453,37.369393],"type":"Point"}
}