{
  "type": "Feature",
  "properties": {
    "iso:country":"US",
    "sg:address":"1480 Fruitvale Ave",
    "sg:city":"Oakland",
    "sg:classifiers":[
        {
            "category":"Health Services",
            "subcategory":"Health Practitioner",
            "type":"Services"
        }
    ],
    "sg:phone":"+1 510 534 5600",
    "sg:postcode":"94601",
    "sg:province":"CA",
    "sg:tags":[
        "medicine",
        "alternative"
    ],
    "wof:name":"Clinica LA Luna Ey El Sol",
    "wof:placetype":"venue"
},
  "geometry": {"coordinates":[-122.225289,37.778476],"type":"Point"}
}