{
  "type": "Feature",
  "properties": {
    "addr:full":"2537 Murrell Rd Santa Barbara CA 93109",
    "addr:housenumber":"2537",
    "addr:postcode":"93109",
    "addr:street":"Murrell Rd",
    "iso:country":"US",
    "sg:address":"2537 Murrell Rd",
    "sg:city":"Santa Barbara",
    "sg:classifiers":[
        {
            "category":"Professional",
            "type":"Services"
        }
    ],
    "sg:phone":"+1 805 965 2937",
    "sg:postcode":"93109",
    "sg:province":"CA",
    "wof:name":"Olin Bausback",
    "wof:placetype":"venue"
},
  "geometry": {"coordinates":[-119.732642,34.402187],"type":"Point"}
}