{
  "type": "Feature",
  "properties": {
    "addr:full":"7880 Brentwood Blvd Brentwood CA 94513",
    "addr:housenumber":"7880",
    "addr:postcode":"ca 94513",
    "addr:street":"Brentwood Blvd",
    "iso:country":"US",
    "sg:address":"7880 Brentwood Blvd",
    "sg:city":"Brentwood",
    "sg:classifiers":[
        {
            "category":"Personal",
            "subcategory":"Beauty Salon",
            "type":"Services"
        }
    ],
    "sg:phone":"+1 925 240 1580",
    "sg:postcode":"94513",
    "sg:province":"CA",
    "wof:name":"Genesis Beauty Salon",
    "wof:placetype":"venue"
},
  "geometry": {"coordinates":[-121.69618199999999,37.941677],"type":"Point"}
}