{
  "type": "Feature",
  "properties": {
    "iso:country":"US",
    "sg:address":"4764 Park Granada",
    "sg:city":"Calabasas",
    "sg:classifiers":[
        {
            "category":"Arts & Performance",
            "subcategory":"Theater",
            "type":"Entertainment"
        }
    ],
    "sg:phone":"+1 818 222 9000",
    "sg:postcode":"91302",
    "sg:province":"CA",
    "sg:tags":[
        "television",
        "program",
        "producer"
    ],
    "wof:name":"Planet Pictures",
    "wof:placetype":"venue"
},
  "geometry": {"coordinates":[-118.642449,34.154695],"type":"Point"}
}