{
  "type": "Feature",
  "properties": {
    "addr:full":"511 Pier Ave Santa Monica CA 90405",
    "addr:housenumber":"511",
    "addr:postcode":"90405",
    "addr:street":"Pier Ave",
    "iso:country":"US",
    "sg:address":"511 Pier Ave",
    "sg:city":"Santa Monica",
    "sg:classifiers":[
        {
            "category":"Organizations",
            "subcategory":"Non-profit Organization",
            "type":"Services"
        }
    ],
    "sg:phone":"+1 310 396 0166",
    "sg:postcode":"90405",
    "sg:province":"CA",
    "sg:tags":[
        "charitable",
        "institution"
    ],
    "wof:name":"Guam Communications Network",
    "wof:placetype":"venue"
},
  "geometry": {"coordinates":[-118.477087,34.001142],"type":"Point"}
}