{
  "type": "Feature",
  "properties": {
    "iso:country":"US",
    "sg:address":"69115 Ramon Rd Ste F3",
    "sg:city":"Cathedral City",
    "sg:classifiers":[
        {
            "category":"Shopping",
            "subcategory":"Beauty & Cosmetics",
            "type":"Retail Goods"
        }
    ],
    "sg:phone":"+1 760 324 3145",
    "sg:postcode":"92234",
    "sg:province":"CA",
    "sg:tags":[
        "supply"
    ],
    "wof:name":"Nail & Beauty Emporium",
    "wof:placetype":"venue"
},
  "geometry": {"coordinates":[-116.45721500000001,33.813842],"type":"Point"}
}