{
  "type": "Feature",
  "properties": {
    "addr:full":"222 Broadway San Diego CA 92101",
    "addr:housenumber":"222",
    "addr:postcode":"92101",
    "addr:street":"Broadway",
    "iso:country":"US",
    "sg:address":"222 Broadway",
    "sg:city":"San Diego",
    "sg:classifiers":[
        {
            "category":"Travel",
            "subcategory":"Travel Agent",
            "type":"Entertainment"
        }
    ],
    "sg:phone":"+1 619 238 7100",
    "sg:postcode":"92101",
    "sg:province":"CA",
    "sg:tags":[
        "agency"
    ],
    "wof:name":"Uniglobe Signature Travel",
    "wof:placetype":"venue"
},
  "geometry": {"coordinates":[-117.162189,32.715778],"type":"Point"}
}