{
  "type": "Feature",
  "properties": {
    "iso:country":"US",
    "sg:address":"1605 W Holt Ave",
    "sg:city":"Pomona",
    "sg:classifiers":[
        {
            "category":"Personal",
            "subcategory":"Beauty Salon",
            "type":"Services"
        }
    ],
    "sg:phone":"+1 909 629 0836",
    "sg:postcode":"91768",
    "sg:province":"CA",
    "wof:name":"Lourdes Beauty Salon",
    "wof:placetype":"venue"
},
  "geometry": {"coordinates":[-117.778783,34.061745],"type":"Point"}
}