{
  "type": "Feature",
  "properties": {
    "iso:country":"US",
    "sg:address":"201 San Antonio Rd",
    "sg:city":"Mountain View",
    "sg:classifiers":[
        {
            "category":"Social Services",
            "type":"Services"
        }
    ],
    "sg:phone":"+1 650 941 2212",
    "sg:postcode":"94040",
    "sg:province":"CA",
    "sg:tags":[
        "counselor",
        "marriage",
        "family"
    ],
    "wof:name":"Bay Counseling & Consulting",
    "wof:placetype":"venue"
},
  "geometry": {"coordinates":[-122.108895,37.407542],"type":"Point"}
}