{
  "type": "Feature",
  "properties": {
    "iso:country":"US",
    "sg:address":"1030 3rd Ave",
    "sg:city":"Chula Vista",
    "sg:classifiers":[
        {
            "category":"Banks & Credit Unions",
            "subcategory":"Bank",
            "type":"Services"
        }
    ],
    "sg:phone":"+1 619 426 5691",
    "sg:postcode":"91911",
    "sg:province":"CA",
    "sg:tags":[
        "banking",
        "system"
    ],
    "wof:name":"Electronic Funds Transfer",
    "wof:placetype":"venue"
},
  "geometry": {"coordinates":[-117.06912199999999,32.61351],"type":"Point"}
}