{
  "type": "Feature",
  "properties": {
    "addr:full":"6837 Farmdale Ave North Hollywood CA 91606",
    "addr:housenumber":"6837",
    "addr:postcode":"91606",
    "addr:street":"Farmdale Ave",
    "iso:country":"US",
    "sg:address":"6837 Farmdale Ave",
    "sg:city":"North Hollywood",
    "sg:classifiers":[
        {
            "category":"Professional",
            "type":"Services"
        }
    ],
    "sg:phone":"+1 818 765 7266",
    "sg:postcode":"91606",
    "sg:province":"CA",
    "sg:tags":[
        "establishment"
    ],
    "sg:website":"www.pacificmagnetic.com",
    "wof:name":"Pacific Mag & Penetrant Co",
    "wof:placetype":"venue"
},
  "geometry": {"coordinates":[-118.38122799999999,34.197567],"type":"Point"}
}