{
  "type": "Feature",
  "properties": {
    "iso:country":"US",
    "sg:address":"1663 Spring Valley Rd",
    "sg:city":"Clearlake Oaks",
    "sg:classifiers":[
        {
            "category":"Farming",
            "subcategory":"Livestock Farm",
            "type":"Manufacturing & Wholesale Goods"
        }
    ],
    "sg:phone":"+1 530 473 2402",
    "sg:postcode":"95423",
    "sg:province":"CA",
    "sg:tags":[
        "ranch"
    ],
    "wof:name":"Gillott Ranches",
    "wof:placetype":"venue"
},
  "geometry": {"coordinates":[-122.587688,39.05525],"type":"Point"}
}