{
  "type": "Feature",
  "properties": {
    "addr:full":"778 Sage Dr Vacaville CA 95687",
    "addr:housenumber":"778",
    "addr:postcode":"95687",
    "addr:street":"Sage Dr",
    "iso:country":"US",
    "sg:address":"778 Sage Dr",
    "sg:city":"Vacaville",
    "sg:classifiers":[
        {
            "category":"Freight",
            "type":"Transportation"
        }
    ],
    "sg:phone":"+1 707 452 8595",
    "sg:postcode":"95687",
    "sg:province":"CA",
    "sg:tags":[
        "hauling",
        "trucking"
    ],
    "wof:name":"Holler For Hauling",
    "wof:placetype":"venue"
},
  "geometry": {"coordinates":[-121.959926,38.323908],"type":"Point"}
}