{
  "type": "Feature",
  "properties": {
    "addr:full":"11827 Birchville Rd Nevada City CA 95960",
    "addr:housenumber":"11827",
    "addr:postcode":"95960",
    "addr:street":"Birchville Rd",
    "iso:country":"US",
    "sg:address":"11827 Birchville Rd",
    "sg:city":"Nevada City",
    "sg:classifiers":[
        {
            "category":"Farming",
            "subcategory":"Farm",
            "type":"Manufacturing & Wholesale Goods"
        }
    ],
    "sg:phone":"+1 530 277 5998",
    "sg:postcode":"95960",
    "sg:province":"CA",
    "wof:name":"Redbud Farm",
    "wof:placetype":"venue"
},
  "geometry": {"coordinates":[-121.14810300000001,39.318546],"type":"Point"}
}