{
  "type": "Feature",
  "properties": {
    "addr:full":"1551 W Redondo Beach Blvd Gardena CA 90247",
    "addr:housenumber":"1551",
    "addr:postcode":"90247",
    "addr:street":"W Redondo Beach Blvd",
    "iso:country":"US",
    "sg:address":"1551 W Redondo Beach Blvd",
    "sg:city":"Gardena",
    "sg:classifiers":[
        {
            "category":"Health Services",
            "subcategory":"Health Practitioner",
            "type":"Services"
        }
    ],
    "sg:phone":"+1 310 327 0093",
    "sg:postcode":"90247",
    "sg:province":"CA",
    "sg:tags":[
        "paramedic"
    ],
    "wof:name":"EMSI-Exam 1",
    "wof:placetype":"venue"
},
  "geometry": {"coordinates":[-118.303459,33.890491],"type":"Point"}
}