{
  "type": "Feature",
  "properties": {
    "addr:full":"747 N Lake Ave Pasadena CA 91104",
    "addr:housenumber":"747",
    "addr:postcode":"91104",
    "addr:street":"N Lake Ave",
    "iso:country":"US",
    "sg:address":"747 N Lake Ave",
    "sg:city":"Pasadena",
    "sg:classifiers":[
        {
            "category":"Real Estate",
            "subcategory":"Real Estate Agent",
            "type":"Services"
        }
    ],
    "sg:phone":"+1 626 798 4607",
    "sg:postcode":"91104",
    "sg:province":"CA",
    "sg:tags":[
        "management"
    ],
    "wof:name":"Master",
    "wof:placetype":"venue"
},
  "geometry": {"coordinates":[-118.132546,34.158747],"type":"Point"}
}