{
  "type": "Feature",
  "properties": {
    "iso:country":"US",
    "sg:address":"3356 Yorba Linda Blvd",
    "sg:city":"Fullerton",
    "sg:classifiers":[
        {
            "category":"Arena",
            "subcategory":"Sports Club",
            "type":"Entertainment"
        }
    ],
    "sg:phone":"+1 714 792 0449",
    "sg:postcode":"92831",
    "sg:province":"CA",
    "sg:tags":[
        "martial art"
    ],
    "wof:name":"United Studios of Self Defense",
    "wof:placetype":"venue"
},
  "geometry": {"coordinates":[-117.86599699999999,33.888],"type":"Point"}
}