{
  "type": "Feature",
  "properties": {
    "iso:country":"US",
    "sg:address":"2220 Ariano Ln",
    "sg:city":"Ceres",
    "sg:classifiers":[
        {
            "category":"Building & Trades",
            "subcategory":"Plumbing",
            "type":"Services"
        }
    ],
    "sg:phone":"+1 209 410 2902",
    "sg:postcode":"95307",
    "sg:province":"CA",
    "wof:name":"California Drain Rooter & Plumbing",
    "wof:placetype":"venue"
},
  "geometry": {"coordinates":[-120.924336,37.596641],"type":"Point"}
}