{
  "type": "Feature",
  "properties": {
    "addr:full":"9065 Hearst Dr San Simeon CA 93452",
    "addr:housenumber":"9065",
    "addr:postcode":"93452",
    "addr:street":"Hearst Dr",
    "iso:country":"US",
    "sg:address":"9065 Hearst Dr",
    "sg:city":"San Simeon",
    "sg:classifiers":[
        {
            "category":"Travel",
            "subcategory":"Hotels & Motels",
            "type":"Entertainment"
        }
    ],
    "sg:phone":"+1 805 927 3284",
    "sg:postcode":"93452",
    "sg:province":"CA",
    "sg:tags":[
        "operation"
    ],
    "sg:website":"www.seabreezeinnsansimeon.com/",
    "wof:name":"Sea Breeze Inn",
    "wof:placetype":"venue"
},
  "geometry": {"coordinates":[-121.144997,35.613201],"type":"Point"}
}