{
  "type": "Feature",
  "properties": {
    "iso:country":"US",
    "sg:address":"1675 Rollins Rd",
    "sg:city":"Burlingame",
    "sg:classifiers":[
        {
            "category":"Health Services",
            "subcategory":"Medical Lab",
            "type":"Services"
        }
    ],
    "sg:phone":"+1 650 697 8320",
    "sg:postcode":"94010",
    "sg:province":"CA",
    "sg:tags":[
        "laboratory"
    ],
    "wof:name":"Felipe's Dental Lab",
    "wof:placetype":"venue"
},
  "geometry": {"coordinates":[-122.377804,37.596597],"type":"Point"}
}