{
  "type": "Feature",
  "properties": {
    "iso:country":"US",
    "sg:address":"1022-1024 22nd St",
    "sg:city":"Sacramento",
    "sg:classifiers":[
        {
            "category":"Arts & Performance",
            "subcategory":"Art Gallery",
            "type":"Entertainment"
        }
    ],
    "sg:phone":"+1 916 446 5133",
    "sg:postcode":"95857",
    "sg:province":"CA",
    "sg:website":"www.larazagaleriaposada.org/",
    "wof:name":"La Raza Galeria Posada",
    "wof:placetype":"venue"
},
  "geometry": {"coordinates":[-121.477594,38.575142],"type":"Point"}
}