{
  "type": "Feature",
  "properties": {
    "addr:full":"5121 Seabreeze Way Oxnard CA 93035",
    "addr:housenumber":"5121",
    "addr:postcode":"93035",
    "addr:street":"Seabreeze Way",
    "iso:country":"US",
    "sg:address":"5121 Seabreeze Way",
    "sg:city":"Oxnard",
    "sg:classifiers":[
        {
            "category":"Professional",
            "subcategory":"Business Services",
            "type":"Services"
        }
    ],
    "sg:phone":"+1 805 985 1460",
    "sg:postcode":"93035",
    "sg:province":"CA",
    "sg:tags":[
        "inspection"
    ],
    "wof:name":"Morrissey Home Inspection",
    "wof:placetype":"venue"
},
  "geometry": {"coordinates":[-119.240989,34.192874],"type":"Point"}
}