{
  "type": "Feature",
  "properties": {
    "addr:full":"6001 20th St Riverside CA 92509",
    "addr:housenumber":"6001",
    "addr:postcode":"92509",
    "addr:street":"20Th St",
    "iso:country":"US",
    "sg:address":"6001 20th St",
    "sg:city":"Riverside",
    "sg:classifiers":[
        {
            "category":"Wholesale",
            "subcategory":"Motor Vehicles",
            "type":"Manufacturing & Wholesale Goods"
        }
    ],
    "sg:phone":"+1 951 680 9400",
    "sg:postcode":"92509",
    "sg:province":"CA",
    "sg:tags":[
        "recreational"
    ],
    "wof:name":"Flounder Motor Homes",
    "wof:placetype":"venue"
},
  "geometry": {"coordinates":[-117.39571599999999,34.020903],"type":"Point"}
}