{
  "type": "Feature",
  "properties": {
    "iso:country":"US",
    "sg:address":"6001 20th St",
    "sg:city":"Riverside",
    "sg:classifiers":[
        {
            "category":"Wholesale",
            "subcategory":"Motor Vehicles",
            "type":"Manufacturing & Wholesale Goods"
        }
    ],
    "sg:phone":"+1 951 680 9400",
    "sg:postcode":"92509",
    "sg:province":"CA",
    "sg:tags":[
        "recreational"
    ],
    "wof:name":"Flounder Motor Homes",
    "wof:placetype":"venue"
},
  "geometry": {"coordinates":[-117.395716,34.020903],"type":"Point"}
}