{
  "type": "Feature",
  "properties": {
    "iso:country":"US",
    "sg:address":"2883 E Gage Avenue",
    "sg:city":"Huntington Park",
    "sg:classifiers":[
        {
            "category":"Insurance",
            "subcategory":"Health Insurance",
            "type":"Services"
        }
    ],
    "sg:phone":"+1 323 583 6108",
    "sg:postcode":"90255",
    "sg:province":"CA",
    "sg:tags":[
        "market"
    ],
    "wof:name":"Baby's Nutrition",
    "wof:placetype":"venue"
},
  "geometry": {"coordinates":[-118.21811599999999,33.981506],"type":"Point"}
}