{
  "type": "Feature",
  "properties": {
    "iso:country":"US",
    "sg:address":"7576 Winnetka Ave",
    "sg:city":"Canoga Park",
    "sg:classifiers":[
        {
            "category":"Shopping",
            "subcategory":"Computers & Home Electronics",
            "type":"Retail Goods"
        }
    ],
    "sg:phone":"+1 818 886 9200",
    "sg:postcode":"91306",
    "sg:province":"CA",
    "wof:name":"Global Communications",
    "wof:placetype":"venue"
},
  "geometry": {"coordinates":[-118.570834,34.20788],"type":"Point"}
}