{
  "type": "Feature",
  "properties": {
    "addr:full":"3670 The Barnyard Carmel CA 93923",
    "addr:housenumber":"3670",
    "addr:postcode":"93923",
    "addr:street":"The Barnyard",
    "iso:country":"US",
    "sg:address":"3670 The Barnyard",
    "sg:city":"Carmel",
    "sg:classifiers":[
        {
            "category":"Restaurant",
            "type":"Food & Drink"
        }
    ],
    "sg:phone":"+1 831 626 3779",
    "sg:postcode":"93923",
    "sg:province":"CA",
    "sg:tags":[
        "french"
    ],
    "sg:website":"swissbistro.com/",
    "wof:name":"Lugano Swiss Bistro",
    "wof:placetype":"venue"
},
  "geometry": {"coordinates":[-121.906983,36.540258],"type":"Point"}
}