{
  "type": "Feature",
  "properties": {
    "addr:full":"901 Lincoln Ave San Jose CA 95126",
    "addr:housenumber":"901",
    "addr:postcode":"95126",
    "addr:street":"Lincoln Ave",
    "iso:country":"US",
    "sg:address":"901 Lincoln Ave",
    "sg:city":"San Jose",
    "sg:classifiers":[
        {
            "category":"Organizations",
            "subcategory":"Religious Organization",
            "type":"Services"
        }
    ],
    "sg:phone":"+1 408 279 0279",
    "sg:postcode":"95126",
    "sg:province":"CA",
    "sg:tags":[
        "church"
    ],
    "wof:name":"Croatian Catholic Mission",
    "wof:placetype":"venue"
},
  "geometry": {"coordinates":[-121.904467,37.312915],"type":"Point"}
}