{
  "type": "Feature",
  "properties": {
    "addr:full":"712 W 1st St Los Angeles CA 90012",
    "addr:housenumber":"712",
    "addr:postcode":"90012",
    "addr:street":"W 1St St",
    "iso:country":"US",
    "sg:address":"712 W 1st St",
    "sg:city":"Los Angeles",
    "sg:classifiers":[
        {
            "category":"Insurance",
            "subcategory":"Hazard Insurance",
            "type":"Services"
        }
    ],
    "sg:phone":"+1 213 225 0655",
    "sg:postcode":"90012",
    "sg:province":"CA",
    "sg:website":"www.ramonsinsurance.com",
    "wof:name":"Ramon Pantoja - State Farm Insurance",
    "wof:placetype":"venue"
},
  "geometry": {"coordinates":[-118.250388,34.056702],"type":"Point"}
}