{
  "type": "Feature",
  "properties": {
    "iso:country":"US",
    "sg:address":"3801 E Slauson Ave",
    "sg:city":"Maywood",
    "sg:classifiers":[
        {
            "category":"Organizations",
            "subcategory":"Religious Organization",
            "type":"Services"
        }
    ],
    "sg:phone":"+1 323 582 8547",
    "sg:postcode":"90270",
    "sg:province":"CA",
    "sg:tags":[
        "church"
    ],
    "wof:name":"Iglesia Betania",
    "wof:placetype":"venue"
},
  "geometry": {"coordinates":[-118.194397,33.988056],"type":"Point"}
}