{
  "type": "Feature",
  "properties": {
    "addr:full":"1271 Treat St San Francisco CA 94110",
    "addr:housenumber":"1271",
    "addr:postcode":"94110",
    "addr:street":"Treat St",
    "iso:country":"US",
    "sg:address":"1271 Treat St",
    "sg:city":"San Francisco",
    "sg:classifiers":[
        {
            "category":"Sports & Exercise",
            "subcategory":"Swimming Pool",
            "type":"Entertainment"
        }
    ],
    "sg:phone":"+1 415 695 5001",
    "sg:postcode":"94110",
    "sg:province":"CA",
    "sg:website":"www.parks.sfgov.org/wcm_recpark/...",
    "wof:name":"Garfield Swimming Pool",
    "wof:placetype":"venue"
},
  "geometry": {"coordinates":[-122.41272600000001,37.749847],"type":"Point"}
}