{
  "type": "Feature",
  "properties": {
    "addr:full":"41658 Big Bear Blvd Big Bear Lake CA 92314",
    "addr:housenumber":"41658",
    "addr:postcode":"92314",
    "addr:street":"Big Bear Blvd",
    "iso:country":"US",
    "sg:address":"41658 Big Bear Blvd",
    "sg:city":"Big Bear Lake",
    "sg:classifiers":[
        {
            "category":"Manufacturing",
            "subcategory":"Tools & Machinery",
            "type":"Manufacturing & Wholesale Goods"
        }
    ],
    "sg:phone":"+1 909 866 8884",
    "sg:postcode":"92314",
    "sg:province":"CA",
    "sg:tags":[
        "search"
    ],
    "sg:website":"www.ollilaindustries.com",
    "wof:name":"Ollila Industries",
    "wof:placetype":"venue"
},
  "geometry": {"coordinates":[-116.893225,34.243493],"type":"Point"}
}