{
  "type": "Feature",
  "properties": {
    "addr:full":"1625 Schrader Blvd Los Angeles CA 90028",
    "addr:housenumber":"1625",
    "addr:postcode":"90028",
    "addr:street":"Schrader Blvd",
    "iso:country":"US",
    "sg:address":"1625 Schrader Blvd",
    "sg:city":"Los Angeles",
    "sg:classifiers":[
        {
            "category":"Professional",
            "type":"Services"
        }
    ],
    "sg:phone":"+1 323 860 7302",
    "sg:postcode":"90028",
    "sg:province":"CA",
    "sg:tags":[
        "establishment"
    ],
    "wof:name":"Village At Ed Gould Plaza",
    "wof:placetype":"venue"
},
  "geometry": {"coordinates":[-118.33255200000001,34.101138],"type":"Point"}
}