{
  "type": "Feature",
  "properties": {
    "addr:full":"2209 California St Stockton CA 95204",
    "addr:housenumber":"2209",
    "addr:postcode":"95204",
    "addr:street":"California St",
    "iso:country":"US",
    "sg:address":"2209 California St",
    "sg:city":"Stockton",
    "sg:classifiers":[
        {
            "category":"Health Services",
            "subcategory":"Doctor",
            "type":"Services"
        }
    ],
    "sg:phone":"+1 209 943 0305",
    "sg:postcode":"95204",
    "sg:province":"CA",
    "sg:tags":[
        "physician",
        "surgeon"
    ],
    "wof:name":"F Karl Gregorius Inc",
    "wof:placetype":"venue"
},
  "geometry": {"coordinates":[-121.29055099999999,37.974141],"type":"Point"}
}