{
  "type": "Feature",
  "properties": {
    "addr:full":"7277 Hayvenhurst Ave Van Nuys CA 91406",
    "addr:housenumber":"7277",
    "addr:postcode":"91406",
    "addr:street":"Hayvenhurst Ave",
    "iso:country":"US",
    "sg:address":"7277 Hayvenhurst Ave",
    "sg:city":"Van Nuys",
    "sg:classifiers":[
        {
            "category":"Wholesale",
            "subcategory":"Jewelry",
            "type":"Manufacturing & Wholesale Goods"
        }
    ],
    "sg:phone":"+1 818 785 3376",
    "sg:postcode":"91406",
    "sg:province":"CA",
    "sg:tags":[
        "clocks"
    ],
    "sg:website":"www.timezonestore.com",
    "wof:name":"Timezone Co",
    "wof:placetype":"venue"
},
  "geometry": {"coordinates":[-118.492733,34.202174],"type":"Point"}
}