{
  "type": "Feature",
  "properties": {
    "addr:full":"13031 San Antonio Dr Norwalk CA 90650",
    "addr:housenumber":"13031",
    "addr:postcode":"90650",
    "addr:street":"San Antonio Dr",
    "iso:country":"US",
    "sg:address":"13031 San Antonio Dr",
    "sg:city":"Norwalk",
    "sg:classifiers":[
        {
            "category":"Health Services",
            "subcategory":"Clinic",
            "type":"Services"
        }
    ],
    "sg:phone":"+1 562 929 3100",
    "sg:postcode":"90650",
    "sg:province":"CA",
    "sg:tags":[
        "home",
        "care"
    ],
    "wof:name":"Bev 2001 Health Care",
    "wof:placetype":"venue"
},
  "geometry": {"coordinates":[-118.073781,33.91185],"type":"Point"}
}