{
  "type": "Feature",
  "properties": {
    "addr:full":"128 N Fair Oaks Ave Suite 107 Pasadena CA 91103",
    "addr:housenumber":"128",
    "addr:postcode":"91103",
    "addr:street":"N Fair Oaks Ave Suite 107",
    "iso:country":"US",
    "sg:address":"128 N Fair Oaks Ave Suite 107",
    "sg:city":"Pasadena",
    "sg:classifiers":[
        {
            "category":"Professional",
            "subcategory":"Lawyer & Legal Services",
            "type":"Services"
        }
    ],
    "sg:phone":"+1 626 797 2777",
    "sg:postcode":"91103",
    "sg:province":"CA",
    "sg:tags":[
        "personal",
        "injury"
    ],
    "sg:website":"www.nosexualharassment.com",
    "wof:name":"Law Offices of Jason L Oliver",
    "wof:placetype":"venue"
},
  "geometry": {"coordinates":[-118.15030899999999,34.147941],"type":"Point"}
}