{
  "type": "Feature",
  "properties": {
    "iso:country":"US",
    "sg:address":"851 Van Ness Ave Ste 2",
    "sg:city":"San Francisco",
    "sg:classifiers":[
        {
            "category":"Utilities",
            "type":"Services"
        }
    ],
    "sg:phone":"+1 415 233 4100",
    "sg:postcode":"94109",
    "sg:province":"CA",
    "sg:tags":[
        "provider",
        "internet"
    ],
    "sg:website":"www.web-pass.com",
    "wof:name":"Webpass",
    "wof:placetype":"venue"
},
  "geometry": {"coordinates":[-122.421356,37.78352],"type":"Point"}
}