{
  "type": "Feature",
  "properties": {
    "iso:country":"US",
    "sg:address":"444 Nelo St",
    "sg:city":"Santa Clara",
    "sg:classifiers":[
        {
            "category":"Wholesale",
            "subcategory":"Electrical",
            "type":"Manufacturing & Wholesale Goods"
        }
    ],
    "sg:phone":"+1 408 988 3330",
    "sg:postcode":"95054",
    "sg:province":"CA",
    "sg:tags":[
        "harness",
        "wire"
    ],
    "wof:name":"Forward Intergration Tech",
    "wof:placetype":"venue"
},
  "geometry": {"coordinates":[-121.942407,37.387463],"type":"Point"}
}