{
  "type": "Feature",
  "properties": {
    "addr:full":"5159 Terramar Way Oxnard CA 93035",
    "addr:housenumber":"5159",
    "addr:postcode":"93035",
    "addr:street":"Terramar Way",
    "iso:country":"US",
    "sg:address":"5159 Terramar Way",
    "sg:city":"Oxnard",
    "sg:classifiers":[
        {
            "category":"Wholesale",
            "subcategory":"Auto Parts",
            "type":"Manufacturing & Wholesale Goods"
        }
    ],
    "sg:phone":"+1 805 312 3422",
    "sg:postcode":"93035",
    "sg:province":"CA",
    "wof:name":"Quality Automotive Group Inc",
    "wof:placetype":"venue"
},
  "geometry": {"coordinates":[-119.239687,34.189371],"type":"Point"}
}