{
  "type": "Feature",
  "properties": {
    "addr:full":"2295 E Colorado Blvd Pasadena CA 91107",
    "addr:housenumber":"2295",
    "addr:postcode":"91107",
    "addr:street":"E Colorado Blvd",
    "iso:country":"US",
    "sg:address":"2295 E Colorado Blvd",
    "sg:city":"Pasadena",
    "sg:classifiers":[
        {
            "category":"Professional",
            "subcategory":"Art Services",
            "type":"Services"
        },
        {
            "category":"Shopping",
            "subcategory":"Crafts & Fabrics",
            "type":"Retail Goods"
        }
    ],
    "sg:phone":"+1 626 796 0970",
    "sg:postcode":"91107",
    "sg:province":"CA",
    "sg:tags":[
        "framing",
        "supply"
    ],
    "sg:website":"www.unitedpictureframe.com/",
    "wof:name":"United Picture & Frame Co",
    "wof:placetype":"venue"
},
  "geometry": {"coordinates":[-118.102997,34.146099],"type":"Point"}
}