{
  "type": "Feature",
  "properties": {
    "iso:country":"US",
    "sg:address":"375 Industrial Rd",
    "sg:city":"Watsonville",
    "sg:classifiers":[
        {
            "category":"Freight",
            "type":"Transportation"
        }
    ],
    "sg:phone":"+1 831 728 1779",
    "sg:postcode":"95076",
    "sg:province":"CA",
    "sg:tags":[
        "warehouse",
        "storage"
    ],
    "wof:name":"VEC Express",
    "wof:placetype":"venue"
},
  "geometry": {"coordinates":[-121.767883,36.899695],"type":"Point"}
}