{
  "type": "Feature",
  "properties": {
    "iso:country":"US",
    "sg:address":"2481 Monaco Dr",
    "sg:city":"Laguna Beach",
    "sg:classifiers":[
        {
            "category":"Organizations",
            "subcategory":"Religious Organization",
            "type":"Services"
        }
    ],
    "sg:phone":"+1 949 494 3650",
    "sg:postcode":"92651",
    "sg:province":"CA",
    "sg:tags":[
        "church"
    ],
    "wof:name":"Baha'i Faith",
    "wof:placetype":"venue"
},
  "geometry": {"coordinates":[-117.81360100000001,33.554735],"type":"Point"}
}