{
  "type": "Feature",
  "properties": {
    "iso:country":"US",
    "sg:address":"9552 Smoke Tree Ave",
    "sg:city":"Fountain Valley",
    "sg:classifiers":[
        {
            "category":"Professional",
            "subcategory":"Engineering",
            "type":"Services"
        }
    ],
    "sg:phone":"+1 714 513 2200",
    "sg:postcode":"92708",
    "sg:province":"CA",
    "wof:name":"Bokam Engineering Inc",
    "wof:placetype":"venue"
},
  "geometry": {"coordinates":[-117.961815,33.688044],"type":"Point"}
}