{
  "type": "Feature",
  "properties": {
    "addr:full":"15991 Magnolia St Westminster CA 92683",
    "addr:housenumber":"15991",
    "addr:postcode":"92683",
    "addr:street":"Magnolia St",
    "iso:country":"US",
    "sg:address":"15991 Magnolia St",
    "sg:city":"Westminster",
    "sg:classifiers":[
        {
            "category":"Food & Beverages",
            "subcategory":"Groceries & Convenience Stores",
            "type":"Retail Goods"
        }
    ],
    "sg:phone":"+1 714 373 6977",
    "sg:postcode":"92683",
    "sg:province":"CA",
    "sg:website":"www.7-eleven.com",
    "wof:name":"7-Eleven",
    "wof:placetype":"venue"
},
  "geometry": {"coordinates":[-117.97254700000001,33.730635],"type":"Point"}
}