{
  "type": "Feature",
  "properties": {
    "addr:full":"26791 Aliso Creek Rd Aliso Viejo CA 92656",
    "addr:housenumber":"26791",
    "addr:postcode":"92656",
    "addr:street":"Aliso Creek Rd",
    "iso:country":"US",
    "sg:address":"26791 Aliso Creek Rd",
    "sg:city":"Aliso Viejo",
    "sg:classifiers":[
        {
            "category":"Shopping",
            "subcategory":"Stationery & Office Supplies",
            "type":"Retail Goods"
        },
        {
            "category":"Professional",
            "subcategory":"Printing & Photocopies",
            "type":"Services"
        },
        {
            "category":"Shopping",
            "subcategory":"Computers & Home Electronics",
            "type":"Retail Goods"
        },
        {
            "category":"Wholesale",
            "subcategory":"Computers",
            "type":"Manufacturing & Wholesale Goods"
        }
    ],
    "sg:phone":"+1 949 448 4120",
    "sg:postcode":"92656",
    "sg:province":"CA",
    "sg:tags":[
        "equipment"
    ],
    "sg:website":"www.staples.com",
    "wof:name":"Staples",
    "wof:placetype":"venue"
},
  "geometry": {"coordinates":[-117.725421,33.573029],"type":"Point"}
}