{
  "type": "Feature",
  "properties": {
    "iso:country":"US",
    "sg:address":"2170 Bryant St",
    "sg:city":"San Francisco",
    "sg:classifiers":[
        {
            "category":"Restaurant",
            "type":"Food & Drink"
        }
    ],
    "sg:menulink":"http://www.allmenus.com/ca/san-francisco/21220-blowfish-sushi-to-die-for/menu/",
    "sg:phone":"+1 415 285 3848",
    "sg:postcode":"94110",
    "sg:province":"CA",
    "sg:tags":[
        "sushi",
        "japanese",
        "asian"
    ],
    "wof:name":"Blowfish Sushi to Die For",
    "wof:placetype":"venue"
},
  "geometry": {"coordinates":[-122.409942,37.759644],"type":"Point"}
}