{
  "type": "Feature",
  "properties": {
    "iso:country":"US",
    "sg:address":"6160 Arlington Ave",
    "sg:city":"Riverside",
    "sg:classifiers":[
        {
            "category":"Health Services",
            "subcategory":"Doctor",
            "type":"Services"
        }
    ],
    "sg:phone":"+1 951 637 0013",
    "sg:postcode":"92504",
    "sg:province":"CA",
    "sg:tags":[
        "dentist"
    ],
    "wof:name":"Arlington Family Dental Care",
    "wof:placetype":"venue"
},
  "geometry": {"coordinates":[-117.436151,33.945866],"type":"Point"}
}