{
  "type": "Feature",
  "properties": {
    "addr:full":"55 Laguna St San Francisco CA 94102",
    "addr:housenumber":"55",
    "addr:postcode":"94102",
    "addr:street":"Laguna St",
    "iso:country":"US",
    "sg:address":"55 Laguna St",
    "sg:city":"San Francisco",
    "sg:classifiers":[
        {
            "category":"Organizations",
            "subcategory":"Membership Organization",
            "type":"Services"
        }
    ],
    "sg:phone":"+1 415 543 3965",
    "sg:postcode":"94102",
    "sg:province":"CA",
    "wof:name":"Center-Learning In Retirement",
    "wof:placetype":"venue"
},
  "geometry": {"coordinates":[-122.425371,37.771625],"type":"Point"}
}