{
  "type": "Feature",
  "properties": {
    "addr:full":"1620 5th Ave San Diego CA 92101",
    "addr:housenumber":"1620",
    "addr:postcode":"92101",
    "addr:street":"5Th Ave",
    "iso:country":"US",
    "sg:address":"1620 5th Ave",
    "sg:city":"San Diego",
    "sg:classifiers":[
        {
            "category":"Real Estate",
            "subcategory":"Real Estate Operator",
            "type":"Services"
        }
    ],
    "sg:phone":"+1 619 231 9960",
    "sg:postcode":"92101",
    "sg:province":"CA",
    "sg:tags":[
        "building",
        "parks"
    ],
    "wof:name":"Robert F Driver Office Bldg",
    "wof:placetype":"venue"
},
  "geometry": {"coordinates":[-117.160217,32.72235],"type":"Point"}
}