{
  "type": "Feature",
  "properties": {
    "iso:country":"US",
    "sg:address":"18233 Arminta St",
    "sg:city":"Reseda",
    "sg:classifiers":[
        {
            "category":"Professional",
            "type":"Services"
        }
    ],
    "sg:phone":"+1 818 342 9001",
    "sg:postcode":"91335",
    "sg:province":"CA",
    "wof:name":"Ole B Broughton",
    "wof:placetype":"venue"
},
  "geometry": {"coordinates":[-118.529295,34.213912],"type":"Point"}
}