{
  "type": "Feature",
  "properties": {
    "iso:country":"US",
    "sg:address":"45420 Cll Los Mochis",
    "sg:city":"Temecula",
    "sg:classifiers":[
        {
            "category":"Wholesale",
            "subcategory":"Auto Parts",
            "type":"Manufacturing & Wholesale Goods"
        }
    ],
    "sg:phone":"+1 951 303 0660",
    "sg:postcode":"92592",
    "sg:province":"CA",
    "sg:tags":[
        "automotive"
    ],
    "wof:name":"GIE Trading",
    "wof:placetype":"venue"
},
  "geometry": {"coordinates":[-117.086097,33.467183],"type":"Point"}
}