{
  "type": "Feature",
  "properties": {
    "iso:country":"US",
    "sg:address":"41965 Margarita Rd",
    "sg:city":"Temecula",
    "sg:classifiers":[
        {
            "category":"Professional",
            "type":"Services"
        }
    ],
    "sg:phone":"+1 951 695 3649",
    "sg:postcode":"92591",
    "sg:province":"CA",
    "wof:name":"Gsk Potato Incorporated",
    "wof:placetype":"venue"
},
  "geometry": {"coordinates":[-117.13950199999999,33.511581],"type":"Point"}
}