{
  "type": "Feature",
  "properties": {
    "iso:country":"US",
    "sg:address":"722 W Betteravia Rd",
    "sg:city":"Santa Maria",
    "sg:classifiers":[
        {
            "category":"Restaurant",
            "type":"Food & Drink"
        }
    ],
    "sg:phone":"+1 805 739 0809",
    "sg:postcode":"93455",
    "sg:province":"CA",
    "sg:tags":[
        "caterer"
    ],
    "wof:name":"Testa Catering",
    "wof:placetype":"venue"
},
  "geometry": {"coordinates":[-120.44385699999999,34.92033],"type":"Point"}
}