{
  "type": "Feature",
  "properties": {
    "addr:full":"13250 Kirkham Way Poway CA 92064",
    "addr:housenumber":"13250",
    "addr:postcode":"ca 92064",
    "addr:street":"Kirkham Way",
    "iso:country":"US",
    "sg:address":"13250 Kirkham Way",
    "sg:city":"Poway",
    "sg:classifiers":[
        {
            "category":"Building & Trades",
            "subcategory":"Electrical",
            "type":"Services"
        }
    ],
    "sg:phone":"+1 858 513 3020",
    "sg:postcode":"92064",
    "sg:province":"CA",
    "sg:tags":[
        "electric",
        "contractor"
    ],
    "sg:website":"www.nealelectric.com",
    "wof:name":"Neal Electric Inc",
    "wof:placetype":"venue"
},
  "geometry": {"coordinates":[-117.044916,32.935069],"type":"Point"}
}