{
  "type": "Feature",
  "properties": {
    "iso:country":"US",
    "sg:address":"1073 Sea Reef Dr",
    "sg:city":"San Diego",
    "sg:classifiers":[
        {
            "category":"Building & Trades",
            "subcategory":"Construction",
            "type":"Services"
        }
    ],
    "sg:phone":"+1 619 671 9590",
    "sg:postcode":"92154",
    "sg:province":"CA",
    "sg:tags":[
        "nonresidential"
    ],
    "wof:name":"Morgan Development",
    "wof:placetype":"venue"
},
  "geometry": {"coordinates":[-117.025762,32.573465],"type":"Point"}
}