{
  "type": "Feature",
  "properties": {
    "iso:country":"US",
    "sg:address":"11614 Atlantic Avenue",
    "sg:city":"Lynwood",
    "sg:classifiers":[
        {
            "category":"Insurance",
            "subcategory":"Hazard Insurance",
            "type":"Services"
        }
    ],
    "sg:phone":"+1 310 667 8778",
    "sg:postcode":"90262",
    "sg:province":"CA",
    "wof:name":"E A T Insurance",
    "wof:placetype":"venue"
},
  "geometry": {"coordinates":[-118.18872,33.918349],"type":"Point"}
}