{
  "type": "Feature",
  "properties": {
    "addr:full":"Embassy Suites 4550 La Jolla Village Dr San Diego CA 92122",
    "addr:housenumber":"4550",
    "addr:postcode":"92122",
    "addr:street":"La Jolla Village Dr",
    "iso:country":"US",
    "sg:address":"Embassy Suites 4550 La Jolla Village Dr",
    "sg:city":"San Diego",
    "sg:classifiers":[
        {
            "category":"Restaurant",
            "type":"Food & Drink"
        }
    ],
    "sg:phone":"+1 858 431 2114",
    "sg:postcode":"92122",
    "sg:province":"CA",
    "sg:website":"www.indulgelajolla.com",
    "wof:name":"Indulge Restaurant & Lounge",
    "wof:placetype":"venue"
},
  "geometry": {"coordinates":[-117.208704,32.874514],"type":"Point"}
}