{
  "type": "Feature",
  "properties": {
    "iso:country":"US",
    "sg:address":"8822 W Pico Boulevard",
    "sg:city":"Los Angeles",
    "sg:classifiers":[
        {
            "category":"Home & Garden",
            "subcategory":"Household Appliances",
            "type":"Retail Goods"
        },
        {
            "category":"Home & Garden",
            "subcategory":"Building Materials",
            "type":"Retail Goods"
        }
    ],
    "sg:phone":"+1 310 271 5619",
    "sg:postcode":"90035",
    "sg:province":"CA",
    "sg:tags":[
        "repair",
        "lighting",
        "fixture",
        "equipment"
    ],
    "wof:name":"Beverly Hills Vacuum",
    "wof:placetype":"venue"
},
  "geometry": {"coordinates":[-118.384146,34.054953],"type":"Point"}
}