{
  "type": "Feature",
  "properties": {
    "addr:full":"699 Castro St San Francisco CA 94114",
    "addr:housenumber":"699",
    "addr:postcode":"94114",
    "addr:street":"Castro St",
    "iso:country":"US",
    "sg:address":"699 Castro St",
    "sg:city":"San Francisco",
    "sg:classifiers":[
        {
            "category":"Building & Trades",
            "subcategory":"Construction",
            "type":"Services"
        }
    ],
    "sg:phone":"+1 415 377 3965",
    "sg:postcode":"94114",
    "sg:province":"CA",
    "sg:tags":[
        "tile",
        "dealer"
    ],
    "wof:name":"City Tile Installation",
    "wof:placetype":"venue"
},
  "geometry": {"coordinates":[-122.434854,37.759288],"type":"Point"}
}