{
  "type": "Feature",
  "properties": {
    "addr:full":"211 W Alameda Ave Burbank CA 91502",
    "addr:housenumber":"211",
    "addr:postcode":"91502",
    "addr:street":"W Alameda Ave",
    "iso:country":"US",
    "sg:address":"211 W Alameda Ave",
    "sg:city":"Burbank",
    "sg:classifiers":[
        {
            "category":"Restaurant",
            "type":"Food & Drink"
        }
    ],
    "sg:phone":"+1 818 953 2940",
    "sg:postcode":"91502",
    "sg:province":"CA",
    "sg:tags":[
        "shop",
        "coffee"
    ],
    "wof:name":"Spencer's Coffee Shop",
    "wof:placetype":"venue"
},
  "geometry": {"coordinates":[-118.305952,34.168827],"type":"Point"}
}