{
  "type": "Feature",
  "properties": {
    "addr:full":"774 35th Ave San Francisco CA 94121",
    "addr:housenumber":"774",
    "addr:postcode":"94121",
    "addr:street":"35Th Ave",
    "iso:country":"US",
    "sg:address":"774 35th Ave",
    "sg:city":"San Francisco",
    "sg:classifiers":[
        {
            "category":"Wholesale",
            "subcategory":"Non-durable Goods",
            "type":"Manufacturing & Wholesale Goods"
        }
    ],
    "sg:phone":"+1 415 668 4555",
    "sg:postcode":"94121",
    "sg:province":"CA",
    "wof:name":"R G S Creative Marketing",
    "wof:placetype":"venue"
},
  "geometry": {"coordinates":[-122.495045,37.77536],"type":"Point"}
}