{
  "type": "Feature",
  "properties": {
    "iso:country":"US",
    "sg:address":"16972 Oak View Dr",
    "sg:city":"Encino",
    "sg:classifiers":[
        {
            "category":"Health Services",
            "subcategory":"Health Practitioner",
            "type":"Services"
        }
    ],
    "sg:phone":"+1 818 501 4435",
    "sg:postcode":"91436",
    "sg:province":"CA",
    "sg:tags":[
        "psychologist"
    ],
    "wof:name":"Martha Widawer PHD",
    "wof:placetype":"venue"
},
  "geometry": {"coordinates":[-118.504223,34.150969],"type":"Point"}
}