{
  "type": "Feature",
  "properties": {
    "addr:full":"4822 W Monte Verde Ct Visalia CA 93277",
    "addr:housenumber":"4822",
    "addr:postcode":"93277",
    "addr:street":"W Monte Verde Ct",
    "iso:country":"US",
    "sg:address":"4822 W Monte Verde Ct",
    "sg:city":"Visalia",
    "sg:classifiers":[
        {
            "category":"Building & Trades",
            "subcategory":"Landscaping Services",
            "type":"Services"
        }
    ],
    "sg:phone":"+1 559 730 4717",
    "sg:postcode":"93277",
    "sg:province":"CA",
    "sg:tags":[
        "lawn",
        "maintenance",
        "grounds"
    ],
    "wof:name":"C & F Yard & Detail Svc",
    "wof:placetype":"venue"
},
  "geometry": {"coordinates":[-119.345249,36.305009],"type":"Point"}
}