{
  "type": "Feature",
  "properties": {
    "addr:full":"28715 Los Aliso Blvd Mission Viejo CA 92692",
    "addr:housenumber":"28715",
    "addr:postcode":"92692",
    "addr:street":"Los Aliso Blvd",
    "iso:country":"US",
    "sg:address":"28715 Los Aliso Blvd",
    "sg:city":"Mission Viejo",
    "sg:classifiers":[
        {
            "category":"Professional",
            "subcategory":"Detective & Security Services",
            "type":"Services"
        }
    ],
    "sg:phone":"+1 949 215 1530",
    "sg:postcode":"92692",
    "sg:province":"CA",
    "sg:tags":[
        "system"
    ],
    "wof:name":"National Imaging Services",
    "wof:placetype":"venue"
},
  "geometry": {"coordinates":[-117.71234200000001,33.555425],"type":"Point"}
}