{
  "type": "Feature",
  "properties": {
    "addr:full":"1666 Midfield Ave San Jose CA 95122",
    "addr:housenumber":"1666",
    "addr:postcode":"95122",
    "addr:street":"Midfield Ave",
    "iso:country":"US",
    "sg:address":"1666 Midfield Ave",
    "sg:city":"San Jose",
    "sg:classifiers":[
        {
            "category":"Building & Trades",
            "subcategory":"Landscaping Services",
            "type":"Services"
        }
    ],
    "sg:phone":"+1 408 347 8798",
    "sg:postcode":"95122",
    "sg:province":"CA",
    "wof:name":"Bronco Gardening",
    "wof:placetype":"venue"
},
  "geometry": {"coordinates":[-121.840018,37.328457],"type":"Point"}
}