{
  "type": "Feature",
  "properties": {
    "addr:full":"3312 Sacramento St San Francisco CA 94118",
    "addr:housenumber":"3312",
    "addr:postcode":"94118",
    "addr:street":"Sacramento St",
    "iso:country":"US",
    "sg:address":"3312 Sacramento St",
    "sg:city":"San Francisco",
    "sg:classifiers":[
        {
            "category":"Personal",
            "subcategory":"Barber",
            "type":"Services"
        }
    ],
    "sg:phone":"+1 415 567 3335",
    "sg:postcode":"94118",
    "sg:province":"CA",
    "wof:name":"Asano Barber Shop",
    "wof:placetype":"venue"
},
  "geometry": {"coordinates":[-122.448505,37.788077],"type":"Point"}
}