{
  "type": "Feature",
  "properties": {
    "addr:full":"2710 Via de la Valle Del Mar CA 92014",
    "addr:housenumber":"2710",
    "addr:postcode":"92014",
    "addr:street":"Via De La Valle",
    "iso:country":"US",
    "sg:address":"2710 Via de la Valle",
    "sg:city":"Del Mar",
    "sg:classifiers":[
        {
            "category":"Shopping",
            "subcategory":"Shoes",
            "type":"Retail Goods"
        }
    ],
    "sg:phone":"+1 858 793 1593",
    "sg:postcode":"92014",
    "sg:province":"CA",
    "wof:name":"Garland Enterprises Inc",
    "wof:placetype":"venue"
},
  "geometry": {"coordinates":[-117.24773500000001,32.981095],"type":"Point"}
}