{
  "type": "Feature",
  "properties": {
    "iso:country":"US",
    "sg:address":"501 Beale #11H",
    "sg:city":"San Francisco",
    "sg:classifiers":[
        {
            "category":"Professional",
            "subcategory":"Computer Services",
            "type":"Services"
        }
    ],
    "sg:province":"CA",
    "sg:tags":[
        "boutique-hotels",
        "luxury-resorts",
        "travel",
        "travel-guides"
    ],
    "sg:website":"http://www.mapplr.com",
    "wof:name":"Mapplr",
    "wof:placetype":"venue"
},
  "geometry": {"coordinates":[-122.389409,37.786041],"type":"Point"}
}