{
  "type": "Feature",
  "properties": {
    "addr:full":"1027 Highland Ave National City CA 91950",
    "addr:housenumber":"1027",
    "addr:postcode":"91950",
    "addr:street":"Highland Ave",
    "iso:country":"US",
    "sg:address":"1027 Highland Ave",
    "sg:city":"National City",
    "sg:classifiers":[
        {
            "category":"Shopping",
            "subcategory":"Clothing, Apparel, & Fashions",
            "type":"Retail Goods"
        }
    ],
    "sg:phone":"+1 619 474 4244",
    "sg:postcode":"91950",
    "sg:province":"CA",
    "sg:tags":[
        "furnishing"
    ],
    "wof:name":"City Boy Men's Wear",
    "wof:placetype":"venue"
},
  "geometry": {"coordinates":[-117.09732700000001,32.674775],"type":"Point"}
}