{
  "type": "Feature",
  "properties": {
    "iso:country":"US",
    "sg:address":"804 Hilldale Ave",
    "sg:city":"West Hollywood",
    "sg:classifiers":[
        {
            "category":"Personal",
            "subcategory":"Beauty Salon",
            "type":"Services"
        }
    ],
    "sg:phone":"+1 310 289 1392",
    "sg:postcode":"90069",
    "sg:province":"CA",
    "sg:tags":[
        "hair"
    ],
    "sg:website":"www.varonhairstudio.com",
    "wof:name":"Varon Hair Studio",
    "wof:placetype":"venue"
},
  "geometry": {"coordinates":[-118.384844,34.084835],"type":"Point"}
}