{
  "type": "Feature",
  "properties": {
    "iso:country":"US",
    "sg:address":"12800 Rosecrans Ave",
    "sg:city":"Norwalk",
    "sg:classifiers":[
        {
            "category":"Autos & Motor Vehicles",
            "subcategory":"Fuel & Gas Station",
            "type":"Retail Goods"
        }
    ],
    "sg:phone":"+1 562 921 3969",
    "sg:postcode":"90650",
    "sg:province":"CA",
    "wof:name":"W W Mobile Service Inc",
    "wof:placetype":"venue"
},
  "geometry": {"coordinates":[-118.059998,33.902199],"type":"Point"}
}