{
  "type": "Feature",
  "properties": {
    "addr:full":"2006 Dwight Way Berkeley CA 94704",
    "addr:housenumber":"2006",
    "addr:postcode":"94704",
    "addr:street":"Dwight Way",
    "iso:country":"US",
    "sg:address":"2006 Dwight Way",
    "sg:city":"Berkeley",
    "sg:classifiers":[
        {
            "category":"Health Services",
            "subcategory":"Chiropractor",
            "type":"Services"
        }
    ],
    "sg:phone":"+1 510 644 4425",
    "sg:postcode":"94704",
    "sg:province":"CA",
    "sg:tags":[
        "chiropractic"
    ],
    "wof:name":"Phillips Scott R DC",
    "wof:placetype":"venue"
},
  "geometry": {"coordinates":[-122.26933200000001,37.863444],"type":"Point"}
}