{
  "type": "Feature",
  "properties": {
    "addr:full":"569 S Fortuna Blvd Fortuna CA 95540",
    "addr:housenumber":"569",
    "addr:postcode":"95540",
    "addr:street":"S Fortuna Blvd",
    "iso:country":"US",
    "sg:address":"569 S Fortuna Blvd",
    "sg:city":"Fortuna",
    "sg:classifiers":[
        {
            "category":"Shopping",
            "subcategory":"Computers & Home Electronics",
            "type":"Retail Goods"
        }
    ],
    "sg:phone":"+1 707 725 3233",
    "sg:postcode":"95540",
    "sg:province":"CA",
    "sg:tags":[
        "software"
    ],
    "wof:name":"Professional Software Systems",
    "wof:placetype":"venue"
},
  "geometry": {"coordinates":[-124.146582,40.586324],"type":"Point"}
}