{
  "type": "Feature",
  "properties": {
    "iso:country":"US",
    "sg:address":"10982 Donner Pass Rd",
    "sg:city":"Truckee",
    "sg:classifiers":[
        {
            "category":"Personal",
            "subcategory":"Hair Removal",
            "type":"Services"
        },
        {
            "category":"Personal",
            "subcategory":"Day Spa",
            "type":"Services"
        },
        {
            "category":"Personal",
            "subcategory":"Skin Care",
            "type":"Services"
        },
        {
            "category":"Personal",
            "subcategory":"Beauty Salon",
            "type":"Services"
        },
        {
            "category":"Personal",
            "subcategory":"Massage",
            "type":"Services"
        },
        {
            "category":"Health Services",
            "subcategory":"Doctor",
            "type":"Services"
        }
    ],
    "sg:phone":"+1 530 587 0198",
    "sg:postcode":"96161",
    "sg:province":"CA",
    "sg:tags":[
        "physician",
        "reconstructive",
        "surgeons",
        "plastic",
        "therapist",
        "surgeon"
    ],
    "sg:website":"http://www.sierracosmeticlaser.com",
    "wof:name":"Sierra Cosmetic Laser, Inc.",
    "wof:placetype":"venue"
},
  "geometry": {"coordinates":[-120.202787,39.326091],"type":"Point"}
}