{
  "type": "Feature",
  "properties": {
    "addr:full":"1233 Castro St San Francisco CA 94112",
    "addr:housenumber":"1233",
    "addr:postcode":"94112",
    "addr:street":"Castro St",
    "iso:country":"US",
    "sg:address":"1233 Castro St",
    "sg:city":"San Francisco",
    "sg:classifiers":[
        {
            "category":"Personal",
            "subcategory":"Beauty Salon",
            "type":"Services"
        }
    ],
    "sg:phone":"+1 415 826 0222",
    "sg:postcode":"94112",
    "sg:province":"CA",
    "sg:tags":[
        "hair"
    ],
    "sg:website":"www.headsuphaircare.com",
    "wof:name":"Heads Up Hair Care",
    "wof:placetype":"venue"
},
  "geometry": {"coordinates":[-122.433869,37.751518],"type":"Point"}
}