{
  "type": "Feature",
  "properties": {
    "addr:full":"3546 el Camino Real Atascadero CA 93422",
    "addr:housenumber":"3546",
    "addr:postcode":"93422",
    "addr:street":"El Camino Real",
    "iso:country":"US",
    "sg:address":"3546 el Camino Real",
    "sg:city":"Atascadero",
    "sg:classifiers":[
        {
            "category":"Health Services",
            "subcategory":"Chiropractor",
            "type":"Services"
        }
    ],
    "sg:phone":"+1 805 466 6378",
    "sg:postcode":"93422",
    "sg:province":"CA",
    "wof:name":"Hart Family Chiropractic",
    "wof:placetype":"venue"
},
  "geometry": {"coordinates":[-120.687562,35.502299],"type":"Point"}
}