{
  "type": "Feature",
  "properties": {
    "iso:country":"US",
    "sg:address":"2617 Bell Ave",
    "sg:city":"Manhattan Beach",
    "sg:classifiers":[
        {
            "category":"Social Services",
            "subcategory":"Child Care",
            "type":"Services"
        }
    ],
    "sg:phone":"+1 310 379 9462",
    "sg:postcode":"90266",
    "sg:province":"CA",
    "sg:tags":[
        "kindergarten",
        "academic",
        "school"
    ],
    "wof:name":"Montessori School",
    "wof:placetype":"venue"
},
  "geometry": {"coordinates":[-118.41113,33.895809],"type":"Point"}
}