{
  "type": "Feature",
  "properties": {
    "iso:country":"US",
    "sg:address":"340 N 2nd St",
    "sg:city":"San Jose",
    "sg:classifiers":[
        {
            "category":"Retail",
            "subcategory":"Auto Repair",
            "type":"Services"
        }
    ],
    "sg:phone":"+1 408 920 0588",
    "sg:postcode":"95112",
    "sg:province":"CA",
    "sg:tags":[
        "muffler",
        "exhaust",
        "system"
    ],
    "wof:name":"Rci Exhaust Pros",
    "wof:placetype":"venue"
},
  "geometry": {"coordinates":[-121.892777,37.341053],"type":"Point"}
}