{
  "type": "Feature",
  "properties": {
    "addr:full":"4748 Park Granada Unit # 255 Calabasas CA 91302",
    "addr:housenumber":"4748",
    "addr:postcode":"91302",
    "addr:street":"Park Granada Unit # 255",
    "iso:country":"US",
    "sg:address":"4748 Park Granada Unit # 255",
    "sg:city":"Calabasas",
    "sg:classifiers":[
        {
            "category":"Building & Trades",
            "subcategory":"Cleaning & Sanitation",
            "type":"Services"
        }
    ],
    "sg:phone":"+1 818 827 1352",
    "sg:postcode":"91302",
    "sg:province":"CA",
    "sg:tags":[
        "carpet"
    ],
    "wof:name":"Calabasas",
    "wof:placetype":"venue"
},
  "geometry": {"coordinates":[-118.642642,34.151757],"type":"Point"}
}