{
  "type": "Feature",
  "properties": {
    "iso:country":"US",
    "sg:address":"44 W College Ave",
    "sg:city":"Santa Rosa",
    "sg:classifiers":[
        {
            "category":"Recreation",
            "type":"Entertainment"
        }
    ],
    "sg:phone":"+1 707 541 0308",
    "sg:postcode":"95401",
    "sg:province":"CA",
    "sg:tags":[
        "psychic",
        "medium"
    ],
    "wof:name":"Grupo Cales",
    "wof:placetype":"venue"
},
  "geometry": {"coordinates":[-122.72943600000001,38.445774],"type":"Point"}
}