{
  "type": "Feature",
  "properties": {
    "iso:country":"US",
    "sg:address":"8057 1st St",
    "sg:city":"Paramount",
    "sg:classifiers":[
        {
            "category":"Building & Trades",
            "subcategory":"Pest Control",
            "type":"Services"
        }
    ],
    "sg:phone":"+1 562 531 1515",
    "sg:postcode":"90723",
    "sg:province":"CA",
    "wof:name":"Exceed Termite Control Inc",
    "wof:placetype":"venue"
},
  "geometry": {"coordinates":[-118.15799699999999,33.8974],"type":"Point"}
}