{
  "type": "Feature",
  "properties": {
    "addr:full":"5121 Van Nuys Blvd Sherman Oaks CA 91403",
    "addr:housenumber":"5121",
    "addr:postcode":"91403",
    "addr:street":"Van Nuys Blvd",
    "iso:country":"US",
    "sg:address":"5121 Van Nuys Blvd",
    "sg:city":"Sherman Oaks",
    "sg:classifiers":[
        {
            "category":"Professional",
            "subcategory":"Management & Consulting",
            "type":"Services"
        }
    ],
    "sg:phone":"+1 818 907 9977",
    "sg:postcode":"91403",
    "sg:province":"CA",
    "sg:tags":[
        "bus",
        "credit",
        "business",
        "con"
    ],
    "wof:name":"Los Angeles Business Dev",
    "wof:placetype":"venue"
},
  "geometry": {"coordinates":[-118.448774,34.163344],"type":"Point"}
}