{
  "type": "Feature",
  "properties": {
    "iso:country":"US",
    "sg:address":"5101 E Marita Ln Apt A",
    "sg:city":"Anaheim",
    "sg:classifiers":[
        {
            "category":"Real Estate",
            "subcategory":"Real Estate Operator",
            "type":"Services"
        }
    ],
    "sg:phone":"+1 714 779 2500",
    "sg:postcode":"92807",
    "sg:province":"CA",
    "sg:tags":[
        "apartment"
    ],
    "wof:name":"Villas Apartments the",
    "wof:placetype":"venue"
},
  "geometry": {"coordinates":[-117.78299699999999,33.853802],"type":"Point"}
}