{
  "type": "Feature",
  "properties": {
    "addr:full":"2778 24th St San Francisco CA 94110",
    "addr:housenumber":"2778",
    "addr:postcode":"94110",
    "addr:street":"24Th St",
    "iso:country":"US",
    "sg:address":"2778 24th St",
    "sg:city":"San Francisco",
    "sg:classifiers":[
        {
            "category":"Wholesale",
            "subcategory":"Groceries",
            "type":"Manufacturing & Wholesale Goods"
        }
    ],
    "sg:phone":"+1 415 282 2400",
    "sg:postcode":"94110",
    "sg:province":"CA",
    "sg:tags":[
        "tortilla"
    ],
    "wof:name":"Casa Sanchez Restaurant",
    "wof:placetype":"venue"
},
  "geometry": {"coordinates":[-122.407781,37.752959],"type":"Point"}
}