{
  "type": "Feature",
  "properties": {
    "iso:country":"US",
    "sg:address":"915 W Foothill Blvd",
    "sg:city":"Claremont",
    "sg:classifiers":[
        {
            "category":"Professional",
            "subcategory":"Accounting & Tax Preparation",
            "type":"Services"
        }
    ],
    "sg:phone":"+1 909 621 5011",
    "sg:postcode":"91711",
    "sg:province":"CA",
    "sg:tags":[
        "return",
        "filing"
    ],
    "wof:name":"Fiducial",
    "wof:placetype":"venue"
},
  "geometry": {"coordinates":[-117.73215999999999,34.107062],"type":"Point"}
}