{
  "type": "Feature",
  "properties": {
    "addr:full":"1777 G St Merced CA 95340",
    "addr:housenumber":"1777",
    "addr:postcode":"95340",
    "addr:street":"G St",
    "iso:country":"US",
    "sg:address":"1777 G St",
    "sg:city":"Merced",
    "sg:classifiers":[
        {
            "category":"Organizations",
            "subcategory":"Non-profit Organization",
            "type":"Services"
        }
    ],
    "sg:phone":"+1 209 383 3277",
    "sg:postcode":"95340",
    "sg:province":"CA",
    "wof:name":"Merced Symphony Assn",
    "wof:placetype":"venue"
},
  "geometry": {"coordinates":[-120.47568099999999,37.298921],"type":"Point"}
}