{
  "type": "Feature",
  "properties": {
    "addr:full":"15268 Proctor Ave City Of Industry CA 91745",
    "addr:housenumber":"15268",
    "addr:postcode":"91745",
    "addr:street":"Proctor Ave",
    "iso:country":"US",
    "sg:address":"15268 Proctor Ave",
    "sg:city":"City Of Industry",
    "sg:classifiers":[
        {
            "category":"Manufacturing",
            "subcategory":"Metals",
            "type":"Manufacturing & Wholesale Goods"
        }
    ],
    "sg:phone":"+1 626 330 7434",
    "sg:postcode":"91745",
    "sg:province":"CA",
    "sg:tags":[
        "screw",
        "nut",
        "bolt"
    ],
    "wof:name":"Stud Welding Systems Inc",
    "wof:placetype":"venue"
},
  "geometry": {"coordinates":[-117.965037,34.023353],"type":"Point"}
}