{
  "type": "Feature",
  "properties": {
    "addr:full":"4261 Hilltop Dr El Sobrante CA 94803",
    "addr:housenumber":"4261",
    "addr:postcode":"94803",
    "addr:street":"Hilltop Dr El Sobrante",
    "iso:country":"US",
    "sg:address":"4261 Hilltop Dr",
    "sg:city":"El Sobrante",
    "sg:classifiers":[
        {
            "category":"Restaurant",
            "type":"Food & Drink"
        }
    ],
    "sg:phone":"+1 510 262 0694",
    "sg:postcode":"94803",
    "sg:province":"CA",
    "wof:name":"Bobby's Cajun BBQ",
    "wof:placetype":"venue"
},
  "geometry": {"coordinates":[-122.313042,37.976425],"type":"Point"}
}