{
  "type": "Feature",
  "properties": {
    "addr:full":"8463 Hallwood Blvd Marysville CA 95901",
    "addr:housenumber":"8463",
    "addr:postcode":"95901",
    "addr:street":"Hallwood Blvd",
    "iso:country":"US",
    "sg:address":"8463 Hallwood Blvd",
    "sg:city":"Marysville",
    "sg:classifiers":[
        {
            "category":"Utilities",
            "subcategory":"Water",
            "type":"Services"
        }
    ],
    "sg:phone":"+1 530 743 6704",
    "sg:postcode":"95901",
    "sg:province":"CA",
    "sg:tags":[
        "company",
        "sewage",
        "supply"
    ],
    "wof:name":"Hallwood Irrigation Co Inc",
    "wof:placetype":"venue"
},
  "geometry": {"coordinates":[-121.51621799999999,39.203118],"type":"Point"}
}