{
  "type": "Feature",
  "properties": {
    "iso:country":"US",
    "sg:address":"1121 Rivas Ln",
    "sg:city":"Oxnard",
    "sg:classifiers":[
        {
            "category":"Manufacturing",
            "subcategory":"Retail Goods",
            "type":"Manufacturing & Wholesale Goods"
        }
    ],
    "sg:phone":"+1 805 271 9963",
    "sg:postcode":"93035",
    "sg:province":"CA",
    "sg:tags":[
        "product",
        "mfg"
    ],
    "wof:name":"Urban Camo",
    "wof:placetype":"venue"
},
  "geometry": {"coordinates":[-119.198007,34.189444],"type":"Point"}
}