{
  "type": "Feature",
  "properties": {
    "addr:full":"1544 Frazee Rd San Diego CA 92108",
    "addr:housenumber":"1544",
    "addr:postcode":"92108",
    "addr:street":"Frazee Rd",
    "iso:country":"US",
    "sg:address":"1544 Frazee Rd",
    "sg:city":"San Diego",
    "sg:classifiers":[
        {
            "category":"Real Estate",
            "subcategory":"Architect",
            "type":"Services"
        }
    ],
    "sg:phone":"+1 619 299 1902",
    "sg:postcode":"92108",
    "sg:province":"CA",
    "sg:tags":[
        "illustrator",
        "architectural"
    ],
    "wof:name":"Attwood Construction",
    "wof:placetype":"venue"
},
  "geometry": {"coordinates":[-117.15900600000001,32.773726],"type":"Point"}
}