{
  "type": "Feature",
  "properties": {
    "addr:full":"76 Stephanie Dr Salinas CA 93901",
    "addr:housenumber":"76",
    "addr:postcode":"93901",
    "addr:street":"Stephanie Dr",
    "iso:country":"US",
    "sg:address":"76 Stephanie Dr",
    "sg:city":"Salinas",
    "sg:classifiers":[
        {
            "category":"Wholesale",
            "subcategory":"Machinery & Supplies",
            "type":"Manufacturing & Wholesale Goods"
        }
    ],
    "sg:phone":"+1 831 783 3300",
    "sg:postcode":"93901",
    "sg:province":"CA",
    "wof:name":"Monterey County Schools Worker",
    "wof:placetype":"venue"
},
  "geometry": {"coordinates":[-121.66400899999999,36.654168],"type":"Point"}
}