{
  "type": "Feature",
  "properties": {
    "addr:full":"3902 Lenawee Avenue Culver City CA 90232",
    "addr:housenumber":"3902",
    "addr:postcode":"90232",
    "addr:street":"Lenawee Avenue",
    "iso:country":"US",
    "sg:address":"3902 Lenawee Avenue",
    "sg:city":"Culver City",
    "sg:classifiers":[
        {
            "category":"Real Estate",
            "subcategory":"Real Estate Operator",
            "type":"Services"
        }
    ],
    "sg:phone":"+1 323 870 8891",
    "sg:postcode":"90232",
    "sg:province":"CA",
    "sg:tags":[
        "apartment"
    ],
    "wof:name":"Keswick Court Apartments",
    "wof:placetype":"venue"
},
  "geometry": {"coordinates":[-118.37488500000001,34.015707],"type":"Point"}
}