{
  "type": "Feature",
  "properties": {
    "addr:full":"37474 Glenmoor Dr Fremont CA 94536",
    "addr:housenumber":"37474",
    "addr:postcode":"94536",
    "addr:street":"Glenmoor Dr",
    "iso:country":"US",
    "sg:address":"37474 Glenmoor Dr",
    "sg:city":"Fremont",
    "sg:classifiers":[
        {
            "category":"Autos & Motor Vehicles",
            "subcategory":"Automobile Sales",
            "type":"Retail Goods"
        }
    ],
    "sg:phone":"+1 510 794 7668",
    "sg:postcode":"94536",
    "sg:province":"CA",
    "sg:tags":[
        "car",
        "dealer"
    ],
    "wof:name":"Kok Sheridan Way Invstmnt LLC",
    "wof:placetype":"venue"
},
  "geometry": {"coordinates":[-122.01245,37.550666],"type":"Point"}
}