{
  "type": "Feature",
  "properties": {
    "iso:country":"US",
    "sg:address":"8700 Beverly Blvd",
    "sg:city":"Los Angeles",
    "sg:classifiers":[
        {
            "category":"Health Services",
            "subcategory":"Hospital",
            "type":"Services"
        }
    ],
    "sg:phone":"+1 310 822 9808",
    "sg:postcode":"90048",
    "sg:province":"CA",
    "sg:tags":[
        "general"
    ],
    "wof:name":"Daniel James Maloney MD",
    "wof:placetype":"venue"
},
  "geometry": {"coordinates":[-118.380921,34.076921],"type":"Point"}
}