{
  "type": "Feature",
  "properties": {
    "addr:full":"231 Hazel Ln Nipomo CA 93444",
    "addr:housenumber":"231",
    "addr:postcode":"93444",
    "addr:street":"Hazel Ln",
    "iso:country":"US",
    "sg:address":"231 Hazel Ln",
    "sg:city":"Nipomo",
    "sg:classifiers":[
        {
            "category":"Professional",
            "subcategory":"Engineering",
            "type":"Services"
        }
    ],
    "sg:phone":"+1 805 489 5380",
    "sg:postcode":"93444",
    "sg:province":"CA",
    "sg:tags":[
        "engineer"
    ],
    "wof:name":"William A Sommermeyer PE",
    "wof:placetype":"venue"
},
  "geometry": {"coordinates":[-120.495385,35.022785],"type":"Point"}
}