{
  "type": "Feature",
  "properties": {
    "addr:full":"237 Ocean Ave Laguna Beach CA 92651",
    "addr:housenumber":"237",
    "addr:postcode":"92651",
    "addr:street":"Ocean Ave",
    "iso:country":"US",
    "sg:address":"237 Ocean Ave",
    "sg:city":"Laguna Beach",
    "sg:classifiers":[
        {
            "category":"Restaurant",
            "type":"Food & Drink"
        }
    ],
    "sg:phone":"+1 949 497 3381",
    "sg:postcode":"92651",
    "sg:province":"CA",
    "sg:website":"www.oceanbrewing.com",
    "wof:name":"Ocean Brewing Co",
    "wof:placetype":"venue"
},
  "geometry": {"coordinates":[-117.782978,33.543936],"type":"Point"}
}