{
  "type": "Feature",
  "properties": {
    "addr:full":"2271 Ringwood Ave San Jose CA 95131",
    "addr:housenumber":"2271",
    "addr:postcode":"95131",
    "addr:street":"Ringwood Ave",
    "iso:country":"US",
    "sg:address":"2271 Ringwood Ave",
    "sg:city":"San Jose",
    "sg:classifiers":[
        {
            "category":"Wholesale",
            "subcategory":"Electrical",
            "type":"Manufacturing & Wholesale Goods"
        }
    ],
    "sg:phone":"+1 510 624 9000",
    "sg:postcode":"95131",
    "sg:province":"CA",
    "sg:tags":[
        "electronic",
        "representative"
    ],
    "sg:website":"www.consolitech.net",
    "wof:name":"Consolitech Electronics Inc",
    "wof:placetype":"venue"
},
  "geometry": {"coordinates":[-121.89802899999999,37.397336],"type":"Point"}
}