{
  "type": "Feature",
  "properties": {
    "addr:full":"30550 Rancho California Rd Temecula CA 92591",
    "addr:housenumber":"30550",
    "addr:postcode":"92591",
    "addr:street":"Rancho California Rd",
    "iso:country":"US",
    "sg:address":"30550 Rancho California Rd",
    "sg:city":"Temecula",
    "sg:classifiers":[
        {
            "category":"Personal",
            "subcategory":"Nail Salon",
            "type":"Services"
        }
    ],
    "sg:phone":"+1 951 676 8457",
    "sg:postcode":"92591",
    "sg:province":"CA",
    "wof:name":"Nails By Lola",
    "wof:placetype":"venue"
},
  "geometry": {"coordinates":[-117.127875,33.508632],"type":"Point"}
}