{
  "type": "Feature",
  "properties": {
    "addr:full":"3505 Paydirt Dr Placerville CA 95667",
    "addr:housenumber":"3505",
    "addr:postcode":"95667",
    "addr:street":"Paydirt Dr",
    "iso:country":"US",
    "sg:address":"3505 Paydirt Dr",
    "sg:city":"Placerville",
    "sg:classifiers":[
        {
            "category":"Professional",
            "subcategory":"Computer Services",
            "type":"Services"
        },
        {
            "category":"Professional",
            "subcategory":"Business Services",
            "type":"Services"
        },
        {
            "category":"Wholesale",
            "subcategory":"Computers",
            "type":"Manufacturing & Wholesale Goods"
        }
    ],
    "sg:phone":"+1 530 626 4930",
    "sg:postcode":"95667",
    "sg:province":"CA",
    "sg:tags":[
        "software",
        "consultant",
        "cd-rom",
        "coach",
        "equipment"
    ],
    "wof:name":"Meredith's Software",
    "wof:placetype":"venue"
},
  "geometry": {"coordinates":[-120.76858900000001,38.719036],"type":"Point"}
}