{
  "type": "Feature",
  "properties": {
    "iso:country":"US",
    "sg:address":"11340 W Olympic Blvd Ste 175",
    "sg:city":"Los Angeles",
    "sg:classifiers":[
        {
            "category":"Professional",
            "subcategory":"Lawyer & Legal Services",
            "type":"Services"
        }
    ],
    "sg:phone":"+1 310 479 3813",
    "sg:postcode":"90064",
    "sg:province":"CA",
    "wof:name":"Boyk Carol S Atty",
    "wof:placetype":"venue"
},
  "geometry": {"coordinates":[-118.442001,34.037701],"type":"Point"}
}