{
  "type": "Feature",
  "properties": {
    "addr:full":"2756 Sunrise Blvd #0652 Rancho Cordova CA 95742",
    "addr:housenumber":"2756",
    "addr:postcode":"95742",
    "addr:street":"Sunrise Blvd # 0652",
    "iso:country":"US",
    "sg:address":"2756 Sunrise Blvd #0652",
    "sg:city":"Rancho Cordova",
    "sg:classifiers":[
        {
            "category":"Home & Garden",
            "subcategory":"Hardware",
            "type":"Retail Goods"
        },
        {
            "category":"Home & Garden",
            "subcategory":"Building Materials",
            "type":"Retail Goods"
        }
    ],
    "sg:phone":"+1 916 852 0900",
    "sg:postcode":"95742",
    "sg:province":"CA",
    "sg:tags":[
        "store",
        "supply"
    ],
    "sg:website":"www.homedepot.com",
    "wof:name":"Home Depot",
    "wof:placetype":"venue"
},
  "geometry": {"coordinates":[-121.267983,38.600614],"type":"Point"}
}