{
  "type": "Feature",
  "properties": {
    "addr:full":"3254 Mattos Ave San Jose CA 95132",
    "addr:housenumber":"3254",
    "addr:postcode":"95132",
    "addr:street":"Mattos Ave",
    "iso:country":"US",
    "sg:address":"3254 Mattos Ave",
    "sg:city":"San Jose",
    "sg:classifiers":[
        {
            "category":"Professional",
            "type":"Services"
        }
    ],
    "sg:phone":"+1 408 926 0447",
    "sg:postcode":"95132",
    "sg:province":"CA",
    "wof:name":"A C General Merchandise",
    "wof:placetype":"venue"
},
  "geometry": {"coordinates":[-121.849664,37.40484],"type":"Point"}
}