{
  "type": "Feature",
  "properties": {
    "addr:full":"18065 Euclid St Fountain Valley CA 92708",
    "addr:housenumber":"18065",
    "addr:postcode":"92708",
    "addr:street":"Euclid St",
    "iso:country":"US",
    "sg:address":"18065 Euclid St",
    "sg:city":"Fountain Valley",
    "sg:classifiers":[
        {
            "category":"Retail",
            "subcategory":"Auto Repair",
            "type":"Services"
        }
    ],
    "sg:phone":"+1 714 968 2555",
    "sg:postcode":"92708",
    "sg:province":"CA",
    "sg:tags":[
        "body",
        "shop"
    ],
    "wof:name":"Maaco Auto Painting & Bodyworks",
    "wof:placetype":"venue"
},
  "geometry": {"coordinates":[-117.93699599999999,33.7005],"type":"Point"}
}