{
  "type": "Feature",
  "properties": {
    "iso:country":"US",
    "sg:address":"2121 S El Camino Real Ste A100",
    "sg:city":"San Mateo",
    "sg:classifiers":[
        {
            "category":"Social Services",
            "subcategory":"Child Care",
            "type":"Services"
        },
        {
            "category":"Education",
            "subcategory":"Preschool",
            "type":"Public Place"
        },
        {
            "category":"Education",
            "subcategory":"School",
            "type":"Public Place"
        }
    ],
    "sg:phone":"+1 650 655 6777",
    "sg:postcode":"94403",
    "sg:province":"CA",
    "sg:tags":[
        "elementary",
        "day"
    ],
    "sg:website":"www.sanmateo4cs.org",
    "wof:name":"Child Care Coordinating Council Of San Mateo County Inc",
    "wof:placetype":"venue"
},
  "geometry": {"coordinates":[-122.308423,37.547301],"type":"Point"}
}