{
  "type": "Feature",
  "properties": {
    "addr:full":"1228 W Glenoaks Blvd Glendale CA 91201",
    "addr:housenumber":"1228",
    "addr:postcode":"91201",
    "addr:street":"W Glenoaks Blvd",
    "iso:country":"US",
    "sg:address":"1228 W Glenoaks Blvd",
    "sg:city":"Glendale",
    "sg:classifiers":[
        {
            "category":"Professional",
            "type":"Services"
        }
    ],
    "sg:phone":"+1 818 242 8333",
    "sg:postcode":"91201",
    "sg:province":"CA",
    "sg:tags":[
        "arts",
        "artist"
    ],
    "wof:name":"St George Coptic Art Studio",
    "wof:placetype":"venue"
},
  "geometry": {"coordinates":[-118.282326,34.165526],"type":"Point"}
}