{
  "type": "Feature",
  "properties": {
    "iso:country":"US",
    "sg:address":"4910 Davenport Ave",
    "sg:city":"Oakland",
    "sg:classifiers":[
        {
            "category":"Professional",
            "type":"Services"
        }
    ],
    "sg:phone":"+1 510 531 3235",
    "sg:postcode":"94619",
    "sg:province":"CA",
    "wof:name":"Willie Holman",
    "wof:placetype":"venue"
},
  "geometry": {"coordinates":[-122.180829,37.78457],"type":"Point"}
}