{
  "type": "Feature",
  "properties": {
    "addr:full":"222 Myrtle Rd Burlingame CA 94010",
    "addr:housenumber":"222",
    "addr:postcode":"94010",
    "addr:street":"Myrtle Rd",
    "iso:country":"US",
    "sg:address":"222 Myrtle Rd",
    "sg:city":"Burlingame",
    "sg:classifiers":[
        {
            "category":"Autos & Motor Vehicles",
            "subcategory":"Automobile Sales",
            "type":"Retail Goods"
        }
    ],
    "sg:phone":"+1 650 347 5466",
    "sg:postcode":"94010",
    "sg:province":"CA",
    "sg:tags":[
        "limo"
    ],
    "wof:name":"Limousine Network",
    "wof:placetype":"venue"
},
  "geometry": {"coordinates":[-122.342614,37.580539],"type":"Point"}
}