{
  "type": "Feature",
  "properties": {
    "iso:country":"US",
    "sg:address":"1558 Victory Blvd",
    "sg:city":"Glendale",
    "sg:classifiers":[
        {
            "category":"Professional",
            "subcategory":"Art Services",
            "type":"Services"
        }
    ],
    "sg:phone":"+1 818 549 9919",
    "sg:postcode":"91201",
    "sg:province":"CA",
    "sg:tags":[
        "graphic",
        "designer"
    ],
    "wof:name":"A Latin Methodology-Art Group",
    "wof:placetype":"venue"
},
  "geometry": {"coordinates":[-118.297881,34.159302],"type":"Point"}
}