{
  "type": "Feature",
  "properties": {
    "addr:full":"795 Elliott Rd Paradise CA 95969",
    "addr:housenumber":"795",
    "addr:postcode":"95969",
    "addr:street":"Elliott Rd",
    "iso:country":"US",
    "sg:address":"795 Elliott Rd",
    "sg:city":"Paradise",
    "sg:classifiers":[
        {
            "category":"Retail",
            "subcategory":"Auto Repair",
            "type":"Services"
        }
    ],
    "sg:phone":"+1 530 877 6016",
    "sg:postcode":"95969",
    "sg:province":"CA",
    "sg:tags":[
        "automobile",
        "electric"
    ],
    "wof:name":"D C Auto Electric",
    "wof:placetype":"venue"
},
  "geometry": {"coordinates":[-121.622328,39.759563],"type":"Point"}
}