{
  "type": "Feature",
  "properties": {
    "iso:country":"US",
    "sg:address":"454 E Garvey Ave",
    "sg:city":"Monterey Park",
    "sg:classifiers":[
        {
            "category":"Retail",
            "subcategory":"Auto Repair",
            "type":"Services"
        }
    ],
    "sg:phone":"+1 626 288 7402",
    "sg:postcode":"91755",
    "sg:province":"CA",
    "sg:tags":[
        "body",
        "shop"
    ],
    "wof:name":"R M Body Shop",
    "wof:placetype":"venue"
},
  "geometry": {"coordinates":[-118.114998,34.062401],"type":"Point"}
}