{
  "type": "Feature",
  "properties": {
    "addr:full":"10656 Roselle St San Diego CA 92121",
    "addr:housenumber":"10656",
    "addr:postcode":"92121",
    "addr:street":"Roselle St",
    "iso:country":"US",
    "sg:address":"10656 Roselle St",
    "sg:city":"San Diego",
    "sg:classifiers":[
        {
            "category":"Professional",
            "type":"Services"
        }
    ],
    "sg:phone":"+1 858 784 0710",
    "sg:postcode":"92121",
    "sg:province":"CA",
    "sg:tags":[
        "establishment"
    ],
    "sg:website":"www.reotemp.com",
    "wof:name":"Reotemp Instrument Corp",
    "wof:placetype":"venue"
},
  "geometry": {"coordinates":[-117.222039,32.896975],"type":"Point"}
}