{
  "type": "Feature",
  "properties": {
    "addr:full":"17723 Penny Ct Grass Valley CA 95949",
    "addr:housenumber":"17723",
    "addr:postcode":"95949",
    "addr:street":"Penny Ct",
    "iso:country":"US",
    "sg:address":"17723 Penny Ct",
    "sg:city":"Grass Valley",
    "sg:classifiers":[
        {
            "category":"Retail",
            "subcategory":"Portrait Studio",
            "type":"Services"
        }
    ],
    "sg:phone":"+1 530 273 8300",
    "sg:postcode":"95949",
    "sg:province":"CA",
    "sg:tags":[
        "photographer"
    ],
    "sg:website":"www.verdooner.net",
    "wof:name":"Forensic Imaging Consultants",
    "wof:placetype":"venue"
},
  "geometry": {"coordinates":[-121.058173,39.103869],"type":"Point"}
}