{
  "type": "Feature",
  "properties": {
    "addr:full":"419 E Monterey Ave Pomona CA 91767",
    "addr:housenumber":"419",
    "addr:postcode":"91767",
    "addr:street":"E Monterey Ave",
    "iso:country":"US",
    "sg:address":"419 E Monterey Ave",
    "sg:city":"Pomona",
    "sg:classifiers":[
        {
            "category":"Manufacturing",
            "subcategory":"Printing",
            "type":"Manufacturing & Wholesale Goods"
        }
    ],
    "sg:phone":"+1 909 629 9573",
    "sg:postcode":"91767",
    "sg:province":"CA",
    "sg:tags":[
        "engraver"
    ],
    "wof:name":"Pomona Photo Engraving Co",
    "wof:placetype":"venue"
},
  "geometry": {"coordinates":[-117.74263000000001,34.060821],"type":"Point"}
}