{
  "type": "Feature",
  "properties": {
    "iso:country":"US",
    "sg:address":"1716 4th St",
    "sg:city":"Berkeley",
    "sg:classifiers":[
        {
            "category":"Wholesale",
            "subcategory":"Machinery & Supplies",
            "type":"Manufacturing & Wholesale Goods"
        }
    ],
    "sg:phone":"+1 510 559 9796",
    "sg:postcode":"94710",
    "sg:province":"CA",
    "sg:tags":[
        "salon",
        "beauty"
    ],
    "sg:website":"www.hydrasoap.com",
    "wof:name":"Hydra",
    "wof:placetype":"venue"
},
  "geometry": {"coordinates":[-122.301176,37.871333],"type":"Point"}
}