{
  "type": "Feature",
  "properties": {
    "addr:full":"8750 Baseline Rd Alta Loma CA 91701",
    "addr:housenumber":"8750",
    "addr:postcode":"91701",
    "addr:street":"Baseline Rd",
    "iso:country":"US",
    "sg:address":"8750 Baseline Rd",
    "sg:city":"Alta Loma",
    "sg:classifiers":[
        {
            "category":"Shopping",
            "subcategory":"Pharmacy",
            "type":"Retail Goods"
        }
    ],
    "sg:phone":"+1 909 987 1701",
    "sg:postcode":"91701",
    "sg:province":"CA",
    "wof:name":"Gemmel Pharmacy Group Inc",
    "wof:placetype":"venue"
},
  "geometry": {"coordinates":[-117.614884,34.121637],"type":"Point"}
}