{
  "type": "Feature",
  "properties": {
    "addr:full":"1213 E Hammer Ln Stockton CA 95210",
    "addr:housenumber":"1213",
    "addr:postcode":"95210",
    "addr:street":"E Hammer Ln",
    "iso:country":"US",
    "sg:address":"1213 E Hammer Ln",
    "sg:city":"Stockton",
    "sg:classifiers":[
        {
            "category":"Shopping",
            "subcategory":"Music",
            "type":"Retail Goods"
        }
    ],
    "sg:phone":"+1 209 957 4236",
    "sg:postcode":"95210",
    "sg:province":"CA",
    "sg:tags":[
        "video",
        "disc",
        "tape",
        "cassette"
    ],
    "wof:name":"Video 1000",
    "wof:placetype":"venue"
},
  "geometry": {"coordinates":[-121.296926,38.020992],"type":"Point"}
}