{
  "type": "Feature",
  "properties": {
    "iso:country":"US",
    "sg:address":"19634 Ventura Blvd",
    "sg:city":"Tarzana",
    "sg:classifiers":[
        {
            "category":"Health Services",
            "subcategory":"Health Practitioner",
            "type":"Services"
        }
    ],
    "sg:phone":"+1 818 705 5415",
    "sg:postcode":"91356",
    "sg:province":"CA",
    "sg:tags":[
        "acupuncture"
    ],
    "wof:name":"Cai Dening Acupuncturist",
    "wof:placetype":"venue"
},
  "geometry": {"coordinates":[-118.561563,34.172585],"type":"Point"}
}