{
  "type": "Feature",
  "properties": {
    "iso:country":"US",
    "sg:address":"113 Walnut Ave",
    "sg:city":"Santa Cruz",
    "sg:classifiers":[
        {
            "category":"Restaurant",
            "type":"Food & Drink"
        }
    ],
    "sg:phone":"+1 831 459 9770",
    "sg:postcode":"95060",
    "sg:province":"CA",
    "sg:tags":[
        "middle",
        "eastern"
    ],
    "sg:website":"www.falafelhousesantacruz.com/",
    "wof:name":"Falafel House",
    "wof:placetype":"venue"
},
  "geometry": {"coordinates":[-122.027,36.973301],"type":"Point"}
}