{
  "type": "Feature",
  "properties": {
    "addr:full":"715 Ruberta Ave Glendale CA 91201",
    "addr:housenumber":"715",
    "addr:postcode":"91201",
    "addr:street":"Ruberta Ave",
    "iso:country":"US",
    "sg:address":"715 Ruberta Ave",
    "sg:city":"Glendale",
    "sg:classifiers":[
        {
            "category":"Building & Trades",
            "subcategory":"Cleaning & Sanitation",
            "type":"Services"
        }
    ],
    "sg:phone":"+1 800 900 7876",
    "sg:postcode":"91201",
    "sg:province":"CA",
    "sg:tags":[
        "fire",
        "water",
        "restoration",
        "damage"
    ],
    "wof:name":"Tri-Tech Restoration",
    "wof:placetype":"venue"
},
  "geometry": {"coordinates":[-118.29217300000001,34.163716],"type":"Point"}
}