{
  "type": "Feature",
  "properties": {
    "addr:full":"4553 Hammonton Rd Marysville CA 95901",
    "addr:housenumber":"4553",
    "addr:postcode":"95901",
    "addr:street":"Hammonton Rd",
    "iso:country":"US",
    "sg:address":"4553 Hammonton Rd",
    "sg:city":"Marysville",
    "sg:classifiers":[
        {
            "category":"Wholesale",
            "subcategory":"Construction Materials",
            "type":"Manufacturing & Wholesale Goods"
        }
    ],
    "sg:phone":"+1 530 741 0290",
    "sg:postcode":"95901",
    "sg:province":"CA",
    "sg:tags":[
        "sand",
        "gravel"
    ],
    "wof:name":"Silica Resources Inc",
    "wof:placetype":"venue"
},
  "geometry": {"coordinates":[-121.451671,39.175561],"type":"Point"}
}