{
  "type": "Feature",
  "properties": {
    "addr:full":"22725 Cantlay St Canoga Park CA 91307",
    "addr:postcode":"22725;91307",
    "addr:street":"Cantlay St",
    "iso:country":"US",
    "sg:address":"22725 Cantlay St",
    "sg:city":"Canoga Park",
    "sg:classifiers":[
        {
            "category":"Wholesale",
            "subcategory":"Vending Machines",
            "type":"Manufacturing & Wholesale Goods"
        }
    ],
    "sg:phone":"+1 818 887 3620",
    "sg:postcode":"91307",
    "sg:province":"CA",
    "sg:tags":[
        "operator"
    ],
    "wof:name":"C V R Vending Service",
    "wof:placetype":"venue"
},
  "geometry": {"coordinates":[-118.622137,34.201973],"type":"Point"}
}