{
  "type": "Feature",
  "properties": {
    "iso:country":"US",
    "sg:address":"1510 Charm Way",
    "sg:city":"Sacramento",
    "sg:classifiers":[
        {
            "category":"Wholesale",
            "subcategory":"Medical Equipment & Supplies",
            "type":"Manufacturing & Wholesale Goods"
        }
    ],
    "sg:phone":"+1 916 419 6897",
    "sg:postcode":"95835",
    "sg:province":"CA",
    "wof:name":"Polar Electro Inc",
    "wof:placetype":"venue"
},
  "geometry": {"coordinates":[-121.494576,38.679873],"type":"Point"}
}