{
  "type": "Feature",
  "properties": {
    "addr:full":"77570 Springfield Ln Palm Desert CA 92211",
    "addr:housenumber":"77570",
    "addr:postcode":"ca 92211",
    "addr:street":"Springfield Ln",
    "iso:country":"US",
    "sg:address":"77570 Springfield Ln",
    "sg:city":"Palm Desert",
    "sg:classifiers":[
        {
            "category":"Building & Trades",
            "subcategory":"Construction",
            "type":"Services"
        }
    ],
    "sg:phone":"+1 760 200 9290",
    "sg:postcode":"92211",
    "sg:province":"CA",
    "sg:tags":[
        "contractor"
    ],
    "sg:website":"www.ashbrookcommunities.com",
    "wof:name":"Ashbrook Distinctive Choices",
    "wof:placetype":"venue"
},
  "geometry": {"coordinates":[-116.31117999999999,33.75945],"type":"Point"}
}