{
  "type": "Feature",
  "properties": {
    "iso:country":"US",
    "sg:address":"1119 W Lowen St",
    "sg:city":"Wilmington",
    "sg:classifiers":[
        {
            "category":"Home & Garden",
            "subcategory":"Garden Supply",
            "type":"Retail Goods"
        }
    ],
    "sg:phone":"+1 310 834 3036",
    "sg:postcode":"90744",
    "sg:province":"CA",
    "sg:tags":[
        "sprinkler"
    ],
    "wof:name":"Ricardo Flores",
    "wof:placetype":"venue"
},
  "geometry": {"coordinates":[-118.276318,33.795233],"type":"Point"}
}