{
  "type": "Feature",
  "properties": {
    "addr:full":"12121 Wilshire Blvd Ste 505 Los Angeles CA 90025",
    "addr:housenumber":"12121",
    "addr:postcode":"90025",
    "addr:street":"Wilshire Blvd Ste 505",
    "iso:country":"US",
    "sg:address":"12121 Wilshire Blvd Ste 505",
    "sg:city":"Los Angeles",
    "sg:classifiers":[
        {
            "category":"Education",
            "subcategory":"University",
            "type":"Public Place"
        }
    ],
    "sg:phone":"+1 310 207 8441",
    "sg:postcode":"90025",
    "sg:province":"CA",
    "sg:tags":[
        "college"
    ],
    "wof:name":"Institute Of Contemporary Psychoanalysis",
    "wof:placetype":"venue"
},
  "geometry": {"coordinates":[-118.467758,34.40643],"type":"Point"}
}