{
  "type": "Feature",
  "properties": {
    "addr:full":"921 Armory Rd Barstow CA 92311",
    "addr:housenumber":"921",
    "addr:postcode":"92311",
    "addr:street":"Armory Rd",
    "iso:country":"US",
    "sg:address":"921 Armory Rd",
    "sg:city":"Barstow",
    "sg:classifiers":[
        {
            "category":"Health Services",
            "subcategory":"Optometrist",
            "type":"Services"
        }
    ],
    "sg:phone":"+1 760 252 7518",
    "sg:postcode":"92311",
    "sg:province":"CA",
    "wof:name":"Eye Shop",
    "wof:placetype":"venue"
},
  "geometry": {"coordinates":[-117.014695,34.884122],"type":"Point"}
}