{
  "type": "Feature",
  "properties": {
    "iso:country":"US",
    "sg:address":"1216 W Winton Ave",
    "sg:city":"Hayward",
    "sg:classifiers":[
        {
            "category":"Health Services",
            "subcategory":"Clinic",
            "type":"Services"
        }
    ],
    "sg:phone":"+1 510 887 4466",
    "sg:postcode":"94545",
    "sg:province":"CA",
    "sg:tags":[
        "home",
        "care"
    ],
    "wof:name":"AGM Signs",
    "wof:placetype":"venue"
},
  "geometry": {"coordinates":[-122.113225,37.653049],"type":"Point"}
}