{
  "type": "Feature",
  "properties": {
    "iso:country":"US",
    "sg:address":"7380 Croy Rd",
    "sg:city":"Morgan Hill",
    "sg:classifiers":[
        {
            "category":"Manufacturing",
            "subcategory":"Tools & Machinery",
            "type":"Manufacturing & Wholesale Goods"
        }
    ],
    "sg:phone":"+1 408 779 4898",
    "sg:postcode":"95037",
    "sg:province":"CA",
    "sg:tags":[
        "designed",
        "built"
    ],
    "wof:name":"Quality Design Engineering",
    "wof:placetype":"venue"
},
  "geometry": {"coordinates":[-121.79363,37.08423],"type":"Point"}
}