{
  "type": "Feature",
  "properties": {
    "iso:country":"US",
    "sg:address":"2945 E Broadway",
    "sg:city":"Long Beach",
    "sg:classifiers":[
        {
            "category":"Restaurant",
            "type":"Food & Drink"
        }
    ],
    "sg:menulink":"http://www.allmenus.com/ca/long-beach-lakewood/277633-la-parolaccia-osteria-italiana/menu/",
    "sg:phone":"+1 562 438 1235",
    "sg:postcode":"90803",
    "sg:province":"CA",
    "sg:tags":[
        "italian"
    ],
    "wof:name":"La Parolaccia Osteria Italiana",
    "wof:placetype":"venue"
},
  "geometry": {"coordinates":[-118.157014,33.765118],"type":"Point"}
}