{
  "type": "Feature",
  "properties": {
    "addr:full":"1530 E 12th St Oakland CA 94606",
    "addr:housenumber":"1530",
    "addr:postcode":"94606",
    "addr:street":"E 12Th St",
    "iso:country":"US",
    "sg:address":"1530 E 12th St",
    "sg:city":"Oakland",
    "sg:classifiers":[
        {
            "category":"Health Services",
            "subcategory":"Clinic",
            "type":"Services"
        }
    ],
    "sg:phone":"+1 510 698 4446",
    "sg:postcode":"94606",
    "sg:province":"CA",
    "sg:tags":[
        "medical"
    ],
    "sg:website":"www.steephilllab.com",
    "wof:name":"Steep Hill Lab",
    "wof:placetype":"venue"
},
  "geometry": {"coordinates":[-122.24520200000001,37.788024],"type":"Point"}
}