{
  "type": "Feature",
  "properties": {
    "iso:country":"US",
    "sg:address":"1919 S Catalina Ave",
    "sg:city":"Redondo Beach",
    "sg:classifiers":[
        {
            "category":"Health Services",
            "subcategory":"Chiropractor",
            "type":"Services"
        }
    ],
    "sg:phone":"+1 310 378 7246",
    "sg:postcode":"90277",
    "sg:province":"CA",
    "sg:website":"www.catalinamedical.com",
    "wof:name":"Catalina Medical Ctr",
    "wof:placetype":"venue"
},
  "geometry": {"coordinates":[-118.38675000000001,33.815569],"type":"Point"}
}