{
  "type": "Feature",
  "properties": {
    "iso:country":"US",
    "sg:address":"950 Saxony Rd",
    "sg:city":"Encinitas",
    "sg:classifiers":[
        {
            "category":"Shopping",
            "type":"Retail Goods"
        }
    ],
    "sg:phone":"+1 760 942 5918",
    "sg:postcode":"92024",
    "sg:province":"CA",
    "sg:tags":[
        "merchandise"
    ],
    "wof:name":"Peasantworks",
    "wof:placetype":"venue"
},
  "geometry": {"coordinates":[-117.28576099999999,33.067345],"type":"Point"}
}