{
  "type": "Feature",
  "properties": {
    "iso:country":"US",
    "sg:address":"1115 W Bush St",
    "sg:city":"Lemoore",
    "sg:classifiers":[
        {
            "category":"Food & Beverages",
            "subcategory":"Groceries & Convenience Stores",
            "type":"Retail Goods"
        }
    ],
    "sg:phone":"+1 559 924 2356",
    "sg:postcode":"93245",
    "sg:province":"CA",
    "sg:tags":[
        "grocer"
    ],
    "wof:name":"Discount Dollar Mart-99 Cents",
    "wof:placetype":"venue"
},
  "geometry": {"coordinates":[-119.797275,36.298123],"type":"Point"}
}