{
  "type": "Feature",
  "properties": {
    "iso:country":"US",
    "sg:address":"18685 Loree Ave",
    "sg:city":"Cupertino",
    "sg:classifiers":[
        {
            "category":"Professional",
            "subcategory":"Computer Services",
            "type":"Services"
        }
    ],
    "sg:phone":"+1 408 506 9707",
    "sg:postcode":"95014",
    "sg:province":"CA",
    "sg:tags":[
        "consultant",
        "designer"
    ],
    "wof:name":"S & E Consulting Svc",
    "wof:placetype":"venue"
},
  "geometry": {"coordinates":[-121.996843,37.320384],"type":"Point"}
}