{
  "type": "Feature",
  "properties": {
    "iso:country":"US",
    "sg:address":"822 Sunnybrae Blvd",
    "sg:city":"San Mateo",
    "sg:classifiers":[
        {
            "category":"Social Services",
            "subcategory":"Adult Care",
            "type":"Services"
        }
    ],
    "sg:phone":"+1 650 345 8001",
    "sg:postcode":"94402",
    "sg:province":"CA",
    "sg:tags":[
        "home",
        "residential"
    ],
    "wof:name":"Kaufusi Residential Care Home",
    "wof:placetype":"venue"
},
  "geometry": {"coordinates":[-122.308963,37.560627],"type":"Point"}
}