{
  "type": "Feature",
  "properties": {
    "iso:country":"US",
    "sg:address":"4650 Edison Ave",
    "sg:city":"Chino",
    "sg:classifiers":[
        {
            "category":"Home & Garden",
            "subcategory":"Building Materials",
            "type":"Retail Goods"
        }
    ],
    "sg:phone":"+1 909 591 4841",
    "sg:postcode":"91710",
    "sg:province":"CA",
    "sg:tags":[
        "lumber-used"
    ],
    "wof:name":"Heritage Hardwoods",
    "wof:placetype":"venue"
},
  "geometry": {"coordinates":[-117.703227,33.997206],"type":"Point"}
}