{
  "type": "Feature",
  "properties": {
    "addr:full":"Wells Tax Consulting Corporation 466 Foothill Blvd Ste 308 La Canada Flintridge CA 91011",
    "addr:housenumber":"466",
    "addr:postcode":"91011",
    "addr:street":"Foothill Blvd Ste 308 La Canada",
    "iso:country":"US",
    "sg:address":"Wells Tax Consulting Corporation 466 Foothill Blvd Ste 308",
    "sg:city":"La Canada Flintridge",
    "sg:classifiers":[
        {
            "category":"Professional",
            "subcategory":"Accounting & Tax Preparation",
            "type":"Services"
        }
    ],
    "sg:phone":"+1 818 790 2839",
    "sg:postcode":"91011",
    "sg:province":"CA",
    "sg:tags":[
        "accountant"
    ],
    "wof:name":"Martin Wells, EA, CPA",
    "wof:placetype":"venue"
},
  "geometry": {"coordinates":[-118.18852,34.199026],"type":"Point"}
}