{
  "type": "Feature",
  "properties": {
    "addr:full":"111 Mint Leaf Way Sacramento CA 95838",
    "addr:housenumber":"111",
    "addr:postcode":"95838",
    "addr:street":"Mint Leaf Way",
    "iso:country":"US",
    "sg:address":"111 Mint Leaf Way",
    "sg:city":"Sacramento",
    "sg:classifiers":[
        {
            "category":"Building & Trades",
            "subcategory":"Landscaping Services",
            "type":"Services"
        }
    ],
    "sg:phone":"+1 916 564 1897",
    "sg:postcode":"95838",
    "sg:province":"CA",
    "wof:name":"Simple Solutions",
    "wof:placetype":"venue"
},
  "geometry": {"coordinates":[-121.46021399999999,38.658286],"type":"Point"}
}