{
  "type": "Feature",
  "properties": {
    "iso:country":"US",
    "sg:address":"18596 Lomita Ave",
    "sg:city":"Sonoma",
    "sg:classifiers":[
        {
            "category":"Professional",
            "type":"Services"
        }
    ],
    "sg:phone":"+1 707 938 8272",
    "sg:postcode":"95476",
    "sg:province":"CA",
    "wof:name":"Daniel Docher",
    "wof:placetype":"venue"
},
  "geometry": {"coordinates":[-122.46268000000001,38.314576],"type":"Point"}
}