{
  "type": "Feature",
  "properties": {
    "addr:full":"2654 Pocket Mine Rd Placerville CA 95667",
    "addr:housenumber":"2654",
    "addr:postcode":"95667",
    "addr:street":"Pocket Mine Rd",
    "iso:country":"US",
    "sg:address":"2654 Pocket Mine Rd",
    "sg:city":"Placerville",
    "sg:classifiers":[
        {
            "category":"Professional",
            "type":"Services"
        }
    ],
    "sg:phone":"+1 530 295 1366",
    "sg:postcode":"95667",
    "sg:province":"CA",
    "wof:name":"Running Rock Art",
    "wof:placetype":"venue"
},
  "geometry": {"coordinates":[-120.79226800000001,38.753484],"type":"Point"}
}