{
  "type": "Feature",
  "properties": {
    "iso:country":"US",
    "sg:address":"6876 Bear River Row",
    "sg:city":"San Diego",
    "sg:classifiers":[
        {
            "category":"Social Services",
            "subcategory":"Adult Care",
            "type":"Services"
        }
    ],
    "sg:phone":"+1 619 267 0714",
    "sg:postcode":"92139",
    "sg:province":"CA",
    "sg:tags":[
        "home",
        "residential"
    ],
    "wof:name":"Blessed Home Care Inc",
    "wof:placetype":"venue"
},
  "geometry": {"coordinates":[-117.045039,32.679281],"type":"Point"}
}