{
  "type": "Feature",
  "properties": {
    "addr:full":"7200 Regional St Dublin CA 94568",
    "addr:housenumber":"7200",
    "addr:postcode":"94568",
    "addr:street":"Regional St",
    "iso:country":"US",
    "sg:address":"7200 Regional St",
    "sg:city":"Dublin",
    "sg:classifiers":[
        {
            "category":"Professional",
            "type":"Services"
        },
        {
            "category":"Restaurant",
            "type":"Food & Drink"
        }
    ],
    "sg:phone":"+1 925 829 5292",
    "sg:postcode":"94568",
    "sg:province":"CA",
    "sg:tags":[
        "chinese",
        "caterer"
    ],
    "sg:website":"http://www.chinavillagerestaurant.net",
    "wof:name":"China Village",
    "wof:placetype":"venue"
},
  "geometry": {"coordinates":[-121.93437,37.704379],"type":"Point"}
}