{
  "type": "Feature",
  "properties": {
    "iso:country":"US",
    "sg:address":"3601 W Florida Ave",
    "sg:city":"Hemet",
    "sg:classifiers":[
        {
            "category":"Health Services",
            "subcategory":"Optometrist",
            "type":"Services"
        }
    ],
    "sg:phone":"+1 951 652 3372",
    "sg:postcode":"92545",
    "sg:province":"CA",
    "wof:name":"Eyexam Of California",
    "wof:placetype":"venue"
},
  "geometry": {"coordinates":[-117.011833,33.746486],"type":"Point"}
}