{
  "type": "Feature",
  "properties": {
    "iso:country":"US",
    "sg:address":"84 Alydar Pl",
    "sg:city":"Paso Robles",
    "sg:classifiers":[
        {
            "category":"Real Estate",
            "subcategory":"Developer",
            "type":"Services"
        }
    ],
    "sg:phone":"+1 805 434 3314",
    "sg:postcode":"93446",
    "sg:province":"CA",
    "sg:tags":[
        "cemetery"
    ],
    "wof:name":"Templeton Cemetery District",
    "wof:placetype":"venue"
},
  "geometry": {"coordinates":[-120.70193500000001,35.645224],"type":"Point"}
}