{
  "type": "Feature",
  "properties": {
    "iso:country":"US",
    "sg:address":"201 N Civic Dr",
    "sg:city":"Walnut Creek",
    "sg:classifiers":[
        {
            "category":"Restaurant",
            "type":"Food & Drink"
        }
    ],
    "sg:phone":"+1 925 934 5105",
    "sg:postcode":"94596",
    "sg:province":"CA",
    "sg:tags":[
        "delicatessen"
    ],
    "wof:name":"Civic Garden Deli",
    "wof:placetype":"venue"
},
  "geometry": {"coordinates":[-122.05875399999999,37.90882],"type":"Point"}
}