{
  "type": "Feature",
  "properties": {
    "addr:full":"5818 W Pico Blvd Los Angeles CA 90019",
    "addr:housenumber":"5818",
    "addr:postcode":"90019",
    "addr:street":"W Pico Blvd",
    "iso:country":"US",
    "sg:address":"5818 W Pico Blvd",
    "sg:city":"Los Angeles",
    "sg:classifiers":[
        {
            "category":"Shopping",
            "subcategory":"Clothing, Apparel, & Fashions",
            "type":"Retail Goods"
        }
    ],
    "sg:phone":"+1 323 933 0400",
    "sg:postcode":"90019",
    "sg:province":"CA",
    "sg:tags":[
        "accessory",
        "clothing",
        "women's"
    ],
    "wof:name":"Hi-Fashion Clothing",
    "wof:placetype":"venue"
},
  "geometry": {"coordinates":[-118.365324,34.051201],"type":"Point"}
}