{
  "type": "Feature",
  "properties": {
    "addr:full":"1955 W Texas St Fairfield CA 94533",
    "addr:housenumber":"1955",
    "addr:postcode":"94533",
    "addr:street":"W Texas St",
    "iso:country":"US",
    "sg:address":"1955 W Texas St",
    "sg:city":"Fairfield",
    "sg:classifiers":[
        {
            "category":"Retail",
            "subcategory":"Laundry & Dry Cleaning",
            "type":"Services"
        }
    ],
    "sg:phone":"+1 707 438 0301",
    "sg:postcode":"94533",
    "sg:province":"CA",
    "sg:tags":[
        "cleaners",
        "rug",
        "carpet"
    ],
    "wof:name":"Variety Maintenance",
    "wof:placetype":"venue"
},
  "geometry": {"coordinates":[-122.06296500000001,38.249376],"type":"Point"}
}