{
  "type": "Feature",
  "properties": {
    "addr:full":"4931 Lincoln Ave Cypress CA 90630",
    "addr:housenumber":"4931",
    "addr:postcode":"90630",
    "addr:street":"Lincoln Ave",
    "iso:country":"US",
    "sg:address":"4931 Lincoln Ave",
    "sg:city":"Cypress",
    "sg:classifiers":[
        {
            "category":"Shopping",
            "subcategory":"Books",
            "type":"Retail Goods"
        }
    ],
    "sg:phone":"+1 714 761 1552",
    "sg:postcode":"90630",
    "sg:province":"CA",
    "sg:tags":[
        "bookstore"
    ],
    "wof:name":"Sunshine Books",
    "wof:placetype":"venue"
},
  "geometry": {"coordinates":[-118.046997,33.831902],"type":"Point"}
}