{
  "type": "Feature",
  "properties": {
    "addr:full":"2690 N State St Ukiah CA 95482",
    "addr:housenumber":"2690",
    "addr:postcode":"ca 95482",
    "addr:street":"N State St",
    "iso:country":"US",
    "sg:address":"2690 N State St",
    "sg:city":"Ukiah",
    "sg:classifiers":[
        {
            "category":"Government",
            "subcategory":"Office",
            "type":"Public Place"
        }
    ],
    "sg:phone":"+1 707 463 4716",
    "sg:postcode":"95482",
    "sg:province":"CA",
    "wof:name":"Dept Of Gen Svc Radio Shop",
    "wof:placetype":"venue"
},
  "geometry": {"coordinates":[-123.209637,39.184208],"type":"Point"}
}