{
  "type": "Feature",
  "properties": {
    "iso:country":"US",
    "sg:address":"2101 White Ln",
    "sg:city":"Bakersfield",
    "sg:classifiers":[
        {
            "category":"Utilities",
            "subcategory":"Recycling",
            "type":"Services"
        }
    ],
    "sg:phone":"+1 661 834 2363",
    "sg:postcode":"93304",
    "sg:province":"CA",
    "wof:name":"Joey Recycling Center",
    "wof:placetype":"venue"
},
  "geometry": {"coordinates":[-119.026625,35.317603],"type":"Point"}
}