{
  "type": "Feature",
  "properties": {
    "addr:full":"591 Broadway Sonoma CA 95476",
    "addr:housenumber":"591",
    "addr:postcode":"95476",
    "addr:street":"Broadway",
    "iso:country":"US",
    "sg:address":"591 Broadway",
    "sg:city":"Sonoma",
    "sg:classifiers":[
        {
            "category":"Banks & Credit Unions",
            "subcategory":"Bank",
            "type":"Services"
        }
    ],
    "sg:phone":"+1 707 939 2210",
    "sg:postcode":"95476",
    "sg:province":"CA",
    "wof:name":"Washington Mutual",
    "wof:placetype":"venue"
},
  "geometry": {"coordinates":[-122.458178,38.290306],"type":"Point"}
}