{
  "type": "Feature",
  "properties": {
    "iso:country":"US",
    "sg:address":"125 Briggs Ranch Dr",
    "sg:city":"Folsom",
    "sg:classifiers":[
        {
            "category":"Retail",
            "subcategory":"Portrait Studio",
            "type":"Services"
        }
    ],
    "sg:phone":"+1 916 947 5098",
    "sg:postcode":"95630",
    "sg:province":"CA",
    "sg:tags":[
        "photographer"
    ],
    "wof:name":"DSS",
    "wof:placetype":"venue"
},
  "geometry": {"coordinates":[-121.138739,38.69008],"type":"Point"}
}