{
  "type": "Feature",
  "properties": {
    "addr:full":"4860 Irvine Blvd Irvine CA 92620",
    "addr:housenumber":"4860",
    "addr:postcode":"92620",
    "addr:street":"Irvine Blvd",
    "iso:country":"US",
    "sg:address":"4860 Irvine Blvd",
    "sg:city":"Irvine",
    "sg:classifiers":[
        {
            "category":"Professional",
            "subcategory":"Lawyer & Legal Services",
            "type":"Services"
        }
    ],
    "sg:phone":"+1 949 249 9033",
    "sg:postcode":"92620",
    "sg:province":"CA",
    "wof:name":"Risner Mark T Atty At Law",
    "wof:placetype":"venue"
},
  "geometry": {"coordinates":[-117.759198,33.712597],"type":"Point"}
}