{
  "type": "Feature",
  "properties": {
    "iso:country":"US",
    "sg:address":"38020 6th St E",
    "sg:city":"Palmdale",
    "sg:classifiers":[
        {
            "category":"Retail",
            "subcategory":"Auto Repair",
            "type":"Services"
        }
    ],
    "sg:phone":"+1 661 947 7499",
    "sg:postcode":"93550",
    "sg:province":"CA",
    "sg:tags":[
        "repairing",
        "automobile"
    ],
    "wof:name":"Amigos Auto Repair",
    "wof:placetype":"venue"
},
  "geometry": {"coordinates":[-118.117031,34.572643],"type":"Point"}
}