{
  "type": "Feature",
  "properties": {
    "iso:country":"US",
    "sg:address":"824 S Auburn St",
    "sg:city":"Grass Valley",
    "sg:classifiers":[
        {
            "category":"Retail",
            "subcategory":"Auto Repair",
            "type":"Services"
        }
    ],
    "sg:phone":"+1 530 271 7357",
    "sg:postcode":"95945",
    "sg:province":"CA",
    "sg:tags":[
        "repairing",
        "automobile"
    ],
    "wof:name":"Douglas Automotive",
    "wof:placetype":"venue"
},
  "geometry": {"coordinates":[-121.060077,39.201764],"type":"Point"}
}