{
  "type": "Feature",
  "properties": {
    "addr:full":"9895 Warner Ave Ste A Fountain Valley CA 92708",
    "addr:housenumber":"9895",
    "addr:postcode":"92708",
    "addr:street":"Warner Ave Ste A",
    "iso:country":"US",
    "sg:address":"9895 Warner Ave Ste A",
    "sg:city":"Fountain Valley",
    "sg:classifiers":[
        {
            "category":"Food & Beverages",
            "subcategory":"Groceries & Convenience Stores",
            "type":"Retail Goods"
        }
    ],
    "sg:phone":"+1 714 378 0588",
    "sg:postcode":"92708",
    "sg:province":"CA",
    "wof:name":"Hamle Super Market",
    "wof:placetype":"venue"
},
  "geometry": {"coordinates":[-117.956367,33.716625],"type":"Point"}
}