{
  "type": "Feature",
  "properties": {
    "addr:full":"392 Elizabeth Ln Corona CA 92880",
    "addr:housenumber":"392",
    "addr:postcode":"92880",
    "addr:street":"Elizabeth Ln",
    "iso:country":"US",
    "sg:address":"392 Elizabeth Ln",
    "sg:city":"Corona",
    "sg:classifiers":[
        {
            "category":"Manufacturing",
            "subcategory":"Watercraft",
            "type":"Manufacturing & Wholesale Goods"
        }
    ],
    "sg:phone":"+1 951 371 7567",
    "sg:postcode":"92880",
    "sg:province":"CA",
    "sg:tags":[
        "hardware",
        "transportation",
        "mfg"
    ],
    "wof:name":"Wpm Racing",
    "wof:placetype":"venue"
},
  "geometry": {"coordinates":[-117.597408,33.891125],"type":"Point"}
}