{
  "type": "Feature",
  "properties": {
    "addr:full":"2340 Powell St Ste 223 Emeryville CA 94608",
    "addr:housenumber":"2340",
    "addr:postcode":"94608",
    "addr:street":"Powell St Ste 223",
    "iso:country":"US",
    "sg:address":"2340 Powell St Ste 223",
    "sg:city":"Emeryville",
    "sg:classifiers":[
        {
            "category":"Professional",
            "subcategory":"Management & Consulting",
            "type":"Services"
        }
    ],
    "sg:phone":"+1 510 301 0668",
    "sg:postcode":"94608",
    "sg:province":"CA",
    "sg:tags":[
        "consultant"
    ],
    "wof:name":"Craig Hart Consulting",
    "wof:placetype":"venue"
},
  "geometry": {"coordinates":[-122.303214,37.837166],"type":"Point"}
}