{
  "type": "Feature",
  "properties": {
    "iso:country":"US",
    "sg:address":"85 Magnolia Ave",
    "sg:city":"Clovis",
    "sg:classifiers":[
        {
            "category":"Insurance",
            "subcategory":"Insurance Agent",
            "type":"Services"
        }
    ],
    "sg:phone":"+1 559 322 7300",
    "sg:postcode":"93611",
    "sg:province":"CA",
    "wof:name":"Eckrich Insurance Services",
    "wof:placetype":"venue"
},
  "geometry": {"coordinates":[-119.667317,36.829174],"type":"Point"}
}