{
  "type": "Feature",
  "properties": {
    "iso:country":"US",
    "sg:address":"3580 Orcutt Rd",
    "sg:city":"Santa Maria",
    "sg:classifiers":[
        {
            "category":"Food & Beverages",
            "subcategory":"Groceries & Convenience Stores",
            "type":"Retail Goods"
        }
    ],
    "sg:phone":"+1 805 937 3702",
    "sg:postcode":"93455",
    "sg:province":"CA",
    "sg:tags":[
        "grocer"
    ],
    "sg:website":"www.spencersfreshmarkets.com",
    "wof:name":"Spencer's Fresh Markets",
    "wof:placetype":"venue"
},
  "geometry": {"coordinates":[-120.435997,34.8946],"type":"Point"}
}