{
  "type": "Feature",
  "properties": {
    "iso:country":"US",
    "sg:address":"1200 3rd Ave",
    "sg:city":"San Diego",
    "sg:classifiers":[
        {
            "category":"Government",
            "subcategory":"Office",
            "type":"Public Place"
        }
    ],
    "sg:phone":"+1 619 236 6050",
    "sg:postcode":"92101",
    "sg:province":"CA",
    "sg:tags":[
        "executive"
    ],
    "wof:name":"Real Estate Assets",
    "wof:placetype":"venue"
},
  "geometry": {"coordinates":[-117.16202699999999,32.71884],"type":"Point"}
}