{
  "type": "Feature",
  "properties": {
    "addr:full":"7050 Friars Rd San Diego CA 92108",
    "addr:housenumber":"7050",
    "addr:postcode":"92108",
    "addr:street":"Friars Rd",
    "iso:country":"US",
    "sg:address":"7050 Friars Rd",
    "sg:city":"San Diego",
    "sg:classifiers":[
        {
            "category":"Professional",
            "subcategory":"Management & Consulting",
            "type":"Services"
        }
    ],
    "sg:phone":"+1 619 683 5544",
    "sg:postcode":"92108",
    "sg:province":"CA",
    "sg:tags":[
        "consultant",
        "government"
    ],
    "wof:name":"J Whalen Assoc",
    "wof:placetype":"venue"
},
  "geometry": {"coordinates":[-117.166083,32.769927],"type":"Point"}
}