{
  "type": "Feature",
  "properties": {
    "addr:full":"20665 Lomita Ave Saratoga CA 95070",
    "addr:postcode":"20665;95070",
    "addr:street":"Lomita Ave",
    "iso:country":"US",
    "sg:address":"20665 Lomita Ave",
    "sg:city":"Saratoga",
    "sg:classifiers":[
        {
            "category":"Real Estate",
            "subcategory":"Real Estate Services",
            "type":"Services"
        },
        {
            "category":"Real Estate",
            "subcategory":"Real Estate Agent",
            "type":"Services"
        }
    ],
    "sg:phone":"+1 408 568 4713",
    "sg:postcode":"95070",
    "sg:province":"CA",
    "sg:tags":[
        "buyer",
        "broker"
    ],
    "wof:name":"Lifetime Real Estate Group",
    "wof:placetype":"venue"
},
  "geometry": {"coordinates":[-122.034982,37.254512],"type":"Point"}
}