{
  "type": "Feature",
  "properties": {
    "addr:full":"5922 Edinger Ave Huntington Beach CA 92649",
    "addr:housenumber":"5922",
    "addr:postcode":"92649",
    "addr:street":"Edinger Ave",
    "iso:country":"US",
    "sg:address":"5922 Edinger Ave",
    "sg:city":"Huntington Beach",
    "sg:classifiers":[
        {
            "category":"Banks & Credit Unions",
            "subcategory":"Bank",
            "type":"Services"
        }
    ],
    "sg:phone":"+1 714 377 6633",
    "sg:postcode":"92649",
    "sg:province":"CA",
    "sg:website":"usbank.com",
    "wof:name":"US Bank",
    "wof:placetype":"venue"
},
  "geometry": {"coordinates":[-118.024905,33.729921],"type":"Point"}
}