{
  "type": "Feature",
  "properties": {
    "addr:full":"234 E 17th St Costa Mesa CA 92627",
    "addr:housenumber":"234",
    "addr:postcode":"92627",
    "addr:street":"E 17Th St",
    "iso:country":"US",
    "sg:address":"234 E 17th St",
    "sg:city":"Costa Mesa",
    "sg:classifiers":[
        {
            "category":"Real Estate",
            "subcategory":"Real Estate Services",
            "type":"Services"
        },
        {
            "category":"Real Estate",
            "subcategory":"Real Estate Operator",
            "type":"Services"
        }
    ],
    "sg:phone":"+1 714 557 2481",
    "sg:postcode":"92627",
    "sg:province":"CA",
    "sg:tags":[
        "apartment",
        "property",
        "management"
    ],
    "wof:name":"South Court Townhomes Apartments",
    "wof:placetype":"venue"
},
  "geometry": {"coordinates":[-117.917102,33.634464],"type":"Point"}
}