{
  "type": "Feature",
  "properties": {
    "iso:country":"US",
    "sg:address":"711 N Main St",
    "sg:city":"Fort Bragg",
    "sg:classifiers":[
        {
            "category":"Manufacturing",
            "subcategory":"Printing",
            "type":"Manufacturing & Wholesale Goods"
        }
    ],
    "sg:phone":"+1 707 964 2522",
    "sg:postcode":"95437",
    "sg:province":"CA",
    "sg:tags":[
        "printer"
    ],
    "sg:website":"www.studio-z.com",
    "wof:name":"Zida Borcich Letterpress",
    "wof:placetype":"venue"
},
  "geometry": {"coordinates":[-123.806004,39.449411],"type":"Point"}
}