{
  "type": "Feature",
  "properties": {
    "iso:country":"US",
    "sg:address":"20 Foxboro",
    "sg:city":"Irvine",
    "sg:classifiers":[
        {
            "category":"Professional",
            "subcategory":"Lawyer & Legal Services",
            "type":"Services"
        }
    ],
    "sg:phone":"+1 714 752 1100",
    "sg:postcode":"92614",
    "sg:province":"CA",
    "sg:tags":[
        "attorney"
    ],
    "wof:name":"Gibson Haglund & Johnson",
    "wof:placetype":"venue"
},
  "geometry": {"coordinates":[-117.80155499999999,33.669023],"type":"Point"}
}