{
  "type": "Feature",
  "properties": {
    "addr:full":"3394 E Butler Ave Fresno CA 93702",
    "addr:housenumber":"3394",
    "addr:postcode":"93702",
    "addr:street":"E Butler Ave",
    "iso:country":"US",
    "sg:address":"3394 E Butler Ave",
    "sg:city":"Fresno",
    "sg:classifiers":[
        {
            "category":"Food & Beverages",
            "subcategory":"Meat & Fish",
            "type":"Retail Goods"
        }
    ],
    "sg:phone":"+1 559 237 3350",
    "sg:postcode":"93702",
    "sg:province":"CA",
    "wof:name":"Los Primos Carniceria",
    "wof:placetype":"venue"
},
  "geometry": {"coordinates":[-119.767534,36.72859],"type":"Point"}
}