{
  "type": "Feature",
  "properties": {
    "iso:country":"US",
    "sg:address":"15551 Highcliff St",
    "sg:city":"Westminster",
    "sg:classifiers":[
        {
            "category":"Shopping",
            "subcategory":"Bicycles & Sporting Goods",
            "type":"Retail Goods"
        }
    ],
    "sg:phone":"+1 714 901 5094",
    "sg:postcode":"92683",
    "sg:province":"CA",
    "wof:name":"Calliente Sales",
    "wof:placetype":"venue"
},
  "geometry": {"coordinates":[-117.971605,33.73607],"type":"Point"}
}