{
  "type": "Feature",
  "properties": {
    "iso:country":"US",
    "sg:address":"13195 Yorba Ave",
    "sg:city":"Chino",
    "sg:classifiers":[
        {
            "category":"Personal",
            "type":"Services"
        },
        {
            "category":"Retail",
            "subcategory":"Auto Repair",
            "type":"Services"
        }
    ],
    "sg:phone":"+1 909 517 3400",
    "sg:postcode":"91710",
    "sg:province":"CA",
    "sg:tags":[
        "body",
        "repairing",
        "automobile",
        "dent",
        "towing",
        "removal",
        "painting"
    ],
    "wof:name":"Pro Towing & Service",
    "wof:placetype":"venue"
},
  "geometry": {"coordinates":[-117.702342,34.014246],"type":"Point"}
}