{
  "type": "Feature",
  "properties": {
    "iso:country":"US",
    "sg:address":"4375 Admiralty Way",
    "sg:city":"Marina Del Rey",
    "sg:classifiers":[
        {
            "category":"Professional",
            "type":"Services"
        }
    ],
    "sg:phone":"+1 310 822 3038",
    "sg:postcode":"90292",
    "sg:province":"CA",
    "wof:name":"E Process Control Inc",
    "wof:placetype":"venue"
},
  "geometry": {"coordinates":[-118.45228899999999,33.98513],"type":"Point"}
}