{
  "type": "Feature",
  "properties": {
    "addr:full":"2837 Whipple Rd Union City CA 94587",
    "addr:housenumber":"2837",
    "addr:postcode":"94587",
    "addr:street":"Whipple Rd",
    "iso:country":"US",
    "sg:address":"2837 Whipple Rd",
    "sg:city":"Union City",
    "sg:classifiers":[
        {
            "category":"Manufacturing",
            "subcategory":"Wood Products",
            "type":"Manufacturing & Wholesale Goods"
        }
    ],
    "sg:phone":"+1 510 489 8866",
    "sg:postcode":"94587",
    "sg:province":"CA",
    "sg:tags":[
        "mfg"
    ],
    "wof:name":"E E C International Express",
    "wof:placetype":"venue"
},
  "geometry": {"coordinates":[-122.075402,37.605744],"type":"Point"}
}