{
  "type": "Feature",
  "properties": {
    "iso:country":"US",
    "sg:address":"225 S Festival Dr",
    "sg:city":"Anaheim",
    "sg:classifiers":[
        {
            "category":"Real Estate",
            "subcategory":"Real Estate Operator",
            "type":"Services"
        }
    ],
    "sg:phone":"+1 714 282 2276",
    "sg:postcode":"92808",
    "sg:province":"CA",
    "sg:tags":[
        "apartment"
    ],
    "wof:name":"The Fountains",
    "wof:placetype":"venue"
},
  "geometry": {"coordinates":[-117.751999,33.864601],"type":"Point"}
}