{
  "type": "Feature",
  "properties": {
    "iso:country":"US",
    "sg:address":"44 S Raymond Ave",
    "sg:city":"Pasadena",
    "sg:classifiers":[
        {
            "category":"Shopping",
            "subcategory":"Crafts & Fabrics",
            "type":"Retail Goods"
        }
    ],
    "sg:phone":"+1 626 795 4985",
    "sg:postcode":"91105",
    "sg:province":"CA",
    "sg:tags":[
        "art",
        "supply"
    ],
    "sg:website":"www.dickblick.com",
    "wof:name":"Blick Art Materials",
    "wof:placetype":"venue"
},
  "geometry": {"coordinates":[-118.148895,34.144936],"type":"Point"}
}