{
  "type": "Feature",
  "properties": {
    "iso:country":"US",
    "sg:address":"2740 S Bristol St Ste 100",
    "sg:city":"Santa Ana",
    "sg:classifiers":[
        {
            "category":"Health Services",
            "subcategory":"Doctor",
            "type":"Services"
        }
    ],
    "sg:phone":"+1 714 825 1844",
    "sg:postcode":"92704",
    "sg:province":"CA",
    "wof:name":"Lopez Jorge R MD",
    "wof:placetype":"venue"
},
  "geometry": {"coordinates":[-117.905998,33.7257],"type":"Point"}
}