{
  "type": "Feature",
  "properties": {
    "addr:full":"17207 S Broadway St Gardena CA 90248",
    "addr:housenumber":"17207",
    "addr:postcode":"90248",
    "addr:street":"S Broadway St",
    "iso:country":"US",
    "sg:address":"17207 S Broadway St",
    "sg:city":"Gardena",
    "sg:classifiers":[
        {
            "category":"Professional",
            "type":"Services"
        }
    ],
    "sg:phone":"+1 310 324 1759",
    "sg:postcode":"90248",
    "sg:province":"CA",
    "sg:website":"www.quickdrawsigns.biz",
    "wof:name":"Quickdraw Signs and Graphics",
    "wof:placetype":"venue"
},
  "geometry": {"coordinates":[-118.278094,33.874795],"type":"Point"}
}