{
  "type": "Feature",
  "properties": {
    "addr:full":"2211 N Lakewood Blvd Long Beach CA 90815",
    "addr:housenumber":"2211",
    "addr:postcode":"90815",
    "addr:street":"N Lakewood Blvd",
    "iso:country":"US",
    "sg:address":"2211 N Lakewood Blvd",
    "sg:city":"Long Beach",
    "sg:classifiers":[
        {
            "category":"Professional",
            "subcategory":"Computer Services",
            "type":"Services"
        }
    ],
    "sg:phone":"+1 888 999 8357",
    "sg:postcode":"90815",
    "sg:province":"CA",
    "sg:tags":[
        "repair"
    ],
    "sg:website":"www.thesuperteks.com",
    "wof:name":"SuperTeks Computer Repair",
    "wof:placetype":"venue"
},
  "geometry": {"coordinates":[-118.14280100000001,33.796495],"type":"Point"}
}