{
  "type": "Feature",
  "properties": {
    "iso:country":"US",
    "sg:address":"1517 Webster St",
    "sg:city":"Alameda",
    "sg:classifiers":[
        {
            "category":"Shopping",
            "subcategory":"Florist",
            "type":"Retail Goods"
        }
    ],
    "sg:phone":"+1 510 521 2370",
    "sg:postcode":"94501",
    "sg:province":"CA",
    "wof:name":"Alameda Florist",
    "wof:placetype":"venue"
},
  "geometry": {"coordinates":[-122.277,37.773899],"type":"Point"}
}