{
  "type": "Feature",
  "properties": {
    "iso:country":"US",
    "sg:address":"3810 Jefferson Ave",
    "sg:city":"Redwood City",
    "sg:classifiers":[
        {
            "category":"Building & Trades",
            "subcategory":"Landscaping Services",
            "type":"Services"
        }
    ],
    "sg:phone":"+1 650 366 3203",
    "sg:postcode":"94062",
    "sg:province":"CA",
    "wof:name":"A Saroberrys Yard Service",
    "wof:placetype":"venue"
},
  "geometry": {"coordinates":[-122.257226,37.460448],"type":"Point"}
}