{
  "type": "Feature",
  "properties": {
    "iso:country":"US",
    "sg:address":"1015 S Harbor Blvd",
    "sg:city":"Fullerton",
    "sg:classifiers":[
        {
            "category":"Travel",
            "subcategory":"Hotels & Motels",
            "type":"Entertainment"
        }
    ],
    "sg:phone":"+1 714 447 4373",
    "sg:postcode":"92832",
    "sg:province":"CA",
    "sg:tags":[
        "operation"
    ],
    "wof:name":"Devendra P Barot",
    "wof:placetype":"venue"
},
  "geometry": {"coordinates":[-117.924285,33.86119],"type":"Point"}
}