{
  "type": "Feature",
  "properties": {
    "addr:full":"17977 Apache Trl Los Gatos CA 95033",
    "addr:housenumber":"17977",
    "addr:postcode":"95033",
    "addr:street":"Apache Trl",
    "iso:country":"US",
    "sg:address":"17977 Apache Trl",
    "sg:city":"Los Gatos",
    "sg:classifiers":[
        {
            "category":"Banks & Credit Unions",
            "subcategory":"Bank",
            "type":"Services"
        }
    ],
    "sg:phone":"+1 408 353 2700",
    "sg:postcode":"95033",
    "sg:province":"CA",
    "sg:tags":[
        "machine",
        "teller",
        "automated"
    ],
    "wof:name":"Atm Concepts Inc",
    "wof:placetype":"venue"
},
  "geometry": {"coordinates":[-121.98384299999999,37.163869],"type":"Point"}
}