{
  "type": "Feature",
  "properties": {
    "iso:country":"US",
    "sg:address":"5120 E la Palma Ave",
    "sg:city":"Anaheim",
    "sg:classifiers":[
        {
            "category":"Health Services",
            "subcategory":"Hospice",
            "type":"Services"
        }
    ],
    "sg:phone":"+1 714 970 0081",
    "sg:postcode":"92807",
    "sg:province":"CA",
    "wof:name":"Sunrise Hospice Care Corporation",
    "wof:placetype":"venue"
},
  "geometry": {"coordinates":[-117.806371,33.859491],"type":"Point"}
}