{
  "type": "Feature",
  "properties": {
    "iso:country":"US",
    "sg:address":"10638 Ramona Ave",
    "sg:city":"Montclair",
    "sg:classifiers":[
        {
            "category":"Autos & Motor Vehicles",
            "subcategory":"Auto Supplies",
            "type":"Retail Goods"
        },
        {
            "category":"Retail",
            "subcategory":"Auto Repair",
            "type":"Services"
        }
    ],
    "sg:phone":"+1 909 622 5665",
    "sg:postcode":"91763",
    "sg:province":"CA",
    "sg:tags":[
        "automotive",
        "parts",
        "automobile"
    ],
    "wof:name":"Road Haus Motorsport",
    "wof:placetype":"venue"
},
  "geometry": {"coordinates":[-117.707061,34.061139],"type":"Point"}
}