{
  "type": "Feature",
  "properties": {
    "addr:full":"359 Parkway Plz El Cajon CA 92020",
    "addr:housenumber":"359",
    "addr:postcode":"92020",
    "addr:street":"Parkway Plz",
    "iso:country":"US",
    "sg:address":"359 Parkway Plz",
    "sg:city":"El Cajon",
    "sg:classifiers":[
        {
            "category":"Shopping",
            "subcategory":"Clothing, Apparel, & Fashions",
            "type":"Retail Goods"
        }
    ],
    "sg:phone":"+1 619 401 8937",
    "sg:postcode":"92020",
    "sg:province":"CA",
    "sg:tags":[
        "accessory",
        "clothing",
        "women's"
    ],
    "wof:name":"Forever 21",
    "wof:placetype":"venue"
},
  "geometry": {"coordinates":[-116.96399700000001,32.805599],"type":"Point"}
}