{
  "type": "Feature",
  "properties": {
    "addr:full":"1805 Lomita Blvd Lomita CA 90717",
    "addr:housenumber":"1805",
    "addr:postcode":"90717",
    "addr:street":"Lomita Blvd",
    "iso:country":"US",
    "sg:address":"1805 Lomita Blvd",
    "sg:city":"Lomita",
    "sg:classifiers":[
        {
            "category":"Personal",
            "subcategory":"Hair Removal",
            "type":"Services"
        }
    ],
    "sg:phone":"+1 310 530 1640",
    "sg:postcode":"90717",
    "sg:province":"CA",
    "sg:tags":[
        "removing"
    ],
    "wof:name":"Ramon Hair Waxing",
    "wof:placetype":"venue"
},
  "geometry": {"coordinates":[-118.309403,33.79799],"type":"Point"}
}