{
  "type": "Feature",
  "properties": {
    "addr:full":"3750 Schaufele Avenue Long Beach CA 90808",
    "addr:housenumber":"3750",
    "addr:postcode":"90808",
    "addr:street":"Schaufele Avenue",
    "iso:country":"US",
    "sg:address":"3750 Schaufele Avenue",
    "sg:city":"Long Beach",
    "sg:classifiers":[
        {
            "category":"Professional",
            "type":"Services"
        },
        {
            "category":"Restaurant",
            "type":"Food & Drink"
        }
    ],
    "sg:phone":"+1 562 256 6179",
    "sg:postcode":"90808",
    "sg:province":"CA",
    "sg:tags":[
        "pizza",
        "caterer"
    ],
    "sg:website":"pettolapizza.com",
    "wof:name":"Pettola Pizza",
    "wof:placetype":"venue"
},
  "geometry": {"coordinates":[-118.148359,33.825799],"type":"Point"}
}