{
  "type": "Feature",
  "properties": {
    "iso:country":"US",
    "sg:address":"685 E Carnegie Dr",
    "sg:city":"San Bernardino",
    "sg:classifiers":[
        {
            "category":"Health Services",
            "subcategory":"Clinic",
            "type":"Services"
        }
    ],
    "sg:phone":"+1 213 413 6219",
    "sg:postcode":"92408",
    "sg:province":"CA",
    "sg:tags":[
        "donor",
        "organ",
        "procurement"
    ],
    "wof:name":"One Lagacy",
    "wof:placetype":"venue"
},
  "geometry": {"coordinates":[-117.27456,34.068396],"type":"Point"}
}