{
  "type": "Feature",
  "properties": {
    "addr:full":"9831 Valley Home Rd Oakdale CA 95361",
    "addr:housenumber":"9831",
    "addr:postcode":"95361",
    "addr:street":"Valley Home Rd",
    "iso:country":"US",
    "sg:address":"9831 Valley Home Rd",
    "sg:city":"Oakdale",
    "sg:classifiers":[
        {
            "category":"Bars & Pubs",
            "type":"Food & Drink"
        }
    ],
    "sg:phone":"+1 209 847 2474",
    "sg:postcode":"95361",
    "sg:province":"CA",
    "sg:tags":[
        "lounge",
        "cocktail"
    ],
    "wof:name":"Whiskey River Saloon",
    "wof:placetype":"venue"
},
  "geometry": {"coordinates":[-120.855403,37.780992],"type":"Point"}
}