{
  "type": "Feature",
  "properties": {
    "addr:full":"929 Madrone Rd Glen Ellen CA 95442",
    "addr:housenumber":"929",
    "addr:postcode":"95442",
    "addr:street":"Madrone Rd",
    "iso:country":"US",
    "sg:address":"929 Madrone Rd",
    "sg:city":"Glen Ellen",
    "sg:classifiers":[
        {
            "category":"Food & Beverages",
            "subcategory":"Groceries & Convenience Stores",
            "type":"Retail Goods"
        }
    ],
    "sg:phone":"+1 707 935 3996",
    "sg:postcode":"95442",
    "sg:province":"CA",
    "sg:tags":[
        "market"
    ],
    "wof:name":"Madrone Market",
    "wof:placetype":"venue"
},
  "geometry": {"coordinates":[-122.50926699999999,38.339915],"type":"Point"}
}