{
  "type": "Feature",
  "properties": {
    "addr:full":"7320 Woodlake Ave Ste 310 West Hills CA 91307",
    "addr:housenumber":"7320",
    "addr:postcode":"91307",
    "addr:street":"Woodlake Ave Ste 310",
    "iso:country":"US",
    "sg:address":"7320 Woodlake Ave Ste 310",
    "sg:city":"West Hills",
    "sg:classifiers":[
        {
            "category":"Health Services",
            "subcategory":"Doctor",
            "type":"Services"
        }
    ],
    "sg:phone":"+1 818 703 7412",
    "sg:postcode":"91307",
    "sg:province":"CA",
    "wof:name":"Top Surgeons",
    "wof:placetype":"venue"
},
  "geometry": {"coordinates":[-118.63213,34.20291],"type":"Point"}
}