{
  "type": "Feature",
  "properties": {
    "addr:full":"1500 E Hamilton Ave Ste 202 Campbell CA 95008",
    "addr:housenumber":"1500",
    "addr:postcode":"95008",
    "addr:street":"E Hamilton Ave Ste 202",
    "iso:country":"US",
    "sg:address":"1500 E Hamilton Ave Ste 202",
    "sg:city":"Campbell",
    "sg:classifiers":[
        {
            "category":"Professional",
            "subcategory":"Lawyer & Legal Services",
            "type":"Services"
        }
    ],
    "sg:phone":"+1 408 879 8500",
    "sg:postcode":"95008",
    "sg:province":"CA",
    "wof:name":"Omni Law Group LLP",
    "wof:placetype":"venue"
},
  "geometry": {"coordinates":[-121.923528,37.294181],"type":"Point"}
}