{
  "type": "Feature",
  "properties": {
    "iso:country":"US",
    "sg:address":"11450 Huntsman Leap",
    "sg:city":"Truckee",
    "sg:classifiers":[
        {
            "category":"Retail",
            "subcategory":"Repair Shop",
            "type":"Services"
        }
    ],
    "sg:phone":"+1 530 587 9534",
    "sg:postcode":"96161",
    "sg:province":"CA",
    "sg:tags":[
        "welding"
    ],
    "wof:name":"Sprague's Construction",
    "wof:placetype":"venue"
},
  "geometry": {"coordinates":[-120.103028,39.369369],"type":"Point"}
}