{
  "type": "Feature",
  "properties": {
    "iso:country":"US",
    "sg:address":"1802 N Kenmore Ave",
    "sg:city":"Los Angeles",
    "sg:classifiers":[
        {
            "category":"Arts & Performance",
            "subcategory":"Theater",
            "type":"Entertainment"
        }
    ],
    "sg:phone":"+1 323 665 4004",
    "sg:postcode":"90027",
    "sg:province":"CA",
    "sg:tags":[
        "theatrical",
        "manager",
        "producer"
    ],
    "sg:website":"www.bluemaxent.com",
    "wof:name":"Blue Max Management",
    "wof:placetype":"venue"
},
  "geometry": {"coordinates":[-118.297183,34.103525],"type":"Point"}
}