{
  "type": "Feature",
  "properties": {
    "addr:full":"2800 Broadway Oakland CA 94611",
    "addr:housenumber":"2800",
    "addr:postcode":"94611",
    "addr:street":"Broadway",
    "iso:country":"US",
    "sg:address":"2800 Broadway",
    "sg:city":"Oakland",
    "sg:classifiers":[
        {
            "category":"Retail",
            "subcategory":"Repair Shop",
            "type":"Services"
        }
    ],
    "sg:phone":"+1 510 832 4455",
    "sg:postcode":"94611",
    "sg:province":"CA",
    "sg:tags":[
        "reupholstery",
        "furniture"
    ],
    "wof:name":"King Kovers",
    "wof:placetype":"venue"
},
  "geometry": {"coordinates":[-122.26300000000001,37.816502],"type":"Point"}
}