{
  "type": "Feature",
  "properties": {
    "iso:country":"US",
    "sg:address":"1118 E Walnut St",
    "sg:city":"Santa Ana",
    "sg:classifiers":[
        {
            "category":"Manufacturing",
            "subcategory":"Printing",
            "type":"Manufacturing & Wholesale Goods"
        }
    ],
    "sg:phone":"+1 714 973 4749",
    "sg:postcode":"92701",
    "sg:province":"CA",
    "sg:tags":[
        "lithographic",
        "screen",
        "commercial"
    ],
    "wof:name":"Abril Screen Printing",
    "wof:placetype":"venue"
},
  "geometry": {"coordinates":[-117.85319699999999,33.744365],"type":"Point"}
}