{
  "type": "Feature",
  "properties": {
    "addr:full":"1909 Atlantic Ave Long Beach CA 90806",
    "addr:housenumber":"1909",
    "addr:postcode":"90806",
    "addr:street":"Atlantic Ave",
    "iso:country":"US",
    "sg:address":"1909 Atlantic Ave",
    "sg:city":"Long Beach",
    "sg:classifiers":[
        {
            "category":"Organizations",
            "subcategory":"Non-profit Organization",
            "type":"Services"
        }
    ],
    "sg:phone":"+1 562 218 5243",
    "sg:postcode":"90806",
    "sg:province":"CA",
    "sg:tags":[
        "info",
        "addiction",
        "abuse",
        "treatment",
        "drug"
    ],
    "sg:website":"www.atlantic.org",
    "wof:name":"Atlantic Recovery Svc",
    "wof:placetype":"venue"
},
  "geometry": {"coordinates":[-118.185097,33.792431],"type":"Point"}
}