{
  "type": "Feature",
  "properties": {
    "iso:country":"US",
    "sg:address":"27360 Alicia Pkwy",
    "sg:city":"Laguna Niguel",
    "sg:classifiers":[
        {
            "category":"Restaurant",
            "type":"Food & Drink"
        }
    ],
    "sg:phone":"+1 949 643 0010",
    "sg:postcode":"92677",
    "sg:province":"CA",
    "wof:name":"Coco's Family Restaurant",
    "wof:placetype":"venue"
},
  "geometry": {"coordinates":[-117.71700300000001,33.559399],"type":"Point"}
}