{
  "type": "Feature",
  "properties": {
    "iso:country":"US",
    "sg:address":"117 E 25th Ave",
    "sg:city":"San Mateo",
    "sg:classifiers":[
        {
            "category":"Home & Garden",
            "subcategory":"Building Materials",
            "type":"Retail Goods"
        }
    ],
    "sg:phone":"+1 650 349 3212",
    "sg:postcode":"94403",
    "sg:province":"CA",
    "sg:tags":[
        "lumber",
        "supply"
    ],
    "wof:name":"Condon & Sons Lumber Co",
    "wof:placetype":"venue"
},
  "geometry": {"coordinates":[-122.304001,37.545601],"type":"Point"}
}