{
  "type": "Feature",
  "properties": {
    "addr:full":"11851 Art St Sun Valley CA 91352",
    "addr:housenumber":"11851",
    "addr:postcode":"91352",
    "addr:street":"Art St",
    "iso:country":"US",
    "sg:address":"11851 Art St",
    "sg:city":"Sun Valley",
    "sg:classifiers":[
        {
            "category":"Building & Trades",
            "subcategory":"Landscaping Services",
            "type":"Services"
        }
    ],
    "sg:phone":"+1 818 768 9910",
    "sg:postcode":"91352",
    "sg:province":"CA",
    "wof:name":"Garcia Gardening Service",
    "wof:placetype":"venue"
},
  "geometry": {"coordinates":[-118.391976,34.233508],"type":"Point"}
}