{
  "type": "Feature",
  "properties": {
    "iso:country":"US",
    "sg:address":"7597 Kirwin Ln",
    "sg:city":"Cupertino",
    "sg:classifiers":[
        {
            "category":"Freight",
            "type":"Transportation"
        }
    ],
    "sg:phone":"+1 408 996 3033",
    "sg:postcode":"95014",
    "sg:province":"CA",
    "sg:tags":[
        "operator",
        "local",
        "trucking"
    ],
    "wof:name":"Aztec Water Service",
    "wof:placetype":"venue"
},
  "geometry": {"coordinates":[-122.040404,37.313908],"type":"Point"}
}