{
  "type": "Feature",
  "properties": {
    "addr:full":"1142 Sea Breeze Ct Brentwood CA 94513",
    "addr:housenumber":"1142",
    "addr:postcode":"94513",
    "addr:street":"Sea Breeze Ct",
    "iso:country":"US",
    "sg:address":"1142 Sea Breeze Ct",
    "sg:city":"Brentwood",
    "sg:classifiers":[
        {
            "category":"Real Estate",
            "subcategory":"Real Estate Services",
            "type":"Services"
        },
        {
            "category":"Real Estate",
            "subcategory":"Real Estate Agent",
            "type":"Services"
        }
    ],
    "sg:phone":"+1 925 634 9696",
    "sg:postcode":"94513",
    "sg:province":"CA",
    "sg:tags":[
        "management"
    ],
    "wof:name":"D & D Market Solutions",
    "wof:placetype":"venue"
},
  "geometry": {"coordinates":[-121.71881399999999,37.941865],"type":"Point"}
}