{
  "type": "Feature",
  "properties": {
    "addr:full":"3480 Arden Rd Hayward CA 94545",
    "addr:housenumber":"3480",
    "addr:postcode":"94545",
    "addr:street":"Arden Rd",
    "iso:country":"US",
    "sg:address":"3480 Arden Rd",
    "sg:city":"Hayward",
    "sg:classifiers":[
        {
            "category":"Building & Trades",
            "subcategory":"Plumbing",
            "type":"Services"
        }
    ],
    "sg:phone":"+1 510 784 8990",
    "sg:postcode":"94545",
    "sg:province":"CA",
    "sg:website":"www.crsref.com",
    "wof:name":"Crs",
    "wof:placetype":"venue"
},
  "geometry": {"coordinates":[-122.110491,37.620877],"type":"Point"}
}