{
  "type": "Feature",
  "properties": {
    "addr:full":"9797 Atwater Jordan Rd Atwater CA 95301",
    "addr:housenumber":"9797",
    "addr:postcode":"95301",
    "addr:street":"Atwater Jordan Rd",
    "iso:country":"US",
    "sg:address":"9797 Atwater Jordan Rd",
    "sg:city":"Atwater",
    "sg:classifiers":[
        {
            "category":"Insurance",
            "subcategory":"Hazard Insurance",
            "type":"Services"
        }
    ],
    "sg:phone":"+1 209 394 3134",
    "sg:postcode":"95301",
    "sg:province":"CA",
    "sg:tags":[
        "bond"
    ],
    "wof:name":"John Souza Bail Bonds",
    "wof:placetype":"venue"
},
  "geometry": {"coordinates":[-120.664131,37.331207],"type":"Point"}
}