{
  "type": "Feature",
  "properties": {
    "addr:full":"7861 Garden Grove Blvd Garden Grove CA 92841",
    "addr:housenumber":"7861",
    "addr:postcode":"92841",
    "addr:street":"Garden Grove Blvd",
    "iso:country":"US",
    "sg:address":"7861 Garden Grove Blvd",
    "sg:city":"Garden Grove",
    "sg:classifiers":[
        {
            "category":"Shopping",
            "subcategory":"Music",
            "type":"Retail Goods"
        }
    ],
    "sg:phone":"+1 714 889 2400",
    "sg:postcode":"92841",
    "sg:province":"CA",
    "sg:tags":[
        "dvd's"
    ],
    "sg:website":"www.etreby.com",
    "wof:name":"Etreby Computer Company",
    "wof:placetype":"venue"
},
  "geometry": {"coordinates":[-117.995813,33.773905],"type":"Point"}
}