{
  "type": "Feature",
  "properties": {
    "addr:full":"8968 Garvey Ave Rosemead CA 91770",
    "addr:housenumber":"8968",
    "addr:postcode":"91770",
    "addr:street":"Garvey Ave",
    "iso:country":"US",
    "sg:address":"8968 Garvey Ave",
    "sg:city":"Rosemead",
    "sg:classifiers":[
        {
            "category":"Insurance",
            "subcategory":"Insurance Agent",
            "type":"Services"
        }
    ],
    "sg:phone":"+1 626 307 7443",
    "sg:postcode":"91770",
    "sg:province":"CA",
    "wof:name":"Johnny Insurance",
    "wof:placetype":"venue"
},
  "geometry": {"coordinates":[-118.074454,34.062601],"type":"Point"}
}