{
  "type": "Feature",
  "properties": {
    "addr:full":"4475 Market St Ventura CA 93003",
    "addr:housenumber":"4475",
    "addr:postcode":"93003",
    "addr:street":"Market St",
    "iso:country":"US",
    "sg:address":"4475 Market St",
    "sg:city":"Ventura",
    "sg:classifiers":[
        {
            "category":"Education",
            "subcategory":"College",
            "type":"Public Place"
        }
    ],
    "sg:phone":"+1 805 658 0511",
    "sg:postcode":"93003",
    "sg:province":"CA",
    "sg:tags":[
        "academic",
        "school"
    ],
    "sg:website":"www.venturalaw.edu",
    "wof:name":"Ventura College Of Law",
    "wof:placetype":"venue"
},
  "geometry": {"coordinates":[-119.23354500000001,34.257131],"type":"Point"}
}