{
  "type": "Feature",
  "properties": {
    "iso:country":"US",
    "sg:address":"2021 E 4th St Ste 116",
    "sg:city":"Santa Ana",
    "sg:classifiers":[
        {
            "category":"Health Services",
            "subcategory":"Doctor",
            "type":"Services"
        },
        {
            "category":"Health Services",
            "subcategory":"Clinic",
            "type":"Services"
        }
    ],
    "sg:phone":"+1 714 541 5581",
    "sg:postcode":"92705",
    "sg:province":"CA",
    "sg:tags":[
        "counseling",
        "mental"
    ],
    "wof:name":"Olin Gerri M PHD",
    "wof:placetype":"venue"
},
  "geometry": {"coordinates":[-117.837997,33.748299],"type":"Point"}
}