{
  "type": "Feature",
  "properties": {
    "addr:full":"21701 Lake Forest Dr Lake Forest CA 92630",
    "addr:housenumber":"21701",
    "addr:postcode":"92630",
    "addr:street":"Lake Forest Dr",
    "iso:country":"US",
    "sg:address":"21701 Lake Forest Dr",
    "sg:city":"Lake Forest",
    "sg:classifiers":[
        {
            "category":"Restaurant",
            "type":"Food & Drink"
        }
    ],
    "sg:phone":"+1 949 859 6249",
    "sg:postcode":"92630",
    "sg:province":"CA",
    "sg:tags":[
        "parlor",
        "ice",
        "cream"
    ],
    "wof:name":"Maggie Moo Ice Cream & Trtry",
    "wof:placetype":"venue"
},
  "geometry": {"coordinates":[-117.690335,33.64479],"type":"Point"}
}