{
  "type": "Feature",
  "properties": {
    "addr:full":"24567 Corte Descanso Murrieta CA 92562",
    "addr:housenumber":"24567",
    "addr:postcode":"92562",
    "addr:street":"Corte Descanso",
    "iso:country":"US",
    "sg:address":"24567 Corte Descanso",
    "sg:city":"Murrieta",
    "sg:classifiers":[
        {
            "category":"Social Services",
            "subcategory":"Child Care",
            "type":"Services"
        }
    ],
    "sg:phone":"+1 951 698 2428",
    "sg:postcode":"92562",
    "sg:province":"CA",
    "sg:tags":[
        "kindergarten",
        "academic",
        "school"
    ],
    "wof:name":"Home Away From Home Pre-School",
    "wof:placetype":"venue"
},
  "geometry": {"coordinates":[-117.22448300000001,33.554455],"type":"Point"}
}