{
  "type": "Feature",
  "properties": {
    "addr:full":"15216 Donnington Ln Truckee CA 96161",
    "addr:housenumber":"15216",
    "addr:postcode":"96161",
    "addr:street":"Donnington Ln",
    "iso:country":"US",
    "sg:address":"15216 Donnington Ln",
    "sg:city":"Truckee",
    "sg:classifiers":[
        {
            "category":"Manufacturing",
            "subcategory":"Tools & Machinery",
            "type":"Manufacturing & Wholesale Goods"
        }
    ],
    "sg:phone":"+1 530 550 8220",
    "sg:postcode":"96161",
    "sg:province":"CA",
    "sg:tags":[
        "surgical",
        "mfg"
    ],
    "wof:name":"Body Balance Foot Orthotic",
    "wof:placetype":"venue"
},
  "geometry": {"coordinates":[-120.106655,39.349387],"type":"Point"}
}