{
  "type": "Feature",
  "properties": {
    "addr:full":"11156 E Annadale Ave Sanger CA 93657",
    "addr:housenumber":"11156",
    "addr:postcode":"ca 93657",
    "addr:street":"E Annadale Ave",
    "iso:country":"US",
    "sg:address":"11156 E Annadale Ave",
    "sg:city":"Sanger",
    "sg:classifiers":[
        {
            "category":"Wholesale",
            "subcategory":"Fruits & Vegetables",
            "type":"Manufacturing & Wholesale Goods"
        }
    ],
    "sg:phone":"+1 559 875 7181",
    "sg:postcode":"93657",
    "sg:province":"CA",
    "sg:tags":[
        "shipper"
    ],
    "wof:name":"Farmex Land Inc",
    "wof:placetype":"venue"
},
  "geometry": {"coordinates":[-119.58363900000001,36.699519],"type":"Point"}
}