{
  "type": "Feature",
  "properties": {
    "iso:country":"US",
    "sg:address":"2071 Montebello Town Center",
    "sg:city":"Montebello",
    "sg:classifiers":[
        {
            "category":"Shopping",
            "subcategory":"Shoes",
            "type":"Retail Goods"
        }
    ],
    "sg:phone":"+1 323 728 1169",
    "sg:postcode":"90640",
    "sg:province":"CA",
    "wof:name":"Nine West",
    "wof:placetype":"venue"
},
  "geometry": {"coordinates":[-118.087432,34.035765],"type":"Point"}
}