{
  "type": "Feature",
  "properties": {
    "addr:full":"2071 Montebello Town Center Montebello CA 90640",
    "addr:housenumber":"2071",
    "addr:postcode":"90640",
    "addr:street":"Montebello Town",
    "iso:country":"US",
    "sg:address":"2071 Montebello Town Center",
    "sg:city":"Montebello",
    "sg:classifiers":[
        {
            "category":"Shopping",
            "subcategory":"Shoes",
            "type":"Retail Goods"
        }
    ],
    "sg:phone":"+1 323 728 1169",
    "sg:postcode":"90640",
    "sg:province":"CA",
    "wof:name":"Nine West",
    "wof:placetype":"venue"
},
  "geometry": {"coordinates":[-118.08743200000001,34.035765],"type":"Point"}
}