{
  "type": "Feature",
  "properties": {
    "addr:full":"21103 Golden Springs Dr Walnut CA 91789",
    "addr:housenumber":"21103",
    "addr:postcode":"91789",
    "addr:street":"Golden Springs Dr",
    "iso:country":"US",
    "sg:address":"21103 Golden Springs Dr",
    "sg:city":"Walnut",
    "sg:classifiers":[
        {
            "category":"Autos & Motor Vehicles",
            "subcategory":"Fuel & Gas Station",
            "type":"Retail Goods"
        }
    ],
    "sg:phone":"+1 909 598 5506",
    "sg:postcode":"91789",
    "sg:province":"CA",
    "sg:tags":[
        "oil"
    ],
    "wof:name":"Diamond Bar Shell",
    "wof:placetype":"venue"
},
  "geometry": {"coordinates":[-117.839118,34.000803],"type":"Point"}
}