{
  "type": "Feature",
  "properties": {
    "iso:country":"US",
    "sg:address":"235 N Conejo School Rd",
    "sg:city":"Thousand Oaks",
    "sg:classifiers":[
        {
            "category":"Real Estate",
            "subcategory":"Real Estate Operator",
            "type":"Services"
        }
    ],
    "sg:phone":"+1 805 446 6257",
    "sg:postcode":"91362",
    "sg:province":"CA",
    "sg:tags":[
        "apartment"
    ],
    "wof:name":"Premiere Of Thousand Oaks",
    "wof:placetype":"venue"
},
  "geometry": {"coordinates":[-118.83956499999999,34.181581],"type":"Point"}
}