{
  "type": "Feature",
  "properties": {
    "addr:full":"84542 Ave 49 Coachella CA 92236",
    "addr:housenumber":"84542",
    "addr:postcode":"92236",
    "addr:street":"Ave 49",
    "iso:country":"US",
    "sg:address":"84542 Ave 49",
    "sg:city":"Coachella",
    "sg:classifiers":[
        {
            "category":"Organizations",
            "subcategory":"Religious Organization",
            "type":"Services"
        }
    ],
    "sg:phone":"+1 760 398 2204",
    "sg:postcode":"92236",
    "sg:province":"CA",
    "sg:tags":[
        "church"
    ],
    "wof:name":"Pentecostal Church Of Phila",
    "wof:placetype":"venue"
},
  "geometry": {"coordinates":[-116.187082,33.692987],"type":"Point"}
}