{
  "type": "Feature",
  "properties": {
    "iso:country":"US",
    "sg:address":"61 Tamal Vista Blvd",
    "sg:city":"Corte Madera",
    "sg:classifiers":[
        {
            "category":"Real Estate",
            "subcategory":"Architect",
            "type":"Services"
        }
    ],
    "sg:phone":"+1 415 927 9489",
    "sg:postcode":"94925",
    "sg:province":"CA",
    "wof:name":"David Tucker",
    "wof:placetype":"venue"
},
  "geometry": {"coordinates":[-122.51801,37.931838],"type":"Point"}
}