{
  "type": "Feature",
  "properties": {
    "addr:full":"825 Western Ave Glendale CA 91201",
    "addr:housenumber":"825",
    "addr:postcode":"91201",
    "addr:street":"Western Ave",
    "iso:country":"US",
    "sg:address":"825 Western Ave",
    "sg:city":"Glendale",
    "sg:classifiers":[
        {
            "category":"Professional",
            "type":"Services"
        }
    ],
    "sg:phone":"+1 818 265 1533",
    "sg:postcode":"91201",
    "sg:province":"CA",
    "wof:name":"Kevin Woo",
    "wof:placetype":"venue"
},
  "geometry": {"coordinates":[-118.294871,34.16614],"type":"Point"}
}