{
  "type": "Feature",
  "properties": {
    "addr:full":"2367 S Anna St Fresno CA 93706",
    "addr:housenumber":"2367",
    "addr:postcode":"93706",
    "addr:street":"S Anna St",
    "iso:country":"US",
    "sg:address":"2367 S Anna St",
    "sg:city":"Fresno",
    "sg:classifiers":[
        {
            "category":"Building & Trades",
            "subcategory":"Plumbing",
            "type":"Services"
        }
    ],
    "sg:phone":"+1 559 496 0100",
    "sg:postcode":"93706",
    "sg:province":"CA",
    "sg:tags":[
        "plumbing",
        "contractor"
    ],
    "wof:name":"Danico Plumbing",
    "wof:placetype":"venue"
},
  "geometry": {"coordinates":[-119.780511,36.71541],"type":"Point"}
}