{
  "type": "Feature",
  "properties": {
    "iso:country":"US",
    "sg:address":"265 Moulton St",
    "sg:city":"San Francisco",
    "sg:classifiers":[
        {
            "category":"Education",
            "subcategory":"School",
            "type":"Public Place"
        }
    ],
    "sg:phone":"+1 415 345 9184",
    "sg:postcode":"94123",
    "sg:province":"CA",
    "wof:name":"Circle Of Friends Preschool",
    "wof:placetype":"venue"
},
  "geometry": {"coordinates":[-122.436746,37.799272],"type":"Point"}
}