{
  "type": "Feature",
  "properties": {
    "addr:full":"11721 Nevada City Hwy Grass Valley CA 95945",
    "addr:housenumber":"11721",
    "addr:postcode":"95945",
    "addr:street":"Nevada City Hwy",
    "iso:country":"US",
    "sg:address":"11721 Nevada City Hwy",
    "sg:city":"Grass Valley",
    "sg:classifiers":[
        {
            "category":"Real Estate",
            "subcategory":"Real Estate Agent",
            "type":"Services"
        }
    ],
    "sg:phone":"+1 530 265 3578",
    "sg:postcode":"95945",
    "sg:province":"CA",
    "wof:name":"Gmac Real Estate",
    "wof:placetype":"venue"
},
  "geometry": {"coordinates":[-121.040424,39.235171],"type":"Point"}
}