{
  "type": "Feature",
  "properties": {
    "addr:full":"3845 E Thousand Oaks Blvd Westlake Village CA 91362",
    "addr:housenumber":"3845",
    "addr:postcode":"91362",
    "addr:street":"E Thousand Oaks Blvd",
    "iso:country":"US",
    "sg:address":"3845 E Thousand Oaks Blvd",
    "sg:city":"Westlake Village",
    "sg:classifiers":[
        {
            "category":"Shopping",
            "subcategory":"Jewelry",
            "type":"Retail Goods"
        }
    ],
    "sg:phone":"+1 805 373 1002",
    "sg:postcode":"91362",
    "sg:province":"CA",
    "sg:tags":[
        "jeweler"
    ],
    "wof:name":"Dejaun Jewelers",
    "wof:placetype":"venue"
},
  "geometry": {"coordinates":[-118.824636,34.161945],"type":"Point"}
}