{
  "type": "Feature",
  "properties": {
    "addr:full":"14726 Goldenwest St Unit F Westminster CA 92683",
    "addr:postcode":"14726;92683",
    "addr:street":"Goldenwest St Unit F",
    "iso:country":"US",
    "sg:address":"14726 Goldenwest St Unit F",
    "sg:city":"Westminster",
    "sg:classifiers":[
        {
            "category":"Autos & Motor Vehicles",
            "subcategory":"Motorcycle Sales",
            "type":"Retail Goods"
        },
        {
            "category":"Retail",
            "subcategory":"Auto Repair",
            "type":"Services"
        }
    ],
    "sg:phone":"+1 714 894 1942",
    "sg:postcode":"92683",
    "sg:province":"CA",
    "sg:website":"www.illusionmotorcycles.com",
    "wof:name":"Illusion Motorsports",
    "wof:placetype":"venue"
},
  "geometry": {"coordinates":[-118.00627900000001,33.748421],"type":"Point"}
}