{
  "type": "Feature",
  "properties": {
    "addr:full":"17800 S Main Street Suite 307 Gardena CA 90248",
    "addr:housenumber":"17800",
    "addr:postcode":"90248",
    "addr:street":"S Main Street Suite 307",
    "iso:country":"US",
    "sg:address":"17800 S Main Street Suite 307",
    "sg:city":"Gardena",
    "sg:classifiers":[
        {
            "category":"Shopping",
            "subcategory":"Computers & Home Electronics",
            "type":"Retail Goods"
        }
    ],
    "sg:phone":"+1 310 878 1900",
    "sg:postcode":"90248",
    "sg:province":"CA",
    "wof:name":"Tapestockonline",
    "wof:placetype":"venue"
},
  "geometry": {"coordinates":[-118.27540500000001,33.868942],"type":"Point"}
}