{
  "type": "Feature",
  "properties": {
    "addr:full":"368 Fairview Way Milpitas CA 95035",
    "addr:housenumber":"368",
    "addr:postcode":"95035",
    "addr:street":"Fairview Way",
    "iso:country":"US",
    "sg:address":"368 Fairview Way",
    "sg:city":"Milpitas",
    "sg:classifiers":[
        {
            "category":"Insurance",
            "subcategory":"Hazard Insurance",
            "type":"Services"
        }
    ],
    "sg:phone":"+1 408 945 6537",
    "sg:postcode":"95035",
    "sg:province":"CA",
    "wof:name":"Judge For Yourself",
    "wof:placetype":"venue"
},
  "geometry": {"coordinates":[-121.916394,37.445861],"type":"Point"}
}