{
  "type": "Feature",
  "properties": {
    "addr:full":"552 California Blvd San Luis Obispo CA 93405",
    "addr:housenumber":"552",
    "addr:postcode":"93405",
    "addr:street":"California Blvd",
    "iso:country":"US",
    "sg:address":"552 California Blvd",
    "sg:city":"San Luis Obispo",
    "sg:classifiers":[
        {
            "category":"Retail",
            "subcategory":"Self-service Laundry",
            "type":"Services"
        }
    ],
    "sg:phone":"+1 805 544 8266",
    "sg:postcode":"93405",
    "sg:province":"CA",
    "wof:name":"California Coin Laundry",
    "wof:placetype":"venue"
},
  "geometry": {"coordinates":[-120.66034999999999,35.290977],"type":"Point"}
}