{
  "type": "Feature",
  "properties": {
    "addr:full":"2045 Hallmark Dr Sacramento CA 95825",
    "addr:housenumber":"2045",
    "addr:postcode":"95825",
    "addr:street":"Hallmark Dr",
    "iso:country":"US",
    "sg:address":"2045 Hallmark Dr",
    "sg:city":"Sacramento",
    "sg:classifiers":[
        {
            "category":"Professional",
            "subcategory":"Business Services",
            "type":"Services"
        }
    ],
    "sg:phone":"+1 916 565 3900",
    "sg:postcode":"95825",
    "sg:province":"CA",
    "sg:tags":[
        "arbitration"
    ],
    "wof:name":"Arbitration Works",
    "wof:placetype":"venue"
},
  "geometry": {"coordinates":[-121.419293,38.591555],"type":"Point"}
}