{
  "type": "Feature",
  "properties": {
    "addr:full":"901 Sunrise Ave Roseville CA 95661",
    "addr:housenumber":"901",
    "addr:postcode":"95661",
    "addr:street":"Sunrise Ave",
    "iso:country":"US",
    "sg:address":"901 Sunrise Ave",
    "sg:city":"Roseville",
    "sg:classifiers":[
        {
            "category":"Restaurant",
            "type":"Food & Drink"
        }
    ],
    "sg:phone":"+1 916 772 4344",
    "sg:postcode":"95661",
    "sg:province":"CA",
    "wof:name":"Sushi House",
    "wof:placetype":"venue"
},
  "geometry": {"coordinates":[-121.272075,38.729495],"type":"Point"}
}