{
  "type": "Feature",
  "properties": {
    "iso:country":"US",
    "sg:address":"26679 Agoura Rd",
    "sg:city":"Calabasas",
    "sg:classifiers":[
        {
            "category":"Restaurant",
            "type":"Food & Drink"
        }
    ],
    "sg:phone":"+1 818 878 0132",
    "sg:postcode":"91302",
    "sg:province":"CA",
    "wof:name":"Company Cafe",
    "wof:placetype":"venue"
},
  "geometry": {"coordinates":[-118.70500199999999,34.1409],"type":"Point"}
}