{
  "type": "Feature",
  "properties": {
    "addr:full":"4233 W Sierra Madre Ave # 103 Fresno CA 93722",
    "addr:housenumber":"4233",
    "addr:postcode":"93722",
    "addr:street":"W Sierra Madre Ave # 103",
    "iso:country":"US",
    "sg:address":"4233 W Sierra Madre Ave # 103",
    "sg:city":"Fresno",
    "sg:classifiers":[
        {
            "category":"Transit Center",
            "subcategory":"Freight",
            "type":"Transportation"
        }
    ],
    "sg:phone":"+1 800 214 8009",
    "sg:postcode":"93722",
    "sg:province":"CA",
    "sg:tags":[
        "forwarding"
    ],
    "sg:website":"http://www.clippergroup.com",
    "wof:name":"Clipper Exxpress Company",
    "wof:placetype":"venue"
},
  "geometry": {"coordinates":[-119.867643,36.806751],"type":"Point"}
}