{
  "type": "Feature",
  "properties": {
    "addr:full":"2682 W Imperial Hwy Inglewood CA 90303",
    "addr:housenumber":"2682",
    "addr:postcode":"90303",
    "addr:street":"W Imperial Hwy",
    "iso:country":"US",
    "sg:address":"2682 W Imperial Hwy",
    "sg:city":"Inglewood",
    "sg:classifiers":[
        {
            "category":"Shopping",
            "subcategory":"Jewelry",
            "type":"Retail Goods"
        }
    ],
    "sg:phone":"+1 323 779 8166",
    "sg:postcode":"90303",
    "sg:province":"CA",
    "wof:name":"Joe's Fine Jewelry",
    "wof:placetype":"venue"
},
  "geometry": {"coordinates":[-118.32351199999999,33.930893],"type":"Point"}
}