{
  "type": "Feature",
  "properties": {
    "addr:full":"11577 Kelsey St Studio City CA 91604",
    "addr:housenumber":"11577",
    "addr:postcode":"91604",
    "addr:street":"Kelsey St",
    "iso:country":"US",
    "sg:address":"11577 Kelsey St",
    "sg:city":"Studio City",
    "sg:classifiers":[
        {
            "category":"Professional",
            "type":"Services"
        }
    ],
    "sg:phone":"+1 818 760 2882",
    "sg:postcode":"91604",
    "sg:province":"CA",
    "wof:name":"Terry R Corbin Inc",
    "wof:placetype":"venue"
},
  "geometry": {"coordinates":[-118.384895,34.141964],"type":"Point"}
}