{
  "type": "Feature",
  "properties": {
    "addr:full":"11307 Paul Barwick Ct San Diego CA 92126",
    "addr:housenumber":"11307",
    "addr:postcode":"92126",
    "addr:street":"Paul Barwick Ct",
    "iso:country":"US",
    "sg:address":"11307 Paul Barwick Ct",
    "sg:city":"San Diego",
    "sg:classifiers":[
        {
            "category":"Professional",
            "subcategory":"Research",
            "type":"Services"
        }
    ],
    "sg:phone":"+1 858 566 2529",
    "sg:postcode":"92126",
    "sg:province":"CA",
    "sg:tags":[
        "environmental",
        "ecological"
    ],
    "wof:name":"Gray Environmental Inc",
    "wof:placetype":"venue"
},
  "geometry": {"coordinates":[-117.16492100000001,32.923464],"type":"Point"}
}