{
  "type": "Feature",
  "properties": {
    "iso:country":"US",
    "sg:address":"6571 Colgate Ave",
    "sg:city":"Los Angeles",
    "sg:classifiers":[
        {
            "category":"Professional",
            "type":"Services"
        }
    ],
    "sg:phone":"+1 323 935 9131",
    "sg:postcode":"90048",
    "sg:province":"CA",
    "wof:name":"Kardiac LLC",
    "wof:placetype":"venue"
},
  "geometry": {"coordinates":[-118.368556,34.069895],"type":"Point"}
}