{
  "type": "Feature",
  "properties": {
    "iso:country":"US",
    "sg:address":"880 Mitten Rd",
    "sg:city":"Burlingame",
    "sg:classifiers":[
        {
            "category":"Autos & Motor Vehicles",
            "subcategory":"Automobile Sales",
            "type":"Retail Goods"
        }
    ],
    "sg:phone":"+1 650 372 0609",
    "sg:postcode":"94010",
    "sg:province":"CA",
    "sg:tags":[
        "limo"
    ],
    "wof:name":"Nafis Town Car Service",
    "wof:placetype":"venue"
},
  "geometry": {"coordinates":[-122.374308,37.600746],"type":"Point"}
}