{
  "type": "Feature",
  "properties": {
    "addr:full":"11965 Venice Blvd Ste 405 Los Angeles CA 90024",
    "addr:housenumber":"11965",
    "addr:postcode":"90024",
    "addr:street":"Venice Blvd Ste 405",
    "iso:country":"US",
    "sg:address":"11965 Venice Blvd Ste 405",
    "sg:city":"Los Angeles",
    "sg:classifiers":[
        {
            "category":"Health Services",
            "subcategory":"Clinic",
            "type":"Services"
        }
    ],
    "sg:phone":"+1 888 724 0040",
    "sg:postcode":"90024",
    "sg:province":"CA",
    "sg:tags":[
        "medical"
    ],
    "sg:website":"www.pchtreatment.com",
    "wof:name":"PCH Treatment Center",
    "wof:placetype":"venue"
},
  "geometry": {"coordinates":[-118.429002,34.006397],"type":"Point"}
}