{
  "type": "Feature",
  "properties": {
    "iso:country":"US",
    "sg:address":"6940 Lemp Ave",
    "sg:city":"North Hollywood",
    "sg:classifiers":[
        {
            "category":"Retail",
            "subcategory":"Auto Repair",
            "type":"Services"
        }
    ],
    "sg:phone":"+1 818 765 4611",
    "sg:postcode":"91605",
    "sg:province":"CA",
    "sg:tags":[
        "repairing",
        "automobile"
    ],
    "wof:name":"A & S Auto Svc Ctr",
    "wof:placetype":"venue"
},
  "geometry": {"coordinates":[-118.384503,34.197007],"type":"Point"}
}