{
  "type": "Feature",
  "properties": {
    "iso:country":"US",
    "sg:address":"2461 Maywood Dr",
    "sg:city":"San Bruno",
    "sg:classifiers":[
        {
            "category":"Retail",
            "subcategory":"Auto Rental",
            "type":"Services"
        }
    ],
    "sg:phone":"+1 650 583 3425",
    "sg:postcode":"94066",
    "sg:province":"CA",
    "sg:tags":[
        "automobile",
        "leasing"
    ],
    "wof:name":"Royal Stewart Auto Leasing",
    "wof:placetype":"venue"
},
  "geometry": {"coordinates":[-122.447167,37.633723],"type":"Point"}
}