{
  "type": "Feature",
  "properties": {
    "addr:full":"1165 Chess Dr Foster City CA 94404",
    "addr:housenumber":"1165",
    "addr:postcode":"94404",
    "addr:street":"Chess Dr",
    "iso:country":"US",
    "sg:address":"1165 Chess Dr",
    "sg:city":"Foster City",
    "sg:classifiers":[
        {
            "category":"Wholesale",
            "subcategory":"Medical Equipment & Supplies",
            "type":"Manufacturing & Wholesale Goods"
        }
    ],
    "sg:phone":"+1 650 871 8576",
    "sg:postcode":"94404",
    "sg:province":"CA",
    "sg:tags":[
        "hospital"
    ],
    "wof:name":"Rapid Sense",
    "wof:placetype":"venue"
},
  "geometry": {"coordinates":[-122.27369400000001,37.56792],"type":"Point"}
}