{
  "type": "Feature",
  "properties": {
    "iso:country":"US",
    "sg:address":"7167 Echo Ridge Dr",
    "sg:city":"San Jose",
    "sg:classifiers":[
        {
            "category":"Retail",
            "subcategory":"Laundry & Dry Cleaning",
            "type":"Services"
        }
    ],
    "sg:phone":"+1 408 997 3976",
    "sg:postcode":"95120",
    "sg:province":"CA",
    "sg:tags":[
        "cleaners",
        "rug",
        "carpet"
    ],
    "wof:name":"Choice Carpet Upholstery Clnrs",
    "wof:placetype":"venue"
},
  "geometry": {"coordinates":[-121.858024,37.201311],"type":"Point"}
}