{
  "type": "Feature",
  "properties": {
    "iso:country":"US",
    "sg:address":"7290 Vineyard Dr",
    "sg:city":"Paso Robles",
    "sg:classifiers":[
        {
            "category":"Insurance",
            "subcategory":"Insurance Agent",
            "type":"Services"
        }
    ],
    "sg:phone":"+1 805 237 1424",
    "sg:postcode":"93446",
    "sg:province":"CA",
    "sg:website":"www.targetplanning.com",
    "wof:name":"Target Planning Corp",
    "wof:placetype":"venue"
},
  "geometry": {"coordinates":[-120.832115,35.597761],"type":"Point"}
}