{
  "type": "Feature",
  "properties": {
    "iso:country":"US",
    "sg:address":"3807 Wilshire Blvd",
    "sg:city":"Los Angeles",
    "sg:classifiers":[
        {
            "category":"Building & Trades",
            "subcategory":"Construction",
            "type":"Services"
        }
    ],
    "sg:phone":"+1 213 386 4858",
    "sg:postcode":"90010",
    "sg:province":"CA",
    "sg:tags":[
        "contractor"
    ],
    "sg:website":"www.richriverdev.com",
    "wof:name":"Rich River Development Co",
    "wof:placetype":"venue"
},
  "geometry": {"coordinates":[-118.310203,34.061768],"type":"Point"}
}