{
  "type": "Feature",
  "properties": {
    "addr:full":"6334 Riverdale St San Diego CA 92120",
    "addr:housenumber":"6334",
    "addr:postcode":"92120",
    "addr:street":"Riverdale St",
    "iso:country":"US",
    "sg:address":"6334 Riverdale St",
    "sg:city":"San Diego",
    "sg:classifiers":[
        {
            "category":"Professional",
            "subcategory":"Advertising",
            "type":"Services"
        }
    ],
    "sg:phone":"+1 619 280 4343",
    "sg:postcode":"92120",
    "sg:province":"CA",
    "wof:name":"G 3 Graphics Inc",
    "wof:placetype":"venue"
},
  "geometry": {"coordinates":[-117.09960599999999,32.788767],"type":"Point"}
}