{
  "type": "Feature",
  "properties": {
    "iso:country":"US",
    "sg:address":"7275 Hollywood Blvd",
    "sg:city":"West Hollywood",
    "sg:classifiers":[
        {
            "category":"Recreation",
            "type":"Entertainment"
        }
    ],
    "sg:phone":"+1 323 969 9076",
    "sg:postcode":"90046",
    "sg:province":"CA",
    "sg:tags":[
        "stable"
    ],
    "wof:name":"Stables Schwab & Trujillo Inc",
    "wof:placetype":"venue"
},
  "geometry": {"coordinates":[-118.348313,34.101694],"type":"Point"}
}