{
  "type": "Feature",
  "properties": {
    "addr:full":"23757 Via Segovia Murrieta CA 92562",
    "addr:housenumber":"23757",
    "addr:postcode":"92562",
    "addr:street":"Via Segovia",
    "iso:country":"US",
    "sg:address":"23757 Via Segovia",
    "sg:city":"Murrieta",
    "sg:classifiers":[
        {
            "category":"Manufacturing",
            "subcategory":"Tools & Machinery",
            "type":"Manufacturing & Wholesale Goods"
        }
    ],
    "sg:phone":"+1 951 677 2780",
    "sg:postcode":"92562",
    "sg:province":"CA",
    "sg:tags":[
        "equipment",
        "lighting",
        "mfg"
    ],
    "wof:name":"Starlite Enterprises",
    "wof:placetype":"venue"
},
  "geometry": {"coordinates":[-117.198612,33.596244],"type":"Point"}
}