{
  "type": "Feature",
  "properties": {
    "addr:full":"4212 Alabama St San Diego CA 92104",
    "addr:housenumber":"4212",
    "addr:postcode":"92104",
    "addr:street":"Alabama St",
    "iso:country":"US",
    "sg:address":"4212 Alabama St",
    "sg:city":"San Diego",
    "sg:classifiers":[
        {
            "category":"Professional",
            "subcategory":"Art Services",
            "type":"Services"
        }
    ],
    "sg:phone":"+1 619 291 1196",
    "sg:postcode":"92104",
    "sg:province":"CA",
    "sg:tags":[
        "graphic",
        "designer"
    ],
    "wof:name":"Contois Design Studio Inc",
    "wof:placetype":"venue"
},
  "geometry": {"coordinates":[-117.14259800000001,32.754485],"type":"Point"}
}