{
  "type": "Feature",
  "properties": {
    "addr:full":"41937 Colt Ct Coarsegold CA 93614",
    "addr:housenumber":"41937",
    "addr:postcode":"93614",
    "addr:street":"Colt Ct",
    "iso:country":"US",
    "sg:address":"41937 Colt Ct",
    "sg:city":"Coarsegold",
    "sg:classifiers":[
        {
            "category":"Real Estate",
            "subcategory":"Real Estate Agent",
            "type":"Services"
        }
    ],
    "sg:phone":"+1 559 683 7596",
    "sg:postcode":"93614",
    "sg:province":"CA",
    "wof:name":"Donald A Dauro Appraisals",
    "wof:placetype":"venue"
},
  "geometry": {"coordinates":[-119.781031,37.189098],"type":"Point"}
}