{
  "type": "Feature",
  "properties": {
    "iso:country":"US",
    "sg:address":"3107 22nd St",
    "sg:city":"San Francisco",
    "sg:classifiers":[
        {
            "category":"Professional",
            "subcategory":"Accounting & Tax Preparation",
            "type":"Services"
        }
    ],
    "sg:phone":"+1 415 826 3952",
    "sg:postcode":"94110",
    "sg:province":"CA",
    "sg:tags":[
        "accountant"
    ],
    "sg:website":"www.e-file-ez.com",
    "wof:name":"Canizalez Tax Svc",
    "wof:placetype":"venue"
},
  "geometry": {"coordinates":[-122.417517,37.755438],"type":"Point"}
}