{
  "type": "Feature",
  "properties": {
    "addr:full":"22133 S Vermont Ave Torrance CA 90502",
    "addr:housenumber":"22133",
    "addr:postcode":"90502",
    "addr:street":"S Vermont Ave",
    "iso:country":"US",
    "sg:address":"22133 S Vermont Ave",
    "sg:city":"Torrance",
    "sg:classifiers":[
        {
            "category":"Home & Garden",
            "subcategory":"Carpets & Floor Coverings",
            "type":"Retail Goods"
        }
    ],
    "sg:phone":"+1 310 891 2275",
    "sg:postcode":"90502",
    "sg:province":"CA",
    "sg:tags":[
        "carpeting"
    ],
    "wof:name":"Anchor Floor Covering",
    "wof:placetype":"venue"
},
  "geometry": {"coordinates":[-118.2903,33.826346],"type":"Point"}
}