{
  "type": "Feature",
  "properties": {
    "iso:country":"US",
    "sg:address":"12515 Burbank Blvd",
    "sg:city":"Valley Village",
    "sg:classifiers":[
        {
            "category":"Restaurant",
            "type":"Food & Drink"
        }
    ],
    "sg:phone":"+1 818 760 8198",
    "sg:postcode":"91607",
    "sg:province":"CA",
    "sg:tags":[
        "kosher",
        "pizza"
    ],
    "wof:name":"La Pizza",
    "wof:placetype":"venue"
},
  "geometry": {"coordinates":[-118.405998,34.172001],"type":"Point"}
}