{
  "type": "Feature",
  "properties": {
    "addr:full":"20334 Londelius St Canoga Park CA 91306",
    "addr:postcode":"20334;91306",
    "addr:street":"Londelius St",
    "iso:country":"US",
    "sg:address":"20334 Londelius St",
    "sg:city":"Canoga Park",
    "sg:classifiers":[
        {
            "category":"Social Services",
            "subcategory":"Child Care",
            "type":"Services"
        }
    ],
    "sg:phone":"+1 818 709 4603",
    "sg:postcode":"91306",
    "sg:province":"CA",
    "wof:name":"Stepping Tots Family Day Care",
    "wof:placetype":"venue"
},
  "geometry": {"coordinates":[-118.577771,34.229016],"type":"Point"}
}