{
  "type": "Feature",
  "properties": {
    "addr:full":"898 S McGlincey Ln Campbell CA 95008",
    "addr:housenumber":"898",
    "addr:postcode":"95008",
    "addr:street":"S Mcglincey Ln",
    "iso:country":"US",
    "sg:address":"898 S McGlincey Ln",
    "sg:city":"Campbell",
    "sg:classifiers":[
        {
            "category":"Autos & Motor Vehicles",
            "subcategory":"Auto Supplies",
            "type":"Retail Goods"
        }
    ],
    "sg:phone":"+1 408 379 3136",
    "sg:postcode":"95008",
    "sg:province":"CA",
    "sg:tags":[
        "wheel",
        "cover"
    ],
    "wof:name":"Zenith Wire Wheel Co",
    "wof:placetype":"venue"
},
  "geometry": {"coordinates":[-121.945054,37.274074],"type":"Point"}
}