{
  "type": "Feature",
  "properties": {
    "iso:country":"US",
    "sg:address":"288 Redwood Dr",
    "sg:city":"Felton",
    "sg:classifiers":[
        {
            "category":"Manufacturing",
            "subcategory":"Petroleum Products",
            "type":"Manufacturing & Wholesale Goods"
        }
    ],
    "sg:phone":"+1 831 295 9479",
    "sg:postcode":"95018",
    "sg:province":"CA",
    "sg:tags":[
        "candles-wholesale",
        "manufacturer"
    ],
    "wof:name":"Natures Serenity Candles",
    "wof:placetype":"venue"
},
  "geometry": {"coordinates":[-122.075749,37.043088],"type":"Point"}
}