{
  "type": "Feature",
  "properties": {
    "iso:country":"US",
    "sg:address":"9257 International Blvd",
    "sg:city":"Oakland",
    "sg:classifiers":[
        {
            "category":"Professional",
            "type":"Services"
        }
    ],
    "sg:phone":"+1 510 569 6425",
    "sg:postcode":"94603",
    "sg:province":"CA",
    "wof:name":"Makadar African Braids",
    "wof:placetype":"venue"
},
  "geometry": {"coordinates":[-122.173347,37.748252],"type":"Point"}
}