{
  "type": "Feature",
  "properties": {
    "addr:full":"1202 N Glassell St Orange CA 92867",
    "addr:housenumber":"1202",
    "addr:postcode":"92867",
    "addr:street":"N Glassell St",
    "iso:country":"US",
    "sg:address":"1202 N Glassell St",
    "sg:city":"Orange",
    "sg:classifiers":[
        {
            "category":"Manufacturing",
            "subcategory":"Motor Vehicles & Parts",
            "type":"Manufacturing & Wholesale Goods"
        }
    ],
    "sg:phone":"+1 714 639 5220",
    "sg:postcode":"92867",
    "sg:province":"CA",
    "sg:tags":[
        "exhaust",
        "mfg",
        "auto",
        "repair"
    ],
    "wof:name":"Mike Leach Inc",
    "wof:placetype":"venue"
},
  "geometry": {"coordinates":[-117.8531,33.807842],"type":"Point"}
}