{
  "type": "Feature",
  "properties": {
    "iso:country":"US",
    "sg:address":"1457 Venice Blvd",
    "sg:city":"Los Angeles",
    "sg:classifiers":[
        {
            "category":"Organizations",
            "subcategory":"Religious Organization",
            "type":"Services"
        }
    ],
    "sg:phone":"+1 213 389 2729",
    "sg:postcode":"90006",
    "sg:province":"CA",
    "sg:tags":[
        "church"
    ],
    "wof:name":"Iglesia De Dios De LA Profesia",
    "wof:placetype":"venue"
},
  "geometry": {"coordinates":[-118.286169,34.044303],"type":"Point"}
}