{
  "type": "Feature",
  "properties": {
    "iso:country":"US",
    "sg:address":"2410 Grand Ave",
    "sg:city":"Sacramento",
    "sg:classifiers":[
        {
            "category":"Wholesale",
            "subcategory":"Machinery & Supplies",
            "type":"Manufacturing & Wholesale Goods"
        }
    ],
    "sg:phone":"+1 916 641 3434",
    "sg:postcode":"95838",
    "sg:province":"CA",
    "sg:tags":[
        "truck"
    ],
    "wof:name":"Pape Material Handling",
    "wof:placetype":"venue"
},
  "geometry": {"coordinates":[-121.407604,38.636906],"type":"Point"}
}