{
  "type": "Feature",
  "properties": {
    "addr:full":"19510 Ventura Blvd Tarzana CA 91356",
    "addr:housenumber":"19510",
    "addr:postcode":"91356",
    "addr:street":"Ventura Blvd",
    "iso:country":"US",
    "sg:address":"19510 Ventura Blvd",
    "sg:city":"Tarzana",
    "sg:classifiers":[
        {
            "category":"Banks & Credit Unions",
            "subcategory":"Bank",
            "type":"Services"
        }
    ],
    "sg:phone":"+1 818 708 7272",
    "sg:postcode":"91356",
    "sg:province":"CA",
    "sg:tags":[
        "assistance",
        "foreclosure"
    ],
    "wof:name":"Reliable Trust Deed Svc",
    "wof:placetype":"venue"
},
  "geometry": {"coordinates":[-118.559819,34.17273],"type":"Point"}
}