{
  "type": "Feature",
  "properties": {
    "addr:full":"200 Pier Ave Hermosa Beach CA 90254",
    "addr:housenumber":"200",
    "addr:postcode":"90254",
    "addr:street":"Pier Ave",
    "iso:country":"US",
    "sg:address":"200 Pier Ave",
    "sg:city":"Hermosa Beach",
    "sg:classifiers":[
        {
            "category":"Building & Trades",
            "subcategory":"Equipment Rental",
            "type":"Services"
        }
    ],
    "sg:phone":"+1 310 379 8724",
    "sg:postcode":"90254",
    "sg:province":"CA",
    "sg:tags":[
        "aircraft",
        "leasing",
        "charter"
    ],
    "wof:name":"Altitude Aviation",
    "wof:placetype":"venue"
},
  "geometry": {"coordinates":[-118.398814,33.863406],"type":"Point"}
}