{
  "type": "Feature",
  "properties": {
    "iso:country":"US",
    "sg:address":"3150 Almaden Expy",
    "sg:city":"San Jose",
    "sg:classifiers":[
        {
            "category":"Shopping",
            "type":"Retail Goods"
        }
    ],
    "sg:phone":"+1 408 907 4100",
    "sg:postcode":"95118",
    "sg:province":"CA",
    "wof:name":"Umbrella Solutions",
    "wof:placetype":"venue"
},
  "geometry": {"coordinates":[-121.878345,37.276358],"type":"Point"}
}