{
  "type": "Feature",
  "properties": {
    "addr:full":"969 Industrial Rd San Carlos CA 94070",
    "addr:housenumber":"969",
    "addr:postcode":"94070",
    "addr:street":"Industrial Rd",
    "iso:country":"US",
    "sg:address":"969 Industrial Rd",
    "sg:city":"San Carlos",
    "sg:classifiers":[
        {
            "category":"Travel",
            "subcategory":"Travel Agent",
            "type":"Entertainment"
        }
    ],
    "sg:phone":"+1 650 637 8833",
    "sg:postcode":"94070",
    "sg:province":"CA",
    "sg:tags":[
        "agency"
    ],
    "wof:name":"World Explorer Cruises Inc",
    "wof:placetype":"venue"
},
  "geometry": {"coordinates":[-122.24854499999999,37.504072],"type":"Point"}
}