{
  "type": "Feature",
  "properties": {
    "iso:country":"US",
    "sg:address":"1704 Marshallfield Ln",
    "sg:city":"Redondo Beach",
    "sg:classifiers":[
        {
            "category":"Wholesale",
            "subcategory":"Durable Goods & Equipment",
            "type":"Manufacturing & Wholesale Goods"
        }
    ],
    "sg:phone":"+1 310 372 3487",
    "sg:postcode":"90278",
    "sg:province":"CA",
    "wof:name":"JM Sound",
    "wof:placetype":"venue"
},
  "geometry": {"coordinates":[-118.38118900000001,33.865137],"type":"Point"}
}