{
  "type": "Feature",
  "properties": {
    "addr:full":"8455 Beverly Blvd Los Angeles CA 90048",
    "addr:housenumber":"8455",
    "addr:postcode":"90048",
    "addr:street":"Beverly Blvd",
    "iso:country":"US",
    "sg:address":"8455 Beverly Blvd",
    "sg:city":"Los Angeles",
    "sg:classifiers":[
        {
            "category":"Restaurant",
            "type":"Food & Drink"
        }
    ],
    "sg:phone":"+1 323 655 2523",
    "sg:postcode":"90048",
    "sg:province":"CA",
    "wof:name":"Hanmar Enterprises",
    "wof:placetype":"venue"
},
  "geometry": {"coordinates":[-118.374572,34.076122],"type":"Point"}
}