{
  "type": "Feature",
  "properties": {
    "iso:country":"US",
    "sg:address":"3130 Standard St",
    "sg:city":"Bakersfield",
    "sg:classifiers":[
        {
            "category":"Building & Trades",
            "subcategory":"Construction",
            "type":"Services"
        }
    ],
    "sg:phone":"+1 661 638 0304",
    "sg:postcode":"93308",
    "sg:province":"CA",
    "sg:tags":[
        "contractor"
    ],
    "wof:name":"Tri Star Roofing",
    "wof:placetype":"venue"
},
  "geometry": {"coordinates":[-119.047571,35.387912],"type":"Point"}
}