{
  "type": "Feature",
  "properties": {
    "addr:full":"3130 Skyway Dr Santa Maria CA 93455",
    "addr:housenumber":"3130",
    "addr:postcode":"93455",
    "addr:street":"Skyway Dr",
    "iso:country":"US",
    "sg:address":"3130 Skyway Dr",
    "sg:city":"Santa Maria",
    "sg:classifiers":[
        {
            "category":"Organizations",
            "subcategory":"Religious Organization",
            "type":"Services"
        }
    ],
    "sg:phone":"+1 805 739 1922",
    "sg:postcode":"93455",
    "sg:province":"CA",
    "wof:name":"Holy Family Ministries",
    "wof:placetype":"venue"
},
  "geometry": {"coordinates":[-120.449736,34.903214],"type":"Point"}
}