{
  "type": "Feature",
  "properties": {
    "iso:country":"US",
    "sg:address":"14816 Valley Blvd",
    "sg:city":"Fontana",
    "sg:classifiers":[
        {
            "category":"Retail",
            "subcategory":"Auto Repair",
            "type":"Services"
        }
    ],
    "sg:phone":"+1 909 357 3666",
    "sg:postcode":"92335",
    "sg:province":"CA",
    "sg:tags":[
        "wrecker"
    ],
    "wof:name":"South State Towing",
    "wof:placetype":"venue"
},
  "geometry": {"coordinates":[-117.482218,34.070278],"type":"Point"}
}