{
  "type": "Feature",
  "properties": {
    "iso:country":"US",
    "sg:address":"4875 E Ramon Rd",
    "sg:city":"Palm Springs",
    "sg:classifiers":[
        {
            "category":"Autos & Motor Vehicles",
            "subcategory":"Fuel & Gas Station",
            "type":"Retail Goods"
        }
    ],
    "sg:phone":"+1 760 325 5785",
    "sg:postcode":"92264",
    "sg:province":"CA",
    "sg:tags":[
        "oil"
    ],
    "wof:name":"Gene Autry Shell",
    "wof:placetype":"venue"
},
  "geometry": {"coordinates":[-116.49494799999999,33.815806],"type":"Point"}
}