{
  "type": "Feature",
  "properties": {
    "addr:full":"7820 International Blvd Oakland CA 94621",
    "addr:housenumber":"7820",
    "addr:postcode":"94621",
    "addr:street":"International Blvd",
    "iso:country":"US",
    "sg:address":"7820 International Blvd",
    "sg:city":"Oakland",
    "sg:classifiers":[
        {
            "category":"Autos & Motor Vehicles",
            "subcategory":"Automobile Sales",
            "type":"Retail Goods"
        }
    ],
    "sg:phone":"+1 510 638 7476",
    "sg:postcode":"94621",
    "sg:province":"CA",
    "sg:tags":[
        "car",
        "dealer"
    ],
    "wof:name":"TBS Auto Buyline System",
    "wof:placetype":"venue"
},
  "geometry": {"coordinates":[-122.182659,37.756968],"type":"Point"}
}