{
  "type": "Feature",
  "properties": {
    "iso:country":"US",
    "sg:address":"3699 San Gabriel River Pkwy",
    "sg:city":"Pico Rivera",
    "sg:classifiers":[
        {
            "category":"Manufacturing",
            "subcategory":"Signs",
            "type":"Manufacturing & Wholesale Goods"
        }
    ],
    "sg:phone":"+1 562 463 7378",
    "sg:postcode":"90660",
    "sg:province":"CA",
    "sg:tags":[
        "advertising",
        "specialty"
    ],
    "wof:name":"Tony Signs",
    "wof:placetype":"venue"
},
  "geometry": {"coordinates":[-118.05743200000001,34.014284],"type":"Point"}
}