{
  "type": "Feature",
  "properties": {
    "addr:full":"3892 Sierra Ave Fontana CA 92336",
    "addr:housenumber":"3892",
    "addr:postcode":"92336",
    "addr:street":"Sierra Ave",
    "iso:country":"US",
    "sg:address":"3892 Sierra Ave",
    "sg:city":"Fontana",
    "sg:classifiers":[
        {
            "category":"Autos & Motor Vehicles",
            "subcategory":"Fuel & Gas Station",
            "type":"Retail Goods"
        }
    ],
    "sg:phone":"+1 909 429 7886",
    "sg:postcode":"92336",
    "sg:province":"CA",
    "sg:tags":[
        "oil"
    ],
    "wof:name":"Midland Oil Inc",
    "wof:placetype":"venue"
},
  "geometry": {"coordinates":[-117.43774000000001,34.183387],"type":"Point"}
}