{
  "type": "Feature",
  "properties": {
    "iso:country":"US",
    "sg:address":"1220 W Main St",
    "sg:city":"El Cajon",
    "sg:classifiers":[
        {
            "category":"Travel",
            "subcategory":"Hotels & Motels",
            "type":"Entertainment"
        }
    ],
    "sg:phone":"+1 619 442 2576",
    "sg:postcode":"92020",
    "sg:province":"CA",
    "sg:website":"www.relaxinnsd.com",
    "wof:name":"Relax Inn And Suite",
    "wof:placetype":"venue"
},
  "geometry": {"coordinates":[-116.977993,32.795579],"type":"Point"}
}