{
  "type": "Feature",
  "properties": {
    "addr:full":"1233 W Carlton Ave West Covina CA 91790",
    "addr:housenumber":"1233",
    "addr:postcode":"91790",
    "addr:street":"W Carlton Ave",
    "iso:country":"US",
    "sg:address":"1233 W Carlton Ave",
    "sg:city":"West Covina",
    "sg:classifiers":[
        {
            "category":"Building & Trades",
            "subcategory":"Plumbing",
            "type":"Services"
        }
    ],
    "sg:phone":"+1 626 962 5668",
    "sg:postcode":"91790",
    "sg:province":"CA",
    "wof:name":"Zerbel Plumbing",
    "wof:placetype":"venue"
},
  "geometry": {"coordinates":[-117.931898,34.081201],"type":"Point"}
}