{
  "type": "Feature",
  "properties": {
    "iso:country":"US",
    "sg:address":"449 Gold Run Dr",
    "sg:city":"Modesto",
    "sg:classifiers":[
        {
            "category":"Shopping",
            "subcategory":"Computers & Home Electronics",
            "type":"Retail Goods"
        }
    ],
    "sg:phone":"+1 209 544 8253",
    "sg:postcode":"95354",
    "sg:province":"CA",
    "sg:tags":[
        "parts",
        "supply"
    ],
    "wof:name":"Netcom",
    "wof:placetype":"venue"
},
  "geometry": {"coordinates":[-120.932746,37.643582],"type":"Point"}
}