{
  "type": "Feature",
  "properties": {
    "addr:full":"30 S Roop St Susanville CA 96130",
    "addr:housenumber":"30",
    "addr:postcode":"96130",
    "addr:street":"S Roop St",
    "iso:country":"US",
    "sg:address":"30 S Roop St",
    "sg:city":"Susanville",
    "sg:classifiers":[
        {
            "category":"Utilities",
            "subcategory":"Water",
            "type":"Services"
        }
    ],
    "sg:phone":"+1 530 257 8040",
    "sg:postcode":"96130",
    "sg:province":"CA",
    "sg:tags":[
        "supply"
    ],
    "wof:name":"Susan River Park Water Co",
    "wof:placetype":"venue"
},
  "geometry": {"coordinates":[-120.663331,40.418663],"type":"Point"}
}