{
  "type": "Feature",
  "properties": {
    "addr:full":"216 State St Santa Barbara CA 93101",
    "addr:housenumber":"216",
    "addr:postcode":"93101",
    "addr:street":"State St",
    "iso:country":"US",
    "sg:address":"216 State St",
    "sg:city":"Santa Barbara",
    "sg:classifiers":[
        {
            "category":"Recreation",
            "type":"Entertainment"
        }
    ],
    "sg:phone":"+1 805 962 4488",
    "sg:postcode":"93101",
    "sg:province":"CA",
    "sg:tags":[
        "aquarium"
    ],
    "wof:name":"Ocean Floor",
    "wof:placetype":"venue"
},
  "geometry": {"coordinates":[-119.692689,34.414837],"type":"Point"}
}