{
  "type": "Feature",
  "properties": {
    "addr:full":"2700 S Palm Canyon Dr Palm Springs CA 92264",
    "addr:housenumber":"2700",
    "addr:postcode":"92264",
    "addr:street":"S Palm Canyon Dr",
    "iso:country":"US",
    "sg:address":"2700 S Palm Canyon Dr",
    "sg:city":"Palm Springs",
    "sg:classifiers":[
        {
            "category":"Real Estate",
            "subcategory":"Real Estate Agent",
            "type":"Services"
        }
    ],
    "sg:phone":"+1 760 323 5366",
    "sg:postcode":"92264",
    "sg:province":"CA",
    "sg:tags":[
        "sharing",
        "condominium"
    ],
    "wof:name":"Timeshare Resale Alliance",
    "wof:placetype":"venue"
},
  "geometry": {"coordinates":[-116.545371,33.780501],"type":"Point"}
}