{
  "type": "Feature",
  "properties": {
    "iso:country":"US",
    "sg:address":"3430 Tully Rd",
    "sg:city":"Modesto",
    "sg:classifiers":[
        {
            "category":"Personal",
            "subcategory":"Beauty Salon",
            "type":"Services"
        }
    ],
    "sg:phone":"+1 209 572 2887",
    "sg:postcode":"95350",
    "sg:province":"CA",
    "wof:name":"Modern Cuts",
    "wof:placetype":"venue"
},
  "geometry": {"coordinates":[-121.012405,37.688561],"type":"Point"}
}