{
  "type": "Feature",
  "properties": {
    "iso:country":"US",
    "sg:address":"8555 San Ysidro Ave",
    "sg:city":"Gilroy",
    "sg:classifiers":[
        {
            "category":"Shopping",
            "type":"Retail Goods"
        }
    ],
    "sg:phone":"+1 408 847 0326",
    "sg:postcode":"95020",
    "sg:province":"CA",
    "sg:tags":[
        "factory",
        "outlet"
    ],
    "wof:name":"Van Heusen",
    "wof:placetype":"venue"
},
  "geometry": {"coordinates":[-121.5675,37.02757],"type":"Point"}
}