{
  "type": "Feature",
  "properties": {
    "iso:country":"US",
    "sg:address":"270 South Bristol St Suite #101-229",
    "sg:city":"Costa Mesa",
    "sg:classifiers":[
        {
            "category":"Professional",
            "type":"Services"
        }
    ],
    "sg:phone":"+1 800 884 7559",
    "sg:postcode":"92626",
    "sg:province":"CA",
    "sg:website":"www.zephyrnetworks.com",
    "wof:name":"Zephyr Networks",
    "wof:placetype":"venue"
},
  "geometry": {"coordinates":[-117.883066,33.667356],"type":"Point"}
}