{
  "type": "Feature",
  "properties": {
    "iso:country":"US",
    "sg:address":"26917 Augusta Pl",
    "sg:city":"Valencia",
    "sg:classifiers":[
        {
            "category":"Professional",
            "subcategory":"Management & Consulting",
            "type":"Services"
        }
    ],
    "sg:phone":"+1 661 288 2218",
    "sg:postcode":"91355",
    "sg:province":"CA",
    "sg:tags":[
        "consultant"
    ],
    "wof:name":"C Silos Consulting",
    "wof:placetype":"venue"
},
  "geometry": {"coordinates":[-118.570522,34.412176],"type":"Point"}
}