{
  "type": "Feature",
  "properties": {
    "addr:full":"3812 Grim Ave San Diego CA 92104",
    "addr:housenumber":"3812",
    "addr:postcode":"92104",
    "addr:street":"Grim Ave",
    "iso:country":"US",
    "sg:address":"3812 Grim Ave",
    "sg:city":"San Diego",
    "sg:classifiers":[
        {
            "category":"Shopping",
            "subcategory":"Books",
            "type":"Retail Goods"
        }
    ],
    "sg:phone":"+1 619 291 4381",
    "sg:postcode":"92104",
    "sg:province":"CA",
    "sg:tags":[
        "bookstore"
    ],
    "sg:website":"www.ebiblebookstore.com",
    "wof:name":"Evangelical Bible Book Store",
    "wof:placetype":"venue"
},
  "geometry": {"coordinates":[-117.128355,32.747706],"type":"Point"}
}