{
  "type": "Feature",
  "properties": {
    "iso:country":"US",
    "sg:address":"3832 Arden Way",
    "sg:city":"Sacramento",
    "sg:classifiers":[
        {
            "category":"Manufacturing",
            "subcategory":"Printing",
            "type":"Manufacturing & Wholesale Goods"
        }
    ],
    "sg:phone":"+1 916 359 1916",
    "sg:postcode":"95864",
    "sg:province":"CA",
    "sg:tags":[
        "publisher"
    ],
    "wof:name":"Anima Solis Music & Publishing",
    "wof:placetype":"venue"
},
  "geometry": {"coordinates":[-121.377307,38.595675],"type":"Point"}
}