{
  "type": "Feature",
  "properties": {
    "addr:full":"600 S Commonwealth Ave Los Angeles CA 90005",
    "addr:housenumber":"600",
    "addr:postcode":"90005",
    "addr:street":"S Commonwealth Ave",
    "iso:country":"US",
    "sg:address":"600 S Commonwealth Ave",
    "sg:city":"Los Angeles",
    "sg:classifiers":[
        {
            "category":"Government",
            "subcategory":"Court House",
            "type":"Public Place"
        }
    ],
    "sg:phone":"+1 213 351 8225",
    "sg:postcode":"90005",
    "sg:province":"CA",
    "sg:tags":[
        "legal"
    ],
    "wof:name":"Public Defender",
    "wof:placetype":"venue"
},
  "geometry": {"coordinates":[-118.285646,34.062836],"type":"Point"}
}