{
  "type": "Feature",
  "properties": {
    "iso:country":"US",
    "sg:address":"6011 N Palm Ave",
    "sg:city":"Fresno",
    "sg:classifiers":[
        {
            "category":"Restaurant",
            "type":"Food & Drink"
        }
    ],
    "sg:phone":"+1 559 439 7008",
    "sg:postcode":"93704",
    "sg:province":"CA",
    "sg:tags":[
        "shop",
        "coffee"
    ],
    "wof:name":"Aviano Internatl Coffee House",
    "wof:placetype":"venue"
},
  "geometry": {"coordinates":[-119.808406,36.824505],"type":"Point"}
}