{
  "type": "Feature",
  "properties": {
    "addr:full":"1906 Hillhurst Ave Los Angeles CA 90027",
    "addr:housenumber":"1906",
    "addr:postcode":"90027",
    "addr:street":"Hillhurst Ave",
    "iso:country":"US",
    "sg:address":"1906 Hillhurst Ave",
    "sg:city":"Los Angeles",
    "sg:classifiers":[
        {
            "category":"Restaurant",
            "type":"Food & Drink"
        }
    ],
    "sg:phone":"+1 323 663 4884",
    "sg:postcode":"90027",
    "sg:province":"CA",
    "sg:tags":[
        "sushi",
        "bar"
    ],
    "wof:name":"Tosa Express",
    "wof:placetype":"venue"
},
  "geometry": {"coordinates":[-118.287003,34.105701],"type":"Point"}
}