{
  "type": "Feature",
  "properties": {
    "addr:full":"7660 Fay Ave, Ste H324 La Jolla CA 92037",
    "addr:housenumber":"7660",
    "addr:postcode":"92037",
    "addr:street":"Fay Ave Ste H324",
    "iso:country":"US",
    "sg:address":"7660 Fay Ave, Ste H324",
    "sg:city":"La Jolla",
    "sg:classifiers":[
        {
            "category":"Arts & Performance",
            "subcategory":"Arts Center",
            "type":"Entertainment"
        }
    ],
    "sg:postcode":"92037",
    "sg:province":"CA",
    "sg:website":"www.radionigel.com",
    "wof:name":"Radio Nigel",
    "wof:placetype":"venue"
},
  "geometry": {"coordinates":[-117.274962,32.8429],"type":"Point"}
}