{
  "type": "Feature",
  "properties": {
    "addr:full":"603 S Rampart Blvd Los Angeles CA 90057",
    "addr:housenumber":"603",
    "addr:postcode":"90057",
    "addr:street":"S Rampart Blvd",
    "iso:country":"US",
    "sg:address":"603 S Rampart Blvd",
    "sg:city":"Los Angeles",
    "sg:classifiers":[
        {
            "category":"Real Estate",
            "subcategory":"Real Estate Operator",
            "type":"Services"
        }
    ],
    "sg:phone":"+1 213 454 6433",
    "sg:postcode":"90057",
    "sg:province":"CA",
    "sg:tags":[
        "apartment"
    ],
    "wof:name":"Rampart Arms",
    "wof:placetype":"venue"
},
  "geometry": {"coordinates":[-118.281682,34.06221],"type":"Point"}
}