{
  "type": "Feature",
  "properties": {
    "iso:country":"US",
    "sg:address":"22900 Broadway",
    "sg:city":"Sonoma",
    "sg:classifiers":[
        {
            "category":"Restaurant",
            "type":"Food & Drink"
        }
    ],
    "sg:phone":"+1 707 996 5151",
    "sg:postcode":"95476",
    "sg:province":"CA",
    "wof:name":"Schellville Grill",
    "wof:placetype":"venue"
},
  "geometry": {"coordinates":[-122.449026,38.242443],"type":"Point"}
}