{
  "type": "Feature",
  "properties": {
    "iso:country":"US",
    "sg:address":"17605 Harvard Avenue",
    "sg:city":"Irvine",
    "sg:classifiers":[
        {
            "category":"Banks & Credit Unions",
            "subcategory":"Bank",
            "type":"Services"
        }
    ],
    "sg:phone":"+1 949 261 9924",
    "sg:postcode":"92614",
    "sg:province":"CA",
    "wof:name":"Union Bank of California",
    "wof:placetype":"venue"
},
  "geometry": {"coordinates":[-117.831506,33.676851],"type":"Point"}
}