{
  "type": "Feature",
  "properties": {
    "addr:full":"352 E Greystone Ave Monrovia CA 91016",
    "addr:housenumber":"352",
    "addr:postcode":"91016",
    "addr:street":"E Greystone Ave",
    "iso:country":"US",
    "sg:address":"352 E Greystone Ave",
    "sg:city":"Monrovia",
    "sg:classifiers":[
        {
            "category":"Communications",
            "type":"Services"
        }
    ],
    "sg:phone":"+1 626 357 2078",
    "sg:postcode":"91016",
    "sg:province":"CA",
    "sg:tags":[
        "communication"
    ],
    "wof:name":"General Pacific Communict",
    "wof:placetype":"venue"
},
  "geometry": {"coordinates":[-117.99566299999999,34.156867],"type":"Point"}
}