{
  "type": "Feature",
  "properties": {
    "addr:full":"110 Inland Ctr San Bernardino CA 92408",
    "addr:housenumber":"110",
    "addr:postcode":"92408",
    "addr:street":"Inland Ctr",
    "iso:country":"US",
    "sg:address":"110 Inland Ctr",
    "sg:city":"San Bernardino",
    "sg:classifiers":[
        {
            "category":"Restaurant",
            "type":"Food & Drink"
        }
    ],
    "sg:menulink":"http://www.allmenus.com/ca/san-bernardino/228535-hot-dog-on-a-stick/menu/",
    "sg:postcode":"92408",
    "sg:province":"CA",
    "sg:tags":[
        "american"
    ],
    "wof:name":"HOT DOG ON A STICK",
    "wof:placetype":"venue"
},
  "geometry": {"coordinates":[-117.297152,34.088802],"type":"Point"}
}