{
  "type": "Feature",
  "properties": {
    "iso:country":"US",
    "sg:address":"4008 White Ln",
    "sg:city":"Bakersfield",
    "sg:classifiers":[
        {
            "category":"Place Of Worship",
            "subcategory":"Church",
            "type":"Public Place"
        },
        {
            "category":"Place Of Worship",
            "type":"Public Place"
        }
    ],
    "sg:phone":"+1 661 835 8100",
    "sg:postcode":"93309",
    "sg:province":"CA",
    "sg:tags":[
        "churches-interdenominational",
        "churches-charismatic",
        "churches-various",
        "denomination"
    ],
    "wof:name":"Citygate Christian Center",
    "wof:placetype":"venue"
},
  "geometry": {"coordinates":[-119.046924,35.317806],"type":"Point"}
}