{
  "type": "Feature",
  "properties": {
    "addr:full":"3612 W Estates Ln Rolling Hls Ests CA 90274",
    "addr:housenumber":"3612",
    "addr:postcode":"90274",
    "addr:street":"W Estates Ln",
    "iso:country":"US",
    "sg:address":"3612 W Estates Ln",
    "sg:city":"Rolling Hls Ests",
    "sg:classifiers":[
        {
            "category":"Professional",
            "subcategory":"Engineering",
            "type":"Services"
        }
    ],
    "sg:phone":"+1 310 544 9928",
    "sg:postcode":"90274",
    "sg:province":"CA",
    "sg:tags":[
        "engineer"
    ],
    "wof:name":"Jeff Hashemi",
    "wof:placetype":"venue"
},
  "geometry": {"coordinates":[-118.341003,33.785977],"type":"Point"}
}