{
  "type": "Feature",
  "properties": {
    "iso:country":"US",
    "sg:address":"14585 Lauren Ln",
    "sg:city":"Grass Valley",
    "sg:classifiers":[
        {
            "category":"Education",
            "subcategory":"Special Training",
            "type":"Public Place"
        }
    ],
    "sg:phone":"+1 530 477 7895",
    "sg:postcode":"95949",
    "sg:province":"CA",
    "sg:tags":[
        "educational"
    ],
    "wof:name":"Lifestyles Education Svc",
    "wof:placetype":"venue"
},
  "geometry": {"coordinates":[-121.039928,39.153892],"type":"Point"}
}