{
  "type": "Feature",
  "properties": {
    "iso:country":"US",
    "sg:address":"5440 S Central Ave",
    "sg:city":"Los Angeles",
    "sg:classifiers":[
        {
            "category":"Retail",
            "subcategory":"Self-service Laundry",
            "type":"Services"
        }
    ],
    "sg:phone":"+1 323 233 3303",
    "sg:postcode":"90011",
    "sg:province":"CA",
    "wof:name":"King Coin Laundry",
    "wof:placetype":"venue"
},
  "geometry": {"coordinates":[-118.25637,33.993115],"type":"Point"}
}