{
  "type": "Feature",
  "properties": {
    "iso:country":"US",
    "sg:address":"1060 S Broadway",
    "sg:city":"Los Angeles",
    "sg:classifiers":[
        {
            "category":"Manufacturing",
            "subcategory":"Apparel",
            "type":"Manufacturing & Wholesale Goods"
        }
    ],
    "sg:phone":"+1 213 749 4256",
    "sg:postcode":"90015",
    "sg:province":"CA",
    "sg:tags":[
        "clothing",
        "mfg"
    ],
    "wof:name":"D D & Company",
    "wof:placetype":"venue"
},
  "geometry": {"coordinates":[-118.258032,34.040352],"type":"Point"}
}