{
  "type": "Feature",
  "properties": {
    "iso:country":"US",
    "sg:address":"233 Lawrence Ct",
    "sg:city":"Fairfield",
    "sg:classifiers":[
        {
            "category":"Building & Trades",
            "subcategory":"Construction",
            "type":"Services"
        }
    ],
    "sg:phone":"+1 707 429 7177",
    "sg:postcode":"94533",
    "sg:province":"CA",
    "sg:tags":[
        "gen",
        "contractor"
    ],
    "wof:name":"Any Angle Construction Co",
    "wof:placetype":"venue"
},
  "geometry": {"coordinates":[-122.052346,38.244305],"type":"Point"}
}