{
  "type": "Feature",
  "properties": {
    "addr:full":"110 E 9th St Los Angeles CA 90015",
    "addr:housenumber":"110",
    "addr:postcode":"90015",
    "addr:street":"E 9Th St",
    "iso:country":"US",
    "sg:address":"110 E 9th St",
    "sg:city":"Los Angeles",
    "sg:classifiers":[
        {
            "category":"Professional",
            "subcategory":"Lawyer & Legal Services",
            "type":"Services"
        }
    ],
    "sg:phone":"+1 213 489 1310",
    "sg:postcode":"90015",
    "sg:province":"CA",
    "sg:tags":[
        "attorney"
    ],
    "wof:name":"Esquire",
    "wof:placetype":"venue"
},
  "geometry": {"coordinates":[-118.254773,34.041342],"type":"Point"}
}