{
  "type": "Feature",
  "properties": {
    "addr:full":"319 W 11th St Azusa CA 91702",
    "addr:housenumber":"319",
    "addr:postcode":"91702",
    "addr:street":"W 11Th St",
    "iso:country":"US",
    "sg:address":"319 W 11th St",
    "sg:city":"Azusa",
    "sg:classifiers":[
        {
            "category":"Building & Trades",
            "subcategory":"Construction",
            "type":"Services"
        }
    ],
    "sg:phone":"+1 626 334 5709",
    "sg:postcode":"91702",
    "sg:province":"CA",
    "sg:tags":[
        "contractor"
    ],
    "wof:name":"Lindberg Robt",
    "wof:placetype":"venue"
},
  "geometry": {"coordinates":[-117.91112800000001,34.140938],"type":"Point"}
}