{
  "type": "Feature",
  "properties": {
    "addr:full":"4639 Missouri Flat Rd Diamond Springs CA 95667",
    "addr:housenumber":"4639",
    "addr:postcode":"95667",
    "addr:street":"Missouri Flat Rd",
    "iso:country":"US",
    "sg:address":"4639 Missouri Flat Rd",
    "sg:city":"Diamond Springs",
    "sg:classifiers":[
        {
            "category":"Autos & Motor Vehicles",
            "subcategory":"Auto Supplies",
            "type":"Retail Goods"
        }
    ],
    "sg:phone":"+1 530 622 9414",
    "sg:postcode":"95667",
    "sg:province":"CA",
    "sg:tags":[
        "automobile",
        "parts"
    ],
    "wof:name":"Diamond Auto",
    "wof:placetype":"venue"
},
  "geometry": {"coordinates":[-120.82352,38.696345],"type":"Point"}
}