{
  "type": "Feature",
  "properties": {
    "iso:country":"US",
    "sg:address":"1880 Century Park East Suite 250",
    "sg:city":"Los Angeles",
    "sg:classifiers":[
        {
            "category":"Professional",
            "subcategory":"Computer Services",
            "type":"Services"
        }
    ],
    "sg:phone":"+1 800 820 0827",
    "sg:postcode":"90067",
    "sg:province":"CA",
    "sg:tags":[
        "qa",
        "q--a",
        "answers",
        "questions",
        "mobile-search",
        "search",
        "human-powered-search",
        "mobile-search-mobile-answers",
        "question-and-answers-service"
    ],
    "sg:website":"http://www.chacha.com",
    "wof:name":"ChaCha",
    "wof:placetype":"venue"
},
  "geometry": {"coordinates":[-118.41430200000001,34.061402],"type":"Point"}
}