{
  "type": "Feature",
  "properties": {
    "iso:country":"US",
    "sg:address":"4201 Camino De La Plaza",
    "sg:city":"San Diego",
    "sg:classifiers":[
        {
            "category":"Shopping",
            "subcategory":"Shoes",
            "type":"Retail Goods"
        }
    ],
    "sg:phone":"+1 619 690 5378",
    "sg:postcode":"92173",
    "sg:province":"CA",
    "sg:tags":[
        "store"
    ],
    "wof:name":"Adidas Retail Store",
    "wof:placetype":"venue"
},
  "geometry": {"coordinates":[-117.04261,32.545463],"type":"Point"}
}