{
  "type": "Feature",
  "properties": {
    "addr:full":"5539 H St Ste 70 Sacramento CA 95819",
    "addr:housenumber":"5539",
    "addr:postcode":"95819",
    "addr:street":"H St Ste 70",
    "iso:country":"US",
    "sg:address":"5539 H St Ste 70",
    "sg:city":"Sacramento",
    "sg:classifiers":[
        {
            "category":"Personal",
            "subcategory":"Beauty Salon",
            "type":"Services"
        }
    ],
    "sg:phone":"+1 916 452 5539",
    "sg:postcode":"95819",
    "sg:province":"CA",
    "sg:tags":[
        "hair"
    ],
    "sg:website":"www.fireflysalon.com",
    "wof:name":"Firefly Salon & Boutique",
    "wof:placetype":"venue"
},
  "geometry": {"coordinates":[-121.434448,38.567502],"type":"Point"}
}