{
  "type": "Feature",
  "properties": {
    "iso:country":"US",
    "sg:address":"280 E del Mar Blvd",
    "sg:city":"Pasadena",
    "sg:classifiers":[
        {
            "category":"Real Estate",
            "subcategory":"Architect",
            "type":"Services"
        }
    ],
    "sg:phone":"+1 626 683 3426",
    "sg:postcode":"91101",
    "sg:province":"CA",
    "sg:tags":[
        "designer",
        "architectural"
    ],
    "wof:name":"Teg Development",
    "wof:placetype":"venue"
},
  "geometry": {"coordinates":[-118.14473,34.140296],"type":"Point"}
}