{
  "type": "Feature",
  "properties": {
    "addr:full":"25 Main St Chico CA 95928",
    "addr:housenumber":"25",
    "addr:postcode":"95928",
    "addr:street":"Main St",
    "iso:country":"US",
    "sg:address":"25 Main St",
    "sg:city":"Chico",
    "sg:classifiers":[
        {
            "category":"Health Services",
            "subcategory":"Doctor",
            "type":"Services"
        }
    ],
    "sg:phone":"+1 530 879 5000",
    "sg:postcode":"95928",
    "sg:province":"CA",
    "sg:tags":[
        "clinic"
    ],
    "wof:name":"US Veterans Affairs Dept",
    "wof:placetype":"venue"
},
  "geometry": {"coordinates":[-121.841359,39.731163],"type":"Point"}
}