{
  "type": "Feature",
  "properties": {
    "addr:full":"2748 Spring St Paso Robles CA 93446",
    "addr:housenumber":"2748",
    "addr:postcode":"93446",
    "addr:street":"Spring St",
    "iso:country":"US",
    "sg:address":"2748 Spring St",
    "sg:city":"Paso Robles",
    "sg:classifiers":[
        {
            "category":"Sports & Exercise",
            "subcategory":"Bowling",
            "type":"Entertainment"
        }
    ],
    "sg:phone":"+1 805 238 5020",
    "sg:postcode":"93446",
    "sg:province":"CA",
    "sg:tags":[
        "center"
    ],
    "wof:name":"Wilson's Lanes",
    "wof:placetype":"venue"
},
  "geometry": {"coordinates":[-120.692633,35.643058],"type":"Point"}
}