{
  "type": "Feature",
  "properties": {
    "iso:country":"US",
    "sg:address":"137 S Brand Blvd",
    "sg:city":"Glendale",
    "sg:classifiers":[
        {
            "category":"Shopping",
            "subcategory":"Clothing, Apparel, & Fashions",
            "type":"Retail Goods"
        }
    ],
    "sg:phone":"+1 818 241 1861",
    "sg:postcode":"91206",
    "sg:province":"CA",
    "sg:tags":[
        "clothing",
        "women's"
    ],
    "sg:website":"www.freepeople.com",
    "wof:name":"Free People",
    "wof:placetype":"venue"
},
  "geometry": {"coordinates":[-118.255073,34.144907],"type":"Point"}
}