{
  "type": "Feature",
  "properties": {
    "addr:full":"5225 Wilshire Blvd Los Angeles CA 90036",
    "addr:housenumber":"5225",
    "addr:postcode":"90036",
    "addr:street":"Wilshire Blvd",
    "iso:country":"US",
    "sg:address":"5225 Wilshire Blvd",
    "sg:city":"Los Angeles",
    "sg:classifiers":[
        {
            "category":"Professional",
            "type":"Services"
        }
    ],
    "sg:phone":"+1 323 932 0897",
    "sg:postcode":"90036",
    "sg:province":"CA",
    "sg:tags":[
        "establishment"
    ],
    "wof:name":"Raine Agency Inc",
    "wof:placetype":"venue"
},
  "geometry": {"coordinates":[-118.343819,34.06224],"type":"Point"}
}