{
  "type": "Feature",
  "properties": {
    "iso:country":"US",
    "sg:address":"28148 Mountain Meadow Rd",
    "sg:city":"Escondido",
    "sg:classifiers":[
        {
            "category":"Professional",
            "type":"Services"
        }
    ],
    "sg:phone":"+1 760 751 9813",
    "sg:postcode":"92026",
    "sg:province":"CA",
    "wof:name":"Hofmeister LLC",
    "wof:placetype":"venue"
},
  "geometry": {"coordinates":[-117.110712,33.219845],"type":"Point"}
}