{
  "type": "Feature",
  "properties": {
    "addr:full":"1649 S Main St Ste 102 Milpitas CA 95035",
    "addr:housenumber":"1649",
    "addr:postcode":"95035",
    "addr:street":"S Main St Ste 102",
    "iso:country":"US",
    "sg:address":"1649 S Main St Ste 102",
    "sg:city":"Milpitas",
    "sg:classifiers":[
        {
            "category":"Health Services",
            "subcategory":"Health Practitioner",
            "type":"Services"
        }
    ],
    "sg:phone":"+1 408 935 8777",
    "sg:postcode":"95035",
    "sg:province":"CA",
    "sg:tags":[
        "acupuncture"
    ],
    "wof:name":"Sun Bloom Acupuncture Center",
    "wof:placetype":"venue"
},
  "geometry": {"coordinates":[-121.903009,37.406545],"type":"Point"}
}