{
  "type": "Feature",
  "properties": {
    "iso:country":"US",
    "sg:address":"5199 Clairemont Mesa Blvd",
    "sg:city":"San Diego",
    "sg:classifiers":[
        {
            "category":"Food & Beverages",
            "subcategory":"Liquor & Beverages",
            "type":"Retail Goods"
        }
    ],
    "sg:phone":"+1 858 279 6858",
    "sg:postcode":"92117",
    "sg:province":"CA",
    "wof:name":"PAR Grocery & Liquor",
    "wof:placetype":"venue"
},
  "geometry": {"coordinates":[-117.17989300000001,32.834407],"type":"Point"}
}