{
  "type": "Feature",
  "properties": {
    "addr:full":"310 Grau Dr Fremont CA 94536",
    "addr:housenumber":"310",
    "addr:postcode":"94536",
    "addr:street":"Grau Dr",
    "iso:country":"US",
    "sg:address":"310 Grau Dr",
    "sg:city":"Fremont",
    "sg:classifiers":[
        {
            "category":"Home & Garden",
            "subcategory":"Household Appliances",
            "type":"Retail Goods"
        }
    ],
    "sg:phone":"+1 510 582 2079",
    "sg:postcode":"94536",
    "sg:province":"CA",
    "wof:name":"A P Appliances Repair Svc",
    "wof:placetype":"venue"
},
  "geometry": {"coordinates":[-121.994084,37.582391],"type":"Point"}
}