{
  "type": "Feature",
  "properties": {
    "addr:full":"175 N Mill Creek Rd Quincy CA 95971",
    "addr:housenumber":"175",
    "addr:postcode":"95971",
    "addr:street":"N Mill Creek Rd",
    "iso:country":"US",
    "sg:address":"175 N Mill Creek Rd",
    "sg:city":"Quincy",
    "sg:classifiers":[
        {
            "category":"Education",
            "subcategory":"School",
            "type":"Public Place"
        }
    ],
    "sg:phone":"+1 530 283 6520",
    "sg:postcode":"95971",
    "sg:province":"CA",
    "sg:tags":[
        "elementary"
    ],
    "sg:website":"http://www.plumascharterschool.org",
    "wof:name":"Pioneer Elementary School",
    "wof:placetype":"venue"
},
  "geometry": {"coordinates":[-120.904837,39.937252],"type":"Point"}
}