{
  "type": "Feature",
  "properties": {
    "addr:full":"1840 41st Ave Capitola CA 95010",
    "addr:housenumber":"1840",
    "addr:postcode":"95010",
    "addr:street":"41St Ave",
    "iso:country":"US",
    "sg:address":"1840 41st Ave",
    "sg:city":"Capitola",
    "sg:classifiers":[
        {
            "category":"Health Services",
            "subcategory":"Clinic",
            "type":"Services"
        }
    ],
    "sg:phone":"+1 831 465 0160",
    "sg:postcode":"95010",
    "sg:province":"CA",
    "sg:tags":[
        "medical"
    ],
    "sg:website":"www.bodytimechiropractic.com/",
    "wof:name":"Body Time Chiropractic",
    "wof:placetype":"venue"
},
  "geometry": {"coordinates":[-121.963832,36.976259],"type":"Point"}
}