{
  "type": "Feature",
  "properties": {
    "iso:country":"US",
    "sg:address":"1377 S Lilac Ave",
    "sg:city":"Bloomington",
    "sg:classifiers":[
        {
            "category":"Food & Beverages",
            "subcategory":"Groceries & Convenience Stores",
            "type":"Retail Goods"
        }
    ],
    "sg:phone":"+1 909 877 5921",
    "sg:postcode":"92316",
    "sg:province":"CA",
    "sg:tags":[
        "grocer"
    ],
    "wof:name":"Lilac Market",
    "wof:placetype":"venue"
},
  "geometry": {"coordinates":[-117.378946,34.07741],"type":"Point"}
}