{
  "type": "Feature",
  "properties": {
    "iso:country":"US",
    "sg:address":"24950 Ave 212",
    "sg:city":"Lindsay",
    "sg:classifiers":[
        {
            "category":"Professional",
            "subcategory":"Accounting & Tax Preparation",
            "type":"Services"
        }
    ],
    "sg:phone":"+1 559 568 0053",
    "sg:postcode":"93247",
    "sg:province":"CA",
    "sg:tags":[
        "billing"
    ],
    "wof:name":"Physician Services Unlimited",
    "wof:placetype":"venue"
},
  "geometry": {"coordinates":[-119.014691,36.174658],"type":"Point"}
}