{
  "type": "Feature",
  "properties": {
    "addr:full":"9462 Asbury Cir Westminster CA 92683",
    "addr:housenumber":"9462",
    "addr:postcode":"92683",
    "addr:street":"Asbury Cir",
    "iso:country":"US",
    "sg:address":"9462 Asbury Cir",
    "sg:city":"Westminster",
    "sg:classifiers":[
        {
            "category":"Personal",
            "subcategory":"Nail Salon",
            "type":"Services"
        }
    ],
    "sg:phone":"+1 714 839 6780",
    "sg:postcode":"92683",
    "sg:province":"CA",
    "wof:name":"Mimi's Hair & Nails",
    "wof:placetype":"venue"
},
  "geometry": {"coordinates":[-117.96445,33.738768],"type":"Point"}
}