{
  "type": "Feature",
  "properties": {
    "addr:full":"2530 Skypark Dr Torrance CA 90505",
    "addr:housenumber":"2530",
    "addr:postcode":"90505",
    "addr:street":"Skypark Dr",
    "iso:country":"US",
    "sg:address":"2530 Skypark Dr",
    "sg:city":"Torrance",
    "sg:classifiers":[
        {
            "category":"Manufacturing",
            "subcategory":"Aerospace",
            "type":"Manufacturing & Wholesale Goods"
        }
    ],
    "sg:phone":"+1 310 326 4760",
    "sg:postcode":"90505",
    "sg:province":"CA",
    "sg:tags":[
        "engine",
        "aircraft",
        "parts"
    ],
    "wof:name":"Tridair Aerospace Mechanisms",
    "wof:placetype":"venue"
},
  "geometry": {"coordinates":[-118.32825099999999,33.801084],"type":"Point"}
}