{
  "type": "Feature",
  "properties": {
    "addr:full":"1930 Northstar way #154 San Marcos CA 92078",
    "addr:housenumber":"1930",
    "addr:postcode":"92078",
    "addr:street":"Northstar Way # 154",
    "iso:country":"US",
    "sg:address":"1930 Northstar way #154",
    "sg:city":"San Marcos",
    "sg:classifiers":[
        {
            "category":"Communications",
            "type":"Services"
        }
    ],
    "sg:phone":"+1 760 798 4508",
    "sg:postcode":"92078",
    "sg:province":"CA",
    "sg:tags":[
        "web",
        "design"
    ],
    "sg:website":"www.knappstead.com",
    "wof:name":"Knappstead",
    "wof:placetype":"venue"
},
  "geometry": {"coordinates":[-117.218896,33.099411],"type":"Point"}
}