{
  "type": "Feature",
  "properties": {
    "addr:full":"119 Stoney Creek Rd Santa Cruz CA 95060",
    "addr:housenumber":"119",
    "addr:postcode":"95060",
    "addr:street":"Stoney Creek Rd",
    "iso:country":"US",
    "sg:address":"119 Stoney Creek Rd",
    "sg:city":"Santa Cruz",
    "sg:classifiers":[
        {
            "category":"Communications",
            "type":"Services"
        }
    ],
    "sg:phone":"+1 831 457 2363",
    "sg:postcode":"95060",
    "sg:province":"CA",
    "sg:tags":[
        "communication"
    ],
    "wof:name":"Milagro Communications Inc",
    "wof:placetype":"venue"
},
  "geometry": {"coordinates":[-122.014939,36.988101],"type":"Point"}
}