{
  "type": "Feature",
  "properties": {
    "iso:country":"US",
    "sg:address":"1257 Broadway",
    "sg:city":"El Cajon",
    "sg:classifiers":[
        {
            "category":"Shopping",
            "subcategory":"Computers & Home Electronics",
            "type":"Retail Goods"
        }
    ],
    "sg:phone":"+1 619 442 8420",
    "sg:postcode":"92021",
    "sg:province":"CA",
    "wof:name":"Affordable Satellte Sys By SPD",
    "wof:placetype":"venue"
},
  "geometry": {"coordinates":[-116.935957,32.80763],"type":"Point"}
}