{
  "type": "Feature",
  "properties": {
    "iso:country":"US",
    "sg:address":"228 N Washington St",
    "sg:city":"Sonora",
    "sg:classifiers":[
        {
            "category":"Shopping",
            "subcategory":"Pharmacy",
            "type":"Retail Goods"
        }
    ],
    "sg:phone":"+1 209 536 9393",
    "sg:postcode":"95370",
    "sg:province":"CA",
    "wof:name":"Touch Of Light Ayurveda",
    "wof:placetype":"venue"
},
  "geometry": {"coordinates":[-120.384654,37.988565],"type":"Point"}
}