{
  "type": "Feature",
  "properties": {
    "addr:full":"4405 39th St San Diego CA 92116",
    "addr:housenumber":"4405",
    "addr:postcode":"92116",
    "addr:street":"39Th St",
    "iso:country":"US",
    "sg:address":"4405 39th St",
    "sg:city":"San Diego",
    "sg:classifiers":[
        {
            "category":"Professional",
            "type":"Services"
        }
    ],
    "sg:phone":"+1 619 280 0059",
    "sg:postcode":"92116",
    "sg:province":"CA",
    "wof:name":"Healthy Home Service",
    "wof:placetype":"venue"
},
  "geometry": {"coordinates":[-117.11030700000001,32.758902],"type":"Point"}
}