{
  "type": "Feature",
  "properties": {
    "addr:full":"346 N Curson Ave Los Angeles CA 90036",
    "addr:housenumber":"346",
    "addr:postcode":"90036",
    "addr:street":"N Curson Ave",
    "iso:country":"US",
    "sg:address":"346 N Curson Ave",
    "sg:city":"Los Angeles",
    "sg:classifiers":[
        {
            "category":"Sports & Exercise",
            "subcategory":"Gym",
            "type":"Entertainment"
        }
    ],
    "sg:phone":"+1 323 932 6506",
    "sg:postcode":"90036",
    "sg:province":"CA",
    "sg:tags":[
        "club",
        "health",
        "studio",
        "gymnasium"
    ],
    "wof:name":"X Kids",
    "wof:placetype":"venue"
},
  "geometry": {"coordinates":[-118.35521799999999,34.077241],"type":"Point"}
}