{
  "type": "Feature",
  "properties": {
    "addr:full":"2917 W Cubbon St Santa Ana CA 92704",
    "addr:housenumber":"2917",
    "addr:postcode":"92704",
    "addr:street":"W Cubbon St",
    "iso:country":"US",
    "sg:address":"2917 W Cubbon St",
    "sg:city":"Santa Ana",
    "sg:classifiers":[
        {
            "category":"Professional",
            "type":"Services"
        }
    ],
    "sg:phone":"+1 714 836 8967",
    "sg:postcode":"92704",
    "sg:province":"CA",
    "wof:name":"El Chilango 2",
    "wof:placetype":"venue"
},
  "geometry": {"coordinates":[-117.90833000000001,33.735086],"type":"Point"}
}