{
  "type": "Feature",
  "properties": {
    "iso:country":"US",
    "sg:address":"5920 Monterey Rd",
    "sg:city":"Los Angeles",
    "sg:classifiers":[
        {
            "category":"Retail",
            "subcategory":"Laundry & Dry Cleaning",
            "type":"Services"
        }
    ],
    "sg:phone":"+1 323 257 0439",
    "sg:postcode":"90042",
    "sg:province":"CA",
    "wof:name":"Spincycle Coin Laundry",
    "wof:placetype":"venue"
},
  "geometry": {"coordinates":[-118.183998,34.105099],"type":"Point"}
}