{
  "type": "Feature",
  "properties": {
    "iso:country":"US",
    "sg:address":"2 Fifer Ave",
    "sg:city":"Corte Madera",
    "sg:classifiers":[
        {
            "category":"Health Services",
            "subcategory":"Doctor",
            "type":"Services"
        }
    ],
    "sg:phone":"+1 415 927 6695",
    "sg:postcode":"94925",
    "sg:province":"CA",
    "sg:tags":[
        "physician",
        "surgeon"
    ],
    "wof:name":"Scott Olson DO",
    "wof:placetype":"venue"
},
  "geometry": {"coordinates":[-122.518682,37.938324],"type":"Point"}
}