{
  "type": "Feature",
  "properties": {
    "iso:country":"US",
    "sg:address":"44904 Rd 136",
    "sg:city":"Orange Cove",
    "sg:classifiers":[
        {
            "category":"Real Estate",
            "subcategory":"Real Estate Operator",
            "type":"Services"
        }
    ],
    "sg:phone":"+1 559 626 7262",
    "sg:postcode":"93646",
    "sg:province":"CA",
    "sg:tags":[
        "property",
        "lessor"
    ],
    "wof:name":"Irene Hendrixson",
    "wof:placetype":"venue"
},
  "geometry": {"coordinates":[-119.269091,36.602766],"type":"Point"}
}