{
  "type": "Feature",
  "properties": {
    "addr:full":"800 S Broadway Walnut Creek CA 94596",
    "addr:housenumber":"800",
    "addr:postcode":"94596",
    "addr:street":"S Broadway",
    "iso:country":"US",
    "sg:address":"800 S Broadway",
    "sg:city":"Walnut Creek",
    "sg:classifiers":[
        {
            "category":"Social Services",
            "type":"Services"
        }
    ],
    "sg:phone":"+1 925 946 9658",
    "sg:postcode":"94596",
    "sg:province":"CA",
    "sg:tags":[
        "agency",
        "adoption"
    ],
    "wof:name":"Partners For Adoption",
    "wof:placetype":"venue"
},
  "geometry": {"coordinates":[-122.05868599999999,37.894199],"type":"Point"}
}