{
  "type": "Feature",
  "properties": {
    "addr:full":"520 Houston St West Sacramento CA 95691",
    "addr:housenumber":"520",
    "addr:postcode":"95691",
    "addr:street":"Houston St",
    "iso:country":"US",
    "sg:address":"520 Houston St",
    "sg:city":"West Sacramento",
    "sg:classifiers":[
        {
            "category":"Freight",
            "type":"Transportation"
        }
    ],
    "sg:phone":"+1 916 362 0120",
    "sg:postcode":"95691",
    "sg:province":"CA",
    "sg:tags":[
        "trucking"
    ],
    "wof:name":"KTL",
    "wof:placetype":"venue"
},
  "geometry": {"coordinates":[-121.55118400000001,38.580236],"type":"Point"}
}