{
  "type": "Feature",
  "properties": {
    "addr:full":"456 E Mission Rd San Marcos CA 92069",
    "addr:housenumber":"456",
    "addr:postcode":"92069",
    "addr:street":"E Mission Rd",
    "iso:country":"US",
    "sg:address":"456 E Mission Rd",
    "sg:city":"San Marcos",
    "sg:classifiers":[
        {
            "category":"Sports & Exercise",
            "subcategory":"Gym",
            "type":"Entertainment"
        }
    ],
    "sg:phone":"+1 760 744 4562",
    "sg:postcode":"92069",
    "sg:province":"CA",
    "sg:tags":[
        "club",
        "health",
        "studio",
        "gymnasium"
    ],
    "wof:name":"International Fitness Ctr",
    "wof:placetype":"venue"
},
  "geometry": {"coordinates":[-117.15535300000001,33.142739],"type":"Point"}
}