{
  "type": "Feature",
  "properties": {
    "iso:country":"US",
    "sg:address":"5327 Romford Dr",
    "sg:city":"San Jose",
    "sg:classifiers":[
        {
            "category":"Professional",
            "subcategory":"Lawyer & Legal Services",
            "type":"Services"
        }
    ],
    "sg:phone":"+1 925 648 4839",
    "sg:postcode":"95124",
    "sg:province":"CA",
    "sg:tags":[
        "patent",
        "agent"
    ],
    "wof:name":"Allmark Trademark Svc",
    "wof:placetype":"venue"
},
  "geometry": {"coordinates":[-121.915915,37.241755],"type":"Point"}
}