{
  "type": "Feature",
  "properties": {
    "addr:full":"3120 Telegraph Ave Berkeley CA 94705",
    "addr:housenumber":"3120",
    "addr:postcode":"94705",
    "addr:street":"Telegraph Ave",
    "iso:country":"US",
    "sg:address":"3120 Telegraph Ave",
    "sg:city":"Berkeley",
    "sg:classifiers":[
        {
            "category":"Health Services",
            "subcategory":"Health Practitioner",
            "type":"Services"
        }
    ],
    "sg:phone":"+1 510 704 0707",
    "sg:postcode":"94705",
    "sg:province":"CA",
    "sg:tags":[
        "psychotherapist"
    ],
    "wof:name":"Patricia Bland",
    "wof:placetype":"venue"
},
  "geometry": {"coordinates":[-122.25997099999999,37.854071],"type":"Point"}
}