{
  "type": "Feature",
  "properties": {
    "addr:full":"1048 W Fremont St Stockton CA 95203",
    "addr:housenumber":"1048",
    "addr:postcode":"95203",
    "addr:street":"W Fremont St",
    "iso:country":"US",
    "sg:address":"1048 W Fremont St",
    "sg:city":"Stockton",
    "sg:classifiers":[
        {
            "category":"Building & Trades",
            "subcategory":"Construction",
            "type":"Services"
        }
    ],
    "sg:phone":"+1 209 460 1073",
    "sg:postcode":"95203",
    "sg:province":"CA",
    "sg:tags":[
        "contractor"
    ],
    "wof:name":"Niche Builders",
    "wof:placetype":"venue"
},
  "geometry": {"coordinates":[-121.30624400000001,37.955107],"type":"Point"}
}