{
  "type": "Feature",
  "properties": {
    "addr:full":"2740 Tidelands Ave National City CA 91950",
    "addr:housenumber":"2740",
    "addr:postcode":"91950",
    "addr:street":"Tidelands Ave",
    "iso:country":"US",
    "sg:address":"2740 Tidelands Ave",
    "sg:city":"National City",
    "sg:classifiers":[
        {
            "category":"Manufacturing",
            "subcategory":"Building Materials",
            "type":"Manufacturing & Wholesale Goods"
        }
    ],
    "sg:phone":"+1 619 477 3791",
    "sg:postcode":"91950",
    "sg:province":"CA",
    "sg:tags":[
        "truss"
    ],
    "sg:website":"www.dixieline.com",
    "wof:name":"Dixieline Lumber",
    "wof:placetype":"venue"
},
  "geometry": {"coordinates":[-117.113572,32.655122],"type":"Point"}
}