{
  "type": "Feature",
  "properties": {
    "addr:full":"307 4th St Sausalito CA 94965",
    "addr:housenumber":"307",
    "addr:postcode":"94965",
    "addr:street":"4Th St",
    "iso:country":"US",
    "sg:address":"307 4th St",
    "sg:city":"Sausalito",
    "sg:classifiers":[
        {
            "category":"Professional",
            "subcategory":"Management & Consulting",
            "type":"Services"
        }
    ],
    "sg:phone":"+1 415 331 4036",
    "sg:postcode":"94965",
    "sg:province":"CA",
    "sg:tags":[
        "consultant",
        "business"
    ],
    "wof:name":"Pacific Associates",
    "wof:placetype":"venue"
},
  "geometry": {"coordinates":[-122.482587,37.850777],"type":"Point"}
}