{
  "type": "Feature",
  "properties": {
    "addr:full":"1930 Placentia Ave Costa Mesa CA 92627",
    "addr:postcode":"1930;92627",
    "addr:street":"Placentia Ave",
    "iso:country":"US",
    "sg:address":"1930 Placentia Ave",
    "sg:city":"Costa Mesa",
    "sg:classifiers":[
        {
            "category":"Autos & Motor Vehicles",
            "subcategory":"Automobile Sales",
            "type":"Retail Goods"
        }
    ],
    "sg:phone":"+1 714 335 4773",
    "sg:postcode":"92627",
    "sg:province":"CA",
    "sg:tags":[
        "used"
    ],
    "wof:name":"Coast Motors",
    "wof:placetype":"venue"
},
  "geometry": {"coordinates":[-117.931929,33.644314],"type":"Point"}
}