{
  "type": "Feature",
  "properties": {
    "addr:full":"2015 Westminster Mall Westminster CA 92683",
    "addr:housenumber":"2015",
    "addr:postcode":"92683",
    "addr:street":"Westminster Mall",
    "iso:country":"US",
    "sg:address":"2015 Westminster Mall",
    "sg:city":"Westminster",
    "sg:classifiers":[
        {
            "category":"Restaurant",
            "type":"Food & Drink"
        }
    ],
    "sg:phone":"+1 714 899 3344",
    "sg:postcode":"92683",
    "sg:province":"CA",
    "sg:tags":[
        "italian"
    ],
    "wof:name":"Spankie's Italian Cafe",
    "wof:placetype":"venue"
},
  "geometry": {"coordinates":[-118.009479,33.747526],"type":"Point"}
}