{
  "type": "Feature",
  "properties": {
    "addr:full":"17246 Hawthorne Blvd Torrance CA 90504",
    "addr:housenumber":"17246",
    "addr:postcode":"90504",
    "addr:street":"Hawthorne Blvd",
    "iso:country":"US",
    "sg:address":"17246 Hawthorne Blvd",
    "sg:city":"Torrance",
    "sg:classifiers":[
        {
            "category":"Professional",
            "subcategory":"Employment Agencies",
            "type":"Services"
        }
    ],
    "sg:phone":"+1 310 542 4008",
    "sg:postcode":"90504",
    "sg:province":"CA",
    "sg:tags":[
        "opportunity"
    ],
    "sg:website":"www.a-w-f.com",
    "wof:name":"American Work Force",
    "wof:placetype":"venue"
},
  "geometry": {"coordinates":[-118.352997,33.873901],"type":"Point"}
}