{
  "type": "Feature",
  "properties": {
    "iso:country":"US",
    "sg:address":"12644 Lakewood Blvd",
    "sg:city":"Downey",
    "sg:classifiers":[
        {
            "category":"Travel",
            "subcategory":"Hotels & Motels",
            "type":"Entertainment"
        }
    ],
    "sg:phone":"+1 562 861 7278",
    "sg:postcode":"90242",
    "sg:province":"CA",
    "sg:website":"www.socalinns.com",
    "wof:name":"American Inn",
    "wof:placetype":"venue"
},
  "geometry": {"coordinates":[-118.138,33.916698],"type":"Point"}
}