{
  "type": "Feature",
  "properties": {
    "iso:country":"US",
    "sg:address":"2825 Fir St",
    "sg:city":"Live Oak",
    "sg:classifiers":[
        {
            "category":"Organizations",
            "subcategory":"Religious Organization",
            "type":"Services"
        }
    ],
    "sg:phone":"+1 530 695 2617",
    "sg:postcode":"95953",
    "sg:province":"CA",
    "wof:name":"Islamic Center Of Live Oak",
    "wof:placetype":"venue"
},
  "geometry": {"coordinates":[-121.66626100000001,39.274046],"type":"Point"}
}