{
  "type": "Feature",
  "properties": {
    "iso:country":"US",
    "sg:address":"4334 E 49th St",
    "sg:city":"Vernon",
    "sg:classifiers":[
        {
            "category":"Real Estate",
            "subcategory":"Developer",
            "type":"Services"
        }
    ],
    "sg:phone":"+1 909 636 3633",
    "sg:postcode":"90058",
    "sg:province":"CA",
    "wof:name":"Ampler Development Co",
    "wof:placetype":"venue"
},
  "geometry": {"coordinates":[-118.200914,33.998156],"type":"Point"}
}