{
  "type": "Feature",
  "properties": {
    "addr:full":"11944 Bernardo Plaza Dr San Diego CA 92128",
    "addr:housenumber":"11944",
    "addr:postcode":"92128",
    "addr:street":"Bernardo Plaza Dr",
    "iso:country":"US",
    "sg:address":"11944 Bernardo Plaza Dr",
    "sg:city":"San Diego",
    "sg:classifiers":[
        {
            "category":"Health Services",
            "subcategory":"Optometrist",
            "type":"Services"
        }
    ],
    "sg:phone":"+1 858 451 1250",
    "sg:postcode":"92128",
    "sg:province":"CA",
    "wof:name":"Lee & Assoc",
    "wof:placetype":"venue"
},
  "geometry": {"coordinates":[-117.074347,33.020277],"type":"Point"}
}