{
  "type": "Feature",
  "properties": {
    "iso:country":"US",
    "sg:address":"1027 W Main St",
    "sg:city":"Santa Maria",
    "sg:classifiers":[
        {
            "category":"Shopping",
            "type":"Retail Goods"
        },
        {
            "category":"Retail",
            "subcategory":"Animal Services",
            "type":"Services"
        }
    ],
    "sg:phone":"+1 805 925 7661",
    "sg:postcode":"93458",
    "sg:province":"CA",
    "sg:tags":[
        "pet",
        "grooming",
        "washing",
        "merchandise"
    ],
    "wof:name":"Suzie's Poodle",
    "wof:placetype":"venue"
},
  "geometry": {"coordinates":[-120.449789,34.953399],"type":"Point"}
}