{
  "type": "Feature",
  "properties": {
    "iso:country":"US",
    "sg:address":"2146 W Lincoln Ave",
    "sg:city":"Anaheim",
    "sg:classifiers":[
        {
            "category":"Autos & Motor Vehicles",
            "subcategory":"Auto Supplies",
            "type":"Retail Goods"
        },
        {
            "category":"Retail",
            "subcategory":"Auto Repair",
            "type":"Services"
        }
    ],
    "sg:phone":"+1 714 535 2831",
    "sg:postcode":"92801",
    "sg:province":"CA",
    "sg:tags":[
        "tire"
    ],
    "sg:website":"www.mitchelltireservice.com/inde...",
    "wof:name":"Firestone-Mitchell Tire Service",
    "wof:placetype":"venue"
},
  "geometry": {"coordinates":[-117.95700100000001,33.8326],"type":"Point"}
}