{
  "type": "Feature",
  "properties": {
    "iso:country":"US",
    "sg:address":"4131 Industrial Way",
    "sg:city":"Tracy",
    "sg:classifiers":[
        {
            "category":"Building & Trades",
            "subcategory":"Construction",
            "type":"Services"
        }
    ],
    "sg:phone":"+1 209 833 4400",
    "sg:postcode":"95304",
    "sg:province":"CA",
    "sg:tags":[
        "excavating",
        "contractor"
    ],
    "sg:website":"www.minyardexcavating.com",
    "wof:name":"Minyard Excavating",
    "wof:placetype":"venue"
},
  "geometry": {"coordinates":[-121.431704,37.766683],"type":"Point"}
}