{
  "type": "Feature",
  "properties": {
    "iso:country":"US",
    "sg:address":"1304 S 51st St",
    "sg:city":"Richmond",
    "sg:classifiers":[
        {
            "category":"Professional",
            "subcategory":"Computer Services",
            "type":"Services"
        }
    ],
    "sg:phone":"+1 510 215 3400",
    "sg:postcode":"94804",
    "sg:province":"CA",
    "sg:tags":[
        "repair"
    ],
    "wof:name":"SSP Data",
    "wof:placetype":"venue"
},
  "geometry": {"coordinates":[-122.327003,37.9119],"type":"Point"}
}