{
  "type": "Feature",
  "properties": {
    "iso:country":"US",
    "sg:address":"6115 Selma Ave",
    "sg:city":"Los Angeles",
    "sg:classifiers":[
        {
            "category":"Freight",
            "type":"Transportation"
        }
    ],
    "sg:phone":"+1 323 467 9213",
    "sg:postcode":"90028",
    "sg:province":"CA",
    "sg:tags":[
        "operator",
        "local",
        "courier",
        "trucking"
    ],
    "wof:name":"The Courier Express",
    "wof:placetype":"venue"
},
  "geometry": {"coordinates":[-118.323566,34.099886],"type":"Point"}
}