{
  "type": "Feature",
  "properties": {
    "iso:country":"US",
    "sg:address":"10407 Los Alamitos Blvd",
    "sg:city":"Los Alamitos",
    "sg:classifiers":[
        {
            "category":"Banks & Credit Unions",
            "subcategory":"Financial Services",
            "type":"Services"
        }
    ],
    "sg:phone":"+1 562 598 8818",
    "sg:postcode":"90720",
    "sg:province":"CA",
    "sg:tags":[
        "broker",
        "mortgage"
    ],
    "wof:name":"Preferred Real Estate Finance",
    "wof:placetype":"venue"
},
  "geometry": {"coordinates":[-118.207723,33.811106],"type":"Point"}
}