{
  "type": "Feature",
  "properties": {
    "iso:country":"US",
    "sg:address":"10126 Lev Ave",
    "sg:city":"Pacoima",
    "sg:classifiers":[
        {
            "category":"Shopping",
            "type":"Retail Goods"
        }
    ],
    "sg:phone":"+1 818 896 2287",
    "sg:postcode":"91331",
    "sg:province":"CA",
    "sg:tags":[
        "merchandise"
    ],
    "wof:name":"Speakers Etc",
    "wof:placetype":"venue"
},
  "geometry": {"coordinates":[-118.436673,34.253338],"type":"Point"}
}