{
  "type": "Feature",
  "properties": {
    "addr:full":"17003 Ripon Ave Bellflower CA 90706",
    "addr:postcode":"17003;90706",
    "addr:street":"Ripon Ave",
    "iso:country":"US",
    "sg:address":"17003 Ripon Ave",
    "sg:city":"Bellflower",
    "sg:classifiers":[
        {
            "category":"Building & Trades",
            "subcategory":"Landscaping Services",
            "type":"Services"
        }
    ],
    "sg:phone":"+1 562 866 9858",
    "sg:postcode":"90706",
    "sg:province":"CA",
    "sg:tags":[
        "landscape",
        "contractor"
    ],
    "wof:name":"Luke's Gardening",
    "wof:placetype":"venue"
},
  "geometry": {"coordinates":[-118.11154999999999,33.878937],"type":"Point"}
}