{
  "type": "Feature",
  "properties": {
    "addr:full":"2691 Reservoir Ln Redding CA 96002",
    "addr:housenumber":"2691",
    "addr:postcode":"96002",
    "addr:street":"Reservoir Ln",
    "iso:country":"US",
    "sg:address":"2691 Reservoir Ln",
    "sg:city":"Redding",
    "sg:classifiers":[
        {
            "category":"Utilities",
            "subcategory":"Telephone",
            "type":"Services"
        }
    ],
    "sg:phone":"+1 530 949 8234",
    "sg:postcode":"96002",
    "sg:province":"CA",
    "sg:tags":[
        "telecommunication"
    ],
    "wof:name":"KERN Telecom",
    "wof:placetype":"venue"
},
  "geometry": {"coordinates":[-122.345209,40.569035],"type":"Point"}
}