{
  "type": "Feature",
  "properties": {
    "iso:country":"US",
    "sg:address":"2107 Westminster Mall",
    "sg:city":"Westminster",
    "sg:classifiers":[
        {
            "category":"Restaurant",
            "type":"Food & Drink"
        }
    ],
    "sg:menulink":"http://www.allmenus.com/ca/north-coast/216169-mcdonalds/menu/",
    "sg:postcode":"92683",
    "sg:province":"CA",
    "sg:tags":[
        "burger",
        "american"
    ],
    "wof:name":"McDonald's",
    "wof:placetype":"venue"
},
  "geometry": {"coordinates":[-118.01041499999999,33.748601],"type":"Point"}
}