{
  "type": "Feature",
  "properties": {
    "iso:country":"US",
    "sg:address":"1100 Olympic Dr",
    "sg:city":"Corona",
    "sg:classifiers":[
        {
            "category":"Shopping",
            "type":"Retail Goods"
        }
    ],
    "sg:phone":"+1 951 340 3426",
    "sg:postcode":"92881",
    "sg:province":"CA",
    "sg:tags":[
        "picture",
        "frame"
    ],
    "wof:name":"On The Wall Frames",
    "wof:placetype":"venue"
},
  "geometry": {"coordinates":[-117.53901399999999,33.85955],"type":"Point"}
}