{
  "type": "Feature",
  "properties": {
    "addr:full":"53800 Dinkey Creek Rd Shaver Lake CA 93664",
    "addr:postcode":"53800;93664",
    "addr:street":"Dinkey Creek Rd",
    "iso:country":"US",
    "sg:address":"53800 Dinkey Creek Rd",
    "sg:city":"Shaver Lake",
    "sg:classifiers":[
        {
            "category":"Government",
            "subcategory":"Office",
            "type":"Public Place"
        }
    ],
    "sg:phone":"+1 559 841 3404",
    "sg:postcode":"93664",
    "sg:province":"CA",
    "sg:tags":[
        "conservation"
    ],
    "wof:name":"Dinkey Ranger Station",
    "wof:placetype":"venue"
},
  "geometry": {"coordinates":[-119.156183,37.085772],"type":"Point"}
}