{
  "type": "Feature",
  "properties": {
    "addr:full":"3330 Hillview Ave Palo Alto CA 94304",
    "addr:housenumber":"3330",
    "addr:postcode":"94304",
    "addr:street":"Hillview Ave",
    "iso:country":"US",
    "sg:address":"3330 Hillview Ave",
    "sg:city":"Palo Alto",
    "sg:classifiers":[
        {
            "category":"Professional",
            "subcategory":"Lawyer & Legal Services",
            "type":"Services"
        }
    ],
    "sg:phone":"+1 650 251 5000",
    "sg:postcode":"94304",
    "sg:province":"CA",
    "sg:tags":[
        "attorney"
    ],
    "sg:website":"www.simpsonthacher.com",
    "wof:name":"Simpson Thacher & Bartlett",
    "wof:placetype":"venue"
},
  "geometry": {"coordinates":[-122.145875,37.405038],"type":"Point"}
}