{
  "type": "Feature",
  "properties": {
    "iso:country":"US",
    "sg:address":"1010 Lootens Pl",
    "sg:city":"San Rafael",
    "sg:classifiers":[
        {
            "category":"Shopping",
            "subcategory":"Clothing, Apparel, & Fashions",
            "type":"Retail Goods"
        }
    ],
    "sg:phone":"+1 415 454 9454",
    "sg:postcode":"94901",
    "sg:province":"CA",
    "sg:tags":[
        "tailor"
    ],
    "wof:name":"Indru's Tailoring & Alteration",
    "wof:placetype":"venue"
},
  "geometry": {"coordinates":[-122.52590600000001,37.97364],"type":"Point"}
}