{
  "type": "Feature",
  "properties": {
    "addr:full":"42145 Lyndie Ln Ste 116 Temecula CA 92591",
    "addr:postcode":"42145;92591",
    "addr:street":"Lyndie Ln Ste 116",
    "iso:country":"US",
    "sg:address":"42145 Lyndie Ln Ste 116",
    "sg:city":"Temecula",
    "sg:classifiers":[
        {
            "category":"Banks & Credit Unions",
            "subcategory":"Investment Brokerage",
            "type":"Services"
        },
        {
            "category":"Banks & Credit Unions",
            "subcategory":"Financial Services",
            "type":"Services"
        }
    ],
    "sg:phone":"+1 951 587 6106",
    "sg:postcode":"92591",
    "sg:province":"CA",
    "sg:tags":[
        "planning",
        "advisory",
        "planner",
        "consultant"
    ],
    "sg:website":"http://www.theplannersnetwork.com",
    "wof:name":"Agave Landform, Inc.",
    "wof:placetype":"venue"
},
  "geometry": {"coordinates":[-117.142591,33.507332],"type":"Point"}
}