{
  "type": "Feature",
  "properties": {
    "iso:country":"US",
    "sg:address":"24110 Congress Springs Rd",
    "sg:city":"Saratoga",
    "sg:classifiers":[
        {
            "category":"Manufacturing",
            "subcategory":"Paper Products",
            "type":"Manufacturing & Wholesale Goods"
        }
    ],
    "sg:phone":"+1 408 741 5494",
    "sg:postcode":"95070",
    "sg:province":"CA",
    "sg:tags":[
        "mill"
    ],
    "wof:name":"International Paper",
    "wof:placetype":"venue"
},
  "geometry": {"coordinates":[-122.069991,37.248157],"type":"Point"}
}