{
  "type": "Feature",
  "properties": {
    "addr:full":"2435 C St #5 San Diego CA 92102",
    "addr:housenumber":"2435",
    "addr:postcode":"92102",
    "addr:street":"C St # 5",
    "iso:country":"US",
    "sg:address":"2435 C St #5",
    "sg:city":"San Diego",
    "sg:classifiers":[
        {
            "category":"Animal Shelter",
            "type":"Public Place"
        }
    ],
    "sg:phone":"+1 619 721 3647",
    "sg:postcode":"92102",
    "sg:province":"CA",
    "sg:website":"www.secondchancedogrescue.org",
    "wof:name":"Second Chance Dog Rescue",
    "wof:placetype":"venue"
},
  "geometry": {"coordinates":[-117.14169699999999,32.716563],"type":"Point"}
}