{
  "type": "Feature",
  "properties": {
    "addr:full":"19204 Figueroa St Carson CA 90745",
    "addr:housenumber":"19204",
    "addr:postcode":"90745",
    "addr:street":"Figueroa St",
    "iso:country":"US",
    "sg:address":"19204 Figueroa St",
    "sg:city":"Carson",
    "sg:classifiers":[
        {
            "category":"Banks & Credit Unions",
            "subcategory":"Bank",
            "type":"Services"
        }
    ],
    "sg:phone":"+1 888 505 9378",
    "sg:postcode":"90745",
    "sg:province":"CA",
    "wof:name":"Best of The West Distribution",
    "wof:placetype":"venue"
},
  "geometry": {"coordinates":[-118.285984,33.83477],"type":"Point"}
}