{
  "type": "Feature",
  "properties": {
    "addr:full":"707 Montana Ave Santa Monica CA 90403",
    "addr:housenumber":"707",
    "addr:postcode":"90403",
    "addr:street":"Montana Ave",
    "iso:country":"US",
    "sg:address":"707 Montana Ave",
    "sg:city":"Santa Monica",
    "sg:classifiers":[
        {
            "category":"Personal",
            "subcategory":"Beauty Salon",
            "type":"Services"
        }
    ],
    "sg:phone":"+1 310 393 2334",
    "sg:postcode":"90403",
    "sg:province":"CA",
    "wof:name":"American Beauty Hair Fashions",
    "wof:placetype":"venue"
},
  "geometry": {"coordinates":[-118.501409,34.027224],"type":"Point"}
}