{
  "type": "Feature",
  "properties": {
    "addr:full":"7007 Friars Road Fasion Valley San Diego CA 92108",
    "addr:housenumber":"7007",
    "addr:postcode":"92108",
    "addr:street":"Friars Road Fasion Valley",
    "iso:country":"US",
    "sg:address":"7007 Friars Road Fasion Valley",
    "sg:city":"San Diego",
    "sg:classifiers":[
        {
            "category":"Shopping",
            "subcategory":"Clothing, Apparel, & Fashions",
            "type":"Retail Goods"
        }
    ],
    "sg:phone":"+1 619 291 1295",
    "sg:postcode":"92108",
    "sg:province":"CA",
    "sg:tags":[
        "clothing",
        "women's"
    ],
    "sg:website":"Toryburch.com",
    "wof:name":"Tory Burch",
    "wof:placetype":"venue"
},
  "geometry": {"coordinates":[-117.16895,32.769558],"type":"Point"}
}