{
  "type": "Feature",
  "properties": {
    "addr:full":"796 Main St Venice CA 90291",
    "addr:housenumber":"796",
    "addr:postcode":"90291",
    "addr:street":"Main St",
    "iso:country":"US",
    "sg:address":"796 Main St",
    "sg:city":"Venice",
    "sg:classifiers":[
        {
            "category":"Restaurant",
            "type":"Food & Drink"
        }
    ],
    "sg:phone":"+1 310 821 6331",
    "sg:postcode":"90291",
    "sg:province":"CA",
    "sg:tags":[
        "caterer"
    ],
    "wof:name":"Co For Dinner",
    "wof:placetype":"venue"
},
  "geometry": {"coordinates":[-118.47460599999999,33.992954],"type":"Point"}
}