{
  "type": "Feature",
  "properties": {
    "iso:country":"US",
    "sg:address":"105 Bernal Rd",
    "sg:city":"San Jose",
    "sg:classifiers":[
        {
            "category":"Fast Food",
            "type":"Food & Drink"
        }
    ],
    "sg:phone":"+1 408 578 9835",
    "sg:postcode":"95119",
    "sg:province":"CA",
    "wof:name":"McDonald's",
    "wof:placetype":"venue"
},
  "geometry": {"coordinates":[-121.773151,37.231715],"type":"Point"}
}