{
  "type": "Feature",
  "properties": {
    "iso:country":"US",
    "sg:address":"1933 Davis Street",
    "sg:city":"San Leandro",
    "sg:classifiers":[
        {
            "category":"Restaurant",
            "type":"Food & Drink"
        }
    ],
    "sg:phone":"+1 510 383 9898",
    "sg:postcode":"94577",
    "sg:province":"CA",
    "sg:tags":[
        "hawaiian",
        "barbeque"
    ],
    "sg:website":"www.hawaiianislandbbq.com",
    "wof:name":"Ohana Hawaiian BBQ",
    "wof:placetype":"venue"
},
  "geometry": {"coordinates":[-122.18119,37.717861],"type":"Point"}
}