{
  "type": "Feature",
  "properties": {
    "addr:full":"76 Marina Lakes Dr Richmond CA 94804",
    "addr:housenumber":"76",
    "addr:postcode":"94804",
    "addr:street":"Marina Lakes Dr",
    "iso:country":"US",
    "sg:address":"76 Marina Lakes Dr",
    "sg:city":"Richmond",
    "sg:classifiers":[
        {
            "category":"Shopping",
            "subcategory":"Computers & Home Electronics",
            "type":"Retail Goods"
        }
    ],
    "sg:phone":"+1 510 236 0936",
    "sg:postcode":"94804",
    "sg:province":"CA",
    "sg:tags":[
        "software"
    ],
    "wof:name":"Luluwest",
    "wof:placetype":"venue"
},
  "geometry": {"coordinates":[-122.34040899999999,37.911892],"type":"Point"}
}