{
  "type": "Feature",
  "properties": {
    "addr:full":"8601 Westminster Ave Garden Grove CA 92844",
    "addr:housenumber":"8601",
    "addr:postcode":"92844",
    "addr:street":"Westminster Ave",
    "iso:country":"US",
    "sg:address":"8601 Westminster Ave",
    "sg:city":"Garden Grove",
    "sg:classifiers":[
        {
            "category":"Retail",
            "subcategory":"Auto Repair",
            "type":"Services"
        }
    ],
    "sg:phone":"+1 714 895 1075",
    "sg:postcode":"92844",
    "sg:province":"CA",
    "wof:name":"John Auto Repair",
    "wof:placetype":"venue"
},
  "geometry": {"coordinates":[-117.979114,33.759554],"type":"Point"}
}