{
  "type": "Feature",
  "properties": {
    "addr:full":"2655 W Olympic Blvd Los Angeles CA 90006",
    "addr:housenumber":"2655",
    "addr:postcode":"90006",
    "addr:street":"W Olympic Blvd",
    "iso:country":"US",
    "sg:address":"2655 W Olympic Blvd",
    "sg:city":"Los Angeles",
    "sg:classifiers":[
        {
            "category":"Health Services",
            "subcategory":"Health Practitioner",
            "type":"Services"
        }
    ],
    "sg:phone":"+1 213 251 9980",
    "sg:postcode":"90006",
    "sg:province":"CA",
    "sg:tags":[
        "medicine",
        "physician"
    ],
    "wof:name":"Young Sam Acupuncture",
    "wof:placetype":"venue"
},
  "geometry": {"coordinates":[-118.289464,34.052479],"type":"Point"}
}