{
  "type": "Feature",
  "properties": {
    "addr:full":"2580 Pioneer Ave Vista CA 92081",
    "addr:housenumber":"2580",
    "addr:postcode":"92081",
    "addr:street":"Pioneer Ave",
    "iso:country":"US",
    "sg:address":"2580 Pioneer Ave",
    "sg:city":"Vista",
    "sg:classifiers":[
        {
            "category":"Professional",
            "type":"Services"
        }
    ],
    "sg:phone":"+1 760 597 1606",
    "sg:postcode":"92081",
    "sg:province":"CA",
    "wof:name":"Prestige Fullfillment",
    "wof:placetype":"venue"
},
  "geometry": {"coordinates":[-117.222224,33.148522],"type":"Point"}
}