{
  "type": "Feature",
  "properties": {
    "addr:full":"4967 Rafton Dr San Jose CA 95124",
    "addr:housenumber":"4967",
    "addr:postcode":"95124",
    "addr:street":"Rafton Dr",
    "iso:country":"US",
    "sg:address":"4967 Rafton Dr",
    "sg:city":"San Jose",
    "sg:classifiers":[
        {
            "category":"Professional",
            "type":"Services"
        }
    ],
    "sg:phone":"+1 408 978 5664",
    "sg:postcode":"95124",
    "sg:province":"CA",
    "wof:name":"Designing Look",
    "wof:placetype":"venue"
},
  "geometry": {"coordinates":[-121.91136400000001,37.247657],"type":"Point"}
}