{
  "type": "Feature",
  "properties": {
    "iso:country":"US",
    "sg:address":"21886 Wilson Ct",
    "sg:city":"Cupertino",
    "sg:classifiers":[
        {
            "category":"Manufacturing",
            "subcategory":"Apparel",
            "type":"Manufacturing & Wholesale Goods"
        }
    ],
    "sg:phone":"+1 408 996 8020",
    "sg:postcode":"95014",
    "sg:province":"CA",
    "wof:name":"Distinctive Threads",
    "wof:placetype":"venue"
},
  "geometry": {"coordinates":[-122.057327,37.330663],"type":"Point"}
}