{
  "type": "Feature",
  "properties": {
    "iso:country":"US",
    "sg:address":"950 Folsom St",
    "sg:city":"San Francisco",
    "sg:classifiers":[
        {
            "category":"Retail",
            "subcategory":"Auto Repair",
            "type":"Services"
        }
    ],
    "sg:phone":"+1 415 357 9828",
    "sg:postcode":"94107",
    "sg:province":"CA",
    "sg:tags":[
        "body",
        "shop"
    ],
    "wof:name":"Bay Area Auto Body",
    "wof:placetype":"venue"
},
  "geometry": {"coordinates":[-122.404678,37.779455],"type":"Point"}
}