{
  "type": "Feature",
  "properties": {
    "addr:full":"631 S Olive Street Los Angeles CA 90014",
    "addr:housenumber":"631",
    "addr:postcode":"90014",
    "addr:street":"S Olive Street",
    "iso:country":"US",
    "sg:address":"631 S Olive Street",
    "sg:city":"Los Angeles",
    "sg:classifiers":[
        {
            "category":"Shopping",
            "subcategory":"Jewelry",
            "type":"Retail Goods"
        }
    ],
    "sg:phone":"+1 213 624 0043",
    "sg:postcode":"90014",
    "sg:province":"CA",
    "wof:name":"Farsi Jewelry Mfg Company",
    "wof:placetype":"venue"
},
  "geometry": {"coordinates":[-118.25456800000001,34.047634],"type":"Point"}
}