{
  "type": "Feature",
  "properties": {
    "iso:country":"US",
    "sfac:artist":"Martinez, Julian",
    "sfac:created_at":"01/01/1970 12:32:47 AM +0000",
    "sfac:credit_line":"Gift to San Francisco from Luis Encina, the Governor of the State of Sonora, Mexico 1967.",
    "sfac:display_dimensions":"88 in. x 142 in. x 70 in.",
    "sfac:location_description":"Public Display : District 7 : Sunset Circle parking Lot, Sunset and Lake Merced",
    "sfac:medium":"Bronze ",
    "sfac:revision":"2-ca9fc039e5bd8b73fccfd1edd8c5fe54",
    "sfac:title":"Juan Bautista de Anza",
    "wof:name":"Juan Bautista de Anza",
    "wof:placetype":"venue"
},
  "geometry": {"coordinates":[-122.4194155,37.7749295],"type":"Point"}
}