{
  "type": "Feature",
  "properties": {
    "addr:full":"3781 Cimarron St Los Angeles CA 90018",
    "addr:housenumber":"3781",
    "addr:postcode":"90018",
    "addr:street":"Cimarron St",
    "iso:country":"US",
    "sg:address":"3781 Cimarron St",
    "sg:city":"Los Angeles",
    "sg:classifiers":[
        {
            "category":"Professional",
            "subcategory":"Lawyer & Legal Services",
            "type":"Services"
        }
    ],
    "sg:phone":"+1 323 299 1664",
    "sg:postcode":"90018",
    "sg:province":"CA",
    "sg:tags":[
        "litigation"
    ],
    "wof:name":"Law Offices of Gabriel H Avina",
    "wof:placetype":"venue"
},
  "geometry": {"coordinates":[-118.31636,34.018133],"type":"Point"}
}