{
  "type": "Feature",
  "properties": {
    "iso:country":"US",
    "sg:address":"76 Whitney Pl",
    "sg:city":"Fremont",
    "sg:classifiers":[
        {
            "category":"Professional",
            "subcategory":"Computer Services",
            "type":"Services"
        }
    ],
    "sg:phone":"+1 510 661 0791",
    "sg:postcode":"94539",
    "sg:province":"CA",
    "sg:tags":[
        "electronics"
    ],
    "wof:name":"Genesys Testware",
    "wof:placetype":"venue"
},
  "geometry": {"coordinates":[-121.92033600000001,37.469407],"type":"Point"}
}