{
  "type": "Feature",
  "properties": {
    "addr:full":"432 N Mount Shasta Blvd Mount Shasta CA 96067",
    "addr:housenumber":"432",
    "addr:postcode":"96067",
    "addr:street":"N Mount Shasta Blvd",
    "iso:country":"US",
    "sg:address":"432 N Mount Shasta Blvd",
    "sg:city":"Mount Shasta",
    "sg:classifiers":[
        {
            "category":"Professional",
            "type":"Services"
        }
    ],
    "sg:phone":"+1 530 926 3614",
    "sg:postcode":"96067",
    "sg:province":"CA",
    "wof:name":"Leslie Curley",
    "wof:placetype":"venue"
},
  "geometry": {"coordinates":[-122.313525,41.314298],"type":"Point"}
}