{
  "type": "Feature",
  "properties": {
    "iso:country":"US",
    "sg:address":"401 Industrial Pl",
    "sg:city":"Palm Springs",
    "sg:classifiers":[
        {
            "category":"Home & Garden",
            "subcategory":"Household Appliances",
            "type":"Retail Goods"
        }
    ],
    "sg:phone":"+1 760 318 9707",
    "sg:postcode":"92264",
    "sg:province":"CA",
    "sg:tags":[
        "retailer"
    ],
    "wof:name":"Palm Springs Vacuum",
    "wof:placetype":"venue"
},
  "geometry": {"coordinates":[-116.541271,33.811471],"type":"Point"}
}