{
  "type": "Feature",
  "properties": {
    "addr:full":"101 Broadway Oakland CA 94607",
    "addr:housenumber":"101",
    "addr:postcode":"94607",
    "addr:street":"Broadway",
    "iso:country":"US",
    "sg:address":"101 Broadway",
    "sg:city":"Oakland",
    "sg:classifiers":[
        {
            "category":"Bars & Pubs",
            "subcategory":"Lounge",
            "type":"Food & Drink"
        },
        {
            "category":"Restaurant",
            "type":"Food & Drink"
        }
    ],
    "sg:phone":"+1 510 836 6600",
    "sg:postcode":"94607",
    "sg:province":"CA",
    "sg:tags":[
        "vietnamese"
    ],
    "sg:website":"silkroadlounge.net",
    "wof:name":"The Silk Road Lounge",
    "wof:placetype":"venue"
},
  "geometry": {"coordinates":[-122.277,37.795601],"type":"Point"}
}