{
  "type": "Feature",
  "properties": {
    "addr:full":"1315 N 10th St San Jose CA 95112",
    "addr:housenumber":"1315",
    "addr:postcode":"95112",
    "addr:street":"N 10Th St",
    "iso:country":"US",
    "sg:address":"1315 N 10th St",
    "sg:city":"San Jose",
    "sg:classifiers":[
        {
            "category":"Autos & Motor Vehicles",
            "subcategory":"Auto Supplies",
            "type":"Retail Goods"
        }
    ],
    "sg:phone":"+1 408 295 1742",
    "sg:postcode":"95112",
    "sg:province":"CA",
    "sg:tags":[
        "tire"
    ],
    "wof:name":"Bruce's Tire Inc",
    "wof:placetype":"venue"
},
  "geometry": {"coordinates":[-121.899002,37.363998],"type":"Point"}
}