{
  "type": "Feature",
  "properties": {
    "addr:full":"1111 Story Rd San Jose CA 95122",
    "addr:housenumber":"1111",
    "addr:postcode":"95122",
    "addr:street":"Story Rd",
    "iso:country":"US",
    "sg:address":"1111 Story Rd",
    "sg:city":"San Jose",
    "sg:classifiers":[
        {
            "category":"Juice Bar",
            "subcategory":"None",
            "type":"Food & Drink"
        }
    ],
    "sg:postcode":"95122",
    "sg:province":"CA",
    "sg:tags":[
        "smoothy"
    ],
    "wof:name":"Mak's Juice and Desserts",
    "wof:placetype":"venue"
},
  "geometry": {"coordinates":[-121.856486,37.332943],"type":"Point"}
}