{
  "type": "Feature",
  "properties": {
    "iso:country":"US",
    "sg:address":"8255 Alpine Ave",
    "sg:city":"Sacramento",
    "sg:classifiers":[
        {
            "category":"Home & Garden",
            "subcategory":"Building Materials",
            "type":"Retail Goods"
        },
        {
            "category":"Manufacturing",
            "subcategory":"Metals",
            "type":"Manufacturing & Wholesale Goods"
        }
    ],
    "sg:phone":"+1 916 739 6135",
    "sg:postcode":"95826",
    "sg:province":"CA",
    "sg:tags":[
        "windows",
        "door",
        "mfg"
    ],
    "wof:name":"Merzon Industries Inc",
    "wof:placetype":"venue"
},
  "geometry": {"coordinates":[-121.401841,38.53562],"type":"Point"}
}