{
  "type": "Feature",
  "properties": {
    "addr:full":"144 N Indian Hill Blvd Claremont CA 91711",
    "addr:housenumber":"144",
    "addr:postcode":"91711",
    "addr:street":"N Indian Hill Blvd",
    "iso:country":"US",
    "sg:address":"144 N Indian Hill Blvd",
    "sg:city":"Claremont",
    "sg:classifiers":[
        {
            "category":"Professional",
            "subcategory":"Lawyer & Legal Services",
            "type":"Services"
        }
    ],
    "sg:phone":"+1 909 625 4785",
    "sg:postcode":"91711",
    "sg:province":"CA",
    "sg:tags":[
        "attorney",
        "estate",
        "business",
        "corporation",
        "partnership",
        "tax",
        "planning",
        "law",
        "bankruptcy"
    ],
    "sg:website":"http://www.tsw-lawyers.com",
    "wof:name":"Taylor, Simonson, & Winter LLP",
    "wof:placetype":"venue"
},
  "geometry": {"coordinates":[-117.719307,34.095352],"type":"Point"}
}