{
  "type": "Feature",
  "properties": {
    "addr:full":"445 Ferry St San Pedro CA 90731",
    "addr:housenumber":"445",
    "addr:postcode":"90731",
    "addr:street":"Ferry St",
    "iso:country":"US",
    "sg:address":"445 Ferry St",
    "sg:city":"San Pedro",
    "sg:classifiers":[
        {
            "category":"Government",
            "subcategory":"Office",
            "type":"Public Place"
        }
    ],
    "sg:phone":"+1 310 548 7520",
    "sg:postcode":"90731",
    "sg:province":"CA",
    "sg:tags":[
        "village"
    ],
    "wof:name":"Treatment Plant",
    "wof:placetype":"venue"
},
  "geometry": {"coordinates":[-118.261224,33.745709],"type":"Point"}
}