{
  "type": "Feature",
  "properties": {
    "addr:full":"3826 San Pablo Dam Rd El Sobrante CA 94803",
    "addr:housenumber":"3826",
    "addr:postcode":"94803",
    "addr:street":"San Pablo Dam Rd",
    "iso:country":"US",
    "sg:address":"3826 San Pablo Dam Rd",
    "sg:city":"El Sobrante",
    "sg:classifiers":[
        {
            "category":"Shopping",
            "subcategory":"Bicycles & Sporting Goods",
            "type":"Retail Goods"
        }
    ],
    "sg:phone":"+1 510 222 3420",
    "sg:postcode":"94803",
    "sg:province":"CA",
    "sg:website":"www.theped.com",
    "wof:name":"Pedaler",
    "wof:placetype":"venue"
},
  "geometry": {"coordinates":[-122.312977,37.965114],"type":"Point"}
}