{
  "type": "Feature",
  "properties": {
    "addr:full":"895 Dove St Newport Beach CA 92660",
    "addr:housenumber":"895",
    "addr:postcode":"92660",
    "addr:street":"Dove St",
    "iso:country":"US",
    "sg:address":"895 Dove St",
    "sg:city":"Newport Beach",
    "sg:classifiers":[
        {
            "category":"Shopping",
            "subcategory":"Computers & Home Electronics",
            "type":"Retail Goods"
        }
    ],
    "sg:phone":"+1 949 955 4922",
    "sg:postcode":"92660",
    "sg:province":"CA",
    "sg:tags":[
        "parts",
        "supply"
    ],
    "sg:website":"www.teklogix.com",
    "wof:name":"Teklogix Corp",
    "wof:placetype":"venue"
},
  "geometry": {"coordinates":[-117.86588399999999,33.656919],"type":"Point"}
}