{
  "type": "Feature",
  "properties": {
    "addr:full":"4501 S Alameda St Los Angeles CA 90058",
    "addr:housenumber":"4501",
    "addr:postcode":"90058",
    "addr:street":"S Alameda St",
    "iso:country":"US",
    "sg:address":"4501 S Alameda St",
    "sg:city":"Los Angeles",
    "sg:classifiers":[
        {
            "category":"Food & Beverages",
            "subcategory":"Specialty",
            "type":"Retail Goods"
        }
    ],
    "sg:phone":"+1 323 846 1006",
    "sg:postcode":"90058",
    "sg:province":"CA",
    "sg:tags":[
        "herb"
    ],
    "wof:name":"Botanica Mexico",
    "wof:placetype":"venue"
},
  "geometry": {"coordinates":[-118.239013,34.001636],"type":"Point"}
}