{
  "type": "Feature",
  "properties": {
    "addr:full":"13011 5th St Chino CA 91710",
    "addr:housenumber":"13011",
    "addr:postcode":"91710",
    "addr:street":"5Th St",
    "iso:country":"US",
    "sg:address":"13011 5th St",
    "sg:city":"Chino",
    "sg:classifiers":[
        {
            "category":"Organizations",
            "subcategory":"Community Association",
            "type":"Services"
        }
    ],
    "sg:phone":"+1 909 591 5864",
    "sg:postcode":"91710",
    "sg:province":"CA",
    "sg:tags":[
        "club"
    ],
    "wof:name":"Chino Community Action Council Inc",
    "wof:placetype":"venue"
},
  "geometry": {"coordinates":[-117.69310400000001,34.017073],"type":"Point"}
}