{
  "type": "Feature",
  "properties": {
    "iso:country":"US",
    "sg:address":"1449 Mission St",
    "sg:city":"San Francisco",
    "sg:classifiers":[
        {
            "category":"Wholesale",
            "subcategory":"Home Furnishings",
            "type":"Manufacturing & Wholesale Goods"
        }
    ],
    "sg:phone":"+1 415 863 0377",
    "sg:postcode":"94103",
    "sg:province":"CA",
    "sg:tags":[
        "rug",
        "carpet"
    ],
    "sg:website":"www.hgertco.com",
    "wof:name":"Henry Gertmenian Co",
    "wof:placetype":"venue"
},
  "geometry": {"coordinates":[-122.416588,37.774736],"type":"Point"}
}