{
  "type": "Feature",
  "properties": {
    "addr:full":"9196 Carmel Valley Rd Carmel CA 93923",
    "addr:housenumber":"9196",
    "addr:postcode":"93923",
    "addr:street":"Carmel Valley Rd",
    "iso:country":"US",
    "sg:address":"9196 Carmel Valley Rd",
    "sg:city":"Carmel",
    "sg:classifiers":[
        {
            "category":"Wholesale",
            "subcategory":"Fruits & Vegetables",
            "type":"Manufacturing & Wholesale Goods"
        }
    ],
    "sg:phone":"+1 831 422 0911",
    "sg:postcode":"93923",
    "sg:province":"CA",
    "wof:name":"Tracy Willis Co",
    "wof:placetype":"venue"
},
  "geometry": {"coordinates":[-121.818336,36.528143],"type":"Point"}
}