{
  "type": "Feature",
  "properties": {
    "iso:country":"US",
    "sg:address":"16315 Piuma Ave",
    "sg:city":"Cerritos",
    "sg:classifiers":[
        {
            "category":"Shopping",
            "subcategory":"Computers & Home Electronics",
            "type":"Retail Goods"
        }
    ],
    "sg:phone":"+1 562 809 5918",
    "sg:postcode":"90703",
    "sg:province":"CA",
    "wof:name":"Schireson Bros Inc",
    "wof:placetype":"venue"
},
  "geometry": {"coordinates":[-118.104783,33.883364],"type":"Point"}
}