{
  "type": "Feature",
  "properties": {
    "addr:full":"4600 Adeline St Emeryville CA 94608",
    "addr:housenumber":"4600",
    "addr:postcode":"94608",
    "addr:street":"Adeline St",
    "iso:country":"US",
    "sg:address":"4600 Adeline St",
    "sg:city":"Emeryville",
    "sg:classifiers":[
        {
            "category":"Home & Garden",
            "subcategory":"Home Furnishings",
            "type":"Retail Goods"
        }
    ],
    "sg:phone":"+1 510 658 3533",
    "sg:postcode":"94608",
    "sg:province":"CA",
    "sg:tags":[
        "window",
        "covering"
    ],
    "wof:name":"Blue Sage",
    "wof:placetype":"venue"
},
  "geometry": {"coordinates":[-122.276549,37.836209],"type":"Point"}
}