{
  "type": "Feature",
  "properties": {
    "iso:country":"US",
    "sg:address":"321 S Hutchins St",
    "sg:city":"Lodi",
    "sg:classifiers":[
        {
            "category":"Restaurant",
            "type":"Food & Drink"
        }
    ],
    "sg:phone":"+1 209 369 9381",
    "sg:postcode":"95240",
    "sg:province":"CA",
    "sg:tags":[
        "shop",
        "coffee"
    ],
    "wof:name":"Java Stop",
    "wof:placetype":"venue"
},
  "geometry": {"coordinates":[-121.279187,38.129219],"type":"Point"}
}