{
  "type": "Feature",
  "properties": {
    "addr:full":"505 S Pastoria Avenue Sunnyvale CA 94086",
    "addr:housenumber":"505",
    "addr:postcode":"94086",
    "addr:street":"S Pastoria Avenue",
    "iso:country":"US",
    "sg:address":"505 S Pastoria Avenue",
    "sg:city":"Sunnyvale",
    "sg:classifiers":[
        {
            "category":"Personal",
            "subcategory":"Beauty Salon",
            "type":"Services"
        }
    ],
    "sg:phone":"+1 408 735 1522",
    "sg:postcode":"94086",
    "sg:province":"CA",
    "sg:tags":[
        "hair"
    ],
    "wof:name":"Hair Art Salon",
    "wof:placetype":"venue"
},
  "geometry": {"coordinates":[-122.040532,37.371117],"type":"Point"}
}