{
  "type": "Feature",
  "properties": {
    "addr:full":"825 Fee Ana St Placentia CA 92870",
    "addr:housenumber":"825",
    "addr:postcode":"ca 92870",
    "addr:street":"Fee Ana St",
    "iso:country":"US",
    "sg:address":"825 Fee Ana St",
    "sg:city":"Placentia",
    "sg:classifiers":[
        {
            "category":"Building & Trades",
            "subcategory":"Landscaping Services",
            "type":"Services"
        }
    ],
    "sg:phone":"+1 714 524 2218",
    "sg:postcode":"92870",
    "sg:province":"CA",
    "sg:tags":[
        "specializing",
        "residential",
        "contractor"
    ],
    "wof:name":"Environment Unlimited",
    "wof:placetype":"venue"
},
  "geometry": {"coordinates":[-117.82344000000001,33.864599],"type":"Point"}
}