{
  "type": "Feature",
  "properties": {
    "iso:country":"US",
    "sg:address":"6105 Miravale Ct",
    "sg:city":"Citrus Heights",
    "sg:classifiers":[
        {
            "category":"Freight",
            "type":"Transportation"
        }
    ],
    "sg:phone":"+1 916 729 5201",
    "sg:postcode":"95621",
    "sg:province":"CA",
    "sg:tags":[
        "local",
        "storage",
        "trucking"
    ],
    "wof:name":"H L Bearman and Associates",
    "wof:placetype":"venue"
},
  "geometry": {"coordinates":[-121.322135,38.701107],"type":"Point"}
}