{
  "type": "Feature",
  "properties": {
    "addr:full":"42263 50th St W Ste 622 Lancaster CA 93536",
    "addr:housenumber":"42263",
    "addr:postcode":"93536",
    "addr:street":"50Th St W Ste 622",
    "iso:country":"US",
    "sg:address":"42263 50th St W Ste 622",
    "sg:city":"Lancaster",
    "sg:classifiers":[
        {
            "category":"Banks & Credit Unions",
            "subcategory":"Financial Services",
            "type":"Services"
        }
    ],
    "sg:phone":"+1 888 525 6264",
    "sg:postcode":"93536",
    "sg:province":"CA",
    "sg:tags":[
        "mortgage"
    ],
    "wof:name":"Dream Home Loans",
    "wof:placetype":"venue"
},
  "geometry": {"coordinates":[-118.21854999999999,34.65039],"type":"Point"}
}