{
  "type": "Feature",
  "properties": {
    "iso:country":"US",
    "sg:address":"10062 Miller Ave",
    "sg:city":"Cupertino",
    "sg:classifiers":[
        {
            "category":"Professional",
            "type":"Services"
        }
    ],
    "sg:phone":"+1 408 973 9229",
    "sg:postcode":"95014",
    "sg:province":"CA",
    "wof:name":"Chua Moh",
    "wof:placetype":"venue"
},
  "geometry": {"coordinates":[-122.014025,37.322454],"type":"Point"}
}