{
  "type": "Feature",
  "properties": {
    "iso:country":"US",
    "sg:address":"9209 Swinton Ave",
    "sg:city":"Sepulveda",
    "sg:classifiers":[
        {
            "category":"Arts & Performance",
            "subcategory":"Theater",
            "type":"Entertainment"
        }
    ],
    "sg:phone":"+1 818 891 1222",
    "sg:postcode":"91343",
    "sg:province":"CA",
    "sg:tags":[
        "bureau"
    ],
    "wof:name":"Si Promotion & Marketing",
    "wof:placetype":"venue"
},
  "geometry": {"coordinates":[-118.48621199999999,34.237803],"type":"Point"}
}