{
  "type": "Feature",
  "properties": {
    "iso:country":"US",
    "sg:address":"16510 Jackson Oaks Dr",
    "sg:city":"Morgan Hill",
    "sg:classifiers":[
        {
            "category":"Home & Garden",
            "subcategory":"Building Materials",
            "type":"Retail Goods"
        }
    ],
    "sg:phone":"+1 408 778 0235",
    "sg:postcode":"95037",
    "sg:province":"CA",
    "wof:name":"Elegance Custom Stained Glass",
    "wof:placetype":"venue"
},
  "geometry": {"coordinates":[-121.588921,37.1404],"type":"Point"}
}