{
  "type": "Feature",
  "properties": {
    "iso:country":"US",
    "sg:address":"2500 82nd Ave",
    "sg:city":"Oakland",
    "sg:classifiers":[
        {
            "category":"Health Services",
            "subcategory":"Nursing And Care Facility",
            "type":"Services"
        }
    ],
    "sg:phone":"+1 510 562 6710",
    "sg:postcode":"94605",
    "sg:province":"CA",
    "wof:name":"Clark Boarding",
    "wof:placetype":"venue"
},
  "geometry": {"coordinates":[-122.164942,37.762685],"type":"Point"}
}