{
  "type": "Feature",
  "properties": {
    "addr:full":"2830 S Central Ave Los Angeles CA 90011",
    "addr:housenumber":"2830",
    "addr:postcode":"90011",
    "addr:street":"S Central Ave",
    "iso:country":"US",
    "sg:address":"2830 S Central Ave",
    "sg:city":"Los Angeles",
    "sg:classifiers":[
        {
            "category":"Social Services",
            "type":"Services"
        }
    ],
    "sg:phone":"+1 323 846 5689",
    "sg:postcode":"90011",
    "sg:province":"CA",
    "sg:tags":[
        "youth",
        "service/non-profit",
        "community",
        "center"
    ],
    "sg:website":"www.apch.org/",
    "wof:name":"A Place Called Home",
    "wof:placetype":"venue"
},
  "geometry": {"coordinates":[-118.25575000000001,34.015736],"type":"Point"}
}