{
  "type": "Feature",
  "properties": {
    "iso:country":"US",
    "sg:address":"1214 E Green St",
    "sg:city":"Pasadena",
    "sg:classifiers":[
        {
            "category":"Professional",
            "subcategory":"Business Services",
            "type":"Services"
        }
    ],
    "sg:phone":"+1 626 304 0900",
    "sg:postcode":"91105",
    "sg:province":"CA",
    "sg:tags":[
        "appraiser"
    ],
    "sg:website":"www.nancymartinappraisals.com",
    "wof:name":"Nancy A Martin",
    "wof:placetype":"venue"
},
  "geometry": {"coordinates":[-118.124986,34.144531],"type":"Point"}
}