{
  "type": "Feature",
  "properties": {
    "iso:country":"US",
    "sg:address":"1601 W Redondo Beach Blvd",
    "sg:city":"Gardena",
    "sg:classifiers":[
        {
            "category":"Health Services",
            "subcategory":"Medical Lab",
            "type":"Services"
        }
    ],
    "sg:phone":"+1 310 515 5343",
    "sg:postcode":"90247",
    "sg:province":"CA",
    "sg:tags":[
        "laboratory"
    ],
    "wof:name":"Ideal Dimisions",
    "wof:placetype":"venue"
},
  "geometry": {"coordinates":[-118.30615299999999,33.88948],"type":"Point"}
}