{
  "type": "Feature",
  "properties": {
    "iso:country":"US",
    "sg:address":"6083 N Marks Ave",
    "sg:city":"Fresno",
    "sg:classifiers":[
        {
            "category":"Retail",
            "subcategory":"Portrait Studio",
            "type":"Services"
        }
    ],
    "sg:phone":"+1 559 435 6250",
    "sg:postcode":"93711",
    "sg:province":"CA",
    "sg:tags":[
        "photographer"
    ],
    "wof:name":"Village Studio Of Photography",
    "wof:placetype":"venue"
},
  "geometry": {"coordinates":[-119.844401,36.825914],"type":"Point"}
}