{
  "type": "Feature",
  "properties": {
    "iso:country":"US",
    "sg:address":"2420 Vista Way Ste 210",
    "sg:city":"Oceanside",
    "sg:classifiers":[
        {
            "category":"Banks & Credit Unions",
            "subcategory":"Financial Services",
            "type":"Services"
        }
    ],
    "sg:phone":"+1 760 543 0201",
    "sg:postcode":"92054",
    "sg:province":"CA",
    "sg:tags":[
        "broker",
        "mortgage"
    ],
    "wof:name":"Providers Financial",
    "wof:placetype":"venue"
},
  "geometry": {"coordinates":[-117.335284,33.183367],"type":"Point"}
}