{
  "type": "Feature",
  "properties": {
    "iso:country":"US",
    "sg:address":"500 S Broadway",
    "sg:city":"Los Angeles",
    "sg:classifiers":[
        {
            "category":"Shopping",
            "subcategory":"Shoes",
            "type":"Retail Goods"
        }
    ],
    "sg:phone":"+1 213 892 8006",
    "sg:postcode":"90013",
    "sg:province":"CA",
    "wof:name":"Shoe Fantasy Inc",
    "wof:placetype":"venue"
},
  "geometry": {"coordinates":[-118.252032,34.046648],"type":"Point"}
}