{
  "type": "Feature",
  "properties": {
    "iso:country":"US",
    "sg:address":"32193 Road 160",
    "sg:city":"Ivanhoe",
    "sg:classifiers":[
        {
            "category":"Autos & Motor Vehicles",
            "subcategory":"Auto Supplies",
            "type":"Retail Goods"
        }
    ],
    "sg:phone":"+1 559 731 8369",
    "sg:postcode":"93235",
    "sg:province":"CA",
    "sg:tags":[
        "wheel"
    ],
    "wof:name":"Home Made Hot Wheels",
    "wof:placetype":"venue"
},
  "geometry": {"coordinates":[-119.21564499999999,36.374076],"type":"Point"}
}