{
  "type": "Feature",
  "properties": {
    "iso:country":"US",
    "sg:address":"12556 Jomani Dr",
    "sg:city":"Bakersfield",
    "sg:classifiers":[
        {
            "category":"Manufacturing",
            "subcategory":"Buildings",
            "type":"Manufacturing & Wholesale Goods"
        },
        {
            "category":"Home & Garden",
            "subcategory":"Building Materials",
            "type":"Retail Goods"
        },
        {
            "category":"Building & Trades",
            "subcategory":"Construction",
            "type":"Services"
        }
    ],
    "sg:phone":"+1 661 410 5268",
    "sg:postcode":"93312",
    "sg:province":"CA",
    "sg:tags":[
        "concrete",
        "builder",
        "staining",
        "contractor"
    ],
    "wof:name":"Clanton Construction Inc",
    "wof:placetype":"venue"
},
  "geometry": {"coordinates":[-119.141856,35.392252],"type":"Point"}
}