{
  "type": "Feature",
  "properties": {
    "iso:country":"US",
    "sg:address":"2550 Honolulu Ave Ste 208",
    "sg:city":"Montrose",
    "sg:classifiers":[
        {
            "category":"Building & Trades",
            "subcategory":"Electrical",
            "type":"Services"
        }
    ],
    "sg:phone":"+1 818 957 0770",
    "sg:postcode":"91020",
    "sg:province":"CA",
    "sg:tags":[
        "industrial",
        "electrician",
        "contractors-commercial",
        "electric"
    ],
    "wof:name":"Downs Electric Inc",
    "wof:placetype":"venue"
},
  "geometry": {"coordinates":[-118.234001,34.207901],"type":"Point"}
}