{
  "type": "Feature",
  "properties": {
    "iso:country":"US",
    "sg:address":"16550 Ventura Blvd",
    "sg:city":"Encino",
    "sg:classifiers":[
        {
            "category":"Health Services",
            "subcategory":"Doctor",
            "type":"Services"
        }
    ],
    "sg:phone":"+1 818 784 7784",
    "sg:postcode":"91436",
    "sg:province":"CA",
    "sg:tags":[
        "physician",
        "surgeon"
    ],
    "wof:name":"Encino Physicians Medical Grp",
    "wof:placetype":"venue"
},
  "geometry": {"coordinates":[-118.493365,34.157602],"type":"Point"}
}