{
  "type": "Feature",
  "properties": {
    "iso:country":"US",
    "sg:address":"4401 W Redondo Beach Blvd",
    "sg:city":"Torrance",
    "sg:classifiers":[
        {
            "category":"Shopping",
            "subcategory":"Computers & Home Electronics",
            "type":"Retail Goods"
        }
    ],
    "sg:phone":"+1 310 214 0081",
    "sg:postcode":"90501",
    "sg:province":"CA",
    "wof:name":"A-Video and Audio Center",
    "wof:placetype":"venue"
},
  "geometry": {"coordinates":[-118.31500200000001,33.827599],"type":"Point"}
}