{
  "type": "Feature",
  "properties": {
    "addr:full":"551 Nevada St San Francisco CA 94110",
    "addr:housenumber":"551",
    "addr:postcode":"94110",
    "addr:street":"Nevada St",
    "iso:country":"US",
    "sg:address":"551 Nevada St",
    "sg:city":"San Francisco",
    "sg:classifiers":[
        {
            "category":"Organizations",
            "subcategory":"Religious Organization",
            "type":"Services"
        }
    ],
    "sg:phone":"+1 415 824 9662",
    "sg:postcode":"94110",
    "sg:province":"CA",
    "sg:tags":[
        "church"
    ],
    "wof:name":"Good Hope Baptist Church",
    "wof:placetype":"venue"
},
  "geometry": {"coordinates":[-122.411709,37.735218],"type":"Point"}
}