{
  "type": "Feature",
  "properties": {
    "addr:full":"2511 Q St Rio Linda CA 95673",
    "addr:housenumber":"2511",
    "addr:postcode":"95673",
    "addr:street":"Q St",
    "iso:country":"US",
    "sg:address":"2511 Q St",
    "sg:city":"Rio Linda",
    "sg:classifiers":[
        {
            "category":"Building & Trades",
            "subcategory":"Construction",
            "type":"Services"
        }
    ],
    "sg:phone":"+1 916 991 9174",
    "sg:postcode":"95673",
    "sg:province":"CA",
    "sg:tags":[
        "plastering",
        "contractor"
    ],
    "wof:name":"Novi Plastering",
    "wof:placetype":"venue"
},
  "geometry": {"coordinates":[-121.40796400000001,38.697916],"type":"Point"}
}