{
  "type": "Feature",
  "properties": {
    "addr:full":"1604 Kentucky Way Rocklin CA 95765",
    "addr:housenumber":"1604",
    "addr:postcode":"95765",
    "addr:street":"Kentucky Way",
    "iso:country":"US",
    "sg:address":"1604 Kentucky Way",
    "sg:city":"Rocklin",
    "sg:classifiers":[
        {
            "category":"Shopping",
            "subcategory":"Clothing, Apparel, & Fashions",
            "type":"Retail Goods"
        }
    ],
    "sg:phone":"+1 916 435 1982",
    "sg:postcode":"95765",
    "sg:province":"CA",
    "sg:tags":[
        "clothing",
        "store"
    ],
    "wof:name":"Banana Tees Inc",
    "wof:placetype":"venue"
},
  "geometry": {"coordinates":[-121.26005600000001,38.809396],"type":"Point"}
}