{
  "type": "Feature",
  "properties": {
    "addr:full":"3621 Swallow Ct Castro Valley CA 94546",
    "addr:housenumber":"3621",
    "addr:postcode":"94546",
    "addr:street":"Swallow Ct",
    "iso:country":"US",
    "sg:address":"3621 Swallow Ct",
    "sg:city":"Castro Valley",
    "sg:classifiers":[
        {
            "category":"Social Services",
            "subcategory":"Child Care",
            "type":"Services"
        }
    ],
    "sg:phone":"+1 510 581 0641",
    "sg:postcode":"94546",
    "sg:province":"CA",
    "wof:name":"Creative Kids Daycare",
    "wof:placetype":"venue"
},
  "geometry": {"coordinates":[-122.08681900000001,37.708747],"type":"Point"}
}