{
  "type": "Feature",
  "properties": {
    "addr:full":"183 W Woodruff Ave Arcadia CA 91007",
    "addr:housenumber":"183",
    "addr:postcode":"91007",
    "addr:street":"W Woodruff Ave",
    "iso:country":"US",
    "sg:address":"183 W Woodruff Ave",
    "sg:city":"Arcadia",
    "sg:classifiers":[
        {
            "category":"Building & Trades",
            "subcategory":"Cleaning & Sanitation",
            "type":"Services"
        }
    ],
    "sg:phone":"+1 626 446 3176",
    "sg:postcode":"91007",
    "sg:province":"CA",
    "sg:tags":[
        "ventilating",
        "system"
    ],
    "wof:name":"DEV Industries Inc",
    "wof:placetype":"venue"
},
  "geometry": {"coordinates":[-118.03754499999999,34.10948],"type":"Point"}
}