{
  "type": "Feature",
  "properties": {
    "iso:country":"US",
    "sg:address":"31640 McCray Rd",
    "sg:city":"Cloverdale",
    "sg:classifiers":[
        {
            "category":"Building & Trades",
            "subcategory":"Landscaping Services",
            "type":"Services"
        }
    ],
    "sg:phone":"+1 707 894 5300",
    "sg:postcode":"95425",
    "sg:province":"CA",
    "wof:name":"Brookescapes",
    "wof:placetype":"venue"
},
  "geometry": {"coordinates":[-123.01451900000001,38.821823],"type":"Point"}
}