{
  "type": "Feature",
  "properties": {
    "addr:full":"5750 Redwood Rd Oakland CA 94619",
    "addr:housenumber":"5750",
    "addr:postcode":"94619",
    "addr:street":"Redwood Rd",
    "iso:country":"US",
    "sg:address":"5750 Redwood Rd",
    "sg:city":"Oakland",
    "sg:classifiers":[
        {
            "category":"Sports & Exercise",
            "subcategory":"Sports Center",
            "type":"Entertainment"
        }
    ],
    "sg:phone":"+1 510 336 0850",
    "sg:postcode":"94619",
    "sg:province":"CA",
    "sg:website":"http://www.skyline-ranch.com",
    "wof:name":"Skyline Ranch Equestrian Ctr",
    "wof:placetype":"venue"
},
  "geometry": {"coordinates":[-122.17012800000001,37.801102],"type":"Point"}
}