{
  "type": "Feature",
  "properties": {
    "iso:country":"US",
    "sg:address":"14543 Grinnell Ct",
    "sg:city":"Magalia",
    "sg:classifiers":[
        {
            "category":"Shopping",
            "subcategory":"Crafts & Fabrics",
            "type":"Retail Goods"
        }
    ],
    "sg:phone":"+1 530 873 2670",
    "sg:postcode":"95954",
    "sg:province":"CA",
    "sg:tags":[
        "material",
        "quilting",
        "supply"
    ],
    "wof:name":"Seams To B",
    "wof:placetype":"venue"
},
  "geometry": {"coordinates":[-121.615845,39.834358],"type":"Point"}
}