{
  "type": "Feature",
  "properties": {
    "iso:country":"US",
    "sg:address":"351 Hitchcock Way",
    "sg:city":"Santa Barbara",
    "sg:classifiers":[
        {
            "category":"Banks & Credit Unions",
            "subcategory":"Bank",
            "type":"Services"
        }
    ],
    "sg:phone":"+1 805 682 0951",
    "sg:postcode":"93105",
    "sg:province":"CA",
    "sg:tags":[
        "loan"
    ],
    "wof:name":"Atlantic American Acceptance",
    "wof:placetype":"venue"
},
  "geometry": {"coordinates":[-119.745845,34.434097],"type":"Point"}
}