{
  "type": "Feature",
  "properties": {
    "addr:full":"2040 17th St San Francisco CA 94103",
    "addr:housenumber":"2040",
    "addr:postcode":"94103",
    "addr:street":"17Th St",
    "iso:country":"US",
    "sg:address":"2040 17th St",
    "sg:city":"San Francisco",
    "sg:classifiers":[
        {
            "category":"Retail",
            "subcategory":"Auto Repair",
            "type":"Services"
        }
    ],
    "sg:phone":"+1 415 487 1210",
    "sg:postcode":"94103",
    "sg:province":"CA",
    "sg:tags":[
        "repairing",
        "automobile"
    ],
    "wof:name":"Action Auto Care",
    "wof:placetype":"venue"
},
  "geometry": {"coordinates":[-122.40412499999999,37.764917],"type":"Point"}
}