{
  "type": "Feature",
  "properties": {
    "iso:country":"US",
    "sg:address":"823 Camino Del Mar",
    "sg:city":"Del Mar",
    "sg:classifiers":[
        {
            "category":"Personal",
            "subcategory":"Massage",
            "type":"Services"
        },
        {
            "category":"Personal",
            "subcategory":"Day Spa",
            "type":"Services"
        },
        {
            "category":"Personal",
            "subcategory":"Skin Care",
            "type":"Services"
        }
    ],
    "sg:phone":"+1 858 755 5754",
    "sg:postcode":"92014",
    "sg:province":"CA",
    "sg:website":"renousdayspa.com",
    "wof:name":"Re-Nous Day Spa",
    "wof:placetype":"venue"
},
  "geometry": {"coordinates":[-117.262643,32.952784],"type":"Point"}
}