{
  "type": "Feature",
  "properties": {
    "iso:country":"US",
    "sg:address":"5960 S Hoover St",
    "sg:city":"Los Angeles",
    "sg:classifiers":[
        {
            "category":"Shopping",
            "subcategory":"Clothing, Apparel, & Fashions",
            "type":"Retail Goods"
        }
    ],
    "sg:phone":"+1 323 781 2997",
    "sg:postcode":"90044",
    "sg:province":"CA",
    "wof:name":"L A Clothing",
    "wof:placetype":"venue"
},
  "geometry": {"coordinates":[-118.286948,33.985621],"type":"Point"}
}