{
  "type": "Feature",
  "properties": {
    "iso:country":"US",
    "sg:address":"9841 Irvine Center Dr",
    "sg:city":"Irvine",
    "sg:classifiers":[
        {
            "category":"Health Services",
            "subcategory":"Health Practitioner",
            "type":"Services"
        }
    ],
    "sg:phone":"+1 949 861 8901",
    "sg:postcode":"92618",
    "sg:province":"CA",
    "sg:tags":[
        "acupuncture"
    ],
    "sg:website":"www.orangecountyacupuncture.com",
    "wof:name":"OC Acupuncture - Kathleen Albertson LAC PHD",
    "wof:placetype":"venue"
},
  "geometry": {"coordinates":[-117.729213,33.631486],"type":"Point"}
}