{
  "type": "Feature",
  "properties": {
    "iso:country":"US",
    "sg:address":"446 Old Newport Boulevard",
    "sg:city":"Newport Beach",
    "sg:classifiers":[
        {
            "category":"Health Services",
            "subcategory":"Doctor",
            "type":"Services"
        }
    ],
    "sg:phone":"+1 949 645 3223",
    "sg:postcode":"92663",
    "sg:province":"CA",
    "wof:name":"Kelley Timothy F MD",
    "wof:placetype":"venue"
},
  "geometry": {"coordinates":[-117.92615000000001,33.627019],"type":"Point"}
}