{
  "type": "Feature",
  "properties": {
    "iso:country":"US",
    "sg:address":"404 W 7th Street Suite 1001",
    "sg:city":"Los Angeles",
    "sg:classifiers":[
        {
            "category":"Shopping",
            "subcategory":"Jewelry",
            "type":"Retail Goods"
        }
    ],
    "sg:phone":"+1 213 622 5653",
    "sg:postcode":"90014",
    "sg:province":"CA",
    "wof:name":"M G Jewelry",
    "wof:placetype":"venue"
},
  "geometry": {"coordinates":[-118.2545,34.045934],"type":"Point"}
}