{
  "type": "Feature",
  "properties": {
    "addr:full":"3204 N Highland Ave Manhattan Beach CA 90266",
    "addr:housenumber":"3204",
    "addr:postcode":"90266",
    "addr:street":"N Highland Ave",
    "iso:country":"US",
    "sg:address":"3204 N Highland Ave",
    "sg:city":"Manhattan Beach",
    "sg:classifiers":[
        {
            "category":"Professional",
            "type":"Services"
        }
    ],
    "sg:phone":"+1 310 545 2735",
    "sg:postcode":"90266",
    "sg:province":"CA",
    "sg:tags":[
        "establishment"
    ],
    "wof:name":"Paris Notes Newsletter",
    "wof:placetype":"venue"
},
  "geometry": {"coordinates":[-118.416461,33.898042],"type":"Point"}
}