{
  "type": "Feature",
  "properties": {
    "iso:country":"US",
    "sg:address":"1510 Florida Ave",
    "sg:city":"Modesto",
    "sg:classifiers":[
        {
            "category":"Health Services",
            "subcategory":"Doctor",
            "type":"Services"
        }
    ],
    "sg:phone":"+1 209 574 1378",
    "sg:postcode":"95350",
    "sg:province":"CA",
    "sg:tags":[
        "obstetrician",
        "gynecologist"
    ],
    "wof:name":"Stallone William MD",
    "wof:placetype":"venue"
},
  "geometry": {"coordinates":[-120.996002,37.665699],"type":"Point"}
}