{
  "type": "Feature",
  "properties": {
    "addr:full":"34930 Judy Ln Cathedral City CA 92234",
    "addr:postcode":"34930;92234",
    "addr:street":"Judy Ln",
    "iso:country":"US",
    "sg:address":"34930 Judy Ln",
    "sg:city":"Cathedral City",
    "sg:classifiers":[
        {
            "category":"Building & Trades",
            "subcategory":"Landscaping Services",
            "type":"Services"
        }
    ],
    "sg:phone":"+1 760 328 1523",
    "sg:postcode":"92234",
    "sg:province":"CA",
    "wof:name":"Junior Gardening",
    "wof:placetype":"venue"
},
  "geometry": {"coordinates":[-116.45255,33.797576],"type":"Point"}
}