{
  "type": "Feature",
  "properties": {
    "iso:country":"US",
    "sg:address":"117 W 9th St",
    "sg:city":"Los Angeles",
    "sg:classifiers":[
        {
            "category":"Manufacturing",
            "subcategory":"Apparel",
            "type":"Manufacturing & Wholesale Goods"
        }
    ],
    "sg:phone":"+1 213 488 9484",
    "sg:postcode":"90015",
    "sg:province":"CA",
    "sg:tags":[
        "mfg",
        "junior",
        "size"
    ],
    "wof:name":"Wizdumb Clothing",
    "wof:placetype":"venue"
},
  "geometry": {"coordinates":[-118.255214,34.041843],"type":"Point"}
}