{
  "type": "Feature",
  "properties": {
    "addr:full":"7554 Central Ave Lemon Grove CA 91945",
    "addr:housenumber":"7554",
    "addr:postcode":"91945",
    "addr:street":"Central Ave",
    "iso:country":"US",
    "sg:address":"7554 Central Ave",
    "sg:city":"Lemon Grove",
    "sg:classifiers":[
        {
            "category":"Building & Trades",
            "subcategory":"Construction",
            "type":"Services"
        }
    ],
    "sg:phone":"+1 619 644 0810",
    "sg:postcode":"91945",
    "sg:province":"CA",
    "sg:tags":[
        "plastering",
        "contractor"
    ],
    "wof:name":"S & S Plastering",
    "wof:placetype":"venue"
},
  "geometry": {"coordinates":[-117.035369,32.739013],"type":"Point"}
}