{
  "type": "Feature",
  "properties": {
    "addr:full":"3173 W Shaw Ave Fresno CA 93711",
    "addr:housenumber":"3173",
    "addr:postcode":"93711",
    "addr:street":"W Shaw Ave",
    "iso:country":"US",
    "sg:address":"3173 W Shaw Ave",
    "sg:city":"Fresno",
    "sg:classifiers":[
        {
            "category":"Professional",
            "subcategory":"Management & Consulting",
            "type":"Services"
        }
    ],
    "sg:phone":"+1 559 229 6130",
    "sg:postcode":"93711",
    "sg:province":"CA",
    "sg:tags":[
        "consultant",
        "lighting"
    ],
    "wof:name":"Enlight Co",
    "wof:placetype":"venue"
},
  "geometry": {"coordinates":[-119.84513800000001,36.808209],"type":"Point"}
}