{
  "type": "Feature",
  "properties": {
    "iso:country":"US",
    "sg:address":"715 N Arrowhead Ave",
    "sg:city":"San Bernardino",
    "sg:classifiers":[
        {
            "category":"Professional",
            "subcategory":"Lawyer & Legal Services",
            "type":"Services"
        }
    ],
    "sg:phone":"+1 909 884 8615",
    "sg:postcode":"92401",
    "sg:province":"CA",
    "sg:tags":[
        "attorney"
    ],
    "wof:name":"Inland Counties Legal Svc",
    "wof:placetype":"venue"
},
  "geometry": {"coordinates":[-117.289604,34.113678],"type":"Point"}
}