{
  "type": "Feature",
  "properties": {
    "addr:full":"3636 Castro Valley Blvd Castro Valley CA 94546",
    "addr:housenumber":"3636",
    "addr:postcode":"94546",
    "addr:street":"Castro Valley Blvd",
    "iso:country":"US",
    "sg:address":"3636 Castro Valley Blvd",
    "sg:city":"Castro Valley",
    "sg:classifiers":[
        {
            "category":"Personal",
            "subcategory":"Nail Salon",
            "type":"Services"
        }
    ],
    "sg:phone":"+1 510 538 4797",
    "sg:postcode":"94546",
    "sg:province":"CA",
    "wof:name":"Style Co the-Teri Keith",
    "wof:placetype":"venue"
},
  "geometry": {"coordinates":[-122.07199900000001,37.695202],"type":"Point"}
}