{
  "type": "Feature",
  "properties": {
    "addr:full":"2395 Glendale Blvd Unit C Los Angeles CA 90039",
    "addr:housenumber":"2395",
    "addr:postcode":"90039",
    "addr:street":"Glendale Blvd Unit C",
    "iso:country":"US",
    "sg:address":"2395 Glendale Blvd Unit C",
    "sg:city":"Los Angeles",
    "sg:classifiers":[
        {
            "category":"Shopping",
            "subcategory":"Clothing, Apparel, & Fashions",
            "type":"Retail Goods"
        },
        {
            "category":"Shopping",
            "subcategory":"Hobbies, Toys, & Games",
            "type":"Retail Goods"
        }
    ],
    "sg:phone":"+1 323 667 0344",
    "sg:postcode":"90039",
    "sg:province":"CA",
    "sg:tags":[
        "children's",
        "toy",
        "clothing",
        "store"
    ],
    "sg:website":"www.juvieshop.com",
    "wof:name":"Juvie",
    "wof:placetype":"venue"
},
  "geometry": {"coordinates":[-118.25923,34.100001],"type":"Point"}
}