{
  "type": "Feature",
  "properties": {
    "addr:full":"2900 W Broadway Los Angeles CA 90041",
    "addr:housenumber":"2900",
    "addr:postcode":"90041",
    "addr:street":"W Broadway",
    "iso:country":"US",
    "sg:address":"2900 W Broadway",
    "sg:city":"Los Angeles",
    "sg:classifiers":[
        {
            "category":"Insurance",
            "subcategory":"Hazard Insurance",
            "type":"Services"
        }
    ],
    "sg:phone":"+1 323 550 7900",
    "sg:postcode":"90041",
    "sg:province":"CA",
    "sg:website":"www.arroyoins.com",
    "wof:name":"Arroyo Insurance",
    "wof:placetype":"venue"
},
  "geometry": {"coordinates":[-118.22760100000001,34.144782],"type":"Point"}
}