{
  "type": "Feature",
  "properties": {
    "iso:country":"US",
    "sg:address":"2900 W Broadway",
    "sg:city":"Los Angeles",
    "sg:classifiers":[
        {
            "category":"Insurance",
            "subcategory":"Hazard Insurance",
            "type":"Services"
        }
    ],
    "sg:phone":"+1 323 550 7900",
    "sg:postcode":"90041",
    "sg:province":"CA",
    "sg:website":"www.arroyoins.com",
    "wof:name":"Arroyo Insurance",
    "wof:placetype":"venue"
},
  "geometry": {"coordinates":[-118.227601,34.144782],"type":"Point"}
}