{
  "type": "Feature",
  "properties": {
    "addr:full":"280 Spreckels Ave Manteca CA 95336",
    "addr:housenumber":"280",
    "addr:postcode":"95336",
    "addr:street":"Spreckels Ave",
    "iso:country":"US",
    "sg:address":"280 Spreckels Ave",
    "sg:city":"Manteca",
    "sg:phone":"+1 704 540 2042",
    "sg:postcode":"95336",
    "sg:province":"CA",
    "wof:name":"Citysearch.com",
    "wof:placetype":"venue"
},
  "geometry": {"coordinates":[-121.197884,37.794547],"type":"Point"}
}