{
  "type": "Feature",
  "properties": {
    "iso:country":"US",
    "sg:address":"12329 N Armstrong Ave",
    "sg:city":"Clovis",
    "sg:classifiers":[
        {
            "category":"Restaurant",
            "type":"Food & Drink"
        }
    ],
    "sg:phone":"+1 559 298 4684",
    "sg:postcode":"93619",
    "sg:province":"CA",
    "wof:name":"The Soda Jerk Works",
    "wof:placetype":"venue"
},
  "geometry": {"coordinates":[-119.676942,36.910486],"type":"Point"}
}