{
  "type": "Feature",
  "properties": {
    "iso:country":"US",
    "sg:address":"2426 N Euclid Ave",
    "sg:city":"Upland",
    "sg:classifiers":[
        {
            "category":"Organizations",
            "subcategory":"Religious Organization",
            "type":"Services"
        }
    ],
    "sg:phone":"+1 909 981 4848",
    "sg:postcode":"91784",
    "sg:province":"CA",
    "sg:tags":[
        "church"
    ],
    "sg:website":"www.lbfchurch.com",
    "wof:name":"Life Bible Fellowship",
    "wof:placetype":"venue"
},
  "geometry": {"coordinates":[-117.651888,34.152107],"type":"Point"}
}