{
  "type": "Feature",
  "properties": {
    "addr:full":"5253 Riverside Dr Chino CA 91710",
    "addr:housenumber":"5253",
    "addr:postcode":"91710",
    "addr:street":"Riverside Dr",
    "iso:country":"US",
    "sg:address":"5253 Riverside Dr",
    "sg:city":"Chino",
    "sg:classifiers":[
        {
            "category":"Health Services",
            "subcategory":"Doctor",
            "type":"Services"
        }
    ],
    "sg:phone":"+1 909 464 2845",
    "sg:postcode":"91710",
    "sg:province":"CA",
    "sg:tags":[
        "physician",
        "surgeon"
    ],
    "wof:name":"Lisa Stockford DO",
    "wof:placetype":"venue"
},
  "geometry": {"coordinates":[-117.68951199999999,34.01901],"type":"Point"}
}