{
  "type": "Feature",
  "properties": {
    "iso:country":"US",
    "sg:address":"223 Puffin Ct",
    "sg:city":"Foster City",
    "sg:classifiers":[
        {
            "category":"Building & Trades",
            "subcategory":"Construction",
            "type":"Services"
        }
    ],
    "sg:phone":"+1 650 345 8828",
    "sg:postcode":"94404",
    "sg:province":"CA",
    "sg:tags":[
        "tile",
        "dealer"
    ],
    "wof:name":"Northern California Constr",
    "wof:placetype":"venue"
},
  "geometry": {"coordinates":[-122.259629,37.570212],"type":"Point"}
}