{
  "type": "Feature",
  "properties": {
    "iso:country":"US",
    "sg:address":"23846 Sunnymead Blvd",
    "sg:city":"Moreno Valley",
    "sg:classifiers":[
        {
            "category":"Real Estate",
            "subcategory":"Real Estate Agent",
            "type":"Services"
        }
    ],
    "sg:phone":"+1 951 924 4315",
    "sg:postcode":"92553",
    "sg:province":"CA",
    "sg:tags":[
        "management"
    ],
    "wof:name":"Management One",
    "wof:placetype":"venue"
},
  "geometry": {"coordinates":[-117.247363,33.939105],"type":"Point"}
}