{
  "type": "Feature",
  "properties": {
    "iso:country":"US",
    "sg:address":"630 N 13th Ave",
    "sg:city":"Upland",
    "sg:classifiers":[
        {
            "category":"Health Services",
            "subcategory":"Doctor",
            "type":"Services"
        }
    ],
    "sg:phone":"+1 909 985 7257",
    "sg:postcode":"91786",
    "sg:province":"CA",
    "sg:tags":[
        "physician",
        "pediatrics",
        "family",
        "practice",
        "surgeons",
        "medicine",
        "surgeon"
    ],
    "wof:name":"Perez, Glenn M, Md - Perez & Perez",
    "wof:placetype":"venue"
},
  "geometry": {"coordinates":[-117.63357499999999,34.100801],"type":"Point"}
}