{
  "type": "Feature",
  "properties": {
    "iso:country":"US",
    "sg:address":"2 McLaren Suite H",
    "sg:city":"Irvine",
    "sg:classifiers":[
        {
            "category":"Retail",
            "subcategory":"Auto Repair",
            "type":"Services"
        }
    ],
    "sg:phone":"+1 949 916 9411",
    "sg:postcode":"92618",
    "sg:province":"CA",
    "sg:tags":[
        "detailing"
    ],
    "sg:website":"www.Detailing.com",
    "wof:name":"Detailing.com",
    "wof:placetype":"venue"
},
  "geometry": {"coordinates":[-117.718828,33.63388],"type":"Point"}
}