{
  "type": "Feature",
  "properties": {
    "addr:full":"1180 Patricia Ave Simi Valley CA 93065",
    "addr:housenumber":"1180",
    "addr:postcode":"93065",
    "addr:street":"Patricia Ave",
    "iso:country":"US",
    "sg:address":"1180 Patricia Ave",
    "sg:city":"Simi Valley",
    "sg:classifiers":[
        {
            "category":"Organizations",
            "subcategory":"Religious Organization",
            "type":"Services"
        }
    ],
    "sg:phone":"+1 805 527 0199",
    "sg:postcode":"93065",
    "sg:province":"CA",
    "sg:tags":[
        "church"
    ],
    "wof:name":"Calvary Chapel Of Simi Valley",
    "wof:placetype":"venue"
},
  "geometry": {"coordinates":[-118.775751,34.270654],"type":"Point"}
}