{
  "type": "Feature",
  "properties": {
    "iso:country":"US",
    "sg:address":"3111 N Main St",
    "sg:city":"Walnut Creek",
    "sg:classifiers":[
        {
            "category":"Retail",
            "subcategory":"Funeral Services",
            "type":"Services"
        }
    ],
    "sg:phone":"+1 925 934 6500",
    "sg:postcode":"94597",
    "sg:province":"CA",
    "sg:tags":[
        "director"
    ],
    "wof:name":"Oak Park Hills Chapel",
    "wof:placetype":"venue"
},
  "geometry": {"coordinates":[-122.06084,37.931585],"type":"Point"}
}