{
  "type": "Feature",
  "properties": {
    "iso:country":"US",
    "sg:address":"1880 Bird St",
    "sg:city":"Oroville",
    "sg:classifiers":[
        {
            "category":"Shopping",
            "subcategory":"Jewelry",
            "type":"Retail Goods"
        }
    ],
    "sg:phone":"+1 530 533 0153",
    "sg:postcode":"95965",
    "sg:province":"CA",
    "sg:tags":[
        "jeweler"
    ],
    "wof:name":"Crown Jewelry Co",
    "wof:placetype":"venue"
},
  "geometry": {"coordinates":[-121.557003,39.512594],"type":"Point"}
}