{
  "type": "Feature",
  "properties": {
    "iso:country":"US",
    "sg:address":"1120 Bay Blvd Ste C",
    "sg:city":"Chula Vista",
    "sg:classifiers":[
        {
            "category":"Home & Garden",
            "subcategory":"Hardware",
            "type":"Retail Goods"
        }
    ],
    "sg:phone":"+1 619 691 6901",
    "sg:postcode":"91911",
    "sg:province":"CA",
    "sg:tags":[
        "store"
    ],
    "wof:name":"Hardex",
    "wof:placetype":"venue"
},
  "geometry": {"coordinates":[-117.22673399999999,32.6092],"type":"Point"}
}