{
  "type": "Feature",
  "properties": {
    "iso:country":"US",
    "sg:address":"1601 New Stine Rd",
    "sg:city":"Bakersfield",
    "sg:classifiers":[
        {
            "category":"Real Estate",
            "subcategory":"Real Estate Agent",
            "type":"Services"
        }
    ],
    "sg:phone":"+1 661 837 8100",
    "sg:postcode":"93309",
    "sg:province":"CA",
    "wof:name":"South Bay Realty",
    "wof:placetype":"venue"
},
  "geometry": {"coordinates":[-119.061208,35.341044],"type":"Point"}
}