{
  "type": "Feature",
  "properties": {
    "addr:full":"14212 Oxnard St Van Nuys CA 91401",
    "addr:housenumber":"14212",
    "addr:postcode":"91401",
    "addr:street":"Oxnard St",
    "iso:country":"US",
    "sg:address":"14212 Oxnard St",
    "sg:city":"Van Nuys",
    "sg:classifiers":[
        {
            "category":"Retail",
            "subcategory":"Auto Repair",
            "type":"Services"
        }
    ],
    "sg:phone":"+1 818 988 3883",
    "sg:postcode":"91401",
    "sg:province":"CA",
    "sg:tags":[
        "repairing",
        "automobile"
    ],
    "wof:name":"California Muscle Cars",
    "wof:placetype":"venue"
},
  "geometry": {"coordinates":[-118.444123,34.179318],"type":"Point"}
}