{
  "type": "Feature",
  "properties": {
    "iso:country":"US",
    "sg:address":"17915 Sky Park Cir Ste A",
    "sg:city":"Irvine",
    "sg:classifiers":[
        {
            "category":"Retail",
            "subcategory":"Laundry & Dry Cleaning",
            "type":"Services"
        },
        {
            "category":"Building & Trades",
            "subcategory":"Cleaning & Sanitation",
            "type":"Services"
        }
    ],
    "sg:phone":"+1 949 724 8155",
    "sg:postcode":"92614",
    "sg:province":"CA",
    "sg:tags":[
        "cleaner",
        "rug",
        "carpet"
    ],
    "wof:name":"Fiber Seal",
    "wof:placetype":"venue"
},
  "geometry": {"coordinates":[-117.86068899999999,33.690882],"type":"Point"}
}