{
  "type": "Feature",
  "properties": {
    "addr:full":"501 E Hardy Street Inglewood CA 90301",
    "addr:housenumber":"501",
    "addr:postcode":"90301",
    "addr:street":"E Hardy Street",
    "iso:country":"US",
    "sg:address":"501 E Hardy Street",
    "sg:city":"Inglewood",
    "sg:classifiers":[
        {
            "category":"Health Services",
            "subcategory":"Doctor",
            "type":"Services"
        }
    ],
    "sg:phone":"+1 310 673 4900",
    "sg:postcode":"90301",
    "sg:province":"CA",
    "wof:name":"Smith Craig M MD",
    "wof:placetype":"venue"
},
  "geometry": {"coordinates":[-118.349175,33.949108],"type":"Point"}
}