{
  "type": "Feature",
  "properties": {
    "iso:country":"US",
    "sg:address":"5600 Linden Ave",
    "sg:city":"Long Beach",
    "sg:classifiers":[
        {
            "category":"Organizations",
            "subcategory":"Religious Organization",
            "type":"Services"
        }
    ],
    "sg:phone":"+1 562 422 1635",
    "sg:postcode":"90805",
    "sg:province":"CA",
    "sg:tags":[
        "church"
    ],
    "wof:name":"North Long Beach United Meth",
    "wof:placetype":"venue"
},
  "geometry": {"coordinates":[-118.185968,33.858409],"type":"Point"}
}