{
  "type": "Feature",
  "properties": {
    "iso:country":"US",
    "sg:address":"1493 Balhan Dr",
    "sg:city":"Concord",
    "sg:classifiers":[
        {
            "category":"Building & Trades",
            "subcategory":"Plumbing",
            "type":"Services"
        }
    ],
    "sg:phone":"+1 408 616 8935",
    "sg:postcode":"94521",
    "sg:province":"CA",
    "sg:tags":[
        "conditioning",
        "air",
        "system",
        "contractor"
    ],
    "wof:name":"Plus Services",
    "wof:placetype":"venue"
},
  "geometry": {"coordinates":[-121.9627,37.953336],"type":"Point"}
}