{
  "type": "Feature",
  "properties": {
    "iso:country":"US",
    "sg:address":"1188 Franklin St",
    "sg:city":"San Francisco",
    "sg:classifiers":[
        {
            "category":"Building & Trades",
            "subcategory":"Cleaning & Sanitation",
            "type":"Services"
        }
    ],
    "sg:phone":"+1 415 563 1425",
    "sg:postcode":"94109",
    "sg:province":"CA",
    "sg:tags":[
        "janitor"
    ],
    "wof:name":"R J Sam Co",
    "wof:placetype":"venue"
},
  "geometry": {"coordinates":[-122.422895,37.785123],"type":"Point"}
}