{
  "type": "Feature",
  "properties": {
    "iso:country":"US",
    "sg:address":"2300 Fletcher Dr",
    "sg:city":"Los Angeles",
    "sg:classifiers":[
        {
            "category":"Restaurant",
            "type":"Food & Drink"
        }
    ],
    "sg:phone":"+1 323 663 9241",
    "sg:postcode":"90039",
    "sg:province":"CA",
    "sg:tags":[
        "traditional",
        "american",
        "diner"
    ],
    "sg:website":"www.astrofamilyrestaurant.com",
    "wof:name":"Astro Family Restaurant",
    "wof:placetype":"venue"
},
  "geometry": {"coordinates":[-118.25900300000001,34.104599],"type":"Point"}
}