{
  "type": "Feature",
  "properties": {
    "addr:full":"110 Admiral Callaghan Ln Vallejo CA 94591",
    "addr:housenumber":"110",
    "addr:postcode":"94591",
    "addr:street":"Admiral Callaghan Ln",
    "iso:country":"US",
    "sg:address":"110 Admiral Callaghan Ln",
    "sg:city":"Vallejo",
    "sg:classifiers":[
        {
            "category":"Personal",
            "subcategory":"Beauty Salon",
            "type":"Services"
        }
    ],
    "sg:phone":"+1 707 334 1969",
    "sg:postcode":"94591",
    "sg:province":"CA",
    "sg:tags":[
        "treatment",
        "skin"
    ],
    "wof:name":"Touch Of Elegance",
    "wof:placetype":"venue"
},
  "geometry": {"coordinates":[-122.229472,38.114867],"type":"Point"}
}