{
  "type": "Feature",
  "properties": {
    "iso:country":"US",
    "sg:address":"8691 Echo Dr",
    "sg:city":"La Mesa",
    "sg:classifiers":[
        {
            "category":"Organizations",
            "subcategory":"Religious Organization",
            "type":"Services"
        }
    ],
    "sg:phone":"+1 619 462 5929",
    "sg:postcode":"91941",
    "sg:province":"CA",
    "sg:tags":[
        "church"
    ],
    "wof:name":"Eglesia De Cristo Mllf Inc",
    "wof:placetype":"venue"
},
  "geometry": {"coordinates":[-117.008422,32.756587],"type":"Point"}
}