{
  "type": "Feature",
  "properties": {
    "addr:full":"1122 Main St Fortuna CA 95540",
    "addr:housenumber":"1122",
    "addr:postcode":"95540",
    "addr:street":"Main St",
    "iso:country":"US",
    "sg:address":"1122 Main St",
    "sg:city":"Fortuna",
    "sg:classifiers":[
        {
            "category":"Shopping",
            "subcategory":"Used Merchandise",
            "type":"Retail Goods"
        }
    ],
    "sg:phone":"+1 707 725 5503",
    "sg:postcode":"95540",
    "sg:province":"CA",
    "sg:tags":[
        "antique"
    ],
    "wof:name":"Antique Depot",
    "wof:placetype":"venue"
},
  "geometry": {"coordinates":[-124.155351,40.598076],"type":"Point"}
}