{
  "type": "Feature",
  "properties": {
    "addr:full":"1739 N Case St Orange CA 92865",
    "addr:housenumber":"1739",
    "addr:postcode":"92865",
    "addr:street":"N Case St",
    "iso:country":"US",
    "sg:address":"1739 N Case St",
    "sg:city":"Orange",
    "sg:classifiers":[
        {
            "category":"Home & Garden",
            "subcategory":"Home Furnishings",
            "type":"Retail Goods"
        }
    ],
    "sg:phone":"+1 714 998 8997",
    "sg:postcode":"92865",
    "sg:province":"CA",
    "sg:tags":[
        "bath",
        "kitchen"
    ],
    "sg:website":"www.qualitycountertops.com",
    "wof:name":"Quality Countertops Inc",
    "wof:placetype":"venue"
},
  "geometry": {"coordinates":[-117.85862299999999,33.816315],"type":"Point"}
}