{
  "type": "Feature",
  "properties": {
    "addr:full":"76 E Main St Heber CA 92249",
    "addr:housenumber":"76",
    "addr:postcode":"92249",
    "addr:street":"E Main St",
    "iso:country":"US",
    "sg:address":"76 E Main St",
    "sg:city":"Heber",
    "sg:classifiers":[
        {
            "category":"Professional",
            "subcategory":"Management & Consulting",
            "type":"Services"
        }
    ],
    "sg:phone":"+1 760 352 3227",
    "sg:postcode":"92249",
    "sg:province":"CA",
    "sg:tags":[
        "consultant",
        "safety"
    ],
    "wof:name":"Ruiz & Assoc",
    "wof:placetype":"venue"
},
  "geometry": {"coordinates":[-115.526071,32.73078],"type":"Point"}
}