{
  "type": "Feature",
  "properties": {
    "iso:country":"US",
    "sg:address":"455 de Guigne Dr",
    "sg:city":"Sunnyvale",
    "sg:classifiers":[
        {
            "category":"Building & Trades",
            "subcategory":"Construction",
            "type":"Services"
        }
    ],
    "sg:phone":"+1 408 735 9500",
    "sg:postcode":"94086",
    "sg:province":"CA",
    "sg:tags":[
        "dry wall",
        "contractor"
    ],
    "wof:name":"K & C Drywall Inc",
    "wof:placetype":"venue"
},
  "geometry": {"coordinates":[-122.007238,37.384491],"type":"Point"}
}