{
  "type": "Feature",
  "properties": {
    "addr:full":"549 S Western Ave Los Angeles CA 90020",
    "addr:housenumber":"549",
    "addr:postcode":"90020",
    "addr:street":"S Western Ave",
    "iso:country":"US",
    "sg:address":"549 S Western Ave",
    "sg:city":"Los Angeles",
    "sg:classifiers":[
        {
            "category":"Ice Cream",
            "type":"Food & Drink"
        }
    ],
    "sg:phone":"+1 213 386 1199",
    "sg:postcode":"90020",
    "sg:province":"CA",
    "sg:tags":[
        "frozen",
        "yogurt"
    ],
    "wof:name":"Berry Nutty",
    "wof:placetype":"venue"
},
  "geometry": {"coordinates":[-118.309105,34.06384],"type":"Point"}
}