{
  "type": "Feature",
  "properties": {
    "iso:country":"US",
    "sg:address":"23691 Ave 95",
    "sg:city":"Terra Bella",
    "sg:classifiers":[
        {
            "category":"Food & Beverages",
            "subcategory":"Groceries & Convenience Stores",
            "type":"Retail Goods"
        }
    ],
    "sg:phone":"+1 559 535 1635",
    "sg:postcode":"93270",
    "sg:province":"CA",
    "wof:name":"Terra Bella Handy Market",
    "wof:placetype":"venue"
},
  "geometry": {"coordinates":[-119.043366,35.96237],"type":"Point"}
}