{
  "type": "Feature",
  "properties": {
    "addr:full":"4878 Ronson Ct San Diego CA 92111",
    "addr:housenumber":"4878",
    "addr:postcode":"92111",
    "addr:street":"Ronson Ct",
    "iso:country":"US",
    "sg:address":"4878 Ronson Ct",
    "sg:city":"San Diego",
    "sg:classifiers":[
        {
            "category":"Professional",
            "subcategory":"Art Services",
            "type":"Services"
        }
    ],
    "sg:phone":"+1 858 715 0228",
    "sg:postcode":"92111",
    "sg:province":"CA",
    "sg:tags":[
        "artist"
    ],
    "wof:name":"Midwest Graphix",
    "wof:placetype":"venue"
},
  "geometry": {"coordinates":[-117.146035,32.829538],"type":"Point"}
}