{
  "type": "Feature",
  "properties": {
    "addr:full":"222 Herlong Ave San Jose CA 95123",
    "addr:housenumber":"222",
    "addr:postcode":"95123",
    "addr:street":"Herlong Ave",
    "iso:country":"US",
    "sg:address":"222 Herlong Ave",
    "sg:city":"San Jose",
    "sg:classifiers":[
        {
            "category":"Social Services",
            "subcategory":"Child Care",
            "type":"Services"
        }
    ],
    "sg:phone":"+1 408 227 0640",
    "sg:postcode":"95123",
    "sg:province":"CA",
    "wof:name":"Little Z Daycare",
    "wof:placetype":"venue"
},
  "geometry": {"coordinates":[-121.81232,37.243808],"type":"Point"}
}