{
  "type": "Feature",
  "properties": {
    "addr:full":"7627 Wilcox Ave Bell CA 90201",
    "addr:housenumber":"7627",
    "addr:postcode":"90201",
    "addr:street":"Wilcox Ave",
    "iso:country":"US",
    "sg:address":"7627 Wilcox Ave",
    "sg:city":"Bell",
    "sg:classifiers":[
        {
            "category":"Professional",
            "type":"Services"
        }
    ],
    "sg:phone":"+1 323 560 3398",
    "sg:postcode":"90201",
    "sg:province":"CA",
    "wof:name":"Bella Novia",
    "wof:placetype":"venue"
},
  "geometry": {"coordinates":[-118.178454,33.965737],"type":"Point"}
}