{
  "type": "Feature",
  "properties": {
    "iso:country":"US",
    "sg:address":"18583 Main St",
    "sg:city":"Huntington Beach",
    "sg:classifiers":[
        {
            "category":"Shopping",
            "subcategory":"Pets & Pet Supplies",
            "type":"Retail Goods"
        }
    ],
    "sg:phone":"+1 714 848 5859",
    "sg:postcode":"92648",
    "sg:province":"CA",
    "sg:tags":[
        "store"
    ],
    "wof:name":"Pets Pets Pets",
    "wof:placetype":"venue"
},
  "geometry": {"coordinates":[-117.989998,33.693001],"type":"Point"}
}