{
  "type": "Feature",
  "properties": {
    "addr:full":"7809 Bear Mountain Blvd Bakersfield CA 93313",
    "addr:housenumber":"7809",
    "addr:postcode":"93313",
    "addr:street":"Bear Mountain Blvd",
    "iso:country":"US",
    "sg:address":"7809 Bear Mountain Blvd",
    "sg:city":"Bakersfield",
    "sg:classifiers":[
        {
            "category":"Manufacturing",
            "subcategory":"Textiles",
            "type":"Manufacturing & Wholesale Goods"
        }
    ],
    "sg:phone":"+1 661 831 2834",
    "sg:postcode":"93313",
    "sg:province":"CA",
    "sg:tags":[
        "processing",
        "cotton"
    ],
    "wof:name":"KERN Delta Weedpatch Cotton",
    "wof:placetype":"venue"
},
  "geometry": {"coordinates":[-119.08468499999999,35.208688],"type":"Point"}
}