{
  "type": "Feature",
  "properties": {
    "addr:full":"1428 Haight St San Francisco CA 94117",
    "addr:housenumber":"1428",
    "addr:postcode":"94117",
    "addr:street":"Haight St",
    "iso:country":"US",
    "sg:address":"1428 Haight St",
    "sg:city":"San Francisco",
    "sg:classifiers":[
        {
            "category":"Bakery",
            "type":"Food & Drink"
        }
    ],
    "sg:menulink":"http://www.allmenus.com/ca/san-francisco/64988-squat--gobble/menu/",
    "sg:phone":"+1 415 864 8484",
    "sg:postcode":"94117",
    "sg:province":"CA",
    "sg:tags":[
        "wrap",
        "american",
        "sandwich",
        "pastry"
    ],
    "wof:name":"Squat & Gobble",
    "wof:placetype":"venue"
},
  "geometry": {"coordinates":[-122.445864,37.770202],"type":"Point"}
}