{
  "type": "Feature",
  "properties": {
    "iso:country":"US",
    "sg:address":"1628 Webster St",
    "sg:city":"Oakland",
    "sg:classifiers":[
        {
            "category":"Restaurant",
            "type":"Food & Drink"
        }
    ],
    "sg:phone":"+1 510 268 0170",
    "sg:postcode":"94612",
    "sg:province":"CA",
    "sg:tags":[
        "new",
        "american"
    ],
    "sg:website":"www.spicemonkeycafe.com",
    "wof:name":"Spice Monkey",
    "wof:placetype":"venue"
},
  "geometry": {"coordinates":[-122.267557,37.805429],"type":"Point"}
}