{
  "type": "Feature",
  "properties": {
    "iso:country":"US",
    "sg:address":"6976 Chestnut St",
    "sg:city":"Gilroy",
    "sg:classifiers":[
        {
            "category":"Insurance",
            "subcategory":"Insurance Agent",
            "type":"Services"
        }
    ],
    "sg:phone":"+1 408 848 9085",
    "sg:postcode":"95020",
    "sg:province":"CA",
    "sg:website":"www.dicarinsurancemarketing.com",
    "wof:name":"Dicar Insurance Marketing",
    "wof:placetype":"venue"
},
  "geometry": {"coordinates":[-121.56050999999999,37.001549],"type":"Point"}
}