{
  "type": "Feature",
  "properties": {
    "iso:country":"US",
    "sg:address":"1642 el Capitan Dr",
    "sg:city":"Redding",
    "sg:classifiers":[
        {
            "category":"Building & Trades",
            "subcategory":"Electrical",
            "type":"Services"
        }
    ],
    "sg:phone":"+1 530 242 0700",
    "sg:postcode":"96001",
    "sg:province":"CA",
    "sg:tags":[
        "booth",
        "equipment",
        "telephone",
        "pay"
    ],
    "wof:name":"Mountain Communication",
    "wof:placetype":"venue"
},
  "geometry": {"coordinates":[-122.427753,40.575423],"type":"Point"}
}