{
  "type": "Feature",
  "properties": {
    "addr:full":"1850 Humboldt Rd Chico CA 95928",
    "addr:housenumber":"1850",
    "addr:postcode":"95928",
    "addr:street":"Humboldt Rd",
    "iso:country":"US",
    "sg:address":"1850 Humboldt Rd",
    "sg:city":"Chico",
    "sg:classifiers":[
        {
            "category":"Building & Trades",
            "subcategory":"Electrical",
            "type":"Services"
        }
    ],
    "sg:phone":"+1 530 892 2212",
    "sg:postcode":"95928",
    "sg:province":"CA",
    "sg:tags":[
        "electric",
        "contractor"
    ],
    "wof:name":"Elite Electric",
    "wof:placetype":"venue"
},
  "geometry": {"coordinates":[-121.81537,39.735394],"type":"Point"}
}