{
  "type": "Feature",
  "properties": {
    "addr:full":"3111 Fallow Field Dr Diamond Bar CA 91765",
    "addr:housenumber":"3111",
    "addr:postcode":"91765",
    "addr:street":"Fallow Field Dr",
    "iso:country":"US",
    "sg:address":"3111 Fallow Field Dr",
    "sg:city":"Diamond Bar",
    "sg:classifiers":[
        {
            "category":"Manufacturing",
            "subcategory":"Printing",
            "type":"Manufacturing & Wholesale Goods"
        }
    ],
    "sg:phone":"+1 909 594 9280",
    "sg:postcode":"91765",
    "sg:province":"CA",
    "sg:tags":[
        "publishing"
    ],
    "wof:name":"Jonopher Publishing",
    "wof:placetype":"venue"
},
  "geometry": {"coordinates":[-117.848923,33.970549],"type":"Point"}
}