{
  "type": "Feature",
  "properties": {
    "addr:full":"140 Marine View Ave Solana Beach CA 92075",
    "addr:housenumber":"140",
    "addr:postcode":"92075",
    "addr:street":"Marine View Ave",
    "iso:country":"US",
    "sg:address":"140 Marine View Ave",
    "sg:city":"Solana Beach",
    "sg:classifiers":[
        {
            "category":"Education",
            "subcategory":"Special Training",
            "type":"Public Place"
        }
    ],
    "sg:phone":"+1 858 755 0485",
    "sg:postcode":"92075",
    "sg:province":"CA",
    "sg:tags":[
        "school",
        "art"
    ],
    "sg:website":"www.artsattack.com",
    "wof:name":"Arts Attack",
    "wof:placetype":"venue"
},
  "geometry": {"coordinates":[-117.255526,32.993654],"type":"Point"}
}