{
  "type": "Feature",
  "properties": {
    "iso:country":"US",
    "sg:address":"517 Portsmouth Ct",
    "sg:city":"Agoura Hills",
    "sg:classifiers":[
        {
            "category":"Professional",
            "subcategory":"Business Services",
            "type":"Services"
        }
    ],
    "sg:phone":"+1 818 889 5726",
    "sg:postcode":"91377",
    "sg:province":"CA",
    "wof:name":"Kovarik -Markham Design",
    "wof:placetype":"venue"
},
  "geometry": {"coordinates":[-118.778756,34.178646],"type":"Point"}
}