{
  "type": "Feature",
  "properties": {
    "addr:full":"1931 Donna Ave Los Osos CA 93402",
    "addr:housenumber":"1931",
    "addr:postcode":"93402",
    "addr:street":"Donna Ave",
    "iso:country":"US",
    "sg:address":"1931 Donna Ave",
    "sg:city":"Los Osos",
    "sg:classifiers":[
        {
            "category":"Professional",
            "subcategory":"Business Services",
            "type":"Services"
        }
    ],
    "sg:phone":"+1 805 534 0612",
    "sg:postcode":"93402",
    "sg:province":"CA",
    "sg:tags":[
        "interior",
        "consultant",
        "design",
        "decorator"
    ],
    "wof:name":"Rozanne Griffiths Interior",
    "wof:placetype":"venue"
},
  "geometry": {"coordinates":[-120.84733,35.31627],"type":"Point"}
}