{
  "type": "Feature",
  "properties": {
    "addr:full":"6330 Pine Ave Bell CA 90201",
    "addr:housenumber":"6330",
    "addr:postcode":"90201",
    "addr:street":"Pine Ave",
    "iso:country":"US",
    "sg:address":"6330 Pine Ave",
    "sg:city":"Bell",
    "sg:classifiers":[
        {
            "category":"Government",
            "subcategory":"Office",
            "type":"Public Place"
        }
    ],
    "sg:phone":"+1 323 588 6211",
    "sg:postcode":"90201",
    "sg:province":"CA",
    "sg:tags":[
        "city"
    ],
    "wof:name":"City of Bell",
    "wof:placetype":"venue"
},
  "geometry": {"coordinates":[-118.188855,33.979188],"type":"Point"}
}