{
  "type": "Feature",
  "properties": {
    "iso:country":"US",
    "sg:address":"5150 Sunrise Blvd Suite F-6",
    "sg:city":"Fair Oaks",
    "sg:classifiers":[
        {
            "category":"Shopping",
            "subcategory":"Party Supplies",
            "type":"Retail Goods"
        },
        {
            "category":"Personal",
            "type":"Services"
        }
    ],
    "sg:phone":"+1 916 961 1799",
    "sg:postcode":"95628",
    "sg:province":"CA",
    "sg:tags":[
        "planning",
        "event"
    ],
    "sg:website":"www.balloonbutler.com",
    "wof:name":"The Balloon Butler",
    "wof:placetype":"venue"
},
  "geometry": {"coordinates":[-121.271799,38.659752],"type":"Point"}
}