{
  "type": "Feature",
  "properties": {
    "iso:country":"US",
    "sg:address":"1350 Pacific Ave",
    "sg:city":"Santa Cruz",
    "sg:classifiers":[
        {
            "category":"Shopping",
            "subcategory":"Shoes",
            "type":"Retail Goods"
        }
    ],
    "sg:phone":"+1 831 423 3824",
    "sg:postcode":"95060",
    "sg:province":"CA",
    "sg:tags":[
        "store"
    ],
    "wof:name":"Bunny's Shoes",
    "wof:placetype":"venue"
},
  "geometry": {"coordinates":[-122.02600099999999,36.9744],"type":"Point"}
}