{
  "type": "Feature",
  "properties": {
    "addr:full":"5545 E Airways Blvd Fresno CA 93727",
    "addr:housenumber":"5545",
    "addr:postcode":"93727",
    "addr:street":"E Airways Blvd",
    "iso:country":"US",
    "sg:address":"5545 E Airways Blvd",
    "sg:city":"Fresno",
    "sg:classifiers":[
        {
            "category":"Government",
            "subcategory":"Office",
            "type":"Public Place"
        }
    ],
    "sg:phone":"+1 559 297 3879",
    "sg:postcode":"93727",
    "sg:province":"CA",
    "sg:tags":[
        "administrative",
        "program",
        "health"
    ],
    "wof:name":"Facilities Management Section",
    "wof:placetype":"venue"
},
  "geometry": {"coordinates":[-119.70106,36.772308],"type":"Point"}
}