{
  "type": "Feature",
  "properties": {
    "addr:full":"2921 S Main St Santa Ana CA 92707",
    "addr:housenumber":"2921",
    "addr:postcode":"92707",
    "addr:street":"S Main St",
    "iso:country":"US",
    "sg:address":"2921 S Main St",
    "sg:city":"Santa Ana",
    "sg:classifiers":[
        {
            "category":"Wholesale",
            "subcategory":"Machinery & Supplies",
            "type":"Manufacturing & Wholesale Goods"
        }
    ],
    "sg:phone":"+1 714 549 7725",
    "sg:postcode":"92707",
    "sg:province":"CA",
    "sg:tags":[
        "industrial"
    ],
    "wof:name":"Drillco Devices Ltd",
    "wof:placetype":"venue"
},
  "geometry": {"coordinates":[-117.86795600000001,33.706948],"type":"Point"}
}