{
  "type": "Feature",
  "properties": {
    "iso:country":"US",
    "sg:address":"1411 Cypress St",
    "sg:city":"Berkeley",
    "sg:classifiers":[
        {
            "category":"Wholesale",
            "subcategory":"Groceries",
            "type":"Manufacturing & Wholesale Goods"
        }
    ],
    "sg:phone":"+1 510 527 5259",
    "sg:postcode":"94703",
    "sg:province":"CA",
    "sg:tags":[
        "food",
        "product",
        "health"
    ],
    "wof:name":"Ali's Bazaar Co",
    "wof:placetype":"venue"
},
  "geometry": {"coordinates":[-122.27816799999999,37.879659],"type":"Point"}
}