{
  "type": "Feature",
  "properties": {
    "addr:full":"131 Tustin Ave Tustin CA 92780",
    "addr:housenumber":"131",
    "addr:postcode":"92780",
    "addr:street":"Tustin Ave",
    "iso:country":"US",
    "sg:address":"131 Tustin Ave",
    "sg:city":"Tustin",
    "sg:classifiers":[
        {
            "category":"Banks & Credit Unions",
            "subcategory":"Bank",
            "type":"Services"
        }
    ],
    "sg:phone":"+1 714 245 2808",
    "sg:postcode":"92780",
    "sg:province":"CA",
    "sg:tags":[
        "mortgage"
    ],
    "wof:name":"Coastview Financial",
    "wof:placetype":"venue"
},
  "geometry": {"coordinates":[-117.834205,33.74608],"type":"Point"}
}