{
  "type": "Feature",
  "properties": {
    "iso:country":"US",
    "sg:address":"5821 39th St",
    "sg:city":"Sacramento",
    "sg:classifiers":[
        {
            "category":"Transit Center",
            "subcategory":"Passenger",
            "type":"Transportation"
        },
        {
            "category":"Local Transit",
            "type":"Transportation"
        }
    ],
    "sg:phone":"+1 916 429 2958",
    "sg:postcode":"95824",
    "sg:province":"CA",
    "sg:tags":[
        "line",
        "public"
    ],
    "wof:name":"Swift Transit",
    "wof:placetype":"venue"
},
  "geometry": {"coordinates":[-121.463044,38.520589],"type":"Point"}
}