{
  "type": "Feature",
  "properties": {
    "addr:full":"3602 Munster St Hayward CA 94545",
    "addr:housenumber":"3602",
    "addr:postcode":"94545",
    "addr:street":"Munster St",
    "iso:country":"US",
    "sg:address":"3602 Munster St",
    "sg:city":"Hayward",
    "sg:classifiers":[
        {
            "category":"Personal",
            "subcategory":"Beauty Salon",
            "type":"Services"
        }
    ],
    "sg:phone":"+1 510 293 6909",
    "sg:postcode":"94545",
    "sg:province":"CA",
    "sg:tags":[
        "spa"
    ],
    "wof:name":"Pacific Home Products",
    "wof:placetype":"venue"
},
  "geometry": {"coordinates":[-122.126999,37.6413],"type":"Point"}
}