{
  "type": "Feature",
  "properties": {
    "iso:country":"US",
    "sg:address":"1851 N Riverside Ave",
    "sg:city":"Rialto",
    "sg:classifiers":[
        {
            "category":"Health Services",
            "subcategory":"Doctor",
            "type":"Services"
        }
    ],
    "sg:phone":"+1 909 874 2371",
    "sg:postcode":"92376",
    "sg:province":"CA",
    "sg:tags":[
        "physician",
        "surgeon"
    ],
    "wof:name":"U S Familycare",
    "wof:placetype":"venue"
},
  "geometry": {"coordinates":[-117.37038,34.129563],"type":"Point"}
}