{
  "type": "Feature",
  "properties": {
    "addr:full":"988 N Mount Vernon Ave San Bernardino CA 92411",
    "addr:housenumber":"988",
    "addr:postcode":"92411",
    "addr:street":"N Mount Vernon Ave",
    "iso:country":"US",
    "sg:address":"988 N Mount Vernon Ave",
    "sg:city":"San Bernardino",
    "sg:classifiers":[
        {
            "category":"Shopping",
            "subcategory":"Books",
            "type":"Retail Goods"
        }
    ],
    "sg:phone":"+1 909 889 5551",
    "sg:postcode":"92411",
    "sg:province":"CA",
    "sg:tags":[
        "travel",
        "agency"
    ],
    "wof:name":"Quetzal Travel Agency",
    "wof:placetype":"venue"
},
  "geometry": {"coordinates":[-117.31391600000001,34.116003],"type":"Point"}
}