{
  "type": "Feature",
  "properties": {
    "iso:country":"US",
    "sg:address":"50 N La Cienega Blvd Ste 310",
    "sg:city":"Beverly Hills",
    "sg:classifiers":[
        {
            "category":"Community Center",
            "type":"Public Place"
        }
    ],
    "sg:phone":"+1 310 358 9404",
    "sg:postcode":"90211",
    "sg:province":"CA",
    "sg:tags":[
        "medical"
    ],
    "sg:website":"www.crhsystem.com",
    "wof:name":"The Center For Colorectal Health",
    "wof:placetype":"venue"
},
  "geometry": {"coordinates":[-118.375919,34.066902],"type":"Point"}
}