{
  "type": "Feature",
  "properties": {
    "iso:country":"US",
    "sg:address":"1014 E Washington Ave",
    "sg:city":"El Cajon",
    "sg:classifiers":[
        {
            "category":"Professional",
            "subcategory":"Accounting & Tax Preparation",
            "type":"Services"
        }
    ],
    "sg:phone":"+1 619 579 5560",
    "sg:postcode":"92020",
    "sg:province":"CA",
    "sg:tags":[
        "return",
        "filing"
    ],
    "wof:name":"Sarah & Anne Tax Consultants",
    "wof:placetype":"venue"
},
  "geometry": {"coordinates":[-116.947462,32.787732],"type":"Point"}
}