{
  "type": "Feature",
  "properties": {
    "iso:country":"US",
    "sg:address":"2924 E Laurel Ave",
    "sg:city":"Visalia",
    "sg:classifiers":[
        {
            "category":"Farming",
            "subcategory":"Farm",
            "type":"Manufacturing & Wholesale Goods"
        }
    ],
    "sg:phone":"+1 559 734 8283",
    "sg:postcode":"93292",
    "sg:province":"CA",
    "wof:name":"Franklin Cardoza Farms",
    "wof:placetype":"venue"
},
  "geometry": {"coordinates":[-119.256846,36.32076],"type":"Point"}
}