{
  "type": "Feature",
  "properties": {
    "iso:country":"US",
    "sg:address":"26500 Agoura Rd",
    "sg:city":"Calabasas",
    "sg:classifiers":[
        {
            "category":"Professional",
            "subcategory":"Lawyer & Legal Services",
            "type":"Services"
        }
    ],
    "sg:phone":"+1 818 880 8990",
    "sg:postcode":"91302",
    "sg:province":"CA",
    "sg:tags":[
        "divorce",
        "law",
        "family"
    ],
    "wof:name":"Warner Center Law Offices",
    "wof:placetype":"venue"
},
  "geometry": {"coordinates":[-118.697998,34.144001],"type":"Point"}
}