{
  "type": "Feature",
  "properties": {
    "iso:country":"US",
    "sg:address":"2120 Wilcox Rd",
    "sg:city":"Stockton",
    "sg:classifiers":[
        {
            "category":"Building & Trades",
            "subcategory":"Construction",
            "type":"Services"
        }
    ],
    "sg:phone":"+1 209 931 3210",
    "sg:postcode":"95215",
    "sg:province":"CA",
    "sg:tags":[
        "water",
        "well",
        "drilling"
    ],
    "wof:name":"Moorman's Water Systems",
    "wof:placetype":"venue"
},
  "geometry": {"coordinates":[-121.244012,37.987358],"type":"Point"}
}