{
  "type": "Feature",
  "properties": {
    "iso:country":"US",
    "sg:address":"6535 Wilshire Blvd.",
    "sg:city":"Los Angeles",
    "sg:classifiers":[
        {
            "category":"Health Services",
            "subcategory":"Clinic",
            "type":"Services"
        }
    ],
    "sg:postcode":"90048",
    "sg:province":"CA",
    "sg:tags":[
        "counseling",
        "mental"
    ],
    "wof:name":"Bradley A. Tepaske, Ph.D.",
    "wof:placetype":"venue"
},
  "geometry": {"coordinates":[-118.37107399999999,34.06426],"type":"Point"}
}