{
  "type": "Feature",
  "properties": {
    "addr:full":"11140 Fair Oaks Boulevard Suite 8 Fair Oaks CA 95628",
    "addr:housenumber":"11140",
    "addr:postcode":"95628",
    "addr:street":"Fair Oaks Boulevard Suite 8",
    "iso:country":"US",
    "sg:address":"11140 Fair Oaks Boulevard Suite 8",
    "sg:city":"Fair Oaks",
    "sg:classifiers":[
        {
            "category":"Professional",
            "subcategory":"Lawyer & Legal Services",
            "type":"Services"
        }
    ],
    "sg:phone":"+1 916 966 2260",
    "sg:postcode":"95628",
    "sg:province":"CA",
    "wof:name":"Bpe Law Group",
    "wof:placetype":"venue"
},
  "geometry": {"coordinates":[-121.264278,38.654434],"type":"Point"}
}