{
  "type": "Feature",
  "properties": {
    "addr:full":"509 S Harbor Blvd Santa Ana CA 92704",
    "addr:housenumber":"509",
    "addr:postcode":"92704",
    "addr:street":"S Harbor Blvd",
    "iso:country":"US",
    "sg:address":"509 S Harbor Blvd",
    "sg:city":"Santa Ana",
    "sg:classifiers":[
        {
            "category":"Professional",
            "subcategory":"Accounting & Tax Preparation",
            "type":"Services"
        }
    ],
    "sg:phone":"+1 714 531 2474",
    "sg:postcode":"92704",
    "sg:province":"CA",
    "sg:tags":[
        "accountant"
    ],
    "sg:website":"www.libertytax.com",
    "wof:name":"Liberty Tax Service",
    "wof:placetype":"venue"
},
  "geometry": {"coordinates":[-117.919877,33.738325],"type":"Point"}
}