{
  "type": "Feature",
  "properties": {
    "iso:country":"US",
    "sg:address":"710 E 6th St",
    "sg:city":"Corona",
    "sg:classifiers":[
        {
            "category":"Restaurant",
            "type":"Food & Drink"
        }
    ],
    "sg:phone":"+1 951 737 5977",
    "sg:postcode":"92879",
    "sg:province":"CA",
    "wof:name":"Silver Dollar Pancake House",
    "wof:placetype":"venue"
},
  "geometry": {"coordinates":[-117.55397499999999,33.874533],"type":"Point"}
}