{
  "type": "Feature",
  "properties": {
    "addr:full":"8993 S Gate Ave South Gate CA 90280",
    "addr:housenumber":"8993",
    "addr:postcode":"90280",
    "addr:street":"S Gate Ave;Gate",
    "iso:country":"US",
    "sg:address":"8993 S Gate Ave",
    "sg:city":"South Gate",
    "sg:classifiers":[
        {
            "category":"Travel",
            "subcategory":"Hotels & Motels",
            "type":"Entertainment"
        }
    ],
    "sg:phone":"+1 323 569 9320",
    "sg:postcode":"90280",
    "sg:province":"CA",
    "wof:name":"Malta Motel",
    "wof:placetype":"venue"
},
  "geometry": {"coordinates":[-118.21471099999999,33.954454],"type":"Point"}
}