{
  "type": "Feature",
  "properties": {
    "addr:full":"11185 Commercial Pkwy Castroville CA 95012",
    "addr:housenumber":"11185",
    "addr:postcode":"95012",
    "addr:street":"Commercial Pkwy",
    "iso:country":"US",
    "sg:address":"11185 Commercial Pkwy",
    "sg:city":"Castroville",
    "sg:classifiers":[
        {
            "category":"Professional",
            "subcategory":"Business Services",
            "type":"Services"
        }
    ],
    "sg:phone":"+1 831 624 8659",
    "sg:postcode":"95012",
    "sg:province":"CA",
    "sg:tags":[
        "interior",
        "consultant",
        "design",
        "decorator"
    ],
    "wof:name":"Stoneworks Design",
    "wof:placetype":"venue"
},
  "geometry": {"coordinates":[-121.740668,36.754987],"type":"Point"}
}