{
  "type": "Feature",
  "properties": {
    "iso:country":"US",
    "sg:address":"1874 S Western Avenue",
    "sg:city":"Los Angeles",
    "sg:classifiers":[
        {
            "category":"Food & Beverages",
            "subcategory":"Groceries & Convenience Stores",
            "type":"Retail Goods"
        }
    ],
    "sg:phone":"+1 323 373 1607",
    "sg:postcode":"90006",
    "sg:province":"CA",
    "wof:name":"7-Eleven Food Stores",
    "wof:placetype":"venue"
},
  "geometry": {"coordinates":[-118.309124,34.040127],"type":"Point"}
}