{
  "type": "Feature",
  "properties": {
    "addr:full":"12539 Carson St. Hawaiian Gardens CA 90716",
    "addr:housenumber":"12539",
    "addr:postcode":"90716",
    "addr:street":"Carson St. Hawaiian Gardens",
    "iso:country":"US",
    "sg:address":"12539 Carson St.",
    "sg:city":"Hawaiian Gardens",
    "sg:classifiers":[
        {
            "category":"Building & Trades",
            "subcategory":"Construction",
            "type":"Services"
        },
        {
            "category":"Home & Garden",
            "subcategory":"Carpets & Floor Coverings",
            "type":"Retail Goods"
        }
    ],
    "sg:phone":"+1 562 402 8681",
    "sg:postcode":"90716",
    "sg:province":"CA",
    "sg:tags":[
        "interior",
        "design",
        "handyman",
        "flooring"
    ],
    "wof:name":"Hanmi Carpet",
    "wof:placetype":"venue"
},
  "geometry": {"coordinates":[-118.06472599999999,33.831667],"type":"Point"}
}