{
  "type": "Feature",
  "properties": {
    "iso:country":"US",
    "sg:address":"4425 Torrance Blvd",
    "sg:city":"Torrance",
    "sg:classifiers":[
        {
            "category":"Personal",
            "subcategory":"Beauty Salon",
            "type":"Services"
        }
    ],
    "sg:phone":"+1 310 371 1006",
    "sg:postcode":"90503",
    "sg:province":"CA",
    "wof:name":"Cut Ups",
    "wof:placetype":"venue"
},
  "geometry": {"coordinates":[-118.362296,33.837663],"type":"Point"}
}