{
  "type": "Feature",
  "properties": {
    "iso:country":"US",
    "sg:address":"18339 Oakmont Dr",
    "sg:city":"Canyon Country",
    "sg:classifiers":[
        {
            "category":"Communications",
            "subcategory":"Film & Video Production",
            "type":"Services"
        }
    ],
    "sg:phone":"+1 818 512 7069",
    "sg:postcode":"91387",
    "sg:province":"CA",
    "sg:tags":[
        "motion"
    ],
    "wof:name":"Red Hawk Productions Inc",
    "wof:placetype":"venue"
},
  "geometry": {"coordinates":[-118.455827,34.407412],"type":"Point"}
}