{
  "type": "Feature",
  "properties": {
    "addr:full":"602 N Paulina Ave Redondo Beach CA 90277",
    "addr:housenumber":"602",
    "addr:postcode":"90277",
    "addr:street":"N Paulina Ave",
    "iso:country":"US",
    "sg:address":"602 N Paulina Ave",
    "sg:city":"Redondo Beach",
    "sg:classifiers":[
        {
            "category":"Building & Trades",
            "subcategory":"Cleaning & Sanitation",
            "type":"Services"
        }
    ],
    "sg:phone":"+1 310 351 7062",
    "sg:postcode":"90277",
    "sg:province":"CA",
    "sg:tags":[
        "window",
        "washing"
    ],
    "wof:name":"Rob The Window Meister",
    "wof:placetype":"venue"
},
  "geometry": {"coordinates":[-118.381118,33.852613],"type":"Point"}
}