{
  "type": "Feature",
  "properties": {
    "iso:country":"US",
    "sg:address":"2990 Northgate Blvd",
    "sg:city":"Sacramento",
    "sg:classifiers":[
        {
            "category":"Restaurant",
            "type":"Food & Drink"
        }
    ],
    "sg:phone":"+1 916 565 1125",
    "sg:postcode":"95833",
    "sg:province":"CA",
    "sg:tags":[
        "mexican"
    ],
    "wof:name":"Los Gallos Taqueria",
    "wof:placetype":"venue"
},
  "geometry": {"coordinates":[-121.474998,38.619202],"type":"Point"}
}