{
  "type": "Feature",
  "properties": {
    "addr:full":"8974 Cord Ln San Diego CA 92126",
    "addr:housenumber":"8974",
    "addr:postcode":"92126",
    "addr:street":"Cord Ln",
    "iso:country":"US",
    "sg:address":"8974 Cord Ln",
    "sg:city":"San Diego",
    "sg:classifiers":[
        {
            "category":"Social Services",
            "subcategory":"Child Care",
            "type":"Services"
        }
    ],
    "sg:phone":"+1 858 695 1930",
    "sg:postcode":"92126",
    "sg:province":"CA",
    "wof:name":"Maria Elena Davo Fmly Child",
    "wof:placetype":"venue"
},
  "geometry": {"coordinates":[-117.131146,32.912885],"type":"Point"}
}