{
  "type": "Feature",
  "properties": {
    "addr:full":"12325 Rosecrans Ave Norwalk CA 90650",
    "addr:housenumber":"12325",
    "addr:postcode":"90650",
    "addr:street":"Rosecrans Ave",
    "iso:country":"US",
    "sg:address":"12325 Rosecrans Ave",
    "sg:city":"Norwalk",
    "sg:classifiers":[
        {
            "category":"Retail",
            "subcategory":"Funeral Services",
            "type":"Services"
        }
    ],
    "sg:phone":"+1 562 868 0788",
    "sg:postcode":"90650",
    "sg:province":"CA",
    "sg:tags":[
        "director"
    ],
    "wof:name":"Han Kook Mortuary",
    "wof:placetype":"venue"
},
  "geometry": {"coordinates":[-118.070099,33.902301],"type":"Point"}
}