{
  "type": "Feature",
  "properties": {
    "iso:country":"US",
    "sg:address":"1901 Newport Blvd",
    "sg:city":"Costa Mesa",
    "sg:classifiers":[
        {
            "category":"Recreation",
            "subcategory":"Dance Hall",
            "type":"Entertainment"
        }
    ],
    "sg:phone":"+1 949 548 9500",
    "sg:postcode":"92627",
    "sg:province":"CA",
    "sg:tags":[
        "club"
    ],
    "sg:website":"www.clubvegas.us",
    "wof:name":"Club Vegas",
    "wof:placetype":"venue"
},
  "geometry": {"coordinates":[-117.917,33.6436],"type":"Point"}
}