{
  "type": "Feature",
  "properties": {
    "iso:country":"US",
    "sg:address":"121 Guilford Cir",
    "sg:city":"Orland",
    "sg:classifiers":[
        {
            "category":"Farming",
            "subcategory":"Crops",
            "type":"Manufacturing & Wholesale Goods"
        }
    ],
    "sg:phone":"+1 530 865 2335",
    "sg:postcode":"95963",
    "sg:province":"CA",
    "sg:tags":[
        "grove",
        "nut",
        "tree"
    ],
    "wof:name":"Gary Anderson",
    "wof:placetype":"venue"
},
  "geometry": {"coordinates":[-122.19076,39.740941],"type":"Point"}
}