{
  "type": "Feature",
  "properties": {
    "addr:full":"4875 Mowry Ave Fremont CA 94538",
    "addr:housenumber":"4875",
    "addr:postcode":"94538",
    "addr:street":"Mowry Ave",
    "iso:country":"US",
    "sg:address":"4875 Mowry Ave",
    "sg:city":"Fremont",
    "sg:classifiers":[
        {
            "category":"Building & Trades",
            "subcategory":"Plumbing",
            "type":"Services"
        }
    ],
    "sg:phone":"+1 510 656 3289",
    "sg:postcode":"94538",
    "sg:province":"CA",
    "sg:tags":[
        "control",
        "air",
        "pollution"
    ],
    "wof:name":"Arc Flash Co",
    "wof:placetype":"venue"
},
  "geometry": {"coordinates":[-121.998463,37.536556],"type":"Point"}
}