{
  "type": "Feature",
  "properties": {
    "addr:full":"32 Mariposa Ave Watsonville CA 95076",
    "addr:housenumber":"32",
    "addr:postcode":"95076",
    "addr:street":"Mariposa Ave",
    "iso:country":"US",
    "sg:address":"32 Mariposa Ave",
    "sg:city":"Watsonville",
    "sg:classifiers":[
        {
            "category":"Freight",
            "type":"Transportation"
        }
    ],
    "sg:phone":"+1 831 761 8204",
    "sg:postcode":"95076",
    "sg:province":"CA",
    "sg:tags":[
        "operator",
        "local",
        "trucking"
    ],
    "wof:name":"Mexico Express",
    "wof:placetype":"venue"
},
  "geometry": {"coordinates":[-121.76852700000001,36.927939],"type":"Point"}
}