{
  "type": "Feature",
  "properties": {
    "addr:full":"210 S Irwindale Ave Azusa CA 91702",
    "addr:housenumber":"210",
    "addr:postcode":"91702",
    "addr:street":"S Irwindale Ave",
    "iso:country":"US",
    "sg:address":"210 S Irwindale Ave",
    "sg:city":"Azusa",
    "sg:classifiers":[
        {
            "category":"Organizations",
            "subcategory":"Religious Organization",
            "type":"Services"
        }
    ],
    "sg:phone":"+1 626 969 3350",
    "sg:postcode":"91702",
    "sg:province":"CA",
    "sg:tags":[
        "church"
    ],
    "wof:name":"Holy Place Church",
    "wof:placetype":"venue"
},
  "geometry": {"coordinates":[-117.93387199999999,34.118648],"type":"Point"}
}