{
  "type": "Feature",
  "properties": {
    "addr:full":"168 S E St San Bernardino CA 92401",
    "addr:housenumber":"168",
    "addr:postcode":"92401",
    "addr:street":"S E St",
    "iso:country":"US",
    "sg:address":"168 S E St",
    "sg:city":"San Bernardino",
    "sg:classifiers":[
        {
            "category":"Shopping",
            "subcategory":"Clothing, Apparel, & Fashions",
            "type":"Retail Goods"
        }
    ],
    "sg:phone":"+1 909 889 3777",
    "sg:postcode":"92401",
    "sg:province":"CA",
    "sg:tags":[
        "tailor"
    ],
    "wof:name":"Cordova's Tailor Shop",
    "wof:placetype":"venue"
},
  "geometry": {"coordinates":[-117.29424299999999,34.098675],"type":"Point"}
}