{
  "type": "Feature",
  "properties": {
    "iso:country":"US",
    "sg:address":"2335 Roll Dr",
    "sg:city":"San Diego",
    "sg:classifiers":[
        {
            "category":"Restaurant",
            "type":"Food & Drink"
        }
    ],
    "sg:phone":"+1 619 671 9138",
    "sg:postcode":"92154",
    "sg:province":"CA",
    "wof:name":"Golden Gate Chinese Food To Go",
    "wof:placetype":"venue"
},
  "geometry": {"coordinates":[-116.937354,32.553535],"type":"Point"}
}