{
  "type": "Feature",
  "properties": {
    "iso:country":"US",
    "sg:address":"4106 Stoneridge Dr",
    "sg:city":"Tracy",
    "sg:classifiers":[
        {
            "category":"Health Services",
            "subcategory":"Doctor",
            "type":"Services"
        }
    ],
    "sg:phone":"+1 209 830 0350",
    "sg:postcode":"95304",
    "sg:province":"CA",
    "sg:tags":[
        "clinic"
    ],
    "wof:name":"C J Medical Svc",
    "wof:placetype":"venue"
},
  "geometry": {"coordinates":[-121.35515,37.751699],"type":"Point"}
}