{
  "type": "Feature",
  "properties": {
    "addr:full":"4106 Stoneridge Dr Tracy CA 95304",
    "addr:housenumber":"4106",
    "addr:postcode":"95304",
    "addr:street":"Stoneridge Dr",
    "iso:country":"US",
    "sg:address":"4106 Stoneridge Dr",
    "sg:city":"Tracy",
    "sg:classifiers":[
        {
            "category":"Health Services",
            "subcategory":"Doctor",
            "type":"Services"
        }
    ],
    "sg:phone":"+1 209 830 0350",
    "sg:postcode":"95304",
    "sg:province":"CA",
    "sg:tags":[
        "clinic"
    ],
    "wof:name":"C J Medical Svc",
    "wof:placetype":"venue"
},
  "geometry": {"coordinates":[-121.35514999999999,37.751699],"type":"Point"}
}