{
  "type": "Feature",
  "properties": {
    "addr:full":"4150 Clement St San Francisco CA 94121",
    "addr:housenumber":"4150",
    "addr:postcode":"94121",
    "addr:street":"Clement St",
    "iso:country":"US",
    "sg:address":"4150 Clement St",
    "sg:city":"San Francisco",
    "sg:classifiers":[
        {
            "category":"Health Services",
            "subcategory":"Hospital",
            "type":"Services"
        }
    ],
    "sg:phone":"+1 415 221 4810",
    "sg:postcode":"94121",
    "sg:province":"CA",
    "sg:website":"www.sanfrancisco.va.gov",
    "wof:name":"San Francisco VA Medical Center",
    "wof:placetype":"venue"
},
  "geometry": {"coordinates":[-122.502101,37.78125],"type":"Point"}
}