{
  "type": "Feature",
  "properties": {
    "iso:country":"US",
    "sg:address":"2443 W 208th St",
    "sg:city":"Torrance",
    "sg:classifiers":[
        {
            "category":"Shopping",
            "subcategory":"Hobbies, Toys, & Games",
            "type":"Retail Goods"
        }
    ],
    "sg:phone":"+1 310 533 9774",
    "sg:postcode":"90501",
    "sg:province":"CA",
    "sg:tags":[
        "supply"
    ],
    "wof:name":"Games Anytime",
    "wof:placetype":"venue"
},
  "geometry": {"coordinates":[-118.328172,33.843811],"type":"Point"}
}