{
  "type": "Feature",
  "properties": {
    "addr:full":"1748 Market St Ste 201 San Francisco CA 94102",
    "addr:housenumber":"1748",
    "addr:postcode":"94102",
    "addr:street":"Market St Ste 201",
    "iso:country":"US",
    "sg:address":"1748 Market St Ste 201",
    "sg:city":"San Francisco",
    "sg:classifiers":[
        {
            "category":"Community Center",
            "type":"Public Place"
        }
    ],
    "sg:phone":"+1 415 565 7667",
    "sg:postcode":"94102",
    "sg:province":"CA",
    "sg:tags":[
        "medical"
    ],
    "sg:website":"www.lyon-martin.org",
    "wof:name":"Lyon Martin Health Services",
    "wof:placetype":"venue"
},
  "geometry": {"coordinates":[-122.423157,37.772191],"type":"Point"}
}