{
  "type": "Feature",
  "properties": {
    "addr:full":"21031 Ventura Blvd Woodland Hills CA 91364",
    "addr:housenumber":"21031",
    "addr:postcode":"91364",
    "addr:street":"Ventura Blvd",
    "iso:country":"US",
    "sg:address":"21031 Ventura Blvd",
    "sg:city":"Woodland Hills",
    "sg:classifiers":[
        {
            "category":"Professional",
            "subcategory":"Lawyer & Legal Services",
            "type":"Services"
        }
    ],
    "sg:phone":"+1 818 226 5662",
    "sg:postcode":"91364",
    "sg:province":"CA",
    "sg:tags":[
        "attorney"
    ],
    "wof:name":"Robert Lampl Law Office",
    "wof:placetype":"venue"
},
  "geometry": {"coordinates":[-118.592268,34.166874],"type":"Point"}
}