{
  "type": "Feature",
  "properties": {
    "iso:country":"US",
    "sg:address":"7300 Stockdale Hwy",
    "sg:city":"Bakersfield",
    "sg:classifiers":[
        {
            "category":"Social Services",
            "subcategory":"Child Care",
            "type":"Services"
        }
    ],
    "sg:phone":"+1 661 397 0101",
    "sg:postcode":"93309",
    "sg:province":"CA",
    "sg:tags":[
        "kindergarten",
        "academic",
        "school"
    ],
    "wof:name":"Precious Lambs Christian",
    "wof:placetype":"venue"
},
  "geometry": {"coordinates":[-119.086516,35.354355],"type":"Point"}
}