{
  "type": "Feature",
  "properties": {
    "iso:country":"US",
    "sg:address":"375 N Capitol Ave Ste A",
    "sg:city":"San Jose",
    "sg:classifiers":[
        {
            "category":"Sports & Exercise",
            "subcategory":"Gym",
            "type":"Entertainment"
        }
    ],
    "sg:phone":"+1 408 923 2639",
    "sg:postcode":"95133",
    "sg:province":"CA",
    "sg:tags":[
        "trainer"
    ],
    "sg:website":"www.24hourfitness.com",
    "wof:name":"24 Hour Fitness",
    "wof:placetype":"venue"
},
  "geometry": {"coordinates":[-121.846615,37.371058],"type":"Point"}
}