{
  "type": "Feature",
  "properties": {
    "iso:country":"US",
    "sg:address":"10797 Foothill Blvd",
    "sg:city":"Rancho Cucamonga",
    "sg:classifiers":[
        {
            "category":"Health Services",
            "subcategory":"Doctor",
            "type":"Services"
        }
    ],
    "sg:phone":"+1 909 581 0888",
    "sg:postcode":"91730",
    "sg:province":"CA",
    "sg:tags":[
        "dentist"
    ],
    "wof:name":"North Rancho Cucamonga Dental",
    "wof:placetype":"venue"
},
  "geometry": {"coordinates":[-117.568917,34.106421],"type":"Point"}
}