{
  "type": "Feature",
  "properties": {
    "iso:country":"US",
    "sg:address":"3818 W Burbank Blvd",
    "sg:city":"Burbank",
    "sg:classifiers":[
        {
            "category":"Manufacturing",
            "subcategory":"Printing",
            "type":"Manufacturing & Wholesale Goods"
        }
    ],
    "sg:phone":"+1 818 846 1655",
    "sg:postcode":"91505",
    "sg:province":"CA",
    "sg:tags":[
        "multimedia"
    ],
    "sg:website":"www.datamediastore.com",
    "wof:name":"DATAMEDIASTORE.COM",
    "wof:placetype":"venue"
},
  "geometry": {"coordinates":[-118.352036,34.174011],"type":"Point"}
}