{
  "type": "Feature",
  "properties": {
    "addr:full":"21991 El Toro Road Ste 7 Lake Forest CA 92630",
    "addr:housenumber":"21991",
    "addr:postcode":"92630",
    "addr:street":"El Toro Road Ste 7",
    "iso:country":"US",
    "sg:address":"21991 El Toro Road Ste 7",
    "sg:city":"Lake Forest",
    "sg:classifiers":[
        {
            "category":"Restaurant",
            "type":"Food & Drink"
        }
    ],
    "sg:phone":"+1 949 587 5016",
    "sg:postcode":"92630",
    "sg:province":"CA",
    "sg:tags":[
        "mexican"
    ],
    "wof:name":"LA Rana",
    "wof:placetype":"venue"
},
  "geometry": {"coordinates":[-117.667997,33.643146],"type":"Point"}
}