{
  "type": "Feature",
  "properties": {
    "addr:full":"555 Capitol Mall Sacramento CA 95814",
    "addr:housenumber":"555",
    "addr:postcode":"95814",
    "addr:street":"Capitol Mall",
    "iso:country":"US",
    "sg:address":"555 Capitol Mall",
    "sg:city":"Sacramento",
    "sg:classifiers":[
        {
            "category":"Restaurant",
            "type":"Food & Drink"
        }
    ],
    "sg:menulink":"http://www.allmenus.com/ca/sacramento/267884-55-degrees/menu/",
    "sg:phone":"+1 916 553 4100",
    "sg:postcode":"95814",
    "sg:province":"CA",
    "sg:tags":[
        "american"
    ],
    "wof:name":"55 Degrees",
    "wof:placetype":"venue"
},
  "geometry": {"coordinates":[-121.50060999999999,38.579164],"type":"Point"}
}