{
  "type": "Feature",
  "properties": {
    "addr:full":"601 Van Ness Ave Ste P San Francisco CA 94102",
    "addr:housenumber":"601",
    "addr:postcode":"94102",
    "addr:street":"Van Ness Ave Ste P",
    "iso:country":"US",
    "sg:address":"601 Van Ness Ave Ste P",
    "sg:city":"San Francisco",
    "sg:classifiers":[
        {
            "category":"Banks & Credit Unions",
            "subcategory":"Financial Services",
            "type":"Services"
        }
    ],
    "sg:phone":"+1 415 794 6639",
    "sg:postcode":"94102",
    "sg:province":"CA",
    "sg:tags":[
        "broker",
        "mortgage"
    ],
    "sg:website":"www.ryanlugbauer.com",
    "wof:name":"Ryan Lugbauer- Guarantee Mortgage Corp",
    "wof:placetype":"venue"
},
  "geometry": {"coordinates":[-122.42074,37.781332],"type":"Point"}
}