{
  "type": "Feature",
  "properties": {
    "addr:full":"2727 Pennington Rd Live Oak CA 95953",
    "addr:housenumber":"2727",
    "addr:postcode":"95953",
    "addr:street":"Pennington Rd",
    "iso:country":"US",
    "sg:address":"2727 Pennington Rd",
    "sg:city":"Live Oak",
    "sg:classifiers":[
        {
            "category":"Building & Trades",
            "subcategory":"Equipment Rental",
            "type":"Services"
        }
    ],
    "sg:phone":"+1 530 695 0607",
    "sg:postcode":"95953",
    "sg:province":"CA",
    "sg:tags":[
        "yard"
    ],
    "wof:name":"U-Haul Co",
    "wof:placetype":"venue"
},
  "geometry": {"coordinates":[-121.66402600000001,39.276166],"type":"Point"}
}