{
  "type": "Feature",
  "properties": {
    "addr:full":"765 Twin Creeks Way San Luis Obispo CA 93401",
    "addr:housenumber":"765",
    "addr:postcode":"93401",
    "addr:street":"Twin Creeks Way",
    "iso:country":"US",
    "sg:address":"765 Twin Creeks Way",
    "sg:city":"San Luis Obispo",
    "sg:classifiers":[
        {
            "category":"Shopping",
            "subcategory":"Clothing, Apparel, & Fashions",
            "type":"Retail Goods"
        }
    ],
    "sg:phone":"+1 805 544 9191",
    "sg:postcode":"93401",
    "sg:province":"CA",
    "sg:tags":[
        "wear"
    ],
    "wof:name":"Kathleen C Fritzley CPA",
    "wof:placetype":"venue"
},
  "geometry": {"coordinates":[-120.60795400000001,35.20371],"type":"Point"}
}