{
  "type": "Feature",
  "properties": {
    "addr:full":"1976 W Charter Way Stockton CA 95206",
    "addr:housenumber":"1976",
    "addr:postcode":"95206",
    "addr:street":"W Charter Way",
    "iso:country":"US",
    "sg:address":"1976 W Charter Way",
    "sg:city":"Stockton",
    "sg:classifiers":[
        {
            "category":"Restaurant",
            "type":"Food & Drink"
        }
    ],
    "sg:phone":"+1 209 948 7870",
    "sg:postcode":"95206",
    "sg:province":"CA",
    "wof:name":"Pacific Market Place",
    "wof:placetype":"venue"
},
  "geometry": {"coordinates":[-121.314791,37.932155],"type":"Point"}
}