{
  "type": "Feature",
  "properties": {
    "addr:full":"4122 Lakeshore Ave Oakland CA 94610",
    "addr:housenumber":"4122",
    "addr:postcode":"94610",
    "addr:street":"Lakeshore Ave",
    "iso:country":"US",
    "sg:address":"4122 Lakeshore Ave",
    "sg:city":"Oakland",
    "sg:classifiers":[
        {
            "category":"Real Estate",
            "subcategory":"Architect",
            "type":"Services"
        }
    ],
    "sg:phone":"+1 510 444 6229",
    "sg:postcode":"94610",
    "sg:province":"CA",
    "sg:website":"www.wslarch.com",
    "wof:name":"William S. Lyons",
    "wof:placetype":"venue"
},
  "geometry": {"coordinates":[-122.234467,37.81576],"type":"Point"}
}