{
  "type": "Feature",
  "properties": {
    "iso:country":"US",
    "sg:address":"35963 Date Palm Dr",
    "sg:city":"Cathedral City",
    "sg:classifiers":[
        {
            "category":"Banks & Credit Unions",
            "subcategory":"Bank",
            "type":"Services"
        }
    ],
    "sg:phone":"+1 760 770 4553",
    "sg:postcode":"92234",
    "sg:province":"CA",
    "sg:tags":[
        "loan",
        "real estate"
    ],
    "wof:name":"American General Financial",
    "wof:placetype":"venue"
},
  "geometry": {"coordinates":[-116.45817099999999,33.791799],"type":"Point"}
}