{
  "type": "Feature",
  "properties": {
    "iso:country":"US",
    "sg:address":"265 Miller Ave",
    "sg:city":"Mill Valley",
    "sg:classifiers":[
        {
            "category":"Professional",
            "subcategory":"Lawyer & Legal Services",
            "type":"Services"
        }
    ],
    "sg:phone":"+1 415 383 1070",
    "sg:postcode":"94941",
    "sg:province":"CA",
    "sg:tags":[
        "attorney"
    ],
    "wof:name":"Stephen J Perelson",
    "wof:placetype":"venue"
},
  "geometry": {"coordinates":[-122.540708,37.900639],"type":"Point"}
}