{
  "type": "Feature",
  "properties": {
    "addr:full":"240 F St Eureka CA 95501",
    "addr:housenumber":"240",
    "addr:postcode":"95501",
    "addr:street":"F St",
    "iso:country":"US",
    "sg:address":"240 F St",
    "sg:city":"Eureka",
    "sg:classifiers":[
        {
            "category":"Restaurant",
            "type":"Food & Drink"
        }
    ],
    "sg:phone":"+1 707 443 7489",
    "sg:postcode":"95501",
    "sg:province":"CA",
    "wof:name":"Ritz Teppamyaki & Sushi Bar",
    "wof:placetype":"venue"
},
  "geometry": {"coordinates":[-124.16656,40.804089],"type":"Point"}
}