{
  "type": "Feature",
  "properties": {
    "addr:full":"2513 Jenifer Ct Antioch CA 94509",
    "addr:housenumber":"2513",
    "addr:postcode":"ca 94509",
    "addr:street":"Jenifer Ct",
    "iso:country":"US",
    "sg:address":"2513 Jenifer Ct",
    "sg:city":"Antioch",
    "sg:classifiers":[
        {
            "category":"Professional",
            "type":"Services"
        }
    ],
    "sg:phone":"+1 925 778 4250",
    "sg:postcode":"94509",
    "sg:province":"CA",
    "wof:name":"Sweet Expressions By Lisa",
    "wof:placetype":"venue"
},
  "geometry": {"coordinates":[-121.841869,37.996931],"type":"Point"}
}