{
  "type": "Feature",
  "properties": {
    "addr:full":"1072 N el Centro Ave Los Angeles CA 90038",
    "addr:housenumber":"1072",
    "addr:postcode":"90038",
    "addr:street":"N El Centro Ave",
    "iso:country":"US",
    "sg:address":"1072 N el Centro Ave",
    "sg:city":"Los Angeles",
    "sg:classifiers":[
        {
            "category":"Organizations",
            "subcategory":"Religious Organization",
            "type":"Services"
        }
    ],
    "sg:phone":"+1 323 462 1447",
    "sg:postcode":"90038",
    "sg:province":"CA",
    "sg:tags":[
        "church"
    ],
    "wof:name":"Children Of The Shepherd",
    "wof:placetype":"venue"
},
  "geometry": {"coordinates":[-118.32436800000001,34.090329],"type":"Point"}
}