{
  "type": "Feature",
  "properties": {
    "addr:full":"419 Stony Point Rd Santa Rosa CA 95401",
    "addr:housenumber":"419",
    "addr:postcode":"95401",
    "addr:street":"Stony Point Rd",
    "iso:country":"US",
    "sg:address":"419 Stony Point Rd",
    "sg:city":"Santa Rosa",
    "sg:classifiers":[
        {
            "category":"Food & Beverages",
            "subcategory":"Groceries & Convenience Stores",
            "type":"Retail Goods"
        }
    ],
    "sg:phone":"+1 707 576 1288",
    "sg:postcode":"95401",
    "sg:province":"CA",
    "wof:name":"C S Grocery Mart",
    "wof:placetype":"venue"
},
  "geometry": {"coordinates":[-122.742259,38.433107],"type":"Point"}
}