{
  "type": "Feature",
  "properties": {
    "addr:full":"954 W Thornton Ave Hemet CA 92543",
    "addr:housenumber":"954",
    "addr:postcode":"92543",
    "addr:street":"W Thornton Ave",
    "iso:country":"US",
    "sg:address":"954 W Thornton Ave",
    "sg:city":"Hemet",
    "sg:classifiers":[
        {
            "category":"Restaurant",
            "type":"Food & Drink"
        }
    ],
    "sg:phone":"+1 951 766 0600",
    "sg:postcode":"92543",
    "sg:province":"CA",
    "sg:tags":[
        "eating"
    ],
    "wof:name":"China America Connect Consult",
    "wof:placetype":"venue"
},
  "geometry": {"coordinates":[-116.980644,33.725751],"type":"Point"}
}