{
  "type": "Feature",
  "properties": {
    "addr:full":"627 Charmain Dr Campbell CA 95008",
    "addr:housenumber":"627",
    "addr:postcode":"95008",
    "addr:street":"Charmain Dr",
    "iso:country":"US",
    "sg:address":"627 Charmain Dr",
    "sg:city":"Campbell",
    "sg:classifiers":[
        {
            "category":"Shopping",
            "subcategory":"Computers & Home Electronics",
            "type":"Retail Goods"
        }
    ],
    "sg:phone":"+1 408 370 7055",
    "sg:postcode":"95008",
    "sg:province":"CA",
    "sg:tags":[
        "parts",
        "supply"
    ],
    "wof:name":"Global Innovations Inc",
    "wof:placetype":"venue"
},
  "geometry": {"coordinates":[-121.961724,37.288338],"type":"Point"}
}