{
  "type": "Feature",
  "properties": {
    "iso:country":"US",
    "sg:address":"23011 Moulton Parkway Suite F7",
    "sg:city":"Laguna Hills",
    "sg:classifiers":[
        {
            "category":"Insurance",
            "subcategory":"Health Insurance",
            "type":"Services"
        }
    ],
    "sg:phone":"+1 949 586 6300",
    "sg:postcode":"92653",
    "sg:province":"CA",
    "sg:tags":[
        "market"
    ],
    "wof:name":"P-Bee Products",
    "wof:placetype":"venue"
},
  "geometry": {"coordinates":[-117.70844,33.592288],"type":"Point"}
}