{
  "type": "Feature",
  "properties": {
    "iso:country":"US",
    "sg:address":"806 W Harding Rd",
    "sg:city":"Turlock",
    "sg:classifiers":[
        {
            "category":"Farming",
            "subcategory":"Livestock Farm",
            "type":"Manufacturing & Wholesale Goods"
        }
    ],
    "sg:phone":"+1 209 632 1252",
    "sg:postcode":"95380",
    "sg:province":"CA",
    "sg:tags":[
        "ranch"
    ],
    "wof:name":"C Bart T",
    "wof:placetype":"venue"
},
  "geometry": {"coordinates":[-120.858047,37.463447],"type":"Point"}
}