{
  "type": "Feature",
  "properties": {
    "iso:country":"US",
    "sg:address":"13550 Tolton Ave",
    "sg:city":"Corona",
    "sg:classifiers":[
        {
            "category":"Social Services",
            "subcategory":"Child Care",
            "type":"Services"
        }
    ],
    "sg:phone":"+1 951 549 8492",
    "sg:postcode":"92879",
    "sg:province":"CA",
    "wof:name":"Home Gardens Headstart",
    "wof:placetype":"venue"
},
  "geometry": {"coordinates":[-117.52102499999999,33.876632],"type":"Point"}
}