{
  "type": "Feature",
  "properties": {
    "addr:full":"21098 Bake Pkwy Ste 114 Lake Forest CA 92630",
    "addr:housenumber":"21098",
    "addr:postcode":"92630",
    "addr:street":"Bake Pkwy Ste 114",
    "iso:country":"US",
    "sg:address":"21098 Bake Pkwy Ste 114",
    "sg:city":"Lake Forest",
    "sg:classifiers":[
        {
            "category":"Shopping",
            "subcategory":"Florist",
            "type":"Retail Goods"
        }
    ],
    "sg:phone":"+1 949 380 4873",
    "sg:postcode":"92630",
    "sg:province":"CA",
    "wof:name":"Foothill Ranch Florist Inc",
    "wof:placetype":"venue"
},
  "geometry": {"coordinates":[-117.70245,33.655494],"type":"Point"}
}