{
  "type": "Feature",
  "properties": {
    "addr:full":"598 Chenery Street San Francisco CA 94199",
    "addr:housenumber":"598",
    "addr:postcode":"94199",
    "addr:street":"Chenery Street",
    "iso:country":"US",
    "sg:address":"598 Chenery Street",
    "sg:city":"San Francisco",
    "sg:classifiers":[
        {
            "category":"Bakery",
            "type":"Food & Drink"
        }
    ],
    "sg:phone":"+1 415 238 6953",
    "sg:postcode":"94199",
    "sg:province":"CA",
    "sg:website":"www.sanfranciscocookie.com",
    "wof:name":"San Francisco Cookie Company",
    "wof:placetype":"venue"
},
  "geometry": {"coordinates":[-122.43241399999999,37.734567],"type":"Point"}
}