{
  "type": "Feature",
  "properties": {
    "iso:country":"US",
    "sg:address":"3234 Edward Avenue Suite F",
    "sg:city":"Santa Clara",
    "sg:classifiers":[
        {
            "category":"Retail",
            "subcategory":"Auto Repair",
            "type":"Services"
        }
    ],
    "sg:phone":"+1 866 624 2284",
    "sg:postcode":"95054",
    "sg:province":"CA",
    "sg:website":"www.esp-europeanautorepair.com/",
    "wof:name":"European Specialized Performance",
    "wof:placetype":"venue"
},
  "geometry": {"coordinates":[-121.939877,37.382986],"type":"Point"}
}