{
  "type": "Feature",
  "properties": {
    "iso:country":"US",
    "sg:address":"1100 Broad St",
    "sg:city":"San Luis Obispo",
    "sg:classifiers":[
        {
            "category":"Professional",
            "subcategory":"Lawyer & Legal Services",
            "type":"Services"
        }
    ],
    "sg:phone":"+1 805 549 9546",
    "sg:postcode":"93401",
    "sg:province":"CA",
    "sg:tags":[
        "attorney"
    ],
    "wof:name":"Robert K M Meyers",
    "wof:placetype":"venue"
},
  "geometry": {"coordinates":[-120.664485,35.278893],"type":"Point"}
}