{
  "type": "Feature",
  "properties": {
    "addr:full":"1415 N Market Blvd Sacramento CA 95834",
    "addr:housenumber":"1415",
    "addr:postcode":"95834",
    "addr:street":"N Market Blvd",
    "iso:country":"US",
    "sg:address":"1415 N Market Blvd",
    "sg:city":"Sacramento",
    "sg:classifiers":[
        {
            "category":"Health Services",
            "subcategory":"Health Practitioner",
            "type":"Services"
        }
    ],
    "sg:phone":"+1 916 928 1234",
    "sg:postcode":"95834",
    "sg:province":"CA",
    "sg:tags":[
        "therapist",
        "physical"
    ],
    "wof:name":"Burger Physical Therapy Rehab",
    "wof:placetype":"venue"
},
  "geometry": {"coordinates":[-121.502358,38.646706],"type":"Point"}
}