{
  "type": "Feature",
  "properties": {
    "iso:country":"US",
    "sg:address":"5438 W Washington Boulevard",
    "sg:city":"Los Angeles",
    "sg:classifiers":[
        {
            "category":"Real Estate",
            "subcategory":"Real Estate Services",
            "type":"Services"
        }
    ],
    "sg:phone":"+1 323 938 4747",
    "sg:postcode":"90016",
    "sg:province":"CA",
    "sg:tags":[
        "management",
        "property"
    ],
    "sg:website":"www.manfield.net",
    "wof:name":"Manfield & Associates",
    "wof:placetype":"venue"
},
  "geometry": {"coordinates":[-118.361619,34.038565],"type":"Point"}
}