{
  "type": "Feature",
  "properties": {
    "iso:country":"US",
    "sg:address":"9415 Stevenson Bridge Rd",
    "sg:city":"Winters",
    "sg:classifiers":[
        {
            "category":"Professional",
            "type":"Services"
        }
    ],
    "sg:phone":"+1 530 753 4703",
    "sg:postcode":"95694",
    "sg:province":"CA",
    "wof:name":"Borchard Pter F Trstee of Pter",
    "wof:placetype":"venue"
},
  "geometry": {"coordinates":[-121.84979,38.534798],"type":"Point"}
}