{
  "type": "Feature",
  "properties": {
    "addr:full":"2400 W Coast Hwy Newport Beach CA 92663",
    "addr:housenumber":"2400",
    "addr:postcode":"92663",
    "addr:street":"W Coast Hwy",
    "iso:country":"US",
    "sg:address":"2400 W Coast Hwy",
    "sg:city":"Newport Beach",
    "sg:classifiers":[
        {
            "category":"Restaurant",
            "type":"Food & Drink"
        }
    ],
    "sg:menulink":"http://www.allmenus.com/ca/central-coast/62327-jack-shrimp/menu/",
    "sg:phone":"+1 949 650 5577",
    "sg:postcode":"92663",
    "sg:province":"CA",
    "sg:tags":[
        "seafood",
        "american"
    ],
    "wof:name":"Jack Shrimp",
    "wof:placetype":"venue"
},
  "geometry": {"coordinates":[-117.92137099999999,33.618917],"type":"Point"}
}