{
  "type": "Feature",
  "properties": {
    "addr:full":"28295 Newhall Ranch Rd Valencia CA 91355",
    "addr:housenumber":"28295",
    "addr:postcode":"91355",
    "addr:street":"Newhall Ranch Rd",
    "iso:country":"US",
    "sg:address":"28295 Newhall Ranch Rd",
    "sg:city":"Valencia",
    "sg:classifiers":[
        {
            "category":"Restaurant",
            "type":"Food & Drink"
        }
    ],
    "sg:phone":"+1 661 257 4304",
    "sg:postcode":"91355",
    "sg:province":"CA",
    "sg:tags":[
        "mexican"
    ],
    "sg:website":"www.qdoba.com",
    "wof:name":"Qdoba",
    "wof:placetype":"venue"
},
  "geometry": {"coordinates":[-118.589172,34.444999],"type":"Point"}
}