{
  "type": "Feature",
  "properties": {
    "addr:full":"5600 Imhoff Dr Concord CA 94520",
    "addr:postcode":"5600;94520",
    "addr:street":"Imhoff Dr",
    "iso:country":"US",
    "sg:address":"5600 Imhoff Dr",
    "sg:city":"Concord",
    "sg:classifiers":[
        {
            "category":"Manufacturing",
            "subcategory":"Tools & Machinery",
            "type":"Manufacturing & Wholesale Goods"
        }
    ],
    "sg:phone":"+1 925 356 2548",
    "sg:postcode":"94520",
    "sg:province":"CA",
    "sg:tags":[
        "control",
        "flood",
        "equipment"
    ],
    "wof:name":"Steamatic Of Contra Costa And Solano",
    "wof:placetype":"venue"
},
  "geometry": {"coordinates":[-122.063087,38.001808],"type":"Point"}
}