{
  "type": "Feature",
  "properties": {
    "addr:full":"608 Hayes St San Francisco CA 94102",
    "addr:housenumber":"608",
    "addr:postcode":"94102",
    "addr:street":"Hayes St",
    "iso:country":"US",
    "sg:address":"608 Hayes St",
    "sg:city":"San Francisco",
    "sg:classifiers":[
        {
            "category":"Organizations",
            "subcategory":"Religious Organization",
            "type":"Services"
        }
    ],
    "sg:phone":"+1 415 621 8748",
    "sg:postcode":"94102",
    "sg:province":"CA",
    "sg:tags":[
        "church"
    ],
    "wof:name":"Neighborhood Baptist Church",
    "wof:placetype":"venue"
},
  "geometry": {"coordinates":[-122.427819,37.776345],"type":"Point"}
}