{
  "type": "Feature",
  "properties": {
    "iso:country":"US",
    "sg:address":"111 W Dyer Rd",
    "sg:city":"Santa Ana",
    "sg:classifiers":[
        {
            "category":"Manufacturing",
            "subcategory":"Printing",
            "type":"Manufacturing & Wholesale Goods"
        }
    ],
    "sg:phone":"+1 714 641 0220",
    "sg:postcode":"92707",
    "sg:province":"CA",
    "sg:tags":[
        "printer"
    ],
    "wof:name":"Bullfrog Printing",
    "wof:placetype":"venue"
},
  "geometry": {"coordinates":[-117.868781,33.708742],"type":"Point"}
}