{
  "type": "Feature",
  "properties": {
    "iso:country":"US",
    "sg:address":"2083 Martian Way",
    "sg:city":"Redding",
    "sg:classifiers":[
        {
            "category":"Building & Trades",
            "subcategory":"Landscaping Services",
            "type":"Services"
        }
    ],
    "sg:phone":"+1 530 221 5672",
    "sg:postcode":"96002",
    "sg:province":"CA",
    "sg:tags":[
        "landscape"
    ],
    "wof:name":"Wheeler Jeremiah Ldscp & Maint",
    "wof:placetype":"venue"
},
  "geometry": {"coordinates":[-122.333146,40.549645],"type":"Point"}
}