{
  "type": "Feature",
  "properties": {
    "addr:full":"860 S Winchester Blvd San Jose CA 95128",
    "addr:housenumber":"860",
    "addr:postcode":"95128",
    "addr:street":"S Winchester Blvd",
    "iso:country":"US",
    "sg:address":"860 S Winchester Blvd",
    "sg:city":"San Jose",
    "sg:classifiers":[
        {
            "category":"Shopping",
            "subcategory":"Mobile Phones",
            "type":"Retail Goods"
        },
        {
            "category":"Professional",
            "subcategory":"Computer Services",
            "type":"Services"
        }
    ],
    "sg:phone":"+1 408 557 8807",
    "sg:postcode":"95128",
    "sg:province":"CA",
    "sg:tags":[
        "repair"
    ],
    "sg:website":"www.mobilekangaroo.com",
    "wof:name":"Mobile Kangaroo",
    "wof:placetype":"venue"
},
  "geometry": {"coordinates":[-121.94954199999999,37.311784],"type":"Point"}
}