{
  "type": "Feature",
  "properties": {
    "iso:country":"US",
    "sg:address":"1400 Yosemite Pkwy",
    "sg:city":"Merced",
    "sg:classifiers":[
        {
            "category":"Autos & Motor Vehicles",
            "subcategory":"Fuel & Gas Station",
            "type":"Retail Goods"
        },
        {
            "category":"Food & Beverages",
            "subcategory":"Groceries & Convenience Stores",
            "type":"Retail Goods"
        }
    ],
    "sg:phone":"+1 209 723 5146",
    "sg:postcode":"95341",
    "sg:province":"CA",
    "sg:website":"http://www.divi.com",
    "wof:name":"Beacon Ultramar",
    "wof:placetype":"venue"
},
  "geometry": {"coordinates":[-120.45893100000001,37.295212],"type":"Point"}
}