{
  "type": "Feature",
  "properties": {
    "iso:country":"US",
    "sg:address":"221 El Camino del Mar",
    "sg:city":"San Francisco",
    "sg:classifiers":[
        {
            "category":"Health Services",
            "subcategory":"Health Practitioner",
            "type":"Services"
        }
    ],
    "sg:phone":"+1 415 221 6635",
    "sg:postcode":"94121",
    "sg:province":"CA",
    "sg:tags":[
        "naturopathic/holistic"
    ],
    "sg:website":"www.sfhomeopath.com",
    "wof:name":"Renita Herrmann, Classical Homeopath",
    "wof:placetype":"venue"
},
  "geometry": {"coordinates":[-122.48572,37.787345],"type":"Point"}
}