{
  "type": "Feature",
  "properties": {
    "iso:country":"US",
    "sg:address":"150 W Juana Ave",
    "sg:city":"San Leandro",
    "sg:classifiers":[
        {
            "category":"Restaurant",
            "type":"Food & Drink"
        }
    ],
    "sg:phone":"+1 510 895 0880",
    "sg:postcode":"94577",
    "sg:province":"CA",
    "sg:tags":[
        "pizza"
    ],
    "wof:name":"Sergio's Pizzeria",
    "wof:placetype":"venue"
},
  "geometry": {"coordinates":[-122.154999,37.723301],"type":"Point"}
}