{
  "type": "Feature",
  "properties": {
    "addr:full":"4433 El Cajon Blvd San Diego CA 92115",
    "addr:housenumber":"4433",
    "addr:postcode":"92115",
    "addr:street":"El Cajon Blvd",
    "iso:country":"US",
    "sg:address":"4433 El Cajon Blvd",
    "sg:city":"San Diego",
    "sg:classifiers":[
        {
            "category":"Restaurant",
            "type":"Food & Drink"
        }
    ],
    "sg:phone":"+1 619 241 2222",
    "sg:postcode":"92115",
    "sg:province":"CA",
    "sg:tags":[
        "mexican"
    ],
    "wof:name":"Tacos El Panson",
    "wof:placetype":"venue"
},
  "geometry": {"coordinates":[-117.099419,32.754963],"type":"Point"}
}