{
  "type": "Feature",
  "properties": {
    "iso:country":"US",
    "sg:address":"802 Reading St",
    "sg:city":"Folsom",
    "sg:classifiers":[
        {
            "category":"Building & Trades",
            "subcategory":"Construction",
            "type":"Services"
        }
    ],
    "sg:phone":"+1 916 985 5550",
    "sg:postcode":"95630",
    "sg:province":"CA",
    "sg:tags":[
        "builder",
        "stair"
    ],
    "wof:name":"Folsom Trim & Finish",
    "wof:placetype":"venue"
},
  "geometry": {"coordinates":[-121.175109,38.670137],"type":"Point"}
}