{
  "type": "Feature",
  "properties": {
    "iso:country":"US",
    "sg:address":"9718 Glenoaks Blvd",
    "sg:city":"Sun Valley",
    "sg:classifiers":[
        {
            "category":"Shopping",
            "subcategory":"Music",
            "type":"Retail Goods"
        }
    ],
    "sg:phone":"+1 818 768 8720",
    "sg:postcode":"91352",
    "sg:province":"CA",
    "wof:name":"Adult Video Warehouse",
    "wof:placetype":"venue"
},
  "geometry": {"coordinates":[-118.383166,34.245657],"type":"Point"}
}