{
  "type": "Feature",
  "properties": {
    "addr:full":"6528 S Central Ave Los Angeles CA 90001",
    "addr:housenumber":"6528",
    "addr:postcode":"90001",
    "addr:street":"S Central Ave",
    "iso:country":"US",
    "sg:address":"6528 S Central Ave",
    "sg:city":"Los Angeles",
    "sg:classifiers":[
        {
            "category":"Personal",
            "subcategory":"Beauty Salon",
            "type":"Services"
        }
    ],
    "sg:phone":"+1 323 583 2093",
    "sg:postcode":"90001",
    "sg:province":"CA",
    "wof:name":"Skin Care",
    "wof:placetype":"venue"
},
  "geometry": {"coordinates":[-118.256353,33.980242],"type":"Point"}
}