{
  "type": "Feature",
  "properties": {
    "iso:country":"US",
    "sg:address":"42474 Bob Hope Dr",
    "sg:city":"Rancho Mirage",
    "sg:classifiers":[
        {
            "category":"Shopping",
            "subcategory":"Computers & Home Electronics",
            "type":"Retail Goods"
        }
    ],
    "sg:phone":"+1 760 776 1616",
    "sg:postcode":"92270",
    "sg:province":"CA",
    "wof:name":"Rutledge David Audio & Video",
    "wof:placetype":"venue"
},
  "geometry": {"coordinates":[-116.40799699999999,33.738899],"type":"Point"}
}