{
  "type": "Feature",
  "properties": {
    "addr:full":"9170 Rundelay Way Sacramento CA 95826",
    "addr:housenumber":"9170",
    "addr:postcode":"95826",
    "addr:street":"Rundelay Way",
    "iso:country":"US",
    "sg:address":"9170 Rundelay Way",
    "sg:city":"Sacramento",
    "sg:classifiers":[
        {
            "category":"Health Services",
            "subcategory":"Clinic",
            "type":"Services"
        }
    ],
    "sg:phone":"+1 916 369 1179",
    "sg:postcode":"95826",
    "sg:province":"CA",
    "sg:tags":[
        "welfare"
    ],
    "wof:name":"Tammys Medical Billing",
    "wof:placetype":"venue"
},
  "geometry": {"coordinates":[-121.35854399999999,38.554315],"type":"Point"}
}