{
  "type": "Feature",
  "properties": {
    "iso:country":"US",
    "sg:address":"5140 N Fruit Ave",
    "sg:city":"Fresno",
    "sg:classifiers":[
        {
            "category":"Organizations",
            "subcategory":"Religious Organization",
            "type":"Services"
        }
    ],
    "sg:phone":"+1 559 225 2092",
    "sg:postcode":"93711",
    "sg:province":"CA",
    "sg:tags":[
        "church"
    ],
    "sg:website":"www.goodshepherdfresno.org",
    "wof:name":"Good Shepherd Lutheran CHR",
    "wof:placetype":"venue"
},
  "geometry": {"coordinates":[-119.817329,36.810977],"type":"Point"}
}