{
  "type": "Feature",
  "properties": {
    "iso:country":"US",
    "sg:address":"15 San Antonio Place",
    "sg:city":"San Francisco",
    "sg:classifiers":[
        {
            "category":"Professional",
            "type":"Services"
        },
        {
            "category":"Education",
            "subcategory":"Special Training",
            "type":"Public Place"
        }
    ],
    "sg:phone":"+1 415 839 8668",
    "sg:postcode":"94133",
    "sg:province":"CA",
    "sg:tags":[
        "school",
        "specialty"
    ],
    "sg:website":"www.motifsf.com",
    "wof:name":"Motif Lifestyle Consultancy",
    "wof:placetype":"venue"
},
  "geometry": {"coordinates":[-122.406358,37.799302],"type":"Point"}
}