{
  "type": "Feature",
  "properties": {
    "addr:full":"121 Starfish Way Crescent City CA 95531",
    "addr:housenumber":"121",
    "addr:postcode":"95531",
    "addr:street":"Starfish Way Crescent",
    "iso:country":"US",
    "sg:address":"121 Starfish Way",
    "sg:city":"Crescent City",
    "sg:classifiers":[
        {
            "category":"Recreation",
            "subcategory":"Marina",
            "type":"Entertainment"
        }
    ],
    "sg:phone":"+1 707 464 9219",
    "sg:postcode":"95531",
    "sg:province":"CA",
    "sg:tags":[
        "repairing",
        "boat"
    ],
    "wof:name":"Fashion Blacksmith Inc",
    "wof:placetype":"venue"
},
  "geometry": {"coordinates":[-124.18178899999999,41.747214],"type":"Point"}
}