{
  "type": "Feature",
  "properties": {
    "addr:full":"7902 Gerber Rd Sacramento CA 95828",
    "addr:housenumber":"7902",
    "addr:postcode":"95828",
    "addr:street":"Gerber Rd",
    "iso:country":"US",
    "sg:address":"7902 Gerber Rd",
    "sg:city":"Sacramento",
    "sg:classifiers":[
        {
            "category":"Retail",
            "subcategory":"Portrait Studio",
            "type":"Services"
        }
    ],
    "sg:phone":"+1 916 203 4198",
    "sg:postcode":"95828",
    "sg:province":"CA",
    "sg:tags":[
        "photographer",
        "wedding"
    ],
    "wof:name":"Dave Hammel Photography",
    "wof:placetype":"venue"
},
  "geometry": {"coordinates":[-121.409023,38.481616],"type":"Point"}
}