{
  "type": "Feature",
  "properties": {
    "addr:full":"7271 E Slauson Ave Commerce CA 90040",
    "addr:housenumber":"7271",
    "addr:postcode":"90040",
    "addr:street":"E Slauson Ave",
    "iso:country":"US",
    "sg:address":"7271 E Slauson Ave",
    "sg:city":"Commerce",
    "sg:classifiers":[
        {
            "category":"Wholesale",
            "subcategory":"Home Furnishings",
            "type":"Manufacturing & Wholesale Goods"
        }
    ],
    "sg:phone":"+1 323 724 6087",
    "sg:postcode":"90040",
    "sg:province":"CA",
    "sg:tags":[
        "plumbing",
        "supplies-wholesale",
        "part",
        "fixture",
        "manufacturer"
    ],
    "sg:website":"http://www.carrhill.com",
    "wof:name":"Carrhill Co.",
    "wof:placetype":"venue"
},
  "geometry": {"coordinates":[-118.133197,33.978638],"type":"Point"}
}