{
  "type": "Feature",
  "properties": {
    "addr:full":"3344 S Fairway St Visalia CA 93277",
    "addr:housenumber":"3344",
    "addr:postcode":"93277",
    "addr:street":"S Fairway St",
    "iso:country":"US",
    "sg:address":"3344 S Fairway St",
    "sg:city":"Visalia",
    "sg:classifiers":[
        {
            "category":"Professional",
            "subcategory":"Business Services",
            "type":"Services"
        }
    ],
    "sg:phone":"+1 559 732 1481",
    "sg:postcode":"93277",
    "sg:province":"CA",
    "sg:tags":[
        "interior",
        "consultant",
        "design",
        "decorator"
    ],
    "wof:name":"Creating Interiors",
    "wof:placetype":"venue"
},
  "geometry": {"coordinates":[-119.31067299999999,36.30098],"type":"Point"}
}