{
  "type": "Feature",
  "properties": {
    "iso:country":"US",
    "sg:address":"30955 Huntwood Ave",
    "sg:city":"Hayward",
    "sg:classifiers":[
        {
            "category":"Professional",
            "type":"Services"
        }
    ],
    "sg:phone":"+1 510 489 6800",
    "sg:postcode":"94544",
    "sg:province":"CA",
    "wof:name":"Rate Pak Dept",
    "wof:placetype":"venue"
},
  "geometry": {"coordinates":[-122.054923,37.616106],"type":"Point"}
}