{
  "type": "Feature",
  "properties": {
    "iso:country":"US",
    "sg:address":"24338 el Toro Rd",
    "sg:city":"Laguna Woods",
    "sg:classifiers":[
        {
            "category":"Restaurant",
            "type":"Food & Drink"
        }
    ],
    "sg:phone":"+1 949 830 3000",
    "sg:postcode":"92637",
    "sg:province":"CA",
    "wof:name":"Domino's Pizza",
    "wof:placetype":"venue"
},
  "geometry": {"coordinates":[-117.729297,33.609077],"type":"Point"}
}