{
  "type": "Feature",
  "properties": {
    "iso:country":"US",
    "sg:address":"2307 Levante St",
    "sg:city":"Carlsbad",
    "sg:classifiers":[
        {
            "category":"Communications",
            "type":"Services"
        }
    ],
    "sg:phone":"+1 760 944 4517",
    "sg:postcode":"92009",
    "sg:province":"CA",
    "wof:name":"North County Voice",
    "wof:placetype":"venue"
},
  "geometry": {"coordinates":[-117.257599,33.084509],"type":"Point"}
}