{
  "type": "Feature",
  "properties": {
    "iso:country":"US",
    "sg:address":"1519 Palma Dr",
    "sg:city":"Ventura",
    "sg:classifiers":[
        {
            "category":"Professional",
            "subcategory":"Business Services",
            "type":"Services"
        }
    ],
    "sg:phone":"+1 805 642 9609",
    "sg:postcode":"93003",
    "sg:province":"CA",
    "sg:tags":[
        "specialty",
        "mfg"
    ],
    "wof:name":"Ventura Signs",
    "wof:placetype":"venue"
},
  "geometry": {"coordinates":[-119.227509,34.258376],"type":"Point"}
}