{
  "type": "Feature",
  "properties": {
    "iso:country":"US",
    "sg:address":"1624 Franklin St Ste 520",
    "sg:city":"Oakland",
    "sg:classifiers":[
        {
            "category":"Health Services",
            "subcategory":"Doctor",
            "type":"Services"
        }
    ],
    "sg:phone":"+1 510 893 2089",
    "sg:postcode":"94612",
    "sg:province":"CA",
    "sg:tags":[
        "surgeon",
        "oral"
    ],
    "sg:website":"www.smilesolutionsdrliu.com/",
    "wof:name":"Aimin Liu, DDS",
    "wof:placetype":"venue"
},
  "geometry": {"coordinates":[-122.268292,37.805837],"type":"Point"}
}