{
  "type": "Feature",
  "properties": {
    "iso:country":"US",
    "sg:address":"13661 Hilford Ln",
    "sg:city":"Redding",
    "sg:classifiers":[
        {
            "category":"Communications",
            "type":"Services"
        }
    ],
    "sg:phone":"+1 530 275 3610",
    "sg:postcode":"96003",
    "sg:province":"CA",
    "sg:tags":[
        "communication"
    ],
    "wof:name":"Abate Communications",
    "wof:placetype":"venue"
},
  "geometry": {"coordinates":[-122.280538,40.687949],"type":"Point"}
}