{
  "type": "Feature",
  "properties": {
    "addr:full":"148 Noe St San Francisco CA 94199",
    "addr:housenumber":"148",
    "addr:postcode":"94199",
    "addr:street":"Noe St",
    "iso:country":"US",
    "sg:address":"148 Noe St",
    "sg:city":"San Francisco",
    "sg:classifiers":[
        {
            "category":"Community Center",
            "type":"Public Place"
        }
    ],
    "sg:phone":"+1 415 487 8960",
    "sg:postcode":"94199",
    "sg:province":"CA",
    "sg:tags":[
        "medical"
    ],
    "wof:name":"Stanford University Medical Center Blood Lab",
    "wof:placetype":"venue"
},
  "geometry": {"coordinates":[-122.43336499999999,37.766713],"type":"Point"}
}