{
  "type": "Feature",
  "properties": {
    "addr:full":"22138 S Vermont Ave Torrance CA 90502",
    "addr:housenumber":"22138",
    "addr:postcode":"90502",
    "addr:street":"S Vermont Ave",
    "iso:country":"US",
    "sg:address":"22138 S Vermont Ave",
    "sg:city":"Torrance",
    "sg:classifiers":[
        {
            "category":"Building & Trades",
            "subcategory":"Construction",
            "type":"Services"
        }
    ],
    "sg:phone":"+1 310 533 4900",
    "sg:postcode":"90502",
    "sg:province":"CA",
    "sg:tags":[
        "maker",
        "cabinet"
    ],
    "wof:name":"Custom Design",
    "wof:placetype":"venue"
},
  "geometry": {"coordinates":[-118.290192,33.827918],"type":"Point"}
}