{
  "type": "Feature",
  "properties": {
    "addr:full":"826 N Clybourn Ave Burbank CA 91505",
    "addr:housenumber":"826",
    "addr:postcode":"91505",
    "addr:street":"N Clybourn Ave",
    "iso:country":"US",
    "sg:address":"826 N Clybourn Ave",
    "sg:city":"Burbank",
    "sg:classifiers":[
        {
            "category":"Building & Trades",
            "subcategory":"Equipment Rental",
            "type":"Services"
        },
        {
            "category":"Shopping",
            "subcategory":"Computers & Home Electronics",
            "type":"Retail Goods"
        }
    ],
    "sg:phone":"+1 818 556 6267",
    "sg:postcode":"91505",
    "sg:province":"CA",
    "sg:tags":[
        "sound",
        "audio-visual",
        "leasing",
        "system",
        "equipment-renting"
    ],
    "wof:name":"Bruin Grip Service",
    "wof:placetype":"venue"
},
  "geometry": {"coordinates":[-118.35356899999999,34.162301],"type":"Point"}
}