{
  "type": "Feature",
  "properties": {
    "addr:full":"43535 17th St W Lancaster CA 93534",
    "addr:housenumber":"43535",
    "addr:postcode":"93534",
    "addr:street":"17Th St W",
    "iso:country":"US",
    "sg:address":"43535 17th St W",
    "sg:city":"Lancaster",
    "sg:classifiers":[
        {
            "category":"Personal",
            "subcategory":"Massage",
            "type":"Services"
        },
        {
            "category":"Health Services",
            "subcategory":"Health Practitioner",
            "type":"Services"
        }
    ],
    "sg:phone":"+1 661 723 1200",
    "sg:postcode":"93534",
    "sg:province":"CA",
    "sg:tags":[
        "holistic",
        "therapist"
    ],
    "sg:website":"http://www.avholistic.com",
    "wof:name":"Holistic Healing Massage Therapy & Reiki Center",
    "wof:placetype":"venue"
},
  "geometry": {"coordinates":[-118.161248,34.673564],"type":"Point"}
}