{
  "type": "Feature",
  "properties": {
    "iso:country":"US",
    "sg:address":"12157 Paramount Blvd",
    "sg:city":"Downey",
    "sg:classifiers":[
        {
            "category":"Wholesale",
            "subcategory":"Stationery",
            "type":"Manufacturing & Wholesale Goods"
        }
    ],
    "sg:phone":"+1 562 869 1801",
    "sg:postcode":"90242",
    "sg:province":"CA",
    "sg:tags":[
        "school",
        "supply"
    ],
    "wof:name":"A Touch Of Classroom",
    "wof:placetype":"venue"
},
  "geometry": {"coordinates":[-118.14696600000001,33.930806],"type":"Point"}
}