{
  "type": "Feature",
  "properties": {
    "addr:full":"19 E Live Oak Ave Arcadia CA 91006",
    "addr:housenumber":"19",
    "addr:postcode":"91006",
    "addr:street":"E Live Oak Ave",
    "iso:country":"US",
    "sg:address":"19 E Live Oak Ave",
    "sg:city":"Arcadia",
    "sg:classifiers":[
        {
            "category":"Professional",
            "type":"Services"
        }
    ],
    "sg:phone":"+1 626 821 0097",
    "sg:postcode":"91006",
    "sg:province":"CA",
    "wof:name":"Silverstone Direct",
    "wof:placetype":"venue"
},
  "geometry": {"coordinates":[-118.03008800000001,34.107469],"type":"Point"}
}