{
  "type": "Feature",
  "properties": {
    "addr:full":"340 E Canal Dr Turlock CA 95380",
    "addr:housenumber":"340",
    "addr:postcode":"95380",
    "addr:street":"E Canal Dr",
    "iso:country":"US",
    "sg:address":"340 E Canal Dr",
    "sg:city":"Turlock",
    "sg:classifiers":[
        {
            "category":"Personal",
            "type":"Services"
        }
    ],
    "sg:phone":"+1 209 614 4391",
    "sg:postcode":"95380",
    "sg:province":"CA",
    "sg:tags":[
        "therapist",
        "massage"
    ],
    "wof:name":"Kaye's Electrology & Massage",
    "wof:placetype":"venue"
},
  "geometry": {"coordinates":[-120.84407400000001,37.50021],"type":"Point"}
}