{
  "type": "Feature",
  "properties": {
    "addr:full":"10295 Carey Dr Grass Valley CA 95945",
    "addr:housenumber":"10295",
    "addr:postcode":"95945",
    "addr:street":"Carey Dr",
    "iso:country":"US",
    "sg:address":"10295 Carey Dr",
    "sg:city":"Grass Valley",
    "sg:classifiers":[
        {
            "category":"Shopping",
            "subcategory":"Clothing, Apparel, & Fashions",
            "type":"Retail Goods"
        }
    ],
    "sg:phone":"+1 530 273 4130",
    "sg:postcode":"95945",
    "sg:province":"CA",
    "sg:tags":[
        "theatrical",
        "costume"
    ],
    "wof:name":"Gold River Costumes",
    "wof:placetype":"venue"
},
  "geometry": {"coordinates":[-121.075632,39.229878],"type":"Point"}
}