{
  "type": "Feature",
  "properties": {
    "addr:full":"2525 E Plaza Blvd National City CA 91950",
    "addr:housenumber":"2525",
    "addr:postcode":"91950",
    "addr:street":"E Plaza Blvd",
    "iso:country":"US",
    "sg:address":"2525 E Plaza Blvd",
    "sg:city":"National City",
    "sg:classifiers":[
        {
            "category":"Cinema",
            "subcategory":"Movie Theater",
            "type":"Entertainment"
        }
    ],
    "sg:phone":"+1 619 470 7240",
    "sg:postcode":"91950",
    "sg:province":"CA",
    "wof:name":"Blockbuster Video",
    "wof:placetype":"venue"
},
  "geometry": {"coordinates":[-117.08000199999999,32.68],"type":"Point"}
}