{
  "type": "Feature",
  "properties": {
    "addr:full":"136 1/2 Vernon St Santa Cruz CA 95060",
    "addr:housenumber":"136 1 / 2",
    "addr:postcode":"95060",
    "addr:street":"Vernon St",
    "iso:country":"US",
    "sg:address":"136 1/2 Vernon St",
    "sg:city":"Santa Cruz",
    "sg:classifiers":[
        {
            "category":"Retail",
            "subcategory":"Pet Boarding",
            "type":"Services"
        }
    ],
    "sg:phone":"+1 831 427 2287",
    "sg:postcode":"95060",
    "sg:province":"CA",
    "sg:tags":[
        "boarding/pet",
        "sitting"
    ],
    "sg:website":"www.kittyhillresort.com",
    "wof:name":"Kitty Hill Resort for Cats",
    "wof:placetype":"venue"
},
  "geometry": {"coordinates":[-122.03254699999999,36.990574],"type":"Point"}
}