{
  "type": "Feature",
  "properties": {
    "addr:full":"210 E Jefferson Ave Pomona CA 91767",
    "addr:housenumber":"210",
    "addr:postcode":"91767",
    "addr:street":"E Jefferson Ave",
    "iso:country":"US",
    "sg:address":"210 E Jefferson Ave",
    "sg:city":"Pomona",
    "sg:classifiers":[
        {
            "category":"Wholesale",
            "subcategory":"Auto Parts",
            "type":"Manufacturing & Wholesale Goods"
        }
    ],
    "sg:phone":"+1 909 629 6651",
    "sg:postcode":"91767",
    "sg:province":"CA",
    "sg:tags":[
        "retail",
        "export"
    ],
    "wof:name":"CSI",
    "wof:placetype":"venue"
},
  "geometry": {"coordinates":[-117.748186,34.069643],"type":"Point"}
}