{
  "type": "Feature",
  "properties": {
    "iso:country":"US",
    "sg:address":"1301 Ashland Ave",
    "sg:city":"Santa Monica",
    "sg:classifiers":[
        {
            "category":"Wholesale",
            "subcategory":"Construction Materials",
            "type":"Manufacturing & Wholesale Goods"
        }
    ],
    "sg:phone":"+1 626 446 1823",
    "sg:postcode":"90405",
    "sg:province":"CA",
    "sg:tags":[
        "equipment",
        "supply"
    ],
    "wof:name":"Laura Park Inc",
    "wof:placetype":"venue"
},
  "geometry": {"coordinates":[-118.467918,34.008207],"type":"Point"}
}