{
  "type": "Feature",
  "properties": {
    "addr:full":"225 Brooks St Oceanside CA 92054",
    "addr:housenumber":"225",
    "addr:postcode":"92054",
    "addr:street":"Brooks St",
    "iso:country":"US",
    "sg:address":"225 Brooks St",
    "sg:city":"Oceanside",
    "sg:classifiers":[
        {
            "category":"Sports & Exercise",
            "subcategory":"Bicycle Rental",
            "type":"Entertainment"
        }
    ],
    "sg:phone":"+1 760 722 7826",
    "sg:postcode":"92054",
    "sg:province":"CA",
    "sg:tags":[
        "wear"
    ],
    "sg:website":"www.usascuba.com",
    "wof:name":"Underwater Schools of America",
    "wof:placetype":"venue"
},
  "geometry": {"coordinates":[-117.36799600000001,33.198101],"type":"Point"}
}