{
  "type": "Feature",
  "properties": {
    "iso:country":"US",
    "sg:address":"4660 La Jolla Village Drive",
    "sg:city":"San Diego",
    "sg:classifiers":[
        {
            "category":"Professional",
            "subcategory":"Accounting & Tax Preparation",
            "type":"Services"
        }
    ],
    "sg:phone":"+1 858 452 4300",
    "sg:postcode":"92122",
    "sg:province":"CA",
    "sg:tags":[
        "accountant"
    ],
    "wof:name":"Nasella Lawrence J CPA",
    "wof:placetype":"venue"
},
  "geometry": {"coordinates":[-117.20657300000001,32.874229],"type":"Point"}
}