{
  "type": "Feature",
  "properties": {
    "addr:full":"4665 Clayton Rd Concord CA 94521",
    "addr:housenumber":"4665",
    "addr:postcode":"94521",
    "addr:street":"Clayton Rd",
    "iso:country":"US",
    "sg:address":"4665 Clayton Rd",
    "sg:city":"Concord",
    "sg:classifiers":[
        {
            "category":"Shopping",
            "subcategory":"Department Store",
            "type":"Retail Goods"
        },
        {
            "category":"Shopping",
            "subcategory":"Discount & Variety Stores",
            "type":"Retail Goods"
        }
    ],
    "sg:phone":"+1 925 674 9799",
    "sg:postcode":"94521",
    "sg:province":"CA",
    "sg:website":"http://www.bargainw.com",
    "wof:name":"99 Cents Only Stores",
    "wof:placetype":"venue"
},
  "geometry": {"coordinates":[-121.98374200000001,37.96167],"type":"Point"}
}