{
  "type": "Feature",
  "properties": {
    "addr:full":"204 S Rosemead Blvd Pasadena CA 91107",
    "addr:housenumber":"204",
    "addr:postcode":"91107",
    "addr:street":"S Rosemead Blvd",
    "iso:country":"US",
    "sg:address":"204 S Rosemead Blvd",
    "sg:city":"Pasadena",
    "sg:classifiers":[
        {
            "category":"Building & Trades",
            "subcategory":"Plumbing",
            "type":"Services"
        }
    ],
    "sg:phone":"+1 626 446 8844",
    "sg:postcode":"91107",
    "sg:province":"CA",
    "sg:tags":[
        "system",
        "heating",
        "contractor",
        "air conditioning",
        "conditioning/hvac"
    ],
    "sg:website":"www.airtechac1.com/",
    "wof:name":"Air-Tech Heating & Air Conditioning Inc",
    "wof:placetype":"venue"
},
  "geometry": {"coordinates":[-118.072998,34.1427],"type":"Point"}
}