{
  "type": "Feature",
  "properties": {
    "addr:full":"125 N Jackson Avenue San Jose CA 95116",
    "addr:housenumber":"125",
    "addr:postcode":"95116",
    "addr:street":"N Jackson Avenue",
    "iso:country":"US",
    "sg:address":"125 N Jackson Avenue",
    "sg:city":"San Jose",
    "sg:classifiers":[
        {
            "category":"Health Services",
            "subcategory":"Doctor",
            "type":"Services"
        },
        {
            "category":"Health Services",
            "subcategory":"Health Practitioner",
            "type":"Services"
        }
    ],
    "sg:phone":"+1 408 937 3999",
    "sg:postcode":"95116",
    "sg:province":"CA",
    "sg:tags":[
        "therapy",
        "physical"
    ],
    "wof:name":"Jackson Medical Therapy",
    "wof:placetype":"venue"
},
  "geometry": {"coordinates":[-121.84653400000001,37.361537],"type":"Point"}
}