{
  "type": "Feature",
  "properties": {
    "iso:country":"US",
    "sg:address":"12620 Brookhurst St",
    "sg:city":"Garden Grove",
    "sg:classifiers":[
        {
            "category":"Professional",
            "subcategory":"Lawyer & Legal Services",
            "type":"Services"
        }
    ],
    "sg:phone":"+1 714 530 5030",
    "sg:postcode":"92840",
    "sg:province":"CA",
    "sg:tags":[
        "attorney"
    ],
    "wof:name":"Gerald Block",
    "wof:placetype":"venue"
},
  "geometry": {"coordinates":[-117.95847999999999,33.7813],"type":"Point"}
}