{
  "type": "Feature",
  "properties": {
    "iso:country":"US",
    "sg:address":"1515 W 7th St",
    "sg:city":"Los Angeles",
    "sg:classifiers":[
        {
            "category":"Manufacturing",
            "subcategory":"Printing",
            "type":"Manufacturing & Wholesale Goods"
        }
    ],
    "sg:phone":"+1 213 483 9424",
    "sg:postcode":"90017",
    "sg:province":"CA",
    "sg:tags":[
        "lithographic",
        "commercial"
    ],
    "wof:name":"Active Graphics",
    "wof:placetype":"venue"
},
  "geometry": {"coordinates":[-118.270895,34.053845],"type":"Point"}
}