{
  "type": "Feature",
  "properties": {
    "addr:full":"160 N Linden Ave Rialto CA 92376",
    "addr:housenumber":"160",
    "addr:postcode":"92376",
    "addr:street":"N Linden Ave",
    "iso:country":"US",
    "sg:address":"160 N Linden Ave",
    "sg:city":"Rialto",
    "sg:classifiers":[
        {
            "category":"Real Estate",
            "subcategory":"Real Estate Operator",
            "type":"Services"
        }
    ],
    "sg:phone":"+1 909 357 2920",
    "sg:postcode":"92376",
    "sg:province":"CA",
    "sg:tags":[
        "apartment"
    ],
    "wof:name":"Las Palmas Apartments",
    "wof:placetype":"venue"
},
  "geometry": {"coordinates":[-117.512387,34.948123],"type":"Point"}
}