{
  "type": "Feature",
  "properties": {
    "iso:country":"US",
    "sg:address":"3120 Freeboard Dr",
    "sg:city":"West Sacramento",
    "sg:classifiers":[
        {
            "category":"Real Estate",
            "subcategory":"Real Estate Agent",
            "type":"Services"
        }
    ],
    "sg:phone":"+1 916 414 4400",
    "sg:postcode":"95691",
    "sg:province":"CA",
    "sg:tags":[
        "authorities",
        "housing"
    ],
    "wof:name":"Mercy Housing California",
    "wof:placetype":"venue"
},
  "geometry": {"coordinates":[-121.552044,38.574587],"type":"Point"}
}