{
  "type": "Feature",
  "properties": {
    "iso:country":"US",
    "sg:address":"1525 N Main St",
    "sg:city":"Walnut Creek",
    "sg:classifiers":[
        {
            "category":"Restaurant",
            "type":"Food & Drink"
        }
    ],
    "sg:menulink":"http://www.allmenus.com/ca/central-contra-costa/58739-the-san-franciscan/menu/",
    "sg:phone":"+1 925 934 4831",
    "sg:postcode":"94596",
    "sg:province":"CA",
    "sg:tags":[
        "american",
        "californian"
    ],
    "wof:name":"The San Franciscan",
    "wof:placetype":"venue"
},
  "geometry": {"coordinates":[-122.06108999999999,37.900186],"type":"Point"}
}