{
  "type": "Feature",
  "properties": {
    "iso:country":"US",
    "sg:address":"3755 E Olympic Blvd",
    "sg:city":"Los Angeles",
    "sg:classifiers":[
        {
            "category":"Manufacturing",
            "subcategory":"Tools & Machinery",
            "type":"Manufacturing & Wholesale Goods"
        }
    ],
    "sg:phone":"+1 323 265 3097",
    "sg:postcode":"90023",
    "sg:province":"CA",
    "sg:tags":[
        "industrial",
        "mfg"
    ],
    "wof:name":"Precision Volkswagen",
    "wof:placetype":"venue"
},
  "geometry": {"coordinates":[-118.193387,34.018934],"type":"Point"}
}