{
  "type": "Feature",
  "properties": {
    "addr:full":"10332 Wallavista Rd Los Angeles CA 90064",
    "addr:housenumber":"10332",
    "addr:postcode":"90064",
    "addr:street":"Wallavista Rd",
    "iso:country":"US",
    "sg:address":"10332 Wallavista Rd",
    "sg:city":"Los Angeles",
    "sg:classifiers":[
        {
            "category":"Wholesale",
            "subcategory":"Non-durable Goods",
            "type":"Manufacturing & Wholesale Goods"
        }
    ],
    "sg:phone":"+1 310 838 3979",
    "sg:postcode":"90064",
    "sg:province":"CA",
    "sg:tags":[
        "store",
        "variety"
    ],
    "wof:name":"Yorkie Specialties",
    "wof:placetype":"venue"
},
  "geometry": {"coordinates":[-118.41216,34.032065],"type":"Point"}
}