{
  "type": "Feature",
  "properties": {
    "iso:country":"US",
    "sg:address":"8799 Elk Grove Blvd",
    "sg:city":"Elk Grove",
    "sg:classifiers":[
        {
            "category":"Banks & Credit Unions",
            "subcategory":"Bank",
            "type":"Services"
        }
    ],
    "sg:phone":"+1 916 394 3200",
    "sg:postcode":"95624",
    "sg:province":"CA",
    "sg:tags":[
        "state",
        "commercial",
        "national"
    ],
    "wof:name":"Farmers Insurance",
    "wof:placetype":"venue"
},
  "geometry": {"coordinates":[-121.377557,38.408989],"type":"Point"}
}