{
  "type": "Feature",
  "properties": {
    "addr:full":"8713 Oranmore Ct Sacramento CA 95828",
    "addr:postcode":"8713;95828",
    "addr:street":"Oranmore Ct",
    "iso:country":"US",
    "sg:address":"8713 Oranmore Ct",
    "sg:city":"Sacramento",
    "sg:classifiers":[
        {
            "category":"Wholesale",
            "subcategory":"Jewelry",
            "type":"Manufacturing & Wholesale Goods"
        }
    ],
    "sg:phone":"+1 916 769 1234",
    "sg:postcode":"95828",
    "sg:province":"CA",
    "sg:tags":[
        "stone"
    ],
    "wof:name":"First Place Sports & Awards",
    "wof:placetype":"venue"
},
  "geometry": {"coordinates":[-121.38086699999999,38.455791],"type":"Point"}
}