{
  "type": "Feature",
  "properties": {
    "iso:country":"US",
    "sg:address":"2763 Explorer Way",
    "sg:city":"Turlock",
    "sg:classifiers":[
        {
            "category":"Social Services",
            "subcategory":"Child Care",
            "type":"Services"
        }
    ],
    "sg:phone":"+1 209 669 8191",
    "sg:postcode":"95382",
    "sg:province":"CA",
    "wof:name":"Blossom Day Care",
    "wof:placetype":"venue"
},
  "geometry": {"coordinates":[-120.87857099999999,37.528558],"type":"Point"}
}