{
  "type": "Feature",
  "properties": {
    "addr:full":"25 Cadillac Dr Sacramento CA 95825",
    "addr:housenumber":"25",
    "addr:postcode":"95825",
    "addr:street":"Cadillac Dr",
    "iso:country":"US",
    "sg:address":"25 Cadillac Dr",
    "sg:city":"Sacramento",
    "sg:classifiers":[
        {
            "category":"Shopping",
            "subcategory":"Hobbies, Toys, & Games",
            "type":"Retail Goods"
        }
    ],
    "sg:phone":"+1 916 648 1676",
    "sg:postcode":"95825",
    "sg:province":"CA",
    "sg:tags":[
        "toy",
        "store",
        "supply"
    ],
    "wof:name":"Sitecom Inc",
    "wof:placetype":"venue"
},
  "geometry": {"coordinates":[-121.41851,38.57451],"type":"Point"}
}