{
  "type": "Feature",
  "properties": {
    "iso:country":"US",
    "sg:address":"165 N Redwood Dr",
    "sg:city":"San Rafael",
    "sg:classifiers":[
        {
            "category":"Freight",
            "type":"Transportation"
        }
    ],
    "sg:phone":"+1 415 499 3149",
    "sg:postcode":"94903",
    "sg:province":"CA",
    "sg:tags":[
        "forwarding",
        "export"
    ],
    "wof:name":"Ohanneson Freight Forwarding",
    "wof:placetype":"venue"
},
  "geometry": {"coordinates":[-122.535839,38.024205],"type":"Point"}
}