{
  "type": "Feature",
  "properties": {
    "addr:full":"2625 W Alameda Ave Ste 420 Burbank CA 91505",
    "addr:housenumber":"2625",
    "addr:postcode":"91505",
    "addr:street":"W Alameda Ave Ste 420",
    "iso:country":"US",
    "sg:address":"2625 W Alameda Ave Ste 420",
    "sg:city":"Burbank",
    "sg:classifiers":[
        {
            "category":"Health Services",
            "subcategory":"Doctor",
            "type":"Services"
        }
    ],
    "sg:phone":"+1 818 955 7788",
    "sg:postcode":"91505",
    "sg:province":"CA",
    "sg:tags":[
        "surgeon",
        "oral"
    ],
    "sg:website":"www.alexdds.com",
    "wof:name":"Alexandre HK Tavitian DDS",
    "wof:placetype":"venue"
},
  "geometry": {"coordinates":[-118.329002,34.157799],"type":"Point"}
}