{
  "type": "Feature",
  "properties": {
    "addr:full":"23501 White Dove Dr Lake Forest CA 92630",
    "addr:housenumber":"23501",
    "addr:postcode":"92630",
    "addr:street":"White Dove Dr",
    "iso:country":"US",
    "sg:address":"23501 White Dove Dr",
    "sg:city":"Lake Forest",
    "sg:classifiers":[
        {
            "category":"Professional",
            "type":"Services"
        }
    ],
    "sg:phone":"+1 949 305 5883",
    "sg:postcode":"92630",
    "sg:province":"CA",
    "wof:name":"Dosa Hut of India",
    "wof:placetype":"venue"
},
  "geometry": {"coordinates":[-117.71194300000001,33.621068],"type":"Point"}
}