{
  "type": "Feature",
  "properties": {
    "iso:country":"US",
    "sg:address":"1300 Fairmont Dr",
    "sg:city":"San Leandro",
    "sg:classifiers":[
        {
            "category":"Food & Beverages",
            "subcategory":"Groceries & Convenience Stores",
            "type":"Retail Goods"
        }
    ],
    "sg:phone":"+1 510 276 6905",
    "sg:postcode":"94578",
    "sg:province":"CA",
    "sg:website":"www.luckysupermarkets.com",
    "wof:name":"Lucky Supermarket",
    "wof:placetype":"venue"
},
  "geometry": {"coordinates":[-122.126999,37.702099],"type":"Point"}
}