{
  "type": "Feature",
  "properties": {
    "iso:country":"US",
    "sg:address":"1035 Murray St",
    "sg:city":"Berkeley",
    "sg:classifiers":[
        {
            "category":"Home & Garden",
            "subcategory":"Building Materials",
            "type":"Retail Goods"
        }
    ],
    "sg:phone":"+1 510 843 3334",
    "sg:postcode":"94710",
    "sg:province":"CA",
    "sg:tags":[
        "shower",
        "door",
        "enclosure",
        "supply"
    ],
    "sg:website":"www.wilsonglass.com",
    "wof:name":"Wilson Glass",
    "wof:placetype":"venue"
},
  "geometry": {"coordinates":[-122.288146,37.851413],"type":"Point"}
}