{
  "type": "Feature",
  "properties": {
    "addr:full":"823 Sutter St Folsom CA 95630",
    "addr:housenumber":"823",
    "addr:postcode":"95630",
    "addr:street":"Sutter St",
    "iso:country":"US",
    "sg:address":"823 Sutter St",
    "sg:city":"Folsom",
    "sg:classifiers":[
        {
            "category":"Museum",
            "type":"Entertainment"
        }
    ],
    "sg:phone":"+1 916 985 2707",
    "sg:postcode":"95630",
    "sg:province":"CA",
    "sg:website":"www.folsomhistorymuseum.org",
    "wof:name":"Folsom History Museum",
    "wof:placetype":"venue"
},
  "geometry": {"coordinates":[-121.17876800000001,38.676356],"type":"Point"}
}