{
  "type": "Feature",
  "properties": {
    "addr:full":"5711 Schaefer Ave Chino CA 91710",
    "addr:housenumber":"5711",
    "addr:postcode":"91710",
    "addr:street":"Schaefer Ave",
    "iso:country":"US",
    "sg:address":"5711 Schaefer Ave",
    "sg:city":"Chino",
    "sg:classifiers":[
        {
            "category":"Building & Trades",
            "subcategory":"Plumbing",
            "type":"Services"
        }
    ],
    "sg:phone":"+1 909 590 0644",
    "sg:postcode":"91710",
    "sg:province":"CA",
    "sg:tags":[
        "conditioning",
        "air",
        "system",
        "contractor"
    ],
    "wof:name":"Diamond Air",
    "wof:placetype":"venue"
},
  "geometry": {"coordinates":[-117.67649299999999,34.004561],"type":"Point"}
}