{
  "type": "Feature",
  "properties": {
    "addr:full":"5624 Lankershim Blvd North Hollywood CA 91601",
    "addr:postcode":"5624;91601",
    "addr:street":"Lankershim Blvd",
    "iso:country":"US",
    "sg:address":"5624 Lankershim Blvd",
    "sg:city":"North Hollywood",
    "sg:classifiers":[
        {
            "category":"Government",
            "subcategory":"Office",
            "type":"Public Place"
        }
    ],
    "sg:phone":"+1 818 997 7879",
    "sg:postcode":"91601",
    "sg:province":"CA",
    "sg:tags":[
        "state",
        "program",
        "health"
    ],
    "wof:name":"Affirmative Health Care",
    "wof:placetype":"venue"
},
  "geometry": {"coordinates":[-118.379828,34.173562],"type":"Point"}
}