{
  "type": "Feature",
  "properties": {
    "addr:full":"1117 W Robert Ave Ridgecrest CA 93555",
    "addr:housenumber":"1117",
    "addr:postcode":"93555",
    "addr:street":"W Robert Ave",
    "iso:country":"US",
    "sg:address":"1117 W Robert Ave",
    "sg:city":"Ridgecrest",
    "sg:classifiers":[
        {
            "category":"Wholesale",
            "subcategory":"Groceries",
            "type":"Manufacturing & Wholesale Goods"
        }
    ],
    "sg:phone":"+1 760 375 2499",
    "sg:postcode":"93555",
    "sg:province":"CA",
    "sg:tags":[
        "nutritional",
        "supply"
    ],
    "wof:name":"Over Edge Enterprises Inc",
    "wof:placetype":"venue"
},
  "geometry": {"coordinates":[-117.693984,35.634694],"type":"Point"}
}