{
  "type": "Feature",
  "properties": {
    "addr:full":"15660 Rockwell Ave Fontana CA 92336",
    "addr:housenumber":"15660",
    "addr:postcode":"92336",
    "addr:street":"Rockwell Ave",
    "iso:country":"US",
    "sg:address":"15660 Rockwell Ave",
    "sg:city":"Fontana",
    "sg:classifiers":[
        {
            "category":"Retail",
            "subcategory":"Photofinishing",
            "type":"Services"
        }
    ],
    "sg:phone":"+1 909 355 9884",
    "sg:postcode":"92336",
    "sg:province":"CA",
    "sg:tags":[
        "photo",
        "restoration",
        "retouching"
    ],
    "wof:name":"Fabulous Photo Albums",
    "wof:placetype":"venue"
},
  "geometry": {"coordinates":[-117.46494,34.134731],"type":"Point"}
}