{
  "type": "Feature",
  "properties": {
    "addr:full":"518 E Rio Grande St Pasadena CA 91104",
    "addr:housenumber":"518",
    "addr:postcode":"91104",
    "addr:street":"E Rio Grande St",
    "iso:country":"US",
    "sg:address":"518 E Rio Grande St",
    "sg:city":"Pasadena",
    "sg:classifiers":[
        {
            "category":"Utilities",
            "subcategory":"Refuse",
            "type":"Services"
        }
    ],
    "sg:phone":"+1 626 296 9922",
    "sg:postcode":"91104",
    "sg:province":"CA",
    "sg:tags":[
        "electronics",
        "waste",
        "solution",
        "provides"
    ],
    "wof:name":"Truecycle Inc",
    "wof:placetype":"venue"
},
  "geometry": {"coordinates":[-118.138958,34.170263],"type":"Point"}
}