{
  "type": "Feature",
  "properties": {
    "iso:country":"US",
    "sg:address":"335 14th Ave",
    "sg:city":"San Francisco",
    "sg:classifiers":[
        {
            "category":"Health Services",
            "subcategory":"Clinic",
            "type":"Services"
        }
    ],
    "sg:phone":"+1 415 831 9000",
    "sg:postcode":"94118",
    "sg:province":"CA",
    "sg:tags":[
        "medical"
    ],
    "wof:name":"Doctors Billing Service",
    "wof:placetype":"venue"
},
  "geometry": {"coordinates":[-122.473106,37.781896],"type":"Point"}
}