{
  "type": "Feature",
  "properties": {
    "addr:full":"508 Glenoaks Blvd San Fernando CA 91340",
    "addr:housenumber":"508",
    "addr:postcode":"91340",
    "addr:street":"Glenoaks Blvd",
    "iso:country":"US",
    "sg:address":"508 Glenoaks Blvd",
    "sg:city":"San Fernando",
    "sg:classifiers":[
        {
            "category":"Manufacturing",
            "subcategory":"Apparel",
            "type":"Manufacturing & Wholesale Goods"
        }
    ],
    "sg:phone":"+1 818 365 0992",
    "sg:postcode":"91340",
    "sg:province":"CA",
    "sg:tags":[
        "sewing",
        "contractor"
    ],
    "wof:name":"Valencia Sportswear",
    "wof:placetype":"venue"
},
  "geometry": {"coordinates":[-118.425179,34.286471],"type":"Point"}
}