{
  "type": "Feature",
  "properties": {
    "addr:full":"1425 Burlingame Ave Burlingame CA 94010",
    "addr:housenumber":"1425",
    "addr:postcode":"94010",
    "addr:street":"Burlingame Ave",
    "iso:country":"US",
    "sg:address":"1425 Burlingame Ave",
    "sg:city":"Burlingame",
    "sg:classifiers":[
        {
            "category":"Restaurant",
            "type":"Food & Drink"
        }
    ],
    "sg:menulink":"http://www.allmenus.com/ca/south-san-francisco/22358-prime-on-the-avenue/menu/",
    "sg:phone":"+1 650 344 7746",
    "sg:postcode":"94010",
    "sg:province":"CA",
    "sg:tags":[
        "american",
        "steakhouse"
    ],
    "wof:name":"Prime on the Avenue",
    "wof:placetype":"venue"
},
  "geometry": {"coordinates":[-122.34865499999999,37.577452],"type":"Point"}
}