{
  "type": "Feature",
  "properties": {
    "addr:full":"3230 E Mineral King Ave Visalia CA 93292",
    "addr:housenumber":"3230",
    "addr:postcode":"93292",
    "addr:street":"E Mineral King Ave",
    "iso:country":"US",
    "sg:address":"3230 E Mineral King Ave",
    "sg:city":"Visalia",
    "sg:classifiers":[
        {
            "category":"Social Services",
            "subcategory":"Child Care",
            "type":"Services"
        }
    ],
    "sg:phone":"+1 559 733 5125",
    "sg:postcode":"93292",
    "sg:province":"CA",
    "wof:name":"Far Mac Farm Daycare",
    "wof:placetype":"venue"
},
  "geometry": {"coordinates":[-119.256972,36.327569],"type":"Point"}
}