{
  "type": "Feature",
  "properties": {
    "addr:full":"730 Quintana Rd Morro Bay CA 93442",
    "addr:housenumber":"730",
    "addr:postcode":"93442",
    "addr:street":"Quintana Rd",
    "iso:country":"US",
    "sg:address":"730 Quintana Rd",
    "sg:city":"Morro Bay",
    "sg:classifiers":[
        {
            "category":"Coffee & Tea",
            "type":"Food & Drink"
        }
    ],
    "sg:menulink":"http://www.allmenus.com/ca/north-coast/118768-starbucks-coffee/menu/",
    "sg:postcode":"93442",
    "sg:province":"CA",
    "sg:tags":[
        "american"
    ],
    "wof:name":"Starbucks Coffee",
    "wof:placetype":"venue"
},
  "geometry": {"coordinates":[-120.84187,35.36715],"type":"Point"}
}