{
  "type": "Feature",
  "properties": {
    "addr:full":"321 N Larchmont Boulevard Los Angeles CA 90004",
    "addr:housenumber":"321",
    "addr:postcode":"90004",
    "addr:street":"N Larchmont Boulevard",
    "iso:country":"US",
    "sg:address":"321 N Larchmont Boulevard",
    "sg:city":"Los Angeles",
    "sg:classifiers":[
        {
            "category":"Health Services",
            "subcategory":"Dentist",
            "type":"Services"
        }
    ],
    "sg:phone":"+1 323 463 3173",
    "sg:postcode":"90004",
    "sg:province":"CA",
    "sg:tags":[
        "orthodontist"
    ],
    "sg:website":"www.drnewhart.com",
    "wof:name":"Newhart Orthodontics",
    "wof:placetype":"venue"
},
  "geometry": {"coordinates":[-118.32379299999999,34.076458],"type":"Point"}
}