{
  "type": "Feature",
  "properties": {
    "iso:country":"US",
    "sg:address":"6330 Christie Avenue",
    "sg:city":"Emeryville",
    "sg:classifiers":[
        {
            "category":"Arena",
            "subcategory":"Stadium",
            "type":"Entertainment"
        }
    ],
    "sg:phone":"+1 510 420 0492",
    "sg:postcode":"94608",
    "sg:province":"CA",
    "wof:name":"UA Emery Bay Stadium 10",
    "wof:placetype":"venue"
},
  "geometry": {"coordinates":[-122.29499800000001,37.840099],"type":"Point"}
}