{
  "type": "Feature",
  "properties": {
    "addr:full":"1875 Marin St San Francisco CA 94124",
    "addr:housenumber":"1875",
    "addr:postcode":"94124",
    "addr:street":"Marin St",
    "iso:country":"US",
    "sg:address":"1875 Marin St",
    "sg:city":"San Francisco",
    "sg:classifiers":[
        {
            "category":"Professional",
            "subcategory":"Business Services",
            "type":"Services"
        }
    ],
    "sg:postcode":"94124",
    "sg:province":"CA",
    "sg:tags":[
        "delivery",
        "courier"
    ],
    "sg:website":"www.fedex.com",
    "wof:name":"FedEx",
    "wof:placetype":"venue"
},
  "geometry": {"coordinates":[-122.39575000000001,37.748465],"type":"Point"}
}