{
  "type": "Feature",
  "properties": {
    "iso:country":"US",
    "sg:address":"8428 Lemon Ave",
    "sg:city":"La Mesa",
    "sg:classifiers":[
        {
            "category":"Professional",
            "subcategory":"Accounting & Tax Preparation",
            "type":"Services"
        }
    ],
    "sg:phone":"+1 619 466 6567",
    "sg:postcode":"91941",
    "sg:province":"CA",
    "wof:name":"John P Lucy Accountancy Corp",
    "wof:placetype":"venue"
},
  "geometry": {"coordinates":[-117.015631,32.765565],"type":"Point"}
}