{
  "type": "Feature",
  "properties": {
    "iso:country":"US",
    "sg:address":"2609 Hillside Dr",
    "sg:city":"Burlingame",
    "sg:classifiers":[
        {
            "category":"Wholesale",
            "subcategory":"Machinery & Supplies",
            "type":"Manufacturing & Wholesale Goods"
        }
    ],
    "sg:phone":"+1 650 579 2919",
    "sg:postcode":"94010",
    "sg:province":"CA",
    "sg:tags":[
        "food",
        "equipment",
        "processing",
        "mfg"
    ],
    "wof:name":"Diversified Equipment Sales",
    "wof:placetype":"venue"
},
  "geometry": {"coordinates":[-122.378597,37.579917],"type":"Point"}
}