{
  "type": "Feature",
  "properties": {
    "iso:country":"US",
    "sg:address":"26074 Ave Hall",
    "sg:city":"Valencia",
    "sg:classifiers":[
        {
            "category":"Professional",
            "type":"Services"
        }
    ],
    "sg:phone":"+1 661 775 0270",
    "sg:postcode":"91355",
    "sg:province":"CA",
    "sg:tags":[
        "establishment"
    ],
    "sg:website":"www.buygen.com",
    "wof:name":"Generation Imaging Consumables",
    "wof:placetype":"venue"
},
  "geometry": {"coordinates":[-118.589573,34.442556],"type":"Point"}
}