{
  "type": "Feature",
  "properties": {
    "addr:full":"17942 Van Buren Blvd Riverside CA 92508",
    "addr:housenumber":"17942",
    "addr:postcode":"92508",
    "addr:street":"Van Buren Blvd",
    "iso:country":"US",
    "sg:address":"17942 Van Buren Blvd",
    "sg:city":"Riverside",
    "sg:classifiers":[
        {
            "category":"Health Services",
            "subcategory":"Doctor",
            "type":"Services"
        }
    ],
    "sg:phone":"+1 951 780 8831",
    "sg:postcode":"92508",
    "sg:province":"CA",
    "sg:tags":[
        "dentist"
    ],
    "wof:name":"Woodcrest Dental",
    "wof:placetype":"venue"
},
  "geometry": {"coordinates":[-117.35011799999999,33.885201],"type":"Point"}
}