{
  "type": "Feature",
  "properties": {
    "iso:country":"US",
    "sg:address":"1662 Centinela Ave",
    "sg:city":"Inglewood",
    "sg:classifiers":[
        {
            "category":"Bars & Pubs",
            "type":"Food & Drink"
        }
    ],
    "sg:phone":"+1 310 649 6776",
    "sg:postcode":"90302",
    "sg:province":"CA",
    "sg:tags":[
        "lounge",
        "nightlife",
        "cocktail"
    ],
    "wof:name":"Green Horse the",
    "wof:placetype":"venue"
},
  "geometry": {"coordinates":[-118.36799600000001,33.9772],"type":"Point"}
}