{
  "type": "Feature",
  "properties": {
    "iso:country":"US",
    "sg:address":"12050 Roscoe Blvd",
    "sg:city":"North Hollywood",
    "sg:classifiers":[
        {
            "category":"Food & Beverages",
            "subcategory":"Groceries & Convenience Stores",
            "type":"Retail Goods"
        }
    ],
    "sg:phone":"+1 818 768 4738",
    "sg:postcode":"91605",
    "sg:province":"CA",
    "wof:name":"North Hollywood Mini Mart",
    "wof:placetype":"venue"
},
  "geometry": {"coordinates":[-118.396106,34.2213],"type":"Point"}
}