{
  "type": "Feature",
  "properties": {
    "addr:full":"1224 Santa Barbara St San Diego CA 92107",
    "addr:housenumber":"1224",
    "addr:postcode":"92107",
    "addr:street":"Santa Barbara St",
    "iso:country":"US",
    "sg:address":"1224 Santa Barbara St",
    "sg:city":"San Diego",
    "sg:classifiers":[
        {
            "category":"Retail",
            "subcategory":"Event Space",
            "type":"Services"
        }
    ],
    "sg:phone":"+1 619 224 5264",
    "sg:postcode":"92107",
    "sg:province":"CA",
    "sg:tags":[
        "venue"
    ],
    "sg:website":"www.thethursdayclub.org",
    "wof:name":"Thursday Club",
    "wof:placetype":"venue"
},
  "geometry": {"coordinates":[-117.249138,32.728652],"type":"Point"}
}