{
  "type": "Feature",
  "properties": {
    "addr:full":"1331 N G St San Bernardino CA 92405",
    "addr:housenumber":"1331",
    "addr:postcode":"92405",
    "addr:street":"N G St",
    "iso:country":"US",
    "sg:address":"1331 N G St",
    "sg:city":"San Bernardino",
    "sg:classifiers":[
        {
            "category":"Personal",
            "subcategory":"Beauty Salon",
            "type":"Services"
        }
    ],
    "sg:phone":"+1 909 381 1646",
    "sg:postcode":"92405",
    "sg:province":"CA",
    "wof:name":"Lisa's Braids",
    "wof:placetype":"venue"
},
  "geometry": {"coordinates":[-117.298581,34.12462],"type":"Point"}
}