{
  "type": "Feature",
  "properties": {
    "addr:full":"899 N King Rd San Jose CA 95133",
    "addr:housenumber":"899",
    "addr:postcode":"95133",
    "addr:street":"N King Rd",
    "iso:country":"US",
    "sg:address":"899 N King Rd",
    "sg:city":"San Jose",
    "sg:classifiers":[
        {
            "category":"Real Estate",
            "subcategory":"Real Estate Operator",
            "type":"Services"
        }
    ],
    "sg:phone":"+1 408 272 1588",
    "sg:postcode":"95133",
    "sg:province":"CA",
    "sg:tags":[
        "apartment"
    ],
    "wof:name":"Arbor Park Apartments",
    "wof:placetype":"venue"
},
  "geometry": {"coordinates":[-121.871534,37.368525],"type":"Point"}
}