{
  "type": "Feature",
  "properties": {
    "addr:full":"70380 Camino Del Sol Rancho Mirage CA 92270",
    "addr:housenumber":"70380",
    "addr:postcode":"92270",
    "addr:street":"Camino Del Sol",
    "iso:country":"US",
    "sg:address":"70380 Camino Del Sol",
    "sg:city":"Rancho Mirage",
    "sg:classifiers":[
        {
            "category":"Travel",
            "subcategory":"Hotels & Motels",
            "type":"Entertainment"
        }
    ],
    "sg:phone":"+1 760 328 4237",
    "sg:postcode":"92270",
    "sg:province":"CA",
    "wof:name":"Thunderbird Villas",
    "wof:placetype":"venue"
},
  "geometry": {"coordinates":[-116.435997,33.757301],"type":"Point"}
}