{
  "type": "Feature",
  "properties": {
    "addr:full":"2180 Edinboro Ave Claremont CA 91711",
    "addr:housenumber":"2180",
    "addr:postcode":"91711",
    "addr:street":"Edinboro Ave",
    "iso:country":"US",
    "sg:address":"2180 Edinboro Ave",
    "sg:city":"Claremont",
    "sg:classifiers":[
        {
            "category":"Shopping",
            "subcategory":"Catalog Store",
            "type":"Retail Goods"
        }
    ],
    "sg:phone":"+1 909 624 8684",
    "sg:postcode":"91711",
    "sg:province":"CA",
    "sg:tags":[
        "house",
        "mail"
    ],
    "wof:name":"Rgr Copier & Fax",
    "wof:placetype":"venue"
},
  "geometry": {"coordinates":[-117.708816,34.123495],"type":"Point"}
}