{
  "type": "Feature",
  "properties": {
    "iso:country":"US",
    "sg:address":"2080 E 20th St",
    "sg:city":"Chico",
    "sg:classifiers":[
        {
            "category":"Professional",
            "subcategory":"Management & Consulting",
            "type":"Services"
        }
    ],
    "sg:phone":"+1 530 879 8000",
    "sg:postcode":"95928",
    "sg:province":"CA",
    "sg:tags":[
        "plan"
    ],
    "wof:name":"United Healthcare",
    "wof:placetype":"venue"
},
  "geometry": {"coordinates":[-121.800231,39.727373],"type":"Point"}
}