{
  "type": "Feature",
  "properties": {
    "addr:full":"2625 Alcatraz Ave Berkeley CA 94705",
    "addr:housenumber":"2625",
    "addr:postcode":"94705",
    "addr:street":"Alcatraz Ave",
    "iso:country":"US",
    "sg:address":"2625 Alcatraz Ave",
    "sg:city":"Berkeley",
    "sg:classifiers":[
        {
            "category":"Professional",
            "type":"Services"
        }
    ],
    "sg:phone":"+1 510 649 9571",
    "sg:postcode":"94705",
    "sg:province":"CA",
    "sg:tags":[
        "establishment"
    ],
    "wof:name":"Donald Aitken Assoc",
    "wof:placetype":"venue"
},
  "geometry": {"coordinates":[-122.252653,37.851283],"type":"Point"}
}