{
  "type": "Feature",
  "properties": {
    "addr:full":"4620 Pine St Riverside CA 92501",
    "addr:housenumber":"4620",
    "addr:postcode":"92501",
    "addr:street":"Pine St",
    "iso:country":"US",
    "sg:address":"4620 Pine St",
    "sg:city":"Riverside",
    "sg:classifiers":[
        {
            "category":"Sports & Exercise",
            "subcategory":"Gym",
            "type":"Entertainment"
        }
    ],
    "sg:phone":"+1 951 786 9233",
    "sg:postcode":"92501",
    "sg:province":"CA",
    "sg:tags":[
        "club",
        "health",
        "studio",
        "gymnasium"
    ],
    "sg:website":"www.totalday.com",
    "wof:name":"Total Fitness",
    "wof:placetype":"venue"
},
  "geometry": {"coordinates":[-117.389144,33.977065],"type":"Point"}
}