{
  "type": "Feature",
  "properties": {
    "iso:country":"US",
    "sg:address":"77 Cadillac Dr",
    "sg:city":"Sacramento",
    "sg:classifiers":[
        {
            "category":"Health Services",
            "subcategory":"Doctor",
            "type":"Services"
        }
    ],
    "sg:phone":"+1 916 929 8564",
    "sg:postcode":"95825",
    "sg:province":"CA",
    "wof:name":"Kashyap Rohit MD",
    "wof:placetype":"venue"
},
  "geometry": {"coordinates":[-121.41797699999999,38.574872],"type":"Point"}
}