{
  "type": "Feature",
  "properties": {
    "addr:full":"150 W Cypress Ave Burbank CA 91502",
    "addr:housenumber":"150",
    "addr:postcode":"91502",
    "addr:street":"W Cypress Ave",
    "iso:country":"US",
    "sg:address":"150 W Cypress Ave",
    "sg:city":"Burbank",
    "sg:classifiers":[
        {
            "category":"Building & Trades",
            "subcategory":"Construction",
            "type":"Services"
        }
    ],
    "sg:phone":"+1 818 563 3576",
    "sg:postcode":"91502",
    "sg:province":"CA",
    "sg:tags":[
        "carpenter"
    ],
    "wof:name":"Hope Enterprises Inc",
    "wof:placetype":"venue"
},
  "geometry": {"coordinates":[-118.318203,34.180109],"type":"Point"}
}