{
  "type": "Feature",
  "properties": {
    "addr:full":"98775 Hwy 111 Mecca CA 92254",
    "addr:housenumber":"98775",
    "addr:postcode":"92254",
    "addr:street":"Hwy 111",
    "iso:country":"US",
    "sg:address":"98775 Hwy 111",
    "sg:city":"Mecca",
    "sg:classifiers":[
        {
            "category":"Bars & Pubs",
            "type":"Food & Drink"
        }
    ],
    "sg:phone":"+1 760 393 3696",
    "sg:postcode":"92254",
    "sg:province":"CA",
    "sg:tags":[
        "lounge",
        "cocktail"
    ],
    "wof:name":"Swamp Cooler",
    "wof:placetype":"venue"
},
  "geometry": {"coordinates":[-115.941287,33.526901],"type":"Point"}
}