{
  "type": "Feature",
  "properties": {
    "iso:country":"US",
    "sg:address":"5642 Walnut Rd",
    "sg:city":"Hughson",
    "sg:classifiers":[
        {
            "category":"Farming",
            "subcategory":"Crops",
            "type":"Manufacturing & Wholesale Goods"
        }
    ],
    "sg:phone":"+1 209 632 9193",
    "sg:postcode":"95326",
    "sg:province":"CA",
    "sg:tags":[
        "grove",
        "nut",
        "tree"
    ],
    "wof:name":"Troy Bunch Farm",
    "wof:placetype":"venue"
},
  "geometry": {"coordinates":[-120.865232,37.554116],"type":"Point"}
}