{
  "type": "Feature",
  "properties": {
    "iso:country":"US",
    "sg:address":"10 Main St",
    "sg:city":"Belvedere Tibrn",
    "sg:classifiers":[
        {
            "category":"Shopping",
            "subcategory":"Used Merchandise",
            "type":"Retail Goods"
        }
    ],
    "sg:phone":"+1 415 435 4090",
    "sg:postcode":"94920",
    "sg:province":"CA",
    "sg:tags":[
        "antique"
    ],
    "wof:name":"Stephen's Antiques",
    "wof:placetype":"venue"
},
  "geometry": {"coordinates":[-122.45676,37.873217],"type":"Point"}
}