{
  "type": "Feature",
  "properties": {
    "iso:country":"US",
    "sg:address":"1116 N 2nd St",
    "sg:city":"El Cajon",
    "sg:classifiers":[
        {
            "category":"Real Estate",
            "subcategory":"Real Estate Agent",
            "type":"Services"
        }
    ],
    "sg:phone":"+1 619 440 3111",
    "sg:postcode":"92021",
    "sg:province":"CA",
    "wof:name":"Golden Realty",
    "wof:placetype":"venue"
},
  "geometry": {"coordinates":[-116.935798,32.811223],"type":"Point"}
}