{
  "type": "Feature",
  "properties": {
    "iso:country":"US",
    "sg:address":"530 Water St Ste 5",
    "sg:city":"Oakland",
    "sg:phone":"+1 510 238 4320",
    "sg:postcode":"94607",
    "sg:province":"CA",
    "sg:website":"http://www.amtrak.com",
    "wof:name":"Amtrak-Okj",
    "wof:placetype":"venue"
},
  "geometry": {"coordinates":[-122.27873200000001,37.795374],"type":"Point"}
}