{
  "type": "Feature",
  "properties": {
    "iso:country":"US",
    "sg:address":"1501 Rancho Conejo Blvd",
    "sg:city":"Newbury Park",
    "sg:classifiers":[
        {
            "category":"Freight",
            "type":"Transportation"
        }
    ],
    "sg:phone":"+1 805 375 1832",
    "sg:postcode":"91320",
    "sg:province":"CA",
    "sg:tags":[
        "courier"
    ],
    "wof:name":"UPS",
    "wof:placetype":"venue"
},
  "geometry": {"coordinates":[-118.925455,34.203848],"type":"Point"}
}