{
  "type": "Feature",
  "properties": {
    "addr:full":"197 la Mirada Ave Oroville CA 95966",
    "addr:housenumber":"197",
    "addr:postcode":"95966",
    "addr:street":"La Mirada Ave",
    "iso:country":"US",
    "sg:address":"197 la Mirada Ave",
    "sg:city":"Oroville",
    "sg:classifiers":[
        {
            "category":"Building & Trades",
            "subcategory":"Landscaping Services",
            "type":"Services"
        },
        {
            "category":"Health Services",
            "subcategory":"Nursing And Care Facility",
            "type":"Services"
        },
        {
            "category":"Social Services",
            "subcategory":"Retirement Home",
            "type":"Services"
        }
    ],
    "sg:phone":"+1 530 589 1781",
    "sg:postcode":"95966",
    "sg:province":"CA",
    "sg:tags":[
        "residential",
        "convalescent",
        "aged",
        "homes-institutional"
    ],
    "wof:name":"La Mirada Villa",
    "wof:placetype":"venue"
},
  "geometry": {"coordinates":[-121.48462000000001,39.499011],"type":"Point"}
}