{
  "type": "Feature",
  "properties": {
    "addr:full":"8720 S Main St San Joaquin CA 93660",
    "addr:housenumber":"8720",
    "addr:postcode":"93660",
    "addr:street":"S Main St",
    "iso:country":"US",
    "sg:address":"8720 S Main St",
    "sg:city":"San Joaquin",
    "sg:classifiers":[
        {
            "category":"Shopping",
            "subcategory":"Gifts & Souvenirs",
            "type":"Retail Goods"
        }
    ],
    "sg:phone":"+1 559 693 9294",
    "sg:postcode":"93660",
    "sg:province":"CA",
    "sg:tags":[
        "shop"
    ],
    "wof:name":"San Joaquin Gift Store",
    "wof:placetype":"venue"
},
  "geometry": {"coordinates":[-120.18619,36.607697],"type":"Point"}
}