{
  "type": "Feature",
  "properties": {
    "addr:full":"21 Ashbury St San Francisco CA 94117",
    "addr:housenumber":"21",
    "addr:postcode":"94117",
    "addr:street":"Ashbury St",
    "iso:country":"US",
    "sg:address":"21 Ashbury St",
    "sg:city":"San Francisco",
    "sg:classifiers":[
        {
            "category":"Health Services",
            "subcategory":"Chiropractor",
            "type":"Services"
        }
    ],
    "sg:phone":"+1 415 751 2345",
    "sg:postcode":"94117",
    "sg:province":"CA",
    "wof:name":"Noe Valley Chiropractic",
    "wof:placetype":"venue"
},
  "geometry": {"coordinates":[-122.44798299999999,37.774845],"type":"Point"}
}