{
  "type": "Feature",
  "properties": {
    "addr:full":"18622 Wildwood Dr Twain Harte CA 95383",
    "addr:housenumber":"18622",
    "addr:postcode":"95383",
    "addr:street":"Wildwood Dr",
    "iso:country":"US",
    "sg:address":"18622 Wildwood Dr",
    "sg:city":"Twain Harte",
    "sg:classifiers":[
        {
            "category":"Manufacturing",
            "subcategory":"Printing",
            "type":"Manufacturing & Wholesale Goods"
        }
    ],
    "sg:phone":"+1 650 341 7453",
    "sg:postcode":"95383",
    "sg:province":"CA",
    "wof:name":"Westland Printing",
    "wof:placetype":"venue"
},
  "geometry": {"coordinates":[-120.23106199999999,38.045172],"type":"Point"}
}