{
  "type": "Feature",
  "properties": {
    "addr:full":"2982 E Jensen Ave Fresno CA 93706",
    "addr:housenumber":"2982",
    "addr:postcode":"93706",
    "addr:street":"E Jensen Ave",
    "iso:country":"US",
    "sg:address":"2982 E Jensen Ave",
    "sg:city":"Fresno",
    "sg:classifiers":[
        {
            "category":"Autos & Motor Vehicles",
            "subcategory":"Automobile Sales",
            "type":"Retail Goods"
        }
    ],
    "sg:phone":"+1 559 497 7204",
    "sg:postcode":"93706",
    "sg:province":"CA",
    "sg:tags":[
        "new",
        "used",
        "car"
    ],
    "wof:name":"Central Califorina Kenworth",
    "wof:placetype":"venue"
},
  "geometry": {"coordinates":[-119.84432200000001,36.706619],"type":"Point"}
}