{
  "type": "Feature",
  "properties": {
    "iso:country":"US",
    "sg:address":"400 29th St",
    "sg:city":"Oakland",
    "sg:classifiers":[
        {
            "category":"Professional",
            "subcategory":"Testing Lab",
            "type":"Services"
        }
    ],
    "sg:phone":"+1 510 893 3413",
    "sg:postcode":"94609",
    "sg:province":"CA",
    "sg:tags":[
        "consultant",
        "forensic"
    ],
    "wof:name":"Paul SD Berg & Assoc",
    "wof:placetype":"venue"
},
  "geometry": {"coordinates":[-122.266486,37.818017],"type":"Point"}
}