{
  "type": "Feature",
  "properties": {
    "addr:full":"930 Montgomery St Ste 500 San Francisco CA 94133",
    "addr:housenumber":"930",
    "addr:postcode":"94133",
    "addr:street":"Montgomery St Ste 500",
    "iso:country":"US",
    "sg:address":"930 Montgomery St Ste 500",
    "sg:city":"San Francisco",
    "sg:classifiers":[
        {
            "category":"Real Estate",
            "subcategory":"Architect",
            "type":"Services"
        }
    ],
    "sg:phone":"+1 415 693 9234",
    "sg:postcode":"94133",
    "sg:province":"CA",
    "wof:name":"Meeks Coates & Eaton Architects",
    "wof:placetype":"venue"
},
  "geometry": {"coordinates":[-122.40355099999999,37.797759],"type":"Point"}
}