{
  "type": "Feature",
  "properties": {
    "iso:country":"US",
    "sg:address":"2469 Alvin Ave",
    "sg:city":"San Jose",
    "sg:classifiers":[
        {
            "category":"Shopping",
            "type":"Retail Goods"
        }
    ],
    "sg:phone":"+1 408 238 7573",
    "sg:postcode":"95121",
    "sg:province":"CA",
    "sg:tags":[
        "pet",
        "food",
        "store",
        "supply"
    ],
    "wof:name":"CD Aquarium",
    "wof:placetype":"venue"
},
  "geometry": {"coordinates":[-121.827851,37.319478],"type":"Point"}
}