{
  "type": "Feature",
  "properties": {
    "addr:full":"9400 Mason Ave Chatsworth CA 91311",
    "addr:housenumber":"9400",
    "addr:postcode":"91311",
    "addr:street":"Mason Ave",
    "iso:country":"US",
    "sg:address":"9400 Mason Ave",
    "sg:city":"Chatsworth",
    "sg:classifiers":[
        {
            "category":"Wholesale",
            "subcategory":"Groceries",
            "type":"Manufacturing & Wholesale Goods"
        }
    ],
    "sg:phone":"+1 203 863 0556",
    "sg:postcode":"91311",
    "sg:province":"CA",
    "sg:tags":[
        "business"
    ],
    "wof:name":"Great Spring Waters of America",
    "wof:placetype":"venue"
},
  "geometry": {"coordinates":[-118.579722,34.240536],"type":"Point"}
}