{
  "type": "Feature",
  "properties": {
    "iso:country":"US",
    "sg:address":"2472 Flores St",
    "sg:city":"San Mateo",
    "sg:classifiers":[
        {
            "category":"Retail",
            "subcategory":"Laundry & Dry Cleaning",
            "type":"Services"
        }
    ],
    "sg:phone":"+1 650 345 2108",
    "sg:postcode":"94403",
    "sg:province":"CA",
    "wof:name":"Jessie's Laundromat & Cleaners",
    "wof:placetype":"venue"
},
  "geometry": {"coordinates":[-122.307034,37.543993],"type":"Point"}
}