{
  "type": "Feature",
  "properties": {
    "iso:country":"US",
    "sg:address":"1911 Douglas Blvd",
    "sg:city":"Roseville",
    "sg:classifiers":[
        {
            "category":"Recreation",
            "type":"Entertainment"
        }
    ],
    "sg:phone":"+1 916 645 1108",
    "sg:postcode":"95661",
    "sg:province":"CA",
    "sg:tags":[
        "entertainers-family",
        "business"
    ],
    "wof:name":"Showmasters",
    "wof:placetype":"venue"
},
  "geometry": {"coordinates":[-121.25730900000001,38.744241],"type":"Point"}
}