{
  "type": "Feature",
  "properties": {
    "addr:full":"1915 Fremont Ave South Pasadena CA 91030",
    "addr:housenumber":"1915",
    "addr:postcode":"91030",
    "addr:street":"Fremont Ave",
    "iso:country":"US",
    "sg:address":"1915 Fremont Ave",
    "sg:city":"South Pasadena",
    "sg:classifiers":[
        {
            "category":"Health Services",
            "subcategory":"Dentist",
            "type":"Services"
        }
    ],
    "sg:phone":"+1 323 340 8882",
    "sg:postcode":"91030",
    "sg:province":"CA",
    "wof:name":"Fremont Dentistry",
    "wof:placetype":"venue"
},
  "geometry": {"coordinates":[-118.152,34.103401],"type":"Point"}
}