{
  "type": "Feature",
  "properties": {
    "iso:country":"US",
    "sg:address":"882 H St",
    "sg:city":"Crescent City",
    "sg:classifiers":[
        {
            "category":"Professional",
            "subcategory":"Secretarial Services",
            "type":"Services"
        }
    ],
    "sg:phone":"+1 707 464 6465",
    "sg:postcode":"95531",
    "sg:province":"CA",
    "sg:tags":[
        "convention",
        "court",
        "reporter"
    ],
    "wof:name":"Beard Reporting Svc",
    "wof:placetype":"venue"
},
  "geometry": {"coordinates":[-124.20135,41.755602],"type":"Point"}
}