{
  "type": "Feature",
  "properties": {
    "iso:country":"US",
    "sg:address":"1068 G St",
    "sg:city":"Fresno",
    "sg:classifiers":[
        {
            "category":"Home & Garden",
            "subcategory":"Garden Supply",
            "type":"Retail Goods"
        }
    ],
    "sg:phone":"+1 559 268 9221",
    "sg:postcode":"93706",
    "sg:province":"CA",
    "sg:tags":[
        "lawn"
    ],
    "sg:website":"www.jensenandpilegard.com",
    "wof:name":"Jensen & Pilegard",
    "wof:placetype":"venue"
},
  "geometry": {"coordinates":[-119.794291,36.731548],"type":"Point"}
}