{
  "type": "Feature",
  "properties": {
    "iso:country":"US",
    "sg:address":"110 J St",
    "sg:city":"Fremont",
    "sg:classifiers":[
        {
            "category":"Insurance",
            "subcategory":"Insurance Agent",
            "type":"Services"
        }
    ],
    "sg:phone":"+1 510 797 4211",
    "sg:postcode":"94536",
    "sg:province":"CA",
    "wof:name":"De Sousa Insurance & Financial",
    "wof:placetype":"venue"
},
  "geometry": {"coordinates":[-121.976885,37.576014],"type":"Point"}
}