{
  "type": "Feature",
  "properties": {
    "iso:country":"US",
    "sg:address":"1017 L St",
    "sg:city":"Sacramento",
    "sg:phone":"+1 916 745 4974",
    "sg:postcode":"95814",
    "sg:province":"CA",
    "wof:name":"Professional Couriers, Inc.",
    "wof:placetype":"venue"
},
  "geometry": {"coordinates":[-121.494173,38.578062],"type":"Point"}
}