{
  "type": "Feature",
  "properties": {
    "addr:full":"660 Ash Street San Diego CA 92101",
    "addr:housenumber":"660",
    "addr:postcode":"92101",
    "addr:street":"Ash Street",
    "iso:country":"US",
    "sg:address":"660 Ash Street",
    "sg:city":"San Diego",
    "sg:classifiers":[
        {
            "category":"Real Estate",
            "subcategory":"Architect",
            "type":"Services"
        }
    ],
    "sg:phone":"+1 619 239 0294",
    "sg:postcode":"92101",
    "sg:province":"CA",
    "sg:website":"www.lmaconsultinggroup.com",
    "wof:name":"Lma Consulting Group",
    "wof:placetype":"venue"
},
  "geometry": {"coordinates":[-117.158655,32.719783],"type":"Point"}
}