{
  "type": "Feature",
  "properties": {
    "iso:country":"US",
    "sg:address":"501 Sweetwater Rd",
    "sg:city":"Spring Valley",
    "sg:classifiers":[
        {
            "category":"Restaurant",
            "type":"Food & Drink"
        }
    ],
    "sg:phone":"+1 619 589 7020",
    "sg:postcode":"91977",
    "sg:province":"CA",
    "sg:tags":[
        "chinese"
    ],
    "wof:name":"Linlee's Chinese Cuisine",
    "wof:placetype":"venue"
},
  "geometry": {"coordinates":[-117.011002,32.706501],"type":"Point"}
}