{
  "type": "Feature",
  "properties": {
    "iso:country":"US",
    "sg:address":"464 19th St",
    "sg:city":"Oakland",
    "sg:classifiers":[
        {
            "category":"Communications",
            "subcategory":"Film & Video Production",
            "type":"Services"
        }
    ],
    "sg:phone":"+1 510 288 7545",
    "sg:postcode":"94612",
    "sg:province":"CA",
    "sg:tags":[
        "studio",
        "rental"
    ],
    "wof:name":"Jusbnrl Entertainment",
    "wof:placetype":"venue"
},
  "geometry": {"coordinates":[-122.269596,37.808053],"type":"Point"}
}