{
  "type": "Feature",
  "properties": {
    "iso:country":"US",
    "sg:address":"2409 Thomas Ave",
    "sg:city":"Redondo Beach",
    "sg:classifiers":[
        {
            "category":"Building & Trades",
            "subcategory":"Construction",
            "type":"Services"
        }
    ],
    "sg:phone":"+1 310 542 7596",
    "sg:postcode":"90278",
    "sg:province":"CA",
    "sg:tags":[
        "house"
    ],
    "wof:name":"Hopkins Construction Co",
    "wof:placetype":"venue"
},
  "geometry": {"coordinates":[-118.366597,33.884702],"type":"Point"}
}