{
  "type": "Feature",
  "properties": {
    "iso:country":"US",
    "sg:address":"12626 Baccarat Ct",
    "sg:city":"Grass Valley",
    "sg:classifiers":[
        {
            "category":"Real Estate",
            "subcategory":"Real Estate Agent",
            "type":"Services"
        }
    ],
    "sg:phone":"+1 530 272 0257",
    "sg:postcode":"95945",
    "sg:province":"CA",
    "wof:name":"La Jolla Bank",
    "wof:placetype":"venue"
},
  "geometry": {"coordinates":[-120.985548,39.211633],"type":"Point"}
}