{
  "type": "Feature",
  "properties": {
    "addr:full":"11674 Tuxford St Sun Valley CA 91352",
    "addr:housenumber":"11674",
    "addr:postcode":"91352",
    "addr:street":"Tuxford St",
    "iso:country":"US",
    "sg:address":"11674 Tuxford St",
    "sg:city":"Sun Valley",
    "sg:classifiers":[
        {
            "category":"Wholesale",
            "subcategory":"Groceries",
            "type":"Manufacturing & Wholesale Goods"
        }
    ],
    "sg:phone":"+1 818 767 7667",
    "sg:postcode":"91352",
    "sg:province":"CA",
    "sg:tags":[
        "bakery",
        "baker"
    ],
    "wof:name":"Pane Pane Inc",
    "wof:placetype":"venue"
},
  "geometry": {"coordinates":[-118.387001,34.223],"type":"Point"}
}