{
  "type": "Feature",
  "properties": {
    "addr:full":"2357 Air Ln San Diego CA 92101",
    "addr:housenumber":"2357",
    "addr:postcode":"92101",
    "addr:street":"Air Ln",
    "iso:country":"US",
    "sg:address":"2357 Air Ln",
    "sg:city":"San Diego",
    "sg:classifiers":[
        {
            "category":"Airline",
            "type":"Transportation"
        }
    ],
    "sg:phone":"+1 619 298 0948",
    "sg:postcode":"92101",
    "sg:province":"CA",
    "sg:tags":[
        "company"
    ],
    "wof:name":"America West Airlines Inc",
    "wof:placetype":"venue"
},
  "geometry": {"coordinates":[-117.1951,32.730676],"type":"Point"}
}