{
  "type": "Feature",
  "properties": {
    "iso:country":"US",
    "sg:address":"2429 E Ball Rd",
    "sg:city":"Anaheim",
    "sg:classifiers":[
        {
            "category":"Food & Beverages",
            "subcategory":"Groceries & Convenience Stores",
            "type":"Retail Goods"
        }
    ],
    "sg:phone":"+1 714 991 8733",
    "sg:postcode":"92806",
    "sg:province":"CA",
    "wof:name":"OC Mini Mart",
    "wof:placetype":"venue"
},
  "geometry": {"coordinates":[-117.881665,33.81829],"type":"Point"}
}