{
  "type": "Feature",
  "properties": {
    "addr:full":"2901 E Miraloma Ave Anaheim CA 92806",
    "addr:housenumber":"2901",
    "addr:postcode":"92806",
    "addr:street":"E Miraloma Ave",
    "iso:country":"US",
    "sg:address":"2901 E Miraloma Ave",
    "sg:city":"Anaheim",
    "sg:classifiers":[
        {
            "category":"Manufacturing",
            "subcategory":"Metals",
            "type":"Manufacturing & Wholesale Goods"
        }
    ],
    "sg:phone":"+1 714 632 1298",
    "sg:postcode":"92806",
    "sg:province":"CA",
    "sg:tags":[
        "coating",
        "specialty",
        "mfg"
    ],
    "wof:name":"Pivotal Coating Technologies",
    "wof:placetype":"venue"
},
  "geometry": {"coordinates":[-117.869787,33.855496],"type":"Point"}
}