{
  "type": "Feature",
  "properties": {
    "addr:full":"7007 Balsam Way Oakland CA 94611",
    "addr:housenumber":"7007",
    "addr:postcode":"94611",
    "addr:street":"Balsam Way",
    "iso:country":"US",
    "sg:address":"7007 Balsam Way",
    "sg:city":"Oakland",
    "sg:classifiers":[
        {
            "category":"Professional",
            "subcategory":"Engineering",
            "type":"Services"
        }
    ],
    "sg:phone":"+1 510 923 1267",
    "sg:postcode":"94611",
    "sg:province":"CA",
    "sg:tags":[
        "engineer"
    ],
    "wof:name":"Allen Consulting Group",
    "wof:placetype":"venue"
},
  "geometry": {"coordinates":[-122.211538,37.850281],"type":"Point"}
}