{
  "type": "Feature",
  "properties": {
    "iso:country":"US",
    "sg:address":"7420 Clairmont Mesa Blvd.",
    "sg:city":"San Diego",
    "sg:classifiers":[
        {
            "category":"Personal",
            "subcategory":"Tanning Parlor",
            "type":"Services"
        }
    ],
    "sg:phone":"+1 858 569 6059",
    "sg:postcode":"92111",
    "sg:province":"CA",
    "sg:website":"www.californiatansandiego.com/",
    "wof:name":"California Tan",
    "wof:placetype":"venue"
},
  "geometry": {"coordinates":[-117.158445,32.833353],"type":"Point"}
}