{
  "type": "Feature",
  "properties": {
    "addr:full":"13774 Raywood Dr Los Angeles CA 90049",
    "addr:postcode":"13774;90049",
    "addr:street":"Raywood Dr",
    "iso:country":"US",
    "sg:address":"13774 Raywood Dr",
    "sg:city":"Los Angeles",
    "sg:classifiers":[
        {
            "category":"Wholesale",
            "subcategory":"Hardware",
            "type":"Manufacturing & Wholesale Goods"
        }
    ],
    "sg:phone":"+1 310 476 2323",
    "sg:postcode":"90049",
    "sg:province":"CA",
    "sg:tags":[
        "operator",
        "advisory",
        "tour",
        "investment"
    ],
    "wof:name":"Mandrick Company Inc",
    "wof:placetype":"venue"
},
  "geometry": {"coordinates":[-118.506687,34.080148],"type":"Point"}
}