{
  "type": "Feature",
  "properties": {
    "addr:full":"2610 Hop Ranch Rd Union City CA 94587",
    "addr:housenumber":"2610",
    "addr:postcode":"94587",
    "addr:street":"Hop Ranch Rd",
    "iso:country":"US",
    "sg:address":"2610 Hop Ranch Rd",
    "sg:city":"Union City",
    "sg:classifiers":[
        {
            "category":"Shopping",
            "subcategory":"Discount & Variety Stores",
            "type":"Retail Goods"
        }
    ],
    "sg:phone":"+1 510 487 9111",
    "sg:postcode":"94587",
    "sg:province":"CA",
    "sg:tags":[
        "merchandise",
        "general"
    ],
    "wof:name":"Alpha Products Co",
    "wof:placetype":"venue"
},
  "geometry": {"coordinates":[-122.047275,37.593635],"type":"Point"}
}