{
  "type": "Feature",
  "properties": {
    "addr:full":"11430 Deerfield Dr Bldg 1 Truckee CA 96161",
    "addr:housenumber":"11430",
    "addr:postcode":"96161",
    "addr:street":"Deerfield Dr Bldg 1",
    "iso:country":"US",
    "sg:address":"11430 Deerfield Dr Bldg 1",
    "sg:city":"Truckee",
    "sg:classifiers":[
        {
            "category":"Restaurant",
            "type":"Food & Drink"
        }
    ],
    "sg:phone":"+1 530 587 1831",
    "sg:postcode":"96161",
    "sg:province":"CA",
    "sg:tags":[
        "asian",
        "chinese",
        "pan"
    ],
    "wof:name":"Wong's Garden",
    "wof:placetype":"venue"
},
  "geometry": {"coordinates":[-120.209372,39.320659],"type":"Point"}
}