{
  "type": "Feature",
  "properties": {
    "iso:country":"US",
    "sg:address":"106 La Casa Via",
    "sg:city":"Walnut Creek",
    "sg:classifiers":[
        {
            "category":"Health Services",
            "subcategory":"Doctor",
            "type":"Services"
        }
    ],
    "sg:phone":"+1 925 280 8777",
    "sg:postcode":"94598",
    "sg:province":"CA",
    "sg:tags":[
        "medicine",
        "internal"
    ],
    "wof:name":"Pirkle Ross MD",
    "wof:placetype":"venue"
},
  "geometry": {"coordinates":[-122.316608,37.912698],"type":"Point"}
}