{
  "type": "Feature",
  "properties": {
    "iso:country":"US",
    "sg:address":"441 March Ave",
    "sg:city":"Healdsburg",
    "sg:classifiers":[
        {
            "category":"Health Services",
            "subcategory":"Health Practitioner",
            "type":"Services"
        }
    ],
    "sg:phone":"+1 707 433 5219",
    "sg:postcode":"95448",
    "sg:province":"CA",
    "sg:tags":[
        "therapist",
        "physical"
    ],
    "wof:name":"Healdsburg Physical Therapy",
    "wof:placetype":"venue"
},
  "geometry": {"coordinates":[-122.864673,38.625991],"type":"Point"}
}