{
  "type": "Feature",
  "properties": {
    "iso:country":"US",
    "sg:address":"174 N Main St",
    "sg:city":"Bishop",
    "sg:classifiers":[
        {
            "category":"Professional",
            "subcategory":"Computer Services",
            "type":"Services"
        }
    ],
    "sg:phone":"+1 760 873 4377",
    "sg:postcode":"93514",
    "sg:province":"CA",
    "sg:tags":[
        "repair"
    ],
    "sg:website":"www.schat.com",
    "wof:name":"SCHAT.NET",
    "wof:placetype":"venue"
},
  "geometry": {"coordinates":[-118.395293,37.362134],"type":"Point"}
}