{
  "type": "Feature",
  "properties": {
    "addr:full":"23065 Cavanaugh Road Lake Forest CA 92630",
    "addr:housenumber":"23065",
    "addr:postcode":"92630",
    "addr:street":"Cavanaugh Road",
    "iso:country":"US",
    "sg:address":"23065 Cavanaugh Road",
    "sg:city":"Lake Forest",
    "sg:classifiers":[
        {
            "category":"Building & Trades",
            "subcategory":"Construction",
            "type":"Services"
        }
    ],
    "sg:phone":"+1 949 581 4550",
    "sg:postcode":"92630",
    "sg:province":"CA",
    "sg:tags":[
        "contractor"
    ],
    "wof:name":"Concept Doors",
    "wof:placetype":"venue"
},
  "geometry": {"coordinates":[-117.699279,33.626896],"type":"Point"}
}