{
  "type": "Feature",
  "properties": {
    "addr:full":"777 Stockton St San Francisco CA 94108",
    "addr:housenumber":"777",
    "addr:postcode":"94108",
    "addr:street":"Stockton St",
    "iso:country":"US",
    "sg:address":"777 Stockton St",
    "sg:city":"San Francisco",
    "sg:classifiers":[
        {
            "category":"Social Services",
            "subcategory":"Adult Care",
            "type":"Services"
        }
    ],
    "sg:phone":"+1 415 391 3843",
    "sg:postcode":"94108",
    "sg:province":"CA",
    "sg:tags":[
        "home",
        "residential"
    ],
    "wof:name":"Self Help For The Elderly",
    "wof:placetype":"venue"
},
  "geometry": {"coordinates":[-122.407759,37.792903],"type":"Point"}
}