{
  "type": "Feature",
  "properties": {
    "addr:full":"609 Deep Valley Dr Palos Verdes Peninsula CA 90274",
    "addr:housenumber":"609",
    "addr:postcode":"90274",
    "addr:street":"Deep Valley Dr Palos",
    "iso:country":"US",
    "sg:address":"609 Deep Valley Dr",
    "sg:city":"Palos Verdes Peninsula",
    "sg:classifiers":[
        {
            "category":"Wholesale",
            "subcategory":"Non-durable Goods",
            "type":"Manufacturing & Wholesale Goods"
        }
    ],
    "sg:phone":"+1 310 377 4866",
    "sg:postcode":"90274",
    "sg:province":"CA",
    "wof:name":"Litex",
    "wof:placetype":"venue"
},
  "geometry": {"coordinates":[-118.36882300000001,33.769497],"type":"Point"}
}