{
  "type": "Feature",
  "properties": {
    "iso:country":"US",
    "sg:address":"11300 W Olympic Blvd",
    "sg:city":"Los Angeles",
    "sg:classifiers":[
        {
            "category":"Insurance",
            "subcategory":"Insurance Agent",
            "type":"Services"
        }
    ],
    "sg:phone":"+1 310 478 2625",
    "sg:postcode":"90064",
    "sg:province":"CA",
    "sg:website":"www.lyddy.com",
    "wof:name":"Liddy Martin Insurance",
    "wof:placetype":"venue"
},
  "geometry": {"coordinates":[-118.442211,34.037618],"type":"Point"}
}