{
  "type": "Feature",
  "properties": {
    "addr:full":"720 State St Santa Barbara CA 93101",
    "addr:housenumber":"720",
    "addr:postcode":"93101",
    "addr:street":"State St",
    "iso:country":"US",
    "sg:address":"720 State St",
    "sg:city":"Santa Barbara",
    "sg:classifiers":[
        {
            "category":"Restaurant",
            "type":"Food & Drink"
        }
    ],
    "sg:phone":"+1 805 962 5715",
    "sg:postcode":"93101",
    "sg:province":"CA",
    "wof:name":"Blenders In The Grass",
    "wof:placetype":"venue"
},
  "geometry": {"coordinates":[-119.698662,34.419201],"type":"Point"}
}