{
  "type": "Feature",
  "properties": {
    "addr:full":"7561 Park Ave Garden Grove CA 92841",
    "addr:housenumber":"7561",
    "addr:postcode":"92841",
    "addr:street":"Park Ave",
    "iso:country":"US",
    "sg:address":"7561 Park Ave",
    "sg:city":"Garden Grove",
    "sg:classifiers":[
        {
            "category":"Building & Trades",
            "subcategory":"Construction",
            "type":"Services"
        }
    ],
    "sg:phone":"+1 714 894 3313",
    "sg:postcode":"92841",
    "sg:province":"CA",
    "sg:tags":[
        "industrial",
        "painting",
        "painter"
    ],
    "wof:name":"Star Paintings & Refinishing",
    "wof:placetype":"venue"
},
  "geometry": {"coordinates":[-118.000012,33.776969],"type":"Point"}
}