{
  "type": "Feature",
  "properties": {
    "iso:country":"US",
    "sg:address":"4712 Seminary Rd",
    "sg:city":"Camarillo",
    "sg:classifiers":[
        {
            "category":"Building & Trades",
            "subcategory":"Electrical",
            "type":"Services"
        }
    ],
    "sg:phone":"+1 805 987 8998",
    "sg:postcode":"93012",
    "sg:province":"CA",
    "sg:tags":[
        "electrical",
        "contractor"
    ],
    "wof:name":"Bee Vee Company",
    "wof:placetype":"venue"
},
  "geometry": {"coordinates":[-119.00926,34.243667],"type":"Point"}
}