{
  "type": "Feature",
  "properties": {
    "iso:country":"US",
    "sg:address":"1155 12th St",
    "sg:city":"Los Osos",
    "sg:classifiers":[
        {
            "category":"Building & Trades",
            "subcategory":"Landscaping Services",
            "type":"Services"
        }
    ],
    "sg:phone":"+1 805 528 0849",
    "sg:postcode":"93402",
    "sg:province":"CA",
    "sg:tags":[
        "landscape"
    ],
    "wof:name":"Kevin ODonnell",
    "wof:placetype":"venue"
},
  "geometry": {"coordinates":[-120.829946,35.330746],"type":"Point"}
}