{
  "type": "Feature",
  "properties": {
    "addr:full":"69941 Papaya Ln Cathedral City CA 92234",
    "addr:housenumber":"69941",
    "addr:postcode":"92234",
    "addr:street":"Papaya Ln",
    "iso:country":"US",
    "sg:address":"69941 Papaya Ln",
    "sg:city":"Cathedral City",
    "sg:classifiers":[
        {
            "category":"Building & Trades",
            "subcategory":"Construction",
            "type":"Services"
        }
    ],
    "sg:phone":"+1 760 346 1131",
    "sg:postcode":"92234",
    "sg:province":"CA",
    "sg:tags":[
        "painting",
        "contractor"
    ],
    "wof:name":"Avriette & Co",
    "wof:placetype":"venue"
},
  "geometry": {"coordinates":[-116.444299,33.780738],"type":"Point"}
}