{
  "type": "Feature",
  "properties": {
    "addr:full":"2295 W Broadway Anaheim CA 92804",
    "addr:housenumber":"2295",
    "addr:postcode":"92804",
    "addr:street":"W Broadway",
    "iso:country":"US",
    "sg:address":"2295 W Broadway",
    "sg:city":"Anaheim",
    "sg:classifiers":[
        {
            "category":"Professional",
            "type":"Services"
        }
    ],
    "sg:phone":"+1 714 502 0270",
    "sg:postcode":"92804",
    "sg:province":"CA",
    "wof:name":"Ccomm",
    "wof:placetype":"venue"
},
  "geometry": {"coordinates":[-117.962981,33.828888],"type":"Point"}
}