{
  "type": "Feature",
  "properties": {
    "addr:full":"41676 Carmen St Fremont CA 94539",
    "addr:postcode":"41676;94539",
    "addr:street":"Carmen St",
    "iso:country":"US",
    "sg:address":"41676 Carmen St",
    "sg:city":"Fremont",
    "sg:classifiers":[
        {
            "category":"Professional",
            "type":"Services"
        }
    ],
    "sg:phone":"+1 510 651 4630",
    "sg:postcode":"94539",
    "sg:province":"CA",
    "sg:tags":[
        "establishment"
    ],
    "wof:name":"Palmland Co",
    "wof:placetype":"venue"
},
  "geometry": {"coordinates":[-121.94959900000001,37.536205],"type":"Point"}
}