{
  "type": "Feature",
  "properties": {
    "addr:full":"2060 S Broderick Ave Duarte CA 91010",
    "addr:housenumber":"2060",
    "addr:postcode":"91010",
    "addr:street":"S Broderick Ave",
    "iso:country":"US",
    "sg:address":"2060 S Broderick Ave",
    "sg:city":"Duarte",
    "sg:classifiers":[
        {
            "category":"Professional",
            "subcategory":"Business Services",
            "type":"Services"
        }
    ],
    "sg:phone":"+1 626 359 0391",
    "sg:postcode":"91010",
    "sg:province":"CA",
    "sg:tags":[
        "pool",
        "swimming"
    ],
    "wof:name":"M & J Pool & Spa Svc",
    "wof:placetype":"venue"
},
  "geometry": {"coordinates":[-117.990897,34.12702],"type":"Point"}
}