{
  "type": "Feature",
  "properties": {
    "addr:full":"2576 Shattuck Ave Berkeley CA 94704",
    "addr:housenumber":"2576",
    "addr:postcode":"94704",
    "addr:street":"Shattuck Ave",
    "iso:country":"US",
    "sg:address":"2576 Shattuck Ave",
    "sg:city":"Berkeley",
    "sg:classifiers":[
        {
            "category":"Health Services",
            "subcategory":"Clinic",
            "type":"Services"
        }
    ],
    "sg:phone":"+1 510 336 1005",
    "sg:postcode":"94704",
    "sg:province":"CA",
    "sg:tags":[
        "holistic",
        "practitioner"
    ],
    "wof:name":"Energy Healing",
    "wof:placetype":"venue"
},
  "geometry": {"coordinates":[-122.26736099999999,37.862648],"type":"Point"}
}