{
  "type": "Feature",
  "properties": {
    "addr:full":"12753 Waltham St Baldwin Park CA 91706",
    "addr:housenumber":"12753",
    "addr:postcode":"91706",
    "addr:street":"Waltham St",
    "iso:country":"US",
    "sg:address":"12753 Waltham St",
    "sg:city":"Baldwin Park",
    "sg:classifiers":[
        {
            "category":"Home & Garden",
            "subcategory":"Home Furnishings",
            "type":"Retail Goods"
        }
    ],
    "sg:phone":"+1 626 338 9411",
    "sg:postcode":"91706",
    "sg:province":"CA",
    "sg:tags":[
        "kitchen",
        "accessory"
    ],
    "wof:name":"Vapor Kitchen Products",
    "wof:placetype":"venue"
},
  "geometry": {"coordinates":[-117.996225,34.071842],"type":"Point"}
}