{
  "type": "Feature",
  "properties": {
    "addr:full":"4862 Alex Dr San Jose CA 95130",
    "addr:housenumber":"4862",
    "addr:postcode":"95130",
    "addr:street":"Alex Dr",
    "iso:country":"US",
    "sg:address":"4862 Alex Dr",
    "sg:city":"San Jose",
    "sg:classifiers":[
        {
            "category":"Shopping",
            "subcategory":"Computers & Home Electronics",
            "type":"Retail Goods"
        }
    ],
    "sg:phone":"+1 408 849 2373",
    "sg:postcode":"95130",
    "sg:province":"CA",
    "sg:tags":[
        "installation",
        "theatre"
    ],
    "sg:website":"www.audiovideoevolution.net",
    "wof:name":"Audio Video Evolution",
    "wof:placetype":"venue"
},
  "geometry": {"coordinates":[-121.986429,37.27933],"type":"Point"}
}