{
  "type": "Feature",
  "properties": {
    "addr:full":"510 Luther Rd Red Bluff CA 96080",
    "addr:housenumber":"510",
    "addr:postcode":"96080",
    "addr:street":"Luther Rd",
    "iso:country":"US",
    "sg:address":"510 Luther Rd",
    "sg:city":"Red Bluff",
    "sg:classifiers":[
        {
            "category":"Retail",
            "subcategory":"Repair Shop",
            "type":"Services"
        }
    ],
    "sg:phone":"+1 530 527 4234",
    "sg:postcode":"96080",
    "sg:province":"CA",
    "sg:tags":[
        "welding"
    ],
    "wof:name":"Wiggley's Divine Line",
    "wof:placetype":"venue"
},
  "geometry": {"coordinates":[-122.230192,40.160912],"type":"Point"}
}