{
  "type": "Feature",
  "properties": {
    "addr:full":"34 S del Puerto Ave Patterson CA 95363",
    "addr:housenumber":"34",
    "addr:postcode":"95363",
    "addr:street":"S Del Puerto Ave",
    "iso:country":"US",
    "sg:address":"34 S del Puerto Ave",
    "sg:city":"Patterson",
    "sg:classifiers":[
        {
            "category":"Restaurant",
            "type":"Food & Drink"
        }
    ],
    "sg:phone":"+1 209 892 5282",
    "sg:postcode":"95363",
    "sg:province":"CA",
    "wof:name":"Blues Cafe",
    "wof:placetype":"venue"
},
  "geometry": {"coordinates":[-121.130391,37.47028],"type":"Point"}
}