{
  "type": "Feature",
  "properties": {
    "addr:full":"1449 Simpson Way Escondido CA 92029",
    "addr:housenumber":"1449",
    "addr:postcode":"92029",
    "addr:street":"Simpson Way",
    "iso:country":"US",
    "sg:address":"1449 Simpson Way",
    "sg:city":"Escondido",
    "sg:classifiers":[
        {
            "category":"Manufacturing",
            "subcategory":"Paper Products",
            "type":"Manufacturing & Wholesale Goods"
        }
    ],
    "sg:phone":"+1 760 741 3912",
    "sg:postcode":"92029",
    "sg:province":"CA",
    "sg:tags":[
        "material",
        "honeycomb"
    ],
    "sg:website":"www.unicelcorp.com",
    "wof:name":"Unicel Corp",
    "wof:placetype":"venue"
},
  "geometry": {"coordinates":[-117.10758800000001,33.121952],"type":"Point"}
}