{
  "type": "Feature",
  "properties": {
    "iso:country":"US",
    "sg:address":"111 West Jefferson",
    "sg:city":"Los Angeles",
    "sg:classifiers":[
        {
            "category":"Shopping",
            "subcategory":"Party Supplies",
            "type":"Retail Goods"
        }
    ],
    "sg:phone":"+1 213 748 3002",
    "sg:postcode":"90007",
    "sg:province":"CA",
    "sg:website":"www.thejumperwarehouse.com",
    "wof:name":"The Jumper Warehouse",
    "wof:placetype":"venue"
},
  "geometry": {"coordinates":[-118.273028,34.01885],"type":"Point"}
}