{
  "type": "Feature",
  "properties": {
    "addr:full":"2200 Hamner Ave Norco CA 92860",
    "addr:housenumber":"2200",
    "addr:postcode":"92860",
    "addr:street":"Hamner Ave",
    "iso:country":"US",
    "sg:address":"2200 Hamner Ave",
    "sg:city":"Norco",
    "sg:classifiers":[
        {
            "category":"Social Services",
            "subcategory":"Child Care",
            "type":"Services"
        }
    ],
    "sg:phone":"+1 951 279 3454",
    "sg:postcode":"92860",
    "sg:province":"CA",
    "wof:name":"Little Rascals Pre-School",
    "wof:placetype":"venue"
},
  "geometry": {"coordinates":[-117.560575,33.913399],"type":"Point"}
}