{
  "type": "Feature",
  "properties": {
    "addr:full":"7752 Jackson St Paramount CA 90723",
    "addr:housenumber":"7752",
    "addr:postcode":"90723",
    "addr:street":"Jackson St",
    "iso:country":"US",
    "sg:address":"7752 Jackson St",
    "sg:city":"Paramount",
    "sg:classifiers":[
        {
            "category":"Retail",
            "subcategory":"Storage",
            "type":"Services"
        }
    ],
    "sg:phone":"+1 562 634 7233",
    "sg:postcode":"90723",
    "sg:province":"CA",
    "sg:tags":[
        "self"
    ],
    "wof:name":"Storage Outlet Self Storage",
    "wof:placetype":"venue"
},
  "geometry": {"coordinates":[-118.16300200000001,33.885502],"type":"Point"}
}