{
  "type": "Feature",
  "properties": {
    "addr:full":"1234 Wilshire Blvd Santa Monica CA 90403",
    "addr:housenumber":"1234",
    "addr:postcode":"90403",
    "addr:street":"Wilshire Blvd",
    "iso:country":"US",
    "sg:address":"1234 Wilshire Blvd",
    "sg:city":"Santa Monica",
    "sg:classifiers":[
        {
            "category":"Shopping",
            "subcategory":"Shoes",
            "type":"Retail Goods"
        }
    ],
    "sg:phone":"+1 310 260 9911",
    "sg:postcode":"90403",
    "sg:province":"CA",
    "sg:website":"www.shoepavilion.com",
    "wof:name":"Shoe Pavilion",
    "wof:placetype":"venue"
},
  "geometry": {"coordinates":[-118.49050699999999,34.025304],"type":"Point"}
}