{
  "type": "Feature",
  "properties": {
    "iso:country":"US",
    "sg:address":"763 N Main St",
    "sg:city":"Bishop",
    "sg:classifiers":[
        {
            "category":"Food & Beverages",
            "subcategory":"Bakery",
            "type":"Retail Goods"
        }
    ],
    "sg:phone":"+1 760 873 7156",
    "sg:postcode":"93514",
    "sg:province":"CA",
    "wof:name":"Schats Bakery Erick",
    "wof:placetype":"venue"
},
  "geometry": {"coordinates":[-118.395459,37.368907],"type":"Point"}
}