{
  "type": "Feature",
  "properties": {
    "addr:full":"12328 Gladstone Ave Sylmar CA 91342",
    "addr:housenumber":"12328",
    "addr:postcode":"91342",
    "addr:street":"Gladstone Ave",
    "iso:country":"US",
    "sg:address":"12328 Gladstone Ave",
    "sg:city":"Sylmar",
    "sg:classifiers":[
        {
            "category":"Building & Trades",
            "subcategory":"Construction",
            "type":"Services"
        }
    ],
    "sg:phone":"+1 818 837 7213",
    "sg:postcode":"91342",
    "sg:province":"CA",
    "sg:tags":[
        "elevator"
    ],
    "wof:name":"Action Elevator Inc",
    "wof:placetype":"venue"
},
  "geometry": {"coordinates":[-118.411405,34.294272],"type":"Point"}
}