{
  "type": "Feature",
  "properties": {
    "iso:country":"US",
    "sg:address":"1258 Palomino Dr",
    "sg:city":"Tracy",
    "sg:classifiers":[
        {
            "category":"Professional",
            "type":"Services"
        }
    ],
    "sg:phone":"+1 209 832 2224",
    "sg:postcode":"95376",
    "sg:province":"CA",
    "wof:name":"Gabriel Sarmiento",
    "wof:placetype":"venue"
},
  "geometry": {"coordinates":[-121.441271,37.726095],"type":"Point"}
}