{
  "type": "Feature",
  "properties": {
    "iso:country":"US",
    "sg:address":"1638 L St",
    "sg:city":"Fresno",
    "sg:classifiers":[
        {
            "category":"Social Services",
            "type":"Services"
        }
    ],
    "sg:phone":"+1 559 233 2663",
    "sg:postcode":"93721",
    "sg:province":"CA",
    "sg:tags":[
        "organization",
        "welfare"
    ],
    "wof:name":"Turning Point Transitional Ctr",
    "wof:placetype":"venue"
},
  "geometry": {"coordinates":[-119.795274,36.741972],"type":"Point"}
}