{
  "type": "Feature",
  "properties": {
    "addr:full":"1638 L St Fresno CA 93721",
    "addr:housenumber":"1638",
    "addr:postcode":"93721",
    "addr:street":"L St",
    "iso:country":"US",
    "sg:address":"1638 L St",
    "sg:city":"Fresno",
    "sg:classifiers":[
        {
            "category":"Social Services",
            "type":"Services"
        }
    ],
    "sg:phone":"+1 559 233 2663",
    "sg:postcode":"93721",
    "sg:province":"CA",
    "sg:tags":[
        "organization",
        "welfare"
    ],
    "wof:name":"Turning Point Transitional Ctr",
    "wof:placetype":"venue"
},
  "geometry": {"coordinates":[-119.79527400000001,36.741972],"type":"Point"}
}