{
  "type": "Feature",
  "properties": {
    "addr:full":"7611 Garvey Ave Rosemead CA 91770",
    "addr:housenumber":"7611",
    "addr:postcode":"91770",
    "addr:street":"Garvey Ave",
    "iso:country":"US",
    "sg:address":"7611 Garvey Ave",
    "sg:city":"Rosemead",
    "sg:classifiers":[
        {
            "category":"Shopping",
            "subcategory":"Beauty & Cosmetics",
            "type":"Retail Goods"
        }
    ],
    "sg:phone":"+1 626 280 9105",
    "sg:postcode":"91770",
    "sg:province":"CA",
    "sg:tags":[
        "supply"
    ],
    "wof:name":"Tommy Nail Supply",
    "wof:placetype":"venue"
},
  "geometry": {"coordinates":[-118.102997,34.062801],"type":"Point"}
}