{
  "type": "Feature",
  "properties": {
    "addr:full":"7282 Murdy Cir Huntington Beach CA 92647",
    "addr:housenumber":"7282",
    "addr:postcode":"92647",
    "addr:street":"Murdy Cir",
    "iso:country":"US",
    "sg:address":"7282 Murdy Cir",
    "sg:city":"Huntington Beach",
    "sg:classifiers":[
        {
            "category":"Professional",
            "subcategory":"Employment Agencies",
            "type":"Services"
        }
    ],
    "sg:phone":"+1 714 842 1577",
    "sg:postcode":"92647",
    "sg:province":"CA",
    "sg:website":"www.statco-engineering.com",
    "wof:name":"Statco Engineering",
    "wof:placetype":"venue"
},
  "geometry": {"coordinates":[-118.000889,33.727103],"type":"Point"}
}