{
  "type": "Feature",
  "properties": {
    "addr:full":"9852 Sheep Creek Rd Phelan CA 92371",
    "addr:housenumber":"9852",
    "addr:postcode":"92371",
    "addr:street":"Sheep Creek Rd",
    "iso:country":"US",
    "sg:address":"9852 Sheep Creek Rd",
    "sg:city":"Phelan",
    "sg:classifiers":[
        {
            "category":"Place Of Worship",
            "subcategory":"Church",
            "type":"Public Place"
        },
        {
            "category":"Place Of Worship",
            "type":"Public Place"
        }
    ],
    "sg:phone":"+1 760 868 6335",
    "sg:postcode":"92371",
    "sg:province":"CA",
    "sg:tags":[
        "christ",
        "churches-christian",
        "churches-community"
    ],
    "wof:name":"Phelan Community Church",
    "wof:placetype":"venue"
},
  "geometry": {"coordinates":[-117.57257799999999,34.427544],"type":"Point"}
}