{
  "type": "Feature",
  "properties": {
    "addr:full":"1300 Clay St Ste 820 Oakland CA 94612",
    "addr:housenumber":"1300",
    "addr:postcode":"94612",
    "addr:street":"Clay St Ste 820",
    "iso:country":"US",
    "sg:address":"1300 Clay St Ste 820",
    "sg:city":"Oakland",
    "sg:classifiers":[
        {
            "category":"Professional",
            "subcategory":"Lawyer & Legal Services",
            "type":"Services"
        }
    ],
    "sg:phone":"+1 510 763 5611",
    "sg:postcode":"94612",
    "sg:province":"CA",
    "sg:tags":[
        "divorce",
        "law",
        "family"
    ],
    "wof:name":"Lomhoff Peter Atty",
    "wof:placetype":"venue"
},
  "geometry": {"coordinates":[-122.273819,37.804715],"type":"Point"}
}