{
  "type": "Feature",
  "properties": {
    "addr:full":"100 Monte Ave Piedmont CA 94611",
    "addr:housenumber":"100",
    "addr:postcode":"94611",
    "addr:street":"Monte Ave",
    "iso:country":"US",
    "sg:address":"100 Monte Ave",
    "sg:city":"Piedmont",
    "sg:classifiers":[
        {
            "category":"Shopping",
            "subcategory":"Clothing, Apparel, & Fashions",
            "type":"Retail Goods"
        }
    ],
    "sg:phone":"+1 510 562 2000",
    "sg:postcode":"94611",
    "sg:province":"CA",
    "wof:name":"Rainbow",
    "wof:placetype":"venue"
},
  "geometry": {"coordinates":[-122.231792,37.828514],"type":"Point"}
}