{
  "type": "Feature",
  "properties": {
    "addr:full":"3 Parkcenter Dr Sacramento CA 95825",
    "addr:housenumber":"3",
    "addr:postcode":"95825",
    "addr:street":"Parkcenter Dr",
    "iso:country":"US",
    "sg:address":"3 Parkcenter Dr",
    "sg:city":"Sacramento",
    "sg:classifiers":[
        {
            "category":"Real Estate",
            "subcategory":"Real Estate Services",
            "type":"Services"
        }
    ],
    "sg:phone":"+1 916 921 8166",
    "sg:postcode":"95825",
    "sg:province":"CA",
    "sg:tags":[
        "company",
        "title"
    ],
    "wof:name":"Fidelity National Title",
    "wof:placetype":"venue"
},
  "geometry": {"coordinates":[-121.41521899999999,38.572326],"type":"Point"}
}