{
  "type": "Feature",
  "properties": {
    "iso:country":"US",
    "sg:address":"345 Parkside Dr",
    "sg:city":"San Fernando",
    "sg:classifiers":[
        {
            "category":"Wholesale",
            "subcategory":"Electrical",
            "type":"Manufacturing & Wholesale Goods"
        }
    ],
    "sg:phone":"+1 818 838 3123",
    "sg:postcode":"91340",
    "sg:province":"CA",
    "sg:tags":[
        "lighting",
        "fixture"
    ],
    "wof:name":"Topaz Lighting West Corp",
    "wof:placetype":"venue"
},
  "geometry": {"coordinates":[-118.431879,34.280824],"type":"Point"}
}