{
  "type": "Feature",
  "properties": {
    "iso:country":"US",
    "sg:address":"16701 Prairie Ave",
    "sg:city":"Lawndale",
    "sg:classifiers":[
        {
            "category":"Building & Trades",
            "subcategory":"Construction",
            "type":"Services"
        }
    ],
    "sg:phone":"+1 310 542 9153",
    "sg:postcode":"90260",
    "sg:province":"CA",
    "sg:tags":[
        "hanging",
        "contractor"
    ],
    "wof:name":"Pops Home Improvement",
    "wof:placetype":"venue"
},
  "geometry": {"coordinates":[-118.343794,33.878513],"type":"Point"}
}