{
  "type": "Feature",
  "properties": {
    "iso:country":"US",
    "sg:address":"5322 Misty Meadow Way",
    "sg:city":"Elk Grove",
    "sg:classifiers":[
        {
            "category":"Building & Trades",
            "subcategory":"Construction",
            "type":"Services"
        }
    ],
    "sg:phone":"+1 916 271 3194",
    "sg:postcode":"95758",
    "sg:province":"CA",
    "sg:tags":[
        "general",
        "contractor"
    ],
    "wof:name":"WMO Fernandez Gen Contr",
    "wof:placetype":"venue"
},
  "geometry": {"coordinates":[-121.443829,38.427229],"type":"Point"}
}