{
  "type": "Feature",
  "properties": {
    "addr:full":"218 S Main St Bishop CA 93514",
    "addr:housenumber":"218",
    "addr:postcode":"93514",
    "addr:street":"S Main St",
    "iso:country":"US",
    "sg:address":"218 S Main St",
    "sg:city":"Bishop",
    "sg:classifiers":[
        {
            "category":"Organizations",
            "subcategory":"Non-profit Organization",
            "type":"Services"
        }
    ],
    "sg:phone":"+1 760 872 5570",
    "sg:postcode":"93514",
    "sg:province":"CA",
    "sg:tags":[
        "action",
        "agency",
        "community"
    ],
    "wof:name":"IMACA Community Work Exprn",
    "wof:placetype":"venue"
},
  "geometry": {"coordinates":[-118.395195,37.36034],"type":"Point"}
}