{
  "type": "Feature",
  "properties": {
    "iso:country":"US",
    "sg:address":"5554 Monterey Hwy",
    "sg:city":"San Jose",
    "sg:classifiers":[
        {
            "category":"Food & Beverages",
            "subcategory":"Specialty",
            "type":"Retail Goods"
        }
    ],
    "sg:phone":"+1 408 972 4283",
    "sg:postcode":"95138",
    "sg:province":"CA",
    "sg:tags":[
        "water",
        "bulk",
        "company"
    ],
    "wof:name":"Crystal Pure Water",
    "wof:placetype":"venue"
},
  "geometry": {"coordinates":[-121.795418,37.251674],"type":"Point"}
}