{
  "type": "Feature",
  "properties": {
    "addr:full":"17225 Studebaker Rd Cerritos CA 90703",
    "addr:housenumber":"17225",
    "addr:postcode":"ca 90703",
    "addr:street":"Studebaker Rd",
    "iso:country":"US",
    "sg:address":"17225 Studebaker Rd",
    "sg:city":"Cerritos",
    "sg:classifiers":[
        {
            "category":"Professional",
            "subcategory":"Lawyer & Legal Services",
            "type":"Services"
        }
    ],
    "sg:phone":"+1 562 860 1900",
    "sg:postcode":"90703",
    "sg:province":"CA",
    "sg:tags":[
        "attorney",
        "practice",
        "plan"
    ],
    "wof:name":"Law Offices Of Duarte Gre",
    "wof:placetype":"venue"
},
  "geometry": {"coordinates":[-118.09983099999999,33.875053],"type":"Point"}
}