{
  "type": "Feature",
  "properties": {
    "iso:country":"US",
    "sg:address":"320 Dardanelli Ln",
    "sg:city":"Los Gatos",
    "sg:classifiers":[
        {
            "category":"Health Services",
            "subcategory":"Doctor",
            "type":"Services"
        }
    ],
    "sg:phone":"+1 408 866 7830",
    "sg:postcode":"95032",
    "sg:province":"CA",
    "sg:tags":[
        "pediatrician"
    ],
    "wof:name":"Keswani Sanjivini MD",
    "wof:placetype":"venue"
},
  "geometry": {"coordinates":[-121.96700300000001,37.261799],"type":"Point"}
}