{
  "type": "Feature",
  "properties": {
    "acgov:api":"819.0",
    "acgov:type":"MS",
    "addr:full":"3951 East Avenue Livermore CA",
    "wof:categories":[
        "education_and_religion:education=school"
    ],
    "wof:name":"East Avenue Middle",
    "wof:placetype":"venue"
},
  "geometry": {"coordinates":[-121.75002493796855,37.67973396210878],"type":"Point"}
}