{
  "type": "Feature",
  "properties": {
    "iso:country":"US",
    "sg:address":"27536 Ynez Rd",
    "sg:city":"Temecula",
    "sg:classifiers":[
        {
            "category":"Shopping",
            "subcategory":"Books",
            "type":"Retail Goods"
        }
    ],
    "sg:phone":"+1 951 676 7551",
    "sg:postcode":"92591",
    "sg:province":"CA",
    "sg:tags":[
        "dealer"
    ],
    "wof:name":"Crown Books",
    "wof:placetype":"venue"
},
  "geometry": {"coordinates":[-117.150088,33.50646],"type":"Point"}
}