{
  "type": "Feature",
  "properties": {
    "iso:country":"US",
    "sg:address":"1227 Pine St",
    "sg:city":"Paso Robles",
    "sg:classifiers":[
        {
            "category":"Shopping",
            "subcategory":"Gifts & Souvenirs",
            "type":"Retail Goods"
        }
    ],
    "sg:phone":"+1 805 237 0191",
    "sg:postcode":"93446",
    "sg:province":"CA",
    "sg:tags":[
        "merchandise"
    ],
    "wof:name":"Kalis Meowtique Collectibles",
    "wof:placetype":"venue"
},
  "geometry": {"coordinates":[-120.68894,35.627037],"type":"Point"}
}