{
  "type": "Feature",
  "properties": {
    "iso:country":"US",
    "sg:address":"677 W Ranger Ave",
    "sg:city":"Alameda",
    "sg:classifiers":[
        {
            "category":"Social Services",
            "type":"Services"
        }
    ],
    "sg:phone":"+1 510 898 7800",
    "sg:postcode":"94501",
    "sg:province":"CA",
    "sg:tags":[
        "human"
    ],
    "wof:name":"Alameda Point Collaborative",
    "wof:placetype":"venue"
},
  "geometry": {"coordinates":[-122.2987,37.784592],"type":"Point"}
}