{
  "type": "Feature",
  "properties": {
    "addr:full":"28375 Chrisman Rd Tracy CA 95304",
    "addr:postcode":"28375;95304",
    "addr:street":"Chrisman Rd",
    "iso:country":"US",
    "sg:address":"28375 Chrisman Rd",
    "sg:city":"Tracy",
    "sg:classifiers":[
        {
            "category":"Organizations",
            "subcategory":"Political Organization",
            "type":"Services"
        }
    ],
    "sg:phone":"+1 209 836 9496",
    "sg:postcode":"95304",
    "sg:province":"CA",
    "sg:website":"www.richardpombo.com",
    "wof:name":"Richard Pombo For Congress",
    "wof:placetype":"venue"
},
  "geometry": {"coordinates":[-121.398072,37.697711],"type":"Point"}
}