{
  "type": "Feature",
  "properties": {
    "iso:country":"US",
    "sg:address":"895 Washington St",
    "sg:city":"San Francisco",
    "sg:classifiers":[
        {
            "category":"Shopping",
            "subcategory":"Pharmacy",
            "type":"Retail Goods"
        }
    ],
    "sg:phone":"+1 415 989 9292",
    "sg:postcode":"94108",
    "sg:province":"CA",
    "wof:name":"Mandarin Tower Pharmacy",
    "wof:placetype":"venue"
},
  "geometry": {"coordinates":[-122.40779000000001,37.794912],"type":"Point"}
}