{
  "type": "Feature",
  "properties": {
    "iso:country":"US",
    "sg:address":"5355 Sierra Road",
    "sg:city":"San Jose",
    "sg:classifiers":[
        {
            "category":"Shopping",
            "subcategory":"Bicycles & Sporting Goods",
            "type":"Retail Goods"
        }
    ],
    "sg:phone":"+1 408 923 7777",
    "sg:postcode":"95132",
    "sg:province":"CA",
    "wof:name":"Black Knight USA",
    "wof:placetype":"venue"
},
  "geometry": {"coordinates":[-121.79091699999999,37.413449],"type":"Point"}
}