{
  "type": "Feature",
  "properties": {
    "addr:full":"2030 Addison St Ste 410 Suite 308 Berkeley CA 94704",
    "addr:housenumber":"2030",
    "addr:postcode":"94704",
    "addr:street":"Addison St Ste 410 Suite 308",
    "iso:country":"US",
    "sg:address":"2030 Addison St Ste 410 Suite 308",
    "sg:city":"Berkeley",
    "sg:classifiers":[
        {
            "category":"Professional",
            "subcategory":"Lawyer & Legal Services",
            "type":"Services"
        }
    ],
    "sg:phone":"+1 510 548 7070",
    "sg:postcode":"94704",
    "sg:province":"CA",
    "sg:tags":[
        "information",
        "attorney",
        "referral",
        "plan"
    ],
    "wof:name":"Alexander Berkey Williams & Weathers Llp",
    "wof:placetype":"venue"
},
  "geometry": {"coordinates":[-122.269274,37.870979],"type":"Point"}
}