{
  "type": "Feature",
  "properties": {
    "iso:country":"US",
    "sg:address":"26450 Ruether Ave",
    "sg:city":"Santa Clarita",
    "sg:classifiers":[
        {
            "category":"Personal",
            "type":"Services"
        }
    ],
    "sg:phone":"+1 661 250 8420",
    "sg:postcode":"91350",
    "sg:province":"CA",
    "sg:tags":[
        "home"
    ],
    "wof:name":"Frames Connection",
    "wof:placetype":"venue"
},
  "geometry": {"coordinates":[-118.501999,34.4105],"type":"Point"}
}