{
  "type": "Feature",
  "properties": {
    "iso:country":"US",
    "sg:address":"1201 S Anaheim Blvd",
    "sg:city":"Anaheim",
    "sg:classifiers":[
        {
            "category":"Restaurant",
            "type":"Food & Drink"
        }
    ],
    "sg:phone":"+1 714 635 8750",
    "sg:postcode":"92805",
    "sg:province":"CA",
    "wof:name":"Burger King",
    "wof:placetype":"venue"
},
  "geometry": {"coordinates":[-117.90799699999999,33.817699],"type":"Point"}
}