{
  "type": "Feature",
  "properties": {
    "addr:full":"3296 Runnymede Ct Pleasanton CA 94588",
    "addr:housenumber":"3296",
    "addr:postcode":"94588",
    "addr:street":"Runnymede Ct",
    "iso:country":"US",
    "sg:address":"3296 Runnymede Ct",
    "sg:city":"Pleasanton",
    "sg:classifiers":[
        {
            "category":"Manufacturing",
            "subcategory":"Tools & Machinery",
            "type":"Manufacturing & Wholesale Goods"
        }
    ],
    "sg:phone":"+1 925 426 0904",
    "sg:postcode":"94588",
    "sg:province":"CA",
    "sg:tags":[
        "machine",
        "shop",
        "industrial",
        "mfg"
    ],
    "wof:name":"Tri Valley Tool & Mfg",
    "wof:placetype":"venue"
},
  "geometry": {"coordinates":[-121.869298,37.694403],"type":"Point"}
}