{
  "type": "Feature",
  "properties": {
    "addr:full":"338 8th St Oakland CA 94607",
    "addr:housenumber":"338",
    "addr:postcode":"94607",
    "addr:street":"8Th St",
    "iso:country":"US",
    "sg:address":"338 8th St",
    "sg:city":"Oakland",
    "sg:classifiers":[
        {
            "category":"Health Services",
            "subcategory":"Clinic",
            "type":"Services"
        }
    ],
    "sg:phone":"+1 510 835 4190",
    "sg:postcode":"94607",
    "sg:province":"CA",
    "sg:tags":[
        "medical"
    ],
    "wof:name":"Unilab Quest Diagnostics, Inc",
    "wof:placetype":"venue"
},
  "geometry": {"coordinates":[-122.27110399999999,37.799167],"type":"Point"}
}