{
  "type": "Feature",
  "properties": {
    "addr:full":"2310 Tripaldi Way Hayward CA 94545",
    "addr:housenumber":"2310",
    "addr:postcode":"94545",
    "addr:street":"Tripaldi Way",
    "iso:country":"US",
    "sg:address":"2310 Tripaldi Way",
    "sg:city":"Hayward",
    "sg:classifiers":[
        {
            "category":"Personal",
            "subcategory":"Barber",
            "type":"Services"
        }
    ],
    "sg:phone":"+1 510 881 1516",
    "sg:postcode":"94545",
    "sg:province":"CA",
    "wof:name":"Barber Construction",
    "wof:placetype":"venue"
},
  "geometry": {"coordinates":[-122.083102,37.614409],"type":"Point"}
}