{
  "type": "Feature",
  "properties": {
    "iso:country":"US",
    "sg:address":"2043 Springs Rd",
    "sg:city":"Vallejo",
    "sg:classifiers":[
        {
            "category":"Food & Beverages",
            "subcategory":"Groceries & Convenience Stores",
            "type":"Retail Goods"
        }
    ],
    "sg:phone":"+1 707 552 2178",
    "sg:postcode":"94591",
    "sg:province":"CA",
    "sg:tags":[
        "grocer"
    ],
    "wof:name":"G & C Dollar Plus Inc",
    "wof:placetype":"venue"
},
  "geometry": {"coordinates":[-122.217736,38.106017],"type":"Point"}
}