{
  "type": "Feature",
  "properties": {
    "addr:full":"1131 W 6th St Ontario CA 91762",
    "addr:housenumber":"1131",
    "addr:postcode":"91762",
    "addr:street":"W 6Th St",
    "iso:country":"US",
    "sg:address":"1131 W 6th St",
    "sg:city":"Ontario",
    "sg:classifiers":[
        {
            "category":"Professional",
            "subcategory":"Lawyer & Legal Services",
            "type":"Services"
        }
    ],
    "sg:phone":"+1 909 983 4777",
    "sg:postcode":"91762",
    "sg:province":"CA",
    "sg:tags":[
        "attorney"
    ],
    "wof:name":"Haslam & Perri",
    "wof:placetype":"venue"
},
  "geometry": {"coordinates":[-117.67171,34.085089],"type":"Point"}
}