{
  "type": "Feature",
  "properties": {
    "iso:country":"US",
    "sg:address":"4224 Pleasant Valley Rd",
    "sg:city":"Camarillo",
    "sg:classifiers":[
        {
            "category":"Food & Beverages",
            "subcategory":"Groceries & Convenience Stores",
            "type":"Retail Goods"
        }
    ],
    "sg:phone":"+1 805 484 0703",
    "sg:postcode":"93012",
    "sg:province":"CA",
    "wof:name":"East Farms",
    "wof:placetype":"venue"
},
  "geometry": {"coordinates":[-119.014,34.205799],"type":"Point"}
}