{
  "type": "Feature",
  "properties": {
    "iso:country":"US",
    "sg:address":"43101 Portola Ave",
    "sg:city":"Palm Desert",
    "sg:classifiers":[
        {
            "category":"Real Estate",
            "subcategory":"Developer",
            "type":"Services"
        }
    ],
    "sg:phone":"+1 760 346 1508",
    "sg:postcode":"92260",
    "sg:province":"CA",
    "sg:tags":[
        "mobile",
        "home"
    ],
    "wof:name":"Palm Desert Mobile Estates",
    "wof:placetype":"venue"
},
  "geometry": {"coordinates":[-116.373792,33.736111],"type":"Point"}
}