{
  "type": "Feature",
  "properties": {
    "addr:full":"13203 Rosecrans Ave Santa Fe Springs CA 90670",
    "addr:housenumber":"13203",
    "addr:postcode":"90670",
    "addr:street":"Rosecrans Ave",
    "iso:country":"US",
    "sg:address":"13203 Rosecrans Ave",
    "sg:city":"Santa Fe Springs",
    "sg:classifiers":[
        {
            "category":"Shopping",
            "subcategory":"Computers & Home Electronics",
            "type":"Retail Goods"
        }
    ],
    "sg:phone":"+1 562 229 3113",
    "sg:postcode":"90670",
    "sg:province":"CA",
    "sg:tags":[
        "equipment",
        "dealer"
    ],
    "wof:name":"Aiya Inc",
    "wof:placetype":"venue"
},
  "geometry": {"coordinates":[-118.049277,33.902415],"type":"Point"}
}