{
  "type": "Feature",
  "properties": {
    "addr:full":"6723 Mowry Ave Newark CA 94560",
    "addr:housenumber":"6723",
    "addr:postcode":"94560",
    "addr:street":"Mowry Ave",
    "iso:country":"US",
    "sg:address":"6723 Mowry Ave",
    "sg:city":"Newark",
    "sg:classifiers":[
        {
            "category":"Professional",
            "type":"Services"
        }
    ],
    "sg:phone":"+1 510 791 1371",
    "sg:postcode":"94560",
    "sg:province":"CA",
    "wof:name":"Vistamax",
    "wof:placetype":"venue"
},
  "geometry": {"coordinates":[-122.010654,37.519188],"type":"Point"}
}