{
  "type": "Feature",
  "properties": {
    "iso:country":"US",
    "sg:address":"9905 Cherry Ave",
    "sg:city":"Fontana",
    "sg:classifiers":[
        {
            "category":"Autos & Motor Vehicles",
            "subcategory":"Automobile Sales",
            "type":"Retail Goods"
        }
    ],
    "sg:phone":"+1 909 815 5563",
    "sg:postcode":"92335",
    "sg:province":"CA",
    "sg:tags":[
        "truck"
    ],
    "wof:name":"Allied Enterprises",
    "wof:placetype":"venue"
},
  "geometry": {"coordinates":[-117.488793,34.077271],"type":"Point"}
}