{
  "type": "Feature",
  "properties": {
    "addr:full":"467 Eaton Ave Tracy CA 95376",
    "addr:housenumber":"467",
    "addr:postcode":"95376",
    "addr:street":"Eaton Ave",
    "iso:country":"US",
    "sg:address":"467 Eaton Ave",
    "sg:city":"Tracy",
    "sg:classifiers":[
        {
            "category":"Health Services",
            "subcategory":"Doctor",
            "type":"Services"
        }
    ],
    "sg:phone":"+1 209 834 0626",
    "sg:postcode":"95376",
    "sg:province":"CA",
    "sg:tags":[
        "physician",
        "surgeon"
    ],
    "wof:name":"Thomas B Mc Nemar MD",
    "wof:placetype":"venue"
},
  "geometry": {"coordinates":[-121.418302,37.743564],"type":"Point"}
}