{
  "type": "Feature",
  "properties": {
    "iso:country":"US",
    "sg:address":"641 10th Ave",
    "sg:city":"Kingsburg",
    "sg:classifiers":[
        {
            "category":"Shopping",
            "type":"Retail Goods"
        }
    ],
    "sg:phone":"+1 559 897 2110",
    "sg:postcode":"93631",
    "sg:province":"CA",
    "sg:tags":[
        "monument"
    ],
    "wof:name":"Beer Monument Works Inc",
    "wof:placetype":"venue"
},
  "geometry": {"coordinates":[-119.556899,36.505963],"type":"Point"}
}