{
  "type": "Feature",
  "properties": {
    "iso:country":"US",
    "sg:address":"15400 Charter Oak Blvd",
    "sg:city":"Salinas",
    "sg:classifiers":[
        {
            "category":"Health Services",
            "subcategory":"Health Practitioner",
            "type":"Services"
        }
    ],
    "sg:phone":"+1 831 633 2269",
    "sg:postcode":"93907",
    "sg:province":"CA",
    "sg:tags":[
        "nurse",
        "registry"
    ],
    "wof:name":"Counseling & Consultation Svc",
    "wof:placetype":"venue"
},
  "geometry": {"coordinates":[-121.706311,36.780672],"type":"Point"}
}