{
  "type": "Feature",
  "properties": {
    "iso:country":"US",
    "sg:address":"1 Wildwood Gdns",
    "sg:city":"Piedmont",
    "sg:classifiers":[
        {
            "category":"Professional",
            "subcategory":"Management & Consulting",
            "type":"Services"
        }
    ],
    "sg:phone":"+1 415 244 4241",
    "sg:postcode":"94611",
    "sg:province":"CA",
    "sg:tags":[
        "consultant"
    ],
    "wof:name":"Michael Papanek Consulting",
    "wof:placetype":"venue"
},
  "geometry": {"coordinates":[-122.22840100000001,37.819653],"type":"Point"}
}