{
  "type": "Feature",
  "properties": {
    "iso:country":"US",
    "sg:address":"3733 Main St",
    "sg:city":"Chula Vista",
    "sg:classifiers":[
        {
            "category":"Restaurant",
            "type":"Food & Drink"
        }
    ],
    "sg:phone":"+1 619 476 6623",
    "sg:postcode":"91911",
    "sg:province":"CA",
    "wof:name":"El Meson",
    "wof:placetype":"venue"
},
  "geometry": {"coordinates":[-117.05219,32.594644],"type":"Point"}
}