{
  "type": "Feature",
  "properties": {
    "addr:full":"14554 Brookhurst St Westminster CA 92683",
    "addr:housenumber":"14554",
    "addr:postcode":"92683",
    "addr:street":"Brookhurst St",
    "iso:country":"US",
    "sg:address":"14554 Brookhurst St",
    "sg:city":"Westminster",
    "sg:classifiers":[
        {
            "category":"Autos & Motor Vehicles",
            "subcategory":"Auto Supplies",
            "type":"Retail Goods"
        }
    ],
    "sg:phone":"+1 714 418 0575",
    "sg:postcode":"92683",
    "sg:province":"CA",
    "wof:name":"Sound World",
    "wof:placetype":"venue"
},
  "geometry": {"coordinates":[-117.954804,33.74956],"type":"Point"}
}