{
  "type": "Feature",
  "properties": {
    "iso:country":"US",
    "sg:address":"1058 W 9th St",
    "sg:city":"Upland",
    "sg:classifiers":[
        {
            "category":"Retail",
            "subcategory":"Auto Repair",
            "type":"Services"
        }
    ],
    "sg:phone":"+1 909 949 9950",
    "sg:postcode":"91786",
    "sg:province":"CA",
    "sg:tags":[
        "recreational",
        "vehicle"
    ],
    "wof:name":"Best Rv Svc & Repair",
    "wof:placetype":"venue"
},
  "geometry": {"coordinates":[-117.668569,34.095961],"type":"Point"}
}