{
  "type": "Feature",
  "properties": {
    "addr:full":"3101 Garrity Way Richmond CA 94806",
    "addr:housenumber":"3101",
    "addr:postcode":"94806",
    "addr:street":"Garrity Way",
    "iso:country":"US",
    "sg:address":"3101 Garrity Way",
    "sg:city":"Richmond",
    "sg:classifiers":[
        {
            "category":"Restaurant",
            "type":"Food & Drink"
        }
    ],
    "sg:phone":"+1 510 222 9802",
    "sg:postcode":"94806",
    "sg:province":"CA",
    "wof:name":"Chevys Fresh Mex Mexican",
    "wof:placetype":"venue"
},
  "geometry": {"coordinates":[-122.32126,37.978114],"type":"Point"}
}