{
  "type": "Feature",
  "properties": {
    "addr:full":"27555 Ynez Rd Ste 203 Temecula CA 92591",
    "addr:housenumber":"27555",
    "addr:postcode":"92591",
    "addr:street":"Ynez Rd Ste 203",
    "iso:country":"US",
    "sg:address":"27555 Ynez Rd Ste 203",
    "sg:city":"Temecula",
    "sg:classifiers":[
        {
            "category":"Communications",
            "subcategory":"Television Station",
            "type":"Services"
        }
    ],
    "sg:phone":"+1 951 587 8660",
    "sg:postcode":"92591",
    "sg:province":"CA",
    "sg:tags":[
        "satellite",
        "cable"
    ],
    "sg:website":"http://www.timewarnercable.com",
    "wof:name":"Time Warner",
    "wof:placetype":"venue"
},
  "geometry": {"coordinates":[-117.14940199999999,33.503993],"type":"Point"}
}