{
  "type": "Feature",
  "properties": {
    "iso:country":"US",
    "sg:address":"1919 G St",
    "sg:city":"Bakersfield",
    "sg:classifiers":[
        {
            "category":"Health Services",
            "subcategory":"Doctor",
            "type":"Services"
        }
    ],
    "sg:phone":"+1 661 323 8585",
    "sg:postcode":"93301",
    "sg:province":"CA",
    "sg:tags":[
        "dentist"
    ],
    "wof:name":"Stephen E KANN Inc",
    "wof:placetype":"venue"
},
  "geometry": {"coordinates":[-119.022424,35.37703],"type":"Point"}
}