{
  "type": "Feature",
  "properties": {
    "addr:full":"1111 E 8th St Upland CA 91786",
    "addr:housenumber":"1111",
    "addr:postcode":"91786",
    "addr:street":"E 8Th St",
    "iso:country":"US",
    "sg:address":"1111 E 8th St",
    "sg:city":"Upland",
    "sg:classifiers":[
        {
            "category":"Food & Beverages",
            "subcategory":"Specialty",
            "type":"Retail Goods"
        }
    ],
    "sg:phone":"+1 909 946 1080",
    "sg:postcode":"91786",
    "sg:province":"CA",
    "sg:tags":[
        "herb"
    ],
    "wof:name":"Yeh Herbs Mfg",
    "wof:placetype":"venue"
},
  "geometry": {"coordinates":[-117.63319,34.092584],"type":"Point"}
}