{
  "type": "Feature",
  "properties": {
    "iso:country":"US",
    "sg:address":"2101 Alpine Blvd",
    "sg:city":"Alpine",
    "sg:classifiers":[
        {
            "category":"Shopping",
            "subcategory":"Pets & Pet Supplies",
            "type":"Retail Goods"
        }
    ],
    "sg:phone":"+1 619 445 1550",
    "sg:postcode":"91901",
    "sg:province":"CA",
    "sg:tags":[
        "furnishing",
        "dog",
        "store",
        "cat"
    ],
    "wof:name":"Natural Instincts Healthy Pet Center",
    "wof:placetype":"venue"
},
  "geometry": {"coordinates":[-116.767887,32.83558],"type":"Point"}
}