{
  "type": "Feature",
  "properties": {
    "iso:country":"US",
    "sg:address":"3974 Atlantic Ave",
    "sg:city":"Long Beach",
    "sg:classifiers":[
        {
            "category":"Wholesale",
            "subcategory":"Construction Materials",
            "type":"Manufacturing & Wholesale Goods"
        }
    ],
    "sg:phone":"+1 562 938 9311",
    "sg:postcode":"90807",
    "sg:province":"CA",
    "sg:tags":[
        "glass"
    ],
    "wof:name":"Glass Products",
    "wof:placetype":"venue"
},
  "geometry": {"coordinates":[-118.184924,33.82939],"type":"Point"}
}