{
  "type": "Feature",
  "properties": {
    "iso:country":"US",
    "sg:address":"13910 Struikman Rd",
    "sg:city":"Buena Park",
    "sg:classifiers":[
        {
            "category":"Recreation",
            "subcategory":"Boat Charter",
            "type":"Entertainment"
        }
    ],
    "sg:phone":"+1 714 739 1003",
    "sg:postcode":"90620",
    "sg:province":"CA",
    "sg:tags":[
        "boating"
    ],
    "wof:name":"Lee's Marine",
    "wof:placetype":"venue"
},
  "geometry": {"coordinates":[-118.010002,33.8419],"type":"Point"}
}