{
  "type": "Feature",
  "properties": {
    "addr:full":"11425 Rivera Rd Whittier CA 90606",
    "addr:housenumber":"11425",
    "addr:postcode":"90606",
    "addr:street":"Rivera Rd",
    "iso:country":"US",
    "sg:address":"11425 Rivera Rd",
    "sg:city":"Whittier",
    "sg:classifiers":[
        {
            "category":"Education",
            "subcategory":"School",
            "type":"Public Place"
        }
    ],
    "sg:phone":"+1 562 695 0637",
    "sg:postcode":"90606",
    "sg:province":"CA",
    "sg:website":"losnietosms.losnietos.k12.ca.us",
    "wof:name":"Los Nietos Middle School",
    "wof:placetype":"venue"
},
  "geometry": {"coordinates":[-118.074997,33.963299],"type":"Point"}
}