{
  "type": "Feature",
  "properties": {
    "iso:country":"US",
    "sg:address":"575 Country Club Dr",
    "sg:city":"Simi Valley",
    "sg:classifiers":[
        {
            "category":"Shopping",
            "subcategory":"Gifts & Souvenirs",
            "type":"Retail Goods"
        }
    ],
    "sg:phone":"+1 805 522 6987",
    "sg:postcode":"93065",
    "sg:province":"CA",
    "sg:tags":[
        "shop"
    ],
    "wof:name":"Eclectique",
    "wof:placetype":"venue"
},
  "geometry": {"coordinates":[-118.81269,34.252508],"type":"Point"}
}