{
  "type": "Feature",
  "properties": {
    "iso:country":"US",
    "sg:address":"300 S Grand Ave",
    "sg:city":"Los Angeles",
    "sg:classifiers":[
        {
            "category":"Professional",
            "subcategory":"Lawyer & Legal Services",
            "type":"Services"
        }
    ],
    "sg:phone":"+1 213 612 2528",
    "sg:postcode":"90071",
    "sg:province":"CA",
    "wof:name":"Ruskin Steven M Atty",
    "wof:placetype":"venue"
},
  "geometry": {"coordinates":[-118.253998,34.051601],"type":"Point"}
}