{
  "type": "Feature",
  "properties": {
    "iso:country":"US",
    "sg:address":"4140 Paramount Blvd",
    "sg:city":"Lakewood",
    "sg:classifiers":[
        {
            "category":"Education",
            "subcategory":"Special Training",
            "type":"Public Place"
        }
    ],
    "sg:phone":"+1 562 496 2308",
    "sg:postcode":"90712",
    "sg:province":"CA",
    "sg:tags":[
        "school",
        "instruction",
        "traffic",
        "driving"
    ],
    "sg:website":"www.lowbudgettraffic.com/",
    "wof:name":"Low Budget Traffic School",
    "wof:placetype":"venue"
},
  "geometry": {"coordinates":[-118.15989399999999,33.833668],"type":"Point"}
}