{
  "type": "Feature",
  "properties": {
    "addr:full":"210 E Avenue L Lancaster CA 93535",
    "addr:housenumber":"210",
    "addr:postcode":"93535",
    "addr:street":"E Avenue L",
    "iso:country":"US",
    "sg:address":"210 E Avenue L",
    "sg:city":"Lancaster",
    "sg:classifiers":[
        {
            "category":"Building & Trades",
            "subcategory":"Construction",
            "type":"Services"
        }
    ],
    "sg:phone":"+1 661 940 8600",
    "sg:postcode":"93535",
    "sg:province":"CA",
    "sg:tags":[
        "handyman"
    ],
    "wof:name":"Age Nu Auto Repair",
    "wof:placetype":"venue"
},
  "geometry": {"coordinates":[-118.127836,34.659993],"type":"Point"}
}