{
  "type": "Feature",
  "properties": {
    "iso:country":"US",
    "sg:address":"S. Sepulveda and La Tijera",
    "sg:city":"Los Angeles",
    "sg:classifiers":[
        {
            "category":"Restaurant",
            "type":"Food & Drink"
        }
    ],
    "sg:postcode":"90045",
    "sg:province":"CA",
    "wof:name":"Glass Fruit Cart Vendor",
    "wof:placetype":"venue"
},
  "geometry": {"coordinates":[-118.396194,33.957238],"type":"Point"}
}