{
  "type": "Feature",
  "properties": {
    "addr:full":"26921 Aliso Creek Rd Ste A Aliso Viejo CA 92656",
    "addr:housenumber":"26921",
    "addr:postcode":"92656",
    "addr:street":"Aliso Creek Rd Ste A",
    "iso:country":"US",
    "sg:address":"26921 Aliso Creek Rd Ste A",
    "sg:city":"Aliso Viejo",
    "sg:classifiers":[
        {
            "category":"Shopping",
            "subcategory":"Mobile Phones",
            "type":"Retail Goods"
        }
    ],
    "sg:phone":"+1 949 448 5101",
    "sg:postcode":"92656",
    "sg:province":"CA",
    "wof:name":"Sprint",
    "wof:placetype":"venue"
},
  "geometry": {"coordinates":[-117.723664,33.572],"type":"Point"}
}