{
  "type": "Feature",
  "properties": {
    "iso:country":"US",
    "sg:address":"1802 Commercenter Ct",
    "sg:city":"San Bernardino",
    "sg:classifiers":[
        {
            "category":"Wholesale",
            "subcategory":"Medical Equipment & Supplies",
            "type":"Manufacturing & Wholesale Goods"
        }
    ],
    "sg:phone":"+1 909 890 2699",
    "sg:postcode":"92408",
    "sg:province":"CA",
    "sg:tags":[
        "hospital"
    ],
    "wof:name":"Lincare",
    "wof:placetype":"venue"
},
  "geometry": {"coordinates":[-117.282341,34.068611],"type":"Point"}
}