{
  "type": "Feature",
  "properties": {
    "addr:full":"2020 Pioneer Ct San Mateo CA 94403",
    "addr:housenumber":"2020",
    "addr:postcode":"94403",
    "addr:street":"Pioneer Ct",
    "iso:country":"US",
    "sg:address":"2020 Pioneer Ct",
    "sg:city":"San Mateo",
    "sg:classifiers":[
        {
            "category":"Professional",
            "type":"Services"
        }
    ],
    "sg:phone":"+1 650 578 0140",
    "sg:postcode":"94403",
    "sg:province":"CA",
    "sg:tags":[
        "establishment"
    ],
    "wof:name":"Asset Analysis",
    "wof:placetype":"venue"
},
  "geometry": {"coordinates":[-122.31190700000001,37.54652],"type":"Point"}
}