{
  "type": "Feature",
  "properties": {
    "iso:country":"US",
    "sg:address":"1058 Terminal Way",
    "sg:city":"San Carlos",
    "sg:classifiers":[
        {
            "category":"Manufacturing",
            "subcategory":"Metals",
            "type":"Manufacturing & Wholesale Goods"
        }
    ],
    "sg:phone":"+1 650 596 8240",
    "sg:postcode":"94070",
    "sg:province":"CA",
    "wof:name":"A B Heagney Custom Metal Fab",
    "wof:placetype":"venue"
},
  "geometry": {"coordinates":[-122.256561,37.506514],"type":"Point"}
}