{
  "type": "Feature",
  "properties": {
    "iso:country":"US",
    "sg:address":"15300 del Monte Farms Rd",
    "sg:city":"Castroville",
    "sg:classifiers":[
        {
            "category":"Farming",
            "subcategory":"Poultry Farm",
            "type":"Manufacturing & Wholesale Goods"
        }
    ],
    "sg:phone":"+1 831 633 0529",
    "sg:postcode":"95012",
    "sg:province":"CA",
    "sg:tags":[
        "hatchery"
    ],
    "wof:name":"D&H Ornamental Poultry",
    "wof:placetype":"venue"
},
  "geometry": {"coordinates":[-121.70790100000001,36.791123],"type":"Point"}
}