{
  "type": "Feature",
  "properties": {
    "iso:country":"US",
    "sg:address":"32331 Golden Lantern",
    "sg:city":"Laguna Niguel",
    "sg:classifiers":[
        {
            "category":"Banks & Credit Unions",
            "subcategory":"Bank",
            "type":"Services"
        }
    ],
    "sg:phone":"+1 949 240 0709",
    "sg:postcode":"92677",
    "sg:province":"CA",
    "wof:name":"Wells Fargo Bank",
    "wof:placetype":"venue"
},
  "geometry": {"coordinates":[-117.692931,33.49833],"type":"Point"}
}