{
  "type": "Feature",
  "properties": {
    "addr:full":"628 Royer St Roseville CA 95678",
    "addr:housenumber":"628",
    "addr:postcode":"95678",
    "addr:street":"Royer St",
    "iso:country":"US",
    "sg:address":"628 Royer St",
    "sg:city":"Roseville",
    "sg:classifiers":[
        {
            "category":"Organizations",
            "subcategory":"Religious Organization",
            "type":"Services"
        }
    ],
    "sg:phone":"+1 916 774 9933",
    "sg:postcode":"95678",
    "sg:province":"CA",
    "sg:tags":[
        "church"
    ],
    "wof:name":"Clear Voice Ministries Church",
    "wof:placetype":"venue"
},
  "geometry": {"coordinates":[-121.285602,38.744723],"type":"Point"}
}