{
  "type": "Feature",
  "properties": {
    "addr:full":"431 Snta Paula Ojai Rd Santa Paula CA 93060",
    "addr:housenumber":"431",
    "addr:postcode":"93060",
    "addr:street":"Snta Paula Ojai Rd",
    "iso:country":"US",
    "sg:address":"431 Snta Paula Ojai Rd",
    "sg:city":"Santa Paula",
    "sg:classifiers":[
        {
            "category":"Restaurant",
            "type":"Food & Drink"
        }
    ],
    "sg:menulink":"http://www.allmenus.com/ca/santa-paula/74158-dominos-pizza/menu/",
    "sg:phone":"+1 805 933 2771",
    "sg:postcode":"93060",
    "sg:province":"CA",
    "sg:tags":[
        "american",
        "wing",
        "pizza"
    ],
    "wof:name":"Domino's Pizza",
    "wof:placetype":"venue"
},
  "geometry": {"coordinates":[-119.061091,34.360795],"type":"Point"}
}