{
  "type": "Feature",
  "properties": {
    "iso:country":"US",
    "sg:address":"1150 Silverado St",
    "sg:city":"La Jolla",
    "sg:classifiers":[
        {
            "category":"Professional",
            "subcategory":"Accounting & Tax Preparation",
            "type":"Services"
        }
    ],
    "sg:phone":"+1 858 459 1007",
    "sg:postcode":"92037",
    "sg:province":"CA",
    "sg:tags":[
        "accountant"
    ],
    "wof:name":"Johnston Raymond D CPA",
    "wof:placetype":"venue"
},
  "geometry": {"coordinates":[-117.272003,32.845501],"type":"Point"}
}