{
  "type": "Feature",
  "properties": {
    "addr:full":"1504 S Coast Hwy Laguna Beach CA 92651",
    "addr:housenumber":"1504",
    "addr:postcode":"92651",
    "addr:street":"S Coast Hwy",
    "iso:country":"US",
    "sg:address":"1504 S Coast Hwy",
    "sg:city":"Laguna Beach",
    "sg:classifiers":[
        {
            "category":"Building & Trades",
            "subcategory":"Landscaping Services",
            "type":"Services"
        }
    ],
    "sg:phone":"+1 949 497 8298",
    "sg:postcode":"92651",
    "sg:province":"CA",
    "sg:tags":[
        "designer",
        "landscape"
    ],
    "sg:website":"www.stamperwhitinworks.com",
    "wof:name":"Stamper Whithin Works",
    "wof:placetype":"venue"
},
  "geometry": {"coordinates":[-117.772666,33.530048],"type":"Point"}
}