{
  "type": "Feature",
  "properties": {
    "iso:country":"US",
    "sg:address":"2804 Taft Hwy",
    "sg:city":"Bakersfield",
    "sg:classifiers":[
        {
            "category":"Restaurant",
            "type":"Food & Drink"
        }
    ],
    "sg:phone":"+1 661 836 1778",
    "sg:postcode":"93313",
    "sg:province":"CA",
    "wof:name":"Nuevo Loasis Restaurant",
    "wof:placetype":"venue"
},
  "geometry": {"coordinates":[-119.032367,35.266951],"type":"Point"}
}