{
  "type": "Feature",
  "properties": {
    "addr:full":"2804 Taft Hwy Bakersfield CA 93313",
    "addr:housenumber":"2804",
    "addr:postcode":"93313",
    "addr:street":"Taft Hwy",
    "iso:country":"US",
    "sg:address":"2804 Taft Hwy",
    "sg:city":"Bakersfield",
    "sg:classifiers":[
        {
            "category":"Restaurant",
            "type":"Food & Drink"
        }
    ],
    "sg:phone":"+1 661 836 1778",
    "sg:postcode":"93313",
    "sg:province":"CA",
    "wof:name":"Nuevo Loasis Restaurant",
    "wof:placetype":"venue"
},
  "geometry": {"coordinates":[-119.03236699999999,35.266951],"type":"Point"}
}