{
  "type": "Feature",
  "properties": {
    "iso:country":"US",
    "sg:address":"11285 Commercial Pkwy",
    "sg:city":"Castroville",
    "sg:classifiers":[
        {
            "category":"Freight",
            "type":"Transportation"
        }
    ],
    "sg:phone":"+1 800 349 4539",
    "sg:postcode":"95012",
    "sg:province":"CA",
    "sg:tags":[
        "mover"
    ],
    "wof:name":"Wiley Transfer",
    "wof:placetype":"venue"
},
  "geometry": {"coordinates":[-121.73855500000001,36.754398],"type":"Point"}
}