{
  "type": "Feature",
  "properties": {
    "addr:full":"26302 La Paz Rd Ste 106 Mission Viejo CA 92691",
    "addr:housenumber":"26302",
    "addr:postcode":"92691",
    "addr:street":"La Paz Rd Ste 106",
    "iso:country":"US",
    "sg:address":"26302 La Paz Rd Ste 106",
    "sg:city":"Mission Viejo",
    "sg:classifiers":[
        {
            "category":"Health Services",
            "subcategory":"Doctor",
            "type":"Services"
        }
    ],
    "sg:phone":"+1 949 770 3138",
    "sg:postcode":"92691",
    "sg:province":"CA",
    "wof:name":"Alan B ROSS MD",
    "wof:placetype":"venue"
},
  "geometry": {"coordinates":[-117.670069,33.600203],"type":"Point"}
}