{
  "type": "Feature",
  "properties": {
    "addr:full":"1601 Auto Mall Dr Turlock CA 95380",
    "addr:housenumber":"1601",
    "addr:postcode":"95380",
    "addr:street":"Auto Mall Dr",
    "iso:country":"US",
    "sg:address":"1601 Auto Mall Dr",
    "sg:city":"Turlock",
    "sg:classifiers":[
        {
            "category":"Autos & Motor Vehicles",
            "subcategory":"Automobile Sales",
            "type":"Retail Goods"
        }
    ],
    "sg:phone":"+1 209 632 3946",
    "sg:postcode":"95380",
    "sg:province":"CA",
    "sg:tags":[
        "dealership"
    ],
    "wof:name":"Smith Chevrolet Co Inc",
    "wof:placetype":"venue"
},
  "geometry": {"coordinates":[-120.881383,37.509734],"type":"Point"}
}