{
  "type": "Feature",
  "properties": {
    "addr:full":"1111 Flora Rd Arroyo Grande CA 93420",
    "addr:housenumber":"1111",
    "addr:postcode":"93420",
    "addr:street":"Flora Rd",
    "iso:country":"US",
    "sg:address":"1111 Flora Rd",
    "sg:city":"Arroyo Grande",
    "sg:classifiers":[
        {
            "category":"Building & Trades",
            "subcategory":"Construction",
            "type":"Services"
        }
    ],
    "sg:phone":"+1 805 481 5127",
    "sg:postcode":"93420",
    "sg:province":"CA",
    "sg:tags":[
        "painter"
    ],
    "wof:name":"Douglas Ingham Painting",
    "wof:placetype":"venue"
},
  "geometry": {"coordinates":[-120.55640699999999,35.125167],"type":"Point"}
}