{
  "type": "Feature",
  "properties": {
    "addr:full":"2911 Taft Hwy Bakersfield CA 93313",
    "addr:housenumber":"2911",
    "addr:postcode":"93313",
    "addr:street":"Taft Hwy",
    "iso:country":"US",
    "sg:address":"2911 Taft Hwy",
    "sg:city":"Bakersfield",
    "sg:classifiers":[
        {
            "category":"Restaurant",
            "type":"Food & Drink"
        }
    ],
    "sg:phone":"+1 661 831 9540",
    "sg:postcode":"93313",
    "sg:province":"CA",
    "wof:name":"Los Arcos Restaurant",
    "wof:placetype":"venue"
},
  "geometry": {"coordinates":[-119.033731,35.266806],"type":"Point"}
}