{
  "type": "Feature",
  "properties": {
    "addr:full":"3951 Beatty Dr Riverside CA 92506",
    "addr:housenumber":"3951",
    "addr:postcode":"92506",
    "addr:street":"Beatty Dr",
    "iso:country":"US",
    "sg:address":"3951 Beatty Dr",
    "sg:city":"Riverside",
    "sg:classifiers":[
        {
            "category":"Retail",
            "subcategory":"Laundry & Dry Cleaning",
            "type":"Services"
        }
    ],
    "sg:phone":"+1 951 781 7765",
    "sg:postcode":"92506",
    "sg:province":"CA",
    "sg:tags":[
        "cleaners"
    ],
    "wof:name":"Ideal Cleaners",
    "wof:placetype":"venue"
},
  "geometry": {"coordinates":[-117.396035,33.955647],"type":"Point"}
}