{
  "type": "Feature",
  "properties": {
    "addr:full":"4213 North Ave Modesto CA 95358",
    "addr:housenumber":"4213",
    "addr:postcode":"ca 95358",
    "addr:street":"North Ave",
    "iso:country":"US",
    "sg:address":"4213 North Ave",
    "sg:city":"Modesto",
    "sg:classifiers":[
        {
            "category":"Wholesale",
            "subcategory":"Machinery & Supplies",
            "type":"Manufacturing & Wholesale Goods"
        }
    ],
    "sg:phone":"+1 209 526 9836",
    "sg:postcode":"95358",
    "sg:province":"CA",
    "sg:tags":[
        "industrial"
    ],
    "wof:name":"AG & Industrial Supplies",
    "wof:placetype":"venue"
},
  "geometry": {"coordinates":[-121.074496,37.674547],"type":"Point"}
}