{
  "type": "Feature",
  "properties": {
    "iso:country":"US",
    "sg:address":"8000 Wheatland Ave Ste B",
    "sg:city":"Sun Valley",
    "sg:classifiers":[
        {
            "category":"Cinema",
            "subcategory":"Movie Rental",
            "type":"Entertainment"
        }
    ],
    "sg:phone":"+1 818 841 0900",
    "sg:postcode":"91352",
    "sg:province":"CA",
    "sg:tags":[
        "game",
        "video"
    ],
    "wof:name":"Game DOC",
    "wof:placetype":"venue"
},
  "geometry": {"coordinates":[-118.36199999999999,34.216499],"type":"Point"}
}