{
  "type": "Feature",
  "properties": {
    "addr:full":"2637 Manhattan Beach Blvd Redondo Beach CA 90278",
    "addr:housenumber":"2637",
    "addr:postcode":"90278",
    "addr:street":"Manhattan Beach Blvd",
    "iso:country":"US",
    "sg:address":"2637 Manhattan Beach Blvd",
    "sg:city":"Redondo Beach",
    "sg:classifiers":[
        {
            "category":"Freight",
            "type":"Transportation"
        }
    ],
    "sg:phone":"+1 310 727 1940",
    "sg:postcode":"90278",
    "sg:province":"CA",
    "sg:tags":[
        "arrangement"
    ],
    "wof:name":"Minatoya Corporation",
    "wof:placetype":"venue"
},
  "geometry": {"coordinates":[-118.36366200000001,33.887445],"type":"Point"}
}