{
  "type": "Feature",
  "properties": {
    "addr:full":"6245 Bristol Parkway Culver City CA 90230",
    "addr:housenumber":"6245",
    "addr:postcode":"90230",
    "addr:street":"Bristol Parkway",
    "iso:country":"US",
    "sg:address":"6245 Bristol Parkway",
    "sg:city":"Culver City",
    "sg:classifiers":[
        {
            "category":"Professional",
            "subcategory":"Lawyer & Legal Services",
            "type":"Services"
        }
    ],
    "sg:phone":"+1 310 417 3084",
    "sg:postcode":"90230",
    "sg:province":"CA",
    "sg:tags":[
        "notary"
    ],
    "wof:name":"Mail Plus",
    "wof:placetype":"venue"
},
  "geometry": {"coordinates":[-118.39103799999999,33.983073],"type":"Point"}
}