{
  "type": "Feature",
  "properties": {
    "iso:country":"US",
    "sg:address":"3710 Stevens Creek Boulevard",
    "sg:city":"San Jose",
    "sg:classifiers":[
        {
            "category":"Autos & Motor Vehicles",
            "subcategory":"Automobile Sales",
            "type":"Retail Goods"
        }
    ],
    "sg:phone":"+1 408 241 9500",
    "sg:postcode":"95117",
    "sg:province":"CA",
    "sg:tags":[
        "car"
    ],
    "wof:name":"House of Imports",
    "wof:placetype":"venue"
},
  "geometry": {"coordinates":[-121.967488,37.32325],"type":"Point"}
}