{
  "type": "Feature",
  "properties": {
    "addr:full":"3943 Arizona St San Diego CA 92104",
    "addr:housenumber":"3943",
    "addr:postcode":"92104",
    "addr:street":"Arizona St",
    "iso:country":"US",
    "sg:address":"3943 Arizona St",
    "sg:city":"San Diego",
    "sg:classifiers":[
        {
            "category":"Real Estate",
            "subcategory":"Real Estate Operator",
            "type":"Services"
        }
    ],
    "sg:phone":"+1 619 291 9247",
    "sg:postcode":"92104",
    "sg:province":"CA",
    "sg:tags":[
        "apartment"
    ],
    "wof:name":"Arizona Street Apartments",
    "wof:placetype":"venue"
},
  "geometry": {"coordinates":[-117.137495,32.749516],"type":"Point"}
}