{
  "type": "Feature",
  "properties": {
    "addr:full":"301 Pine Ave Long Beach CA 90802",
    "addr:housenumber":"301",
    "addr:postcode":"90802",
    "addr:street":"Pine Ave",
    "iso:country":"US",
    "sg:address":"301 Pine Ave",
    "sg:city":"Long Beach",
    "sg:classifiers":[
        {
            "category":"Shopping",
            "subcategory":"Shoes",
            "type":"Retail Goods"
        }
    ],
    "sg:phone":"+1 562 983 1222",
    "sg:postcode":"90802",
    "sg:province":"CA",
    "wof:name":"9.99 Shoe Outlet Long Beach",
    "wof:placetype":"venue"
},
  "geometry": {"coordinates":[-118.19237699999999,33.771044],"type":"Point"}
}