{
  "type": "Feature",
  "properties": {
    "iso:country":"US",
    "sg:address":"1414 S Robertson Blvd",
    "sg:city":"Los Angeles",
    "sg:classifiers":[
        {
            "category":"Communications",
            "subcategory":"Newspaper",
            "type":"Services"
        }
    ],
    "sg:phone":"+1 310 858 1804",
    "sg:postcode":"90035",
    "sg:province":"CA",
    "sg:tags":[
        "magazine"
    ],
    "wof:name":"Robertson Newsstand",
    "wof:placetype":"venue"
},
  "geometry": {"coordinates":[-118.383819,34.054031],"type":"Point"}
}