{
  "type": "Feature",
  "properties": {
    "iso:country":"US",
    "sg:address":"3550 Mowry Ave Ste 101",
    "sg:city":"Fremont",
    "sg:classifiers":[
        {
            "category":"Health Services",
            "subcategory":"Doctor",
            "type":"Services"
        }
    ],
    "sg:phone":"+1 510 797 5502",
    "sg:postcode":"94538",
    "sg:province":"CA",
    "sg:tags":[
        "physician",
        "surgeons",
        "medicine",
        "surgeon",
        "rehabilitation",
        "physical"
    ],
    "wof:name":"Mahawar Suresh Md",
    "wof:placetype":"venue"
},
  "geometry": {"coordinates":[-121.986214,37.551214],"type":"Point"}
}