{
  "type": "Feature",
  "properties": {
    "addr:full":"83 Fortune Dr Irvine CA 92618",
    "addr:housenumber":"83",
    "addr:postcode":"92618",
    "addr:street":"Fortune Dr",
    "iso:country":"US",
    "sg:address":"83 Fortune Dr",
    "sg:city":"Irvine",
    "sg:classifiers":[
        {
            "category":"Shopping",
            "subcategory":"Hobbies, Toys, & Games",
            "type":"Retail Goods"
        }
    ],
    "sg:phone":"+1 949 453 1321",
    "sg:postcode":"92618",
    "sg:province":"CA",
    "sg:tags":[
        "toy",
        "store"
    ],
    "wof:name":"Child's Play Toys Inc",
    "wof:placetype":"venue"
},
  "geometry": {"coordinates":[-117.746002,33.650299],"type":"Point"}
}