{
  "type": "Feature",
  "properties": {
    "addr:full":"400 Seaport Ct Redwood City CA 94063",
    "addr:housenumber":"400",
    "addr:postcode":"94063",
    "addr:street":"Seaport Ct",
    "iso:country":"US",
    "sg:address":"400 Seaport Ct",
    "sg:city":"Redwood City",
    "sg:classifiers":[
        {
            "category":"Insurance",
            "subcategory":"Insurance Agent",
            "type":"Services"
        }
    ],
    "sg:phone":"+1 650 367 8700",
    "sg:postcode":"94063",
    "sg:province":"CA",
    "sg:website":"www.techins.com",
    "wof:name":"Technology Insurance Svc",
    "wof:placetype":"venue"
},
  "geometry": {"coordinates":[-122.210701,37.502834],"type":"Point"}
}