{
  "type": "Feature",
  "properties": {
    "addr:full":"6704 Milton Ave Whittier CA 90601",
    "addr:housenumber":"6704",
    "addr:postcode":"90601",
    "addr:street":"Milton Ave",
    "iso:country":"US",
    "sg:address":"6704 Milton Ave",
    "sg:city":"Whittier",
    "sg:classifiers":[
        {
            "category":"Education",
            "subcategory":"Special Training",
            "type":"Public Place"
        }
    ],
    "sg:phone":"+1 562 789 0239",
    "sg:postcode":"90601",
    "sg:province":"CA",
    "sg:tags":[
        "center"
    ],
    "wof:name":"Gorman Learning Ctr",
    "wof:placetype":"venue"
},
  "geometry": {"coordinates":[-118.039627,33.979127],"type":"Point"}
}