{
  "type": "Feature",
  "properties": {
    "addr:full":"319 Festival Dr Oceanside CA 92057",
    "addr:housenumber":"319",
    "addr:postcode":"92057",
    "addr:street":"Festival Dr",
    "iso:country":"US",
    "sg:address":"319 Festival Dr",
    "sg:city":"Oceanside",
    "sg:classifiers":[
        {
            "category":"Building & Trades",
            "subcategory":"Plumbing",
            "type":"Services"
        }
    ],
    "sg:phone":"+1 760 754 1194",
    "sg:postcode":"92057",
    "sg:province":"CA",
    "sg:tags":[
        "conditioning",
        "air",
        "system",
        "contractor"
    ],
    "wof:name":"American Eagle Electric",
    "wof:placetype":"venue"
},
  "geometry": {"coordinates":[-117.318179,33.25099],"type":"Point"}
}