{
  "type": "Feature",
  "properties": {
    "addr:full":"2221 S Main St Los Angeles CA 90007",
    "addr:housenumber":"2221",
    "addr:postcode":"90007",
    "addr:street":"S Main St",
    "iso:country":"US",
    "sg:address":"2221 S Main St",
    "sg:city":"Los Angeles",
    "sg:classifiers":[
        {
            "category":"Manufacturing",
            "subcategory":"Apparel",
            "type":"Manufacturing & Wholesale Goods"
        }
    ],
    "sg:phone":"+1 213 747 3330",
    "sg:postcode":"90007",
    "sg:province":"CA",
    "sg:tags":[
        "sportswear"
    ],
    "wof:name":"Hope Sportswear",
    "wof:placetype":"venue"
},
  "geometry": {"coordinates":[-118.26692300000001,34.027751],"type":"Point"}
}