{
  "type": "Feature",
  "properties": {
    "iso:country":"US",
    "sg:address":"19264 Easton St",
    "sg:city":"Rialto",
    "sg:classifiers":[
        {
            "category":"Retail",
            "subcategory":"Repair Shop",
            "type":"Services"
        }
    ],
    "sg:phone":"+1 909 875 7565",
    "sg:postcode":"92376",
    "sg:province":"CA",
    "sg:tags":[
        "plumbing",
        "drain",
        "cleaning",
        "sewer"
    ],
    "wof:name":"Rialto Rooter",
    "wof:placetype":"venue"
},
  "geometry": {"coordinates":[-117.38476,34.134277],"type":"Point"}
}