{
  "type": "Feature",
  "properties": {
    "addr:full":"5038 E Washington St Stockton CA 95215",
    "addr:housenumber":"5038",
    "addr:postcode":"95215",
    "addr:street":"E Washington St",
    "iso:country":"US",
    "sg:address":"5038 E Washington St",
    "sg:city":"Stockton",
    "sg:classifiers":[
        {
            "category":"Place Of Worship",
            "subcategory":"Church",
            "type":"Public Place"
        },
        {
            "category":"Place Of Worship",
            "type":"Public Place"
        }
    ],
    "sg:phone":"+1 209 462 5196",
    "sg:postcode":"95215",
    "sg:province":"CA",
    "sg:tags":[
        "churches-pentecostal-independent",
        "churches-pentecostal"
    ],
    "wof:name":"Word Of Life Ministries",
    "wof:placetype":"venue"
},
  "geometry": {"coordinates":[-121.228458,37.964933],"type":"Point"}
}