{
  "type": "Feature",
  "properties": {
    "iso:country":"US",
    "sg:address":"3931 Rohnerville Rd",
    "sg:city":"Fortuna",
    "sg:classifiers":[
        {
            "category":"Manufacturing",
            "subcategory":"Lumber",
            "type":"Manufacturing & Wholesale Goods"
        }
    ],
    "sg:phone":"+1 707 768 3743",
    "sg:postcode":"95540",
    "sg:province":"CA",
    "sg:tags":[
        "forester"
    ],
    "wof:name":"Hohman & Assoc Forestry Cnslnt",
    "wof:placetype":"venue"
},
  "geometry": {"coordinates":[-124.12697799999999,40.571591],"type":"Point"}
}