{
  "type": "Feature",
  "properties": {
    "addr:full":"3709 Utah St San Diego CA 92104",
    "addr:housenumber":"3709",
    "addr:postcode":"92104",
    "addr:street":"Utah St",
    "iso:country":"US",
    "sg:address":"3709 Utah St",
    "sg:city":"San Diego",
    "sg:classifiers":[
        {
            "category":"Food & Beverages",
            "subcategory":"Specialty",
            "type":"Retail Goods"
        }
    ],
    "sg:phone":"+1 619 293 7888",
    "sg:postcode":"92104",
    "sg:province":"CA",
    "sg:tags":[
        "tea",
        "coffee"
    ],
    "wof:name":"R C Distr",
    "wof:placetype":"venue"
},
  "geometry": {"coordinates":[-117.13272499999999,32.746148],"type":"Point"}
}