{
  "type": "Feature",
  "properties": {
    "addr:full":"105 Broadway St King City CA 93930",
    "addr:housenumber":"105",
    "addr:postcode":"93930",
    "addr:street":"Broadway St",
    "iso:country":"US",
    "sg:address":"105 Broadway St",
    "sg:city":"King City",
    "sg:classifiers":[
        {
            "category":"Shopping",
            "subcategory":"Clothing, Apparel, & Fashions",
            "type":"Retail Goods"
        }
    ],
    "sg:phone":"+1 831 386 9020",
    "sg:postcode":"93930",
    "sg:province":"CA",
    "sg:tags":[
        "infant",
        "wear"
    ],
    "wof:name":"Carrousel",
    "wof:placetype":"venue"
},
  "geometry": {"coordinates":[-121.123627,36.214254],"type":"Point"}
}