{
  "type": "Feature",
  "properties": {
    "iso:country":"US",
    "sg:address":"906 W Henderson Ave",
    "sg:city":"Porterville",
    "sg:classifiers":[
        {
            "category":"Government",
            "subcategory":"Office",
            "type":"Public Place"
        }
    ],
    "sg:phone":"+1 559 784 6824",
    "sg:postcode":"93257",
    "sg:province":"CA",
    "sg:tags":[
        "national",
        "security"
    ],
    "wof:name":"US Recruiting Army Dept",
    "wof:placetype":"venue"
},
  "geometry": {"coordinates":[-119.03867,36.080586],"type":"Point"}
}