{
  "type": "Feature",
  "properties": {
    "addr:full":"20 California Street San Francisco CA 94111",
    "addr:housenumber":"20",
    "addr:postcode":"94111",
    "addr:street":"California Street",
    "iso:country":"US",
    "sg:address":"20 California Street",
    "sg:city":"San Francisco",
    "sg:classifiers":[
        {
            "category":"Professional",
            "subcategory":"Lawyer & Legal Services",
            "type":"Services"
        }
    ],
    "sg:phone":"+1 415 362 2375",
    "sg:postcode":"94111",
    "sg:province":"CA",
    "wof:name":"Manwell & Schwartz Attorneys At Law",
    "wof:placetype":"venue"
},
  "geometry": {"coordinates":[-122.39666200000001,37.793657],"type":"Point"}
}