{
  "type": "Feature",
  "properties": {
    "iso:country":"US",
    "sg:address":"5660 Mother Lode Dr",
    "sg:city":"Placerville",
    "sg:classifiers":[
        {
            "category":"Government",
            "subcategory":"Fire Station",
            "type":"Public Place"
        }
    ],
    "sg:phone":"+1 530 622 3858",
    "sg:postcode":"95667",
    "sg:province":"CA",
    "sg:tags":[
        "protection"
    ],
    "wof:name":"California Dept Forstry & Fire",
    "wof:placetype":"venue"
},
  "geometry": {"coordinates":[-120.86998199999999,38.680039],"type":"Point"}
}