{
  "type": "Feature",
  "properties": {
    "iso:country":"US",
    "sg:address":"7440 Laguna Blvd",
    "sg:city":"Elk Grove",
    "sg:classifiers":[
        {
            "category":"Professional",
            "subcategory":"Employment Agencies",
            "type":"Services"
        }
    ],
    "sg:phone":"+1 916 683 3836",
    "sg:postcode":"95758",
    "sg:province":"CA",
    "sg:tags":[
        "opportunity"
    ],
    "wof:name":"Apple One Employment Svc",
    "wof:placetype":"venue"
},
  "geometry": {"coordinates":[-121.40912899999999,38.421958],"type":"Point"}
}