{
  "type": "Feature",
  "properties": {
    "addr:full":"10801 Downey Ave Downey CA 90241",
    "addr:housenumber":"10801",
    "addr:postcode":"90241",
    "addr:street":"Downey Ave",
    "iso:country":"US",
    "sg:address":"10801 Downey Ave",
    "sg:city":"Downey",
    "sg:classifiers":[
        {
            "category":"Education",
            "subcategory":"Preschool",
            "type":"Public Place"
        },
        {
            "category":"Education",
            "subcategory":"School",
            "type":"Public Place"
        }
    ],
    "sg:phone":"+1 562 923 8719",
    "sg:postcode":"90241",
    "sg:province":"CA",
    "sg:tags":[
        "elementary"
    ],
    "sg:website":"www.umc.org",
    "wof:name":"Downey United Methodist Pre-School",
    "wof:placetype":"venue"
},
  "geometry": {"coordinates":[-118.129997,33.943699],"type":"Point"}
}