{
  "type": "Feature",
  "properties": {
    "addr:full":"2245 W Washington Blvd Los Angeles CA 90018",
    "addr:housenumber":"2245",
    "addr:postcode":"90018",
    "addr:street":"W Washington Blvd",
    "iso:country":"US",
    "sg:address":"2245 W Washington Blvd",
    "sg:city":"Los Angeles",
    "sg:classifiers":[
        {
            "category":"Retail",
            "subcategory":"Repair Shop",
            "type":"Services"
        }
    ],
    "sg:phone":"+1 323 572 4820",
    "sg:postcode":"90018",
    "sg:province":"CA",
    "sg:tags":[
        "reupholstery",
        "furniture"
    ],
    "wof:name":"RAMON'S CUSTOM DRAPERIES & UPHOLSTERY",
    "wof:placetype":"venue"
},
  "geometry": {"coordinates":[-118.31044,34.006713],"type":"Point"}
}