{
  "type": "Feature",
  "properties": {
    "iso:country":"US",
    "sg:address":"550 Orange Ave",
    "sg:city":"Long Beach",
    "sg:classifiers":[
        {
            "category":"Wholesale",
            "subcategory":"Vending Machines",
            "type":"Manufacturing & Wholesale Goods"
        }
    ],
    "sg:phone":"+1 562 437 0292",
    "sg:postcode":"90802",
    "sg:province":"CA",
    "sg:tags":[
        "operator"
    ],
    "wof:name":"Parkers Vending",
    "wof:placetype":"venue"
},
  "geometry": {"coordinates":[-118.176253,33.773545],"type":"Point"}
}