{
  "type": "Feature",
  "properties": {
    "iso:country":"US",
    "sg:address":"3701 Sacramento St",
    "sg:city":"San Francisco",
    "sg:classifiers":[
        {
            "category":"Shopping",
            "type":"Retail Goods"
        }
    ],
    "sg:phone":"+1 415 346 0466",
    "sg:postcode":"94118",
    "sg:province":"CA",
    "sg:tags":[
        "merchandise"
    ],
    "wof:name":"Bitapi Photocards",
    "wof:placetype":"venue"
},
  "geometry": {"coordinates":[-122.455236,37.787137],"type":"Point"}
}