{
  "type": "Feature",
  "properties": {
    "addr:full":"229 Newbury Way Martinez CA 94503",
    "addr:housenumber":"229",
    "addr:postcode":"94503",
    "addr:street":"Newbury Way",
    "iso:country":"US",
    "sg:address":"229 Newbury Way",
    "sg:city":"Martinez",
    "sg:classifiers":[
        {
            "category":"Professional",
            "type":"Services"
        }
    ],
    "sg:phone":"+1 707 648 3804",
    "sg:postcode":"94503",
    "sg:province":"CA",
    "sg:tags":[
        "establishment"
    ],
    "wof:name":"Matthew House",
    "wof:placetype":"venue"
},
  "geometry": {"coordinates":[-122.262715,38.167328],"type":"Point"}
}