{
  "type": "Feature",
  "properties": {
    "iso:country":"US",
    "sg:address":"3450 el Camino Real",
    "sg:city":"Santa Clara",
    "sg:classifiers":[
        {
            "category":"Shopping",
            "subcategory":"Gifts & Souvenirs",
            "type":"Retail Goods"
        }
    ],
    "sg:phone":"+1 408 247 1642",
    "sg:postcode":"95051",
    "sg:province":"CA",
    "sg:tags":[
        "shop",
        "home",
        "furnishing"
    ],
    "wof:name":"Royal Houseware & Gifts",
    "wof:placetype":"venue"
},
  "geometry": {"coordinates":[-121.992296,37.352123],"type":"Point"}
}