{
  "type": "Feature",
  "properties": {
    "addr:full":"1151 Dove Street Newport Beach CA 92660",
    "addr:housenumber":"1151",
    "addr:postcode":"92660",
    "addr:street":"Dove Street",
    "iso:country":"US",
    "sg:address":"1151 Dove Street",
    "sg:city":"Newport Beach",
    "sg:classifiers":[
        {
            "category":"Banks & Credit Unions",
            "subcategory":"Financial Services",
            "type":"Services"
        }
    ],
    "sg:phone":"+1 949 567 1980",
    "sg:postcode":"92660",
    "sg:province":"CA",
    "sg:tags":[
        "broker",
        "mortgage"
    ],
    "wof:name":"D & J Funding.",
    "wof:placetype":"venue"
},
  "geometry": {"coordinates":[-117.86468000000001,33.660341],"type":"Point"}
}