{
  "type": "Feature",
  "properties": {
    "addr:full":"25619 Rancho Adobe Rd Valencia CA 91355",
    "addr:housenumber":"25619",
    "addr:postcode":"91355",
    "addr:street":"Rancho Adobe Rd",
    "iso:country":"US",
    "sg:address":"25619 Rancho Adobe Rd",
    "sg:city":"Valencia",
    "sg:classifiers":[
        {
            "category":"Professional",
            "type":"Services"
        }
    ],
    "sg:phone":"+1 661 287 3471",
    "sg:postcode":"91355",
    "sg:province":"CA",
    "wof:name":"Cornerstone Chrstn Hm Edcators",
    "wof:placetype":"venue"
},
  "geometry": {"coordinates":[-118.547461,34.400011],"type":"Point"}
}