{
  "type": "Feature",
  "properties": {
    "addr:full":"4624 E Blue Bird Ave Orange CA 92869",
    "addr:housenumber":"4624",
    "addr:postcode":"92869",
    "addr:street":"E Blue Bird Ave",
    "iso:country":"US",
    "sg:address":"4624 E Blue Bird Ave",
    "sg:city":"Orange",
    "sg:classifiers":[
        {
            "category":"Retail",
            "subcategory":"Auto Repair",
            "type":"Services"
        }
    ],
    "sg:phone":"+1 714 516 1806",
    "sg:postcode":"92869",
    "sg:province":"CA",
    "sg:tags":[
        "body",
        "repairing",
        "painting",
        "automobile"
    ],
    "wof:name":"Chips Away",
    "wof:placetype":"venue"
},
  "geometry": {"coordinates":[-117.804648,33.801064],"type":"Point"}
}