{
  "type": "Feature",
  "properties": {
    "iso:country":"US",
    "sg:address":"1025 S San Fernando Blvd",
    "sg:city":"Burbank",
    "sg:classifiers":[
        {
            "category":"Autos & Motor Vehicles",
            "subcategory":"Automobile Sales",
            "type":"Retail Goods"
        },
        {
            "category":"Retail",
            "subcategory":"Auto Rental",
            "type":"Services"
        }
    ],
    "sg:phone":"+1 818 841 1000",
    "sg:postcode":"91502",
    "sg:province":"CA",
    "sg:tags":[
        "car"
    ],
    "wof:name":"Bestway Rent a Car",
    "wof:placetype":"venue"
},
  "geometry": {"coordinates":[-118.299255,34.173973],"type":"Point"}
}