{
  "type": "Feature",
  "properties": {
    "addr:full":"811 S B St San Mateo CA 94401",
    "addr:housenumber":"811",
    "addr:postcode":"94401",
    "addr:street":"S B St",
    "iso:country":"US",
    "sg:address":"811 S B St",
    "sg:city":"San Mateo",
    "sg:classifiers":[
        {
            "category":"Building & Trades",
            "subcategory":"Plumbing",
            "type":"Services"
        }
    ],
    "sg:phone":"+1 650 574 5740",
    "sg:postcode":"94401",
    "sg:province":"CA",
    "sg:tags":[
        "conditioning",
        "air",
        "system",
        "contractor"
    ],
    "wof:name":"Gaffigan Co",
    "wof:placetype":"venue"
},
  "geometry": {"coordinates":[-122.318175,37.561746],"type":"Point"}
}