{
  "type": "Feature",
  "properties": {
    "addr:full":"1119 E Stanley Blvd Livermore CA 94550",
    "addr:housenumber":"1119",
    "addr:postcode":"94550",
    "addr:street":"E Stanley Blvd",
    "iso:country":"US",
    "sg:address":"1119 E Stanley Blvd",
    "sg:city":"Livermore",
    "sg:classifiers":[
        {
            "category":"Health Services",
            "subcategory":"Health Practitioner",
            "type":"Services"
        }
    ],
    "sg:phone":"+1 925 373 4019",
    "sg:postcode":"94550",
    "sg:province":"CA",
    "sg:tags":[
        "pathologist",
        "speech"
    ],
    "wof:name":"Valleycare Health System Sport",
    "wof:placetype":"venue"
},
  "geometry": {"coordinates":[-121.781246,37.679145],"type":"Point"}
}