{
  "type": "Feature",
  "properties": {
    "iso:country":"US",
    "sg:address":"5750 W Olympic Blvd",
    "sg:city":"Los Angeles",
    "sg:classifiers":[
        {
            "category":"Organizations",
            "subcategory":"Religious Organization",
            "type":"Services"
        }
    ],
    "sg:phone":"+1 323 954 8845",
    "sg:postcode":"90036",
    "sg:province":"CA",
    "sg:tags":[
        "church"
    ],
    "wof:name":"Los Angeles Presbyterian",
    "wof:placetype":"venue"
},
  "geometry": {"coordinates":[-118.355939,34.057435],"type":"Point"}
}