{
  "type": "Feature",
  "properties": {
    "addr:full":"32905 Cll San Marcos San Juan Capistrano CA 92675",
    "addr:postcode":"32905;92675",
    "addr:street":"Cll San Marcos",
    "iso:country":"US",
    "sg:address":"32905 Cll San Marcos",
    "sg:city":"San Juan Capistrano",
    "sg:classifiers":[
        {
            "category":"Farming",
            "subcategory":"Livestock Farm",
            "type":"Manufacturing & Wholesale Goods"
        }
    ],
    "sg:phone":"+1 949 218 2760",
    "sg:postcode":"92675",
    "sg:province":"CA",
    "sg:tags":[
        "animal",
        "general"
    ],
    "wof:name":"Kane Ranch LLC",
    "wof:placetype":"venue"
},
  "geometry": {"coordinates":[-117.678259,33.48507],"type":"Point"}
}