{
  "type": "Feature",
  "properties": {
    "addr:full":"411 W Lambert Rd Brea CA 92821",
    "addr:housenumber":"411",
    "addr:postcode":"92821",
    "addr:street":"W Lambert Rd",
    "iso:country":"US",
    "sg:address":"411 W Lambert Rd",
    "sg:city":"Brea",
    "sg:classifiers":[
        {
            "category":"Professional",
            "subcategory":"Business Services",
            "type":"Services"
        }
    ],
    "sg:phone":"+1 714 990 6639",
    "sg:postcode":"92821",
    "sg:province":"CA",
    "sg:tags":[
        "drafting"
    ],
    "wof:name":"Continuum",
    "wof:placetype":"venue"
},
  "geometry": {"coordinates":[-117.900891,33.924917],"type":"Point"}
}