{
  "type": "Feature",
  "properties": {
    "iso:country":"US",
    "sg:address":"10661 Business Dr",
    "sg:city":"Fontana",
    "sg:classifiers":[
        {
            "category":"Wholesale",
            "subcategory":"Books, Periodicals, & Newspapers",
            "type":"Manufacturing & Wholesale Goods"
        }
    ],
    "sg:phone":"+1 562 331 6237",
    "sg:postcode":"92337",
    "sg:province":"CA",
    "sg:tags":[
        "magazine"
    ],
    "sg:website":"http://www.metrodotpop.com",
    "wof:name":"Metro-Pop Magazine",
    "wof:placetype":"venue"
},
  "geometry": {"coordinates":[-117.50933999999999,34.059873],"type":"Point"}
}