{
  "type": "Feature",
  "properties": {
    "iso:country":"US",
    "sg:address":"13716 Quinton Rd",
    "sg:city":"San Diego",
    "sg:classifiers":[
        {
            "category":"Insurance",
            "subcategory":"Insurance Agent",
            "type":"Services"
        }
    ],
    "sg:phone":"+1 858 537 9093",
    "sg:postcode":"92129",
    "sg:province":"CA",
    "wof:name":"Randy Fenster Insurance Svcs",
    "wof:placetype":"venue"
},
  "geometry": {"coordinates":[-117.111586,32.967339],"type":"Point"}
}