{
  "type": "Feature",
  "properties": {
    "iso:country":"US",
    "sg:address":"5758 Las Virgenes Rd # 287",
    "sg:city":"Calabasas",
    "sg:classifiers":[
        {
            "category":"Manufacturing",
            "subcategory":"Chemicals & Compounds",
            "type":"Manufacturing & Wholesale Goods"
        }
    ],
    "sg:phone":"+1 818 880 5213",
    "sg:postcode":"91302",
    "sg:province":"CA",
    "sg:tags":[
        "chemicals-wholesale",
        "manufacturer"
    ],
    "wof:name":"Environment & Energy Inc",
    "wof:placetype":"venue"
},
  "geometry": {"coordinates":[-118.702698,34.162121],"type":"Point"}
}