{
  "type": "Feature",
  "properties": {
    "iso:country":"US",
    "sg:address":"4418 International Blvd",
    "sg:city":"Oakland",
    "sg:classifiers":[
        {
            "category":"Shopping",
            "subcategory":"Gifts & Souvenirs",
            "type":"Retail Goods"
        }
    ],
    "sg:phone":"+1 510 533 1079",
    "sg:postcode":"94601",
    "sg:province":"CA",
    "sg:tags":[
        "shop"
    ],
    "wof:name":"T & L Gift Shop",
    "wof:placetype":"venue"
},
  "geometry": {"coordinates":[-122.213016,37.771637],"type":"Point"}
}