{
  "type": "Feature",
  "properties": {
    "iso:country":"US",
    "sg:address":"1156 N Tustin St",
    "sg:city":"Orange",
    "sg:classifiers":[
        {
            "category":"Professional",
            "subcategory":"Lawyer & Legal Services",
            "type":"Services"
        }
    ],
    "sg:phone":"+1 714 288 7400",
    "sg:postcode":"92867",
    "sg:province":"CA",
    "sg:tags":[
        "attorney",
        "bureau"
    ],
    "sg:website":"www.microquick.com",
    "wof:name":"Micro Quick",
    "wof:placetype":"venue"
},
  "geometry": {"coordinates":[-117.83577699999999,33.807259],"type":"Point"}
}