{
  "type": "Feature",
  "properties": {
    "addr:full":"125 S Anderson Rd Exeter CA 93221",
    "addr:housenumber":"125",
    "addr:postcode":"93221",
    "addr:street":"S Anderson Rd",
    "iso:country":"US",
    "sg:address":"125 S Anderson Rd",
    "sg:city":"Exeter",
    "sg:classifiers":[
        {
            "category":"Professional",
            "subcategory":"Art Services",
            "type":"Services"
        }
    ],
    "sg:phone":"+1 559 592 6026",
    "sg:postcode":"93221",
    "sg:province":"CA",
    "sg:tags":[
        "graphic",
        "designer"
    ],
    "wof:name":"L W Concepts",
    "wof:placetype":"venue"
},
  "geometry": {"coordinates":[-119.1721,36.294714],"type":"Point"}
}