{
  "type": "Feature",
  "properties": {
    "iso:country":"US",
    "sg:address":"465 - 34TH STREET",
    "sg:city":"Oakland",
    "sg:classifiers":[
        {
            "category":"Health Services",
            "subcategory":"Health Practitioner",
            "type":"Services"
        }
    ],
    "sg:phone":"+1 510 287 9456",
    "sg:postcode":"94609",
    "sg:province":"CA",
    "sg:tags":[
        "psychotherapist"
    ],
    "sg:website":"http://www.johnnickensphd.com",
    "wof:name":"John Nickens, PhD",
    "wof:placetype":"venue"
},
  "geometry": {"coordinates":[-122.266582,37.828711],"type":"Point"}
}