{
  "type": "Feature",
  "properties": {
    "addr:full":"3108 5th Ave San Diego CA 92103",
    "addr:housenumber":"3108",
    "addr:postcode":"92103",
    "addr:street":"5Th Ave",
    "iso:country":"US",
    "sg:address":"3108 5th Ave",
    "sg:city":"San Diego",
    "sg:classifiers":[
        {
            "category":"Manufacturing",
            "subcategory":"Printing",
            "type":"Manufacturing & Wholesale Goods"
        }
    ],
    "sg:phone":"+1 619 295 3150",
    "sg:postcode":"92103",
    "sg:province":"CA",
    "sg:tags":[
        "printer"
    ],
    "wof:name":"D B Hess Co",
    "wof:placetype":"venue"
},
  "geometry": {"coordinates":[-117.160427,32.73863],"type":"Point"}
}