{
  "type": "Feature",
  "properties": {
    "addr:full":"5470 Jefferson Ave Chino CA 91710",
    "addr:housenumber":"5470",
    "addr:postcode":"91710",
    "addr:street":"Jefferson Ave",
    "iso:country":"US",
    "sg:address":"5470 Jefferson Ave",
    "sg:city":"Chino",
    "sg:classifiers":[
        {
            "category":"Health Services",
            "subcategory":"Doctor",
            "type":"Services"
        }
    ],
    "sg:phone":"+1 909 464 8955",
    "sg:postcode":"91710",
    "sg:province":"CA",
    "sg:tags":[
        "physician",
        "surgeon"
    ],
    "wof:name":"Chino Valley MRI Ctr",
    "wof:placetype":"venue"
},
  "geometry": {"coordinates":[-117.68306699999999,34.0248],"type":"Point"}
}