{
  "type": "Feature",
  "properties": {
    "addr:full":"521 Market Street San Diego CA 92101",
    "addr:housenumber":"521",
    "addr:postcode":"92101",
    "addr:street":"Market Street",
    "iso:country":"US",
    "sg:address":"521 Market Street",
    "sg:city":"San Diego",
    "sg:classifiers":[
        {
            "category":"Travel",
            "subcategory":"Hostel",
            "type":"Entertainment"
        }
    ],
    "sg:phone":"+1 619 525 1531",
    "sg:postcode":"92101",
    "sg:province":"CA",
    "sg:website":"www.sandiegohostels.org/",
    "wof:name":"Hostelling International - Downtown San Diego",
    "wof:placetype":"venue"
},
  "geometry": {"coordinates":[-117.159695,32.711382],"type":"Point"}
}