{
  "type": "Feature",
  "properties": {
    "addr:full":"1155 N 1st Street San Jose CA 95112",
    "addr:housenumber":"1155",
    "addr:postcode":"95112",
    "addr:street":"N 1St Street",
    "iso:country":"US",
    "sg:address":"1155 N 1st Street",
    "sg:city":"San Jose",
    "sg:classifiers":[
        {
            "category":"Professional",
            "type":"Services"
        }
    ],
    "sg:phone":"+1 408 293 9004",
    "sg:postcode":"95112",
    "sg:province":"CA",
    "sg:website":"www.knoxservices.com",
    "wof:name":"Knox Services",
    "wof:placetype":"venue"
},
  "geometry": {"coordinates":[-121.905812,37.356755],"type":"Point"}
}