{
  "type": "Feature",
  "properties": {
    "addr:full":"5103 Venice Blvd Los Angeles CA 90019",
    "addr:housenumber":"5103",
    "addr:postcode":"90019",
    "addr:street":"Venice Blvd",
    "iso:country":"US",
    "sg:address":"5103 Venice Blvd",
    "sg:city":"Los Angeles",
    "sg:classifiers":[
        {
            "category":"Personal",
            "subcategory":"Nail Salon",
            "type":"Services"
        }
    ],
    "sg:phone":"+1 323 936 5422",
    "sg:postcode":"90019",
    "sg:province":"CA",
    "wof:name":"Kim Ly Nails",
    "wof:placetype":"venue"
},
  "geometry": {"coordinates":[-118.350998,34.045101],"type":"Point"}
}