{
  "type": "Feature",
  "properties": {
    "addr:full":"2602 Transportation Ave National City CA 91950",
    "addr:housenumber":"2602",
    "addr:postcode":"91950",
    "addr:street":"Transportation Ave",
    "iso:country":"US",
    "sg:address":"2602 Transportation Ave",
    "sg:city":"National City",
    "sg:classifiers":[
        {
            "category":"Manufacturing",
            "subcategory":"Printing",
            "type":"Manufacturing & Wholesale Goods"
        }
    ],
    "sg:phone":"+1 619 477 5594",
    "sg:postcode":"91950",
    "sg:province":"CA",
    "sg:tags":[
        "printer",
        "commercial"
    ],
    "wof:name":"J B Litho",
    "wof:placetype":"venue"
},
  "geometry": {"coordinates":[-117.10203,32.659394],"type":"Point"}
}