{
  "type": "Feature",
  "properties": {
    "addr:full":"235 Broderick St San Francisco CA 94117",
    "addr:housenumber":"235",
    "addr:postcode":"94117",
    "addr:street":"Broderick St",
    "iso:country":"US",
    "sg:address":"235 Broderick St",
    "sg:city":"San Francisco",
    "sg:classifiers":[
        {
            "category":"Professional",
            "subcategory":"Lawyer & Legal Services",
            "type":"Services"
        }
    ],
    "sg:phone":"+1 415 863 5074",
    "sg:postcode":"94117",
    "sg:province":"CA",
    "sg:tags":[
        "attorney"
    ],
    "wof:name":"Bruce J Levitz Law Offices",
    "wof:placetype":"venue"
},
  "geometry": {"coordinates":[-122.439111,37.772586],"type":"Point"}
}