{
  "type": "Feature",
  "properties": {
    "iso:country":"US",
    "sg:address":"190 Pasadena Ave",
    "sg:city":"South Pasadena",
    "sg:classifiers":[
        {
            "category":"Personal",
            "subcategory":"Adult",
            "type":"Services"
        }
    ],
    "sg:phone":"+1 323 982 9574",
    "sg:postcode":"91030",
    "sg:province":"CA",
    "sg:tags":[
        "escort"
    ],
    "wof:name":"Motorcyle Escort Co",
    "wof:placetype":"venue"
},
  "geometry": {"coordinates":[-118.174524,34.112147],"type":"Point"}
}