{
  "type": "Feature",
  "properties": {
    "iso:country":"US",
    "sg:address":"4280 Phelan Rd",
    "sg:city":"Phelan",
    "sg:classifiers":[
        {
            "category":"Shopping",
            "subcategory":"Discount & Variety Stores",
            "type":"Retail Goods"
        },
        {
            "category":"Retail",
            "subcategory":"Repair Shop",
            "type":"Services"
        }
    ],
    "sg:phone":"+1 760 868 2022",
    "sg:postcode":"92371",
    "sg:province":"CA",
    "sg:tags":[
        "cleaners",
        "parts",
        "vacuum"
    ],
    "wof:name":"Country Variety Store",
    "wof:placetype":"venue"
},
  "geometry": {"coordinates":[-117.56733199999999,34.426448],"type":"Point"}
}