{
  "type": "Feature",
  "properties": {
    "iso:country":"US",
    "sg:address":"3407 Sunnyside Dr",
    "sg:city":"Riverside",
    "sg:classifiers":[
        {
            "category":"Professional",
            "type":"Services"
        }
    ],
    "sg:phone":"+1 951 682 7221",
    "sg:postcode":"92506",
    "sg:province":"CA",
    "wof:name":"Chemgen Inc",
    "wof:placetype":"venue"
},
  "geometry": {"coordinates":[-117.384274,33.95668],"type":"Point"}
}