{
  "type": "Feature",
  "properties": {
    "addr:full":"900 Northstar Dr Truckee CA 96161",
    "addr:housenumber":"900",
    "addr:postcode":"96161",
    "addr:street":"Northstar Dr",
    "iso:country":"US",
    "sg:address":"900 Northstar Dr",
    "sg:city":"Truckee",
    "sg:classifiers":[
        {
            "category":"Real Estate",
            "subcategory":"Real Estate Services",
            "type":"Services"
        }
    ],
    "sg:phone":"+1 530 562 0378",
    "sg:postcode":"96161",
    "sg:province":"CA",
    "sg:tags":[
        "management",
        "property"
    ],
    "wof:name":"Camco-Condominium Association Management Co",
    "wof:placetype":"venue"
},
  "geometry": {"coordinates":[-120.106003,39.2869],"type":"Point"}
}