{
  "type": "Feature",
  "properties": {
    "iso:country":"US",
    "sg:address":"400 Avon St",
    "sg:city":"Oakland",
    "sg:classifiers":[
        {
            "category":"Taxi",
            "type":"Transportation"
        }
    ],
    "sg:phone":"+1 510 654 8294",
    "sg:postcode":"94618",
    "sg:province":"CA",
    "wof:name":"Yellow Arrow Cab Company",
    "wof:placetype":"venue"
},
  "geometry": {"coordinates":[-122.25778200000001,37.837312],"type":"Point"}
}