{
  "type": "Feature",
  "properties": {
    "iso:country":"US",
    "sg:address":"601 N Avalon Blvd",
    "sg:city":"Wilmington",
    "sg:classifiers":[
        {
            "category":"Banks & Credit Unions",
            "subcategory":"Investment Brokerage",
            "type":"Services"
        }
    ],
    "sg:phone":"+1 310 834 4000",
    "sg:postcode":"90744",
    "sg:province":"CA",
    "sg:tags":[
        "investing"
    ],
    "wof:name":"Golsun Investments",
    "wof:placetype":"venue"
},
  "geometry": {"coordinates":[-118.26237399999999,33.777069],"type":"Point"}
}