{
  "type": "Feature",
  "properties": {
    "addr:full":"390 Industrial Street Campbell CA 95008",
    "addr:housenumber":"390",
    "addr:postcode":"95008",
    "addr:street":"Industrial Street",
    "iso:country":"US",
    "sg:address":"390 Industrial Street",
    "sg:city":"Campbell",
    "sg:classifiers":[
        {
            "category":"Building & Trades",
            "subcategory":"Construction",
            "type":"Services"
        }
    ],
    "sg:phone":"+1 408 866 6682",
    "sg:postcode":"95008",
    "sg:province":"CA",
    "sg:tags":[
        "contractor"
    ],
    "sg:website":"duplanconstruction.com/",
    "wof:name":"Duplan Construction",
    "wof:placetype":"venue"
},
  "geometry": {"coordinates":[-121.947996,37.280563],"type":"Point"}
}