{
  "type": "Feature",
  "properties": {
    "addr:full":"1787 Mesa Verde Ave Ventura CA 93003",
    "addr:housenumber":"1787",
    "addr:postcode":"93003",
    "addr:street":"Mesa Verde Ave",
    "iso:country":"US",
    "sg:address":"1787 Mesa Verde Ave",
    "sg:city":"Ventura",
    "sg:classifiers":[
        {
            "category":"Banks & Credit Unions",
            "subcategory":"Financial Services",
            "type":"Services"
        },
        {
            "category":"Professional",
            "subcategory":"Credit Reporting & Collection",
            "type":"Services"
        }
    ],
    "sg:phone":"+1 805 856 9030",
    "sg:postcode":"93003",
    "sg:province":"CA",
    "sg:tags":[
        "debt",
        "adjuster",
        "agency"
    ],
    "wof:name":"Arm Solutions",
    "wof:placetype":"venue"
},
  "geometry": {"coordinates":[-119.21673199999999,34.2562],"type":"Point"}
}