{
  "type": "Feature",
  "properties": {
    "addr:full":"585 N Mountain Ave Upland CA 91786",
    "addr:housenumber":"585",
    "addr:postcode":"91786",
    "addr:street":"N Mountain Ave",
    "iso:country":"US",
    "sg:address":"585 N Mountain Ave",
    "sg:city":"Upland",
    "sg:classifiers":[
        {
            "category":"Health Services",
            "subcategory":"Doctor",
            "type":"Services"
        }
    ],
    "sg:phone":"+1 909 949 2077",
    "sg:postcode":"91786",
    "sg:province":"CA",
    "sg:tags":[
        "physician",
        "surgeon"
    ],
    "wof:name":"Cris A Armada Jr DO",
    "wof:placetype":"venue"
},
  "geometry": {"coordinates":[-117.670261,34.10306],"type":"Point"}
}