{
  "type": "Feature",
  "properties": {
    "addr:full":"23647 El Toro Rd Lake Forest CA 92630",
    "addr:housenumber":"23647",
    "addr:postcode":"92630",
    "addr:street":"El Toro Rd",
    "iso:country":"US",
    "sg:address":"23647 El Toro Rd",
    "sg:city":"Lake Forest",
    "sg:classifiers":[
        {
            "category":"Personal",
            "subcategory":"Beauty Salon",
            "type":"Services"
        }
    ],
    "sg:phone":"+1 949 770 2243",
    "sg:postcode":"92630",
    "sg:province":"CA",
    "sg:tags":[
        "hair"
    ],
    "sg:website":"www.sportclips.com",
    "wof:name":"Sport Clips",
    "wof:placetype":"venue"
},
  "geometry": {"coordinates":[-117.702769,33.618911],"type":"Point"}
}