{
  "type": "Feature",
  "properties": {
    "iso:country":"US",
    "sg:address":"1812 Woolley Way",
    "sg:city":"Sacramento",
    "sg:classifiers":[
        {
            "category":"Retail",
            "subcategory":"Auto Repair",
            "type":"Services"
        }
    ],
    "sg:phone":"+1 916 921 9439",
    "sg:postcode":"95815",
    "sg:province":"CA",
    "sg:tags":[
        "repairing",
        "automobile"
    ],
    "wof:name":"Vue's Auto Repair",
    "wof:placetype":"venue"
},
  "geometry": {"coordinates":[-121.42388,38.609717],"type":"Point"}
}