{
  "type": "Feature",
  "properties": {
    "iso:country":"US",
    "sg:address":"9715 Main St",
    "sg:city":"Lamont",
    "sg:classifiers":[
        {
            "category":"Personal",
            "type":"Services"
        }
    ],
    "sg:phone":"+1 661 827 1004",
    "sg:postcode":"93241",
    "sg:province":"CA",
    "sg:tags":[
        "control",
        "weight"
    ],
    "wof:name":"Bella Figura",
    "wof:placetype":"venue"
},
  "geometry": {"coordinates":[-118.914466,35.266844],"type":"Point"}
}