{
  "type": "Feature",
  "properties": {
    "addr:full":"901 D St Arcata CA 95521",
    "addr:housenumber":"901",
    "addr:postcode":"95521",
    "addr:street":"D St",
    "iso:country":"US",
    "sg:address":"901 D St",
    "sg:city":"Arcata",
    "sg:classifiers":[
        {
            "category":"Manufacturing",
            "subcategory":"Musical Instruments",
            "type":"Manufacturing & Wholesale Goods"
        }
    ],
    "sg:phone":"+1 707 822 9570",
    "sg:postcode":"95521",
    "sg:province":"CA",
    "sg:website":"www.marimba1.com",
    "wof:name":"Marimba One",
    "wof:placetype":"venue"
},
  "geometry": {"coordinates":[-124.082273,40.86889],"type":"Point"}
}