{
  "type": "Feature",
  "properties": {
    "iso:country":"US",
    "sg:address":"29397 Agoura Rd",
    "sg:city":"Agoura Hills",
    "sg:classifiers":[
        {
            "category":"Wholesale",
            "subcategory":"Medical Equipment & Supplies",
            "type":"Manufacturing & Wholesale Goods"
        }
    ],
    "sg:phone":"+1 818 597 0311",
    "sg:postcode":"91301",
    "sg:province":"CA",
    "sg:tags":[
        "microscope"
    ],
    "wof:name":"Quesant Instruments",
    "wof:placetype":"venue"
},
  "geometry": {"coordinates":[-118.771299,34.145136],"type":"Point"}
}