{
  "type": "Feature",
  "properties": {
    "addr:full":"777 N Baldwin Park Blvd City Of Industry CA 91746",
    "addr:housenumber":"777",
    "addr:postcode":"91746",
    "addr:street":"N Baldwin Park Blvd",
    "iso:country":"US",
    "sg:address":"777 N Baldwin Park Blvd",
    "sg:city":"City Of Industry",
    "sg:classifiers":[
        {
            "category":"Freight",
            "type":"Transportation"
        }
    ],
    "sg:phone":"+1 626 336 7488",
    "sg:postcode":"91746",
    "sg:province":"CA",
    "sg:tags":[
        "trucking"
    ],
    "wof:name":"Cross America Shipping & Haul",
    "wof:placetype":"venue"
},
  "geometry": {"coordinates":[-117.989469,34.059657],"type":"Point"}
}