{
  "type": "Feature",
  "properties": {
    "iso:country":"US",
    "sg:address":"1610 Montana Ave",
    "sg:city":"Santa Monica",
    "sg:classifiers":[
        {
            "category":"Personal",
            "subcategory":"Day Spa",
            "type":"Services"
        }
    ],
    "sg:phone":"+1 310 453 6700",
    "sg:postcode":"90403",
    "sg:province":"CA",
    "sg:website":"www.lasertherapybyinas.com",
    "wof:name":"Laser Therapy by Inas Anis",
    "wof:placetype":"venue"
},
  "geometry": {"coordinates":[-118.492836,34.39057],"type":"Point"}
}