{
  "type": "Feature",
  "properties": {
    "iso:country":"US",
    "sg:address":"1459 E Plaza Blvd",
    "sg:city":"National City",
    "sg:classifiers":[
        {
            "category":"Personal",
            "subcategory":"Beauty Salon",
            "type":"Services"
        }
    ],
    "sg:phone":"+1 619 474 5244",
    "sg:postcode":"91950",
    "sg:province":"CA",
    "sg:tags":[
        "nail",
        "manicuring"
    ],
    "wof:name":"Charlene's Nails",
    "wof:placetype":"venue"
},
  "geometry": {"coordinates":[-117.091003,32.676899],"type":"Point"}
}