{
  "type": "Feature",
  "properties": {
    "iso:country":"US",
    "sg:address":"1585 Limewood Pl",
    "sg:city":"Pittsburg",
    "sg:classifiers":[
        {
            "category":"Real Estate",
            "subcategory":"Real Estate Agent",
            "type":"Services"
        }
    ],
    "sg:phone":"+1 925 432 3985",
    "sg:postcode":"94565",
    "sg:province":"CA",
    "sg:tags":[
        "appraiser"
    ],
    "wof:name":"Mangin's Appraisal Co",
    "wof:placetype":"venue"
},
  "geometry": {"coordinates":[-121.86288,38.001996],"type":"Point"}
}