{
  "type": "Feature",
  "properties": {
    "iso:country":"US",
    "sg:address":"127 Robertson Blvd",
    "sg:city":"Chowchilla",
    "sg:classifiers":[
        {
            "category":"Shopping",
            "subcategory":"Clothing, Apparel, & Fashions",
            "type":"Retail Goods"
        },
        {
            "category":"Shopping",
            "subcategory":"Antiques",
            "type":"Retail Goods"
        },
        {
            "category":"Shopping",
            "subcategory":"Used Merchandise",
            "type":"Retail Goods"
        }
    ],
    "sg:phone":"+1 559 665 7319",
    "sg:postcode":"93610",
    "sg:province":"CA",
    "sg:tags":[
        "resale",
        "shop",
        "consignment"
    ],
    "wof:name":"The Consignment Gallery",
    "wof:placetype":"venue"
},
  "geometry": {"coordinates":[-120.25940300000001,37.123346],"type":"Point"}
}