{
  "type": "Feature",
  "properties": {
    "iso:country":"US",
    "sg:address":"2101 Dove St",
    "sg:city":"Newport Beach",
    "sg:classifiers":[
        {
            "category":"Autos & Motor Vehicles",
            "subcategory":"Auto Supplies",
            "type":"Retail Goods"
        },
        {
            "category":"Retail",
            "subcategory":"Auto Repair",
            "type":"Services"
        }
    ],
    "sg:phone":"+1 949 270 9800",
    "sg:postcode":"92660",
    "sg:province":"CA",
    "sg:tags":[
        "part"
    ],
    "wof:name":"Jaguar Land Rover Newport Beach Service Department",
    "wof:placetype":"venue"
},
  "geometry": {"coordinates":[-117.86937500000001,33.666513],"type":"Point"}
}