{
  "type": "Feature",
  "properties": {
    "addr:full":"4060 Power Inn Rd Sacramento CA 95826",
    "addr:housenumber":"4060",
    "addr:postcode":"95826",
    "addr:street":"Power Inn Rd",
    "iso:country":"US",
    "sg:address":"4060 Power Inn Rd",
    "sg:city":"Sacramento",
    "sg:classifiers":[
        {
            "category":"Shopping",
            "subcategory":"Pets & Pet Supplies",
            "type":"Retail Goods"
        },
        {
            "category":"Retail",
            "subcategory":"Pet Boarding",
            "type":"Services"
        }
    ],
    "sg:phone":"+1 916 456 4720",
    "sg:postcode":"95826",
    "sg:province":"CA",
    "sg:tags":[
        "boarding/pet",
        "store",
        "sitting"
    ],
    "sg:website":"www.animaldenpetresort.com",
    "wof:name":"Animal Den Pet Resort & Spa",
    "wof:placetype":"venue"
},
  "geometry": {"coordinates":[-121.40996,38.537891],"type":"Point"}
}