{
  "type": "Feature",
  "properties": {
    "addr:full":"2305 Duncan Ln Redding CA 96002",
    "addr:housenumber":"2305",
    "addr:postcode":"96002",
    "addr:street":"Duncan Ln",
    "iso:country":"US",
    "sg:address":"2305 Duncan Ln",
    "sg:city":"Redding",
    "sg:classifiers":[
        {
            "category":"Food & Beverages",
            "subcategory":"Dairy",
            "type":"Retail Goods"
        }
    ],
    "sg:phone":"+1 530 221 3481",
    "sg:postcode":"96002",
    "sg:province":"CA",
    "sg:tags":[
        "product"
    ],
    "wof:name":"Grant Amen Dairy",
    "wof:placetype":"venue"
},
  "geometry": {"coordinates":[-122.328864,40.498226],"type":"Point"}
}