{
  "type": "Feature",
  "properties": {
    "addr:full":"1710 Janes Rd Arcata CA 95521",
    "addr:housenumber":"1710",
    "addr:postcode":"95521",
    "addr:street":"Janes Rd",
    "iso:country":"US",
    "sg:address":"1710 Janes Rd",
    "sg:city":"Arcata",
    "sg:classifiers":[
        {
            "category":"Education",
            "subcategory":"School",
            "type":"Public Place"
        }
    ],
    "sg:phone":"+1 707 822 5626",
    "sg:postcode":"95521",
    "sg:province":"CA",
    "sg:website":"www.laureltree.expage.com",
    "wof:name":"Laurel Tree Learning Ctr",
    "wof:placetype":"venue"
},
  "geometry": {"coordinates":[-124.10036599999999,40.881],"type":"Point"}
}