{
  "type": "Feature",
  "properties": {
    "addr:full":"1518 Park St Alameda CA 94501",
    "addr:housenumber":"1518",
    "addr:postcode":"94501",
    "addr:street":"Park St",
    "iso:country":"US",
    "sg:address":"1518 Park St",
    "sg:city":"Alameda",
    "sg:classifiers":[
        {
            "category":"Restaurant",
            "type":"Food & Drink"
        }
    ],
    "sg:menulink":"http://www.allmenus.com/ca/alameda/279158-havana/menu/",
    "sg:phone":"+1 510 521 0130",
    "sg:postcode":"94501",
    "sg:province":"CA",
    "sg:tags":[
        "cuban"
    ],
    "wof:name":"Havana",
    "wof:placetype":"venue"
},
  "geometry": {"coordinates":[-122.241381,37.765716],"type":"Point"}
}