{
  "type": "Feature",
  "properties": {
    "iso:country":"US",
    "sg:address":"6503 Lincoln Ave",
    "sg:city":"Carmichael",
    "sg:classifiers":[
        {
            "category":"Professional",
            "type":"Services"
        }
    ],
    "sg:phone":"+1 916 944 4935",
    "sg:postcode":"95608",
    "sg:province":"CA",
    "wof:name":"Eye Sportswear",
    "wof:placetype":"venue"
},
  "geometry": {"coordinates":[-121.31305399999999,38.640312],"type":"Point"}
}