{
  "type": "Feature",
  "properties": {
    "addr:full":"701 Lighthouse Ave Pacific Grove CA 93950",
    "addr:housenumber":"701",
    "addr:postcode":"93950",
    "addr:street":"Lighthouse Ave",
    "iso:country":"US",
    "sg:address":"701 Lighthouse Ave",
    "sg:city":"Pacific Grove",
    "sg:classifiers":[
        {
            "category":"Restaurant",
            "type":"Food & Drink"
        }
    ],
    "sg:menulink":"http://www.allmenus.com/ca/seaside-monterey/273825-passionfish/menu/",
    "sg:phone":"+1 831 655 3311",
    "sg:postcode":"93950",
    "sg:province":"CA",
    "sg:tags":[
        "seafood",
        "american"
    ],
    "wof:name":"Passionfish",
    "wof:placetype":"venue"
},
  "geometry": {"coordinates":[-121.920889,36.622365],"type":"Point"}
}