{
  "type": "Feature",
  "properties": {
    "iso:country":"US",
    "sg:address":"18228 Parthenia St",
    "sg:city":"Northridge",
    "sg:classifiers":[
        {
            "category":"Shopping",
            "type":"Retail Goods"
        }
    ],
    "sg:phone":"+1 818 701 0557",
    "sg:postcode":"91325",
    "sg:province":"CA",
    "sg:tags":[
        "equipment",
        "beer",
        "supply"
    ],
    "sg:website":"www.homebrew.com",
    "wof:name":"Brew Wizards",
    "wof:placetype":"venue"
},
  "geometry": {"coordinates":[-118.529669,34.228591],"type":"Point"}
}