{
  "type": "Feature",
  "properties": {
    "addr:full":"2005 E Highland Ave San Bernardino CA 92404",
    "addr:housenumber":"2005",
    "addr:postcode":"92404",
    "addr:street":"E Highland Ave",
    "iso:country":"US",
    "sg:address":"2005 E Highland Ave",
    "sg:city":"San Bernardino",
    "sg:classifiers":[
        {
            "category":"Food & Beverages",
            "subcategory":"Groceries & Convenience Stores",
            "type":"Retail Goods"
        }
    ],
    "sg:phone":"+1 909 884 1902",
    "sg:postcode":"92404",
    "sg:province":"CA",
    "sg:tags":[
        "grocer"
    ],
    "wof:name":"Rocky Market",
    "wof:placetype":"venue"
},
  "geometry": {"coordinates":[-117.239378,34.135934],"type":"Point"}
}