{
  "type": "Feature",
  "properties": {
    "iso:country":"US",
    "sg:address":"10140 Magnolia St",
    "sg:city":"Bloomington",
    "sg:classifiers":[
        {
            "category":"Bars & Pubs",
            "type":"Food & Drink"
        }
    ],
    "sg:phone":"+1 909 877 2391",
    "sg:postcode":"92316",
    "sg:province":"CA",
    "sg:tags":[
        "lounge",
        "cocktail"
    ],
    "wof:name":"Sundowner",
    "wof:placetype":"venue"
},
  "geometry": {"coordinates":[-117.39783799999999,34.069635],"type":"Point"}
}