{
  "type": "Feature",
  "properties": {
    "addr:full":"15100 Jack Tone Rd Manteca CA 95336",
    "addr:housenumber":"15100",
    "addr:postcode":"95336",
    "addr:street":"Jack Tone Rd",
    "iso:country":"US",
    "sg:address":"15100 Jack Tone Rd",
    "sg:city":"Manteca",
    "sg:classifiers":[
        {
            "category":"Farming",
            "subcategory":"Farm",
            "type":"Manufacturing & Wholesale Goods"
        }
    ],
    "sg:phone":"+1 209 823 6995",
    "sg:postcode":"95336",
    "sg:province":"CA",
    "sg:tags":[
        "management",
        "crop",
        "general"
    ],
    "sg:website":"www.vgandsons.com",
    "wof:name":"Van Groningen & Sons Inc",
    "wof:placetype":"venue"
},
  "geometry": {"coordinates":[-121.144261,37.826789],"type":"Point"}
}