{
  "type": "Feature",
  "properties": {
    "iso:country":"US",
    "sg:address":"4927 Firestone Boulevard",
    "sg:city":"South Gate",
    "sg:classifiers":[
        {
            "category":"Building & Trades",
            "subcategory":"Pest Control",
            "type":"Services"
        }
    ],
    "sg:phone":"+1 323 569 7496",
    "sg:postcode":"90280",
    "sg:province":"CA",
    "wof:name":"Pest Solutions",
    "wof:placetype":"venue"
},
  "geometry": {"coordinates":[-118.182562,33.951922],"type":"Point"}
}