{
  "type": "Feature",
  "properties": {
    "addr:full":"404 E Redlands Blvd Redlands CA 92373",
    "addr:housenumber":"404",
    "addr:postcode":"92373",
    "addr:street":"E Redlands Blvd",
    "iso:country":"US",
    "sg:address":"404 E Redlands Blvd",
    "sg:city":"Redlands",
    "sg:classifiers":[
        {
            "category":"Manufacturing",
            "subcategory":"Signs",
            "type":"Manufacturing & Wholesale Goods"
        }
    ],
    "sg:phone":"+1 909 792 5577",
    "sg:postcode":"92373",
    "sg:province":"CA",
    "sg:website":"www.signsnowredlands.com",
    "wof:name":"Signs Now",
    "wof:placetype":"venue"
},
  "geometry": {"coordinates":[-117.17728,34.056878],"type":"Point"}
}