{
  "type": "Feature",
  "properties": {
    "addr:full":"430 Newton Way Angwin CA 94508",
    "addr:housenumber":"430",
    "addr:postcode":"94508",
    "addr:street":"Newton Way",
    "iso:country":"US",
    "sg:address":"430 Newton Way",
    "sg:city":"Angwin",
    "sg:classifiers":[
        {
            "category":"Wholesale",
            "subcategory":"Vending Machines",
            "type":"Manufacturing & Wholesale Goods"
        }
    ],
    "sg:phone":"+1 707 965 0617",
    "sg:postcode":"94508",
    "sg:province":"CA",
    "sg:tags":[
        "operator"
    ],
    "wof:name":"Rs Vending",
    "wof:placetype":"venue"
},
  "geometry": {"coordinates":[-122.44568700000001,38.580485],"type":"Point"}
}