{
  "type": "Feature",
  "properties": {
    "iso:country":"US",
    "sg:address":"1984 N Main St",
    "sg:city":"Los Angeles",
    "sg:classifiers":[
        {
            "category":"Professional",
            "type":"Services"
        }
    ],
    "sg:phone":"+1 323 221 5006",
    "sg:postcode":"90031",
    "sg:province":"CA",
    "wof:name":"Miseryloves Co",
    "wof:placetype":"venue"
},
  "geometry": {"coordinates":[-118.219336,34.066038],"type":"Point"}
}