{
  "type": "Feature",
  "properties": {
    "addr:full":"1900 S del Mar Ave San Gabriel CA 91776",
    "addr:housenumber":"1900",
    "addr:postcode":"91776",
    "addr:street":"S Del Mar Ave",
    "iso:country":"US",
    "sg:address":"1900 S del Mar Ave",
    "sg:city":"San Gabriel",
    "sg:classifiers":[
        {
            "category":"Professional",
            "type":"Services"
        }
    ],
    "sg:phone":"+1 626 307 8719",
    "sg:postcode":"91776",
    "sg:province":"CA",
    "sg:tags":[
        "establishment"
    ],
    "sg:website":"www.welllinkus.com",
    "wof:name":"Welllink Corp",
    "wof:placetype":"venue"
},
  "geometry": {"coordinates":[-118.099541,34.07524],"type":"Point"}
}