{
  "type": "Feature",
  "properties": {
    "iso:country":"US",
    "sg:address":"1989 Santa Rita Rd",
    "sg:city":"Pleasanton",
    "sg:classifiers":[
        {
            "category":"Shopping",
            "subcategory":"Clothing, Apparel, & Fashions",
            "type":"Retail Goods"
        }
    ],
    "sg:phone":"+1 925 462 7130",
    "sg:postcode":"94566",
    "sg:province":"CA",
    "sg:tags":[
        "jewelry"
    ],
    "wof:name":"Significant Pieces",
    "wof:placetype":"venue"
},
  "geometry": {"coordinates":[-121.874786,37.678545],"type":"Point"}
}