{
  "type": "Feature",
  "properties": {
    "iso:country":"US",
    "sg:address":"2201 S Santa Fe Ave",
    "sg:city":"Compton",
    "sg:classifiers":[
        {
            "category":"Manufacturing",
            "subcategory":"Retail Goods",
            "type":"Manufacturing & Wholesale Goods"
        }
    ],
    "sg:phone":"+1 323 774 7930",
    "sg:postcode":"90221",
    "sg:province":"CA",
    "sg:tags":[
        "manufacturer"
    ],
    "wof:name":"A-Bec Industries",
    "wof:placetype":"venue"
},
  "geometry": {"coordinates":[-118.21480200000001,33.875425],"type":"Point"}
}