{
  "type": "Feature",
  "properties": {
    "addr:full":"5305 N Fresno St Fresno CA 93710",
    "addr:housenumber":"5305",
    "addr:postcode":"93710",
    "addr:street":"N Fresno",
    "iso:country":"US",
    "sg:address":"5305 N Fresno St",
    "sg:city":"Fresno",
    "sg:classifiers":[
        {
            "category":"Health Services",
            "subcategory":"Doctor",
            "type":"Services"
        }
    ],
    "sg:phone":"+1 559 222 5241",
    "sg:postcode":"93710",
    "sg:province":"CA",
    "sg:tags":[
        "physician",
        "surgeon"
    ],
    "wof:name":"Melvyn Froese MD",
    "wof:placetype":"venue"
},
  "geometry": {"coordinates":[-119.781406,36.815666],"type":"Point"}
}