{
  "type": "Feature",
  "properties": {
    "addr:full":"1260 S State Hwy 59 Merced CA 95340",
    "addr:housenumber":"1260",
    "addr:postcode":"95340",
    "addr:street":"S State Hwy 59",
    "iso:country":"US",
    "sg:address":"1260 S State Hwy 59",
    "sg:city":"Merced",
    "sg:classifiers":[
        {
            "category":"Wholesale",
            "subcategory":"Farm Supplies",
            "type":"Manufacturing & Wholesale Goods"
        }
    ],
    "sg:phone":"+1 209 722 2072",
    "sg:postcode":"95340",
    "sg:province":"CA",
    "sg:tags":[
        "hay",
        "broker"
    ],
    "wof:name":"Moss Hay Inc",
    "wof:placetype":"venue"
},
  "geometry": {"coordinates":[-120.48776599999999,37.269619],"type":"Point"}
}