{
  "type": "Feature",
  "properties": {
    "addr:full":"321 E Alameda Ave Burbank CA 91502",
    "addr:housenumber":"321",
    "addr:postcode":"91502",
    "addr:street":"E Alameda Ave",
    "iso:country":"US",
    "sg:address":"321 E Alameda Ave",
    "sg:city":"Burbank",
    "sg:classifiers":[
        {
            "category":"Professional",
            "type":"Services"
        }
    ],
    "sg:phone":"+1 818 845 6237",
    "sg:postcode":"91502",
    "sg:province":"CA",
    "wof:name":"Kevin Siv",
    "wof:placetype":"venue"
},
  "geometry": {"coordinates":[-118.298543,34.175681],"type":"Point"}
}