{
  "type": "Feature",
  "properties": {
    "iso:country":"US",
    "sg:address":"111 Deerwood Pl",
    "sg:city":"San Ramon",
    "sg:classifiers":[
        {
            "category":"Manufacturing",
            "subcategory":"Retail Goods",
            "type":"Manufacturing & Wholesale Goods"
        }
    ],
    "sg:phone":"+1 925 855 3285",
    "sg:postcode":"94583",
    "sg:province":"CA",
    "sg:tags":[
        "product",
        "mfg"
    ],
    "wof:name":"Young & Co",
    "wof:placetype":"venue"
},
  "geometry": {"coordinates":[-121.988213,37.774607],"type":"Point"}
}