{
  "type": "Feature",
  "properties": {
    "iso:country":"US",
    "sg:address":"105 S el Molino Ave",
    "sg:city":"Pasadena",
    "sg:classifiers":[
        {
            "category":"Home & Garden",
            "subcategory":"Household Appliances",
            "type":"Retail Goods"
        }
    ],
    "sg:phone":"+1 626 795 9999",
    "sg:postcode":"91101",
    "sg:province":"CA",
    "sg:website":"www.americanappliancerepair.com",
    "wof:name":"American Appliance Repair",
    "wof:placetype":"venue"
},
  "geometry": {"coordinates":[-118.13693600000001,34.144356],"type":"Point"}
}