{
  "type": "Feature",
  "properties": {
    "iso:country":"US",
    "sg:address":"15434 Gale Ave",
    "sg:city":"Hacienda Heights",
    "sg:classifiers":[
        {
            "category":"Banks & Credit Unions",
            "subcategory":"Bank",
            "type":"Services"
        }
    ],
    "sg:phone":"+1 626 369 4660",
    "sg:postcode":"91745",
    "sg:province":"CA",
    "sg:tags":[
        "broker",
        "mortgage"
    ],
    "wof:name":"Anne Bleaden-Castro",
    "wof:placetype":"venue"
},
  "geometry": {"coordinates":[-117.97172399999999,34.013466],"type":"Point"}
}