{
  "type": "Feature",
  "properties": {
    "iso:country":"US",
    "sg:address":"3029 25th St",
    "sg:city":"San Francisco",
    "sg:classifiers":[
        {
            "category":"Personal",
            "type":"Services"
        }
    ],
    "sg:postcode":"94110",
    "sg:province":"CA",
    "sg:tags":[
        "home"
    ],
    "sg:website":"www.sunset.com/sunset/home/artic...",
    "wof:name":"Sunset Idea House",
    "wof:placetype":"venue"
},
  "geometry": {"coordinates":[-122.410445,37.751116],"type":"Point"}
}