{
  "type": "Feature",
  "properties": {
    "iso:country":"US",
    "sg:address":"15592 Graham St",
    "sg:city":"Huntington Beach",
    "sg:classifiers":[
        {
            "category":"Real Estate",
            "subcategory":"Real Estate Operator",
            "type":"Services"
        }
    ],
    "sg:phone":"+1 714 379 1718",
    "sg:postcode":"92649",
    "sg:province":"CA",
    "sg:tags":[
        "building",
        "nonresidential"
    ],
    "wof:name":"Progressive Enterprise",
    "wof:placetype":"venue"
},
  "geometry": {"coordinates":[-118.03256,33.735536],"type":"Point"}
}