{
  "type": "Feature",
  "properties": {
    "addr:full":"69600 Hwy 111 Rancho Mirage CA 92270",
    "addr:housenumber":"69600",
    "addr:postcode":"92270",
    "addr:street":"Hwy 111",
    "iso:country":"US",
    "sg:address":"69600 Hwy 111",
    "sg:city":"Rancho Mirage",
    "sg:classifiers":[
        {
            "category":"Restaurant",
            "type":"Food & Drink"
        }
    ],
    "sg:phone":"+1 760 328 9200",
    "sg:postcode":"92270",
    "sg:province":"CA",
    "sg:tags":[
        "chinese"
    ],
    "wof:name":"Emperor Asian Buffet",
    "wof:placetype":"venue"
},
  "geometry": {"coordinates":[-116.448218,33.774432],"type":"Point"}
}