{
  "type": "Feature",
  "properties": {
    "addr:full":"18200 Abbott Ln Villa Park CA 92861",
    "addr:housenumber":"18200",
    "addr:postcode":"92861",
    "addr:street":"Abbott Ln",
    "iso:country":"US",
    "sg:address":"18200 Abbott Ln",
    "sg:city":"Villa Park",
    "sg:classifiers":[
        {
            "category":"Taxi",
            "type":"Transportation"
        }
    ],
    "sg:phone":"+1 714 547 2442",
    "sg:postcode":"92861",
    "sg:province":"CA",
    "sg:tags":[
        "taxicab"
    ],
    "wof:name":"Yellaaa Cab",
    "wof:placetype":"venue"
},
  "geometry": {"coordinates":[-117.814148,33.811908],"type":"Point"}
}