{
  "type": "Feature",
  "properties": {
    "addr:full":"307 S Main St Dorris CA 96023",
    "addr:housenumber":"307",
    "addr:postcode":"96023",
    "addr:street":"S Main St",
    "iso:country":"US",
    "sg:address":"307 S Main St",
    "sg:city":"Dorris",
    "sg:classifiers":[
        {
            "category":"Government",
            "subcategory":"Office",
            "type":"Public Place"
        }
    ],
    "sg:phone":"+1 530 397 2350",
    "sg:postcode":"96023",
    "sg:province":"CA",
    "sg:tags":[
        "county",
        "resource"
    ],
    "wof:name":"Siskiyou County Wic Program",
    "wof:placetype":"venue"
},
  "geometry": {"coordinates":[-121.918314,41.963609],"type":"Point"}
}