{
  "type": "Feature",
  "properties": {
    "addr:full":"4885 Las Virgenes Rd Calabasas CA 91302",
    "addr:housenumber":"4885",
    "addr:postcode":"91302",
    "addr:street":"Las Virgenes Rd",
    "iso:country":"US",
    "sg:address":"4885 Las Virgenes Rd",
    "sg:city":"Calabasas",
    "sg:phone":"+1 323 460 4252",
    "sg:postcode":"91302",
    "sg:province":"CA",
    "wof:name":"Spotless Window Washing",
    "wof:placetype":"venue"
},
  "geometry": {"coordinates":[-118.697974,34.146265],"type":"Point"}
}