{
  "type": "Feature",
  "properties": {
    "addr:full":"111 Hawkins St Hollister CA 95023",
    "addr:housenumber":"111",
    "addr:postcode":"hollister ca 95023",
    "addr:street":"Hawkins St",
    "iso:country":"US",
    "sg:address":"111 Hawkins St",
    "sg:city":"Hollister",
    "sg:classifiers":[
        {
            "category":"Manufacturing",
            "subcategory":"Food",
            "type":"Manufacturing & Wholesale Goods"
        }
    ],
    "sg:phone":"+1 831 637 4434",
    "sg:postcode":"95023",
    "sg:province":"CA",
    "sg:tags":[
        "canned",
        "specialty"
    ],
    "sg:website":"www.sanbenitofoods.com",
    "wof:name":"San Benito Foods",
    "wof:placetype":"venue"
},
  "geometry": {"coordinates":[-121.40112000000001,36.846447],"type":"Point"}
}