{
  "type": "Feature",
  "properties": {
    "addr:full":"938 26th St Oakland CA 94607",
    "addr:housenumber":"938",
    "addr:postcode":"94607",
    "addr:street":"26Th St",
    "iso:country":"US",
    "sg:address":"938 26th St",
    "sg:city":"Oakland",
    "sg:classifiers":[
        {
            "category":"Professional",
            "subcategory":"Business Services",
            "type":"Services"
        }
    ],
    "sg:phone":"+1 510 355 7373",
    "sg:postcode":"94607",
    "sg:province":"CA",
    "sg:tags":[
        "consultant",
        "coach"
    ],
    "wof:name":"Rbi International Inc",
    "wof:placetype":"venue"
},
  "geometry": {"coordinates":[-122.27838300000001,37.817697],"type":"Point"}
}