{
  "type": "Feature",
  "properties": {
    "iso:country":"US",
    "sg:address":"3 South Pointe Dr",
    "sg:city":"Lake Forest",
    "sg:classifiers":[
        {
            "category":"Travel",
            "subcategory":"Hotels & Motels",
            "type":"Entertainment"
        },
        {
            "category":"Retail",
            "subcategory":"Event Space",
            "type":"Services"
        }
    ],
    "sg:phone":"+1 949 598 9105",
    "sg:postcode":"92630",
    "sg:province":"CA",
    "sg:tags":[
        "venue"
    ],
    "sg:website":"www.candlewoodsuites.com",
    "wof:name":"Candlewood Suites Extended Stay Hotel Orange County Irvine",
    "wof:placetype":"venue"
},
  "geometry": {"coordinates":[-117.699146,33.659043],"type":"Point"}
}