{
  "type": "Feature",
  "properties": {
    "addr:full":"520 Mesa Rd Point Reyes Sta CA 94956",
    "addr:housenumber":"520",
    "addr:postcode":"94956",
    "addr:street":"Mesa Rd;Reyes Sta",
    "iso:country":"US",
    "sg:address":"520 Mesa Rd",
    "sg:city":"Point Reyes Sta",
    "sg:classifiers":[
        {
            "category":"Organizations",
            "subcategory":"Non-profit Organization",
            "type":"Services"
        }
    ],
    "sg:phone":"+1 415 663 1158",
    "sg:postcode":"94956",
    "sg:province":"CA",
    "sg:website":"www.malt.org",
    "wof:name":"Marin Agricultural Land Trust",
    "wof:placetype":"venue"
},
  "geometry": {"coordinates":[-122.807418,38.069812],"type":"Point"}
}