{
  "type": "Feature",
  "properties": {
    "addr:full":"6649 W Olympic Blvd Los Angeles CA 90048",
    "addr:housenumber":"6649",
    "addr:postcode":"90048",
    "addr:street":"W Olympic Blvd",
    "iso:country":"US",
    "sg:address":"6649 W Olympic Blvd",
    "sg:city":"Los Angeles",
    "sg:classifiers":[
        {
            "category":"Manufacturing",
            "subcategory":"Apparel",
            "type":"Manufacturing & Wholesale Goods"
        }
    ],
    "sg:phone":"+1 323 954 8822",
    "sg:postcode":"90048",
    "sg:province":"CA",
    "sg:tags":[
        "manufacture",
        "costume",
        "jewelry"
    ],
    "wof:name":"Sparkling Sage LLC",
    "wof:placetype":"venue"
},
  "geometry": {"coordinates":[-118.374591,34.059482],"type":"Point"}
}