{
  "type": "Feature",
  "properties": {
    "addr:full":"3105 W Monte Vista Ave Turlock CA 95380",
    "addr:housenumber":"3105",
    "addr:postcode":"95380",
    "addr:street":"W Monte Vista Ave",
    "iso:country":"US",
    "sg:address":"3105 W Monte Vista Ave",
    "sg:city":"Turlock",
    "sg:classifiers":[
        {
            "category":"Fast Food",
            "type":"Food & Drink"
        }
    ],
    "sg:phone":"+1 209 667 9901",
    "sg:postcode":"95380",
    "sg:province":"CA",
    "sg:tags":[
        "burger"
    ],
    "sg:website":"www.redrobin.com",
    "wof:name":"Red Robin",
    "wof:placetype":"venue"
},
  "geometry": {"coordinates":[-120.883126,37.521996],"type":"Point"}
}