{
  "type": "Feature",
  "properties": {
    "iso:country":"US",
    "sg:address":"3080 Marlow Rd",
    "sg:city":"Santa Rosa",
    "sg:classifiers":[
        {
            "category":"Personal",
            "subcategory":"Beauty Salon",
            "type":"Services"
        }
    ],
    "sg:phone":"+1 707 569 8846",
    "sg:postcode":"95403",
    "sg:province":"CA",
    "sg:tags":[
        "manicuring"
    ],
    "wof:name":"My Lovely Nails",
    "wof:placetype":"venue"
},
  "geometry": {"coordinates":[-122.751202,38.467093],"type":"Point"}
}