{
  "type": "Feature",
  "properties": {
    "iso:country":"US",
    "sg:address":"620 W Mill St",
    "sg:city":"San Bernardino",
    "sg:classifiers":[
        {
            "category":"Manufacturing",
            "subcategory":"Motor Vehicles & Parts",
            "type":"Manufacturing & Wholesale Goods"
        }
    ],
    "sg:phone":"+1 909 376 9083",
    "sg:postcode":"92410",
    "sg:province":"CA",
    "sg:tags":[
        "automobile",
        "supply"
    ],
    "sg:website":"www.beetlecup.com",
    "wof:name":"Beetle Cup Connection",
    "wof:placetype":"venue"
},
  "geometry": {"coordinates":[-117.296603,34.092222],"type":"Point"}
}