{
  "type": "Feature",
  "properties": {
    "addr:full":"975 Osos St San Luis Obispo CA 93401",
    "addr:housenumber":"975",
    "addr:postcode":"93401",
    "addr:street":"Osos St",
    "iso:country":"US",
    "sg:address":"975 Osos St",
    "sg:city":"San Luis Obispo",
    "sg:classifiers":[
        {
            "category":"Professional",
            "subcategory":"Research",
            "type":"Services"
        }
    ],
    "sg:phone":"+1 805 546 1860",
    "sg:postcode":"93401",
    "sg:province":"CA",
    "sg:tags":[
        "commercial",
        "physical"
    ],
    "wof:name":"Essex Environmental",
    "wof:placetype":"venue"
},
  "geometry": {"coordinates":[-120.661686,35.281952],"type":"Point"}
}