{
  "type": "Feature",
  "properties": {
    "iso:country":"US",
    "sg:address":"2262 California St",
    "sg:city":"San Francisco",
    "sg:classifiers":[
        {
            "category":"Health Services",
            "subcategory":"Clinic",
            "type":"Services"
        },
        {
            "category":"Education",
            "subcategory":"Special Training",
            "type":"Public Place"
        }
    ],
    "sg:phone":"+1 888 724 7840",
    "sg:postcode":"94199",
    "sg:province":"CA",
    "sg:tags":[
        "counseling",
        "mental",
        "adult"
    ],
    "sg:website":"www.mcmoylermethod.com",
    "wof:name":"McMoyler Method",
    "wof:placetype":"venue"
},
  "geometry": {"coordinates":[-122.43161600000001,37.789233],"type":"Point"}
}