{
  "type": "Feature",
  "properties": {
    "addr:full":"125 W Chanslor Way Blythe CA 92225",
    "addr:housenumber":"125",
    "addr:postcode":"92225",
    "addr:street":"W Chanslor Way",
    "iso:country":"US",
    "sg:address":"125 W Chanslor Way",
    "sg:city":"Blythe",
    "sg:classifiers":[
        {
            "category":"Education",
            "subcategory":"Library",
            "type":"Public Place"
        }
    ],
    "sg:phone":"+1 760 922 5371",
    "sg:postcode":"92225",
    "sg:province":"CA",
    "sg:website":"www.paloverdevalleylibrary.com",
    "wof:name":"Palo Verde Valley Library",
    "wof:placetype":"venue"
},
  "geometry": {"coordinates":[-114.59725400000001,33.617697],"type":"Point"}
}