{
  "type": "Feature",
  "properties": {
    "addr:full":"6308 Woodman Ave Van Nuys CA 91401",
    "addr:housenumber":"6308",
    "addr:postcode":"91401",
    "addr:street":"Woodman Ave",
    "iso:country":"US",
    "sg:address":"6308 Woodman Ave",
    "sg:city":"Van Nuys",
    "sg:classifiers":[
        {
            "category":"Professional",
            "subcategory":"Lawyer & Legal Services",
            "type":"Services"
        }
    ],
    "sg:phone":"+1 818 989 3598",
    "sg:postcode":"91401",
    "sg:province":"CA",
    "wof:name":"Hammer Sheryl",
    "wof:placetype":"venue"
},
  "geometry": {"coordinates":[-118.431,34.185001],"type":"Point"}
}