{
  "type": "Feature",
  "properties": {
    "addr:full":"6320 San Ignacio Ave San Jose CA 95119",
    "addr:housenumber":"6320",
    "addr:postcode":"95119",
    "addr:street":"San Ignacio Ave",
    "iso:country":"US",
    "sg:address":"6320 San Ignacio Ave",
    "sg:city":"San Jose",
    "sg:classifiers":[
        {
            "category":"Professional",
            "subcategory":"Computer Services",
            "type":"Services"
        }
    ],
    "sg:phone":"+1 408 284 6200",
    "sg:postcode":"95119",
    "sg:province":"CA",
    "wof:name":"San Valley Systems",
    "wof:placetype":"venue"
},
  "geometry": {"coordinates":[-121.779481,37.236591],"type":"Point"}
}