{
  "type": "Feature",
  "properties": {
    "addr:full":"1835 Bus Center Dr Duarte CA 91010",
    "addr:housenumber":"1835",
    "addr:postcode":"91010",
    "addr:street":"Bus Center Dr",
    "iso:country":"US",
    "sg:address":"1835 Bus Center Dr",
    "sg:city":"Duarte",
    "sg:classifiers":[
        {
            "category":"Wholesale",
            "subcategory":"Machinery & Supplies",
            "type":"Manufacturing & Wholesale Goods"
        }
    ],
    "sg:phone":"+1 626 357 9764",
    "sg:postcode":"91010",
    "sg:province":"CA",
    "sg:tags":[
        "pipe",
        "fitting"
    ],
    "wof:name":"DMM Pipe Fitting & Supply",
    "wof:placetype":"venue"
},
  "geometry": {"coordinates":[-117.965137,34.133998],"type":"Point"}
}