{
  "type": "Feature",
  "properties": {
    "iso:country":"US",
    "sg:address":"2851 E Gage Ave",
    "sg:city":"Huntington Park",
    "sg:classifiers":[
        {
            "category":"Autos & Motor Vehicles",
            "subcategory":"Automobile Sales",
            "type":"Retail Goods"
        }
    ],
    "sg:phone":"+1 323 581 0672",
    "sg:postcode":"90255",
    "sg:province":"CA",
    "sg:tags":[
        "car",
        "dealer"
    ],
    "wof:name":"LA Mesa Enterprises",
    "wof:placetype":"venue"
},
  "geometry": {"coordinates":[-118.218683,33.981528],"type":"Point"}
}