{
  "type": "Feature",
  "properties": {
    "iso:country":"US",
    "sg:address":"14416 Friar St",
    "sg:city":"Van Nuys",
    "sg:classifiers":[
        {
            "category":"Food & Beverages",
            "subcategory":"Bakery",
            "type":"Retail Goods"
        }
    ],
    "sg:phone":"+1 818 901 1355",
    "sg:postcode":"91401",
    "sg:province":"CA",
    "sg:tags":[
        "baker"
    ],
    "wof:name":"Wild Angels Bakery",
    "wof:placetype":"venue"
},
  "geometry": {"coordinates":[-118.448419,34.185596],"type":"Point"}
}