{
  "type": "Feature",
  "properties": {
    "addr:full":"5650 Van Buren Blvd Riverside CA 92503",
    "addr:housenumber":"5650",
    "addr:postcode":"92503",
    "addr:street":"Van Buren Blvd",
    "iso:country":"US",
    "sg:address":"5650 Van Buren Blvd",
    "sg:city":"Riverside",
    "sg:classifiers":[
        {
            "category":"Restaurant",
            "type":"Food & Drink"
        }
    ],
    "sg:phone":"+1 951 353 2272",
    "sg:postcode":"92503",
    "sg:province":"CA",
    "wof:name":"Mi Casa",
    "wof:placetype":"venue"
},
  "geometry": {"coordinates":[-117.454007,33.940906],"type":"Point"}
}