{
  "type": "Feature",
  "properties": {
    "addr:full":"128 6th Ave City Of Industry CA 91746",
    "addr:housenumber":"128",
    "addr:postcode":"91746",
    "addr:street":"6Th Ave",
    "iso:country":"US",
    "sg:address":"128 6th Ave",
    "sg:city":"City Of Industry",
    "sg:classifiers":[
        {
            "category":"Wholesale",
            "subcategory":"Machinery & Supplies",
            "type":"Manufacturing & Wholesale Goods"
        }
    ],
    "sg:phone":"+1 626 961 4648",
    "sg:postcode":"91746",
    "sg:province":"CA",
    "sg:tags":[
        "material",
        "ink"
    ],
    "wof:name":"Acujet USA Inc",
    "wof:placetype":"venue"
},
  "geometry": {"coordinates":[-117.980921,34.034556],"type":"Point"}
}