{
  "type": "Feature",
  "properties": {
    "iso:country":"US",
    "sg:address":"13310 Frame Rd",
    "sg:city":"Poway",
    "sg:classifiers":[
        {
            "category":"Professional",
            "type":"Services"
        }
    ],
    "sg:phone":"+1 858 486 1676",
    "sg:postcode":"92064",
    "sg:province":"CA",
    "wof:name":"Yetz and Crosby",
    "wof:placetype":"venue"
},
  "geometry": {"coordinates":[-117.060976,32.959501],"type":"Point"}
}