{
  "type": "Feature",
  "properties": {
    "addr:full":"2905 N Sunnyside Ave Fresno CA 93727",
    "addr:housenumber":"2905",
    "addr:postcode":"93727",
    "addr:street":"N Sunnyside Ave",
    "iso:country":"US",
    "sg:address":"2905 N Sunnyside Ave",
    "sg:city":"Fresno",
    "sg:classifiers":[
        {
            "category":"Retail",
            "subcategory":"Auto Repair",
            "type":"Services"
        }
    ],
    "sg:phone":"+1 559 292 3412",
    "sg:postcode":"93727",
    "sg:province":"CA",
    "sg:tags":[
        "repairing",
        "automobile"
    ],
    "wof:name":"Ian Souza's Complete Auto Care",
    "wof:placetype":"venue"
},
  "geometry": {"coordinates":[-119.69176400000001,36.776837],"type":"Point"}
}