{
  "type": "Feature",
  "properties": {
    "addr:full":"9160 Rosedale Hwy Bakersfield CA 93312",
    "addr:housenumber":"9160",
    "addr:postcode":"93312",
    "addr:street":"Rosedale Hwy",
    "iso:country":"US",
    "sg:address":"9160 Rosedale Hwy",
    "sg:city":"Bakersfield",
    "sg:classifiers":[
        {
            "category":"Ice Cream",
            "type":"Food & Drink"
        }
    ],
    "sg:menulink":"http://www.allmenus.com/ca/rosedale/183770-cold-stone-creamery/menu/",
    "sg:phone":"+1 661 588 5707",
    "sg:postcode":"93312",
    "sg:province":"CA",
    "sg:tags":[
        "smoothy",
        "juice",
        "american"
    ],
    "wof:name":"Cold Stone Creamery",
    "wof:placetype":"venue"
},
  "geometry": {"coordinates":[-119.104304,35.385466],"type":"Point"}
}