{
  "type": "Feature",
  "properties": {
    "addr:full":"1531 57th Ave Oakland CA 94621",
    "addr:housenumber":"1531",
    "addr:postcode":"94621",
    "addr:street":"57Th Ave",
    "iso:country":"US",
    "sg:address":"1531 57th Ave",
    "sg:city":"Oakland",
    "sg:classifiers":[
        {
            "category":"Building & Trades",
            "subcategory":"Construction",
            "type":"Services"
        }
    ],
    "sg:phone":"+1 510 261 7500",
    "sg:postcode":"94621",
    "sg:province":"CA",
    "sg:tags":[
        "resurfacing",
        "laying",
        "refinishing",
        "floor"
    ],
    "wof:name":"Above Grade Wood Flooring",
    "wof:placetype":"venue"
},
  "geometry": {"coordinates":[-122.200113,37.767272],"type":"Point"}
}