{
  "type": "Feature",
  "properties": {
    "iso:country":"US",
    "sg:address":"973 Foothill Blvd",
    "sg:city":"Oakland",
    "sg:classifiers":[
        {
            "category":"Recreation",
            "type":"Entertainment"
        }
    ],
    "sg:phone":"+1 805 541 9882",
    "sg:postcode":"94606",
    "sg:province":"CA",
    "sg:tags":[
        "paint",
        "ball",
        "sport"
    ],
    "wof:name":"Breakout Paintball Supply",
    "wof:placetype":"venue"
},
  "geometry": {"coordinates":[-122.248435,37.793887],"type":"Point"}
}