{
  "type": "Feature",
  "properties": {
    "addr:full":"80 Liberty Ship Way Sausalito CA 94965",
    "addr:housenumber":"80",
    "addr:postcode":"94965",
    "addr:street":"Liberty Ship Way",
    "iso:country":"US",
    "sg:address":"80 Liberty Ship Way",
    "sg:city":"Sausalito",
    "sg:classifiers":[
        {
            "category":"Communications",
            "subcategory":"Radio Station",
            "type":"Services"
        },
        {
            "category":"Professional",
            "subcategory":"Art Services",
            "type":"Services"
        }
    ],
    "sg:phone":"+1 415 332 3400",
    "sg:postcode":"94965",
    "sg:province":"CA",
    "sg:tags":[
        "graphic",
        "medium",
        "broker",
        "designer"
    ],
    "wof:name":"Butler Shine Stern & Partners",
    "wof:placetype":"venue"
},
  "geometry": {"coordinates":[-122.493291,37.863199],"type":"Point"}
}