{
  "type": "Feature",
  "properties": {
    "addr:full":"5614 E Washington Blvd City Of Commerce CA 90040",
    "addr:housenumber":"5614",
    "addr:postcode":"90040",
    "addr:street":"E Washington Blvd",
    "iso:country":"US",
    "sg:address":"5614 E Washington Blvd",
    "sg:city":"City Of Commerce",
    "sg:classifiers":[
        {
            "category":"Manufacturing",
            "subcategory":"Tools & Machinery",
            "type":"Manufacturing & Wholesale Goods"
        }
    ],
    "sg:phone":"+1 323 726 9005",
    "sg:postcode":"90040",
    "sg:province":"CA",
    "sg:tags":[
        "machine",
        "shop"
    ],
    "wof:name":"J & J Machine & Engineering",
    "wof:placetype":"venue"
},
  "geometry": {"coordinates":[-118.156323,33.999076],"type":"Point"}
}