{
  "type": "Feature",
  "properties": {
    "addr:full":"11510 Woodside Ave Santee CA 92071",
    "addr:housenumber":"11510",
    "addr:postcode":"92071",
    "addr:street":"Woodside Ave",
    "iso:country":"US",
    "sg:address":"11510 Woodside Ave",
    "sg:city":"Santee",
    "sg:classifiers":[
        {
            "category":"Wholesale",
            "subcategory":"Construction Materials",
            "type":"Manufacturing & Wholesale Goods"
        }
    ],
    "sg:phone":"+1 619 449 3800",
    "sg:postcode":"92071",
    "sg:province":"CA",
    "wof:name":"Pacific Mobile Homes Inc",
    "wof:placetype":"venue"
},
  "geometry": {"coordinates":[-116.94860799999999,32.852831],"type":"Point"}
}