{
  "type": "Feature",
  "properties": {
    "addr:full":"4538 Blanca Dr Cypress CA 90630",
    "addr:housenumber":"4538",
    "addr:postcode":"90630",
    "addr:street":"Blanca Dr",
    "iso:country":"US",
    "sg:address":"4538 Blanca Dr",
    "sg:city":"Cypress",
    "sg:classifiers":[
        {
            "category":"Building & Trades",
            "subcategory":"Construction",
            "type":"Services"
        }
    ],
    "sg:phone":"+1 714 821 3756",
    "sg:postcode":"90630",
    "sg:province":"CA",
    "sg:tags":[
        "road",
        "contractor"
    ],
    "wof:name":"Crooks Truck & Equipment Rntl",
    "wof:placetype":"venue"
},
  "geometry": {"coordinates":[-118.05268599999999,33.828116],"type":"Point"}
}