{
  "type": "Feature",
  "properties": {
    "addr:full":"306 Willow Hill Ct Los Gatos CA 95032",
    "addr:housenumber":"306",
    "addr:postcode":"95032",
    "addr:street":"Willow Hill Ct",
    "iso:country":"US",
    "sg:address":"306 Willow Hill Ct",
    "sg:city":"Los Gatos",
    "sg:classifiers":[
        {
            "category":"Travel",
            "subcategory":"Travel Agent",
            "type":"Entertainment"
        }
    ],
    "sg:phone":"+1 408 374 9813",
    "sg:postcode":"95032",
    "sg:province":"CA",
    "sg:tags":[
        "agency"
    ],
    "wof:name":"Travel Planner",
    "wof:placetype":"venue"
},
  "geometry": {"coordinates":[-121.96333,37.255164],"type":"Point"}
}