{
  "type": "Feature",
  "properties": {
    "iso:country":"US",
    "sg:address":"334 Center St",
    "sg:city":"Healdsburg",
    "sg:classifiers":[
        {
            "category":"Home & Garden",
            "subcategory":"Building Materials",
            "type":"Retail Goods"
        }
    ],
    "sg:phone":"+1 707 433 2374",
    "sg:postcode":"95448",
    "sg:province":"CA",
    "sg:tags":[
        "paint"
    ],
    "wof:name":"Plaza Paint & Supply",
    "wof:placetype":"venue"
},
  "geometry": {"coordinates":[-122.869562,38.611395],"type":"Point"}
}