{
  "type": "Feature",
  "properties": {
    "iso:country":"US",
    "sg:address":"521 Front St",
    "sg:city":"Soledad",
    "sg:classifiers":[
        {
            "category":"Restaurant",
            "type":"Food & Drink"
        }
    ],
    "sg:phone":"+1 831 678 3828",
    "sg:postcode":"93960",
    "sg:province":"CA",
    "sg:tags":[
        "parlor",
        "ice",
        "cream"
    ],
    "wof:name":"Lolita's Ice Cream",
    "wof:placetype":"venue"
},
  "geometry": {"coordinates":[-121.329003,36.426837],"type":"Point"}
}