{
  "type": "Feature",
  "properties": {
    "addr:full":"42307 Osgood Rd Fremont CA 94539",
    "addr:housenumber":"42307",
    "addr:postcode":"94539",
    "addr:street":"Osgood Rd",
    "iso:country":"US",
    "sg:address":"42307 Osgood Rd",
    "sg:city":"Fremont",
    "sg:classifiers":[
        {
            "category":"Manufacturing",
            "subcategory":"Tools & Machinery",
            "type":"Manufacturing & Wholesale Goods"
        }
    ],
    "sg:phone":"+1 510 683 8600",
    "sg:postcode":"94539",
    "sg:province":"CA",
    "sg:tags":[
        "computer"
    ],
    "sg:website":"www.rtronics.com",
    "wof:name":"R Tronics",
    "wof:placetype":"venue"
},
  "geometry": {"coordinates":[-121.95328600000001,37.532592],"type":"Point"}
}