{
  "type": "Feature",
  "properties": {
    "addr:full":"490 Post Street San Francisco CA 94102",
    "addr:housenumber":"490",
    "addr:postcode":"94102",
    "addr:street":"Post Street",
    "iso:country":"US",
    "sg:address":"490 Post Street",
    "sg:city":"San Francisco",
    "sg:classifiers":[
        {
            "category":"Health Services",
            "subcategory":"Doctor",
            "type":"Services"
        },
        {
            "category":"Personal",
            "subcategory":"Hair Removal",
            "type":"Services"
        }
    ],
    "sg:phone":"+1 415 392 3333",
    "sg:postcode":"94102",
    "sg:province":"CA",
    "sg:tags":[
        "surgeon",
        "laser",
        "cosmetic",
        "dermatologist"
    ],
    "wof:name":"Center For Laser Hair Removal At Union Square",
    "wof:placetype":"venue"
},
  "geometry": {"coordinates":[-122.410004,37.788101],"type":"Point"}
}