{
  "type": "Feature",
  "properties": {
    "iso:country":"US",
    "sg:address":"348 E King Ave",
    "sg:city":"Tulare",
    "sg:classifiers":[
        {
            "category":"Home & Garden",
            "subcategory":"Household Appliances",
            "type":"Retail Goods"
        }
    ],
    "sg:phone":"+1 559 686 3729",
    "sg:postcode":"93274",
    "sg:province":"CA",
    "wof:name":"Gordon's Electric",
    "wof:placetype":"venue"
},
  "geometry": {"coordinates":[-119.34504099999999,36.209576],"type":"Point"}
}