{
  "type": "Feature",
  "properties": {
    "addr:full":"11040 Camarillo St North Hollywood CA 91602",
    "addr:housenumber":"11040",
    "addr:postcode":"91602",
    "addr:street":"Camarillo St",
    "iso:country":"US",
    "sg:address":"11040 Camarillo St",
    "sg:city":"North Hollywood",
    "sg:classifiers":[
        {
            "category":"Shopping",
            "subcategory":"Clothing, Apparel, & Fashions",
            "type":"Retail Goods"
        }
    ],
    "sg:phone":"+1 818 763 3900",
    "sg:postcode":"91602",
    "sg:province":"CA",
    "sg:tags":[
        "baby",
        "accessory"
    ],
    "sg:website":"www.mrbabyproofer.com",
    "wof:name":"Mr Baby Proofer",
    "wof:placetype":"venue"
},
  "geometry": {"coordinates":[-118.370683,34.157571],"type":"Point"}
}