{
  "type": "Feature",
  "properties": {
    "iso:country":"US",
    "sg:address":"2358 Alameda St",
    "sg:city":"Diablo",
    "sg:classifiers":[
        {
            "category":"Professional",
            "subcategory":"Management & Consulting",
            "type":"Services"
        }
    ],
    "sg:phone":"+1 925 743 9196",
    "sg:postcode":"94590",
    "sg:province":"CA",
    "sg:tags":[
        "fuel",
        "business"
    ],
    "wof:name":"Spencer Management Associates",
    "wof:placetype":"venue"
},
  "geometry": {"coordinates":[-122.247744,38.120364],"type":"Point"}
}