{
  "type": "Feature",
  "properties": {
    "addr:full":"10744 Rockville St Ste 101 Santee CA 92071",
    "addr:housenumber":"10744",
    "addr:postcode":"92071",
    "addr:street":"Rockville St Ste 101",
    "iso:country":"US",
    "sg:address":"10744 Rockville St Ste 101",
    "sg:city":"Santee",
    "sg:classifiers":[
        {
            "category":"Building & Trades",
            "subcategory":"Electrical",
            "type":"Services"
        }
    ],
    "sg:phone":"+1 619 749 4058",
    "sg:postcode":"92071",
    "sg:province":"CA",
    "sg:tags":[
        "electrician"
    ],
    "sg:website":"http://www.freedomelectricco.com",
    "wof:name":"Freedom Electric Co.",
    "wof:placetype":"venue"
},
  "geometry": {"coordinates":[-116.964348,32.83761],"type":"Point"}
}