{
  "type": "Feature",
  "properties": {
    "addr:full":"5646 N Palm Ave Fresno CA 93704",
    "addr:housenumber":"5646",
    "addr:postcode":"93704",
    "addr:street":"N Palm Ave",
    "iso:country":"US",
    "sg:address":"5646 N Palm Ave",
    "sg:city":"Fresno",
    "sg:classifiers":[
        {
            "category":"Health Services",
            "subcategory":"Doctor",
            "type":"Services"
        },
        {
            "category":"Health Services",
            "subcategory":"Dentist",
            "type":"Services"
        }
    ],
    "sg:phone":"+1 559 449 1275",
    "sg:postcode":"93704",
    "sg:province":"CA",
    "sg:tags":[
        "dentists-oral",
        "physician",
        "maxillofacial",
        "surgeons",
        "surgery",
        "oral"
    ],
    "wof:name":"Gorman Jeffrey S DMD",
    "wof:placetype":"venue"
},
  "geometry": {"coordinates":[-119.808258,36.82078],"type":"Point"}
}