{
  "type": "Feature",
  "properties": {
    "iso:country":"US",
    "sg:address":"411 W 7th St",
    "sg:city":"Los Angeles",
    "sg:classifiers":[
        {
            "category":"Shopping",
            "subcategory":"Jewelry",
            "type":"Retail Goods"
        }
    ],
    "sg:phone":"+1 213 239 0064",
    "sg:postcode":"90014",
    "sg:province":"CA",
    "sg:tags":[
        "diamond",
        "setter"
    ],
    "wof:name":"AGA Jewelry",
    "wof:placetype":"venue"
},
  "geometry": {"coordinates":[-118.25473700000001,34.046156],"type":"Point"}
}