{
  "type": "Feature",
  "properties": {
    "addr:full":"3101 I St Sacramento CA 95816",
    "addr:housenumber":"3101",
    "addr:postcode":"95816",
    "addr:street":"I St",
    "iso:country":"US",
    "sg:address":"3101 I St",
    "sg:city":"Sacramento",
    "sg:classifiers":[
        {
            "category":"Social Services",
            "type":"Services"
        }
    ],
    "sg:phone":"+1 916 441 4495",
    "sg:postcode":"95816",
    "sg:province":"CA",
    "sg:tags":[
        "counselor",
        "marriage",
        "family"
    ],
    "wof:name":"Maryanne Lynch",
    "wof:placetype":"venue"
},
  "geometry": {"coordinates":[-121.46189,38.573578],"type":"Point"}
}