{
  "type": "Feature",
  "properties": {
    "addr:full":"2625 Fair Oaks Blvd Sacramento CA 95864",
    "addr:housenumber":"2625",
    "addr:postcode":"95864",
    "addr:street":"Fair Oaks Blvd",
    "iso:country":"US",
    "sg:address":"2625 Fair Oaks Blvd",
    "sg:city":"Sacramento",
    "sg:classifiers":[
        {
            "category":"Real Estate",
            "subcategory":"Real Estate Operator",
            "type":"Services"
        }
    ],
    "sg:phone":"+1 916 485 6800",
    "sg:postcode":"95864",
    "sg:province":"CA",
    "sg:tags":[
        "property",
        "lessor"
    ],
    "wof:name":"Village Commons Investors",
    "wof:placetype":"venue"
},
  "geometry": {"coordinates":[-121.400215,38.574298],"type":"Point"}
}