{
  "type": "Feature",
  "properties": {
    "addr:full":"2470 Waterloo Rd Stockton CA 95205",
    "addr:housenumber":"2470",
    "addr:postcode":"95205",
    "addr:street":"Waterloo Rd",
    "iso:country":"US",
    "sg:address":"2470 Waterloo Rd",
    "sg:city":"Stockton",
    "sg:classifiers":[
        {
            "category":"Autos & Motor Vehicles",
            "subcategory":"Automobile Sales",
            "type":"Retail Goods"
        }
    ],
    "sg:phone":"+1 209 466 4684",
    "sg:postcode":"95205",
    "sg:province":"CA",
    "sg:tags":[
        "car",
        "dealer"
    ],
    "wof:name":"S & S Auto Sales",
    "wof:placetype":"venue"
},
  "geometry": {"coordinates":[-121.262753,37.976174],"type":"Point"}
}