{
  "type": "Feature",
  "properties": {
    "addr:full":"181 2nd Ave San Mateo CA 94401",
    "addr:housenumber":"181",
    "addr:postcode":"94401",
    "addr:street":"2Nd Ave",
    "iso:country":"US",
    "sg:address":"181 2nd Ave",
    "sg:city":"San Mateo",
    "sg:classifiers":[
        {
            "category":"Banks & Credit Unions",
            "subcategory":"Investment Brokerage",
            "type":"Services"
        }
    ],
    "sg:phone":"+1 650 347 6112",
    "sg:postcode":"94401",
    "sg:province":"CA",
    "sg:tags":[
        "stock",
        "bond"
    ],
    "wof:name":"Daniel Spradling",
    "wof:placetype":"venue"
},
  "geometry": {"coordinates":[-122.324747,37.565326],"type":"Point"}
}