{
  "type": "Feature",
  "properties": {
    "addr:full":"647 Haight Ave Alameda CA 94501",
    "addr:housenumber":"647",
    "addr:postcode":"94501",
    "addr:street":"Haight Ave",
    "iso:country":"US",
    "sg:address":"647 Haight Ave",
    "sg:city":"Alameda",
    "sg:classifiers":[
        {
            "category":"Shopping",
            "subcategory":"Music",
            "type":"Retail Goods"
        }
    ],
    "sg:phone":"+1 510 865 2127",
    "sg:postcode":"94501",
    "sg:province":"CA",
    "sg:tags":[
        "video",
        "disc",
        "tape",
        "cassette"
    ],
    "wof:name":"Amihan Video Movie Sale & Rntl",
    "wof:placetype":"venue"
},
  "geometry": {"coordinates":[-122.27788700000001,37.77433],"type":"Point"}
}