{
  "type": "Feature",
  "properties": {
    "addr:full":"259 S Euclid Ave Pasadena CA 91101",
    "addr:housenumber":"259",
    "addr:postcode":"91101",
    "addr:street":"S Euclid Ave",
    "iso:country":"US",
    "sg:address":"259 S Euclid Ave",
    "sg:city":"Pasadena",
    "sg:classifiers":[
        {
            "category":"Health Services",
            "subcategory":"Doctor",
            "type":"Services"
        },
        {
            "category":"Health Services",
            "subcategory":"Clinic",
            "type":"Services"
        }
    ],
    "sg:phone":"+1 626 395 7677",
    "sg:postcode":"91101",
    "sg:province":"CA",
    "sg:tags":[
        "counseling",
        "mental",
        "psychiatrist"
    ],
    "wof:name":"Carder Scott L MD PHD",
    "wof:placetype":"venue"
},
  "geometry": {"coordinates":[-118.14299800000001,34.140999],"type":"Point"}
}