{
  "type": "Feature",
  "properties": {
    "addr:full":"4559 Highway 78 Julian CA 92036",
    "addr:housenumber":"4559",
    "addr:postcode":"92036",
    "addr:street":"Highway 78",
    "iso:country":"US",
    "sg:address":"4559 Highway 78",
    "sg:city":"Julian",
    "sg:classifiers":[
        {
            "category":"Home & Garden",
            "subcategory":"Home Furnishings",
            "type":"Retail Goods"
        },
        {
            "category":"Professional",
            "subcategory":"Art Services",
            "type":"Services"
        },
        {
            "category":"Home & Garden",
            "subcategory":"Carpets & Floor Coverings",
            "type":"Retail Goods"
        }
    ],
    "sg:phone":"+1 760 765 1605",
    "sg:postcode":"92036",
    "sg:province":"CA",
    "sg:tags":[
        "draperies",
        "designer",
        "rug",
        "window",
        "treatment",
        "interior",
        "curtain",
        "decorator",
        "drapery",
        "trimming"
    ],
    "sg:website":"http://www.julianinteriors.com",
    "wof:name":"Julian Interiors",
    "wof:placetype":"venue"
},
  "geometry": {"coordinates":[-116.649271,33.100398],"type":"Point"}
}