{
  "type": "Feature",
  "properties": {
    "iso:country":"US",
    "sg:address":"308 E F St",
    "sg:city":"Oakdale",
    "sg:classifiers":[
        {
            "category":"Food & Beverages",
            "subcategory":"Specialty",
            "type":"Retail Goods"
        }
    ],
    "sg:phone":"+1 209 847 1849",
    "sg:postcode":"95361",
    "sg:province":"CA",
    "sg:tags":[
        "health",
        "diet"
    ],
    "wof:name":"General Nutrition Ctr",
    "wof:placetype":"venue"
},
  "geometry": {"coordinates":[-120.84712,37.766675],"type":"Point"}
}