{
  "type": "Feature",
  "properties": {
    "iso:country":"US",
    "sg:address":"5018 Michaelangelo Ct",
    "sg:city":"Fairfield",
    "sg:classifiers":[
        {
            "category":"Building & Trades",
            "subcategory":"Plumbing",
            "type":"Services"
        }
    ],
    "sg:phone":"+1 707 864 1290",
    "sg:postcode":"94534",
    "sg:province":"CA",
    "sg:tags":[
        "conditioning",
        "air",
        "system",
        "contractor"
    ],
    "wof:name":"Indoor Comfort Heating & AC",
    "wof:placetype":"venue"
},
  "geometry": {"coordinates":[-122.143958,38.220535],"type":"Point"}
}