{
  "type": "Feature",
  "properties": {
    "iso:country":"US",
    "sg:address":"2503 W 12th St",
    "sg:city":"Santa Ana",
    "sg:classifiers":[
        {
            "category":"Building & Trades",
            "subcategory":"Construction",
            "type":"Services"
        }
    ],
    "sg:phone":"+1 714 541 0245",
    "sg:postcode":"92703",
    "sg:province":"CA",
    "sg:tags":[
        "hanging",
        "contractor"
    ],
    "wof:name":"Sun Painting Co",
    "wof:placetype":"venue"
},
  "geometry": {"coordinates":[-117.903176,33.754774],"type":"Point"}
}