{
  "type": "Feature",
  "properties": {
    "iso:country":"US",
    "sg:address":"730 E Gilbert St",
    "sg:city":"San Bernardino",
    "sg:classifiers":[
        {
            "category":"Government",
            "subcategory":"Court House",
            "type":"Public Place"
        }
    ],
    "sg:phone":"+1 909 387 7525",
    "sg:postcode":"92404",
    "sg:province":"CA",
    "sg:tags":[
        "legal"
    ],
    "wof:name":"Public Defender Office of The",
    "wof:placetype":"venue"
},
  "geometry": {"coordinates":[-117.272694,34.126812],"type":"Point"}
}