{
  "type": "Feature",
  "properties": {
    "iso:country":"US",
    "sg:address":"27405 Bouquet Canyon Rd",
    "sg:city":"Santa Clarita",
    "sg:classifiers":[
        {
            "category":"Organizations",
            "subcategory":"Religious Organization",
            "type":"Services"
        }
    ],
    "sg:phone":"+1 661 297 7061",
    "sg:postcode":"91350",
    "sg:province":"CA",
    "wof:name":"Corporation of President of Th",
    "wof:placetype":"venue"
},
  "geometry": {"coordinates":[-118.51376399999999,34.441207],"type":"Point"}
}