{
  "type": "Feature",
  "properties": {
    "addr:full":"13841 Foothill Blvd Sylmar CA 91342",
    "addr:housenumber":"13841",
    "addr:postcode":"91342",
    "addr:street":"Foothill Blvd",
    "iso:country":"US",
    "sg:address":"13841 Foothill Blvd",
    "sg:city":"Sylmar",
    "sg:classifiers":[
        {
            "category":"Retail",
            "subcategory":"Repair Shop",
            "type":"Services"
        }
    ],
    "sg:phone":"+1 818 367 8269",
    "sg:postcode":"91342",
    "sg:province":"CA",
    "sg:tags":[
        "television",
        "radio"
    ],
    "wof:name":"Sylmar TV Sales & Svc",
    "wof:placetype":"venue"
},
  "geometry": {"coordinates":[-118.436424,34.312148],"type":"Point"}
}