{
  "type": "Feature",
  "properties": {
    "addr:full":"308 Trinity Ave Chowchilla CA 93610",
    "addr:housenumber":"308",
    "addr:postcode":"93610",
    "addr:street":"Trinity Ave",
    "iso:country":"US",
    "sg:address":"308 Trinity Ave",
    "sg:city":"Chowchilla",
    "sg:classifiers":[
        {
            "category":"Home & Garden",
            "subcategory":"Hardware",
            "type":"Retail Goods"
        }
    ],
    "sg:phone":"+1 559 665 2750",
    "sg:postcode":"93610",
    "sg:province":"CA",
    "wof:name":"Farmers Hardware & Supply",
    "wof:placetype":"venue"
},
  "geometry": {"coordinates":[-120.260099,37.121356],"type":"Point"}
}