{
  "type": "Feature",
  "properties": {
    "iso:country":"US",
    "sg:address":"850 Capitolio Way",
    "sg:city":"San Luis Obispo",
    "sg:classifiers":[
        {
            "category":"Manufacturing",
            "subcategory":"Tools & Machinery",
            "type":"Manufacturing & Wholesale Goods"
        }
    ],
    "sg:phone":"+1 805 549 9724",
    "sg:postcode":"93401",
    "sg:province":"CA",
    "sg:tags":[
        "water"
    ],
    "sg:website":"www.cwtozone.com",
    "wof:name":"Clearwater",
    "wof:placetype":"venue"
},
  "geometry": {"coordinates":[-120.643542,35.257701],"type":"Point"}
}