{
  "type": "Feature",
  "properties": {
    "addr:full":"975 Lurline Dr Foster City CA 94404",
    "addr:housenumber":"975",
    "addr:postcode":"94404",
    "addr:street":"Lurline Dr",
    "iso:country":"US",
    "sg:address":"975 Lurline Dr",
    "sg:city":"Foster City",
    "sg:classifiers":[
        {
            "category":"Wholesale",
            "subcategory":"Non-durable Goods",
            "type":"Manufacturing & Wholesale Goods"
        },
        {
            "category":"Wholesale",
            "subcategory":"Durable Goods & Equipment",
            "type":"Manufacturing & Wholesale Goods"
        }
    ],
    "sg:phone":"+1 650 349 9353",
    "sg:postcode":"94404",
    "sg:province":"CA",
    "sg:tags":[
        "importer"
    ],
    "wof:name":"Tri-Star Investment Realty Co",
    "wof:placetype":"venue"
},
  "geometry": {"coordinates":[-122.26026,37.557022],"type":"Point"}
}