{
  "type": "Feature",
  "properties": {
    "iso:country":"US",
    "sg:address":"19 Rausch St Ste C",
    "sg:city":"San Francisco",
    "sg:classifiers":[
        {
            "category":"Professional",
            "type":"Services"
        }
    ],
    "sg:postcode":"94103",
    "sg:province":"CA",
    "sg:website":"www.ecolect.net",
    "wof:name":"Ecolect",
    "wof:placetype":"venue"
},
  "geometry": {"coordinates":[-122.410236,37.776866],"type":"Point"}
}