{
  "type": "Feature",
  "properties": {
    "iso:country":"US",
    "sg:address":"7005 Fellers Ln",
    "sg:city":"Sebastopol",
    "sg:classifiers":[
        {
            "category":"Real Estate",
            "subcategory":"Real Estate Operator",
            "type":"Services"
        }
    ],
    "sg:phone":"+1 707 823 0730",
    "sg:postcode":"95472",
    "sg:province":"CA",
    "sg:tags":[
        "apartment"
    ],
    "wof:name":"Redwood Grove Apartments",
    "wof:placetype":"venue"
},
  "geometry": {"coordinates":[-122.81794499999999,38.392827],"type":"Point"}
}