{
  "type": "Feature",
  "properties": {
    "addr:full":"2651 Irvine Ave Ste I Costa Mesa CA 92627",
    "addr:housenumber":"2651",
    "addr:postcode":"92627",
    "addr:street":"Irvine Ave Ste I",
    "iso:country":"US",
    "sg:address":"2651 Irvine Ave Ste I",
    "sg:city":"Costa Mesa",
    "sg:classifiers":[
        {
            "category":"Food & Beverages",
            "subcategory":"Liquor & Beverages",
            "type":"Retail Goods"
        }
    ],
    "sg:phone":"+1 949 642 4774",
    "sg:postcode":"92627",
    "sg:province":"CA",
    "sg:tags":[
        "beer",
        "spirit",
        "wine"
    ],
    "wof:name":"Back Bay Liquor",
    "wof:placetype":"venue"
},
  "geometry": {"coordinates":[-117.88546700000001,33.658285],"type":"Point"}
}