{
  "type": "Feature",
  "properties": {
    "iso:country":"US",
    "sg:address":"18408 S New Hampshire Ave",
    "sg:city":"Gardena",
    "sg:classifiers":[
        {
            "category":"Freight",
            "type":"Transportation"
        }
    ],
    "sg:phone":"+1 310 327 7308",
    "sg:postcode":"90248",
    "sg:province":"CA",
    "sg:tags":[
        "operator",
        "local",
        "trucking"
    ],
    "wof:name":"Elb Trucking",
    "wof:placetype":"venue"
},
  "geometry": {"coordinates":[-118.291943,33.862781],"type":"Point"}
}