{
  "type": "Feature",
  "properties": {
    "iso:country":"US",
    "sg:address":"6557 E Pso Diego",
    "sg:city":"Anaheim",
    "sg:classifiers":[
        {
            "category":"Professional",
            "subcategory":"Business Services",
            "type":"Services"
        }
    ],
    "sg:phone":"+1 714 488 4801",
    "sg:postcode":"92807",
    "sg:province":"CA",
    "sg:tags":[
        "broker"
    ],
    "wof:name":"Eye Magic",
    "wof:placetype":"venue"
},
  "geometry": {"coordinates":[-117.762083,33.833964],"type":"Point"}
}