{
  "type": "Feature",
  "properties": {
    "iso:country":"US",
    "sg:address":"5757 Skyway Rd",
    "sg:city":"Paradise",
    "sg:classifiers":[
        {
            "category":"Shopping",
            "subcategory":"Used Merchandise",
            "type":"Retail Goods"
        }
    ],
    "sg:phone":"+1 530 877 9600",
    "sg:postcode":"95969",
    "sg:province":"CA",
    "wof:name":"Antique Discovery Center",
    "wof:placetype":"venue"
},
  "geometry": {"coordinates":[-121.631055,39.751312],"type":"Point"}
}