{
  "type": "Feature",
  "properties": {
    "addr:full":"4025 Camino Del Rio S San Diego CA 92108",
    "addr:housenumber":"4025",
    "addr:postcode":"92108",
    "addr:street":"Camino Del Rio S",
    "iso:country":"US",
    "sg:address":"4025 Camino Del Rio S",
    "sg:city":"San Diego",
    "sg:classifiers":[
        {
            "category":"Professional",
            "subcategory":"Lawyer & Legal Services",
            "type":"Services"
        }
    ],
    "sg:phone":"+1 619 232 2020",
    "sg:postcode":"92108",
    "sg:province":"CA",
    "wof:name":"Bloomfield Krl Atty Hlbrk & Blo Mfld Attrnys At Lw",
    "wof:placetype":"venue"
},
  "geometry": {"coordinates":[-117.10700199999999,32.778],"type":"Point"}
}