{
  "type": "Feature",
  "properties": {
    "addr:full":"5903 Careybrook Dr Agoura Hills CA 91301",
    "addr:housenumber":"5903",
    "addr:postcode":"91301",
    "addr:street":"Careybrook Dr",
    "iso:country":"US",
    "sg:address":"5903 Careybrook Dr",
    "sg:city":"Agoura Hills",
    "sg:classifiers":[
        {
            "category":"Professional",
            "type":"Services"
        }
    ],
    "sg:phone":"+1 818 597 4847",
    "sg:postcode":"91301",
    "sg:province":"CA",
    "wof:name":"F & L Hybrchts Tr Dted Novembe",
    "wof:placetype":"venue"
},
  "geometry": {"coordinates":[-118.765114,34.159518],"type":"Point"}
}