{
  "type": "Feature",
  "properties": {
    "iso:country":"US",
    "sg:address":"740 E Wilson Ave",
    "sg:city":"Glendale",
    "sg:classifiers":[
        {
            "category":"Professional",
            "subcategory":"Business Services",
            "type":"Services"
        }
    ],
    "sg:phone":"+1 818 265 9800",
    "sg:postcode":"91206",
    "sg:province":"CA",
    "wof:name":"Heno Fagerian",
    "wof:placetype":"venue"
},
  "geometry": {"coordinates":[-118.24569700000001,34.148055],"type":"Point"}
}