{
  "type": "Feature",
  "properties": {
    "addr:full":"16 Coleman Pl Menlo Park CA 94025",
    "addr:housenumber":"16",
    "addr:postcode":"94025",
    "addr:street":"Coleman Pl",
    "iso:country":"US",
    "sg:address":"16 Coleman Pl",
    "sg:city":"Menlo Park",
    "sg:classifiers":[
        {
            "category":"Social Services",
            "subcategory":"Adult Care",
            "type":"Services"
        }
    ],
    "sg:phone":"+1 650 322 2022",
    "sg:postcode":"94025",
    "sg:province":"CA",
    "sg:tags":[
        "home",
        "residential"
    ],
    "wof:name":"Canyon House & Crescent Villa",
    "wof:placetype":"venue"
},
  "geometry": {"coordinates":[-122.161176,37.462351],"type":"Point"}
}