{
  "type": "Feature",
  "properties": {
    "iso:country":"US",
    "sg:address":"15 E 12th St",
    "sg:city":"Marysville",
    "sg:classifiers":[
        {
            "category":"Building & Trades",
            "subcategory":"Construction",
            "type":"Services"
        }
    ],
    "sg:phone":"+1 530 742 8993",
    "sg:postcode":"95901",
    "sg:province":"CA",
    "sg:tags":[
        "contractor"
    ],
    "wof:name":"Larjer Inc",
    "wof:placetype":"venue"
},
  "geometry": {"coordinates":[-121.582673,39.148867],"type":"Point"}
}