{
  "type": "Feature",
  "properties": {
    "iso:country":"US",
    "sg:address":"4331 W 147th St",
    "sg:city":"Lawndale",
    "sg:classifiers":[
        {
            "category":"Organizations",
            "subcategory":"Religious Organization",
            "type":"Services"
        }
    ],
    "sg:phone":"+1 310 676 2598",
    "sg:postcode":"90260",
    "sg:province":"CA",
    "wof:name":"Safari Missions International",
    "wof:placetype":"venue"
},
  "geometry": {"coordinates":[-118.350946,33.898278],"type":"Point"}
}