{
  "type": "Feature",
  "properties": {
    "iso:country":"US",
    "sg:address":"770 Pso Camarillo",
    "sg:city":"Camarillo",
    "sg:classifiers":[
        {
            "category":"Restaurant",
            "type":"Food & Drink"
        }
    ],
    "sg:phone":"+1 805 484 1116",
    "sg:postcode":"93010",
    "sg:province":"CA",
    "sg:tags":[
        "sandwich"
    ],
    "wof:name":"Cinnamon's Sandwich Delight",
    "wof:placetype":"venue"
},
  "geometry": {"coordinates":[-119.095938,34.22056],"type":"Point"}
}