{
  "type": "Feature",
  "properties": {
    "iso:country":"US",
    "sg:address":"1800 Leslie St",
    "sg:city":"San Mateo",
    "sg:classifiers":[
        {
            "category":"Building & Trades",
            "subcategory":"Landscaping Services",
            "type":"Services"
        }
    ],
    "sg:phone":"+1 650 571 0169",
    "sg:postcode":"94402",
    "sg:province":"CA",
    "sg:tags":[
        "tree"
    ],
    "wof:name":"Bay Area Tree Co",
    "wof:placetype":"venue"
},
  "geometry": {"coordinates":[-122.31039199999999,37.553198],"type":"Point"}
}