{
  "type": "Feature",
  "properties": {
    "addr:full":"2985 E Hillcrest Dr Westlake Village CA 91362",
    "addr:housenumber":"2985",
    "addr:postcode":"91362",
    "addr:street":"E Hillcrest Dr",
    "iso:country":"US",
    "sg:address":"2985 E Hillcrest Dr",
    "sg:city":"Westlake Village",
    "sg:classifiers":[
        {
            "category":"Professional",
            "subcategory":"Secretarial Services",
            "type":"Services"
        }
    ],
    "sg:phone":"+1 805 495 8919",
    "sg:postcode":"91362",
    "sg:province":"CA",
    "sg:tags":[
        "convention",
        "court",
        "reporter"
    ],
    "wof:name":"Bob Diehl & Assoc",
    "wof:placetype":"venue"
},
  "geometry": {"coordinates":[-118.83403199999999,34.172843],"type":"Point"}
}