{
  "type": "Feature",
  "properties": {
    "addr:full":"101 Howard St., San Francisco CA 94105",
    "addr:housenumber":"101",
    "addr:postcode":"94105",
    "addr:street":"Howard St.",
    "iso:country":"US",
    "sg:address":"101 Howard St.,",
    "sg:city":"San Francisco",
    "sg:classifiers":[
        {
            "category":"Landmark",
            "subcategory":"Historic",
            "type":"Public Place"
        }
    ],
    "sg:postcode":"94105",
    "sg:province":"CA",
    "sg:tags":[
        "building",
        "historical"
    ],
    "wof:name":"The Folger Coffee Company Building",
    "wof:placetype":"venue"
},
  "geometry": {"coordinates":[-122.39260899999999,37.7911],"type":"Point"}
}