{
  "type": "Feature",
  "properties": {
    "iso:country":"US",
    "sg:address":"7064 W Sunset Blvd Ste B",
    "sg:city":"Los Angeles",
    "sg:classifiers":[
        {
            "category":"Personal",
            "subcategory":"Beauty Salon",
            "type":"Services"
        },
        {
            "category":"Personal",
            "subcategory":"Barber",
            "type":"Services"
        }
    ],
    "sg:phone":"+1 323 463 8023",
    "sg:postcode":"90028",
    "sg:province":"CA",
    "sg:tags":[
        "hair"
    ],
    "sg:website":"www.supercuts.com",
    "wof:name":"Supercuts",
    "wof:placetype":"venue"
},
  "geometry": {"coordinates":[-118.343529,34.097969],"type":"Point"}
}