{
  "type": "Feature",
  "properties": {
    "iso:country":"US",
    "sg:address":"720 Sutter Ave",
    "sg:city":"West Sacramento",
    "sg:classifiers":[
        {
            "category":"Retail",
            "subcategory":"Auto Rental",
            "type":"Services"
        }
    ],
    "sg:phone":"+1 916 372 0188",
    "sg:postcode":"95691",
    "sg:province":"CA",
    "sg:tags":[
        "renting",
        "automobile"
    ],
    "wof:name":"Budget Rent A Car",
    "wof:placetype":"venue"
},
  "geometry": {"coordinates":[-121.554787,38.580661],"type":"Point"}
}