{
  "type": "Feature",
  "properties": {
    "iso:country":"US",
    "sg:address":"1642 Las Trampas Rd",
    "sg:city":"Alamo",
    "sg:classifiers":[
        {
            "category":"Professional",
            "subcategory":"Engineering",
            "type":"Services"
        }
    ],
    "sg:phone":"+1 925 831 6118",
    "sg:postcode":"94507",
    "sg:province":"CA",
    "sg:tags":[
        "engineer",
        "mechanical"
    ],
    "wof:name":"Jamieson, J W",
    "wof:placetype":"venue"
},
  "geometry": {"coordinates":[-122.037712,37.843589],"type":"Point"}
}