{
  "type": "Feature",
  "properties": {
    "addr:full":"15616 E Newton St Hacienda Heights CA 91745",
    "addr:housenumber":"15616",
    "addr:postcode":"91745",
    "addr:street":"E Newton St",
    "iso:country":"US",
    "sg:address":"15616 E Newton St",
    "sg:city":"Hacienda Heights",
    "sg:classifiers":[
        {
            "category":"Education",
            "subcategory":"School",
            "type":"Public Place"
        }
    ],
    "sg:phone":"+1 626 933 1330",
    "sg:postcode":"91745",
    "sg:province":"CA",
    "wof:name":"Newton Middle School",
    "wof:placetype":"venue"
},
  "geometry": {"coordinates":[-117.97378,33.997713],"type":"Point"}
}