{
  "type": "Feature",
  "properties": {
    "addr:full":"1204 Freedom Blvd Watsonville CA 95076",
    "addr:housenumber":"1204",
    "addr:postcode":"95076",
    "addr:street":"Freedom Blvd",
    "iso:country":"US",
    "sg:address":"1204 Freedom Blvd",
    "sg:city":"Watsonville",
    "sg:classifiers":[
        {
            "category":"Retail",
            "subcategory":"Repair Shop",
            "type":"Services"
        }
    ],
    "sg:phone":"+1 831 728 9610",
    "sg:postcode":"95076",
    "sg:province":"CA",
    "sg:tags":[
        "refinishing",
        "furniture"
    ],
    "wof:name":"Friday's Furniture",
    "wof:placetype":"venue"
},
  "geometry": {"coordinates":[-121.762249,36.923953],"type":"Point"}
}