{
  "type": "Feature",
  "properties": {
    "iso:country":"US",
    "sg:address":"655 E Hawkeye Ave Ste 2",
    "sg:city":"Turlock",
    "sg:classifiers":[
        {
            "category":"Health Services",
            "subcategory":"Clinic",
            "type":"Services"
        }
    ],
    "sg:phone":"+1 209 632 1180",
    "sg:postcode":"95380",
    "sg:province":"CA",
    "sg:tags":[
        "blood",
        "bank"
    ],
    "wof:name":"Delta Blood Bank",
    "wof:placetype":"venue"
},
  "geometry": {"coordinates":[-120.84101099999999,37.50732],"type":"Point"}
}