{
  "type": "Feature",
  "properties": {
    "addr:full":"11335 Sunrise Gold Cir Rancho Cordova CA 95742",
    "addr:housenumber":"11335",
    "addr:postcode":"95742",
    "addr:street":"Sunrise Gold Cir",
    "iso:country":"US",
    "sg:address":"11335 Sunrise Gold Cir",
    "sg:city":"Rancho Cordova",
    "sg:classifiers":[
        {
            "category":"Building & Trades",
            "subcategory":"Construction",
            "type":"Services"
        }
    ],
    "sg:phone":"+1 916 919 4786",
    "sg:postcode":"95742",
    "sg:province":"CA",
    "sg:tags":[
        "windows"
    ],
    "wof:name":"Window Co",
    "wof:placetype":"venue"
},
  "geometry": {"coordinates":[-121.26445200000001,38.599897],"type":"Point"}
}