{
  "type": "Feature",
  "properties": {
    "addr:full":"290 Cadillac Dr Sacramento CA 95825",
    "addr:housenumber":"290",
    "addr:postcode":"95825",
    "addr:street":"Cadillac Dr",
    "iso:country":"US",
    "sg:address":"290 Cadillac Dr",
    "sg:city":"Sacramento",
    "sg:classifiers":[
        {
            "category":"Professional",
            "type":"Services"
        }
    ],
    "sg:phone":"+1 916 929 9601",
    "sg:postcode":"95825",
    "sg:province":"CA",
    "wof:name":"Wendys",
    "wof:placetype":"venue"
},
  "geometry": {"coordinates":[-121.418666,38.574388],"type":"Point"}
}