{
  "type": "Feature",
  "properties": {
    "iso:country":"US",
    "sg:address":"9 Mosaic",
    "sg:city":"Irvine",
    "sg:classifiers":[
        {
            "category":"Professional",
            "subcategory":"Research",
            "type":"Services"
        }
    ],
    "sg:phone":"+1 949 586 1885",
    "sg:postcode":"92656",
    "sg:province":"CA",
    "sg:tags":[
        "laboratory"
    ],
    "wof:name":"Air Science Technologies",
    "wof:placetype":"venue"
},
  "geometry": {"coordinates":[-117.73608900000001,33.574475],"type":"Point"}
}