{
  "type": "Feature",
  "properties": {
    "addr:full":"555 N la Patera Ln Goleta CA 93117",
    "addr:housenumber":"555",
    "addr:postcode":"93117",
    "addr:street":"N La Patera Ln",
    "iso:country":"US",
    "sg:address":"555 N la Patera Ln",
    "sg:city":"Goleta",
    "sg:classifiers":[
        {
            "category":"Education",
            "subcategory":"School",
            "type":"Public Place"
        }
    ],
    "sg:phone":"+1 805 681 1280",
    "sg:postcode":"93117",
    "sg:province":"CA",
    "sg:tags":[
        "elementary"
    ],
    "wof:name":"La Patera Elementary School",
    "wof:placetype":"venue"
},
  "geometry": {"coordinates":[-119.846493,34.44731],"type":"Point"}
}