{
  "type": "Feature",
  "properties": {
    "addr:full":"1531 W Olive Ave Porterville CA 93257",
    "addr:housenumber":"1531",
    "addr:postcode":"93257",
    "addr:street":"W Olive Ave",
    "iso:country":"US",
    "sg:address":"1531 W Olive Ave",
    "sg:city":"Porterville",
    "sg:classifiers":[
        {
            "category":"Shopping",
            "subcategory":"Music",
            "type":"Retail Goods"
        }
    ],
    "sg:phone":"+1 559 781 0126",
    "sg:postcode":"93257",
    "sg:province":"CA",
    "sg:tags":[
        "video",
        "disc",
        "tape",
        "cassette"
    ],
    "wof:name":"Sawana Adult Store",
    "wof:placetype":"venue"
},
  "geometry": {"coordinates":[-119.05107700000001,36.065772],"type":"Point"}
}