{
  "type": "Feature",
  "properties": {
    "addr:full":"2727 Stingle Ave Rosemead CA 91770",
    "addr:housenumber":"2727",
    "addr:postcode":"91770",
    "addr:street":"Stingle Ave",
    "iso:country":"US",
    "sg:address":"2727 Stingle Ave",
    "sg:city":"Rosemead",
    "sg:classifiers":[
        {
            "category":"Retail",
            "subcategory":"Auto Repair",
            "type":"Services"
        }
    ],
    "sg:phone":"+1 626 288 4057",
    "sg:postcode":"91770",
    "sg:province":"CA",
    "sg:tags":[
        "repairing",
        "automobile"
    ],
    "wof:name":"Flysky Ca Inc",
    "wof:placetype":"venue"
},
  "geometry": {"coordinates":[-118.074935,34.059508],"type":"Point"}
}