{
  "type": "Feature",
  "properties": {
    "iso:country":"US",
    "sg:address":"1440 Spruce St",
    "sg:city":"Redding",
    "sg:classifiers":[
        {
            "category":"Freight",
            "type":"Transportation"
        }
    ],
    "sg:phone":"+1 530 242 8500",
    "sg:postcode":"96001",
    "sg:province":"CA",
    "sg:tags":[
        "special"
    ],
    "wof:name":"Archive Record Systems",
    "wof:placetype":"venue"
},
  "geometry": {"coordinates":[-122.389805,40.569681],"type":"Point"}
}