{
  "type": "Feature",
  "properties": {
    "iso:country":"US",
    "sg:address":"707 Stockton St",
    "sg:city":"San Francisco",
    "sg:classifiers":[
        {
            "category":"Professional",
            "subcategory":"Business Services",
            "type":"Services"
        },
        {
            "category":"Restaurant",
            "type":"Food & Drink"
        }
    ],
    "sg:phone":"+1 415 398 2293",
    "sg:postcode":"94108",
    "sg:province":"CA",
    "sg:tags":[
        "translator",
        "interpreter",
        "eating"
    ],
    "wof:name":"Japanese Translation Cnsltnt",
    "wof:placetype":"venue"
},
  "geometry": {"coordinates":[-122.40768300000001,37.792673],"type":"Point"}
}