{
  "type": "Feature",
  "properties": {
    "iso:country":"US",
    "sg:address":"17047 Devonshire St",
    "sg:city":"Northridge",
    "sg:classifiers":[
        {
            "category":"Restaurant",
            "type":"Food & Drink"
        }
    ],
    "sg:phone":"+1 818 363 5031",
    "sg:postcode":"91325",
    "sg:province":"CA",
    "wof:name":"El Torito Mexican Restaurant",
    "wof:placetype":"venue"
},
  "geometry": {"coordinates":[-118.505008,34.257605],"type":"Point"}
}