{
  "type": "Feature",
  "properties": {
    "iso:country":"US",
    "sg:address":"701 N A St",
    "sg:city":"Oxnard",
    "sg:classifiers":[
        {
            "category":"Health Services",
            "subcategory":"Doctor",
            "type":"Services"
        }
    ],
    "sg:phone":"+1 805 604 1824",
    "sg:postcode":"93030",
    "sg:province":"CA",
    "sg:tags":[
        "physician",
        "surgeon"
    ],
    "wof:name":"Manoj Khatore MD",
    "wof:placetype":"venue"
},
  "geometry": {"coordinates":[-119.178527,34.209751],"type":"Point"}
}