{
  "type": "Feature",
  "properties": {
    "addr:full":"7301 Topanga Canyon Blvd Canoga Park CA 91303",
    "addr:housenumber":"7301",
    "addr:postcode":"91303",
    "addr:street":"Topanga Canyon Blvd",
    "iso:country":"US",
    "sg:address":"7301 Topanga Canyon Blvd",
    "sg:city":"Canoga Park",
    "sg:classifiers":[
        {
            "category":"Shopping",
            "subcategory":"Music",
            "type":"Retail Goods"
        }
    ],
    "sg:phone":"+1 818 592 0056",
    "sg:postcode":"91303",
    "sg:province":"CA",
    "sg:tags":[
        "video",
        "disc",
        "tape",
        "cassette"
    ],
    "wof:name":"JBI Video",
    "wof:placetype":"venue"
},
  "geometry": {"coordinates":[-118.605858,34.203694],"type":"Point"}
}