{
  "type": "Feature",
  "properties": {
    "addr:full":"2007 W Hedding Street Suite 202 San Jose CA 95128",
    "addr:housenumber":"2007",
    "addr:postcode":"95128",
    "addr:street":"W Hedding Street Suite 202",
    "iso:country":"US",
    "sg:address":"2007 W Hedding Street Suite 202",
    "sg:city":"San Jose",
    "sg:classifiers":[
        {
            "category":"Professional",
            "subcategory":"Lawyer & Legal Services",
            "type":"Services"
        }
    ],
    "sg:phone":"+1 408 246 5500",
    "sg:postcode":"95128",
    "sg:province":"CA",
    "sg:tags":[
        "personal",
        "injury"
    ],
    "wof:name":"Hinkle John H",
    "wof:placetype":"venue"
},
  "geometry": {"coordinates":[-121.934679,37.331841],"type":"Point"}
}