{
  "type": "Feature",
  "properties": {
    "addr:full":"2211 N Macarthur Dr Tracy CA 95376",
    "addr:housenumber":"2211",
    "addr:postcode":"95376",
    "addr:street":"N Macarthur Dr",
    "iso:country":"US",
    "sg:address":"2211 N Macarthur Dr",
    "sg:city":"Tracy",
    "sg:classifiers":[
        {
            "category":"Professional",
            "type":"Services"
        },
        {
            "category":"Sports & Exercise",
            "subcategory":"Gym",
            "type":"Entertainment"
        }
    ],
    "sg:phone":"+1 209 609 8736",
    "sg:postcode":"95376",
    "sg:province":"CA",
    "sg:tags":[
        "instruction",
        "gymnastics",
        "cheerleading"
    ],
    "sg:website":"http://athleticperfectioncheer.com",
    "wof:name":"Athletic Perfection",
    "wof:placetype":"venue"
},
  "geometry": {"coordinates":[-121.414552,37.750546],"type":"Point"}
}