{
  "type": "Feature",
  "properties": {
    "iso:country":"US",
    "sg:address":"5366 Wilshire Blvd",
    "sg:city":"Los Angeles",
    "sg:classifiers":[
        {
            "category":"Real Estate",
            "subcategory":"Architect",
            "type":"Services"
        }
    ],
    "sg:phone":"+1 323 932 1793",
    "sg:postcode":"90036",
    "sg:province":"CA",
    "sg:tags":[
        "home",
        "planning",
        "design"
    ],
    "wof:name":"Building",
    "wof:placetype":"venue"
},
  "geometry": {"coordinates":[-118.34589200000001,34.062131],"type":"Point"}
}