{
  "type": "Feature",
  "properties": {
    "addr:full":"1070 Horizon Dr Fairfield CA 94533",
    "addr:housenumber":"1070",
    "addr:postcode":"94533",
    "addr:street":"Horizon Dr",
    "iso:country":"US",
    "sg:address":"1070 Horizon Dr",
    "sg:city":"Fairfield",
    "sg:classifiers":[
        {
            "category":"Professional",
            "subcategory":"Management & Consulting",
            "type":"Services"
        }
    ],
    "sg:phone":"+1 707 425 7445",
    "sg:postcode":"94533",
    "sg:province":"CA",
    "sg:tags":[
        "consultant",
        "construction"
    ],
    "wof:name":"Bar X Enterprises",
    "wof:placetype":"venue"
},
  "geometry": {"coordinates":[-122.012231,38.273941],"type":"Point"}
}