{
  "type": "Feature",
  "properties": {
    "addr:full":"12815 Oroville-Quincy Hwy Berry Creek CA 95916",
    "addr:housenumber":"12815",
    "addr:postcode":"95916",
    "addr:street":"Oroville-Quincy Hwy Berry",
    "iso:country":"US",
    "sg:address":"12815 Oroville-Quincy Hwy",
    "sg:city":"Berry Creek",
    "sg:classifiers":[
        {
            "category":"Manufacturing",
            "subcategory":"Lumber",
            "type":"Manufacturing & Wholesale Goods"
        }
    ],
    "sg:phone":"+1 530 589 1331",
    "sg:postcode":"95916",
    "sg:province":"CA",
    "sg:tags":[
        "government"
    ],
    "wof:name":"US Forestry Dept",
    "wof:placetype":"venue"
},
  "geometry": {"coordinates":[-121.33700899999999,39.690773],"type":"Point"}
}