{
  "type": "Feature",
  "properties": {
    "iso:country":"US",
    "sg:address":"5892 Kahara Ct",
    "sg:city":"Sacramento",
    "sg:classifiers":[
        {
            "category":"Professional",
            "subcategory":"Business Services",
            "type":"Services"
        }
    ],
    "sg:phone":"+1 916 422 1959",
    "sg:postcode":"95822",
    "sg:province":"CA",
    "sg:tags":[
        "fund",
        "promotion",
        "raising"
    ],
    "wof:name":"IMUR",
    "wof:placetype":"venue"
},
  "geometry": {"coordinates":[-121.51568,38.520597],"type":"Point"}
}