{
  "type": "Feature",
  "properties": {
    "iso:country":"US",
    "sg:address":"140 S Fairmont Blvd",
    "sg:city":"Anaheim",
    "sg:classifiers":[
        {
            "category":"Health Services",
            "subcategory":"Dentist",
            "type":"Services"
        }
    ],
    "sg:phone":"+1 714 637 3240",
    "sg:postcode":"92808",
    "sg:province":"CA",
    "wof:name":"Ching Clayton V DDS",
    "wof:placetype":"venue"
},
  "geometry": {"coordinates":[-117.769997,33.856998],"type":"Point"}
}