{
  "type": "Feature",
  "properties": {
    "addr:full":"1035 Carol Ln Lafayette CA 94549",
    "addr:housenumber":"1035",
    "addr:postcode":"94549",
    "addr:street":"Carol Ln",
    "iso:country":"US",
    "sg:address":"1035 Carol Ln",
    "sg:city":"Lafayette",
    "sg:classifiers":[
        {
            "category":"Education",
            "subcategory":"School",
            "type":"Public Place"
        }
    ],
    "sg:phone":"+1 925 962 9660",
    "sg:postcode":"94549",
    "sg:province":"CA",
    "wof:name":"Springstone School",
    "wof:placetype":"venue"
},
  "geometry": {"coordinates":[-122.10264599999999,37.891427],"type":"Point"}
}