{
  "type": "Feature",
  "properties": {
    "addr:full":"1107 N Chester Ave Bakersfield CA 93308",
    "addr:housenumber":"1107",
    "addr:postcode":"93308",
    "addr:street":"N Chester Ave",
    "iso:country":"US",
    "sg:address":"1107 N Chester Ave",
    "sg:city":"Bakersfield",
    "sg:classifiers":[
        {
            "category":"Organizations",
            "subcategory":"Religious Organization",
            "type":"Services"
        }
    ],
    "sg:phone":"+1 661 392 1530",
    "sg:postcode":"93308",
    "sg:province":"CA",
    "sg:tags":[
        "church"
    ],
    "wof:name":"Jesus Name House Of Prayer",
    "wof:placetype":"venue"
},
  "geometry": {"coordinates":[-119.021227,35.417292],"type":"Point"}
}