{
  "type": "Feature",
  "properties": {
    "iso:country":"US",
    "sg:address":"517 E Brundage Ln",
    "sg:city":"Bakersfield",
    "sg:classifiers":[
        {
            "category":"Home & Garden",
            "subcategory":"Garden Supply",
            "type":"Retail Goods"
        }
    ],
    "sg:phone":"+1 661 322 3989",
    "sg:postcode":"93307",
    "sg:province":"CA",
    "sg:tags":[
        "lawn",
        "mower"
    ],
    "wof:name":"Alex Gomez",
    "wof:placetype":"venue"
},
  "geometry": {"coordinates":[-118.997513,35.353818],"type":"Point"}
}