{
  "type": "Feature",
  "properties": {
    "iso:country":"US",
    "sg:address":"4166 Portola Dr",
    "sg:city":"Palmdale",
    "sg:classifiers":[
        {
            "category":"Banks & Credit Unions",
            "subcategory":"Investment Brokerage",
            "type":"Services"
        }
    ],
    "sg:phone":"+1 661 943 3077",
    "sg:postcode":"93551",
    "sg:province":"CA",
    "sg:tags":[
        "advisory"
    ],
    "wof:name":"Haro Investors",
    "wof:placetype":"venue"
},
  "geometry": {"coordinates":[-118.204712,34.61629],"type":"Point"}
}