{
  "type": "Feature",
  "properties": {
    "iso:country":"US",
    "sg:address":"8607 Garibaldi Ave",
    "sg:city":"San Gabriel",
    "sg:classifiers":[
        {
            "category":"Retail",
            "subcategory":"Laundry & Dry Cleaning",
            "type":"Services"
        }
    ],
    "sg:phone":"+1 626 961 7977",
    "sg:postcode":"91775",
    "sg:province":"CA",
    "sg:tags":[
        "cleaners"
    ],
    "wof:name":"Atlantic Garment Dye & Laundry",
    "wof:placetype":"venue"
},
  "geometry": {"coordinates":[-118.080451,34.109374],"type":"Point"}
}