{
  "type": "Feature",
  "properties": {
    "addr:full":"3325 Palo Verde Ave Long Beach CA 90808",
    "addr:housenumber":"3325",
    "addr:postcode":"90808",
    "addr:street":"Palo Verde Ave",
    "iso:country":"US",
    "sg:address":"3325 Palo Verde Ave",
    "sg:city":"Long Beach",
    "sg:classifiers":[
        {
            "category":"Health Services",
            "subcategory":"Doctor",
            "type":"Services"
        }
    ],
    "sg:phone":"+1 562 425 1802",
    "sg:postcode":"90808",
    "sg:province":"CA",
    "sg:tags":[
        "physician",
        "surgeon"
    ],
    "wof:name":"West Coast Orthopedics",
    "wof:placetype":"venue"
},
  "geometry": {"coordinates":[-118.10790900000001,33.81841],"type":"Point"}
}