{
  "type": "Feature",
  "properties": {
    "iso:country":"US",
    "sg:address":"4750 Von Karman Ave",
    "sg:city":"Newport Beach",
    "sg:classifiers":[
        {
            "category":"Shopping",
            "subcategory":"Clothing, Apparel, & Fashions",
            "type":"Retail Goods"
        }
    ],
    "sg:phone":"+1 949 474 6003",
    "sg:postcode":"92612",
    "sg:province":"CA",
    "sg:tags":[
        "alteration"
    ],
    "wof:name":"Kids Ink",
    "wof:placetype":"venue"
},
  "geometry": {"coordinates":[-117.860428,33.66819],"type":"Point"}
}