{
  "type": "Feature",
  "properties": {
    "addr:full":"4619 Aldrich Rd Hughson CA 95326",
    "addr:housenumber":"4619",
    "addr:postcode":"95326",
    "addr:street":"Aldrich Rd",
    "iso:country":"US",
    "sg:address":"4619 Aldrich Rd",
    "sg:city":"Hughson",
    "sg:classifiers":[
        {
            "category":"Farming",
            "subcategory":"Farm",
            "type":"Manufacturing & Wholesale Goods"
        }
    ],
    "sg:phone":"+1 209 883 2763",
    "sg:postcode":"95326",
    "sg:province":"CA",
    "sg:tags":[
        "crop",
        "general"
    ],
    "wof:name":"Dan Hames",
    "wof:placetype":"venue"
},
  "geometry": {"coordinates":[-120.837971,37.568813],"type":"Point"}
}