{
  "type": "Feature",
  "properties": {
    "iso:country":"US",
    "sg:address":"1630 N Main St",
    "sg:city":"Walnut Creek",
    "sg:classifiers":[
        {
            "category":"Wholesale",
            "subcategory":"Medical Equipment & Supplies",
            "type":"Manufacturing & Wholesale Goods"
        }
    ],
    "sg:phone":"+1 925 932 8887",
    "sg:postcode":"94596",
    "sg:province":"CA",
    "wof:name":"Barr Medical Corp",
    "wof:placetype":"venue"
},
  "geometry": {"coordinates":[-122.06150100000001,37.901135],"type":"Point"}
}