{
  "type": "Feature",
  "properties": {
    "addr:full":"260 Button Ave Manteca CA 95336",
    "addr:housenumber":"260",
    "addr:postcode":"95336",
    "addr:street":"Button Ave",
    "iso:country":"US",
    "sg:address":"260 Button Ave",
    "sg:city":"Manteca",
    "sg:classifiers":[
        {
            "category":"Home & Garden",
            "subcategory":"Carpets & Floor Coverings",
            "type":"Retail Goods"
        }
    ],
    "sg:phone":"+1 209 239 6264",
    "sg:postcode":"95336",
    "sg:province":"CA",
    "sg:tags":[
        "install"
    ],
    "wof:name":"Abbey Carpet Of Manteca",
    "wof:placetype":"venue"
},
  "geometry": {"coordinates":[-121.193135,37.80279],"type":"Point"}
}