{
  "type": "Feature",
  "properties": {
    "addr:full":"732 9th St Arcata CA 95521",
    "addr:housenumber":"732",
    "addr:postcode":"95521",
    "addr:street":"9Th St",
    "iso:country":"US",
    "sg:address":"732 9th St",
    "sg:city":"Arcata",
    "sg:classifiers":[
        {
            "category":"Bars & Pubs",
            "type":"Food & Drink"
        }
    ],
    "sg:phone":"+1 707 822 0919",
    "sg:postcode":"95521",
    "sg:province":"CA",
    "sg:tags":[
        "lounge",
        "cocktail"
    ],
    "wof:name":"Sidelines Sports Bar",
    "wof:placetype":"venue"
},
  "geometry": {"coordinates":[-124.08651500000001,40.869018],"type":"Point"}
}