{
  "type": "Feature",
  "properties": {
    "iso:country":"US",
    "sg:address":"5388 Saint Helena Hwy",
    "sg:city":"Napa",
    "sg:classifiers":[
        {
            "category":"Shopping",
            "subcategory":"Hobbies, Toys, & Games",
            "type":"Retail Goods"
        }
    ],
    "sg:phone":"+1 707 257 3331",
    "sg:postcode":"94558",
    "sg:province":"CA",
    "sg:tags":[
        "craft",
        "supply"
    ],
    "wof:name":"Tole'n Treasure Loft",
    "wof:placetype":"venue"
},
  "geometry": {"coordinates":[-122.34172100000001,38.372763],"type":"Point"}
}