{
  "type": "Feature",
  "properties": {
    "addr:full":"847 E 5th St Calexico CA 92231",
    "addr:housenumber":"847",
    "addr:postcode":"92231",
    "addr:street":"E 5Th St",
    "iso:country":"US",
    "sg:address":"847 E 5th St",
    "sg:city":"Calexico",
    "sg:classifiers":[
        {
            "category":"Restaurant",
            "type":"Food & Drink"
        }
    ],
    "sg:phone":"+1 760 768 3195",
    "sg:postcode":"92231",
    "sg:province":"CA",
    "sg:tags":[
        "parlor",
        "ice",
        "cream"
    ],
    "wof:name":"Raspados Cuchis",
    "wof:placetype":"venue"
},
  "geometry": {"coordinates":[-115.487404,32.669896],"type":"Point"}
}