{
  "type": "Feature",
  "properties": {
    "iso:country":"US",
    "sg:address":"18501 Devonshire St",
    "sg:city":"Northridge",
    "sg:classifiers":[
        {
            "category":"Building & Trades",
            "subcategory":"Equipment Rental",
            "type":"Services"
        }
    ],
    "sg:phone":"+1 818 360 0137",
    "sg:postcode":"91324",
    "sg:province":"CA",
    "sg:tags":[
        "moving",
        "supply"
    ],
    "wof:name":"Budget Truck Rental",
    "wof:placetype":"venue"
},
  "geometry": {"coordinates":[-118.54115400000001,34.257265],"type":"Point"}
}