{
  "type": "Feature",
  "properties": {
    "addr:full":"10235 Fair Oaks Blvd Fair Oaks CA 95628",
    "addr:housenumber":"10235",
    "addr:postcode":"95628",
    "addr:street":"Fair Oaks Blvd",
    "iso:country":"US",
    "sg:address":"10235 Fair Oaks Blvd",
    "sg:city":"Fair Oaks",
    "sg:classifiers":[
        {
            "category":"Retail",
            "subcategory":"Repair Shop",
            "type":"Services"
        }
    ],
    "sg:phone":"+1 916 965 5318",
    "sg:postcode":"95628",
    "sg:province":"CA",
    "sg:tags":[
        "antique",
        "watch"
    ],
    "wof:name":"Fair Oaks Jewelers Watch & Clock Repair",
    "wof:placetype":"venue"
},
  "geometry": {"coordinates":[-121.269997,38.642799],"type":"Point"}
}