{
  "type": "Feature",
  "properties": {
    "iso:country":"US",
    "sg:address":"38745 Tierra Subida Ave",
    "sg:city":"Palmdale",
    "sg:classifiers":[
        {
            "category":"Professional",
            "subcategory":"Accounting & Tax Preparation",
            "type":"Services"
        }
    ],
    "sg:phone":"+1 661 266 9568",
    "sg:postcode":"93551",
    "sg:province":"CA",
    "sg:tags":[
        "return",
        "filing"
    ],
    "wof:name":"H & R Block Tax Svc",
    "wof:placetype":"venue"
},
  "geometry": {"coordinates":[-118.147497,34.583949],"type":"Point"}
}