{
  "type": "Feature",
  "properties": {
    "iso:country":"US",
    "sg:address":"625 San Anselmo Ave",
    "sg:city":"San Anselmo",
    "sg:classifiers":[
        {
            "category":"Food & Beverages",
            "subcategory":"Bakery",
            "type":"Retail Goods"
        }
    ],
    "sg:phone":"+1 415 453 5368",
    "sg:postcode":"94960",
    "sg:province":"CA",
    "sg:tags":[
        "baker"
    ],
    "wof:name":"Royal Sweet Bakery",
    "wof:placetype":"venue"
},
  "geometry": {"coordinates":[-122.562916,37.97587],"type":"Point"}
}