{
  "type": "Feature",
  "properties": {
    "iso:country":"US",
    "sg:address":"2900 N Bellflower Blvd",
    "sg:city":"Long Beach",
    "sg:classifiers":[
        {
            "category":"Shopping",
            "subcategory":"Department Store",
            "type":"Retail Goods"
        }
    ],
    "sg:phone":"+1 562 377 0618",
    "sg:postcode":"90815",
    "sg:province":"CA",
    "sg:website":"www.kmart.com",
    "wof:name":"Kmart Stores",
    "wof:placetype":"venue"
},
  "geometry": {"coordinates":[-118.125,33.809601],"type":"Point"}
}