{
  "type": "Feature",
  "properties": {
    "iso:country":"US",
    "sg:address":"2020 Coffee Rd",
    "sg:city":"Modesto",
    "sg:classifiers":[
        {
            "category":"Social Services",
            "type":"Services"
        }
    ],
    "sg:phone":"+1 209 575 5559",
    "sg:postcode":"95355",
    "sg:province":"CA",
    "sg:tags":[
        "counselor",
        "marriage",
        "family"
    ],
    "wof:name":"Jerold Rosenthal",
    "wof:placetype":"venue"
},
  "geometry": {"coordinates":[-120.975674,37.673861],"type":"Point"}
}