{
  "type": "Feature",
  "properties": {
    "iso:country":"US",
    "sg:address":"464 Ellis Street",
    "sg:city":"Mountain View",
    "sg:classifiers":[
        {
            "category":"Professional",
            "subcategory":"Research",
            "type":"Services"
        }
    ],
    "sg:phone":"+1 888 437 2935",
    "sg:postcode":"94303",
    "sg:province":"CA",
    "sg:website":"http://www.reliant-tech.com/",
    "wof:name":"Reliant Technologies",
    "wof:placetype":"venue"
},
  "geometry": {"coordinates":[-122.141075,37.468827],"type":"Point"}
}