{
  "type": "Feature",
  "properties": {
    "addr:full":"9200 Bolsa Avenue Suite 215 Westminster CA 92683",
    "addr:housenumber":"9200",
    "addr:postcode":"92683",
    "addr:street":"Bolsa Avenue Suite 215",
    "iso:country":"US",
    "sg:address":"9200 Bolsa Avenue Suite 215",
    "sg:city":"Westminster",
    "sg:classifiers":[
        {
            "category":"Shopping",
            "subcategory":"Jewelry",
            "type":"Retail Goods"
        }
    ],
    "sg:phone":"+1 714 903 8666",
    "sg:postcode":"92683",
    "sg:province":"CA",
    "wof:name":"Kh Diamond",
    "wof:placetype":"venue"
},
  "geometry": {"coordinates":[-117.968952,33.744824],"type":"Point"}
}