{
  "type": "Feature",
  "properties": {
    "iso:country":"US",
    "sg:address":"321 Orange Ave",
    "sg:city":"Sand City",
    "sg:classifiers":[
        {
            "category":"Wholesale",
            "subcategory":"Hardware",
            "type":"Manufacturing & Wholesale Goods"
        }
    ],
    "sg:phone":"+1 831 394 8576",
    "sg:postcode":"93955",
    "sg:province":"CA",
    "sg:tags":[
        "plumbing",
        "fixture",
        "supply"
    ],
    "wof:name":"Slakey Brothers Inc",
    "wof:placetype":"venue"
},
  "geometry": {"coordinates":[-121.853804,36.610734],"type":"Point"}
}