{
  "type": "Feature",
  "properties": {
    "addr:full":"2300 S Flower St Los Angeles CA 90007",
    "addr:housenumber":"2300",
    "addr:postcode":"90007",
    "addr:street":"S Flower St",
    "iso:country":"US",
    "sg:address":"2300 S Flower St",
    "sg:city":"Los Angeles",
    "sg:classifiers":[
        {
            "category":"Health Services",
            "subcategory":"Clinic",
            "type":"Services"
        }
    ],
    "sg:phone":"+1 323 734 8575",
    "sg:postcode":"90007",
    "sg:province":"CA",
    "wof:name":"Rhino Care",
    "wof:placetype":"venue"
},
  "geometry": {"coordinates":[-118.27372099999999,34.029008],"type":"Point"}
}