{
  "type": "Feature",
  "properties": {
    "addr:full":"18050 S Central Ave Carson CA 90746",
    "addr:housenumber":"18050",
    "addr:postcode":"90746",
    "addr:street":"S Central Ave",
    "iso:country":"US",
    "sg:address":"18050 S Central Ave",
    "sg:city":"Carson",
    "sg:classifiers":[
        {
            "category":"Manufacturing",
            "subcategory":"Printing",
            "type":"Manufacturing & Wholesale Goods"
        }
    ],
    "sg:phone":"+1 310 608 6200",
    "sg:postcode":"90746",
    "sg:province":"CA",
    "sg:tags":[
        "printer"
    ],
    "wof:name":"Bowne & Co",
    "wof:placetype":"venue"
},
  "geometry": {"coordinates":[-118.24849,33.867156],"type":"Point"}
}