{
  "type": "Feature",
  "properties": {
    "addr:full":"212 Paradox Ln El Cajon CA 92021",
    "addr:housenumber":"212",
    "addr:postcode":"92021",
    "addr:street":"Paradox Ln",
    "iso:country":"US",
    "sg:address":"212 Paradox Ln",
    "sg:city":"El Cajon",
    "sg:classifiers":[
        {
            "category":"Professional",
            "subcategory":"Management & Consulting",
            "type":"Services"
        }
    ],
    "sg:phone":"+1 619 440 0357",
    "sg:postcode":"92021",
    "sg:province":"CA",
    "sg:tags":[
        "construction"
    ],
    "wof:name":"C & R Pier",
    "wof:placetype":"venue"
},
  "geometry": {"coordinates":[-116.85948,32.81439],"type":"Point"}
}