{
  "type": "Feature",
  "properties": {
    "iso:country":"US",
    "sg:address":"19440 Highline Rd",
    "sg:city":"Tehachapi",
    "sg:classifiers":[
        {
            "category":"Wholesale",
            "subcategory":"Fruits & Vegetables",
            "type":"Manufacturing & Wholesale Goods"
        }
    ],
    "sg:phone":"+1 661 822 5021",
    "sg:postcode":"93561",
    "sg:province":"CA",
    "wof:name":"Appletree",
    "wof:placetype":"venue"
},
  "geometry": {"coordinates":[-118.470025,35.109398],"type":"Point"}
}