{
  "type": "Feature",
  "properties": {
    "iso:country":"US",
    "sg:address":"773 W California Ave",
    "sg:city":"Glendale",
    "sg:classifiers":[
        {
            "category":"Building & Trades",
            "subcategory":"Construction",
            "type":"Services"
        }
    ],
    "sg:phone":"+1 818 812 4101",
    "sg:postcode":"91203",
    "sg:province":"CA",
    "sg:tags":[
        "contractor"
    ],
    "sg:website":"www.stargaragedoors.com",
    "wof:name":"Star Garage Doors Glendale",
    "wof:placetype":"venue"
},
  "geometry": {"coordinates":[-118.27308499999999,34.150066],"type":"Point"}
}