{
  "type": "Feature",
  "properties": {
    "iso:country":"US",
    "sg:address":"4454 Van Nuys Blvd Ste F",
    "sg:city":"Sherman Oaks",
    "sg:classifiers":[
        {
            "category":"Professional",
            "type":"Services"
        },
        {
            "category":"Personal",
            "type":"Services"
        }
    ],
    "sg:phone":"+1 818 986 8047",
    "sg:postcode":"91403",
    "sg:province":"CA",
    "sg:tags":[
        "sewing",
        "alteration"
    ],
    "sg:website":"www.drbluejeans.com",
    "wof:name":"Doctor Blue Jeanns",
    "wof:placetype":"venue"
},
  "geometry": {"coordinates":[-118.44756700000001,34.152318],"type":"Point"}
}