{
  "type": "Feature",
  "properties": {
    "addr:full":"303 Vintage Park Dr Foster City CA 94404",
    "addr:housenumber":"303",
    "addr:postcode":"94404",
    "addr:street":"Vintage Park Dr",
    "iso:country":"US",
    "sg:address":"303 Vintage Park Dr",
    "sg:city":"Foster City",
    "sg:classifiers":[
        {
            "category":"Banks & Credit Unions",
            "subcategory":"Investment Brokerage",
            "type":"Services"
        }
    ],
    "sg:phone":"+1 650 548 9200",
    "sg:postcode":"94404",
    "sg:province":"CA",
    "sg:tags":[
        "investing"
    ],
    "wof:name":"Neumann Capital Management",
    "wof:placetype":"venue"
},
  "geometry": {"coordinates":[-122.277254,37.567517],"type":"Point"}
}