{
  "type": "Feature",
  "properties": {
    "addr:full":"10600 W Pico Blvd Los Angeles CA 90064",
    "addr:housenumber":"10600",
    "addr:postcode":"90064",
    "addr:street":"W Pico Blvd",
    "iso:country":"US",
    "sg:address":"10600 W Pico Blvd",
    "sg:city":"Los Angeles",
    "sg:classifiers":[
        {
            "category":"Real Estate",
            "subcategory":"Real Estate Agent",
            "type":"Services"
        }
    ],
    "sg:phone":"+1 310 917 1167",
    "sg:postcode":"90064",
    "sg:province":"CA",
    "sg:tags":[
        "management"
    ],
    "wof:name":"Khm Management",
    "wof:placetype":"venue"
},
  "geometry": {"coordinates":[-118.422855,34.042964],"type":"Point"}
}