{
  "type": "Feature",
  "properties": {
    "iso:country":"US",
    "sg:address":"317 S Broadway",
    "sg:city":"Los Angeles",
    "sg:classifiers":[
        {
            "category":"Manufacturing",
            "subcategory":"Toys & Sporting Goods",
            "type":"Manufacturing & Wholesale Goods"
        }
    ],
    "sg:phone":"+1 323 731 6642",
    "sg:postcode":"90013",
    "sg:province":"CA",
    "sg:tags":[
        "mfg"
    ],
    "wof:name":"Karla Decorations",
    "wof:placetype":"venue"
},
  "geometry": {"coordinates":[-118.249237,34.049802],"type":"Point"}
}