{
  "type": "Feature",
  "properties": {
    "addr:full":"6410 Waring Ave Los Angeles CA 90038",
    "addr:housenumber":"6410",
    "addr:postcode":"90038",
    "addr:street":"Waring Ave",
    "iso:country":"US",
    "sg:address":"6410 Waring Ave",
    "sg:city":"Los Angeles",
    "sg:classifiers":[
        {
            "category":"Government",
            "subcategory":"Office",
            "type":"Public Place"
        }
    ],
    "sg:phone":"+1 310 548 7657",
    "sg:postcode":"90038",
    "sg:province":"CA",
    "sg:tags":[
        "village"
    ],
    "wof:name":"Los Anglees Sewer & Storm",
    "wof:placetype":"venue"
},
  "geometry": {"coordinates":[-118.335127,34.085211],"type":"Point"}
}