{
  "type": "Feature",
  "properties": {
    "iso:country":"US",
    "sg:address":"4772 Stirling St",
    "sg:city":"Granite Bay",
    "sg:classifiers":[
        {
            "category":"Building & Trades",
            "subcategory":"Construction",
            "type":"Services"
        }
    ],
    "sg:phone":"+1 916 247 5403",
    "sg:postcode":"95746",
    "sg:province":"CA",
    "sg:tags":[
        "excavating",
        "contractor"
    ],
    "wof:name":"L C Veale & Son Excavating",
    "wof:placetype":"venue"
},
  "geometry": {"coordinates":[-121.212574,38.745301],"type":"Point"}
}