{
  "type": "Feature",
  "properties": {
    "addr:full":"1563 Botelho Dr Walnut Creek CA 94596",
    "addr:housenumber":"1563",
    "addr:postcode":"94596",
    "addr:street":"Botelho Dr",
    "iso:country":"US",
    "sg:address":"1563 Botelho Dr",
    "sg:city":"Walnut Creek",
    "sg:classifiers":[
        {
            "category":"Manufacturing",
            "subcategory":"Wood Products",
            "type":"Manufacturing & Wholesale Goods"
        }
    ],
    "sg:phone":"+1 925 937 0558",
    "sg:postcode":"94596",
    "sg:province":"CA",
    "sg:tags":[
        "merchandise",
        "mfg"
    ],
    "wof:name":"Deck The Walls",
    "wof:placetype":"venue"
},
  "geometry": {"coordinates":[-122.060591,37.894913],"type":"Point"}
}