{
  "type": "Feature",
  "properties": {
    "iso:country":"US",
    "sg:address":"5330 Madison Ave Ste F",
    "sg:city":"Sacramento",
    "sg:classifiers":[
        {
            "category":"Professional",
            "subcategory":"Lawyer & Legal Services",
            "type":"Services"
        }
    ],
    "sg:phone":"+1 916 332 8122",
    "sg:postcode":"95841",
    "sg:province":"CA",
    "sg:tags":[
        "divorce",
        "law",
        "family"
    ],
    "wof:name":"Gary Till & Burlingham",
    "wof:placetype":"venue"
},
  "geometry": {"coordinates":[-121.339761,38.660281],"type":"Point"}
}