{
  "type": "Feature",
  "properties": {
    "addr:full":"930 Sunset Dr Hollister CA 95023",
    "addr:housenumber":"930",
    "addr:postcode":"hollister ca 95023",
    "addr:street":"Sunset Dr",
    "iso:country":"US",
    "sg:address":"930 Sunset Dr",
    "sg:city":"Hollister",
    "sg:classifiers":[
        {
            "category":"Health Services",
            "subcategory":"Doctor",
            "type":"Services"
        }
    ],
    "sg:phone":"+1 831 637 1689",
    "sg:postcode":"95023",
    "sg:province":"CA",
    "sg:tags":[
        "clinic"
    ],
    "wof:name":"Salinas Allergy Clinic",
    "wof:placetype":"venue"
},
  "geometry": {"coordinates":[-121.38650699999999,36.835237],"type":"Point"}
}