{
  "type": "Feature",
  "properties": {
    "iso:country":"US",
    "sg:address":"140 McHenry Ave Ste 9",
    "sg:city":"Modesto",
    "sg:classifiers":[
        {
            "category":"Health Services",
            "subcategory":"Dentist",
            "type":"Services"
        }
    ],
    "sg:phone":"+1 209 571 3225",
    "sg:postcode":"95354",
    "sg:province":"CA",
    "wof:name":"Alexander Michael DMD",
    "wof:placetype":"venue"
},
  "geometry": {"coordinates":[-120.99400300000001,37.646198],"type":"Point"}
}