{
  "type": "Feature",
  "properties": {
    "iso:country":"US",
    "sg:address":"311 Nevada Street",
    "sg:city":"Santa Cruz",
    "sg:classifiers":[
        {
            "category":"Personal",
            "type":"Services"
        }
    ],
    "sg:phone":"+1 831 420 0419",
    "sg:postcode":"95060",
    "sg:province":"CA",
    "sg:tags":[
        "mover"
    ],
    "sg:website":"www.lambertmoving.com",
    "wof:name":"Lambert & Son Moving",
    "wof:placetype":"venue"
},
  "geometry": {"coordinates":[-122.032205,36.955994],"type":"Point"}
}