{
  "type": "Feature",
  "properties": {
    "addr:full":"712 E Villa St Pasadena CA 91101",
    "addr:housenumber":"712",
    "addr:postcode":"91101",
    "addr:street":"E Villa St",
    "iso:country":"US",
    "sg:address":"712 E Villa St",
    "sg:city":"Pasadena",
    "sg:classifiers":[
        {
            "category":"Organizations",
            "subcategory":"Non-profit Organization",
            "type":"Services"
        }
    ],
    "sg:phone":"+1 626 449 4960",
    "sg:postcode":"91101",
    "sg:province":"CA",
    "sg:tags":[
        "fund",
        "counselor",
        "raising"
    ],
    "wof:name":"Lake Avenue Foundation",
    "wof:placetype":"venue"
},
  "geometry": {"coordinates":[-118.134719,34.154187],"type":"Point"}
}