{
  "type": "Feature",
  "properties": {
    "iso:country":"US",
    "sg:address":"9420 Lilac Cir",
    "sg:city":"Westminster",
    "sg:classifiers":[
        {
            "category":"Manufacturing",
            "subcategory":"Tools & Machinery",
            "type":"Manufacturing & Wholesale Goods"
        }
    ],
    "sg:phone":"+1 714 531 7671",
    "sg:postcode":"92683",
    "sg:province":"CA",
    "sg:tags":[
        "measuring",
        "instrument",
        "electrical",
        "mfg"
    ],
    "wof:name":"Accelerated Computer Tech",
    "wof:placetype":"venue"
},
  "geometry": {"coordinates":[-117.965138,33.735957],"type":"Point"}
}