{
  "type": "Feature",
  "properties": {
    "addr:full":"3105 la Madera Way Antelope CA 95843",
    "addr:housenumber":"3105",
    "addr:postcode":"95843",
    "addr:street":"La Madera Way",
    "iso:country":"US",
    "sg:address":"3105 la Madera Way",
    "sg:city":"Antelope",
    "sg:classifiers":[
        {
            "category":"Building & Trades",
            "subcategory":"Plumbing",
            "type":"Services"
        }
    ],
    "sg:phone":"+1 916 723 3233",
    "sg:postcode":"95843",
    "sg:province":"CA",
    "sg:tags":[
        "plumber",
        "industrial",
        "contractors-commercial"
    ],
    "wof:name":"Standard Plumbing Service",
    "wof:placetype":"venue"
},
  "geometry": {"coordinates":[-121.39034700000001,38.725773],"type":"Point"}
}