{
  "type": "Feature",
  "properties": {
    "addr:full":"1081 Alameda Belmont CA 94002",
    "addr:housenumber":"1081",
    "addr:postcode":"94002",
    "addr:street":"Alameda Belmont",
    "iso:country":"US",
    "sg:address":"1081 Alameda",
    "sg:city":"Belmont",
    "sg:classifiers":[
        {
            "category":"Building & Trades",
            "subcategory":"Construction",
            "type":"Services"
        }
    ],
    "sg:phone":"+1 650 593 7515",
    "sg:postcode":"94002",
    "sg:province":"CA",
    "sg:tags":[
        "contractor"
    ],
    "wof:name":"Randolph Construction",
    "wof:placetype":"venue"
},
  "geometry": {"coordinates":[-122.293707,37.511136],"type":"Point"}
}