{
  "type": "Feature",
  "properties": {
    "iso:country":"US",
    "sg:address":"7932 Beverly Boulevard",
    "sg:city":"Los Angeles",
    "sg:classifiers":[
        {
            "category":"Personal",
            "type":"Services"
        },
        {
            "category":"Retail",
            "subcategory":"Laundry & Dry Cleaning",
            "type":"Services"
        }
    ],
    "sg:phone":"+1 323 931 6835",
    "sg:postcode":"90048",
    "sg:province":"CA",
    "sg:tags":[
        "sewing",
        "alteration"
    ],
    "wof:name":"Royale Cleaners",
    "wof:placetype":"venue"
},
  "geometry": {"coordinates":[-118.362506,34.076208],"type":"Point"}
}