{
  "type": "Feature",
  "properties": {
    "addr:full":"501 Lucard St Taft CA 93268",
    "addr:housenumber":"501",
    "addr:postcode":"93268",
    "addr:street":"Lucard St",
    "iso:country":"US",
    "sg:address":"501 Lucard St",
    "sg:city":"Taft",
    "sg:classifiers":[
        {
            "category":"Retail",
            "subcategory":"Funeral Services",
            "type":"Services"
        }
    ],
    "sg:phone":"+1 661 765 4111",
    "sg:postcode":"93268",
    "sg:province":"CA",
    "sg:tags":[
        "director"
    ],
    "wof:name":"Erickson & Brown Funeral Home",
    "wof:placetype":"venue"
},
  "geometry": {"coordinates":[-119.45915599999999,35.144082],"type":"Point"}
}