{
  "type": "Feature",
  "properties": {
    "iso:country":"US",
    "sg:address":"2030 Douglas Blvd",
    "sg:city":"Roseville",
    "sg:classifiers":[
        {
            "category":"Wholesale",
            "subcategory":"Jewelry",
            "type":"Manufacturing & Wholesale Goods"
        }
    ],
    "sg:phone":"+1 916 782 1014",
    "sg:postcode":"95678",
    "sg:province":"CA",
    "sg:tags":[
        "beads"
    ],
    "wof:name":"Bead Shoppe",
    "wof:placetype":"venue"
},
  "geometry": {"coordinates":[-121.247151,38.744201],"type":"Point"}
}