{
  "type": "Feature",
  "properties": {
    "addr:full":"1085 Tasman Dr Sunnyvale CA 94089",
    "addr:housenumber":"1085",
    "addr:postcode":"94089",
    "addr:street":"Tasman Dr",
    "iso:country":"US",
    "sg:address":"1085 Tasman Dr",
    "sg:city":"Sunnyvale",
    "sg:classifiers":[
        {
            "category":"Professional",
            "type":"Services"
        }
    ],
    "sg:phone":"+1 408 734 4680",
    "sg:postcode":"94089",
    "sg:province":"CA",
    "wof:name":"Iadored",
    "wof:placetype":"venue"
},
  "geometry": {"coordinates":[-121.999771,37.40324],"type":"Point"}
}