{
  "type": "Feature",
  "properties": {
    "iso:country":"US",
    "sg:address":"748 Morningside Dr",
    "sg:city":"Millbrae",
    "sg:classifiers":[
        {
            "category":"Building & Trades",
            "subcategory":"Construction",
            "type":"Services"
        }
    ],
    "sg:phone":"+1 650 697 9494",
    "sg:postcode":"94030",
    "sg:province":"CA",
    "sg:tags":[
        "remodeling",
        "contractor"
    ],
    "wof:name":"Pape Russ Construction",
    "wof:placetype":"venue"
},
  "geometry": {"coordinates":[-122.407382,37.596936],"type":"Point"}
}