{
  "type": "Feature",
  "properties": {
    "addr:full":"420 W Center St Pomona CA 91768",
    "addr:housenumber":"420",
    "addr:postcode":"91768",
    "addr:street":"W Center St",
    "iso:country":"US",
    "sg:address":"420 W Center St",
    "sg:city":"Pomona",
    "sg:classifiers":[
        {
            "category":"Shopping",
            "subcategory":"Florist",
            "type":"Retail Goods"
        }
    ],
    "sg:phone":"+1 909 865 5090",
    "sg:postcode":"91768",
    "sg:province":"CA",
    "wof:name":"Flower Shop",
    "wof:placetype":"venue"
},
  "geometry": {"coordinates":[-117.75644800000001,34.061218],"type":"Point"}
}