{
  "type": "Feature",
  "properties": {
    "addr:full":"15121 Graham St Huntington Beach CA 92649",
    "addr:housenumber":"15121",
    "addr:postcode":"92649",
    "addr:street":"Graham St",
    "iso:country":"US",
    "sg:address":"15121 Graham St",
    "sg:city":"Huntington Beach",
    "sg:classifiers":[
        {
            "category":"Wholesale",
            "subcategory":"Machinery & Supplies",
            "type":"Manufacturing & Wholesale Goods"
        }
    ],
    "sg:phone":"+1 714 903 6487",
    "sg:postcode":"92649",
    "sg:province":"CA",
    "sg:tags":[
        "control",
        "factory",
        "system"
    ],
    "wof:name":"Ecsi",
    "wof:placetype":"venue"
},
  "geometry": {"coordinates":[-118.032945,33.741768],"type":"Point"}
}