{
  "type": "Feature",
  "properties": {
    "iso:country":"US",
    "sg:address":"350 S Grand Ave Two California Plaza",
    "sg:city":"Los Angeles",
    "sg:classifiers":[
        {
            "category":"Bars & Pubs",
            "type":"Food & Drink"
        },
        {
            "category":"Restaurant",
            "type":"Food & Drink"
        }
    ],
    "sg:phone":"+1 213 621 2249",
    "sg:postcode":"90071",
    "sg:province":"CA",
    "sg:tags":[
        "mexican"
    ],
    "sg:website":"casadowntown.com",
    "wof:name":"Casa Cocina Y Cantina",
    "wof:placetype":"venue"
},
  "geometry": {"coordinates":[-118.25139299999999,34.051502],"type":"Point"}
}