{
  "type": "Feature",
  "properties": {
    "addr:full":"2003 Laguna Canyon Road Laguna Beach CA 92651",
    "addr:housenumber":"2003",
    "addr:postcode":"92651",
    "addr:street":"Laguna Canyon Road",
    "iso:country":"US",
    "sg:address":"2003 Laguna Canyon Road",
    "sg:city":"Laguna Beach",
    "sg:classifiers":[
        {
            "category":"Personal",
            "type":"Services"
        },
        {
            "category":"Sports & Exercise",
            "subcategory":"Sports Center",
            "type":"Entertainment"
        }
    ],
    "sg:phone":"+1 949 497 6757",
    "sg:postcode":"92651",
    "sg:province":"CA",
    "sg:tags":[
        "party",
        "planning",
        "amateur",
        "event",
        "team"
    ],
    "wof:name":"Laguna Batting Cages and Training Academy",
    "wof:placetype":"venue"
},
  "geometry": {"coordinates":[-117.77476,33.555639],"type":"Point"}
}