{
  "type": "Feature",
  "properties": {
    "iso:country":"US",
    "sg:address":"7415 Clairemont Mesa Boulevard",
    "sg:city":"San Diego",
    "sg:classifiers":[
        {
            "category":"Restaurant",
            "type":"Food & Drink"
        }
    ],
    "sg:phone":"+1 858 715 0075",
    "sg:postcode":"92111",
    "sg:province":"CA",
    "sg:website":"www.originaltommys.com/",
    "wof:name":"Tommy's Original World Famous Hamburgers",
    "wof:placetype":"venue"
},
  "geometry": {"coordinates":[-117.15906,32.832707],"type":"Point"}
}