{
  "type": "Feature",
  "properties": {
    "iso:country":"US",
    "sg:address":"621 N Alta Ave",
    "sg:city":"Dinuba",
    "sg:classifiers":[
        {
            "category":"Shopping",
            "subcategory":"Tobacco",
            "type":"Retail Goods"
        }
    ],
    "sg:phone":"+1 559 595 9171",
    "sg:postcode":"93618",
    "sg:province":"CA",
    "sg:tags":[
        "cigarette",
        "cigar",
        "dealer"
    ],
    "wof:name":"Cigs & More",
    "wof:placetype":"venue"
},
  "geometry": {"coordinates":[-119.39525399999999,36.551916],"type":"Point"}
}