{
  "type": "Feature",
  "properties": {
    "addr:full":"15060 Foothill Ave Morgan Hill CA 95037",
    "addr:housenumber":"15060",
    "addr:postcode":"95037",
    "addr:street":"Foothill Ave",
    "iso:country":"US",
    "sg:address":"15060 Foothill Ave",
    "sg:city":"Morgan Hill",
    "sg:classifiers":[
        {
            "category":"Recreation",
            "type":"Entertainment"
        }
    ],
    "sg:phone":"+1 408 782 7101",
    "sg:postcode":"95037",
    "sg:province":"CA",
    "sg:tags":[
        "course",
        "golf"
    ],
    "wof:name":"Institute Golf Course",
    "wof:placetype":"venue"
},
  "geometry": {"coordinates":[-121.59364600000001,37.116923],"type":"Point"}
}