{
  "type": "Feature",
  "properties": {
    "iso:country":"US",
    "sg:address":"8009 Imperial Hwy",
    "sg:city":"Downey",
    "sg:classifiers":[
        {
            "category":"Donuts",
            "subcategory":"None",
            "type":"Food & Drink"
        }
    ],
    "sg:phone":"+1 562 861 6480",
    "sg:postcode":"90242",
    "sg:province":"CA",
    "wof:name":"USA Donuts & Croissants",
    "wof:placetype":"venue"
},
  "geometry": {"coordinates":[-118.15161999999999,33.923953],"type":"Point"}
}