{
  "type": "Feature",
  "properties": {
    "iso:country":"US",
    "sg:address":"1717 30th St",
    "sg:city":"Bakersfield",
    "sg:classifiers":[
        {
            "category":"Health Services",
            "subcategory":"Doctor",
            "type":"Services"
        }
    ],
    "sg:phone":"+1 661 638 0322",
    "sg:postcode":"93301",
    "sg:province":"CA",
    "sg:tags":[
        "dentist"
    ],
    "wof:name":"Norman F Salisbury Inc",
    "wof:placetype":"venue"
},
  "geometry": {"coordinates":[-119.023309,35.386668],"type":"Point"}
}