{
  "type": "Feature",
  "properties": {
    "addr:full":"19 Franciscan Way Kensington CA 94707",
    "addr:housenumber":"19",
    "addr:postcode":"94707",
    "addr:street":"Franciscan Way",
    "iso:country":"US",
    "sg:address":"19 Franciscan Way",
    "sg:city":"Kensington",
    "sg:classifiers":[
        {
            "category":"Professional",
            "type":"Services"
        }
    ],
    "sg:phone":"+1 510 524 7675",
    "sg:postcode":"94707",
    "sg:province":"CA",
    "sg:tags":[
        "arts",
        "artist"
    ],
    "wof:name":"Julian Block",
    "wof:placetype":"venue"
},
  "geometry": {"coordinates":[-122.286789,37.912726],"type":"Point"}
}