{
  "type": "Feature",
  "properties": {
    "iso:country":"US",
    "sg:address":"2307 Blanding Ave",
    "sg:city":"Alameda",
    "sg:classifiers":[
        {
            "category":"Arena",
            "subcategory":"Sports Club",
            "type":"Entertainment"
        }
    ],
    "sg:phone":"+1 510 522 2224",
    "sg:postcode":"94501",
    "sg:province":"CA",
    "sg:tags":[
        "martial art"
    ],
    "sg:website":"www.elitekickstkd.com",
    "wof:name":"Elite Kicks Tae Kwon Do",
    "wof:placetype":"venue"
},
  "geometry": {"coordinates":[-122.23831300000001,37.771418],"type":"Point"}
}