{
  "type": "Feature",
  "properties": {
    "addr:full":"1330 S Olive Street Los Angeles CA 90015",
    "addr:housenumber":"1330",
    "addr:postcode":"90015",
    "addr:street":"S Olive Street",
    "iso:country":"US",
    "sg:address":"1330 S Olive Street",
    "sg:city":"Los Angeles",
    "sg:classifiers":[
        {
            "category":"Real Estate",
            "subcategory":"Real Estate Operator",
            "type":"Services"
        }
    ],
    "sg:phone":"+1 213 765 0991",
    "sg:postcode":"90015",
    "sg:province":"CA",
    "sg:tags":[
        "apartment"
    ],
    "wof:name":"A Community of Friends",
    "wof:placetype":"venue"
},
  "geometry": {"coordinates":[-118.263617,34.037329],"type":"Point"}
}