{
  "type": "Feature",
  "properties": {
    "iso:country":"US",
    "sg:address":"2822 W Border Links Dr",
    "sg:city":"Visalia",
    "sg:classifiers":[
        {
            "category":"Professional",
            "subcategory":"Management & Consulting",
            "type":"Services"
        }
    ],
    "sg:phone":"+1 559 732 8433",
    "sg:postcode":"93291",
    "sg:province":"CA",
    "sg:tags":[
        "consultant",
        "business"
    ],
    "wof:name":"Robert J Graves Management",
    "wof:placetype":"venue"
},
  "geometry": {"coordinates":[-119.322483,36.333969],"type":"Point"}
}