{
  "type": "Feature",
  "properties": {
    "iso:country":"US",
    "sg:address":"214 Beardsley Ave",
    "sg:city":"Bakersfield",
    "sg:classifiers":[
        {
            "category":"Food & Beverages",
            "subcategory":"Groceries & Convenience Stores",
            "type":"Retail Goods"
        }
    ],
    "sg:phone":"+1 661 393 1400",
    "sg:postcode":"93308",
    "sg:province":"CA",
    "sg:tags":[
        "grocer"
    ],
    "wof:name":"Beardsley Market",
    "wof:placetype":"venue"
},
  "geometry": {"coordinates":[-119.02521400000001,35.405034],"type":"Point"}
}