{
  "type": "Feature",
  "properties": {
    "iso:country":"US",
    "sg:address":"458 E Mission Rd",
    "sg:city":"San Marcos",
    "sg:classifiers":[
        {
            "category":"Freight",
            "type":"Transportation"
        }
    ],
    "sg:phone":"+1 760 744 1191",
    "sg:postcode":"92069",
    "sg:province":"CA",
    "sg:tags":[
        "commercial",
        "storage"
    ],
    "wof:name":"Mission Road Self Storage",
    "wof:placetype":"venue"
},
  "geometry": {"coordinates":[-117.155408,33.142695],"type":"Point"}
}