{
  "type": "Feature",
  "properties": {
    "iso:country":"US",
    "sg:address":"68300 Ramon Rd Ste 8",
    "sg:city":"Cathedral City",
    "sg:classifiers":[
        {
            "category":"Shopping",
            "subcategory":"Mobile Phones",
            "type":"Retail Goods"
        }
    ],
    "sg:phone":"+1 760 324 5058",
    "sg:postcode":"92234",
    "sg:province":"CA",
    "wof:name":"Pager Express",
    "wof:placetype":"venue"
},
  "geometry": {"coordinates":[-116.470001,33.815899],"type":"Point"}
}