{
  "type": "Feature",
  "properties": {
    "iso:country":"US",
    "sg:address":"3500 W Olive Ave",
    "sg:city":"Burbank",
    "sg:classifiers":[
        {
            "category":"Farming",
            "subcategory":"Farm",
            "type":"Manufacturing & Wholesale Goods"
        }
    ],
    "sg:phone":"+1 818 207 4561",
    "sg:postcode":"91505",
    "sg:province":"CA",
    "wof:name":"Lb/L Epac Rancho Camargo",
    "wof:placetype":"venue"
},
  "geometry": {"coordinates":[-118.338539,34.15255],"type":"Point"}
}