{
  "type": "Feature",
  "properties": {
    "addr:full":"17183 Retrac Way Grass Valley CA 95949",
    "addr:postcode":"17183;95949",
    "addr:street":"Retrac Way",
    "iso:country":"US",
    "sg:address":"17183 Retrac Way",
    "sg:city":"Grass Valley",
    "sg:classifiers":[
        {
            "category":"Health Services",
            "subcategory":"Hospital",
            "type":"Services"
        }
    ],
    "sg:phone":"+1 530 268 0877",
    "sg:postcode":"95949",
    "sg:province":"CA",
    "sg:tags":[
        "mental"
    ],
    "sg:website":"www.christianencounter.net",
    "wof:name":"Christian Encounter Ministries",
    "wof:placetype":"venue"
},
  "geometry": {"coordinates":[-121.101266,39.115397],"type":"Point"}
}