{
  "type": "Feature",
  "properties": {
    "addr:full":"2750 E Imperial Hwy Brea CA 92821",
    "addr:housenumber":"2750",
    "addr:postcode":"92821",
    "addr:street":"E Imperial Hwy",
    "iso:country":"US",
    "sg:address":"2750 E Imperial Hwy",
    "sg:city":"Brea",
    "sg:classifiers":[
        {
            "category":"Personal",
            "type":"Services"
        },
        {
            "category":"Retail",
            "subcategory":"Storage",
            "type":"Services"
        }
    ],
    "sg:phone":"+1 877 258 8230",
    "sg:postcode":"92821",
    "sg:province":"CA",
    "sg:tags":[
        "self",
        "full",
        "commercial",
        "mover",
        "household"
    ],
    "sg:website":"http://www.publicstorage.com/?pid=ypcomCPCingenio",
    "wof:name":"Public Storage",
    "wof:placetype":"venue"
},
  "geometry": {"coordinates":[-117.861406,33.911012],"type":"Point"}
}