{
  "type": "Feature",
  "properties": {
    "iso:country":"US",
    "sg:address":"1329 B St",
    "sg:city":"Marysville",
    "sg:classifiers":[
        {
            "category":"Restaurant",
            "type":"Food & Drink"
        }
    ],
    "sg:phone":"+1 530 742 2277",
    "sg:postcode":"95901",
    "sg:province":"CA",
    "sg:tags":[
        "parlor",
        "ice",
        "cream"
    ],
    "wof:name":"Dairy Queen",
    "wof:placetype":"venue"
},
  "geometry": {"coordinates":[-121.587261,39.150346],"type":"Point"}
}