{
  "type": "Feature",
  "properties": {
    "addr:full":"2795 2nd St Davis CA 95618",
    "addr:housenumber":"2795",
    "addr:postcode":"95618",
    "addr:street":"2Nd St",
    "iso:country":"US",
    "sg:address":"2795 2nd St",
    "sg:city":"Davis",
    "sg:classifiers":[
        {
            "category":"Professional",
            "type":"Services"
        }
    ],
    "sg:phone":"+1 530 297 4700",
    "sg:postcode":"95618",
    "sg:province":"CA",
    "sg:tags":[
        "establishment"
    ],
    "wof:name":"Sagres Discovery",
    "wof:placetype":"venue"
},
  "geometry": {"coordinates":[-121.71567400000001,38.548933],"type":"Point"}
}