{
  "type": "Feature",
  "properties": {
    "iso:country":"US",
    "sg:address":"111 Balsam St",
    "sg:city":"Ridgecrest",
    "sg:classifiers":[
        {
            "category":"Professional",
            "type":"Services"
        }
    ],
    "sg:phone":"+1 760 371 2305",
    "sg:postcode":"93555",
    "sg:province":"CA",
    "sg:tags":[
        "establishment"
    ],
    "wof:name":"Fire Mountain Foundation",
    "wof:placetype":"venue"
},
  "geometry": {"coordinates":[-117.671251,35.622726],"type":"Point"}
}