{
  "type": "Feature",
  "properties": {
    "addr:full":"520 E California Ave Ridgecrest CA 93555",
    "addr:housenumber":"520",
    "addr:postcode":"93555",
    "addr:street":"E California Ave",
    "iso:country":"US",
    "sg:address":"520 E California Ave",
    "sg:city":"Ridgecrest",
    "sg:classifiers":[
        {
            "category":"Building & Trades",
            "subcategory":"Landscaping Services",
            "type":"Services"
        }
    ],
    "sg:phone":"+1 760 384 0090",
    "sg:postcode":"93555",
    "sg:province":"CA",
    "sg:tags":[
        "landscape"
    ],
    "wof:name":"Treehouse Landscape Design",
    "wof:placetype":"venue"
},
  "geometry": {"coordinates":[-117.65906699999999,35.620694],"type":"Point"}
}