{
  "type": "Feature",
  "properties": {
    "addr:full":"500 S Sepulveda Blvd Manhattan Beach CA 90266",
    "addr:housenumber":"500",
    "addr:postcode":"90266",
    "addr:street":"S Sepulveda Blvd",
    "iso:country":"US",
    "sg:address":"500 S Sepulveda Blvd",
    "sg:city":"Manhattan Beach",
    "sg:classifiers":[
        {
            "category":"Banks & Credit Unions",
            "subcategory":"Bank",
            "type":"Services"
        }
    ],
    "sg:phone":"+1 310 376 5810",
    "sg:postcode":"90266",
    "sg:province":"CA",
    "sg:tags":[
        "escrow"
    ],
    "wof:name":"So Cal Escrow",
    "wof:placetype":"venue"
},
  "geometry": {"coordinates":[-118.395889,33.877411],"type":"Point"}
}