{
  "type": "Feature",
  "properties": {
    "addr:full":"2237 Stagecoach Rd Stockton CA 95215",
    "addr:housenumber":"2237",
    "addr:postcode":"95215",
    "addr:street":"Stagecoach Rd",
    "iso:country":"US",
    "sg:address":"2237 Stagecoach Rd",
    "sg:city":"Stockton",
    "sg:classifiers":[
        {
            "category":"Professional",
            "subcategory":"Business Services",
            "type":"Services"
        }
    ],
    "sg:phone":"+1 209 464 8979",
    "sg:postcode":"95215",
    "sg:province":"CA",
    "sg:tags":[
        "embroidery"
    ],
    "wof:name":"Exactacator Inc",
    "wof:placetype":"venue"
},
  "geometry": {"coordinates":[-121.232131,37.940991],"type":"Point"}
}