{
  "type": "Feature",
  "properties": {
    "addr:full":"3533 Haven Ave Redwood City CA 94063",
    "addr:housenumber":"3533",
    "addr:postcode":"94063",
    "addr:street":"Haven Ave",
    "iso:country":"US",
    "sg:address":"3533 Haven Ave",
    "sg:city":"Redwood City",
    "sg:classifiers":[
        {
            "category":"Building & Trades",
            "subcategory":"Construction",
            "type":"Services"
        }
    ],
    "sg:phone":"+1 650 366 7867",
    "sg:postcode":"94063",
    "sg:province":"CA",
    "sg:tags":[
        "concrete",
        "pumping"
    ],
    "wof:name":"Warbucks Concrete Pumping",
    "wof:placetype":"venue"
},
  "geometry": {"coordinates":[-122.189876,37.486048],"type":"Point"}
}