{
  "type": "Feature",
  "properties": {
    "addr:full":"1617 Westcliff Dr Newport Beach CA 92660",
    "addr:housenumber":"1617",
    "addr:postcode":"92660",
    "addr:street":"Westcliff Dr",
    "iso:country":"US",
    "sg:address":"1617 Westcliff Dr",
    "sg:city":"Newport Beach",
    "sg:classifiers":[
        {
            "category":"Restaurant",
            "type":"Food & Drink"
        }
    ],
    "sg:phone":"+1 949 645 7077",
    "sg:postcode":"92660",
    "sg:province":"CA",
    "sg:tags":[
        "traditional",
        "american"
    ],
    "wof:name":"The Arches on 17th",
    "wof:placetype":"venue"
},
  "geometry": {"coordinates":[-117.908649,33.628319],"type":"Point"}
}