{
  "type": "Feature",
  "properties": {
    "addr:full":"807 Americana Way Glendale CA 91210",
    "addr:housenumber":"807",
    "addr:postcode":"91210",
    "addr:street":"Americana Way",
    "iso:country":"US",
    "sg:address":"807 Americana Way",
    "sg:city":"Glendale",
    "sg:classifiers":[
        {
            "category":"Restaurant",
            "type":"Food & Drink"
        }
    ],
    "sg:phone":"+1 818 550 0472",
    "sg:postcode":"91210",
    "sg:province":"CA",
    "sg:tags":[
        "new",
        "american"
    ],
    "sg:website":"www.granvillecafe.com",
    "wof:name":"Granville Cafe",
    "wof:placetype":"venue"
},
  "geometry": {"coordinates":[-118.255093,34.145109],"type":"Point"}
}