{
  "type": "Feature",
  "properties": {
    "addr:full":"43585 Monterey Ave Palm Desert CA 92260",
    "addr:housenumber":"43585",
    "addr:postcode":"ca 92260",
    "addr:street":"Monterey Ave",
    "iso:country":"US",
    "sg:address":"43585 Monterey Ave",
    "sg:city":"Palm Desert",
    "sg:classifiers":[
        {
            "category":"Professional",
            "subcategory":"Business Services",
            "type":"Services"
        }
    ],
    "sg:phone":"+1 760 770 7777",
    "sg:postcode":"92260",
    "sg:province":"CA",
    "wof:name":"M L Weiner & Assoc",
    "wof:placetype":"venue"
},
  "geometry": {"coordinates":[-116.39126899999999,33.731207],"type":"Point"}
}