{
  "type": "Feature",
  "properties": {
    "addr:full":"22411 Bonita St Carson CA 90745",
    "addr:housenumber":"22411",
    "addr:postcode":"90745",
    "addr:street":"Bonita St",
    "iso:country":"US",
    "sg:address":"22411 Bonita St",
    "sg:city":"Carson",
    "sg:classifiers":[
        {
            "category":"Autos & Motor Vehicles",
            "subcategory":"Auto Supplies",
            "type":"Retail Goods"
        }
    ],
    "sg:phone":"+1 310 233 2507",
    "sg:postcode":"90745",
    "sg:province":"CA",
    "sg:tags":[
        "tire"
    ],
    "wof:name":"Heafner Tire Group",
    "wof:placetype":"venue"
},
  "geometry": {"coordinates":[-118.25900300000001,33.8232],"type":"Point"}
}