{
  "type": "Feature",
  "properties": {
    "iso:country":"US",
    "sg:address":"22411 Bonita St",
    "sg:city":"Carson",
    "sg:classifiers":[
        {
            "category":"Autos & Motor Vehicles",
            "subcategory":"Auto Supplies",
            "type":"Retail Goods"
        }
    ],
    "sg:phone":"+1 310 233 2507",
    "sg:postcode":"90745",
    "sg:province":"CA",
    "sg:tags":[
        "tire"
    ],
    "wof:name":"Heafner Tire Group",
    "wof:placetype":"venue"
},
  "geometry": {"coordinates":[-118.259003,33.8232],"type":"Point"}
}