{
  "type": "Feature",
  "properties": {
    "addr:full":"2440 Fremont St Monterey CA 93940",
    "addr:housenumber":"2440",
    "addr:postcode":"93940",
    "addr:street":"Fremont St",
    "iso:country":"US",
    "sg:address":"2440 Fremont St",
    "sg:city":"Monterey",
    "sg:classifiers":[
        {
            "category":"Restaurant",
            "type":"Food & Drink"
        }
    ],
    "sg:menulink":"http://www.allmenus.com/ca/seaside-monterey/150348-subway/menu/",
    "sg:phone":"+1 831 375 6060",
    "sg:postcode":"93940",
    "sg:province":"CA",
    "sg:tags":[
        "american",
        "sandwich"
    ],
    "wof:name":"Subway",
    "wof:placetype":"venue"
},
  "geometry": {"coordinates":[-121.852135,36.59796],"type":"Point"}
}