{
  "type": "Feature",
  "properties": {
    "addr:full":"4301 S Figueroa St Los Angeles CA 90037",
    "addr:housenumber":"4301",
    "addr:postcode":"90037",
    "addr:street":"S Figueroa St",
    "iso:country":"US",
    "sg:address":"4301 S Figueroa St",
    "sg:city":"Los Angeles",
    "sg:classifiers":[
        {
            "category":"Health Services",
            "subcategory":"Doctor",
            "type":"Services"
        }
    ],
    "sg:phone":"+1 323 231 7700",
    "sg:postcode":"90037",
    "sg:province":"CA",
    "sg:tags":[
        "clinic"
    ],
    "wof:name":"Clinica De Los Angeles",
    "wof:placetype":"venue"
},
  "geometry": {"coordinates":[-118.28270500000001,34.004597],"type":"Point"}
}