{
  "type": "Feature",
  "properties": {
    "iso:country":"US",
    "sg:address":"Phoenix Theatre 414 Mason St 6th Fl",
    "sg:city":"San Francisco",
    "sg:classifiers":[
        {
            "category":"Arts & Performance",
            "subcategory":"Arts Center",
            "type":"Entertainment"
        }
    ],
    "sg:phone":"+1 415 407 3214",
    "sg:postcode":"94102",
    "sg:province":"CA",
    "sg:tags":[
        "performing"
    ],
    "wof:name":"Hedda Gabler by Ibsen",
    "wof:placetype":"venue"
},
  "geometry": {"coordinates":[-122.40974199999999,37.787511],"type":"Point"}
}