{
  "type": "Feature",
  "properties": {
    "addr:full":"179 Rio Mesa Way Galt CA 95632",
    "addr:housenumber":"179",
    "addr:postcode":"95632",
    "addr:street":"Rio Mesa Way",
    "iso:country":"US",
    "sg:address":"179 Rio Mesa Way",
    "sg:city":"Galt",
    "sg:classifiers":[
        {
            "category":"Shopping",
            "subcategory":"Bicycles & Sporting Goods",
            "type":"Retail Goods"
        }
    ],
    "sg:phone":"+1 209 744 8248",
    "sg:postcode":"95632",
    "sg:province":"CA",
    "wof:name":"Sporting Days",
    "wof:placetype":"venue"
},
  "geometry": {"coordinates":[-121.318241,38.250728],"type":"Point"}
}