{
  "type": "Feature",
  "properties": {
    "addr:full":"500 Tamal Plz Corte Madera CA 94925",
    "addr:housenumber":"500",
    "addr:postcode":"94925",
    "addr:street":"Tamal Plz",
    "iso:country":"US",
    "sg:address":"500 Tamal Plz",
    "sg:city":"Corte Madera",
    "sg:classifiers":[
        {
            "category":"Communications",
            "subcategory":"Film & Video Production",
            "type":"Services"
        }
    ],
    "sg:phone":"+1 415 945 0880",
    "sg:postcode":"94925",
    "sg:province":"CA",
    "sg:tags":[
        "motion",
        "picture",
        "studio",
        "producer"
    ],
    "wof:name":"Summertime Films",
    "wof:placetype":"venue"
},
  "geometry": {"coordinates":[-122.519786,37.936924],"type":"Point"}
}