{
  "type": "Feature",
  "properties": {
    "iso:country":"US",
    "sg:address":"5776 W Ave L",
    "sg:city":"Lancaster",
    "sg:classifiers":[
        {
            "category":"Farming",
            "subcategory":"Livestock Farm",
            "type":"Manufacturing & Wholesale Goods"
        }
    ],
    "sg:phone":"+1 661 943 1194",
    "sg:postcode":"93536",
    "sg:province":"CA",
    "sg:tags":[
        "ranch",
        "beef",
        "cattle"
    ],
    "wof:name":"Frank A Lane",
    "wof:placetype":"venue"
},
  "geometry": {"coordinates":[-118.23279599999999,34.660128],"type":"Point"}
}