{
  "type": "Feature",
  "properties": {
    "iso:country":"US",
    "sg:address":"11518 Elbow Rd",
    "sg:city":"Morongo Valley",
    "sg:classifiers":[
        {
            "category":"Organizations",
            "subcategory":"Religious Organization",
            "type":"Services"
        }
    ],
    "sg:phone":"+1 760 363 0046",
    "sg:postcode":"92256",
    "sg:province":"CA",
    "sg:tags":[
        "church"
    ],
    "wof:name":"Church Of The Lighted Cross",
    "wof:placetype":"venue"
},
  "geometry": {"coordinates":[-116.58694300000001,34.042712],"type":"Point"}
}