{
  "type": "Feature",
  "properties": {
    "iso:country":"US",
    "sg:address":"26856 State Hwy 189",
    "sg:city":"Blue Jay",
    "sg:classifiers":[
        {
            "category":"Insurance",
            "subcategory":"Insurance Agent",
            "type":"Services"
        }
    ],
    "sg:phone":"+1 909 337 2518",
    "sg:postcode":"92407",
    "sg:province":"CA",
    "sg:website":"www.ritapriceinsurance.com",
    "wof:name":"Rita M Price Insurance",
    "wof:placetype":"venue"
},
  "geometry": {"coordinates":[-117.218174,34.238449],"type":"Point"}
}