{
  "type": "Feature",
  "properties": {
    "iso:country":"US",
    "sg:address":"1741 E 7th St",
    "sg:city":"Long Beach",
    "sg:classifiers":[
        {
            "category":"Wholesale",
            "subcategory":"Hardware",
            "type":"Manufacturing & Wholesale Goods"
        }
    ],
    "sg:phone":"+1 562 218 3562",
    "sg:postcode":"90813",
    "sg:province":"CA",
    "sg:tags":[
        "plumbing"
    ],
    "wof:name":"Genesis Agua",
    "wof:placetype":"venue"
},
  "geometry": {"coordinates":[-118.170193,33.775417],"type":"Point"}
}