{
  "type": "Feature",
  "properties": {
    "addr:full":"2670 S White Road Suite 250 San Jose CA 95148",
    "addr:housenumber":"2670",
    "addr:postcode":"95148",
    "addr:street":"S White Road Suite 250",
    "iso:country":"US",
    "sg:address":"2670 S White Road Suite 250",
    "sg:city":"San Jose",
    "sg:classifiers":[
        {
            "category":"Banks & Credit Unions",
            "subcategory":"Financial Services",
            "type":"Services"
        }
    ],
    "sg:phone":"+1 408 223 3555",
    "sg:postcode":"95148",
    "sg:province":"CA",
    "sg:tags":[
        "broker",
        "mortgage"
    ],
    "wof:name":"Silver Creek Financial",
    "wof:placetype":"venue"
},
  "geometry": {"coordinates":[-121.798455,37.329653],"type":"Point"}
}