{
  "type": "Feature",
  "properties": {
    "iso:country":"US",
    "sg:address":"401 Scott Pl",
    "sg:city":"Pasadena",
    "sg:classifiers":[
        {
            "category":"Building & Trades",
            "subcategory":"Landscaping Services",
            "type":"Services"
        }
    ],
    "sg:phone":"+1 626 796 0580",
    "sg:postcode":"91103",
    "sg:province":"CA",
    "sg:tags":[
        "landscape"
    ],
    "wof:name":"Tanabe Design & Landscape Inc",
    "wof:placetype":"venue"
},
  "geometry": {"coordinates":[-118.160611,34.153191],"type":"Point"}
}