{
  "type": "Feature",
  "properties": {
    "addr:full":"14042 Luna Rd Victorville CA 92392",
    "addr:housenumber":"14042",
    "addr:postcode":"92392",
    "addr:street":"Luna Rd",
    "iso:country":"US",
    "sg:address":"14042 Luna Rd",
    "sg:city":"Victorville",
    "sg:classifiers":[
        {
            "category":"Freight",
            "type":"Transportation"
        }
    ],
    "sg:phone":"+1 760 951 2934",
    "sg:postcode":"92392",
    "sg:province":"CA",
    "sg:tags":[
        "operator",
        "local",
        "trucking"
    ],
    "wof:name":"Keen & Sons Trucking",
    "wof:placetype":"venue"
},
  "geometry": {"coordinates":[-117.35666999999999,34.492288],"type":"Point"}
}