{
  "type": "Feature",
  "properties": {
    "iso:country":"US",
    "sg:address":"740 N 2nd St",
    "sg:city":"San Jose",
    "sg:classifiers":[
        {
            "category":"Shopping",
            "subcategory":"Discount & Variety Stores",
            "type":"Retail Goods"
        }
    ],
    "sg:phone":"+1 408 293 5575",
    "sg:postcode":"95112",
    "sg:province":"CA",
    "sg:tags":[
        "merchandise",
        "general"
    ],
    "wof:name":"Datanet Sales",
    "wof:placetype":"venue"
},
  "geometry": {"coordinates":[-121.90009,37.350898],"type":"Point"}
}