{
  "type": "Feature",
  "properties": {
    "addr:full":"350 South El Portal Encinitas CA 92024",
    "addr:housenumber":"350",
    "addr:postcode":"92024",
    "addr:street":"South El Portal",
    "iso:country":"US",
    "sg:address":"350 South El Portal",
    "sg:city":"Encinitas",
    "sg:classifiers":[
        {
            "category":"Recreation",
            "subcategory":"Water Park",
            "type":"Entertainment"
        }
    ],
    "sg:postcode":"92024",
    "sg:province":"CA",
    "sg:tags":[
        "beach"
    ],
    "sg:website":"www.ci.encinitas.ca.us/CE/Govern...",
    "wof:name":"Stonesteps Beach",
    "wof:placetype":"venue"
},
  "geometry": {"coordinates":[-117.30058699999999,33.054799],"type":"Point"}
}