{
  "type": "Feature",
  "properties": {
    "addr:full":"233 Southwind Dr Pleasant Hill CA 94523",
    "addr:housenumber":"233",
    "addr:postcode":"94523",
    "addr:street":"Southwind Dr",
    "iso:country":"US",
    "sg:address":"233 Southwind Dr",
    "sg:city":"Pleasant Hill",
    "sg:classifiers":[
        {
            "category":"Professional",
            "subcategory":"Management & Consulting",
            "type":"Services"
        }
    ],
    "sg:phone":"+1 925 370 2013",
    "sg:postcode":"94523",
    "sg:province":"CA",
    "sg:tags":[
        "consultant",
        "educational"
    ],
    "wof:name":"Education Credit Corp",
    "wof:placetype":"venue"
},
  "geometry": {"coordinates":[-122.096964,37.970862],"type":"Point"}
}