{
  "type": "Feature",
  "properties": {
    "addr:full":"18349 Robscott Ave Hayward CA 94541",
    "addr:postcode":"18349;94541",
    "addr:street":"Robscott Ave",
    "iso:country":"US",
    "sg:address":"18349 Robscott Ave",
    "sg:city":"Hayward",
    "sg:classifiers":[
        {
            "category":"Health Services",
            "subcategory":"Nursing And Care Facility",
            "type":"Services"
        }
    ],
    "sg:phone":"+1 510 317 9091",
    "sg:postcode":"94541",
    "sg:province":"CA",
    "sg:tags":[
        "home",
        "retirement",
        "community"
    ],
    "wof:name":"Mariana Family Home",
    "wof:placetype":"venue"
},
  "geometry": {"coordinates":[-122.12128300000001,37.672885],"type":"Point"}
}