{
  "type": "Feature",
  "properties": {
    "addr:full":"14797 Hwy 76 Pauma Valley CA 92061",
    "addr:housenumber":"14797",
    "addr:postcode":"92061",
    "addr:street":"Hwy 76",
    "iso:country":"US",
    "sg:address":"14797 Hwy 76",
    "sg:city":"Pauma Valley",
    "sg:classifiers":[
        {
            "category":"Farming",
            "subcategory":"Orchard",
            "type":"Manufacturing & Wholesale Goods"
        }
    ],
    "sg:phone":"+1 760 742 3614",
    "sg:postcode":"92061",
    "sg:province":"CA",
    "sg:tags":[
        "fruit",
        "tree"
    ],
    "wof:name":"Bar 2 Ranch",
    "wof:placetype":"venue"
},
  "geometry": {"coordinates":[-117.01243100000001,33.340312],"type":"Point"}
}