{
  "type": "Feature",
  "properties": {
    "addr:full":"926 Soquel Ave Santa Cruz CA 95062",
    "addr:housenumber":"926",
    "addr:postcode":"95062",
    "addr:street":"Soquel Ave",
    "iso:country":"US",
    "sg:address":"926 Soquel Ave",
    "sg:city":"Santa Cruz",
    "sg:classifiers":[
        {
            "category":"Home & Garden",
            "subcategory":"Household Appliances",
            "type":"Retail Goods"
        }
    ],
    "sg:phone":"+1 831 427 3004",
    "sg:postcode":"95062",
    "sg:province":"CA",
    "sg:tags":[
        "machine",
        "sewing"
    ],
    "wof:name":"Santa Cruz Sewing Machines",
    "wof:placetype":"venue"
},
  "geometry": {"coordinates":[-122.013234,36.978318],"type":"Point"}
}