{
  "type": "Feature",
  "properties": {
    "iso:country":"US",
    "sg:address":"327 Moffett Blvd",
    "sg:city":"Mountain View",
    "sg:classifiers":[
        {
            "category":"Personal",
            "subcategory":"Beauty Salon",
            "type":"Services"
        }
    ],
    "sg:phone":"+1 650 961 9388",
    "sg:postcode":"94043",
    "sg:province":"CA",
    "wof:name":"Simply Unique Hair Designs",
    "wof:placetype":"venue"
},
  "geometry": {"coordinates":[-122.075434,37.398535],"type":"Point"}
}