{
  "type": "Feature",
  "properties": {
    "addr:full":"200 N Glendora Ave Glendora CA 91741",
    "addr:housenumber":"200",
    "addr:postcode":"91741",
    "addr:street":"N Glendora Ave",
    "iso:country":"US",
    "sg:address":"200 N Glendora Ave",
    "sg:city":"Glendora",
    "sg:classifiers":[
        {
            "category":"Professional",
            "subcategory":"Management & Consulting",
            "type":"Services"
        }
    ],
    "sg:phone":"+1 626 914 6848",
    "sg:postcode":"91741",
    "sg:province":"CA",
    "sg:tags":[
        "consultant",
        "lighting"
    ],
    "sg:website":"www.thinkpositiveenergy.com",
    "wof:name":"Positive Energy",
    "wof:placetype":"venue"
},
  "geometry": {"coordinates":[-117.86543899999999,34.139071],"type":"Point"}
}