{
  "type": "Feature",
  "properties": {
    "iso:country":"US",
    "sg:address":"17671 Irvine Blvd",
    "sg:city":"Tustin",
    "sg:classifiers":[
        {
            "category":"Wholesale",
            "subcategory":"Electrical",
            "type":"Manufacturing & Wholesale Goods"
        }
    ],
    "sg:phone":"+1 714 368 0357",
    "sg:postcode":"92780",
    "sg:province":"CA",
    "sg:tags":[
        "computer",
        "electronic",
        "related"
    ],
    "wof:name":"Strata Technologies LLC",
    "wof:placetype":"venue"
},
  "geometry": {"coordinates":[-117.82352,33.748324],"type":"Point"}
}