{
  "type": "Feature",
  "properties": {
    "iso:country":"US",
    "sg:address":"18023 Sky Park Cir",
    "sg:city":"Irvine",
    "sg:classifiers":[
        {
            "category":"Building & Trades",
            "subcategory":"Construction",
            "type":"Services"
        }
    ],
    "sg:phone":"+1 949 660 7979",
    "sg:postcode":"92614",
    "sg:province":"CA",
    "sg:tags":[
        "interior",
        "design"
    ],
    "wof:name":"Chameleon Design",
    "wof:placetype":"venue"
},
  "geometry": {"coordinates":[-117.856695,33.687696],"type":"Point"}
}