{
  "type": "Feature",
  "properties": {
    "addr:full":"14970 Don Julian Rd City Of Industry CA 91746",
    "addr:housenumber":"14970",
    "addr:postcode":"91746",
    "addr:street":"Don Julian Rd",
    "iso:country":"US",
    "sg:address":"14970 Don Julian Rd",
    "sg:city":"City Of Industry",
    "sg:classifiers":[
        {
            "category":"Manufacturing",
            "subcategory":"Food",
            "type":"Manufacturing & Wholesale Goods"
        }
    ],
    "sg:phone":"+1 626 961 8911",
    "sg:postcode":"91746",
    "sg:province":"CA",
    "sg:tags":[
        "mayonnaise",
        "salad",
        "dressing"
    ],
    "sg:website":"www.venturafoods.com",
    "wof:name":"Ventura Foods",
    "wof:placetype":"venue"
},
  "geometry": {"coordinates":[-117.974777,34.025033],"type":"Point"}
}