{
  "type": "Feature",
  "properties": {
    "iso:country":"US",
    "sg:address":"20320 Redwood Rd",
    "sg:city":"Castro Valley",
    "sg:classifiers":[
        {
            "category":"Professional",
            "subcategory":"Lawyer & Legal Services",
            "type":"Services"
        }
    ],
    "sg:phone":"+1 510 881 5026",
    "sg:postcode":"94546",
    "sg:province":"CA",
    "wof:name":"Woidtke Jay A Atty",
    "wof:placetype":"venue"
},
  "geometry": {"coordinates":[-122.07399700000001,37.697701],"type":"Point"}
}