{
  "type": "Feature",
  "properties": {
    "addr:full":"1702 Willowside Rd Santa Rosa CA 95401",
    "addr:housenumber":"1702",
    "addr:postcode":"95401",
    "addr:street":"Willowside Rd",
    "iso:country":"US",
    "sg:address":"1702 Willowside Rd",
    "sg:city":"Santa Rosa",
    "sg:classifiers":[
        {
            "category":"Manufacturing",
            "subcategory":"Building Materials",
            "type":"Manufacturing & Wholesale Goods"
        }
    ],
    "sg:phone":"+1 707 546 9359",
    "sg:postcode":"95401",
    "sg:province":"CA",
    "sg:tags":[
        "mfg"
    ],
    "wof:name":"Sonoma Millwork & Design",
    "wof:placetype":"venue"
},
  "geometry": {"coordinates":[-122.80674999999999,38.460765],"type":"Point"}
}