{
  "type": "Feature",
  "properties": {
    "addr:full":"304 Pearson Ave Bakersfield CA 93308",
    "addr:housenumber":"304",
    "addr:postcode":"93308",
    "addr:street":"Pearson Ave",
    "iso:country":"US",
    "sg:address":"304 Pearson Ave",
    "sg:city":"Bakersfield",
    "sg:classifiers":[
        {
            "category":"Building & Trades",
            "subcategory":"Electrical",
            "type":"Services"
        }
    ],
    "sg:phone":"+1 661 399 3950",
    "sg:postcode":"93308",
    "sg:province":"CA",
    "sg:tags":[
        "electrician",
        "contractor"
    ],
    "wof:name":"Twin Electric",
    "wof:placetype":"venue"
},
  "geometry": {"coordinates":[-119.01652300000001,35.413318],"type":"Point"}
}