{
  "type": "Feature",
  "properties": {
    "iso:country":"US",
    "sg:address":"16606 Crenshaw Blvd",
    "sg:city":"Torrance",
    "sg:classifiers":[
        {
            "category":"Wholesale",
            "subcategory":"Home Furnishings",
            "type":"Manufacturing & Wholesale Goods"
        },
        {
            "category":"Home & Garden",
            "subcategory":"Carpets & Floor Coverings",
            "type":"Retail Goods"
        }
    ],
    "sg:phone":"+1 310 354 3001",
    "sg:postcode":"90504",
    "sg:province":"CA",
    "sg:tags":[
        "blind",
        "shade",
        "carpeting"
    ],
    "wof:name":"Ron's Floor Coverings",
    "wof:placetype":"venue"
},
  "geometry": {"coordinates":[-118.32637800000001,33.879826],"type":"Point"}
}