{
  "type": "Feature",
  "properties": {
    "iso:country":"US",
    "sg:address":"28141 Crown Valley Pkwy",
    "sg:city":"Laguna Niguel",
    "sg:classifiers":[
        {
            "category":"Restaurant",
            "type":"Food & Drink"
        }
    ],
    "sg:phone":"+1 949 362 9770",
    "sg:postcode":"92677",
    "sg:province":"CA",
    "sg:website":"www.tgifridays.com",
    "wof:name":"Friday's",
    "wof:placetype":"venue"
},
  "geometry": {"coordinates":[-117.691511,33.543601],"type":"Point"}
}