{
  "type": "Feature",
  "properties": {
    "addr:full":"14834 San Fernando Rd Sylmar CA 91342",
    "addr:housenumber":"14834",
    "addr:postcode":"91342",
    "addr:street":"San Fernando Rd",
    "iso:country":"US",
    "sg:address":"14834 San Fernando Rd",
    "sg:city":"Sylmar",
    "sg:classifiers":[
        {
            "category":"Manufacturing",
            "subcategory":"Wood Products",
            "type":"Manufacturing & Wholesale Goods"
        }
    ],
    "sg:phone":"+1 818 833 0680",
    "sg:postcode":"91342",
    "sg:province":"CA",
    "sg:tags":[
        "firewood"
    ],
    "wof:name":"Sonora & Vega Firewood",
    "wof:placetype":"venue"
},
  "geometry": {"coordinates":[-118.503478,34.324706],"type":"Point"}
}