{
  "type": "Feature",
  "properties": {
    "iso:country":"US",
    "sg:address":"315 N Harold St",
    "sg:city":"Fort Bragg",
    "sg:classifiers":[
        {
            "category":"Retail",
            "subcategory":"Laundry & Dry Cleaning",
            "type":"Services"
        }
    ],
    "sg:phone":"+1 707 964 2846",
    "sg:postcode":"95437",
    "sg:province":"CA",
    "sg:tags":[
        "cleaners",
        "rug",
        "carpet"
    ],
    "wof:name":"A1 Carpet Cleaners",
    "wof:placetype":"venue"
},
  "geometry": {"coordinates":[-123.798092,39.445286],"type":"Point"}
}