{
  "type": "Feature",
  "properties": {
    "addr:full":"1358 Fairmont Dr San Leandro CA 94578",
    "addr:housenumber":"1358",
    "addr:postcode":"94578",
    "addr:street":"Fairmont Dr",
    "iso:country":"US",
    "sg:address":"1358 Fairmont Dr",
    "sg:city":"San Leandro",
    "sg:classifiers":[
        {
            "category":"Manufacturing",
            "subcategory":"Printing",
            "type":"Manufacturing & Wholesale Goods"
        }
    ],
    "sg:phone":"+1 510 276 6456",
    "sg:postcode":"94578",
    "sg:province":"CA",
    "sg:tags":[
        "copy",
        "offset"
    ],
    "wof:name":"Copy-N-Print",
    "wof:placetype":"venue"
},
  "geometry": {"coordinates":[-122.12599899999999,37.703098],"type":"Point"}
}