{
  "type": "Feature",
  "properties": {
    "addr:full":"101 California St Ste 950 San Francisco CA 94111",
    "addr:housenumber":"101",
    "addr:postcode":"94111",
    "addr:street":"California St Ste 950",
    "iso:country":"US",
    "sg:address":"101 California St Ste 950",
    "sg:city":"San Francisco",
    "sg:classifiers":[
        {
            "category":"Professional",
            "subcategory":"Employment Agencies",
            "type":"Services"
        }
    ],
    "sg:phone":"+1 415 403 9000",
    "sg:postcode":"94111",
    "sg:province":"CA",
    "sg:website":"www.visuals.com",
    "wof:name":"Visuals",
    "wof:placetype":"venue"
},
  "geometry": {"coordinates":[-122.397564,37.793446],"type":"Point"}
}