{
  "type": "Feature",
  "properties": {
    "iso:country":"US",
    "sg:address":"5988 Silver Creek Valley Rd Ste 60",
    "sg:city":"San Jose",
    "sg:classifiers":[
        {
            "category":"Education",
            "subcategory":"Special Training",
            "type":"Public Place"
        }
    ],
    "sg:phone":"+1 408 270 4548",
    "sg:postcode":"95138",
    "sg:province":"CA",
    "sg:tags":[
        "tutoring"
    ],
    "wof:name":"Pinecone Active Learning",
    "wof:placetype":"venue"
},
  "geometry": {"coordinates":[-121.784871,37.258062],"type":"Point"}
}