{
  "type": "Feature",
  "properties": {
    "addr:full":"10331 Lakewood Blvd Downey CA 90241",
    "addr:housenumber":"10331",
    "addr:postcode":"90241",
    "addr:street":"Lakewood Blvd",
    "iso:country":"US",
    "sg:address":"10331 Lakewood Blvd",
    "sg:city":"Downey",
    "sg:classifiers":[
        {
            "category":"Retail",
            "subcategory":"Repair Shop",
            "type":"Services"
        }
    ],
    "sg:phone":"+1 562 861 0006",
    "sg:postcode":"90241",
    "sg:province":"CA",
    "sg:tags":[
        "lock",
        "locksmith"
    ],
    "wof:name":"A 1 Action Lock & Key Svc",
    "wof:placetype":"venue"
},
  "geometry": {"coordinates":[-118.118494,33.945083],"type":"Point"}
}