{
  "type": "Feature",
  "properties": {
    "addr:full":"625 Las Tunas Dr Arcadia CA 91007",
    "addr:housenumber":"625",
    "addr:postcode":"91007",
    "addr:street":"Las Tunas Dr",
    "iso:country":"US",
    "sg:address":"625 Las Tunas Dr",
    "sg:city":"Arcadia",
    "sg:classifiers":[
        {
            "category":"Autos & Motor Vehicles",
            "subcategory":"Fuel & Gas Station",
            "type":"Retail Goods"
        }
    ],
    "sg:phone":"+1 626 447 2067",
    "sg:postcode":"91007",
    "sg:province":"CA",
    "wof:name":"ampm",
    "wof:placetype":"venue"
},
  "geometry": {"coordinates":[-118.152018,34.10764],"type":"Point"}
}