{
  "type": "Feature",
  "properties": {
    "iso:country":"US",
    "sg:address":"965 Mission St Ste 350",
    "sg:city":"San Francisco",
    "sg:classifiers":[
        {
            "category":"Arts & Performance",
            "subcategory":"Arts Center",
            "type":"Entertainment"
        }
    ],
    "sg:phone":"+1 415 690 7658",
    "sg:postcode":"94103",
    "sg:province":"CA",
    "sg:website":"www.roltheatre.com/",
    "wof:name":"Ray of Light Theatre",
    "wof:placetype":"venue"
},
  "geometry": {"coordinates":[-122.40754699999999,37.78141],"type":"Point"}
}