{
  "type": "Feature",
  "properties": {
    "addr:full":"781 Los Osos Valley Rd Los Osos CA 93402",
    "addr:housenumber":"781",
    "addr:postcode":"93402",
    "addr:street":"Los Osos Valley Rd",
    "iso:country":"US",
    "sg:address":"781 Los Osos Valley Rd",
    "sg:city":"Los Osos",
    "sg:classifiers":[
        {
            "category":"Organizations",
            "subcategory":"Professional Association",
            "type":"Services"
        }
    ],
    "sg:phone":"+1 805 528 4884",
    "sg:postcode":"93402",
    "sg:province":"CA",
    "sg:tags":[
        "chambers",
        "commerce"
    ],
    "wof:name":"Los Osos Chamber Of Commerce",
    "wof:placetype":"venue"
},
  "geometry": {"coordinates":[-120.83730799999999,35.311847],"type":"Point"}
}