{
  "type": "Feature",
  "properties": {
    "iso:country":"US",
    "sg:address":"1601 Cortland Avenue",
    "sg:city":"San Francisco",
    "sg:classifiers":[
        {
            "category":"Building & Trades",
            "subcategory":"Construction",
            "type":"Services"
        }
    ],
    "sg:phone":"+1 415 647 4010",
    "sg:postcode":"94110",
    "sg:province":"CA",
    "sg:tags":[
        "contractor"
    ],
    "wof:name":"A Ruiz Construction",
    "wof:placetype":"venue"
},
  "geometry": {"coordinates":[-122.40867,37.739782],"type":"Point"}
}