{
  "type": "Feature",
  "properties": {
    "addr:full":"1700 McHenry Ave Ste 66C Modesto CA 95350",
    "addr:housenumber":"1700",
    "addr:postcode":"ca 95350",
    "addr:street":"Mchenry Ave Ste 66C",
    "iso:country":"US",
    "sg:address":"1700 McHenry Ave Ste 66C",
    "sg:city":"Modesto",
    "sg:classifiers":[
        {
            "category":"Sports & Exercise",
            "subcategory":"Gym",
            "type":"Entertainment"
        }
    ],
    "sg:phone":"+1 209 578 5441",
    "sg:postcode":"95350",
    "sg:province":"CA",
    "sg:tags":[
        "yoga"
    ],
    "wof:name":"Village Yoga Center",
    "wof:placetype":"venue"
},
  "geometry": {"coordinates":[-120.99400300000001,37.6688],"type":"Point"}
}