{
  "type": "Feature",
  "properties": {
    "addr:full":"1313 N Carolan Ave Burlingame CA 94010",
    "addr:housenumber":"1313",
    "addr:postcode":"94010",
    "addr:street":"N Carolan Ave",
    "iso:country":"US",
    "sg:address":"1313 N Carolan Ave",
    "sg:city":"Burlingame",
    "sg:classifiers":[
        {
            "category":"Building & Trades",
            "subcategory":"Cleaning & Sanitation",
            "type":"Services"
        }
    ],
    "sg:phone":"+1 650 347 8242",
    "sg:postcode":"94010",
    "sg:province":"CA",
    "sg:tags":[
        "chemical"
    ],
    "wof:name":"Aldran Chemical Inc",
    "wof:placetype":"venue"
},
  "geometry": {"coordinates":[-122.36902000000001,37.591092],"type":"Point"}
}