{
  "type": "Feature",
  "properties": {
    "iso:country":"US",
    "sg:address":"108 University Ave",
    "sg:city":"San Diego",
    "sg:classifiers":[
        {
            "category":"Organizations",
            "subcategory":"Non-profit Organization",
            "type":"Services"
        }
    ],
    "sg:phone":"+1 619 298 7050",
    "sg:postcode":"92103",
    "sg:province":"CA",
    "sg:tags":[
        "social"
    ],
    "wof:name":"Operation School Bell",
    "wof:placetype":"venue"
},
  "geometry": {"coordinates":[-117.163376,32.748316],"type":"Point"}
}