{
  "type": "Feature",
  "properties": {
    "iso:country":"US",
    "sg:address":"32100 Avalon Ln",
    "sg:city":"Menifee",
    "sg:classifiers":[
        {
            "category":"Professional",
            "subcategory":"Management & Consulting",
            "type":"Services"
        }
    ],
    "sg:phone":"+1 951 672 1838",
    "sg:postcode":"92584",
    "sg:province":"CA",
    "sg:tags":[
        "consultant",
        "educational"
    ],
    "wof:name":"Imagination Unlimited Group",
    "wof:placetype":"venue"
},
  "geometry": {"coordinates":[-117.14747,33.65422],"type":"Point"}
}