{
  "type": "Feature",
  "properties": {
    "addr:full":"3658 W 139th St Hawthorne CA 90250",
    "addr:housenumber":"3658",
    "addr:postcode":"90250",
    "addr:street":"W 139Th St",
    "iso:country":"US",
    "sg:address":"3658 W 139th St",
    "sg:city":"Hawthorne",
    "sg:classifiers":[
        {
            "category":"Building & Trades",
            "subcategory":"Construction",
            "type":"Services"
        }
    ],
    "sg:phone":"+1 310 973 4642",
    "sg:postcode":"90250",
    "sg:province":"CA",
    "sg:tags":[
        "maker",
        "cabinet"
    ],
    "wof:name":"Salmon Custom Cabinetry",
    "wof:placetype":"venue"
},
  "geometry": {"coordinates":[-118.337236,33.905482],"type":"Point"}
}