{
  "type": "Feature",
  "properties": {
    "iso:country":"US",
    "sg:address":"159 Washington Blvd",
    "sg:city":"Fremont",
    "sg:classifiers":[
        {
            "category":"Organizations",
            "subcategory":"Religious Organization",
            "type":"Services"
        }
    ],
    "sg:phone":"+1 510 624 4500",
    "sg:postcode":"94539",
    "sg:province":"CA",
    "sg:tags":[
        "monastery",
        "convent"
    ],
    "wof:name":"Sisters Of The Holy Family",
    "wof:placetype":"venue"
},
  "geometry": {"coordinates":[-121.920779,37.533411],"type":"Point"}
}