{
  "type": "Feature",
  "properties": {
    "addr:full":"134 Weeks Way Sebastopol CA 95472",
    "addr:housenumber":"134",
    "addr:postcode":"95472",
    "addr:street":"Weeks Way",
    "iso:country":"US",
    "sg:address":"134 Weeks Way",
    "sg:city":"Sebastopol",
    "sg:classifiers":[
        {
            "category":"Wholesale",
            "subcategory":"Medical Equipment & Supplies",
            "type":"Manufacturing & Wholesale Goods"
        }
    ],
    "sg:phone":"+1 800 834 5640",
    "sg:postcode":"95472",
    "sg:province":"CA",
    "sg:tags":[
        "assistive",
        "aid",
        "device",
        "hearing"
    ],
    "wof:name":"In-Home Hearing AID Services",
    "wof:placetype":"venue"
},
  "geometry": {"coordinates":[-122.823933,38.40309],"type":"Point"}
}