{
  "type": "Feature",
  "properties": {
    "addr:full":"1017 S Montebello Blvd Montebello CA 90640",
    "addr:housenumber":"1017",
    "addr:postcode":"90640",
    "addr:street":"S Montebello Blvd",
    "iso:country":"US",
    "sg:address":"1017 S Montebello Blvd",
    "sg:city":"Montebello",
    "sg:classifiers":[
        {
            "category":"Shopping",
            "type":"Retail Goods"
        }
    ],
    "sg:phone":"+1 323 728 0613",
    "sg:postcode":"90640",
    "sg:province":"CA",
    "sg:tags":[
        "bird"
    ],
    "wof:name":"K & H Birds",
    "wof:placetype":"venue"
},
  "geometry": {"coordinates":[-118.117,33.992734],"type":"Point"}
}