{
  "type": "Feature",
  "properties": {
    "iso:country":"US",
    "sg:address":"14 Westminster Ave",
    "sg:city":"Venice",
    "sg:classifiers":[
        {
            "category":"Personal",
            "type":"Services"
        }
    ],
    "sg:phone":"+1 310 399 1390",
    "sg:postcode":"90291",
    "sg:province":"CA",
    "sg:tags":[
        "control",
        "weight"
    ],
    "wof:name":"Herbalife Distributor",
    "wof:placetype":"venue"
},
  "geometry": {"coordinates":[-118.47360500000001,33.98931],"type":"Point"}
}