{
  "type": "Feature",
  "properties": {
    "addr:full":"7932 Sunset Ave Ste I Fair Oaks CA 95628",
    "addr:housenumber":"7932",
    "addr:postcode":"95628",
    "addr:street":"Sunset Ave Ste I",
    "iso:country":"US",
    "sg:address":"7932 Sunset Ave Ste I",
    "sg:city":"Fair Oaks",
    "sg:classifiers":[
        {
            "category":"Building & Trades",
            "subcategory":"Cleaning & Sanitation",
            "type":"Services"
        },
        {
            "category":"Social Services",
            "subcategory":"Child Care",
            "type":"Services"
        }
    ],
    "sg:phone":"+1 916 985 7676",
    "sg:postcode":"95628",
    "sg:province":"CA",
    "sg:tags":[
        "home",
        "day"
    ],
    "wof:name":"Panda's Complete Domestic Agency",
    "wof:placetype":"venue"
},
  "geometry": {"coordinates":[-121.272037,38.652373],"type":"Point"}
}