{
  "type": "Feature",
  "properties": {
    "addr:full":"334 Main St Vista CA 92084",
    "addr:housenumber":"334",
    "addr:postcode":"92084",
    "addr:street":"Main St",
    "iso:country":"US",
    "sg:address":"334 Main St",
    "sg:city":"Vista",
    "sg:classifiers":[
        {
            "category":"Professional",
            "subcategory":"Business Services",
            "type":"Services"
        }
    ],
    "sg:phone":"+1 760 945 5353",
    "sg:postcode":"92084",
    "sg:province":"CA",
    "sg:tags":[
        "foreground",
        "music"
    ],
    "wof:name":"Karaoke Systems Plus",
    "wof:placetype":"venue"
},
  "geometry": {"coordinates":[-117.241193,33.203754],"type":"Point"}
}