{
  "type": "Feature",
  "properties": {
    "iso:country":"US",
    "sg:address":"1029 McHenry Ave",
    "sg:city":"Modesto",
    "sg:classifiers":[
        {
            "category":"Health Services",
            "subcategory":"Doctor",
            "type":"Services"
        }
    ],
    "sg:phone":"+1 209 522 9054",
    "sg:postcode":"95350",
    "sg:province":"CA",
    "sg:tags":[
        "practice",
        "family"
    ],
    "wof:name":"Freitas M F Fnp-C PA-C",
    "wof:placetype":"venue"
},
  "geometry": {"coordinates":[-120.99400300000001,37.657501],"type":"Point"}
}