{
  "type": "Feature",
  "properties": {
    "iso:country":"US",
    "sg:address":"2245 E 38th St",
    "sg:city":"Los Angeles",
    "sg:classifiers":[
        {
            "category":"Home & Garden",
            "subcategory":"Home Furnishings",
            "type":"Retail Goods"
        }
    ],
    "sg:phone":"+1 323 584 7300",
    "sg:postcode":"90058",
    "sg:province":"CA",
    "sg:tags":[
        "curtain",
        "made",
        "drapery"
    ],
    "wof:name":"Schwimmer Drapery",
    "wof:placetype":"venue"
},
  "geometry": {"coordinates":[-118.235621,34.008136],"type":"Point"}
}