{
  "type": "Feature",
  "properties": {
    "addr:full":"39550 Liberty St Fremont CA 94538",
    "addr:housenumber":"39550",
    "addr:postcode":"94538",
    "addr:street":"Liberty St",
    "iso:country":"US",
    "sg:address":"39550 Liberty St",
    "sg:city":"Fremont",
    "sg:classifiers":[
        {
            "category":"Government",
            "subcategory":"Office",
            "type":"Public Place"
        }
    ],
    "sg:phone":"+1 510 494 4792",
    "sg:postcode":"94538",
    "sg:province":"CA",
    "sg:tags":[
        "city",
        "taxation"
    ],
    "wof:name":"Treasury Division",
    "wof:placetype":"venue"
},
  "geometry": {"coordinates":[-121.97659,37.548209],"type":"Point"}
}