{
  "type": "Feature",
  "properties": {
    "addr:full":"8460 Baldwin St Oakland CA 94621",
    "addr:housenumber":"8460",
    "addr:postcode":"94621",
    "addr:street":"Baldwin St",
    "iso:country":"US",
    "sg:address":"8460 Baldwin St",
    "sg:city":"Oakland",
    "sg:classifiers":[
        {
            "category":"Building & Trades",
            "subcategory":"Construction",
            "type":"Services"
        }
    ],
    "sg:phone":"+1 510 430 9996",
    "sg:postcode":"94621",
    "sg:province":"CA",
    "sg:tags":[
        "wallcoverings-installation",
        "wallpaper",
        "painting",
        "contractor"
    ],
    "wof:name":"Blumert Walter & Co Painters &",
    "wof:placetype":"venue"
},
  "geometry": {"coordinates":[-122.19185,37.74458],"type":"Point"}
}