{
  "type": "Feature",
  "properties": {
    "iso:country":"US",
    "sg:address":"1608 Hillhurst Ave",
    "sg:city":"Los Angeles",
    "sg:classifiers":[
        {
            "category":"Retail",
            "subcategory":"Auto Rental",
            "type":"Services"
        }
    ],
    "sg:phone":"+1 323 660 2311",
    "sg:postcode":"90027",
    "sg:province":"CA",
    "sg:tags":[
        "renting",
        "car",
        "automobile"
    ],
    "wof:name":"Enterprise Rent-A-Car",
    "wof:placetype":"venue"
},
  "geometry": {"coordinates":[-118.28704399999999,34.100284],"type":"Point"}
}