{
  "type": "Feature",
  "properties": {
    "addr:full":"8341 Fair Oaks Blvd Carmichael CA 95608",
    "addr:housenumber":"8341",
    "addr:postcode":"95608",
    "addr:street":"Fair Oaks Blvd",
    "iso:country":"US",
    "sg:address":"8341 Fair Oaks Blvd",
    "sg:city":"Carmichael",
    "sg:classifiers":[
        {
            "category":"Professional",
            "subcategory":"Lawyer & Legal Services",
            "type":"Services"
        }
    ],
    "sg:phone":"+1 916 944 0055",
    "sg:postcode":"95608",
    "sg:province":"CA",
    "sg:website":"www.lmlawsf.com",
    "wof:name":"Leach & McGreevy, LLP",
    "wof:placetype":"venue"
},
  "geometry": {"coordinates":[-121.308515,38.636543],"type":"Point"}
}