{
  "type": "Feature",
  "properties": {
    "addr:full":"4010 Moratalla Ter San Diego CA 92130",
    "addr:housenumber":"4010",
    "addr:postcode":"92130",
    "addr:street":"Moratalla Ter",
    "iso:country":"US",
    "sg:address":"4010 Moratalla Ter",
    "sg:city":"San Diego",
    "sg:classifiers":[
        {
            "category":"Retail",
            "subcategory":"Portrait Studio",
            "type":"Services"
        }
    ],
    "sg:phone":"+1 858 484 0088",
    "sg:postcode":"92130",
    "sg:province":"CA",
    "sg:tags":[
        "photographer"
    ],
    "wof:name":"Mark Frapwell Photography",
    "wof:placetype":"venue"
},
  "geometry": {"coordinates":[-117.22823200000001,32.945254],"type":"Point"}
}