{
  "type": "Feature",
  "properties": {
    "addr:full":"15250 Hesperian Blvd Ste 200 San Leandro CA 94578",
    "addr:housenumber":"15250",
    "addr:postcode":"94578",
    "addr:street":"Hesperian Blvd Ste 200",
    "iso:country":"US",
    "sg:address":"15250 Hesperian Blvd Ste 200",
    "sg:city":"San Leandro",
    "sg:classifiers":[
        {
            "category":"Banks & Credit Unions",
            "subcategory":"Bank",
            "type":"Services"
        }
    ],
    "sg:phone":"+1 510 278 4000",
    "sg:postcode":"94578",
    "sg:province":"CA",
    "wof:name":"State Farm",
    "wof:placetype":"venue"
},
  "geometry": {"coordinates":[-122.129997,37.696301],"type":"Point"}
}