{
  "type": "Feature",
  "properties": {
    "addr:full":"10915 Hawthorne Boulevard Inglewood CA 90304",
    "addr:housenumber":"10915",
    "addr:postcode":"90304",
    "addr:street":"Hawthorne Boulevard",
    "iso:country":"US",
    "sg:address":"10915 Hawthorne Boulevard",
    "sg:city":"Inglewood",
    "sg:classifiers":[
        {
            "category":"Retail",
            "subcategory":"Auto Repair",
            "type":"Services"
        }
    ],
    "sg:phone":"+1 310 674 5450",
    "sg:postcode":"90304",
    "sg:province":"CA",
    "sg:tags":[
        "body",
        "painting",
        "repairing",
        "automobile"
    ],
    "wof:name":"Sal's Body & Paint Shop",
    "wof:placetype":"venue"
},
  "geometry": {"coordinates":[-118.352538,33.936454],"type":"Point"}
}