{
  "type": "Feature",
  "properties": {
    "addr:full":"648 Menlo Ave Menlo Park CA 94025",
    "addr:housenumber":"648",
    "addr:postcode":"94025",
    "addr:street":"Menlo Ave",
    "iso:country":"US",
    "sg:address":"648 Menlo Ave",
    "sg:city":"Menlo Park",
    "sg:classifiers":[
        {
            "category":"Shopping",
            "subcategory":"Clothing, Apparel, & Fashions",
            "type":"Retail Goods"
        }
    ],
    "sg:phone":"+1 650 289 0908",
    "sg:postcode":"94025",
    "sg:province":"CA",
    "sg:tags":[
        "designer"
    ],
    "wof:name":"Boomba Boutique",
    "wof:placetype":"venue"
},
  "geometry": {"coordinates":[-122.182811,37.451809],"type":"Point"}
}