{
  "type": "Feature",
  "properties": {
    "addr:full":"619 S Atlantic Boulevard Los Angeles CA 90022",
    "addr:housenumber":"619",
    "addr:postcode":"90022",
    "addr:street":"S Atlantic Boulevard",
    "iso:country":"US",
    "sg:address":"619 S Atlantic Boulevard",
    "sg:city":"Los Angeles",
    "sg:classifiers":[
        {
            "category":"Food & Beverages",
            "subcategory":"Groceries & Convenience Stores",
            "type":"Retail Goods"
        }
    ],
    "sg:phone":"+1 323 268 0888",
    "sg:postcode":"90022",
    "sg:province":"CA",
    "wof:name":"Little Farmers Market",
    "wof:placetype":"venue"
},
  "geometry": {"coordinates":[-118.156201,34.023526],"type":"Point"}
}