{
  "type": "Feature",
  "properties": {
    "addr:full":"801 Turk Street San Francisco CA 94102",
    "addr:housenumber":"801",
    "addr:postcode":"94102",
    "addr:street":"Turk Street",
    "iso:country":"US",
    "sg:address":"801 Turk Street",
    "sg:city":"San Francisco",
    "sg:classifiers":[
        {
            "category":"Professional",
            "subcategory":"Employment Agencies",
            "type":"Services"
        }
    ],
    "sg:phone":"+1 415 749 7503",
    "sg:postcode":"94102",
    "sg:province":"CA",
    "sg:website":"www.onestopsf.org",
    "wof:name":"California State of",
    "wof:placetype":"venue"
},
  "geometry": {"coordinates":[-122.422997,37.781601],"type":"Point"}
}