{
  "type": "Feature",
  "properties": {
    "iso:country":"US",
    "sg:address":"121 Soquel Ave",
    "sg:city":"Santa Cruz",
    "sg:classifiers":[
        {
            "category":"Restaurant",
            "type":"Food & Drink"
        }
    ],
    "sg:phone":"+1 831 423 7427",
    "sg:postcode":"95060",
    "sg:province":"CA",
    "sg:tags":[
        "seafood"
    ],
    "sg:website":"www.oswaldrestaurant.com",
    "wof:name":"Oswald",
    "wof:placetype":"venue"
},
  "geometry": {"coordinates":[-122.02493800000001,36.973188],"type":"Point"}
}