{
  "type": "Feature",
  "properties": {
    "iso:country":"US",
    "sg:address":"6955 El Camino Real",
    "sg:city":"Carlsbad",
    "sg:classifiers":[
        {
            "category":"Bagels",
            "subcategory":"None",
            "type":"Food & Drink"
        }
    ],
    "sg:phone":"+1 760 929 8047",
    "sg:postcode":"92009",
    "sg:province":"CA",
    "wof:name":"Sun Flour Bagel",
    "wof:placetype":"venue"
},
  "geometry": {"coordinates":[-117.266792,33.103505],"type":"Point"}
}