{
  "type": "Feature",
  "properties": {
    "addr:full":"10299 Folsom Blvd Rancho Cordova CA 95670",
    "addr:housenumber":"10299",
    "addr:postcode":"95670",
    "addr:street":"Folsom Blvd",
    "iso:country":"US",
    "sg:address":"10299 Folsom Blvd",
    "sg:city":"Rancho Cordova",
    "sg:classifiers":[
        {
            "category":"Autos & Motor Vehicles",
            "subcategory":"Fuel & Gas Station",
            "type":"Retail Goods"
        }
    ],
    "sg:phone":"+1 916 369 1909",
    "sg:postcode":"95670",
    "sg:province":"CA",
    "sg:tags":[
        "oil"
    ],
    "wof:name":"United Petroleum",
    "wof:placetype":"venue"
},
  "geometry": {"coordinates":[-121.30835399999999,38.5864],"type":"Point"}
}