{
  "type": "Feature",
  "properties": {
    "iso:country":"US",
    "sg:address":"10299 Folsom Blvd",
    "sg:city":"Rancho Cordova",
    "sg:classifiers":[
        {
            "category":"Autos & Motor Vehicles",
            "subcategory":"Fuel & Gas Station",
            "type":"Retail Goods"
        }
    ],
    "sg:phone":"+1 916 369 1909",
    "sg:postcode":"95670",
    "sg:province":"CA",
    "sg:tags":[
        "oil"
    ],
    "wof:name":"United Petroleum",
    "wof:placetype":"venue"
},
  "geometry": {"coordinates":[-121.308354,38.5864],"type":"Point"}
}