{
  "type": "Feature",
  "properties": {
    "addr:full":"5670 Wilshire Blvd Ste 200 Los Angeles CA 90036",
    "addr:housenumber":"5670",
    "addr:postcode":"90036",
    "addr:street":"Wilshire Blvd Ste 200",
    "iso:country":"US",
    "sg:address":"5670 Wilshire Blvd Ste 200",
    "sg:city":"Los Angeles",
    "sg:classifiers":[
        {
            "category":"Communications",
            "subcategory":"Radio Station",
            "type":"Services"
        }
    ],
    "sg:phone":"+1 323 937 0226",
    "sg:postcode":"90036",
    "sg:province":"CA",
    "sg:website":"www.cbsradio.com",
    "wof:name":"CBS Radio",
    "wof:placetype":"venue"
},
  "geometry": {"coordinates":[-118.352172,34.219286],"type":"Point"}
}