{
  "type": "Feature",
  "properties": {
    "addr:full":"235 W McArthur Blvd Oakland CA 94611",
    "addr:housenumber":"235",
    "addr:postcode":"94611",
    "addr:street":"W Mcarthur Blvd",
    "iso:country":"US",
    "sg:address":"235 W McArthur Blvd",
    "sg:city":"Oakland",
    "sg:classifiers":[
        {
            "category":"Community Center",
            "type":"Public Place"
        }
    ],
    "sg:postcode":"94611",
    "sg:province":"CA",
    "sg:tags":[
        "medical"
    ],
    "wof:name":"Kaiser Occupational Health",
    "wof:placetype":"venue"
},
  "geometry": {"coordinates":[-122.258128,37.823259],"type":"Point"}
}