{
  "type": "Feature",
  "properties": {
    "iso:country":"US",
    "sg:address":"2257 Mason St",
    "sg:city":"San Francisco",
    "sg:classifiers":[
        {
            "category":"Restaurant",
            "type":"Food & Drink"
        }
    ],
    "sg:menulink":"http://www.allmenus.com/ca/san-francisco/49160-taqueria-san-jose--3/menu/",
    "sg:phone":"+1 415 749 0826",
    "sg:postcode":"94133",
    "sg:province":"CA",
    "sg:tags":[
        "mexican"
    ],
    "wof:name":"Taqueria San Jose # 3",
    "wof:placetype":"venue"
},
  "geometry": {"coordinates":[-122.41341300000001,37.804524],"type":"Point"}
}