{
  "type": "Feature",
  "properties": {
    "addr:full":"3840 Cll Fortunada San Diego CA 92123",
    "addr:postcode":"3840;92123",
    "addr:street":"Cll Fortunada",
    "iso:country":"US",
    "sg:address":"3840 Cll Fortunada",
    "sg:city":"San Diego",
    "sg:classifiers":[
        {
            "category":"Education",
            "subcategory":"Special Training",
            "type":"Public Place"
        }
    ],
    "sg:phone":"+1 858 541 2268",
    "sg:postcode":"92123",
    "sg:province":"CA",
    "sg:tags":[
        "aircraft",
        "school"
    ],
    "sg:website":"www.kingschools.com",
    "wof:name":"King Schools Inc",
    "wof:placetype":"venue"
},
  "geometry": {"coordinates":[-117.122595,32.813751],"type":"Point"}
}