{
  "type": "Feature",
  "properties": {
    "iso:country":"US",
    "sfac:artist":"Chomenko, Mary",
    "sfac:created_at":"01/01/1970 12:33:08 AM +0000",
    "sfac:credit_line":"Commissioned by the San Francisco Art Commission for the Clean Water Program",
    "sfac:display_dimensions":"84 \" diameter approx",
    "sfac:location_description":"Public Display : District 4 : Great Highway at Pacheco",
    "sfac:medium":"cast bronze",
    "sfac:revision":"2-35de9a899f9e3697f40be943c494c48d",
    "sfac:title":"Ocean Beach Fossil",
    "wof:name":"Ocean Beach Fossil",
    "wof:placetype":"venue"
},
  "geometry": {"coordinates":[-122.5079516,37.749111],"type":"Point"}
}