{
  "type": "Feature",
  "properties": {
    "addr:full":"1516 S Bundy Dr Los Angeles CA 90025",
    "addr:housenumber":"1516",
    "addr:postcode":"90025",
    "addr:street":"S Bundy Dr",
    "iso:country":"US",
    "sg:address":"1516 S Bundy Dr",
    "sg:city":"Los Angeles",
    "sg:classifiers":[
        {
            "category":"Professional",
            "subcategory":"Management & Consulting",
            "type":"Services"
        }
    ],
    "sg:phone":"+1 310 207 3657",
    "sg:postcode":"90025",
    "sg:province":"CA",
    "sg:tags":[
        "consultant",
        "business"
    ],
    "wof:name":"Log-An",
    "wof:placetype":"venue"
},
  "geometry": {"coordinates":[-118.46133,34.038981],"type":"Point"}
}