{
  "type": "Feature",
  "properties": {
    "iso:country":"US",
    "sg:address":"1732 N Texas St",
    "sg:city":"Fairfield",
    "sg:classifiers":[
        {
            "category":"Manufacturing",
            "subcategory":"Apparel",
            "type":"Manufacturing & Wholesale Goods"
        }
    ],
    "sg:phone":"+1 707 422 2202",
    "sg:postcode":"94533",
    "sg:province":"CA",
    "wof:name":"Ad Special TS",
    "wof:placetype":"venue"
},
  "geometry": {"coordinates":[-122.034153,38.261786],"type":"Point"}
}