{
  "type": "Feature",
  "properties": {
    "addr:full":"5013 Densmore Ave Encino CA 91436",
    "addr:housenumber":"5013",
    "addr:postcode":"91436",
    "addr:street":"Densmore Ave",
    "iso:country":"US",
    "sg:address":"5013 Densmore Ave",
    "sg:city":"Encino",
    "sg:classifiers":[
        {
            "category":"Manufacturing",
            "subcategory":"Printing",
            "type":"Manufacturing & Wholesale Goods"
        }
    ],
    "sg:phone":"+1 818 981 6666",
    "sg:postcode":"91436",
    "sg:province":"CA",
    "sg:tags":[
        "house"
    ],
    "wof:name":"Jab",
    "wof:placetype":"venue"
},
  "geometry": {"coordinates":[-118.477146,34.156818],"type":"Point"}
}