{
  "type": "Feature",
  "properties": {
    "addr:full":"3994 Foothills Blvd Roseville CA 95747",
    "addr:housenumber":"3994",
    "addr:postcode":"95747",
    "addr:street":"Foothills Blvd",
    "iso:country":"US",
    "sg:address":"3994 Foothills Blvd",
    "sg:city":"Roseville",
    "sg:classifiers":[
        {
            "category":"Restaurant",
            "type":"Food & Drink"
        }
    ],
    "sg:phone":"+1 916 783 3587",
    "sg:postcode":"95747",
    "sg:province":"CA",
    "wof:name":"Mc Donald's",
    "wof:placetype":"venue"
},
  "geometry": {"coordinates":[-121.309027,38.743777],"type":"Point"}
}