{
  "type": "Feature",
  "properties": {
    "iso:country":"US",
    "sg:address":"9608 Ave Monterey",
    "sg:city":"Cypress",
    "sg:classifiers":[
        {
            "category":"Retail",
            "subcategory":"Auto Repair",
            "type":"Services"
        }
    ],
    "sg:phone":"+1 714 334 6100",
    "sg:postcode":"90630",
    "sg:province":"CA",
    "sg:tags":[
        "body",
        "automobile",
        "painting"
    ],
    "wof:name":"Chip N Dents",
    "wof:placetype":"venue"
},
  "geometry": {"coordinates":[-118.057366,33.822604],"type":"Point"}
}