{
  "type": "Feature",
  "properties": {
    "addr:full":"25715 Rd 156 Visalia CA 93292",
    "addr:postcode":"25715;93292",
    "addr:street":"Rd 156",
    "iso:country":"US",
    "sg:address":"25715 Rd 156",
    "sg:city":"Visalia",
    "sg:classifiers":[
        {
            "category":"Farming",
            "subcategory":"Crops",
            "type":"Manufacturing & Wholesale Goods"
        }
    ],
    "sg:phone":"+1 559 747 0964",
    "sg:postcode":"93292",
    "sg:province":"CA",
    "sg:tags":[
        "grove",
        "nut",
        "tree"
    ],
    "wof:name":"Ruth Campbell",
    "wof:placetype":"venue"
},
  "geometry": {"coordinates":[-119.224915,36.261377],"type":"Point"}
}