{
  "type": "Feature",
  "properties": {
    "addr:full":"10112 Strathmore Dr Santee CA 92071",
    "addr:housenumber":"10112",
    "addr:postcode":"92071",
    "addr:street":"Strathmore Dr",
    "iso:country":"US",
    "sg:address":"10112 Strathmore Dr",
    "sg:city":"Santee",
    "sg:classifiers":[
        {
            "category":"Shopping",
            "subcategory":"Hobbies, Toys, & Games",
            "type":"Retail Goods"
        }
    ],
    "sg:phone":"+1 619 596 8715",
    "sg:postcode":"92071",
    "sg:province":"CA",
    "wof:name":"Four Quarders Enterprises",
    "wof:placetype":"venue"
},
  "geometry": {"coordinates":[-117.004199,32.86043],"type":"Point"}
}