{
  "type": "Feature",
  "properties": {
    "iso:country":"US",
    "sg:address":"4684 Via Los Santos",
    "sg:city":"Santa Barbara",
    "sg:classifiers":[
        {
            "category":"Education",
            "subcategory":"Special Training",
            "type":"Public Place"
        }
    ],
    "sg:phone":"+1 805 967 2804",
    "sg:postcode":"93111",
    "sg:province":"CA",
    "sg:tags":[
        "educational"
    ],
    "sg:website":"www.newsquizgame.com",
    "wof:name":"Creative Educational Svc",
    "wof:placetype":"venue"
},
  "geometry": {"coordinates":[-119.78492,34.45614],"type":"Point"}
}