{
  "type": "Feature",
  "properties": {
    "addr:full":"418 E Olive Ave Burbank CA 91501",
    "addr:housenumber":"418",
    "addr:postcode":"91501",
    "addr:street":"E Olive Ave",
    "iso:country":"US",
    "sg:address":"418 E Olive Ave",
    "sg:city":"Burbank",
    "sg:classifiers":[
        {
            "category":"Health Services",
            "subcategory":"Dentist",
            "type":"Services"
        }
    ],
    "sg:phone":"+1 818 846 3377",
    "sg:postcode":"91501",
    "sg:province":"CA",
    "wof:name":"Dental Team The",
    "wof:placetype":"venue"
},
  "geometry": {"coordinates":[-118.305894,34.183328],"type":"Point"}
}