{
  "type": "Feature",
  "properties": {
    "addr:full":"2025 N D St San Bernardino CA 92405",
    "addr:housenumber":"2025",
    "addr:postcode":"92405",
    "addr:street":"N D St",
    "iso:country":"US",
    "sg:address":"2025 N D St",
    "sg:city":"San Bernardino",
    "sg:classifiers":[
        {
            "category":"Social Services",
            "type":"Services"
        }
    ],
    "sg:phone":"+1 909 475 8793",
    "sg:postcode":"92405",
    "sg:province":"CA",
    "sg:tags":[
        "organization",
        "welfare"
    ],
    "wof:name":"Nuevo Amanecer Latino Children",
    "wof:placetype":"venue"
},
  "geometry": {"coordinates":[-117.29186,34.133774],"type":"Point"}
}