{
  "type": "Feature",
  "properties": {
    "iso:country":"US",
    "sg:address":"261 W Macarthur St",
    "sg:city":"Sonoma",
    "sg:classifiers":[
        {
            "category":"Manufacturing",
            "subcategory":"Textiles",
            "type":"Manufacturing & Wholesale Goods"
        }
    ],
    "sg:phone":"+1 707 996 7412",
    "sg:postcode":"95476",
    "sg:province":"CA",
    "sg:tags":[
        "coated",
        "fabric",
        "mfg"
    ],
    "wof:name":"Northbay Diamon Fusion",
    "wof:placetype":"venue"
},
  "geometry": {"coordinates":[-122.463207,38.285184],"type":"Point"}
}