{
  "type": "Feature",
  "properties": {
    "addr:full":"9317 Washington Blvd Pico Rivera CA 90660",
    "addr:housenumber":"9317",
    "addr:postcode":"90660",
    "addr:street":"Washington Blvd",
    "iso:country":"US",
    "sg:address":"9317 Washington Blvd",
    "sg:city":"Pico Rivera",
    "sg:classifiers":[
        {
            "category":"Taxi",
            "type":"Transportation"
        }
    ],
    "sg:phone":"+1 562 408 0200",
    "sg:postcode":"90660",
    "sg:province":"CA",
    "wof:name":"Yellow Cab Taxi",
    "wof:placetype":"venue"
},
  "geometry": {"coordinates":[-118.094846,33.980039],"type":"Point"}
}