{
  "type": "Feature",
  "properties": {
    "addr:full":"42 Red Hill Ave San Anselmo CA 94960",
    "addr:housenumber":"42",
    "addr:postcode":"94960",
    "addr:street":"Red Hill Ave",
    "iso:country":"US",
    "sg:address":"42 Red Hill Ave",
    "sg:city":"San Anselmo",
    "sg:classifiers":[
        {
            "category":"Autos & Motor Vehicles",
            "subcategory":"Motorcycle Sales",
            "type":"Retail Goods"
        }
    ],
    "sg:phone":"+1 415 488 1441",
    "sg:postcode":"94960",
    "sg:province":"CA",
    "sg:tags":[
        "scooter"
    ],
    "wof:name":"Hatt's",
    "wof:placetype":"venue"
},
  "geometry": {"coordinates":[-122.552153,37.976681],"type":"Point"}
}