{
  "type": "Feature",
  "properties": {
    "addr:full":"2143 S Union Ave Bakersfield CA 93307",
    "addr:housenumber":"2143",
    "addr:postcode":"93307",
    "addr:street":"S Union Ave",
    "iso:country":"US",
    "sg:address":"2143 S Union Ave",
    "sg:city":"Bakersfield",
    "sg:classifiers":[
        {
            "category":"Autos & Motor Vehicles",
            "subcategory":"Automobile Sales",
            "type":"Retail Goods"
        },
        {
            "category":"Wholesale",
            "subcategory":"Scrap",
            "type":"Manufacturing & Wholesale Goods"
        },
        {
            "category":"Shopping",
            "subcategory":"Discount & Variety Stores",
            "type":"Retail Goods"
        },
        {
            "category":"Wholesale",
            "subcategory":"Auto Parts",
            "type":"Manufacturing & Wholesale Goods"
        },
        {
            "category":"Autos & Motor Vehicles",
            "subcategory":"Auto Supplies",
            "type":"Retail Goods"
        }
    ],
    "sg:phone":"+1 661 833 6100",
    "sg:postcode":"93307",
    "sg:province":"CA",
    "sg:tags":[
        "wheel",
        "surplus",
        "wrecking",
        "vehicles-supplies",
        "drive",
        "four",
        "equipment",
        "truck",
        "supplies-used",
        "rebuilt",
        "salvage",
        "merchandise"
    ],
    "sg:website":"http://www.pickupsalvage.com",
    "wof:name":"Pickup Salvage",
    "wof:placetype":"venue"
},
  "geometry": {"coordinates":[-119.003119,35.32524],"type":"Point"}
}