{
  "type": "Feature",
  "properties": {
    "addr:full":"207 Harbor Way S San Francisco CA 94080",
    "addr:housenumber":"207",
    "addr:postcode":"94080",
    "addr:street":"Harbor Way S",
    "iso:country":"US",
    "sg:address":"207 Harbor Way",
    "sg:city":"S San Francisco",
    "sg:classifiers":[
        {
            "category":"Wholesale",
            "subcategory":"Machinery & Supplies",
            "type":"Manufacturing & Wholesale Goods"
        }
    ],
    "sg:phone":"+1 650 588 5642",
    "sg:postcode":"94080",
    "sg:province":"CA",
    "sg:tags":[
        "engine"
    ],
    "wof:name":"Shore Line Diesel Maintenance",
    "wof:placetype":"venue"
},
  "geometry": {"coordinates":[-122.40003900000001,37.650816],"type":"Point"}
}