{
  "type": "Feature",
  "properties": {
    "addr:full":"22478 Barton Rd Grand Terrace CA 92313",
    "addr:housenumber":"22478",
    "addr:postcode":"92313",
    "addr:street":"Barton Rd Grand Terrace",
    "iso:country":"US",
    "sg:address":"22478 Barton Rd",
    "sg:city":"Grand Terrace",
    "sg:classifiers":[
        {
            "category":"Real Estate",
            "subcategory":"Real Estate Agent",
            "type":"Services"
        }
    ],
    "sg:phone":"+1 909 370 4477",
    "sg:postcode":"92313",
    "sg:province":"CA",
    "sg:website":"www.americanmortgagecapital.org",
    "wof:name":"Sunrise Realty & Investments",
    "wof:placetype":"venue"
},
  "geometry": {"coordinates":[-117.31600400000001,34.03398],"type":"Point"}
}