{
  "type": "Feature",
  "properties": {
    "iso:country":"US",
    "sg:address":"Ocean Avenue Btw Lincoln & Dolores",
    "sg:city":"Carmel",
    "sg:classifiers":[
        {
            "category":"Arts & Performance",
            "subcategory":"Art Gallery",
            "type":"Entertainment"
        }
    ],
    "sg:phone":"+1 831 626 6700",
    "sg:postcode":"93921",
    "sg:province":"CA",
    "wof:name":"Studio in the Garden",
    "wof:placetype":"venue"
},
  "geometry": {"coordinates":[-121.912003,36.555901],"type":"Point"}
}