{
  "type": "Feature",
  "properties": {
    "iso:country":"US",
    "sg:address":"50 California Street",
    "sg:city":"San Francisco",
    "sg:classifiers":[
        {
            "category":"Professional",
            "subcategory":"Accounting & Tax Preparation",
            "type":"Services"
        }
    ],
    "sg:phone":"+1 415 395 9500",
    "sg:postcode":"94111",
    "sg:province":"CA",
    "sg:tags":[
        "accountant"
    ],
    "wof:name":"Ghiasi & Company",
    "wof:placetype":"venue"
},
  "geometry": {"coordinates":[-122.397003,37.793598],"type":"Point"}
}