{
  "type": "Feature",
  "properties": {
    "addr:full":"3533 Paradise View Rd Yucca Valley CA 92284",
    "addr:housenumber":"3533",
    "addr:postcode":"92284",
    "addr:street":"Paradise View Rd",
    "iso:country":"US",
    "sg:address":"3533 Paradise View Rd",
    "sg:city":"Yucca Valley",
    "sg:classifiers":[
        {
            "category":"Retail",
            "subcategory":"Auto Repair",
            "type":"Services"
        }
    ],
    "sg:phone":"+1 760 369 3800",
    "sg:postcode":"92284",
    "sg:province":"CA",
    "sg:tags":[
        "automobile",
        "restoration",
        "classic"
    ],
    "wof:name":"Born Again Restorations",
    "wof:placetype":"venue"
},
  "geometry": {"coordinates":[-116.37372499999999,34.189361],"type":"Point"}
}