{
  "type": "Feature",
  "properties": {
    "iso:country":"US",
    "sg:address":"95 Jackson St",
    "sg:city":"Hayward",
    "sg:classifiers":[
        {
            "category":"Health Services",
            "subcategory":"Chiropractor",
            "type":"Services"
        }
    ],
    "sg:phone":"+1 510 581 5813",
    "sg:postcode":"94544",
    "sg:province":"CA",
    "sg:website":"www.hayward-chiropractors.com",
    "wof:name":"Hagan Kent DC",
    "wof:placetype":"venue"
},
  "geometry": {"coordinates":[-122.08699799999999,37.657398],"type":"Point"}
}