{
  "type": "Feature",
  "properties": {
    "iso:country":"US",
    "sg:address":"3185 Brougham Ct",
    "sg:city":"Oceanside",
    "sg:classifiers":[
        {
            "category":"Professional",
            "subcategory":"Business Services",
            "type":"Services"
        }
    ],
    "sg:phone":"+1 760 310 0304",
    "sg:postcode":"92056",
    "sg:province":"CA",
    "sg:tags":[
        "delivery",
        "courier"
    ],
    "sg:website":"www.sandiegoflyerdelivery.vpweb.com",
    "wof:name":"North San Diego County Flyer Delivery Service",
    "wof:placetype":"venue"
},
  "geometry": {"coordinates":[-117.31872199999999,33.189048],"type":"Point"}
}