{
  "type": "Feature",
  "properties": {
    "addr:full":"734 Main St Cambria CA 93428",
    "addr:housenumber":"734",
    "addr:postcode":"93428",
    "addr:street":"Main St",
    "iso:country":"US",
    "sg:address":"734 Main St",
    "sg:city":"Cambria",
    "sg:classifiers":[
        {
            "category":"Winery",
            "type":"Food & Drink"
        }
    ],
    "sg:phone":"+1 805 927 5110",
    "sg:postcode":"93428",
    "sg:province":"CA",
    "wof:name":"JP Rosilez Winery",
    "wof:placetype":"venue"
},
  "geometry": {"coordinates":[-121.100515,35.567576],"type":"Point"}
}