{
  "type": "Feature",
  "properties": {
    "addr:full":"7104 Lawson Ct Highland CA 92346",
    "addr:housenumber":"7104",
    "addr:postcode":"92346",
    "addr:street":"Lawson Ct",
    "iso:country":"US",
    "sg:address":"7104 Lawson Ct",
    "sg:city":"Highland",
    "sg:classifiers":[
        {
            "category":"Banks & Credit Unions",
            "subcategory":"Investment Brokerage",
            "type":"Services"
        }
    ],
    "sg:phone":"+1 909 862 2095",
    "sg:postcode":"92346",
    "sg:province":"CA",
    "sg:tags":[
        "advisory"
    ],
    "wof:name":"Madani Investments",
    "wof:placetype":"venue"
},
  "geometry": {"coordinates":[-117.15904500000001,34.124815],"type":"Point"}
}