{
  "type": "Feature",
  "properties": {
    "iso:country":"US",
    "sg:address":"3960 Wilshire Blvd",
    "sg:city":"Los Angeles",
    "sg:classifiers":[
        {
            "category":"Professional",
            "subcategory":"Accounting & Tax Preparation",
            "type":"Services"
        }
    ],
    "sg:phone":"+1 213 385 7595",
    "sg:postcode":"90010",
    "sg:province":"CA",
    "sg:tags":[
        "bookkeeping",
        "general"
    ],
    "wof:name":"Cgc Business Svc",
    "wof:placetype":"venue"
},
  "geometry": {"coordinates":[-118.311268,34.061618],"type":"Point"}
}