{
  "type": "Feature",
  "properties": {
    "iso:country":"US",
    "sg:address":"21759 Erwin St",
    "sg:city":"Woodland Hills",
    "sg:classifiers":[
        {
            "category":"Building & Trades",
            "subcategory":"Construction",
            "type":"Services"
        }
    ],
    "sg:phone":"+1 818 577 4320",
    "sg:postcode":"91367",
    "sg:province":"CA",
    "sg:tags":[
        "interior",
        "design"
    ],
    "wof:name":"Creative Resource Associates Inc",
    "wof:placetype":"venue"
},
  "geometry": {"coordinates":[-118.603221,34.182977],"type":"Point"}
}