{
  "type": "Feature",
  "properties": {
    "iso:country":"US",
    "sg:address":"510 La Sierra Drive",
    "sg:city":"Sacramento",
    "sg:classifiers":[
        {
            "category":"Fast Food",
            "type":"Food & Drink"
        },
        {
            "category":"Deli",
            "type":"Food & Drink"
        },
        {
            "category":"Restaurant",
            "type":"Food & Drink"
        },
        {
            "category":"Food & Beverages",
            "subcategory":"Bakery",
            "type":"Retail Goods"
        }
    ],
    "sg:phone":"+1 916 971 3354",
    "sg:postcode":"95864",
    "sg:province":"CA",
    "sg:tags":[
        "delicatessen",
        "sandwich",
        "american",
        "take"
    ],
    "wof:name":"Beach Hut Deli",
    "wof:placetype":"venue"
},
  "geometry": {"coordinates":[-121.382206,38.574741],"type":"Point"}
}