{
  "type": "Feature",
  "properties": {
    "iso:country":"US",
    "sg:address":"910 W State Rte 246",
    "sg:city":"Buellton",
    "sg:classifiers":[
        {
            "category":"Retail",
            "subcategory":"Veterinary Services",
            "type":"Services"
        }
    ],
    "sg:phone":"+1 805 688 2825",
    "sg:postcode":"93427",
    "sg:province":"CA",
    "sg:tags":[
        "equine"
    ],
    "wof:name":"Bramsen Benjamin Dvm",
    "wof:placetype":"venue"
},
  "geometry": {"coordinates":[-120.216858,34.622445],"type":"Point"}
}