{
  "type": "Feature",
  "properties": {
    "iso:country":"US",
    "sg:address":"662 Moraga Way",
    "sg:city":"Orinda",
    "sg:classifiers":[
        {
            "category":"Professional",
            "type":"Services"
        }
    ],
    "sg:phone":"+1 925 376 7910",
    "sg:postcode":"94563",
    "sg:province":"CA",
    "wof:name":"Transformers",
    "wof:placetype":"venue"
},
  "geometry": {"coordinates":[-122.14726400000001,37.843815],"type":"Point"}
}