{
  "type": "Feature",
  "properties": {
    "iso:country":"US",
    "sg:address":"7660 Beverly Blvd Ste 102",
    "sg:city":"Los Angeles",
    "sg:classifiers":[
        {
            "category":"Building & Trades",
            "subcategory":"Locksmith",
            "type":"Services"
        }
    ],
    "sg:phone":"+1 310 746 8771",
    "sg:postcode":"90036",
    "sg:province":"CA",
    "sg:tags":[
        "key"
    ],
    "sg:website":"www.kinglockandkey.com",
    "wof:name":"Triple A Locksmith",
    "wof:placetype":"venue"
},
  "geometry": {"coordinates":[-118.35655,34.075946],"type":"Point"}
}