{
  "type": "Feature",
  "properties": {
    "iso:country":"US",
    "sg:address":"10 Santa Rosa St",
    "sg:city":"San Luis Obispo",
    "sg:classifiers":[
        {
            "category":"Health Services",
            "subcategory":"Doctor",
            "type":"Services"
        }
    ],
    "sg:phone":"+1 805 597 5354",
    "sg:postcode":"93405",
    "sg:province":"CA",
    "sg:tags":[
        "physician",
        "surgeon"
    ],
    "wof:name":"Alexander Krakovsky MD",
    "wof:placetype":"venue"
},
  "geometry": {"coordinates":[-120.667726,35.293765],"type":"Point"}
}