{
  "type": "Feature",
  "properties": {
    "addr:full":"1810 Randall Rd San Mateo CA 94402",
    "addr:housenumber":"1810",
    "addr:postcode":"94402",
    "addr:street":"Randall Rd",
    "iso:country":"US",
    "sg:address":"1810 Randall Rd",
    "sg:city":"San Mateo",
    "sg:classifiers":[
        {
            "category":"Retail",
            "subcategory":"Laundry & Dry Cleaning",
            "type":"Services"
        }
    ],
    "sg:phone":"+1 650 341 6180",
    "sg:postcode":"94402",
    "sg:province":"CA",
    "sg:tags":[
        "cleaners",
        "rug",
        "carpet"
    ],
    "wof:name":"LA Rose Carpet & Upholstery",
    "wof:placetype":"venue"
},
  "geometry": {"coordinates":[-122.33346299999999,37.527068],"type":"Point"}
}