{
  "type": "Feature",
  "properties": {
    "addr:full":"500 1st St Davis CA 95616",
    "addr:housenumber":"500",
    "addr:postcode":"95616",
    "addr:street":"1St St",
    "iso:country":"US",
    "sg:address":"500 1st St",
    "sg:city":"Davis",
    "sg:classifiers":[
        {
            "category":"Restaurant",
            "type":"Food & Drink"
        }
    ],
    "sg:phone":"+1 530 756 5964",
    "sg:postcode":"95616",
    "sg:province":"CA",
    "sg:tags":[
        "parlor",
        "ice",
        "cream"
    ],
    "wof:name":"Ben & Jerry's",
    "wof:placetype":"venue"
},
  "geometry": {"coordinates":[-121.740702,38.541949],"type":"Point"}
}