{
  "type": "Feature",
  "properties": {
    "iso:country":"US",
    "sg:address":"925 Commercial St",
    "sg:city":"Palo Alto",
    "sg:classifiers":[
        {
            "category":"Manufacturing",
            "subcategory":"Tools & Machinery",
            "type":"Manufacturing & Wholesale Goods"
        }
    ],
    "sg:phone":"+1 650 493 9155",
    "sg:postcode":"94303",
    "sg:province":"CA",
    "sg:tags":[
        "physician",
        "surgeon"
    ],
    "sg:website":"www.sciton.com",
    "wof:name":"Sciton LLC",
    "wof:placetype":"venue"
},
  "geometry": {"coordinates":[-122.100133,37.423115],"type":"Point"}
}