{
  "type": "Feature",
  "properties": {
    "addr:full":"2621 Denver St San Diego CA 92110",
    "addr:housenumber":"2621",
    "addr:postcode":"92110",
    "addr:street":"Denver St",
    "iso:country":"US",
    "sg:address":"2621 Denver St",
    "sg:city":"San Diego",
    "sg:classifiers":[
        {
            "category":"Social Services",
            "type":"Services"
        }
    ],
    "sg:phone":"+1 619 275 3160",
    "sg:postcode":"92110",
    "sg:province":"CA",
    "sg:tags":[
        "worker"
    ],
    "wof:name":"Allen & Hoctor Counseling Ctr",
    "wof:placetype":"venue"
},
  "geometry": {"coordinates":[-117.203262,32.790182],"type":"Point"}
}