{
  "type": "Feature",
  "properties": {
    "iso:country":"US",
    "sg:address":"429 W Valerio St",
    "sg:city":"Santa Barbara",
    "sg:classifiers":[
        {
            "category":"Real Estate",
            "subcategory":"Real Estate Operator",
            "type":"Services"
        }
    ],
    "sg:phone":"+1 805 569 0608",
    "sg:postcode":"93101",
    "sg:province":"CA",
    "sg:tags":[
        "apartment"
    ],
    "wof:name":"Merhoo Apartments",
    "wof:placetype":"venue"
},
  "geometry": {"coordinates":[-119.716581,34.423079],"type":"Point"}
}