{
  "type": "Feature",
  "properties": {
    "iso:country":"US",
    "sg:address":"8207 Woodman Ave",
    "sg:city":"Panorama City",
    "sg:classifiers":[
        {
            "category":"Shopping",
            "subcategory":"Tobacco",
            "type":"Retail Goods"
        }
    ],
    "sg:phone":"+1 818 902 2121",
    "sg:postcode":"91402",
    "sg:province":"CA",
    "sg:tags":[
        "product"
    ],
    "wof:name":"Smoke Hut",
    "wof:placetype":"venue"
},
  "geometry": {"coordinates":[-118.432807,34.221528],"type":"Point"}
}