{
  "type": "Feature",
  "properties": {
    "iso:country":"US",
    "sg:address":"5296 Valley Blvd",
    "sg:city":"Los Angeles",
    "sg:classifiers":[
        {
            "category":"Manufacturing",
            "subcategory":"Apparel",
            "type":"Manufacturing & Wholesale Goods"
        }
    ],
    "sg:phone":"+1 323 222 2690",
    "sg:postcode":"90032",
    "sg:province":"CA",
    "sg:tags":[
        "sewing",
        "contractor"
    ],
    "wof:name":"Esquisite Trend Inc",
    "wof:placetype":"venue"
},
  "geometry": {"coordinates":[-118.170035,34.073324],"type":"Point"}
}