{
  "type": "Feature",
  "properties": {
    "addr:full":"23060 Soledad Canyon Rd Santa Clarita CA 91350",
    "addr:housenumber":"23060",
    "addr:postcode":"91350",
    "addr:street":"Soledad Canyon Rd",
    "iso:country":"US",
    "sg:address":"23060 Soledad Canyon Rd",
    "sg:city":"Santa Clarita",
    "sg:classifiers":[
        {
            "category":"Autos & Motor Vehicles",
            "subcategory":"Fuel & Gas Station",
            "type":"Retail Goods"
        }
    ],
    "sg:phone":"+1 661 255 6444",
    "sg:postcode":"91350",
    "sg:province":"CA",
    "sg:website":"www.samsmobil.com",
    "wof:name":"Sam's Mobil",
    "wof:placetype":"venue"
},
  "geometry": {"coordinates":[-118.541,34.422699],"type":"Point"}
}