{
  "type": "Feature",
  "properties": {
    "addr:full":"6333 W 3rd St Ste 316 Los Angeles CA 90036",
    "addr:housenumber":"6333",
    "addr:postcode":"90036",
    "addr:street":"W 3Rd St Ste 316",
    "iso:country":"US",
    "sg:address":"6333 W 3rd St Ste 316",
    "sg:city":"Los Angeles",
    "sg:classifiers":[
        {
            "category":"Bakery",
            "type":"Food & Drink"
        }
    ],
    "sg:phone":"+1 323 937 1968",
    "sg:postcode":"90036",
    "sg:province":"CA",
    "wof:name":"Thee's Continental Pastries",
    "wof:placetype":"venue"
},
  "geometry": {"coordinates":[-118.360001,34.071301],"type":"Point"}
}