{
  "type": "Feature",
  "properties": {
    "addr:full":"1014 Fritz Rd Mckinleyville CA 95519",
    "addr:housenumber":"1014",
    "addr:postcode":"95519",
    "addr:street":"Fritz Rd",
    "iso:country":"US",
    "sg:address":"1014 Fritz Rd",
    "sg:city":"Mckinleyville",
    "sg:classifiers":[
        {
            "category":"Building & Trades",
            "subcategory":"Electrical",
            "type":"Services"
        }
    ],
    "sg:phone":"+1 707 839 9304",
    "sg:postcode":"95519",
    "sg:province":"CA",
    "sg:tags":[
        "electric",
        "contractor"
    ],
    "wof:name":"Cooke Lighting & Electric",
    "wof:placetype":"venue"
},
  "geometry": {"coordinates":[-124.114283,40.940491],"type":"Point"}
}