{
  "type": "Feature",
  "properties": {
    "addr:full":"4120 N Harbor Blvd Fullerton CA 92835",
    "addr:housenumber":"4120",
    "addr:postcode":"92835",
    "addr:street":"N Harbor Blvd",
    "iso:country":"US",
    "sg:address":"4120 N Harbor Blvd",
    "sg:city":"Fullerton",
    "sg:classifiers":[
        {
            "category":"Retail",
            "subcategory":"Laundry & Dry Cleaning",
            "type":"Services"
        }
    ],
    "sg:phone":"+1 714 680 8890",
    "sg:postcode":"92835",
    "sg:province":"CA",
    "sg:tags":[
        "cleaners"
    ],
    "wof:name":"Express 1 Cleaners & Laundry",
    "wof:placetype":"venue"
},
  "geometry": {"coordinates":[-117.932418,33.913906],"type":"Point"}
}