{
  "type": "Feature",
  "properties": {
    "iso:country":"US",
    "sg:address":"901 E Santa Ana Blvd",
    "sg:city":"Santa Ana",
    "sg:classifiers":[
        {
            "category":"Wholesale",
            "subcategory":"Computers",
            "type":"Manufacturing & Wholesale Goods"
        }
    ],
    "sg:phone":"+1 714 963 0030",
    "sg:postcode":"92701",
    "sg:province":"CA",
    "sg:tags":[
        "hardware"
    ],
    "wof:name":"Polestar International",
    "wof:placetype":"venue"
},
  "geometry": {"coordinates":[-117.85799,33.75232],"type":"Point"}
}