{
  "type": "Feature",
  "properties": {
    "addr:full":"28451 Fieldbrook Mission Viejo CA 92692",
    "addr:postcode":"28451;92692",
    "addr:street":"Fieldbrook",
    "iso:country":"US",
    "sg:address":"28451 Fieldbrook",
    "sg:city":"Mission Viejo",
    "sg:classifiers":[
        {
            "category":"Wholesale",
            "subcategory":"Home Furnishings",
            "type":"Manufacturing & Wholesale Goods"
        }
    ],
    "sg:phone":"+1 949 768 9019",
    "sg:postcode":"92692",
    "sg:province":"CA",
    "sg:tags":[
        "material"
    ],
    "wof:name":"Sherman Trading Corp",
    "wof:placetype":"venue"
},
  "geometry": {"coordinates":[-117.63428,33.64167],"type":"Point"}
}