{
  "type": "Feature",
  "properties": {
    "iso:country":"US",
    "sg:address":"7242 Scout Ave",
    "sg:city":"Bell Gardens",
    "sg:phone":"+1 562 928 2538",
    "sg:postcode":"90201",
    "sg:province":"CA",
    "sg:tags":[
        "machine",
        "parts",
        "vending",
        "supply"
    ],
    "wof:name":"Astro Operators Vending Mach",
    "wof:placetype":"venue"
},
  "geometry": {"coordinates":[-118.14219900000001,33.963443],"type":"Point"}
}