{
  "type": "Feature",
  "properties": {
    "iso:country":"US",
    "sg:address":"230 Glencrest Cir",
    "sg:city":"Ventura",
    "sg:classifiers":[
        {
            "category":"Manufacturing",
            "subcategory":"Retail Goods",
            "type":"Manufacturing & Wholesale Goods"
        }
    ],
    "sg:phone":"+1 805 642 7282",
    "sg:postcode":"93003",
    "sg:province":"CA",
    "sg:tags":[
        "product",
        "inventor",
        "mfg"
    ],
    "wof:name":"Axtell Expressions, Inc.",
    "wof:placetype":"venue"
},
  "geometry": {"coordinates":[-119.20968999999999,34.298815],"type":"Point"}
}