{
  "type": "Feature",
  "properties": {
    "addr:full":"21507 Main St Carson CA 90745",
    "addr:housenumber":"21507",
    "addr:postcode":"90745",
    "addr:street":"Main St",
    "iso:country":"US",
    "sg:address":"21507 Main St",
    "sg:city":"Carson",
    "sg:classifiers":[
        {
            "category":"Building & Trades",
            "subcategory":"Landscaping Services",
            "type":"Services"
        }
    ],
    "sg:phone":"+1 310 834 4911",
    "sg:postcode":"90745",
    "sg:province":"CA",
    "sg:tags":[
        "sod",
        "sodding"
    ],
    "wof:name":"Eileen Ohara",
    "wof:placetype":"venue"
},
  "geometry": {"coordinates":[-118.275195,33.817862],"type":"Point"}
}