{
  "type": "Feature",
  "properties": {
    "iso:country":"US",
    "sg:address":"1065 Brea Mall",
    "sg:city":"Brea",
    "sg:classifiers":[
        {
            "category":"Food & Beverages",
            "subcategory":"Specialty",
            "type":"Retail Goods"
        }
    ],
    "sg:phone":"+1 714 674 0954",
    "sg:postcode":"92821",
    "sg:province":"CA",
    "sg:tags":[
        "product",
        "health",
        "diet"
    ],
    "wof:name":"Green Tea Hp",
    "wof:placetype":"venue"
},
  "geometry": {"coordinates":[-117.886047,33.913392],"type":"Point"}
}