{
  "type": "Feature",
  "properties": {
    "iso:country":"US",
    "sg:address":"21272 Cll Gruta",
    "sg:city":"Lake Forest",
    "sg:classifiers":[
        {
            "category":"Manufacturing",
            "subcategory":"Apparel",
            "type":"Manufacturing & Wholesale Goods"
        }
    ],
    "sg:phone":"+1 949 454 9409",
    "sg:postcode":"92630",
    "sg:province":"CA",
    "sg:tags":[
        "emblem"
    ],
    "sg:website":"www.semperfimac.net",
    "wof:name":"Semper Fi Mac",
    "wof:placetype":"venue"
},
  "geometry": {"coordinates":[-117.693009,33.654089],"type":"Point"}
}