{
  "type": "Feature",
  "properties": {
    "iso:country":"US",
    "sg:address":"351 W Cromwell Ave",
    "sg:city":"Fresno",
    "sg:classifiers":[
        {
            "category":"Wholesale",
            "subcategory":"Furniture",
            "type":"Manufacturing & Wholesale Goods"
        }
    ],
    "sg:phone":"+1 559 438 5991",
    "sg:postcode":"93711",
    "sg:province":"CA",
    "wof:name":"Allforms Safeguard",
    "wof:placetype":"venue"
},
  "geometry": {"coordinates":[-119.79738500000001,36.847491],"type":"Point"}
}