{
  "type": "Feature",
  "properties": {
    "iso:country":"US",
    "sg:address":"517 Mystic Way",
    "sg:city":"Laguna Beach",
    "sg:classifiers":[
        {
            "category":"Professional",
            "type":"Services"
        }
    ],
    "sg:phone":"+1 949 497 7856",
    "sg:postcode":"92651",
    "sg:province":"CA",
    "wof:name":"Red Rock Center LLC",
    "wof:placetype":"venue"
},
  "geometry": {"coordinates":[-117.777866,33.54442],"type":"Point"}
}