{
  "type": "Feature",
  "properties": {
    "iso:country":"US",
    "sg:address":"17870 Sky Park Cir # 107",
    "sg:city":"Irvine",
    "sg:classifiers":[
        {
            "category":"Education",
            "subcategory":"Music School",
            "type":"Public Place"
        }
    ],
    "sg:phone":"+1 949 251 1162",
    "sg:postcode":"92614",
    "sg:province":"CA",
    "sg:tags":[
        "instruction-vocal"
    ],
    "sg:website":"http://www.vocaldynamics.com",
    "wof:name":"Vdp Publishing",
    "wof:placetype":"venue"
},
  "geometry": {"coordinates":[-117.855812,33.691101],"type":"Point"}
}