{
  "type": "Feature",
  "properties": {
    "iso:country":"US",
    "sg:address":"66 Marin St",
    "sg:city":"Watsonville",
    "sg:classifiers":[
        {
            "category":"Real Estate",
            "subcategory":"Developer",
            "type":"Services"
        }
    ],
    "sg:phone":"+1 831 722 0310",
    "sg:postcode":"95076",
    "sg:province":"CA",
    "sg:tags":[
        "executive",
        "cemetery"
    ],
    "wof:name":"Pajaro Valley Cemetery Dst",
    "wof:placetype":"venue"
},
  "geometry": {"coordinates":[-121.763712,36.923806],"type":"Point"}
}