{
  "type": "Feature",
  "properties": {
    "iso:country":"US",
    "sg:address":"6942 Village Pkwy",
    "sg:city":"Dublin",
    "sg:classifiers":[
        {
            "category":"Insurance",
            "subcategory":"Insurance Agent",
            "type":"Services"
        }
    ],
    "sg:phone":"+1 925 829 4211",
    "sg:postcode":"94568",
    "sg:province":"CA",
    "wof:name":"Gliedt & Stone Insurance",
    "wof:placetype":"venue"
},
  "geometry": {"coordinates":[-121.924049,37.706248],"type":"Point"}
}