{
  "type": "Feature",
  "properties": {
    "addr:full":"6990 65th Stxp Sacramento CA 95823",
    "addr:housenumber":"6990",
    "addr:postcode":"95823",
    "addr:street":"65Th Stxp",
    "iso:country":"US",
    "sg:address":"6990 65th Stxp",
    "sg:city":"Sacramento",
    "sg:classifiers":[
        {
            "category":"Organizations",
            "subcategory":"Religious Organization",
            "type":"Services"
        }
    ],
    "sg:phone":"+1 916 392 6687",
    "sg:postcode":"95823",
    "sg:province":"CA",
    "sg:tags":[
        "church"
    ],
    "sg:website":"www.masjidannur.com",
    "wof:name":"Masjid Annur Inc",
    "wof:placetype":"venue"
},
  "geometry": {"coordinates":[-121.42929100000001,38.501514],"type":"Point"}
}