{
  "type": "Feature",
  "properties": {
    "iso:country":"US",
    "sg:address":"52 Helena Ave",
    "sg:city":"Santa Barbara",
    "sg:classifiers":[
        {
            "category":"Shopping",
            "subcategory":"Used Merchandise",
            "type":"Retail Goods"
        }
    ],
    "sg:phone":"+1 805 966 1915",
    "sg:postcode":"93101",
    "sg:province":"CA",
    "sg:tags":[
        "antique"
    ],
    "wof:name":"Uptown",
    "wof:placetype":"venue"
},
  "geometry": {"coordinates":[-119.689181,34.413196],"type":"Point"}
}