{
  "type": "Feature",
  "properties": {
    "iso:country":"US",
    "sg:address":"657 Renaissance Ave",
    "sg:city":"Fairfield",
    "sg:classifiers":[
        {
            "category":"Insurance",
            "subcategory":"Insurance Agent",
            "type":"Services"
        }
    ],
    "sg:phone":"+1 707 864 8770",
    "sg:postcode":"94534",
    "sg:province":"CA",
    "wof:name":"Erich Aviation Insurance Svc",
    "wof:placetype":"venue"
},
  "geometry": {"coordinates":[-122.14744399999999,38.225],"type":"Point"}
}