{
  "type": "Feature",
  "properties": {
    "addr:full":"5171 Golden Ave Riverside CA 92505",
    "addr:housenumber":"5171",
    "addr:postcode":"92505",
    "addr:street":"Golden Ave",
    "iso:country":"US",
    "sg:address":"5171 Golden Ave",
    "sg:city":"Riverside",
    "sg:classifiers":[
        {
            "category":"Manufacturing",
            "subcategory":"Tools & Machinery",
            "type":"Manufacturing & Wholesale Goods"
        }
    ],
    "sg:phone":"+1 213 687 8935",
    "sg:postcode":"92505",
    "sg:province":"CA",
    "sg:tags":[
        "measuring",
        "machine"
    ],
    "wof:name":"Doug Volk Svc",
    "wof:placetype":"venue"
},
  "geometry": {"coordinates":[-117.49785199999999,33.923801],"type":"Point"}
}