{
  "type": "Feature",
  "properties": {
    "addr:full":"459 W Marengo Ave Shafter CA 93263",
    "addr:housenumber":"459",
    "addr:postcode":"93263",
    "addr:street":"W Marengo Ave",
    "iso:country":"US",
    "sg:address":"459 W Marengo Ave",
    "sg:city":"Shafter",
    "sg:classifiers":[
        {
            "category":"Real Estate",
            "subcategory":"Real Estate Agent",
            "type":"Services"
        }
    ],
    "sg:phone":"+1 661 746 3422",
    "sg:postcode":"93263",
    "sg:province":"CA",
    "wof:name":"Leticia Real",
    "wof:placetype":"venue"
},
  "geometry": {"coordinates":[-119.286277,35.499045],"type":"Point"}
}