{
  "type": "Feature",
  "properties": {
    "iso:country":"US",
    "sg:address":"14539 Blythe St",
    "sg:city":"Panorama City",
    "sg:classifiers":[
        {
            "category":"Building & Trades",
            "subcategory":"Construction",
            "type":"Services"
        }
    ],
    "sg:phone":"+1 818 901 7810",
    "sg:postcode":"91402",
    "sg:province":"CA",
    "sg:tags":[
        "woodworker"
    ],
    "wof:name":"Customized Woodwork",
    "wof:placetype":"venue"
},
  "geometry": {"coordinates":[-118.452548,34.215284],"type":"Point"}
}