{
  "type": "Feature",
  "properties": {
    "iso:country":"US",
    "sg:address":"13752 Sanderstead Rd",
    "sg:city":"Santa Ana",
    "sg:classifiers":[
        {
            "category":"Professional",
            "type":"Services"
        }
    ],
    "sg:phone":"+1 714 730 8229",
    "sg:postcode":"92705",
    "sg:province":"CA",
    "wof:name":"Safehrbor Recovery Empowerment",
    "wof:placetype":"venue"
},
  "geometry": {"coordinates":[-117.81465799999999,33.760722],"type":"Point"}
}