{
  "type": "Feature",
  "properties": {
    "iso:country":"US",
    "sg:address":"2200 Harbor Blvd",
    "sg:city":"Costa Mesa",
    "sg:classifiers":[
        {
            "category":"Personal",
            "subcategory":"Beauty Salon",
            "type":"Services"
        }
    ],
    "sg:phone":"+1 949 548 2442",
    "sg:postcode":"92627",
    "sg:province":"CA",
    "wof:name":"Chic Beauty Salon",
    "wof:placetype":"venue"
},
  "geometry": {"coordinates":[-117.919006,33.652604],"type":"Point"}
}