{
  "type": "Feature",
  "properties": {
    "iso:country":"US",
    "sg:address":"8045 Garfield Ave",
    "sg:city":"Bell Gardens",
    "sg:classifiers":[
        {
            "category":"Food & Beverages",
            "subcategory":"Liquor & Beverages",
            "type":"Retail Goods"
        }
    ],
    "sg:phone":"+1 562 806 5698",
    "sg:postcode":"90201",
    "sg:province":"CA",
    "sg:tags":[
        "beer",
        "spirit",
        "wine"
    ],
    "wof:name":"Garfield Liquor & Market",
    "wof:placetype":"venue"
},
  "geometry": {"coordinates":[-118.158997,33.957699],"type":"Point"}
}