{
  "type": "Feature",
  "properties": {
    "iso:country":"US",
    "sg:address":"11572 Merritt St",
    "sg:city":"Castroville",
    "sg:classifiers":[
        {
            "category":"Food & Beverages",
            "subcategory":"Bakery",
            "type":"Retail Goods"
        }
    ],
    "sg:phone":"+1 831 633 6500",
    "sg:postcode":"95012",
    "sg:province":"CA",
    "sg:tags":[
        "donut",
        "doughnut"
    ],
    "wof:name":"Missing Hole Donut Shop",
    "wof:placetype":"venue"
},
  "geometry": {"coordinates":[-121.75099899999999,36.760502],"type":"Point"}
}