{
  "type": "Feature",
  "properties": {
    "iso:country":"US",
    "sg:address":"913 Hermosa Ct",
    "sg:city":"Sunnyvale",
    "sg:classifiers":[
        {
            "category":"Freight",
            "type":"Transportation"
        }
    ],
    "sg:phone":"+1 408 732 8800",
    "sg:postcode":"94085",
    "sg:province":"CA",
    "sg:tags":[
        "company",
        "enterprise",
        "offering",
        "software"
    ],
    "wof:name":"Instantis Inc",
    "wof:placetype":"venue"
},
  "geometry": {"coordinates":[-122.039497,37.387449],"type":"Point"}
}