{
  "type": "Feature",
  "properties": {
    "iso:country":"US",
    "sg:address":"3288 Pierce St",
    "sg:city":"Richmond",
    "sg:classifiers":[
        {
            "category":"Shopping",
            "subcategory":"Music",
            "type":"Retail Goods"
        }
    ],
    "sg:phone":"+1 510 558 7115",
    "sg:postcode":"94804",
    "sg:province":"CA",
    "sg:tags":[
        "video",
        "disc",
        "tape",
        "cassette"
    ],
    "wof:name":"99 Video Rental",
    "wof:placetype":"venue"
},
  "geometry": {"coordinates":[-122.309048,37.900022],"type":"Point"}
}