{
  "type": "Feature",
  "properties": {
    "addr:full":"1921 Cll Barcelona Carlsbad CA 92009",
    "addr:housenumber":"1921",
    "addr:postcode":"92009",
    "addr:street":"Cll Barcelona",
    "iso:country":"US",
    "sg:address":"1921 Cll Barcelona",
    "sg:city":"Carlsbad",
    "sg:classifiers":[
        {
            "category":"Restaurant",
            "type":"Food & Drink"
        }
    ],
    "sg:phone":"+1 760 479 2533",
    "sg:postcode":"92009",
    "sg:province":"CA",
    "wof:name":"Buca Di Beppo",
    "wof:placetype":"venue"
},
  "geometry": {"coordinates":[-117.26468800000001,33.072978],"type":"Point"}
}