{
  "type": "Feature",
  "properties": {
    "addr:full":"1026 W Evelyn Ave Ste C Sunnyvale CA 94086",
    "addr:housenumber":"1026",
    "addr:postcode":"94086",
    "addr:street":"W Evelyn Ave Ste C",
    "iso:country":"US",
    "sg:address":"1026 W Evelyn Ave Ste C",
    "sg:city":"Sunnyvale",
    "sg:classifiers":[
        {
            "category":"Retail",
            "subcategory":"Auto Repair",
            "type":"Services"
        }
    ],
    "sg:phone":"+1 408 738 3979",
    "sg:postcode":"94086",
    "sg:province":"CA",
    "wof:name":"Zuccato's Auto Care",
    "wof:placetype":"venue"
},
  "geometry": {"coordinates":[-122.045998,37.3834],"type":"Point"}
}