{
  "type": "Feature",
  "properties": {
    "addr:full":"11367 Wills Creek Rd San Diego CA 92131",
    "addr:housenumber":"11367",
    "addr:postcode":"92131",
    "addr:street":"Wills Creek Rd",
    "iso:country":"US",
    "sg:address":"11367 Wills Creek Rd",
    "sg:city":"San Diego",
    "sg:classifiers":[
        {
            "category":"Shopping",
            "subcategory":"Clothing, Apparel, & Fashions",
            "type":"Retail Goods"
        }
    ],
    "sg:phone":"+1 858 578 8880",
    "sg:postcode":"92131",
    "sg:province":"CA",
    "wof:name":"Star Embroidery",
    "wof:placetype":"venue"
},
  "geometry": {"coordinates":[-117.083765,32.925513],"type":"Point"}
}