{
  "type": "Feature",
  "properties": {
    "addr:full":"6446 Telegraph Road Los Angeles CA 90040",
    "addr:housenumber":"6446",
    "addr:postcode":"90040",
    "addr:street":"Telegraph Road",
    "iso:country":"US",
    "sg:address":"6446 Telegraph Road",
    "sg:city":"Los Angeles",
    "sg:classifiers":[
        {
            "category":"Shopping",
            "subcategory":"Stationery & Office Supplies",
            "type":"Retail Goods"
        },
        {
            "category":"Wholesale",
            "subcategory":"Computers",
            "type":"Manufacturing & Wholesale Goods"
        }
    ],
    "sg:phone":"+1 323 890 0131",
    "sg:postcode":"90040",
    "sg:province":"CA",
    "sg:tags":[
        "equipment"
    ],
    "wof:name":"Office Depot",
    "wof:placetype":"venue"
},
  "geometry": {"coordinates":[-118.140812,33.992206],"type":"Point"}
}