{
  "type": "Feature",
  "properties": {
    "addr:full":"108 N H St Fresno CA 93701",
    "addr:housenumber":"108",
    "addr:postcode":"93701",
    "addr:street":"N H St",
    "iso:country":"US",
    "sg:address":"108 N H St",
    "sg:city":"Fresno",
    "sg:classifiers":[
        {
            "category":"Retail",
            "subcategory":"Auto Repair",
            "type":"Services"
        }
    ],
    "sg:phone":"+1 559 459 0276",
    "sg:postcode":"93701",
    "sg:province":"CA",
    "sg:tags":[
        "repairing",
        "automobile"
    ],
    "wof:name":"Auto Repair Leal",
    "wof:placetype":"venue"
},
  "geometry": {"coordinates":[-119.806596,36.745231],"type":"Point"}
}