{
  "type": "Feature",
  "properties": {
    "iso:country":"US",
    "sg:address":"11278 Los Alamitos Blvd Ste 204",
    "sg:city":"Los Alamitos",
    "sg:classifiers":[
        {
            "category":"Professional",
            "subcategory":"Computer Services",
            "type":"Services"
        }
    ],
    "sg:phone":"+1 562 598 9977",
    "sg:postcode":"90720",
    "sg:province":"CA",
    "sg:tags":[
        "repair"
    ],
    "sg:website":"www.fastteks.com/LosAlamitos/",
    "wof:name":"Fast-teks On-Site Computer Services",
    "wof:placetype":"venue"
},
  "geometry": {"coordinates":[-118.071967,33.798931],"type":"Point"}
}