{
  "type": "Feature",
  "properties": {
    "iso:country":"US",
    "sg:address":"9740 Telfair Ave",
    "sg:city":"Pacoima",
    "sg:classifiers":[
        {
            "category":"Autos & Motor Vehicles",
            "subcategory":"Automobile Sales",
            "type":"Retail Goods"
        }
    ],
    "sg:phone":"+1 818 756 4755",
    "sg:postcode":"91331",
    "sg:province":"CA",
    "sg:tags":[
        "car",
        "dealer"
    ],
    "wof:name":"Cars For Causes",
    "wof:placetype":"venue"
},
  "geometry": {"coordinates":[-118.407764,34.246778],"type":"Point"}
}