{
  "type": "Feature",
  "properties": {
    "addr:full":"4424 Pacific Blvd Vernon CA 90058",
    "addr:housenumber":"4424",
    "addr:postcode":"90058",
    "addr:street":"Pacific Blvd",
    "iso:country":"US",
    "sg:address":"4424 Pacific Blvd",
    "sg:city":"Vernon",
    "sg:classifiers":[
        {
            "category":"Professional",
            "subcategory":"Business Services",
            "type":"Services"
        }
    ],
    "sg:phone":"+1 323 587 2672",
    "sg:postcode":"90058",
    "sg:province":"CA",
    "sg:tags":[
        "cloth",
        "cutting"
    ],
    "wof:name":"J D Illusion Cutting Svc",
    "wof:placetype":"venue"
},
  "geometry": {"coordinates":[-118.22890200000001,34.004033],"type":"Point"}
}