{
  "type": "Feature",
  "properties": {
    "iso:country":"US",
    "sg:address":"34231 Cam Capistrano",
    "sg:city":"Capistrano Beach",
    "sg:classifiers":[
        {
            "category":"Professional",
            "type":"Services"
        }
    ],
    "sg:phone":"+1 949 487 9010",
    "sg:postcode":"92624",
    "sg:province":"CA",
    "wof:name":"Equipmentvendors",
    "wof:placetype":"venue"
},
  "geometry": {"coordinates":[-117.673528,33.466149],"type":"Point"}
}