{
  "type": "Feature",
  "properties": {
    "iso:country":"US",
    "sg:address":"45800 Dillon Rd",
    "sg:city":"Coachella",
    "sg:classifiers":[
        {
            "category":"Autos & Motor Vehicles",
            "subcategory":"Fuel & Gas Station",
            "type":"Retail Goods"
        }
    ],
    "sg:phone":"+1 760 398 4317",
    "sg:postcode":"92236",
    "sg:province":"CA",
    "sg:tags":[
        "oil"
    ],
    "wof:name":"Valley Gas",
    "wof:placetype":"venue"
},
  "geometry": {"coordinates":[-116.164052,33.723549],"type":"Point"}
}