{
  "type": "Feature",
  "properties": {
    "iso:country":"US",
    "sg:address":"23920 Community Blvd",
    "sg:city":"Hinkley",
    "sg:classifiers":[
        {
            "category":"Wholesale",
            "subcategory":"Dairy",
            "type":"Manufacturing & Wholesale Goods"
        },
        {
            "category":"Farming",
            "subcategory":"Dairy Farm",
            "type":"Manufacturing & Wholesale Goods"
        }
    ],
    "sg:phone":"+1 760 253 7723",
    "sg:postcode":"92347",
    "sg:province":"CA",
    "sg:tags":[
        "product"
    ],
    "wof:name":"Harmsen Family Dairy",
    "wof:placetype":"venue"
},
  "geometry": {"coordinates":[-117.144593,34.907452],"type":"Point"}
}