{
  "type": "Feature",
  "properties": {
    "iso:country":"US",
    "sg:address":"2199 S K St",
    "sg:city":"Tulare",
    "sg:classifiers":[
        {
            "category":"Retail",
            "subcategory":"Repair Shop",
            "type":"Services"
        }
    ],
    "sg:phone":"+1 559 686 2460",
    "sg:postcode":"93274",
    "sg:province":"CA",
    "sg:tags":[
        "welding"
    ],
    "wof:name":"H & H Custom Welding Inc",
    "wof:placetype":"venue"
},
  "geometry": {"coordinates":[-119.340361,36.182186],"type":"Point"}
}