{
  "type": "Feature",
  "properties": {
    "addr:full":"5604 Rhodes Ave North Hollywood CA 91607",
    "addr:housenumber":"5604",
    "addr:postcode":"91607",
    "addr:street":"Rhodes Ave",
    "iso:country":"US",
    "sg:address":"5604 Rhodes Ave",
    "sg:city":"North Hollywood",
    "sg:classifiers":[
        {
            "category":"Communications",
            "subcategory":"Film & Video Production",
            "type":"Services"
        }
    ],
    "sg:phone":"+1 818 761 5886",
    "sg:postcode":"91607",
    "sg:province":"CA",
    "sg:tags":[
        "taping"
    ],
    "wof:name":"Swartz Boyd Productions",
    "wof:placetype":"venue"
},
  "geometry": {"coordinates":[-118.403042,34.173166],"type":"Point"}
}