{
  "type": "Feature",
  "properties": {
    "addr:full":"15181 Nantes Cir Irvine CA 92604",
    "addr:postcode":"15181;92604",
    "addr:street":"Nantes Cir",
    "iso:country":"US",
    "sg:address":"15181 Nantes Cir",
    "sg:city":"Irvine",
    "sg:classifiers":[
        {
            "category":"Professional",
            "type":"Services"
        }
    ],
    "sg:phone":"+1 949 733 1420",
    "sg:postcode":"92604",
    "sg:province":"CA",
    "wof:name":"Caltechsearchcom Inc",
    "wof:placetype":"venue"
},
  "geometry": {"coordinates":[-117.784598,33.68914],"type":"Point"}
}