{
  "type": "Feature",
  "properties": {
    "addr:full":"5145 Avenida Encinas Ste A Carlsbad CA 92008",
    "addr:housenumber":"5145",
    "addr:postcode":"92008",
    "addr:street":"Avenida Encinas Ste A",
    "iso:country":"US",
    "sg:address":"5145 Avenida Encinas Ste A",
    "sg:city":"Carlsbad",
    "sg:classifiers":[
        {
            "category":"Shopping",
            "subcategory":"Party Supplies",
            "type":"Retail Goods"
        },
        {
            "category":"Home & Garden",
            "subcategory":"Furniture",
            "type":"Retail Goods"
        }
    ],
    "sg:phone":"+1 888 229 9990",
    "sg:postcode":"92008",
    "sg:province":"CA",
    "sg:tags":[
        "store"
    ],
    "sg:website":"www.loungeappeal.com",
    "wof:name":"Lounge Appeal",
    "wof:placetype":"venue"
},
  "geometry": {"coordinates":[-117.33041,33.133045],"type":"Point"}
}