{
  "type": "Feature",
  "properties": {
    "addr:full":"11702 Imperial Hwy Ste 103 Norwalk CA 90650",
    "addr:housenumber":"11702",
    "addr:postcode":"90650",
    "addr:street":"Imperial Hwy Ste 103",
    "iso:country":"US",
    "sg:address":"11702 Imperial Hwy Ste 103",
    "sg:city":"Norwalk",
    "sg:classifiers":[
        {
            "category":"Shopping",
            "subcategory":"Mobile Phones",
            "type":"Retail Goods"
        }
    ],
    "sg:phone":"+1 951 674 5850",
    "sg:postcode":"90650",
    "sg:province":"CA",
    "wof:name":"E-Z Cash Advance",
    "wof:placetype":"venue"
},
  "geometry": {"coordinates":[-118.084,33.917],"type":"Point"}
}