{
  "type": "Feature",
  "properties": {
    "iso:country":"US",
    "sg:address":"704 N Valley St Ste K",
    "sg:city":"Anaheim",
    "sg:classifiers":[
        {
            "category":"Professional",
            "subcategory":"Printing & Photocopies",
            "type":"Services"
        }
    ],
    "sg:phone":"+1 714 535 5391",
    "sg:postcode":"92801",
    "sg:province":"CA",
    "sg:tags":[
        "lithographer"
    ],
    "wof:name":"Cal Pacific Printing & Graphics",
    "wof:placetype":"venue"
},
  "geometry": {"coordinates":[-117.95639300000001,33.841147],"type":"Point"}
}