{
  "type": "Feature",
  "properties": {
    "iso:country":"US",
    "sg:address":"26846 Seco Canyon Rd",
    "sg:city":"Santa Clarita",
    "sg:classifiers":[
        {
            "category":"Food & Beverages",
            "subcategory":"Liquor & Beverages",
            "type":"Retail Goods"
        }
    ],
    "sg:phone":"+1 661 297 0055",
    "sg:postcode":"91350",
    "sg:province":"CA",
    "sg:tags":[
        "beer",
        "spirit",
        "wine"
    ],
    "wof:name":"Kwik Stop Liquor Number 4",
    "wof:placetype":"venue"
},
  "geometry": {"coordinates":[-118.531998,34.437],"type":"Point"}
}