{
  "type": "Feature",
  "properties": {
    "iso:country":"US",
    "sg:address":"3034 Crater Ln",
    "sg:city":"San Jose",
    "sg:classifiers":[
        {
            "category":"Sports & Exercise",
            "subcategory":"Golf",
            "type":"Entertainment"
        }
    ],
    "sg:phone":"+1 408 687 1140",
    "sg:postcode":"95132",
    "sg:province":"CA",
    "sg:website":"www.marksmacygolfinstruction.com",
    "wof:name":"Mark S. Macy Golf Instruction",
    "wof:placetype":"venue"
},
  "geometry": {"coordinates":[-121.855829,37.398159],"type":"Point"}
}