{
  "type": "Feature",
  "properties": {
    "addr:full":"1578 N 1st St Fresno CA 93703",
    "addr:housenumber":"1578",
    "addr:postcode":"93703",
    "addr:street":"N 1St St",
    "iso:country":"US",
    "sg:address":"1578 N 1st St",
    "sg:city":"Fresno",
    "sg:classifiers":[
        {
            "category":"Professional",
            "subcategory":"Accounting & Tax Preparation",
            "type":"Services"
        },
        {
            "category":"Banks & Credit Unions",
            "subcategory":"Financial Services",
            "type":"Services"
        }
    ],
    "sg:phone":"+1 559 237 2029",
    "sg:postcode":"93703",
    "sg:province":"CA",
    "sg:tags":[
        "return",
        "preparation-business",
        "taxes-consultants",
        "loan",
        "reporting",
        "representative",
        "alternative",
        "bookkeeping"
    ],
    "sg:website":"http://www.hrblock.com",
    "wof:name":"H&R Block",
    "wof:placetype":"venue"
},
  "geometry": {"coordinates":[-119.772453,36.764695],"type":"Point"}
}