{
  "type": "Feature",
  "properties": {
    "addr:full":"4255 E Main St Ventura CA 93003",
    "addr:housenumber":"4255",
    "addr:postcode":"93003",
    "addr:street":"E Main St",
    "iso:country":"US",
    "sg:address":"4255 E Main St",
    "sg:city":"Ventura",
    "sg:classifiers":[
        {
            "category":"Personal",
            "type":"Services"
        }
    ],
    "sg:phone":"+1 805 477 7501",
    "sg:postcode":"93003",
    "sg:province":"CA",
    "sg:tags":[
        "therapist",
        "massage"
    ],
    "wof:name":"Massage Place",
    "wof:placetype":"venue"
},
  "geometry": {"coordinates":[-119.235045,34.262732],"type":"Point"}
}