{
  "type": "Feature",
  "properties": {
    "addr:full":"2000 Bridgeway Sausalito CA 94965",
    "addr:housenumber":"2000",
    "addr:postcode":"94965",
    "addr:street":"Bridgeway",
    "iso:country":"US",
    "sg:address":"2000 Bridgeway",
    "sg:city":"Sausalito",
    "sg:classifiers":[
        {
            "category":"Manufacturing",
            "subcategory":"Printing",
            "type":"Manufacturing & Wholesale Goods"
        }
    ],
    "sg:phone":"+1 415 332 1344",
    "sg:postcode":"94965",
    "sg:province":"CA",
    "sg:tags":[
        "consulting",
        "management",
        "commercial",
        "printer"
    ],
    "wof:name":"Joanne's Print Shop",
    "wof:placetype":"venue"
},
  "geometry": {"coordinates":[-122.49539799999999,37.86256],"type":"Point"}
}