{
  "type": "Feature",
  "properties": {
    "iso:country":"US",
    "sg:address":"16096 Village Dr",
    "sg:city":"Victorville",
    "sg:classifiers":[
        {
            "category":"Building & Trades",
            "subcategory":"Cleaning & Sanitation",
            "type":"Services"
        }
    ],
    "sg:phone":"+1 760 951 1946",
    "sg:postcode":"92394",
    "sg:province":"CA",
    "sg:tags":[
        "property",
        "maintenance"
    ],
    "wof:name":"Larry's Property Maintenance",
    "wof:placetype":"venue"
},
  "geometry": {"coordinates":[-117.328733,34.54328],"type":"Point"}
}