{
  "type": "Feature",
  "properties": {
    "iso:country":"US",
    "sg:address":"845 W 30th St",
    "sg:city":"San Pedro",
    "sg:classifiers":[
        {
            "category":"Organizations",
            "subcategory":"Political Organization",
            "type":"Services"
        }
    ],
    "sg:phone":"+1 310 548 1344",
    "sg:postcode":"90731",
    "sg:province":"CA",
    "wof:name":"Dominguez Consultants",
    "wof:placetype":"venue"
},
  "geometry": {"coordinates":[-118.298396,33.71786],"type":"Point"}
}