{
  "type": "Feature",
  "properties": {
    "iso:country":"US",
    "sg:address":"1159 Green Valley Rd",
    "sg:city":"Napa",
    "sg:classifiers":[
        {
            "category":"Building & Trades",
            "subcategory":"Construction",
            "type":"Services"
        }
    ],
    "sg:phone":"+1 707 224 0506",
    "sg:postcode":"94558",
    "sg:province":"CA",
    "sg:tags":[
        "concrete",
        "contractor"
    ],
    "wof:name":"Green Valley Concrete Contr",
    "wof:placetype":"venue"
},
  "geometry": {"coordinates":[-122.219102,38.283159],"type":"Point"}
}