{
  "type": "Feature",
  "properties": {
    "iso:country":"US",
    "sg:address":"2704 Highland Ave",
    "sg:city":"National City",
    "sg:classifiers":[
        {
            "category":"Home & Garden",
            "subcategory":"Furniture",
            "type":"Retail Goods"
        },
        {
            "category":"Home & Garden",
            "subcategory":"Carpets & Floor Coverings",
            "type":"Retail Goods"
        }
    ],
    "sg:phone":"+1 619 477 1363",
    "sg:postcode":"91950",
    "sg:province":"CA",
    "sg:tags":[
        "store",
        "mattress"
    ],
    "wof:name":"Maple Cottage Furniture",
    "wof:placetype":"venue"
},
  "geometry": {"coordinates":[-117.09200300000001,32.661598],"type":"Point"}
}