{
  "type": "Feature",
  "properties": {
    "iso:country":"US",
    "sg:address":"611 W Fir St",
    "sg:city":"San Diego",
    "sg:classifiers":[
        {
            "category":"Organizations",
            "subcategory":"Religious Organization",
            "type":"Services"
        }
    ],
    "sg:phone":"+1 619 255 5861",
    "sg:postcode":"92101",
    "sg:province":"CA",
    "wof:name":"Cathedral Home",
    "wof:placetype":"venue"
},
  "geometry": {"coordinates":[-117.167778,32.724589],"type":"Point"}
}