{
  "type": "Feature",
  "properties": {
    "addr:full":"2918 Topaz Ave Simi Valley CA 93063",
    "addr:housenumber":"2918",
    "addr:postcode":"93063",
    "addr:street":"Topaz Ave",
    "iso:country":"US",
    "sg:address":"2918 Topaz Ave",
    "sg:city":"Simi Valley",
    "sg:classifiers":[
        {
            "category":"Building & Trades",
            "subcategory":"Construction",
            "type":"Services"
        }
    ],
    "sg:phone":"+1 805 579 8540",
    "sg:postcode":"93063",
    "sg:province":"CA",
    "sg:tags":[
        "grading",
        "contractor"
    ],
    "wof:name":"Winkler Grading",
    "wof:placetype":"venue"
},
  "geometry": {"coordinates":[-118.732142,34.288738],"type":"Point"}
}