{
  "type": "Feature",
  "properties": {
    "addr:full":"1048 Crimson Dr San Marcos CA 92069",
    "addr:housenumber":"1048",
    "addr:postcode":"92069",
    "addr:street":"Crimson Dr",
    "iso:country":"US",
    "sg:address":"1048 Crimson Dr",
    "sg:city":"San Marcos",
    "sg:classifiers":[
        {
            "category":"Building & Trades",
            "subcategory":"Construction",
            "type":"Services"
        }
    ],
    "sg:phone":"+1 760 471 2402",
    "sg:postcode":"92069",
    "sg:province":"CA",
    "sg:tags":[
        "floor",
        "laying",
        "contractor"
    ],
    "wof:name":"Forrest Reardon & Associates",
    "wof:placetype":"venue"
},
  "geometry": {"coordinates":[-117.143344,33.160145],"type":"Point"}
}