{
  "type": "Feature",
  "properties": {
    "iso:country":"US",
    "sg:address":"3867 4th Ave",
    "sg:city":"San Diego",
    "sg:classifiers":[
        {
            "category":"Shopping",
            "subcategory":"Clothing, Apparel, & Fashions",
            "type":"Retail Goods"
        }
    ],
    "sg:phone":"+1 619 291 1845",
    "sg:postcode":"92103",
    "sg:province":"CA",
    "sg:tags":[
        "garment",
        "accessory"
    ],
    "sg:website":"www.americanapparel.net",
    "wof:name":"American Apparel",
    "wof:placetype":"venue"
},
  "geometry": {"coordinates":[-117.161597,32.747957],"type":"Point"}
}