{
  "type": "Feature",
  "properties": {
    "iso:country":"US",
    "sg:address":"345 California Dr",
    "sg:city":"Burlingame",
    "sg:classifiers":[
        {
            "category":"Education",
            "subcategory":"Special Training",
            "type":"Public Place"
        }
    ],
    "sg:phone":"+1 650 588 4900",
    "sg:postcode":"94010",
    "sg:province":"CA",
    "sg:tags":[
        "instruction",
        "driving"
    ],
    "wof:name":"A-California Highway Driving",
    "wof:placetype":"venue"
},
  "geometry": {"coordinates":[-122.346715,37.580295],"type":"Point"}
}