{
  "type": "Feature",
  "properties": {
    "iso:country":"US",
    "sg:address":"652 N Westmoreland Ave",
    "sg:city":"Los Angeles",
    "sg:classifiers":[
        {
            "category":"Organizations",
            "subcategory":"Religious Organization",
            "type":"Services"
        }
    ],
    "sg:phone":"+1 323 663 1719",
    "sg:postcode":"90004",
    "sg:province":"CA",
    "wof:name":"Iglesia Evangelica Rios De Agua Viva",
    "wof:placetype":"venue"
},
  "geometry": {"coordinates":[-118.28800200000001,34.082802],"type":"Point"}
}