{
  "type": "Feature",
  "properties": {
    "addr:full":"3019 Kilson Dr Santa Ana CA 92707",
    "addr:housenumber":"3019",
    "addr:postcode":"92707",
    "addr:street":"Kilson Dr",
    "iso:country":"US",
    "sg:address":"3019 Kilson Dr",
    "sg:city":"Santa Ana",
    "sg:classifiers":[
        {
            "category":"Manufacturing",
            "subcategory":"Electronics",
            "type":"Manufacturing & Wholesale Goods"
        }
    ],
    "sg:phone":"+1 714 546 2162",
    "sg:postcode":"92707",
    "sg:province":"CA",
    "sg:tags":[
        "mfg",
        "boards",
        "circuit",
        "printed"
    ],
    "wof:name":"Accurate Circuit Engineering",
    "wof:placetype":"venue"
},
  "geometry": {"coordinates":[-117.86193299999999,33.707897],"type":"Point"}
}