{
  "type": "Feature",
  "properties": {
    "addr:full":"400 Day Street San Francisco CA 94131",
    "addr:housenumber":"400",
    "addr:postcode":"94131",
    "addr:street":"Day Street",
    "iso:country":"US",
    "sg:address":"400 Day Street",
    "sg:city":"San Francisco",
    "sg:classifiers":[
        {
            "category":"Professional",
            "type":"Services"
        },
        {
            "category":"Building & Trades",
            "subcategory":"Construction",
            "type":"Services"
        }
    ],
    "sg:phone":"+1 415 550 1993",
    "sg:postcode":"94131",
    "sg:province":"CA",
    "sg:tags":[
        "contractor"
    ],
    "wof:name":"Wallace Remodeling",
    "wof:placetype":"venue"
},
  "geometry": {"coordinates":[-122.431,37.742699],"type":"Point"}
}