{
  "type": "Feature",
  "properties": {
    "addr:full":"1688 N Perris Blvd Perris CA 92571",
    "addr:housenumber":"1688",
    "addr:postcode":"92571",
    "addr:street":"N Perris Blvd",
    "iso:country":"US",
    "sg:address":"1688 N Perris Blvd",
    "sg:city":"Perris",
    "sg:classifiers":[
        {
            "category":"Restaurant",
            "type":"Food & Drink"
        }
    ],
    "sg:phone":"+1 951 943 2363",
    "sg:postcode":"92571",
    "sg:province":"CA",
    "sg:website":"http://www.bk.com",
    "wof:name":"Burger King",
    "wof:placetype":"venue"
},
  "geometry": {"coordinates":[-117.22620999999999,33.802934],"type":"Point"}
}