{
  "type": "Feature",
  "properties": {
    "iso:country":"US",
    "sg:address":"425 Battery St Ste E",
    "sg:city":"San Francisco",
    "sg:classifiers":[
        {
            "category":"Professional",
            "subcategory":"Printing & Photocopies",
            "type":"Services"
        }
    ],
    "sg:phone":"+1 415 576 0430",
    "sg:postcode":"94111",
    "sg:province":"CA",
    "sg:website":"www.copycentral.com",
    "wof:name":"Copy Central",
    "wof:placetype":"venue"
},
  "geometry": {"coordinates":[-122.400733,37.795197],"type":"Point"}
}