{
  "type": "Feature",
  "properties": {
    "iso:country":"US",
    "sg:address":"9144 Jackson Rd",
    "sg:city":"Sacramento",
    "sg:classifiers":[
        {
            "category":"Retail",
            "subcategory":"Auto Repair",
            "type":"Services"
        }
    ],
    "sg:phone":"+1 916 363 8400",
    "sg:postcode":"95826",
    "sg:province":"CA",
    "sg:tags":[
        "automobile",
        "smog"
    ],
    "wof:name":"VIP Smog Inc",
    "wof:placetype":"venue"
},
  "geometry": {"coordinates":[-121.36491599999999,38.537272],"type":"Point"}
}