{
  "type": "Feature",
  "properties": {
    "iso:country":"US",
    "sg:address":"1129 N Garey Ave",
    "sg:city":"Pomona",
    "sg:classifiers":[
        {
            "category":"Banks & Credit Unions",
            "subcategory":"Investment Brokerage",
            "type":"Services"
        }
    ],
    "sg:phone":"+1 909 620 4441",
    "sg:postcode":"91767",
    "sg:province":"CA",
    "sg:tags":[
        "advisory",
        "financial"
    ],
    "wof:name":"Assured Financial",
    "wof:placetype":"venue"
},
  "geometry": {"coordinates":[-117.75214800000001,34.069265],"type":"Point"}
}