{
  "type": "Feature",
  "properties": {
    "addr:full":"22452 Birds Eye Dr Diamond Bar CA 91765",
    "addr:postcode":"22452;91765",
    "addr:street":"Birds Eye Dr",
    "iso:country":"US",
    "sg:address":"22452 Birds Eye Dr",
    "sg:city":"Diamond Bar",
    "sg:classifiers":[
        {
            "category":"Shopping",
            "type":"Retail Goods"
        }
    ],
    "sg:phone":"+1 909 861 4955",
    "sg:postcode":"91765",
    "sg:province":"CA",
    "sg:tags":[
        "enforcement",
        "law",
        "supply"
    ],
    "wof:name":"Leach Enterprises",
    "wof:placetype":"venue"
},
  "geometry": {"coordinates":[-117.826222,33.998838],"type":"Point"}
}