{
  "type": "Feature",
  "properties": {
    "addr:full":"3439 Martin Luther King Jr Blvd Lynwood CA 90262",
    "addr:housenumber":"3439",
    "addr:postcode":"90262",
    "addr:street":"Martin Luther King Jr Blvd",
    "iso:country":"US",
    "sg:address":"3439 Martin Luther King Jr Blvd",
    "sg:city":"Lynwood",
    "sg:classifiers":[
        {
            "category":"Retail",
            "subcategory":"Auto Repair",
            "type":"Services"
        }
    ],
    "sg:phone":"+1 323 566 7525",
    "sg:postcode":"90262",
    "sg:province":"CA",
    "sg:tags":[
        "repairing",
        "automobile"
    ],
    "wof:name":"Baja Imports Auto Repair",
    "wof:placetype":"venue"
},
  "geometry": {"coordinates":[-118.20842399999999,33.936409],"type":"Point"}
}