{
  "type": "Feature",
  "properties": {
    "iso:country":"US",
    "sg:address":"2260 E Colorado Blvd",
    "sg:city":"Pasadena",
    "sg:classifiers":[
        {
            "category":"Autos & Motor Vehicles",
            "subcategory":"Motorcycle Sales",
            "type":"Retail Goods"
        }
    ],
    "sg:phone":"+1 626 577 3000",
    "sg:postcode":"91107",
    "sg:province":"CA",
    "sg:website":"www.pasadenayamaha.com/",
    "wof:name":"Pasadena Yamaha",
    "wof:placetype":"venue"
},
  "geometry": {"coordinates":[-118.103996,34.146],"type":"Point"}
}