{
  "type": "Feature",
  "properties": {
    "iso:country":"US",
    "sg:address":"625 Main St",
    "sg:city":"Sausalito",
    "sg:classifiers":[
        {
            "category":"Organizations",
            "subcategory":"Non-profit Organization",
            "type":"Services"
        }
    ],
    "sg:phone":"+1 415 332 0174",
    "sg:postcode":"94965",
    "sg:province":"CA",
    "sg:tags":[
        "elementary",
        "school"
    ],
    "wof:name":"Sausalito Nursery School",
    "wof:placetype":"venue"
},
  "geometry": {"coordinates":[-122.48400100000001,37.848801],"type":"Point"}
}