{
  "type": "Feature",
  "properties": {
    "iso:country":"US",
    "sg:address":"8137 Lloyd Ave",
    "sg:city":"North Hollywood",
    "sg:classifiers":[
        {
            "category":"Manufacturing",
            "subcategory":"Aerospace",
            "type":"Manufacturing & Wholesale Goods"
        }
    ],
    "sg:phone":"+1 818 801 0884",
    "sg:postcode":"91605",
    "sg:province":"CA",
    "sg:tags":[
        "distributor",
        "sealant",
        "aircraft"
    ],
    "wof:name":"Sealants & More",
    "wof:placetype":"venue"
},
  "geometry": {"coordinates":[-118.42078100000001,34.219178],"type":"Point"}
}