{
  "type": "Feature",
  "properties": {
    "iso:country":"US",
    "sg:address":"6135 Buena Vista Ave",
    "sg:city":"Oakland",
    "sg:classifiers":[
        {
            "category":"Social Services",
            "subcategory":"Job Training",
            "type":"Services"
        },
        {
            "category":"Education",
            "subcategory":"Special Training",
            "type":"Public Place"
        },
        {
            "category":"Professional",
            "subcategory":"Employment Agencies",
            "type":"Services"
        }
    ],
    "sg:phone":"+1 510 654 4352",
    "sg:postcode":"94618",
    "sg:province":"CA",
    "sg:tags":[
        "career",
        "opportunity",
        "vocational",
        "counseling"
    ],
    "sg:website":"http://www.careersteps123.com",
    "wof:name":"Career Steps Coaching",
    "wof:placetype":"venue"
},
  "geometry": {"coordinates":[-122.23251399999999,37.844121],"type":"Point"}
}