{
  "type": "Feature",
  "properties": {
    "addr:full":"14140 All American Way Westminster CA 92683",
    "addr:housenumber":"14140",
    "addr:postcode":"92683",
    "addr:street":"All American Way",
    "iso:country":"US",
    "sg:address":"14140 All American Way",
    "sg:city":"Westminster",
    "sg:classifiers":[
        {
            "category":"Arts & Performance",
            "subcategory":"Arts Center",
            "type":"Entertainment"
        }
    ],
    "sg:phone":"+1 714 793 1150",
    "sg:postcode":"92683",
    "sg:province":"CA",
    "sg:tags":[
        "performing"
    ],
    "sg:website":"www.rosecentertheater.com",
    "wof:name":"Rose Center Theater",
    "wof:placetype":"venue"
},
  "geometry": {"coordinates":[-117.98486800000001,33.756375],"type":"Point"}
}