{
  "type": "Feature",
  "properties": {
    "addr:full":"440 Greenfield Ave Hanford CA 93230",
    "addr:housenumber":"440",
    "addr:postcode":"ca 93230",
    "addr:street":"Greenfield Ave",
    "iso:country":"US",
    "sg:address":"440 Greenfield Ave",
    "sg:city":"Hanford",
    "sg:classifiers":[
        {
            "category":"Health Services",
            "subcategory":"Doctor",
            "type":"Services"
        }
    ],
    "sg:phone":"+1 559 582 9061",
    "sg:postcode":"93230",
    "sg:province":"CA",
    "sg:tags":[
        "physician",
        "surgeon"
    ],
    "wof:name":"Carlos Santivanez Inc",
    "wof:placetype":"venue"
},
  "geometry": {"coordinates":[-119.65738899999999,36.332173],"type":"Point"}
}