{
  "type": "Feature",
  "properties": {
    "iso:country":"US",
    "sg:address":"351 Astro Dr",
    "sg:city":"Hollister",
    "sg:classifiers":[
        {
            "category":"Organizations",
            "subcategory":"Community Association",
            "type":"Services"
        }
    ],
    "sg:phone":"+1 831 637 1436",
    "sg:postcode":"95023",
    "sg:province":"CA",
    "sg:tags":[
        "fraternal"
    ],
    "wof:name":"Elks Lodge",
    "wof:placetype":"venue"
},
  "geometry": {"coordinates":[-121.401177,36.889135],"type":"Point"}
}