{
  "type": "Feature",
  "properties": {
    "iso:country":"US",
    "sg:address":"950 Camden Ave PMB 109-176",
    "sg:city":"San Jose",
    "sg:classifiers":[
        {
            "category":"Building & Trades",
            "subcategory":"Construction",
            "type":"Services"
        }
    ],
    "sg:phone":"+1 408 971 1814",
    "sg:postcode":"95120",
    "sg:province":"CA",
    "sg:tags":[
        "air",
        "heating",
        "conditioning/hvac"
    ],
    "sg:website":"www.dnheatair.com",
    "wof:name":"Day & Night Heating & Air",
    "wof:placetype":"venue"
},
  "geometry": {"coordinates":[-121.949168,37.273324],"type":"Point"}
}