{
  "type": "Feature",
  "properties": {
    "iso:country":"US",
    "sg:address":"3166 Ashbrook Dr",
    "sg:city":"Chino Hills",
    "sg:classifiers":[
        {
            "category":"Building & Trades",
            "subcategory":"Cleaning & Sanitation",
            "type":"Services"
        }
    ],
    "sg:phone":"+1 951 756 1255",
    "sg:postcode":"91709",
    "sg:province":"CA",
    "sg:tags":[
        "janitor"
    ],
    "wof:name":"Hand Made USA",
    "wof:placetype":"venue"
},
  "geometry": {"coordinates":[-117.734894,33.965441],"type":"Point"}
}