{
  "type": "Feature",
  "properties": {
    "addr:full":"8207 3rd Street Downey CA 90241",
    "addr:housenumber":"8207",
    "addr:postcode":"90241",
    "addr:street":"3Rd Street",
    "iso:country":"US",
    "sg:address":"8207 3rd Street",
    "sg:city":"Downey",
    "sg:classifiers":[
        {
            "category":"Health Services",
            "subcategory":"Doctor",
            "type":"Services"
        }
    ],
    "sg:phone":"+1 562 923 1183",
    "sg:postcode":"90241",
    "sg:province":"CA",
    "sg:tags":[
        "physician",
        "family",
        "practice",
        "surgeons",
        "medicine",
        "surgeon"
    ],
    "wof:name":"Smith Wm MD",
    "wof:placetype":"venue"
},
  "geometry": {"coordinates":[-118.133351,33.942662],"type":"Point"}
}