{
  "type": "Feature",
  "properties": {
    "iso:country":"US",
    "sg:address":"301 S Willowbrook Ave",
    "sg:city":"Compton",
    "sg:classifiers":[
        {
            "category":"Government",
            "subcategory":"Police Station",
            "type":"Public Place"
        }
    ],
    "sg:phone":"+1 310 605 5600",
    "sg:postcode":"90220",
    "sg:province":"CA",
    "sg:tags":[
        "protection"
    ],
    "wof:name":"Sheriffs Dept",
    "wof:placetype":"venue"
},
  "geometry": {"coordinates":[-118.224442,33.895876],"type":"Point"}
}