{
  "type": "Feature",
  "properties": {
    "iso:country":"US",
    "sg:address":"4714 Woodman Ave",
    "sg:city":"Sherman Oaks",
    "sg:classifiers":[
        {
            "category":"Health Services",
            "subcategory":"Clinic",
            "type":"Services"
        }
    ],
    "sg:phone":"+1 818 654 0330",
    "sg:postcode":"91423",
    "sg:province":"CA",
    "sg:tags":[
        "home",
        "care"
    ],
    "wof:name":"Health Entps Life-Long Plans",
    "wof:placetype":"venue"
},
  "geometry": {"coordinates":[-118.431157,34.156277],"type":"Point"}
}