{
  "type": "Feature",
  "properties": {
    "iso:country":"US",
    "sg:address":"416 N Bedford Drive",
    "sg:city":"Beverly Hills",
    "sg:classifiers":[
        {
            "category":"Health Services",
            "subcategory":"Dentist",
            "type":"Services"
        }
    ],
    "sg:phone":"+1 310 207 5255",
    "sg:postcode":"90210",
    "sg:province":"CA",
    "wof:name":"Vaziri Charles DDS",
    "wof:placetype":"venue"
},
  "geometry": {"coordinates":[-118.40528,34.068175],"type":"Point"}
}