{
  "type": "Feature",
  "properties": {
    "addr:full":"2742 Loker Ave W Carlsbad CA 92010",
    "addr:housenumber":"2742",
    "addr:postcode":"92010",
    "addr:street":"Loker Ave W",
    "iso:country":"US",
    "sg:address":"2742 Loker Ave W",
    "sg:city":"Carlsbad",
    "sg:classifiers":[
        {
            "category":"Shopping",
            "subcategory":"Bicycles & Sporting Goods",
            "type":"Retail Goods"
        }
    ],
    "sg:phone":"+1 760 476 0804",
    "sg:postcode":"92010",
    "sg:province":"CA",
    "wof:name":"No Fear",
    "wof:placetype":"venue"
},
  "geometry": {"coordinates":[-117.25703,33.134306],"type":"Point"}
}