{
  "type": "Feature",
  "properties": {
    "iso:country":"US",
    "sg:address":"6301 W Eight Mile Rd",
    "sg:city":"Stockton",
    "sg:classifiers":[
        {
            "category":"Professional",
            "type":"Services"
        }
    ],
    "sg:phone":"+1 209 956 6158",
    "sg:postcode":"95219",
    "sg:province":"CA",
    "wof:name":"Reserve Banquet Pavillion",
    "wof:placetype":"venue"
},
  "geometry": {"coordinates":[-121.392884,38.057849],"type":"Point"}
}