{
  "type": "Feature",
  "properties": {
    "iso:country":"US",
    "sg:address":"875 Rincon Ave",
    "sg:city":"Livermore",
    "sg:classifiers":[
        {
            "category":"Restaurant",
            "type":"Food & Drink"
        }
    ],
    "sg:phone":"+1 925 606 8266",
    "sg:postcode":"94551",
    "sg:province":"CA",
    "wof:name":"Pine Street Sports Bar & Grill",
    "wof:placetype":"venue"
},
  "geometry": {"coordinates":[-121.783351,37.688147],"type":"Point"}
}