{
  "type": "Feature",
  "properties": {
    "iso:country":"US",
    "sg:address":"3271 Pasternack Pl",
    "sg:city":"San Diego",
    "sg:classifiers":[
        {
            "category":"Shopping",
            "subcategory":"Computers & Home Electronics",
            "type":"Retail Goods"
        }
    ],
    "sg:phone":"+1 619 318 6224",
    "sg:postcode":"92123",
    "sg:province":"CA",
    "wof:name":"Techsoft Corporation",
    "wof:placetype":"venue"
},
  "geometry": {"coordinates":[-117.134041,32.800174],"type":"Point"}
}