{
  "type": "Feature",
  "properties": {
    "iso:country":"US",
    "sg:address":"100 Oceangate",
    "sg:city":"Long Beach",
    "sg:classifiers":[
        {
            "category":"Real Estate",
            "subcategory":"Real Estate Agent",
            "type":"Services"
        }
    ],
    "sg:phone":"+1 562 901 9021",
    "sg:postcode":"90802",
    "sg:province":"CA",
    "wof:name":"Arden Realty Group Inc",
    "wof:placetype":"venue"
},
  "geometry": {"coordinates":[-118.19936,33.76651],"type":"Point"}
}