{
  "type": "Feature",
  "properties": {
    "iso:country":"US",
    "sg:address":"4858 Anna Dr",
    "sg:city":"San Jose",
    "sg:classifiers":[
        {
            "category":"Building & Trades",
            "subcategory":"Plumbing",
            "type":"Services"
        }
    ],
    "sg:phone":"+1 408 591 3324",
    "sg:postcode":"95124",
    "sg:province":"CA",
    "sg:website":"www.jobsmadebest.com",
    "wof:name":"JMB Plumbing & Construction Inc",
    "wof:placetype":"venue"
},
  "geometry": {"coordinates":[-121.92479299999999,37.249293],"type":"Point"}
}