{
  "type": "Feature",
  "properties": {
    "iso:country":"US",
    "sg:address":"2065 Arnold Way",
    "sg:city":"Alpine",
    "sg:classifiers":[
        {
            "category":"Professional",
            "type":"Services"
        }
    ],
    "sg:phone":"+1 619 445 1353",
    "sg:postcode":"91901",
    "sg:province":"CA",
    "wof:name":"Steven J Lizanich",
    "wof:placetype":"venue"
},
  "geometry": {"coordinates":[-116.772598,32.836029],"type":"Point"}
}