{
  "type": "Feature",
  "properties": {
    "iso:country":"US",
    "sg:address":"201 Turk St",
    "sg:city":"San Francisco",
    "sg:classifiers":[
        {
            "category":"Shopping",
            "type":"Retail Goods"
        }
    ],
    "sg:phone":"+1 415 771 9187",
    "sg:postcode":"94102",
    "sg:province":"CA",
    "sg:tags":[
        "telephone",
        "cellular"
    ],
    "wof:name":"City Radio",
    "wof:placetype":"venue"
},
  "geometry": {"coordinates":[-122.413003,37.782928],"type":"Point"}
}