{
  "type": "Feature",
  "properties": {
    "iso:country":"US",
    "sg:address":"8115 el Dorado St",
    "sg:city":"French Camp",
    "sg:classifiers":[
        {
            "category":"Food & Beverages",
            "subcategory":"Groceries & Convenience Stores",
            "type":"Retail Goods"
        }
    ],
    "sg:phone":"+1 209 982 0897",
    "sg:postcode":"95231",
    "sg:province":"CA",
    "sg:tags":[
        "grocer"
    ],
    "wof:name":"J & L Market",
    "wof:placetype":"venue"
},
  "geometry": {"coordinates":[-121.276241,37.879673],"type":"Point"}
}