{
  "type": "Feature",
  "properties": {
    "addr:full":"613 S 7th St Modesto CA 95351",
    "addr:housenumber":"613",
    "addr:postcode":"ca 95351",
    "addr:street":"S 7Th St",
    "iso:country":"US",
    "sg:address":"613 S 7th St",
    "sg:city":"Modesto",
    "sg:classifiers":[
        {
            "category":"Real Estate",
            "subcategory":"Real Estate Operator",
            "type":"Services"
        }
    ],
    "sg:phone":"+1 209 522 5757",
    "sg:postcode":"95351",
    "sg:province":"CA",
    "sg:tags":[
        "mobile",
        "home",
        "community"
    ],
    "wof:name":"California Trailor Court",
    "wof:placetype":"venue"
},
  "geometry": {"coordinates":[-120.992704,37.624265],"type":"Point"}
}