{
  "type": "Feature",
  "properties": {
    "addr:full":"210 Walter Hays Dr Palo Alto CA 94303",
    "addr:housenumber":"210",
    "addr:postcode":"94303",
    "addr:street":"Walter Hays Dr",
    "iso:country":"US",
    "sg:address":"210 Walter Hays Dr",
    "sg:city":"Palo Alto",
    "sg:classifiers":[
        {
            "category":"Professional",
            "subcategory":"Management & Consulting",
            "type":"Services"
        }
    ],
    "sg:phone":"+1 650 321 2971",
    "sg:postcode":"94303",
    "sg:province":"CA",
    "sg:tags":[
        "consultant",
        "business"
    ],
    "wof:name":"Biotechnology Group",
    "wof:placetype":"venue"
},
  "geometry": {"coordinates":[-122.137621,37.448085],"type":"Point"}
}