{
  "type": "Feature",
  "properties": {
    "iso:country":"US",
    "sg:address":"1206 Kearsarge Ave",
    "sg:city":"Ridgecrest",
    "sg:classifiers":[
        {
            "category":"Education",
            "subcategory":"School",
            "type":"Public Place"
        }
    ],
    "sg:phone":"+1 760 446 2531",
    "sg:postcode":"93555",
    "sg:province":"CA",
    "wof:name":"Richmond Elementary School",
    "wof:placetype":"venue"
},
  "geometry": {"coordinates":[-117.641561,35.658027],"type":"Point"}
}