{
  "type": "Feature",
  "properties": {
    "iso:country":"US",
    "sg:address":"2209 Via Gavilan",
    "sg:city":"San Clemente",
    "sg:classifiers":[
        {
            "category":"Manufacturing",
            "subcategory":"Tools & Machinery",
            "type":"Manufacturing & Wholesale Goods"
        }
    ],
    "sg:phone":"+1 949 369 9954",
    "sg:postcode":"92673",
    "sg:province":"CA",
    "sg:tags":[
        "physician",
        "surgeon"
    ],
    "wof:name":"Crandall Medical Devices",
    "wof:placetype":"venue"
},
  "geometry": {"coordinates":[-117.62421399999999,33.445609],"type":"Point"}
}