{
  "type": "Feature",
  "properties": {
    "addr:full":"1381 Warner Ave Tustin CA 92707",
    "addr:housenumber":"1381",
    "addr:postcode":"92707",
    "addr:street":"Warner Ave",
    "iso:country":"US",
    "sg:address":"1381 Warner Ave",
    "sg:city":"Tustin",
    "sg:classifiers":[
        {
            "category":"Professional",
            "subcategory":"Credit Reporting & Collection",
            "type":"Services"
        }
    ],
    "sg:phone":"+1 714 247 1050",
    "sg:postcode":"92707",
    "sg:province":"CA",
    "wof:name":"Residential Credit Reports",
    "wof:placetype":"venue"
},
  "geometry": {"coordinates":[-117.83775300000001,33.711445],"type":"Point"}
}