{
  "type": "Feature",
  "properties": {
    "addr:full":"400 Morris St Sebastopol CA 95472",
    "addr:housenumber":"400",
    "addr:postcode":"95472",
    "addr:street":"Morris St",
    "iso:country":"US",
    "sg:address":"400 Morris St",
    "sg:city":"Sebastopol",
    "sg:classifiers":[
        {
            "category":"Manufacturing",
            "subcategory":"Glass & Minerals",
            "type":"Manufacturing & Wholesale Goods"
        },
        {
            "category":"Shopping",
            "subcategory":"Hobbies, Toys, & Games",
            "type":"Retail Goods"
        }
    ],
    "sg:phone":"+1 707 824 4160",
    "sg:postcode":"95472",
    "sg:province":"CA",
    "sg:tags":[
        "product",
        "nonmetallic",
        "mfg"
    ],
    "wof:name":"Anaglyph Sculpture Inc",
    "wof:placetype":"venue"
},
  "geometry": {"coordinates":[-122.820401,38.408002],"type":"Point"}
}