{
  "type": "Feature",
  "properties": {
    "addr:full":"1718 E Mineral King Ave Visalia CA 93292",
    "addr:housenumber":"1718",
    "addr:postcode":"93292",
    "addr:street":"E Mineral King Ave",
    "iso:country":"US",
    "sg:address":"1718 E Mineral King Ave",
    "sg:city":"Visalia",
    "sg:classifiers":[
        {
            "category":"Restaurant",
            "type":"Food & Drink"
        }
    ],
    "sg:phone":"+1 559 734 4267",
    "sg:postcode":"93292",
    "sg:province":"CA",
    "wof:name":"The Corner Cafe",
    "wof:placetype":"venue"
},
  "geometry": {"coordinates":[-119.273033,36.327339],"type":"Point"}
}