{
  "type": "Feature",
  "properties": {
    "iso:country":"US",
    "sg:address":"3498 Mearn Ct",
    "sg:city":"Redding",
    "sg:classifiers":[
        {
            "category":"Real Estate",
            "subcategory":"Real Estate Operator",
            "type":"Services"
        }
    ],
    "sg:phone":"+1 530 221 2174",
    "sg:postcode":"96002",
    "sg:province":"CA",
    "sg:tags":[
        "apartment"
    ],
    "wof:name":"Quail Run Manor",
    "wof:placetype":"venue"
},
  "geometry": {"coordinates":[-122.333549,40.557201],"type":"Point"}
}