{
  "type": "Feature",
  "properties": {
    "iso:country":"US",
    "sg:address":"161 Park Plaza Dr",
    "sg:city":"Daly City",
    "sg:classifiers":[
        {
            "category":"Professional",
            "type":"Services"
        }
    ],
    "sg:phone":"+1 650 465 3227",
    "sg:postcode":"94015",
    "sg:province":"CA",
    "wof:name":"Huyen Bui",
    "wof:placetype":"venue"
},
  "geometry": {"coordinates":[-122.481023,37.699907],"type":"Point"}
}