{
  "type": "Feature",
  "properties": {
    "addr:full":"1720 El Camino Real Burlingame CA 94010",
    "addr:housenumber":"1720",
    "addr:postcode":"94010",
    "addr:street":"El Camino Real",
    "iso:country":"US",
    "sg:address":"1720 El Camino Real",
    "sg:city":"Burlingame",
    "sg:classifiers":[
        {
            "category":"Health Services",
            "subcategory":"Doctor",
            "type":"Services"
        }
    ],
    "sg:phone":"+1 650 697 8808",
    "sg:postcode":"94010",
    "sg:province":"CA",
    "wof:name":"Xie Haichun MD",
    "wof:placetype":"venue"
},
  "geometry": {"coordinates":[-122.380764,37.592978],"type":"Point"}
}