{
  "type": "Feature",
  "properties": {
    "iso:country":"US",
    "sg:address":"16149 Otsego St",
    "sg:city":"Encino",
    "sg:classifiers":[
        {
            "category":"Professional",
            "subcategory":"Advertising",
            "type":"Services"
        }
    ],
    "sg:phone":"+1 818 501 2881",
    "sg:postcode":"91436",
    "sg:province":"CA",
    "sg:tags":[
        "counselor"
    ],
    "wof:name":"PFK Inc",
    "wof:placetype":"venue"
},
  "geometry": {"coordinates":[-118.484923,34.163153],"type":"Point"}
}