{
  "type": "Feature",
  "properties": {
    "iso:country":"US",
    "sg:address":"19271 Colima Rd",
    "sg:city":"Rowland Heights",
    "sg:classifiers":[
        {
            "category":"Social Services",
            "subcategory":"Adult Care",
            "type":"Services"
        }
    ],
    "sg:phone":"+1 626 581 7980",
    "sg:postcode":"91748",
    "sg:province":"CA",
    "sg:tags":[
        "organization",
        "senior",
        "citizen"
    ],
    "wof:name":"East LA Chinese Everspring",
    "wof:placetype":"venue"
},
  "geometry": {"coordinates":[-117.884255,33.987286],"type":"Point"}
}