{
  "type": "Feature",
  "properties": {
    "iso:country":"US",
    "sg:address":"1800 W Garvey Ave Garvey and Casuda Canyon Dr",
    "sg:city":"Monterey Park",
    "sg:classifiers":[
        {
            "category":"Food & Beverages",
            "subcategory":"Groceries & Convenience Stores",
            "type":"Retail Goods"
        }
    ],
    "sg:phone":"+1 626 308 3443",
    "sg:postcode":"91754",
    "sg:province":"CA",
    "wof:name":"Santa Fe Market",
    "wof:placetype":"venue"
},
  "geometry": {"coordinates":[-118.153209,34.062089],"type":"Point"}
}