{
  "type": "Feature",
  "properties": {
    "addr:full":"14163 Nassau Rd San Leandro CA 94577",
    "addr:housenumber":"14163",
    "addr:postcode":"94577",
    "addr:street":"Nassau Rd",
    "iso:country":"US",
    "sg:address":"14163 Nassau Rd",
    "sg:city":"San Leandro",
    "sg:classifiers":[
        {
            "category":"Wholesale",
            "subcategory":"Drugs",
            "type":"Manufacturing & Wholesale Goods"
        }
    ],
    "sg:phone":"+1 510 357 2013",
    "sg:postcode":"94577",
    "sg:province":"CA",
    "sg:tags":[
        "product",
        "french",
        "bath"
    ],
    "wof:name":"Echo France",
    "wof:placetype":"venue"
},
  "geometry": {"coordinates":[-122.17759599999999,37.693063],"type":"Point"}
}