{
  "type": "Feature",
  "properties": {
    "iso:country":"US",
    "sg:address":"151 Oak Forest Cir",
    "sg:city":"Glendora",
    "sg:classifiers":[
        {
            "category":"Banks & Credit Unions",
            "subcategory":"Investment Brokerage",
            "type":"Services"
        }
    ],
    "sg:phone":"+1 626 335 4892",
    "sg:postcode":"91741",
    "sg:province":"CA",
    "sg:tags":[
        "trust"
    ],
    "wof:name":"Waters Family Living Trust",
    "wof:placetype":"venue"
},
  "geometry": {"coordinates":[-117.839088,34.13483],"type":"Point"}
}