{
  "type": "Feature",
  "properties": {
    "addr:full":"1200 Carlsbad Village Dr Carlsbad CA 92008",
    "addr:housenumber":"1200",
    "addr:postcode":"92008",
    "addr:street":"Carlsbad Village Dr",
    "iso:country":"US",
    "sg:address":"1200 Carlsbad Village Dr",
    "sg:city":"Carlsbad",
    "sg:classifiers":[
        {
            "category":"Government",
            "subcategory":"City Hall",
            "type":"Public Place"
        },
        {
            "category":"Government",
            "subcategory":"Office",
            "type":"Public Place"
        }
    ],
    "sg:phone":"+1 760 434 2920",
    "sg:postcode":"92008",
    "sg:province":"CA",
    "sg:tags":[
        "town",
        "township",
        "planner",
        "government-city",
        "village"
    ],
    "wof:name":"Cultural Arts Office",
    "wof:placetype":"venue"
},
  "geometry": {"coordinates":[-117.341072,33.16399],"type":"Point"}
}