{
  "type": "Feature",
  "properties": {
    "addr:full":"2503 Santa Fe Ave Long Beach CA 90810",
    "addr:housenumber":"2503",
    "addr:postcode":"90810",
    "addr:street":"Santa Fe Ave",
    "iso:country":"US",
    "sg:address":"2503 Santa Fe Ave",
    "sg:city":"Long Beach",
    "sg:classifiers":[
        {
            "category":"Bars & Pubs",
            "type":"Food & Drink"
        }
    ],
    "sg:phone":"+1 562 424 0500",
    "sg:postcode":"90810",
    "sg:province":"CA",
    "wof:name":"Tooties Bar",
    "wof:placetype":"venue"
},
  "geometry": {"coordinates":[-118.21551700000001,33.804344],"type":"Point"}
}