{
  "type": "Feature",
  "properties": {
    "iso:country":"US",
    "sg:address":"2980 White Thorn Rd",
    "sg:city":"Shingle Springs",
    "sg:classifiers":[
        {
            "category":"Professional",
            "subcategory":"Lawyer & Legal Services",
            "type":"Services"
        }
    ],
    "sg:phone":"+1 530 676 5396",
    "sg:postcode":"95682",
    "sg:province":"CA",
    "sg:tags":[
        "attorney"
    ],
    "wof:name":"George Appelbaum",
    "wof:placetype":"venue"
},
  "geometry": {"coordinates":[-120.961676,38.561444],"type":"Point"}
}