{
  "type": "Feature",
  "properties": {
    "addr:full":"3801 S Harbor Blvd Ste B Santa Ana CA 92704",
    "addr:housenumber":"3801",
    "addr:postcode":"92704",
    "addr:street":"S Harbor Blvd Ste B",
    "iso:country":"US",
    "sg:address":"3801 S Harbor Blvd Ste B",
    "sg:city":"Santa Ana",
    "sg:classifiers":[
        {
            "category":"Health Services",
            "subcategory":"Chiropractor",
            "type":"Services"
        }
    ],
    "sg:phone":"+1 714 540 5555",
    "sg:postcode":"92704",
    "sg:province":"CA",
    "wof:name":"CsadC",
    "wof:placetype":"venue"
},
  "geometry": {"coordinates":[-117.919382,33.696719],"type":"Point"}
}