{
  "type": "Feature",
  "properties": {
    "addr:full":"508 W Ramsey St Banning CA 92220",
    "addr:housenumber":"508",
    "addr:postcode":"92220",
    "addr:street":"W Ramsey St",
    "iso:country":"US",
    "sg:address":"508 W Ramsey St",
    "sg:city":"Banning",
    "sg:classifiers":[
        {
            "category":"Retail",
            "subcategory":"Self-service Laundry",
            "type":"Services"
        }
    ],
    "sg:phone":"+1 951 922 1681",
    "sg:postcode":"92220",
    "sg:province":"CA",
    "wof:name":"Banning Laundromat",
    "wof:placetype":"venue"
},
  "geometry": {"coordinates":[-116.882251,33.925356],"type":"Point"}
}