{
  "type": "Feature",
  "properties": {
    "addr:full":"2542 W 3rd St Ste F Los Angeles CA 90057",
    "addr:housenumber":"2542",
    "addr:postcode":"90057",
    "addr:street":"W 3Rd St Ste F",
    "iso:country":"US",
    "sg:address":"2542 W 3rd St Ste F",
    "sg:city":"Los Angeles",
    "sg:classifiers":[
        {
            "category":"Health Services",
            "subcategory":"Dentist",
            "type":"Services"
        }
    ],
    "sg:phone":"+1 213 384 2204",
    "sg:postcode":"90057",
    "sg:province":"CA",
    "wof:name":"Ordonez Mariano M Jr DMD Fadi",
    "wof:placetype":"venue"
},
  "geometry": {"coordinates":[-118.27800000000001,34.065201],"type":"Point"}
}