{
  "type": "Feature",
  "properties": {
    "iso:country":"US",
    "sg:address":"1240 Bayshore Hwy",
    "sg:city":"Burlingame",
    "sg:classifiers":[
        {
            "category":"Manufacturing",
            "subcategory":"Buildings",
            "type":"Manufacturing & Wholesale Goods"
        },
        {
            "category":"Building & Trades",
            "subcategory":"Construction",
            "type":"Services"
        }
    ],
    "sg:phone":"+1 650 347 1555",
    "sg:postcode":"94010",
    "sg:province":"CA",
    "sg:tags":[
        "home",
        "builder",
        "contractor"
    ],
    "wof:name":"Ecc Coakley Camp Lejeune",
    "wof:placetype":"venue"
},
  "geometry": {"coordinates":[-122.362303,37.59201],"type":"Point"}
}