{
  "type": "Feature",
  "properties": {
    "addr:full":"28603 Milky Way Sun City CA 92586",
    "addr:postcode":"28603;92586",
    "addr:street":"Milky Way",
    "iso:country":"US",
    "sg:address":"28603 Milky Way",
    "sg:city":"Sun City",
    "sg:classifiers":[
        {
            "category":"Building & Trades",
            "subcategory":"Landscaping Services",
            "type":"Services"
        }
    ],
    "sg:phone":"+1 951 672 3123",
    "sg:postcode":"92586",
    "sg:province":"CA",
    "sg:tags":[
        "landscape"
    ],
    "wof:name":"Calscape",
    "wof:placetype":"venue"
},
  "geometry": {"coordinates":[-117.213967,33.706233],"type":"Point"}
}