{
  "type": "Feature",
  "properties": {
    "addr:full":"4680 Hidalgo Ave San Diego CA 92117",
    "addr:housenumber":"4680",
    "addr:postcode":"92117",
    "addr:street":"Hidalgo Ave",
    "iso:country":"US",
    "sg:address":"4680 Hidalgo Ave",
    "sg:city":"San Diego",
    "sg:classifiers":[
        {
            "category":"Social Services",
            "subcategory":"Child Care",
            "type":"Services"
        }
    ],
    "sg:phone":"+1 858 274 4509",
    "sg:postcode":"92117",
    "sg:province":"CA",
    "sg:tags":[
        "day"
    ],
    "wof:name":"Alcott Extended Day Child Care Program",
    "wof:placetype":"venue"
},
  "geometry": {"coordinates":[-117.221001,32.831902],"type":"Point"}
}