{
  "type": "Feature",
  "properties": {
    "addr:full":"4414 San Joaquin St Oceanside CA 92057",
    "addr:housenumber":"4414",
    "addr:postcode":"92057",
    "addr:street":"San Joaquin St",
    "iso:country":"US",
    "sg:address":"4414 San Joaquin St",
    "sg:city":"Oceanside",
    "sg:classifiers":[
        {
            "category":"Place Of Worship",
            "subcategory":"Church",
            "type":"Public Place"
        },
        {
            "category":"Place Of Worship",
            "type":"Public Place"
        }
    ],
    "sg:phone":"+1 760 721 8370",
    "sg:postcode":"92057",
    "sg:province":"CA",
    "sg:tags":[
        "churches-apostolic",
        "churches-pentecostal-apostolic"
    ],
    "wof:name":"Faith Tabernacle Apostolic Church Inc",
    "wof:placetype":"venue"
},
  "geometry": {"coordinates":[-117.321877,33.24284],"type":"Point"}
}