{
  "type": "Feature",
  "properties": {
    "addr:full":"9011 S Gate Ave South Gate CA 90280",
    "addr:housenumber":"9011",
    "addr:postcode":"90280",
    "addr:street":"S Gate Ave;Gate",
    "iso:country":"US",
    "sg:address":"9011 S Gate Ave",
    "sg:city":"South Gate",
    "sg:classifiers":[
        {
            "category":"Shopping",
            "subcategory":"Gifts & Souvenirs",
            "type":"Retail Goods"
        }
    ],
    "sg:phone":"+1 562 928 5888",
    "sg:postcode":"90280",
    "sg:province":"CA",
    "wof:name":"Craft Depot",
    "wof:placetype":"venue"
},
  "geometry": {"coordinates":[-118.214675,33.954737],"type":"Point"}
}