{
  "type": "Feature",
  "properties": {
    "iso:country":"US",
    "sg:address":"3930 Shoemake Ave",
    "sg:city":"Modesto",
    "sg:classifiers":[
        {
            "category":"Education",
            "subcategory":"School",
            "type":"Public Place"
        }
    ],
    "sg:phone":"+1 209 523 9979",
    "sg:postcode":"95358",
    "sg:province":"CA",
    "wof:name":"Hart-Ransom Union School",
    "wof:placetype":"venue"
},
  "geometry": {"coordinates":[-121.04698500000001,37.667469],"type":"Point"}
}