{
  "type": "Feature",
  "properties": {
    "addr:full":"5621 Palmer Way Carlsbad CA 92010",
    "addr:housenumber":"5621",
    "addr:postcode":"92010",
    "addr:street":"Palmer Way",
    "iso:country":"US",
    "sg:address":"5621 Palmer Way",
    "sg:city":"Carlsbad",
    "sg:classifiers":[
        {
            "category":"Shopping",
            "subcategory":"Bicycles & Sporting Goods",
            "type":"Retail Goods"
        }
    ],
    "sg:phone":"+1 760 438 7674",
    "sg:postcode":"92010",
    "sg:province":"CA",
    "sg:tags":[
        "snowboard"
    ],
    "wof:name":"Pacific Sports Group LLC",
    "wof:placetype":"venue"
},
  "geometry": {"coordinates":[-117.274016,33.141321],"type":"Point"}
}