{
  "type": "Feature",
  "properties": {
    "iso:country":"US",
    "sg:address":"8160 14th Ave",
    "sg:city":"Sacramento",
    "sg:classifiers":[
        {
            "category":"Manufacturing",
            "subcategory":"Metals",
            "type":"Manufacturing & Wholesale Goods"
        }
    ],
    "sg:phone":"+1 916 451 9126",
    "sg:postcode":"95826",
    "sg:province":"CA",
    "sg:tags":[
        "steel",
        "spring",
        "wire"
    ],
    "wof:name":"Hanley's Blacksmith & Spring",
    "wof:placetype":"venue"
},
  "geometry": {"coordinates":[-121.40662,38.539491],"type":"Point"}
}