{
  "type": "Feature",
  "properties": {
    "iso:country":"US",
    "sg:address":"24236 Archwood St",
    "sg:city":"West Hills",
    "sg:classifiers":[
        {
            "category":"Communications",
            "subcategory":"Film & Video Production",
            "type":"Services"
        }
    ],
    "sg:phone":"+1 818 917 6687",
    "sg:postcode":"91307",
    "sg:province":"CA",
    "sg:tags":[
        "animated"
    ],
    "wof:name":"Kai Animation",
    "wof:placetype":"venue"
},
  "geometry": {"coordinates":[-118.65193,34.192367],"type":"Point"}
}