{
  "type": "Feature",
  "properties": {
    "addr:full":"232 N Benwiley Ave Santa Maria CA 93458",
    "addr:housenumber":"232",
    "addr:postcode":"93458",
    "addr:street":"N Benwiley Ave",
    "iso:country":"US",
    "sg:address":"232 N Benwiley Ave",
    "sg:city":"Santa Maria",
    "sg:classifiers":[
        {
            "category":"Wholesale",
            "subcategory":"Groceries",
            "type":"Manufacturing & Wholesale Goods"
        }
    ],
    "sg:phone":"+1 805 922 6360",
    "sg:postcode":"93458",
    "sg:province":"CA",
    "sg:tags":[
        "delicatessen"
    ],
    "wof:name":"Sausage Co Silva Linguica",
    "wof:placetype":"venue"
},
  "geometry": {"coordinates":[-120.445623,34.95541],"type":"Point"}
}