{
  "type": "Feature",
  "properties": {
    "iso:country":"US",
    "sg:address":"382 S Mountain Ave",
    "sg:city":"Upland",
    "sg:classifiers":[
        {
            "category":"Personal",
            "subcategory":"Beauty Salon",
            "type":"Services"
        }
    ],
    "sg:phone":"+1 909 982 2920",
    "sg:postcode":"91786",
    "sg:province":"CA",
    "wof:name":"Great Clips",
    "wof:placetype":"venue"
},
  "geometry": {"coordinates":[-117.670064,34.092124],"type":"Point"}
}