{
  "type": "Feature",
  "properties": {
    "addr:full":"115 G St Lincoln CA 95648",
    "addr:housenumber":"115",
    "addr:postcode":"95648",
    "addr:street":"G St",
    "iso:country":"US",
    "sg:address":"115 G St",
    "sg:city":"Lincoln",
    "sg:classifiers":[
        {
            "category":"Restaurant",
            "type":"Food & Drink"
        }
    ],
    "sg:menulink":"http://www.allmenus.com/ca/west-valley/171827-burger-king/menu/",
    "sg:phone":"+1 916 645 6839",
    "sg:postcode":"95648",
    "sg:province":"CA",
    "sg:tags":[
        "burger",
        "american"
    ],
    "wof:name":"Burger King",
    "wof:placetype":"venue"
},
  "geometry": {"coordinates":[-121.29251499999999,38.886945],"type":"Point"}
}