{
  "type": "Feature",
  "properties": {
    "iso:country":"US",
    "sg:address":"31857 Hayman St",
    "sg:city":"Hayward",
    "sg:classifiers":[
        {
            "category":"Manufacturing",
            "subcategory":"Tools & Machinery",
            "type":"Manufacturing & Wholesale Goods"
        },
        {
            "category":"Wholesale",
            "subcategory":"Electrical",
            "type":"Manufacturing & Wholesale Goods"
        }
    ],
    "sg:phone":"+1 510 324 9070",
    "sg:postcode":"94544",
    "sg:province":"CA",
    "sg:tags":[
        "equipment",
        "manufacturer",
        "supplies-wholesale",
        "electric",
        "supply"
    ],
    "wof:name":"Advantage Electric Supply",
    "wof:placetype":"venue"
},
  "geometry": {"coordinates":[-122.045119,37.609551],"type":"Point"}
}