{
  "type": "Feature",
  "properties": {
    "addr:full":"10835 Santa Monica Blvd Los Angeles CA 90025",
    "addr:housenumber":"10835",
    "addr:postcode":"90025",
    "addr:street":"Santa Monica Blvd",
    "iso:country":"US",
    "sg:address":"10835 Santa Monica Blvd",
    "sg:city":"Los Angeles",
    "sg:classifiers":[
        {
            "category":"Travel",
            "subcategory":"Travel Agent",
            "type":"Entertainment"
        }
    ],
    "sg:phone":"+1 310 441 4739",
    "sg:postcode":"90025",
    "sg:province":"CA",
    "sg:tags":[
        "tours",
        "promoter"
    ],
    "wof:name":"Portofino Tours",
    "wof:placetype":"venue"
},
  "geometry": {"coordinates":[-118.436915,34.049956],"type":"Point"}
}