{
  "type": "Feature",
  "properties": {
    "iso:country":"US",
    "sg:address":"1 Malibu Ct",
    "sg:city":"Merced",
    "sg:classifiers":[
        {
            "category":"Manufacturing",
            "subcategory":"Watercraft",
            "type":"Manufacturing & Wholesale Goods"
        }
    ],
    "sg:phone":"+1 209 383 7469",
    "sg:postcode":"95341",
    "sg:province":"CA",
    "sg:website":"www.malibuboats.com",
    "wof:name":"Malibu Boats West Inc",
    "wof:placetype":"venue"
},
  "geometry": {"coordinates":[-120.52206200000001,37.287338],"type":"Point"}
}