{
  "type": "Feature",
  "properties": {
    "addr:full":"15 Kent St Petaluma CA 94952",
    "addr:housenumber":"15",
    "addr:postcode":"94952",
    "addr:street":"Kent St",
    "iso:country":"US",
    "sg:address":"15 Kent St",
    "sg:city":"Petaluma",
    "sg:classifiers":[
        {
            "category":"Manufacturing",
            "subcategory":"Printing",
            "type":"Manufacturing & Wholesale Goods"
        }
    ],
    "sg:phone":"+1 707 762 0510",
    "sg:postcode":"94952",
    "sg:province":"CA",
    "sg:tags":[
        "commercial"
    ],
    "wof:name":"Anchor & Acorn Press",
    "wof:placetype":"venue"
},
  "geometry": {"coordinates":[-122.64433,38.239633],"type":"Point"}
}