{
  "type": "Feature",
  "properties": {
    "iso:country":"US",
    "sg:address":"24427 Crenshaw Blvd Ste E",
    "sg:city":"Torrance",
    "sg:classifiers":[
        {
            "category":"Bagels",
            "subcategory":"None",
            "type":"Food & Drink"
        }
    ],
    "sg:phone":"+1 310 539 3582",
    "sg:postcode":"90505",
    "sg:province":"CA",
    "wof:name":"Lox of Bagel",
    "wof:placetype":"venue"
},
  "geometry": {"coordinates":[-118.328003,33.803299],"type":"Point"}
}