{
  "type": "Feature",
  "properties": {
    "iso:country":"US",
    "sg:address":"2372 Pacific Coast Hwy",
    "sg:city":"Lomita",
    "sg:classifiers":[
        {
            "category":"Restaurant",
            "type":"Food & Drink"
        }
    ],
    "sg:phone":"+1 310 784 0393",
    "sg:postcode":"90717",
    "sg:province":"CA",
    "sg:tags":[
        "mexican"
    ],
    "wof:name":"Alfredo's Restaurant No 4",
    "wof:placetype":"venue"
},
  "geometry": {"coordinates":[-118.324997,33.7896],"type":"Point"}
}