{
  "type": "Feature",
  "properties": {
    "iso:country":"US",
    "sg:address":"39 Bay St",
    "sg:city":"San Rafael",
    "sg:classifiers":[
        {
            "category":"Wholesale",
            "subcategory":"Construction Materials",
            "type":"Manufacturing & Wholesale Goods"
        }
    ],
    "sg:phone":"+1 415 454 4647",
    "sg:postcode":"94901",
    "sg:province":"CA",
    "sg:tags":[
        "marble"
    ],
    "sg:website":"www.carrera-marble.com",
    "wof:name":"Carrera Marble Co",
    "wof:placetype":"venue"
},
  "geometry": {"coordinates":[-122.515112,37.967926],"type":"Point"}
}