{
  "type": "Feature",
  "properties": {
    "iso:country":"US",
    "sg:address":"875 Quince Ave",
    "sg:city":"Santa Clara",
    "sg:classifiers":[
        {
            "category":"Organizations",
            "subcategory":"Religious Organization",
            "type":"Services"
        }
    ],
    "sg:phone":"+1 408 248 3621",
    "sg:postcode":"95051",
    "sg:province":"CA",
    "wof:name":"Corporation of President of Th",
    "wof:placetype":"venue"
},
  "geometry": {"coordinates":[-121.986213,37.340799],"type":"Point"}
}