{
  "type": "Feature",
  "properties": {
    "addr:full":"401 N Brand Blvd Glendale CA 91203",
    "addr:housenumber":"401",
    "addr:postcode":"91203",
    "addr:street":"N Brand Blvd",
    "iso:country":"US",
    "sg:address":"401 N Brand Blvd",
    "sg:city":"Glendale",
    "sg:classifiers":[
        {
            "category":"Communications",
            "type":"Services"
        }
    ],
    "sg:phone":"+1 818 956 8000",
    "sg:postcode":"91203",
    "sg:province":"CA",
    "sg:tags":[
        "communication"
    ],
    "wof:name":"Media Pcrs",
    "wof:placetype":"venue"
},
  "geometry": {"coordinates":[-118.255093,34.152913],"type":"Point"}
}