{
  "type": "Feature",
  "properties": {
    "iso:country":"US",
    "sg:address":"900 S Santa Anita Ave",
    "sg:city":"Arcadia",
    "sg:classifiers":[
        {
            "category":"Food & Beverages",
            "subcategory":"Specialty",
            "type":"Retail Goods"
        }
    ],
    "sg:phone":"+1 626 444 9400",
    "sg:postcode":"91006",
    "sg:province":"CA",
    "wof:name":"Nichols Egg Ranches",
    "wof:placetype":"venue"
},
  "geometry": {"coordinates":[-118.031237,34.129506],"type":"Point"}
}