{
  "type": "Feature",
  "properties": {
    "addr:full":"650 Lighthouse Ave Pacific Grove CA 93950",
    "addr:housenumber":"650",
    "addr:postcode":"93950",
    "addr:street":"Lighthouse Ave",
    "iso:country":"US",
    "sg:address":"650 Lighthouse Ave",
    "sg:city":"Pacific Grove",
    "sg:classifiers":[
        {
            "category":"Banks & Credit Unions",
            "subcategory":"Investment Brokerage",
            "type":"Services"
        }
    ],
    "sg:phone":"+1 831 375 4683",
    "sg:postcode":"93950",
    "sg:province":"CA",
    "sg:tags":[
        "consultant",
        "planning",
        "financial"
    ],
    "wof:name":"Sara Pashin Financial Svc",
    "wof:placetype":"venue"
},
  "geometry": {"coordinates":[-121.919408,36.62193],"type":"Point"}
}