{
  "type": "Feature",
  "properties": {
    "iso:country":"US",
    "sg:address":"305 E Olive Ave",
    "sg:city":"Porterville",
    "sg:classifiers":[
        {
            "category":"Food & Beverages",
            "subcategory":"Supermarket",
            "type":"Retail Goods"
        },
        {
            "category":"Food & Beverages",
            "subcategory":"Groceries & Convenience Stores",
            "type":"Retail Goods"
        }
    ],
    "sg:phone":"+1 559 306 1323",
    "sg:postcode":"93257",
    "sg:province":"CA",
    "sg:tags":[
        "super"
    ],
    "wof:name":"Vallarta Supermarkets",
    "wof:placetype":"venue"
},
  "geometry": {"coordinates":[-119.012607,36.065097],"type":"Point"}
}