{
  "type": "Feature",
  "properties": {
    "iso:country":"US",
    "sg:address":"13273 Ventura Blvd Ste 209",
    "sg:city":"Studio City",
    "sg:classifiers":[
        {
            "category":"Building & Trades",
            "subcategory":"Construction",
            "type":"Services"
        }
    ],
    "sg:phone":"+1 818 905 1004",
    "sg:postcode":"91604",
    "sg:province":"CA",
    "sg:tags":[
        "contractor"
    ],
    "wof:name":"Race Point Inc",
    "wof:placetype":"venue"
},
  "geometry": {"coordinates":[-118.421997,34.1465],"type":"Point"}
}