{
  "type": "Feature",
  "properties": {
    "addr:full":"15556 Pomona Rincon Rd Chino Hills CA 91709",
    "addr:housenumber":"15556",
    "addr:postcode":"91709",
    "addr:street":"Pomona Rincon Rd",
    "iso:country":"US",
    "sg:address":"15556 Pomona Rincon Rd",
    "sg:city":"Chino Hills",
    "sg:classifiers":[
        {
            "category":"Professional",
            "subcategory":"Art Services",
            "type":"Services"
        }
    ],
    "sg:phone":"+1 909 606 0351",
    "sg:postcode":"91709",
    "sg:province":"CA",
    "sg:tags":[
        "artist"
    ],
    "wof:name":"Kolor Kings",
    "wof:placetype":"venue"
},
  "geometry": {"coordinates":[-117.69270299999999,33.969683],"type":"Point"}
}