{
  "type": "Feature",
  "properties": {
    "addr:full":"43767 Boscell Rd Fremont CA 94538",
    "addr:housenumber":"43767",
    "addr:postcode":"94538",
    "addr:street":"Boscell Rd",
    "iso:country":"US",
    "sg:address":"43767 Boscell Rd",
    "sg:city":"Fremont",
    "sg:classifiers":[
        {
            "category":"Restaurant",
            "type":"Food & Drink"
        }
    ],
    "sg:menulink":"http://www.allmenus.com/ca/fremont/276185-a-la-shanghai/menu/",
    "sg:phone":"+1 650 324 8749",
    "sg:postcode":"94538",
    "sg:province":"CA",
    "sg:tags":[
        "asian",
        "chinese"
    ],
    "wof:name":"A La Shanghai",
    "wof:placetype":"venue"
},
  "geometry": {"coordinates":[-121.973343,37.500785],"type":"Point"}
}