{
  "type": "Feature",
  "properties": {
    "iso:country":"US",
    "sg:address":"24100 Avalon Blvd",
    "sg:city":"Carson",
    "sg:classifiers":[
        {
            "category":"Organizations",
            "subcategory":"Religious Organization",
            "type":"Services"
        }
    ],
    "sg:phone":"+1 310 834 6951",
    "sg:postcode":"90745",
    "sg:province":"CA",
    "sg:tags":[
        "church"
    ],
    "wof:name":"Rock Of Salvation",
    "wof:placetype":"venue"
},
  "geometry": {"coordinates":[-118.264008,33.805772],"type":"Point"}
}