{
  "type": "Feature",
  "properties": {
    "addr:full":"1653 E Emerald Ave Fresno CA 93720",
    "addr:housenumber":"1653",
    "addr:postcode":"93720",
    "addr:street":"E Emerald Ave",
    "iso:country":"US",
    "sg:address":"1653 E Emerald Ave",
    "sg:city":"Fresno",
    "sg:classifiers":[
        {
            "category":"Personal",
            "subcategory":"Adult",
            "type":"Services"
        }
    ],
    "sg:phone":"+1 559 434 4216",
    "sg:postcode":"93720",
    "sg:province":"CA",
    "sg:tags":[
        "escort"
    ],
    "wof:name":"Executive Referral Svc",
    "wof:placetype":"venue"
},
  "geometry": {"coordinates":[-119.754261,36.87904],"type":"Point"}
}