{
  "type": "Feature",
  "properties": {
    "addr:full":"5660 Stockdale Hwy Bakersfield CA 93309",
    "addr:housenumber":"5660",
    "addr:postcode":"93309",
    "addr:street":"Stockdale Hwy",
    "iso:country":"US",
    "sg:address":"5660 Stockdale Hwy",
    "sg:city":"Bakersfield",
    "sg:classifiers":[
        {
            "category":"Cinema",
            "subcategory":"Movie Rental",
            "type":"Entertainment"
        }
    ],
    "sg:phone":"+1 661 631 1373",
    "sg:postcode":"93309",
    "sg:province":"CA",
    "sg:tags":[
        "leasing",
        "video",
        "disc",
        "tape"
    ],
    "sg:website":"www.hollywoodvideo.com",
    "wof:name":"Hollywood Video",
    "wof:placetype":"venue"
},
  "geometry": {"coordinates":[-119.06383099999999,35.354324],"type":"Point"}
}