{
  "type": "Feature",
  "properties": {
    "addr:full":"300 Montgomery Street Suite 1200 San Francisco CA 94104",
    "addr:housenumber":"300",
    "addr:postcode":"94104",
    "addr:street":"Montgomery Street Suite 1200",
    "iso:country":"US",
    "sg:address":"300 Montgomery Street Suite 1200",
    "sg:city":"San Francisco",
    "sg:classifiers":[
        {
            "category":"Professional",
            "subcategory":"Accounting & Tax Preparation",
            "type":"Services"
        }
    ],
    "sg:phone":"+1 415 956 8323",
    "sg:postcode":"94104",
    "sg:province":"CA",
    "sg:tags":[
        "accountant"
    ],
    "wof:name":"Rgl Gallagher Ilp",
    "wof:placetype":"venue"
},
  "geometry": {"coordinates":[-122.40253,37.791936],"type":"Point"}
}