{
  "type": "Feature",
  "properties": {
    "iso:country":"US",
    "sg:address":"1348 Abbot Kinney Blvd",
    "sg:city":"Venice",
    "sg:classifiers":[
        {
            "category":"Building & Trades",
            "subcategory":"Construction",
            "type":"Services"
        }
    ],
    "sg:phone":"+1 310 392 8887",
    "sg:postcode":"90291",
    "sg:province":"CA",
    "sg:tags":[
        "contractor"
    ],
    "wof:name":"Eis Designs",
    "wof:placetype":"venue"
},
  "geometry": {"coordinates":[-118.46617500000001,33.990621],"type":"Point"}
}