{
  "type": "Feature",
  "properties": {
    "iso:country":"US",
    "sg:address":"1970 Straits View Dr",
    "sg:city":"Belvedere Tibrn",
    "sg:classifiers":[
        {
            "category":"Real Estate",
            "subcategory":"Architect",
            "type":"Services"
        }
    ],
    "sg:phone":"+1 415 435 2000",
    "sg:postcode":"94920",
    "sg:province":"CA",
    "sg:website":"www.dkassociates.com",
    "wof:name":"Danadjieva & Koenig Assoc",
    "wof:placetype":"venue"
},
  "geometry": {"coordinates":[-122.449799,37.879214],"type":"Point"}
}