{
  "type": "Feature",
  "properties": {
    "iso:country":"US",
    "sg:address":"120 McHenry Ave",
    "sg:city":"Modesto",
    "sg:classifiers":[
        {
            "category":"Retail",
            "subcategory":"Auto Repair",
            "type":"Services"
        }
    ],
    "sg:phone":"+1 209 544 0445",
    "sg:postcode":"95354",
    "sg:province":"CA",
    "sg:tags":[
        "automobile",
        "lubrication"
    ],
    "sg:website":"www.oilcanhenry.com",
    "wof:name":"Oil Can Henry's",
    "wof:placetype":"venue"
},
  "geometry": {"coordinates":[-120.99363099999999,37.645692],"type":"Point"}
}