{
  "type": "Feature",
  "properties": {
    "iso:country":"US",
    "sg:address":"1213 Gordon St",
    "sg:city":"Los Angeles",
    "sg:classifiers":[
        {
            "category":"Real Estate",
            "subcategory":"Real Estate Agent",
            "type":"Services"
        }
    ],
    "sg:phone":"+1 323 572 0267",
    "sg:postcode":"90038",
    "sg:province":"CA",
    "sg:tags":[
        "investing"
    ],
    "wof:name":"Time Limit Inc",
    "wof:placetype":"venue"
},
  "geometry": {"coordinates":[-118.320172,34.094175],"type":"Point"}
}