{
  "type": "Feature",
  "properties": {
    "iso:country":"US",
    "sg:address":"2211 Lawson Ln",
    "sg:city":"Santa Clara",
    "sg:classifiers":[
        {
            "category":"Manufacturing",
            "subcategory":"Electronics",
            "type":"Manufacturing & Wholesale Goods"
        }
    ],
    "sg:phone":"+1 408 654 5600",
    "sg:postcode":"95054",
    "sg:province":"CA",
    "sg:tags":[
        "mfg",
        "comm",
        "sat"
    ],
    "wof:name":"Vertex Communications Corp",
    "wof:placetype":"venue"
},
  "geometry": {"coordinates":[-121.963649,37.374322],"type":"Point"}
}