{
  "type": "Feature",
  "properties": {
    "iso:country":"US",
    "sg:address":"3401 Wible Rd",
    "sg:city":"Bakersfield",
    "sg:classifiers":[
        {
            "category":"Real Estate",
            "subcategory":"Developer",
            "type":"Services"
        }
    ],
    "sg:phone":"+1 661 834 0640",
    "sg:postcode":"93309",
    "sg:province":"CA",
    "wof:name":"St Clair Development",
    "wof:placetype":"venue"
},
  "geometry": {"coordinates":[-119.039033,35.320415],"type":"Point"}
}