{
  "type": "Feature",
  "properties": {
    "addr:full":"14034 Ventura Blvd Sherman Oaks CA 91423",
    "addr:housenumber":"14034",
    "addr:postcode":"91423",
    "addr:street":"Ventura Blvd",
    "iso:country":"US",
    "sg:address":"14034 Ventura Blvd",
    "sg:city":"Sherman Oaks",
    "sg:classifiers":[
        {
            "category":"Shopping",
            "subcategory":"Jewelry",
            "type":"Retail Goods"
        },
        {
            "category":"Shopping",
            "subcategory":"Antiques",
            "type":"Retail Goods"
        }
    ],
    "sg:phone":"+1 818 906 0338",
    "sg:postcode":"91423",
    "sg:province":"CA",
    "sg:website":"www.soantiquemall.com",
    "wof:name":"Sherman Oaks Antique Mall",
    "wof:placetype":"venue"
},
  "geometry": {"coordinates":[-118.438537,34.148938],"type":"Point"}
}