{
  "type": "Feature",
  "properties": {
    "iso:country":"US",
    "sg:address":"1149 S Hill St",
    "sg:city":"Los Angeles",
    "sg:classifiers":[
        {
            "category":"Real Estate",
            "subcategory":"Real Estate Agent",
            "type":"Services"
        }
    ],
    "sg:phone":"+1 213 741 7400",
    "sg:postcode":"90015",
    "sg:province":"CA",
    "wof:name":"C B Richard Ellis",
    "wof:placetype":"venue"
},
  "geometry": {"coordinates":[-118.26066400000001,34.039489],"type":"Point"}
}