{
  "type": "Feature",
  "properties": {
    "addr:full":"1800 San Carlos Ave Ste 7 San Carlos CA 94070",
    "addr:housenumber":"1800",
    "addr:postcode":"94070",
    "addr:street":"San Carlos Ave Ste 7",
    "iso:country":"US",
    "sg:address":"1800 San Carlos Ave Ste 7",
    "sg:city":"San Carlos",
    "sg:classifiers":[
        {
            "category":"Personal",
            "type":"Services"
        }
    ],
    "sg:phone":"+1 650 921 5537",
    "sg:postcode":"94070",
    "sg:province":"CA",
    "sg:tags":[
        "mover"
    ],
    "sg:website":"www.armalanservices.com",
    "wof:name":"Armalan Moving Services LLC",
    "wof:placetype":"venue"
},
  "geometry": {"coordinates":[-122.266687,37.5028],"type":"Point"}
}