{
  "type": "Feature",
  "properties": {
    "iso:country":"US",
    "sg:address":"3195 Red Hill Ave Suite E",
    "sg:city":"Costa Mesa",
    "sg:classifiers":[
        {
            "category":"Retail",
            "subcategory":"Event Space",
            "type":"Services"
        }
    ],
    "sg:phone":"+1 714 545 9900",
    "sg:postcode":"92626",
    "sg:province":"CA",
    "sg:tags":[
        "venue"
    ],
    "sg:website":"www.juxtapositionhome.com/juxtap...",
    "wof:name":"Juxtapositon Studio",
    "wof:placetype":"venue"
},
  "geometry": {"coordinates":[-117.87075299999999,33.684781],"type":"Point"}
}