{
  "type": "Feature",
  "properties": {
    "addr:full":"212 Kruse Ave Monrovia CA 91016",
    "addr:housenumber":"212",
    "addr:postcode":"91016",
    "addr:street":"Kruse Ave",
    "iso:country":"US",
    "sg:address":"212 Kruse Ave",
    "sg:city":"Monrovia",
    "sg:classifiers":[
        {
            "category":"Wholesale",
            "subcategory":"Auto Parts",
            "type":"Manufacturing & Wholesale Goods"
        }
    ],
    "sg:phone":"+1 626 305 0860",
    "sg:postcode":"91016",
    "sg:province":"CA",
    "wof:name":"Golden State Automotive Entprs",
    "wof:placetype":"venue"
},
  "geometry": {"coordinates":[-117.99966000000001,34.127625],"type":"Point"}
}