{
  "type": "Feature",
  "properties": {
    "addr:full":"2618 Lunar Ln Sacramento CA 95864",
    "addr:housenumber":"2618",
    "addr:postcode":"95864",
    "addr:street":"Lunar Ln",
    "iso:country":"US",
    "sg:address":"2618 Lunar Ln",
    "sg:city":"Sacramento",
    "sg:classifiers":[
        {
            "category":"Local Transit",
            "type":"Transportation"
        }
    ],
    "sg:phone":"+1 916 482 5200",
    "sg:postcode":"95864",
    "sg:province":"CA",
    "sg:tags":[
        "limousine"
    ],
    "sg:website":"www.gobarrett.com",
    "wof:name":"Barrett Executive Trnsprtn",
    "wof:placetype":"venue"
},
  "geometry": {"coordinates":[-121.40059599999999,38.582435],"type":"Point"}
}