{
  "type": "Feature",
  "properties": {
    "iso:country":"US",
    "sg:address":"1950 E 20th St",
    "sg:city":"Chico",
    "sg:classifiers":[
        {
            "category":"Banks & Credit Unions",
            "subcategory":"Bank",
            "type":"Services"
        }
    ],
    "sg:phone":"+1 530 343 3541",
    "sg:postcode":"95928",
    "sg:province":"CA",
    "sg:tags":[
        "loan",
        "real estate"
    ],
    "wof:name":"Beneficial California Inc",
    "wof:placetype":"venue"
},
  "geometry": {"coordinates":[-121.80263,39.727383],"type":"Point"}
}