{
  "type": "Feature",
  "properties": {
    "iso:country":"US",
    "sg:address":"2651 Donner Trl",
    "sg:city":"Riverbank",
    "sg:classifiers":[
        {
            "category":"Banks & Credit Unions",
            "subcategory":"Bank",
            "type":"Services"
        }
    ],
    "sg:phone":"+1 209 342 0800",
    "sg:postcode":"95357",
    "sg:province":"CA",
    "sg:tags":[
        "loan",
        "real estate"
    ],
    "wof:name":"Union Street Mortgage",
    "wof:placetype":"venue"
},
  "geometry": {"coordinates":[-120.947955,37.716026],"type":"Point"}
}