{
  "type": "Feature",
  "properties": {
    "addr:full":"1118 Pacific Coast Hwy Unit C Huntington Beach CA 92648",
    "addr:housenumber":"1118",
    "addr:postcode":"92648",
    "addr:street":"Pacific Coast Hwy Unit C",
    "iso:country":"US",
    "sg:address":"1118 Pacific Coast Hwy Unit C",
    "sg:city":"Huntington Beach",
    "sg:classifiers":[
        {
            "category":"Insurance",
            "subcategory":"Hazard Insurance",
            "type":"Services"
        }
    ],
    "sg:phone":"+1 877 840 0554",
    "sg:postcode":"92648",
    "sg:province":"CA",
    "sg:website":"www.ca-insurancefinder.com",
    "wof:name":"California Insurance Finder",
    "wof:placetype":"venue"
},
  "geometry": {"coordinates":[-118.007932,33.661976],"type":"Point"}
}