{
  "type": "Feature",
  "properties": {
    "iso:country":"US",
    "sg:address":"5600 Rickenbacker Rd",
    "sg:city":"Bell",
    "sg:classifiers":[
        {
            "category":"Government",
            "subcategory":"Office",
            "type":"Public Place"
        }
    ],
    "sg:phone":"+1 213 894 5363",
    "sg:postcode":"90201",
    "sg:province":"CA",
    "sg:tags":[
        "fish",
        "inspection"
    ],
    "wof:name":"National Ocnic Atmospheric Adm",
    "wof:placetype":"venue"
},
  "geometry": {"coordinates":[-118.162994,33.989264],"type":"Point"}
}