{
  "type": "Feature",
  "properties": {
    "iso:country":"US",
    "sg:address":"10623 S Vermont Ave",
    "sg:city":"Los Angeles",
    "sg:classifiers":[
        {
            "category":"Retail",
            "subcategory":"Repair Shop",
            "type":"Services"
        }
    ],
    "sg:phone":"+1 323 777 5589",
    "sg:postcode":"90044",
    "sg:province":"CA",
    "sg:tags":[
        "upholsterer"
    ],
    "wof:name":"Kelly's Custom Upholstery",
    "wof:placetype":"venue"
},
  "geometry": {"coordinates":[-118.291911,33.939107],"type":"Point"}
}