{
  "type": "Feature",
  "properties": {
    "addr:full":"28420 Yosemite Springs Pkwy Coarsegold CA 93614",
    "addr:housenumber":"28420",
    "addr:postcode":"93614",
    "addr:street":"Yosemite Springs Pkwy",
    "iso:country":"US",
    "sg:address":"28420 Yosemite Springs Pkwy",
    "sg:city":"Coarsegold",
    "sg:classifiers":[
        {
            "category":"Education",
            "subcategory":"School",
            "type":"Public Place"
        }
    ],
    "sg:phone":"+1 559 683 0808",
    "sg:postcode":"93614",
    "sg:province":"CA",
    "wof:name":"Chawanakee Home Study School",
    "wof:placetype":"venue"
},
  "geometry": {"coordinates":[-119.748244,37.161541],"type":"Point"}
}