{
  "type": "Feature",
  "properties": {
    "addr:full":"66 Schooner Hl Oakland CA 94618",
    "addr:housenumber":"66",
    "addr:postcode":"94618",
    "addr:street":"Schooner",
    "iso:country":"US",
    "sg:address":"66 Schooner Hl",
    "sg:city":"Oakland",
    "sg:classifiers":[
        {
            "category":"Professional",
            "subcategory":"Employment Agencies",
            "type":"Services"
        }
    ],
    "sg:phone":"+1 510 385 7273",
    "sg:postcode":"94618",
    "sg:province":"CA",
    "sg:tags":[
        "consultants-referral"
    ],
    "wof:name":"Adrem Biotech Inc.",
    "wof:placetype":"venue"
},
  "geometry": {"coordinates":[-122.225731,37.854338],"type":"Point"}
}