{
  "type": "Feature",
  "properties": {
    "iso:country":"US",
    "sg:address":"727 Line St",
    "sg:city":"Hollister",
    "sg:classifiers":[
        {
            "category":"Farming",
            "subcategory":"Farm",
            "type":"Manufacturing & Wholesale Goods"
        }
    ],
    "sg:phone":"+1 831 637 1344",
    "sg:postcode":"95023",
    "sg:province":"CA",
    "sg:tags":[
        "crop",
        "general"
    ],
    "wof:name":"P Fancher",
    "wof:placetype":"venue"
},
  "geometry": {"coordinates":[-121.412857,36.849345],"type":"Point"}
}