{
  "type": "Feature",
  "properties": {
    "iso:country":"US",
    "sg:address":"7636 N Ingram Ave",
    "sg:city":"Fresno",
    "sg:classifiers":[
        {
            "category":"Professional",
            "subcategory":"Management & Consulting",
            "type":"Services"
        }
    ],
    "sg:phone":"+1 559 437 3884",
    "sg:postcode":"93650",
    "sg:province":"CA",
    "sg:tags":[
        "accident",
        "reconstruction"
    ],
    "sg:website":"www.j2eng.com",
    "wof:name":"J 2 Engineering",
    "wof:placetype":"venue"
},
  "geometry": {"coordinates":[-119.801756,36.846769],"type":"Point"}
}