{
  "type": "Feature",
  "properties": {
    "iso:country":"US",
    "sg:address":"980 Admiral Callaghan Ln",
    "sg:city":"Vallejo",
    "sg:classifiers":[
        {
            "category":"Restaurant",
            "type":"Food & Drink"
        }
    ],
    "sg:phone":"+1 707 557 4551",
    "sg:postcode":"94591",
    "sg:province":"CA",
    "sg:tags":[
        "family"
    ],
    "wof:name":"Lyons Restaurant 441",
    "wof:placetype":"venue"
},
  "geometry": {"coordinates":[-122.222475,38.133917],"type":"Point"}
}