{
  "type": "Feature",
  "properties": {
    "addr:full":"1440 S Cochran Ave Los Angeles CA 90019",
    "addr:housenumber":"1440",
    "addr:postcode":"90019",
    "addr:street":"S Cochran Ave",
    "iso:country":"US",
    "sg:address":"1440 S Cochran Ave",
    "sg:city":"Los Angeles",
    "sg:classifiers":[
        {
            "category":"Health Services",
            "subcategory":"Hospital",
            "type":"Services"
        }
    ],
    "sg:phone":"+1 323 934 0158",
    "sg:postcode":"90019",
    "sg:province":"CA",
    "sg:tags":[
        "specialty"
    ],
    "wof:name":"A W Sober Living",
    "wof:placetype":"venue"
},
  "geometry": {"coordinates":[-118.353185,34.046939],"type":"Point"}
}