{
  "type": "Feature",
  "properties": {
    "iso:country":"US",
    "sg:address":"200 Old Ranch Rd",
    "sg:city":"Santa Cruz",
    "sg:classifiers":[
        {
            "category":"Professional",
            "subcategory":"Advertising",
            "type":"Services"
        }
    ],
    "sg:phone":"+1 831 423 5249",
    "sg:postcode":"95060",
    "sg:province":"CA",
    "sg:website":"www.kidsafetyproducts.com",
    "wof:name":"KIDSAFETYPRODUCTS.COM",
    "wof:placetype":"venue"
},
  "geometry": {"coordinates":[-122.010572,37.004957],"type":"Point"}
}