{
  "type": "Feature",
  "properties": {
    "addr:full":"4955 Van Nuys Blvd Ste 502 Van Nuys CA 91403",
    "addr:housenumber":"4955",
    "addr:postcode":"91403",
    "addr:street":"Van Nuys Blvd Ste 502",
    "iso:country":"US",
    "sg:address":"4955 Van Nuys Blvd Ste 502",
    "sg:city":"Van Nuys",
    "sg:classifiers":[
        {
            "category":"Health Services",
            "subcategory":"Doctor",
            "type":"Services"
        }
    ],
    "sg:phone":"+1 818 325 0200",
    "sg:postcode":"91403",
    "sg:province":"CA",
    "sg:website":"www.mvpsleepdiagnosticlab.com",
    "wof:name":"Mid Valley Pulmonary Medical Group",
    "wof:placetype":"venue"
},
  "geometry": {"coordinates":[-118.44885499999999,34.160429],"type":"Point"}
}