{
  "type": "Feature",
  "properties": {
    "iso:country":"US",
    "sg:address":"21739 Rd 19",
    "sg:city":"Chowchilla",
    "sg:classifiers":[
        {
            "category":"Utilities",
            "subcategory":"Refuse",
            "type":"Services"
        }
    ],
    "sg:phone":"+1 559 665 3099",
    "sg:postcode":"93610",
    "sg:province":"CA",
    "sg:tags":[
        "garbage",
        "collection"
    ],
    "wof:name":"Madera Disposal Systems Inc",
    "wof:placetype":"venue"
},
  "geometry": {"coordinates":[-120.20234600000001,37.065701],"type":"Point"}
}