{
  "type": "Feature",
  "properties": {
    "addr:full":"1806 Monticello Rd Napa CA 94558",
    "addr:housenumber":"1806",
    "addr:postcode":"94558",
    "addr:street":"Monticello Rd",
    "iso:country":"US",
    "sg:address":"1806 Monticello Rd",
    "sg:city":"Napa",
    "sg:classifiers":[
        {
            "category":"Farming",
            "subcategory":"Livestock Farm",
            "type":"Manufacturing & Wholesale Goods"
        }
    ],
    "sg:phone":"+1 707 255 0275",
    "sg:postcode":"94558",
    "sg:province":"CA",
    "sg:tags":[
        "ranch",
        "cattle"
    ],
    "wof:name":"Bishop Cattle Company",
    "wof:placetype":"venue"
},
  "geometry": {"coordinates":[-122.26175499999999,38.337032],"type":"Point"}
}