{
  "type": "Feature",
  "properties": {
    "iso:country":"US",
    "sg:address":"25652 Old Trabuco Rd",
    "sg:city":"Lake Forest",
    "sg:classifiers":[
        {
            "category":"Health Services",
            "subcategory":"Nursing And Care Facility",
            "type":"Services"
        }
    ],
    "sg:phone":"+1 949 380 9380",
    "sg:postcode":"92630",
    "sg:province":"CA",
    "sg:tags":[
        "home",
        "medical",
        "skilled",
        "convalescent"
    ],
    "sg:website":"www.lcca.com",
    "wof:name":"Lake Forest Nursing Center",
    "wof:placetype":"venue"
},
  "geometry": {"coordinates":[-117.682721,33.645313],"type":"Point"}
}