{
  "type": "Feature",
  "properties": {
    "addr:full":"400 Capitol Mall Sacramento CA 95814",
    "addr:housenumber":"400",
    "addr:postcode":"95814",
    "addr:street":"Capitol Mall",
    "iso:country":"US",
    "sg:address":"400 Capitol Mall",
    "sg:city":"Sacramento",
    "sg:classifiers":[
        {
            "category":"Professional",
            "subcategory":"Accounting & Tax Preparation",
            "type":"Services"
        }
    ],
    "sg:phone":"+1 916 442 9100",
    "sg:postcode":"95814",
    "sg:province":"CA",
    "sg:tags":[
        "accountant"
    ],
    "sg:website":"www.reznickgroup.com",
    "wof:name":"Norwood Mary Beth CPA",
    "wof:placetype":"venue"
},
  "geometry": {"coordinates":[-121.502926,38.579005],"type":"Point"}
}