{
  "type": "Feature",
  "properties": {
    "iso:country":"US",
    "sg:address":"6965 El Camino Real Ste 105 #559",
    "sg:city":"Carlsbad",
    "sg:classifiers":[
        {
            "category":"Professional",
            "subcategory":"Advertising",
            "type":"Services"
        },
        {
            "category":"Professional",
            "subcategory":"Business Services",
            "type":"Services"
        },
        {
            "category":"Communications",
            "type":"Services"
        }
    ],
    "sg:phone":"+1 760 822 0556",
    "sg:postcode":"92011",
    "sg:province":"CA",
    "sg:tags":[
        "marketing",
        "design",
        "public",
        "relation",
        "web"
    ],
    "sg:website":"www.firestartermarketing.com",
    "wof:name":"Firestarter Consulting",
    "wof:placetype":"venue"
},
  "geometry": {"coordinates":[-117.266773,33.103249],"type":"Point"}
}