{
  "type": "Feature",
  "properties": {
    "iso:country":"US",
    "sg:address":"833 S Spring St",
    "sg:city":"Los Angeles",
    "sg:classifiers":[
        {
            "category":"Wholesale",
            "subcategory":"Apparel",
            "type":"Manufacturing & Wholesale Goods"
        },
        {
            "category":"Manufacturing",
            "subcategory":"Apparel",
            "type":"Manufacturing & Wholesale Goods"
        }
    ],
    "sg:phone":"+1 213 629 1810",
    "sg:postcode":"90014",
    "sg:province":"CA",
    "sg:tags":[
        "clothing",
        "contemporary",
        "mfg"
    ],
    "wof:name":"Beautiful People",
    "wof:placetype":"venue"
},
  "geometry": {"coordinates":[-118.254678,34.042144],"type":"Point"}
}