{
  "type": "Feature",
  "properties": {
    "iso:country":"US",
    "sg:address":"42156 10th St W",
    "sg:city":"Lancaster",
    "sg:classifiers":[
        {
            "category":"Social Services",
            "type":"Services"
        }
    ],
    "sg:phone":"+1 661 942 1027",
    "sg:postcode":"93534",
    "sg:province":"CA",
    "sg:tags":[
        "counselor",
        "marriage",
        "family"
    ],
    "wof:name":"Rosemary Peterson",
    "wof:placetype":"venue"
},
  "geometry": {"coordinates":[-118.147582,34.647994],"type":"Point"}
}