{
  "type": "Feature",
  "properties": {
    "iso:country":"US",
    "sg:address":"2930 W Imperial Hwy",
    "sg:city":"Inglewood",
    "sg:classifiers":[
        {
            "category":"Manufacturing",
            "subcategory":"Printing",
            "type":"Manufacturing & Wholesale Goods"
        }
    ],
    "sg:phone":"+1 323 755 7600",
    "sg:postcode":"90303",
    "sg:province":"CA",
    "sg:tags":[
        "commercial"
    ],
    "wof:name":"Tj Enterprise Publications",
    "wof:placetype":"venue"
},
  "geometry": {"coordinates":[-118.32572,33.930824],"type":"Point"}
}