{
  "type": "Feature",
  "properties": {
    "iso:country":"US",
    "sg:address":"1638 Colorado Boulevard",
    "sg:city":"Los Angeles",
    "sg:classifiers":[
        {
            "category":"Education",
            "subcategory":"Special Training",
            "type":"Public Place"
        }
    ],
    "sg:phone":"+1 323 478 0644",
    "sg:postcode":"90041",
    "sg:province":"CA",
    "sg:tags":[
        "school",
        "art"
    ],
    "wof:name":"The Chouinard Foundation",
    "wof:placetype":"venue"
},
  "geometry": {"coordinates":[-118.202365,34.13949],"type":"Point"}
}