{
  "type": "Feature",
  "properties": {
    "addr:full":"12904 Maxwell Dr Tustin CA 92782",
    "addr:housenumber":"12904",
    "addr:postcode":"92782",
    "addr:street":"Maxwell Dr",
    "iso:country":"US",
    "sg:address":"12904 Maxwell Dr",
    "sg:city":"Tustin",
    "sg:classifiers":[
        {
            "category":"Wholesale",
            "subcategory":"Home Furnishings",
            "type":"Manufacturing & Wholesale Goods"
        }
    ],
    "sg:phone":"+1 714 273 1271",
    "sg:postcode":"92782",
    "sg:province":"CA",
    "wof:name":"Aka Home Decor",
    "wof:placetype":"venue"
},
  "geometry": {"coordinates":[-117.78945400000001,33.736292],"type":"Point"}
}