{
  "type": "Feature",
  "properties": {
    "iso:country":"US",
    "sg:address":"6442 N Maroa Ave",
    "sg:city":"Fresno",
    "sg:classifiers":[
        {
            "category":"Banks & Credit Unions",
            "subcategory":"Bank",
            "type":"Services"
        }
    ],
    "sg:phone":"+1 559 322 4420",
    "sg:postcode":"93704",
    "sg:province":"CA",
    "sg:tags":[
        "loan",
        "real estate"
    ],
    "wof:name":"World Charter Mortgage",
    "wof:placetype":"venue"
},
  "geometry": {"coordinates":[-119.79922500000001,36.830762],"type":"Point"}
}