{
  "type": "Feature",
  "properties": {
    "iso:country":"US",
    "sg:address":"77564 Country Club Dr",
    "sg:city":"Palm Desert",
    "sg:classifiers":[
        {
            "category":"Organizations",
            "subcategory":"Non-profit Organization",
            "type":"Services"
        }
    ],
    "sg:phone":"+1 760 772 4287",
    "sg:postcode":"92211",
    "sg:province":"CA",
    "sg:tags":[
        "charitable",
        "institution"
    ],
    "wof:name":"Allied Funding Group",
    "wof:placetype":"venue"
},
  "geometry": {"coordinates":[-116.31610000000001,33.758352],"type":"Point"}
}