{
  "type": "Feature",
  "properties": {
    "iso:country":"US",
    "sg:address":"1019 N Lemoore Ave",
    "sg:city":"Lemoore",
    "sg:classifiers":[
        {
            "category":"Restaurant",
            "type":"Food & Drink"
        }
    ],
    "sg:menulink":"http://www.allmenus.com/ca/lemoore/197692-kfc---kentucky-fried-chicken/menu/",
    "sg:phone":"+1 559 924 2744",
    "sg:postcode":"93245",
    "sg:province":"CA",
    "sg:tags":[
        "american",
        "chicken"
    ],
    "wof:name":"KFC - Kentucky Fried Chicken",
    "wof:placetype":"venue"
},
  "geometry": {"coordinates":[-119.780846,36.311821],"type":"Point"}
}