{
  "type": "Feature",
  "properties": {
    "addr:full":"10511 Long Beach Blvd Lynwood CA 90262",
    "addr:housenumber":"10511",
    "addr:postcode":"90262",
    "addr:street":"Long Beach Blvd",
    "iso:country":"US",
    "sg:address":"10511 Long Beach Blvd",
    "sg:city":"Lynwood",
    "sg:classifiers":[
        {
            "category":"Professional",
            "subcategory":"Accounting & Tax Preparation",
            "type":"Services"
        }
    ],
    "sg:phone":"+1 323 249 5117",
    "sg:postcode":"90262",
    "sg:province":"CA",
    "sg:tags":[
        "return",
        "filing"
    ],
    "wof:name":"Xpress Tax Group",
    "wof:placetype":"venue"
},
  "geometry": {"coordinates":[-118.21387199999999,33.937921],"type":"Point"}
}