{
  "type": "Feature",
  "properties": {
    "addr:full":"2257 Chestnut St San Francisco CA 94123",
    "addr:housenumber":"2257",
    "addr:postcode":"94123",
    "addr:street":"Chestnut St",
    "iso:country":"US",
    "sg:address":"2257 Chestnut St",
    "sg:city":"San Francisco",
    "sg:classifiers":[
        {
            "category":"Deli",
            "type":"Food & Drink"
        }
    ],
    "sg:menulink":"http://www.allmenus.com/ca/san-francisco/45994-the-pita-pit/menu/",
    "sg:phone":"+1 415 674 8288",
    "sg:postcode":"94123",
    "sg:province":"CA",
    "sg:tags":[
        "salad",
        "soup",
        "eastern",
        "mediterranean",
        "middle",
        "american",
        "greek"
    ],
    "wof:name":"The Pita Pit",
    "wof:placetype":"venue"
},
  "geometry": {"coordinates":[-122.440535,37.800307],"type":"Point"}
}