{
  "type": "Feature",
  "properties": {
    "addr:full":"9111 Avalon Blvd Los Angeles CA 90003",
    "addr:housenumber":"9111",
    "addr:postcode":"90003",
    "addr:street":"Avalon Blvd",
    "iso:country":"US",
    "sg:address":"9111 Avalon Blvd",
    "sg:city":"Los Angeles",
    "sg:classifiers":[
        {
            "category":"Wholesale",
            "subcategory":"Electrical",
            "type":"Manufacturing & Wholesale Goods"
        }
    ],
    "sg:phone":"+1 323 754 4366",
    "sg:postcode":"90003",
    "sg:province":"CA",
    "sg:tags":[
        "control",
        "security",
        "system"
    ],
    "wof:name":"Avalon Security Works",
    "wof:placetype":"venue"
},
  "geometry": {"coordinates":[-118.265214,33.952992],"type":"Point"}
}