{
  "type": "Feature",
  "properties": {
    "iso:country":"US",
    "sg:address":"4080 Mission Blvd",
    "sg:city":"Montclair",
    "sg:classifiers":[
        {
            "category":"Building & Trades",
            "subcategory":"Construction",
            "type":"Services"
        }
    ],
    "sg:phone":"+1 909 397 5770",
    "sg:postcode":"91763",
    "sg:province":"CA",
    "sg:tags":[
        "industrial",
        "wallcoverings-installation",
        "wallpaper",
        "contractor",
        "contractors-commercial",
        "painting"
    ],
    "sg:website":"http://www.cramerpainting.com",
    "wof:name":"Ccm Solutions Inc",
    "wof:placetype":"venue"
},
  "geometry": {"coordinates":[-117.71607400000001,34.05768],"type":"Point"}
}