{
  "type": "Feature",
  "properties": {
    "iso:country":"US",
    "sg:address":"12909 Sherman Way",
    "sg:city":"North Hollywood",
    "sg:classifiers":[
        {
            "category":"Bakery",
            "type":"Food & Drink"
        }
    ],
    "sg:phone":"+1 818 764 1011",
    "sg:postcode":"91605",
    "sg:province":"CA",
    "sg:website":"www.baklavafactory.com",
    "wof:name":"Baklava Factory",
    "wof:placetype":"venue"
},
  "geometry": {"coordinates":[-118.414001,34.201099],"type":"Point"}
}