{
  "type": "Feature",
  "properties": {
    "iso:country":"US",
    "sg:address":"3085 Atlantic Ave",
    "sg:city":"Long Beach",
    "sg:classifiers":[
        {
            "category":"Mining & Drilling",
            "type":"Manufacturing & Wholesale Goods"
        }
    ],
    "sg:phone":"+1 562 424 2523",
    "sg:postcode":"90807",
    "sg:province":"CA",
    "sg:tags":[
        "oil",
        "gas",
        "producer"
    ],
    "wof:name":"Herley-Kelley Co",
    "wof:placetype":"venue"
},
  "geometry": {"coordinates":[-118.185087,33.811894],"type":"Point"}
}