{
  "type": "Feature",
  "properties": {
    "addr:full":"Downey Landings 12140 Lakewood Blvd Downey CA 90242",
    "addr:housenumber":"12140",
    "addr:postcode":"90242",
    "addr:street":"Lakewood Blvd",
    "iso:country":"US",
    "sg:address":"Downey Landings 12140 Lakewood Blvd",
    "sg:city":"Downey",
    "sg:classifiers":[
        {
            "category":"Shopping",
            "subcategory":"Gifts & Souvenirs",
            "type":"Retail Goods"
        }
    ],
    "sg:phone":"+1 562 940 8202",
    "sg:postcode":"90242",
    "sg:province":"CA",
    "sg:tags":[
        "flower"
    ],
    "sg:website":"www.ediblearrangements.com",
    "wof:name":"Edible Arrangements",
    "wof:placetype":"venue"
},
  "geometry": {"coordinates":[-118.13237599999999,33.924047],"type":"Point"}
}