{
  "type": "Feature",
  "properties": {
    "iso:country":"US",
    "sg:address":"189 N Elmwood Ave",
    "sg:city":"Lindsay",
    "sg:classifiers":[
        {
            "category":"Social Services",
            "type":"Services"
        }
    ],
    "sg:phone":"+1 559 562 4434",
    "sg:postcode":"93247",
    "sg:province":"CA",
    "sg:tags":[
        "worker"
    ],
    "wof:name":"Lindsay Strathmore Council",
    "wof:placetype":"venue"
},
  "geometry": {"coordinates":[-119.090203,36.202666],"type":"Point"}
}