{
  "type": "Feature",
  "properties": {
    "iso:country":"US",
    "sg:address":"10025 Imperial Hwy",
    "sg:city":"Downey",
    "sg:classifiers":[
        {
            "category":"Professional",
            "subcategory":"Art Services",
            "type":"Services"
        }
    ],
    "sg:phone":"+1 562 803 9800",
    "sg:postcode":"90242",
    "sg:province":"CA",
    "sg:tags":[
        "graphic",
        "designer"
    ],
    "wof:name":"American Graphic Co",
    "wof:placetype":"venue"
},
  "geometry": {"coordinates":[-118.112398,33.917096],"type":"Point"}
}