{
  "type": "Feature",
  "properties": {
    "addr:full":"908 3rd Ave Chula Vista CA 91911",
    "addr:housenumber":"908",
    "addr:postcode":"91911",
    "addr:street":"3Rd Ave",
    "iso:country":"US",
    "sg:address":"908 3rd Ave",
    "sg:city":"Chula Vista",
    "sg:classifiers":[
        {
            "category":"Manufacturing",
            "subcategory":"Tools & Machinery",
            "type":"Manufacturing & Wholesale Goods"
        }
    ],
    "sg:phone":"+1 619 585 4555",
    "sg:postcode":"91911",
    "sg:province":"CA",
    "sg:tags":[
        "machine",
        "shop"
    ],
    "wof:name":"South Bay Auto Machine",
    "wof:placetype":"venue"
},
  "geometry": {"coordinates":[-117.070804,32.617842],"type":"Point"}
}