{
  "type": "Feature",
  "properties": {
    "iso:country":"US",
    "sg:address":"1100 N Eastern Ave",
    "sg:city":"Los Angeles",
    "sg:classifiers":[
        {
            "category":"Government",
            "subcategory":"Office",
            "type":"Public Place"
        }
    ],
    "sg:phone":"+1 323 267 3186",
    "sg:postcode":"90063",
    "sg:province":"CA",
    "sg:tags":[
        "executive"
    ],
    "wof:name":"La Co Isd Contracts & Purchasi",
    "wof:placetype":"venue"
},
  "geometry": {"coordinates":[-118.172922,34.053467],"type":"Point"}
}