{
  "type": "Feature",
  "properties": {
    "iso:country":"US",
    "sg:address":"16 Evergreen Dr",
    "sg:city":"Orinda",
    "sg:classifiers":[
        {
            "category":"Professional",
            "type":"Services"
        }
    ],
    "sg:phone":"+1 925 253 9679",
    "sg:postcode":"94563",
    "sg:province":"CA",
    "wof:name":"Robert Demoro",
    "wof:placetype":"venue"
},
  "geometry": {"coordinates":[-122.170356,37.877244],"type":"Point"}
}