{
  "type": "Feature",
  "properties": {
    "addr:full":"2058 Maricio Cir Thousand Oaks CA 91360",
    "addr:housenumber":"2058",
    "addr:postcode":"91360",
    "addr:street":"Maricio Cir",
    "iso:country":"US",
    "sg:address":"2058 Maricio Cir",
    "sg:city":"Thousand Oaks",
    "sg:classifiers":[
        {
            "category":"Utilities",
            "subcategory":"Mobile Phone",
            "type":"Services"
        }
    ],
    "sg:phone":"+1 805 494 8947",
    "sg:postcode":"91360",
    "sg:province":"CA",
    "sg:tags":[
        "communication",
        "radiotelephone"
    ],
    "wof:name":"Wireless Websites Inc",
    "wof:placetype":"venue"
},
  "geometry": {"coordinates":[-118.874689,34.205484],"type":"Point"}
}