{
  "type": "Feature",
  "properties": {
    "iso:country":"US",
    "sg:address":"22044 Lassen St",
    "sg:city":"Chatsworth",
    "sg:classifiers":[
        {
            "category":"Farming",
            "subcategory":"Livestock Farm",
            "type":"Manufacturing & Wholesale Goods"
        }
    ],
    "sg:phone":"+1 818 717 0775",
    "sg:postcode":"91311",
    "sg:province":"CA",
    "sg:tags":[
        "animal",
        "general"
    ],
    "wof:name":"Urban Ranch",
    "wof:placetype":"venue"
},
  "geometry": {"coordinates":[-118.606125,34.249967],"type":"Point"}
}