{
  "type": "Feature",
  "properties": {
    "addr:full":"1222 S Glendale Ave Ste 3 Glendale CA 91205",
    "addr:housenumber":"1222",
    "addr:postcode":"91205",
    "addr:street":"S Glendale Ave Ste 3",
    "iso:country":"US",
    "sg:address":"1222 S Glendale Ave Ste 3",
    "sg:city":"Glendale",
    "sg:classifiers":[
        {
            "category":"Health Services",
            "subcategory":"Optometrist",
            "type":"Services"
        }
    ],
    "sg:phone":"+1 818 230 0550",
    "sg:postcode":"91205",
    "sg:province":"CA",
    "sg:website":"www.drhalabi.com",
    "wof:name":"Ani Halabi, OD",
    "wof:placetype":"venue"
},
  "geometry": {"coordinates":[-118.251802,34.131796],"type":"Point"}
}