{
  "type": "Feature",
  "properties": {
    "addr:full":"36580 Orange Grove Ave Madera CA 93636",
    "addr:housenumber":"36580",
    "addr:postcode":"93636",
    "addr:street":"Orange Grove Ave",
    "iso:country":"US",
    "sg:address":"36580 Orange Grove Ave",
    "sg:city":"Madera",
    "sg:classifiers":[
        {
            "category":"Building & Trades",
            "subcategory":"Construction",
            "type":"Services"
        }
    ],
    "sg:phone":"+1 559 645 4525",
    "sg:postcode":"93636",
    "sg:province":"CA",
    "sg:tags":[
        "wallcoverings-installation",
        "wallpaper",
        "painting",
        "contractor"
    ],
    "wof:name":"Wayne Burns Painting",
    "wof:placetype":"venue"
},
  "geometry": {"coordinates":[-119.88361,36.922115],"type":"Point"}
}