{
  "type": "Feature",
  "properties": {
    "iso:country":"US",
    "sg:address":"2412 Professional Dr",
    "sg:city":"Roseville",
    "sg:classifiers":[
        {
            "category":"Professional",
            "subcategory":"Lawyer & Legal Services",
            "type":"Services"
        }
    ],
    "sg:phone":"+1 916 772 3300",
    "sg:postcode":"95661",
    "sg:province":"CA",
    "sg:tags":[
        "attorney"
    ],
    "wof:name":"Robert T Haney & Assoc",
    "wof:placetype":"venue"
},
  "geometry": {"coordinates":[-121.24719,38.742497],"type":"Point"}
}