{
  "type": "Feature",
  "properties": {
    "addr:full":"1440 E Camper Dr San Dimas CA 91792",
    "addr:housenumber":"1440",
    "addr:postcode":"91792",
    "addr:street":"E Camper Dr",
    "iso:country":"US",
    "sg:address":"1440 E Camper Dr",
    "sg:city":"San Dimas",
    "sg:classifiers":[
        {
            "category":"Building & Trades",
            "subcategory":"Construction",
            "type":"Services"
        }
    ],
    "sg:phone":"+1 909 394 1079",
    "sg:postcode":"91792",
    "sg:province":"CA",
    "sg:tags":[
        "contractor"
    ],
    "wof:name":"O Tb Maintenance",
    "wof:placetype":"venue"
},
  "geometry": {"coordinates":[-117.91597899999999,34.046244],"type":"Point"}
}