{
  "type": "Feature",
  "properties": {
    "addr:full":"848 N Sacramento Ave Ontario CA 91764",
    "addr:housenumber":"848",
    "addr:postcode":"91764",
    "addr:street":"N Sacramento Ave",
    "iso:country":"US",
    "sg:address":"848 N Sacramento Ave",
    "sg:city":"Ontario",
    "sg:classifiers":[
        {
            "category":"Cinema",
            "subcategory":"Movie Rental",
            "type":"Entertainment"
        }
    ],
    "sg:phone":"+1 951 295 9138",
    "sg:postcode":"91764",
    "sg:province":"CA",
    "sg:tags":[
        "motion",
        "picture",
        "distributor",
        "film",
        "exchange"
    ],
    "wof:name":"Cadillac Dreamz Productions",
    "wof:placetype":"venue"
},
  "geometry": {"coordinates":[-117.612982,34.073719],"type":"Point"}
}