{
  "type": "Feature",
  "properties": {
    "iso:country":"US",
    "sg:address":"1570 The Alameda",
    "sg:city":"San Jose",
    "sg:classifiers":[
        {
            "category":"Insurance",
            "subcategory":"Insurance Agent",
            "type":"Services"
        }
    ],
    "sg:phone":"+1 408 294 5940",
    "sg:postcode":"95126",
    "sg:province":"CA",
    "sg:website":"www.sellsfs.com",
    "wof:name":"Met Life",
    "wof:placetype":"venue"
},
  "geometry": {"coordinates":[-121.916257,37.335161],"type":"Point"}
}