{
  "type": "Feature",
  "properties": {
    "addr:full":"40577 Grimmer Blvd Fremont CA 94538",
    "addr:postcode":"40577;94538",
    "addr:street":"Grimmer Blvd",
    "iso:country":"US",
    "sg:address":"40577 Grimmer Blvd",
    "sg:city":"Fremont",
    "sg:classifiers":[
        {
            "category":"Communications",
            "type":"Services"
        },
        {
            "category":"Communications",
            "subcategory":"Television Station",
            "type":"Services"
        }
    ],
    "sg:phone":"+1 510 440 0907",
    "sg:postcode":"94538",
    "sg:province":"CA",
    "sg:tags":[
        "equipment",
        "satellite",
        "cable",
        "antenna",
        "system"
    ],
    "wof:name":"Aaa Satellite",
    "wof:placetype":"venue"
},
  "geometry": {"coordinates":[-121.965744,37.536167],"type":"Point"}
}