{
  "type": "Feature",
  "properties": {
    "addr:full":"2459 Stanford Way Antioch CA 94531",
    "addr:housenumber":"2459",
    "addr:postcode":"ca 94531",
    "addr:street":"Stanford Way",
    "iso:country":"US",
    "sg:address":"2459 Stanford Way",
    "sg:city":"Antioch",
    "sg:phone":"+1 925 778 2231",
    "sg:postcode":"94531",
    "sg:province":"CA",
    "wof:name":"J M Electric",
    "wof:placetype":"venue"
},
  "geometry": {"coordinates":[-121.784077,37.956956],"type":"Point"}
}