{
  "type": "Feature",
  "properties": {
    "iso:country":"US",
    "sg:address":"3254 Eureka Pl",
    "sg:city":"Carlsbad",
    "sg:classifiers":[
        {
            "category":"Organizations",
            "subcategory":"Religious Organization",
            "type":"Services"
        }
    ],
    "sg:phone":"+1 760 720 6363",
    "sg:postcode":"92008",
    "sg:province":"CA",
    "sg:tags":[
        "church"
    ],
    "wof:name":"North Coast Christian Flwshp",
    "wof:placetype":"venue"
},
  "geometry": {"coordinates":[-117.339074,33.160519],"type":"Point"}
}