{
  "type": "Feature",
  "properties": {
    "addr:full":"7799 Pardee Ln Oakland CA 94621",
    "addr:housenumber":"7799",
    "addr:postcode":"94621",
    "addr:street":"Pardee Ln",
    "iso:country":"US",
    "sg:address":"7799 Pardee Ln",
    "sg:city":"Oakland",
    "sg:classifiers":[
        {
            "category":"Professional",
            "subcategory":"Research",
            "type":"Services"
        }
    ],
    "sg:phone":"+1 510 568 8338",
    "sg:postcode":"94621",
    "sg:province":"CA",
    "sg:tags":[
        "physical",
        "mfg"
    ],
    "wof:name":"Baxter Novacor",
    "wof:placetype":"venue"
},
  "geometry": {"coordinates":[-122.20450700000001,37.743179],"type":"Point"}
}