{
  "type": "Feature",
  "properties": {
    "addr:full":"5853 Snell Ave San Jose CA 95123",
    "addr:housenumber":"5853",
    "addr:postcode":"95123",
    "addr:street":"Snell Ave",
    "iso:country":"US",
    "sg:address":"5853 Snell Ave",
    "sg:city":"San Jose",
    "sg:classifiers":[
        {
            "category":"Building & Trades",
            "subcategory":"Landscaping Services",
            "type":"Services"
        }
    ],
    "sg:phone":"+1 408 644 4601",
    "sg:postcode":"95123",
    "sg:province":"CA",
    "sg:tags":[
        "landscape"
    ],
    "wof:name":"Soto Efrain Landscaping",
    "wof:placetype":"venue"
},
  "geometry": {"coordinates":[-121.830781,37.24322],"type":"Point"}
}