{
  "type": "Feature",
  "properties": {
    "addr:full":"408 S Venice Blvd Venice CA 90291",
    "addr:housenumber":"408",
    "addr:postcode":"90291",
    "addr:street":"S Venice Blvd",
    "iso:country":"US",
    "sg:address":"408 S Venice Blvd",
    "sg:city":"Venice",
    "sg:classifiers":[
        {
            "category":"Wholesale",
            "subcategory":"Vending Machines",
            "type":"Manufacturing & Wholesale Goods"
        }
    ],
    "sg:phone":"+1 310 577 1510",
    "sg:postcode":"90291",
    "sg:province":"CA",
    "sg:tags":[
        "operator"
    ],
    "wof:name":"Vending 4u",
    "wof:placetype":"venue"
},
  "geometry": {"coordinates":[-118.465599,33.986873],"type":"Point"}
}