{
  "type": "Feature",
  "properties": {
    "addr:full":"3500 W 6th St Ste 224 Los Angeles CA 90020",
    "addr:housenumber":"3500",
    "addr:postcode":"90020",
    "addr:street":"W 6Th St Ste 224",
    "iso:country":"US",
    "sg:address":"3500 W 6th St Ste 224",
    "sg:city":"Los Angeles",
    "sg:classifiers":[
        {
            "category":"Restaurant",
            "type":"Food & Drink"
        }
    ],
    "sg:phone":"+1 213 384 1312",
    "sg:postcode":"90020",
    "sg:province":"CA",
    "sg:tags":[
        "korean"
    ],
    "wof:name":"Corea BBQ",
    "wof:placetype":"venue"
},
  "geometry": {"coordinates":[-118.29806600000001,34.063746],"type":"Point"}
}