{
  "type": "Feature",
  "properties": {
    "addr:full":"3695 Harbor Blvd Ventura CA 93001",
    "addr:housenumber":"3695",
    "addr:postcode":"93001",
    "addr:street":"Harbor Blvd",
    "iso:country":"US",
    "sg:address":"3695 Harbor Blvd",
    "sg:city":"Ventura",
    "sg:classifiers":[
        {
            "category":"Shopping",
            "subcategory":"Bicycles & Sporting Goods",
            "type":"Retail Goods"
        }
    ],
    "sg:phone":"+1 805 642 2522",
    "sg:postcode":"93001",
    "sg:province":"CA",
    "sg:tags":[
        "tackle",
        "fishing"
    ],
    "wof:name":"Fishermans Industry Supply",
    "wof:placetype":"venue"
},
  "geometry": {"coordinates":[-119.25677899999999,34.242398],"type":"Point"}
}