{
  "type": "Feature",
  "properties": {
    "addr:full":"441 Eaton Ave Tracy CA 95376",
    "addr:housenumber":"441",
    "addr:postcode":"95376",
    "addr:street":"Eaton Ave",
    "iso:country":"US",
    "sg:address":"441 Eaton Ave",
    "sg:city":"Tracy",
    "sg:classifiers":[
        {
            "category":"Health Services",
            "subcategory":"Podiatrist",
            "type":"Services"
        }
    ],
    "sg:phone":"+1 209 830 2115",
    "sg:postcode":"95376",
    "sg:province":"CA",
    "wof:name":"Eaton Plaza Podiatry Group",
    "wof:placetype":"venue"
},
  "geometry": {"coordinates":[-121.417939,37.743565],"type":"Point"}
}