{
  "type": "Feature",
  "properties": {
    "addr:full":"1631 Jenks Dr Corona CA 92880",
    "addr:housenumber":"1631",
    "addr:postcode":"92880",
    "addr:street":"Jenks Dr",
    "iso:country":"US",
    "sg:address":"1631 Jenks Dr",
    "sg:city":"Corona",
    "sg:classifiers":[
        {
            "category":"Professional",
            "type":"Services"
        },
        {
            "category":"Professional",
            "subcategory":"Advertising",
            "type":"Services"
        },
        {
            "category":"Professional",
            "subcategory":"Management & Consulting",
            "type":"Services"
        }
    ],
    "sg:phone":"+1 951 340 1171",
    "sg:postcode":"92880",
    "sg:province":"CA",
    "sg:tags":[
        "product",
        "fair",
        "marketing",
        "trade",
        "program",
        "exposition",
        "consultant",
        "advertising-promotional",
        "shows"
    ],
    "sg:website":"http://www.rstaffing.net",
    "wof:name":"Resource Solutions, Inc.",
    "wof:placetype":"venue"
},
  "geometry": {"coordinates":[-117.594414,33.890011],"type":"Point"}
}