{
  "type": "Feature",
  "properties": {
    "iso:country":"US",
    "sg:address":"9118 Glenoaks Blvd",
    "sg:city":"Sun Valley",
    "sg:classifiers":[
        {
            "category":"Wholesale",
            "subcategory":"Auto Parts",
            "type":"Manufacturing & Wholesale Goods"
        }
    ],
    "sg:phone":"+1 818 768 7500",
    "sg:postcode":"91352",
    "sg:province":"CA",
    "sg:tags":[
        "automobile"
    ],
    "wof:name":"Annex Auto Dismantling Inc",
    "wof:placetype":"venue"
},
  "geometry": {"coordinates":[-118.37261700000001,34.235783],"type":"Point"}
}