{
  "type": "Feature",
  "properties": {
    "addr:full":"1019 W Gardena Blvd Gardena CA 90247",
    "addr:housenumber":"1019",
    "addr:postcode":"90247",
    "addr:street":"W Gardena Blvd",
    "iso:country":"US",
    "sg:address":"1019 W Gardena Blvd",
    "sg:city":"Gardena",
    "sg:classifiers":[
        {
            "category":"Shopping",
            "subcategory":"Clothing, Apparel, & Fashions",
            "type":"Retail Goods"
        }
    ],
    "sg:phone":"+1 310 327 9906",
    "sg:postcode":"90247",
    "sg:province":"CA",
    "wof:name":"Zion Enterprises",
    "wof:placetype":"venue"
},
  "geometry": {"coordinates":[-118.292159,33.881652],"type":"Point"}
}