{
  "type": "Feature",
  "properties": {
    "addr:full":"50 Iron Point Cir Folsom CA 95630",
    "addr:housenumber":"50",
    "addr:postcode":"95630",
    "addr:street":"Iron Point Cir",
    "iso:country":"US",
    "sg:address":"50 Iron Point Cir",
    "sg:city":"Folsom",
    "sg:classifiers":[
        {
            "category":"Real Estate",
            "subcategory":"Real Estate Services",
            "type":"Services"
        },
        {
            "category":"Banks & Credit Unions",
            "subcategory":"Financial Services",
            "type":"Services"
        }
    ],
    "sg:phone":"+1 916 932 1700",
    "sg:postcode":"95630",
    "sg:province":"CA",
    "sg:tags":[
        "loan",
        "mortgage"
    ],
    "sg:website":"http://www.premiumlending.com",
    "wof:name":"Sierra Pacific Mortgage Co Inc",
    "wof:placetype":"venue"
},
  "geometry": {"coordinates":[-121.143168,38.643489],"type":"Point"}
}