{
  "type": "Feature",
  "properties": {
    "addr:full":"6700 Fallbrook Ave West Hills CA 91307",
    "addr:housenumber":"6700",
    "addr:postcode":"91307",
    "addr:street":"Fallbrook Ave",
    "iso:country":"US",
    "sg:address":"6700 Fallbrook Ave",
    "sg:city":"West Hills",
    "sg:classifiers":[
        {
            "category":"Personal",
            "type":"Services"
        }
    ],
    "sg:phone":"+1 818 888 8199",
    "sg:postcode":"91307",
    "sg:province":"CA",
    "sg:tags":[
        "mover"
    ],
    "wof:name":"ABC Moving & Storage",
    "wof:placetype":"venue"
},
  "geometry": {"coordinates":[-118.62319599999999,34.192211],"type":"Point"}
}