{
  "type": "Feature",
  "properties": {
    "iso:country":"US",
    "sg:address":"1245 Space Park Way",
    "sg:city":"Mountain View",
    "sg:classifiers":[
        {
            "category":"Manufacturing",
            "subcategory":"Tools & Machinery",
            "type":"Manufacturing & Wholesale Goods"
        }
    ],
    "sg:phone":"+1 650 965 0500",
    "sg:postcode":"94043",
    "sg:province":"CA",
    "sg:website":"www.appliedphysics.com",
    "wof:name":"Applied Physics Systems",
    "wof:placetype":"venue"
},
  "geometry": {"coordinates":[-122.076275,37.417025],"type":"Point"}
}