{
  "type": "Feature",
  "properties": {
    "addr:full":"780 N State St Ukiah CA 95482",
    "addr:housenumber":"780",
    "addr:postcode":"ca 95482",
    "addr:street":"N State St",
    "iso:country":"US",
    "sg:address":"780 N State St",
    "sg:city":"Ukiah",
    "sg:classifiers":[
        {
            "category":"Personal",
            "subcategory":"Beauty Salon",
            "type":"Services"
        }
    ],
    "sg:phone":"+1 707 468 5555",
    "sg:postcode":"95482",
    "sg:province":"CA",
    "wof:name":"Elegant Touch Beauty Salon",
    "wof:placetype":"venue"
},
  "geometry": {"coordinates":[-123.20848100000001,39.157551],"type":"Point"}
}