{
  "type": "Feature",
  "properties": {
    "iso:country":"US",
    "sg:address":"14411 Meadow Dr",
    "sg:city":"Grass Valley",
    "sg:classifiers":[
        {
            "category":"Real Estate",
            "subcategory":"Real Estate Agent",
            "type":"Services"
        }
    ],
    "sg:phone":"+1 530 272 5922",
    "sg:postcode":"95945",
    "sg:province":"CA",
    "wof:name":"Better Homes & Gardens",
    "wof:placetype":"venue"
},
  "geometry": {"coordinates":[-120.995062,39.181328],"type":"Point"}
}