{
  "type": "Feature",
  "properties": {
    "addr:full":"3352 Eaton Dr Roseville CA 95661",
    "addr:housenumber":"3352",
    "addr:postcode":"95661",
    "addr:street":"Eaton Dr",
    "iso:country":"US",
    "sg:address":"3352 Eaton Dr",
    "sg:city":"Roseville",
    "sg:classifiers":[
        {
            "category":"Farming",
            "subcategory":"Dairy Farm",
            "type":"Manufacturing & Wholesale Goods"
        }
    ],
    "sg:phone":"+1 916 783 0649",
    "sg:postcode":"95661",
    "sg:province":"CA",
    "wof:name":"Inderkums Dairy",
    "wof:placetype":"venue"
},
  "geometry": {"coordinates":[-121.231844,38.73014],"type":"Point"}
}