{
  "type": "Feature",
  "properties": {
    "addr:full":"260 N Mathilda Ave Ofc Sunnyvale CA 94086",
    "addr:housenumber":"260",
    "addr:postcode":"94086",
    "addr:street":"N Mathilda Ave",
    "iso:country":"US",
    "sg:address":"260 N Mathilda Ave Ofc",
    "sg:city":"Sunnyvale",
    "sg:classifiers":[
        {
            "category":"Real Estate",
            "subcategory":"Real Estate Operator",
            "type":"Services"
        }
    ],
    "sg:phone":"+1 408 739 5533",
    "sg:postcode":"94086",
    "sg:province":"CA",
    "sg:tags":[
        "apartment"
    ],
    "wof:name":"Wildwood Manor Apartments",
    "wof:placetype":"venue"
},
  "geometry": {"coordinates":[-122.031998,37.3834],"type":"Point"}
}