{
  "type": "Feature",
  "properties": {
    "iso:country":"US",
    "sg:address":"39290 Via Belleza",
    "sg:city":"Murrieta",
    "sg:classifiers":[
        {
            "category":"Professional",
            "subcategory":"Management & Consulting",
            "type":"Services"
        }
    ],
    "sg:phone":"+1 951 805 3345",
    "sg:postcode":"92563",
    "sg:province":"CA",
    "sg:tags":[
        "business"
    ],
    "wof:name":"Temecula Bio Assoc",
    "wof:placetype":"venue"
},
  "geometry": {"coordinates":[-117.138288,33.541781],"type":"Point"}
}