{
  "type": "Feature",
  "properties": {
    "iso:country":"US",
    "sg:address":"314 Lemon St",
    "sg:city":"Vallejo",
    "sg:classifiers":[
        {
            "category":"Building & Trades",
            "subcategory":"Construction",
            "type":"Services"
        },
        {
            "category":"Home & Garden",
            "subcategory":"Furniture",
            "type":"Retail Goods"
        }
    ],
    "sg:phone":"+1 707 648 2588",
    "sg:postcode":"94590",
    "sg:province":"CA",
    "sg:tags":[
        "cabinet",
        "house",
        "contractor",
        "equipment",
        "kitchen",
        "carpentry"
    ],
    "wof:name":"J & J Construction Co",
    "wof:placetype":"venue"
},
  "geometry": {"coordinates":[-122.245332,38.08683],"type":"Point"}
}