{
  "type": "Feature",
  "properties": {
    "addr:full":"7241 Eagle Rd Fair Oaks CA 95628",
    "addr:housenumber":"7241",
    "addr:postcode":"95628",
    "addr:street":"Eagle Rd",
    "iso:country":"US",
    "sg:address":"7241 Eagle Rd",
    "sg:city":"Fair Oaks",
    "sg:classifiers":[
        {
            "category":"Building & Trades",
            "subcategory":"Landscaping Services",
            "type":"Services"
        }
    ],
    "sg:phone":"+1 916 967 1354",
    "sg:postcode":"95628",
    "sg:province":"CA",
    "sg:tags":[
        "landscape",
        "contractor"
    ],
    "wof:name":"Precision Pruning & Garden",
    "wof:placetype":"venue"
},
  "geometry": {"coordinates":[-121.295739,38.655167],"type":"Point"}
}