{
  "type": "Feature",
  "properties": {
    "iso:country":"US",
    "sg:address":"401 S Pacific Coast Hwy",
    "sg:city":"Redondo Beach",
    "sg:classifiers":[
        {
            "category":"Home & Garden",
            "subcategory":"Furniture",
            "type":"Retail Goods"
        }
    ],
    "sg:phone":"+1 310 316 9282",
    "sg:postcode":"90277",
    "sg:province":"CA",
    "wof:name":"Rustic Romance Home & Garden",
    "wof:placetype":"venue"
},
  "geometry": {"coordinates":[-118.385113,33.834706],"type":"Point"}
}