{
  "type": "Feature",
  "properties": {
    "iso:country":"US",
    "sg:address":"4103 Eagles Nest",
    "sg:city":"Mather",
    "sg:classifiers":[
        {
            "category":"Utilities",
            "subcategory":"Natural Gas",
            "type":"Services"
        }
    ],
    "sg:phone":"+1 916 364 4120",
    "sg:postcode":"95603",
    "sg:province":"CA",
    "sg:tags":[
        "company"
    ],
    "wof:name":"West Coast Gas Co",
    "wof:placetype":"venue"
},
  "geometry": {"coordinates":[-121.071776,38.870065],"type":"Point"}
}