{
  "type": "Feature",
  "properties": {
    "addr:full":"9310 Topanga Canyon Blvd Chatsworth CA 91311",
    "addr:postcode":"9310;91311",
    "addr:street":"Topanga Canyon Blvd",
    "iso:country":"US",
    "sg:address":"9310 Topanga Canyon Blvd",
    "sg:city":"Chatsworth",
    "sg:classifiers":[
        {
            "category":"Home & Garden",
            "subcategory":"Building Materials",
            "type":"Retail Goods"
        }
    ],
    "sg:phone":"+1 818 576 8200",
    "sg:postcode":"91311",
    "sg:province":"CA",
    "sg:tags":[
        "shutter"
    ],
    "wof:name":"Danmer Custom Shutters",
    "wof:placetype":"venue"
},
  "geometry": {"coordinates":[-118.605936,34.240782],"type":"Point"}
}