{
  "type": "Feature",
  "properties": {
    "iso:country":"US",
    "sg:address":"1880 Smythe Ave",
    "sg:city":"San Ysidro",
    "sg:classifiers":[
        {
            "category":"Education",
            "subcategory":"School",
            "type":"Public Place"
        }
    ],
    "sg:phone":"+1 619 428 4447",
    "sg:postcode":"92173",
    "sg:province":"CA",
    "sg:tags":[
        "high",
        "middle",
        "elementary"
    ],
    "sg:website":"www.sanysidro.com",
    "wof:name":"Smythe Ave Elementary School",
    "wof:placetype":"venue"
},
  "geometry": {"coordinates":[-117.049004,32.5625],"type":"Point"}
}