{
  "type": "Feature",
  "properties": {
    "iso:country":"US",
    "sg:address":"12065 Pike St",
    "sg:city":"Santa Fe Springs",
    "sg:classifiers":[
        {
            "category":"Freight",
            "type":"Transportation"
        }
    ],
    "sg:phone":"+1 562 695 2392",
    "sg:postcode":"90670",
    "sg:province":"CA",
    "sg:tags":[
        "trucking"
    ],
    "wof:name":"Cerritos Trucking",
    "wof:placetype":"venue"
},
  "geometry": {"coordinates":[-118.06833899999999,33.953148],"type":"Point"}
}