{
  "type": "Feature",
  "properties": {
    "addr:full":"1826 Sonoma St Redding CA 96001",
    "addr:housenumber":"1826",
    "addr:postcode":"96001",
    "addr:street":"Sonoma St",
    "iso:country":"US",
    "sg:address":"1826 Sonoma St",
    "sg:city":"Redding",
    "sg:classifiers":[
        {
            "category":"Health Services",
            "subcategory":"Doctor",
            "type":"Services"
        }
    ],
    "sg:phone":"+1 530 243 9500",
    "sg:postcode":"96001",
    "sg:province":"CA",
    "sg:tags":[
        "physician",
        "surgeon"
    ],
    "wof:name":"Evan K Reasor MD",
    "wof:placetype":"venue"
},
  "geometry": {"coordinates":[-122.392652,40.575627],"type":"Point"}
}