{
  "type": "Feature",
  "properties": {
    "addr:full":"25056 Viking St Hayward CA 94545",
    "addr:housenumber":"25056",
    "addr:postcode":"94545",
    "addr:street":"Viking St",
    "iso:country":"US",
    "sg:address":"25056 Viking St",
    "sg:city":"Hayward",
    "sg:classifiers":[
        {
            "category":"Wholesale",
            "subcategory":"Construction Materials",
            "type":"Manufacturing & Wholesale Goods"
        }
    ],
    "sg:phone":"+1 510 887 8198",
    "sg:postcode":"94545",
    "sg:province":"CA",
    "sg:tags":[
        "granite"
    ],
    "wof:name":"D & E Granite & Marble",
    "wof:placetype":"venue"
},
  "geometry": {"coordinates":[-122.124674,37.63595],"type":"Point"}
}