{
  "type": "Feature",
  "properties": {
    "iso:country":"US",
    "sg:address":"4105 N Wilson Way",
    "sg:city":"Stockton",
    "sg:classifiers":[
        {
            "category":"Recreation",
            "subcategory":"Amusement Park",
            "type":"Entertainment"
        }
    ],
    "sg:phone":"+1 209 466 9999",
    "sg:postcode":"95205",
    "sg:province":"CA",
    "wof:name":"Stockton 99 Speedway",
    "wof:placetype":"venue"
},
  "geometry": {"coordinates":[-121.265404,37.993779],"type":"Point"}
}