{
  "type": "Feature",
  "properties": {
    "addr:full":"9961 Elk Grove Florin Rd Elk Grove CA 95624",
    "addr:housenumber":"9961",
    "addr:postcode":"95624",
    "addr:street":"Elk Grove Florin Rd",
    "iso:country":"US",
    "sg:address":"9961 Elk Grove Florin Rd",
    "sg:city":"Elk Grove",
    "sg:classifiers":[
        {
            "category":"Organizations",
            "subcategory":"Religious Organization",
            "type":"Services"
        }
    ],
    "sg:phone":"+1 916 685 3681",
    "sg:postcode":"95624",
    "sg:province":"CA",
    "sg:tags":[
        "church"
    ],
    "sg:website":"www.stjoseph-elkgrove.org",
    "wof:name":"St Joseph's Catholic Church",
    "wof:placetype":"venue"
},
  "geometry": {"coordinates":[-121.37142,38.395258],"type":"Point"}
}