{
  "type": "Feature",
  "properties": {
    "addr:full":"336 N Main St 93901 Salinas CA 93901",
    "addr:housenumber":"336",
    "addr:postcode":"93901;93901",
    "addr:street":"N Main St",
    "iso:country":"US",
    "sg:address":"336 N Main St 93901",
    "sg:city":"Salinas",
    "sg:classifiers":[
        {
            "category":"Utilities",
            "subcategory":"Water",
            "type":"Services"
        }
    ],
    "sg:phone":"+1 800 540 5004",
    "sg:postcode":"93901",
    "sg:province":"CA",
    "sg:tags":[
        "bulk",
        "companies-bottled"
    ],
    "wof:name":"Culligan Bottled Water Co.",
    "wof:placetype":"venue"
},
  "geometry": {"coordinates":[-121.653498,36.682485],"type":"Point"}
}