{
  "type": "Feature",
  "properties": {
    "addr:full":"7810 Quill Dr Downey CA 90242",
    "addr:housenumber":"7810",
    "addr:postcode":"90242",
    "addr:street":"Quill Dr",
    "iso:country":"US",
    "sg:address":"7810 Quill Dr",
    "sg:city":"Downey",
    "sg:classifiers":[
        {
            "category":"Organizations",
            "subcategory":"Non-profit Organization",
            "type":"Services"
        }
    ],
    "sg:phone":"+1 562 862 8800",
    "sg:postcode":"90242",
    "sg:province":"CA",
    "sg:tags":[
        "service/non-profit",
        "community"
    ],
    "wof:name":"Human Services Association",
    "wof:placetype":"venue"
},
  "geometry": {"coordinates":[-118.15406,33.928839],"type":"Point"}
}