{
  "type": "Feature",
  "properties": {
    "iso:country":"US",
    "sg:address":"East Bay Osteopathic Medical Center 3099 Telegraph Ave.",
    "sg:city":"Berkeley",
    "sg:classifiers":[
        {
            "category":"Health Services",
            "subcategory":"Doctor",
            "type":"Services"
        },
        {
            "category":"Personal",
            "subcategory":"Massage",
            "type":"Services"
        },
        {
            "category":"Health Services",
            "subcategory":"Health Practitioner",
            "type":"Services"
        }
    ],
    "sg:phone":"+1 510 421 1118",
    "sg:postcode":"94705",
    "sg:province":"CA",
    "sg:tags":[
        "acupuncture",
        "medicine",
        "sport"
    ],
    "wof:name":"Joe Cleary, LAc",
    "wof:placetype":"venue"
},
  "geometry": {"coordinates":[-122.25958799999999,37.853882],"type":"Point"}
}