{
  "type": "Feature",
  "properties": {
    "addr:full":"1740 Main St Escalon CA 95320",
    "addr:housenumber":"1740",
    "addr:postcode":"95320",
    "addr:street":"Main St",
    "iso:country":"US",
    "sg:address":"1740 Main St",
    "sg:city":"Escalon",
    "sg:classifiers":[
        {
            "category":"Professional",
            "subcategory":"Business Services",
            "type":"Services"
        }
    ],
    "sg:phone":"+1 209 838 8600",
    "sg:postcode":"95320",
    "sg:province":"CA",
    "sg:tags":[
        "interior",
        "consultant",
        "design",
        "decorator"
    ],
    "wof:name":"Memories",
    "wof:placetype":"venue"
},
  "geometry": {"coordinates":[-120.992862,37.794702],"type":"Point"}
}