{
  "type": "Feature",
  "properties": {
    "iso:country":"US",
    "sg:address":"10170 Central Ave",
    "sg:city":"Montclair",
    "sg:classifiers":[
        {
            "category":"Home & Garden",
            "subcategory":"Carpets & Floor Coverings",
            "type":"Retail Goods"
        }
    ],
    "sg:phone":"+1 909 445 1733",
    "sg:postcode":"91763",
    "sg:province":"CA",
    "sg:tags":[
        "dealer",
        "rug"
    ],
    "wof:name":"Fashion Carpets For Less",
    "wof:placetype":"venue"
},
  "geometry": {"coordinates":[-117.689626,34.068058],"type":"Point"}
}