{
  "type": "Feature",
  "properties": {
    "addr:full":"620 Pine Knot Ave Big Bear Lake CA 92315",
    "addr:housenumber":"620",
    "addr:postcode":"92315",
    "addr:street":"Pine Knot Ave",
    "iso:country":"US",
    "sg:address":"620 Pine Knot Ave",
    "sg:city":"Big Bear Lake",
    "sg:classifiers":[
        {
            "category":"Shopping",
            "type":"Retail Goods"
        }
    ],
    "sg:phone":"+1 909 866 5558",
    "sg:postcode":"92315",
    "sg:province":"CA",
    "sg:tags":[
        "art",
        "gallery",
        "dealer"
    ],
    "wof:name":"Schoettger Gallery",
    "wof:placetype":"venue"
},
  "geometry": {"coordinates":[-116.911564,34.242225],"type":"Point"}
}