{
  "type": "Feature",
  "properties": {
    "iso:country":"US",
    "sg:address":"810 W Hyde Park Blvd",
    "sg:city":"Inglewood",
    "sg:classifiers":[
        {
            "category":"Manufacturing",
            "subcategory":"Tools & Machinery",
            "type":"Manufacturing & Wholesale Goods"
        }
    ],
    "sg:phone":"+1 310 671 7919",
    "sg:postcode":"90302",
    "sg:province":"CA",
    "sg:tags":[
        "machine",
        "shop"
    ],
    "sg:website":"www.custservinc.com",
    "wof:name":"Custom Services",
    "wof:placetype":"venue"
},
  "geometry": {"coordinates":[-118.368703,33.967168],"type":"Point"}
}