{
  "type": "Feature",
  "properties": {
    "addr:full":"345 Stanford Shopping Center Palo Alto CA 94304",
    "addr:housenumber":"345",
    "addr:postcode":"94304",
    "addr:street":"Stanford Shopping Center",
    "iso:country":"US",
    "sg:address":"345 Stanford Shopping Center",
    "sg:city":"Palo Alto",
    "sg:classifiers":[
        {
            "category":"Professional",
            "subcategory":"Business Services",
            "type":"Services"
        }
    ],
    "sg:phone":"+1 650 324 8082",
    "sg:postcode":"94304",
    "sg:province":"CA",
    "sg:tags":[
        "packaging"
    ],
    "wof:name":"Postal Annex",
    "wof:placetype":"venue"
},
  "geometry": {"coordinates":[-122.172211,37.444296],"type":"Point"}
}