{
  "type": "Feature",
  "properties": {
    "iso:country":"US",
    "sg:address":"1619 E Palmyra Ave",
    "sg:city":"Orange",
    "sg:classifiers":[
        {
            "category":"Personal",
            "subcategory":"Barber",
            "type":"Services"
        }
    ],
    "sg:phone":"+1 714 639 6087",
    "sg:postcode":"92866",
    "sg:province":"CA",
    "wof:name":"Back Street Barbers",
    "wof:placetype":"venue"
},
  "geometry": {"coordinates":[-117.835999,33.784302],"type":"Point"}
}