{
  "type": "Feature",
  "properties": {
    "addr:full":"15720 Horace St Granada Hills CA 91344",
    "addr:housenumber":"15720",
    "addr:postcode":"91344",
    "addr:street":"Horace St",
    "iso:country":"US",
    "sg:address":"15720 Horace St",
    "sg:city":"Granada Hills",
    "sg:classifiers":[
        {
            "category":"Wholesale",
            "subcategory":"Durable Goods & Equipment",
            "type":"Manufacturing & Wholesale Goods"
        }
    ],
    "sg:phone":"+1 818 366 0177",
    "sg:postcode":"91344",
    "sg:province":"CA",
    "sg:tags":[
        "fire",
        "extinguisher"
    ],
    "wof:name":"Angelus Fire Extinguisher Co",
    "wof:placetype":"venue"
},
  "geometry": {"coordinates":[-118.474074,34.269893],"type":"Point"}
}