{
  "type": "Feature",
  "properties": {
    "iso:country":"US",
    "sg:address":"125 Stockdale Cir",
    "sg:city":"Bakersfield",
    "sg:classifiers":[
        {
            "category":"Building & Trades",
            "subcategory":"Electrical",
            "type":"Services"
        }
    ],
    "sg:phone":"+1 661 889 4437",
    "sg:postcode":"93309",
    "sg:province":"CA",
    "sg:tags":[
        "electrician"
    ],
    "wof:name":"Manuel E Wright Electric Co",
    "wof:placetype":"venue"
},
  "geometry": {"coordinates":[-119.077592,35.355708],"type":"Point"}
}