{
  "type": "Feature",
  "properties": {
    "iso:country":"US",
    "sg:address":"500 Harrington St",
    "sg:city":"Corona",
    "sg:classifiers":[
        {
            "category":"Building & Trades",
            "subcategory":"Plumbing",
            "type":"Services"
        }
    ],
    "sg:phone":"+1 951 734 6220",
    "sg:postcode":"92880",
    "sg:province":"CA",
    "sg:tags":[
        "cooling",
        "heating",
        "contractor"
    ],
    "wof:name":"Ricor Air Conditioning",
    "wof:placetype":"venue"
},
  "geometry": {"coordinates":[-117.57472300000001,33.894019],"type":"Point"}
}