{
  "type": "Feature",
  "properties": {
    "iso:country":"US",
    "sg:address":"255 E Temple St",
    "sg:city":"Los Angeles",
    "sg:classifiers":[
        {
            "category":"Government",
            "subcategory":"City Hall",
            "type":"Public Place"
        }
    ],
    "sg:postcode":"90006",
    "sg:province":"CA",
    "wof:name":"Edward R. Roybal Federal Building",
    "wof:placetype":"venue"
},
  "geometry": {"coordinates":[-118.269687,34.0708],"type":"Point"}
}