{
  "type": "Feature",
  "properties": {
    "iso:country":"US",
    "sg:address":"100 Littleway Ln",
    "sg:city":"Watsonville",
    "sg:classifiers":[
        {
            "category":"Retail",
            "subcategory":"Veterinary Services",
            "type":"Services"
        }
    ],
    "sg:phone":"+1 831 728 5118",
    "sg:postcode":"95076",
    "sg:province":"CA",
    "wof:name":"Thomas R Meyers DVM",
    "wof:placetype":"venue"
},
  "geometry": {"coordinates":[-121.759582,36.959641],"type":"Point"}
}