{
  "type": "Feature",
  "properties": {
    "addr:full":"5718 Shady Ln Paradise CA 95969",
    "addr:housenumber":"5718",
    "addr:postcode":"95969",
    "addr:street":"Shady Ln",
    "iso:country":"US",
    "sg:address":"5718 Shady Ln",
    "sg:city":"Paradise",
    "sg:classifiers":[
        {
            "category":"Retail",
            "subcategory":"Laundry & Dry Cleaning",
            "type":"Services"
        }
    ],
    "sg:phone":"+1 530 877 8699",
    "sg:postcode":"95969",
    "sg:province":"CA",
    "sg:tags":[
        "cleaner",
        "rug",
        "carpet"
    ],
    "wof:name":"Sunbrite",
    "wof:placetype":"venue"
},
  "geometry": {"coordinates":[-121.619597,39.754199],"type":"Point"}
}