{
  "type": "Feature",
  "properties": {
    "addr:full":"444 S Flower Street Los Angeles CA 90071",
    "addr:housenumber":"444",
    "addr:postcode":"90071",
    "addr:street":"S Flower Street",
    "iso:country":"US",
    "sg:address":"444 S Flower Street",
    "sg:city":"Los Angeles",
    "sg:classifiers":[
        {
            "category":"Professional",
            "subcategory":"Lawyer & Legal Services",
            "type":"Services"
        }
    ],
    "sg:phone":"+1 213 243 6198",
    "sg:postcode":"90071",
    "sg:province":"CA",
    "wof:name":"Lombardo Kevin J Atty",
    "wof:placetype":"venue"
},
  "geometry": {"coordinates":[-118.255431,34.05222],"type":"Point"}
}