{
  "type": "Feature",
  "properties": {
    "iso:country":"US",
    "sg:address":"1639 11th St",
    "sg:city":"Santa Monica",
    "sg:classifiers":[
        {
            "category":"Professional",
            "type":"Services"
        }
    ],
    "sg:phone":"+1 310 581 5115",
    "sg:postcode":"90404",
    "sg:province":"CA",
    "wof:name":"Bradley Collection",
    "wof:placetype":"venue"
},
  "geometry": {"coordinates":[-118.483746,34.017641],"type":"Point"}
}