{
  "type": "Feature",
  "properties": {
    "iso:country":"US",
    "sg:address":"9916 Big Horn St",
    "sg:city":"Ventura",
    "sg:classifiers":[
        {
            "category":"Professional",
            "subcategory":"Management & Consulting",
            "type":"Services"
        }
    ],
    "sg:phone":"+1 805 647 8225",
    "sg:postcode":"93004",
    "sg:province":"CA",
    "sg:tags":[
        "counselor",
        "public",
        "relations"
    ],
    "sg:website":"www.silverfoxco.com",
    "wof:name":"Silver Fox Communications",
    "wof:placetype":"venue"
},
  "geometry": {"coordinates":[-119.164286,34.270597],"type":"Point"}
}