{
  "type": "Feature",
  "properties": {
    "iso:country":"US",
    "sg:address":"291 Emaron Dr",
    "sg:city":"San Bruno",
    "sg:classifiers":[
        {
            "category":"Personal",
            "subcategory":"Massage",
            "type":"Services"
        }
    ],
    "sg:phone":"+1 650 359 9000",
    "sg:postcode":"94066",
    "sg:province":"CA",
    "wof:name":"Finishing Touch",
    "wof:placetype":"venue"
},
  "geometry": {"coordinates":[-122.455569,37.629863],"type":"Point"}
}