{
  "type": "Feature",
  "properties": {
    "addr:full":"9230 Lakewood Boulevard Downey CA 90240",
    "addr:housenumber":"9230",
    "addr:postcode":"90240",
    "addr:street":"Lakewood Boulevard",
    "iso:country":"US",
    "sg:address":"9230 Lakewood Boulevard",
    "sg:city":"Downey",
    "sg:classifiers":[
        {
            "category":"Restaurant",
            "type":"Food & Drink"
        }
    ],
    "sg:phone":"+1 562 622 7832",
    "sg:postcode":"90240",
    "sg:province":"CA",
    "wof:name":"Lee's Maui Hawaiin Barbeque",
    "wof:placetype":"venue"
},
  "geometry": {"coordinates":[-118.113022,33.955586],"type":"Point"}
}