{
  "type": "Feature",
  "properties": {
    "addr:full":"1889 W Commonwealth Ave Fullerton CA 92833",
    "addr:housenumber":"1889",
    "addr:postcode":"92833",
    "addr:street":"W Commonwealth Ave",
    "iso:country":"US",
    "sg:address":"1889 W Commonwealth Ave",
    "sg:city":"Fullerton",
    "sg:classifiers":[
        {
            "category":"Autos & Motor Vehicles",
            "subcategory":"Auto Supplies",
            "type":"Retail Goods"
        }
    ],
    "sg:phone":"+1 714 870 4702",
    "sg:postcode":"92833",
    "sg:province":"CA",
    "sg:tags":[
        "alternator",
        "generator"
    ],
    "wof:name":"Fullerton Diesel Electric",
    "wof:placetype":"venue"
},
  "geometry": {"coordinates":[-117.968099,33.870125],"type":"Point"}
}