{
  "type": "Feature",
  "properties": {
    "addr:full":"Grand Star Jazz Club 943 N Broadway Los Angeles CA 90012",
    "addr:housenumber":"943",
    "addr:postcode":"90012",
    "addr:street":"N Broadway",
    "iso:country":"US",
    "sg:address":"Grand Star Jazz Club 943 N Broadway",
    "sg:city":"Los Angeles",
    "sg:classifiers":[
        {
            "category":"Arts & Performance",
            "subcategory":"Music",
            "type":"Entertainment"
        },
        {
            "category":"Arts & Performance",
            "subcategory":"Jazz & Blues",
            "type":"Entertainment"
        }
    ],
    "sg:phone":"+1 818 720 6650",
    "sg:postcode":"90012",
    "sg:province":"CA",
    "sg:tags":[
        "venue"
    ],
    "sg:website":"shinkawasaki.com/midtones",
    "wof:name":"MidTones Open Jam",
    "wof:placetype":"venue"
},
  "geometry": {"coordinates":[-118.237127,34.065189],"type":"Point"}
}