{
  "type": "Feature",
  "properties": {
    "iso:country":"US",
    "sg:address":"169 Pheasant Dr",
    "sg:city":"Galt",
    "sg:classifiers":[
        {
            "category":"Professional",
            "subcategory":"Accounting & Tax Preparation",
            "type":"Services"
        }
    ],
    "sg:phone":"+1 209 745 8885",
    "sg:postcode":"95632",
    "sg:province":"CA",
    "sg:tags":[
        "bookkeeping",
        "general"
    ],
    "wof:name":"Suzanne Campbell Bookkeeping",
    "wof:placetype":"venue"
},
  "geometry": {"coordinates":[-121.316867,38.260118],"type":"Point"}
}