{
  "type": "Feature",
  "properties": {
    "iso:country":"US",
    "sg:address":"5771 E Shields Ave",
    "sg:city":"Fresno",
    "sg:classifiers":[
        {
            "category":"Professional",
            "subcategory":"Business Services",
            "type":"Services"
        }
    ],
    "sg:phone":"+1 559 346 1612",
    "sg:postcode":"93727",
    "sg:province":"CA",
    "sg:tags":[
        "embroidery"
    ],
    "wof:name":"Big Valley Embroidery",
    "wof:placetype":"venue"
},
  "geometry": {"coordinates":[-119.695411,36.779491],"type":"Point"}
}