{
  "type": "Feature",
  "properties": {
    "addr:full":"5771 E Shields Ave Fresno CA 93727",
    "addr:housenumber":"5771",
    "addr:postcode":"93727",
    "addr:street":"E Shields Ave",
    "iso:country":"US",
    "sg:address":"5771 E Shields Ave",
    "sg:city":"Fresno",
    "sg:classifiers":[
        {
            "category":"Professional",
            "subcategory":"Business Services",
            "type":"Services"
        }
    ],
    "sg:phone":"+1 559 346 1612",
    "sg:postcode":"93727",
    "sg:province":"CA",
    "sg:tags":[
        "embroidery"
    ],
    "wof:name":"Big Valley Embroidery",
    "wof:placetype":"venue"
},
  "geometry": {"coordinates":[-119.69541099999999,36.779491],"type":"Point"}
}