{
  "type": "Feature",
  "properties": {
    "addr:full":"1343 W 58th St Los Angeles CA 90037",
    "addr:housenumber":"1343",
    "addr:postcode":"90037",
    "addr:street":"W 58Th St",
    "iso:country":"US",
    "sg:address":"1343 W 58th St",
    "sg:city":"Los Angeles",
    "sg:classifiers":[
        {
            "category":"Building & Trades",
            "subcategory":"Construction",
            "type":"Services"
        }
    ],
    "sg:phone":"+1 323 752 6145",
    "sg:postcode":"90037",
    "sg:province":"CA",
    "sg:tags":[
        "contractor"
    ],
    "wof:name":"Andrews & Sons Building Mtce",
    "wof:placetype":"venue"
},
  "geometry": {"coordinates":[-118.297602,33.989946],"type":"Point"}
}