{
  "type": "Feature",
  "properties": {
    "iso:country":"US",
    "sg:address":"240 Cll Cebu",
    "sg:city":"Salinas",
    "sg:classifiers":[
        {
            "category":"Organizations",
            "subcategory":"Religious Organization",
            "type":"Services"
        }
    ],
    "sg:phone":"+1 831 422 6543",
    "sg:postcode":"93901",
    "sg:province":"CA",
    "sg:tags":[
        "church"
    ],
    "wof:name":"Christ The King Church",
    "wof:placetype":"venue"
},
  "geometry": {"coordinates":[-121.650019,36.68015],"type":"Point"}
}