{
  "type": "Feature",
  "properties": {
    "addr:full":"794 N Ramona Blvd San Jacinto CA 92583",
    "addr:housenumber":"794",
    "addr:postcode":"92583",
    "addr:street":"N Ramona Blvd",
    "iso:country":"US",
    "sg:address":"794 N Ramona Blvd",
    "sg:city":"San Jacinto",
    "sg:classifiers":[
        {
            "category":"Food & Beverages",
            "subcategory":"Fruits & Vegetables",
            "type":"Retail Goods"
        }
    ],
    "sg:phone":"+1 951 654 9774",
    "sg:postcode":"92583",
    "sg:province":"CA",
    "sg:tags":[
        "produce"
    ],
    "wof:name":"Ramona Produce",
    "wof:placetype":"venue"
},
  "geometry": {"coordinates":[-116.971374,33.794273],"type":"Point"}
}