{
  "type": "Feature",
  "properties": {
    "iso:country":"US",
    "sg:address":"11104 Whittier Blvd",
    "sg:city":"Whittier",
    "sg:phone":"+1 562 699 1045",
    "sg:postcode":"90606",
    "sg:province":"CA",
    "sg:website":"http://www.stuftpizza.com",
    "wof:name":"Stuft Pizza",
    "wof:placetype":"venue"
},
  "geometry": {"coordinates":[-118.060436,33.987492],"type":"Point"}
}