{
  "type": "Feature",
  "properties": {
    "addr:full":"291 E Main St # C Los Gatos CA 95030",
    "addr:housenumber":"291",
    "addr:postcode":"95030",
    "addr:street":"E Main St # C",
    "iso:country":"US",
    "sg:address":"291 E Main St # C",
    "sg:city":"Los Gatos",
    "sg:classifiers":[
        {
            "category":"Personal",
            "subcategory":"Beauty Salon",
            "type":"Services"
        }
    ],
    "sg:phone":"+1 408 395 4678",
    "sg:postcode":"95030",
    "sg:province":"CA",
    "sg:tags":[
        "hair"
    ],
    "wof:name":"IMRU Salon",
    "wof:placetype":"venue"
},
  "geometry": {"coordinates":[-121.97462,37.22131],"type":"Point"}
}