{
  "type": "Feature",
  "properties": {
    "iso:country":"US",
    "sg:address":"3821 Cherry Hill Rd",
    "sg:city":"Santa Maria",
    "sg:classifiers":[
        {
            "category":"Professional",
            "subcategory":"Business Services",
            "type":"Services"
        }
    ],
    "sg:phone":"+1 805 937 7786",
    "sg:postcode":"93455",
    "sg:province":"CA",
    "sg:tags":[
        "translator",
        "interpreter"
    ],
    "wof:name":"General Services & Intrprtng",
    "wof:placetype":"venue"
},
  "geometry": {"coordinates":[-120.418251,34.889862],"type":"Point"}
}