{
  "type": "Feature",
  "properties": {
    "addr:full":"9211 Clairemont Mesa Blvd San Diego CA 92123",
    "addr:housenumber":"9211",
    "addr:postcode":"92123",
    "addr:street":"Clairemont Mesa Blvd",
    "iso:country":"US",
    "sg:address":"9211 Clairemont Mesa Blvd",
    "sg:city":"San Diego",
    "sg:classifiers":[
        {
            "category":"Restaurant",
            "type":"Food & Drink"
        }
    ],
    "sg:menulink":"http://www.allmenus.com/ca/san-diego/164047-togos-eatery/menu/",
    "sg:phone":"+1 858 627 9199",
    "sg:postcode":"92123",
    "sg:province":"CA",
    "sg:tags":[
        "wrap",
        "american",
        "sandwich"
    ],
    "wof:name":"Togo's Eatery",
    "wof:placetype":"venue"
},
  "geometry": {"coordinates":[-117.13063099999999,32.830866],"type":"Point"}
}