{
  "type": "Feature",
  "properties": {
    "addr:full":"40600 Washington St Bermuda Dunes CA 92203",
    "addr:housenumber":"40600",
    "addr:postcode":"92203",
    "addr:street":"Washington St",
    "iso:country":"US",
    "sg:address":"40600 Washington St",
    "sg:city":"Bermuda Dunes",
    "sg:classifiers":[
        {
            "category":"Real Estate",
            "subcategory":"Real Estate Operator",
            "type":"Services"
        }
    ],
    "sg:phone":"+1 760 200 0810",
    "sg:postcode":"92203",
    "sg:province":"CA",
    "sg:tags":[
        "apartment"
    ],
    "wof:name":"Bermuda Park Apartments",
    "wof:placetype":"venue"
},
  "geometry": {"coordinates":[-116.303732,33.751598],"type":"Point"}
}