{
  "type": "Feature",
  "properties": {
    "addr:full":"7022 Alondra Blvd Paramount CA 90723",
    "addr:housenumber":"7022",
    "addr:postcode":"90723",
    "addr:street":"Alondra Blvd",
    "iso:country":"US",
    "sg:address":"7022 Alondra Blvd",
    "sg:city":"Paramount",
    "sg:classifiers":[
        {
            "category":"Manufacturing",
            "subcategory":"Metals",
            "type":"Manufacturing & Wholesale Goods"
        }
    ],
    "sg:phone":"+1 562 408 1808",
    "sg:postcode":"90723",
    "sg:province":"CA",
    "sg:tags":[
        "production",
        "grinding"
    ],
    "sg:website":"www.a1technologies.com",
    "wof:name":"A-1 Technologies",
    "wof:placetype":"venue"
},
  "geometry": {"coordinates":[-118.175185,33.888982],"type":"Point"}
}