{
  "type": "Feature",
  "properties": {
    "iso:country":"US",
    "sg:address":"30 Rancheria Rd",
    "sg:city":"Greenbrae",
    "sg:classifiers":[
        {
            "category":"Real Estate",
            "subcategory":"Real Estate Agent",
            "type":"Services"
        }
    ],
    "sg:phone":"+1 415 461 2566",
    "sg:postcode":"94904",
    "sg:province":"CA",
    "wof:name":"Noyer Terry",
    "wof:placetype":"venue"
},
  "geometry": {"coordinates":[-122.551462,37.950533],"type":"Point"}
}