{
  "type": "Feature",
  "properties": {
    "iso:country":"US",
    "sg:address":"1331 S Clark Rd",
    "sg:city":"El Centro",
    "sg:classifiers":[
        {
            "category":"Social Services",
            "type":"Services"
        }
    ],
    "sg:phone":"+1 760 353 8482",
    "sg:postcode":"92243",
    "sg:province":"CA",
    "sg:tags":[
        "organization",
        "welfare"
    ],
    "wof:name":"Volunteers Of America",
    "wof:placetype":"venue"
},
  "geometry": {"coordinates":[-115.560509,32.746955],"type":"Point"}
}