{
  "type": "Feature",
  "properties": {
    "addr:full":"2192 Athens Ave Simi Valley CA 93065",
    "addr:housenumber":"2192",
    "addr:postcode":"93065",
    "addr:street":"Athens Ave",
    "iso:country":"US",
    "sg:address":"2192 Athens Ave",
    "sg:city":"Simi Valley",
    "sg:classifiers":[
        {
            "category":"Building & Trades",
            "subcategory":"Electrical",
            "type":"Services"
        }
    ],
    "sg:phone":"+1 805 581 4807",
    "sg:postcode":"93065",
    "sg:province":"CA",
    "sg:tags":[
        "telecommunication",
        "contractor"
    ],
    "wof:name":"Phone Connection",
    "wof:placetype":"venue"
},
  "geometry": {"coordinates":[-118.79481,34.274956],"type":"Point"}
}