{
  "type": "Feature",
  "properties": {
    "iso:country":"US",
    "sg:address":"947 Iris Ave",
    "sg:city":"Sunnyvale",
    "sg:classifiers":[
        {
            "category":"Professional",
            "subcategory":"Detective & Security Services",
            "type":"Services"
        }
    ],
    "sg:phone":"+1 408 732 5397",
    "sg:postcode":"94086",
    "sg:province":"CA",
    "wof:name":"Keystone Internet Security",
    "wof:placetype":"venue"
},
  "geometry": {"coordinates":[-122.01071,37.362739],"type":"Point"}
}