{
  "type": "Feature",
  "properties": {
    "iso:country":"US",
    "sg:address":"11377 West Olympic Boulevard, Suite 900",
    "sg:city":"Los Angeles",
    "sg:classifiers":[
        {
            "category":"Professional",
            "subcategory":"Lawyer & Legal Services",
            "type":"Services"
        }
    ],
    "sg:phone":"+1 310 693 6093",
    "sg:postcode":"90064",
    "sg:province":"CA",
    "sg:website":"info.realpractice.com/ostrin-ban...",
    "wof:name":"Law Offices Of Ronald E. Ostrin",
    "wof:placetype":"venue"
},
  "geometry": {"coordinates":[-118.442898,34.037394],"type":"Point"}
}