{
  "type": "Feature",
  "properties": {
    "addr:full":"17 Lovell Ave San Rafael CA 94901",
    "addr:housenumber":"17",
    "addr:postcode":"94901",
    "addr:street":"Lovell Ave",
    "iso:country":"US",
    "sg:address":"17 Lovell Ave",
    "sg:city":"San Rafael",
    "sg:classifiers":[
        {
            "category":"Professional",
            "type":"Services"
        }
    ],
    "sg:phone":"+1 415 456 9560",
    "sg:postcode":"94901",
    "sg:province":"CA",
    "sg:tags":[
        "art",
        "restoring"
    ],
    "wof:name":"Michael Leach",
    "wof:placetype":"venue"
},
  "geometry": {"coordinates":[-122.52233699999999,37.964245],"type":"Point"}
}