{
  "type": "Feature",
  "properties": {
    "addr:full":"424 N Isabel St Glendale CA 91206",
    "addr:housenumber":"424",
    "addr:postcode":"91206",
    "addr:street":"N Isabel St",
    "iso:country":"US",
    "sg:address":"424 N Isabel St",
    "sg:city":"Glendale",
    "sg:classifiers":[
        {
            "category":"Local Transit",
            "type":"Transportation"
        }
    ],
    "sg:phone":"+1 818 241 0606",
    "sg:postcode":"91206",
    "sg:province":"CA",
    "sg:tags":[
        "limousine"
    ],
    "sg:website":"www.airportmasters.com",
    "wof:name":"Airport Masters & Melody Limo",
    "wof:placetype":"venue"
},
  "geometry": {"coordinates":[-118.248819,34.154359],"type":"Point"}
}