{
  "type": "Feature",
  "properties": {
    "iso:country":"US",
    "sg:address":"8745 Trautwein Rd",
    "sg:city":"Riverside",
    "sg:classifiers":[
        {
            "category":"Restaurant",
            "type":"Food & Drink"
        }
    ],
    "sg:menulink":"http://www.allmenus.com/ca/riverside/174507-wendys/menu/",
    "sg:phone":"+1 951 780 5846",
    "sg:postcode":"92508",
    "sg:province":"CA",
    "sg:tags":[
        "burger",
        "american",
        "soup"
    ],
    "wof:name":"Wendy's",
    "wof:placetype":"venue"
},
  "geometry": {"coordinates":[-117.32481799999999,33.8909],"type":"Point"}
}