{
  "type": "Feature",
  "properties": {
    "addr:full":"9500 Kiefer Blvd Sacramento CA 95827",
    "addr:housenumber":"9500",
    "addr:postcode":"95827",
    "addr:street":"Kiefer Blvd",
    "iso:country":"US",
    "sg:address":"9500 Kiefer Blvd",
    "sg:city":"Sacramento",
    "sg:classifiers":[
        {
            "category":"Government",
            "subcategory":"Post Office",
            "type":"Public Place"
        }
    ],
    "sg:phone":"+1 916 255 5104",
    "sg:postcode":"95827",
    "sg:province":"CA",
    "sg:website":"www.usps.com",
    "wof:name":"United States Postal Service",
    "wof:placetype":"venue"
},
  "geometry": {"coordinates":[-121.34332999999999,38.544507],"type":"Point"}
}