{
  "type": "Feature",
  "properties": {
    "addr:full":"5001 Lankershim Blvd North Hollywood CA 91601",
    "addr:housenumber":"5001",
    "addr:postcode":"91601",
    "addr:street":"Lankershim Blvd",
    "iso:country":"US",
    "sg:address":"5001 Lankershim Blvd",
    "sg:city":"North Hollywood",
    "sg:classifiers":[
        {
            "category":"Restaurant",
            "type":"Food & Drink"
        }
    ],
    "sg:phone":"+1 818 508 0788",
    "sg:postcode":"91601",
    "sg:province":"CA",
    "sg:tags":[
        "sushi",
        "bar",
        "japanese"
    ],
    "sg:website":"www.dragonmiyako.com",
    "wof:name":"Miyako",
    "wof:placetype":"venue"
},
  "geometry": {"coordinates":[-118.372761,34.160959],"type":"Point"}
}