{
  "type": "Feature",
  "properties": {
    "addr:full":"101 Howson St Gilroy CA 95020",
    "addr:housenumber":"101",
    "addr:postcode":"95020",
    "addr:street":"Howson St",
    "iso:country":"US",
    "sg:address":"101 Howson St",
    "sg:city":"Gilroy",
    "sg:classifiers":[
        {
            "category":"Retail",
            "subcategory":"Auto Repair",
            "type":"Services"
        }
    ],
    "sg:phone":"+1 408 848 2677",
    "sg:postcode":"95020",
    "sg:province":"CA",
    "sg:tags":[
        "body",
        "painting",
        "repairing",
        "automobile"
    ],
    "wof:name":"Armando's Body Shop",
    "wof:placetype":"venue"
},
  "geometry": {"coordinates":[-121.573851,37.017392],"type":"Point"}
}