{
  "type": "Feature",
  "properties": {
    "iso:country":"US",
    "sg:address":"8201 Demetre Ave",
    "sg:city":"Sacramento",
    "sg:classifiers":[
        {
            "category":"Freight",
            "type":"Transportation"
        }
    ],
    "sg:phone":"+1 916 448 8888",
    "sg:postcode":"95828",
    "sg:province":"CA",
    "sg:tags":[
        "trucking"
    ],
    "wof:name":"Rath Trucking",
    "wof:placetype":"venue"
},
  "geometry": {"coordinates":[-121.396742,38.520205],"type":"Point"}
}