{
  "type": "Feature",
  "properties": {
    "iso:country":"US",
    "sg:address":"3131 Roeding Rd",
    "sg:city":"Ceres",
    "sg:classifiers":[
        {
            "category":"Education",
            "subcategory":"Vocational School",
            "type":"Public Place"
        }
    ],
    "sg:phone":"+1 209 581 0620",
    "sg:postcode":"95307",
    "sg:province":"CA",
    "sg:tags":[
        "instruction",
        "truck",
        "driving"
    ],
    "wof:name":"Freedom Truck Driving School",
    "wof:placetype":"venue"
},
  "geometry": {"coordinates":[-120.936526,37.587556],"type":"Point"}
}