{
  "type": "Feature",
  "properties": {
    "addr:full":"335 N Thorne Ave Fresno CA 93706",
    "addr:housenumber":"335",
    "addr:postcode":"93706",
    "addr:street":"N Thorne Ave",
    "iso:country":"US",
    "sg:address":"335 N Thorne Ave",
    "sg:city":"Fresno",
    "sg:classifiers":[
        {
            "category":"Building & Trades",
            "subcategory":"Construction",
            "type":"Services"
        }
    ],
    "sg:phone":"+1 559 268 1540",
    "sg:postcode":"93706",
    "sg:province":"CA",
    "sg:tags":[
        "contractor"
    ],
    "sg:website":"www.kaweahconstruction.com",
    "wof:name":"Kaweah Construction",
    "wof:placetype":"venue"
},
  "geometry": {"coordinates":[-119.81311599999999,36.746809],"type":"Point"}
}