{
  "type": "Feature",
  "properties": {
    "addr:full":"5542 Brisa St Livermore CA 94550",
    "addr:postcode":"5542;94550",
    "addr:street":"Brisa St",
    "iso:country":"US",
    "sg:address":"5542 Brisa St",
    "sg:city":"Livermore",
    "sg:classifiers":[
        {
            "category":"Building & Trades",
            "subcategory":"Plumbing",
            "type":"Services"
        }
    ],
    "sg:phone":"+1 925 294 9000",
    "sg:postcode":"94550",
    "sg:province":"CA",
    "sg:tags":[
        "system",
        "radiant",
        "cooling",
        "heating"
    ],
    "wof:name":"J B Mechanical Inc",
    "wof:placetype":"venue"
},
  "geometry": {"coordinates":[-121.72500700000001,37.697212],"type":"Point"}
}