{
  "type": "Feature",
  "properties": {
    "iso:country":"US",
    "sg:address":"23605 Lancaster Rd",
    "sg:city":"Lancaster",
    "sg:classifiers":[
        {
            "category":"Freight",
            "type":"Transportation"
        }
    ],
    "sg:phone":"+1 661 724 9180",
    "sg:postcode":"93536",
    "sg:province":"CA",
    "sg:tags":[
        "operator",
        "local",
        "trucking"
    ],
    "wof:name":"Martys Tractor",
    "wof:placetype":"venue"
},
  "geometry": {"coordinates":[-118.54832,34.761127],"type":"Point"}
}