{
  "type": "Feature",
  "properties": {
    "iso:country":"US",
    "sg:address":"1520 Alum Rock Ave.",
    "sg:city":"San Jose",
    "sg:classifiers":[
        {
            "category":"Restaurant",
            "type":"Food & Drink"
        }
    ],
    "sg:phone":"+1 408 729 8028",
    "sg:postcode":"95116",
    "sg:province":"CA",
    "sg:tags":[
        "mexican"
    ],
    "wof:name":"Taqueria El Gallo Jr.",
    "wof:placetype":"venue"
},
  "geometry": {"coordinates":[-121.86000799999999,37.350324],"type":"Point"}
}