{
  "type": "Feature",
  "properties": {
    "addr:full":"44759 Sierra Hwy Lancaster CA 93534",
    "addr:housenumber":"44759",
    "addr:postcode":"93534",
    "addr:street":"Sierra Hwy",
    "iso:country":"US",
    "sg:address":"44759 Sierra Hwy",
    "sg:city":"Lancaster",
    "sg:classifiers":[
        {
            "category":"Restaurant",
            "type":"Food & Drink"
        }
    ],
    "sg:phone":"+1 661 948 6464",
    "sg:postcode":"93534",
    "sg:province":"CA",
    "wof:name":"Thai Restaurant",
    "wof:placetype":"venue"
},
  "geometry": {"coordinates":[-118.136594,34.695822],"type":"Point"}
}