{
  "type": "Feature",
  "properties": {
    "addr:full":"1149 E Las Tunas Dr San Gabriel CA 91776",
    "addr:housenumber":"1149",
    "addr:postcode":"91776",
    "addr:street":"E Las Tunas Dr",
    "iso:country":"US",
    "sg:address":"1149 E Las Tunas Dr",
    "sg:city":"San Gabriel",
    "sg:classifiers":[
        {
            "category":"Shopping",
            "type":"Retail Goods"
        }
    ],
    "sg:phone":"+1 626 285 5779",
    "sg:postcode":"91776",
    "sg:province":"CA",
    "sg:tags":[
        "telephone",
        "cellular"
    ],
    "wof:name":"Lai Yi-Kuan",
    "wof:placetype":"venue"
},
  "geometry": {"coordinates":[-118.08162299999999,34.103527],"type":"Point"}
}