{
  "type": "Feature",
  "properties": {
    "addr:full":"25720 Jefferson Ave Murrieta CA 92562",
    "addr:housenumber":"25720",
    "addr:postcode":"92562",
    "addr:street":"Jefferson Ave",
    "iso:country":"US",
    "sg:address":"25720 Jefferson Ave",
    "sg:city":"Murrieta",
    "sg:classifiers":[
        {
            "category":"Manufacturing",
            "subcategory":"Tools & Machinery",
            "type":"Manufacturing & Wholesale Goods"
        }
    ],
    "sg:phone":"+1 951 696 7840",
    "sg:postcode":"92562",
    "sg:province":"CA",
    "sg:tags":[
        "equipment",
        "industry",
        "mfg"
    ],
    "sg:website":"www.cryoquip.com",
    "wof:name":"Cryogenic Industries",
    "wof:placetype":"venue"
},
  "geometry": {"coordinates":[-117.190844,33.543145],"type":"Point"}
}