{
  "type": "Feature",
  "properties": {
    "iso:country":"US",
    "sg:address":"9712 Marbella Ct",
    "sg:city":"Elk Grove",
    "sg:classifiers":[
        {
            "category":"Professional",
            "subcategory":"Business Services",
            "type":"Services"
        }
    ],
    "sg:phone":"+1 916 686 7943",
    "sg:postcode":"95624",
    "sg:province":"CA",
    "wof:name":"Osborne Business Svc",
    "wof:placetype":"venue"
},
  "geometry": {"coordinates":[-121.341415,38.404969],"type":"Point"}
}