{
  "type": "Feature",
  "properties": {
    "addr:full":"4949 Centennial Blvd Santa Clara CA 95054",
    "addr:housenumber":"4949",
    "addr:postcode":"95054",
    "addr:street":"Centennial Blvd",
    "iso:country":"US",
    "sg:address":"4949 Centennial Blvd",
    "sg:city":"Santa Clara",
    "sg:classifiers":[
        {
            "category":"Utilities",
            "subcategory":"Telephone",
            "type":"Services"
        }
    ],
    "sg:phone":"+1 408 727 4952",
    "sg:postcode":"95054",
    "sg:province":"CA",
    "sg:tags":[
        "communications"
    ],
    "wof:name":"Exin LLC",
    "wof:placetype":"venue"
},
  "geometry": {"coordinates":[-121.968591,37.403429],"type":"Point"}
}