{
  "type": "Feature",
  "properties": {
    "addr:full":"136 Las Ondas Santa Barbara CA 93109",
    "addr:housenumber":"136",
    "addr:postcode":"93109",
    "addr:street":"Las Ondas",
    "iso:country":"US",
    "sg:address":"136 Las Ondas",
    "sg:city":"Santa Barbara",
    "sg:classifiers":[
        {
            "category":"Building & Trades",
            "subcategory":"Construction",
            "type":"Services"
        }
    ],
    "sg:phone":"+1 805 962 1732",
    "sg:postcode":"93109",
    "sg:province":"CA",
    "sg:tags":[
        "contractor"
    ],
    "wof:name":"Vaughan Masonry",
    "wof:placetype":"venue"
},
  "geometry": {"coordinates":[-119.706149,34.399543],"type":"Point"}
}