{
  "type": "Feature",
  "properties": {
    "addr:full":"441 E Yucca St Oxnard CA 93033",
    "addr:housenumber":"441",
    "addr:postcode":"93033",
    "addr:street":"E Yucca St",
    "iso:country":"US",
    "sg:address":"441 E Yucca St",
    "sg:city":"Oxnard",
    "sg:classifiers":[
        {
            "category":"Building & Trades",
            "subcategory":"Electrical",
            "type":"Services"
        }
    ],
    "sg:phone":"+1 805 484 2949",
    "sg:postcode":"93033",
    "sg:province":"CA",
    "sg:tags":[
        "electric",
        "contractor"
    ],
    "wof:name":"Current Electric",
    "wof:placetype":"venue"
},
  "geometry": {"coordinates":[-119.17536699999999,34.165785],"type":"Point"}
}