{
  "type": "Feature",
  "properties": {
    "addr:full":"1330 F St Wasco CA 93280",
    "addr:housenumber":"1330",
    "addr:postcode":"ca 93280",
    "addr:street":"F St",
    "iso:country":"US",
    "sg:address":"1330 F St",
    "sg:city":"Wasco",
    "sg:classifiers":[
        {
            "category":"Insurance",
            "subcategory":"Insurance Agent",
            "type":"Services"
        }
    ],
    "sg:phone":"+1 661 758 0406",
    "sg:postcode":"93280",
    "sg:province":"CA",
    "wof:name":"Bunny Allen",
    "wof:placetype":"venue"
},
  "geometry": {"coordinates":[-119.333736,35.588099],"type":"Point"}
}