{
  "type": "Feature",
  "properties": {
    "iso:country":"US",
    "sg:address":"876 W Tulare Rd",
    "sg:city":"Lindsay",
    "sg:classifiers":[
        {
            "category":"Professional",
            "subcategory":"Credit Reporting & Collection",
            "type":"Services"
        }
    ],
    "sg:phone":"+1 559 562 2608",
    "sg:postcode":"93247",
    "sg:province":"CA",
    "sg:tags":[
        "agency"
    ],
    "wof:name":"Golden State Judgement",
    "wof:placetype":"venue"
},
  "geometry": {"coordinates":[-119.101726,36.210385],"type":"Point"}
}