{
  "type": "Feature",
  "properties": {
    "iso:country":"US",
    "sg:address":"20801 S Western Ave",
    "sg:city":"Torrance",
    "sg:classifiers":[
        {
            "category":"Bars & Pubs",
            "type":"Food & Drink"
        }
    ],
    "sg:phone":"+1 310 328 5899",
    "sg:postcode":"90501",
    "sg:province":"CA",
    "wof:name":"Phaze Karaoke Bar",
    "wof:placetype":"venue"
},
  "geometry": {"coordinates":[-118.309299,33.84186],"type":"Point"}
}