{
  "type": "Feature",
  "properties": {
    "addr:full":"1910 W Main St Alhambra CA 91801",
    "addr:housenumber":"1910",
    "addr:postcode":"91801",
    "addr:street":"W Main St",
    "iso:country":"US",
    "sg:address":"1910 W Main St",
    "sg:city":"Alhambra",
    "sg:classifiers":[
        {
            "category":"Banks & Credit Unions",
            "subcategory":"Bank",
            "type":"Services"
        }
    ],
    "sg:phone":"+1 626 356 8235",
    "sg:postcode":"91801",
    "sg:province":"CA",
    "sg:website":"www.wellsfargo.com",
    "wof:name":"Wells Fargo",
    "wof:placetype":"venue"
},
  "geometry": {"coordinates":[-118.144102,34.136286],"type":"Point"}
}