{
  "type": "Feature",
  "properties": {
    "iso:country":"US",
    "sg:address":"301 N Lake Ave",
    "sg:city":"Pasadena",
    "sg:classifiers":[
        {
            "category":"Banks & Credit Unions",
            "subcategory":"Investment Brokerage",
            "type":"Services"
        }
    ],
    "sg:phone":"+1 626 683 4600",
    "sg:postcode":"91101",
    "sg:province":"CA",
    "sg:tags":[
        "stock",
        "bond"
    ],
    "wof:name":"Smith Barney",
    "wof:placetype":"venue"
},
  "geometry": {"coordinates":[-118.132481,34.150925],"type":"Point"}
}