{
  "type": "Feature",
  "properties": {
    "iso:country":"US",
    "sg:address":"211 Ottawa St",
    "sg:city":"San Mateo",
    "sg:classifiers":[
        {
            "category":"Building & Trades",
            "subcategory":"Electrical",
            "type":"Services"
        }
    ],
    "sg:phone":"+1 650 348 2730",
    "sg:postcode":"94401",
    "sg:province":"CA",
    "sg:tags":[
        "electrical",
        "contractor"
    ],
    "wof:name":"Lester Electrical",
    "wof:placetype":"venue"
},
  "geometry": {"coordinates":[-122.317051,37.579951],"type":"Point"}
}