{
  "type": "Feature",
  "properties": {
    "addr:full":"2400 Devpar Ct Antioch CA 94509",
    "addr:housenumber":"2400",
    "addr:postcode":"ca 94509",
    "addr:street":"Devpar Ct",
    "iso:country":"US",
    "sg:address":"2400 Devpar Ct",
    "sg:city":"Antioch",
    "sg:classifiers":[
        {
            "category":"Home & Garden",
            "subcategory":"Building Materials",
            "type":"Retail Goods"
        }
    ],
    "sg:phone":"+1 925 778 4687",
    "sg:postcode":"94509",
    "sg:province":"CA",
    "sg:tags":[
        "door"
    ],
    "wof:name":"C & K Doors",
    "wof:placetype":"venue"
},
  "geometry": {"coordinates":[-121.790629,37.998253],"type":"Point"}
}