{
  "type": "Feature",
  "properties": {
    "iso:country":"US",
    "sg:address":"400 Wall St",
    "sg:city":"Livermore",
    "sg:classifiers":[
        {
            "category":"Education",
            "subcategory":"School",
            "type":"Public Place"
        }
    ],
    "sg:phone":"+1 925 606 4800",
    "sg:postcode":"94550",
    "sg:province":"CA",
    "sg:tags":[
        "high",
        "senior"
    ],
    "wof:name":"Granada Senior High School",
    "wof:placetype":"venue"
},
  "geometry": {"coordinates":[-121.78986,37.672685],"type":"Point"}
}