{
  "type": "Feature",
  "properties": {
    "addr:full":"2255 Hearst Ave Berkeley CA 94709",
    "addr:housenumber":"2255",
    "addr:postcode":"94709",
    "addr:street":"Hearst Ave",
    "iso:country":"US",
    "sg:address":"2255 Hearst Ave",
    "sg:city":"Berkeley",
    "sg:classifiers":[
        {
            "category":"Manufacturing",
            "subcategory":"Tools & Machinery",
            "type":"Manufacturing & Wholesale Goods"
        }
    ],
    "sg:phone":"+1 510 703 6887",
    "sg:postcode":"94709",
    "sg:province":"CA",
    "sg:tags":[
        "cell",
        "equipment"
    ],
    "wof:name":"Cellonix Corporation",
    "wof:placetype":"venue"
},
  "geometry": {"coordinates":[-122.264602,37.874469],"type":"Point"}
}