{
  "type": "Feature",
  "properties": {
    "addr:full":"1601 Baines Ave Sacramento CA 95835",
    "addr:housenumber":"1601",
    "addr:postcode":"95835",
    "addr:street":"Baines Ave",
    "iso:country":"US",
    "sg:address":"1601 Baines Ave",
    "sg:city":"Sacramento",
    "sg:classifiers":[
        {
            "category":"Social Services",
            "subcategory":"Child Care",
            "type":"Services"
        }
    ],
    "sg:phone":"+1 916 419 3347",
    "sg:postcode":"95835",
    "sg:province":"CA",
    "wof:name":"Tender Care Preschool Daycare",
    "wof:placetype":"venue"
},
  "geometry": {"coordinates":[-121.49557799999999,38.661879],"type":"Point"}
}