{
  "type": "Feature",
  "properties": {
    "addr:full":"1011 W Taft Ave Orange CA 92865",
    "addr:housenumber":"1011",
    "addr:postcode":"92865",
    "addr:street":"W Taft Ave",
    "iso:country":"US",
    "sg:address":"1011 W Taft Ave",
    "sg:city":"Orange",
    "sg:classifiers":[
        {
            "category":"Home & Garden",
            "subcategory":"Carpets & Floor Coverings",
            "type":"Retail Goods"
        }
    ],
    "sg:phone":"+1 714 279 6799",
    "sg:postcode":"92865",
    "sg:province":"CA",
    "sg:tags":[
        "carpeting"
    ],
    "sg:website":"www.bixbyknollscarpet.net",
    "wof:name":"Bixby Knolls Carpet",
    "wof:placetype":"venue"
},
  "geometry": {"coordinates":[-117.86392499999999,33.816017],"type":"Point"}
}