{
  "type": "Feature",
  "properties": {
    "iso:country":"US",
    "sg:address":"526 E Alisal St",
    "sg:city":"Salinas",
    "sg:classifiers":[
        {
            "category":"Freight",
            "type":"Transportation"
        }
    ],
    "sg:phone":"+1 831 759 9789",
    "sg:postcode":"93905",
    "sg:province":"CA",
    "sg:tags":[
        "operator",
        "local",
        "trucking"
    ],
    "wof:name":"Aeroexpress TU Mexico",
    "wof:placetype":"venue"
},
  "geometry": {"coordinates":[-121.637722,36.673892],"type":"Point"}
}