{
  "type": "Feature",
  "properties": {
    "addr:full":"3453 Enterprise Ave Hayward CA 94545",
    "addr:housenumber":"3453",
    "addr:postcode":"94545",
    "addr:street":"Enterprise Ave",
    "iso:country":"US",
    "sg:address":"3453 Enterprise Ave",
    "sg:city":"Hayward",
    "sg:classifiers":[
        {
            "category":"Building & Trades",
            "subcategory":"Construction",
            "type":"Services"
        }
    ],
    "sg:phone":"+1 510 785 2050",
    "sg:postcode":"94545",
    "sg:province":"CA",
    "sg:tags":[
        "excavating",
        "contractor"
    ],
    "wof:name":"Vanier Excavating Co Inc",
    "wof:placetype":"venue"
},
  "geometry": {"coordinates":[-122.12216100000001,37.633389],"type":"Point"}
}