{
  "type": "Feature",
  "properties": {
    "iso:country":"US",
    "sg:address":"15545 Bellflower Blvd",
    "sg:city":"Bellflower",
    "sg:classifiers":[
        {
            "category":"Real Estate",
            "subcategory":"Real Estate Services",
            "type":"Services"
        }
    ],
    "sg:phone":"+1 562 461 0332",
    "sg:postcode":"90706",
    "sg:province":"CA",
    "sg:tags":[
        "management",
        "property"
    ],
    "wof:name":"M & F Properties",
    "wof:placetype":"venue"
},
  "geometry": {"coordinates":[-118.125,33.892601],"type":"Point"}
}