{
  "type": "Feature",
  "properties": {
    "addr:full":"10551 Kasten St Mendocino CA 95460",
    "addr:postcode":"10551;95460",
    "addr:street":"Kasten St",
    "iso:country":"US",
    "sg:address":"10551 Kasten St",
    "sg:city":"Mendocino",
    "sg:classifiers":[
        {
            "category":"Home & Garden",
            "subcategory":"Garden Supply",
            "type":"Retail Goods"
        }
    ],
    "sg:phone":"+1 707 937 3459",
    "sg:postcode":"95460",
    "sg:province":"CA",
    "sg:tags":[
        "nurseryman"
    ],
    "wof:name":"Mendocino Garden Shop",
    "wof:placetype":"venue"
},
  "geometry": {"coordinates":[-123.801799,39.306615],"type":"Point"}
}