{
  "type": "Feature",
  "properties": {
    "addr:full":"1442 E 7th St Long Beach CA 90813",
    "addr:housenumber":"1442",
    "addr:postcode":"90813",
    "addr:street":"E 7Th St",
    "iso:country":"US",
    "sg:address":"1442 E 7th St",
    "sg:city":"Long Beach",
    "sg:classifiers":[
        {
            "category":"Shopping",
            "subcategory":"Musical Instruments",
            "type":"Retail Goods"
        }
    ],
    "sg:phone":"+1 562 983 9884",
    "sg:postcode":"90813",
    "sg:province":"CA",
    "sg:tags":[
        "music",
        "dealer"
    ],
    "wof:name":"Discoteca Dorado",
    "wof:placetype":"venue"
},
  "geometry": {"coordinates":[-118.17228299999999,33.775264],"type":"Point"}
}