{
  "type": "Feature",
  "properties": {
    "addr:full":"429 Via Hidalgo Greenbrae CA 94904",
    "addr:housenumber":"429",
    "addr:postcode":"94904",
    "addr:street":"Via Hidalgo",
    "iso:country":"US",
    "sg:address":"429 Via Hidalgo",
    "sg:city":"Greenbrae",
    "sg:classifiers":[
        {
            "category":"Wholesale",
            "subcategory":"Stationery",
            "type":"Manufacturing & Wholesale Goods"
        }
    ],
    "sg:phone":"+1 415 461 9174",
    "sg:postcode":"94904",
    "sg:province":"CA",
    "sg:tags":[
        "supply"
    ],
    "wof:name":"Lifematters",
    "wof:placetype":"venue"
},
  "geometry": {"coordinates":[-122.531982,37.948077],"type":"Point"}
}