{
  "type": "Feature",
  "properties": {
    "addr:full":"12606 Culver Boulevard Los Angeles CA 90066",
    "addr:housenumber":"12606",
    "addr:postcode":"90066",
    "addr:street":"Culver Boulevard",
    "iso:country":"US",
    "sg:address":"12606 Culver Boulevard",
    "sg:city":"Los Angeles",
    "sg:classifiers":[
        {
            "category":"Education",
            "subcategory":"School",
            "type":"Public Place"
        }
    ],
    "sg:phone":"+1 310 827 5511",
    "sg:postcode":"90066",
    "sg:province":"CA",
    "sg:tags":[
        "high",
        "middle",
        "elementary"
    ],
    "wof:name":"Ocean Charter School",
    "wof:placetype":"venue"
},
  "geometry": {"coordinates":[-118.42451699999999,33.986707],"type":"Point"}
}