{
  "type": "Feature",
  "properties": {
    "iso:country":"US",
    "sg:address":"585 Meyers Ave",
    "sg:city":"Gridley",
    "sg:classifiers":[
        {
            "category":"Farming",
            "subcategory":"Livestock Farm",
            "type":"Manufacturing & Wholesale Goods"
        }
    ],
    "sg:phone":"+1 530 695 3814",
    "sg:postcode":"95948",
    "sg:province":"CA",
    "sg:tags":[
        "specialty",
        "animal"
    ],
    "wof:name":"Sutter Buttes Canine Rescue",
    "wof:placetype":"venue"
},
  "geometry": {"coordinates":[-121.67870000000001,39.324763],"type":"Point"}
}