{
  "type": "Feature",
  "properties": {
    "iso:country":"US",
    "sg:address":"801 E Katella Ave",
    "sg:city":"Anaheim",
    "sg:classifiers":[
        {
            "category":"Health Services",
            "subcategory":"Clinic",
            "type":"Services"
        }
    ],
    "sg:phone":"+1 714 456 0160",
    "sg:postcode":"92805",
    "sg:province":"CA",
    "sg:tags":[
        "home",
        "care"
    ],
    "wof:name":"Vnais Pharmacy",
    "wof:placetype":"venue"
},
  "geometry": {"coordinates":[-117.898444,33.803415],"type":"Point"}
}