{
  "type": "Feature",
  "properties": {
    "addr:full":"1758 Cape Coral Dr San Jose CA 95133",
    "addr:housenumber":"1758",
    "addr:postcode":"95133",
    "addr:street":"Cape Coral Dr",
    "iso:country":"US",
    "sg:address":"1758 Cape Coral Dr",
    "sg:city":"San Jose",
    "sg:classifiers":[
        {
            "category":"Manufacturing",
            "subcategory":"Retail Goods",
            "type":"Manufacturing & Wholesale Goods"
        }
    ],
    "sg:phone":"+1 408 251 3255",
    "sg:postcode":"95133",
    "sg:province":"CA",
    "sg:tags":[
        "mfg"
    ],
    "wof:name":"Bonnies Bows",
    "wof:placetype":"venue"
},
  "geometry": {"coordinates":[-121.87021300000001,37.372511],"type":"Point"}
}