{
  "type": "Feature",
  "properties": {
    "iso:country":"US",
    "sfac:artist":"Riley, Cheryl",
    "sfac:created_at":"01/01/1970 12:33:19 AM +0000",
    "sfac:credit_line":"Commissioned for art enrichment of the 911 Emergency Center",
    "sfac:display_dimensions":"7' H X 63 'L overall; concrete tiles 12\" X 12\"; resin tiles 4\" X 4\".",
    "sfac:location_description":"City Department : 911 Emergency Services Center : 1011 Turk St. : Exterior",
    "sfac:medium":"Cast concrete, GFRC tile and resin, mixed media, found objects.",
    "sfac:revision":"2-1fb66b7a8efc2259dacf92437243d66a",
    "sfac:title":"Angels of Mercy",
    "wof:name":"Angels of Mercy",
    "wof:placetype":"venue"
},
  "geometry": {"coordinates":[-122.4194155,37.7749295],"type":"Point"}
}