{
  "type": "Feature",
  "properties": {
    "addr:full":"23140 Gonzales Dr Woodland Hills CA 91367",
    "addr:housenumber":"23140",
    "addr:postcode":"91367",
    "addr:street":"Gonzales Dr",
    "iso:country":"US",
    "sg:address":"23140 Gonzales Dr",
    "sg:city":"Woodland Hills",
    "sg:classifiers":[
        {
            "category":"Farming",
            "subcategory":"Livestock Farm",
            "type":"Manufacturing & Wholesale Goods"
        }
    ],
    "sg:phone":"+1 818 615 0384",
    "sg:postcode":"91367",
    "sg:province":"CA",
    "sg:tags":[
        "equine"
    ],
    "wof:name":"Mason Bay Farm",
    "wof:placetype":"venue"
},
  "geometry": {"coordinates":[-118.6315,34.165987],"type":"Point"}
}