{
  "type": "Feature",
  "properties": {
    "addr:full":"750 Sycamore Ave Vista CA 92083",
    "addr:housenumber":"750",
    "addr:postcode":"92083",
    "addr:street":"Sycamore Ave",
    "iso:country":"US",
    "sg:address":"750 Sycamore Ave",
    "sg:city":"Vista",
    "sg:classifiers":[
        {
            "category":"Government",
            "subcategory":"Office",
            "type":"Public Place"
        }
    ],
    "sg:phone":"+1 760 599 2650",
    "sg:postcode":"92083",
    "sg:province":"CA",
    "sg:tags":[
        "national",
        "security"
    ],
    "wof:name":"Naval Reserves",
    "wof:placetype":"venue"
},
  "geometry": {"coordinates":[-117.218855,33.162023],"type":"Point"}
}