{
  "type": "Feature",
  "properties": {
    "iso:country":"US",
    "sg:address":"26057 Bouquet Canyon Rd",
    "sg:city":"Santa Clarita",
    "sg:classifiers":[
        {
            "category":"Wholesale",
            "subcategory":"Machinery & Supplies",
            "type":"Manufacturing & Wholesale Goods"
        }
    ],
    "sg:phone":"+1 661 253 1445",
    "sg:postcode":"91350",
    "sg:province":"CA",
    "sg:tags":[
        "equipment",
        "establishment"
    ],
    "wof:name":"Cosmoprof",
    "wof:placetype":"venue"
},
  "geometry": {"coordinates":[-118.541939,34.418232],"type":"Point"}
}