{
  "type": "Feature",
  "properties": {
    "addr:full":"22 Meadow Wood Dr Trabuco Canyon CA 92679",
    "addr:housenumber":"22",
    "addr:postcode":"92679",
    "addr:street":"Meadow Wood Dr",
    "iso:country":"US",
    "sg:address":"22 Meadow Wood Dr",
    "sg:city":"Trabuco Canyon",
    "sg:classifiers":[
        {
            "category":"Manufacturing",
            "subcategory":"Retail Goods",
            "type":"Manufacturing & Wholesale Goods"
        }
    ],
    "sg:phone":"+1 949 499 3821",
    "sg:postcode":"92679",
    "sg:province":"CA",
    "sg:tags":[
        "product",
        "mfg"
    ],
    "wof:name":"Rahal Industries Inc",
    "wof:placetype":"venue"
},
  "geometry": {"coordinates":[-117.579857,33.609748],"type":"Point"}
}