{
  "type": "Feature",
  "properties": {
    "iso:country":"US",
    "sg:address":"2110 S Bascom Ave",
    "sg:city":"Campbell",
    "sg:classifiers":[
        {
            "category":"Building & Trades",
            "subcategory":"Construction",
            "type":"Services"
        }
    ],
    "sg:phone":"+1 408 626 9090",
    "sg:postcode":"95008",
    "sg:province":"CA",
    "sg:tags":[
        "contractor"
    ],
    "wof:name":"Fernandes & Sons",
    "wof:placetype":"venue"
},
  "geometry": {"coordinates":[-121.931387,37.284866],"type":"Point"}
}