{
  "type": "Feature",
  "properties": {
    "addr:full":"2200 E Tulare Ave Tulare CA 93274",
    "addr:housenumber":"2200",
    "addr:postcode":"93274",
    "addr:street":"E Tulare Ave",
    "iso:country":"US",
    "sg:address":"2200 E Tulare Ave",
    "sg:city":"Tulare",
    "sg:classifiers":[
        {
            "category":"Autos & Motor Vehicles",
            "subcategory":"Auto Supplies",
            "type":"Retail Goods"
        }
    ],
    "sg:phone":"+1 559 688 5040",
    "sg:postcode":"93274",
    "sg:province":"CA",
    "sg:tags":[
        "tire"
    ],
    "wof:name":"Carroll's Tire Warehouse",
    "wof:placetype":"venue"
},
  "geometry": {"coordinates":[-119.313351,36.211366],"type":"Point"}
}