{
  "type": "Feature",
  "properties": {
    "addr:full":"7031 N Monte Ave Fresno CA 93711",
    "addr:housenumber":"7031",
    "addr:postcode":"93711",
    "addr:street":"N Monte Ave",
    "iso:country":"US",
    "sg:address":"7031 N Monte Ave",
    "sg:city":"Fresno",
    "sg:classifiers":[
        {
            "category":"Shopping",
            "subcategory":"Department Store",
            "type":"Retail Goods"
        }
    ],
    "sg:phone":"+1 559 447 9716",
    "sg:postcode":"93711",
    "sg:province":"CA",
    "wof:name":"Palais, Inc.",
    "wof:placetype":"venue"
},
  "geometry": {"coordinates":[-119.844527,36.83801],"type":"Point"}
}