{
  "type": "Feature",
  "properties": {
    "addr:full":"4480 Treat Blvd Concord CA 94521",
    "addr:housenumber":"4480",
    "addr:postcode":"94521",
    "addr:street":"Treat Blvd",
    "iso:country":"US",
    "sg:address":"4480 Treat Blvd",
    "sg:city":"Concord",
    "sg:classifiers":[
        {
            "category":"Building & Trades",
            "subcategory":"Electrical",
            "type":"Services"
        }
    ],
    "sg:phone":"+1 925 825 0806",
    "sg:postcode":"94521",
    "sg:province":"CA",
    "sg:tags":[
        "electric",
        "contractor"
    ],
    "wof:name":"Smitty's Electric",
    "wof:placetype":"venue"
},
  "geometry": {"coordinates":[-121.992901,37.964166],"type":"Point"}
}