{
  "type": "Feature",
  "properties": {
    "addr:full":"7301 Orangethorpe Ave Buena Park CA 90621",
    "addr:housenumber":"7301",
    "addr:postcode":"90621",
    "addr:street":"Orangethorpe Ave",
    "iso:country":"US",
    "sg:address":"7301 Orangethorpe Ave",
    "sg:city":"Buena Park",
    "sg:classifiers":[
        {
            "category":"Food & Beverages",
            "subcategory":"Liquor & Beverages",
            "type":"Retail Goods"
        }
    ],
    "sg:phone":"+1 714 522 3670",
    "sg:postcode":"90621",
    "sg:province":"CA",
    "sg:tags":[
        "beer",
        "spirit",
        "wine"
    ],
    "wof:name":"Sunshine Check Cashing",
    "wof:placetype":"venue"
},
  "geometry": {"coordinates":[-118.004997,33.8591],"type":"Point"}
}