{
  "type": "Feature",
  "properties": {
    "iso:country":"US",
    "sg:address":"9195 E Mountain View Ave",
    "sg:city":"Selma",
    "sg:classifiers":[
        {
            "category":"Farming",
            "subcategory":"Vineyard",
            "type":"Manufacturing & Wholesale Goods"
        }
    ],
    "sg:phone":"+1 559 896 7633",
    "sg:postcode":"93662",
    "sg:province":"CA",
    "sg:tags":[
        "grape"
    ],
    "wof:name":"Davis Farms",
    "wof:placetype":"venue"
},
  "geometry": {"coordinates":[-119.627258,36.547035],"type":"Point"}
}