{
  "type": "Feature",
  "properties": {
    "addr:full":"2702 Lytton St San Diego CA 92110",
    "addr:housenumber":"2702",
    "addr:postcode":"92110",
    "addr:street":"Lytton St",
    "iso:country":"US",
    "sg:address":"2702 Lytton St",
    "sg:city":"San Diego",
    "sg:classifiers":[
        {
            "category":"Shopping",
            "subcategory":"Thrift Store",
            "type":"Retail Goods"
        }
    ],
    "sg:phone":"+1 619 224 9174",
    "sg:postcode":"92110",
    "sg:province":"CA",
    "sg:website":"www.great-curves.com",
    "wof:name":"Great Curves",
    "wof:placetype":"venue"
},
  "geometry": {"coordinates":[-117.20943800000001,32.742725],"type":"Point"}
}