{
  "type": "Feature",
  "properties": {
    "iso:country":"US",
    "sg:address":"610 Lunar Ave",
    "sg:city":"Brea",
    "sg:classifiers":[
        {
            "category":"Shopping",
            "subcategory":"Computers & Home Electronics",
            "type":"Retail Goods"
        }
    ],
    "sg:phone":"+1 714 990 1005",
    "sg:postcode":"92821",
    "sg:province":"CA",
    "sg:tags":[
        "equipment",
        "dealer"
    ],
    "wof:name":"Advanced Computer & Networking",
    "wof:placetype":"venue"
},
  "geometry": {"coordinates":[-117.902182,33.929573],"type":"Point"}
}