{
  "type": "Feature",
  "properties": {
    "iso:country":"US",
    "sg:address":"2595 Huntington Dr",
    "sg:city":"San Marino",
    "sg:classifiers":[
        {
            "category":"Health Services",
            "subcategory":"Doctor",
            "type":"Services"
        },
        {
            "category":"Health Services",
            "subcategory":"Dentist",
            "type":"Services"
        }
    ],
    "sg:phone":"+1 626 796 0615",
    "sg:postcode":"91108",
    "sg:province":"CA",
    "sg:tags":[
        "surgeon",
        "oral",
        "orthodontist"
    ],
    "sg:website":"www.tmsmiles.com",
    "wof:name":"Siu Orthodontics",
    "wof:placetype":"venue"
},
  "geometry": {"coordinates":[-118.106459,34.121397],"type":"Point"}
}