{
  "type": "Feature",
  "properties": {
    "addr:full":"7227 Broadway Lemon Grove CA 91945",
    "addr:housenumber":"7227",
    "addr:postcode":"91945",
    "addr:street":"Broadway",
    "iso:country":"US",
    "sg:address":"7227 Broadway",
    "sg:city":"Lemon Grove",
    "sg:classifiers":[
        {
            "category":"Social Services",
            "type":"Services"
        }
    ],
    "sg:phone":"+1 619 460 0925",
    "sg:postcode":"91945",
    "sg:province":"CA",
    "sg:tags":[
        "organization",
        "welfare"
    ],
    "wof:name":"Liberty Unlimited Ministries",
    "wof:placetype":"venue"
},
  "geometry": {"coordinates":[-117.041601,32.742494],"type":"Point"}
}