{
  "type": "Feature",
  "properties": {
    "iso:country":"US",
    "sg:address":"5080 S Montclair Plaza Ln",
    "sg:city":"Montclair",
    "sg:classifiers":[
        {
            "category":"Professional",
            "subcategory":"Accounting & Tax Preparation",
            "type":"Services"
        }
    ],
    "sg:phone":"+1 909 626 0323",
    "sg:postcode":"91763",
    "sg:province":"CA",
    "sg:tags":[
        "return",
        "filing"
    ],
    "wof:name":"H & R Block Tax Svc",
    "wof:placetype":"venue"
},
  "geometry": {"coordinates":[-117.692059,34.085002],"type":"Point"}
}