{
  "type": "Feature",
  "properties": {
    "addr:full":"607 S Hill St Ste 204 Los Angeles CA 90014",
    "addr:housenumber":"607",
    "addr:postcode":"90014",
    "addr:street":"S Hill St Ste 204",
    "iso:country":"US",
    "sg:address":"607 S Hill St Ste 204",
    "sg:city":"Los Angeles",
    "sg:classifiers":[
        {
            "category":"Shopping",
            "subcategory":"Jewelry",
            "type":"Retail Goods"
        },
        {
            "category":"Shopping",
            "subcategory":"Bridal",
            "type":"Retail Goods"
        }
    ],
    "sg:phone":"+1 213 892 0772",
    "sg:postcode":"90014",
    "sg:province":"CA",
    "sg:website":"www.singlestone.com",
    "wof:name":"Single Stone",
    "wof:placetype":"venue"
},
  "geometry": {"coordinates":[-118.253606,34.047301],"type":"Point"}
}