{
  "type": "Feature",
  "properties": {
    "addr:full":"1501 E Artesia Blvd Long Beach CA 90805",
    "addr:housenumber":"1501",
    "addr:postcode":"90805",
    "addr:street":"E Artesia Blvd",
    "iso:country":"US",
    "sg:address":"1501 E Artesia Blvd",
    "sg:city":"Long Beach",
    "sg:classifiers":[
        {
            "category":"Real Estate",
            "subcategory":"Real Estate Agent",
            "type":"Services"
        }
    ],
    "sg:phone":"+1 562 423 3322",
    "sg:postcode":"90805",
    "sg:province":"CA",
    "wof:name":"Palazzo Realty Inc",
    "wof:placetype":"venue"
},
  "geometry": {"coordinates":[-118.17302599999999,33.874623],"type":"Point"}
}