{
  "type": "Feature",
  "properties": {
    "addr:full":"2820 N Figueroa St Los Angeles CA 90065",
    "addr:housenumber":"2820",
    "addr:postcode":"90065",
    "addr:street":"N Figueroa St",
    "iso:country":"US",
    "sg:address":"2820 N Figueroa St",
    "sg:city":"Los Angeles",
    "sg:classifiers":[
        {
            "category":"Social Services",
            "type":"Services"
        }
    ],
    "sg:phone":"+1 323 222 6600",
    "sg:postcode":"90065",
    "sg:province":"CA",
    "sg:tags":[
        "care",
        "center",
        "day"
    ],
    "wof:name":"Primavera ADHC",
    "wof:placetype":"venue"
},
  "geometry": {"coordinates":[-118.220319,34.085352],"type":"Point"}
}