{
  "type": "Feature",
  "properties": {
    "iso:country":"US",
    "sg:address":"9358 Claymore St",
    "sg:city":"Pico Rivera",
    "sg:classifiers":[
        {
            "category":"Arts & Performance",
            "subcategory":"Theater",
            "type":"Entertainment"
        }
    ],
    "sg:phone":"+1 562 948 5342",
    "sg:postcode":"90660",
    "sg:province":"CA",
    "sg:tags":[
        "opera",
        "company"
    ],
    "sg:website":"www.clowns4all.com",
    "wof:name":"Charmandhappy.Com Clowns",
    "wof:placetype":"venue"
},
  "geometry": {"coordinates":[-118.10235299999999,33.956995],"type":"Point"}
}