{
  "type": "Feature",
  "properties": {
    "iso:country":"US",
    "sg:address":"1100 E Holt Ave",
    "sg:city":"Pomona",
    "sg:classifiers":[
        {
            "category":"Shopping",
            "type":"Retail Goods"
        }
    ],
    "sg:phone":"+1 909 469 6205",
    "sg:postcode":"91767",
    "sg:province":"CA",
    "sg:tags":[
        "mexican"
    ],
    "wof:name":"Sophia's Mexican Food",
    "wof:placetype":"venue"
},
  "geometry": {"coordinates":[-117.729027,34.062901],"type":"Point"}
}