{
  "type": "Feature",
  "properties": {
    "addr:full":"2121 E California Ave Bakersfield CA 93307",
    "addr:housenumber":"2121",
    "addr:postcode":"93307",
    "addr:street":"E California Ave",
    "iso:country":"US",
    "sg:address":"2121 E California Ave",
    "sg:city":"Bakersfield",
    "sg:classifiers":[
        {
            "category":"Utilities",
            "subcategory":"Mobile Phone",
            "type":"Services"
        }
    ],
    "sg:phone":"+1 661 324 4255",
    "sg:postcode":"93307",
    "sg:province":"CA",
    "sg:tags":[
        "telephone",
        "cellular"
    ],
    "wof:name":"My Wireless",
    "wof:placetype":"venue"
},
  "geometry": {"coordinates":[-118.967877,35.368542],"type":"Point"}
}